{
  "type": "Feature",
  "properties": {
    "iso:country":"AU",
    "sg:address":"209 Darling St",
    "sg:city":"Balmain",
    "sg:classifiers":[
        {
            "category":"Arts & Performance",
            "subcategory":"Art Gallery",
            "type":"Entertainment"
        }
    ],
    "sg:phone":"+61 2 9810 1014",
    "sg:postcode":"2041",
    "sg:province":"NSW",
    "wof:name":"Punch Gallery",
    "wof:placetype":"venue"
},
  "geometry": {"coordinates":[151.18469200000001,-33.858139],"type":"Point"}
}