{
  "type": "Feature",
  "properties": {
    "addr:full":"17 Regent St Kogarah NSW 2217",
    "addr:housenumber":"17",
    "addr:postcode":"2217",
    "addr:street":"Regent St",
    "iso:country":"AU",
    "sg:address":"17 Regent St",
    "sg:city":"Kogarah",
    "sg:classifiers":[
        {
            "category":"Food & Beverages",
            "subcategory":"Supermarket",
            "type":"Retail Goods"
        }
    ],
    "sg:phone":"+61 2 9587 3617",
    "sg:postcode":"2217",
    "sg:province":"NSW",
    "sg:tags":[
        "grocery",
        "store"
    ],
    "wof:name":"Patel Brothers",
    "wof:placetype":"venue"
},
  "geometry": {"coordinates":[151.133759,-33.962532],"type":"Point"}
}