{
  "type": "Feature",
  "properties": {
    "iso:country":"AU",
    "sg:address":"7/ 18 Mountain View Ave",
    "sg:city":"Miami",
    "sg:classifiers":[
        {
            "category":"Building & Trades",
            "subcategory":"Construction",
            "type":"Services"
        }
    ],
    "sg:phone":"+61 7 5576 6830",
    "sg:postcode":"4220",
    "sg:province":"QLD",
    "sg:tags":[
        "home",
        "air conditioning"
    ],
    "sg:website":"http://www.surfair.net.au",
    "wof:name":"Surf Air Airconditioning Pty Ltd",
    "wof:placetype":"venue"
},
  "geometry": {"coordinates":[153.443359375,-28.0756034851],"type":"Point"}
}