{
  "type": "Feature",
  "properties": {
    "addr:full":"53 Shoreham Rd Red Hill South VIC 3937",
    "addr:housenumber":"53",
    "addr:postcode":"3937",
    "addr:street":"Shoreham Rd",
    "iso:country":"AU",
    "sg:address":"53 Shoreham Rd",
    "sg:city":"Red Hill South",
    "sg:classifiers":[
        {
            "category":"Farming",
            "subcategory":"Vineyard",
            "type":"Manufacturing & Wholesale Goods"
        }
    ],
    "sg:phone":"+61 3 5931 0177",
    "sg:postcode":"3937",
    "sg:province":"VIC",
    "sg:tags":[
        "winery"
    ],
    "wof:name":"Red Hill Estate & Maxs Restaurant",
    "wof:placetype":"venue"
},
  "geometry": {"coordinates":[145.020263672,-38.3851966858],"type":"Point"}
}