{
  "type": "Feature",
  "properties": {
    "addr:full":"274 Anzac Hwy Plympton SA 5038",
    "addr:housenumber":"274",
    "addr:postcode":"5038",
    "addr:street":"Anzac Hwy",
    "iso:country":"AU",
    "sg:address":"274 Anzac Hwy",
    "sg:city":"Plympton",
    "sg:classifiers":[
        {
            "category":"Building & Trades",
            "subcategory":"Construction",
            "type":"Services"
        }
    ],
    "sg:phone":"+61 8 8351 2022",
    "sg:postcode":"5038",
    "sg:province":"SA",
    "sg:tags":[
        "contractor"
    ],
    "sg:website":"http://www.regenthomes.com.au",
    "wof:name":"Regent Homes Pty Ltd",
    "wof:placetype":"venue"
},
  "geometry": {"coordinates":[138.556182861,-34.9633293152],"type":"Point"}
}