{
  "type": "Feature",
  "properties": {
    "addr:full":"176 Kensington Rd Footscray VIC 3011",
    "addr:housenumber":"176",
    "addr:postcode":"3011",
    "addr:street":"Kensington Rd",
    "iso:country":"AU",
    "sg:address":"176 Kensington Rd",
    "sg:city":"Footscray",
    "sg:classifiers":[
        {
            "category":"Shopping",
            "type":"Retail Goods"
        }
    ],
    "sg:phone":"+61 3 9689 9300",
    "sg:postcode":"3011",
    "sg:province":"VIC",
    "sg:tags":[
        "product",
        "plastic"
    ],
    "wof:name":"Cue B.R. Plastics Pty Ltd",
    "wof:placetype":"venue"
},
  "geometry": {"coordinates":[144.914993286,-37.8014297485],"type":"Point"}
}