{
  "type": "Feature",
  "properties": {
    "iso:country":"AU",
    "sg:address":"Shp2/ 1 High St",
    "sg:city":"Bayswater",
    "sg:classifiers":[
        {
            "category":"Fast Food",
            "type":"Food & Drink"
        }
    ],
    "sg:phone":"+61 3 9729 1286",
    "sg:postcode":"3153",
    "sg:province":"VIC",
    "sg:tags":[
        "away",
        "take"
    ],
    "wof:name":"Bayswater Noodle Bar",
    "wof:placetype":"venue"
},
  "geometry": {"coordinates":[145.26596069300001,-37.8420028687],"type":"Point"}
}