{
  "type": "Feature",
  "properties": {
    "addr:full":"Mort St Balmain NSW 2041",
    "addr:postcode":"2041",
    "addr:street":"Mort St",
    "iso:country":"AU",
    "sg:address":"Mort St",
    "sg:city":"Balmain",
    "sg:classifiers":[
        {
            "category":"Health Services",
            "subcategory":"Health Practitioner",
            "type":"Services"
        }
    ],
    "sg:phone":"+61 418 632 578",
    "sg:postcode":"2041",
    "sg:province":"NSW",
    "sg:tags":[
        "hypnotherapy"
    ],
    "wof:name":"Werner Meyer",
    "wof:placetype":"venue"
},
  "geometry": {"coordinates":[151.18073999999999,-33.857227],"type":"Point"}
}