{
  "type": "Feature",
  "properties": {
    "iso:country":"AU",
    "sg:address":"2/ 1 Ireland St",
    "sg:city":"Bright",
    "sg:classifiers":[
        {
            "category":"Health Services",
            "subcategory":"Dentist",
            "type":"Services"
        }
    ],
    "sg:phone":"+61 3 5755 1776",
    "sg:postcode":"3741",
    "sg:province":"VIC",
    "wof:name":"Alliance Dental Group",
    "wof:placetype":"venue"
},
  "geometry": {"coordinates":[146.96104399999999,-36.730099],"type":"Point"}
}