{
  "type": "Feature",
  "properties": {
    "addr:full":"PO Box 259 Robe SA 5276",
    "addr:postcode":"5276",
    "iso:country":"AU",
    "sg:address":"PO Box 259",
    "sg:city":"Robe",
    "sg:classifiers":[
        {
            "category":"Commercial Area",
            "type":"Public Place"
        }
    ],
    "sg:phone":"+61 408 856 273",
    "sg:postcode":"5276",
    "sg:province":"SA",
    "sg:tags":[
        "heavy",
        "carrier"
    ],
    "wof:name":"Robe Transport Services",
    "wof:placetype":"venue"
},
  "geometry": {"coordinates":[139.787125,-37.168129],"type":"Point"}
}