{
  "type": "Feature",
  "properties": {
    "addr:full":"U4 38 Cohn St Carlisle WA 6101",
    "addr:housenumber":"38",
    "addr:postcode":"6101",
    "addr:street":"U4;Cohn St",
    "iso:country":"AU",
    "sg:address":"U4 38 Cohn St",
    "sg:city":"Carlisle",
    "sg:classifiers":[
        {
            "category":"Wholesale",
            "subcategory":"Home Furnishings",
            "type":"Manufacturing & Wholesale Goods"
        }
    ],
    "sg:phone":"+61 8 9470 3291",
    "sg:postcode":"6101",
    "sg:province":"WA",
    "sg:tags":[
        "wholesaler",
        "mfrs",
        "manchester"
    ],
    "wof:name":"Speckles",
    "wof:placetype":"venue"
},
  "geometry": {"coordinates":[115.92456817599999,-31.9831619263],"type":"Point"}
}