{
  "type": "Feature",
  "properties": {
    "addr:full":"Near PO, 291 Watkins Rd Wangi Wangi NSW 2267",
    "addr:housenumber":"291",
    "addr:postcode":"2267",
    "addr:street":"Near Po;Watkins Rd",
    "iso:country":"AU",
    "sg:address":"Near PO, 291 Watkins Rd",
    "sg:city":"Wangi Wangi",
    "sg:classifiers":[
        {
            "category":"Personal",
            "subcategory":"Beauty Salon",
            "type":"Services"
        }
    ],
    "sg:phone":"+61 2 4975 1191",
    "sg:postcode":"2267",
    "sg:province":"NSW",
    "sg:tags":[
        "hairdresser"
    ],
    "wof:name":"Wangi Hair Villa",
    "wof:placetype":"venue"
},
  "geometry": {"coordinates":[151.58836400000001,-33.069309],"type":"Point"}
}