{
  "type": "Feature",
  "properties": {
    "addr:full":"2 Lamana St Mordialloc VIC 3195",
    "addr:housenumber":"2",
    "addr:postcode":"3195",
    "addr:street":"Lamana St",
    "iso:country":"AU",
    "sg:address":"2 Lamana St",
    "sg:city":"Mordialloc",
    "sg:classifiers":[
        {
            "category":"Utilities",
            "type":"Services"
        }
    ],
    "sg:phone":"+61 1300 361 186",
    "sg:postcode":"3195",
    "sg:province":"VIC",
    "sg:tags":[
        "refrigeration",
        "industrial",
        "commercial",
        "retail"
    ],
    "wof:name":"Ozcool Refrigeration Pty Ltd",
    "wof:placetype":"venue"
},
  "geometry": {"coordinates":[145.09840393100001,-38.0086326599],"type":"Point"}
}