{
  "type": "Feature",
  "properties": {
    "addr:full":"Unit 1/ 64 Railway St Bomaderry NSW 2541",
    "addr:housenumber":"64",
    "addr:postcode":"2541",
    "addr:street":"Railway St",
    "iso:country":"AU",
    "sg:address":"Unit 1/ 64 Railway St",
    "sg:city":"Bomaderry",
    "sg:classifiers":[
        {
            "category":"Autos & Motor Vehicles",
            "subcategory":"Auto Supplies",
            "type":"Retail Goods"
        }
    ],
    "sg:phone":"+61 418 642 424",
    "sg:postcode":"2541",
    "sg:province":"NSW",
    "sg:tags":[
        "battery",
        "automotive"
    ],
    "wof:name":"Supercharge Batteries",
    "wof:placetype":"venue"
},
  "geometry": {"coordinates":[150.612548828,-34.8497428894],"type":"Point"}
}