{
  "type": "Feature",
  "properties": {
    "addr:full":"73 Lewis Rd Glynde SA 5070",
    "addr:housenumber":"73",
    "addr:postcode":"5070",
    "addr:street":"Lewis Rd",
    "iso:country":"AU",
    "sg:address":"73 Lewis Rd",
    "sg:city":"Glynde",
    "sg:classifiers":[
        {
            "category":"Building & Trades",
            "subcategory":"Construction",
            "type":"Services"
        }
    ],
    "sg:phone":"+61 412 803 782",
    "sg:postcode":"5070",
    "sg:province":"SA",
    "sg:tags":[
        "mural"
    ],
    "wof:name":"New Face Signs",
    "wof:placetype":"venue"
},
  "geometry": {"coordinates":[138.65272522000001,-34.8933029175],"type":"Point"}
}