{
  "type": "Feature",
  "properties": {
    "addr:full":"114 Marks Rd Gorokan NSW 2263",
    "addr:housenumber":"114",
    "addr:postcode":"2263",
    "addr:street":"Marks Rd",
    "iso:country":"AU",
    "sg:address":"114 Marks Rd",
    "sg:city":"Gorokan",
    "sg:classifiers":[
        {
            "category":"Professional",
            "subcategory":"Accounting & Tax Preparation",
            "type":"Services"
        }
    ],
    "sg:phone":"+61 2 4392 2240",
    "sg:postcode":"2263",
    "sg:province":"NSW",
    "sg:tags":[
        "accountant",
        "auditor"
    ],
    "wof:name":"Granger J",
    "wof:placetype":"venue"
},
  "geometry": {"coordinates":[151.50213600000001,-33.261974],"type":"Point"}
}