{
  "type": "Feature",
  "properties": {
    "iso:country":"AU",
    "sg:address":"98 Atkinson St",
    "sg:city":"Oakleigh",
    "sg:classifiers":[
        {
            "category":"Health Services",
            "subcategory":"Health Practitioner",
            "type":"Services"
        }
    ],
    "sg:phone":"+61 3 9568 3170",
    "sg:postcode":"3166",
    "sg:province":"VIC",
    "sg:tags":[
        "psychologist"
    ],
    "sg:website":"http://www.acaciacounselling.com.au",
    "wof:name":"Acacia Counselling & Psychology Centre",
    "wof:placetype":"venue"
},
  "geometry": {"coordinates":[145.093017578,-37.8964309692],"type":"Point"}
}