{
  "type": "Feature",
  "properties": {
    "iso:country":"AU",
    "sg:address":"42-44 Manilla St",
    "sg:city":"East Brisbane",
    "sg:classifiers":[
        {
            "category":"Wholesale",
            "subcategory":"Electrical",
            "type":"Manufacturing & Wholesale Goods"
        }
    ],
    "sg:phone":"+61 7 3391 8311",
    "sg:postcode":"4169",
    "sg:province":"QLD",
    "sg:tags":[
        "control",
        "equipment",
        "switch"
    ],
    "wof:name":"Bell Electrical Products",
    "wof:placetype":"venue"
},
  "geometry": {"coordinates":[153.04156494099999,-27.4822654724],"type":"Point"}
}