{
  "type": "Feature",
  "properties": {
    "addr:full":"63 Melbourne St South Brisbane QLD 4101",
    "addr:housenumber":"63",
    "addr:postcode":"4101",
    "addr:street":"Melbourne St",
    "iso:country":"AU",
    "sg:address":"63 Melbourne St",
    "sg:city":"South Brisbane",
    "sg:classifiers":[
        {
            "category":"Professional",
            "subcategory":"Employment Agencies",
            "type":"Services"
        }
    ],
    "sg:phone":"+61 7 3846 6606",
    "sg:postcode":"4101",
    "sg:province":"QLD",
    "sg:tags":[
        "hire",
        "labour",
        "contractor"
    ],
    "wof:name":"Quinn & Associates",
    "wof:placetype":"venue"
},
  "geometry": {"coordinates":[153.01756286599999,-27.4742622375],"type":"Point"}
}