{
  "type": "Feature",
  "properties": {
    "addr:full":"14 Elaroo Ave Phillip Bay NSW 2036",
    "addr:housenumber":"14",
    "addr:postcode":"2036",
    "addr:street":"Elaroo Ave Phillip",
    "iso:country":"AU",
    "sg:address":"14 Elaroo Ave",
    "sg:city":"Phillip Bay",
    "sg:classifiers":[
        {
            "category":"Building & Trades",
            "subcategory":"Cleaning & Sanitation",
            "type":"Services"
        }
    ],
    "sg:phone":"+61 2 9694 1350",
    "sg:postcode":"2036",
    "sg:province":"NSW",
    "sg:tags":[
        "industrial",
        "commercial",
        "contractor"
    ],
    "wof:name":"Pandaclean",
    "wof:placetype":"venue"
},
  "geometry": {"coordinates":[151.232131958,-33.9823570251],"type":"Point"}
}