{
  "type": "Feature",
  "properties": {
    "addr:full":"62 Aqueduck Rd Langwarrin VIC 3910",
    "addr:housenumber":"62",
    "addr:postcode":"3910",
    "addr:street":"Aqueduck Rd",
    "iso:country":"AU",
    "sg:address":"62 Aqueduck Rd",
    "sg:city":"Langwarrin",
    "sg:classifiers":[
        {
            "category":"Professional",
            "subcategory":"Art Services",
            "type":"Services"
        }
    ],
    "sg:phone":"+61 3 9789 9846",
    "sg:postcode":"3910",
    "sg:province":"VIC",
    "sg:tags":[
        "decorator",
        "painter"
    ],
    "wof:name":"L & S Moran",
    "wof:placetype":"venue"
},
  "geometry": {"coordinates":[145.207229614,-38.1657676697],"type":"Point"}
}