{
  "type": "Feature",
  "properties": {
    "addr:full":"134 Cromwell St Collingwood VIC 3066",
    "addr:housenumber":"134",
    "addr:postcode":"3066",
    "addr:street":"Cromwell St",
    "iso:country":"AU",
    "sg:address":"134 Cromwell St",
    "sg:city":"Collingwood",
    "sg:classifiers":[
        {
            "category":"Shopping",
            "subcategory":"Clothing, Apparel, & Fashions",
            "type":"Retail Goods"
        }
    ],
    "sg:phone":"+61 3 9416 5206",
    "sg:postcode":"3066",
    "sg:province":"VIC",
    "sg:tags":[
        "lady",
        "wear"
    ],
    "wof:name":"Beaches Fashion",
    "wof:placetype":"venue"
},
  "geometry": {"coordinates":[144.99055480999999,-37.8038825989],"type":"Point"}
}