{
  "type": "Feature",
  "properties": {
    "addr:full":"120 Clarence St Sydney NSW 2001",
    "addr:housenumber":"120",
    "addr:postcode":"2001",
    "addr:street":"Clarence St",
    "iso:country":"AU",
    "sg:address":"120 Clarence St",
    "sg:city":"Sydney",
    "sg:classifiers":[
        {
            "category":"Shopping",
            "subcategory":"Clothing, Apparel, & Fashions",
            "type":"Retail Goods"
        }
    ],
    "sg:phone":"+61 1800 035 345",
    "sg:postcode":"2001",
    "sg:province":"NSW",
    "sg:tags":[
        "uniform"
    ],
    "wof:name":"Perri Cutten Corporate Apparel",
    "wof:placetype":"venue"
},
  "geometry": {"coordinates":[151.20542907699999,-33.8686027527],"type":"Point"}
}