{
  "type": "Feature",
  "properties": {
    "iso:country":"AU",
    "sg:address":"16 Alpine Rd",
    "sg:city":"Kalamunda",
    "sg:classifiers":[
        {
            "category":"Shopping",
            "subcategory":"Computers & Home Electronics",
            "type":"Retail Goods"
        }
    ],
    "sg:phone":"+61 8 9293 1221",
    "sg:postcode":"6076",
    "sg:province":"WA",
    "sg:tags":[
        "equipment",
        "part",
        "electronic"
    ],
    "wof:name":"Peter Proposch Electronics",
    "wof:placetype":"venue"
},
  "geometry": {"coordinates":[116.046386719,-31.9767551422],"type":"Point"}
}