{
  "type": "Feature",
  "properties": {
    "iso:country":"AU",
    "sg:address":"Unit 1/ 1935 Beach Rd",
    "sg:city":"Malaga",
    "sg:classifiers":[
        {
            "category":"Building & Trades",
            "subcategory":"Construction",
            "type":"Services"
        }
    ],
    "sg:phone":"+61 412 586 736",
    "sg:postcode":"6090",
    "sg:province":"WA",
    "sg:tags":[
        "home",
        "air conditioning"
    ],
    "wof:name":"Escape Airconditioning",
    "wof:placetype":"venue"
},
  "geometry": {"coordinates":[115.88722991900001,-31.8555812836],"type":"Point"}
}