{
  "type": "Feature",
  "properties": {
    "addr:full":"600 George St Sydney NSW 2000",
    "addr:housenumber":"600",
    "addr:postcode":"2000",
    "addr:street":"George St",
    "iso:country":"AU",
    "sg:address":"600 George St",
    "sg:city":"Sydney",
    "sg:classifiers":[
        {
            "category":"Travel",
            "subcategory":"Travel Agent",
            "type":"Entertainment"
        }
    ],
    "sg:phone":"+61 2 9283 5818",
    "sg:postcode":"2000",
    "sg:province":"NSW",
    "sg:tags":[
        "consultant"
    ],
    "wof:name":"Mid City Travel",
    "wof:placetype":"venue"
},
  "geometry": {"coordinates":[151.206832886,-33.8750152588],"type":"Point"}
}