{
  "type": "Feature",
  "properties": {
    "addr:full":"22 Flinders St Wollongong NSW 2500",
    "addr:housenumber":"22",
    "addr:postcode":"2500",
    "addr:street":"Flinders St",
    "iso:country":"AU",
    "sg:address":"22 Flinders St",
    "sg:city":"Wollongong",
    "sg:classifiers":[
        {
            "category":"Utilities",
            "subcategory":"Water",
            "type":"Services"
        }
    ],
    "sg:phone":"+61 2 4229 6200",
    "sg:postcode":"2500",
    "sg:province":"NSW",
    "sg:tags":[
        "hot",
        "system"
    ],
    "wof:name":"Ian Jones Hot Water Maintenance",
    "wof:placetype":"venue"
},
  "geometry": {"coordinates":[150.89274599999999,-34.415005],"type":"Point"}
}