{
  "type": "Feature",
  "properties": {
    "addr:full":"Kennedy Hwy Atherton QLD 4883",
    "addr:postcode":"4883",
    "addr:street":"Kennedy Hwy",
    "iso:country":"AU",
    "sg:address":"Kennedy Hwy",
    "sg:city":"Atherton",
    "sg:classifiers":[
        {
            "category":"Farming",
            "subcategory":"Farm",
            "type":"Manufacturing & Wholesale Goods"
        }
    ],
    "sg:phone":"+61 7 4091 1032",
    "sg:postcode":"4883",
    "sg:province":"QLD",
    "sg:tags":[
        "farmer"
    ],
    "wof:name":"Barletta Fred & Rose",
    "wof:placetype":"venue"
},
  "geometry": {"coordinates":[145.48304748499999,-17.269651413],"type":"Point"}
}