{
  "type": "Feature",
  "properties": {
    "iso:country":"AU",
    "sg:address":"Lot 4, Pacific Hwy West",
    "sg:city":"Ballina",
    "sg:classifiers":[
        {
            "category":"Autos & Motor Vehicles",
            "subcategory":"Automobile Sales",
            "type":"Retail Goods"
        }
    ],
    "sg:phone":"+61 2 6686 7315",
    "sg:postcode":"2478",
    "sg:province":"NSW",
    "sg:tags":[
        "car",
        "used"
    ],
    "wof:name":"Can Steer Pty Ltd",
    "wof:placetype":"venue"
},
  "geometry": {"coordinates":[153.516723633,-28.8626613617],"type":"Point"}
}