{
  "type": "Feature",
  "properties": {
    "iso:country":"AU",
    "sg:address":"59 Arnott St",
    "sg:city":"Manjimup",
    "sg:classifiers":[
        {
            "category":"Building & Trades",
            "subcategory":"Construction",
            "type":"Services"
        }
    ],
    "sg:phone":"+61 8 9777 1209",
    "sg:postcode":"6258",
    "sg:province":"WA",
    "sg:tags":[
        "plasterboard",
        "plasterer",
        "fixer"
    ],
    "wof:name":"Brotherton Doug",
    "wof:placetype":"venue"
},
  "geometry": {"coordinates":[116.137901306,-34.2351455688],"type":"Point"}
}