{
  "type": "Feature",
  "properties": {
    "iso:country":"AU",
    "sg:address":"62 Stella St",
    "sg:city":"Holland Park",
    "sg:classifiers":[
        {
            "category":"Arts & Performance",
            "subcategory":"Dance",
            "type":"Entertainment"
        }
    ],
    "sg:phone":"+61 7 3394 4925",
    "sg:postcode":"4121",
    "sg:province":"QLD",
    "sg:tags":[
        "theatrical",
        "ballet",
        "tuition"
    ],
    "wof:name":"Regional Co-Ordinators For Queensland",
    "wof:placetype":"venue"
},
  "geometry": {"coordinates":[153.068084717,-27.5173950195],"type":"Point"}
}