{
  "type": "Feature",
  "properties": {
    "addr:full":"Unit 37/ 12- 14 Clubb Crs Miranda NSW 2228",
    "addr:housenumber":"/;14",
    "addr:postcode":"2228",
    "addr:street":"Clubb Crs Miranda",
    "iso:country":"AU",
    "sg:address":"Unit 37/ 12- 14 Clubb Crs",
    "sg:city":"Miranda",
    "sg:classifiers":[
        {
            "category":"Building & Trades",
            "subcategory":"Pest Control",
            "type":"Services"
        }
    ],
    "sg:phone":"+61 2 9525 8616",
    "sg:postcode":"2228",
    "sg:province":"NSW",
    "wof:name":"Hunt&#039;em Out Pest Control P/L",
    "wof:placetype":"venue"
},
  "geometry": {"coordinates":[151.10531616200001,-34.0398597717],"type":"Point"}
}