{
  "type": "Feature",
  "properties": {
    "iso:country":"AU",
    "sg:address":"Fox Valley Medical & Dental Centre 187 Fox Valley Rd",
    "sg:city":"Wahroonga",
    "sg:classifiers":[
        {
            "category":"Health Services",
            "subcategory":"Doctor",
            "type":"Services"
        }
    ],
    "sg:phone":"+61 2 9487 9700",
    "sg:postcode":"2076",
    "sg:province":"NSW",
    "sg:tags":[
        "medical",
        "practitioner"
    ],
    "wof:name":"Lee D",
    "wof:placetype":"venue"
},
  "geometry": {"coordinates":[151.100006103,-33.7345161438],"type":"Point"}
}