{
  "type": "Feature",
  "properties": {
    "iso:country":"AU",
    "sg:address":"40 Ethel St",
    "sg:city":"Traralgon",
    "sg:classifiers":[
        {
            "category":"Building & Trades",
            "subcategory":"Construction",
            "type":"Services"
        }
    ],
    "sg:phone":"+61 3 5174 3829",
    "sg:postcode":"3844",
    "sg:province":"VIC",
    "sg:tags":[
        "renovation",
        "alterations",
        "extension",
        "contractor"
    ],
    "wof:name":"Hollingsworth Shane Craftsman Builder",
    "wof:placetype":"venue"
},
  "geometry": {"coordinates":[146.52972412099999,-38.1957588196],"type":"Point"}
}