{
  "type": "Feature",
  "properties": {
    "addr:full":"19 Castlereagh St Coonamble NSW 2829",
    "addr:housenumber":"19",
    "addr:postcode":"2829",
    "addr:street":"Castlereagh St",
    "iso:country":"AU",
    "sg:address":"19 Castlereagh St",
    "sg:city":"Coonamble",
    "sg:classifiers":[
        {
            "category":"Health Services",
            "subcategory":"Doctor",
            "type":"Services"
        }
    ],
    "sg:phone":"+61 2 6822 1055",
    "sg:postcode":"2829",
    "sg:province":"NSW",
    "sg:tags":[
        "medical",
        "practitioner"
    ],
    "wof:name":"Nguyen H Dr",
    "wof:placetype":"venue"
},
  "geometry": {"coordinates":[148.38902282699999,-30.9514808655],"type":"Point"}
}