{
  "type": "Feature",
  "properties": {
    "iso:country":"AU",
    "sg:address":"4091 Princes Hwy",
    "sg:city":"Lyons",
    "sg:classifiers":[
        {
            "category":"Farming",
            "subcategory":"Fish & Marine Products",
            "type":"Manufacturing & Wholesale Goods"
        }
    ],
    "sg:phone":"+61 3 5528 4200",
    "sg:postcode":"3304",
    "sg:province":"VIC",
    "sg:tags":[
        "organic"
    ],
    "wof:name":"Ostara Organics",
    "wof:placetype":"venue"
},
  "geometry": {"coordinates":[141.46188354500001,-38.0101776123],"type":"Point"}
}