{
  "type": "Feature",
  "properties": {
    "iso:country":"AU",
    "sg:address":"43a Rankins Rd",
    "sg:city":"Monbulk",
    "sg:classifiers":[
        {
            "category":"Building & Trades",
            "subcategory":"Construction",
            "type":"Services"
        }
    ],
    "sg:phone":"+61 407 097 556",
    "sg:postcode":"3793",
    "sg:province":"VIC",
    "sg:tags":[
        "polishing",
        "sanding",
        "floor"
    ],
    "wof:name":"Mirror Finish Floors",
    "wof:placetype":"venue"
},
  "geometry": {"coordinates":[145.42279052699999,-37.8899345398],"type":"Point"}
}