{
  "type": "Feature",
  "properties": {
    "addr:full":"136 Springbank Rd Brundee NSW 2540",
    "addr:housenumber":"136",
    "addr:postcode":"2540",
    "addr:street":"Springbank Rd",
    "iso:country":"AU",
    "sg:address":"136 Springbank Rd",
    "sg:city":"Brundee",
    "sg:classifiers":[
        {
            "category":"Building & Trades",
            "subcategory":"Pest Control",
            "type":"Services"
        }
    ],
    "sg:phone":"+61 413 722 263",
    "sg:postcode":"2540",
    "sg:province":"NSW",
    "wof:name":"Total Feral Control",
    "wof:placetype":"venue"
},
  "geometry": {"coordinates":[150.66941833499999,-34.9253807068],"type":"Point"}
}