{
  "type": "Feature",
  "properties": {
    "addr:full":"326 Hobart Rd Youngtown TAS 7249",
    "addr:housenumber":"326",
    "addr:postcode":"7249",
    "addr:street":"Hobart Rd",
    "iso:country":"AU",
    "sg:address":"326 Hobart Rd",
    "sg:city":"Youngtown",
    "sg:classifiers":[
        {
            "category":"Professional",
            "subcategory":"Engineering",
            "type":"Services"
        }
    ],
    "sg:phone":"+61 3 6344 4032",
    "sg:postcode":"7249",
    "sg:province":"TAS",
    "sg:tags":[
        "refrigeration",
        "engineer"
    ],
    "wof:name":"Dakin Refrigeration",
    "wof:placetype":"venue"
},
  "geometry": {"coordinates":[147.16729736299999,-41.4821586609],"type":"Point"}
}