{
  "type": "Feature",
  "properties": {
    "iso:country":"AU",
    "sg:address":"40b Wantirna Rd",
    "sg:city":"Ringwood",
    "sg:classifiers":[
        {
            "category":"Personal",
            "subcategory":"Beauty Salon",
            "type":"Services"
        }
    ],
    "sg:phone":"+61 3 9879 6031",
    "sg:postcode":"3134",
    "sg:province":"VIC",
    "wof:name":"Little Lush Health & Beauty",
    "wof:placetype":"venue"
},
  "geometry": {"coordinates":[145.22714233400001,-37.8206825256],"type":"Point"}
}