{
  "type": "Feature",
  "properties": {
    "addr:full":"Myrtle Rd Epsom VIC 3551",
    "addr:postcode":"3551",
    "addr:street":"Myrtle Rd",
    "iso:country":"AU",
    "sg:address":"Myrtle Rd",
    "sg:city":"Epsom",
    "sg:classifiers":[
        {
            "category":"Education",
            "subcategory":"Kindergarten",
            "type":"Public Place"
        }
    ],
    "sg:phone":"+61 3 5448 4037",
    "sg:postcode":"3551",
    "sg:province":"VIC",
    "sg:tags":[
        "pre-schools"
    ],
    "wof:name":"Epsom Pre-School Centre",
    "wof:placetype":"venue"
},
  "geometry": {"coordinates":[144.320556641,-36.7115898132],"type":"Point"}
}