{
  "type": "Feature",
  "properties": {
    "addr:full":"118 Pearcedale Rd Pearcedale VIC 3912",
    "addr:housenumber":"118",
    "addr:postcode":"3912",
    "addr:street":"Pearcedale Rd",
    "iso:country":"AU",
    "sg:address":"118 Pearcedale Rd",
    "sg:city":"Pearcedale",
    "sg:classifiers":[
        {
            "category":"Home & Garden",
            "subcategory":"Carpets & Floor Coverings",
            "type":"Retail Goods"
        }
    ],
    "sg:phone":"+61 3 5978 6538",
    "sg:postcode":"3912",
    "sg:province":"VIC",
    "sg:tags":[
        "layer",
        "planner"
    ],
    "wof:name":"Moody Ray",
    "wof:placetype":"venue"
},
  "geometry": {"coordinates":[145.23619079599999,-38.1980934143],"type":"Point"}
}