{
  "type": "Feature",
  "properties": {
    "addr:full":"49 Uralba St Lismore NSW 2480",
    "addr:housenumber":"49",
    "addr:postcode":"2480",
    "addr:street":"Uralba St",
    "iso:country":"AU",
    "sg:address":"49 Uralba St",
    "sg:city":"Lismore",
    "sg:classifiers":[
        {
            "category":"Health Services",
            "subcategory":"Dentist",
            "type":"Services"
        }
    ],
    "sg:phone":"+61 2 6622 1211",
    "sg:postcode":"2480",
    "sg:province":"NSW",
    "wof:name":"McDonough Maurice Dr",
    "wof:placetype":"venue"
},
  "geometry": {"coordinates":[153.29069519000001,-28.8100261688],"type":"Point"}
}