{
  "type": "Feature",
  "properties": {
    "addr:full":"Cnr Alan St & The Horsley Drv Fairfield NSW 2165",
    "addr:postcode":"2165",
    "addr:street":"Alan St & The Horsley Drv",
    "iso:country":"AU",
    "sg:address":"Cnr Alan St & The Horsley Drv",
    "sg:city":"Fairfield",
    "sg:classifiers":[
        {
            "category":"Fast Food",
            "type":"Food & Drink"
        }
    ],
    "sg:phone":"+61 2 9728 6037",
    "sg:postcode":"2165",
    "sg:province":"NSW",
    "sg:tags":[
        "away",
        "take"
    ],
    "wof:name":"KFC",
    "wof:placetype":"venue"
},
  "geometry": {"coordinates":[150.958618164,-33.869720459],"type":"Point"}
}