{
  "type": "Feature",
  "properties": {
    "iso:country":"AU",
    "sg:address":"110 Station St",
    "sg:city":"Rooty Hill",
    "sg:classifiers":[
        {
            "category":"Retail",
            "subcategory":"Auto Repair",
            "type":"Services"
        }
    ],
    "sg:phone":"+61 2 9625 0001",
    "sg:postcode":"2766",
    "sg:province":"NSW",
    "sg:tags":[
        "repairer",
        "motor",
        "engineer"
    ],
    "wof:name":"Szepco Motors Pty Ltd",
    "wof:placetype":"venue"
},
  "geometry": {"coordinates":[150.84591674800001,-33.7623558044],"type":"Point"}
}