{
  "type": "Feature",
  "properties": {
    "addr:full":"Burrum St Bundaberg QLD 4670",
    "addr:postcode":"4670",
    "addr:street":"St",
    "iso:country":"AU",
    "sg:address":"Burrum St",
    "sg:city":"Bundaberg",
    "sg:classifiers":[
        {
            "category":"Education",
            "subcategory":"Music School",
            "type":"Public Place"
        }
    ],
    "sg:phone":"+61 7 4153 5326",
    "sg:postcode":"4670",
    "sg:province":"QLD",
    "sg:tags":[
        "choir",
        "bands",
        "orchestra"
    ],
    "wof:name":"Bundaberg Municipal Band The",
    "wof:placetype":"venue"
},
  "geometry": {"coordinates":[152.344573975,-24.8679332733],"type":"Point"}
}