{
  "type": "Feature",
  "properties": {
    "addr:full":"1 Bardo La Wagga Wagga NSW 2650",
    "addr:housenumber":"1",
    "addr:postcode":"2650",
    "addr:street":"Bardo La",
    "iso:country":"AU",
    "sg:address":"1 Bardo La",
    "sg:city":"Wagga Wagga",
    "sg:classifiers":[
        {
            "category":"Utilities",
            "subcategory":"Electric",
            "type":"Services"
        }
    ],
    "sg:phone":"+61 2 6971 7300",
    "sg:postcode":"2650",
    "sg:province":"NSW",
    "sg:tags":[
        "electrical",
        "contractor"
    ],
    "wof:name":"Apac Electrics",
    "wof:placetype":"venue"
},
  "geometry": {"coordinates":[147.37396240199999,-35.1126022339],"type":"Point"}
}