{
  "type": "Feature",
  "properties": {
    "iso:country":"AU",
    "sg:address":"3 Evelyn St",
    "sg:city":"Toowoomba",
    "sg:classifiers":[
        {
            "category":"Retail",
            "subcategory":"Auto Repair",
            "type":"Services"
        }
    ],
    "sg:phone":"+61 7 4632 3844",
    "sg:postcode":"4350",
    "sg:province":"QLD",
    "sg:tags":[
        "beater",
        "painter",
        "panel"
    ],
    "wof:name":"Holmes Smash Repairs Pty. Ltd.",
    "wof:placetype":"venue"
},
  "geometry": {"coordinates":[151.95564300000001,-27.553099],"type":"Point"}
}