{
  "type": "Feature",
  "properties": {
    "iso:country":"AU",
    "sg:address":"South Rd",
    "sg:city":"Officer",
    "sg:classifiers":[
        {
            "category":"Utilities",
            "subcategory":"Telephone",
            "type":"Services"
        }
    ],
    "sg:phone":"+61 3 5943 1070",
    "sg:postcode":"3809",
    "sg:province":"VIC",
    "sg:tags":[
        "installation",
        "system",
        "maintenance"
    ],
    "wof:name":"ABE Telephone Systems",
    "wof:placetype":"venue"
},
  "geometry": {"coordinates":[145.37982199999999,-38.048008],"type":"Point"}
}