{
  "type": "Feature",
  "properties": {
    "addr:full":"12 Heatherhill Rd Frankston VIC 3199",
    "addr:housenumber":"12",
    "addr:postcode":"3199",
    "addr:street":"Heatherhill Rd",
    "iso:country":"AU",
    "sg:address":"12 Heatherhill Rd",
    "sg:city":"Frankston",
    "sg:classifiers":[
        {
            "category":"Health Services",
            "subcategory":"Chiropractor",
            "type":"Services"
        }
    ],
    "sg:phone":"+61 3 9781 4855",
    "sg:postcode":"3199",
    "sg:province":"VIC",
    "wof:name":"Tarburton Kerrin",
    "wof:placetype":"venue"
},
  "geometry": {"coordinates":[145.13742065400001,-38.1582107544],"type":"Point"}
}