{
  "type": "Feature",
  "properties": {
    "iso:country":"AU",
    "sg:address":"Cnr Bursill St & Railway Tce",
    "sg:city":"Guildford",
    "sg:classifiers":[
        {
            "category":"Health Services",
            "subcategory":"Nursing And Care Facility",
            "type":"Services"
        }
    ],
    "sg:phone":"+61 2 9632 2496",
    "sg:postcode":"2161",
    "sg:province":"NSW",
    "sg:tags":[
        "home"
    ],
    "wof:name":"Guildford Aged Care Facility",
    "wof:placetype":"venue"
},
  "geometry": {"coordinates":[150.99121093799999,-33.8509483337],"type":"Point"}
}