{
  "type": "Feature",
  "properties": {
    "addr:full":"Warrego Hwy Plainland QLD 4341",
    "addr:postcode":"4341",
    "addr:street":"Warrego Hwy",
    "iso:country":"AU",
    "sg:address":"Warrego Hwy",
    "sg:city":"Plainland",
    "sg:classifiers":[
        {
            "category":"Home & Garden",
            "subcategory":"Building Materials",
            "type":"Retail Goods"
        }
    ],
    "sg:phone":"+61 7 5465 6648",
    "sg:postcode":"4341",
    "sg:province":"QLD",
    "sg:tags":[
        "fencing"
    ],
    "wof:name":"Plainland's Hardware & Rural Centre",
    "wof:placetype":"venue"
},
  "geometry": {"coordinates":[152.42181396500001,-27.5650100708],"type":"Point"}
}