{
  "type": "Feature",
  "properties": {
    "iso:country":"AU",
    "sg:address":"12/ 20 Cook Rd",
    "sg:city":"Marrickville",
    "sg:classifiers":[
        {
            "category":"Building & Trades",
            "subcategory":"Construction",
            "type":"Services"
        }
    ],
    "sg:phone":"+61 2 9524 7045",
    "sg:postcode":"2204",
    "sg:province":"NSW",
    "sg:tags":[
        "industrial",
        "commercial",
        "air conditioning"
    ],
    "wof:name":"Aireffect (A Division Of Croydon Industries)",
    "wof:placetype":"venue"
},
  "geometry": {"coordinates":[151.166595,-33.904408],"type":"Point"}
}