{
  "type": "Feature",
  "properties": {
    "iso:country":"AU",
    "sg:address":"Units 4 & 5/ 122 Connaught St",
    "sg:city":"Sandgate",
    "sg:phone":"+61 7 3869 0155",
    "sg:postcode":"4017",
    "sg:province":"QLD",
    "sg:website":"http://www.brisbanetanks.com.au",
    "wof:name":"Brisbane Tank Manufacturing",
    "wof:placetype":"venue"
},
  "geometry": {"coordinates":[153.05648803700001,-27.3186206818],"type":"Point"}
}