{
  "type": "Feature",
  "properties": {
    "addr:full":"8 Pearl St Torquay VIC 3228",
    "addr:housenumber":"8",
    "addr:postcode":"3228",
    "addr:street":"Pearl St",
    "iso:country":"AU",
    "sg:address":"8 Pearl St",
    "sg:city":"Torquay",
    "sg:classifiers":[
        {
            "category":"Fast Food",
            "type":"Food & Drink"
        }
    ],
    "sg:phone":"+61 3 5261 2681",
    "sg:postcode":"3228",
    "sg:province":"VIC",
    "sg:tags":[
        "away",
        "take"
    ],
    "wof:name":"Surf Coast Pizza",
    "wof:placetype":"venue"
},
  "geometry": {"coordinates":[144.32360800000001,-38.332645],"type":"Point"}
}