{
  "type": "Feature",
  "properties": {
    "addr:full":"187 Scarborough Beach Rd Mt Hawthorn WA 6016",
    "addr:housenumber":"187",
    "addr:postcode":"6016",
    "addr:street":"Scarborough Beach Rd",
    "iso:country":"AU",
    "sg:address":"187 Scarborough Beach Rd",
    "sg:city":"Mt Hawthorn",
    "sg:classifiers":[
        {
            "category":"Health Services",
            "subcategory":"Dentist",
            "type":"Services"
        }
    ],
    "sg:phone":"+61 8 9443 6188",
    "sg:postcode":"6016",
    "sg:province":"WA",
    "wof:name":"Southall Peter J",
    "wof:placetype":"venue"
},
  "geometry": {"coordinates":[115.83032989500001,-31.9153766632],"type":"Point"}
}