{
  "type": "Feature",
  "properties": {
    "addr:full":"16 Joseph St Lidcombe NSW 2141",
    "addr:housenumber":"16",
    "addr:postcode":"2141",
    "addr:street":"Joseph St",
    "iso:country":"AU",
    "sg:address":"16 Joseph St",
    "sg:city":"Lidcombe",
    "sg:classifiers":[
        {
            "category":"Personal",
            "subcategory":"Beauty Salon",
            "type":"Services"
        }
    ],
    "sg:phone":"+61 2 9749 2247",
    "sg:postcode":"2141",
    "sg:province":"NSW",
    "sg:tags":[
        "hairdresser"
    ],
    "wof:name":"Karhani Yehya",
    "wof:placetype":"venue"
},
  "geometry": {"coordinates":[151.043533325,-33.8643531799],"type":"Point"}
}