{
  "type": "Feature",
  "properties": {
    "addr:full":"1059 Doncaster Rd Doncaster East VIC 3109",
    "addr:housenumber":"1059",
    "addr:postcode":"3109",
    "addr:street":"Doncaster Rd",
    "iso:country":"AU",
    "sg:address":"1059 Doncaster Rd",
    "sg:city":"Doncaster East",
    "sg:classifiers":[
        {
            "category":"Health Services",
            "subcategory":"Dentist",
            "type":"Services"
        }
    ],
    "sg:phone":"+61 3 9841 8350",
    "sg:postcode":"3109",
    "sg:province":"VIC",
    "wof:name":"Wong Edward",
    "wof:placetype":"venue"
},
  "geometry": {"coordinates":[145.16526794399999,-37.7893638611],"type":"Point"}
}