{
  "type": "Feature",
  "properties": {
    "iso:country":"AU",
    "sg:address":"36 Second St",
    "sg:city":"Parkdale",
    "sg:classifiers":[
        {
            "category":"Building & Trades",
            "subcategory":"Plumbing",
            "type":"Services"
        }
    ],
    "sg:phone":"+61 419 331 172",
    "sg:postcode":"3195",
    "sg:province":"VIC",
    "sg:tags":[
        "plumber",
        "gasfitters"
    ],
    "wof:name":"R & J Wadham Plumbing",
    "wof:placetype":"venue"
},
  "geometry": {"coordinates":[145.07388305699999,-37.9845046997],"type":"Point"}
}