{
  "type": "Feature",
  "properties": {
    "addr:full":"193 Honour Ave Chelmer QLD 4068",
    "addr:housenumber":"193",
    "addr:postcode":"4068",
    "addr:street":"Honour Ave",
    "iso:country":"AU",
    "sg:address":"193 Honour Ave",
    "sg:city":"Chelmer",
    "sg:classifiers":[
        {
            "category":"Insurance",
            "subcategory":"Insurance Agent",
            "type":"Services"
        }
    ],
    "sg:phone":"+61 7 3278 4344",
    "sg:postcode":"4068",
    "sg:province":"QLD",
    "sg:tags":[
        "broker"
    ],
    "wof:name":"Infocus General Insurance",
    "wof:placetype":"venue"
},
  "geometry": {"coordinates":[152.97317504899999,-27.5156784058],"type":"Point"}
}