{
  "type": "Feature",
  "properties": {
    "iso:country":"AU",
    "sg:address":"Upstairs 123-125 St John's St",
    "sg:city":"Launceston",
    "sg:classifiers":[
        {
            "category":"Organizations",
            "subcategory":"Community Association",
            "type":"Services"
        }
    ],
    "sg:phone":"+61 3 6334 4556",
    "sg:postcode":"7250",
    "sg:province":"TAS",
    "sg:tags":[
        "organisation",
        "family",
        "welfare"
    ],
    "wof:name":"Glenhaven Family Care",
    "wof:placetype":"venue"
},
  "geometry": {"coordinates":[147.14021301299999,-41.4388084412],"type":"Point"}
}