{
  "type": "Feature",
  "properties": {
    "addr:full":"299 Darling St Balmain NSW 2041",
    "addr:housenumber":"299",
    "addr:postcode":"2041",
    "addr:street":"Darling St",
    "iso:country":"AU",
    "sg:address":"299 Darling St",
    "sg:city":"Balmain",
    "sg:classifiers":[
        {
            "category":"Personal",
            "subcategory":"Beauty Salon",
            "type":"Services"
        }
    ],
    "sg:phone":"+61 2 9810 3910",
    "sg:postcode":"2041",
    "sg:province":"NSW",
    "sg:tags":[
        "hairdresser"
    ],
    "wof:name":"Ricciardone's Unisex Hair Stylists",
    "wof:placetype":"venue"
},
  "geometry": {"coordinates":[151.18052700000001,-33.857147],"type":"Point"}
}