{
  "type": "Feature",
  "properties": {
    "addr:full":"Rear of 69 Burswood Rd Burswood WA 6100",
    "addr:housenumber":"rear of 69",
    "addr:postcode":"6100",
    "addr:street":"Burswood Rd",
    "iso:country":"AU",
    "sg:address":"Rear of 69 Burswood Rd",
    "sg:city":"Burswood",
    "sg:classifiers":[
        {
            "category":"Manufacturing",
            "subcategory":"Motor Vehicles & Parts",
            "type":"Manufacturing & Wholesale Goods"
        }
    ],
    "sg:phone":"+61 8 9355 2712",
    "sg:postcode":"6100",
    "sg:province":"WA",
    "sg:tags":[
        "replacement"
    ],
    "wof:name":"Renault",
    "wof:placetype":"venue"
},
  "geometry": {"coordinates":[115.893493652,-31.9676837921],"type":"Point"}
}