{
  "type": "Feature",
  "properties": {
    "addr:full":"56 Bungil St Roma QLD 4455",
    "addr:housenumber":"56",
    "addr:postcode":"4455",
    "addr:street":"Bungil St",
    "iso:country":"AU",
    "sg:address":"56 Bungil St",
    "sg:city":"Roma",
    "sg:classifiers":[
        {
            "category":"Real Estate",
            "subcategory":"Surveying",
            "type":"Services"
        }
    ],
    "sg:phone":"+61 7 4622 2777",
    "sg:postcode":"4455",
    "sg:province":"QLD",
    "sg:tags":[
        "surveyor",
        "land"
    ],
    "wof:name":"Hedges Geomeasure",
    "wof:placetype":"venue"
},
  "geometry": {"coordinates":[148.79536438,-26.5722503662],"type":"Point"}
}