{
  "type": "Feature",
  "properties": {
    "addr:full":"6 Sommadatta Crt Nerang QLD 4211",
    "addr:housenumber":"6",
    "addr:postcode":"4211",
    "addr:street":"Sommadatta Crt",
    "iso:country":"AU",
    "sg:address":"6 Sommadatta Crt",
    "sg:city":"Nerang",
    "sg:classifiers":[
        {
            "category":"Social Services",
            "subcategory":"Adult Care",
            "type":"Services"
        }
    ],
    "sg:phone":"+61 7 5596 1729",
    "sg:postcode":"4211",
    "sg:province":"QLD",
    "sg:tags":[
        "towing"
    ],
    "wof:name":"Robin Wood 25 Hour Towing",
    "wof:placetype":"venue"
},
  "geometry": {"coordinates":[153.34393310600001,-27.9645767212],"type":"Point"}
}