{
  "type": "Feature",
  "properties": {
    "iso:country":"AU",
    "sg:address":"Cnr Pioneer Rd & Eastbourne Ave",
    "sg:city":"Bellambi",
    "sg:classifiers":[
        {
            "category":"Fast Food",
            "type":"Food & Drink"
        }
    ],
    "sg:phone":"+61 2 4283 2895",
    "sg:postcode":"2518",
    "sg:province":"NSW",
    "sg:tags":[
        "away",
        "take"
    ],
    "wof:name":"Bellambi Chicken Shop",
    "wof:placetype":"venue"
},
  "geometry": {"coordinates":[150.910248,-34.368607],"type":"Point"}
}