{
  "type": "Feature",
  "properties": {
    "addr:full":"Anketell St Tuggerawong NSW 2259",
    "addr:postcode":"2259",
    "addr:street":"Anketell St",
    "iso:country":"AU",
    "sg:address":"Anketell St",
    "sg:city":"Tuggerawong",
    "sg:classifiers":[
        {
            "category":"Sports & Exercise",
            "subcategory":"Gym",
            "type":"Entertainment"
        }
    ],
    "sg:phone":"+61 2 6293 3122",
    "sg:postcode":"2259",
    "sg:province":"NSW",
    "sg:tags":[
        "health",
        "fitness"
    ],
    "wof:name":"Lakeside Leisure Centre",
    "wof:placetype":"venue"
},
  "geometry": {"coordinates":[151.47962951700001,-33.2810783386],"type":"Point"}
}