{
  "type": "Feature",
  "properties": {
    "iso:country":"AU",
    "sg:address":"43 May Rd",
    "sg:city":"Lalor",
    "sg:classifiers":[
        {
            "category":"Personal",
            "subcategory":"Beauty Salon",
            "type":"Services"
        }
    ],
    "sg:phone":"+61 3 9465 0838",
    "sg:postcode":"3075",
    "sg:province":"VIC",
    "sg:tags":[
        "hairdresser"
    ],
    "wof:name":"Tuccis Hair And Beauty",
    "wof:placetype":"venue"
},
  "geometry": {"coordinates":[145.005981445,-37.8473205566],"type":"Point"}
}