{
  "type": "Feature",
  "properties": {
    "addr:full":"U4/ 474 Darling St Balmain NSW 2041",
    "addr:housenumber":"474",
    "addr:postcode":"2041",
    "addr:street":"U4 /;Darling St",
    "iso:country":"AU",
    "sg:address":"U4/ 474 Darling St",
    "sg:city":"Balmain",
    "sg:classifiers":[
        {
            "category":"Building & Trades",
            "subcategory":"Plumbing",
            "type":"Services"
        }
    ],
    "sg:phone":"+61 412 916 570",
    "sg:postcode":"2041",
    "sg:province":"NSW",
    "sg:tags":[
        "plumber",
        "gasfitters"
    ],
    "wof:name":"Allpipe Plumbing",
    "wof:placetype":"venue"
},
  "geometry": {"coordinates":[151.17242400000001,-33.857803],"type":"Point"}
}