{
  "type": "Feature",
  "properties": {
    "iso:country":"AU",
    "sg:address":"1/ 28 Templestowe Ave",
    "sg:city":"Conder",
    "sg:classifiers":[
        {
            "category":"Retail",
            "subcategory":"Storage",
            "type":"Services"
        }
    ],
    "sg:phone":"+61 438 543 348",
    "sg:postcode":"2906",
    "sg:province":"ACT",
    "sg:tags":[
        "removal",
        "furniture"
    ],
    "wof:name":"Mini Move Removals",
    "wof:placetype":"venue"
},
  "geometry": {"coordinates":[149.10905456500001,-35.4628639221],"type":"Point"}
}