{
  "type": "Feature",
  "properties": {
    "iso:country":"AU",
    "sg:address":"97 Swan St",
    "sg:city":"Morpeth",
    "sg:classifiers":[
        {
            "category":"Travel",
            "subcategory":"Hotels & Motels",
            "type":"Entertainment"
        }
    ],
    "sg:phone":"+61 2 4933 6202",
    "sg:postcode":"2321",
    "sg:province":"NSW",
    "sg:tags":[
        "accommodation"
    ],
    "wof:name":"River Royal Inn The",
    "wof:placetype":"venue"
},
  "geometry": {"coordinates":[151.62916564899999,-32.7248458862],"type":"Point"}
}