{
  "type": "Feature",
  "properties": {
    "addr:full":"72 McDowall St Roma QLD 4455",
    "addr:housenumber":"72",
    "addr:postcode":"4455",
    "addr:street":"Mcdowall St",
    "iso:country":"AU",
    "sg:address":"72 McDowall St",
    "sg:city":"Roma",
    "sg:classifiers":[
        {
            "category":"Professional",
            "subcategory":"Employment Agencies",
            "type":"Services"
        }
    ],
    "sg:phone":"+61 7 4622 8885",
    "sg:postcode":"4455",
    "sg:province":"QLD",
    "wof:name":"Skill Centred Queensland",
    "wof:placetype":"venue"
},
  "geometry": {"coordinates":[148.79017639200001,-26.5718383789],"type":"Point"}
}