{
  "type": "Feature",
  "properties": {
    "iso:country":"AU",
    "sg:address":"Bayswater Rd",
    "sg:city":"Rushcutters Bay",
    "sg:classifiers":[
        {
            "category":"Building & Trades",
            "subcategory":"Locksmith",
            "type":"Services"
        }
    ],
    "sg:phone":"+61 1300 736 683",
    "sg:postcode":"2011",
    "sg:province":"NSW",
    "sg:tags":[
        "equipment",
        "operating",
        "door",
        "gate"
    ],
    "wof:name":"A AAAllgate Automation",
    "wof:placetype":"venue"
},
  "geometry": {"coordinates":[151.22578430199999,-33.8760757446],"type":"Point"}
}