{
  "type": "Feature",
  "properties": {
    "iso:country":"AU",
    "sg:address":"12 Coronation Ave",
    "sg:city":"Pottsville",
    "sg:classifiers":[
        {
            "category":"Restaurant",
            "type":"Food & Drink"
        }
    ],
    "sg:phone":"+61 2 6676 4949",
    "sg:postcode":"2489",
    "sg:province":"NSW",
    "wof:name":"Cottage On Coronation",
    "wof:placetype":"venue"
},
  "geometry": {"coordinates":[153.563430786,-28.3896217346],"type":"Point"}
}