{
  "type": "Feature",
  "properties": {
    "addr:full":"2 Gears Ave Drummoyne NSW 2047",
    "addr:housenumber":"2",
    "addr:postcode":"2047",
    "addr:street":"Gears Ave",
    "iso:country":"AU",
    "sg:address":"2 Gears Ave",
    "sg:city":"Drummoyne",
    "sg:classifiers":[
        {
            "category":"Professional",
            "subcategory":"Art Services",
            "type":"Services"
        }
    ],
    "sg:phone":"+61 2 9705 2552",
    "sg:postcode":"2047",
    "sg:province":"NSW",
    "sg:tags":[
        "graphic",
        "designer"
    ],
    "wof:name":"Blueberry Creative",
    "wof:placetype":"venue"
},
  "geometry": {"coordinates":[151.14627100000001,-33.856171],"type":"Point"}
}