{
  "type": "Feature",
  "properties": {
    "addr:full":"124 McIlwraith Ave Norman Park QLD 4170",
    "addr:housenumber":"124",
    "addr:postcode":"4170",
    "addr:street":"Mcilwraith Ave",
    "iso:country":"AU",
    "sg:address":"124 McIlwraith Ave",
    "sg:city":"Norman Park",
    "sg:classifiers":[
        {
            "category":"Health Services",
            "subcategory":"Doctor",
            "type":"Services"
        }
    ],
    "sg:phone":"+61 7 3831 9999",
    "sg:postcode":"4170",
    "sg:province":"QLD",
    "sg:tags":[
        "medical",
        "practitioner"
    ],
    "wof:name":"Norman Park Group Practice",
    "wof:placetype":"venue"
},
  "geometry": {"coordinates":[153.07066345199999,-27.4849872589],"type":"Point"}
}