{
  "type": "Feature",
  "properties": {
    "addr:full":"267 Forrest St Kalgoorlie WA 6430",
    "addr:housenumber":"267",
    "addr:postcode":"6430",
    "addr:street":"Forrest St",
    "iso:country":"AU",
    "sg:address":"267 Forrest St",
    "sg:city":"Kalgoorlie",
    "sg:classifiers":[
        {
            "category":"Home & Garden",
            "subcategory":"Building Materials",
            "type":"Retail Goods"
        }
    ],
    "sg:phone":"+61 8 9021 5899",
    "sg:postcode":"6430",
    "sg:province":"WA",
    "sg:tags":[
        "secondhand"
    ],
    "wof:name":"Kalgoorlie Salvage & Demolition",
    "wof:placetype":"venue"
},
  "geometry": {"coordinates":[121.46405792199999,-30.7496623993],"type":"Point"}
}