{
  "type": "Feature",
  "properties": {
    "addr:full":"24 Aquarium Ave Hemmant QLD 4174",
    "addr:postcode":"4174",
    "addr:street":"Aquarium Ave",
    "iso:country":"AU",
    "sg:address":"24 Aquarium Ave",
    "sg:city":"Hemmant",
    "sg:classifiers":[
        {
            "category":"Retail",
            "subcategory":"Funeral Services",
            "type":"Services"
        }
    ],
    "sg:phone":"+61 7 3390 4122",
    "sg:postcode":"4174",
    "sg:province":"QLD",
    "sg:tags":[
        "director"
    ],
    "wof:name":"Queensland Funerals",
    "wof:placetype":"venue"
},
  "geometry": {"coordinates":[153.12597656200001,-27.4438896179],"type":"Point"}
}