{
  "type": "Feature",
  "properties": {
    "iso:country":"AU",
    "sg:address":"12/ 120 Edward St",
    "sg:city":"Brisbane",
    "sg:classifiers":[
        {
            "category":"Wholesale",
            "subcategory":"Medical Equipment & Supplies",
            "type":"Manufacturing & Wholesale Goods"
        }
    ],
    "sg:phone":"+61 7 3211 2086",
    "sg:postcode":"4000",
    "sg:province":"QLD",
    "sg:tags":[
        "dental"
    ],
    "wof:name":"Dental Medical Technologies International Pty Ltd",
    "wof:placetype":"venue"
},
  "geometry": {"coordinates":[153.02850341800001,-27.4700927734],"type":"Point"}
}