{
  "type": "Feature",
  "properties": {
    "addr:full":"36 Rae St Colac VIC 3250",
    "addr:housenumber":"36",
    "addr:postcode":"3250",
    "addr:street":"Rae St",
    "iso:country":"AU",
    "sg:address":"36 Rae St",
    "sg:city":"Colac",
    "sg:classifiers":[
        {
            "category":"Health Services",
            "subcategory":"Health Practitioner",
            "type":"Services"
        }
    ],
    "sg:phone":"+61 3 5232 1696",
    "sg:postcode":"3250",
    "sg:province":"VIC",
    "sg:tags":[
        "naturopath"
    ],
    "wof:name":"Capon D C",
    "wof:placetype":"venue"
},
  "geometry": {"coordinates":[143.583832,-38.340687],"type":"Point"}
}