{
  "type": "Feature",
  "properties": {
    "addr:full":"7/ 30 Currumbin Ck Rd Currumbin QLD 4223",
    "addr:housenumber":"/ 30",
    "addr:postcode":"4223",
    "addr:street":"Currumbin Ck Rd",
    "iso:country":"AU",
    "sg:address":"7/ 30 Currumbin Ck Rd",
    "sg:city":"Currumbin",
    "sg:classifiers":[
        {
            "category":"Wholesale",
            "subcategory":"Farm Supplies",
            "type":"Manufacturing & Wholesale Goods"
        }
    ],
    "sg:phone":"+61 7 5559 5984",
    "sg:postcode":"4223",
    "sg:province":"QLD",
    "sg:tags":[
        "feed",
        "supplement",
        "stock"
    ],
    "wof:name":"Creek Stockfeeds",
    "wof:placetype":"venue"
},
  "geometry": {"coordinates":[153.47276306099999,-28.1420288086],"type":"Point"}
}