{
  "type": "Feature",
  "properties": {
    "iso:country":"AU",
    "sg:address":"97 Main St",
    "sg:city":"Gembrook",
    "sg:classifiers":[
        {
            "category":"Cafe",
            "type":"Food & Drink"
        }
    ],
    "sg:phone":"+61 3 5968 1715",
    "sg:postcode":"3783",
    "sg:province":"VIC",
    "wof:name":"Charlottes Of Gembrook",
    "wof:placetype":"venue"
},
  "geometry": {"coordinates":[145.55261200000001,-37.952881],"type":"Point"}
}