{
  "type": "Feature",
  "properties": {
    "addr:full":"16 Eynham Rd Milperra NSW 2214",
    "addr:housenumber":"16",
    "addr:postcode":"2214",
    "addr:street":"Eynham Rd",
    "iso:country":"AU",
    "sg:address":"16 Eynham Rd",
    "sg:city":"Milperra",
    "sg:classifiers":[
        {
            "category":"Professional",
            "subcategory":"Detective & Security Services",
            "type":"Services"
        }
    ],
    "sg:phone":"+61 2 9792 2288",
    "sg:postcode":"2214",
    "sg:province":"NSW",
    "sg:tags":[
        "consultant",
        "system"
    ],
    "wof:name":"Castile Security",
    "wof:placetype":"venue"
},
  "geometry": {"coordinates":[150.98135400000001,-33.940578],"type":"Point"}
}