{
  "type": "Feature",
  "properties": {
    "addr:full":"151 Victoria Pde East Melbourne VIC 3002",
    "addr:housenumber":"151",
    "addr:postcode":"3002",
    "addr:street":"Victoria Pde",
    "iso:country":"AU",
    "sg:address":"151 Victoria Pde",
    "sg:city":"East Melbourne",
    "sg:classifiers":[
        {
            "category":"Retail",
            "subcategory":"Auto Repair",
            "type":"Services"
        }
    ],
    "sg:phone":"+61 3 9416 1123",
    "sg:postcode":"3002",
    "sg:province":"VIC",
    "sg:tags":[
        "repairer",
        "motor",
        "engineer"
    ],
    "wof:name":"UltraTune",
    "wof:placetype":"venue"
},
  "geometry": {"coordinates":[144.97976684599999,-37.8083229065],"type":"Point"}
}