{
  "type": "Feature",
  "properties": {
    "addr:full":"33 Delgarno Rd Bonnyrigg NSW 2177",
    "addr:housenumber":"33",
    "addr:postcode":"2177",
    "addr:street":"Delgarno Rd",
    "iso:country":"AU",
    "sg:address":"33 Delgarno Rd",
    "sg:city":"Bonnyrigg",
    "sg:classifiers":[
        {
            "category":"Building & Trades",
            "subcategory":"Construction",
            "type":"Services"
        }
    ],
    "sg:phone":"+61 2 9823 9349",
    "sg:postcode":"2177",
    "sg:province":"NSW",
    "sg:tags":[
        "waterproofing",
        "contractor"
    ],
    "wof:name":"Arid Waterproofing",
    "wof:placetype":"venue"
},
  "geometry": {"coordinates":[150.875274658,-33.8950042725],"type":"Point"}
}