{
  "type": "Feature",
  "properties": {
    "iso:country":"AU",
    "sg:address":"832 Nepean Hwy",
    "sg:city":"Mornington",
    "sg:classifiers":[
        {
            "category":"Government",
            "subcategory":"Fire Station",
            "type":"Public Place"
        }
    ],
    "sg:phone":"+61 3 5975 4293",
    "sg:postcode":"3931",
    "sg:province":"VIC",
    "sg:tags":[
        "brick",
        "mfrs",
        "repairer"
    ],
    "wof:name":"McAllister R E",
    "wof:placetype":"venue"
},
  "geometry": {"coordinates":[145.03652954099999,-38.2403106689],"type":"Point"}
}