{
  "type": "Feature",
  "properties": {
    "addr:full":"Cnr Spencer & Warton Rds Huntingdale WA 6110",
    "addr:postcode":"6110",
    "addr:street":"Cnr",
    "iso:country":"AU",
    "sg:address":"Cnr Spencer & Warton Rds",
    "sg:city":"Huntingdale",
    "sg:classifiers":[
        {
            "category":"Health Services",
            "subcategory":"Dentist",
            "type":"Services"
        }
    ],
    "sg:phone":"+61 8 9493 1400",
    "sg:postcode":"6110",
    "sg:province":"WA",
    "wof:name":"Moody C",
    "wof:placetype":"venue"
},
  "geometry": {"coordinates":[115.959640503,-32.0765151978],"type":"Point"}
}