{
  "type": "Feature",
  "properties": {
    "iso:country":"AU",
    "sg:address":"Unit 1/ 12 Hayden Crt",
    "sg:city":"Myaree",
    "sg:classifiers":[
        {
            "category":"Wholesale",
            "subcategory":"Apparel",
            "type":"Manufacturing & Wholesale Goods"
        }
    ],
    "sg:phone":"+61 8 9330 5588",
    "sg:postcode":"6154",
    "sg:province":"WA",
    "sg:tags":[
        "wholesaler",
        "mfrs",
        "uniform"
    ],
    "wof:name":"Nell Gray Manufacturing",
    "wof:placetype":"venue"
},
  "geometry": {"coordinates":[115.817459,-32.044582],"type":"Point"}
}