{
  "type": "Feature",
  "properties": {
    "addr:full":"36 York St Sydney NSW 2000",
    "addr:housenumber":"36",
    "addr:postcode":"2000",
    "addr:street":"York St",
    "iso:country":"AU",
    "sg:address":"36 York St",
    "sg:city":"Sydney",
    "sg:classifiers":[
        {
            "category":"Health Services",
            "subcategory":"Doctor",
            "type":"Services"
        }
    ],
    "sg:phone":"+61 2 9262 2866",
    "sg:postcode":"2000",
    "sg:province":"NSW",
    "sg:tags":[
        "medical",
        "practitioner"
    ],
    "wof:name":"Thomas Maxwell",
    "wof:placetype":"venue"
},
  "geometry": {"coordinates":[151.20625305199999,-33.8689880371],"type":"Point"}
}