{
  "type": "Feature",
  "properties": {
    "iso:country":"AU",
    "sg:address":"Shop 2, Alawa Village Alawa Crs",
    "sg:city":"Alawa",
    "sg:classifiers":[
        {
            "category":"Food & Beverages",
            "subcategory":"Bakery",
            "type":"Retail Goods"
        }
    ],
    "sg:phone":"+61 8 8948 4088",
    "sg:postcode":"0810",
    "sg:province":"NT",
    "sg:tags":[
        "cake",
        "shop",
        "pastry"
    ],
    "wof:name":"Dimitrios Speciality Cakes",
    "wof:placetype":"venue"
},
  "geometry": {"coordinates":[130.87542724599999,-12.3819999695],"type":"Point"}
}