{
  "type": "Feature",
  "properties": {
    "iso:country":"AU",
    "sg:address":"2791 Newell Hwy",
    "sg:city":"Parkes",
    "sg:classifiers":[
        {
            "category":"Communications",
            "type":"Services"
        }
    ],
    "sg:phone":"+61 2 6862 5197",
    "sg:postcode":"2870",
    "sg:province":"NSW",
    "sg:tags":[
        "equipment",
        "radio"
    ],
    "wof:name":"Dave's Electronics",
    "wof:placetype":"venue"
},
  "geometry": {"coordinates":[148.169785,-33.141533],"type":"Point"}
}