{
  "type": "Feature",
  "properties": {
    "addr:full":"U7/ 55 Newton Rd Wetherill Park NSW 2164",
    "addr:housenumber":"55",
    "addr:postcode":"2164",
    "addr:street":"U7 /;Newton Rd",
    "iso:country":"AU",
    "sg:address":"U7/ 55 Newton Rd",
    "sg:city":"Wetherill Park",
    "sg:classifiers":[
        {
            "category":"Recreation",
            "subcategory":"Fishing",
            "type":"Entertainment"
        }
    ],
    "sg:phone":"+61 2 9756 6977",
    "sg:postcode":"2164",
    "sg:province":"NSW",
    "sg:tags":[
        "tackle"
    ],
    "wof:name":"Twin Peaks Leisure",
    "wof:placetype":"venue"
},
  "geometry": {"coordinates":[150.88536071799999,-33.8449516296],"type":"Point"}
}