{
  "type": "Feature",
  "properties": {
    "iso:country":"AU",
    "sg:address":"Waterworth Drv",
    "sg:city":"Mt Annan",
    "sg:classifiers":[
        {
            "category":"Fast Food",
            "type":"Food & Drink"
        }
    ],
    "sg:phone":"+61 2 4647 1222",
    "sg:postcode":"2567",
    "sg:province":"NSW",
    "sg:tags":[
        "away",
        "take"
    ],
    "wof:name":"McDonald's Family Restaurants",
    "wof:placetype":"venue"
},
  "geometry": {"coordinates":[150.76046752900001,-34.0505065918],"type":"Point"}
}