{
  "type": "Feature",
  "properties": {
    "addr:full":"494 Blackburn Rd Mt Waverley VIC 3149",
    "addr:housenumber":"494",
    "addr:postcode":"3149",
    "addr:street":"Blackburn Rd",
    "iso:country":"AU",
    "sg:address":"494 Blackburn Rd",
    "sg:city":"Mt Waverley",
    "sg:classifiers":[
        {
            "category":"Building & Trades",
            "subcategory":"Landscaping Services",
            "type":"Services"
        }
    ],
    "sg:phone":"+61 419 352 700",
    "sg:postcode":"3149",
    "sg:province":"VIC",
    "sg:tags":[
        "gardener"
    ],
    "wof:name":"Morrells Maintenance & Gardening Service",
    "wof:placetype":"venue"
},
  "geometry": {"coordinates":[145.14447021500001,-37.8936805725],"type":"Point"}
}