{
  "type": "Feature",
  "properties": {
    "addr:full":"Shop 47 518 Bunnerong Rd Matraville NSW 2036",
    "addr:housenumber":"shop 47",
    "addr:postcode":"518;2036",
    "addr:street":"Bunnerong Rd",
    "iso:country":"AU",
    "sg:address":"Shop 47 518 Bunnerong Rd",
    "sg:city":"Matraville",
    "sg:classifiers":[
        {
            "category":"Building & Trades",
            "subcategory":"Construction",
            "type":"Services"
        }
    ],
    "sg:phone":"+61 2 9311 2845",
    "sg:postcode":"2036",
    "sg:province":"NSW",
    "sg:tags":[
        "repair",
        "maintenance",
        "contractor"
    ],
    "wof:name":"Stevens O&#039;Neill & Associates (Developments) Pty Ltd",
    "wof:placetype":"venue"
},
  "geometry": {"coordinates":[151.23118591299999,-33.958782196],"type":"Point"}
}