{
  "type": "Feature",
  "properties": {
    "iso:country":"AU",
    "sg:address":"Level 2, 245 Pacific Hwy",
    "sg:city":"North Sydney",
    "sg:classifiers":[
        {
            "category":"Banks & Credit Unions",
            "subcategory":"Bureau De Change",
            "type":"Services"
        }
    ],
    "sg:phone":"+61 2 9959 5099",
    "sg:postcode":"2060",
    "sg:province":"NSW",
    "sg:tags":[
        "planning",
        "family"
    ],
    "wof:name":"Mediguide Family Planning",
    "wof:placetype":"venue"
},
  "geometry": {"coordinates":[151.20518493599999,-33.8346366882],"type":"Point"}
}