{
  "type": "Feature",
  "properties": {
    "iso:country":"AU",
    "sg:address":"South Coolum Rd",
    "sg:city":"Coolum Beach",
    "sg:classifiers":[
        {
            "category":"Home & Garden",
            "subcategory":"Garden Supply",
            "type":"Retail Goods"
        }
    ],
    "sg:phone":"+61 7 5446 4144",
    "sg:postcode":"4573",
    "sg:province":"QLD",
    "sg:tags":[
        "landscape"
    ],
    "wof:name":"Coolum Sand & Gravel",
    "wof:placetype":"venue"
},
  "geometry": {"coordinates":[153.078217,-26.536676],"type":"Point"}
}