{
  "type": "Feature",
  "properties": {
    "iso:country":"AU",
    "sg:address":"15 Stirling St",
    "sg:city":"Thebarton",
    "sg:classifiers":[
        {
            "category":"Home & Garden",
            "subcategory":"Carpets & Floor Coverings",
            "type":"Retail Goods"
        }
    ],
    "sg:phone":"+61 8 8352 4700",
    "sg:postcode":"5031",
    "sg:province":"SA",
    "sg:website":"http://www.carpetburners.com.au",
    "wof:name":"Carpet Burners",
    "wof:placetype":"venue"
},
  "geometry": {"coordinates":[138.572341919,-34.9125671387],"type":"Point"}
}