{
  "type": "Feature",
  "properties": {
    "iso:country":"AU",
    "sg:address":"88 Buckett Pl",
    "sg:city":"Kurrajong",
    "sg:classifiers":[
        {
            "category":"Building & Trades",
            "subcategory":"Construction",
            "type":"Services"
        }
    ],
    "sg:phone":"+61 2 4573 2261",
    "sg:postcode":"2758",
    "sg:province":"NSW",
    "sg:tags":[
        "earth",
        "excavating",
        "moving",
        "contractor"
    ],
    "wof:name":"Gill C H & L M",
    "wof:placetype":"venue"
},
  "geometry": {"coordinates":[150.660690308,-33.5556335449],"type":"Point"}
}