{
  "type": "Feature",
  "properties": {
    "iso:country":"AU",
    "sg:address":"29 Arthur St",
    "sg:city":"Prospect",
    "sg:classifiers":[
        {
            "category":"Education",
            "subcategory":"School",
            "type":"Public Place"
        }
    ],
    "sg:phone":"+61 8 8344 4604",
    "sg:postcode":"5082",
    "sg:province":"SA",
    "sg:tags":[
        "state",
        "except",
        "nsw"
    ],
    "wof:name":"Blair Athol Primary",
    "wof:placetype":"venue"
},
  "geometry": {"coordinates":[138.59602355999999,-34.874622345],"type":"Point"}
}