{
  "type": "Feature",
  "properties": {
    "iso:country":"AU",
    "sg:address":"165 Argyle St",
    "sg:city":"Traralgon",
    "sg:classifiers":[
        {
            "category":"Professional",
            "subcategory":"Detective & Security Services",
            "type":"Services"
        }
    ],
    "sg:phone":"+61 1300 361 281",
    "sg:postcode":"3844",
    "sg:province":"VIC",
    "sg:tags":[
        "consultant",
        "system"
    ],
    "wof:name":"Five Star Security",
    "wof:placetype":"venue"
},
  "geometry": {"coordinates":[146.55770874000001,-38.191696167],"type":"Point"}
}