{
  "type": "Feature",
  "properties": {
    "iso:country":"AU",
    "sg:address":"Rose St",
    "sg:city":"Daisy Hill",
    "sg:classifiers":[
        {
            "category":"Arena",
            "subcategory":"Sports Club",
            "type":"Entertainment"
        }
    ],
    "sg:phone":"+61 7 3290 0908",
    "sg:postcode":"4127",
    "sg:province":"QLD",
    "sg:tags":[
        "league",
        "rugby"
    ],
    "wof:name":"Slacks Creek RLFC Inc",
    "wof:placetype":"venue"
},
  "geometry": {"coordinates":[153.15626525900001,-27.6434669495],"type":"Point"}
}