{
  "type": "Feature",
  "properties": {
    "iso:country":"AU",
    "sg:address":"Merewether St",
    "sg:city":"Newcastle",
    "sg:classifiers":[
        {
            "category":"Building & Trades",
            "subcategory":"Landscaping Services",
            "type":"Services"
        }
    ],
    "sg:phone":"+61 2 4926 2133",
    "sg:postcode":"2300",
    "sg:province":"NSW",
    "sg:tags":[
        "market"
    ],
    "wof:name":"Honeysuckle Markets",
    "wof:placetype":"venue"
},
  "geometry": {"coordinates":[151.772964,-32.926704],"type":"Point"}
}