{
  "type": "Feature",
  "properties": {
    "addr:full":"40A Brookman St Kalgoorlie WA 6430",
    "addr:housenumber":"40a",
    "addr:postcode":"6430",
    "addr:street":"Brookman St",
    "iso:country":"AU",
    "sg:address":"40A Brookman St",
    "sg:city":"Kalgoorlie",
    "sg:classifiers":[
        {
            "category":"Real Estate",
            "subcategory":"Real Estate Agent",
            "type":"Services"
        }
    ],
    "sg:phone":"+61 8 9022 2155",
    "sg:postcode":"6430",
    "sg:province":"WA",
    "wof:name":"Goldfields Realty",
    "wof:placetype":"venue"
},
  "geometry": {"coordinates":[121.469017029,-30.7489471436],"type":"Point"}
}