{
  "type": "Feature",
  "properties": {
    "addr:full":"Unit 4 237 Main Rd McLaren Vale SA 5171",
    "addr:housenumber":"237",
    "addr:postcode":"5171",
    "addr:street":"Main Rd",
    "iso:country":"AU",
    "sg:address":"Unit 4 237 Main Rd",
    "sg:city":"McLaren Vale",
    "sg:classifiers":[
        {
            "category":"Farming",
            "subcategory":"Vineyard",
            "type":"Manufacturing & Wholesale Goods"
        }
    ],
    "sg:phone":"+61 8 8323 9935",
    "sg:postcode":"5171",
    "sg:province":"SA",
    "sg:tags":[
        "winery"
    ],
    "wof:name":"Boston Recruitment",
    "wof:placetype":"venue"
},
  "geometry": {"coordinates":[138.53028869600001,-35.2098083496],"type":"Point"}
}