{
  "type": "Feature",
  "properties": {
    "iso:country":"AU",
    "sg:address":"8 Redgate Rd",
    "sg:city":"South Golden Beach",
    "sg:classifiers":[
        {
            "category":"Health Services",
            "subcategory":"Health Practitioner",
            "type":"Services"
        }
    ],
    "sg:phone":"+61 2 6680 1456",
    "sg:postcode":"2483",
    "sg:province":"NSW",
    "sg:tags":[
        "acupuncture"
    ],
    "wof:name":"Walsh, Jacqueline",
    "wof:placetype":"venue"
},
  "geometry": {"coordinates":[153.548706055,-28.4977741241],"type":"Point"}
}