{
  "type": "Feature",
  "properties": {
    "addr:full":"1 Radovick St Korumburra VIC 3950",
    "addr:housenumber":"1",
    "addr:postcode":"3950",
    "addr:street":"Radovick St",
    "iso:country":"AU",
    "sg:address":"1 Radovick St",
    "sg:city":"Korumburra",
    "sg:classifiers":[
        {
            "category":"Personal",
            "subcategory":"Beauty Salon",
            "type":"Services"
        }
    ],
    "sg:phone":"+61 3 5655 1193",
    "sg:postcode":"3950",
    "sg:province":"VIC",
    "sg:tags":[
        "hairdresser"
    ],
    "wof:name":"J & M's Hairpoint",
    "wof:placetype":"venue"
},
  "geometry": {"coordinates":[145.82281494099999,-38.4323501587],"type":"Point"}
}