{
  "type": "Feature",
  "properties": {
    "iso:country":"AU",
    "sg:address":"9 Canberra St",
    "sg:city":"Charlestown",
    "sg:classifiers":[
        {
            "category":"Health Services",
            "subcategory":"Doctor",
            "type":"Services"
        }
    ],
    "sg:phone":"+61 2 4942 1211",
    "sg:postcode":"2290",
    "sg:province":"NSW",
    "sg:tags":[
        "medical",
        "practitioner"
    ],
    "wof:name":"Bowler Michael D",
    "wof:placetype":"venue"
},
  "geometry": {"coordinates":[151.69215393100001,-32.963634491],"type":"Point"}
}