{
  "type": "Feature",
  "properties": {
    "iso:country":"AU",
    "sg:address":"7 / 16 Milne Ave",
    "sg:city":"Seaford",
    "sg:classifiers":[
        {
            "category":"Home & Garden",
            "subcategory":"Building Materials",
            "type":"Retail Goods"
        }
    ],
    "sg:phone":"+61 3 9773 6835",
    "sg:postcode":"3198",
    "sg:province":"VIC",
    "sg:tags":[
        "fitting",
        "door"
    ],
    "sg:website":"http://www.lotusdoors.com.au",
    "wof:name":"Lotus Folding Walls & Doors Pty Ltd",
    "wof:placetype":"venue"
},
  "geometry": {"coordinates":[145.132522583,-38.1190681458],"type":"Point"}
}