{
  "type": "Feature",
  "properties": {
    "addr:full":"Commercial Centre, Suite 19 St Peters Pl Isle Of Capri QLD 4217",
    "addr:postcode":"4217",
    "addr:street":"Peters Pl",
    "iso:country":"AU",
    "sg:address":"Commercial Centre, Suite 19 St Peters Pl",
    "sg:city":"Isle Of Capri",
    "sg:classifiers":[
        {
            "category":"Health Services",
            "subcategory":"Dentist",
            "type":"Services"
        }
    ],
    "sg:phone":"+61 7 5531 7259",
    "sg:postcode":"4217",
    "sg:province":"QLD",
    "wof:name":"Wallace Ian",
    "wof:placetype":"venue"
},
  "geometry": {"coordinates":[153.42379760700001,-28.0114707947],"type":"Point"}
}