{
  "type": "Feature",
  "properties": {
    "addr:full":"29 Canberra St Hemmant QLD 4174",
    "addr:housenumber":"29",
    "addr:postcode":"4174",
    "addr:street":"Canberra St",
    "iso:country":"AU",
    "sg:address":"29 Canberra St",
    "sg:city":"Hemmant",
    "sg:classifiers":[
        {
            "category":"Wholesale",
            "subcategory":"Construction Materials",
            "type":"Manufacturing & Wholesale Goods"
        }
    ],
    "sg:phone":"+61 7 3890 0522",
    "sg:postcode":"4174",
    "sg:province":"QLD",
    "sg:tags":[
        "lift"
    ],
    "wof:name":"Liftronic Pty Limited",
    "wof:placetype":"venue"
},
  "geometry": {"coordinates":[153.129150391,-27.4442996979],"type":"Point"}
}