{
  "type": "Feature",
  "properties": {
    "iso:country":"AU",
    "sg:address":"80 Premier Drv",
    "sg:city":"Campbellfield",
    "sg:classifiers":[
        {
            "category":"Wholesale",
            "subcategory":"Drugs",
            "type":"Manufacturing & Wholesale Goods"
        }
    ],
    "sg:phone":"+61 3 9357 8173",
    "sg:postcode":"3061",
    "sg:province":"VIC",
    "sg:tags":[
        "wholesaler",
        "pharmaceutical",
        "product",
        "mfrs"
    ],
    "wof:name":"Chemita Pty Ltd",
    "wof:placetype":"venue"
},
  "geometry": {"coordinates":[144.96499633799999,-37.659122467],"type":"Point"}
}