{
  "type": "Feature",
  "properties": {
    "iso:country":"AU",
    "sg:address":"PO Box 165",
    "sg:city":"Wooroloo",
    "sg:classifiers":[
        {
            "category":"Building & Trades",
            "subcategory":"Construction",
            "type":"Services"
        }
    ],
    "sg:phone":"+61 417 032 280",
    "sg:postcode":"6558",
    "sg:province":"WA",
    "sg:tags":[
        "welding"
    ],
    "wof:name":"G M J Contracting",
    "wof:placetype":"venue"
},
  "geometry": {"coordinates":[116.326332092,-31.8085308075],"type":"Point"}
}