{
  "type": "Feature",
  "properties": {
    "iso:country":"AU",
    "sg:address":"1- 5 Union Rd",
    "sg:city":"Ascot Vale",
    "sg:classifiers":[
        {
            "category":"Professional",
            "subcategory":"Printing & Photocopies",
            "type":"Services"
        }
    ],
    "sg:phone":"+61 3 9370 8440",
    "sg:postcode":"3032",
    "sg:province":"VIC",
    "sg:tags":[
        "trophy"
    ],
    "wof:name":"Ascot Vale Sports & Trophies",
    "wof:placetype":"venue"
},
  "geometry": {"coordinates":[144.914703,-37.780163],"type":"Point"}
}