{
  "type": "Feature",
  "properties": {
    "addr:full":"61 Magellan St Lismore NSW 2480",
    "addr:housenumber":"61",
    "addr:postcode":"2480",
    "addr:street":"Magellan St",
    "iso:country":"AU",
    "sg:address":"61 Magellan St",
    "sg:city":"Lismore",
    "sg:classifiers":[
        {
            "category":"Arts & Performance",
            "subcategory":"Music",
            "type":"Entertainment"
        }
    ],
    "sg:phone":"+61 2 6622 4756",
    "sg:postcode":"2480",
    "sg:province":"NSW",
    "sg:tags":[
        "hi-fi",
        "equipment"
    ],
    "wof:name":"Audio Room",
    "wof:placetype":"venue"
},
  "geometry": {"coordinates":[153.277267456,-28.8096485138],"type":"Point"}
}