{
  "type": "Feature",
  "properties": {
    "addr:full":"12 Blackwood St East Ipswich QLD 4305",
    "addr:housenumber":"12",
    "addr:postcode":"4305",
    "addr:street":"Blackwood St East",
    "iso:country":"AU",
    "sg:address":"12 Blackwood St",
    "sg:city":"East Ipswich",
    "sg:classifiers":[
        {
            "category":"Education",
            "subcategory":"School",
            "type":"Public Place"
        }
    ],
    "sg:phone":"+61 7 3432 6316",
    "sg:postcode":"4305",
    "sg:province":"QLD",
    "sg:tags":[
        "state",
        "except",
        "nsw"
    ],
    "wof:name":"Ipswich East Preschool",
    "wof:placetype":"venue"
},
  "geometry": {"coordinates":[152.77822875999999,-27.6059036255],"type":"Point"}
}