{
  "type": "Feature",
  "properties": {
    "addr:full":"Lot 1813 Makagon Rd Berrimah NT 0828",
    "addr:housenumber":"1813",
    "addr:postcode":"nt 0828",
    "addr:street":"Makagon Rd",
    "iso:country":"AU",
    "sg:address":"Lot 1813 Makagon Rd",
    "sg:city":"Berrimah",
    "sg:classifiers":[
        {
            "category":"Manufacturing",
            "subcategory":"Metals",
            "type":"Manufacturing & Wholesale Goods"
        }
    ],
    "sg:phone":"+61 8 8984 4771",
    "sg:postcode":"0828",
    "sg:province":"NT",
    "sg:tags":[
        "steel",
        "fabricator",
        "mfrs"
    ],
    "wof:name":"Ornasteel Pty Ltd",
    "wof:placetype":"venue"
},
  "geometry": {"coordinates":[130.927368164,-12.4419603348],"type":"Point"}
}