{
  "type": "Feature",
  "properties": {
    "iso:country":"AU",
    "sg:address":"Corner of Penny's Lane & Kings Cross Road",
    "sg:city":"Kings Cross",
    "sg:classifiers":[
        {
            "category":"Restaurant",
            "type":"Food & Drink"
        }
    ],
    "sg:phone":"+61 2 9356 8177",
    "sg:postcode":"2011",
    "sg:province":"NSW",
    "wof:name":"Penny's Lane Restaurant",
    "wof:placetype":"venue"
},
  "geometry": {"coordinates":[151.222045898,-33.8754234314],"type":"Point"}
}