{
  "type": "Feature",
  "properties": {
    "iso:country":"AU",
    "sg:address":"Cnr Cooyong & Mona Vale Rds",
    "sg:city":"Terrey Hills",
    "sg:classifiers":[
        {
            "category":"Building & Trades",
            "subcategory":"Landscaping Services",
            "type":"Services"
        }
    ],
    "sg:phone":"+61 2 9486 3151",
    "sg:postcode":"2084",
    "sg:province":"NSW",
    "sg:tags":[
        "designer",
        "landscape",
        "contractor"
    ],
    "wof:name":"Bonds Nursery Landscaping Centre",
    "wof:placetype":"venue"
},
  "geometry": {"coordinates":[151.22744750999999,-33.6864204407],"type":"Point"}
}