{
  "type": "Feature",
  "properties": {
    "addr:full":"25 Veronica St Northcote VIC 3070",
    "addr:housenumber":"25",
    "addr:postcode":"3070",
    "addr:street":"Veronica St",
    "iso:country":"AU",
    "sg:address":"25 Veronica St",
    "sg:city":"Northcote",
    "sg:classifiers":[
        {
            "category":"Social Services",
            "subcategory":"Retirement Home",
            "type":"Services"
        }
    ],
    "sg:phone":"+61 3 9482 6655",
    "sg:postcode":"3070",
    "sg:province":"VIC",
    "sg:tags":[
        "village"
    ],
    "wof:name":"Aveo Veronica Gardens",
    "wof:placetype":"venue"
},
  "geometry": {"coordinates":[144.98666399999999,-37.761433],"type":"Point"}
}