{
  "type": "Feature",
  "properties": {
    "iso:country":"AU",
    "sg:address":"RMB 2014 Indigo Creek Road Barnawartha",
    "sg:city":"Indigo Valley",
    "sg:classifiers":[
        {
            "category":"Education",
            "subcategory":"School",
            "type":"Public Place"
        }
    ],
    "sg:phone":"+61 2 6026 9235",
    "sg:postcode":"3688",
    "sg:province":"VIC",
    "sg:tags":[
        "state",
        "-",
        "nsw"
    ],
    "wof:name":"Middle Indigo Primary School",
    "wof:placetype":"venue"
},
  "geometry": {"coordinates":[146.70962524399999,-36.1448860168],"type":"Point"}
}