{
  "type": "Feature",
  "properties": {
    "addr:full":"Shp 17/ 20 Marshall St Dapto NSW 2530",
    "addr:housenumber":"17 / 20",
    "addr:postcode":"2530",
    "addr:street":"Marshall St",
    "iso:country":"AU",
    "sg:address":"Shp 17/ 20 Marshall St",
    "sg:city":"Dapto",
    "sg:classifiers":[
        {
            "category":"Cafe",
            "type":"Food & Drink"
        }
    ],
    "sg:phone":"+61 2 4261 1111",
    "sg:postcode":"2530",
    "sg:province":"NSW",
    "wof:name":"Backstreet Cafe & Catering",
    "wof:placetype":"venue"
},
  "geometry": {"coordinates":[150.791549683,-34.4956817627],"type":"Point"}
}