{
  "type": "Feature",
  "properties": {
    "addr:full":"524 Malvern Rd Hawksburn VIC 3142",
    "addr:housenumber":"524",
    "addr:postcode":"3142",
    "addr:street":"Malvern Rd",
    "iso:country":"AU",
    "sg:address":"524 Malvern Rd",
    "sg:city":"Hawksburn",
    "sg:classifiers":[
        {
            "category":"Shopping",
            "subcategory":"Baby Store",
            "type":"Retail Goods"
        }
    ],
    "sg:phone":"+61 3 9533 7576",
    "sg:postcode":"3142",
    "sg:province":"VIC",
    "sg:tags":[
        "children's",
        "wear"
    ],
    "wof:name":"AK Home Children & Textiles",
    "wof:placetype":"venue"
},
  "geometry": {"coordinates":[145.003982544,-37.8483123779],"type":"Point"}
}