{
  "type": "Feature",
  "properties": {
    "addr:full":"14 Toolara St Boreen Point QLD 4565",
    "addr:housenumber":"14",
    "addr:postcode":"4565",
    "addr:street":"Toolara St",
    "iso:country":"AU",
    "sg:address":"14 Toolara St",
    "sg:city":"Boreen Point",
    "sg:classifiers":[
        {
            "category":"Shopping",
            "subcategory":"Computers & Home Electronics",
            "type":"Retail Goods"
        }
    ],
    "sg:phone":"+61 7 5485 3555",
    "sg:postcode":"4565",
    "sg:province":"QLD",
    "sg:tags":[
        "equipment",
        "multimedia"
    ],
    "wof:name":"Anim8 Productions",
    "wof:placetype":"venue"
},
  "geometry": {"coordinates":[152.99478149399999,-26.2836952209],"type":"Point"}
}