{
  "type": "Feature",
  "properties": {
    "iso:country":"AU",
    "sg:address":"78 Turf St",
    "sg:city":"Grafton",
    "sg:classifiers":[
        {
            "category":"Building & Trades",
            "subcategory":"Construction",
            "type":"Services"
        }
    ],
    "sg:phone":"+61 2 6642 6905",
    "sg:postcode":"2460",
    "sg:province":"NSW",
    "sg:tags":[
        "builder",
        "designer",
        "room",
        "cool"
    ],
    "wof:name":"Ian Williamson",
    "wof:placetype":"venue"
},
  "geometry": {"coordinates":[152.929077148,-29.6805858612],"type":"Point"}
}