{
  "type": "Feature",
  "properties": {
    "addr:full":"321 Bay St Brighton VIC 3186",
    "addr:housenumber":"321",
    "addr:postcode":"3186",
    "addr:street":"Bay St",
    "iso:country":"AU",
    "sg:address":"321 Bay St",
    "sg:city":"Brighton",
    "sg:classifiers":[
        {
            "category":"Health Services",
            "subcategory":"Dentist",
            "type":"Services"
        }
    ],
    "sg:phone":"+61 3 9596 3379",
    "sg:postcode":"3186",
    "sg:province":"VIC",
    "wof:name":"Love S Dr",
    "wof:placetype":"venue"
},
  "geometry": {"coordinates":[145.00315856899999,-37.9054718018],"type":"Point"}
}