{
  "type": "Feature",
  "properties": {
    "addr:full":"2- 6 Caroline Springs Blv Caroline Springs VIC 3023",
    "addr:housenumber":"6",
    "addr:postcode":"3023",
    "addr:street":"Caroline Springs Blv",
    "iso:country":"AU",
    "sg:address":"2- 6",
    "sg:city":"Caroline Springs Blv Caroline Springs",
    "sg:classifiers":[
        {
            "category":"Health Services",
            "subcategory":"Health Practitioner",
            "type":"Services"
        }
    ],
    "sg:phone":"+61 3 8361 7237",
    "sg:postcode":"3023",
    "sg:province":"VIC",
    "sg:tags":[
        "physiotherapist"
    ],
    "wof:name":"Caroline Springs Physiotherapy",
    "wof:placetype":"venue"
},
  "geometry": {"coordinates":[144.73994400000001,-37.755428],"type":"Point"}
}