{
  "type": "Feature",
  "properties": {
    "iso:country":"AU",
    "sg:address":"23 Tusmore Ave",
    "sg:city":"Leabrook",
    "sg:classifiers":[
        {
            "category":"Home & Garden",
            "subcategory":"Kitchen Supply",
            "type":"Retail Goods"
        }
    ],
    "sg:phone":"+61 8 8431 3199",
    "sg:postcode":"5068",
    "sg:province":"SA",
    "sg:tags":[
        "traffic",
        "equipment",
        "safety",
        "road"
    ],
    "wof:name":"Adelaide Convex Mirrors",
    "wof:placetype":"venue"
},
  "geometry": {"coordinates":[138.65109252900001,-34.9287109375],"type":"Point"}
}