{
  "type": "Feature",
  "properties": {
    "iso:country":"AU",
    "sg:address":"43 Aberdare St",
    "sg:city":"Darra",
    "sg:classifiers":[
        {
            "category":"Health Services",
            "subcategory":"Health Practitioner",
            "type":"Services"
        }
    ],
    "sg:phone":"+61 7 3375 7877",
    "sg:postcode":"4076",
    "sg:province":"QLD",
    "sg:tags":[
        "herbalist"
    ],
    "wof:name":"Health Care Naturally",
    "wof:placetype":"venue"
},
  "geometry": {"coordinates":[152.96090698200001,-27.5573711395],"type":"Point"}
}