{
  "type": "Feature",
  "properties": {
    "addr:full":"10 Sunderland St Moonah TAS 7009",
    "addr:housenumber":"10",
    "addr:postcode":"7009",
    "addr:street":"Sunderland St",
    "iso:country":"AU",
    "sg:address":"10 Sunderland St",
    "sg:city":"Moonah",
    "sg:classifiers":[
        {
            "category":"Wholesale",
            "subcategory":"Machinery & Supplies",
            "type":"Manufacturing & Wholesale Goods"
        }
    ],
    "sg:phone":"+61 3 6228 6253",
    "sg:postcode":"7009",
    "sg:province":"TAS",
    "sg:tags":[
        "engineer"
    ],
    "wof:name":"Industrial Transmission & Engineering Supplies",
    "wof:placetype":"venue"
},
  "geometry": {"coordinates":[147.29592895499999,-42.8447952271],"type":"Point"}
}