{
  "type": "Feature",
  "properties": {
    "addr:full":"14 Maryland St Stanthorpe QLD 4380",
    "addr:housenumber":"14",
    "addr:postcode":"4380",
    "addr:street":"Maryland St",
    "iso:country":"AU",
    "sg:address":"14 Maryland St",
    "sg:city":"Stanthorpe",
    "sg:classifiers":[
        {
            "category":"Government",
            "subcategory":"Post Office",
            "type":"Public Place"
        }
    ],
    "sg:phone":"+61 13 13 18",
    "sg:postcode":"4380",
    "sg:province":"QLD",
    "sg:tags":[
        "postal"
    ],
    "wof:name":"Australia Post",
    "wof:placetype":"venue"
},
  "geometry": {"coordinates":[151.93374600000001,-28.655563],"type":"Point"}
}