{
  "type": "Feature",
  "properties": {
    "addr:full":"155 Fergusson Rd Brighton TAS 7030",
    "addr:housenumber":"155",
    "addr:postcode":"7030",
    "addr:street":"Fergusson Rd",
    "iso:country":"AU",
    "sg:address":"155 Fergusson Rd",
    "sg:city":"Brighton",
    "sg:classifiers":[
        {
            "category":"Professional",
            "subcategory":"Business Services",
            "type":"Services"
        }
    ],
    "sg:phone":"+61 3 6268 0063",
    "sg:postcode":"7030",
    "sg:province":"TAS",
    "sg:tags":[
        "drafting"
    ],
    "wof:name":"Duo Design",
    "wof:placetype":"venue"
},
  "geometry": {"coordinates":[147.221725464,-42.68775177],"type":"Point"}
}