{
  "type": "Feature",
  "properties": {
    "addr:full":"3 Carey La Southport QLD 4215",
    "addr:housenumber":"3",
    "addr:postcode":"4215",
    "addr:street":"Carey La",
    "iso:country":"AU",
    "sg:address":"3 Carey La",
    "sg:city":"Southport",
    "sg:classifiers":[
        {
            "category":"Social Services",
            "subcategory":"Child Care",
            "type":"Services"
        }
    ],
    "sg:phone":"+61 7 5531 3019",
    "sg:postcode":"4215",
    "sg:province":"QLD",
    "wof:name":"Trinity Child Care Centre",
    "wof:placetype":"venue"
},
  "geometry": {"coordinates":[153.40602111800001,-27.9713287354],"type":"Point"}
}