{
  "type": "Feature",
  "properties": {
    "addr:full":"David St Renmark SA 5341",
    "addr:postcode":"5341",
    "addr:street":"David St",
    "iso:country":"AU",
    "sg:address":"David St",
    "sg:city":"Renmark",
    "sg:classifiers":[
        {
            "category":"Farming",
            "subcategory":"Berry Farm",
            "type":"Manufacturing & Wholesale Goods"
        }
    ],
    "sg:phone":"+61 8 8595 3330",
    "sg:postcode":"5341",
    "sg:province":"SA",
    "sg:tags":[
        "fruit",
        "grower"
    ],
    "wof:name":"Strachan R J & J A",
    "wof:placetype":"venue"
},
  "geometry": {"coordinates":[140.74313354500001,-34.1406517029],"type":"Point"}
}