{
  "type": "Feature",
  "properties": {
    "addr:full":"Monier Rd Rockhampton QLD 4700",
    "addr:postcode":"4700",
    "addr:street":"Monier Rd",
    "iso:country":"AU",
    "sg:address":"Monier Rd",
    "sg:city":"Rockhampton",
    "sg:classifiers":[
        {
            "category":"Military Area",
            "subcategory":"Air Force Base",
            "type":"Public Place"
        }
    ],
    "sg:phone":"+61 7 4936 1233",
    "sg:postcode":"4700",
    "sg:province":"QLD",
    "sg:tags":[
        "pole",
        "lighting",
        "power"
    ],
    "wof:name":"Rocla",
    "wof:placetype":"venue"
},
  "geometry": {"coordinates":[150.506713867,-23.3185920715],"type":"Point"}
}