{
  "type": "Feature",
  "properties": {
    "addr:full":"748 Waverley Rd Malvern East VIC 3145",
    "addr:housenumber":"748",
    "addr:postcode":"3145",
    "addr:street":"Waverley Rd",
    "iso:country":"AU",
    "sg:address":"748 Waverley Rd",
    "sg:city":"Malvern East",
    "sg:classifiers":[
        {
            "category":"Building & Trades",
            "subcategory":"Construction",
            "type":"Services"
        }
    ],
    "sg:phone":"+61 3 9569 4566",
    "sg:postcode":"3145",
    "sg:province":"VIC",
    "sg:tags":[
        "contractor"
    ],
    "wof:name":"Hardran Industries Pty Ltd",
    "wof:placetype":"venue"
},
  "geometry": {"coordinates":[145.09016418499999,-37.8800468445],"type":"Point"}
}