{
  "type": "Feature",
  "properties": {
    "addr:full":"270 Maroondah Hwy Ringwood VIC 3134",
    "addr:housenumber":"270",
    "addr:postcode":"3134",
    "addr:street":"Maroondah Hwy",
    "iso:country":"AU",
    "sg:address":"270 Maroondah Hwy",
    "sg:city":"Ringwood",
    "sg:classifiers":[
        {
            "category":"Social Services",
            "subcategory":"Child Care",
            "type":"Services"
        }
    ],
    "sg:phone":"+61 3 9727 2235",
    "sg:postcode":"3134",
    "sg:province":"VIC",
    "wof:name":"Platypus Junction",
    "wof:placetype":"venue"
},
  "geometry": {"coordinates":[145.237915039,-37.8109970093],"type":"Point"}
}