{
  "type": "Feature",
  "properties": {
    "addr:full":"Shop 4/ 41 Hall Drv Menai NSW 2234",
    "addr:housenumber":"shop 4 / 41",
    "addr:postcode":"2234",
    "addr:street":"Hall Drv",
    "iso:country":"AU",
    "sg:address":"Shop 4/ 41 Hall Drv",
    "sg:city":"Menai",
    "sg:classifiers":[
        {
            "category":"Sports & Exercise",
            "subcategory":"Gym",
            "type":"Entertainment"
        }
    ],
    "sg:phone":"+61 2 9541 4325",
    "sg:postcode":"2234",
    "sg:province":"NSW",
    "sg:tags":[
        "health",
        "fitness"
    ],
    "wof:name":"Healing Matters",
    "wof:placetype":"venue"
},
  "geometry": {"coordinates":[151.00526428200001,-34.012840271],"type":"Point"}
}