{
  "type": "Feature",
  "properties": {
    "addr:full":"103 Teatree Ave Leeton NSW 2705",
    "addr:housenumber":"103",
    "addr:postcode":"2705",
    "addr:street":"Teatree Ave",
    "iso:country":"AU",
    "sg:address":"103 Teatree Ave",
    "sg:city":"Leeton",
    "sg:classifiers":[
        {
            "category":"Retail",
            "subcategory":"Auto Repair",
            "type":"Services"
        }
    ],
    "sg:phone":"+61 2 6953 6393",
    "sg:postcode":"2705",
    "sg:province":"NSW",
    "sg:tags":[
        "repairer",
        "motor",
        "engineer"
    ],
    "wof:name":"Millemaggi Mechanical",
    "wof:placetype":"venue"
},
  "geometry": {"coordinates":[146.39796447800001,-34.5498390198],"type":"Point"}
}