{
  "type": "Feature",
  "properties": {
    "iso:country":"AU",
    "sg:address":"Albert La",
    "sg:city":"Mittagong",
    "sg:classifiers":[
        {
            "category":"Retail",
            "subcategory":"Self-service Laundry",
            "type":"Services"
        }
    ],
    "sg:phone":"+61 2 4871 3406",
    "sg:postcode":"2575",
    "sg:province":"NSW",
    "wof:name":"DW's Laundrette",
    "wof:placetype":"venue"
},
  "geometry": {"coordinates":[150.447387695,-34.449634552],"type":"Point"}
}