{
  "type": "Feature",
  "properties": {
    "iso:country":"AU",
    "sg:address":"2 Violet St",
    "sg:city":"Miami",
    "sg:classifiers":[
        {
            "category":"Professional",
            "subcategory":"Computer Services",
            "type":"Services"
        }
    ],
    "sg:phone":"+61 7 5535 5545",
    "sg:postcode":"4220",
    "sg:province":"QLD",
    "sg:tags":[
        "technical",
        "support"
    ],
    "wof:name":"BRS Computing Services",
    "wof:placetype":"venue"
},
  "geometry": {"coordinates":[153.433135986,-28.0709209442],"type":"Point"}
}