{
  "type": "Feature",
  "properties": {
    "iso:country":"AU",
    "sg:address":"299 Elizabeth Drv",
    "sg:city":"Sunbury",
    "sg:classifiers":[
        {
            "category":"Professional",
            "subcategory":"Art Services",
            "type":"Services"
        }
    ],
    "sg:phone":"+61 3 9740 8338",
    "sg:postcode":"3429",
    "sg:province":"VIC",
    "sg:tags":[
        "decorator",
        "painter"
    ],
    "wof:name":"Index Painting & Decorating",
    "wof:placetype":"venue"
},
  "geometry": {"coordinates":[144.72491455100001,-37.5677490234],"type":"Point"}
}