{
  "type": "Feature",
  "properties": {
    "addr:full":"7 Verdehlo Drv The Vines WA 6069",
    "addr:housenumber":"7",
    "addr:postcode":"6069",
    "addr:street":"Verdehlo Drv",
    "iso:country":"AU",
    "sg:address":"7 Verdehlo Drv",
    "sg:city":"The Vines",
    "sg:classifiers":[
        {
            "category":"Real Estate",
            "subcategory":"Developer",
            "type":"Services"
        }
    ],
    "sg:phone":"+61 8 9297 4166",
    "sg:postcode":"6069",
    "sg:province":"WA",
    "sg:tags":[
        "development"
    ],
    "wof:name":"Pavilion Circle Land Sales",
    "wof:placetype":"venue"
},
  "geometry": {"coordinates":[116.006080627,-31.7661933899],"type":"Point"}
}