{
  "type": "Feature",
  "properties": {
    "addr:full":"Newell Hwy Peak Hill NSW 2869",
    "addr:postcode":"2869",
    "addr:street":"Newell Hwy",
    "iso:country":"AU",
    "sg:address":"Newell Hwy",
    "sg:city":"Peak Hill",
    "sg:classifiers":[
        {
            "category":"Wholesale",
            "subcategory":"Farm Supplies",
            "type":"Manufacturing & Wholesale Goods"
        }
    ],
    "sg:phone":"+61 2 6869 1700",
    "sg:postcode":"2869",
    "sg:province":"NSW",
    "sg:tags":[
        "equipment"
    ],
    "wof:name":"Peak Hill Industries Pty Ltd",
    "wof:placetype":"venue"
},
  "geometry": {"coordinates":[148.191162109,-32.724609375],"type":"Point"}
}