{
  "type": "Feature",
  "properties": {
    "addr:full":"35- 45 Lithgow St Abbotsford VIC 3067",
    "addr:housenumber":"45",
    "addr:postcode":"3067",
    "addr:street":"Lithgow St",
    "iso:country":"AU",
    "sg:address":"35- 45 Lithgow St",
    "sg:city":"Abbotsford",
    "sg:classifiers":[
        {
            "category":"Professional",
            "subcategory":"Business Services",
            "type":"Services"
        }
    ],
    "sg:phone":"+61 3 9421 2800",
    "sg:postcode":"3067",
    "sg:province":"VIC",
    "sg:tags":[
        "record",
        "management",
        "storage"
    ],
    "wof:name":"Speedscan Pty Ltd",
    "wof:placetype":"venue"
},
  "geometry": {"coordinates":[144.99848938,-37.8084220886],"type":"Point"}
}