{
  "type": "Feature",
  "properties": {
    "addr:full":"7A Campbell St Balmain NSW 2041",
    "addr:housenumber":"7a",
    "addr:postcode":"2041",
    "addr:street":"Campbell St",
    "iso:country":"AU",
    "sg:address":"7A Campbell St",
    "sg:city":"Balmain",
    "sg:classifiers":[
        {
            "category":"Education",
            "subcategory":"Special Training",
            "type":"Public Place"
        }
    ],
    "sg:phone":"+61 2 9960 2885",
    "sg:postcode":"2041",
    "sg:province":"NSW",
    "sg:tags":[
        "school",
        "art"
    ],
    "wof:name":"Balmain Art School",
    "wof:placetype":"venue"
},
  "geometry": {"coordinates":[151.184753,-33.857189],"type":"Point"}
}