{
  "type": "Feature",
  "properties": {
    "addr:full":"Centenary Marketplace McLaughlin Rd Centenary Park QLD 4869",
    "addr:postcode":"4869",
    "addr:street":"Mclaughlin Rd Centenary",
    "iso:country":"AU",
    "sg:address":"Centenary Marketplace McLaughlin Rd",
    "sg:city":"Centenary Park",
    "sg:classifiers":[
        {
            "category":"Fast Food",
            "type":"Food & Drink"
        }
    ],
    "sg:phone":"+61 7 4055 5944",
    "sg:postcode":"4869",
    "sg:province":"QLD",
    "sg:tags":[
        "away",
        "take"
    ],
    "wof:name":"China Bowl Chinese Take Away",
    "wof:placetype":"venue"
},
  "geometry": {"coordinates":[145.736938477,-17.0120258331],"type":"Point"}
}