{
  "type": "Feature",
  "properties": {
    "addr:full":"PO Box 141 West Melbourne VIC 3003",
    "addr:postcode":"3003",
    "iso:country":"AU",
    "sg:address":"PO Box 141",
    "sg:city":"West Melbourne",
    "sg:classifiers":[
        {
            "category":"Professional",
            "subcategory":"Computer Services",
            "type":"Services"
        }
    ],
    "sg:phone":"+61 1800 241 993",
    "sg:postcode":"3003",
    "sg:province":"VIC",
    "sg:tags":[
        "training"
    ],
    "wof:name":"Computer Gym",
    "wof:placetype":"venue"
},
  "geometry": {"coordinates":[144.93093872099999,-37.8105697632],"type":"Point"}
}