{
  "type": "Feature",
  "properties": {
    "addr:full":"148- 150 Imlay St Eden NSW 2551",
    "addr:housenumber":"150",
    "addr:postcode":"2551",
    "addr:street":"Imlay St",
    "iso:country":"AU",
    "sg:address":"148- 150 Imlay St",
    "sg:city":"Eden",
    "sg:classifiers":[
        {
            "category":"Shopping",
            "subcategory":"Clothing, Apparel, & Fashions",
            "type":"Retail Goods"
        }
    ],
    "sg:phone":"+61 2 6496 1748",
    "sg:postcode":"2551",
    "sg:province":"NSW",
    "sg:tags":[
        "menswear"
    ],
    "wof:name":"Mark Anthonys Clothing Company",
    "wof:placetype":"venue"
},
  "geometry": {"coordinates":[149.91136169399999,-37.0729064941],"type":"Point"}
}