{
  "type": "Feature",
  "properties": {
    "addr:full":"663 Chapel St South Yarra VIC 3141",
    "addr:housenumber":"663",
    "addr:postcode":"3141",
    "addr:street":"Chapel St",
    "iso:country":"AU",
    "sg:address":"663 Chapel St",
    "sg:city":"South Yarra",
    "sg:classifiers":[
        {
            "category":"Wholesale",
            "subcategory":"Photographic Equipment",
            "type":"Manufacturing & Wholesale Goods"
        }
    ],
    "sg:phone":"+61 3 9823 1555",
    "sg:postcode":"3141",
    "sg:province":"VIC",
    "sg:tags":[
        "wholesaler",
        "mfrs",
        "supply"
    ],
    "wof:name":"Kennedy C R & Co. Pty Ltd",
    "wof:placetype":"venue"
},
  "geometry": {"coordinates":[144.99606323200001,-37.8364295959],"type":"Point"}
}