{
  "type": "Feature",
  "properties": {
    "addr:full":"Alexa Rd North Haven SA 5018",
    "addr:postcode":"5018",
    "addr:street":"Alexa Rd",
    "iso:country":"AU",
    "sg:address":"Alexa Rd",
    "sg:city":"North Haven",
    "sg:classifiers":[
        {
            "category":"Professional",
            "subcategory":"Engineering",
            "type":"Services"
        }
    ],
    "sg:phone":"+61 8 8341 8505",
    "sg:postcode":"5018",
    "sg:province":"SA",
    "sg:tags":[
        "diesel",
        "engineer"
    ],
    "wof:name":"YANMAR",
    "wof:placetype":"venue"
},
  "geometry": {"coordinates":[138.48965454099999,-34.7858085632],"type":"Point"}
}