{
  "type": "Feature",
  "properties": {
    "addr:full":"57 Rosa St Oatley NSW 2223",
    "addr:housenumber":"57",
    "addr:postcode":"2223",
    "addr:street":"Rosa St",
    "iso:country":"AU",
    "sg:address":"57 Rosa St",
    "sg:city":"Oatley",
    "sg:classifiers":[
        {
            "category":"Education",
            "subcategory":"Kindergarten",
            "type":"Public Place"
        }
    ],
    "sg:phone":"+61 2 9580 3004",
    "sg:postcode":"2223",
    "sg:province":"NSW",
    "sg:tags":[
        "pre-schools"
    ],
    "wof:name":"Arndu St Pauls Pre-School",
    "wof:placetype":"venue"
},
  "geometry": {"coordinates":[151.082565308,-33.9843254089],"type":"Point"}
}