{
  "type": "Feature",
  "properties": {
    "addr:full":"18 Belfast St Henley Beach SA 5022",
    "addr:housenumber":"18",
    "addr:postcode":"5022",
    "addr:street":"Belfast St",
    "iso:country":"AU",
    "sg:address":"18 Belfast St",
    "sg:city":"Henley Beach",
    "sg:classifiers":[
        {
            "category":"Wholesale",
            "subcategory":"Photographic Equipment",
            "type":"Manufacturing & Wholesale Goods"
        }
    ],
    "sg:phone":"+61 8 8355 2069",
    "sg:postcode":"5022",
    "sg:province":"SA",
    "sg:tags":[
        "wholesaler",
        "mfrs",
        "supply"
    ],
    "wof:name":"Archival Products Aust. P/L",
    "wof:placetype":"venue"
},
  "geometry": {"coordinates":[138.50395202600001,-34.908618927],"type":"Point"}
}