{
  "type": "Feature",
  "properties": {
    "addr:full":"Beach Rd Shoreham VIC 3916",
    "addr:postcode":"3916",
    "addr:street":"Beach Rd",
    "iso:country":"AU",
    "sg:address":"Beach Rd",
    "sg:city":"Shoreham",
    "sg:classifiers":[
        {
            "category":"Real Estate",
            "subcategory":"Architect",
            "type":"Services"
        }
    ],
    "sg:phone":"+61 3 5989 8284",
    "sg:postcode":"3916",
    "sg:province":"VIC",
    "wof:name":"Padey R E",
    "wof:placetype":"venue"
},
  "geometry": {"coordinates":[145.04374694800001,-38.4339675903],"type":"Point"}
}