{
  "type": "Feature",
  "properties": {
    "addr:full":"3 Cathedral St Bridgeman Downs QLD 4035",
    "addr:housenumber":"3",
    "addr:postcode":"4035",
    "addr:street":"Cathedral St",
    "iso:country":"AU",
    "sg:address":"3 Cathedral St",
    "sg:city":"Bridgeman Downs",
    "sg:classifiers":[
        {
            "category":"Professional",
            "subcategory":"Management & Consulting",
            "type":"Services"
        }
    ],
    "sg:phone":"+61 7 3263 1764",
    "sg:postcode":"4035",
    "sg:province":"QLD",
    "sg:tags":[
        "consultant",
        "educational"
    ],
    "wof:name":"Pirozzo Consultancy Services",
    "wof:placetype":"venue"
},
  "geometry": {"coordinates":[153.00341800000001,-27.347124],"type":"Point"}
}