{
  "type": "Feature",
  "properties": {
    "iso:country":"AU",
    "sg:address":"Level 3 126 Wellington Pde",
    "sg:city":"East Melbourne",
    "sg:classifiers":[
        {
            "category":"Professional",
            "subcategory":"Research",
            "type":"Services"
        }
    ],
    "sg:phone":"+61 3 9416 4100",
    "sg:postcode":"3002",
    "sg:province":"VIC",
    "sg:tags":[
        "market"
    ],
    "wof:name":"Newspoll Market Research",
    "wof:placetype":"venue"
},
  "geometry": {"coordinates":[144.98558044399999,-37.8162307739],"type":"Point"}
}