{
  "type": "Feature",
  "properties": {
    "iso:country":"AU",
    "sg:address":"1/ 760 Brunswick St",
    "sg:city":"New Farm",
    "sg:classifiers":[
        {
            "category":"Shopping",
            "subcategory":"Jewelry",
            "type":"Retail Goods"
        }
    ],
    "sg:phone":"+61 7 3358 6388",
    "sg:postcode":"4005",
    "sg:province":"QLD",
    "sg:tags":[
        "jeweller"
    ],
    "wof:name":"Ari Jewellery",
    "wof:placetype":"venue"
},
  "geometry": {"coordinates":[153.04393005399999,-27.4652729034],"type":"Point"}
}