{
  "type": "Feature",
  "properties": {
    "iso:country":"AU",
    "sg:address":"465 Plummer St",
    "sg:city":"Port Melbourne",
    "sg:classifiers":[
        {
            "category":"Utilities",
            "subcategory":"Refuse",
            "type":"Services"
        }
    ],
    "sg:phone":"+61 3 9676 3666",
    "sg:postcode":"3207",
    "sg:province":"VIC",
    "sg:tags":[
        "disposal",
        "reduction",
        "waste"
    ],
    "wof:name":"Cleanaway Technical Services",
    "wof:placetype":"venue"
},
  "geometry": {"coordinates":[144.929123,-37.831745],"type":"Point"}
}