{
  "type": "Feature",
  "properties": {
    "iso:country":"AU",
    "sg:address":"2/ 25 Isabel St",
    "sg:city":"Toowoomba",
    "sg:classifiers":[
        {
            "category":"Health Services",
            "subcategory":"Doctor",
            "type":"Services"
        }
    ],
    "sg:phone":"+61 7 4638 5711",
    "sg:postcode":"4350",
    "sg:province":"QLD",
    "sg:tags":[
        "medical",
        "practitioner"
    ],
    "wof:name":"McGuiness B R Dr",
    "wof:placetype":"venue"
},
  "geometry": {"coordinates":[151.94688400000001,-27.55905],"type":"Point"}
}