{
  "type": "Feature",
  "properties": {
    "addr:full":"71 Arthur St Roma QLD 4455",
    "addr:housenumber":"71",
    "addr:postcode":"4455",
    "addr:street":"Arthur St",
    "iso:country":"AU",
    "sg:address":"71 Arthur St",
    "sg:city":"Roma",
    "sg:classifiers":[
        {
            "category":"Organizations",
            "subcategory":"Membership Organization",
            "type":"Services"
        }
    ],
    "sg:phone":"+61 7 4622 1416",
    "sg:postcode":"4455",
    "sg:province":"QLD",
    "sg:tags":[
        "railway"
    ],
    "wof:name":"Maranoa Travel Centre",
    "wof:placetype":"venue"
},
  "geometry": {"coordinates":[148.78944397000001,-26.5718402863],"type":"Point"}
}