{
  "type": "Feature",
  "properties": {
    "addr:full":"5 Bertram St Mortlake NSW 2137",
    "addr:housenumber":"5",
    "addr:postcode":"2137",
    "addr:street":"Bertram St",
    "iso:country":"AU",
    "sg:address":"5 Bertram St",
    "sg:city":"Mortlake",
    "sg:classifiers":[
        {
            "category":"Retail",
            "subcategory":"Event Space",
            "type":"Services"
        }
    ],
    "sg:phone":"+61 2 9736 3634",
    "sg:postcode":"2137",
    "sg:province":"NSW",
    "sg:tags":[
        "venue",
        "reception",
        "wedding"
    ],
    "wof:name":"A Seivadis Charters",
    "wof:placetype":"venue"
},
  "geometry": {"coordinates":[151.10707092300001,-33.8432693481],"type":"Point"}
}