{
  "type": "Feature",
  "properties": {
    "addr:full":"34 Murray St Vincentia NSW 2540",
    "addr:housenumber":"34",
    "addr:postcode":"2540",
    "addr:street":"Murray St",
    "iso:country":"AU",
    "sg:address":"34 Murray St",
    "sg:city":"Vincentia",
    "sg:classifiers":[
        {
            "category":"Social Services",
            "type":"Services"
        }
    ],
    "sg:phone":"+61 2 4441 8928",
    "sg:postcode":"2540",
    "sg:province":"NSW",
    "sg:tags":[
        "disabled",
        "person",
        "equipment"
    ],
    "wof:name":"SCSN Supplies",
    "wof:placetype":"venue"
},
  "geometry": {"coordinates":[150.59800720199999,-35.0906333923],"type":"Point"}
}