{
  "type": "Feature",
  "properties": {
    "addr:full":"U1/ 62 Chapman St Proserpine QLD 4800",
    "addr:housenumber":"62",
    "addr:postcode":"4800",
    "addr:street":"U1 /;Chapman St",
    "iso:country":"AU",
    "sg:address":"U1/ 62 Chapman St",
    "sg:city":"Proserpine",
    "sg:classifiers":[
        {
            "category":"Professional",
            "subcategory":"Accounting & Tax Preparation",
            "type":"Services"
        }
    ],
    "sg:phone":"+61 7 4945 4400",
    "sg:postcode":"4800",
    "sg:province":"QLD",
    "sg:tags":[
        "bookkeeping"
    ],
    "wof:name":"Flynn & Porter",
    "wof:placetype":"venue"
},
  "geometry": {"coordinates":[148.582565308,-20.405828476],"type":"Point"}
}