{
  "type": "Feature",
  "properties": {
    "addr:full":"4372 Golden Hwy Denman NSW 2328",
    "addr:housenumber":"4372",
    "addr:postcode":"2328",
    "addr:street":"Golden Hwy",
    "iso:country":"AU",
    "sg:address":"4372 Golden Hwy",
    "sg:city":"Denman",
    "sg:classifiers":[
        {
            "category":"Autos & Motor Vehicles",
            "subcategory":"Automobile Sales",
            "type":"Retail Goods"
        }
    ],
    "sg:phone":"+61 2 6547 2029",
    "sg:postcode":"2328",
    "sg:province":"NSW",
    "sg:tags":[
        "equipment",
        "trailer"
    ],
    "wof:name":"NKW Trailers & Metal Fabrications",
    "wof:placetype":"venue"
},
  "geometry": {"coordinates":[150.69195556599999,-32.3755989075],"type":"Point"}
}