{
  "type": "Feature",
  "properties": {
    "addr:full":"1 Port Beach Rd North Fremantle WA 6159",
    "addr:housenumber":"1",
    "addr:postcode":"6159",
    "addr:street":"Port Beach Rd",
    "iso:country":"AU",
    "sg:address":"1 Port Beach Rd",
    "sg:city":"North Fremantle",
    "sg:classifiers":[
        {
            "category":"Transit Center",
            "subcategory":"Freight",
            "type":"Transportation"
        }
    ],
    "sg:phone":"+61 8 9434 2387",
    "sg:postcode":"6159",
    "sg:province":"WA",
    "sg:tags":[
        "agent",
        "shipping"
    ],
    "wof:name":"Inchcape Shipping Services",
    "wof:placetype":"venue"
},
  "geometry": {"coordinates":[115.74582700000001,-32.035465],"type":"Point"}
}