{
  "type": "Feature",
  "properties": {
    "addr:full":"14 Magnet Crt Sandy Bay TAS 7005",
    "addr:housenumber":"14",
    "addr:postcode":"7005",
    "addr:street":"Magnet Crt",
    "iso:country":"AU",
    "sg:address":"14 Magnet Crt",
    "sg:city":"Sandy Bay",
    "sg:classifiers":[
        {
            "category":"Travel",
            "subcategory":"Hotels & Motels",
            "type":"Entertainment"
        }
    ],
    "sg:phone":"+61 3 6224 7695",
    "sg:postcode":"7005",
    "sg:province":"TAS",
    "sg:tags":[
        "accommodation"
    ],
    "wof:name":"It's An Island",
    "wof:placetype":"venue"
},
  "geometry": {"coordinates":[147.32777404800001,-42.8947677612],"type":"Point"}
}