{
  "type": "Feature",
  "properties": {
    "addr:full":"7 Northcote St Richmond VIC 3121",
    "addr:housenumber":"7",
    "addr:postcode":"3121",
    "addr:street":"Northcote St",
    "iso:country":"AU",
    "sg:address":"7 Northcote St",
    "sg:city":"Richmond",
    "sg:classifiers":[
        {
            "category":"Education",
            "subcategory":"Special Training",
            "type":"Public Place"
        }
    ],
    "sg:phone":"+61 3 9429 7551",
    "sg:postcode":"3121",
    "sg:province":"VIC",
    "sg:tags":[
        "development"
    ],
    "wof:name":"Linda Wyse & Associates",
    "wof:placetype":"venue"
},
  "geometry": {"coordinates":[144.99754333499999,-37.8297843933],"type":"Point"}
}