{
  "type": "Feature",
  "properties": {
    "addr:full":"Australia Fair Shopping Centre Cnr Scarborough & Y Southport QLD 4215",
    "addr:postcode":"4215",
    "addr:street":"Cnr",
    "iso:country":"AU",
    "sg:address":"Australia Fair Shopping Centre Cnr Scarborough & Y",
    "sg:city":"Southport",
    "sg:classifiers":[
        {
            "category":"Shopping",
            "subcategory":"Clothing, Apparel, & Fashions",
            "type":"Retail Goods"
        }
    ],
    "sg:phone":"+61 7 5591 7166",
    "sg:postcode":"4215",
    "sg:province":"QLD",
    "sg:tags":[
        "uniform"
    ],
    "wof:name":"Complete Kitchenware & Hospitality Supplies",
    "wof:placetype":"venue"
},
  "geometry": {"coordinates":[153.413406372,-27.9661636353],"type":"Point"}
}