{
  "type": "Feature",
  "properties": {
    "addr:full":"608 Canterbury Rd Vermont VIC 3133",
    "addr:housenumber":"608",
    "addr:postcode":"3133",
    "addr:street":"Canterbury Rd",
    "iso:country":"AU",
    "sg:address":"608 Canterbury Rd",
    "sg:city":"Vermont",
    "sg:classifiers":[
        {
            "category":"Food & Beverages",
            "subcategory":"Liquor & Beverages",
            "type":"Retail Goods"
        }
    ],
    "sg:phone":"+61 3 9874 3148",
    "sg:postcode":"3133",
    "sg:province":"VIC",
    "sg:tags":[
        "store"
    ],
    "wof:name":"Vermont Cellars",
    "wof:placetype":"venue"
},
  "geometry": {"coordinates":[145.19515991200001,-37.836391449],"type":"Point"}
}