{
  "type": "Feature",
  "properties": {
    "addr:full":"51 Rosedale Ave Greenacre NSW 2190",
    "addr:housenumber":"51",
    "addr:postcode":"2190",
    "addr:street":"Rosedale Ave",
    "iso:country":"AU",
    "sg:address":"51 Rosedale Ave",
    "sg:city":"Greenacre",
    "sg:classifiers":[
        {
            "category":"Building & Trades",
            "subcategory":"Plumbing",
            "type":"Services"
        }
    ],
    "sg:phone":"+61 2 8700 2666",
    "sg:postcode":"2190",
    "sg:province":"NSW",
    "sg:tags":[
        "plumber",
        "gasfitters"
    ],
    "wof:name":"Coyle F R Pty Ltd",
    "wof:placetype":"venue"
},
  "geometry": {"coordinates":[151.04118299999999,-33.900604],"type":"Point"}
}