{
  "type": "Feature",
  "properties": {
    "addr:full":"22 Macleay St Potts Point NSW 2011",
    "addr:housenumber":"22",
    "addr:postcode":"2011",
    "addr:street":"Macleay St",
    "iso:country":"AU",
    "sg:address":"22 Macleay St",
    "sg:city":"Potts Point",
    "sg:classifiers":[
        {
            "category":"Professional",
            "subcategory":"Art Services",
            "type":"Services"
        }
    ],
    "sg:phone":"+61 2 9331 0100",
    "sg:postcode":"2011",
    "sg:province":"NSW",
    "wof:name":"Martin Browne Fine Art",
    "wof:placetype":"venue"
},
  "geometry": {"coordinates":[151.225708008,-33.8693733215],"type":"Point"}
}