{
  "type": "Feature",
  "properties": {
    "addr:full":"42 Oloway Crs Alexandra Headland QLD 4572",
    "addr:housenumber":"42",
    "addr:postcode":"4572",
    "addr:street":"Oloway Crs",
    "iso:country":"AU",
    "sg:address":"42 Oloway Crs",
    "sg:city":"Alexandra Headland",
    "sg:classifiers":[
        {
            "category":"Building & Trades",
            "subcategory":"Cleaning & Sanitation",
            "type":"Services"
        }
    ],
    "sg:phone":"+61 7 5479 2022",
    "sg:postcode":"4572",
    "sg:province":"QLD",
    "sg:tags":[
        "industrial",
        "commercial",
        "contractor"
    ],
    "wof:name":"Dependon Cleaners",
    "wof:placetype":"venue"
},
  "geometry": {"coordinates":[153.10432399999999,-26.669649],"type":"Point"}
}