{
  "type": "Feature",
  "properties": {
    "addr:full":"PO Box 425 Highfields QLD 4352",
    "addr:postcode":"4352",
    "iso:country":"AU",
    "sg:address":"PO Box 425",
    "sg:city":"Highfields",
    "sg:classifiers":[
        {
            "category":"Utilities",
            "subcategory":"Electric",
            "type":"Services"
        }
    ],
    "sg:phone":"+61 7 4696 9968",
    "sg:postcode":"4352",
    "sg:province":"QLD",
    "sg:tags":[
        "electrical",
        "contractor"
    ],
    "wof:name":"A R Butlin Electrical",
    "wof:placetype":"venue"
},
  "geometry": {"coordinates":[151.95332300000001,-27.464439],"type":"Point"}
}