{
  "type": "Feature",
  "properties": {
    "addr:full":"Lot 103 Sutherland Way Picton WA 6229",
    "addr:housenumber":"103",
    "addr:postcode":"6229",
    "addr:street":"Sutherland Way",
    "iso:country":"AU",
    "sg:address":"Lot 103 Sutherland Way",
    "sg:city":"Picton",
    "sg:classifiers":[
        {
            "category":"Building & Trades",
            "subcategory":"Construction",
            "type":"Services"
        }
    ],
    "sg:phone":"+61 8 9725 6588",
    "sg:postcode":"6229",
    "sg:province":"WA",
    "sg:tags":[
        "concrete",
        "paving"
    ],
    "wof:name":"MGM Concrete",
    "wof:placetype":"venue"
},
  "geometry": {"coordinates":[115.70526099999999,-33.342941],"type":"Point"}
}