{
  "type": "Feature",
  "properties": {
    "iso:country":"AU",
    "sg:address":"12 Hinde St",
    "sg:city":"Southport",
    "sg:classifiers":[
        {
            "category":"Retail",
            "subcategory":"Auto Repair",
            "type":"Services"
        }
    ],
    "sg:phone":"+61 7 5531 2044",
    "sg:postcode":"4215",
    "sg:province":"QLD",
    "sg:tags":[
        "body",
        "motor",
        "trimmer"
    ],
    "wof:name":"Precise Trimming",
    "wof:placetype":"venue"
},
  "geometry": {"coordinates":[153.38804626500001,-27.9790401459],"type":"Point"}
}