{
  "type": "Feature",
  "properties": {
    "iso:country":"AU",
    "sg:address":"13 Monash Ave",
    "sg:city":"Belair",
    "sg:classifiers":[
        {
            "category":"Professional",
            "subcategory":"Engineering",
            "type":"Services"
        }
    ],
    "sg:phone":"+61 8 8278 4597",
    "sg:postcode":"5052",
    "sg:province":"SA",
    "sg:tags":[
        "electronic",
        "engineer"
    ],
    "wof:name":"V.K.N. Electronics",
    "wof:placetype":"venue"
},
  "geometry": {"coordinates":[138.621017,-35.003811],"type":"Point"}
}