{
  "type": "Feature",
  "properties": {
    "addr:full":"49 Lynden St Camberwell VIC 3124",
    "addr:housenumber":"49",
    "addr:postcode":"3124",
    "addr:street":"Lynden St",
    "iso:country":"AU",
    "sg:address":"49 Lynden St",
    "sg:city":"Camberwell",
    "sg:classifiers":[
        {
            "category":"Travel",
            "subcategory":"Hostel",
            "type":"Entertainment"
        }
    ],
    "sg:phone":"+61 3 9889 4807",
    "sg:postcode":"3124",
    "sg:province":"VIC",
    "sg:tags":[
        "home"
    ],
    "wof:name":"Gaffney House Hostel",
    "wof:placetype":"venue"
},
  "geometry": {"coordinates":[145.08616638199999,-37.8415489197],"type":"Point"}
}