{
  "type": "Feature",
  "properties": {
    "addr:full":"2 Jones St Nailsworth SA 5083",
    "addr:housenumber":"2",
    "addr:postcode":"5083",
    "addr:street":"Jones St",
    "iso:country":"AU",
    "sg:address":"2 Jones St",
    "sg:city":"Nailsworth",
    "sg:classifiers":[
        {
            "category":"Retail",
            "subcategory":"Auto Repair",
            "type":"Services"
        }
    ],
    "sg:phone":"+61 8 8269 3166",
    "sg:postcode":"5083",
    "sg:province":"SA",
    "sg:tags":[
        "repairer",
        "motor",
        "engineer"
    ],
    "wof:name":"Northpark Automotive Services",
    "wof:placetype":"venue"
},
  "geometry": {"coordinates":[138.60284423799999,-34.8809013367],"type":"Point"}
}