{
  "type": "Feature",
  "properties": {
    "iso:country":"AU",
    "sg:address":"477 Dorset Rd",
    "sg:city":"Bayswater",
    "sg:classifiers":[
        {
            "category":"Retail",
            "subcategory":"Auto Repair",
            "type":"Services"
        }
    ],
    "sg:phone":"+61 3 9738 1199",
    "sg:postcode":"3153",
    "sg:province":"VIC",
    "sg:tags":[
        "repairer",
        "motor",
        "engineer"
    ],
    "wof:name":"For Serv",
    "wof:placetype":"venue"
},
  "geometry": {"coordinates":[145.28692626899999,-37.8351821899],"type":"Point"}
}