{
  "type": "Feature",
  "properties": {
    "addr:full":"412 Tarean Rd Karuah NSW 2324",
    "addr:housenumber":"412",
    "addr:postcode":"2324",
    "addr:street":"Tarean Rd",
    "iso:country":"AU",
    "sg:address":"412 Tarean Rd",
    "sg:city":"Karuah",
    "sg:classifiers":[
        {
            "category":"Food & Beverages",
            "subcategory":"Bakery",
            "type":"Retail Goods"
        }
    ],
    "sg:phone":"+61 2 4997 5655",
    "sg:postcode":"2324",
    "sg:province":"NSW",
    "sg:tags":[
        "baker"
    ],
    "wof:name":"Maso's Hot Bread Shop",
    "wof:placetype":"venue"
},
  "geometry": {"coordinates":[151.93678283700001,-32.6342315674],"type":"Point"}
}