{
  "type": "Feature",
  "properties": {
    "addr:full":"Main Victor Harbor Rd Pages Flat SA 5172",
    "addr:postcode":"5172",
    "addr:street":"Victor Harbor Rd",
    "iso:country":"AU",
    "sg:address":"Main Victor Harbor Rd",
    "sg:city":"Pages Flat",
    "sg:classifiers":[
        {
            "category":"Professional",
            "subcategory":"Employment Agencies",
            "type":"Services"
        }
    ],
    "sg:phone":"+61 8 8556 1196",
    "sg:postcode":"5172",
    "sg:province":"SA",
    "sg:tags":[
        "entertainer",
        "agent"
    ],
    "wof:name":"Pryers On The Fleurieu",
    "wof:placetype":"venue"
},
  "geometry": {"coordinates":[138.578689575,-35.3176078796],"type":"Point"}
}