{
  "type": "Feature",
  "properties": {
    "addr:full":"14 Boneparte Pl Greenwith SA 5125",
    "addr:housenumber":"14",
    "addr:postcode":"5125",
    "addr:street":"Boneparte Pl",
    "iso:country":"AU",
    "sg:address":"14 Boneparte Pl",
    "sg:city":"Greenwith",
    "sg:classifiers":[
        {
            "category":"Professional",
            "subcategory":"Art Services",
            "type":"Services"
        }
    ],
    "sg:phone":"+61 8 8289 7083",
    "sg:postcode":"5125",
    "sg:province":"SA",
    "sg:tags":[
        "decorator",
        "painter"
    ],
    "wof:name":"Gully Decorators",
    "wof:placetype":"venue"
},
  "geometry": {"coordinates":[138.70773315400001,-34.7645950317],"type":"Point"}
}