{
  "type": "Feature",
  "properties": {
    "iso:country":"AU",
    "sg:address":"Unit 10/ 61 River Rd",
    "sg:city":"Redbank",
    "sg:classifiers":[
        {
            "category":"Professional",
            "subcategory":"Detective & Security Services",
            "type":"Services"
        }
    ],
    "sg:phone":"+61 7 3818 2949",
    "sg:postcode":"4301",
    "sg:province":"QLD",
    "sg:tags":[
        "equipment",
        "window",
        "doors"
    ],
    "wof:name":"A You&#039;re Secure A",
    "wof:placetype":"venue"
},
  "geometry": {"coordinates":[152.86790466299999,-27.5977306366],"type":"Point"}
}