{
  "type": "Feature",
  "properties": {
    "iso:country":"AU",
    "sg:address":"4A Campbell Crs",
    "sg:city":"Terrigal",
    "sg:classifiers":[
        {
            "category":"Real Estate",
            "subcategory":"Real Estate Agent",
            "type":"Services"
        }
    ],
    "sg:phone":"+61 2 4385 8885",
    "sg:postcode":"2260",
    "sg:province":"NSW",
    "wof:name":"Richardson & Wrench",
    "wof:placetype":"venue"
},
  "geometry": {"coordinates":[151.44570899999999,-33.4478],"type":"Point"}
}