{
  "type": "Feature",
  "properties": {
    "addr:full":"251 Central St Labrador QLD 4215",
    "addr:housenumber":"251",
    "addr:postcode":"4215",
    "addr:street":"Central St",
    "iso:country":"AU",
    "sg:address":"251 Central St",
    "sg:city":"Labrador",
    "sg:classifiers":[
        {
            "category":"Fast Food",
            "type":"Food & Drink"
        }
    ],
    "sg:phone":"+61 7 5591 5367",
    "sg:postcode":"4215",
    "sg:province":"QLD",
    "sg:tags":[
        "away",
        "take"
    ],
    "wof:name":"BJ's Snackbar Place",
    "wof:placetype":"venue"
},
  "geometry": {"coordinates":[153.40751648,-27.9492969513],"type":"Point"}
}