{
  "type": "Feature",
  "properties": {
    "iso:country":"AU",
    "sg:address":"24 McLean Rd",
    "sg:city":"Canning Vale",
    "sg:classifiers":[
        {
            "category":"Professional",
            "subcategory":"Engineering",
            "type":"Services"
        }
    ],
    "sg:phone":"+61 8 9256 2688",
    "sg:postcode":"6155",
    "sg:province":"WA",
    "sg:tags":[
        "engineer"
    ],
    "wof:name":"Online Engineering Services Pty Ltd",
    "wof:placetype":"venue"
},
  "geometry": {"coordinates":[115.927773,-32.067348],"type":"Point"}
}