{
  "type": "Feature",
  "properties": {
    "addr:full":"72 Kings Park Rd West Perth WA 6005",
    "addr:housenumber":"72",
    "addr:postcode":"6005",
    "addr:street":"Kings Park Rd",
    "iso:country":"AU",
    "sg:address":"72 Kings Park Rd",
    "sg:city":"West Perth",
    "sg:classifiers":[
        {
            "category":"Banks & Credit Unions",
            "subcategory":"Investment Brokerage",
            "type":"Services"
        }
    ],
    "sg:phone":"+61 428 921 794",
    "sg:postcode":"6005",
    "sg:province":"WA",
    "sg:tags":[
        "finance",
        "broker"
    ],
    "wof:name":"Westside Finance Group Pty Ltd",
    "wof:placetype":"venue"
},
  "geometry": {"coordinates":[115.83403015099999,-31.9504642487],"type":"Point"}
}