{
  "type": "Feature",
  "properties": {
    "iso:country":"AU",
    "sg:address":"Shop 9/157 Crown St",
    "sg:city":"Mall Wollongong",
    "sg:classifiers":[
        {
            "category":"Personal",
            "subcategory":"Beauty Salon",
            "type":"Services"
        }
    ],
    "sg:phone":"+61 2 4226 6860",
    "sg:postcode":"2500",
    "sg:province":"NSW",
    "wof:name":"Carmelitas Beauty",
    "wof:placetype":"venue"
},
  "geometry": {"coordinates":[150.89520300000001,-34.425323],"type":"Point"}
}