{
  "type": "Feature",
  "properties": {
    "iso:country":"AU",
    "sg:address":"14 Williams Ave",
    "sg:city":"Keilor East",
    "sg:classifiers":[
        {
            "category":"Retail",
            "subcategory":"Auto Repair",
            "type":"Services"
        }
    ],
    "sg:phone":"+61 3 9336 4473",
    "sg:postcode":"3033",
    "sg:province":"VIC",
    "sg:tags":[
        "beater",
        "painter",
        "panel"
    ],
    "wof:name":"R.A. Mobile Panels",
    "wof:placetype":"venue"
},
  "geometry": {"coordinates":[144.857437,-37.732185],"type":"Point"}
}