{
  "type": "Feature",
  "properties": {
    "iso:country":"AU",
    "sg:address":"352 Shepherds Hill Rd",
    "sg:city":"Blackwood",
    "sg:classifiers":[
        {
            "category":"Personal",
            "subcategory":"Beauty Salon",
            "type":"Services"
        }
    ],
    "sg:phone":"+61 8 8278 7867",
    "sg:postcode":"5051",
    "sg:province":"SA",
    "wof:name":"Reflection Skin Care centres",
    "wof:placetype":"venue"
},
  "geometry": {"coordinates":[138.615585,-35.021126],"type":"Point"}
}