{
  "type": "Feature",
  "properties": {
    "addr:full":"62 Glenwood Drv Thornton NSW 2322",
    "addr:housenumber":"62",
    "addr:postcode":"2322",
    "addr:street":"Glenwood Drv",
    "iso:country":"AU",
    "sg:address":"62 Glenwood Drv",
    "sg:city":"Thornton",
    "sg:classifiers":[
        {
            "category":"Banks & Credit Unions",
            "subcategory":"Bank",
            "type":"Services"
        }
    ],
    "sg:phone":"+61 2 4966 8866",
    "sg:postcode":"2322",
    "sg:province":"NSW",
    "sg:tags":[
        "concrete",
        "reinforcement"
    ],
    "wof:name":"Neumann Steel",
    "wof:placetype":"venue"
},
  "geometry": {"coordinates":[151.62965393100001,-32.7878036499],"type":"Point"}
}