{
  "type": "Feature",
  "properties": {
    "iso:country":"AU",
    "sg:address":"16 Blackbutt Rd",
    "sg:city":"Port Macquarie",
    "sg:classifiers":[
        {
            "category":"Home & Garden",
            "subcategory":"Building Materials",
            "type":"Retail Goods"
        }
    ],
    "sg:phone":"+61 2 6581 2526",
    "sg:postcode":"2444",
    "sg:province":"NSW",
    "sg:tags":[
        "insulation"
    ],
    "wof:name":"Fast Plast",
    "wof:placetype":"venue"
},
  "geometry": {"coordinates":[152.88826,-31.452457],"type":"Point"}
}