{
  "type": "Feature",
  "properties": {
    "iso:country":"AU",
    "sg:address":"7/155 King William Rd",
    "sg:city":"Hyde Park",
    "sg:classifiers":[
        {
            "category":"Health Services",
            "subcategory":"Optometrist",
            "type":"Services"
        }
    ],
    "sg:phone":"+61 8 8373 5662",
    "sg:postcode":"5061",
    "sg:province":"SA",
    "wof:name":"Hunt Phil",
    "wof:placetype":"venue"
},
  "geometry": {"coordinates":[138.60038757300001,-34.9564590454],"type":"Point"}
}