{
  "type": "Feature",
  "properties": {
    "iso:country":"AU",
    "sg:address":"75 Fifth Ave",
    "sg:city":"Austral",
    "sg:classifiers":[
        {
            "category":"Building & Trades",
            "subcategory":"Construction",
            "type":"Services"
        }
    ],
    "sg:phone":"+61 407 488 878",
    "sg:postcode":"2171",
    "sg:province":"NSW",
    "sg:tags":[
        "earth",
        "excavating",
        "moving",
        "contractor"
    ],
    "wof:name":"On Call Excavations",
    "wof:placetype":"venue"
},
  "geometry": {"coordinates":[150.81471252399999,-33.9480285645],"type":"Point"}
}