{
  "type": "Feature",
  "properties": {
    "iso:country":"AU",
    "sg:address":"49 Faversham Rd",
    "sg:city":"Canterbury",
    "sg:classifiers":[
        {
            "category":"Shopping",
            "subcategory":"Musical Instruments",
            "type":"Retail Goods"
        }
    ],
    "sg:phone":"+61 3 9836 2883",
    "sg:postcode":"3126",
    "sg:province":"VIC",
    "sg:tags":[
        "musician",
        "agent"
    ],
    "wof:name":"Faversham Singers",
    "wof:placetype":"venue"
},
  "geometry": {"coordinates":[145.08479309099999,-37.8193244934],"type":"Point"}
}