{
  "type": "Feature",
  "properties": {
    "addr:full":"84 Mortimer St Mudgee NSW 2850",
    "addr:housenumber":"84",
    "addr:postcode":"2850",
    "addr:street":"Mortimer St",
    "iso:country":"AU",
    "sg:address":"84 Mortimer St",
    "sg:city":"Mudgee",
    "sg:classifiers":[
        {
            "category":"Professional",
            "subcategory":"Employment Agencies",
            "type":"Services"
        }
    ],
    "sg:phone":"+61 2 6372 0577",
    "sg:postcode":"2850",
    "sg:province":"NSW",
    "wof:name":"Country Employment Services Pty Ltd",
    "wof:placetype":"venue"
},
  "geometry": {"coordinates":[149.587616,-32.592869],"type":"Point"}
}