{
  "type": "Feature",
  "properties": {
    "iso:country":"AU",
    "sg:address":"145- 147 Glenlyon Rd",
    "sg:city":"Brunswick",
    "sg:classifiers":[
        {
            "category":"Professional",
            "subcategory":"Art Services",
            "type":"Services"
        }
    ],
    "sg:phone":"+61 3 9380 1344",
    "sg:postcode":"3056",
    "sg:province":"VIC",
    "sg:tags":[
        "picture",
        "frame",
        "framing"
    ],
    "wof:name":"Kastor Australia Pty Ltd",
    "wof:placetype":"venue"
},
  "geometry": {"coordinates":[144.97036743199999,-37.7723503113],"type":"Point"}
}