{
  "type": "Feature",
  "properties": {
    "iso:country":"AU",
    "sg:address":"Factory 12, 8-9 Gabrielle Crt",
    "sg:city":"Bayswater North",
    "sg:classifiers":[
        {
            "category":"Professional",
            "subcategory":"Printing & Photocopies",
            "type":"Services"
        }
    ],
    "sg:phone":"+61 3 9761 6889",
    "sg:postcode":"3153",
    "sg:province":"VIC",
    "sg:tags":[
        "rubber",
        "stamp",
        "metal"
    ],
    "wof:name":"Mail Mart Marketing",
    "wof:placetype":"venue"
},
  "geometry": {"coordinates":[145.28607177699999,-37.8236236572],"type":"Point"}
}