{
  "type": "Feature",
  "properties": {
    "addr:full":"15 Bungama St Deagon QLD 4017",
    "addr:housenumber":"15",
    "addr:postcode":"4017",
    "addr:street":"Bungama St",
    "iso:country":"AU",
    "sg:address":"15 Bungama St",
    "sg:city":"Deagon",
    "sg:classifiers":[
        {
            "category":"Building & Trades",
            "subcategory":"Construction",
            "type":"Services"
        }
    ],
    "sg:phone":"+61 7 3869 1104",
    "sg:postcode":"4017",
    "sg:province":"QLD",
    "sg:tags":[
        "earth",
        "excavating",
        "moving",
        "contractor"
    ],
    "wof:name":"Cameron Harry",
    "wof:placetype":"venue"
},
  "geometry": {"coordinates":[153.06427001899999,-27.328622818],"type":"Point"}
}