{
  "type": "Feature",
  "properties": {
    "addr:full":"15 Cecil Rd Rose Bay NSW 2029",
    "addr:housenumber":"15",
    "addr:postcode":"2029",
    "addr:street":"Cecil Rd",
    "iso:country":"AU",
    "sg:address":"15 Cecil Rd",
    "sg:city":"Rose Bay",
    "sg:classifiers":[
        {
            "category":"Health Services",
            "subcategory":"Doctor",
            "type":"Services"
        }
    ],
    "sg:phone":"+61 2 9337 6201",
    "sg:postcode":"2029",
    "sg:province":"NSW",
    "sg:tags":[
        "medical",
        "practitioner"
    ],
    "wof:name":"Sztolcman Paul",
    "wof:placetype":"venue"
},
  "geometry": {"coordinates":[151.27577209500001,-33.8651542664],"type":"Point"}
}