{
  "type": "Feature",
  "properties": {
    "addr:full":"33 Old Main Rd Bridgewater TAS 7030",
    "addr:housenumber":"33",
    "addr:postcode":"7030",
    "addr:street":"Old Main Rd",
    "iso:country":"AU",
    "sg:address":"33 Old Main Rd",
    "sg:city":"Bridgewater",
    "sg:classifiers":[
        {
            "category":"Autos & Motor Vehicles",
            "subcategory":"Auto Supplies",
            "type":"Retail Goods"
        }
    ],
    "sg:phone":"+61 3 6263 6464",
    "sg:postcode":"7030",
    "sg:province":"TAS",
    "sg:tags":[
        "accessory"
    ],
    "wof:name":"Road Runners Auto Spares Pty Ltd",
    "wof:placetype":"venue"
},
  "geometry": {"coordinates":[147.22869873100001,-42.7355957031],"type":"Point"}
}