{
  "type": "Feature",
  "properties": {
    "iso:country":"AU",
    "sg:address":"477 Stubbs Rd",
    "sg:city":"Forth",
    "sg:classifiers":[
        {
            "category":"Farming",
            "subcategory":"Farm",
            "type":"Manufacturing & Wholesale Goods"
        }
    ],
    "sg:phone":"+61 3 6428 2130",
    "sg:postcode":"7310",
    "sg:province":"TAS",
    "sg:tags":[
        "farmer"
    ],
    "wof:name":"McConnon S L & E A",
    "wof:placetype":"venue"
},
  "geometry": {"coordinates":[146.22947692899999,-41.1937026978],"type":"Point"}
}