{
  "type": "Feature",
  "properties": {
    "addr:full":"1 Edwin St Maryville NSW 2293",
    "addr:housenumber":"1",
    "addr:postcode":"2293",
    "addr:street":"Edwin St",
    "iso:country":"AU",
    "sg:address":"1 Edwin St",
    "sg:city":"Maryville",
    "sg:classifiers":[
        {
            "category":"Home & Garden",
            "subcategory":"Hardware",
            "type":"Retail Goods"
        }
    ],
    "sg:phone":"+61 2 4962 2875",
    "sg:postcode":"2293",
    "sg:province":"NSW",
    "sg:tags":[
        "nut",
        "bolt"
    ],
    "wof:name":"A.B.C. Thread Repair Systems & Helical Inserts (Kross-Threads) Supply Co",
    "wof:placetype":"venue"
},
  "geometry": {"coordinates":[151.755462647,-32.9119567871],"type":"Point"}
}