{
  "type": "Feature",
  "properties": {
    "addr:full":"Unit 2 40 Veronica St Warilla NSW 2528",
    "addr:housenumber":"40",
    "addr:postcode":"2528",
    "addr:street":"Veronica St",
    "iso:country":"AU",
    "sg:address":"Unit 2 40 Veronica St",
    "sg:city":"Warilla",
    "sg:classifiers":[
        {
            "category":"Retail",
            "subcategory":"Auto Repair",
            "type":"Services"
        }
    ],
    "sg:phone":"+61 2 4297 7277",
    "sg:postcode":"2528",
    "sg:province":"NSW",
    "sg:tags":[
        "clutch",
        "brake"
    ],
    "wof:name":"F M Discount Spares & Accessories",
    "wof:placetype":"venue"
},
  "geometry": {"coordinates":[150.86749267600001,-34.5483055115],"type":"Point"}
}