{
  "type": "Feature",
  "properties": {
    "addr:full":"4 Edgar St Port Hedland WA 6721",
    "addr:housenumber":"4",
    "addr:postcode":"6721",
    "addr:street":"Edgar St",
    "iso:country":"AU",
    "sg:address":"4 Edgar St",
    "sg:city":"Port Hedland",
    "sg:classifiers":[
        {
            "category":"Health Services",
            "subcategory":"Chiropractor",
            "type":"Services"
        }
    ],
    "sg:phone":"+61 8 9173 5570",
    "sg:postcode":"6721",
    "sg:province":"WA",
    "wof:name":"Boulevard Chiropractic",
    "wof:placetype":"venue"
},
  "geometry": {"coordinates":[118.576339722,-20.3110942841],"type":"Point"}
}