{
  "type": "Feature",
  "properties": {
    "addr:full":"24 Durrington Rd Elizabeth SA 5112",
    "addr:housenumber":"24",
    "addr:postcode":"5112",
    "addr:street":"Durrington Rd",
    "iso:country":"AU",
    "sg:address":"24 Durrington Rd",
    "sg:city":"Elizabeth",
    "sg:classifiers":[
        {
            "category":"Education",
            "subcategory":"School",
            "type":"Public Place"
        }
    ],
    "sg:phone":"+61 8 8255 6613",
    "sg:postcode":"5112",
    "sg:province":"SA",
    "sg:tags":[
        "state",
        "except",
        "nsw"
    ],
    "wof:name":"Elizabeth Special School",
    "wof:placetype":"venue"
},
  "geometry": {"coordinates":[138.67449951200001,-34.7109832764],"type":"Point"}
}