{
  "type": "Feature",
  "properties": {
    "iso:country":"AU",
    "sg:address":"Shop 10 Eton Arcade Eton St",
    "sg:city":"Sutherland",
    "sg:classifiers":[
        {
            "category":"Shopping",
            "subcategory":"Crafts & Fabrics",
            "type":"Retail Goods"
        }
    ],
    "sg:phone":"+61 2 9545 2623",
    "sg:postcode":"2232",
    "sg:province":"NSW",
    "sg:tags":[
        "material",
        "dress"
    ],
    "wof:name":"Flora Fabrics",
    "wof:placetype":"venue"
},
  "geometry": {"coordinates":[151.05743408199999,-34.0387153625],"type":"Point"}
}