{
  "type": "Feature",
  "properties": {
    "iso:country":"AU",
    "sg:address":"15 Cattai Creek Drv",
    "sg:city":"Kellyville",
    "sg:classifiers":[
        {
            "category":"Professional",
            "subcategory":"Detective & Security Services",
            "type":"Services"
        }
    ],
    "sg:phone":"+61 2 9659 4505",
    "sg:postcode":"2155",
    "sg:province":"NSW",
    "sg:tags":[
        "identification",
        "system"
    ],
    "wof:name":"Packaging Development Resources",
    "wof:placetype":"venue"
},
  "geometry": {"coordinates":[150.97259521500001,-33.7009048462],"type":"Point"}
}