{
  "type": "Feature",
  "properties": {
    "addr:full":"57 Laura Rd Knoxfield VIC 3180",
    "addr:housenumber":"57",
    "addr:postcode":"3180",
    "addr:street":"Laura Rd",
    "iso:country":"AU",
    "sg:address":"57 Laura Rd",
    "sg:city":"Knoxfield",
    "sg:classifiers":[
        {
            "category":"Building & Trades",
            "subcategory":"Cleaning & Sanitation",
            "type":"Services"
        }
    ],
    "sg:phone":"+61 419 539 999",
    "sg:postcode":"3180",
    "sg:province":"VIC",
    "sg:tags":[
        "chemical",
        "pressure",
        "steam",
        "contractor"
    ],
    "wof:name":"Graffiti Solutions",
    "wof:placetype":"venue"
},
  "geometry": {"coordinates":[145.24310302699999,-37.8922348022],"type":"Point"}
}