{
  "type": "Feature",
  "properties": {
    "iso:country":"AU",
    "sg:address":"7 Kanangra Drv",
    "sg:city":"Thirroul",
    "sg:classifiers":[
        {
            "category":"Professional",
            "subcategory":"Management & Consulting",
            "type":"Services"
        }
    ],
    "sg:phone":"+61 2 4268 1300",
    "sg:postcode":"2515",
    "sg:province":"NSW",
    "sg:tags":[
        "consultant",
        "economic"
    ],
    "wof:name":"Illawarra Economic Consulting Pty Ltd",
    "wof:placetype":"venue"
},
  "geometry": {"coordinates":[150.911179,-34.314945],"type":"Point"}
}