{
  "type": "Feature",
  "properties": {
    "iso:country":"AU",
    "sg:address":"553 Wyndham St",
    "sg:city":"Shepparton",
    "sg:classifiers":[
        {
            "category":"Health Services",
            "subcategory":"Health Practitioner",
            "type":"Services"
        }
    ],
    "sg:phone":"+61 3 5821 2249",
    "sg:postcode":"3630",
    "sg:province":"VIC",
    "sg:tags":[
        "osteopath"
    ],
    "wof:name":"O&#039;Callaghan Tara",
    "wof:placetype":"venue"
},
  "geometry": {"coordinates":[145.39698791500001,-36.3933639526],"type":"Point"}
}