{
  "type": "Feature",
  "properties": {
    "iso:country":"AU",
    "sg:address":"444 Ballan Rd",
    "sg:city":"Werribee",
    "sg:classifiers":[
        {
            "category":"Farming",
            "subcategory":"Farm & Veterinary Services",
            "type":"Manufacturing & Wholesale Goods"
        }
    ],
    "sg:phone":"+61 3 9741 3509",
    "sg:postcode":"3030",
    "sg:province":"VIC",
    "sg:tags":[
        "blacksmith",
        "farrier"
    ],
    "wof:name":"Sammartino Peter",
    "wof:placetype":"venue"
},
  "geometry": {"coordinates":[144.616013,-37.875446],"type":"Point"}
}