{
  "type": "Feature",
  "properties": {
    "addr:full":"235 Bussell Hwy Busselton WA 6280",
    "addr:housenumber":"235",
    "addr:postcode":"6280",
    "addr:street":"Bussell Hwy",
    "iso:country":"AU",
    "sg:address":"235 Bussell Hwy",
    "sg:city":"Busselton",
    "sg:classifiers":[
        {
            "category":"Fast Food",
            "type":"Food & Drink"
        }
    ],
    "sg:phone":"+61 8 9752 2959",
    "sg:postcode":"6280",
    "sg:province":"WA",
    "sg:tags":[
        "away",
        "take"
    ],
    "wof:name":"West End Takeaways",
    "wof:placetype":"venue"
},
  "geometry": {"coordinates":[115.317871094,-33.6565856934],"type":"Point"}
}