{
  "type": "Feature",
  "properties": {
    "addr:full":"128 Sanklin St Adelaide SA 5000",
    "addr:housenumber":"128",
    "addr:postcode":"5000",
    "addr:street":"Sanklin St",
    "iso:country":"AU",
    "sg:address":"128 Sanklin St",
    "sg:city":"Adelaide",
    "sg:classifiers":[
        {
            "category":"Professional",
            "subcategory":"Employment Agencies",
            "type":"Services"
        }
    ],
    "sg:phone":"+61 8 8212 7133",
    "sg:postcode":"5000",
    "sg:province":"SA",
    "sg:tags":[
        "hire",
        "labour",
        "contractor"
    ],
    "wof:name":"World Workers",
    "wof:placetype":"venue"
},
  "geometry": {"coordinates":[138.594024658,-34.9281578064],"type":"Point"}
}