{
  "type": "Feature",
  "properties": {
    "addr:full":"71 Wiseman Rd Silvan VIC 3795",
    "addr:housenumber":"71",
    "addr:postcode":"3795",
    "addr:street":"Wiseman Rd",
    "iso:country":"AU",
    "sg:address":"71 Wiseman Rd",
    "sg:city":"Silvan",
    "sg:classifiers":[
        {
            "category":"Wholesale",
            "subcategory":"Plants",
            "type":"Manufacturing & Wholesale Goods"
        }
    ],
    "sg:phone":"+61 3 9737 9250",
    "sg:postcode":"3795",
    "sg:province":"VIC",
    "sg:tags":[
        "florist"
    ],
    "wof:name":"Sunny Hill Flowers",
    "wof:placetype":"venue"
},
  "geometry": {"coordinates":[145.45187377900001,-37.8405265808],"type":"Point"}
}