{
  "type": "Feature",
  "properties": {
    "iso:country":"AU",
    "sg:address":"5 Fisher St",
    "sg:city":"Myrtle Bank",
    "sg:classifiers":[
        {
            "category":"Education",
            "subcategory":"School",
            "type":"Public Place"
        }
    ],
    "sg:phone":"+61 8 8379 0500",
    "sg:postcode":"5064",
    "sg:province":"SA",
    "sg:tags":[
        "state",
        "except",
        "nsw"
    ],
    "wof:name":"Glen Osmond Primary",
    "wof:placetype":"venue"
},
  "geometry": {"coordinates":[138.63705444300001,-34.9564361572],"type":"Point"}
}