{
  "type": "Feature",
  "properties": {
    "iso:country":"AU",
    "sg:address":"83 Campbell St",
    "sg:city":"Millmerran",
    "sg:classifiers":[
        {
            "category":"Autos & Motor Vehicles",
            "subcategory":"Auto Supplies",
            "type":"Retail Goods"
        }
    ],
    "sg:phone":"+61 7 4695 1278",
    "sg:postcode":"4357",
    "sg:province":"QLD",
    "sg:tags":[
        "tyre"
    ],
    "wof:name":"Millmerran Tyre Service",
    "wof:placetype":"venue"
},
  "geometry": {"coordinates":[151.26924099999999,-27.878738],"type":"Point"}
}