{
  "type": "Feature",
  "properties": {
    "addr:full":"71 King St Caboolture QLD 4510",
    "addr:housenumber":"71",
    "addr:postcode":"4510",
    "addr:street":"King St",
    "iso:country":"AU",
    "sg:address":"71 King St",
    "sg:city":"Caboolture",
    "sg:classifiers":[
        {
            "category":"Professional",
            "subcategory":"Accounting & Tax Preparation",
            "type":"Services"
        }
    ],
    "sg:phone":"+61 7 5495 3669",
    "sg:postcode":"4510",
    "sg:province":"QLD",
    "sg:tags":[
        "accountant",
        "auditor"
    ],
    "wof:name":"Clarke Chris",
    "wof:placetype":"venue"
},
  "geometry": {"coordinates":[152.949219,-27.084455],"type":"Point"}
}