{
  "type": "Feature",
  "properties": {
    "addr:full":"West St Harden NSW 2587",
    "addr:postcode":"2587",
    "addr:street":"West St",
    "iso:country":"AU",
    "sg:address":"West St",
    "sg:city":"Harden",
    "sg:classifiers":[
        {
            "category":"Freight",
            "type":"Transportation"
        }
    ],
    "sg:phone":"+61 2 6386 2040",
    "sg:postcode":"2587",
    "sg:province":"NSW",
    "sg:tags":[
        "transport",
        "refrigerated"
    ],
    "wof:name":"Madden's Refrigerated Transport",
    "wof:placetype":"venue"
},
  "geometry": {"coordinates":[148.345535278,-34.5476455688],"type":"Point"}
}