{
  "type": "Feature",
  "properties": {
    "addr:full":"289 Canterbury Rd Forest Hill VIC 3131",
    "addr:housenumber":"289",
    "addr:postcode":"3131",
    "addr:street":"Canterbury Rd",
    "iso:country":"AU",
    "sg:address":"289 Canterbury Rd",
    "sg:city":"Forest Hill",
    "sg:classifiers":[
        {
            "category":"Home & Garden",
            "subcategory":"Furniture",
            "type":"Retail Goods"
        }
    ],
    "sg:phone":"+61 3 9894 4577",
    "sg:postcode":"3131",
    "sg:province":"VIC",
    "sg:tags":[
        "business"
    ],
    "wof:name":"Canterbury Used Office Furniture",
    "wof:placetype":"venue"
},
  "geometry": {"coordinates":[145.171585083,-37.834438324],"type":"Point"}
}