{
  "type": "Feature",
  "properties": {
    "addr:full":"Suite 2 & 3, 133 Sharp Cooma NSW 2630",
    "addr:housenumber":"&;133",
    "addr:postcode":"2630",
    "addr:street":"3",
    "iso:country":"AU",
    "sg:address":"Suite 2 & 3, 133",
    "sg:city":"Sharp Cooma",
    "sg:classifiers":[
        {
            "category":"Professional",
            "subcategory":"Employment Agencies",
            "type":"Services"
        }
    ],
    "sg:phone":"+61 2 6450 2900",
    "sg:postcode":"2630",
    "sg:province":"NSW",
    "wof:name":"Campbell Page Employment Services",
    "wof:placetype":"venue"
},
  "geometry": {"coordinates":[149.13409423799999,-36.2312316895],"type":"Point"}
}