{
  "type": "Feature",
  "properties": {
    "addr:full":"90 Belgrave St Kempsey NSW 2440",
    "addr:housenumber":"90",
    "addr:postcode":"2440",
    "addr:street":"Belgrave St",
    "iso:country":"AU",
    "sg:address":"90 Belgrave St",
    "sg:city":"Kempsey",
    "sg:classifiers":[
        {
            "category":"Retail",
            "subcategory":"Auto Repair",
            "type":"Services"
        }
    ],
    "sg:phone":"+61 13 23 81",
    "sg:postcode":"2440",
    "sg:province":"NSW",
    "sg:tags":[
        "wheel",
        "balancing",
        "alignment"
    ],
    "wof:name":"Beaurepaires",
    "wof:placetype":"venue"
},
  "geometry": {"coordinates":[152.837906,-31.080219],"type":"Point"}
}