{
  "type": "Feature",
  "properties": {
    "iso:country":"AU",
    "sg:address":"2 Chapman St",
    "sg:city":"Gladesville",
    "sg:classifiers":[
        {
            "category":"Building & Trades",
            "subcategory":"Construction",
            "type":"Services"
        }
    ],
    "sg:phone":"+61 2 9817 2319",
    "sg:postcode":"2111",
    "sg:province":"NSW",
    "sg:tags":[
        "contractor"
    ],
    "wof:name":"Andrew Harris",
    "wof:placetype":"venue"
},
  "geometry": {"coordinates":[151.11648559599999,-33.8267440796],"type":"Point"}
}