{
  "type": "Feature",
  "properties": {
    "iso:country":"AU",
    "sg:address":"119 Toolooa St",
    "sg:city":"Gladstone",
    "sg:classifiers":[
        {
            "category":"Food & Beverages",
            "subcategory":"Supermarket",
            "type":"Retail Goods"
        }
    ],
    "sg:phone":"+61 7 4972 1998",
    "sg:postcode":"4680",
    "sg:province":"QLD",
    "sg:tags":[
        "grocery",
        "store"
    ],
    "wof:name":"Cast's Progressive Supermarket",
    "wof:placetype":"venue"
},
  "geometry": {"coordinates":[151.26942443900001,-23.8570823669],"type":"Point"}
}