{
  "type": "Feature",
  "properties": {
    "iso:country":"AU",
    "sg:address":"3 Ollerton Ave",
    "sg:city":"Newborough",
    "sg:classifiers":[
        {
            "category":"Manufacturing",
            "subcategory":"Food",
            "type":"Manufacturing & Wholesale Goods"
        }
    ],
    "sg:phone":"+61 3 5127 3326",
    "sg:postcode":"3825",
    "sg:province":"VIC",
    "sg:tags":[
        "function",
        "catering"
    ],
    "wof:name":"Jaspers Cafe",
    "wof:placetype":"venue"
},
  "geometry": {"coordinates":[146.27742,-38.183155],"type":"Point"}
}