{
  "type": "Feature",
  "properties": {
    "addr:full":"Lilac Pl Goulburn NSW 2580",
    "addr:postcode":"2580",
    "addr:street":"Lilac Pl",
    "iso:country":"AU",
    "sg:address":"Lilac Pl",
    "sg:city":"Goulburn",
    "sg:classifiers":[
        {
            "category":"Cinema",
            "subcategory":"Movie Theater",
            "type":"Entertainment"
        }
    ],
    "sg:phone":"+61 2 4822 1616",
    "sg:postcode":"2580",
    "sg:province":"NSW",
    "wof:name":"Lilac City Cinema",
    "wof:placetype":"venue"
},
  "geometry": {"coordinates":[149.71810913100001,-34.7533721924],"type":"Point"}
}