{
  "type": "Feature",
  "properties": {
    "addr:full":"Shp 2/ 93 Goondoon St Gladstone QLD 4680",
    "addr:housenumber":"/ 93",
    "addr:postcode":"4680",
    "addr:street":"Goondoon St",
    "iso:country":"AU",
    "sg:address":"Shp 2/ 93 Goondoon St",
    "sg:city":"Gladstone",
    "sg:classifiers":[
        {
            "category":"Shopping",
            "subcategory":"Shoes",
            "type":"Retail Goods"
        }
    ],
    "sg:phone":"+61 7 4972 0411",
    "sg:postcode":"4680",
    "sg:province":"QLD",
    "sg:tags":[
        "footwear"
    ],
    "wof:name":"Leather Souls",
    "wof:placetype":"venue"
},
  "geometry": {"coordinates":[151.255325317,-23.842672348],"type":"Point"}
}