{
  "type": "Feature",
  "properties": {
    "addr:full":"Unit 3, 84 Sunnyholt Rd Blacktown NSW 2148",
    "addr:housenumber":"84",
    "addr:postcode":"2148",
    "addr:street":"Sunnyholt Rd",
    "iso:country":"AU",
    "sg:address":"Unit 3, 84 Sunnyholt Rd",
    "sg:city":"Blacktown",
    "sg:classifiers":[
        {
            "category":"Retail",
            "subcategory":"Auto Repair",
            "type":"Services"
        }
    ],
    "sg:phone":"+61 2 9622 2029",
    "sg:postcode":"2148",
    "sg:province":"NSW",
    "sg:tags":[
        "engine",
        "reconditioning"
    ],
    "wof:name":"JPS Performance",
    "wof:placetype":"venue"
},
  "geometry": {"coordinates":[150.911575317,-33.7714233398],"type":"Point"}
}