{
  "type": "Feature",
  "properties": {
    "addr:full":"32 The Peninsula Pl Noosa Waters QLD 4567",
    "addr:housenumber":"32",
    "addr:postcode":"4567",
    "addr:street":"The Peninsula Pl Noosa",
    "iso:country":"AU",
    "sg:address":"32 The Peninsula Pl",
    "sg:city":"Noosa Waters",
    "sg:classifiers":[
        {
            "category":"Professional",
            "subcategory":"Art Services",
            "type":"Services"
        }
    ],
    "sg:phone":"+61 414 316 316",
    "sg:postcode":"4567",
    "sg:province":"QLD",
    "sg:tags":[
        "decorator",
        "painter"
    ],
    "wof:name":"Steve Connell",
    "wof:placetype":"venue"
},
  "geometry": {"coordinates":[153.08430480999999,-26.4013938904],"type":"Point"}
}