{
  "type": "Feature",
  "properties": {
    "addr:full":"21 Parkland Rd Mona Vale NSW 2103",
    "addr:housenumber":"21",
    "addr:postcode":"2103",
    "addr:street":"Parkland Rd",
    "iso:country":"AU",
    "sg:address":"21 Parkland Rd",
    "sg:city":"Mona Vale",
    "sg:classifiers":[
        {
            "category":"Shopping",
            "subcategory":"Computers & Home Electronics",
            "type":"Retail Goods"
        }
    ],
    "sg:phone":"+61 2 9997 7234",
    "sg:postcode":"2103",
    "sg:province":"NSW",
    "sg:tags":[
        "equipment",
        "multimedia"
    ],
    "wof:name":"Ingenious Computing",
    "wof:placetype":"venue"
},
  "geometry": {"coordinates":[151.29498290999999,-33.6715812683],"type":"Point"}
}