{
  "type": "Feature",
  "properties": {
    "iso:country":"AU",
    "sg:address":"178 Pitt Town Rd",
    "sg:city":"Kenthurst",
    "sg:classifiers":[
        {
            "category":"Building & Trades",
            "subcategory":"Plumbing",
            "type":"Services"
        }
    ],
    "sg:phone":"+61 2 9654 8551",
    "sg:postcode":"2156",
    "sg:province":"NSW",
    "sg:tags":[
        "plumber",
        "gasfitters"
    ],
    "wof:name":"Norwest Gas Pty Ltd",
    "wof:placetype":"venue"
},
  "geometry": {"coordinates":[150.97381591800001,-33.6562652588],"type":"Point"}
}