{
  "type": "Feature",
  "properties": {
    "addr:full":"19 Sir Laurence Drv Seaford VIC 3198",
    "addr:housenumber":"19",
    "addr:postcode":"3198",
    "addr:street":"Sir Laurence Drv",
    "iso:country":"AU",
    "sg:address":"19 Sir Laurence Drv",
    "sg:city":"Seaford",
    "sg:classifiers":[
        {
            "category":"Autos & Motor Vehicles",
            "subcategory":"Boat Sales",
            "type":"Retail Goods"
        }
    ],
    "sg:phone":"+61 3 9773 6692",
    "sg:postcode":"3198",
    "sg:province":"VIC",
    "sg:tags":[
        "equipment",
        "yacht"
    ],
    "wof:name":"Seaford Pleasure Boats",
    "wof:placetype":"venue"
},
  "geometry": {"coordinates":[145.144241333,-38.1154937744],"type":"Point"}
}