{
  "type": "Feature",
  "properties": {
    "addr:full":"25 Kearny Drv Aspendale Gardens VIC 3195",
    "addr:housenumber":"25",
    "addr:postcode":"3195",
    "addr:street":"Kearny Drv",
    "iso:country":"AU",
    "sg:address":"25 Kearny Drv",
    "sg:city":"Aspendale Gardens",
    "sg:classifiers":[
        {
            "category":"Building & Trades",
            "subcategory":"Plumbing",
            "type":"Services"
        }
    ],
    "sg:phone":"+61 407 811 659",
    "sg:postcode":"3195",
    "sg:province":"VIC",
    "sg:tags":[
        "plumber",
        "gasfitters"
    ],
    "wof:name":"Blackrock Plumbing",
    "wof:placetype":"venue"
},
  "geometry": {"coordinates":[145.10911560100001,-38.0186347961],"type":"Point"}
}