{
  "type": "Feature",
  "properties": {
    "addr:full":"Warringah Rd Forestville NSW 2087",
    "addr:postcode":"2087",
    "addr:street":"Warringah Rd",
    "iso:country":"AU",
    "sg:address":"Warringah Rd",
    "sg:city":"Forestville",
    "sg:classifiers":[
        {
            "category":"Social Services",
            "subcategory":"Retirement Home",
            "type":"Services"
        }
    ],
    "sg:phone":"+61 414 984 901",
    "sg:postcode":"2087",
    "sg:province":"NSW",
    "sg:tags":[
        "life",
        "coaching"
    ],
    "wof:name":"Phil Breheny",
    "wof:placetype":"venue"
},
  "geometry": {"coordinates":[151.21543884299999,-33.7607803345],"type":"Point"}
}