{
  "type": "Feature",
  "properties": {
    "addr:full":"13 Bosworth Rd Woolgoolga NSW 2456",
    "addr:housenumber":"13",
    "addr:postcode":"2456",
    "addr:street":"Bosworth Rd",
    "iso:country":"AU",
    "sg:address":"13 Bosworth Rd",
    "sg:city":"Woolgoolga",
    "sg:classifiers":[
        {
            "category":"Banks & Credit Unions",
            "subcategory":"Investment Brokerage",
            "type":"Services"
        }
    ],
    "sg:phone":"+61 2 6654 0903",
    "sg:postcode":"2456",
    "sg:province":"NSW",
    "sg:tags":[
        "radiator",
        "motor"
    ],
    "wof:name":"Northern Beaches Radiators",
    "wof:placetype":"venue"
},
  "geometry": {"coordinates":[153.193893,-30.12499],"type":"Point"}
}