{
  "type": "Feature",
  "properties": {
    "iso:country":"AU",
    "sg:address":"Elizabeth Street Pr",
    "sg:city":"Hobart",
    "sg:classifiers":[
        {
            "category":"Restaurant",
            "type":"Food & Drink"
        }
    ],
    "sg:phone":"+61 3 6224 4428",
    "sg:postcode":"7000",
    "sg:province":"TAS",
    "sg:website":"http://www.marqueiv.com.au",
    "wof:name":"Marque IV The Restaurant",
    "wof:placetype":"venue"
},
  "geometry": {"coordinates":[147.31666564899999,-42.874168396],"type":"Point"}
}