{
  "type": "Feature",
  "properties": {
    "addr:full":"30 Bouverie St Mundubbera QLD 4626",
    "addr:housenumber":"30",
    "addr:postcode":"4626",
    "addr:street":"Bouverie St",
    "iso:country":"AU",
    "sg:address":"30 Bouverie St",
    "sg:city":"Mundubbera",
    "sg:classifiers":[
        {
            "category":"Utilities",
            "subcategory":"Electric",
            "type":"Services"
        }
    ],
    "sg:phone":"+61 7 4165 4183",
    "sg:postcode":"4626",
    "sg:province":"QLD",
    "sg:tags":[
        "electrical",
        "contractor"
    ],
    "wof:name":"Mundubbera Electrical",
    "wof:placetype":"venue"
},
  "geometry": {"coordinates":[151.29963699999999,-25.58774],"type":"Point"}
}