{
  "type": "Feature",
  "properties": {
    "addr:full":"8 Kennedy St South Grafton NSW 2460",
    "addr:housenumber":"8",
    "addr:postcode":"2460",
    "addr:street":"Kennedy St",
    "iso:country":"AU",
    "sg:address":"8 Kennedy St",
    "sg:city":"South Grafton",
    "sg:classifiers":[
        {
            "category":"Professional",
            "subcategory":"Printing & Photocopies",
            "type":"Services"
        }
    ],
    "sg:phone":"+61 2 6642 7754",
    "sg:postcode":"2460",
    "sg:province":"NSW",
    "sg:tags":[
        "screen",
        "printer"
    ],
    "wof:name":"Greame Evans Screen Printer",
    "wof:placetype":"venue"
},
  "geometry": {"coordinates":[152.930908203,-29.7030467987],"type":"Point"}
}