{
  "type": "Feature",
  "properties": {
    "addr:full":"59 Macleay Street Potts Point Sydney 2011",
    "addr:housenumber":"59",
    "addr:postcode":"2011",
    "addr:street":"Macleay Street",
    "iso:country":"AU",
    "sg:address":"59 Macleay Street Potts Point",
    "sg:city":"Sydney",
    "sg:classifiers":[
        {
            "category":"Professional",
            "subcategory":"Business Services",
            "type":"Services"
        }
    ],
    "sg:postcode":"2011",
    "sg:tags":[
        "flash-voip-telephony-widget-voice"
    ],
    "sg:website":"http://www.icondial.com",
    "wof:name":"iconDial",
    "wof:placetype":"venue"
},
  "geometry": {"coordinates":[151.22536099999999,-33.8687],"type":"Point"}
}