{
  "type": "Feature",
  "properties": {
    "addr:full":"52 Fishburn Crs Watanobbi NSW 2259",
    "addr:housenumber":"52",
    "addr:postcode":"2259",
    "addr:street":"Fishburn Crs",
    "iso:country":"AU",
    "sg:address":"52 Fishburn Crs",
    "sg:city":"Watanobbi",
    "sg:classifiers":[
        {
            "category":"Home & Garden",
            "subcategory":"Garden Supply",
            "type":"Retail Goods"
        }
    ],
    "sg:phone":"+61 438 775 735",
    "sg:postcode":"2259",
    "sg:province":"NSW",
    "sg:tags":[
        "nursery"
    ],
    "wof:name":"Coirking",
    "wof:placetype":"venue"
},
  "geometry": {"coordinates":[151.431350708,-33.2703781128],"type":"Point"}
}