{
  "type": "Feature",
  "properties": {
    "iso:country":"AU",
    "sg:address":"77 Devereux Rd",
    "sg:city":"Linden Park",
    "sg:classifiers":[
        {
            "category":"Retail",
            "subcategory":"Auto Repair",
            "type":"Services"
        }
    ],
    "sg:phone":"+61 8 8379 7544",
    "sg:postcode":"5065",
    "sg:province":"SA",
    "sg:tags":[
        "repairer",
        "motor",
        "engineer"
    ],
    "wof:name":"Devereux Motors",
    "wof:placetype":"venue"
},
  "geometry": {"coordinates":[138.651901245,-34.9471511841],"type":"Point"}
}