{
  "type": "Feature",
  "properties": {
    "addr:full":"180 High St Belmont VIC 3216",
    "addr:housenumber":"180",
    "addr:postcode":"3216",
    "addr:street":"High St",
    "iso:country":"AU",
    "sg:address":"180 High St",
    "sg:city":"Belmont",
    "sg:classifiers":[
        {
            "category":"Fast Food",
            "type":"Food & Drink"
        }
    ],
    "sg:phone":"+61 3 5247 4455",
    "sg:postcode":"3216",
    "sg:province":"VIC",
    "sg:tags":[
        "away",
        "take"
    ],
    "wof:name":"Domino's Pizza",
    "wof:placetype":"venue"
},
  "geometry": {"coordinates":[144.34259033199999,-38.174987793],"type":"Point"}
}