{
  "type": "Feature",
  "properties": {
    "addr:full":"229 Darlinghurst Rd Darlinghurst NSW 2010",
    "addr:housenumber":"229",
    "addr:postcode":"2010",
    "addr:street":"Darlinghurst Rd",
    "iso:country":"AU",
    "sg:address":"229 Darlinghurst Rd",
    "sg:city":"Darlinghurst",
    "sg:classifiers":[
        {
            "category":"Travel",
            "subcategory":"Hotels & Motels",
            "type":"Entertainment"
        }
    ],
    "sg:phone":"+61 2 9332 2011",
    "sg:postcode":"2010",
    "sg:province":"NSW",
    "sg:tags":[
        "accommodation"
    ],
    "wof:name":"Eight Hotels Australia",
    "wof:placetype":"venue"
},
  "geometry": {"coordinates":[151.22039794899999,-33.8778266907],"type":"Point"}
}