{
  "type": "Feature",
  "properties": {
    "addr:full":"5 Briar Rd Felixstow SA 5070",
    "addr:housenumber":"5",
    "addr:postcode":"5070",
    "addr:street":"Briar Rd",
    "iso:country":"AU",
    "sg:address":"5 Briar Rd",
    "sg:city":"Felixstow",
    "sg:classifiers":[
        {
            "category":"Education",
            "subcategory":"Kindergarten",
            "type":"Public Place"
        }
    ],
    "sg:phone":"+61 8 8365 9808",
    "sg:postcode":"5070",
    "sg:province":"SA",
    "sg:tags":[
        "pre-schools"
    ],
    "wof:name":"The Briars Special Early Learning Centre",
    "wof:placetype":"venue"
},
  "geometry": {"coordinates":[138.64466857900001,-34.8918151855],"type":"Point"}
}