{
  "type": "Feature",
  "properties": {
    "addr:full":"4 Kanandah Rd Broken Hill NSW 2880",
    "addr:housenumber":"4",
    "addr:postcode":"2880",
    "addr:street":"Kanandah Rd",
    "iso:country":"AU",
    "sg:address":"4 Kanandah Rd",
    "sg:city":"Broken Hill",
    "sg:classifiers":[
        {
            "category":"Wholesale",
            "subcategory":"Construction Materials",
            "type":"Manufacturing & Wholesale Goods"
        }
    ],
    "sg:phone":"+61 8 8088 5222",
    "sg:postcode":"2880",
    "sg:province":"NSW",
    "sg:tags":[
        "protective",
        "coating"
    ],
    "wof:name":"Fillery Antiwear Products",
    "wof:placetype":"venue"
},
  "geometry": {"coordinates":[141.43318176299999,-31.9823188782],"type":"Point"}
}