{
  "type": "Feature",
  "properties": {
    "addr:full":"8 Messina Crs Keilor Lodge VIC 3038",
    "addr:housenumber":"8",
    "addr:postcode":"3038",
    "addr:street":"Messina Crs",
    "iso:country":"AU",
    "sg:address":"8 Messina Crs",
    "sg:city":"Keilor Lodge",
    "sg:classifiers":[
        {
            "category":"Building & Trades",
            "subcategory":"Plumbing",
            "type":"Services"
        }
    ],
    "sg:phone":"+61 3 9390 1055",
    "sg:postcode":"3038",
    "sg:province":"VIC",
    "sg:tags":[
        "drainers"
    ],
    "wof:name":"AMT Excavations Pty Ltd",
    "wof:placetype":"venue"
},
  "geometry": {"coordinates":[144.79896500000001,-37.701321],"type":"Point"}
}