{
  "type": "Feature",
  "properties": {
    "addr:full":"5 Oxford Pl Arundel QLD 4214",
    "addr:housenumber":"5",
    "addr:postcode":"4214",
    "addr:street":"Oxford Pl",
    "iso:country":"AU",
    "sg:address":"5 Oxford Pl",
    "sg:city":"Arundel",
    "sg:classifiers":[
        {
            "category":"Personal",
            "subcategory":"Beauty Salon",
            "type":"Services"
        }
    ],
    "sg:phone":"+61 7 5574 5029",
    "sg:postcode":"4214",
    "sg:province":"QLD",
    "wof:name":"Aroma Essence",
    "wof:placetype":"venue"
},
  "geometry": {"coordinates":[153.35711669899999,-27.9309215546],"type":"Point"}
}