{
  "type": "Feature",
  "properties": {
    "iso:country":"AU",
    "sg:address":"4/ 52 Township Drv",
    "sg:city":"West Burleigh",
    "sg:classifiers":[
        {
            "category":"Utilities",
            "subcategory":"Electric",
            "type":"Services"
        }
    ],
    "sg:phone":"+61 411 768 830",
    "sg:postcode":"4219",
    "sg:province":"QLD",
    "sg:tags":[
        "electrical",
        "contractor"
    ],
    "wof:name":"RDE Electrical Contractors Pty Ltd",
    "wof:placetype":"venue"
},
  "geometry": {"coordinates":[153.43377685600001,-28.1131896973],"type":"Point"}
}