{
  "type": "Feature",
  "properties": {
    "iso:country":"AU",
    "sg:address":"16 Bates St",
    "sg:city":"Merredin",
    "sg:classifiers":[
        {
            "category":"Shopping",
            "subcategory":"Clothing, Apparel, & Fashions",
            "type":"Retail Goods"
        }
    ],
    "sg:phone":"+61 8 9041 1013",
    "sg:postcode":"6415",
    "sg:province":"WA",
    "sg:tags":[
        "menswear"
    ],
    "wof:name":"Drakefords Economic Stores Pty Ltd",
    "wof:placetype":"venue"
},
  "geometry": {"coordinates":[118.27848815900001,-31.4813137054],"type":"Point"}
}