{
  "type": "Feature",
  "properties": {
    "iso:country":"AU",
    "sg:address":"12 Bennet St",
    "sg:city":"Port Macquarie",
    "sg:classifiers":[
        {
            "category":"Building & Trades",
            "subcategory":"Construction",
            "type":"Services"
        }
    ],
    "sg:phone":"+61 418 653 777",
    "sg:postcode":"2444",
    "sg:province":"NSW",
    "sg:tags":[
        "plasterboard",
        "plasterer",
        "fixer"
    ],
    "wof:name":"Shane Hughes Interior Linings",
    "wof:placetype":"venue"
},
  "geometry": {"coordinates":[152.892273,-31.441818],"type":"Point"}
}