{
  "type": "Feature",
  "properties": {
    "addr:full":"14 Cranbrook La Bellevue Hill NSW 2023",
    "addr:housenumber":"14",
    "addr:postcode":"2023",
    "addr:street":"Cranbrook La Bellevue",
    "iso:country":"AU",
    "sg:address":"14 Cranbrook La",
    "sg:city":"Bellevue Hill",
    "sg:classifiers":[
        {
            "category":"Wholesale",
            "subcategory":"Auto Parts",
            "type":"Manufacturing & Wholesale Goods"
        }
    ],
    "sg:phone":"+61 2 9326 2330",
    "sg:postcode":"2023",
    "sg:province":"NSW",
    "sg:tags":[
        "watch"
    ],
    "wof:name":"The Watch Factory",
    "wof:placetype":"venue"
},
  "geometry": {"coordinates":[151.25375366200001,-33.8727722168],"type":"Point"}
}