{
  "type": "Feature",
  "properties": {
    "addr:full":"24 Baile Rd Canning Vale WA 6155",
    "addr:housenumber":"24",
    "addr:postcode":"6155",
    "addr:street":"Baile Rd",
    "iso:country":"AU",
    "sg:address":"24 Baile Rd",
    "sg:city":"Canning Vale",
    "sg:classifiers":[
        {
            "category":"Utilities",
            "subcategory":"Water",
            "type":"Services"
        }
    ],
    "sg:phone":"+61 8 9455 1137",
    "sg:postcode":"6155",
    "sg:province":"WA",
    "sg:tags":[
        "hot",
        "system"
    ],
    "wof:name":"A-Altona Plumbing",
    "wof:placetype":"venue"
},
  "geometry": {"coordinates":[115.91467299999999,-32.066677],"type":"Point"}
}