{
  "type": "Feature",
  "properties": {
    "addr:full":"9 Coates Pl Wetherill Park NSW 2164",
    "addr:housenumber":"9",
    "addr:postcode":"2164",
    "addr:street":"Coates Pl",
    "iso:country":"AU",
    "sg:address":"9 Coates Pl",
    "sg:city":"Wetherill Park",
    "sg:classifiers":[
        {
            "category":"Shopping",
            "subcategory":"Discount & Variety Stores",
            "type":"Retail Goods"
        }
    ],
    "sg:phone":"+61 2 9756 0600",
    "sg:postcode":"2164",
    "sg:province":"NSW",
    "sg:tags":[
        "dangerous",
        "storage"
    ],
    "wof:name":"Dangerous Goods Logistics Pty Ltd",
    "wof:placetype":"venue"
},
  "geometry": {"coordinates":[150.88511657699999,-33.84034729],"type":"Point"}
}