{
  "type": "Feature",
  "properties": {
    "addr:full":"13 Allnut Crt Bunbury WA 6230",
    "addr:housenumber":"13",
    "addr:postcode":"6230",
    "addr:street":"Allnut Crt",
    "iso:country":"AU",
    "sg:address":"13 Allnut Crt",
    "sg:city":"Bunbury",
    "sg:classifiers":[
        {
            "category":"Home & Garden",
            "subcategory":"Building Materials",
            "type":"Retail Goods"
        }
    ],
    "sg:phone":"+61 8 9726 2049",
    "sg:postcode":"6230",
    "sg:province":"WA",
    "sg:tags":[
        "roofing"
    ],
    "wof:name":"BGC Metal Roofing",
    "wof:placetype":"venue"
},
  "geometry": {"coordinates":[115.66503899999999,-33.360222],"type":"Point"}
}