{
  "type": "Feature",
  "properties": {
    "addr:full":"23 Mungala St Wynnum QLD 4178",
    "addr:housenumber":"23",
    "addr:postcode":"4178",
    "addr:street":"Mungala St",
    "iso:country":"AU",
    "sg:address":"23 Mungala St",
    "sg:city":"Wynnum",
    "sg:classifiers":[
        {
            "category":"Professional",
            "subcategory":"Engineering",
            "type":"Services"
        }
    ],
    "sg:phone":"+61 7 3396 2004",
    "sg:postcode":"4178",
    "sg:province":"QLD",
    "sg:tags":[
        "electrical",
        "engineer"
    ],
    "wof:name":"Southeast Control Services",
    "wof:placetype":"venue"
},
  "geometry": {"coordinates":[153.16708374000001,-27.4382476807],"type":"Point"}
}