{
  "type": "Feature",
  "properties": {
    "iso:country":"AU",
    "sg:address":"162 Hume St",
    "sg:city":"Toowoomba",
    "sg:classifiers":[
        {
            "category":"Real Estate",
            "subcategory":"Architect",
            "type":"Services"
        }
    ],
    "sg:phone":"+61 7 4632 0200",
    "sg:postcode":"4350",
    "sg:province":"QLD",
    "sg:tags":[
        "building",
        "designer"
    ],
    "wof:name":"Ehrlich Layton Architects",
    "wof:placetype":"venue"
},
  "geometry": {"coordinates":[151.957565,-27.56321],"type":"Point"}
}