{
  "type": "Feature",
  "properties": {
    "addr:full":"Unit 5, 26 Warehouse Rd Southport QLD 4215",
    "addr:housenumber":"26",
    "addr:postcode":"4215",
    "addr:street":"Warehouse Rd",
    "iso:country":"AU",
    "sg:address":"Unit 5, 26 Warehouse Rd",
    "sg:city":"Southport",
    "sg:classifiers":[
        {
            "category":"Retail",
            "subcategory":"Storage",
            "type":"Services"
        }
    ],
    "sg:phone":"+61 7 5532 0055",
    "sg:postcode":"4215",
    "sg:province":"QLD",
    "sg:tags":[
        "removal",
        "furniture"
    ],
    "wof:name":"Coastwide Removals",
    "wof:placetype":"venue"
},
  "geometry": {"coordinates":[153.408935547,-27.979801178],"type":"Point"}
}