{
  "type": "Feature",
  "properties": {
    "addr:full":"Haysey Rd Narre Warren East VIC 3804",
    "addr:postcode":"3804",
    "addr:street":"Haysey Rd",
    "iso:country":"AU",
    "sg:address":"Haysey Rd",
    "sg:city":"Narre Warren East",
    "sg:classifiers":[
        {
            "category":"Utilities",
            "subcategory":"Water",
            "type":"Services"
        }
    ],
    "sg:phone":"+61 3 9796 8560",
    "sg:postcode":"3804",
    "sg:province":"VIC",
    "sg:tags":[
        "cartage"
    ],
    "wof:name":"Stephenson Water Cartage",
    "wof:placetype":"venue"
},
  "geometry": {"coordinates":[145.37130737300001,-37.9650192261],"type":"Point"}
}