{
  "type": "Feature",
  "properties": {
    "addr:full":"49 Richardson Rd Narellan NSW 2567",
    "addr:housenumber":"49",
    "addr:postcode":"2567",
    "addr:street":"Richardson Rd",
    "iso:country":"AU",
    "sg:address":"49 Richardson Rd",
    "sg:city":"Narellan",
    "sg:classifiers":[
        {
            "category":"Building & Trades",
            "subcategory":"Construction",
            "type":"Services"
        }
    ],
    "sg:phone":"+61 2 4647 0064",
    "sg:postcode":"2567",
    "sg:province":"NSW",
    "sg:tags":[
        "ceiling"
    ],
    "wof:name":"Professional Ceiling Cleaning",
    "wof:placetype":"venue"
},
  "geometry": {"coordinates":[150.73658752399999,-34.0487060547],"type":"Point"}
}