{
  "type": "Feature",
  "properties": {
    "iso:country":"AU",
    "sg:address":"16 Erica St",
    "sg:city":"Springvale",
    "sg:classifiers":[
        {
            "category":"Food & Beverages",
            "subcategory":"Bakery",
            "type":"Retail Goods"
        }
    ],
    "sg:phone":"+61 3 9546 1117",
    "sg:postcode":"3171",
    "sg:province":"VIC",
    "sg:tags":[
        "cake",
        "shop",
        "pastry"
    ],
    "wof:name":"Dutch Waffle",
    "wof:placetype":"venue"
},
  "geometry": {"coordinates":[145.138275147,-37.9587135315],"type":"Point"}
}