{
  "type": "Feature",
  "properties": {
    "addr:full":"14 McKenzie St Ceduna SA 5690",
    "addr:housenumber":"14",
    "addr:postcode":"5690",
    "addr:street":"Mckenzie St",
    "iso:country":"AU",
    "sg:address":"14 McKenzie St",
    "sg:city":"Ceduna",
    "sg:classifiers":[
        {
            "category":"Shopping",
            "subcategory":"Clothing, Apparel, & Fashions",
            "type":"Retail Goods"
        }
    ],
    "sg:phone":"+61 8 8625 2023",
    "sg:postcode":"5690",
    "sg:province":"SA",
    "sg:tags":[
        "menswear"
    ],
    "wof:name":"Whitmarsh & Son",
    "wof:placetype":"venue"
},
  "geometry": {"coordinates":[133.67460632300001,-32.1261940002],"type":"Point"}
}