{
  "type": "Feature",
  "properties": {
    "addr:full":"6/ 40 Clyde St Kempsey NSW 2440",
    "addr:housenumber":"/ 40",
    "addr:postcode":"2440",
    "addr:street":"Clyde St",
    "iso:country":"AU",
    "sg:address":"6/ 40 Clyde St",
    "sg:city":"Kempsey",
    "sg:classifiers":[
        {
            "category":"Wholesale",
            "subcategory":"Painting Supplies",
            "type":"Manufacturing & Wholesale Goods"
        }
    ],
    "sg:phone":"+61 2 6562 4041",
    "sg:postcode":"2440",
    "sg:province":"NSW",
    "sg:tags":[
        "painter"
    ],
    "wof:name":"Belgrave Paint Specialists",
    "wof:placetype":"venue"
},
  "geometry": {"coordinates":[152.841171,-31.077667],"type":"Point"}
}