{
  "type": "Feature",
  "properties": {
    "addr:full":"2/ 35 Elmsfield Rd Midvale WA 6056",
    "addr:housenumber":"/ 35",
    "addr:postcode":"6056",
    "addr:street":"Elmsfield Rd",
    "iso:country":"AU",
    "sg:address":"2/ 35 Elmsfield Rd",
    "sg:city":"Midvale",
    "sg:classifiers":[
        {
            "category":"Home & Garden",
            "subcategory":"Furniture",
            "type":"Retail Goods"
        }
    ],
    "sg:phone":"+61 8 9274 4171",
    "sg:postcode":"6056",
    "sg:province":"WA",
    "sg:tags":[
        "outdoor"
    ],
    "wof:name":"Timber Living - Outdoor",
    "wof:placetype":"venue"
},
  "geometry": {"coordinates":[116.033706665,-31.8901157379],"type":"Point"}
}