{
  "type": "Feature",
  "properties": {
    "iso:country":"AU",
    "sg:address":"38 Moon St",
    "sg:city":"Eaglehawk",
    "sg:classifiers":[
        {
            "category":"Building & Trades",
            "subcategory":"Landscaping Services",
            "type":"Services"
        }
    ],
    "sg:phone":"+61 3 5446 7100",
    "sg:postcode":"3556",
    "sg:province":"VIC",
    "sg:tags":[
        "consultant"
    ],
    "wof:name":"Glynn Lewis",
    "wof:placetype":"venue"
},
  "geometry": {"coordinates":[144.245407105,-36.7048835754],"type":"Point"}
}