{
  "type": "Feature",
  "properties": {
    "iso:country":"AU",
    "sg:address":"99 Rookwood Rd",
    "sg:city":"Yagoona",
    "sg:classifiers":[
        {
            "category":"Shopping",
            "subcategory":"Stationery & Office Supplies",
            "type":"Retail Goods"
        }
    ],
    "sg:phone":"+61 2 9790 4026",
    "sg:postcode":"2199",
    "sg:province":"NSW",
    "sg:tags":[
        "packaging",
        "material"
    ],
    "wof:name":"Williamson MFG. Pty Ltd",
    "wof:placetype":"venue"
},
  "geometry": {"coordinates":[151.037094,-33.901398],"type":"Point"}
}