{
  "type": "Feature",
  "properties": {
    "addr:full":"115 Glebe Point Rd Glebe NSW 2037",
    "addr:housenumber":"115",
    "addr:postcode":"2037",
    "addr:street":"Glebe Point Rd",
    "iso:country":"AU",
    "sg:address":"115 Glebe Point Rd",
    "sg:city":"Glebe",
    "sg:classifiers":[
        {
            "category":"Shopping",
            "subcategory":"Antiques",
            "type":"Retail Goods"
        }
    ],
    "sg:phone":"+61 2 9660 0444",
    "sg:postcode":"2037",
    "sg:province":"NSW",
    "wof:name":"Antichita-The Niche of Time",
    "wof:placetype":"venue"
},
  "geometry": {"coordinates":[151.189743042,-33.8819694519],"type":"Point"}
}