{
  "type": "Feature",
  "properties": {
    "addr:full":"19 Middleten Rd Dee Why NSW 2099",
    "addr:housenumber":"19",
    "addr:postcode":"2099",
    "addr:street":"Middleten Rd",
    "iso:country":"AU",
    "sg:address":"19 Middleten Rd",
    "sg:city":"Dee Why",
    "sg:classifiers":[
        {
            "category":"Home & Garden",
            "subcategory":"Furniture",
            "type":"Retail Goods"
        }
    ],
    "sg:phone":"+61 2 9972 3026",
    "sg:postcode":"2099",
    "sg:province":"NSW",
    "sg:tags":[
        "outdoor"
    ],
    "wof:name":"Australian Squatters Chair",
    "wof:placetype":"venue"
},
  "geometry": {"coordinates":[151.282272339,-33.7347755432],"type":"Point"}
}