{
  "type": "Feature",
  "properties": {
    "addr:full":"11- 13 Halifax St Adelaide SA 5000",
    "addr:housenumber":"13",
    "addr:postcode":"5000",
    "addr:street":"Halifax St",
    "iso:country":"AU",
    "sg:address":"11- 13 Halifax St",
    "sg:city":"Adelaide",
    "sg:classifiers":[
        {
            "category":"Banks & Credit Unions",
            "subcategory":"Bank",
            "type":"Services"
        }
    ],
    "sg:phone":"+61 8 8212 4475",
    "sg:postcode":"5000",
    "sg:province":"SA",
    "sg:tags":[
        "broker",
        "mortgage"
    ],
    "wof:name":"CMO Finance",
    "wof:placetype":"venue"
},
  "geometry": {"coordinates":[138.60096740700001,-34.9330406189],"type":"Point"}
}