{
  "type": "Feature",
  "properties": {
    "addr:full":"155 Cathies La Wantirna VIC 3152",
    "addr:housenumber":"155",
    "addr:postcode":"3152",
    "addr:street":"Cathies La",
    "iso:country":"AU",
    "sg:address":"155 Cathies La",
    "sg:city":"Wantirna",
    "sg:classifiers":[
        {
            "category":"Building & Trades",
            "subcategory":"Landscaping Services",
            "type":"Services"
        }
    ],
    "sg:phone":"+61 3 9876 8152",
    "sg:postcode":"3152",
    "sg:province":"VIC",
    "sg:tags":[
        "stump",
        "tree",
        "felling",
        "removal"
    ],
    "wof:name":"Outer Eastern Tree Management P/L",
    "wof:placetype":"venue"
},
  "geometry": {"coordinates":[145.21548461899999,-37.8751220703],"type":"Point"}
}