{
  "type": "Feature",
  "properties": {
    "addr:full":"PO Box 3902 Weston ACT 2611",
    "addr:postcode":"2611",
    "iso:country":"AU",
    "sg:address":"PO Box 3902",
    "sg:city":"Weston",
    "sg:classifiers":[
        {
            "category":"Professional",
            "subcategory":"Art Services",
            "type":"Services"
        }
    ],
    "sg:phone":"+61 2 6287 1430",
    "sg:postcode":"2611",
    "sg:province":"ACT",
    "sg:tags":[
        "interior",
        "designer"
    ],
    "wof:name":"Spacelift Design Consultancy",
    "wof:placetype":"venue"
},
  "geometry": {"coordinates":[149.05569457999999,-35.3367500305],"type":"Point"}
}