{
  "type": "Feature",
  "properties": {
    "addr:full":"Unit 4 A / South Brisbane QLD 4101",
    "addr:postcode":"4101",
    "iso:country":"AU",
    "sg:address":"Unit 4",
    "sg:city":"A / South Brisbane",
    "sg:classifiers":[
        {
            "category":"Professional",
            "subcategory":"Computer Services",
            "type":"Services"
        }
    ],
    "sg:phone":"+61 7 3010 1388",
    "sg:postcode":"4101",
    "sg:province":"QLD",
    "sg:tags":[
        "repairs",
        "upgrade",
        "equipment"
    ],
    "wof:name":"Byte Power",
    "wof:placetype":"venue"
},
  "geometry": {"coordinates":[153.00184631400001,-27.4949531555],"type":"Point"}
}