{
  "type": "Feature",
  "properties": {
    "addr:full":"8 Otranto Ave Caloundra QLD 4551",
    "addr:housenumber":"8",
    "addr:postcode":"4551",
    "addr:street":"Otranto Ave",
    "iso:country":"AU",
    "sg:address":"8 Otranto Ave",
    "sg:city":"Caloundra",
    "sg:classifiers":[
        {
            "category":"Personal",
            "subcategory":"Beauty Salon",
            "type":"Services"
        }
    ],
    "sg:phone":"+61 7 5499 6100",
    "sg:postcode":"4551",
    "sg:province":"QLD",
    "sg:tags":[
        "hairdresser"
    ],
    "wof:name":"Creative Cuts",
    "wof:placetype":"venue"
},
  "geometry": {"coordinates":[153.130249023,-26.8043403625],"type":"Point"}
}