{
  "type": "Feature",
  "properties": {
    "addr:full":"Suite 2, Floor 1 Forster Shopping Village Breese P Forster NSW 2428",
    "addr:postcode":"2428",
    "addr:street":"Breese",
    "iso:country":"AU",
    "sg:address":"Suite 2, Floor 1 Forster Shopping Village Breese P",
    "sg:city":"Forster",
    "sg:classifiers":[
        {
            "category":"Health Services",
            "subcategory":"Dentist",
            "type":"Services"
        }
    ],
    "sg:phone":"+61 2 6555 8363",
    "sg:postcode":"2428",
    "sg:province":"NSW",
    "wof:name":"Smyth James",
    "wof:placetype":"venue"
},
  "geometry": {"coordinates":[152.52041600000001,-32.200291],"type":"Point"}
}