{
  "type": "Feature",
  "properties": {
    "iso:country":"AU",
    "sg:address":"Stirrat St",
    "sg:city":"Calliope",
    "sg:classifiers":[
        {
            "category":"Education",
            "subcategory":"School",
            "type":"Public Place"
        }
    ],
    "sg:phone":"+61 7 4975 8317",
    "sg:postcode":"4680",
    "sg:province":"QLD",
    "sg:tags":[
        "state",
        "except",
        "nsw"
    ],
    "wof:name":"Calliope Preschool",
    "wof:placetype":"venue"
},
  "geometry": {"coordinates":[151.20372009299999,-24.0046463013],"type":"Point"}
}