{
  "type": "Feature",
  "properties": {
    "addr:full":"153 Talbot Rd Hazelmere WA 6055",
    "addr:housenumber":"153",
    "addr:postcode":"6055",
    "addr:street":"Talbot Rd",
    "iso:country":"AU",
    "sg:address":"153 Talbot Rd",
    "sg:city":"Hazelmere",
    "sg:classifiers":[
        {
            "category":"Building & Trades",
            "subcategory":"Pest Control",
            "type":"Services"
        }
    ],
    "sg:phone":"+61 1800 035 691",
    "sg:postcode":"6055",
    "sg:province":"WA",
    "sg:tags":[
        "horse",
        "transport"
    ],
    "wof:name":"Interstate Horse Transport Service Pty Ltd",
    "wof:placetype":"venue"
},
  "geometry": {"coordinates":[116.01402299999999,-31.923685],"type":"Point"}
}