{
  "type": "Feature",
  "properties": {
    "iso:country":"AU",
    "sg:address":"Showroom 3/ 50 McEvoy St",
    "sg:city":"Waterloo",
    "sg:classifiers":[
        {
            "category":"Wholesale",
            "subcategory":"Apparel",
            "type":"Manufacturing & Wholesale Goods"
        }
    ],
    "sg:phone":"+61 2 9319 6892",
    "sg:postcode":"2017",
    "sg:province":"NSW",
    "sg:tags":[
        "wholesaler",
        "mfrs",
        "uniform"
    ],
    "wof:name":"Star Apparel",
    "wof:placetype":"venue"
},
  "geometry": {"coordinates":[151.20297241200001,-33.9011611938],"type":"Point"}
}