{
  "type": "Feature",
  "properties": {
    "addr:full":"Shop 3, food Court, Fountain Gate Shopping Cntr Fountain Gate VIC 3805",
    "addr:housenumber":"shop 3",
    "addr:postcode":"3805",
    "addr:street":"Food;Shopping",
    "iso:country":"AU",
    "sg:address":"Shop 3, food Court, Fountain Gate Shopping Cntr",
    "sg:city":"Fountain Gate",
    "sg:classifiers":[
        {
            "category":"Fast Food",
            "type":"Food & Drink"
        }
    ],
    "sg:phone":"+61 3 9705 1074",
    "sg:postcode":"3805",
    "sg:province":"VIC",
    "sg:tags":[
        "away",
        "take"
    ],
    "wof:name":"KFC",
    "wof:placetype":"venue"
},
  "geometry": {"coordinates":[145.295593,-38.014805],"type":"Point"}
}