{
  "type": "Feature",
  "properties": {
    "addr:full":"7 Wells St Frankston VIC 3199",
    "addr:housenumber":"7",
    "addr:postcode":"3199",
    "addr:street":"Wells St",
    "iso:country":"AU",
    "sg:address":"7 Wells St",
    "sg:city":"Frankston",
    "sg:classifiers":[
        {
            "category":"Fast Food",
            "type":"Food & Drink"
        }
    ],
    "sg:phone":"+61 3 9781 4344",
    "sg:postcode":"3199",
    "sg:province":"VIC",
    "sg:tags":[
        "away",
        "take"
    ],
    "wof:name":"Mayur Curry Pot",
    "wof:placetype":"venue"
},
  "geometry": {"coordinates":[145.088546753,-37.8187332153],"type":"Point"}
}