{
  "type": "Feature",
  "properties": {
    "addr:full":"23 Wagner Rd Neerim South VIC 3831",
    "addr:housenumber":"23",
    "addr:postcode":"3831",
    "addr:street":"Wagner Rd",
    "iso:country":"AU",
    "sg:address":"23 Wagner Rd",
    "sg:city":"Neerim South",
    "sg:classifiers":[
        {
            "category":"Shopping",
            "subcategory":"Music",
            "type":"Retail Goods"
        }
    ],
    "sg:phone":"+61 417 535 067",
    "sg:postcode":"3831",
    "sg:province":"VIC",
    "sg:tags":[
        "instrument",
        "musical"
    ],
    "wof:name":"Adam Sheehan Music",
    "wof:placetype":"venue"
},
  "geometry": {"coordinates":[145.950928,-38.017326],"type":"Point"}
}