{
  "type": "Feature",
  "properties": {
    "iso:country":"AU",
    "sg:address":"74 Pepperina Drv",
    "sg:city":"Stockleigh",
    "sg:classifiers":[
        {
            "category":"Health Services",
            "subcategory":"Health Practitioner",
            "type":"Services"
        }
    ],
    "sg:phone":"+61 7 5546 3680",
    "sg:postcode":"4280",
    "sg:province":"QLD",
    "sg:tags":[
        "pathologist",
        "speech"
    ],
    "wof:name":"Maree Castle Speech Therapy",
    "wof:placetype":"venue"
},
  "geometry": {"coordinates":[153.08038300000001,-27.77186],"type":"Point"}
}