{
  "type": "Feature",
  "properties": {
    "addr:full":"Shop 13 Southside Shopping Village Charlotte Cl Woree QLD 4868",
    "addr:housenumber":"shop 13",
    "addr:postcode":"4868",
    "addr:street":"Southside;Cl Woree",
    "iso:country":"AU",
    "sg:address":"Shop 13 Southside Shopping Village Charlotte Cl",
    "sg:city":"Woree",
    "sg:classifiers":[
        {
            "category":"Personal",
            "subcategory":"Massage",
            "type":"Services"
        }
    ],
    "sg:phone":"+61 7 4033 7255",
    "sg:postcode":"4868",
    "sg:province":"QLD",
    "sg:tags":[
        "therapy"
    ],
    "wof:name":"Body & Beauty Unlimited",
    "wof:placetype":"venue"
},
  "geometry": {"coordinates":[145.74688720699999,-16.954410553],"type":"Point"}
}