{
  "type": "Feature",
  "properties": {
    "addr:full":"311 Healesville Yarra Glen Rd Yarra Glen VIC 3775",
    "addr:housenumber":"311",
    "addr:postcode":"3775",
    "addr:street":"Healesville Yarra Glen Rd",
    "iso:country":"AU",
    "sg:address":"311 Healesville Yarra Glen Rd",
    "sg:city":"Yarra Glen",
    "sg:classifiers":[
        {
            "category":"Farming",
            "subcategory":"Vineyard",
            "type":"Manufacturing & Wholesale Goods"
        }
    ],
    "sg:phone":"+61 3 5962 3311",
    "sg:postcode":"3775",
    "sg:province":"VIC",
    "sg:tags":[
        "winery"
    ],
    "wof:name":"Tarrawarra Estate",
    "wof:placetype":"venue"
},
  "geometry": {"coordinates":[145.37704500000001,-37.658604],"type":"Point"}
}