{
  "type": "Feature",
  "properties": {
    "addr:full":"21 Victoria Crs Mt Barker SA 5251",
    "addr:housenumber":"21",
    "addr:postcode":"5251",
    "addr:street":"Victoria Crs Mt",
    "iso:country":"AU",
    "sg:address":"21 Victoria Crs",
    "sg:city":"Mt Barker",
    "sg:classifiers":[
        {
            "category":"Food & Beverages",
            "subcategory":"Bakery",
            "type":"Retail Goods"
        }
    ],
    "sg:phone":"+61 8 8398 2044",
    "sg:postcode":"5251",
    "sg:province":"SA",
    "sg:tags":[
        "baker"
    ],
    "wof:name":"Brezel Bakehouse",
    "wof:placetype":"venue"
},
  "geometry": {"coordinates":[138.867721558,-35.0779762268],"type":"Point"}
}