{
  "type": "Feature",
  "properties": {
    "addr:full":"68 Frederick St Merewether NSW 2291",
    "addr:housenumber":"68",
    "addr:postcode":"2291",
    "addr:street":"Frederick St",
    "iso:country":"AU",
    "sg:address":"68 Frederick St",
    "sg:city":"Merewether",
    "sg:classifiers":[
        {
            "category":"Autos & Motor Vehicles",
            "subcategory":"Auto Supplies",
            "type":"Retail Goods"
        }
    ],
    "sg:phone":"+61 2 4963 6106",
    "sg:postcode":"2291",
    "sg:province":"NSW",
    "sg:tags":[
        "oil",
        "spirit"
    ],
    "wof:name":"Lubrication Engineers Pty. Ltd.",
    "wof:placetype":"venue"
},
  "geometry": {"coordinates":[151.756103516,-32.9469680786],"type":"Point"}
}