{
  "type": "Feature",
  "properties": {
    "iso:country":"AU",
    "sg:address":"PO Box 1440",
    "sg:city":"Runaway Bay",
    "sg:phone":"+61 407 531 432",
    "sg:postcode":"4216",
    "sg:province":"QLD",
    "wof:name":"TAD Rainwater Tanks Pty Ltd",
    "wof:placetype":"venue"
},
  "geometry": {"coordinates":[153.403930664,-27.9242191315],"type":"Point"}
}