{
  "type": "Feature",
  "properties": {
    "addr:full":"Great Alpine Rd Swifts Creek VIC 3896",
    "addr:postcode":"3896",
    "addr:street":"Alpine Rd",
    "iso:country":"AU",
    "sg:address":"Great Alpine Rd",
    "sg:city":"Swifts Creek",
    "sg:classifiers":[
        {
            "category":"Education",
            "subcategory":"School",
            "type":"Public Place"
        }
    ],
    "sg:phone":"+61 3 5159 4267",
    "sg:postcode":"3896",
    "sg:province":"VIC",
    "sg:tags":[
        "state",
        "except",
        "nsw"
    ],
    "wof:name":"Swifts Creek Primary School",
    "wof:placetype":"venue"
},
  "geometry": {"coordinates":[147.72187805199999,-37.2637062073],"type":"Point"}
}