{
  "type": "Feature",
  "properties": {
    "iso:country":"AU",
    "sg:address":"105 High St",
    "sg:city":"Fremantle",
    "sg:classifiers":[
        {
            "category":"Shopping",
            "subcategory":"Clothing, Apparel, & Fashions",
            "type":"Retail Goods"
        }
    ],
    "sg:phone":"+61 8 9335 1289",
    "sg:postcode":"6160",
    "sg:province":"WA",
    "sg:tags":[
        "sportswear"
    ],
    "wof:name":"Fluid Surf Shop",
    "wof:placetype":"venue"
},
  "geometry": {"coordinates":[115.744179,-32.055069],"type":"Point"}
}