{
  "type": "Feature",
  "properties": {
    "addr:full":"Fcty 2/ 23 Simcock St Somerville VIC 3912",
    "addr:housenumber":"/ 23",
    "addr:postcode":"3912",
    "addr:street":"Simcock St",
    "iso:country":"AU",
    "sg:address":"Fcty 2/ 23 Simcock St",
    "sg:city":"Somerville",
    "sg:classifiers":[
        {
            "category":"Retail",
            "subcategory":"Auto Repair",
            "type":"Services"
        }
    ],
    "sg:phone":"+61 3 5977 7112",
    "sg:postcode":"3912",
    "sg:province":"VIC",
    "sg:tags":[
        "repairer",
        "motor",
        "engineer"
    ],
    "wof:name":"Exedon Motors",
    "wof:placetype":"venue"
},
  "geometry": {"coordinates":[145.18121337900001,-38.221446991],"type":"Point"}
}