{
  "type": "Feature",
  "properties": {
    "iso:country":"AU",
    "sg:address":"Ste11/ 87 Mclarty Ave",
    "sg:city":"Joondalup",
    "sg:classifiers":[
        {
            "category":"Banks & Credit Unions",
            "subcategory":"Investment Brokerage",
            "type":"Services"
        }
    ],
    "sg:phone":"+61 8 9301 0200",
    "sg:postcode":"6027",
    "sg:province":"WA",
    "sg:tags":[
        "finance",
        "broker"
    ],
    "wof:name":"All Seasons Finance",
    "wof:placetype":"venue"
},
  "geometry": {"coordinates":[115.767486572,-31.7408390045],"type":"Point"}
}