{
  "type": "Feature",
  "properties": {
    "iso:country":"AU",
    "sg:address":"31 Clark St",
    "sg:city":"Wangaratta",
    "sg:classifiers":[
        {
            "category":"Health Services",
            "subcategory":"Dentist",
            "type":"Services"
        }
    ],
    "sg:phone":"+61 3 5721 7411",
    "sg:postcode":"3677",
    "sg:province":"VIC",
    "sg:tags":[
        "dental",
        "prosthetist"
    ],
    "wof:name":"Kenmac Denture Clinic",
    "wof:placetype":"venue"
},
  "geometry": {"coordinates":[146.312988281,-36.3493728638],"type":"Point"}
}