{
  "type": "Feature",
  "properties": {
    "addr:full":"13 Binnia St Coolah NSW 2843",
    "addr:housenumber":"13",
    "addr:postcode":"2843",
    "addr:street":"Binnia St",
    "iso:country":"AU",
    "sg:address":"13 Binnia St",
    "sg:city":"Coolah",
    "sg:classifiers":[
        {
            "category":"Education",
            "subcategory":"School",
            "type":"Public Place"
        }
    ],
    "sg:phone":"+61 2 6377 1101",
    "sg:postcode":"2843",
    "sg:province":"NSW",
    "sg:tags":[
        "state",
        "-",
        "nsw"
    ],
    "wof:name":"Coolah Central School",
    "wof:placetype":"venue"
},
  "geometry": {"coordinates":[149.72242700000001,-31.822653],"type":"Point"}
}