{
  "type": "Feature",
  "properties": {
    "addr:full":"PO Box 765 Paddington QLD 4064",
    "addr:postcode":"4064",
    "iso:country":"AU",
    "sg:address":"PO Box 765",
    "sg:city":"Paddington",
    "sg:classifiers":[
        {
            "category":"Professional",
            "subcategory":"Art Services",
            "type":"Services"
        }
    ],
    "sg:phone":"+61 7 3300 0066",
    "sg:postcode":"4064",
    "sg:province":"QLD",
    "sg:tags":[
        "graphic",
        "designer"
    ],
    "wof:name":"Charcoal Design",
    "wof:placetype":"venue"
},
  "geometry": {"coordinates":[153.00668335,-27.4619503021],"type":"Point"}
}