{
  "type": "Feature",
  "properties": {
    "addr:full":"7 Mineral Rd Oak Flats NSW 2529",
    "addr:housenumber":"7",
    "addr:postcode":"2529",
    "addr:street":"Mineral Rd",
    "iso:country":"AU",
    "sg:address":"7 Mineral Rd",
    "sg:city":"Oak Flats",
    "sg:classifiers":[
        {
            "category":"Retail",
            "subcategory":"Auto Repair",
            "type":"Services"
        }
    ],
    "sg:phone":"+61 2 4257 5969",
    "sg:postcode":"2529",
    "sg:province":"NSW",
    "sg:tags":[
        "repairer",
        "motor",
        "engineer"
    ],
    "wof:name":"Shellharbour City Automotive",
    "wof:placetype":"venue"
},
  "geometry": {"coordinates":[150.810348511,-34.5658760071],"type":"Point"}
}