{
  "type": "Feature",
  "properties": {
    "iso:country":"AU",
    "sg:address":"PO Box 6009",
    "sg:city":"Maroochydore BC",
    "sg:classifiers":[
        {
            "category":"Building & Trades",
            "subcategory":"Construction",
            "type":"Services"
        }
    ],
    "sg:phone":"+61 439 078 237",
    "sg:postcode":"4558",
    "sg:province":"QLD",
    "sg:tags":[
        "contractor"
    ],
    "wof:name":"Avid Homes",
    "wof:placetype":"venue"
},
  "geometry": {"coordinates":[153.09274292000001,-26.6657295227],"type":"Point"}
}