{
  "type": "Feature",
  "properties": {
    "iso:country":"AU",
    "sg:address":"49 Nicholson St",
    "sg:city":"Footscray",
    "sg:classifiers":[
        {
            "category":"Personal",
            "type":"Services"
        }
    ],
    "sg:phone":"+61 3 9689 5533",
    "sg:postcode":"3011",
    "sg:province":"VIC",
    "sg:tags":[
        "counselling",
        "alcohol",
        "drug"
    ],
    "wof:name":"Westadd Inc.",
    "wof:placetype":"venue"
},
  "geometry": {"coordinates":[144.900115967,-37.7976417542],"type":"Point"}
}