{
  "type": "Feature",
  "properties": {
    "addr:full":"University Rd Annandale QLD 4814",
    "addr:postcode":"4814",
    "addr:street":"University Rd",
    "iso:country":"AU",
    "sg:address":"University Rd",
    "sg:city":"Annandale",
    "sg:classifiers":[
        {
            "category":"Health Services",
            "subcategory":"Nursing And Care Facility",
            "type":"Services"
        }
    ],
    "sg:phone":"+61 7 4772 9900",
    "sg:postcode":"4814",
    "sg:province":"QLD",
    "sg:tags":[
        "home"
    ],
    "sg:website":"http://www.tgsh.org.au",
    "wof:name":"The Good Shepherd Home Townsville",
    "wof:placetype":"venue"
},
  "geometry": {"coordinates":[146.81144699999999,-19.317696],"type":"Point"}
}