{
  "type": "Feature",
  "properties": {
    "addr:full":"Patterson St Matraville NSW 2036",
    "addr:postcode":"2036",
    "addr:street":"Patterson St",
    "iso:country":"AU",
    "sg:address":"Patterson St",
    "sg:city":"Matraville",
    "sg:classifiers":[
        {
            "category":"Building & Trades",
            "subcategory":"Plumbing",
            "type":"Services"
        }
    ],
    "sg:phone":"+61 2 9311 4100",
    "sg:postcode":"2036",
    "sg:province":"NSW",
    "sg:tags":[
        "plumber",
        "gasfitters"
    ],
    "wof:name":"Gerabong Plumbing Pty Ltd",
    "wof:placetype":"venue"
},
  "geometry": {"coordinates":[151.23385620100001,-33.9593734741],"type":"Point"}
}