{
  "type": "Feature",
  "properties": {
    "iso:country":"AU",
    "sg:address":"38 Western Rd",
    "sg:city":"Cohuna",
    "sg:classifiers":[
        {
            "category":"Retail",
            "subcategory":"Auto Repair",
            "type":"Services"
        }
    ],
    "sg:phone":"+61 3 5456 2044",
    "sg:postcode":"3568",
    "sg:province":"VIC",
    "sg:tags":[
        "repairer",
        "motor",
        "engineer"
    ],
    "wof:name":"Bruce Johnson Service Centre",
    "wof:placetype":"venue"
},
  "geometry": {"coordinates":[144.20980835,-35.8050460815],"type":"Point"}
}