{
  "type": "Feature",
  "properties": {
    "addr:full":"78 Duke St Roma QLD 4455",
    "addr:housenumber":"78",
    "addr:postcode":"4455",
    "addr:street":"Duke St",
    "iso:country":"AU",
    "sg:address":"78 Duke St",
    "sg:city":"Roma",
    "sg:classifiers":[
        {
            "category":"Commercial Area",
            "type":"Public Place"
        }
    ],
    "sg:phone":"+61 7 4622 3955",
    "sg:postcode":"4455",
    "sg:province":"QLD",
    "sg:tags":[
        "heavy",
        "carrier"
    ],
    "wof:name":"Kurtz Transport Pty Ltd",
    "wof:placetype":"venue"
},
  "geometry": {"coordinates":[148.78099060100001,-26.5756835938],"type":"Point"}
}