{
  "type": "Feature",
  "properties": {
    "addr:full":"Ste 7, John James Medical Cntr 175 Strickland Crs Deakin ACT 2600",
    "addr:housenumber":"175",
    "addr:postcode":"2600",
    "addr:street":"Strickland Crs",
    "iso:country":"AU",
    "sg:address":"Ste 7, John James Medical Cntr 175 Strickland Crs",
    "sg:city":"Deakin",
    "sg:classifiers":[
        {
            "category":"Health Services",
            "subcategory":"Doctor",
            "type":"Services"
        }
    ],
    "sg:phone":"+61 2 6285 1866",
    "sg:postcode":"2600",
    "sg:province":"ACT",
    "sg:tags":[
        "medical",
        "practitioner"
    ],
    "wof:name":"Hurwitz M Dr",
    "wof:placetype":"venue"
},
  "geometry": {"coordinates":[149.103347778,-35.3408889771],"type":"Point"}
}