{
  "type": "Feature",
  "properties": {
    "iso:country":"AU",
    "sg:address":"9 Fyans St",
    "sg:city":"Geelong",
    "sg:classifiers":[
        {
            "category":"Building & Trades",
            "subcategory":"Plumbing",
            "type":"Services"
        }
    ],
    "sg:phone":"+61 3 5229 7006",
    "sg:postcode":"3220",
    "sg:province":"VIC",
    "sg:tags":[
        "consultant"
    ],
    "wof:name":"Little G & Y Pty Ltd",
    "wof:placetype":"venue"
},
  "geometry": {"coordinates":[144.35119599999999,-38.160725],"type":"Point"}
}