{
  "type": "Feature",
  "properties": {
    "iso:country":"AU",
    "sg:address":"8 Railway St",
    "sg:city":"Lowood",
    "sg:classifiers":[
        {
            "category":"Shopping",
            "subcategory":"Crafts & Fabrics",
            "type":"Retail Goods"
        }
    ],
    "sg:phone":"+61 7 5426 1332",
    "sg:postcode":"4311",
    "sg:province":"QLD",
    "sg:tags":[
        "supply"
    ],
    "wof:name":"Folk Art Co-operative Society Ltd",
    "wof:placetype":"venue"
},
  "geometry": {"coordinates":[152.582199097,-27.4633274078],"type":"Point"}
}