{
  "type": "Feature",
  "properties": {
    "iso:country":"AU",
    "sg:address":"1 Leigh Drv",
    "sg:city":"Pakenham",
    "sg:classifiers":[
        {
            "category":"Food & Beverages",
            "subcategory":"Groceries & Convenience Stores",
            "type":"Retail Goods"
        }
    ],
    "sg:phone":"+61 3 5940 2559",
    "sg:postcode":"3810",
    "sg:province":"VIC",
    "wof:name":"Pakenham Hills General Store",
    "wof:placetype":"venue"
},
  "geometry": {"coordinates":[145.497467,-38.060368],"type":"Point"}
}