{
  "type": "Feature",
  "properties": {
    "addr:full":"2a George St Hindmarsh SA 5007",
    "addr:housenumber":"2a",
    "addr:postcode":"5007",
    "addr:street":"George St",
    "iso:country":"AU",
    "sg:address":"2a George St",
    "sg:city":"Hindmarsh",
    "sg:classifiers":[
        {
            "category":"Professional",
            "type":"Services"
        }
    ],
    "sg:phone":"+61 8 8340 8340",
    "sg:postcode":"5007",
    "sg:province":"SA",
    "sg:tags":[
        "mail",
        "contractor"
    ],
    "wof:name":"Adelaide Business Bureaux",
    "wof:placetype":"venue"
},
  "geometry": {"coordinates":[138.56893920900001,-34.9042282104],"type":"Point"}
}