{
  "type": "Feature",
  "properties": {
    "addr:full":"AIMMS, 308A Pultney St Adelaide SA 5000",
    "addr:housenumber":"308a",
    "addr:postcode":"5000",
    "addr:street":"Aimms;Pultney St",
    "iso:country":"AU",
    "sg:address":"AIMMS, 308A Pultney St",
    "sg:city":"Adelaide",
    "sg:classifiers":[
        {
            "category":"Education",
            "subcategory":"Special Training",
            "type":"Public Place"
        }
    ],
    "sg:phone":"+61 8 8223 5888",
    "sg:postcode":"5000",
    "sg:province":"SA",
    "sg:tags":[
        "drama",
        "speech",
        "speaking",
        "tuition"
    ],
    "wof:name":"Pembo Goes Public",
    "wof:placetype":"venue"
},
  "geometry": {"coordinates":[138.60635375999999,-34.9308700562],"type":"Point"}
}