{
  "type": "Feature",
  "properties": {
    "addr:full":"6 Hilliard St Gladstone QLD 4680",
    "addr:housenumber":"6",
    "addr:postcode":"4680",
    "addr:street":"Hilliard St",
    "iso:country":"AU",
    "sg:address":"6 Hilliard St",
    "sg:city":"Gladstone",
    "sg:classifiers":[
        {
            "category":"Building & Trades",
            "subcategory":"Construction",
            "type":"Services"
        }
    ],
    "sg:phone":"+61 417 725 099",
    "sg:postcode":"4680",
    "sg:province":"QLD",
    "sg:tags":[
        "welding"
    ],
    "wof:name":"Trevor Watson Fabrications",
    "wof:placetype":"venue"
},
  "geometry": {"coordinates":[151.24266052199999,-23.8430938721],"type":"Point"}
}