{
  "type": "Feature",
  "properties": {
    "iso:country":"AU",
    "sg:address":"Level 1/ 56 Norton St",
    "sg:city":"Leichhardt",
    "sg:classifiers":[
        {
            "category":"Health Services",
            "subcategory":"Health Practitioner",
            "type":"Services"
        }
    ],
    "sg:phone":"+61 2 9569 2533",
    "sg:postcode":"2040",
    "sg:province":"NSW",
    "sg:tags":[
        "acupuncture"
    ],
    "wof:name":"GSR Naturopathic Clinic",
    "wof:placetype":"venue"
},
  "geometry": {"coordinates":[151.157242,-33.886127],"type":"Point"}
}