{
  "type": "Feature",
  "properties": {
    "iso:country":"AU",
    "sg:address":"PO Box 149",
    "sg:city":"Horsham",
    "sg:classifiers":[
        {
            "category":"Farming",
            "subcategory":"Farm & Veterinary Services",
            "type":"Manufacturing & Wholesale Goods"
        }
    ],
    "sg:phone":"+61 428 405 261",
    "sg:postcode":"3402",
    "sg:province":"VIC",
    "sg:tags":[
        "contracting"
    ],
    "wof:name":"Clean Grain",
    "wof:placetype":"venue"
},
  "geometry": {"coordinates":[142.20489501899999,-36.7117118835],"type":"Point"}
}