{
  "type": "Feature",
  "properties": {
    "addr:full":"PO Box 3806 Weston Creek ACT 2611",
    "addr:postcode":"2611",
    "iso:country":"AU",
    "sg:address":"PO Box 3806",
    "sg:city":"Weston Creek",
    "sg:classifiers":[
        {
            "category":"Education",
            "subcategory":"Special Training",
            "type":"Public Place"
        }
    ],
    "sg:phone":"+61 2 6285 3244",
    "sg:postcode":"2611",
    "sg:province":"ACT",
    "sg:tags":[
        "development"
    ],
    "wof:name":"Chris Adams & Associates",
    "wof:placetype":"venue"
},
  "geometry": {"coordinates":[149.03364563,-35.2974281311],"type":"Point"}
}