{
  "type": "Feature",
  "properties": {
    "addr:full":"264 Main Rd East St Albans VIC 3021",
    "addr:housenumber":"264",
    "addr:postcode":"3021",
    "addr:street":"Main Rd East",
    "iso:country":"AU",
    "sg:address":"264 Main Rd East St",
    "sg:city":"Albans",
    "sg:classifiers":[
        {
            "category":"Health Services",
            "subcategory":"Doctor",
            "type":"Services"
        }
    ],
    "sg:phone":"+61 3 9367 1122",
    "sg:postcode":"3021",
    "sg:province":"VIC",
    "sg:tags":[
        "medical",
        "practitioner"
    ],
    "wof:name":"Maria Wegrzynowski Dr",
    "wof:placetype":"venue"
},
  "geometry": {"coordinates":[144.805206,-37.744717],"type":"Point"}
}