{
  "type": "Feature",
  "properties": {
    "addr:full":"118 Link Rd Victoria Point QLD 4165",
    "addr:housenumber":"118",
    "addr:postcode":"4165",
    "addr:street":"Link Rd",
    "iso:country":"AU",
    "sg:address":"118 Link Rd",
    "sg:city":"Victoria Point",
    "sg:classifiers":[
        {
            "category":"Banks & Credit Unions",
            "subcategory":"Investment Brokerage",
            "type":"Services"
        }
    ],
    "sg:phone":"+61 7 3820 7253",
    "sg:postcode":"4165",
    "sg:province":"QLD",
    "sg:tags":[
        "care",
        "day",
        "family",
        "child"
    ],
    "wof:name":"FirstLearnings Victoria Point",
    "wof:placetype":"venue"
},
  "geometry": {"coordinates":[153.29461669899999,-27.5862121582],"type":"Point"}
}