{
  "type": "Feature",
  "properties": {
    "iso:country":"AU",
    "sg:address":"34- 38 Christie St",
    "sg:city":"St Marys",
    "sg:classifiers":[
        {
            "category":"Building & Trades",
            "subcategory":"Cleaning & Sanitation",
            "type":"Services"
        }
    ],
    "sg:phone":"+61 2 9673 6677",
    "sg:postcode":"2760",
    "sg:province":"NSW",
    "sg:tags":[
        "grease",
        "trap"
    ],
    "sg:website":"http://www.remondis.com.au",
    "wof:name":"REMONDIS Sydney Liquid Waste Pty Ltd",
    "wof:placetype":"venue"
},
  "geometry": {"coordinates":[150.77145385700001,-33.7473716736],"type":"Point"}
}