{
  "type": "Feature",
  "properties": {
    "addr:full":"551 Ruthven St Toowoomba QLD 4350",
    "addr:housenumber":"551",
    "addr:postcode":"4350",
    "addr:street":"Ruthven St",
    "iso:country":"AU",
    "sg:address":"551 Ruthven St",
    "sg:city":"Toowoomba",
    "sg:classifiers":[
        {
            "category":"Banks & Credit Unions",
            "subcategory":"Investment Brokerage",
            "type":"Services"
        }
    ],
    "sg:phone":"+61 7 4638 2522",
    "sg:postcode":"4350",
    "sg:province":"QLD",
    "sg:tags":[
        "finance",
        "broker"
    ],
    "wof:name":"Capitalcorp Financial Services",
    "wof:placetype":"venue"
},
  "geometry": {"coordinates":[151.952316,-27.568096],"type":"Point"}
}