{
  "type": "Feature",
  "properties": {
    "addr:full":"8 Hyson Crt Carrum Downs VIC 3201",
    "addr:housenumber":"8",
    "addr:postcode":"3201",
    "addr:street":"Hyson Crt",
    "iso:country":"AU",
    "sg:address":"8 Hyson Crt",
    "sg:city":"Carrum Downs",
    "sg:classifiers":[
        {
            "category":"Retail",
            "subcategory":"Repair Shop",
            "type":"Services"
        }
    ],
    "sg:phone":"+61 3 9782 1455",
    "sg:postcode":"3201",
    "sg:province":"VIC",
    "sg:tags":[
        "machine",
        "sewing"
    ],
    "wof:name":"E & W Sewing Machines",
    "wof:placetype":"venue"
},
  "geometry": {"coordinates":[145.19418300000001,-38.103981],"type":"Point"}
}