{
  "type": "Feature",
  "properties": {
    "addr:full":"Unit 1/ 39 Eddy Rd Minchinbury NSW 2770",
    "addr:housenumber":"39",
    "addr:postcode":"2770",
    "addr:street":"Eddy Rd",
    "iso:country":"AU",
    "sg:address":"Unit 1/ 39 Eddy Rd",
    "sg:city":"Minchinbury",
    "sg:classifiers":[
        {
            "category":"Utilities",
            "type":"Services"
        }
    ],
    "sg:phone":"+61 2 9675 7574",
    "sg:postcode":"2770",
    "sg:province":"NSW",
    "sg:tags":[
        "refrigeration",
        "industrial",
        "commercial",
        "retail"
    ],
    "wof:name":"Ultra Refigeration Pty Ltd",
    "wof:placetype":"venue"
},
  "geometry": {"coordinates":[150.79742431599999,-33.7904434204],"type":"Point"}
}