{
  "type": "Feature",
  "properties": {
    "addr:full":"1302 Glen St Milsons Point NSW 2061",
    "addr:housenumber":"1302",
    "addr:postcode":"2061",
    "addr:street":"Glen St",
    "iso:country":"AU",
    "sg:address":"1302 Glen St",
    "sg:city":"Milsons Point",
    "sg:classifiers":[
        {
            "category":"Professional",
            "subcategory":"Business Services",
            "type":"Services"
        }
    ],
    "sg:phone":"+61 2 9922 7322",
    "sg:postcode":"2061",
    "sg:province":"NSW",
    "sg:tags":[
        "exporter"
    ],
    "wof:name":"Je - Jet Pty Ltd",
    "wof:placetype":"venue"
},
  "geometry": {"coordinates":[151.21061706500001,-33.8473205566],"type":"Point"}
}