{
  "type": "Feature",
  "properties": {
    "addr:full":"Suite 3/ 17 Waterloo St Cleveland QLD 4163",
    "addr:housenumber":"17",
    "addr:postcode":"4163",
    "addr:street":"Waterloo St",
    "iso:country":"AU",
    "sg:address":"Suite 3/ 17 Waterloo St",
    "sg:city":"Cleveland",
    "sg:classifiers":[
        {
            "category":"Health Services",
            "subcategory":"Dentist",
            "type":"Services"
        }
    ],
    "sg:phone":"+61 7 3821 3900",
    "sg:postcode":"4163",
    "sg:province":"QLD",
    "sg:tags":[
        "technician",
        "dental"
    ],
    "wof:name":"Davis Mark",
    "wof:placetype":"venue"
},
  "geometry": {"coordinates":[153.26487731899999,-27.5269565582],"type":"Point"}
}