{
  "type": "Feature",
  "properties": {
    "addr:full":"PO Box 459 Hyde Park QLD 4812",
    "addr:postcode":"4812",
    "iso:country":"AU",
    "sg:address":"PO Box 459",
    "sg:city":"Hyde Park",
    "sg:classifiers":[
        {
            "category":"Shopping",
            "subcategory":"Pets & Pet Supplies",
            "type":"Retail Goods"
        }
    ],
    "sg:phone":"+61 7 4778 4918",
    "sg:postcode":"4812",
    "sg:province":"QLD",
    "sg:tags":[
        "food"
    ],
    "wof:name":"Cluden Pet Motel",
    "wof:placetype":"venue"
},
  "geometry": {"coordinates":[146.79513499999999,-19.27693],"type":"Point"}
}