{
  "type": "Feature",
  "properties": {
    "addr:full":"200 Summer St Orange NSW 2800",
    "addr:housenumber":"200",
    "addr:postcode":"2800",
    "addr:street":"Summer St",
    "iso:country":"AU",
    "sg:address":"200 Summer St",
    "sg:city":"Orange",
    "sg:classifiers":[
        {
            "category":"Personal",
            "subcategory":"Beauty Salon",
            "type":"Services"
        }
    ],
    "sg:phone":"+61 2 6362 1014",
    "sg:postcode":"2800",
    "sg:province":"NSW",
    "sg:tags":[
        "hairdresser"
    ],
    "wof:name":"Iko Iko Hair",
    "wof:placetype":"venue"
},
  "geometry": {"coordinates":[149.10125732399999,-33.2839202881],"type":"Point"}
}