{
  "type": "Feature",
  "properties": {
    "iso:country":"AU",
    "sg:address":"PO Box 135",
    "sg:city":"Baxter",
    "sg:classifiers":[
        {
            "category":"Professional",
            "subcategory":"Computer Services",
            "type":"Services"
        }
    ],
    "sg:phone":"+61 3 5971 4315",
    "sg:postcode":"3911",
    "sg:province":"VIC",
    "sg:tags":[
        "package",
        "software"
    ],
    "wof:name":"Hammock Enterprises",
    "wof:placetype":"venue"
},
  "geometry": {"coordinates":[145.16244506800001,-38.1893081665],"type":"Point"}
}