{
  "type": "Feature",
  "properties": {
    "addr:full":"500 Churchill Rd Kilburn SA 5084",
    "addr:housenumber":"500",
    "addr:postcode":"5084",
    "addr:street":"Churchill Rd",
    "iso:country":"AU",
    "sg:address":"500 Churchill Rd",
    "sg:city":"Kilburn",
    "sg:classifiers":[
        {
            "category":"Bars & Pubs",
            "subcategory":"Lounge",
            "type":"Food & Drink"
        }
    ],
    "sg:phone":"+61 8 8359 5635",
    "sg:postcode":"5084",
    "sg:province":"SA",
    "sg:tags":[
        "water",
        "filter",
        "drinking"
    ],
    "wof:name":"Culligan",
    "wof:placetype":"venue"
},
  "geometry": {"coordinates":[138.58297729500001,-34.8552246094],"type":"Point"}
}