{
  "type": "Feature",
  "properties": {
    "iso:country":"AU",
    "sg:address":"2 Goodwin St",
    "sg:city":"East Ipswich",
    "sg:classifiers":[
        {
            "category":"Health Services",
            "subcategory":"Health Practitioner",
            "type":"Services"
        }
    ],
    "sg:phone":"+61 7 3812 4171",
    "sg:postcode":"4305",
    "sg:province":"QLD",
    "sg:tags":[
        "naturopath"
    ],
    "wof:name":"Healthnette - Health & Wellness Clinics",
    "wof:placetype":"venue"
},
  "geometry": {"coordinates":[152.772903442,-27.6035404205],"type":"Point"}
}