{
  "type": "Feature",
  "properties": {
    "addr:full":"Highgate St Auburn NSW 2144",
    "addr:postcode":"2144",
    "addr:street":"Highgate St",
    "iso:country":"AU",
    "sg:address":"Highgate St",
    "sg:city":"Auburn",
    "sg:classifiers":[
        {
            "category":"Military Area",
            "subcategory":"Army Base",
            "type":"Public Place"
        }
    ],
    "sg:phone":"+61 2 9395 1555",
    "sg:postcode":"2144",
    "sg:province":"NSW",
    "sg:tags":[
        "wholesaler",
        "mfrs",
        "cement",
        "supply"
    ],
    "wof:name":"Melcann Limited",
    "wof:placetype":"venue"
},
  "geometry": {"coordinates":[151.02940368599999,-33.8411026001],"type":"Point"}
}