{
  "type": "Feature",
  "properties": {
    "addr:full":"33 Wattleblossom Rd Warrandyte VIC 3113",
    "addr:housenumber":"33",
    "addr:postcode":"3113",
    "addr:street":"Wattleblossom Rd",
    "iso:country":"AU",
    "sg:address":"33 Wattleblossom Rd",
    "sg:city":"Warrandyte",
    "sg:classifiers":[
        {
            "category":"Building & Trades",
            "subcategory":"Construction",
            "type":"Services"
        }
    ],
    "sg:phone":"+61 3 9844 2105",
    "sg:postcode":"3113",
    "sg:province":"VIC",
    "sg:tags":[
        "contractor"
    ],
    "wof:name":"McHugh J",
    "wof:placetype":"venue"
},
  "geometry": {"coordinates":[145.22967529300001,-37.7435760498],"type":"Point"}
}