{
  "type": "Feature",
  "properties": {
    "addr:full":"12 Larissa Ave Ringwood VIC 3134",
    "addr:housenumber":"12",
    "addr:postcode":"3134",
    "addr:street":"Larissa Ave",
    "iso:country":"AU",
    "sg:address":"12 Larissa Ave",
    "sg:city":"Ringwood",
    "sg:classifiers":[
        {
            "category":"Education",
            "subcategory":"Special Training",
            "type":"Public Place"
        }
    ],
    "sg:phone":"+61 3 9879 5099",
    "sg:postcode":"3134",
    "sg:province":"VIC",
    "sg:tags":[
        "tuition-educational"
    ],
    "wof:name":"Kip McGrath Education Centres",
    "wof:placetype":"venue"
},
  "geometry": {"coordinates":[145.23387145999999,-37.8114967346],"type":"Point"}
}