{
  "type": "Feature",
  "properties": {
    "iso:country":"AU",
    "sg:address":"3 Bruce Hwy",
    "sg:city":"Parkhurst",
    "sg:classifiers":[
        {
            "category":"Farming",
            "subcategory":"Livestock Farm",
            "type":"Manufacturing & Wholesale Goods"
        }
    ],
    "sg:phone":"+61 7 4936 4937",
    "sg:postcode":"4702",
    "sg:province":"QLD",
    "sg:tags":[
        "buyer"
    ],
    "wof:name":"Parkhurst Produve",
    "wof:placetype":"venue"
},
  "geometry": {"coordinates":[150.538452148,-23.4761047363],"type":"Point"}
}