{
  "type": "Feature",
  "properties": {
    "addr:full":"Unit 13/ 2 Barry Rd Chipping Norton NSW 2170",
    "addr:housenumber":"/ 2",
    "addr:postcode":"2170",
    "addr:street":"Barry Rd",
    "iso:country":"AU",
    "sg:address":"Unit 13/ 2 Barry Rd",
    "sg:city":"Chipping Norton",
    "sg:classifiers":[
        {
            "category":"Manufacturing",
            "subcategory":"Tools & Machinery",
            "type":"Manufacturing & Wholesale Goods"
        }
    ],
    "sg:phone":"+61 2 9755 3550",
    "sg:postcode":"2170",
    "sg:province":"NSW",
    "sg:tags":[
        "fastener",
        "industrial"
    ],
    "wof:name":"J D V Engineering Suppliers Of Knox Pty Ltd",
    "wof:placetype":"venue"
},
  "geometry": {"coordinates":[150.967926025,-33.915145874],"type":"Point"}
}