{
  "type": "Feature",
  "properties": {
    "addr:full":"Grampians Rd Wartook VIC 3400",
    "addr:postcode":"3400",
    "addr:street":"Grampians Rd",
    "iso:country":"AU",
    "sg:address":"Grampians Rd",
    "sg:city":"Wartook",
    "sg:classifiers":[
        {
            "category":"Wholesale",
            "subcategory":"Plants",
            "type":"Manufacturing & Wholesale Goods"
        }
    ],
    "sg:phone":"+61 3 5383 6235",
    "sg:postcode":"3400",
    "sg:province":"VIC",
    "sg:tags":[
        "florist"
    ],
    "wof:name":"Winnel Ausnative Flora",
    "wof:placetype":"venue"
},
  "geometry": {"coordinates":[142.19619750999999,-36.7172393799],"type":"Point"}
}