{
  "type": "Feature",
  "properties": {
    "iso:country":"AU",
    "sg:address":"127 Somerville Rd",
    "sg:city":"Hampton Park",
    "sg:classifiers":[
        {
            "category":"Banks & Credit Unions",
            "subcategory":"Bank",
            "type":"Services"
        }
    ],
    "sg:phone":"+61 1300 556 958",
    "sg:postcode":"3976",
    "sg:province":"VIC",
    "sg:tags":[
        "broker",
        "mortgage"
    ],
    "wof:name":"Capital Lending Group",
    "wof:placetype":"venue"
},
  "geometry": {"coordinates":[145.26625060999999,-38.0318527222],"type":"Point"}
}