{
  "type": "Feature",
  "properties": {
    "addr:full":"89 Granville St West Launceston TAS 7250",
    "addr:housenumber":"89",
    "addr:postcode":"7250",
    "addr:street":"Granville St West",
    "iso:country":"AU",
    "sg:address":"89 Granville St",
    "sg:city":"West Launceston",
    "sg:classifiers":[
        {
            "category":"Building & Trades",
            "subcategory":"Construction",
            "type":"Services"
        }
    ],
    "sg:phone":"+61 438 340 301",
    "sg:postcode":"7250",
    "sg:province":"TAS",
    "sg:tags":[
        "contractor"
    ],
    "wof:name":"Lifestyle Design & Construction",
    "wof:placetype":"venue"
},
  "geometry": {"coordinates":[147.13490295400001,-41.4581336975],"type":"Point"}
}