{
  "type": "Feature",
  "properties": {
    "iso:country":"AU",
    "sg:address":"30 Ottrey St",
    "sg:city":"Pyramid Hill",
    "sg:classifiers":[
        {
            "category":"Wholesale",
            "subcategory":"Machinery & Supplies",
            "type":"Manufacturing & Wholesale Goods"
        }
    ],
    "sg:phone":"+61 3 5455 7180",
    "sg:postcode":"3575",
    "sg:province":"VIC",
    "sg:tags":[
        "equipment",
        "welding"
    ],
    "wof:name":"Pyramidhill Welding Supplies",
    "wof:placetype":"venue"
},
  "geometry": {"coordinates":[144.12011718799999,-36.0535850525],"type":"Point"}
}