{
  "type": "Feature",
  "properties": {
    "addr:full":"PO Box 3017 Nowra North NSW 2541",
    "addr:postcode":"2541",
    "iso:country":"AU",
    "sg:address":"PO Box 3017",
    "sg:city":"Nowra North",
    "sg:classifiers":[
        {
            "category":"Building & Trades",
            "subcategory":"Plumbing",
            "type":"Services"
        }
    ],
    "sg:phone":"+61 2 4422 1976",
    "sg:postcode":"2541",
    "sg:province":"NSW",
    "sg:tags":[
        "plumber",
        "gasfitters"
    ],
    "wof:name":"Thomas J.G. & C.D. Contractors",
    "wof:placetype":"venue"
},
  "geometry": {"coordinates":[150.59147644000001,-34.8607292175],"type":"Point"}
}