{
  "type": "Feature",
  "properties": {
    "addr:full":"152 May St Newdegate WA 6355",
    "addr:housenumber":"152",
    "addr:postcode":"6355",
    "addr:street":"May St",
    "iso:country":"AU",
    "sg:address":"152 May St",
    "sg:city":"Newdegate",
    "sg:classifiers":[
        {
            "category":"Wholesale",
            "subcategory":"Machinery & Supplies",
            "type":"Manufacturing & Wholesale Goods"
        }
    ],
    "sg:phone":"+61 8 9871 1543",
    "sg:postcode":"6355",
    "sg:province":"WA",
    "sg:tags":[
        "agricultural"
    ],
    "wof:name":"G.A.R.S. General Agricultural Repair Service",
    "wof:placetype":"venue"
},
  "geometry": {"coordinates":[119.02491000000001,-33.094158],"type":"Point"}
}