{
  "type": "Feature",
  "properties": {
    "addr:full":"5 Gap Rd Riddells Creek VIC 3431",
    "addr:housenumber":"5",
    "addr:postcode":"3431",
    "addr:street":"Gap Rd",
    "iso:country":"AU",
    "sg:address":"5 Gap Rd",
    "sg:city":"Riddells Creek",
    "sg:classifiers":[
        {
            "category":"Building & Trades",
            "subcategory":"Construction",
            "type":"Services"
        }
    ],
    "sg:phone":"+61 3 5428 6573",
    "sg:postcode":"3431",
    "sg:province":"VIC",
    "sg:tags":[
        "earth",
        "excavating",
        "moving",
        "contractor"
    ],
    "wof:name":"Riddells Creek Earthmoving Pty Ltd",
    "wof:placetype":"venue"
},
  "geometry": {"coordinates":[144.683029175,-37.4572105408],"type":"Point"}
}