{
  "type": "Feature",
  "properties": {
    "addr:full":"619 Springvale Rd Mulgrave VIC 3170",
    "addr:housenumber":"619",
    "addr:postcode":"3170",
    "addr:street":"Springvale Rd",
    "iso:country":"AU",
    "sg:address":"619 Springvale Rd",
    "sg:city":"Mulgrave",
    "sg:classifiers":[
        {
            "category":"Home & Garden",
            "subcategory":"Building Materials",
            "type":"Retail Goods"
        }
    ],
    "sg:phone":"+61 3 9566 3566",
    "sg:postcode":"3170",
    "sg:province":"VIC",
    "sg:tags":[
        "fitting",
        "door"
    ],
    "wof:name":"Trollope Silverwood & Beck",
    "wof:placetype":"venue"
},
  "geometry": {"coordinates":[145.15985107399999,-37.9105606079],"type":"Point"}
}