{
  "type": "Feature",
  "properties": {
    "addr:full":"Shop 1, 10 Endeavour Sq Nhulunbuy NT 0880",
    "addr:housenumber":"shop;10",
    "addr:postcode":"nt 0880",
    "addr:street":"Endeavour Sq",
    "iso:country":"AU",
    "sg:address":"Shop 1, 10 Endeavour Sq",
    "sg:city":"Nhulunbuy",
    "sg:classifiers":[
        {
            "category":"Cafe",
            "type":"Food & Drink"
        }
    ],
    "sg:phone":"+61 8 8987 8477",
    "sg:postcode":"0880",
    "sg:province":"NT",
    "wof:name":"Munch & Crunch",
    "wof:placetype":"venue"
},
  "geometry": {"coordinates":[136.78602599999999,-12.18588],"type":"Point"}
}