{
  "type": "Feature",
  "properties": {
    "addr:full":"RMB/ 7120 Maffra Rd Bundalaguah VIC 3851",
    "addr:postcode":"3851",
    "addr:street":"Maffra Rd",
    "iso:country":"AU",
    "sg:address":"RMB/ 7120 Maffra Rd",
    "sg:city":"Bundalaguah",
    "sg:classifiers":[
        {
            "category":"Building & Trades",
            "subcategory":"Construction",
            "type":"Services"
        }
    ],
    "sg:phone":"+61 422 174 098",
    "sg:postcode":"3851",
    "sg:province":"VIC",
    "sg:tags":[
        "fencing",
        "contractor"
    ],
    "wof:name":"L & R Fencing",
    "wof:placetype":"venue"
},
  "geometry": {"coordinates":[147.216033936,-38.3536987305],"type":"Point"}
}