{
  "type": "Feature",
  "properties": {
    "addr:full":"173 Fullers Rd Chatswood NSW 2067",
    "addr:housenumber":"173",
    "addr:postcode":"2067",
    "addr:street":"Fullers Rd",
    "iso:country":"AU",
    "sg:address":"173 Fullers Rd",
    "sg:city":"Chatswood",
    "sg:classifiers":[
        {
            "category":"Health Services",
            "subcategory":"Doctor",
            "type":"Services"
        }
    ],
    "sg:phone":"+61 2 9413 4123",
    "sg:postcode":"2067",
    "sg:province":"NSW",
    "sg:tags":[
        "medical",
        "practitioner"
    ],
    "wof:name":"Dahms J W Dr",
    "wof:placetype":"venue"
},
  "geometry": {"coordinates":[151.16311645499999,-33.7937812805],"type":"Point"}
}