{
  "type": "Feature",
  "properties": {
    "iso:country":"AU",
    "sg:address":"20c Lyne Rd",
    "sg:city":"Cheltenham",
    "sg:classifiers":[
        {
            "category":"Home & Garden",
            "subcategory":"Building Materials",
            "type":"Retail Goods"
        }
    ],
    "sg:phone":"+61 2 9868 5469",
    "sg:postcode":"2119",
    "sg:province":"NSW",
    "sg:tags":[
        "plaster",
        "plasterboard",
        "supply"
    ],
    "wof:name":"George Lapardin",
    "wof:placetype":"venue"
},
  "geometry": {"coordinates":[151.07800293,-33.7598762512],"type":"Point"}
}