{
  "type": "Feature",
  "properties": {
    "iso:country":"AU",
    "sg:address":"Hunter St",
    "sg:city":"Newcastle",
    "sg:classifiers":[
        {
            "category":"Professional",
            "subcategory":"Employment Agencies",
            "type":"Services"
        }
    ],
    "sg:phone":"+61 417 085 213",
    "sg:postcode":"2300",
    "sg:province":"NSW",
    "sg:tags":[
        "entertainer",
        "agent"
    ],
    "wof:name":"The Pyrostix School Of Fire Twirling",
    "wof:placetype":"venue"
},
  "geometry": {"coordinates":[151.781036,-32.926991],"type":"Point"}
}