{
  "type": "Feature",
  "properties": {
    "iso:country":"AU",
    "sg:address":"50 Browns Rd",
    "sg:city":"Kingston",
    "sg:classifiers":[
        {
            "category":"Home & Garden",
            "subcategory":"Hardware",
            "type":"Retail Goods"
        }
    ],
    "sg:phone":"+61 3 6229 5677",
    "sg:postcode":"7050",
    "sg:province":"TAS",
    "sg:tags":[
        "plumber",
        "supply"
    ],
    "wof:name":"Tradelink Plumbing Centres",
    "wof:placetype":"venue"
},
  "geometry": {"coordinates":[147.31308000000001,-42.969452],"type":"Point"}
}