{
  "type": "Feature",
  "properties": {
    "addr:full":"196 Marsh St Armidale NSW 2350",
    "addr:housenumber":"196",
    "addr:postcode":"2350",
    "addr:street":"Marsh St",
    "iso:country":"AU",
    "sg:address":"196 Marsh St",
    "sg:city":"Armidale",
    "sg:classifiers":[
        {
            "category":"Farming",
            "subcategory":"Farm & Veterinary Services",
            "type":"Manufacturing & Wholesale Goods"
        }
    ],
    "sg:phone":"+61 2 6771 2277",
    "sg:postcode":"2350",
    "sg:province":"NSW",
    "sg:tags":[
        "agricultural",
        "advisory"
    ],
    "wof:name":"Tuart Anne",
    "wof:placetype":"venue"
},
  "geometry": {"coordinates":[151.66578674300001,-30.522441864],"type":"Point"}
}