{
  "type": "Feature",
  "properties": {
    "addr:full":"Pittwater Rd Dee Why NSW 2099",
    "addr:postcode":"2099",
    "addr:street":"Pittwater Rd",
    "iso:country":"AU",
    "sg:address":"Pittwater Rd",
    "sg:city":"Dee Why",
    "sg:classifiers":[
        {
            "category":"Retail",
            "subcategory":"Auto Rental",
            "type":"Services"
        }
    ],
    "sg:phone":"+61 2 9981 2033",
    "sg:postcode":"2099",
    "sg:province":"NSW",
    "sg:tags":[
        "car",
        "hire",
        "minibus"
    ],
    "wof:name":"Aero Auto Rentals",
    "wof:placetype":"venue"
},
  "geometry": {"coordinates":[151.285232544,-33.7537498474],"type":"Point"}
}