{
  "type": "Feature",
  "properties": {
    "addr:full":"18 Delmont Crt Endeavour Hills VIC 3802",
    "addr:housenumber":"18",
    "addr:postcode":"3802",
    "addr:street":"Delmont Crt",
    "iso:country":"AU",
    "sg:address":"18 Delmont Crt",
    "sg:city":"Endeavour Hills",
    "sg:classifiers":[
        {
            "category":"Autos & Motor Vehicles",
            "subcategory":"Fuel & Gas Station",
            "type":"Retail Goods"
        }
    ],
    "sg:phone":"+61 3 9700 5954",
    "sg:postcode":"3802",
    "sg:province":"VIC",
    "sg:tags":[
        "petrol",
        "marketing",
        "pump",
        "equipment"
    ],
    "wof:name":"Arcal Petroleum Services Pty Ltd",
    "wof:placetype":"venue"
},
  "geometry": {"coordinates":[145.26707458499999,-37.9845237732],"type":"Point"}
}