{
  "type": "Feature",
  "properties": {
    "addr:full":"27 Anthony Rd Tamworth NSW 2340",
    "addr:housenumber":"27",
    "addr:postcode":"2340",
    "addr:street":"Anthony Rd",
    "iso:country":"AU",
    "sg:address":"27 Anthony Rd",
    "sg:city":"Tamworth",
    "sg:classifiers":[
        {
            "category":"Health Services",
            "subcategory":"Doctor",
            "type":"Services"
        }
    ],
    "sg:phone":"+61 2 6761 8927",
    "sg:postcode":"2340",
    "sg:province":"NSW",
    "sg:tags":[
        "occupational",
        "safety"
    ],
    "wof:name":"St John Ambulance Australia",
    "wof:placetype":"venue"
},
  "geometry": {"coordinates":[150.91116332999999,-31.1066226959],"type":"Point"}
}