{
  "type": "Feature",
  "properties": {
    "iso:country":"AU",
    "sg:address":"150 Wallace Rd",
    "sg:city":"Wantirna South",
    "sg:classifiers":[
        {
            "category":"Professional",
            "subcategory":"Accounting & Tax Preparation",
            "type":"Services"
        }
    ],
    "sg:phone":"+61 3 9887 1079",
    "sg:postcode":"3152",
    "sg:province":"VIC",
    "sg:tags":[
        "accountant",
        "auditor"
    ],
    "wof:name":"Ponton Reg N",
    "wof:placetype":"venue"
},
  "geometry": {"coordinates":[145.238449097,-37.8782653809],"type":"Point"}
}