{
  "type": "Feature",
  "properties": {
    "iso:country":"AU",
    "sg:address":"374 Stapylton Jacobs Well Rd",
    "sg:city":"Stapylton",
    "sg:classifiers":[
        {
            "category":"Structure",
            "subcategory":"Office Building",
            "type":"Public Place"
        }
    ],
    "sg:phone":"+61 7 3807 8816",
    "sg:postcode":"4207",
    "sg:province":"QLD",
    "sg:tags":[
        "tie",
        "concrete",
        "formwork",
        "form",
        "accessory"
    ],
    "wof:name":"Fitzgerald Formwork & Construction",
    "wof:placetype":"venue"
},
  "geometry": {"coordinates":[153.236404419,-27.7312145233],"type":"Point"}
}