{
  "type": "Feature",
  "properties": {
    "iso:country":"AU",
    "sg:address":"170 Elmore-Barnadown Rd",
    "sg:city":"Goornong",
    "sg:classifiers":[
        {
            "category":"Farming",
            "subcategory":"Farm",
            "type":"Manufacturing & Wholesale Goods"
        }
    ],
    "sg:phone":"+61 3 5432 2314",
    "sg:postcode":"3557",
    "sg:province":"VIC",
    "sg:tags":[
        "farmer"
    ],
    "wof:name":"McKinstry J D",
    "wof:placetype":"venue"
},
  "geometry": {"coordinates":[144.5415802,-36.6349945068],"type":"Point"}
}