{
  "type": "Feature",
  "properties": {
    "addr:full":"32 Bathurst St Condobolin NSW 2877",
    "addr:housenumber":"32",
    "addr:postcode":"2877",
    "addr:street":"Bathurst St",
    "iso:country":"AU",
    "sg:address":"32 Bathurst St",
    "sg:city":"Condobolin",
    "sg:classifiers":[
        {
            "category":"Organizations",
            "subcategory":"Professional Association",
            "type":"Services"
        }
    ],
    "sg:phone":"+61 2 6895 2152",
    "sg:postcode":"2877",
    "sg:province":"NSW",
    "sg:tags":[
        "rural",
        "organisation",
        "production",
        "primary"
    ],
    "wof:name":"Rural Lands Protection Boards",
    "wof:placetype":"venue"
},
  "geometry": {"coordinates":[147.14700300000001,-33.08828],"type":"Point"}
}