{
  "type": "Feature",
  "properties": {
    "addr:full":"2/ 20 Sir Laurence Drv Seaford VIC 3198",
    "addr:housenumber":"/ 20",
    "addr:postcode":"3198",
    "addr:street":"Sir Laurence Drv",
    "iso:country":"AU",
    "sg:address":"2/ 20 Sir Laurence Drv",
    "sg:city":"Seaford",
    "sg:classifiers":[
        {
            "category":"Professional",
            "subcategory":"Detective & Security Services",
            "type":"Services"
        }
    ],
    "sg:phone":"+61 1300 881 823",
    "sg:postcode":"3198",
    "sg:province":"VIC",
    "sg:tags":[
        "consultant",
        "system"
    ],
    "wof:name":"Quad Security",
    "wof:placetype":"venue"
},
  "geometry": {"coordinates":[145.13815307600001,-38.1154174805],"type":"Point"}
}