{
  "type": "Feature",
  "properties": {
    "iso:country":"AU",
    "sg:address":"6 Dougan St",
    "sg:city":"Ashfield",
    "sg:classifiers":[
        {
            "category":"Home & Garden",
            "subcategory":"Carpets & Floor Coverings",
            "type":"Retail Goods"
        }
    ],
    "sg:phone":"+61 2 9797 9250",
    "sg:postcode":"2131",
    "sg:province":"NSW",
    "sg:tags":[
        "tile",
        "wall",
        "layer"
    ],
    "wof:name":"Stoyko T",
    "wof:placetype":"venue"
},
  "geometry": {"coordinates":[151.117584228,-33.8943748474],"type":"Point"}
}