{
  "type": "Feature",
  "properties": {
    "addr:full":"5 Trinity Ave Kellyville NSW 2155",
    "addr:housenumber":"5",
    "addr:postcode":"2155",
    "addr:street":"Trinity Ave",
    "iso:country":"AU",
    "sg:address":"5 Trinity Ave",
    "sg:city":"Kellyville",
    "sg:classifiers":[
        {
            "category":"Utilities",
            "subcategory":"Electric",
            "type":"Services"
        }
    ],
    "sg:phone":"+61 402 722 994",
    "sg:postcode":"2155",
    "sg:province":"NSW",
    "sg:tags":[
        "electrical",
        "contractor"
    ],
    "wof:name":"Active Electrical Solutions",
    "wof:placetype":"venue"
},
  "geometry": {"coordinates":[150.96490478499999,-33.7112083435],"type":"Point"}
}