{
  "type": "Feature",
  "properties": {
    "iso:country":"AU",
    "sg:address":"33a Peel St",
    "sg:city":"Mackay",
    "sg:classifiers":[
        {
            "category":"Real Estate",
            "subcategory":"Real Estate Agent",
            "type":"Services"
        }
    ],
    "sg:phone":"+61 7 4953 5355",
    "sg:postcode":"4740",
    "sg:province":"QLD",
    "wof:name":"Progressive Realty",
    "wof:placetype":"venue"
},
  "geometry": {"coordinates":[149.179214,-21.144142],"type":"Point"}
}