{
  "type": "Feature",
  "properties": {
    "iso:country":"AU",
    "sg:address":"35 Anzac Ave",
    "sg:city":"Toowoomba",
    "sg:classifiers":[
        {
            "category":"Retail",
            "subcategory":"Repair Shop",
            "type":"Services"
        }
    ],
    "sg:phone":"+61 7 4632 5211",
    "sg:postcode":"4350",
    "sg:province":"QLD",
    "sg:tags":[
        "repairing",
        "piano",
        "tuning"
    ],
    "wof:name":"Bill Rider Piano Tuner & Repairer",
    "wof:placetype":"venue"
},
  "geometry": {"coordinates":[151.939682,-27.559084],"type":"Point"}
}