{
  "type": "Feature",
  "properties": {
    "addr:full":"88 Cooper St Maroubra Junction NSW 2035",
    "addr:housenumber":"88",
    "addr:postcode":"2035",
    "addr:street":"Cooper St",
    "iso:country":"AU",
    "sg:address":"88 Cooper St",
    "sg:city":"Maroubra Junction",
    "sg:classifiers":[
        {
            "category":"Social Services",
            "subcategory":"Child Care",
            "type":"Services"
        }
    ],
    "sg:phone":"+61 2 9349 6714",
    "sg:postcode":"2035",
    "sg:province":"NSW",
    "wof:name":"Maroubra Junction French Australian Pre-School",
    "wof:placetype":"venue"
},
  "geometry": {"coordinates":[151.24461364699999,-33.9417991638],"type":"Point"}
}