{
  "type": "Feature",
  "properties": {
    "addr:full":"65 Highland Drv Bowral NSW 2576",
    "addr:housenumber":"65",
    "addr:postcode":"2576",
    "addr:street":"Highland Drv",
    "iso:country":"AU",
    "sg:address":"65 Highland Drv",
    "sg:city":"Bowral",
    "sg:classifiers":[
        {
            "category":"Personal",
            "subcategory":"Massage",
            "type":"Services"
        }
    ],
    "sg:phone":"+61 427 404 847",
    "sg:postcode":"2576",
    "sg:province":"NSW",
    "sg:tags":[
        "therapy"
    ],
    "wof:name":"Penelope G. Wardle",
    "wof:placetype":"venue"
},
  "geometry": {"coordinates":[150.44662475600001,-34.4981231689],"type":"Point"}
}