{
  "type": "Feature",
  "properties": {
    "addr:full":"61 - 69 Brighton Rd Elwood VIC 3184",
    "addr:housenumber":"69",
    "addr:postcode":"3184",
    "addr:street":"Brighton Rd",
    "iso:country":"AU",
    "sg:address":"61 - 69 Brighton Rd",
    "sg:city":"Elwood",
    "sg:classifiers":[
        {
            "category":"Health Services",
            "subcategory":"Doctor",
            "type":"Services"
        }
    ],
    "sg:phone":"+61 3 9531 9811",
    "sg:postcode":"3184",
    "sg:province":"VIC",
    "sg:tags":[
        "medical",
        "practitioner"
    ],
    "wof:name":"Montague Graeme Dr",
    "wof:placetype":"venue"
},
  "geometry": {"coordinates":[144.98945617699999,-37.8724517822],"type":"Point"}
}