{
  "type": "Feature",
  "properties": {
    "addr:full":"2/ 52 Burelli St Wollongong NSW 2500",
    "addr:housenumber":"/ 52",
    "addr:postcode":"2500",
    "addr:street":"Burelli St",
    "iso:country":"AU",
    "sg:address":"2/ 52 Burelli St",
    "sg:city":"Wollongong",
    "sg:classifiers":[
        {
            "category":"Professional",
            "subcategory":"Printing & Photocopies",
            "type":"Services"
        }
    ],
    "sg:phone":"+61 2 4229 4461",
    "sg:postcode":"2500",
    "sg:province":"NSW",
    "sg:tags":[
        "trophy"
    ],
    "wof:name":"Gala Trophies",
    "wof:placetype":"venue"
},
  "geometry": {"coordinates":[150.896942,-34.426426],"type":"Point"}
}