{
  "type": "Feature",
  "properties": {
    "iso:country":"AU",
    "sg:address":"7 Bodalla Pl",
    "sg:city":"Merimbula",
    "sg:classifiers":[
        {
            "category":"Arts & Performance",
            "subcategory":"Art Gallery",
            "type":"Entertainment"
        }
    ],
    "sg:phone":"+61 2 6495 4608",
    "sg:postcode":"2548",
    "sg:province":"NSW",
    "wof:name":"Boardwalkart",
    "wof:placetype":"venue"
},
  "geometry": {"coordinates":[149.90284729000001,-36.895111084],"type":"Point"}
}