{
  "type": "Feature",
  "properties": {
    "iso:country":"AU",
    "sg:address":"161 Cambridge St",
    "sg:city":"Stanmore",
    "sg:classifiers":[
        {
            "category":"Food & Beverages",
            "subcategory":"Liquor & Beverages",
            "type":"Retail Goods"
        }
    ],
    "sg:phone":"+61 2 9560 9323",
    "sg:postcode":"2048",
    "sg:province":"NSW",
    "sg:tags":[
        "store"
    ],
    "wof:name":"Stanmore Cellars",
    "wof:placetype":"venue"
},
  "geometry": {"coordinates":[151.164612,-33.894756],"type":"Point"}
}