{
  "type": "Feature",
  "properties": {
    "addr:full":"12 Joanne St Woonona NSW 2517",
    "addr:housenumber":"12",
    "addr:postcode":"2517",
    "addr:street":"Joanne St",
    "iso:country":"AU",
    "sg:address":"12 Joanne St",
    "sg:city":"Woonona",
    "sg:classifiers":[
        {
            "category":"Real Estate",
            "subcategory":"Architect",
            "type":"Services"
        }
    ],
    "sg:phone":"+61 2 4285 0129",
    "sg:postcode":"2517",
    "sg:province":"NSW",
    "wof:name":"Maurice Hayler and Associates",
    "wof:placetype":"venue"
},
  "geometry": {"coordinates":[150.897537,-34.336597],"type":"Point"}
}