{
  "type": "Feature",
  "properties": {
    "addr:full":"28 Altair St Tweed Heads South NSW 2486",
    "addr:housenumber":"28",
    "addr:postcode":"2486",
    "addr:street":"Altair St",
    "iso:country":"AU",
    "sg:address":"28 Altair St",
    "sg:city":"Tweed Heads South",
    "sg:classifiers":[
        {
            "category":"Personal",
            "subcategory":"Beauty Salon",
            "type":"Services"
        }
    ],
    "sg:phone":"+61 7 5524 3575",
    "sg:postcode":"2486",
    "sg:province":"NSW",
    "sg:tags":[
        "hairdresser"
    ],
    "wof:name":"Lindy's Hair Design",
    "wof:placetype":"venue"
},
  "geometry": {"coordinates":[153.54684448200001,-28.1962051392],"type":"Point"}
}