{
  "type": "Feature",
  "properties": {
    "addr:full":"143 Gabriel St Cloverdale WA 6105",
    "addr:housenumber":"143",
    "addr:postcode":"6105",
    "addr:street":"Gabriel St",
    "iso:country":"AU",
    "sg:address":"143 Gabriel St",
    "sg:city":"Cloverdale",
    "sg:classifiers":[
        {
            "category":"Building & Trades",
            "subcategory":"Cleaning & Sanitation",
            "type":"Services"
        }
    ],
    "sg:phone":"+61 8 9277 2149",
    "sg:postcode":"6105",
    "sg:province":"WA",
    "sg:tags":[
        "industrial",
        "commercial",
        "contractor"
    ],
    "wof:name":"Kevin Downs Building Maintenance & Office Cleaning Service",
    "wof:placetype":"venue"
},
  "geometry": {"coordinates":[115.942802429,-31.9638938904],"type":"Point"}
}