{
  "type": "Feature",
  "properties": {
    "iso:country":"AU",
    "sg:address":"900 Princes Hwy",
    "sg:city":"Springvale",
    "sg:classifiers":[
        {
            "category":"Autos & Motor Vehicles",
            "subcategory":"Auto Supplies",
            "type":"Retail Goods"
        }
    ],
    "sg:phone":"+61 3 9547 4011",
    "sg:postcode":"3171",
    "sg:province":"VIC",
    "sg:tags":[
        "tyre"
    ],
    "wof:name":"Canterbury Tyre & Mag Supamart",
    "wof:placetype":"venue"
},
  "geometry": {"coordinates":[145.158370972,-37.9343719482],"type":"Point"}
}