{
  "type": "Feature",
  "properties": {
    "iso:country":"AU",
    "sg:address":"Private Bag 7",
    "sg:city":"Wauchope",
    "sg:classifiers":[
        {
            "category":"Manufacturing",
            "subcategory":"Tools & Machinery",
            "type":"Manufacturing & Wholesale Goods"
        }
    ],
    "sg:phone":"+61 2 6585 1000",
    "sg:postcode":"2446",
    "sg:province":"NSW",
    "sg:tags":[
        "earth",
        "excavating",
        "moving",
        "equipment"
    ],
    "wof:name":"Expressway Spares Pty Ltd",
    "wof:placetype":"venue"
},
  "geometry": {"coordinates":[152.81041,-31.482935],"type":"Point"}
}