{
  "type": "Feature",
  "properties": {
    "addr:full":"11 Skarratt St Auburn NSW 2144",
    "addr:housenumber":"11",
    "addr:postcode":"2144",
    "addr:street":"Skarratt St",
    "iso:country":"AU",
    "sg:address":"11 Skarratt St",
    "sg:city":"Auburn",
    "sg:classifiers":[
        {
            "category":"Manufacturing",
            "subcategory":"Retail Goods",
            "type":"Manufacturing & Wholesale Goods"
        }
    ],
    "sg:phone":"+61 2 9648 3111",
    "sg:postcode":"2144",
    "sg:province":"NSW",
    "sg:tags":[
        "merchant",
        "pump",
        "mfrs"
    ],
    "wof:name":"Atom Electrical Service Pty Ltd",
    "wof:placetype":"venue"
},
  "geometry": {"coordinates":[151.03427124000001,-33.8388595581],"type":"Point"}
}