{
  "type": "Feature",
  "properties": {
    "addr:full":"44 Lichfield St Victoria Park WA 6100",
    "addr:housenumber":"44",
    "addr:postcode":"6100",
    "addr:street":"Lichfield St",
    "iso:country":"AU",
    "sg:address":"44 Lichfield St",
    "sg:city":"Victoria Park",
    "sg:classifiers":[
        {
            "category":"Home & Garden",
            "subcategory":"Carpets & Floor Coverings",
            "type":"Retail Goods"
        }
    ],
    "sg:phone":"+61 416 149 936",
    "sg:postcode":"6100",
    "sg:province":"WA",
    "sg:tags":[
        "tile",
        "wall",
        "layer"
    ],
    "wof:name":"Quicklay Tiling",
    "wof:placetype":"venue"
},
  "geometry": {"coordinates":[115.901786804,-31.9781284332],"type":"Point"}
}