{
  "type": "Feature",
  "properties": {
    "addr:full":"Shop 12 Patullos Rd Lara VIC 3212",
    "addr:housenumber":"shop 12",
    "addr:postcode":"3212",
    "addr:street":"Patullos Rd",
    "iso:country":"AU",
    "sg:address":"Shop 12 Patullos Rd",
    "sg:city":"Lara",
    "sg:classifiers":[
        {
            "category":"Personal",
            "subcategory":"Massage",
            "type":"Services"
        }
    ],
    "sg:phone":"+61 3 5282 3133",
    "sg:postcode":"3212",
    "sg:province":"VIC",
    "sg:tags":[
        "therapy"
    ],
    "wof:name":"Leah Belleville",
    "wof:placetype":"venue"
},
  "geometry": {"coordinates":[144.395874023,-38.0227890015],"type":"Point"}
}