{
  "type": "Feature",
  "properties": {
    "iso:country":"AU",
    "sg:address":"102 Hannans Rd",
    "sg:city":"Narwee",
    "sg:classifiers":[
        {
            "category":"Building & Trades",
            "subcategory":"Landscaping Services",
            "type":"Services"
        }
    ],
    "sg:phone":"+61 438 220 027",
    "sg:postcode":"2209",
    "sg:province":"NSW",
    "sg:tags":[
        "stump",
        "tree",
        "felling",
        "removal"
    ],
    "wof:name":"Adam Tree Service",
    "wof:placetype":"venue"
},
  "geometry": {"coordinates":[151.06880200000001,-33.9468],"type":"Point"}
}