{
  "type": "Feature",
  "properties": {
    "iso:country":"AU",
    "sg:address":"Unit 20/ 167 Pitt St",
    "sg:city":"Eltham",
    "sg:classifiers":[
        {
            "category":"Building & Trades",
            "subcategory":"Cleaning & Sanitation",
            "type":"Services"
        }
    ],
    "sg:phone":"+61 3 9439 4447",
    "sg:postcode":"3095",
    "sg:province":"VIC",
    "sg:tags":[
        "industrial",
        "commercial",
        "contractor"
    ],
    "wof:name":"A.G.T. Cleaning Services",
    "wof:placetype":"venue"
},
  "geometry": {"coordinates":[145.157302856,-37.7219848633],"type":"Point"}
}