{
  "type": "Feature",
  "properties": {
    "addr:full":"Unit 4/ 15 Bonner Drv Malaga WA 6090",
    "addr:housenumber":"15",
    "addr:postcode":"6090",
    "addr:street":"Bonner Drv",
    "iso:country":"AU",
    "sg:address":"Unit 4/ 15 Bonner Drv",
    "sg:city":"Malaga",
    "sg:classifiers":[
        {
            "category":"Food & Beverages",
            "subcategory":"Bakery",
            "type":"Retail Goods"
        }
    ],
    "sg:phone":"+61 8 9249 2355",
    "sg:postcode":"6090",
    "sg:province":"WA",
    "sg:tags":[
        "cake",
        "shop",
        "pastry"
    ],
    "wof:name":"Cheesecake Shop The",
    "wof:placetype":"venue"
},
  "geometry": {"coordinates":[115.87895965600001,-31.8499889374],"type":"Point"}
}