{
  "type": "Feature",
  "properties": {
    "addr:full":"Shp3/ 346 Charlton Esp Scarness QLD 4655",
    "addr:housenumber":"346",
    "addr:postcode":"4655",
    "iso:country":"AU",
    "sg:address":"Shp3/ 346 Charlton Esp",
    "sg:city":"Scarness",
    "sg:classifiers":[
        {
            "category":"Fast Food",
            "type":"Food & Drink"
        }
    ],
    "sg:phone":"+61 7 4194 5611",
    "sg:postcode":"4655",
    "sg:province":"QLD",
    "sg:tags":[
        "away",
        "take"
    ],
    "wof:name":"Scarness Takeaway",
    "wof:placetype":"venue"
},
  "geometry": {"coordinates":[152.846664,-25.282457],"type":"Point"}
}