{
  "type": "Feature",
  "properties": {
    "addr:full":"96 Gorge Rd Newton SA 5074",
    "addr:housenumber":"96",
    "addr:postcode":"5074",
    "addr:street":"Gorge Rd",
    "iso:country":"AU",
    "sg:address":"96 Gorge Rd",
    "sg:city":"Newton",
    "sg:classifiers":[
        {
            "category":"Fast Food",
            "type":"Food & Drink"
        }
    ],
    "sg:phone":"+61 8 8336 7419",
    "sg:postcode":"5074",
    "sg:province":"SA",
    "sg:tags":[
        "away",
        "take"
    ],
    "wof:name":"The Gorge Takeaway",
    "wof:placetype":"venue"
},
  "geometry": {"coordinates":[138.67604064899999,-34.8763313293],"type":"Point"}
}