{
  "type": "Feature",
  "properties": {
    "addr:full":"64- 78 Vicars St Mitchell ACT 2911",
    "addr:housenumber":"78",
    "addr:postcode":"2911",
    "addr:street":"Vicars St",
    "iso:country":"AU",
    "sg:address":"64- 78 Vicars St",
    "sg:city":"Mitchell",
    "sg:classifiers":[
        {
            "category":"Home & Garden",
            "subcategory":"Building Materials",
            "type":"Retail Goods"
        }
    ],
    "sg:phone":"+61 2 6242 2211",
    "sg:postcode":"2911",
    "sg:province":"ACT",
    "sg:tags":[
        "roofing"
    ],
    "wof:name":"Canberra Metal Fascia",
    "wof:placetype":"venue"
},
  "geometry": {"coordinates":[149.142288208,-35.2098960876],"type":"Point"}
}