{
  "type": "Feature",
  "properties": {
    "addr:full":"76 Hoddle St Abbotsford VIC 3067",
    "addr:housenumber":"76",
    "addr:postcode":"3067",
    "addr:street":"Hoddle St",
    "iso:country":"AU",
    "sg:address":"76 Hoddle St",
    "sg:city":"Abbotsford",
    "sg:classifiers":[
        {
            "category":"Banks & Credit Unions",
            "subcategory":"Bureau De Change",
            "type":"Services"
        }
    ],
    "sg:phone":"+61 3 8415 1800",
    "sg:postcode":"3067",
    "sg:province":"VIC",
    "sg:tags":[
        "motorised",
        "scooter"
    ],
    "wof:name":"Scootermarket Pty Ltd",
    "wof:placetype":"venue"
},
  "geometry": {"coordinates":[144.9921875,-37.8062133789],"type":"Point"}
}