{
  "type": "Feature",
  "properties": {
    "addr:full":"13 Cornwall St Taree NSW 2430",
    "addr:housenumber":"13",
    "addr:postcode":"2430",
    "addr:street":"Cornwall St",
    "iso:country":"AU",
    "sg:address":"13 Cornwall St",
    "sg:city":"Taree",
    "sg:classifiers":[
        {
            "category":"Wholesale",
            "subcategory":"Non-durable Goods",
            "type":"Manufacturing & Wholesale Goods"
        }
    ],
    "sg:phone":"+61 2 6551 2313",
    "sg:postcode":"2430",
    "sg:province":"NSW",
    "sg:tags":[
        "wholesaler",
        "craft",
        "mfrs"
    ],
    "wof:name":"Northern Leisure Sales",
    "wof:placetype":"venue"
},
  "geometry": {"coordinates":[152.45091199999999,-31.910681],"type":"Point"}
}