{
  "type": "Feature",
  "properties": {
    "addr:full":"227 North East Rd Hampstead Gardens SA 5086",
    "addr:housenumber":"227",
    "addr:postcode":"5086",
    "addr:street":"North East Rd",
    "iso:country":"AU",
    "sg:address":"227 North East Rd",
    "sg:city":"Hampstead Gardens",
    "sg:classifiers":[
        {
            "category":"Building & Trades",
            "subcategory":"Construction",
            "type":"Services"
        }
    ],
    "sg:phone":"+61 8 8369 1400",
    "sg:postcode":"5086",
    "sg:province":"SA",
    "sg:tags":[
        "earth",
        "excavating",
        "moving",
        "contractor"
    ],
    "wof:name":"Hedgehog Construction Services",
    "wof:placetype":"venue"
},
  "geometry": {"coordinates":[138.62896728499999,-34.8772392273],"type":"Point"}
}