{
  "type": "Feature",
  "properties": {
    "addr:full":"27- 29 Boomerang Pl Seven Hills NSW 2147",
    "addr:housenumber":"29",
    "addr:postcode":"2147",
    "addr:street":"Boomerang Pl",
    "iso:country":"AU",
    "sg:address":"27- 29 Boomerang Pl",
    "sg:city":"Seven Hills",
    "sg:classifiers":[
        {
            "category":"Shopping",
            "subcategory":"Pets & Pet Supplies",
            "type":"Retail Goods"
        }
    ],
    "sg:phone":"+61 2 9622 3372",
    "sg:postcode":"2147",
    "sg:province":"NSW",
    "sg:tags":[
        "food"
    ],
    "wof:name":"Seven Hills Pet Foods",
    "wof:placetype":"venue"
},
  "geometry": {"coordinates":[150.93635559099999,-33.7749404907],"type":"Point"}
}