{
  "type": "Feature",
  "properties": {
    "addr:full":"6 Robertson St Toowoomba QLD 4350",
    "addr:housenumber":"6",
    "addr:postcode":"4350",
    "addr:street":"Robertson St",
    "iso:country":"AU",
    "sg:address":"6 Robertson St",
    "sg:city":"Toowoomba",
    "sg:classifiers":[
        {
            "category":"Professional",
            "subcategory":"Printing & Photocopies",
            "type":"Services"
        }
    ],
    "sg:phone":"+61 7 4659 7677",
    "sg:postcode":"4350",
    "sg:province":"QLD",
    "sg:tags":[
        "photocopying"
    ],
    "wof:name":"Spotcolour",
    "wof:placetype":"venue"
},
  "geometry": {"coordinates":[151.95147700000001,-27.569895],"type":"Point"}
}