{
  "type": "Feature",
  "properties": {
    "addr:full":"62 Blackmore St Windsor QLD 4030",
    "addr:housenumber":"62",
    "addr:postcode":"4030",
    "addr:street":"Blackmore St",
    "iso:country":"AU",
    "sg:address":"62 Blackmore St",
    "sg:city":"Windsor",
    "sg:classifiers":[
        {
            "category":"Building & Trades",
            "subcategory":"Landscaping Services",
            "type":"Services"
        }
    ],
    "sg:phone":"+61 7 3357 9198",
    "sg:postcode":"4030",
    "sg:province":"QLD",
    "sg:tags":[
        "stump",
        "tree",
        "felling",
        "removal"
    ],
    "wof:name":"Classic Tree Lopping",
    "wof:placetype":"venue"
},
  "geometry": {"coordinates":[153.03732299999999,-27.430098],"type":"Point"}
}