{
  "type": "Feature",
  "properties": {
    "iso:country":"AU",
    "sg:address":"39 Amber St",
    "sg:city":"Katanning",
    "sg:classifiers":[
        {
            "category":"Farming",
            "subcategory":"Farm & Veterinary Services",
            "type":"Manufacturing & Wholesale Goods"
        }
    ],
    "sg:phone":"+61 8 9821 4214",
    "sg:postcode":"6317",
    "sg:province":"WA",
    "sg:tags":[
        "shearing",
        "contractor"
    ],
    "wof:name":"South Shear Pty Ltd",
    "wof:placetype":"venue"
},
  "geometry": {"coordinates":[117.54792022700001,-33.6946144104],"type":"Point"}
}