{
  "type": "Feature",
  "properties": {
    "iso:country":"AU",
    "sg:address":"117 Dennison St",
    "sg:city":"Deakin",
    "sg:classifiers":[
        {
            "category":"Social Services",
            "subcategory":"Adult Care",
            "type":"Services"
        }
    ],
    "sg:phone":"+61 2 6285 2082",
    "sg:postcode":"2600",
    "sg:province":"ACT",
    "sg:tags":[
        "aged"
    ],
    "wof:name":"CARERS ACT - THE COTTAGE (DEMENTIA)",
    "wof:placetype":"venue"
},
  "geometry": {"coordinates":[149.09242248499999,-35.3251800537],"type":"Point"}
}