{
  "type": "Feature",
  "properties": {
    "iso:country":"AU",
    "sg:address":"28 Trugania Rd",
    "sg:city":"Malaga",
    "sg:classifiers":[
        {
            "category":"Wholesale",
            "subcategory":"Construction Materials",
            "type":"Manufacturing & Wholesale Goods"
        }
    ],
    "sg:phone":"+61 8 9209 7100",
    "sg:postcode":"6090",
    "sg:province":"WA",
    "sg:tags":[
        "wholesaler",
        "lighting",
        "mfrs",
        "accessory"
    ],
    "wof:name":"Pierlite",
    "wof:placetype":"venue"
},
  "geometry": {"coordinates":[115.885597229,-31.8639278412],"type":"Point"}
}