{
  "type": "Feature",
  "properties": {
    "iso:country":"AU",
    "sg:address":"James Strs",
    "sg:city":"Toowoomba",
    "sg:classifiers":[
        {
            "category":"Retail",
            "subcategory":"Auto Rental",
            "type":"Services"
        }
    ],
    "sg:phone":"+61 7 4639 3799",
    "sg:postcode":"4350",
    "sg:province":"QLD",
    "sg:tags":[
        "car",
        "hire",
        "minibus"
    ],
    "wof:name":"Europcar",
    "wof:placetype":"venue"
},
  "geometry": {"coordinates":[151.951904,-27.569506],"type":"Point"}
}