{
  "type": "Feature",
  "properties": {
    "addr:full":"339 Church St Richmond VIC 3121",
    "addr:housenumber":"339",
    "addr:postcode":"3121",
    "addr:street":"Church St",
    "iso:country":"AU",
    "sg:address":"339 Church St",
    "sg:city":"Richmond",
    "sg:classifiers":[
        {
            "category":"Education",
            "subcategory":"Special Training",
            "type":"Public Place"
        }
    ],
    "sg:phone":"+61 3 9427 7122",
    "sg:postcode":"3121",
    "sg:province":"VIC",
    "sg:tags":[
        "development"
    ],
    "wof:name":"ERGOSH Safety Training",
    "wof:placetype":"venue"
},
  "geometry": {"coordinates":[144.998657227,-37.8225097656],"type":"Point"}
}