{
  "type": "Feature",
  "properties": {
    "iso:country":"AU",
    "sg:address":"25 Memorial Ave",
    "sg:city":"South West Rocks",
    "sg:classifiers":[
        {
            "category":"Food & Beverages",
            "subcategory":"Supermarket",
            "type":"Retail Goods"
        }
    ],
    "sg:phone":"+61 2 6566 6273",
    "sg:postcode":"2431",
    "sg:province":"NSW",
    "sg:tags":[
        "grocery",
        "store"
    ],
    "wof:name":"Charlies Corner Supermarket",
    "wof:placetype":"venue"
},
  "geometry": {"coordinates":[153.041321,-30.886631],"type":"Point"}
}