{
  "type": "Feature",
  "properties": {
    "iso:country":"AU",
    "sg:address":"Suite 4 95 King William St",
    "sg:city":"Unley",
    "sg:classifiers":[
        {
            "category":"Health Services",
            "subcategory":"Health Practitioner",
            "type":"Services"
        }
    ],
    "sg:phone":"+61 8 8274 1644",
    "sg:postcode":"5061",
    "sg:province":"SA",
    "sg:tags":[
        "psychologist"
    ],
    "wof:name":"Alder John",
    "wof:placetype":"venue"
},
  "geometry": {"coordinates":[138.60028076200001,-34.9555053711],"type":"Point"}
}