{
  "type": "Feature",
  "properties": {
    "addr:full":"205 Walker St Casino NSW 2470",
    "addr:housenumber":"205",
    "addr:postcode":"2470",
    "addr:street":"Walker St",
    "iso:country":"AU",
    "sg:address":"205 Walker St",
    "sg:city":"Casino",
    "sg:classifiers":[
        {
            "category":"Retail",
            "subcategory":"Auto Repair",
            "type":"Services"
        }
    ],
    "sg:phone":"+61 2 6662 1464",
    "sg:postcode":"2470",
    "sg:province":"NSW",
    "sg:tags":[
        "beater",
        "painter",
        "panel"
    ],
    "wof:name":"Walker Bros",
    "wof:placetype":"venue"
},
  "geometry": {"coordinates":[153.049362183,-28.8576812744],"type":"Point"}
}