{
  "type": "Feature",
  "properties": {
    "addr:full":"Unit 4/ 35 William St Beckenham WA 6107",
    "addr:housenumber":"35",
    "addr:postcode":"6107",
    "addr:street":"William St",
    "iso:country":"AU",
    "sg:address":"Unit 4/ 35 William St",
    "sg:city":"Beckenham",
    "sg:classifiers":[
        {
            "category":"Wholesale",
            "subcategory":"Painting Supplies",
            "type":"Manufacturing & Wholesale Goods"
        }
    ],
    "sg:phone":"+61 8 9458 1859",
    "sg:postcode":"6107",
    "sg:province":"WA",
    "sg:tags":[
        "product",
        "cleaning"
    ],
    "wof:name":"Sheraton Cleaning Products",
    "wof:placetype":"venue"
},
  "geometry": {"coordinates":[115.95224761999999,-32.0245056152],"type":"Point"}
}