{
  "type": "Feature",
  "properties": {
    "iso:country":"AU",
    "sg:address":"59 Cambridge Rd",
    "sg:city":"Bellerive",
    "sg:classifiers":[
        {
            "category":"Education",
            "subcategory":"Special Training",
            "type":"Public Place"
        }
    ],
    "sg:phone":"+61 3 6244 6785",
    "sg:postcode":"7018",
    "sg:province":"TAS",
    "sg:tags":[
        "school",
        "art"
    ],
    "wof:name":"Foreshore Art School",
    "wof:placetype":"venue"
},
  "geometry": {"coordinates":[147.36976623499999,-42.8724822998],"type":"Point"}
}