{
  "type": "Feature",
  "properties": {
    "iso:country":"AU",
    "sg:address":"263 Old Sale Rd",
    "sg:city":"Newborough North",
    "sg:classifiers":[
        {
            "category":"Communications",
            "subcategory":"Film & Video Production",
            "type":"Services"
        }
    ],
    "sg:phone":"+61 3 5126 1616",
    "sg:postcode":"3825",
    "sg:province":"VIC",
    "sg:tags":[
        "dvd",
        "library"
    ],
    "wof:name":"Network Video Newborough",
    "wof:placetype":"venue"
},
  "geometry": {"coordinates":[146.28836100000001,-38.175488],"type":"Point"}
}