{
  "type": "Feature",
  "properties": {
    "addr:full":"113 Dandaloo St Narromine NSW 2821",
    "addr:housenumber":"113",
    "addr:postcode":"2821",
    "addr:street":"Dandaloo St",
    "iso:country":"AU",
    "sg:address":"113 Dandaloo St",
    "sg:city":"Narromine",
    "sg:classifiers":[
        {
            "category":"Autos & Motor Vehicles",
            "subcategory":"Auto Supplies",
            "type":"Retail Goods"
        }
    ],
    "sg:phone":"+61 2 6889 1564",
    "sg:postcode":"2821",
    "sg:province":"NSW",
    "sg:tags":[
        "oil",
        "spirit"
    ],
    "wof:name":"Castrol Australia Pty Ltd",
    "wof:placetype":"venue"
},
  "geometry": {"coordinates":[148.23928832999999,-32.2345085144],"type":"Point"}
}