{
  "type": "Feature",
  "properties": {
    "iso:country":"AU",
    "sg:address":"PO Box 60",
    "sg:city":"Kuranda",
    "sg:classifiers":[
        {
            "category":"Freight",
            "type":"Transportation"
        }
    ],
    "sg:phone":"+61 407 184 331",
    "sg:postcode":"4872",
    "sg:province":"QLD",
    "sg:tags":[
        "light",
        "carrier"
    ],
    "wof:name":"Kuranda-Carriers",
    "wof:placetype":"venue"
},
  "geometry": {"coordinates":[145.1068573,-17.9841003418],"type":"Point"}
}