{
  "type": "Feature",
  "properties": {
    "addr:full":"PO Box 17 Sorell TAS 7172",
    "addr:postcode":"7172",
    "iso:country":"AU",
    "sg:address":"PO Box 17",
    "sg:city":"Sorell",
    "sg:classifiers":[
        {
            "category":"Building & Trades",
            "subcategory":"Construction",
            "type":"Services"
        }
    ],
    "sg:phone":"+61 408 317 746",
    "sg:postcode":"7172",
    "sg:province":"TAS",
    "sg:tags":[
        "earth",
        "excavating",
        "moving",
        "contractor"
    ],
    "wof:name":"Fletcher-Jones Scott",
    "wof:placetype":"venue"
},
  "geometry": {"coordinates":[147.563598633,-42.7815818787],"type":"Point"}
}