{
  "type": "Feature",
  "properties": {
    "iso:country":"AU",
    "sg:address":"19 Pitt St",
    "sg:city":"Sydney",
    "sg:classifiers":[
        {
            "category":"Banks & Credit Unions",
            "subcategory":"Financial Services",
            "type":"Services"
        }
    ],
    "sg:phone":"+61 2 9252 4616",
    "sg:postcode":"2000",
    "sg:province":"NSW",
    "sg:tags":[
        "merchant",
        "banker"
    ],
    "wof:name":"Cunnington & Co",
    "wof:placetype":"venue"
},
  "geometry": {"coordinates":[151.20901489299999,-33.8619728088],"type":"Point"}
}