{
  "type": "Feature",
  "properties": {
    "iso:country":"AU",
    "sg:address":"Blanche St",
    "sg:city":"Edithburgh",
    "sg:classifiers":[
        {
            "category":"Travel",
            "subcategory":"Hotels & Motels",
            "type":"Entertainment"
        }
    ],
    "sg:phone":"+61 8 8852 6013",
    "sg:postcode":"5583",
    "sg:province":"SA",
    "wof:name":"Troubridge Hotel",
    "wof:placetype":"venue"
},
  "geometry": {"coordinates":[137.74577331500001,-35.0841255188],"type":"Point"}
}