{
  "type": "Feature",
  "properties": {
    "addr:full":"Cnr Hallam & Abbott Rds Hallam VIC 3803",
    "addr:postcode":"3803",
    "addr:street":"Cnr",
    "iso:country":"AU",
    "sg:address":"Cnr Hallam & Abbott Rds",
    "sg:city":"Hallam",
    "sg:classifiers":[
        {
            "category":"Professional",
            "subcategory":"Engineering",
            "type":"Services"
        }
    ],
    "sg:phone":"+61 3 9703 2878",
    "sg:postcode":"3803",
    "sg:province":"VIC",
    "sg:tags":[
        "engineer",
        "structural"
    ],
    "wof:name":"Steelfinne Fabrications Pty Ltd",
    "wof:placetype":"venue"
},
  "geometry": {"coordinates":[145.27320861800001,-38.0067749023],"type":"Point"}
}