{
  "type": "Feature",
  "properties": {
    "addr:full":"Sargood St Jerilderie NSW 2716",
    "addr:postcode":"2716",
    "iso:country":"AU",
    "sg:address":"Sargood St",
    "sg:city":"Jerilderie",
    "sg:classifiers":[
        {
            "category":"Building & Trades",
            "subcategory":"Construction",
            "type":"Services"
        }
    ],
    "sg:phone":"+61 3 5886 1289",
    "sg:postcode":"2716",
    "sg:province":"NSW",
    "sg:tags":[
        "welding"
    ],
    "wof:name":"East End Welding & Hardware",
    "wof:placetype":"venue"
},
  "geometry": {"coordinates":[145.74095153799999,-35.3609580994],"type":"Point"}
}