{
  "type": "Feature",
  "properties": {
    "addr:full":"Shop 1/ 247 Belmore Rd Riverwood NSW 2210",
    "addr:housenumber":"shop 1 / 247",
    "addr:postcode":"2210",
    "addr:street":"Belmore Rd",
    "iso:country":"AU",
    "sg:address":"Shop 1/ 247 Belmore Rd",
    "sg:city":"Riverwood",
    "sg:classifiers":[
        {
            "category":"Health Services",
            "subcategory":"Doctor",
            "type":"Services"
        }
    ],
    "sg:phone":"+61 2 9584 2077",
    "sg:postcode":"2210",
    "sg:province":"NSW",
    "sg:tags":[
        "medical",
        "practitioner"
    ],
    "wof:name":"Chen E Dr",
    "wof:placetype":"venue"
},
  "geometry": {"coordinates":[151.05169699999999,-33.952824],"type":"Point"}
}