{
  "type": "Feature",
  "properties": {
    "addr:full":"75 George St Millicent SA 5280",
    "addr:housenumber":"75",
    "addr:postcode":"5280",
    "addr:street":"George St",
    "iso:country":"AU",
    "sg:address":"75 George St",
    "sg:city":"Millicent",
    "sg:classifiers":[
        {
            "category":"Personal",
            "subcategory":"Beauty Salon",
            "type":"Services"
        }
    ],
    "sg:phone":"+61 8 8733 2055",
    "sg:postcode":"5280",
    "sg:province":"SA",
    "sg:tags":[
        "hairdresser"
    ],
    "wof:name":"Angs Hair Affair",
    "wof:placetype":"venue"
},
  "geometry": {"coordinates":[140.354309,-37.595406],"type":"Point"}
}