{
  "type": "Feature",
  "properties": {
    "addr:full":"Lot 32 Jubilee Rd Glen Iris WA 6230",
    "addr:housenumber":"32",
    "addr:postcode":"6230",
    "addr:street":"Jubilee Rd",
    "iso:country":"AU",
    "sg:address":"Lot 32 Jubilee Rd",
    "sg:city":"Glen Iris",
    "sg:classifiers":[
        {
            "category":"Farming",
            "subcategory":"Fish & Marine Products",
            "type":"Manufacturing & Wholesale Goods"
        }
    ],
    "sg:phone":"+61 8 9725 4865",
    "sg:postcode":"6230",
    "sg:province":"WA",
    "sg:tags":[
        "fisherman"
    ],
    "wof:name":"Scimone B G & L S",
    "wof:placetype":"venue"
},
  "geometry": {"coordinates":[115.683922,-33.336163],"type":"Point"}
}