{
  "type": "Feature",
  "properties": {
    "addr:full":"42 Foxmont Drv Carina QLD 4152",
    "addr:housenumber":"42",
    "addr:postcode":"4152",
    "addr:street":"Foxmont Drv",
    "iso:country":"AU",
    "sg:address":"42 Foxmont Drv",
    "sg:city":"Carina",
    "sg:classifiers":[
        {
            "category":"Professional",
            "subcategory":"Accounting & Tax Preparation",
            "type":"Services"
        }
    ],
    "sg:phone":"+61 7 3398 1681",
    "sg:postcode":"4152",
    "sg:province":"QLD",
    "sg:tags":[
        "bookkeeping"
    ],
    "wof:name":"Competent Services",
    "wof:placetype":"venue"
},
  "geometry": {"coordinates":[153.099151611,-27.4799537659],"type":"Point"}
}