{
  "type": "Feature",
  "properties": {
    "addr:full":"9 White St Bayswater WA 6053",
    "addr:housenumber":"9",
    "addr:postcode":"6053",
    "addr:street":"White St",
    "iso:country":"AU",
    "sg:address":"9 White St",
    "sg:city":"Bayswater",
    "sg:classifiers":[
        {
            "category":"Manufacturing",
            "subcategory":"Furniture",
            "type":"Manufacturing & Wholesale Goods"
        }
    ],
    "sg:phone":"+61 8 9370 4933",
    "sg:postcode":"6053",
    "sg:province":"WA",
    "sg:tags":[
        "builder",
        "designer",
        "custom"
    ],
    "wof:name":"Kendor Industries",
    "wof:placetype":"venue"
},
  "geometry": {"coordinates":[115.921058655,-31.9105358124],"type":"Point"}
}