{
  "type": "Feature",
  "properties": {
    "iso:country":"AU",
    "sg:address":"10/ 10a Edward St",
    "sg:city":"Baulkham Hills",
    "sg:classifiers":[
        {
            "category":"Building & Trades",
            "subcategory":"Construction",
            "type":"Services"
        }
    ],
    "sg:phone":"+61 2 9686 3265",
    "sg:postcode":"2153",
    "sg:province":"NSW",
    "sg:tags":[
        "earth",
        "excavating",
        "moving",
        "contractor"
    ],
    "wof:name":"Hartnett R M",
    "wof:placetype":"venue"
},
  "geometry": {"coordinates":[150.99554443400001,-33.7487182617],"type":"Point"}
}