{
  "type": "Feature",
  "properties": {
    "addr:full":"30 Overport Rd Frankston South VIC 3199",
    "addr:housenumber":"30",
    "addr:postcode":"3199",
    "addr:street":"Overport Rd",
    "iso:country":"AU",
    "sg:address":"30 Overport Rd",
    "sg:city":"Frankston South",
    "sg:classifiers":[
        {
            "category":"Personal",
            "subcategory":"Massage",
            "type":"Services"
        }
    ],
    "sg:phone":"+61 3 9783 5156",
    "sg:postcode":"3199",
    "sg:province":"VIC",
    "sg:tags":[
        "therapy"
    ],
    "wof:name":"Lelean Peter",
    "wof:placetype":"venue"
},
  "geometry": {"coordinates":[145.12806701700001,-38.1636047363],"type":"Point"}
}