{
  "type": "Feature",
  "properties": {
    "addr:full":"47 Somerset Crs South Hedland WA 6722",
    "addr:housenumber":"47",
    "addr:postcode":"6722",
    "addr:street":"Somerset Crs South",
    "iso:country":"AU",
    "sg:address":"47 Somerset Crs",
    "sg:city":"South Hedland",
    "sg:classifiers":[
        {
            "category":"Utilities",
            "subcategory":"Electric",
            "type":"Services"
        }
    ],
    "sg:phone":"+61 8 9172 1772",
    "sg:postcode":"6722",
    "sg:province":"WA",
    "sg:tags":[
        "electrical",
        "contractor"
    ],
    "wof:name":"Ibbotson Electrical Drafting Pty Ltd",
    "wof:placetype":"venue"
},
  "geometry": {"coordinates":[118.60131072999999,-20.4081993103],"type":"Point"}
}