{
  "type": "Feature",
  "properties": {
    "addr:full":"211 Newton Rd Wetherill Park NSW 2164",
    "addr:housenumber":"211",
    "addr:postcode":"2164",
    "addr:street":"Newton Rd",
    "iso:country":"AU",
    "sg:address":"211 Newton Rd",
    "sg:city":"Wetherill Park",
    "sg:classifiers":[
        {
            "category":"Home & Garden",
            "subcategory":"Building Materials",
            "type":"Retail Goods"
        }
    ],
    "sg:phone":"+61 2 9604 6860",
    "sg:postcode":"2164",
    "sg:province":"NSW",
    "sg:tags":[
        "fitting",
        "door"
    ],
    "wof:name":"In Style Doors",
    "wof:placetype":"venue"
},
  "geometry": {"coordinates":[150.89202880900001,-33.8390159607],"type":"Point"}
}