{
  "type": "Feature",
  "properties": {
    "addr:full":"22 Chewings St Alice Springs NT 0870",
    "addr:housenumber":"22",
    "addr:postcode":"nt 0870",
    "addr:street":"Chewings St",
    "iso:country":"AU",
    "sg:address":"22 Chewings St",
    "sg:city":"Alice Springs",
    "sg:classifiers":[
        {
            "category":"Travel",
            "subcategory":"Travel Agent",
            "type":"Entertainment"
        }
    ],
    "sg:phone":"+61 8 8953 2933",
    "sg:postcode":"0870",
    "sg:province":"NT",
    "sg:tags":[
        "tour",
        "holiday",
        "adventure"
    ],
    "wof:name":"Trek Larapinta",
    "wof:placetype":"venue"
},
  "geometry": {"coordinates":[133.889282227,-23.6932353973],"type":"Point"}
}