{
  "type": "Feature",
  "properties": {
    "addr:full":"Unit 4, 17 Barton St Katoomba NSW 2780",
    "addr:housenumber":"17",
    "addr:postcode":"2780",
    "addr:street":"Barton St",
    "iso:country":"AU",
    "sg:address":"Unit 4, 17 Barton St",
    "sg:city":"Katoomba",
    "sg:classifiers":[
        {
            "category":"Social Services",
            "subcategory":"Adult Care",
            "type":"Services"
        }
    ],
    "sg:phone":"+61 2 4782 3346",
    "sg:postcode":"2780",
    "sg:province":"NSW",
    "sg:tags":[
        "towing"
    ],
    "wof:name":"Katoomba Smash Repairs",
    "wof:placetype":"venue"
},
  "geometry": {"coordinates":[150.31565856899999,-33.7032966614],"type":"Point"}
}