{
  "type": "Feature",
  "properties": {
    "addr:full":"Davey St Taradale VIC 3447",
    "addr:postcode":"3447",
    "addr:street":"Davey St",
    "iso:country":"AU",
    "sg:address":"Davey St",
    "sg:city":"Taradale",
    "sg:classifiers":[
        {
            "category":"Professional",
            "subcategory":"Accounting & Tax Preparation",
            "type":"Services"
        }
    ],
    "sg:phone":"+61 3 5423 2003",
    "sg:postcode":"3447",
    "sg:province":"VIC",
    "sg:tags":[
        "bookkeeping"
    ],
    "wof:name":"Express Bookkeeping Maryborough",
    "wof:placetype":"venue"
},
  "geometry": {"coordinates":[144.347213745,-37.1366386414],"type":"Point"}
}