{
  "type": "Feature",
  "properties": {
    "addr:full":"81 Limestone St Ipswich QLD 4305",
    "addr:housenumber":"81",
    "addr:postcode":"4305",
    "addr:street":"Limestone St",
    "iso:country":"AU",
    "sg:address":"81 Limestone St",
    "sg:city":"Ipswich",
    "sg:classifiers":[
        {
            "category":"Real Estate",
            "subcategory":"Real Estate Agent",
            "type":"Services"
        }
    ],
    "sg:phone":"+61 7 3282 9655",
    "sg:postcode":"4305",
    "sg:province":"QLD",
    "wof:name":"Ray White Commercial",
    "wof:placetype":"venue"
},
  "geometry": {"coordinates":[152.756469727,-27.6150493622],"type":"Point"}
}