{
  "type": "Feature",
  "properties": {
    "addr:full":"PO Box 582 Echuca VIC 3564",
    "addr:postcode":"3564",
    "iso:country":"AU",
    "sg:address":"PO Box 582",
    "sg:city":"Echuca",
    "sg:classifiers":[
        {
            "category":"Professional",
            "subcategory":"Art Services",
            "type":"Services"
        }
    ],
    "sg:phone":"+61 408 303 632",
    "sg:postcode":"3564",
    "sg:province":"VIC",
    "sg:tags":[
        "decorator",
        "painter"
    ],
    "wof:name":"C & L Hauke",
    "wof:placetype":"venue"
},
  "geometry": {"coordinates":[144.74836730999999,-36.1293907166],"type":"Point"}
}