{
  "type": "Feature",
  "properties": {
    "iso:country":"AU",
    "sg:address":"Cnr Old Hume Hwy & Cavendish St",
    "sg:city":"Mittagong",
    "sg:classifiers":[
        {
            "category":"Insurance",
            "subcategory":"Hazard Insurance",
            "type":"Services"
        }
    ],
    "sg:phone":"+61 2 4872 1951",
    "sg:postcode":"2575",
    "sg:province":"NSW",
    "sg:tags":[
        "motor",
        "vehicle"
    ],
    "wof:name":"Greenslip King The",
    "wof:placetype":"venue"
},
  "geometry": {"coordinates":[150.44769287099999,-34.4510383606],"type":"Point"}
}