{
  "type": "Feature",
  "properties": {
    "iso:country":"AU",
    "sg:address":"Level 4/ 88 Ricketts Rd",
    "sg:city":"Mt Waverley",
    "sg:classifiers":[
        {
            "category":"Insurance",
            "subcategory":"Insurance Agent",
            "type":"Services"
        }
    ],
    "sg:phone":"+61 3 9550 6020",
    "sg:postcode":"3149",
    "sg:province":"VIC",
    "sg:tags":[
        "broker"
    ],
    "wof:name":"Aged Care Insurance Services Pty Ltd",
    "wof:placetype":"venue"
},
  "geometry": {"coordinates":[145.130783081,-37.8948364258],"type":"Point"}
}