{
  "type": "Feature",
  "properties": {
    "addr:full":"30 Barford St Speers Point NSW 2284",
    "addr:housenumber":"30",
    "addr:postcode":"2284",
    "addr:street":"Barford St",
    "iso:country":"AU",
    "sg:address":"30 Barford St",
    "sg:city":"Speers Point",
    "sg:classifiers":[
        {
            "category":"Autos & Motor Vehicles",
            "subcategory":"Auto Supplies",
            "type":"Retail Goods"
        }
    ],
    "sg:phone":"+61 2 4958 3266",
    "sg:postcode":"2284",
    "sg:province":"NSW",
    "sg:tags":[
        "tyre"
    ],
    "wof:name":"Damo's Second Hand Tyres",
    "wof:placetype":"venue"
},
  "geometry": {"coordinates":[151.62628173799999,-32.9625968933],"type":"Point"}
}