{
  "type": "Feature",
  "properties": {
    "addr:full":"8 Lancelot Crt Hillside (Sydenham) VIC 3037",
    "addr:housenumber":"8",
    "addr:postcode":"3037",
    "addr:street":"Lancelot Crt Hillside",
    "iso:country":"AU",
    "sg:address":"8 Lancelot Crt",
    "sg:city":"Hillside (Sydenham)",
    "sg:classifiers":[
        {
            "category":"Professional",
            "type":"Services"
        }
    ],
    "sg:phone":"+61 405 040 090",
    "sg:postcode":"3037",
    "sg:province":"VIC",
    "sg:tags":[
        "transport"
    ],
    "wof:name":"Zokee Transportation",
    "wof:placetype":"venue"
},
  "geometry": {"coordinates":[144.72846999999999,-37.68187],"type":"Point"}
}