{
  "type": "Feature",
  "properties": {
    "addr:full":"Unit 7 /53- 55 Gladesville Rd Hunters Hill NSW 2110",
    "addr:housenumber":"55",
    "addr:postcode":"2110",
    "addr:street":"Gladesville Rd",
    "iso:country":"AU",
    "sg:address":"Unit 7 /53- 55 Gladesville Rd",
    "sg:city":"Hunters Hill",
    "sg:classifiers":[
        {
            "category":"Professional",
            "subcategory":"Engineering",
            "type":"Services"
        }
    ],
    "sg:phone":"+61 2 9816 1577",
    "sg:postcode":"2110",
    "sg:province":"NSW",
    "sg:tags":[
        "consulting",
        "engineer"
    ],
    "wof:name":"CNF & Associates Pty Limited",
    "wof:placetype":"venue"
},
  "geometry": {"coordinates":[151.14419555699999,-33.8336105347],"type":"Point"}
}