{
  "type": "Feature",
  "properties": {
    "iso:country":"AU",
    "sg:address":"Gordon St",
    "sg:city":"Footscray",
    "sg:classifiers":[
        {
            "category":"Shopping",
            "subcategory":"Computers & Home Electronics",
            "type":"Retail Goods"
        }
    ],
    "sg:phone":"+61 3 9687 7820",
    "sg:postcode":"3011",
    "sg:province":"VIC",
    "sg:tags":[
        "equipment",
        "multimedia"
    ],
    "wof:name":"Nectarine",
    "wof:placetype":"venue"
},
  "geometry": {"coordinates":[144.889434814,-37.7915725708],"type":"Point"}
}