{
  "type": "Feature",
  "properties": {
    "addr:full":"Factory 3, 5 Aristoc Rd Glen Waverley VIC 3150",
    "addr:housenumber":"5",
    "addr:postcode":"3150",
    "addr:street":"Aristoc Rd",
    "iso:country":"AU",
    "sg:address":"Factory 3, 5 Aristoc Rd",
    "sg:city":"Glen Waverley",
    "sg:classifiers":[
        {
            "category":"Manufacturing",
            "subcategory":"Motor Vehicles & Parts",
            "type":"Manufacturing & Wholesale Goods"
        }
    ],
    "sg:phone":"+61 3 9560 3400",
    "sg:postcode":"3150",
    "sg:province":"VIC",
    "sg:tags":[
        "replacement"
    ],
    "wof:name":"R & E Autos",
    "wof:placetype":"venue"
},
  "geometry": {"coordinates":[145.158035278,-37.8849182129],"type":"Point"}
}