{
  "type": "Feature",
  "properties": {
    "iso:country":"AU",
    "sg:address":"52A Wellington St",
    "sg:city":"Longford",
    "sg:classifiers":[
        {
            "category":"Banks & Credit Unions",
            "subcategory":"Bureau De Change",
            "type":"Services"
        }
    ],
    "sg:phone":"+61 418 135 729",
    "sg:postcode":"7301",
    "sg:province":"TAS",
    "sg:tags":[
        "repairs",
        "part",
        "appliance",
        "electrical"
    ],
    "wof:name":"Ross Chugg Appliance Repairs & Service",
    "wof:placetype":"venue"
},
  "geometry": {"coordinates":[147.12123099999999,-41.592133],"type":"Point"}
}