{
  "type": "Feature",
  "properties": {
    "addr:full":"PO Box 86 Belmont WA 6104",
    "addr:postcode":"6104",
    "iso:country":"AU",
    "sg:address":"PO Box 86",
    "sg:city":"Belmont",
    "sg:classifiers":[
        {
            "category":"Coffee & Tea",
            "type":"Food & Drink"
        }
    ],
    "sg:phone":"+61 8 9378 1333",
    "sg:postcode":"6104",
    "sg:province":"WA",
    "sg:tags":[
        "kayak",
        "canoe"
    ],
    "wof:name":"Ascot Kayak Club",
    "wof:placetype":"venue"
},
  "geometry": {"coordinates":[115.933372498,-31.941619873],"type":"Point"}
}