{
  "type": "Feature",
  "properties": {
    "addr:full":"Cnr Service Rd & Watland St Springwood QLD 4127",
    "addr:postcode":"4127",
    "addr:street":"Service Rd &;St",
    "iso:country":"AU",
    "sg:address":"Cnr Service Rd & Watland St",
    "sg:city":"Springwood",
    "sg:classifiers":[
        {
            "category":"Professional",
            "subcategory":"Printing & Photocopies",
            "type":"Services"
        }
    ],
    "sg:phone":"+61 7 3299 5488",
    "sg:postcode":"4127",
    "sg:province":"QLD",
    "sg:tags":[
        "photocopying"
    ],
    "wof:name":"Instant Print & Copy",
    "wof:placetype":"venue"
},
  "geometry": {"coordinates":[153.132324219,-27.6249332428],"type":"Point"}
}