{
  "type": "Feature",
  "properties": {
    "iso:country":"AU",
    "sg:address":"Shop 49 Lansell Plaza",
    "sg:city":"Kangaroo Flat",
    "sg:classifiers":[
        {
            "category":"Food & Beverages",
            "subcategory":"Bakery",
            "type":"Retail Goods"
        }
    ],
    "sg:phone":"+61 3 5447 1181",
    "sg:postcode":"3555",
    "sg:province":"VIC",
    "sg:tags":[
        "baker"
    ],
    "wof:name":"Baker's Delight Holdings",
    "wof:placetype":"venue"
},
  "geometry": {"coordinates":[144.244903564,-36.7924613953],"type":"Point"}
}