{
  "type": "Feature",
  "properties": {
    "addr:full":"PO Box 273 Chelsea VIC 3196",
    "addr:postcode":"3196",
    "iso:country":"AU",
    "sg:address":"PO Box 273",
    "sg:city":"Chelsea",
    "sg:classifiers":[
        {
            "category":"Health Services",
            "subcategory":"Health Practitioner",
            "type":"Services"
        }
    ],
    "sg:phone":"+61 3 9776 0142",
    "sg:postcode":"3196",
    "sg:province":"VIC",
    "sg:tags":[
        "psychologist"
    ],
    "wof:name":"Catanese A.A. (Tony) & Associates",
    "wof:placetype":"venue"
},
  "geometry": {"coordinates":[145.113937378,-38.0481185913],"type":"Point"}
}