{
  "type": "Feature",
  "properties": {
    "addr:full":"14/ 2 Brown St Labrador QLD 4215",
    "addr:housenumber":"14 / 2",
    "addr:postcode":"4215",
    "addr:street":"Brown St",
    "iso:country":"AU",
    "sg:address":"14/ 2 Brown St",
    "sg:city":"Labrador",
    "sg:classifiers":[
        {
            "category":"Banks & Credit Unions",
            "subcategory":"Financial Services",
            "type":"Services"
        }
    ],
    "sg:phone":"+61 7 5532 0997",
    "sg:postcode":"4215",
    "sg:province":"QLD",
    "sg:tags":[
        "planning"
    ],
    "wof:name":"Financial Tactics",
    "wof:placetype":"venue"
},
  "geometry": {"coordinates":[153.39454650900001,-27.9471912384],"type":"Point"}
}