{
  "type": "Feature",
  "properties": {
    "addr:full":"121 Tillyard Drv Charnwood ACT 2615",
    "addr:housenumber":"121",
    "addr:postcode":"2615",
    "addr:street":"Tillyard Drv",
    "iso:country":"AU",
    "sg:address":"121 Tillyard Drv",
    "sg:city":"Charnwood",
    "sg:classifiers":[
        {
            "category":"Food & Beverages",
            "subcategory":"Supermarket",
            "type":"Retail Goods"
        }
    ],
    "sg:phone":"+61 2 6258 0658",
    "sg:postcode":"2615",
    "sg:province":"ACT",
    "sg:tags":[
        "grocery",
        "store"
    ],
    "wof:name":"Charnwood Supermarket",
    "wof:placetype":"venue"
},
  "geometry": {"coordinates":[149.044555664,-35.1978111267],"type":"Point"}
}