{
  "type": "Feature",
  "properties": {
    "iso:country":"AU",
    "sg:address":"239 Sydney Rd",
    "sg:city":"Fairlight",
    "sg:classifiers":[
        {
            "category":"Health Services",
            "subcategory":"Chiropractor",
            "type":"Services"
        }
    ],
    "sg:phone":"+61 2 9948 1767",
    "sg:postcode":"2094",
    "sg:province":"NSW",
    "wof:name":"Prestidge Chiropractic",
    "wof:placetype":"venue"
},
  "geometry": {"coordinates":[151.271362305,-33.7951278687],"type":"Point"}
}