{
  "type": "Feature",
  "properties": {
    "iso:country":"AU",
    "sg:address":"42 Central St",
    "sg:city":"Labrador",
    "sg:classifiers":[
        {
            "category":"Building & Trades",
            "subcategory":"Cleaning & Sanitation",
            "type":"Services"
        }
    ],
    "sg:phone":"+61 7 5531 4207",
    "sg:postcode":"4215",
    "sg:province":"QLD",
    "sg:tags":[
        "commercial",
        "maintenance"
    ],
    "wof:name":"John Butler & Associates",
    "wof:placetype":"venue"
},
  "geometry": {"coordinates":[153.40484619099999,-27.9490013123],"type":"Point"}
}