{
  "type": "Feature",
  "properties": {
    "addr:full":"77 York St Prahran VIC 3181",
    "addr:housenumber":"77",
    "addr:postcode":"3181",
    "addr:street":"York St",
    "iso:country":"AU",
    "sg:address":"77 York St",
    "sg:city":"Prahran",
    "sg:classifiers":[
        {
            "category":"Communications",
            "type":"Services"
        }
    ],
    "sg:phone":"+61 3 9510 9286",
    "sg:postcode":"3181",
    "sg:province":"VIC",
    "sg:tags":[
        "translation"
    ],
    "wof:name":"Japanese Language Services (Aust)",
    "wof:placetype":"venue"
},
  "geometry": {"coordinates":[144.99818420400001,-37.8496284485],"type":"Point"}
}