{
  "type": "Feature",
  "properties": {
    "iso:country":"AU",
    "sg:address":"67 Hampden Rd",
    "sg:city":"Nedlands",
    "sg:classifiers":[
        {
            "category":"Banks & Credit Unions",
            "subcategory":"Financial Services",
            "type":"Services"
        }
    ],
    "sg:phone":"+61 8 9389 8871",
    "sg:postcode":"6009",
    "sg:province":"WA",
    "sg:tags":[
        "planning"
    ],
    "wof:name":"Advice Line",
    "wof:placetype":"venue"
},
  "geometry": {"coordinates":[115.813316,-31.975128],"type":"Point"}
}