{
  "type": "Feature",
  "properties": {
    "iso:country":"AU",
    "sg:address":"Mill St",
    "sg:city":"Canowindra",
    "sg:classifiers":[
        {
            "category":"Wholesale",
            "subcategory":"Machinery & Supplies",
            "type":"Manufacturing & Wholesale Goods"
        }
    ],
    "sg:phone":"+61 2 6344 1208",
    "sg:postcode":"2804",
    "sg:province":"NSW",
    "sg:tags":[
        "agricultural"
    ],
    "wof:name":"Lucerne Foods Canowindra Pty Ltd",
    "wof:placetype":"venue"
},
  "geometry": {"coordinates":[148.659500122,-33.5588417053],"type":"Point"}
}