{
  "type": "Feature",
  "properties": {
    "iso:country":"AU",
    "sg:address":"U5/ 3 La",
    "sg:city":"Fayette Blv Bibra Lake",
    "sg:classifiers":[
        {
            "category":"Building & Trades",
            "subcategory":"Construction",
            "type":"Services"
        }
    ],
    "sg:phone":"+61 8 9434 4044",
    "sg:postcode":"6163",
    "sg:province":"WA",
    "sg:tags":[
        "contractor"
    ],
    "wof:name":"Pattersons Pty Ltd",
    "wof:placetype":"venue"
},
  "geometry": {"coordinates":[115.813782,-32.090302],"type":"Point"}
}