{
  "type": "Feature",
  "properties": {
    "addr:full":"320 Narellan Rd Mt Annan NSW 2567",
    "addr:housenumber":"320",
    "addr:postcode":"2567",
    "addr:street":"Narellan Rd",
    "iso:country":"AU",
    "sg:address":"320 Narellan Rd",
    "sg:city":"Mt Annan",
    "sg:classifiers":[
        {
            "category":"Home & Garden",
            "subcategory":"Building Materials",
            "type":"Retail Goods"
        }
    ],
    "sg:phone":"+61 2 4647 3788",
    "sg:postcode":"2567",
    "sg:province":"NSW",
    "sg:tags":[
        "retaining",
        "wall"
    ],
    "wof:name":"Flower Power Pty Ltd",
    "wof:placetype":"venue"
},
  "geometry": {"coordinates":[150.76399230999999,-34.0499534607],"type":"Point"}
}