{
  "type": "Feature",
  "properties": {
    "iso:country":"AU",
    "sg:address":"PO Box 490",
    "sg:city":"Bohle",
    "sg:classifiers":[
        {
            "category":"Mining & Drilling",
            "type":"Manufacturing & Wholesale Goods"
        }
    ],
    "sg:phone":"+61 417 889 800",
    "sg:postcode":"4818",
    "sg:province":"QLD",
    "sg:tags":[
        "boring",
        "contractor"
    ],
    "wof:name":"Jennings Drill & Blast",
    "wof:placetype":"venue"
},
  "geometry": {"coordinates":[146.711548,-19.262779],"type":"Point"}
}