{
  "type": "Feature",
  "properties": {
    "addr:full":"123 Charlotte St Cooktown QLD 4895",
    "addr:housenumber":"123",
    "addr:postcode":"4895",
    "addr:street":"Charlotte St",
    "iso:country":"AU",
    "sg:address":"123 Charlotte St",
    "sg:city":"Cooktown",
    "sg:classifiers":[
        {
            "category":"Banks & Credit Unions",
            "subcategory":"Bank",
            "type":"Services"
        }
    ],
    "sg:phone":"+61 13 20 32",
    "sg:postcode":"4895",
    "sg:province":"QLD",
    "wof:name":"Westpac Banking Corporation",
    "wof:placetype":"venue"
},
  "geometry": {"coordinates":[145.24710082999999,-15.475479126],"type":"Point"}
}