{
  "type": "Feature",
  "properties": {
    "iso:country":"AU",
    "sg:address":"Cnr Young Rd & Ranken St",
    "sg:city":"Cowra",
    "sg:classifiers":[
        {
            "category":"School Buses",
            "type":"Transportation"
        }
    ],
    "sg:phone":"+61 2 6342 1194",
    "sg:postcode":"2794",
    "sg:province":"NSW",
    "sg:tags":[
        "brick"
    ],
    "wof:name":"Cowra Concrete Products",
    "wof:placetype":"venue"
},
  "geometry": {"coordinates":[148.66810607900001,-33.845123291],"type":"Point"}
}