{
  "type": "Feature",
  "properties": {
    "addr:full":"1272 North East Rd St Agnes SA 5097",
    "addr:housenumber":"1272",
    "addr:postcode":"5097",
    "addr:street":"North East Rd",
    "iso:country":"AU",
    "sg:address":"1272 North East Rd St",
    "sg:city":"Agnes",
    "sg:classifiers":[
        {
            "category":"Personal",
            "type":"Services"
        }
    ],
    "sg:phone":"+61 8 8396 2280",
    "sg:postcode":"5097",
    "sg:province":"SA",
    "sg:tags":[
        "gift"
    ],
    "wof:name":"A Touch of Tahiti",
    "wof:placetype":"venue"
},
  "geometry": {"coordinates":[138.71607971200001,-34.8213615417],"type":"Point"}
}