{
  "type": "Feature",
  "properties": {
    "iso:country":"AU",
    "sg:address":"40 Rose St",
    "sg:city":"Fitzroy",
    "sg:classifiers":[
        {
            "category":"Real Estate",
            "subcategory":"Architect",
            "type":"Services"
        }
    ],
    "sg:phone":"+61 3 9974 4400",
    "sg:postcode":"3065",
    "sg:province":"VIC",
    "wof:name":"Cowland North Architecture Interior Design",
    "wof:placetype":"venue"
},
  "geometry": {"coordinates":[144.97645568900001,-37.7958106995],"type":"Point"}
}