{
  "type": "Feature",
  "properties": {
    "addr:full":"16A Main St Foster VIC 3960",
    "addr:housenumber":"16a",
    "addr:postcode":"3960",
    "addr:street":"Main St",
    "iso:country":"AU",
    "sg:address":"16A Main St",
    "sg:city":"Foster",
    "sg:classifiers":[
        {
            "category":"Shopping",
            "subcategory":"Shoes",
            "type":"Retail Goods"
        }
    ],
    "sg:phone":"+61 3 5682 1800",
    "sg:postcode":"3960",
    "sg:province":"VIC",
    "sg:tags":[
        "footwear"
    ],
    "wof:name":"Dragon Your Feet",
    "wof:placetype":"venue"
},
  "geometry": {"coordinates":[146.38706970199999,-38.7091407776],"type":"Point"}
}