{
  "type": "Feature",
  "properties": {
    "addr:full":"2 Lane St Wentworthville NSW 2145",
    "addr:housenumber":"2",
    "addr:postcode":"2145",
    "addr:street":"Lane St",
    "iso:country":"AU",
    "sg:address":"2 Lane St",
    "sg:city":"Wentworthville",
    "sg:classifiers":[
        {
            "category":"Manufacturing",
            "subcategory":"Food",
            "type":"Manufacturing & Wholesale Goods"
        }
    ],
    "sg:phone":"+61 2 9631 3066",
    "sg:postcode":"2145",
    "sg:province":"NSW",
    "sg:tags":[
        "function",
        "catering"
    ],
    "wof:name":"Herc John Catering",
    "wof:placetype":"venue"
},
  "geometry": {"coordinates":[150.97346496599999,-33.808303833],"type":"Point"}
}