{
  "type": "Feature",
  "properties": {
    "addr:full":"Shop 4 Hazelwood Village Shopng Cntr Churchill VIC 3842",
    "addr:housenumber":"shop 4",
    "addr:postcode":"3842",
    "addr:street":"Hazelwood Village Shopng Cntr",
    "iso:country":"AU",
    "sg:address":"Shop 4 Hazelwood Village Shopng Cntr",
    "sg:city":"Churchill",
    "sg:classifiers":[
        {
            "category":"Personal",
            "subcategory":"Tanning Parlor",
            "type":"Services"
        }
    ],
    "sg:phone":"+61 3 5122 3311",
    "sg:postcode":"3842",
    "sg:province":"VIC",
    "sg:tags":[
        "solarium"
    ],
    "wof:name":"Kats Hair Design",
    "wof:placetype":"venue"
},
  "geometry": {"coordinates":[146.42181396500001,-38.3153915405],"type":"Point"}
}