{
  "type": "Feature",
  "properties": {
    "iso:country":"AU",
    "sg:address":"1/ 5 Brand Drv",
    "sg:city":"Thomastown",
    "sg:classifiers":[
        {
            "category":"Home & Garden",
            "subcategory":"Garden Supply",
            "type":"Retail Goods"
        }
    ],
    "sg:phone":"+61 3 9465 2020",
    "sg:postcode":"3074",
    "sg:province":"VIC",
    "sg:tags":[
        "equipment",
        "hydroponics"
    ],
    "wof:name":"Waterworks Hydroponics",
    "wof:placetype":"venue"
},
  "geometry": {"coordinates":[145.03395080600001,-37.6927833557],"type":"Point"}
}