{
  "type": "Feature",
  "properties": {
    "addr:full":"316 St Pauls Tce Fortitude Valley QLD 4006",
    "addr:housenumber":"316",
    "addr:postcode":"4006",
    "addr:street":"St Pauls Tce",
    "iso:country":"AU",
    "sg:address":"316 St",
    "sg:city":"Pauls Tce Fortitude Valley",
    "sg:classifiers":[
        {
            "category":"Shopping",
            "subcategory":"Optical Goods",
            "type":"Retail Goods"
        }
    ],
    "sg:phone":"+61 7 3252 2061",
    "sg:postcode":"4006",
    "sg:province":"QLD",
    "sg:tags":[
        "supply"
    ],
    "wof:name":"A York Optical & Scientific",
    "wof:placetype":"venue"
},
  "geometry": {"coordinates":[153.031341553,-27.4560661316],"type":"Point"}
}