{
  "type": "Feature",
  "properties": {
    "addr:full":"401/ 177-185 William St Darlinghurst NSW 2010",
    "addr:housenumber":"401 / 177-185",
    "addr:postcode":"2010",
    "addr:street":"William St",
    "iso:country":"AU",
    "sg:address":"401/ 177-185 William St",
    "sg:city":"Darlinghurst",
    "sg:classifiers":[
        {
            "category":"Organizations",
            "subcategory":"Professional Association",
            "type":"Services"
        }
    ],
    "sg:phone":"+61 2 9947 2920",
    "sg:postcode":"2010",
    "sg:province":"NSW",
    "sg:tags":[
        "web",
        "internet"
    ],
    "wof:name":"Allure Media",
    "wof:placetype":"venue"
},
  "geometry": {"coordinates":[151.219314575,-33.8749694824],"type":"Point"}
}