{
  "type": "Feature",
  "properties": {
    "addr:full":"200 Eleventh St Mildura VIC 3500",
    "addr:housenumber":"200",
    "addr:postcode":"3500",
    "addr:street":"Eleventh St",
    "iso:country":"AU",
    "sg:address":"200 Eleventh St",
    "sg:city":"Mildura",
    "sg:classifiers":[
        {
            "category":"Farming",
            "subcategory":"Fish & Marine Products",
            "type":"Manufacturing & Wholesale Goods"
        }
    ],
    "sg:phone":"+61 3 5021 2230",
    "sg:postcode":"3500",
    "sg:province":"VIC",
    "sg:tags":[
        "organic"
    ],
    "wof:name":"Organics On Eleventh",
    "wof:placetype":"venue"
},
  "geometry": {"coordinates":[142.16189575199999,-34.1930961609],"type":"Point"}
}