{
  "type": "Feature",
  "properties": {
    "addr:full":"79- 83 Rawson Rd Woy Woy NSW 2256",
    "addr:housenumber":"83",
    "addr:postcode":"2256",
    "addr:street":"Rawson Rd",
    "iso:country":"AU",
    "sg:address":"79- 83 Rawson Rd",
    "sg:city":"Woy Woy",
    "sg:classifiers":[
        {
            "category":"Retail",
            "subcategory":"Auto Repair",
            "type":"Services"
        }
    ],
    "sg:phone":"+61 2 4341 9353",
    "sg:postcode":"2256",
    "sg:province":"NSW",
    "sg:tags":[
        "repairer",
        "motor",
        "engineer"
    ],
    "wof:name":"Woy Woy Automatic Transmission Service",
    "wof:placetype":"venue"
},
  "geometry": {"coordinates":[151.32000732399999,-33.4935836792],"type":"Point"}
}