{
  "type": "Feature",
  "properties": {
    "addr:full":"Suite 3, 31-33 Hosken St Bluff Point, Geraldton WA 6530",
    "addr:housenumber":"31-33",
    "addr:postcode":"6530",
    "addr:street":"Hosken St Bluff",
    "iso:country":"AU",
    "sg:address":"Suite 3, 31-33 Hosken St",
    "sg:city":"Bluff Point, Geraldton",
    "sg:classifiers":[
        {
            "category":"Banks & Credit Unions",
            "subcategory":"Bank",
            "type":"Services"
        }
    ],
    "sg:phone":"+61 8 9923 0288",
    "sg:postcode":"6530",
    "sg:province":"WA",
    "wof:name":"Rabobank",
    "wof:placetype":"venue"
},
  "geometry": {"coordinates":[114.625610352,-28.7366542816],"type":"Point"}
}