{
  "type": "Feature",
  "properties": {
    "iso:country":"AU",
    "sg:address":"31 Cutler Rd",
    "sg:city":"Jandakot",
    "sg:classifiers":[
        {
            "category":"Building & Trades",
            "subcategory":"Pest Control",
            "type":"Services"
        }
    ],
    "sg:phone":"+61 8 9417 2300",
    "sg:postcode":"6164",
    "sg:province":"WA",
    "sg:tags":[
        "equipment",
        "abattoir",
        "machinery"
    ],
    "wof:name":"Construct Engineering",
    "wof:placetype":"venue"
},
  "geometry": {"coordinates":[115.868378,-32.120716],"type":"Point"}
}