{
  "type": "Feature",
  "properties": {
    "addr:full":"5 Hilder Rd The Gap QLD 4061",
    "addr:housenumber":"5",
    "addr:postcode":"4061",
    "addr:street":"Hilder Rd",
    "iso:country":"AU",
    "sg:address":"5 Hilder Rd",
    "sg:city":"The Gap",
    "sg:classifiers":[
        {
            "category":"Insurance",
            "subcategory":"Insurance Agent",
            "type":"Services"
        }
    ],
    "sg:phone":"+61 7 3300 6663",
    "sg:postcode":"4061",
    "sg:province":"QLD",
    "wof:name":"Cross W & R and Associates Pty Ltd",
    "wof:placetype":"venue"
},
  "geometry": {"coordinates":[152.93800354000001,-27.4419174194],"type":"Point"}
}