{
  "type": "Feature",
  "properties": {
    "addr:full":"Ipswich Rd Buranda QLD 4102",
    "addr:postcode":"4102",
    "addr:street":"Ipswich Rd",
    "iso:country":"AU",
    "sg:address":"Ipswich Rd",
    "sg:city":"Buranda",
    "sg:classifiers":[
        {
            "category":"Fast Food",
            "type":"Food & Drink"
        }
    ],
    "sg:phone":"+61 7 3391 8699",
    "sg:postcode":"4102",
    "sg:province":"QLD",
    "sg:tags":[
        "away",
        "take"
    ],
    "wof:name":"Origin Kebab",
    "wof:placetype":"venue"
},
  "geometry": {"coordinates":[153.03825378400001,-27.4935073853],"type":"Point"}
}