{
  "type": "Feature",
  "properties": {
    "iso:country":"AU",
    "sg:address":"76 Regentville Rd",
    "sg:city":"Penrith",
    "sg:classifiers":[
        {
            "category":"Shopping",
            "subcategory":"Discount & Variety Stores",
            "type":"Retail Goods"
        }
    ],
    "sg:phone":"+61 2 9625 3888",
    "sg:postcode":"2750",
    "sg:province":"NSW",
    "sg:tags":[
        "register",
        "cash"
    ],
    "wof:name":"McCalls Services Business Equipment",
    "wof:placetype":"venue"
},
  "geometry": {"coordinates":[150.680908203,-33.7683105469],"type":"Point"}
}