{
  "type": "Feature",
  "properties": {
    "iso:country":"AU",
    "sg:address":"231 Springvale Rd",
    "sg:city":"Springvale",
    "sg:classifiers":[
        {
            "category":"Fast Food",
            "type":"Food & Drink"
        }
    ],
    "sg:phone":"+61 3 9546 8865",
    "sg:postcode":"3171",
    "sg:province":"VIC",
    "sg:tags":[
        "away",
        "take"
    ],
    "wof:name":"Hippos Hamburgers",
    "wof:placetype":"venue"
},
  "geometry": {"coordinates":[145.15342712399999,-37.9468536377],"type":"Point"}
}