{
  "type": "Feature",
  "properties": {
    "addr:full":"14 Aitken St Aitkenvale QLD 4814",
    "addr:housenumber":"14",
    "addr:postcode":"4814",
    "addr:street":"Aitken St",
    "iso:country":"AU",
    "sg:address":"14 Aitken St",
    "sg:city":"Aitkenvale",
    "sg:classifiers":[
        {
            "category":"Wholesale",
            "subcategory":"Apparel",
            "type":"Manufacturing & Wholesale Goods"
        }
    ],
    "sg:phone":"+61 7 4779 7577",
    "sg:postcode":"4814",
    "sg:province":"QLD",
    "sg:tags":[
        "wholesaler",
        "men's",
        "mfrs",
        "sportswear"
    ],
    "wof:name":"G.T. Shirts Pty Ltd",
    "wof:placetype":"venue"
},
  "geometry": {"coordinates":[146.770645,-19.295544],"type":"Point"}
}