{
  "type": "Feature",
  "properties": {
    "addr:full":"4 Howard Crt Bayswater VIC 3153",
    "addr:housenumber":"4",
    "addr:postcode":"3153",
    "addr:street":"Howard Crt",
    "iso:country":"AU",
    "sg:address":"4 Howard Crt",
    "sg:city":"Bayswater",
    "sg:classifiers":[
        {
            "category":"Retail",
            "subcategory":"Repair Shop",
            "type":"Services"
        }
    ],
    "sg:phone":"+61 3 9729 1989",
    "sg:postcode":"3153",
    "sg:province":"VIC",
    "sg:tags":[
        "upholsterer"
    ],
    "wof:name":"Eden Upholstery",
    "wof:placetype":"venue"
},
  "geometry": {"coordinates":[145.29713439899999,-37.8339195251],"type":"Point"}
}