{
  "type": "Feature",
  "properties": {
    "addr:full":"21 Ashley Ave West Pennant Hills NSW 2125",
    "addr:housenumber":"21",
    "addr:postcode":"2125",
    "addr:street":"Ashley Ave",
    "iso:country":"AU",
    "sg:address":"21 Ashley Ave",
    "sg:city":"West Pennant Hills",
    "sg:classifiers":[
        {
            "category":"Utilities",
            "subcategory":"Electric",
            "type":"Services"
        }
    ],
    "sg:phone":"+61 2 9872 1595",
    "sg:postcode":"2125",
    "sg:province":"NSW",
    "sg:tags":[
        "electrical",
        "contractor"
    ],
    "wof:name":"The Switch Doctor Electrical Pty Ltd",
    "wof:placetype":"venue"
},
  "geometry": {"coordinates":[151.04302978499999,-33.7555389404],"type":"Point"}
}