{
  "type": "Feature",
  "properties": {
    "addr:full":"6/41 C Stewart St Devonport TAS 7310",
    "addr:housenumber":"/ 41 c",
    "addr:postcode":"7310",
    "addr:street":"Stewart St",
    "iso:country":"AU",
    "sg:address":"6/41 C Stewart St",
    "sg:city":"Devonport",
    "sg:classifiers":[
        {
            "category":"Government",
            "subcategory":"Court House",
            "type":"Public Place"
        }
    ],
    "sg:phone":"+61 3 6423 6500",
    "sg:postcode":"7310",
    "sg:province":"TAS",
    "sg:tags":[
        "personal",
        "marriage",
        "family",
        "counselling"
    ],
    "wof:name":"Bowring Tony Counselling",
    "wof:placetype":"venue"
},
  "geometry": {"coordinates":[146.35145568900001,-41.1789703369],"type":"Point"}
}