{
  "type": "Feature",
  "properties": {
    "iso:country":"AU",
    "sg:address":"PO Box 874",
    "sg:city":"Gymea",
    "sg:classifiers":[
        {
            "category":"Industrial Area",
            "type":"Public Place"
        }
    ],
    "sg:phone":"+61 2 9521 5000",
    "sg:postcode":"2227",
    "sg:province":"NSW",
    "sg:tags":[
        "protective",
        "clothing"
    ],
    "wof:name":"000 Warning Products",
    "wof:placetype":"venue"
},
  "geometry": {"coordinates":[151.08496093799999,-34.0353317261],"type":"Point"}
}