{
  "type": "Feature",
  "properties": {
    "addr:full":"Lot 25 Scadden St Kellerberrin WA 6410",
    "addr:postcode":"6410",
    "addr:street":"St",
    "iso:country":"AU",
    "sg:address":"Lot 25 Scadden St",
    "sg:city":"Kellerberrin",
    "sg:classifiers":[
        {
            "category":"Building & Trades",
            "subcategory":"Construction",
            "type":"Services"
        }
    ],
    "sg:phone":"+61 8 9045 4346",
    "sg:postcode":"6410",
    "sg:province":"WA",
    "sg:tags":[
        "contractor"
    ],
    "wof:name":"Alcock Building",
    "wof:placetype":"venue"
},
  "geometry": {"coordinates":[117.702941895,-31.6342945099],"type":"Point"}
}