{
  "type": "Feature",
  "properties": {
    "addr:full":"371 Hillsborough Rd Warners Bay NSW 2282",
    "addr:housenumber":"371",
    "addr:postcode":"2282",
    "addr:street":"Hillsborough Rd",
    "iso:country":"AU",
    "sg:address":"371 Hillsborough Rd",
    "sg:city":"Warners Bay",
    "sg:classifiers":[
        {
            "category":"Home & Garden",
            "subcategory":"Building Materials",
            "type":"Retail Goods"
        }
    ],
    "sg:phone":"+61 2 4956 8333",
    "sg:postcode":"2282",
    "sg:province":"NSW",
    "sg:tags":[
        "retaining",
        "wall"
    ],
    "wof:name":"Beveridge Building Products",
    "wof:placetype":"venue"
},
  "geometry": {"coordinates":[151.655487061,-32.9659843445],"type":"Point"}
}