{
  "type": "Feature",
  "properties": {
    "iso:country":"AU",
    "sg:address":"14 Gerald Ave",
    "sg:city":"Roseville",
    "sg:classifiers":[
        {
            "category":"Professional",
            "subcategory":"Accounting & Tax Preparation",
            "type":"Services"
        }
    ],
    "sg:phone":"+61 2 9416 2137",
    "sg:postcode":"2069",
    "sg:province":"NSW",
    "sg:tags":[
        "accountant",
        "auditor"
    ],
    "wof:name":"Gilfillan Ashley",
    "wof:placetype":"venue"
},
  "geometry": {"coordinates":[151.18023681599999,-33.7796897888],"type":"Point"}
}