{
  "type": "Feature",
  "properties": {
    "addr:full":"4a Wyee St Kogarah Bay NSW 2217",
    "addr:housenumber":"4a",
    "addr:postcode":"2217",
    "addr:street":"Wyee St",
    "iso:country":"AU",
    "sg:address":"4a Wyee St",
    "sg:city":"Kogarah Bay",
    "sg:classifiers":[
        {
            "category":"Personal",
            "subcategory":"Beauty Salon",
            "type":"Services"
        }
    ],
    "sg:phone":"+61 2 9546 8311",
    "sg:postcode":"2217",
    "sg:province":"NSW",
    "sg:tags":[
        "hairdresser"
    ],
    "wof:name":"Daryl Moore Hairdressing",
    "wof:placetype":"venue"
},
  "geometry": {"coordinates":[151.125519,-33.982483],"type":"Point"}
}