{
  "type": "Feature",
  "properties": {
    "addr:full":"Downes St Esperance WA 6450",
    "addr:postcode":"6450",
    "addr:street":"St",
    "iso:country":"AU",
    "sg:address":"Downes St",
    "sg:city":"Esperance",
    "sg:classifiers":[
        {
            "category":"Utilities",
            "subcategory":"Electric",
            "type":"Services"
        }
    ],
    "sg:phone":"+61 418 936 916",
    "sg:postcode":"6450",
    "sg:province":"WA",
    "sg:tags":[
        "electrical",
        "contractor"
    ],
    "wof:name":"Griffs Electrical",
    "wof:placetype":"venue"
},
  "geometry": {"coordinates":[121.861572266,-33.8659934998],"type":"Point"}
}