{
  "type": "Feature",
  "properties": {
    "addr:full":"96 Vienna Rd Alexandra Hills QLD 4161",
    "addr:housenumber":"96",
    "addr:postcode":"4161",
    "addr:street":"Vienna Rd",
    "iso:country":"AU",
    "sg:address":"96 Vienna Rd",
    "sg:city":"Alexandra Hills",
    "sg:classifiers":[
        {
            "category":"Building & Trades",
            "subcategory":"Landscaping Services",
            "type":"Services"
        }
    ],
    "sg:phone":"+61 410 459 014",
    "sg:postcode":"4161",
    "sg:province":"QLD",
    "sg:tags":[
        "designer",
        "landscape",
        "contractor"
    ],
    "wof:name":"Ian Gardeners",
    "wof:placetype":"venue"
},
  "geometry": {"coordinates":[153.22662353499999,-27.5335826874],"type":"Point"}
}