{
  "type": "Feature",
  "properties": {
    "addr:full":"27/ 7 Bungan St Mona Vale NSW 2103",
    "addr:housenumber":"27 / 7",
    "addr:postcode":"2103",
    "addr:street":"Bungan St",
    "iso:country":"AU",
    "sg:address":"27/ 7 Bungan St",
    "sg:city":"Mona Vale",
    "sg:classifiers":[
        {
            "category":"Health Services",
            "subcategory":"Doctor",
            "type":"Services"
        }
    ],
    "sg:phone":"+61 2 9997 5377",
    "sg:postcode":"2103",
    "sg:province":"NSW",
    "sg:tags":[
        "medical",
        "practitioner"
    ],
    "wof:name":"Zaininger Amely Dr",
    "wof:placetype":"venue"
},
  "geometry": {"coordinates":[151.30232238799999,-33.6768341064],"type":"Point"}
}