{
  "type": "Feature",
  "properties": {
    "addr:full":"540 High St Preston VIC 3072",
    "addr:housenumber":"540",
    "addr:postcode":"3072",
    "addr:street":"High St",
    "iso:country":"AU",
    "sg:address":"540 High St",
    "sg:city":"Preston",
    "sg:classifiers":[
        {
            "category":"Health Services",
            "subcategory":"Doctor",
            "type":"Services"
        }
    ],
    "sg:phone":"+61 3 9478 8054",
    "sg:postcode":"3072",
    "sg:province":"VIC",
    "sg:tags":[
        "medical",
        "practitioner"
    ],
    "wof:name":"Butterfield David J",
    "wof:placetype":"venue"
},
  "geometry": {"coordinates":[145.0050354,-37.7326316833],"type":"Point"}
}