{
  "type": "Feature",
  "properties": {
    "addr:full":"Keys Rd Hampton QLD 4352",
    "addr:postcode":"4352",
    "addr:street":"Keys Rd",
    "iso:country":"AU",
    "sg:address":"Keys Rd",
    "sg:city":"Hampton",
    "sg:classifiers":[
        {
            "category":"Farming",
            "subcategory":"Berry Farm",
            "type":"Manufacturing & Wholesale Goods"
        }
    ],
    "sg:phone":"+61 7 4697 9168",
    "sg:postcode":"4352",
    "sg:province":"QLD",
    "sg:tags":[
        "fruit",
        "grower"
    ],
    "wof:name":"Kiwi Land Orchard",
    "wof:placetype":"venue"
},
  "geometry": {"coordinates":[152.06126399999999,-27.359936],"type":"Point"}
}