{
  "type": "Feature",
  "properties": {
    "addr:full":"Suite 1, 336 Keira St Wollongong NSW 2500",
    "addr:housenumber":"336",
    "addr:postcode":"2500",
    "addr:street":"Keira St",
    "iso:country":"AU",
    "sg:address":"Suite 1, 336 Keira St",
    "sg:city":"Wollongong",
    "sg:classifiers":[
        {
            "category":"Professional",
            "subcategory":"Employment Agencies",
            "type":"Services"
        }
    ],
    "sg:phone":"+61 1800 073 070",
    "sg:postcode":"2500",
    "sg:province":"NSW",
    "wof:name":"Select Appointments",
    "wof:placetype":"venue"
},
  "geometry": {"coordinates":[150.89215100000001,-34.433254],"type":"Point"}
}