{
  "type": "Feature",
  "properties": {
    "addr:full":"25 Wilberforce Rd Revesby NSW 2212",
    "addr:housenumber":"25",
    "addr:postcode":"2212",
    "addr:street":"Wilberforce Rd",
    "iso:country":"AU",
    "sg:address":"25 Wilberforce Rd",
    "sg:city":"Revesby",
    "sg:classifiers":[
        {
            "category":"Building & Trades",
            "subcategory":"Construction",
            "type":"Services"
        }
    ],
    "sg:phone":"+61 417 411 331",
    "sg:postcode":"2212",
    "sg:province":"NSW",
    "sg:tags":[
        "brick",
        "paving"
    ],
    "wof:name":"J.J.'s Prestige Pave",
    "wof:placetype":"venue"
},
  "geometry": {"coordinates":[151.02053799999999,-33.950272],"type":"Point"}
}