{
  "type": "Feature",
  "properties": {
    "iso:country":"AU",
    "sg:address":"Shop 3/ 11-13 Dumaresq St",
    "sg:city":"Campbelltown",
    "sg:classifiers":[
        {
            "category":"Personal",
            "subcategory":"Piercing",
            "type":"Services"
        }
    ],
    "sg:phone":"+61 2 4625 5999",
    "sg:postcode":"2560",
    "sg:province":"NSW",
    "sg:tags":[
        "body",
        "ear"
    ],
    "wof:name":"Pattie's Piercing Parlour",
    "wof:placetype":"venue"
},
  "geometry": {"coordinates":[150.81195068400001,-34.0669708252],"type":"Point"}
}