{
  "type": "Feature",
  "properties": {
    "addr:full":"81 Barossa Rd Glenorchy TAS 7010",
    "addr:housenumber":"81",
    "addr:postcode":"7010",
    "addr:street":"Barossa Rd",
    "iso:country":"AU",
    "sg:address":"81 Barossa Rd",
    "sg:city":"Glenorchy",
    "sg:classifiers":[
        {
            "category":"Fast Food",
            "type":"Food & Drink"
        }
    ],
    "sg:phone":"+61 3 6273 0797",
    "sg:postcode":"7010",
    "sg:province":"TAS",
    "sg:tags":[
        "away",
        "take"
    ],
    "wof:name":"Charlie's Supermarket & Take Away",
    "wof:placetype":"venue"
},
  "geometry": {"coordinates":[147.2681427,-42.8506240845],"type":"Point"}
}