{
  "type": "Feature",
  "properties": {
    "addr:full":"247 Belmore Rd Riverwood NSW 2210",
    "addr:housenumber":"247",
    "addr:postcode":"2210",
    "addr:street":"Belmore Rd",
    "iso:country":"AU",
    "sg:address":"247 Belmore Rd",
    "sg:city":"Riverwood",
    "sg:classifiers":[
        {
            "category":"Food & Beverages",
            "subcategory":"Bakery",
            "type":"Retail Goods"
        }
    ],
    "sg:phone":"+61 2 9534 1719",
    "sg:postcode":"2210",
    "sg:province":"NSW",
    "sg:tags":[
        "baker"
    ],
    "wof:name":"Success Bakery",
    "wof:placetype":"venue"
},
  "geometry": {"coordinates":[151.05169699999999,-33.952824],"type":"Point"}
}