{
  "type": "Feature",
  "properties": {
    "addr:full":"PO Box 885 Somerville VIC 3912",
    "addr:postcode":"3912",
    "iso:country":"AU",
    "sg:address":"PO Box 885",
    "sg:city":"Somerville",
    "sg:classifiers":[
        {
            "category":"Building & Trades",
            "subcategory":"Construction",
            "type":"Services"
        }
    ],
    "sg:phone":"+61 401 819 150",
    "sg:postcode":"3912",
    "sg:province":"VIC",
    "sg:tags":[
        "plasterboard",
        "plasterer",
        "fixer"
    ],
    "wof:name":"All Points Plaster",
    "wof:placetype":"venue"
},
  "geometry": {"coordinates":[145.1824646,-38.2295417786],"type":"Point"}
}