{
  "type": "Feature",
  "properties": {
    "addr:full":"105 Gavenlock Rd Tuggerah NSW 2259",
    "addr:housenumber":"105",
    "addr:postcode":"2259",
    "addr:street":"Gavenlock Rd",
    "iso:country":"AU",
    "sg:address":"105 Gavenlock Rd",
    "sg:city":"Tuggerah",
    "sg:classifiers":[
        {
            "category":"Retail",
            "subcategory":"Auto Rental",
            "type":"Services"
        }
    ],
    "sg:phone":"+61 2 4351 3322",
    "sg:postcode":"2259",
    "sg:province":"NSW",
    "sg:tags":[
        "bus",
        "truck"
    ],
    "wof:name":"Wyong Truck Rentals",
    "wof:placetype":"venue"
},
  "geometry": {"coordinates":[151.41729736299999,-33.2989768982],"type":"Point"}
}