{
  "type": "Feature",
  "properties": {
    "addr:full":"Shop 4 Woodbury Court, Mcivor Hwy Bendigo VIC 3550",
    "addr:housenumber":"shop 4",
    "addr:postcode":"3550",
    "addr:street":"Woodbury Court Mcivor Hwy",
    "iso:country":"AU",
    "sg:address":"Shop 4 Woodbury Court, Mcivor Hwy",
    "sg:city":"Bendigo",
    "sg:classifiers":[
        {
            "category":"Banks & Credit Unions",
            "subcategory":"Investment Brokerage",
            "type":"Services"
        }
    ],
    "sg:phone":"+61 3 5441 3033",
    "sg:postcode":"3550",
    "sg:province":"VIC",
    "sg:tags":[
        "debt",
        "collection"
    ],
    "wof:name":"Australian Receivables Ltd",
    "wof:placetype":"venue"
},
  "geometry": {"coordinates":[144.28062439000001,-36.7580871582],"type":"Point"}
}