{
  "type": "Feature",
  "properties": {
    "iso:country":"AU",
    "sg:address":"80 Collins St",
    "sg:city":"Melbourne",
    "sg:classifiers":[
        {
            "category":"Professional",
            "subcategory":"Management & Consulting",
            "type":"Services"
        }
    ],
    "sg:phone":"+61 3 9258 6755",
    "sg:postcode":"3000",
    "sg:province":"VIC",
    "sg:tags":[
        "consultant"
    ],
    "wof:name":"Board Appointments",
    "wof:placetype":"venue"
},
  "geometry": {"coordinates":[144.97105407699999,-37.8140335083],"type":"Point"}
}