{
  "type": "Feature",
  "properties": {
    "addr:full":"11 Briggs St Warwick QLD 4370",
    "addr:housenumber":"11",
    "addr:postcode":"4370",
    "addr:street":"Briggs St",
    "iso:country":"AU",
    "sg:address":"11 Briggs St",
    "sg:city":"Warwick",
    "sg:classifiers":[
        {
            "category":"Commercial Area",
            "type":"Public Place"
        }
    ],
    "sg:phone":"+61 7 4661 2080",
    "sg:postcode":"4370",
    "sg:province":"QLD",
    "sg:tags":[
        "heavy",
        "carrier"
    ],
    "wof:name":"Warwick Sand & Gravel Supplies",
    "wof:placetype":"venue"
},
  "geometry": {"coordinates":[152.04301452600001,-28.2080955505],"type":"Point"}
}