{
  "type": "Feature",
  "properties": {
    "iso:country":"AU",
    "sg:address":"76 Racecourse Rd Cnr Windermere Rd",
    "sg:city":"Ascot",
    "sg:classifiers":[
        {
            "category":"Real Estate",
            "subcategory":"Real Estate Agent",
            "type":"Services"
        }
    ],
    "sg:phone":"+61 7 3868 3955",
    "sg:postcode":"4007",
    "sg:province":"QLD",
    "wof:name":"Raine & Horne (Qld) Pty Ltd",
    "wof:placetype":"venue"
},
  "geometry": {"coordinates":[153.06054700000001,-27.435167],"type":"Point"}
}