{
  "type": "Feature",
  "properties": {
    "iso:country":"AU",
    "sg:address":"191 West St",
    "sg:city":"Umina",
    "sg:classifiers":[
        {
            "category":"Real Estate",
            "subcategory":"Real Estate Agent",
            "type":"Services"
        }
    ],
    "sg:phone":"+61 2 4341 1011",
    "sg:postcode":"2257",
    "sg:province":"NSW",
    "wof:name":"Re/Max All Properties",
    "wof:placetype":"venue"
},
  "geometry": {"coordinates":[151.325073242,-33.5220336914],"type":"Point"}
}