{
  "type": "Feature",
  "properties": {
    "iso:country":"AU",
    "sg:address":"PO Box 2017",
    "sg:city":"Deer Park North",
    "sg:classifiers":[
        {
            "category":"Professional",
            "subcategory":"Computer Services",
            "type":"Services"
        }
    ],
    "sg:phone":"+61 3 9366 5224",
    "sg:postcode":"3023",
    "sg:province":"VIC",
    "sg:tags":[
        "repairs",
        "upgrade",
        "equipment"
    ],
    "wof:name":"Mobile-Tech Computer Services",
    "wof:placetype":"venue"
},
  "geometry": {"coordinates":[144.756958,-37.769184],"type":"Point"}
}