{
  "type": "Feature",
  "properties": {
    "iso:country":"AU",
    "sg:address":"Shp 3/ 326 The Entrance Rd",
    "sg:city":"Long Jetty",
    "sg:classifiers":[
        {
            "category":"Autos & Motor Vehicles",
            "subcategory":"Fuel & Gas Station",
            "type":"Retail Goods"
        }
    ],
    "sg:phone":"+61 2 4333 7988",
    "sg:postcode":"2261",
    "sg:province":"NSW",
    "wof:name":"Falken Petroleum",
    "wof:placetype":"venue"
},
  "geometry": {"coordinates":[151.48434399999999,-33.35918],"type":"Point"}
}