{
  "type": "Feature",
  "properties": {
    "addr:full":"Cnr Craigends La & Sydney Hwy Tamworth NSW 2340",
    "addr:postcode":"2340",
    "addr:street":"Cnr Craigends La;Sydney Hwy",
    "iso:country":"AU",
    "sg:address":"Cnr Craigends La & Sydney Hwy",
    "sg:city":"Tamworth",
    "sg:classifiers":[
        {
            "category":"Restaurant",
            "type":"Food & Drink"
        }
    ],
    "sg:phone":"+61 2 6762 2238",
    "sg:postcode":"2340",
    "sg:province":"NSW",
    "sg:website":"http://www.sssbbq.com.au",
    "wof:name":"SSS BBQ Barns",
    "wof:placetype":"venue"
},
  "geometry": {"coordinates":[150.92042541500001,-31.1235351562],"type":"Point"}
}