{
  "type": "Feature",
  "properties": {
    "addr:full":"Stocklands Shopng Cntr 310 Ross River Rd Aitkenvale QLD 4814",
    "addr:housenumber":"310",
    "addr:postcode":"4814",
    "addr:street":"Ross River Rd",
    "iso:country":"AU",
    "sg:address":"Stocklands Shopng Cntr 310 Ross River Rd",
    "sg:city":"Aitkenvale",
    "sg:classifiers":[
        {
            "category":"Shopping",
            "subcategory":"Mobile Phones",
            "type":"Retail Goods"
        }
    ],
    "sg:phone":"+61 7 4761 8414",
    "sg:postcode":"4814",
    "sg:province":"QLD",
    "sg:tags":[
        "telephone",
        "accessory"
    ],
    "wof:name":"Telstra Shop",
    "wof:placetype":"venue"
},
  "geometry": {"coordinates":[146.76419100000001,-19.297947],"type":"Point"}
}