{
  "type": "Feature",
  "properties": {
    "addr:full":"Level 1, Spring Hill Marketplace, 356 Turbot Spring Hill QLD 4000",
    "addr:housenumber":"356",
    "addr:postcode":"4000",
    "addr:street":"Turbot",
    "iso:country":"AU",
    "sg:address":"Level 1, Spring Hill Marketplace, 356",
    "sg:city":"Turbot Spring Hill",
    "sg:classifiers":[
        {
            "category":"Health Services",
            "subcategory":"Health Practitioner",
            "type":"Services"
        }
    ],
    "sg:phone":"+61 7 3839 4323",
    "sg:postcode":"4000",
    "sg:province":"QLD",
    "sg:tags":[
        "physiotherapist"
    ],
    "wof:name":"Nathan Carloss",
    "wof:placetype":"venue"
},
  "geometry": {"coordinates":[153.026153564,-27.4650211334],"type":"Point"}
}