{
  "type": "Feature",
  "properties": {
    "iso:country":"AU",
    "sg:address":"Cnr Sayers Rd & Poets La",
    "sg:city":"Hoppers Crossing",
    "sg:classifiers":[
        {
            "category":"Building & Trades",
            "subcategory":"Construction",
            "type":"Services"
        }
    ],
    "sg:phone":"+61 3 9369 5436",
    "sg:postcode":"3029",
    "sg:province":"VIC",
    "sg:tags":[
        "contractor"
    ],
    "wof:name":"Domaine Homes",
    "wof:placetype":"venue"
},
  "geometry": {"coordinates":[144.708206,-37.850697],"type":"Point"}
}