{
  "type": "Feature",
  "properties": {
    "iso:country":"AU",
    "sg:address":"193 Bayswater Rd",
    "sg:city":"Bayswater",
    "sg:classifiers":[
        {
            "category":"Organizations",
            "subcategory":"Non-profit Organization",
            "type":"Services"
        }
    ],
    "sg:phone":"+61 3 9720 1118",
    "sg:postcode":"3153",
    "sg:province":"VIC",
    "sg:tags":[
        "support",
        "disability",
        "organisation"
    ],
    "wof:name":"Autism Victoria",
    "wof:placetype":"venue"
},
  "geometry": {"coordinates":[145.26922607399999,-37.8194084167],"type":"Point"}
}