{
  "type": "Feature",
  "properties": {
    "addr:full":"Shp 18, Hibiscus Shopping Town Leanyer Drv Leanyer NT 0812",
    "addr:housenumber":"18",
    "addr:postcode":"nt 0812",
    "addr:street":"Hibiscus;Leanyer Drv",
    "iso:country":"AU",
    "sg:address":"Shp 18, Hibiscus Shopping Town Leanyer Drv",
    "sg:city":"Leanyer",
    "sg:classifiers":[
        {
            "category":"Casinos & Gambling",
            "type":"Entertainment"
        }
    ],
    "sg:phone":"+61 8 8927 4932",
    "sg:postcode":"0812",
    "sg:province":"NT",
    "sg:tags":[
        "lottery",
        "agent"
    ],
    "wof:name":"Leanyer Newsagency",
    "wof:placetype":"venue"
},
  "geometry": {"coordinates":[130.89506499999999,-12.378151],"type":"Point"}
}