{
  "type": "Feature",
  "properties": {
    "addr:full":"15 Ballarat Rd Hamilton VIC 3300",
    "addr:housenumber":"15",
    "addr:postcode":"3300",
    "addr:street":"Ballarat Rd",
    "iso:country":"AU",
    "sg:address":"15 Ballarat Rd",
    "sg:city":"Hamilton",
    "sg:classifiers":[
        {
            "category":"Utilities",
            "type":"Services"
        }
    ],
    "sg:phone":"+61 3 5571 1755",
    "sg:postcode":"3300",
    "sg:province":"VIC",
    "sg:tags":[
        "refrigeration",
        "industrial",
        "commercial",
        "retail"
    ],
    "wof:name":"Fox Refrigeration Pty Ltd",
    "wof:placetype":"venue"
},
  "geometry": {"coordinates":[142.03492736800001,-37.7417869568],"type":"Point"}
}