{
  "type": "Feature",
  "properties": {
    "iso:country":"AU",
    "sg:address":"181 King St",
    "sg:city":"Newcastle",
    "sg:classifiers":[
        {
            "category":"Shopping",
            "subcategory":"Jewelry",
            "type":"Retail Goods"
        }
    ],
    "sg:phone":"+61 2 4927 0333",
    "sg:postcode":"2300",
    "sg:province":"NSW",
    "sg:tags":[
        "jeweller"
    ],
    "wof:name":"Dru Designs",
    "wof:placetype":"venue"
},
  "geometry": {"coordinates":[151.776764,-32.927162],"type":"Point"}
}