{
  "type": "Feature",
  "properties": {
    "iso:country":"AU",
    "sg:address":"7 Clegg Ave",
    "sg:city":"Croydon",
    "sg:classifiers":[
        {
            "category":"Building & Trades",
            "subcategory":"Landscaping Services",
            "type":"Services"
        }
    ],
    "sg:phone":"+61 3 9725 8356",
    "sg:postcode":"3136",
    "sg:province":"VIC",
    "sg:tags":[
        "designer",
        "landscape",
        "contractor"
    ],
    "wof:name":"Patch22",
    "wof:placetype":"venue"
},
  "geometry": {"coordinates":[145.26632690400001,-37.7992706299],"type":"Point"}
}