{
  "type": "Feature",
  "properties": {
    "iso:country":"AU",
    "sg:address":"53 Kentucky St",
    "sg:city":"Glossodia",
    "sg:classifiers":[
        {
            "category":"Manufacturing",
            "subcategory":"Tools & Machinery",
            "type":"Manufacturing & Wholesale Goods"
        }
    ],
    "sg:phone":"+61 412 811 850",
    "sg:postcode":"2756",
    "sg:province":"NSW",
    "sg:tags":[
        "earth",
        "excavating",
        "moving",
        "equipment"
    ],
    "wof:name":"M & M Haber Tip Truck & Bobcat Hire",
    "wof:placetype":"venue"
},
  "geometry": {"coordinates":[150.75942993199999,-33.5311279297],"type":"Point"}
}