{
  "type": "Feature",
  "properties": {
    "iso:country":"AU",
    "sg:address":"15 High St",
    "sg:city":"Wodonga",
    "sg:classifiers":[
        {
            "category":"Building & Trades",
            "subcategory":"Construction",
            "type":"Services"
        }
    ],
    "sg:phone":"+61 2 6931 9655",
    "sg:postcode":"3689",
    "sg:province":"VIC",
    "sg:tags":[
        "contractor"
    ],
    "wof:name":"Executive Homes",
    "wof:placetype":"venue"
},
  "geometry": {"coordinates":[146.89248699999999,-36.113705],"type":"Point"}
}