{
  "type": "Feature",
  "properties": {
    "addr:full":"124 North Boundary Rd Hamilton VIC 3300",
    "addr:housenumber":"124",
    "addr:postcode":"3300",
    "addr:street":"North Boundary Rd",
    "iso:country":"AU",
    "sg:address":"124 North Boundary Rd",
    "sg:city":"Hamilton",
    "sg:classifiers":[
        {
            "category":"Organizations",
            "subcategory":"Professional Association",
            "type":"Services"
        }
    ],
    "sg:phone":"+61 3 5572 5229",
    "sg:postcode":"3300",
    "sg:province":"VIC",
    "sg:tags":[
        "web",
        "internet"
    ],
    "wof:name":"Michelle Thompson",
    "wof:placetype":"venue"
},
  "geometry": {"coordinates":[142.021575928,-37.7422294617],"type":"Point"}
}