{
  "type": "Feature",
  "properties": {
    "iso:country":"AU",
    "sg:address":"345 Gt Eastern Hwy",
    "sg:city":"Redcliffe",
    "sg:classifiers":[
        {
            "category":"Retail",
            "subcategory":"Auto Rental",
            "type":"Services"
        }
    ],
    "sg:phone":"+61 8 9277 4624",
    "sg:postcode":"6104",
    "sg:province":"WA",
    "sg:tags":[
        "car",
        "hire",
        "minibus"
    ],
    "wof:name":"Advantage Car Rental Western Australia",
    "wof:placetype":"venue"
},
  "geometry": {"coordinates":[115.939979553,-31.9376754761],"type":"Point"}
}