{
  "type": "Feature",
  "properties": {
    "iso:country":"AU",
    "sg:address":"PO Box 408",
    "sg:city":"Hamilton",
    "sg:classifiers":[
        {
            "category":"Building & Trades",
            "subcategory":"Plumbing",
            "type":"Services"
        }
    ],
    "sg:phone":"+61 7 3868 2424",
    "sg:postcode":"4007",
    "sg:province":"QLD",
    "sg:tags":[
        "drainers"
    ],
    "wof:name":"Central Plumbing Services",
    "wof:placetype":"venue"
},
  "geometry": {"coordinates":[153.064606,-27.4375],"type":"Point"}
}