{
  "type": "Feature",
  "properties": {
    "iso:country":"AU",
    "sg:address":"142 Ingham Ave",
    "sg:city":"Five Dock",
    "sg:classifiers":[
        {
            "category":"Retail",
            "subcategory":"Repair Shop",
            "type":"Services"
        }
    ],
    "sg:phone":"+61 2 9713 1919",
    "sg:postcode":"2046",
    "sg:province":"NSW",
    "sg:tags":[
        "upholsterer"
    ],
    "wof:name":"Restwell Upholstery",
    "wof:placetype":"venue"
},
  "geometry": {"coordinates":[151.13732899999999,-33.863213],"type":"Point"}
}