{
  "type": "Feature",
  "properties": {
    "iso:country":"AU",
    "sg:address":"131 Birrell St",
    "sg:city":"Waverley",
    "sg:classifiers":[
        {
            "category":"Education",
            "subcategory":"School",
            "type":"Public Place"
        }
    ],
    "sg:phone":"+61 2 9369 0600",
    "sg:postcode":"2024",
    "sg:province":"NSW",
    "sg:tags":[
        "boy"
    ],
    "wof:name":"Waverley College",
    "wof:placetype":"venue"
},
  "geometry": {"coordinates":[151.254806519,-33.8966522217],"type":"Point"}
}