{
  "type": "Feature",
  "properties": {
    "addr:full":"26/3- 5 Flora St Kirrawee NSW 2232",
    "addr:housenumber":"26 / 3 5",
    "addr:postcode":"2232",
    "addr:street":"Flora St",
    "iso:country":"AU",
    "sg:address":"26/3- 5 Flora St",
    "sg:city":"Kirrawee",
    "sg:classifiers":[
        {
            "category":"Shopping",
            "subcategory":"Bicycles & Sporting Goods",
            "type":"Retail Goods"
        }
    ],
    "sg:phone":"+61 2 9542 4436",
    "sg:postcode":"2232",
    "sg:province":"NSW",
    "sg:tags":[
        "dance",
        "accessory",
        "wear",
        "supply"
    ],
    "wof:name":"Starz On Stage",
    "wof:placetype":"venue"
},
  "geometry": {"coordinates":[151.07516479500001,-34.0340766907],"type":"Point"}
}