{
  "type": "Feature",
  "properties": {
    "iso:country":"AU",
    "sg:address":"58 Tuckers Rd",
    "sg:city":"Templestowe",
    "sg:classifiers":[
        {
            "category":"Professional",
            "subcategory":"Employment Agencies",
            "type":"Services"
        }
    ],
    "sg:phone":"+61 3 9841 7627",
    "sg:postcode":"3106",
    "sg:province":"VIC",
    "sg:tags":[
        "provider",
        "internet"
    ],
    "wof:name":"i Net Designs",
    "wof:placetype":"venue"
},
  "geometry": {"coordinates":[145.15623474099999,-37.7683906555],"type":"Point"}
}