{
  "type": "Feature",
  "properties": {
    "addr:full":"Cnr South & Nicholas St Ipswich QLD 4305",
    "addr:postcode":"4305",
    "addr:street":"Cnr South & Nicholas St",
    "iso:country":"AU",
    "sg:address":"Cnr South & Nicholas St",
    "sg:city":"Ipswich",
    "sg:classifiers":[
        {
            "category":"Organizations",
            "subcategory":"Membership Organization",
            "type":"Services"
        }
    ],
    "sg:phone":"+61 7 3810 6659",
    "sg:postcode":"4305",
    "sg:province":"QLD",
    "sg:tags":[
        "support",
        "health",
        "organisation"
    ],
    "wof:name":"60 & Better Program",
    "wof:placetype":"venue"
},
  "geometry": {"coordinates":[152.74435424800001,-27.6248931885],"type":"Point"}
}