{
  "type": "Feature",
  "properties": {
    "iso:country":"AU",
    "sg:address":"Unit 1/ 4 Achievement Way",
    "sg:city":"Wangara",
    "sg:classifiers":[
        {
            "category":"Building & Trades",
            "subcategory":"Construction",
            "type":"Services"
        }
    ],
    "sg:phone":"+61 8 9303 4655",
    "sg:postcode":"6065",
    "sg:province":"WA",
    "sg:tags":[
        "concrete",
        "treatment",
        "repair"
    ],
    "wof:name":"Permatech",
    "wof:placetype":"venue"
},
  "geometry": {"coordinates":[115.829040527,-31.7895641327],"type":"Point"}
}