{
  "type": "Feature",
  "properties": {
    "iso:country":"AU",
    "sg:address":"Level 18, Allianz Centre 2 Market St",
    "sg:city":"Sydney",
    "sg:classifiers":[
        {
            "category":"Professional",
            "subcategory":"Detective & Security Services",
            "type":"Services"
        }
    ],
    "sg:phone":"+61 2 9313 5732",
    "sg:postcode":"2000",
    "sg:province":"NSW",
    "sg:tags":[
        "guard",
        "patrol"
    ],
    "wof:name":"Wilson Security",
    "wof:placetype":"venue"
},
  "geometry": {"coordinates":[151.203979492,-33.8708496094],"type":"Point"}
}