{
  "type": "Feature",
  "properties": {
    "iso:country":"AU",
    "sg:address":"6457 Mount Lindesay Hwy",
    "sg:city":"Gleneagle",
    "sg:classifiers":[
        {
            "category":"Wholesale",
            "subcategory":"Farm Supplies",
            "type":"Manufacturing & Wholesale Goods"
        }
    ],
    "sg:phone":"+61 7 5543 1460",
    "sg:postcode":"4285",
    "sg:province":"QLD",
    "sg:tags":[
        "feed",
        "supplement",
        "stock"
    ],
    "wof:name":"Gleneagle Wholesale Produce",
    "wof:placetype":"venue"
},
  "geometry": {"coordinates":[152.99316400000001,-27.95965],"type":"Point"}
}