{
  "type": "Feature",
  "properties": {
    "addr:full":"375 Chapel St South Yarra VIC 3141",
    "addr:housenumber":"375",
    "addr:postcode":"3141",
    "addr:street":"Chapel St",
    "iso:country":"AU",
    "sg:address":"375 Chapel St",
    "sg:city":"South Yarra",
    "sg:classifiers":[
        {
            "category":"Manufacturing",
            "subcategory":"Apparel",
            "type":"Manufacturing & Wholesale Goods"
        }
    ],
    "sg:phone":"+61 3 9826 5011",
    "sg:postcode":"3141",
    "sg:province":"VIC",
    "sg:tags":[
        "wholesaler",
        "mfrs",
        "footwear"
    ],
    "wof:name":"Reebok Store Chapel St.",
    "wof:placetype":"venue"
},
  "geometry": {"coordinates":[144.99415588400001,-37.8459892273],"type":"Point"}
}