{
  "type": "Feature",
  "properties": {
    "addr:full":"3067 Murray Valley Hwy Robinvale VIC 3549",
    "addr:housenumber":"3067",
    "addr:postcode":"3549",
    "addr:street":"Murray Valley Hwy",
    "iso:country":"AU",
    "sg:address":"3067 Murray Valley Hwy",
    "sg:city":"Robinvale",
    "sg:classifiers":[
        {
            "category":"Manufacturing",
            "subcategory":"Food",
            "type":"Manufacturing & Wholesale Goods"
        }
    ],
    "sg:phone":"+61 3 5026 9310",
    "sg:postcode":"3549",
    "sg:province":"VIC",
    "sg:tags":[
        "product",
        "nut",
        "edible"
    ],
    "wof:name":"Australian Pioneer Pistachio Company Pty Ltd",
    "wof:placetype":"venue"
},
  "geometry": {"coordinates":[142.770065308,-34.5828895569],"type":"Point"}
}