{
  "type": "Feature",
  "properties": {
    "addr:full":"4 Clingin St Reservoir VIC 3073",
    "addr:housenumber":"4",
    "addr:postcode":"3073",
    "addr:street":"Clingin St",
    "iso:country":"AU",
    "sg:address":"4 Clingin St",
    "sg:city":"Reservoir",
    "sg:classifiers":[
        {
            "category":"Social Services",
            "subcategory":"Child Care",
            "type":"Services"
        }
    ],
    "sg:phone":"+61 401 194 703",
    "sg:postcode":"3073",
    "sg:province":"VIC",
    "sg:tags":[
        "baby",
        "sitter"
    ],
    "wof:name":"Amila",
    "wof:placetype":"venue"
},
  "geometry": {"coordinates":[145.03587341299999,-37.7289390564],"type":"Point"}
}