{
  "type": "Feature",
  "properties": {
    "iso:country":"AU",
    "sg:address":"123 Herald St",
    "sg:city":"Cheltenham",
    "sg:classifiers":[
        {
            "category":"Wholesale",
            "subcategory":"Hardware",
            "type":"Manufacturing & Wholesale Goods"
        }
    ],
    "sg:phone":"+61 3 9555 4990",
    "sg:postcode":"3192",
    "sg:province":"VIC",
    "wof:name":"Maze Distribution",
    "wof:placetype":"venue"
},
  "geometry": {"coordinates":[145.07307434099999,-37.9538917542],"type":"Point"}
}