{
  "type": "Feature",
  "properties": {
    "addr:full":"425 Burwood Hwy Wantirna South VIC 3152",
    "addr:housenumber":"425",
    "addr:postcode":"3152",
    "addr:street":"Burwood Hwy",
    "iso:country":"AU",
    "sg:address":"425 Burwood Hwy",
    "sg:city":"Wantirna South",
    "sg:classifiers":[
        {
            "category":"Shopping",
            "subcategory":"Computers & Home Electronics",
            "type":"Retail Goods"
        }
    ],
    "sg:phone":"+61 3 9801 5700",
    "sg:postcode":"3152",
    "sg:province":"VIC",
    "sg:tags":[
        "hi-fi",
        "equipment"
    ],
    "wof:name":"Big Picture People",
    "wof:placetype":"venue"
},
  "geometry": {"coordinates":[145.23806762699999,-37.8702659607],"type":"Point"}
}