{
  "type": "Feature",
  "properties": {
    "iso:country":"AU",
    "sg:address":"Suite 2/ 1 High St",
    "sg:city":"Fremantle",
    "sg:classifiers":[
        {
            "category":"Professional",
            "subcategory":"Computer Services",
            "type":"Services"
        }
    ],
    "sg:phone":"+61 8 9335 8100",
    "sg:postcode":"6160",
    "sg:province":"WA",
    "sg:tags":[
        "consultant",
        "system"
    ],
    "wof:name":"Expand Pty Ltd",
    "wof:placetype":"venue"
},
  "geometry": {"coordinates":[115.742119,-32.055977],"type":"Point"}
}