{
  "type": "Feature",
  "properties": {
    "iso:country":"AU",
    "sg:address":"9/ 62 Edgar St",
    "sg:city":"Glen Iris",
    "sg:classifiers":[
        {
            "category":"Personal",
            "type":"Services"
        }
    ],
    "sg:phone":"+61 1300 369 197",
    "sg:postcode":"3146",
    "sg:province":"VIC",
    "sg:tags":[
        "gift"
    ],
    "wof:name":"Thankx Hampers",
    "wof:placetype":"venue"
},
  "geometry": {"coordinates":[145.04589843799999,-37.8517723083],"type":"Point"}
}