{
  "type": "Feature",
  "properties": {
    "addr:full":"6 Cratloe Rd Mt Waverley VIC 3149",
    "addr:housenumber":"6",
    "addr:postcode":"3149",
    "addr:street":"Cratloe Rd",
    "iso:country":"AU",
    "sg:address":"6 Cratloe Rd",
    "sg:city":"Mt Waverley",
    "sg:classifiers":[
        {
            "category":"Professional",
            "subcategory":"Accounting & Tax Preparation",
            "type":"Services"
        }
    ],
    "sg:phone":"+61 3 9808 7453",
    "sg:postcode":"3149",
    "sg:province":"VIC",
    "sg:tags":[
        "accountant",
        "auditor"
    ],
    "wof:name":"Rodger J W H",
    "wof:placetype":"venue"
},
  "geometry": {"coordinates":[145.12680053700001,-37.8577041626],"type":"Point"}
}