{
  "type": "Feature",
  "properties": {
    "addr:full":"29 Enterprise St Richlands QLD 4077",
    "addr:housenumber":"29",
    "addr:postcode":"4077",
    "addr:street":"Enterprise St",
    "iso:country":"AU",
    "sg:address":"29 Enterprise St",
    "sg:city":"Richlands",
    "sg:classifiers":[
        {
            "category":"Manufacturing",
            "subcategory":"Metals",
            "type":"Manufacturing & Wholesale Goods"
        }
    ],
    "sg:phone":"+61 7 3375 6366",
    "sg:postcode":"4077",
    "sg:province":"QLD",
    "sg:tags":[
        "steel",
        "fabricator",
        "mfrs"
    ],
    "wof:name":"Fritz Steel",
    "wof:placetype":"venue"
},
  "geometry": {"coordinates":[152.94688415499999,-27.5858516693],"type":"Point"}
}