{
  "type": "Feature",
  "properties": {
    "addr:full":"Shops 1 & 2 Happeny La Katoomba NSW 2780",
    "addr:housenumber":"shops 1 & 2",
    "addr:postcode":"2780",
    "addr:street":"Happeny La",
    "iso:country":"AU",
    "sg:address":"Shops 1 & 2 Happeny La",
    "sg:city":"Katoomba",
    "sg:classifiers":[
        {
            "category":"Farming",
            "subcategory":"Fish & Marine Products",
            "type":"Manufacturing & Wholesale Goods"
        }
    ],
    "sg:phone":"+61 2 4782 5890",
    "sg:postcode":"2780",
    "sg:province":"NSW",
    "sg:tags":[
        "organic"
    ],
    "wof:name":"Blue Mountains Food Co-Op Ltd",
    "wof:placetype":"venue"
},
  "geometry": {"coordinates":[150.30918884299999,-33.7262458801],"type":"Point"}
}