{
  "type": "Feature",
  "properties": {
    "addr:full":"148 Springfield Ave Moonah TAS 7009",
    "addr:housenumber":"148",
    "addr:postcode":"7009",
    "addr:street":"Springfield Ave",
    "iso:country":"AU",
    "sg:address":"148 Springfield Ave",
    "sg:city":"Moonah",
    "sg:classifiers":[
        {
            "category":"Health Services",
            "subcategory":"Health Practitioner",
            "type":"Services"
        }
    ],
    "sg:phone":"+61 3 6272 9694",
    "sg:postcode":"7009",
    "sg:province":"TAS",
    "sg:tags":[
        "naturopath"
    ],
    "wof:name":"Pearson Bill",
    "wof:placetype":"venue"
},
  "geometry": {"coordinates":[147.27993774399999,-42.8505516052],"type":"Point"}
}