{
  "type": "Feature",
  "properties": {
    "addr:full":"41 Gilda Drv Narara NSW 2250",
    "addr:housenumber":"41",
    "addr:postcode":"2250",
    "addr:street":"Gilda Drv",
    "iso:country":"AU",
    "sg:address":"41 Gilda Drv",
    "sg:city":"Narara",
    "sg:classifiers":[
        {
            "category":"Social Services",
            "type":"Services"
        }
    ],
    "sg:phone":"+61 2 4328 3035",
    "sg:postcode":"2250",
    "sg:province":"NSW",
    "sg:tags":[
        "kinesiology"
    ],
    "wof:name":"Martine Bass - Kinesiologist",
    "wof:placetype":"venue"
},
  "geometry": {"coordinates":[151.34727477999999,-33.3865776062],"type":"Point"}
}