{
  "type": "Feature",
  "properties": {
    "addr:full":"75 Brisbane St Ipswich QLD 4305",
    "addr:housenumber":"75",
    "addr:postcode":"4305",
    "addr:street":"Brisbane St",
    "iso:country":"AU",
    "sg:address":"75 Brisbane St",
    "sg:city":"Ipswich",
    "sg:classifiers":[
        {
            "category":"Shopping",
            "subcategory":"Computers & Home Electronics",
            "type":"Retail Goods"
        }
    ],
    "sg:phone":"+61 7 3812 3900",
    "sg:postcode":"4305",
    "sg:province":"QLD",
    "sg:tags":[
        "hardware",
        "equipment"
    ],
    "wof:name":"Ace Computer World",
    "wof:placetype":"venue"
},
  "geometry": {"coordinates":[152.761642456,-27.6145820618],"type":"Point"}
}