{
  "type": "Feature",
  "properties": {
    "addr:full":"Factory 3, 85 Bardia Av Seaford VIC 3198",
    "addr:housenumber":"85",
    "addr:postcode":"3198",
    "addr:street":"Bardia Av",
    "iso:country":"AU",
    "sg:address":"Factory 3, 85 Bardia Av",
    "sg:city":"Seaford",
    "sg:classifiers":[
        {
            "category":"Building & Trades",
            "subcategory":"Plumbing",
            "type":"Services"
        }
    ],
    "sg:phone":"+61 3 9785 2022",
    "sg:postcode":"3198",
    "sg:province":"VIC",
    "sg:tags":[
        "repair",
        "appliance",
        "system",
        "heating"
    ],
    "wof:name":"Southside Heating & Cooling",
    "wof:placetype":"venue"
},
  "geometry": {"coordinates":[145.13534545900001,-38.11901474],"type":"Point"}
}