{
  "type": "Feature",
  "properties": {
    "addr:full":"1 Besley St Bruthen VIC 3885",
    "addr:housenumber":"1",
    "addr:postcode":"3885",
    "addr:street":"Besley St",
    "iso:country":"AU",
    "sg:address":"1 Besley St",
    "sg:city":"Bruthen",
    "sg:classifiers":[
        {
            "category":"Organizations",
            "subcategory":"Membership Organization",
            "type":"Services"
        }
    ],
    "sg:phone":"+61 3 5175 5226",
    "sg:postcode":"3885",
    "sg:province":"VIC",
    "sg:tags":[
        "club",
        "car"
    ],
    "wof:name":"Classic & Historic Automobile Club of Riveria Lake",
    "wof:placetype":"venue"
},
  "geometry": {"coordinates":[147.83229064899999,-37.7052268982],"type":"Point"}
}