{
  "type": "Feature",
  "properties": {
    "addr:full":"150 Waverley Rd Malvern East VIC 3145",
    "addr:housenumber":"150",
    "addr:postcode":"3145",
    "addr:street":"Waverley Rd",
    "iso:country":"AU",
    "sg:address":"150 Waverley Rd",
    "sg:city":"Malvern East",
    "sg:classifiers":[
        {
            "category":"Manufacturing",
            "subcategory":"Furniture",
            "type":"Manufacturing & Wholesale Goods"
        }
    ],
    "sg:phone":"+61 3 9571 3809",
    "sg:postcode":"3145",
    "sg:province":"VIC",
    "sg:tags":[
        "builder",
        "designer",
        "custom"
    ],
    "wof:name":"Red Dust Furniture",
    "wof:placetype":"venue"
},
  "geometry": {"coordinates":[145.050613403,-37.8763389587],"type":"Point"}
}