{
  "type": "Feature",
  "properties": {
    "iso:country":"AU",
    "sg:address":"121 Glenhaven Rd",
    "sg:city":"Glenhaven",
    "sg:classifiers":[
        {
            "category":"Personal",
            "subcategory":"Beauty Salon",
            "type":"Services"
        }
    ],
    "sg:phone":"+61 2 9899 8794",
    "sg:postcode":"2156",
    "sg:province":"NSW",
    "wof:name":"Belinda's Salon Of Hair & Wax",
    "wof:placetype":"venue"
},
  "geometry": {"coordinates":[150.99559020999999,-33.6968460083],"type":"Point"}
}