{
  "type": "Feature",
  "properties": {
    "addr:full":"5 Onkara Ave Ingle Farm SA 5098",
    "addr:housenumber":"5",
    "addr:postcode":"5098",
    "addr:street":"Onkara Ave",
    "iso:country":"AU",
    "sg:address":"5 Onkara Ave",
    "sg:city":"Ingle Farm",
    "sg:classifiers":[
        {
            "category":"Building & Trades",
            "subcategory":"Construction",
            "type":"Services"
        }
    ],
    "sg:phone":"+61 8 8262 9522",
    "sg:postcode":"5098",
    "sg:province":"SA",
    "sg:tags":[
        "concrete",
        "contractor"
    ],
    "wof:name":"Elite Foundations Pty Ltd",
    "wof:placetype":"venue"
},
  "geometry": {"coordinates":[138.63420105,-34.8348655701],"type":"Point"}
}