{
  "type": "Feature",
  "properties": {
    "addr:full":"81 Planthurst Rd Carlton NSW 2218",
    "addr:housenumber":"81",
    "addr:postcode":"2218",
    "addr:street":"Planthurst Rd",
    "iso:country":"AU",
    "sg:address":"81 Planthurst Rd",
    "sg:city":"Carlton",
    "sg:classifiers":[
        {
            "category":"Wholesale",
            "subcategory":"Machinery & Supplies",
            "type":"Manufacturing & Wholesale Goods"
        }
    ],
    "sg:phone":"+61 2 9546 6489",
    "sg:postcode":"2218",
    "sg:province":"NSW",
    "sg:tags":[
        "instrument"
    ],
    "wof:name":"Davidson Instrument Co Pty Ltd",
    "wof:placetype":"venue"
},
  "geometry": {"coordinates":[151.11506700000001,-33.979622],"type":"Point"}
}