{
  "type": "Feature",
  "properties": {
    "iso:country":"AU",
    "sg:address":"203 Coxs Rd",
    "sg:city":"North Ryde",
    "sg:classifiers":[
        {
            "category":"Shopping",
            "subcategory":"Clothing, Apparel, & Fashions",
            "type":"Retail Goods"
        }
    ],
    "sg:phone":"+61 2 9888 6947",
    "sg:postcode":"2113",
    "sg:province":"NSW",
    "sg:tags":[
        "lady",
        "wear"
    ],
    "wof:name":"Hunter Robyn",
    "wof:placetype":"venue"
},
  "geometry": {"coordinates":[151.12197875999999,-33.7946510315],"type":"Point"}
}