{
  "type": "Feature",
  "properties": {
    "addr:full":"60 Cooper Rd Birrong NSW 2143",
    "addr:housenumber":"60",
    "addr:postcode":"2143",
    "addr:street":"Cooper Rd",
    "iso:country":"AU",
    "sg:address":"60 Cooper Rd",
    "sg:city":"Birrong",
    "sg:classifiers":[
        {
            "category":"Shopping",
            "type":"Retail Goods"
        }
    ],
    "sg:phone":"+61 2 9644 3195",
    "sg:postcode":"2143",
    "sg:province":"NSW",
    "sg:tags":[
        "supply",
        "religious",
        "church"
    ],
    "wof:name":"Y-Judes",
    "wof:placetype":"venue"
},
  "geometry": {"coordinates":[151.02653503400001,-33.8935623169],"type":"Point"}
}