{
  "type": "Feature",
  "properties": {
    "iso:country":"AU",
    "sg:address":"160 Arthur Hwy",
    "sg:city":"Dunalley",
    "sg:classifiers":[
        {
            "category":"Government",
            "subcategory":"Post Office",
            "type":"Public Place"
        }
    ],
    "sg:phone":"+61 3 6253 5102",
    "sg:postcode":"7177",
    "sg:province":"TAS",
    "sg:tags":[
        "postal"
    ],
    "wof:name":"Australia Post Offices",
    "wof:placetype":"venue"
},
  "geometry": {"coordinates":[147.80661,-42.889702],"type":"Point"}
}