{
  "type": "Feature",
  "properties": {
    "iso:country":"AU",
    "sg:address":"85 Vulcan Rd",
    "sg:city":"Canning Vale",
    "sg:classifiers":[
        {
            "category":"Building & Trades",
            "subcategory":"Construction",
            "type":"Services"
        }
    ],
    "sg:phone":"+61 8 9334 4600",
    "sg:postcode":"6155",
    "sg:province":"WA",
    "sg:tags":[
        "window",
        "aluminium"
    ],
    "wof:name":"Affinity",
    "wof:placetype":"venue"
},
  "geometry": {"coordinates":[115.91481,-32.055141],"type":"Point"}
}