{
  "type": "Feature",
  "properties": {
    "iso:country":"AU",
    "sg:address":"351 Rooty Hill North Rd",
    "sg:city":"Plumpton",
    "sg:classifiers":[
        {
            "category":"Education",
            "subcategory":"Kindergarten",
            "type":"Public Place"
        }
    ],
    "sg:phone":"+61 2 9677 2772",
    "sg:postcode":"2761",
    "sg:province":"NSW",
    "sg:tags":[
        "pre-schools"
    ],
    "wof:name":"St George Kindergarten Long Day Care Centre",
    "wof:placetype":"venue"
},
  "geometry": {"coordinates":[150.841812,-33.747757],"type":"Point"}
}