{
  "type": "Feature",
  "properties": {
    "addr:full":"487 Kiewa St Albury NSW 2640",
    "addr:housenumber":"487",
    "addr:postcode":"2640",
    "addr:street":"Kiewa St",
    "iso:country":"AU",
    "sg:address":"487 Kiewa St",
    "sg:city":"Albury",
    "sg:classifiers":[
        {
            "category":"Food & Beverages",
            "subcategory":"Bakery",
            "type":"Retail Goods"
        }
    ],
    "sg:phone":"+61 2 6021 0411",
    "sg:postcode":"2640",
    "sg:province":"NSW",
    "sg:tags":[
        "baker"
    ],
    "wof:name":"Muffin Break",
    "wof:placetype":"venue"
},
  "geometry": {"coordinates":[146.91717529300001,-36.0712203979],"type":"Point"}
}