{
  "type": "Feature",
  "properties": {
    "addr:full":"Room 3302 923 Davidlow Way Marcoola QLD 4564",
    "addr:housenumber":"3302",
    "addr:postcode":"4564",
    "addr:street":"923 Davidlow Way",
    "iso:country":"AU",
    "sg:address":"Room 3302 923 Davidlow Way",
    "sg:city":"Marcoola",
    "sg:classifiers":[
        {
            "category":"Retail",
            "subcategory":"Storage",
            "type":"Services"
        }
    ],
    "sg:phone":"+61 7 5412 0100",
    "sg:postcode":"4564",
    "sg:province":"QLD",
    "sg:tags":[
        "removal",
        "furniture"
    ],
    "wof:name":"Movan",
    "wof:placetype":"venue"
},
  "geometry": {"coordinates":[153.09611511200001,-26.6012039185],"type":"Point"}
}