{
  "type": "Feature",
  "properties": {
    "addr:full":"2B Kooringal Ave Legana TAS 7277",
    "addr:housenumber":"2b",
    "addr:postcode":"7277",
    "addr:street":"Kooringal Ave",
    "iso:country":"AU",
    "sg:address":"2B Kooringal Ave",
    "sg:city":"Legana",
    "sg:classifiers":[
        {
            "category":"Home & Garden",
            "subcategory":"Hardware",
            "type":"Retail Goods"
        }
    ],
    "sg:phone":"+61 418 374 415",
    "sg:postcode":"7277",
    "sg:province":"TAS",
    "sg:tags":[
        "pumping",
        "contractor"
    ],
    "wof:name":"JMB Envirosept",
    "wof:placetype":"venue"
},
  "geometry": {"coordinates":[147.056915283,-41.3490371704],"type":"Point"}
}