{
  "type": "Feature",
  "properties": {
    "addr:full":"Cnr Bypass & Rafferty Rds Mandurah WA 6210",
    "addr:postcode":"6210",
    "addr:street":"Cnr Bypass & Rafferty Rds",
    "iso:country":"AU",
    "sg:address":"Cnr Bypass & Rafferty Rds",
    "sg:city":"Mandurah",
    "sg:classifiers":[
        {
            "category":"Industrial Area",
            "type":"Public Place"
        }
    ],
    "sg:phone":"+61 8 9535 4066",
    "sg:postcode":"6210",
    "sg:province":"WA",
    "sg:tags":[
        "rural",
        "shed"
    ],
    "wof:name":"Outdoor City",
    "wof:placetype":"venue"
},
  "geometry": {"coordinates":[115.748306,-32.518337],"type":"Point"}
}