{
  "type": "Feature",
  "properties": {
    "iso:country":"AU",
    "sg:address":"10/ 176 South Creek Rd",
    "sg:city":"Cromer",
    "sg:classifiers":[
        {
            "category":"Professional",
            "subcategory":"Engineering",
            "type":"Services"
        }
    ],
    "sg:phone":"+61 2 9984 8651",
    "sg:postcode":"2099",
    "sg:province":"NSW",
    "sg:tags":[
        "diesel",
        "engineer"
    ],
    "wof:name":"Diesel Experts Pty Ltd",
    "wof:placetype":"venue"
},
  "geometry": {"coordinates":[151.279663086,-33.7342834473],"type":"Point"}
}