{
  "type": "Feature",
  "properties": {
    "addr:full":"36 Railway Crs Bentleigh VIC 3204",
    "addr:housenumber":"36",
    "addr:postcode":"3204",
    "addr:street":"Railway Crs",
    "iso:country":"AU",
    "sg:address":"36 Railway Crs",
    "sg:city":"Bentleigh",
    "sg:classifiers":[
        {
            "category":"Retail",
            "subcategory":"Auto Rental",
            "type":"Services"
        }
    ],
    "sg:phone":"+61 411 565 676",
    "sg:postcode":"3204",
    "sg:province":"VIC",
    "sg:tags":[
        "chauffeur",
        "car",
        "hire",
        "driven",
        "limousine"
    ],
    "wof:name":"Limousine Registry",
    "wof:placetype":"venue"
},
  "geometry": {"coordinates":[145.05282600000001,-37.891773],"type":"Point"}
}