{
  "type": "Feature",
  "properties": {
    "addr:full":"113 Brisbane St Beaudesert QLD 4285",
    "addr:housenumber":"113",
    "addr:postcode":"4285",
    "addr:street":"Brisbane St",
    "iso:country":"AU",
    "sg:address":"113 Brisbane St",
    "sg:city":"Beaudesert",
    "sg:classifiers":[
        {
            "category":"Real Estate",
            "subcategory":"Real Estate Agent",
            "type":"Services"
        }
    ],
    "sg:phone":"+61 7 5541 3300",
    "sg:postcode":"4285",
    "sg:province":"QLD",
    "wof:name":"Beaudesert Properties",
    "wof:placetype":"venue"
},
  "geometry": {"coordinates":[152.99588,-27.986717],"type":"Point"}
}