{
  "type": "Feature",
  "properties": {
    "iso:country":"AU",
    "sg:address":"86-92 Denmark St",
    "sg:city":"Kew",
    "sg:classifiers":[
        {
            "category":"Professional",
            "subcategory":"Computer Services",
            "type":"Services"
        }
    ],
    "sg:phone":"+61 3 9853 7322",
    "sg:postcode":"3101",
    "sg:province":"VIC",
    "sg:tags":[
        "consultant",
        "system"
    ],
    "wof:name":"Votar Partners Pty Ltd",
    "wof:placetype":"venue"
},
  "geometry": {"coordinates":[145.02897644000001,-37.8086166382],"type":"Point"}
}