{
  "type": "Feature",
  "properties": {
    "addr:full":"PO Box 34 Hazelbrook NSW 2779",
    "addr:postcode":"2779",
    "iso:country":"AU",
    "sg:address":"PO Box 34",
    "sg:city":"Hazelbrook",
    "sg:classifiers":[
        {
            "category":"Building & Trades",
            "subcategory":"Landscaping Services",
            "type":"Services"
        }
    ],
    "sg:phone":"+61 418 667 558",
    "sg:postcode":"2779",
    "sg:province":"NSW",
    "sg:tags":[
        "designer",
        "landscape",
        "contractor"
    ],
    "wof:name":"Great Gardens Design",
    "wof:placetype":"venue"
},
  "geometry": {"coordinates":[150.45307922399999,-33.7224311829],"type":"Point"}
}