{
  "type": "Feature",
  "properties": {
    "iso:country":"AU",
    "sg:address":"8 Sunset Drv",
    "sg:city":"Wangaratta",
    "sg:classifiers":[
        {
            "category":"Personal",
            "subcategory":"Beauty Salon",
            "type":"Services"
        }
    ],
    "sg:phone":"+61 439 820 660",
    "sg:postcode":"3677",
    "sg:province":"VIC",
    "wof:name":"TechnoTan",
    "wof:placetype":"venue"
},
  "geometry": {"coordinates":[146.29315185600001,-36.3494148254],"type":"Point"}
}