{
  "type": "Feature",
  "properties": {
    "addr:full":"53 Sanger St Corowa NSW 2646",
    "addr:housenumber":"53",
    "addr:postcode":"2646",
    "addr:street":"Sanger St",
    "iso:country":"AU",
    "sg:address":"53 Sanger St",
    "sg:city":"Corowa",
    "sg:classifiers":[
        {
            "category":"Travel",
            "subcategory":"Hotels & Motels",
            "type":"Entertainment"
        }
    ],
    "sg:phone":"+61 2 6033 1965",
    "sg:postcode":"2646",
    "sg:province":"NSW",
    "sg:tags":[
        "accommodation"
    ],
    "wof:name":"Corowa Hotel",
    "wof:placetype":"venue"
},
  "geometry": {"coordinates":[146.39134216299999,-35.9949035645],"type":"Point"}
}