{
  "type": "Feature",
  "properties": {
    "addr:full":"90 Ocean St Woollahra NSW 2025",
    "addr:housenumber":"90",
    "addr:postcode":"2025",
    "addr:street":"Ocean St",
    "iso:country":"AU",
    "sg:address":"90 Ocean St",
    "sg:city":"Woollahra",
    "sg:classifiers":[
        {
            "category":"Education",
            "subcategory":"Dance Studio",
            "type":"Public Place"
        }
    ],
    "sg:phone":"+61 2 8356 8366",
    "sg:postcode":"2025",
    "sg:province":"NSW",
    "sg:tags":[
        "instruction",
        "language"
    ],
    "wof:name":"Goethe- Institut",
    "wof:placetype":"venue"
},
  "geometry": {"coordinates":[151.23793029800001,-33.8813438416],"type":"Point"}
}