{
  "type": "Feature",
  "properties": {
    "addr:full":"35 Edmondson St Corinda QLD 4075",
    "addr:housenumber":"35",
    "addr:postcode":"4075",
    "addr:street":"Edmondson St",
    "iso:country":"AU",
    "sg:address":"35 Edmondson St",
    "sg:city":"Corinda",
    "sg:classifiers":[
        {
            "category":"Building & Trades",
            "subcategory":"Construction",
            "type":"Services"
        }
    ],
    "sg:phone":"+61 413 830 664",
    "sg:postcode":"4075",
    "sg:province":"QLD",
    "sg:tags":[
        "rendering",
        "cement"
    ],
    "sg:website":"http://www.texturecoatingqld.com.au",
    "wof:name":"Texture Coating QLD Pty Ltd",
    "wof:placetype":"venue"
},
  "geometry": {"coordinates":[152.989471436,-27.5488052368],"type":"Point"}
}