{
  "type": "Feature",
  "properties": {
    "addr:full":"1567 Channel Hwy Margate TAS 7054",
    "addr:housenumber":"1567",
    "addr:postcode":"7054",
    "addr:street":"Channel Hwy",
    "iso:country":"AU",
    "sg:address":"1567 Channel Hwy",
    "sg:city":"Margate",
    "sg:classifiers":[
        {
            "category":"Shopping",
            "subcategory":"Antiques",
            "type":"Retail Goods"
        }
    ],
    "sg:phone":"+61 3 6267 1667",
    "sg:postcode":"7054",
    "sg:province":"TAS",
    "wof:name":"The Good The Bad And The Ugly Secondhand",
    "wof:placetype":"venue"
},
  "geometry": {"coordinates":[147.27044699999999,-43.017704],"type":"Point"}
}