{
  "type": "Feature",
  "properties": {
    "addr:full":"Unit 5, Water Gardens Shpng Cntr Melton Hwy Taylors Lakes VIC 3038",
    "addr:housenumber":"5",
    "addr:postcode":"3038",
    "addr:street":"Water Gardens Shpng Cntr Melton Hwy",
    "iso:country":"AU",
    "sg:address":"Unit 5, Water Gardens Shpng Cntr Melton Hwy",
    "sg:city":"Taylors Lakes",
    "sg:classifiers":[
        {
            "category":"Manufacturing",
            "subcategory":"Motor Vehicles & Parts",
            "type":"Manufacturing & Wholesale Goods"
        }
    ],
    "sg:phone":"+61 3 9390 9699",
    "sg:postcode":"3038",
    "sg:province":"VIC",
    "sg:tags":[
        "replacement"
    ],
    "wof:name":"Super Cheap Auto",
    "wof:placetype":"venue"
},
  "geometry": {"coordinates":[144.781036,-37.697227],"type":"Point"}
}