{
  "type": "Feature",
  "properties": {
    "addr:full":"22 Tuscan Crt Thomastown VIC 3074",
    "addr:housenumber":"22",
    "addr:postcode":"3074",
    "addr:street":"Tuscan Crt",
    "iso:country":"AU",
    "sg:address":"22 Tuscan Crt",
    "sg:city":"Thomastown",
    "sg:classifiers":[
        {
            "category":"Autos & Motor Vehicles",
            "subcategory":"Automobile Sales",
            "type":"Retail Goods"
        }
    ],
    "sg:phone":"+61 3 9469 2039",
    "sg:postcode":"3074",
    "sg:province":"VIC",
    "sg:tags":[
        "equipment",
        "trailer"
    ],
    "wof:name":"Stallion Floats",
    "wof:placetype":"venue"
},
  "geometry": {"coordinates":[145.007354736,-37.6873245239],"type":"Point"}
}