{
  "type": "Feature",
  "properties": {
    "iso:country":"AU",
    "sg:address":"345 Belmore Rd",
    "sg:city":"Riverwood",
    "sg:classifiers":[
        {
            "category":"Autos & Motor Vehicles",
            "subcategory":"Fuel & Gas Station",
            "type":"Retail Goods"
        }
    ],
    "sg:phone":"+61 2 9153 8752",
    "sg:postcode":"2210",
    "sg:province":"NSW",
    "wof:name":"Riverwood Service Station",
    "wof:placetype":"venue"
},
  "geometry": {"coordinates":[151.05247499999999,-33.949173],"type":"Point"}
}