{
  "type": "Feature",
  "properties": {
    "addr:full":"212 Upper Miles Ave Kelso QLD 4815",
    "addr:housenumber":"212",
    "addr:postcode":"4815",
    "addr:street":"Upper Miles Ave",
    "iso:country":"AU",
    "sg:address":"212 Upper Miles Ave",
    "sg:city":"Kelso",
    "sg:classifiers":[
        {
            "category":"Health Services",
            "subcategory":"Doctor",
            "type":"Services"
        }
    ],
    "sg:phone":"+61 7 4789 0747",
    "sg:postcode":"4815",
    "sg:province":"QLD",
    "sg:tags":[
        "medical",
        "practitioner"
    ],
    "wof:name":"Ratle Pty Ltd",
    "wof:placetype":"venue"
},
  "geometry": {"coordinates":[146.729141,-19.386574],"type":"Point"}
}