{
  "type": "Feature",
  "properties": {
    "addr:full":"Level 34 Exchange Plaza, 2 The Esplande Perth WA 6000",
    "addr:housenumber":"2",
    "addr:postcode":"6000",
    "addr:street":"The",
    "iso:country":"AU",
    "sg:address":"Level 34 Exchange Plaza, 2 The Esplande",
    "sg:city":"Perth",
    "sg:classifiers":[
        {
            "category":"Banks & Credit Unions",
            "subcategory":"Investment Brokerage",
            "type":"Services"
        }
    ],
    "sg:phone":"+61 1300 799 569",
    "sg:postcode":"6000",
    "sg:province":"WA",
    "sg:tags":[
        "share",
        "broker",
        "stock"
    ],
    "sg:website":"http://www.cunninghamsec.com.au",
    "wof:name":"Cunningham Securities Pty Ltd",
    "wof:placetype":"venue"
},
  "geometry": {"coordinates":[115.858642578,-31.9566688538],"type":"Point"}
}