{
  "type": "Feature",
  "properties": {
    "addr:full":"2639 Murray Valley Hwy Nyah VIC 3594",
    "addr:housenumber":"2639",
    "addr:postcode":"3594",
    "addr:street":"Murray Valley Hwy",
    "iso:country":"AU",
    "sg:address":"2639 Murray Valley Hwy",
    "sg:city":"Nyah",
    "sg:classifiers":[
        {
            "category":"Building & Trades",
            "subcategory":"Construction",
            "type":"Services"
        }
    ],
    "sg:phone":"+61 3 5030 2234",
    "sg:postcode":"3594",
    "sg:province":"VIC",
    "sg:tags":[
        "road",
        "contractor"
    ],
    "wof:name":"Coburn's Earthmoving",
    "wof:placetype":"venue"
},
  "geometry": {"coordinates":[143.367843628,-35.1491088867],"type":"Point"}
}