{
  "type": "Feature",
  "properties": {
    "iso:country":"AU",
    "sg:address":"77- 79 Hunter St",
    "sg:city":"Newcastle",
    "sg:classifiers":[
        {
            "category":"Banks & Credit Unions",
            "subcategory":"Investment Brokerage",
            "type":"Services"
        }
    ],
    "sg:phone":"+61 2 4926 5255",
    "sg:postcode":"2300",
    "sg:province":"NSW",
    "sg:tags":[
        "share",
        "broker",
        "stock"
    ],
    "wof:name":"Bridges Personal Investment Services",
    "wof:placetype":"venue"
},
  "geometry": {"coordinates":[151.78294399999999,-32.927593],"type":"Point"}
}