{
  "type": "Feature",
  "properties": {
    "addr:full":"1 Baird Ave Holden Hill SA 5088",
    "addr:housenumber":"1",
    "addr:postcode":"5088",
    "addr:street":"Baird Ave",
    "iso:country":"AU",
    "sg:address":"1 Baird Ave",
    "sg:city":"Holden Hill",
    "sg:classifiers":[
        {
            "category":"Professional",
            "subcategory":"Art Services",
            "type":"Services"
        }
    ],
    "sg:phone":"+61 8 8266 1384",
    "sg:postcode":"5088",
    "sg:province":"SA",
    "sg:tags":[
        "decorator",
        "painter"
    ],
    "wof:name":"DaVinci Painting Services",
    "wof:placetype":"venue"
},
  "geometry": {"coordinates":[138.665817261,-34.8549957275],"type":"Point"}
}