{
  "type": "Feature",
  "properties": {
    "addr:full":"Mt View Rd Cessnock NSW 2325",
    "addr:postcode":"2325",
    "addr:street":"Mt View Rd",
    "iso:country":"AU",
    "sg:address":"Mt View Rd",
    "sg:city":"Cessnock",
    "sg:classifiers":[
        {
            "category":"Farming",
            "subcategory":"Vineyard",
            "type":"Manufacturing & Wholesale Goods"
        }
    ],
    "sg:phone":"+61 2 4990 3307",
    "sg:postcode":"2325",
    "sg:province":"NSW",
    "sg:tags":[
        "winery"
    ],
    "wof:name":"Mount View Wines",
    "wof:placetype":"venue"
},
  "geometry": {"coordinates":[151.35044860799999,-32.8337936401],"type":"Point"}
}