{
  "type": "Feature",
  "properties": {
    "addr:full":"2/ 126 - 130 Parramatta Road Auburn NSW 2144",
    "addr:housenumber":"/ 126 130",
    "addr:postcode":"2144",
    "addr:street":"Parramatta Road",
    "iso:country":"AU",
    "sg:address":"2/ 126 - 130 Parramatta Road",
    "sg:city":"Auburn",
    "sg:classifiers":[
        {
            "category":"Home & Garden",
            "subcategory":"Carpets & Floor Coverings",
            "type":"Retail Goods"
        }
    ],
    "sg:phone":"+61 2 9648 4944",
    "sg:postcode":"2144",
    "sg:province":"NSW",
    "sg:tags":[
        "wood"
    ],
    "wof:name":"Carpet Call",
    "wof:placetype":"venue"
},
  "geometry": {"coordinates":[151.04069519000001,-33.8441925049],"type":"Point"}
}