{
  "type": "Feature",
  "properties": {
    "addr:full":"Level 2, 224 Victoria Rd Drummoyne NSW 2047",
    "addr:housenumber":"224",
    "addr:postcode":"2047",
    "addr:street":"Victoria Rd",
    "iso:country":"AU",
    "sg:address":"Level 2, 224 Victoria Rd",
    "sg:city":"Drummoyne",
    "sg:classifiers":[
        {
            "category":"Sports & Exercise",
            "subcategory":"Gym",
            "type":"Entertainment"
        }
    ],
    "sg:phone":"+61 2 9819 7400",
    "sg:postcode":"2047",
    "sg:province":"NSW",
    "sg:tags":[
        "pilate",
        "method"
    ],
    "wof:name":"Exact Pilates",
    "wof:placetype":"venue"
},
  "geometry": {"coordinates":[151.155136,-33.851463],"type":"Point"}
}