{
  "type": "Feature",
  "properties": {
    "iso:country":"AU",
    "sg:address":"Unit 11/ 369 Holmes Rd",
    "sg:city":"Forrestfield",
    "sg:classifiers":[
        {
            "category":"Retail",
            "subcategory":"Auto Repair",
            "type":"Services"
        }
    ],
    "sg:phone":"+61 8 9453 3307",
    "sg:postcode":"6058",
    "sg:province":"WA",
    "sg:tags":[
        "electrical"
    ],
    "wof:name":"Forrestfield Auto Electrics",
    "wof:placetype":"venue"
},
  "geometry": {"coordinates":[116.016548157,-31.988445282],"type":"Point"}
}