{
  "type": "Feature",
  "properties": {
    "addr:full":"17 Albert St Broadbeach QLD 4218",
    "addr:housenumber":"17",
    "addr:postcode":"4218",
    "addr:street":"Albert St",
    "iso:country":"AU",
    "sg:address":"17 Albert St",
    "sg:city":"Broadbeach",
    "sg:classifiers":[
        {
            "category":"Professional",
            "subcategory":"Art Services",
            "type":"Services"
        }
    ],
    "sg:phone":"+61 7 5539 9399",
    "sg:postcode":"4218",
    "sg:province":"QLD",
    "sg:tags":[
        "graphic",
        "designer"
    ],
    "wof:name":"Sexty Peter Graphic Design",
    "wof:placetype":"venue"
},
  "geometry": {"coordinates":[153.43197631800001,-28.0281028748],"type":"Point"}
}