{
  "type": "Feature",
  "properties": {
    "addr:full":"1131 Dandenong Rd Malvern East VIC 3145",
    "addr:housenumber":"1131",
    "addr:postcode":"3145",
    "addr:street":"Dandenong Rd",
    "iso:country":"AU",
    "sg:address":"1131 Dandenong Rd",
    "sg:city":"Malvern East",
    "sg:classifiers":[
        {
            "category":"Health Services",
            "subcategory":"Health Practitioner",
            "type":"Services"
        }
    ],
    "sg:phone":"+61 3 9571 2240",
    "sg:postcode":"3145",
    "sg:province":"VIC",
    "sg:tags":[
        "osteopath"
    ],
    "wof:name":"Jacqueline Tinbury Osteopath",
    "wof:placetype":"venue"
},
  "geometry": {"coordinates":[145.06050109899999,-37.8839759827],"type":"Point"}
}