{
  "type": "Feature",
  "properties": {
    "addr:full":"cnr Kenthurst & Maple Sts Round Corner NSW 2158",
    "addr:postcode":"2158",
    "addr:street":"Cnr;Sts Round",
    "iso:country":"AU",
    "sg:address":"cnr Kenthurst & Maple Sts",
    "sg:city":"Round Corner",
    "sg:classifiers":[
        {
            "category":"Health Services",
            "subcategory":"Dentist",
            "type":"Services"
        }
    ],
    "sg:phone":"+61 2 9651 4488",
    "sg:postcode":"2158",
    "sg:province":"NSW",
    "wof:name":"Laurie Kobler & Kaye Schelbach",
    "wof:placetype":"venue"
},
  "geometry": {"coordinates":[151.01979064899999,-33.693397522],"type":"Point"}
}