{
  "type": "Feature",
  "properties": {
    "addr:full":"432 Dandelion Drv Rowville VIC 3178",
    "addr:housenumber":"432",
    "addr:postcode":"3178",
    "addr:street":"Dandelion Drv",
    "iso:country":"AU",
    "sg:address":"432 Dandelion Drv",
    "sg:city":"Rowville",
    "sg:classifiers":[
        {
            "category":"Shopping",
            "subcategory":"Optical Goods",
            "type":"Retail Goods"
        }
    ],
    "sg:phone":"+61 401 055 666",
    "sg:postcode":"3178",
    "sg:province":"VIC",
    "sg:tags":[
        "supply"
    ],
    "wof:name":"New Vision Import",
    "wof:placetype":"venue"
},
  "geometry": {"coordinates":[145.25755310100001,-37.9262771606],"type":"Point"}
}