{
  "type": "Feature",
  "properties": {
    "iso:country":"AU",
    "sg:address":"29 Trade Pl",
    "sg:city":"Vermont",
    "sg:classifiers":[
        {
            "category":"Manufacturing",
            "subcategory":"Glass & Minerals",
            "type":"Manufacturing & Wholesale Goods"
        }
    ],
    "sg:phone":"+61 3 9872 4033",
    "sg:postcode":"3133",
    "sg:province":"VIC",
    "sg:tags":[
        "fabricator",
        "foam",
        "processor"
    ],
    "wof:name":"Era Polymers Pty Ltd",
    "wof:placetype":"venue"
},
  "geometry": {"coordinates":[145.18635559099999,-37.8336753845],"type":"Point"}
}