{
  "type": "Feature",
  "properties": {
    "addr:full":"178 Riseley St Booragoon WA 6154",
    "addr:housenumber":"178",
    "addr:postcode":"6154",
    "addr:street":"Riseley St",
    "iso:country":"AU",
    "sg:address":"178 Riseley St",
    "sg:city":"Booragoon",
    "sg:classifiers":[
        {
            "category":"Health Services",
            "subcategory":"Dentist",
            "type":"Services"
        }
    ],
    "sg:phone":"+61 8 9316 2304",
    "sg:postcode":"6154",
    "sg:province":"WA",
    "wof:name":"Perkins Simon",
    "wof:placetype":"venue"
},
  "geometry": {"coordinates":[115.83812,-32.037457],"type":"Point"}
}