{
  "type": "Feature",
  "properties": {
    "iso:country":"AU",
    "sg:address":"109 Auburn St",
    "sg:city":"Wollongong",
    "sg:classifiers":[
        {
            "category":"Building & Trades",
            "subcategory":"Electrical",
            "type":"Services"
        }
    ],
    "sg:phone":"+61 2 4227 3088",
    "sg:postcode":"2500",
    "sg:province":"NSW",
    "sg:tags":[
        "repair",
        "generator",
        "electric",
        "motor"
    ],
    "sg:website":"http://www.arrow-electrical.com.au",
    "wof:name":"Arrow Electrical Services",
    "wof:placetype":"venue"
},
  "geometry": {"coordinates":[150.88743600000001,-34.437084],"type":"Point"}
}