{
  "type": "Feature",
  "properties": {
    "addr:full":"480 Norman Rd North Rockhampton QLD 4701",
    "addr:housenumber":"480",
    "addr:postcode":"4701",
    "addr:street":"Norman Rd North",
    "iso:country":"AU",
    "sg:address":"480 Norman Rd",
    "sg:city":"North Rockhampton",
    "sg:classifiers":[
        {
            "category":"Education",
            "subcategory":"School",
            "type":"Public Place"
        }
    ],
    "sg:phone":"+61 7 4926 4895",
    "sg:postcode":"4701",
    "sg:province":"QLD",
    "wof:name":"Lighthouse Christian School",
    "wof:placetype":"venue"
},
  "geometry": {"coordinates":[150.53382873499999,-23.3335456848],"type":"Point"}
}