{
  "type": "Feature",
  "properties": {
    "addr:full":"146 Gordon St Port Macquarie NSW 2444",
    "addr:housenumber":"146",
    "addr:postcode":"2444",
    "addr:street":"Gordon St",
    "iso:country":"AU",
    "sg:address":"146 Gordon St",
    "sg:city":"Port Macquarie",
    "sg:classifiers":[
        {
            "category":"Shopping",
            "subcategory":"Computers & Home Electronics",
            "type":"Retail Goods"
        }
    ],
    "sg:phone":"+61 2 6584 0255",
    "sg:postcode":"2444",
    "sg:province":"NSW",
    "sg:tags":[
        "hardware",
        "equipment"
    ],
    "wof:name":"Hastings Computer Services",
    "wof:placetype":"venue"
},
  "geometry": {"coordinates":[152.90141299999999,-31.4349],"type":"Point"}
}