{
  "type": "Feature",
  "properties": {
    "iso:country":"AU",
    "sg:address":"Samford Country Centre, 15 Main St",
    "sg:city":"Samford",
    "sg:classifiers":[
        {
            "category":"Health Services",
            "subcategory":"Doctor",
            "type":"Services"
        }
    ],
    "sg:phone":"+61 7 3289 2366",
    "sg:postcode":"4520",
    "sg:province":"QLD",
    "sg:tags":[
        "medical",
        "practitioner"
    ],
    "wof:name":"Watson Dr Alex",
    "wof:placetype":"venue"
},
  "geometry": {"coordinates":[152.88679500000001,-27.372972],"type":"Point"}
}