{
  "type": "Feature",
  "properties": {
    "addr:full":"292 Myall St Dubbo NSW 2830",
    "addr:housenumber":"292",
    "addr:postcode":"2830",
    "addr:street":"Myall St",
    "iso:country":"AU",
    "sg:address":"292 Myall St",
    "sg:city":"Dubbo",
    "sg:classifiers":[
        {
            "category":"Building & Trades",
            "subcategory":"Construction",
            "type":"Services"
        }
    ],
    "sg:phone":"+61 438 821 098",
    "sg:postcode":"2830",
    "sg:province":"NSW",
    "sg:tags":[
        "plasterboard",
        "plasterer",
        "fixer"
    ],
    "wof:name":"Greg Marks Plastering",
    "wof:placetype":"venue"
},
  "geometry": {"coordinates":[148.63059997600001,-32.2425994873],"type":"Point"}
}