{
  "type": "Feature",
  "properties": {
    "addr:full":"9-11 Railway Ave Huntingdale VIC 3166",
    "addr:housenumber":"9-11",
    "addr:postcode":"3166",
    "addr:street":"Railway Ave",
    "iso:country":"AU",
    "sg:address":"9-11 Railway Ave",
    "sg:city":"Huntingdale",
    "sg:classifiers":[
        {
            "category":"Shopping",
            "subcategory":"Mobile Phones",
            "type":"Retail Goods"
        }
    ],
    "sg:phone":"+61 3 9568 3247",
    "sg:postcode":"3166",
    "sg:province":"VIC",
    "sg:tags":[
        "wholesaler",
        "mfrs",
        "electrical",
        "switchboard"
    ],
    "wof:name":"E.M.F.",
    "wof:placetype":"venue"
},
  "geometry": {"coordinates":[145.101364136,-37.9090995789],"type":"Point"}
}