{
  "type": "Feature",
  "properties": {
    "addr:full":"41 North St Rockhampton QLD 4700",
    "addr:housenumber":"41",
    "addr:postcode":"4700",
    "addr:street":"North St",
    "iso:country":"AU",
    "sg:address":"41 North St",
    "sg:city":"Rockhampton",
    "sg:classifiers":[
        {
            "category":"Professional",
            "subcategory":"Computer Services",
            "type":"Services"
        }
    ],
    "sg:phone":"+61 1300 724 556",
    "sg:postcode":"4700",
    "sg:province":"QLD",
    "sg:tags":[
        "package",
        "software"
    ],
    "wof:name":"FrontDesk Software",
    "wof:placetype":"venue"
},
  "geometry": {"coordinates":[150.49707031200001,-23.3760795593],"type":"Point"}
}