{
  "type": "Feature",
  "properties": {
    "iso:country":"AU",
    "sg:address":"157 Brampton Drv",
    "sg:city":"Kellyville",
    "sg:classifiers":[
        {
            "category":"Home & Garden",
            "subcategory":"Building Materials",
            "type":"Retail Goods"
        }
    ],
    "sg:phone":"+61 2 8824 4747",
    "sg:postcode":"2155",
    "sg:province":"NSW",
    "sg:tags":[
        "concrete",
        "gutter",
        "kerb"
    ],
    "wof:name":"Hills Kerbs",
    "wof:placetype":"venue"
},
  "geometry": {"coordinates":[150.94711303700001,-33.7018623352],"type":"Point"}
}