{
  "type": "Feature",
  "properties": {
    "addr:full":"27 Cabragh St Ferny Grove QLD 4055",
    "addr:housenumber":"27",
    "addr:postcode":"4055",
    "addr:street":"Cabragh St",
    "iso:country":"AU",
    "sg:address":"27 Cabragh St",
    "sg:city":"Ferny Grove",
    "sg:classifiers":[
        {
            "category":"Professional",
            "subcategory":"Art Services",
            "type":"Services"
        }
    ],
    "sg:phone":"+61 418 169 404",
    "sg:postcode":"4055",
    "sg:province":"QLD",
    "sg:tags":[
        "graphic",
        "designer"
    ],
    "wof:name":"Merete Lublin",
    "wof:placetype":"venue"
},
  "geometry": {"coordinates":[152.925292969,-27.3953971863],"type":"Point"}
}