{
  "type": "Feature",
  "properties": {
    "addr:full":"Heaslip Rd Angle Vale SA 5117",
    "addr:postcode":"5117",
    "addr:street":"Heaslip Rd",
    "iso:country":"AU",
    "sg:address":"Heaslip Rd",
    "sg:city":"Angle Vale",
    "sg:classifiers":[
        {
            "category":"Personal",
            "subcategory":"Beauty Salon",
            "type":"Services"
        }
    ],
    "sg:phone":"+61 8 8284 7166",
    "sg:postcode":"5117",
    "sg:province":"SA",
    "sg:tags":[
        "hairdresser"
    ],
    "wof:name":"Country Flair Hairdressing & Beauty",
    "wof:placetype":"venue"
},
  "geometry": {"coordinates":[138.64659118599999,-34.6392250061],"type":"Point"}
}