{
  "type": "Feature",
  "properties": {
    "addr:full":"Suite 3, 54- 58 Nerang St Nerang QLD 4211",
    "addr:housenumber":"54 58",
    "addr:postcode":"4211",
    "addr:street":"Nerang St",
    "iso:country":"AU",
    "sg:address":"Suite 3, 54- 58 Nerang St",
    "sg:city":"Nerang",
    "sg:classifiers":[
        {
            "category":"Professional",
            "subcategory":"Engineering",
            "type":"Services"
        }
    ],
    "sg:phone":"+61 7 5557 1000",
    "sg:postcode":"4211",
    "sg:province":"QLD",
    "sg:tags":[
        "consulting",
        "engineer"
    ],
    "wof:name":"GHD",
    "wof:placetype":"venue"
},
  "geometry": {"coordinates":[153.339187622,-27.9880695343],"type":"Point"}
}