{
  "type": "Feature",
  "properties": {
    "addr:full":"185 Geaney La Deeragun QLD 4818",
    "addr:housenumber":"185",
    "addr:postcode":"4818",
    "addr:street":"Geaney La Deeragun",
    "iso:country":"AU",
    "sg:address":"185 Geaney La",
    "sg:city":"Deeragun",
    "sg:classifiers":[
        {
            "category":"Building & Trades",
            "subcategory":"Construction",
            "type":"Services"
        }
    ],
    "sg:phone":"+61 409 056 011",
    "sg:postcode":"4818",
    "sg:province":"QLD",
    "sg:tags":[
        "installation",
        "air conditioning"
    ],
    "wof:name":"Chillout Airconditioning & Refrigeration",
    "wof:placetype":"venue"
},
  "geometry": {"coordinates":[146.66056800000001,-19.248325],"type":"Point"}
}