{
  "type": "Feature",
  "properties": {
    "iso:country":"AU",
    "sg:address":"Donaldson St",
    "sg:city":"Braddon",
    "sg:classifiers":[
        {
            "category":"Social Services",
            "subcategory":"Child Care",
            "type":"Services"
        }
    ],
    "sg:phone":"+61 2 6249 1740",
    "sg:postcode":"2612",
    "sg:province":"ACT",
    "wof:name":"Ainslie Primary School After School Care",
    "wof:placetype":"venue"
},
  "geometry": {"coordinates":[149.13768005399999,-35.2748718262],"type":"Point"}
}