{
  "type": "Feature",
  "properties": {
    "addr:full":"Unit 2/ 8 Ereton Drv Labrador QLD 4215",
    "addr:housenumber":"8",
    "addr:postcode":"4215",
    "addr:street":"Ereton Drv",
    "iso:country":"AU",
    "sg:address":"Unit 2/ 8 Ereton Drv",
    "sg:city":"Labrador",
    "sg:classifiers":[
        {
            "category":"Recreation",
            "subcategory":"Boat Charter",
            "type":"Entertainment"
        }
    ],
    "sg:phone":"+61 7 5537 3166",
    "sg:postcode":"4215",
    "sg:province":"QLD",
    "sg:tags":[
        "canopy",
        "motor"
    ],
    "wof:name":"Broadwater Boat Upholstery",
    "wof:placetype":"venue"
},
  "geometry": {"coordinates":[153.38624572800001,-27.9345798492],"type":"Point"}
}