{
  "type": "Feature",
  "properties": {
    "addr:full":"38 Commercial Rd Salisbury SA 5108",
    "addr:housenumber":"38",
    "addr:postcode":"5108",
    "addr:street":"Commercial Rd",
    "iso:country":"AU",
    "sg:address":"38 Commercial Rd",
    "sg:city":"Salisbury",
    "sg:classifiers":[
        {
            "category":"Professional",
            "subcategory":"Accounting & Tax Preparation",
            "type":"Services"
        }
    ],
    "sg:phone":"+61 8 8281 1898",
    "sg:postcode":"5108",
    "sg:province":"SA",
    "sg:tags":[
        "accountant",
        "auditor"
    ],
    "wof:name":"Ann Matic",
    "wof:placetype":"venue"
},
  "geometry": {"coordinates":[138.649124145,-34.7552947998],"type":"Point"}
}