{
  "type": "Feature",
  "properties": {
    "iso:country":"AU",
    "sg:address":"21R Old Dubbo Rd",
    "sg:city":"Dubbo",
    "sg:classifiers":[
        {
            "category":"Professional",
            "type":"Services"
        }
    ],
    "sg:phone":"+61 2 6882 2463",
    "sg:postcode":"2830",
    "sg:province":"NSW",
    "sg:tags":[
        "transport"
    ],
    "wof:name":"Dick Smith Transport Pty Ltd",
    "wof:placetype":"venue"
},
  "geometry": {"coordinates":[148.60194397000001,-32.2627830505],"type":"Point"}
}