{
  "type": "Feature",
  "properties": {
    "iso:country":"AU",
    "sg:address":"164 Hare St",
    "sg:city":"Echuca",
    "sg:classifiers":[
        {
            "category":"Shopping",
            "subcategory":"Clothing, Apparel, & Fashions",
            "type":"Retail Goods"
        }
    ],
    "sg:phone":"+61 3 5480 7977",
    "sg:postcode":"3564",
    "sg:province":"VIC",
    "sg:tags":[
        "accessory"
    ],
    "wof:name":"Kleins",
    "wof:placetype":"venue"
},
  "geometry": {"coordinates":[144.749099731,-36.1267814636],"type":"Point"}
}