{
  "type": "Feature",
  "properties": {
    "addr:full":"40 Gladstone St Glenrowan VIC 3675",
    "addr:housenumber":"40",
    "addr:postcode":"3675",
    "addr:street":"Gladstone St",
    "iso:country":"AU",
    "sg:address":"40 Gladstone St",
    "sg:city":"Glenrowan",
    "sg:classifiers":[
        {
            "category":"Fast Food",
            "type":"Food & Drink"
        }
    ],
    "sg:phone":"+61 3 5766 2023",
    "sg:postcode":"3675",
    "sg:province":"VIC",
    "sg:tags":[
        "away",
        "take"
    ],
    "wof:name":"Ned's Burger House",
    "wof:placetype":"venue"
},
  "geometry": {"coordinates":[146.223465,-36.463894],"type":"Point"}
}