{
  "type": "Feature",
  "properties": {
    "addr:full":"1/ 341 Bong Bong St Bowral NSW 2576",
    "addr:housenumber":"/ 341",
    "addr:postcode":"2576",
    "addr:street":"Bong Bong St",
    "iso:country":"AU",
    "sg:address":"1/ 341 Bong Bong St",
    "sg:city":"Bowral",
    "sg:classifiers":[
        {
            "category":"Professional",
            "subcategory":"Computer Services",
            "type":"Services"
        }
    ],
    "sg:phone":"+61 2 4861 4477",
    "sg:postcode":"2576",
    "sg:province":"NSW",
    "sg:tags":[
        "training"
    ],
    "wof:name":"Bowral Computer Centre",
    "wof:placetype":"venue"
},
  "geometry": {"coordinates":[150.417694092,-34.4804611206],"type":"Point"}
}