{
  "type": "Feature",
  "properties": {
    "addr:full":"12 Birdwood St Golden Beach QLD 4551",
    "addr:housenumber":"12",
    "addr:postcode":"4551",
    "addr:street":"Birdwood St",
    "iso:country":"AU",
    "sg:address":"12 Birdwood St",
    "sg:city":"Golden Beach",
    "sg:classifiers":[
        {
            "category":"Building & Trades",
            "subcategory":"Construction",
            "type":"Services"
        }
    ],
    "sg:phone":"+61 7 5492 3500",
    "sg:postcode":"4551",
    "sg:province":"QLD",
    "sg:tags":[
        "contractor"
    ],
    "wof:name":"Brown M L & P D",
    "wof:placetype":"venue"
},
  "geometry": {"coordinates":[153.117477417,-26.8258419037],"type":"Point"}
}