{
  "type": "Feature",
  "properties": {
    "iso:country":"AU",
    "sg:address":"40 Franleigh Drv",
    "sg:city":"Narre Warren",
    "sg:classifiers":[
        {
            "category":"Insurance",
            "subcategory":"Insurance Agent",
            "type":"Services"
        }
    ],
    "sg:phone":"+61 3 9796 7325",
    "sg:postcode":"3805",
    "sg:province":"VIC",
    "wof:name":"David J Allen & Associates Pty Ltd",
    "wof:placetype":"venue"
},
  "geometry": {"coordinates":[145.30422999999999,-38.008148],"type":"Point"}
}