{
  "type": "Feature",
  "properties": {
    "addr:full":"495 Nepean Hwy Frankston VIC 3199",
    "addr:housenumber":"495",
    "addr:postcode":"3199",
    "addr:street":"Nepean Hwy",
    "iso:country":"AU",
    "sg:address":"495 Nepean Hwy",
    "sg:city":"Frankston",
    "sg:classifiers":[
        {
            "category":"Recreation",
            "subcategory":"Fishing",
            "type":"Entertainment"
        }
    ],
    "sg:phone":"+61 3 9783 9774",
    "sg:postcode":"3199",
    "sg:province":"VIC",
    "sg:tags":[
        "tackle"
    ],
    "wof:name":"Billfisher Tackle",
    "wof:placetype":"venue"
},
  "geometry": {"coordinates":[145.011154175,-37.9084587097],"type":"Point"}
}