{
  "type": "Feature",
  "properties": {
    "addr:full":"11 Eleazar Drv Blacksoil QLD 4306",
    "addr:housenumber":"11",
    "addr:postcode":"4306",
    "addr:street":"Eleazar Drv",
    "iso:country":"AU",
    "sg:address":"11 Eleazar Drv",
    "sg:city":"Blacksoil",
    "sg:classifiers":[
        {
            "category":"Social Services",
            "subcategory":"Child Care",
            "type":"Services"
        }
    ],
    "sg:phone":"+61 7 3201 4231",
    "sg:postcode":"4306",
    "sg:province":"QLD",
    "wof:name":"Bush Kidz Child Care Centre",
    "wof:placetype":"venue"
},
  "geometry": {"coordinates":[152.70709228499999,-27.5761413574],"type":"Point"}
}