{
  "type": "Feature",
  "properties": {
    "iso:country":"AU",
    "sg:address":"3 Pinewood Drv",
    "sg:city":"Sanctuary Cove",
    "sg:classifiers":[
        {
            "category":"Autos & Motor Vehicles",
            "subcategory":"Fuel & Gas Station",
            "type":"Retail Goods"
        }
    ],
    "sg:phone":"+61 7 5577 8688",
    "sg:postcode":"4212",
    "sg:province":"QLD",
    "wof:name":"Mobil Oil Aust Ltd",
    "wof:placetype":"venue"
},
  "geometry": {"coordinates":[153.275878906,-27.897731781],"type":"Point"}
}