{
  "type": "Feature",
  "properties": {
    "addr:full":"34 Redwood Crs Melville WA 6156",
    "addr:housenumber":"34",
    "addr:postcode":"6156",
    "addr:street":"Redwood Crs",
    "iso:country":"AU",
    "sg:address":"34 Redwood Crs",
    "sg:city":"Melville",
    "sg:classifiers":[
        {
            "category":"Shopping",
            "subcategory":"Computers & Home Electronics",
            "type":"Retail Goods"
        }
    ],
    "sg:phone":"+61 419 949 060",
    "sg:postcode":"6156",
    "sg:province":"WA",
    "sg:tags":[
        "detector",
        "electronic"
    ],
    "wof:name":"B.Z. Plumbing & Gas",
    "wof:placetype":"venue"
},
  "geometry": {"coordinates":[115.80201,-32.042488],"type":"Point"}
}