{
  "type": "Feature",
  "properties": {
    "addr:full":"62 Lines St Grange SA 5022",
    "addr:housenumber":"62",
    "addr:postcode":"5022",
    "addr:street":"Lines St",
    "iso:country":"AU",
    "sg:address":"62 Lines St",
    "sg:city":"Grange",
    "sg:classifiers":[
        {
            "category":"Home & Garden",
            "subcategory":"Carpets & Floor Coverings",
            "type":"Retail Goods"
        }
    ],
    "sg:phone":"+61 412 718 795",
    "sg:postcode":"5022",
    "sg:province":"SA",
    "sg:tags":[
        "tile",
        "wall",
        "layer"
    ],
    "wof:name":"Frank Parisi Tiling",
    "wof:placetype":"venue"
},
  "geometry": {"coordinates":[138.50088500999999,-34.8954429626],"type":"Point"}
}