{
  "type": "Feature",
  "properties": {
    "addr:full":"81 Roberts Rd Lathlain WA 6100",
    "addr:housenumber":"81",
    "addr:postcode":"6100",
    "addr:street":"Roberts Rd",
    "iso:country":"AU",
    "sg:address":"81 Roberts Rd",
    "sg:city":"Lathlain",
    "sg:classifiers":[
        {
            "category":"Shopping",
            "subcategory":"Computers & Home Electronics",
            "type":"Retail Goods"
        }
    ],
    "sg:phone":"+61 8 9362 2777",
    "sg:postcode":"6100",
    "sg:province":"WA",
    "sg:tags":[
        "small",
        "equipment",
        "business"
    ],
    "wof:name":"That Computer Shop",
    "wof:placetype":"venue"
},
  "geometry": {"coordinates":[115.914932251,-31.9689331055],"type":"Point"}
}