{
  "type": "Feature",
  "properties": {
    "addr:full":"77 Scarborough Beach Rd Mt Hawthorn WA 6016",
    "addr:housenumber":"77",
    "addr:postcode":"6016",
    "addr:street":"Scarborough Beach Rd",
    "iso:country":"AU",
    "sg:address":"77 Scarborough Beach Rd",
    "sg:city":"Mt Hawthorn",
    "sg:classifiers":[
        {
            "category":"Health Services",
            "subcategory":"Health Practitioner",
            "type":"Services"
        }
    ],
    "sg:phone":"+61 8 9444 2024",
    "sg:postcode":"6016",
    "sg:province":"WA",
    "sg:tags":[
        "physiotherapist"
    ],
    "wof:name":"Leederville/North Perth Physiotherapy & Sports Injury Centre",
    "wof:placetype":"venue"
},
  "geometry": {"coordinates":[115.84607696499999,-31.9241428375],"type":"Point"}
}