{
  "type": "Feature",
  "properties": {
    "addr:full":"4/ 23 Scott St Cairns QLD 4870",
    "addr:housenumber":"/ 23",
    "addr:postcode":"4870",
    "addr:street":"Scott St",
    "iso:country":"AU",
    "sg:address":"4/ 23 Scott St",
    "sg:city":"Cairns",
    "sg:classifiers":[
        {
            "category":"Professional",
            "subcategory":"Business Services",
            "type":"Services"
        }
    ],
    "sg:phone":"+61 7 4031 1031",
    "sg:postcode":"4870",
    "sg:province":"QLD",
    "sg:tags":[
        "consultant",
        "leasing"
    ],
    "wof:name":"John Roberts Finance",
    "wof:placetype":"venue"
},
  "geometry": {"coordinates":[145.76846313499999,-16.9275760651],"type":"Point"}
}