{
  "type": "Feature",
  "properties": {
    "addr:full":"Unit 6 / 31 Dwyer St Gosford North NSW 2250",
    "addr:housenumber":"31",
    "addr:postcode":"2250",
    "addr:street":"Dwyer St",
    "iso:country":"AU",
    "sg:address":"Unit 6 / 31 Dwyer St",
    "sg:city":"Gosford North",
    "sg:classifiers":[
        {
            "category":"Professional",
            "subcategory":"Engineering",
            "type":"Services"
        }
    ],
    "sg:phone":"+61 2 4324 3551",
    "sg:postcode":"2250",
    "sg:province":"NSW",
    "sg:tags":[
        "engineer"
    ],
    "wof:name":"DPC Engineering Services Pty Ltd",
    "wof:placetype":"venue"
},
  "geometry": {"coordinates":[151.34344482399999,-33.4150848389],"type":"Point"}
}