{
  "type": "Feature",
  "properties": {
    "iso:country":"AU",
    "sg:address":"11 Daphne St",
    "sg:city":"Lismore",
    "sg:classifiers":[
        {
            "category":"Personal",
            "subcategory":"Massage",
            "type":"Services"
        }
    ],
    "sg:phone":"+61 2 6622 1668",
    "sg:postcode":"2480",
    "sg:province":"NSW",
    "sg:tags":[
        "therapy"
    ],
    "wof:name":"Morgan Neville",
    "wof:placetype":"venue"
},
  "geometry": {"coordinates":[153.28125,-28.8181800842],"type":"Point"}
}