{
  "type": "Feature",
  "properties": {
    "iso:country":"AU",
    "sg:address":"358 Barry Rd",
    "sg:city":"Campbellfield",
    "sg:classifiers":[
        {
            "category":"Social Services",
            "subcategory":"Child Care",
            "type":"Services"
        }
    ],
    "sg:phone":"+61 3 9357 8758",
    "sg:postcode":"3061",
    "sg:province":"VIC",
    "wof:name":"Broadmeadows Multicultural Early Learning Centre",
    "wof:placetype":"venue"
},
  "geometry": {"coordinates":[144.947555542,-37.6663665771],"type":"Point"}
}