{
  "type": "Feature",
  "properties": {
    "addr:full":"63 Aumuller St Portsmith QLD 4870",
    "addr:housenumber":"63",
    "addr:postcode":"4870",
    "addr:street":"Aumuller St Portsmith",
    "iso:country":"AU",
    "sg:address":"63 Aumuller St",
    "sg:city":"Portsmith",
    "sg:classifiers":[
        {
            "category":"Food & Beverages",
            "subcategory":"Liquor & Beverages",
            "type":"Retail Goods"
        }
    ],
    "sg:phone":"+61 7 4041 9544",
    "sg:postcode":"4870",
    "sg:province":"QLD",
    "sg:tags":[
        "store"
    ],
    "wof:name":"Hedley Liquor Group Head Office",
    "wof:placetype":"venue"
},
  "geometry": {"coordinates":[145.76643371599999,-16.9406051636],"type":"Point"}
}