{
  "type": "Feature",
  "properties": {
    "addr:full":"192 Wattle St Lyneham ACT 2602",
    "addr:housenumber":"192",
    "addr:postcode":"2602",
    "addr:street":"Wattle St",
    "iso:country":"AU",
    "sg:address":"192 Wattle St",
    "sg:city":"Lyneham",
    "sg:classifiers":[
        {
            "category":"Health Services",
            "subcategory":"Health Practitioner",
            "type":"Services"
        }
    ],
    "sg:phone":"+61 2 6161 4159",
    "sg:postcode":"2602",
    "sg:province":"ACT",
    "sg:tags":[
        "naturopath"
    ],
    "wof:name":"Brigitta Rudnicki-Herbalist",
    "wof:placetype":"venue"
},
  "geometry": {"coordinates":[149.118087769,-35.2462425232],"type":"Point"}
}