{
  "type": "Feature",
  "properties": {
    "iso:country":"AU",
    "sg:address":"825 Zillmere Rd",
    "sg:city":"Aspley",
    "sg:classifiers":[
        {
            "category":"Shopping",
            "subcategory":"Crafts & Fabrics",
            "type":"Retail Goods"
        }
    ],
    "sg:phone":"+61 7 3862 9144",
    "sg:postcode":"4034",
    "sg:province":"QLD",
    "sg:tags":[
        "supply"
    ],
    "wof:name":"A Scented Garden",
    "wof:placetype":"venue"
},
  "geometry": {"coordinates":[153.017517,-27.356058],"type":"Point"}
}