{
  "type": "Feature",
  "properties": {
    "iso:country":"AU",
    "sg:address":"Level 1, Suite 3, 28 Somerset Ave",
    "sg:city":"Narellan",
    "sg:classifiers":[
        {
            "category":"Professional",
            "subcategory":"Art Services",
            "type":"Services"
        }
    ],
    "sg:phone":"+61 2 4648 6500",
    "sg:postcode":"2567",
    "sg:province":"NSW",
    "sg:tags":[
        "graphic",
        "designer"
    ],
    "wof:name":"Ocorp Media Pty Ltd",
    "wof:placetype":"venue"
},
  "geometry": {"coordinates":[150.7396698,-34.0418357849],"type":"Point"}
}