{
  "type": "Feature",
  "properties": {
    "iso:country":"AU",
    "sg:address":"Unit 1/ 14 Vista St",
    "sg:city":"Penrith",
    "sg:classifiers":[
        {
            "category":"Arena",
            "subcategory":"Sports Club",
            "type":"Entertainment"
        }
    ],
    "sg:phone":"+61 2 4722 5206",
    "sg:postcode":"2750",
    "sg:province":"NSW",
    "sg:tags":[
        "tour",
        "holiday"
    ],
    "wof:name":"Golf Sydney Tours Pty Ltd",
    "wof:placetype":"venue"
},
  "geometry": {"coordinates":[151.154541016,-33.7381095886],"type":"Point"}
}