{
  "type": "Feature",
  "properties": {
    "addr:full":"Unit 1, 185 The Entrance Rd Erina NSW 2250",
    "addr:housenumber":"185",
    "addr:postcode":"2250",
    "addr:street":"The Entrance Rd",
    "iso:country":"AU",
    "sg:address":"Unit 1, 185 The Entrance Rd",
    "sg:city":"Erina",
    "sg:classifiers":[
        {
            "category":"Building & Trades",
            "subcategory":"Equipment Rental",
            "type":"Services"
        }
    ],
    "sg:phone":"+61 2 4365 6455",
    "sg:postcode":"2250",
    "sg:province":"NSW",
    "sg:tags":[
        "fitness"
    ],
    "wof:name":"Elite Fitness Equipment",
    "wof:placetype":"venue"
},
  "geometry": {"coordinates":[151.38473510700001,-33.4361152649],"type":"Point"}
}