{
  "type": "Feature",
  "properties": {
    "addr:full":"34 Buckley St Marrickville NSW 2204",
    "addr:housenumber":"34",
    "addr:postcode":"2204",
    "addr:street":"Buckley St",
    "iso:country":"AU",
    "sg:address":"34 Buckley St",
    "sg:city":"Marrickville",
    "sg:classifiers":[
        {
            "category":"Farming",
            "subcategory":"Fish & Marine Products",
            "type":"Manufacturing & Wholesale Goods"
        }
    ],
    "sg:phone":"+61 2 9519 3785",
    "sg:postcode":"2204",
    "sg:province":"NSW",
    "sg:tags":[
        "supplier",
        "oyster",
        "farmer"
    ],
    "wof:name":"Faros Bros Oyster Supplies Pty Ltd",
    "wof:placetype":"venue"
},
  "geometry": {"coordinates":[151.16473400000001,-33.913864],"type":"Point"}
}