{
  "type": "Feature",
  "properties": {
    "addr:full":"116 Abercrombie St Chippendale NSW 2008",
    "addr:housenumber":"116",
    "addr:postcode":"2008",
    "addr:street":"Abercrombie St",
    "iso:country":"AU",
    "sg:address":"116 Abercrombie St",
    "sg:city":"Chippendale",
    "sg:classifiers":[
        {
            "category":"Shopping",
            "subcategory":"Stationery & Office Supplies",
            "type":"Retail Goods"
        }
    ],
    "sg:phone":"+61 2 9319 6359",
    "sg:postcode":"2008",
    "sg:province":"NSW",
    "wof:name":"Officesmart",
    "wof:placetype":"venue"
},
  "geometry": {"coordinates":[151.19900512699999,-33.8884925842],"type":"Point"}
}