{
  "type": "Feature",
  "properties": {
    "addr:full":"Unit 3/ 2 Forge St Blacktown NSW 2148",
    "addr:housenumber":"2",
    "addr:postcode":"2148",
    "addr:street":"Forge St",
    "iso:country":"AU",
    "sg:address":"Unit 3/ 2 Forge St",
    "sg:city":"Blacktown",
    "sg:classifiers":[
        {
            "category":"Manufacturing",
            "subcategory":"Furniture",
            "type":"Manufacturing & Wholesale Goods"
        }
    ],
    "sg:phone":"+61 2 9621 1016",
    "sg:postcode":"2148",
    "sg:province":"NSW",
    "sg:tags":[
        "builder",
        "designer",
        "custom"
    ],
    "wof:name":"Impressive Furnishings",
    "wof:placetype":"venue"
},
  "geometry": {"coordinates":[150.90934753400001,-33.7570533752],"type":"Point"}
}