{
  "type": "Feature",
  "properties": {
    "addr:full":"Shop 14 176 The Entrance Rd Erina NSW 2250",
    "addr:housenumber":"shop 14 176",
    "addr:postcode":"2250",
    "addr:street":"The Entrance Rd",
    "iso:country":"AU",
    "sg:address":"Shop 14 176 The Entrance Rd",
    "sg:city":"Erina",
    "sg:classifiers":[
        {
            "category":"Retail",
            "subcategory":"Repair Shop",
            "type":"Services"
        }
    ],
    "sg:phone":"+61 2 4365 1127",
    "sg:postcode":"2250",
    "sg:province":"NSW",
    "sg:tags":[
        "machine",
        "sewing"
    ],
    "wof:name":"Erina Sewing Centre",
    "wof:placetype":"venue"
},
  "geometry": {"coordinates":[151.38470459000001,-33.4361572266],"type":"Point"}
}