{
  "type": "Feature",
  "properties": {
    "addr:full":"88 Broadway St Cobram NSW 3644",
    "addr:housenumber":"88",
    "addr:postcode":"3644",
    "addr:street":"Broadway St",
    "iso:country":"AU",
    "sg:address":"88 Broadway St",
    "sg:city":"Cobram",
    "sg:classifiers":[
        {
            "category":"Manufacturing",
            "subcategory":"Retail Goods",
            "type":"Manufacturing & Wholesale Goods"
        }
    ],
    "sg:phone":"+61 3 5872 1430",
    "sg:postcode":"3644",
    "sg:province":"NSW",
    "sg:tags":[
        "merchant",
        "pump",
        "mfrs"
    ],
    "wof:name":"A.E.M. Engineering (Cobram) Pty Ltd",
    "wof:placetype":"venue"
},
  "geometry": {"coordinates":[145.644042969,-35.9166221619],"type":"Point"}
}