{
  "type": "Feature",
  "properties": {
    "addr:full":"Unit 10 200 Carrington Rd Randwick NSW 2031",
    "addr:housenumber":"200",
    "addr:postcode":"2031",
    "addr:street":"Carrington Rd",
    "iso:country":"AU",
    "sg:address":"Unit 10 200 Carrington Rd",
    "sg:city":"Randwick",
    "sg:classifiers":[
        {
            "category":"Building & Trades",
            "subcategory":"Plumbing",
            "type":"Services"
        }
    ],
    "sg:phone":"+61 400 932 822",
    "sg:postcode":"2031",
    "sg:province":"NSW",
    "sg:tags":[
        "drainers"
    ],
    "wof:name":"Electric Eel",
    "wof:placetype":"venue"
},
  "geometry": {"coordinates":[151.24888610799999,-33.9158935547],"type":"Point"}
}