{
  "type": "Feature",
  "properties": {
    "addr:full":"213 South St Beaconsfield WA 6162",
    "addr:housenumber":"213",
    "addr:postcode":"6162",
    "addr:street":"South St",
    "iso:country":"AU",
    "sg:address":"213 South St",
    "sg:city":"Beaconsfield",
    "sg:classifiers":[
        {
            "category":"Health Services",
            "subcategory":"Doctor",
            "type":"Services"
        }
    ],
    "sg:phone":"+61 8 9335 9884",
    "sg:postcode":"6162",
    "sg:province":"WA",
    "sg:tags":[
        "medical",
        "practitioner"
    ],
    "wof:name":"Lim Stephen Dr",
    "wof:placetype":"venue"
},
  "geometry": {"coordinates":[115.77336099999999,-32.063461],"type":"Point"}
}