{
  "type": "Feature",
  "properties": {
    "iso:country":"AU",
    "sg:address":"Level 1/ 25 Adelaide St",
    "sg:city":"Brisbane",
    "sg:classifiers":[
        {
            "category":"Internet Cafe",
            "subcategory":"None",
            "type":"Food & Drink"
        }
    ],
    "sg:phone":"+61 7 3012 9331",
    "sg:postcode":"4000",
    "sg:province":"QLD",
    "wof:name":"Cyber Room",
    "wof:placetype":"venue"
},
  "geometry": {"coordinates":[153.02331543,-27.4699382782],"type":"Point"}
}