{
  "type": "Feature",
  "properties": {
    "addr:full":"3 Bond St South Yarra VIC 3141",
    "addr:housenumber":"3",
    "addr:postcode":"3141",
    "addr:street":"Bond St",
    "iso:country":"AU",
    "sg:address":"3 Bond St",
    "sg:city":"South Yarra",
    "sg:classifiers":[
        {
            "category":"Shopping",
            "subcategory":"Computers & Home Electronics",
            "type":"Retail Goods"
        }
    ],
    "sg:phone":"+61 3 9827 6511",
    "sg:postcode":"3141",
    "sg:province":"VIC",
    "sg:tags":[
        "equipment",
        "multimedia"
    ],
    "wof:name":"Australian Business Theatre",
    "wof:placetype":"venue"
},
  "geometry": {"coordinates":[144.99472045900001,-37.8408508301],"type":"Point"}
}