{
  "type": "Feature",
  "properties": {
    "iso:country":"AU",
    "sg:address":"PO Box 401",
    "sg:city":"Bellingen",
    "sg:classifiers":[
        {
            "category":"Professional",
            "subcategory":"Computer Services",
            "type":"Services"
        }
    ],
    "sg:phone":"+61 2 6655 9744",
    "sg:postcode":"2454",
    "sg:province":"NSW",
    "sg:tags":[
        "consultant",
        "system"
    ],
    "wof:name":"Progressive Business Management",
    "wof:placetype":"venue"
},
  "geometry": {"coordinates":[152.898636,-30.452419],"type":"Point"}
}