{
  "type": "Feature",
  "properties": {
    "addr:full":"16 Salisbury Hwy Salisbury SA 5108",
    "addr:housenumber":"16",
    "addr:postcode":"5108",
    "addr:street":"Salisbury Hwy",
    "iso:country":"AU",
    "sg:address":"16 Salisbury Hwy",
    "sg:city":"Salisbury",
    "sg:classifiers":[
        {
            "category":"Health Services",
            "subcategory":"Chiropractor",
            "type":"Services"
        }
    ],
    "sg:phone":"+61 8 8281 0911",
    "sg:postcode":"5108",
    "sg:province":"SA",
    "wof:name":"Reader Odette T",
    "wof:placetype":"venue"
},
  "geometry": {"coordinates":[138.64682006800001,-34.7564353943],"type":"Point"}
}