{
  "type": "Feature",
  "properties": {
    "iso:country":"AU",
    "sg:address":"Lvl 3 12 Waters Rd",
    "sg:city":"Neutral Bay",
    "sg:classifiers":[
        {
            "category":"Health Services",
            "subcategory":"Health Practitioner",
            "type":"Services"
        }
    ],
    "sg:phone":"+61 2 9908 4434",
    "sg:postcode":"2089",
    "sg:province":"NSW",
    "sg:tags":[
        "psychologist"
    ],
    "wof:name":"Allum Shirley",
    "wof:placetype":"venue"
},
  "geometry": {"coordinates":[151.223480225,-33.830783844],"type":"Point"}
}