{
  "type": "Feature",
  "properties": {
    "addr:full":"458 Stuart Hwy Winnellie NT 0820",
    "addr:housenumber":"458",
    "addr:postcode":"nt 0820",
    "addr:street":"Stuart Hwy",
    "iso:country":"AU",
    "sg:address":"458 Stuart Hwy",
    "sg:city":"Winnellie",
    "sg:classifiers":[
        {
            "category":"Building & Trades",
            "subcategory":"Construction",
            "type":"Services"
        }
    ],
    "sg:phone":"+61 1300 654 247",
    "sg:postcode":"0820",
    "sg:province":"NT",
    "sg:tags":[
        "industrial",
        "commercial",
        "air conditioning"
    ],
    "wof:name":"Carrier Air Conditioning Pty Ltd",
    "wof:placetype":"venue"
},
  "geometry": {"coordinates":[130.882324219,-12.4253158569],"type":"Point"}
}