{
  "type": "Feature",
  "properties": {
    "addr:full":"3/ 7 St Georges Crs Faulconbridge NSW 2776",
    "addr:housenumber":"/ 7",
    "addr:postcode":"2776",
    "addr:street":"St Georges Crs",
    "iso:country":"AU",
    "sg:address":"3/ 7 St Georges Crs",
    "sg:city":"Faulconbridge",
    "sg:classifiers":[
        {
            "category":"Home & Garden",
            "subcategory":"Building Materials",
            "type":"Retail Goods"
        }
    ],
    "sg:phone":"+61 2 4751 8711",
    "sg:postcode":"2776",
    "sg:province":"NSW",
    "sg:tags":[
        "roofing"
    ],
    "wof:name":"Australian School of Outdoor Technical Training",
    "wof:placetype":"venue"
},
  "geometry": {"coordinates":[151.08518981899999,-33.9645462036],"type":"Point"}
}