{
  "type": "Feature",
  "properties": {
    "addr:full":"363 Camberwell Rd Camberwell VIC 3124",
    "addr:housenumber":"363",
    "addr:postcode":"3124",
    "addr:street":"Camberwell Rd",
    "iso:country":"AU",
    "sg:address":"363 Camberwell Rd",
    "sg:city":"Camberwell",
    "sg:classifiers":[
        {
            "category":"Banks & Credit Unions",
            "subcategory":"Financial Services",
            "type":"Services"
        }
    ],
    "sg:phone":"+61 3 9805 0500",
    "sg:postcode":"3124",
    "sg:province":"VIC",
    "sg:tags":[
        "planning"
    ],
    "wof:name":"Mercer Financial Planning P/L",
    "wof:placetype":"venue"
},
  "geometry": {"coordinates":[145.06044006400001,-37.8342971802],"type":"Point"}
}