{
  "type": "Feature",
  "properties": {
    "addr:full":"690a Great Western Hwy Faulconbridge NSW 2776",
    "addr:housenumber":"690a",
    "addr:postcode":"2776",
    "addr:street":"Great Western Hwy",
    "iso:country":"AU",
    "sg:address":"690a Great Western Hwy",
    "sg:city":"Faulconbridge",
    "sg:classifiers":[
        {
            "category":"Autos & Motor Vehicles",
            "subcategory":"Fuel & Gas Station",
            "type":"Retail Goods"
        }
    ],
    "sg:phone":"+61 2 4751 1119",
    "sg:postcode":"2776",
    "sg:province":"NSW",
    "wof:name":"Galluzzi John",
    "wof:placetype":"venue"
},
  "geometry": {"coordinates":[150.52961730999999,-33.7044868469],"type":"Point"}
}