{
  "type": "Feature",
  "properties": {
    "addr:full":"Level 1 153 Park St South Melbourne VIC 3205",
    "addr:housenumber":"153",
    "addr:postcode":"3205",
    "addr:street":"Park St",
    "iso:country":"AU",
    "sg:address":"Level 1 153 Park St",
    "sg:city":"South Melbourne",
    "sg:classifiers":[
        {
            "category":"Professional",
            "subcategory":"Management & Consulting",
            "type":"Services"
        }
    ],
    "sg:phone":"+61 3 9782 6467",
    "sg:postcode":"3205",
    "sg:province":"VIC",
    "sg:tags":[
        "consultant"
    ],
    "wof:name":"Breakthrough Transformations",
    "wof:placetype":"venue"
},
  "geometry": {"coordinates":[144.96347,-37.834797],"type":"Point"}
}