{
  "type": "Feature",
  "properties": {
    "iso:country":"AU",
    "sg:address":"68 Meakin St",
    "sg:city":"Watsonia",
    "sg:classifiers":[
        {
            "category":"Professional",
            "subcategory":"Art Services",
            "type":"Services"
        }
    ],
    "sg:phone":"+61 415 310 655",
    "sg:postcode":"3087",
    "sg:province":"VIC",
    "sg:tags":[
        "interior",
        "decorator"
    ],
    "wof:name":"Degani & Son Pro Painters",
    "wof:placetype":"venue"
},
  "geometry": {"coordinates":[145.089447022,-37.6998710632],"type":"Point"}
}