{
  "type": "Feature",
  "properties": {
    "iso:country":"AU",
    "sg:address":"Off Vanderlin Drv",
    "sg:city":"Leanyer",
    "sg:classifiers":[
        {
            "category":"Home & Garden",
            "subcategory":"Garden Supply",
            "type":"Retail Goods"
        }
    ],
    "sg:phone":"+61 1300 558 449",
    "sg:postcode":"0812",
    "sg:province":"NT",
    "sg:tags":[
        "landscape"
    ],
    "wof:name":"Shoal Bay Mulch",
    "wof:placetype":"venue"
},
  "geometry": {"coordinates":[130.891953,-12.37748],"type":"Point"}
}