{
  "type": "Feature",
  "properties": {
    "addr:full":"15 Tecoma St Kingston QLD 4114",
    "addr:housenumber":"15",
    "addr:postcode":"4114",
    "addr:street":"Tecoma St",
    "iso:country":"AU",
    "sg:address":"15 Tecoma St",
    "sg:city":"Kingston",
    "sg:classifiers":[
        {
            "category":"Manufacturing",
            "subcategory":"Musical Instruments",
            "type":"Manufacturing & Wholesale Goods"
        }
    ],
    "sg:phone":"+61 7 3290 2641",
    "sg:postcode":"4114",
    "sg:province":"QLD",
    "sg:tags":[
        "repair",
        "maker"
    ],
    "wof:name":"Conchord Guitars",
    "wof:placetype":"venue"
},
  "geometry": {"coordinates":[153.10496520999999,-27.6616802216],"type":"Point"}
}