{
  "type": "Feature",
  "properties": {
    "addr:full":"23B Fairbrother St Belmont WA 6104",
    "addr:housenumber":"23b",
    "addr:postcode":"6104",
    "addr:street":"Fairbrother St",
    "iso:country":"AU",
    "sg:address":"23B Fairbrother St",
    "sg:city":"Belmont",
    "sg:classifiers":[
        {
            "category":"Shopping",
            "subcategory":"Bicycles & Sporting Goods",
            "type":"Retail Goods"
        }
    ],
    "sg:phone":"+61 8 9277 3900",
    "sg:postcode":"6104",
    "sg:province":"WA",
    "sg:tags":[
        "synthetic",
        "surface"
    ],
    "wof:name":"Synthetic Astro Lawn",
    "wof:placetype":"venue"
},
  "geometry": {"coordinates":[115.92825317400001,-31.9516639709],"type":"Point"}
}