{
  "type": "Feature",
  "properties": {
    "iso:country":"AU",
    "sg:address":"Shp 6 / 1 Hay St",
    "sg:city":"The Garrison Building Port Macquarie",
    "sg:classifiers":[
        {
            "category":"Shopping",
            "subcategory":"Clothing, Apparel, & Fashions",
            "type":"Retail Goods"
        }
    ],
    "sg:phone":"+61 2 6584 9872",
    "sg:postcode":"2444",
    "sg:province":"NSW",
    "sg:tags":[
        "maternity",
        "wear"
    ],
    "wof:name":"Belly And Babe",
    "wof:placetype":"venue"
},
  "geometry": {"coordinates":[152.909897,-31.432638],"type":"Point"}
}