{
  "type": "Feature",
  "properties": {
    "addr:full":"228 St Pauls Tce Fortitude Valley QLD 4006",
    "addr:housenumber":"228",
    "addr:postcode":"4006",
    "addr:street":"St Pauls Tce",
    "iso:country":"AU",
    "sg:address":"228 St Pauls Tce",
    "sg:city":"Fortitude Valley",
    "sg:classifiers":[
        {
            "category":"Social Services",
            "subcategory":"Child Care",
            "type":"Services"
        }
    ],
    "sg:phone":"+61 7 3252 2667",
    "sg:postcode":"4006",
    "sg:province":"QLD",
    "wof:name":"The Gowrie (Qld) Inc",
    "wof:placetype":"venue"
},
  "geometry": {"coordinates":[153.029907227,-27.4575595856],"type":"Point"}
}