{
  "type": "Feature",
  "properties": {
    "addr:full":"1 Owen Stanley Rd Glenfield NSW 2167",
    "addr:housenumber":"1",
    "addr:postcode":"2167",
    "addr:street":"Owen Stanley Rd",
    "iso:country":"AU",
    "sg:address":"1 Owen Stanley Rd",
    "sg:city":"Glenfield",
    "sg:classifiers":[
        {
            "category":"Building & Trades",
            "subcategory":"Construction",
            "type":"Services"
        }
    ],
    "sg:phone":"+61 2 9618 5858",
    "sg:postcode":"2167",
    "sg:province":"NSW",
    "sg:tags":[
        "fencing",
        "contractor"
    ],
    "wof:name":"Australia's Best Fencing",
    "wof:placetype":"venue"
},
  "geometry": {"coordinates":[150.89848327600001,-33.9800491333],"type":"Point"}
}