{
  "type": "Feature",
  "properties": {
    "addr:full":"1/ 14 Brolo Crt O&#039;Connor WA 6163",
    "addr:housenumber":"/ 14",
    "addr:postcode":"6163",
    "addr:street":"Brolo Crt O &",
    "iso:country":"AU",
    "sg:address":"1/ 14 Brolo Crt",
    "sg:city":"O&#039;Connor",
    "sg:classifiers":[
        {
            "category":"Retail",
            "subcategory":"Auto Repair",
            "type":"Services"
        }
    ],
    "sg:phone":"+61 8 9331 3717",
    "sg:postcode":"6163",
    "sg:province":"WA",
    "sg:tags":[
        "body",
        "builder",
        "motor"
    ],
    "wof:name":"Outwest Equipment",
    "wof:placetype":"venue"
},
  "geometry": {"coordinates":[115.789497,-32.057903],"type":"Point"}
}