{
  "type": "Feature",
  "properties": {
    "addr:full":"4/ 14 Timms Crt Woodridge QLD 4114",
    "addr:housenumber":"/ 14",
    "addr:postcode":"4114",
    "addr:street":"Timms Crt",
    "iso:country":"AU",
    "sg:address":"4/ 14 Timms Crt",
    "sg:city":"Woodridge",
    "sg:classifiers":[
        {
            "category":"Autos & Motor Vehicles",
            "subcategory":"Auto Supplies",
            "type":"Retail Goods"
        }
    ],
    "sg:phone":"+61 7 3208 4821",
    "sg:postcode":"4114",
    "sg:province":"QLD",
    "sg:tags":[
        "part",
        "cycles",
        "accessory"
    ],
    "wof:name":"Taverner Motorcycles",
    "wof:placetype":"venue"
},
  "geometry": {"coordinates":[153.10700988799999,-27.620349884],"type":"Point"}
}