{
  "type": "Feature",
  "properties": {
    "addr:full":"Hays Rd Point Henry VIC 3221",
    "addr:postcode":"3221",
    "addr:street":"Hays Rd",
    "iso:country":"AU",
    "sg:address":"Hays Rd",
    "sg:city":"Point Henry",
    "sg:classifiers":[
        {
            "category":"Manufacturing",
            "subcategory":"Chemicals & Compounds",
            "type":"Manufacturing & Wholesale Goods"
        }
    ],
    "sg:phone":"+61 3 5227 6333",
    "sg:postcode":"3221",
    "sg:province":"VIC",
    "sg:tags":[
        "industrial"
    ],
    "wof:name":"Rohm & Haas Australia Pty Ltd",
    "wof:placetype":"venue"
},
  "geometry": {"coordinates":[144.432526,-38.156944],"type":"Point"}
}