{
  "type": "Feature",
  "properties": {
    "iso:country":"AU",
    "sg:address":"186 Kings Rd",
    "sg:city":"Mysterton",
    "sg:classifiers":[
        {
            "category":"Farming",
            "subcategory":"Farm & Veterinary Services",
            "type":"Manufacturing & Wholesale Goods"
        }
    ],
    "sg:phone":"+61 409 499 926",
    "sg:postcode":"4812",
    "sg:province":"QLD",
    "sg:tags":[
        "seedsman"
    ],
    "wof:name":"Syngenta Seeds P/L",
    "wof:placetype":"venue"
},
  "geometry": {"coordinates":[146.791077,-19.28684],"type":"Point"}
}