{
  "type": "Feature",
  "properties": {
    "iso:country":"AU",
    "sg:address":"61 Parker St",
    "sg:city":"Bega",
    "sg:classifiers":[
        {
            "category":"Health Services",
            "subcategory":"Health Practitioner",
            "type":"Services"
        }
    ],
    "sg:phone":"+61 2 6492 2222",
    "sg:postcode":"2550",
    "sg:province":"NSW",
    "sg:tags":[
        "naturopath"
    ],
    "wof:name":"Howard Trish ND BHSC. ATMS",
    "wof:placetype":"venue"
},
  "geometry": {"coordinates":[149.69696044899999,-36.7635612488],"type":"Point"}
}