{
  "type": "Feature",
  "properties": {
    "addr:full":"26 Giles St Kingston ACT 2604",
    "addr:housenumber":"26",
    "addr:postcode":"2604",
    "addr:street":"Giles St",
    "iso:country":"AU",
    "sg:address":"26 Giles St",
    "sg:city":"Kingston",
    "sg:classifiers":[
        {
            "category":"Real Estate",
            "subcategory":"Real Estate Agent",
            "type":"Services"
        }
    ],
    "sg:phone":"+61 2 6295 3211",
    "sg:postcode":"2604",
    "sg:province":"ACT",
    "wof:name":"Horizon Real Estate",
    "wof:placetype":"venue"
},
  "geometry": {"coordinates":[149.14015197800001,-35.3159751892],"type":"Point"}
}