{
  "type": "Feature",
  "properties": {
    "addr:full":"115 Ogilvie Ave Echuca VIC 3564",
    "addr:housenumber":"115",
    "addr:postcode":"3564",
    "addr:street":"Ogilvie Ave",
    "iso:country":"AU",
    "sg:address":"115 Ogilvie Ave",
    "sg:city":"Echuca",
    "sg:classifiers":[
        {
            "category":"Manufacturing",
            "subcategory":"Metals",
            "type":"Manufacturing & Wholesale Goods"
        }
    ],
    "sg:phone":"+61 3 5482 1420",
    "sg:postcode":"3564",
    "sg:province":"VIC",
    "sg:tags":[
        "sheet",
        "worker"
    ],
    "wof:name":"North Central Sheet Metal Fabrication",
    "wof:placetype":"venue"
},
  "geometry": {"coordinates":[144.74827575699999,-36.1404953003],"type":"Point"}
}