{
  "type": "Feature",
  "properties": {
    "iso:country":"AU",
    "sg:address":"86 Maitland St",
    "sg:city":"Bingara",
    "sg:classifiers":[
        {
            "category":"Professional",
            "subcategory":"Accounting & Tax Preparation",
            "type":"Services"
        }
    ],
    "sg:phone":"+61 2 6724 1305",
    "sg:postcode":"2404",
    "sg:province":"NSW",
    "sg:tags":[
        "consultant",
        "taxation"
    ],
    "wof:name":"Maltby Philip & Co",
    "wof:placetype":"venue"
},
  "geometry": {"coordinates":[150.57208251899999,-29.8697891235],"type":"Point"}
}