{
  "type": "Feature",
  "properties": {
    "iso:country":"AU",
    "sg:address":"5 Tubbs St",
    "sg:city":"Clontarf",
    "sg:classifiers":[
        {
            "category":"Manufacturing",
            "subcategory":"Glass & Minerals",
            "type":"Manufacturing & Wholesale Goods"
        }
    ],
    "sg:phone":"+61 7 3284 2488",
    "sg:postcode":"4019",
    "sg:province":"QLD",
    "sg:tags":[
        "repair",
        "fibreglass",
        "product"
    ],
    "wof:name":"Gremlin Fibreglass",
    "wof:placetype":"venue"
},
  "geometry": {"coordinates":[153.08233642600001,-27.2373008728],"type":"Point"}
}