{
  "type": "Feature",
  "properties": {
    "iso:country":"AU",
    "sg:address":"102 Ryrie St",
    "sg:city":"Geelong",
    "sg:classifiers":[
        {
            "category":"Shopping",
            "subcategory":"Crafts & Fabrics",
            "type":"Retail Goods"
        }
    ],
    "sg:phone":"+61 3 5221 0988",
    "sg:postcode":"3220",
    "sg:province":"VIC",
    "sg:tags":[
        "supply"
    ],
    "wof:name":"Bead Werks",
    "wof:placetype":"venue"
},
  "geometry": {"coordinates":[144.357681,-38.148869],"type":"Point"}
}