{
  "type": "Feature",
  "properties": {
    "addr:full":"PO Box 271 South West Rocks NSW 2431",
    "addr:postcode":"2431",
    "addr:street":"West",
    "iso:country":"AU",
    "sg:address":"PO Box 271",
    "sg:city":"South West Rocks",
    "sg:classifiers":[
        {
            "category":"Building & Trades",
            "subcategory":"Construction",
            "type":"Services"
        }
    ],
    "sg:phone":"+61 411 227 092",
    "sg:postcode":"2431",
    "sg:province":"NSW",
    "sg:tags":[
        "contractor"
    ],
    "wof:name":"James Lewis",
    "wof:placetype":"venue"
},
  "geometry": {"coordinates":[153.04188537600001,-30.8868503571],"type":"Point"}
}