{
  "type": "Feature",
  "properties": {
    "iso:country":"AU",
    "sg:address":"Gravesend St",
    "sg:city":"Colac",
    "sg:classifiers":[
        {
            "category":"Arena",
            "subcategory":"Sports Club",
            "type":"Entertainment"
        }
    ],
    "sg:phone":"+61 3 5231 5772",
    "sg:postcode":"3250",
    "sg:province":"VIC",
    "sg:tags":[
        "australian",
        "football",
        "rule"
    ],
    "wof:name":"Colac Football Club",
    "wof:placetype":"venue"
},
  "geometry": {"coordinates":[143.58552599999999,-38.344116],"type":"Point"}
}