{
  "type": "Feature",
  "properties": {
    "iso:country":"AU",
    "sg:address":"7 Hereford St",
    "sg:city":"Portarlington",
    "sg:classifiers":[
        {
            "category":"Professional",
            "subcategory":"Art Services",
            "type":"Services"
        }
    ],
    "sg:phone":"+61 3 5259 3693",
    "sg:postcode":"3223",
    "sg:province":"VIC",
    "sg:tags":[
        "artist"
    ],
    "wof:name":"Benz Simon",
    "wof:placetype":"venue"
},
  "geometry": {"coordinates":[144.636963,-38.118961],"type":"Point"}
}