{
  "type": "Feature",
  "properties": {
    "addr:full":"530 Jumbuk Rd Yinnar VIC 3869",
    "addr:housenumber":"530",
    "addr:postcode":"3869",
    "addr:street":"Jumbuk Rd",
    "iso:country":"AU",
    "sg:address":"530 Jumbuk Rd",
    "sg:city":"Yinnar",
    "sg:classifiers":[
        {
            "category":"Professional",
            "type":"Services"
        }
    ],
    "sg:phone":"+61 402 355 309",
    "sg:postcode":"3869",
    "sg:province":"VIC",
    "sg:tags":[
        "shop",
        "fitting"
    ],
    "wof:name":"Joe Didio Carpenter & Shopfitter",
    "wof:placetype":"venue"
},
  "geometry": {"coordinates":[146.366577148,-38.3452224731],"type":"Point"}
}