{
  "type": "Feature",
  "properties": {
    "iso:country":"AU",
    "sg:address":"Unit 1/ 8 Forge St",
    "sg:city":"Blacktown",
    "sg:classifiers":[
        {
            "category":"Shopping",
            "type":"Retail Goods"
        }
    ],
    "sg:phone":"+61 2 9671 5279",
    "sg:postcode":"2148",
    "sg:province":"NSW",
    "sg:tags":[
        "product",
        "plastic"
    ],
    "wof:name":"Lion Packaging",
    "wof:placetype":"venue"
},
  "geometry": {"coordinates":[150.90945434599999,-33.7564964294],"type":"Point"}
}