{
  "type": "Feature",
  "properties": {
    "addr:full":"1060 Betley Rd Dunolly VIC 3472",
    "addr:housenumber":"1060",
    "addr:postcode":"3472",
    "addr:street":"Betley Rd",
    "iso:country":"AU",
    "sg:address":"1060 Betley Rd",
    "sg:city":"Dunolly",
    "sg:classifiers":[
        {
            "category":"Home & Garden",
            "subcategory":"Building Materials",
            "type":"Retail Goods"
        }
    ],
    "sg:phone":"+61 3 5468 1766",
    "sg:postcode":"3472",
    "sg:province":"VIC",
    "sg:tags":[
        "secondhand"
    ],
    "wof:name":"Dunolly Demolition & Salvage Yard",
    "wof:placetype":"venue"
},
  "geometry": {"coordinates":[143.746490478,-36.8704414368],"type":"Point"}
}