{
  "type": "Feature",
  "properties": {
    "iso:country":"AU",
    "sg:address":"Unit 2/ 5 Wenban Pl",
    "sg:city":"Wetherill Park",
    "sg:classifiers":[
        {
            "category":"Manufacturing",
            "subcategory":"Rubber & Plastics",
            "type":"Manufacturing & Wholesale Goods"
        }
    ],
    "sg:phone":"+61 2 9757 3777",
    "sg:postcode":"2164",
    "sg:province":"NSW",
    "sg:tags":[
        "moulders"
    ],
    "wof:name":"Uniplas Mouldings International Pty Ltd",
    "wof:placetype":"venue"
},
  "geometry": {"coordinates":[150.904052734,-33.8378334045],"type":"Point"}
}