{
  "type": "Feature",
  "properties": {
    "addr:full":"77 Gladstone St Bellambi NSW 2518",
    "addr:housenumber":"77",
    "addr:postcode":"2518",
    "addr:street":"Gladstone St",
    "iso:country":"AU",
    "sg:address":"77 Gladstone St",
    "sg:city":"Bellambi",
    "sg:classifiers":[
        {
            "category":"Health Services",
            "subcategory":"Doctor",
            "type":"Services"
        }
    ],
    "sg:phone":"+61 2 4284 8922",
    "sg:postcode":"2518",
    "sg:province":"NSW",
    "sg:tags":[
        "medical",
        "practitioner"
    ],
    "wof:name":"Sokolovska Emilija",
    "wof:placetype":"venue"
},
  "geometry": {"coordinates":[150.91171299999999,-34.367893],"type":"Point"}
}