{
  "type": "Feature",
  "properties": {
    "addr:full":"10 Callaghan Drv Taranganba QLD 4703",
    "addr:housenumber":"10",
    "addr:postcode":"4703",
    "addr:street":"Callaghan Drv",
    "iso:country":"AU",
    "sg:address":"10 Callaghan Drv",
    "sg:city":"Taranganba",
    "sg:classifiers":[
        {
            "category":"Building & Trades",
            "subcategory":"Construction",
            "type":"Services"
        }
    ],
    "sg:phone":"+61 7 4939 4221",
    "sg:postcode":"4703",
    "sg:province":"QLD",
    "sg:tags":[
        "home",
        "air conditioning"
    ],
    "wof:name":"Precise Airconditoning Technologies",
    "wof:placetype":"venue"
},
  "geometry": {"coordinates":[150.75050354000001,-23.1462574005],"type":"Point"}
}