{
  "type": "Feature",
  "properties": {
    "iso:country":"AU",
    "sg:address":"9/ 401 Great Eastern Hwy",
    "sg:city":"Midland",
    "sg:classifiers":[
        {
            "category":"Autos & Motor Vehicles",
            "subcategory":"Auto Supplies",
            "type":"Retail Goods"
        }
    ],
    "sg:phone":"+61 8 9274 5900",
    "sg:postcode":"6056",
    "sg:province":"WA",
    "sg:tags":[
        "wheel",
        "four",
        "equipment",
        "drive",
        "accessory"
    ],
    "wof:name":"Midland Disposals Stores",
    "wof:placetype":"venue"
},
  "geometry": {"coordinates":[116.003479004,-31.8913936615],"type":"Point"}
}