{
  "type": "Feature",
  "properties": {
    "iso:country":"AU",
    "sg:address":"Heatherton Rd",
    "sg:city":"Noble Park",
    "sg:classifiers":[
        {
            "category":"Health Services",
            "subcategory":"Health Practitioner",
            "type":"Services"
        }
    ],
    "sg:phone":"+61 409 964 015",
    "sg:postcode":"3174",
    "sg:province":"VIC",
    "sg:tags":[
        "psychologist"
    ],
    "wof:name":"Diana Des",
    "wof:placetype":"venue"
},
  "geometry": {"coordinates":[145.18997192399999,-37.966960907],"type":"Point"}
}