{
  "type": "Feature",
  "properties": {
    "addr:full":"Level 9, Dymocks Building, 428 George Street Sydney NSW 2000",
    "addr:housenumber":"428",
    "addr:postcode":"2000",
    "addr:street":"George Street",
    "iso:country":"AU",
    "sg:address":"Level 9, Dymocks Building, 428 George Street",
    "sg:city":"Sydney",
    "sg:classifiers":[
        {
            "category":"Health Services",
            "subcategory":"Doctor",
            "type":"Services"
        }
    ],
    "sg:phone":"+61 2 9872 9499",
    "sg:postcode":"2000",
    "sg:province":"NSW",
    "sg:tags":[
        "nurse",
        "nursing"
    ],
    "wof:name":"Nursesearch",
    "wof:placetype":"venue"
},
  "geometry": {"coordinates":[151.207122803,-33.8700141907],"type":"Point"}
}