{
  "type": "Feature",
  "properties": {
    "iso:country":"AU",
    "sg:address":"Cnr O'Connell & Harold Sts",
    "sg:city":"North Parramatta",
    "sg:classifiers":[
        {
            "category":"Real Estate",
            "subcategory":"Architect",
            "type":"Services"
        }
    ],
    "sg:phone":"+61 2 9630 7811",
    "sg:postcode":"2151",
    "sg:province":"NSW",
    "sg:tags":[
        "building",
        "designer"
    ],
    "wof:name":"Orhan Kaba Design Pty Ltd",
    "wof:placetype":"venue"
},
  "geometry": {"coordinates":[151.00904846200001,-33.8049888611],"type":"Point"}
}