{
  "type": "Feature",
  "properties": {
    "addr:full":"413 Military Rd Largs Bay SA 5016",
    "addr:housenumber":"413",
    "addr:postcode":"5016",
    "addr:street":"Military Rd",
    "iso:country":"AU",
    "sg:address":"413 Military Rd",
    "sg:city":"Largs Bay",
    "sg:classifiers":[
        {
            "category":"Professional",
            "subcategory":"Printing & Photocopies",
            "type":"Services"
        }
    ],
    "sg:phone":"+61 8 8449 3842",
    "sg:postcode":"5016",
    "sg:province":"SA",
    "sg:tags":[
        "embroidery"
    ],
    "wof:name":"Dynamic Embroidery Design",
    "wof:placetype":"venue"
},
  "geometry": {"coordinates":[138.48828125,-34.82862854],"type":"Point"}
}