{
  "type": "Feature",
  "properties": {
    "iso:country":"AU",
    "sg:address":"31 Mt Leyshon Rd",
    "sg:city":"Mosman Park",
    "sg:classifiers":[
        {
            "category":"Building & Trades",
            "subcategory":"Construction",
            "type":"Services"
        }
    ],
    "sg:phone":"+61 7 4787 4410",
    "sg:postcode":"4820",
    "sg:province":"QLD",
    "sg:tags":[
        "window",
        "tinting"
    ],
    "wof:name":"D & A Rolfe Window Tinting",
    "wof:placetype":"venue"
},
  "geometry": {"coordinates":[146.261414,-20.091368],"type":"Point"}
}