{
  "type": "Feature",
  "properties": {
    "addr:full":"3821 Moggill Rd Moggill QLD 4070",
    "addr:housenumber":"3821",
    "addr:postcode":"4070",
    "addr:street":"Moggill Rd",
    "iso:country":"AU",
    "sg:address":"3821 Moggill Rd",
    "sg:city":"Moggill",
    "sg:classifiers":[
        {
            "category":"Home & Garden",
            "subcategory":"Building Materials",
            "type":"Retail Goods"
        }
    ],
    "sg:phone":"+61 7 3202 7674",
    "sg:postcode":"4070",
    "sg:province":"QLD",
    "sg:tags":[
        "lawn",
        "cutting",
        "maintenance"
    ],
    "wof:name":"Magnum Home Maintenance",
    "wof:placetype":"venue"
},
  "geometry": {"coordinates":[152.86051940900001,-27.5892620087],"type":"Point"}
}