{
  "type": "Feature",
  "properties": {
    "addr:full":"39 Elizabeth Bay Rd Elizabeth Bay NSW 2011",
    "addr:housenumber":"39",
    "addr:postcode":"2011",
    "addr:street":"Elizabeth Bay Rd",
    "iso:country":"AU",
    "sg:address":"39 Elizabeth Bay Rd",
    "sg:city":"Elizabeth Bay",
    "sg:classifiers":[
        {
            "category":"Insurance",
            "subcategory":"Insurance Agent",
            "type":"Services"
        }
    ],
    "sg:phone":"+61 2 9357 2968",
    "sg:postcode":"2011",
    "sg:province":"NSW",
    "wof:name":"Tresboy Pty Ltd",
    "wof:placetype":"venue"
},
  "geometry": {"coordinates":[151.22763061500001,-33.872127533],"type":"Point"}
}