{
  "type": "Feature",
  "properties": {
    "addr:full":"165 Muzzelwood Lodge St Thredbo Village NSW 2625",
    "addr:housenumber":"165",
    "addr:postcode":"2625",
    "addr:street":"Muzzelwood Lodge St",
    "iso:country":"AU",
    "sg:address":"165 Muzzelwood Lodge St",
    "sg:city":"Thredbo Village",
    "sg:classifiers":[
        {
            "category":"Health Services",
            "subcategory":"Doctor",
            "type":"Services"
        }
    ],
    "sg:phone":"+61 2 6457 6337",
    "sg:postcode":"2625",
    "sg:province":"NSW",
    "sg:tags":[
        "medical",
        "practitioner"
    ],
    "wof:name":"Diamond R A",
    "wof:placetype":"venue"
},
  "geometry": {"coordinates":[148.30847168,-36.5016517639],"type":"Point"}
}