{
  "type": "Feature",
  "properties": {
    "addr:full":"9/ 47 Musgrave Rd Coopers Plains QLD 4108",
    "addr:housenumber":"/ 47",
    "addr:postcode":"4108",
    "addr:street":"Musgrave Rd",
    "iso:country":"AU",
    "sg:address":"9/ 47 Musgrave Rd",
    "sg:city":"Coopers Plains",
    "sg:classifiers":[
        {
            "category":"Shopping",
            "subcategory":"Computers & Home Electronics",
            "type":"Retail Goods"
        }
    ],
    "sg:phone":"+61 7 3276 8383",
    "sg:postcode":"4108",
    "sg:province":"QLD",
    "sg:tags":[
        "equipment",
        "supply"
    ],
    "wof:name":"Tonertime",
    "wof:placetype":"venue"
},
  "geometry": {"coordinates":[153.02540588400001,-27.5612373352],"type":"Point"}
}