{
  "type": "Feature",
  "properties": {
    "addr:full":"24 Mayne St Murrurundi NSW 2338",
    "addr:housenumber":"24",
    "addr:postcode":"2338",
    "addr:street":"Mayne St",
    "iso:country":"AU",
    "sg:address":"24 Mayne St",
    "sg:city":"Murrurundi",
    "sg:classifiers":[
        {
            "category":"Government",
            "subcategory":"Fire Station",
            "type":"Public Place"
        }
    ],
    "sg:phone":"+61 2 6546 6019",
    "sg:postcode":"2338",
    "sg:province":"NSW",
    "sg:tags":[
        "brigade"
    ],
    "wof:name":"Fire Brigades-NSW",
    "wof:placetype":"venue"
},
  "geometry": {"coordinates":[150.831375122,-31.7615299225],"type":"Point"}
}