{
  "type": "Feature",
  "properties": {
    "addr:full":"Unit 2 2 Barnett Pl Molendinar QLD 4214",
    "addr:housenumber":"2",
    "addr:postcode":"4214",
    "addr:street":"Barnett Pl",
    "iso:country":"AU",
    "sg:address":"Unit 2 2 Barnett Pl",
    "sg:city":"Molendinar",
    "sg:classifiers":[
        {
            "category":"Retail",
            "subcategory":"Storage",
            "type":"Services"
        }
    ],
    "sg:phone":"+61 7 5552 2100",
    "sg:postcode":"4214",
    "sg:province":"QLD",
    "sg:tags":[
        "removal",
        "furniture"
    ],
    "sg:website":"http://www.movingagain.com.au",
    "wof:name":"Moving Again",
    "wof:placetype":"venue"
},
  "geometry": {"coordinates":[153.36128234899999,-27.9656276703],"type":"Point"}
}