{
  "type": "Feature",
  "properties": {
    "iso:country":"AU",
    "sg:address":"Shp4/ 204 Main South St",
    "sg:city":"Morphett Vale",
    "sg:classifiers":[
        {
            "category":"Fast Food",
            "type":"Food & Drink"
        }
    ],
    "sg:phone":"+61 8 8384 1455",
    "sg:postcode":"5162",
    "sg:province":"SA",
    "sg:tags":[
        "away",
        "take"
    ],
    "wof:name":"Morphett Vale Charcoal Chicken",
    "wof:placetype":"venue"
},
  "geometry": {"coordinates":[138.52333068900001,-35.1194038391],"type":"Point"}
}