{
  "type": "Feature",
  "properties": {
    "addr:full":"Byron Rd Marong VIC 3515",
    "addr:postcode":"3515",
    "addr:street":"Byron Rd",
    "iso:country":"AU",
    "sg:address":"Byron Rd",
    "sg:city":"Marong",
    "sg:classifiers":[
        {
            "category":"Home & Garden",
            "subcategory":"Building Materials",
            "type":"Retail Goods"
        }
    ],
    "sg:phone":"+61 3 5435 2453",
    "sg:postcode":"3515",
    "sg:province":"VIC",
    "sg:tags":[
        "balustrading"
    ],
    "wof:name":"Bill Grant Balustrading & Hand Rails",
    "wof:placetype":"venue"
},
  "geometry": {"coordinates":[144.14904799999999,-36.755699],"type":"Point"}
}