{
  "type": "Feature",
  "properties": {
    "addr:full":"PO Box 5430 Chatswood West Private Bxs NSW 1515",
    "addr:postcode":"1515",
    "addr:street":"West Private",
    "iso:country":"AU",
    "sg:address":"PO Box 5430",
    "sg:city":"Chatswood West Private Bxs",
    "sg:classifiers":[
        {
            "category":"Social Services",
            "subcategory":"Child Care",
            "type":"Services"
        }
    ],
    "sg:phone":"+61 413 268 300",
    "sg:postcode":"1515",
    "sg:province":"NSW",
    "sg:tags":[
        "support",
        "health"
    ],
    "wof:name":"4 Your Peace of Mind",
    "wof:placetype":"venue"
},
  "geometry": {"coordinates":[151.19012451200001,-33.7924385071],"type":"Point"}
}