{
  "type": "Feature",
  "properties": {
    "addr:full":"PO Box 1796 Bowral NSW 2576",
    "addr:postcode":"2576",
    "iso:country":"AU",
    "sg:address":"PO Box 1796",
    "sg:city":"Bowral",
    "sg:classifiers":[
        {
            "category":"Retail",
            "subcategory":"Auto Repair",
            "type":"Services"
        }
    ],
    "sg:phone":"+61 419 973 375",
    "sg:postcode":"2576",
    "sg:province":"NSW",
    "sg:tags":[
        "electrical"
    ],
    "wof:name":"D & M Auto Electrics",
    "wof:placetype":"venue"
},
  "geometry": {"coordinates":[150.385894775,-34.4550590515],"type":"Point"}
}