{
  "type": "Feature",
  "properties": {
    "iso:country":"AU",
    "sg:address":"Unit 1/ 5 Millrose Drv",
    "sg:city":"Malaga",
    "sg:classifiers":[
        {
            "category":"Shopping",
            "subcategory":"Stationery & Office Supplies",
            "type":"Retail Goods"
        }
    ],
    "sg:phone":"+61 8 9249 8799",
    "sg:postcode":"6090",
    "sg:province":"WA",
    "sg:tags":[
        "partition"
    ],
    "wof:name":"Scope Interiors",
    "wof:placetype":"venue"
},
  "geometry": {"coordinates":[115.89666748,-31.8645515442],"type":"Point"}
}