{
  "type": "Feature",
  "properties": {
    "addr:full":"571 Canterbury Rd Campsie NSW 2194",
    "addr:housenumber":"571",
    "addr:postcode":"2194",
    "addr:street":"Canterbury Rd",
    "iso:country":"AU",
    "sg:address":"571 Canterbury Rd",
    "sg:city":"Campsie",
    "sg:classifiers":[
        {
            "category":"Health Services",
            "subcategory":"Dentist",
            "type":"Services"
        }
    ],
    "sg:phone":"+61 2 9787 6611",
    "sg:postcode":"2194",
    "sg:province":"NSW",
    "wof:name":"Dang Dr P.N.Johnny",
    "wof:placetype":"venue"
},
  "geometry": {"coordinates":[151.099884,-33.919952],"type":"Point"}
}