{
  "type": "Feature",
  "properties": {
    "iso:country":"AU",
    "sg:address":"29 Downs St",
    "sg:city":"Brunswick",
    "sg:classifiers":[
        {
            "category":"Building & Trades",
            "subcategory":"Construction",
            "type":"Services"
        }
    ],
    "sg:phone":"+61 419 887 388",
    "sg:postcode":"3056",
    "sg:province":"VIC",
    "sg:tags":[
        "earth",
        "excavating",
        "moving",
        "contractor"
    ],
    "wof:name":"Nicopoulos Peter",
    "wof:placetype":"venue"
},
  "geometry": {"coordinates":[144.955154419,-37.7568321228],"type":"Point"}
}