{
  "type": "Feature",
  "properties": {
    "addr:full":"Unit 4/ 18 Biscayne Way Jandakot WA 6164",
    "addr:housenumber":"18",
    "addr:postcode":"6164",
    "addr:street":"Biscayne Way",
    "iso:country":"AU",
    "sg:address":"Unit 4/ 18",
    "sg:city":"Biscayne Way Jandakot",
    "sg:classifiers":[
        {
            "category":"Sports & Exercise",
            "subcategory":"Gym",
            "type":"Entertainment"
        }
    ],
    "sg:phone":"+61 417 945 455",
    "sg:postcode":"6164",
    "sg:province":"WA",
    "sg:tags":[
        "health",
        "fitness"
    ],
    "wof:name":"Onyx Fitness",
    "wof:placetype":"venue"
},
  "geometry": {"coordinates":[115.87233000000001,-32.121716],"type":"Point"}
}