{
  "type": "Feature",
  "properties": {
    "addr:full":"Unit 1/20- 30 Malcolm Rd Braeside VIC 3195",
    "addr:housenumber":"30",
    "addr:postcode":"3195",
    "addr:street":"Malcolm Rd",
    "iso:country":"AU",
    "sg:address":"Unit 1/20- 30 Malcolm Rd",
    "sg:city":"Braeside",
    "sg:classifiers":[
        {
            "category":"Banks & Credit Unions",
            "subcategory":"Bureau De Change",
            "type":"Services"
        }
    ],
    "sg:phone":"+61 3 9580 5677",
    "sg:postcode":"3195",
    "sg:province":"VIC",
    "sg:tags":[
        "supply",
        "equipment",
        "beating",
        "panel"
    ],
    "wof:name":"Car Bench Australia Pty Ltd",
    "wof:placetype":"venue"
},
  "geometry": {"coordinates":[145.10794067399999,-38.0007171631],"type":"Point"}
}