{
  "type": "Feature",
  "properties": {
    "addr:full":"2b McArthur St Dromana VIC 3936",
    "addr:housenumber":"2b",
    "addr:postcode":"3936",
    "addr:street":"Mcarthur St",
    "iso:country":"AU",
    "sg:address":"2b McArthur St",
    "sg:city":"Dromana",
    "sg:classifiers":[
        {
            "category":"Professional",
            "subcategory":"Business Services",
            "type":"Services"
        }
    ],
    "sg:phone":"+61 3 5981 9301",
    "sg:postcode":"3936",
    "sg:province":"VIC",
    "sg:tags":[
        "drafting"
    ],
    "wof:name":"Bill Arnel",
    "wof:placetype":"venue"
},
  "geometry": {"coordinates":[144.954421997,-38.3402328491],"type":"Point"}
}