{
  "type": "Feature",
  "properties": {
    "addr:full":"Shed 3 Low St Eumundi QLD 4562",
    "addr:housenumber":"3",
    "addr:postcode":"4562",
    "addr:street":"Low St",
    "iso:country":"AU",
    "sg:address":"Shed 3 Low St",
    "sg:city":"Eumundi",
    "sg:classifiers":[
        {
            "category":"Professional",
            "subcategory":"Art Services",
            "type":"Services"
        }
    ],
    "sg:phone":"+61 7 5442 7776",
    "sg:postcode":"4562",
    "sg:province":"QLD",
    "sg:tags":[
        "work",
        "metal"
    ],
    "wof:name":"Iron Creations",
    "wof:placetype":"venue"
},
  "geometry": {"coordinates":[152.95298767099999,-26.4813213348],"type":"Point"}
}