{
  "type": "Feature",
  "properties": {
    "addr:full":"Factory 4 45- 49 Popes Rd Keysborough VIC 3173",
    "addr:housenumber":"45 49",
    "addr:postcode":"3173",
    "addr:street":"Popes Rd",
    "iso:country":"AU",
    "sg:address":"Factory 4 45- 49 Popes Rd",
    "sg:city":"Keysborough",
    "sg:classifiers":[
        {
            "category":"Professional",
            "type":"Services"
        }
    ],
    "sg:phone":"+61 3 9701 5770",
    "sg:postcode":"3173",
    "sg:province":"VIC",
    "sg:tags":[
        "spray",
        "painting"
    ],
    "wof:name":"AAA Cabinet Coatings",
    "wof:placetype":"venue"
},
  "geometry": {"coordinates":[145.19023132300001,-37.9826583862],"type":"Point"}
}