{
  "type": "Feature",
  "properties": {
    "addr:full":"3 Frederick St Morisset NSW 2264",
    "addr:housenumber":"3",
    "addr:postcode":"2264",
    "addr:street":"Frederick St",
    "iso:country":"AU",
    "sg:address":"3 Frederick St",
    "sg:city":"Morisset",
    "sg:classifiers":[
        {
            "category":"Personal",
            "subcategory":"Massage",
            "type":"Services"
        }
    ],
    "sg:phone":"+61 414 764 217",
    "sg:postcode":"2264",
    "sg:province":"NSW",
    "sg:tags":[
        "therapy"
    ],
    "wof:name":"Laucht Paula",
    "wof:placetype":"venue"
},
  "geometry": {"coordinates":[151.53001399999999,-33.117657],"type":"Point"}
}