{
  "type": "Feature",
  "properties": {
    "addr:full":"76 Station St Somerville VIC 3912",
    "addr:housenumber":"76",
    "addr:postcode":"3912",
    "addr:street":"Station St",
    "iso:country":"AU",
    "sg:address":"76 Station St",
    "sg:city":"Somerville",
    "sg:classifiers":[
        {
            "category":"Food & Beverages",
            "subcategory":"Groceries & Convenience Stores",
            "type":"Retail Goods"
        }
    ],
    "sg:phone":"+61 3 5977 5223",
    "sg:postcode":"3912",
    "sg:province":"VIC",
    "wof:name":"S Hassan",
    "wof:placetype":"venue"
},
  "geometry": {"coordinates":[145.175094605,-38.2249565125],"type":"Point"}
}