{
  "type": "Feature",
  "properties": {
    "iso:country":"AU",
    "sg:address":"1251 Bellarine Hwy",
    "sg:city":"Geelong",
    "sg:classifiers":[
        {
            "category":"Communications",
            "subcategory":"News Services",
            "type":"Services"
        }
    ],
    "sg:phone":"+61 3 5250 2756",
    "sg:postcode":"3220",
    "sg:province":"VIC",
    "sg:tags":[
        "information",
        "tourist",
        "attractions"
    ],
    "wof:name":"Adventure Park",
    "wof:placetype":"venue"
},
  "geometry": {"coordinates":[144.361938,-38.156956],"type":"Point"}
}