{
  "type": "Feature",
  "properties": {
    "addr:full":"Shop 21, Lesmurdie Village Shopng Cntr Sanderson Rd Lesmurdie WA 6076",
    "addr:housenumber":"shop 21",
    "addr:postcode":"6076",
    "addr:street":"Rd",
    "iso:country":"AU",
    "sg:address":"Shop 21, Lesmurdie Village Shopng Cntr Sanderson Rd",
    "sg:city":"Lesmurdie",
    "sg:classifiers":[
        {
            "category":"Retail",
            "subcategory":"Veterinary Services",
            "type":"Services"
        }
    ],
    "sg:phone":"+61 8 9291 0126",
    "sg:postcode":"6076",
    "sg:province":"WA",
    "sg:tags":[
        "surgeon"
    ],
    "wof:name":"Lesmurdie Veterinary Clinic",
    "wof:placetype":"venue"
},
  "geometry": {"coordinates":[116.046150208,-32.0097351074],"type":"Point"}
}