{
  "type": "Feature",
  "properties": {
    "addr:full":"12/30- 32 Old Pacific Hwy Yatala QLD 4207",
    "addr:housenumber":"12 / 30 32",
    "addr:postcode":"4207",
    "addr:street":"Old Pacific Hwy",
    "iso:country":"AU",
    "sg:address":"12/30- 32 Old Pacific Hwy",
    "sg:city":"Yatala",
    "sg:classifiers":[
        {
            "category":"Professional",
            "subcategory":"Art Services",
            "type":"Services"
        }
    ],
    "sg:phone":"+61 7 3807 4822",
    "sg:postcode":"4207",
    "sg:province":"QLD",
    "sg:tags":[
        "interior",
        "decorator"
    ],
    "wof:name":"Rowe Fabrics",
    "wof:placetype":"venue"
},
  "geometry": {"coordinates":[153.22416687,-27.733423233],"type":"Point"}
}