{
  "type": "Feature",
  "properties": {
    "iso:country":"AU",
    "sg:address":"18 Wood St",
    "sg:city":"Bassendean",
    "sg:classifiers":[
        {
            "category":"Retail",
            "subcategory":"Repair Shop",
            "type":"Services"
        }
    ],
    "sg:phone":"+61 8 9378 3111",
    "sg:postcode":"6054",
    "sg:province":"WA",
    "sg:tags":[
        "leadlights"
    ],
    "wof:name":"Statewide Salvage",
    "wof:placetype":"venue"
},
  "geometry": {"coordinates":[115.93470764200001,-31.9118347168],"type":"Point"}
}