{
  "type": "Feature",
  "properties": {
    "addr:full":"19 Tern La Busselton WA 6280",
    "addr:housenumber":"19",
    "addr:postcode":"6280",
    "addr:street":"Tern La",
    "iso:country":"AU",
    "sg:address":"19 Tern La",
    "sg:city":"Busselton",
    "sg:classifiers":[
        {
            "category":"Building & Trades",
            "subcategory":"Cleaning & Sanitation",
            "type":"Services"
        }
    ],
    "sg:phone":"+61 8 9752 3945",
    "sg:postcode":"6280",
    "sg:province":"WA",
    "sg:tags":[
        "window"
    ],
    "wof:name":"Bay Cleaning Services",
    "wof:placetype":"venue"
},
  "geometry": {"coordinates":[115.291748047,-33.6643066406],"type":"Point"}
}