{
  "type": "Feature",
  "properties": {
    "addr:full":"29 McDougall St Milton QLD 4064",
    "addr:housenumber":"29",
    "addr:postcode":"4064",
    "addr:street":"Mcdougall St",
    "iso:country":"AU",
    "sg:address":"29 McDougall St",
    "sg:city":"Milton",
    "sg:classifiers":[
        {
            "category":"Building & Trades",
            "subcategory":"Landscaping Services",
            "type":"Services"
        }
    ],
    "sg:phone":"+61 7 3360 1444",
    "sg:postcode":"4064",
    "sg:province":"QLD",
    "sg:tags":[
        "consultant"
    ],
    "wof:name":"Pioneer Homes Australia",
    "wof:placetype":"venue"
},
  "geometry": {"coordinates":[153.00672912600001,-27.4705104828],"type":"Point"}
}