{
  "type": "Feature",
  "properties": {
    "addr:full":"Lvl 1 Ste 107, 37- 39 The Corso Manly NSW 2095",
    "addr:housenumber":"39",
    "addr:postcode":"2095",
    "addr:street":"37;Corso",
    "iso:country":"AU",
    "sg:address":"Lvl 1 Ste 107, 37- 39",
    "sg:city":"The Corso Manly",
    "sg:classifiers":[
        {
            "category":"Banks & Credit Unions",
            "subcategory":"Financial Services",
            "type":"Services"
        }
    ],
    "sg:phone":"+61 2 9977 8800",
    "sg:postcode":"2095",
    "sg:province":"NSW",
    "sg:tags":[
        "planning"
    ],
    "wof:name":"Genesys Wealth Advisers",
    "wof:placetype":"venue"
},
  "geometry": {"coordinates":[151.286575317,-33.7978630066],"type":"Point"}
}