{
  "type": "Feature",
  "properties": {
    "addr:full":"69 Hargreaves Drv Taree NSW 2430",
    "addr:housenumber":"69",
    "addr:postcode":"2430",
    "addr:street":"Hargreaves Drv",
    "iso:country":"AU",
    "sg:address":"69 Hargreaves Drv",
    "sg:city":"Taree",
    "sg:classifiers":[
        {
            "category":"Professional",
            "type":"Services"
        }
    ],
    "sg:phone":"+61 2 6552 6555",
    "sg:postcode":"2430",
    "sg:province":"NSW",
    "sg:tags":[
        "shop",
        "fitting"
    ],
    "wof:name":"RSF Commercial Interiors Pty Limited",
    "wof:placetype":"venue"
},
  "geometry": {"coordinates":[152.42198181099999,-31.8822364807],"type":"Point"}
}