{
  "type": "Feature",
  "properties": {
    "addr:full":"618 Old Cleveland Rd Camp Hill QLD 4152",
    "addr:housenumber":"618",
    "addr:postcode":"4152",
    "addr:street":"Old Cleveland Rd",
    "iso:country":"AU",
    "sg:address":"618 Old Cleveland Rd",
    "sg:city":"Camp Hill",
    "sg:classifiers":[
        {
            "category":"Professional",
            "subcategory":"Business Services",
            "type":"Services"
        }
    ],
    "sg:phone":"+61 7 3398 1223",
    "sg:postcode":"4152",
    "sg:province":"QLD",
    "sg:tags":[
        "broker"
    ],
    "wof:name":"Home & Business Brokers",
    "wof:placetype":"venue"
},
  "geometry": {"coordinates":[153.075317383,-27.4926395416],"type":"Point"}
}