{
  "type": "Feature",
  "properties": {
    "addr:full":"Unit 1/ 2 Industrial Ave Wacol QLD 4076",
    "addr:housenumber":"2",
    "addr:postcode":"4076",
    "addr:street":"Industrial Ave",
    "iso:country":"AU",
    "sg:address":"Unit 1/ 2 Industrial Ave",
    "sg:city":"Wacol",
    "sg:classifiers":[
        {
            "category":"Retail",
            "subcategory":"Auto Repair",
            "type":"Services"
        }
    ],
    "sg:phone":"+61 7 3271 5044",
    "sg:postcode":"4076",
    "sg:province":"QLD",
    "sg:tags":[
        "clutch",
        "brake"
    ],
    "wof:name":"Wacol Muffler & Brake Shop",
    "wof:placetype":"venue"
},
  "geometry": {"coordinates":[152.92999267600001,-27.5909900665],"type":"Point"}
}