{
  "type": "Feature",
  "properties": {
    "addr:full":"19 Attunga Rd Blaxland NSW 2774",
    "addr:housenumber":"19",
    "addr:postcode":"2774",
    "addr:street":"Attunga Rd",
    "iso:country":"AU",
    "sg:address":"19 Attunga Rd",
    "sg:city":"Blaxland",
    "sg:classifiers":[
        {
            "category":"Retail",
            "subcategory":"Auto Repair",
            "type":"Services"
        }
    ],
    "sg:phone":"+61 2 4739 1006",
    "sg:postcode":"2774",
    "sg:province":"NSW",
    "sg:tags":[
        "repairer",
        "motor",
        "engineer"
    ],
    "wof:name":"Mountain Autos",
    "wof:placetype":"venue"
},
  "geometry": {"coordinates":[150.61004638700001,-33.736946106],"type":"Point"}
}