{
  "type": "Feature",
  "properties": {
    "iso:country":"AU",
    "sg:address":"Unit 3/ 60 McMinn St",
    "sg:city":"Darwin",
    "sg:classifiers":[
        {
            "category":"Shopping",
            "subcategory":"Computers & Home Electronics",
            "type":"Retail Goods"
        }
    ],
    "sg:phone":"+61 8 8981 9111",
    "sg:postcode":"0800",
    "sg:province":"NT",
    "sg:tags":[
        "small",
        "equipment",
        "business"
    ],
    "wof:name":"Hallmark Computer Int. (NT) Pty Ltd",
    "wof:placetype":"venue"
},
  "geometry": {"coordinates":[130.841705322,-12.4563655853],"type":"Point"}
}