{
  "type": "Feature",
  "properties": {
    "iso:country":"AU",
    "sg:address":"1 Susan St",
    "sg:city":"Auburn",
    "sg:classifiers":[
        {
            "category":"Government",
            "subcategory":"Department Of Motor Vehicles",
            "type":"Public Place"
        }
    ],
    "sg:phone":"+61 2 9735 1222",
    "sg:postcode":"2144",
    "sg:province":"NSW",
    "sg:tags":[
        "organisation",
        "local"
    ],
    "wof:name":"Auburn Council",
    "wof:placetype":"venue"
},
  "geometry": {"coordinates":[151.03364563,-33.8530693054],"type":"Point"}
}