{
  "type": "Feature",
  "properties": {
    "addr:full":"Fcty 3/ 30 Bridge St Eltham VIC 3095",
    "addr:housenumber":"/ 30",
    "addr:postcode":"3095",
    "addr:street":"Bridge St",
    "iso:country":"AU",
    "sg:address":"Fcty 3/ 30 Bridge St",
    "sg:city":"Eltham",
    "sg:classifiers":[
        {
            "category":"Manufacturing",
            "subcategory":"Metals",
            "type":"Manufacturing & Wholesale Goods"
        }
    ],
    "sg:phone":"+61 3 9464 6880",
    "sg:postcode":"3095",
    "sg:province":"VIC",
    "sg:tags":[
        "steel",
        "fabricator",
        "mfrs"
    ],
    "wof:name":"Super Steel Lattice",
    "wof:placetype":"venue"
},
  "geometry": {"coordinates":[145.14073181099999,-37.7184677124],"type":"Point"}
}