{
  "type": "Feature",
  "properties": {
    "addr:full":"16-22 York St Airport West VIC 3042",
    "addr:housenumber":"16-22",
    "addr:postcode":"3042",
    "addr:street":"York St",
    "iso:country":"AU",
    "sg:address":"16-22 York St",
    "sg:city":"Airport West",
    "sg:classifiers":[
        {
            "category":"Wholesale",
            "subcategory":"Furniture",
            "type":"Manufacturing & Wholesale Goods"
        }
    ],
    "sg:phone":"+61 3 9338 7003",
    "sg:postcode":"3042",
    "sg:province":"VIC",
    "sg:tags":[
        "wholesaler",
        "mfrs"
    ],
    "wof:name":"Munro Furniture Pty Ltd",
    "wof:placetype":"venue"
},
  "geometry": {"coordinates":[144.88900756800001,-37.7262687683],"type":"Point"}
}