{
  "type": "Feature",
  "properties": {
    "addr:full":"Level 10, 66 Hunter St Sydney NSW 2000",
    "addr:housenumber":"66",
    "addr:postcode":"2000",
    "addr:street":"Hunter St",
    "iso:country":"AU",
    "sg:address":"Level 10, 66 Hunter St",
    "sg:city":"Sydney",
    "sg:classifiers":[
        {
            "category":"Structure",
            "subcategory":"Office Building",
            "type":"Public Place"
        }
    ],
    "sg:phone":"+61 1300 555 220",
    "sg:postcode":"2000",
    "sg:province":"NSW",
    "sg:tags":[
        "serviced"
    ],
    "wof:name":"Business Executive Suites (Hunter Street)",
    "wof:placetype":"venue"
},
  "geometry": {"coordinates":[151.210281372,-33.8661270142],"type":"Point"}
}