{
  "type": "Feature",
  "properties": {
    "addr:full":"163 Byrnes St Mareeba QLD 4880",
    "addr:housenumber":"163",
    "addr:postcode":"4880",
    "addr:street":"Byrnes St",
    "iso:country":"AU",
    "sg:address":"163 Byrnes St",
    "sg:city":"Mareeba",
    "sg:classifiers":[
        {
            "category":"Real Estate",
            "subcategory":"Real Estate Agent",
            "type":"Services"
        }
    ],
    "sg:phone":"+61 7 4092 5255",
    "sg:postcode":"4880",
    "sg:province":"QLD",
    "wof:name":"Rogato Bros",
    "wof:placetype":"venue"
},
  "geometry": {"coordinates":[145.42015075699999,-16.985824585],"type":"Point"}
}