{
  "type": "Feature",
  "properties": {
    "iso:country":"AU",
    "sg:address":"26 Dytes Pde",
    "sg:city":"Ballarat",
    "sg:classifiers":[
        {
            "category":"Shopping",
            "subcategory":"Computers & Home Electronics",
            "type":"Retail Goods"
        }
    ],
    "sg:phone":"+61 3 5331 2862",
    "sg:postcode":"3350",
    "sg:province":"VIC",
    "sg:tags":[
        "wholesaler",
        "mfrs",
        "part",
        "electronic"
    ],
    "wof:name":"Dynamic Rentals Pty Ltd",
    "wof:placetype":"venue"
},
  "geometry": {"coordinates":[143.87489299999999,-37.559448],"type":"Point"}
}