{
  "type": "Feature",
  "properties": {
    "addr:full":"7 10 A Gillies St Wollstonecraft NSW 2065",
    "addr:housenumber":"10 a",
    "addr:postcode":"2065",
    "addr:street":"7;Gillies St",
    "iso:country":"AU",
    "sg:address":"7 10 A Gillies St",
    "sg:city":"Wollstonecraft",
    "sg:classifiers":[
        {
            "category":"Food & Beverages",
            "subcategory":"Liquor & Beverages",
            "type":"Retail Goods"
        }
    ],
    "sg:phone":"+61 2 9957 4825",
    "sg:postcode":"2065",
    "sg:province":"NSW",
    "sg:tags":[
        "store"
    ],
    "wof:name":"Unreal Imports Pty Ltd",
    "wof:placetype":"venue"
},
  "geometry": {"coordinates":[151.198852539,-33.8299179077],"type":"Point"}
}