{
  "type": "Feature",
  "properties": {
    "iso:country":"AU",
    "sg:address":"1920 Main Drain Rd",
    "sg:city":"Garfield",
    "sg:classifiers":[
        {
            "category":"Farming",
            "subcategory":"Farm",
            "type":"Manufacturing & Wholesale Goods"
        }
    ],
    "sg:phone":"+61 3 5629 2256",
    "sg:postcode":"3814",
    "sg:province":"VIC",
    "sg:tags":[
        "farmer"
    ],
    "wof:name":"Scamporlino G & N",
    "wof:placetype":"venue"
},
  "geometry": {"coordinates":[145.672775,-38.131157],"type":"Point"}
}