{
  "type": "Feature",
  "properties": {
    "iso:country":"AU",
    "sg:address":"90 Mossiface Rd",
    "sg:city":"Swan Reach",
    "sg:classifiers":[
        {
            "category":"Building & Trades",
            "subcategory":"Construction",
            "type":"Services"
        }
    ],
    "sg:phone":"+61 3 5156 4422",
    "sg:postcode":"3903",
    "sg:province":"VIC",
    "sg:tags":[
        "contractor"
    ],
    "wof:name":"Chapman Designer Homes",
    "wof:placetype":"venue"
},
  "geometry": {"coordinates":[147.87039184599999,-37.815448761],"type":"Point"}
}