{
  "type": "Feature",
  "properties": {
    "addr:full":"24 Keera Crt Maddington WA 6109",
    "addr:housenumber":"24",
    "addr:postcode":"6109",
    "addr:street":"Keera Crt",
    "iso:country":"AU",
    "sg:address":"24 Keera Crt",
    "sg:city":"Maddington",
    "sg:classifiers":[
        {
            "category":"Building & Trades",
            "subcategory":"Construction",
            "type":"Services"
        }
    ],
    "sg:phone":"+61 8 9459 6566",
    "sg:postcode":"6109",
    "sg:province":"WA",
    "sg:tags":[
        "window",
        "aluminium"
    ],
    "wof:name":"Cunningham S B & Co",
    "wof:placetype":"venue"
},
  "geometry": {"coordinates":[115.99102020300001,-32.0444450378],"type":"Point"}
}