{
  "type": "Feature",
  "properties": {
    "addr:full":"Cnr Lathlain & Wales Sts Belconnen ACT 2617",
    "addr:postcode":"2617",
    "addr:street":"Cnr",
    "iso:country":"AU",
    "sg:address":"Cnr Lathlain & Wales Sts",
    "sg:city":"Belconnen",
    "sg:classifiers":[
        {
            "category":"Health Services",
            "subcategory":"Dentist",
            "type":"Services"
        }
    ],
    "sg:phone":"+61 2 6251 4846",
    "sg:postcode":"2617",
    "sg:province":"ACT",
    "wof:name":"Tin Stephen",
    "wof:placetype":"venue"
},
  "geometry": {"coordinates":[149.063552856,-35.2397499084],"type":"Point"}
}