{
  "type": "Feature",
  "properties": {
    "addr:full":"11 Stuart Ave Hampton Park VIC 3976",
    "addr:housenumber":"11",
    "addr:postcode":"3976",
    "addr:street":"Stuart Ave Hampton",
    "iso:country":"AU",
    "sg:address":"11 Stuart Ave",
    "sg:city":"Hampton Park",
    "sg:classifiers":[
        {
            "category":"Health Services",
            "subcategory":"Health Practitioner",
            "type":"Services"
        }
    ],
    "sg:phone":"+61 3 9799 1333",
    "sg:postcode":"3976",
    "sg:province":"VIC",
    "sg:tags":[
        "physiotherapist"
    ],
    "wof:name":"Arslan Yasemin",
    "wof:placetype":"venue"
},
  "geometry": {"coordinates":[145.26385498100001,-38.0330123901],"type":"Point"}
}