{
  "type": "Feature",
  "properties": {
    "addr:full":"173 Scott St Bungalow QLD 4870",
    "addr:housenumber":"173",
    "addr:postcode":"4870",
    "addr:street":"Scott St",
    "iso:country":"AU",
    "sg:address":"173 Scott St",
    "sg:city":"Bungalow",
    "sg:classifiers":[
        {
            "category":"Autos & Motor Vehicles",
            "subcategory":"Auto Supplies",
            "type":"Retail Goods"
        }
    ],
    "sg:phone":"+61 7 4051 4105",
    "sg:postcode":"4870",
    "sg:province":"QLD",
    "sg:tags":[
        "accessory"
    ],
    "wof:name":"Global 4x4 Accessories",
    "wof:placetype":"venue"
},
  "geometry": {"coordinates":[145.75462341299999,-16.9384784698],"type":"Point"}
}