{
  "type": "Feature",
  "properties": {
    "iso:country":"AU",
    "sg:address":"4 Norwood Crt",
    "sg:city":"Yatala",
    "sg:classifiers":[
        {
            "category":"Bars & Pubs",
            "subcategory":"Lounge",
            "type":"Food & Drink"
        }
    ],
    "sg:phone":"+61 7 3287 5226",
    "sg:postcode":"4207",
    "sg:province":"QLD",
    "sg:tags":[
        "water",
        "filter",
        "drinking"
    ],
    "wof:name":"Water Magic",
    "wof:placetype":"venue"
},
  "geometry": {"coordinates":[153.207641602,-27.7566127777],"type":"Point"}
}