{
  "type": "Feature",
  "properties": {
    "iso:country":"AU",
    "sg:address":"16- 18 Ryrie St",
    "sg:city":"Geelong",
    "sg:classifiers":[
        {
            "category":"Shopping",
            "subcategory":"Antiques",
            "type":"Retail Goods"
        }
    ],
    "sg:phone":"+61 3 5229 2970",
    "sg:postcode":"3220",
    "sg:province":"VIC",
    "wof:name":"Rosenberg John",
    "wof:placetype":"venue"
},
  "geometry": {"coordinates":[144.353683,-38.147766],"type":"Point"}
}