{
  "type": "Feature",
  "properties": {
    "addr:full":"Unit 1, 12 Canham Way Greenwood WA 6024",
    "addr:housenumber":"12",
    "addr:postcode":"6024",
    "addr:street":"Canham Way",
    "iso:country":"AU",
    "sg:address":"Unit 1, 12 Canham Way",
    "sg:city":"Greenwood",
    "sg:classifiers":[
        {
            "category":"Professional",
            "subcategory":"Detective & Security Services",
            "type":"Services"
        }
    ],
    "sg:phone":"+61 8 9343 1666",
    "sg:postcode":"6024",
    "sg:province":"WA",
    "sg:tags":[
        "equipment",
        "window",
        "doors"
    ],
    "wof:name":"Louie's Flyscreens Allsafe",
    "wof:placetype":"venue"
},
  "geometry": {"coordinates":[115.81738281200001,-31.8213233948],"type":"Point"}
}