{
  "type": "Feature",
  "properties": {
    "iso:country":"AU",
    "sg:address":"38 Waterside Drv",
    "sg:city":"Mandurah",
    "sg:classifiers":[
        {
            "category":"Recreation",
            "subcategory":"Boat Charter",
            "type":"Entertainment"
        }
    ],
    "sg:phone":"+61 8 9535 1177",
    "sg:postcode":"6210",
    "sg:province":"WA",
    "sg:tags":[
        "hire",
        "drive"
    ],
    "wof:name":"Murray River Houseboats",
    "wof:placetype":"venue"
},
  "geometry": {"coordinates":[115.72268699999999,-32.548725],"type":"Point"}
}