{
  "type": "Feature",
  "properties": {
    "iso:country":"AU",
    "sg:address":"343 Cleveland-Redland Bay Rd",
    "sg:city":"Thornlands",
    "sg:classifiers":[
        {
            "category":"Travel",
            "subcategory":"Hostel",
            "type":"Entertainment"
        }
    ],
    "sg:phone":"+61 7 3207 8100",
    "sg:postcode":"4164",
    "sg:province":"QLD",
    "sg:tags":[
        "home"
    ],
    "wof:name":"Finlandia Village",
    "wof:placetype":"venue"
},
  "geometry": {"coordinates":[153.279205322,-27.5758914948],"type":"Point"}
}