{
  "type": "Feature",
  "properties": {
    "addr:full":"PO Box 213 Katherine NT 0851",
    "addr:postcode":"nt 0851",
    "iso:country":"AU",
    "sg:address":"PO Box 213",
    "sg:city":"Katherine",
    "sg:classifiers":[
        {
            "category":"Building & Trades",
            "subcategory":"Construction",
            "type":"Services"
        }
    ],
    "sg:phone":"+61 417 168 954",
    "sg:postcode":"0851",
    "sg:province":"NT",
    "sg:tags":[
        "fencing",
        "contractor"
    ],
    "wof:name":"Jesky Fencing & Contracting",
    "wof:placetype":"venue"
},
  "geometry": {"coordinates":[132.26362599999999,-14.46575],"type":"Point"}
}