{
  "type": "Feature",
  "properties": {
    "addr:full":"Shop 25 Sefton Plaza Shopping Centre Sefton Park SA 5083",
    "addr:housenumber":"shop 25",
    "addr:postcode":"5083",
    "addr:street":"Sefton",
    "iso:country":"AU",
    "sg:address":"Shop 25 Sefton Plaza Shopping Centre",
    "sg:city":"Sefton Park",
    "sg:classifiers":[
        {
            "category":"Shopping",
            "subcategory":"Clothing, Apparel, & Fashions",
            "type":"Retail Goods"
        }
    ],
    "sg:phone":"+61 8 8269 4443",
    "sg:postcode":"5083",
    "sg:province":"SA",
    "sg:tags":[
        "jean"
    ],
    "wof:name":"Just Jeans",
    "wof:placetype":"venue"
},
  "geometry": {"coordinates":[138.60601806599999,-34.8765296936],"type":"Point"}
}