{
  "type": "Feature",
  "properties": {
    "iso:country":"AU",
    "sg:address":"12 Gordon St",
    "sg:city":"Port Macquarie",
    "sg:classifiers":[
        {
            "category":"Travel",
            "subcategory":"Hotels & Motels",
            "type":"Entertainment"
        }
    ],
    "sg:phone":"+61 2 6583 8899",
    "sg:postcode":"2444",
    "sg:province":"NSW",
    "wof:name":"Town Beach Motor Inn",
    "wof:placetype":"venue"
},
  "geometry": {"coordinates":[152.91426100000001,-31.433132],"type":"Point"}
}