{
  "type": "Feature",
  "properties": {
    "iso:country":"AU",
    "sg:address":"Shop 1, 39 Peel St",
    "sg:city":"(North) Ballarat",
    "sg:classifiers":[
        {
            "category":"Building & Trades",
            "subcategory":"Construction",
            "type":"Services"
        }
    ],
    "sg:phone":"+61 3 5332 8699",
    "sg:postcode":"3350",
    "sg:province":"VIC",
    "sg:tags":[
        "contractor"
    ],
    "wof:name":"Dennis Family Homes",
    "wof:placetype":"venue"
},
  "geometry": {"coordinates":[143.86399800000001,-37.560799],"type":"Point"}
}