{
  "type": "Feature",
  "properties": {
    "iso:country":"AU",
    "sg:address":"15 McDonald Rd",
    "sg:city":"Brooklyn",
    "sg:classifiers":[
        {
            "category":"Utilities",
            "subcategory":"Refuse",
            "type":"Services"
        }
    ],
    "sg:phone":"+61 13 29 55",
    "sg:postcode":"3025",
    "sg:province":"VIC",
    "sg:tags":[
        "disposal",
        "reduction",
        "waste"
    ],
    "wof:name":"Dial-A-Bin",
    "wof:placetype":"venue"
},
  "geometry": {"coordinates":[144.84697,-37.814377],"type":"Point"}
}