{
  "type": "Feature",
  "properties": {
    "addr:full":"39 Delatour St Coconut Grove NT 0810",
    "addr:housenumber":"39",
    "addr:postcode":"0810",
    "addr:street":"Delatour St",
    "iso:country":"AU",
    "sg:address":"39 Delatour St",
    "sg:city":"Coconut Grove",
    "sg:classifiers":[
        {
            "category":"Retail",
            "subcategory":"Laundry & Dry Cleaning",
            "type":"Services"
        }
    ],
    "sg:phone":"+61 8 8948 4100",
    "sg:postcode":"0810",
    "sg:province":"NT",
    "sg:tags":[
        "machine",
        "commercial",
        "industrial",
        "washing"
    ],
    "wof:name":"Australian Laundry Systems (NT) Pty Ltd",
    "wof:placetype":"venue"
},
  "geometry": {"coordinates":[130.85494995100001,-12.3988170624],"type":"Point"}
}