{
  "type": "Feature",
  "properties": {
    "addr:full":"Unit 2, 127 Grandstand Rd Belmont WA 6104",
    "addr:housenumber":"127",
    "addr:postcode":"6104",
    "addr:street":"Grandstand Rd",
    "iso:country":"AU",
    "sg:address":"Unit 2, 127 Grandstand Rd",
    "sg:city":"Belmont",
    "sg:classifiers":[
        {
            "category":"Autos & Motor Vehicles",
            "subcategory":"Auto Supplies",
            "type":"Retail Goods"
        }
    ],
    "sg:phone":"+61 8 9479 1388",
    "sg:postcode":"6104",
    "sg:province":"WA",
    "sg:tags":[
        "transmission",
        "equipment",
        "power"
    ],
    "wof:name":"Renold Australia",
    "wof:placetype":"venue"
},
  "geometry": {"coordinates":[115.925086975,-31.9410362244],"type":"Point"}
}