{
  "type": "Feature",
  "properties": {
    "addr:full":"411 Gardeners Rd Mascot NSW 2020",
    "addr:housenumber":"411",
    "addr:postcode":"2020",
    "addr:street":"Gardeners Rd",
    "iso:country":"AU",
    "sg:address":"411 Gardeners Rd",
    "sg:city":"Mascot",
    "sg:classifiers":[
        {
            "category":"Restaurant",
            "type":"Food & Drink"
        }
    ],
    "sg:phone":"+61 2 9693 2027",
    "sg:postcode":"2020",
    "sg:province":"NSW",
    "wof:name":"Alamak Chinese Restaurant",
    "wof:placetype":"venue"
},
  "geometry": {"coordinates":[151.20152282699999,-33.9223022461],"type":"Point"}
}