{
  "type": "Feature",
  "properties": {
    "addr:full":"2 Western Hwy Nhill VIC 3418",
    "addr:housenumber":"2",
    "addr:postcode":"3418",
    "addr:street":"Western Hwy",
    "iso:country":"AU",
    "sg:address":"2 Western Hwy",
    "sg:city":"Nhill",
    "sg:classifiers":[
        {
            "category":"Building & Trades",
            "subcategory":"Equipment Rental",
            "type":"Services"
        }
    ],
    "sg:phone":"+61 3 5391 3091",
    "sg:postcode":"3418",
    "sg:province":"VIC",
    "sg:tags":[
        "demolition",
        "contractor"
    ],
    "wof:name":"A-M J Hassall Demolition & Excavation Pty Ltd",
    "wof:placetype":"venue"
},
  "geometry": {"coordinates":[141.66278076200001,-36.334022522],"type":"Point"}
}