{
  "type": "Feature",
  "properties": {
    "iso:country":"AU",
    "sg:address":"27 Korong St",
    "sg:city":"Southport",
    "sg:classifiers":[
        {
            "category":"Home & Garden",
            "subcategory":"Building Materials",
            "type":"Retail Goods"
        }
    ],
    "sg:phone":"+61 7 5570 2410",
    "sg:postcode":"4215",
    "sg:province":"QLD",
    "sg:tags":[
        "lawn",
        "cutting",
        "maintenance"
    ],
    "wof:name":"Arborgreen Gardenscapes",
    "wof:placetype":"venue"
},
  "geometry": {"coordinates":[153.41517639200001,-27.9888935089],"type":"Point"}
}