{
  "type": "Feature",
  "properties": {
    "addr:full":"480 Whitehorse Rd Mitcham VIC 3132",
    "addr:housenumber":"480",
    "addr:postcode":"3132",
    "addr:street":"Whitehorse Rd",
    "iso:country":"AU",
    "sg:address":"480 Whitehorse Rd",
    "sg:city":"Mitcham",
    "sg:classifiers":[
        {
            "category":"Home & Garden",
            "subcategory":"Building Materials",
            "type":"Retail Goods"
        }
    ],
    "sg:phone":"+61 3 9873 5222",
    "sg:postcode":"3132",
    "sg:province":"VIC",
    "sg:tags":[
        "merchant",
        "glass",
        "glazier"
    ],
    "wof:name":"Reddy Glass",
    "wof:placetype":"venue"
},
  "geometry": {"coordinates":[145.18913269000001,-37.8172035217],"type":"Point"}
}