{
  "type": "Feature",
  "properties": {
    "iso:country":"AU",
    "sg:address":"7 Walter Pde",
    "sg:city":"Black Hill",
    "sg:classifiers":[
        {
            "category":"Professional",
            "subcategory":"Testing Lab",
            "type":"Services"
        }
    ],
    "sg:phone":"+61 413 809 978",
    "sg:postcode":"2322",
    "sg:province":"NSW",
    "sg:tags":[
        "inspection"
    ],
    "wof:name":"BRES PTY LTD",
    "wof:placetype":"venue"
},
  "geometry": {"coordinates":[151.64096069300001,-32.8269348145],"type":"Point"}
}