{
  "type": "Feature",
  "properties": {
    "addr:full":"13 Bellevue Rd Bellevue Hill NSW 2023",
    "addr:housenumber":"13",
    "addr:postcode":"2023",
    "addr:street":"Bellevue Rd",
    "iso:country":"AU",
    "sg:address":"13 Bellevue Rd",
    "sg:city":"Bellevue Hill",
    "sg:classifiers":[
        {
            "category":"Retail",
            "subcategory":"Self-service Laundry",
            "type":"Services"
        }
    ],
    "sg:phone":"+61 2 9389 6107",
    "sg:postcode":"2023",
    "sg:province":"NSW",
    "wof:name":"Bellevue Hill Laundromat",
    "wof:placetype":"venue"
},
  "geometry": {"coordinates":[151.258010864,-33.8862724304],"type":"Point"}
}