{
  "type": "Feature",
  "properties": {
    "addr:full":"58-60 Byron Pl Adelaide SA 5000",
    "addr:housenumber":"58-60",
    "addr:postcode":"5000",
    "addr:street":"Byron Pl",
    "iso:country":"AU",
    "sg:address":"58-60 Byron Pl",
    "sg:city":"Adelaide",
    "sg:classifiers":[
        {
            "category":"Retail",
            "subcategory":"Auto Repair",
            "type":"Services"
        }
    ],
    "sg:phone":"+61 8 8212 1448",
    "sg:postcode":"5000",
    "sg:province":"SA",
    "sg:tags":[
        "clutch",
        "brake"
    ],
    "wof:name":"Light Wheel Alignment Specialists Pty Ltd",
    "wof:placetype":"venue"
},
  "geometry": {"coordinates":[138.59213256800001,-34.9287719727],"type":"Point"}
}