{
  "type": "Feature",
  "properties": {
    "addr:full":"Launder Ave Wonga Park VIC 3115",
    "addr:postcode":"3115",
    "addr:street":"Launder Ave",
    "iso:country":"AU",
    "sg:address":"Launder Ave",
    "sg:city":"Wonga Park",
    "sg:classifiers":[
        {
            "category":"Arts & Performance",
            "subcategory":"Dance",
            "type":"Entertainment"
        }
    ],
    "sg:phone":"+61 3 9723 7637",
    "sg:postcode":"3115",
    "sg:province":"VIC",
    "sg:tags":[
        "theatrical",
        "ballet",
        "tuition"
    ],
    "wof:name":"Janden Dance School",
    "wof:placetype":"venue"
},
  "geometry": {"coordinates":[145.26968383799999,-37.7385482788],"type":"Point"}
}