{
  "type": "Feature",
  "properties": {
    "addr:full":"7 Alan St Port Noarlunga SA 5167",
    "addr:housenumber":"7",
    "addr:postcode":"5167",
    "addr:street":"Alan St",
    "iso:country":"AU",
    "sg:address":"7 Alan St",
    "sg:city":"Port Noarlunga",
    "sg:classifiers":[
        {
            "category":"Farming",
            "subcategory":"Fish & Marine Products",
            "type":"Manufacturing & Wholesale Goods"
        }
    ],
    "sg:phone":"+61 8 8384 7520",
    "sg:postcode":"5167",
    "sg:province":"SA",
    "sg:tags":[
        "lead",
        "supply"
    ],
    "wof:name":"Cottage Leadlight Co",
    "wof:placetype":"venue"
},
  "geometry": {"coordinates":[138.47218322800001,-35.1477127075],"type":"Point"}
}