{
  "type": "Feature",
  "properties": {
    "addr:full":"Cnr Kiew St & Hume Hwy Albury NSW 2640",
    "addr:postcode":"2640",
    "addr:street":"Cnr Kiew St & Hume Hwy",
    "iso:country":"AU",
    "sg:address":"Cnr Kiew St & Hume Hwy",
    "sg:city":"Albury",
    "sg:classifiers":[
        {
            "category":"Shopping",
            "subcategory":"Stationery & Office Supplies",
            "type":"Retail Goods"
        }
    ],
    "sg:phone":"+61 2 6041 2700",
    "sg:postcode":"2640",
    "sg:province":"NSW",
    "sg:tags":[
        "equipment",
        "facsimile"
    ],
    "wof:name":"Pakstat Office National",
    "wof:placetype":"venue"
},
  "geometry": {"coordinates":[146.908813477,-36.0840759277],"type":"Point"}
}