{
  "type": "Feature",
  "properties": {
    "addr:full":"97 Euchie St Peak Hill NSW 2869",
    "addr:housenumber":"97",
    "addr:postcode":"2869",
    "addr:street":"Euchie St",
    "iso:country":"AU",
    "sg:address":"97 Euchie St",
    "sg:city":"Peak Hill",
    "sg:classifiers":[
        {
            "category":"Social Services",
            "subcategory":"Child Care",
            "type":"Services"
        }
    ],
    "sg:phone":"+61 2 6869 1655",
    "sg:postcode":"2869",
    "sg:province":"NSW",
    "wof:name":"Peak Hill Pre School",
    "wof:placetype":"venue"
},
  "geometry": {"coordinates":[148.19374084500001,-32.7265701294],"type":"Point"}
}