{
  "type": "Feature",
  "properties": {
    "iso:country":"AU",
    "sg:address":"Lvl 5, 1 James Pl",
    "sg:city":"North Sydney",
    "sg:classifiers":[
        {
            "category":"Organizations",
            "subcategory":"Professional Association",
            "type":"Services"
        }
    ],
    "sg:phone":"+61 2 8907 4940",
    "sg:postcode":"2060",
    "sg:province":"NSW",
    "sg:tags":[
        "web",
        "internet"
    ],
    "wof:name":"OneMedia Pty Ltd",
    "wof:placetype":"venue"
},
  "geometry": {"coordinates":[151.20715332,-33.8329124451],"type":"Point"}
}