{
  "type": "Feature",
  "properties": {
    "addr:full":"640b Princes Hwy Jaspers Brush NSW 2535",
    "addr:housenumber":"640b",
    "addr:postcode":"2535",
    "addr:street":"Princes Hwy",
    "iso:country":"AU",
    "sg:address":"640b Princes Hwy",
    "sg:city":"Jaspers Brush",
    "sg:classifiers":[
        {
            "category":"Retail",
            "subcategory":"Event Space",
            "type":"Services"
        }
    ],
    "sg:phone":"+61 2 4448 6160",
    "sg:postcode":"2535",
    "sg:province":"NSW",
    "sg:tags":[
        "venue",
        "reception",
        "wedding"
    ],
    "wof:name":"Silo's Restaurant The",
    "wof:placetype":"venue"
},
  "geometry": {"coordinates":[150.65870666500001,-34.8030509949],"type":"Point"}
}