{
  "type": "Feature",
  "properties": {
    "addr:full":"3 Platt St Waratah NSW 2298",
    "addr:housenumber":"3",
    "addr:postcode":"2298",
    "addr:street":"Platt St",
    "iso:country":"AU",
    "sg:address":"3 Platt St",
    "sg:city":"Waratah",
    "sg:classifiers":[
        {
            "category":"Professional",
            "subcategory":"Detective & Security Services",
            "type":"Services"
        }
    ],
    "sg:phone":"+61 2 4967 4555",
    "sg:postcode":"2298",
    "sg:province":"NSW",
    "sg:tags":[
        "consultant",
        "system"
    ],
    "wof:name":"Gold Star Security",
    "wof:placetype":"venue"
},
  "geometry": {"coordinates":[151.728591919,-32.9011154175],"type":"Point"}
}