{
  "type": "Feature",
  "properties": {
    "addr:full":"61 Glenferrie Rd Malvern VIC 3144",
    "addr:housenumber":"61",
    "addr:postcode":"3144",
    "addr:street":"Glenferrie Rd",
    "iso:country":"AU",
    "sg:address":"61 Glenferrie Rd",
    "sg:city":"Malvern",
    "sg:classifiers":[
        {
            "category":"Shopping",
            "subcategory":"Mobile Phones",
            "type":"Retail Goods"
        }
    ],
    "sg:phone":"+61 3 9509 7511",
    "sg:postcode":"3144",
    "sg:province":"VIC",
    "sg:tags":[
        "telephone",
        "accessory"
    ],
    "wof:name":"Teletronics Communications",
    "wof:placetype":"venue"
},
  "geometry": {"coordinates":[145.02801513700001,-37.8632926941],"type":"Point"}
}