{
  "type": "Feature",
  "properties": {
    "addr:full":"Ipswich Road Medical Centre Annerley QLD 4103",
    "addr:postcode":"4103",
    "addr:street":"Ipswich",
    "iso:country":"AU",
    "sg:address":"Ipswich Road Medical Centre",
    "sg:city":"Annerley",
    "sg:classifiers":[
        {
            "category":"Health Services",
            "subcategory":"Health Practitioner",
            "type":"Services"
        }
    ],
    "sg:phone":"+61 7 3399 8028",
    "sg:postcode":"4103",
    "sg:province":"QLD",
    "sg:tags":[
        "pathologist",
        "speech"
    ],
    "wof:name":"Louise M. Tyquin",
    "wof:placetype":"venue"
},
  "geometry": {"coordinates":[153.03111267099999,-27.5135726929],"type":"Point"}
}