{
  "type": "Feature",
  "properties": {
    "addr:full":"449 Victoria St Wetherill Park NSW 2164",
    "addr:housenumber":"449",
    "addr:postcode":"2164",
    "addr:street":"Victoria St",
    "iso:country":"AU",
    "sg:address":"449 Victoria St",
    "sg:city":"Wetherill Park",
    "sg:classifiers":[
        {
            "category":"Home & Garden",
            "subcategory":"Building Materials",
            "type":"Retail Goods"
        }
    ],
    "sg:phone":"+61 2 9756 3322",
    "sg:postcode":"2164",
    "sg:province":"NSW",
    "sg:tags":[
        "merchant",
        "glass",
        "glazier"
    ],
    "wof:name":"V & N Glass Pty Ltd",
    "wof:placetype":"venue"
},
  "geometry": {"coordinates":[150.89236450199999,-33.8444595337],"type":"Point"}
}