{
  "type": "Feature",
  "properties": {
    "addr:full":"246 Rusden St Armidale NSW 2350",
    "addr:housenumber":"246",
    "addr:postcode":"2350",
    "addr:street":"Rusden St",
    "iso:country":"AU",
    "sg:address":"246 Rusden St",
    "sg:city":"Armidale",
    "sg:classifiers":[
        {
            "category":"Retail",
            "subcategory":"Repair Shop",
            "type":"Services"
        }
    ],
    "sg:phone":"+61 2 6771 1039",
    "sg:postcode":"2350",
    "sg:province":"NSW",
    "sg:tags":[
        "upholsterer"
    ],
    "wof:name":"Covered In Style Upholstery",
    "wof:placetype":"venue"
},
  "geometry": {"coordinates":[151.652145386,-30.5109977722],"type":"Point"}
}