{
  "type": "Feature",
  "properties": {
    "addr:full":"68 Petra St Palmyra WA 6157",
    "addr:housenumber":"68",
    "addr:postcode":"6157",
    "addr:street":"Petra St",
    "iso:country":"AU",
    "sg:address":"68 Petra St",
    "sg:city":"Palmyra",
    "sg:classifiers":[
        {
            "category":"Arena",
            "subcategory":"Sports Club",
            "type":"Entertainment"
        }
    ],
    "sg:phone":"+61 8 9319 2299",
    "sg:postcode":"6157",
    "sg:province":"WA",
    "sg:tags":[
        "hunt",
        "racing"
    ],
    "wof:name":"Fremantle Harness Racing Club",
    "wof:placetype":"venue"
},
  "geometry": {"coordinates":[115.776321,-32.039543],"type":"Point"}
}