{
  "type": "Feature",
  "properties": {
    "addr:full":"6 Roseberry Ave Brighton East VIC 3187",
    "addr:housenumber":"6",
    "addr:postcode":"3187",
    "addr:street":"Roseberry Ave",
    "iso:country":"AU",
    "sg:address":"6 Roseberry Ave",
    "sg:city":"Brighton East",
    "sg:classifiers":[
        {
            "category":"Personal",
            "type":"Services"
        }
    ],
    "sg:phone":"+61 3 9553 8094",
    "sg:postcode":"3187",
    "sg:province":"VIC",
    "sg:tags":[
        "gift"
    ],
    "wof:name":"Absolutely Fabulous Products Pty Ltd",
    "wof:placetype":"venue"
},
  "geometry": {"coordinates":[145.01014709500001,-37.9101638794],"type":"Point"}
}