{
  "type": "Feature",
  "properties": {
    "iso:country":"AU",
    "sg:address":"6 Kintyre Crt",
    "sg:city":"Greenwith",
    "sg:classifiers":[
        {
            "category":"Personal",
            "type":"Services"
        }
    ],
    "sg:phone":"+61 1300 785 882",
    "sg:postcode":"5125",
    "sg:province":"SA",
    "sg:tags":[
        "gift"
    ],
    "wof:name":"Absolutely Fabulous Boxes, Baskets & Balloons",
    "wof:placetype":"venue"
},
  "geometry": {"coordinates":[138.698151,-34.774193],"type":"Point"}
}