{
  "type": "Feature",
  "properties": {
    "addr:full":"36 Lyons St Williamstown VIC 3016",
    "addr:housenumber":"36",
    "addr:postcode":"3016",
    "addr:street":"Lyons St",
    "iso:country":"AU",
    "sg:address":"36 Lyons St",
    "sg:city":"Williamstown",
    "sg:classifiers":[
        {
            "category":"Health Services",
            "subcategory":"Doctor",
            "type":"Services"
        }
    ],
    "sg:phone":"+61 3 9397 0134",
    "sg:postcode":"3016",
    "sg:province":"VIC",
    "sg:tags":[
        "medical",
        "practitioner"
    ],
    "wof:name":"Pereira Jeremy J Dr",
    "wof:placetype":"venue"
},
  "geometry": {"coordinates":[144.896316528,-37.8590240479],"type":"Point"}
}