{
  "type": "Feature",
  "properties": {
    "addr:full":"Shop 5, 182 Forest Rd Hurstville NSW 2220",
    "addr:housenumber":"shop 5 182",
    "addr:postcode":"2220",
    "addr:street":"Forest Rd",
    "iso:country":"AU",
    "sg:address":"Shop 5, 182 Forest Rd",
    "sg:city":"Hurstville",
    "sg:classifiers":[
        {
            "category":"Real Estate",
            "subcategory":"Real Estate Agent",
            "type":"Services"
        }
    ],
    "sg:phone":"+61 2 9580 8860",
    "sg:postcode":"2220",
    "sg:province":"NSW",
    "wof:name":"Century 21 Hurstville",
    "wof:placetype":"venue"
},
  "geometry": {"coordinates":[151.103149414,-33.9671821594],"type":"Point"}
}