{
  "type": "Feature",
  "properties": {
    "addr:full":"58 James St Fortitude Valley QLD 4006",
    "addr:housenumber":"58",
    "addr:postcode":"4006",
    "addr:street":"James St",
    "iso:country":"AU",
    "sg:address":"58 James St",
    "sg:city":"Fortitude Valley",
    "sg:classifiers":[
        {
            "category":"Home & Garden",
            "subcategory":"Carpets & Floor Coverings",
            "type":"Retail Goods"
        }
    ],
    "sg:phone":"+61 7 3358 4499",
    "sg:postcode":"4006",
    "sg:province":"QLD",
    "wof:name":"Brisbane Carpet & Rug Co",
    "wof:placetype":"venue"
},
  "geometry": {"coordinates":[153.041015625,-27.457403183],"type":"Point"}
}