{
  "type": "Feature",
  "properties": {
    "iso:country":"AU",
    "sg:address":"29 William Rd",
    "sg:city":"Riverwood",
    "sg:classifiers":[
        {
            "category":"Social Services",
            "subcategory":"Child Care",
            "type":"Services"
        }
    ],
    "sg:phone":"+61 2 9584 1691",
    "sg:postcode":"2210",
    "sg:province":"NSW",
    "wof:name":"William Road Child Care Centre",
    "wof:placetype":"venue"
},
  "geometry": {"coordinates":[151.047562,-33.951286],"type":"Point"}
}