{
  "type": "Feature",
  "properties": {
    "addr:full":"4 Mimosa Crt Buxton VIC 3711",
    "addr:housenumber":"4",
    "addr:postcode":"3711",
    "addr:street":"Mimosa Crt",
    "iso:country":"AU",
    "sg:address":"4 Mimosa Crt",
    "sg:city":"Buxton",
    "sg:classifiers":[
        {
            "category":"Building & Trades",
            "subcategory":"Construction",
            "type":"Services"
        }
    ],
    "sg:phone":"+61 408 159 963",
    "sg:postcode":"3711",
    "sg:province":"VIC",
    "sg:tags":[
        "polishing",
        "sanding",
        "floor"
    ],
    "wof:name":"John Corbett",
    "wof:placetype":"venue"
},
  "geometry": {"coordinates":[145.708908081,-37.4228591919],"type":"Point"}
}