{
  "type": "Feature",
  "properties": {
    "addr:full":"78 Largs Ave Largs NSW 2320",
    "addr:housenumber":"78",
    "addr:postcode":"2320",
    "addr:street":"Largs Ave",
    "iso:country":"AU",
    "sg:address":"78 Largs Ave",
    "sg:city":"Largs",
    "sg:classifiers":[
        {
            "category":"Education",
            "subcategory":"Kindergarten",
            "type":"Public Place"
        }
    ],
    "sg:phone":"+61 2 4930 1080",
    "sg:postcode":"2320",
    "sg:province":"NSW",
    "sg:tags":[
        "pre-schools"
    ],
    "wof:name":"Tilly's Play & Development Centre",
    "wof:placetype":"venue"
},
  "geometry": {"coordinates":[151.60154724099999,-32.7009887695],"type":"Point"}
}