{
  "type": "Feature",
  "properties": {
    "addr:full":"29 Mungindi Rd Moree NSW 2400",
    "addr:housenumber":"29",
    "addr:postcode":"2400",
    "addr:street":"Mungindi Rd",
    "iso:country":"AU",
    "sg:address":"29 Mungindi Rd",
    "sg:city":"Moree",
    "sg:classifiers":[
        {
            "category":"Farming",
            "subcategory":"Nursery",
            "type":"Manufacturing & Wholesale Goods"
        }
    ],
    "sg:phone":"+61 2 6752 8009",
    "sg:postcode":"2400",
    "sg:province":"NSW",
    "wof:name":"Moree Day Lily Nursery",
    "wof:placetype":"venue"
},
  "geometry": {"coordinates":[149.845504761,-29.448928833],"type":"Point"}
}