{
  "type": "Feature",
  "properties": {
    "iso:country":"AU",
    "sg:address":"3 McBurnie Drv",
    "sg:city":"Melton",
    "sg:classifiers":[
        {
            "category":"Home & Garden",
            "subcategory":"Household Appliances",
            "type":"Retail Goods"
        }
    ],
    "sg:phone":"+61 3 9743 1281",
    "sg:postcode":"3337",
    "sg:province":"VIC",
    "sg:tags":[
        "heating",
        "system"
    ],
    "wof:name":"G J P Heating & Cooling",
    "wof:placetype":"venue"
},
  "geometry": {"coordinates":[144.572372,-37.667625],"type":"Point"}
}