{
  "type": "Feature",
  "properties": {
    "addr:full":"3 George St Dubbo NSW 2830",
    "addr:housenumber":"3",
    "addr:postcode":"2830",
    "addr:street":"George St",
    "iso:country":"AU",
    "sg:address":"3 George St",
    "sg:city":"Dubbo",
    "sg:classifiers":[
        {
            "category":"Building & Trades",
            "subcategory":"Construction",
            "type":"Services"
        }
    ],
    "sg:phone":"+61 2 6884 2002",
    "sg:postcode":"2830",
    "sg:province":"NSW",
    "sg:tags":[
        "renovation",
        "alterations",
        "extension",
        "contractor"
    ],
    "wof:name":"Stephen Parish",
    "wof:placetype":"venue"
},
  "geometry": {"coordinates":[148.61170959500001,-32.2510070801],"type":"Point"}
}