{
  "type": "Feature",
  "properties": {
    "iso:country":"AU",
    "sg:address":"PO Box 14",
    "sg:city":"Mitchell",
    "sg:classifiers":[
        {
            "category":"Government",
            "subcategory":"Fire Station",
            "type":"Public Place"
        }
    ],
    "sg:phone":"+61 2 6241 6322",
    "sg:postcode":"2911",
    "sg:province":"ACT",
    "sg:tags":[
        "equipment",
        "protection",
        "consultant"
    ],
    "wof:name":"Bowsers",
    "wof:placetype":"venue"
},
  "geometry": {"coordinates":[149.13471984899999,-35.2194900513],"type":"Point"}
}