{
  "type": "Feature",
  "properties": {
    "addr:full":"Wonnerup South Rd Busselton WA 6280",
    "addr:postcode":"6280",
    "addr:street":"South Rd",
    "iso:country":"AU",
    "sg:address":"Wonnerup South Rd",
    "sg:city":"Busselton",
    "sg:classifiers":[
        {
            "category":"Home & Garden",
            "subcategory":"Garden Supply",
            "type":"Retail Goods"
        }
    ],
    "sg:phone":"+61 8 9753 3282",
    "sg:postcode":"6280",
    "sg:province":"WA",
    "sg:tags":[
        "turf",
        "lawn"
    ],
    "wof:name":"Down South Turf Supplies",
    "wof:placetype":"venue"
},
  "geometry": {"coordinates":[115.44042968799999,-33.6465682983],"type":"Point"}
}