{
  "type": "Feature",
  "properties": {
    "addr:full":"2585 Settlement Rd Kilmany South VIC 3851",
    "addr:housenumber":"2585",
    "addr:postcode":"3851",
    "addr:street":"Settlement Rd",
    "iso:country":"AU",
    "sg:address":"2585 Settlement Rd",
    "sg:city":"Kilmany South",
    "sg:classifiers":[
        {
            "category":"Building & Trades",
            "subcategory":"Construction",
            "type":"Services"
        }
    ],
    "sg:phone":"+61 3 5149 2220",
    "sg:postcode":"3851",
    "sg:province":"VIC",
    "sg:tags":[
        "earth",
        "excavating",
        "moving",
        "contractor"
    ],
    "wof:name":"Neville Anderson Earthmoving & Laser Grading",
    "wof:placetype":"venue"
},
  "geometry": {"coordinates":[146.97108459500001,-38.1338577271],"type":"Point"}
}