{
  "type": "Feature",
  "properties": {
    "addr:full":"35 Moore St Coffs Harbour NSW 2450",
    "addr:housenumber":"35",
    "addr:postcode":"2450",
    "addr:street":"Moore St",
    "iso:country":"AU",
    "sg:address":"35 Moore St",
    "sg:city":"Coffs Harbour",
    "sg:classifiers":[
        {
            "category":"Health Services",
            "subcategory":"Health Practitioner",
            "type":"Services"
        }
    ],
    "sg:phone":"+61 2 6651 1158",
    "sg:postcode":"2450",
    "sg:province":"NSW",
    "sg:tags":[
        "osteopath"
    ],
    "wof:name":"Bingham Philip D",
    "wof:placetype":"venue"
},
  "geometry": {"coordinates":[153.133499,-30.305532],"type":"Point"}
}