{
  "type": "Feature",
  "properties": {
    "addr:full":"Channel Crt Kingston TAS 7050",
    "addr:postcode":"7050",
    "addr:street":"Channel Crt",
    "iso:country":"AU",
    "sg:address":"Channel Crt",
    "sg:city":"Kingston",
    "sg:classifiers":[
        {
            "category":"Fast Food",
            "type":"Food & Drink"
        }
    ],
    "sg:phone":"+61 3 6229 2232",
    "sg:postcode":"7050",
    "sg:province":"TAS",
    "sg:tags":[
        "away",
        "take"
    ],
    "wof:name":"Mures Kingston",
    "wof:placetype":"venue"
},
  "geometry": {"coordinates":[147.30561800000001,-42.975594],"type":"Point"}
}