{
  "type": "Feature",
  "properties": {
    "addr:full":"7 Ashwood Cl Glenning Valley NSW 2259",
    "addr:housenumber":"7",
    "addr:postcode":"2259",
    "addr:street":"Ashwood Cl Glenning",
    "iso:country":"AU",
    "sg:address":"7 Ashwood Cl",
    "sg:city":"Glenning Valley",
    "sg:classifiers":[
        {
            "category":"Building & Trades",
            "subcategory":"Cleaning & Sanitation",
            "type":"Services"
        }
    ],
    "sg:phone":"+61 2 4389 7644",
    "sg:postcode":"2259",
    "sg:province":"NSW",
    "sg:tags":[
        "cleaner",
        "repairer",
        "roof"
    ],
    "sg:website":"http://www.riverinaroofing.com.au",
    "wof:name":"Riverina Roofing (Tiles)",
    "wof:placetype":"venue"
},
  "geometry": {"coordinates":[151.42291259800001,-33.1819992065],"type":"Point"}
}