{
  "type": "Feature",
  "properties": {
    "addr:full":"Lot 570 Ivanhoe Rd Kununurra WA 6743",
    "addr:postcode":"6743",
    "addr:street":"Ivanhoe Rd",
    "iso:country":"AU",
    "sg:address":"Lot 570 Ivanhoe Rd",
    "sg:city":"Kununurra",
    "sg:classifiers":[
        {
            "category":"Professional",
            "type":"Services"
        }
    ],
    "sg:phone":"+61 8 9168 1577",
    "sg:postcode":"6743",
    "sg:province":"WA",
    "sg:tags":[
        "transport"
    ],
    "wof:name":"Toll West",
    "wof:placetype":"venue"
},
  "geometry": {"coordinates":[128.73110961899999,-15.775396347],"type":"Point"}
}