{
  "type": "Feature",
  "properties": {
    "addr:full":"1 Industrial Rd Harrington NSW 2427",
    "addr:housenumber":"1",
    "addr:postcode":"2427",
    "addr:street":"Industrial Rd",
    "iso:country":"AU",
    "sg:address":"1 Industrial Rd",
    "sg:city":"Harrington",
    "sg:classifiers":[
        {
            "category":"Shopping",
            "subcategory":"Stationery & Office Supplies",
            "type":"Retail Goods"
        }
    ],
    "sg:phone":"+61 2 6556 1760",
    "sg:postcode":"2427",
    "sg:province":"NSW",
    "sg:tags":[
        "equipment",
        "badge",
        "making"
    ],
    "wof:name":"Alarka Australia Pty Ltd",
    "wof:placetype":"venue"
},
  "geometry": {"coordinates":[152.66845699999999,-31.868332],"type":"Point"}
}