{
  "type": "Feature",
  "properties": {
    "addr:full":"4/ 65 Connells Point Rd Hurstville South NSW 2221",
    "addr:housenumber":"/ 65",
    "addr:postcode":"2221",
    "addr:street":"Connells Point Rd",
    "iso:country":"AU",
    "sg:address":"4/ 65 Connells Point Rd",
    "sg:city":"Hurstville South",
    "sg:classifiers":[
        {
            "category":"Health Services",
            "subcategory":"Doctor",
            "type":"Services"
        }
    ],
    "sg:phone":"+61 2 9547 1099",
    "sg:postcode":"2221",
    "sg:province":"NSW",
    "sg:tags":[
        "medical",
        "practitioner"
    ],
    "wof:name":"South Hurstville Family Practice",
    "wof:placetype":"venue"
},
  "geometry": {"coordinates":[151.09393310600001,-33.9866294861],"type":"Point"}
}