{
  "type": "Feature",
  "properties": {
    "addr:full":"Boyup Brook - Arthur River Rd Boyup Brook WA 6244",
    "addr:postcode":"6244",
    "addr:street":"River Rd",
    "iso:country":"AU",
    "sg:address":"Boyup Brook - Arthur River Rd",
    "sg:city":"Boyup Brook",
    "sg:classifiers":[
        {
            "category":"Communications",
            "subcategory":"News Services",
            "type":"Services"
        }
    ],
    "sg:phone":"+61 8 9765 1125",
    "sg:postcode":"6244",
    "sg:province":"WA",
    "sg:tags":[
        "information",
        "tourist",
        "attractions"
    ],
    "wof:name":"Harvey Dickson's Country Music Centre",
    "wof:placetype":"venue"
},
  "geometry": {"coordinates":[116.388328552,-33.8355484009],"type":"Point"}
}