{
  "type": "Feature",
  "properties": {
    "iso:country":"AU",
    "sg:address":"58 Dalkeith Rd",
    "sg:city":"Nedlands",
    "sg:classifiers":[
        {
            "category":"Banks & Credit Unions",
            "subcategory":"Investment Brokerage",
            "type":"Services"
        }
    ],
    "sg:phone":"+61 8 9386 8217",
    "sg:postcode":"6009",
    "sg:province":"WA",
    "sg:tags":[
        "care",
        "day",
        "family",
        "child"
    ],
    "wof:name":"Dalkeith Day Care Centre",
    "wof:placetype":"venue"
},
  "geometry": {"coordinates":[115.802757,-31.979818],"type":"Point"}
}