{
  "type": "Feature",
  "properties": {
    "iso:country":"AU",
    "sg:address":"George St",
    "sg:city":"Singleton",
    "sg:classifiers":[
        {
            "category":"Health Services",
            "subcategory":"Hospital",
            "type":"Services"
        }
    ],
    "sg:phone":"+61 13 12 33",
    "sg:postcode":"2330",
    "sg:province":"NSW",
    "sg:tags":[
        "ambulance"
    ],
    "wof:name":"Ambulance Service Of NSW",
    "wof:placetype":"venue"
},
  "geometry": {"coordinates":[151.179306,-32.567799],"type":"Point"}
}