{
  "type": "Feature",
  "properties": {
    "addr:full":"Kalgoorlie Rd West Kalgoorlie WA 6430",
    "addr:postcode":"6430",
    "addr:street":"Kalgoorlie Rd West",
    "iso:country":"AU",
    "sg:address":"Kalgoorlie Rd",
    "sg:city":"West Kalgoorlie",
    "sg:classifiers":[
        {
            "category":"Autos & Motor Vehicles",
            "subcategory":"Auto Supplies",
            "type":"Retail Goods"
        }
    ],
    "sg:phone":"+61 8 9021 2437",
    "sg:postcode":"6430",
    "sg:province":"WA",
    "sg:tags":[
        "oil",
        "spirit"
    ],
    "wof:name":"Statewide Oil Distributors",
    "wof:placetype":"venue"
},
  "geometry": {"coordinates":[121.427612305,-30.7831516266],"type":"Point"}
}