{
  "type": "Feature",
  "properties": {
    "addr:full":"156 Southwood Rd Stuart QLD 4811",
    "addr:housenumber":"156",
    "addr:postcode":"4811",
    "addr:street":"Southwood Rd",
    "iso:country":"AU",
    "sg:address":"156 Southwood Rd",
    "sg:city":"Stuart",
    "sg:classifiers":[
        {
            "category":"Shopping",
            "subcategory":"Pets & Pet Supplies",
            "type":"Retail Goods"
        }
    ],
    "sg:phone":"+61 7 4778 1596",
    "sg:postcode":"4811",
    "sg:province":"QLD",
    "sg:tags":[
        "food"
    ],
    "wof:name":"Townsville Pet Care Centre",
    "wof:placetype":"venue"
},
  "geometry": {"coordinates":[146.858047,-19.348118],"type":"Point"}
}