{
  "type": "Feature",
  "properties": {
    "iso:country":"AU",
    "sg:address":"16 Fitzroy St",
    "sg:city":"Rockhampton",
    "sg:classifiers":[
        {
            "category":"Education",
            "subcategory":"Music School",
            "type":"Public Place"
        }
    ],
    "sg:phone":"+61 7 4923 7464",
    "sg:postcode":"4700",
    "sg:province":"QLD",
    "sg:tags":[
        "teacher"
    ],
    "wof:name":"Bel Canto Singing & Music Academy",
    "wof:placetype":"venue"
},
  "geometry": {"coordinates":[150.501342773,-23.3834114075],"type":"Point"}
}