{
  "type": "Feature",
  "properties": {
    "addr:full":"Garroorigang Rd Goulburn NSW 2580",
    "addr:postcode":"2580",
    "addr:street":"Garroorigang Rd",
    "iso:country":"AU",
    "sg:address":"Garroorigang Rd",
    "sg:city":"Goulburn",
    "sg:classifiers":[
        {
            "category":"Fast Food",
            "type":"Food & Drink"
        }
    ],
    "sg:phone":"+61 2 4822 5166",
    "sg:postcode":"2580",
    "sg:province":"NSW",
    "sg:tags":[
        "away",
        "take"
    ],
    "wof:name":"McDonald's Family Restaurants",
    "wof:placetype":"venue"
},
  "geometry": {"coordinates":[149.69700622600001,-34.7770080566],"type":"Point"}
}