{
  "type": "Feature",
  "properties": {
    "addr:full":"7 Nadene Pl Pymble NSW 2073",
    "addr:housenumber":"7",
    "addr:postcode":"2073",
    "addr:street":"Nadene Pl",
    "iso:country":"AU",
    "sg:address":"7 Nadene Pl",
    "sg:city":"Pymble",
    "sg:classifiers":[
        {
            "category":"Professional",
            "subcategory":"Computer Services",
            "type":"Services"
        }
    ],
    "sg:phone":"+61 2 9880 2612",
    "sg:postcode":"2073",
    "sg:province":"NSW",
    "sg:tags":[
        "consultant",
        "system"
    ],
    "wof:name":"Automated Office (NSW) Pty Ltd The",
    "wof:placetype":"venue"
},
  "geometry": {"coordinates":[151.140136719,-33.7539825439],"type":"Point"}
}