{
  "type": "Feature",
  "properties": {
    "addr:full":"Shop 2A, 122 Edinburgh Rd Castlecrag NSW 2068",
    "addr:housenumber":"shop 2a 122",
    "addr:postcode":"2068",
    "addr:street":"Edinburgh Rd",
    "iso:country":"AU",
    "sg:address":"Shop 2A, 122 Edinburgh Rd",
    "sg:city":"Castlecrag",
    "sg:classifiers":[
        {
            "category":"Restaurant",
            "type":"Food & Drink"
        }
    ],
    "sg:phone":"+61 2 9967 3433",
    "sg:postcode":"2068",
    "sg:province":"NSW",
    "wof:name":"Bai Yok Modern Thai Cuisine",
    "wof:placetype":"venue"
},
  "geometry": {"coordinates":[151.21311950699999,-33.8025131226],"type":"Point"}
}