{
  "type": "Feature",
  "properties": {
    "addr:full":"Unit 2, 54- 58 Walter Rd West Bedford WA 6052",
    "addr:housenumber":"54 58",
    "addr:postcode":"6052",
    "addr:street":"Walter Rd",
    "iso:country":"AU",
    "sg:address":"Unit 2, 54- 58 Walter Rd West",
    "sg:city":"Bedford",
    "sg:classifiers":[
        {
            "category":"Professional",
            "subcategory":"Computer Services",
            "type":"Services"
        }
    ],
    "sg:phone":"+61 8 9471 8999",
    "sg:postcode":"6052",
    "sg:province":"WA",
    "sg:tags":[
        "repairs",
        "upgrade",
        "equipment"
    ],
    "wof:name":"Anti Virus Doctor",
    "wof:placetype":"venue"
},
  "geometry": {"coordinates":[115.88127899200001,-31.9079322815],"type":"Point"}
}