{
  "type": "Feature",
  "properties": {
    "iso:country":"AU",
    "sg:address":"Sale Maffra Rd",
    "sg:city":"Bundalaguah",
    "sg:classifiers":[
        {
            "category":"Education",
            "subcategory":"School",
            "type":"Public Place"
        }
    ],
    "sg:phone":"+61 3 5147 1110",
    "sg:postcode":"3851",
    "sg:province":"VIC",
    "sg:tags":[
        "state",
        "except",
        "nsw"
    ],
    "wof:name":"Bundalaguah Primary School",
    "wof:placetype":"venue"
},
  "geometry": {"coordinates":[147.216033936,-38.3536987305],"type":"Point"}
}