{
  "type": "Feature",
  "properties": {
    "addr:full":"Neudorf Rd Lobethal SA 5241",
    "addr:postcode":"5241",
    "addr:street":"Neudorf Rd",
    "iso:country":"AU",
    "sg:address":"Neudorf Rd",
    "sg:city":"Lobethal",
    "sg:classifiers":[
        {
            "category":"Wholesale",
            "subcategory":"Plants",
            "type":"Manufacturing & Wholesale Goods"
        }
    ],
    "sg:phone":"+61 417 876 240",
    "sg:postcode":"5241",
    "sg:province":"SA",
    "sg:tags":[
        "florist"
    ],
    "wof:name":"S.T. Flowers",
    "wof:placetype":"venue"
},
  "geometry": {"coordinates":[138.860427856,-34.904750824],"type":"Point"}
}