{
  "type": "Feature",
  "properties": {
    "addr:full":"3/ 44 Buckingham St Surry Hills NSW 2010",
    "addr:housenumber":"/ 44",
    "addr:postcode":"2010",
    "addr:street":"Buckingham St",
    "iso:country":"AU",
    "sg:address":"3/ 44 Buckingham St",
    "sg:city":"Surry Hills",
    "sg:classifiers":[
        {
            "category":"Building & Trades",
            "subcategory":"Construction",
            "type":"Services"
        }
    ],
    "sg:phone":"+61 2 9319 2177",
    "sg:postcode":"2010",
    "sg:province":"NSW",
    "sg:tags":[
        "contractor"
    ],
    "wof:name":"ASVP",
    "wof:placetype":"venue"
},
  "geometry": {"coordinates":[151.20762634299999,-33.8874511719],"type":"Point"}
}