{
  "type": "Feature",
  "properties": {
    "addr:full":"40 Kydd Rd Labertouche VIC 3816",
    "addr:housenumber":"40",
    "addr:postcode":"3816",
    "addr:street":"Kydd Rd",
    "iso:country":"AU",
    "sg:address":"40 Kydd Rd",
    "sg:city":"Labertouche",
    "sg:classifiers":[
        {
            "category":"Building & Trades",
            "subcategory":"Plumbing",
            "type":"Services"
        }
    ],
    "sg:phone":"+61 3 5628 7691",
    "sg:postcode":"3816",
    "sg:province":"VIC",
    "sg:tags":[
        "plumber",
        "gasfitters"
    ],
    "wof:name":"B.P.K. Plumbing Services",
    "wof:placetype":"venue"
},
  "geometry": {"coordinates":[145.80038500000001,-38.059071],"type":"Point"}
}