{
  "type": "Feature",
  "properties": {
    "addr:full":"Shop 3/ 11 Bruce Pde Glass House Mountains QLD 4518",
    "addr:housenumber":"shop 3 / 11",
    "addr:postcode":"4518",
    "addr:street":"Bruce Pde",
    "iso:country":"AU",
    "sg:address":"Shop 3/ 11 Bruce Pde",
    "sg:city":"Glass House Mountains",
    "sg:classifiers":[
        {
            "category":"Retail",
            "subcategory":"Laundry & Dry Cleaning",
            "type":"Services"
        }
    ],
    "sg:phone":"+61 433 895 126",
    "sg:postcode":"4518",
    "sg:province":"QLD",
    "wof:name":"Havachat Laundramats",
    "wof:placetype":"venue"
},
  "geometry": {"coordinates":[152.95729064899999,-26.8977355957],"type":"Point"}
}