{
  "type": "Feature",
  "properties": {
    "addr:full":"Ste 3, 96 Chandos St St Leonards NSW 2065",
    "addr:housenumber":"96",
    "addr:postcode":"2065",
    "addr:street":"Chandos St",
    "iso:country":"AU",
    "sg:address":"Ste 3, 96 Chandos St",
    "sg:city":"St Leonards",
    "sg:classifiers":[
        {
            "category":"Professional",
            "subcategory":"Business Services",
            "type":"Services"
        }
    ],
    "sg:phone":"+61 2 9436 4322",
    "sg:postcode":"2065",
    "sg:province":"NSW",
    "sg:tags":[
        "management",
        "event"
    ],
    "wof:name":"SMPT Events",
    "wof:placetype":"venue"
},
  "geometry": {"coordinates":[151.20022582999999,-33.8219223022],"type":"Point"}
}