{
  "type": "Feature",
  "properties": {
    "addr:full":"153 High St Thomastown VIC 3074",
    "addr:housenumber":"153",
    "addr:postcode":"3074",
    "addr:street":"High St",
    "iso:country":"AU",
    "sg:address":"153 High St",
    "sg:city":"Thomastown",
    "sg:classifiers":[
        {
            "category":"Food & Beverages",
            "subcategory":"Supermarket",
            "type":"Retail Goods"
        }
    ],
    "sg:phone":"+61 3 9465 7613",
    "sg:postcode":"3074",
    "sg:province":"VIC",
    "sg:tags":[
        "grocery",
        "store"
    ],
    "wof:name":"Bollywood Bazaar",
    "wof:placetype":"venue"
},
  "geometry": {"coordinates":[145.013305664,-37.6822547913],"type":"Point"}
}