{
  "type": "Feature",
  "properties": {
    "iso:country":"AU",
    "sg:address":"4/ 96 Yarralea St",
    "sg:city":"Alphington",
    "sg:classifiers":[
        {
            "category":"Organizations",
            "subcategory":"Professional Association",
            "type":"Services"
        }
    ],
    "sg:phone":"+61 3 9499 4790",
    "sg:postcode":"3078",
    "sg:province":"VIC",
    "sg:tags":[
        "web",
        "internet"
    ],
    "wof:name":"Abetz-Rouse Services",
    "wof:placetype":"venue"
},
  "geometry": {"coordinates":[145.032745361,-37.7788276672],"type":"Point"}
}