{
  "type": "Feature",
  "properties": {
    "addr:full":"160 Clarendon St Cranbourne VIC 3977",
    "addr:housenumber":"160",
    "addr:postcode":"3977",
    "addr:street":"Clarendon St",
    "iso:country":"AU",
    "sg:address":"160 Clarendon St",
    "sg:city":"Cranbourne",
    "sg:classifiers":[
        {
            "category":"Building & Trades",
            "subcategory":"Cleaning & Sanitation",
            "type":"Services"
        }
    ],
    "sg:phone":"+61 428 128 491",
    "sg:postcode":"3977",
    "sg:province":"VIC",
    "sg:tags":[
        "window"
    ],
    "wof:name":"Pane Fully Window Cleaning",
    "wof:placetype":"venue"
},
  "geometry": {"coordinates":[145.29086303700001,-38.1066513062],"type":"Point"}
}