{
  "type": "Feature",
  "properties": {
    "addr:full":"Unit 7-8 320 Commercial Street West Gambia 5290 Electrona TAS 7054",
    "addr:housenumber":"320;5290",
    "addr:postcode":"7054",
    "addr:street":"Commercial Street West Gambia",
    "iso:country":"AU",
    "sg:address":"Unit 7-8 320 Commercial Street West Gambia 5290",
    "sg:city":"Electrona",
    "sg:classifiers":[
        {
            "category":"Wholesale",
            "subcategory":"Seafood",
            "type":"Manufacturing & Wholesale Goods"
        }
    ],
    "sg:phone":"+61 418 360 766",
    "sg:postcode":"7054",
    "sg:province":"TAS",
    "sg:tags":[
        "fish"
    ],
    "wof:name":"Kenneth Aqua Marine Products Tasmania",
    "wof:placetype":"venue"
},
  "geometry": {"coordinates":[147.26267999999999,-43.052769],"type":"Point"}
}