{
  "type": "Feature",
  "properties": {
    "iso:country":"AU",
    "sg:address":"3 Buna St",
    "sg:city":"Albury North",
    "sg:classifiers":[
        {
            "category":"Shopping",
            "subcategory":"Musical Instruments",
            "type":"Retail Goods"
        }
    ],
    "sg:phone":"+61 2 6025 6975",
    "sg:postcode":"2640",
    "sg:province":"NSW",
    "sg:tags":[
        "musician",
        "agent"
    ],
    "wof:name":"Recover",
    "wof:placetype":"venue"
},
  "geometry": {"coordinates":[146.92990112300001,-36.0525627136],"type":"Point"}
}