{
  "type": "Feature",
  "properties": {
    "iso:country":"AU",
    "sg:address":"1040 Yaamba Rd",
    "sg:city":"Parkhurst",
    "sg:classifiers":[
        {
            "category":"Education",
            "subcategory":"Special Training",
            "type":"Public Place"
        }
    ],
    "sg:phone":"+61 7 4936 1519",
    "sg:postcode":"4702",
    "sg:province":"QLD",
    "sg:tags":[
        "drama",
        "tuition"
    ],
    "wof:name":"Bobbi Cruice Drama & Theatre Consultant",
    "wof:placetype":"venue"
},
  "geometry": {"coordinates":[150.33833313,-23.2601299286],"type":"Point"}
}