{
  "type": "Feature",
  "properties": {
    "addr:full":"1 Torquay Ave Chadstone VIC 3148",
    "addr:housenumber":"1",
    "addr:postcode":"3148",
    "addr:street":"Torquay Ave",
    "iso:country":"AU",
    "sg:address":"1 Torquay Ave",
    "sg:city":"Chadstone",
    "sg:classifiers":[
        {
            "category":"Utilities",
            "subcategory":"Electric",
            "type":"Services"
        }
    ],
    "sg:phone":"+61 3 9888 1881",
    "sg:postcode":"3148",
    "sg:province":"VIC",
    "sg:tags":[
        "electrical",
        "contractor"
    ],
    "wof:name":"Catterall J G & Co Pty Ltd",
    "wof:placetype":"venue"
},
  "geometry": {"coordinates":[145.10690307600001,-37.8847541809],"type":"Point"}
}