{
  "type": "Feature",
  "properties": {
    "addr:full":"Shp 3/ 33 Brisbane Rd Bundamba QLD 4304",
    "addr:housenumber":"/ 33",
    "addr:postcode":"4304",
    "addr:street":"Brisbane Rd",
    "iso:country":"AU",
    "sg:address":"Shp 3/ 33 Brisbane Rd",
    "sg:city":"Bundamba",
    "sg:classifiers":[
        {
            "category":"Food & Beverages",
            "subcategory":"Bakery",
            "type":"Retail Goods"
        }
    ],
    "sg:phone":"+61 7 3282 2038",
    "sg:postcode":"4304",
    "sg:province":"QLD",
    "sg:tags":[
        "baker"
    ],
    "wof:name":"SK Bakery",
    "wof:placetype":"venue"
},
  "geometry": {"coordinates":[152.81109619099999,-27.6086521149],"type":"Point"}
}