{
  "type": "Feature",
  "properties": {
    "addr:full":"Euramo Rd Euramo QLD 4854",
    "addr:postcode":"4854",
    "addr:street":"Euramo Rd",
    "iso:country":"AU",
    "sg:address":"Euramo Rd",
    "sg:city":"Euramo",
    "sg:classifiers":[
        {
            "category":"Farming",
            "subcategory":"Farm",
            "type":"Manufacturing & Wholesale Goods"
        }
    ],
    "sg:phone":"+61 7 4066 7802",
    "sg:postcode":"4854",
    "sg:province":"QLD",
    "sg:tags":[
        "farmer"
    ],
    "wof:name":"Cargnello P",
    "wof:placetype":"venue"
},
  "geometry": {"coordinates":[145.936004639,-17.9983024597],"type":"Point"}
}