{
  "type": "Feature",
  "properties": {
    "addr:full":"11 Johns St Bayswater WA 6053",
    "addr:housenumber":"11",
    "addr:postcode":"6053",
    "addr:street":"Johns St",
    "iso:country":"AU",
    "sg:address":"11 Johns St",
    "sg:city":"Bayswater",
    "sg:classifiers":[
        {
            "category":"Building & Trades",
            "subcategory":"Cleaning & Sanitation",
            "type":"Services"
        }
    ],
    "sg:phone":"+61 414 784 525",
    "sg:postcode":"6053",
    "sg:province":"WA",
    "sg:tags":[
        "abrasive",
        "blasting"
    ],
    "wof:name":"B & N Sandblasting Pty Ltd",
    "wof:placetype":"venue"
},
  "geometry": {"coordinates":[115.918403626,-31.9104232788],"type":"Point"}
}