{
  "type": "Feature",
  "properties": {
    "iso:country":"AU",
    "sg:address":"18 Dunn Crs",
    "sg:city":"Dandenong",
    "sg:classifiers":[
        {
            "category":"Professional",
            "subcategory":"Detective & Security Services",
            "type":"Services"
        }
    ],
    "sg:phone":"+61 3 9792 3632",
    "sg:postcode":"3175",
    "sg:province":"VIC",
    "sg:tags":[
        "identification",
        "system"
    ],
    "wof:name":"Bri-Dor Marking Co",
    "wof:placetype":"venue"
},
  "geometry": {"coordinates":[145.218215942,-37.9853210449],"type":"Point"}
}