{
  "type": "Feature",
  "properties": {
    "addr:full":"2 Dutton St Northam WA 6401",
    "addr:housenumber":"2",
    "addr:postcode":"6401",
    "addr:street":"Dutton St",
    "iso:country":"AU",
    "sg:address":"2 Dutton St",
    "sg:city":"Northam",
    "sg:classifiers":[
        {
            "category":"Professional",
            "type":"Services"
        }
    ],
    "sg:phone":"+61 418 840 924",
    "sg:postcode":"6401",
    "sg:province":"WA",
    "sg:tags":[
        "courier"
    ],
    "wof:name":"Northam Courier Service",
    "wof:placetype":"venue"
},
  "geometry": {"coordinates":[116.677627563,-31.6554355621],"type":"Point"}
}