{
  "type": "Feature",
  "properties": {
    "addr:full":"36 Stadcor St Wavell Heights QLD 4012",
    "addr:housenumber":"36",
    "addr:postcode":"4012",
    "addr:street":"Stadcor St",
    "iso:country":"AU",
    "sg:address":"36 Stadcor St",
    "sg:city":"Wavell Heights",
    "sg:classifiers":[
        {
            "category":"Professional",
            "subcategory":"Art Services",
            "type":"Services"
        }
    ],
    "sg:phone":"+61 7 3630 4430",
    "sg:postcode":"4012",
    "sg:province":"QLD",
    "sg:tags":[
        "picture",
        "frame",
        "framing"
    ],
    "wof:name":"Kingsridge Framing",
    "wof:placetype":"venue"
},
  "geometry": {"coordinates":[153.050216675,-27.3872909546],"type":"Point"}
}