{
  "type": "Feature",
  "properties": {
    "addr:full":"174 Northstead St Scarborough WA 6019",
    "addr:housenumber":"174",
    "addr:postcode":"6019",
    "addr:street":"Northstead St",
    "iso:country":"AU",
    "sg:address":"174 Northstead St",
    "sg:city":"Scarborough",
    "sg:classifiers":[
        {
            "category":"Utilities",
            "subcategory":"Electric",
            "type":"Services"
        }
    ],
    "sg:phone":"+61 8 9245 4400",
    "sg:postcode":"6019",
    "sg:province":"WA",
    "sg:tags":[
        "electrical",
        "contractor"
    ],
    "wof:name":"Westelect",
    "wof:placetype":"venue"
},
  "geometry": {"coordinates":[115.77292633099999,-31.8946552277],"type":"Point"}
}