{
  "type": "Feature",
  "properties": {
    "addr:full":"508 Dorset Rd Croydon South VIC 3136",
    "addr:housenumber":"508",
    "addr:postcode":"3136",
    "addr:street":"Dorset Rd",
    "iso:country":"AU",
    "sg:address":"508 Dorset Rd",
    "sg:city":"Croydon South",
    "sg:classifiers":[
        {
            "category":"Personal",
            "subcategory":"Beauty Salon",
            "type":"Services"
        }
    ],
    "sg:phone":"+61 3 9722 8997",
    "sg:postcode":"3136",
    "sg:province":"VIC",
    "wof:name":"Vicki's Bodylounge",
    "wof:placetype":"venue"
},
  "geometry": {"coordinates":[145.28741455100001,-37.8164405823],"type":"Point"}
}