{
  "type": "Feature",
  "properties": {
    "addr:full":"Easy T Medical Shop 5/ 42 Scottsdale Drv Robina QLD 4226",
    "addr:housenumber":"5 / 42",
    "addr:postcode":"4226",
    "addr:street":"Scottsdale Drv",
    "iso:country":"AU",
    "sg:address":"Easy T Medical Shop 5/ 42 Scottsdale Drv",
    "sg:city":"Robina",
    "sg:classifiers":[
        {
            "category":"Health Services",
            "subcategory":"Dentist",
            "type":"Services"
        }
    ],
    "sg:phone":"+61 7 5580 9926",
    "sg:postcode":"4226",
    "sg:province":"QLD",
    "wof:name":"Easy Teeth Dental Care",
    "wof:placetype":"venue"
},
  "geometry": {"coordinates":[153.38949585,-28.079580307],"type":"Point"}
}