{
  "type": "Feature",
  "properties": {
    "addr:full":"13 Walton St Cowes VIC 3922",
    "addr:housenumber":"13",
    "addr:postcode":"3922",
    "addr:street":"Walton St",
    "iso:country":"AU",
    "sg:address":"13 Walton St",
    "sg:city":"Cowes",
    "sg:classifiers":[
        {
            "category":"Building & Trades",
            "subcategory":"Construction",
            "type":"Services"
        }
    ],
    "sg:phone":"+61 3 5952 2759",
    "sg:postcode":"3922",
    "sg:province":"VIC",
    "sg:tags":[
        "contractor"
    ],
    "wof:name":"Noble W R & E M",
    "wof:placetype":"venue"
},
  "geometry": {"coordinates":[145.245697022,-38.4582328796],"type":"Point"}
}