{
  "type": "Feature",
  "properties": {
    "iso:country":"AU",
    "sg:address":"Unit 2 56 Lancaster St",
    "sg:city":"Ingleburn",
    "sg:classifiers":[
        {
            "category":"Military Area",
            "subcategory":"Air Force Base",
            "type":"Public Place"
        }
    ],
    "sg:phone":"+61 2 9829 0164",
    "sg:postcode":"2565",
    "sg:province":"NSW",
    "sg:tags":[
        "merchant",
        "eftpos",
        "facility"
    ],
    "wof:name":"Fortronics",
    "wof:placetype":"venue"
},
  "geometry": {"coordinates":[150.857543945,-33.9984283447],"type":"Point"}
}