{
  "type": "Feature",
  "properties": {
    "iso:country":"AU",
    "sg:address":"167 Parkin St",
    "sg:city":"Rockingham",
    "sg:classifiers":[
        {
            "category":"Real Estate",
            "subcategory":"Real Estate Services",
            "type":"Services"
        }
    ],
    "sg:phone":"+61 8 9528 1120",
    "sg:postcode":"6168",
    "sg:province":"WA",
    "sg:tags":[
        "valuer"
    ],
    "wof:name":"JJ Le Fevre",
    "wof:placetype":"venue"
},
  "geometry": {"coordinates":[115.729027,-32.27763],"type":"Point"}
}