{
  "type": "Feature",
  "properties": {
    "iso:country":"AU",
    "sg:address":"4b Clarke St",
    "sg:city":"Earlwood",
    "sg:classifiers":[
        {
            "category":"Personal",
            "subcategory":"Beauty Salon",
            "type":"Services"
        }
    ],
    "sg:phone":"+61 2 9558 3844",
    "sg:postcode":"2206",
    "sg:province":"NSW",
    "sg:tags":[
        "hairdresser"
    ],
    "wof:name":"Chez Coiffure",
    "wof:placetype":"venue"
},
  "geometry": {"coordinates":[151.124878,-33.926495],"type":"Point"}
}