{
  "type": "Feature",
  "properties": {
    "addr:full":"193 Main Rd McLaren Vale SA 5171",
    "addr:housenumber":"193",
    "addr:postcode":"5171",
    "addr:street":"Main Rd",
    "iso:country":"AU",
    "sg:address":"193 Main Rd",
    "sg:city":"McLaren Vale",
    "sg:classifiers":[
        {
            "category":"Health Services",
            "subcategory":"Chiropractor",
            "type":"Services"
        }
    ],
    "sg:phone":"+61 8 8323 9755",
    "sg:postcode":"5171",
    "sg:province":"SA",
    "wof:name":"Rowlands Scott T.",
    "wof:placetype":"venue"
},
  "geometry": {"coordinates":[138.53758239699999,-35.2152557373],"type":"Point"}
}