{
  "type": "Feature",
  "properties": {
    "addr:full":"269 Lings Rd Buttai NSW 2323",
    "addr:housenumber":"269",
    "addr:postcode":"2323",
    "addr:street":"Lings Rd",
    "iso:country":"AU",
    "sg:address":"269 Lings Rd",
    "sg:city":"Buttai",
    "sg:classifiers":[
        {
            "category":"Building & Trades",
            "subcategory":"Plumbing",
            "type":"Services"
        }
    ],
    "sg:phone":"+61 412 498 055",
    "sg:postcode":"2323",
    "sg:province":"NSW",
    "sg:tags":[
        "plumber",
        "gasfitters"
    ],
    "wof:name":"D N D Wicks Plumbing Service",
    "wof:placetype":"venue"
},
  "geometry": {"coordinates":[151.56007385300001,-32.8229103088],"type":"Point"}
}