{
  "type": "Feature",
  "properties": {
    "addr:full":"Rm 11/151- 153 Pacific Hwy Hornsby NSW 2077",
    "addr:housenumber":"/ 151 153",
    "addr:postcode":"2077",
    "addr:street":"Pacific Hwy",
    "iso:country":"AU",
    "sg:address":"Rm 11/151- 153 Pacific Hwy",
    "sg:city":"Hornsby",
    "sg:classifiers":[
        {
            "category":"Personal",
            "subcategory":"Hair Removal",
            "type":"Services"
        }
    ],
    "sg:phone":"+61 2 9482 7774",
    "sg:postcode":"2077",
    "sg:province":"NSW",
    "wof:name":"Perrott Sister Electrolysis",
    "wof:placetype":"venue"
},
  "geometry": {"coordinates":[151.097366333,-33.7037277222],"type":"Point"}
}