{
  "type": "Feature",
  "properties": {
    "addr:full":"75 Anzac Ave Seymour VIC 3660",
    "addr:housenumber":"75",
    "addr:postcode":"3660",
    "addr:street":"Anzac Ave",
    "iso:country":"AU",
    "sg:address":"75 Anzac Ave",
    "sg:city":"Seymour",
    "sg:classifiers":[
        {
            "category":"Personal",
            "subcategory":"Tattoo Parlor",
            "type":"Services"
        }
    ],
    "sg:phone":"+61 3 5792 4018",
    "sg:postcode":"3660",
    "sg:province":"VIC",
    "sg:tags":[
        "tattooing"
    ],
    "wof:name":"Razorback Tattoos",
    "wof:placetype":"venue"
},
  "geometry": {"coordinates":[145.144439697,-37.0291481018],"type":"Point"}
}