{
  "type": "Feature",
  "properties": {
    "addr:full":"13 Rochester St Homebush NSW 2140",
    "addr:housenumber":"13",
    "addr:postcode":"2140",
    "addr:street":"Rochester St",
    "iso:country":"AU",
    "sg:address":"13 Rochester St",
    "sg:city":"Homebush",
    "sg:classifiers":[
        {
            "category":"Food & Beverages",
            "subcategory":"Bakery",
            "type":"Retail Goods"
        }
    ],
    "sg:phone":"+61 2 9764 3459",
    "sg:postcode":"2140",
    "sg:province":"NSW",
    "sg:tags":[
        "baker"
    ],
    "wof:name":"Phan's Hot Bread",
    "wof:placetype":"venue"
},
  "geometry": {"coordinates":[151.084716797,-33.8668518066],"type":"Point"}
}