{
  "type": "Feature",
  "properties": {
    "addr:full":"1051 Pacific Hwy Pymble NSW 2073",
    "addr:housenumber":"1051",
    "addr:postcode":"2073",
    "addr:street":"Pacific Hwy",
    "iso:country":"AU",
    "sg:address":"1051 Pacific Hwy",
    "sg:city":"Pymble",
    "sg:classifiers":[
        {
            "category":"Health Services",
            "subcategory":"Chiropractor",
            "type":"Services"
        }
    ],
    "sg:phone":"+61 2 9983 1283",
    "sg:postcode":"2073",
    "sg:province":"NSW",
    "wof:name":"Lough S P",
    "wof:placetype":"venue"
},
  "geometry": {"coordinates":[151.13984680199999,-33.7425041199],"type":"Point"}
}