{
  "type": "Feature",
  "properties": {
    "addr:full":"50 Capella St Clermont QLD 4721",
    "addr:housenumber":"50",
    "addr:postcode":"4721",
    "addr:street":"Capella St",
    "iso:country":"AU",
    "sg:address":"50 Capella St",
    "sg:city":"Clermont",
    "sg:classifiers":[
        {
            "category":"Autos & Motor Vehicles",
            "subcategory":"Automobile Sales",
            "type":"Retail Goods"
        }
    ],
    "sg:phone":"+61 7 4983 1811",
    "sg:postcode":"4721",
    "sg:province":"QLD",
    "sg:tags":[
        "car",
        "new"
    ],
    "wof:name":"G.R. Motors",
    "wof:placetype":"venue"
},
  "geometry": {"coordinates":[147.64050293,-22.8239021301],"type":"Point"}
}