{
  "type": "Feature",
  "properties": {
    "addr:full":"Level 3 70 Castlereagh St Sydney NSW 2000",
    "addr:housenumber":"70",
    "addr:postcode":"2000",
    "addr:street":"Castlereagh St",
    "iso:country":"AU",
    "sg:address":"Level 3 70 Castlereagh St",
    "sg:city":"Sydney",
    "sg:classifiers":[
        {
            "category":"Health Services",
            "subcategory":"Optometrist",
            "type":"Services"
        }
    ],
    "sg:phone":"+61 2 9233 4944",
    "sg:postcode":"2000",
    "sg:province":"NSW",
    "wof:name":"Jody Glasser",
    "wof:placetype":"venue"
},
  "geometry": {"coordinates":[151.20985412600001,-33.8689956665],"type":"Point"}
}