{
  "type": "Feature",
  "properties": {
    "addr:full":"56 Maritana Crs Thomastown VIC 3074",
    "addr:housenumber":"56",
    "addr:postcode":"3074",
    "addr:street":"Maritana Crs",
    "iso:country":"AU",
    "sg:address":"56 Maritana Crs",
    "sg:city":"Thomastown",
    "sg:classifiers":[
        {
            "category":"Train Station",
            "subcategory":"Light Rail",
            "type":"Transportation"
        }
    ],
    "sg:phone":"+61 3 9466 3771",
    "sg:postcode":"3074",
    "sg:province":"VIC",
    "sg:tags":[
        "equipment",
        "energy",
        "solar"
    ],
    "wof:name":"AAA Solar Power design",
    "wof:placetype":"venue"
},
  "geometry": {"coordinates":[145.01148986800001,-37.6832199097],"type":"Point"}
}