{
  "type": "Feature",
  "properties": {
    "addr:full":"PO Box 10 Leppington NSW 2171",
    "addr:postcode":"2171",
    "iso:country":"AU",
    "sg:address":"PO Box 10",
    "sg:city":"Leppington",
    "sg:classifiers":[
        {
            "category":"Shopping",
            "subcategory":"Party Supplies",
            "type":"Retail Goods"
        }
    ],
    "sg:phone":"+61 2 9820 6626",
    "sg:postcode":"2171",
    "sg:province":"NSW",
    "sg:tags":[
        "children's"
    ],
    "wof:name":"Fastlane Karting",
    "wof:placetype":"venue"
},
  "geometry": {"coordinates":[150.846237183,-33.9284286499],"type":"Point"}
}