{
  "type": "Feature",
  "properties": {
    "addr:full":"PO Box 64 Highett VIC 3190",
    "addr:postcode":"3190",
    "iso:country":"AU",
    "sg:address":"PO Box 64",
    "sg:city":"Highett",
    "sg:classifiers":[
        {
            "category":"Communications",
            "type":"Services"
        }
    ],
    "sg:phone":"+61 3 9502 4085",
    "sg:postcode":"3190",
    "sg:province":"VIC",
    "sg:tags":[
        "antenna"
    ],
    "wof:name":"Globetrotter Digital Solutions",
    "wof:placetype":"venue"
},
  "geometry": {"coordinates":[145.04006957999999,-37.9506187439],"type":"Point"}
}