{
  "type": "Feature",
  "properties": {
    "iso:country":"AU",
    "sg:address":"1 Conrad Pl",
    "sg:city":"Fulham Gardens",
    "sg:classifiers":[
        {
            "category":"Arts & Performance",
            "subcategory":"Dance",
            "type":"Entertainment"
        }
    ],
    "sg:phone":"+61 411 294 070",
    "sg:postcode":"5024",
    "sg:province":"SA",
    "sg:tags":[
        "theatrical",
        "ballet",
        "tuition"
    ],
    "wof:name":"Visual Energy Studios",
    "wof:placetype":"venue"
},
  "geometry": {"coordinates":[138.506515503,-34.917804718],"type":"Point"}
}