{
  "type": "Feature",
  "properties": {
    "iso:country":"AU",
    "sg:address":"32 Hartnett Drv",
    "sg:city":"Seaford",
    "sg:classifiers":[
        {
            "category":"Banks & Credit Unions",
            "subcategory":"Investment Brokerage",
            "type":"Services"
        }
    ],
    "sg:phone":"+61 3 9776 9111",
    "sg:postcode":"3198",
    "sg:province":"VIC",
    "sg:tags":[
        "broker"
    ],
    "wof:name":"Bartercard",
    "wof:placetype":"venue"
},
  "geometry": {"coordinates":[145.141159058,-38.1140136719],"type":"Point"}
}