{
  "type": "Feature",
  "properties": {
    "addr:full":"3 Golders Green La Kingsley WA 6026",
    "addr:housenumber":"3",
    "addr:postcode":"6026",
    "addr:street":"Golders Green La",
    "iso:country":"AU",
    "sg:address":"3 Golders Green La",
    "sg:city":"Kingsley",
    "sg:classifiers":[
        {
            "category":"Autos & Motor Vehicles",
            "subcategory":"Recreational Vehicle Sales",
            "type":"Retail Goods"
        }
    ],
    "sg:phone":"+61 8 9409 8082",
    "sg:postcode":"6026",
    "sg:province":"WA",
    "sg:tags":[
        "industrial",
        "sewing",
        "contractor"
    ],
    "wof:name":"Rhapsody Contractors",
    "wof:placetype":"venue"
},
  "geometry": {"coordinates":[115.785499573,-31.8037643433],"type":"Point"}
}