{
  "type": "Feature",
  "properties": {
    "iso:country":"AU",
    "sg:address":"31 Lake St",
    "sg:city":"Northbridge",
    "sg:classifiers":[
        {
            "category":"Recreation",
            "subcategory":"Amusement Park",
            "type":"Entertainment"
        }
    ],
    "sg:phone":"+61 8 9328 7115",
    "sg:postcode":"6003",
    "sg:province":"WA",
    "wof:name":"Timezone",
    "wof:placetype":"venue"
},
  "geometry": {"coordinates":[115.85674285899999,-31.9476680756],"type":"Point"}
}