{
  "type": "Feature",
  "properties": {
    "iso:country":"AU",
    "sg:address":"620 Newcastle St",
    "sg:city":"Leederville",
    "sg:classifiers":[
        {
            "category":"Professional",
            "subcategory":"Accounting & Tax Preparation",
            "type":"Services"
        }
    ],
    "sg:phone":"+61 8 9227 0055",
    "sg:postcode":"6007",
    "sg:province":"WA",
    "sg:tags":[
        "consultant",
        "taxation"
    ],
    "wof:name":"Galluccio Griggs",
    "wof:placetype":"venue"
},
  "geometry": {"coordinates":[115.844909668,-31.9386825562],"type":"Point"}
}