{
  "type": "Feature",
  "properties": {
    "addr:full":"Cnr Challenger Ave & Meares Ave Parmelia WA 6167",
    "addr:postcode":"6167",
    "addr:street":"Challenger Ave & Meares Ave",
    "iso:country":"AU",
    "sg:address":"Cnr Challenger Ave & Meares Ave",
    "sg:city":"Parmelia",
    "sg:classifiers":[
        {
            "category":"Autos & Motor Vehicles",
            "subcategory":"Fuel & Gas Station",
            "type":"Retail Goods"
        }
    ],
    "sg:phone":"+61 8 9419 4494",
    "sg:postcode":"6167",
    "sg:province":"WA",
    "wof:name":"Gull Petroleum (WA) Pty Ltd",
    "wof:placetype":"venue"
},
  "geometry": {"coordinates":[115.825104,-32.250126],"type":"Point"}
}