{
  "type": "Feature",
  "properties": {
    "addr:full":"Cnr of Trower Rd & Vanderlin Drive Casuarina NT 0810",
    "addr:postcode":"nt 0810",
    "addr:street":"Rd & Vanderlin Drive",
    "iso:country":"AU",
    "sg:address":"Cnr of Trower Rd",
    "sg:city":"& Vanderlin Drive Casuarina",
    "sg:classifiers":[
        {
            "category":"Food & Beverages",
            "subcategory":"Bakery",
            "type":"Retail Goods"
        }
    ],
    "sg:phone":"+61 8 8947 9000",
    "sg:postcode":"0810",
    "sg:province":"NT",
    "sg:tags":[
        "cake",
        "shop",
        "pastry"
    ],
    "wof:name":"The Cheesecake Shop",
    "wof:placetype":"venue"
},
  "geometry": {"coordinates":[130.88352966299999,-12.3699035645],"type":"Point"}
}