{
  "type": "Feature",
  "properties": {
    "iso:country":"AU",
    "sg:address":"30 Park West Rd",
    "sg:city":"Eltham",
    "sg:classifiers":[
        {
            "category":"Professional",
            "subcategory":"Management & Consulting",
            "type":"Services"
        }
    ],
    "sg:phone":"+61 3 9431 4286",
    "sg:postcode":"3095",
    "sg:province":"VIC",
    "sg:tags":[
        "consultant",
        "migration"
    ],
    "wof:name":"Wallis Karren+",
    "wof:placetype":"venue"
},
  "geometry": {"coordinates":[145.15655517600001,-37.7056617737],"type":"Point"}
}