{
  "type": "Feature",
  "properties": {
    "addr:full":"22 Trainers Drv Kilmore VIC 3764",
    "addr:housenumber":"22",
    "addr:postcode":"3764",
    "addr:street":"Trainers Drv",
    "iso:country":"AU",
    "sg:address":"22 Trainers Drv",
    "sg:city":"Kilmore",
    "sg:classifiers":[
        {
            "category":"Building & Trades",
            "subcategory":"Cleaning & Sanitation",
            "type":"Services"
        }
    ],
    "sg:phone":"+61 3 5782 2328",
    "sg:postcode":"3764",
    "sg:province":"VIC",
    "sg:tags":[
        "industrial",
        "commercial",
        "contractor"
    ],
    "wof:name":"Puraclean Cleaning Service",
    "wof:placetype":"venue"
},
  "geometry": {"coordinates":[144.96841430699999,-37.2733421326],"type":"Point"}
}