{
  "type": "Feature",
  "properties": {
    "addr:full":"110 Lane Cove Rd Ryde NSW 2112",
    "addr:housenumber":"110",
    "addr:postcode":"2112",
    "addr:street":"Lane Cove Rd",
    "iso:country":"AU",
    "sg:address":"110 Lane Cove Rd",
    "sg:city":"Ryde",
    "sg:classifiers":[
        {
            "category":"Retail",
            "subcategory":"Auto Repair",
            "type":"Services"
        }
    ],
    "sg:phone":"+61 2 9870 7590",
    "sg:postcode":"2112",
    "sg:province":"NSW",
    "sg:tags":[
        "repairer",
        "motor",
        "engineer"
    ],
    "wof:name":"R & M Mechnical Workshop",
    "wof:placetype":"venue"
},
  "geometry": {"coordinates":[151.11453247099999,-33.798286438],"type":"Point"}
}