{
  "type": "Feature",
  "properties": {
    "iso:country":"AU",
    "sg:address":"24 Knutsford St",
    "sg:city":"Fremantle",
    "sg:classifiers":[
        {
            "category":"Professional",
            "subcategory":"Business Services",
            "type":"Services"
        }
    ],
    "sg:phone":"+61 8 9430 4633",
    "sg:postcode":"6160",
    "sg:province":"WA",
    "sg:tags":[
        "exporter"
    ],
    "wof:name":"Austfish Pty Ltd",
    "wof:placetype":"venue"
},
  "geometry": {"coordinates":[115.76254299999999,-32.052853],"type":"Point"}
}