{
  "type": "Feature",
  "properties": {
    "addr:full":"338 Waverley Rd Malvern East VIC 3145",
    "addr:housenumber":"338",
    "addr:postcode":"3145",
    "addr:street":"Waverley Rd",
    "iso:country":"AU",
    "sg:address":"338 Waverley Rd",
    "sg:city":"Malvern East",
    "sg:classifiers":[
        {
            "category":"Food & Beverages",
            "subcategory":"Bakery",
            "type":"Retail Goods"
        }
    ],
    "sg:phone":"+61 3 9571 5420",
    "sg:postcode":"3145",
    "sg:province":"VIC",
    "sg:tags":[
        "baker"
    ],
    "wof:name":"Loafers Bakery & Deli",
    "wof:placetype":"venue"
},
  "geometry": {"coordinates":[145.05906677199999,-37.8773956299],"type":"Point"}
}