{
  "type": "Feature",
  "properties": {
    "addr:full":"Suite 804, Level 8, 32 York St Sydney NSW 2000",
    "addr:housenumber":"32",
    "addr:postcode":"2000",
    "addr:street":"804;York St",
    "iso:country":"AU",
    "sg:address":"Suite 804, Level 8, 32 York St",
    "sg:city":"Sydney",
    "sg:classifiers":[
        {
            "category":"Travel",
            "subcategory":"Travel Agent",
            "type":"Entertainment"
        }
    ],
    "sg:phone":"+61 2 9299 9973",
    "sg:postcode":"2000",
    "sg:province":"NSW",
    "sg:tags":[
        "consultant"
    ],
    "wof:name":"Australian Andean Adventures",
    "wof:placetype":"venue"
},
  "geometry": {"coordinates":[151.20622253400001,-33.8688354492],"type":"Point"}
}