{
  "type": "Feature",
  "properties": {
    "iso:country":"AU",
    "sg:address":"414 Stoney Creek Rd",
    "sg:city":"Kingsgrove",
    "sg:classifiers":[
        {
            "category":"Health Services",
            "subcategory":"Chiropractor",
            "type":"Services"
        }
    ],
    "sg:phone":"+61 2 9150 5200",
    "sg:postcode":"2208",
    "sg:province":"NSW",
    "wof:name":"Goldsworthy Simon",
    "wof:placetype":"venue"
},
  "geometry": {"coordinates":[151.092514,-33.950981],"type":"Point"}
}