{
  "type": "Feature",
  "properties": {
    "iso:country":"AU",
    "sg:address":"50 Topp Rd",
    "sg:city":"Tonimbuk",
    "sg:classifiers":[
        {
            "category":"Education",
            "subcategory":"Vocational School",
            "type":"Public Place"
        }
    ],
    "sg:phone":"+61 425 381 867",
    "sg:postcode":"3815",
    "sg:province":"VIC",
    "sg:tags":[
        "tafe",
        "college",
        "training"
    ],
    "wof:name":"Indonesian Internship",
    "wof:placetype":"venue"
},
  "geometry": {"coordinates":[145.714005,-38.034176],"type":"Point"}
}