{
  "type": "Feature",
  "properties": {
    "addr:full":"103 Chapel Rd Keysborough VIC 3173",
    "addr:housenumber":"103",
    "addr:postcode":"3173",
    "addr:street":"Chapel Rd",
    "iso:country":"AU",
    "sg:address":"103 Chapel Rd",
    "sg:city":"Keysborough",
    "sg:classifiers":[
        {
            "category":"Building & Trades",
            "subcategory":"Plumbing",
            "type":"Services"
        }
    ],
    "sg:phone":"+61 3 9798 3375",
    "sg:postcode":"3173",
    "sg:province":"VIC",
    "sg:tags":[
        "plumber",
        "gasfitters"
    ],
    "wof:name":"Alderbrook Plumbing",
    "wof:placetype":"venue"
},
  "geometry": {"coordinates":[145.161621094,-38.0014419556],"type":"Point"}
}