{
  "type": "Feature",
  "properties": {
    "addr:full":"70 Charles St Prahran VIC 3181",
    "addr:housenumber":"70",
    "addr:postcode":"3181",
    "addr:street":"Charles St",
    "iso:country":"AU",
    "sg:address":"70 Charles St",
    "sg:city":"Prahran",
    "sg:classifiers":[
        {
            "category":"Travel",
            "subcategory":"Hostel",
            "type":"Entertainment"
        }
    ],
    "sg:phone":"+61 3 9510 6100",
    "sg:postcode":"3181",
    "sg:province":"VIC",
    "sg:tags":[
        "home"
    ],
    "wof:name":"MECWA Sir Donald & Lady Trescowthick Centre",
    "wof:placetype":"venue"
},
  "geometry": {"coordinates":[144.98945617699999,-37.8480911255],"type":"Point"}
}