{
  "type": "Feature",
  "properties": {
    "addr:full":"6 Industry Rd McGraths Hill NSW 2756",
    "addr:housenumber":"6",
    "addr:postcode":"2756",
    "addr:street":"Industry Rd",
    "iso:country":"AU",
    "sg:address":"6 Industry Rd",
    "sg:city":"McGraths Hill",
    "sg:classifiers":[
        {
            "category":"Retail",
            "subcategory":"Auto Repair",
            "type":"Services"
        }
    ],
    "sg:phone":"+61 2 4577 6553",
    "sg:postcode":"2756",
    "sg:province":"NSW",
    "sg:tags":[
        "camper-trailers",
        "caravan",
        "servicing"
    ],
    "sg:website":"http://www.richmondcaravans.com.au",
    "wof:name":"Richmond Caravans (Aust) P/L",
    "wof:placetype":"venue"
},
  "geometry": {"coordinates":[150.84254455600001,-33.6305198669],"type":"Point"}
}