{
  "type": "Feature",
  "properties": {
    "iso:country":"AU",
    "sg:address":"78 Lithgow St",
    "sg:city":"Campbelltown",
    "sg:classifiers":[
        {
            "category":"Social Services",
            "subcategory":"Retirement Home",
            "type":"Services"
        }
    ],
    "sg:phone":"+61 2 4625 5513",
    "sg:postcode":"2560",
    "sg:province":"NSW",
    "sg:tags":[
        "accommodation",
        "special"
    ],
    "wof:name":"Drug & Alcohol Womens Network (D.A.W.N)",
    "wof:placetype":"venue"
},
  "geometry": {"coordinates":[150.81541442899999,-34.0691261292],"type":"Point"}
}