{
  "type": "Feature",
  "properties": {
    "addr:full":"40 Campbell St Bowen Hills QLD 4006",
    "addr:housenumber":"40",
    "addr:postcode":"4006",
    "addr:street":"Campbell St",
    "iso:country":"AU",
    "sg:address":"40 Campbell St",
    "sg:city":"Bowen Hills",
    "sg:classifiers":[
        {
            "category":"Home & Garden",
            "subcategory":"Building Materials",
            "type":"Retail Goods"
        }
    ],
    "sg:phone":"+61 7 3270 1810",
    "sg:postcode":"4006",
    "sg:province":"QLD",
    "sg:tags":[
        "shutter",
        "roller",
        "grille"
    ],
    "wof:name":"Kone",
    "wof:placetype":"venue"
},
  "geometry": {"coordinates":[153.03497314399999,-27.4474601746],"type":"Point"}
}