{
  "type": "Feature",
  "properties": {
    "addr:full":"1b Murrawal Rd Stanwell Park NSW 2508",
    "addr:housenumber":"1b",
    "addr:postcode":"2508",
    "addr:street":"Murrawal Rd",
    "iso:country":"AU",
    "sg:address":"1b Murrawal Rd",
    "sg:city":"Stanwell Park",
    "sg:classifiers":[
        {
            "category":"Building & Trades",
            "subcategory":"Construction",
            "type":"Services"
        }
    ],
    "sg:phone":"+61 2 4294 1856",
    "sg:postcode":"2508",
    "sg:province":"NSW",
    "sg:tags":[
        "contractor"
    ],
    "wof:name":"T & J Hunter Constructions Pty Ltd",
    "wof:placetype":"venue"
},
  "geometry": {"coordinates":[150.982697,-34.231873],"type":"Point"}
}