{
  "type": "Feature",
  "properties": {
    "iso:country":"AU",
    "sg:address":"Shop 10 Angel Pl",
    "sg:city":"Sydney",
    "sg:classifiers":[
        {
            "category":"Cafe",
            "type":"Food & Drink"
        }
    ],
    "sg:phone":"+61 2 9232 0188",
    "sg:postcode":"2000",
    "sg:province":"NSW",
    "wof:name":"Angel Cafe Bar-Licensed",
    "wof:placetype":"venue"
},
  "geometry": {"coordinates":[151.20799255399999,-33.8670578003],"type":"Point"}
}