{
  "type": "Feature",
  "properties": {
    "iso:country":"AU",
    "sg:address":"1/ 6 June St",
    "sg:city":"Coffs Harbour",
    "sg:classifiers":[
        {
            "category":"Retail",
            "subcategory":"Auto Repair",
            "type":"Services"
        }
    ],
    "sg:phone":"+61 2 6652 4986",
    "sg:postcode":"2450",
    "sg:province":"NSW",
    "sg:tags":[
        "repairer",
        "motor",
        "engineer"
    ],
    "wof:name":"Repco Authorised Service",
    "wof:placetype":"venue"
},
  "geometry": {"coordinates":[153.115204,-30.290562],"type":"Point"}
}