{
  "type": "Feature",
  "properties": {
    "addr:full":"Bundaberg Plaza Maryborough St Bundaberg QLD 4670",
    "addr:postcode":"4670",
    "addr:street":"St",
    "iso:country":"AU",
    "sg:address":"Bundaberg Plaza Maryborough St",
    "sg:city":"Bundaberg",
    "sg:classifiers":[
        {
            "category":"Personal",
            "subcategory":"Shoe Repair & Shine",
            "type":"Services"
        }
    ],
    "sg:phone":"+61 7 4152 9777",
    "sg:postcode":"4670",
    "sg:province":"QLD",
    "sg:tags":[
        "footwear"
    ],
    "wof:name":"Country Cobblers The",
    "wof:placetype":"venue"
},
  "geometry": {"coordinates":[152.34671020499999,-24.8670425415],"type":"Point"}
}