{
  "type": "Feature",
  "properties": {
    "addr:full":"43 Wheelers La Dubbo NSW 2830",
    "addr:housenumber":"43",
    "addr:postcode":"2830",
    "addr:street":"Wheelers La",
    "iso:country":"AU",
    "sg:address":"43 Wheelers La",
    "sg:city":"Dubbo",
    "sg:classifiers":[
        {
            "category":"Transit Center",
            "subcategory":"Freight",
            "type":"Transportation"
        }
    ],
    "sg:phone":"+61 2 6882 1745",
    "sg:postcode":"2830",
    "sg:province":"NSW",
    "sg:tags":[
        "forklift",
        "truck"
    ],
    "wof:name":"Dubbo Fork Truck Service",
    "wof:placetype":"venue"
},
  "geometry": {"coordinates":[148.631256103,-32.2445793152],"type":"Point"}
}