{
  "type": "Feature",
  "properties": {
    "addr:full":"Childers Rd Biggenden QLD 4621",
    "addr:postcode":"4621",
    "addr:street":"Childers Rd",
    "iso:country":"AU",
    "sg:address":"Childers Rd",
    "sg:city":"Biggenden",
    "sg:classifiers":[
        {
            "category":"Sports & Exercise",
            "subcategory":"Golf",
            "type":"Entertainment"
        }
    ],
    "sg:phone":"+61 7 4127 1454",
    "sg:postcode":"4621",
    "sg:province":"QLD",
    "sg:tags":[
        "club"
    ],
    "wof:name":"Biggenden Golf Club",
    "wof:placetype":"venue"
},
  "geometry": {"coordinates":[152.04362499999999,-25.509911],"type":"Point"}
}