{
  "type": "Feature",
  "properties": {
    "addr:full":"77 Perrin St Robinvale VIC 3549",
    "addr:housenumber":"77",
    "addr:postcode":"3549",
    "addr:street":"Perrin St",
    "iso:country":"AU",
    "sg:address":"77 Perrin St",
    "sg:city":"Robinvale",
    "sg:classifiers":[
        {
            "category":"Professional",
            "subcategory":"Business Services",
            "type":"Services"
        }
    ],
    "sg:phone":"+61 3 5051 8600",
    "sg:postcode":"3549",
    "sg:province":"VIC",
    "sg:tags":[
        "small",
        "advisory"
    ],
    "wof:name":"Xcel Management Services",
    "wof:placetype":"venue"
},
  "geometry": {"coordinates":[142.772705078,-34.5840072632],"type":"Point"}
}