{
  "type": "Feature",
  "properties": {
    "addr:full":"Greta South Rd Molyullah VIC 3673",
    "addr:postcode":"3673",
    "addr:street":"Greta South Rd",
    "iso:country":"AU",
    "sg:address":"Greta South Rd",
    "sg:city":"Molyullah",
    "sg:classifiers":[
        {
            "category":"Building & Trades",
            "subcategory":"Landscaping Services",
            "type":"Services"
        }
    ],
    "sg:phone":"+61 3 5766 6333",
    "sg:postcode":"3673",
    "sg:province":"VIC",
    "sg:tags":[
        "grazier"
    ],
    "wof:name":"Collins D T",
    "wof:placetype":"venue"
},
  "geometry": {"coordinates":[146.14231899999999,-36.526688],"type":"Point"}
}