{
  "type": "Feature",
  "properties": {
    "iso:country":"AU",
    "sg:address":"151 Railway Pde",
    "sg:city":"Thorneside",
    "sg:classifiers":[
        {
            "category":"Home & Garden",
            "subcategory":"Garden Supply",
            "type":"Retail Goods"
        }
    ],
    "sg:phone":"+61 7 3207 2793",
    "sg:postcode":"4158",
    "sg:province":"QLD",
    "sg:tags":[
        "equipment"
    ],
    "wof:name":"Peter's Glen",
    "wof:placetype":"venue"
},
  "geometry": {"coordinates":[153.195114136,-27.4879074097],"type":"Point"}
}