{
  "type": "Feature",
  "properties": {
    "addr:full":"Wood St Thomastown VIC 3074",
    "addr:postcode":"3074",
    "addr:street":"Wood St",
    "iso:country":"AU",
    "sg:address":"Wood St",
    "sg:city":"Thomastown",
    "sg:classifiers":[
        {
            "category":"Building & Trades",
            "subcategory":"Landscaping Services",
            "type":"Services"
        }
    ],
    "sg:phone":"+61 3 9465 5523",
    "sg:postcode":"3074",
    "sg:province":"VIC",
    "sg:tags":[
        "market"
    ],
    "wof:name":"Thomas Town Market",
    "wof:placetype":"venue"
},
  "geometry": {"coordinates":[145.02520751899999,-37.6930465698],"type":"Point"}
}