{
  "type": "Feature",
  "properties": {
    "iso:country":"AU",
    "sg:address":"2 16 Mayfair Pl",
    "sg:city":"Forster",
    "sg:classifiers":[
        {
            "category":"Professional",
            "subcategory":"Printing & Photocopies",
            "type":"Services"
        }
    ],
    "sg:phone":"+61 2 6555 7357",
    "sg:postcode":"2428",
    "sg:province":"NSW",
    "sg:tags":[
        "photocopier"
    ],
    "wof:name":"Laser Copier Parts",
    "wof:placetype":"venue"
},
  "geometry": {"coordinates":[152.520187,-32.197468],"type":"Point"}
}