{
  "type": "Feature",
  "properties": {
    "addr:full":"25 Morgan St Cannington WA 6107",
    "addr:housenumber":"25",
    "addr:postcode":"6107",
    "addr:street":"Morgan St",
    "iso:country":"AU",
    "sg:address":"25 Morgan St",
    "sg:city":"Cannington",
    "sg:classifiers":[
        {
            "category":"Building & Trades",
            "subcategory":"Construction",
            "type":"Services"
        }
    ],
    "sg:phone":"+61 8 9356 2877",
    "sg:postcode":"6107",
    "sg:province":"WA",
    "sg:tags":[
        "bitumen",
        "paving",
        "asphalt"
    ],
    "wof:name":"Rumenos Earthmoving",
    "wof:placetype":"venue"
},
  "geometry": {"coordinates":[115.94834136999999,-32.0209999084],"type":"Point"}
}