{
  "type": "Feature",
  "properties": {
    "addr:full":"44 Pasley St South Yarra VIC 3141",
    "addr:housenumber":"44",
    "addr:postcode":"3141",
    "addr:street":"Pasley St",
    "iso:country":"AU",
    "sg:address":"44 Pasley St",
    "sg:city":"South Yarra",
    "sg:classifiers":[
        {
            "category":"Health Services",
            "subcategory":"Health Practitioner",
            "type":"Services"
        }
    ],
    "sg:phone":"+61 3 9459 3669",
    "sg:postcode":"3141",
    "sg:province":"VIC",
    "sg:tags":[
        "psychologist"
    ],
    "wof:name":"Say Stephen",
    "wof:placetype":"venue"
},
  "geometry": {"coordinates":[144.98460388199999,-37.8428230286],"type":"Point"}
}