{
  "type": "Feature",
  "properties": {
    "addr:full":"Level 1/ 10 Park St Mona Vale NSW 2103",
    "addr:housenumber":"/ 10",
    "addr:postcode":"2103",
    "addr:street":"Park St",
    "iso:country":"AU",
    "sg:address":"Level 1/ 10 Park St",
    "sg:city":"Mona Vale",
    "sg:classifiers":[
        {
            "category":"Organizations",
            "subcategory":"Non-profit Organization",
            "type":"Services"
        }
    ],
    "sg:phone":"+61 2 9979 7677",
    "sg:postcode":"2103",
    "sg:province":"NSW",
    "sg:tags":[
        "support",
        "disability",
        "organisation"
    ],
    "wof:name":"Community Care Northern Beaches",
    "wof:placetype":"venue"
},
  "geometry": {"coordinates":[151.30526733400001,-33.6764183044],"type":"Point"}
}