{
  "type": "Feature",
  "properties": {
    "iso:country":"AU",
    "sg:address":"17 Newton Rd",
    "sg:city":"Wetherill Park",
    "sg:classifiers":[
        {
            "category":"Retail",
            "subcategory":"Storage",
            "type":"Services"
        }
    ],
    "sg:phone":"+61 2 9756 1755",
    "sg:postcode":"2164",
    "sg:province":"NSW",
    "sg:tags":[
        "shelving",
        "system"
    ],
    "wof:name":"Storetek",
    "wof:placetype":"venue"
},
  "geometry": {"coordinates":[150.893035889,-33.8465690613],"type":"Point"}
}