{
  "type": "Feature",
  "properties": {
    "iso:country":"AU",
    "sg:address":"King St",
    "sg:city":"Boort",
    "sg:classifiers":[
        {
            "category":"Social Services",
            "subcategory":"Child Care",
            "type":"Services"
        }
    ],
    "sg:phone":"+61 3 5455 2192",
    "sg:postcode":"3537",
    "sg:province":"VIC",
    "sg:tags":[
        "support",
        "health"
    ],
    "wof:name":"Maternal & Child Health Centres",
    "wof:placetype":"venue"
},
  "geometry": {"coordinates":[143.72706600000001,-36.116161],"type":"Point"}
}