{
  "type": "Feature",
  "properties": {
    "addr:full":"232 Koornang Rd Carnegie VIC 3163",
    "addr:housenumber":"232",
    "addr:postcode":"3163",
    "addr:street":"Koornang Rd",
    "iso:country":"AU",
    "sg:address":"232 Koornang Rd",
    "sg:city":"Carnegie",
    "sg:classifiers":[
        {
            "category":"Health Services",
            "subcategory":"Dentist",
            "type":"Services"
        }
    ],
    "sg:phone":"+61 1300 661 159",
    "sg:postcode":"3163",
    "sg:province":"VIC",
    "wof:name":"A Whiter Smiley",
    "wof:placetype":"venue"
},
  "geometry": {"coordinates":[145.056365967,-37.8935928345],"type":"Point"}
}