{
  "type": "Feature",
  "properties": {
    "addr:full":"Unit 27, 42- 44 Abel St Penrith South NSW 2750",
    "addr:housenumber":"42 44",
    "addr:postcode":"2750",
    "addr:street":"Abel St",
    "iso:country":"AU",
    "sg:address":"Unit 27, 42- 44 Abel St",
    "sg:city":"Penrith South",
    "sg:classifiers":[
        {
            "category":"Building & Trades",
            "subcategory":"Landscaping Services",
            "type":"Services"
        }
    ],
    "sg:phone":"+61 1300 304 420",
    "sg:postcode":"2750",
    "sg:province":"NSW",
    "sg:tags":[
        "consultant"
    ],
    "wof:name":"Urban Approvals Pty Ltd",
    "wof:placetype":"venue"
},
  "geometry": {"coordinates":[150.68363952600001,-33.7652587891],"type":"Point"}
}