{
  "type": "Feature",
  "properties": {
    "addr:full":"Shop 9, Randall Court, 214 Kingston Rd Slacks Creek QLD 4127",
    "addr:housenumber":"shop 9;214",
    "addr:postcode":"4127",
    "addr:street":"Randall;Kingston Rd",
    "iso:country":"AU",
    "sg:address":"Shop 9, Randall Court, 214 Kingston Rd",
    "sg:city":"Slacks Creek",
    "sg:classifiers":[
        {
            "category":"Education",
            "subcategory":"Dance Studio",
            "type":"Public Place"
        }
    ],
    "sg:phone":"+61 409 750 949",
    "sg:postcode":"4127",
    "sg:province":"QLD",
    "sg:tags":[
        "venue",
        "tuition"
    ],
    "sg:website":"http://www.freewebs.com/clubrumba",
    "wof:name":"Club Rumba Social Dance Tuition",
    "wof:placetype":"venue"
},
  "geometry": {"coordinates":[153.118850708,-27.6403999329],"type":"Point"}
}