{
  "type": "Feature",
  "properties": {
    "iso:country":"AU",
    "sg:address":"23 Labouchere Rd",
    "sg:city":"South Perth",
    "sg:classifiers":[
        {
            "category":"Professional",
            "subcategory":"Computer Services",
            "type":"Services"
        }
    ],
    "sg:phone":"+61 8 9368 6880",
    "sg:postcode":"6151",
    "sg:province":"WA",
    "sg:tags":[
        "information"
    ],
    "wof:name":"Delaney, Woods & Associates",
    "wof:placetype":"venue"
},
  "geometry": {"coordinates":[115.851013,-31.974133],"type":"Point"}
}