{
  "type": "Feature",
  "properties": {
    "iso:country":"AU",
    "sg:address":"54 Telford St",
    "sg:city":"Virginia",
    "sg:classifiers":[
        {
            "category":"Home & Garden",
            "subcategory":"Building Materials",
            "type":"Retail Goods"
        }
    ],
    "sg:phone":"+61 7 3265 1999",
    "sg:postcode":"4014",
    "sg:province":"QLD",
    "sg:tags":[
        "concrete",
        "panel",
        "pre-cast"
    ],
    "wof:name":"Girotto Precast Concrete",
    "wof:placetype":"venue"
},
  "geometry": {"coordinates":[153.065185547,-27.3682250977],"type":"Point"}
}