{
  "type": "Feature",
  "properties": {
    "addr:full":"PO Box 1118 Glenelg South SA 5045",
    "addr:postcode":"5045",
    "iso:country":"AU",
    "sg:address":"PO Box 1118",
    "sg:city":"Glenelg South",
    "sg:classifiers":[
        {
            "category":"Professional",
            "subcategory":"Art Services",
            "type":"Services"
        }
    ],
    "sg:phone":"+61 8 8295 7203",
    "sg:postcode":"5045",
    "sg:province":"SA",
    "sg:tags":[
        "decorator",
        "painter"
    ],
    "wof:name":"Bay Painting Service",
    "wof:placetype":"venue"
},
  "geometry": {"coordinates":[138.517166,-34.986511],"type":"Point"}
}