{
  "type": "Feature",
  "properties": {
    "addr:full":"130 Hannan St Kalgoorlie WA 6430",
    "addr:housenumber":"130",
    "addr:postcode":"6430",
    "addr:street":"Hannan St",
    "iso:country":"AU",
    "sg:address":"130 Hannan St",
    "sg:city":"Kalgoorlie",
    "sg:classifiers":[
        {
            "category":"Health Services",
            "subcategory":"Medical Lab",
            "type":"Services"
        }
    ],
    "sg:phone":"+61 8 9091 1802",
    "sg:postcode":"6430",
    "sg:province":"WA",
    "sg:tags":[
        "laboratory",
        "dental"
    ],
    "wof:name":"Goldfields Denture Service",
    "wof:placetype":"venue"
},
  "geometry": {"coordinates":[121.467391968,-30.7519207001],"type":"Point"}
}