{
  "type": "Feature",
  "properties": {
    "addr:full":"30 High St Ashgrove QLD 4060",
    "addr:housenumber":"30",
    "addr:postcode":"4060",
    "addr:street":"High St",
    "iso:country":"AU",
    "sg:address":"30 High St",
    "sg:city":"Ashgrove",
    "sg:classifiers":[
        {
            "category":"Shopping",
            "subcategory":"Antiques",
            "type":"Retail Goods"
        }
    ],
    "sg:phone":"+61 7 3366 8228",
    "sg:postcode":"4060",
    "sg:province":"QLD",
    "sg:tags":[
        "collectable",
        "memorabilia"
    ],
    "wof:name":"Nick Nack Nook",
    "wof:placetype":"venue"
},
  "geometry": {"coordinates":[152.989776611,-27.4330921173],"type":"Point"}
}