{
  "type": "Feature",
  "properties": {
    "addr:full":"Podium Level 1 500 George St Sydney NSW 2000",
    "addr:housenumber":"1 500",
    "addr:postcode":"2000",
    "addr:street":"George St",
    "iso:country":"AU",
    "sg:address":"Podium Level 1 500 George St",
    "sg:city":"Sydney",
    "sg:classifiers":[
        {
            "category":"Professional",
            "subcategory":"Accounting & Tax Preparation",
            "type":"Services"
        }
    ],
    "sg:phone":"+61 2 9266 2200",
    "sg:postcode":"2000",
    "sg:province":"NSW",
    "sg:tags":[
        "accountant",
        "auditor"
    ],
    "wof:name":"Economos Pty Ltd",
    "wof:placetype":"venue"
},
  "geometry": {"coordinates":[151.207199097,-33.872127533],"type":"Point"}
}