{
  "type": "Feature",
  "properties": {
    "addr:full":"420 Princess Hwy Narre Warren VIC 3805",
    "addr:housenumber":"420",
    "addr:postcode":"3805",
    "addr:street":"Princess Hwy",
    "iso:country":"AU",
    "sg:address":"420 Princess Hwy",
    "sg:city":"Narre Warren",
    "sg:classifiers":[
        {
            "category":"Education",
            "subcategory":"Special Training",
            "type":"Public Place"
        }
    ],
    "sg:phone":"+61 407 357 356",
    "sg:postcode":"3805",
    "sg:province":"VIC",
    "sg:tags":[
        "feldenkrais"
    ],
    "wof:name":"Masterton Katharine",
    "wof:placetype":"venue"
},
  "geometry": {"coordinates":[145.30650299999999,-38.025703],"type":"Point"}
}