{
  "type": "Feature",
  "properties": {
    "addr:full":"5 Enterprise St Molendinar QLD 4214",
    "addr:housenumber":"5",
    "addr:postcode":"4214",
    "addr:street":"Enterprise St",
    "iso:country":"AU",
    "sg:address":"5 Enterprise St",
    "sg:city":"Molendinar",
    "sg:classifiers":[
        {
            "category":"Home & Garden",
            "subcategory":"Carpets & Floor Coverings",
            "type":"Retail Goods"
        }
    ],
    "sg:phone":"+61 7 5597 6011",
    "sg:postcode":"4214",
    "sg:province":"QLD",
    "sg:tags":[
        "tile",
        "wall"
    ],
    "wof:name":"MJS Floorcoverings",
    "wof:placetype":"venue"
},
  "geometry": {"coordinates":[153.37847900400001,-27.9759941101],"type":"Point"}
}