{
  "type": "Feature",
  "properties": {
    "addr:full":"2 Duke St Daylesford VIC 3460",
    "addr:housenumber":"2",
    "addr:postcode":"3460",
    "addr:street":"Duke St",
    "iso:country":"AU",
    "sg:address":"2 Duke St",
    "sg:city":"Daylesford",
    "sg:classifiers":[
        {
            "category":"Health Services",
            "subcategory":"Doctor",
            "type":"Services"
        }
    ],
    "sg:phone":"+61 3 5348 2912",
    "sg:postcode":"3460",
    "sg:province":"VIC",
    "sg:tags":[
        "medical",
        "practitioner"
    ],
    "wof:name":"Stewart G F",
    "wof:placetype":"venue"
},
  "geometry": {"coordinates":[144.14395141599999,-37.3418540955],"type":"Point"}
}