{
  "type": "Feature",
  "properties": {
    "addr:full":"9 Perak St Mona Vale NSW 2103",
    "addr:housenumber":"9",
    "addr:postcode":"2103",
    "addr:street":"Perak St",
    "iso:country":"AU",
    "sg:address":"9 Perak St",
    "sg:city":"Mona Vale",
    "sg:classifiers":[
        {
            "category":"Professional",
            "subcategory":"Art Services",
            "type":"Services"
        }
    ],
    "sg:phone":"+61 2 9999 1805",
    "sg:postcode":"2103",
    "sg:province":"NSW",
    "sg:tags":[
        "picture",
        "frame",
        "framing"
    ],
    "wof:name":"Jackson Frames",
    "wof:placetype":"venue"
},
  "geometry": {"coordinates":[151.308303833,-33.6738700867],"type":"Point"}
}