{
  "type": "Feature",
  "properties": {
    "addr:full":"27 Norman St Woodville SA 5011",
    "addr:housenumber":"27",
    "addr:postcode":"5011",
    "addr:street":"Norman St",
    "iso:country":"AU",
    "sg:address":"27 Norman St",
    "sg:city":"Woodville",
    "sg:classifiers":[
        {
            "category":"Education",
            "subcategory":"Kindergarten",
            "type":"Public Place"
        }
    ],
    "sg:phone":"+61 8 8345 3931",
    "sg:postcode":"5011",
    "sg:province":"SA",
    "sg:tags":[
        "pre-schools"
    ],
    "wof:name":"St Margaret's Kindergarten",
    "wof:placetype":"venue"
},
  "geometry": {"coordinates":[138.539627075,-34.8809509277],"type":"Point"}
}