{
  "type": "Feature",
  "properties": {
    "addr:full":"Cnr Main & Drummond Sts Rutherglen VIC 3685",
    "addr:postcode":"3685",
    "addr:street":"Cnr Main & Drummond Sts",
    "iso:country":"AU",
    "sg:address":"Cnr Main & Drummond Sts",
    "sg:city":"Rutherglen",
    "sg:classifiers":[
        {
            "category":"Travel",
            "subcategory":"Hotels & Motels",
            "type":"Entertainment"
        }
    ],
    "sg:phone":"+61 2 6032 9588",
    "sg:postcode":"3685",
    "sg:province":"VIC",
    "wof:name":"Motel Woongarra",
    "wof:placetype":"venue"
},
  "geometry": {"coordinates":[146.45509338400001,-36.0528640747],"type":"Point"}
}