{
  "type": "Feature",
  "properties": {
    "addr:full":"Lot 5 Western Hwy Ballarat VIC 3350",
    "addr:postcode":"3350",
    "addr:street":"Western Hwy",
    "iso:country":"AU",
    "sg:address":"Lot 5 Western Hwy",
    "sg:city":"Ballarat",
    "sg:classifiers":[
        {
            "category":"Building & Trades",
            "subcategory":"Construction",
            "type":"Services"
        }
    ],
    "sg:phone":"+61 3 5334 2177",
    "sg:postcode":"3350",
    "sg:province":"VIC",
    "sg:tags":[
        "renovation",
        "alterations",
        "extension",
        "contractor"
    ],
    "wof:name":"J G King Pty Ltd Master Builders",
    "wof:placetype":"venue"
},
  "geometry": {"coordinates":[143.893494,-37.545727],"type":"Point"}
}