{
  "type": "Feature",
  "properties": {
    "iso:country":"AU",
    "sg:address":"8 Aberdeen Ave",
    "sg:city":"Benowa",
    "sg:classifiers":[
        {
            "category":"Building & Trades",
            "subcategory":"Construction",
            "type":"Services"
        }
    ],
    "sg:phone":"+61 412 575 753",
    "sg:postcode":"4217",
    "sg:province":"QLD",
    "sg:tags":[
        "contractor"
    ],
    "wof:name":"Home Assured Pty Ltd",
    "wof:placetype":"venue"
},
  "geometry": {"coordinates":[153.398162842,-28.0124206543],"type":"Point"}
}