{
  "type": "Feature",
  "properties": {
    "addr:full":"PO Box 695 Moonah TAS 7009",
    "addr:postcode":"7009",
    "iso:country":"AU",
    "sg:address":"PO Box 695",
    "sg:city":"Moonah",
    "sg:classifiers":[
        {
            "category":"Professional",
            "subcategory":"Detective & Security Services",
            "type":"Services"
        }
    ],
    "sg:phone":"+61 3 6278 3255",
    "sg:postcode":"7009",
    "sg:province":"TAS",
    "sg:tags":[
        "guard",
        "patrol"
    ],
    "wof:name":"Coverall Security Pty Ltd",
    "wof:placetype":"venue"
},
  "geometry": {"coordinates":[147.295455933,-42.8458518982],"type":"Point"}
}