{
  "type": "Feature",
  "properties": {
    "addr:full":"Suite 17 Eton Arc 754- 758 Old Princes Hwy Sutherland NSW 2232",
    "addr:housenumber":"754 758",
    "addr:postcode":"2232",
    "addr:street":"Eton Arc;Old Princes Hwy",
    "iso:country":"AU",
    "sg:address":"Suite 17 Eton Arc 754- 758 Old Princes Hwy",
    "sg:city":"Sutherland",
    "sg:classifiers":[
        {
            "category":"Personal",
            "subcategory":"Massage",
            "type":"Services"
        }
    ],
    "sg:phone":"+61 2 9545 2992",
    "sg:postcode":"2232",
    "sg:province":"NSW",
    "sg:tags":[
        "therapy"
    ],
    "wof:name":"Sutherland Shire Naturopathic Clinic",
    "wof:placetype":"venue"
},
  "geometry": {"coordinates":[151.05807495100001,-34.0314674377],"type":"Point"}
}