{
  "type": "Feature",
  "properties": {
    "addr:full":"Turner Crt Portarlington VIC 3223",
    "addr:postcode":"3223",
    "addr:street":"Turner",
    "iso:country":"AU",
    "sg:address":"Turner Crt",
    "sg:city":"Portarlington",
    "sg:classifiers":[
        {
            "category":"Retail",
            "subcategory":"Event Space",
            "type":"Services"
        }
    ],
    "sg:phone":"+61 3 5259 3202",
    "sg:postcode":"3223",
    "sg:province":"VIC",
    "sg:tags":[
        "venue",
        "reception",
        "wedding"
    ],
    "wof:name":"Portarlington Mill",
    "wof:placetype":"venue"
},
  "geometry": {"coordinates":[144.64686599999999,-38.11359],"type":"Point"}
}