{
  "type": "Feature",
  "properties": {
    "iso:country":"AU",
    "sg:address":"18 Fortune St",
    "sg:city":"South Perth",
    "sg:classifiers":[
        {
            "category":"Health Services",
            "subcategory":"Doctor",
            "type":"Services"
        }
    ],
    "sg:phone":"+61 8 9474 2960",
    "sg:postcode":"6151",
    "sg:province":"WA",
    "sg:tags":[
        "podiatrist"
    ],
    "wof:name":"Anton J Claux",
    "wof:placetype":"venue"
},
  "geometry": {"coordinates":[115.86309799999999,-31.987665],"type":"Point"}
}