{
  "type": "Feature",
  "properties": {
    "addr:full":"U2/ 25 Gillam Drv Kelmscott WA 6111",
    "addr:housenumber":"25",
    "addr:postcode":"6111",
    "addr:street":"U2 /;Gillam Drv",
    "iso:country":"AU",
    "sg:address":"U2/ 25 Gillam Drv",
    "sg:city":"Kelmscott",
    "sg:classifiers":[
        {
            "category":"Fast Food",
            "type":"Food & Drink"
        }
    ],
    "sg:phone":"+61 8 9495 1449",
    "sg:postcode":"6111",
    "sg:province":"WA",
    "sg:tags":[
        "away",
        "take"
    ],
    "wof:name":"Mark's Place",
    "wof:placetype":"venue"
},
  "geometry": {"coordinates":[116.007080078,-32.1281204224],"type":"Point"}
}