{
  "type": "Feature",
  "properties": {
    "iso:country":"AU",
    "sg:address":"112 Beddoes St",
    "sg:city":"Holland Park",
    "sg:classifiers":[
        {
            "category":"Travel",
            "subcategory":"Hostel",
            "type":"Entertainment"
        }
    ],
    "sg:phone":"+61 7 3343 3666",
    "sg:postcode":"4121",
    "sg:province":"QLD",
    "sg:tags":[
        "home"
    ],
    "wof:name":"Southern Cross Care (QLD) Inc",
    "wof:placetype":"venue"
},
  "geometry": {"coordinates":[153.07420349099999,-27.5227775574],"type":"Point"}
}