{
  "type": "Feature",
  "properties": {
    "addr:full":"Suite 15 15 Albert Ave Broadbeach QLD 4218",
    "addr:housenumber":"15",
    "addr:postcode":"4218",
    "addr:street":"Albert Ave",
    "iso:country":"AU",
    "sg:address":"Suite 15 15 Albert Ave",
    "sg:city":"Broadbeach",
    "sg:classifiers":[
        {
            "category":"Organizations",
            "subcategory":"Non-profit Organization",
            "type":"Services"
        }
    ],
    "sg:phone":"+61 7 5527 7716",
    "sg:postcode":"4218",
    "sg:province":"QLD",
    "sg:tags":[
        "support",
        "disability",
        "organisation"
    ],
    "wof:name":"Staff Connections",
    "wof:placetype":"venue"
},
  "geometry": {"coordinates":[153.432174683,-28.0280647278],"type":"Point"}
}