{
  "type": "Feature",
  "properties": {
    "addr:full":"Unit 1 28 Skinner Ave Riverwood NSW 2210",
    "addr:housenumber":"28",
    "addr:postcode":"2210",
    "addr:street":"Skinner Ave",
    "iso:country":"AU",
    "sg:address":"Unit 1 28 Skinner Ave",
    "sg:city":"Riverwood",
    "sg:classifiers":[
        {
            "category":"Manufacturing",
            "subcategory":"Retail Goods",
            "type":"Manufacturing & Wholesale Goods"
        }
    ],
    "sg:phone":"+61 2 9584 2099",
    "sg:postcode":"2210",
    "sg:province":"NSW",
    "sg:tags":[
        "merchant",
        "pump",
        "mfrs"
    ],
    "wof:name":"Ajax Pumps",
    "wof:placetype":"venue"
},
  "geometry": {"coordinates":[151.06277499999999,-33.939922],"type":"Point"}
}