{
  "type": "Feature",
  "properties": {
    "addr:full":"1/ 66 Hassall St Wetherill Park NSW 2164",
    "addr:housenumber":"/ 66",
    "addr:postcode":"2164",
    "addr:street":"Hassall St",
    "iso:country":"AU",
    "sg:address":"1/ 66 Hassall St",
    "sg:city":"Wetherill Park",
    "sg:classifiers":[
        {
            "category":"Autos & Motor Vehicles",
            "subcategory":"Motorcycle Sales",
            "type":"Retail Goods"
        }
    ],
    "sg:phone":"+61 2 9609 1027",
    "sg:postcode":"2164",
    "sg:province":"NSW",
    "sg:tags":[
        "outboard"
    ],
    "wof:name":"A & J Outboard & Boating",
    "wof:placetype":"venue"
},
  "geometry": {"coordinates":[150.912277222,-33.8399429321],"type":"Point"}
}