{
  "type": "Feature",
  "properties": {
    "addr:full":"Level 7/ 12 Castlereagh St Sydney NSW 2000",
    "addr:housenumber":"/ 12",
    "addr:postcode":"2000",
    "addr:street":"Castlereagh St",
    "iso:country":"AU",
    "sg:address":"Level 7/ 12 Castlereagh St",
    "sg:city":"Sydney",
    "sg:classifiers":[
        {
            "category":"Professional",
            "subcategory":"Computer Services",
            "type":"Services"
        }
    ],
    "sg:phone":"+61 2 9224 6200",
    "sg:postcode":"2000",
    "sg:province":"NSW",
    "sg:tags":[
        "package",
        "software"
    ],
    "wof:name":"Acumen Business Solutions",
    "wof:placetype":"venue"
},
  "geometry": {"coordinates":[151.210113525,-33.8669242859],"type":"Point"}
}