{
  "type": "Feature",
  "properties": {
    "addr:full":"84 Pacific Ave Mermaid Beach QLD 4218",
    "addr:housenumber":"84",
    "addr:postcode":"4218",
    "addr:street":"Pacific Ave",
    "iso:country":"AU",
    "sg:address":"84 Pacific Ave",
    "sg:city":"Mermaid Beach",
    "sg:classifiers":[
        {
            "category":"Arena",
            "subcategory":"Sports Club",
            "type":"Entertainment"
        }
    ],
    "sg:phone":"+61 7 5527 7156",
    "sg:postcode":"4218",
    "sg:province":"QLD",
    "sg:tags":[
        "defence",
        "supply",
        "self",
        "instruction",
        "martial art"
    ],
    "sg:website":"http://www.nationaltaekwondo.net",
    "wof:name":"Australian National Tae Kwon-Do",
    "wof:placetype":"venue"
},
  "geometry": {"coordinates":[153.432937622,-28.0629901886],"type":"Point"}
}