{
  "type": "Feature",
  "properties": {
    "addr:full":"415 Golden Four Drv Tugun QLD 4224",
    "addr:housenumber":"415",
    "addr:postcode":"4224",
    "addr:street":"Golden Four Drv",
    "iso:country":"AU",
    "sg:address":"415 Golden Four Drv",
    "sg:city":"Tugun",
    "sg:classifiers":[
        {
            "category":"Education",
            "subcategory":"Music School",
            "type":"Public Place"
        }
    ],
    "sg:phone":"+61 7 5525 0444",
    "sg:postcode":"4224",
    "sg:province":"QLD",
    "sg:tags":[
        "therapy",
        "relaxation"
    ],
    "wof:name":"Tugun Wholistic Massage",
    "wof:placetype":"venue"
},
  "geometry": {"coordinates":[153.49659729000001,-28.1447887421],"type":"Point"}
}