{
  "type": "Feature",
  "properties": {
    "iso:country":"AU",
    "sg:address":"Commissioner St",
    "sg:city":"(Carpark) Cooma",
    "sg:classifiers":[
        {
            "category":"Retail",
            "subcategory":"Repair Shop",
            "type":"Services"
        }
    ],
    "sg:phone":"+61 2 6452 6365",
    "sg:postcode":"2630",
    "sg:province":"NSW",
    "sg:tags":[
        "machine",
        "repairs",
        "part",
        "dryer",
        "washing"
    ],
    "wof:name":"Millers Appliance Repairs",
    "wof:placetype":"venue"
},
  "geometry": {"coordinates":[149.132278442,-36.2333564758],"type":"Point"}
}