{
  "type": "Feature",
  "properties": {
    "addr:full":"444 Stud Rd Wantirna South VIC 3152",
    "addr:housenumber":"444",
    "addr:postcode":"3152",
    "addr:street":"Stud Rd",
    "iso:country":"AU",
    "sg:address":"444 Stud Rd",
    "sg:city":"Wantirna South",
    "sg:classifiers":[
        {
            "category":"Autos & Motor Vehicles",
            "subcategory":"Fuel & Gas Station",
            "type":"Retail Goods"
        }
    ],
    "sg:phone":"+61 3 9801 5515",
    "sg:postcode":"3152",
    "sg:province":"VIC",
    "wof:name":"BP Australia Pty Ltd",
    "wof:placetype":"venue"
},
  "geometry": {"coordinates":[145.232711792,-37.8765525818],"type":"Point"}
}