{
  "type": "Feature",
  "properties": {
    "addr:full":"Millstream Rd Karratha WA 6714",
    "addr:postcode":"6714",
    "addr:street":"Millstream Rd",
    "iso:country":"AU",
    "sg:address":"Millstream Rd",
    "sg:city":"Karratha",
    "sg:classifiers":[
        {
            "category":"Arts & Performance",
            "subcategory":"Theater",
            "type":"Entertainment"
        }
    ],
    "sg:phone":"+61 8 9159 6860",
    "sg:postcode":"6714",
    "sg:province":"WA",
    "sg:tags":[
        "theatre"
    ],
    "sg:website":"http://www.pilbaratafe.wa.edu.au",
    "wof:name":"Walkington Theatre",
    "wof:placetype":"venue"
},
  "geometry": {"coordinates":[116.84954834,-20.7377128601],"type":"Point"}
}