{
  "type": "Feature",
  "properties": {
    "iso:country":"AU",
    "sg:address":"127 Macquarie St",
    "sg:city":"Dubbo",
    "sg:classifiers":[
        {
            "category":"Fast Food",
            "type":"Food & Drink"
        }
    ],
    "sg:phone":"+61 2 6882 2441",
    "sg:postcode":"2830",
    "sg:province":"NSW",
    "sg:tags":[
        "away",
        "take"
    ],
    "wof:name":"Fu Lee Wah Chinese Restaurant",
    "wof:placetype":"venue"
},
  "geometry": {"coordinates":[148.600952148,-32.248336792],"type":"Point"}
}