{
  "type": "Feature",
  "properties": {
    "iso:country":"AU",
    "sg:address":"149 Queensport Rd",
    "sg:city":"Murarrie",
    "sg:classifiers":[
        {
            "category":"Shopping",
            "subcategory":"Stationery & Office Supplies",
            "type":"Retail Goods"
        }
    ],
    "sg:phone":"+61 7 3390 6719",
    "sg:postcode":"4172",
    "sg:province":"QLD",
    "sg:tags":[
        "packaging",
        "material"
    ],
    "wof:name":"Cairns B.R.",
    "wof:placetype":"venue"
},
  "geometry": {"coordinates":[153.10633850100001,-27.4571819305],"type":"Point"}
}