{
  "type": "Feature",
  "properties": {
    "iso:country":"AU",
    "sg:address":"64 View Rd",
    "sg:city":"Springvale",
    "sg:classifiers":[
        {
            "category":"Professional",
            "subcategory":"Printing & Photocopies",
            "type":"Services"
        }
    ],
    "sg:phone":"+61 3 9547 2968",
    "sg:postcode":"3171",
    "sg:province":"VIC",
    "sg:tags":[
        "embroidery"
    ],
    "wof:name":"Stitch Art",
    "wof:placetype":"venue"
},
  "geometry": {"coordinates":[145.15704345699999,-37.9587173462],"type":"Point"}
}