{
  "type": "Feature",
  "properties": {
    "addr:full":"56 Daws Rd Edwardstown SA 5039",
    "addr:housenumber":"56",
    "addr:postcode":"5039",
    "addr:street":"Daws Rd",
    "iso:country":"AU",
    "sg:address":"56 Daws Rd",
    "sg:city":"Edwardstown",
    "sg:classifiers":[
        {
            "category":"Deli",
            "type":"Food & Drink"
        }
    ],
    "sg:phone":"+61 8 8276 2752",
    "sg:postcode":"5039",
    "sg:province":"SA",
    "sg:tags":[
        "delicatessen"
    ],
    "wof:name":"California Court Deli",
    "wof:placetype":"venue"
},
  "geometry": {"coordinates":[138.56915283199999,-34.9928970337],"type":"Point"}
}