{
  "type": "Feature",
  "properties": {
    "iso:country":"AU",
    "sg:address":"Unit 1 Wakefield Business Park 276-278 New Line Rd",
    "sg:city":"Dural",
    "sg:classifiers":[
        {
            "category":"Farming",
            "subcategory":"Farm & Veterinary Services",
            "type":"Manufacturing & Wholesale Goods"
        }
    ],
    "sg:phone":"+61 1300 797 950",
    "sg:postcode":"2158",
    "sg:province":"NSW",
    "sg:tags":[
        "irrigation",
        "reticulation",
        "system"
    ],
    "wof:name":"Water Mart",
    "wof:placetype":"venue"
},
  "geometry": {"coordinates":[151.03053283700001,-33.6961631775],"type":"Point"}
}