{
  "type": "Feature",
  "properties": {
    "iso:country":"AU",
    "sg:address":"Level 1, 40 Leichhardt St",
    "sg:city":"Spring Hill",
    "sg:classifiers":[
        {
            "category":"Organizations",
            "subcategory":"Professional Association",
            "type":"Services"
        }
    ],
    "sg:phone":"+61 7 3367 2000",
    "sg:postcode":"4000",
    "sg:province":"QLD",
    "sg:tags":[
        "web",
        "internet"
    ],
    "wof:name":"Digicon",
    "wof:placetype":"venue"
},
  "geometry": {"coordinates":[153.022506714,-27.4619369507],"type":"Point"}
}