{
  "type": "Feature",
  "properties": {
    "addr:full":"Unit 1/ 223 Rockingham Rd Spearwood WA 6163",
    "addr:housenumber":"/ 223",
    "addr:postcode":"6163",
    "addr:street":"Rockingham Rd",
    "iso:country":"AU",
    "sg:address":"Unit 1/ 223 Rockingham Rd",
    "sg:city":"Spearwood",
    "sg:classifiers":[
        {
            "category":"Health Services",
            "subcategory":"Doctor",
            "type":"Services"
        }
    ],
    "sg:phone":"+61 8 9434 3555",
    "sg:postcode":"6163",
    "sg:province":"WA",
    "sg:tags":[
        "medical",
        "practitioner"
    ],
    "wof:name":"Fiorina Gabba Dr",
    "wof:placetype":"venue"
},
  "geometry": {"coordinates":[115.782600403,-32.0939369202],"type":"Point"}
}