{
  "type": "Feature",
  "properties": {
    "addr:full":"Unit 3/ 319 Mann St Gosford NSW 2250",
    "addr:housenumber":"/ 319",
    "addr:postcode":"2250",
    "addr:street":"Mann St",
    "iso:country":"AU",
    "sg:address":"Unit 3/ 319 Mann St",
    "sg:city":"Gosford",
    "sg:classifiers":[
        {
            "category":"Conference Center",
            "type":"Public Place"
        }
    ],
    "sg:phone":"+61 2 4324 6562",
    "sg:postcode":"2250",
    "sg:province":"NSW",
    "sg:tags":[
        "venue",
        "convention"
    ],
    "wof:name":"Weddings To Remember",
    "wof:placetype":"venue"
},
  "geometry": {"coordinates":[151.34344482399999,-33.4199295044],"type":"Point"}
}