{
  "type": "Feature",
  "properties": {
    "addr:full":"42 Box Rd Taren Point NSW 2229",
    "addr:housenumber":"42",
    "addr:postcode":"2229",
    "addr:street":"Box Rd",
    "iso:country":"AU",
    "sg:address":"42 Box Rd",
    "sg:city":"Taren Point",
    "sg:classifiers":[
        {
            "category":"Home & Garden",
            "subcategory":"Home Furnishings",
            "type":"Retail Goods"
        }
    ],
    "sg:phone":"+61 13 20 57",
    "sg:postcode":"2229",
    "sg:province":"NSW",
    "sg:tags":[
        "shower",
        "screen"
    ],
    "sg:website":"http://www.bettawardrobes.com.au",
    "wof:name":"Betta Wardrobes & Shower Screens",
    "wof:placetype":"venue"
},
  "geometry": {"coordinates":[151.121780395,-34.0245056152],"type":"Point"}
}