{
  "type": "Feature",
  "properties": {
    "iso:country":"AU",
    "sg:address":"6 June St",
    "sg:city":"Port Macquarie",
    "sg:classifiers":[
        {
            "category":"Professional",
            "subcategory":"Computer Services",
            "type":"Services"
        }
    ],
    "sg:phone":"+61 2 6583 6441",
    "sg:postcode":"2444",
    "sg:province":"NSW",
    "sg:tags":[
        "consultant",
        "system"
    ],
    "wof:name":"Thomas Computing Services",
    "wof:placetype":"venue"
},
  "geometry": {"coordinates":[152.913208,-31.444933],"type":"Point"}
}