{
  "type": "Feature",
  "properties": {
    "addr:full":"1st Floor 16 Mouat St Fremantle WA 6160",
    "addr:housenumber":"16",
    "addr:postcode":"6160",
    "addr:street":"Mouat St",
    "iso:country":"AU",
    "sg:address":"1st Floor 16 Mouat St",
    "sg:city":"Fremantle",
    "sg:classifiers":[
        {
            "category":"Real Estate",
            "subcategory":"Surveying",
            "type":"Services"
        }
    ],
    "sg:phone":"+61 8 9336 4344",
    "sg:postcode":"6160",
    "sg:province":"WA",
    "sg:tags":[
        "surveyor",
        "marine",
        "cargo"
    ],
    "wof:name":"Captain C Keys",
    "wof:placetype":"venue"
},
  "geometry": {"coordinates":[115.74324799999999,-32.055077],"type":"Point"}
}