{
  "type": "Feature",
  "properties": {
    "iso:country":"AU",
    "sg:address":"1st Floor 16 Mouat St",
    "sg:city":"Fremantle",
    "sg:classifiers":[
        {
            "category":"Real Estate",
            "subcategory":"Surveying",
            "type":"Services"
        }
    ],
    "sg:phone":"+61 8 9336 4344",
    "sg:postcode":"6160",
    "sg:province":"WA",
    "sg:tags":[
        "surveyor",
        "marine",
        "cargo"
    ],
    "wof:name":"Captain C Keys",
    "wof:placetype":"venue"
},
  "geometry": {"coordinates":[115.743248,-32.055077],"type":"Point"}
}