{
  "type": "Feature",
  "properties": {
    "iso:country":"AU",
    "sg:address":"36 Burrows St",
    "sg:city":"Bowen Hills",
    "sg:classifiers":[
        {
            "category":"Arts & Performance",
            "subcategory":"Theater",
            "type":"Entertainment"
        }
    ],
    "sg:phone":"+61 7 3252 9198",
    "sg:postcode":"4006",
    "sg:province":"QLD",
    "sg:tags":[
        "theatrical",
        "supply"
    ],
    "wof:name":"Lighting Dimensions",
    "wof:placetype":"venue"
},
  "geometry": {"coordinates":[153.040939331,-27.4354305267],"type":"Point"}
}