{
  "type": "Feature",
  "properties": {
    "addr:full":"41 McCartin St Leongatha VIC 3953",
    "addr:housenumber":"41",
    "addr:postcode":"3953",
    "addr:street":"Mccartin St",
    "iso:country":"AU",
    "sg:address":"41 McCartin St",
    "sg:city":"Leongatha",
    "sg:classifiers":[
        {
            "category":"Banks & Credit Unions",
            "subcategory":"Financial Services",
            "type":"Services"
        }
    ],
    "sg:phone":"+61 3 5662 2529",
    "sg:postcode":"3953",
    "sg:province":"VIC",
    "sg:tags":[
        "loan",
        "finance",
        "mortgage"
    ],
    "wof:name":"Gippsreal Limited",
    "wof:placetype":"venue"
},
  "geometry": {"coordinates":[145.944625855,-38.4776916504],"type":"Point"}
}