{
  "type": "Feature",
  "properties": {
    "addr:full":"30 Johnston St Bulimba QLD 4171",
    "addr:housenumber":"30",
    "addr:postcode":"4171",
    "addr:street":"Johnston St",
    "iso:country":"AU",
    "sg:address":"30 Johnston St",
    "sg:city":"Bulimba",
    "sg:classifiers":[
        {
            "category":"Manufacturing",
            "subcategory":"Motor Vehicles & Parts",
            "type":"Manufacturing & Wholesale Goods"
        }
    ],
    "sg:phone":"+61 7 3399 0834",
    "sg:postcode":"4171",
    "sg:province":"QLD",
    "sg:tags":[
        "wholesaler",
        "cycle",
        "mfrs",
        "accessory"
    ],
    "wof:name":"Addfast Accessories",
    "wof:placetype":"venue"
},
  "geometry": {"coordinates":[153.05870056099999,-27.4446582794],"type":"Point"}
}