{
  "type": "Feature",
  "properties": {
    "addr:full":"Shop 29-30 Shellharbour Rd Warilla NSW 2528",
    "addr:housenumber":"29-30",
    "addr:postcode":"2528",
    "addr:street":"Shellharbour Rd",
    "iso:country":"AU",
    "sg:address":"Shop 29-30 Shellharbour Rd",
    "sg:city":"Warilla",
    "sg:classifiers":[
        {
            "category":"Shopping",
            "subcategory":"Clothing, Apparel, & Fashions",
            "type":"Retail Goods"
        }
    ],
    "sg:phone":"+61 2 4297 7230",
    "sg:postcode":"2528",
    "sg:province":"NSW",
    "sg:tags":[
        "lady",
        "wear"
    ],
    "wof:name":"Miller's Fashion Club",
    "wof:placetype":"venue"
},
  "geometry": {"coordinates":[150.86102294899999,-34.5492401123],"type":"Point"}
}