{
  "type": "Feature",
  "properties": {
    "iso:country":"AU",
    "sg:address":"14 Queen Elizabeth Dr",
    "sg:city":"Dysart",
    "sg:classifiers":[
        {
            "category":"Travel",
            "subcategory":"Hotels & Motels",
            "type":"Entertainment"
        }
    ],
    "sg:phone":"+61 7 4958 1155",
    "sg:postcode":"4745",
    "sg:province":"QLD",
    "wof:name":"Jolly Collier Hotel Motel",
    "wof:placetype":"venue"
},
  "geometry": {"coordinates":[148.34883099999999,-22.589066],"type":"Point"}
}