{
  "type": "Feature",
  "properties": {
    "addr:full":"35 Charles St Lorne VIC 3232",
    "addr:housenumber":"35",
    "addr:postcode":"3232",
    "addr:street":"Charles St",
    "iso:country":"AU",
    "sg:address":"35 Charles St",
    "sg:city":"Lorne",
    "sg:classifiers":[
        {
            "category":"Professional",
            "subcategory":"Art Services",
            "type":"Services"
        }
    ],
    "sg:phone":"+61 3 5289 2177",
    "sg:postcode":"3232",
    "sg:province":"VIC",
    "sg:tags":[
        "picture",
        "frame",
        "framing"
    ],
    "wof:name":"Lorne Custom Framing",
    "wof:placetype":"venue"
},
  "geometry": {"coordinates":[143.97825599999999,-38.546257],"type":"Point"}
}