{
  "type": "Feature",
  "properties": {
    "addr:full":"1a Haig Rd Dalkeith WA 6009",
    "addr:housenumber":"1a",
    "addr:postcode":"6009",
    "addr:street":"Haig Rd",
    "iso:country":"AU",
    "sg:address":"1a Haig Rd",
    "sg:city":"Dalkeith",
    "sg:classifiers":[
        {
            "category":"Real Estate",
            "subcategory":"Architect",
            "type":"Services"
        }
    ],
    "sg:phone":"+61 8 6389 2255",
    "sg:postcode":"6009",
    "sg:province":"WA",
    "wof:name":"Sansom Gregory",
    "wof:placetype":"venue"
},
  "geometry": {"coordinates":[115.80027800000001,-32.000546],"type":"Point"}
}