{
  "type": "Feature",
  "properties": {
    "iso:country":"AU",
    "sg:address":"4 Christo Rd",
    "sg:city":"Georgetown",
    "sg:classifiers":[
        {
            "category":"Home & Garden",
            "subcategory":"Household Appliances",
            "type":"Retail Goods"
        }
    ],
    "sg:phone":"+61 2 4960 9400",
    "sg:postcode":"2298",
    "sg:province":"NSW",
    "sg:tags":[
        "chemical",
        "equipment",
        "steam",
        "cleaning",
        "pressure"
    ],
    "wof:name":"Daynatech",
    "wof:placetype":"venue"
},
  "geometry": {"coordinates":[151.73220825199999,-32.9115638733],"type":"Point"}
}