{
  "type": "Feature",
  "properties": {
    "addr:full":"36 Fishermans Rd Maroochydore QLD 4558",
    "addr:housenumber":"36",
    "addr:postcode":"4558",
    "addr:street":"Fishermans Rd",
    "iso:country":"AU",
    "sg:address":"36 Fishermans Rd",
    "sg:city":"Maroochydore",
    "sg:classifiers":[
        {
            "category":"Professional",
            "subcategory":"Engineering",
            "type":"Services"
        }
    ],
    "sg:phone":"+61 7 5443 6955",
    "sg:postcode":"4558",
    "sg:province":"QLD",
    "sg:tags":[
        "engineer",
        "mechanical"
    ],
    "wof:name":"Fishermans Rd Mechanical",
    "wof:placetype":"venue"
},
  "geometry": {"coordinates":[153.055511475,-26.6537437439],"type":"Point"}
}