{
  "type": "Feature",
  "properties": {
    "addr:full":"32 Brougham St Gosford East NSW 2250",
    "addr:housenumber":"32",
    "addr:postcode":"2250",
    "addr:street":"Brougham St",
    "iso:country":"AU",
    "sg:address":"32 Brougham St",
    "sg:city":"Gosford East",
    "sg:classifiers":[
        {
            "category":"Government",
            "subcategory":"Post Office",
            "type":"Public Place"
        }
    ],
    "sg:phone":"+61 2 4323 1773",
    "sg:postcode":"2250",
    "sg:province":"NSW",
    "sg:tags":[
        "horse",
        "dentist"
    ],
    "wof:name":"Goodwood Equine Dental Care",
    "wof:placetype":"venue"
},
  "geometry": {"coordinates":[151.35415649399999,-33.4368667603],"type":"Point"}
}