{
  "type": "Feature",
  "properties": {
    "addr:full":"25 Winterton Rd Clayton VIC 3168",
    "addr:housenumber":"25",
    "addr:postcode":"3168",
    "addr:street":"Winterton Rd",
    "iso:country":"AU",
    "sg:address":"25 Winterton Rd",
    "sg:city":"Clayton",
    "sg:classifiers":[
        {
            "category":"Shopping",
            "subcategory":"Computers & Home Electronics",
            "type":"Retail Goods"
        }
    ],
    "sg:phone":"+61 3 9562 8222",
    "sg:postcode":"3168",
    "sg:province":"VIC",
    "sg:tags":[
        "wholesaler",
        "mfrs",
        "part",
        "electronic"
    ],
    "wof:name":"HY-Q International (Aust) Pty Ltd",
    "wof:placetype":"venue"
},
  "geometry": {"coordinates":[145.13540649399999,-37.9225616455],"type":"Point"}
}