{
  "type": "Feature",
  "properties": {
    "addr:full":"13 Knowles St Horsham VIC 3400",
    "addr:housenumber":"13",
    "addr:postcode":"3400",
    "addr:street":"Knowles St",
    "iso:country":"AU",
    "sg:address":"13 Knowles St",
    "sg:city":"Horsham",
    "sg:classifiers":[
        {
            "category":"Building & Trades",
            "subcategory":"Construction",
            "type":"Services"
        }
    ],
    "sg:phone":"+61 3 5382 1765",
    "sg:postcode":"3400",
    "sg:province":"VIC",
    "sg:tags":[
        "plasterboard",
        "plasterer",
        "fixer"
    ],
    "wof:name":"MT & AM Kennedy Plasterers",
    "wof:placetype":"venue"
},
  "geometry": {"coordinates":[142.21734619099999,-36.7052650452],"type":"Point"}
}