{
  "type": "Feature",
  "properties": {
    "iso:country":"AU",
    "sg:address":"18C Bournemouth Crs",
    "sg:city":"Wembley Downs",
    "sg:classifiers":[
        {
            "category":"Food & Beverages",
            "subcategory":"Specialty",
            "type":"Retail Goods"
        }
    ],
    "sg:phone":"+61 401 954 164",
    "sg:postcode":"6019",
    "sg:province":"WA",
    "sg:tags":[
        "product",
        "health"
    ],
    "wof:name":"Kombucha Culture",
    "wof:placetype":"venue"
},
  "geometry": {"coordinates":[115.755622864,-31.8837585449],"type":"Point"}
}