{
  "type": "Feature",
  "properties": {
    "addr:full":"42 McCombe Rd Bunbury WA 6230",
    "addr:housenumber":"42",
    "addr:postcode":"6230",
    "addr:street":"Mccombe Rd",
    "iso:country":"AU",
    "sg:address":"42 McCombe Rd",
    "sg:city":"Bunbury",
    "sg:classifiers":[
        {
            "category":"Autos & Motor Vehicles",
            "subcategory":"Automobile Sales",
            "type":"Retail Goods"
        }
    ],
    "sg:phone":"+61 8 9724 9100",
    "sg:postcode":"6230",
    "sg:province":"WA",
    "sg:tags":[
        "equipment",
        "trailer"
    ],
    "sg:website":"http://www.awbbearings.com.au",
    "wof:name":"AWB Bearings",
    "wof:placetype":"venue"
},
  "geometry": {"coordinates":[115.67691000000001,-33.360176],"type":"Point"}
}