{
  "type": "Feature",
  "properties": {
    "iso:country":"AU",
    "sg:address":"20 Alban St",
    "sg:city":"Montmorency",
    "sg:classifiers":[
        {
            "category":"Home & Garden",
            "subcategory":"Building Materials",
            "type":"Retail Goods"
        }
    ],
    "sg:phone":"+61 407 845 797",
    "sg:postcode":"3094",
    "sg:province":"VIC",
    "sg:tags":[
        "retaining",
        "wall"
    ],
    "wof:name":"D W Bedford Constructions",
    "wof:placetype":"venue"
},
  "geometry": {"coordinates":[145.12142944300001,-37.7210121155],"type":"Point"}
}