{
  "type": "Feature",
  "properties": {
    "addr:full":"U 1/ 158 Lime Ave Mildura VIC 3500",
    "addr:housenumber":"/ 158",
    "addr:postcode":"3500",
    "addr:street":"Lime Ave",
    "iso:country":"AU",
    "sg:address":"U 1/ 158 Lime Ave",
    "sg:city":"Mildura",
    "sg:classifiers":[
        {
            "category":"Health Services",
            "subcategory":"Chiropractor",
            "type":"Services"
        }
    ],
    "sg:phone":"+61 3 5022 1966",
    "sg:postcode":"3500",
    "sg:province":"VIC",
    "wof:name":"Wagstaff Peter G",
    "wof:placetype":"venue"
},
  "geometry": {"coordinates":[142.155685425,-34.1875114441],"type":"Point"}
}