{
  "type": "Feature",
  "properties": {
    "addr:full":"42 Ramsden St Clifton Hill VIC 3068",
    "addr:housenumber":"42",
    "addr:postcode":"3068",
    "addr:street":"Ramsden St",
    "iso:country":"AU",
    "sg:address":"42 Ramsden St",
    "sg:city":"Clifton Hill",
    "sg:classifiers":[
        {
            "category":"Professional",
            "subcategory":"Research",
            "type":"Services"
        }
    ],
    "sg:phone":"+61 3 9481 3451",
    "sg:postcode":"3068",
    "sg:province":"VIC",
    "sg:tags":[
        "analyst"
    ],
    "wof:name":"Microns to Measure",
    "wof:placetype":"venue"
},
  "geometry": {"coordinates":[144.99749755900001,-37.7904205322],"type":"Point"}
}