{
  "type": "Feature",
  "properties": {
    "addr:full":"26 Hume St Adelaide SA 5000",
    "addr:housenumber":"26",
    "addr:postcode":"5000",
    "addr:street":"Hume St",
    "iso:country":"AU",
    "sg:address":"26 Hume St",
    "sg:city":"Adelaide",
    "sg:classifiers":[
        {
            "category":"Professional",
            "subcategory":"Computer Services",
            "type":"Services"
        }
    ],
    "sg:phone":"+61 400 636 077",
    "sg:postcode":"5000",
    "sg:province":"SA",
    "sg:tags":[
        "technical",
        "support"
    ],
    "wof:name":"Outback Online Service Pty Ltd",
    "wof:placetype":"venue"
},
  "geometry": {"coordinates":[138.61174011200001,-34.9300994873],"type":"Point"}
}