{
  "type": "Feature",
  "properties": {
    "iso:country":"AU",
    "sg:address":"Shop 2, Cnr Kularoo Drv",
    "sg:city":"& Trades Crt, Forster",
    "sg:classifiers":[
        {
            "category":"Personal",
            "subcategory":"Beauty Salon",
            "type":"Services"
        }
    ],
    "sg:phone":"+61 2 6557 2000",
    "sg:postcode":"2428",
    "sg:province":"NSW",
    "sg:tags":[
        "hairdresser"
    ],
    "wof:name":"Katrinas Kuts &#039;N&#039; Kurls",
    "wof:placetype":"venue"
},
  "geometry": {"coordinates":[152.52375799999999,-32.196754],"type":"Point"}
}