{
  "type": "Feature",
  "properties": {
    "iso:country":"AU",
    "sg:address":"3 Panorama St",
    "sg:city":"Maryborough",
    "sg:classifiers":[
        {
            "category":"Arena",
            "subcategory":"Sports Club",
            "type":"Entertainment"
        }
    ],
    "sg:phone":"+61 7 4122 4009",
    "sg:postcode":"4650",
    "sg:province":"QLD",
    "sg:tags":[
        "organisation",
        "sporting"
    ],
    "wof:name":"Maryborough & District Hockey Association",
    "wof:placetype":"venue"
},
  "geometry": {"coordinates":[152.694702,-25.512186],"type":"Point"}
}