{
  "type": "Feature",
  "properties": {
    "addr:full":"2 Patrick Crt Seaford VIC 3198",
    "addr:housenumber":"2",
    "addr:postcode":"3198",
    "addr:street":"Patrick Crt",
    "iso:country":"AU",
    "sg:address":"2 Patrick Crt",
    "sg:city":"Seaford",
    "sg:classifiers":[
        {
            "category":"Retail",
            "subcategory":"Auto Repair",
            "type":"Services"
        }
    ],
    "sg:phone":"+61 3 9786 0277",
    "sg:postcode":"3198",
    "sg:province":"VIC",
    "sg:tags":[
        "repairer",
        "motor",
        "engineer"
    ],
    "wof:name":"Tovon Auto Repairs",
    "wof:placetype":"venue"
},
  "geometry": {"coordinates":[145.13545227,-38.1180496216],"type":"Point"}
}