{
  "type": "Feature",
  "properties": {
    "iso:country":"AU",
    "sg:address":"456 Centre Rd",
    "sg:city":"Bentleigh",
    "sg:classifiers":[
        {
            "category":"Shopping",
            "subcategory":"Clothing, Apparel, & Fashions",
            "type":"Retail Goods"
        }
    ],
    "sg:phone":"+61 3 9557 8333",
    "sg:postcode":"3204",
    "sg:province":"VIC",
    "sg:tags":[
        "lady",
        "wear"
    ],
    "wof:name":"Why Clothing Pty Ltd",
    "wof:placetype":"venue"
},
  "geometry": {"coordinates":[145.039154,-37.918598],"type":"Point"}
}