{
  "type": "Feature",
  "properties": {
    "addr:full":"308 Doncaster Rd Balwyn North VIC 3104",
    "addr:housenumber":"308",
    "addr:postcode":"3104",
    "addr:street":"Doncaster Rd",
    "iso:country":"AU",
    "sg:address":"308 Doncaster Rd",
    "sg:city":"Balwyn North",
    "sg:classifiers":[
        {
            "category":"Building & Trades",
            "subcategory":"Construction",
            "type":"Services"
        }
    ],
    "sg:phone":"+61 3 9857 6911",
    "sg:postcode":"3104",
    "sg:province":"VIC",
    "sg:tags":[
        "pool",
        "swimming"
    ],
    "wof:name":"Paul Vallos Pool Builder",
    "wof:placetype":"venue"
},
  "geometry": {"coordinates":[145.09481811500001,-37.7915992737],"type":"Point"}
}