{
  "type": "Feature",
  "properties": {
    "iso:country":"AU",
    "sg:address":"PO Box 38",
    "sg:city":"Leppington",
    "sg:classifiers":[
        {
            "category":"Communications",
            "subcategory":"Film & Video Production",
            "type":"Services"
        }
    ],
    "sg:phone":"+61 408 790 010",
    "sg:postcode":"2179",
    "sg:province":"NSW",
    "sg:tags":[
        "television",
        "system",
        "circuit",
        "closed"
    ],
    "wof:name":"A & L Pipe Testing Pty Ltd",
    "wof:placetype":"venue"
},
  "geometry": {"coordinates":[150.812103272,-33.9723892212],"type":"Point"}
}