{
  "type": "Feature",
  "properties": {
    "iso:country":"AU",
    "sg:address":"1 Baird Pl",
    "sg:city":"Scullin",
    "sg:classifiers":[
        {
            "category":"Building & Trades",
            "subcategory":"Landscaping Services",
            "type":"Services"
        }
    ],
    "sg:phone":"+61 418 681 141",
    "sg:postcode":"2614",
    "sg:province":"ACT",
    "sg:tags":[
        "designer",
        "landscape",
        "contractor"
    ],
    "wof:name":"Dillon Landscaping & Maintenance",
    "wof:placetype":"venue"
},
  "geometry": {"coordinates":[149.037963867,-35.2375068665],"type":"Point"}
}