{
  "type": "Feature",
  "properties": {
    "addr:full":"53 Grantham St Brunswick West VIC 3055",
    "addr:housenumber":"53",
    "addr:postcode":"3055",
    "addr:street":"Grantham St",
    "iso:country":"AU",
    "sg:address":"53 Grantham St",
    "sg:city":"Brunswick West",
    "sg:classifiers":[
        {
            "category":"Autos & Motor Vehicles",
            "subcategory":"Auto Supplies",
            "type":"Retail Goods"
        }
    ],
    "sg:phone":"+61 3 9388 9000",
    "sg:postcode":"3055",
    "sg:province":"VIC",
    "sg:tags":[
        "part",
        "cycles",
        "accessory"
    ],
    "wof:name":"Fx Racing Australia",
    "wof:placetype":"venue"
},
  "geometry": {"coordinates":[144.949295044,-37.7720108032],"type":"Point"}
}