{
  "type": "Feature",
  "properties": {
    "iso:country":"AU",
    "sg:address":"48 Wallington Rd",
    "sg:city":"Ocean Grove",
    "sg:classifiers":[
        {
            "category":"Autos & Motor Vehicles",
            "subcategory":"Fuel & Gas Station",
            "type":"Retail Goods"
        }
    ],
    "sg:phone":"+61 3 5256 1036",
    "sg:postcode":"3226",
    "sg:province":"VIC",
    "wof:name":"Loftys Ampol Service Station",
    "wof:placetype":"venue"
},
  "geometry": {"coordinates":[144.5121,-38.262337],"type":"Point"}
}