{
  "type": "Feature",
  "properties": {
    "addr:full":"Unit 2/ 11 Griffith St Coolangatta QLD 4225",
    "addr:housenumber":"11",
    "addr:postcode":"4225",
    "addr:street":"Griffith St",
    "iso:country":"AU",
    "sg:address":"Unit 2/ 11 Griffith St",
    "sg:city":"Coolangatta",
    "sg:classifiers":[
        {
            "category":"Professional",
            "subcategory":"Accounting & Tax Preparation",
            "type":"Services"
        }
    ],
    "sg:phone":"+61 7 5599 1244",
    "sg:postcode":"4225",
    "sg:province":"QLD",
    "sg:tags":[
        "consultant",
        "taxation"
    ],
    "wof:name":"Sullivan & Associates",
    "wof:placetype":"venue"
},
  "geometry": {"coordinates":[153.536056519,-28.168006897],"type":"Point"}
}