{
  "type": "Feature",
  "properties": {
    "iso:country":"AU",
    "sg:address":"116 Maribyrnong Rd",
    "sg:city":"Moonee Ponds",
    "sg:classifiers":[
        {
            "category":"Professional",
            "subcategory":"Art Services",
            "type":"Services"
        }
    ],
    "sg:phone":"+61 3 9370 6063",
    "sg:postcode":"3039",
    "sg:province":"VIC",
    "sg:tags":[
        "picture",
        "frame",
        "framing"
    ],
    "wof:name":"Carella R",
    "wof:placetype":"venue"
},
  "geometry": {"coordinates":[144.915894,-37.771549],"type":"Point"}
}