{
  "type": "Feature",
  "properties": {
    "iso:country":"AU",
    "sg:address":"23 Sherbrooke Lodge Rd",
    "sg:city":"Sherbrooke",
    "sg:classifiers":[
        {
            "category":"Professional",
            "subcategory":"Management & Consulting",
            "type":"Services"
        }
    ],
    "sg:phone":"+61 3 9755 1985",
    "sg:postcode":"3789",
    "sg:province":"VIC",
    "sg:tags":[
        "consultant",
        "business"
    ],
    "wof:name":"ACE Technical Consulting",
    "wof:placetype":"venue"
},
  "geometry": {"coordinates":[145.358597,-37.884472],"type":"Point"}
}