{
  "type": "Feature",
  "properties": {
    "iso:country":"AU",
    "sg:address":"Unit 13/ 10 Bruce Field St",
    "sg:city":"South West Rocks",
    "sg:classifiers":[
        {
            "category":"Personal",
            "subcategory":"Massage",
            "type":"Services"
        }
    ],
    "sg:phone":"+61 2 6566 5880",
    "sg:postcode":"2431",
    "sg:province":"NSW",
    "sg:tags":[
        "therapy"
    ],
    "wof:name":"South West Rocks - Terry Trevillian ATMS",
    "wof:placetype":"venue"
},
  "geometry": {"coordinates":[153.03732299999999,-30.895926],"type":"Point"}
}