{
  "type": "Feature",
  "properties": {
    "iso:country":"AU",
    "sg:address":"PO Box 67",
    "sg:city":"Bald Hills",
    "sg:classifiers":[
        {
            "category":"Building & Trades",
            "subcategory":"Cleaning & Sanitation",
            "type":"Services"
        }
    ],
    "sg:phone":"+61 411 400 751",
    "sg:postcode":"4036",
    "sg:province":"QLD",
    "sg:tags":[
        "industrial",
        "commercial",
        "contractor"
    ],
    "wof:name":"Cobra Cleaning Services",
    "wof:placetype":"venue"
},
  "geometry": {"coordinates":[153.021637,-27.309469],"type":"Point"}
}