{
  "type": "Feature",
  "properties": {
    "iso:country":"AU",
    "sg:address":"Unit 5, 4 Arrigo St",
    "sg:city":"Wangara",
    "sg:classifiers":[
        {
            "category":"Professional",
            "subcategory":"Printing & Photocopies",
            "type":"Services"
        }
    ],
    "sg:phone":"+61 8 9409 2766",
    "sg:postcode":"6065",
    "sg:province":"WA",
    "sg:tags":[
        "textile",
        "clothing"
    ],
    "wof:name":"Print Shed The",
    "wof:placetype":"venue"
},
  "geometry": {"coordinates":[115.81787872300001,-31.7884044647],"type":"Point"}
}