{
  "type": "Feature",
  "properties": {
    "addr:full":"1686 Princes Hwy Clayton VIC 3168",
    "addr:housenumber":"1686",
    "addr:postcode":"3168",
    "addr:street":"Princes Hwy",
    "iso:country":"AU",
    "sg:address":"1686 Princes Hwy",
    "sg:city":"Clayton",
    "sg:classifiers":[
        {
            "category":"Professional",
            "subcategory":"Detective & Security Services",
            "type":"Services"
        }
    ],
    "sg:phone":"+61 3 9562 9989",
    "sg:postcode":"3168",
    "sg:province":"VIC",
    "sg:tags":[
        "equipment",
        "window",
        "doors"
    ],
    "wof:name":"Hi-Light",
    "wof:placetype":"venue"
},
  "geometry": {"coordinates":[145.12059020999999,-37.9107055664],"type":"Point"}
}