{
  "type": "Feature",
  "properties": {
    "iso:country":"AU",
    "sg:address":"653 Yandina Creek Rd",
    "sg:city":"Yandina Creek",
    "sg:classifiers":[
        {
            "category":"Building & Trades",
            "subcategory":"Construction",
            "type":"Services"
        }
    ],
    "sg:phone":"+61 419 669 194",
    "sg:postcode":"4561",
    "sg:province":"QLD",
    "sg:tags":[
        "contractor"
    ],
    "wof:name":"Hennig Trevor",
    "wof:placetype":"venue"
},
  "geometry": {"coordinates":[152.95773315400001,-26.5522060394],"type":"Point"}
}