{
  "type": "Feature",
  "properties": {
    "addr:full":"Caloola Drv Tweed Heads West NSW 2485",
    "addr:postcode":"2485",
    "addr:street":"Caloola Drv",
    "iso:country":"AU",
    "sg:address":"Caloola Drv",
    "sg:city":"Tweed Heads West",
    "sg:classifiers":[
        {
            "category":"Education",
            "subcategory":"Kindergarten",
            "type":"Public Place"
        }
    ],
    "sg:phone":"+61 7 5599 2656",
    "sg:postcode":"2485",
    "sg:province":"NSW",
    "sg:tags":[
        "pre-schools"
    ],
    "wof:name":"Lakeside Christian Primary School",
    "wof:placetype":"venue"
},
  "geometry": {"coordinates":[153.52517700199999,-28.1791057587],"type":"Point"}
}