{
  "type": "Feature",
  "properties": {
    "iso:country":"AU",
    "sg:address":"6 Percy St",
    "sg:city":"Kalgoorlie",
    "sg:classifiers":[
        {
            "category":"Building & Trades",
            "subcategory":"Equipment Rental",
            "type":"Services"
        }
    ],
    "sg:phone":"+61 8 9088 6300",
    "sg:postcode":"6430",
    "sg:province":"WA",
    "sg:tags":[
        "crane",
        "hire"
    ],
    "wof:name":"Boom Logistics Ltd",
    "wof:placetype":"venue"
},
  "geometry": {"coordinates":[121.438491821,-30.7863712311],"type":"Point"}
}