{
  "type": "Feature",
  "properties": {
    "addr:full":"Tasman St Devonport TAS 7310",
    "addr:postcode":"7310",
    "addr:street":"Tasman St",
    "iso:country":"AU",
    "sg:address":"Tasman St",
    "sg:city":"Devonport",
    "sg:classifiers":[
        {
            "category":"Shopping",
            "subcategory":"Department Store",
            "type":"Retail Goods"
        }
    ],
    "sg:phone":"+61 3 6424 6345",
    "sg:postcode":"7310",
    "sg:province":"TAS",
    "sg:tags":[
        "towel",
        "supply"
    ],
    "wof:name":"Australian Weaving Mills",
    "wof:placetype":"venue"
},
  "geometry": {"coordinates":[146.34751892099999,-41.1816520691],"type":"Point"}
}