{
  "type": "Feature",
  "properties": {
    "addr:full":"255 Eddystone Ave Beldon WA 6027",
    "addr:housenumber":"255",
    "addr:postcode":"6027",
    "addr:street":"Eddystone Ave",
    "iso:country":"AU",
    "sg:address":"255 Eddystone Ave",
    "sg:city":"Beldon",
    "sg:classifiers":[
        {
            "category":"Health Services",
            "subcategory":"Health Practitioner",
            "type":"Services"
        }
    ],
    "sg:phone":"+61 8 9307 6900",
    "sg:postcode":"6027",
    "sg:province":"WA",
    "sg:tags":[
        "alternative"
    ],
    "wof:name":"Valma Truu",
    "wof:placetype":"venue"
},
  "geometry": {"coordinates":[115.767051697,-31.7712211609],"type":"Point"}
}