{
  "type": "Feature",
  "properties": {
    "iso:country":"AU",
    "sg:address":"3 Tarquin Pl",
    "sg:city":"Hillside",
    "sg:classifiers":[
        {
            "category":"Building & Trades",
            "subcategory":"Cleaning & Sanitation",
            "type":"Services"
        }
    ],
    "sg:phone":"+61 418 379 337",
    "sg:postcode":"3037",
    "sg:province":"VIC",
    "sg:tags":[
        "cleaner",
        "repairer",
        "roof"
    ],
    "wof:name":"P & S Roofing",
    "wof:placetype":"venue"
},
  "geometry": {"coordinates":[144.747055,-37.686146],"type":"Point"}
}