{
  "type": "Feature",
  "properties": {
    "addr:full":"16a Alexander St Royal Park SA 5014",
    "addr:housenumber":"16a",
    "addr:postcode":"5014",
    "addr:street":"Alexander St",
    "iso:country":"AU",
    "sg:address":"16a Alexander St",
    "sg:city":"Royal Park",
    "sg:classifiers":[
        {
            "category":"Building & Trades",
            "subcategory":"Construction",
            "type":"Services"
        }
    ],
    "sg:phone":"+61 412 565 182",
    "sg:postcode":"5014",
    "sg:province":"SA",
    "sg:tags":[
        "plasterboard",
        "plasterer",
        "fixer"
    ],
    "wof:name":"Robert Tenikoff",
    "wof:placetype":"venue"
},
  "geometry": {"coordinates":[138.506134033,-34.8760070801],"type":"Point"}
}