{
  "type": "Feature",
  "properties": {
    "iso:country":"AU",
    "sg:address":"147 Swan St",
    "sg:city":"Morpeth",
    "sg:classifiers":[
        {
            "category":"Retail",
            "subcategory":"Auto Rental",
            "type":"Services"
        }
    ],
    "sg:phone":"+61 2 4934 6080",
    "sg:postcode":"2321",
    "sg:province":"NSW",
    "sg:tags":[
        "car",
        "wedding"
    ],
    "sg:website":"http://www.classiclimousine.com.au",
    "wof:name":"A Classic Limousine",
    "wof:placetype":"venue"
},
  "geometry": {"coordinates":[151.625610352,-32.7250862122],"type":"Point"}
}