{
  "type": "Feature",
  "properties": {
    "addr:full":"19 Hunter Ave Matraville NSW 2036",
    "addr:housenumber":"19",
    "addr:postcode":"2036",
    "addr:street":"Hunter Ave",
    "iso:country":"AU",
    "sg:address":"19 Hunter Ave",
    "sg:city":"Matraville",
    "sg:classifiers":[
        {
            "category":"Building & Trades",
            "subcategory":"Construction",
            "type":"Services"
        }
    ],
    "sg:phone":"+61 418 111 605",
    "sg:postcode":"2036",
    "sg:province":"NSW",
    "sg:tags":[
        "contractor"
    ],
    "wof:name":"Songlen Pty Ltd",
    "wof:placetype":"venue"
},
  "geometry": {"coordinates":[151.234100342,-33.9601783752],"type":"Point"}
}