{
  "type": "Feature",
  "properties": {
    "iso:country":"AU",
    "sg:address":"684 Sackville St",
    "sg:city":"Albury",
    "sg:classifiers":[
        {
            "category":"Wholesale",
            "subcategory":"Medical Equipment & Supplies",
            "type":"Manufacturing & Wholesale Goods"
        }
    ],
    "sg:phone":"+61 2 6021 4946",
    "sg:postcode":"2640",
    "sg:province":"NSW",
    "sg:tags":[
        "aid",
        "care",
        "health",
        "home"
    ],
    "wof:name":"Stepless Shower Base",
    "wof:placetype":"venue"
},
  "geometry": {"coordinates":[146.912765503,-36.0709953308],"type":"Point"}
}