{
  "type": "Feature",
  "properties": {
    "addr:full":"10 Wheal-Gawler St Glen Osmond SA 5064",
    "addr:housenumber":"10",
    "addr:postcode":"5064",
    "addr:street":"Wheal-Gawler St",
    "iso:country":"AU",
    "sg:address":"10 Wheal-Gawler St",
    "sg:city":"Glen Osmond",
    "sg:classifiers":[
        {
            "category":"Building & Trades",
            "subcategory":"Construction",
            "type":"Services"
        }
    ],
    "sg:phone":"+61 408 841 450",
    "sg:postcode":"5064",
    "sg:province":"SA",
    "sg:tags":[
        "contractor"
    ],
    "wof:name":"Beltrame Brothers Builders Pty. Ltd.",
    "wof:placetype":"venue"
},
  "geometry": {"coordinates":[138.65461730999999,-34.9597167969],"type":"Point"}
}