{
  "type": "Feature",
  "properties": {
    "addr:full":"192 Glen Eira Rd Elsternwick VIC 3185",
    "addr:housenumber":"192",
    "addr:postcode":"3185",
    "addr:street":"Glen Eira Rd",
    "iso:country":"AU",
    "sg:address":"192 Glen Eira Rd",
    "sg:city":"Elsternwick",
    "sg:classifiers":[
        {
            "category":"Health Services",
            "subcategory":"Health Practitioner",
            "type":"Services"
        }
    ],
    "sg:phone":"+61 3 9523 7462",
    "sg:postcode":"3185",
    "sg:province":"VIC",
    "sg:tags":[
        "naturopath"
    ],
    "wof:name":"Lalor L",
    "wof:placetype":"venue"
},
  "geometry": {"coordinates":[145.0027771,-37.8776130676],"type":"Point"}
}