{
  "type": "Feature",
  "properties": {
    "iso:country":"AU",
    "sg:address":"Kegworth Rd",
    "sg:city":"Melrose Park",
    "sg:classifiers":[
        {
            "category":"Manufacturing",
            "subcategory":"Motor Vehicles & Parts",
            "type":"Manufacturing & Wholesale Goods"
        }
    ],
    "sg:phone":"+61 8 8276 9542",
    "sg:postcode":"5039",
    "sg:province":"SA",
    "sg:tags":[
        "replacement"
    ],
    "wof:name":"Volks Auto Parts Pty Ltd",
    "wof:placetype":"venue"
},
  "geometry": {"coordinates":[138.57777404800001,-34.9825668335],"type":"Point"}
}