{
  "type": "Feature",
  "properties": {
    "iso:country":"AU",
    "sg:address":"Burrabil Ave",
    "sg:city":"Gosford",
    "sg:classifiers":[
        {
            "category":"Health Services",
            "subcategory":"Doctor",
            "type":"Services"
        }
    ],
    "sg:phone":"+61 2 4323 1122",
    "sg:postcode":"2250",
    "sg:province":"NSW",
    "sg:tags":[
        "medical",
        "practitioner"
    ],
    "wof:name":"Coastal Orthopaedics & Sports Injuries",
    "wof:placetype":"venue"
},
  "geometry": {"coordinates":[151.34992980999999,-33.418006897],"type":"Point"}
}