{
  "type": "Feature",
  "properties": {
    "addr:full":"16 Firebrace St Horsham VIC 3400",
    "addr:housenumber":"16",
    "addr:postcode":"3400",
    "addr:street":"Firebrace St",
    "iso:country":"AU",
    "sg:address":"16 Firebrace St",
    "sg:city":"Horsham",
    "sg:classifiers":[
        {
            "category":"Fast Food",
            "type":"Food & Drink"
        }
    ],
    "sg:phone":"+61 3 5382 6388",
    "sg:postcode":"3400",
    "sg:province":"VIC",
    "sg:tags":[
        "away",
        "take"
    ],
    "wof:name":"Chicken Chef",
    "wof:placetype":"venue"
},
  "geometry": {"coordinates":[142.19955444300001,-36.7121772766],"type":"Point"}
}