{
  "type": "Feature",
  "properties": {
    "addr:full":"24 Eugenia St Rivett ACT 2611",
    "addr:housenumber":"24",
    "addr:postcode":"2611",
    "addr:street":"Eugenia St",
    "iso:country":"AU",
    "sg:address":"24 Eugenia St",
    "sg:city":"Rivett",
    "sg:classifiers":[
        {
            "category":"Professional",
            "subcategory":"Art Services",
            "type":"Services"
        }
    ],
    "sg:phone":"+61 2 6287 1163",
    "sg:postcode":"2611",
    "sg:province":"ACT",
    "sg:tags":[
        "interior",
        "decorator"
    ],
    "wof:name":"Michele Belford Interiors",
    "wof:placetype":"venue"
},
  "geometry": {"coordinates":[149.031784058,-35.345035553],"type":"Point"}
}