{
  "type": "Feature",
  "properties": {
    "addr:full":"28 Quality Drv Dandenong South VIC 3164",
    "addr:housenumber":"28",
    "addr:postcode":"3164",
    "addr:street":"Quality Drv",
    "iso:country":"AU",
    "sg:address":"28 Quality Drv",
    "sg:city":"Dandenong South",
    "sg:classifiers":[
        {
            "category":"Government",
            "subcategory":"Department Of Motor Vehicles",
            "type":"Public Place"
        }
    ],
    "sg:phone":"+61 3 9706 5055",
    "sg:postcode":"3164",
    "sg:province":"VIC",
    "sg:tags":[
        "wholesaler",
        "mfrs",
        "accessory"
    ],
    "wof:name":"TSB",
    "wof:placetype":"venue"
},
  "geometry": {"coordinates":[145.201705933,-38.0340309143],"type":"Point"}
}