{
  "type": "Feature",
  "properties": {
    "iso:country":"AU",
    "sg:address":"Barnes St",
    "sg:city":"Tamworth",
    "sg:classifiers":[
        {
            "category":"Building & Trades",
            "subcategory":"Equipment Rental",
            "type":"Services"
        }
    ],
    "sg:phone":"+61 13 15 52",
    "sg:postcode":"2340",
    "sg:province":"NSW",
    "sg:tags":[
        "platform",
        "hire",
        "work",
        "elevating"
    ],
    "wof:name":"Coates Hire",
    "wof:placetype":"venue"
},
  "geometry": {"coordinates":[150.91795349099999,-31.0887184143],"type":"Point"}
}