{
  "type": "Feature",
  "properties": {
    "iso:country":"AU",
    "sg:address":"5 Ocean Drv",
    "sg:city":"South West Rocks",
    "sg:classifiers":[
        {
            "category":"Shopping",
            "subcategory":"Crafts & Fabrics",
            "type":"Retail Goods"
        }
    ],
    "sg:phone":"+61 2 6566 7525",
    "sg:postcode":"2431",
    "sg:province":"NSW",
    "sg:tags":[
        "supply"
    ],
    "wof:name":"South West Rocks Arts & Craft Association Inc",
    "wof:placetype":"venue"
},
  "geometry": {"coordinates":[153.038925,-30.883896],"type":"Point"}
}