{
  "type": "Feature",
  "properties": {
    "addr:full":"5 Ocean Drv South West Rocks NSW 2431",
    "addr:housenumber":"5",
    "addr:postcode":"2431",
    "addr:street":"Ocean Drv South West Rocks",
    "iso:country":"AU",
    "sg:address":"5 Ocean Drv",
    "sg:city":"South West Rocks",
    "sg:classifiers":[
        {
            "category":"Shopping",
            "subcategory":"Crafts & Fabrics",
            "type":"Retail Goods"
        }
    ],
    "sg:phone":"+61 2 6566 7525",
    "sg:postcode":"2431",
    "sg:province":"NSW",
    "sg:tags":[
        "supply"
    ],
    "wof:name":"South West Rocks Arts & Craft Association Inc",
    "wof:placetype":"venue"
},
  "geometry": {"coordinates":[153.03892500000001,-30.883896],"type":"Point"}
}