{
  "type": "Feature",
  "properties": {
    "iso:country":"AU",
    "sg:address":"269-271 Gaffney St (Cnr Derby St & Gaffney St)",
    "sg:city":"Pascoe Vale",
    "sg:classifiers":[
        {
            "category":"Health Services",
            "subcategory":"Dentist",
            "type":"Services"
        }
    ],
    "sg:phone":"+61 3 9354 7111",
    "sg:postcode":"3044",
    "sg:province":"VIC",
    "wof:name":"Pascoe Vale Dental Group",
    "wof:placetype":"venue"
},
  "geometry": {"coordinates":[144.945922852,-37.7323608398],"type":"Point"}
}