{
  "type": "Feature",
  "properties": {
    "addr:full":"32 Gilmore Crs Garran ACT 2605",
    "addr:housenumber":"32",
    "addr:postcode":"2605",
    "addr:street":"Gilmore Crs",
    "iso:country":"AU",
    "sg:address":"32 Gilmore Crs",
    "sg:city":"Garran",
    "sg:classifiers":[
        {
            "category":"Sports & Exercise",
            "subcategory":"Gym",
            "type":"Entertainment"
        }
    ],
    "sg:phone":"+61 2 6282 8991",
    "sg:postcode":"2605",
    "sg:province":"ACT",
    "sg:tags":[
        "pilate",
        "method"
    ],
    "wof:name":"Bud Chapple",
    "wof:placetype":"venue"
},
  "geometry": {"coordinates":[149.10896301299999,-35.3422203064],"type":"Point"}
}