{
  "type": "Feature",
  "properties": {
    "addr:full":"6 Dunn Ave Ferny Creek VIC 3786",
    "addr:housenumber":"6",
    "addr:postcode":"3786",
    "addr:street":"Dunn Ave",
    "iso:country":"AU",
    "sg:address":"6 Dunn Ave",
    "sg:city":"Ferny Creek",
    "sg:classifiers":[
        {
            "category":"Shopping",
            "subcategory":"Antiques",
            "type":"Retail Goods"
        }
    ],
    "sg:phone":"+61 3 9755 2470",
    "sg:postcode":"3786",
    "sg:province":"VIC",
    "wof:name":"Marani Arts & Antiques",
    "wof:placetype":"venue"
},
  "geometry": {"coordinates":[145.32960499999999,-37.880539],"type":"Point"}
}