{
  "type": "Feature",
  "properties": {
    "iso:country":"AU",
    "sg:address":"Shp 67/ 2 Wembley & Kingston Rd",
    "sg:city":"Logan Central",
    "sg:classifiers":[
        {
            "category":"Personal",
            "subcategory":"Beauty Salon",
            "type":"Services"
        }
    ],
    "sg:phone":"+61 7 3386 0250",
    "sg:postcode":"4114",
    "sg:province":"QLD",
    "sg:tags":[
        "hairdresser"
    ],
    "wof:name":"Africana Hair Braiding & Extension Centre",
    "wof:placetype":"venue"
},
  "geometry": {"coordinates":[153.118530273,-27.6425895691],"type":"Point"}
}