{
  "type": "Feature",
  "properties": {
    "iso:country":"AU",
    "sg:address":"Shop 309, Lvl 2 Westfield Shoppingtown Park Rd",
    "sg:city":"Hurstville",
    "sg:classifiers":[
        {
            "category":"Shopping",
            "subcategory":"Clothing, Apparel, & Fashions",
            "type":"Retail Goods"
        }
    ],
    "sg:phone":"+61 2 9585 0922",
    "sg:postcode":"2220",
    "sg:province":"NSW",
    "sg:tags":[
        "lady",
        "wear"
    ],
    "wof:name":"Suite Boutique",
    "wof:placetype":"venue"
},
  "geometry": {"coordinates":[151.10458374000001,-33.9650840759],"type":"Point"}
}