{
  "type": "Feature",
  "properties": {
    "iso:country":"AU",
    "sg:address":"300 Princess Hwy",
    "sg:city":"Werribee",
    "sg:classifiers":[
        {
            "category":"Health Services",
            "subcategory":"Doctor",
            "type":"Services"
        }
    ],
    "sg:phone":"+61 3 9216 8633",
    "sg:postcode":"3030",
    "sg:province":"VIC",
    "sg:tags":[
        "medical",
        "practitioner"
    ],
    "wof:name":"Werribee Mercy Hospital Consulting Suite",
    "wof:placetype":"venue"
},
  "geometry": {"coordinates":[144.699524,-37.885296],"type":"Point"}
}