{
  "type": "Feature",
  "properties": {
    "iso:country":"AU",
    "sg:address":"1104 Howitt St",
    "sg:city":"Wendouree",
    "sg:classifiers":[
        {
            "category":"Health Services",
            "subcategory":"Doctor",
            "type":"Services"
        }
    ],
    "sg:phone":"+61 3 5339 4547",
    "sg:postcode":"3355",
    "sg:province":"VIC",
    "sg:tags":[
        "medical",
        "practitioner"
    ],
    "wof:name":"Ghaie Paul",
    "wof:placetype":"venue"
},
  "geometry": {"coordinates":[143.83395385700001,-37.5402526855],"type":"Point"}
}