{
  "type": "Feature",
  "properties": {
    "addr:full":"10 Hewitt St Colyton NSW 2760",
    "addr:housenumber":"10",
    "addr:postcode":"2760",
    "addr:street":"Hewitt St",
    "iso:country":"AU",
    "sg:address":"10 Hewitt St",
    "sg:city":"Colyton",
    "sg:classifiers":[
        {
            "category":"Education",
            "subcategory":"University",
            "type":"Public Place"
        }
    ],
    "sg:phone":"+61 2 9673 3222",
    "sg:postcode":"2760",
    "sg:province":"NSW",
    "sg:tags":[
        "educational",
        "organisation",
        "cultural"
    ],
    "wof:name":"Life Education NSW",
    "wof:placetype":"venue"
},
  "geometry": {"coordinates":[150.80142211899999,-33.7808837891],"type":"Point"}
}