{
  "type": "Feature",
  "properties": {
    "addr:full":"12 Leicester St Chester Hill NSW 2162",
    "addr:housenumber":"12",
    "addr:postcode":"2162",
    "addr:street":"Leicester St",
    "iso:country":"AU",
    "sg:address":"12 Leicester St",
    "sg:city":"Chester Hill",
    "sg:classifiers":[
        {
            "category":"Health Services",
            "subcategory":"Doctor",
            "type":"Services"
        }
    ],
    "sg:phone":"+61 2 9645 1581",
    "sg:postcode":"2162",
    "sg:province":"NSW",
    "sg:tags":[
        "medical",
        "practitioner"
    ],
    "wof:name":"Berger M & Wacher M",
    "wof:placetype":"venue"
},
  "geometry": {"coordinates":[151.00115966800001,-33.8817062378],"type":"Point"}
}