{
  "type": "Feature",
  "properties": {
    "iso:country":"AU",
    "sg:address":"Glenelg St",
    "sg:city":"Portland",
    "sg:classifiers":[
        {
            "category":"Museum",
            "type":"Entertainment"
        }
    ],
    "sg:phone":"+61 3 5523 5795",
    "sg:postcode":"3305",
    "sg:province":"VIC",
    "wof:name":"Powerhouse Motor & Car Museum",
    "wof:placetype":"venue"
},
  "geometry": {"coordinates":[141.610473633,-38.3527755737],"type":"Point"}
}