{
  "type": "Feature",
  "properties": {
    "addr:full":"37 Ken Crs Monterey Keys QLD 4212",
    "addr:housenumber":"37",
    "addr:postcode":"4212",
    "addr:street":"Ken Crs",
    "iso:country":"AU",
    "sg:address":"37 Ken Crs",
    "sg:city":"Monterey Keys",
    "sg:classifiers":[
        {
            "category":"Building & Trades",
            "subcategory":"Construction",
            "type":"Services"
        }
    ],
    "sg:phone":"+61 411 743 773",
    "sg:postcode":"4212",
    "sg:province":"QLD",
    "sg:tags":[
        "contractor"
    ],
    "wof:name":"J & A Richards Constructions",
    "wof:placetype":"venue"
},
  "geometry": {"coordinates":[153.340942383,-27.8899898529],"type":"Point"}
}