{
  "type": "Feature",
  "properties": {
    "addr:full":"Unit 9, 29/ 31 Manuka Pde Gorokan NSW 2263",
    "addr:housenumber":"29 / 31",
    "addr:postcode":"2263",
    "addr:street":"Manuka Pde",
    "iso:country":"AU",
    "sg:address":"Unit 9, 29/ 31 Manuka Pde",
    "sg:city":"Gorokan",
    "sg:classifiers":[
        {
            "category":"Personal",
            "subcategory":"Massage",
            "type":"Services"
        }
    ],
    "sg:phone":"+61 2 4392 0989",
    "sg:postcode":"2263",
    "sg:province":"NSW",
    "sg:tags":[
        "therapy"
    ],
    "wof:name":"Fell Trevor",
    "wof:placetype":"venue"
},
  "geometry": {"coordinates":[151.51280199999999,-33.255688],"type":"Point"}
}