{
  "type": "Feature",
  "properties": {
    "iso:country":"AU",
    "sg:address":"16 Pinjarra Rd",
    "sg:city":"Mandurah",
    "sg:classifiers":[
        {
            "category":"Real Estate",
            "subcategory":"Real Estate Agent",
            "type":"Services"
        }
    ],
    "sg:phone":"+61 8 9535 1877",
    "sg:postcode":"6210",
    "sg:province":"WA",
    "sg:website":"http://www.bassettscarfe.com.au",
    "wof:name":"Bassett-Scarfe Realty",
    "wof:placetype":"venue"
},
  "geometry": {"coordinates":[115.719322,-32.53463],"type":"Point"}
}