{
  "type": "Feature",
  "properties": {
    "iso:country":"AU",
    "sg:address":"U4/ 2 Purdy Pl",
    "sg:city":"Canning Vale",
    "sg:classifiers":[
        {
            "category":"Building & Trades",
            "subcategory":"Plumbing",
            "type":"Services"
        }
    ],
    "sg:phone":"+61 8 9256 4550",
    "sg:postcode":"6155",
    "sg:province":"WA",
    "sg:tags":[
        "fitting",
        "hose",
        "supply"
    ],
    "wof:name":"Hose Fittings Plus Canning Vale",
    "wof:placetype":"venue"
},
  "geometry": {"coordinates":[115.907013,-32.06192],"type":"Point"}
}