{
  "type": "Feature",
  "properties": {
    "addr:full":"60- 68 Brunker Rd Broadmeadow NSW 2292",
    "addr:housenumber":"68",
    "addr:postcode":"2292",
    "addr:street":"Brunker Rd",
    "iso:country":"AU",
    "sg:address":"60- 68 Brunker Rd",
    "sg:city":"Broadmeadow",
    "sg:classifiers":[
        {
            "category":"Airline",
            "type":"Transportation"
        }
    ],
    "sg:phone":"+61 2 4962 2399",
    "sg:postcode":"2292",
    "sg:province":"NSW",
    "sg:tags":[
        "aircraft",
        "rental",
        "charter"
    ],
    "wof:name":"Direct Air Services",
    "wof:placetype":"venue"
},
  "geometry": {"coordinates":[151.73353576700001,-32.9272918701],"type":"Point"}
}