{
  "type": "Feature",
  "properties": {
    "addr:full":"Shop 11, 114 James St Templestowe VIC 3106",
    "addr:housenumber":"shop 11 114",
    "addr:postcode":"3106",
    "addr:street":"James St",
    "iso:country":"AU",
    "sg:address":"Shop 11, 114 James St",
    "sg:city":"Templestowe",
    "sg:classifiers":[
        {
            "category":"Health Services",
            "subcategory":"Health Practitioner",
            "type":"Services"
        }
    ],
    "sg:phone":"+61 3 9846 5888",
    "sg:postcode":"3106",
    "sg:province":"VIC",
    "sg:tags":[
        "physiotherapist"
    ],
    "wof:name":"M D Health Physiotherapy",
    "wof:placetype":"venue"
},
  "geometry": {"coordinates":[145.12855529800001,-37.7570495605],"type":"Point"}
}