{
  "type": "Feature",
  "properties": {
    "addr:full":"323 South Dowling St Surry Hills NSW 2010",
    "addr:housenumber":"323",
    "addr:postcode":"2010",
    "addr:street":"South Dowling St",
    "iso:country":"AU",
    "sg:address":"323 South Dowling St",
    "sg:city":"Surry Hills",
    "sg:classifiers":[
        {
            "category":"Personal",
            "subcategory":"Beauty Salon",
            "type":"Services"
        }
    ],
    "sg:phone":"+61 2 9361 3636",
    "sg:postcode":"2010",
    "sg:province":"NSW",
    "sg:tags":[
        "hairdresser"
    ],
    "wof:name":"Boo's Hair",
    "wof:placetype":"venue"
},
  "geometry": {"coordinates":[151.21888732900001,-33.8819084167],"type":"Point"}
}