{
  "type": "Feature",
  "properties": {
    "addr:full":"7988 Melbourne Rd Shepparton VIC 3630",
    "addr:housenumber":"7988",
    "addr:postcode":"3630",
    "addr:street":"Melbourne Rd",
    "iso:country":"AU",
    "sg:address":"7988 Melbourne Rd",
    "sg:city":"Shepparton",
    "sg:classifiers":[
        {
            "category":"Home & Garden",
            "subcategory":"Household Appliances",
            "type":"Retail Goods"
        }
    ],
    "sg:phone":"+61 3 5823 2133",
    "sg:postcode":"3630",
    "sg:province":"VIC",
    "sg:tags":[
        "heating",
        "system"
    ],
    "wof:name":"G.V. Floorheating",
    "wof:placetype":"venue"
},
  "geometry": {"coordinates":[145.39328002900001,-36.4113845825],"type":"Point"}
}