{
  "type": "Feature",
  "properties": {
    "addr:full":"510 Glynburn Rd Burnside SA 5066",
    "addr:housenumber":"510",
    "addr:postcode":"5066",
    "addr:street":"Glynburn Rd",
    "iso:country":"AU",
    "sg:address":"510 Glynburn Rd",
    "sg:city":"Burnside",
    "sg:classifiers":[
        {
            "category":"Health Services",
            "subcategory":"Dentist",
            "type":"Services"
        }
    ],
    "sg:phone":"+61 8 8331 0436",
    "sg:postcode":"5066",
    "sg:province":"SA",
    "wof:name":"Walsh Simon Dr",
    "wof:placetype":"venue"
},
  "geometry": {"coordinates":[138.66027832,-34.9371261597],"type":"Point"}
}