{
  "type": "Feature",
  "properties": {
    "addr:full":"Whitsunday Shopping Centre, Shute Harbour Rd Cannonvale QLD 4802",
    "addr:postcode":"4802",
    "addr:street":"Shute Harbour Rd",
    "iso:country":"AU",
    "sg:address":"Whitsunday Shopping Centre, Shute Harbour Rd",
    "sg:city":"Cannonvale",
    "sg:classifiers":[
        {
            "category":"Social Services",
            "subcategory":"Child Care",
            "type":"Services"
        }
    ],
    "sg:phone":"+61 7 4946 7002",
    "sg:postcode":"4802",
    "sg:province":"QLD",
    "wof:name":"Bizy Kidz Whitsundays",
    "wof:placetype":"venue"
},
  "geometry": {"coordinates":[148.69070434599999,-20.2801074982],"type":"Point"}
}