{
  "type": "Feature",
  "properties": {
    "addr:full":"Unit 5/ 77 John St Welshpool WA 6106",
    "addr:housenumber":"77",
    "addr:postcode":"6106",
    "addr:street":"John St",
    "iso:country":"AU",
    "sg:address":"Unit 5/ 77 John St",
    "sg:city":"Welshpool",
    "sg:classifiers":[
        {
            "category":"Retail",
            "subcategory":"Auto Repair",
            "type":"Services"
        }
    ],
    "sg:phone":"+61 8 9358 0302",
    "sg:postcode":"6106",
    "sg:province":"WA",
    "sg:tags":[
        "repairer",
        "motor",
        "engineer"
    ],
    "wof:name":"Crockenberg Motors",
    "wof:placetype":"venue"
},
  "geometry": {"coordinates":[115.925537109,-31.9960136414],"type":"Point"}
}