{
  "type": "Feature",
  "properties": {
    "iso:country":"AU",
    "sg:address":"Whitens St",
    "sg:city":"Lakes Entrance",
    "sg:classifiers":[
        {
            "category":"Building & Trades",
            "subcategory":"Construction",
            "type":"Services"
        }
    ],
    "sg:phone":"+61 3 5155 1809",
    "sg:postcode":"3909",
    "sg:province":"VIC",
    "sg:tags":[
        "concrete",
        "contractor"
    ],
    "wof:name":"Pioneer Construction Materials Pty Ltd",
    "wof:placetype":"venue"
},
  "geometry": {"coordinates":[148.000274658,-37.8765678406],"type":"Point"}
}