{
  "type": "Feature",
  "properties": {
    "iso:country":"AU",
    "sg:address":"18 Greenock Crs",
    "sg:city":"Wantirna",
    "sg:classifiers":[
        {
            "category":"Professional",
            "subcategory":"Employment Agencies",
            "type":"Services"
        }
    ],
    "sg:phone":"+61 3 9738 1166",
    "sg:postcode":"3152",
    "sg:province":"VIC",
    "sg:tags":[
        "provider",
        "internet"
    ],
    "wof:name":"Webtrek Enterprise Mulitmedia",
    "wof:placetype":"venue"
},
  "geometry": {"coordinates":[145.22923278799999,-37.8482017517],"type":"Point"}
}