{
  "type": "Feature",
  "properties": {
    "iso:country":"AU",
    "sg:address":"51 Robinson St",
    "sg:city":"Dandenong",
    "sg:classifiers":[
        {
            "category":"Organizations",
            "subcategory":"Community Association",
            "type":"Services"
        }
    ],
    "sg:phone":"+61 3 9793 5588",
    "sg:postcode":"3175",
    "sg:province":"VIC",
    "sg:tags":[
        "registered",
        "trustee",
        "bankruptcy"
    ],
    "wof:name":"Vince & Associates",
    "wof:placetype":"venue"
},
  "geometry": {"coordinates":[145.21119689899999,-37.9852333069],"type":"Point"}
}