{
  "type": "Feature",
  "properties": {
    "iso:country":"AU",
    "sg:address":"3 Lister St",
    "sg:city":"St Albans",
    "sg:classifiers":[
        {
            "category":"Education",
            "subcategory":"Music School",
            "type":"Public Place"
        }
    ],
    "sg:phone":"+61 3 9364 2969",
    "sg:postcode":"3021",
    "sg:province":"VIC",
    "sg:tags":[
        "teacher"
    ],
    "wof:name":"St. Albans School Of Music",
    "wof:placetype":"venue"
},
  "geometry": {"coordinates":[144.80394000000001,-37.755314],"type":"Point"}
}