{
  "type": "Feature",
  "properties": {
    "addr:full":"2596 Cunningham Hwy Willowbank QLD 4306",
    "addr:housenumber":"2596",
    "addr:postcode":"4306",
    "addr:street":"Cunningham Hwy",
    "iso:country":"AU",
    "sg:address":"2596 Cunningham Hwy",
    "sg:city":"Willowbank",
    "sg:classifiers":[
        {
            "category":"Building & Trades",
            "subcategory":"Landscaping Services",
            "type":"Services"
        }
    ],
    "sg:phone":"+61 7 5467 3142",
    "sg:postcode":"4306",
    "sg:province":"QLD",
    "sg:tags":[
        "slashing",
        "contractor"
    ],
    "wof:name":"Dunnes Tractor Slashing",
    "wof:placetype":"venue"
},
  "geometry": {"coordinates":[152.693756103,-27.6609954834],"type":"Point"}
}