{
  "type": "Feature",
  "properties": {
    "addr:full":"278 Invermay Rd Mowbray Heights TAS 7248",
    "addr:housenumber":"278",
    "addr:postcode":"7248",
    "addr:street":"Invermay Rd",
    "iso:country":"AU",
    "sg:address":"278 Invermay Rd",
    "sg:city":"Mowbray Heights",
    "sg:classifiers":[
        {
            "category":"Health Services",
            "subcategory":"Doctor",
            "type":"Services"
        }
    ],
    "sg:phone":"+61 3 6336 0555",
    "sg:postcode":"7248",
    "sg:province":"TAS",
    "sg:tags":[
        "medical",
        "practitioner"
    ],
    "wof:name":"Kerkenezov Paul",
    "wof:placetype":"venue"
},
  "geometry": {"coordinates":[147.132415772,-41.404750824],"type":"Point"}
}