{
  "type": "Feature",
  "properties": {
    "iso:country":"AU",
    "sg:address":"410 North East Rd",
    "sg:city":"Windsor Gardens",
    "sg:classifiers":[
        {
            "category":"Sports & Exercise",
            "subcategory":"Playing Field",
            "type":"Entertainment"
        }
    ],
    "sg:phone":"+61 8 8261 3522",
    "sg:postcode":"5087",
    "sg:province":"SA",
    "sg:tags":[
        "gaming",
        "venue"
    ],
    "wof:name":"Adelaides Windsor Hotel Pty Ltd",
    "wof:placetype":"venue"
},
  "geometry": {"coordinates":[138.64494323700001,-34.8655014038],"type":"Point"}
}