{
  "type": "Feature",
  "properties": {
    "addr:full":"Shp 2 Nelson Bay Rd Salt Ash NSW 2318",
    "addr:housenumber":"2",
    "addr:postcode":"2318",
    "addr:street":"Nelson Bay Rd",
    "iso:country":"AU",
    "sg:address":"Shp 2 Nelson Bay Rd",
    "sg:city":"Salt Ash",
    "sg:classifiers":[
        {
            "category":"Cafe",
            "type":"Food & Drink"
        }
    ],
    "sg:phone":"+61 2 4982 6855",
    "sg:postcode":"2318",
    "sg:province":"NSW",
    "wof:name":"Saxby Bakery Hunters At Greenhills",
    "wof:placetype":"venue"
},
  "geometry": {"coordinates":[151.88299599999999,-32.803127],"type":"Point"}
}