{
  "type": "Feature",
  "properties": {
    "addr:full":"Cnr Fitzgerald Rd & Westgate Drv Laverton North VIC 3026",
    "addr:postcode":"3026",
    "addr:street":"Cnr Fitzgerald Rd & Westgate Drv",
    "iso:country":"AU",
    "sg:address":"Cnr Fitzgerald Rd & Westgate Drv",
    "sg:city":"Laverton North",
    "sg:classifiers":[
        {
            "category":"Freight",
            "type":"Transportation"
        }
    ],
    "sg:phone":"+61 3 9369 6300",
    "sg:postcode":"3026",
    "sg:province":"VIC",
    "sg:tags":[
        "car",
        "carrier",
        "transporting"
    ],
    "wof:name":"Adelaide Car Express",
    "wof:placetype":"venue"
},
  "geometry": {"coordinates":[144.78637699999999,-37.821983],"type":"Point"}
}