{
  "type": "Feature",
  "properties": {
    "addr:full":"37 Robinson Rd Virginia QLD 4014",
    "addr:housenumber":"37",
    "addr:postcode":"4014",
    "addr:street":"Robinson Rd",
    "iso:country":"AU",
    "sg:address":"37 Robinson Rd",
    "sg:city":"Virginia",
    "sg:classifiers":[
        {
            "category":"Home & Garden",
            "subcategory":"Carpets & Floor Coverings",
            "type":"Retail Goods"
        }
    ],
    "sg:phone":"+61 7 3266 8822",
    "sg:postcode":"4014",
    "sg:province":"QLD",
    "sg:tags":[
        "mattress"
    ],
    "wof:name":"Bedzz Direct",
    "wof:placetype":"venue"
},
  "geometry": {"coordinates":[153.05986023,-27.3701133728],"type":"Point"}
}