{
  "type": "Feature",
  "properties": {
    "iso:country":"AU",
    "sg:address":"PO Box 150",
    "sg:city":"Palmwoods",
    "sg:classifiers":[
        {
            "category":"Farming",
            "subcategory":"Nursery",
            "type":"Manufacturing & Wholesale Goods"
        }
    ],
    "sg:phone":"+61 7 5442 3045",
    "sg:postcode":"4555",
    "sg:province":"QLD",
    "wof:name":"Australian Plant Specialists",
    "wof:placetype":"venue"
},
  "geometry": {"coordinates":[152.956207275,-26.6875400543],"type":"Point"}
}