{
  "type": "Feature",
  "properties": {
    "addr:full":"194 Bambra Rd Caulfield South VIC 3162",
    "addr:housenumber":"194",
    "addr:postcode":"3162",
    "addr:street":"Bambra Rd",
    "iso:country":"AU",
    "sg:address":"194 Bambra Rd",
    "sg:city":"Caulfield South",
    "sg:classifiers":[
        {
            "category":"Shopping",
            "subcategory":"Computers & Home Electronics",
            "type":"Retail Goods"
        }
    ],
    "sg:phone":"+61 3 9571 0355",
    "sg:postcode":"3162",
    "sg:province":"VIC",
    "sg:tags":[
        "equipment",
        "multimedia"
    ],
    "wof:name":"Taletold",
    "wof:placetype":"venue"
},
  "geometry": {"coordinates":[145.02877807600001,-37.888710022],"type":"Point"}
}