{
  "type": "Feature",
  "properties": {
    "addr:full":"132 Boulder Rd Kalgoorlie WA 6430",
    "addr:housenumber":"132",
    "addr:postcode":"6430",
    "addr:street":"Boulder Rd",
    "iso:country":"AU",
    "sg:address":"132 Boulder Rd",
    "sg:city":"Kalgoorlie",
    "sg:classifiers":[
        {
            "category":"Manufacturing",
            "subcategory":"Food",
            "type":"Manufacturing & Wholesale Goods"
        }
    ],
    "sg:phone":"+61 8 9021 3441",
    "sg:postcode":"6430",
    "sg:province":"WA",
    "sg:tags":[
        "function",
        "catering"
    ],
    "wof:name":"KFC",
    "wof:placetype":"venue"
},
  "geometry": {"coordinates":[121.47624206499999,-30.748046875],"type":"Point"}
}