{
  "type": "Feature",
  "properties": {
    "addr:full":"94 Rivergum Drv Morayfield QLD 4506",
    "addr:housenumber":"94",
    "addr:postcode":"4506",
    "addr:street":"Rivergum Drv",
    "iso:country":"AU",
    "sg:address":"94 Rivergum Drv",
    "sg:city":"Morayfield",
    "sg:classifiers":[
        {
            "category":"Commercial Area",
            "type":"Public Place"
        }
    ],
    "sg:phone":"+61 7 5495 2330",
    "sg:postcode":"4506",
    "sg:province":"QLD",
    "sg:tags":[
        "heavy",
        "carrier"
    ],
    "wof:name":"Topp & Co. Haulage",
    "wof:placetype":"venue"
},
  "geometry": {"coordinates":[152.934204102,-27.1528377533],"type":"Point"}
}