{
  "type": "Feature",
  "properties": {
    "addr:full":"PO Box 322 Moree NSW 2400",
    "addr:postcode":"2400",
    "iso:country":"AU",
    "sg:address":"PO Box 322",
    "sg:city":"Moree",
    "sg:classifiers":[
        {
            "category":"Building & Trades",
            "subcategory":"Construction",
            "type":"Services"
        }
    ],
    "sg:phone":"+61 408 668 887",
    "sg:postcode":"2400",
    "sg:province":"NSW",
    "sg:tags":[
        "joiner",
        "carpenter"
    ],
    "wof:name":"Michael Hellmann",
    "wof:placetype":"venue"
},
  "geometry": {"coordinates":[149.841598511,-29.4661998749],"type":"Point"}
}