{
  "type": "Feature",
  "properties": {
    "addr:full":"PMB 3 Alyangula 0885 Alyangula NT 0885",
    "addr:housenumber":"3",
    "addr:postcode":"0885;nt 0885",
    "addr:street":"Alyangula",
    "iso:country":"AU",
    "sg:address":"PMB 3 Alyangula 0885",
    "sg:city":"Alyangula",
    "sg:classifiers":[
        {
            "category":"Education",
            "subcategory":"School",
            "type":"Public Place"
        }
    ],
    "sg:phone":"+61 8 8987 6366",
    "sg:postcode":"0885",
    "sg:province":"NT",
    "sg:tags":[
        "state",
        "except",
        "nsw"
    ],
    "wof:name":"Alyangula Area School",
    "wof:placetype":"venue"
},
  "geometry": {"coordinates":[136.42091400000001,-13.85047],"type":"Point"}
}