{
  "type": "Feature",
  "properties": {
    "addr:full":"32- 34 Station St Engadine NSW 2233",
    "addr:housenumber":"34",
    "addr:postcode":"2233",
    "addr:street":"Station St",
    "iso:country":"AU",
    "sg:address":"32- 34 Station St",
    "sg:city":"Engadine",
    "sg:classifiers":[
        {
            "category":"Sports & Exercise",
            "subcategory":"Ski Slope",
            "type":"Entertainment"
        }
    ],
    "sg:phone":"+61 2 9520 2719",
    "sg:postcode":"2233",
    "sg:province":"NSW",
    "sg:tags":[
        "equipment",
        "hire",
        "retail",
        "snow"
    ],
    "wof:name":"Island Aclassic Surf & Snow",
    "wof:placetype":"venue"
},
  "geometry": {"coordinates":[151.01400756800001,-34.0667037964],"type":"Point"}
}