{
  "type": "Feature",
  "properties": {
    "iso:country":"AU",
    "sg:address":"2 Norman St",
    "sg:city":"Woodville",
    "sg:classifiers":[
        {
            "category":"Professional",
            "subcategory":"Business Services",
            "type":"Services"
        }
    ],
    "sg:phone":"+61 8 8244 7831",
    "sg:postcode":"5011",
    "sg:province":"SA",
    "sg:tags":[
        "drafting"
    ],
    "wof:name":"Abela Design & Drafting",
    "wof:placetype":"venue"
},
  "geometry": {"coordinates":[138.53715515100001,-34.8789901733],"type":"Point"}
}