{
  "type": "Feature",
  "properties": {
    "addr:full":"22/ 4 Aileen Crs Burnie TAS 7320",
    "addr:housenumber":"22 / 4",
    "addr:postcode":"7320",
    "addr:street":"Aileen Crs",
    "iso:country":"AU",
    "sg:address":"22/ 4 Aileen Crs",
    "sg:city":"Burnie",
    "sg:classifiers":[
        {
            "category":"Professional",
            "subcategory":"Employment Agencies",
            "type":"Services"
        }
    ],
    "sg:phone":"+61 407 334 615",
    "sg:postcode":"7320",
    "sg:province":"TAS",
    "sg:tags":[
        "hire",
        "labour",
        "contractor"
    ],
    "wof:name":"Aus Personnel Hire",
    "wof:placetype":"venue"
},
  "geometry": {"coordinates":[145.89825400000001,-41.075859],"type":"Point"}
}