{
  "type": "Feature",
  "properties": {
    "addr:full":"2/ 244a Darling St Balmain NSW 2041",
    "addr:housenumber":"/ 244a",
    "addr:postcode":"2041",
    "addr:street":"Darling St",
    "iso:country":"AU",
    "sg:address":"2/ 244a Darling St",
    "sg:city":"Balmain",
    "sg:classifiers":[
        {
            "category":"Personal",
            "subcategory":"Massage",
            "type":"Services"
        }
    ],
    "sg:phone":"+61 2 9555 5121",
    "sg:postcode":"2041",
    "sg:province":"NSW",
    "sg:tags":[
        "therapy"
    ],
    "wof:name":"Balmain Massage Centre",
    "wof:placetype":"venue"
},
  "geometry": {"coordinates":[151.18255600000001,-33.857922],"type":"Point"}
}