{
  "type": "Feature",
  "properties": {
    "iso:country":"AU",
    "sg:address":"2/ 244a Darling St",
    "sg:city":"Balmain",
    "sg:classifiers":[
        {
            "category":"Personal",
            "subcategory":"Massage",
            "type":"Services"
        }
    ],
    "sg:phone":"+61 2 9555 5121",
    "sg:postcode":"2041",
    "sg:province":"NSW",
    "sg:tags":[
        "therapy"
    ],
    "wof:name":"Balmain Massage Centre",
    "wof:placetype":"venue"
},
  "geometry": {"coordinates":[151.182556,-33.857922],"type":"Point"}
}