{
  "type": "Feature",
  "properties": {
    "addr:full":"Boyd St Tugun QLD 4224",
    "addr:postcode":"4224",
    "addr:street":"Boyd St",
    "iso:country":"AU",
    "sg:address":"Boyd St",
    "sg:city":"Tugun",
    "sg:classifiers":[
        {
            "category":"Health Services",
            "subcategory":"Doctor",
            "type":"Services"
        }
    ],
    "sg:phone":"+61 7 5598 9190",
    "sg:postcode":"4224",
    "sg:province":"QLD",
    "sg:tags":[
        "medical",
        "practitioner"
    ],
    "wof:name":"Jackson Adrian",
    "wof:placetype":"venue"
},
  "geometry": {"coordinates":[153.49902343799999,-28.1515522003],"type":"Point"}
}