{
  "type": "Feature",
  "properties": {
    "addr:full":"Junction Bridge Farm RMB 2620 Gingin Brook Rd Gingin WA 6503",
    "addr:postcode":"6503",
    "addr:street":"Gingin Brook Rd",
    "iso:country":"AU",
    "sg:address":"Junction Bridge Farm RMB 2620 Gingin Brook Rd",
    "sg:city":"Gingin",
    "sg:classifiers":[
        {
            "category":"Farming",
            "subcategory":"Poultry Farm",
            "type":"Manufacturing & Wholesale Goods"
        }
    ],
    "sg:phone":"+61 8 9575 7600",
    "sg:postcode":"6503",
    "sg:province":"WA",
    "sg:tags":[
        "farmer"
    ],
    "wof:name":"Junction Bridge Farm",
    "wof:placetype":"venue"
},
  "geometry": {"coordinates":[115.69873800000001,-31.316263],"type":"Point"}
}