{
  "type": "Feature",
  "properties": {
    "addr:full":"Perth Modern School 90 Roberts Rd Subiaco WA 6008",
    "addr:housenumber":"90",
    "addr:postcode":"6008",
    "addr:street":"Roberts Rd",
    "iso:country":"AU",
    "sg:address":"Perth Modern School 90 Roberts Rd",
    "sg:city":"Subiaco",
    "sg:classifiers":[
        {
            "category":"Education",
            "subcategory":"School",
            "type":"Public Place"
        }
    ],
    "sg:phone":"+61 8 9380 0555",
    "sg:postcode":"6008",
    "sg:province":"WA",
    "sg:tags":[
        "state",
        "except",
        "nsw"
    ],
    "wof:name":"Schools Government (Public)",
    "wof:placetype":"venue"
},
  "geometry": {"coordinates":[115.839317322,-31.9452323914],"type":"Point"}
}