{
  "type": "Feature",
  "properties": {
    "addr:full":"Old Tumbarumba Rd Batlow NSW 2730",
    "addr:postcode":"2730",
    "addr:street":"Tumbarumba Rd",
    "iso:country":"AU",
    "sg:address":"Old Tumbarumba Rd",
    "sg:city":"Batlow",
    "sg:classifiers":[
        {
            "category":"Farming",
            "subcategory":"Orchard",
            "type":"Manufacturing & Wholesale Goods"
        }
    ],
    "sg:phone":"+61 2 6949 1765",
    "sg:postcode":"2730",
    "sg:province":"NSW",
    "sg:tags":[
        "pear",
        "apple",
        "grower"
    ],
    "wof:name":"Mount View Orchards Batlow",
    "wof:placetype":"venue"
},
  "geometry": {"coordinates":[148.099503,-35.529709],"type":"Point"}
}