{
  "type": "Feature",
  "properties": {
    "iso:country":"AU",
    "sg:address":"Shop 12/ 14 Clarence St",
    "sg:city":"Port Macquarie",
    "sg:classifiers":[
        {
            "category":"Personal",
            "subcategory":"Beauty Salon",
            "type":"Services"
        }
    ],
    "sg:phone":"+61 2 6583 3544",
    "sg:postcode":"2444",
    "sg:province":"NSW",
    "sg:tags":[
        "hairdresser"
    ],
    "wof:name":"Beauty Sanctum The",
    "wof:placetype":"venue"
},
  "geometry": {"coordinates":[152.91192599999999,-31.429075],"type":"Point"}
}