{
  "type": "Feature",
  "properties": {
    "iso:country":"AU",
    "sg:address":"755 Burke Rd",
    "sg:city":"Camberwell",
    "sg:classifiers":[
        {
            "category":"Retail",
            "subcategory":"Repair Shop",
            "type":"Services"
        }
    ],
    "sg:phone":"+61 3 9882 3099",
    "sg:postcode":"3124",
    "sg:province":"VIC",
    "sg:tags":[
        "handbag"
    ],
    "wof:name":"Bag Factory Pty Ltd The",
    "wof:placetype":"venue"
},
  "geometry": {"coordinates":[145.05674743599999,-37.8301773071],"type":"Point"}
}