{
  "type": "Feature",
  "properties": {
    "iso:country":"AU",
    "sg:address":"83 Richland Ave",
    "sg:city":"Coopers Plains",
    "sg:classifiers":[
        {
            "category":"Home & Garden",
            "subcategory":"Home Furnishings",
            "type":"Retail Goods"
        }
    ],
    "sg:phone":"+61 7 3275 2419",
    "sg:postcode":"4108",
    "sg:province":"QLD",
    "sg:tags":[
        "wholesaler",
        "wallpaper",
        "mfrs",
        "wallcoverings"
    ],
    "wof:name":"Oasis Enterprises",
    "wof:placetype":"venue"
},
  "geometry": {"coordinates":[153.02821350100001,-27.5652389526],"type":"Point"}
}