{
  "type": "Feature",
  "properties": {
    "addr:full":"89 Yeedong Rd Falcon WA 6210",
    "addr:housenumber":"89",
    "addr:postcode":"6210",
    "addr:street":"Yeedong Rd",
    "iso:country":"AU",
    "sg:address":"89 Yeedong Rd",
    "sg:city":"Falcon",
    "sg:classifiers":[
        {
            "category":"Building & Trades",
            "subcategory":"Construction",
            "type":"Services"
        }
    ],
    "sg:phone":"+61 8 9534 2838",
    "sg:postcode":"6210",
    "sg:province":"WA",
    "sg:tags":[
        "earth",
        "excavating",
        "moving",
        "contractor"
    ],
    "wof:name":"South Side Earth Moving",
    "wof:placetype":"venue"
},
  "geometry": {"coordinates":[115.654861,-32.588196],"type":"Point"}
}