{
  "type": "Feature",
  "properties": {
    "iso:country":"AU",
    "sg:address":"45 Roebuck St",
    "sg:city":"Newtown",
    "sg:classifiers":[
        {
            "category":"Building & Trades",
            "subcategory":"Construction",
            "type":"Services"
        }
    ],
    "sg:phone":"+61 418 525 588",
    "sg:postcode":"3220",
    "sg:province":"VIC",
    "sg:tags":[
        "contractor"
    ],
    "wof:name":"Grigg Wes",
    "wof:placetype":"venue"
},
  "geometry": {"coordinates":[144.360016,-38.160843],"type":"Point"}
}