{
  "type": "Feature",
  "properties": {
    "addr:full":"127 Lower Dandenong Rd Mentone VIC 3194",
    "addr:housenumber":"127",
    "addr:postcode":"3194",
    "addr:street":"Lower Dandenong Rd",
    "iso:country":"AU",
    "sg:address":"127 Lower Dandenong Rd",
    "sg:city":"Mentone",
    "sg:classifiers":[
        {
            "category":"Fast Food",
            "type":"Food & Drink"
        }
    ],
    "sg:phone":"+61 3 9585 1034",
    "sg:postcode":"3194",
    "sg:province":"VIC",
    "sg:tags":[
        "away",
        "take"
    ],
    "wof:name":"Giovanni's Pizzeria",
    "wof:placetype":"venue"
},
  "geometry": {"coordinates":[145.085662842,-37.9835929871],"type":"Point"}
}