{
  "type": "Feature",
  "properties": {
    "addr:full":"5 Karne St Sanctuary Point NSW 2540",
    "addr:housenumber":"5",
    "addr:postcode":"2540",
    "addr:street":"Karne St",
    "iso:country":"AU",
    "sg:address":"5 Karne St",
    "sg:city":"Sanctuary Point",
    "sg:classifiers":[
        {
            "category":"Professional",
            "subcategory":"Business Services",
            "type":"Services"
        }
    ],
    "sg:phone":"+61 2 4443 8664",
    "sg:postcode":"2540",
    "sg:province":"NSW",
    "sg:tags":[
        "drafting"
    ],
    "wof:name":"Cadstuctions Pty Ltd",
    "wof:placetype":"venue"
},
  "geometry": {"coordinates":[150.63645935100001,-35.1118583679],"type":"Point"}
}