{
  "type": "Feature",
  "properties": {
    "addr:full":"52 Glen St Aspendale VIC 3195",
    "addr:housenumber":"52",
    "addr:postcode":"3195",
    "addr:street":"Glen St",
    "iso:country":"AU",
    "sg:address":"52 Glen St",
    "sg:city":"Aspendale",
    "sg:classifiers":[
        {
            "category":"Education",
            "subcategory":"Special Training",
            "type":"Public Place"
        }
    ],
    "sg:phone":"+61 3 9587 1859",
    "sg:postcode":"3195",
    "sg:province":"VIC",
    "sg:tags":[
        "school",
        "sailing"
    ],
    "wof:name":"Bayside Sailing Sea School",
    "wof:placetype":"venue"
},
  "geometry": {"coordinates":[145.10667419399999,-38.0217247009],"type":"Point"}
}