{
  "type": "Feature",
  "properties": {
    "addr:full":"Great Eastern Hwy Northam WA 6401",
    "addr:postcode":"6401",
    "addr:street":"Eastern Hwy",
    "iso:country":"AU",
    "sg:address":"Great Eastern Hwy",
    "sg:city":"Northam",
    "sg:classifiers":[
        {
            "category":"Arena",
            "subcategory":"Sports Club",
            "type":"Entertainment"
        }
    ],
    "sg:phone":"+61 8 9622 7765",
    "sg:postcode":"6401",
    "sg:province":"WA",
    "sg:tags":[
        "hunt",
        "racing"
    ],
    "wof:name":"Northam Race Club",
    "wof:placetype":"venue"
},
  "geometry": {"coordinates":[116.65460967999999,-31.6309757233],"type":"Point"}
}