{
  "type": "Feature",
  "properties": {
    "addr:full":"45a Monaro St Queanbeyan ACT 2620",
    "addr:housenumber":"45a",
    "addr:postcode":"2620",
    "addr:street":"Monaro St",
    "iso:country":"AU",
    "sg:address":"45a Monaro St",
    "sg:city":"Queanbeyan",
    "sg:classifiers":[
        {
            "category":"Fast Food",
            "type":"Food & Drink"
        }
    ],
    "sg:phone":"+61 2 6297 1071",
    "sg:postcode":"2620",
    "sg:province":"ACT",
    "sg:tags":[
        "away",
        "take"
    ],
    "wof:name":"Melita Food Bar",
    "wof:placetype":"venue"
},
  "geometry": {"coordinates":[149.161865234,-35.4787063599],"type":"Point"}
}