{
  "type": "Feature",
  "properties": {
    "addr:full":"Benaroon Rd Belmore NSW 2192",
    "addr:postcode":"2192",
    "addr:street":"Benaroon Rd",
    "iso:country":"AU",
    "sg:address":"Benaroon Rd",
    "sg:city":"Belmore",
    "sg:classifiers":[
        {
            "category":"Shopping",
            "subcategory":"Stationery & Office Supplies",
            "type":"Retail Goods"
        }
    ],
    "sg:phone":"+61 2 9758 0980",
    "sg:postcode":"2192",
    "sg:province":"NSW",
    "sg:tags":[
        "partition"
    ],
    "wof:name":"Gridmans Pty Ltd",
    "wof:placetype":"venue"
},
  "geometry": {"coordinates":[151.08122299999999,-33.915836],"type":"Point"}
}