{
  "type": "Feature",
  "properties": {
    "addr:full":"9 Nicholson St Brunswick East VIC 3057",
    "addr:housenumber":"9",
    "addr:postcode":"3057",
    "addr:street":"Nicholson St",
    "iso:country":"AU",
    "sg:address":"9 Nicholson St",
    "sg:city":"Brunswick East",
    "sg:classifiers":[
        {
            "category":"Fast Food",
            "type":"Food & Drink"
        }
    ],
    "sg:phone":"+61 3 9387 3306",
    "sg:postcode":"3057",
    "sg:province":"VIC",
    "sg:tags":[
        "away",
        "take"
    ],
    "wof:name":"Wendy's Fish & Chips Shop",
    "wof:placetype":"venue"
},
  "geometry": {"coordinates":[144.97793579099999,-37.7795982361],"type":"Point"}
}