{
  "type": "Feature",
  "properties": {
    "addr:full":"153 Rakow St Broken Hill NSW 2880",
    "addr:housenumber":"153",
    "addr:postcode":"2880",
    "addr:street":"Rakow St",
    "iso:country":"AU",
    "sg:address":"153 Rakow St",
    "sg:city":"Broken Hill",
    "sg:classifiers":[
        {
            "category":"Travel",
            "subcategory":"Hotels & Motels",
            "type":"Entertainment"
        }
    ],
    "sg:phone":"+61 8 8087 3558",
    "sg:postcode":"2880",
    "sg:province":"NSW",
    "wof:name":"Sturt Motel",
    "wof:placetype":"venue"
},
  "geometry": {"coordinates":[141.442260742,-31.9588432312],"type":"Point"}
}