{
  "type": "Feature",
  "properties": {
    "iso:country":"AU",
    "sg:address":"9 Cross St",
    "sg:city":"Red Hill",
    "sg:classifiers":[
        {
            "category":"Building & Trades",
            "subcategory":"Construction",
            "type":"Services"
        }
    ],
    "sg:phone":"+61 7 3369 6317",
    "sg:postcode":"4059",
    "sg:province":"QLD",
    "sg:tags":[
        "contractor"
    ],
    "wof:name":"Zumbo Francesco",
    "wof:placetype":"venue"
},
  "geometry": {"coordinates":[153.006256103,-27.4526672363],"type":"Point"}
}