{
  "type": "Feature",
  "properties": {
    "iso:country":"AU",
    "sg:address":"Shop 5 48 Cross St",
    "sg:city":"Old Bar",
    "sg:classifiers":[
        {
            "category":"Personal",
            "subcategory":"Beauty Salon",
            "type":"Services"
        }
    ],
    "sg:phone":"+61 2 6553 3322",
    "sg:postcode":"2430",
    "sg:province":"NSW",
    "sg:tags":[
        "hairdresser"
    ],
    "wof:name":"Artistry Hair Design",
    "wof:placetype":"venue"
},
  "geometry": {"coordinates":[152.584656,-31.969875],"type":"Point"}
}