{
  "type": "Feature",
  "properties": {
    "addr:full":"2 Carbeen St Tieri QLD 4709",
    "addr:housenumber":"2",
    "addr:postcode":"4709",
    "addr:street":"Carbeen St",
    "iso:country":"AU",
    "sg:address":"2 Carbeen St",
    "sg:city":"Tieri",
    "sg:classifiers":[
        {
            "category":"Social Services",
            "subcategory":"Child Care",
            "type":"Services"
        }
    ],
    "sg:phone":"+61 7 4984 8554",
    "sg:postcode":"4709",
    "sg:province":"QLD",
    "wof:name":"Tieri Day Care Centre",
    "wof:placetype":"venue"
},
  "geometry": {"coordinates":[148.34051513700001,-23.0340518951],"type":"Point"}
}