{
  "type": "Feature",
  "properties": {
    "addr:full":"4 Mengal Crt Salisbury South SA 5106",
    "addr:housenumber":"4",
    "addr:postcode":"5106",
    "addr:street":"Mengal Crt",
    "iso:country":"AU",
    "sg:address":"4 Mengal Crt",
    "sg:city":"Salisbury South",
    "sg:classifiers":[
        {
            "category":"Home & Garden",
            "subcategory":"Building Materials",
            "type":"Retail Goods"
        }
    ],
    "sg:phone":"+61 8 8283 4352",
    "sg:postcode":"5106",
    "sg:province":"SA",
    "sg:tags":[
        "fitting",
        "door"
    ],
    "wof:name":"Adelaide Bifolds",
    "wof:placetype":"venue"
},
  "geometry": {"coordinates":[138.64558400000001,-34.787514],"type":"Point"}
}