{
  "type": "Feature",
  "properties": {
    "addr:full":"PO Box 1664 Wangara PLB WA 6947",
    "addr:postcode":"6947",
    "iso:country":"AU",
    "sg:address":"PO Box 1664",
    "sg:city":"Wangara PLB",
    "sg:classifiers":[
        {
            "category":"Building & Trades",
            "subcategory":"Plumbing",
            "type":"Services"
        }
    ],
    "sg:phone":"+61 8 9304 1812",
    "sg:postcode":"6947",
    "sg:province":"WA",
    "sg:tags":[
        "plumber",
        "gasfitters"
    ],
    "wof:name":"Bobs Budget Drain Cleaning Service",
    "wof:placetype":"venue"
},
  "geometry": {"coordinates":[115.83036041299999,-31.7966709137],"type":"Point"}
}