{
  "type": "Feature",
  "properties": {
    "addr:full":"30 Kingtel Pl Geebung QLD 4034",
    "addr:housenumber":"30",
    "addr:postcode":"4034",
    "addr:street":"Kingtel Pl",
    "iso:country":"AU",
    "sg:address":"30 Kingtel Pl",
    "sg:city":"Geebung",
    "sg:classifiers":[
        {
            "category":"Shopping",
            "subcategory":"Stationery & Office Supplies",
            "type":"Retail Goods"
        }
    ],
    "sg:phone":"+61 7 3265 1188",
    "sg:postcode":"4034",
    "sg:province":"QLD",
    "sg:tags":[
        "packaging",
        "equipment",
        "sealing",
        "filling"
    ],
    "wof:name":"Promark Packaging Pty Ltd",
    "wof:placetype":"venue"
},
  "geometry": {"coordinates":[153.05188000000001,-27.367582],"type":"Point"}
}