{
  "type": "Feature",
  "properties": {
    "iso:country":"AU",
    "sg:address":"191 St Georges Rd",
    "sg:city":"Fitzroy North",
    "sg:classifiers":[
        {
            "category":"Sports & Exercise",
            "subcategory":"Gym",
            "type":"Entertainment"
        }
    ],
    "sg:phone":"+61 3 9486 2822",
    "sg:postcode":"3068",
    "sg:province":"VIC",
    "sg:tags":[
        "health",
        "fitness"
    ],
    "wof:name":"healthy fit",
    "wof:placetype":"venue"
},
  "geometry": {"coordinates":[144.984176636,-37.7831420898],"type":"Point"}
}