{
  "type": "Feature",
  "properties": {
    "addr:full":"David Jones 310 Bourke St Melbourne VIC 3000",
    "addr:housenumber":"310",
    "addr:postcode":"3000",
    "addr:street":"Bourke St",
    "iso:country":"AU",
    "sg:address":"David Jones 310 Bourke St",
    "sg:city":"Melbourne",
    "sg:classifiers":[
        {
            "category":"Shopping",
            "subcategory":"Clothing, Apparel, & Fashions",
            "type":"Retail Goods"
        }
    ],
    "sg:phone":"+61 3 9639 1507",
    "sg:postcode":"3000",
    "sg:province":"VIC",
    "sg:tags":[
        "lady",
        "wear"
    ],
    "wof:name":"Carla Zampatti Pty Ltd",
    "wof:placetype":"venue"
},
  "geometry": {"coordinates":[144.95574951200001,-37.8154945374],"type":"Point"}
}