{
  "type": "Feature",
  "properties": {
    "addr:full":"23 Lawrence St Harbord NSW 2096",
    "addr:housenumber":"23",
    "addr:postcode":"2096",
    "addr:street":"Lawrence St",
    "iso:country":"AU",
    "sg:address":"23 Lawrence St",
    "sg:city":"Harbord",
    "sg:classifiers":[
        {
            "category":"Health Services",
            "subcategory":"Health Practitioner",
            "type":"Services"
        }
    ],
    "sg:phone":"+61 2 9938 5263",
    "sg:postcode":"2096",
    "sg:province":"NSW",
    "sg:tags":[
        "acupuncture"
    ],
    "wof:name":"Wong-See H M",
    "wof:placetype":"venue"
},
  "geometry": {"coordinates":[151.28419494600001,-33.7787094116],"type":"Point"}
}