{
  "type": "Feature",
  "properties": {
    "addr:full":"4 Kiah Crs Sheidow Park SA 5158",
    "addr:housenumber":"4",
    "addr:postcode":"5158",
    "addr:street":"Kiah Crs",
    "iso:country":"AU",
    "sg:address":"4 Kiah Crs",
    "sg:city":"Sheidow Park",
    "sg:classifiers":[
        {
            "category":"Personal",
            "subcategory":"Beauty Salon",
            "type":"Services"
        }
    ],
    "sg:phone":"+61 413 595 000",
    "sg:postcode":"5158",
    "sg:province":"SA",
    "sg:tags":[
        "supply",
        "artist",
        "make-up"
    ],
    "wof:name":"Marked By Mark",
    "wof:placetype":"venue"
},
  "geometry": {"coordinates":[138.5284729,-35.073638916],"type":"Point"}
}