{
  "type": "Feature",
  "properties": {
    "addr:full":"Old Sturt Hwy Berri SA 5343",
    "addr:postcode":"5343",
    "addr:street":"Sturt Hwy",
    "iso:country":"AU",
    "sg:address":"Old Sturt Hwy",
    "sg:city":"Berri",
    "sg:classifiers":[
        {
            "category":"Industrial Area",
            "type":"Public Place"
        }
    ],
    "sg:phone":"+61 8 8582 3020",
    "sg:postcode":"5343",
    "sg:province":"SA",
    "sg:tags":[
        "rural",
        "shed"
    ],
    "wof:name":"Hoffys Steel Engineering & Erections",
    "wof:placetype":"venue"
},
  "geometry": {"coordinates":[140.595214844,-34.2835884094],"type":"Point"}
}