{
  "type": "Feature",
  "properties": {
    "iso:country":"AU",
    "sg:address":"Cnr Harbour Rd & Graeme Heggie St",
    "sg:city":"Mackay",
    "sg:classifiers":[
        {
            "category":"Utilities",
            "subcategory":"Recycling",
            "type":"Services"
        }
    ],
    "sg:phone":"+61 7 4955 6864",
    "sg:postcode":"4740",
    "sg:province":"QLD",
    "wof:name":"Smorgonsteel Recycling",
    "wof:placetype":"venue"
},
  "geometry": {"coordinates":[149.190369,-21.128302],"type":"Point"}
}