{
  "type": "Feature",
  "properties": {
    "addr:full":"155 Rosamund Rd Highpoint City VIC 3032",
    "addr:housenumber":"155",
    "addr:postcode":"3032",
    "addr:street":"Rosamund Rd",
    "iso:country":"AU",
    "sg:address":"155 Rosamund Rd",
    "sg:city":"Highpoint City",
    "sg:classifiers":[
        {
            "category":"Retail",
            "subcategory":"Auto Repair",
            "type":"Services"
        }
    ],
    "sg:phone":"+61 3 9318 5666",
    "sg:postcode":"3032",
    "sg:province":"VIC",
    "sg:tags":[
        "clutch",
        "brake"
    ],
    "wof:name":"Brakes Plus",
    "wof:placetype":"venue"
},
  "geometry": {"coordinates":[144.88548299999999,-37.775105],"type":"Point"}
}