{
  "type": "Feature",
  "properties": {
    "addr:full":"15 Sheldon Pl Sunshine West VIC 3020",
    "addr:housenumber":"15",
    "addr:postcode":"3020",
    "addr:street":"Sheldon Pl",
    "iso:country":"AU",
    "sg:address":"15 Sheldon Pl",
    "sg:city":"Sunshine West",
    "sg:classifiers":[
        {
            "category":"Shopping",
            "subcategory":"Crafts & Fabrics",
            "type":"Retail Goods"
        }
    ],
    "sg:phone":"+61 3 9363 3978",
    "sg:postcode":"3020",
    "sg:province":"VIC",
    "sg:tags":[
        "synthetic",
        "canvas",
        "product"
    ],
    "wof:name":"Four Seasons Canvas Prod",
    "wof:placetype":"venue"
},
  "geometry": {"coordinates":[144.804474,-37.794235],"type":"Point"}
}