{
  "type": "Feature",
  "properties": {
    "addr:full":"43 Grange Rd Hindmarsh West SA 5007",
    "addr:housenumber":"43",
    "addr:postcode":"5007",
    "addr:street":"Grange Rd",
    "iso:country":"AU",
    "sg:address":"43 Grange Rd",
    "sg:city":"Hindmarsh West",
    "sg:classifiers":[
        {
            "category":"Personal",
            "subcategory":"Beauty Salon",
            "type":"Services"
        }
    ],
    "sg:phone":"+61 8 8346 6937",
    "sg:postcode":"5007",
    "sg:province":"SA",
    "sg:tags":[
        "hairdresser"
    ],
    "wof:name":"Silver Scissors",
    "wof:placetype":"venue"
},
  "geometry": {"coordinates":[138.56158447300001,-34.9039459229],"type":"Point"}
}