{
  "type": "Feature",
  "properties": {
    "iso:country":"AU",
    "sg:address":"Baxter-Tooradin Rd",
    "sg:city":"Baxter",
    "sg:classifiers":[
        {
            "category":"Retail",
            "subcategory":"Event Space",
            "type":"Services"
        }
    ],
    "sg:phone":"+61 400 870 388",
    "sg:postcode":"3911",
    "sg:province":"VIC",
    "sg:tags":[
        "function",
        "organiser"
    ],
    "wof:name":"Baxter Masonic Hall",
    "wof:placetype":"venue"
},
  "geometry": {"coordinates":[145.166213989,-38.1964683533],"type":"Point"}
}