{
  "type": "Feature",
  "properties": {
    "addr:full":"University of Queensland, Warrego Hwy Gatton College QLD 4345",
    "addr:postcode":"4345",
    "addr:street":"Warrego Hwy",
    "iso:country":"AU",
    "sg:address":"University of Queensland, Warrego Hwy",
    "sg:city":"Gatton College",
    "sg:classifiers":[
        {
            "category":"Social Services",
            "subcategory":"Child Care",
            "type":"Services"
        }
    ],
    "sg:phone":"+61 7 5460 1080",
    "sg:postcode":"4345",
    "sg:province":"QLD",
    "wof:name":"Nyamul Child Care Centre (Gatton).",
    "wof:placetype":"venue"
},
  "geometry": {"coordinates":[152.332275391,-27.548084259],"type":"Point"}
}