{
  "type": "Feature",
  "properties": {
    "addr:full":"Shop 2, 143 Palmerin St Warwick QLD 4370",
    "addr:housenumber":"shop 2",
    "addr:postcode":"143;4370",
    "addr:street":"Palmerin St",
    "iso:country":"AU",
    "sg:address":"Shop 2, 143 Palmerin St",
    "sg:city":"Warwick",
    "sg:classifiers":[
        {
            "category":"Shopping",
            "subcategory":"Luggage & Leather Goods",
            "type":"Retail Goods"
        }
    ],
    "sg:phone":"+61 7 4661 4111",
    "sg:postcode":"4370",
    "sg:province":"QLD",
    "wof:name":"Showtime Saddelry",
    "wof:placetype":"venue"
},
  "geometry": {"coordinates":[152.03222656200001,-28.2175521851],"type":"Point"}
}