{
  "type": "Feature",
  "properties": {
    "iso:country":"AU",
    "sg:address":"124 Boniface St",
    "sg:city":"Archerfield",
    "sg:classifiers":[
        {
            "category":"Wholesale",
            "subcategory":"Auto Parts",
            "type":"Manufacturing & Wholesale Goods"
        }
    ],
    "sg:phone":"+61 7 3255 5700",
    "sg:postcode":"4108",
    "sg:province":"QLD",
    "sg:tags":[
        "tyre"
    ],
    "wof:name":"Kenda Tyres",
    "wof:placetype":"venue"
},
  "geometry": {"coordinates":[153.01994323700001,-27.5642566681],"type":"Point"}
}