{
  "type": "Feature",
  "properties": {
    "iso:country":"AU",
    "sg:address":"239 Bay St",
    "sg:city":"Brighton",
    "sg:classifiers":[
        {
            "category":"Real Estate",
            "subcategory":"Architect",
            "type":"Services"
        }
    ],
    "sg:phone":"+61 3 9596 8411",
    "sg:postcode":"3186",
    "sg:province":"VIC",
    "wof:name":"JDA Architects",
    "wof:placetype":"venue"
},
  "geometry": {"coordinates":[145.002853394,-37.8971099854],"type":"Point"}
}