{
  "type": "Feature",
  "properties": {
    "addr:full":"1 Spring Rd Highett VIC 3190",
    "addr:housenumber":"1",
    "addr:postcode":"3190",
    "addr:street":"Spring Rd",
    "iso:country":"AU",
    "sg:address":"1 Spring Rd",
    "sg:city":"Highett",
    "sg:classifiers":[
        {
            "category":"Personal",
            "subcategory":"Beauty Salon",
            "type":"Services"
        }
    ],
    "sg:phone":"+61 3 9532 0207",
    "sg:postcode":"3190",
    "sg:province":"VIC",
    "sg:tags":[
        "hairdresser"
    ],
    "wof:name":"Golden Mirror Salon The",
    "wof:placetype":"venue"
},
  "geometry": {"coordinates":[145.031784058,-37.9474258423],"type":"Point"}
}