{
  "type": "Feature",
  "properties": {
    "iso:country":"AU",
    "sg:address":"108 George St",
    "sg:city":"East Maitland",
    "sg:classifiers":[
        {
            "category":"Professional",
            "subcategory":"Lawyer & Legal Services",
            "type":"Services"
        }
    ],
    "sg:phone":"+61 2 4933 3333",
    "sg:postcode":"2323",
    "sg:province":"NSW",
    "sg:tags":[
        "process",
        "server"
    ],
    "wof:name":"Carwell Mercantile Agency",
    "wof:placetype":"venue"
},
  "geometry": {"coordinates":[151.588180542,-32.750957489],"type":"Point"}
}