{
  "type": "Feature",
  "properties": {
    "iso:country":"AU",
    "sg:address":"87a Foster St",
    "sg:city":"Dandenong",
    "sg:classifiers":[
        {
            "category":"Real Estate",
            "subcategory":"Real Estate Services",
            "type":"Services"
        }
    ],
    "sg:phone":"+61 3 9793 3488",
    "sg:postcode":"3175",
    "sg:province":"VIC",
    "sg:tags":[
        "valuer"
    ],
    "wof:name":"Propertylinx Valuations & Advisory",
    "wof:placetype":"venue"
},
  "geometry": {"coordinates":[145.21232605,-37.9898071289],"type":"Point"}
}