{
  "type": "Feature",
  "properties": {
    "addr:full":"25 Lyton St Blacktown NSW 2148",
    "addr:housenumber":"25",
    "addr:postcode":"2148",
    "addr:street":"Lyton St",
    "iso:country":"AU",
    "sg:address":"25 Lyton St",
    "sg:city":"Blacktown",
    "sg:classifiers":[
        {
            "category":"Farming",
            "subcategory":"Poultry Farm",
            "type":"Manufacturing & Wholesale Goods"
        }
    ],
    "sg:phone":"+61 2 9671 5380",
    "sg:postcode":"2148",
    "sg:province":"NSW",
    "sg:tags":[
        "breeder",
        "bird"
    ],
    "wof:name":"Bird Breeders Information Line",
    "wof:placetype":"venue"
},
  "geometry": {"coordinates":[150.8931427,-33.7655677795],"type":"Point"}
}