{
  "type": "Feature",
  "properties": {
    "addr:full":"Level 3/ 146 Bundall Rd Bundall QLD 4217",
    "addr:housenumber":"/ 146",
    "addr:postcode":"4217",
    "addr:street":"Bundall Rd",
    "iso:country":"AU",
    "sg:address":"Level 3/ 146 Bundall Rd",
    "sg:city":"Bundall",
    "sg:classifiers":[
        {
            "category":"Banks & Credit Unions",
            "subcategory":"Financial Services",
            "type":"Services"
        }
    ],
    "sg:phone":"+61 7 5574 3712",
    "sg:postcode":"4217",
    "sg:province":"QLD",
    "sg:tags":[
        "financier"
    ],
    "wof:name":"The Finance Division Pty Ltd",
    "wof:placetype":"venue"
},
  "geometry": {"coordinates":[153.41401672399999,-28.0007076263],"type":"Point"}
}