{
  "type": "Feature",
  "properties": {
    "addr:full":"40 Ridgway Drv Flagstaff Hill SA 5159",
    "addr:housenumber":"40",
    "addr:postcode":"5159",
    "addr:street":"Ridgway Drv",
    "iso:country":"AU",
    "sg:address":"40 Ridgway Drv",
    "sg:city":"Flagstaff Hill",
    "sg:classifiers":[
        {
            "category":"Professional",
            "subcategory":"Art Services",
            "type":"Services"
        }
    ],
    "sg:phone":"+61 411 346 973",
    "sg:postcode":"5159",
    "sg:province":"SA",
    "sg:tags":[
        "decorator",
        "painter"
    ],
    "wof:name":"DS Painting & Decorating",
    "wof:placetype":"venue"
},
  "geometry": {"coordinates":[138.587493897,-35.051071167],"type":"Point"}
}