{
  "type": "Feature",
  "properties": {
    "addr:full":"Cnr Fourth Ave & Seventh Ave Austral NSW 2171",
    "addr:postcode":"2171",
    "addr:street":"Cnr Fourth Ave & Seventh Ave Austral",
    "iso:country":"AU",
    "sg:address":"Cnr Fourth Ave & Seventh Ave",
    "sg:city":"Austral",
    "sg:classifiers":[
        {
            "category":"Wholesale",
            "subcategory":"Auto Parts",
            "type":"Manufacturing & Wholesale Goods"
        }
    ],
    "sg:phone":"+61 2 9606 9516",
    "sg:postcode":"2171",
    "sg:province":"NSW",
    "sg:tags":[
        "recyclers"
    ],
    "wof:name":"Austral Wreckers",
    "wof:placetype":"venue"
},
  "geometry": {"coordinates":[150.80409240700001,-33.9408454895],"type":"Point"}
}