{
  "type": "Feature",
  "properties": {
    "iso:country":"AU",
    "sg:address":"Shp2/ 1932 Logan Rd",
    "sg:city":"Upper Mt Gravatt",
    "sg:classifiers":[
        {
            "category":"Fast Food",
            "type":"Food & Drink"
        }
    ],
    "sg:phone":"+61 7 3420 5027",
    "sg:postcode":"4122",
    "sg:province":"QLD",
    "sg:tags":[
        "away",
        "take"
    ],
    "wof:name":"Village Fresh Kebabs",
    "wof:placetype":"venue"
},
  "geometry": {"coordinates":[153.080352783,-27.5569229126],"type":"Point"}
}