{
  "type": "Feature",
  "properties": {
    "iso:country":"AU",
    "sg:address":"85 Milton St",
    "sg:city":"Ashfield",
    "sg:classifiers":[
        {
            "category":"Health Services",
            "subcategory":"Health Practitioner",
            "type":"Services"
        }
    ],
    "sg:phone":"+61 2 9716 6633",
    "sg:postcode":"2131",
    "sg:province":"NSW",
    "sg:tags":[
        "psychologist"
    ],
    "wof:name":"Drobny Juliette",
    "wof:placetype":"venue"
},
  "geometry": {"coordinates":[151.116943359,-33.8920555115],"type":"Point"}
}