{
  "type": "Feature",
  "properties": {
    "addr:full":"17 Gorman St Willoughby NSW 2068",
    "addr:housenumber":"17",
    "addr:postcode":"2068",
    "addr:street":"Gorman St",
    "iso:country":"AU",
    "sg:address":"17 Gorman St",
    "sg:city":"Willoughby",
    "sg:classifiers":[
        {
            "category":"Professional",
            "subcategory":"Engineering",
            "type":"Services"
        }
    ],
    "sg:phone":"+61 2 9405 5631",
    "sg:postcode":"2068",
    "sg:province":"NSW",
    "sg:tags":[
        "consulting",
        "engineer"
    ],
    "wof:name":"Terrey Civil & Rail Pty Ltd",
    "wof:placetype":"venue"
},
  "geometry": {"coordinates":[151.19784545900001,-33.8085174561],"type":"Point"}
}