{
  "type": "Feature",
  "properties": {
    "addr:full":"5 Dowie Crt Romsey VIC 3434",
    "addr:housenumber":"5",
    "addr:postcode":"3434",
    "addr:street":"Dowie Crt",
    "iso:country":"AU",
    "sg:address":"5 Dowie Crt",
    "sg:city":"Romsey",
    "sg:classifiers":[
        {
            "category":"Farming",
            "subcategory":"Nursery",
            "type":"Manufacturing & Wholesale Goods"
        }
    ],
    "sg:phone":"+61 3 5429 5991",
    "sg:postcode":"3434",
    "sg:province":"VIC",
    "wof:name":"Phil's Conifers",
    "wof:placetype":"venue"
},
  "geometry": {"coordinates":[144.753173828,-37.3483200073],"type":"Point"}
}