{
  "type": "Feature",
  "properties": {
    "iso:country":"AU",
    "sg:address":"Cnr Slater & Webber Pde",
    "sg:city":"Keilor East",
    "sg:classifiers":[
        {
            "category":"Wholesale",
            "subcategory":"Auto Parts",
            "type":"Manufacturing & Wholesale Goods"
        }
    ],
    "sg:phone":"+61 3 9331 6669",
    "sg:postcode":"3033",
    "sg:province":"VIC",
    "sg:tags":[
        "recyclers"
    ],
    "wof:name":"Mazdaman",
    "wof:placetype":"venue"
},
  "geometry": {"coordinates":[144.85501099999999,-37.736553],"type":"Point"}
}