{
  "type": "Feature",
  "properties": {
    "addr:full":"Cnr of Sanger & River Street Corowa NSW 2646",
    "addr:postcode":"2646",
    "addr:street":"Street",
    "iso:country":"AU",
    "sg:address":"Cnr of Sanger & River Street",
    "sg:city":"Corowa",
    "sg:classifiers":[
        {
            "category":"Personal",
            "subcategory":"Beauty Salon",
            "type":"Services"
        }
    ],
    "sg:phone":"+61 2 6033 1313",
    "sg:postcode":"2646",
    "sg:province":"NSW",
    "sg:tags":[
        "hairdresser"
    ],
    "wof:name":"Corowa Hair Design",
    "wof:placetype":"venue"
},
  "geometry": {"coordinates":[146.391189575,-35.9954185486],"type":"Point"}
}