{
  "type": "Feature",
  "properties": {
    "addr:full":"37 Albert St Moe VIC 3825",
    "addr:housenumber":"37",
    "addr:postcode":"3825",
    "addr:street":"Albert St",
    "iso:country":"AU",
    "sg:address":"37 Albert St",
    "sg:city":"Moe",
    "sg:classifiers":[
        {
            "category":"Health Services",
            "subcategory":"Chiropractor",
            "type":"Services"
        }
    ],
    "sg:phone":"+61 3 5127 5757",
    "sg:postcode":"3825",
    "sg:province":"VIC",
    "wof:name":"Gippsland Chiropractic Centre",
    "wof:placetype":"venue"
},
  "geometry": {"coordinates":[146.264816,-38.175034],"type":"Point"}
}