{
  "type": "Feature",
  "properties": {
    "addr:full":"Nelson Bay RSL Shoal Bay Rd Nelson Bay NSW 2315",
    "addr:postcode":"2315",
    "addr:street":"Shoal Bay Rd",
    "iso:country":"AU",
    "sg:address":"Nelson Bay RSL Shoal Bay Rd",
    "sg:city":"Nelson Bay",
    "sg:classifiers":[
        {
            "category":"Sports & Exercise",
            "subcategory":"Gym",
            "type":"Entertainment"
        }
    ],
    "sg:phone":"+61 2 4984 8335",
    "sg:postcode":"2315",
    "sg:province":"NSW",
    "sg:tags":[
        "health",
        "fitness"
    ],
    "wof:name":"Club Fitness",
    "wof:placetype":"venue"
},
  "geometry": {"coordinates":[152.15107699999999,-32.716469],"type":"Point"}
}