{
  "type": "Feature",
  "properties": {
    "iso:country":"AU",
    "sg:address":"Shop 7, Boulevard Shopng Cntr 31 Gayton Rd",
    "sg:city":"City Beach",
    "sg:classifiers":[
        {
            "category":"Personal",
            "subcategory":"Beauty Salon",
            "type":"Services"
        }
    ],
    "sg:phone":"+61 8 9385 7371",
    "sg:postcode":"6015",
    "sg:province":"WA",
    "wof:name":"Boulevard Skin And Beauty Centre",
    "wof:placetype":"venue"
},
  "geometry": {"coordinates":[115.76764679,-31.9261741638],"type":"Point"}
}