{
  "type": "Feature",
  "properties": {
    "addr:full":"280 Auburn Rd Hawthorn VIC 3122",
    "addr:housenumber":"280",
    "addr:postcode":"3122",
    "addr:street":"Auburn Rd",
    "iso:country":"AU",
    "sg:address":"280 Auburn Rd",
    "sg:city":"Hawthorn",
    "sg:classifiers":[
        {
            "category":"Retail",
            "subcategory":"Storage",
            "type":"Services"
        }
    ],
    "sg:phone":"+61 3 9815 1044",
    "sg:postcode":"3122",
    "sg:province":"VIC",
    "sg:tags":[
        "removal",
        "furniture"
    ],
    "wof:name":"Australian Backload Express",
    "wof:placetype":"venue"
},
  "geometry": {"coordinates":[145.04356384299999,-37.8294754028],"type":"Point"}
}