{
  "type": "Feature",
  "properties": {
    "iso:country":"AU",
    "sg:address":"208 Pioneer Rd",
    "sg:city":"Yarrambat",
    "sg:classifiers":[
        {
            "category":"Farming",
            "subcategory":"Farm & Veterinary Services",
            "type":"Manufacturing & Wholesale Goods"
        }
    ],
    "sg:phone":"+61 417 052 949",
    "sg:postcode":"3091",
    "sg:province":"VIC",
    "sg:tags":[
        "irrigation",
        "reticulation",
        "system"
    ],
    "wof:name":"Northern Turf & Irrigation",
    "wof:placetype":"venue"
},
  "geometry": {"coordinates":[145.13653564399999,-37.6462478638],"type":"Point"}
}