{
  "type": "Feature",
  "properties": {
    "addr:full":"63 Corin St West Launceston TAS 7250",
    "addr:housenumber":"63",
    "addr:postcode":"7250",
    "addr:street":"Corin St West",
    "iso:country":"AU",
    "sg:address":"63 Corin St",
    "sg:city":"West Launceston",
    "sg:classifiers":[
        {
            "category":"Real Estate",
            "subcategory":"Architect",
            "type":"Services"
        }
    ],
    "sg:phone":"+61 3 6343 2642",
    "sg:postcode":"7250",
    "sg:province":"TAS",
    "sg:tags":[
        "building",
        "designer"
    ],
    "wof:name":"Diez Designs",
    "wof:placetype":"venue"
},
  "geometry": {"coordinates":[147.120269775,-41.4602165222],"type":"Point"}
}