{
  "type": "Feature",
  "properties": {
    "addr:full":"Church St Healesville VIC 3777",
    "addr:postcode":"3777",
    "addr:street":"Church St",
    "iso:country":"AU",
    "sg:address":"Church St",
    "sg:city":"Healesville",
    "sg:classifiers":[
        {
            "category":"Health Services",
            "subcategory":"Health Practitioner",
            "type":"Services"
        }
    ],
    "sg:phone":"+61 402 783 635",
    "sg:postcode":"3777",
    "sg:province":"VIC",
    "sg:tags":[
        "psychologist"
    ],
    "wof:name":"Hocking Sandra",
    "wof:placetype":"venue"
},
  "geometry": {"coordinates":[145.514084,-37.653973],"type":"Point"}
}