{
  "type": "Feature",
  "properties": {
    "iso:country":"AU",
    "sg:address":"Suite 202, 15 Marine Pde",
    "sg:city":"Southport",
    "sg:classifiers":[
        {
            "category":"Health Services",
            "subcategory":"Doctor",
            "type":"Services"
        }
    ],
    "sg:phone":"+61 7 5591 7309",
    "sg:postcode":"4215",
    "sg:province":"QLD",
    "sg:tags":[
        "medical",
        "practitioner"
    ],
    "wof:name":"Alex Liew Dr",
    "wof:placetype":"venue"
},
  "geometry": {"coordinates":[153.41726684599999,-27.9711284637],"type":"Point"}
}