{
  "type": "Feature",
  "properties": {
    "addr:full":"Level 2 74-76 Whiting St Artarmon NSW 2064",
    "addr:housenumber":"74-76",
    "addr:postcode":"2064",
    "addr:street":"Whiting St",
    "iso:country":"AU",
    "sg:address":"Level 2 74-76 Whiting St",
    "sg:city":"Artarmon",
    "sg:classifiers":[
        {
            "category":"Banks & Credit Unions",
            "subcategory":"Bureau De Change",
            "type":"Services"
        }
    ],
    "sg:phone":"+61 2 9439 3999",
    "sg:postcode":"2064",
    "sg:province":"NSW",
    "sg:tags":[
        "preparation",
        "processing",
        "data"
    ],
    "wof:name":"Axiom Databases Pty Ltd",
    "wof:placetype":"venue"
},
  "geometry": {"coordinates":[151.180145264,-33.8169174194],"type":"Point"}
}