{
  "type": "Feature",
  "properties": {
    "addr:full":"47 Maguires Rd Maraylya NSW 2765",
    "addr:housenumber":"47",
    "addr:postcode":"2765",
    "addr:street":"Maguires Rd",
    "iso:country":"AU",
    "sg:address":"47 Maguires Rd",
    "sg:city":"Maraylya",
    "sg:classifiers":[
        {
            "category":"Education",
            "subcategory":"Dance Studio",
            "type":"Public Place"
        }
    ],
    "sg:phone":"+61 417 221 338",
    "sg:postcode":"2765",
    "sg:province":"NSW",
    "sg:tags":[
        "training",
        "video",
        "film"
    ],
    "wof:name":"Machine Men Film Services",
    "wof:placetype":"venue"
},
  "geometry": {"coordinates":[150.90782165499999,-33.6132240295],"type":"Point"}
}