{
  "type": "Feature",
  "properties": {
    "addr:full":"18 Sweaney St Inverell NSW 2360",
    "addr:housenumber":"18",
    "addr:postcode":"2360",
    "addr:street":"Sweaney St",
    "iso:country":"AU",
    "sg:address":"18 Sweaney St",
    "sg:city":"Inverell",
    "sg:classifiers":[
        {
            "category":"Shopping",
            "type":"Retail Goods"
        }
    ],
    "sg:phone":"+61 2 6721 1576",
    "sg:postcode":"2360",
    "sg:province":"NSW",
    "sg:tags":[
        "agent",
        "stock"
    ],
    "wof:name":"Baldwin McGregors",
    "wof:placetype":"venue"
},
  "geometry": {"coordinates":[151.11491394000001,-29.7701683044],"type":"Point"}
}