{
  "type": "Feature",
  "properties": {
    "iso:country":"AU",
    "sg:address":"\"The 12 Mile\"",
    "sg:city":"Boonah",
    "sg:classifiers":[
        {
            "category":"Building & Trades",
            "subcategory":"Landscaping Services",
            "type":"Services"
        }
    ],
    "sg:phone":"+61 7 5463 5955",
    "sg:postcode":"4310",
    "sg:province":"QLD",
    "sg:tags":[
        "grazier"
    ],
    "wof:name":"Smith S H O",
    "wof:placetype":"venue"
},
  "geometry": {"coordinates":[152.68232727,-27.9942798615],"type":"Point"}
}