{
  "type": "Feature",
  "properties": {
    "addr:full":"Cumberland Ave Nowra NSW 2541",
    "addr:postcode":"2541",
    "addr:street":"Cumberland Ave",
    "iso:country":"AU",
    "sg:address":"Cumberland Ave",
    "sg:city":"Nowra",
    "sg:classifiers":[
        {
            "category":"Home & Garden",
            "subcategory":"Building Materials",
            "type":"Retail Goods"
        }
    ],
    "sg:phone":"+61 2 4423 1166",
    "sg:postcode":"2541",
    "sg:province":"NSW",
    "sg:tags":[
        "pre-mixed",
        "concrete"
    ],
    "wof:name":"CSR Readymix Concrete",
    "wof:placetype":"venue"
},
  "geometry": {"coordinates":[150.586868286,-34.908744812],"type":"Point"}
}