{
  "type": "Feature",
  "properties": {
    "addr:full":"9439 Western Hwy Ballarat VIC 3352",
    "addr:housenumber":"9439",
    "addr:postcode":"3352",
    "addr:street":"Western Hwy",
    "iso:country":"AU",
    "sg:address":"9439 Western Hwy",
    "sg:city":"Ballarat",
    "sg:classifiers":[
        {
            "category":"Retail",
            "subcategory":"Auto Repair",
            "type":"Services"
        }
    ],
    "sg:phone":"+61 3 5334 8194",
    "sg:postcode":"3352",
    "sg:province":"VIC",
    "sg:tags":[
        "camper-trailers",
        "caravan",
        "servicing"
    ],
    "wof:name":"Trounce Caravans",
    "wof:placetype":"venue"
},
  "geometry": {"coordinates":[143.92884799999999,-37.562935],"type":"Point"}
}