{
  "type": "Feature",
  "properties": {
    "addr:full":"Factory 3/ 30 Industrial Drv Hoppers Crossing VIC 3029",
    "addr:housenumber":"/ 30",
    "addr:postcode":"3029",
    "addr:street":"Industrial Drv",
    "iso:country":"AU",
    "sg:address":"Factory 3/ 30 Industrial Drv",
    "sg:city":"Hoppers Crossing",
    "sg:classifiers":[
        {
            "category":"Home & Garden",
            "subcategory":"Garden Supply",
            "type":"Retail Goods"
        }
    ],
    "sg:phone":"+61 414 920 933",
    "sg:postcode":"3029",
    "sg:province":"VIC",
    "sg:tags":[
        "equipment"
    ],
    "wof:name":"D G Light Engineereing",
    "wof:placetype":"venue"
},
  "geometry": {"coordinates":[144.72860700000001,-37.867855],"type":"Point"}
}