{
  "type": "Feature",
  "properties": {
    "iso:country":"AU",
    "sg:address":"7 Watson Rd",
    "sg:city":"Padstow",
    "sg:classifiers":[
        {
            "category":"Manufacturing",
            "subcategory":"Petroleum Products",
            "type":"Manufacturing & Wholesale Goods"
        }
    ],
    "sg:phone":"+61 2 9792 3262",
    "sg:postcode":"2211",
    "sg:province":"NSW",
    "sg:tags":[
        "fuel",
        "oil",
        "additive"
    ],
    "wof:name":"Fuel 2 Race Pty Ltd",
    "wof:placetype":"venue"
},
  "geometry": {"coordinates":[151.035675,-33.944561],"type":"Point"}
}