{
  "type": "Feature",
  "properties": {
    "iso:country":"AU",
    "sg:address":"38 Fernlea St",
    "sg:city":"Geebung",
    "sg:classifiers":[
        {
            "category":"Building & Trades",
            "subcategory":"Plumbing",
            "type":"Services"
        }
    ],
    "sg:phone":"+61 7 3359 3436",
    "sg:postcode":"4034",
    "sg:province":"QLD",
    "sg:tags":[
        "plumber",
        "gasfitters"
    ],
    "wof:name":"John Angove Plumbing",
    "wof:placetype":"venue"
},
  "geometry": {"coordinates":[153.036697,-27.369722],"type":"Point"}
}