{
  "type": "Feature",
  "properties": {
    "addr:full":"438 Oxford St Paddington NSW 2021",
    "addr:housenumber":"438",
    "addr:postcode":"2021",
    "addr:street":"Oxford St",
    "iso:country":"AU",
    "sg:address":"438 Oxford St",
    "sg:city":"Paddington",
    "sg:classifiers":[
        {
            "category":"Food & Beverages",
            "subcategory":"Bakery",
            "type":"Retail Goods"
        }
    ],
    "sg:phone":"+61 2 9332 3700",
    "sg:postcode":"2021",
    "sg:province":"NSW",
    "sg:tags":[
        "cake",
        "shop",
        "pastry"
    ],
    "wof:name":"The Cupcake Bakery Pty Ltd",
    "wof:placetype":"venue"
},
  "geometry": {"coordinates":[151.23130798299999,-33.8876457214],"type":"Point"}
}