{
  "type": "Feature",
  "properties": {
    "addr:full":"Creek Rd (cnr Pickwick St) Cannon Hill QLD 4170",
    "addr:postcode":"4170",
    "addr:street":"Creek Rd Cnr Pickwick St",
    "iso:country":"AU",
    "sg:address":"Creek Rd",
    "sg:city":"(cnr Pickwick St) Cannon Hill",
    "sg:classifiers":[
        {
            "category":"Autos & Motor Vehicles",
            "subcategory":"Fuel & Gas Station",
            "type":"Retail Goods"
        }
    ],
    "sg:phone":"+61 7 3399 2734",
    "sg:postcode":"4170",
    "sg:province":"QLD",
    "wof:name":"Shell",
    "wof:placetype":"venue"
},
  "geometry": {"coordinates":[153.09820556599999,-27.458530426],"type":"Point"}
}