{
  "type": "Feature",
  "properties": {
    "iso:country":"AU",
    "sg:address":"Waldeck St",
    "sg:city":"Dongara",
    "sg:classifiers":[
        {
            "category":"Travel",
            "subcategory":"Hotels & Motels",
            "type":"Entertainment"
        }
    ],
    "sg:phone":"+61 8 9927 1200",
    "sg:postcode":"6525",
    "sg:province":"WA",
    "sg:tags":[
        "accommodation"
    ],
    "wof:name":"Dongara Old Mill Motel",
    "wof:placetype":"venue"
},
  "geometry": {"coordinates":[114.93122863799999,-29.24974823],"type":"Point"}
}