{
  "type": "Feature",
  "properties": {
    "addr:full":"23w Fitzroy St Walcha NSW 2354",
    "addr:housenumber":"23w",
    "addr:postcode":"2354",
    "addr:street":"Fitzroy St",
    "iso:country":"AU",
    "sg:address":"23w Fitzroy St",
    "sg:city":"Walcha",
    "sg:classifiers":[
        {
            "category":"Food & Beverages",
            "subcategory":"Bakery",
            "type":"Retail Goods"
        }
    ],
    "sg:phone":"+61 2 6777 1202",
    "sg:postcode":"2354",
    "sg:province":"NSW",
    "sg:tags":[
        "baker"
    ],
    "wof:name":"Moons Bakery",
    "wof:placetype":"venue"
},
  "geometry": {"coordinates":[151.586135864,-30.9839096069],"type":"Point"}
}