{
  "type": "Feature",
  "properties": {
    "iso:country":"AU",
    "sg:address":"21 Lauretta Ave",
    "sg:city":"Springwood",
    "sg:classifiers":[
        {
            "category":"Professional",
            "subcategory":"Art Services",
            "type":"Services"
        }
    ],
    "sg:phone":"+61 7 3208 4159",
    "sg:postcode":"4127",
    "sg:province":"QLD",
    "sg:tags":[
        "decorator",
        "painter"
    ],
    "wof:name":"Project Painting Contractors",
    "wof:placetype":"venue"
},
  "geometry": {"coordinates":[153.13053894000001,-27.6118106842],"type":"Point"}
}