{
  "type": "Feature",
  "properties": {
    "addr:full":"55 Tully St South Townsville QLD 4810",
    "addr:housenumber":"55",
    "addr:postcode":"4810",
    "addr:street":"Tully St",
    "iso:country":"AU",
    "sg:address":"55 Tully St",
    "sg:city":"South Townsville",
    "sg:classifiers":[
        {
            "category":"Arts & Performance",
            "subcategory":"Music",
            "type":"Entertainment"
        }
    ],
    "sg:phone":"+61 419 026 895",
    "sg:postcode":"4810",
    "sg:province":"QLD",
    "sg:tags":[
        "mobile",
        "jockey",
        "disc"
    ],
    "wof:name":"The Sound Space Mobile Disco & PA",
    "wof:placetype":"venue"
},
  "geometry": {"coordinates":[146.824432,-19.267229],"type":"Point"}
}