{
  "type": "Feature",
  "properties": {
    "addr:full":"7 Ocean St Maroochydore QLD 4558",
    "addr:housenumber":"7",
    "addr:postcode":"4558",
    "addr:street":"Ocean St",
    "iso:country":"AU",
    "sg:address":"7 Ocean St",
    "sg:city":"Maroochydore",
    "sg:classifiers":[
        {
            "category":"Banks & Credit Unions",
            "subcategory":"Investment Brokerage",
            "type":"Services"
        }
    ],
    "sg:phone":"+61 1300 881 460",
    "sg:postcode":"4558",
    "sg:province":"QLD",
    "sg:tags":[
        "finance",
        "broker"
    ],
    "wof:name":"Investor Finace P/L",
    "wof:placetype":"venue"
},
  "geometry": {"coordinates":[153.09120178200001,-26.6518287659],"type":"Point"}
}