{
  "type": "Feature",
  "properties": {
    "addr:full":"7 Hudson La Terrigal NSW 2260",
    "addr:housenumber":"7",
    "addr:postcode":"2260",
    "addr:street":"Hudson La",
    "iso:country":"AU",
    "sg:address":"7 Hudson La",
    "sg:city":"Terrigal",
    "sg:classifiers":[
        {
            "category":"Personal",
            "subcategory":"Beauty Salon",
            "type":"Services"
        }
    ],
    "sg:phone":"+61 2 4385 2137",
    "sg:postcode":"2260",
    "sg:province":"NSW",
    "sg:tags":[
        "supply",
        "artist",
        "make-up"
    ],
    "wof:name":"Serenity Beauty Care",
    "wof:placetype":"venue"
},
  "geometry": {"coordinates":[151.44444300000001,-33.447334],"type":"Point"}
}