{
  "type": "Feature",
  "properties": {
    "iso:country":"AU",
    "sg:address":"Factory 5 / 93 Wells Rd",
    "sg:city":"Chelsea Heights",
    "sg:classifiers":[
        {
            "category":"Structure",
            "subcategory":"Building",
            "type":"Public Place"
        }
    ],
    "sg:phone":"+61 411 108 554",
    "sg:postcode":"3196",
    "sg:province":"VIC",
    "sg:tags":[
        "sail",
        "shade"
    ],
    "wof:name":"Sunsoft Shade Cloth Systems Australia Pty Ltd",
    "wof:placetype":"venue"
},
  "geometry": {"coordinates":[145.13446044899999,-38.0337486267],"type":"Point"}
}