{
  "type": "Feature",
  "properties": {
    "addr:full":"100 Sharp St Cooma NSW 2630",
    "addr:housenumber":"100",
    "addr:postcode":"2630",
    "addr:street":"Sharp St",
    "iso:country":"AU",
    "sg:address":"100 Sharp St",
    "sg:city":"Cooma",
    "sg:classifiers":[
        {
            "category":"Food & Beverages",
            "subcategory":"Bakery",
            "type":"Retail Goods"
        }
    ],
    "sg:phone":"+61 2 6452 5159",
    "sg:postcode":"2630",
    "sg:province":"NSW",
    "sg:tags":[
        "baker"
    ],
    "wof:name":"Pastry Box The",
    "wof:placetype":"venue"
},
  "geometry": {"coordinates":[149.13409423799999,-36.2312316895],"type":"Point"}
}