{
  "type": "Feature",
  "properties": {
    "addr:full":"126 Melrose St Mt Pleasant SA 5235",
    "addr:housenumber":"126",
    "addr:postcode":"5235",
    "addr:street":"Melrose St",
    "iso:country":"AU",
    "sg:address":"126 Melrose St",
    "sg:city":"Mt Pleasant",
    "sg:classifiers":[
        {
            "category":"Fast Food",
            "type":"Food & Drink"
        }
    ],
    "sg:phone":"+61 8 8568 2888",
    "sg:postcode":"5235",
    "sg:province":"SA",
    "sg:tags":[
        "away",
        "take"
    ],
    "wof:name":"Steam & Whistle Bakery-Take Away",
    "wof:placetype":"venue"
},
  "geometry": {"coordinates":[139.05082702600001,-34.7734146118],"type":"Point"}
}