{
  "type": "Feature",
  "properties": {
    "iso:country":"AU",
    "sg:address":"80 Roberts St",
    "sg:city":"Osborne Park",
    "sg:classifiers":[
        {
            "category":"Building & Trades",
            "subcategory":"Construction",
            "type":"Services"
        }
    ],
    "sg:phone":"+61 8 9444 5766",
    "sg:postcode":"6017",
    "sg:province":"WA",
    "sg:tags":[
        "contractor"
    ],
    "wof:name":"Universal Constructions Pty Ltd",
    "wof:placetype":"venue"
},
  "geometry": {"coordinates":[115.826148987,-31.9079647064],"type":"Point"}
}