{
  "type": "Feature",
  "properties": {
    "addr:full":"PO Box 4440 Dubbo NSW 2830",
    "addr:postcode":"2830",
    "iso:country":"AU",
    "sg:address":"PO Box 4440",
    "sg:city":"Dubbo",
    "sg:classifiers":[
        {
            "category":"Building & Trades",
            "subcategory":"Pest Control",
            "type":"Services"
        }
    ],
    "sg:phone":"+61 2 6882 6427",
    "sg:postcode":"2830",
    "sg:province":"NSW",
    "wof:name":"Watts Don Pest Control",
    "wof:placetype":"venue"
},
  "geometry": {"coordinates":[148.60118102999999,-32.2478713989],"type":"Point"}
}