{
  "type": "Feature",
  "properties": {
    "iso:country":"AU",
    "sg:address":"C/o Coles Express, Cnr Main St & Joyce Ave",
    "sg:city":"Greensborough",
    "sg:classifiers":[
        {
            "category":"Retail",
            "subcategory":"Auto Repair",
            "type":"Services"
        }
    ],
    "sg:phone":"+61 3 9434 7453",
    "sg:postcode":"3088",
    "sg:province":"VIC",
    "sg:tags":[
        "repairer",
        "motor",
        "engineer"
    ],
    "wof:name":"Kmart Tyre & Auto Service",
    "wof:placetype":"venue"
},
  "geometry": {"coordinates":[145.10263061500001,-37.7043380737],"type":"Point"}
}