{
  "type": "Feature",
  "properties": {
    "addr:full":"7 Underwood Rd Homebush NSW 2140",
    "addr:housenumber":"7",
    "addr:postcode":"2140",
    "addr:street":"Underwood Rd",
    "iso:country":"AU",
    "sg:address":"7 Underwood Rd",
    "sg:city":"Homebush",
    "sg:classifiers":[
        {
            "category":"Insurance",
            "subcategory":"Insurance Agent",
            "type":"Services"
        }
    ],
    "sg:phone":"+61 2 9763 1455",
    "sg:postcode":"2140",
    "sg:province":"NSW",
    "sg:tags":[
        "broker"
    ],
    "wof:name":"IEA (Brokers) Pty Ltd",
    "wof:placetype":"venue"
},
  "geometry": {"coordinates":[151.07876586899999,-33.8553657532],"type":"Point"}
}