{
  "type": "Feature",
  "properties": {
    "iso:country":"AU",
    "sg:address":"Shop 9 Isabella St",
    "sg:city":"Wingham",
    "sg:classifiers":[
        {
            "category":"Personal",
            "subcategory":"Beauty Salon",
            "type":"Services"
        }
    ],
    "sg:phone":"+61 2 6553 4581",
    "sg:postcode":"2429",
    "sg:province":"NSW",
    "sg:tags":[
        "hairdresser"
    ],
    "wof:name":"Nardas New Generation",
    "wof:placetype":"venue"
},
  "geometry": {"coordinates":[152.372269,-31.868788],"type":"Point"}
}