{
  "type": "Feature",
  "properties": {
    "addr:full":"Shop 9 Isabella St Wingham NSW 2429",
    "addr:housenumber":"shop 9",
    "addr:postcode":"2429",
    "addr:street":"Isabella St",
    "iso:country":"AU",
    "sg:address":"Shop 9 Isabella St",
    "sg:city":"Wingham",
    "sg:classifiers":[
        {
            "category":"Personal",
            "subcategory":"Beauty Salon",
            "type":"Services"
        }
    ],
    "sg:phone":"+61 2 6553 4581",
    "sg:postcode":"2429",
    "sg:province":"NSW",
    "sg:tags":[
        "hairdresser"
    ],
    "wof:name":"Nardas New Generation",
    "wof:placetype":"venue"
},
  "geometry": {"coordinates":[152.37226899999999,-31.868788],"type":"Point"}
}