{
  "type": "Feature",
  "properties": {
    "iso:country":"AU",
    "sg:address":"Shop 6/ 232 Carlisle St",
    "sg:city":"St Kilda East",
    "sg:classifiers":[
        {
            "category":"Personal",
            "subcategory":"Shoe Repair & Shine",
            "type":"Services"
        }
    ],
    "sg:phone":"+61 3 9534 4260",
    "sg:postcode":"3183",
    "sg:province":"VIC",
    "sg:tags":[
        "footwear"
    ],
    "wof:name":"Keyworx",
    "wof:placetype":"venue"
},
  "geometry": {"coordinates":[144.99183654800001,-37.8684158325],"type":"Point"}
}