{
  "type": "Feature",
  "properties": {
    "addr:full":"14 Scott St Cairns QLD 4870",
    "addr:housenumber":"14",
    "addr:postcode":"4870",
    "addr:street":"Scott St",
    "iso:country":"AU",
    "sg:address":"14 Scott St",
    "sg:city":"Cairns",
    "sg:classifiers":[
        {
            "category":"Shopping",
            "subcategory":"Party Supplies",
            "type":"Retail Goods"
        }
    ],
    "sg:phone":"+61 7 4052 1521",
    "sg:postcode":"4870",
    "sg:province":"QLD",
    "sg:tags":[
        "hire",
        "costume"
    ],
    "wof:name":"Cairns Costume Hire",
    "wof:placetype":"venue"
},
  "geometry": {"coordinates":[145.752243042,-16.9400634766],"type":"Point"}
}