{
  "type": "Feature",
  "properties": {
    "addr:full":"6 Longview Crt Thomastown VIC 3074",
    "addr:housenumber":"6",
    "addr:postcode":"3074",
    "addr:street":"Longview Crt",
    "iso:country":"AU",
    "sg:address":"6 Longview Crt",
    "sg:city":"Thomastown",
    "sg:classifiers":[
        {
            "category":"Retail",
            "subcategory":"Funeral Services",
            "type":"Services"
        }
    ],
    "sg:phone":"+61 3 9466 1111",
    "sg:postcode":"3074",
    "sg:province":"VIC",
    "sg:tags":[
        "supply"
    ],
    "wof:name":"Coachcraft Engineering",
    "wof:placetype":"venue"
},
  "geometry": {"coordinates":[145.04307556099999,-37.6900749207],"type":"Point"}
}