{
  "type": "Feature",
  "properties": {
    "iso:country":"AU",
    "sg:address":"1 Peel St",
    "sg:city":"Mackay",
    "sg:classifiers":[
        {
            "category":"Autos & Motor Vehicles",
            "subcategory":"Automobile Sales",
            "type":"Retail Goods"
        }
    ],
    "sg:phone":"+61 7 4944 1019",
    "sg:postcode":"4740",
    "sg:province":"QLD",
    "sg:tags":[
        "car",
        "used"
    ],
    "wof:name":"Vehicle Buyers Outlet",
    "wof:placetype":"venue"
},
  "geometry": {"coordinates":[149.179932,-21.139458],"type":"Point"}
}