{
  "type": "Feature",
  "properties": {
    "addr:full":"177 Victoria Ave Albert Park VIC 3206",
    "addr:housenumber":"177",
    "addr:postcode":"3206",
    "addr:street":"Victoria Ave",
    "iso:country":"AU",
    "sg:address":"177 Victoria Ave",
    "sg:city":"Albert Park",
    "sg:classifiers":[
        {
            "category":"Manufacturing",
            "subcategory":"Food",
            "type":"Manufacturing & Wholesale Goods"
        }
    ],
    "sg:phone":"+61 3 9690 5831",
    "sg:postcode":"3206",
    "sg:province":"VIC",
    "sg:tags":[
        "function",
        "catering"
    ],
    "sg:website":"http://www.bayleafcatering.com.au",
    "wof:name":"Bay Leaf Catering Pty Ltd",
    "wof:placetype":"venue"
},
  "geometry": {"coordinates":[144.948959,-37.847107],"type":"Point"}
}