{
  "type": "Feature",
  "properties": {
    "iso:country":"AU",
    "sg:address":"41 Cerberus St",
    "sg:city":"Donvale",
    "sg:classifiers":[
        {
            "category":"Building & Trades",
            "subcategory":"Construction",
            "type":"Services"
        }
    ],
    "sg:phone":"+61 418 563 767",
    "sg:postcode":"3111",
    "sg:province":"VIC",
    "sg:tags":[
        "welding"
    ],
    "wof:name":"Siteweld",
    "wof:placetype":"venue"
},
  "geometry": {"coordinates":[145.17324829099999,-37.8001785278],"type":"Point"}
}