{
  "type": "Feature",
  "properties": {
    "addr:full":"45 High St Kyneton VIC 3444",
    "addr:housenumber":"45",
    "addr:postcode":"3444",
    "addr:street":"High St",
    "iso:country":"AU",
    "sg:address":"45 High St",
    "sg:city":"Kyneton",
    "sg:classifiers":[
        {
            "category":"Personal",
            "subcategory":"Massage",
            "type":"Services"
        }
    ],
    "sg:phone":"+61 418 688 196",
    "sg:postcode":"3444",
    "sg:province":"VIC",
    "sg:tags":[
        "therapy"
    ],
    "wof:name":"Brett Bassett",
    "wof:placetype":"venue"
},
  "geometry": {"coordinates":[144.45550537099999,-37.2501373291],"type":"Point"}
}