{
  "type": "Feature",
  "properties": {
    "addr:full":"174a Somerville Rd Footscray West VIC 3012",
    "addr:housenumber":"174a",
    "addr:postcode":"3012",
    "addr:street":"Somerville Rd",
    "iso:country":"AU",
    "sg:address":"174a Somerville Rd",
    "sg:city":"Footscray West",
    "sg:classifiers":[
        {
            "category":"Shopping",
            "subcategory":"Computers & Home Electronics",
            "type":"Retail Goods"
        }
    ],
    "sg:phone":"+61 3 9315 4050",
    "sg:postcode":"3012",
    "sg:province":"VIC",
    "sg:tags":[
        "hardware",
        "equipment"
    ],
    "wof:name":"Naiko Personal Computers",
    "wof:placetype":"venue"
},
  "geometry": {"coordinates":[144.88276672399999,-37.8125762939],"type":"Point"}
}