{
  "type": "Feature",
  "properties": {
    "addr:full":"Adelaide St Adelaide SA 5000",
    "addr:postcode":"5000",
    "addr:street":"Adelaide St",
    "iso:country":"AU",
    "sg:address":"Adelaide St",
    "sg:city":"Adelaide",
    "sg:classifiers":[
        {
            "category":"Professional",
            "subcategory":"Employment Agencies",
            "type":"Services"
        }
    ],
    "sg:phone":"+61 1300 555 520",
    "sg:postcode":"5000",
    "sg:province":"SA",
    "sg:tags":[
        "provider",
        "internet"
    ],
    "wof:name":"Compuserve Pacific",
    "wof:placetype":"venue"
},
  "geometry": {"coordinates":[138.60076904300001,-34.9256401062],"type":"Point"}
}