{
  "type": "Feature",
  "properties": {
    "iso:country":"AU",
    "sg:address":"962- 969 Kingston Rd",
    "sg:city":"Waterford",
    "sg:classifiers":[
        {
            "category":"Food & Beverages",
            "subcategory":"Liquor & Beverages",
            "type":"Retail Goods"
        }
    ],
    "sg:phone":"+61 7 3826 0900",
    "sg:postcode":"4133",
    "sg:province":"QLD",
    "sg:tags":[
        "store"
    ],
    "wof:name":"1st Choice Liquor Superstore",
    "wof:placetype":"venue"
},
  "geometry": {"coordinates":[153.13560485799999,-27.6917686462],"type":"Point"}
}