{
  "type": "Feature",
  "properties": {
    "addr:full":"PO Box 592 Burwood NSW 1805",
    "addr:postcode":"1805",
    "iso:country":"AU",
    "sg:address":"PO Box 592",
    "sg:city":"Burwood",
    "sg:classifiers":[
        {
            "category":"Professional",
            "subcategory":"Detective & Security Services",
            "type":"Services"
        }
    ],
    "sg:phone":"+61 1300 133 519",
    "sg:postcode":"1805",
    "sg:province":"NSW",
    "sg:tags":[
        "investigator"
    ],
    "wof:name":"Suspicious Minds Pty Ltd",
    "wof:placetype":"venue"
},
  "geometry": {"coordinates":[151.10368299999999,-33.877419],"type":"Point"}
}