{
  "type": "Feature",
  "properties": {
    "addr:full":"4 / 61 Bayliss St Auchenflower QLD 4066",
    "addr:housenumber":"/ 61",
    "addr:postcode":"4066",
    "addr:street":"Bayliss St",
    "iso:country":"AU",
    "sg:address":"4 / 61 Bayliss St",
    "sg:city":"Auchenflower",
    "sg:classifiers":[
        {
            "category":"Health Services",
            "subcategory":"Health Practitioner",
            "type":"Services"
        }
    ],
    "sg:phone":"+61 402 036 331",
    "sg:postcode":"4066",
    "sg:province":"QLD",
    "sg:tags":[
        "psychologist"
    ],
    "wof:name":"Mark Pitcher Clinical Psychologist",
    "wof:placetype":"venue"
},
  "geometry": {"coordinates":[152.99339294399999,-27.478685379],"type":"Point"}
}