{
  "type": "Feature",
  "properties": {
    "addr:full":"529 Glynburn Rd Hazelwood Park SA 5066",
    "addr:housenumber":"529",
    "addr:postcode":"5066",
    "addr:street":"Glynburn Rd",
    "iso:country":"AU",
    "sg:address":"529 Glynburn Rd",
    "sg:city":"Hazelwood Park",
    "sg:classifiers":[
        {
            "category":"Social Services",
            "subcategory":"Child Care",
            "type":"Services"
        }
    ],
    "sg:phone":"+61 8 8364 5466",
    "sg:postcode":"5066",
    "sg:province":"SA",
    "wof:name":"Childrens Educational Care Centre",
    "wof:placetype":"venue"
},
  "geometry": {"coordinates":[138.66004943900001,-34.9388389587],"type":"Point"}
}