{
  "type": "Feature",
  "properties": {
    "addr:full":"134b Young St Ayr QLD 4807",
    "addr:housenumber":"134b",
    "addr:postcode":"4807",
    "addr:street":"Young St",
    "iso:country":"AU",
    "sg:address":"134b Young St",
    "sg:city":"Ayr",
    "sg:classifiers":[
        {
            "category":"Personal",
            "subcategory":"Beauty Salon",
            "type":"Services"
        }
    ],
    "sg:phone":"+61 7 4783 2408",
    "sg:postcode":"4807",
    "sg:province":"QLD",
    "sg:tags":[
        "hairdresser"
    ],
    "wof:name":"The Ayr House Of Hair",
    "wof:placetype":"venue"
},
  "geometry": {"coordinates":[147.40507507300001,-19.5756282806],"type":"Point"}
}