{
  "type": "Feature",
  "properties": {
    "iso:country":"AU",
    "sg:address":"17 Alford St",
    "sg:city":"Quakers Hill",
    "sg:classifiers":[
        {
            "category":"Health Services",
            "subcategory":"Doctor",
            "type":"Services"
        }
    ],
    "sg:phone":"+61 2 9626 7919",
    "sg:postcode":"2763",
    "sg:province":"NSW",
    "sg:tags":[
        "medical",
        "practitioner"
    ],
    "wof:name":"Tan Allan",
    "wof:placetype":"venue"
},
  "geometry": {"coordinates":[150.872116089,-33.7430114746],"type":"Point"}
}