{
  "type": "Feature",
  "properties": {
    "addr:full":"3 Yanco Crs Toronto NSW 2283",
    "addr:housenumber":"3",
    "addr:postcode":"2283",
    "addr:street":"Yanco Crs",
    "iso:country":"AU",
    "sg:address":"3 Yanco Crs",
    "sg:city":"Toronto",
    "sg:classifiers":[
        {
            "category":"Building & Trades",
            "subcategory":"Cleaning & Sanitation",
            "type":"Services"
        }
    ],
    "sg:phone":"+61 2 4959 6337",
    "sg:postcode":"2283",
    "sg:province":"NSW",
    "sg:tags":[
        "chemical",
        "pressure",
        "steam",
        "contractor"
    ],
    "wof:name":"All Gone Graffiti Removal & Pressure Cleaning",
    "wof:placetype":"venue"
},
  "geometry": {"coordinates":[151.585083008,-33.0113792419],"type":"Point"}
}