{
  "type": "Feature",
  "properties": {
    "addr:full":"146b Railway Pde West Leederville WA 6007",
    "addr:housenumber":"146b",
    "addr:postcode":"6007",
    "addr:street":"Railway Pde West",
    "iso:country":"AU",
    "sg:address":"146b Railway Pde",
    "sg:city":"West Leederville",
    "sg:classifiers":[
        {
            "category":"Manufacturing",
            "subcategory":"Apparel",
            "type":"Manufacturing & Wholesale Goods"
        }
    ],
    "sg:phone":"+61 8 9382 2271",
    "sg:postcode":"6007",
    "sg:province":"WA",
    "sg:tags":[
        "makers-up",
        "clothing"
    ],
    "wof:name":"Whitman Clothing",
    "wof:placetype":"venue"
},
  "geometry": {"coordinates":[115.840637207,-31.9428081512],"type":"Point"}
}