{
  "type": "Feature",
  "properties": {
    "addr:full":"4 Doorey St Railway Estate QLD 4810",
    "addr:housenumber":"4",
    "addr:postcode":"4810",
    "addr:street":"Doorey St",
    "iso:country":"AU",
    "sg:address":"4 Doorey St",
    "sg:city":"Railway Estate",
    "sg:classifiers":[
        {
            "category":"Food & Beverages",
            "subcategory":"Meat & Fish",
            "type":"Retail Goods"
        }
    ],
    "sg:phone":"+61 7 4772 2036",
    "sg:postcode":"4810",
    "sg:province":"QLD",
    "sg:tags":[
        "aquaculture"
    ],
    "wof:name":"Captain Red Claw",
    "wof:placetype":"venue"
},
  "geometry": {"coordinates":[146.81646699999999,-19.280146],"type":"Point"}
}