{
  "type": "Feature",
  "properties": {
    "addr:full":"Shop1, 235 Princes Hwy Corrimal NSW 2518",
    "addr:housenumber":"235",
    "addr:postcode":"2518",
    "addr:street":"Princes Hwy",
    "iso:country":"AU",
    "sg:address":"Shop1, 235 Princes Hwy",
    "sg:city":"Corrimal",
    "sg:classifiers":[
        {
            "category":"Shopping",
            "subcategory":"Baby Store",
            "type":"Retail Goods"
        }
    ],
    "sg:phone":"+61 2 4283 2779",
    "sg:postcode":"2518",
    "sg:province":"NSW",
    "sg:tags":[
        "wear"
    ],
    "wof:name":"Trendy Wendy's Childrens Boutique",
    "wof:placetype":"venue"
},
  "geometry": {"coordinates":[150.89660599999999,-34.373463],"type":"Point"}
}