{
  "type": "Feature",
  "properties": {
    "addr:full":"25 Amberley Park Drv Narre Warren VIC 3805",
    "addr:housenumber":"25",
    "addr:postcode":"3805",
    "addr:street":"Amberley Park Drv",
    "iso:country":"AU",
    "sg:address":"25 Amberley Park Drv",
    "sg:city":"Narre Warren",
    "sg:classifiers":[
        {
            "category":"Building & Trades",
            "subcategory":"Construction",
            "type":"Services"
        }
    ],
    "sg:phone":"+61 3 9704 8297",
    "sg:postcode":"3805",
    "sg:province":"VIC",
    "sg:tags":[
        "earth",
        "excavating",
        "moving",
        "contractor"
    ],
    "wof:name":"J & D Neville Earthmoving",
    "wof:placetype":"venue"
},
  "geometry": {"coordinates":[145.29260300000001,-38.047012],"type":"Point"}
}