{
  "type": "Feature",
  "properties": {
    "addr:full":"Megalong Rd Katoomba NSW 2780",
    "addr:postcode":"2780",
    "addr:street":"Megalong Rd",
    "iso:country":"AU",
    "sg:address":"Megalong Rd",
    "sg:city":"Katoomba",
    "sg:classifiers":[
        {
            "category":"Home & Garden",
            "subcategory":"Building Materials",
            "type":"Retail Goods"
        }
    ],
    "sg:phone":"+61 2 4787 6285",
    "sg:postcode":"2780",
    "sg:province":"NSW",
    "sg:tags":[
        "fencing"
    ],
    "wof:name":"Sugarloaf Timber",
    "wof:placetype":"venue"
},
  "geometry": {"coordinates":[150.316574097,-33.7124557495],"type":"Point"}
}