{
  "type": "Feature",
  "properties": {
    "addr:full":"Level 1/ 827 Burke Rd Camberwell VIC 3124",
    "addr:housenumber":"/ 827",
    "addr:postcode":"3124",
    "addr:street":"Burke Rd",
    "iso:country":"AU",
    "sg:address":"Level 1/ 827 Burke Rd",
    "sg:city":"Camberwell",
    "sg:classifiers":[
        {
            "category":"Personal",
            "subcategory":"Beauty Salon",
            "type":"Services"
        }
    ],
    "sg:phone":"+61 3 9882 9904",
    "sg:postcode":"3124",
    "sg:province":"VIC",
    "wof:name":"Nicole's Body Boutique",
    "wof:placetype":"venue"
},
  "geometry": {"coordinates":[145.05708313,-37.8284111023],"type":"Point"}
}