{
  "type": "Feature",
  "properties": {
    "addr:full":"Dickson Rd Jilliby NSW 2259",
    "addr:postcode":"2259",
    "addr:street":"Dickson Rd",
    "iso:country":"AU",
    "sg:address":"Dickson Rd",
    "sg:city":"Jilliby",
    "sg:classifiers":[
        {
            "category":"Transit Center",
            "subcategory":"Freight",
            "type":"Transportation"
        }
    ],
    "sg:phone":"+61 2 4355 1341",
    "sg:postcode":"2259",
    "sg:province":"NSW",
    "sg:tags":[
        "honey",
        "merchant"
    ],
    "wof:name":"Highland Park Apiaries",
    "wof:placetype":"venue"
},
  "geometry": {"coordinates":[151.39791870100001,-33.2446365356],"type":"Point"}
}