{
  "type": "Feature",
  "properties": {
    "addr:full":"Unit 11, 64 Sugar Rd Maroochydore QLD 4558",
    "addr:housenumber":"64",
    "addr:postcode":"4558",
    "addr:street":"Sugar Rd",
    "iso:country":"AU",
    "sg:address":"Unit 11, 64 Sugar Rd",
    "sg:city":"Maroochydore",
    "sg:classifiers":[
        {
            "category":"Building & Trades",
            "subcategory":"Construction",
            "type":"Services"
        }
    ],
    "sg:phone":"+61 7 5479 4411",
    "sg:postcode":"4558",
    "sg:province":"QLD",
    "sg:tags":[
        "window",
        "timber"
    ],
    "wof:name":"Duce Windows & Doors",
    "wof:placetype":"venue"
},
  "geometry": {"coordinates":[153.093017578,-26.6668109894],"type":"Point"}
}