{
  "type": "Feature",
  "properties": {
    "iso:country":"AU",
    "sg:address":"47 Richland Ave",
    "sg:city":"Coopers Plains",
    "sg:classifiers":[
        {
            "category":"Social Services",
            "type":"Services"
        }
    ],
    "sg:phone":"+61 7 3275 3037",
    "sg:postcode":"4108",
    "sg:province":"QLD",
    "sg:tags":[
        "disabled",
        "person",
        "equipment"
    ],
    "wof:name":"Yarrow Building & Plumbing Pty Ltd",
    "wof:placetype":"venue"
},
  "geometry": {"coordinates":[153.027908325,-27.5668678284],"type":"Point"}
}