{
  "type": "Feature",
  "properties": {
    "iso:country":"AU",
    "sg:address":"54 Gingin Rd",
    "sg:city":"Lancelin",
    "sg:classifiers":[
        {
            "category":"Retail",
            "subcategory":"Auto Repair",
            "type":"Services"
        }
    ],
    "sg:phone":"+61 8 9655 2115",
    "sg:postcode":"6044",
    "sg:province":"WA",
    "sg:tags":[
        "repairer",
        "motor",
        "engineer"
    ],
    "wof:name":"Whitesands Mechanical Repairs",
    "wof:placetype":"venue"
},
  "geometry": {"coordinates":[115.329421997,-31.0118751526],"type":"Point"}
}