{
  "type": "Feature",
  "properties": {
    "addr:full":"205 Onlsow Rd Shenton Park WA 6008",
    "addr:housenumber":"205",
    "addr:postcode":"6008",
    "addr:street":"Onlsow Rd",
    "iso:country":"AU",
    "sg:address":"205 Onlsow Rd",
    "sg:city":"Shenton Park",
    "sg:classifiers":[
        {
            "category":"Health Services",
            "subcategory":"Health Practitioner",
            "type":"Services"
        }
    ],
    "sg:phone":"+61 8 9388 9171",
    "sg:postcode":"6008",
    "sg:province":"WA",
    "sg:tags":[
        "herbalist"
    ],
    "wof:name":"Julie Constantine",
    "wof:placetype":"venue"
},
  "geometry": {"coordinates":[115.811973572,-31.9609642029],"type":"Point"}
}