{
  "type": "Feature",
  "properties": {
    "iso:country":"AU",
    "sg:address":"14 Daniel St",
    "sg:city":"Caloundra",
    "sg:classifiers":[
        {
            "category":"Home & Garden",
            "subcategory":"Building Materials",
            "type":"Retail Goods"
        }
    ],
    "sg:phone":"+61 7 5491 2933",
    "sg:postcode":"4551",
    "sg:province":"QLD",
    "sg:tags":[
        "supply"
    ],
    "wof:name":"Austral Masonry Caloundra",
    "wof:placetype":"venue"
},
  "geometry": {"coordinates":[153.109130859,-26.7932834625],"type":"Point"}
}