{
  "type": "Feature",
  "properties": {
    "addr:full":"102 Dalrymple St Bowen QLD 4805",
    "addr:housenumber":"102",
    "addr:postcode":"4805",
    "addr:street":"Dalrymple St",
    "iso:country":"AU",
    "sg:address":"102 Dalrymple St",
    "sg:city":"Bowen",
    "sg:classifiers":[
        {
            "category":"Health Services",
            "subcategory":"Dentist",
            "type":"Services"
        }
    ],
    "sg:phone":"+61 418 869 216",
    "sg:postcode":"4805",
    "sg:province":"QLD",
    "sg:tags":[
        "dental",
        "prosthetist"
    ],
    "wof:name":"Bowen Denture Centre",
    "wof:placetype":"venue"
},
  "geometry": {"coordinates":[148.239700317,-20.0202999115],"type":"Point"}
}