{
  "type": "Feature",
  "properties": {
    "addr:full":"66 Myrtle St Chippendale NSW 2008",
    "addr:housenumber":"66",
    "addr:postcode":"2008",
    "addr:street":"Myrtle St",
    "iso:country":"AU",
    "sg:address":"66 Myrtle St",
    "sg:city":"Chippendale",
    "sg:classifiers":[
        {
            "category":"Professional",
            "subcategory":"Art Services",
            "type":"Services"
        }
    ],
    "sg:phone":"+61 2 9310 5844",
    "sg:postcode":"2008",
    "sg:province":"NSW",
    "sg:tags":[
        "interior",
        "designer"
    ],
    "wof:name":"i creative",
    "wof:placetype":"venue"
},
  "geometry": {"coordinates":[151.197174072,-33.8875198364],"type":"Point"}
}