{
  "type": "Feature",
  "properties": {
    "addr:full":"9 Candiru Crt Sorrento WA 6020",
    "addr:housenumber":"9",
    "addr:postcode":"6020",
    "addr:street":"Candiru Crt",
    "iso:country":"AU",
    "sg:address":"9 Candiru Crt",
    "sg:city":"Sorrento",
    "sg:classifiers":[
        {
            "category":"Professional",
            "subcategory":"Accounting & Tax Preparation",
            "type":"Services"
        }
    ],
    "sg:phone":"+61 8 9203 5350",
    "sg:postcode":"6020",
    "sg:province":"WA",
    "sg:tags":[
        "bookkeeping"
    ],
    "wof:name":"A1 Bookkeping Services",
    "wof:placetype":"venue"
},
  "geometry": {"coordinates":[115.75984954800001,-31.8212127686],"type":"Point"}
}