{
  "type": "Feature",
  "properties": {
    "addr:full":"215 Waverley Rd Malvern East VIC 3145",
    "addr:housenumber":"215",
    "addr:postcode":"3145",
    "addr:street":"Waverley Rd",
    "iso:country":"AU",
    "sg:address":"215 Waverley Rd",
    "sg:city":"Malvern East",
    "sg:classifiers":[
        {
            "category":"Professional",
            "subcategory":"Business Services",
            "type":"Services"
        }
    ],
    "sg:phone":"+61 3 9571 5525",
    "sg:postcode":"3145",
    "sg:province":"VIC",
    "sg:tags":[
        "drafting"
    ],
    "wof:name":"AUSDRAFT PTY. LTD.",
    "wof:placetype":"venue"
},
  "geometry": {"coordinates":[145.05267334000001,-37.8763542175],"type":"Point"}
}