{
  "type": "Feature",
  "properties": {
    "addr:full":"3 Miles Rd Kewdale WA 6105",
    "addr:housenumber":"3",
    "addr:postcode":"6105",
    "addr:street":"Miles Rd",
    "iso:country":"AU",
    "sg:address":"3 Miles Rd",
    "sg:city":"Kewdale",
    "sg:classifiers":[
        {
            "category":"Transit Center",
            "subcategory":"Freight",
            "type":"Transportation"
        }
    ],
    "sg:phone":"+61 8 9353 6144",
    "sg:postcode":"6105",
    "sg:province":"WA",
    "sg:tags":[
        "equipment",
        "transport",
        "road",
        "vehicle"
    ],
    "wof:name":"Holland Hitch (Aust) Pty Ltd",
    "wof:placetype":"venue"
},
  "geometry": {"coordinates":[115.943649292,-31.9816589355],"type":"Point"}
}