{
  "type": "Feature",
  "properties": {
    "addr:full":"58 Birrel St Bondi Junction NSW 2022",
    "addr:housenumber":"58",
    "addr:postcode":"2022",
    "addr:street":"Birrel St",
    "iso:country":"AU",
    "sg:address":"58 Birrel St",
    "sg:city":"Bondi Junction",
    "sg:classifiers":[
        {
            "category":"Shopping",
            "subcategory":"Party Supplies",
            "type":"Retail Goods"
        }
    ],
    "sg:phone":"+61 410 191 591",
    "sg:postcode":"2022",
    "sg:province":"NSW",
    "sg:tags":[
        "children's"
    ],
    "wof:name":"Absolutely Amazing Entertainment",
    "wof:placetype":"venue"
},
  "geometry": {"coordinates":[151.245803833,-33.8952598572],"type":"Point"}
}