{
  "type": "Feature",
  "properties": {
    "iso:country":"AU",
    "sg:address":"611a Marion Rd",
    "sg:city":"South Plympton",
    "sg:classifiers":[
        {
            "category":"Education",
            "subcategory":"University",
            "type":"Public Place"
        }
    ],
    "sg:phone":"+61 8 8276 5233",
    "sg:postcode":"5038",
    "sg:province":"SA",
    "sg:tags":[
        "sewing",
        "dressmaking",
        "tuition"
    ],
    "wof:name":"Adelaide Needleworks",
    "wof:placetype":"venue"
},
  "geometry": {"coordinates":[138.556350708,-34.9819564819],"type":"Point"}
}