{
  "type": "Feature",
  "properties": {
    "addr:full":"Grd Flr, 1 Market Place Drv Beenleigh QLD 4207",
    "addr:postcode":"4207",
    "addr:street":"Grd;Market Place Drv",
    "iso:country":"AU",
    "sg:address":"Grd Flr, 1 Market Place Drv",
    "sg:city":"Beenleigh",
    "sg:classifiers":[
        {
            "category":"Professional",
            "subcategory":"Employment Agencies",
            "type":"Services"
        }
    ],
    "sg:phone":"+61 7 3382 0444",
    "sg:postcode":"4207",
    "sg:province":"QLD",
    "wof:name":"MAX Employment",
    "wof:placetype":"venue"
},
  "geometry": {"coordinates":[153.20469665499999,-27.7185764313],"type":"Point"}
}