{
  "type": "Feature",
  "properties": {
    "addr:full":"250 Stirling Hwy Claremont WA 6010",
    "addr:housenumber":"250",
    "addr:postcode":"6010",
    "addr:street":"Stirling Hwy",
    "iso:country":"AU",
    "sg:address":"250 Stirling Hwy",
    "sg:city":"Claremont",
    "sg:classifiers":[
        {
            "category":"Communications",
            "subcategory":"Film & Video Production",
            "type":"Services"
        }
    ],
    "sg:phone":"+61 8 9284 2203",
    "sg:postcode":"6010",
    "sg:province":"WA",
    "sg:tags":[
        "fan",
        "blower"
    ],
    "wof:name":"ALTI Lighting",
    "wof:placetype":"venue"
},
  "geometry": {"coordinates":[115.785980225,-31.9823589325],"type":"Point"}
}