{
  "type": "Feature",
  "properties": {
    "addr:full":"5 Percy St Mt Gambier SA 5290",
    "addr:housenumber":"5",
    "addr:postcode":"5290",
    "addr:street":"Percy St",
    "iso:country":"AU",
    "sg:address":"5 Percy St",
    "sg:city":"Mt Gambier",
    "sg:classifiers":[
        {
            "category":"Education",
            "subcategory":"Special Training",
            "type":"Public Place"
        }
    ],
    "sg:phone":"+61 8 8723 1062",
    "sg:postcode":"5290",
    "sg:province":"SA",
    "sg:tags":[
        "tuition-educational"
    ],
    "wof:name":"Kip McGrath Education Centres",
    "wof:placetype":"venue"
},
  "geometry": {"coordinates":[140.78117399999999,-37.827816],"type":"Point"}
}