{
  "type": "Feature",
  "properties": {
    "addr:full":"12 Anne St Koroit VIC 3282",
    "addr:housenumber":"12",
    "addr:postcode":"3282",
    "addr:street":"Anne St",
    "iso:country":"AU",
    "sg:address":"12 Anne St",
    "sg:city":"Koroit",
    "sg:classifiers":[
        {
            "category":"Farming",
            "subcategory":"Farm & Veterinary Services",
            "type":"Manufacturing & Wholesale Goods"
        }
    ],
    "sg:phone":"+61 3 5565 8333",
    "sg:postcode":"3282",
    "sg:province":"VIC",
    "sg:tags":[
        "agricultural",
        "advisory"
    ],
    "wof:name":"T N N Industries Pty Ltd",
    "wof:placetype":"venue"
},
  "geometry": {"coordinates":[142.37173461899999,-38.302532196],"type":"Point"}
}