{
  "type": "Feature",
  "properties": {
    "addr:full":"125 Oakwood School Rd Gooburrum QLD 4670",
    "addr:housenumber":"125",
    "addr:postcode":"4670",
    "addr:street":"Oakwood School Rd",
    "iso:country":"AU",
    "sg:address":"125 Oakwood School Rd",
    "sg:city":"Gooburrum",
    "sg:classifiers":[
        {
            "category":"Education",
            "subcategory":"School",
            "type":"Public Place"
        }
    ],
    "sg:phone":"+61 7 4130 9308",
    "sg:postcode":"4670",
    "sg:province":"QLD",
    "sg:tags":[
        "state",
        "except",
        "nsw"
    ],
    "wof:name":"Oakwood Preschool",
    "wof:placetype":"venue"
},
  "geometry": {"coordinates":[152.30006408700001,-24.8440914154],"type":"Point"}
}