{
  "type": "Feature",
  "properties": {
    "addr:full":"27 Halley St Chisholm ACT 2905",
    "addr:housenumber":"27",
    "addr:postcode":"2905",
    "addr:street":"Halley St",
    "iso:country":"AU",
    "sg:address":"27 Halley St",
    "sg:city":"Chisholm",
    "sg:classifiers":[
        {
            "category":"Education",
            "subcategory":"Kindergarten",
            "type":"Public Place"
        }
    ],
    "sg:phone":"+61 2 6292 3624",
    "sg:postcode":"2905",
    "sg:province":"ACT",
    "sg:tags":[
        "pre-schools"
    ],
    "wof:name":"Bunyarra Childrens Centre",
    "wof:placetype":"venue"
},
  "geometry": {"coordinates":[149.129272461,-35.4131774902],"type":"Point"}
}