{
  "type": "Feature",
  "properties": {
    "addr:full":"74 McDowall St Roma QLD 4455",
    "addr:housenumber":"74",
    "addr:postcode":"4455",
    "addr:street":"Mcdowall St",
    "iso:country":"AU",
    "sg:address":"74 McDowall St",
    "sg:city":"Roma",
    "sg:classifiers":[
        {
            "category":"Shopping",
            "type":"Retail Goods"
        }
    ],
    "sg:phone":"+61 7 4622 1222",
    "sg:postcode":"4455",
    "sg:province":"QLD",
    "sg:tags":[
        "agent",
        "stock"
    ],
    "wof:name":"Watkins & Company",
    "wof:placetype":"venue"
},
  "geometry": {"coordinates":[148.790084839,-26.5718250275],"type":"Point"}
}