{
  "type": "Feature",
  "properties": {
    "addr:full":"792 Elizabeth St Melbourne VIC 3000",
    "addr:housenumber":"792",
    "addr:postcode":"3000",
    "addr:street":"Elizabeth St",
    "iso:country":"AU",
    "sg:address":"792 Elizabeth St",
    "sg:city":"Melbourne",
    "sg:classifiers":[
        {
            "category":"Travel",
            "subcategory":"Hotels & Motels",
            "type":"Entertainment"
        }
    ],
    "sg:phone":"+61 13 24 00",
    "sg:postcode":"3000",
    "sg:province":"VIC",
    "sg:tags":[
        "accommodation"
    ],
    "wof:name":"Choice Hotels Australasia",
    "wof:placetype":"venue"
},
  "geometry": {"coordinates":[144.957885742,-37.7999038696],"type":"Point"}
}