{
  "type": "Feature",
  "properties": {
    "iso:country":"AU",
    "sg:address":"341 Bourbong St",
    "sg:city":"Bundaberg",
    "sg:classifiers":[
        {
            "category":"Travel",
            "subcategory":"Hostel",
            "type":"Entertainment"
        }
    ],
    "sg:phone":"+61 7 4131 8700",
    "sg:postcode":"4670",
    "sg:province":"QLD",
    "sg:tags":[
        "home"
    ],
    "wof:name":"Blue Care",
    "wof:placetype":"venue"
},
  "geometry": {"coordinates":[152.32606506400001,-24.872209549],"type":"Point"}
}