{
  "type": "Feature",
  "properties": {
    "addr:full":"613 Hillyards Rd Cedar Point NSW 2474",
    "addr:housenumber":"613",
    "addr:postcode":"2474",
    "addr:street":"Hillyards Rd",
    "iso:country":"AU",
    "sg:address":"613 Hillyards Rd",
    "sg:city":"Cedar Point",
    "sg:classifiers":[
        {
            "category":"Building & Trades",
            "subcategory":"Plumbing",
            "type":"Services"
        }
    ],
    "sg:phone":"+61 2 6633 5398",
    "sg:postcode":"2474",
    "sg:province":"NSW",
    "sg:tags":[
        "plumber",
        "gasfitters"
    ],
    "wof:name":"John Gannon Plumber& Drainer",
    "wof:placetype":"venue"
},
  "geometry": {"coordinates":[153.00096130399999,-28.6809024811],"type":"Point"}
}