{
  "type": "Feature",
  "properties": {
    "addr:full":"10 Liberty St Cairns QLD 4870",
    "addr:housenumber":"10",
    "addr:postcode":"4870",
    "addr:street":"Liberty St",
    "iso:country":"AU",
    "sg:address":"10 Liberty St",
    "sg:city":"Cairns",
    "sg:classifiers":[
        {
            "category":"Building & Trades",
            "subcategory":"Construction",
            "type":"Services"
        }
    ],
    "sg:phone":"+61 7 4035 2999",
    "sg:postcode":"4870",
    "sg:province":"QLD",
    "sg:tags":[
        "equipment",
        "balancing"
    ],
    "wof:name":"Cummins Nerco",
    "wof:placetype":"venue"
},
  "geometry": {"coordinates":[145.77000427199999,-16.9458065033],"type":"Point"}
}