{
  "type": "Feature",
  "properties": {
    "addr:full":"Colac Rd Napoleons VIC 3352",
    "addr:postcode":"3352",
    "addr:street":"Colac Rd",
    "iso:country":"AU",
    "sg:address":"Colac Rd",
    "sg:city":"Napoleons",
    "sg:classifiers":[
        {
            "category":"Food & Beverages",
            "subcategory":"Groceries & Convenience Stores",
            "type":"Retail Goods"
        }
    ],
    "sg:phone":"+61 3 5342 0455",
    "sg:postcode":"3352",
    "sg:province":"VIC",
    "wof:name":"Jeffrey W & J",
    "wof:placetype":"venue"
},
  "geometry": {"coordinates":[143.914444,-37.530121],"type":"Point"}
}