{
  "type": "Feature",
  "properties": {
    "addr:full":"216 Cheltenham Rd Keysborough VIC 3173",
    "addr:housenumber":"216",
    "addr:postcode":"3173",
    "addr:street":"Cheltenham Rd",
    "iso:country":"AU",
    "sg:address":"216 Cheltenham Rd",
    "sg:city":"Keysborough",
    "sg:classifiers":[
        {
            "category":"Arts & Performance",
            "subcategory":"Theater",
            "type":"Entertainment"
        }
    ],
    "sg:phone":"+61 414 458 828",
    "sg:postcode":"3173",
    "sg:province":"VIC",
    "sg:tags":[
        "theatrical",
        "supply"
    ],
    "wof:name":"Zaffa Staging",
    "wof:placetype":"venue"
},
  "geometry": {"coordinates":[145.18568420400001,-37.9944763184],"type":"Point"}
}