{
  "type": "Feature",
  "properties": {
    "addr:full":"521 West Mt Cotton Rd Mt Cotton QLD 4165",
    "addr:housenumber":"521",
    "addr:postcode":"4165",
    "addr:street":"West Mt Cotton Rd",
    "iso:country":"AU",
    "sg:address":"521 West Mt Cotton Rd",
    "sg:city":"Mt Cotton",
    "sg:classifiers":[
        {
            "category":"Transit Center",
            "subcategory":"Freight",
            "type":"Transportation"
        }
    ],
    "sg:phone":"+61 7 3829 9548",
    "sg:postcode":"4165",
    "sg:province":"QLD",
    "sg:tags":[
        "forklift",
        "truck"
    ],
    "wof:name":"Independant Machinery Repairs Pty Ltd",
    "wof:placetype":"venue"
},
  "geometry": {"coordinates":[153.20989990199999,-27.5999317169],"type":"Point"}
}