{
  "type": "Feature",
  "properties": {
    "addr:full":"19 Old Warburton Rd Seville VIC 3139",
    "addr:housenumber":"19",
    "addr:postcode":"3139",
    "addr:street":"Old Warburton Rd",
    "iso:country":"AU",
    "sg:address":"19 Old Warburton Rd",
    "sg:city":"Seville",
    "sg:classifiers":[
        {
            "category":"Professional",
            "subcategory":"Accounting & Tax Preparation",
            "type":"Services"
        }
    ],
    "sg:phone":"+61 3 5964 4259",
    "sg:postcode":"3139",
    "sg:province":"VIC",
    "sg:tags":[
        "bookkeeping"
    ],
    "wof:name":"Yarra Ranges Bookkeeping",
    "wof:placetype":"venue"
},
  "geometry": {"coordinates":[145.46173095699999,-37.7723503113],"type":"Point"}
}