{
  "type": "Feature",
  "properties": {
    "addr:full":"114 Anderson St Cairns QLD 4870",
    "addr:housenumber":"114",
    "addr:postcode":"4870",
    "addr:street":"Anderson St",
    "iso:country":"AU",
    "sg:address":"114 Anderson St",
    "sg:city":"Cairns",
    "sg:classifiers":[
        {
            "category":"Building & Trades",
            "subcategory":"Construction",
            "type":"Services"
        }
    ],
    "sg:phone":"+61 7 4032 3611",
    "sg:postcode":"4870",
    "sg:province":"QLD",
    "sg:tags":[
        "home",
        "air conditioning"
    ],
    "wof:name":"Winfield's Electrical",
    "wof:placetype":"venue"
},
  "geometry": {"coordinates":[145.745330811,-16.9158325195],"type":"Point"}
}