{
  "type": "Feature",
  "properties": {
    "iso:country":"AU",
    "sg:address":"24 Brougham St",
    "sg:city":"Gosford East",
    "sg:classifiers":[
        {
            "category":"Sports & Exercise",
            "subcategory":"Gym",
            "type":"Entertainment"
        }
    ],
    "sg:phone":"+61 2 4323 7499",
    "sg:postcode":"2250",
    "sg:province":"NSW",
    "sg:tags":[
        "health",
        "fitness"
    ],
    "wof:name":"East Gosford Physiotherapy & Sports Injury Centre",
    "wof:placetype":"venue"
},
  "geometry": {"coordinates":[151.354782105,-33.4376068115],"type":"Point"}
}