{
  "type": "Feature",
  "properties": {
    "addr:full":"16 Broula Ave Baulkham Hills NSW 2153",
    "addr:housenumber":"16",
    "addr:postcode":"2153",
    "addr:street":"Broula Ave",
    "iso:country":"AU",
    "sg:address":"16 Broula Ave",
    "sg:city":"Baulkham Hills",
    "sg:classifiers":[
        {
            "category":"Real Estate",
            "subcategory":"Surveying",
            "type":"Services"
        }
    ],
    "sg:phone":"+61 2 9624 1813",
    "sg:postcode":"2153",
    "sg:province":"NSW",
    "sg:tags":[
        "surveyor",
        "land"
    ],
    "wof:name":"Timbs D W & M H",
    "wof:placetype":"venue"
},
  "geometry": {"coordinates":[150.96351623499999,-33.7537269592],"type":"Point"}
}