{
  "type": "Feature",
  "properties": {
    "iso:country":"AU",
    "sg:address":"Bellamy Farm Rd",
    "sg:city":"West Pennant Hills",
    "sg:classifiers":[
        {
            "category":"Food & Beverages",
            "subcategory":"Specialty",
            "type":"Retail Goods"
        }
    ],
    "sg:phone":"+61 2 9873 3138",
    "sg:postcode":"2125",
    "sg:province":"NSW",
    "sg:tags":[
        "product",
        "health"
    ],
    "wof:name":"Herbalife Independent Distributors",
    "wof:placetype":"venue"
},
  "geometry": {"coordinates":[151.03785705600001,-33.7520675659],"type":"Point"}
}