{
  "type": "Feature",
  "properties": {
    "iso:country":"AU",
    "sg:address":"Hope St",
    "sg:city":"Walgett",
    "sg:classifiers":[
        {
            "category":"Building & Trades",
            "subcategory":"Construction",
            "type":"Services"
        }
    ],
    "sg:phone":"+61 2 6828 1194",
    "sg:postcode":"2832",
    "sg:province":"NSW",
    "sg:tags":[
        "welding"
    ],
    "wof:name":"Weate R D & C I",
    "wof:placetype":"venue"
},
  "geometry": {"coordinates":[148.11407470699999,-30.0296134949],"type":"Point"}
}