{
  "type": "Feature",
  "properties": {
    "addr:full":"167 Edwards St Melrose Park SA 5039",
    "addr:housenumber":"167",
    "addr:postcode":"5039",
    "addr:street":"Edwards St",
    "iso:country":"AU",
    "sg:address":"167 Edwards St",
    "sg:city":"Melrose Park",
    "sg:classifiers":[
        {
            "category":"Retail",
            "subcategory":"Auto Repair",
            "type":"Services"
        }
    ],
    "sg:phone":"+61 8 8297 4170",
    "sg:postcode":"5039",
    "sg:province":"SA",
    "sg:tags":[
        "repairer",
        "motor",
        "engineer"
    ],
    "wof:name":"Steven Shippey Automotive",
    "wof:placetype":"venue"
},
  "geometry": {"coordinates":[138.573944092,-34.9782447815],"type":"Point"}
}