{
  "type": "Feature",
  "properties": {
    "addr:full":"Unit 1 32 Court Rd Fairfield NSW 2165",
    "addr:housenumber":"32",
    "addr:postcode":"2165",
    "addr:street":"Court Rd",
    "iso:country":"AU",
    "sg:address":"Unit 1 32 Court Rd",
    "sg:city":"Fairfield",
    "sg:classifiers":[
        {
            "category":"Insurance",
            "subcategory":"Insurance Agent",
            "type":"Services"
        }
    ],
    "sg:phone":"+61 2 9727 2660",
    "sg:postcode":"2165",
    "sg:province":"NSW",
    "wof:name":"Fairgas Petrol Service Station Pty Ltd",
    "wof:placetype":"venue"
},
  "geometry": {"coordinates":[150.95797729500001,-33.8701324463],"type":"Point"}
}