{
  "type": "Feature",
  "properties": {
    "addr:full":"347 Princes Hwy Woonona NSW 2517",
    "addr:housenumber":"347",
    "addr:postcode":"2517",
    "addr:street":"Princes Hwy",
    "iso:country":"AU",
    "sg:address":"347 Princes Hwy",
    "sg:city":"Woonona",
    "sg:classifiers":[
        {
            "category":"Fast Food",
            "type":"Food & Drink"
        }
    ],
    "sg:phone":"+61 13 11 66",
    "sg:postcode":"2517",
    "sg:province":"NSW",
    "sg:tags":[
        "away",
        "take"
    ],
    "wof:name":"Pizza Hut",
    "wof:placetype":"venue"
},
  "geometry": {"coordinates":[150.907837,-34.339951],"type":"Point"}
}