{
  "type": "Feature",
  "properties": {
    "addr:full":"1/11 Turbo Rd Kings Park NSW 2148",
    "addr:housenumber":"/ 11",
    "addr:postcode":"2148",
    "addr:street":"Turbo Rd",
    "iso:country":"AU",
    "sg:address":"1/11 Turbo Rd",
    "sg:city":"Kings Park",
    "sg:classifiers":[
        {
            "category":"Manufacturing",
            "subcategory":"Electronics",
            "type":"Manufacturing & Wholesale Goods"
        }
    ],
    "sg:phone":"+61 2 9831 6477",
    "sg:postcode":"2148",
    "sg:province":"NSW",
    "sg:tags":[
        "wholesaler",
        "equipment",
        "part",
        "mfrs",
        "refrigeration"
    ],
    "wof:name":"Catering & Refrigeration Hardware",
    "wof:placetype":"venue"
},
  "geometry": {"coordinates":[150.90452575699999,-33.7453117371],"type":"Point"}
}