{
  "type": "Feature",
  "properties": {
    "addr:full":"67 High St Woodend VIC 3442",
    "addr:housenumber":"67",
    "addr:postcode":"3442",
    "addr:street":"High St",
    "iso:country":"AU",
    "sg:address":"67 High St",
    "sg:city":"Woodend",
    "sg:classifiers":[
        {
            "category":"Travel",
            "subcategory":"Hotels & Motels",
            "type":"Entertainment"
        }
    ],
    "sg:phone":"+61 3 5427 2721",
    "sg:postcode":"3442",
    "sg:province":"VIC",
    "sg:tags":[
        "pub"
    ],
    "wof:name":"Victoria Hotel Woodend",
    "wof:placetype":"venue"
},
  "geometry": {"coordinates":[144.527954102,-37.3556404114],"type":"Point"}
}