{
  "type": "Feature",
  "properties": {
    "iso:country":"AU",
    "sg:address":"6A Samaria Rd",
    "sg:city":"Benalla",
    "sg:classifiers":[
        {
            "category":"Wholesale",
            "subcategory":"Machinery & Supplies",
            "type":"Manufacturing & Wholesale Goods"
        }
    ],
    "sg:phone":"+61 3 5762 8366",
    "sg:postcode":"3672",
    "sg:province":"VIC",
    "sg:tags":[
        "equipment",
        "hydraulic"
    ],
    "wof:name":"Rapid Hose Systems",
    "wof:placetype":"venue"
},
  "geometry": {"coordinates":[146.012665,-36.544182],"type":"Point"}
}