{
  "type": "Feature",
  "properties": {
    "addr:full":"Unit 2, Cnr Murray Rd & Dowd St Welshpool WA 6106",
    "addr:housenumber":"cnr",
    "addr:postcode":"6106",
    "addr:street":"Murray Rd & Dowd St",
    "iso:country":"AU",
    "sg:address":"Unit 2, Cnr Murray Rd & Dowd St",
    "sg:city":"Welshpool",
    "sg:classifiers":[
        {
            "category":"Autos & Motor Vehicles",
            "subcategory":"Motorcycle Sales",
            "type":"Retail Goods"
        }
    ],
    "sg:phone":"+61 8 9458 1537",
    "sg:postcode":"6106",
    "sg:province":"WA",
    "sg:tags":[
        "outboard"
    ],
    "wof:name":"Janes Marine Service",
    "wof:placetype":"venue"
},
  "geometry": {"coordinates":[115.95829773,-31.9959602356],"type":"Point"}
}