{
  "type": "Feature",
  "properties": {
    "addr:full":"20 Clematis Dr Taylors Lakes VIC 3038",
    "addr:housenumber":"20",
    "addr:postcode":"3038",
    "addr:street":"Clematis Dr",
    "iso:country":"AU",
    "sg:address":"20 Clematis Dr",
    "sg:city":"Taylors Lakes",
    "sg:classifiers":[
        {
            "category":"Retail",
            "subcategory":"Auto Rental",
            "type":"Services"
        }
    ],
    "sg:phone":"+61 1300 884 407",
    "sg:postcode":"3038",
    "sg:province":"VIC",
    "sg:tags":[
        "chauffeur",
        "car",
        "hire",
        "driven",
        "limousine"
    ],
    "wof:name":"Chauffeured Cars Masters",
    "wof:placetype":"venue"
},
  "geometry": {"coordinates":[144.78788800000001,-37.693237],"type":"Point"}
}