{
  "type": "Feature",
  "properties": {
    "addr:full":"99 Grafton St Coffs Harbour NSW 2450",
    "addr:housenumber":"99",
    "addr:postcode":"2450",
    "addr:street":"Grafton St",
    "iso:country":"AU",
    "sg:address":"99 Grafton St",
    "sg:city":"Coffs Harbour",
    "sg:classifiers":[
        {
            "category":"Food & Beverages",
            "subcategory":"Meat & Fish",
            "type":"Retail Goods"
        }
    ],
    "sg:phone":"+61 2 6652 8818",
    "sg:postcode":"2450",
    "sg:province":"NSW",
    "sg:tags":[
        "seafood"
    ],
    "wof:name":"Funky Fish",
    "wof:placetype":"venue"
},
  "geometry": {"coordinates":[153.114609,-30.295755],"type":"Point"}
}