{
  "type": "Feature",
  "properties": {
    "iso:country":"AU",
    "sg:address":"11 Steege St",
    "sg:city":"Ashgrove",
    "sg:classifiers":[
        {
            "category":"Building & Trades",
            "subcategory":"Plumbing",
            "type":"Services"
        }
    ],
    "sg:phone":"+61 7 3366 5920",
    "sg:postcode":"4060",
    "sg:province":"QLD",
    "sg:tags":[
        "plumber",
        "gasfitters"
    ],
    "wof:name":"Burton S J & M T",
    "wof:placetype":"venue"
},
  "geometry": {"coordinates":[152.992385864,-27.4365673065],"type":"Point"}
}