{
  "type": "Feature",
  "properties": {
    "addr:full":"560 Hume St Albury NSW 2640",
    "addr:housenumber":"560",
    "addr:postcode":"2640",
    "addr:street":"Hume St",
    "iso:country":"AU",
    "sg:address":"560 Hume St",
    "sg:city":"Albury",
    "sg:classifiers":[
        {
            "category":"Building & Trades",
            "subcategory":"Pest Control",
            "type":"Services"
        }
    ],
    "sg:phone":"+61 2 6041 5645",
    "sg:postcode":"2640",
    "sg:province":"NSW",
    "sg:tags":[
        "equipment",
        "insect"
    ],
    "wof:name":"Barbeques Galore",
    "wof:placetype":"venue"
},
  "geometry": {"coordinates":[146.913894653,-36.0845108032],"type":"Point"}
}