{
  "type": "Feature",
  "properties": {
    "iso:country":"AU",
    "sg:address":"Brisbane Antique Market Shop 20/ 791 Sandgate Rd",
    "sg:city":"Clayfield",
    "sg:classifiers":[
        {
            "category":"Shopping",
            "subcategory":"Musical Instruments",
            "type":"Retail Goods"
        }
    ],
    "sg:phone":"+61 7 3263 5613",
    "sg:postcode":"4011",
    "sg:province":"QLD",
    "sg:tags":[
        "piano",
        "organ"
    ],
    "wof:name":"Duncan Wise",
    "wof:placetype":"venue"
},
  "geometry": {"coordinates":[153.058319,-27.416611],"type":"Point"}
}