{
  "type": "Feature",
  "properties": {
    "iso:country":"AU",
    "sg:address":"293 Chapel Rd South",
    "sg:city":"Bankstown",
    "sg:classifiers":[
        {
            "category":"Health Services",
            "subcategory":"Optometrist",
            "type":"Services"
        }
    ],
    "sg:phone":"+61 2 9796 4825",
    "sg:postcode":"2200",
    "sg:province":"NSW",
    "wof:name":"Family Eyecare Centre",
    "wof:placetype":"venue"
},
  "geometry": {"coordinates":[151.031769,-33.91967],"type":"Point"}
}