{
  "type": "Feature",
  "properties": {
    "iso:country":"AU",
    "sg:address":"39 Norton Drv",
    "sg:city":"Shailer Park",
    "sg:classifiers":[
        {
            "category":"Building & Trades",
            "subcategory":"Pest Control",
            "type":"Services"
        }
    ],
    "sg:phone":"+61 7 3801 4588",
    "sg:postcode":"4128",
    "sg:province":"QLD",
    "wof:name":"A Clean Scene",
    "wof:placetype":"venue"
},
  "geometry": {"coordinates":[153.16920471200001,-27.6539516449],"type":"Point"}
}