{
  "type": "Feature",
  "properties": {
    "addr:full":"35 Pickles St Scullin ACT 2614",
    "addr:housenumber":"35",
    "addr:postcode":"2614",
    "addr:street":"Pickles St",
    "iso:country":"AU",
    "sg:address":"35 Pickles St",
    "sg:city":"Scullin",
    "sg:classifiers":[
        {
            "category":"Personal",
            "subcategory":"Massage",
            "type":"Services"
        }
    ],
    "sg:phone":"+61 2 6254 5672",
    "sg:postcode":"2614",
    "sg:province":"ACT",
    "sg:tags":[
        "therapy"
    ],
    "wof:name":"de Plater Ian",
    "wof:placetype":"venue"
},
  "geometry": {"coordinates":[149.03533935600001,-35.2393074036],"type":"Point"}
}