{
  "type": "Feature",
  "properties": {
    "iso:country":"AU",
    "sg:address":"110 William St",
    "sg:city":"Bathurst",
    "sg:classifiers":[
        {
            "category":"Travel",
            "subcategory":"Hotels & Motels",
            "type":"Entertainment"
        }
    ],
    "sg:phone":"+61 2 6332 4500",
    "sg:postcode":"2795",
    "sg:province":"NSW",
    "sg:tags":[
        "accommodation"
    ],
    "wof:name":"Knickerbocker Hotel",
    "wof:placetype":"venue"
},
  "geometry": {"coordinates":[149.579315186,-33.4191360474],"type":"Point"}
}