{
  "type": "Feature",
  "properties": {
    "addr:full":"79 Alma Rd Clayfield QLD 4011",
    "addr:housenumber":"79",
    "addr:postcode":"4011",
    "addr:street":"Alma Rd",
    "iso:country":"AU",
    "sg:address":"79 Alma Rd",
    "sg:city":"Clayfield",
    "sg:classifiers":[
        {
            "category":"Professional",
            "subcategory":"Employment Agencies",
            "type":"Services"
        }
    ],
    "sg:phone":"+61 7 3262 9695",
    "sg:postcode":"4011",
    "sg:province":"QLD",
    "sg:tags":[
        "broker",
        "custom"
    ],
    "wof:name":"Trent Barratt",
    "wof:placetype":"venue"
},
  "geometry": {"coordinates":[153.058075,-27.411737],"type":"Point"}
}