{
  "type": "Feature",
  "properties": {
    "iso:country":"AU",
    "sg:address":"4/ 41 Roslyn St",
    "sg:city":"Rushcutters Bay",
    "sg:classifiers":[
        {
            "category":"Personal",
            "subcategory":"Adult",
            "type":"Services"
        }
    ],
    "sg:phone":"+61 2 9360 5693",
    "sg:postcode":"2011",
    "sg:province":"NSW",
    "sg:tags":[
        "vic",
        "except",
        "state",
        "escort",
        "social",
        "qld"
    ],
    "wof:name":"Talent Agency",
    "wof:placetype":"venue"
},
  "geometry": {"coordinates":[151.22552490199999,-33.874874115],"type":"Point"}
}