{
  "type": "Feature",
  "properties": {
    "iso:country":"AU",
    "sg:address":"12 King St",
    "sg:city":"Swan Hill",
    "sg:classifiers":[
        {
            "category":"Home & Garden",
            "subcategory":"Building Materials",
            "type":"Retail Goods"
        }
    ],
    "sg:phone":"+61 3 5032 1354",
    "sg:postcode":"3585",
    "sg:province":"VIC",
    "sg:tags":[
        "supply"
    ],
    "wof:name":"Hovendens Plaster Works",
    "wof:placetype":"venue"
},
  "geometry": {"coordinates":[143.55697599999999,-35.327976],"type":"Point"}
}