{
  "type": "Feature",
  "properties": {
    "iso:country":"AU",
    "sg:address":"Kioma Rd",
    "sg:city":"Kioma",
    "sg:classifiers":[
        {
            "category":"Education",
            "subcategory":"School",
            "type":"Public Place"
        }
    ],
    "sg:phone":"+61 7 4677 6169",
    "sg:postcode":"4498",
    "sg:province":"QLD",
    "sg:tags":[
        "state",
        "except",
        "nsw"
    ],
    "wof:name":"Kioma Primary",
    "wof:placetype":"venue"
},
  "geometry": {"coordinates":[149.78431701700001,-28.2955818176],"type":"Point"}
}