{
  "type": "Feature",
  "properties": {
    "addr:full":"Level 8, 150 Queen St Dandenong VIC 3175",
    "addr:housenumber":"150",
    "addr:postcode":"3175",
    "addr:street":"Queen St",
    "iso:country":"AU",
    "sg:address":"Level 8, 150 Queen St",
    "sg:city":"Dandenong",
    "sg:classifiers":[
        {
            "category":"Professional",
            "subcategory":"Management & Consulting",
            "type":"Services"
        }
    ],
    "sg:phone":"+61 3 9793 2655",
    "sg:postcode":"3175",
    "sg:province":"VIC",
    "sg:tags":[
        "consultant",
        "migration"
    ],
    "wof:name":"Cope Thornton",
    "wof:placetype":"venue"
},
  "geometry": {"coordinates":[145.198120117,-37.972530365],"type":"Point"}
}