{
  "type": "Feature",
  "properties": {
    "iso:country":"AU",
    "sg:address":"6 Fisher St",
    "sg:city":"Bucasia",
    "sg:classifiers":[
        {
            "category":"Education",
            "subcategory":"Kindergarten",
            "type":"Public Place"
        }
    ],
    "sg:phone":"+61 7 4954 6585",
    "sg:postcode":"4750",
    "sg:province":"QLD",
    "sg:tags":[
        "pre-schools"
    ],
    "wof:name":"C & K",
    "wof:placetype":"venue"
},
  "geometry": {"coordinates":[149.155777,-21.025593],"type":"Point"}
}