{
  "type": "Feature",
  "properties": {
    "addr:full":"74 Platinum St Crestmead QLD 4132",
    "addr:housenumber":"74",
    "addr:postcode":"4132",
    "addr:street":"Platinum St",
    "iso:country":"AU",
    "sg:address":"74 Platinum St",
    "sg:city":"Crestmead",
    "sg:classifiers":[
        {
            "category":"Home & Garden",
            "subcategory":"Garden Supply",
            "type":"Retail Goods"
        }
    ],
    "sg:phone":"+61 7 3827 8000",
    "sg:postcode":"4132",
    "sg:province":"QLD",
    "sg:tags":[
        "shed"
    ],
    "wof:name":"Spanbilt",
    "wof:placetype":"venue"
},
  "geometry": {"coordinates":[153.07542419399999,-27.6871147156],"type":"Point"}
}