{
  "type": "Feature",
  "properties": {
    "iso:country":"AU",
    "sg:address":"103 Corrimal St",
    "sg:city":"Wollongong",
    "sg:classifiers":[
        {
            "category":"Health Services",
            "subcategory":"Doctor",
            "type":"Services"
        }
    ],
    "sg:phone":"+61 2 4228 6111",
    "sg:postcode":"2500",
    "sg:province":"NSW",
    "sg:tags":[
        "medical",
        "practitioner"
    ],
    "wof:name":"Di Marco Anna",
    "wof:placetype":"venue"
},
  "geometry": {"coordinates":[150.90033,-34.424129],"type":"Point"}
}