{
  "type": "Feature",
  "properties": {
    "addr:full":"25 Anvil Rd Seven Hills NSW 2147",
    "addr:housenumber":"25",
    "addr:postcode":"2147",
    "addr:street":"Anvil Rd",
    "iso:country":"AU",
    "sg:address":"25 Anvil Rd",
    "sg:city":"Seven Hills",
    "sg:classifiers":[
        {
            "category":"Home & Garden",
            "subcategory":"Building Materials",
            "type":"Retail Goods"
        }
    ],
    "sg:phone":"+61 2 9624 4900",
    "sg:postcode":"2147",
    "sg:province":"NSW",
    "sg:tags":[
        "pre-mixed",
        "concrete"
    ],
    "wof:name":"Mini - Crete Pty Ltd",
    "wof:placetype":"venue"
},
  "geometry": {"coordinates":[150.958374023,-33.7783355713],"type":"Point"}
}