{
  "type": "Feature",
  "properties": {
    "addr:full":"62 Rowley Rd Burpengary QLD 4505",
    "addr:housenumber":"62",
    "addr:postcode":"4505",
    "addr:street":"Rowley Rd",
    "iso:country":"AU",
    "sg:address":"62 Rowley Rd",
    "sg:city":"Burpengary",
    "sg:classifiers":[
        {
            "category":"Building & Trades",
            "subcategory":"Construction",
            "type":"Services"
        }
    ],
    "sg:phone":"+61 7 3886 8681",
    "sg:postcode":"4505",
    "sg:province":"QLD",
    "sg:tags":[
        "earth",
        "excavating",
        "moving",
        "contractor"
    ],
    "wof:name":"L & R Earthmoving",
    "wof:placetype":"venue"
},
  "geometry": {"coordinates":[152.94630432100001,-27.1592922211],"type":"Point"}
}