{
  "type": "Feature",
  "properties": {
    "addr:full":"172 Georges River Rd Croydon Park NSW 2133",
    "addr:housenumber":"172",
    "addr:postcode":"2133",
    "addr:street":"Georges River Rd",
    "iso:country":"AU",
    "sg:address":"172 Georges River Rd",
    "sg:city":"Croydon Park",
    "sg:classifiers":[
        {
            "category":"Cafe",
            "type":"Food & Drink"
        }
    ],
    "sg:phone":"+61 2 9798 4660",
    "sg:postcode":"2133",
    "sg:province":"NSW",
    "wof:name":"IL Cafe Blu",
    "wof:placetype":"venue"
},
  "geometry": {"coordinates":[151.10797119099999,-33.8955612183],"type":"Point"}
}