{
  "type": "Feature",
  "properties": {
    "iso:country":"AU",
    "sg:address":"Kiosk 2 Market Square",
    "sg:city":"Geelong",
    "sg:classifiers":[
        {
            "category":"Building & Trades",
            "subcategory":"Locksmith",
            "type":"Services"
        }
    ],
    "sg:phone":"+61 3 5222 1557",
    "sg:postcode":"3220",
    "sg:province":"VIC",
    "sg:tags":[
        "lock"
    ],
    "wof:name":"Arcade Locksmiths",
    "wof:placetype":"venue"
},
  "geometry": {"coordinates":[144.35997,-38.151119],"type":"Point"}
}