{
  "type": "Feature",
  "properties": {
    "addr:full":"1A Anama St Fairy Meadow NSW 2519",
    "addr:housenumber":"1a",
    "addr:postcode":"2519",
    "addr:street":"Anama St",
    "iso:country":"AU",
    "sg:address":"1A Anama St",
    "sg:city":"Fairy Meadow",
    "sg:classifiers":[
        {
            "category":"Travel",
            "subcategory":"Hotels & Motels",
            "type":"Entertainment"
        }
    ],
    "sg:phone":"+61 2 4284 4000",
    "sg:postcode":"2519",
    "sg:province":"NSW",
    "wof:name":"Cabbage Tree Motel",
    "wof:placetype":"venue"
},
  "geometry": {"coordinates":[150.89335600000001,-34.391663],"type":"Point"}
}