{
  "type": "Feature",
  "properties": {
    "iso:country":"AU",
    "sg:address":"11 Windsor Rd",
    "sg:city":"Red Hill",
    "sg:classifiers":[
        {
            "category":"Health Services",
            "subcategory":"Doctor",
            "type":"Services"
        }
    ],
    "sg:phone":"+61 7 3369 2444",
    "sg:postcode":"4059",
    "sg:province":"QLD",
    "sg:tags":[
        "medical",
        "practitioner"
    ],
    "wof:name":"Turner Dana",
    "wof:placetype":"venue"
},
  "geometry": {"coordinates":[153.00703430199999,-27.4542312622],"type":"Point"}
}