{
  "type": "Feature",
  "properties": {
    "addr:full":"Crystal St Broken Hill NSW 2880",
    "addr:postcode":"2880",
    "addr:street":"Crystal St",
    "iso:country":"AU",
    "sg:address":"Crystal St",
    "sg:city":"Broken Hill",
    "sg:classifiers":[
        {
            "category":"Travel",
            "subcategory":"Travel Agent",
            "type":"Entertainment"
        }
    ],
    "sg:phone":"+61 8 8087 1400",
    "sg:postcode":"2880",
    "sg:province":"NSW",
    "sg:tags":[
        "consultant"
    ],
    "wof:name":"Countrylink",
    "wof:placetype":"venue"
},
  "geometry": {"coordinates":[141.46554565400001,-31.9597682953],"type":"Point"}
}