{
  "type": "Feature",
  "properties": {
    "iso:country":"AU",
    "sg:address":"Shp1/ 26 Pratt St",
    "sg:city":"Moonee Ponds",
    "sg:classifiers":[
        {
            "category":"Fast Food",
            "type":"Food & Drink"
        }
    ],
    "sg:phone":"+61 3 9370 7507",
    "sg:postcode":"3039",
    "sg:province":"VIC",
    "sg:tags":[
        "away",
        "take"
    ],
    "wof:name":"Burger Edge",
    "wof:placetype":"venue"
},
  "geometry": {"coordinates":[144.922043,-37.767342],"type":"Point"}
}