{
  "type": "Feature",
  "properties": {
    "addr:full":"PO Box 226 Kalgoorlie WA 6430",
    "addr:postcode":"6430",
    "iso:country":"AU",
    "sg:address":"PO Box 226",
    "sg:city":"Kalgoorlie",
    "sg:classifiers":[
        {
            "category":"Home & Garden",
            "subcategory":"Carpets & Floor Coverings",
            "type":"Retail Goods"
        }
    ],
    "sg:phone":"+61 8 9091 3400",
    "sg:postcode":"6430",
    "sg:province":"WA",
    "sg:tags":[
        "tile",
        "wall",
        "layer"
    ],
    "wof:name":"Tom The Tiler",
    "wof:placetype":"venue"
},
  "geometry": {"coordinates":[121.46343231199999,-30.7528495789],"type":"Point"}
}