{
  "type": "Feature",
  "properties": {
    "addr:full":"Unit 23, 17- 21 Bowden St Alexandria NSW 2015",
    "addr:housenumber":"17 21",
    "addr:postcode":"2015",
    "addr:street":"Bowden St",
    "iso:country":"AU",
    "sg:address":"Unit 23, 17- 21 Bowden St",
    "sg:city":"Alexandria",
    "sg:classifiers":[
        {
            "category":"Building & Trades",
            "subcategory":"Construction",
            "type":"Services"
        }
    ],
    "sg:phone":"+61 2 9318 1744",
    "sg:postcode":"2015",
    "sg:province":"NSW",
    "sg:tags":[
        "contractor"
    ],
    "wof:name":"Andrew Johnson Constructions Pty Ltd",
    "wof:placetype":"venue"
},
  "geometry": {"coordinates":[151.19595336899999,-33.9044761658],"type":"Point"}
}