{
  "type": "Feature",
  "properties": {
    "addr:full":"2a Old Creamy La Berry NSW 2535",
    "addr:housenumber":"2a",
    "addr:postcode":"2535",
    "addr:street":"Old Creamy La Berry",
    "iso:country":"AU",
    "sg:address":"2a Old Creamy La",
    "sg:city":"Berry",
    "sg:classifiers":[
        {
            "category":"Social Services",
            "subcategory":"Child Care",
            "type":"Services"
        }
    ],
    "sg:phone":"+61 2 4464 2744",
    "sg:postcode":"2535",
    "sg:province":"NSW",
    "sg:tags":[
        "breeding",
        "artificial"
    ],
    "wof:name":"Herd Improvers Australia Pty Ltd",
    "wof:placetype":"venue"
},
  "geometry": {"coordinates":[150.69612121599999,-34.7813873291],"type":"Point"}
}