{
  "type": "Feature",
  "properties": {
    "addr:full":"Level 24 Riverside Centre 123 Eagle St Brisbane QLD 4000",
    "addr:housenumber":"123",
    "addr:postcode":"4000",
    "addr:street":"Eagle St",
    "iso:country":"AU",
    "sg:address":"Level 24 Riverside Centre 123 Eagle St",
    "sg:city":"Brisbane",
    "sg:classifiers":[
        {
            "category":"Real Estate",
            "subcategory":"Real Estate Agent",
            "type":"Services"
        }
    ],
    "sg:phone":"+61 7 3231 2239",
    "sg:postcode":"4000",
    "sg:province":"QLD",
    "wof:name":"Ray White Prestige (Brisbane)",
    "wof:placetype":"venue"
},
  "geometry": {"coordinates":[153.03010559099999,-27.4673233032],"type":"Point"}
}