{
  "type": "Feature",
  "properties": {
    "addr:full":"2 Zeleny Rd Minchinbury NSW 2770",
    "addr:housenumber":"2",
    "addr:postcode":"2770",
    "addr:street":"Zeleny Rd",
    "iso:country":"AU",
    "sg:address":"2 Zeleny Rd",
    "sg:city":"Minchinbury",
    "sg:classifiers":[
        {
            "category":"Retail",
            "subcategory":"Storage",
            "type":"Services"
        }
    ],
    "sg:phone":"+61 2 9625 0200",
    "sg:postcode":"2770",
    "sg:province":"NSW",
    "wof:name":"Storage Australia Hornsby Pty Ltd",
    "wof:placetype":"venue"
},
  "geometry": {"coordinates":[150.810836792,-33.7823944092],"type":"Point"}
}