{
  "type": "Feature",
  "properties": {
    "addr:full":"5/ 16 Totterdel St Belconnen ACT 2617",
    "addr:housenumber":"/ 16",
    "addr:postcode":"2617",
    "addr:street":"Totterdel St",
    "iso:country":"AU",
    "sg:address":"5/ 16 Totterdel St",
    "sg:city":"Belconnen",
    "sg:classifiers":[
        {
            "category":"Professional",
            "subcategory":"Art Services",
            "type":"Services"
        }
    ],
    "sg:phone":"+61 422 269 074",
    "sg:postcode":"2617",
    "sg:province":"ACT",
    "sg:tags":[
        "decorator",
        "painter"
    ],
    "wof:name":"Horizon Painting Service",
    "wof:placetype":"venue"
},
  "geometry": {"coordinates":[149.059356689,-35.2347602844],"type":"Point"}
}