{
  "type": "Feature",
  "properties": {
    "addr:full":"65 Russell Rd Woodford NSW 2778",
    "addr:housenumber":"65",
    "addr:postcode":"2778",
    "addr:street":"Russell Rd",
    "iso:country":"AU",
    "sg:address":"65 Russell Rd",
    "sg:city":"Woodford",
    "sg:classifiers":[
        {
            "category":"Arts & Performance",
            "subcategory":"Art Gallery",
            "type":"Entertainment"
        }
    ],
    "sg:phone":"+61 2 6647 7262",
    "sg:postcode":"2778",
    "sg:province":"NSW",
    "wof:name":"Joanna Terpstras Studio Gallery",
    "wof:placetype":"venue"
},
  "geometry": {"coordinates":[150.47720336899999,-33.7344589233],"type":"Point"}
}