{
  "type": "Feature",
  "properties": {
    "addr:full":"21 Anzac Rd Leederville WA 6007",
    "addr:housenumber":"21",
    "addr:postcode":"6007",
    "addr:street":"Anzac Rd",
    "iso:country":"AU",
    "sg:address":"21 Anzac Rd",
    "sg:city":"Leederville",
    "sg:classifiers":[
        {
            "category":"Shopping",
            "subcategory":"Stationery & Office Supplies",
            "type":"Retail Goods"
        }
    ],
    "sg:phone":"+61 8 9444 7401",
    "sg:postcode":"6007",
    "sg:province":"WA",
    "sg:tags":[
        "partition"
    ],
    "wof:name":"A.B.M. Building Maintenance",
    "wof:placetype":"venue"
},
  "geometry": {"coordinates":[115.834472656,-31.9252071381],"type":"Point"}
}