{
  "type": "Feature",
  "properties": {
    "addr:full":"6 Caledonia Rd Australind WA 6233",
    "addr:housenumber":"6",
    "addr:postcode":"6233",
    "addr:street":"Caledonia Rd",
    "iso:country":"AU",
    "sg:address":"6 Caledonia Rd",
    "sg:city":"Australind",
    "sg:classifiers":[
        {
            "category":"Education",
            "subcategory":"School",
            "type":"Public Place"
        }
    ],
    "sg:phone":"+61 8 9841 1760",
    "sg:postcode":"6233",
    "sg:province":"WA",
    "sg:tags":[
        "co-educational"
    ],
    "wof:name":"Australind Baptist College",
    "wof:placetype":"venue"
},
  "geometry": {"coordinates":[115.72049,-33.283119],"type":"Point"}
}