{
  "type": "Feature",
  "properties": {
    "iso:country":"AU",
    "sg:address":"31 Bethania St",
    "sg:city":"Lota",
    "sg:classifiers":[
        {
            "category":"Shopping",
            "subcategory":"Party Supplies",
            "type":"Retail Goods"
        }
    ],
    "sg:phone":"+61 7 3901 0233",
    "sg:postcode":"4179",
    "sg:province":"QLD",
    "sg:tags":[
        "children's"
    ],
    "wof:name":"Rad Rides For Kidz",
    "wof:placetype":"venue"
},
  "geometry": {"coordinates":[153.184326172,-27.4692134857],"type":"Point"}
}