{
  "type": "Feature",
  "properties": {
    "addr:full":"Suite 9/ 13 Avalon Pde Avalon Beach NSW 2107",
    "addr:postcode":"2107",
    "addr:street":"Avalon Pde",
    "iso:country":"AU",
    "sg:address":"Suite 9/ 13 Avalon Pde",
    "sg:city":"Avalon Beach",
    "sg:classifiers":[
        {
            "category":"Professional",
            "subcategory":"Accounting & Tax Preparation",
            "type":"Services"
        }
    ],
    "sg:phone":"+61 2 9918 9900",
    "sg:postcode":"2107",
    "sg:province":"NSW",
    "sg:tags":[
        "accountant",
        "auditor"
    ],
    "wof:name":"Anthony Suters & Associates",
    "wof:placetype":"venue"
},
  "geometry": {"coordinates":[151.33590698200001,-33.6275253296],"type":"Point"}
}