{
  "type": "Feature",
  "properties": {
    "addr:full":"6 Masters St Riverton SA 5412",
    "addr:housenumber":"6",
    "addr:postcode":"5412",
    "addr:street":"Masters St",
    "iso:country":"AU",
    "sg:address":"6 Masters St",
    "sg:city":"Riverton",
    "sg:classifiers":[
        {
            "category":"Professional",
            "subcategory":"Accounting & Tax Preparation",
            "type":"Services"
        }
    ],
    "sg:phone":"+61 8 8847 2002",
    "sg:postcode":"5412",
    "sg:province":"SA",
    "sg:tags":[
        "consultant",
        "taxation"
    ],
    "wof:name":"Ford, McCarthy & Associates",
    "wof:placetype":"venue"
},
  "geometry": {"coordinates":[138.745849609,-34.1590385437],"type":"Point"}
}