{
  "type": "Feature",
  "properties": {
    "addr:full":"10 Farm Drv Redwood Park SA 5097",
    "addr:housenumber":"10",
    "addr:postcode":"5097",
    "addr:street":"Farm Drv",
    "iso:country":"AU",
    "sg:address":"10 Farm Drv",
    "sg:city":"Redwood Park",
    "sg:classifiers":[
        {
            "category":"Retail",
            "subcategory":"Repair Shop",
            "type":"Services"
        }
    ],
    "sg:phone":"+61 411 049 239",
    "sg:postcode":"5097",
    "sg:province":"SA",
    "sg:tags":[
        "machine",
        "sewing"
    ],
    "wof:name":"Doctor Needles",
    "wof:placetype":"venue"
},
  "geometry": {"coordinates":[138.70936584500001,-34.8116760254],"type":"Point"}
}