{
  "type": "Feature",
  "properties": {
    "addr:full":"PO Box 7095 Karingal VIC 3199",
    "addr:postcode":"3199",
    "iso:country":"AU",
    "sg:address":"PO Box 7095",
    "sg:city":"Karingal",
    "sg:classifiers":[
        {
            "category":"Professional",
            "subcategory":"Engineering",
            "type":"Services"
        }
    ],
    "sg:phone":"+61 3 9785 6299",
    "sg:postcode":"3199",
    "sg:province":"VIC",
    "sg:tags":[
        "engineer",
        "structural"
    ],
    "wof:name":"E-Struct Pty Ltd",
    "wof:placetype":"venue"
},
  "geometry": {"coordinates":[145.152832031,-38.1436195374],"type":"Point"}
}