{
  "type": "Feature",
  "properties": {
    "addr:full":"34 Holden St Fitzroy North VIC 3068",
    "addr:housenumber":"34",
    "addr:postcode":"3068",
    "addr:street":"Holden St",
    "iso:country":"AU",
    "sg:address":"34 Holden St",
    "sg:city":"Fitzroy North",
    "sg:classifiers":[
        {
            "category":"Building & Trades",
            "subcategory":"Construction",
            "type":"Services"
        }
    ],
    "sg:phone":"+61 417 301 976",
    "sg:postcode":"3068",
    "sg:province":"VIC",
    "sg:tags":[
        "polishing",
        "sanding",
        "floor"
    ],
    "wof:name":"TC Complete Floors",
    "wof:placetype":"venue"
},
  "geometry": {"coordinates":[144.97962951700001,-37.7793273926],"type":"Point"}
}