{
  "type": "Feature",
  "properties": {
    "addr:full":"16 Thomas St West Perth WA 6005",
    "addr:housenumber":"16",
    "addr:postcode":"6005",
    "addr:street":"Thomas St",
    "iso:country":"AU",
    "sg:address":"16 Thomas St",
    "sg:city":"West Perth",
    "sg:classifiers":[
        {
            "category":"Professional",
            "subcategory":"Art Services",
            "type":"Services"
        }
    ],
    "sg:phone":"+61 418 948 588",
    "sg:postcode":"6005",
    "sg:province":"WA",
    "sg:tags":[
        "interior",
        "designer"
    ],
    "wof:name":"Milton Barker Interior Design",
    "wof:placetype":"venue"
},
  "geometry": {"coordinates":[115.841163635,-31.9443073273],"type":"Point"}
}