{
  "type": "Feature",
  "properties": {
    "addr:full":"33 Wills Rd Long Point NSW 2564",
    "addr:housenumber":"33",
    "addr:postcode":"2564",
    "addr:street":"Wills Rd",
    "iso:country":"AU",
    "sg:address":"33 Wills Rd",
    "sg:city":"Long Point",
    "sg:classifiers":[
        {
            "category":"Building & Trades",
            "subcategory":"Construction",
            "type":"Services"
        }
    ],
    "sg:phone":"+61 2 9605 1406",
    "sg:postcode":"2564",
    "sg:province":"NSW",
    "sg:tags":[
        "contractor"
    ],
    "wof:name":"Mott Homes Pty Ltd",
    "wof:placetype":"venue"
},
  "geometry": {"coordinates":[150.898193359,-34.0123329163],"type":"Point"}
}