{
  "type": "Feature",
  "properties": {
    "addr:full":"Highland Park Shopping Plaza 106-112 Alexander Drv Nerang QLD 4211",
    "addr:housenumber":"106-112",
    "addr:postcode":"4211",
    "addr:street":"Alexander Drv",
    "iso:country":"AU",
    "sg:address":"Highland Park Shopping Plaza 106-112 Alexander Drv",
    "sg:city":"Nerang",
    "sg:classifiers":[
        {
            "category":"Retail",
            "subcategory":"Veterinary Services",
            "type":"Services"
        }
    ],
    "sg:phone":"+61 7 5574 9622",
    "sg:postcode":"4211",
    "sg:province":"QLD",
    "sg:tags":[
        "surgeon"
    ],
    "wof:name":"Medivet Highland Park",
    "wof:placetype":"venue"
},
  "geometry": {"coordinates":[153.335449219,-28.0136032104],"type":"Point"}
}