{
  "type": "Feature",
  "properties": {
    "addr:full":"Unit 2/ 54 Northbourne Ave Canberra City ACT 2601",
    "addr:housenumber":"54",
    "addr:postcode":"2601",
    "addr:street":"Northbourne Ave",
    "iso:country":"AU",
    "sg:address":"Unit 2/ 54 Northbourne Ave",
    "sg:city":"Canberra City",
    "sg:classifiers":[
        {
            "category":"Professional",
            "subcategory":"Engineering",
            "type":"Services"
        }
    ],
    "sg:phone":"+61 2 6248 7366",
    "sg:postcode":"2601",
    "sg:province":"ACT",
    "sg:tags":[
        "consulting",
        "engineer"
    ],
    "wof:name":"Coffey MPW Pty Ltd",
    "wof:placetype":"venue"
},
  "geometry": {"coordinates":[149.129592895,-35.2786865234],"type":"Point"}
}