{
  "type": "Feature",
  "properties": {
    "addr:full":"11 Peck St Hamilton VIC 3300",
    "addr:housenumber":"11",
    "addr:postcode":"3300",
    "addr:street":"Peck St",
    "iso:country":"AU",
    "sg:address":"11 Peck St",
    "sg:city":"Hamilton",
    "sg:classifiers":[
        {
            "category":"Home & Garden",
            "subcategory":"Household Appliances",
            "type":"Retail Goods"
        }
    ],
    "sg:phone":"+61 3 5571 1535",
    "sg:postcode":"3300",
    "sg:province":"VIC",
    "sg:tags":[
        "equipment",
        "gas"
    ],
    "wof:name":"Hutchins Dale",
    "wof:placetype":"venue"
},
  "geometry": {"coordinates":[142.00340270999999,-37.7267723083],"type":"Point"}
}