{
  "type": "Feature",
  "properties": {
    "iso:country":"AU",
    "sg:address":"282 Oxford St",
    "sg:city":"Paddington",
    "sg:classifiers":[
        {
            "category":"Shopping",
            "subcategory":"Music",
            "type":"Retail Goods"
        }
    ],
    "sg:phone":"+61 2 9361 3980",
    "sg:postcode":"2021",
    "sg:province":"NSW",
    "sg:tags":[
        "store"
    ],
    "wof:name":"Leading Edge Music",
    "wof:placetype":"venue"
},
  "geometry": {"coordinates":[151.227981567,-33.8852233887],"type":"Point"}
}