{
  "type": "Feature",
  "properties": {
    "addr:full":"680 Kiewa St Albury NSW 2640",
    "addr:housenumber":"680",
    "addr:postcode":"2640",
    "addr:street":"Kiewa St",
    "iso:country":"AU",
    "sg:address":"680 Kiewa St",
    "sg:city":"Albury",
    "sg:classifiers":[
        {
            "category":"Organizations",
            "subcategory":"Non-profit Organization",
            "type":"Services"
        }
    ],
    "sg:phone":"+61 2 6041 3432",
    "sg:postcode":"2640",
    "sg:province":"NSW",
    "sg:tags":[
        "support",
        "disability",
        "organisation"
    ],
    "wof:name":"Kalparrin Inc",
    "wof:placetype":"venue"
},
  "geometry": {"coordinates":[146.91749572800001,-36.0712089539],"type":"Point"}
}