{
  "type": "Feature",
  "properties": {
    "addr:full":"161 Collins St Melbourne VIC 3000",
    "addr:housenumber":"161",
    "addr:postcode":"3000",
    "addr:street":"Collins St",
    "iso:country":"AU",
    "sg:address":"161 Collins St",
    "sg:city":"Melbourne",
    "sg:classifiers":[
        {
            "category":"Shopping",
            "subcategory":"Clothing, Apparel, & Fashions",
            "type":"Retail Goods"
        }
    ],
    "sg:phone":"+61 3 9654 4299",
    "sg:postcode":"3000",
    "sg:province":"VIC",
    "sg:tags":[
        "lady",
        "wear"
    ],
    "wof:name":"Zambesi",
    "wof:placetype":"venue"
},
  "geometry": {"coordinates":[144.968383789,-37.8150634766],"type":"Point"}
}