{
  "type": "Feature",
  "properties": {
    "addr:full":"739 Camp Cable Rd Jimboomba QLD 4280",
    "addr:housenumber":"739",
    "addr:postcode":"4280",
    "addr:street":"Camp Cable Rd",
    "iso:country":"AU",
    "sg:address":"739 Camp Cable Rd",
    "sg:city":"Jimboomba",
    "sg:classifiers":[
        {
            "category":"Professional",
            "subcategory":"Computer Services",
            "type":"Services"
        }
    ],
    "sg:phone":"+61 407 655 455",
    "sg:postcode":"4280",
    "sg:province":"QLD",
    "sg:tags":[
        "repairs",
        "upgrade",
        "equipment"
    ],
    "wof:name":"Gedco Electronics",
    "wof:placetype":"venue"
},
  "geometry": {"coordinates":[153.02903699999999,-27.813055],"type":"Point"}
}