{
  "type": "Feature",
  "properties": {
    "iso:country":"AU",
    "sg:address":"81 Wingewarra St",
    "sg:city":"Dubbo",
    "sg:classifiers":[
        {
            "category":"Health Services",
            "subcategory":"Optometrist",
            "type":"Services"
        }
    ],
    "sg:phone":"+61 2 6882 6633",
    "sg:postcode":"2830",
    "sg:province":"NSW",
    "wof:name":"Morrisons Family Eye Care Centre",
    "wof:placetype":"venue"
},
  "geometry": {"coordinates":[148.60142517099999,-32.2489051819],"type":"Point"}
}