{
  "type": "Feature",
  "properties": {
    "addr:full":"Unit 2/ 6 Frank St Doncaster VIC 3108",
    "addr:housenumber":"6",
    "addr:postcode":"3108",
    "addr:street":"Frank St",
    "iso:country":"AU",
    "sg:address":"Unit 2/ 6 Frank St",
    "sg:city":"Doncaster",
    "sg:classifiers":[
        {
            "category":"Professional",
            "subcategory":"Computer Services",
            "type":"Services"
        }
    ],
    "sg:phone":"+61 3 9840 2003",
    "sg:postcode":"3108",
    "sg:province":"VIC",
    "sg:tags":[
        "package",
        "software"
    ],
    "wof:name":"Abacus Software",
    "wof:placetype":"venue"
},
  "geometry": {"coordinates":[145.127120972,-37.7937164307],"type":"Point"}
}