{
  "type": "Feature",
  "properties": {
    "addr:full":"194 Bayswater Rd Bayswater North VIC 3153",
    "addr:housenumber":"194",
    "addr:postcode":"3153",
    "addr:street":"Bayswater Rd",
    "iso:country":"AU",
    "sg:address":"194 Bayswater Rd",
    "sg:city":"Bayswater North",
    "sg:classifiers":[
        {
            "category":"Real Estate",
            "subcategory":"Architect",
            "type":"Services"
        }
    ],
    "sg:phone":"+61 3 9720 2144",
    "sg:postcode":"3153",
    "sg:province":"VIC",
    "sg:tags":[
        "fuel",
        "equipment",
        "pump",
        "carburettor"
    ],
    "wof:name":"Autosport",
    "wof:placetype":"venue"
},
  "geometry": {"coordinates":[145.268920898,-37.8186149597],"type":"Point"}
}