{
  "type": "Feature",
  "properties": {
    "addr:full":"Shp 2/ 208 Prospect Rd Prospect SA 5082",
    "addr:housenumber":"/ 208",
    "addr:postcode":"5082",
    "addr:street":"Prospect Rd",
    "iso:country":"AU",
    "sg:address":"Shp 2/ 208 Prospect Rd",
    "sg:city":"Prospect",
    "sg:classifiers":[
        {
            "category":"Shopping",
            "subcategory":"Crafts & Fabrics",
            "type":"Retail Goods"
        }
    ],
    "sg:phone":"+61 8 8344 5066",
    "sg:postcode":"5082",
    "sg:province":"SA",
    "sg:tags":[
        "supply"
    ],
    "wof:name":"Christina's Craft & Gifts",
    "wof:placetype":"venue"
},
  "geometry": {"coordinates":[138.593353272,-34.879611969],"type":"Point"}
}