{
  "type": "Feature",
  "properties": {
    "addr:full":"23 Mt Pleasant Ave Normanhurst NSW 2076",
    "addr:housenumber":"23",
    "addr:postcode":"2076",
    "addr:street":"Mt Pleasant Ave",
    "iso:country":"AU",
    "sg:address":"23 Mt Pleasant Ave",
    "sg:city":"Normanhurst",
    "sg:classifiers":[
        {
            "category":"Building & Trades",
            "subcategory":"Plumbing",
            "type":"Services"
        }
    ],
    "sg:phone":"+61 1300 665 452",
    "sg:postcode":"2076",
    "sg:province":"NSW",
    "sg:tags":[
        "plumber",
        "gasfitters"
    ],
    "wof:name":"Purple Group Plumbing",
    "wof:placetype":"venue"
},
  "geometry": {"coordinates":[151.099441528,-33.7257766724],"type":"Point"}
}