{
  "type": "Feature",
  "properties": {
    "addr:full":"7 Fern Ave Tea Tree Gully SA 5091",
    "addr:housenumber":"7",
    "addr:postcode":"5091",
    "addr:street":"Fern Ave",
    "iso:country":"AU",
    "sg:address":"7 Fern Ave",
    "sg:city":"Tea Tree Gully",
    "sg:classifiers":[
        {
            "category":"Building & Trades",
            "subcategory":"Landscaping Services",
            "type":"Services"
        }
    ],
    "sg:phone":"+61 413 698 480",
    "sg:postcode":"5091",
    "sg:province":"SA",
    "sg:tags":[
        "designer",
        "landscape",
        "contractor"
    ],
    "wof:name":"Adelaide Outdoor Living",
    "wof:placetype":"venue"
},
  "geometry": {"coordinates":[138.72145080600001,-34.8272247314],"type":"Point"}
}