{
  "type": "Feature",
  "properties": {
    "iso:country":"AU",
    "sg:address":"1379 Botany Rd",
    "sg:city":"Botany",
    "sg:classifiers":[
        {
            "category":"Fast Food",
            "type":"Food & Drink"
        }
    ],
    "sg:phone":"+61 2 9695 1441",
    "sg:postcode":"2019",
    "sg:province":"NSW",
    "sg:tags":[
        "away",
        "take"
    ],
    "wof:name":"The Sandwich Platter",
    "wof:placetype":"venue"
},
  "geometry": {"coordinates":[151.19598388700001,-33.9434623718],"type":"Point"}
}