{
  "type": "Feature",
  "properties": {
    "addr:full":"71 Dr Mays Rd Bundaberg QLD 4670",
    "addr:housenumber":"71",
    "addr:postcode":"4670",
    "addr:street":"Dr Mays Rd",
    "iso:country":"AU",
    "sg:address":"71 Dr Mays Rd",
    "sg:city":"Bundaberg",
    "sg:classifiers":[
        {
            "category":"Travel",
            "subcategory":"Hostel",
            "type":"Entertainment"
        }
    ],
    "sg:phone":"+61 7 4153 8000",
    "sg:postcode":"4670",
    "sg:province":"QLD",
    "sg:tags":[
        "home"
    ],
    "wof:name":"Bundaberg - Gracehaven Lutheran Homes",
    "wof:placetype":"venue"
},
  "geometry": {"coordinates":[152.33085632300001,-24.8857517242],"type":"Point"}
}