{
  "type": "Feature",
  "properties": {
    "iso:country":"AU",
    "sg:address":"Level 11 120 Edward St",
    "sg:city":"Brisbane",
    "sg:classifiers":[
        {
            "category":"Banks & Credit Unions",
            "subcategory":"Financial Services",
            "type":"Services"
        }
    ],
    "sg:phone":"+61 1300 363 895",
    "sg:postcode":"4000",
    "sg:province":"QLD",
    "sg:tags":[
        "annuity",
        "rollover",
        "superannuation",
        "consultant"
    ],
    "wof:name":"Host Plus Superannuation Fund",
    "wof:placetype":"venue"
},
  "geometry": {"coordinates":[153.02850341800001,-27.4700927734],"type":"Point"}
}