{
  "type": "Feature",
  "properties": {
    "iso:country":"AU",
    "sg:address":"Lvl 40/ 140 William St",
    "sg:city":"Melbourne",
    "sg:classifiers":[
        {
            "category":"Retail",
            "subcategory":"Auto Rental",
            "type":"Services"
        }
    ],
    "sg:phone":"+61 3 9016 3736",
    "sg:postcode":"3000",
    "sg:province":"VIC",
    "sg:tags":[
        "chauffeur",
        "car",
        "hire",
        "driven",
        "limousine"
    ],
    "wof:name":"Melbourne Chauffeur Driven Limousines & Buses",
    "wof:placetype":"venue"
},
  "geometry": {"coordinates":[144.95840454099999,-37.8157501221],"type":"Point"}
}