{
  "type": "Feature",
  "properties": {
    "addr:full":"16 Tarlington Pl Smithfield NSW 2164",
    "addr:housenumber":"16",
    "addr:postcode":"2164",
    "addr:street":"Tarlington Pl",
    "iso:country":"AU",
    "sg:address":"16 Tarlington Pl",
    "sg:city":"Smithfield",
    "sg:classifiers":[
        {
            "category":"Wholesale",
            "subcategory":"Painting Supplies",
            "type":"Manufacturing & Wholesale Goods"
        }
    ],
    "sg:phone":"+61 2 9604 1511",
    "sg:postcode":"2164",
    "sg:province":"NSW",
    "sg:tags":[
        "product",
        "cleaning"
    ],
    "wof:name":"Magic Chemical Co. The",
    "wof:placetype":"venue"
},
  "geometry": {"coordinates":[150.926467895,-33.8351478577],"type":"Point"}
}