{
  "type": "Feature",
  "properties": {
    "iso:country":"AU",
    "sg:address":"41 Miners Dr",
    "sg:city":"Wonthaggi",
    "sg:classifiers":[
        {
            "category":"Building & Trades",
            "subcategory":"Plumbing",
            "type":"Services"
        }
    ],
    "sg:phone":"+61 412 248 234",
    "sg:postcode":"3995",
    "sg:province":"VIC",
    "sg:tags":[
        "plumber",
        "gasfitters"
    ],
    "wof:name":"Keith Weitering",
    "wof:placetype":"venue"
},
  "geometry": {"coordinates":[145.598648,-38.613899],"type":"Point"}
}