{
  "type": "Feature",
  "properties": {
    "iso:country":"AU",
    "sg:address":"Level 19, 2 Market St,",
    "sg:city":"Sydney",
    "sg:classifiers":[
        {
            "category":"Banks & Credit Unions",
            "subcategory":"Financial Services",
            "type":"Services"
        }
    ],
    "sg:phone":"+61 1300 138 991",
    "sg:postcode":"2000",
    "sg:province":"NSW",
    "sg:tags":[
        "advisory",
        "planning",
        "retirement"
    ],
    "wof:name":"BDO Kendalls",
    "wof:placetype":"venue"
},
  "geometry": {"coordinates":[151.203979492,-33.8708496094],"type":"Point"}
}