{
  "type": "Feature",
  "properties": {
    "addr:full":"23 Scammel St Campbellfield VIC 3061",
    "addr:housenumber":"23",
    "addr:postcode":"3061",
    "addr:street":"Scammel St",
    "iso:country":"AU",
    "sg:address":"23 Scammel St",
    "sg:city":"Campbellfield",
    "sg:classifiers":[
        {
            "category":"Manufacturing",
            "subcategory":"Metals",
            "type":"Manufacturing & Wholesale Goods"
        }
    ],
    "sg:phone":"+61 3 9303 7324",
    "sg:postcode":"3061",
    "sg:province":"VIC",
    "sg:tags":[
        "polisher"
    ],
    "wof:name":"T.E.A.M. Metal Finishing",
    "wof:placetype":"venue"
},
  "geometry": {"coordinates":[144.94439697300001,-37.6457595825],"type":"Point"}
}