{
  "type": "Feature",
  "properties": {
    "addr:full":"Suite F/ 116 Dempster St Esperance WA 6450",
    "addr:housenumber":"suite;/ 116",
    "addr:postcode":"6450",
    "addr:street":"Dempster St",
    "iso:country":"AU",
    "sg:address":"Suite F/ 116 Dempster St",
    "sg:city":"Esperance",
    "sg:classifiers":[
        {
            "category":"Health Services",
            "subcategory":"Dentist",
            "type":"Services"
        }
    ],
    "sg:phone":"+61 8 9071 3289",
    "sg:postcode":"6450",
    "sg:province":"WA",
    "wof:name":"Harris Christopher Dr",
    "wof:placetype":"venue"
},
  "geometry": {"coordinates":[121.893081665,-33.8596305847],"type":"Point"}
}