{
  "type": "Feature",
  "properties": {
    "addr:full":"2 Driffield Crs Sassafras VIC 3787",
    "addr:postcode":"3787",
    "addr:street":"2 Driffield Crs",
    "iso:country":"AU",
    "sg:address":"2 Driffield Crs",
    "sg:city":"Sassafras",
    "sg:classifiers":[
        {
            "category":"Professional",
            "subcategory":"Art Services",
            "type":"Services"
        }
    ],
    "sg:phone":"+61 3 9755 2268",
    "sg:postcode":"3787",
    "sg:province":"VIC",
    "sg:tags":[
        "graphic",
        "designer"
    ],
    "wof:name":"Matthew Schwerbtfeger",
    "wof:placetype":"venue"
},
  "geometry": {"coordinates":[145.35128800000001,-37.86301],"type":"Point"}
}