{
  "type": "Feature",
  "properties": {
    "addr:full":"124 Reid La Gundowring VIC 3691",
    "addr:housenumber":"124",
    "addr:postcode":"3691",
    "addr:street":"Reid La Gundowring",
    "iso:country":"AU",
    "sg:address":"124 Reid La",
    "sg:city":"Gundowring",
    "sg:classifiers":[
        {
            "category":"Utilities",
            "subcategory":"Water",
            "type":"Services"
        }
    ],
    "sg:phone":"+61 408 698 634",
    "sg:postcode":"3691",
    "sg:province":"VIC",
    "sg:tags":[
        "hot",
        "system"
    ],
    "wof:name":"Allsop R & J",
    "wof:placetype":"venue"
},
  "geometry": {"coordinates":[147.076401,-36.344196],"type":"Point"}
}