{
  "type": "Feature",
  "properties": {
    "addr:full":"55 Hetherton Rd Endeavour Hills VIC 3802",
    "addr:housenumber":"55",
    "addr:postcode":"3802",
    "addr:street":"Hetherton Rd",
    "iso:country":"AU",
    "sg:address":"55 Hetherton Rd",
    "sg:city":"Endeavour Hills",
    "sg:classifiers":[
        {
            "category":"Travel",
            "subcategory":"Hostel",
            "type":"Entertainment"
        }
    ],
    "sg:phone":"+61 3 9706 2188",
    "sg:postcode":"3802",
    "sg:province":"VIC",
    "sg:tags":[
        "home"
    ],
    "wof:name":"Viewhills Manor",
    "wof:placetype":"venue"
},
  "geometry": {"coordinates":[145.27630615199999,-37.976890564],"type":"Point"}
}