{
  "type": "Feature",
  "properties": {
    "addr:full":"305 Oxley Rd Graceville East QLD 4075",
    "addr:housenumber":"305",
    "addr:postcode":"4075",
    "addr:street":"Oxley Rd",
    "iso:country":"AU",
    "sg:address":"305 Oxley Rd",
    "sg:city":"Graceville East",
    "sg:classifiers":[
        {
            "category":"Professional",
            "subcategory":"Computer Services",
            "type":"Services"
        }
    ],
    "sg:phone":"+61 414 535 727",
    "sg:postcode":"4075",
    "sg:province":"QLD",
    "sg:tags":[
        "consultant",
        "system"
    ],
    "wof:name":"St Leger Systems",
    "wof:placetype":"venue"
},
  "geometry": {"coordinates":[152.981033325,-27.5253334045],"type":"Point"}
}