{
  "type": "Feature",
  "properties": {
    "addr:full":"Shop 31 , Karratha Shopping Vlge Karratha WA 6714",
    "addr:housenumber":"shop 31",
    "addr:postcode":"6714",
    "addr:street":"Karratha Shopping",
    "iso:country":"AU",
    "sg:address":"Shop 31",
    "sg:city":", Karratha Shopping Vlge Karratha",
    "sg:classifiers":[
        {
            "category":"Professional",
            "subcategory":"Employment Agencies",
            "type":"Services"
        }
    ],
    "sg:phone":"+61 3 9215 9222",
    "sg:postcode":"6714",
    "sg:province":"WA",
    "sg:tags":[
        "hire",
        "labour",
        "contractor"
    ],
    "wof:name":"Drake",
    "wof:placetype":"venue"
},
  "geometry": {"coordinates":[116.84902954099999,-20.7548427582],"type":"Point"}
}