{
  "type": "Feature",
  "properties": {
    "iso:country":"AU",
    "sg:address":"11 High St",
    "sg:city":"New Norfolk",
    "sg:classifiers":[
        {
            "category":"Professional",
            "subcategory":"Accounting & Tax Preparation",
            "type":"Services"
        }
    ],
    "sg:phone":"+61 3 6261 3532",
    "sg:postcode":"7140",
    "sg:province":"TAS",
    "sg:tags":[
        "consultant",
        "taxation"
    ],
    "wof:name":"H & R Block",
    "wof:placetype":"venue"
},
  "geometry": {"coordinates":[147.06184400000001,-42.781414],"type":"Point"}
}