{
  "type": "Feature",
  "properties": {
    "addr:full":"67 East St Rockhampton QLD 4700",
    "addr:housenumber":"67",
    "addr:postcode":"4700",
    "addr:street":"East St",
    "iso:country":"AU",
    "sg:address":"67 East St",
    "sg:city":"Rockhampton",
    "sg:classifiers":[
        {
            "category":"Organizations",
            "subcategory":"Community Association",
            "type":"Services"
        }
    ],
    "sg:phone":"+61 7 4922 7668",
    "sg:postcode":"4700",
    "sg:province":"QLD",
    "sg:tags":[
        "organisation",
        "family",
        "welfare"
    ],
    "wof:name":"Community Rent Scheme (C H A)",
    "wof:placetype":"venue"
},
  "geometry": {"coordinates":[150.521194458,-23.3889884949],"type":"Point"}
}