{
  "type": "Feature",
  "properties": {
    "addr:full":"23 Farr St Marrickville NSW 2204",
    "addr:housenumber":"23",
    "addr:postcode":"2204",
    "addr:street":"Farr St",
    "iso:country":"AU",
    "sg:address":"23 Farr St",
    "sg:city":"Marrickville",
    "sg:classifiers":[
        {
            "category":"Retail",
            "subcategory":"Driving School",
            "type":"Services"
        }
    ],
    "sg:phone":"+61 2 9560 5239",
    "sg:postcode":"2204",
    "sg:province":"NSW",
    "sg:tags":[
        "equipment",
        "pile",
        "contractor"
    ],
    "wof:name":"MacDonald Sheet Piling",
    "wof:placetype":"venue"
},
  "geometry": {"coordinates":[151.16142300000001,-33.908276],"type":"Point"}
}