{
  "type": "Feature",
  "properties": {
    "iso:country":"AU",
    "sg:address":"2 Bennetts Grove Ave",
    "sg:city":"Paddington",
    "sg:classifiers":[
        {
            "category":"Shopping",
            "subcategory":"Clothing, Apparel, & Fashions",
            "type":"Retail Goods"
        }
    ],
    "sg:phone":"+61 2 9361 4733",
    "sg:postcode":"2021",
    "sg:province":"NSW",
    "sg:tags":[
        "textile",
        "designer"
    ],
    "wof:name":"Meridian Fashion Concepts",
    "wof:placetype":"venue"
},
  "geometry": {"coordinates":[151.22889709500001,-33.884311676],"type":"Point"}
}