{
  "type": "Feature",
  "properties": {
    "addr:full":"92 Aiken Rd West Pennant Hills NSW 2125",
    "addr:housenumber":"92",
    "addr:postcode":"2125",
    "addr:street":"Aiken Rd",
    "iso:country":"AU",
    "sg:address":"92 Aiken Rd",
    "sg:city":"West Pennant Hills",
    "sg:classifiers":[
        {
            "category":"Professional",
            "subcategory":"Computer Services",
            "type":"Services"
        }
    ],
    "sg:phone":"+61 416 259 485",
    "sg:postcode":"2125",
    "sg:province":"NSW",
    "sg:tags":[
        "consultant",
        "system"
    ],
    "wof:name":"Speirsoft Pty Ltd",
    "wof:placetype":"venue"
},
  "geometry": {"coordinates":[151.03044128400001,-33.7526321411],"type":"Point"}
}