{
  "type": "Feature",
  "properties": {
    "addr:full":"Unit 4, 15- 17 Pease St Manunda QLD 4870",
    "addr:housenumber":"15 17",
    "addr:postcode":"4870",
    "addr:street":"Pease St",
    "iso:country":"AU",
    "sg:address":"Unit 4, 15- 17 Pease St",
    "sg:city":"Manunda",
    "sg:classifiers":[
        {
            "category":"Health Services",
            "subcategory":"Health Practitioner",
            "type":"Services"
        }
    ],
    "sg:phone":"+61 7 4053 6111",
    "sg:postcode":"4870",
    "sg:province":"QLD",
    "sg:tags":[
        "audiologists"
    ],
    "wof:name":"Philippa Carter",
    "wof:placetype":"venue"
},
  "geometry": {"coordinates":[145.74160766599999,-16.9110012054],"type":"Point"}
}