{
  "type": "Feature",
  "properties": {
    "iso:country":"AU",
    "sg:address":"450 Canning Hwy",
    "sg:city":"Como",
    "sg:classifiers":[
        {
            "category":"Personal",
            "subcategory":"Massage",
            "type":"Services"
        }
    ],
    "sg:phone":"+61 8 9450 7111",
    "sg:postcode":"6152",
    "sg:province":"WA",
    "sg:tags":[
        "therapy"
    ],
    "wof:name":"Birtwistle Susan Remedial Massage Therapy",
    "wof:placetype":"venue"
},
  "geometry": {"coordinates":[115.860313,-32.004517],"type":"Point"}
}