{
  "type": "Feature",
  "properties": {
    "iso:country":"AU",
    "sg:address":"74 Augustin Drv",
    "sg:city":"Highton",
    "sg:classifiers":[
        {
            "category":"Utilities",
            "subcategory":"Electric",
            "type":"Services"
        }
    ],
    "sg:phone":"+61 418 524 321",
    "sg:postcode":"3216",
    "sg:province":"VIC",
    "sg:tags":[
        "electrical",
        "contractor"
    ],
    "wof:name":"Geelong Safety Switches",
    "wof:placetype":"venue"
},
  "geometry": {"coordinates":[144.31251525900001,-38.1943893433],"type":"Point"}
}