{
  "type": "Feature",
  "properties": {
    "addr:full":"Shop 19 Market Square Shopng Cntr Geelong VIC 3220",
    "addr:housenumber":"shop 19",
    "addr:postcode":"3220",
    "addr:street":"Market Square Shopng",
    "iso:country":"AU",
    "sg:address":"Shop 19",
    "sg:city":"Market Square Shopng Cntr Geelong",
    "sg:classifiers":[
        {
            "category":"Fast Food",
            "type":"Food & Drink"
        }
    ],
    "sg:phone":"+61 3 5229 8181",
    "sg:postcode":"3220",
    "sg:province":"VIC",
    "sg:tags":[
        "away",
        "take"
    ],
    "wof:name":"Cooks Cuisine",
    "wof:placetype":"venue"
},
  "geometry": {"coordinates":[144.34605400000001,-38.157108],"type":"Point"}
}