{
  "type": "Feature",
  "properties": {
    "iso:country":"AU",
    "sg:address":"Ste 7/ 157 Queen St",
    "sg:city":"Campbelltown",
    "sg:classifiers":[
        {
            "category":"Professional",
            "subcategory":"Accounting & Tax Preparation",
            "type":"Services"
        }
    ],
    "sg:phone":"+61 2 4627 8599",
    "sg:postcode":"2560",
    "sg:province":"NSW",
    "sg:tags":[
        "accountant",
        "auditor"
    ],
    "wof:name":"Henry Assaf",
    "wof:placetype":"venue"
},
  "geometry": {"coordinates":[150.814208984,-34.0665130615],"type":"Point"}
}