{
  "type": "Feature",
  "properties": {
    "addr:full":"371 Guildford Rd Bayswater WA 6053",
    "addr:housenumber":"371",
    "addr:postcode":"6053",
    "addr:street":"Guildford Rd",
    "iso:country":"AU",
    "sg:address":"371 Guildford Rd",
    "sg:city":"Bayswater",
    "sg:classifiers":[
        {
            "category":"Retail",
            "subcategory":"Auto Rental",
            "type":"Services"
        }
    ],
    "sg:phone":"+61 8 9271 4813",
    "sg:postcode":"6053",
    "sg:province":"WA",
    "sg:tags":[
        "bus",
        "truck"
    ],
    "wof:name":"Swan Car Rentals",
    "wof:placetype":"venue"
},
  "geometry": {"coordinates":[115.918983459,-31.9242191315],"type":"Point"}
}