{
  "type": "Feature",
  "properties": {
    "addr:full":"17 Ryan Rd Mt Isa QLD 4825",
    "addr:housenumber":"17",
    "addr:postcode":"4825",
    "addr:street":"Ryan Rd",
    "iso:country":"AU",
    "sg:address":"17 Ryan Rd",
    "sg:city":"Mt Isa",
    "sg:classifiers":[
        {
            "category":"Building & Trades",
            "subcategory":"Construction",
            "type":"Services"
        }
    ],
    "sg:phone":"+61 7 4743 5177",
    "sg:postcode":"4825",
    "sg:province":"QLD",
    "sg:tags":[
        "welding"
    ],
    "wof:name":"Wrights Welding",
    "wof:placetype":"venue"
},
  "geometry": {"coordinates":[139.49813800000001,-20.700869],"type":"Point"}
}