{
  "type": "Feature",
  "properties": {
    "iso:country":"AU",
    "sg:address":"359 Settlement Rd",
    "sg:city":"Thomastown",
    "sg:classifiers":[
        {
            "category":"Fast Food",
            "type":"Food & Drink"
        }
    ],
    "sg:phone":"+61 3 9466 3508",
    "sg:postcode":"3074",
    "sg:province":"VIC",
    "sg:tags":[
        "away",
        "take"
    ],
    "wof:name":"Pegasus Fast Food",
    "wof:placetype":"venue"
},
  "geometry": {"coordinates":[145.01890564000001,-37.6886444092],"type":"Point"}
}