{
  "type": "Feature",
  "properties": {
    "iso:country":"AU",
    "sg:address":"106 Goulburn St",
    "sg:city":"Crookwell",
    "sg:classifiers":[
        {
            "category":"Banks & Credit Unions",
            "subcategory":"Investment Brokerage",
            "type":"Services"
        }
    ],
    "sg:phone":"+61 1800 502 522",
    "sg:postcode":"2583",
    "sg:province":"NSW",
    "sg:tags":[
        "share",
        "broker",
        "stock"
    ],
    "wof:name":"Capricorn Financial Planners",
    "wof:placetype":"venue"
},
  "geometry": {"coordinates":[149.47306823700001,-34.4602050781],"type":"Point"}
}