{
  "type": "Feature",
  "properties": {
    "iso:country":"AU",
    "sg:address":"Shop 7 2 Chard Rd",
    "sg:city":"Brookvale",
    "sg:classifiers":[
        {
            "category":"Personal",
            "subcategory":"Beauty Salon",
            "type":"Services"
        }
    ],
    "sg:phone":"+61 2 9905 5249",
    "sg:postcode":"2100",
    "sg:province":"NSW",
    "sg:tags":[
        "hairdresser"
    ],
    "wof:name":"Hair Solution Centre",
    "wof:placetype":"venue"
},
  "geometry": {"coordinates":[151.27182006800001,-33.762878418],"type":"Point"}
}