{
  "type": "Feature",
  "properties": {
    "addr:full":"201 Manifold St Camperdown VIC 3260",
    "addr:housenumber":"201",
    "addr:postcode":"3260",
    "addr:street":"Manifold St",
    "iso:country":"AU",
    "sg:address":"201 Manifold St",
    "sg:city":"Camperdown",
    "sg:classifiers":[
        {
            "category":"Fast Food",
            "type":"Food & Drink"
        }
    ],
    "sg:phone":"+61 3 5593 2015",
    "sg:postcode":"3260",
    "sg:province":"VIC",
    "sg:tags":[
        "away",
        "take"
    ],
    "wof:name":"Davis Milkbar",
    "wof:placetype":"venue"
},
  "geometry": {"coordinates":[143.14590454099999,-38.2321815491],"type":"Point"}
}