{
  "type": "Feature",
  "properties": {
    "iso:country":"AU",
    "sg:address":"81 Redland Bay Rd",
    "sg:city":"Capalaba",
    "sg:classifiers":[
        {
            "category":"Retail",
            "subcategory":"Storage",
            "type":"Services"
        }
    ],
    "sg:phone":"+61 7 3823 1000",
    "sg:postcode":"4157",
    "sg:province":"QLD",
    "wof:name":"Maximum Security Self Storage Redlands",
    "wof:placetype":"venue"
},
  "geometry": {"coordinates":[153.207687378,-27.5357074738],"type":"Point"}
}