{
  "type": "Feature",
  "properties": {
    "iso:country":"AU",
    "sg:address":"71 Capel Drv",
    "sg:city":"Capel",
    "sg:classifiers":[
        {
            "category":"Building & Trades",
            "subcategory":"Construction",
            "type":"Services"
        }
    ],
    "sg:phone":"+61 8 9727 2645",
    "sg:postcode":"6271",
    "sg:province":"WA",
    "sg:tags":[
        "earth",
        "excavating",
        "moving",
        "contractor"
    ],
    "wof:name":"NW & B Weston",
    "wof:placetype":"venue"
},
  "geometry": {"coordinates":[115.561203003,-33.5519180298],"type":"Point"}
}