{
  "type": "Feature",
  "properties": {
    "addr:full":"31 Cypress Drv Ashgrove QLD 4060",
    "addr:housenumber":"31",
    "addr:postcode":"4060",
    "addr:street":"Cypress Drv",
    "iso:country":"AU",
    "sg:address":"31 Cypress Drv",
    "sg:city":"Ashgrove",
    "sg:classifiers":[
        {
            "category":"Professional",
            "subcategory":"Art Services",
            "type":"Services"
        }
    ],
    "sg:phone":"+61 7 3366 3389",
    "sg:postcode":"4060",
    "sg:province":"QLD",
    "sg:tags":[
        "decorator",
        "painter"
    ],
    "wof:name":"Michael Anderson Painting",
    "wof:placetype":"venue"
},
  "geometry": {"coordinates":[152.979415894,-27.4456386566],"type":"Point"}
}