{
  "type": "Feature",
  "properties": {
    "addr:full":"6 Rae Crt Melton South VIC 3338",
    "addr:housenumber":"6",
    "addr:postcode":"3338",
    "addr:street":"Rae Crt",
    "iso:country":"AU",
    "sg:address":"6 Rae Crt",
    "sg:city":"Melton South",
    "sg:classifiers":[
        {
            "category":"Health Services",
            "subcategory":"Doctor",
            "type":"Services"
        }
    ],
    "sg:phone":"+61 412 512 454",
    "sg:postcode":"3338",
    "sg:province":"VIC",
    "sg:tags":[
        "occupational",
        "safety"
    ],
    "wof:name":"Safenet (Aust) Pty Ltd",
    "wof:placetype":"venue"
},
  "geometry": {"coordinates":[144.57470699999999,-37.692295],"type":"Point"}
}