{
  "type": "Feature",
  "properties": {
    "addr:full":"311 Collier Rd Bassendean WA 6054",
    "addr:housenumber":"311",
    "addr:postcode":"6054",
    "addr:street":"Collier Rd",
    "iso:country":"AU",
    "sg:address":"311 Collier Rd",
    "sg:city":"Bassendean",
    "sg:classifiers":[
        {
            "category":"Home & Garden",
            "subcategory":"Building Materials",
            "type":"Retail Goods"
        }
    ],
    "sg:phone":"+61 8 9279 9999",
    "sg:postcode":"6054",
    "sg:province":"WA",
    "sg:tags":[
        "fencing"
    ],
    "wof:name":"Southern Wire",
    "wof:placetype":"venue"
},
  "geometry": {"coordinates":[115.93296051,-31.9055595398],"type":"Point"}
}