{
  "type": "Feature",
  "properties": {
    "addr:full":"1 Victor Rd Bentleigh East VIC 3165",
    "addr:housenumber":"1",
    "addr:postcode":"3165",
    "addr:street":"Victor Rd",
    "iso:country":"AU",
    "sg:address":"1 Victor Rd",
    "sg:city":"Bentleigh East",
    "sg:classifiers":[
        {
            "category":"Retail",
            "subcategory":"Event Space",
            "type":"Services"
        }
    ],
    "sg:phone":"+61 3 9579 4855",
    "sg:postcode":"3165",
    "sg:province":"VIC",
    "sg:tags":[
        "venue",
        "reception",
        "wedding"
    ],
    "wof:name":"South Oakleigh Club",
    "wof:placetype":"venue"
},
  "geometry": {"coordinates":[145.077957153,-37.9308357239],"type":"Point"}
}