{
  "type": "Feature",
  "properties": {
    "addr:full":"59 Garfield St Launceston TAS 7250",
    "addr:housenumber":"59",
    "addr:postcode":"7250",
    "addr:street":"Garfield St",
    "iso:country":"AU",
    "sg:address":"59 Garfield St",
    "sg:city":"Launceston",
    "sg:classifiers":[
        {
            "category":"Manufacturing",
            "subcategory":"Retail Goods",
            "type":"Manufacturing & Wholesale Goods"
        }
    ],
    "sg:phone":"+61 3 6344 8811",
    "sg:postcode":"7250",
    "sg:province":"TAS",
    "sg:tags":[
        "merchant",
        "pump",
        "mfrs"
    ],
    "wof:name":"Bamford H M (Launceston)",
    "wof:placetype":"venue"
},
  "geometry": {"coordinates":[147.14256286599999,-41.4512443542],"type":"Point"}
}