{
  "type": "Feature",
  "properties": {
    "addr:full":"103 Bussell Hwy Margaret River WA 6285",
    "addr:housenumber":"103",
    "addr:postcode":"6285",
    "addr:street":"Bussell Hwy",
    "iso:country":"AU",
    "sg:address":"103 Bussell Hwy",
    "sg:city":"Margaret River",
    "sg:classifiers":[
        {
            "category":"Fast Food",
            "type":"Food & Drink"
        }
    ],
    "sg:phone":"+61 8 9757 2722",
    "sg:postcode":"6285",
    "sg:province":"WA",
    "sg:tags":[
        "away",
        "take"
    ],
    "wof:name":"Subway",
    "wof:placetype":"venue"
},
  "geometry": {"coordinates":[115.074363709,-33.9492874146],"type":"Point"}
}