{
  "type": "Feature",
  "properties": {
    "iso:country":"AU",
    "sg:address":"62 Noorong Ave",
    "sg:city":"Forresters Beach",
    "sg:classifiers":[
        {
            "category":"Building & Trades",
            "subcategory":"Construction",
            "type":"Services"
        }
    ],
    "sg:phone":"+61 2 4385 8280",
    "sg:postcode":"2260",
    "sg:province":"NSW",
    "sg:tags":[
        "contractor"
    ],
    "wof:name":"Allard Building Co Pty Ltd",
    "wof:placetype":"venue"
},
  "geometry": {"coordinates":[151.460541,-33.41341],"type":"Point"}
}