{
  "type": "Feature",
  "properties": {
    "addr:full":"3/ 28 Norfolk Rd South Brisbane QLD 4101",
    "addr:housenumber":"/ 28",
    "addr:postcode":"4101",
    "addr:street":"Norfolk Rd",
    "iso:country":"AU",
    "sg:address":"3/ 28 Norfolk Rd",
    "sg:city":"South Brisbane",
    "sg:classifiers":[
        {
            "category":"Building & Trades",
            "subcategory":"Cleaning & Sanitation",
            "type":"Services"
        }
    ],
    "sg:phone":"+61 7 3846 2666",
    "sg:postcode":"4101",
    "sg:province":"QLD",
    "sg:tags":[
        "window"
    ],
    "wof:name":"Pickwick Group Pty Ltd",
    "wof:placetype":"venue"
},
  "geometry": {"coordinates":[153.011474609,-27.475566864],"type":"Point"}
}