{
  "type": "Feature",
  "properties": {
    "addr:full":"Unit 4/ 16 Ledgar Rd Balcatta WA 6021",
    "addr:postcode":"6021",
    "addr:street":"16 Ledgar Rd",
    "iso:country":"AU",
    "sg:address":"Unit 4/ 16 Ledgar Rd",
    "sg:city":"Balcatta",
    "sg:classifiers":[
        {
            "category":"Communications",
            "subcategory":"Film & Video Production",
            "type":"Services"
        }
    ],
    "sg:phone":"+61 8 9240 6051",
    "sg:postcode":"6021",
    "sg:province":"WA",
    "sg:tags":[
        "fan",
        "blower"
    ],
    "wof:name":"Mineair Australia Pty Ltd",
    "wof:placetype":"venue"
},
  "geometry": {"coordinates":[115.80342865,-31.8649215698],"type":"Point"}
}