{
  "type": "Feature",
  "properties": {
    "addr:full":"28 Main Rd Paynesville VIC 3880",
    "addr:housenumber":"28",
    "addr:postcode":"3880",
    "addr:street":"Main Rd",
    "iso:country":"AU",
    "sg:address":"28 Main Rd",
    "sg:city":"Paynesville",
    "sg:classifiers":[
        {
            "category":"Professional",
            "subcategory":"Art Services",
            "type":"Services"
        }
    ],
    "sg:phone":"+61 418 516 872",
    "sg:postcode":"3880",
    "sg:province":"VIC",
    "sg:tags":[
        "decorator",
        "painter"
    ],
    "wof:name":"BJ John Saunders Painters",
    "wof:placetype":"venue"
},
  "geometry": {"coordinates":[147.72013855,-37.9074211121],"type":"Point"}
}