{
  "type": "Feature",
  "properties": {
    "iso:country":"AU",
    "sg:address":"8 Sherbrooke Rd",
    "sg:city":"West Ryde",
    "sg:classifiers":[
        {
            "category":"Health Services",
            "subcategory":"Nursing And Care Facility",
            "type":"Services"
        }
    ],
    "sg:phone":"+61 2 9809 3217",
    "sg:postcode":"2114",
    "sg:province":"NSW",
    "sg:tags":[
        "home"
    ],
    "wof:name":"Fernleigh Nursing Home",
    "wof:placetype":"venue"
},
  "geometry": {"coordinates":[151.08578491200001,-33.8136749268],"type":"Point"}
}