{
  "type": "Feature",
  "properties": {
    "addr:full":"26 Tait St Newport VIC 3015",
    "addr:housenumber":"26",
    "addr:postcode":"3015",
    "addr:street":"Tait St",
    "iso:country":"AU",
    "sg:address":"26 Tait St",
    "sg:city":"Newport",
    "sg:classifiers":[
        {
            "category":"Autos & Motor Vehicles",
            "subcategory":"Auto Supplies",
            "type":"Retail Goods"
        }
    ],
    "sg:phone":"+61 3 9391 1183",
    "sg:postcode":"3015",
    "sg:province":"VIC",
    "sg:tags":[
        "part",
        "cycles",
        "accessory"
    ],
    "wof:name":"Bikelug Pty Ltd",
    "wof:placetype":"venue"
},
  "geometry": {"coordinates":[144.88536071799999,-37.8428001404],"type":"Point"}
}