{
  "type": "Feature",
  "properties": {
    "iso:country":"AU",
    "sg:address":"PO Box 7114",
    "sg:city":"Safety Bay",
    "sg:classifiers":[
        {
            "category":"Retail",
            "subcategory":"Auto Repair",
            "type":"Services"
        }
    ],
    "sg:phone":"+61 8 9437 9990",
    "sg:postcode":"6169",
    "sg:province":"WA",
    "sg:tags":[
        "repairer",
        "motor",
        "engineer"
    ],
    "wof:name":"Mechanic On The Move",
    "wof:placetype":"venue"
},
  "geometry": {"coordinates":[115.732857,-32.308941],"type":"Point"}
}