{
  "type": "Feature",
  "properties": {
    "addr:full":"PO Box 186 Morisset NSW 2264",
    "addr:postcode":"2264",
    "iso:country":"AU",
    "sg:address":"PO Box 186",
    "sg:city":"Morisset",
    "sg:classifiers":[
        {
            "category":"Utilities",
            "subcategory":"Electric",
            "type":"Services"
        }
    ],
    "sg:phone":"+61 2 4973 1237",
    "sg:postcode":"2264",
    "sg:province":"NSW",
    "sg:tags":[
        "electrical",
        "contractor"
    ],
    "wof:name":"Roy Mould",
    "wof:placetype":"venue"
},
  "geometry": {"coordinates":[151.46464499999999,-33.141376],"type":"Point"}
}