{
  "type": "Feature",
  "properties": {
    "iso:country":"AU",
    "sg:address":"63 Patty St",
    "sg:city":"Mentone",
    "sg:classifiers":[
        {
            "category":"Building & Trades",
            "subcategory":"Construction",
            "type":"Services"
        }
    ],
    "sg:phone":"+61 3 9584 4226",
    "sg:postcode":"3194",
    "sg:province":"VIC",
    "sg:tags":[
        "contractor"
    ],
    "wof:name":"M P Hellier Builders Pty Ltd",
    "wof:placetype":"venue"
},
  "geometry": {"coordinates":[145.06019592300001,-37.9773254395],"type":"Point"}
}