{
  "type": "Feature",
  "properties": {
    "addr:full":"2288 Gold Coast Hwy Mermaid Beach QLD 4218",
    "addr:housenumber":"2288",
    "addr:postcode":"4218",
    "addr:street":"Gold Coast Hwy",
    "iso:country":"AU",
    "sg:address":"2288 Gold Coast Hwy",
    "sg:city":"Mermaid Beach",
    "sg:classifiers":[
        {
            "category":"Building & Trades",
            "subcategory":"Pest Control",
            "type":"Services"
        }
    ],
    "sg:phone":"+61 7 5570 1114",
    "sg:postcode":"4218",
    "sg:province":"QLD",
    "wof:name":"Kaldoe Building Inspections",
    "wof:placetype":"venue"
},
  "geometry": {"coordinates":[153.437103272,-28.0545501709],"type":"Point"}
}