{
  "type": "Feature",
  "properties": {
    "addr:full":"475A Centre Rd Bentleigh VIC 3204",
    "addr:housenumber":"475a",
    "addr:postcode":"3204",
    "addr:street":"Centre Rd",
    "iso:country":"AU",
    "sg:address":"475A Centre Rd",
    "sg:city":"Bentleigh",
    "sg:classifiers":[
        {
            "category":"Fast Food",
            "type":"Food & Drink"
        }
    ],
    "sg:phone":"+61 3 9557 8148",
    "sg:postcode":"3204",
    "sg:province":"VIC",
    "sg:tags":[
        "away",
        "take"
    ],
    "wof:name":"Bentleigh Charcoal Chickens and Salads",
    "wof:placetype":"venue"
},
  "geometry": {"coordinates":[145.041946,-37.918709],"type":"Point"}
}