{
  "type": "Feature",
  "properties": {
    "iso:country":"AU",
    "sg:address":"PO Box 143",
    "sg:city":"Deakin West",
    "sg:classifiers":[
        {
            "category":"Professional",
            "subcategory":"Art Services",
            "type":"Services"
        }
    ],
    "sg:phone":"+61 2 6232 5720",
    "sg:postcode":"2600",
    "sg:province":"ACT",
    "sg:tags":[
        "interior",
        "designer"
    ],
    "wof:name":"Karin McNamara Design",
    "wof:placetype":"venue"
},
  "geometry": {"coordinates":[149.10168457,-35.3217124939],"type":"Point"}
}