{
  "type": "Feature",
  "properties": {
    "addr:full":"59a Stewart Ave Hamilton NSW 2303",
    "addr:housenumber":"59a",
    "addr:postcode":"2303",
    "addr:street":"Stewart Ave",
    "iso:country":"AU",
    "sg:address":"59a Stewart Ave",
    "sg:city":"Hamilton",
    "sg:classifiers":[
        {
            "category":"Real Estate",
            "subcategory":"Real Estate Agent",
            "type":"Services"
        }
    ],
    "sg:phone":"+61 2 4962 3388",
    "sg:postcode":"2303",
    "sg:province":"NSW",
    "wof:name":"Griffiths Garth",
    "wof:placetype":"venue"
},
  "geometry": {"coordinates":[151.75344799999999,-32.931721],"type":"Point"}
}