{
  "type": "Feature",
  "properties": {
    "addr:full":"2- 4 Westmelton Drv Melton West VIC 3337",
    "addr:housenumber":"4",
    "addr:postcode":"3337",
    "addr:street":"Westmelton Drv",
    "iso:country":"AU",
    "sg:address":"2- 4 Westmelton Drv",
    "sg:city":"Melton West",
    "sg:classifiers":[
        {
            "category":"Social Services",
            "subcategory":"Child Care",
            "type":"Services"
        }
    ],
    "sg:phone":"+61 3 9743 5068",
    "sg:postcode":"3337",
    "sg:province":"VIC",
    "sg:tags":[
        "support",
        "health"
    ],
    "wof:name":"Maternal & Child Health Centres",
    "wof:placetype":"venue"
},
  "geometry": {"coordinates":[144.568985,-37.677624],"type":"Point"}
}