{
  "type": "Feature",
  "properties": {
    "addr:full":"88 Commercial Rd Port Augusta SA 5700",
    "addr:housenumber":"88",
    "addr:postcode":"5700",
    "addr:street":"Commercial Rd",
    "iso:country":"AU",
    "sg:address":"88 Commercial Rd",
    "sg:city":"Port Augusta",
    "sg:classifiers":[
        {
            "category":"Banks & Credit Unions",
            "subcategory":"Bank",
            "type":"Services"
        }
    ],
    "sg:phone":"+61 13 20 32",
    "sg:postcode":"5700",
    "sg:province":"SA",
    "wof:name":"Westpac",
    "wof:placetype":"venue"
},
  "geometry": {"coordinates":[137.76365661599999,-32.4932136536],"type":"Point"}
}