{
  "type": "Feature",
  "properties": {
    "addr:full":"242 Young St Waterloo NSW 2017",
    "addr:housenumber":"242",
    "addr:postcode":"2017",
    "addr:street":"Young St",
    "iso:country":"AU",
    "sg:address":"242 Young St",
    "sg:city":"Waterloo",
    "sg:classifiers":[
        {
            "category":"Shopping",
            "subcategory":"Computers & Home Electronics",
            "type":"Retail Goods"
        }
    ],
    "sg:phone":"+61 2 9699 3122",
    "sg:postcode":"2017",
    "sg:province":"NSW",
    "sg:tags":[
        "plate",
        "name"
    ],
    "wof:name":"Coates Signco",
    "wof:placetype":"venue"
},
  "geometry": {"coordinates":[151.208526611,-33.900718689],"type":"Point"}
}