{
  "type": "Feature",
  "properties": {
    "addr:full":"11 Kelly Ave Armidale NSW 2350",
    "addr:housenumber":"11",
    "addr:postcode":"2350",
    "addr:street":"Kelly Ave",
    "iso:country":"AU",
    "sg:address":"11 Kelly Ave",
    "sg:city":"Armidale",
    "sg:classifiers":[
        {
            "category":"Utilities",
            "type":"Services"
        }
    ],
    "sg:phone":"+61 408 668 033",
    "sg:postcode":"2350",
    "sg:province":"NSW",
    "sg:tags":[
        "refrigeration",
        "industrial",
        "commercial",
        "retail"
    ],
    "wof:name":"Armidale District Refrigeration",
    "wof:placetype":"venue"
},
  "geometry": {"coordinates":[151.671783447,-30.5042419434],"type":"Point"}
}