{
  "type": "Feature",
  "properties": {
    "addr:full":"Shop 43 Menai Market Place Allison Crs Menai NSW 2234",
    "addr:housenumber":"shop 43",
    "addr:postcode":"2234",
    "addr:street":"Market Place Allison Crs",
    "iso:country":"AU",
    "sg:address":"Shop 43 Menai Market Place Allison Crs",
    "sg:city":"Menai",
    "sg:classifiers":[
        {
            "category":"Personal",
            "subcategory":"Beauty Salon",
            "type":"Services"
        }
    ],
    "sg:phone":"+61 2 9541 0822",
    "sg:postcode":"2234",
    "sg:province":"NSW",
    "wof:name":"Skin Expressions Menai",
    "wof:placetype":"venue"
},
  "geometry": {"coordinates":[151.04327392600001,-34.0198097229],"type":"Point"}
}