{
  "type": "Feature",
  "properties": {
    "addr:full":"22 Mackenzie St Young NSW 2594",
    "addr:housenumber":"22",
    "addr:postcode":"2594",
    "addr:street":"Mackenzie St",
    "iso:country":"AU",
    "sg:address":"22 Mackenzie St",
    "sg:city":"Young",
    "sg:classifiers":[
        {
            "category":"Structure",
            "subcategory":"Bridge",
            "type":"Public Place"
        }
    ],
    "sg:phone":"+61 2 6382 2870",
    "sg:postcode":"2594",
    "sg:province":"NSW",
    "sg:tags":[
        "chainsaw",
        "brushcutters"
    ],
    "wof:name":"Lambing Flat Engineering",
    "wof:placetype":"venue"
},
  "geometry": {"coordinates":[148.28411865199999,-34.3129386902],"type":"Point"}
}