{
  "type": "Feature",
  "properties": {
    "addr:full":"1 Abbotsford Rd Katoomba NSW 2780",
    "addr:housenumber":"1",
    "addr:postcode":"2780",
    "addr:street":"Abbotsford Rd",
    "iso:country":"AU",
    "sg:address":"1 Abbotsford Rd",
    "sg:city":"Katoomba",
    "sg:classifiers":[
        {
            "category":"Health Services",
            "subcategory":"Doctor",
            "type":"Services"
        }
    ],
    "sg:phone":"+61 2 4782 9482",
    "sg:postcode":"2780",
    "sg:province":"NSW",
    "sg:tags":[
        "medical",
        "practitioner"
    ],
    "wof:name":"Kolos Dr Phillip Paediatrician",
    "wof:placetype":"venue"
},
  "geometry": {"coordinates":[150.31019592300001,-33.7201080322],"type":"Point"}
}