{
  "type": "Feature",
  "properties": {
    "addr:full":"41 Leighton Pl Asquith NSW 2077",
    "addr:housenumber":"41",
    "addr:postcode":"2077",
    "addr:street":"Leighton Pl",
    "iso:country":"AU",
    "sg:address":"41 Leighton Pl",
    "sg:city":"Asquith",
    "sg:classifiers":[
        {
            "category":"Wholesale",
            "subcategory":"Hardware",
            "type":"Manufacturing & Wholesale Goods"
        }
    ],
    "sg:phone":"+61 2 9476 7400",
    "sg:postcode":"2077",
    "sg:province":"NSW",
    "wof:name":"Fix-A-Tap Australia Pty Ltd",
    "wof:placetype":"venue"
},
  "geometry": {"coordinates":[151.11723327600001,-33.6941604614],"type":"Point"}
}