{
  "type": "Feature",
  "properties": {
    "iso:country":"AU",
    "sg:address":"24b Annette St",
    "sg:city":"Oatley",
    "sg:classifiers":[
        {
            "category":"Building & Trades",
            "subcategory":"Construction",
            "type":"Services"
        }
    ],
    "sg:phone":"+61 2 9580 5251",
    "sg:postcode":"2223",
    "sg:province":"NSW",
    "sg:tags":[
        "contractor"
    ],
    "wof:name":"Ioannidis D",
    "wof:placetype":"venue"
},
  "geometry": {"coordinates":[151.08244323700001,-33.9873504639],"type":"Point"}
}