{
  "type": "Feature",
  "properties": {
    "addr:full":"6 Tennyson St Clyde NSW 2142",
    "addr:housenumber":"6",
    "addr:postcode":"2142",
    "addr:street":"Tennyson St",
    "iso:country":"AU",
    "sg:address":"6 Tennyson St",
    "sg:city":"Clyde",
    "sg:classifiers":[
        {
            "category":"Shopping Center",
            "type":"Public Place"
        }
    ],
    "sg:phone":"+61 2 9637 2550",
    "sg:postcode":"2142",
    "sg:province":"NSW",
    "sg:tags":[
        "spawn",
        "supplier",
        "mushroom"
    ],
    "wof:name":"Country Fresh Mushrooms Pty Ltd",
    "wof:placetype":"venue"
},
  "geometry": {"coordinates":[151.027053833,-33.8332595825],"type":"Point"}
}