{
  "type": "Feature",
  "properties": {
    "addr:full":"PO Box 141 Wulguru QLD 4811",
    "addr:postcode":"4811",
    "iso:country":"AU",
    "sg:address":"PO Box 141",
    "sg:city":"Wulguru",
    "sg:classifiers":[
        {
            "category":"Shopping",
            "subcategory":"Party Supplies",
            "type":"Retail Goods"
        }
    ],
    "sg:phone":"+61 7 4778 2969",
    "sg:postcode":"4811",
    "sg:province":"QLD",
    "sg:tags":[
        "children's"
    ],
    "wof:name":"Polly's Crafts",
    "wof:placetype":"venue"
},
  "geometry": {"coordinates":[146.820786,-19.326389],"type":"Point"}
}