{
  "type": "Feature",
  "properties": {
    "iso:country":"AU",
    "sg:address":"522- 524",
    "sg:city":"Kingsway Miranda",
    "sg:classifiers":[
        {
            "category":"Building & Trades",
            "subcategory":"Plumbing",
            "type":"Services"
        }
    ],
    "sg:phone":"+61 418 445 394",
    "sg:postcode":"2228",
    "sg:province":"NSW",
    "sg:tags":[
        "plumber",
        "gasfitters"
    ],
    "wof:name":"A.A. Abaabolish Blocked Drains Berger Plumbing Pty Ltd",
    "wof:placetype":"venue"
},
  "geometry": {"coordinates":[151.10432434099999,-34.0345458984],"type":"Point"}
}