{
  "type": "Feature",
  "properties": {
    "addr:full":"Shop 1 103 George St Kalbar QLD 4309",
    "addr:housenumber":"shop 1 103",
    "addr:postcode":"4309",
    "addr:street":"George St",
    "iso:country":"AU",
    "sg:address":"Shop 1 103 George St",
    "sg:city":"Kalbar",
    "sg:classifiers":[
        {
            "category":"Personal",
            "subcategory":"Beauty Salon",
            "type":"Services"
        }
    ],
    "sg:phone":"+61 7 5463 7172",
    "sg:postcode":"4309",
    "sg:province":"QLD",
    "wof:name":"The Lilac Room Skin.Body.Nails",
    "wof:placetype":"venue"
},
  "geometry": {"coordinates":[152.62478637699999,-27.934431076],"type":"Point"}
}