{
  "type": "Feature",
  "properties": {
    "iso:country":"AU",
    "sg:address":"120 Princess Hwy",
    "sg:city":"Milton",
    "sg:classifiers":[
        {
            "category":"Building & Trades",
            "subcategory":"Landscaping Services",
            "type":"Services"
        }
    ],
    "sg:phone":"+61 2 4454 0812",
    "sg:postcode":"2538",
    "sg:province":"NSW",
    "sg:tags":[
        "inspection"
    ],
    "wof:name":"Rapid Inspect",
    "wof:placetype":"venue"
},
  "geometry": {"coordinates":[150.44003295900001,-35.3176307678],"type":"Point"}
}