{
  "type": "Feature",
  "properties": {
    "addr:full":"168 Gilbert St Adelaide SA 5000",
    "addr:housenumber":"168",
    "addr:postcode":"5000",
    "addr:street":"Gilbert St",
    "iso:country":"AU",
    "sg:address":"168 Gilbert St",
    "sg:city":"Adelaide",
    "sg:classifiers":[
        {
            "category":"Retail",
            "subcategory":"Car Wash",
            "type":"Services"
        }
    ],
    "sg:phone":"+61 8 8231 2912",
    "sg:postcode":"5000",
    "sg:province":"SA",
    "sg:tags":[
        "truck",
        "cleaning"
    ],
    "wof:name":"Brodason Transport Pty Ltd",
    "wof:placetype":"venue"
},
  "geometry": {"coordinates":[138.59410095199999,-34.9344902039],"type":"Point"}
}