{
  "type": "Feature",
  "properties": {
    "addr:full":"7 Colane St Concord West NSW 2138",
    "addr:housenumber":"7",
    "addr:postcode":"2138",
    "addr:street":"Colane St",
    "iso:country":"AU",
    "sg:address":"7 Colane St",
    "sg:city":"Concord West",
    "sg:classifiers":[
        {
            "category":"Utilities",
            "subcategory":"Electric",
            "type":"Services"
        }
    ],
    "sg:phone":"+61 409 819 389",
    "sg:postcode":"2138",
    "sg:province":"NSW",
    "sg:tags":[
        "electrical",
        "contractor"
    ],
    "wof:name":"Elliot C J",
    "wof:placetype":"venue"
},
  "geometry": {"coordinates":[151.093185425,-33.8419799805],"type":"Point"}
}