{
  "type": "Feature",
  "properties": {
    "iso:country":"AU",
    "sg:address":"56 John St",
    "sg:city":"Cabramatta",
    "sg:classifiers":[
        {
            "category":"Shopping",
            "subcategory":"Crafts & Fabrics",
            "type":"Retail Goods"
        }
    ],
    "sg:phone":"+61 2 9728 7928",
    "sg:postcode":"2166",
    "sg:province":"NSW",
    "sg:tags":[
        "material",
        "dress"
    ],
    "wof:name":"Hai Ha Fabrics",
    "wof:placetype":"venue"
},
  "geometry": {"coordinates":[150.936279297,-33.8952217102],"type":"Point"}
}