{
  "type": "Feature",
  "properties": {
    "addr:full":"Factory 25, 36 Norfolk Crt Coburg North VIC 3058",
    "addr:housenumber":"36",
    "addr:postcode":"3058",
    "addr:street":"Norfolk Crt",
    "iso:country":"AU",
    "sg:address":"Factory 25, 36 Norfolk Crt",
    "sg:city":"Coburg North",
    "sg:classifiers":[
        {
            "category":"Professional",
            "subcategory":"Printing & Photocopies",
            "type":"Services"
        }
    ],
    "sg:phone":"+61 3 9350 5433",
    "sg:postcode":"3058",
    "sg:province":"VIC",
    "sg:tags":[
        "photocopying"
    ],
    "wof:name":"A.S.A.P Print Copy Bind P/L",
    "wof:placetype":"venue"
},
  "geometry": {"coordinates":[144.98042297399999,-37.7218437195],"type":"Point"}
}