{
  "type": "Feature",
  "properties": {
    "iso:country":"AU",
    "sg:address":"229 Lower Dandenong Rd",
    "sg:city":"Mordialloc",
    "sg:classifiers":[
        {
            "category":"Commercial Area",
            "type":"Public Place"
        }
    ],
    "sg:phone":"+61 3 9587 7200",
    "sg:postcode":"3195",
    "sg:province":"VIC",
    "sg:tags":[
        "heavy",
        "carrier"
    ],
    "wof:name":"Finnegan Transport",
    "wof:placetype":"venue"
},
  "geometry": {"coordinates":[145.09568786599999,-37.9848060608],"type":"Point"}
}