{
  "type": "Feature",
  "properties": {
    "addr:full":"136 Giles St Katherine NT 0850",
    "addr:housenumber":"136",
    "addr:postcode":"nt 0850",
    "addr:street":"Giles St",
    "iso:country":"AU",
    "sg:address":"136 Giles St",
    "sg:city":"Katherine",
    "sg:classifiers":[
        {
            "category":"Home & Garden",
            "subcategory":"Garden Supply",
            "type":"Retail Goods"
        }
    ],
    "sg:phone":"+61 8 8971 0521",
    "sg:postcode":"0850",
    "sg:province":"NT",
    "sg:tags":[
        "equipment"
    ],
    "wof:name":"K.A Nursery & Hardware",
    "wof:placetype":"venue"
},
  "geometry": {"coordinates":[132.26889,-14.446389],"type":"Point"}
}