{
  "type": "Feature",
  "properties": {
    "addr:full":"1/ 2 Masters Rd Mt St Thomas NSW 2500",
    "addr:housenumber":"/ 2",
    "addr:postcode":"2500",
    "addr:street":"Masters Rd Mt",
    "iso:country":"AU",
    "sg:address":"1/ 2 Masters Rd Mt St",
    "sg:city":"Thomas",
    "sg:classifiers":[
        {
            "category":"Shopping",
            "subcategory":"Party Supplies",
            "type":"Retail Goods"
        }
    ],
    "sg:phone":"+61 2 4285 4326",
    "sg:postcode":"2500",
    "sg:province":"NSW",
    "sg:tags":[
        "children's"
    ],
    "wof:name":"Illawarra Gymnastic Sporting Complex",
    "wof:placetype":"venue"
},
  "geometry": {"coordinates":[150.86918600000001,-34.443649],"type":"Point"}
}