{
  "type": "Feature",
  "properties": {
    "iso:country":"AU",
    "sg:address":"U3/ 20 Neumann Rd",
    "sg:city":"Capalaba",
    "sg:classifiers":[
        {
            "category":"Social Services",
            "subcategory":"Child Care",
            "type":"Services"
        }
    ],
    "sg:phone":"+61 7 3390 1095",
    "sg:postcode":"4157",
    "sg:province":"QLD",
    "sg:tags":[
        "equipment",
        "supply"
    ],
    "wof:name":"Annie's Attic",
    "wof:placetype":"venue"
},
  "geometry": {"coordinates":[153.2056427,-27.5332183838],"type":"Point"}
}