{
  "type": "Feature",
  "properties": {
    "iso:country":"AU",
    "sg:address":"30- 36 Mark Anthony Drv",
    "sg:city":"Dandenong",
    "sg:classifiers":[
        {
            "category":"Shopping",
            "subcategory":"Crafts & Fabrics",
            "type":"Retail Goods"
        }
    ],
    "sg:phone":"+61 3 9706 6905",
    "sg:postcode":"3175",
    "sg:province":"VIC",
    "sg:tags":[
        "synthetic",
        "canvas",
        "product"
    ],
    "wof:name":"Selbys Pty Ltd",
    "wof:placetype":"venue"
},
  "geometry": {"coordinates":[145.194213867,-38.0350074768],"type":"Point"}
}