{
  "type": "Feature",
  "properties": {
    "addr:full":"20 Eungai Pl Narrabeen NSW 2101",
    "addr:housenumber":"20",
    "addr:postcode":"2101",
    "addr:street":"Eungai Pl",
    "iso:country":"AU",
    "sg:address":"20 Eungai Pl",
    "sg:city":"Narrabeen",
    "sg:classifiers":[
        {
            "category":"Professional",
            "subcategory":"Art Services",
            "type":"Services"
        }
    ],
    "sg:phone":"+61 2 9944 7787",
    "sg:postcode":"2101",
    "sg:province":"NSW",
    "sg:tags":[
        "graphic",
        "designer"
    ],
    "wof:name":"Wild BlueYonder Visual Communications",
    "wof:placetype":"venue"
},
  "geometry": {"coordinates":[151.28602599999999,-33.699314],"type":"Point"}
}