{
  "type": "Feature",
  "properties": {
    "addr:full":"Suite 3 77 Asling St Brighton VIC 3186",
    "addr:housenumber":"77",
    "addr:postcode":"3186",
    "addr:street":"Asling St",
    "iso:country":"AU",
    "sg:address":"Suite 3 77 Asling St",
    "sg:city":"Brighton",
    "sg:classifiers":[
        {
            "category":"Health Services",
            "subcategory":"Health Practitioner",
            "type":"Services"
        }
    ],
    "sg:phone":"+61 3 9596 8866",
    "sg:postcode":"3186",
    "sg:province":"VIC",
    "sg:tags":[
        "audiologists"
    ],
    "wof:name":"A. Bayside Hearing Clinic",
    "wof:placetype":"venue"
},
  "geometry": {"coordinates":[145.002883911,-37.8976898193],"type":"Point"}
}