{
  "type": "Feature",
  "properties": {
    "addr:full":"118 Park St South Melbourne VIC 3205",
    "addr:housenumber":"118",
    "addr:postcode":"3205",
    "addr:street":"Park St",
    "iso:country":"AU",
    "sg:address":"118 Park St",
    "sg:city":"South Melbourne",
    "sg:classifiers":[
        {
            "category":"Restaurant",
            "type":"Food & Drink"
        }
    ],
    "sg:phone":"+61 3 9699 7810",
    "sg:postcode":"3205",
    "sg:province":"VIC",
    "wof:name":"Curried Away",
    "wof:placetype":"venue"
},
  "geometry": {"coordinates":[144.96700999999999,-37.833511],"type":"Point"}
}