{
  "type": "Feature",
  "properties": {
    "addr:full":"43 Greville Rd Rosanna VIC 3084",
    "addr:housenumber":"43",
    "addr:postcode":"3084",
    "addr:street":"Greville Rd",
    "iso:country":"AU",
    "sg:address":"43 Greville Rd",
    "sg:city":"Rosanna",
    "sg:classifiers":[
        {
            "category":"Personal",
            "subcategory":"Massage",
            "type":"Services"
        }
    ],
    "sg:phone":"+61 3 9459 9659",
    "sg:postcode":"3084",
    "sg:province":"VIC",
    "sg:tags":[
        "therapy"
    ],
    "wof:name":"House Of Seasons Hair And Beauty Centre",
    "wof:placetype":"venue"
},
  "geometry": {"coordinates":[145.07681274399999,-37.7461700439],"type":"Point"}
}