{
  "type": "Feature",
  "properties": {
    "addr:full":"Level 5 495 Boundary St Brisbane QLD 4000",
    "addr:housenumber":"495",
    "addr:postcode":"4000",
    "addr:street":"Boundary St",
    "iso:country":"AU",
    "sg:address":"Level 5 495 Boundary St",
    "sg:city":"Brisbane",
    "sg:classifiers":[
        {
            "category":"Education",
            "subcategory":"Special Training",
            "type":"Public Place"
        }
    ],
    "sg:phone":"+61 7 3236 0477",
    "sg:postcode":"4000",
    "sg:province":"QLD",
    "sg:tags":[
        "development"
    ],
    "wof:name":"Queensland Industry Training Council Inc",
    "wof:placetype":"venue"
},
  "geometry": {"coordinates":[153.02285766599999,-27.4604606628],"type":"Point"}
}