{
  "type": "Feature",
  "properties": {
    "addr:full":"U 3/ 93 Prinsep Rd Jandakot WA 6164",
    "addr:postcode":"6164",
    "addr:street":"93 Prinsep Rd",
    "iso:country":"AU",
    "sg:address":"U 3/ 93 Prinsep Rd",
    "sg:city":"Jandakot",
    "sg:classifiers":[
        {
            "category":"Professional",
            "subcategory":"Computer Services",
            "type":"Services"
        }
    ],
    "sg:phone":"+61 8 9417 8553",
    "sg:postcode":"6164",
    "sg:province":"WA",
    "sg:tags":[
        "technical",
        "support"
    ],
    "wof:name":"CSP Computing",
    "wof:placetype":"venue"
},
  "geometry": {"coordinates":[115.8591,-32.108738],"type":"Point"}
}