{
  "type": "Feature",
  "properties": {
    "addr:full":"66 Hill St Port Macquarie NSW 2444",
    "addr:housenumber":"66",
    "addr:postcode":"2444",
    "addr:street":"Hill St",
    "iso:country":"AU",
    "sg:address":"66 Hill St",
    "sg:city":"Port Macquarie",
    "sg:classifiers":[
        {
            "category":"Home & Garden",
            "subcategory":"Building Materials",
            "type":"Retail Goods"
        }
    ],
    "sg:phone":"+61 2 6584 2895",
    "sg:postcode":"2444",
    "sg:province":"NSW",
    "sg:tags":[
        "anti-corrosive",
        "composition",
        "flooring"
    ],
    "wof:name":"Riley Industries",
    "wof:placetype":"venue"
},
  "geometry": {"coordinates":[152.913635,-31.439096],"type":"Point"}
}