{
  "type": "Feature",
  "properties": {
    "addr:full":"1 Florence St Woodville SA 5011",
    "addr:housenumber":"1",
    "addr:postcode":"5011",
    "addr:street":"Florence St",
    "iso:country":"AU",
    "sg:address":"1 Florence St",
    "sg:city":"Woodville",
    "sg:classifiers":[
        {
            "category":"Building & Trades",
            "subcategory":"Construction",
            "type":"Services"
        }
    ],
    "sg:phone":"+61 8 8244 2090",
    "sg:postcode":"5011",
    "sg:province":"SA",
    "sg:tags":[
        "roof"
    ],
    "wof:name":"Jason Jarvis",
    "wof:placetype":"venue"
},
  "geometry": {"coordinates":[138.54432678200001,-34.8751335144],"type":"Point"}
}