{
  "type": "Feature",
  "properties": {
    "addr:full":"590 North East Rd Holden Hill SA 5088",
    "addr:housenumber":"590",
    "addr:postcode":"5088",
    "addr:street":"North East Rd",
    "iso:country":"AU",
    "sg:address":"590 North East Rd",
    "sg:city":"Holden Hill",
    "sg:classifiers":[
        {
            "category":"Shopping",
            "subcategory":"Mobile Phones",
            "type":"Retail Goods"
        }
    ],
    "sg:phone":"+61 8 8369 1985",
    "sg:postcode":"5088",
    "sg:province":"SA",
    "sg:tags":[
        "telephone",
        "accessory"
    ],
    "wof:name":"Fone Zone",
    "wof:placetype":"venue"
},
  "geometry": {"coordinates":[138.6615448,-34.8547286987],"type":"Point"}
}