{
  "type": "Feature",
  "properties": {
    "iso:country":"AU",
    "sg:address":"22 Georges La",
    "sg:city":"Taree",
    "sg:classifiers":[
        {
            "category":"Building & Trades",
            "subcategory":"Pest Control",
            "type":"Services"
        }
    ],
    "sg:phone":"+61 2 6551 0010",
    "sg:postcode":"2430",
    "sg:province":"NSW",
    "wof:name":"Bill Colquhoun",
    "wof:placetype":"venue"
},
  "geometry": {"coordinates":[152.454407,-31.907621],"type":"Point"}
}