{
  "type": "Feature",
  "properties": {
    "addr:full":"12 Carmen Drv Carlingford NSW 2118",
    "addr:housenumber":"12",
    "addr:postcode":"2118",
    "addr:street":"Carmen Drv",
    "iso:country":"AU",
    "sg:address":"12 Carmen Drv",
    "sg:city":"Carlingford",
    "sg:classifiers":[
        {
            "category":"Food & Beverages",
            "subcategory":"Supermarket",
            "type":"Retail Goods"
        }
    ],
    "sg:phone":"+61 2 9871 1349",
    "sg:postcode":"2118",
    "sg:province":"NSW",
    "sg:tags":[
        "grocery",
        "store"
    ],
    "wof:name":"Carmen Drive Food Store",
    "wof:placetype":"venue"
},
  "geometry": {"coordinates":[151.04098510700001,-33.7609634399],"type":"Point"}
}