{
  "type": "Feature",
  "properties": {
    "addr:full":"51 Rockley Rd South Yarra VIC 3141",
    "addr:housenumber":"51",
    "addr:postcode":"3141",
    "addr:street":"Rockley Rd",
    "iso:country":"AU",
    "sg:address":"51 Rockley Rd",
    "sg:city":"South Yarra",
    "sg:classifiers":[
        {
            "category":"Real Estate",
            "subcategory":"Architect",
            "type":"Services"
        }
    ],
    "sg:phone":"+61 3 9827 4899",
    "sg:postcode":"3141",
    "sg:province":"VIC",
    "wof:name":"John Chandler Architect Pty Ltd",
    "wof:placetype":"venue"
},
  "geometry": {"coordinates":[145.00021362300001,-37.8351097107],"type":"Point"}
}