{
  "type": "Feature",
  "properties": {
    "addr:full":"369 Burnley St Richmond VIC 3121",
    "addr:housenumber":"369",
    "addr:postcode":"3121",
    "addr:street":"Burnley St",
    "iso:country":"AU",
    "sg:address":"369 Burnley St",
    "sg:city":"Richmond",
    "sg:classifiers":[
        {
            "category":"Personal",
            "subcategory":"Beauty Salon",
            "type":"Services"
        }
    ],
    "sg:phone":"+61 3 9421 3929",
    "sg:postcode":"3121",
    "sg:province":"VIC",
    "sg:tags":[
        "hairdresser"
    ],
    "wof:name":"Ferae Naturae Hair",
    "wof:placetype":"venue"
},
  "geometry": {"coordinates":[145.007324219,-37.8257904053],"type":"Point"}
}