{
  "type": "Feature",
  "properties": {
    "addr:full":"3 Creswell St Revesby NSW 2212",
    "addr:housenumber":"3",
    "addr:postcode":"2212",
    "addr:street":"Creswell St",
    "iso:country":"AU",
    "sg:address":"3 Creswell St",
    "sg:city":"Revesby",
    "sg:classifiers":[
        {
            "category":"Building & Trades",
            "subcategory":"Construction",
            "type":"Services"
        }
    ],
    "sg:phone":"+61 2 9380 4785",
    "sg:postcode":"2212",
    "sg:province":"NSW",
    "sg:tags":[
        "polishing",
        "sanding",
        "floor"
    ],
    "wof:name":"&#034;Return To Sander&#034; Pty Ltd",
    "wof:placetype":"venue"
},
  "geometry": {"coordinates":[151.00874300000001,-33.948143],"type":"Point"}
}