{
  "type": "Feature",
  "properties": {
    "addr:full":"Ground Floor, 87 York St South Melbourne VIC 3205",
    "addr:housenumber":"87",
    "addr:postcode":"3205",
    "addr:street":"York St",
    "iso:country":"AU",
    "sg:address":"Ground Floor, 87 York St",
    "sg:city":"South Melbourne",
    "sg:classifiers":[
        {
            "category":"Banks & Credit Unions",
            "subcategory":"Financial Services",
            "type":"Services"
        }
    ],
    "sg:phone":"+61 3 9682 2566",
    "sg:postcode":"3205",
    "sg:province":"VIC",
    "sg:tags":[
        "planning"
    ],
    "wof:name":"Chris Eade",
    "wof:placetype":"venue"
},
  "geometry": {"coordinates":[144.95976300000001,-37.830849],"type":"Point"}
}