{
  "type": "Feature",
  "properties": {
    "addr:full":"165- 175 Mitchell Rd Alexandria NSW 2015",
    "addr:housenumber":"165 175",
    "addr:postcode":"2015",
    "addr:street":"Mitchell Rd",
    "iso:country":"AU",
    "sg:address":"165- 175 Mitchell Rd",
    "sg:city":"Alexandria",
    "sg:classifiers":[
        {
            "category":"Government",
            "subcategory":"Post Office",
            "type":"Public Place"
        }
    ],
    "sg:phone":"+61 2 8594 7000",
    "sg:postcode":"2015",
    "sg:province":"NSW",
    "sg:tags":[
        "postal"
    ],
    "wof:name":"Gallagher Infomanagement Group",
    "wof:placetype":"venue"
},
  "geometry": {"coordinates":[151.18771362300001,-33.9066467285],"type":"Point"}
}