{
  "type": "Feature",
  "properties": {
    "iso:country":"AU",
    "sg:address":"3 Miller St",
    "sg:city":"Urangan",
    "sg:classifiers":[
        {
            "category":"Social Services",
            "subcategory":"Adult Care",
            "type":"Services"
        }
    ],
    "sg:phone":"+61 7 4128 4145",
    "sg:postcode":"4655",
    "sg:province":"QLD",
    "sg:tags":[
        "towing"
    ],
    "wof:name":"Fraser Coast Towing & Auto Salvage",
    "wof:placetype":"venue"
},
  "geometry": {"coordinates":[152.896942,-25.288872],"type":"Point"}
}