{
  "type": "Feature",
  "properties": {
    "iso:country":"AU",
    "sg:address":"4/ 62 Keane St",
    "sg:city":"Currajong",
    "sg:classifiers":[
        {
            "category":"Home & Garden",
            "subcategory":"Hardware",
            "type":"Retail Goods"
        }
    ],
    "sg:phone":"+61 7 4724 1234",
    "sg:postcode":"4812",
    "sg:province":"QLD",
    "sg:tags":[
        "battery",
        "dry",
        "rechargeable",
        "cell"
    ],
    "wof:name":"Dura Sales",
    "wof:placetype":"venue"
},
  "geometry": {"coordinates":[146.775543,-19.271448],"type":"Point"}
}