{
  "type": "Feature",
  "properties": {
    "iso:country":"AU",
    "sg:address":"760 Anzac Hwy",
    "sg:city":"Glenelg",
    "sg:classifiers":[
        {
            "category":"Travel",
            "subcategory":"Hotels & Motels",
            "type":"Entertainment"
        }
    ],
    "sg:phone":"+61 8 8294 1011",
    "sg:postcode":"5045",
    "sg:province":"SA",
    "wof:name":"Atlantic Tower Motor Inn",
    "wof:placetype":"venue"
},
  "geometry": {"coordinates":[138.513733,-34.976826],"type":"Point"}
}