{
  "type": "Feature",
  "properties": {
    "addr:full":"Murray St Gawler SA 5118",
    "addr:postcode":"5118",
    "addr:street":"Murray St",
    "iso:country":"AU",
    "sg:address":"Murray St",
    "sg:city":"Gawler",
    "sg:classifiers":[
        {
            "category":"Government",
            "subcategory":"Court House",
            "type":"Public Place"
        }
    ],
    "sg:phone":"+61 8 8524 6133",
    "sg:postcode":"5118",
    "sg:province":"SA",
    "sg:tags":[
        "personal",
        "marriage",
        "family",
        "counselling"
    ],
    "wof:name":"Broadbent L",
    "wof:placetype":"venue"
},
  "geometry": {"coordinates":[138.74902299999999,-34.595798],"type":"Point"}
}