{
  "type": "Feature",
  "properties": {
    "iso:country":"AU",
    "sg:address":"25 Cook Drv",
    "sg:city":"Coffs Harbour",
    "sg:classifiers":[
        {
            "category":"Autos & Motor Vehicles",
            "subcategory":"Automobile Sales",
            "type":"Retail Goods"
        }
    ],
    "sg:phone":"+61 2 6651 4219",
    "sg:postcode":"2450",
    "sg:province":"NSW",
    "sg:tags":[
        "equipment",
        "trailer"
    ],
    "wof:name":"Coastal Camper Trailers",
    "wof:placetype":"venue"
},
  "geometry": {"coordinates":[153.09993,-30.315903],"type":"Point"}
}