{
  "type": "Feature",
  "properties": {
    "addr:full":"Hurricane Drv Raby NSW 2566",
    "addr:postcode":"2566",
    "addr:street":"Hurricane Drv",
    "iso:country":"AU",
    "sg:address":"Hurricane Drv",
    "sg:city":"Raby",
    "sg:classifiers":[
        {
            "category":"Fast Food",
            "type":"Food & Drink"
        }
    ],
    "sg:phone":"+61 2 9824 8297",
    "sg:postcode":"2566",
    "sg:province":"NSW",
    "sg:tags":[
        "away",
        "take"
    ],
    "wof:name":"Chinese Takeaway The",
    "wof:placetype":"venue"
},
  "geometry": {"coordinates":[150.8203125,-34.0254211426],"type":"Point"}
}