{
  "type": "Feature",
  "properties": {
    "addr:full":"59a Osborne Ave Springvale VIC 3171",
    "addr:housenumber":"59a",
    "addr:postcode":"3171",
    "addr:street":"Osborne Ave",
    "iso:country":"AU",
    "sg:address":"59a Osborne Ave",
    "sg:city":"Springvale",
    "sg:classifiers":[
        {
            "category":"Home & Garden",
            "subcategory":"Building Materials",
            "type":"Retail Goods"
        }
    ],
    "sg:phone":"+61 3 9574 0856",
    "sg:postcode":"3171",
    "sg:province":"VIC",
    "sg:tags":[
        "wall",
        "frame",
        "truss",
        "roof"
    ],
    "wof:name":"Kure Roof Truss & Frames",
    "wof:placetype":"venue"
},
  "geometry": {"coordinates":[145.14219665499999,-37.9460296631],"type":"Point"}
}