{
  "type": "Feature",
  "properties": {
    "addr:full":"247 Canning Hwy Como WA 6152",
    "addr:housenumber":"247",
    "addr:postcode":"6152",
    "addr:street":"Canning Hwy",
    "iso:country":"AU",
    "sg:address":"247 Canning Hwy",
    "sg:city":"Como",
    "sg:classifiers":[
        {
            "category":"Health Services",
            "subcategory":"Health Practitioner",
            "type":"Services"
        }
    ],
    "sg:phone":"+61 8 9474 1711",
    "sg:postcode":"6152",
    "sg:province":"WA",
    "sg:tags":[
        "psychologist"
    ],
    "wof:name":"Psychological Consultancy Services of Como",
    "wof:placetype":"venue"
},
  "geometry": {"coordinates":[115.870598,-31.988749],"type":"Point"}
}