{
  "type": "Feature",
  "properties": {
    "iso:country":"AU",
    "sg:address":"85 Tiers Rd",
    "sg:city":"Snug",
    "sg:classifiers":[
        {
            "category":"Professional",
            "type":"Services"
        }
    ],
    "sg:phone":"+61 418 535 988",
    "sg:postcode":"7054",
    "sg:province":"TAS",
    "sg:tags":[
        "transport"
    ],
    "wof:name":"Kemp Contract Cartage",
    "wof:placetype":"venue"
},
  "geometry": {"coordinates":[147.255447,-43.066799],"type":"Point"}
}