{
  "type": "Feature",
  "properties": {
    "addr:full":"Rocklands Drv Casuarina NT 0810",
    "addr:postcode":"nt 0810",
    "addr:street":"Rocklands Drv",
    "iso:country":"AU",
    "sg:address":"Rocklands Drv",
    "sg:city":"Casuarina",
    "sg:classifiers":[
        {
            "category":"Health Services",
            "subcategory":"Doctor",
            "type":"Services"
        }
    ],
    "sg:phone":"+61 8 8920 6183",
    "sg:postcode":"0810",
    "sg:province":"NT",
    "sg:tags":[
        "medical",
        "practitioner"
    ],
    "wof:name":"S. Selva-nayagam",
    "wof:placetype":"venue"
},
  "geometry": {"coordinates":[130.88432312,-12.3591680527],"type":"Point"}
}