{
  "type": "Feature",
  "properties": {
    "iso:country":"AU",
    "sg:address":"8 David Lee Rd",
    "sg:city":"Hallam",
    "sg:classifiers":[
        {
            "category":"Retail",
            "subcategory":"Auto Repair",
            "type":"Services"
        }
    ],
    "sg:phone":"+61 3 9702 3030",
    "sg:postcode":"3803",
    "sg:province":"VIC",
    "sg:tags":[
        "muffler",
        "exhaust",
        "system"
    ],
    "wof:name":"Hallam Performance Exhaust",
    "wof:placetype":"venue"
},
  "geometry": {"coordinates":[145.26669311500001,-38.0134468079],"type":"Point"}
}