{
  "type": "Feature",
  "properties": {
    "iso:country":"AU",
    "sg:address":"172 Barrington St",
    "sg:city":"Spearwood",
    "sg:classifiers":[
        {
            "category":"Retail",
            "subcategory":"Auto Repair",
            "type":"Services"
        }
    ],
    "sg:phone":"+61 8 9418 1514",
    "sg:postcode":"6163",
    "sg:province":"WA",
    "sg:tags":[
        "repairer",
        "motor",
        "engineer"
    ],
    "wof:name":"Dennis Wood Auto Repairs",
    "wof:placetype":"venue"
},
  "geometry": {"coordinates":[115.788689,-32.116508],"type":"Point"}
}