{
  "type": "Feature",
  "properties": {
    "iso:country":"AU",
    "sg:address":"399 Shoreline Drv",
    "sg:city":"Port Macquarie",
    "sg:classifiers":[
        {
            "category":"Professional",
            "subcategory":"Engineering",
            "type":"Services"
        }
    ],
    "sg:phone":"+61 2 6583 6675",
    "sg:postcode":"2444",
    "sg:province":"NSW",
    "sg:tags":[
        "engineer"
    ],
    "wof:name":"Jeffrey J Jenkins",
    "wof:placetype":"venue"
},
  "geometry": {"coordinates":[152.87098700000001,-31.411076],"type":"Point"}
}