{
  "type": "Feature",
  "properties": {
    "addr:full":"34- 48 Stanley Drv Somerton VIC 3062",
    "addr:housenumber":"48",
    "addr:postcode":"3062",
    "addr:street":"Stanley Drv",
    "iso:country":"AU",
    "sg:address":"34- 48 Stanley Drv",
    "sg:city":"Somerton",
    "sg:classifiers":[
        {
            "category":"Autos & Motor Vehicles",
            "subcategory":"Auto Supplies",
            "type":"Retail Goods"
        }
    ],
    "sg:phone":"+61 1300 366 024",
    "sg:postcode":"3062",
    "sg:province":"VIC",
    "sg:tags":[
        "camper-trailers",
        "caravan",
        "equipment"
    ],
    "wof:name":"Northern City Electrical",
    "wof:placetype":"venue"
},
  "geometry": {"coordinates":[144.942306519,-37.6277046204],"type":"Point"}
}