{
  "type": "Feature",
  "properties": {
    "addr:full":"377 Oxford St Mt Hawthorn WA 6016",
    "addr:housenumber":"377",
    "addr:postcode":"6016",
    "addr:street":"Oxford St Mt",
    "iso:country":"AU",
    "sg:address":"377 Oxford St",
    "sg:city":"Mt Hawthorn",
    "sg:classifiers":[
        {
            "category":"Shopping",
            "subcategory":"Clothing, Apparel, & Fashions",
            "type":"Retail Goods"
        }
    ],
    "sg:phone":"+61 8 9443 8885",
    "sg:postcode":"6016",
    "sg:province":"WA",
    "sg:tags":[
        "boutique"
    ],
    "wof:name":"Mandolin Boutique & Gifts",
    "wof:placetype":"venue"
},
  "geometry": {"coordinates":[115.841072083,-31.9248256683],"type":"Point"}
}