{
  "type": "Feature",
  "properties": {
    "iso:country":"AU",
    "sg:address":"1- 3 Woodman Crt",
    "sg:city":"Hyde Park",
    "sg:classifiers":[
        {
            "category":"Shopping",
            "subcategory":"Computers & Home Electronics",
            "type":"Retail Goods"
        }
    ],
    "sg:phone":"+61 7 4724 1524",
    "sg:postcode":"4812",
    "sg:province":"QLD",
    "sg:tags":[
        "small",
        "equipment",
        "business"
    ],
    "wof:name":"Leading Edge Computers",
    "wof:placetype":"venue"
},
  "geometry": {"coordinates":[146.792267,-19.269716],"type":"Point"}
}