{
  "type": "Feature",
  "properties": {
    "addr:full":"1- 3 Woodman Crt Hyde Park QLD 4812",
    "addr:housenumber":"3",
    "addr:postcode":"4812",
    "addr:street":"Woodman Crt",
    "iso:country":"AU",
    "sg:address":"1- 3 Woodman Crt",
    "sg:city":"Hyde Park",
    "sg:classifiers":[
        {
            "category":"Shopping",
            "subcategory":"Computers & Home Electronics",
            "type":"Retail Goods"
        }
    ],
    "sg:phone":"+61 7 4724 1524",
    "sg:postcode":"4812",
    "sg:province":"QLD",
    "sg:tags":[
        "small",
        "equipment",
        "business"
    ],
    "wof:name":"Leading Edge Computers",
    "wof:placetype":"venue"
},
  "geometry": {"coordinates":[146.79226700000001,-19.269716],"type":"Point"}
}