{
  "type": "Feature",
  "properties": {
    "iso:country":"AU",
    "sg:address":"10/ 210 Queensport Rd North",
    "sg:city":"Murarrie",
    "sg:classifiers":[
        {
            "category":"Home & Garden",
            "subcategory":"Furniture",
            "type":"Retail Goods"
        }
    ],
    "sg:phone":"+61 1300 138 426",
    "sg:postcode":"4172",
    "sg:province":"QLD",
    "sg:tags":[
        "outdoor"
    ],
    "sg:website":"http://www.aussiebbqs.com.au",
    "wof:name":"Aussie BBQs",
    "wof:placetype":"venue"
},
  "geometry": {"coordinates":[153.10673523,-27.4529438019],"type":"Point"}
}