{
  "type": "Feature",
  "properties": {
    "addr:full":"Shop 4 Pembee Crt Pemberton WA 6260",
    "addr:housenumber":"shop 4",
    "addr:postcode":"6260",
    "addr:street":"Pembee Crt",
    "iso:country":"AU",
    "sg:address":"Shop 4 Pembee Crt",
    "sg:city":"Pemberton",
    "sg:classifiers":[
        {
            "category":"Food & Beverages",
            "subcategory":"Bakery",
            "type":"Retail Goods"
        }
    ],
    "sg:phone":"+61 8 9776 1577",
    "sg:postcode":"6260",
    "sg:province":"WA",
    "sg:tags":[
        "baker"
    ],
    "wof:name":"Pemberton Bakehouse",
    "wof:placetype":"venue"
},
  "geometry": {"coordinates":[116.034538269,-34.4448318481],"type":"Point"}
}