{
  "type": "Feature",
  "properties": {
    "addr:full":"54 Sandy Bay Rd Battery Point TAS 7004",
    "addr:housenumber":"54",
    "addr:postcode":"7004",
    "addr:street":"Sandy Bay Rd",
    "iso:country":"AU",
    "sg:address":"54 Sandy Bay Rd",
    "sg:city":"Battery Point",
    "sg:classifiers":[
        {
            "category":"Real Estate",
            "subcategory":"Real Estate Agent",
            "type":"Services"
        }
    ],
    "sg:phone":"+61 3 6224 1353",
    "sg:postcode":"7004",
    "sg:province":"TAS",
    "wof:name":"Peterswalds Partners",
    "wof:placetype":"venue"
},
  "geometry": {"coordinates":[147.329055786,-42.890537262],"type":"Point"}
}