{
  "type": "Feature",
  "properties": {
    "addr:full":"Suite 6/ 764 Sandgate Rd Clayfield QLD 4011",
    "addr:housenumber":"/ 764",
    "addr:postcode":"4011",
    "addr:street":"Sandgate Rd",
    "iso:country":"AU",
    "sg:address":"Suite 6/ 764 Sandgate Rd",
    "sg:city":"Clayfield",
    "sg:classifiers":[
        {
            "category":"Professional",
            "type":"Services"
        }
    ],
    "sg:phone":"+61 1300 656 595",
    "sg:postcode":"4011",
    "sg:province":"QLD",
    "sg:tags":[
        "mail",
        "contractor"
    ],
    "wof:name":"Mail Plus Australia Pty Ltd",
    "wof:placetype":"venue"
},
  "geometry": {"coordinates":[153.05688499999999,-27.417261],"type":"Point"}
}