{
  "type": "Feature",
  "properties": {
    "iso:country":"AU",
    "sg:address":"19 Edgar St",
    "sg:city":"Ainslie",
    "sg:classifiers":[
        {
            "category":"Health Services",
            "subcategory":"Medical Lab",
            "type":"Services"
        }
    ],
    "sg:phone":"+61 2 6249 1940",
    "sg:postcode":"2602",
    "sg:province":"ACT",
    "sg:tags":[
        "laboratory",
        "pathology"
    ],
    "wof:name":"Capital Pathology",
    "wof:placetype":"venue"
},
  "geometry": {"coordinates":[149.14576721200001,-35.2617340088],"type":"Point"}
}