{
  "type": "Feature",
  "properties": {
    "iso:country":"AU",
    "sg:address":"49 Muldoon St",
    "sg:city":"Taree",
    "sg:classifiers":[
        {
            "category":"Utilities",
            "subcategory":"Recycling",
            "type":"Services"
        }
    ],
    "sg:phone":"+61 2 6552 2840",
    "sg:postcode":"2430",
    "sg:province":"NSW",
    "wof:name":"Smorgon Steel Recycling",
    "wof:placetype":"venue"
},
  "geometry": {"coordinates":[152.458862,-31.898806],"type":"Point"}
}