{
  "type": "Feature",
  "properties": {
    "addr:full":"20 Eldorado Crs Coolaroo VIC 3048",
    "addr:housenumber":"20",
    "addr:postcode":"3048",
    "addr:street":"Eldorado Crs",
    "iso:country":"AU",
    "sg:address":"20 Eldorado Crs",
    "sg:city":"Coolaroo",
    "sg:classifiers":[
        {
            "category":"Health Services",
            "subcategory":"Dentist",
            "type":"Services"
        }
    ],
    "sg:phone":"+61 3 9309 9332",
    "sg:postcode":"3048",
    "sg:province":"VIC",
    "wof:name":"Yuen C & F Drs",
    "wof:placetype":"venue"
},
  "geometry": {"coordinates":[144.912476,-37.724133],"type":"Point"}
}