{
  "type": "Feature",
  "properties": {
    "iso:country":"AU",
    "sg:address":"35 North Rd",
    "sg:city":"Lilydale",
    "sg:classifiers":[
        {
            "category":"Home & Garden",
            "subcategory":"Building Materials",
            "type":"Retail Goods"
        }
    ],
    "sg:phone":"+61 3 9739 6022",
    "sg:postcode":"3140",
    "sg:province":"VIC",
    "sg:tags":[
        "supply"
    ],
    "wof:name":"Ceder Imports Pty Ltd",
    "wof:placetype":"venue"
},
  "geometry": {"coordinates":[145.36756897000001,-37.7565307617],"type":"Point"}
}