{
  "type": "Feature",
  "properties": {
    "addr:full":"2/ 7 Woodbine Crt Wantirna South VIC 3152",
    "addr:housenumber":"/ 7",
    "addr:postcode":"3152",
    "addr:street":"Woodbine Crt",
    "iso:country":"AU",
    "sg:address":"2/ 7 Woodbine Crt",
    "sg:city":"Wantirna South",
    "sg:classifiers":[
        {
            "category":"Manufacturing",
            "subcategory":"Tools & Machinery",
            "type":"Manufacturing & Wholesale Goods"
        }
    ],
    "sg:phone":"+61 3 9801 5961",
    "sg:postcode":"3152",
    "sg:province":"VIC",
    "sg:tags":[
        "earth",
        "excavating",
        "moving",
        "equipment"
    ],
    "wof:name":"Keech Castings Australia Pty Ltd",
    "wof:placetype":"venue"
},
  "geometry": {"coordinates":[145.25097656200001,-37.8703460693],"type":"Point"}
}