{
  "type": "Feature",
  "properties": {
    "addr:full":"92 Pacific Hwy Tuggerah NSW 2259",
    "addr:housenumber":"92",
    "addr:postcode":"2259",
    "addr:street":"Pacific Hwy",
    "iso:country":"AU",
    "sg:address":"92 Pacific Hwy",
    "sg:city":"Tuggerah",
    "sg:classifiers":[
        {
            "category":"Building & Trades",
            "subcategory":"Landscaping Services",
            "type":"Services"
        }
    ],
    "sg:phone":"+61 2 4351 1799",
    "sg:postcode":"2259",
    "sg:province":"NSW",
    "sg:tags":[
        "control",
        "weed"
    ],
    "wof:name":"C & B Bugbuster Pest Control",
    "wof:placetype":"venue"
},
  "geometry": {"coordinates":[151.419921875,-33.306427002],"type":"Point"}
}