{
  "type": "Feature",
  "properties": {
    "addr:full":"Lot 1 Callenondah Drv Gladstone QLD 4680",
    "addr:postcode":"4680",
    "addr:street":"Callenondah Drv",
    "iso:country":"AU",
    "sg:address":"Lot 1 Callenondah Drv",
    "sg:city":"Gladstone",
    "sg:classifiers":[
        {
            "category":"Manufacturing",
            "subcategory":"Tools & Machinery",
            "type":"Manufacturing & Wholesale Goods"
        }
    ],
    "sg:phone":"+61 7 4978 2333",
    "sg:postcode":"4680",
    "sg:province":"QLD",
    "sg:tags":[
        "earth",
        "excavating",
        "moving",
        "equipment"
    ],
    "wof:name":"Alistair Pegg",
    "wof:placetype":"venue"
},
  "geometry": {"coordinates":[151.25355529800001,-23.8438205719],"type":"Point"}
}