{
  "type": "Feature",
  "properties": {
    "iso:country":"AU",
    "sg:address":"Suite 6 A Lot 1450 Winnellie Rd",
    "sg:city":"Winnellie",
    "sg:classifiers":[
        {
            "category":"Building & Trades",
            "subcategory":"Construction",
            "type":"Services"
        }
    ],
    "sg:phone":"+61 8 8984 4003",
    "sg:postcode":"0820",
    "sg:province":"NT",
    "sg:tags":[
        "contractor"
    ],
    "wof:name":"Contractor Accreditation Ltd",
    "wof:placetype":"venue"
},
  "geometry": {"coordinates":[130.89242553700001,-12.4266233444],"type":"Point"}
}