{
  "type": "Feature",
  "properties": {
    "iso:country":"AU",
    "sg:address":"Lot1/ Enterprise Drv",
    "sg:city":"Berkeley Vale",
    "sg:classifiers":[
        {
            "category":"Fast Food",
            "type":"Food & Drink"
        }
    ],
    "sg:phone":"+61 2 4388 6776",
    "sg:postcode":"2261",
    "sg:province":"NSW",
    "sg:tags":[
        "away",
        "take"
    ],
    "wof:name":"Bimbos Takeaway",
    "wof:placetype":"venue"
},
  "geometry": {"coordinates":[151.438583,-33.344639],"type":"Point"}
}