{
  "type": "Feature",
  "properties": {
    "addr:full":"Woodlake Vlge Shopng Cntr, 20 Sunray Crcle Ellenbrook WA 6069",
    "addr:housenumber":"20",
    "addr:postcode":"6069",
    "addr:street":"Sunray Crcle",
    "iso:country":"AU",
    "sg:address":"Woodlake Vlge Shopng Cntr, 20",
    "sg:city":"Sunray Crcle Ellenbrook",
    "sg:classifiers":[
        {
            "category":"Food & Beverages",
            "subcategory":"Supermarket",
            "type":"Retail Goods"
        }
    ],
    "sg:phone":"+61 8 9296 8902",
    "sg:postcode":"6069",
    "sg:province":"WA",
    "sg:tags":[
        "grocery",
        "store"
    ],
    "wof:name":"Dewsons Supermarkets",
    "wof:placetype":"venue"
},
  "geometry": {"coordinates":[115.97013855,-31.7888202667],"type":"Point"}
}