{
  "type": "Feature",
  "properties": {
    "addr:full":"Shop 9A Helensvale Plaza Sir John Overall Drv Helensvale QLD 4212",
    "addr:housenumber":"shop 9a",
    "addr:postcode":"4212",
    "addr:street":"Sir John Overall Drv",
    "iso:country":"AU",
    "sg:address":"Shop 9A Helensvale Plaza Sir John Overall Drv",
    "sg:city":"Helensvale",
    "sg:classifiers":[
        {
            "category":"Shopping",
            "subcategory":"Bicycles & Sporting Goods",
            "type":"Retail Goods"
        }
    ],
    "sg:phone":"+61 7 5573 7677",
    "sg:postcode":"4212",
    "sg:province":"QLD",
    "sg:tags":[
        "chemical",
        "equipment",
        "pool",
        "swimming"
    ],
    "wof:name":"Northern Pool & Spa",
    "wof:placetype":"venue"
},
  "geometry": {"coordinates":[153.33572387699999,-27.9226989746],"type":"Point"}
}