{
  "type": "Feature",
  "properties": {
    "addr:full":"6/ 15 Port Kembla Drv Bibra Lake WA 6163",
    "addr:housenumber":"/ 15",
    "addr:postcode":"6163",
    "addr:street":"Port Kembla Drv",
    "iso:country":"AU",
    "sg:address":"6/ 15 Port Kembla Drv",
    "sg:city":"Bibra Lake",
    "sg:classifiers":[
        {
            "category":"Retail",
            "subcategory":"Auto Repair",
            "type":"Services"
        }
    ],
    "sg:phone":"+61 8 9434 2511",
    "sg:postcode":"6163",
    "sg:province":"WA",
    "sg:tags":[
        "repairer",
        "motor",
        "engineer"
    ],
    "wof:name":"Repco Authorised Service",
    "wof:placetype":"venue"
},
  "geometry": {"coordinates":[115.801033,-32.096443],"type":"Point"}
}