{
  "type": "Feature",
  "properties": {
    "iso:country":"AU",
    "sg:address":"8 Wiggs Rd",
    "sg:city":"Riverwood",
    "sg:classifiers":[
        {
            "category":"Building & Trades",
            "subcategory":"Construction",
            "type":"Services"
        }
    ],
    "sg:phone":"+61 414 863 735",
    "sg:postcode":"2210",
    "sg:province":"NSW",
    "sg:tags":[
        "installation",
        "air conditioning"
    ],
    "wof:name":"A.Ang Airconditioning Services",
    "wof:placetype":"venue"
},
  "geometry": {"coordinates":[151.051682,-33.938885],"type":"Point"}
}