{
  "type": "Feature",
  "properties": {
    "iso:country":"AU",
    "sg:address":"Shop 3/ 28 Shuter St",
    "sg:city":"Moonee Ponds",
    "sg:classifiers":[
        {
            "category":"Personal",
            "subcategory":"Beauty Salon",
            "type":"Services"
        }
    ],
    "sg:phone":"+61 3 9375 1500",
    "sg:postcode":"3039",
    "sg:province":"VIC",
    "wof:name":"Beauty Sensation Day Spa",
    "wof:placetype":"venue"
},
  "geometry": {"coordinates":[144.920959,-37.76704],"type":"Point"}
}