{
  "type": "Feature",
  "properties": {
    "addr:full":"21 Morrison St Hobart TAS 7000",
    "addr:housenumber":"21",
    "addr:postcode":"7000",
    "addr:street":"Morrison St",
    "iso:country":"AU",
    "sg:address":"21 Morrison St",
    "sg:city":"Hobart",
    "sg:classifiers":[
        {
            "category":"Structure",
            "subcategory":"Building",
            "type":"Public Place"
        }
    ],
    "sg:phone":"+61 3 6234 5422",
    "sg:postcode":"7000",
    "sg:province":"TAS",
    "sg:tags":[
        "sail",
        "shade"
    ],
    "wof:name":"Doyle-Fraser Sails",
    "wof:placetype":"venue"
},
  "geometry": {"coordinates":[147.33135986299999,-42.884475708],"type":"Point"}
}