{
  "type": "Feature",
  "properties": {
    "iso:country":"AU",
    "sg:address":"11 Beaconsfield St",
    "sg:city":"Bexley",
    "sg:classifiers":[
        {
            "category":"Building & Trades",
            "subcategory":"Construction",
            "type":"Services"
        }
    ],
    "sg:phone":"+61 2 9556 1936",
    "sg:postcode":"2207",
    "sg:province":"NSW",
    "sg:tags":[
        "contractor"
    ],
    "wof:name":"J C A Constructions Pty Ltd",
    "wof:placetype":"venue"
},
  "geometry": {"coordinates":[151.131363,-33.954102],"type":"Point"}
}