{
  "type": "Feature",
  "properties": {
    "addr:full":"Lvl 2/ 118 Queen St Melbourne VIC 3000",
    "addr:housenumber":"/ 118",
    "addr:postcode":"3000",
    "addr:street":"Queen St",
    "iso:country":"AU",
    "sg:address":"Lvl 2/ 118 Queen St",
    "sg:city":"Melbourne",
    "sg:classifiers":[
        {
            "category":"Professional",
            "subcategory":"Accounting & Tax Preparation",
            "type":"Services"
        }
    ],
    "sg:phone":"+61 3 9670 8438",
    "sg:postcode":"3000",
    "sg:province":"VIC",
    "sg:tags":[
        "bookkeeping"
    ],
    "wof:name":"Sagemore",
    "wof:placetype":"venue"
},
  "geometry": {"coordinates":[144.961227417,-37.8157234192],"type":"Point"}
}