{
  "type": "Feature",
  "properties": {
    "addr:full":"4 Belmore St Junee NSW 2663",
    "addr:housenumber":"4",
    "addr:postcode":"2663",
    "addr:street":"Belmore St",
    "iso:country":"AU",
    "sg:address":"4 Belmore St",
    "sg:city":"Junee",
    "sg:classifiers":[
        {
            "category":"Autos & Motor Vehicles",
            "subcategory":"Automobile Sales",
            "type":"Retail Goods"
        }
    ],
    "sg:phone":"+61 2 6924 1996",
    "sg:postcode":"2663",
    "sg:province":"NSW",
    "sg:tags":[
        "car",
        "new"
    ],
    "wof:name":"Moore Ford",
    "wof:placetype":"venue"
},
  "geometry": {"coordinates":[147.58473205600001,-34.8714752197],"type":"Point"}
}