{
  "type": "Feature",
  "properties": {
    "addr:full":"5 Crown St Henley NSW 2111",
    "addr:housenumber":"5",
    "addr:postcode":"2111",
    "addr:street":"Crown St",
    "iso:country":"AU",
    "sg:address":"5 Crown St",
    "sg:city":"Henley",
    "sg:classifiers":[
        {
            "category":"Shopping",
            "subcategory":"Bicycles & Sporting Goods",
            "type":"Retail Goods"
        }
    ],
    "sg:phone":"+61 2 9817 3145",
    "sg:postcode":"2111",
    "sg:province":"NSW",
    "sg:tags":[
        "chemical",
        "equipment",
        "pool",
        "swimming"
    ],
    "wof:name":"Xp Swimming Pools Pty Ltd",
    "wof:placetype":"venue"
},
  "geometry": {"coordinates":[151.13583374000001,-33.8420829773],"type":"Point"}
}