{
  "type": "Feature",
  "properties": {
    "addr:full":"62 Genista St San Remo VIC 3925",
    "addr:housenumber":"62",
    "addr:postcode":"3925",
    "addr:street":"Genista St",
    "iso:country":"AU",
    "sg:address":"62 Genista St",
    "sg:city":"San Remo",
    "sg:classifiers":[
        {
            "category":"Utilities",
            "subcategory":"Refuse",
            "type":"Services"
        }
    ],
    "sg:phone":"+61 3 5952 6662",
    "sg:postcode":"3925",
    "sg:province":"VIC",
    "sg:tags":[
        "remover",
        "rubbish"
    ],
    "wof:name":"Island Mowing",
    "wof:placetype":"venue"
},
  "geometry": {"coordinates":[145.37373352,-38.5214157104],"type":"Point"}
}