{
  "type": "Feature",
  "properties": {
    "iso:country":"AU",
    "sg:address":"Level 1, Suite 2/ 358 Main Rd W",
    "sg:city":"St Albans",
    "sg:classifiers":[
        {
            "category":"Professional",
            "subcategory":"Business Services",
            "type":"Services"
        }
    ],
    "sg:phone":"+61 3 9310 8800",
    "sg:postcode":"3021",
    "sg:province":"VIC",
    "sg:tags":[
        "drafting"
    ],
    "wof:name":"Express Building Design Group & Direction One",
    "wof:placetype":"venue"
},
  "geometry": {"coordinates":[144.76944,-37.740906],"type":"Point"}
}