{
  "type": "Feature",
  "properties": {
    "addr:full":"1 Coleman Rd Warranwood VIC 3134",
    "addr:housenumber":"1",
    "addr:postcode":"3134",
    "addr:street":"Coleman Rd",
    "iso:country":"AU",
    "sg:address":"1 Coleman Rd",
    "sg:city":"Warranwood",
    "sg:classifiers":[
        {
            "category":"Retail",
            "subcategory":"Veterinary Services",
            "type":"Services"
        }
    ],
    "sg:phone":"+61 3 9879 0900",
    "sg:postcode":"3134",
    "sg:province":"VIC",
    "sg:tags":[
        "surgeon"
    ],
    "wof:name":"Natural Therapies",
    "wof:placetype":"venue"
},
  "geometry": {"coordinates":[145.24720764200001,-37.8246612549],"type":"Point"}
}