{
  "type": "Feature",
  "properties": {
    "addr:full":"Ste 8/ 3 Bishop St Morley WA 6062",
    "addr:postcode":"6062",
    "addr:street":"Bishop St",
    "iso:country":"AU",
    "sg:address":"Ste 8/ 3 Bishop St",
    "sg:city":"Morley",
    "sg:classifiers":[
        {
            "category":"Shopping",
            "subcategory":"Jewelry",
            "type":"Retail Goods"
        }
    ],
    "sg:phone":"+61 8 9375 9833",
    "sg:postcode":"6062",
    "sg:province":"WA",
    "sg:tags":[
        "jeweller",
        "supply"
    ],
    "wof:name":"Michael Quy Jewellery",
    "wof:placetype":"venue"
},
  "geometry": {"coordinates":[115.89772796600001,-31.8959140778],"type":"Point"}
}