{
  "type": "Feature",
  "properties": {
    "addr:full":"8 Railway Pde Granville NSW 2142",
    "addr:housenumber":"8",
    "addr:postcode":"2142",
    "addr:street":"Railway Pde",
    "iso:country":"AU",
    "sg:address":"8 Railway Pde",
    "sg:city":"Granville",
    "sg:classifiers":[
        {
            "category":"Real Estate",
            "subcategory":"Real Estate Agent",
            "type":"Services"
        }
    ],
    "sg:phone":"+61 2 9637 6655",
    "sg:postcode":"2142",
    "sg:province":"NSW",
    "wof:name":"Bobb Partners Real Estate",
    "wof:placetype":"venue"
},
  "geometry": {"coordinates":[151.00962829599999,-33.8318405151],"type":"Point"}
}