{
  "type": "Feature",
  "properties": {
    "addr:full":"PO Box 355 Echunga SA 5153",
    "addr:postcode":"5153",
    "iso:country":"AU",
    "sg:address":"PO Box 355",
    "sg:city":"Echunga",
    "sg:classifiers":[
        {
            "category":"Home & Garden",
            "subcategory":"Kitchen Supply",
            "type":"Retail Goods"
        }
    ],
    "sg:phone":"+61 429 868 368",
    "sg:postcode":"5153",
    "sg:province":"SA",
    "sg:tags":[
        "traffic",
        "equipment",
        "safety",
        "road"
    ],
    "wof:name":"Safety Barrier Services",
    "wof:placetype":"venue"
},
  "geometry": {"coordinates":[138.793426514,-35.1000900269],"type":"Point"}
}