{
  "type": "Feature",
  "properties": {
    "addr:full":"15 Kanoona Ave Homebush NSW 2140",
    "addr:housenumber":"15",
    "addr:postcode":"2140",
    "addr:street":"Kanoona Ave",
    "iso:country":"AU",
    "sg:address":"15 Kanoona Ave",
    "sg:city":"Homebush",
    "sg:classifiers":[
        {
            "category":"Building & Trades",
            "subcategory":"Construction",
            "type":"Services"
        }
    ],
    "sg:phone":"+61 2 9632 3323",
    "sg:postcode":"2140",
    "sg:province":"NSW",
    "sg:tags":[
        "installation",
        "air conditioning"
    ],
    "wof:name":"Strathfield Sydney Wide Air Pty Ltd",
    "wof:placetype":"venue"
},
  "geometry": {"coordinates":[151.07754516599999,-33.8615455627],"type":"Point"}
}