{
  "type": "Feature",
  "properties": {
    "iso:country":"AU",
    "sg:address":"The Village Shopping Centre Suite 18 54 Bradshaw Tce",
    "sg:city":"Casuarina",
    "sg:classifiers":[
        {
            "category":"Health Services",
            "subcategory":"Dentist",
            "type":"Services"
        }
    ],
    "sg:phone":"+61 8 8945 1005",
    "sg:postcode":"0810",
    "sg:province":"NT",
    "wof:name":"Ong Ean",
    "wof:placetype":"venue"
},
  "geometry": {"coordinates":[130.846832275,-12.3787002563],"type":"Point"}
}