{
  "type": "Feature",
  "properties": {
    "addr:full":"Cnr Beach St & Dandenong Rd Frankston VIC 3199",
    "addr:postcode":"3199",
    "addr:street":"Cnr Beach St & Dandenong Rd",
    "iso:country":"AU",
    "sg:address":"Cnr Beach St & Dandenong Rd",
    "sg:city":"Frankston",
    "sg:classifiers":[
        {
            "category":"Retail",
            "subcategory":"Auto Repair",
            "type":"Services"
        }
    ],
    "sg:phone":"+61 3 9783 4799",
    "sg:postcode":"3199",
    "sg:province":"VIC",
    "sg:tags":[
        "clutch",
        "brake"
    ],
    "wof:name":"Brake Care",
    "wof:placetype":"venue"
},
  "geometry": {"coordinates":[145.126586914,-38.1413269043],"type":"Point"}
}