{
  "type": "Feature",
  "properties": {
    "addr:full":"80 Shannon Ave Geelong West VIC 3218",
    "addr:housenumber":"80",
    "addr:postcode":"3218",
    "addr:street":"Shannon Ave",
    "iso:country":"AU",
    "sg:address":"80 Shannon Ave",
    "sg:city":"Geelong West",
    "sg:classifiers":[
        {
            "category":"Fast Food",
            "type":"Food & Drink"
        }
    ],
    "sg:phone":"+61 3 5229 8877",
    "sg:postcode":"3218",
    "sg:province":"VIC",
    "sg:tags":[
        "away",
        "take"
    ],
    "wof:name":"Sammy's Seafood",
    "wof:placetype":"venue"
},
  "geometry": {"coordinates":[144.337646484,-38.134979248],"type":"Point"}
}