{
  "type": "Feature",
  "properties": {
    "addr:full":"72 Standish St Myrtleford VIC 3737",
    "addr:housenumber":"72",
    "addr:postcode":"3737",
    "addr:street":"Standish St",
    "iso:country":"AU",
    "sg:address":"72 Standish St",
    "sg:city":"Myrtleford",
    "sg:classifiers":[
        {
            "category":"Professional",
            "subcategory":"Business Services",
            "type":"Services"
        }
    ],
    "sg:phone":"+61 3 5752 2999",
    "sg:postcode":"3737",
    "sg:province":"VIC",
    "sg:tags":[
        "small",
        "advisory"
    ],
    "wof:name":"Stewart & Noble Lawyers",
    "wof:placetype":"venue"
},
  "geometry": {"coordinates":[146.724685669,-36.5602607727],"type":"Point"}
}