{
  "type": "Feature",
  "properties": {
    "addr:full":"276 Highett Rd Highett VIC 3190",
    "addr:housenumber":"276",
    "addr:postcode":"3190",
    "addr:street":"Highett Rd",
    "iso:country":"AU",
    "sg:address":"276 Highett Rd",
    "sg:city":"Highett",
    "sg:classifiers":[
        {
            "category":"Building & Trades",
            "subcategory":"Cleaning & Sanitation",
            "type":"Services"
        }
    ],
    "sg:phone":"+61 3 9532 3866",
    "sg:postcode":"3190",
    "sg:province":"VIC",
    "sg:tags":[
        "industrial",
        "commercial",
        "contractor"
    ],
    "wof:name":"Hygiclean Australia Pty Ltd",
    "wof:placetype":"venue"
},
  "geometry": {"coordinates":[145.040161133,-37.9486618042],"type":"Point"}
}