{
  "type": "Feature",
  "properties": {
    "addr:full":"Orana Rd Ocean Shores NSW 2483",
    "addr:postcode":"2483",
    "addr:street":"Orana Rd",
    "iso:country":"AU",
    "sg:address":"Orana Rd",
    "sg:city":"Ocean Shores",
    "sg:classifiers":[
        {
            "category":"Sports & Exercise",
            "subcategory":"Golf",
            "type":"Entertainment"
        }
    ],
    "sg:phone":"+61 2 6680 1008",
    "sg:postcode":"2483",
    "sg:province":"NSW",
    "sg:tags":[
        "club"
    ],
    "wof:name":"Ocean Shores Country Club",
    "wof:placetype":"venue"
},
  "geometry": {"coordinates":[153.53346252399999,-28.5170516968],"type":"Point"}
}