{
  "type": "Feature",
  "properties": {
    "iso:country":"AU",
    "sg:address":"Shp 11/ 53 Synnot St",
    "sg:city":"Werribee",
    "sg:classifiers":[
        {
            "category":"Restaurant",
            "type":"Food & Drink"
        }
    ],
    "sg:phone":"+61 3 9741 9402",
    "sg:postcode":"3030",
    "sg:province":"VIC",
    "wof:name":"Delicious Kebabs",
    "wof:placetype":"venue"
},
  "geometry": {"coordinates":[144.660477,-37.903397],"type":"Point"}
}