{
  "type": "Feature",
  "properties": {
    "addr:full":"163 Hillside Rd Avoca Beach NSW 2251",
    "addr:housenumber":"163",
    "addr:postcode":"2251",
    "addr:street":"Hillside Rd",
    "iso:country":"AU",
    "sg:address":"163 Hillside Rd",
    "sg:city":"Avoca Beach",
    "sg:classifiers":[
        {
            "category":"Building & Trades",
            "subcategory":"Plumbing",
            "type":"Services"
        }
    ],
    "sg:phone":"+61 2 4381 2100",
    "sg:postcode":"2251",
    "sg:province":"NSW",
    "sg:tags":[
        "plumber",
        "gasfitters"
    ],
    "wof:name":"AMPS",
    "wof:placetype":"venue"
},
  "geometry": {"coordinates":[151.425613403,-33.4638900757],"type":"Point"}
}