{
  "type": "Feature",
  "properties": {
    "addr:full":"Cnr Tomlinson & Welshpool Rds Welshpool WA 6106",
    "addr:postcode":"6106",
    "addr:street":"Rds",
    "iso:country":"AU",
    "sg:address":"Cnr Tomlinson & Welshpool Rds",
    "sg:city":"Welshpool",
    "sg:classifiers":[
        {
            "category":"Professional",
            "subcategory":"Employment Agencies",
            "type":"Services"
        }
    ],
    "sg:phone":"+61 8 9229 8222",
    "sg:postcode":"6106",
    "sg:province":"WA",
    "sg:tags":[
        "hire",
        "labour",
        "contractor"
    ],
    "wof:name":"Skilled",
    "wof:placetype":"venue"
},
  "geometry": {"coordinates":[115.927391052,-31.9915924072],"type":"Point"}
}