{
  "type": "Feature",
  "properties": {
    "addr:full":"290A Beauchamp Rd Maroubra NSW 2035",
    "addr:housenumber":"290a",
    "addr:postcode":"2035",
    "addr:street":"Beauchamp Rd",
    "iso:country":"AU",
    "sg:address":"290A Beauchamp Rd",
    "sg:city":"Maroubra",
    "sg:classifiers":[
        {
            "category":"Home & Garden",
            "subcategory":"Building Materials",
            "type":"Retail Goods"
        }
    ],
    "sg:phone":"+61 406 151 517",
    "sg:postcode":"2035",
    "sg:province":"NSW",
    "sg:tags":[
        "balustrading"
    ],
    "wof:name":"A1 Balustrade",
    "wof:placetype":"venue"
},
  "geometry": {"coordinates":[151.23733520499999,-33.9538116455],"type":"Point"}
}