{
  "type": "Feature",
  "properties": {
    "addr:full":"Shop 5/ 92 St Bernards Rd Magill North SA 5072",
    "addr:housenumber":"shop 5 / 92",
    "addr:postcode":"5072",
    "addr:street":"St Bernards Rd",
    "iso:country":"AU",
    "sg:address":"Shop 5/ 92 St Bernards Rd",
    "sg:city":"Magill North",
    "sg:classifiers":[
        {
            "category":"Government",
            "subcategory":"Post Office",
            "type":"Public Place"
        }
    ],
    "sg:phone":"+61 8 8431 6701",
    "sg:postcode":"5072",
    "sg:province":"SA",
    "sg:tags":[
        "postal"
    ],
    "wof:name":"Australia Post",
    "wof:placetype":"venue"
},
  "geometry": {"coordinates":[138.67547607399999,-34.9028739929],"type":"Point"}
}