{
  "type": "Feature",
  "properties": {
    "addr:full":"Suite 4 49 Ord St West Perth WA 6005",
    "addr:housenumber":"49",
    "addr:postcode":"6005",
    "addr:street":"Ord St",
    "iso:country":"AU",
    "sg:address":"Suite 4 49 Ord St",
    "sg:city":"West Perth",
    "sg:classifiers":[
        {
            "category":"Insurance",
            "subcategory":"Hazard Insurance",
            "type":"Services"
        }
    ],
    "sg:phone":"+61 8 9481 3773",
    "sg:postcode":"6005",
    "sg:province":"WA",
    "sg:tags":[
        "fire",
        "accident",
        "marine"
    ],
    "wof:name":"Underwriting Agencies Of Australia Pty Ltd",
    "wof:placetype":"venue"
},
  "geometry": {"coordinates":[115.837097168,-31.9494991302],"type":"Point"}
}