{
  "type": "Feature",
  "properties": {
    "iso:country":"AU",
    "sg:address":"11 Love St",
    "sg:city":"Cloverdale",
    "sg:classifiers":[
        {
            "category":"Fast Food",
            "type":"Food & Drink"
        }
    ],
    "sg:phone":"+61 8 9277 2083",
    "sg:postcode":"6105",
    "sg:province":"WA",
    "sg:tags":[
        "away",
        "take"
    ],
    "wof:name":"Jubilee Fish & Chips Takeaway",
    "wof:placetype":"venue"
},
  "geometry": {"coordinates":[115.947120666,-31.9556922913],"type":"Point"}
}