{
  "type": "Feature",
  "properties": {
    "addr:full":"424 George St Sydney NSW 2000",
    "addr:housenumber":"424",
    "addr:postcode":"2000",
    "addr:street":"George St",
    "iso:country":"AU",
    "sg:address":"424 George St",
    "sg:city":"Sydney",
    "sg:classifiers":[
        {
            "category":"Personal",
            "subcategory":"Beauty Salon",
            "type":"Services"
        }
    ],
    "sg:phone":"+61 2 9231 1290",
    "sg:postcode":"2000",
    "sg:province":"NSW",
    "wof:name":"Suntronic International",
    "wof:placetype":"venue"
},
  "geometry": {"coordinates":[151.207122803,-33.8698883057],"type":"Point"}
}