{
  "type": "Feature",
  "properties": {
    "addr:full":"40 Bailey St Bairnsdale VIC 3875",
    "addr:housenumber":"40",
    "addr:postcode":"3875",
    "addr:street":"Bailey St",
    "iso:country":"AU",
    "sg:address":"40 Bailey St",
    "sg:city":"Bairnsdale",
    "sg:classifiers":[
        {
            "category":"Personal",
            "subcategory":"Massage",
            "type":"Services"
        }
    ],
    "sg:phone":"+61 3 5152 6617",
    "sg:postcode":"3875",
    "sg:province":"VIC",
    "sg:tags":[
        "therapy"
    ],
    "wof:name":"Alan Mihan",
    "wof:placetype":"venue"
},
  "geometry": {"coordinates":[147.63186645499999,-37.8262443542],"type":"Point"}
}