{
  "type": "Feature",
  "properties": {
    "addr:full":"Allman Rd Denison VIC 3858",
    "addr:postcode":"3858",
    "addr:street":"Allman Rd",
    "iso:country":"AU",
    "sg:address":"Allman Rd",
    "sg:city":"Denison",
    "sg:classifiers":[
        {
            "category":"Professional",
            "subcategory":"Business Services",
            "type":"Services"
        }
    ],
    "sg:phone":"+61 3 5148 6382",
    "sg:postcode":"3858",
    "sg:province":"VIC",
    "sg:tags":[
        "livestock",
        "transport"
    ],
    "wof:name":"Allman M G & B I",
    "wof:placetype":"venue"
},
  "geometry": {"coordinates":[146.78752136200001,-37.9784240723],"type":"Point"}
}