{
  "type": "Feature",
  "properties": {
    "addr:full":"7 Eighth Ave Chelsea Heights VIC 3196",
    "addr:housenumber":"7",
    "addr:postcode":"3196",
    "addr:street":"Eighth Ave",
    "iso:country":"AU",
    "sg:address":"7 Eighth Ave",
    "sg:city":"Chelsea Heights",
    "sg:classifiers":[
        {
            "category":"Home & Garden",
            "subcategory":"Building Materials",
            "type":"Retail Goods"
        }
    ],
    "sg:phone":"+61 3 9773 8546",
    "sg:postcode":"3196",
    "sg:province":"VIC",
    "sg:tags":[
        "lawn",
        "cutting",
        "maintenance"
    ],
    "wof:name":"Able Grass Cutters",
    "wof:placetype":"venue"
},
  "geometry": {"coordinates":[145.13633727999999,-38.0392494202],"type":"Point"}
}