{
  "type": "Feature",
  "properties": {
    "addr:full":"Staff Rd Unanderra NSW 2526",
    "addr:postcode":"2526",
    "addr:street":"Staff Rd",
    "iso:country":"AU",
    "sg:address":"Staff Rd",
    "sg:city":"Unanderra",
    "sg:classifiers":[
        {
            "category":"Banks & Credit Unions",
            "subcategory":"Bureau De Change",
            "type":"Services"
        }
    ],
    "sg:phone":"+61 2 4271 7258",
    "sg:postcode":"2526",
    "sg:province":"NSW",
    "sg:tags":[
        "beekeeping",
        "supply"
    ],
    "wof:name":"Cox A D",
    "wof:placetype":"venue"
},
  "geometry": {"coordinates":[150.84039306599999,-34.4466209412],"type":"Point"}
}