{
  "type": "Feature",
  "properties": {
    "iso:country":"AU",
    "sg:address":"228 Hare St",
    "sg:city":"Echuca",
    "sg:classifiers":[
        {
            "category":"Shopping",
            "subcategory":"Jewelry",
            "type":"Retail Goods"
        }
    ],
    "sg:phone":"+61 3 5482 1627",
    "sg:postcode":"3564",
    "sg:province":"VIC",
    "sg:tags":[
        "jeweller"
    ],
    "wof:name":"Kismet Jewellery & Gifts",
    "wof:placetype":"venue"
},
  "geometry": {"coordinates":[144.74993896500001,-36.1294517517],"type":"Point"}
}