{
  "type": "Feature",
  "properties": {
    "iso:country":"AU",
    "sg:address":"Suite 2, 137 Sutton St",
    "sg:city":"Redcliffe",
    "sg:classifiers":[
        {
            "category":"Health Services",
            "subcategory":"Health Practitioner",
            "type":"Services"
        }
    ],
    "sg:phone":"+61 7 3284 0788",
    "sg:postcode":"4020",
    "sg:province":"QLD",
    "sg:tags":[
        "alternative"
    ],
    "wof:name":"Anand Dev Dr",
    "wof:placetype":"venue"
},
  "geometry": {"coordinates":[153.114426,-27.22901],"type":"Point"}
}