{
  "type": "Feature",
  "properties": {
    "addr:full":"56 Princes Hwy Dandenong VIC 3175",
    "addr:housenumber":"56",
    "addr:postcode":"3175",
    "addr:street":"Princes Hwy",
    "iso:country":"AU",
    "sg:address":"56 Princes Hwy",
    "sg:city":"Dandenong",
    "sg:classifiers":[
        {
            "category":"Organizations",
            "subcategory":"Community Association",
            "type":"Services"
        }
    ],
    "sg:phone":"+61 3 9792 1110",
    "sg:postcode":"3175",
    "sg:province":"VIC",
    "sg:tags":[
        "organisation",
        "family",
        "welfare"
    ],
    "wof:name":"Berry Street - Southern Services",
    "wof:placetype":"venue"
},
  "geometry": {"coordinates":[145.21128845199999,-37.9816055298],"type":"Point"}
}