{
  "type": "Feature",
  "properties": {
    "iso:country":"AU",
    "sg:address":"Suite 4 104 Cronulla St",
    "sg:city":"Cronulla",
    "sg:classifiers":[
        {
            "category":"Professional",
            "subcategory":"Accounting & Tax Preparation",
            "type":"Services"
        }
    ],
    "sg:phone":"+61 2 9544 0900",
    "sg:postcode":"2230",
    "sg:province":"NSW",
    "sg:tags":[
        "accountant",
        "auditor"
    ],
    "wof:name":"Saunders Meade",
    "wof:placetype":"venue"
},
  "geometry": {"coordinates":[151.15213012699999,-34.0545921326],"type":"Point"}
}