{
  "type": "Feature",
  "properties": {
    "iso:country":"AU",
    "sg:address":"U1/ 26 Vine St",
    "sg:city":"Ascot",
    "sg:classifiers":[
        {
            "category":"Professional",
            "subcategory":"Employment Agencies",
            "type":"Services"
        }
    ],
    "sg:phone":"+61 7 3868 2950",
    "sg:postcode":"4007",
    "sg:province":"QLD",
    "sg:tags":[
        "broker",
        "custom"
    ],
    "wof:name":"Fast Link Cube QLD",
    "wof:placetype":"venue"
},
  "geometry": {"coordinates":[153.066437,-27.431562],"type":"Point"}
}