{
  "type": "Feature",
  "properties": {
    "addr:full":"Central Ave Weipa QLD 4874",
    "addr:postcode":"4874",
    "addr:street":"Central Ave",
    "iso:country":"AU",
    "sg:address":"Central Ave",
    "sg:city":"Weipa",
    "sg:classifiers":[
        {
            "category":"Education",
            "subcategory":"School",
            "type":"Public Place"
        }
    ],
    "sg:phone":"+61 7 4090 6444",
    "sg:postcode":"4874",
    "sg:province":"QLD",
    "sg:tags":[
        "state",
        "except",
        "nsw"
    ],
    "wof:name":"Western Cape College Primary School - Weipa",
    "wof:placetype":"venue"
},
  "geometry": {"coordinates":[141.873703003,-12.636964798],"type":"Point"}
}