{
  "type": "Feature",
  "properties": {
    "iso:country":"AU",
    "sg:address":"William St",
    "sg:city":"Thallon",
    "sg:classifiers":[
        {
            "category":"Autos & Motor Vehicles",
            "subcategory":"Fuel & Gas Station",
            "type":"Retail Goods"
        }
    ],
    "sg:phone":"+61 7 4625 2114",
    "sg:postcode":"4497",
    "sg:province":"QLD",
    "wof:name":"BP Australia Limited",
    "wof:placetype":"venue"
},
  "geometry": {"coordinates":[148.86753845199999,-28.6362514496],"type":"Point"}
}