{
  "type": "Feature",
  "properties": {
    "addr:full":"1 Wilford Ave Underdale SA 5032",
    "addr:housenumber":"1",
    "addr:postcode":"5032",
    "addr:street":"Wilford Ave",
    "iso:country":"AU",
    "sg:address":"1 Wilford Ave",
    "sg:city":"Underdale",
    "sg:classifiers":[
        {
            "category":"Professional",
            "subcategory":"Printing & Photocopies",
            "type":"Services"
        }
    ],
    "sg:phone":"+61 8 8302 6965",
    "sg:postcode":"5032",
    "sg:province":"SA",
    "sg:tags":[
        "photocopying"
    ],
    "wof:name":"Document Services",
    "wof:placetype":"venue"
},
  "geometry": {"coordinates":[138.553497314,-34.9176063538],"type":"Point"}
}