{
  "type": "Feature",
  "properties": {
    "addr:full":"169 Barrier Reef Drv Robina QLD 4226",
    "addr:housenumber":"169",
    "addr:postcode":"4226",
    "addr:street":"Barrier Reef Drv",
    "iso:country":"AU",
    "sg:address":"169 Barrier Reef Drv",
    "sg:city":"Robina",
    "sg:classifiers":[
        {
            "category":"Social Services",
            "subcategory":"Child Care",
            "type":"Services"
        }
    ],
    "sg:phone":"+61 7 5572 2611",
    "sg:postcode":"4226",
    "sg:province":"QLD",
    "wof:name":"Robina Parks Children's Centre",
    "wof:placetype":"venue"
},
  "geometry": {"coordinates":[153.41546630900001,-28.0472202301],"type":"Point"}
}