{
  "type": "Feature",
  "properties": {
    "iso:country":"AU",
    "sg:address":"11 Muncaster Pl",
    "sg:city":"Cranebrook",
    "sg:classifiers":[
        {
            "category":"Industrial Area",
            "type":"Public Place"
        }
    ],
    "sg:phone":"+61 2 4729 4844",
    "sg:postcode":"2749",
    "sg:province":"NSW",
    "sg:tags":[
        "rural",
        "shed"
    ],
    "wof:name":"Sure Sheds Pty Ltd",
    "wof:placetype":"venue"
},
  "geometry": {"coordinates":[150.716308594,-33.7232933044],"type":"Point"}
}