{
  "type": "Feature",
  "properties": {
    "addr:full":"Suite 2c, 131 Lonsdale St Melbourne VIC 3000",
    "addr:housenumber":"2c 131",
    "addr:postcode":"3000",
    "addr:street":"Lonsdale St",
    "iso:country":"AU",
    "sg:address":"Suite 2c, 131 Lonsdale St",
    "sg:city":"Melbourne",
    "sg:classifiers":[
        {
            "category":"Health Services",
            "subcategory":"Health Practitioner",
            "type":"Services"
        }
    ],
    "sg:phone":"+61 417 386 848",
    "sg:postcode":"3000",
    "sg:province":"VIC",
    "sg:tags":[
        "psychologist"
    ],
    "wof:name":"Pickering Gabrielle Dr",
    "wof:placetype":"venue"
},
  "geometry": {"coordinates":[144.968475342,-37.8105964661],"type":"Point"}
}