{
  "type": "Feature",
  "properties": {
    "addr:full":"Shop 6, 152 Bellarine Hwy Newcomb VIC 3219",
    "addr:housenumber":"shop 6",
    "addr:postcode":"152;3219",
    "addr:street":"Bellarine Hwy",
    "iso:country":"AU",
    "sg:address":"Shop 6, 152 Bellarine Hwy",
    "sg:city":"Newcomb",
    "sg:classifiers":[
        {
            "category":"Real Estate",
            "subcategory":"Real Estate Agent",
            "type":"Services"
        }
    ],
    "sg:phone":"+61 3 5248 8611",
    "sg:postcode":"3219",
    "sg:province":"VIC",
    "wof:name":"Hooker L J",
    "wof:placetype":"venue"
},
  "geometry": {"coordinates":[144.398529053,-38.1727180481],"type":"Point"}
}