{
  "type": "Feature",
  "properties": {
    "iso:country":"AU",
    "sg:address":"AAMI Stadium Gate L Brebner Drv",
    "sg:city":"West Lakes",
    "sg:classifiers":[
        {
            "category":"Health Services",
            "subcategory":"Doctor",
            "type":"Services"
        }
    ],
    "sg:phone":"+61 8 8347 2043",
    "sg:postcode":"5021",
    "sg:province":"SA",
    "sg:tags":[
        "podiatrist"
    ],
    "wof:name":"Jaques Nicole",
    "wof:placetype":"venue"
},
  "geometry": {"coordinates":[138.491744995,-34.8766365051],"type":"Point"}
}