{
  "type": "Feature",
  "properties": {
    "addr:full":"Augustus St Deniliquin NSW 2710",
    "addr:postcode":"2710",
    "addr:street":"Augustus St",
    "iso:country":"AU",
    "sg:address":"Augustus St",
    "sg:city":"Deniliquin",
    "sg:classifiers":[
        {
            "category":"Building & Trades",
            "subcategory":"Equipment Rental",
            "type":"Services"
        }
    ],
    "sg:phone":"+61 3 5881 3104",
    "sg:postcode":"2710",
    "sg:province":"NSW",
    "sg:tags":[
        "crane",
        "hire"
    ],
    "wof:name":"Murray Constructions Pty Ltd",
    "wof:placetype":"venue"
},
  "geometry": {"coordinates":[144.98257446299999,-35.513999939],"type":"Point"}
}