{
  "type": "Feature",
  "properties": {
    "iso:country":"AU",
    "sg:address":"Shp4/ 156 Oxford St",
    "sg:city":"Leederville",
    "sg:classifiers":[
        {
            "category":"Personal",
            "subcategory":"Beauty Salon",
            "type":"Services"
        }
    ],
    "sg:phone":"+61 8 9443 1050",
    "sg:postcode":"6007",
    "sg:province":"WA",
    "wof:name":"Leederville Beauty Room",
    "wof:placetype":"venue"
},
  "geometry": {"coordinates":[115.841392517,-31.936252594],"type":"Point"}
}