{
  "type": "Feature",
  "properties": {
    "iso:country":"AU",
    "sg:address":"38 Henley Rd",
    "sg:city":"Mt Pleasant",
    "sg:classifiers":[
        {
            "category":"Education",
            "subcategory":"Music School",
            "type":"Public Place"
        }
    ],
    "sg:phone":"+61 8 9364 4391",
    "sg:postcode":"6153",
    "sg:province":"WA",
    "sg:tags":[
        "choir",
        "bands",
        "orchestra"
    ],
    "wof:name":"Perth Harmony Chorus",
    "wof:placetype":"venue"
},
  "geometry": {"coordinates":[115.84417,-32.029503],"type":"Point"}
}