{
  "type": "Feature",
  "properties": {
    "addr:full":"Shp 5c Cottonwood Plaza 3- 5 Cottonwood Pl Oxenford QLD 4210",
    "addr:housenumber":"5c;3 5",
    "addr:postcode":"4210",
    "addr:street":"Cottonwood Plaza;Cottonwood Pl",
    "iso:country":"AU",
    "sg:address":"Shp 5c Cottonwood Plaza 3- 5 Cottonwood Pl",
    "sg:city":"Oxenford",
    "sg:classifiers":[
        {
            "category":"Sports & Exercise",
            "subcategory":"Gym",
            "type":"Entertainment"
        }
    ],
    "sg:phone":"+61 7 5580 1825",
    "sg:postcode":"4210",
    "sg:province":"QLD",
    "sg:tags":[
        "health",
        "fitness"
    ],
    "wof:name":"Curves Oxenford",
    "wof:placetype":"venue"
},
  "geometry": {"coordinates":[153.31236267099999,-27.8920307159],"type":"Point"}
}