{
  "type": "Feature",
  "properties": {
    "addr:full":"21 Dargie Crt Broadmeadows VIC 3047",
    "addr:housenumber":"21",
    "addr:postcode":"3047",
    "addr:street":"Dargie Crt",
    "iso:country":"AU",
    "sg:address":"21 Dargie Crt",
    "sg:city":"Broadmeadows",
    "sg:classifiers":[
        {
            "category":"Food & Beverages",
            "subcategory":"Groceries & Convenience Stores",
            "type":"Retail Goods"
        }
    ],
    "sg:phone":"+61 3 9309 1608",
    "sg:postcode":"3047",
    "sg:province":"VIC",
    "wof:name":"Dallas Milkbar",
    "wof:placetype":"venue"
},
  "geometry": {"coordinates":[144.930343628,-37.6727676392],"type":"Point"}
}