{
  "type": "Feature",
  "properties": {
    "addr:full":"23 Mylne St Gladstone QLD 4680",
    "addr:housenumber":"23",
    "addr:postcode":"4680",
    "addr:street":"Mylne St",
    "iso:country":"AU",
    "sg:address":"23 Mylne St",
    "sg:city":"Gladstone",
    "sg:classifiers":[
        {
            "category":"Utilities",
            "subcategory":"Electric",
            "type":"Services"
        }
    ],
    "sg:phone":"+61 7 4972 1929",
    "sg:postcode":"4680",
    "sg:province":"QLD",
    "sg:tags":[
        "electrical",
        "contractor"
    ],
    "wof:name":"Aulec Electrical Services",
    "wof:placetype":"venue"
},
  "geometry": {"coordinates":[151.244308472,-23.8472747803],"type":"Point"}
}