{
  "type": "Feature",
  "properties": {
    "addr:full":"Cnr Melton Hwy & Sydenham Rd Sydenham VIC 3037",
    "addr:postcode":"3037",
    "addr:street":"Cnr Melton Hwy & Sydenham Rd",
    "iso:country":"AU",
    "sg:address":"Cnr Melton Hwy & Sydenham Rd",
    "sg:city":"Sydenham",
    "sg:classifiers":[
        {
            "category":"Food & Beverages",
            "subcategory":"Supermarket",
            "type":"Retail Goods"
        }
    ],
    "sg:phone":"+61 3 9449 1000",
    "sg:postcode":"3037",
    "sg:province":"VIC",
    "sg:tags":[
        "grocery",
        "store"
    ],
    "wof:name":"Bi-Lo Pty Ltd",
    "wof:placetype":"venue"
},
  "geometry": {"coordinates":[144.764847,-37.694668],"type":"Point"}
}