{
  "type": "Feature",
  "properties": {
    "addr:full":"Factory 4/ 57 Power Rd Bayswater VIC 3153",
    "addr:housenumber":"/ 57",
    "addr:postcode":"3153",
    "addr:street":"Power Rd",
    "iso:country":"AU",
    "sg:address":"Factory 4/ 57 Power Rd",
    "sg:city":"Bayswater",
    "sg:classifiers":[
        {
            "category":"Building & Trades",
            "subcategory":"Construction",
            "type":"Services"
        }
    ],
    "sg:phone":"+61 3 9720 4548",
    "sg:postcode":"3153",
    "sg:province":"VIC",
    "sg:tags":[
        "concrete",
        "treatment",
        "repair"
    ],
    "wof:name":"Concrete Floor Grinding Company",
    "wof:placetype":"venue"
},
  "geometry": {"coordinates":[145.27655029300001,-37.849571228],"type":"Point"}
}