{
  "type": "Feature",
  "properties": {
    "addr:full":"109- 111 Flora Ave Mildura VIC 3502",
    "addr:housenumber":"111",
    "addr:postcode":"3502",
    "addr:street":"Flora Ave",
    "iso:country":"AU",
    "sg:address":"109- 111 Flora Ave",
    "sg:city":"Mildura",
    "sg:classifiers":[
        {
            "category":"Professional",
            "subcategory":"Accounting & Tax Preparation",
            "type":"Services"
        }
    ],
    "sg:phone":"+61 3 5022 0400",
    "sg:postcode":"3502",
    "sg:province":"VIC",
    "sg:tags":[
        "consultant",
        "taxation"
    ],
    "wof:name":"Thompson Lynette J",
    "wof:placetype":"venue"
},
  "geometry": {"coordinates":[142.154418945,-34.1804122925],"type":"Point"}
}