{
  "type": "Feature",
  "properties": {
    "iso:country":"AU",
    "sg:address":"20 Beaconsfield Drv",
    "sg:city":"Burleigh Waters",
    "sg:classifiers":[
        {
            "category":"Professional",
            "subcategory":"Advertising",
            "type":"Services"
        }
    ],
    "sg:phone":"+61 1300 135 845",
    "sg:postcode":"4220",
    "sg:province":"QLD",
    "sg:tags":[
        "balloon",
        "novelty"
    ],
    "wof:name":"Balloon Event Co",
    "wof:placetype":"venue"
},
  "geometry": {"coordinates":[153.42164611800001,-28.0708847046],"type":"Point"}
}