{
  "type": "Feature",
  "properties": {
    "addr:full":"19 Bridge Rd Hornsby NSW 2077",
    "addr:housenumber":"19",
    "addr:postcode":"2077",
    "addr:street":"Bridge Rd",
    "iso:country":"AU",
    "sg:address":"19 Bridge Rd",
    "sg:city":"Hornsby",
    "sg:classifiers":[
        {
            "category":"Professional",
            "type":"Services"
        }
    ],
    "sg:phone":"+61 418 169 429",
    "sg:postcode":"2077",
    "sg:province":"NSW",
    "sg:tags":[
        "courier"
    ],
    "wof:name":"Pete's Taxi Trucks",
    "wof:placetype":"venue"
},
  "geometry": {"coordinates":[151.10125732399999,-33.6974716187],"type":"Point"}
}