{
  "type": "Feature",
  "properties": {
    "addr:full":"PO Box 170 Corinda QLD 4075",
    "addr:postcode":"4075",
    "iso:country":"AU",
    "sg:address":"PO Box 170",
    "sg:city":"Corinda",
    "sg:classifiers":[
        {
            "category":"Building & Trades",
            "subcategory":"Landscaping Services",
            "type":"Services"
        }
    ],
    "sg:phone":"+61 7 3278 2264",
    "sg:postcode":"4075",
    "sg:province":"QLD",
    "sg:tags":[
        "architect",
        "landscape"
    ],
    "wof:name":"Black Stevens & Associates",
    "wof:placetype":"venue"
},
  "geometry": {"coordinates":[152.98170471200001,-27.5393600464],"type":"Point"}
}