{
  "type": "Feature",
  "properties": {
    "iso:country":"AU",
    "sg:address":"Cnr Oats & Bank Sts",
    "sg:city":"Carlisle",
    "sg:classifiers":[
        {
            "category":"Education",
            "subcategory":"Vocational School",
            "type":"Public Place"
        }
    ],
    "sg:phone":"+61 8 9267 7500",
    "sg:postcode":"6101",
    "sg:province":"WA",
    "sg:tags":[
        "tafe",
        "college",
        "training"
    ],
    "wof:name":"Swan Tafe",
    "wof:placetype":"venue"
},
  "geometry": {"coordinates":[115.925689697,-31.9794635773],"type":"Point"}
}