{
  "type": "Feature",
  "properties": {
    "iso:country":"AU",
    "sg:address":"21 Godfrey St",
    "sg:city":"Banksia",
    "sg:classifiers":[
        {
            "category":"Professional",
            "type":"Services"
        }
    ],
    "sg:phone":"+61 2 9597 6060",
    "sg:postcode":"2216",
    "sg:province":"NSW",
    "sg:tags":[
        "transport"
    ],
    "wof:name":"Rosebud & Sons Haulage",
    "wof:placetype":"venue"
},
  "geometry": {"coordinates":[151.13911400000001,-33.944118],"type":"Point"}
}