{
  "type": "Feature",
  "properties": {
    "iso:country":"AU",
    "sg:address":"82 Railway Pde North",
    "sg:city":"Blackalls Park",
    "sg:classifiers":[
        {
            "category":"Utilities",
            "subcategory":"Water",
            "type":"Services"
        }
    ],
    "sg:phone":"+61 2 4950 4355",
    "sg:postcode":"2283",
    "sg:province":"NSW",
    "sg:tags":[
        "cartage"
    ],
    "wof:name":"Mason Earthmoving",
    "wof:placetype":"venue"
},
  "geometry": {"coordinates":[151.58822631800001,-33.0056991577],"type":"Point"}
}