{
  "type": "Feature",
  "properties": {
    "addr:full":"Lot 5 Ash St Yamanto QLD 4305",
    "addr:housenumber":"5",
    "addr:postcode":"4305",
    "addr:street":"Ash St",
    "iso:country":"AU",
    "sg:address":"Lot 5 Ash St",
    "sg:city":"Yamanto",
    "sg:classifiers":[
        {
            "category":"Food & Beverages",
            "subcategory":"Supermarket",
            "type":"Retail Goods"
        }
    ],
    "sg:phone":"+61 7 3288 0166",
    "sg:postcode":"4305",
    "sg:province":"QLD",
    "sg:tags":[
        "grocery",
        "store"
    ],
    "wof:name":"Action Supermarkets",
    "wof:placetype":"venue"
},
  "geometry": {"coordinates":[152.75245666500001,-27.6543102264],"type":"Point"}
}