{
  "type": "Feature",
  "properties": {
    "addr:full":"101 Isabella St Wingham NSW 2429",
    "addr:housenumber":"101",
    "addr:postcode":"2429",
    "addr:street":"Isabella St",
    "iso:country":"AU",
    "sg:address":"101 Isabella St",
    "sg:city":"Wingham",
    "sg:classifiers":[
        {
            "category":"Health Services",
            "subcategory":"Dentist",
            "type":"Services"
        }
    ],
    "sg:phone":"+61 2 6553 4269",
    "sg:postcode":"2429",
    "sg:province":"NSW",
    "wof:name":"Stockard J D",
    "wof:placetype":"venue"
},
  "geometry": {"coordinates":[152.372604,-31.868595],"type":"Point"}
}