{
  "type": "Feature",
  "properties": {
    "iso:country":"AU",
    "sg:address":"41 Nevin Drv",
    "sg:city":"Thomastown",
    "sg:classifiers":[
        {
            "category":"Wholesale",
            "subcategory":"Chemicals & Plastics",
            "type":"Manufacturing & Wholesale Goods"
        }
    ],
    "sg:phone":"+61 3 9466 2921",
    "sg:postcode":"3074",
    "sg:province":"VIC",
    "sg:tags":[
        "bag"
    ],
    "wof:name":"United Multibags Australia",
    "wof:placetype":"venue"
},
  "geometry": {"coordinates":[145.03323364299999,-37.6963386536],"type":"Point"}
}