{
  "type": "Feature",
  "properties": {
    "addr:full":"397 Bridge St Toowoomba QLD 4350",
    "addr:housenumber":"397",
    "addr:postcode":"4350",
    "addr:street":"Bridge St",
    "iso:country":"AU",
    "sg:address":"397 Bridge St",
    "sg:city":"Toowoomba",
    "sg:classifiers":[
        {
            "category":"Fast Food",
            "type":"Food & Drink"
        }
    ],
    "sg:phone":"+61 7 4633 1464",
    "sg:postcode":"4350",
    "sg:province":"QLD",
    "sg:tags":[
        "away",
        "take"
    ],
    "wof:name":"Hungry Jacks Pty Ltd",
    "wof:placetype":"venue"
},
  "geometry": {"coordinates":[151.89904799999999,-27.533037],"type":"Point"}
}