{
  "type": "Feature",
  "properties": {
    "iso:country":"AU",
    "sg:address":"52 Chrystal St",
    "sg:city":"Roma",
    "sg:classifiers":[
        {
            "category":"Personal",
            "subcategory":"Tattoo Parlor",
            "type":"Services"
        }
    ],
    "sg:phone":"+61 7 4622 7727",
    "sg:postcode":"4455",
    "sg:province":"QLD",
    "sg:tags":[
        "tattooing"
    ],
    "wof:name":"Roma Ink",
    "wof:placetype":"venue"
},
  "geometry": {"coordinates":[148.78970336899999,-26.5781173706],"type":"Point"}
}