{
  "type": "Feature",
  "properties": {
    "addr:full":"11- 15 Bertram St Mortlake NSW 2137",
    "addr:housenumber":"15",
    "addr:postcode":"2137",
    "addr:street":"Bertram St",
    "iso:country":"AU",
    "sg:address":"11- 15 Bertram St",
    "sg:city":"Mortlake",
    "sg:classifiers":[
        {
            "category":"Building & Trades",
            "subcategory":"Construction",
            "type":"Services"
        }
    ],
    "sg:phone":"+61 2 9743 1500",
    "sg:postcode":"2137",
    "sg:province":"NSW",
    "sg:tags":[
        "contractor"
    ],
    "wof:name":"Proline Building Commercial Pty Ltd",
    "wof:placetype":"venue"
},
  "geometry": {"coordinates":[151.106887817,-33.8430747986],"type":"Point"}
}