{
  "type": "Feature",
  "properties": {
    "addr:full":"Karadoc Ave Irymple VIC 3498",
    "addr:postcode":"3498",
    "addr:street":"Karadoc Ave",
    "iso:country":"AU",
    "sg:address":"Karadoc Ave",
    "sg:city":"Irymple",
    "sg:classifiers":[
        {
            "category":"Farming",
            "subcategory":"Berry Farm",
            "type":"Manufacturing & Wholesale Goods"
        }
    ],
    "sg:phone":"+61 3 5024 5662",
    "sg:postcode":"3498",
    "sg:province":"VIC",
    "sg:tags":[
        "fruit",
        "grower"
    ],
    "wof:name":"Jones D L",
    "wof:placetype":"venue"
},
  "geometry": {"coordinates":[142.165893555,-34.2313804626],"type":"Point"}
}