{
  "type": "Feature",
  "properties": {
    "addr:full":"9/ 475 Blackburn Rd Mt Waverley VIC 3149",
    "addr:housenumber":"/ 475",
    "addr:postcode":"3149",
    "addr:street":"Blackburn Rd",
    "iso:country":"AU",
    "sg:address":"9/ 475 Blackburn Rd",
    "sg:city":"Mt Waverley",
    "sg:classifiers":[
        {
            "category":"Shopping",
            "type":"Retail Goods"
        }
    ],
    "sg:phone":"+61 3 9544 6300",
    "sg:postcode":"3149",
    "sg:province":"VIC",
    "sg:tags":[
        "equipment",
        "safety",
        "accessory"
    ],
    "wof:name":"Pilz Australia",
    "wof:placetype":"venue"
},
  "geometry": {"coordinates":[145.14372253400001,-37.8959770203],"type":"Point"}
}