{
  "type": "Feature",
  "properties": {
    "addr:full":"4 Punari St Currajong QLD 4812",
    "addr:housenumber":"4",
    "addr:postcode":"4812",
    "addr:street":"Punari St",
    "iso:country":"AU",
    "sg:address":"4 Punari St",
    "sg:city":"Currajong",
    "sg:classifiers":[
        {
            "category":"Retail",
            "subcategory":"Auto Repair",
            "type":"Services"
        }
    ],
    "sg:phone":"+61 7 4779 3614",
    "sg:postcode":"4812",
    "sg:province":"QLD",
    "sg:tags":[
        "beater",
        "painter",
        "panel"
    ],
    "wof:name":"Douglas & Miller Motor Body Repairs",
    "wof:placetype":"venue"
},
  "geometry": {"coordinates":[146.772324,-19.273401],"type":"Point"}
}