{
  "type": "Feature",
  "properties": {
    "iso:country":"AU",
    "sg:address":"3 Belgrave Crt",
    "sg:city":"Parkside",
    "sg:classifiers":[
        {
            "category":"Professional",
            "subcategory":"Accounting & Tax Preparation",
            "type":"Services"
        }
    ],
    "sg:phone":"+61 8 8373 1533",
    "sg:postcode":"5063",
    "sg:province":"SA",
    "sg:tags":[
        "consultant",
        "taxation"
    ],
    "wof:name":"Dix Roger H & Associates",
    "wof:placetype":"venue"
},
  "geometry": {"coordinates":[138.60746765100001,-34.9462661743],"type":"Point"}
}