{
  "type": "Feature",
  "properties": {
    "addr:full":"6 Branch Rd South Johnstone QLD 4859",
    "addr:housenumber":"6",
    "addr:postcode":"4859",
    "addr:street":"Branch Rd",
    "iso:country":"AU",
    "sg:address":"6 Branch Rd",
    "sg:city":"South Johnstone",
    "sg:classifiers":[
        {
            "category":"Farming",
            "subcategory":"Farm",
            "type":"Manufacturing & Wholesale Goods"
        }
    ],
    "sg:phone":"+61 7 4064 2239",
    "sg:postcode":"4859",
    "sg:province":"QLD",
    "sg:tags":[
        "farmer"
    ],
    "wof:name":"Cole A H",
    "wof:placetype":"venue"
},
  "geometry": {"coordinates":[145.99586486800001,-17.59623909],"type":"Point"}
}