{
  "type": "Feature",
  "properties": {
    "addr:full":"26 Second Ave Macquarie Fields NSW 2564",
    "addr:housenumber":"26",
    "addr:postcode":"2564",
    "addr:street":"Second Ave",
    "iso:country":"AU",
    "sg:address":"26 Second Ave",
    "sg:city":"Macquarie Fields",
    "sg:classifiers":[
        {
            "category":"Utilities",
            "subcategory":"Electric",
            "type":"Services"
        }
    ],
    "sg:phone":"+61 402 444 446",
    "sg:postcode":"2564",
    "sg:province":"NSW",
    "sg:tags":[
        "electrical",
        "contractor"
    ],
    "wof:name":"Electra Buzz",
    "wof:placetype":"venue"
},
  "geometry": {"coordinates":[150.903442383,-33.9986801147],"type":"Point"}
}