{
  "type": "Feature",
  "properties": {
    "addr:full":"635 Nicholson St Carlton North VIC 3054",
    "addr:housenumber":"635",
    "addr:postcode":"3054",
    "addr:street":"Nicholson St",
    "iso:country":"AU",
    "sg:address":"635 Nicholson St",
    "sg:city":"Carlton North",
    "sg:classifiers":[
        {
            "category":"Personal",
            "subcategory":"Beauty Salon",
            "type":"Services"
        }
    ],
    "sg:phone":"+61 3 9387 0711",
    "sg:postcode":"3054",
    "sg:province":"VIC",
    "sg:tags":[
        "hairdresser"
    ],
    "wof:name":"Meei Hairdressing",
    "wof:placetype":"venue"
},
  "geometry": {"coordinates":[144.97708129899999,-37.7844314575],"type":"Point"}
}