{
  "type": "Feature",
  "properties": {
    "addr:full":"31 Harcourt Rd Payneham SA 5070",
    "addr:housenumber":"31",
    "addr:postcode":"5070",
    "addr:street":"Harcourt Rd",
    "iso:country":"AU",
    "sg:address":"31 Harcourt Rd",
    "sg:city":"Payneham",
    "sg:classifiers":[
        {
            "category":"Communications",
            "type":"Services"
        }
    ],
    "sg:phone":"+61 411 181 048",
    "sg:postcode":"5070",
    "sg:province":"SA",
    "sg:tags":[
        "translation"
    ],
    "wof:name":"Interpreters & Translators",
    "wof:placetype":"venue"
},
  "geometry": {"coordinates":[138.63609314000001,-34.9020881653],"type":"Point"}
}