{
  "type": "Feature",
  "properties": {
    "addr:full":"3/ 81 Scott St Liverpool NSW 2170",
    "addr:housenumber":"/ 81",
    "addr:postcode":"2170",
    "addr:street":"Scott St",
    "iso:country":"AU",
    "sg:address":"3/ 81 Scott St",
    "sg:city":"Liverpool",
    "sg:classifiers":[
        {
            "category":"Social Services",
            "subcategory":"Retirement Home",
            "type":"Services"
        }
    ],
    "sg:phone":"+61 2 9734 7611",
    "sg:postcode":"2170",
    "sg:province":"NSW",
    "sg:tags":[
        "visa"
    ],
    "wof:name":"M. Elias & Associates",
    "wof:placetype":"venue"
},
  "geometry": {"coordinates":[150.92332458499999,-33.9247627258],"type":"Point"}
}