{
  "type": "Feature",
  "properties": {
    "addr:full":"255 William St Melbourne VIC 3000",
    "addr:housenumber":"255",
    "addr:postcode":"3000",
    "addr:street":"William St",
    "iso:country":"AU",
    "sg:address":"255 William St",
    "sg:city":"Melbourne",
    "sg:classifiers":[
        {
            "category":"Cafe",
            "type":"Food & Drink"
        }
    ],
    "sg:phone":"+61 3 9600 0311",
    "sg:postcode":"3000",
    "sg:province":"VIC",
    "wof:name":"Petty Session",
    "wof:placetype":"venue"
},
  "geometry": {"coordinates":[144.956863403,-37.8130493164],"type":"Point"}
}