{
  "type": "Feature",
  "properties": {
    "addr:full":"19 Transport Ave Mackay QLD 4740",
    "addr:housenumber":"19",
    "addr:postcode":"4740",
    "addr:street":"Transport Ave",
    "iso:country":"AU",
    "sg:address":"19 Transport Ave",
    "sg:city":"Mackay",
    "sg:classifiers":[
        {
            "category":"Mining & Drilling",
            "type":"Manufacturing & Wholesale Goods"
        }
    ],
    "sg:phone":"+61 7 4952 6658",
    "sg:postcode":"4740",
    "sg:province":"QLD",
    "sg:tags":[
        "equipment",
        "quarrying",
        "supply"
    ],
    "wof:name":"FSP Australia Pty Ltd",
    "wof:placetype":"venue"
},
  "geometry": {"coordinates":[149.16709900000001,-21.171547],"type":"Point"}
}