{
  "type": "Feature",
  "properties": {
    "addr:full":"48 Bonnyvale Rd Ocean Grove VIC 3226",
    "addr:housenumber":"48",
    "addr:postcode":"3226",
    "addr:street":"Bonnyvale Rd",
    "iso:country":"AU",
    "sg:address":"48 Bonnyvale Rd",
    "sg:city":"Ocean Grove",
    "sg:classifiers":[
        {
            "category":"Utilities",
            "subcategory":"Electric",
            "type":"Services"
        }
    ],
    "sg:phone":"+61 3 5256 1132",
    "sg:postcode":"3226",
    "sg:province":"VIC",
    "sg:tags":[
        "electrical",
        "contractor"
    ],
    "wof:name":"Irwin Electrical Service",
    "wof:placetype":"venue"
},
  "geometry": {"coordinates":[144.55415300000001,-38.263535],"type":"Point"}
}