{
  "type": "Feature",
  "properties": {
    "addr:full":"21 Princes St McMahons Point NSW 2060",
    "addr:housenumber":"21",
    "addr:postcode":"2060",
    "addr:street":"Princes St",
    "iso:country":"AU",
    "sg:address":"21 Princes St",
    "sg:city":"McMahons Point",
    "sg:classifiers":[
        {
            "category":"Social Services",
            "subcategory":"Adult Care",
            "type":"Services"
        }
    ],
    "sg:phone":"+61 2 9923 2599",
    "sg:postcode":"2060",
    "sg:province":"NSW",
    "sg:tags":[
        "aged"
    ],
    "wof:name":"Mature Relocation",
    "wof:placetype":"venue"
},
  "geometry": {"coordinates":[151.203689575,-33.8446960449],"type":"Point"}
}