{
  "type": "Feature",
  "properties": {
    "iso:country":"AU",
    "sg:address":"2/ 6 Aldershot Rd",
    "sg:city":"Lonsdale",
    "sg:classifiers":[
        {
            "category":"Home & Garden",
            "subcategory":"Home Furnishings",
            "type":"Retail Goods"
        }
    ],
    "sg:phone":"+61 8 8186 0645",
    "sg:postcode":"5160",
    "sg:province":"SA",
    "sg:tags":[
        "shower",
        "screen"
    ],
    "wof:name":"Affordable Glass",
    "wof:placetype":"venue"
},
  "geometry": {"coordinates":[138.50782775900001,-35.1154289246],"type":"Point"}
}