{
  "type": "Feature",
  "properties": {
    "addr:full":"180 Macquarie St Hobart TAS 7000",
    "addr:housenumber":"180",
    "addr:postcode":"7000",
    "addr:street":"Macquarie St",
    "iso:country":"AU",
    "sg:address":"180 Macquarie St",
    "sg:city":"Hobart",
    "sg:classifiers":[
        {
            "category":"Health Services",
            "subcategory":"Optometrist",
            "type":"Services"
        }
    ],
    "sg:phone":"+61 3 6224 2253",
    "sg:postcode":"7000",
    "sg:province":"TAS",
    "wof:name":"Tasmanian Cataract Clinic",
    "wof:placetype":"venue"
},
  "geometry": {"coordinates":[147.3256073,-42.8864784241],"type":"Point"}
}