{
  "type": "Feature",
  "properties": {
    "iso:country":"AU",
    "sg:address":"191 Roach Rd",
    "sg:city":"Wagga Wagga",
    "sg:classifiers":[
        {
            "category":"Commercial Area",
            "type":"Public Place"
        }
    ],
    "sg:phone":"+61 427 753 756",
    "sg:postcode":"2650",
    "sg:province":"NSW",
    "sg:tags":[
        "heavy",
        "carrier"
    ],
    "wof:name":"Wagga Tilt Tray Service",
    "wof:placetype":"venue"
},
  "geometry": {"coordinates":[147.31300354000001,-35.1094322205],"type":"Point"}
}