{
  "type": "Feature",
  "properties": {
    "addr:full":"23 Watt St Newcastle NSW 2300",
    "addr:housenumber":"23",
    "addr:postcode":"2300",
    "addr:street":"Watt St",
    "iso:country":"AU",
    "sg:address":"23 Watt St",
    "sg:city":"Newcastle",
    "sg:classifiers":[
        {
            "category":"Professional",
            "subcategory":"Management & Consulting",
            "type":"Services"
        }
    ],
    "sg:phone":"+61 2 4926 3823",
    "sg:postcode":"2300",
    "sg:province":"NSW",
    "sg:tags":[
        "consultant"
    ],
    "wof:name":"Executive Coaching On-Line",
    "wof:placetype":"venue"
},
  "geometry": {"coordinates":[151.78445400000001,-32.928013],"type":"Point"}
}