{
  "type": "Feature",
  "properties": {
    "addr:full":"Cooper St Chinchilla QLD 4413",
    "addr:postcode":"4413",
    "addr:street":"Cooper St",
    "iso:country":"AU",
    "sg:address":"Cooper St",
    "sg:city":"Chinchilla",
    "sg:classifiers":[
        {
            "category":"Professional",
            "subcategory":"Engineering",
            "type":"Services"
        }
    ],
    "sg:phone":"+61 7 4662 7490",
    "sg:postcode":"4413",
    "sg:province":"QLD",
    "sg:tags":[
        "engineer"
    ],
    "wof:name":"Scouller Engineering",
    "wof:placetype":"venue"
},
  "geometry": {"coordinates":[150.642379761,-26.7485256195],"type":"Point"}
}