{
  "type": "Feature",
  "properties": {
    "addr:full":"Arch Rd Eaglehawk Neck TAS 7179",
    "addr:postcode":"7179",
    "addr:street":"Arch Rd",
    "iso:country":"AU",
    "sg:address":"Arch Rd",
    "sg:city":"Eaglehawk Neck",
    "sg:classifiers":[
        {
            "category":"Recreation",
            "subcategory":"Boat Charter",
            "type":"Entertainment"
        }
    ],
    "sg:phone":"+61 3 6250 3350",
    "sg:postcode":"7179",
    "sg:province":"TAS",
    "wof:name":"Doongaa Sea Charters",
    "wof:placetype":"venue"
},
  "geometry": {"coordinates":[147.91336059599999,-43.0190811157],"type":"Point"}
}