{
  "type": "Feature",
  "properties": {
    "addr:full":"1st Floor 277 Old Cleveland Rd Coorparoo QLD 4151",
    "addr:housenumber":"277",
    "addr:postcode":"4151",
    "addr:street":"Old Cleveland Rd",
    "iso:country":"AU",
    "sg:address":"1st Floor 277 Old Cleveland Rd",
    "sg:city":"Coorparoo",
    "sg:classifiers":[
        {
            "category":"Health Services",
            "subcategory":"Dentist",
            "type":"Services"
        }
    ],
    "sg:phone":"+61 7 3397 7866",
    "sg:postcode":"4151",
    "sg:province":"QLD",
    "sg:tags":[
        "dental",
        "prosthetist"
    ],
    "wof:name":"Personal Denture Services",
    "wof:placetype":"venue"
},
  "geometry": {"coordinates":[153.05804443400001,-27.4952583313],"type":"Point"}
}