{
  "type": "Feature",
  "properties": {
    "addr:full":"Lot 4 Industrial Drv Emerald QLD 4720",
    "addr:postcode":"4720",
    "addr:street":"Industrial Drv",
    "iso:country":"AU",
    "sg:address":"Lot 4 Industrial Drv",
    "sg:city":"Emerald",
    "sg:classifiers":[
        {
            "category":"Building & Trades",
            "subcategory":"Plumbing",
            "type":"Services"
        }
    ],
    "sg:phone":"+61 7 4987 8400",
    "sg:postcode":"4720",
    "sg:province":"QLD",
    "sg:tags":[
        "pump",
        "repairer"
    ],
    "wof:name":"Custom Fluidpower Pty Ltd",
    "wof:placetype":"venue"
},
  "geometry": {"coordinates":[148.15193199999999,-23.504358],"type":"Point"}
}