{
  "type": "Feature",
  "properties": {
    "addr:full":"18 Cobbs Rd Woombye QLD 4559",
    "addr:housenumber":"18",
    "addr:postcode":"4559",
    "addr:street":"Cobbs Rd",
    "iso:country":"AU",
    "sg:address":"18 Cobbs Rd",
    "sg:city":"Woombye",
    "sg:classifiers":[
        {
            "category":"Education",
            "subcategory":"Music School",
            "type":"Public Place"
        }
    ],
    "sg:phone":"+61 7 5442 1281",
    "sg:postcode":"4559",
    "sg:province":"QLD",
    "sg:tags":[
        "teacher"
    ],
    "wof:name":"Dixon Robyn",
    "wof:placetype":"venue"
},
  "geometry": {"coordinates":[152.961303711,-26.6497135162],"type":"Point"}
}