{
  "type": "Feature",
  "properties": {
    "addr:full":"5 Keswick St Banyo QLD 4014",
    "addr:housenumber":"5",
    "addr:postcode":"4014",
    "addr:street":"Keswick St",
    "iso:country":"AU",
    "sg:address":"5 Keswick St",
    "sg:city":"Banyo",
    "sg:classifiers":[
        {
            "category":"Professional",
            "subcategory":"Art Services",
            "type":"Services"
        }
    ],
    "sg:phone":"+61 7 3267 0454",
    "sg:postcode":"4014",
    "sg:province":"QLD",
    "sg:tags":[
        "decorator",
        "painter"
    ],
    "wof:name":"Robert Ian",
    "wof:placetype":"venue"
},
  "geometry": {"coordinates":[153.078033447,-27.3692626953],"type":"Point"}
}