{
  "type": "Feature",
  "properties": {
    "addr:full":"6 Princes St Newport NSW 2106",
    "addr:housenumber":"6",
    "addr:postcode":"2106",
    "addr:street":"Princes St",
    "iso:country":"AU",
    "sg:address":"6 Princes St",
    "sg:city":"Newport",
    "sg:classifiers":[
        {
            "category":"Autos & Motor Vehicles",
            "subcategory":"Boat Sales",
            "type":"Retail Goods"
        }
    ],
    "sg:phone":"+61 2 9999 1486",
    "sg:postcode":"2106",
    "sg:province":"NSW",
    "sg:tags":[
        "equipment",
        "yacht"
    ],
    "wof:name":"Letts Trading Co",
    "wof:placetype":"venue"
},
  "geometry": {"coordinates":[151.30862426799999,-33.6574516296],"type":"Point"}
}