{
  "type": "Feature",
  "properties": {
    "addr:full":"59 Maitland St Branxton NSW 2335",
    "addr:housenumber":"59",
    "addr:postcode":"2335",
    "addr:street":"Maitland St",
    "iso:country":"AU",
    "sg:address":"59 Maitland St",
    "sg:city":"Branxton",
    "sg:classifiers":[
        {
            "category":"Building & Trades",
            "subcategory":"Construction",
            "type":"Services"
        }
    ],
    "sg:phone":"+61 2 4938 1425",
    "sg:postcode":"2335",
    "sg:province":"NSW",
    "sg:tags":[
        "industrial",
        "commercial",
        "air conditioning"
    ],
    "wof:name":"Branxair Clemeco Pty Ltd",
    "wof:placetype":"venue"
},
  "geometry": {"coordinates":[151.352050781,-32.6558151245],"type":"Point"}
}