{
  "type": "Feature",
  "properties": {
    "iso:country":"AU",
    "sg:address":"PO Box 7726",
    "sg:city":"Bondi Beach",
    "sg:classifiers":[
        {
            "category":"Professional",
            "subcategory":"Accounting & Tax Preparation",
            "type":"Services"
        }
    ],
    "sg:phone":"+61 419 755 500",
    "sg:postcode":"2026",
    "sg:province":"NSW",
    "sg:tags":[
        "consultant",
        "taxation"
    ],
    "wof:name":"Tax Services Australia",
    "wof:placetype":"venue"
},
  "geometry": {"coordinates":[151.277786255,-33.8887290955],"type":"Point"}
}