{
  "type": "Feature",
  "properties": {
    "iso:country":"AU",
    "sg:address":"Casino St",
    "sg:city":"Glenwood",
    "sg:classifiers":[
        {
            "category":"Building & Trades",
            "subcategory":"Construction",
            "type":"Services"
        }
    ],
    "sg:phone":"+61 414 390 577",
    "sg:postcode":"2768",
    "sg:province":"NSW",
    "sg:tags":[
        "contractor"
    ],
    "wof:name":"Neo-Way Pty Ltd",
    "wof:placetype":"venue"
},
  "geometry": {"coordinates":[150.934982,-33.734005],"type":"Point"}
}