{
  "type": "Feature",
  "properties": {
    "addr:full":"28 Kendella Pde Kahibah NSW 2290",
    "addr:housenumber":"28",
    "addr:postcode":"2290",
    "addr:street":"Kendella Pde",
    "iso:country":"AU",
    "sg:address":"28 Kendella Pde",
    "sg:city":"Kahibah",
    "sg:classifiers":[
        {
            "category":"Professional",
            "subcategory":"Printing & Photocopies",
            "type":"Services"
        }
    ],
    "sg:phone":"+61 2 4943 7693",
    "sg:postcode":"2290",
    "sg:province":"NSW",
    "sg:tags":[
        "rubber",
        "stamp",
        "metal"
    ],
    "wof:name":"Chandelier Printing",
    "wof:placetype":"venue"
},
  "geometry": {"coordinates":[151.70860290499999,-32.956817627],"type":"Point"}
}