{
  "type": "Feature",
  "properties": {
    "iso:country":"AU",
    "sg:address":"25 Merion Crt",
    "sg:city":"Robina",
    "sg:classifiers":[
        {
            "category":"Professional",
            "subcategory":"Accounting & Tax Preparation",
            "type":"Services"
        }
    ],
    "sg:phone":"+61 7 5593 1681",
    "sg:postcode":"4226",
    "sg:province":"QLD",
    "sg:tags":[
        "bookkeeping"
    ],
    "wof:name":"Bookkeeping Specialists",
    "wof:placetype":"venue"
},
  "geometry": {"coordinates":[153.39653015100001,-28.0732154846],"type":"Point"}
}