{
  "type": "Feature",
  "properties": {
    "iso:country":"AU",
    "sg:address":"1- 7 Lloyd St",
    "sg:city":"Kensington",
    "sg:classifiers":[
        {
            "category":"Wholesale",
            "subcategory":"Seafood",
            "type":"Manufacturing & Wholesale Goods"
        }
    ],
    "sg:phone":"+61 3 9376 7133",
    "sg:postcode":"3031",
    "sg:province":"VIC",
    "sg:tags":[
        "fish"
    ],
    "wof:name":"United Seafood",
    "wof:placetype":"venue"
},
  "geometry": {"coordinates":[144.931747,-37.801468],"type":"Point"}
}