{
  "type": "Feature",
  "properties": {
    "iso:country":"AU",
    "sg:address":"Suite 1 / 15 Vere St",
    "sg:city":"Collingwood",
    "sg:classifiers":[
        {
            "category":"Professional",
            "subcategory":"Printing & Photocopies",
            "type":"Services"
        }
    ],
    "sg:phone":"+61 3 9415 9600",
    "sg:postcode":"3066",
    "sg:province":"VIC",
    "sg:tags":[
        "textile",
        "clothing"
    ],
    "wof:name":"Super Special",
    "wof:placetype":"venue"
},
  "geometry": {"coordinates":[144.988006592,-37.8021736145],"type":"Point"}
}