{
  "type": "Feature",
  "properties": {
    "addr:full":"25/ 9 Hudson Ave Baulkham Hills NSW 2153",
    "addr:housenumber":"25 / 9",
    "addr:postcode":"2153",
    "addr:street":"Hudson Ave",
    "iso:country":"AU",
    "sg:address":"25/ 9 Hudson Ave",
    "sg:city":"Baulkham Hills",
    "sg:classifiers":[
        {
            "category":"Professional",
            "subcategory":"Detective & Security Services",
            "type":"Services"
        }
    ],
    "sg:phone":"+61 1300 658 809",
    "sg:postcode":"2153",
    "sg:province":"NSW",
    "sg:tags":[
        "guard",
        "patrol"
    ],
    "wof:name":"Abacus Security & Surveillance Pty Ltd",
    "wof:placetype":"venue"
},
  "geometry": {"coordinates":[150.97482299800001,-33.7295227051],"type":"Point"}
}