{
  "type": "Feature",
  "properties": {
    "addr:full":"PO Box 13 Montrose VIC 3765",
    "addr:postcode":"3765",
    "iso:country":"AU",
    "sg:address":"PO Box 13",
    "sg:city":"Montrose",
    "sg:classifiers":[
        {
            "category":"Building & Trades",
            "subcategory":"Construction",
            "type":"Services"
        }
    ],
    "sg:phone":"+61 3 9761 8011",
    "sg:postcode":"3765",
    "sg:province":"VIC",
    "sg:tags":[
        "window",
        "tinting"
    ],
    "wof:name":"High Performance Films Commercial",
    "wof:placetype":"venue"
},
  "geometry": {"coordinates":[145.34880065900001,-37.8171806335],"type":"Point"}
}