{
  "type": "Feature",
  "properties": {
    "addr:full":"150 Lime Ave Mildura VIC 3500",
    "addr:housenumber":"150",
    "addr:postcode":"3500",
    "addr:street":"Lime Ave",
    "iso:country":"AU",
    "sg:address":"150 Lime Ave",
    "sg:city":"Mildura",
    "sg:classifiers":[
        {
            "category":"Professional",
            "subcategory":"Accounting & Tax Preparation",
            "type":"Services"
        }
    ],
    "sg:phone":"+61 3 5023 7789",
    "sg:postcode":"3500",
    "sg:province":"VIC",
    "sg:tags":[
        "bookkeeping"
    ],
    "wof:name":"Sue Laird Bookkeeping",
    "wof:placetype":"venue"
},
  "geometry": {"coordinates":[142.156005859,-34.18724823],"type":"Point"}
}