{
  "type": "Feature",
  "properties": {
    "iso:country":"AU",
    "sg:address":"265 Greenwattle St",
    "sg:city":"Toowoomba",
    "sg:classifiers":[
        {
            "category":"Health Services",
            "subcategory":"Health Practitioner",
            "type":"Services"
        }
    ],
    "sg:phone":"+61 7 4634 2025",
    "sg:postcode":"4350",
    "sg:province":"QLD",
    "sg:tags":[
        "acupuncture"
    ],
    "wof:name":"NG James",
    "wof:placetype":"venue"
},
  "geometry": {"coordinates":[151.91468800000001,-27.567446],"type":"Point"}
}