{
  "type": "Feature",
  "properties": {
    "iso:country":"AU",
    "sg:address":"8 Kingsway Ave",
    "sg:city":"Rankin Park",
    "sg:classifiers":[
        {
            "category":"Professional",
            "subcategory":"Art Services",
            "type":"Services"
        }
    ],
    "sg:phone":"+61 2 4956 3160",
    "sg:postcode":"2287",
    "sg:province":"NSW",
    "sg:tags":[
        "decorator",
        "painter"
    ],
    "wof:name":"P & L Woolmer",
    "wof:placetype":"venue"
},
  "geometry": {"coordinates":[151.68605041500001,-32.9276809692],"type":"Point"}
}