{
  "type": "Feature",
  "properties": {
    "addr:full":"Unit 3/ 39 Hugh Ryan Drv Garbutt QLD 4814",
    "addr:housenumber":"39",
    "addr:postcode":"4814",
    "addr:street":"Hugh Ryan Drv",
    "iso:country":"AU",
    "sg:address":"Unit 3/ 39 Hugh Ryan Drv",
    "sg:city":"Garbutt",
    "sg:classifiers":[
        {
            "category":"Manufacturing",
            "subcategory":"Tools & Machinery",
            "type":"Manufacturing & Wholesale Goods"
        }
    ],
    "sg:phone":"+61 7 4725 7799",
    "sg:postcode":"4814",
    "sg:province":"QLD",
    "sg:tags":[
        "fastener",
        "industrial"
    ],
    "wof:name":"Townsville Fasteners",
    "wof:placetype":"venue"
},
  "geometry": {"coordinates":[146.7621,-19.271032],"type":"Point"}
}