{
  "type": "Feature",
  "properties": {
    "iso:country":"AU",
    "sg:address":"30 Mulgrave St",
    "sg:city":"South Launceston",
    "sg:classifiers":[
        {
            "category":"Personal",
            "subcategory":"Massage",
            "type":"Services"
        }
    ],
    "sg:phone":"+61 3 6344 7115",
    "sg:postcode":"7249",
    "sg:province":"TAS",
    "sg:tags":[
        "therapy"
    ],
    "wof:name":"Healing Hands Massage & Natural Therapies",
    "wof:placetype":"venue"
},
  "geometry": {"coordinates":[147.14614868199999,-41.4489059448],"type":"Point"}
}