{
  "type": "Feature",
  "properties": {
    "iso:country":"AU",
    "sg:address":"Henty Hwy",
    "sg:city":"Beulah",
    "sg:classifiers":[
        {
            "category":"Education",
            "subcategory":"School",
            "type":"Public Place"
        }
    ],
    "sg:phone":"+61 3 5390 2332",
    "sg:postcode":"3395",
    "sg:province":"VIC",
    "sg:tags":[
        "state",
        "except",
        "nsw"
    ],
    "wof:name":"Beulah Primary School",
    "wof:placetype":"venue"
},
  "geometry": {"coordinates":[142.41928100600001,-35.9449882507],"type":"Point"}
}