{
  "type": "Feature",
  "properties": {
    "addr:full":"Level 1 Westfield Shoppingtown 175 Church St Parramatta NSW 2150",
    "addr:housenumber":"175",
    "addr:postcode":"2150",
    "addr:street":"Church St",
    "iso:country":"AU",
    "sg:address":"Level 1 Westfield Shoppingtown 175 Church St",
    "sg:city":"Parramatta",
    "sg:classifiers":[
        {
            "category":"Shopping",
            "subcategory":"Clothing, Apparel, & Fashions",
            "type":"Retail Goods"
        }
    ],
    "sg:phone":"+61 2 9841 3555",
    "sg:postcode":"2150",
    "sg:province":"NSW",
    "sg:tags":[
        "lady",
        "wear"
    ],
    "wof:name":"Esprit Retail Pty Ltd",
    "wof:placetype":"venue"
},
  "geometry": {"coordinates":[151.11903381400001,-33.8752593994],"type":"Point"}
}