{
  "type": "Feature",
  "properties": {
    "addr:full":"15 Freeburgh Ave Mt Beauty VIC 3699",
    "addr:housenumber":"15",
    "addr:postcode":"3699",
    "addr:street":"Freeburgh Ave",
    "iso:country":"AU",
    "sg:address":"15 Freeburgh Ave",
    "sg:city":"Mt Beauty",
    "sg:classifiers":[
        {
            "category":"Taxi",
            "type":"Transportation"
        }
    ],
    "sg:phone":"+61 3 5754 4735",
    "sg:postcode":"3699",
    "sg:province":"VIC",
    "sg:tags":[
        "cab"
    ],
    "wof:name":"Mount Beauty Taxi Service",
    "wof:placetype":"venue"
},
  "geometry": {"coordinates":[147.17649841299999,-36.7334365845],"type":"Point"}
}