{
  "type": "Feature",
  "properties": {
    "addr:full":"Centre Cnr Ferntree Gully Rd & Burwood Hwy Ferntree Gully VIC 3156",
    "addr:postcode":"3156",
    "addr:street":"Ferntree Gully Rd & Burwood Hwy",
    "iso:country":"AU",
    "sg:address":"Centre Cnr Ferntree Gully Rd & Burwood Hwy",
    "sg:city":"Ferntree Gully",
    "sg:classifiers":[
        {
            "category":"Real Estate",
            "subcategory":"Real Estate Agent",
            "type":"Services"
        }
    ],
    "sg:phone":"+61 3 9758 9900",
    "sg:postcode":"3156",
    "sg:province":"VIC",
    "wof:name":"Stockdale & Leggo (Mountain Gate) Pty Ltd",
    "wof:placetype":"venue"
},
  "geometry": {"coordinates":[145.27755737300001,-37.8827362061],"type":"Point"}
}