{
  "type": "Feature",
  "properties": {
    "addr:full":"29 York Rd Penrith NSW 2750",
    "addr:housenumber":"29",
    "addr:postcode":"2750",
    "addr:street":"York Rd",
    "iso:country":"AU",
    "sg:address":"29 York Rd",
    "sg:city":"Penrith",
    "sg:classifiers":[
        {
            "category":"Government",
            "subcategory":"Fire Station",
            "type":"Public Place"
        }
    ],
    "sg:phone":"+61 2 4731 2444",
    "sg:postcode":"2750",
    "sg:province":"NSW",
    "sg:tags":[
        "spring",
        "shock",
        "absorbers",
        "suspension"
    ],
    "wof:name":"Pedders Suspension",
    "wof:placetype":"venue"
},
  "geometry": {"coordinates":[150.688598633,-33.7637329102],"type":"Point"}
}