{
  "type": "Feature",
  "properties": {
    "addr:full":"34 Condover St North Balgowlah NSW 2093",
    "addr:housenumber":"34",
    "addr:postcode":"2093",
    "addr:street":"Condover St",
    "iso:country":"AU",
    "sg:address":"34 Condover St",
    "sg:city":"North Balgowlah",
    "sg:classifiers":[
        {
            "category":"Personal",
            "subcategory":"Massage",
            "type":"Services"
        }
    ],
    "sg:phone":"+61 2 9948 7638",
    "sg:postcode":"2093",
    "sg:province":"NSW",
    "sg:tags":[
        "therapy"
    ],
    "wof:name":"EveryBody Professional Beauty",
    "wof:placetype":"venue"
},
  "geometry": {"coordinates":[151.25831604000001,-33.7870445251],"type":"Point"}
}