{
  "type": "Feature",
  "properties": {
    "iso:country":"AU",
    "sg:address":"248 Flinders St",
    "sg:city":"Adelaide",
    "sg:classifiers":[
        {
            "category":"Professional",
            "subcategory":"Accounting & Tax Preparation",
            "type":"Services"
        }
    ],
    "sg:phone":"+61 1300 138 991",
    "sg:postcode":"5000",
    "sg:province":"SA",
    "sg:tags":[
        "consultant",
        "taxation"
    ],
    "wof:name":"BDO",
    "wof:placetype":"venue"
},
  "geometry": {"coordinates":[138.60963439899999,-34.9265327454],"type":"Point"}
}