{
  "type": "Feature",
  "properties": {
    "iso:country":"AU",
    "sg:address":"Factory La",
    "sg:city":"Allansford",
    "sg:classifiers":[
        {
            "category":"Home & Garden",
            "subcategory":"Garden Supply",
            "type":"Retail Goods"
        }
    ],
    "sg:phone":"+61 3 5565 1424",
    "sg:postcode":"3277",
    "sg:province":"VIC",
    "sg:tags":[
        "fertilizer"
    ],
    "wof:name":"White E T & D A",
    "wof:placetype":"venue"
},
  "geometry": {"coordinates":[142.618484497,-38.3982582092],"type":"Point"}
}