{
  "type": "Feature",
  "properties": {
    "iso:country":"AU",
    "sg:address":"72 Bathurst St",
    "sg:city":"Sydney",
    "sg:classifiers":[
        {
            "category":"Education",
            "subcategory":"Dance Studio",
            "type":"Public Place"
        }
    ],
    "sg:phone":"+61 2 9264 2781",
    "sg:postcode":"2000",
    "sg:province":"NSW",
    "sg:tags":[
        "instruction",
        "language"
    ],
    "sg:website":"http://www.weasydney.nsw.edu.au",
    "wof:name":"WEA Sydney",
    "wof:placetype":"venue"
},
  "geometry": {"coordinates":[151.20460510300001,-33.874004364],"type":"Point"}
}