{
  "type": "Feature",
  "properties": {
    "iso:country":"AU",
    "sg:address":"30 Katoomba Crs",
    "sg:city":"Toowoomba",
    "sg:classifiers":[
        {
            "category":"Real Estate",
            "subcategory":"Developer",
            "type":"Services"
        }
    ],
    "sg:phone":"+61 7 4638 3552",
    "sg:postcode":"4350",
    "sg:province":"QLD",
    "sg:tags":[
        "development"
    ],
    "wof:name":"Blueford Pty Ltd",
    "wof:placetype":"venue"
},
  "geometry": {"coordinates":[151.875641,-27.55761],"type":"Point"}
}