{
  "type": "Feature",
  "properties": {
    "addr:full":"22 Royal St Kenwick WA 6107",
    "addr:housenumber":"22",
    "addr:postcode":"6107",
    "addr:street":"Royal St",
    "iso:country":"AU",
    "sg:address":"22 Royal St",
    "sg:city":"Kenwick",
    "sg:classifiers":[
        {
            "category":"Retail",
            "subcategory":"Auto Repair",
            "type":"Services"
        }
    ],
    "sg:phone":"+61 8 9493 3170",
    "sg:postcode":"6107",
    "sg:province":"WA",
    "sg:tags":[
        "repairer",
        "motor",
        "engineer"
    ],
    "wof:name":"Thornlie Automotives",
    "wof:placetype":"venue"
},
  "geometry": {"coordinates":[115.967887878,-32.0388679504],"type":"Point"}
}