{
  "type": "Feature",
  "properties": {
    "addr:full":"PO Box 1053 Roma QLD 4455",
    "addr:postcode":"4455",
    "iso:country":"AU",
    "sg:address":"PO Box 1053",
    "sg:city":"Roma",
    "sg:classifiers":[
        {
            "category":"Farming",
            "subcategory":"Farm & Veterinary Services",
            "type":"Manufacturing & Wholesale Goods"
        }
    ],
    "sg:phone":"+61 7 4622 3425",
    "sg:postcode":"4455",
    "sg:province":"QLD",
    "sg:tags":[
        "contracting"
    ],
    "wof:name":"Burey Seed Cleaning",
    "wof:placetype":"venue"
},
  "geometry": {"coordinates":[148.78732299800001,-26.5734291077],"type":"Point"}
}