{
  "type": "Feature",
  "properties": {
    "addr:full":"61 Plantain Rd Shailer Park QLD 4128",
    "addr:housenumber":"61",
    "addr:postcode":"4128",
    "addr:street":"Plantain Rd",
    "iso:country":"AU",
    "sg:address":"61 Plantain Rd",
    "sg:city":"Shailer Park",
    "sg:classifiers":[
        {
            "category":"Building & Trades",
            "subcategory":"Construction",
            "type":"Services"
        }
    ],
    "sg:phone":"+61 7 3801 3149",
    "sg:postcode":"4128",
    "sg:province":"QLD",
    "sg:tags":[
        "contractor"
    ],
    "wof:name":"Arm Builders",
    "wof:placetype":"venue"
},
  "geometry": {"coordinates":[153.18765258799999,-27.6578502655],"type":"Point"}
}