{
  "type": "Feature",
  "properties": {
    "addr:full":"17 Ellingworth Pde Box Hill VIC 3128",
    "addr:housenumber":"17",
    "addr:postcode":"3128",
    "addr:street":"Ellingworth Pde",
    "iso:country":"AU",
    "sg:address":"17 Ellingworth Pde",
    "sg:city":"Box Hill",
    "sg:classifiers":[
        {
            "category":"Professional",
            "subcategory":"Accounting & Tax Preparation",
            "type":"Services"
        }
    ],
    "sg:phone":"+61 3 9899 1980",
    "sg:postcode":"3128",
    "sg:province":"VIC",
    "sg:tags":[
        "accountant",
        "auditor"
    ],
    "wof:name":"Hutchins J A",
    "wof:placetype":"venue"
},
  "geometry": {"coordinates":[145.12504577600001,-37.8204727173],"type":"Point"}
}