{
  "type": "Feature",
  "properties": {
    "addr:full":"17 Albert St Lake Illawarra NSW 2528",
    "addr:housenumber":"17",
    "addr:postcode":"2528",
    "addr:street":"Albert St",
    "iso:country":"AU",
    "sg:address":"17 Albert St",
    "sg:city":"Lake Illawarra",
    "sg:classifiers":[
        {
            "category":"Building & Trades",
            "subcategory":"Construction",
            "type":"Services"
        }
    ],
    "sg:phone":"+61 2 4297 5150",
    "sg:postcode":"2528",
    "sg:province":"NSW",
    "sg:tags":[
        "brick",
        "paving"
    ],
    "wof:name":"Illawarra Lakeside Landscapes",
    "wof:placetype":"venue"
},
  "geometry": {"coordinates":[150.858322144,-34.5440406799],"type":"Point"}
}