{
  "type": "Feature",
  "properties": {
    "addr:full":"34 Somerset Drv North Rocks NSW 2151",
    "addr:housenumber":"34",
    "addr:postcode":"2151",
    "addr:street":"Somerset Drv",
    "iso:country":"AU",
    "sg:address":"34 Somerset Drv",
    "sg:city":"North Rocks",
    "sg:classifiers":[
        {
            "category":"Real Estate",
            "subcategory":"Architect",
            "type":"Services"
        }
    ],
    "sg:phone":"+61 2 9871 0330",
    "sg:postcode":"2151",
    "sg:province":"NSW",
    "sg:tags":[
        "naval"
    ],
    "wof:name":"Makin Consulting Pty Ltd",
    "wof:placetype":"venue"
},
  "geometry": {"coordinates":[151.022750855,-33.7770805359],"type":"Point"}
}