{
  "type": "Feature",
  "properties": {
    "iso:country":"AU",
    "sg:address":"19 Stanley St",
    "sg:city":"Capalaba",
    "sg:classifiers":[
        {
            "category":"Manufacturing",
            "subcategory":"Rubber & Plastics",
            "type":"Manufacturing & Wholesale Goods"
        }
    ],
    "sg:phone":"+61 7 3245 2655",
    "sg:postcode":"4157",
    "sg:province":"QLD",
    "sg:tags":[
        "wholesaler",
        "product",
        "mfrs"
    ],
    "wof:name":"Polycube Australia",
    "wof:placetype":"venue"
},
  "geometry": {"coordinates":[153.19671630900001,-27.5570259094],"type":"Point"}
}