{
  "type": "Feature",
  "properties": {
    "addr:full":"3 Hope St Waterman WA 6020",
    "addr:housenumber":"3",
    "addr:postcode":"6020",
    "addr:street":"Hope St",
    "iso:country":"AU",
    "sg:address":"3 Hope St",
    "sg:city":"Waterman",
    "sg:classifiers":[
        {
            "category":"Real Estate",
            "subcategory":"Real Estate Agent",
            "type":"Services"
        }
    ],
    "sg:phone":"+61 412 226 377",
    "sg:postcode":"6020",
    "sg:province":"WA",
    "wof:name":"Shean Bill",
    "wof:placetype":"venue"
},
  "geometry": {"coordinates":[115.757980347,-31.8487644196],"type":"Point"}
}