{
  "type": "Feature",
  "properties": {
    "addr:full":"80 Queen St Woollahra NSW 2025",
    "addr:housenumber":"80",
    "addr:postcode":"2025",
    "addr:street":"Queen St",
    "iso:country":"AU",
    "sg:address":"80 Queen St",
    "sg:city":"Woollahra",
    "sg:classifiers":[
        {
            "category":"Shopping",
            "subcategory":"Antiques",
            "type":"Retail Goods"
        }
    ],
    "sg:phone":"+61 2 9363 2817",
    "sg:postcode":"2025",
    "sg:province":"NSW",
    "wof:name":"Art Of Wine & Food The",
    "wof:placetype":"venue"
},
  "geometry": {"coordinates":[151.23573303200001,-33.8885726929],"type":"Point"}
}