{
  "type": "Feature",
  "properties": {
    "addr:full":"Ste5/ 461 High St Penrith NSW 2751",
    "addr:housenumber":"461",
    "addr:postcode":"2751",
    "addr:street":"High St",
    "iso:country":"AU",
    "sg:address":"Ste5/ 461 High St",
    "sg:city":"Penrith",
    "sg:classifiers":[
        {
            "category":"Shopping",
            "subcategory":"Stationery & Office Supplies",
            "type":"Retail Goods"
        }
    ],
    "sg:phone":"+61 1300 368 021",
    "sg:postcode":"2751",
    "sg:province":"NSW",
    "wof:name":"Franksmart",
    "wof:placetype":"venue"
},
  "geometry": {"coordinates":[150.915557861,-33.8949508667],"type":"Point"}
}