{
  "type": "Feature",
  "properties": {
    "iso:country":"AU",
    "sg:address":"22 Main St",
    "sg:city":"Littlehampton",
    "sg:classifiers":[
        {
            "category":"Manufacturing",
            "subcategory":"Food",
            "type":"Manufacturing & Wholesale Goods"
        }
    ],
    "sg:phone":"+61 412 479 345",
    "sg:postcode":"5250",
    "sg:province":"SA",
    "sg:tags":[
        "function",
        "catering"
    ],
    "wof:name":"Dial A Roast",
    "wof:placetype":"venue"
},
  "geometry": {"coordinates":[138.853713989,-35.0545082092],"type":"Point"}
}