{
  "type": "Feature",
  "properties": {
    "iso:country":"AU",
    "sg:address":"2/ 12 Christensen Rd",
    "sg:city":"Stapylton",
    "sg:classifiers":[
        {
            "category":"Autos & Motor Vehicles",
            "subcategory":"Auto Supplies",
            "type":"Retail Goods"
        }
    ],
    "sg:phone":"+61 7 3804 6311",
    "sg:postcode":"4207",
    "sg:province":"QLD",
    "sg:tags":[
        "part",
        "cycles",
        "accessory"
    ],
    "wof:name":"T Js Performance Motorcycle Centre",
    "wof:placetype":"venue"
},
  "geometry": {"coordinates":[153.23080444300001,-27.7358760834],"type":"Point"}
}