{
  "type": "Feature",
  "properties": {
    "addr:full":"248 New Cleveland Rd Tingalpa QLD 4173",
    "addr:housenumber":"248",
    "addr:postcode":"4173",
    "addr:street":"New Cleveland Rd",
    "iso:country":"AU",
    "sg:address":"248 New Cleveland Rd",
    "sg:city":"Tingalpa",
    "sg:classifiers":[
        {
            "category":"Manufacturing",
            "subcategory":"Motor Vehicles & Parts",
            "type":"Manufacturing & Wholesale Goods"
        }
    ],
    "sg:phone":"+61 7 3390 6133",
    "sg:postcode":"4173",
    "sg:province":"QLD",
    "sg:tags":[
        "replacement"
    ],
    "wof:name":"Action Auto Dismantlers",
    "wof:placetype":"venue"
},
  "geometry": {"coordinates":[153.140914917,-27.4760303497],"type":"Point"}
}