{
  "type": "Feature",
  "properties": {
    "iso:country":"AU",
    "sg:address":"58 Beach Rd",
    "sg:city":"Bunbury",
    "sg:classifiers":[
        {
            "category":"Government",
            "subcategory":"Court House",
            "type":"Public Place"
        }
    ],
    "sg:phone":"+61 8 9721 2457",
    "sg:postcode":"6230",
    "sg:province":"WA",
    "sg:tags":[
        "personal",
        "marriage",
        "family",
        "counselling"
    ],
    "wof:name":"Joy Simpson and Associates.",
    "wof:placetype":"venue"
},
  "geometry": {"coordinates":[115.638779,-33.335823],"type":"Point"}
}