{
  "type": "Feature",
  "properties": {
    "addr:full":"Central Mall Lowe St Nambour QLD 4560",
    "addr:postcode":"4560",
    "addr:street":"Lowe St",
    "iso:country":"AU",
    "sg:address":"Central Mall Lowe St",
    "sg:city":"Nambour",
    "sg:classifiers":[
        {
            "category":"Banks & Credit Unions",
            "subcategory":"Bank",
            "type":"Services"
        }
    ],
    "sg:phone":"+61 7 5459 2000",
    "sg:postcode":"4560",
    "sg:province":"QLD",
    "wof:name":"Wide Bay Australia Ltd",
    "wof:placetype":"venue"
},
  "geometry": {"coordinates":[152.960403442,-26.6258125305],"type":"Point"}
}