{
  "type": "Feature",
  "properties": {
    "iso:country":"AU",
    "sg:address":"39 Taunton Drv",
    "sg:city":"Cheltenham",
    "sg:classifiers":[
        {
            "category":"Train Station",
            "subcategory":"Light Rail",
            "type":"Transportation"
        }
    ],
    "sg:phone":"+61 3 8586 3444",
    "sg:postcode":"3192",
    "sg:province":"VIC",
    "sg:tags":[
        "searchlight"
    ],
    "sg:website":"http://www.phaseshiftproductions.com",
    "wof:name":"Phaseshift Productions",
    "wof:placetype":"venue"
},
  "geometry": {"coordinates":[145.08424377399999,-37.972240448],"type":"Point"}
}