{
  "type": "Feature",
  "properties": {
    "addr:full":"116 Briggs St Welshpool WA 6106",
    "addr:housenumber":"116",
    "addr:postcode":"6106",
    "addr:street":"Briggs St",
    "iso:country":"AU",
    "sg:address":"116 Briggs St",
    "sg:city":"Welshpool",
    "sg:classifiers":[
        {
            "category":"Autos & Motor Vehicles",
            "subcategory":"Automobile Sales",
            "type":"Retail Goods"
        }
    ],
    "sg:phone":"+61 8 9362 6996",
    "sg:postcode":"6106",
    "sg:province":"WA",
    "sg:tags":[
        "equipment",
        "trailer"
    ],
    "wof:name":"Wanderer Trailers",
    "wof:placetype":"venue"
},
  "geometry": {"coordinates":[115.92900848399999,-31.9822044373],"type":"Point"}
}