{
  "type": "Feature",
  "properties": {
    "addr:full":"U 12/ 22 Mavis St Revesby NSW 2212",
    "addr:housenumber":"12 / 22",
    "addr:postcode":"2212",
    "addr:street":"Mavis St",
    "iso:country":"AU",
    "sg:address":"U 12/ 22 Mavis St",
    "sg:city":"Revesby",
    "sg:classifiers":[
        {
            "category":"Home & Garden",
            "subcategory":"Carpets & Floor Coverings",
            "type":"Retail Goods"
        }
    ],
    "sg:phone":"+61 2 9793 2258",
    "sg:postcode":"2212",
    "sg:province":"NSW",
    "sg:tags":[
        "tile",
        "wall"
    ],
    "wof:name":"Marisol Holdings Pty Ltd",
    "wof:placetype":"venue"
},
  "geometry": {"coordinates":[151.01869199999999,-33.936134],"type":"Point"}
}