{
  "type": "Feature",
  "properties": {
    "iso:country":"AU",
    "sg:address":"PO Box 768",
    "sg:city":"Sanderson",
    "sg:classifiers":[
        {
            "category":"Building & Trades",
            "subcategory":"Plumbing",
            "type":"Services"
        }
    ],
    "sg:phone":"+61 408 018 701",
    "sg:postcode":"0813",
    "sg:province":"NT",
    "sg:tags":[
        "plumber",
        "gasfitters"
    ],
    "wof:name":"Ausplumb",
    "wof:placetype":"venue"
},
  "geometry": {"coordinates":[130.89891052199999,-12.3905000687],"type":"Point"}
}