{
  "type": "Feature",
  "properties": {
    "iso:country":"AU",
    "sg:address":"Shop 619, 239- 241 Maroondah Hwy",
    "sg:city":"Chirnside Park",
    "sg:classifiers":[
        {
            "category":"Shopping",
            "subcategory":"Mobile Phones",
            "type":"Retail Goods"
        }
    ],
    "sg:phone":"+61 3 9727 3222",
    "sg:postcode":"3116",
    "sg:province":"VIC",
    "sg:tags":[
        "telephone",
        "accessory"
    ],
    "wof:name":"Telstra Shop",
    "wof:placetype":"venue"
},
  "geometry": {"coordinates":[145.355072022,-37.7574462891],"type":"Point"}
}