{
  "type": "Feature",
  "properties": {
    "iso:country":"AU",
    "sg:address":"50 Athol Rd",
    "sg:city":"Noble Park",
    "sg:classifiers":[
        {
            "category":"Building & Trades",
            "subcategory":"Construction",
            "type":"Services"
        }
    ],
    "sg:phone":"+61 3 9548 4390",
    "sg:postcode":"3174",
    "sg:province":"VIC",
    "sg:tags":[
        "fencing",
        "contractor"
    ],
    "wof:name":"Nu Fence & Gates",
    "wof:placetype":"venue"
},
  "geometry": {"coordinates":[145.161346436,-37.9727020264],"type":"Point"}
}