{
  "type": "Feature",
  "properties": {
    "addr:full":"15 Mallett Rd Tullamarine VIC 3043",
    "addr:housenumber":"15",
    "addr:postcode":"3043",
    "addr:street":"Mallett Rd",
    "iso:country":"AU",
    "sg:address":"15 Mallett Rd",
    "sg:city":"Tullamarine",
    "sg:classifiers":[
        {
            "category":"Wholesale",
            "subcategory":"Furniture",
            "type":"Manufacturing & Wholesale Goods"
        }
    ],
    "sg:phone":"+61 3 9330 2933",
    "sg:postcode":"3043",
    "sg:province":"VIC",
    "sg:tags":[
        "wholesaler",
        "mfrs"
    ],
    "wof:name":"September Imports Pty Ltd",
    "wof:placetype":"venue"
},
  "geometry": {"coordinates":[144.84982299800001,-37.706905365],"type":"Point"}
}