{
  "type": "Feature",
  "properties": {
    "addr:full":"423- 425 High St Maitland NSW 2320",
    "addr:housenumber":"425",
    "addr:postcode":"2320",
    "addr:street":"High St",
    "iso:country":"AU",
    "sg:address":"423- 425 High St",
    "sg:city":"Maitland",
    "sg:classifiers":[
        {
            "category":"Shopping",
            "subcategory":"Department Store",
            "type":"Retail Goods"
        }
    ],
    "sg:phone":"+61 2 4933 8244",
    "sg:postcode":"2320",
    "sg:province":"NSW",
    "wof:name":"Best & Less Retail Stores",
    "wof:placetype":"venue"
},
  "geometry": {"coordinates":[151.55458068900001,-32.7317466736],"type":"Point"}
}