{
  "type": "Feature",
  "properties": {
    "iso:country":"AU",
    "sg:address":"Suite 6/ 63 Stud Rd",
    "sg:city":"Bayswater",
    "sg:classifiers":[
        {
            "category":"Food & Beverages",
            "subcategory":"Fruits & Vegetables",
            "type":"Retail Goods"
        }
    ],
    "sg:phone":"+61 3 9729 3129",
    "sg:postcode":"3153",
    "sg:province":"VIC",
    "sg:tags":[
        "wholesale"
    ],
    "wof:name":"Maxwell Food Products Pty Ltd",
    "wof:placetype":"venue"
},
  "geometry": {"coordinates":[145.246536255,-37.847946167],"type":"Point"}
}