{
  "type": "Feature",
  "properties": {
    "iso:country":"AU",
    "sg:address":"148 Rooks Rd",
    "sg:city":"Nunawading",
    "sg:classifiers":[
        {
            "category":"Personal",
            "subcategory":"Beauty Salon",
            "type":"Services"
        }
    ],
    "sg:phone":"+61 3 9873 7797",
    "sg:postcode":"3131",
    "sg:province":"VIC",
    "sg:tags":[
        "hairdresser"
    ],
    "wof:name":"Secrets On Rooks Hair & Beauty",
    "wof:placetype":"venue"
},
  "geometry": {"coordinates":[145.186813355,-37.8301467896],"type":"Point"}
}