{
  "type": "Feature",
  "properties": {
    "iso:country":"AU",
    "sg:address":"71 Addison Rd",
    "sg:city":"Marrickville",
    "sg:classifiers":[
        {
            "category":"Real Estate",
            "subcategory":"Real Estate Agent",
            "type":"Services"
        }
    ],
    "sg:phone":"+61 2 9568 6800",
    "sg:postcode":"2204",
    "sg:province":"NSW",
    "wof:name":"Colonial United Real Estate",
    "wof:placetype":"venue"
},
  "geometry": {"coordinates":[151.16549699999999,-33.902882],"type":"Point"}
}