{
  "type": "Feature",
  "properties": {
    "iso:country":"AU",
    "sg:address":"PO Box 4141",
    "sg:city":"Candelo",
    "sg:classifiers":[
        {
            "category":"Utilities",
            "subcategory":"Sewage",
            "type":"Services"
        }
    ],
    "sg:phone":"+61 2 6493 2242",
    "sg:postcode":"2550",
    "sg:province":"NSW",
    "sg:tags":[
        "water",
        "waste",
        "treatment"
    ],
    "wof:name":"Rota-Loo Compost Toilet Systems",
    "wof:placetype":"venue"
},
  "geometry": {"coordinates":[149.69422912600001,-36.765171051],"type":"Point"}
}