{
  "type": "Feature",
  "properties": {
    "addr:full":"Unit 3/ 72 Brookman St Kalgoorlie WA 6430",
    "addr:housenumber":"72",
    "addr:postcode":"6430",
    "addr:street":"Brookman St",
    "iso:country":"AU",
    "sg:address":"Unit 3/ 72 Brookman St",
    "sg:city":"Kalgoorlie",
    "sg:classifiers":[
        {
            "category":"Health Services",
            "subcategory":"Doctor",
            "type":"Services"
        }
    ],
    "sg:phone":"+61 8 9021 7078",
    "sg:postcode":"6430",
    "sg:province":"WA",
    "sg:tags":[
        "occupational",
        "safety"
    ],
    "wof:name":"KMW",
    "wof:placetype":"venue"
},
  "geometry": {"coordinates":[121.468849182,-30.7490997314],"type":"Point"}
}