{
  "type": "Feature",
  "properties": {
    "iso:country":"AU",
    "sg:address":"Elizabeth Park Lot 1000 Unit 1 Edinborough Cct",
    "sg:city":"Cecil Hills",
    "sg:classifiers":[
        {
            "category":"Banks & Credit Unions",
            "subcategory":"Bank",
            "type":"Services"
        }
    ],
    "sg:phone":"+61 2 9822 1300",
    "sg:postcode":"2171",
    "sg:province":"NSW",
    "wof:name":"Colonial State Bank",
    "wof:placetype":"venue"
},
  "geometry": {"coordinates":[150.856323242,-33.8939590454],"type":"Point"}
}