{
  "type": "Feature",
  "properties": {
    "iso:country":"AU",
    "sg:address":"116 McCredie Rd",
    "sg:city":"Guildford West",
    "sg:classifiers":[
        {
            "category":"Professional",
            "subcategory":"Detective & Security Services",
            "type":"Services"
        }
    ],
    "sg:phone":"+61 1300 553 266",
    "sg:postcode":"2161",
    "sg:province":"NSW",
    "sg:tags":[
        "consultant",
        "system"
    ],
    "wof:name":"Sound Security Pty Ltd",
    "wof:placetype":"venue"
},
  "geometry": {"coordinates":[150.960479736,-33.8503189087],"type":"Point"}
}