{
  "type": "Feature",
  "properties": {
    "iso:country":"AU",
    "sg:address":"34 Bambury St",
    "sg:city":"Boronia",
    "sg:classifiers":[
        {
            "category":"Shopping",
            "subcategory":"Computers & Home Electronics",
            "type":"Retail Goods"
        }
    ],
    "sg:phone":"+61 3 9762 9544",
    "sg:postcode":"3155",
    "sg:province":"VIC",
    "sg:tags":[
        "small",
        "equipment",
        "business"
    ],
    "wof:name":"Thomastronics Computers & Communications Pty Ltd",
    "wof:placetype":"venue"
},
  "geometry": {"coordinates":[145.29371643100001,-37.8576507568],"type":"Point"}
}