{
  "type": "Feature",
  "properties": {
    "addr:full":"Barloa Rd Mont Albert VIC 3127",
    "addr:postcode":"3127",
    "addr:street":"Barloa Rd",
    "iso:country":"AU",
    "sg:address":"Barloa Rd",
    "sg:city":"Mont Albert",
    "sg:classifiers":[
        {
            "category":"Education",
            "subcategory":"School",
            "type":"Public Place"
        }
    ],
    "sg:phone":"+61 3 9890 1331",
    "sg:postcode":"3127",
    "sg:province":"VIC",
    "sg:tags":[
        "state",
        "except",
        "nsw"
    ],
    "wof:name":"Mont Albert Primary School",
    "wof:placetype":"venue"
},
  "geometry": {"coordinates":[145.102386475,-37.8136901855],"type":"Point"}
}