{
  "type": "Feature",
  "properties": {
    "addr:full":"37 Benalla Rd Shepparton VIC 3630",
    "addr:housenumber":"37",
    "addr:postcode":"3630",
    "addr:street":"Benalla Rd",
    "iso:country":"AU",
    "sg:address":"37 Benalla Rd",
    "sg:city":"Shepparton",
    "sg:classifiers":[
        {
            "category":"Retail",
            "subcategory":"Repair Shop",
            "type":"Services"
        }
    ],
    "sg:phone":"+61 408 860 301",
    "sg:postcode":"3630",
    "sg:province":"VIC",
    "sg:tags":[
        "windscreen"
    ],
    "wof:name":"The Windscreen Savers",
    "wof:placetype":"venue"
},
  "geometry": {"coordinates":[145.4165802,-36.3837509155],"type":"Point"}
}