{
  "type": "Feature",
  "properties": {
    "iso:country":"AU",
    "sg:address":"28 Sprigg Pl",
    "sg:city":"Mt Colah",
    "sg:classifiers":[
        {
            "category":"Professional",
            "subcategory":"Accounting & Tax Preparation",
            "type":"Services"
        }
    ],
    "sg:phone":"+61 2 9476 2925",
    "sg:postcode":"2079",
    "sg:province":"NSW",
    "sg:tags":[
        "consultant",
        "taxation"
    ],
    "wof:name":"Mount Colah Taxation Services",
    "wof:placetype":"venue"
},
  "geometry": {"coordinates":[151.11936950699999,-33.6637649536],"type":"Point"}
}