{
  "type": "Feature",
  "properties": {
    "addr:full":"4 Harris St Wellington Point QLD 4160",
    "addr:housenumber":"4",
    "addr:postcode":"4160",
    "addr:street":"Harris St",
    "iso:country":"AU",
    "sg:address":"4 Harris St",
    "sg:city":"Wellington Point",
    "sg:classifiers":[
        {
            "category":"Professional",
            "subcategory":"Art Services",
            "type":"Services"
        }
    ],
    "sg:phone":"+61 7 3207 3764",
    "sg:postcode":"4160",
    "sg:province":"QLD",
    "sg:tags":[
        "decorator",
        "painter"
    ],
    "wof:name":"Grant T & S",
    "wof:placetype":"venue"
},
  "geometry": {"coordinates":[153.24017334000001,-27.4935665131],"type":"Point"}
}