{
  "type": "Feature",
  "properties": {
    "iso:country":"AU",
    "sg:address":"104 Coleman Rd",
    "sg:city":"Boronia",
    "sg:classifiers":[
        {
            "category":"Food & Beverages",
            "subcategory":"Supermarket",
            "type":"Retail Goods"
        }
    ],
    "sg:phone":"+61 3 9887 2480",
    "sg:postcode":"3155",
    "sg:province":"VIC",
    "sg:tags":[
        "grocery",
        "store"
    ],
    "wof:name":"Ausind International",
    "wof:placetype":"venue"
},
  "geometry": {"coordinates":[145.25259399399999,-37.8612594604],"type":"Point"}
}