{
  "type": "Feature",
  "properties": {
    "addr:full":"Shop 10, Hamilton Hill Shopping Centre, Simms Rd Hamilton Hill WA 6163",
    "addr:housenumber":"shop 10",
    "addr:postcode":"6163",
    "addr:street":"Simms Rd",
    "iso:country":"AU",
    "sg:address":"Shop 10, Hamilton Hill Shopping Centre, Simms Rd",
    "sg:city":"Hamilton Hill",
    "sg:classifiers":[
        {
            "category":"Food & Beverages",
            "subcategory":"Bakery",
            "type":"Retail Goods"
        }
    ],
    "sg:phone":"+61 8 9314 7434",
    "sg:postcode":"6163",
    "sg:province":"WA",
    "sg:tags":[
        "baker"
    ],
    "wof:name":"Bakers Delight",
    "wof:placetype":"venue"
},
  "geometry": {"coordinates":[115.78160099999999,-32.075333],"type":"Point"}
}