{
  "type": "Feature",
  "properties": {
    "addr:full":"22 Thesiger Crt Deakin ACT 2600",
    "addr:housenumber":"22",
    "addr:postcode":"2600",
    "addr:street":"Thesiger Crt",
    "iso:country":"AU",
    "sg:address":"22 Thesiger Crt",
    "sg:city":"Deakin",
    "sg:classifiers":[
        {
            "category":"Health Services",
            "subcategory":"Doctor",
            "type":"Services"
        }
    ],
    "sg:phone":"+61 2 6282 4383",
    "sg:postcode":"2600",
    "sg:province":"ACT",
    "sg:tags":[
        "medical",
        "practitioner"
    ],
    "wof:name":"Stone Hilton",
    "wof:placetype":"venue"
},
  "geometry": {"coordinates":[149.095825195,-35.3172988892],"type":"Point"}
}