{
  "type": "Feature",
  "properties": {
    "iso:country":"AU",
    "sg:address":"39 Young St East",
    "sg:city":"Redfern",
    "sg:classifiers":[
        {
            "category":"Government",
            "subcategory":"Court House",
            "type":"Public Place"
        }
    ],
    "sg:phone":"+61 2 8399 3390",
    "sg:postcode":"2016",
    "sg:province":"NSW",
    "sg:tags":[
        "personal",
        "marriage",
        "family",
        "counselling"
    ],
    "wof:name":"Surry Hills Holistic Counselling & Healing",
    "wof:placetype":"venue"
},
  "geometry": {"coordinates":[151.210571289,-33.892326355],"type":"Point"}
}