{
  "type": "Feature",
  "properties": {
    "iso:country":"AU",
    "sg:address":"44 Market St",
    "sg:city":"Cohuna",
    "sg:classifiers":[
        {
            "category":"Personal",
            "subcategory":"Beauty Salon",
            "type":"Services"
        }
    ],
    "sg:phone":"+61 3 5456 3035",
    "sg:postcode":"3568",
    "sg:province":"VIC",
    "sg:tags":[
        "hairdresser"
    ],
    "wof:name":"Hair Trend 67",
    "wof:placetype":"venue"
},
  "geometry": {"coordinates":[144.21875,-35.8137512207],"type":"Point"}
}