{
  "type": "Feature",
  "properties": {
    "addr:full":"67- 69 Lorien Way Kingscliff NSW 2487",
    "addr:housenumber":"69",
    "addr:postcode":"2487",
    "addr:street":"Lorien Way",
    "iso:country":"AU",
    "sg:address":"67- 69 Lorien Way",
    "sg:city":"Kingscliff",
    "sg:classifiers":[
        {
            "category":"Education",
            "subcategory":"Kindergarten",
            "type":"Public Place"
        }
    ],
    "sg:phone":"+61 2 6674 3966",
    "sg:postcode":"2487",
    "sg:province":"NSW",
    "sg:tags":[
        "pre-schools"
    ],
    "wof:name":"Bossy Boots Child Care Centre",
    "wof:placetype":"venue"
},
  "geometry": {"coordinates":[153.56933593799999,-28.2558498383],"type":"Point"}
}