{
  "type": "Feature",
  "properties": {
    "addr:full":"Unit 11 66 Roberts St Osborne Park WA 6017",
    "addr:housenumber":"66",
    "addr:postcode":"6017",
    "addr:street":"Roberts St",
    "iso:country":"AU",
    "sg:address":"Unit 11 66 Roberts St",
    "sg:city":"Osborne Park",
    "sg:classifiers":[
        {
            "category":"Retail",
            "subcategory":"Auto Repair",
            "type":"Services"
        }
    ],
    "sg:phone":"+61 8 9242 5585",
    "sg:postcode":"6017",
    "sg:province":"WA",
    "sg:tags":[
        "repairer",
        "motor",
        "engineer"
    ],
    "wof:name":"Lau Auto Repairs",
    "wof:placetype":"venue"
},
  "geometry": {"coordinates":[115.823928833,-31.9079647064],"type":"Point"}
}