{
  "type": "Feature",
  "properties": {
    "addr:full":"9 Tanglewood St Runcorn QLD 4113",
    "addr:housenumber":"9",
    "addr:postcode":"4113",
    "addr:street":"Tanglewood St",
    "iso:country":"AU",
    "sg:address":"9 Tanglewood St",
    "sg:city":"Runcorn",
    "sg:classifiers":[
        {
            "category":"Personal",
            "subcategory":"Beauty Salon",
            "type":"Services"
        }
    ],
    "sg:phone":"+61 7 3344 1842",
    "sg:postcode":"4113",
    "sg:province":"QLD",
    "sg:tags":[
        "hairdresser"
    ],
    "wof:name":"Adrenaline Hair Studio",
    "wof:placetype":"venue"
},
  "geometry": {"coordinates":[153.06478881800001,-27.5972270966],"type":"Point"}
}