{
  "type": "Feature",
  "properties": {
    "addr:full":"Masons Rd Bowenville QLD 4404",
    "addr:postcode":"4404",
    "addr:street":"Masons Rd",
    "iso:country":"AU",
    "sg:address":"Masons Rd",
    "sg:city":"Bowenville",
    "sg:classifiers":[
        {
            "category":"Farming",
            "subcategory":"Farm",
            "type":"Manufacturing & Wholesale Goods"
        }
    ],
    "sg:phone":"+61 7 4663 7117",
    "sg:postcode":"4404",
    "sg:province":"QLD",
    "sg:tags":[
        "farmer"
    ],
    "wof:name":"McCaffrey S & J M",
    "wof:placetype":"venue"
},
  "geometry": {"coordinates":[151.511962891,-27.3350086212],"type":"Point"}
}