{
  "type": "Feature",
  "properties": {
    "iso:country":"AU",
    "sg:address":"77 Salamanca Pl",
    "sg:city":"Hobart",
    "sg:classifiers":[
        {
            "category":"Farming",
            "subcategory":"Farm & Veterinary Services",
            "type":"Manufacturing & Wholesale Goods"
        }
    ],
    "sg:phone":"+61 3 6224 4441",
    "sg:postcode":"7000",
    "sg:province":"TAS",
    "sg:tags":[
        "blacksmith",
        "farrier"
    ],
    "wof:name":"Hammer & Hand",
    "wof:placetype":"venue"
},
  "geometry": {"coordinates":[147.334274292,-42.8868370056],"type":"Point"}
}