{
  "type": "Feature",
  "properties": {
    "iso:country":"AU",
    "sg:address":"U501/ 55 Holt St",
    "sg:city":"Surry Hills",
    "sg:classifiers":[
        {
            "category":"Farming",
            "subcategory":"Orchard",
            "type":"Manufacturing & Wholesale Goods"
        }
    ],
    "sg:phone":"+61 2 8021 1768",
    "sg:postcode":"2010",
    "sg:province":"NSW",
    "sg:tags":[
        "wholesaler",
        "jean",
        "mfrs"
    ],
    "wof:name":"Chic Circle",
    "wof:placetype":"venue"
},
  "geometry": {"coordinates":[151.20912170400001,-33.8862609863],"type":"Point"}
}