{
  "type": "Feature",
  "properties": {
    "iso:country":"AU",
    "sg:address":"185 King St",
    "sg:city":"Charleville",
    "sg:classifiers":[
        {
            "category":"Professional",
            "subcategory":"Business Services",
            "type":"Services"
        }
    ],
    "sg:phone":"+61 417 743 468",
    "sg:postcode":"4470",
    "sg:province":"QLD",
    "sg:tags":[
        "livestock",
        "transport"
    ],
    "wof:name":"John Everitt",
    "wof:placetype":"venue"
},
  "geometry": {"coordinates":[146.253814697,-26.3993549347],"type":"Point"}
}