{
  "type": "Feature",
  "properties": {
    "iso:country":"AU",
    "sg:address":"Unit 2/ 46 Gilbert Park Drv",
    "sg:city":"Scoresby",
    "sg:classifiers":[
        {
            "category":"Retail",
            "subcategory":"Storage",
            "type":"Services"
        }
    ],
    "sg:phone":"+61 3 9753 3311",
    "sg:postcode":"3179",
    "sg:province":"VIC",
    "sg:tags":[
        "shelving",
        "system"
    ],
    "wof:name":"All Type Shelving Pty Ltd",
    "wof:placetype":"venue"
},
  "geometry": {"coordinates":[145.25315856899999,-37.898399353],"type":"Point"}
}