{
  "type": "Feature",
  "properties": {
    "iso:country":"AU",
    "sg:address":"6, 90- 94 Carnarvon St",
    "sg:city":"Silverwater",
    "sg:classifiers":[
        {
            "category":"Building & Trades",
            "subcategory":"Construction",
            "type":"Services"
        }
    ],
    "sg:phone":"+61 2 9648 6350",
    "sg:postcode":"2128",
    "sg:province":"NSW",
    "sg:tags":[
        "window",
        "tinting"
    ],
    "wof:name":"SunGard Silverwater",
    "wof:placetype":"venue"
},
  "geometry": {"coordinates":[151.04193115199999,-33.8378181458],"type":"Point"}
}