{
  "type": "Feature",
  "properties": {
    "addr:full":"Level 6 / Suite 6 125 Swanston St Melbourne VIC 3000",
    "addr:housenumber":"/ suite;125",
    "addr:postcode":"3000",
    "addr:street":"Swanston St",
    "iso:country":"AU",
    "sg:address":"Level 6 / Suite 6 125 Swanston St",
    "sg:city":"Melbourne",
    "sg:classifiers":[
        {
            "category":"Military Area",
            "subcategory":"Air Force Base",
            "type":"Public Place"
        }
    ],
    "sg:phone":"+61 3 9654 8914",
    "sg:postcode":"3000",
    "sg:province":"VIC",
    "sg:tags":[
        "men's",
        "tailor"
    ],
    "wof:name":"City Tailoring & Alteration Service",
    "wof:placetype":"venue"
},
  "geometry": {"coordinates":[144.966064453,-37.8147964478],"type":"Point"}
}