{
  "type": "Feature",
  "properties": {
    "iso:country":"AU",
    "sg:address":"20 Hughes St",
    "sg:city":"Cabramatta",
    "sg:classifiers":[
        {
            "category":"Communications",
            "subcategory":"Film & Video Production",
            "type":"Services"
        }
    ],
    "sg:phone":"+61 2 9724 1583",
    "sg:postcode":"2166",
    "sg:province":"NSW",
    "sg:tags":[
        "dvd",
        "library"
    ],
    "wof:name":"AA Video",
    "wof:placetype":"venue"
},
  "geometry": {"coordinates":[150.93634033199999,-33.893573761],"type":"Point"}
}