{
  "type": "Feature",
  "properties": {
    "iso:country":"AU",
    "sg:address":"105 Miller St",
    "sg:city":"North Sydney",
    "sg:classifiers":[
        {
            "category":"Shopping",
            "subcategory":"Jewelry",
            "type":"Retail Goods"
        }
    ],
    "sg:phone":"+61 2 9955 9030",
    "sg:postcode":"2060",
    "sg:province":"NSW",
    "sg:tags":[
        "jeweller"
    ],
    "wof:name":"Hourglass Jewellers",
    "wof:placetype":"venue"
},
  "geometry": {"coordinates":[151.20707702600001,-33.8387489319],"type":"Point"}
}