{
  "type": "Feature",
  "properties": {
    "iso:country":"AU",
    "sg:address":"Unit 6, 26 Kremzow Rd",
    "sg:city":"Brendale",
    "sg:classifiers":[
        {
            "category":"Professional",
            "subcategory":"Accounting & Tax Preparation",
            "type":"Services"
        }
    ],
    "sg:phone":"+61 7 3881 0471",
    "sg:postcode":"4500",
    "sg:province":"QLD",
    "sg:tags":[
        "consultant",
        "taxation"
    ],
    "sg:website":"http://www.pstokesco.com.au",
    "wof:name":"P. Stokes & Co",
    "wof:placetype":"venue"
},
  "geometry": {"coordinates":[152.98350524899999,-27.3177127838],"type":"Point"}
}