{
  "type": "Feature",
  "properties": {
    "addr:full":"Shed 1, 34 Southern Cross Drv Ballina NSW 2478",
    "addr:housenumber":"34",
    "addr:postcode":"2478",
    "addr:street":"Southern Cross Drv",
    "iso:country":"AU",
    "sg:address":"Shed 1, 34 Southern Cross Drv",
    "sg:city":"Ballina",
    "sg:classifiers":[
        {
            "category":"Home & Garden",
            "subcategory":"Building Materials",
            "type":"Retail Goods"
        }
    ],
    "sg:phone":"+61 2 6686 7981",
    "sg:postcode":"2478",
    "sg:province":"NSW",
    "sg:tags":[
        "merchant",
        "glass",
        "glazier"
    ],
    "wof:name":"Ballina Aluminium Windows & Glass",
    "wof:placetype":"venue"
},
  "geometry": {"coordinates":[153.55473327600001,-28.8485298157],"type":"Point"}
}