{
  "type": "Feature",
  "properties": {
    "addr:full":"Shop 8 Albion St Mittagong NSW 2575",
    "addr:housenumber":"shop 8",
    "addr:postcode":"2575",
    "addr:street":"Albion St",
    "iso:country":"AU",
    "sg:address":"Shop 8 Albion St",
    "sg:city":"Mittagong",
    "sg:classifiers":[
        {
            "category":"Health Services",
            "subcategory":"Health Practitioner",
            "type":"Services"
        }
    ],
    "sg:phone":"+61 2 4871 3064",
    "sg:postcode":"2575",
    "sg:province":"NSW",
    "sg:tags":[
        "physiotherapist"
    ],
    "wof:name":"Bowral Mittagong Physiotherapy & Sports Injuries Centre",
    "wof:placetype":"venue"
},
  "geometry": {"coordinates":[150.45083618199999,-34.4511222839],"type":"Point"}
}