{
  "type": "Feature",
  "properties": {
    "addr:full":"1444a Henley Beach Rd Torrensville SA 5031",
    "addr:housenumber":"1444a",
    "addr:postcode":"5031",
    "addr:street":"Henley Beach Rd",
    "iso:country":"AU",
    "sg:address":"1444a Henley Beach Rd",
    "sg:city":"Torrensville",
    "sg:classifiers":[
        {
            "category":"Shopping",
            "subcategory":"Computers & Home Electronics",
            "type":"Retail Goods"
        }
    ],
    "sg:phone":"+61 1300 732 227",
    "sg:postcode":"5031",
    "sg:province":"SA",
    "sg:tags":[
        "cleaning"
    ],
    "wof:name":"BACS I.T. Protection",
    "wof:placetype":"venue"
},
  "geometry": {"coordinates":[138.5574646,-34.9242477417],"type":"Point"}
}