{
  "type": "Feature",
  "properties": {
    "iso:country":"AU",
    "sg:address":"22 Sarah St",
    "sg:city":"Angaston",
    "sg:classifiers":[
        {
            "category":"Professional",
            "subcategory":"Printing & Photocopies",
            "type":"Services"
        }
    ],
    "sg:phone":"+61 8 8564 2846",
    "sg:postcode":"5353",
    "sg:province":"SA",
    "sg:tags":[
        "trophy"
    ],
    "wof:name":"Barossa Trophies",
    "wof:placetype":"venue"
},
  "geometry": {"coordinates":[139.044754028,-34.4871253967],"type":"Point"}
}