{
  "type": "Feature",
  "properties": {
    "addr:full":"89 Winfield Rd Balwyn North VIC 3104",
    "addr:housenumber":"89",
    "addr:postcode":"3104",
    "addr:street":"Winfield Rd",
    "iso:country":"AU",
    "sg:address":"89 Winfield Rd",
    "sg:city":"Balwyn North",
    "sg:classifiers":[
        {
            "category":"Shopping",
            "subcategory":"Musical Instruments",
            "type":"Retail Goods"
        }
    ],
    "sg:phone":"+61 3 9857 4694",
    "sg:postcode":"3104",
    "sg:province":"VIC",
    "sg:tags":[
        "musician",
        "agent"
    ],
    "wof:name":"Serenade Strings",
    "wof:placetype":"venue"
},
  "geometry": {"coordinates":[145.10551452600001,-37.7935295105],"type":"Point"}
}