{
  "type": "Feature",
  "properties": {
    "iso:country":"AU",
    "sg:address":"6 West St",
    "sg:city":"Mt Isa",
    "sg:classifiers":[
        {
            "category":"Fast Food",
            "type":"Food & Drink"
        }
    ],
    "sg:phone":"+61 7 4743 3318",
    "sg:postcode":"4825",
    "sg:province":"QLD",
    "sg:tags":[
        "away",
        "take"
    ],
    "wof:name":"Tip Top Milk Bar & Delicatessen",
    "wof:placetype":"venue"
},
  "geometry": {"coordinates":[139.49029540999999,-20.7272548676],"type":"Point"}
}