{
  "type": "Feature",
  "properties": {
    "iso:country":"AU",
    "sg:address":"127 Nerang St",
    "sg:city":"Southport",
    "sg:classifiers":[
        {
            "category":"Health Services",
            "subcategory":"Dentist",
            "type":"Services"
        }
    ],
    "sg:phone":"+61 7 5531 3211",
    "sg:postcode":"4215",
    "sg:province":"QLD",
    "wof:name":"Nerang Street Dental Clinic",
    "wof:placetype":"venue"
},
  "geometry": {"coordinates":[153.40742492699999,-27.9710636139],"type":"Point"}
}