{
  "type": "Feature",
  "properties": {
    "addr:full":"10 Industry Drv Caboolture QLD 4510",
    "addr:housenumber":"10",
    "addr:postcode":"4510",
    "addr:street":"Industry Drv",
    "iso:country":"AU",
    "sg:address":"10 Industry Drv",
    "sg:city":"Caboolture",
    "sg:classifiers":[
        {
            "category":"Industrial Area",
            "type":"Public Place"
        }
    ],
    "sg:phone":"+61 7 5495 6533",
    "sg:postcode":"4510",
    "sg:province":"QLD",
    "sg:tags":[
        "rural",
        "shed"
    ],
    "wof:name":"Sunshine Landscaping Supplies",
    "wof:placetype":"venue"
},
  "geometry": {"coordinates":[152.94581600000001,-27.07192],"type":"Point"}
}