{
  "type": "Feature",
  "properties": {
    "addr:full":"Unit 1/ 31 Ledgar Rd Balcatta WA 6021",
    "addr:postcode":"6021",
    "addr:street":"31 Ledgar Rd",
    "iso:country":"AU",
    "sg:address":"Unit 1/ 31 Ledgar Rd",
    "sg:city":"Balcatta",
    "sg:classifiers":[
        {
            "category":"Shopping",
            "subcategory":"Bicycles & Sporting Goods",
            "type":"Retail Goods"
        }
    ],
    "sg:phone":"+61 8 9240 8611",
    "sg:postcode":"6021",
    "sg:province":"WA",
    "sg:tags":[
        "chemical",
        "equipment",
        "pool",
        "swimming"
    ],
    "wof:name":"Zodiac Group Australia Pty Ltd",
    "wof:placetype":"venue"
},
  "geometry": {"coordinates":[115.803672791,-31.8620014191],"type":"Point"}
}