{
  "type": "Feature",
  "properties": {
    "addr:full":"424 San Mateo Ave Mildura VIC 3500",
    "addr:housenumber":"424",
    "addr:postcode":"3500",
    "addr:street":"San Mateo Ave",
    "iso:country":"AU",
    "sg:address":"424 San Mateo Ave",
    "sg:city":"Mildura",
    "sg:classifiers":[
        {
            "category":"Home & Garden",
            "subcategory":"Carpets & Floor Coverings",
            "type":"Retail Goods"
        }
    ],
    "sg:phone":"+61 3 5022 7551",
    "sg:postcode":"3500",
    "sg:province":"VIC",
    "wof:name":"Carpet One",
    "wof:placetype":"venue"
},
  "geometry": {"coordinates":[142.143508911,-34.2094116211],"type":"Point"}
}