{
  "type": "Feature",
  "properties": {
    "iso:country":"AU",
    "sg:address":"Cnr Moordale & Moggill Rds",
    "sg:city":"Chapel Hill",
    "sg:classifiers":[
        {
            "category":"Health Services",
            "subcategory":"Health Practitioner",
            "type":"Services"
        }
    ],
    "sg:phone":"+61 7 3399 8028",
    "sg:postcode":"4069",
    "sg:province":"QLD",
    "sg:tags":[
        "pathologist",
        "speech"
    ],
    "wof:name":"Louise M. Tyquin",
    "wof:placetype":"venue"
},
  "geometry": {"coordinates":[152.95631408700001,-27.503074646],"type":"Point"}
}