{
  "type": "Feature",
  "properties": {
    "iso:country":"AU",
    "sg:address":"48 Darlington Drv",
    "sg:city":"Cherrybrook",
    "sg:classifiers":[
        {
            "category":"Social Services",
            "subcategory":"Retirement Home",
            "type":"Services"
        }
    ],
    "sg:phone":"+61 2 9659 7411",
    "sg:postcode":"2126",
    "sg:province":"NSW",
    "sg:tags":[
        "environmental",
        "consultant",
        "pollution"
    ],
    "wof:name":"Airteraq Pty Ltd",
    "wof:placetype":"venue"
},
  "geometry": {"coordinates":[151.03323364299999,-33.7238464355],"type":"Point"}
}