{
  "type": "Feature",
  "properties": {
    "addr:full":"Unit 2, 365 Bayswater Rd Garbutt QLD 4814",
    "addr:housenumber":"365",
    "addr:postcode":"4814",
    "addr:street":"Bayswater Rd",
    "iso:country":"AU",
    "sg:address":"Unit 2, 365 Bayswater Rd",
    "sg:city":"Garbutt",
    "sg:classifiers":[
        {
            "category":"Banks & Credit Unions",
            "subcategory":"Investment Brokerage",
            "type":"Services"
        }
    ],
    "sg:phone":"+61 7 4755 0444",
    "sg:postcode":"4814",
    "sg:province":"QLD",
    "sg:tags":[
        "shutter",
        "louvre"
    ],
    "wof:name":"N.Q. Blinds & Shutters P/L",
    "wof:placetype":"venue"
},
  "geometry": {"coordinates":[146.760559,-19.272945],"type":"Point"}
}