{
  "type": "Feature",
  "properties": {
    "addr:full":"36 Seidels Road (Via Ipswich) Walloon QLD 4306",
    "addr:housenumber":"36",
    "addr:postcode":"4306",
    "addr:street":"Seidels Road Via Ipswich",
    "iso:country":"AU",
    "sg:address":"36 Seidels Road (Via Ipswich)",
    "sg:city":"Walloon",
    "sg:classifiers":[
        {
            "category":"Manufacturing",
            "subcategory":"Metals",
            "type":"Manufacturing & Wholesale Goods"
        }
    ],
    "sg:phone":"+61 7 5464 5233",
    "sg:postcode":"4306",
    "sg:province":"QLD",
    "sg:tags":[
        "fabricator",
        "aluminium"
    ],
    "wof:name":"Karrick Fabrications & Truck Repairs",
    "wof:placetype":"venue"
},
  "geometry": {"coordinates":[152.68026733400001,-27.6033725739],"type":"Point"}
}