{
  "type": "Feature",
  "properties": {
    "iso:country":"AU",
    "sg:address":"Warehouse 6/ 14 Broadland Drv",
    "sg:city":"Newstead",
    "sg:classifiers":[
        {
            "category":"Shopping",
            "subcategory":"Stationery & Office Supplies",
            "type":"Retail Goods"
        }
    ],
    "sg:phone":"+61 3 6334 5504",
    "sg:postcode":"7250",
    "sg:province":"TAS",
    "sg:tags":[
        "packaging",
        "material"
    ],
    "wof:name":"Tudors Pack N Wrap",
    "wof:placetype":"venue"
},
  "geometry": {"coordinates":[147.155151367,-41.4311180115],"type":"Point"}
}