{
  "type": "Feature",
  "properties": {
    "addr:full":"1068 Caratel St North Albury NSW 2640",
    "addr:postcode":"1068;2640",
    "addr:street":"Caratel St North",
    "iso:country":"AU",
    "sg:address":"1068 Caratel St",
    "sg:city":"North Albury",
    "sg:classifiers":[
        {
            "category":"Health Services",
            "subcategory":"Doctor",
            "type":"Services"
        }
    ],
    "sg:phone":"+61 2 6025 5455",
    "sg:postcode":"2640",
    "sg:province":"NSW",
    "sg:tags":[
        "nurse",
        "nursing"
    ],
    "wof:name":"N.G.M. Home Nurses",
    "wof:placetype":"venue"
},
  "geometry": {"coordinates":[146.934036255,-36.0544204712],"type":"Point"}
}