{
  "type": "Feature",
  "properties": {
    "addr:full":"35 Cinderella Drv Springwood QLD 4127",
    "addr:housenumber":"35",
    "addr:postcode":"4127",
    "addr:street":"Cinderella Drv",
    "iso:country":"AU",
    "sg:address":"35 Cinderella Drv",
    "sg:city":"Springwood",
    "sg:classifiers":[
        {
            "category":"Health Services",
            "subcategory":"Doctor",
            "type":"Services"
        }
    ],
    "sg:phone":"+61 7 3344 7033",
    "sg:postcode":"4127",
    "sg:province":"QLD",
    "sg:tags":[
        "podiatrist"
    ],
    "wof:name":"Cardinal Stephen Podiatry Group",
    "wof:placetype":"venue"
},
  "geometry": {"coordinates":[153.12550354000001,-27.6097393036],"type":"Point"}
}