{
  "type": "Feature",
  "properties": {
    "iso:country":"AU",
    "sg:address":"Civil St",
    "sg:city":"Garbutt",
    "sg:classifiers":[
        {
            "category":"Utilities",
            "subcategory":"Refuse",
            "type":"Services"
        }
    ],
    "sg:phone":"+61 7 4788 7134",
    "sg:postcode":"4814",
    "sg:province":"QLD",
    "sg:tags":[
        "remover",
        "rubbish"
    ],
    "wof:name":"Twin Cities Garden Waste",
    "wof:placetype":"venue"
},
  "geometry": {"coordinates":[146.762863,-19.270237],"type":"Point"}
}