{
  "type": "Feature",
  "properties": {
    "iso:country":"AU",
    "sg:address":"3 Barlow Av",
    "sg:city":"Cheltenham",
    "sg:classifiers":[
        {
            "category":"Shopping",
            "subcategory":"Computers & Home Electronics",
            "type":"Retail Goods"
        }
    ],
    "sg:phone":"+61 3 9583 2341",
    "sg:postcode":"3192",
    "sg:province":"VIC",
    "sg:tags":[
        "equipment",
        "multimedia"
    ],
    "wof:name":"Jam Tin Sound Studios",
    "wof:placetype":"venue"
},
  "geometry": {"coordinates":[145.07463073700001,-37.9571647644],"type":"Point"}
}