{
  "type": "Feature",
  "properties": {
    "addr:full":"PO Box 276 Picton NSW 2571",
    "addr:postcode":"2571",
    "iso:country":"AU",
    "sg:address":"PO Box 276",
    "sg:city":"Picton",
    "sg:classifiers":[
        {
            "category":"Utilities",
            "subcategory":"Mobile Phone",
            "type":"Services"
        }
    ],
    "sg:phone":"+61 2 4680 8112",
    "sg:postcode":"2571",
    "sg:province":"NSW",
    "sg:tags":[
        "aviation",
        "consultant"
    ],
    "wof:name":"Aero Safe Industries Pty Ltd",
    "wof:placetype":"venue"
},
  "geometry": {"coordinates":[150.611495972,-34.1690788269],"type":"Point"}
}