{
  "type": "Feature",
  "properties": {
    "iso:country":"AU",
    "sg:address":"Unit 8/ 185 Lake Rd",
    "sg:city":"Port Macquarie",
    "sg:classifiers":[
        {
            "category":"Freight",
            "type":"Transportation"
        }
    ],
    "sg:phone":"+61 2 6581 2223",
    "sg:postcode":"2444",
    "sg:province":"NSW",
    "sg:tags":[
        "light",
        "carrier"
    ],
    "wof:name":"Fastway Couriers",
    "wof:placetype":"venue"
},
  "geometry": {"coordinates":[152.891327,-31.448988],"type":"Point"}
}