{
  "type": "Feature",
  "properties": {
    "addr:full":"112 Balmain Rd Leichhardt NSW 2040",
    "addr:housenumber":"112",
    "addr:postcode":"2040",
    "addr:street":"Balmain Rd",
    "iso:country":"AU",
    "sg:address":"112 Balmain Rd",
    "sg:city":"Leichhardt",
    "sg:classifiers":[
        {
            "category":"Health Services",
            "subcategory":"Doctor",
            "type":"Services"
        }
    ],
    "sg:phone":"+61 2 9561 0300",
    "sg:postcode":"2040",
    "sg:province":"NSW",
    "sg:tags":[
        "medical",
        "practitioner"
    ],
    "wof:name":"Van Kesteren Tanya",
    "wof:placetype":"venue"
},
  "geometry": {"coordinates":[151.15887499999999,-33.883202],"type":"Point"}
}