{
  "type": "Feature",
  "properties": {
    "iso:country":"AU",
    "sg:address":"St",
    "sg:city":"Vincent Hospital East Toowoomba",
    "sg:classifiers":[
        {
            "category":"Health Services",
            "subcategory":"Health Practitioner",
            "type":"Services"
        }
    ],
    "sg:phone":"+61 7 4659 5474",
    "sg:postcode":"4350",
    "sg:province":"QLD",
    "sg:tags":[
        "psychologist"
    ],
    "wof:name":"Mandala Psychology",
    "wof:placetype":"venue"
},
  "geometry": {"coordinates":[151.972031,-27.566719],"type":"Point"}
}