{
  "type": "Feature",
  "properties": {
    "iso:country":"AU",
    "sg:address":"Hickox St",
    "sg:city":"Traralgon",
    "sg:classifiers":[
        {
            "category":"Education",
            "subcategory":"School",
            "type":"Public Place"
        }
    ],
    "sg:phone":"+61 3 5174 1956",
    "sg:postcode":"3844",
    "sg:province":"VIC",
    "wof:name":"Traralgon Special Developmental School",
    "wof:placetype":"venue"
},
  "geometry": {"coordinates":[146.53297424300001,-38.2007904053],"type":"Point"}
}