{
  "type": "Feature",
  "properties": {
    "addr:full":"15 Teape St Silkstone QLD 4304",
    "addr:housenumber":"15",
    "addr:postcode":"4304",
    "addr:street":"Teape St",
    "iso:country":"AU",
    "sg:address":"15 Teape St",
    "sg:city":"Silkstone",
    "sg:classifiers":[
        {
            "category":"Education",
            "subcategory":"Music School",
            "type":"Public Place"
        }
    ],
    "sg:phone":"+61 7 3812 7225",
    "sg:postcode":"4304",
    "sg:province":"QLD",
    "sg:tags":[
        "therapy",
        "relaxation"
    ],
    "wof:name":"Jane's Natural Healing Centre",
    "wof:placetype":"venue"
},
  "geometry": {"coordinates":[152.78904724099999,-27.6192836761],"type":"Point"}
}