{
  "type": "Feature",
  "properties": {
    "addr:full":"27a Davis Rd Wetherill Park NSW 2164",
    "addr:housenumber":"27a",
    "addr:postcode":"2164",
    "addr:street":"Davis Rd",
    "iso:country":"AU",
    "sg:address":"27a Davis Rd",
    "sg:city":"Wetherill Park",
    "sg:classifiers":[
        {
            "category":"Manufacturing",
            "subcategory":"Furniture",
            "type":"Manufacturing & Wholesale Goods"
        }
    ],
    "sg:phone":"+61 2 9787 3585",
    "sg:postcode":"2164",
    "sg:province":"NSW",
    "sg:tags":[
        "mfrs",
        "supply"
    ],
    "wof:name":"Matic Furniture",
    "wof:placetype":"venue"
},
  "geometry": {"coordinates":[150.90330505399999,-33.8363761902],"type":"Point"}
}