{
  "type": "Feature",
  "properties": {
    "addr:full":"Lyons Pde Forestville SA 5035",
    "addr:postcode":"5035",
    "addr:street":"Lyons",
    "iso:country":"AU",
    "sg:address":"Lyons Pde",
    "sg:city":"Forestville",
    "sg:classifiers":[
        {
            "category":"Shopping",
            "subcategory":"Stationery & Office Supplies",
            "type":"Retail Goods"
        }
    ],
    "sg:phone":"+61 8 8297 3582",
    "sg:postcode":"5035",
    "sg:province":"SA",
    "sg:tags":[
        "equipment",
        "badge",
        "making"
    ],
    "wof:name":"Olson Allan J Badges",
    "wof:placetype":"venue"
},
  "geometry": {"coordinates":[138.585403442,-34.9529190063],"type":"Point"}
}