{
  "type": "Feature",
  "properties": {
    "addr:full":"Roberts St Norseman WA 6443",
    "addr:postcode":"6443",
    "addr:street":"Roberts St",
    "iso:country":"AU",
    "sg:address":"Roberts St",
    "sg:city":"Norseman",
    "sg:classifiers":[
        {
            "category":"Utilities",
            "subcategory":"Fuel Oil & Lpg",
            "type":"Services"
        }
    ],
    "sg:phone":"+61 8 9071 1065",
    "sg:postcode":"6443",
    "sg:province":"WA",
    "sg:tags":[
        "merchant"
    ],
    "wof:name":"South East Petroleum",
    "wof:placetype":"venue"
},
  "geometry": {"coordinates":[121.78041076700001,-32.1954345703],"type":"Point"}
}