{
  "type": "Feature",
  "properties": {
    "addr:full":"Roadside Mail Box 2149 Apsley VIC 3319",
    "addr:postcode":"3319",
    "iso:country":"AU",
    "sg:address":"Roadside Mail Box 2149",
    "sg:city":"Apsley",
    "sg:classifiers":[
        {
            "category":"Building & Trades",
            "subcategory":"Plumbing",
            "type":"Services"
        }
    ],
    "sg:phone":"+61 3 5586 5224",
    "sg:postcode":"3319",
    "sg:province":"VIC",
    "sg:tags":[
        "plumber",
        "gasfitters"
    ],
    "wof:name":"Grigg K",
    "wof:placetype":"venue"
},
  "geometry": {"coordinates":[141.07774352999999,-36.966381073],"type":"Point"}
}