{
  "type": "Feature",
  "properties": {
    "addr:full":"132 Howard St Nambour QLD 4560",
    "addr:housenumber":"132",
    "addr:postcode":"4560",
    "addr:street":"Howard St",
    "iso:country":"AU",
    "sg:address":"132 Howard St",
    "sg:city":"Nambour",
    "sg:classifiers":[
        {
            "category":"Retail",
            "subcategory":"Auto Rental",
            "type":"Services"
        }
    ],
    "sg:phone":"+61 412 952 317",
    "sg:postcode":"4560",
    "sg:province":"QLD",
    "sg:tags":[
        "camper-trailers",
        "caravan",
        "hire"
    ],
    "wof:name":"Queensland's Cheapest Caravans & Trailers",
    "wof:placetype":"venue"
},
  "geometry": {"coordinates":[152.965942383,-26.6264629364],"type":"Point"}
}