{
  "type": "Feature",
  "properties": {
    "addr:full":"Shop 6/2 Merrigang St (Cnr Station St) Bowral NSW 2576",
    "addr:housenumber":"shop 6 / 2",
    "addr:postcode":"2576",
    "addr:street":"Merrigang St Cnr Station St",
    "iso:country":"AU",
    "sg:address":"Shop 6/2 Merrigang St",
    "sg:city":"(Cnr Station St) Bowral",
    "sg:classifiers":[
        {
            "category":"Utilities",
            "subcategory":"Water",
            "type":"Services"
        }
    ],
    "sg:phone":"+61 2 4861 3900",
    "sg:postcode":"2576",
    "sg:province":"NSW",
    "sg:tags":[
        "hot",
        "system"
    ],
    "wof:name":"Hot Water Maintenance",
    "wof:placetype":"venue"
},
  "geometry": {"coordinates":[150.418365478,-34.4776077271],"type":"Point"}
}