{
  "type": "Feature",
  "properties": {
    "addr:full":"5 Carrick St Mont Albert VIC 3127",
    "addr:housenumber":"5",
    "addr:postcode":"3127",
    "addr:street":"Carrick St",
    "iso:country":"AU",
    "sg:address":"5 Carrick St",
    "sg:city":"Mont Albert",
    "sg:classifiers":[
        {
            "category":"Farming",
            "subcategory":"Vineyard",
            "type":"Manufacturing & Wholesale Goods"
        }
    ],
    "sg:phone":"+61 3 9898 7476",
    "sg:postcode":"3127",
    "sg:province":"VIC",
    "sg:tags":[
        "winery"
    ],
    "wof:name":"Dixons Run Wines Pty Ltd",
    "wof:placetype":"venue"
},
  "geometry": {"coordinates":[145.101730347,-37.8111457825],"type":"Point"}
}