{
  "type": "Feature",
  "properties": {
    "addr:full":"Holdsworth Rd Bendigo VIC 3550",
    "addr:postcode":"3550",
    "addr:street":"Holdsworth Rd",
    "iso:country":"AU",
    "sg:address":"Holdsworth Rd",
    "sg:city":"Bendigo",
    "sg:classifiers":[
        {
            "category":"Retail",
            "subcategory":"Funeral Services",
            "type":"Services"
        }
    ],
    "sg:phone":"+61 3 5446 1566",
    "sg:postcode":"3550",
    "sg:province":"VIC",
    "sg:tags":[
        "cemetery"
    ],
    "wof:name":"White Hills Cemetery",
    "wof:placetype":"venue"
},
  "geometry": {"coordinates":[144.28045654300001,-36.7344055176],"type":"Point"}
}