{
  "type": "Feature",
  "properties": {
    "iso:country":"AU",
    "sg:address":"2 Cronulla St",
    "sg:city":"Slacks Creek",
    "sg:classifiers":[
        {
            "category":"Social Services",
            "subcategory":"Retirement Home",
            "type":"Services"
        }
    ],
    "sg:phone":"+61 7 3208 0607",
    "sg:postcode":"4127",
    "sg:province":"QLD",
    "sg:tags":[
        "t-shirt",
        "supplier"
    ],
    "wof:name":"Printworks Clothing Co",
    "wof:placetype":"venue"
},
  "geometry": {"coordinates":[153.12031555199999,-27.6181049347],"type":"Point"}
}