{
  "type": "Feature",
  "properties": {
    "iso:country":"AU",
    "sg:address":"Shop 9, 8-16 Redland Bay Rd",
    "sg:city":"Capalaba",
    "sg:classifiers":[
        {
            "category":"Shopping",
            "subcategory":"Party Supplies",
            "type":"Retail Goods"
        }
    ],
    "sg:phone":"+61 7 3245 5570",
    "sg:postcode":"4157",
    "sg:province":"QLD",
    "wof:name":"Its My Party",
    "wof:placetype":"venue"
},
  "geometry": {"coordinates":[153.19456481899999,-27.5274620056],"type":"Point"}
}