{
  "type": "Feature",
  "properties": {
    "iso:country":"AU",
    "sg:address":"48 Stirling Rd",
    "sg:city":"Mt Buller",
    "sg:classifiers":[
        {
            "category":"Sports & Exercise",
            "subcategory":"Ski Resort",
            "type":"Entertainment"
        }
    ],
    "sg:phone":"+61 3 5777 6248",
    "sg:postcode":"3723",
    "sg:province":"VIC",
    "sg:tags":[
        "tour",
        "centres"
    ],
    "wof:name":"Alpine Retreat Pty Ltd",
    "wof:placetype":"venue"
},
  "geometry": {"coordinates":[146.45628356899999,-37.1488342285],"type":"Point"}
}