{
  "type": "Feature",
  "properties": {
    "iso:country":"AU",
    "sg:address":"15 Vanden Way",
    "sg:city":"Joondalup",
    "sg:classifiers":[
        {
            "category":"Shopping",
            "subcategory":"Party Supplies",
            "type":"Retail Goods"
        }
    ],
    "sg:phone":"+61 8 9300 2669",
    "sg:postcode":"6027",
    "sg:province":"WA",
    "sg:website":"http://www.jumbospartyhire.com.au",
    "wof:name":"Jumbo's Party Hire",
    "wof:placetype":"venue"
},
  "geometry": {"coordinates":[115.761016846,-31.7434520721],"type":"Point"}
}