{
  "type": "Feature",
  "properties": {
    "addr:full":"Suite 35 1 Thomas St Hornsby NSW 2077",
    "addr:housenumber":"1",
    "addr:postcode":"2077",
    "addr:street":"Thomas St",
    "iso:country":"AU",
    "sg:address":"Suite 35 1 Thomas St",
    "sg:city":"Hornsby",
    "sg:classifiers":[
        {
            "category":"Professional",
            "subcategory":"Computer Services",
            "type":"Services"
        }
    ],
    "sg:phone":"+61 2 9476 8988",
    "sg:postcode":"2077",
    "sg:province":"NSW",
    "sg:tags":[
        "consultant",
        "system"
    ],
    "wof:name":"Marics System Solutions",
    "wof:placetype":"venue"
},
  "geometry": {"coordinates":[151.10194397000001,-33.7077903748],"type":"Point"}
}