{
  "type": "Feature",
  "properties": {
    "iso:country":"AU",
    "sg:address":"65 McCombe Rd",
    "sg:city":"Bunbury",
    "sg:classifiers":[
        {
            "category":"Professional",
            "subcategory":"Detective & Security Services",
            "type":"Services"
        }
    ],
    "sg:phone":"+61 8 9725 7466",
    "sg:postcode":"6230",
    "sg:province":"WA",
    "sg:tags":[
        "equipment",
        "window",
        "doors"
    ],
    "wof:name":"Ascot Aluminium",
    "wof:placetype":"venue"
},
  "geometry": {"coordinates":[115.681374,-33.363689],"type":"Point"}
}