{
  "type": "Feature",
  "properties": {
    "iso:country":"AU",
    "sg:address":"Unit 10, 63- 65 McAlister St",
    "sg:city":"Sale",
    "sg:classifiers":[
        {
            "category":"Professional",
            "subcategory":"Accounting & Tax Preparation",
            "type":"Services"
        }
    ],
    "sg:phone":"+61 3 5144 7288",
    "sg:postcode":"3850",
    "sg:province":"VIC",
    "sg:tags":[
        "consultant",
        "taxation"
    ],
    "wof:name":"H&R Block",
    "wof:placetype":"venue"
},
  "geometry": {"coordinates":[147.065872192,-38.1092681885],"type":"Point"}
}