{
  "type": "Feature",
  "properties": {
    "iso:country":"AU",
    "sg:address":"10- 12 Lyell St",
    "sg:city":"Fyshwick",
    "sg:classifiers":[
        {
            "category":"Communications",
            "subcategory":"Film & Video Production",
            "type":"Services"
        }
    ],
    "sg:phone":"+61 2 6239 2932",
    "sg:postcode":"2609",
    "sg:province":"ACT",
    "sg:tags":[
        "fan",
        "blower"
    ],
    "wof:name":"Uniflex (Aust) P/L",
    "wof:placetype":"venue"
},
  "geometry": {"coordinates":[149.17396545400001,-35.3283882141],"type":"Point"}
}