{
  "type": "Feature",
  "properties": {
    "addr:full":"St Kilda Sea Baths Complex St Kilda VIC 3182",
    "addr:postcode":"3182",
    "iso:country":"AU",
    "sg:address":"St Kilda Sea Baths Complex St",
    "sg:city":"Kilda",
    "sg:classifiers":[
        {
            "category":"Restaurant",
            "type":"Food & Drink"
        }
    ],
    "sg:phone":"+61 3 8598 9055",
    "sg:postcode":"3182",
    "sg:province":"VIC",
    "wof:name":"Amello",
    "wof:placetype":"venue"
},
  "geometry": {"coordinates":[144.98277282699999,-37.8571586609],"type":"Point"}
}