{
  "type": "Feature",
  "properties": {
    "addr:full":"652 Blackforrest Drv Macedon VIC 3440",
    "addr:housenumber":"652",
    "addr:postcode":"3440",
    "addr:street":"Blackforrest Drv",
    "iso:country":"AU",
    "sg:address":"652 Blackforrest Drv",
    "sg:city":"Macedon",
    "sg:classifiers":[
        {
            "category":"Travel",
            "subcategory":"Hotels & Motels",
            "type":"Entertainment"
        }
    ],
    "sg:phone":"+61 3 5426 4044",
    "sg:postcode":"3440",
    "sg:province":"VIC",
    "sg:tags":[
        "accommodation"
    ],
    "wof:name":"Macedon Spa Motel",
    "wof:placetype":"venue"
},
  "geometry": {"coordinates":[144.54460144000001,-37.4143257141],"type":"Point"}
}