{
  "type": "Feature",
  "properties": {
    "iso:country":"AU",
    "sg:address":"42- 44 Gordon St",
    "sg:city":"Coffs Harbour",
    "sg:classifiers":[
        {
            "category":"Health Services",
            "subcategory":"Doctor",
            "type":"Services"
        }
    ],
    "sg:phone":"+61 2 6648 5222",
    "sg:postcode":"2450",
    "sg:province":"NSW",
    "sg:tags":[
        "medical",
        "practitioner"
    ],
    "wof:name":"May Stephen Dr",
    "wof:placetype":"venue"
},
  "geometry": {"coordinates":[153.118546,-30.295876],"type":"Point"}
}