{
  "type": "Feature",
  "properties": {
    "addr:full":"170 Railway Pde Kogarah NSW 2217",
    "addr:housenumber":"170",
    "addr:postcode":"2217",
    "addr:street":"Railway Pde",
    "iso:country":"AU",
    "sg:address":"170 Railway Pde",
    "sg:city":"Kogarah",
    "sg:classifiers":[
        {
            "category":"Real Estate",
            "subcategory":"Real Estate Agent",
            "type":"Services"
        }
    ],
    "sg:phone":"+61 2 9553 6335",
    "sg:postcode":"2217",
    "sg:province":"NSW",
    "wof:name":"Ray White Kogarah",
    "wof:placetype":"venue"
},
  "geometry": {"coordinates":[151.131439,-33.965904],"type":"Point"}
}