{
  "type": "Feature",
  "properties": {
    "iso:country":"AU",
    "sg:address":"47 Flood St",
    "sg:city":"Leichhardt",
    "sg:classifiers":[
        {
            "category":"Sports & Exercise",
            "subcategory":"Gym",
            "type":"Entertainment"
        }
    ],
    "sg:phone":"+61 2 9518 0954",
    "sg:postcode":"2040",
    "sg:province":"NSW",
    "sg:tags":[
        "pilate",
        "method"
    ],
    "wof:name":"Evolution Pilates",
    "wof:placetype":"venue"
},
  "geometry": {"coordinates":[151.15005500000001,-33.885654],"type":"Point"}
}