{
  "type": "Feature",
  "properties": {
    "addr:full":"Cnr Turton & Fieldsend Sts East Maitland NSW 2323",
    "addr:postcode":"2323",
    "addr:street":"Cnr",
    "iso:country":"AU",
    "sg:address":"Cnr Turton & Fieldsend Sts",
    "sg:city":"East Maitland",
    "sg:classifiers":[
        {
            "category":"Retail",
            "subcategory":"Storage",
            "type":"Services"
        }
    ],
    "sg:phone":"+61 2 4933 7223",
    "sg:postcode":"2323",
    "sg:province":"NSW",
    "wof:name":"The Spaceplace Maitland",
    "wof:placetype":"venue"
},
  "geometry": {"coordinates":[151.60043335,-32.7554893494],"type":"Point"}
}