{
  "type": "Feature",
  "properties": {
    "iso:country":"AU",
    "sg:address":"Golden Grove Drv",
    "sg:city":"Narre Warren",
    "sg:classifiers":[
        {
            "category":"Building & Trades",
            "subcategory":"Construction",
            "type":"Services"
        }
    ],
    "sg:phone":"+61 3 9704 1075",
    "sg:postcode":"3805",
    "sg:province":"VIC",
    "sg:tags":[
        "contractor"
    ],
    "wof:name":"Clarendon Homes",
    "wof:placetype":"venue"
},
  "geometry": {"coordinates":[145.295334,-38.067513],"type":"Point"}
}