{
  "type": "Feature",
  "properties": {
    "addr:full":"10 Tikalara St Regency Park SA 5010",
    "addr:housenumber":"10",
    "addr:postcode":"5010",
    "addr:street":"Tikalara St",
    "iso:country":"AU",
    "sg:address":"10 Tikalara St",
    "sg:city":"Regency Park",
    "sg:classifiers":[
        {
            "category":"Wholesale",
            "subcategory":"Machinery & Supplies",
            "type":"Manufacturing & Wholesale Goods"
        }
    ],
    "sg:phone":"+61 1800 285 904",
    "sg:postcode":"5010",
    "sg:province":"SA",
    "sg:tags":[
        "equipment",
        "hydraulic"
    ],
    "wof:name":"Berendsen Fluid Power Pty Ltd",
    "wof:placetype":"venue"
},
  "geometry": {"coordinates":[138.57215881400001,-34.8701705933],"type":"Point"}
}