{
  "type": "Feature",
  "properties": {
    "addr:full":"53 Russell St Toowoomba QLD 4350",
    "addr:housenumber":"53",
    "addr:postcode":"4350",
    "addr:street":"Russell St",
    "iso:country":"AU",
    "sg:address":"53 Russell St",
    "sg:city":"Toowoomba",
    "sg:classifiers":[
        {
            "category":"Shopping",
            "subcategory":"Computers & Home Electronics",
            "type":"Retail Goods"
        }
    ],
    "sg:phone":"+61 7 4639 6333",
    "sg:postcode":"4350",
    "sg:province":"QLD",
    "sg:tags":[
        "hardware",
        "equipment"
    ],
    "wof:name":"Topline Computers",
    "wof:placetype":"venue"
},
  "geometry": {"coordinates":[151.952606,-27.558836],"type":"Point"}
}