{
  "type": "Feature",
  "properties": {
    "addr:full":"170 St Johns Rd Glebe NSW 2037",
    "addr:housenumber":"170",
    "addr:postcode":"2037",
    "addr:street":"St Johns Rd",
    "iso:country":"AU",
    "sg:address":"170 St Johns Rd",
    "sg:city":"Glebe",
    "sg:classifiers":[
        {
            "category":"Shopping",
            "subcategory":"Clothing, Apparel, & Fashions",
            "type":"Retail Goods"
        }
    ],
    "sg:phone":"+61 2 9660 0488",
    "sg:postcode":"2037",
    "sg:province":"NSW",
    "sg:tags":[
        "sportswear"
    ],
    "wof:name":"Sue Rice Swimwear",
    "wof:placetype":"venue"
},
  "geometry": {"coordinates":[151.18084716800001,-33.8806190491],"type":"Point"}
}