{
  "type": "Feature",
  "properties": {
    "iso:country":"AU",
    "sg:address":"852a Beaufort St",
    "sg:city":"Inglewood",
    "sg:classifiers":[
        {
            "category":"Sports & Exercise",
            "subcategory":"Gym",
            "type":"Entertainment"
        }
    ],
    "sg:phone":"+61 8 9370 4229",
    "sg:postcode":"6052",
    "sg:province":"WA",
    "sg:tags":[
        "health",
        "fitness"
    ],
    "wof:name":"Vibrolife Health",
    "wof:placetype":"venue"
},
  "geometry": {"coordinates":[115.884170532,-31.9230442047],"type":"Point"}
}