{
  "type": "Feature",
  "properties": {
    "addr:full":"45 Tuckey St Mandurah WA 6210",
    "addr:housenumber":"45",
    "addr:postcode":"6210",
    "addr:street":"Tuckey St",
    "iso:country":"AU",
    "sg:address":"45 Tuckey St",
    "sg:city":"Mandurah",
    "sg:classifiers":[
        {
            "category":"Personal",
            "subcategory":"Beauty Salon",
            "type":"Services"
        }
    ],
    "sg:phone":"+61 8 9535 2667",
    "sg:postcode":"6210",
    "sg:province":"WA",
    "sg:tags":[
        "hairdresser"
    ],
    "wof:name":"Aphrodite's Artistic Designers",
    "wof:placetype":"venue"
},
  "geometry": {"coordinates":[115.7257,-32.532772],"type":"Point"}
}