{
  "type": "Feature",
  "properties": {
    "iso:country":"AU",
    "sg:address":"12 Alice St",
    "sg:city":"Cheltenham",
    "sg:classifiers":[
        {
            "category":"Building & Trades",
            "subcategory":"Cleaning & Sanitation",
            "type":"Services"
        }
    ],
    "sg:phone":"+61 3 9583 5073",
    "sg:postcode":"3192",
    "sg:province":"VIC",
    "sg:tags":[
        "cleaner",
        "repairer",
        "roof"
    ],
    "wof:name":"Dingle J & V",
    "wof:placetype":"venue"
},
  "geometry": {"coordinates":[145.07936096200001,-37.9738693237],"type":"Point"}
}