{
  "type": "Feature",
  "properties": {
    "iso:country":"AU",
    "sg:address":"211 Broadmeadow Rd",
    "sg:city":"Broadmeadow",
    "sg:classifiers":[
        {
            "category":"Utilities",
            "subcategory":"Electric",
            "type":"Services"
        }
    ],
    "sg:phone":"+61 2 4961 4746",
    "sg:postcode":"2292",
    "sg:province":"NSW",
    "sg:tags":[
        "electrical",
        "contractor"
    ],
    "wof:name":"Hamilton Electrical Services",
    "wof:placetype":"venue"
},
  "geometry": {"coordinates":[151.73667907699999,-32.9236412048],"type":"Point"}
}