{
  "type": "Feature",
  "properties": {
    "addr:full":"78 High St Terang VIC 3264",
    "addr:housenumber":"78",
    "addr:postcode":"3264",
    "addr:street":"High St",
    "iso:country":"AU",
    "sg:address":"78 High St",
    "sg:city":"Terang",
    "sg:classifiers":[
        {
            "category":"Shopping",
            "subcategory":"Shoes",
            "type":"Retail Goods"
        }
    ],
    "sg:phone":"+61 3 5592 1294",
    "sg:postcode":"3264",
    "sg:province":"VIC",
    "sg:tags":[
        "footwear"
    ],
    "wof:name":"Heel & Toe",
    "wof:placetype":"venue"
},
  "geometry": {"coordinates":[142.91673278799999,-38.2408218384],"type":"Point"}
}