{
  "type": "Feature",
  "properties": {
    "addr:full":"Shop 305 Westfield Shoppingtown Victoria Ave Chatswood NSW 2067",
    "addr:housenumber":"305",
    "addr:postcode":"2067",
    "addr:street":"Westfield Shoppingtown Victoria Ave",
    "iso:country":"AU",
    "sg:address":"Shop 305 Westfield Shoppingtown Victoria Ave",
    "sg:city":"Chatswood",
    "sg:classifiers":[
        {
            "category":"Shopping",
            "subcategory":"Clothing, Apparel, & Fashions",
            "type":"Retail Goods"
        }
    ],
    "sg:phone":"+61 2 9411 7636",
    "sg:postcode":"2067",
    "sg:province":"NSW",
    "sg:tags":[
        "lady",
        "wear"
    ],
    "wof:name":"Portmans",
    "wof:placetype":"venue"
},
  "geometry": {"coordinates":[151.183868408,-33.796081543],"type":"Point"}
}