{
  "type": "Feature",
  "properties": {
    "addr:full":"298 Victoria Ave Chatswood NSW 2057",
    "addr:housenumber":"298",
    "addr:postcode":"2057",
    "addr:street":"Victoria Ave",
    "iso:country":"AU",
    "sg:address":"298 Victoria Ave",
    "sg:city":"Chatswood",
    "sg:classifiers":[
        {
            "category":"Banks & Credit Unions",
            "subcategory":"Bureau De Change",
            "type":"Services"
        }
    ],
    "sg:phone":"+61 1800 637 642",
    "sg:postcode":"2057",
    "sg:province":"NSW",
    "sg:tags":[
        "currency",
        "exchange",
        "foreign"
    ],
    "wof:name":"Travelex",
    "wof:placetype":"venue"
},
  "geometry": {"coordinates":[151.186295,-33.795452],"type":"Point"}
}