{
  "type": "Feature",
  "properties": {
    "addr:full":"Shop 22 d Warriewood Shopping Square Warriewood NSW 2102",
    "addr:housenumber":"shop 22 d",
    "addr:postcode":"2102",
    "addr:street":"Shopping",
    "iso:country":"AU",
    "sg:address":"Shop 22",
    "sg:city":"d Warriewood Shopping Square Warriewood",
    "sg:classifiers":[
        {
            "category":"Personal",
            "subcategory":"Piercing",
            "type":"Services"
        }
    ],
    "sg:phone":"+61 2 9913 1922",
    "sg:postcode":"2102",
    "sg:province":"NSW",
    "sg:tags":[
        "body",
        "ear"
    ],
    "wof:name":"Shape Hair & Body",
    "wof:placetype":"venue"
},
  "geometry": {"coordinates":[151.302628,-33.691463],"type":"Point"}
}