{
  "type": "Feature",
  "properties": {
    "iso:country":"AU",
    "sg:address":"52 Fordson Rd",
    "sg:city":"Campbellfield",
    "sg:classifiers":[
        {
            "category":"Building & Trades",
            "subcategory":"Construction",
            "type":"Services"
        }
    ],
    "sg:phone":"+61 415 529 758",
    "sg:postcode":"3061",
    "sg:province":"VIC",
    "sg:tags":[
        "contractor"
    ],
    "wof:name":"Karison Homes",
    "wof:placetype":"venue"
},
  "geometry": {"coordinates":[144.95999145499999,-37.6738700867],"type":"Point"}
}