{
  "type": "Feature",
  "properties": {
    "addr:full":"12 Grevillea St Byron Bay NSW 2481",
    "addr:housenumber":"12",
    "addr:postcode":"2481",
    "addr:street":"Grevillea St",
    "iso:country":"AU",
    "sg:address":"12 Grevillea St",
    "sg:city":"Byron Bay",
    "sg:classifiers":[
        {
            "category":"Wholesale",
            "subcategory":"Auto Parts",
            "type":"Manufacturing & Wholesale Goods"
        }
    ],
    "sg:phone":"+61 2 6685 7909",
    "sg:postcode":"2481",
    "sg:province":"NSW",
    "sg:tags":[
        "recyclers"
    ],
    "wof:name":"Byron Bay European Warehouse",
    "wof:placetype":"venue"
},
  "geometry": {"coordinates":[153.58241272000001,-28.6367835999],"type":"Point"}
}