{
  "type": "Feature",
  "properties": {
    "addr:full":"Shop 3 Bouke St Melbourne VIC 3000",
    "addr:housenumber":"shop 3",
    "addr:postcode":"3000",
    "addr:street":"Bouke St",
    "iso:country":"AU",
    "sg:address":"Shop 3 Bouke St",
    "sg:city":"Melbourne",
    "sg:classifiers":[
        {
            "category":"Personal",
            "subcategory":"Beauty Salon",
            "type":"Services"
        }
    ],
    "sg:phone":"+61 3 9639 2669",
    "sg:postcode":"3000",
    "sg:province":"VIC",
    "sg:tags":[
        "hairdresser"
    ],
    "wof:name":"Wax Mens Haircutters",
    "wof:placetype":"venue"
},
  "geometry": {"coordinates":[144.97303772000001,-37.8114814758],"type":"Point"}
}