{
  "type": "Feature",
  "properties": {
    "addr:full":"28 Colray Ave Osborne Park WA 6017",
    "addr:housenumber":"28",
    "addr:postcode":"6017",
    "addr:street":"Colray Ave",
    "iso:country":"AU",
    "sg:address":"28 Colray Ave",
    "sg:city":"Osborne Park",
    "sg:classifiers":[
        {
            "category":"Wholesale",
            "subcategory":"Construction Materials",
            "type":"Manufacturing & Wholesale Goods"
        }
    ],
    "sg:phone":"+61 8 9443 9477",
    "sg:postcode":"6017",
    "sg:province":"WA",
    "sg:tags":[
        "wholesaler",
        "equipment",
        "bathroom",
        "mfrs",
        "accessory"
    ],
    "wof:name":"Marbletrend Bathroom Industries",
    "wof:placetype":"venue"
},
  "geometry": {"coordinates":[115.81909942599999,-31.908826828],"type":"Point"}
}