{
  "type": "Feature",
  "properties": {
    "addr:full":"20 Hackett St Pascoe Vale VIC 3044",
    "addr:housenumber":"20",
    "addr:postcode":"3044",
    "addr:street":"Hackett St",
    "iso:country":"AU",
    "sg:address":"20 Hackett St",
    "sg:city":"Pascoe Vale",
    "sg:classifiers":[
        {
            "category":"Building & Trades",
            "subcategory":"Plumbing",
            "type":"Services"
        }
    ],
    "sg:phone":"+61 412 390 899",
    "sg:postcode":"3044",
    "sg:province":"VIC",
    "sg:tags":[
        "plumber",
        "gasfitters"
    ],
    "wof:name":"G.J.L. Plumbing Services",
    "wof:placetype":"venue"
},
  "geometry": {"coordinates":[144.93318176299999,-37.7402801514],"type":"Point"}
}