{
  "type": "Feature",
  "properties": {
    "addr:full":"Cnr Namatjira Drv & McNalley St Weston ACT 2611",
    "addr:postcode":"2611",
    "addr:street":"Cnr Namatjira Drv & Mcnalley St",
    "iso:country":"AU",
    "sg:address":"Cnr Namatjira Drv & McNalley St",
    "sg:city":"Weston",
    "sg:classifiers":[
        {
            "category":"Fast Food",
            "type":"Food & Drink"
        }
    ],
    "sg:phone":"+61 2 6288 4811",
    "sg:postcode":"2611",
    "sg:province":"ACT",
    "sg:tags":[
        "away",
        "take"
    ],
    "wof:name":"McDonald's Family Restaurants",
    "wof:placetype":"venue"
},
  "geometry": {"coordinates":[149.05480957,-35.3392753601],"type":"Point"}
}