{
  "type": "Feature",
  "properties": {
    "addr:full":"Suite 4/ Level 1/ 81 Great North Rd Five Dock NSW 2046",
    "addr:housenumber":"/ 81",
    "addr:postcode":"2046",
    "addr:street":"Great North Rd",
    "iso:country":"AU",
    "sg:address":"Suite 4/ Level 1/ 81 Great North Rd",
    "sg:city":"Five Dock",
    "sg:classifiers":[
        {
            "category":"Banks & Credit Unions",
            "subcategory":"Investment Brokerage",
            "type":"Services"
        }
    ],
    "sg:phone":"+61 2 9712 1111",
    "sg:postcode":"2046",
    "sg:province":"NSW",
    "wof:name":"Primrose Financial Group",
    "wof:placetype":"venue"
},
  "geometry": {"coordinates":[151.12956199999999,-33.869602],"type":"Point"}
}