{
  "type": "Feature",
  "properties": {
    "iso:country":"AU",
    "sg:address":"48b Wantirna Rd",
    "sg:city":"Ringwood",
    "sg:classifiers":[
        {
            "category":"Donuts",
            "subcategory":"None",
            "type":"Food & Drink"
        }
    ],
    "sg:phone":"+61 3 9879 4011",
    "sg:postcode":"3134",
    "sg:province":"VIC",
    "sg:tags":[
        "die",
        "engraver",
        "sinker"
    ],
    "wof:name":"The Engraver",
    "wof:placetype":"venue"
},
  "geometry": {"coordinates":[145.22714233400001,-37.8210906982],"type":"Point"}
}