{
  "type": "Feature",
  "properties": {
    "addr:full":"558 Princes Hwy Kirrawee NSW 2232",
    "addr:housenumber":"558",
    "addr:postcode":"2232",
    "addr:street":"Princes Hwy",
    "iso:country":"AU",
    "sg:address":"558 Princes Hwy",
    "sg:city":"Kirrawee",
    "sg:classifiers":[
        {
            "category":"Home & Garden",
            "subcategory":"Building Materials",
            "type":"Retail Goods"
        }
    ],
    "sg:phone":"+61 2 9542 3300",
    "sg:postcode":"2232",
    "sg:province":"NSW",
    "sg:tags":[
        "supply"
    ],
    "wof:name":"Hudson Building Supplies",
    "wof:placetype":"venue"
},
  "geometry": {"coordinates":[151.07307434099999,-34.0323753357],"type":"Point"}
}