{
  "type": "Feature",
  "properties": {
    "iso:country":"AU",
    "sg:address":"PO Box 2061",
    "sg:city":"Grovedale East",
    "sg:classifiers":[
        {
            "category":"Building & Trades",
            "subcategory":"Cleaning & Sanitation",
            "type":"Services"
        }
    ],
    "sg:phone":"+61 418 348 766",
    "sg:postcode":"3216",
    "sg:province":"VIC",
    "sg:tags":[
        "cleaner",
        "repairer",
        "roof"
    ],
    "wof:name":"City Roof Maintenance Pty Ltd",
    "wof:placetype":"venue"
},
  "geometry": {"coordinates":[144.299560547,-38.2272911072],"type":"Point"}
}