{
  "type": "Feature",
  "properties": {
    "addr:full":"33 Nautilus Crs St Huberts Island NSW 2257",
    "addr:housenumber":"33",
    "addr:postcode":"2257",
    "addr:street":"Nautilus Crs St",
    "iso:country":"AU",
    "sg:address":"33 Nautilus Crs St",
    "sg:city":"Huberts Island",
    "sg:classifiers":[
        {
            "category":"Building & Trades",
            "subcategory":"Plumbing",
            "type":"Services"
        }
    ],
    "sg:phone":"+61 2 4342 3227",
    "sg:postcode":"2257",
    "sg:province":"NSW",
    "sg:tags":[
        "plumber",
        "gasfitters"
    ],
    "wof:name":"Delaney Plumbing",
    "wof:placetype":"venue"
},
  "geometry": {"coordinates":[151.34226989699999,-33.4899101257],"type":"Point"}
}