{
  "type": "Feature",
  "properties": {
    "iso:country":"AU",
    "sg:address":"28 Piper St",
    "sg:city":"Caboolture",
    "sg:classifiers":[
        {
            "category":"Professional",
            "type":"Services"
        }
    ],
    "sg:phone":"+61 7 5432 3555",
    "sg:postcode":"4510",
    "sg:province":"QLD",
    "sg:tags":[
        "control",
        "equipment",
        "traffic"
    ],
    "wof:name":"Men At Work Traffic Control",
    "wof:placetype":"venue"
},
  "geometry": {"coordinates":[152.983643,-27.083279],"type":"Point"}
}