{
  "type": "Feature",
  "properties": {
    "addr:full":"256 Toongabbie Rd Girraween NSW 2145",
    "addr:housenumber":"256",
    "addr:postcode":"2145",
    "addr:street":"Toongabbie Rd",
    "iso:country":"AU",
    "sg:address":"256 Toongabbie Rd",
    "sg:city":"Girraween",
    "sg:classifiers":[
        {
            "category":"Home & Garden",
            "subcategory":"Building Materials",
            "type":"Retail Goods"
        }
    ],
    "sg:phone":"+61 2 9896 7485",
    "sg:postcode":"2145",
    "sg:province":"NSW",
    "sg:tags":[
        "lawn",
        "cutting",
        "maintenance"
    ],
    "wof:name":"Kennards Groundcare Hire",
    "wof:placetype":"venue"
},
  "geometry": {"coordinates":[150.93513488799999,-33.8060455322],"type":"Point"}
}