{
  "type": "Feature",
  "properties": {
    "iso:country":"AU",
    "sg:address":"54 Hannah Ave",
    "sg:city":"Sydenham",
    "sg:classifiers":[
        {
            "category":"Professional",
            "subcategory":"Art Services",
            "type":"Services"
        }
    ],
    "sg:phone":"+61 3 9390 4353",
    "sg:postcode":"3037",
    "sg:province":"VIC",
    "sg:tags":[
        "decorator",
        "painter"
    ],
    "wof:name":"Niklaz Pty Ltd",
    "wof:placetype":"venue"
},
  "geometry": {"coordinates":[144.753204,-37.700756],"type":"Point"}
}