{
  "type": "Feature",
  "properties": {
    "addr:full":"4/ 9 Farrall Rd Midvale WA 6056",
    "addr:housenumber":"/ 9",
    "addr:postcode":"6056",
    "addr:street":"Farrall Rd",
    "iso:country":"AU",
    "sg:address":"4/ 9 Farrall Rd",
    "sg:city":"Midvale",
    "sg:classifiers":[
        {
            "category":"Shopping",
            "subcategory":"Clothing, Apparel, & Fashions",
            "type":"Retail Goods"
        }
    ],
    "sg:phone":"+61 8 9274 5547",
    "sg:postcode":"6056",
    "sg:province":"WA",
    "sg:tags":[
        "lingerie",
        "hosiery",
        "sleepwear"
    ],
    "wof:name":"Lacere Lingerie",
    "wof:placetype":"venue"
},
  "geometry": {"coordinates":[116.032608032,-31.8936767578],"type":"Point"}
}