{
  "type": "Feature",
  "properties": {
    "iso:country":"AU",
    "sg:address":"80 Main St",
    "sg:city":"Woodside",
    "sg:classifiers":[
        {
            "category":"Real Estate",
            "subcategory":"Real Estate Agent",
            "type":"Services"
        }
    ],
    "sg:phone":"+61 8 8389 7787",
    "sg:postcode":"5244",
    "sg:province":"SA",
    "wof:name":"Raine & Horne",
    "wof:placetype":"venue"
},
  "geometry": {"coordinates":[138.87457275400001,-34.9038581848],"type":"Point"}
}