{
  "type": "Feature",
  "properties": {
    "iso:country":"AU",
    "sg:address":"56 Water St",
    "sg:city":"Caringbah",
    "sg:classifiers":[
        {
            "category":"Building & Trades",
            "subcategory":"Construction",
            "type":"Services"
        }
    ],
    "sg:phone":"+61 419 616 697",
    "sg:postcode":"2229",
    "sg:province":"NSW",
    "sg:tags":[
        "contractor"
    ],
    "wof:name":"Burraneer Bay Building",
    "wof:placetype":"venue"
},
  "geometry": {"coordinates":[151.13192749000001,-34.056350708],"type":"Point"}
}