{
  "type": "Feature",
  "properties": {
    "addr:full":"40 Canterbury St Oakleigh VIC 3166",
    "addr:housenumber":"40",
    "addr:postcode":"3166",
    "addr:street":"Canterbury St",
    "iso:country":"AU",
    "sg:address":"40 Canterbury St",
    "sg:city":"Oakleigh",
    "sg:classifiers":[
        {
            "category":"Professional",
            "subcategory":"Art Services",
            "type":"Services"
        }
    ],
    "sg:phone":"+61 3 9568 4875",
    "sg:postcode":"3166",
    "sg:province":"VIC",
    "sg:tags":[
        "decorator",
        "painter"
    ],
    "wof:name":"V & R Moore Painting",
    "wof:placetype":"venue"
},
  "geometry": {"coordinates":[145.081100464,-37.9042243958],"type":"Point"}
}