{
  "type": "Feature",
  "properties": {
    "addr:full":"PO Box 6426 South Sydney BC NSW 2015",
    "addr:postcode":"nsw 2015",
    "addr:street":"South",
    "iso:country":"AU",
    "sg:address":"PO Box 6426",
    "sg:city":"South Sydney BC",
    "sg:classifiers":[
        {
            "category":"Professional",
            "subcategory":"Detective & Security Services",
            "type":"Services"
        }
    ],
    "sg:phone":"+61 1300 882 373",
    "sg:postcode":"2015",
    "sg:province":"NSW",
    "sg:tags":[
        "guard",
        "patrol"
    ],
    "sg:website":"http://www.asap.com.au",
    "wof:name":"ASAP Australian Security & Protection",
    "wof:placetype":"venue"
},
  "geometry": {"coordinates":[151.201248169,-33.9130210876],"type":"Point"}
}