{
  "type": "Feature",
  "properties": {
    "addr:full":"496 Napier St White Hills VIC 3550",
    "addr:housenumber":"496",
    "addr:postcode":"3550",
    "addr:street":"Napier St",
    "iso:country":"AU",
    "sg:address":"496 Napier St",
    "sg:city":"White Hills",
    "sg:classifiers":[
        {
            "category":"Personal",
            "subcategory":"Massage",
            "type":"Services"
        }
    ],
    "sg:phone":"+61 3 5442 8849",
    "sg:postcode":"3550",
    "sg:province":"VIC",
    "sg:tags":[
        "therapy"
    ],
    "wof:name":"Lawry Kate",
    "wof:placetype":"venue"
},
  "geometry": {"coordinates":[144.30599975600001,-36.7302474976],"type":"Point"}
}