{
  "type": "Feature",
  "properties": {
    "iso:country":"AU",
    "sg:address":"Lot84 Mummery Crs",
    "sg:city":"East Bunbury",
    "sg:classifiers":[
        {
            "category":"Retail",
            "subcategory":"Auto Repair",
            "type":"Services"
        }
    ],
    "sg:phone":"+61 8 9792 4288",
    "sg:postcode":"6230",
    "sg:province":"WA",
    "sg:tags":[
        "gas",
        "conversion",
        "natural",
        "lp",
        "vehicle"
    ],
    "wof:name":"Farmport Auto Gas",
    "wof:placetype":"venue"
},
  "geometry": {"coordinates":[115.654541,-33.338879],"type":"Point"}
}