{
  "type": "Feature",
  "properties": {
    "addr:full":"Lvl 13/ 390 St Kilda Rd Melbourne VIC 3000",
    "addr:housenumber":"/ 390",
    "addr:postcode":"3000",
    "addr:street":"St Kilda Rd",
    "iso:country":"AU",
    "sg:address":"Lvl 13/ 390 St Kilda Rd",
    "sg:city":"Melbourne",
    "sg:classifiers":[
        {
            "category":"Banks & Credit Unions",
            "subcategory":"Financial Services",
            "type":"Services"
        }
    ],
    "sg:phone":"+61 1300 669 891",
    "sg:postcode":"3000",
    "sg:province":"VIC",
    "sg:tags":[
        "planning"
    ],
    "wof:name":"DirEquity Pty Ltd",
    "wof:placetype":"venue"
},
  "geometry": {"coordinates":[144.97352600100001,-37.8341751099],"type":"Point"}
}