{
  "type": "Feature",
  "properties": {
    "iso:country":"AU",
    "sg:address":"Suite A1, 2 Reliance Drv",
    "sg:city":"Tuggerah Business Park Tuggerah",
    "sg:classifiers":[
        {
            "category":"Education",
            "subcategory":"Special Training",
            "type":"Public Place"
        }
    ],
    "sg:phone":"+61 2 4355 1659",
    "sg:postcode":"2259",
    "sg:province":"NSW",
    "sg:tags":[
        "development"
    ],
    "wof:name":"Ready Workforce",
    "wof:placetype":"venue"
},
  "geometry": {"coordinates":[151.421142578,-33.3138313293],"type":"Point"}
}