{
  "type": "Feature",
  "properties": {
    "addr:full":"61 Longfield St Cabramatta NSW 2166",
    "addr:housenumber":"61",
    "addr:postcode":"2166",
    "addr:street":"Longfield St",
    "iso:country":"AU",
    "sg:address":"61 Longfield St",
    "sg:city":"Cabramatta",
    "sg:classifiers":[
        {
            "category":"Food & Beverages",
            "subcategory":"Supermarket",
            "type":"Retail Goods"
        }
    ],
    "sg:phone":"+61 2 9724 0807",
    "sg:postcode":"2166",
    "sg:province":"NSW",
    "sg:tags":[
        "grocery",
        "store"
    ],
    "wof:name":"Longfield Supermarket",
    "wof:placetype":"venue"
},
  "geometry": {"coordinates":[150.94517517099999,-33.8933563232],"type":"Point"}
}