{
  "type": "Feature",
  "properties": {
    "addr:full":"4 Belgrave Ave Cockatoo VIC 3781",
    "addr:housenumber":"4",
    "addr:postcode":"3781",
    "addr:street":"Belgrave Ave Cockatoo",
    "iso:country":"AU",
    "sg:address":"4 Belgrave Ave",
    "sg:city":"Cockatoo",
    "sg:classifiers":[
        {
            "category":"Professional",
            "subcategory":"Computer Services",
            "type":"Services"
        }
    ],
    "sg:phone":"+61 3 5968 9298",
    "sg:postcode":"3781",
    "sg:province":"VIC",
    "sg:tags":[
        "package",
        "software"
    ],
    "wof:name":"Sootys Computers",
    "wof:placetype":"venue"
},
  "geometry": {"coordinates":[145.495667,-37.927177],"type":"Point"}
}