{
  "type": "Feature",
  "properties": {
    "iso:country":"AU",
    "sg:address":"3/ 1 Gibbens Rd",
    "sg:city":"Gosford West",
    "sg:classifiers":[
        {
            "category":"Professional",
            "subcategory":"Engineering",
            "type":"Services"
        }
    ],
    "sg:phone":"+61 2 4323 9494",
    "sg:postcode":"2250",
    "sg:province":"NSW",
    "sg:tags":[
        "electronic",
        "engineer"
    ],
    "wof:name":"Gabriel Electronics",
    "wof:placetype":"venue"
},
  "geometry": {"coordinates":[151.324676514,-33.4153366089],"type":"Point"}
}