{
  "type": "Feature",
  "properties": {
    "iso:country":"AU",
    "sg:address":"Break-O-Day Drv",
    "sg:city":"Australind",
    "sg:classifiers":[
        {
            "category":"Building & Trades",
            "subcategory":"Construction",
            "type":"Services"
        }
    ],
    "sg:phone":"+61 8 9797 1167",
    "sg:postcode":"6233",
    "sg:province":"WA",
    "sg:tags":[
        "pool",
        "swimming"
    ],
    "wof:name":"Australind Pools",
    "wof:placetype":"venue"
},
  "geometry": {"coordinates":[115.727379,-33.277546],"type":"Point"}
}