{
  "type": "Feature",
  "properties": {
    "addr:full":"63-65 Sheppard St Hume ACT 2620",
    "addr:housenumber":"63-65",
    "addr:postcode":"2620",
    "addr:street":"Sheppard St",
    "iso:country":"AU",
    "sg:address":"63-65 Sheppard St",
    "sg:city":"Hume",
    "sg:classifiers":[
        {
            "category":"Shopping",
            "subcategory":"Pets & Pet Supplies",
            "type":"Retail Goods"
        }
    ],
    "sg:phone":"+61 2 6260 1010",
    "sg:postcode":"2620",
    "sg:province":"ACT",
    "sg:tags":[
        "dog"
    ],
    "wof:name":"ACT Dog World",
    "wof:placetype":"venue"
},
  "geometry": {"coordinates":[149.165359497,-35.3923873901],"type":"Point"}
}