{
  "type": "Feature",
  "properties": {
    "addr:full":"New England Hwy Murrurundi NSW 2338",
    "addr:postcode":"2338",
    "addr:street":"England Hwy",
    "iso:country":"AU",
    "sg:address":"New England Hwy",
    "sg:city":"Murrurundi",
    "sg:classifiers":[
        {
            "category":"Travel",
            "subcategory":"Hotels & Motels",
            "type":"Entertainment"
        }
    ],
    "sg:phone":"+61 2 6546 6082",
    "sg:postcode":"2338",
    "sg:province":"NSW",
    "wof:name":"Motel Murrurundi",
    "wof:placetype":"venue"
},
  "geometry": {"coordinates":[150.83421325699999,-31.763338089],"type":"Point"}
}