{
  "type": "Feature",
  "properties": {
    "iso:country":"AU",
    "sg:address":"1038 Albany Hwy",
    "sg:city":"St James",
    "sg:classifiers":[
        {
            "category":"Autos & Motor Vehicles",
            "subcategory":"Automobile Sales",
            "type":"Retail Goods"
        }
    ],
    "sg:phone":"+61 8 9361 0020",
    "sg:postcode":"6102",
    "sg:province":"WA",
    "sg:tags":[
        "car",
        "used"
    ],
    "wof:name":"St James Auto Trader",
    "wof:placetype":"venue"
},
  "geometry": {"coordinates":[115.915786743,-31.997713089],"type":"Point"}
}