{
  "type": "Feature",
  "properties": {
    "addr:full":"Cnr Park Ave & Northcote Drv Adamstown NSW 2289",
    "addr:postcode":"2289",
    "addr:street":"Ave;Northcote Drv",
    "iso:country":"AU",
    "sg:address":"Cnr Park Ave & Northcote Drv",
    "sg:city":"Adamstown",
    "sg:classifiers":[
        {
            "category":"Food & Beverages",
            "subcategory":"Liquor & Beverages",
            "type":"Retail Goods"
        }
    ],
    "sg:phone":"+61 2 4957 0355",
    "sg:postcode":"2289",
    "sg:province":"NSW",
    "sg:tags":[
        "store"
    ],
    "wof:name":"Macs Liquor",
    "wof:placetype":"venue"
},
  "geometry": {"coordinates":[151.720626831,-32.9336967468],"type":"Point"}
}