{
  "type": "Feature",
  "properties": {
    "iso:country":"AU",
    "sg:address":"61 Ravenwood Rd",
    "sg:city":"Launceston",
    "sg:classifiers":[
        {
            "category":"Commercial Area",
            "type":"Public Place"
        }
    ],
    "sg:phone":"+61 408 134 987",
    "sg:postcode":"7250",
    "sg:province":"TAS",
    "sg:tags":[
        "heavy",
        "carrier"
    ],
    "wof:name":"Ben Wright Transport",
    "wof:placetype":"venue"
},
  "geometry": {"coordinates":[147.17405700699999,-41.425113678],"type":"Point"}
}