{
  "type": "Feature",
  "properties": {
    "addr:full":"650 Main Rd Berriedale TAS 7011",
    "addr:housenumber":"650",
    "addr:postcode":"7011",
    "addr:street":"Main Rd",
    "iso:country":"AU",
    "sg:address":"650 Main Rd",
    "sg:city":"Berriedale",
    "sg:classifiers":[
        {
            "category":"Building & Trades",
            "subcategory":"Construction",
            "type":"Services"
        }
    ],
    "sg:phone":"+61 3 6239 0425",
    "sg:postcode":"7011",
    "sg:province":"TAS",
    "sg:tags":[
        "joinery"
    ],
    "wof:name":"Careforce Maintenance Group Pty Ltd",
    "wof:placetype":"venue"
},
  "geometry": {"coordinates":[147.254730225,-42.8135604858],"type":"Point"}
}