{
  "type": "Feature",
  "properties": {
    "iso:country":"AU",
    "sg:address":"Cnr Kent & Erskine Sts",
    "sg:city":"Sydney",
    "sg:classifiers":[
        {
            "category":"Food & Beverages",
            "subcategory":"Liquor & Beverages",
            "type":"Retail Goods"
        }
    ],
    "sg:phone":"+61 2 9279 3133",
    "sg:postcode":"2001",
    "sg:province":"NSW",
    "sg:tags":[
        "store"
    ],
    "wof:name":"Pubmart",
    "wof:placetype":"venue"
},
  "geometry": {"coordinates":[151.20439148,-33.8667144775],"type":"Point"}
}