{
  "type": "Feature",
  "properties": {
    "addr:full":"51 Herbert St Ingham QLD 4850",
    "addr:housenumber":"51",
    "addr:postcode":"4850",
    "addr:street":"Herbert St",
    "iso:country":"AU",
    "sg:address":"51 Herbert St",
    "sg:city":"Ingham",
    "sg:classifiers":[
        {
            "category":"Retail",
            "subcategory":"Auto Repair",
            "type":"Services"
        }
    ],
    "sg:phone":"+61 7 4776 2050",
    "sg:postcode":"4850",
    "sg:province":"QLD",
    "sg:tags":[
        "repairer",
        "motor",
        "engineer"
    ],
    "wof:name":"Toigo S & N C",
    "wof:placetype":"venue"
},
  "geometry": {"coordinates":[146.15870666500001,-18.6488399506],"type":"Point"}
}