{
  "type": "Feature",
  "properties": {
    "addr:full":"57 Winchester Rd Alexandra Hills QLD 4161",
    "addr:housenumber":"57",
    "addr:postcode":"4161",
    "addr:street":"Winchester Rd",
    "iso:country":"AU",
    "sg:address":"57 Winchester Rd",
    "sg:city":"Alexandra Hills",
    "sg:classifiers":[
        {
            "category":"Home & Garden",
            "subcategory":"Building Materials",
            "type":"Retail Goods"
        }
    ],
    "sg:phone":"+61 7 3824 7221",
    "sg:postcode":"4161",
    "sg:province":"QLD",
    "sg:tags":[
        "merchant",
        "glass",
        "glazier"
    ],
    "wof:name":"Gecko Glass",
    "wof:placetype":"venue"
},
  "geometry": {"coordinates":[153.23373413100001,-27.5318584442],"type":"Point"}
}