{
  "type": "Feature",
  "properties": {
    "addr:full":"Pier 35 Marina 263- 329 Lorimer St Port Melbourne VIC 3207",
    "addr:housenumber":"263 329",
    "addr:postcode":"3207",
    "addr:street":"Marina;Lorimer St",
    "iso:country":"AU",
    "sg:address":"Pier 35 Marina 263- 329 Lorimer St",
    "sg:city":"Port Melbourne",
    "sg:classifiers":[
        {
            "category":"Recreation",
            "subcategory":"Boat Charter",
            "type":"Entertainment"
        }
    ],
    "sg:phone":"+61 3 9645 1100",
    "sg:postcode":"3207",
    "sg:province":"VIC",
    "sg:tags":[
        "hire",
        "drive"
    ],
    "wof:name":"Pier 35 Boat Rentals",
    "wof:placetype":"venue"
},
  "geometry": {"coordinates":[144.906845,-37.824261],"type":"Point"}
}