{
  "type": "Feature",
  "properties": {
    "iso:country":"AU",
    "sg:address":"27 Vista St",
    "sg:city":"Greenwich",
    "sg:classifiers":[
        {
            "category":"Professional",
            "subcategory":"Business Services",
            "type":"Services"
        }
    ],
    "sg:phone":"+61 2 9460 7020",
    "sg:postcode":"2065",
    "sg:province":"NSW",
    "sg:tags":[
        "broker"
    ],
    "wof:name":"Pharmacy Solutions",
    "wof:placetype":"venue"
},
  "geometry": {"coordinates":[151.18756103499999,-33.8334274292],"type":"Point"}
}