{
  "type": "Feature",
  "properties": {
    "iso:country":"AU",
    "sg:address":"1221 Sandgate Rd",
    "sg:city":"Nundah",
    "sg:classifiers":[
        {
            "category":"Real Estate",
            "subcategory":"Real Estate Agent",
            "type":"Services"
        }
    ],
    "sg:phone":"+61 7 3833 6650",
    "sg:postcode":"4012",
    "sg:province":"QLD",
    "wof:name":"Rental Hotline",
    "wof:placetype":"venue"
},
  "geometry": {"coordinates":[153.06048584000001,-27.4026145935],"type":"Point"}
}