{
  "type": "Feature",
  "properties": {
    "addr:full":"Shop 8/ 27 Park Ave Burleigh Heads QLD 4220",
    "addr:housenumber":"shop 8 / 27",
    "addr:postcode":"4220",
    "addr:street":"Park Ave",
    "iso:country":"AU",
    "sg:address":"Shop 8/ 27 Park Ave",
    "sg:city":"Burleigh Heads",
    "sg:classifiers":[
        {
            "category":"Food & Beverages",
            "subcategory":"Specialty",
            "type":"Retail Goods"
        }
    ],
    "sg:phone":"+61 7 5576 1777",
    "sg:postcode":"4220",
    "sg:province":"QLD",
    "sg:tags":[
        "product",
        "health"
    ],
    "wof:name":"Physical Action Sports Supplies",
    "wof:placetype":"venue"
},
  "geometry": {"coordinates":[153.44955444300001,-28.0898342133],"type":"Point"}
}