{
  "type": "Feature",
  "properties": {
    "addr:full":"9 Colo St Arana Hills QLD 4054",
    "addr:housenumber":"9",
    "addr:postcode":"4054",
    "addr:street":"Colo St",
    "iso:country":"AU",
    "sg:address":"9 Colo St",
    "sg:city":"Arana Hills",
    "sg:classifiers":[
        {
            "category":"Professional",
            "subcategory":"Research",
            "type":"Services"
        }
    ],
    "sg:phone":"+61 7 3351 6371",
    "sg:postcode":"4054",
    "sg:province":"QLD",
    "sg:tags":[
        "historical"
    ],
    "wof:name":"Brisbane History Group",
    "wof:placetype":"venue"
},
  "geometry": {"coordinates":[152.95758056599999,-27.3933143616],"type":"Point"}
}