{
  "type": "Feature",
  "properties": {
    "iso:country":"AU",
    "sg:address":"Shp 6/ 465 Oxley Rd",
    "sg:city":"Sherwood",
    "sg:classifiers":[
        {
            "category":"Arts & Performance",
            "subcategory":"Art Gallery",
            "type":"Entertainment"
        }
    ],
    "sg:phone":"+61 7 3379 7828",
    "sg:postcode":"4075",
    "sg:province":"QLD",
    "wof:name":"Lily-Lee Gallery & Studios",
    "wof:placetype":"venue"
},
  "geometry": {"coordinates":[152.98304748499999,-27.5312175751],"type":"Point"}
}