{
  "type": "Feature",
  "properties": {
    "iso:country":"AU",
    "sg:address":"275 Lonsdale St",
    "sg:city":"Dandenong",
    "sg:classifiers":[
        {
            "category":"Food & Beverages",
            "subcategory":"Supermarket",
            "type":"Retail Goods"
        }
    ],
    "sg:phone":"+61 3 9792 2366",
    "sg:postcode":"3175",
    "sg:province":"VIC",
    "sg:tags":[
        "grocery",
        "store"
    ],
    "wof:name":"Supreme Enterprise International",
    "wof:placetype":"venue"
},
  "geometry": {"coordinates":[145.213943481,-37.9873924255],"type":"Point"}
}