{
  "type": "Feature",
  "properties": {
    "iso:country":"AU",
    "sg:address":"187 Weidlich Rd",
    "sg:city":"Eltham North",
    "sg:classifiers":[
        {
            "category":"Building & Trades",
            "subcategory":"Construction",
            "type":"Services"
        }
    ],
    "sg:phone":"+61 3 9432 1013",
    "sg:postcode":"3095",
    "sg:province":"VIC",
    "sg:tags":[
        "contractor"
    ],
    "wof:name":"Colautti Builders Pty Ltd",
    "wof:placetype":"venue"
},
  "geometry": {"coordinates":[145.13548278799999,-37.6883583069],"type":"Point"}
}