{
  "type": "Feature",
  "properties": {
    "iso:country":"AU",
    "sg:address":"17 Trinity Crs",
    "sg:city":"Sippy Downs",
    "sg:classifiers":[
        {
            "category":"Building & Trades",
            "subcategory":"Construction",
            "type":"Services"
        }
    ],
    "sg:phone":"+61 7 5476 6705",
    "sg:postcode":"4556",
    "sg:province":"QLD",
    "sg:tags":[
        "concrete",
        "contractor"
    ],
    "wof:name":"p.Vel's Concreting",
    "wof:placetype":"venue"
},
  "geometry": {"coordinates":[153.056762695,-26.7121295929],"type":"Point"}
}