{
  "type": "Feature",
  "properties": {
    "addr:full":"Cnr Cumberland Hwy & Neville St Smithfield NSW 2164",
    "addr:postcode":"2164",
    "addr:street":"Cnr Cumberland Hwy & Neville St",
    "iso:country":"AU",
    "sg:address":"Cnr Cumberland Hwy & Neville St",
    "sg:city":"Smithfield",
    "sg:classifiers":[
        {
            "category":"Retail",
            "subcategory":"Event Space",
            "type":"Services"
        }
    ],
    "sg:phone":"+61 2 9604 4411",
    "sg:postcode":"2164",
    "sg:province":"NSW",
    "sg:tags":[
        "venue",
        "reception",
        "wedding"
    ],
    "wof:name":"Smithfield RSL Club",
    "wof:placetype":"venue"
},
  "geometry": {"coordinates":[150.92982482900001,-33.8538856506],"type":"Point"}
}