{
  "type": "Feature",
  "properties": {
    "addr:full":"76 Jetty Rd Glenelg SA 5045",
    "addr:housenumber":"76",
    "addr:postcode":"5045",
    "addr:street":"Jetty Rd",
    "iso:country":"AU",
    "sg:address":"76 Jetty Rd",
    "sg:city":"Glenelg",
    "sg:classifiers":[
        {
            "category":"Travel",
            "subcategory":"Travel Agent",
            "type":"Entertainment"
        }
    ],
    "sg:phone":"+61 8 8295 8291",
    "sg:postcode":"5045",
    "sg:province":"SA",
    "sg:tags":[
        "consultant"
    ],
    "wof:name":"Escape Travel",
    "wof:placetype":"venue"
},
  "geometry": {"coordinates":[138.51507599999999,-34.980427],"type":"Point"}
}