{
  "type": "Feature",
  "properties": {
    "addr:full":"5 Wilding St Bundaberg QLD 4670",
    "addr:housenumber":"5",
    "addr:postcode":"4670",
    "addr:street":"Wilding St",
    "iso:country":"AU",
    "sg:address":"5 Wilding St",
    "sg:city":"Bundaberg",
    "sg:classifiers":[
        {
            "category":"Building & Trades",
            "subcategory":"Pest Control",
            "type":"Services"
        }
    ],
    "sg:phone":"+61 7 4152 6275",
    "sg:postcode":"4670",
    "sg:province":"QLD",
    "wof:name":"You Beaut Pest Control",
    "wof:placetype":"venue"
},
  "geometry": {"coordinates":[152.36360168499999,-24.8723297119],"type":"Point"}
}