{
  "type": "Feature",
  "properties": {
    "addr:full":"431 Goodwood Rd Woolsthorpe VIC 3276",
    "addr:housenumber":"431",
    "addr:postcode":"3276",
    "addr:street":"Goodwood Rd",
    "iso:country":"AU",
    "sg:address":"431 Goodwood Rd",
    "sg:city":"Woolsthorpe",
    "sg:classifiers":[
        {
            "category":"Farming",
            "subcategory":"Farm",
            "type":"Manufacturing & Wholesale Goods"
        }
    ],
    "sg:phone":"+61 3 5569 1523",
    "sg:postcode":"3276",
    "sg:province":"VIC",
    "sg:tags":[
        "farmer"
    ],
    "wof:name":"Morrison R L",
    "wof:placetype":"venue"
},
  "geometry": {"coordinates":[142.44227600100001,-38.0342750549],"type":"Point"}
}