{
  "type": "Feature",
  "properties": {
    "iso:country":"AU",
    "sg:address":"5 Cocos Crt",
    "sg:city":"Warnbro",
    "sg:classifiers":[
        {
            "category":"Building & Trades",
            "subcategory":"Cleaning & Sanitation",
            "type":"Services"
        }
    ],
    "sg:phone":"+61 402 374 663",
    "sg:postcode":"6169",
    "sg:province":"WA",
    "sg:tags":[
        "cleaner",
        "repairer",
        "roof"
    ],
    "wof:name":"James Jones",
    "wof:placetype":"venue"
},
  "geometry": {"coordinates":[115.76309999999999,-32.342979],"type":"Point"}
}