{
  "type": "Feature",
  "properties": {
    "addr:full":"Shop 21A Cnr Christine Ave & Scottsdale Road Robina QLD 4226",
    "addr:housenumber":"21a",
    "addr:postcode":"4226",
    "addr:street":"Cnr Christine Ave & Scottsdale Road",
    "iso:country":"AU",
    "sg:address":"Shop 21A Cnr Christine Ave & Scottsdale Road",
    "sg:city":"Robina",
    "sg:classifiers":[
        {
            "category":"Restaurant",
            "type":"Food & Drink"
        }
    ],
    "sg:phone":"+61 7 5578 7688",
    "sg:postcode":"4226",
    "sg:province":"QLD",
    "wof:name":"Krish Indian Cuisine",
    "wof:placetype":"venue"
},
  "geometry": {"coordinates":[153.38667297399999,-28.0812683105],"type":"Point"}
}