{
  "type": "Feature",
  "properties": {
    "addr:full":"RMB 466a Daruka Rd Tamworth NSW 2340",
    "addr:postcode":"2340",
    "addr:street":"Daruka Rd",
    "iso:country":"AU",
    "sg:address":"RMB 466a Daruka Rd",
    "sg:city":"Tamworth",
    "sg:classifiers":[
        {
            "category":"Building & Trades",
            "subcategory":"Construction",
            "type":"Services"
        }
    ],
    "sg:phone":"+61 2 6767 1007",
    "sg:postcode":"2340",
    "sg:province":"NSW",
    "sg:tags":[
        "fencing",
        "contractor"
    ],
    "wof:name":"Action Fencing",
    "wof:placetype":"venue"
},
  "geometry": {"coordinates":[150.948394775,-31.0614318848],"type":"Point"}
}