{
  "type": "Feature",
  "properties": {
    "addr:full":"PO Box 2374 Green Hills NSW 2323",
    "addr:postcode":"2323",
    "iso:country":"AU",
    "sg:address":"PO Box 2374",
    "sg:city":"Green Hills",
    "sg:classifiers":[
        {
            "category":"Arena",
            "subcategory":"Sports Club",
            "type":"Entertainment"
        }
    ],
    "sg:phone":"+61 2 4933 0771",
    "sg:postcode":"2323",
    "sg:province":"NSW",
    "sg:tags":[
        "defence",
        "supply",
        "self",
        "instruction",
        "martial art"
    ],
    "wof:name":"Hunter Valley Karate",
    "wof:placetype":"venue"
},
  "geometry": {"coordinates":[151.66401672399999,-32.7930526733],"type":"Point"}
}