{
  "type": "Feature",
  "properties": {
    "iso:country":"AU",
    "sg:address":"Tamar St",
    "sg:city":"Palmyra",
    "sg:classifiers":[
        {
            "category":"Retail",
            "subcategory":"Repair Shop",
            "type":"Services"
        }
    ],
    "sg:phone":"+61 422 910 572",
    "sg:postcode":"6157",
    "sg:province":"WA",
    "sg:tags":[
        "mending",
        "clothing",
        "alteration"
    ],
    "wof:name":"Odeliska Fashion Service Provider",
    "wof:placetype":"venue"
},
  "geometry": {"coordinates":[115.77786999999999,-32.044819],"type":"Point"}
}