{
  "type": "Feature",
  "properties": {
    "iso:country":"AU",
    "sg:address":"41 Maple Ave",
    "sg:city":"Rostrevor",
    "sg:classifiers":[
        {
            "category":"Building & Trades",
            "subcategory":"Construction",
            "type":"Services"
        }
    ],
    "sg:phone":"+61 8 8337 1283",
    "sg:postcode":"5073",
    "sg:province":"SA",
    "sg:tags":[
        "scaffolding"
    ],
    "wof:name":"Adelaide Scaffolding Services",
    "wof:placetype":"venue"
},
  "geometry": {"coordinates":[138.682403564,-34.8951683044],"type":"Point"}
}