{
  "type": "Feature",
  "properties": {
    "iso:country":"AU",
    "sg:address":"Lot 2450 McKinnon Rd",
    "sg:city":"Pinelands",
    "sg:classifiers":[
        {
            "category":"Government",
            "subcategory":"Department Of Motor Vehicles",
            "type":"Public Place"
        }
    ],
    "sg:phone":"+61 8 8931 1741",
    "sg:postcode":"0829",
    "sg:province":"NT",
    "sg:tags":[
        "tank",
        "cleaning"
    ],
    "wof:name":"Norblast Industrial Solutions",
    "wof:placetype":"venue"
},
  "geometry": {"coordinates":[130.964233398,-12.4541091919],"type":"Point"}
}