{
  "type": "Feature",
  "properties": {
    "addr:full":"St Vincent's Specialist Medical Cntr, 20 Dalley St Lismore NSW 2480",
    "addr:housenumber":"20",
    "addr:postcode":"2480",
    "addr:street":"Dalley St",
    "iso:country":"AU",
    "sg:address":"St Vincent's Specialist Medical Cntr, 20 Dalley St",
    "sg:city":"Lismore",
    "sg:classifiers":[
        {
            "category":"Health Services",
            "subcategory":"Doctor",
            "type":"Services"
        }
    ],
    "sg:phone":"+61 2 6621 9105",
    "sg:postcode":"2480",
    "sg:province":"NSW",
    "sg:tags":[
        "medical",
        "practitioner"
    ],
    "wof:name":"Graham John C",
    "wof:placetype":"venue"
},
  "geometry": {"coordinates":[153.28677368199999,-28.8204708099],"type":"Point"}
}