{
  "type": "Feature",
  "properties": {
    "addr:full":"26 Collingwood St Osborne Park WA 6017",
    "addr:housenumber":"26",
    "addr:postcode":"6017",
    "addr:street":"Collingwood St",
    "iso:country":"AU",
    "sg:address":"26 Collingwood St",
    "sg:city":"Osborne Park",
    "sg:classifiers":[
        {
            "category":"Communications",
            "type":"Services"
        }
    ],
    "sg:phone":"+61 8 9244 4858",
    "sg:postcode":"6017",
    "sg:province":"WA",
    "sg:tags":[
        "equipment",
        "radio"
    ],
    "wof:name":"Signalling Technology Pty Ltd",
    "wof:placetype":"venue"
},
  "geometry": {"coordinates":[115.81590271,-31.903547287],"type":"Point"}
}