{
  "type": "Feature",
  "properties": {
    "addr:full":"Level 5, 56 Station St Parramatta NSW 2150",
    "addr:housenumber":"56",
    "addr:postcode":"2150",
    "addr:street":"Station St",
    "iso:country":"AU",
    "sg:address":"Level 5, 56 Station St",
    "sg:city":"Parramatta",
    "sg:classifiers":[
        {
            "category":"Real Estate",
            "subcategory":"Real Estate Agent",
            "type":"Services"
        }
    ],
    "sg:phone":"+61 1300 729 115",
    "sg:postcode":"2150",
    "sg:province":"NSW",
    "wof:name":"Justlisted.com.au",
    "wof:placetype":"venue"
},
  "geometry": {"coordinates":[150.97207641599999,-33.8085670471],"type":"Point"}
}