{
  "type": "Feature",
  "properties": {
    "iso:country":"AU",
    "sg:address":"51A Werona Ave",
    "sg:city":"Gordon",
    "sg:classifiers":[
        {
            "category":"Travel",
            "subcategory":"Travel Agent",
            "type":"Entertainment"
        }
    ],
    "sg:phone":"+61 2 9499 5444",
    "sg:postcode":"2072",
    "sg:province":"NSW",
    "sg:tags":[
        "tour",
        "holiday",
        "adventure"
    ],
    "wof:name":"Boutique Wine Tours",
    "wof:placetype":"venue"
},
  "geometry": {"coordinates":[151.15736389200001,-33.758934021],"type":"Point"}
}