{
  "type": "Feature",
  "properties": {
    "iso:country":"AU",
    "sg:address":"125 Lyrebird Drv",
    "sg:city":"Pheasants Nest",
    "sg:classifiers":[
        {
            "category":"Building & Trades",
            "subcategory":"Construction",
            "type":"Services"
        }
    ],
    "sg:phone":"+61 2 4684 2290",
    "sg:postcode":"2574",
    "sg:province":"NSW",
    "sg:tags":[
        "home",
        "air conditioning"
    ],
    "wof:name":"Wayne New",
    "wof:placetype":"venue"
},
  "geometry": {"coordinates":[150.625274658,-34.2433319092],"type":"Point"}
}