{
  "type": "Feature",
  "properties": {
    "iso:country":"AU",
    "sg:address":"113 Gilbert St",
    "sg:city":"Latrobe",
    "sg:classifiers":[
        {
            "category":"Government",
            "subcategory":"Post Office",
            "type":"Public Place"
        }
    ],
    "sg:phone":"+61 3 6426 1211",
    "sg:postcode":"7307",
    "sg:province":"TAS",
    "sg:tags":[
        "postal"
    ],
    "wof:name":"Australia Post",
    "wof:placetype":"venue"
},
  "geometry": {"coordinates":[146.41123999999999,-41.235382],"type":"Point"}
}