{
  "type": "Feature",
  "properties": {
    "iso:country":"AU",
    "sg:address":"367 Newman Rd",
    "sg:city":"Geebung",
    "sg:classifiers":[
        {
            "category":"Wholesale",
            "subcategory":"Machinery & Supplies",
            "type":"Manufacturing & Wholesale Goods"
        }
    ],
    "sg:phone":"+61 7 3632 1111",
    "sg:postcode":"4034",
    "sg:province":"QLD",
    "wof:name":"Ravinvic Enterprises Pty Ltd",
    "wof:placetype":"venue"
},
  "geometry": {"coordinates":[153.048126,-27.368633],"type":"Point"}
}