{
  "type": "Feature",
  "properties": {
    "addr:full":"2 Lambert Rd Royston Park SA 5070",
    "addr:housenumber":"2",
    "addr:postcode":"5070",
    "addr:street":"Lambert Rd",
    "iso:country":"AU",
    "sg:address":"2 Lambert Rd",
    "sg:city":"Royston Park",
    "sg:classifiers":[
        {
            "category":"Professional",
            "subcategory":"Art Services",
            "type":"Services"
        }
    ],
    "sg:phone":"+61 8 8362 1787",
    "sg:postcode":"5070",
    "sg:province":"SA",
    "sg:tags":[
        "decorator",
        "painter"
    ],
    "wof:name":"Barone Painting Services",
    "wof:placetype":"venue"
},
  "geometry": {"coordinates":[138.63398742699999,-34.9018669128],"type":"Point"}
}