{
  "type": "Feature",
  "properties": {
    "iso:country":"AU",
    "sg:address":"21 Brandview Ave",
    "sg:city":"Mulgrave",
    "sg:classifiers":[
        {
            "category":"Building & Trades",
            "subcategory":"Landscaping Services",
            "type":"Services"
        }
    ],
    "sg:phone":"+61 403 256 218",
    "sg:postcode":"3170",
    "sg:province":"VIC",
    "sg:tags":[
        "designer",
        "landscape",
        "contractor"
    ],
    "wof:name":"Melbourne Designer Landscapes",
    "wof:placetype":"venue"
},
  "geometry": {"coordinates":[145.12579345699999,-37.9067306519],"type":"Point"}
}