{
  "type": "Feature",
  "properties": {
    "iso:country":"AU",
    "sg:address":"24a Karama Shopping Plaza Kalymnos Drv",
    "sg:city":"Karama",
    "sg:classifiers":[
        {
            "category":"Health Services",
            "subcategory":"Optometrist",
            "type":"Services"
        }
    ],
    "sg:phone":"+61 8 8945 1111",
    "sg:postcode":"0812",
    "sg:province":"NT",
    "wof:name":"John Crimmings",
    "wof:placetype":"venue"
},
  "geometry": {"coordinates":[130.916168,-12.40159],"type":"Point"}
}