{
  "type": "Feature",
  "properties": {
    "addr:full":"Shop 2, Lot 1, cnr Dwyer Turn Joondalup WA 6027",
    "addr:housenumber":"shop 2 lot 1 cnr",
    "addr:postcode":"6027",
    "addr:street":"Dwyer Turn",
    "iso:country":"AU",
    "sg:address":"Shop 2, Lot 1, cnr Dwyer Turn",
    "sg:city":"Joondalup",
    "sg:classifiers":[
        {
            "category":"Ice Cream",
            "type":"Food & Drink"
        }
    ],
    "sg:phone":"+61 8 9301 0284",
    "sg:postcode":"6027",
    "sg:province":"WA",
    "sg:tags":[
        "retail"
    ],
    "wof:name":"Baskin-Robbins Australia Pty Ltd",
    "wof:placetype":"venue"
},
  "geometry": {"coordinates":[115.764556885,-31.7403755188],"type":"Point"}
}