{
  "type": "Feature",
  "properties": {
    "iso:country":"AU",
    "sg:address":"Unit 2, 13 Rose St",
    "sg:city":"Bunbury",
    "sg:classifiers":[
        {
            "category":"Shopping",
            "subcategory":"Party Supplies",
            "type":"Retail Goods"
        }
    ],
    "sg:phone":"+61 8 9721 8439",
    "sg:postcode":"6230",
    "sg:province":"WA",
    "wof:name":"Creations Unlimited",
    "wof:placetype":"venue"
},
  "geometry": {"coordinates":[115.642273,-33.335064],"type":"Point"}
}