{
  "type": "Feature",
  "properties": {
    "addr:full":"17 Angus Ave Wyoming NSW 2250",
    "addr:housenumber":"17",
    "addr:postcode":"2250",
    "addr:street":"Angus Ave",
    "iso:country":"AU",
    "sg:address":"17 Angus Ave",
    "sg:city":"Wyoming",
    "sg:classifiers":[
        {
            "category":"Building & Trades",
            "subcategory":"Construction",
            "type":"Services"
        }
    ],
    "sg:phone":"+61 2 4329 3383",
    "sg:postcode":"2250",
    "sg:province":"NSW",
    "sg:tags":[
        "repairing",
        "window"
    ],
    "wof:name":"A.S.A.P. Maintenance",
    "wof:placetype":"venue"
},
  "geometry": {"coordinates":[151.34861755399999,-33.3987846375],"type":"Point"}
}