{
  "type": "Feature",
  "properties": {
    "iso:country":"AU",
    "sg:address":"PO Box 349",
    "sg:city":"Subiaco",
    "sg:classifiers":[
        {
            "category":"Professional",
            "subcategory":"Accounting & Tax Preparation",
            "type":"Services"
        }
    ],
    "sg:phone":"+61 8 9381 9377",
    "sg:postcode":"6904",
    "sg:province":"WA",
    "sg:tags":[
        "accountant",
        "auditor"
    ],
    "wof:name":"Ewen Malcolm Pty Ltd",
    "wof:placetype":"venue"
},
  "geometry": {"coordinates":[115.817261,-31.96817],"type":"Point"}
}