{
  "type": "Feature",
  "properties": {
    "iso:country":"AU",
    "sg:address":"75 Darling Rd",
    "sg:city":"Malvern East",
    "sg:classifiers":[
        {
            "category":"Utilities",
            "type":"Services"
        }
    ],
    "sg:phone":"+61 3 9572 1567",
    "sg:postcode":"3145",
    "sg:province":"VIC",
    "sg:tags":[
        "refrigeration",
        "industrial",
        "commercial",
        "retail"
    ],
    "wof:name":"Fridge Seal",
    "wof:placetype":"venue"
},
  "geometry": {"coordinates":[145.05917358400001,-37.8771476746],"type":"Point"}
}