{
  "type": "Feature",
  "properties": {
    "addr:full":"23 King St Smithton TAS 7330",
    "addr:housenumber":"23",
    "addr:postcode":"7330",
    "addr:street":"King St",
    "iso:country":"AU",
    "sg:address":"23 King St",
    "sg:city":"Smithton",
    "sg:classifiers":[
        {
            "category":"Farming",
            "subcategory":"Fish & Marine Products",
            "type":"Manufacturing & Wholesale Goods"
        }
    ],
    "sg:phone":"+61 3 6452 1878",
    "sg:postcode":"7330",
    "sg:province":"TAS",
    "sg:tags":[
        "production",
        "seafood",
        "processing"
    ],
    "wof:name":"Redrock Lobster Pty Ltd",
    "wof:placetype":"venue"
},
  "geometry": {"coordinates":[145.12515300000001,-40.839851],"type":"Point"}
}