{
  "type": "Feature",
  "properties": {
    "iso:country":"AU",
    "sg:address":"Level 4 29 Elkhorn Ave",
    "sg:city":"Surfers Paradise",
    "sg:classifiers":[
        {
            "category":"Professional",
            "subcategory":"Art Services",
            "type":"Services"
        }
    ],
    "sg:phone":"+61 411 591 244",
    "sg:postcode":"4217",
    "sg:province":"QLD",
    "sg:tags":[
        "interior",
        "designer"
    ],
    "wof:name":"In Habitat Interiors",
    "wof:placetype":"venue"
},
  "geometry": {"coordinates":[153.42759704599999,-27.9986419678],"type":"Point"}
}