{
  "type": "Feature",
  "properties": {
    "addr:full":"211 Keen St Lismore NSW 2480",
    "addr:housenumber":"211",
    "addr:postcode":"2480",
    "addr:street":"Keen St",
    "iso:country":"AU",
    "sg:address":"211 Keen St",
    "sg:city":"Lismore",
    "sg:classifiers":[
        {
            "category":"Shopping",
            "subcategory":"Mobile Phones",
            "type":"Retail Goods"
        }
    ],
    "sg:phone":"+61 2 6622 2232",
    "sg:postcode":"2480",
    "sg:province":"NSW",
    "sg:tags":[
        "telephone",
        "accessory"
    ],
    "wof:name":"Lismore Phones & Car Audio",
    "wof:placetype":"venue"
},
  "geometry": {"coordinates":[153.272140503,-28.8231925964],"type":"Point"}
}