{
  "type": "Feature",
  "properties": {
    "iso:country":"AU",
    "sg:address":"Macedon St",
    "sg:city":"Sunbury",
    "sg:classifiers":[
        {
            "category":"Education",
            "subcategory":"School",
            "type":"Public Place"
        }
    ],
    "sg:phone":"+61 3 9744 1066",
    "sg:postcode":"3429",
    "sg:province":"VIC",
    "sg:tags":[
        "state",
        "except",
        "nsw"
    ],
    "wof:name":"Sunbury Secondary College",
    "wof:placetype":"venue"
},
  "geometry": {"coordinates":[144.73263549800001,-37.5778999329],"type":"Point"}
}