{
  "type": "Feature",
  "properties": {
    "iso:country":"AU",
    "sg:address":"8 Kelcey Tier Rd",
    "sg:city":"Spreyton",
    "sg:classifiers":[
        {
            "category":"Shopping",
            "subcategory":"Stationery & Office Supplies",
            "type":"Retail Goods"
        }
    ],
    "sg:phone":"+61 3 6427 3010",
    "sg:postcode":"7310",
    "sg:province":"TAS",
    "sg:tags":[
        "packaging",
        "material"
    ],
    "wof:name":"Visy Board Pty Ltd",
    "wof:placetype":"venue"
},
  "geometry": {"coordinates":[146.343551636,-41.2177848816],"type":"Point"}
}