{
  "type": "Feature",
  "properties": {
    "iso:country":"AU",
    "sg:address":"98 B High St",
    "sg:city":"Cranbourne",
    "sg:classifiers":[
        {
            "category":"Professional",
            "subcategory":"Accounting & Tax Preparation",
            "type":"Services"
        }
    ],
    "sg:phone":"+61 3 5996 1990",
    "sg:postcode":"3977",
    "sg:province":"VIC",
    "sg:tags":[
        "accountant",
        "auditor"
    ],
    "wof:name":"Shand Solutions Pty Ltd",
    "wof:placetype":"venue"
},
  "geometry": {"coordinates":[145.283004761,-38.098236084],"type":"Point"}
}