{
  "type": "Feature",
  "properties": {
    "addr:full":"127/ 85 Reynolds St Balmain NSW 2041",
    "addr:housenumber":"127 / 85",
    "addr:postcode":"2041",
    "addr:street":"Reynolds St",
    "iso:country":"AU",
    "sg:address":"127/ 85 Reynolds St",
    "sg:city":"Balmain",
    "sg:classifiers":[
        {
            "category":"Government",
            "subcategory":"Customs House",
            "type":"Public Place"
        }
    ],
    "sg:phone":"+61 2 9818 6842",
    "sg:postcode":"2041",
    "sg:province":"NSW",
    "sg:tags":[
        "title",
        "management",
        "stratum"
    ],
    "wof:name":"Ace Body Corporate Management",
    "wof:placetype":"venue"
},
  "geometry": {"coordinates":[151.17602500000001,-33.85603],"type":"Point"}
}