{
  "type": "Feature",
  "properties": {
    "iso:country":"AU",
    "sg:address":"39- 45 Wedgewood Rd",
    "sg:city":"Hallam",
    "sg:classifiers":[
        {
            "category":"Autos & Motor Vehicles",
            "subcategory":"Auto Supplies",
            "type":"Retail Goods"
        }
    ],
    "sg:phone":"+61 3 9213 5555",
    "sg:postcode":"3803",
    "sg:province":"VIC",
    "sg:tags":[
        "equipment",
        "part",
        "truck"
    ],
    "wof:name":"Dana Australia",
    "wof:placetype":"venue"
},
  "geometry": {"coordinates":[145.25709533700001,-38.0056114197],"type":"Point"}
}