{
  "type": "Feature",
  "properties": {
    "addr:full":"10 Rennies Rd Indooroopilly QLD 4068",
    "addr:housenumber":"10",
    "addr:postcode":"4068",
    "addr:street":"Rennies Rd",
    "iso:country":"AU",
    "sg:address":"10 Rennies Rd",
    "sg:city":"Indooroopilly",
    "sg:classifiers":[
        {
            "category":"Building & Trades",
            "subcategory":"Construction",
            "type":"Services"
        }
    ],
    "sg:phone":"+61 7 3378 6822",
    "sg:postcode":"4068",
    "sg:province":"QLD",
    "sg:tags":[
        "scaffolding"
    ],
    "wof:name":"Westside Builders Hire.",
    "wof:placetype":"venue"
},
  "geometry": {"coordinates":[152.96247863799999,-27.5050868988],"type":"Point"}
}