{
  "type": "Feature",
  "properties": {
    "addr:full":"25 Alacrity Pl Henderson WA 6166",
    "addr:housenumber":"25",
    "addr:postcode":"6166",
    "addr:street":"Alacrity Pl",
    "iso:country":"AU",
    "sg:address":"25 Alacrity Pl",
    "sg:city":"Henderson",
    "sg:classifiers":[
        {
            "category":"Professional",
            "subcategory":"Employment Agencies",
            "type":"Services"
        }
    ],
    "sg:phone":"+61 411 430 286",
    "sg:postcode":"6166",
    "sg:province":"WA",
    "sg:tags":[
        "hire",
        "labour",
        "contractor"
    ],
    "wof:name":"Rigtech Oil & Gas",
    "wof:placetype":"venue"
},
  "geometry": {"coordinates":[115.774841,-32.16571],"type":"Point"}
}