{
  "type": "Feature",
  "properties": {
    "iso:country":"AU",
    "sg:address":"10 McCready St",
    "sg:city":"Woolgoolga",
    "sg:classifiers":[
        {
            "category":"Building & Trades",
            "subcategory":"Construction",
            "type":"Services"
        }
    ],
    "sg:phone":"+61 417 471 374",
    "sg:postcode":"2456",
    "sg:province":"NSW",
    "sg:tags":[
        "concrete",
        "contractor"
    ],
    "wof:name":"Darren Keys Concreting",
    "wof:placetype":"venue"
},
  "geometry": {"coordinates":[153.187729,-30.116188],"type":"Point"}
}