{
  "type": "Feature",
  "properties": {
    "addr:full":"3a Kiama St Miranda NSW 2228",
    "addr:housenumber":"3a",
    "addr:postcode":"2228",
    "addr:street":"Kiama St Miranda",
    "iso:country":"AU",
    "sg:address":"3a Kiama St",
    "sg:city":"Miranda",
    "sg:classifiers":[
        {
            "category":"Professional",
            "subcategory":"Engineering",
            "type":"Services"
        }
    ],
    "sg:phone":"+61 2 9544 9477",
    "sg:postcode":"2228",
    "sg:province":"NSW",
    "sg:tags":[
        "engineer",
        "mechanical"
    ],
    "wof:name":"Port Hacking Automotive",
    "wof:placetype":"venue"
},
  "geometry": {"coordinates":[151.10513305699999,-34.0220489502],"type":"Point"}
}