{
  "type": "Feature",
  "properties": {
    "addr:full":"Kiora Rd Miranda NSW 2228",
    "addr:postcode":"2228",
    "addr:street":"Kiora Rd",
    "iso:country":"AU",
    "sg:address":"Kiora Rd",
    "sg:city":"Miranda",
    "sg:classifiers":[
        {
            "category":"Government",
            "subcategory":"Court House",
            "type":"Public Place"
        }
    ],
    "sg:phone":"+61 2 9314 7697",
    "sg:postcode":"2228",
    "sg:province":"NSW",
    "sg:tags":[
        "personal",
        "marriage",
        "family",
        "counselling"
    ],
    "wof:name":"Mind Matters Counselling & Psychology",
    "wof:placetype":"venue"
},
  "geometry": {"coordinates":[151.102493286,-34.0339202881],"type":"Point"}
}