{
  "type": "Feature",
  "properties": {
    "addr:full":"14/ 1031 Old Princes Hwy Engadine NSW 2233",
    "addr:housenumber":"14 / 1031",
    "addr:postcode":"2233",
    "addr:street":"Old Princes Hwy",
    "iso:country":"AU",
    "sg:address":"14/ 1031 Old Princes Hwy",
    "sg:city":"Engadine",
    "sg:classifiers":[
        {
            "category":"Shopping",
            "subcategory":"Mobile Phones",
            "type":"Retail Goods"
        }
    ],
    "sg:phone":"+61 2 9548 1744",
    "sg:postcode":"2233",
    "sg:province":"NSW",
    "sg:tags":[
        "telephone",
        "accessory"
    ],
    "wof:name":"Leading Edge Engadine",
    "wof:placetype":"venue"
},
  "geometry": {"coordinates":[151.013214111,-34.0648956299],"type":"Point"}
}