{
  "type": "Feature",
  "properties": {
    "addr:full":"52 Jones St Kingswood NSW 2747",
    "addr:housenumber":"52",
    "addr:postcode":"2747",
    "addr:street":"Jones St",
    "iso:country":"AU",
    "sg:address":"52 Jones St",
    "sg:city":"Kingswood",
    "sg:classifiers":[
        {
            "category":"Social Services",
            "subcategory":"Adult Care",
            "type":"Services"
        }
    ],
    "sg:phone":"+61 412 227 191",
    "sg:postcode":"2747",
    "sg:province":"NSW",
    "sg:tags":[
        "towing"
    ],
    "wof:name":"Abbouds Mr Tilt Towing",
    "wof:placetype":"venue"
},
  "geometry": {"coordinates":[150.72286987300001,-33.7653236389],"type":"Point"}
}