{
  "type": "Feature",
  "properties": {
    "addr:full":"Rear 467 Hay St Perth WA 6000",
    "addr:housenumber":"467",
    "addr:postcode":"6000",
    "addr:street":"Hay St",
    "iso:country":"AU",
    "sg:address":"Rear 467 Hay St",
    "sg:city":"Perth",
    "sg:classifiers":[
        {
            "category":"Professional",
            "subcategory":"Computer Services",
            "type":"Services"
        }
    ],
    "sg:phone":"+61 8 9221 2146",
    "sg:postcode":"6000",
    "sg:province":"WA",
    "sg:tags":[
        "training"
    ],
    "wof:name":"PCU Computer Service Centre",
    "wof:placetype":"venue"
},
  "geometry": {"coordinates":[115.855697632,-31.9532527924],"type":"Point"}
}