{
  "type": "Feature",
  "properties": {
    "addr:full":"159 Emerald Rd Monbulk VIC 3793",
    "addr:housenumber":"159",
    "addr:postcode":"3793",
    "addr:street":"Emerald Rd",
    "iso:country":"AU",
    "sg:address":"159 Emerald Rd",
    "sg:city":"Monbulk",
    "sg:classifiers":[
        {
            "category":"Farming",
            "subcategory":"Nursery",
            "type":"Manufacturing & Wholesale Goods"
        }
    ],
    "sg:phone":"+61 3 9756 6285",
    "sg:postcode":"3793",
    "sg:province":"VIC",
    "wof:name":"Great Pine Nursery",
    "wof:placetype":"venue"
},
  "geometry": {"coordinates":[145.42523193400001,-37.8750305176],"type":"Point"}
}