{
  "type": "Feature",
  "properties": {
    "iso:country":"AU",
    "sg:address":"Shop 6/ 72b Yarrara Rd",
    "sg:city":"Pennant Hills",
    "sg:classifiers":[
        {
            "category":"Cafe",
            "type":"Food & Drink"
        }
    ],
    "sg:phone":"+61 2 9481 8737",
    "sg:postcode":"2120",
    "sg:province":"NSW",
    "wof:name":"Corner Cafe Pennant Hills",
    "wof:placetype":"venue"
},
  "geometry": {"coordinates":[151.072021484,-33.737827301],"type":"Point"}
}