{
  "type": "Feature",
  "properties": {
    "addr:full":"706 Creswick Rd Ballarat VIC 3350",
    "addr:housenumber":"706",
    "addr:postcode":"3350",
    "addr:street":"Creswick Rd",
    "iso:country":"AU",
    "sg:address":"706 Creswick Rd",
    "sg:city":"Ballarat",
    "sg:classifiers":[
        {
            "category":"Manufacturing",
            "subcategory":"Metals",
            "type":"Manufacturing & Wholesale Goods"
        }
    ],
    "sg:phone":"+61 3 5339 4832",
    "sg:postcode":"3350",
    "sg:province":"VIC",
    "sg:tags":[
        "sheet",
        "worker"
    ],
    "wof:name":"Kermeen & Co",
    "wof:placetype":"venue"
},
  "geometry": {"coordinates":[143.84951799999999,-37.535362],"type":"Point"}
}