{
  "type": "Feature",
  "properties": {
    "iso:country":"AU",
    "sg:address":"Sandpiper Crs",
    "sg:city":"Aberfoyle Park",
    "sg:classifiers":[
        {
            "category":"Manufacturing",
            "subcategory":"Motor Vehicles & Parts",
            "type":"Manufacturing & Wholesale Goods"
        }
    ],
    "sg:phone":"+61 8 8270 7344",
    "sg:postcode":"5159",
    "sg:province":"SA",
    "sg:tags":[
        "replacement"
    ],
    "wof:name":"Sprint Auto Parts Pty Ltd",
    "wof:placetype":"venue"
},
  "geometry": {"coordinates":[138.593307495,-35.0763092041],"type":"Point"}
}