{
  "type": "Feature",
  "properties": {
    "addr:full":"Camp St Sutton Vlge Sutton NSW 2620",
    "addr:postcode":"2620",
    "addr:street":"St;Vlge",
    "iso:country":"AU",
    "sg:address":"Camp St Sutton Vlge",
    "sg:city":"Sutton",
    "sg:classifiers":[
        {
            "category":"Farming",
            "subcategory":"Farm & Veterinary Services",
            "type":"Manufacturing & Wholesale Goods"
        }
    ],
    "sg:phone":"+61 2 6230 3404",
    "sg:postcode":"2620",
    "sg:province":"NSW",
    "sg:tags":[
        "agricultural",
        "advisory"
    ],
    "wof:name":"Sutton Rural Sales & Supplies",
    "wof:placetype":"venue"
},
  "geometry": {"coordinates":[149.25306701700001,-35.1617774963],"type":"Point"}
}