{
  "type": "Feature",
  "properties": {
    "addr:full":"10 Macquarie Drv Cherrybrook NSW 2126",
    "addr:housenumber":"10",
    "addr:postcode":"2126",
    "addr:street":"Macquarie Drv",
    "iso:country":"AU",
    "sg:address":"10 Macquarie Drv",
    "sg:city":"Cherrybrook",
    "sg:classifiers":[
        {
            "category":"Professional",
            "subcategory":"Business Services",
            "type":"Services"
        }
    ],
    "sg:phone":"+61 2 9980 8424",
    "sg:postcode":"2126",
    "sg:province":"NSW",
    "sg:tags":[
        "drafting"
    ],
    "wof:name":"A & D Drafting",
    "wof:placetype":"venue"
},
  "geometry": {"coordinates":[151.047927856,-33.7271270752],"type":"Point"}
}