{
  "type": "Feature",
  "properties": {
    "addr:full":"19- 33 Kent Rd Mascot NSW 2020",
    "addr:housenumber":"33",
    "addr:postcode":"2020",
    "addr:street":"Kent Rd",
    "iso:country":"AU",
    "sg:address":"19- 33 Kent Rd",
    "sg:city":"Mascot",
    "sg:classifiers":[
        {
            "category":"Freight",
            "type":"Transportation"
        }
    ],
    "sg:phone":"+61 13 23 45",
    "sg:postcode":"2020",
    "sg:province":"NSW",
    "sg:tags":[
        "cargo",
        "air"
    ],
    "wof:name":"Star Track Express",
    "wof:placetype":"venue"
},
  "geometry": {"coordinates":[151.18406677199999,-33.9236602783],"type":"Point"}
}