{
  "type": "Feature",
  "properties": {
    "addr:full":"286 Napier St Bendigo VIC 3550",
    "addr:housenumber":"286",
    "addr:postcode":"3550",
    "addr:street":"Napier St",
    "iso:country":"AU",
    "sg:address":"286 Napier St",
    "sg:city":"Bendigo",
    "sg:classifiers":[
        {
            "category":"Retail",
            "subcategory":"Event Space",
            "type":"Services"
        }
    ],
    "sg:phone":"+61 3 5445 5344",
    "sg:postcode":"3550",
    "sg:province":"VIC",
    "sg:tags":[
        "venue",
        "reception",
        "wedding"
    ],
    "wof:name":"Quills Restaurant",
    "wof:placetype":"venue"
},
  "geometry": {"coordinates":[144.29238891599999,-36.7478370667],"type":"Point"}
}