{
  "type": "Feature",
  "properties": {
    "addr:full":"66 Donkey Gully Rd Yapeen VIC 3451",
    "addr:housenumber":"66",
    "addr:postcode":"3451",
    "addr:street":"Donkey Gully Rd",
    "iso:country":"AU",
    "sg:address":"66 Donkey Gully Rd",
    "sg:city":"Yapeen",
    "sg:classifiers":[
        {
            "category":"Retail",
            "subcategory":"Repair Shop",
            "type":"Services"
        }
    ],
    "sg:phone":"+61 3 5472 1806",
    "sg:postcode":"3451",
    "sg:province":"VIC",
    "sg:tags":[
        "machine",
        "repairs",
        "part",
        "dryer",
        "washing"
    ],
    "wof:name":"Castlemaine Service Centre",
    "wof:placetype":"venue"
},
  "geometry": {"coordinates":[144.18507385300001,-37.1251487732],"type":"Point"}
}