{
  "type": "Feature",
  "properties": {
    "iso:country":"AU",
    "sg:address":"6 St Georges Rd",
    "sg:city":"Northcote",
    "sg:classifiers":[
        {
            "category":"Retail",
            "subcategory":"Auto Repair",
            "type":"Services"
        }
    ],
    "sg:phone":"+61 3 9482 4700",
    "sg:postcode":"3070",
    "sg:province":"VIC",
    "sg:tags":[
        "electrical"
    ],
    "wof:name":"Robs Auto Elecs",
    "wof:placetype":"venue"
},
  "geometry": {"coordinates":[144.990173,-37.776108],"type":"Point"}
}