{
  "type": "Feature",
  "properties": {
    "addr:full":"1st Floor The Gap Village Shopping Centre 1000 Wat The Gap QLD 4061",
    "addr:postcode":"1000;4061",
    "addr:street":"Wat The Gap",
    "iso:country":"AU",
    "sg:address":"1st Floor The Gap Village Shopping Centre 1000 Wat",
    "sg:city":"The Gap",
    "sg:classifiers":[
        {
            "category":"Health Services",
            "subcategory":"Dentist",
            "type":"Services"
        }
    ],
    "sg:phone":"+61 7 3300 5355",
    "sg:postcode":"4061",
    "sg:province":"QLD",
    "wof:name":"Dyer Mark",
    "wof:placetype":"venue"
},
  "geometry": {"coordinates":[152.95196533199999,-27.4452991486],"type":"Point"}
}