{
  "type": "Feature",
  "properties": {
    "iso:country":"AU",
    "sg:address":"U4/ 54",
    "sg:city":"Murray Tce Oaklands Park",
    "sg:classifiers":[
        {
            "category":"Professional",
            "subcategory":"Computer Services",
            "type":"Services"
        }
    ],
    "sg:phone":"+61 8 8296 3670",
    "sg:postcode":"5046",
    "sg:province":"SA",
    "sg:tags":[
        "consultant",
        "system"
    ],
    "wof:name":"Stophers IT Solution",
    "wof:placetype":"venue"
},
  "geometry": {"coordinates":[138.54598999999999,-35.01244],"type":"Point"}
}