{
  "type": "Feature",
  "properties": {
    "iso:country":"AU",
    "sg:address":"63 Knight St",
    "sg:city":"Shepparton",
    "sg:classifiers":[
        {
            "category":"Banks & Credit Unions",
            "subcategory":"Investment Brokerage",
            "type":"Services"
        }
    ],
    "sg:phone":"+61 3 5823 6300",
    "sg:postcode":"3630",
    "sg:province":"VIC",
    "sg:tags":[
        "finance",
        "broker"
    ],
    "wof:name":"Vehicle & Equipment Finance",
    "wof:placetype":"venue"
},
  "geometry": {"coordinates":[145.413696289,-36.3758659363],"type":"Point"}
}