{
  "type": "Feature",
  "properties": {
    "addr:full":"Ste3/ 481 High St Penrith NSW 2750",
    "addr:housenumber":"481",
    "addr:postcode":"2750",
    "addr:street":"High St",
    "iso:country":"AU",
    "sg:address":"Ste3/ 481 High St",
    "sg:city":"Penrith",
    "sg:classifiers":[
        {
            "category":"Banks & Credit Unions",
            "subcategory":"Bank",
            "type":"Services"
        }
    ],
    "sg:phone":"+61 2 4722 3206",
    "sg:postcode":"2750",
    "sg:province":"NSW",
    "sg:tags":[
        "broker",
        "mortgage"
    ],
    "wof:name":"Above & Beyond Financial Services Pty Ltd",
    "wof:placetype":"venue"
},
  "geometry": {"coordinates":[150.915557861,-33.8949737549],"type":"Point"}
}