{
  "type": "Feature",
  "properties": {
    "addr:full":"Oval Rd Reynella SA 5161",
    "addr:postcode":"5161",
    "addr:street":"Oval Rd",
    "iso:country":"AU",
    "sg:address":"Oval Rd",
    "sg:city":"Reynella",
    "sg:classifiers":[
        {
            "category":"Government",
            "subcategory":"City Hall",
            "type":"Public Place"
        }
    ],
    "sg:phone":"+61 8 8381 3076",
    "sg:postcode":"5161",
    "sg:province":"SA",
    "wof:name":"Reynella Community Centre Incorporated",
    "wof:placetype":"venue"
},
  "geometry": {"coordinates":[138.54249572800001,-35.0886077881],"type":"Point"}
}