{
  "type": "Feature",
  "properties": {
    "addr:full":"PO Box 372 Cooma North NSW 2630",
    "addr:postcode":"2630",
    "iso:country":"AU",
    "sg:address":"PO Box 372",
    "sg:city":"Cooma North",
    "sg:classifiers":[
        {
            "category":"Banks & Credit Unions",
            "subcategory":"Financial Services",
            "type":"Services"
        }
    ],
    "sg:phone":"+61 2 6452 5387",
    "sg:postcode":"2630",
    "sg:province":"NSW",
    "sg:tags":[
        "planning"
    ],
    "wof:name":"Talyealye",
    "wof:placetype":"venue"
},
  "geometry": {"coordinates":[149.131393433,-36.2195892334],"type":"Point"}
}