{
  "type": "Feature",
  "properties": {
    "iso:country":"AU",
    "sg:address":"Lot 23 Alex Fraiser Drv",
    "sg:city":"Laverton",
    "sg:classifiers":[
        {
            "category":"Farming",
            "subcategory":"Fish & Marine Products",
            "type":"Manufacturing & Wholesale Goods"
        }
    ],
    "sg:phone":"+61 3 8360 9200",
    "sg:postcode":"3028",
    "sg:province":"VIC",
    "sg:tags":[
        "bitumen"
    ],
    "wof:name":"SAMI Bitumen Technologies",
    "wof:placetype":"venue"
},
  "geometry": {"coordinates":[144.769699,-37.86277],"type":"Point"}
}