{
  "type": "Feature",
  "properties": {
    "addr:full":"16 Seymour Ave Dianella WA 6059",
    "addr:housenumber":"16",
    "addr:postcode":"6059",
    "addr:street":"Seymour Ave",
    "iso:country":"AU",
    "sg:address":"16 Seymour Ave",
    "sg:city":"Dianella",
    "sg:classifiers":[
        {
            "category":"Real Estate",
            "subcategory":"Real Estate Agent",
            "type":"Services"
        }
    ],
    "sg:phone":"+61 8 9375 1098",
    "sg:postcode":"6059",
    "sg:province":"WA",
    "sg:tags":[
        "export"
    ],
    "wof:name":"Almor Agencies",
    "wof:placetype":"venue"
},
  "geometry": {"coordinates":[115.799293518,-31.9357471466],"type":"Point"}
}