{
  "type": "Feature",
  "properties": {
    "addr:full":"17 Ironbark Rd Little Mountain QLD 4551",
    "addr:housenumber":"17",
    "addr:postcode":"4551",
    "addr:street":"Ironbark Rd",
    "iso:country":"AU",
    "sg:address":"17 Ironbark Rd",
    "sg:city":"Little Mountain",
    "sg:classifiers":[
        {
            "category":"Building & Trades",
            "subcategory":"Construction",
            "type":"Services"
        }
    ],
    "sg:phone":"+61 7 5491 6006",
    "sg:postcode":"4551",
    "sg:province":"QLD",
    "sg:tags":[
        "ceiling"
    ],
    "wof:name":"J & T Burns & Sons Pty Ltd",
    "wof:placetype":"venue"
},
  "geometry": {"coordinates":[153.09501648,-26.788482666],"type":"Point"}
}