{
  "type": "Feature",
  "properties": {
    "addr:full":"602/ 70 Lorimer St Docklands VIC 3008",
    "addr:housenumber":"602 / 70",
    "addr:postcode":"3008",
    "addr:street":"Lorimer St",
    "iso:country":"AU",
    "sg:address":"602/ 70 Lorimer St",
    "sg:city":"Docklands",
    "sg:classifiers":[
        {
            "category":"Education",
            "subcategory":"Special Training",
            "type":"Public Place"
        }
    ],
    "sg:phone":"+61 3 9645 3505",
    "sg:postcode":"3008",
    "sg:province":"VIC",
    "sg:tags":[
        "development"
    ],
    "wof:name":"Corporate Fitness Services Pty Ltd",
    "wof:placetype":"venue"
},
  "geometry": {"coordinates":[144.944259644,-37.8248023987],"type":"Point"}
}