{
  "type": "Feature",
  "properties": {
    "iso:country":"AU",
    "sg:address":"296 Woolooware Rd",
    "sg:city":"Cronulla",
    "sg:classifiers":[
        {
            "category":"Building & Trades",
            "subcategory":"Plumbing",
            "type":"Services"
        }
    ],
    "sg:phone":"+61 410 545 333",
    "sg:postcode":"2230",
    "sg:province":"NSW",
    "sg:tags":[
        "plumber",
        "gasfitters"
    ],
    "wof:name":"D Bennett Plumbing",
    "wof:placetype":"venue"
},
  "geometry": {"coordinates":[151.13734435999999,-34.0653190613],"type":"Point"}
}