{
  "type": "Feature",
  "properties": {
    "addr:full":"79 Rankin St Forbes NSW 2871",
    "addr:housenumber":"79",
    "addr:postcode":"2871",
    "addr:street":"Rankin St",
    "iso:country":"AU",
    "sg:address":"79 Rankin St",
    "sg:city":"Forbes",
    "sg:classifiers":[
        {
            "category":"Shopping",
            "subcategory":"Music",
            "type":"Retail Goods"
        }
    ],
    "sg:phone":"+61 2 6852 2101",
    "sg:postcode":"2871",
    "sg:province":"NSW",
    "sg:tags":[
        "instrument",
        "musical"
    ],
    "wof:name":"Bundaburrah Music",
    "wof:placetype":"venue"
},
  "geometry": {"coordinates":[148.00770600000001,-33.383488],"type":"Point"}
}