{
  "type": "Feature",
  "properties": {
    "iso:country":"AU",
    "sg:address":"Warrego Hwy",
    "sg:city":"Dalby",
    "sg:classifiers":[
        {
            "category":"Manufacturing",
            "subcategory":"Rubber & Plastics",
            "type":"Manufacturing & Wholesale Goods"
        }
    ],
    "sg:phone":"+61 7 4669 8040",
    "sg:postcode":"4405",
    "sg:province":"QLD",
    "sg:tags":[
        "moulders"
    ],
    "wof:name":"Clark Tanks",
    "wof:placetype":"venue"
},
  "geometry": {"coordinates":[151.255325317,-27.1777229309],"type":"Point"}
}