{
  "type": "Feature",
  "properties": {
    "iso:country":"AU",
    "sg:address":"124 Marsden St",
    "sg:city":"Parramatta",
    "sg:classifiers":[
        {
            "category":"Personal",
            "subcategory":"Beauty Salon",
            "type":"Services"
        }
    ],
    "sg:phone":"+61 2 9891 6546",
    "sg:postcode":"2150",
    "sg:province":"NSW",
    "wof:name":"Face & Body",
    "wof:placetype":"venue"
},
  "geometry": {"coordinates":[151.00088500999999,-33.8168525696],"type":"Point"}
}