{
  "type": "Feature",
  "properties": {
    "addr:full":"24 Warren Rd Nannup WA 6275",
    "addr:housenumber":"24",
    "addr:postcode":"6275",
    "addr:street":"Warren Rd",
    "iso:country":"AU",
    "sg:address":"24 Warren Rd",
    "sg:city":"Nannup",
    "sg:classifiers":[
        {
            "category":"Cafe",
            "type":"Food & Drink"
        }
    ],
    "sg:phone":"+61 8 9756 1120",
    "sg:postcode":"6275",
    "sg:province":"WA",
    "wof:name":"Blackwood Cafe",
    "wof:placetype":"venue"
},
  "geometry": {"coordinates":[115.76551055900001,-33.9843215942],"type":"Point"}
}