{
  "type": "Feature",
  "properties": {
    "iso:country":"AU",
    "sg:address":"245 Ormond Rd",
    "sg:city":"Narre Warren South",
    "sg:classifiers":[
        {
            "category":"Food & Beverages",
            "subcategory":"Supermarket",
            "type":"Retail Goods"
        }
    ],
    "sg:phone":"+61 3 8790 2600",
    "sg:postcode":"3805",
    "sg:province":"VIC",
    "sg:tags":[
        "grocery",
        "store"
    ],
    "wof:name":"Foodworks Supermarket",
    "wof:placetype":"venue"
},
  "geometry": {"coordinates":[145.287094,-38.052128],"type":"Point"}
}