{
  "type": "Feature",
  "properties": {
    "addr:full":"Fantasy Rd Bridgewater VIC 3516",
    "addr:postcode":"3516",
    "addr:street":"Fantasy Rd",
    "iso:country":"AU",
    "sg:address":"Fantasy Rd",
    "sg:city":"Bridgewater",
    "sg:classifiers":[
        {
            "category":"Farming",
            "subcategory":"Poultry Farm",
            "type":"Manufacturing & Wholesale Goods"
        }
    ],
    "sg:phone":"+61 3 5437 3100",
    "sg:postcode":"3516",
    "sg:province":"VIC",
    "sg:tags":[
        "farmer"
    ],
    "wof:name":"Loddon Valley Eggs",
    "wof:placetype":"venue"
},
  "geometry": {"coordinates":[143.952636719,-36.6182594299],"type":"Point"}
}