{
  "type": "Feature",
  "properties": {
    "addr:full":"8 Fogarty St Alice Springs NT 0870",
    "addr:housenumber":"8",
    "addr:postcode":"nt 0870",
    "addr:street":"Fogarty St",
    "iso:country":"AU",
    "sg:address":"8 Fogarty St",
    "sg:city":"Alice Springs",
    "sg:classifiers":[
        {
            "category":"Shopping",
            "subcategory":"Mobile Phones",
            "type":"Retail Goods"
        }
    ],
    "sg:phone":"+61 13 17 60",
    "sg:postcode":"0870",
    "sg:province":"NT",
    "sg:tags":[
        "telephone",
        "accessory"
    ],
    "wof:name":"Battery World",
    "wof:placetype":"venue"
},
  "geometry": {"coordinates":[133.87240600600001,-23.7003116608],"type":"Point"}
}