{
  "type": "Feature",
  "properties": {
    "addr:full":"92 Fairbank Rd Clayton South VIC 3169",
    "addr:housenumber":"92",
    "addr:postcode":"3169",
    "addr:street":"Fairbank Rd",
    "iso:country":"AU",
    "sg:address":"92 Fairbank Rd",
    "sg:city":"Clayton South",
    "sg:classifiers":[
        {
            "category":"Manufacturing",
            "subcategory":"Chemicals & Compounds",
            "type":"Manufacturing & Wholesale Goods"
        }
    ],
    "sg:phone":"+61 3 8542 5111",
    "sg:postcode":"3169",
    "sg:province":"VIC",
    "sg:tags":[
        "industrial"
    ],
    "wof:name":"Applied Chemicals Pty Ltd",
    "wof:placetype":"venue"
},
  "geometry": {"coordinates":[145.12727355999999,-37.9417610168],"type":"Point"}
}