{
  "type": "Feature",
  "properties": {
    "addr:full":"68 Barry St Bayswater VIC 3153",
    "addr:housenumber":"68",
    "addr:postcode":"3153",
    "addr:street":"Barry St",
    "iso:country":"AU",
    "sg:address":"68 Barry St",
    "sg:city":"Bayswater",
    "sg:classifiers":[
        {
            "category":"Manufacturing",
            "subcategory":"Leather Goods",
            "type":"Manufacturing & Wholesale Goods"
        }
    ],
    "sg:phone":"+61 3 9762 7700",
    "sg:postcode":"3153",
    "sg:province":"VIC",
    "sg:tags":[
        "wholesaler",
        "mfrs"
    ],
    "wof:name":"Hellweg International Pty Ltd",
    "wof:placetype":"venue"
},
  "geometry": {"coordinates":[145.28448486299999,-37.8481903076],"type":"Point"}
}