{
  "type": "Feature",
  "properties": {
    "addr:full":"Lvl 5, 17 Randle St Surry Hills NSW 2010",
    "addr:housenumber":"17",
    "addr:postcode":"2010",
    "addr:street":"Randle St",
    "iso:country":"AU",
    "sg:address":"Lvl 5, 17 Randle St",
    "sg:city":"Surry Hills",
    "sg:classifiers":[
        {
            "category":"Real Estate",
            "subcategory":"Surveying",
            "type":"Services"
        }
    ],
    "sg:phone":"+61 2 9212 4655",
    "sg:postcode":"2010",
    "sg:province":"NSW",
    "sg:tags":[
        "surveyor",
        "land"
    ],
    "wof:name":"Denny Linker & Co",
    "wof:placetype":"venue"
},
  "geometry": {"coordinates":[151.207275391,-33.8853607178],"type":"Point"}
}