{
  "type": "Feature",
  "properties": {
    "iso:country":"AU",
    "sg:address":"215 Port Rd",
    "sg:city":"Hindmarsh",
    "sg:classifiers":[
        {
            "category":"Professional",
            "subcategory":"Art Services",
            "type":"Services"
        }
    ],
    "sg:phone":"+61 8 8340 2799",
    "sg:postcode":"5007",
    "sg:province":"SA",
    "sg:tags":[
        "interior",
        "designer"
    ],
    "wof:name":"Thomson Rossi",
    "wof:placetype":"venue"
},
  "geometry": {"coordinates":[138.570587158,-34.9038505554],"type":"Point"}
}