{
  "type": "Feature",
  "properties": {
    "addr:full":"4 Cookson Pl Banks ACT 2906",
    "addr:housenumber":"4",
    "addr:postcode":"2906",
    "addr:street":"Cookson Pl",
    "iso:country":"AU",
    "sg:address":"4 Cookson Pl",
    "sg:city":"Banks",
    "sg:classifiers":[
        {
            "category":"Building & Trades",
            "subcategory":"Construction",
            "type":"Services"
        }
    ],
    "sg:phone":"+61 416 642 527",
    "sg:postcode":"2906",
    "sg:province":"ACT",
    "sg:tags":[
        "earth",
        "excavating",
        "moving",
        "contractor"
    ],
    "wof:name":"Andros Bobcats",
    "wof:placetype":"venue"
},
  "geometry": {"coordinates":[149.102005005,-35.4770202637],"type":"Point"}
}