{
  "type": "Feature",
  "properties": {
    "addr:full":"226 High St Belmont VIC 3216",
    "addr:housenumber":"226",
    "addr:postcode":"3216",
    "addr:street":"High St",
    "iso:country":"AU",
    "sg:address":"226 High St",
    "sg:city":"Belmont",
    "sg:classifiers":[
        {
            "category":"Health Services",
            "subcategory":"Chiropractor",
            "type":"Services"
        }
    ],
    "sg:phone":"+61 3 5243 9060",
    "sg:postcode":"3216",
    "sg:province":"VIC",
    "wof:name":"Susanne Weisenberger",
    "wof:placetype":"venue"
},
  "geometry": {"coordinates":[144.33877563499999,-38.1785507202],"type":"Point"}
}