{
  "type": "Feature",
  "properties": {
    "addr:full":"1st Floor 458 Swanston St Carlton VIC 3053",
    "addr:housenumber":"458",
    "addr:postcode":"3053",
    "addr:street":"Swanston St",
    "iso:country":"AU",
    "sg:address":"1st Floor 458 Swanston St",
    "sg:city":"Carlton",
    "sg:classifiers":[
        {
            "category":"Health Services",
            "subcategory":"Doctor",
            "type":"Services"
        }
    ],
    "sg:phone":"+61 3 9341 5200",
    "sg:postcode":"3053",
    "sg:province":"VIC",
    "sg:tags":[
        "medical",
        "practitioner"
    ],
    "wof:name":"General Practice Divisions - Victoria",
    "wof:placetype":"venue"
},
  "geometry": {"coordinates":[144.96311950699999,-37.8062019348],"type":"Point"}
}