{
  "type": "Feature",
  "properties": {
    "addr:full":"Aberdeen St Port Adelaide SA 5015",
    "addr:postcode":"5015",
    "addr:street":"Aberdeen St",
    "iso:country":"AU",
    "sg:address":"Aberdeen St",
    "sg:city":"Port Adelaide",
    "sg:classifiers":[
        {
            "category":"Professional",
            "subcategory":"Engineering",
            "type":"Services"
        }
    ],
    "sg:phone":"+61 8 8240 0287",
    "sg:postcode":"5015",
    "sg:province":"SA",
    "sg:tags":[
        "engineer"
    ],
    "wof:name":"Norman Engineering",
    "wof:placetype":"venue"
},
  "geometry": {"coordinates":[138.511795044,-34.8448410034],"type":"Point"}
}