{
  "type": "Feature",
  "properties": {
    "iso:country":"AU",
    "sg:address":"89-91 Kensington Rd",
    "sg:city":"Summer Hill",
    "sg:classifiers":[
        {
            "category":"Professional",
            "subcategory":"Art Services",
            "type":"Services"
        }
    ],
    "sg:phone":"+61 2 9907 1256",
    "sg:postcode":"2130",
    "sg:province":"NSW",
    "sg:tags":[
        "interior",
        "designer"
    ],
    "wof:name":"Groth & Sons",
    "wof:placetype":"venue"
},
  "geometry": {"coordinates":[151.138473511,-33.8870849609],"type":"Point"}
}