{
  "type": "Feature",
  "properties": {
    "iso:country":"AU",
    "sg:address":"53 Arrowsmith St",
    "sg:city":"Camp Hill",
    "sg:classifiers":[
        {
            "category":"Building & Trades",
            "subcategory":"Landscaping Services",
            "type":"Services"
        }
    ],
    "sg:phone":"+61 7 3398 3172",
    "sg:postcode":"4152",
    "sg:province":"QLD",
    "sg:tags":[
        "designer",
        "landscape",
        "contractor"
    ],
    "wof:name":"Kwik Kerb Camp Hill",
    "wof:placetype":"venue"
},
  "geometry": {"coordinates":[153.08624267600001,-27.4904880524],"type":"Point"}
}