{
  "type": "Feature",
  "properties": {
    "iso:country":"AU",
    "sg:address":"18 Vista Heights Rd",
    "sg:city":"Miranda",
    "sg:classifiers":[
        {
            "category":"Building & Trades",
            "subcategory":"Construction",
            "type":"Services"
        }
    ],
    "sg:phone":"+61 2 9522 8462",
    "sg:postcode":"2228",
    "sg:province":"NSW",
    "sg:tags":[
        "stonework",
        "stone",
        "mason"
    ],
    "wof:name":"D'Arcy Nagle Pty Ltd",
    "wof:placetype":"venue"
},
  "geometry": {"coordinates":[151.10084533700001,-34.0272636414],"type":"Point"}
}