{
  "type": "Feature",
  "properties": {
    "iso:country":"AU",
    "sg:address":"high St",
    "sg:city":"Drysdale",
    "sg:classifiers":[
        {
            "category":"Education",
            "subcategory":"Dance Studio",
            "type":"Public Place"
        }
    ],
    "sg:phone":"+61 3 5250 3244",
    "sg:postcode":"3222",
    "sg:province":"VIC",
    "sg:tags":[
        "venue",
        "tuition"
    ],
    "wof:name":"Debbie Lee School Of Dancing",
    "wof:placetype":"venue"
},
  "geometry": {"coordinates":[144.570816,-38.173065],"type":"Point"}
}