{
  "type": "Feature",
  "properties": {
    "addr:full":"82 Gilbert St Latrobe TAS 7307",
    "addr:housenumber":"82",
    "addr:postcode":"7307",
    "addr:street":"Gilbert St",
    "iso:country":"AU",
    "sg:address":"82 Gilbert St",
    "sg:city":"Latrobe",
    "sg:classifiers":[
        {
            "category":"Professional",
            "subcategory":"Accounting & Tax Preparation",
            "type":"Services"
        }
    ],
    "sg:phone":"+61 3 6426 2855",
    "sg:postcode":"7307",
    "sg:province":"TAS",
    "sg:tags":[
        "consultant",
        "taxation"
    ],
    "wof:name":"Johnson, Ranson & Lutje",
    "wof:placetype":"venue"
},
  "geometry": {"coordinates":[146.409515,-41.235386],"type":"Point"}
}