{
  "type": "Feature",
  "properties": {
    "iso:country":"AU",
    "sg:address":"Raward Rd",
    "sg:city":"Torquay",
    "sg:classifiers":[
        {
            "category":"Arena",
            "subcategory":"Sports Club",
            "type":"Entertainment"
        }
    ],
    "sg:phone":"+61 7 4125 5045",
    "sg:postcode":"4655",
    "sg:province":"QLD",
    "sg:tags":[
        "australian",
        "football",
        "rule"
    ],
    "wof:name":"Hervey Bay Australian Rules Football Club Inc",
    "wof:placetype":"venue"
},
  "geometry": {"coordinates":[152.86634799999999,-25.302891],"type":"Point"}
}