{
  "type": "Feature",
  "properties": {
    "iso:country":"AU",
    "sg:address":"52 Railway St",
    "sg:city":"Dirranbandi",
    "sg:classifiers":[
        {
            "category":"Food & Beverages",
            "subcategory":"Supermarket",
            "type":"Retail Goods"
        }
    ],
    "sg:phone":"+61 7 4625 8143",
    "sg:postcode":"4486",
    "sg:province":"QLD",
    "sg:tags":[
        "grocery",
        "store"
    ],
    "wof:name":"Cut Price Store & Hardware Dirranbandi",
    "wof:placetype":"venue"
},
  "geometry": {"coordinates":[148.227462769,-28.5855865479],"type":"Point"}
}