{
  "type": "Feature",
  "properties": {
    "iso:country":"AU",
    "sg:address":"PO Box 761",
    "sg:city":"e Earlville",
    "sg:classifiers":[
        {
            "category":"Building & Trades",
            "subcategory":"Construction",
            "type":"Services"
        }
    ],
    "sg:phone":"+61 412 366 618",
    "sg:postcode":"4870",
    "sg:province":"QLD",
    "sg:tags":[
        "earth",
        "excavating",
        "moving",
        "contractor"
    ],
    "wof:name":"Dingo Hire By THP",
    "wof:placetype":"venue"
},
  "geometry": {"coordinates":[145.736206055,-16.9474105835],"type":"Point"}
}