{
  "type": "Feature",
  "properties": {
    "addr:full":"Unit 26 11 Underwood Rd Homebush NSW 2140",
    "addr:housenumber":"11",
    "addr:postcode":"2140",
    "addr:street":"Underwood Rd",
    "iso:country":"AU",
    "sg:address":"Unit 26 11 Underwood Rd",
    "sg:city":"Homebush",
    "sg:classifiers":[
        {
            "category":"Wholesale",
            "subcategory":"Medical Equipment & Supplies",
            "type":"Manufacturing & Wholesale Goods"
        }
    ],
    "sg:phone":"+61 2 8746 0280",
    "sg:postcode":"2140",
    "sg:province":"NSW",
    "sg:tags":[
        "dental"
    ],
    "wof:name":"Stone Glass Industries",
    "wof:placetype":"venue"
},
  "geometry": {"coordinates":[151.07928466800001,-33.855922699],"type":"Point"}
}