{
  "type": "Feature",
  "properties": {
    "iso:country":"AU",
    "sg:address":"Ground Floor, Shop 1 475-477 Marrickville Rd",
    "sg:city":"Dulwich Hill",
    "sg:classifiers":[
        {
            "category":"Professional",
            "subcategory":"Accounting & Tax Preparation",
            "type":"Services"
        }
    ],
    "sg:phone":"+61 2 9550 9999",
    "sg:postcode":"2203",
    "sg:province":"NSW",
    "sg:tags":[
        "accountant",
        "auditor"
    ],
    "wof:name":"T Y Francis & Co",
    "wof:placetype":"venue"
},
  "geometry": {"coordinates":[151.143417,-33.90406],"type":"Point"}
}