{
  "type": "Feature",
  "properties": {
    "iso:country":"AU",
    "sg:address":"46- 48 Orchard St",
    "sg:city":"Kilsyth",
    "sg:classifiers":[
        {
            "category":"Retail",
            "subcategory":"Storage",
            "type":"Services"
        }
    ],
    "sg:phone":"+61 3 9725 0066",
    "sg:postcode":"3137",
    "sg:province":"VIC",
    "wof:name":"The Space Place",
    "wof:placetype":"venue"
},
  "geometry": {"coordinates":[145.30958557100001,-37.8105239868],"type":"Point"}
}