{
  "type": "Feature",
  "properties": {
    "addr:full":"11 Fig Tree Hill Drv Lennox Head NSW 2478",
    "addr:housenumber":"11",
    "addr:postcode":"2478",
    "addr:street":"Fig Tree Hill Drv",
    "iso:country":"AU",
    "sg:address":"11 Fig Tree Hill Drv",
    "sg:city":"Lennox Head",
    "sg:classifiers":[
        {
            "category":"Building & Trades",
            "subcategory":"Construction",
            "type":"Services"
        }
    ],
    "sg:phone":"+61 2 6687 5166",
    "sg:postcode":"2478",
    "sg:province":"NSW",
    "sg:tags":[
        "contractor"
    ],
    "wof:name":"Lyon G J",
    "wof:placetype":"venue"
},
  "geometry": {"coordinates":[153.5756073,-28.7837314606],"type":"Point"}
}