{
  "type": "Feature",
  "properties": {
    "addr:full":"305 Elizabeth St North Hobart TAS 7000",
    "addr:housenumber":"305",
    "addr:postcode":"7000",
    "addr:street":"Elizabeth St",
    "iso:country":"AU",
    "sg:address":"305 Elizabeth St",
    "sg:city":"North Hobart",
    "sg:classifiers":[
        {
            "category":"Fast Food",
            "type":"Food & Drink"
        }
    ],
    "sg:phone":"+61 3 6236 9500",
    "sg:postcode":"7000",
    "sg:province":"TAS",
    "sg:tags":[
        "away",
        "take"
    ],
    "wof:name":"Annapurna Indian Cuisine",
    "wof:placetype":"venue"
},
  "geometry": {"coordinates":[147.317016602,-42.8743095398],"type":"Point"}
}