{
  "type": "Feature",
  "properties": {
    "iso:country":"AU",
    "sg:address":"Shop 16 Narellan Town Cntr",
    "sg:city":"Narellan",
    "sg:classifiers":[
        {
            "category":"Shopping",
            "type":"Retail Goods"
        }
    ],
    "sg:phone":"+61 2 4647 4493",
    "sg:postcode":"2567",
    "sg:province":"NSW",
    "sg:tags":[
        "repair",
        "travel"
    ],
    "wof:name":"Camden Bags Store",
    "wof:placetype":"venue"
},
  "geometry": {"coordinates":[150.779205322,-34.0582008362],"type":"Point"}
}