{
  "type": "Feature",
  "properties": {
    "iso:country":"AU",
    "sg:address":"Shp 2/ 2 Bowral Rd",
    "sg:city":"Mittagong",
    "sg:classifiers":[
        {
            "category":"Health Services",
            "subcategory":"Dentist",
            "type":"Services"
        }
    ],
    "sg:phone":"+61 1300 762 203",
    "sg:postcode":"2575",
    "sg:province":"NSW",
    "sg:tags":[
        "dental",
        "prosthetist"
    ],
    "wof:name":"Eddie Reznikas Dental Prosthetists",
    "wof:placetype":"venue"
},
  "geometry": {"coordinates":[150.44747924800001,-34.4511833191],"type":"Point"}
}