{
  "type": "Feature",
  "properties": {
    "addr:full":"611 Robinson Rd Aspley QLD 4034",
    "addr:housenumber":"611",
    "addr:postcode":"4034",
    "addr:street":"Robinson Rd",
    "iso:country":"AU",
    "sg:address":"611 Robinson Rd",
    "sg:city":"Aspley",
    "sg:classifiers":[
        {
            "category":"Fast Food",
            "type":"Food & Drink"
        }
    ],
    "sg:phone":"+61 7 3263 7707",
    "sg:postcode":"4034",
    "sg:province":"QLD",
    "sg:tags":[
        "away",
        "take"
    ],
    "wof:name":"Sun Sun Chinese BYO Restaurant & Takeaway",
    "wof:placetype":"venue"
},
  "geometry": {"coordinates":[153.02290300000001,-27.364565],"type":"Point"}
}