{
  "type": "Feature",
  "properties": {
    "iso:country":"AU",
    "sg:address":"30 Faunce St",
    "sg:city":"Queanbeyan",
    "sg:classifiers":[
        {
            "category":"Structure",
            "subcategory":"Office Building",
            "type":"Public Place"
        }
    ],
    "sg:phone":"+61 2 6284 4977",
    "sg:postcode":"2620",
    "sg:province":"ACT",
    "sg:tags":[
        "tie",
        "concrete",
        "formwork",
        "form",
        "accessory"
    ],
    "wof:name":"TMC Formwork",
    "wof:placetype":"venue"
},
  "geometry": {"coordinates":[149.24984741200001,-35.3404846191],"type":"Point"}
}