{
  "type": "Feature",
  "properties": {
    "addr:full":"PO Box 99 Drayton North QLD 4350",
    "addr:postcode":"4350",
    "iso:country":"AU",
    "sg:address":"PO Box 99",
    "sg:city":"Drayton North",
    "sg:classifiers":[
        {
            "category":"Building & Trades",
            "subcategory":"Construction",
            "type":"Services"
        }
    ],
    "sg:phone":"+61 427 386 611",
    "sg:postcode":"4350",
    "sg:province":"QLD",
    "sg:tags":[
        "earth",
        "excavating",
        "moving",
        "contractor"
    ],
    "wof:name":"GB Earthworks QLD Pty Ltd",
    "wof:placetype":"venue"
},
  "geometry": {"coordinates":[151.915955,-27.589491],"type":"Point"}
}