{
  "type": "Feature",
  "properties": {
    "addr:full":"460 Queen St Melbourne VIC 3000",
    "addr:housenumber":"460",
    "addr:postcode":"3000",
    "addr:street":"Queen St",
    "iso:country":"AU",
    "sg:address":"460 Queen St",
    "sg:city":"Melbourne",
    "sg:classifiers":[
        {
            "category":"Shopping",
            "subcategory":"Jewelry",
            "type":"Retail Goods"
        }
    ],
    "sg:phone":"+61 3 9077 0085",
    "sg:postcode":"3000",
    "sg:province":"VIC",
    "sg:tags":[
        "jeweller"
    ],
    "wof:name":"Australian Opals Direct",
    "wof:placetype":"venue"
},
  "geometry": {"coordinates":[144.95811462399999,-37.8079376221],"type":"Point"}
}