{
  "type": "Feature",
  "properties": {
    "iso:country":"AU",
    "sg:address":"12 Forsyth St",
    "sg:city":"Whyalla",
    "sg:classifiers":[
        {
            "category":"Real Estate",
            "subcategory":"Real Estate Agent",
            "type":"Services"
        }
    ],
    "sg:phone":"+61 8 8645 1266",
    "sg:postcode":"5600",
    "sg:province":"SA",
    "wof:name":"Whyalla Conveyancers",
    "wof:placetype":"venue"
},
  "geometry": {"coordinates":[137.584518,-33.033932],"type":"Point"}
}