{
  "type": "Feature",
  "properties": {
    "iso:country":"AU",
    "sg:address":"3 Lyne Rd",
    "sg:city":"Cheltenham",
    "sg:classifiers":[
        {
            "category":"Utilities",
            "subcategory":"Electric",
            "type":"Services"
        }
    ],
    "sg:phone":"+61 2 9869 7754",
    "sg:postcode":"2119",
    "sg:province":"NSW",
    "sg:tags":[
        "electrical",
        "contractor"
    ],
    "wof:name":"McGill T F",
    "wof:placetype":"venue"
},
  "geometry": {"coordinates":[151.07933044399999,-33.7584953308],"type":"Point"}
}