{
  "type": "Feature",
  "properties": {
    "iso:country":"AU",
    "sg:address":"1/ 68 King William St",
    "sg:city":"Kent Town",
    "sg:classifiers":[
        {
            "category":"Utilities",
            "subcategory":"Electric",
            "type":"Services"
        }
    ],
    "sg:phone":"+61 8 8363 1844",
    "sg:postcode":"5067",
    "sg:province":"SA",
    "sg:tags":[
        "tube",
        "lamps",
        "globe"
    ],
    "wof:name":"National Lighting",
    "wof:placetype":"venue"
},
  "geometry": {"coordinates":[138.61935424800001,-34.9188575745],"type":"Point"}
}