{
  "type": "Feature",
  "properties": {
    "addr:full":"209 Bunda St Parramatta Park QLD 4870",
    "addr:housenumber":"209",
    "addr:postcode":"4870",
    "addr:street":"Bunda St",
    "iso:country":"AU",
    "sg:address":"209 Bunda St",
    "sg:city":"Parramatta Park",
    "sg:classifiers":[
        {
            "category":"Retail",
            "subcategory":"Auto Repair",
            "type":"Services"
        }
    ],
    "sg:phone":"+61 7 4051 6985",
    "sg:postcode":"4870",
    "sg:province":"QLD",
    "sg:tags":[
        "electrical"
    ],
    "wof:name":"Autoelect",
    "wof:placetype":"venue"
},
  "geometry": {"coordinates":[145.76953125,-16.9245014191],"type":"Point"}
}