{
  "type": "Feature",
  "properties": {
    "addr:full":"141 Mitchell St Larrakeyah NT 0820",
    "addr:housenumber":"141",
    "addr:postcode":"nt 0820",
    "addr:street":"Mitchell St",
    "iso:country":"AU",
    "sg:address":"141 Mitchell St",
    "sg:city":"Larrakeyah",
    "sg:classifiers":[
        {
            "category":"Food & Beverages",
            "subcategory":"Supermarket",
            "type":"Retail Goods"
        }
    ],
    "sg:phone":"+61 8 8981 7449",
    "sg:postcode":"0820",
    "sg:province":"NT",
    "sg:tags":[
        "grocery",
        "store"
    ],
    "wof:name":"Larrakeyah Larder",
    "wof:placetype":"venue"
},
  "geometry": {"coordinates":[130.83203125,-12.4557132721],"type":"Point"}
}