{
  "type": "Feature",
  "properties": {
    "iso:country":"AU",
    "sg:address":"29 Bellingham St",
    "sg:city":"Narellan",
    "sg:classifiers":[
        {
            "category":"Retail",
            "subcategory":"Auto Repair",
            "type":"Services"
        }
    ],
    "sg:phone":"+61 2 4648 2178",
    "sg:postcode":"2567",
    "sg:province":"NSW",
    "sg:tags":[
        "recapping",
        "repairing",
        "retreading",
        "tyre"
    ],
    "wof:name":"South West RingTread Tyres",
    "wof:placetype":"venue"
},
  "geometry": {"coordinates":[150.732543945,-34.0387306213],"type":"Point"}
}