{
  "type": "Feature",
  "properties": {
    "iso:country":"AU",
    "sg:address":"200 Upper Heidleberg Rd",
    "sg:city":"Ivanhoe",
    "sg:classifiers":[
        {
            "category":"Personal",
            "subcategory":"Tanning Parlor",
            "type":"Services"
        }
    ],
    "sg:phone":"+61 3 9497 2088",
    "sg:postcode":"3079",
    "sg:province":"VIC",
    "sg:tags":[
        "solarium"
    ],
    "wof:name":"Body Bronze Ivanhoe",
    "wof:placetype":"venue"
},
  "geometry": {"coordinates":[145.04414367699999,-37.7675590515],"type":"Point"}
}