{
  "type": "Feature",
  "properties": {
    "iso:country":"AU",
    "sg:address":"60 Fulton Rd",
    "sg:city":"Mt Eliza",
    "sg:classifiers":[
        {
            "category":"Building & Trades",
            "subcategory":"Construction",
            "type":"Services"
        }
    ],
    "sg:phone":"+61 409 744 464",
    "sg:postcode":"3930",
    "sg:province":"VIC",
    "sg:tags":[
        "builder",
        "designer",
        "room",
        "cool"
    ],
    "wof:name":"A Melbourne Bathroom Safety Flooring",
    "wof:placetype":"venue"
},
  "geometry": {"coordinates":[145.10757446299999,-38.1854057312],"type":"Point"}
}