{
  "type": "Feature",
  "properties": {
    "addr:full":"56 Avandina Crs Greensborough VIC 3088",
    "addr:housenumber":"56",
    "addr:postcode":"3088",
    "addr:street":"Avandina Crs",
    "iso:country":"AU",
    "sg:address":"56 Avandina Crs",
    "sg:city":"Greensborough",
    "sg:classifiers":[
        {
            "category":"Professional",
            "subcategory":"Accounting & Tax Preparation",
            "type":"Services"
        }
    ],
    "sg:phone":"+61 3 9432 5573",
    "sg:postcode":"3088",
    "sg:province":"VIC",
    "sg:tags":[
        "accountant",
        "auditor"
    ],
    "wof:name":"Galileos Charles",
    "wof:placetype":"venue"
},
  "geometry": {"coordinates":[145.10215759299999,-37.7044715881],"type":"Point"}
}