{
  "type": "Feature",
  "properties": {
    "addr:full":"44 Dutruc St Randwick NSW 2031",
    "addr:housenumber":"44",
    "addr:postcode":"2031",
    "addr:street":"Dutruc St",
    "iso:country":"AU",
    "sg:address":"44 Dutruc St",
    "sg:city":"Randwick",
    "sg:classifiers":[
        {
            "category":"Building & Trades",
            "subcategory":"Landscaping Services",
            "type":"Services"
        }
    ],
    "sg:phone":"+61 415 803 669",
    "sg:postcode":"2031",
    "sg:province":"NSW",
    "sg:tags":[
        "gardener"
    ],
    "wof:name":"A Grass Above The Rest",
    "wof:placetype":"venue"
},
  "geometry": {"coordinates":[151.245162964,-33.9118881226],"type":"Point"}
}