{
  "type": "Feature",
  "properties": {
    "addr:full":"451 Elizabeth St Melbourne VIC 3000",
    "addr:housenumber":"451",
    "addr:postcode":"3000",
    "addr:street":"Elizabeth St",
    "iso:country":"AU",
    "sg:address":"451 Elizabeth St",
    "sg:city":"Melbourne",
    "sg:classifiers":[
        {
            "category":"Travel",
            "subcategory":"Travel Agent",
            "type":"Entertainment"
        }
    ],
    "sg:phone":"+61 3 9329 9221",
    "sg:postcode":"3000",
    "sg:province":"VIC",
    "sg:tags":[
        "consultant"
    ],
    "wof:name":"Peterpan's Adventure Travel",
    "wof:placetype":"venue"
},
  "geometry": {"coordinates":[144.960372925,-37.8084945679],"type":"Point"}
}