{
  "type": "Feature",
  "properties": {
    "addr:full":"250 Roberts Rd Subiaco WA 6008",
    "addr:housenumber":"250",
    "addr:postcode":"6008",
    "addr:street":"Roberts Rd",
    "iso:country":"AU",
    "sg:address":"250 Roberts Rd",
    "sg:city":"Subiaco",
    "sg:classifiers":[
        {
            "category":"Arena",
            "subcategory":"Sports Club",
            "type":"Entertainment"
        }
    ],
    "sg:phone":"+61 8 9381 5599",
    "sg:postcode":"6008",
    "sg:province":"WA",
    "sg:tags":[
        "australian",
        "football",
        "rule"
    ],
    "wof:name":"West Australian Football Commission (Inc)",
    "wof:placetype":"venue"
},
  "geometry": {"coordinates":[115.838050842,-31.9453277588],"type":"Point"}
}