{
  "type": "Feature",
  "properties": {
    "addr:full":"Suite 72 Brookfield Rd Minto NSW 2566",
    "addr:postcode":"2566",
    "addr:street":"Brookfield Rd",
    "iso:country":"AU",
    "sg:address":"Suite 72 Brookfield Rd",
    "sg:city":"Minto",
    "sg:classifiers":[
        {
            "category":"Health Services",
            "subcategory":"Doctor",
            "type":"Services"
        }
    ],
    "sg:phone":"+61 2 9603 3211",
    "sg:postcode":"2566",
    "sg:province":"NSW",
    "sg:tags":[
        "medical",
        "practitioner"
    ],
    "wof:name":"Minto Mall Medical Centre",
    "wof:placetype":"venue"
},
  "geometry": {"coordinates":[150.84863281200001,-34.0308456421],"type":"Point"}
}