{
  "type": "Feature",
  "properties": {
    "iso:country":"AU",
    "sg:address":"lst Floor 47 Gouger St",
    "sg:city":"Adelaide",
    "sg:classifiers":[
        {
            "category":"Travel",
            "subcategory":"Hostel",
            "type":"Entertainment"
        }
    ],
    "sg:phone":"+61 8 8212 8866",
    "sg:postcode":"5000",
    "sg:province":"SA",
    "sg:tags":[
        "home"
    ],
    "wof:name":"Jads Group Pty Ltd",
    "wof:placetype":"venue"
},
  "geometry": {"coordinates":[138.59751892099999,-34.9303817749],"type":"Point"}
}