{
  "type": "Feature",
  "properties": {
    "addr:full":"363 Cambridge St Wembley WA 6014",
    "addr:housenumber":"363",
    "addr:postcode":"6014",
    "addr:street":"Cambridge St",
    "iso:country":"AU",
    "sg:address":"363 Cambridge St",
    "sg:city":"Wembley",
    "sg:classifiers":[
        {
            "category":"Cafe",
            "type":"Food & Drink"
        }
    ],
    "sg:phone":"+61 8 9383 9000",
    "sg:postcode":"6014",
    "sg:province":"WA",
    "wof:name":"Al Kebab Cafe",
    "wof:placetype":"venue"
},
  "geometry": {"coordinates":[115.80935669,-31.9408855438],"type":"Point"}
}