{
  "type": "Feature",
  "properties": {
    "addr:full":"Lot 103 Jade St Maddington WA 6109",
    "addr:housenumber":"103",
    "addr:postcode":"6109",
    "addr:street":"Jade St",
    "iso:country":"AU",
    "sg:address":"Lot 103 Jade St",
    "sg:city":"Maddington",
    "sg:classifiers":[
        {
            "category":"Manufacturing",
            "subcategory":"Chemicals & Compounds",
            "type":"Manufacturing & Wholesale Goods"
        }
    ],
    "sg:phone":"+61 8 9493 2353",
    "sg:postcode":"6109",
    "sg:province":"WA",
    "sg:tags":[
        "oil",
        "recovery",
        "dispersal",
        "spill"
    ],
    "wof:name":"Australian Oil Separators",
    "wof:placetype":"venue"
},
  "geometry": {"coordinates":[116.001731873,-32.0396232605],"type":"Point"}
}