{
  "type": "Feature",
  "properties": {
    "addr:full":"98 Fullerton St Stockton NSW 2295",
    "addr:housenumber":"98",
    "addr:postcode":"2295",
    "addr:street":"Fullerton St",
    "iso:country":"AU",
    "sg:address":"98 Fullerton St",
    "sg:city":"Stockton",
    "sg:classifiers":[
        {
            "category":"Autos & Motor Vehicles",
            "subcategory":"Boat Sales",
            "type":"Retail Goods"
        }
    ],
    "sg:phone":"+61 2 4920 1584",
    "sg:postcode":"2295",
    "sg:province":"NSW",
    "sg:tags":[
        "machine",
        "dishwashing"
    ],
    "wof:name":"Lester Gilmore Commercial Services",
    "wof:placetype":"venue"
},
  "geometry": {"coordinates":[151.77952575699999,-32.9105300903],"type":"Point"}
}