{
  "type": "Feature",
  "properties": {
    "addr:full":"Gandy St Manjimup WA 6258",
    "addr:postcode":"6258",
    "addr:street":"Gandy St",
    "iso:country":"AU",
    "sg:address":"Gandy St",
    "sg:city":"Manjimup",
    "sg:classifiers":[
        {
            "category":"Building & Trades",
            "subcategory":"Construction",
            "type":"Services"
        }
    ],
    "sg:phone":"+61 8 9771 2589",
    "sg:postcode":"6258",
    "sg:province":"WA",
    "sg:tags":[
        "earth",
        "excavating",
        "moving",
        "contractor"
    ],
    "wof:name":"Owens B A & C A Pty Ltd",
    "wof:placetype":"venue"
},
  "geometry": {"coordinates":[116.14922332800001,-34.2554740906],"type":"Point"}
}