{
  "type": "Feature",
  "properties": {
    "addr:full":"Suit 1 24-26 Flora St Kirrawee NSW 2232",
    "addr:housenumber":"1",
    "addr:postcode":"24-26;2232",
    "addr:street":"Flora St",
    "iso:country":"AU",
    "sg:address":"Suit 1 24-26 Flora St",
    "sg:city":"Kirrawee",
    "sg:classifiers":[
        {
            "category":"Retail",
            "subcategory":"Car Wash",
            "type":"Services"
        }
    ],
    "sg:phone":"+61 2 9521 8088",
    "sg:postcode":"2232",
    "sg:province":"NSW",
    "sg:tags":[
        "truck",
        "cleaning"
    ],
    "wof:name":"Formula 1 Car Detailing",
    "wof:placetype":"venue"
},
  "geometry": {"coordinates":[151.073196411,-34.0340957642],"type":"Point"}
}