{
  "type": "Feature",
  "properties": {
    "iso:country":"AU",
    "sg:address":"16 Murphy St",
    "sg:city":"Bendigo",
    "sg:classifiers":[
        {
            "category":"Building & Trades",
            "subcategory":"Landscaping Services",
            "type":"Services"
        }
    ],
    "sg:phone":"+61 427 437 440",
    "sg:postcode":"3550",
    "sg:province":"VIC",
    "sg:tags":[
        "firebreak",
        "clearing",
        "land",
        "contractor"
    ],
    "wof:name":"Bob Truscott",
    "wof:placetype":"venue"
},
  "geometry": {"coordinates":[144.292724609,-36.7781333923],"type":"Point"}
}