{
  "type": "Feature",
  "properties": {
    "iso:country":"AU",
    "sg:address":"38 McCoy St",
    "sg:city":"Myaree",
    "sg:classifiers":[
        {
            "category":"Building & Trades",
            "subcategory":"Cleaning & Sanitation",
            "type":"Services"
        }
    ],
    "sg:phone":"+61 8 9330 2611",
    "sg:postcode":"6154",
    "sg:province":"WA",
    "sg:tags":[
        "commercial",
        "maintenance"
    ],
    "wof:name":"Robinson BuildTech",
    "wof:placetype":"venue"
},
  "geometry": {"coordinates":[115.811951,-32.043449],"type":"Point"}
}