{
  "type": "Feature",
  "properties": {
    "addr:full":"Park St Dubbo NSW 2830",
    "addr:postcode":"2830",
    "addr:street":"St",
    "iso:country":"AU",
    "sg:address":"Park St",
    "sg:city":"Dubbo",
    "sg:classifiers":[
        {
            "category":"Sports & Exercise",
            "subcategory":"Sports Center",
            "type":"Entertainment"
        }
    ],
    "sg:phone":"+61 434 149 829",
    "sg:postcode":"2830",
    "sg:province":"NSW",
    "sg:tags":[
        "coach",
        "tennis"
    ],
    "wof:name":"Brian Cooper",
    "wof:placetype":"venue"
},
  "geometry": {"coordinates":[148.60604858400001,-32.2426071167],"type":"Point"}
}