{
  "type": "Feature",
  "properties": {
    "addr:full":"20 Westbourne St Brunswick West VIC 3055",
    "addr:housenumber":"20",
    "addr:postcode":"3055",
    "addr:street":"Westbourne St",
    "iso:country":"AU",
    "sg:address":"20 Westbourne St",
    "sg:city":"Brunswick West",
    "sg:classifiers":[
        {
            "category":"Building & Trades",
            "subcategory":"Landscaping Services",
            "type":"Services"
        }
    ],
    "sg:phone":"+61 1300 136 945",
    "sg:postcode":"3055",
    "sg:province":"VIC",
    "sg:tags":[
        "consultant"
    ],
    "wof:name":"Integrity Building Surveyors",
    "wof:placetype":"venue"
},
  "geometry": {"coordinates":[144.95188903799999,-37.7616348267],"type":"Point"}
}