{
  "type": "Feature",
  "properties": {
    "iso:country":"AU",
    "sg:address":"375 Sturt Pl",
    "sg:city":"Hay",
    "sg:classifiers":[
        {
            "category":"Taxi",
            "type":"Transportation"
        }
    ],
    "sg:phone":"+61 427 933 183",
    "sg:postcode":"2711",
    "sg:province":"NSW",
    "sg:tags":[
        "truck"
    ],
    "wof:name":"Super Fast Service",
    "wof:placetype":"venue"
},
  "geometry": {"coordinates":[144.84703064000001,-34.5059928894],"type":"Point"}
}