{
  "type": "Feature",
  "properties": {
    "addr:full":"PO Box 232 Kilsyth VIC 3137",
    "addr:postcode":"3137",
    "iso:country":"AU",
    "sg:address":"PO Box 232",
    "sg:city":"Kilsyth",
    "sg:classifiers":[
        {
            "category":"Banks & Credit Unions",
            "subcategory":"Bank",
            "type":"Services"
        }
    ],
    "sg:phone":"+61 418 327 842",
    "sg:postcode":"3137",
    "sg:province":"VIC",
    "sg:tags":[
        "line",
        "marking",
        "road"
    ],
    "wof:name":"Precision Line Marking & Floorcoating",
    "wof:placetype":"venue"
},
  "geometry": {"coordinates":[145.31497192399999,-37.8026504517],"type":"Point"}
}