{
  "type": "Feature",
  "properties": {
    "addr:full":"25 Gleddon Rd Bullcreek WA 6149",
    "addr:housenumber":"25",
    "addr:postcode":"6149",
    "addr:street":"Gleddon Rd",
    "iso:country":"AU",
    "sg:address":"25 Gleddon Rd",
    "sg:city":"Bullcreek",
    "sg:classifiers":[
        {
            "category":"Travel",
            "subcategory":"Hostel",
            "type":"Entertainment"
        }
    ],
    "sg:phone":"+61 8 9310 7022",
    "sg:postcode":"6149",
    "sg:province":"WA",
    "sg:tags":[
        "home"
    ],
    "wof:name":"Amana Living",
    "wof:placetype":"venue"
},
  "geometry": {"coordinates":[115.860313,-32.052448],"type":"Point"}
}