{
  "type": "Feature",
  "properties": {
    "addr:full":"2 Wembley Ave Yarraville VIC 3013",
    "addr:housenumber":"2",
    "addr:postcode":"3013",
    "addr:street":"Wembley Ave",
    "iso:country":"AU",
    "sg:address":"2 Wembley Ave",
    "sg:city":"Yarraville",
    "sg:classifiers":[
        {
            "category":"Food & Beverages",
            "subcategory":"Supermarket",
            "type":"Retail Goods"
        }
    ],
    "sg:phone":"+61 3 9314 7171",
    "sg:postcode":"3013",
    "sg:province":"VIC",
    "sg:tags":[
        "grocery",
        "store"
    ],
    "wof:name":"Zaharis Food Store",
    "wof:placetype":"venue"
},
  "geometry": {"coordinates":[144.87385559099999,-37.8194847107],"type":"Point"}
}