{
  "type": "Feature",
  "properties": {
    "iso:country":"AU",
    "sg:address":"49 High St",
    "sg:city":"Sorrento",
    "sg:classifiers":[
        {
            "category":"Home & Garden",
            "subcategory":"Carpets & Floor Coverings",
            "type":"Retail Goods"
        }
    ],
    "sg:phone":"+61 8 9448 1836",
    "sg:postcode":"6020",
    "sg:province":"WA",
    "sg:tags":[
        "tile",
        "wall"
    ],
    "wof:name":"Alex Korwin",
    "wof:placetype":"venue"
},
  "geometry": {"coordinates":[115.754249573,-31.8364143372],"type":"Point"}
}