{
  "type": "Feature",
  "properties": {
    "iso:country":"AU",
    "sg:address":"Lynwood Ave",
    "sg:city":"Lynwood",
    "sg:classifiers":[
        {
            "category":"Communications",
            "subcategory":"Film & Video Production",
            "type":"Services"
        }
    ],
    "sg:phone":"+61 8 9458 7702",
    "sg:postcode":"6147",
    "sg:province":"WA",
    "sg:tags":[
        "dvd",
        "library"
    ],
    "wof:name":"Video Ezy",
    "wof:placetype":"venue"
},
  "geometry": {"coordinates":[115.933258,-32.040703],"type":"Point"}
}