{
  "type": "Feature",
  "properties": {
    "addr:full":"305 Church St Granville NSW 2142",
    "addr:housenumber":"305",
    "addr:postcode":"2142",
    "addr:street":"Church St",
    "iso:country":"AU",
    "sg:address":"305 Church St",
    "sg:city":"Granville",
    "sg:classifiers":[
        {
            "category":"Autos & Motor Vehicles",
            "subcategory":"Auto Supplies",
            "type":"Retail Goods"
        }
    ],
    "sg:phone":"+61 2 9897 5500",
    "sg:postcode":"2142",
    "sg:province":"NSW",
    "sg:tags":[
        "automotive",
        "stereo",
        "radio"
    ],
    "wof:name":"Power Sound",
    "wof:placetype":"venue"
},
  "geometry": {"coordinates":[151.004837036,-33.8263664246],"type":"Point"}
}