{
  "type": "Feature",
  "properties": {
    "addr:full":"Building 24 , Uni Clinic Campbelltown Campus, UWS Campbel NSW 2560",
    "addr:postcode":"2560",
    "iso:country":"AU",
    "sg:address":"Building 24",
    "sg:city":", Uni Clinic Campbelltown Campus, UWS Campbel",
    "sg:classifiers":[
        {
            "category":"Health Services",
            "subcategory":"Health Practitioner",
            "type":"Services"
        }
    ],
    "sg:phone":"+61 2 4620 3734",
    "sg:postcode":"2560",
    "sg:province":"NSW",
    "sg:tags":[
        "acupuncture"
    ],
    "wof:name":"Zhu Xiao Shu",
    "wof:placetype":"venue"
},
  "geometry": {"coordinates":[150.82493591299999,-34.063167572],"type":"Point"}
}