{
  "type": "Feature",
  "properties": {
    "addr:full":"247 Waterdale Rd Ivanhoe VIC 3079",
    "addr:housenumber":"247",
    "addr:postcode":"3079",
    "addr:street":"Waterdale Rd",
    "iso:country":"AU",
    "sg:address":"247 Waterdale Rd",
    "sg:city":"Ivanhoe",
    "sg:classifiers":[
        {
            "category":"Autos & Motor Vehicles",
            "subcategory":"Fuel & Gas Station",
            "type":"Retail Goods"
        }
    ],
    "sg:phone":"+61 3 9499 2437",
    "sg:postcode":"3079",
    "sg:province":"VIC",
    "wof:name":"Ivanhoe Fuel",
    "wof:placetype":"venue"
},
  "geometry": {"coordinates":[145.044921875,-37.7582321167],"type":"Point"}
}