{
  "type": "Feature",
  "properties": {
    "iso:country":"AU",
    "sg:address":"31 Davenport St",
    "sg:city":"Port Augusta",
    "sg:classifiers":[
        {
            "category":"Professional",
            "subcategory":"Printing & Photocopies",
            "type":"Services"
        }
    ],
    "sg:phone":"+61 8 8641 0200",
    "sg:postcode":"5700",
    "sg:province":"SA",
    "sg:tags":[
        "equipment",
        "plan"
    ],
    "wof:name":"Augusta Design Centre",
    "wof:placetype":"venue"
},
  "geometry": {"coordinates":[137.77476501500001,-32.4892845154],"type":"Point"}
}