{
  "type": "Feature",
  "properties": {
    "addr:full":"2 Alfred Rd Brookvale NSW 2100",
    "addr:housenumber":"2",
    "addr:postcode":"2100",
    "addr:street":"Alfred Rd",
    "iso:country":"AU",
    "sg:address":"2 Alfred Rd",
    "sg:city":"Brookvale",
    "sg:classifiers":[
        {
            "category":"Organizations",
            "subcategory":"Non-profit Organization",
            "type":"Services"
        }
    ],
    "sg:phone":"+61 2 9907 4222",
    "sg:postcode":"2100",
    "sg:province":"NSW",
    "sg:tags":[
        "support",
        "disability",
        "organisation"
    ],
    "wof:name":"Learning Links",
    "wof:placetype":"venue"
},
  "geometry": {"coordinates":[151.271774292,-33.7614936829],"type":"Point"}
}