{
  "type": "Feature",
  "properties": {
    "iso:country":"AU",
    "sg:address":"88 Holdom Rd",
    "sg:city":"Karuah",
    "sg:classifiers":[
        {
            "category":"Social Services",
            "subcategory":"Retirement Home",
            "type":"Services"
        }
    ],
    "sg:phone":"+61 2 4997 5520",
    "sg:postcode":"2324",
    "sg:province":"NSW",
    "sg:tags":[
        "village"
    ],
    "wof:name":"Karuah Jetty Village",
    "wof:placetype":"venue"
},
  "geometry": {"coordinates":[151.962615967,-32.6617164612],"type":"Point"}
}