{
  "type": "Feature",
  "properties": {
    "addr:full":"Unit 4, 1 Cavendish St Mittagong NSW 2575",
    "addr:housenumber":"1",
    "addr:postcode":"2575",
    "addr:street":"Cavendish St",
    "iso:country":"AU",
    "sg:address":"Unit 4, 1 Cavendish St",
    "sg:city":"Mittagong",
    "sg:classifiers":[
        {
            "category":"Utilities",
            "subcategory":"Electric",
            "type":"Services"
        }
    ],
    "sg:phone":"+61 2 4872 1711",
    "sg:postcode":"2575",
    "sg:province":"NSW",
    "sg:tags":[
        "electrical",
        "contractor"
    ],
    "wof:name":"FRH Electrical",
    "wof:placetype":"venue"
},
  "geometry": {"coordinates":[150.43423461899999,-34.4474525452],"type":"Point"}
}