{
  "type": "Feature",
  "properties": {
    "iso:country":"AU",
    "sg:address":"44 Earl St",
    "sg:city":"Wilberforce",
    "sg:classifiers":[
        {
            "category":"Recreation",
            "subcategory":"Boat Charter",
            "type":"Entertainment"
        }
    ],
    "sg:phone":"+61 2 4575 1893",
    "sg:postcode":"2756",
    "sg:province":"NSW",
    "wof:name":"A Australian Sports Fishing & Bass Adventures",
    "wof:placetype":"venue"
},
  "geometry": {"coordinates":[150.837493897,-33.5606002808],"type":"Point"}
}