{
  "type": "Feature",
  "properties": {
    "iso:country":"AU",
    "sg:address":"Monduran Rd",
    "sg:city":"Gin Gin",
    "sg:classifiers":[
        {
            "category":"Farming",
            "subcategory":"Orchard",
            "type":"Manufacturing & Wholesale Goods"
        }
    ],
    "sg:phone":"+61 7 4157 3316",
    "sg:postcode":"4671",
    "sg:province":"QLD",
    "sg:tags":[
        "citrus",
        "fruit",
        "grower"
    ],
    "wof:name":"Monduran Citrus",
    "wof:placetype":"venue"
},
  "geometry": {"coordinates":[151.934525,-24.794527],"type":"Point"}
}