{
  "type": "Feature",
  "properties": {
    "addr:full":"70 Beach St Woolgoolga NSW 2456",
    "addr:housenumber":"70",
    "addr:postcode":"2456",
    "addr:street":"Beach St",
    "iso:country":"AU",
    "sg:address":"70 Beach St",
    "sg:city":"Woolgoolga",
    "sg:classifiers":[
        {
            "category":"Food & Beverages",
            "subcategory":"Fruits & Vegetables",
            "type":"Retail Goods"
        }
    ],
    "sg:phone":"+61 2 6654 2488",
    "sg:postcode":"2456",
    "sg:province":"NSW",
    "sg:tags":[
        "greengrocer",
        "fruiterer"
    ],
    "wof:name":"Planet Fruit & Vege",
    "wof:placetype":"venue"
},
  "geometry": {"coordinates":[153.20181299999999,-30.110449],"type":"Point"}
}