{
  "type": "Feature",
  "properties": {
    "addr:full":"155-175 Bonnyvale Rd Ocean Grove VIC 3226",
    "addr:housenumber":"155-175",
    "addr:postcode":"3226",
    "addr:street":"Bonnyvale Rd",
    "iso:country":"AU",
    "sg:address":"155-175 Bonnyvale Rd",
    "sg:city":"Ocean Grove",
    "sg:classifiers":[
        {
            "category":"Travel",
            "subcategory":"Hotels & Motels",
            "type":"Entertainment"
        }
    ],
    "sg:phone":"+61 3 5255 1122",
    "sg:postcode":"3226",
    "sg:province":"VIC",
    "sg:tags":[
        "accommodation"
    ],
    "wof:name":"Ocean Grove Hotel Motel",
    "wof:placetype":"venue"
},
  "geometry": {"coordinates":[144.55766299999999,-38.259892],"type":"Point"}
}