{
  "type": "Feature",
  "properties": {
    "addr:full":"29 Penny La McCrae VIC 3938",
    "addr:housenumber":"29",
    "addr:postcode":"3938",
    "addr:street":"Penny La Mccrae",
    "iso:country":"AU",
    "sg:address":"29 Penny La",
    "sg:city":"McCrae",
    "sg:classifiers":[
        {
            "category":"Organizations",
            "subcategory":"Professional Association",
            "type":"Services"
        }
    ],
    "sg:phone":"+61 1800 852 853",
    "sg:postcode":"3938",
    "sg:province":"VIC",
    "sg:tags":[
        "web",
        "internet"
    ],
    "wof:name":"I-Sold It Victoria Tasmania Pty Ltd",
    "wof:placetype":"venue"
},
  "geometry": {"coordinates":[144.934524536,-38.3460464478],"type":"Point"}
}