{
  "type": "Feature",
  "properties": {
    "addr:full":"25- 27 Alma Ave Woy Woy NSW 2256",
    "addr:housenumber":"27",
    "addr:postcode":"2256",
    "addr:street":"Alma Ave",
    "iso:country":"AU",
    "sg:address":"25- 27 Alma Ave",
    "sg:city":"Woy Woy",
    "sg:classifiers":[
        {
            "category":"Commercial Area",
            "type":"Public Place"
        }
    ],
    "sg:phone":"+61 2 4344 1110",
    "sg:postcode":"2256",
    "sg:province":"NSW",
    "sg:tags":[
        "heavy",
        "carrier"
    ],
    "sg:website":"http://www.roylamb.com.au",
    "wof:name":"Roy Lamb",
    "wof:placetype":"venue"
},
  "geometry": {"coordinates":[151.324310303,-33.5037765503],"type":"Point"}
}