{
  "type": "Feature",
  "properties": {
    "addr:full":"51 Howard Rd Dingley VIC 3172",
    "addr:housenumber":"51",
    "addr:postcode":"3172",
    "addr:street":"Howard Rd",
    "iso:country":"AU",
    "sg:address":"51 Howard Rd",
    "sg:city":"Dingley",
    "sg:classifiers":[
        {
            "category":"Professional",
            "subcategory":"Art Services",
            "type":"Services"
        }
    ],
    "sg:phone":"+61 411 420 429",
    "sg:postcode":"3172",
    "sg:province":"VIC",
    "sg:tags":[
        "decorator",
        "painter"
    ],
    "wof:name":"D.A.W Painters",
    "wof:placetype":"venue"
},
  "geometry": {"coordinates":[145.12176513700001,-37.980682373],"type":"Point"}
}