{
  "type": "Feature",
  "properties": {
    "addr:full":"U3/ 350 Great Eastern Hwy Midland WA 6056",
    "addr:housenumber":"350",
    "addr:postcode":"6056",
    "addr:street":"U3 /;Great Eastern Hwy",
    "iso:country":"AU",
    "sg:address":"U3/ 350 Great Eastern Hwy",
    "sg:city":"Midland",
    "sg:classifiers":[
        {
            "category":"Retail",
            "subcategory":"Auto Repair",
            "type":"Services"
        }
    ],
    "sg:phone":"+61 8 9274 2066",
    "sg:postcode":"6056",
    "sg:province":"WA",
    "sg:tags":[
        "repairer",
        "motor",
        "engineer"
    ],
    "wof:name":"Ultra Lube 2000",
    "wof:placetype":"venue"
},
  "geometry": {"coordinates":[116.012588501,-31.8918380737],"type":"Point"}
}