{
  "type": "Feature",
  "properties": {
    "addr:full":"6 Simmonds Pl Endeavour Hills VIC 3802",
    "addr:housenumber":"6",
    "addr:postcode":"3802",
    "addr:street":"Simmonds Pl",
    "iso:country":"AU",
    "sg:address":"6 Simmonds Pl",
    "sg:city":"Endeavour Hills",
    "sg:classifiers":[
        {
            "category":"Utilities",
            "subcategory":"Natural Gas",
            "type":"Services"
        }
    ],
    "sg:phone":"+61 3 9706 2681",
    "sg:postcode":"3802",
    "sg:province":"VIC",
    "sg:tags":[
        "supplier"
    ],
    "wof:name":"Gas To Go Australia",
    "wof:placetype":"venue"
},
  "geometry": {"coordinates":[145.248123169,-37.9796028137],"type":"Point"}
}