{
  "type": "Feature",
  "properties": {
    "addr:full":"442 Sheridan St Cairns QLD 4870",
    "addr:housenumber":"442",
    "addr:postcode":"4870",
    "addr:street":"Sheridan St",
    "iso:country":"AU",
    "sg:address":"442 Sheridan St",
    "sg:city":"Cairns",
    "sg:classifiers":[
        {
            "category":"Banks & Credit Unions",
            "subcategory":"Investment Brokerage",
            "type":"Services"
        }
    ],
    "sg:phone":"+61 1300 797 003",
    "sg:postcode":"4870",
    "sg:province":"QLD",
    "sg:tags":[
        "radiator",
        "motor"
    ],
    "wof:name":"Adrad Radiator Experts",
    "wof:placetype":"venue"
},
  "geometry": {"coordinates":[145.75416564899999,-16.8947105408],"type":"Point"}
}