{
  "type": "Feature",
  "properties": {
    "addr:full":"4/ 63 Walters Drv Herdsman WA 6017",
    "addr:housenumber":"/ 63",
    "addr:postcode":"6017",
    "addr:street":"Walters Drv",
    "iso:country":"AU",
    "sg:address":"4/ 63 Walters Drv",
    "sg:city":"Herdsman",
    "sg:classifiers":[
        {
            "category":"Building & Trades",
            "subcategory":"Pest Control",
            "type":"Services"
        }
    ],
    "sg:phone":"+61 8 9231 4744",
    "sg:postcode":"6017",
    "sg:province":"WA",
    "wof:name":"Envirotechnics Professional Pest Management",
    "wof:placetype":"venue"
},
  "geometry": {"coordinates":[115.814331055,-31.9130764008],"type":"Point"}
}