{
  "type": "Feature",
  "properties": {
    "iso:country":"AU",
    "sg:address":"37 Buckingham Drv",
    "sg:city":"Wangara",
    "sg:classifiers":[
        {
            "category":"Building & Trades",
            "subcategory":"Equipment Rental",
            "type":"Services"
        }
    ],
    "sg:phone":"+61 8 9409 3344",
    "sg:postcode":"6065",
    "sg:province":"WA",
    "sg:tags":[
        "renting",
        "trailer"
    ],
    "wof:name":"The Hire Guys",
    "wof:placetype":"venue"
},
  "geometry": {"coordinates":[115.819229126,-31.7868976593],"type":"Point"}
}