{
  "type": "Feature",
  "properties": {
    "addr:full":"51 Port Rd Kadina SA 5554",
    "addr:housenumber":"51",
    "addr:postcode":"5554",
    "addr:street":"Port Rd",
    "iso:country":"AU",
    "sg:address":"51 Port Rd",
    "sg:city":"Kadina",
    "sg:classifiers":[
        {
            "category":"Shopping",
            "subcategory":"Mobile Phones",
            "type":"Retail Goods"
        }
    ],
    "sg:phone":"+61 8 8821 4000",
    "sg:postcode":"5554",
    "sg:province":"SA",
    "sg:tags":[
        "telephone",
        "accessory"
    ],
    "wof:name":"Copper Coast Auto Electrical",
    "wof:placetype":"venue"
},
  "geometry": {"coordinates":[137.69801330600001,-33.9596252441],"type":"Point"}
}