{
  "type": "Feature",
  "properties": {
    "iso:country":"AU",
    "sg:address":"Suite 1.1 Epworth Medical Centre 173 Lennox St",
    "sg:city":"Richmond",
    "sg:classifiers":[
        {
            "category":"Health Services",
            "subcategory":"Doctor",
            "type":"Services"
        }
    ],
    "sg:phone":"+61 3 9428 8998",
    "sg:postcode":"3121",
    "sg:province":"VIC",
    "sg:tags":[
        "medical",
        "practitioner"
    ],
    "wof:name":"Burns Paul A",
    "wof:placetype":"venue"
},
  "geometry": {"coordinates":[144.9949646,-37.8170166016],"type":"Point"}
}