{
  "type": "Feature",
  "properties": {
    "addr:full":"91 Moreland St Footscray VIC 3011",
    "addr:housenumber":"91",
    "addr:postcode":"3011",
    "addr:street":"Moreland St",
    "iso:country":"AU",
    "sg:address":"91 Moreland St",
    "sg:city":"Footscray",
    "sg:classifiers":[
        {
            "category":"Fast Food",
            "type":"Food & Drink"
        }
    ],
    "sg:phone":"+61 3 9689 8460",
    "sg:postcode":"3011",
    "sg:province":"VIC",
    "sg:tags":[
        "away",
        "take"
    ],
    "wof:name":"Quality Corner Take Away",
    "wof:placetype":"venue"
},
  "geometry": {"coordinates":[144.905563355,-37.8053436279],"type":"Point"}
}