{
  "type": "Feature",
  "properties": {
    "addr:full":"376a Unley Rd Unley SA 5061",
    "addr:housenumber":"376a",
    "addr:postcode":"5061",
    "addr:street":"Unley Rd",
    "iso:country":"AU",
    "sg:address":"376a Unley Rd",
    "sg:city":"Unley",
    "sg:classifiers":[
        {
            "category":"Retail",
            "subcategory":"Repair Shop",
            "type":"Services"
        }
    ],
    "sg:phone":"+61 1300 361 363",
    "sg:postcode":"5061",
    "sg:province":"SA",
    "sg:tags":[
        "machine",
        "repairs",
        "part",
        "dryer",
        "washing"
    ],
    "wof:name":"Ivesons Electrical Pty Ltd",
    "wof:placetype":"venue"
},
  "geometry": {"coordinates":[138.608184814,-34.9615974426],"type":"Point"}
}