{
  "type": "Feature",
  "properties": {
    "iso:country":"AU",
    "sg:address":"Un 3/ 33 Rockingham Beach Rd",
    "sg:city":"Rockingham",
    "sg:classifiers":[
        {
            "category":"Shopping",
            "subcategory":"Clothing, Apparel, & Fashions",
            "type":"Retail Goods"
        }
    ],
    "sg:phone":"+61 8 9591 3699",
    "sg:postcode":"6168",
    "sg:province":"WA",
    "sg:tags":[
        "lady",
        "wear"
    ],
    "wof:name":"Danica's Design Studio",
    "wof:placetype":"venue"
},
  "geometry": {"coordinates":[115.73155199999999,-32.274563],"type":"Point"}
}