{
  "type": "Feature",
  "properties": {
    "iso:country":"AU",
    "sg:address":"15 Colin St",
    "sg:city":"West Perth",
    "sg:classifiers":[
        {
            "category":"Health Services",
            "subcategory":"Health Practitioner",
            "type":"Services"
        }
    ],
    "sg:phone":"+61 417 986 353",
    "sg:postcode":"6005",
    "sg:province":"WA",
    "sg:tags":[
        "alternative"
    ],
    "wof:name":"Dennis Talbot",
    "wof:placetype":"venue"
},
  "geometry": {"coordinates":[115.840843201,-31.9512825012],"type":"Point"}
}