{
  "type": "Feature",
  "properties": {
    "iso:country":"AU",
    "sg:address":"5 Bay St",
    "sg:city":"Port Melbourne",
    "sg:classifiers":[
        {
            "category":"Retail",
            "subcategory":"Storage",
            "type":"Services"
        }
    ],
    "sg:phone":"+61 3 9646 8590",
    "sg:postcode":"3207",
    "sg:province":"VIC",
    "sg:tags":[
        "removal",
        "furniture"
    ],
    "wof:name":"Victorian Furniture Removers Association",
    "wof:placetype":"venue"
},
  "geometry": {"coordinates":[144.938324,-37.842705],"type":"Point"}
}