{
  "type": "Feature",
  "properties": {
    "addr:full":"1 Jacques Rd Narre Warren North VIC 3804",
    "addr:housenumber":"1",
    "addr:postcode":"3804",
    "addr:street":"Jacques Rd",
    "iso:country":"AU",
    "sg:address":"1 Jacques Rd",
    "sg:city":"Narre Warren North",
    "sg:classifiers":[
        {
            "category":"Building & Trades",
            "subcategory":"Equipment Rental",
            "type":"Services"
        }
    ],
    "sg:phone":"+61 3 9796 8366",
    "sg:postcode":"3804",
    "sg:province":"VIC",
    "sg:tags":[
        "renting",
        "trailer"
    ],
    "wof:name":"McGarry Horse Floats",
    "wof:placetype":"venue"
},
  "geometry": {"coordinates":[145.29566955600001,-37.9885787964],"type":"Point"}
}