{
  "type": "Feature",
  "properties": {
    "iso:country":"AU",
    "sg:address":"339 Pacific Hwy",
    "sg:city":"Artarmon",
    "sg:classifiers":[
        {
            "category":"Banks & Credit Unions",
            "subcategory":"Investment Brokerage",
            "type":"Services"
        }
    ],
    "sg:phone":"+61 2 9906 7119",
    "sg:postcode":"2064",
    "sg:province":"NSW",
    "sg:tags":[
        "finance",
        "broker"
    ],
    "wof:name":"Affiliated Finance Pty Ltd",
    "wof:placetype":"venue"
},
  "geometry": {"coordinates":[151.180541992,-33.8172149658],"type":"Point"}
}