{
  "type": "Feature",
  "properties": {
    "addr:full":"187 Sanger St Corowa NSW 2646",
    "addr:housenumber":"187",
    "addr:postcode":"2646",
    "addr:street":"Sanger St",
    "iso:country":"AU",
    "sg:address":"187 Sanger St",
    "sg:city":"Corowa",
    "sg:classifiers":[
        {
            "category":"Home & Garden",
            "subcategory":"Carpets & Floor Coverings",
            "type":"Retail Goods"
        }
    ],
    "sg:phone":"+61 2 6033 2499",
    "sg:postcode":"2646",
    "sg:province":"NSW",
    "wof:name":"Corowa Interiors",
    "wof:placetype":"venue"
},
  "geometry": {"coordinates":[146.391357422,-35.9958686829],"type":"Point"}
}