{
  "type": "Feature",
  "properties": {
    "iso:country":"AU",
    "sg:address":"4th Floor, 31 Dixon St",
    "sg:city":"(Entrance Via Factory St) Sydney",
    "sg:classifiers":[
        {
            "category":"Arena",
            "subcategory":"Sports Club",
            "type":"Entertainment"
        }
    ],
    "sg:phone":"+61 412 232 988",
    "sg:postcode":"2000",
    "sg:province":"NSW",
    "sg:tags":[
        "defence",
        "supply",
        "self",
        "instruction",
        "martial art"
    ],
    "wof:name":"Master Cheuk-Fai Chan",
    "wof:placetype":"venue"
},
  "geometry": {"coordinates":[151.203857422,-33.8781089783],"type":"Point"}
}