{
  "type": "Feature",
  "properties": {
    "addr:full":"155 Bellingara Rd Miranda NSW 2228",
    "addr:housenumber":"155",
    "addr:postcode":"2228",
    "addr:street":"Bellingara Rd",
    "iso:country":"AU",
    "sg:address":"155 Bellingara Rd",
    "sg:city":"Miranda",
    "sg:classifiers":[
        {
            "category":"Education",
            "subcategory":"Music School",
            "type":"Public Place"
        }
    ],
    "sg:phone":"+61 2 9522 7478",
    "sg:postcode":"2228",
    "sg:province":"NSW",
    "sg:tags":[
        "teacher"
    ],
    "wof:name":"A Piano Teacher For All Ages",
    "wof:placetype":"venue"
},
  "geometry": {"coordinates":[151.099212647,-34.0273208618],"type":"Point"}
}