{
  "type": "Feature",
  "properties": {
    "iso:country":"AU",
    "sg:address":"220 Cressy St",
    "sg:city":"Deniliquin",
    "sg:classifiers":[
        {
            "category":"Shopping",
            "subcategory":"Computers & Home Electronics",
            "type":"Retail Goods"
        }
    ],
    "sg:phone":"+61 3 5881 3672",
    "sg:postcode":"2710",
    "sg:province":"NSW",
    "sg:tags":[
        "equipment",
        "part",
        "electronic"
    ],
    "wof:name":"Dick Smith Electronics Pty Ltd",
    "wof:placetype":"venue"
},
  "geometry": {"coordinates":[144.96188354500001,-35.5279769897],"type":"Point"}
}