{
  "type": "Feature",
  "properties": {
    "addr:full":"12a Carabella St Kirribilli NSW 2061",
    "addr:housenumber":"12a",
    "addr:postcode":"2061",
    "addr:street":"Carabella St",
    "iso:country":"AU",
    "sg:address":"12a Carabella St",
    "sg:city":"Kirribilli",
    "sg:classifiers":[
        {
            "category":"Travel",
            "subcategory":"Hotels & Motels",
            "type":"Entertainment"
        }
    ],
    "sg:phone":"+61 1800 121 011",
    "sg:postcode":"2061",
    "sg:province":"NSW",
    "sg:tags":[
        "accommodation"
    ],
    "wof:name":"Glenferrie Lodge",
    "wof:placetype":"venue"
},
  "geometry": {"coordinates":[151.21844482399999,-33.8501091003],"type":"Point"}
}