{
  "type": "Feature",
  "properties": {
    "addr:full":"325 George St Brisbane City QLD 4000",
    "addr:housenumber":"325",
    "addr:postcode":"4000",
    "addr:street":"George St",
    "iso:country":"AU",
    "sg:address":"325 George St",
    "sg:city":"Brisbane City",
    "sg:classifiers":[
        {
            "category":"Restaurant",
            "type":"Food & Drink"
        }
    ],
    "sg:phone":"+61 7 3308 0736",
    "sg:postcode":"4000",
    "sg:province":"QLD",
    "wof:name":"Cerello's Bar Cafe",
    "wof:placetype":"venue"
},
  "geometry": {"coordinates":[153.02191162099999,-27.4690513611],"type":"Point"}
}