{
  "type": "Feature",
  "properties": {
    "addr:full":"255 Belmore Rd Balwyn North VIC 3104",
    "addr:housenumber":"255",
    "addr:postcode":"3104",
    "addr:street":"Belmore Rd",
    "iso:country":"AU",
    "sg:address":"255 Belmore Rd",
    "sg:city":"Balwyn North",
    "sg:classifiers":[
        {
            "category":"Food & Beverages",
            "subcategory":"Supermarket",
            "type":"Retail Goods"
        }
    ],
    "sg:phone":"+61 3 9857 4182",
    "sg:postcode":"3104",
    "sg:province":"VIC",
    "sg:tags":[
        "grocery",
        "store"
    ],
    "wof:name":"Friendly Grocer IGA",
    "wof:placetype":"venue"
},
  "geometry": {"coordinates":[145.08396911599999,-37.8034210205],"type":"Point"}
}