{
  "type": "Feature",
  "properties": {
    "addr:full":"Unit 5, 16 O&#039;Shea Drv Nerang QLD 4211",
    "addr:housenumber":"16",
    "addr:postcode":"4211",
    "addr:street":"O &;Shea Drv",
    "iso:country":"AU",
    "sg:address":"Unit 5, 16 O&#039;Shea Drv",
    "sg:city":"Nerang",
    "sg:classifiers":[
        {
            "category":"Professional",
            "subcategory":"Testing Lab",
            "type":"Services"
        }
    ],
    "sg:phone":"+61 7 5500 4666",
    "sg:postcode":"4211",
    "sg:province":"QLD",
    "sg:tags":[
        "soil",
        "investigation"
    ],
    "wof:name":"Soil and Water Laboratories",
    "wof:placetype":"venue"
},
  "geometry": {"coordinates":[153.344284058,-27.9996376038],"type":"Point"}
}