{
  "type": "Feature",
  "properties": {
    "addr:full":"Mobil Rd Bell Bay TAS 7253",
    "addr:postcode":"7253",
    "addr:street":"Rd",
    "iso:country":"AU",
    "sg:address":"Mobil Rd",
    "sg:city":"Bell Bay",
    "sg:classifiers":[
        {
            "category":"Wholesale",
            "subcategory":"Construction Materials",
            "type":"Manufacturing & Wholesale Goods"
        }
    ],
    "sg:phone":"+61 409 940 715",
    "sg:postcode":"7253",
    "sg:province":"TAS",
    "sg:tags":[
        "protective",
        "coating"
    ],
    "wof:name":"Al's Painting Service",
    "wof:placetype":"venue"
},
  "geometry": {"coordinates":[146.866653442,-41.1310157776],"type":"Point"}
}