{
  "type": "Feature",
  "properties": {
    "addr:full":"174 Byng St Orange NSW 2800",
    "addr:housenumber":"174",
    "addr:postcode":"2800",
    "addr:street":"Byng St",
    "iso:country":"AU",
    "sg:address":"174 Byng St",
    "sg:city":"Orange",
    "sg:classifiers":[
        {
            "category":"Utilities",
            "subcategory":"Fuel Oil & Lpg",
            "type":"Services"
        }
    ],
    "sg:phone":"+61 2 6362 7655",
    "sg:postcode":"2800",
    "sg:province":"NSW",
    "sg:tags":[
        "merchant"
    ],
    "wof:name":"Hayes Petroleum",
    "wof:placetype":"venue"
},
  "geometry": {"coordinates":[149.094970703,-33.2808570862],"type":"Point"}
}