{
  "type": "Feature",
  "properties": {
    "iso:country":"AU",
    "sg:address":"91 Chatham St",
    "sg:city":"Broadmeadow",
    "sg:classifiers":[
        {
            "category":"Health Services",
            "subcategory":"Doctor",
            "type":"Services"
        }
    ],
    "sg:phone":"+61 2 4940 0470",
    "sg:postcode":"2292",
    "sg:province":"NSW",
    "sg:tags":[
        "medical",
        "practitioner"
    ],
    "wof:name":"Bailey K",
    "wof:placetype":"venue"
},
  "geometry": {"coordinates":[151.737228394,-32.9255371094],"type":"Point"}
}