{
  "type": "Feature",
  "properties": {
    "addr:full":"205-207 Plain St East Perth WA 6004",
    "addr:housenumber":"205-207",
    "addr:postcode":"6004",
    "addr:street":"Plain St East",
    "iso:country":"AU",
    "sg:address":"205-207 Plain St",
    "sg:city":"East Perth",
    "sg:classifiers":[
        {
            "category":"Shopping",
            "subcategory":"Stationery & Office Supplies",
            "type":"Retail Goods"
        }
    ],
    "sg:phone":"+61 8 9221 4300",
    "sg:postcode":"6004",
    "sg:province":"WA",
    "sg:tags":[
        "packaging",
        "material"
    ],
    "wof:name":"Impacked Pty Ltd",
    "wof:placetype":"venue"
},
  "geometry": {"coordinates":[115.877388001,-31.9540958405],"type":"Point"}
}