{
  "type": "Feature",
  "properties": {
    "iso:country":"AU",
    "sg:address":"Factory 3, 65 Heatherdale Rd",
    "sg:city":"Ringwood",
    "sg:classifiers":[
        {
            "category":"Wholesale",
            "subcategory":"Machinery & Supplies",
            "type":"Manufacturing & Wholesale Goods"
        }
    ],
    "sg:phone":"+61 3 9872 3122",
    "sg:postcode":"3134",
    "sg:province":"VIC",
    "sg:tags":[
        "bearing",
        "bushing"
    ],
    "wof:name":"Bearing Wholesalers Pty Ltd",
    "wof:placetype":"venue"
},
  "geometry": {"coordinates":[145.213500977,-37.8233566284],"type":"Point"}
}