{
  "type": "Feature",
  "properties": {
    "iso:country":"AU",
    "sg:address":"3 Animoo Ave",
    "sg:city":"Griffith",
    "sg:classifiers":[
        {
            "category":"Health Services",
            "subcategory":"Medical Lab",
            "type":"Services"
        }
    ],
    "sg:phone":"+61 2 6964 1103",
    "sg:postcode":"2680",
    "sg:province":"NSW",
    "sg:tags":[
        "laboratory",
        "pathology"
    ],
    "wof:name":"Griffith Mansfield Pathology",
    "wof:placetype":"venue"
},
  "geometry": {"coordinates":[146.041946,-34.282261],"type":"Point"}
}