{
  "type": "Feature",
  "properties": {
    "iso:country":"AU",
    "sg:address":"25 Parry St",
    "sg:city":"Fremantle",
    "sg:classifiers":[
        {
            "category":"Health Services",
            "subcategory":"Health Practitioner",
            "type":"Services"
        }
    ],
    "sg:phone":"+61 8 9430 5277",
    "sg:postcode":"6160",
    "sg:province":"WA",
    "sg:tags":[
        "psychologist"
    ],
    "wof:name":"Ryan Paul",
    "wof:placetype":"venue"
},
  "geometry": {"coordinates":[115.75160200000001,-32.053658],"type":"Point"}
}