{
  "type": "Feature",
  "properties": {
    "addr:full":"8 Lions Club Drv Kelso NSW 2795",
    "addr:housenumber":"8",
    "addr:postcode":"2795",
    "addr:street":"Lions Club Drv",
    "iso:country":"AU",
    "sg:address":"8 Lions Club Drv",
    "sg:city":"Kelso",
    "sg:classifiers":[
        {
            "category":"Shopping",
            "subcategory":"Clothing, Apparel, & Fashions",
            "type":"Retail Goods"
        }
    ],
    "sg:phone":"+61 2 6332 1799",
    "sg:postcode":"2795",
    "sg:province":"NSW",
    "sg:tags":[
        "recycled",
        "clothing"
    ],
    "wof:name":"Royal Far West Oppurtunity Shop",
    "wof:placetype":"venue"
},
  "geometry": {"coordinates":[149.59349060100001,-33.4163780212],"type":"Point"}
}