{
  "type": "Feature",
  "properties": {
    "addr:full":"Claymore Shopping Centre Claymore NSW 2559",
    "addr:postcode":"2559",
    "iso:country":"AU",
    "sg:address":"Claymore Shopping Centre",
    "sg:city":"Claymore",
    "sg:classifiers":[
        {
            "category":"Health Services",
            "subcategory":"Doctor",
            "type":"Services"
        }
    ],
    "sg:phone":"+61 2 4625 7382",
    "sg:postcode":"2559",
    "sg:province":"NSW",
    "sg:tags":[
        "medical",
        "practitioner"
    ],
    "wof:name":"Macarthur Square Medical & Dental Centre",
    "wof:placetype":"venue"
},
  "geometry": {"coordinates":[150.81414794899999,-34.0449409485],"type":"Point"}
}