{
  "type": "Feature",
  "properties": {
    "iso:country":"AU",
    "sg:address":"PO Box 2076",
    "sg:city":"Kent Town",
    "sg:classifiers":[
        {
            "category":"Building & Trades",
            "subcategory":"Cleaning & Sanitation",
            "type":"Services"
        }
    ],
    "sg:phone":"+61 412 190 919",
    "sg:postcode":"5067",
    "sg:province":"SA",
    "sg:tags":[
        "window"
    ],
    "wof:name":"Daren Russell Window Cleaning",
    "wof:placetype":"venue"
},
  "geometry": {"coordinates":[138.617584228,-34.9208984375],"type":"Point"}
}