{
  "type": "Feature",
  "properties": {
    "addr:full":"362-368 Swan St Richmond VIC 3121",
    "addr:housenumber":"362-368",
    "addr:postcode":"3121",
    "addr:street":"Swan St",
    "iso:country":"AU",
    "sg:address":"362-368 Swan St",
    "sg:city":"Richmond",
    "sg:classifiers":[
        {
            "category":"Shopping",
            "subcategory":"Computers & Home Electronics",
            "type":"Retail Goods"
        }
    ],
    "sg:phone":"+61 3 9429 9355",
    "sg:postcode":"3121",
    "sg:province":"VIC",
    "sg:tags":[
        "equipment",
        "supply"
    ],
    "wof:name":"Discosource Australia Pty Ltd",
    "wof:placetype":"venue"
},
  "geometry": {"coordinates":[145.00367736800001,-37.826423645],"type":"Point"}
}