{
  "type": "Feature",
  "properties": {
    "addr:full":"198 Wolfram St Broken Hill NSW 2880",
    "addr:housenumber":"198",
    "addr:postcode":"2880",
    "addr:street":"Wolfram St",
    "iso:country":"AU",
    "sg:address":"198 Wolfram St",
    "sg:city":"Broken Hill",
    "sg:classifiers":[
        {
            "category":"Organizations",
            "subcategory":"Community Association",
            "type":"Services"
        }
    ],
    "sg:phone":"+61 8 8087 1999",
    "sg:postcode":"2880",
    "sg:province":"NSW",
    "sg:tags":[
        "organisation",
        "family",
        "welfare"
    ],
    "wof:name":"Catherine Haven Crisis Accommodation",
    "wof:placetype":"venue"
},
  "geometry": {"coordinates":[141.465499878,-31.9526290894],"type":"Point"}
}