{
  "type": "Feature",
  "properties": {
    "iso:country":"AU",
    "sg:address":"639 Pacific Hwy",
    "sg:city":"Chatswood",
    "sg:classifiers":[
        {
            "category":"Autos & Motor Vehicles",
            "subcategory":"Auto Supplies",
            "type":"Retail Goods"
        }
    ],
    "sg:phone":"+61 2 9413 4888",
    "sg:postcode":"2067",
    "sg:province":"NSW",
    "sg:tags":[
        "wheel",
        "automotive",
        "rim"
    ],
    "wof:name":"Payless Tyres & Brakes",
    "wof:placetype":"venue"
},
  "geometry": {"coordinates":[151.17811584500001,-33.7963752747],"type":"Point"}
}