{
  "type": "Feature",
  "properties": {
    "addr:full":"109 Woodville Rd Woodville SA 5011",
    "addr:housenumber":"109",
    "addr:postcode":"5011",
    "addr:street":"Woodville Rd",
    "iso:country":"AU",
    "sg:address":"109 Woodville Rd",
    "sg:city":"Woodville",
    "sg:classifiers":[
        {
            "category":"Arena",
            "subcategory":"Sports Club",
            "type":"Entertainment"
        }
    ],
    "sg:phone":"+61 405 142 333",
    "sg:postcode":"5011",
    "sg:province":"SA",
    "sg:tags":[
        "defence",
        "supply",
        "self",
        "instruction",
        "martial art"
    ],
    "wof:name":"Golden Eagle Institute of Martial Arts Pty Ltd",
    "wof:placetype":"venue"
},
  "geometry": {"coordinates":[138.541305542,-34.8741493225],"type":"Point"}
}