{
  "type": "Feature",
  "properties": {
    "addr:full":"37 Brisbane Rd Labrador QLD 4215",
    "addr:housenumber":"37",
    "addr:postcode":"4215",
    "addr:street":"Brisbane Rd",
    "iso:country":"AU",
    "sg:address":"37 Brisbane Rd",
    "sg:city":"Labrador",
    "sg:classifiers":[
        {
            "category":"Travel",
            "subcategory":"Hotels & Motels",
            "type":"Entertainment"
        }
    ],
    "sg:phone":"+61 7 5537 9000",
    "sg:postcode":"4215",
    "sg:province":"QLD",
    "wof:name":"Sunburst Motel",
    "wof:placetype":"venue"
},
  "geometry": {"coordinates":[153.4034729,-27.9360561371],"type":"Point"}
}