{
  "type": "Feature",
  "properties": {
    "addr:full":"2 Tunks St Waverton NSW 2060",
    "addr:housenumber":"2",
    "addr:postcode":"2060",
    "addr:street":"Tunks St",
    "iso:country":"AU",
    "sg:address":"2 Tunks St",
    "sg:city":"Waverton",
    "sg:classifiers":[
        {
            "category":"Professional",
            "subcategory":"Employment Agencies",
            "type":"Services"
        }
    ],
    "sg:phone":"+61 414 587 798",
    "sg:postcode":"2060",
    "sg:province":"NSW",
    "sg:tags":[
        "entertainer",
        "agent"
    ],
    "wof:name":"Fab Face Painting",
    "wof:placetype":"venue"
},
  "geometry": {"coordinates":[151.19563293499999,-33.8373184204],"type":"Point"}
}