{
  "type": "Feature",
  "properties": {
    "addr:full":"Beach Drv Fraser Island QLD 4650",
    "addr:postcode":"4650",
    "addr:street":"Beach Drv Fraser",
    "iso:country":"AU",
    "sg:address":"Beach Drv",
    "sg:city":"Fraser Island",
    "sg:classifiers":[
        {
            "category":"Retail",
            "subcategory":"Auto Rental",
            "type":"Services"
        }
    ],
    "sg:phone":"+61 7 4125 4499",
    "sg:postcode":"4650",
    "sg:province":"QLD",
    "sg:tags":[
        "car",
        "hire",
        "minibus"
    ],
    "wof:name":"Beach 4WD Hire",
    "wof:placetype":"venue"
},
  "geometry": {"coordinates":[152.64482100000001,-25.631109],"type":"Point"}
}