{
  "type": "Feature",
  "properties": {
    "addr:full":"Shop 12 Town Square, Bussell Hwy Margaret River WA 6285",
    "addr:housenumber":"shop 12",
    "addr:postcode":"6285",
    "addr:street":"Town Square Bussell Hwy",
    "iso:country":"AU",
    "sg:address":"Shop 12 Town Square, Bussell Hwy",
    "sg:city":"Margaret River",
    "sg:classifiers":[
        {
            "category":"Fast Food",
            "type":"Food & Drink"
        }
    ],
    "sg:phone":"+61 8 9757 2695",
    "sg:postcode":"6285",
    "sg:province":"WA",
    "sg:tags":[
        "away",
        "take"
    ],
    "wof:name":"Chooks Fresh and Tasty",
    "wof:placetype":"venue"
},
  "geometry": {"coordinates":[115.07350921600001,-33.9533653259],"type":"Point"}
}