{
  "type": "Feature",
  "properties": {
    "addr:full":"43 Loftus St Moonah West TAS 7009",
    "addr:housenumber":"43",
    "addr:postcode":"7009",
    "addr:street":"Loftus St",
    "iso:country":"AU",
    "sg:address":"43 Loftus St",
    "sg:city":"Moonah West",
    "sg:classifiers":[
        {
            "category":"Professional",
            "subcategory":"Computer Services",
            "type":"Services"
        }
    ],
    "sg:phone":"+61 417 306 623",
    "sg:postcode":"7009",
    "sg:province":"TAS",
    "sg:tags":[
        "package",
        "software"
    ],
    "wof:name":"Spartan Systems",
    "wof:placetype":"venue"
},
  "geometry": {"coordinates":[147.27117919899999,-42.8516426086],"type":"Point"}
}