{
  "type": "Feature",
  "properties": {
    "addr:full":"86 Murray St Hobart TAS 7000",
    "addr:housenumber":"86",
    "addr:postcode":"7000",
    "addr:street":"Murray St",
    "iso:country":"AU",
    "sg:address":"86 Murray St",
    "sg:city":"Hobart",
    "sg:classifiers":[
        {
            "category":"Health Services",
            "subcategory":"Health Practitioner",
            "type":"Services"
        }
    ],
    "sg:phone":"+61 3 6234 5585",
    "sg:postcode":"7000",
    "sg:province":"TAS",
    "sg:tags":[
        "audiologists"
    ],
    "wof:name":"Audio Clinic Tasmania",
    "wof:placetype":"venue"
},
  "geometry": {"coordinates":[147.32612609899999,-42.8829994202],"type":"Point"}
}