{
  "type": "Feature",
  "properties": {
    "addr:full":"21 Terracolta Drv Blackburn VIC 3130",
    "addr:housenumber":"21",
    "addr:postcode":"3130",
    "addr:street":"Terracolta Drv",
    "iso:country":"AU",
    "sg:address":"21 Terracolta Drv",
    "sg:city":"Blackburn",
    "sg:classifiers":[
        {
            "category":"Social Services",
            "type":"Services"
        }
    ],
    "sg:phone":"+61 3 8878 9420",
    "sg:postcode":"3130",
    "sg:province":"VIC",
    "sg:tags":[
        "disabled",
        "person",
        "equipment"
    ],
    "wof:name":"Mobility One",
    "wof:placetype":"venue"
},
  "geometry": {"coordinates":[145.16291809099999,-37.8208198547],"type":"Point"}
}