{
  "type": "Feature",
  "properties": {
    "addr:full":"317 Abotts Rd Dandenong South VIC 3175",
    "addr:housenumber":"317",
    "addr:postcode":"3175",
    "addr:street":"Abotts Rd",
    "iso:country":"AU",
    "sg:address":"317 Abotts Rd",
    "sg:city":"Dandenong South",
    "sg:classifiers":[
        {
            "category":"Manufacturing",
            "subcategory":"Tools & Machinery",
            "type":"Manufacturing & Wholesale Goods"
        }
    ],
    "sg:phone":"+61 3 8791 9300",
    "sg:postcode":"3175",
    "sg:province":"VIC",
    "wof:name":"Cyclone Industries Pty Ltd",
    "wof:placetype":"venue"
},
  "geometry": {"coordinates":[145.24276733400001,-38.0352249146],"type":"Point"}
}