{
  "type": "Feature",
  "properties": {
    "addr:full":"25 Palmerston Ave Bronte NSW 2024",
    "addr:housenumber":"25",
    "addr:postcode":"2024",
    "addr:street":"Palmerston Ave",
    "iso:country":"AU",
    "sg:address":"25 Palmerston Ave",
    "sg:city":"Bronte",
    "sg:classifiers":[
        {
            "category":"Airport",
            "subcategory":"International",
            "type":"Transportation"
        }
    ],
    "sg:phone":"+61 408 237 032",
    "sg:postcode":"2024",
    "sg:province":"NSW",
    "sg:tags":[
        "diving",
        "commercial"
    ],
    "wof:name":"A A Marine Pty Ltd",
    "wof:placetype":"venue"
},
  "geometry": {"coordinates":[151.26104736299999,-33.9008407593],"type":"Point"}
}