{
  "type": "Feature",
  "properties": {
    "iso:country":"AU",
    "sg:address":"1 Martin Drv",
    "sg:city":"Tomago",
    "sg:classifiers":[
        {
            "category":"Building & Trades",
            "subcategory":"Construction",
            "type":"Services"
        }
    ],
    "sg:phone":"+61 2 4964 8400",
    "sg:postcode":"2322",
    "sg:province":"NSW",
    "sg:tags":[
        "contractor"
    ],
    "sg:website":"http://www.freedomhomes.com.au",
    "wof:name":"Freedom Homes",
    "wof:placetype":"venue"
},
  "geometry": {"coordinates":[151.70489501899999,-32.820980072],"type":"Point"}
}