{
  "type": "Feature",
  "properties": {
    "addr:full":"Princes Hwy Noble Park VIC 3174",
    "addr:postcode":"3174",
    "addr:street":"Princes Hwy",
    "iso:country":"AU",
    "sg:address":"Princes Hwy",
    "sg:city":"Noble Park",
    "sg:classifiers":[
        {
            "category":"Building & Trades",
            "subcategory":"Plumbing",
            "type":"Services"
        }
    ],
    "sg:phone":"+61 3 9547 1171",
    "sg:postcode":"3174",
    "sg:province":"VIC",
    "sg:tags":[
        "plumber",
        "gasfitters"
    ],
    "wof:name":"Plumbcare",
    "wof:placetype":"venue"
},
  "geometry": {"coordinates":[145.19256591800001,-37.9655914307],"type":"Point"}
}