{
  "type": "Feature",
  "properties": {
    "addr:full":"Lot 1 Murrays Rd Woodstock QLD 4816",
    "addr:postcode":"4816",
    "addr:street":"Murrays Rd",
    "iso:country":"AU",
    "sg:address":"Lot 1 Murrays Rd",
    "sg:city":"Woodstock",
    "sg:classifiers":[
        {
            "category":"Farming",
            "subcategory":"Livestock Farm",
            "type":"Manufacturing & Wholesale Goods"
        }
    ],
    "sg:phone":"+61 7 4778 8871",
    "sg:postcode":"4816",
    "sg:province":"QLD",
    "sg:tags":[
        "breeder",
        "horse",
        "stud"
    ],
    "wof:name":"HRH Arabians",
    "wof:placetype":"venue"
},
  "geometry": {"coordinates":[146.83656300000001,-19.60158],"type":"Point"}
}