{
  "type": "Feature",
  "properties": {
    "addr:full":"51 Byron Pl Adelaide SA 5000",
    "addr:housenumber":"51",
    "addr:postcode":"5000",
    "addr:street":"Byron Pl",
    "iso:country":"AU",
    "sg:address":"51 Byron Pl",
    "sg:city":"Adelaide",
    "sg:classifiers":[
        {
            "category":"Professional",
            "subcategory":"Engineering",
            "type":"Services"
        }
    ],
    "sg:phone":"+61 8 8231 5966",
    "sg:postcode":"5000",
    "sg:province":"SA",
    "sg:tags":[
        "electronic",
        "engineer"
    ],
    "wof:name":"eLabtronics",
    "wof:placetype":"venue"
},
  "geometry": {"coordinates":[138.591796875,-34.9284133911],"type":"Point"}
}