{
  "type": "Feature",
  "properties": {
    "iso:country":"AU",
    "sg:address":"78 Delhi St",
    "sg:city":"Lidcombe",
    "sg:classifiers":[
        {
            "category":"Building & Trades",
            "subcategory":"Construction",
            "type":"Services"
        }
    ],
    "sg:phone":"+61 408 977 510",
    "sg:postcode":"2141",
    "sg:province":"NSW",
    "sg:tags":[
        "fencing",
        "contractor"
    ],
    "wof:name":"Cuthbert Fencing",
    "wof:placetype":"venue"
},
  "geometry": {"coordinates":[151.05241394000001,-33.85496521],"type":"Point"}
}