{
  "type": "Feature",
  "properties": {
    "iso:country":"AU",
    "sg:address":"159 Swallow Drv",
    "sg:city":"Erskine Park",
    "sg:classifiers":[
        {
            "category":"Professional",
            "subcategory":"Detective & Security Services",
            "type":"Services"
        }
    ],
    "sg:phone":"+61 2 9670 5895",
    "sg:postcode":"2759",
    "sg:province":"NSW",
    "sg:tags":[
        "guard",
        "patrol"
    ],
    "wof:name":"Galbraith Q",
    "wof:placetype":"venue"
},
  "geometry": {"coordinates":[150.80775451700001,-33.8051109314],"type":"Point"}
}