{
  "type": "Feature",
  "properties": {
    "addr:full":"Unit 3/ 54 Fairford Rd Padstow NSW 2211",
    "addr:housenumber":"54",
    "addr:postcode":"2211",
    "addr:street":"Fairford Rd",
    "iso:country":"AU",
    "sg:address":"Unit 3/ 54 Fairford Rd",
    "sg:city":"Padstow",
    "sg:classifiers":[
        {
            "category":"Professional",
            "type":"Services"
        }
    ],
    "sg:phone":"+61 2 9708 3090",
    "sg:postcode":"2211",
    "sg:province":"NSW",
    "sg:tags":[
        "transport"
    ],
    "wof:name":"P F S Transport & Installation",
    "wof:placetype":"venue"
},
  "geometry": {"coordinates":[151.036316,-33.937958],"type":"Point"}
}