{
  "type": "Feature",
  "properties": {
    "addr:full":"133 Curragundi Rd Jindalee QLD 4074",
    "addr:housenumber":"133",
    "addr:postcode":"4074",
    "addr:street":"Curragundi Rd",
    "iso:country":"AU",
    "sg:address":"133 Curragundi Rd",
    "sg:city":"Jindalee",
    "sg:classifiers":[
        {
            "category":"Manufacturing",
            "subcategory":"Tools & Machinery",
            "type":"Manufacturing & Wholesale Goods"
        }
    ],
    "sg:phone":"+61 7 3279 2050",
    "sg:postcode":"4074",
    "sg:province":"QLD",
    "sg:tags":[
        "earth",
        "excavating",
        "moving",
        "equipment"
    ],
    "wof:name":"Machinery Consulting Services",
    "wof:placetype":"venue"
},
  "geometry": {"coordinates":[152.93122863799999,-27.5326366425],"type":"Point"}
}