{
  "type": "Feature",
  "properties": {
    "iso:country":"AU",
    "sg:address":"36 Bertoli St",
    "sg:city":"Boort",
    "sg:classifiers":[
        {
            "category":"Autos & Motor Vehicles",
            "subcategory":"Auto Supplies",
            "type":"Retail Goods"
        }
    ],
    "sg:phone":"+61 3 5455 2203",
    "sg:postcode":"3537",
    "sg:province":"VIC",
    "sg:tags":[
        "tyre"
    ],
    "wof:name":"Boort Tyre Service",
    "wof:placetype":"venue"
},
  "geometry": {"coordinates":[143.722977,-36.117134],"type":"Point"}
}