{
  "type": "Feature",
  "properties": {
    "iso:country":"AU",
    "sg:address":"PO Box 3003",
    "sg:city":"Umina",
    "sg:classifiers":[
        {
            "category":"Education",
            "subcategory":"School",
            "type":"Public Place"
        }
    ],
    "sg:phone":"+61 412 488 800",
    "sg:postcode":"2257",
    "sg:province":"NSW",
    "sg:tags":[
        "correspondence"
    ],
    "wof:name":"Soul Cottage International Correspondence School of Thinking Higher by Robin Folklores",
    "wof:placetype":"venue"
},
  "geometry": {"coordinates":[151.36076355,-33.5181312561],"type":"Point"}
}