{
  "type": "Feature",
  "properties": {
    "addr:full":"33 Mustang Rd Champion Lakes WA 6111",
    "addr:housenumber":"33",
    "addr:postcode":"6111",
    "addr:street":"Mustang Rd",
    "iso:country":"AU",
    "sg:address":"33 Mustang Rd",
    "sg:city":"Champion Lakes",
    "sg:classifiers":[
        {
            "category":"Home & Garden",
            "subcategory":"Building Materials",
            "type":"Retail Goods"
        }
    ],
    "sg:phone":"+61 438 584 344",
    "sg:postcode":"6111",
    "sg:province":"WA",
    "sg:tags":[
        "gate"
    ],
    "wof:name":"Gates",
    "wof:placetype":"venue"
},
  "geometry": {"coordinates":[115.978942871,-32.1238441467],"type":"Point"}
}