{
  "type": "Feature",
  "properties": {
    "addr:full":"54 Swan Rd Edensor Park NSW 2176",
    "addr:housenumber":"54",
    "addr:postcode":"2176",
    "addr:street":"Swan Rd",
    "iso:country":"AU",
    "sg:address":"54 Swan Rd",
    "sg:city":"Edensor Park",
    "sg:classifiers":[
        {
            "category":"Personal",
            "subcategory":"Beauty Salon",
            "type":"Services"
        }
    ],
    "sg:phone":"+61 2 9823 5940",
    "sg:postcode":"2176",
    "sg:province":"NSW",
    "wof:name":"Top Coat Nail Studio The",
    "wof:placetype":"venue"
},
  "geometry": {"coordinates":[150.87696838400001,-33.8803215027],"type":"Point"}
}