{
  "type": "Feature",
  "properties": {
    "iso:country":"AU",
    "sg:address":"176 High St",
    "sg:city":"Preston",
    "sg:classifiers":[
        {
            "category":"Professional",
            "subcategory":"Employment Agencies",
            "type":"Services"
        }
    ],
    "sg:phone":"+61 3 9416 8877",
    "sg:postcode":"3072",
    "sg:province":"VIC",
    "wof:name":"Kestrel Employment Services",
    "wof:placetype":"venue"
},
  "geometry": {"coordinates":[145.00296020499999,-37.7456130981],"type":"Point"}
}