{
  "type": "Feature",
  "properties": {
    "addr:full":"102 Malvern Park Rd Denison VIC 3858",
    "addr:housenumber":"102",
    "addr:postcode":"3858",
    "addr:street":"Malvern Park Rd",
    "iso:country":"AU",
    "sg:address":"102 Malvern Park Rd",
    "sg:city":"Denison",
    "sg:classifiers":[
        {
            "category":"Farming",
            "subcategory":"Livestock Farm",
            "type":"Manufacturing & Wholesale Goods"
        }
    ],
    "sg:phone":"+61 427 514 248",
    "sg:postcode":"3858",
    "sg:province":"VIC",
    "sg:tags":[
        "buyer"
    ],
    "wof:name":"B & A Watson (Vic) Pty Ltd",
    "wof:placetype":"venue"
},
  "geometry": {"coordinates":[146.80111694300001,-38.0326271057],"type":"Point"}
}