{
  "type": "Feature",
  "properties": {
    "iso:country":"AU",
    "sg:address":"Lvl 10, 380 Queen St",
    "sg:city":"Brisbane",
    "sg:classifiers":[
        {
            "category":"Airline",
            "type":"Transportation"
        }
    ],
    "sg:phone":"+61 1300 651 960",
    "sg:postcode":"4000",
    "sg:province":"QLD",
    "sg:tags":[
        "agent"
    ],
    "wof:name":"Thai Airways International Ltd.",
    "wof:placetype":"venue"
},
  "geometry": {"coordinates":[153.03007507300001,-27.4657096863],"type":"Point"}
}