{
  "type": "Feature",
  "properties": {
    "addr:full":"122 Melrose St Mt Pleasant SA 5235",
    "addr:housenumber":"122",
    "addr:postcode":"5235",
    "addr:street":"Melrose St",
    "iso:country":"AU",
    "sg:address":"122 Melrose St",
    "sg:city":"Mt Pleasant",
    "sg:classifiers":[
        {
            "category":"Wholesale",
            "subcategory":"Machinery & Supplies",
            "type":"Manufacturing & Wholesale Goods"
        }
    ],
    "sg:phone":"+61 8 8568 2266",
    "sg:postcode":"5235",
    "sg:province":"SA",
    "sg:tags":[
        "agricultural"
    ],
    "wof:name":"Lees Spot On Motorcycles",
    "wof:placetype":"venue"
},
  "geometry": {"coordinates":[139.05052185100001,-34.7737197876],"type":"Point"}
}