{
  "type": "Feature",
  "properties": {
    "addr:full":"6/ 124 Goelvin Drv Bribie Island QLD 4507",
    "addr:housenumber":"/ 124",
    "addr:postcode":"4507",
    "addr:street":"Goelvin Drv",
    "iso:country":"AU",
    "sg:address":"6/ 124 Goelvin Drv",
    "sg:city":"Bribie Island",
    "sg:classifiers":[
        {
            "category":"Building & Trades",
            "subcategory":"Construction",
            "type":"Services"
        }
    ],
    "sg:phone":"+61 1300 130 886",
    "sg:postcode":"4507",
    "sg:province":"QLD",
    "sg:tags":[
        "fencing",
        "contractor"
    ],
    "wof:name":"Angel Fencing",
    "wof:placetype":"venue"
},
  "geometry": {"coordinates":[153.14137268100001,-26.9570903778],"type":"Point"}
}