{
  "type": "Feature",
  "properties": {
    "iso:country":"AU",
    "sg:address":"65 Schulze Rd",
    "sg:city":"Athelstone",
    "sg:classifiers":[
        {
            "category":"Home & Garden",
            "subcategory":"Carpets & Floor Coverings",
            "type":"Retail Goods"
        }
    ],
    "sg:phone":"+61 412 299 165",
    "sg:postcode":"5076",
    "sg:province":"SA",
    "sg:tags":[
        "tile",
        "wall",
        "layer"
    ],
    "wof:name":"Cento Tiling",
    "wof:placetype":"venue"
},
  "geometry": {"coordinates":[138.694259644,-34.8686523438],"type":"Point"}
}