{
  "type": "Feature",
  "properties": {
    "iso:country":"AU",
    "sg:address":"U1/ 24 Crompton Rd",
    "sg:city":"Rockingham",
    "sg:classifiers":[
        {
            "category":"Utilities",
            "subcategory":"Electric",
            "type":"Services"
        }
    ],
    "sg:phone":"+61 8 9592 6045",
    "sg:postcode":"6168",
    "sg:province":"WA",
    "sg:tags":[
        "electrical",
        "contractor"
    ],
    "wof:name":"KRE Electrical",
    "wof:placetype":"venue"
},
  "geometry": {"coordinates":[115.767052,-32.274837],"type":"Point"}
}