{
  "type": "Feature",
  "properties": {
    "iso:country":"AU",
    "sg:address":"80- 82 Bell St",
    "sg:city":"Heidelberg Heights",
    "sg:classifiers":[
        {
            "category":"Communications",
            "type":"Services"
        }
    ],
    "sg:phone":"+61 3 9457 6422",
    "sg:postcode":"3081",
    "sg:province":"VIC",
    "sg:tags":[
        "equipment",
        "radio"
    ],
    "wof:name":"Mobile Communication Systems Pty Ltd",
    "wof:placetype":"venue"
},
  "geometry": {"coordinates":[145.05308532699999,-37.7536582947],"type":"Point"}
}