{
  "type": "Feature",
  "properties": {
    "iso:country":"AU",
    "sg:address":"170 Boundary Rd",
    "sg:city":"Geelong East",
    "sg:classifiers":[
        {
            "category":"Manufacturing",
            "subcategory":"Food",
            "type":"Manufacturing & Wholesale Goods"
        }
    ],
    "sg:phone":"+61 3 5248 3328",
    "sg:postcode":"3219",
    "sg:province":"VIC",
    "sg:tags":[
        "function",
        "catering"
    ],
    "wof:name":"Boundary Rd Chicken & Carvery",
    "wof:placetype":"venue"
},
  "geometry": {"coordinates":[144.38360595699999,-38.1734962463],"type":"Point"}
}