{
  "type": "Feature",
  "properties": {
    "addr:full":"812- 820 Parramatta Rd Lewisham NSW 2049",
    "addr:housenumber":"820",
    "addr:postcode":"2049",
    "addr:street":"Parramatta Rd",
    "iso:country":"AU",
    "sg:address":"812- 820 Parramatta Rd",
    "sg:city":"Lewisham",
    "sg:classifiers":[
        {
            "category":"Shopping",
            "subcategory":"Antiques",
            "type":"Retail Goods"
        }
    ],
    "sg:phone":"+61 2 9560 2211",
    "sg:postcode":"2049",
    "sg:province":"NSW",
    "sg:tags":[
        "restoration",
        "reproduction"
    ],
    "wof:name":"Flinders Antique Centre",
    "wof:placetype":"venue"
},
  "geometry": {"coordinates":[151.145477,-33.890015],"type":"Point"}
}