{
  "type": "Feature",
  "properties": {
    "iso:country":"AU",
    "sg:address":"Lot 2864 Anderson Rd",
    "sg:city":"Karratha",
    "sg:classifiers":[
        {
            "category":"Building & Trades",
            "subcategory":"Construction",
            "type":"Services"
        }
    ],
    "sg:phone":"+61 8 9144 4462",
    "sg:postcode":"6714",
    "sg:province":"WA",
    "sg:tags":[
        "insulation",
        "contractor"
    ],
    "wof:name":"Bains Harding Industries Pty Ltd",
    "wof:placetype":"venue"
},
  "geometry": {"coordinates":[116.872276306,-20.7709712982],"type":"Point"}
}