{
  "type": "Feature",
  "properties": {
    "iso:country":"AU",
    "sg:address":"15 Malwood Pl",
    "sg:city":"Forcett",
    "sg:classifiers":[
        {
            "category":"Shopping",
            "subcategory":"Pets & Pet Supplies",
            "type":"Retail Goods"
        }
    ],
    "sg:phone":"+61 1300 889 035",
    "sg:postcode":"7173",
    "sg:province":"TAS",
    "sg:tags":[
        "food"
    ],
    "wof:name":"Mobile Animal Care (MAC)",
    "wof:placetype":"venue"
},
  "geometry": {"coordinates":[147.62011718799999,-42.8256492615],"type":"Point"}
}