{
  "type": "Feature",
  "properties": {
    "addr:full":"99 Collie St Albany WA 6330",
    "addr:housenumber":"99",
    "addr:postcode":"6330",
    "addr:street":"Collie St",
    "iso:country":"AU",
    "sg:address":"99 Collie St",
    "sg:city":"Albany",
    "sg:classifiers":[
        {
            "category":"Education",
            "subcategory":"Kindergarten",
            "type":"Public Place"
        }
    ],
    "sg:phone":"+61 8 9841 9332",
    "sg:postcode":"6330",
    "sg:province":"WA",
    "sg:tags":[
        "pre-schools"
    ],
    "wof:name":"Albany Regional Day Care Centre",
    "wof:placetype":"venue"
},
  "geometry": {"coordinates":[117.881797791,-35.0238113403],"type":"Point"}
}