{
  "type": "Feature",
  "properties": {
    "addr:full":"13 Kirkham Rd West Keysborough VIC 3173",
    "addr:housenumber":"13",
    "addr:postcode":"3173",
    "addr:street":"Kirkham Rd West",
    "iso:country":"AU",
    "sg:address":"13 Kirkham Rd West",
    "sg:city":"Keysborough",
    "sg:classifiers":[
        {
            "category":"Manufacturing",
            "subcategory":"Apparel",
            "type":"Manufacturing & Wholesale Goods"
        }
    ],
    "sg:phone":"+61 3 9769 1699",
    "sg:postcode":"3173",
    "sg:province":"VIC",
    "sg:tags":[
        "wholesaler",
        "mfrs",
        "footwear"
    ],
    "wof:name":"Cogs Marketing Services Pty Ltd",
    "wof:placetype":"venue"
},
  "geometry": {"coordinates":[145.182571411,-37.9953651428],"type":"Point"}
}