{
  "type": "Feature",
  "properties": {
    "addr:full":"14 Vulcan Rd Canning Vale WA 6155",
    "addr:housenumber":"14",
    "addr:postcode":"6155",
    "addr:street":"Vulcan Rd",
    "iso:country":"AU",
    "sg:address":"14 Vulcan Rd",
    "sg:city":"Canning Vale",
    "sg:classifiers":[
        {
            "category":"Home & Garden",
            "subcategory":"Carpets & Floor Coverings",
            "type":"Retail Goods"
        }
    ],
    "sg:phone":"+61 8 9455 1658",
    "sg:postcode":"6155",
    "sg:province":"WA",
    "sg:tags":[
        "material",
        "waterproofing"
    ],
    "wof:name":"Allflow Durotech",
    "wof:placetype":"venue"
},
  "geometry": {"coordinates":[115.92836800000001,-32.057804],"type":"Point"}
}