{
  "type": "Feature",
  "properties": {
    "addr:full":"501 Peel St Tamworth NSW 2340",
    "addr:housenumber":"501",
    "addr:postcode":"2340",
    "addr:street":"Peel St",
    "iso:country":"AU",
    "sg:address":"501 Peel St",
    "sg:city":"Tamworth",
    "sg:classifiers":[
        {
            "category":"Autos & Motor Vehicles",
            "subcategory":"Automobile Sales",
            "type":"Retail Goods"
        }
    ],
    "sg:phone":"+61 2 6766 1466",
    "sg:postcode":"2340",
    "sg:province":"NSW",
    "sg:tags":[
        "car",
        "new"
    ],
    "wof:name":"Fossey J. T. Pty. Ltd.",
    "wof:placetype":"venue"
},
  "geometry": {"coordinates":[150.93528747600001,-31.0963535309],"type":"Point"}
}