{
  "type": "Feature",
  "properties": {
    "addr:full":"PO Box 164 Albert Park VIC 3206",
    "addr:postcode":"3206",
    "iso:country":"AU",
    "sg:address":"PO Box 164",
    "sg:city":"Albert Park",
    "sg:classifiers":[
        {
            "category":"Professional",
            "subcategory":"Art Services",
            "type":"Services"
        }
    ],
    "sg:phone":"+61 418 567 156",
    "sg:postcode":"3206",
    "sg:province":"VIC",
    "sg:tags":[
        "decorator",
        "painter"
    ],
    "wof:name":"Colorshade Painters",
    "wof:placetype":"venue"
},
  "geometry": {"coordinates":[144.951111,-37.844269],"type":"Point"}
}