{
  "type": "Feature",
  "properties": {
    "addr:full":"Shp11/ 225 Victoria Rd Gladesville NSW 2111",
    "addr:housenumber":"225",
    "addr:postcode":"2111",
    "addr:street":"Victoria Rd",
    "iso:country":"AU",
    "sg:address":"Shp11/ 225 Victoria Rd",
    "sg:city":"Gladesville",
    "sg:classifiers":[
        {
            "category":"Health Services",
            "subcategory":"Health Practitioner",
            "type":"Services"
        }
    ],
    "sg:phone":"+61 2 9879 0889",
    "sg:postcode":"2111",
    "sg:province":"NSW",
    "sg:tags":[
        "acupuncture"
    ],
    "wof:name":"Zy Traditional Chiness Therapy",
    "wof:placetype":"venue"
},
  "geometry": {"coordinates":[151.127075195,-33.831905365],"type":"Point"}
}