{
  "type": "Feature",
  "properties": {
    "addr:full":"10 Karawatha St Buderim QLD 4556",
    "addr:housenumber":"10",
    "addr:postcode":"4556",
    "addr:street":"Karawatha St",
    "iso:country":"AU",
    "sg:address":"10 Karawatha St",
    "sg:city":"Buderim",
    "sg:classifiers":[
        {
            "category":"Real Estate",
            "subcategory":"Architect",
            "type":"Services"
        }
    ],
    "sg:phone":"+61 428 727 625",
    "sg:postcode":"4556",
    "sg:province":"QLD",
    "wof:name":"Kearney Michael",
    "wof:placetype":"venue"
},
  "geometry": {"coordinates":[153.0756073,-26.6927623749],"type":"Point"}
}