{
  "type": "Feature",
  "properties": {
    "addr:full":"131 Kelly St Scone NSW 2337",
    "addr:housenumber":"131",
    "addr:postcode":"2337",
    "addr:street":"Kelly St",
    "iso:country":"AU",
    "sg:address":"131 Kelly St",
    "sg:city":"Scone",
    "sg:classifiers":[
        {
            "category":"Professional",
            "subcategory":"Computer Services",
            "type":"Services"
        }
    ],
    "sg:phone":"+61 2 6545 2202",
    "sg:postcode":"2337",
    "sg:province":"NSW",
    "sg:tags":[
        "repairs",
        "upgrade",
        "equipment"
    ],
    "wof:name":"Racar Computers",
    "wof:placetype":"venue"
},
  "geometry": {"coordinates":[150.86761474599999,-32.0490875244],"type":"Point"}
}