{
  "type": "Feature",
  "properties": {
    "addr:full":"155 High St Thomastown VIC 3074",
    "addr:housenumber":"155",
    "addr:postcode":"3074",
    "addr:street":"High St",
    "iso:country":"AU",
    "sg:address":"155 High St",
    "sg:city":"Thomastown",
    "sg:classifiers":[
        {
            "category":"Professional",
            "subcategory":"Detective & Security Services",
            "type":"Services"
        }
    ],
    "sg:phone":"+61 3 9464 2141",
    "sg:postcode":"3074",
    "sg:province":"VIC",
    "sg:tags":[
        "investigator"
    ],
    "wof:name":"Cheaters Investigation Services",
    "wof:placetype":"venue"
},
  "geometry": {"coordinates":[145.01332092300001,-37.6821975708],"type":"Point"}
}