{
  "type": "Feature",
  "properties": {
    "addr:full":"60 Walsh St Edge Hill QLD 4870",
    "addr:housenumber":"60",
    "addr:postcode":"4870",
    "addr:street":"Walsh St",
    "iso:country":"AU",
    "sg:address":"60 Walsh St",
    "sg:city":"Edge Hill",
    "sg:classifiers":[
        {
            "category":"Retail",
            "subcategory":"Auto Rental",
            "type":"Services"
        }
    ],
    "sg:phone":"+61 407 163 966",
    "sg:postcode":"4870",
    "sg:province":"QLD",
    "sg:tags":[
        "chauffeur",
        "car",
        "hire",
        "driven",
        "limousine"
    ],
    "wof:name":"Tarago Transfers",
    "wof:placetype":"venue"
},
  "geometry": {"coordinates":[145.743774414,-16.897403717],"type":"Point"}
}