{
  "type": "Feature",
  "properties": {
    "addr:full":"U5/ 4-6-6 Wheeler St Berwick VIC 3806",
    "addr:housenumber":"4-6-6",
    "addr:postcode":"3806",
    "addr:street":"U5 /;Wheeler St",
    "iso:country":"AU",
    "sg:address":"U5/ 4-6-6 Wheeler St",
    "sg:city":"Berwick",
    "sg:classifiers":[
        {
            "category":"Professional",
            "subcategory":"Accounting & Tax Preparation",
            "type":"Services"
        }
    ],
    "sg:phone":"+61 3 9769 4811",
    "sg:postcode":"3806",
    "sg:province":"VIC",
    "sg:tags":[
        "accountant",
        "auditor"
    ],
    "wof:name":"The Trustee For Jsp Partners",
    "wof:placetype":"venue"
},
  "geometry": {"coordinates":[145.34823608400001,-38.0303535461],"type":"Point"}
}