{
  "type": "Feature",
  "properties": {
    "iso:country":"AU",
    "sg:address":"Crosse's Rd",
    "sg:city":"Barnawartha",
    "sg:classifiers":[
        {
            "category":"Building & Trades",
            "subcategory":"Construction",
            "type":"Services"
        }
    ],
    "sg:phone":"+61 409 412 558",
    "sg:postcode":"3688",
    "sg:province":"VIC",
    "sg:tags":[
        "contractor"
    ],
    "wof:name":"Crosse R J",
    "wof:placetype":"venue"
},
  "geometry": {"coordinates":[146.68373107900001,-36.1139373779],"type":"Point"}
}