{
  "type": "Feature",
  "properties": {
    "addr:full":"904 Victoria Rd West Ryde NSW 2114",
    "addr:housenumber":"904",
    "addr:postcode":"2114",
    "addr:street":"Victoria Rd",
    "iso:country":"AU",
    "sg:address":"904 Victoria Rd",
    "sg:city":"West Ryde",
    "sg:classifiers":[
        {
            "category":"Home & Garden",
            "subcategory":"Household Appliances",
            "type":"Retail Goods"
        }
    ],
    "sg:phone":"+61 2 9807 8900",
    "sg:postcode":"2114",
    "sg:province":"NSW",
    "sg:tags":[
        "chemical",
        "equipment",
        "steam",
        "cleaning",
        "pressure"
    ],
    "wof:name":"H2O Engineering Services",
    "wof:placetype":"venue"
},
  "geometry": {"coordinates":[151.088058472,-33.8078155518],"type":"Point"}
}