{
  "type": "Feature",
  "properties": {
    "iso:country":"AU",
    "sg:address":"35 Shannon Drv",
    "sg:city":"Woree",
    "sg:classifiers":[
        {
            "category":"Shopping",
            "subcategory":"Crafts & Fabrics",
            "type":"Retail Goods"
        }
    ],
    "sg:phone":"+61 7 4033 1876",
    "sg:postcode":"4868",
    "sg:province":"QLD",
    "sg:tags":[
        "synthetic",
        "canvas",
        "product"
    ],
    "wof:name":"Able Canvas Goods",
    "wof:placetype":"venue"
},
  "geometry": {"coordinates":[145.73666381800001,-16.9627742767],"type":"Point"}
}