{
  "type": "Feature",
  "properties": {
    "addr:full":"98 Augusta Rd Lenah Valley TAS 7008",
    "addr:postcode":"7008",
    "addr:street":"98 Augusta Rd",
    "iso:country":"AU",
    "sg:address":"98 Augusta Rd",
    "sg:city":"Lenah Valley",
    "sg:classifiers":[
        {
            "category":"Government",
            "subcategory":"Post Office",
            "type":"Public Place"
        }
    ],
    "sg:phone":"+61 3 6228 3694",
    "sg:postcode":"7008",
    "sg:province":"TAS",
    "sg:tags":[
        "postal"
    ],
    "wof:name":"Australia Post Offices",
    "wof:placetype":"venue"
},
  "geometry": {"coordinates":[147.297164917,-42.8660202026],"type":"Point"}
}