{
  "type": "Feature",
  "properties": {
    "addr:full":"14 Davington Crt Wantirna VIC 3152",
    "addr:housenumber":"14",
    "addr:postcode":"3152",
    "addr:street":"Davington Crt",
    "iso:country":"AU",
    "sg:address":"14 Davington Crt",
    "sg:city":"Wantirna",
    "sg:classifiers":[
        {
            "category":"Communications",
            "type":"Services"
        }
    ],
    "sg:phone":"+61 3 8801 1266",
    "sg:postcode":"3152",
    "sg:province":"VIC",
    "sg:tags":[
        "public",
        "system",
        "address"
    ],
    "wof:name":"Audio Action",
    "wof:placetype":"venue"
},
  "geometry": {"coordinates":[145.23399352999999,-37.8630065918],"type":"Point"}
}