{
  "type": "Feature",
  "properties": {
    "addr:full":"Tozer St Kempsey NSW 2440",
    "addr:postcode":"2440",
    "addr:street":"Tozer St",
    "iso:country":"AU",
    "sg:address":"Tozer St",
    "sg:city":"Kempsey",
    "sg:classifiers":[
        {
            "category":"Travel",
            "subcategory":"Hotels & Motels",
            "type":"Entertainment"
        }
    ],
    "sg:phone":"+61 2 6562 4310",
    "sg:postcode":"2440",
    "sg:province":"NSW",
    "sg:tags":[
        "accommodation"
    ],
    "wof:name":"West Kempsey Hotel",
    "wof:placetype":"venue"
},
  "geometry": {"coordinates":[152.83017000000001,-31.082232],"type":"Point"}
}