{
  "type": "Feature",
  "properties": {
    "addr:full":"9 Quinta Drv Ballarat VIC 3350",
    "addr:housenumber":"9",
    "addr:postcode":"3350",
    "addr:street":"Quinta Drv",
    "iso:country":"AU",
    "sg:address":"9 Quinta Drv",
    "sg:city":"Ballarat",
    "sg:classifiers":[
        {
            "category":"Professional",
            "subcategory":"Detective & Security Services",
            "type":"Services"
        }
    ],
    "sg:phone":"+61 3 5330 3339",
    "sg:postcode":"3350",
    "sg:province":"VIC",
    "sg:tags":[
        "guard",
        "patrol"
    ],
    "wof:name":"B.S.S. Security",
    "wof:placetype":"venue"
},
  "geometry": {"coordinates":[143.86799600000001,-37.594776],"type":"Point"}
}