{
  "type": "Feature",
  "properties": {
    "addr:full":"Cnr Wellington Rd & Trafalgar St Woolloongabba QLD 4102",
    "addr:postcode":"4102",
    "addr:street":"Cnr Wellington Rd & Trafalgar St",
    "iso:country":"AU",
    "sg:address":"Cnr Wellington Rd & Trafalgar St",
    "sg:city":"Woolloongabba",
    "sg:classifiers":[
        {
            "category":"Shopping",
            "subcategory":"Antiques",
            "type":"Retail Goods"
        }
    ],
    "sg:phone":"+61 7 3891 1990",
    "sg:postcode":"4102",
    "sg:province":"QLD",
    "sg:tags":[
        "restoration",
        "reproduction"
    ],
    "wof:name":"The Attic",
    "wof:placetype":"venue"
},
  "geometry": {"coordinates":[153.039672852,-27.4878387451],"type":"Point"}
}