{
  "type": "Feature",
  "properties": {
    "iso:country":"AU",
    "sg:address":"80 Woodville Park Drv",
    "sg:city":"Hoppers Crossing",
    "sg:classifiers":[
        {
            "category":"Education",
            "subcategory":"Kindergarten",
            "type":"Public Place"
        }
    ],
    "sg:phone":"+61 3 9749 3752",
    "sg:postcode":"3029",
    "sg:province":"VIC",
    "sg:tags":[
        "pre-schools"
    ],
    "wof:name":"Woodville Park Kindergarten",
    "wof:placetype":"venue"
},
  "geometry": {"coordinates":[144.68811,-37.88269],"type":"Point"}
}