{
  "type": "Feature",
  "properties": {
    "iso:country":"AU",
    "sg:address":"PO Box 248",
    "sg:city":"Essendon",
    "sg:classifiers":[
        {
            "category":"Banks & Credit Unions",
            "subcategory":"Bank",
            "type":"Services"
        }
    ],
    "sg:phone":"+61 412 549 141",
    "sg:postcode":"3040",
    "sg:province":"VIC",
    "sg:tags":[
        "broker",
        "mortgage"
    ],
    "wof:name":"Aaramis Finance",
    "wof:placetype":"venue"
},
  "geometry": {"coordinates":[144.90951538100001,-37.7515411377],"type":"Point"}
}