{
  "type": "Feature",
  "properties": {
    "iso:country":"AU",
    "sg:address":"3 Drummond Rd",
    "sg:city":"Shepparton",
    "sg:classifiers":[
        {
            "category":"Building & Trades",
            "subcategory":"Cleaning & Sanitation",
            "type":"Services"
        }
    ],
    "sg:phone":"+61 3 5831 8388",
    "sg:postcode":"3630",
    "sg:province":"VIC",
    "sg:tags":[
        "grease",
        "trap"
    ],
    "wof:name":"Veolia Environmental Services",
    "wof:placetype":"venue"
},
  "geometry": {"coordinates":[145.426147461,-36.3663825989],"type":"Point"}
}