{
  "type": "Feature",
  "properties": {
    "iso:country":"AU",
    "sg:address":"2/ 874 Mountain Hwy",
    "sg:city":"Bayswater",
    "sg:classifiers":[
        {
            "category":"Retail",
            "subcategory":"Auto Repair",
            "type":"Services"
        }
    ],
    "sg:phone":"+61 3 8727 6888",
    "sg:postcode":"3153",
    "sg:province":"VIC",
    "sg:tags":[
        "repairer",
        "motor",
        "engineer"
    ],
    "wof:name":"Knox Ford",
    "wof:placetype":"venue"
},
  "geometry": {"coordinates":[145.279693603,-37.8381958008],"type":"Point"}
}