{
  "type": "Feature",
  "properties": {
    "addr:full":"423 Victoria Ave Chatswood NSW 2067",
    "addr:housenumber":"423",
    "addr:postcode":"2067",
    "addr:street":"Victoria Ave",
    "iso:country":"AU",
    "sg:address":"423 Victoria Ave",
    "sg:city":"Chatswood",
    "sg:classifiers":[
        {
            "category":"Shopping",
            "subcategory":"Crafts & Fabrics",
            "type":"Retail Goods"
        }
    ],
    "sg:phone":"+61 2 9415 3570",
    "sg:postcode":"2067",
    "sg:province":"NSW",
    "sg:tags":[
        "silk"
    ],
    "wof:name":"Silk Fantasy",
    "wof:placetype":"venue"
},
  "geometry": {"coordinates":[151.18341064399999,-33.7960395813],"type":"Point"}
}