{
  "type": "Feature",
  "properties": {
    "iso:country":"AU",
    "sg:address":"75- 77 Northern Hwy",
    "sg:city":"Echuca",
    "sg:classifiers":[
        {
            "category":"Retail",
            "subcategory":"Event Space",
            "type":"Services"
        }
    ],
    "sg:phone":"+61 3 5482 3200",
    "sg:postcode":"3564",
    "sg:province":"VIC",
    "sg:tags":[
        "venue",
        "reception",
        "wedding"
    ],
    "wof:name":"Echuca Fountain Motel",
    "wof:placetype":"venue"
},
  "geometry": {"coordinates":[144.73005676299999,-36.146030426],"type":"Point"}
}