{
  "type": "Feature",
  "properties": {
    "iso:country":"AU",
    "sg:address":"Lot 21 John St",
    "sg:city":"Albany",
    "sg:classifiers":[
        {
            "category":"Home & Garden",
            "subcategory":"Building Materials",
            "type":"Retail Goods"
        }
    ],
    "sg:phone":"+61 8 9842 3100",
    "sg:postcode":"6330",
    "sg:province":"WA",
    "sg:tags":[
        "pre-mixed",
        "concrete"
    ],
    "wof:name":"Great Southern Concrete & Sand Supplies",
    "wof:placetype":"venue"
},
  "geometry": {"coordinates":[117.86459350600001,-34.9893112183],"type":"Point"}
}