{
  "type": "Feature",
  "properties": {
    "addr:full":"Suite C/ 224 Church St Richmond VIC 3121",
    "addr:housenumber":"suite;224",
    "addr:postcode":"3121",
    "addr:street":"C /;Church St",
    "iso:country":"AU",
    "sg:address":"Suite C/ 224 Church St",
    "sg:city":"Richmond",
    "sg:classifiers":[
        {
            "category":"Government",
            "subcategory":"Fire Station",
            "type":"Public Place"
        }
    ],
    "sg:phone":"+61 3 9427 8011",
    "sg:postcode":"3121",
    "sg:province":"VIC",
    "sg:tags":[
        "equipment",
        "protection",
        "consultant"
    ],
    "wof:name":"ICS Australia Pty Ltd",
    "wof:placetype":"venue"
},
  "geometry": {"coordinates":[144.99911499000001,-37.8179092407],"type":"Point"}
}