{
  "type": "Feature",
  "properties": {
    "addr:full":"47- 49 Ordish Rd Dandenong South VIC 3175",
    "addr:housenumber":"49",
    "addr:postcode":"3175",
    "addr:street":"Ordish Rd",
    "iso:country":"AU",
    "sg:address":"47- 49 Ordish Rd",
    "sg:city":"Dandenong South",
    "sg:classifiers":[
        {
            "category":"Shopping",
            "subcategory":"Party Supplies",
            "type":"Retail Goods"
        }
    ],
    "sg:phone":"+61 3 9794 0332",
    "sg:postcode":"3175",
    "sg:province":"VIC",
    "sg:tags":[
        "toilet",
        "portable"
    ],
    "wof:name":"Sani Hire Pty Ltd",
    "wof:placetype":"venue"
},
  "geometry": {"coordinates":[145.19303894000001,-38.0186691284],"type":"Point"}
}