{
  "type": "Feature",
  "properties": {
    "addr:full":"43- 47 Forest St Colac VIC 3250",
    "addr:housenumber":"47",
    "addr:postcode":"3250",
    "addr:street":"Forest St",
    "iso:country":"AU",
    "sg:address":"43- 47 Forest St",
    "sg:city":"Colac",
    "sg:classifiers":[
        {
            "category":"Retail",
            "subcategory":"Storage",
            "type":"Services"
        }
    ],
    "sg:phone":"+61 3 5231 2422",
    "sg:postcode":"3250",
    "sg:province":"VIC",
    "wof:name":"Colac Self Storage",
    "wof:placetype":"venue"
},
  "geometry": {"coordinates":[143.60502600000001,-38.344551],"type":"Point"}
}