{
  "type": "Feature",
  "properties": {
    "iso:country":"AU",
    "sg:address":"41 Mooliabeenee Rd",
    "sg:city":"Bindoon",
    "sg:classifiers":[
        {
            "category":"Travel",
            "subcategory":"Hotels & Motels",
            "type":"Entertainment"
        }
    ],
    "sg:phone":"+61 8 9576 2888",
    "sg:postcode":"6502",
    "sg:province":"WA",
    "sg:tags":[
        "pub"
    ],
    "wof:name":"Orchard Glory Farm Resort",
    "wof:placetype":"venue"
},
  "geometry": {"coordinates":[116.079857,-31.341812],"type":"Point"}
}