{
  "type": "Feature",
  "properties": {
    "iso:country":"AU",
    "sg:address":"PO Box 4228",
    "sg:city":"Pitt Town",
    "sg:classifiers":[
        {
            "category":"Manufacturing",
            "subcategory":"Food",
            "type":"Manufacturing & Wholesale Goods"
        }
    ],
    "sg:phone":"+61 418 679 755",
    "sg:postcode":"2756",
    "sg:province":"NSW",
    "sg:tags":[
        "function",
        "catering"
    ],
    "wof:name":"Leemoore Country Catering",
    "wof:placetype":"venue"
},
  "geometry": {"coordinates":[150.861938477,-33.5864486694],"type":"Point"}
}