{
  "type": "Feature",
  "properties": {
    "addr:full":"17 Fairloch Ave Farmborough Heights NSW 2526",
    "addr:housenumber":"17",
    "addr:postcode":"2526",
    "addr:street":"Fairloch Ave",
    "iso:country":"AU",
    "sg:address":"17 Fairloch Ave",
    "sg:city":"Farmborough Heights",
    "sg:classifiers":[
        {
            "category":"Professional",
            "subcategory":"Art Services",
            "type":"Services"
        }
    ],
    "sg:phone":"+61 429 009 461",
    "sg:postcode":"2526",
    "sg:province":"NSW",
    "sg:tags":[
        "decorator",
        "painter"
    ],
    "wof:name":"Adam S Coulson",
    "wof:placetype":"venue"
},
  "geometry": {"coordinates":[150.818481445,-34.4598007202],"type":"Point"}
}