{
  "type": "Feature",
  "properties": {
    "iso:country":"AU",
    "sg:address":"Highland Shopping Centre Target Hill Rd",
    "sg:city":"Greenwith",
    "sg:classifiers":[
        {
            "category":"Food & Beverages",
            "subcategory":"Liquor & Beverages",
            "type":"Retail Goods"
        }
    ],
    "sg:phone":"+61 8 8288 0721",
    "sg:postcode":"5125",
    "sg:province":"SA",
    "sg:tags":[
        "store"
    ],
    "wof:name":"Booze Brothers",
    "wof:placetype":"venue"
},
  "geometry": {"coordinates":[138.714035,-34.772713],"type":"Point"}
}