{
  "type": "Feature",
  "properties": {
    "addr:full":"362 Frankston-Dandenong Rd Seaford VIC 3198",
    "addr:housenumber":"362",
    "addr:postcode":"3198",
    "addr:street":"Frankston-Dandenong Rd",
    "iso:country":"AU",
    "sg:address":"362 Frankston-Dandenong Rd",
    "sg:city":"Seaford",
    "sg:classifiers":[
        {
            "category":"Travel",
            "subcategory":"Hotels & Motels",
            "type":"Entertainment"
        }
    ],
    "sg:phone":"+61 3 9786 5999",
    "sg:postcode":"3198",
    "sg:province":"VIC",
    "sg:tags":[
        "accommodation"
    ],
    "wof:name":"Tavernerner Hotel Group Pty Ltd",
    "wof:placetype":"venue"
},
  "geometry": {"coordinates":[145.15628051799999,-38.1130828857],"type":"Point"}
}