{
  "type": "Feature",
  "properties": {
    "iso:country":"AU",
    "sg:address":"Level 3, ANZ Bank Chambers, 16A Bolton Street",
    "sg:city":"Newcastle",
    "sg:classifiers":[
        {
            "category":"Banks & Credit Unions",
            "subcategory":"Investment Brokerage",
            "type":"Services"
        }
    ],
    "sg:phone":"+61 2 4929 1541",
    "sg:postcode":"2300",
    "sg:province":"NSW",
    "sg:tags":[
        "share",
        "broker",
        "stock"
    ],
    "wof:name":"Tonkin Scorer Menzies",
    "wof:placetype":"venue"
},
  "geometry": {"coordinates":[151.783127,-32.927361],"type":"Point"}
}