{
  "type": "Feature",
  "properties": {
    "addr:full":"350 South Pine Rd Brendale QLD 4500",
    "addr:housenumber":"350",
    "addr:postcode":"4500",
    "addr:street":"South Pine Rd",
    "iso:country":"AU",
    "sg:address":"350 South Pine Rd",
    "sg:city":"Brendale",
    "sg:classifiers":[
        {
            "category":"Home & Garden",
            "subcategory":"Building Materials",
            "type":"Retail Goods"
        }
    ],
    "sg:phone":"+61 7 3881 2444",
    "sg:postcode":"4500",
    "sg:province":"QLD",
    "sg:tags":[
        "fencing"
    ],
    "wof:name":"Pine Rivers Timber & Hardware",
    "wof:placetype":"venue"
},
  "geometry": {"coordinates":[152.98733520499999,-27.3244686127],"type":"Point"}
}