{
  "type": "Feature",
  "properties": {
    "iso:country":"AU",
    "sg:address":"31 Bligh Ave",
    "sg:city":"Casula",
    "sg:classifiers":[
        {
            "category":"Retail",
            "subcategory":"Repair Shop",
            "type":"Services"
        }
    ],
    "sg:phone":"+61 419 257 972",
    "sg:postcode":"2170",
    "sg:province":"NSW",
    "sg:tags":[
        "maintenance",
        "pool",
        "swimming"
    ],
    "wof:name":"Crystal Waters Mobile Pool Service",
    "wof:placetype":"venue"
},
  "geometry": {"coordinates":[150.89097595199999,-33.945022583],"type":"Point"}
}