{
  "type": "Feature",
  "properties": {
    "addr:full":"Cnr Gladstone & Gray Sts Emerald QLD 4720",
    "addr:postcode":"4720",
    "addr:street":"Cnr",
    "iso:country":"AU",
    "sg:address":"Cnr Gladstone & Gray Sts",
    "sg:city":"Emerald",
    "sg:classifiers":[
        {
            "category":"Education",
            "subcategory":"School",
            "type":"Public Place"
        }
    ],
    "sg:phone":"+61 7 4987 4155",
    "sg:postcode":"4720",
    "sg:province":"QLD",
    "sg:tags":[
        "correspondence"
    ],
    "wof:name":"Capricornia School Of Distance Education",
    "wof:placetype":"venue"
},
  "geometry": {"coordinates":[148.15403699999999,-23.530207],"type":"Point"}
}