{
  "type": "Feature",
  "properties": {
    "addr:full":"30 Western Hwy Stawell VIC 3380",
    "addr:housenumber":"30",
    "addr:postcode":"3380",
    "addr:street":"Western Hwy",
    "iso:country":"AU",
    "sg:address":"30 Western Hwy",
    "sg:city":"Stawell",
    "sg:classifiers":[
        {
            "category":"Home & Garden",
            "subcategory":"Furniture",
            "type":"Retail Goods"
        }
    ],
    "sg:phone":"+61 3 5358 5001",
    "sg:postcode":"3380",
    "sg:province":"VIC",
    "sg:tags":[
        "business"
    ],
    "wof:name":"Aspect Commercial Interiors",
    "wof:placetype":"venue"
},
  "geometry": {"coordinates":[142.76565551799999,-37.0643501282],"type":"Point"}
}