{
  "type": "Feature",
  "properties": {
    "iso:country":"AU",
    "sg:address":"622 Main St",
    "sg:city":"Mordialloc",
    "sg:classifiers":[
        {
            "category":"Shopping",
            "subcategory":"Gifts & Souvenirs",
            "type":"Retail Goods"
        }
    ],
    "sg:phone":"+61 3 9587 0512",
    "sg:postcode":"3195",
    "sg:province":"VIC",
    "sg:tags":[
        "print",
        "poster",
        "pictures"
    ],
    "wof:name":"Image Street",
    "wof:placetype":"venue"
},
  "geometry": {"coordinates":[145.08729553200001,-38.0084953308],"type":"Point"}
}