{
  "type": "Feature",
  "properties": {
    "iso:country":"AU",
    "sg:address":"64 Cavan Rd",
    "sg:city":"Dry Creek",
    "sg:classifiers":[
        {
            "category":"Utilities",
            "subcategory":"Sewage",
            "type":"Services"
        }
    ],
    "sg:phone":"+61 13 24 61",
    "sg:postcode":"5094",
    "sg:province":"SA",
    "sg:tags":[
        "electricity",
        "retailer"
    ],
    "wof:name":"Origin Energy",
    "wof:placetype":"venue"
},
  "geometry": {"coordinates":[138.59022522000001,-34.8419151306],"type":"Point"}
}