{
  "type": "Feature",
  "properties": {
    "addr:full":"Cnr Eighth St & Madden Avenue Mildura VIC 3500",
    "addr:postcode":"3500",
    "addr:street":"Cnr Eighth St & Madden Avenue",
    "iso:country":"AU",
    "sg:address":"Cnr Eighth St & Madden Avenue",
    "sg:city":"Mildura",
    "sg:classifiers":[
        {
            "category":"Professional",
            "subcategory":"Accounting & Tax Preparation",
            "type":"Services"
        }
    ],
    "sg:phone":"+61 3 5022 7709",
    "sg:postcode":"3500",
    "sg:province":"VIC",
    "sg:tags":[
        "accountant",
        "auditor"
    ],
    "wof:name":"Hartmann Peter",
    "wof:placetype":"venue"
},
  "geometry": {"coordinates":[142.171386719,-34.1923179626],"type":"Point"}
}