{
  "type": "Feature",
  "properties": {
    "iso:country":"AU",
    "sg:address":"53 Fernhill Rd",
    "sg:city":"Sandringham",
    "sg:classifiers":[
        {
            "category":"Shopping",
            "subcategory":"Discount & Variety Stores",
            "type":"Retail Goods"
        }
    ],
    "sg:phone":"+61 3 9598 7461",
    "sg:postcode":"3191",
    "sg:province":"VIC",
    "sg:tags":[
        "register",
        "cash"
    ],
    "wof:name":"Tokyo Electric Co",
    "wof:placetype":"venue"
},
  "geometry": {"coordinates":[145.01133727999999,-37.9558334351],"type":"Point"}
}