{
  "type": "Feature",
  "properties": {
    "addr:full":"382 Wellington Rd Mulgrave VIC 3170",
    "addr:housenumber":"382",
    "addr:postcode":"3170",
    "addr:street":"Wellington Rd",
    "iso:country":"AU",
    "sg:address":"382 Wellington Rd",
    "sg:city":"Mulgrave",
    "sg:classifiers":[
        {
            "category":"Banks & Credit Unions",
            "subcategory":"Bank",
            "type":"Services"
        }
    ],
    "sg:phone":"+61 1300 662 675",
    "sg:postcode":"3170",
    "sg:province":"VIC",
    "wof:name":"Readymoney",
    "wof:placetype":"venue"
},
  "geometry": {"coordinates":[145.16448974599999,-37.9195365906],"type":"Point"}
}