{
  "type": "Feature",
  "properties": {
    "iso:country":"AU",
    "sg:address":"87 Kaola St",
    "sg:city":"Belgrave",
    "sg:classifiers":[
        {
            "category":"Social Services",
            "subcategory":"Child Care",
            "type":"Services"
        }
    ],
    "sg:phone":"+61 405 237 056",
    "sg:postcode":"3160",
    "sg:province":"VIC",
    "sg:tags":[
        "baby",
        "sitter"
    ],
    "wof:name":"Priya Pamamull Belgrave",
    "wof:placetype":"venue"
},
  "geometry": {"coordinates":[145.35273742699999,-37.9165039062],"type":"Point"}
}