{
  "type": "Feature",
  "properties": {
    "iso:country":"AU",
    "sg:address":"53 Peel St (South)",
    "sg:city":"Ballarat",
    "sg:classifiers":[
        {
            "category":"Professional",
            "subcategory":"Printing & Photocopies",
            "type":"Services"
        }
    ],
    "sg:phone":"+61 3 5333 1233",
    "sg:postcode":"3354",
    "sg:province":"VIC",
    "sg:tags":[
        "rubber",
        "stamp",
        "metal"
    ],
    "wof:name":"Fletcher R. & Sons",
    "wof:placetype":"venue"
},
  "geometry": {"coordinates":[143.863251,-37.566654],"type":"Point"}
}