{
  "type": "Feature",
  "properties": {
    "addr:full":"Unit 6 72-74 Gibbes St Chatswood NSW 2067",
    "addr:housenumber":"72-74",
    "addr:postcode":"2067",
    "addr:street":"Gibbes St",
    "iso:country":"AU",
    "sg:address":"Unit 6 72-74 Gibbes St",
    "sg:city":"Chatswood",
    "sg:classifiers":[
        {
            "category":"Military Area",
            "subcategory":"Air Force Base",
            "type":"Public Place"
        }
    ],
    "sg:phone":"+61 2 8467 1200",
    "sg:postcode":"2067",
    "sg:province":"NSW",
    "sg:tags":[
        "wholesaler",
        "travel",
        "good",
        "mfrs"
    ],
    "wof:name":"Epicentre Pty Ltd",
    "wof:placetype":"venue"
},
  "geometry": {"coordinates":[151.19851684599999,-33.7863578796],"type":"Point"}
}