{
  "type": "Feature",
  "properties": {
    "addr:full":"141 Redcliffe Pde Redcliffe QLD 4020",
    "addr:housenumber":"141",
    "addr:postcode":"4020",
    "addr:street":"Redcliffe Pde",
    "iso:country":"AU",
    "sg:address":"141 Redcliffe Pde",
    "sg:city":"Redcliffe",
    "sg:classifiers":[
        {
            "category":"Fast Food",
            "type":"Food & Drink"
        }
    ],
    "sg:phone":"+61 7 3883 2393",
    "sg:postcode":"4020",
    "sg:province":"QLD",
    "sg:tags":[
        "away",
        "take"
    ],
    "wof:name":"Super Sub Sandwich Bar",
    "wof:placetype":"venue"
},
  "geometry": {"coordinates":[153.115173,-27.227907],"type":"Point"}
}