{
  "type": "Feature",
  "properties": {
    "iso:country":"AU",
    "sg:address":"6 Queensbridge Sq",
    "sg:city":"Southbank",
    "sg:classifiers":[
        {
            "category":"Restaurant",
            "type":"Food & Drink"
        }
    ],
    "sg:phone":"+61 3 9686 6610",
    "sg:postcode":"3006",
    "sg:province":"VIC",
    "wof:name":"Blvd Bar",
    "wof:placetype":"venue"
},
  "geometry": {"coordinates":[144.961105347,-37.8211898804],"type":"Point"}
}