{
  "type": "Feature",
  "properties": {
    "addr:full":"187 Woolooware Rd Cronulla NSW 2230",
    "addr:housenumber":"187",
    "addr:postcode":"2230",
    "addr:street":"Woolooware Rd",
    "iso:country":"AU",
    "sg:address":"187 Woolooware Rd",
    "sg:city":"Cronulla",
    "sg:classifiers":[
        {
            "category":"Insurance",
            "subcategory":"Title Insurance",
            "type":"Services"
        }
    ],
    "sg:phone":"+61 2 9544 1520",
    "sg:postcode":"2230",
    "sg:province":"NSW",
    "sg:tags":[
        "searcher"
    ],
    "wof:name":"Williamson R D & S J",
    "wof:placetype":"venue"
},
  "geometry": {"coordinates":[151.13926696799999,-34.0574951172],"type":"Point"}
}