{
  "type": "Feature",
  "properties": {
    "iso:country":"AU",
    "sg:address":"17 Trinder Ave",
    "sg:city":"Maroochydore",
    "sg:classifiers":[
        {
            "category":"Autos & Motor Vehicles",
            "subcategory":"Auto Supplies",
            "type":"Retail Goods"
        }
    ],
    "sg:phone":"+61 7 5479 3200",
    "sg:postcode":"4558",
    "sg:province":"QLD",
    "sg:tags":[
        "part",
        "cycles",
        "accessory"
    ],
    "wof:name":"Sunshine Coast Harley-Davidson & Buell",
    "wof:placetype":"venue"
},
  "geometry": {"coordinates":[153.09327697800001,-26.6647644043],"type":"Point"}
}