{
  "type": "Feature",
  "properties": {
    "iso:country":"AU",
    "sg:address":"Shop 3/ 309 Farm St",
    "sg:city":"North Rockhampton",
    "sg:classifiers":[
        {
            "category":"Food & Beverages",
            "subcategory":"Bakery",
            "type":"Retail Goods"
        }
    ],
    "sg:phone":"+61 7 4926 8900",
    "sg:postcode":"4701",
    "sg:province":"QLD",
    "sg:tags":[
        "baker"
    ],
    "wof:name":"Tjayz",
    "wof:placetype":"venue"
},
  "geometry": {"coordinates":[150.52867126500001,-23.3310165405],"type":"Point"}
}