{
  "type": "Feature",
  "properties": {
    "addr:full":"38 Mt Dandenong Rd Ringwood East VIC 3135",
    "addr:housenumber":"38",
    "addr:postcode":"3135",
    "addr:street":"Mt Dandenong Rd",
    "iso:country":"AU",
    "sg:address":"38 Mt Dandenong Rd",
    "sg:city":"Ringwood East",
    "sg:classifiers":[
        {
            "category":"Health Services",
            "subcategory":"Doctor",
            "type":"Services"
        }
    ],
    "sg:phone":"+61 3 9421 2011",
    "sg:postcode":"3135",
    "sg:province":"VIC",
    "sg:tags":[
        "medical",
        "practitioner"
    ],
    "wof:name":"Doig Rowan G Dr",
    "wof:placetype":"venue"
},
  "geometry": {"coordinates":[145.24899292000001,-37.8090782166],"type":"Point"}
}