{
  "type": "Feature",
  "properties": {
    "addr:full":"80 Barkly St Ararat VIC 3377",
    "addr:housenumber":"80",
    "addr:postcode":"3377",
    "addr:street":"Barkly St",
    "iso:country":"AU",
    "sg:address":"80 Barkly St",
    "sg:city":"Ararat",
    "sg:classifiers":[
        {
            "category":"Shopping",
            "subcategory":"Clothing, Apparel, & Fashions",
            "type":"Retail Goods"
        }
    ],
    "sg:phone":"+61 3 5352 3919",
    "sg:postcode":"3377",
    "sg:province":"VIC",
    "sg:tags":[
        "lady",
        "wear"
    ],
    "wof:name":"Pegis Footwear & Clothing",
    "wof:placetype":"venue"
},
  "geometry": {"coordinates":[142.927856445,-37.2844772339],"type":"Point"}
}