{
  "type": "Feature",
  "properties": {
    "addr:full":"1/ 128 High Street Rd Ashwood VIC 3147",
    "addr:housenumber":"/ 128",
    "addr:postcode":"3147",
    "addr:street":"High Street Rd",
    "iso:country":"AU",
    "sg:address":"1/ 128 High Street Rd",
    "sg:city":"Ashwood",
    "sg:classifiers":[
        {
            "category":"Travel",
            "subcategory":"Travel Agent",
            "type":"Entertainment"
        }
    ],
    "sg:phone":"+61 3 9807 0322",
    "sg:postcode":"3147",
    "sg:province":"VIC",
    "sg:tags":[
        "consultant"
    ],
    "wof:name":"Waverley Travel",
    "wof:placetype":"venue"
},
  "geometry": {"coordinates":[145.105224609,-37.8672599792],"type":"Point"}
}