{
  "type": "Feature",
  "properties": {
    "addr:full":"7 Greg Chappell Drv Andrews QLD 4220",
    "addr:housenumber":"7",
    "addr:postcode":"4220",
    "addr:street":"Greg Chappell Drv",
    "iso:country":"AU",
    "sg:address":"7 Greg Chappell Drv",
    "sg:city":"Andrews",
    "sg:classifiers":[
        {
            "category":"Building & Trades",
            "subcategory":"Construction",
            "type":"Services"
        }
    ],
    "sg:phone":"+61 7 5593 5850",
    "sg:postcode":"4220",
    "sg:province":"QLD",
    "sg:tags":[
        "scaffolding"
    ],
    "wof:name":"Boral Formwork & Scaffolding",
    "wof:placetype":"venue"
},
  "geometry": {"coordinates":[153.41197204599999,-28.1037845612],"type":"Point"}
}