{
  "type": "Feature",
  "properties": {
    "addr:full":"Friendship Ave Marcoola QLD 4564",
    "addr:postcode":"4564",
    "addr:street":"Friendship Ave",
    "iso:country":"AU",
    "sg:address":"Friendship Ave",
    "sg:city":"Marcoola",
    "sg:classifiers":[
        {
            "category":"Building & Trades",
            "subcategory":"Pest Control",
            "type":"Services"
        }
    ],
    "sg:phone":"+61 7 5453 1500",
    "sg:postcode":"4564",
    "sg:province":"QLD",
    "sg:tags":[
        "airport"
    ],
    "wof:name":"Sunshine Coast Airport",
    "wof:placetype":"venue"
},
  "geometry": {"coordinates":[153.086547852,-26.6054210663],"type":"Point"}
}