{
  "type": "Feature",
  "properties": {
    "iso:country":"AU",
    "sg:address":"9 De Havilland Crs",
    "sg:city":"Ballina",
    "sg:classifiers":[
        {
            "category":"Shopping",
            "subcategory":"Computers & Home Electronics",
            "type":"Retail Goods"
        }
    ],
    "sg:phone":"+61 2 6686 3269",
    "sg:postcode":"2478",
    "sg:province":"NSW",
    "sg:tags":[
        "wholesaler",
        "equipment",
        "electronic",
        "mfrs"
    ],
    "wof:name":"Bogaard Electronic Services Pty Ltd",
    "wof:placetype":"venue"
},
  "geometry": {"coordinates":[153.5572052,-28.8472175598],"type":"Point"}
}