{
  "type": "Feature",
  "properties": {
    "iso:country":"AU",
    "sg:address":"Gawler Rd",
    "sg:city":"Two Wells",
    "sg:classifiers":[
        {
            "category":"Education",
            "subcategory":"School",
            "type":"Public Place"
        }
    ],
    "sg:phone":"+61 8 8520 2277",
    "sg:postcode":"5501",
    "sg:province":"SA",
    "sg:tags":[
        "state",
        "except",
        "nsw"
    ],
    "wof:name":"Two Wells Primary School",
    "wof:placetype":"venue"
},
  "geometry": {"coordinates":[138.51469399999999,-34.592731],"type":"Point"}
}