{
  "type": "Feature",
  "properties": {
    "addr:full":"100 St Vincent St Port Adelaide SA 5015",
    "addr:housenumber":"100",
    "addr:postcode":"5015",
    "addr:street":"St Vincent St",
    "iso:country":"AU",
    "sg:address":"100 St Vincent St",
    "sg:city":"Port Adelaide",
    "sg:classifiers":[
        {
            "category":"Shopping",
            "subcategory":"Pawn Shop",
            "type":"Retail Goods"
        }
    ],
    "sg:phone":"+61 8 8447 1814",
    "sg:postcode":"5015",
    "sg:province":"SA",
    "sg:tags":[
        "pawnbroker"
    ],
    "wof:name":"Peters Disposals",
    "wof:placetype":"venue"
},
  "geometry": {"coordinates":[138.50201415999999,-34.8451652527],"type":"Point"}
}