{
  "type": "Feature",
  "properties": {
    "iso:country":"AU",
    "sg:address":"Rear 3 Murnin St",
    "sg:city":"Wallsend",
    "sg:classifiers":[
        {
            "category":"Retail",
            "subcategory":"Auto Repair",
            "type":"Services"
        }
    ],
    "sg:phone":"+61 2 4955 8992",
    "sg:postcode":"2287",
    "sg:province":"NSW",
    "sg:tags":[
        "repairer",
        "motor",
        "engineer"
    ],
    "wof:name":"Cleggs Radiator Service",
    "wof:placetype":"venue"
},
  "geometry": {"coordinates":[151.67083740199999,-32.902961731],"type":"Point"}
}