{
  "type": "Feature",
  "properties": {
    "iso:country":"AU",
    "sg:address":"39 Townshend St",
    "sg:city":"Phillip",
    "sg:classifiers":[
        {
            "category":"Wholesale",
            "subcategory":"Electrical",
            "type":"Manufacturing & Wholesale Goods"
        }
    ],
    "sg:phone":"+61 2 6282 2588",
    "sg:postcode":"2606",
    "sg:province":"ACT",
    "sg:tags":[
        "wholesaler"
    ],
    "wof:name":"Project Lighting Pty Ltd",
    "wof:placetype":"venue"
},
  "geometry": {"coordinates":[149.08815002399999,-35.3529129028],"type":"Point"}
}