{
  "type": "Feature",
  "properties": {
    "iso:country":"AU",
    "sg:address":"23 Satsuma Crs",
    "sg:city":"Golden Grove",
    "sg:classifiers":[
        {
            "category":"Building & Trades",
            "subcategory":"Landscaping Services",
            "type":"Services"
        }
    ],
    "sg:phone":"+61 403 252 000",
    "sg:postcode":"5125",
    "sg:province":"SA",
    "sg:tags":[
        "gardener"
    ],
    "wof:name":"Ellul Mark James",
    "wof:placetype":"venue"
},
  "geometry": {"coordinates":[138.72293099999999,-34.779251],"type":"Point"}
}