{
  "type": "Feature",
  "properties": {
    "addr:full":"2/ 13 Melinda Crs Paradise SA 5075",
    "addr:housenumber":"/ 13",
    "addr:postcode":"5075",
    "addr:street":"Melinda Crs",
    "iso:country":"AU",
    "sg:address":"2/ 13 Melinda Crs",
    "sg:city":"Paradise",
    "sg:classifiers":[
        {
            "category":"Personal",
            "subcategory":"Massage",
            "type":"Services"
        }
    ],
    "sg:phone":"+61 8 8165 3930",
    "sg:postcode":"5075",
    "sg:province":"SA",
    "sg:tags":[
        "therapy"
    ],
    "wof:name":"Paul Strauss Remedial & Sports Massage Clinic",
    "wof:placetype":"venue"
},
  "geometry": {"coordinates":[138.683319092,-34.8744850159],"type":"Point"}
}