{
  "type": "Feature",
  "properties": {
    "addr:full":"PO Box 48 Sheffield TAS 7306",
    "addr:postcode":"7306",
    "iso:country":"AU",
    "sg:address":"PO Box 48",
    "sg:city":"Sheffield",
    "sg:classifiers":[
        {
            "category":"Professional",
            "type":"Services"
        }
    ],
    "sg:phone":"+61 3 6491 1227",
    "sg:postcode":"7306",
    "sg:province":"TAS",
    "sg:tags":[
        "transport"
    ],
    "wof:name":"Duff P C",
    "wof:placetype":"venue"
},
  "geometry": {"coordinates":[146.330872,-41.384521],"type":"Point"}
}