{
  "type": "Feature",
  "properties": {
    "addr:full":"100 Bradley St Guyra NSW 2365",
    "addr:housenumber":"100",
    "addr:postcode":"2365",
    "addr:street":"Bradley St",
    "iso:country":"AU",
    "sg:address":"100 Bradley St",
    "sg:city":"Guyra",
    "sg:classifiers":[
        {
            "category":"Shopping",
            "type":"Retail Goods"
        }
    ],
    "sg:phone":"+61 2 6779 1777",
    "sg:postcode":"2365",
    "sg:province":"NSW",
    "sg:tags":[
        "agent",
        "stock"
    ],
    "wof:name":"Jackson Livestock & Property Pty Ltd",
    "wof:placetype":"venue"
},
  "geometry": {"coordinates":[151.672042847,-30.2178440094],"type":"Point"}
}