{
  "type": "Feature",
  "properties": {
    "addr:full":"117 Macquarie St Sydney NSW 2000",
    "addr:housenumber":"117",
    "addr:postcode":"2000",
    "addr:street":"Macquarie St",
    "iso:country":"AU",
    "sg:address":"117 Macquarie St",
    "sg:city":"Sydney",
    "sg:classifiers":[
        {
            "category":"Education",
            "subcategory":"Junior College",
            "type":"Public Place"
        }
    ],
    "sg:phone":"+61 2 9240 1280",
    "sg:postcode":"2000",
    "sg:province":"NSW",
    "sg:tags":[
        "business"
    ],
    "wof:name":"The Hotel School",
    "wof:placetype":"venue"
},
  "geometry": {"coordinates":[151.212814331,-33.8624305725],"type":"Point"}
}