{
  "type": "Feature",
  "properties": {
    "iso:country":"AU",
    "sg:address":"Shp 2b, 142 Pacific Hwy",
    "sg:city":"Wyong",
    "sg:classifiers":[
        {
            "category":"Personal",
            "subcategory":"Beauty Salon",
            "type":"Services"
        }
    ],
    "sg:phone":"+61 2 4352 1986",
    "sg:postcode":"2259",
    "sg:province":"NSW",
    "sg:tags":[
        "hairdresser"
    ],
    "wof:name":"Hair 2 Dye 4",
    "wof:placetype":"venue"
},
  "geometry": {"coordinates":[151.42593383799999,-33.2817993164],"type":"Point"}
}