{
  "type": "Feature",
  "properties": {
    "iso:country":"AU",
    "sg:address":"Community Health Centre Princes Hwy",
    "sg:city":"Nowa Nowa",
    "sg:classifiers":[
        {
            "category":"Social Services",
            "subcategory":"Child Care",
            "type":"Services"
        }
    ],
    "sg:phone":"+61 3 5155 7294",
    "sg:postcode":"3887",
    "sg:province":"VIC",
    "sg:tags":[
        "support",
        "health"
    ],
    "wof:name":"Maternal & Child Health Centres",
    "wof:placetype":"venue"
},
  "geometry": {"coordinates":[148.09475707999999,-37.7305603027],"type":"Point"}
}