{
  "type": "Feature",
  "properties": {
    "iso:country":"AU",
    "sg:address":"Unit 26,/ 70",
    "sg:city":"Marina Blv Ocean Reef",
    "sg:classifiers":[
        {
            "category":"Farming",
            "subcategory":"Crops",
            "type":"Manufacturing & Wholesale Goods"
        }
    ],
    "sg:phone":"+61 8 9401 0772",
    "sg:postcode":"6027",
    "sg:province":"WA",
    "sg:tags":[
        "club",
        "dance"
    ],
    "wof:name":"The Tartan Scottish Country Dancers of WA",
    "wof:placetype":"venue"
},
  "geometry": {"coordinates":[115.742218018,-31.7661323547],"type":"Point"}
}