{
  "type": "Feature",
  "properties": {
    "iso:country":"AU",
    "sg:address":"12 Murlte Crt",
    "sg:city":"Palm Cove",
    "sg:classifiers":[
        {
            "category":"Home & Garden",
            "subcategory":"Building Materials",
            "type":"Retail Goods"
        }
    ],
    "sg:phone":"+61 7 5576 8885",
    "sg:postcode":"4879",
    "sg:province":"QLD",
    "sg:tags":[
        "merchant",
        "glass",
        "glazier"
    ],
    "wof:name":"Pacific Glass & Glazing",
    "wof:placetype":"venue"
},
  "geometry": {"coordinates":[145.67100524899999,-16.7458992004],"type":"Point"}
}