{
  "type": "Feature",
  "properties": {
    "addr:full":"Cnr Booth Ave & Donald St Tannum Sands QLD 4680",
    "addr:postcode":"4680",
    "addr:street":"Cnr Booth Ave & Donald St",
    "iso:country":"AU",
    "sg:address":"Cnr Booth Ave & Donald St",
    "sg:city":"Tannum Sands",
    "sg:classifiers":[
        {
            "category":"Retail",
            "subcategory":"Veterinary Services",
            "type":"Services"
        }
    ],
    "sg:phone":"+61 7 4973 8195",
    "sg:postcode":"4680",
    "sg:province":"QLD",
    "sg:tags":[
        "surgeon"
    ],
    "wof:name":"Hayes St Clair",
    "wof:placetype":"venue"
},
  "geometry": {"coordinates":[151.36984252900001,-23.9508056641],"type":"Point"}
}