{
  "type": "Feature",
  "properties": {
    "addr:full":"Shop 85 Mt Druitt Westfield, Mt Druitt NSW 2770",
    "addr:housenumber":"shop 85;druitt",
    "addr:postcode":"2770",
    "addr:street":"Mt;Mt",
    "iso:country":"AU",
    "sg:address":"Shop 85",
    "sg:city":"Mt Druitt Westfield, Mt Druitt",
    "sg:classifiers":[
        {
            "category":"Shopping",
            "subcategory":"Mobile Phones",
            "type":"Retail Goods"
        }
    ],
    "sg:phone":"+61 2 9832 0777",
    "sg:postcode":"2770",
    "sg:province":"NSW",
    "sg:tags":[
        "telephone",
        "accessory"
    ],
    "wof:name":"Vodafone Digicall",
    "wof:placetype":"venue"
},
  "geometry": {"coordinates":[150.811035156,-33.7732086182],"type":"Point"}
}