{
  "type": "Feature",
  "properties": {
    "addr:full":"20A Coolstores Cnr Moorooduc & Eramosa Rds Moorooduc VIC 3933",
    "addr:housenumber":"20a",
    "addr:postcode":"3933",
    "addr:street":"Coolstores Cnr Moorooduc &",
    "iso:country":"AU",
    "sg:address":"20A Coolstores Cnr Moorooduc & Eramosa Rds",
    "sg:city":"Moorooduc",
    "sg:classifiers":[
        {
            "category":"Personal",
            "type":"Services"
        }
    ],
    "sg:phone":"+61 3 5971 3874",
    "sg:postcode":"3933",
    "sg:province":"VIC",
    "sg:tags":[
        "reducing",
        "treatment",
        "weight"
    ],
    "wof:name":"Leah & Wendy's Place",
    "wof:placetype":"venue"
},
  "geometry": {"coordinates":[145.124725342,-38.2160720825],"type":"Point"}
}