{
  "type": "Feature",
  "properties": {
    "iso:country":"AU",
    "sg:address":"43 Ayliffe Rd",
    "sg:city":"St Marys",
    "sg:classifiers":[
        {
            "category":"Retail",
            "subcategory":"Driving School",
            "type":"Services"
        }
    ],
    "sg:phone":"+61 8 8271 8400",
    "sg:postcode":"5042",
    "sg:province":"SA",
    "wof:name":"Mitcham Driving School",
    "wof:placetype":"venue"
},
  "geometry": {"coordinates":[138.581085,-35.010742],"type":"Point"}
}