{
  "type": "Feature",
  "properties": {
    "iso:country":"AU",
    "sg:address":"240 Currie St",
    "sg:city":"Adelaide",
    "sg:classifiers":[
        {
            "category":"Professional",
            "subcategory":"Accounting & Tax Preparation",
            "type":"Services"
        }
    ],
    "sg:phone":"+61 413 089 082",
    "sg:postcode":"5000",
    "sg:province":"SA",
    "sg:tags":[
        "consultant",
        "taxation"
    ],
    "wof:name":"Cheryl Cook & Associates",
    "wof:placetype":"venue"
},
  "geometry": {"coordinates":[138.58917236299999,-34.9246177673],"type":"Point"}
}