{
  "type": "Feature",
  "properties": {
    "iso:country":"AU",
    "sg:address":"15 Bruce St",
    "sg:city":"Stanmore",
    "sg:classifiers":[
        {
            "category":"Professional",
            "subcategory":"Detective & Security Services",
            "type":"Services"
        }
    ],
    "sg:phone":"+61 2 9564 0934",
    "sg:postcode":"2048",
    "sg:province":"NSW",
    "sg:tags":[
        "guard",
        "patrol"
    ],
    "wof:name":"McAndy Security Services",
    "wof:placetype":"venue"
},
  "geometry": {"coordinates":[151.162048,-33.892265],"type":"Point"}
}