{
  "type": "Feature",
  "properties": {
    "addr:full":"531 Wellington St Perth WA 6000",
    "addr:housenumber":"531",
    "addr:postcode":"6000",
    "addr:street":"Wellington St",
    "iso:country":"AU",
    "sg:address":"531 Wellington St",
    "sg:city":"Perth",
    "sg:classifiers":[
        {
            "category":"Travel",
            "subcategory":"Hotels & Motels",
            "type":"Entertainment"
        }
    ],
    "sg:phone":"+61 8 9338 5100",
    "sg:postcode":"6000",
    "sg:province":"WA",
    "sg:tags":[
        "accommodation"
    ],
    "wof:name":"The Royal Hotel",
    "wof:placetype":"venue"
},
  "geometry": {"coordinates":[115.85735321,-31.9511604309],"type":"Point"}
}