{
  "type": "Feature",
  "properties": {
    "iso:country":"AU",
    "sg:address":"16 Saligna Drv",
    "sg:city":"Tullamarine",
    "sg:classifiers":[
        {
            "category":"Home & Garden",
            "subcategory":"Building Materials",
            "type":"Retail Goods"
        }
    ],
    "sg:phone":"+61 3 9338 9898",
    "sg:postcode":"3043",
    "sg:province":"VIC",
    "sg:tags":[
        "fitting",
        "door"
    ],
    "wof:name":"Doorway Systems Pty Ltd",
    "wof:placetype":"venue"
},
  "geometry": {"coordinates":[144.86369323700001,-37.7117271423],"type":"Point"}
}