{
  "type": "Feature",
  "properties": {
    "iso:country":"AU",
    "sg:address":"18 Canterbury St",
    "sg:city":"Ballarat",
    "sg:classifiers":[
        {
            "category":"Utilities",
            "subcategory":"Electric",
            "type":"Services"
        }
    ],
    "sg:phone":"+61 419 541 926",
    "sg:postcode":"3350",
    "sg:province":"VIC",
    "sg:tags":[
        "electrical",
        "contractor"
    ],
    "wof:name":"GL Szalontai",
    "wof:placetype":"venue"
},
  "geometry": {"coordinates":[143.888351,-37.555283],"type":"Point"}
}