{
  "type": "Feature",
  "properties": {
    "addr:full":"161 Canterbury Rd Toorak VIC 3142",
    "addr:housenumber":"161",
    "addr:postcode":"3142",
    "addr:street":"Canterbury Rd",
    "iso:country":"AU",
    "sg:address":"161 Canterbury Rd",
    "sg:city":"Toorak",
    "sg:classifiers":[
        {
            "category":"Health Services",
            "subcategory":"Health Practitioner",
            "type":"Services"
        }
    ],
    "sg:phone":"+61 422 420 333",
    "sg:postcode":"3142",
    "sg:province":"VIC",
    "sg:tags":[
        "myotherapy"
    ],
    "wof:name":"Mayne Myotherapy",
    "wof:placetype":"venue"
},
  "geometry": {"coordinates":[145.010528564,-37.8414993286],"type":"Point"}
}