{
  "type": "Feature",
  "properties": {
    "iso:country":"AU",
    "sg:address":"Racecourse Rd",
    "sg:city":"Mornington",
    "sg:classifiers":[
        {
            "category":"Building & Trades",
            "subcategory":"Construction",
            "type":"Services"
        }
    ],
    "sg:phone":"+61 3 5986 0866",
    "sg:postcode":"3931",
    "sg:province":"VIC",
    "sg:tags":[
        "road",
        "contractor"
    ],
    "wof:name":"Nepean Roads",
    "wof:placetype":"venue"
},
  "geometry": {"coordinates":[145.06988525400001,-38.230430603],"type":"Point"}
}