{
  "type": "Feature",
  "properties": {
    "iso:country":"AU",
    "sg:address":"PO Box 50",
    "sg:city":"Wahroonga",
    "sg:classifiers":[
        {
            "category":"Professional",
            "subcategory":"Computer Services",
            "type":"Services"
        }
    ],
    "sg:phone":"+61 2 9487 6055",
    "sg:postcode":"2076",
    "sg:province":"NSW",
    "sg:tags":[
        "package",
        "software"
    ],
    "wof:name":"Exant Software",
    "wof:placetype":"venue"
},
  "geometry": {"coordinates":[151.117385864,-33.7187194824],"type":"Point"}
}