{
  "type": "Feature",
  "properties": {
    "addr:full":"354 Bilsen Rd Geebung QLD 4034",
    "addr:housenumber":"354",
    "addr:postcode":"4034",
    "addr:street":"Bilsen Rd",
    "iso:country":"AU",
    "sg:address":"354 Bilsen Rd",
    "sg:city":"Geebung",
    "sg:classifiers":[
        {
            "category":"Wholesale",
            "subcategory":"Medical Equipment & Supplies",
            "type":"Manufacturing & Wholesale Goods"
        }
    ],
    "sg:phone":"+61 7 3637 6360",
    "sg:postcode":"4034",
    "sg:province":"QLD",
    "sg:tags":[
        "aid",
        "care",
        "health",
        "home"
    ],
    "wof:name":"ETS Mobility",
    "wof:placetype":"venue"
},
  "geometry": {"coordinates":[153.055145264,-27.3751144409],"type":"Point"}
}