{
  "type": "Feature",
  "properties": {
    "iso:country":"AU",
    "sg:address":"29 Wilson St",
    "sg:city":"Berwick",
    "sg:classifiers":[
        {
            "category":"Travel",
            "subcategory":"Hostel",
            "type":"Entertainment"
        }
    ],
    "sg:phone":"+61 3 9796 1200",
    "sg:postcode":"3806",
    "sg:province":"VIC",
    "sg:tags":[
        "home"
    ],
    "wof:name":"Berwick Village Aged Care Residence",
    "wof:placetype":"venue"
},
  "geometry": {"coordinates":[145.35098266599999,-38.031627655],"type":"Point"}
}