{
  "type": "Feature",
  "properties": {
    "addr:full":"10 West Pde West Ryde NSW 2114",
    "addr:housenumber":"10",
    "addr:postcode":"2114",
    "addr:street":"West Pde",
    "iso:country":"AU",
    "sg:address":"10 West Pde",
    "sg:city":"West Ryde",
    "sg:classifiers":[
        {
            "category":"Fast Food",
            "type":"Food & Drink"
        }
    ],
    "sg:phone":"+61 2 9809 7876",
    "sg:postcode":"2114",
    "sg:province":"NSW",
    "sg:tags":[
        "away",
        "take"
    ],
    "wof:name":"Belvior's Eatery & Noodle Plus",
    "wof:placetype":"venue"
},
  "geometry": {"coordinates":[151.08883667000001,-33.8073577881],"type":"Point"}
}