{
  "type": "Feature",
  "properties": {
    "addr:full":"111 Lethbridge St Penrith NSW 2750",
    "addr:housenumber":"111",
    "addr:postcode":"2750",
    "addr:street":"Lethbridge St",
    "iso:country":"AU",
    "sg:address":"111 Lethbridge St",
    "sg:city":"Penrith",
    "sg:classifiers":[
        {
            "category":"Health Services",
            "subcategory":"Health Practitioner",
            "type":"Services"
        }
    ],
    "sg:phone":"+61 2 4721 5788",
    "sg:postcode":"2750",
    "sg:province":"NSW",
    "sg:tags":[
        "physiotherapist"
    ],
    "wof:name":"O&#039;Neill Jennifer",
    "wof:placetype":"venue"
},
  "geometry": {"coordinates":[150.701080322,-33.7563591003],"type":"Point"}
}