{
  "type": "Feature",
  "properties": {
    "addr:full":"PO Box 511 Cessnock NSW 2325",
    "addr:postcode":"2325",
    "iso:country":"AU",
    "sg:address":"PO Box 511",
    "sg:city":"Cessnock",
    "sg:classifiers":[
        {
            "category":"Health Services",
            "subcategory":"Doctor",
            "type":"Services"
        }
    ],
    "sg:phone":"+61 2 4991 3122",
    "sg:postcode":"2325",
    "sg:province":"NSW",
    "sg:tags":[
        "occupational",
        "safety"
    ],
    "wof:name":"Workplace Safety & Training Services",
    "wof:placetype":"venue"
},
  "geometry": {"coordinates":[151.354934692,-32.8325691223],"type":"Point"}
}