{
  "type": "Feature",
  "properties": {
    "iso:country":"AU",
    "sg:address":"2 Nartanda Ave",
    "sg:city":"Wamberal",
    "sg:classifiers":[
        {
            "category":"Building & Trades",
            "subcategory":"Construction",
            "type":"Services"
        }
    ],
    "sg:phone":"+61 2 4385 6636",
    "sg:postcode":"2260",
    "sg:province":"NSW",
    "sg:tags":[
        "earth",
        "excavating",
        "moving",
        "contractor"
    ],
    "wof:name":"Robertson Grant",
    "wof:placetype":"venue"
},
  "geometry": {"coordinates":[151.45124799999999,-33.400139],"type":"Point"}
}