{
  "type": "Feature",
  "properties": {
    "addr:full":"Lot 5 West St Bowen QLD 4805",
    "addr:postcode":"4805",
    "addr:street":"St",
    "iso:country":"AU",
    "sg:address":"Lot 5 West St",
    "sg:city":"Bowen",
    "sg:classifiers":[
        {
            "category":"Farming",
            "subcategory":"Dairy Farm",
            "type":"Manufacturing & Wholesale Goods"
        }
    ],
    "sg:phone":"+61 7 4786 4937",
    "sg:postcode":"4805",
    "sg:province":"QLD",
    "sg:tags":[
        "wholesaler",
        "product",
        "mfrs"
    ],
    "wof:name":"Dodds Agencies",
    "wof:placetype":"venue"
},
  "geometry": {"coordinates":[148.230545044,-20.0059509277],"type":"Point"}
}