{
  "type": "Feature",
  "properties": {
    "iso:country":"AU",
    "sg:address":"11 Norseman Ave",
    "sg:city":"Westbourne Park",
    "sg:classifiers":[
        {
            "category":"Professional",
            "subcategory":"Detective & Security Services",
            "type":"Services"
        }
    ],
    "sg:phone":"+61 418 800 637",
    "sg:postcode":"5041",
    "sg:province":"SA",
    "sg:tags":[
        "domestic",
        "alarm",
        "commercial",
        "burglar"
    ],
    "wof:name":"Arthur's Electrical Services",
    "wof:placetype":"venue"
},
  "geometry": {"coordinates":[138.598114,-34.973347],"type":"Point"}
}