{
  "type": "Feature",
  "properties": {
    "addr:full":"Unit 3 / 43 Pearson St Wagga Wagga NSW 2650",
    "addr:housenumber":"43",
    "addr:postcode":"2650",
    "addr:street":"Pearson St",
    "iso:country":"AU",
    "sg:address":"Unit 3 / 43 Pearson St",
    "sg:city":"Wagga Wagga",
    "sg:classifiers":[
        {
            "category":"Building & Trades",
            "subcategory":"Construction",
            "type":"Services"
        }
    ],
    "sg:phone":"+61 2 6925 2770",
    "sg:postcode":"2650",
    "sg:province":"NSW",
    "sg:tags":[
        "insulation",
        "contractor"
    ],
    "wof:name":"Wagga Insulation",
    "wof:placetype":"venue"
},
  "geometry": {"coordinates":[147.345504761,-35.1163024902],"type":"Point"}
}