{
  "type": "Feature",
  "properties": {
    "addr:full":"97 Mt Pleasant Rd Nunawading VIC 3131",
    "addr:housenumber":"97",
    "addr:postcode":"3131",
    "addr:street":"Mt Pleasant Rd",
    "iso:country":"AU",
    "sg:address":"97 Mt Pleasant Rd",
    "sg:city":"Nunawading",
    "sg:classifiers":[
        {
            "category":"Building & Trades",
            "subcategory":"Cleaning & Sanitation",
            "type":"Services"
        }
    ],
    "sg:phone":"+61 3 9878 8711",
    "sg:postcode":"3131",
    "sg:province":"VIC",
    "sg:tags":[
        "industrial",
        "commercial",
        "contractor"
    ],
    "wof:name":"Scholastic Cleaning And Consultancy Services Pty Ltd",
    "wof:placetype":"venue"
},
  "geometry": {"coordinates":[145.17825317399999,-37.8259315491],"type":"Point"}
}