{
  "type": "Feature",
  "properties": {
    "addr:full":"16 Arundel St Fremantle WA 6959",
    "addr:housenumber":"16",
    "addr:postcode":"6959",
    "addr:street":"Arundel St",
    "iso:country":"AU",
    "sg:address":"16 Arundel St",
    "sg:city":"Fremantle",
    "sg:classifiers":[
        {
            "category":"Sports & Exercise",
            "subcategory":"Gym",
            "type":"Entertainment"
        }
    ],
    "sg:phone":"+61 8 9433 4243",
    "sg:postcode":"6959",
    "sg:province":"WA",
    "sg:tags":[
        "pilate",
        "method"
    ],
    "wof:name":"PeopleMaxx Pilates",
    "wof:placetype":"venue"
},
  "geometry": {"coordinates":[115.749443054,-32.0591621399],"type":"Point"}
}