{
  "type": "Feature",
  "properties": {
    "addr:full":"Cnr Huntingdale Rd & Croft St Huntingdale VIC 3166",
    "addr:postcode":"3166",
    "addr:street":"Cnr Huntingdale Rd & Croft St",
    "iso:country":"AU",
    "sg:address":"Cnr Huntingdale Rd & Croft St",
    "sg:city":"Huntingdale",
    "sg:classifiers":[
        {
            "category":"Retail",
            "subcategory":"Auto Repair",
            "type":"Services"
        }
    ],
    "sg:phone":"+61 3 9568 3455",
    "sg:postcode":"3166",
    "sg:province":"VIC",
    "sg:tags":[
        "repairer",
        "motor",
        "engineer"
    ],
    "wof:name":"Swedish Prestige",
    "wof:placetype":"venue"
},
  "geometry": {"coordinates":[145.105300903,-37.901550293],"type":"Point"}
}