{
  "type": "Feature",
  "properties": {
    "addr:full":"17 Parramatta Rd Underwood QLD 4119",
    "addr:housenumber":"17",
    "addr:postcode":"4119",
    "addr:street":"Parramatta Rd",
    "iso:country":"AU",
    "sg:address":"17 Parramatta Rd",
    "sg:city":"Underwood",
    "sg:classifiers":[
        {
            "category":"Building & Trades",
            "subcategory":"Construction",
            "type":"Services"
        }
    ],
    "sg:phone":"+61 7 3209 1449",
    "sg:postcode":"4119",
    "sg:province":"QLD",
    "sg:tags":[
        "concrete",
        "treatment",
        "repair"
    ],
    "wof:name":"Vibro Products Pty Ltd",
    "wof:placetype":"venue"
},
  "geometry": {"coordinates":[153.11590576200001,-27.614440918],"type":"Point"}
}