{
  "type": "Feature",
  "properties": {
    "addr:full":"2 Federal Rd Kalgoorlie WA 6430",
    "addr:housenumber":"2",
    "addr:postcode":"6430",
    "addr:street":"Federal Rd",
    "iso:country":"AU",
    "sg:address":"2 Federal Rd",
    "sg:city":"Kalgoorlie",
    "sg:classifiers":[
        {
            "category":"Home & Garden",
            "subcategory":"Carpets & Floor Coverings",
            "type":"Retail Goods"
        }
    ],
    "sg:phone":"+61 8 9021 5747",
    "sg:postcode":"6430",
    "sg:province":"WA",
    "wof:name":"Solomons",
    "wof:placetype":"venue"
},
  "geometry": {"coordinates":[121.486160278,-30.7586116791],"type":"Point"}
}