{
  "type": "Feature",
  "properties": {
    "addr:full":"468 Main North Rd Blair Athol SA 5084",
    "addr:housenumber":"468",
    "addr:postcode":"5084",
    "addr:street":"Main North Rd",
    "iso:country":"AU",
    "sg:address":"468 Main North Rd",
    "sg:city":"Blair Athol",
    "sg:classifiers":[
        {
            "category":"Autos & Motor Vehicles",
            "subcategory":"Auto Supplies",
            "type":"Retail Goods"
        }
    ],
    "sg:phone":"+61 8 8262 8004",
    "sg:postcode":"5084",
    "sg:province":"SA",
    "sg:tags":[
        "automotive",
        "stereo",
        "radio"
    ],
    "wof:name":"Strathfield",
    "wof:placetype":"venue"
},
  "geometry": {"coordinates":[138.60040283199999,-34.8544616699],"type":"Point"}
}