{
  "type": "Feature",
  "properties": {
    "iso:country":"AU",
    "sg:address":"176 English St",
    "sg:city":"Manunda",
    "sg:classifiers":[
        {
            "category":"Retail",
            "subcategory":"Auto Repair",
            "type":"Services"
        }
    ],
    "sg:phone":"+61 7 4053 5900",
    "sg:postcode":"4870",
    "sg:province":"QLD",
    "sg:tags":[
        "repairer",
        "motor",
        "engineer"
    ],
    "wof:name":"Nathan Lockyer Automotive",
    "wof:placetype":"venue"
},
  "geometry": {"coordinates":[145.74716186500001,-16.9163894653],"type":"Point"}
}