{
  "type": "Feature",
  "properties": {
    "iso:country":"AU",
    "sg:address":"PO Box 5191",
    "sg:city":"Kahibah",
    "sg:classifiers":[
        {
            "category":"Real Estate",
            "subcategory":"Real Estate Agent",
            "type":"Services"
        }
    ],
    "sg:phone":"+61 412 859 539",
    "sg:postcode":"2290",
    "sg:province":"NSW",
    "wof:name":"Bizsmart",
    "wof:placetype":"venue"
},
  "geometry": {"coordinates":[151.71333313,-32.9619102478],"type":"Point"}
}