{
  "type": "Feature",
  "properties": {
    "iso:country":"AU",
    "sg:address":"Mt Walker Rd",
    "sg:city":"Narembeen",
    "sg:classifiers":[
        {
            "category":"Farming",
            "subcategory":"Farm",
            "type":"Manufacturing & Wholesale Goods"
        }
    ],
    "sg:phone":"+61 8 9064 7318",
    "sg:postcode":"6369",
    "sg:province":"WA",
    "sg:tags":[
        "farmer"
    ],
    "wof:name":"Fidge Ross & Helen",
    "wof:placetype":"venue"
},
  "geometry": {"coordinates":[118.391647,-32.072941],"type":"Point"}
}