{
  "type": "Feature",
  "properties": {
    "addr:full":"11 Ross River Rd Rising Sun QLD 4812",
    "addr:housenumber":"11",
    "addr:postcode":"4812",
    "addr:street":"Ross River Rd",
    "iso:country":"AU",
    "sg:address":"11 Ross River Rd",
    "sg:city":"Rising Sun",
    "sg:classifiers":[
        {
            "category":"Coffee & Tea",
            "type":"Food & Drink"
        }
    ],
    "sg:phone":"+61 7 4775 6116",
    "sg:postcode":"4812",
    "sg:province":"QLD",
    "sg:tags":[
        "kayak",
        "canoe"
    ],
    "wof:name":"Adventure Equipment",
    "wof:placetype":"venue"
},
  "geometry": {"coordinates":[146.795502,-19.291666],"type":"Point"}
}