{
  "type": "Feature",
  "properties": {
    "iso:country":"AU",
    "sg:address":"55 Kingsmill Rd",
    "sg:city":"Pickering Brook",
    "sg:classifiers":[
        {
            "category":"Home & Garden",
            "subcategory":"Building Materials",
            "type":"Retail Goods"
        }
    ],
    "sg:phone":"+61 407 160 634",
    "sg:postcode":"6076",
    "sg:province":"WA",
    "sg:tags":[
        "lawn",
        "cutting",
        "maintenance"
    ],
    "wof:name":"Specialized Turf and Horticultural Services",
    "wof:placetype":"venue"
},
  "geometry": {"coordinates":[116.14321899399999,-32.0368881226],"type":"Point"}
}