{
  "type": "Feature",
  "properties": {
    "iso:country":"AU",
    "sg:address":"PO Box 3140",
    "sg:city":"Wheelers Hill",
    "sg:classifiers":[
        {
            "category":"Professional",
            "subcategory":"Detective & Security Services",
            "type":"Services"
        }
    ],
    "sg:phone":"+61 3 9562 5666",
    "sg:postcode":"3150",
    "sg:province":"VIC",
    "sg:tags":[
        "investigator"
    ],
    "wof:name":"Speak Easy Communications Security",
    "wof:placetype":"venue"
},
  "geometry": {"coordinates":[145.18919372600001,-37.9060401917],"type":"Point"}
}