{
  "type": "Feature",
  "properties": {
    "addr:full":"160 Haughton Rd Oakleigh VIC 3166",
    "addr:housenumber":"160",
    "addr:postcode":"3166",
    "addr:street":"Haughton Rd",
    "iso:country":"AU",
    "sg:address":"160 Haughton Rd",
    "sg:city":"Oakleigh",
    "sg:classifiers":[
        {
            "category":"Home & Garden",
            "subcategory":"Building Materials",
            "type":"Retail Goods"
        }
    ],
    "sg:phone":"+61 3 9570 4367",
    "sg:postcode":"3166",
    "sg:province":"VIC",
    "sg:tags":[
        "merchant",
        "glass",
        "glazier"
    ],
    "wof:name":"1 &#039;A&#039; T & E Glass",
    "wof:placetype":"venue"
},
  "geometry": {"coordinates":[145.101486206,-37.9107093811],"type":"Point"}
}