{
  "type": "Feature",
  "properties": {
    "addr:full":"23 Beaumont Rd Killara NSW 2071",
    "addr:housenumber":"23",
    "addr:postcode":"2071",
    "addr:street":"Beaumont Rd",
    "iso:country":"AU",
    "sg:address":"23 Beaumont Rd",
    "sg:city":"Killara",
    "sg:classifiers":[
        {
            "category":"Health Services",
            "subcategory":"Health Practitioner",
            "type":"Services"
        }
    ],
    "sg:phone":"+61 2 9498 1860",
    "sg:postcode":"2071",
    "sg:province":"NSW",
    "sg:tags":[
        "acupuncture"
    ],
    "wof:name":"Acupuncture Asscn of Australia Inc",
    "wof:placetype":"venue"
},
  "geometry": {"coordinates":[151.14422607399999,-33.7727127075],"type":"Point"}
}