{
  "type": "Feature",
  "properties": {
    "iso:country":"AU",
    "sg:address":"Mt Louisa Shopng Cntr Bayswater Rd",
    "sg:city":"Mt Louisa",
    "sg:classifiers":[
        {
            "category":"Personal",
            "subcategory":"Beauty Salon",
            "type":"Services"
        }
    ],
    "sg:phone":"+61 7 4774 4625",
    "sg:postcode":"4814",
    "sg:province":"QLD",
    "wof:name":"Wholistic Nail & Beauty Centre The",
    "wof:placetype":"venue"
},
  "geometry": {"coordinates":[146.74156199999999,-19.271032],"type":"Point"}
}