{
  "type": "Feature",
  "properties": {
    "iso:country":"AU",
    "sg:address":"901 Grand Junction Rd",
    "sg:city":"Valley View",
    "sg:classifiers":[
        {
            "category":"Fast Food",
            "type":"Food & Drink"
        }
    ],
    "sg:phone":"+61 8 8396 4020",
    "sg:postcode":"5093",
    "sg:province":"SA",
    "sg:tags":[
        "away",
        "take"
    ],
    "wof:name":"Valley View Fish Cafe",
    "wof:placetype":"venue"
},
  "geometry": {"coordinates":[138.66288757300001,-34.8451652527],"type":"Point"}
}