{
  "type": "Feature",
  "properties": {
    "iso:country":"AU",
    "sg:address":"22 Stephen St",
    "sg:city":"Bunbury",
    "sg:classifiers":[
        {
            "category":"Cafe",
            "type":"Food & Drink"
        }
    ],
    "sg:phone":"+61 8 9791 8990",
    "sg:postcode":"6230",
    "sg:province":"WA",
    "wof:name":"Janny's Cafe",
    "wof:placetype":"venue"
},
  "geometry": {"coordinates":[115.63768,-33.326294],"type":"Point"}
}