{
  "type": "Feature",
  "properties": {
    "addr:full":"397 Burke St Darlinghurst NSW 2010",
    "addr:housenumber":"397",
    "addr:postcode":"2010",
    "addr:street":"Burke St",
    "iso:country":"AU",
    "sg:address":"397 Burke St",
    "sg:city":"Darlinghurst",
    "sg:classifiers":[
        {
            "category":"Shopping",
            "subcategory":"Clothing, Apparel, & Fashions",
            "type":"Retail Goods"
        }
    ],
    "sg:phone":"+61 2 9360 7334",
    "sg:postcode":"2010",
    "sg:province":"NSW",
    "sg:tags":[
        "menswear"
    ],
    "wof:name":"Nick Brown Menswear",
    "wof:placetype":"venue"
},
  "geometry": {"coordinates":[151.21641540499999,-33.8815422058],"type":"Point"}
}