{
  "type": "Feature",
  "properties": {
    "iso:country":"AU",
    "sg:address":"2/ 4 Warringah Cl",
    "sg:city":"Somersby",
    "sg:classifiers":[
        {
            "category":"Autos & Motor Vehicles",
            "subcategory":"Auto Supplies",
            "type":"Retail Goods"
        }
    ],
    "sg:phone":"+61 2 4340 2355",
    "sg:postcode":"2250",
    "sg:province":"NSW",
    "sg:tags":[
        "part",
        "cycles",
        "accessory"
    ],
    "wof:name":"Nolathane",
    "wof:placetype":"venue"
},
  "geometry": {"coordinates":[151.27992248499999,-33.3779792786],"type":"Point"}
}