{
  "type": "Feature",
  "properties": {
    "addr:full":"2/ 93 Jedda Rd Prestons NSW 2170",
    "addr:housenumber":"/ 93",
    "addr:postcode":"2170",
    "addr:street":"Jedda Rd",
    "iso:country":"AU",
    "sg:address":"2/ 93 Jedda Rd",
    "sg:city":"Prestons",
    "sg:classifiers":[
        {
            "category":"Food & Beverages",
            "subcategory":"Specialty",
            "type":"Retail Goods"
        }
    ],
    "sg:phone":"+61 2 9608 0644",
    "sg:postcode":"2170",
    "sg:province":"NSW",
    "sg:tags":[
        "product",
        "health"
    ],
    "wof:name":"Rhinos Australia",
    "wof:placetype":"venue"
},
  "geometry": {"coordinates":[150.87626648,-33.9329872131],"type":"Point"}
}