{
  "type": "Feature",
  "properties": {
    "addr:full":"239 Hare St Echuca VIC 3564",
    "addr:housenumber":"239",
    "addr:postcode":"3564",
    "addr:street":"Hare St",
    "iso:country":"AU",
    "sg:address":"239 Hare St",
    "sg:city":"Echuca",
    "sg:classifiers":[
        {
            "category":"Travel",
            "subcategory":"Hotels & Motels",
            "type":"Entertainment"
        }
    ],
    "sg:phone":"+61 3 5482 5044",
    "sg:postcode":"3564",
    "sg:province":"VIC",
    "sg:tags":[
        "accommodation"
    ],
    "wof:name":"American Hotel The",
    "wof:placetype":"venue"
},
  "geometry": {"coordinates":[144.748443603,-36.1242218018],"type":"Point"}
}