{
  "type": "Feature",
  "properties": {
    "iso:country":"AU",
    "sg:address":"40 Archibald St",
    "sg:city":"Padstow",
    "sg:phone":"+61 438 677 027",
    "sg:postcode":"2211",
    "sg:province":"NSW",
    "wof:name":"Rainwater Garden Tanks",
    "wof:placetype":"venue"
},
  "geometry": {"coordinates":[151.024338,-33.944996],"type":"Point"}
}