{
  "type": "Feature",
  "properties": {
    "addr:full":"3/ 155 Denman Ave Caringbah NSW 2229",
    "addr:housenumber":"/ 155",
    "addr:postcode":"2229",
    "addr:street":"Denman Ave",
    "iso:country":"AU",
    "sg:address":"3/ 155 Denman Ave",
    "sg:city":"Caringbah",
    "sg:classifiers":[
        {
            "category":"School Buses",
            "type":"Transportation"
        }
    ],
    "sg:phone":"+61 2 9526 8810",
    "sg:postcode":"2229",
    "sg:province":"NSW",
    "sg:tags":[
        "nanny"
    ],
    "wof:name":"Childcare Direct",
    "wof:placetype":"venue"
},
  "geometry": {"coordinates":[151.12272644000001,-34.0411605835],"type":"Point"}
}