{
  "type": "Feature",
  "properties": {
    "iso:country":"AU",
    "sg:address":"11 Maneela St",
    "sg:city":"Forster",
    "sg:classifiers":[
        {
            "category":"Building & Trades",
            "subcategory":"Construction",
            "type":"Services"
        }
    ],
    "sg:phone":"+61 2 6554 8898",
    "sg:postcode":"2428",
    "sg:province":"NSW",
    "sg:tags":[
        "fencing",
        "contractor"
    ],
    "wof:name":"Straightline Quality Fencing",
    "wof:placetype":"venue"
},
  "geometry": {"coordinates":[152.518631,-32.181255],"type":"Point"}
}