{
  "type": "Feature",
  "properties": {
    "iso:country":"AU",
    "sg:address":"26 Cambridge St",
    "sg:city":"Collingwood",
    "sg:classifiers":[
        {
            "category":"Professional",
            "subcategory":"Employment Agencies",
            "type":"Services"
        }
    ],
    "sg:phone":"+61 3 9419 4705",
    "sg:postcode":"3066",
    "sg:province":"VIC",
    "wof:name":"Caretakers (Aust)",
    "wof:placetype":"venue"
},
  "geometry": {"coordinates":[144.985107422,-37.807926178],"type":"Point"}
}