{
  "type": "Feature",
  "properties": {
    "addr:full":"1271 Grand Junction Rd Hope Valley SA 5090",
    "addr:housenumber":"1271",
    "addr:postcode":"5090",
    "addr:street":"Grand Junction Rd",
    "iso:country":"AU",
    "sg:address":"1271 Grand Junction Rd",
    "sg:city":"Hope Valley",
    "sg:classifiers":[
        {
            "category":"Communications",
            "subcategory":"Film & Video Production",
            "type":"Services"
        }
    ],
    "sg:phone":"+61 8 8265 5480",
    "sg:postcode":"5090",
    "sg:province":"SA",
    "sg:tags":[
        "print",
        "poster",
        "wholesale",
        "pictures"
    ],
    "wof:name":"Pinnacle Art Editions",
    "wof:placetype":"venue"
},
  "geometry": {"coordinates":[138.705368042,-34.8427352905],"type":"Point"}
}