{
  "type": "Feature",
  "properties": {
    "addr:full":"30 Crosby Rd Albion QLD 4010",
    "addr:housenumber":"30",
    "addr:postcode":"4010",
    "addr:street":"Crosby Rd",
    "iso:country":"AU",
    "sg:address":"30 Crosby Rd",
    "sg:city":"Albion",
    "sg:classifiers":[
        {
            "category":"Professional",
            "subcategory":"Printing & Photocopies",
            "type":"Services"
        }
    ],
    "sg:phone":"+61 7 3262 5577",
    "sg:postcode":"4010",
    "sg:province":"QLD",
    "sg:tags":[
        "photocopying"
    ],
    "wof:name":"A-AAAPrint & Copier Technology",
    "wof:placetype":"venue"
},
  "geometry": {"coordinates":[153.04496765100001,-27.4321956635],"type":"Point"}
}