{
  "type": "Feature",
  "properties": {
    "addr:full":"76 Through Rd Burwood VIC 3125",
    "addr:housenumber":"76",
    "addr:postcode":"3125",
    "addr:street":"Through Rd",
    "iso:country":"AU",
    "sg:address":"76 Through Rd",
    "sg:city":"Burwood",
    "sg:classifiers":[
        {
            "category":"Building & Trades",
            "subcategory":"Cleaning & Sanitation",
            "type":"Services"
        }
    ],
    "sg:phone":"+61 3 9883 5500",
    "sg:postcode":"3125",
    "sg:province":"VIC",
    "sg:tags":[
        "cleaner",
        "repairer",
        "roof"
    ],
    "wof:name":"Australian Roofing",
    "wof:placetype":"venue"
},
  "geometry": {"coordinates":[145.089279175,-37.8426208496],"type":"Point"}
}