{
  "type": "Feature",
  "properties": {
    "iso:country":"AU",
    "sg:address":"15 Morley Pl",
    "sg:city":"Albany",
    "sg:classifiers":[
        {
            "category":"Utilities",
            "subcategory":"Water",
            "type":"Services"
        }
    ],
    "sg:phone":"+61 8 9841 6422",
    "sg:postcode":"6330",
    "sg:province":"WA",
    "sg:tags":[
        "hot",
        "system"
    ],
    "wof:name":"Great Western Plumbing & Heating",
    "wof:placetype":"venue"
},
  "geometry": {"coordinates":[117.911911011,-35.0271911621],"type":"Point"}
}