{
  "type": "Feature",
  "properties": {
    "addr:full":"142 West Ave Wynnum QLD 4178",
    "addr:housenumber":"142",
    "addr:postcode":"4178",
    "addr:street":"West Ave",
    "iso:country":"AU",
    "sg:address":"142 West Ave",
    "sg:city":"Wynnum",
    "sg:classifiers":[
        {
            "category":"Personal",
            "subcategory":"Beauty Salon",
            "type":"Services"
        }
    ],
    "sg:phone":"+61 408 195 552",
    "sg:postcode":"4178",
    "sg:province":"QLD",
    "sg:tags":[
        "hairdresser"
    ],
    "wof:name":"Dragonfly Hair Extension Studio",
    "wof:placetype":"venue"
},
  "geometry": {"coordinates":[153.16606140100001,-27.4508361816],"type":"Point"}
}