{
  "type": "Feature",
  "properties": {
    "addr:full":"Rear 58 Bell St Mall Heidelberg West VIC 3081",
    "addr:housenumber":"58",
    "addr:postcode":"3081",
    "addr:street":"Bell St Mall",
    "iso:country":"AU",
    "sg:address":"Rear 58 Bell St Mall",
    "sg:city":"Heidelberg West",
    "sg:classifiers":[
        {
            "category":"Retail",
            "subcategory":"Laundry & Dry Cleaning",
            "type":"Services"
        }
    ],
    "sg:phone":"+61 3 9459 1959",
    "sg:postcode":"3081",
    "sg:province":"VIC",
    "wof:name":"Heidelberg West",
    "wof:placetype":"venue"
},
  "geometry": {"coordinates":[145.05416870100001,-37.7540473938],"type":"Point"}
}