{
  "type": "Feature",
  "properties": {
    "addr:full":"PO Box 4117 South Mackay QLD 4740",
    "addr:postcode":"4740",
    "iso:country":"AU",
    "sg:address":"PO Box 4117",
    "sg:city":"South Mackay",
    "sg:classifiers":[
        {
            "category":"Building & Trades",
            "subcategory":"Construction",
            "type":"Services"
        }
    ],
    "sg:phone":"+61 7 4942 6369",
    "sg:postcode":"4740",
    "sg:province":"QLD",
    "sg:tags":[
        "industrial",
        "commercial",
        "air conditioning"
    ],
    "wof:name":"Glenella Electrical & Air Conditioning",
    "wof:placetype":"venue"
},
  "geometry": {"coordinates":[149.174026,-21.160549],"type":"Point"}
}