{
  "type": "Feature",
  "properties": {
    "addr:full":"Level 3/ 60 Collins St Melbourne VIC 3000",
    "addr:housenumber":"/ 60",
    "addr:postcode":"3000",
    "addr:street":"Collins St",
    "iso:country":"AU",
    "sg:address":"Level 3/ 60 Collins St",
    "sg:city":"Melbourne",
    "sg:classifiers":[
        {
            "category":"Professional",
            "subcategory":"Accounting & Tax Preparation",
            "type":"Services"
        }
    ],
    "sg:phone":"+61 3 9663 0333",
    "sg:postcode":"3000",
    "sg:province":"VIC",
    "sg:tags":[
        "accountant",
        "auditor"
    ],
    "wof:name":"Hayes Knight Private Clients",
    "wof:placetype":"venue"
},
  "geometry": {"coordinates":[144.97174072300001,-37.8138237],"type":"Point"}
}