{
  "type": "Feature",
  "properties": {
    "addr:full":"Suite 2/ 4 Sarich Way Bentley WA 6102",
    "addr:housenumber":"4",
    "addr:postcode":"6102",
    "addr:street":"Sarich Way",
    "iso:country":"AU",
    "sg:address":"Suite 2/ 4 Sarich Way",
    "sg:city":"Bentley",
    "sg:classifiers":[
        {
            "category":"Professional",
            "subcategory":"Computer Services",
            "type":"Services"
        }
    ],
    "sg:phone":"+61 8 9472 4522",
    "sg:postcode":"6102",
    "sg:province":"WA",
    "sg:tags":[
        "package",
        "software"
    ],
    "wof:name":"Intercad (WA) Pty Ltd",
    "wof:placetype":"venue"
},
  "geometry": {"coordinates":[115.89206695599999,-31.9964866638],"type":"Point"}
}