{
  "type": "Feature",
  "properties": {
    "iso:country":"AU",
    "sg:address":"Levle 1/ 134",
    "sg:city":"The Parade Norwood",
    "sg:classifiers":[
        {
            "category":"Banks & Credit Unions",
            "subcategory":"Investment Brokerage",
            "type":"Services"
        }
    ],
    "sg:phone":"+61 8 8125 8898",
    "sg:postcode":"5067",
    "sg:province":"SA",
    "sg:tags":[
        "finance",
        "broker"
    ],
    "wof:name":"Loan Shack",
    "wof:placetype":"venue"
},
  "geometry": {"coordinates":[138.63276672399999,-34.92137146],"type":"Point"}
}