{
  "type": "Feature",
  "properties": {
    "iso:country":"AU",
    "sg:address":"20 East St",
    "sg:city":"Toowoomba",
    "sg:classifiers":[
        {
            "category":"Real Estate",
            "subcategory":"Architect",
            "type":"Services"
        }
    ],
    "sg:phone":"+61 7 4632 7000",
    "sg:postcode":"4350",
    "sg:province":"QLD",
    "wof:name":"Brammer P F Pty Ltd",
    "wof:placetype":"venue"
},
  "geometry": {"coordinates":[151.9785,-27.55962],"type":"Point"}
}