{
  "type": "Feature",
  "properties": {
    "addr:full":"1 Mellish St Beechworth VIC 3747",
    "addr:housenumber":"1",
    "addr:postcode":"3747",
    "addr:street":"Mellish St",
    "iso:country":"AU",
    "sg:address":"1 Mellish St",
    "sg:city":"Beechworth",
    "sg:classifiers":[
        {
            "category":"Insurance",
            "subcategory":"Hazard Insurance",
            "type":"Services"
        }
    ],
    "sg:phone":"+61 3 5728 2971",
    "sg:postcode":"3747",
    "sg:province":"VIC",
    "sg:tags":[
        "fire",
        "accident",
        "marine"
    ],
    "wof:name":"Nelanc Insurance Broking Services Pty Ltd",
    "wof:placetype":"venue"
},
  "geometry": {"coordinates":[146.68301399999999,-36.366127],"type":"Point"}
}