{
  "type": "Feature",
  "properties": {
    "iso:country":"AU",
    "sg:address":"Suite 2/ 22 Harris St",
    "sg:city":"Fairfield",
    "sg:classifiers":[
        {
            "category":"Professional",
            "subcategory":"Accounting & Tax Preparation",
            "type":"Services"
        }
    ],
    "sg:phone":"+61 2 9755 5445",
    "sg:postcode":"2165",
    "sg:province":"NSW",
    "sg:tags":[
        "consultant",
        "taxation"
    ],
    "wof:name":"Said Medhat",
    "wof:placetype":"venue"
},
  "geometry": {"coordinates":[150.94841003400001,-33.8717689514],"type":"Point"}
}