{
  "type": "Feature",
  "properties": {
    "addr:full":"Victoria St St George QLD 4487",
    "addr:postcode":"4487",
    "addr:street":"Victoria St",
    "iso:country":"AU",
    "sg:address":"Victoria St St",
    "sg:city":"George",
    "sg:classifiers":[
        {
            "category":"Banks & Credit Unions",
            "subcategory":"Financial Services",
            "type":"Services"
        }
    ],
    "sg:phone":"+61 7 4625 3469",
    "sg:postcode":"4487",
    "sg:province":"QLD",
    "sg:tags":[
        "building",
        "society"
    ],
    "wof:name":"Heritage Building Society Limited",
    "wof:placetype":"venue"
},
  "geometry": {"coordinates":[148.580688477,-28.0360832214],"type":"Point"}
}