{
  "type": "Feature",
  "properties": {
    "addr:full":"1236 Stumpy Gully Rd Moorooduc VIC 3933",
    "addr:housenumber":"1236",
    "addr:postcode":"3933",
    "addr:street":"Stumpy Gully Rd",
    "iso:country":"AU",
    "sg:address":"1236 Stumpy Gully Rd",
    "sg:city":"Moorooduc",
    "sg:classifiers":[
        {
            "category":"Real Estate",
            "subcategory":"Architect",
            "type":"Services"
        }
    ],
    "sg:phone":"+61 3 5978 8666",
    "sg:postcode":"3933",
    "sg:province":"VIC",
    "wof:name":"Nick Veltjens",
    "wof:placetype":"venue"
},
  "geometry": {"coordinates":[145.12736511200001,-38.2603569031],"type":"Point"}
}