{
  "type": "Feature",
  "properties": {
    "iso:country":"AU",
    "sg:address":"94 Essex Rd",
    "sg:city":"Mt Waverley",
    "sg:classifiers":[
        {
            "category":"Education",
            "subcategory":"Kindergarten",
            "type":"Public Place"
        }
    ],
    "sg:phone":"+61 3 9807 9710",
    "sg:postcode":"3149",
    "sg:province":"VIC",
    "sg:tags":[
        "pre-schools"
    ],
    "wof:name":"St Luke's Pre-School Centre",
    "wof:placetype":"venue"
},
  "geometry": {"coordinates":[145.12310790999999,-37.8637771606],"type":"Point"}
}