{
  "type": "Feature",
  "properties": {
    "addr:full":"1/ 483 Newman Rd Geebung QLD 4034",
    "addr:housenumber":"/ 483",
    "addr:postcode":"4034",
    "addr:street":"Newman Rd",
    "iso:country":"AU",
    "sg:address":"1/ 483 Newman Rd",
    "sg:city":"Geebung",
    "sg:phone":"+61 1800 606 140",
    "sg:postcode":"4034",
    "sg:province":"QLD",
    "sg:website":"http://www.aussiewaterwizards.com.au",
    "wof:name":"Aussie Water Wizards",
    "wof:placetype":"venue"
},
  "geometry": {"coordinates":[153.049286,-27.36235],"type":"Point"}
}