{
  "type": "Feature",
  "properties": {
    "addr:full":"Floor 4 29 Crombie Ave Bundall QLD 4217",
    "addr:housenumber":"29",
    "addr:postcode":"4217",
    "addr:street":"Crombie Ave",
    "iso:country":"AU",
    "sg:address":"Floor 4 29 Crombie Ave",
    "sg:city":"Bundall",
    "sg:classifiers":[
        {
            "category":"Banks & Credit Unions",
            "subcategory":"Investment Brokerage",
            "type":"Services"
        }
    ],
    "sg:phone":"+61 7 5574 0555",
    "sg:postcode":"4217",
    "sg:province":"QLD",
    "sg:tags":[
        "debt",
        "collection"
    ],
    "wof:name":"National Credit Watch",
    "wof:placetype":"venue"
},
  "geometry": {"coordinates":[153.41244506800001,-28.0029888153],"type":"Point"}
}