{
  "type": "Feature",
  "properties": {
    "iso:country":"AU",
    "sg:address":"5 Mayvic St",
    "sg:city":"Greenacre",
    "sg:classifiers":[
        {
            "category":"Retail",
            "subcategory":"Auto Repair",
            "type":"Services"
        }
    ],
    "sg:phone":"+61 2 9742 1197",
    "sg:postcode":"2190",
    "sg:province":"NSW",
    "sg:tags":[
        "repairer",
        "motor",
        "engineer"
    ],
    "wof:name":"Alberts Mechanical Repairs",
    "wof:placetype":"venue"
},
  "geometry": {"coordinates":[151.068787,-33.898327],"type":"Point"}
}