{
  "type": "Feature",
  "properties": {
    "addr:full":"1st Floor Suite 6 30- 32 Ellingworth Pde Box Hill VIC 3128",
    "addr:housenumber":"30 32",
    "addr:postcode":"3128",
    "addr:street":"Ellingworth Pde",
    "iso:country":"AU",
    "sg:address":"1st Floor Suite 6 30- 32 Ellingworth Pde",
    "sg:city":"Box Hill",
    "sg:classifiers":[
        {
            "category":"Education",
            "subcategory":"University",
            "type":"Public Place"
        }
    ],
    "sg:phone":"+61 3 9899 2000",
    "sg:postcode":"3128",
    "sg:province":"VIC",
    "sg:tags":[
        "educational",
        "organisation",
        "cultural"
    ],
    "wof:name":"Victorian Adventist Education Foundation",
    "wof:placetype":"venue"
},
  "geometry": {"coordinates":[145.126785278,-37.820930481],"type":"Point"}
}