{
  "type": "Feature",
  "properties": {
    "addr:full":"Suite 4/ 493 Riversdale Rd Camberwell VIC 3124",
    "addr:housenumber":"/ 493",
    "addr:postcode":"3124",
    "addr:street":"Riversdale Rd",
    "iso:country":"AU",
    "sg:address":"Suite 4/ 493 Riversdale Rd",
    "sg:city":"Camberwell",
    "sg:classifiers":[
        {
            "category":"Professional",
            "subcategory":"Management & Consulting",
            "type":"Services"
        }
    ],
    "sg:phone":"+61 3 9813 5959",
    "sg:postcode":"3124",
    "sg:province":"VIC",
    "sg:tags":[
        "consultant",
        "business"
    ],
    "wof:name":"Scenario Consulting Pty Ltd",
    "wof:placetype":"venue"
},
  "geometry": {"coordinates":[145.056884766,-37.8312301636],"type":"Point"}
}