{
  "type": "Feature",
  "properties": {
    "addr:full":"Shop 2 / 10 James Street Yeppoon QLD 4703",
    "addr:housenumber":"shop 2 / 10",
    "addr:postcode":"4703",
    "addr:street":"James Street",
    "iso:country":"AU",
    "sg:address":"Shop 2 / 10 James Street",
    "sg:city":"Yeppoon",
    "sg:classifiers":[
        {
            "category":"Real Estate",
            "subcategory":"Real Estate Agent",
            "type":"Services"
        }
    ],
    "sg:phone":"+61 7 4939 5088",
    "sg:postcode":"4703",
    "sg:province":"QLD",
    "wof:name":"Ray White (Yeppoon)",
    "wof:placetype":"venue"
},
  "geometry": {"coordinates":[150.74659729000001,-23.1290473938],"type":"Point"}
}