{
  "type": "Feature",
  "properties": {
    "addr:full":"12 Hurt Pde Unanderra NSW 2526",
    "addr:housenumber":"12",
    "addr:postcode":"2526",
    "addr:street":"Hurt Pde",
    "iso:country":"AU",
    "sg:address":"12 Hurt Pde",
    "sg:city":"Unanderra",
    "sg:classifiers":[
        {
            "category":"Bars & Pubs",
            "subcategory":"Nightclub",
            "type":"Food & Drink"
        }
    ],
    "sg:phone":"+61 2 4271 7976",
    "sg:postcode":"2526",
    "sg:province":"NSW",
    "sg:tags":[
        "karaoke"
    ],
    "wof:name":"Street Talk Entertainment",
    "wof:placetype":"venue"
},
  "geometry": {"coordinates":[150.84770202600001,-34.4507331848],"type":"Point"}
}