{
  "type": "Feature",
  "properties": {
    "addr:full":"23 Kingston Drv Dingley Village VIC 3172",
    "addr:housenumber":"23",
    "addr:postcode":"3172",
    "addr:street":"Kingston Drv",
    "iso:country":"AU",
    "sg:address":"23 Kingston Drv",
    "sg:city":"Dingley Village",
    "sg:classifiers":[
        {
            "category":"Education",
            "subcategory":"Music School",
            "type":"Public Place"
        }
    ],
    "sg:phone":"+61 3 9551 7363",
    "sg:postcode":"3172",
    "sg:province":"VIC",
    "sg:tags":[
        "choir",
        "bands",
        "orchestra"
    ],
    "wof:name":"Mike McKeon Music",
    "wof:placetype":"venue"
},
  "geometry": {"coordinates":[145.11776733400001,-37.9785194397],"type":"Point"}
}