{
  "type": "Feature",
  "properties": {
    "iso:country":"AU",
    "sg:address":"Shop B15, 131 William St",
    "sg:city":"Perth",
    "sg:classifiers":[
        {
            "category":"Internet Cafe",
            "subcategory":"None",
            "type":"Food & Drink"
        }
    ],
    "sg:phone":"+61 8 9226 5373",
    "sg:postcode":"6805",
    "sg:province":"WA",
    "wof:name":"Internet Station",
    "wof:placetype":"venue"
},
  "geometry": {"coordinates":[115.857239,-31.95302],"type":"Point"}
}