{
  "type": "Feature",
  "properties": {
    "addr:full":"Main Rd Branxholm TAS 7261",
    "addr:postcode":"7261",
    "addr:street":"Main Rd",
    "iso:country":"AU",
    "sg:address":"Main Rd",
    "sg:city":"Branxholm",
    "sg:classifiers":[
        {
            "category":"Autos & Motor Vehicles",
            "subcategory":"Fuel & Gas Station",
            "type":"Retail Goods"
        }
    ],
    "sg:phone":"+61 3 6354 6168",
    "sg:postcode":"7261",
    "sg:province":"TAS",
    "wof:name":"BP Australia Limited",
    "wof:placetype":"venue"
},
  "geometry": {"coordinates":[147.69291687,-41.2142105103],"type":"Point"}
}