{
  "type": "Feature",
  "properties": {
    "addr:full":"Shop 4 Freshfields Shopping Centre Proserpine QLD 4800",
    "addr:housenumber":"shop 4",
    "addr:postcode":"4800",
    "addr:street":"Freshfields Shopping",
    "iso:country":"AU",
    "sg:address":"Shop 4 Freshfields Shopping Centre",
    "sg:city":"Proserpine",
    "sg:classifiers":[
        {
            "category":"Shopping",
            "subcategory":"Clothing, Apparel, & Fashions",
            "type":"Retail Goods"
        }
    ],
    "sg:phone":"+61 7 4945 3442",
    "sg:postcode":"4800",
    "sg:province":"QLD",
    "sg:tags":[
        "lady",
        "wear"
    ],
    "wof:name":"Sue Fellows Fashion Boutique",
    "wof:placetype":"venue"
},
  "geometry": {"coordinates":[148.59341430699999,-20.4060001373],"type":"Point"}
}