{
  "type": "Feature",
  "properties": {
    "addr:full":"26 Chapman Ave Linden NSW 2778",
    "addr:housenumber":"26",
    "addr:postcode":"2778",
    "addr:street":"Chapman Ave",
    "iso:country":"AU",
    "sg:address":"26 Chapman Ave",
    "sg:city":"Linden",
    "sg:classifiers":[
        {
            "category":"Building & Trades",
            "subcategory":"Construction",
            "type":"Services"
        }
    ],
    "sg:phone":"+61 2 4753 1217",
    "sg:postcode":"2778",
    "sg:province":"NSW",
    "sg:tags":[
        "contractor"
    ],
    "wof:name":"Linden Constructions",
    "wof:placetype":"venue"
},
  "geometry": {"coordinates":[150.51484680199999,-33.7157592773],"type":"Point"}
}