{
  "type": "Feature",
  "properties": {
    "addr:full":"20 Grey Gum Rd Taree NSW 2430",
    "addr:housenumber":"20",
    "addr:postcode":"2430",
    "addr:street":"Grey Gum Rd",
    "iso:country":"AU",
    "sg:address":"20 Grey Gum Rd",
    "sg:city":"Taree",
    "sg:classifiers":[
        {
            "category":"Autos & Motor Vehicles",
            "subcategory":"Auto Supplies",
            "type":"Retail Goods"
        }
    ],
    "sg:phone":"+61 2 6552 4363",
    "sg:postcode":"2430",
    "sg:province":"NSW",
    "sg:tags":[
        "tyre"
    ],
    "wof:name":"Manning Tyre & Battery Service",
    "wof:placetype":"venue"
},
  "geometry": {"coordinates":[152.45141599999999,-31.89535],"type":"Point"}
}