{
  "type": "Feature",
  "properties": {
    "iso:country":"AU",
    "sg:address":"150 Murray St",
    "sg:city":"Allenstown",
    "sg:classifiers":[
        {
            "category":"Health Services",
            "subcategory":"Dentist",
            "type":"Services"
        }
    ],
    "sg:phone":"+61 7 4922 8344",
    "sg:postcode":"4700",
    "sg:province":"QLD",
    "sg:tags":[
        "dental",
        "prosthetist"
    ],
    "wof:name":"Rockhampton Denture Clinic",
    "wof:placetype":"venue"
},
  "geometry": {"coordinates":[150.505249023,-23.3826465607],"type":"Point"}
}