{
  "type": "Feature",
  "properties": {
    "addr:full":"60- 62 Georges River Crs Oyster Bay NSW 2225",
    "addr:housenumber":"62",
    "addr:postcode":"2225",
    "addr:street":"Georges River Crs",
    "iso:country":"AU",
    "sg:address":"60- 62 Georges River Crs",
    "sg:city":"Oyster Bay",
    "sg:classifiers":[
        {
            "category":"Education",
            "subcategory":"Kindergarten",
            "type":"Public Place"
        }
    ],
    "sg:phone":"+61 2 9528 4982",
    "sg:postcode":"2225",
    "sg:province":"NSW",
    "sg:tags":[
        "pre-schools"
    ],
    "wof:name":"Oyster Bay Pre-School Kindergarten",
    "wof:placetype":"venue"
},
  "geometry": {"coordinates":[151.073486328,-34.011592865],"type":"Point"}
}