{
  "type": "Feature",
  "properties": {
    "addr:full":"Suite 6, 35- 59 Main St Greensborough VIC 3088",
    "addr:housenumber":"35 59",
    "addr:postcode":"3088",
    "addr:street":"Main St",
    "iso:country":"AU",
    "sg:address":"Suite 6, 35- 59 Main St",
    "sg:city":"Greensborough",
    "sg:classifiers":[
        {
            "category":"Personal",
            "type":"Services"
        }
    ],
    "sg:phone":"+61 418 557 503",
    "sg:postcode":"3088",
    "sg:province":"VIC",
    "sg:tags":[
        "career",
        "counselling"
    ],
    "wof:name":"Kaizen Trak",
    "wof:placetype":"venue"
},
  "geometry": {"coordinates":[145.10438537600001,-37.703163147],"type":"Point"}
}