{
  "type": "Feature",
  "properties": {
    "addr:full":"23a Napoleon St Cottesloe WA 6011",
    "addr:housenumber":"23a",
    "addr:postcode":"6011",
    "addr:street":"Napoleon St",
    "iso:country":"AU",
    "sg:address":"23a Napoleon St",
    "sg:city":"Cottesloe",
    "sg:classifiers":[
        {
            "category":"Shopping",
            "subcategory":"Optical Goods",
            "type":"Retail Goods"
        }
    ],
    "sg:phone":"+61 8 9385 4223",
    "sg:postcode":"6011",
    "sg:province":"WA",
    "sg:tags":[
        "dispenser",
        "prescription"
    ],
    "wof:name":"Specialeyes",
    "wof:placetype":"venue"
},
  "geometry": {"coordinates":[115.76219940199999,-31.9980430603],"type":"Point"}
}