{
  "type": "Feature",
  "properties": {
    "addr:full":"63 Beringarra Ave Malaga WA 6090",
    "addr:housenumber":"63",
    "addr:postcode":"6090",
    "addr:street":"Beringarra Ave",
    "iso:country":"AU",
    "sg:address":"63 Beringarra Ave",
    "sg:city":"Malaga",
    "sg:classifiers":[
        {
            "category":"Autos & Motor Vehicles",
            "subcategory":"Auto Supplies",
            "type":"Retail Goods"
        }
    ],
    "sg:phone":"+61 8 9203 1000",
    "sg:postcode":"6090",
    "sg:province":"WA",
    "sg:tags":[
        "turbochargers"
    ],
    "wof:name":"MTQ Engine Systems (Aust)",
    "wof:placetype":"venue"
},
  "geometry": {"coordinates":[115.90074157700001,-31.8638553619],"type":"Point"}
}