{
  "type": "Feature",
  "properties": {
    "addr:full":"Cnr Mount Dandenong Rd & Civic Square Croydon VIC 3136",
    "addr:postcode":"3136",
    "addr:street":"Cnr Mount Dandenong Rd &;Square",
    "iso:country":"AU",
    "sg:address":"Cnr Mount Dandenong Rd",
    "sg:city":"& Civic Square Croydon",
    "sg:classifiers":[
        {
            "category":"Autos & Motor Vehicles",
            "subcategory":"Auto Supplies",
            "type":"Retail Goods"
        }
    ],
    "sg:phone":"+61 3 9722 9366",
    "sg:postcode":"3136",
    "sg:province":"VIC",
    "sg:tags":[
        "tyre"
    ],
    "wof:name":"Kmart Tyre & Auto Service",
    "wof:placetype":"venue"
},
  "geometry": {"coordinates":[145.27972412099999,-37.7989311218],"type":"Point"}
}