{
  "type": "Feature",
  "properties": {
    "iso:country":"AU",
    "sg:address":"Cnr Richardson Road",
    "sg:city":"& Denning Street North Rockhampton",
    "sg:classifiers":[
        {
            "category":"Health Services",
            "subcategory":"Optometrist",
            "type":"Services"
        }
    ],
    "sg:phone":"+61 7 4928 0650",
    "sg:postcode":"4701",
    "sg:province":"QLD",
    "wof:name":"Lawrie & Taylor Optometrists",
    "wof:placetype":"venue"
},
  "geometry": {"coordinates":[150.53236389200001,-23.3337421417],"type":"Point"}
}