{
  "type": "Feature",
  "properties": {
    "addr:full":"20- 22 Catalina Drv Tullamarine VIC 3043",
    "addr:housenumber":"22",
    "addr:postcode":"3043",
    "addr:street":"Catalina Drv",
    "iso:country":"AU",
    "sg:address":"20- 22 Catalina Drv",
    "sg:city":"Tullamarine",
    "sg:classifiers":[
        {
            "category":"Shopping",
            "subcategory":"Stationery & Office Supplies",
            "type":"Retail Goods"
        }
    ],
    "sg:phone":"+61 3 8336 3633",
    "sg:postcode":"3043",
    "sg:province":"VIC",
    "sg:tags":[
        "partition"
    ],
    "wof:name":"Quadric Pty Ltd",
    "wof:placetype":"venue"
},
  "geometry": {"coordinates":[144.87965393100001,-37.6888313293],"type":"Point"}
}