{
  "type": "Feature",
  "properties": {
    "iso:country":"AU",
    "sg:address":"25 Thompson St",
    "sg:city":"Drummoyne",
    "sg:classifiers":[
        {
            "category":"Building & Trades",
            "subcategory":"Plumbing",
            "type":"Services"
        }
    ],
    "sg:phone":"+61 418 251 181",
    "sg:postcode":"2047",
    "sg:province":"NSW",
    "sg:tags":[
        "plumber",
        "gasfitters"
    ],
    "wof:name":"Fiorini Ralph Plumbing",
    "wof:placetype":"venue"
},
  "geometry": {"coordinates":[151.153564,-33.857754],"type":"Point"}
}