{
  "type": "Feature",
  "properties": {
    "addr:full":"Cnr Seymour St & Princes Hwy Traralgon VIC 3844",
    "addr:postcode":"3844",
    "addr:street":"Seymour St & Princes Hwy",
    "iso:country":"AU",
    "sg:address":"Cnr Seymour St & Princes Hwy",
    "sg:city":"Traralgon",
    "sg:classifiers":[
        {
            "category":"Retail",
            "subcategory":"Auto Rental",
            "type":"Services"
        }
    ],
    "sg:phone":"+61 3 5174 8155",
    "sg:postcode":"3844",
    "sg:province":"VIC",
    "sg:tags":[
        "bus",
        "truck"
    ],
    "wof:name":"Budget",
    "wof:placetype":"venue"
},
  "geometry": {"coordinates":[146.53765869099999,-38.1961669922],"type":"Point"}
}