{
  "type": "Feature",
  "properties": {
    "addr:full":"438 Maitland Road Mayfield West NSW 2304",
    "addr:housenumber":"438",
    "addr:postcode":"2304",
    "addr:street":"Maitland Road",
    "iso:country":"AU",
    "sg:address":"438 Maitland Road",
    "sg:city":"Mayfield West",
    "sg:classifiers":[
        {
            "category":"Retail",
            "subcategory":"Car Wash",
            "type":"Services"
        }
    ],
    "sg:phone":"+61 2 4960 2111",
    "sg:postcode":"2304",
    "sg:province":"NSW",
    "sg:tags":[
        "truck",
        "cleaning"
    ],
    "wof:name":"Newcastle Carwash",
    "wof:placetype":"venue"
},
  "geometry": {"coordinates":[151.72793579099999,-32.8910064697],"type":"Point"}
}