{
  "type": "Feature",
  "properties": {
    "addr:full":"Level 1 125 Pirie St Adelaide SA 5000",
    "addr:housenumber":"125",
    "addr:postcode":"5000",
    "addr:street":"Pirie St",
    "iso:country":"AU",
    "sg:address":"Level 1 125 Pirie St",
    "sg:city":"Adelaide",
    "sg:classifiers":[
        {
            "category":"Government",
            "subcategory":"Post Office",
            "type":"Public Place"
        }
    ],
    "sg:phone":"+61 8 8223 3463",
    "sg:postcode":"5000",
    "sg:province":"SA",
    "sg:tags":[
        "yoga"
    ],
    "wof:name":"Bikram Yoga College of India Adelaide",
    "wof:placetype":"venue"
},
  "geometry": {"coordinates":[138.60435485799999,-34.9256668091],"type":"Point"}
}