{
  "type": "Feature",
  "properties": {
    "addr:full":"8 Awabi Crt Port Fairy VIC 3284",
    "addr:housenumber":"8",
    "addr:postcode":"3284",
    "addr:street":"Awabi Crt",
    "iso:country":"AU",
    "sg:address":"8 Awabi Crt",
    "sg:city":"Port Fairy",
    "sg:classifiers":[
        {
            "category":"Wholesale",
            "subcategory":"Machinery & Supplies",
            "type":"Manufacturing & Wholesale Goods"
        }
    ],
    "sg:phone":"+61 3 5568 3377",
    "sg:postcode":"3284",
    "sg:province":"VIC",
    "sg:tags":[
        "engineer"
    ],
    "wof:name":"South Coast Engineering Pty Ltd",
    "wof:placetype":"venue"
},
  "geometry": {"coordinates":[142.220870972,-38.3835830688],"type":"Point"}
}