{
  "type": "Feature",
  "properties": {
    "iso:country":"AU",
    "sg:address":"81 Cam St",
    "sg:city":"Cambridge Park",
    "sg:classifiers":[
        {
            "category":"Education",
            "subcategory":"Kindergarten",
            "type":"Public Place"
        }
    ],
    "sg:phone":"+61 2 4722 2455",
    "sg:postcode":"2747",
    "sg:province":"NSW",
    "sg:tags":[
        "pre-schools"
    ],
    "wof:name":"Little Joey's Preschool",
    "wof:placetype":"venue"
},
  "geometry": {"coordinates":[150.71824645999999,-33.7512435913],"type":"Point"}
}