{
  "type": "Feature",
  "properties": {
    "addr:full":"31 Gilbert St Adelaide SA 5000",
    "addr:housenumber":"31",
    "addr:postcode":"5000",
    "addr:street":"Gilbert St",
    "iso:country":"AU",
    "sg:address":"31 Gilbert St",
    "sg:city":"Adelaide",
    "sg:classifiers":[
        {
            "category":"Restaurant",
            "type":"Food & Drink"
        }
    ],
    "sg:phone":"+61 8 8410 0511",
    "sg:postcode":"5000",
    "sg:province":"SA",
    "wof:name":"Delish Real Food",
    "wof:placetype":"venue"
},
  "geometry": {"coordinates":[138.59983825699999,-34.9344520569],"type":"Point"}
}