{
  "type": "Feature",
  "properties": {
    "iso:country":"AU",
    "sg:address":"Coles Old Town Mall/ 211 Old South Rd",
    "sg:city":"Old Reynella",
    "sg:classifiers":[
        {
            "category":"Health Services",
            "subcategory":"Chiropractor",
            "type":"Services"
        }
    ],
    "sg:phone":"+61 8 8387 8033",
    "sg:postcode":"5161",
    "sg:province":"SA",
    "wof:name":"Kylie Wingfield & Rowena Pooley",
    "wof:placetype":"venue"
},
  "geometry": {"coordinates":[138.541625977,-35.0886993408],"type":"Point"}
}