{
  "type": "Feature",
  "properties": {
    "addr:full":"Shop 5, Marina Shopping Village, Boardwalk, Santa Barbara Rd Hope Island QLD 4212",
    "addr:housenumber":"shop 5",
    "addr:postcode":"4212",
    "addr:street":"Marina Shopping;Santa Barbara Rd",
    "iso:country":"AU",
    "sg:address":"Shop 5, Marina Shopping Village, Boardwalk, Santa Barbara Rd",
    "sg:city":"Hope Island",
    "sg:classifiers":[
        {
            "category":"Fast Food",
            "type":"Food & Drink"
        }
    ],
    "sg:phone":"+61 7 5510 8882",
    "sg:postcode":"4212",
    "sg:province":"QLD",
    "sg:tags":[
        "away",
        "take"
    ],
    "wof:name":"House Of Siam Thai Restaurant",
    "wof:placetype":"venue"
},
  "geometry": {"coordinates":[153.35121154800001,-27.8684024811],"type":"Point"}
}