{
  "type": "Feature",
  "properties": {
    "addr:full":"22 Telford Drv Shepparton VIC 3630",
    "addr:housenumber":"22",
    "addr:postcode":"3630",
    "addr:street":"Telford Drv",
    "iso:country":"AU",
    "sg:address":"22 Telford Drv",
    "sg:city":"Shepparton",
    "sg:classifiers":[
        {
            "category":"Retail",
            "subcategory":"Auto Repair",
            "type":"Services"
        }
    ],
    "sg:phone":"+61 1800 780 858",
    "sg:postcode":"3630",
    "sg:province":"VIC",
    "sg:tags":[
        "clutch",
        "brake"
    ],
    "wof:name":"NBS Brake Supplies",
    "wof:placetype":"venue"
},
  "geometry": {"coordinates":[145.42869567899999,-36.3764953613],"type":"Point"}
}