{
  "type": "Feature",
  "properties": {
    "iso:country":"AU",
    "sg:address":"Office 11 77 King St",
    "sg:city":"Caboolture",
    "sg:classifiers":[
        {
            "category":"Health Services",
            "subcategory":"Chiropractor",
            "type":"Services"
        }
    ],
    "sg:phone":"+61 7 5495 4991",
    "sg:postcode":"4510",
    "sg:province":"QLD",
    "wof:name":"Bateman Anthony K",
    "wof:placetype":"venue"
},
  "geometry": {"coordinates":[152.95126300000001,-27.085054],"type":"Point"}
}