{
  "type": "Feature",
  "properties": {
    "addr:full":"71 Owen Creek Rd Forest Glen QLD 4556",
    "addr:housenumber":"71",
    "addr:postcode":"4556",
    "addr:street":"Owen Creek Rd",
    "iso:country":"AU",
    "sg:address":"71 Owen Creek Rd",
    "sg:city":"Forest Glen",
    "sg:classifiers":[
        {
            "category":"Retail",
            "subcategory":"Event Space",
            "type":"Services"
        }
    ],
    "sg:phone":"+61 7 5445 6322",
    "sg:postcode":"4556",
    "sg:province":"QLD",
    "sg:tags":[
        "venue",
        "reception",
        "wedding"
    ],
    "wof:name":"Verandahs",
    "wof:placetype":"venue"
},
  "geometry": {"coordinates":[153.00892639200001,-26.6930465698],"type":"Point"}
}