{
  "type": "Feature",
  "properties": {
    "addr:full":"1841 Main North Rd Salisbury Heights SA 5109",
    "addr:housenumber":"1841",
    "addr:postcode":"5109",
    "addr:street":"Main North Rd",
    "iso:country":"AU",
    "sg:address":"1841 Main North Rd",
    "sg:city":"Salisbury Heights",
    "sg:classifiers":[
        {
            "category":"Retail",
            "subcategory":"Auto Repair",
            "type":"Services"
        }
    ],
    "sg:phone":"+61 8 8258 1629",
    "sg:postcode":"5109",
    "sg:province":"SA",
    "sg:tags":[
        "beater",
        "painter",
        "panel"
    ],
    "wof:name":"Caruso Crash Repairs",
    "wof:placetype":"venue"
},
  "geometry": {"coordinates":[138.67601013199999,-34.7583351135],"type":"Point"}
}