{
  "type": "Feature",
  "properties": {
    "addr:full":"48 Kohinoor Rd Kingscote SA 5223",
    "addr:housenumber":"48",
    "addr:postcode":"5223",
    "addr:street":"Kohinoor Rd",
    "iso:country":"AU",
    "sg:address":"48 Kohinoor Rd",
    "sg:city":"Kingscote",
    "sg:classifiers":[
        {
            "category":"Wholesale",
            "subcategory":"Seafood",
            "type":"Manufacturing & Wholesale Goods"
        }
    ],
    "sg:phone":"+61 8 8553 0377",
    "sg:postcode":"5223",
    "sg:province":"SA",
    "sg:tags":[
        "fish"
    ],
    "wof:name":"Ferguson Australia",
    "wof:placetype":"venue"
},
  "geometry": {"coordinates":[137.62869262699999,-35.6523361206],"type":"Point"}
}