{
  "type": "Feature",
  "properties": {
    "iso:country":"AU",
    "sg:address":"Shp1/ 12 West St",
    "sg:city":"Croydon",
    "sg:classifiers":[
        {
            "category":"Professional",
            "subcategory":"Computer Services",
            "type":"Services"
        }
    ],
    "sg:phone":"+61 2 9799 1234",
    "sg:postcode":"2132",
    "sg:province":"NSW",
    "sg:tags":[
        "equipment",
        "networking",
        "installation"
    ],
    "wof:name":"MD Connect Pty Ltd",
    "wof:placetype":"venue"
},
  "geometry": {"coordinates":[151.12550354000001,-33.8739013672],"type":"Point"}
}