{
  "type": "Feature",
  "properties": {
    "addr:full":"132 High St Doncaster VIC 3108",
    "addr:housenumber":"132",
    "addr:postcode":"3108",
    "addr:street":"High St",
    "iso:country":"AU",
    "sg:address":"132 High St",
    "sg:city":"Doncaster",
    "sg:classifiers":[
        {
            "category":"Travel",
            "subcategory":"Travel Agent",
            "type":"Entertainment"
        }
    ],
    "sg:phone":"+61 3 9816 3355",
    "sg:postcode":"3108",
    "sg:province":"VIC",
    "sg:tags":[
        "consultant"
    ],
    "wof:name":"Elite Travel World",
    "wof:placetype":"venue"
},
  "geometry": {"coordinates":[145.11346435600001,-37.778842926],"type":"Point"}
}