{
  "type": "Feature",
  "properties": {
    "addr:full":"8 First St Broadford VIC 3658",
    "addr:housenumber":"8",
    "addr:postcode":"3658",
    "addr:street":"First St",
    "iso:country":"AU",
    "sg:address":"8 First St",
    "sg:city":"Broadford",
    "sg:classifiers":[
        {
            "category":"Wholesale",
            "subcategory":"Machinery & Supplies",
            "type":"Manufacturing & Wholesale Goods"
        }
    ],
    "sg:phone":"+61 3 5784 1351",
    "sg:postcode":"3658",
    "sg:province":"VIC",
    "sg:tags":[
        "engineer"
    ],
    "wof:name":"L.P.R. Tool Makers",
    "wof:placetype":"venue"
},
  "geometry": {"coordinates":[145.036056519,-37.2059020996],"type":"Point"}
}