{
  "type": "Feature",
  "properties": {
    "addr:full":"14 Russell St Woollahra NSW 2025",
    "addr:housenumber":"14",
    "addr:postcode":"2025",
    "addr:street":"Russell St",
    "iso:country":"AU",
    "sg:address":"14 Russell St",
    "sg:city":"Woollahra",
    "sg:classifiers":[
        {
            "category":"Real Estate",
            "subcategory":"Architect",
            "type":"Services"
        }
    ],
    "sg:phone":"+61 2 9369 2474",
    "sg:postcode":"2025",
    "sg:province":"NSW",
    "wof:name":"Szewczyk Edward & Associates",
    "wof:placetype":"venue"
},
  "geometry": {"coordinates":[151.247146606,-33.8877449036],"type":"Point"}
}