{
  "type": "Feature",
  "properties": {
    "addr:full":"58 Governor Macquarie Drv Chipping Norton NSW 2170",
    "addr:housenumber":"58",
    "addr:postcode":"2170",
    "addr:street":"Governor Macquarie Drv",
    "iso:country":"AU",
    "sg:address":"58 Governor Macquarie Drv",
    "sg:city":"Chipping Norton",
    "sg:classifiers":[
        {
            "category":"Building & Trades",
            "subcategory":"Construction",
            "type":"Services"
        }
    ],
    "sg:phone":"+61 1300 652 204",
    "sg:postcode":"2170",
    "sg:province":"NSW",
    "sg:tags":[
        "window",
        "aluminium"
    ],
    "wof:name":"Fantasy Windows & Granite",
    "wof:placetype":"venue"
},
  "geometry": {"coordinates":[150.96202087399999,-33.9222946167],"type":"Point"}
}