{
  "type": "Feature",
  "properties": {
    "addr:full":"598 Pennant Hills Rd West Pennant Hills NSW 2125",
    "addr:housenumber":"598",
    "addr:postcode":"2125",
    "addr:street":"Pennant Hills Rd",
    "iso:country":"AU",
    "sg:address":"598 Pennant Hills Rd",
    "sg:city":"West Pennant Hills",
    "sg:classifiers":[
        {
            "category":"Bars & Pubs",
            "subcategory":"Biergarten",
            "type":"Food & Drink"
        }
    ],
    "sg:phone":"+61 2 9873 6848",
    "sg:postcode":"2125",
    "sg:province":"NSW",
    "sg:tags":[
        "tailor",
        "lady"
    ],
    "wof:name":"Nezz Exclusive Dressmaking & Designing",
    "wof:placetype":"venue"
},
  "geometry": {"coordinates":[151.04783630399999,-33.7527542114],"type":"Point"}
}