{
  "type": "Feature",
  "properties": {
    "addr:full":"31 Longtown St Craigieburn VIC 3064",
    "addr:housenumber":"31",
    "addr:postcode":"3064",
    "addr:street":"Longtown St",
    "iso:country":"AU",
    "sg:address":"31 Longtown St",
    "sg:city":"Craigieburn",
    "sg:classifiers":[
        {
            "category":"Arts & Performance",
            "subcategory":"Music",
            "type":"Entertainment"
        }
    ],
    "sg:phone":"+61 1800 100 606",
    "sg:postcode":"3064",
    "sg:province":"VIC",
    "sg:tags":[
        "mobile",
        "jockey",
        "disc"
    ],
    "wof:name":"Mobydisc",
    "wof:placetype":"venue"
},
  "geometry": {"coordinates":[144.939163208,-37.610118866],"type":"Point"}
}