{
  "type": "Feature",
  "properties": {
    "addr:full":"19/ 243 Ernest St Cammeray NSW 2062",
    "addr:housenumber":"19 / 243",
    "addr:postcode":"2062",
    "addr:street":"Ernest St",
    "iso:country":"AU",
    "sg:address":"19/ 243 Ernest St",
    "sg:city":"Cammeray",
    "sg:classifiers":[
        {
            "category":"Building & Trades",
            "subcategory":"Cleaning & Sanitation",
            "type":"Services"
        }
    ],
    "sg:phone":"+61 412 271 743",
    "sg:postcode":"2062",
    "sg:province":"NSW",
    "sg:tags":[
        "industrial",
        "commercial",
        "contractor"
    ],
    "wof:name":"Ramshankar Associates",
    "wof:placetype":"venue"
},
  "geometry": {"coordinates":[151.21270751899999,-33.8275489807],"type":"Point"}
}