{
  "type": "Feature",
  "properties": {
    "addr:full":"14 Ilma St Bankstown NSW 2200",
    "addr:housenumber":"14",
    "addr:postcode":"2200",
    "addr:street":"Ilma St",
    "iso:country":"AU",
    "sg:address":"14 Ilma St",
    "sg:city":"Bankstown",
    "sg:classifiers":[
        {
            "category":"Building & Trades",
            "subcategory":"Construction",
            "type":"Services"
        }
    ],
    "sg:phone":"+61 2 9771 2575",
    "sg:postcode":"2200",
    "sg:province":"NSW",
    "sg:tags":[
        "equipment",
        "balancing"
    ],
    "wof:name":"Propeller Shaft Services Pty Ltd",
    "wof:placetype":"venue"
},
  "geometry": {"coordinates":[151.013306,-33.93269],"type":"Point"}
}