{
  "type": "Feature",
  "properties": {
    "addr:full":"46 Andrea Pl Riverside TAS 7250",
    "addr:housenumber":"46",
    "addr:postcode":"7250",
    "addr:street":"Andrea Pl",
    "iso:country":"AU",
    "sg:address":"46 Andrea Pl",
    "sg:city":"Riverside",
    "sg:classifiers":[
        {
            "category":"Professional",
            "type":"Services"
        }
    ],
    "sg:phone":"+61 3 6327 3183",
    "sg:postcode":"7250",
    "sg:province":"TAS",
    "sg:tags":[
        "transport"
    ],
    "wof:name":"North East Distributors",
    "wof:placetype":"venue"
},
  "geometry": {"coordinates":[147.091995239,-41.4087486267],"type":"Point"}
}