{
  "type": "Feature",
  "properties": {
    "addr:full":"2 Austral St Malabar NSW 2036",
    "addr:housenumber":"2",
    "addr:postcode":"2036",
    "addr:street":"Austral St",
    "iso:country":"AU",
    "sg:address":"2 Austral St",
    "sg:city":"Malabar",
    "sg:classifiers":[
        {
            "category":"Social Services",
            "subcategory":"Child Care",
            "type":"Services"
        }
    ],
    "sg:phone":"+61 2 9311 4895",
    "sg:postcode":"2036",
    "sg:province":"NSW",
    "wof:name":"John Mewburn Child Care Centre",
    "wof:placetype":"venue"
},
  "geometry": {"coordinates":[151.246017456,-33.9656982422],"type":"Point"}
}