{
  "type": "Feature",
  "properties": {
    "iso:country":"AU",
    "sg:address":"Shop 3, 30 Railway Ave",
    "sg:city":"Thornton",
    "sg:classifiers":[
        {
            "category":"Retail",
            "subcategory":"Veterinary Services",
            "type":"Services"
        }
    ],
    "sg:phone":"+61 2 4966 1133",
    "sg:postcode":"2322",
    "sg:province":"NSW",
    "sg:tags":[
        "surgeon"
    ],
    "wof:name":"Thornton Veterinary Clinic",
    "wof:placetype":"venue"
},
  "geometry": {"coordinates":[151.64120483400001,-32.7837333679],"type":"Point"}
}