{
  "type": "Feature",
  "properties": {
    "addr:full":"Factory 6, 1 Bungaleen Crt Dandenong VIC 3175",
    "addr:housenumber":"1",
    "addr:postcode":"3175",
    "addr:street":"Bungaleen Crt",
    "iso:country":"AU",
    "sg:address":"Factory 6, 1 Bungaleen Crt",
    "sg:city":"Dandenong",
    "sg:classifiers":[
        {
            "category":"Building & Trades",
            "subcategory":"Plumbing",
            "type":"Services"
        }
    ],
    "sg:phone":"+61 3 9768 2233",
    "sg:postcode":"3175",
    "sg:province":"VIC",
    "sg:tags":[
        "fitting",
        "hose",
        "supply"
    ],
    "wof:name":"Pirtek Fluid Systems",
    "wof:placetype":"venue"
},
  "geometry": {"coordinates":[145.20994567899999,-38.0347480774],"type":"Point"}
}