{
  "type": "Feature",
  "properties": {
    "iso:country":"AU",
    "sg:address":"Lot 7 Old Melbourne Rd",
    "sg:city":"Morwell",
    "sg:classifiers":[
        {
            "category":"Building & Trades",
            "subcategory":"Cleaning & Sanitation",
            "type":"Services"
        }
    ],
    "sg:phone":"+61 3 5134 6454",
    "sg:postcode":"3840",
    "sg:province":"VIC",
    "sg:tags":[
        "window"
    ],
    "wof:name":"Morwell Hi-Gloss Cleaning",
    "wof:placetype":"venue"
},
  "geometry": {"coordinates":[146.42120361299999,-38.2013015747],"type":"Point"}
}