{
  "type": "Feature",
  "properties": {
    "addr:full":"33 Churchill St Bardwell Park NSW 2207",
    "addr:housenumber":"33",
    "addr:postcode":"2207",
    "addr:street":"Churchill St",
    "iso:country":"AU",
    "sg:address":"33 Churchill St",
    "sg:city":"Bardwell Park",
    "sg:classifiers":[
        {
            "category":"Building & Trades",
            "subcategory":"Cleaning & Sanitation",
            "type":"Services"
        }
    ],
    "sg:phone":"+61 419 441 138",
    "sg:postcode":"2207",
    "sg:province":"NSW",
    "sg:tags":[
        "industrial",
        "commercial",
        "contractor"
    ],
    "wof:name":"Bardwell Cleaning Services",
    "wof:placetype":"venue"
},
  "geometry": {"coordinates":[151.12240600000001,-33.937099],"type":"Point"}
}