{
  "type": "Feature",
  "properties": {
    "iso:country":"AU",
    "sg:address":"42 Montgomery St",
    "sg:city":"Kogarah",
    "sg:classifiers":[
        {
            "category":"Health Services",
            "subcategory":"Doctor",
            "type":"Services"
        }
    ],
    "sg:phone":"+61 2 9588 1297",
    "sg:postcode":"2217",
    "sg:province":"NSW",
    "sg:tags":[
        "medical",
        "practitioner"
    ],
    "wof:name":"Schiller Peter",
    "wof:placetype":"venue"
},
  "geometry": {"coordinates":[151.13490300000001,-33.964478],"type":"Point"}
}