{
  "type": "Feature",
  "properties": {
    "addr:full":"50 Giles St Katherine NT 0850",
    "addr:housenumber":"50",
    "addr:postcode":"nt 0850",
    "addr:street":"Giles St",
    "iso:country":"AU",
    "sg:address":"50 Giles St",
    "sg:city":"Katherine",
    "sg:classifiers":[
        {
            "category":"Retail",
            "subcategory":"Auto Rental",
            "type":"Services"
        }
    ],
    "sg:phone":"+61 8 8971 1111",
    "sg:postcode":"0850",
    "sg:province":"NT",
    "sg:tags":[
        "car",
        "hire",
        "minibus"
    ],
    "wof:name":"Hertz.",
    "wof:placetype":"venue"
},
  "geometry": {"coordinates":[132.26892100000001,-14.45608],"type":"Point"}
}