{
  "type": "Feature",
  "properties": {
    "iso:country":"AU",
    "sg:address":"Coster St",
    "sg:city":"Benalla",
    "sg:classifiers":[
        {
            "category":"Health Services",
            "subcategory":"Medical Lab",
            "type":"Services"
        }
    ],
    "sg:phone":"+61 3 5760 2277",
    "sg:postcode":"3672",
    "sg:province":"VIC",
    "sg:tags":[
        "laboratory",
        "pathology"
    ],
    "wof:name":"North Eastern Pathology",
    "wof:placetype":"venue"
},
  "geometry": {"coordinates":[145.99529999999999,-36.556572],"type":"Point"}
}