{
  "type": "Feature",
  "properties": {
    "iso:country":"AU",
    "sg:address":"71 Basalt St",
    "sg:city":"Geebung",
    "sg:classifiers":[
        {
            "category":"Manufacturing",
            "subcategory":"Printing",
            "type":"Manufacturing & Wholesale Goods"
        }
    ],
    "sg:phone":"+61 7 3865 9677",
    "sg:postcode":"4034",
    "sg:province":"QLD",
    "sg:tags":[
        "encoding",
        "cheque"
    ],
    "wof:name":"Buckner Printing Company",
    "wof:placetype":"venue"
},
  "geometry": {"coordinates":[153.05191,-27.365356],"type":"Point"}
}