{
  "type": "Feature",
  "properties": {
    "iso:country":"AU",
    "sg:address":"281 Carlisle St",
    "sg:city":"Balaclava",
    "sg:classifiers":[
        {
            "category":"Food & Beverages",
            "subcategory":"Fruits & Vegetables",
            "type":"Retail Goods"
        }
    ],
    "sg:phone":"+61 3 9527 2949",
    "sg:postcode":"3183",
    "sg:province":"VIC",
    "sg:tags":[
        "greengrocer",
        "fruiterer"
    ],
    "wof:name":"Dom's Balaclava Fruit Mart",
    "wof:placetype":"venue"
},
  "geometry": {"coordinates":[144.99613952600001,-37.8691864014],"type":"Point"}
}