{
  "type": "Feature",
  "properties": {
    "addr:full":"53 Cronulla Ave Mermaid Beach QLD 4218",
    "addr:housenumber":"53",
    "addr:postcode":"4218",
    "addr:street":"Cronulla Ave",
    "iso:country":"AU",
    "sg:address":"53 Cronulla Ave",
    "sg:city":"Mermaid Beach",
    "sg:classifiers":[
        {
            "category":"Communications",
            "subcategory":"Film & Video Production",
            "type":"Services"
        }
    ],
    "sg:phone":"+61 7 5575 1341",
    "sg:postcode":"4218",
    "sg:province":"QLD",
    "sg:tags":[
        "mirror"
    ],
    "wof:name":"Mermaid Picture Framing",
    "wof:placetype":"venue"
},
  "geometry": {"coordinates":[153.433197022,-28.0399875641],"type":"Point"}
}