{
  "type": "Feature",
  "properties": {
    "addr:full":"PO Box 3201 Morwell Mail Centre VIC 3841",
    "addr:postcode":"3841",
    "iso:country":"AU",
    "sg:address":"PO Box 3201",
    "sg:city":"Morwell Mail Centre",
    "sg:classifiers":[
        {
            "category":"Building & Trades",
            "subcategory":"Landscaping Services",
            "type":"Services"
        }
    ],
    "sg:phone":"+61 3 5135 6425",
    "sg:postcode":"3841",
    "sg:province":"VIC",
    "sg:tags":[
        "forestry",
        "consultant"
    ],
    "wof:name":"Anc Forestry Group Pty Ltd",
    "wof:placetype":"venue"
},
  "geometry": {"coordinates":[146.41244506800001,-38.3386192322],"type":"Point"}
}