{
  "type": "Feature",
  "properties": {
    "addr:full":"11 Bumborah Point Rd Matraville NSW 2036",
    "addr:housenumber":"11",
    "addr:postcode":"2036",
    "addr:street":"Bumborah Point Rd",
    "iso:country":"AU",
    "sg:address":"11 Bumborah Point Rd",
    "sg:city":"Matraville",
    "sg:classifiers":[
        {
            "category":"Professional",
            "type":"Services"
        }
    ],
    "sg:phone":"+61 2 8304 0215",
    "sg:postcode":"2036",
    "sg:province":"NSW",
    "sg:tags":[
        "forwarding",
        "agent",
        "transport"
    ],
    "wof:name":"Publiship Distribution Services Pty Ltd",
    "wof:placetype":"venue"
},
  "geometry": {"coordinates":[151.224685669,-33.9708061218],"type":"Point"}
}