{
  "type": "Feature",
  "properties": {
    "iso:country":"AU",
    "sg:address":"Suite 3, 869 Point Nepean Rd",
    "sg:city":"Rosebud",
    "sg:classifiers":[
        {
            "category":"Building & Trades",
            "subcategory":"Construction",
            "type":"Services"
        }
    ],
    "sg:phone":"+61 3 5982 0399",
    "sg:postcode":"3939",
    "sg:province":"VIC",
    "sg:tags":[
        "contractor"
    ],
    "wof:name":"Spenco Construction Pty Ltd",
    "wof:placetype":"venue"
},
  "geometry": {"coordinates":[144.911056519,-38.3542175293],"type":"Point"}
}