{
  "type": "Feature",
  "properties": {
    "addr:full":"14 Lennon St Parkville VIC 3052",
    "addr:housenumber":"14",
    "addr:postcode":"3052",
    "addr:street":"Lennon St",
    "iso:country":"AU",
    "sg:address":"14 Lennon St",
    "sg:city":"Parkville",
    "sg:classifiers":[
        {
            "category":"Social Services",
            "subcategory":"Adult Care",
            "type":"Services"
        }
    ],
    "sg:phone":"+61 3 9328 8565",
    "sg:postcode":"3052",
    "sg:province":"VIC",
    "sg:tags":[
        "disadvantaged",
        "aid",
        "organisation",
        "group"
    ],
    "wof:name":"Breast Cancer Support Assoc of Victoria Inc",
    "wof:placetype":"venue"
},
  "geometry": {"coordinates":[144.94108581500001,-37.7865982056],"type":"Point"}
}