{
  "type": "Feature",
  "properties": {
    "addr:full":"8/ 454 Marmion St Myaree WA 6154",
    "addr:housenumber":"/ 454",
    "addr:postcode":"6154",
    "addr:street":"Marmion St",
    "iso:country":"AU",
    "sg:address":"8/ 454 Marmion St",
    "sg:city":"Myaree",
    "sg:classifiers":[
        {
            "category":"Shopping",
            "subcategory":"Music",
            "type":"Retail Goods"
        }
    ],
    "sg:phone":"+61 8 9330 1719",
    "sg:postcode":"6154",
    "sg:province":"WA",
    "sg:tags":[
        "instrument",
        "musical"
    ],
    "wof:name":"Crescendo Myaree",
    "wof:placetype":"venue"
},
  "geometry": {"coordinates":[115.81777200000001,-32.039753],"type":"Point"}
}