{
  "type": "Feature",
  "properties": {
    "addr:full":"2 Norseman Crt Lara VIC 3212",
    "addr:housenumber":"2",
    "addr:postcode":"3212",
    "addr:street":"Norseman Crt",
    "iso:country":"AU",
    "sg:address":"2 Norseman Crt",
    "sg:city":"Lara",
    "sg:classifiers":[
        {
            "category":"Building & Trades",
            "subcategory":"Construction",
            "type":"Services"
        }
    ],
    "sg:phone":"+61 3 5282 3711",
    "sg:postcode":"3212",
    "sg:province":"VIC",
    "sg:tags":[
        "contractor"
    ],
    "wof:name":"Walpole B W & M C",
    "wof:placetype":"venue"
},
  "geometry": {"coordinates":[144.38641357399999,-38.0157775879],"type":"Point"}
}