{
  "type": "Feature",
  "properties": {
    "addr:full":"Shop 146 Blunder Rd Shopng Vlg 146 Blunder Rd Oxley QLD 4075",
    "addr:housenumber":"146;146",
    "addr:postcode":"4075",
    "addr:street":"Blunder Rd;Vlg;Blunder Rd",
    "iso:country":"AU",
    "sg:address":"Shop 146 Blunder Rd Shopng Vlg 146 Blunder Rd",
    "sg:city":"Oxley",
    "sg:classifiers":[
        {
            "category":"Personal",
            "subcategory":"Beauty Salon",
            "type":"Services"
        }
    ],
    "sg:phone":"+61 7 3714 9330",
    "sg:postcode":"4075",
    "sg:province":"QLD",
    "sg:tags":[
        "hairdresser"
    ],
    "wof:name":"B. Jazzy Hair & Beauty",
    "wof:placetype":"venue"
},
  "geometry": {"coordinates":[152.982818603,-27.5756130219],"type":"Point"}
}