{
  "type": "Feature",
  "properties": {
    "addr:full":"139 Musgrave St Rockhampton QLD 4700",
    "addr:housenumber":"139",
    "addr:postcode":"4700",
    "addr:street":"Musgrave St",
    "iso:country":"AU",
    "sg:address":"139 Musgrave St",
    "sg:city":"Rockhampton",
    "sg:classifiers":[
        {
            "category":"Professional",
            "subcategory":"Accounting & Tax Preparation",
            "type":"Services"
        }
    ],
    "sg:phone":"+61 7 4922 5352",
    "sg:postcode":"4700",
    "sg:province":"QLD",
    "sg:tags":[
        "consultant",
        "taxation"
    ],
    "wof:name":"ITP The Income Tax Professionals",
    "wof:placetype":"venue"
},
  "geometry": {"coordinates":[150.521774292,-23.3668022156],"type":"Point"}
}