{
  "type": "Feature",
  "properties": {
    "addr:full":"RPH LABORATORIES Wellington St Perth WA 6000",
    "addr:postcode":"6000",
    "addr:street":"Wellington St",
    "iso:country":"AU",
    "sg:address":"RPH LABORATORIES Wellington St",
    "sg:city":"Perth",
    "sg:classifiers":[
        {
            "category":"Health Services",
            "subcategory":"Medical Lab",
            "type":"Services"
        }
    ],
    "sg:phone":"+61 8 9224 2422",
    "sg:postcode":"6000",
    "sg:province":"WA",
    "sg:tags":[
        "laboratory",
        "pathology"
    ],
    "wof:name":"Pathwest",
    "wof:placetype":"venue"
},
  "geometry": {"coordinates":[115.85492706300001,-31.9502372742],"type":"Point"}
}