{
  "type": "Feature",
  "properties": {
    "addr:full":"6 Queensland Ave Broadbeach QLD 4218",
    "addr:housenumber":"6",
    "addr:postcode":"4218",
    "addr:street":"Queensland Ave",
    "iso:country":"AU",
    "sg:address":"6 Queensland Ave",
    "sg:city":"Broadbeach",
    "sg:classifiers":[
        {
            "category":"Travel",
            "subcategory":"Travel Agent",
            "type":"Entertainment"
        }
    ],
    "sg:phone":"+61 7 5526 2288",
    "sg:postcode":"4218",
    "sg:province":"QLD",
    "sg:tags":[
        "tour",
        "holiday",
        "adventure"
    ],
    "wof:name":"Antigua Beach Resort",
    "wof:placetype":"venue"
},
  "geometry": {"coordinates":[153.433059692,-28.0272121429],"type":"Point"}
}