{
  "type": "Feature",
  "properties": {
    "iso:country":"AU",
    "sg:address":"2/ 421 Gympie Rd",
    "sg:city":"Strathpine",
    "sg:classifiers":[
        {
            "category":"Real Estate",
            "subcategory":"Real Estate Agent",
            "type":"Services"
        }
    ],
    "sg:phone":"+61 7 3889 8188",
    "sg:postcode":"4500",
    "sg:province":"QLD",
    "wof:name":"Richardson & Wrench Strathpine",
    "wof:placetype":"venue"
},
  "geometry": {"coordinates":[152.988845825,-27.3024044037],"type":"Point"}
}