{
  "type": "Feature",
  "properties": {
    "iso:country":"AU",
    "sg:address":"532c Brighton Rd",
    "sg:city":"Brighton",
    "sg:classifiers":[
        {
            "category":"Food & Beverages",
            "subcategory":"Bakery",
            "type":"Retail Goods"
        }
    ],
    "sg:phone":"+61 8 8377 4800",
    "sg:postcode":"5048",
    "sg:province":"SA",
    "sg:tags":[
        "baker"
    ],
    "wof:name":"Buns On Brighton",
    "wof:placetype":"venue"
},
  "geometry": {"coordinates":[138.523315,-35.02243],"type":"Point"}
}