{
  "type": "Feature",
  "properties": {
    "addr:full":"3a David St Mordialloc VIC 3195",
    "addr:housenumber":"3a",
    "addr:postcode":"3195",
    "addr:street":"David St",
    "iso:country":"AU",
    "sg:address":"3a David St",
    "sg:city":"Mordialloc",
    "sg:classifiers":[
        {
            "category":"Professional",
            "subcategory":"Employment Agencies",
            "type":"Services"
        }
    ],
    "sg:phone":"+61 3 9580 4276",
    "sg:postcode":"3195",
    "sg:province":"VIC",
    "wof:name":"Main Street Personnel & Marketing",
    "wof:placetype":"venue"
},
  "geometry": {"coordinates":[145.09217834500001,-38.0006790161],"type":"Point"}
}