{
  "type": "Feature",
  "properties": {
    "addr:full":"75 Albert St Moe VIC 3825",
    "addr:housenumber":"75",
    "addr:postcode":"3825",
    "addr:street":"Albert St",
    "iso:country":"AU",
    "sg:address":"75 Albert St",
    "sg:city":"Moe",
    "sg:classifiers":[
        {
            "category":"Fast Food",
            "type":"Food & Drink"
        }
    ],
    "sg:phone":"+61 3 5127 4616",
    "sg:postcode":"3825",
    "sg:province":"VIC",
    "sg:tags":[
        "away",
        "take"
    ],
    "wof:name":"Big Luck Fish & Chips",
    "wof:placetype":"venue"
},
  "geometry": {"coordinates":[146.26165800000001,-38.174843],"type":"Point"}
}