{
  "type": "Feature",
  "properties": {
    "iso:country":"AU",
    "sg:address":"Shop 56 Marrickville Metro Shpng Cntr",
    "sg:city":"Marrickville",
    "sg:classifiers":[
        {
            "category":"Shopping",
            "subcategory":"Clothing, Apparel, & Fashions",
            "type":"Retail Goods"
        }
    ],
    "sg:phone":"+61 2 9519 2275",
    "sg:postcode":"2204",
    "sg:province":"NSW",
    "sg:tags":[
        "jean"
    ],
    "wof:name":"JeansWest",
    "wof:placetype":"venue"
},
  "geometry": {"coordinates":[151.155304,-33.910168],"type":"Point"}
}