{
  "type": "Feature",
  "properties": {
    "addr:full":"19 Hall St Bondi Beach NSW 2026",
    "addr:housenumber":"19",
    "addr:postcode":"2026",
    "addr:street":"Hall St",
    "iso:country":"AU",
    "sg:address":"19 Hall St",
    "sg:city":"Bondi Beach",
    "sg:classifiers":[
        {
            "category":"Real Estate",
            "subcategory":"Real Estate Agent",
            "type":"Services"
        }
    ],
    "sg:phone":"+61 2 9130 5262",
    "sg:postcode":"2026",
    "sg:province":"NSW",
    "wof:name":"Raine & Horne",
    "wof:placetype":"venue"
},
  "geometry": {"coordinates":[151.27333068900001,-33.8906669617],"type":"Point"}
}