{
  "type": "Feature",
  "properties": {
    "addr:full":"299c Timor St Warrnambool VIC 3280",
    "addr:housenumber":"299c",
    "addr:postcode":"3280",
    "addr:street":"Timor St",
    "iso:country":"AU",
    "sg:address":"299c Timor St",
    "sg:city":"Warrnambool",
    "sg:classifiers":[
        {
            "category":"Health Services",
            "subcategory":"Chiropractor",
            "type":"Services"
        }
    ],
    "sg:phone":"+61 3 5562 1881",
    "sg:postcode":"3280",
    "sg:province":"VIC",
    "wof:name":"Davis Chiropractic Centre",
    "wof:placetype":"venue"
},
  "geometry": {"coordinates":[142.47564697300001,-38.3825645447],"type":"Point"}
}