{
  "type": "Feature",
  "properties": {
    "addr:full":"1 - 3 Slough Ave Silverwater NSW 2128",
    "addr:housenumber":"3",
    "addr:postcode":"2128",
    "addr:street":"Slough Ave",
    "iso:country":"AU",
    "sg:address":"1 - 3 Slough Ave",
    "sg:city":"Silverwater",
    "sg:classifiers":[
        {
            "category":"Home & Garden",
            "subcategory":"Hardware",
            "type":"Retail Goods"
        }
    ],
    "sg:phone":"+61 2 9647 2242",
    "sg:postcode":"2128",
    "sg:province":"NSW",
    "sg:tags":[
        "plumber",
        "supply"
    ],
    "wof:name":"Tradelink Plumbing Centres",
    "wof:placetype":"venue"
},
  "geometry": {"coordinates":[151.04966735799999,-33.8337860107],"type":"Point"}
}