{
  "type": "Feature",
  "properties": {
    "iso:country":"AU",
    "sg:address":"21 Moss St",
    "sg:city":"Nowra",
    "sg:classifiers":[
        {
            "category":"Professional",
            "subcategory":"Accounting & Tax Preparation",
            "type":"Services"
        }
    ],
    "sg:phone":"+61 2 4421 6633",
    "sg:postcode":"2541",
    "sg:province":"NSW",
    "sg:tags":[
        "consultant",
        "taxation"
    ],
    "wof:name":"Morton & Cord Services Pty Ltd",
    "wof:placetype":"venue"
},
  "geometry": {"coordinates":[150.610397339,-34.870891571],"type":"Point"}
}