{
  "type": "Feature",
  "properties": {
    "iso:country":"AU",
    "sg:address":"6 Wedge St",
    "sg:city":"Pialba",
    "sg:classifiers":[
        {
            "category":"Building & Trades",
            "subcategory":"Landscaping Services",
            "type":"Services"
        }
    ],
    "sg:phone":"+61 414 927 836",
    "sg:postcode":"4655",
    "sg:province":"QLD",
    "sg:tags":[
        "stump",
        "tree",
        "felling",
        "removal"
    ],
    "wof:name":"Coastal Quickchip",
    "wof:placetype":"venue"
},
  "geometry": {"coordinates":[152.81939700000001,-25.288107],"type":"Point"}
}