{
  "type": "Feature",
  "properties": {
    "addr:full":"35 Hygeia Rd Ringwood VIC 3134",
    "addr:housenumber":"35",
    "addr:postcode":"3134",
    "addr:street":"Hygeia Rd",
    "iso:country":"AU",
    "sg:address":"35 Hygeia Rd",
    "sg:city":"Ringwood",
    "sg:classifiers":[
        {
            "category":"Professional",
            "subcategory":"Employment Agencies",
            "type":"Services"
        }
    ],
    "sg:phone":"+61 3 9870 1013",
    "sg:postcode":"3134",
    "sg:province":"VIC",
    "sg:tags":[
        "entertainer",
        "agent"
    ],
    "wof:name":"Hundley Ellen",
    "wof:placetype":"venue"
},
  "geometry": {"coordinates":[145.21656799300001,-37.8064727783],"type":"Point"}
}