{
  "type": "Feature",
  "properties": {
    "iso:country":"AU",
    "sg:address":"54 Clavering Rd",
    "sg:city":"Bayswater",
    "sg:classifiers":[
        {
            "category":"Professional",
            "type":"Services"
        }
    ],
    "sg:phone":"+61 8 9272 9499",
    "sg:postcode":"6053",
    "sg:province":"WA",
    "sg:tags":[
        "shop",
        "fitting"
    ],
    "wof:name":"Marvic Packaging Australia",
    "wof:placetype":"venue"
},
  "geometry": {"coordinates":[115.91918182400001,-31.9141197205],"type":"Point"}
}