{
  "type": "Feature",
  "properties": {
    "addr:full":"Suite 3 Creaney Drive Medical Centre Kingsley WA 6026",
    "addr:postcode":"6026",
    "addr:street":"Creaney",
    "iso:country":"AU",
    "sg:address":"Suite 3",
    "sg:city":"Creaney Drive Medical Centre Kingsley",
    "sg:classifiers":[
        {
            "category":"Health Services",
            "subcategory":"Optometrist",
            "type":"Services"
        }
    ],
    "sg:phone":"+61 8 9409 7623",
    "sg:postcode":"6026",
    "sg:province":"WA",
    "wof:name":"Kingsley Optical Services",
    "wof:placetype":"venue"
},
  "geometry": {"coordinates":[115.788093567,-31.8029842377],"type":"Point"}
}