{
  "type": "Feature",
  "properties": {
    "addr:full":"236 Fourth St Wonthella WA 6530",
    "addr:housenumber":"236",
    "addr:postcode":"6530",
    "addr:street":"Fourth St",
    "iso:country":"AU",
    "sg:address":"236 Fourth St",
    "sg:city":"Wonthella",
    "sg:classifiers":[
        {
            "category":"Banks & Credit Unions",
            "subcategory":"Investment Brokerage",
            "type":"Services"
        }
    ],
    "sg:phone":"+61 8 9964 5668",
    "sg:postcode":"6530",
    "sg:province":"WA",
    "sg:tags":[
        "care",
        "day",
        "family",
        "child"
    ],
    "wof:name":"Magic Cottage Child Care Centre",
    "wof:placetype":"venue"
},
  "geometry": {"coordinates":[114.628829956,-28.7639846802],"type":"Point"}
}