{
  "type": "Feature",
  "properties": {
    "iso:country":"AU",
    "sg:address":"Shed 4/ 5 Brown St",
    "sg:city":"Alice Springs",
    "sg:classifiers":[
        {
            "category":"Building & Trades",
            "subcategory":"Construction",
            "type":"Services"
        }
    ],
    "sg:phone":"+61 8 8952 4835",
    "sg:postcode":"0870",
    "sg:province":"NT",
    "sg:tags":[
        "joiner",
        "carpenter"
    ],
    "wof:name":"Fast Carpentry Services Pty Ltd",
    "wof:placetype":"venue"
},
  "geometry": {"coordinates":[133.8697052,-23.6899871826],"type":"Point"}
}