{
  "type": "Feature",
  "properties": {
    "addr:full":"1188 Victoria Rd West Ryde NSW 2114",
    "addr:housenumber":"1188",
    "addr:postcode":"2114",
    "addr:street":"Victoria Rd",
    "iso:country":"AU",
    "sg:address":"1188 Victoria Rd",
    "sg:city":"West Ryde",
    "sg:classifiers":[
        {
            "category":"Travel",
            "subcategory":"Hotels & Motels",
            "type":"Entertainment"
        }
    ],
    "sg:phone":"+61 2 9877 8377",
    "sg:postcode":"2114",
    "sg:province":"NSW",
    "wof:name":"Comfort Inn West Ryde",
    "wof:placetype":"venue"
},
  "geometry": {"coordinates":[151.07423400900001,-33.8064079285],"type":"Point"}
}