{
  "type": "Feature",
  "properties": {
    "addr:full":"1 - 11 Fischer Rd Flinders View QLD 4305",
    "addr:housenumber":"11",
    "addr:postcode":"4305",
    "addr:street":"1;Fischer Rd",
    "iso:country":"AU",
    "sg:address":"1 - 11 Fischer Rd",
    "sg:city":"Flinders View",
    "sg:classifiers":[
        {
            "category":"Building & Trades",
            "subcategory":"Landscaping Services",
            "type":"Services"
        }
    ],
    "sg:phone":"+61 7 3288 0800",
    "sg:postcode":"4305",
    "sg:province":"QLD",
    "sg:tags":[
        "designer",
        "landscape",
        "contractor"
    ],
    "wof:name":"Enviro Landscaping Services",
    "wof:placetype":"venue"
},
  "geometry": {"coordinates":[152.79307556099999,-27.6552028656],"type":"Point"}
}