{
  "type": "Feature",
  "properties": {
    "iso:country":"AU",
    "sg:address":"162 Bossley Rd",
    "sg:city":"Bossley Park",
    "sg:classifiers":[
        {
            "category":"Professional",
            "type":"Services"
        }
    ],
    "sg:phone":"+61 2 9823 6291",
    "sg:postcode":"2176",
    "sg:province":"NSW",
    "sg:tags":[
        "packaging",
        "filling",
        "assembling"
    ],
    "wof:name":"World Shakers",
    "wof:placetype":"venue"
},
  "geometry": {"coordinates":[150.875,-33.8584289551],"type":"Point"}
}