{
  "type": "Feature",
  "properties": {
    "addr:full":"Shop 10 214 Mulgrave Rd Westcourt QLD 4870",
    "addr:housenumber":"shop 10",
    "addr:postcode":"214;4870",
    "addr:street":"Mulgrave Rd",
    "iso:country":"AU",
    "sg:address":"Shop 10 214 Mulgrave Rd",
    "sg:city":"Westcourt",
    "sg:classifiers":[
        {
            "category":"Banks & Credit Unions",
            "subcategory":"Financial Services",
            "type":"Services"
        }
    ],
    "sg:phone":"+61 7 4041 0500",
    "sg:postcode":"4870",
    "sg:province":"QLD",
    "sg:tags":[
        "annuity",
        "rollover",
        "superannuation",
        "consultant"
    ],
    "wof:name":"Sunsuper",
    "wof:placetype":"venue"
},
  "geometry": {"coordinates":[145.75152587900001,-16.9360332489],"type":"Point"}
}