{
  "type": "Feature",
  "properties": {
    "addr:full":"3 Pember Rd Denmark WA 6333",
    "addr:housenumber":"3",
    "addr:postcode":"6333",
    "addr:street":"Pember Rd",
    "iso:country":"AU",
    "sg:address":"3 Pember Rd",
    "sg:city":"Denmark",
    "sg:classifiers":[
        {
            "category":"Professional",
            "subcategory":"Engineering",
            "type":"Services"
        }
    ],
    "sg:phone":"+61 8 9848 2790",
    "sg:postcode":"6333",
    "sg:province":"WA",
    "sg:tags":[
        "consulting",
        "engineer"
    ],
    "wof:name":"Lodge KL",
    "wof:placetype":"venue"
},
  "geometry": {"coordinates":[117.326606751,-34.9982337952],"type":"Point"}
}