{
  "type": "Feature",
  "properties": {
    "addr:full":"97 High St Northcote VIC 3070",
    "addr:housenumber":"97",
    "addr:postcode":"3070",
    "addr:street":"High St",
    "iso:country":"AU",
    "sg:address":"97 High St",
    "sg:city":"Northcote",
    "sg:classifiers":[
        {
            "category":"Food & Beverages",
            "subcategory":"Liquor & Beverages",
            "type":"Retail Goods"
        }
    ],
    "sg:phone":"+61 3 9481 3228",
    "sg:postcode":"3070",
    "sg:province":"VIC",
    "sg:tags":[
        "store"
    ],
    "wof:name":"Westgarth Licensed Groceries",
    "wof:placetype":"venue"
},
  "geometry": {"coordinates":[144.996735,-37.779823],"type":"Point"}
}