{
  "type": "Feature",
  "properties": {
    "iso:country":"AU",
    "sg:address":"1 Swift St",
    "sg:city":"Wellington",
    "sg:classifiers":[
        {
            "category":"Professional",
            "subcategory":"Accounting & Tax Preparation",
            "type":"Services"
        }
    ],
    "sg:phone":"+61 2 6845 2177",
    "sg:postcode":"2820",
    "sg:province":"NSW",
    "sg:tags":[
        "accountant",
        "auditor"
    ],
    "wof:name":"Ryan T J, CA",
    "wof:placetype":"venue"
},
  "geometry": {"coordinates":[148.9453125,-32.5539169312],"type":"Point"}
}