{
  "type": "Feature",
  "properties": {
    "addr:full":"PO Box 114 Caulfield East VIC 3145",
    "addr:postcode":"3145",
    "iso:country":"AU",
    "sg:address":"PO Box 114",
    "sg:city":"Caulfield East",
    "sg:classifiers":[
        {
            "category":"Utilities",
            "subcategory":"Electric",
            "type":"Services"
        }
    ],
    "sg:phone":"+61 412 567 692",
    "sg:postcode":"3145",
    "sg:province":"VIC",
    "sg:tags":[
        "electrical",
        "contractor"
    ],
    "wof:name":"Rap Electrical Contractors",
    "wof:placetype":"venue"
},
  "geometry": {"coordinates":[145.04458618199999,-37.8783683777],"type":"Point"}
}