{
  "type": "Feature",
  "properties": {
    "addr:full":"23 Walker St Windsor South NSW 2756",
    "addr:housenumber":"23",
    "addr:postcode":"2756",
    "addr:street":"Walker St",
    "iso:country":"AU",
    "sg:address":"23 Walker St",
    "sg:city":"Windsor South",
    "sg:classifiers":[
        {
            "category":"Professional",
            "subcategory":"Printing & Photocopies",
            "type":"Services"
        }
    ],
    "sg:phone":"+61 2 4587 8683",
    "sg:postcode":"2756",
    "sg:province":"NSW",
    "sg:tags":[
        "publishing",
        "desktop"
    ],
    "wof:name":"Robinsons' Typesetting Services",
    "wof:placetype":"venue"
},
  "geometry": {"coordinates":[150.80963134800001,-33.6244087219],"type":"Point"}
}