{
  "type": "Feature",
  "properties": {
    "iso:country":"AU",
    "sg:address":"97 Wilson St",
    "sg:city":"Horsham",
    "sg:classifiers":[
        {
            "category":"Retail",
            "subcategory":"Auto Repair",
            "type":"Services"
        }
    ],
    "sg:phone":"+61 3 5382 4519",
    "sg:postcode":"3400",
    "sg:province":"VIC",
    "sg:tags":[
        "engine",
        "reconditioning"
    ],
    "wof:name":"Repco",
    "wof:placetype":"venue"
},
  "geometry": {"coordinates":[142.19648742699999,-36.7167739868],"type":"Point"}
}