{
  "type": "Feature",
  "properties": {
    "addr:full":"Lot13/ Blencowes La Wildes Meadow NSW 2577",
    "addr:postcode":"2577",
    "iso:country":"AU",
    "sg:address":"Lot13/ Blencowes La",
    "sg:city":"Wildes Meadow",
    "sg:classifiers":[
        {
            "category":"Banks & Credit Unions",
            "subcategory":"Investment Brokerage",
            "type":"Services"
        }
    ],
    "sg:phone":"+61 2 4886 4500",
    "sg:postcode":"2577",
    "sg:province":"NSW",
    "sg:tags":[
        "finance",
        "broker"
    ],
    "wof:name":"Automotive People The",
    "wof:placetype":"venue"
},
  "geometry": {"coordinates":[150.53483581500001,-34.6132202148],"type":"Point"}
}