{
  "type": "Feature",
  "properties": {
    "iso:country":"AU",
    "sg:address":"190 Conadilly St",
    "sg:city":"Gunnedah",
    "sg:classifiers":[
        {
            "category":"Shopping",
            "subcategory":"Shoes",
            "type":"Retail Goods"
        }
    ],
    "sg:phone":"+61 2 6742 0972",
    "sg:postcode":"2380",
    "sg:province":"NSW",
    "sg:tags":[
        "footwear"
    ],
    "wof:name":"Bill Syphers Footwear & Saddlery",
    "wof:placetype":"venue"
},
  "geometry": {"coordinates":[150.25250244099999,-30.9770431519],"type":"Point"}
}