{
  "type": "Feature",
  "properties": {
    "addr:full":"54 Tynye St North Adelaide SA 5006",
    "addr:housenumber":"54",
    "addr:postcode":"5006",
    "addr:street":"Tynye St",
    "iso:country":"AU",
    "sg:address":"54 Tynye St",
    "sg:city":"North Adelaide",
    "sg:classifiers":[
        {
            "category":"Food & Beverages",
            "subcategory":"Bakery",
            "type":"Retail Goods"
        }
    ],
    "sg:phone":"+61 8 8267 2766",
    "sg:postcode":"5006",
    "sg:province":"SA",
    "sg:tags":[
        "cake",
        "shop",
        "pastry"
    ],
    "wof:name":"Perrrymans Bakery",
    "wof:placetype":"venue"
},
  "geometry": {"coordinates":[138.598312378,-34.9055404663],"type":"Point"}
}