{
  "type": "Feature",
  "properties": {
    "addr:full":"Unit 6 51 Jersey Rd Bayswater VIC 3153",
    "addr:housenumber":"51",
    "addr:postcode":"3153",
    "addr:street":"Jersey Rd",
    "iso:country":"AU",
    "sg:address":"Unit 6 51 Jersey Rd",
    "sg:city":"Bayswater",
    "sg:classifiers":[
        {
            "category":"Wholesale",
            "subcategory":"Medical Equipment & Supplies",
            "type":"Manufacturing & Wholesale Goods"
        }
    ],
    "sg:phone":"+61 3 9720 6700",
    "sg:postcode":"3153",
    "sg:province":"VIC",
    "sg:tags":[
        "dental"
    ],
    "wof:name":"Durodent",
    "wof:placetype":"venue"
},
  "geometry": {"coordinates":[145.27903747600001,-37.8448677063],"type":"Point"}
}