{
  "type": "Feature",
  "properties": {
    "iso:country":"AU",
    "sg:address":"103 Young St",
    "sg:city":"Carrington",
    "sg:classifiers":[
        {
            "category":"Fast Food",
            "type":"Food & Drink"
        }
    ],
    "sg:phone":"+61 2 4961 1814",
    "sg:postcode":"2294",
    "sg:province":"NSW",
    "sg:tags":[
        "away",
        "take"
    ],
    "wof:name":"Carrington Fare",
    "wof:placetype":"venue"
},
  "geometry": {"coordinates":[151.765548706,-32.915725708],"type":"Point"}
}