{
  "type": "Feature",
  "properties": {
    "addr:full":"53a George St Pinjarra WA 6208",
    "addr:housenumber":"53a",
    "addr:postcode":"6208",
    "addr:street":"George St",
    "iso:country":"AU",
    "sg:address":"53a George St",
    "sg:city":"Pinjarra",
    "sg:classifiers":[
        {
            "category":"Real Estate",
            "subcategory":"Real Estate Agent",
            "type":"Services"
        }
    ],
    "sg:phone":"+61 8 9531 1266",
    "sg:postcode":"6208",
    "sg:province":"WA",
    "wof:name":"Rural & Metro Realty (Pinjarra)",
    "wof:placetype":"venue"
},
  "geometry": {"coordinates":[115.872528,-32.630493],"type":"Point"}
}