{
  "type": "Feature",
  "properties": {
    "addr:full":"Cnr Graham St & McBride Ave Wonthaggi VIC 3995",
    "addr:postcode":"3995",
    "addr:street":"Cnr Graham St & Mcbride Ave",
    "iso:country":"AU",
    "sg:address":"Cnr Graham St & McBride Ave",
    "sg:city":"Wonthaggi",
    "sg:classifiers":[
        {
            "category":"Banks & Credit Unions",
            "subcategory":"Bank",
            "type":"Services"
        }
    ],
    "sg:phone":"+61 3 5672 2699",
    "sg:postcode":"3995",
    "sg:province":"VIC",
    "wof:name":"Bendigo Bank",
    "wof:placetype":"venue"
},
  "geometry": {"coordinates":[145.59446700000001,-38.605728],"type":"Point"}
}