{
  "type": "Feature",
  "properties": {
    "addr:full":"3 Peel St Mackay QLD 4740",
    "addr:housenumber":"3",
    "addr:postcode":"4740",
    "addr:street":"Peel St",
    "iso:country":"AU",
    "sg:address":"3 Peel St",
    "sg:city":"Mackay",
    "sg:classifiers":[
        {
            "category":"Home & Garden",
            "subcategory":"Carpets & Floor Coverings",
            "type":"Retail Goods"
        }
    ],
    "sg:phone":"+61 7 4951 2253",
    "sg:postcode":"4740",
    "sg:province":"QLD",
    "sg:tags":[
        "mattress"
    ],
    "wof:name":"Forty Winks",
    "wof:placetype":"venue"
},
  "geometry": {"coordinates":[149.17953499999999,-21.142168],"type":"Point"}
}