{
  "type": "Feature",
  "properties": {
    "iso:country":"AU",
    "sg:address":"Unit 1/ 3 Arkwright Rd",
    "sg:city":"Rockingham",
    "sg:classifiers":[
        {
            "category":"Banks & Credit Unions",
            "subcategory":"Bureau De Change",
            "type":"Services"
        }
    ],
    "sg:phone":"+61 8 9528 3334",
    "sg:postcode":"6168",
    "sg:province":"WA",
    "sg:tags":[
        "motorised",
        "scooter"
    ],
    "wof:name":"Road n Trail Pty.Ltd.",
    "wof:placetype":"venue"
},
  "geometry": {"coordinates":[115.76795199999999,-32.276386],"type":"Point"}
}