{
  "type": "Feature",
  "properties": {
    "iso:country":"AU",
    "sg:address":"24 Wandana Ave",
    "sg:city":"Seaview Downs",
    "sg:classifiers":[
        {
            "category":"Building & Trades",
            "subcategory":"Cleaning & Sanitation",
            "type":"Services"
        }
    ],
    "sg:phone":"+61 8 8296 6973",
    "sg:postcode":"5049",
    "sg:province":"SA",
    "sg:tags":[
        "window"
    ],
    "wof:name":"Spotless Cleaning Service",
    "wof:placetype":"venue"
},
  "geometry": {"coordinates":[138.539658,-35.039276],"type":"Point"}
}