{
  "type": "Feature",
  "properties": {
    "addr:full":"5 Warrane Rd East Roseville NSW 2069",
    "addr:housenumber":"5",
    "addr:postcode":"2069",
    "addr:street":"Warrane Rd",
    "iso:country":"AU",
    "sg:address":"5 Warrane Rd",
    "sg:city":"East Roseville",
    "sg:classifiers":[
        {
            "category":"Professional",
            "subcategory":"Accounting & Tax Preparation",
            "type":"Services"
        }
    ],
    "sg:phone":"+61 2 9417 3000",
    "sg:postcode":"2069",
    "sg:province":"NSW",
    "sg:tags":[
        "accountant",
        "auditor"
    ],
    "wof:name":"Vernon A L",
    "wof:placetype":"venue"
},
  "geometry": {"coordinates":[151.198944092,-33.78099823],"type":"Point"}
}