{
  "type": "Feature",
  "properties": {
    "iso:country":"AU",
    "sg:address":"111 Bentinck St",
    "sg:city":"Bathurst",
    "sg:classifiers":[
        {
            "category":"Health Services",
            "subcategory":"Dentist",
            "type":"Services"
        }
    ],
    "sg:phone":"+61 2 6331 2788",
    "sg:postcode":"2795",
    "sg:province":"NSW",
    "wof:name":"Cordato Mark A",
    "wof:placetype":"venue"
},
  "geometry": {"coordinates":[149.58076477,-33.4205360413],"type":"Point"}
}