{
  "type": "Feature",
  "properties": {
    "addr:full":"Unit 5, Cnr Gateway & Harbourtown Drv Biggera Waters QLD 4216",
    "addr:housenumber":"cnr",
    "addr:postcode":"4216",
    "addr:street":"Gateway;Harbourtown Drv",
    "iso:country":"AU",
    "sg:address":"Unit 5, Cnr Gateway & Harbourtown Drv",
    "sg:city":"Biggera Waters",
    "sg:classifiers":[
        {
            "category":"Home & Garden",
            "subcategory":"Furniture",
            "type":"Retail Goods"
        }
    ],
    "sg:phone":"+61 7 5528 8244",
    "sg:postcode":"4216",
    "sg:province":"QLD",
    "sg:tags":[
        "repair",
        "restoration"
    ],
    "wof:name":"Sofa Factory",
    "wof:placetype":"venue"
},
  "geometry": {"coordinates":[153.400558472,-27.9347896576],"type":"Point"}
}