{
  "type": "Feature",
  "properties": {
    "addr:full":"Lvl8/ 8 Bennett St East Perth WA 6004",
    "addr:housenumber":"8",
    "addr:postcode":"6004",
    "addr:street":"Bennett St East",
    "iso:country":"AU",
    "sg:address":"Lvl8/ 8 Bennett St",
    "sg:city":"East Perth",
    "sg:classifiers":[
        {
            "category":"Real Estate",
            "subcategory":"Real Estate Agent",
            "type":"Services"
        }
    ],
    "sg:phone":"+61 8 9318 8101",
    "sg:postcode":"6004",
    "sg:province":"WA",
    "wof:name":"Landmark AWB",
    "wof:placetype":"venue"
},
  "geometry": {"coordinates":[115.871261597,-31.9601306915],"type":"Point"}
}