{
  "type": "Feature",
  "properties": {
    "iso:country":"AU",
    "sg:address":"110 Thompson Rd",
    "sg:city":"Panania",
    "sg:classifiers":[
        {
            "category":"Professional",
            "subcategory":"Art Services",
            "type":"Services"
        }
    ],
    "sg:phone":"+61 2 9774 4172",
    "sg:postcode":"2213",
    "sg:province":"NSW",
    "sg:tags":[
        "graphic",
        "designer"
    ],
    "wof:name":"One World Graphics",
    "wof:placetype":"venue"
},
  "geometry": {"coordinates":[151.007156,-33.959148],"type":"Point"}
}