{
  "type": "Feature",
  "properties": {
    "iso:country":"AU",
    "sg:address":"2 Trevally Pl",
    "sg:city":"Golden Bay",
    "sg:classifiers":[
        {
            "category":"Building & Trades",
            "subcategory":"Plumbing",
            "type":"Services"
        }
    ],
    "sg:phone":"+61 417 091 946",
    "sg:postcode":"6174",
    "sg:province":"WA",
    "sg:tags":[
        "plumber",
        "gasfitters"
    ],
    "wof:name":"R & L Plumbing",
    "wof:placetype":"venue"
},
  "geometry": {"coordinates":[115.753304,-32.432976],"type":"Point"}
}