{
  "type": "Feature",
  "properties": {
    "addr:full":"82 Mica St Carole Park QLD 4300",
    "addr:housenumber":"82",
    "addr:postcode":"4300",
    "addr:street":"Mica St",
    "iso:country":"AU",
    "sg:address":"82 Mica St",
    "sg:city":"Carole Park",
    "sg:classifiers":[
        {
            "category":"Building & Trades",
            "subcategory":"Construction",
            "type":"Services"
        }
    ],
    "sg:phone":"+61 7 3271 2344",
    "sg:postcode":"4300",
    "sg:province":"QLD",
    "sg:tags":[
        "scaffolding"
    ],
    "wof:name":"Speedy Gantry Hire Pty Ltd",
    "wof:placetype":"venue"
},
  "geometry": {"coordinates":[152.93380737300001,-27.6215572357],"type":"Point"}
}