{
  "type": "Feature",
  "properties": {
    "addr:full":"2 / 1368 Heatherton Rd Dandenong VIC 3175",
    "addr:housenumber":"/ 1368",
    "addr:postcode":"3175",
    "addr:street":"Heatherton Rd",
    "iso:country":"AU",
    "sg:address":"2 / 1368 Heatherton Rd",
    "sg:city":"Dandenong",
    "sg:classifiers":[
        {
            "category":"Professional",
            "subcategory":"Detective & Security Services",
            "type":"Services"
        }
    ],
    "sg:phone":"+61 3 9792 9599",
    "sg:postcode":"3175",
    "sg:province":"VIC",
    "sg:tags":[
        "consultant",
        "laser"
    ],
    "wof:name":"Laser 3D",
    "wof:placetype":"venue"
},
  "geometry": {"coordinates":[145.19943237300001,-37.9683036804],"type":"Point"}
}