{
  "type": "Feature",
  "properties": {
    "iso:country":"AU",
    "sg:address":"77 Ogilvie Rd",
    "sg:city":"Warwick",
    "sg:classifiers":[
        {
            "category":"Wholesale",
            "subcategory":"Machinery & Supplies",
            "type":"Manufacturing & Wholesale Goods"
        }
    ],
    "sg:phone":"+61 7 4661 1351",
    "sg:postcode":"4370",
    "sg:province":"QLD",
    "sg:tags":[
        "equipment",
        "welding"
    ],
    "wof:name":"CG Welding Pty Ltd",
    "wof:placetype":"venue"
},
  "geometry": {"coordinates":[152.054199219,-28.1964435577],"type":"Point"}
}