{
  "type": "Feature",
  "properties": {
    "iso:country":"AU",
    "sg:address":"44 Third Ave",
    "sg:city":"Macquarie Fields",
    "sg:classifiers":[
        {
            "category":"Professional",
            "subcategory":"Business Services",
            "type":"Services"
        }
    ],
    "sg:phone":"+61 2 9605 9319",
    "sg:postcode":"2564",
    "sg:province":"NSW",
    "sg:tags":[
        "drafting"
    ],
    "wof:name":"Kylloam Pty Ltd",
    "wof:placetype":"venue"
},
  "geometry": {"coordinates":[150.889526367,-33.9916763306],"type":"Point"}
}