{
  "type": "Feature",
  "properties": {
    "addr:full":"4 / 110 Kortum Drv West Burleigh QLD 4219",
    "addr:housenumber":"/ 110",
    "addr:postcode":"4219",
    "addr:street":"Kortum Drv West",
    "iso:country":"AU",
    "sg:address":"4 / 110 Kortum Drv",
    "sg:city":"West Burleigh",
    "sg:classifiers":[
        {
            "category":"Shopping",
            "subcategory":"Pets & Pet Supplies",
            "type":"Retail Goods"
        }
    ],
    "sg:phone":"+61 7 5576 8766",
    "sg:postcode":"4219",
    "sg:province":"QLD",
    "sg:tags":[
        "food"
    ],
    "wof:name":"Gold Coast Pet Centre",
    "wof:placetype":"venue"
},
  "geometry": {"coordinates":[153.42808532699999,-28.1019744873],"type":"Point"}
}