{
  "type": "Feature",
  "properties": {
    "addr:full":"55 Ethel St Seaforth NSW 2092",
    "addr:housenumber":"55",
    "addr:postcode":"2092",
    "addr:street":"Ethel St",
    "iso:country":"AU",
    "sg:address":"55 Ethel St",
    "sg:city":"Seaforth",
    "sg:classifiers":[
        {
            "category":"Retail",
            "subcategory":"Veterinary Services",
            "type":"Services"
        }
    ],
    "sg:phone":"+61 2 9949 1288",
    "sg:postcode":"2092",
    "sg:province":"NSW",
    "sg:tags":[
        "surgeon"
    ],
    "wof:name":"Miller Rob",
    "wof:placetype":"venue"
},
  "geometry": {"coordinates":[151.251495361,-33.7978401184],"type":"Point"}
}