{
  "type": "Feature",
  "properties": {
    "iso:country":"AU",
    "sg:address":"50A Archibald St",
    "sg:city":"Mackay",
    "sg:classifiers":[
        {
            "category":"Retail",
            "subcategory":"Auto Repair",
            "type":"Services"
        }
    ],
    "sg:phone":"+61 7 4952 4850",
    "sg:postcode":"4740",
    "sg:province":"QLD",
    "sg:tags":[
        "repairer",
        "motor",
        "engineer"
    ],
    "wof:name":"P.R.E. Dyno Tuning Pty Ltd",
    "wof:placetype":"venue"
},
  "geometry": {"coordinates":[149.165146,-21.168089],"type":"Point"}
}