{
  "type": "Feature",
  "properties": {
    "addr:full":"Birdcage 3G 64 Doody St Alexandria NSW 2015",
    "addr:housenumber":"3g 64",
    "addr:postcode":"2015",
    "addr:street":"Birdcage;Doody St",
    "iso:country":"AU",
    "sg:address":"Birdcage 3G 64 Doody St",
    "sg:city":"Alexandria",
    "sg:classifiers":[
        {
            "category":"Professional",
            "subcategory":"Art Services",
            "type":"Services"
        }
    ],
    "sg:phone":"+61 2 9700 7778",
    "sg:postcode":"2015",
    "sg:province":"NSW",
    "sg:tags":[
        "graphic",
        "designer"
    ],
    "wof:name":"2MDC Collective",
    "wof:placetype":"venue"
},
  "geometry": {"coordinates":[151.19549560600001,-33.9159164429],"type":"Point"}
}