{
  "type": "Feature",
  "properties": {
    "iso:country":"AU",
    "sg:address":"Suite 18, 1- 5 Jacobs St",
    "sg:city":"Bankstown",
    "sg:classifiers":[
        {
            "category":"Health Services",
            "subcategory":"Health Practitioner",
            "type":"Services"
        }
    ],
    "sg:phone":"+61 2 9709 2022",
    "sg:postcode":"2200",
    "sg:province":"NSW",
    "sg:tags":[
        "psychologist"
    ],
    "wof:name":"Hayek Carol",
    "wof:placetype":"venue"
},
  "geometry": {"coordinates":[151.036987,-33.915081],"type":"Point"}
}