{
  "type": "Feature",
  "properties": {
    "addr:full":"Unit 3/ 7 King Edward Rd Osborne Park WA 6017",
    "addr:postcode":"6017",
    "addr:street":"King Edward Rd",
    "iso:country":"AU",
    "sg:address":"Unit 3/ 7 King Edward Rd",
    "sg:city":"Osborne Park",
    "sg:classifiers":[
        {
            "category":"Shopping",
            "subcategory":"Computers & Home Electronics",
            "type":"Retail Goods"
        }
    ],
    "sg:phone":"+61 8 9446 7799",
    "sg:postcode":"6017",
    "sg:province":"WA",
    "sg:tags":[
        "wholesaler",
        "equipment",
        "electronic",
        "mfrs"
    ],
    "wof:name":"HarrisTech",
    "wof:placetype":"venue"
},
  "geometry": {"coordinates":[115.805130005,-31.9032039642],"type":"Point"}
}