{
  "type": "Feature",
  "properties": {
    "iso:country":"AU",
    "sg:address":"37 Benjamin Drv",
    "sg:city":"Maryland",
    "sg:classifiers":[
        {
            "category":"Building & Trades",
            "subcategory":"Cleaning & Sanitation",
            "type":"Services"
        }
    ],
    "sg:phone":"+61 2 4955 0033",
    "sg:postcode":"2287",
    "sg:province":"NSW",
    "sg:tags":[
        "industrial",
        "commercial",
        "contractor"
    ],
    "wof:name":"Rapid Sweep",
    "wof:placetype":"venue"
},
  "geometry": {"coordinates":[151.65817260700001,-32.8913993835],"type":"Point"}
}