{
  "type": "Feature",
  "properties": {
    "iso:country":"AU",
    "sg:address":"10 Phillips St",
    "sg:city":"Bridgetown",
    "sg:classifiers":[
        {
            "category":"Arts & Performance",
            "subcategory":"Art Gallery",
            "type":"Entertainment"
        }
    ],
    "sg:phone":"+61 427 184 956",
    "sg:postcode":"6255",
    "sg:province":"WA",
    "wof:name":"Tinkahill Studio & Gallery",
    "wof:placetype":"venue"
},
  "geometry": {"coordinates":[116.137046814,-33.9576263428],"type":"Point"}
}