{
  "type": "Feature",
  "properties": {
    "addr:full":"Unit 2 / 7 Marchesi St Kewdale WA 6105",
    "addr:postcode":"6105",
    "addr:street":"Marchesi St",
    "iso:country":"AU",
    "sg:address":"Unit 2 / 7 Marchesi St",
    "sg:city":"Kewdale",
    "sg:classifiers":[
        {
            "category":"Home & Garden",
            "subcategory":"Household Appliances",
            "type":"Retail Goods"
        }
    ],
    "sg:phone":"+61 8 9353 5348",
    "sg:postcode":"6105",
    "sg:province":"WA",
    "sg:tags":[
        "chemical",
        "equipment",
        "steam",
        "cleaning",
        "pressure"
    ],
    "wof:name":"RapidClean Perth",
    "wof:placetype":"venue"
},
  "geometry": {"coordinates":[115.960403442,-31.9780464172],"type":"Point"}
}