{
  "type": "Feature",
  "properties": {
    "addr:full":"7 Currawong Rd Gooburrum QLD 4670",
    "addr:housenumber":"7",
    "addr:postcode":"4670",
    "addr:street":"Currawong Rd",
    "iso:country":"AU",
    "sg:address":"7 Currawong Rd",
    "sg:city":"Gooburrum",
    "sg:classifiers":[
        {
            "category":"Building & Trades",
            "subcategory":"Construction",
            "type":"Services"
        }
    ],
    "sg:phone":"+61 7 4152 7551",
    "sg:postcode":"4670",
    "sg:province":"QLD",
    "sg:tags":[
        "contractor"
    ],
    "wof:name":"Jbm Construction Pty Ltd",
    "wof:placetype":"venue"
},
  "geometry": {"coordinates":[152.34600830100001,-24.8201656342],"type":"Point"}
}