{
  "type": "Feature",
  "properties": {
    "addr:full":"4/ 13 Wallis Pde North Bondi NSW 2026",
    "addr:housenumber":"/ 13",
    "addr:postcode":"2026",
    "addr:street":"Wallis Pde",
    "iso:country":"AU",
    "sg:address":"4/ 13 Wallis Pde",
    "sg:city":"North Bondi",
    "sg:classifiers":[
        {
            "category":"Farming",
            "subcategory":"Farm & Veterinary Services",
            "type":"Manufacturing & Wholesale Goods"
        }
    ],
    "sg:phone":"+61 2 9130 8551",
    "sg:postcode":"2026",
    "sg:province":"NSW",
    "sg:tags":[
        "irrigation",
        "reticulation",
        "system"
    ],
    "wof:name":"Eden Irrigation",
    "wof:placetype":"venue"
},
  "geometry": {"coordinates":[151.28265380900001,-33.8871917725],"type":"Point"}
}