{
  "type": "Feature",
  "properties": {
    "iso:country":"AU",
    "sg:address":"1 Prince Albert Crs",
    "sg:city":"Taylors Lakes",
    "sg:classifiers":[
        {
            "category":"Landmark",
            "subcategory":"Scenic View",
            "type":"Public Place"
        }
    ],
    "sg:phone":"+61 3 9390 3252",
    "sg:postcode":"3038",
    "sg:province":"VIC",
    "sg:tags":[
        "staircase",
        "handrail"
    ],
    "wof:name":"Western Building Services",
    "wof:placetype":"venue"
},
  "geometry": {"coordinates":[144.781326,-37.696911],"type":"Point"}
}