{
  "type": "Feature",
  "properties": {
    "iso:country":"AU",
    "sg:address":"2/ 14 Shaw Rd",
    "sg:city":"Ingleburn",
    "sg:classifiers":[
        {
            "category":"Building & Trades",
            "subcategory":"Plumbing",
            "type":"Services"
        }
    ],
    "sg:phone":"+61 2 9605 8222",
    "sg:postcode":"2565",
    "sg:province":"NSW",
    "sg:tags":[
        "equipment",
        "valves"
    ],
    "wof:name":"T & S Valves & Fitting Supplies Pty Ltd",
    "wof:placetype":"venue"
},
  "geometry": {"coordinates":[150.855926514,-34.0003623962],"type":"Point"}
}