{
  "type": "Feature",
  "properties": {
    "addr:full":"19 Harefield Crs Kealba VIC 3021",
    "addr:housenumber":"19",
    "addr:postcode":"3021",
    "addr:street":"Harefield Crs",
    "iso:country":"AU",
    "sg:address":"19 Harefield Crs",
    "sg:city":"Kealba",
    "sg:classifiers":[
        {
            "category":"Retail",
            "subcategory":"Driving School",
            "type":"Services"
        }
    ],
    "sg:phone":"+61 3 8307 2307",
    "sg:postcode":"3021",
    "sg:province":"VIC",
    "wof:name":"Brimbank Driving School",
    "wof:placetype":"venue"
},
  "geometry": {"coordinates":[144.81572,-37.730061],"type":"Point"}
}