{
  "type": "Feature",
  "properties": {
    "addr:full":"91 Frederick St Merewether NSW 2291",
    "addr:housenumber":"91",
    "addr:postcode":"2291",
    "addr:street":"Frederick St",
    "iso:country":"AU",
    "sg:address":"91 Frederick St",
    "sg:city":"Merewether",
    "sg:classifiers":[
        {
            "category":"Professional",
            "subcategory":"Computer Services",
            "type":"Services"
        }
    ],
    "sg:phone":"+61 2 4963 6999",
    "sg:postcode":"2291",
    "sg:province":"NSW",
    "sg:tags":[
        "consultant",
        "system"
    ],
    "wof:name":"Rich Computing",
    "wof:placetype":"venue"
},
  "geometry": {"coordinates":[151.755615234,-32.9485969543],"type":"Point"}
}