{
  "type": "Feature",
  "properties": {
    "iso:country":"AU",
    "sg:address":"Unit 5/ 2-10 Reservoir Drv",
    "sg:city":"Coolaroo",
    "sg:classifiers":[
        {
            "category":"Retail",
            "subcategory":"Car Wash",
            "type":"Services"
        }
    ],
    "sg:phone":"+61 3 9308 8736",
    "sg:postcode":"3048",
    "sg:province":"VIC",
    "sg:tags":[
        "truck",
        "cleaning"
    ],
    "wof:name":"Multiwash",
    "wof:placetype":"venue"
},
  "geometry": {"coordinates":[144.93142700000001,-37.640888],"type":"Point"}
}