{
  "type": "Feature",
  "properties": {
    "addr:full":"469 Heidelberg Rd Fairfield VIC 3078",
    "addr:housenumber":"469",
    "addr:postcode":"3078",
    "addr:street":"Heidelberg Rd",
    "iso:country":"AU",
    "sg:address":"469 Heidelberg Rd",
    "sg:city":"Fairfield",
    "sg:classifiers":[
        {
            "category":"Retail",
            "subcategory":"Auto Repair",
            "type":"Services"
        }
    ],
    "sg:phone":"+61 3 9403 3888",
    "sg:postcode":"3078",
    "sg:province":"VIC",
    "sg:tags":[
        "repairer",
        "motor",
        "engineer"
    ],
    "wof:name":"BMW-Doncaster BMW",
    "wof:placetype":"venue"
},
  "geometry": {"coordinates":[145.01919555699999,-37.7829322815],"type":"Point"}
}