{
  "type": "Feature",
  "properties": {
    "addr:full":"23 Woodlark St Lismore NSW 2480",
    "addr:housenumber":"23",
    "addr:postcode":"2480",
    "addr:street":"Woodlark St",
    "iso:country":"AU",
    "sg:address":"23 Woodlark St",
    "sg:city":"Lismore",
    "sg:classifiers":[
        {
            "category":"Building & Trades",
            "subcategory":"Equipment Rental",
            "type":"Services"
        }
    ],
    "sg:phone":"+61 2 6621 5177",
    "sg:postcode":"2480",
    "sg:province":"NSW",
    "sg:tags":[
        "fitness"
    ],
    "wof:name":"Keen Sports",
    "wof:placetype":"venue"
},
  "geometry": {"coordinates":[153.27784729000001,-28.8071098328],"type":"Point"}
}