{
  "type": "Feature",
  "properties": {
    "iso:country":"AU",
    "sg:address":"Buckingham St",
    "sg:city":"Pitt Town",
    "sg:classifiers":[
        {
            "category":"Education",
            "subcategory":"School",
            "type":"Public Place"
        }
    ],
    "sg:phone":"+61 2 4572 3126",
    "sg:postcode":"2756",
    "sg:province":"NSW",
    "sg:tags":[
        "state",
        "-",
        "nsw"
    ],
    "wof:name":"Pitt Town Public School",
    "wof:placetype":"venue"
},
  "geometry": {"coordinates":[150.862350464,-33.5846824646],"type":"Point"}
}