{
  "type": "Feature",
  "properties": {
    "addr:full":"12a Redland Drv Mitcham VIC 3132",
    "addr:housenumber":"12a",
    "addr:postcode":"3132",
    "addr:street":"Redland Drv",
    "iso:country":"AU",
    "sg:address":"12a Redland Drv",
    "sg:city":"Mitcham",
    "sg:classifiers":[
        {
            "category":"Retail",
            "subcategory":"Repair Shop",
            "type":"Services"
        }
    ],
    "sg:phone":"+61 3 9872 6850",
    "sg:postcode":"3132",
    "sg:province":"VIC",
    "sg:tags":[
        "machine",
        "repairs",
        "part",
        "dryer",
        "washing"
    ],
    "wof:name":"Bendix Domestic Appliances",
    "wof:placetype":"venue"
},
  "geometry": {"coordinates":[145.19261169399999,-37.8301849365],"type":"Point"}
}