{
  "type": "Feature",
  "properties": {
    "addr:full":"511 Abernethy Rd Kewdale WA 6105",
    "addr:housenumber":"511",
    "addr:postcode":"6105",
    "addr:street":"Abernethy Rd",
    "iso:country":"AU",
    "sg:address":"511 Abernethy Rd",
    "sg:city":"Kewdale",
    "sg:classifiers":[
        {
            "category":"Home & Garden",
            "subcategory":"Furniture",
            "type":"Retail Goods"
        }
    ],
    "sg:phone":"+61 8 9365 5700",
    "sg:postcode":"6105",
    "sg:province":"WA",
    "sg:tags":[
        "business"
    ],
    "wof:name":"Dexion (Australia) Pty Limited",
    "wof:placetype":"venue"
},
  "geometry": {"coordinates":[115.957801819,-31.9782276154],"type":"Point"}
}