{
  "type": "Feature",
  "properties": {
    "addr:full":"Ely St Oxley VIC 3678",
    "addr:postcode":"3678",
    "addr:street":"Ely St",
    "iso:country":"AU",
    "sg:address":"Ely St",
    "sg:city":"Oxley",
    "sg:classifiers":[
        {
            "category":"Professional",
            "subcategory":"Engineering",
            "type":"Services"
        }
    ],
    "sg:phone":"+61 3 5727 3471",
    "sg:postcode":"3678",
    "sg:province":"VIC",
    "sg:tags":[
        "engineer"
    ],
    "wof:name":"Oxley Engineering",
    "wof:placetype":"venue"
},
  "geometry": {"coordinates":[146.38314819300001,-36.4426383972],"type":"Point"}
}