{
  "type": "Feature",
  "properties": {
    "addr:full":"30 William St Brighton VIC 3186",
    "addr:housenumber":"30",
    "addr:postcode":"3186",
    "addr:street":"William St",
    "iso:country":"AU",
    "sg:address":"30 William St",
    "sg:city":"Brighton",
    "sg:classifiers":[
        {
            "category":"Social Services",
            "subcategory":"Retirement Home",
            "type":"Services"
        }
    ],
    "sg:phone":"+61 3 9503 0107",
    "sg:postcode":"3186",
    "sg:province":"VIC",
    "sg:tags":[
        "environmental",
        "consultant",
        "pollution"
    ],
    "wof:name":"Environmental Assessment Services",
    "wof:placetype":"venue"
},
  "geometry": {"coordinates":[145.001556397,-37.90990448],"type":"Point"}
}