{
  "type": "Feature",
  "properties": {
    "addr:full":"Shop 1/ 4 Aerodrome Rd Maroochydore QLD 4558",
    "addr:housenumber":"shop 1 / 4",
    "addr:postcode":"4558",
    "addr:street":"Aerodrome Rd",
    "iso:country":"AU",
    "sg:address":"Shop 1/ 4 Aerodrome Rd",
    "sg:city":"Maroochydore",
    "sg:classifiers":[
        {
            "category":"Personal",
            "subcategory":"Beauty Salon",
            "type":"Services"
        }
    ],
    "sg:phone":"+61 7 5479 1478",
    "sg:postcode":"4558",
    "sg:province":"QLD",
    "sg:tags":[
        "hairdresser"
    ],
    "wof:name":"Lilly Lotus",
    "wof:placetype":"venue"
},
  "geometry": {"coordinates":[153.10467529300001,-26.662399292],"type":"Point"}
}