{
  "type": "Feature",
  "properties": {
    "addr:full":"117 Condon St Kennington VIC 3550",
    "addr:housenumber":"117",
    "addr:postcode":"3550",
    "addr:street":"Condon St",
    "iso:country":"AU",
    "sg:address":"117 Condon St",
    "sg:city":"Kennington",
    "sg:classifiers":[
        {
            "category":"Retail",
            "subcategory":"Car Wash",
            "type":"Services"
        }
    ],
    "sg:phone":"+61 3 5444 2122",
    "sg:postcode":"3550",
    "sg:province":"VIC",
    "sg:tags":[
        "truck",
        "cleaning"
    ],
    "wof:name":"Strathdale Oasis Car Spa",
    "wof:placetype":"venue"
},
  "geometry": {"coordinates":[144.30351257300001,-36.7725219727],"type":"Point"}
}