{
  "type": "Feature",
  "properties": {
    "addr:full":"Shop 23, Park Ave Burleigh Heads QLD 4220",
    "addr:housenumber":"shop 23",
    "addr:postcode":"4220",
    "addr:street":"Park Ave",
    "iso:country":"AU",
    "sg:address":"Shop 23, Park Ave",
    "sg:city":"Burleigh Heads",
    "sg:classifiers":[
        {
            "category":"Shopping",
            "subcategory":"Computers & Home Electronics",
            "type":"Retail Goods"
        }
    ],
    "sg:phone":"+61 7 5520 7200",
    "sg:postcode":"4220",
    "sg:province":"QLD",
    "sg:tags":[
        "small",
        "equipment",
        "business"
    ],
    "wof:name":"Best Computers",
    "wof:placetype":"venue"
},
  "geometry": {"coordinates":[153.44992065400001,-28.0898799896],"type":"Point"}
}