{
  "type": "Feature",
  "properties": {
    "iso:country":"AU",
    "sg:address":"23 Ryedale Rd",
    "sg:city":"West Ryde",
    "sg:classifiers":[
        {
            "category":"Food & Beverages",
            "subcategory":"Supermarket",
            "type":"Retail Goods"
        }
    ],
    "sg:phone":"+61 2 9809 1997",
    "sg:postcode":"2114",
    "sg:province":"NSW",
    "sg:tags":[
        "grocery",
        "store"
    ],
    "wof:name":"Mierra Bea Australasian Food & Grocery",
    "wof:placetype":"venue"
},
  "geometry": {"coordinates":[151.09082031200001,-33.8076171875],"type":"Point"}
}