{
  "type": "Feature",
  "properties": {
    "addr:full":"52 Barolin St Bundaberg QLD 4670",
    "addr:housenumber":"52",
    "addr:postcode":"4670",
    "addr:street":"Barolin St",
    "iso:country":"AU",
    "sg:address":"52 Barolin St",
    "sg:city":"Bundaberg",
    "sg:classifiers":[
        {
            "category":"Building & Trades",
            "subcategory":"Pest Control",
            "type":"Services"
        }
    ],
    "sg:phone":"+61 7 4153 6045",
    "sg:postcode":"4670",
    "sg:province":"QLD",
    "wof:name":"Payne Colin",
    "wof:placetype":"venue"
},
  "geometry": {"coordinates":[152.35194397000001,-24.8734836578],"type":"Point"}
}