{
  "type": "Feature",
  "properties": {
    "addr:full":"53 Grant St Goornong VIC 3557",
    "addr:housenumber":"53",
    "addr:postcode":"3557",
    "addr:street":"Grant St",
    "iso:country":"AU",
    "sg:address":"53 Grant St",
    "sg:city":"Goornong",
    "sg:classifiers":[
        {
            "category":"Building & Trades",
            "subcategory":"Construction",
            "type":"Services"
        }
    ],
    "sg:phone":"+61 418 351 172",
    "sg:postcode":"3557",
    "sg:province":"VIC",
    "sg:tags":[
        "scaffolding"
    ],
    "wof:name":"Universal Safety Systems Bendigo",
    "wof:placetype":"venue"
},
  "geometry": {"coordinates":[144.508636475,-36.615070343],"type":"Point"}
}