{
  "type": "Feature",
  "properties": {
    "addr:full":"PO Box 1964 Byron Bay NSW 2481",
    "addr:postcode":"2481",
    "iso:country":"AU",
    "sg:address":"PO Box 1964",
    "sg:city":"Byron Bay",
    "sg:classifiers":[
        {
            "category":"Home & Garden",
            "subcategory":"Hardware",
            "type":"Retail Goods"
        }
    ],
    "sg:phone":"+61 2 6685 8232",
    "sg:postcode":"2481",
    "sg:province":"NSW",
    "sg:tags":[
        "plumber",
        "supply"
    ],
    "wof:name":"MediDrain Environmental Services Pty Ltd",
    "wof:placetype":"venue"
},
  "geometry": {"coordinates":[153.612915039,-28.6488323212],"type":"Point"}
}