{
  "type": "Feature",
  "properties": {
    "addr:full":"Suite 3, 6 Davallia Rd Duncraig WA 6023",
    "addr:housenumber":"6",
    "addr:postcode":"6023",
    "addr:street":"Davallia Rd",
    "iso:country":"AU",
    "sg:address":"Suite 3, 6 Davallia Rd",
    "sg:city":"Duncraig",
    "sg:classifiers":[
        {
            "category":"Health Services",
            "subcategory":"Chiropractor",
            "type":"Services"
        }
    ],
    "sg:phone":"+61 8 9243 0100",
    "sg:postcode":"6023",
    "sg:province":"WA",
    "wof:name":"Dillon, Paul",
    "wof:placetype":"venue"
},
  "geometry": {"coordinates":[115.785552978,-31.8455734253],"type":"Point"}
}