{
  "type": "Feature",
  "properties": {
    "addr:full":"7 Reflection Drv Louth Park NSW 2320",
    "addr:housenumber":"7",
    "addr:postcode":"2320",
    "addr:street":"Reflection Drv Louth Park",
    "iso:country":"AU",
    "sg:address":"7 Reflection Drv",
    "sg:city":"Louth Park",
    "sg:classifiers":[
        {
            "category":"Banks & Credit Unions",
            "subcategory":"Financial Services",
            "type":"Services"
        }
    ],
    "sg:phone":"+61 2 4933 4829",
    "sg:postcode":"2320",
    "sg:province":"NSW",
    "sg:tags":[
        "planning"
    ],
    "wof:name":"Strategico Pty Ltd",
    "wof:placetype":"venue"
},
  "geometry": {"coordinates":[151.552459717,-32.772354126],"type":"Point"}
}