{
  "type": "Feature",
  "properties": {
    "addr:full":"1/ 35 Owen Rd Kelmscott WA 6111",
    "addr:housenumber":"/ 35",
    "addr:postcode":"6111",
    "addr:street":"Owen Rd",
    "iso:country":"AU",
    "sg:address":"1/ 35 Owen Rd",
    "sg:city":"Kelmscott",
    "sg:classifiers":[
        {
            "category":"Shopping",
            "subcategory":"Pets & Pet Supplies",
            "type":"Retail Goods"
        }
    ],
    "sg:phone":"+61 8 9497 8555",
    "sg:postcode":"6111",
    "sg:province":"WA",
    "sg:tags":[
        "shop",
        "supplier"
    ],
    "wof:name":"Colourstone",
    "wof:placetype":"venue"
},
  "geometry": {"coordinates":[116.006187439,-32.1326675415],"type":"Point"}
}