{
  "type": "Feature",
  "properties": {
    "addr:full":"188 Christine Ave Burleigh Waters QLD 4220",
    "addr:housenumber":"188",
    "addr:postcode":"4220",
    "addr:street":"Christine Ave",
    "iso:country":"AU",
    "sg:address":"188 Christine Ave",
    "sg:city":"Burleigh Waters",
    "sg:classifiers":[
        {
            "category":"Social Services",
            "subcategory":"Child Care",
            "type":"Services"
        }
    ],
    "sg:phone":"+61 7 5593 4306",
    "sg:postcode":"4220",
    "sg:province":"QLD",
    "sg:tags":[
        "baby",
        "sitter"
    ],
    "wof:name":"Milestonz Nannies - Gold Coast",
    "wof:placetype":"venue"
},
  "geometry": {"coordinates":[153.42742919899999,-28.0855426788],"type":"Point"}
}