{
  "type": "Feature",
  "properties": {
    "addr:full":"72 Parramatta Rd Summer Hill (Sydney) NSW 2130",
    "addr:housenumber":"72",
    "addr:postcode":"2130",
    "addr:street":"Parramatta Rd",
    "iso:country":"AU",
    "sg:address":"72 Parramatta Rd",
    "sg:city":"Summer Hill (Sydney)",
    "sg:classifiers":[
        {
            "category":"Home & Garden",
            "subcategory":"Carpets & Floor Coverings",
            "type":"Retail Goods"
        }
    ],
    "sg:phone":"+61 2 9550 3844",
    "sg:postcode":"2130",
    "sg:province":"NSW",
    "sg:tags":[
        "tile",
        "wall"
    ],
    "wof:name":"Gieffe Interior Environments",
    "wof:placetype":"venue"
},
  "geometry": {"coordinates":[151.140167236,-33.8867607117],"type":"Point"}
}