{
  "type": "Feature",
  "properties": {
    "addr:full":"9 Van Haeren St North Rockhampton QLD 4701",
    "addr:housenumber":"9",
    "addr:postcode":"4701",
    "addr:street":"Van Haeren St North",
    "iso:country":"AU",
    "sg:address":"9 Van Haeren St",
    "sg:city":"North Rockhampton",
    "sg:classifiers":[
        {
            "category":"Professional",
            "subcategory":"Computer Services",
            "type":"Services"
        }
    ],
    "sg:phone":"+61 7 4936 3444",
    "sg:postcode":"4701",
    "sg:province":"QLD",
    "sg:tags":[
        "training"
    ],
    "wof:name":"Rockhampton Computer Training",
    "wof:placetype":"venue"
},
  "geometry": {"coordinates":[150.51370239299999,-23.3288421631],"type":"Point"}
}