{
  "type": "Feature",
  "properties": {
    "iso:country":"AU",
    "sg:address":"87 Percy St",
    "sg:city":"Portland",
    "sg:classifiers":[
        {
            "category":"Personal",
            "subcategory":"Beauty Salon",
            "type":"Services"
        }
    ],
    "sg:phone":"+61 3 5523 5726",
    "sg:postcode":"3305",
    "sg:province":"VIC",
    "wof:name":"Beauty For Life",
    "wof:placetype":"venue"
},
  "geometry": {"coordinates":[141.603912353,-38.3461647034],"type":"Point"}
}