{
  "type": "Feature",
  "properties": {
    "iso:country":"AU",
    "sg:address":"Unit 6, 8-10 Wolsley St",
    "sg:city":"Bentleigh",
    "sg:classifiers":[
        {
            "category":"Building & Trades",
            "subcategory":"Cleaning & Sanitation",
            "type":"Services"
        }
    ],
    "sg:phone":"+61 3 9389 3698",
    "sg:postcode":"3204",
    "sg:province":"VIC",
    "sg:tags":[
        "industrial",
        "commercial",
        "contractor"
    ],
    "wof:name":"AA All Trauma Cleaning Services",
    "wof:placetype":"venue"
},
  "geometry": {"coordinates":[145.03045700000001,-37.927067],"type":"Point"}
}