{
  "type": "Feature",
  "properties": {
    "iso:country":"AU",
    "sg:address":"36 Mabel St",
    "sg:city":"Toowoomba City",
    "sg:classifiers":[
        {
            "category":"Professional",
            "subcategory":"Employment Agencies",
            "type":"Services"
        }
    ],
    "sg:phone":"+61 7 4632 2651",
    "sg:postcode":"4350",
    "sg:province":"QLD",
    "sg:tags":[
        "provider",
        "internet"
    ],
    "wof:name":"Enter Net Australia",
    "wof:placetype":"venue"
},
  "geometry": {"coordinates":[151.959641,-27.532804],"type":"Point"}
}