{
  "type": "Feature",
  "properties": {
    "iso:country":"AU",
    "sg:address":"170 Currie St",
    "sg:city":"Nambour",
    "sg:classifiers":[
        {
            "category":"Government",
            "subcategory":"Fire Station",
            "type":"Public Place"
        }
    ],
    "sg:phone":"+61 7 5441 2479",
    "sg:postcode":"4560",
    "sg:province":"QLD",
    "sg:tags":[
        "brigade"
    ],
    "wof:name":"Fire Brigades",
    "wof:placetype":"venue"
},
  "geometry": {"coordinates":[152.959747314,-26.629945755],"type":"Point"}
}