{
  "type": "Feature",
  "properties": {
    "addr:full":"U2/ 29 Lennox St Bellevue Hill NSW 2023",
    "addr:housenumber":"29",
    "addr:postcode":"2023",
    "addr:street":"U2 /;Lennox St",
    "iso:country":"AU",
    "sg:address":"U2/ 29 Lennox St",
    "sg:city":"Bellevue Hill",
    "sg:classifiers":[
        {
            "category":"Personal",
            "type":"Services"
        }
    ],
    "sg:phone":"+61 413 831 697",
    "sg:postcode":"2023",
    "sg:province":"NSW",
    "sg:tags":[
        "reducing",
        "treatment",
        "weight"
    ],
    "wof:name":"Food Coach Australia Pty Ltd The",
    "wof:placetype":"venue"
},
  "geometry": {"coordinates":[151.257522583,-33.8853187561],"type":"Point"}
}