{
  "type": "Feature",
  "properties": {
    "iso:country":"AU",
    "sg:address":"PO Box 3194",
    "sg:city":"Yeronga",
    "sg:classifiers":[
        {
            "category":"Professional",
            "subcategory":"Computer Services",
            "type":"Services"
        }
    ],
    "sg:phone":"+61 438 636 502",
    "sg:postcode":"4104",
    "sg:province":"QLD",
    "sg:tags":[
        "repairs",
        "upgrade",
        "equipment"
    ],
    "wof:name":"TNK Computer",
    "wof:placetype":"venue"
},
  "geometry": {"coordinates":[153.008544922,-27.5105495453],"type":"Point"}
}