{
  "type": "Feature",
  "properties": {
    "addr:full":"Brown & Zirbel Rd Flagstone Creek QLD 4344",
    "addr:postcode":"4344",
    "addr:street":"Rd",
    "iso:country":"AU",
    "sg:address":"Brown & Zirbel Rd",
    "sg:city":"Flagstone Creek",
    "sg:classifiers":[
        {
            "category":"Farming",
            "subcategory":"Farm",
            "type":"Manufacturing & Wholesale Goods"
        }
    ],
    "sg:phone":"+61 7 4697 5130",
    "sg:postcode":"4344",
    "sg:province":"QLD",
    "sg:tags":[
        "farmer"
    ],
    "wof:name":"Cook E G & E R",
    "wof:placetype":"venue"
},
  "geometry": {"coordinates":[152.101471,-27.61931],"type":"Point"}
}