{
  "type": "Feature",
  "properties": {
    "addr:full":"42 Kingston St Oak Flats NSW 2529",
    "addr:housenumber":"42",
    "addr:postcode":"2529",
    "addr:street":"Kingston St Oak Flats",
    "iso:country":"AU",
    "sg:address":"42 Kingston St",
    "sg:city":"Oak Flats",
    "sg:classifiers":[
        {
            "category":"Building & Trades",
            "subcategory":"Pest Control",
            "type":"Services"
        }
    ],
    "sg:phone":"+61 2 4256 0881",
    "sg:postcode":"2529",
    "sg:province":"NSW",
    "wof:name":"Oak Flats Pest Control",
    "wof:placetype":"venue"
},
  "geometry": {"coordinates":[150.82106018100001,-34.5646286011],"type":"Point"}
}