{
  "type": "Feature",
  "properties": {
    "addr:full":"Shop 175, 100 Burwood Rd Burwood NSW 2134",
    "addr:housenumber":"175 100",
    "addr:postcode":"2134",
    "addr:street":"Burwood Rd",
    "iso:country":"AU",
    "sg:address":"Shop 175, 100 Burwood Rd",
    "sg:city":"Burwood",
    "sg:classifiers":[
        {
            "category":"Travel",
            "subcategory":"Hotels & Motels",
            "type":"Entertainment"
        }
    ],
    "sg:phone":"+61 2 9747 5955",
    "sg:postcode":"2134",
    "sg:province":"NSW",
    "sg:tags":[
        "accommodation"
    ],
    "wof:name":"Amber Lounge",
    "wof:placetype":"venue"
},
  "geometry": {"coordinates":[151.10447692899999,-33.8741455078],"type":"Point"}
}