{
  "type": "Feature",
  "properties": {
    "iso:country":"AU",
    "sg:address":"13 Kangaroo Ground Rd",
    "sg:city":"Wattle Glen",
    "sg:classifiers":[
        {
            "category":"Food & Beverages",
            "subcategory":"Groceries & Convenience Stores",
            "type":"Retail Goods"
        }
    ],
    "sg:phone":"+61 3 9438 4030",
    "sg:postcode":"3096",
    "sg:province":"VIC",
    "wof:name":"Pepper's Paddock General Store",
    "wof:placetype":"venue"
},
  "geometry": {"coordinates":[145.06814575199999,-37.8973236084],"type":"Point"}
}