{
  "type": "Feature",
  "properties": {
    "iso:country":"AU",
    "sg:address":"10 Leslie St",
    "sg:city":"Capalaba",
    "sg:classifiers":[
        {
            "category":"Utilities",
            "subcategory":"Electric",
            "type":"Services"
        }
    ],
    "sg:phone":"+61 7 3390 1737",
    "sg:postcode":"4157",
    "sg:province":"QLD",
    "sg:tags":[
        "electrical",
        "contractor"
    ],
    "wof:name":"Robert Sibraa Electrical",
    "wof:placetype":"venue"
},
  "geometry": {"coordinates":[153.19349670400001,-27.541519165],"type":"Point"}
}