{
  "type": "Feature",
  "properties": {
    "addr:full":"21 Erowal St Beaumaris VIC 3193",
    "addr:housenumber":"21",
    "addr:postcode":"3193",
    "addr:street":"Erowal St",
    "iso:country":"AU",
    "sg:address":"21 Erowal St",
    "sg:city":"Beaumaris",
    "sg:classifiers":[
        {
            "category":"Home & Garden",
            "subcategory":"Carpets & Floor Coverings",
            "type":"Retail Goods"
        }
    ],
    "sg:phone":"+61 417 304 275",
    "sg:postcode":"3193",
    "sg:province":"VIC",
    "sg:tags":[
        "tile",
        "wall",
        "layer"
    ],
    "wof:name":"Creative Tiling",
    "wof:placetype":"venue"
},
  "geometry": {"coordinates":[145.03848266599999,-37.9713897705],"type":"Point"}
}