{
  "type": "Feature",
  "properties": {
    "addr:full":"PO Box 638 Brookvale NSW 2100",
    "addr:postcode":"2100",
    "iso:country":"AU",
    "sg:address":"PO Box 638",
    "sg:city":"Brookvale",
    "sg:classifiers":[
        {
            "category":"Building & Trades",
            "subcategory":"Construction",
            "type":"Services"
        }
    ],
    "sg:phone":"+61 2 9400 7400",
    "sg:postcode":"2100",
    "sg:province":"NSW",
    "sg:tags":[
        "fencing",
        "contractor"
    ],
    "wof:name":"Axis Fencing",
    "wof:placetype":"venue"
},
  "geometry": {"coordinates":[151.273071289,-33.7611312866],"type":"Point"}
}