{
  "type": "Feature",
  "properties": {
    "iso:country":"AU",
    "sg:address":"Tenth Ave",
    "sg:city":"Brighton",
    "sg:classifiers":[
        {
            "category":"Arena",
            "subcategory":"Sports Club",
            "type":"Entertainment"
        }
    ],
    "sg:phone":"+61 7 3269 1234",
    "sg:postcode":"4017",
    "sg:province":"QLD",
    "sg:tags":[
        "league",
        "rugby"
    ],
    "wof:name":"Norths Brighton Junior Rugby League Club Inc",
    "wof:placetype":"venue"
},
  "geometry": {"coordinates":[153.06568908700001,-27.3073768616],"type":"Point"}
}