{
  "type": "Feature",
  "properties": {
    "addr:full":"Shp 9, 575 Canning Hwy Alfred Cove WA 6154",
    "addr:housenumber":"575",
    "addr:postcode":"6154",
    "addr:street":"Canning Hwy",
    "iso:country":"AU",
    "sg:address":"Shp 9, 575 Canning Hwy",
    "sg:city":"Alfred Cove",
    "sg:classifiers":[
        {
            "category":"Utilities",
            "subcategory":"Mobile Phone",
            "type":"Services"
        }
    ],
    "sg:phone":"+61 8 9317 6688",
    "sg:postcode":"6154",
    "sg:province":"WA",
    "sg:tags":[
        "repair",
        "telephone"
    ],
    "wof:name":"ACME Audio Visual",
    "wof:placetype":"venue"
},
  "geometry": {"coordinates":[115.813919,-32.031445],"type":"Point"}
}