{
  "type": "Feature",
  "properties": {
    "iso:country":"AU",
    "sg:address":"131- 133 Union St",
    "sg:city":"Prahran",
    "sg:classifiers":[
        {
            "category":"Social Services",
            "subcategory":"Child Care",
            "type":"Services"
        }
    ],
    "sg:phone":"+61 3 9521 4653",
    "sg:postcode":"3181",
    "sg:province":"VIC",
    "wof:name":"Swinburne Prahran Community Childrens Centre",
    "wof:placetype":"venue"
},
  "geometry": {"coordinates":[144.991912842,-37.8546714783],"type":"Point"}
}