{
  "type": "Feature",
  "properties": {
    "addr:full":"107 Queen St North Strathfield NSW 2137",
    "addr:housenumber":"107",
    "addr:postcode":"2137",
    "addr:street":"Queen St",
    "iso:country":"AU",
    "sg:address":"107 Queen St",
    "sg:city":"North Strathfield",
    "sg:classifiers":[
        {
            "category":"Personal",
            "subcategory":"Massage",
            "type":"Services"
        }
    ],
    "sg:phone":"+61 2 9743 3595",
    "sg:postcode":"2137",
    "sg:province":"NSW",
    "sg:tags":[
        "therapy"
    ],
    "wof:name":"Vitality 1 on 1",
    "wof:placetype":"venue"
},
  "geometry": {"coordinates":[151.088821411,-33.8585090637],"type":"Point"}
}