{
  "type": "Feature",
  "properties": {
    "addr:full":"8 Lidgate Ave Rowville VIC 3178",
    "addr:housenumber":"8",
    "addr:postcode":"3178",
    "addr:street":"Lidgate Ave",
    "iso:country":"AU",
    "sg:address":"8 Lidgate Ave",
    "sg:city":"Rowville",
    "sg:classifiers":[
        {
            "category":"Communications",
            "subcategory":"Film & Video Production",
            "type":"Services"
        }
    ],
    "sg:phone":"+61 3 9763 2424",
    "sg:postcode":"3178",
    "sg:province":"VIC",
    "sg:tags":[
        "dvd",
        "library"
    ],
    "wof:name":"Xpress Flix",
    "wof:placetype":"venue"
},
  "geometry": {"coordinates":[145.23204040499999,-37.920917511],"type":"Point"}
}