{
  "type": "Feature",
  "properties": {
    "addr:full":"97 Johnson St Maffra VIC 3860",
    "addr:housenumber":"97",
    "addr:postcode":"3860",
    "addr:street":"Johnson St",
    "iso:country":"AU",
    "sg:address":"97 Johnson St",
    "sg:city":"Maffra",
    "sg:classifiers":[
        {
            "category":"Travel",
            "subcategory":"Hotels & Motels",
            "type":"Entertainment"
        }
    ],
    "sg:phone":"+61 3 5147 1809",
    "sg:postcode":"3860",
    "sg:province":"VIC",
    "sg:tags":[
        "accommodation"
    ],
    "wof:name":"Metropolitan Hotel",
    "wof:placetype":"venue"
},
  "geometry": {"coordinates":[146.975463867,-37.967124939],"type":"Point"}
}