{
  "type": "Feature",
  "properties": {
    "addr:full":"4 Muros Pl Midvale WA 6056",
    "addr:housenumber":"4",
    "addr:postcode":"6056",
    "addr:street":"Pl",
    "iso:country":"AU",
    "sg:address":"4 Muros Pl",
    "sg:city":"Midvale",
    "sg:classifiers":[
        {
            "category":"Manufacturing",
            "subcategory":"Motor Vehicles & Parts",
            "type":"Manufacturing & Wholesale Goods"
        }
    ],
    "sg:phone":"+61 8 9250 3315",
    "sg:postcode":"6056",
    "sg:province":"WA",
    "sg:tags":[
        "engine",
        "equipment",
        "diesel"
    ],
    "wof:name":"PC Diesel Pty Ltd",
    "wof:placetype":"venue"
},
  "geometry": {"coordinates":[116.03222656200001,-31.8886871338],"type":"Point"}
}