{
  "type": "Feature",
  "properties": {
    "iso:country":"AU",
    "sg:address":"Unit 6/ 73 Dobney Ave",
    "sg:city":"Wagga Wagga",
    "sg:classifiers":[
        {
            "category":"Health Services",
            "subcategory":"Dentist",
            "type":"Services"
        }
    ],
    "sg:phone":"+61 408 250 125",
    "sg:postcode":"2650",
    "sg:province":"NSW",
    "sg:tags":[
        "equipment",
        "dental",
        "repair"
    ],
    "wof:name":"Brian McDonald Dental Services",
    "wof:placetype":"venue"
},
  "geometry": {"coordinates":[147.35726928700001,-35.1234474182],"type":"Point"}
}