{
  "type": "Feature",
  "properties": {
    "addr:full":"Unit 5 - 213 Place Rd Geraldton WA 6530",
    "addr:housenumber":"213",
    "addr:postcode":"6530",
    "addr:street":"Place Rd",
    "iso:country":"AU",
    "sg:address":"Unit 5 - 213 Place Rd",
    "sg:city":"Geraldton",
    "sg:classifiers":[
        {
            "category":"Professional",
            "subcategory":"Printing & Photocopies",
            "type":"Services"
        }
    ],
    "sg:phone":"+61 8 9921 6579",
    "sg:postcode":"6530",
    "sg:province":"WA",
    "sg:tags":[
        "photocopying"
    ],
    "wof:name":"Beemac Print & Design",
    "wof:placetype":"venue"
},
  "geometry": {"coordinates":[114.62653350799999,-28.7590637207],"type":"Point"}
}