{
  "type": "Feature",
  "properties": {
    "addr:full":"9 Farley St Derwent Park TAS 7009",
    "addr:housenumber":"9",
    "addr:postcode":"7009",
    "addr:street":"Farley St",
    "iso:country":"AU",
    "sg:address":"9 Farley St",
    "sg:city":"Derwent Park",
    "sg:classifiers":[
        {
            "category":"Shopping",
            "subcategory":"Stationery & Office Supplies",
            "type":"Retail Goods"
        }
    ],
    "sg:phone":"+61 3 6272 0042",
    "sg:postcode":"7009",
    "sg:province":"TAS",
    "sg:tags":[
        "partition"
    ],
    "wof:name":"Specialised Plaster & construction",
    "wof:placetype":"venue"
},
  "geometry": {"coordinates":[147.28651428200001,-42.8344802856],"type":"Point"}
}