{
  "type": "Feature",
  "properties": {
    "iso:country":"AU",
    "sg:address":"94 Farquhar St",
    "sg:city":"Bordertown",
    "sg:classifiers":[
        {
            "category":"Transit Center",
            "subcategory":"Passenger",
            "type":"Transportation"
        }
    ],
    "sg:phone":"+61 8 8752 1025",
    "sg:postcode":"5268",
    "sg:province":"SA",
    "sg:tags":[
        "frozen",
        "food",
        "retail"
    ],
    "wof:name":"Richards Frozen Food Distributors",
    "wof:placetype":"venue"
},
  "geometry": {"coordinates":[140.773956,-36.309975],"type":"Point"}
}