{
  "type": "Feature",
  "properties": {
    "addr:full":"3 Stawell St Cranbourne VIC 3977",
    "addr:housenumber":"3",
    "addr:postcode":"3977",
    "addr:street":"Stawell St",
    "iso:country":"AU",
    "sg:address":"3 Stawell St",
    "sg:city":"Cranbourne",
    "sg:classifiers":[
        {
            "category":"Professional",
            "subcategory":"Employment Agencies",
            "type":"Services"
        }
    ],
    "sg:phone":"+61 3 5995 3705",
    "sg:postcode":"3977",
    "sg:province":"VIC",
    "sg:tags":[
        "hire",
        "labour",
        "contractor"
    ],
    "wof:name":"Workforce Extensions",
    "wof:placetype":"venue"
},
  "geometry": {"coordinates":[145.28361511200001,-38.1078796387],"type":"Point"}
}