{
  "type": "Feature",
  "properties": {
    "addr:full":"U4/ 26 Charles St Abbotsford NSW 2046",
    "addr:housenumber":"26",
    "addr:postcode":"2046",
    "addr:street":"U4 /;Charles St",
    "iso:country":"AU",
    "sg:address":"U4/ 26 Charles St",
    "sg:city":"Abbotsford",
    "sg:classifiers":[
        {
            "category":"Professional",
            "type":"Services"
        }
    ],
    "sg:phone":"+61 418 245 280",
    "sg:postcode":"2046",
    "sg:province":"NSW",
    "sg:tags":[
        "transport"
    ],
    "wof:name":"A Carter & Sons",
    "wof:placetype":"venue"
},
  "geometry": {"coordinates":[151.131317,-33.86219],"type":"Point"}
}