{
  "type": "Feature",
  "properties": {
    "addr:full":"4 Falmouth St Hawthorn VIC 3122",
    "addr:housenumber":"4",
    "addr:postcode":"3122",
    "addr:street":"Falmouth St",
    "iso:country":"AU",
    "sg:address":"4 Falmouth St",
    "sg:city":"Hawthorn",
    "sg:classifiers":[
        {
            "category":"Professional",
            "subcategory":"Secretarial Services",
            "type":"Services"
        }
    ],
    "sg:phone":"+61 3 9815 2127",
    "sg:postcode":"3122",
    "sg:province":"VIC",
    "sg:tags":[
        "typing"
    ],
    "wof:name":"Hummingbird Enterprises",
    "wof:placetype":"venue"
},
  "geometry": {"coordinates":[145.04060363799999,-37.8202056885],"type":"Point"}
}