{
  "type": "Feature",
  "properties": {
    "iso:country":"AU",
    "sg:address":"129 Mackenzie St",
    "sg:city":"Hackett",
    "sg:classifiers":[
        {
            "category":"Organizations",
            "subcategory":"Non-profit Organization",
            "type":"Services"
        }
    ],
    "sg:phone":"+61 2 6248 8004",
    "sg:postcode":"2602",
    "sg:province":"ACT",
    "sg:tags":[
        "environmental",
        "organisation",
        "conservation"
    ],
    "wof:name":"Canberra Organic Growers Society Inc",
    "wof:placetype":"venue"
},
  "geometry": {"coordinates":[149.161834717,-35.2542190552],"type":"Point"}
}