{
  "type": "Feature",
  "properties": {
    "iso:country":"AU",
    "sg:address":"204 Fisheries Rd",
    "sg:city":"Five Ways",
    "sg:classifiers":[
        {
            "category":"Home & Garden",
            "subcategory":"Building Materials",
            "type":"Retail Goods"
        }
    ],
    "sg:phone":"+61 3 5998 2457",
    "sg:postcode":"3977",
    "sg:province":"VIC",
    "sg:tags":[
        "concrete",
        "additive"
    ],
    "wof:name":"Just Dust",
    "wof:placetype":"venue"
},
  "geometry": {"coordinates":[145.31492614699999,-38.1784210205],"type":"Point"}
}