{
  "type": "Feature",
  "properties": {
    "addr:full":"3 Sheridan Ave Frankston VIC 3199",
    "addr:housenumber":"3",
    "addr:postcode":"3199",
    "addr:street":"Sheridan Ave",
    "iso:country":"AU",
    "sg:address":"3 Sheridan Ave",
    "sg:city":"Frankston",
    "sg:classifiers":[
        {
            "category":"Retail",
            "subcategory":"Repair Shop",
            "type":"Services"
        }
    ],
    "sg:phone":"+61 414 473 262",
    "sg:postcode":"3199",
    "sg:province":"VIC",
    "sg:tags":[
        "restorer",
        "repairer",
        "carpet"
    ],
    "wof:name":"Total Recovery",
    "wof:placetype":"venue"
},
  "geometry": {"coordinates":[145.255584717,-37.9323806763],"type":"Point"}
}