{
  "type": "Feature",
  "properties": {
    "addr:full":"37 Boneo Rd Rosebud VIC 3939",
    "addr:housenumber":"37",
    "addr:postcode":"3939",
    "addr:street":"Boneo Rd",
    "iso:country":"AU",
    "sg:address":"37 Boneo Rd",
    "sg:city":"Rosebud",
    "sg:classifiers":[
        {
            "category":"Health Services",
            "subcategory":"Health Practitioner",
            "type":"Services"
        }
    ],
    "sg:phone":"+61 3 5981 1774",
    "sg:postcode":"3939",
    "sg:province":"VIC",
    "sg:tags":[
        "naturopath"
    ],
    "wof:name":"Bayside Holistic Professionals",
    "wof:placetype":"venue"
},
  "geometry": {"coordinates":[144.88975524899999,-38.3629837036],"type":"Point"}
}