{
  "type": "Feature",
  "properties": {
    "iso:country":"AU",
    "sg:address":"62 Armstrong St",
    "sg:city":"North Rockhampton",
    "sg:classifiers":[
        {
            "category":"Social Services",
            "subcategory":"Job Training",
            "type":"Services"
        }
    ],
    "sg:phone":"+61 7 4927 7775",
    "sg:postcode":"4701",
    "sg:province":"QLD",
    "sg:tags":[
        "sport"
    ],
    "wof:name":"Trim Gym Health & Fitness Centre",
    "wof:placetype":"venue"
},
  "geometry": {"coordinates":[150.52330017099999,-23.3667640686],"type":"Point"}
}