{
  "type": "Feature",
  "properties": {
    "addr:full":"PO Box 1161 Windsor VIC 3181",
    "addr:postcode":"3181",
    "iso:country":"AU",
    "sg:address":"PO Box 1161",
    "sg:city":"Windsor",
    "sg:classifiers":[
        {
            "category":"Wholesale",
            "subcategory":"Music Publishers",
            "type":"Manufacturing & Wholesale Goods"
        }
    ],
    "sg:phone":"+61 3 9510 5626",
    "sg:postcode":"3181",
    "sg:province":"VIC",
    "sg:tags":[
        "wholesaler",
        "dvd",
        "mfrs",
        "cd"
    ],
    "wof:name":"Cannon Music Co. Pty Ltd",
    "wof:placetype":"venue"
},
  "geometry": {"coordinates":[144.99253845199999,-37.8561897278],"type":"Point"}
}