{
  "type": "Feature",
  "properties": {
    "addr:full":"1b Patterson Rd Bentleigh VIC 3204",
    "addr:housenumber":"1b",
    "addr:postcode":"3204",
    "addr:street":"Patterson Rd",
    "iso:country":"AU",
    "sg:address":"1b Patterson Rd",
    "sg:city":"Bentleigh",
    "sg:classifiers":[
        {
            "category":"Professional",
            "subcategory":"Art Services",
            "type":"Services"
        }
    ],
    "sg:phone":"+61 438 523 895",
    "sg:postcode":"3204",
    "sg:province":"VIC",
    "sg:tags":[
        "graphic",
        "designer"
    ],
    "wof:name":"Art Design & Illustration",
    "wof:placetype":"venue"
},
  "geometry": {"coordinates":[145.02667199999999,-37.924583],"type":"Point"}
}