{
  "type": "Feature",
  "properties": {
    "iso:country":"AU",
    "sg:address":"Cessnock Rd",
    "sg:city":"Abermain",
    "sg:classifiers":[
        {
            "category":"Government",
            "subcategory":"Fire Station",
            "type":"Public Place"
        }
    ],
    "sg:phone":"+61 2 4930 4271",
    "sg:postcode":"2326",
    "sg:province":"NSW",
    "sg:tags":[
        "brigade"
    ],
    "wof:name":"Fire Brigades-NSW",
    "wof:placetype":"venue"
},
  "geometry": {"coordinates":[151.427490234,-32.8111228943],"type":"Point"}
}