{
  "type": "Feature",
  "properties": {
    "iso:country":"AU",
    "sg:address":"25 Scoresby Rd",
    "sg:city":"Bayswater",
    "sg:classifiers":[
        {
            "category":"Shopping",
            "subcategory":"Discount & Variety Stores",
            "type":"Retail Goods"
        }
    ],
    "sg:phone":"+61 3 9738 1849",
    "sg:postcode":"3153",
    "sg:province":"VIC",
    "sg:tags":[
        "shop",
        "adult"
    ],
    "wof:name":"Club X",
    "wof:placetype":"venue"
},
  "geometry": {"coordinates":[145.27078247099999,-37.8417205811],"type":"Point"}
}