{
  "type": "Feature",
  "properties": {
    "addr:full":"310 Chesterville Rd Moorabbin VIC 3189",
    "addr:housenumber":"310",
    "addr:postcode":"3189",
    "addr:street":"Chesterville Rd",
    "iso:country":"AU",
    "sg:address":"310 Chesterville Rd",
    "sg:city":"Moorabbin",
    "sg:classifiers":[
        {
            "category":"Building & Trades",
            "subcategory":"Construction",
            "type":"Services"
        }
    ],
    "sg:phone":"+61 418 561 398",
    "sg:postcode":"3189",
    "sg:province":"VIC",
    "sg:tags":[
        "fencing",
        "contractor"
    ],
    "wof:name":"John Beyer & Associates",
    "wof:placetype":"venue"
},
  "geometry": {"coordinates":[145.06097412099999,-37.9389762878],"type":"Point"}
}