{
  "type": "Feature",
  "properties": {
    "addr:full":"\"My Lindera Stud\" Sugarloaf Rd Williamstown SA 5351",
    "addr:postcode":"5351",
    "addr:street":"Sugarloaf Rd",
    "iso:country":"AU",
    "sg:address":"\"My Lindera Stud\" Sugarloaf Rd",
    "sg:city":"Williamstown",
    "sg:classifiers":[
        {
            "category":"Farming",
            "subcategory":"Farm",
            "type":"Manufacturing & Wholesale Goods"
        }
    ],
    "sg:phone":"+61 8 8524 6081",
    "sg:postcode":"5351",
    "sg:province":"SA",
    "sg:tags":[
        "farmer"
    ],
    "wof:name":"Koch D R & M J",
    "wof:placetype":"venue"
},
  "geometry": {"coordinates":[138.90452575699999,-34.6435585022],"type":"Point"}
}