{
  "type": "Feature",
  "properties": {
    "iso:country":"AU",
    "sg:address":"1st Flr 48 Flushcombe Rd",
    "sg:city":"Blacktown",
    "sg:classifiers":[
        {
            "category":"Health Services",
            "subcategory":"Dentist",
            "type":"Services"
        }
    ],
    "sg:phone":"+61 2 9621 1530",
    "sg:postcode":"2148",
    "sg:province":"NSW",
    "wof:name":"Ang Sam",
    "wof:placetype":"venue"
},
  "geometry": {"coordinates":[150.90855407699999,-33.7709960938],"type":"Point"}
}