{
  "type": "Feature",
  "properties": {
    "addr:full":"10 Anvil Rd Seven Hills NSW 2147",
    "addr:housenumber":"10",
    "addr:postcode":"2147",
    "addr:street":"Anvil Rd",
    "iso:country":"AU",
    "sg:address":"10 Anvil Rd",
    "sg:city":"Seven Hills",
    "sg:classifiers":[
        {
            "category":"Landmark",
            "subcategory":"Scenic View",
            "type":"Public Place"
        }
    ],
    "sg:phone":"+61 2 9624 8160",
    "sg:postcode":"2147",
    "sg:province":"NSW",
    "sg:tags":[
        "staircase",
        "handrail"
    ],
    "wof:name":"Soltan Pty Ltd",
    "wof:placetype":"venue"
},
  "geometry": {"coordinates":[150.95762634299999,-33.7774505615],"type":"Point"}
}