{
  "type": "Feature",
  "properties": {
    "addr:full":"10 Sunnyside Ave Nunawading VIC 3131",
    "addr:housenumber":"10",
    "addr:postcode":"3131",
    "addr:street":"Sunnyside Ave",
    "iso:country":"AU",
    "sg:address":"10 Sunnyside Ave",
    "sg:city":"Nunawading",
    "sg:classifiers":[
        {
            "category":"Health Services",
            "subcategory":"Health Practitioner",
            "type":"Services"
        }
    ],
    "sg:phone":"+61 3 9874 0470",
    "sg:postcode":"3131",
    "sg:province":"VIC",
    "sg:tags":[
        "naturopath"
    ],
    "wof:name":"Anne M. Mills",
    "wof:placetype":"venue"
},
  "geometry": {"coordinates":[145.18170165999999,-37.8119049072],"type":"Point"}
}