{
  "type": "Feature",
  "properties": {
    "addr:full":"Shop 45, Metro Maddington Shopping Centre Attfield St Maddington WA 6109",
    "addr:housenumber":"shop 45",
    "addr:postcode":"6109",
    "addr:street":"Attfield St",
    "iso:country":"AU",
    "sg:address":"Shop 45, Metro Maddington Shopping Centre Attfield St",
    "sg:city":"Maddington",
    "sg:classifiers":[
        {
            "category":"Food & Beverages",
            "subcategory":"Bakery",
            "type":"Retail Goods"
        }
    ],
    "sg:phone":"+61 8 9452 3300",
    "sg:postcode":"6109",
    "sg:province":"WA",
    "sg:tags":[
        "baker"
    ],
    "wof:name":"Bakers Delight",
    "wof:placetype":"venue"
},
  "geometry": {"coordinates":[115.992759705,-32.0429077148],"type":"Point"}
}