{
  "type": "Feature",
  "properties": {
    "iso:country":"AU",
    "sg:address":"Cnr Sudlow St & Phoenix Rd",
    "sg:city":"Spearwood",
    "sg:classifiers":[
        {
            "category":"Insurance",
            "subcategory":"Insurance Agent",
            "type":"Services"
        }
    ],
    "sg:phone":"+61 8 9418 0888",
    "sg:postcode":"6163",
    "sg:province":"WA",
    "sg:tags":[
        "wool",
        "broker"
    ],
    "wof:name":"Landmark",
    "wof:placetype":"venue"
},
  "geometry": {"coordinates":[115.78331,-32.093731],"type":"Point"}
}