{
  "type": "Feature",
  "properties": {
    "addr:full":"115 Bondi Rd Bondi NSW 2026",
    "addr:housenumber":"115",
    "addr:postcode":"2026",
    "addr:street":"Bondi Rd",
    "iso:country":"AU",
    "sg:address":"115 Bondi Rd",
    "sg:city":"Bondi",
    "sg:classifiers":[
        {
            "category":"Communications",
            "subcategory":"Film & Video Production",
            "type":"Services"
        }
    ],
    "sg:phone":"+61 2 9387 5077",
    "sg:postcode":"2026",
    "sg:province":"NSW",
    "sg:tags":[
        "dvd",
        "library"
    ],
    "wof:name":"Civic Video Bondi Rd",
    "wof:placetype":"venue"
},
  "geometry": {"coordinates":[151.26203918499999,-33.8937644958],"type":"Point"}
}