{
  "type": "Feature",
  "properties": {
    "addr:full":"Room 3/ 550 Englehart St Albury NSW 2640",
    "addr:housenumber":"/ 550",
    "addr:postcode":"2640",
    "addr:street":"Englehart St",
    "iso:country":"AU",
    "sg:address":"Room 3/ 550 Englehart St",
    "sg:city":"Albury",
    "sg:classifiers":[
        {
            "category":"Personal",
            "subcategory":"Massage",
            "type":"Services"
        }
    ],
    "sg:phone":"+61 2 6021 1450",
    "sg:postcode":"2640",
    "sg:province":"NSW",
    "sg:tags":[
        "therapy"
    ],
    "wof:name":"Grant McCallum Sport & Remedial Therapy",
    "wof:placetype":"venue"
},
  "geometry": {"coordinates":[146.915924072,-36.0781364441],"type":"Point"}
}