{
  "type": "Feature",
  "properties": {
    "addr:full":"Shop 1 31 Cambridge Rd Bellerive TAS 7018",
    "addr:housenumber":"shop;31",
    "addr:postcode":"7018",
    "addr:street":"Cambridge Rd",
    "iso:country":"AU",
    "sg:address":"Shop 1 31 Cambridge Rd",
    "sg:city":"Bellerive",
    "sg:classifiers":[
        {
            "category":"Banks & Credit Unions",
            "subcategory":"Bank",
            "type":"Services"
        }
    ],
    "sg:phone":"+61 438 738 055",
    "sg:postcode":"7018",
    "sg:province":"TAS",
    "sg:tags":[
        "broker",
        "mortgage"
    ],
    "wof:name":"Mansfield Finance",
    "wof:placetype":"venue"
},
  "geometry": {"coordinates":[147.36343383799999,-42.8671684265],"type":"Point"}
}