{
  "type": "Feature",
  "properties": {
    "iso:country":"AU",
    "sg:address":"Level 8, 155 King St",
    "sg:city":"Sydney",
    "sg:classifiers":[
        {
            "category":"Real Estate",
            "subcategory":"Real Estate Services",
            "type":"Services"
        }
    ],
    "sg:phone":"+61 2 9221 7500",
    "sg:postcode":"2000",
    "sg:province":"NSW",
    "sg:tags":[
        "valuer"
    ],
    "wof:name":"Antony Christian & Assoc Pty Ltd",
    "wof:placetype":"venue"
},
  "geometry": {"coordinates":[151.20982360799999,-33.8691902161],"type":"Point"}
}