{
  "type": "Feature",
  "properties": {
    "addr:full":"Shop 21 Hub Commercial Centre Kwinana Kwinana WA 6167",
    "addr:housenumber":"shop 21 hub",
    "addr:postcode":"6167",
    "iso:country":"AU",
    "sg:address":"Shop 21",
    "sg:city":"Hub Commercial Centre Kwinana Kwinana",
    "sg:classifiers":[
        {
            "category":"Communications",
            "subcategory":"Film & Video Production",
            "type":"Services"
        }
    ],
    "sg:phone":"+61 8 9439 5599",
    "sg:postcode":"6167",
    "sg:province":"WA",
    "sg:tags":[
        "dvd",
        "library"
    ],
    "wof:name":"Video Ezy",
    "wof:placetype":"venue"
},
  "geometry": {"coordinates":[115.82785,-32.220089],"type":"Point"}
}