{
  "type": "Feature",
  "properties": {
    "addr:full":"351 Dalton Rd Epping VIC 3076",
    "addr:housenumber":"351",
    "addr:postcode":"3076",
    "addr:street":"Dalton Rd",
    "iso:country":"AU",
    "sg:address":"351 Dalton Rd",
    "sg:city":"Epping",
    "sg:classifiers":[
        {
            "category":"Health Services",
            "subcategory":"Doctor",
            "type":"Services"
        }
    ],
    "sg:phone":"+61 3 9401 4444",
    "sg:postcode":"3076",
    "sg:province":"VIC",
    "sg:tags":[
        "medical",
        "practitioner"
    ],
    "wof:name":"Gya Mr.",
    "wof:placetype":"venue"
},
  "geometry": {"coordinates":[145.030319214,-37.6599769592],"type":"Point"}
}