{
  "type": "Feature",
  "properties": {
    "addr:full":"121 Elliott Rd Karrinyup WA 6018",
    "addr:housenumber":"121",
    "addr:postcode":"6018",
    "addr:street":"Elliott Rd",
    "iso:country":"AU",
    "sg:address":"121 Elliott Rd",
    "sg:city":"Karrinyup",
    "sg:classifiers":[
        {
            "category":"Professional",
            "type":"Services"
        }
    ],
    "sg:phone":"+61 8 9245 5400",
    "sg:postcode":"6018",
    "sg:province":"WA",
    "sg:tags":[
        "quality",
        "assurance"
    ],
    "wof:name":"Qamis Quality Assurance Marine & Industrial Services",
    "wof:placetype":"venue"
},
  "geometry": {"coordinates":[115.760887146,-31.8822231293],"type":"Point"}
}