{
  "type": "Feature",
  "properties": {
    "addr:full":"Shop 1, 279 South St Hilton WA 6163",
    "addr:housenumber":"shop 1 279",
    "addr:postcode":"6163",
    "addr:street":"South St",
    "iso:country":"AU",
    "sg:address":"Shop 1, 279 South St",
    "sg:city":"Hilton",
    "sg:classifiers":[
        {
            "category":"Personal",
            "subcategory":"Beauty Salon",
            "type":"Services"
        }
    ],
    "sg:phone":"+61 8 9337 4176",
    "sg:postcode":"6163",
    "sg:province":"WA",
    "sg:tags":[
        "hairdresser"
    ],
    "wof:name":"Essence Hair Design",
    "wof:placetype":"venue"
},
  "geometry": {"coordinates":[115.78009,-32.063381],"type":"Point"}
}