{
  "type": "Feature",
  "properties": {
    "addr:full":"3 Levuka St, Seaford VIC 3198",
    "addr:housenumber":"3",
    "addr:postcode":"3198",
    "addr:street":"Levuka St",
    "iso:country":"AU",
    "sg:address":"3 Levuka St,",
    "sg:city":"Seaford",
    "sg:classifiers":[
        {
            "category":"Building & Trades",
            "subcategory":"Landscaping Services",
            "type":"Services"
        }
    ],
    "sg:phone":"+61 3 9786 4919",
    "sg:postcode":"3198",
    "sg:province":"VIC",
    "sg:tags":[
        "designer",
        "landscape",
        "contractor"
    ],
    "wof:name":"Bayscapes",
    "wof:placetype":"venue"
},
  "geometry": {"coordinates":[145.13059997600001,-38.1116714478],"type":"Point"}
}