{
  "type": "Feature",
  "properties": {
    "addr:full":"Waterside East Office Tower 10 Holden Place Bundall QLD 4217",
    "addr:housenumber":"10",
    "addr:postcode":"4217",
    "addr:street":"Holden Place",
    "iso:country":"AU",
    "sg:address":"Waterside East Office Tower 10",
    "sg:city":"Holden Place Bundall",
    "sg:classifiers":[
        {
            "category":"Professional",
            "subcategory":"Art Services",
            "type":"Services"
        }
    ],
    "sg:phone":"+61 7 5574 1463",
    "sg:postcode":"4217",
    "sg:province":"QLD",
    "sg:tags":[
        "graphic",
        "designer"
    ],
    "wof:name":"Snap Printing",
    "wof:placetype":"venue"
},
  "geometry": {"coordinates":[153.41343689000001,-28.0004253387],"type":"Point"}
}