{
  "type": "Feature",
  "properties": {
    "iso:country":"AU",
    "sg:address":"167 Magill Rd",
    "sg:city":"Maylands",
    "sg:classifiers":[
        {
            "category":"Shopping",
            "subcategory":"Antiques",
            "type":"Retail Goods"
        }
    ],
    "sg:phone":"+61 421 901 075",
    "sg:postcode":"5069",
    "sg:province":"SA",
    "wof:name":"Kensington Rd Antiques",
    "wof:placetype":"venue"
},
  "geometry": {"coordinates":[138.633666992,-34.9149971008],"type":"Point"}
}