{
  "type": "Feature",
  "properties": {
    "addr:full":"U5, 19 San Marco Qys Mandurah WA 6210",
    "addr:housenumber":"19",
    "addr:postcode":"6210",
    "addr:street":"U5",
    "iso:country":"AU",
    "sg:address":"U5, 19 San Marco Qys",
    "sg:city":"Mandurah",
    "sg:classifiers":[
        {
            "category":"Professional",
            "subcategory":"Art Services",
            "type":"Services"
        }
    ],
    "sg:phone":"+61 400 764 603",
    "sg:postcode":"6210",
    "sg:province":"WA",
    "sg:tags":[
        "interior",
        "designer"
    ],
    "wof:name":"Amber Bridgman Design",
    "wof:placetype":"venue"
},
  "geometry": {"coordinates":[115.716362,-32.537605],"type":"Point"}
}