{
  "type": "Feature",
  "properties": {
    "addr:full":"35 MacDonald St Paddington NSW 2021",
    "addr:housenumber":"35",
    "addr:postcode":"2021",
    "addr:street":"Macdonald St",
    "iso:country":"AU",
    "sg:address":"35 MacDonald St",
    "sg:city":"Paddington",
    "sg:classifiers":[
        {
            "category":"Professional",
            "subcategory":"Art Services",
            "type":"Services"
        }
    ],
    "sg:phone":"+61 2 9380 5581",
    "sg:postcode":"2021",
    "sg:province":"NSW",
    "sg:tags":[
        "interior",
        "decorator"
    ],
    "wof:name":"Pruden Patricia Interiors",
    "wof:placetype":"venue"
},
  "geometry": {"coordinates":[151.224884033,-33.8814620972],"type":"Point"}
}