{
  "type": "Feature",
  "properties": {
    "iso:country":"AU",
    "sg:address":"46b Leichardt Pl",
    "sg:city":"Broome",
    "sg:classifiers":[
        {
            "category":"Building & Trades",
            "subcategory":"Cleaning & Sanitation",
            "type":"Services"
        }
    ],
    "sg:phone":"+61 417 988 699",
    "sg:postcode":"6725",
    "sg:province":"WA",
    "sg:tags":[
        "industrial",
        "commercial",
        "contractor"
    ],
    "wof:name":"Kimberley Cleaning Contractors",
    "wof:placetype":"venue"
},
  "geometry": {"coordinates":[122.677589416,-18.2141704559],"type":"Point"}
}