{
  "type": "Feature",
  "properties": {
    "addr:full":"PO Box 4178 + Eight Mile Plains QLD 4113",
    "addr:postcode":"4113",
    "iso:country":"AU",
    "sg:address":"PO Box 4178",
    "sg:city":"+ Eight Mile Plains",
    "sg:classifiers":[
        {
            "category":"Health Services",
            "subcategory":"Doctor",
            "type":"Services"
        }
    ],
    "sg:phone":"+61 7 3841 3358",
    "sg:postcode":"4113",
    "sg:province":"QLD",
    "sg:tags":[
        "medical",
        "practitioner"
    ],
    "wof:name":"Medeco Pty Ltd",
    "wof:placetype":"venue"
},
  "geometry": {"coordinates":[153.08757019000001,-27.5755405426],"type":"Point"}
}