{
  "type": "Feature",
  "properties": {
    "addr:full":"Unit 2/ 78 Adelong Rd Tumut NSW 2720",
    "addr:housenumber":"78",
    "addr:postcode":"2720",
    "addr:street":"Adelong Rd",
    "iso:country":"AU",
    "sg:address":"Unit 2/ 78 Adelong Rd",
    "sg:city":"Tumut",
    "sg:classifiers":[
        {
            "category":"Retail",
            "subcategory":"Auto Rental",
            "type":"Services"
        }
    ],
    "sg:phone":"+61 2 6947 2697",
    "sg:postcode":"2720",
    "sg:province":"NSW",
    "sg:tags":[
        "car",
        "hire",
        "minibus"
    ],
    "wof:name":"Hertz",
    "wof:placetype":"venue"
},
  "geometry": {"coordinates":[148.212143,-35.295868],"type":"Point"}
}