{
  "type": "Feature",
  "properties": {
    "addr:full":"Targinnie Rd Yarwun QLD 4694",
    "addr:postcode":"4694",
    "addr:street":"Targinnie Rd",
    "iso:country":"AU",
    "sg:address":"Targinnie Rd",
    "sg:city":"Yarwun",
    "sg:classifiers":[
        {
            "category":"Farming",
            "subcategory":"Berry Farm",
            "type":"Manufacturing & Wholesale Goods"
        }
    ],
    "sg:phone":"+61 7 4973 6585",
    "sg:postcode":"4694",
    "sg:province":"QLD",
    "sg:tags":[
        "fruit",
        "grower"
    ],
    "wof:name":"Capricorn Tropical Fruits",
    "wof:placetype":"venue"
},
  "geometry": {"coordinates":[151.11932373100001,-23.8337688446],"type":"Point"}
}