{
  "type": "Feature",
  "properties": {
    "iso:country":"AU",
    "sg:address":"14 Wyton Pl",
    "sg:city":"Gosnells",
    "sg:classifiers":[
        {
            "category":"Building & Trades",
            "subcategory":"Equipment Rental",
            "type":"Services"
        }
    ],
    "sg:phone":"+61 8 9398 4512",
    "sg:postcode":"6110",
    "sg:province":"WA",
    "sg:tags":[
        "repairing",
        "changing",
        "retreading",
        "tyre"
    ],
    "wof:name":"Wheel Weight & Patch Suppliers",
    "wof:placetype":"venue"
},
  "geometry": {"coordinates":[115.988647461,-32.0711784363],"type":"Point"}
}