{
  "type": "Feature",
  "properties": {
    "iso:country":"AU",
    "sg:address":"PO Box 63",
    "sg:city":"Kalorama",
    "sg:classifiers":[
        {
            "category":"Real Estate",
            "subcategory":"Architect",
            "type":"Services"
        }
    ],
    "sg:phone":"+61 408 144 572",
    "sg:postcode":"3766",
    "sg:province":"VIC",
    "sg:tags":[
        "building",
        "designer"
    ],
    "wof:name":"Fentech Design Group",
    "wof:placetype":"venue"
},
  "geometry": {"coordinates":[145.36671447800001,-37.8179397583],"type":"Point"}
}