{
  "type": "Feature",
  "properties": {
    "iso:country":"AU",
    "sg:address":"7 Forrest Ave",
    "sg:city":"Bunbury",
    "sg:classifiers":[
        {
            "category":"Health Services",
            "subcategory":"Chiropractor",
            "type":"Services"
        }
    ],
    "sg:phone":"+61 8 9721 6109",
    "sg:postcode":"6230",
    "sg:province":"WA",
    "wof:name":"Willmore Damon",
    "wof:placetype":"venue"
},
  "geometry": {"coordinates":[115.641861,-33.337269],"type":"Point"}
}