{
  "type": "Feature",
  "properties": {
    "addr:full":"24 Narelle St Bondi NSW 2026",
    "addr:housenumber":"24",
    "addr:postcode":"2026",
    "addr:street":"Narelle St",
    "iso:country":"AU",
    "sg:address":"24 Narelle St",
    "sg:city":"Bondi",
    "sg:classifiers":[
        {
            "category":"Communications",
            "subcategory":"News Services",
            "type":"Services"
        }
    ],
    "sg:phone":"+61 2 9388 2021",
    "sg:postcode":"2026",
    "sg:province":"NSW",
    "sg:tags":[
        "information",
        "tourist",
        "attractions"
    ],
    "wof:name":"Signature Tours & Promotions",
    "wof:placetype":"venue"
},
  "geometry": {"coordinates":[151.27421569800001,-33.8791389465],"type":"Point"}
}