{
  "type": "Feature",
  "properties": {
    "iso:country":"AU",
    "sg:address":"5B North St",
    "sg:city":"Balmain",
    "sg:classifiers":[
        {
            "category":"Retail",
            "subcategory":"Repair Shop",
            "type":"Services"
        }
    ],
    "sg:phone":"+61 2 9810 3785",
    "sg:postcode":"2041",
    "sg:province":"NSW",
    "sg:tags":[
        "upholsterer"
    ],
    "wof:name":"Cameron McFarlane Fine Upholstery",
    "wof:placetype":"venue"
},
  "geometry": {"coordinates":[151.177658,-33.856003],"type":"Point"}
}