{
  "type": "Feature",
  "properties": {
    "iso:country":"AU",
    "sg:address":"162 Chisholm Rd",
    "sg:city":"Auburn",
    "sg:classifiers":[
        {
            "category":"Building & Trades",
            "subcategory":"Construction",
            "type":"Services"
        }
    ],
    "sg:phone":"+61 2 9749 4807",
    "sg:postcode":"2144",
    "sg:province":"NSW",
    "sg:tags":[
        "fencing",
        "contractor"
    ],
    "wof:name":"Savrin Fencing",
    "wof:placetype":"venue"
},
  "geometry": {"coordinates":[151.01963806099999,-33.8585662842],"type":"Point"}
}