{
  "type": "Feature",
  "properties": {
    "addr:full":"PO Box 491 Kelmscott PO Boxes WA 6991",
    "addr:postcode":"6991",
    "iso:country":"AU",
    "sg:address":"PO Box 491",
    "sg:city":"Kelmscott PO Boxes",
    "sg:classifiers":[
        {
            "category":"Banks & Credit Unions",
            "subcategory":"Financial Services",
            "type":"Services"
        }
    ],
    "sg:phone":"+61 8 9390 0800",
    "sg:postcode":"6991",
    "sg:province":"WA",
    "sg:tags":[
        "annuity",
        "rollover",
        "superannuation",
        "consultant"
    ],
    "wof:name":"Superannuation Advisory Service",
    "wof:placetype":"venue"
},
  "geometry": {"coordinates":[116.01589199999999,-32.114059],"type":"Point"}
}