{
  "type": "Feature",
  "properties": {
    "addr:full":"2/ 90 Charles St Putney NSW 2112",
    "addr:housenumber":"/ 90",
    "addr:postcode":"2112",
    "addr:street":"Charles St",
    "iso:country":"AU",
    "sg:address":"2/ 90 Charles St",
    "sg:city":"Putney",
    "sg:classifiers":[
        {
            "category":"Real Estate",
            "subcategory":"Real Estate Agent",
            "type":"Services"
        }
    ],
    "sg:phone":"+61 2 9807 2255",
    "sg:postcode":"2112",
    "sg:province":"NSW",
    "wof:name":"Ryde Real Estate",
    "wof:placetype":"venue"
},
  "geometry": {"coordinates":[151.10882568400001,-33.8233413696],"type":"Point"}
}