{
  "type": "Feature",
  "properties": {
    "addr:full":"135 Wanda Rd Upper Mt Gravatt QLD 4122",
    "addr:housenumber":"135",
    "addr:postcode":"4122",
    "addr:street":"Wanda Rd Upper",
    "iso:country":"AU",
    "sg:address":"135 Wanda Rd",
    "sg:city":"Upper Mt Gravatt",
    "sg:classifiers":[
        {
            "category":"Education",
            "subcategory":"Special Training",
            "type":"Public Place"
        }
    ],
    "sg:phone":"+61 7 3841 2949",
    "sg:postcode":"4122",
    "sg:province":"QLD",
    "sg:tags":[
        "tuition-educational"
    ],
    "wof:name":"Ponnampalam S T English Tutor & Lim G S H",
    "wof:placetype":"venue"
},
  "geometry": {"coordinates":[153.087127686,-27.5498504639],"type":"Point"}
}