{
  "type": "Feature",
  "properties": {
    "iso:country":"AU",
    "sg:address":"Unit 1/ 71 Dundas Cct",
    "sg:city":"Phillip",
    "sg:classifiers":[
        {
            "category":"Building & Trades",
            "subcategory":"Construction",
            "type":"Services"
        }
    ],
    "sg:phone":"+61 2 6281 3311",
    "sg:postcode":"2606",
    "sg:province":"ACT",
    "sg:tags":[
        "contractor"
    ],
    "wof:name":"Narona Homes Pty Ltd",
    "wof:placetype":"venue"
},
  "geometry": {"coordinates":[149.089553833,-35.3542709351],"type":"Point"}
}