{
  "type": "Feature",
  "properties": {
    "addr:full":"cnr Maude St & Mc Gibbony Crt Ararat VIC 3377",
    "addr:postcode":"3377",
    "addr:street":"Cnr Maude St & Mc Gibbony Crt",
    "iso:country":"AU",
    "sg:address":"cnr Maude St & Mc Gibbony Crt",
    "sg:city":"Ararat",
    "sg:classifiers":[
        {
            "category":"Professional",
            "subcategory":"Printing & Photocopies",
            "type":"Services"
        }
    ],
    "sg:phone":"+61 3 5352 7778",
    "sg:postcode":"3377",
    "sg:province":"VIC",
    "sg:tags":[
        "embroidery"
    ],
    "wof:name":"EmbroidAbility",
    "wof:placetype":"venue"
},
  "geometry": {"coordinates":[142.94354248100001,-37.2902793884],"type":"Point"}
}