{
  "type": "Feature",
  "properties": {
    "iso:country":"AU",
    "sg:address":"12 Barrinia St",
    "sg:city":"Slacks Creek",
    "sg:classifiers":[
        {
            "category":"Banks & Credit Unions",
            "subcategory":"Bank",
            "type":"Services"
        }
    ],
    "sg:phone":"+61 1800 631 740",
    "sg:postcode":"4127",
    "sg:province":"QLD",
    "sg:tags":[
        "equipment",
        "sale",
        "point"
    ],
    "wof:name":"Southern Imperial",
    "wof:placetype":"venue"
},
  "geometry": {"coordinates":[153.12600707999999,-27.6238002777],"type":"Point"}
}