{
  "type": "Feature",
  "properties": {
    "addr:full":"L 13 55 Clarence St Sydney NSW 2000",
    "addr:housenumber":"55",
    "addr:postcode":"2000",
    "addr:street":"Clarence St",
    "iso:country":"AU",
    "sg:address":"L 13 55 Clarence St",
    "sg:city":"Sydney",
    "sg:classifiers":[
        {
            "category":"Professional",
            "subcategory":"Employment Agencies",
            "type":"Services"
        }
    ],
    "sg:phone":"+61 2 8295 3010",
    "sg:postcode":"2000",
    "sg:province":"NSW",
    "wof:name":"Alliance Recruitment",
    "wof:placetype":"venue"
},
  "geometry": {"coordinates":[151.205154419,-33.8663024902],"type":"Point"}
}