{
  "type": "Feature",
  "properties": {
    "addr:full":"39 Mt Barker Rd Stirling SA 5152",
    "addr:housenumber":"39",
    "addr:postcode":"5152",
    "addr:street":"Mt Barker Rd",
    "iso:country":"AU",
    "sg:address":"39 Mt Barker Rd",
    "sg:city":"Stirling",
    "sg:classifiers":[
        {
            "category":"Sports & Exercise",
            "subcategory":"Gym",
            "type":"Entertainment"
        }
    ],
    "sg:phone":"+61 8 8339 3188",
    "sg:postcode":"5152",
    "sg:province":"SA",
    "sg:tags":[
        "pilate",
        "method"
    ],
    "wof:name":"Pilates ProActive",
    "wof:placetype":"venue"
},
  "geometry": {"coordinates":[138.72184753400001,-35.0078926086],"type":"Point"}
}