{
  "type": "Feature",
  "properties": {
    "iso:country":"AU",
    "sg:address":"638 Burwood Rd",
    "sg:city":"Hawthorn",
    "sg:classifiers":[
        {
            "category":"Utilities",
            "subcategory":"Electric",
            "type":"Services"
        }
    ],
    "sg:phone":"+61 1300 737 247",
    "sg:postcode":"3122",
    "sg:province":"VIC",
    "sg:tags":[
        "electrical",
        "contractor"
    ],
    "wof:name":"1300 Repair Pty Ltd",
    "wof:placetype":"venue"
},
  "geometry": {"coordinates":[145.04652404800001,-37.8240203857],"type":"Point"}
}