{
  "type": "Feature",
  "properties": {
    "iso:country":"AU",
    "sg:address":"1 Flinders St",
    "sg:city":"Port Kembla",
    "sg:classifiers":[
        {
            "category":"Manufacturing",
            "subcategory":"Tools & Machinery",
            "type":"Manufacturing & Wholesale Goods"
        }
    ],
    "sg:phone":"+61 2 4251 5100",
    "sg:postcode":"2505",
    "sg:province":"NSW",
    "sg:tags":[
        "earth",
        "excavating",
        "moving",
        "equipment"
    ],
    "wof:name":"National Hire The Cat Rental Store",
    "wof:placetype":"venue"
},
  "geometry": {"coordinates":[150.88832099999999,-34.473213],"type":"Point"}
}