{
  "type": "Feature",
  "properties": {
    "addr:full":"30 Paddock St Whittlesea VIC 3757",
    "addr:housenumber":"30",
    "addr:postcode":"3757",
    "addr:street":"Paddock St",
    "iso:country":"AU",
    "sg:address":"30 Paddock St",
    "sg:city":"Whittlesea",
    "sg:classifiers":[
        {
            "category":"Utilities",
            "subcategory":"Electric",
            "type":"Services"
        }
    ],
    "sg:phone":"+61 417 318 735",
    "sg:postcode":"3757",
    "sg:province":"VIC",
    "sg:tags":[
        "electrical",
        "contractor"
    ],
    "wof:name":"SKP Electrics Pty Ltd",
    "wof:placetype":"venue"
},
  "geometry": {"coordinates":[145.135513,-37.511429],"type":"Point"}
}