{
  "type": "Feature",
  "properties": {
    "addr:full":"501 South Rd Regency Park SA 5010",
    "addr:housenumber":"501",
    "addr:postcode":"5010",
    "addr:street":"South Rd",
    "iso:country":"AU",
    "sg:address":"501 South Rd",
    "sg:city":"Regency Park",
    "sg:classifiers":[
        {
            "category":"Manufacturing",
            "subcategory":"Motor Vehicles & Parts",
            "type":"Manufacturing & Wholesale Goods"
        }
    ],
    "sg:phone":"+61 8 8241 9400",
    "sg:postcode":"5010",
    "sg:province":"SA",
    "sg:tags":[
        "engine",
        "equipment",
        "diesel"
    ],
    "wof:name":"Scania Australia Pty Ltd",
    "wof:placetype":"venue"
},
  "geometry": {"coordinates":[138.570877075,-34.865978241],"type":"Point"}
}