{
  "type": "Feature",
  "properties": {
    "addr:full":"Murray Valley Hwy Kerang VIC 3579",
    "addr:postcode":"3579",
    "addr:street":"Valley Hwy",
    "iso:country":"AU",
    "sg:address":"Murray Valley Hwy",
    "sg:city":"Kerang",
    "sg:classifiers":[
        {
            "category":"Military Area",
            "subcategory":"Air Force Base",
            "type":"Public Place"
        }
    ],
    "sg:phone":"+61 3 5452 2633",
    "sg:postcode":"3579",
    "sg:province":"VIC",
    "sg:tags":[
        "conditioner",
        "treatment",
        "soil"
    ],
    "wof:name":"Eastern Spreading Services",
    "wof:placetype":"venue"
},
  "geometry": {"coordinates":[143.91793823200001,-35.7366371155],"type":"Point"}
}