{
  "type": "Feature",
  "properties": {
    "iso:country":"AU",
    "sg:address":"1440 Anzac Ave",
    "sg:city":"Kallangur",
    "sg:classifiers":[
        {
            "category":"Professional",
            "subcategory":"Accounting & Tax Preparation",
            "type":"Services"
        }
    ],
    "sg:phone":"+61 7 3204 5144",
    "sg:postcode":"4503",
    "sg:province":"QLD",
    "sg:tags":[
        "consultant",
        "taxation"
    ],
    "wof:name":"Paul Hislop & Associates",
    "wof:placetype":"venue"
},
  "geometry": {"coordinates":[152.99537658700001,-27.2499885559],"type":"Point"}
}