{
  "type": "Feature",
  "properties": {
    "addr:full":"Level 8, 412 Collins St Melbourne VIC 3000",
    "addr:housenumber":"412",
    "addr:postcode":"3000",
    "addr:street":"Collins St",
    "iso:country":"AU",
    "sg:address":"Level 8, 412 Collins St",
    "sg:city":"Melbourne",
    "sg:classifiers":[
        {
            "category":"Health Services",
            "subcategory":"Dentist",
            "type":"Services"
        }
    ],
    "sg:phone":"+61 3 9670 4199",
    "sg:postcode":"3000",
    "sg:province":"VIC",
    "wof:name":"Anaf & Barnes",
    "wof:placetype":"venue"
},
  "geometry": {"coordinates":[144.960494995,-37.8171043396],"type":"Point"}
}