{
  "type": "Feature",
  "properties": {
    "iso:country":"AU",
    "sg:address":"1980 Coolamon Scenic Drv",
    "sg:city":"Mullumbimby",
    "sg:classifiers":[
        {
            "category":"Health Services",
            "subcategory":"Health Practitioner",
            "type":"Services"
        }
    ],
    "sg:phone":"+61 2 6684 4800",
    "sg:postcode":"2482",
    "sg:province":"NSW",
    "sg:tags":[
        "acupuncture"
    ],
    "wof:name":"Androutsopoulos Angeliki",
    "wof:placetype":"venue"
},
  "geometry": {"coordinates":[153.50177001899999,-28.5399398804],"type":"Point"}
}