{
  "type": "Feature",
  "properties": {
    "addr:full":"15 Nepean St Watsonia VIC 3087",
    "addr:housenumber":"15",
    "addr:postcode":"3087",
    "addr:street":"Nepean St",
    "iso:country":"AU",
    "sg:address":"15 Nepean St",
    "sg:city":"Watsonia",
    "sg:classifiers":[
        {
            "category":"Personal",
            "subcategory":"Beauty Salon",
            "type":"Services"
        }
    ],
    "sg:phone":"+61 404 069 192",
    "sg:postcode":"3087",
    "sg:province":"VIC",
    "wof:name":"A Beautiful Secret",
    "wof:placetype":"venue"
},
  "geometry": {"coordinates":[145.087356567,-37.7101478577],"type":"Point"}
}