{
  "type": "Feature",
  "properties": {
    "addr:full":"405 Pacific Hwy Artarmon NSW 2064",
    "addr:housenumber":"405",
    "addr:postcode":"2064",
    "addr:street":"Pacific Hwy",
    "iso:country":"AU",
    "sg:address":"405 Pacific Hwy",
    "sg:city":"Artarmon",
    "sg:classifiers":[
        {
            "category":"Retail",
            "subcategory":"Auto Repair",
            "type":"Services"
        }
    ],
    "sg:phone":"+61 2 9439 4444",
    "sg:postcode":"2064",
    "sg:province":"NSW",
    "sg:tags":[
        "repairer",
        "motor",
        "engineer"
    ],
    "wof:name":"Ford",
    "wof:placetype":"venue"
},
  "geometry": {"coordinates":[151.17701721200001,-33.8137245178],"type":"Point"}
}