{
  "type": "Feature",
  "properties": {
    "addr:full":"Fact 3 / 5- 7 Paul Crt Dandenong VIC 3175",
    "addr:housenumber":"3 / 5 7",
    "addr:postcode":"3175",
    "addr:street":"Fact;Paul Crt",
    "iso:country":"AU",
    "sg:address":"Fact 3 / 5- 7 Paul Crt",
    "sg:city":"Dandenong",
    "sg:phone":"+61 3 9701 3577",
    "sg:postcode":"3175",
    "sg:province":"VIC",
    "wof:name":"Aqueous Logic Purified Drinking Water",
    "wof:placetype":"venue"
},
  "geometry": {"coordinates":[145.202636719,-37.9867477417],"type":"Point"}
}