{
  "type": "Feature",
  "properties": {
    "iso:country":"AU",
    "sg:address":"165 Pinetree Gully Rd",
    "sg:city":"Willetton",
    "sg:classifiers":[
        {
            "category":"Education",
            "subcategory":"Vocational School",
            "type":"Public Place"
        }
    ],
    "sg:phone":"+61 431 278 922",
    "sg:postcode":"6155",
    "sg:province":"WA",
    "sg:tags":[
        "beauty"
    ],
    "wof:name":"International School of Beauty & Health",
    "wof:placetype":"venue"
},
  "geometry": {"coordinates":[115.878128,-32.066669],"type":"Point"}
}