{
  "type": "Feature",
  "properties": {
    "addr:full":"7a Ware St Fairfield NSW 2165",
    "addr:housenumber":"7a",
    "addr:postcode":"2165",
    "addr:street":"Ware St",
    "iso:country":"AU",
    "sg:address":"7a Ware St",
    "sg:city":"Fairfield",
    "sg:classifiers":[
        {
            "category":"Health Services",
            "subcategory":"Doctor",
            "type":"Services"
        }
    ],
    "sg:phone":"+61 2 9726 0840",
    "sg:postcode":"2165",
    "sg:province":"NSW",
    "sg:tags":[
        "medical",
        "practitioner"
    ],
    "wof:name":"Daniel S G & S Pty Ltd",
    "wof:placetype":"venue"
},
  "geometry": {"coordinates":[150.955535889,-33.8725662231],"type":"Point"}
}