{
  "type": "Feature",
  "properties": {
    "iso:country":"AU",
    "sg:address":"Unit 2/ 1 Vincent St",
    "sg:city":"Mackay",
    "sg:classifiers":[
        {
            "category":"Education",
            "subcategory":"Music School",
            "type":"Public Place"
        }
    ],
    "sg:phone":"+61 7 4953 4971",
    "sg:postcode":"4740",
    "sg:province":"QLD",
    "sg:tags":[
        "teacher"
    ],
    "wof:name":"Harvison Margaret F",
    "wof:placetype":"venue"
},
  "geometry": {"coordinates":[149.179565,-21.152349],"type":"Point"}
}