{
  "type": "Feature",
  "properties": {
    "addr:full":"1384 Richmond Rd Richmond TAS 7025",
    "addr:housenumber":"1384",
    "addr:postcode":"7025",
    "addr:street":"Richmond Rd",
    "iso:country":"AU",
    "sg:address":"1384 Richmond Rd",
    "sg:city":"Richmond",
    "sg:classifiers":[
        {
            "category":"Travel",
            "subcategory":"Hotels & Motels",
            "type":"Entertainment"
        }
    ],
    "sg:phone":"+61 13 24 00",
    "sg:postcode":"7025",
    "sg:province":"TAS",
    "sg:tags":[
        "accommodation"
    ],
    "wof:name":"Choice Hotels Australasia",
    "wof:placetype":"venue"
},
  "geometry": {"coordinates":[147.42303466800001,-42.7406005859],"type":"Point"}
}