{
  "type": "Feature",
  "properties": {
    "iso:country":"AU",
    "sg:address":"64 Wadhurst Drv",
    "sg:city":"Boronia West",
    "sg:classifiers":[
        {
            "category":"Autos & Motor Vehicles",
            "subcategory":"Recreational Vehicle Sales",
            "type":"Retail Goods"
        }
    ],
    "sg:phone":"+61 3 9800 0958",
    "sg:postcode":"3155",
    "sg:province":"VIC",
    "sg:tags":[
        "industrial",
        "sewing",
        "contractor"
    ],
    "wof:name":"Allertex",
    "wof:placetype":"venue"
},
  "geometry": {"coordinates":[145.25453185999999,-37.8680953979],"type":"Point"}
}