{
  "type": "Feature",
  "properties": {
    "addr:full":"Suite 11 112 Brooke St (Cnr Anne St) Fortitude Valley QLD 4006",
    "addr:housenumber":"112",
    "addr:postcode":"4006",
    "addr:street":"Brooke St Cnr Anne St",
    "iso:country":"AU",
    "sg:address":"Suite 11 112 Brooke St (Cnr Anne St)",
    "sg:city":"Fortitude Valley",
    "sg:classifiers":[
        {
            "category":"Organizations",
            "subcategory":"Non-profit Organization",
            "type":"Services"
        }
    ],
    "sg:phone":"+61 7 3252 7422",
    "sg:postcode":"4006",
    "sg:province":"QLD",
    "sg:tags":[
        "support",
        "disability",
        "organisation"
    ],
    "wof:name":"National Employment & Psychological Services Centre",
    "wof:placetype":"venue"
},
  "geometry": {"coordinates":[153.038665772,-27.4538650513],"type":"Point"}
}