{
  "type": "Feature",
  "properties": {
    "addr:full":"Shop 2, Daveys Rd Flagstaff Hill SA 5159",
    "addr:housenumber":"shop 2",
    "addr:postcode":"5159",
    "addr:street":"Daveys Rd",
    "iso:country":"AU",
    "sg:address":"Shop 2, Daveys Rd",
    "sg:city":"Flagstaff Hill",
    "sg:classifiers":[
        {
            "category":"Personal",
            "subcategory":"Beauty Salon",
            "type":"Services"
        }
    ],
    "sg:phone":"+61 8 8370 7728",
    "sg:postcode":"5159",
    "sg:province":"SA",
    "wof:name":"Sharee's Nail And Beauty",
    "wof:placetype":"venue"
},
  "geometry": {"coordinates":[138.59788513199999,-35.0563545227],"type":"Point"}
}