{
  "type": "Feature",
  "properties": {
    "iso:country":"AU",
    "sg:address":"Suite 12 Corinna Chambers, 36- 38 Corinna St",
    "sg:city":"Woden",
    "sg:classifiers":[
        {
            "category":"Health Services",
            "subcategory":"Doctor",
            "type":"Services"
        }
    ],
    "sg:phone":"+61 1300 721 111",
    "sg:postcode":"2606",
    "sg:province":"ACT",
    "sg:tags":[
        "nurse",
        "nursing"
    ],
    "wof:name":"Dial An Angel",
    "wof:placetype":"venue"
},
  "geometry": {"coordinates":[149.083740234,-35.3446922302],"type":"Point"}
}