{
  "type": "Feature",
  "properties": {
    "addr:full":"PO Box 5198 Mermaid Waters QLD 4218",
    "addr:postcode":"4218",
    "iso:country":"AU",
    "sg:address":"PO Box 5198",
    "sg:city":"Mermaid Waters",
    "sg:classifiers":[
        {
            "category":"Manufacturing",
            "subcategory":"Tools & Machinery",
            "type":"Manufacturing & Wholesale Goods"
        }
    ],
    "sg:phone":"+61 7 5562 0469",
    "sg:postcode":"4218",
    "sg:province":"QLD",
    "sg:tags":[
        "wholesaler",
        "lingerie",
        "mfrs",
        "sleepwear"
    ],
    "wof:name":"Spangler Bodywear",
    "wof:placetype":"venue"
},
  "geometry": {"coordinates":[153.41163635300001,-28.0360908508],"type":"Point"}
}