{
  "type": "Feature",
  "properties": {
    "iso:country":"AU",
    "sg:address":"1 Booralee St",
    "sg:city":"Botany",
    "sg:classifiers":[
        {
            "category":"Professional",
            "subcategory":"Business Services",
            "type":"Services"
        }
    ],
    "sg:phone":"+61 2 9316 7094",
    "sg:postcode":"2019",
    "sg:province":"NSW",
    "sg:tags":[
        "exporter"
    ],
    "wof:name":"Herculus International",
    "wof:placetype":"venue"
},
  "geometry": {"coordinates":[151.191848755,-33.9465866089],"type":"Point"}
}