{
  "type": "Feature",
  "properties": {
    "addr:full":"41b Wareemba St Five Dock NSW 2046",
    "addr:housenumber":"41b",
    "addr:postcode":"2046",
    "addr:street":"Wareemba St",
    "iso:country":"AU",
    "sg:address":"41b Wareemba St",
    "sg:city":"Five Dock",
    "sg:classifiers":[
        {
            "category":"Building & Trades",
            "subcategory":"Construction",
            "type":"Services"
        }
    ],
    "sg:phone":"+61 2 9712 4850",
    "sg:postcode":"2046",
    "sg:province":"NSW",
    "sg:tags":[
        "contractor"
    ],
    "wof:name":"Bryion Pty Ltd",
    "wof:placetype":"venue"
},
  "geometry": {"coordinates":[151.13493299999999,-33.858315],"type":"Point"}
}