{
  "type": "Feature",
  "properties": {
    "addr:full":"130 James St Northbridge WA 6003",
    "addr:housenumber":"130",
    "addr:postcode":"6003",
    "addr:street":"James St",
    "iso:country":"AU",
    "sg:address":"130 James St",
    "sg:city":"Northbridge",
    "sg:classifiers":[
        {
            "category":"Cafe",
            "type":"Food & Drink"
        }
    ],
    "sg:phone":"+61 8 9228 8858",
    "sg:postcode":"6003",
    "sg:province":"WA",
    "wof:name":"Spaghetti Bar",
    "wof:placetype":"venue"
},
  "geometry": {"coordinates":[115.85740661600001,-31.9482746124],"type":"Point"}
}