{
  "type": "Feature",
  "properties": {
    "iso:country":"AU",
    "sg:address":"5 Penelope Pl",
    "sg:city":"Benowa",
    "sg:classifiers":[
        {
            "category":"Real Estate",
            "subcategory":"Real Estate Services",
            "type":"Services"
        }
    ],
    "sg:phone":"+61 7 5597 2272",
    "sg:postcode":"4217",
    "sg:province":"QLD",
    "sg:tags":[
        "consultant",
        "property"
    ],
    "wof:name":"Tanaka Australia Consulting",
    "wof:placetype":"venue"
},
  "geometry": {"coordinates":[153.38935852,-28.0029506683],"type":"Point"}
}