{
  "type": "Feature",
  "properties": {
    "addr:full":"3- 5 Birmingham Ave Chester Hill NSW 2162",
    "addr:housenumber":"5",
    "addr:postcode":"2162",
    "addr:street":"Birmingham Ave",
    "iso:country":"AU",
    "sg:address":"3- 5 Birmingham Ave",
    "sg:city":"Chester Hill",
    "sg:classifiers":[
        {
            "category":"Home & Garden",
            "subcategory":"Household Appliances",
            "type":"Retail Goods"
        }
    ],
    "sg:phone":"+61 2 9724 8888",
    "sg:postcode":"2162",
    "sg:province":"NSW",
    "sg:tags":[
        "heating",
        "system"
    ],
    "wof:name":"Heritage Woodstoves",
    "wof:placetype":"venue"
},
  "geometry": {"coordinates":[150.986251831,-33.8782653809],"type":"Point"}
}