{
  "type": "Feature",
  "properties": {
    "addr:full":"25 Albert Pl Victor Harbor SA 5211",
    "addr:housenumber":"25",
    "addr:postcode":"5211",
    "addr:street":"Albert Pl",
    "iso:country":"AU",
    "sg:address":"25 Albert Pl",
    "sg:city":"Victor Harbor",
    "sg:classifiers":[
        {
            "category":"Shopping",
            "subcategory":"Crafts & Fabrics",
            "type":"Retail Goods"
        }
    ],
    "sg:phone":"+61 8 8552 5522",
    "sg:postcode":"5211",
    "sg:province":"SA",
    "sg:tags":[
        "supply"
    ],
    "wof:name":"Craft Patch",
    "wof:placetype":"venue"
},
  "geometry": {"coordinates":[138.62260437,-35.5555953979],"type":"Point"}
}