{
  "type": "Feature",
  "properties": {
    "iso:country":"AU",
    "sg:address":"22 Albion St",
    "sg:city":"Warwick",
    "sg:classifiers":[
        {
            "category":"Wholesale",
            "subcategory":"Auto Parts",
            "type":"Manufacturing & Wholesale Goods"
        }
    ],
    "sg:phone":"+61 7 4661 5509",
    "sg:postcode":"4370",
    "sg:province":"QLD",
    "sg:tags":[
        "recyclers"
    ],
    "wof:name":"Benz Auto Dismantlers",
    "wof:placetype":"venue"
},
  "geometry": {"coordinates":[152.03590393100001,-28.2119617462],"type":"Point"}
}