{
  "type": "Feature",
  "properties": {
    "addr:full":"52 Sherringham Rd Cranebrook NSW 2749",
    "addr:housenumber":"52",
    "addr:postcode":"2749",
    "addr:street":"Sherringham Rd",
    "iso:country":"AU",
    "sg:address":"52 Sherringham Rd",
    "sg:city":"Cranebrook",
    "sg:classifiers":[
        {
            "category":"Social Services",
            "subcategory":"Child Care",
            "type":"Services"
        }
    ],
    "sg:phone":"+61 2 4730 3661",
    "sg:postcode":"2749",
    "sg:province":"NSW",
    "wof:name":"A Honey Pot Haven Preschool",
    "wof:placetype":"venue"
},
  "geometry": {"coordinates":[150.71572875999999,-33.7272186279],"type":"Point"}
}