{
  "type": "Feature",
  "properties": {
    "addr:full":"Cnr Queenswharf Rd & King St Melbourne VIC 3000",
    "addr:postcode":"3000",
    "addr:street":"Cnr Queenswharf Rd & King St",
    "iso:country":"AU",
    "sg:address":"Cnr Queenswharf Rd & King St",
    "sg:city":"Melbourne",
    "sg:classifiers":[
        {
            "category":"Retail",
            "subcategory":"Event Space",
            "type":"Services"
        }
    ],
    "sg:phone":"+61 3 9620 0999",
    "sg:postcode":"3000",
    "sg:province":"VIC",
    "sg:tags":[
        "function",
        "organiser"
    ],
    "wof:name":"Function Cove at Melbourne Aquarium",
    "wof:placetype":"venue"
},
  "geometry": {"coordinates":[144.956665039,-37.8183937073],"type":"Point"}
}