{
  "type": "Feature",
  "properties": {
    "addr:full":"47 Lauma Ave Greenacre NSW 2190",
    "addr:housenumber":"47",
    "addr:postcode":"2190",
    "addr:street":"Lauma Ave",
    "iso:country":"AU",
    "sg:address":"47 Lauma Ave",
    "sg:city":"Greenacre",
    "sg:classifiers":[
        {
            "category":"Utilities",
            "subcategory":"Electric",
            "type":"Services"
        }
    ],
    "sg:phone":"+61 2 9011 7047",
    "sg:postcode":"2190",
    "sg:province":"NSW",
    "sg:tags":[
        "electrical",
        "contractor"
    ],
    "wof:name":"Utech",
    "wof:placetype":"venue"
},
  "geometry": {"coordinates":[151.05058299999999,-33.900581],"type":"Point"}
}