{
  "type": "Feature",
  "properties": {
    "iso:country":"AU",
    "sg:address":"160 Clarence St",
    "sg:city":"Sydney",
    "sg:classifiers":[
        {
            "category":"Organizations",
            "subcategory":"Professional Association",
            "type":"Services"
        }
    ],
    "sg:phone":"+61 2 9299 5655",
    "sg:postcode":"2000",
    "sg:province":"NSW",
    "sg:tags":[
        "organisation",
        "business"
    ],
    "wof:name":"POA of NSW",
    "wof:placetype":"venue"
},
  "geometry": {"coordinates":[151.20567321799999,-33.8707695007],"type":"Point"}
}