{
  "type": "Feature",
  "properties": {
    "iso:country":"AU",
    "sg:address":"Unit 1, 4 Kellogg Rd",
    "sg:city":"Glendenning",
    "sg:classifiers":[
        {
            "category":"Wholesale",
            "subcategory":"Toys & Hobbies",
            "type":"Manufacturing & Wholesale Goods"
        }
    ],
    "sg:phone":"+61 2 9832 1399",
    "sg:postcode":"2761",
    "sg:province":"NSW",
    "wof:name":"Ryans Toys Pty Ltd",
    "wof:placetype":"venue"
},
  "geometry": {"coordinates":[150.849289,-33.761425],"type":"Point"}
}