{
  "type": "Feature",
  "properties": {
    "addr:full":"Old Byron Bay Rd Newrybar NSW 2479",
    "addr:postcode":"2479",
    "addr:street":"Old Byron Bay Rd",
    "iso:country":"AU",
    "sg:address":"Old Byron Bay Rd",
    "sg:city":"Newrybar",
    "sg:classifiers":[
        {
            "category":"Government",
            "subcategory":"Department Of Motor Vehicles",
            "type":"Public Place"
        }
    ],
    "sg:phone":"+61 2 6687 1613",
    "sg:postcode":"2479",
    "sg:province":"NSW",
    "sg:tags":[
        "wholesaler",
        "mfrs",
        "accessory"
    ],
    "wof:name":"Summerland Auto Distributors",
    "wof:placetype":"venue"
},
  "geometry": {"coordinates":[153.54592895499999,-28.7347011566],"type":"Point"}
}