{
  "type": "Feature",
  "properties": {
    "addr:full":"6 Links Rd St Marys NSW 2760",
    "addr:housenumber":"6",
    "addr:postcode":"2760",
    "addr:street":"Links Rd",
    "iso:country":"AU",
    "sg:address":"6 Links Rd",
    "sg:city":"St Marys",
    "sg:classifiers":[
        {
            "category":"Retail",
            "subcategory":"Auto Repair",
            "type":"Services"
        }
    ],
    "sg:phone":"+61 2 9833 0833",
    "sg:postcode":"2760",
    "sg:province":"NSW",
    "sg:tags":[
        "bus",
        "truck"
    ],
    "wof:name":"M.N. Trac Mechanical Repairs",
    "wof:placetype":"venue"
},
  "geometry": {"coordinates":[150.77517700199999,-33.7412796021],"type":"Point"}
}