{
  "type": "Feature",
  "properties": {
    "iso:country":"AU",
    "sg:address":"Unit 7, 83- 85 Boundary Rd",
    "sg:city":"Peakhurst",
    "sg:classifiers":[
        {
            "category":"Home & Garden",
            "subcategory":"Building Materials",
            "type":"Retail Goods"
        }
    ],
    "sg:phone":"+61 2 9584 1966",
    "sg:postcode":"2210",
    "sg:province":"NSW",
    "sg:tags":[
        "merchant",
        "glass",
        "glazier"
    ],
    "wof:name":"Neils Glass Service",
    "wof:placetype":"venue"
},
  "geometry": {"coordinates":[151.067993,-33.963825],"type":"Point"}
}