{
  "type": "Feature",
  "properties": {
    "addr:full":"41 Walker St Dandenong VIC 3175",
    "addr:housenumber":"41",
    "addr:postcode":"3175",
    "addr:street":"Walker St",
    "iso:country":"AU",
    "sg:address":"41 Walker St",
    "sg:city":"Dandenong",
    "sg:classifiers":[
        {
            "category":"Professional",
            "subcategory":"Accounting & Tax Preparation",
            "type":"Services"
        }
    ],
    "sg:phone":"+61 3 9793 9182",
    "sg:postcode":"3175",
    "sg:province":"VIC",
    "sg:tags":[
        "accountant",
        "auditor"
    ],
    "wof:name":"Tyabb & Associates Public Accountants",
    "wof:placetype":"venue"
},
  "geometry": {"coordinates":[145.212036133,-37.988117218],"type":"Point"}
}