{
  "type": "Feature",
  "properties": {
    "addr:full":"Reserve St Pomona QLD 4568",
    "addr:postcode":"4568",
    "addr:street":"Reserve St",
    "iso:country":"AU",
    "sg:address":"Reserve St",
    "sg:city":"Pomona",
    "sg:classifiers":[
        {
            "category":"Arena",
            "subcategory":"Sports Club",
            "type":"Entertainment"
        }
    ],
    "sg:phone":"+61 7 5447 7129",
    "sg:postcode":"4568",
    "sg:province":"QLD",
    "sg:tags":[
        "australian",
        "football",
        "rule"
    ],
    "wof:name":"Cooroora Junior Australian Football club",
    "wof:placetype":"venue"
},
  "geometry": {"coordinates":[152.85398864699999,-26.3703575134],"type":"Point"}
}