{
  "type": "Feature",
  "properties": {
    "addr:full":"136 Goondoon St Gladstone QLD 4680",
    "addr:housenumber":"136",
    "addr:postcode":"4680",
    "addr:street":"Goondoon St",
    "iso:country":"AU",
    "sg:address":"136 Goondoon St",
    "sg:city":"Gladstone",
    "sg:classifiers":[
        {
            "category":"Health Services",
            "subcategory":"Optometrist",
            "type":"Services"
        }
    ],
    "sg:phone":"+61 7 4972 1150",
    "sg:postcode":"4680",
    "sg:province":"QLD",
    "wof:name":"Humphries Doug",
    "wof:placetype":"venue"
},
  "geometry": {"coordinates":[151.25672912600001,-23.8444633484],"type":"Point"}
}