{
  "type": "Feature",
  "properties": {
    "addr:full":"36 Walker St Bundaberg QLD 4670",
    "addr:housenumber":"36",
    "addr:postcode":"4670",
    "addr:street":"Walker St",
    "iso:country":"AU",
    "sg:address":"36 Walker St",
    "sg:city":"Bundaberg",
    "sg:classifiers":[
        {
            "category":"Health Services",
            "subcategory":"Health Practitioner",
            "type":"Services"
        }
    ],
    "sg:phone":"+61 7 4153 3404",
    "sg:postcode":"4670",
    "sg:province":"QLD",
    "sg:tags":[
        "hypnotherapy"
    ],
    "wof:name":"Jenny Rasmussen",
    "wof:placetype":"venue"
},
  "geometry": {"coordinates":[152.357666016,-24.8778553009],"type":"Point"}
}