{
  "type": "Feature",
  "properties": {
    "addr:full":"Suite 1, 304 Timor St Warrnambool VIC 3280",
    "addr:housenumber":"304",
    "addr:postcode":"3280",
    "addr:street":"Timor St",
    "iso:country":"AU",
    "sg:address":"Suite 1, 304 Timor St",
    "sg:city":"Warrnambool",
    "sg:classifiers":[
        {
            "category":"Health Services",
            "subcategory":"Chiropractor",
            "type":"Services"
        }
    ],
    "sg:phone":"+61 3 5562 0844",
    "sg:postcode":"3280",
    "sg:province":"VIC",
    "wof:name":"McCann Michael",
    "wof:placetype":"venue"
},
  "geometry": {"coordinates":[142.47425842300001,-38.3816299438],"type":"Point"}
}