{
  "type": "Feature",
  "properties": {
    "iso:country":"AU",
    "sg:address":"Depot on Western Approach Road",
    "sg:city":"Port Lincoln",
    "sg:classifiers":[
        {
            "category":"Home & Garden",
            "subcategory":"Garden Supply",
            "type":"Retail Goods"
        }
    ],
    "sg:phone":"+61 8 8683 3633",
    "sg:postcode":"5606",
    "sg:province":"SA",
    "sg:tags":[
        "equipment"
    ],
    "wof:name":"Mick Treagus Landscape Supplies",
    "wof:placetype":"venue"
},
  "geometry": {"coordinates":[135.849167,-34.742455],"type":"Point"}
}