{
  "type": "Feature",
  "properties": {
    "iso:country":"AU",
    "sg:address":"Newton Drv",
    "sg:city":"Beerwah",
    "sg:classifiers":[
        {
            "category":"Retail",
            "subcategory":"Car Wash",
            "type":"Services"
        }
    ],
    "sg:phone":"+61 412 915 886",
    "sg:postcode":"4519",
    "sg:province":"QLD",
    "sg:tags":[
        "truck",
        "cleaning"
    ],
    "wof:name":"Spotless Mobile Detailing",
    "wof:placetype":"venue"
},
  "geometry": {"coordinates":[152.961166,-26.833736],"type":"Point"}
}