{
  "type": "Feature",
  "properties": {
    "addr:full":"17 Hosies Rd Eden NSW 2551",
    "addr:housenumber":"17",
    "addr:postcode":"2551",
    "addr:street":"Hosies Rd",
    "iso:country":"AU",
    "sg:address":"17 Hosies Rd",
    "sg:city":"Eden",
    "sg:classifiers":[
        {
            "category":"Home & Garden",
            "subcategory":"Building Materials",
            "type":"Retail Goods"
        }
    ],
    "sg:phone":"+61 402 374 786",
    "sg:postcode":"2551",
    "sg:province":"NSW",
    "sg:tags":[
        "lawn",
        "cutting",
        "maintenance"
    ],
    "wof:name":"Sapphire Home & Garden",
    "wof:placetype":"venue"
},
  "geometry": {"coordinates":[149.90911865199999,-37.0632133484],"type":"Point"}
}