{
  "type": "Feature",
  "properties": {
    "addr:full":"121 Canterbury Rd Canterbury NSW 2193",
    "addr:housenumber":"121",
    "addr:postcode":"2193",
    "addr:street":"Canterbury Rd",
    "iso:country":"AU",
    "sg:address":"121 Canterbury Rd",
    "sg:city":"Canterbury",
    "sg:classifiers":[
        {
            "category":"Government",
            "subcategory":"Post Office",
            "type":"Public Place"
        }
    ],
    "sg:phone":"+61 2 9718 1717",
    "sg:postcode":"2193",
    "sg:province":"NSW",
    "sg:tags":[
        "postal"
    ],
    "wof:name":"Canterbury Licensed Post Office",
    "wof:placetype":"venue"
},
  "geometry": {"coordinates":[151.12094099999999,-33.910809],"type":"Point"}
}