{
  "type": "Feature",
  "properties": {
    "iso:country":"AU",
    "sg:address":"Shop 9 210 The Entrance Rd",
    "sg:city":"Erina",
    "sg:classifiers":[
        {
            "category":"Personal",
            "subcategory":"Massage",
            "type":"Services"
        }
    ],
    "sg:phone":"+61 402 406 050",
    "sg:postcode":"2250",
    "sg:province":"NSW",
    "sg:tags":[
        "therapy"
    ],
    "wof:name":"Jenny Waddell Massage Therapy",
    "wof:placetype":"venue"
},
  "geometry": {"coordinates":[151.390823364,-33.4332923889],"type":"Point"}
}