{
  "type": "Feature",
  "properties": {
    "iso:country":"AU",
    "sg:address":"274 Canterbury Rd",
    "sg:city":"Campsie",
    "sg:classifiers":[
        {
            "category":"Professional",
            "subcategory":"Computer Services",
            "type":"Services"
        }
    ],
    "sg:phone":"+61 2 9718 1133",
    "sg:postcode":"2194",
    "sg:province":"NSW",
    "sg:tags":[
        "package",
        "software"
    ],
    "wof:name":"DCD Sell",
    "wof:placetype":"venue"
},
  "geometry": {"coordinates":[151.115723,-33.913734],"type":"Point"}
}