{
  "type": "Feature",
  "properties": {
    "addr:full":"Showroom/Unit 2 7 -11 Central Cct Hillcrest QLD 4118",
    "addr:housenumber":"unit;7 -11",
    "addr:postcode":"4118",
    "addr:street":"Central Cct",
    "iso:country":"AU",
    "sg:address":"Showroom/Unit 2 7",
    "sg:city":"-11 Central Cct Hillcrest",
    "sg:classifiers":[
        {
            "category":"Professional",
            "type":"Services"
        }
    ],
    "sg:phone":"+61 7 3806 8838",
    "sg:postcode":"4118",
    "sg:province":"QLD",
    "sg:tags":[
        "shop",
        "fitting"
    ],
    "wof:name":"A 1 Shopfitters",
    "wof:placetype":"venue"
},
  "geometry": {"coordinates":[153.03643798799999,-27.6604309082],"type":"Point"}
}