{
  "type": "Feature",
  "properties": {
    "addr:full":"34 Attenborough St Dandenong VIC 3175",
    "addr:housenumber":"34",
    "addr:postcode":"3175",
    "addr:street":"Attenborough St",
    "iso:country":"AU",
    "sg:address":"34 Attenborough St",
    "sg:city":"Dandenong",
    "sg:classifiers":[
        {
            "category":"Shopping",
            "subcategory":"Gifts & Souvenirs",
            "type":"Retail Goods"
        }
    ],
    "sg:phone":"+61 3 9793 5020",
    "sg:postcode":"3175",
    "sg:province":"VIC",
    "sg:tags":[
        "wrapping"
    ],
    "wof:name":"Alligator Paper",
    "wof:placetype":"venue"
},
  "geometry": {"coordinates":[145.20016479500001,-37.98595047],"type":"Point"}
}