{
  "type": "Feature",
  "properties": {
    "addr:full":"20 Anderson Rd Hawthorn East VIC 3123",
    "addr:housenumber":"20",
    "addr:postcode":"3123",
    "addr:street":"Anderson Rd",
    "iso:country":"AU",
    "sg:address":"20 Anderson Rd",
    "sg:city":"Hawthorn East",
    "sg:classifiers":[
        {
            "category":"Health Services",
            "subcategory":"Dentist",
            "type":"Services"
        }
    ],
    "sg:phone":"+61 3 9822 2691",
    "sg:postcode":"3123",
    "sg:province":"VIC",
    "wof:name":"Bliss",
    "wof:placetype":"venue"
},
  "geometry": {"coordinates":[145.04844665499999,-37.8410606384],"type":"Point"}
}