{
  "type": "Feature",
  "properties": {
    "addr:full":"30-32 Richmond Rd Homebush NSW 2140",
    "addr:housenumber":"30-32",
    "addr:postcode":"2140",
    "addr:street":"Richmond Rd",
    "iso:country":"AU",
    "sg:address":"30-32 Richmond Rd",
    "sg:city":"Homebush",
    "sg:classifiers":[
        {
            "category":"Professional",
            "subcategory":"Detective & Security Services",
            "type":"Services"
        }
    ],
    "sg:phone":"+61 2 8762 6666",
    "sg:postcode":"2140",
    "sg:province":"NSW",
    "sg:tags":[
        "consultant",
        "system"
    ],
    "wof:name":"Central Signals Pty Ltd",
    "wof:placetype":"venue"
},
  "geometry": {"coordinates":[151.06434631400001,-33.8665657043],"type":"Point"}
}