{
  "type": "Feature",
  "properties": {
    "iso:country":"AU",
    "sg:address":"709- 711 15th St",
    "sg:city":"Mildura",
    "sg:classifiers":[
        {
            "category":"Autos & Motor Vehicles",
            "subcategory":"Automobile Sales",
            "type":"Retail Goods"
        }
    ],
    "sg:phone":"+61 3 5021 5757",
    "sg:postcode":"3500",
    "sg:province":"VIC",
    "sg:tags":[
        "car",
        "new"
    ],
    "wof:name":"Davison Suzuki",
    "wof:placetype":"venue"
},
  "geometry": {"coordinates":[142.12792968799999,-34.2341804504],"type":"Point"}
}