{
  "type": "Feature",
  "properties": {
    "iso:country":"AU",
    "sg:address":"131 Charman Rd",
    "sg:city":"Mentone",
    "sg:classifiers":[
        {
            "category":"Health Services",
            "subcategory":"Doctor",
            "type":"Services"
        }
    ],
    "sg:phone":"+61 3 9584 9472",
    "sg:postcode":"3194",
    "sg:province":"VIC",
    "sg:tags":[
        "medical",
        "practitioner"
    ],
    "wof:name":"Crombie W D",
    "wof:placetype":"venue"
},
  "geometry": {"coordinates":[145.053222656,-37.9779205322],"type":"Point"}
}