{
  "type": "Feature",
  "properties": {
    "addr:full":"Cnr Pacific Hwy & Smart Sts Charlestown NSW 2290",
    "addr:postcode":"2290",
    "addr:street":"Cnr Pacific Hwy &;Sts",
    "iso:country":"AU",
    "sg:address":"Cnr Pacific Hwy & Smart Sts",
    "sg:city":"Charlestown",
    "sg:classifiers":[
        {
            "category":"Shopping",
            "subcategory":"Clothing, Apparel, & Fashions",
            "type":"Retail Goods"
        }
    ],
    "sg:phone":"+61 2 4943 9339",
    "sg:postcode":"2290",
    "sg:province":"NSW",
    "sg:tags":[
        "boutique"
    ],
    "wof:name":"Lynette Fing Boutique",
    "wof:placetype":"venue"
},
  "geometry": {"coordinates":[151.69642639200001,-32.9615097046],"type":"Point"}
}