{
  "type": "Feature",
  "properties": {
    "iso:country":"AU",
    "sg:address":"318 Fussell St",
    "sg:city":"Ballarat",
    "sg:classifiers":[
        {
            "category":"Building & Trades",
            "subcategory":"Plumbing",
            "type":"Services"
        }
    ],
    "sg:phone":"+61 3 5331 5638",
    "sg:postcode":"3350",
    "sg:province":"VIC",
    "sg:tags":[
        "plumber",
        "gasfitters"
    ],
    "wof:name":"Len Robinson Plumbing",
    "wof:placetype":"venue"
},
  "geometry": {"coordinates":[143.892319,-37.572769],"type":"Point"}
}