{
  "type": "Feature",
  "properties": {
    "addr:full":"52 Estuary Drv Blackmans Bay TAS 7052",
    "addr:housenumber":"52",
    "addr:postcode":"7052",
    "addr:street":"Estuary Drv",
    "iso:country":"AU",
    "sg:address":"52 Estuary Drv",
    "sg:city":"Blackmans Bay",
    "sg:classifiers":[
        {
            "category":"Education",
            "subcategory":"Music School",
            "type":"Public Place"
        }
    ],
    "sg:phone":"+61 3 6229 4159",
    "sg:postcode":"7052",
    "sg:province":"TAS",
    "sg:tags":[
        "choir",
        "bands",
        "orchestra"
    ],
    "wof:name":"Hobart Harmony Sweet Adeline Chorus",
    "wof:placetype":"venue"
},
  "geometry": {"coordinates":[147.317261,-43.014942],"type":"Point"}
}