{
  "type": "Feature",
  "properties": {
    "iso:country":"AU",
    "sg:address":"95 North East Rd",
    "sg:city":"Collinswood",
    "sg:classifiers":[
        {
            "category":"Utilities",
            "subcategory":"Water",
            "type":"Services"
        }
    ],
    "sg:phone":"+61 8 8344 8644",
    "sg:postcode":"5081",
    "sg:province":"SA",
    "sg:tags":[
        "equipment",
        "treatment"
    ],
    "wof:name":"Pool Care Pty Ltd",
    "wof:placetype":"venue"
},
  "geometry": {"coordinates":[138.616744995,-34.886882782],"type":"Point"}
}