{
  "type": "Feature",
  "properties": {
    "addr:full":"34 Toolooa St Gladstone QLD 4680",
    "addr:housenumber":"34",
    "addr:postcode":"4680",
    "addr:street":"Toolooa St",
    "iso:country":"AU",
    "sg:address":"34 Toolooa St",
    "sg:city":"Gladstone",
    "sg:classifiers":[
        {
            "category":"Wholesale",
            "subcategory":"Machinery & Supplies",
            "type":"Manufacturing & Wholesale Goods"
        }
    ],
    "sg:phone":"+61 7 4972 3515",
    "sg:postcode":"4680",
    "sg:province":"QLD",
    "sg:tags":[
        "agricultural"
    ],
    "wof:name":"Southbound Agencies",
    "wof:placetype":"venue"
},
  "geometry": {"coordinates":[151.26464843799999,-23.848733902],"type":"Point"}
}