{
  "type": "Feature",
  "properties": {
    "addr:full":"Unit 1/ 9 Symes St Nakara NT 0810",
    "addr:housenumber":"9",
    "addr:postcode":"nt 0810",
    "addr:street":"Symes St",
    "iso:country":"AU",
    "sg:address":"Unit 1/ 9 Symes St",
    "sg:city":"Nakara",
    "sg:classifiers":[
        {
            "category":"Organizations",
            "subcategory":"Professional Association",
            "type":"Services"
        }
    ],
    "sg:phone":"+61 8 8927 7004",
    "sg:postcode":"0810",
    "sg:province":"NT",
    "sg:tags":[
        "organisation",
        "business"
    ],
    "wof:name":"Australian Medical Association",
    "wof:placetype":"venue"
},
  "geometry": {"coordinates":[130.879394531,-12.3744926453],"type":"Point"}
}