{
  "type": "Feature",
  "properties": {
    "addr:full":"Star City 80 Pyrmont St Pyrmont NSW 2009",
    "addr:housenumber":"80",
    "addr:postcode":"2009",
    "addr:street":"Star City;Pyrmont St",
    "iso:country":"AU",
    "sg:address":"Star City 80 Pyrmont St",
    "sg:city":"Pyrmont",
    "sg:classifiers":[
        {
            "category":"Retail",
            "subcategory":"Auto Rental",
            "type":"Services"
        }
    ],
    "sg:phone":"+61 2 9660 7666",
    "sg:postcode":"2009",
    "sg:province":"NSW",
    "sg:tags":[
        "car",
        "hire",
        "minibus"
    ],
    "wof:name":"Avis",
    "wof:placetype":"venue"
},
  "geometry": {"coordinates":[151.19468689000001,-33.8686180115],"type":"Point"}
}