{
  "type": "Feature",
  "properties": {
    "iso:country":"AU",
    "sg:address":"32 Baldwin Drv",
    "sg:city":"Woodroffe",
    "sg:classifiers":[
        {
            "category":"Food & Beverages",
            "subcategory":"Supermarket",
            "type":"Retail Goods"
        }
    ],
    "sg:phone":"+61 8 8932 6388",
    "sg:postcode":"0830",
    "sg:province":"NT",
    "sg:tags":[
        "grocery",
        "store"
    ],
    "wof:name":"Woodroffe Supermarket",
    "wof:placetype":"venue"
},
  "geometry": {"coordinates":[130.978226,-12.500876],"type":"Point"}
}