{
  "type": "Feature",
  "properties": {
    "addr:full":"U22/ 6 Braidwood St Strathfield South NSW 2136",
    "addr:housenumber":"6",
    "addr:postcode":"2136",
    "addr:street":"/;Braidwood St",
    "iso:country":"AU",
    "sg:address":"U22/ 6 Braidwood St",
    "sg:city":"Strathfield South",
    "sg:classifiers":[
        {
            "category":"Professional",
            "subcategory":"Computer Services",
            "type":"Services"
        }
    ],
    "sg:phone":"+61 2 9642 2924",
    "sg:postcode":"2136",
    "sg:province":"NSW",
    "sg:tags":[
        "package",
        "software"
    ],
    "wof:name":"IP Sostcom Australia Pty Ltd",
    "wof:placetype":"venue"
},
  "geometry": {"coordinates":[151.070846558,-33.8868026733],"type":"Point"}
}