{
  "type": "Feature",
  "properties": {
    "addr:full":"528 Mair St Ballarat Central VIC 3350",
    "addr:housenumber":"528",
    "addr:postcode":"3350",
    "addr:street":"Mair St",
    "iso:country":"AU",
    "sg:address":"528 Mair St",
    "sg:city":"Ballarat Central",
    "sg:classifiers":[
        {
            "category":"Professional",
            "subcategory":"Art Services",
            "type":"Services"
        }
    ],
    "sg:phone":"+61 3 5331 4192",
    "sg:postcode":"3350",
    "sg:province":"VIC",
    "sg:tags":[
        "interior",
        "decorator"
    ],
    "wof:name":"Upholstery Gallery The",
    "wof:placetype":"venue"
},
  "geometry": {"coordinates":[143.852417,-37.558945],"type":"Point"}
}