{
  "type": "Feature",
  "properties": {
    "iso:country":"AU",
    "sg:address":"28 Edward Ave",
    "sg:city":"Kings Point",
    "sg:classifiers":[
        {
            "category":"Building & Trades",
            "subcategory":"Landscaping Services",
            "type":"Services"
        }
    ],
    "sg:phone":"+61 2 4455 2378",
    "sg:postcode":"2539",
    "sg:province":"NSW",
    "sg:tags":[
        "designer",
        "landscape",
        "contractor"
    ],
    "wof:name":"Phillip Gilbert Concreting",
    "wof:placetype":"venue"
},
  "geometry": {"coordinates":[150.439163208,-35.3704872131],"type":"Point"}
}