{
  "type": "Feature",
  "properties": {
    "addr:full":"3 Lambourn St Chapel Hill QLD 4069",
    "addr:housenumber":"3",
    "addr:postcode":"4069",
    "addr:street":"Lambourn St",
    "iso:country":"AU",
    "sg:address":"3 Lambourn St",
    "sg:city":"Chapel Hill",
    "sg:classifiers":[
        {
            "category":"Personal",
            "type":"Services"
        }
    ],
    "sg:phone":"+61 7 3378 5537",
    "sg:postcode":"4069",
    "sg:province":"QLD",
    "sg:tags":[
        "reducing",
        "treatment",
        "weight"
    ],
    "wof:name":"Mitchell Paul",
    "wof:placetype":"venue"
},
  "geometry": {"coordinates":[152.94424438499999,-27.488237381],"type":"Point"}
}