{
  "type": "Feature",
  "properties": {
    "addr:full":"80 Main St Pialba QLD 4655",
    "addr:housenumber":"80",
    "addr:postcode":"4655",
    "addr:street":"Main St",
    "iso:country":"AU",
    "sg:address":"80 Main St",
    "sg:city":"Pialba",
    "sg:classifiers":[
        {
            "category":"Professional",
            "subcategory":"Computer Services",
            "type":"Services"
        }
    ],
    "sg:phone":"+61 7 4124 8100",
    "sg:postcode":"4655",
    "sg:province":"QLD",
    "sg:tags":[
        "repairs",
        "upgrade",
        "equipment"
    ],
    "wof:name":"Just Bytes & Gigabytes Computers",
    "wof:placetype":"venue"
},
  "geometry": {"coordinates":[152.83783,-25.289026],"type":"Point"}
}