{
  "type": "Feature",
  "properties": {
    "iso:country":"AU",
    "sg:address":"Macquarie Physiotherapy 1 Skyline Way",
    "sg:city":"Gateshead",
    "sg:classifiers":[
        {
            "category":"Health Services",
            "subcategory":"Health Practitioner",
            "type":"Services"
        }
    ],
    "sg:phone":"+61 2 4942 1322",
    "sg:postcode":"2290",
    "sg:province":"NSW",
    "sg:tags":[
        "physiotherapist"
    ],
    "wof:name":"Lovell Warren",
    "wof:placetype":"venue"
},
  "geometry": {"coordinates":[151.69561767600001,-32.9877281189],"type":"Point"}
}