{
  "type": "Feature",
  "properties": {
    "addr:full":"6 Manton Rd Oakleigh South VIC 3167",
    "addr:housenumber":"6",
    "addr:postcode":"3167",
    "addr:street":"Manton Rd",
    "iso:country":"AU",
    "sg:address":"6 Manton Rd",
    "sg:city":"Oakleigh South",
    "sg:classifiers":[
        {
            "category":"Personal",
            "type":"Services"
        }
    ],
    "sg:phone":"+61 3 8685 8623",
    "sg:postcode":"3167",
    "sg:province":"VIC",
    "sg:tags":[
        "nappy"
    ],
    "wof:name":"Kinderstar",
    "wof:placetype":"venue"
},
  "geometry": {"coordinates":[145.10841369600001,-37.9142303467],"type":"Point"}
}