{
  "type": "Feature",
  "properties": {
    "iso:country":"AU",
    "sg:address":"Lot 8, Port Wakefield Rd",
    "sg:city":"Burton",
    "sg:classifiers":[
        {
            "category":"Wholesale",
            "subcategory":"Machinery & Supplies",
            "type":"Manufacturing & Wholesale Goods"
        }
    ],
    "sg:phone":"+61 8 8280 5200",
    "sg:postcode":"5110",
    "sg:province":"SA",
    "sg:tags":[
        "equipment",
        "hydraulic"
    ],
    "wof:name":"Truck Hydraulics SA",
    "wof:placetype":"venue"
},
  "geometry": {"coordinates":[138.585113525,-34.7380943298],"type":"Point"}
}