{
  "type": "Feature",
  "properties": {
    "iso:country":"AU",
    "sg:address":"Shop 5",
    "sg:city":"Civic Cntr Port Lincoln",
    "sg:classifiers":[
        {
            "category":"Health Services",
            "subcategory":"Health Practitioner",
            "type":"Services"
        }
    ],
    "sg:phone":"+61 8 8683 4344",
    "sg:postcode":"5607",
    "sg:province":"SA",
    "sg:tags":[
        "alternative"
    ],
    "wof:name":"Bridget North",
    "wof:placetype":"venue"
},
  "geometry": {"coordinates":[135.678284,-34.524181],"type":"Point"}
}