{
  "type": "Feature",
  "properties": {
    "addr:full":"121 Camelia Ave Everton Hills QLD 4053",
    "addr:housenumber":"121",
    "addr:postcode":"4053",
    "addr:street":"Camelia Ave",
    "iso:country":"AU",
    "sg:address":"121 Camelia Ave",
    "sg:city":"Everton Hills",
    "sg:classifiers":[
        {
            "category":"Health Services",
            "subcategory":"Health Practitioner",
            "type":"Services"
        }
    ],
    "sg:phone":"+61 1300 366 377",
    "sg:postcode":"4053",
    "sg:province":"QLD",
    "sg:tags":[
        "dietitian"
    ],
    "sg:website":"http://www.trimaweigh.com",
    "wof:name":"Trim-A-Weigh Pty Ltd",
    "wof:placetype":"venue"
},
  "geometry": {"coordinates":[152.96990966800001,-27.3941173553],"type":"Point"}
}