{
  "type": "Feature",
  "properties": {
    "addr:full":"1 Southgate Ave Southbank VIC 3006",
    "addr:housenumber":"1",
    "addr:postcode":"3006",
    "addr:street":"Southgate Ave",
    "iso:country":"AU",
    "sg:address":"1 Southgate Ave",
    "sg:city":"Southbank",
    "sg:classifiers":[
        {
            "category":"Personal",
            "subcategory":"Day Spa",
            "type":"Services"
        }
    ],
    "sg:phone":"+61 3 8696 8111",
    "sg:postcode":"3006",
    "sg:province":"VIC",
    "wof:name":"Chuan Spa",
    "wof:placetype":"venue"
},
  "geometry": {"coordinates":[144.96563720699999,-37.8204498291],"type":"Point"}
}