{
  "type": "Feature",
  "properties": {
    "addr:full":"12 Wingello St Wingello NSW 2579",
    "addr:housenumber":"12",
    "addr:postcode":"2579",
    "addr:street":"Wingello St",
    "iso:country":"AU",
    "sg:address":"12 Wingello St",
    "sg:city":"Wingello",
    "sg:classifiers":[
        {
            "category":"Shopping",
            "subcategory":"Musical Instruments",
            "type":"Retail Goods"
        }
    ],
    "sg:phone":"+61 2 4884 4225",
    "sg:postcode":"2579",
    "sg:province":"NSW",
    "sg:tags":[
        "musician",
        "agent"
    ],
    "wof:name":"Scottish & Irish Piper Hire",
    "wof:placetype":"venue"
},
  "geometry": {"coordinates":[150.158126831,-34.6909942627],"type":"Point"}
}