{
  "type": "Feature",
  "properties": {
    "iso:country":"AU",
    "sg:address":"17-21 Riversdale Rd",
    "sg:city":"Newtown",
    "sg:classifiers":[
        {
            "category":"Building & Trades",
            "subcategory":"Construction",
            "type":"Services"
        }
    ],
    "sg:phone":"+61 3 5222 7080",
    "sg:postcode":"3220",
    "sg:province":"VIC",
    "sg:tags":[
        "earth",
        "excavating",
        "moving",
        "contractor"
    ],
    "wof:name":"Civil Force",
    "wof:placetype":"venue"
},
  "geometry": {"coordinates":[144.33944700000001,-38.16153],"type":"Point"}
}