{
  "type": "Feature",
  "properties": {
    "addr:full":"6 Fiddick Pl Menai NSW 2234",
    "addr:housenumber":"6",
    "addr:postcode":"2234",
    "addr:street":"Fiddick Pl",
    "iso:country":"AU",
    "sg:address":"6 Fiddick Pl",
    "sg:city":"Menai",
    "sg:classifiers":[
        {
            "category":"Retail",
            "subcategory":"Driving School",
            "type":"Services"
        }
    ],
    "sg:phone":"+61 400 432 829",
    "sg:postcode":"2234",
    "sg:province":"NSW",
    "wof:name":"Roadwise Driver Education Pty Ltd",
    "wof:placetype":"venue"
},
  "geometry": {"coordinates":[151.01054382300001,-34.0198860168],"type":"Point"}
}