{
  "type": "Feature",
  "properties": {
    "addr:full":"73 Newton La Broken Hill NSW 2880",
    "addr:housenumber":"73",
    "addr:postcode":"2880",
    "addr:street":"Newton La",
    "iso:country":"AU",
    "sg:address":"73 Newton La",
    "sg:city":"Broken Hill",
    "sg:classifiers":[
        {
            "category":"Wholesale",
            "subcategory":"Wine & Distilled Alcoholic Beverages",
            "type":"Manufacturing & Wholesale Goods"
        }
    ],
    "sg:phone":"+61 8 8088 3905",
    "sg:postcode":"2880",
    "sg:province":"NSW",
    "sg:tags":[
        "collector",
        "bottle"
    ],
    "wof:name":"Channing's Bottle Yard",
    "wof:placetype":"venue"
},
  "geometry": {"coordinates":[141.43417358400001,-31.9664936066],"type":"Point"}
}