{
  "type": "Feature",
  "properties": {
    "addr:full":"Ingle Farm Shopping Centre Shop 19 Ingle Farm SA 5098",
    "addr:housenumber":"shop 19",
    "addr:postcode":"5098",
    "iso:country":"AU",
    "sg:address":"Ingle Farm Shopping Centre Shop 19",
    "sg:city":"Ingle Farm",
    "sg:classifiers":[
        {
            "category":"Shopping",
            "subcategory":"Clothing, Apparel, & Fashions",
            "type":"Retail Goods"
        }
    ],
    "sg:phone":"+61 8 8263 3729",
    "sg:postcode":"5098",
    "sg:province":"SA",
    "sg:tags":[
        "lady",
        "wear"
    ],
    "wof:name":"Millers Fashion Club",
    "wof:placetype":"venue"
},
  "geometry": {"coordinates":[138.64105224599999,-34.8321266174],"type":"Point"}
}