{
  "type": "Feature",
  "properties": {
    "iso:country":"AU",
    "sg:address":"Unit 12, 12 Tindale St",
    "sg:city":"Mandurah",
    "sg:classifiers":[
        {
            "category":"Building & Trades",
            "subcategory":"Construction",
            "type":"Services"
        }
    ],
    "sg:phone":"+61 8 9535 5913",
    "sg:postcode":"6210",
    "sg:province":"WA",
    "sg:tags":[
        "window",
        "tinting"
    ],
    "wof:name":"Bestway Window Tinting",
    "wof:placetype":"venue"
},
  "geometry": {"coordinates":[115.739952,-32.518688],"type":"Point"}
}