{
  "type": "Feature",
  "properties": {
    "addr:full":"847 Booie Rd Nanango QLD 4615",
    "addr:housenumber":"847",
    "addr:postcode":"4615",
    "addr:street":"Booie Rd",
    "iso:country":"AU",
    "sg:address":"847 Booie Rd",
    "sg:city":"Nanango",
    "sg:classifiers":[
        {
            "category":"Wholesale",
            "subcategory":"Chemicals & Plastics",
            "type":"Manufacturing & Wholesale Goods"
        }
    ],
    "sg:phone":"+61 409 633 989",
    "sg:postcode":"4615",
    "sg:province":"QLD",
    "sg:tags":[
        "repair"
    ],
    "wof:name":"Sam Macri's Plastic Welding",
    "wof:placetype":"venue"
},
  "geometry": {"coordinates":[151.99717712399999,-26.6251296997],"type":"Point"}
}