{
  "type": "Feature",
  "properties": {
    "addr:full":"116 George St Thebarton SA 5031",
    "addr:housenumber":"116",
    "addr:postcode":"5031",
    "addr:street":"George St",
    "iso:country":"AU",
    "sg:address":"116 George St",
    "sg:city":"Thebarton",
    "sg:classifiers":[
        {
            "category":"Professional",
            "subcategory":"Management & Consulting",
            "type":"Services"
        }
    ],
    "sg:phone":"+61 8 8301 6600",
    "sg:postcode":"5031",
    "sg:province":"SA",
    "sg:tags":[
        "consultant",
        "educational"
    ],
    "wof:name":"Catholic Education Office",
    "wof:placetype":"venue"
},
  "geometry": {"coordinates":[138.56967163100001,-34.9198760986],"type":"Point"}
}