{
  "type": "Feature",
  "properties": {
    "iso:country":"AU",
    "sg:address":"271 Forestdale Drv",
    "sg:city":"Forestdale",
    "sg:classifiers":[
        {
            "category":"Building & Trades",
            "subcategory":"Cleaning & Sanitation",
            "type":"Services"
        }
    ],
    "sg:phone":"+61 7 3800 1115",
    "sg:postcode":"4118",
    "sg:province":"QLD",
    "sg:tags":[
        "chemical",
        "pressure",
        "steam",
        "contractor"
    ],
    "wof:name":"Jetwater Pressure Cleaning",
    "wof:placetype":"venue"
},
  "geometry": {"coordinates":[152.99723815900001,-27.6651306152],"type":"Point"}
}