{
  "type": "Feature",
  "properties": {
    "iso:country":"AU",
    "sg:address":"Shp 5/ 154 Prospect Rd",
    "sg:city":"Prospect",
    "sg:classifiers":[
        {
            "category":"Shopping",
            "subcategory":"Music",
            "type":"Retail Goods"
        }
    ],
    "sg:phone":"+61 8 8344 2906",
    "sg:postcode":"5082",
    "sg:province":"SA",
    "sg:tags":[
        "store"
    ],
    "wof:name":"Enjoyable Music",
    "wof:placetype":"venue"
},
  "geometry": {"coordinates":[138.59368896500001,-34.8843383789],"type":"Point"}
}