{
  "type": "Feature",
  "properties": {
    "iso:country":"AU",
    "sg:address":"25 Blackall St",
    "sg:city":"Woombye",
    "sg:classifiers":[
        {
            "category":"Health Services",
            "subcategory":"Chiropractor",
            "type":"Services"
        }
    ],
    "sg:phone":"+61 7 5442 2144",
    "sg:postcode":"4559",
    "sg:province":"QLD",
    "wof:name":"Lambert A L",
    "wof:placetype":"venue"
},
  "geometry": {"coordinates":[152.965499878,-26.6603603363],"type":"Point"}
}