{
  "type": "Feature",
  "properties": {
    "iso:country":"AU",
    "sg:address":"8a Larch St",
    "sg:city":"Caulfield South",
    "sg:classifiers":[
        {
            "category":"Professional",
            "subcategory":"Secretarial Services",
            "type":"Services"
        }
    ],
    "sg:phone":"+61 402 453 660",
    "sg:postcode":"3162",
    "sg:province":"VIC",
    "sg:tags":[
        "typing"
    ],
    "wof:name":"Wordskill",
    "wof:placetype":"venue"
},
  "geometry": {"coordinates":[145.02348327600001,-37.8879737854],"type":"Point"}
}