{
  "type": "Feature",
  "properties": {
    "iso:country":"AU",
    "sg:address":"Lot 28 Harbour Drv",
    "sg:city":"Turkey Beach",
    "sg:classifiers":[
        {
            "category":"Building & Trades",
            "subcategory":"Construction",
            "type":"Services"
        }
    ],
    "sg:phone":"+61 7 4974 2298",
    "sg:postcode":"4678",
    "sg:province":"QLD",
    "sg:tags":[
        "earth",
        "excavating",
        "moving",
        "contractor"
    ],
    "wof:name":"Turkey Beach Backhoe and Plant Hire",
    "wof:placetype":"venue"
},
  "geometry": {"coordinates":[151.615082,-24.072922],"type":"Point"}
}