{
  "type": "Feature",
  "properties": {
    "addr:full":"222 Thompson Ave Cowes VIC 3922",
    "addr:housenumber":"222",
    "addr:postcode":"3922",
    "addr:street":"Thompson Ave",
    "iso:country":"AU",
    "sg:address":"222 Thompson Ave",
    "sg:city":"Cowes",
    "sg:classifiers":[
        {
            "category":"Health Services",
            "subcategory":"Health Practitioner",
            "type":"Services"
        }
    ],
    "sg:phone":"+61 408 170 558",
    "sg:postcode":"3922",
    "sg:province":"VIC",
    "sg:tags":[
        "naturopath"
    ],
    "wof:name":"Miriam Strickland",
    "wof:placetype":"venue"
},
  "geometry": {"coordinates":[145.238815308,-38.4619903564],"type":"Point"}
}