{
  "type": "Feature",
  "properties": {
    "addr:full":"5A Mayo Crt Lennox Head NSW 2478",
    "addr:housenumber":"5a",
    "addr:postcode":"2478",
    "addr:street":"Mayo Crt",
    "iso:country":"AU",
    "sg:address":"5A Mayo Crt",
    "sg:city":"Lennox Head",
    "sg:classifiers":[
        {
            "category":"Real Estate",
            "subcategory":"Architect",
            "type":"Services"
        }
    ],
    "sg:phone":"+61 2 6687 6930",
    "sg:postcode":"2478",
    "sg:province":"NSW",
    "sg:tags":[
        "building",
        "designer"
    ],
    "wof:name":"Paul R.Gray",
    "wof:placetype":"venue"
},
  "geometry": {"coordinates":[153.603759766,-28.8291511536],"type":"Point"}
}