{
  "type": "Feature",
  "properties": {
    "addr:full":"15 Langmore La Berwick VIC 3806",
    "addr:housenumber":"15",
    "addr:postcode":"3806",
    "addr:street":"Langmore La",
    "iso:country":"AU",
    "sg:address":"15 Langmore La",
    "sg:city":"Berwick",
    "sg:classifiers":[
        {
            "category":"Health Services",
            "subcategory":"Doctor",
            "type":"Services"
        }
    ],
    "sg:phone":"+61 3 9769 5588",
    "sg:postcode":"3806",
    "sg:province":"VIC",
    "sg:tags":[
        "medical",
        "practitioner"
    ],
    "wof:name":"MIA Victoria",
    "wof:placetype":"venue"
},
  "geometry": {"coordinates":[145.34617614699999,-38.03307724],"type":"Point"}
}