{
  "type": "Feature",
  "properties": {
    "iso:country":"AU",
    "sg:address":"1/ 106 Robinson Ave",
    "sg:city":"Belmont",
    "sg:classifiers":[
        {
            "category":"Building & Trades",
            "subcategory":"Pest Control",
            "type":"Services"
        }
    ],
    "sg:phone":"+61 8 9477 6155",
    "sg:postcode":"6104",
    "sg:province":"WA",
    "wof:name":"Termite Systems Management Pty Ltd",
    "wof:placetype":"venue"
},
  "geometry": {"coordinates":[115.929527283,-31.9596862793],"type":"Point"}
}