{
  "type": "Feature",
  "properties": {
    "addr:full":"55 Albert St Creswick VIC 3363",
    "addr:housenumber":"55",
    "addr:postcode":"3363",
    "addr:street":"Albert St",
    "iso:country":"AU",
    "sg:address":"55 Albert St",
    "sg:city":"Creswick",
    "sg:classifiers":[
        {
            "category":"Professional",
            "subcategory":"Business Services",
            "type":"Services"
        }
    ],
    "sg:phone":"+61 3 5345 1055",
    "sg:postcode":"3363",
    "sg:province":"VIC",
    "sg:tags":[
        "management",
        "event"
    ],
    "wof:name":"Knowers Ark Services",
    "wof:placetype":"venue"
},
  "geometry": {"coordinates":[143.894821167,-37.4230499268],"type":"Point"}
}