{
  "type": "Feature",
  "properties": {
    "iso:country":"AU",
    "sg:address":"Shop 5 Camden Arcade, 166 Argyle St",
    "sg:city":"Camden",
    "sg:classifiers":[
        {
            "category":"Travel",
            "subcategory":"Travel Agent",
            "type":"Entertainment"
        }
    ],
    "sg:phone":"+61 2 4655 7077",
    "sg:postcode":"2570",
    "sg:province":"NSW",
    "sg:tags":[
        "consultant"
    ],
    "wof:name":"Travelscene Camden",
    "wof:placetype":"venue"
},
  "geometry": {"coordinates":[150.726638794,-34.0427284241],"type":"Point"}
}