{
  "type": "Feature",
  "properties": {
    "addr:full":"7 Rainer Rd South Morang VIC 3752",
    "addr:housenumber":"7",
    "addr:postcode":"3752",
    "addr:street":"Rainer Rd",
    "iso:country":"AU",
    "sg:address":"7 Rainer Rd",
    "sg:city":"South Morang",
    "sg:classifiers":[
        {
            "category":"Manufacturing",
            "subcategory":"Tobacco Products",
            "type":"Manufacturing & Wholesale Goods"
        }
    ],
    "sg:phone":"+61 3 9401 3037",
    "sg:postcode":"3752",
    "sg:province":"VIC",
    "sg:tags":[
        "car",
        "truck",
        "cleaning",
        "equipment"
    ],
    "wof:name":"Clean City Services",
    "wof:placetype":"venue"
},
  "geometry": {"coordinates":[145.07101399999999,-37.635506],"type":"Point"}
}