{
  "type": "Feature",
  "properties": {
    "addr:full":"401 Preston Boundary Rd Toowoomba QLD 4350",
    "addr:housenumber":"401",
    "addr:postcode":"4350",
    "addr:street":"Preston Boundary Rd",
    "iso:country":"AU",
    "sg:address":"401 Preston Boundary Rd",
    "sg:city":"Toowoomba",
    "sg:classifiers":[
        {
            "category":"Retail",
            "subcategory":"Event Space",
            "type":"Services"
        }
    ],
    "sg:phone":"+61 7 4630 9329",
    "sg:postcode":"4350",
    "sg:province":"QLD",
    "sg:tags":[
        "venue",
        "reception",
        "wedding"
    ],
    "wof:name":"Preston Village Chapel",
    "wof:placetype":"venue"
},
  "geometry": {"coordinates":[151.941666,-27.632244],"type":"Point"}
}