{
  "type": "Feature",
  "properties": {
    "addr:full":"117 Enterprise Ave Tweed Heads South QLD 2486",
    "addr:housenumber":"117",
    "addr:postcode":"2486",
    "addr:street":"Enterprise Ave",
    "iso:country":"AU",
    "sg:address":"117 Enterprise Ave",
    "sg:city":"Tweed Heads South",
    "sg:classifiers":[
        {
            "category":"Home & Garden",
            "subcategory":"Garden Supply",
            "type":"Retail Goods"
        }
    ],
    "sg:phone":"+61 7 5524 4988",
    "sg:postcode":"2486",
    "sg:province":"QLD",
    "sg:tags":[
        "equipment"
    ],
    "wof:name":"Tweed Landscape Supplies",
    "wof:placetype":"venue"
},
  "geometry": {"coordinates":[153.53440856899999,-28.2040843964],"type":"Point"}
}