{
  "type": "Feature",
  "properties": {
    "addr:full":"23 Fisher St Clifton QLD 4361",
    "addr:housenumber":"23",
    "addr:postcode":"4361",
    "addr:street":"Fisher St",
    "iso:country":"AU",
    "sg:address":"23 Fisher St",
    "sg:city":"Clifton",
    "sg:classifiers":[
        {
            "category":"Cafe",
            "type":"Food & Drink"
        }
    ],
    "sg:phone":"+61 7 4697 3610",
    "sg:postcode":"4361",
    "sg:province":"QLD",
    "wof:name":"Clifton Heritage Cafe & Restaurant",
    "wof:placetype":"venue"
},
  "geometry": {"coordinates":[151.90748596200001,-27.9322566986],"type":"Point"}
}