{
  "type": "Feature",
  "properties": {
    "addr:full":"24 Milnes Rd Strathalbyn SA 5255",
    "addr:housenumber":"24",
    "addr:postcode":"5255",
    "addr:street":"Milnes Rd",
    "iso:country":"AU",
    "sg:address":"24 Milnes Rd",
    "sg:city":"Strathalbyn",
    "sg:classifiers":[
        {
            "category":"Professional",
            "type":"Services"
        }
    ],
    "sg:phone":"+61 413 437 388",
    "sg:postcode":"5255",
    "sg:province":"SA",
    "sg:tags":[
        "transport"
    ],
    "wof:name":"Alloomba",
    "wof:placetype":"venue"
},
  "geometry": {"coordinates":[138.89097595199999,-35.2626838684],"type":"Point"}
}