{
  "type": "Feature",
  "properties": {
    "iso:country":"AU",
    "sg:address":"Shop 27A Jindalee Homemaker Centre 34 Goggs Rd",
    "sg:city":"Jindalee",
    "sg:classifiers":[
        {
            "category":"Building & Trades",
            "subcategory":"Equipment Rental",
            "type":"Services"
        }
    ],
    "sg:phone":"+61 7 3715 7778",
    "sg:postcode":"4074",
    "sg:province":"QLD",
    "sg:tags":[
        "fitness"
    ],
    "wof:name":"Workout World",
    "wof:placetype":"venue"
},
  "geometry": {"coordinates":[152.948974609,-27.5351352692],"type":"Point"}
}