{
  "type": "Feature",
  "properties": {
    "addr:full":"5 Cross Pl Kallangur QLD 4503",
    "addr:housenumber":"5",
    "addr:postcode":"4503",
    "addr:street":"Cross Pl",
    "iso:country":"AU",
    "sg:address":"5 Cross Pl",
    "sg:city":"Kallangur",
    "sg:classifiers":[
        {
            "category":"Building & Trades",
            "subcategory":"Construction",
            "type":"Services"
        }
    ],
    "sg:phone":"+61 419 741 082",
    "sg:postcode":"4503",
    "sg:province":"QLD",
    "sg:tags":[
        "earth",
        "excavating",
        "moving",
        "contractor"
    ],
    "wof:name":"G & K Bobcat Hire",
    "wof:placetype":"venue"
},
  "geometry": {"coordinates":[153.00328064000001,-27.2514305115],"type":"Point"}
}