{
  "type": "Feature",
  "properties": {
    "addr:full":"Level 4/ 67 St Pauls Tce Spring Hill QLD 4000",
    "addr:housenumber":"/ 67",
    "addr:postcode":"4000",
    "addr:street":"St Pauls Tce",
    "iso:country":"AU",
    "sg:address":"Level 4/ 67 St",
    "sg:city":"Pauls Tce Spring Hill",
    "sg:classifiers":[
        {
            "category":"Health Services",
            "subcategory":"Doctor",
            "type":"Services"
        }
    ],
    "sg:phone":"+61 7 3834 9000",
    "sg:postcode":"4000",
    "sg:province":"QLD",
    "sg:tags":[
        "nurse",
        "nursing"
    ],
    "wof:name":"BDS Health & Aged Care",
    "wof:placetype":"venue"
},
  "geometry": {"coordinates":[153.027832031,-27.4600601196],"type":"Point"}
}