{
  "type": "Feature",
  "properties": {
    "addr:full":"58a Riley Rd Leppington NSW 2179",
    "addr:housenumber":"58a",
    "addr:postcode":"2179",
    "addr:street":"Riley Rd",
    "iso:country":"AU",
    "sg:address":"58a Riley Rd",
    "sg:city":"Leppington",
    "sg:classifiers":[
        {
            "category":"Professional",
            "subcategory":"Employment Agencies",
            "type":"Services"
        }
    ],
    "sg:phone":"+61 2 9606 2467",
    "sg:postcode":"2179",
    "sg:province":"NSW",
    "sg:tags":[
        "hire",
        "labour",
        "contractor"
    ],
    "wof:name":"DMP Container Labour",
    "wof:placetype":"venue"
},
  "geometry": {"coordinates":[150.791625977,-33.977481842],"type":"Point"}
}