{
  "type": "Feature",
  "properties": {
    "addr:full":"222 Urana St Wagga Wagga NSW 2650",
    "addr:housenumber":"222",
    "addr:postcode":"2650",
    "addr:street":"Urana St",
    "iso:country":"AU",
    "sg:address":"222 Urana St",
    "sg:city":"Wagga Wagga",
    "sg:classifiers":[
        {
            "category":"Retail",
            "subcategory":"Auto Repair",
            "type":"Services"
        }
    ],
    "sg:phone":"+61 2 6925 2094",
    "sg:postcode":"2650",
    "sg:province":"NSW",
    "sg:tags":[
        "bus",
        "truck"
    ],
    "wof:name":"Sutherland Doug Truck Repairs",
    "wof:placetype":"venue"
},
  "geometry": {"coordinates":[147.34135437,-35.1248817444],"type":"Point"}
}