{
  "type": "Feature",
  "properties": {
    "iso:country":"AU",
    "sg:address":"4 Fairway Drv",
    "sg:city":"Safety Beach",
    "sg:classifiers":[
        {
            "category":"Home & Garden",
            "subcategory":"Kitchen Supply",
            "type":"Retail Goods"
        }
    ],
    "sg:phone":"+61 419 591 943",
    "sg:postcode":"3936",
    "sg:province":"VIC",
    "sg:tags":[
        "sharpening"
    ],
    "wof:name":"The Knife Master",
    "wof:placetype":"venue"
},
  "geometry": {"coordinates":[144.99278259299999,-38.3252754211],"type":"Point"}
}