{
  "type": "Feature",
  "properties": {
    "iso:country":"AU",
    "sg:address":"Odea Rd",
    "sg:city":"Kenton Valley",
    "sg:classifiers":[
        {
            "category":"Professional",
            "subcategory":"Engineering",
            "type":"Services"
        }
    ],
    "sg:phone":"+61 407 608 520",
    "sg:postcode":"5233",
    "sg:province":"SA",
    "sg:tags":[
        "engineer"
    ],
    "wof:name":"Akron Engineering",
    "wof:placetype":"venue"
},
  "geometry": {"coordinates":[138.880249023,-34.8527984619],"type":"Point"}
}