{
  "type": "Feature",
  "properties": {
    "addr:full":"27 Springwood Rd Agnes Banks NSW 2753",
    "addr:housenumber":"27",
    "addr:postcode":"2753",
    "addr:street":"Springwood Rd",
    "iso:country":"AU",
    "sg:address":"27 Springwood Rd",
    "sg:city":"Agnes Banks",
    "sg:classifiers":[
        {
            "category":"Shopping",
            "type":"Retail Goods"
        }
    ],
    "sg:phone":"+61 2 4588 5172",
    "sg:postcode":"2753",
    "sg:province":"NSW",
    "sg:tags":[
        "produce",
        "grain"
    ],
    "wof:name":"Agnes Banks Produce",
    "wof:placetype":"venue"
},
  "geometry": {"coordinates":[150.71075439399999,-33.6143035889],"type":"Point"}
}