{
  "type": "Feature",
  "properties": {
    "iso:country":"AU",
    "sg:address":"24 Shannon Pde",
    "sg:city":"Berkeley Vale",
    "sg:classifiers":[
        {
            "category":"Professional",
            "subcategory":"Business Services",
            "type":"Services"
        }
    ],
    "sg:phone":"+61 2 4388 2545",
    "sg:postcode":"2261",
    "sg:province":"NSW",
    "sg:tags":[
        "drafting"
    ],
    "wof:name":"Drafting Point",
    "wof:placetype":"venue"
},
  "geometry": {"coordinates":[151.437607,-33.34761],"type":"Point"}
}