{
  "type": "Feature",
  "properties": {
    "addr:full":"148 Sturt Hwy Buronga VIC 2739",
    "addr:housenumber":"148",
    "addr:postcode":"2739",
    "addr:street":"Sturt Hwy",
    "iso:country":"AU",
    "sg:address":"148 Sturt Hwy",
    "sg:city":"Buronga",
    "sg:classifiers":[
        {
            "category":"Retail",
            "subcategory":"Veterinary Services",
            "type":"Services"
        }
    ],
    "sg:phone":"+61 3 5022 0099",
    "sg:postcode":"2739",
    "sg:province":"VIC",
    "sg:tags":[
        "surgeon"
    ],
    "wof:name":"Riverbend Veterinary Service",
    "wof:placetype":"venue"
},
  "geometry": {"coordinates":[142.194489,-34.174454],"type":"Point"}
}