{
  "type": "Feature",
  "properties": {
    "addr:full":"1830 Sandgate Rd Virginia QLD 4014",
    "addr:housenumber":"1830",
    "addr:postcode":"4014",
    "addr:street":"Sandgate Rd",
    "iso:country":"AU",
    "sg:address":"1830 Sandgate Rd",
    "sg:city":"Virginia",
    "sg:classifiers":[
        {
            "category":"Retail",
            "subcategory":"Auto Repair",
            "type":"Services"
        }
    ],
    "sg:phone":"+61 7 3265 3638",
    "sg:postcode":"4014",
    "sg:province":"QLD",
    "sg:tags":[
        "testing",
        "inspection",
        "motor",
        "vehicle"
    ],
    "wof:name":"BP Virginia Automotive",
    "wof:placetype":"venue"
},
  "geometry": {"coordinates":[153.06228637699999,-27.3738307953],"type":"Point"}
}