{
  "type": "Feature",
  "properties": {
    "addr:full":"Lvl 5, 172 Georges Tce Perth WA 6000",
    "addr:housenumber":"172",
    "addr:postcode":"6000",
    "addr:street":"Georges Tce",
    "iso:country":"AU",
    "sg:address":"Lvl 5, 172 Georges Tce",
    "sg:city":"Perth",
    "sg:classifiers":[
        {
            "category":"Health Services",
            "subcategory":"Doctor",
            "type":"Services"
        }
    ],
    "sg:phone":"+61 1300 883 273",
    "sg:postcode":"6000",
    "sg:province":"WA",
    "sg:tags":[
        "nurse",
        "nursing"
    ],
    "sg:website":"http://www.cpegroup.biz",
    "wof:name":"CPE Group",
    "wof:placetype":"venue"
},
  "geometry": {"coordinates":[115.852546692,-31.9546794891],"type":"Point"}
}