{
  "type": "Feature",
  "properties": {
    "iso:country":"AU",
    "sg:address":"101 Wilson Rd",
    "sg:city":"Hinchinbrook",
    "sg:classifiers":[
        {
            "category":"Building & Trades",
            "subcategory":"Plumbing",
            "type":"Services"
        }
    ],
    "sg:phone":"+61 417 281 434",
    "sg:postcode":"2168",
    "sg:province":"NSW",
    "sg:tags":[
        "plumber",
        "gasfitters"
    ],
    "wof:name":"Kennedy C & M",
    "wof:placetype":"venue"
},
  "geometry": {"coordinates":[150.864303589,-33.9150276184],"type":"Point"}
}