{
  "type": "Feature",
  "properties": {
    "addr:full":"10 Elizabeth St Burwood NSW 2134",
    "addr:housenumber":"10",
    "addr:postcode":"2134",
    "addr:street":"Elizabeth St",
    "iso:country":"AU",
    "sg:address":"10 Elizabeth St",
    "sg:city":"Burwood",
    "sg:classifiers":[
        {
            "category":"Personal",
            "subcategory":"Adult",
            "type":"Services"
        }
    ],
    "sg:phone":"+61 2 9744 1976",
    "sg:postcode":"2134",
    "sg:province":"NSW",
    "sg:tags":[
        "vic",
        "except",
        "state",
        "escort",
        "social",
        "qld"
    ],
    "wof:name":"Tai-Pan-Studio",
    "wof:placetype":"venue"
},
  "geometry": {"coordinates":[151.10479736299999,-33.8787307739],"type":"Point"}
}