{
  "type": "Feature",
  "properties": {
    "iso:country":"AU",
    "sg:address":"15 Oak Ave",
    "sg:city":"Bridgewater",
    "sg:classifiers":[
        {
            "category":"Home & Garden",
            "subcategory":"Building Materials",
            "type":"Retail Goods"
        }
    ],
    "sg:phone":"+61 8 8339 3602",
    "sg:postcode":"5155",
    "sg:province":"SA",
    "sg:tags":[
        "lawn",
        "cutting",
        "maintenance"
    ],
    "wof:name":"Wattle Mowing Services",
    "wof:placetype":"venue"
},
  "geometry": {"coordinates":[138.76873779300001,-35.0151405334],"type":"Point"}
}