{
  "type": "Feature",
  "properties": {
    "addr:full":"Little Hurley La Cootamundra NSW 2590",
    "addr:postcode":"2590",
    "iso:country":"AU",
    "sg:address":"Little Hurley La",
    "sg:city":"Cootamundra",
    "sg:classifiers":[
        {
            "category":"Real Estate",
            "subcategory":"Real Estate Agent",
            "type":"Services"
        }
    ],
    "sg:phone":"+61 2 6942 1035",
    "sg:postcode":"2590",
    "sg:province":"NSW",
    "wof:name":"Daryl W Sedgwick",
    "wof:placetype":"venue"
},
  "geometry": {"coordinates":[148.02293395999999,-34.6432914734],"type":"Point"}
}