{
  "type": "Feature",
  "properties": {
    "addr:full":"94 Anzac Pde Kensington NSW 2033",
    "addr:housenumber":"94",
    "addr:postcode":"2033",
    "addr:street":"Anzac Pde",
    "iso:country":"AU",
    "sg:address":"94 Anzac Pde",
    "sg:city":"Kensington",
    "sg:classifiers":[
        {
            "category":"Banks & Credit Unions",
            "subcategory":"Financial Services",
            "type":"Services"
        }
    ],
    "sg:phone":"+61 2 9663 1311",
    "sg:postcode":"2033",
    "sg:province":"NSW",
    "sg:tags":[
        "planning"
    ],
    "wof:name":"Winchcombe Carson Financial Planning Pty Ltd",
    "wof:placetype":"venue"
},
  "geometry": {"coordinates":[151.224075,-33.906342],"type":"Point"}
}