{
  "type": "Feature",
  "properties": {
    "addr:full":"229 Sheridan St Cairns North QLD 4870",
    "addr:housenumber":"229",
    "addr:postcode":"4870",
    "addr:street":"Sheridan St",
    "iso:country":"AU",
    "sg:address":"229 Sheridan St",
    "sg:city":"Cairns North",
    "sg:classifiers":[
        {
            "category":"Deli",
            "type":"Food & Drink"
        }
    ],
    "sg:phone":"+61 7 4031 2922",
    "sg:postcode":"4870",
    "sg:province":"QLD",
    "sg:tags":[
        "delicatessen"
    ],
    "wof:name":"Victors Gourmet Deli",
    "wof:placetype":"venue"
},
  "geometry": {"coordinates":[145.759887695,-16.9072723389],"type":"Point"}
}