{
  "type": "Feature",
  "properties": {
    "addr:full":"Cnr Walter Rd & Russell St Morley WA 6062",
    "addr:postcode":"6062",
    "addr:street":"Walter Rd & Russell St",
    "iso:country":"AU",
    "sg:address":"Cnr Walter Rd & Russell St",
    "sg:city":"Morley",
    "sg:classifiers":[
        {
            "category":"Fast Food",
            "type":"Food & Drink"
        }
    ],
    "sg:phone":"+61 8 9275 8600",
    "sg:postcode":"6062",
    "sg:province":"WA",
    "sg:tags":[
        "away",
        "take"
    ],
    "wof:name":"Subway Sandwiches & Salads",
    "wof:placetype":"venue"
},
  "geometry": {"coordinates":[115.896659851,-31.8949699402],"type":"Point"}
}