{
  "type": "Feature",
  "properties": {
    "iso:country":"AU",
    "sg:address":"Unit 3/ 14 Lapis St",
    "sg:city":"Underwood",
    "sg:classifiers":[
        {
            "category":"Retail",
            "subcategory":"Auto Repair",
            "type":"Services"
        }
    ],
    "sg:phone":"+61 7 3290 2177",
    "sg:postcode":"4119",
    "sg:province":"QLD",
    "sg:tags":[
        "repairer",
        "motor",
        "engineer"
    ],
    "wof:name":"Innovative Auto Design",
    "wof:placetype":"venue"
},
  "geometry": {"coordinates":[153.115890503,-27.6198272705],"type":"Point"}
}