{
  "type": "Feature",
  "properties": {
    "addr:full":"173 The Entrance Rd Erina NSW 2250",
    "addr:housenumber":"173",
    "addr:postcode":"2250",
    "addr:street":"The Entrance Rd",
    "iso:country":"AU",
    "sg:address":"173 The Entrance Rd",
    "sg:city":"Erina",
    "sg:classifiers":[
        {
            "category":"Home & Garden",
            "subcategory":"Furniture",
            "type":"Retail Goods"
        }
    ],
    "sg:phone":"+61 2 4323 1122",
    "sg:postcode":"2250",
    "sg:province":"NSW",
    "sg:tags":[
        "repair",
        "restoration"
    ],
    "wof:name":"Ezycut Foam",
    "wof:placetype":"venue"
},
  "geometry": {"coordinates":[151.384689331,-33.4361724854],"type":"Point"}
}