{
  "type": "Feature",
  "properties": {
    "addr:full":"710 Pimpama/Jacobs Well Rd Norwell QLD 4208",
    "addr:housenumber":"710;/",
    "addr:postcode":"4208",
    "addr:street":"Pimpama;Jacobs Well Rd",
    "iso:country":"AU",
    "sg:address":"710 Pimpama/Jacobs Well Rd",
    "sg:city":"Norwell",
    "sg:classifiers":[
        {
            "category":"Utilities",
            "subcategory":"Water",
            "type":"Services"
        }
    ],
    "sg:phone":"+61 419 794 810",
    "sg:postcode":"4208",
    "sg:province":"QLD",
    "sg:tags":[
        "cartage"
    ],
    "wof:name":"The Old Watercart",
    "wof:placetype":"venue"
},
  "geometry": {"coordinates":[153.32618713400001,-27.7888565063],"type":"Point"}
}