{
  "type": "Feature",
  "properties": {
    "addr:full":"12 Horsfall St Lower Templestowe VIC 3107",
    "addr:housenumber":"12",
    "addr:postcode":"3107",
    "addr:street":"Horsfall St",
    "iso:country":"AU",
    "sg:address":"12 Horsfall St",
    "sg:city":"Lower Templestowe",
    "sg:classifiers":[
        {
            "category":"Professional",
            "subcategory":"Accounting & Tax Preparation",
            "type":"Services"
        }
    ],
    "sg:phone":"+61 3 9850 8288",
    "sg:postcode":"3107",
    "sg:province":"VIC",
    "sg:tags":[
        "accountant",
        "auditor"
    ],
    "wof:name":"Millis Terry",
    "wof:placetype":"venue"
},
  "geometry": {"coordinates":[145.11851501500001,-37.7654571533],"type":"Point"}
}