{
  "type": "Feature",
  "properties": {
    "addr:full":"1158 Port Wakefield Rd Burton SA 5110",
    "addr:housenumber":"1158",
    "addr:postcode":"5110",
    "addr:street":"Port Wakefield Rd",
    "iso:country":"AU",
    "sg:address":"1158 Port Wakefield Rd",
    "sg:city":"Burton",
    "sg:phone":"+61 8 8280 8069",
    "sg:postcode":"5110",
    "sg:province":"SA",
    "wof:name":"Betta Tanks",
    "wof:placetype":"venue"
},
  "geometry": {"coordinates":[138.586380005,-34.7430076599],"type":"Point"}
}