{
  "type": "Feature",
  "properties": {
    "iso:country":"AU",
    "sg:address":"Lvl 3, 627 Chapel St",
    "sg:city":"South Yarra",
    "sg:classifiers":[
        {
            "category":"Professional",
            "subcategory":"Management & Consulting",
            "type":"Services"
        }
    ],
    "sg:phone":"+61 3 9804 8887",
    "sg:postcode":"3141",
    "sg:province":"VIC",
    "sg:tags":[
        "consultant",
        "migration"
    ],
    "wof:name":"Hamilton Watts International Migration Services",
    "wof:placetype":"venue"
},
  "geometry": {"coordinates":[144.99566650400001,-37.8383979797],"type":"Point"}
}