{
  "type": "Feature",
  "properties": {
    "addr:full":"Suite 2/ 20 Cliff St Milsons Point NSW 2061",
    "addr:housenumber":"20",
    "addr:postcode":"2061",
    "addr:street":"Cliff St",
    "iso:country":"AU",
    "sg:address":"Suite 2/ 20 Cliff St",
    "sg:city":"Milsons Point",
    "sg:classifiers":[
        {
            "category":"Professional",
            "subcategory":"Art Services",
            "type":"Services"
        }
    ],
    "sg:phone":"+61 2 9959 5656",
    "sg:postcode":"2061",
    "sg:province":"NSW",
    "sg:tags":[
        "interior",
        "decorator"
    ],
    "wof:name":"innersphere Design",
    "wof:placetype":"venue"
},
  "geometry": {"coordinates":[151.21029663100001,-33.8448600769],"type":"Point"}
}