{
  "type": "Feature",
  "properties": {
    "iso:country":"AU",
    "sg:address":"Barkly Hwy, Mt Isa Airport",
    "sg:city":"Mt Isa",
    "sg:classifiers":[
        {
            "category":"Retail",
            "subcategory":"Auto Rental",
            "type":"Services"
        }
    ],
    "sg:phone":"+61 7 4749 1828",
    "sg:postcode":"4825",
    "sg:province":"QLD",
    "sg:tags":[
        "car",
        "hire",
        "minibus"
    ],
    "wof:name":"Budget Rent A Car Mt Isa",
    "wof:placetype":"venue"
},
  "geometry": {"coordinates":[139.49641399999999,-20.712479],"type":"Point"}
}