{
  "type": "Feature",
  "properties": {
    "addr:full":"93 High St Doncaster VIC 3108",
    "addr:housenumber":"93",
    "addr:postcode":"3108",
    "addr:street":"High St",
    "iso:country":"AU",
    "sg:address":"93 High St",
    "sg:city":"Doncaster",
    "sg:classifiers":[
        {
            "category":"Personal",
            "subcategory":"Beauty Salon",
            "type":"Services"
        }
    ],
    "sg:phone":"+61 3 9857 8777",
    "sg:postcode":"3108",
    "sg:province":"VIC",
    "sg:tags":[
        "hairdresser"
    ],
    "wof:name":"V A Professional Hairdressing",
    "wof:placetype":"venue"
},
  "geometry": {"coordinates":[145.11041259800001,-37.7816886902],"type":"Point"}
}