{
  "type": "Feature",
  "properties": {
    "addr:full":"4 Primrose Crt Grange SA 5022",
    "addr:housenumber":"4",
    "addr:postcode":"5022",
    "addr:street":"Primrose Crt",
    "iso:country":"AU",
    "sg:address":"4 Primrose Crt",
    "sg:city":"Grange",
    "sg:classifiers":[
        {
            "category":"Professional",
            "subcategory":"Computer Services",
            "type":"Services"
        }
    ],
    "sg:phone":"+61 8 8355 0292",
    "sg:postcode":"5022",
    "sg:province":"SA",
    "sg:tags":[
        "consultant",
        "system"
    ],
    "wof:name":"Roccisano J & F Consulting Pty Ltd",
    "wof:placetype":"venue"
},
  "geometry": {"coordinates":[138.50286865199999,-34.8929634094],"type":"Point"}
}