{
  "type": "Feature",
  "properties": {
    "iso:country":"AU",
    "sg:address":"Shop 1 The Circle Park Rd",
    "sg:city":"Woonona",
    "sg:classifiers":[
        {
            "category":"Food & Beverages",
            "subcategory":"Bakery",
            "type":"Retail Goods"
        }
    ],
    "sg:phone":"+61 2 4285 2574",
    "sg:postcode":"2517",
    "sg:province":"NSW",
    "sg:tags":[
        "baker"
    ],
    "wof:name":"Phils Hot Bread Shop",
    "wof:placetype":"venue"
},
  "geometry": {"coordinates":[150.914139,-34.349358],"type":"Point"}
}