{
  "type": "Feature",
  "properties": {
    "addr:full":"150 Terania St Lismore NSW 2480",
    "addr:housenumber":"150",
    "addr:postcode":"2480",
    "addr:street":"Terania St",
    "iso:country":"AU",
    "sg:address":"150 Terania St",
    "sg:city":"Lismore",
    "sg:classifiers":[
        {
            "category":"Retail",
            "subcategory":"Auto Repair",
            "type":"Services"
        }
    ],
    "sg:phone":"+61 2 6622 3300",
    "sg:postcode":"2480",
    "sg:province":"NSW",
    "sg:tags":[
        "repairer",
        "motor",
        "engineer"
    ],
    "sg:website":"http://www.albertiniauto.com.au",
    "wof:name":"Chris Albertini Automotive",
    "wof:placetype":"venue"
},
  "geometry": {"coordinates":[153.26651000999999,-28.801612854],"type":"Point"}
}