{
  "type": "Feature",
  "properties": {
    "iso:country":"AU",
    "sg:address":"2 Coll Pl",
    "sg:city":"Warwick",
    "sg:classifiers":[
        {
            "category":"Building & Trades",
            "subcategory":"Construction",
            "type":"Services"
        }
    ],
    "sg:phone":"+61 8 9448 3617",
    "sg:postcode":"6024",
    "sg:province":"WA",
    "sg:tags":[
        "ceiling"
    ],
    "wof:name":"Albert's Ceiling's & Partition's",
    "wof:placetype":"venue"
},
  "geometry": {"coordinates":[115.80065155,-31.839887619],"type":"Point"}
}