{
  "type": "Feature",
  "properties": {
    "addr:full":"4 Normanby St Mermaid Waters QLD 4218",
    "addr:housenumber":"4",
    "addr:postcode":"4218",
    "addr:street":"Normanby St",
    "iso:country":"AU",
    "sg:address":"4 Normanby St",
    "sg:city":"Mermaid Waters",
    "sg:classifiers":[
        {
            "category":"Building & Trades",
            "subcategory":"Plumbing",
            "type":"Services"
        }
    ],
    "sg:phone":"+61 412 140 488",
    "sg:postcode":"4218",
    "sg:province":"QLD",
    "sg:tags":[
        "plumber",
        "gasfitters"
    ],
    "wof:name":"A D S Plumbing",
    "wof:placetype":"venue"
},
  "geometry": {"coordinates":[153.410446167,-28.0483760834],"type":"Point"}
}