{
  "type": "Feature",
  "properties": {
    "addr:full":"84 William St Melbourne VIC 3000",
    "addr:housenumber":"84",
    "addr:postcode":"3000",
    "addr:street":"William St",
    "iso:country":"AU",
    "sg:address":"84 William St",
    "sg:city":"Melbourne",
    "sg:classifiers":[
        {
            "category":"Organizations",
            "subcategory":"Professional Association",
            "type":"Services"
        }
    ],
    "sg:phone":"+61 3 9670 8332",
    "sg:postcode":"3000",
    "sg:province":"VIC",
    "sg:tags":[
        "organisation",
        "business"
    ],
    "wof:name":"Spanish Official Chamber of Commerce (Vic)",
    "wof:placetype":"venue"
},
  "geometry": {"coordinates":[144.959182739,-37.817440033],"type":"Point"}
}