{
  "type": "Feature",
  "properties": {
    "addr:full":"100 Hannan St Kalgoorlie WA 6430",
    "addr:housenumber":"100",
    "addr:postcode":"6430",
    "addr:street":"Hannan St",
    "iso:country":"AU",
    "sg:address":"100 Hannan St",
    "sg:city":"Kalgoorlie",
    "sg:classifiers":[
        {
            "category":"Shopping",
            "subcategory":"Stationery & Office Supplies",
            "type":"Retail Goods"
        }
    ],
    "sg:phone":"+61 8 9021 1166",
    "sg:postcode":"6430",
    "sg:province":"WA",
    "sg:tags":[
        "equipment",
        "facsimile"
    ],
    "wof:name":"G.B.M. Office National",
    "wof:placetype":"venue"
},
  "geometry": {"coordinates":[121.467689514,-30.7516498566],"type":"Point"}
}