{
  "type": "Feature",
  "properties": {
    "addr:full":"11 Elizabeth St George Town TAS 7253",
    "addr:housenumber":"11",
    "addr:postcode":"7253",
    "addr:street":"Elizabeth St",
    "iso:country":"AU",
    "sg:address":"11 Elizabeth St",
    "sg:city":"George Town",
    "sg:classifiers":[
        {
            "category":"Health Services",
            "subcategory":"Health Practitioner",
            "type":"Services"
        }
    ],
    "sg:phone":"+61 3 6382 3717",
    "sg:postcode":"7253",
    "sg:province":"TAS",
    "sg:tags":[
        "hypnotherapy"
    ],
    "wof:name":"Brenda McMahon",
    "wof:placetype":"venue"
},
  "geometry": {"coordinates":[146.82095336899999,-41.1079940796],"type":"Point"}
}