{
  "type": "Feature",
  "properties": {
    "addr:full":"36-38 Butler St Tully QLD 4854",
    "addr:housenumber":"36-38",
    "addr:postcode":"4854",
    "addr:street":"Butler St",
    "iso:country":"AU",
    "sg:address":"36-38 Butler St",
    "sg:city":"Tully",
    "sg:classifiers":[
        {
            "category":"Shopping",
            "subcategory":"Clothing, Apparel, & Fashions",
            "type":"Retail Goods"
        }
    ],
    "sg:phone":"+61 7 4068 1260",
    "sg:postcode":"4854",
    "sg:province":"QLD",
    "sg:tags":[
        "lady",
        "wear"
    ],
    "wof:name":"Pezzutto Fashions",
    "wof:placetype":"venue"
},
  "geometry": {"coordinates":[145.92506408700001,-17.9339046478],"type":"Point"}
}