{
  "type": "Feature",
  "properties": {
    "addr:full":"1840 Sandgate Rd Virginia QLD 4014",
    "addr:housenumber":"1840",
    "addr:postcode":"4014",
    "addr:street":"Sandgate Rd",
    "iso:country":"AU",
    "sg:address":"1840 Sandgate Rd",
    "sg:city":"Virginia",
    "sg:classifiers":[
        {
            "category":"Building & Trades",
            "subcategory":"Equipment Rental",
            "type":"Services"
        }
    ],
    "sg:phone":"+61 7 3865 1377",
    "sg:postcode":"4014",
    "sg:province":"QLD",
    "sg:tags":[
        "supply",
        "catering"
    ],
    "wof:name":"Campbells Catering Services",
    "wof:placetype":"venue"
},
  "geometry": {"coordinates":[153.062210083,-27.3732566833],"type":"Point"}
}