{
  "type": "Feature",
  "properties": {
    "iso:country":"AU",
    "sg:address":"11 Mathieson St",
    "sg:city":"Camperdown",
    "sg:classifiers":[
        {
            "category":"Arts & Performance",
            "subcategory":"Theater",
            "type":"Entertainment"
        }
    ],
    "sg:phone":"+61 2 9565 6540",
    "sg:postcode":"2050",
    "sg:province":"NSW",
    "sg:tags":[
        "theatrical",
        "supply"
    ],
    "wof:name":"Sydney Prop Specialists",
    "wof:placetype":"venue"
},
  "geometry": {"coordinates":[151.172867,-33.886555],"type":"Point"}
}