{
  "type": "Feature",
  "properties": {
    "addr:full":"87 Unitt St Melton VIC 3337",
    "addr:housenumber":"87",
    "addr:postcode":"3337",
    "addr:street":"Unitt St",
    "iso:country":"AU",
    "sg:address":"87 Unitt St",
    "sg:city":"Melton",
    "sg:classifiers":[
        {
            "category":"Fast Food",
            "type":"Food & Drink"
        }
    ],
    "sg:phone":"+61 3 9743 8150",
    "sg:postcode":"3337",
    "sg:province":"VIC",
    "sg:tags":[
        "away",
        "take"
    ],
    "wof:name":"Jim's Fish Shop",
    "wof:placetype":"venue"
},
  "geometry": {"coordinates":[144.581467,-37.682152],"type":"Point"}
}