{
  "type": "Feature",
  "properties": {
    "addr:full":"2 Harrald St Mt Gambier SA 5290",
    "addr:housenumber":"2",
    "addr:postcode":"5290",
    "addr:street":"Harrald St",
    "iso:country":"AU",
    "sg:address":"2 Harrald St",
    "sg:city":"Mt Gambier",
    "sg:classifiers":[
        {
            "category":"Professional",
            "subcategory":"Engineering",
            "type":"Services"
        }
    ],
    "sg:phone":"+61 8 8726 2200",
    "sg:postcode":"5290",
    "sg:province":"SA",
    "sg:tags":[
        "manufacturing",
        "engineer"
    ],
    "wof:name":"Krueger Engineering Pty Ltd",
    "wof:placetype":"venue"
},
  "geometry": {"coordinates":[140.78627,-37.833344],"type":"Point"}
}