{
  "type": "Feature",
  "properties": {
    "addr:full":"92 Flowerdale Rd Liverpool NSW 2170",
    "addr:housenumber":"92",
    "addr:postcode":"2170",
    "addr:street":"Flowerdale Rd",
    "iso:country":"AU",
    "sg:address":"92 Flowerdale Rd",
    "sg:city":"Liverpool",
    "sg:classifiers":[
        {
            "category":"Health Services",
            "subcategory":"Chiropractor",
            "type":"Services"
        }
    ],
    "sg:phone":"+61 2 9734 0044",
    "sg:postcode":"2170",
    "sg:province":"NSW",
    "wof:name":"Brkljac Milan",
    "wof:placetype":"venue"
},
  "geometry": {"coordinates":[150.90805053700001,-33.9230766296],"type":"Point"}
}