{
  "type": "Feature",
  "properties": {
    "iso:country":"AU",
    "sg:address":"Shop 15, HomeBase 252 Pacific Hwy",
    "sg:city":"Coffs Harbour",
    "sg:classifiers":[
        {
            "category":"Home & Garden",
            "subcategory":"Carpets & Floor Coverings",
            "type":"Retail Goods"
        }
    ],
    "sg:phone":"+61 2 6650 9922",
    "sg:postcode":"2450",
    "sg:province":"NSW",
    "sg:tags":[
        "mattress"
    ],
    "wof:name":"Clark Rubber",
    "wof:placetype":"venue"
},
  "geometry": {"coordinates":[153.091217,-30.317438],"type":"Point"}
}