{
  "type": "Feature",
  "properties": {
    "iso:country":"AU",
    "sg:address":"Unit 1/ 9 Shearwater Drv",
    "sg:city":"Taylors Beach",
    "sg:classifiers":[
        {
            "category":"Home & Garden",
            "subcategory":"Furniture",
            "type":"Retail Goods"
        }
    ],
    "sg:phone":"+61 2 4982 2597",
    "sg:postcode":"2316",
    "sg:province":"NSW",
    "sg:tags":[
        "outdoor"
    ],
    "wof:name":"Gateway Outdoor Furniture",
    "wof:placetype":"venue"
},
  "geometry": {"coordinates":[152.069748,-32.751541],"type":"Point"}
}