{
  "type": "Feature",
  "properties": {
    "addr:full":"78 High St Oatlands TAS 7120",
    "addr:housenumber":"78",
    "addr:postcode":"7120",
    "addr:street":"High St",
    "iso:country":"AU",
    "sg:address":"78 High St",
    "sg:city":"Oatlands",
    "sg:classifiers":[
        {
            "category":"Shopping",
            "subcategory":"Antiques",
            "type":"Retail Goods"
        }
    ],
    "sg:phone":"+61 3 6254 0052",
    "sg:postcode":"7120",
    "sg:province":"TAS",
    "wof:name":"Architectural Restorations",
    "wof:placetype":"venue"
},
  "geometry": {"coordinates":[147.372436523,-42.2990112305],"type":"Point"}
}