{
  "type": "Feature",
  "properties": {
    "addr:full":"5 Bell St Booragul NSW 2284",
    "addr:housenumber":"5",
    "addr:postcode":"2284",
    "addr:street":"Bell St",
    "iso:country":"AU",
    "sg:address":"5 Bell St",
    "sg:city":"Booragul",
    "sg:classifiers":[
        {
            "category":"Government",
            "subcategory":"Fire Station",
            "type":"Public Place"
        }
    ],
    "sg:phone":"+61 2 4958 6539",
    "sg:postcode":"2284",
    "sg:province":"NSW",
    "sg:tags":[
        "equipment",
        "protection",
        "consultant"
    ],
    "wof:name":"Slade Plumbing",
    "wof:placetype":"venue"
},
  "geometry": {"coordinates":[151.61094665499999,-32.972782135],"type":"Point"}
}