{
  "type": "Feature",
  "properties": {
    "addr:full":"9 Lenane St Moora WA 6510",
    "addr:housenumber":"9",
    "addr:postcode":"6510",
    "addr:street":"Lenane St",
    "iso:country":"AU",
    "sg:address":"9 Lenane St",
    "sg:city":"Moora",
    "sg:classifiers":[
        {
            "category":"Utilities",
            "subcategory":"Recycling",
            "type":"Services"
        }
    ],
    "sg:phone":"+61 8 9651 1471",
    "sg:postcode":"6510",
    "sg:province":"WA",
    "wof:name":"Moora Marine Collectors Recyclers & Carriers",
    "wof:placetype":"venue"
},
  "geometry": {"coordinates":[116.00157900000001,-30.64315],"type":"Point"}
}