{
  "type": "Feature",
  "properties": {
    "addr:full":"28 Male St Brighton VIC 3186",
    "addr:housenumber":"28",
    "addr:postcode":"3186",
    "addr:street":"Male St",
    "iso:country":"AU",
    "sg:address":"28 Male St",
    "sg:city":"Brighton",
    "sg:classifiers":[
        {
            "category":"Health Services",
            "subcategory":"Doctor",
            "type":"Services"
        }
    ],
    "sg:phone":"+61 3 9592 3403",
    "sg:postcode":"3186",
    "sg:province":"VIC",
    "sg:tags":[
        "podiatrist"
    ],
    "wof:name":"Anant S. Purohit",
    "wof:placetype":"venue"
},
  "geometry": {"coordinates":[144.99928283700001,-37.9143104553],"type":"Point"}
}