{
  "type": "Feature",
  "properties": {
    "addr:full":"4 Grafton Crt Canning Vale WA 6155",
    "addr:housenumber":"4",
    "addr:postcode":"6155",
    "addr:street":"Grafton Crt",
    "iso:country":"AU",
    "sg:address":"4 Grafton Crt",
    "sg:city":"Canning Vale",
    "sg:classifiers":[
        {
            "category":"Insurance",
            "subcategory":"Insurance Agent",
            "type":"Services"
        }
    ],
    "sg:phone":"+61 8 9455 3810",
    "sg:postcode":"6155",
    "sg:province":"WA",
    "wof:name":"Barnes D & Associates-Insurance Agents",
    "wof:placetype":"venue"
},
  "geometry": {"coordinates":[115.94149,-32.076099],"type":"Point"}
}