{
  "type": "Feature",
  "properties": {
    "addr:full":"Paringa Rd Gibson Island QLD 4172",
    "addr:postcode":"4172",
    "addr:street":"Paringa Rd",
    "iso:country":"AU",
    "sg:address":"Paringa Rd",
    "sg:city":"Gibson Island",
    "sg:classifiers":[
        {
            "category":"Home & Garden",
            "subcategory":"Garden Supply",
            "type":"Retail Goods"
        }
    ],
    "sg:phone":"+61 7 3867 9300",
    "sg:postcode":"4172",
    "sg:province":"QLD",
    "sg:tags":[
        "fertilizer"
    ],
    "wof:name":"Incitec Fertilizers",
    "wof:placetype":"venue"
},
  "geometry": {"coordinates":[153.10800170900001,-27.4470748901],"type":"Point"}
}