{
  "type": "Feature",
  "properties": {
    "addr:full":"16-18 Mudlo St Port Douglas QLD 4877",
    "addr:housenumber":"16-18",
    "addr:postcode":"4877",
    "addr:street":"Mudlo St",
    "iso:country":"AU",
    "sg:address":"16-18 Mudlo St",
    "sg:city":"Port Douglas",
    "sg:classifiers":[
        {
            "category":"Travel",
            "subcategory":"Hotels & Motels",
            "type":"Entertainment"
        }
    ],
    "sg:phone":"+61 7 4099 5662",
    "sg:postcode":"4877",
    "sg:province":"QLD",
    "wof:name":"Port Douglas Outrigger",
    "wof:placetype":"venue"
},
  "geometry": {"coordinates":[145.46434020999999,-16.4860363007],"type":"Point"}
}