{
  "type": "Feature",
  "properties": {
    "addr:full":"Uniting Church Hall, Forest St Bendigo VIC 3550",
    "addr:postcode":"3550",
    "addr:street":"Forest St",
    "iso:country":"AU",
    "sg:address":"Uniting Church Hall, Forest St",
    "sg:city":"Bendigo",
    "sg:classifiers":[
        {
            "category":"Arts & Performance",
            "subcategory":"Dance",
            "type":"Entertainment"
        }
    ],
    "sg:phone":"+61 409 470 704",
    "sg:postcode":"3550",
    "sg:province":"VIC",
    "sg:tags":[
        "theatrical",
        "ballet",
        "tuition"
    ],
    "wof:name":"Dynamite Dance",
    "wof:placetype":"venue"
},
  "geometry": {"coordinates":[144.27636718799999,-36.7594909668],"type":"Point"}
}