{
  "type": "Feature",
  "properties": {
    "iso:country":"AU",
    "sg:address":"31 River St",
    "sg:city":"Woolgoolga",
    "sg:classifiers":[
        {
            "category":"Food & Beverages",
            "subcategory":"Supermarket",
            "type":"Retail Goods"
        }
    ],
    "sg:phone":"+61 2 6654 1366",
    "sg:postcode":"2456",
    "sg:province":"NSW",
    "sg:tags":[
        "grocery",
        "store"
    ],
    "wof:name":"Top Town Market",
    "wof:placetype":"venue"
},
  "geometry": {"coordinates":[153.1931,-30.115013],"type":"Point"}
}