{
  "type": "Feature",
  "properties": {
    "addr:full":"13 Mackley St Garbutt QLD 4814",
    "addr:housenumber":"13",
    "addr:postcode":"4814",
    "addr:street":"Mackley St",
    "iso:country":"AU",
    "sg:address":"13 Mackley St",
    "sg:city":"Garbutt",
    "sg:classifiers":[
        {
            "category":"Building & Trades",
            "subcategory":"Construction",
            "type":"Services"
        }
    ],
    "sg:phone":"+61 1300 722 228",
    "sg:postcode":"4814",
    "sg:province":"QLD",
    "sg:tags":[
        "home",
        "air conditioning"
    ],
    "wof:name":"Mitsubishi Electric",
    "wof:placetype":"venue"
},
  "geometry": {"coordinates":[146.76997399999999,-19.272108],"type":"Point"}
}