{
  "type": "Feature",
  "properties": {
    "addr:full":"73 Chadstone Rd Chadstone VIC 3148",
    "addr:housenumber":"73",
    "addr:postcode":"3148",
    "addr:street":"Chadstone Rd",
    "iso:country":"AU",
    "sg:address":"73 Chadstone Rd",
    "sg:city":"Chadstone",
    "sg:classifiers":[
        {
            "category":"Health Services",
            "subcategory":"Doctor",
            "type":"Services"
        }
    ],
    "sg:phone":"+61 3 9569 5796",
    "sg:postcode":"3148",
    "sg:province":"VIC",
    "sg:tags":[
        "podiatrist"
    ],
    "wof:name":"Chadstone Podiatric Clinic",
    "wof:placetype":"venue"
},
  "geometry": {"coordinates":[145.07896423299999,-37.8818244934],"type":"Point"}
}