{
  "type": "Feature",
  "properties": {
    "addr:full":"227 Lum Rd Wheelers Hill VIC 3150",
    "addr:housenumber":"227",
    "addr:postcode":"3150",
    "addr:street":"Lum Rd",
    "iso:country":"AU",
    "sg:address":"227 Lum Rd",
    "sg:city":"Wheelers Hill",
    "sg:classifiers":[
        {
            "category":"Education",
            "subcategory":"School",
            "type":"Public Place"
        }
    ],
    "sg:phone":"+61 3 9561 4309",
    "sg:postcode":"3150",
    "sg:province":"VIC",
    "wof:name":"Ariston Greek School",
    "wof:placetype":"venue"
},
  "geometry": {"coordinates":[145.17860412600001,-37.9109115601],"type":"Point"}
}