{
  "type": "Feature",
  "properties": {
    "addr:full":"30 Grant Ave Rose Park SA 5067",
    "addr:housenumber":"30",
    "addr:postcode":"5067",
    "addr:street":"Grant Ave Rose",
    "iso:country":"AU",
    "sg:address":"30 Grant Ave",
    "sg:city":"Rose Park",
    "sg:classifiers":[
        {
            "category":"Professional",
            "subcategory":"Computer Services",
            "type":"Services"
        }
    ],
    "sg:phone":"+61 8 8364 3766",
    "sg:postcode":"5067",
    "sg:province":"SA",
    "sg:tags":[
        "package",
        "software"
    ],
    "wof:name":"Specialist Magnetics",
    "wof:placetype":"venue"
},
  "geometry": {"coordinates":[138.62701415999999,-34.9323577881],"type":"Point"}
}