{
  "type": "Feature",
  "properties": {
    "addr:full":"95 High St Woodend VIC 3442",
    "addr:housenumber":"95",
    "addr:postcode":"3442",
    "addr:street":"High St",
    "iso:country":"AU",
    "sg:address":"95 High St",
    "sg:city":"Woodend",
    "sg:classifiers":[
        {
            "category":"Manufacturing",
            "subcategory":"Food",
            "type":"Manufacturing & Wholesale Goods"
        }
    ],
    "sg:phone":"+61 3 5427 1608",
    "sg:postcode":"3442",
    "sg:province":"VIC",
    "sg:tags":[
        "function",
        "catering"
    ],
    "wof:name":"Maloa House Gourmet Delights",
    "wof:placetype":"venue"
},
  "geometry": {"coordinates":[144.528442383,-37.3551635742],"type":"Point"}
}