{
  "type": "Feature",
  "properties": {
    "addr:full":"258 Railway Pde Noble Park VIC 3174",
    "addr:housenumber":"258",
    "addr:postcode":"3174",
    "addr:street":"Railway Pde",
    "iso:country":"AU",
    "sg:address":"258 Railway Pde",
    "sg:city":"Noble Park",
    "sg:classifiers":[
        {
            "category":"Retail",
            "subcategory":"Self-service Laundry",
            "type":"Services"
        }
    ],
    "sg:phone":"+61 418 566 027",
    "sg:postcode":"3174",
    "sg:province":"VIC",
    "wof:name":"Noble Park Supawash",
    "wof:placetype":"venue"
},
  "geometry": {"coordinates":[145.18669128400001,-37.9739875793],"type":"Point"}
}