{
  "type": "Feature",
  "properties": {
    "iso:country":"AU",
    "sg:address":"40 Currawong Crs",
    "sg:city":"Leonay",
    "sg:classifiers":[
        {
            "category":"Shopping",
            "subcategory":"Pets & Pet Supplies",
            "type":"Retail Goods"
        }
    ],
    "sg:phone":"+61 2 4735 4050",
    "sg:postcode":"2750",
    "sg:province":"NSW",
    "sg:tags":[
        "dog"
    ],
    "wof:name":"Petcetera Etc",
    "wof:placetype":"venue"
},
  "geometry": {"coordinates":[150.92427063,-33.7353057861],"type":"Point"}
}