{
  "type": "Feature",
  "properties": {
    "iso:country":"AU",
    "sg:address":"347 Cambridge St",
    "sg:city":"Wembley",
    "sg:classifiers":[
        {
            "category":"Manufacturing",
            "subcategory":"Jewelry",
            "type":"Manufacturing & Wholesale Goods"
        }
    ],
    "sg:phone":"+61 8 9285 8599",
    "sg:postcode":"6014",
    "sg:province":"WA",
    "sg:tags":[
        "designer",
        "jewellery"
    ],
    "wof:name":"Trent Malkin",
    "wof:placetype":"venue"
},
  "geometry": {"coordinates":[115.81092834499999,-31.9408855438],"type":"Point"}
}