{
  "type": "Feature",
  "properties": {
    "iso:country":"AU",
    "sg:address":"Shp 181 Westfield Shopngtwn Macquarie St",
    "sg:city":"Liverpool",
    "sg:classifiers":[
        {
            "category":"Shopping",
            "subcategory":"Mobile Phones",
            "type":"Retail Goods"
        }
    ],
    "sg:phone":"+61 2 9602 1299",
    "sg:postcode":"2170",
    "sg:province":"NSW",
    "sg:tags":[
        "telephone",
        "accessory"
    ],
    "wof:name":"Optus World",
    "wof:placetype":"venue"
},
  "geometry": {"coordinates":[150.91822814899999,-33.9286499023],"type":"Point"}
}