{
  "type": "Feature",
  "properties": {
    "addr:full":"41 Woodlands St Baulkham Hills NSW 2153",
    "addr:housenumber":"41",
    "addr:postcode":"2153",
    "addr:street":"Woodlands St",
    "iso:country":"AU",
    "sg:address":"41 Woodlands St",
    "sg:city":"Baulkham Hills",
    "sg:classifiers":[
        {
            "category":"Building & Trades",
            "subcategory":"Plumbing",
            "type":"Services"
        }
    ],
    "sg:phone":"+61 2 9639 1962",
    "sg:postcode":"2153",
    "sg:province":"NSW",
    "sg:tags":[
        "plumber",
        "gasfitters"
    ],
    "wof:name":"Craig Willis Plumbing",
    "wof:placetype":"venue"
},
  "geometry": {"coordinates":[150.99891662600001,-33.7702903748],"type":"Point"}
}