{
  "type": "Feature",
  "properties": {
    "iso:country":"AU",
    "sg:address":"96 Browns Rd",
    "sg:city":"Wahroonga",
    "sg:classifiers":[
        {
            "category":"Health Services",
            "subcategory":"Doctor",
            "type":"Services"
        }
    ],
    "sg:phone":"+61 2 9489 9934",
    "sg:postcode":"2076",
    "sg:province":"NSW",
    "sg:tags":[
        "medical",
        "practitioner"
    ],
    "wof:name":"Arora Anil Dr",
    "wof:placetype":"venue"
},
  "geometry": {"coordinates":[151.093185425,-33.7350578308],"type":"Point"}
}