{
  "type": "Feature",
  "properties": {
    "addr:full":"2 Udall Ave Five Dock NSW 2046",
    "addr:housenumber":"2",
    "addr:postcode":"2046",
    "addr:street":"Udall Ave",
    "iso:country":"AU",
    "sg:address":"2 Udall Ave",
    "sg:city":"Five Dock",
    "sg:classifiers":[
        {
            "category":"Building & Trades",
            "subcategory":"Landscaping Services",
            "type":"Services"
        }
    ],
    "sg:phone":"+61 407 215 802",
    "sg:postcode":"2046",
    "sg:province":"NSW",
    "sg:tags":[
        "designer",
        "landscape",
        "contractor"
    ],
    "wof:name":"On Axis Design",
    "wof:placetype":"venue"
},
  "geometry": {"coordinates":[151.127396,-33.86409],"type":"Point"}
}