{
  "type": "Feature",
  "properties": {
    "iso:country":"AU",
    "sg:address":"58 Victoria St",
    "sg:city":"Taree",
    "sg:classifiers":[
        {
            "category":"Autos & Motor Vehicles",
            "subcategory":"Fuel & Gas Station",
            "type":"Retail Goods"
        }
    ],
    "sg:phone":"+61 2 6552 1581",
    "sg:postcode":"2430",
    "sg:province":"NSW",
    "wof:name":"Mobile Taree Fast Food",
    "wof:placetype":"venue"
},
  "geometry": {"coordinates":[152.466034,-31.910536],"type":"Point"}
}