{
  "type": "Feature",
  "properties": {
    "addr:full":"Shop 8 Kingsley Village Shopping Centre Kingsley WA 6026",
    "addr:housenumber":"shop 8",
    "addr:postcode":"6026",
    "addr:street":"Kingsley Village",
    "iso:country":"AU",
    "sg:address":"Shop 8 Kingsley Village Shopping Centre",
    "sg:city":"Kingsley",
    "sg:classifiers":[
        {
            "category":"Personal",
            "subcategory":"Beauty Salon",
            "type":"Services"
        }
    ],
    "sg:phone":"+61 8 9409 7448",
    "sg:postcode":"6026",
    "sg:province":"WA",
    "sg:tags":[
        "hairdresser"
    ],
    "wof:name":"Frank Basile For Hair",
    "wof:placetype":"venue"
},
  "geometry": {"coordinates":[115.78890991199999,-31.8000125885],"type":"Point"}
}