{
  "type": "Feature",
  "properties": {
    "iso:country":"AU",
    "sg:address":"223 Coopers Camp Rd",
    "sg:city":"Ashgrove",
    "sg:classifiers":[
        {
            "category":"Farming",
            "subcategory":"Nursery",
            "type":"Manufacturing & Wholesale Goods"
        }
    ],
    "sg:phone":"+61 7 3289 1529",
    "sg:postcode":"4060",
    "sg:province":"QLD",
    "wof:name":"Samford Wholesale Nursery",
    "wof:placetype":"venue"
},
  "geometry": {"coordinates":[152.97752380399999,-27.4495296478],"type":"Point"}
}