{
  "type": "Feature",
  "properties": {
    "addr:full":"193 Regent St Redfern NSW 2016",
    "addr:housenumber":"193",
    "addr:postcode":"2016",
    "addr:street":"Regent St",
    "iso:country":"AU",
    "sg:address":"193 Regent St",
    "sg:city":"Redfern",
    "sg:classifiers":[
        {
            "category":"Food & Beverages",
            "subcategory":"Fruits & Vegetables",
            "type":"Retail Goods"
        }
    ],
    "sg:phone":"+61 2 9318 2809",
    "sg:postcode":"2016",
    "sg:province":"NSW",
    "sg:tags":[
        "greengrocer",
        "fruiterer"
    ],
    "wof:name":"Redfern Fruit Market",
    "wof:placetype":"venue"
},
  "geometry": {"coordinates":[151.199462891,-33.8947639465],"type":"Point"}
}