{
  "type": "Feature",
  "properties": {
    "addr:full":"63 Assembly Drv Tullamarine VIC 3043",
    "addr:housenumber":"63",
    "addr:postcode":"3043",
    "addr:street":"Assembly Drv",
    "iso:country":"AU",
    "sg:address":"63 Assembly Drv",
    "sg:city":"Tullamarine",
    "sg:classifiers":[
        {
            "category":"Building & Trades",
            "subcategory":"Construction",
            "type":"Services"
        }
    ],
    "sg:phone":"+61 3 9335 3376",
    "sg:postcode":"3043",
    "sg:province":"VIC",
    "sg:tags":[
        "window",
        "timber"
    ],
    "wof:name":"Racecourse Windows",
    "wof:placetype":"venue"
},
  "geometry": {"coordinates":[144.865692139,-37.7077064514],"type":"Point"}
}