{
  "type": "Feature",
  "properties": {
    "addr:full":"Lvl 1/ 47 Murray St Pyrmont NSW 2009",
    "addr:housenumber":"/ 47",
    "addr:postcode":"2009",
    "addr:street":"Murray St",
    "iso:country":"AU",
    "sg:address":"Lvl 1/ 47 Murray St",
    "sg:city":"Pyrmont",
    "sg:classifiers":[
        {
            "category":"Banks & Credit Unions",
            "subcategory":"Bureau De Change",
            "type":"Services"
        }
    ],
    "sg:phone":"+61 2 9518 4600",
    "sg:postcode":"2009",
    "sg:province":"NSW",
    "sg:tags":[
        "publisher",
        "music"
    ],
    "wof:name":"Origin Music Publishing",
    "wof:placetype":"venue"
},
  "geometry": {"coordinates":[151.197540283,-33.8705215454],"type":"Point"}
}