{
  "type": "Feature",
  "properties": {
    "addr:full":"32 Maud St Albany Creek QLD 4035",
    "addr:housenumber":"32",
    "addr:postcode":"4035",
    "addr:street":"Maud St",
    "iso:country":"AU",
    "sg:address":"32 Maud St",
    "sg:city":"Albany Creek",
    "sg:classifiers":[
        {
            "category":"Building & Trades",
            "subcategory":"Pest Control",
            "type":"Services"
        }
    ],
    "sg:phone":"+61 432 633 863",
    "sg:postcode":"4035",
    "sg:province":"QLD",
    "wof:name":"Simply Pest Control",
    "wof:placetype":"venue"
},
  "geometry": {"coordinates":[152.976303,-27.341215],"type":"Point"}
}