{
  "type": "Feature",
  "properties": {
    "iso:country":"AU",
    "sg:address":"465 Scarborough Beach Rd",
    "sg:city":"Osborne Park",
    "sg:classifiers":[
        {
            "category":"Home & Garden",
            "subcategory":"Home Furnishings",
            "type":"Retail Goods"
        }
    ],
    "sg:phone":"+61 8 9244 4500",
    "sg:postcode":"6017",
    "sg:province":"WA",
    "sg:tags":[
        "storage",
        "rack",
        "wine"
    ],
    "wof:name":"Australasian Wine Exchange",
    "wof:placetype":"venue"
},
  "geometry": {"coordinates":[115.807662964,-31.9053764343],"type":"Point"}
}