{
  "type": "Feature",
  "properties": {
    "iso:country":"AU",
    "sg:address":"Friendship Ave",
    "sg:city":"Maroochydore",
    "sg:classifiers":[
        {
            "category":"Freight",
            "type":"Transportation"
        }
    ],
    "sg:phone":"+61 7 5450 7486",
    "sg:postcode":"4558",
    "sg:province":"QLD",
    "sg:tags":[
        "cargo",
        "air"
    ],
    "wof:name":"Virgin Blue Freight",
    "wof:placetype":"venue"
},
  "geometry": {"coordinates":[153.06553649899999,-26.6553192139],"type":"Point"}
}