{
  "type": "Feature",
  "properties": {
    "addr:full":"PO Box 1472 Warrnambool VIC 3280",
    "addr:postcode":"3280",
    "iso:country":"AU",
    "sg:address":"PO Box 1472",
    "sg:city":"Warrnambool",
    "sg:classifiers":[
        {
            "category":"Wholesale",
            "subcategory":"Painting Supplies",
            "type":"Manufacturing & Wholesale Goods"
        }
    ],
    "sg:phone":"+61 418 527 745",
    "sg:postcode":"3280",
    "sg:province":"VIC",
    "sg:tags":[
        "product",
        "cleaning"
    ],
    "wof:name":"The Soapbox",
    "wof:placetype":"venue"
},
  "geometry": {"coordinates":[142.48323059099999,-38.3842582703],"type":"Point"}
}