{
  "type": "Feature",
  "properties": {
    "iso:country":"AU",
    "sg:address":"Nerang Mall Gilston Rd & New Nerang St",
    "sg:city":"Southport",
    "sg:classifiers":[
        {
            "category":"Professional",
            "subcategory":"Accounting & Tax Preparation",
            "type":"Services"
        }
    ],
    "sg:phone":"+61 7 5532 5588",
    "sg:postcode":"4215",
    "sg:province":"QLD",
    "sg:tags":[
        "consultant",
        "taxation"
    ],
    "wof:name":"ITP The Income Tax Professionals",
    "wof:placetype":"venue"
},
  "geometry": {"coordinates":[153.415939331,-27.9664154053],"type":"Point"}
}