{
  "type": "Feature",
  "properties": {
    "iso:country":"AU",
    "sg:address":"1 Huett Pl",
    "sg:city":"Berowra",
    "sg:classifiers":[
        {
            "category":"Professional",
            "subcategory":"Accounting & Tax Preparation",
            "type":"Services"
        }
    ],
    "sg:phone":"+61 2 9456 4596",
    "sg:postcode":"2081",
    "sg:province":"NSW",
    "sg:tags":[
        "accountant",
        "auditor"
    ],
    "wof:name":"Fiedler Mervyn R G Dr",
    "wof:placetype":"venue"
},
  "geometry": {"coordinates":[151.15321350100001,-33.6168556213],"type":"Point"}
}