{
  "type": "Feature",
  "properties": {
    "iso:country":"AU",
    "sg:address":"Unit 5 / 12-14 Riverside Rd",
    "sg:city":"Chipping Norton",
    "sg:classifiers":[
        {
            "category":"Shopping",
            "type":"Retail Goods"
        }
    ],
    "sg:phone":"+61 2 9726 4055",
    "sg:postcode":"2170",
    "sg:province":"NSW",
    "sg:tags":[
        "equipment",
        "safety",
        "accessory"
    ],
    "wof:name":"Goodmaster Pty Ltd",
    "wof:placetype":"venue"
},
  "geometry": {"coordinates":[150.968475342,-33.9145545959],"type":"Point"}
}