{
  "type": "Feature",
  "properties": {
    "addr:full":"Aldinga Beach Rd Aldinga SA 5173",
    "addr:postcode":"5173",
    "addr:street":"Aldinga Beach Rd",
    "iso:country":"AU",
    "sg:address":"Aldinga Beach Rd",
    "sg:city":"Aldinga",
    "sg:classifiers":[
        {
            "category":"Education",
            "subcategory":"School",
            "type":"Public Place"
        }
    ],
    "sg:phone":"+61 8 8556 6118",
    "sg:postcode":"5173",
    "sg:province":"SA",
    "sg:tags":[
        "co-educational"
    ],
    "wof:name":"Southern Vales Christian College",
    "wof:placetype":"venue"
},
  "geometry": {"coordinates":[138.48110961899999,-35.2779541016],"type":"Point"}
}