{
  "type": "Feature",
  "properties": {
    "addr:full":"30 Frank St Wetherill Park NSW 2164",
    "addr:housenumber":"30",
    "addr:postcode":"2164",
    "addr:street":"Frank St",
    "iso:country":"AU",
    "sg:address":"30 Frank St",
    "sg:city":"Wetherill Park",
    "sg:classifiers":[
        {
            "category":"Freight",
            "type":"Transportation"
        }
    ],
    "sg:phone":"+61 2 9604 5159",
    "sg:postcode":"2164",
    "sg:province":"NSW",
    "sg:tags":[
        "transport",
        "refrigerated"
    ],
    "wof:name":"Nationwide Cold Storage & Distribution Services Pty Ltd",
    "wof:placetype":"venue"
},
  "geometry": {"coordinates":[150.90528869600001,-33.8411521912],"type":"Point"}
}