{
  "type": "Feature",
  "properties": {
    "addr:full":"6A Dunlop Ave Hoppers Crossing VIC 3029",
    "addr:housenumber":"6a",
    "addr:postcode":"3029",
    "addr:street":"Dunlop Ave",
    "iso:country":"AU",
    "sg:address":"6A Dunlop Ave",
    "sg:city":"Hoppers Crossing",
    "sg:classifiers":[
        {
            "category":"Farming",
            "subcategory":"Farm & Veterinary Services",
            "type":"Manufacturing & Wholesale Goods"
        }
    ],
    "sg:phone":"+61 3 9360 9128",
    "sg:postcode":"3029",
    "sg:province":"VIC",
    "sg:tags":[
        "poultry",
        "processing",
        "supply"
    ],
    "wof:name":"Southern Chicken Products",
    "wof:placetype":"venue"
},
  "geometry": {"coordinates":[144.72482299999999,-37.871044],"type":"Point"}
}