{
  "type": "Feature",
  "properties": {
    "addr:full":"19B Kourung St Ettalong Beach NSW 2257",
    "addr:housenumber":"19b",
    "addr:postcode":"2257",
    "addr:street":"Kourung St",
    "iso:country":"AU",
    "sg:address":"19B Kourung St",
    "sg:city":"Ettalong Beach",
    "sg:classifiers":[
        {
            "category":"Building & Trades",
            "subcategory":"Construction",
            "type":"Services"
        }
    ],
    "sg:phone":"+61 418 966 277",
    "sg:postcode":"2257",
    "sg:province":"NSW",
    "sg:tags":[
        "joiner",
        "carpenter"
    ],
    "wof:name":"Fernandes James",
    "wof:placetype":"venue"
},
  "geometry": {"coordinates":[151.328857422,-33.5204238892],"type":"Point"}
}