{
  "type": "Feature",
  "properties": {
    "addr:full":"35 Ryde St Epping NSW 2121",
    "addr:housenumber":"35",
    "addr:postcode":"2121",
    "addr:street":"Ryde St",
    "iso:country":"AU",
    "sg:address":"35 Ryde St",
    "sg:city":"Epping",
    "sg:classifiers":[
        {
            "category":"Communications",
            "subcategory":"Film & Video Production",
            "type":"Services"
        }
    ],
    "sg:phone":"+61 2 9876 8710",
    "sg:postcode":"2121",
    "sg:province":"NSW",
    "sg:tags":[
        "dvd",
        "library"
    ],
    "wof:name":"Global Entertainment Productions",
    "wof:placetype":"venue"
},
  "geometry": {"coordinates":[151.06825256400001,-33.7755508423],"type":"Point"}
}