{
  "type": "Feature",
  "properties": {
    "addr:full":"18 Hawthorn St Dubbo NSW 2830",
    "addr:housenumber":"18",
    "addr:postcode":"2830",
    "addr:street":"Hawthorn St",
    "iso:country":"AU",
    "sg:address":"18 Hawthorn St",
    "sg:city":"Dubbo",
    "sg:classifiers":[
        {
            "category":"Home & Garden",
            "subcategory":"Hardware",
            "type":"Retail Goods"
        }
    ],
    "sg:phone":"+61 2 6884 5210",
    "sg:postcode":"2830",
    "sg:province":"NSW",
    "sg:tags":[
        "generating",
        "set",
        "generator"
    ],
    "wof:name":"JDC-Thomson Electrical Systems Pty Ltd",
    "wof:placetype":"venue"
},
  "geometry": {"coordinates":[148.624710083,-32.258441925],"type":"Point"}
}