{
  "type": "Feature",
  "properties": {
    "iso:country":"AU",
    "sg:address":"5- 7 Racecourse Rd",
    "sg:city":"Beaufort",
    "sg:classifiers":[
        {
            "category":"Home & Garden",
            "subcategory":"Building Materials",
            "type":"Retail Goods"
        }
    ],
    "sg:phone":"+61 3 5349 2066",
    "sg:postcode":"3373",
    "sg:province":"VIC",
    "sg:tags":[
        "wall",
        "frame",
        "truss",
        "roof"
    ],
    "wof:name":"Epping Timber",
    "wof:placetype":"venue"
},
  "geometry": {"coordinates":[143.39044189399999,-37.4292411804],"type":"Point"}
}