{
  "type": "Feature",
  "properties": {
    "addr:full":"8 Herbert St Goondiwindi QLD 4390",
    "addr:housenumber":"8",
    "addr:postcode":"4390",
    "addr:street":"Herbert St",
    "iso:country":"AU",
    "sg:address":"8 Herbert St",
    "sg:city":"Goondiwindi",
    "sg:classifiers":[
        {
            "category":"Professional",
            "subcategory":"Computer Services",
            "type":"Services"
        }
    ],
    "sg:phone":"+61 7 4671 2343",
    "sg:postcode":"4390",
    "sg:province":"QLD",
    "sg:tags":[
        "package",
        "software"
    ],
    "wof:name":"Russell's Business Support Services",
    "wof:placetype":"venue"
},
  "geometry": {"coordinates":[150.30528259299999,-28.547044754],"type":"Point"}
}