{
  "type": "Feature",
  "properties": {
    "addr:full":"328a Clayton Rd Clayton VIC 3168",
    "addr:housenumber":"328a",
    "addr:postcode":"3168",
    "addr:street":"Clayton Rd",
    "iso:country":"AU",
    "sg:address":"328a Clayton Rd",
    "sg:city":"Clayton",
    "sg:classifiers":[
        {
            "category":"Health Services",
            "subcategory":"Optometrist",
            "type":"Services"
        }
    ],
    "sg:phone":"+61 3 9543 2688",
    "sg:postcode":"3168",
    "sg:province":"VIC",
    "wof:name":"Eye Look Visioncare",
    "wof:placetype":"venue"
},
  "geometry": {"coordinates":[145.11952209500001,-37.9269561768],"type":"Point"}
}