{
  "type": "Feature",
  "properties": {
    "addr:full":"25 Frangipani Crt Kallangur QLD 4503",
    "addr:housenumber":"25",
    "addr:postcode":"4503",
    "addr:street":"Frangipani Crt",
    "iso:country":"AU",
    "sg:address":"25 Frangipani Crt",
    "sg:city":"Kallangur",
    "sg:classifiers":[
        {
            "category":"Autos & Motor Vehicles",
            "subcategory":"Fuel & Gas Station",
            "type":"Retail Goods"
        }
    ],
    "sg:phone":"+61 7 3888 1441",
    "sg:postcode":"4503",
    "sg:province":"QLD",
    "wof:name":"Pine Rivers 24 Hour Towing",
    "wof:placetype":"venue"
},
  "geometry": {"coordinates":[153.00517273,-27.2402458191],"type":"Point"}
}