{
  "type": "Feature",
  "properties": {
    "addr:full":"PO Box 715 Modbury SA 5092",
    "addr:postcode":"5092",
    "iso:country":"AU",
    "sg:address":"PO Box 715",
    "sg:city":"Modbury",
    "sg:classifiers":[
        {
            "category":"Home & Garden",
            "subcategory":"Furniture",
            "type":"Retail Goods"
        }
    ],
    "sg:phone":"+61 8 8283 3611",
    "sg:postcode":"5092",
    "sg:province":"SA",
    "sg:tags":[
        "outdoor"
    ],
    "wof:name":"Forpark Australia (SA & NT)",
    "wof:placetype":"venue"
},
  "geometry": {"coordinates":[138.69236755399999,-34.8331794739],"type":"Point"}
}