{
  "type": "Feature",
  "properties": {
    "addr:full":"Cnr Ann & Wharf St Brisbane QLD 4000",
    "addr:postcode":"4000",
    "addr:street":"Cnr;St",
    "iso:country":"AU",
    "sg:address":"Cnr Ann & Wharf St",
    "sg:city":"Brisbane",
    "sg:classifiers":[
        {
            "category":"Travel",
            "subcategory":"Hotels & Motels",
            "type":"Entertainment"
        }
    ],
    "sg:phone":"+61 7 3222 4999",
    "sg:postcode":"4000",
    "sg:province":"QLD",
    "sg:tags":[
        "accommodation"
    ],
    "wof:name":"Lexicon Apartments",
    "wof:placetype":"venue"
},
  "geometry": {"coordinates":[153.027099609,-27.4624042511],"type":"Point"}
}