{
  "type": "Feature",
  "properties": {
    "addr:full":"1st Floor 383 Anzac Pde Kingsford NSW 2032",
    "addr:housenumber":"383",
    "addr:postcode":"2032",
    "addr:street":"Anzac Pde",
    "iso:country":"AU",
    "sg:address":"1st Floor 383 Anzac Pde",
    "sg:city":"Kingsford",
    "sg:classifiers":[
        {
            "category":"Health Services",
            "subcategory":"Doctor",
            "type":"Services"
        }
    ],
    "sg:phone":"+61 2 9313 6188",
    "sg:postcode":"2032",
    "sg:province":"NSW",
    "sg:tags":[
        "medical",
        "practitioner"
    ],
    "wof:name":"Dassos C P",
    "wof:placetype":"venue"
},
  "geometry": {"coordinates":[151.22789001500001,-33.9245071411],"type":"Point"}
}