{
  "type": "Feature",
  "properties": {
    "addr:full":"67 Kelvin Ave Montmorency VIC 3094",
    "addr:housenumber":"67",
    "addr:postcode":"3094",
    "addr:street":"Kelvin Ave",
    "iso:country":"AU",
    "sg:address":"67 Kelvin Ave",
    "sg:city":"Montmorency",
    "sg:classifiers":[
        {
            "category":"Manufacturing",
            "subcategory":"Glass & Minerals",
            "type":"Manufacturing & Wholesale Goods"
        }
    ],
    "sg:phone":"+61 3 9434 1761",
    "sg:postcode":"3094",
    "sg:province":"VIC",
    "sg:tags":[
        "etching"
    ],
    "wof:name":"Glass Art Australia",
    "wof:placetype":"venue"
},
  "geometry": {"coordinates":[145.121368408,-37.7147750854],"type":"Point"}
}