{
  "type": "Feature",
  "properties": {
    "iso:country":"AU",
    "sg:address":"9 Enterprise Drv",
    "sg:city":"Tomago",
    "sg:classifiers":[
        {
            "category":"Wholesale",
            "subcategory":"Machinery & Supplies",
            "type":"Manufacturing & Wholesale Goods"
        }
    ],
    "sg:phone":"+61 2 4962 1500",
    "sg:postcode":"2322",
    "sg:province":"NSW",
    "sg:tags":[
        "distributor",
        "crane",
        "mfrs"
    ],
    "wof:name":"Safe Cranes",
    "wof:placetype":"venue"
},
  "geometry": {"coordinates":[151.74110412600001,-32.8227157593],"type":"Point"}
}