{
  "type": "Feature",
  "properties": {
    "iso:country":"AU",
    "sg:address":"532 Tara Ave",
    "sg:city":"Albury",
    "sg:classifiers":[
        {
            "category":"Professional",
            "subcategory":"Art Services",
            "type":"Services"
        }
    ],
    "sg:phone":"+61 2 6021 6869",
    "sg:postcode":"2640",
    "sg:province":"NSW",
    "sg:tags":[
        "decorator",
        "painter"
    ],
    "wof:name":"Mark Lowe's Painting Service Pty Ltd",
    "wof:placetype":"venue"
},
  "geometry": {"coordinates":[146.931365967,-36.0809211731],"type":"Point"}
}