{
  "type": "Feature",
  "properties": {
    "addr:full":"102 Huntley Grange Rd Springwood NSW 2777",
    "addr:housenumber":"102",
    "addr:postcode":"2777",
    "addr:street":"Huntley Grange Rd",
    "iso:country":"AU",
    "sg:address":"102 Huntley Grange Rd",
    "sg:city":"Springwood",
    "sg:classifiers":[
        {
            "category":"Education",
            "subcategory":"University",
            "type":"Public Place"
        }
    ],
    "sg:phone":"+61 2 4751 6608",
    "sg:postcode":"2777",
    "sg:province":"NSW",
    "sg:tags":[
        "educational",
        "organisation",
        "cultural"
    ],
    "wof:name":"E.F. Foundation For Foreign Study",
    "wof:placetype":"venue"
},
  "geometry": {"coordinates":[150.57232665999999,-33.6907806396],"type":"Point"}
}