{
  "type": "Feature",
  "properties": {
    "addr:full":"8 Curtin Ave Glenroy VIC 3046",
    "addr:housenumber":"8",
    "addr:postcode":"3046",
    "addr:street":"Curtin Ave",
    "iso:country":"AU",
    "sg:address":"8 Curtin Ave",
    "sg:city":"Glenroy",
    "sg:classifiers":[
        {
            "category":"Utilities",
            "subcategory":"Telephone",
            "type":"Services"
        }
    ],
    "sg:phone":"+61 3 9359 5477",
    "sg:postcode":"3046",
    "sg:province":"VIC",
    "sg:tags":[
        "equipment",
        "system"
    ],
    "wof:name":"Phoneright",
    "wof:placetype":"venue"
},
  "geometry": {"coordinates":[144.94712829599999,-37.7092170715],"type":"Point"}
}