{
  "type": "Feature",
  "properties": {
    "addr:full":"11 Kirkwood Ave Epping NSW 2121",
    "addr:housenumber":"11",
    "addr:postcode":"2121",
    "addr:street":"Kirkwood Ave",
    "iso:country":"AU",
    "sg:address":"11 Kirkwood Ave",
    "sg:city":"Epping",
    "sg:classifiers":[
        {
            "category":"Health Services",
            "subcategory":"Doctor",
            "type":"Services"
        }
    ],
    "sg:phone":"+61 2 9876 8079",
    "sg:postcode":"2121",
    "sg:province":"NSW",
    "sg:tags":[
        "reflexology"
    ],
    "wof:name":"Mason Kevin",
    "wof:placetype":"venue"
},
  "geometry": {"coordinates":[151.08598327600001,-33.761390686],"type":"Point"}
}