{
  "type": "Feature",
  "properties": {
    "addr:full":"Level 1 Suite 4 427 Blackburn Rd Mt Waverley VIC 3149",
    "addr:housenumber":"427",
    "addr:postcode":"3149",
    "addr:street":"Blackburn Rd",
    "iso:country":"AU",
    "sg:address":"Level 1 Suite 4 427 Blackburn Rd",
    "sg:city":"Mt Waverley",
    "sg:classifiers":[
        {
            "category":"Professional",
            "subcategory":"Accounting & Tax Preparation",
            "type":"Services"
        }
    ],
    "sg:phone":"+61 3 9886 3600",
    "sg:postcode":"3149",
    "sg:province":"VIC",
    "sg:tags":[
        "accountant",
        "auditor"
    ],
    "wof:name":"Lawsons Chartered Accountants",
    "wof:placetype":"venue"
},
  "geometry": {"coordinates":[145.14474487300001,-37.8906326294],"type":"Point"}
}