{
  "type": "Feature",
  "properties": {
    "addr:full":"102 Linsley St Cobar NSW 2835",
    "addr:housenumber":"102",
    "addr:postcode":"2835",
    "addr:street":"Linsley St",
    "iso:country":"AU",
    "sg:address":"102 Linsley St",
    "sg:city":"Cobar",
    "sg:classifiers":[
        {
            "category":"Building & Trades",
            "subcategory":"Plumbing",
            "type":"Services"
        }
    ],
    "sg:phone":"+61 419 601 532",
    "sg:postcode":"2835",
    "sg:province":"NSW",
    "sg:tags":[
        "plumber",
        "gasfitters"
    ],
    "wof:name":"Cahill W A",
    "wof:placetype":"venue"
},
  "geometry": {"coordinates":[145.83836400000001,-31.499943],"type":"Point"}
}