{
  "type": "Feature",
  "properties": {
    "addr:full":"Lot3, 1397 Wanneroo Rd Wanneroo WA 6065",
    "addr:postcode":"1397;6065",
    "addr:street":"Lot3;Wanneroo Rd",
    "iso:country":"AU",
    "sg:address":"Lot3, 1397 Wanneroo Rd",
    "sg:city":"Wanneroo",
    "sg:classifiers":[
        {
            "category":"Food & Beverages",
            "subcategory":"Fruits & Vegetables",
            "type":"Retail Goods"
        }
    ],
    "sg:phone":"+61 8 9206 2999",
    "sg:postcode":"6065",
    "sg:province":"WA",
    "sg:tags":[
        "greengrocer",
        "fruiterer"
    ],
    "wof:name":"Garden Glow Fruit & Vegetable Wholesalers",
    "wof:placetype":"venue"
},
  "geometry": {"coordinates":[115.78160095200001,-31.7177562714],"type":"Point"}
}