{
  "type": "Feature",
  "properties": {
    "iso:country":"AU",
    "sg:address":"Templeton Reserve Templeton St",
    "sg:city":"Wantirna",
    "sg:classifiers":[
        {
            "category":"Education",
            "subcategory":"Kindergarten",
            "type":"Public Place"
        }
    ],
    "sg:phone":"+61 3 9800 1328",
    "sg:postcode":"3152",
    "sg:province":"VIC",
    "sg:tags":[
        "pre-schools"
    ],
    "wof:name":"Templeton Orchards Pre-School",
    "wof:placetype":"venue"
},
  "geometry": {"coordinates":[145.22850036599999,-37.8577651978],"type":"Point"}
}