{
  "type": "Feature",
  "properties": {
    "iso:country":"AU",
    "sg:address":"54 Puckle St",
    "sg:city":"Moonee Ponds",
    "sg:classifiers":[
        {
            "category":"Food & Beverages",
            "subcategory":"Bakery",
            "type":"Retail Goods"
        }
    ],
    "sg:phone":"+61 3 9370 6574",
    "sg:postcode":"3039",
    "sg:province":"VIC",
    "sg:tags":[
        "cake",
        "shop",
        "pastry"
    ],
    "wof:name":"Ferguson Plarre Bakehouses Pty Ltd",
    "wof:placetype":"venue"
},
  "geometry": {"coordinates":[144.92263800000001,-37.766727],"type":"Point"}
}