{
  "type": "Feature",
  "properties": {
    "iso:country":"AU",
    "sg:address":"130 Eighteenth St",
    "sg:city":"Renmark",
    "sg:classifiers":[
        {
            "category":"Autos & Motor Vehicles",
            "subcategory":"Auto Supplies",
            "type":"Retail Goods"
        }
    ],
    "sg:phone":"+61 8 8586 6142",
    "sg:postcode":"5341",
    "sg:province":"SA",
    "sg:tags":[
        "wheel",
        "automotive",
        "rim"
    ],
    "wof:name":"Tyrepower",
    "wof:placetype":"venue"
},
  "geometry": {"coordinates":[140.74647522000001,-34.1760292053],"type":"Point"}
}