{
  "type": "Feature",
  "properties": {
    "iso:country":"AU",
    "sg:address":"Craig Drv",
    "sg:city":"Bellbridge",
    "sg:classifiers":[
        {
            "category":"Social Services",
            "subcategory":"Child Care",
            "type":"Services"
        }
    ],
    "sg:phone":"+61 2 6026 4228",
    "sg:postcode":"3691",
    "sg:province":"VIC",
    "sg:tags":[
        "support",
        "health"
    ],
    "wof:name":"Maternal & Child Health Centres",
    "wof:placetype":"venue"
},
  "geometry": {"coordinates":[147.06352200000001,-36.098541],"type":"Point"}
}