{
  "type": "Feature",
  "properties": {
    "addr:full":"21 Burunda Rd Rosebud VIC 3939",
    "addr:housenumber":"21",
    "addr:postcode":"3939",
    "addr:street":"Burunda Rd",
    "iso:country":"AU",
    "sg:address":"21 Burunda Rd",
    "sg:city":"Rosebud",
    "sg:classifiers":[
        {
            "category":"Professional",
            "subcategory":"Art Services",
            "type":"Services"
        }
    ],
    "sg:phone":"+61 3 5982 0859",
    "sg:postcode":"3939",
    "sg:province":"VIC",
    "sg:tags":[
        "decorator",
        "painter"
    ],
    "wof:name":"Natural Painting Solutions",
    "wof:placetype":"venue"
},
  "geometry": {"coordinates":[144.92219543499999,-38.3670043945],"type":"Point"}
}