{
  "type": "Feature",
  "properties": {
    "addr:full":"28 Bridge St Brighton VIC 3186",
    "addr:housenumber":"28",
    "addr:postcode":"3186",
    "addr:street":"Bridge St",
    "iso:country":"AU",
    "sg:address":"28 Bridge St",
    "sg:city":"Brighton",
    "sg:classifiers":[
        {
            "category":"Professional",
            "subcategory":"Business Services",
            "type":"Services"
        }
    ],
    "sg:phone":"+61 3 9523 0906",
    "sg:postcode":"3186",
    "sg:province":"VIC",
    "sg:tags":[
        "consultant",
        "system"
    ],
    "wof:name":"MyMate Business & Technical Support",
    "wof:placetype":"venue"
},
  "geometry": {"coordinates":[145.00210571299999,-37.8929862976],"type":"Point"}
}