{
  "type": "Feature",
  "properties": {
    "iso:country":"AU",
    "sg:address":"122 Collins Ave",
    "sg:city":"Edge Hill",
    "sg:classifiers":[
        {
            "category":"Food & Beverages",
            "subcategory":"Specialty",
            "type":"Retail Goods"
        }
    ],
    "sg:phone":"+61 7 4053 7797",
    "sg:postcode":"4870",
    "sg:province":"QLD",
    "sg:tags":[
        "delicacy"
    ],
    "wof:name":"Oriental Gourmet Store",
    "wof:placetype":"venue"
},
  "geometry": {"coordinates":[145.74230957,-16.9008712769],"type":"Point"}
}