{
  "type": "Feature",
  "properties": {
    "addr:full":"&#039;Lumeah&#039; Coltrons Rd Minhamite VIC 3287",
    "addr:postcode":"3287",
    "addr:street":"Coltrons Rd",
    "iso:country":"AU",
    "sg:address":"&#039;Lumeah&#039; Coltrons Rd",
    "sg:city":"Minhamite",
    "sg:classifiers":[
        {
            "category":"Building & Trades",
            "subcategory":"Landscaping Services",
            "type":"Services"
        }
    ],
    "sg:phone":"+61 3 5576 6219",
    "sg:postcode":"3287",
    "sg:province":"VIC",
    "sg:tags":[
        "grazier"
    ],
    "wof:name":"Hausler Colin",
    "wof:placetype":"venue"
},
  "geometry": {"coordinates":[142.34852600100001,-38.0204429626],"type":"Point"}
}