{
  "type": "Feature",
  "properties": {
    "addr:full":"194 Star St Carlisle WA 6101",
    "addr:housenumber":"194",
    "addr:postcode":"6101",
    "addr:street":"Star St",
    "iso:country":"AU",
    "sg:address":"194 Star St",
    "sg:city":"Carlisle",
    "sg:classifiers":[
        {
            "category":"Professional",
            "subcategory":"Engineering",
            "type":"Services"
        }
    ],
    "sg:phone":"+61 8 9361 3449",
    "sg:postcode":"6101",
    "sg:province":"WA",
    "sg:tags":[
        "engineer"
    ],
    "wof:name":"Kerr Engineering (WA) Pty Ltd",
    "wof:placetype":"venue"
},
  "geometry": {"coordinates":[115.921691895,-31.9807662964],"type":"Point"}
}