{
  "type": "Feature",
  "properties": {
    "addr:full":"28 Partridge Crs Frankston VIC 3199",
    "addr:housenumber":"28",
    "addr:postcode":"3199",
    "addr:street":"Partridge Crs",
    "iso:country":"AU",
    "sg:address":"28 Partridge Crs",
    "sg:city":"Frankston",
    "sg:classifiers":[
        {
            "category":"Wholesale",
            "subcategory":"Furniture",
            "type":"Manufacturing & Wholesale Goods"
        }
    ],
    "sg:phone":"+61 3 9770 9011",
    "sg:postcode":"3199",
    "sg:province":"VIC",
    "sg:tags":[
        "wholesaler",
        "mfrs"
    ],
    "wof:name":"Advanced Interiors (Vic) P/L",
    "wof:placetype":"venue"
},
  "geometry": {"coordinates":[145.021194458,-37.6629981995],"type":"Point"}
}