{
  "type": "Feature",
  "properties": {
    "iso:country":"AU",
    "sg:address":"16 Bayview Country La",
    "sg:city":"Bittern",
    "sg:classifiers":[
        {
            "category":"Professional",
            "subcategory":"Accounting & Tax Preparation",
            "type":"Services"
        }
    ],
    "sg:phone":"+61 3 5979 3100",
    "sg:postcode":"3918",
    "sg:province":"VIC",
    "sg:tags":[
        "accountant",
        "auditor"
    ],
    "wof:name":"Skylark Accounting",
    "wof:placetype":"venue"
},
  "geometry": {"coordinates":[145.177246094,-38.3298606873],"type":"Point"}
}