{
  "type": "Feature",
  "properties": {
    "iso:country":"AU",
    "sg:address":"245 Balmain Rd",
    "sg:city":"Leichhardt",
    "sg:classifiers":[
        {
            "category":"Food & Beverages",
            "subcategory":"Bakery",
            "type":"Retail Goods"
        }
    ],
    "sg:phone":"+61 2 9569 7091",
    "sg:postcode":"2040",
    "sg:province":"NSW",
    "sg:tags":[
        "baker"
    ],
    "wof:name":"Continental Bakery Pty Ltd",
    "wof:placetype":"venue"
},
  "geometry": {"coordinates":[151.160721,-33.876423],"type":"Point"}
}