{
  "type": "Feature",
  "properties": {
    "iso:country":"AU",
    "sg:address":"7 Corniche Rd",
    "sg:city":"Church Point",
    "sg:classifiers":[
        {
            "category":"Home & Garden",
            "subcategory":"Garden Supply",
            "type":"Retail Goods"
        }
    ],
    "sg:phone":"+61 412 130 792",
    "sg:postcode":"2105",
    "sg:province":"NSW",
    "sg:tags":[
        "equipment"
    ],
    "wof:name":"Sleepy Hollows Nesting Boxes",
    "wof:placetype":"venue"
},
  "geometry": {"coordinates":[151.287048,-33.653713],"type":"Point"}
}