{
  "type": "Feature",
  "properties": {
    "addr:full":"8 McElroy St Casino NSW 2470",
    "addr:housenumber":"8",
    "addr:postcode":"2470",
    "addr:street":"Mcelroy St",
    "iso:country":"AU",
    "sg:address":"8 McElroy St",
    "sg:city":"Casino",
    "sg:classifiers":[
        {
            "category":"Building & Trades",
            "subcategory":"Construction",
            "type":"Services"
        }
    ],
    "sg:phone":"+61 417 603 337",
    "sg:postcode":"2470",
    "sg:province":"NSW",
    "sg:tags":[
        "earth",
        "excavating",
        "moving",
        "contractor"
    ],
    "wof:name":"Casino Backhoe Hire",
    "wof:placetype":"venue"
},
  "geometry": {"coordinates":[153.04159545900001,-28.8760814667],"type":"Point"}
}