{
  "type": "Feature",
  "properties": {
    "addr:full":"Unit 1 247 Pitt St Waterloo NSW 2017",
    "addr:housenumber":"247",
    "addr:postcode":"2017",
    "addr:street":"Pitt St",
    "iso:country":"AU",
    "sg:address":"Unit 1 247 Pitt St",
    "sg:city":"Waterloo",
    "sg:classifiers":[
        {
            "category":"Professional",
            "subcategory":"Computer Services",
            "type":"Services"
        }
    ],
    "sg:phone":"+61 2 9319 1902",
    "sg:postcode":"2017",
    "sg:province":"NSW",
    "sg:tags":[
        "information"
    ],
    "wof:name":"A & M Nationwide Pty Ltd",
    "wof:placetype":"venue"
},
  "geometry": {"coordinates":[151.20466613799999,-33.9016723633],"type":"Point"}
}