{
  "type": "Feature",
  "properties": {
    "iso:country":"AU",
    "sg:address":"36 Queen St",
    "sg:city":"Burnie",
    "sg:classifiers":[
        {
            "category":"Retail",
            "subcategory":"Event Space",
            "type":"Services"
        }
    ],
    "sg:phone":"+61 3 6431 1088",
    "sg:postcode":"7320",
    "sg:province":"TAS",
    "sg:tags":[
        "venue",
        "reception",
        "wedding"
    ],
    "wof:name":"Weller's Inn",
    "wof:placetype":"venue"
},
  "geometry": {"coordinates":[145.901154,-41.050686],"type":"Point"}
}