{
  "type": "Feature",
  "properties": {
    "addr:full":"6603 Mt Lindesay Hwy Gleneagle QLD 4285",
    "addr:housenumber":"6603",
    "addr:postcode":"4285",
    "addr:street":"Mt Lindesay Hwy",
    "iso:country":"AU",
    "sg:address":"6603 Mt Lindesay Hwy",
    "sg:city":"Gleneagle",
    "sg:classifiers":[
        {
            "category":"Home & Garden",
            "subcategory":"Garden Supply",
            "type":"Retail Goods"
        }
    ],
    "sg:phone":"+61 7 5543 1125",
    "sg:postcode":"4285",
    "sg:province":"QLD",
    "sg:tags":[
        "landscape"
    ],
    "wof:name":"Ironbark Gardens",
    "wof:placetype":"venue"
},
  "geometry": {"coordinates":[152.98376500000001,-27.944155],"type":"Point"}
}