{
  "type": "Feature",
  "properties": {
    "iso:country":"AU",
    "sg:address":"117 The Entrance Rd",
    "sg:city":"The Entrance",
    "sg:classifiers":[
        {
            "category":"Recreation",
            "subcategory":"Fishing",
            "type":"Entertainment"
        }
    ],
    "sg:phone":"+61 2 4334 3219",
    "sg:postcode":"2261",
    "sg:province":"NSW",
    "sg:tags":[
        "bait"
    ],
    "wof:name":"Baits R Us",
    "wof:placetype":"venue"
},
  "geometry": {"coordinates":[151.49469,-33.34584],"type":"Point"}
}