{
  "type": "Feature",
  "properties": {
    "iso:country":"AU",
    "sg:address":"South West Region - Suite 2/ 50 Middle St",
    "sg:city":"Chinchilla",
    "sg:classifiers":[
        {
            "category":"Building & Trades",
            "subcategory":"Landscaping Services",
            "type":"Services"
        }
    ],
    "sg:phone":"+61 7 4669 1166",
    "sg:postcode":"4413",
    "sg:province":"QLD",
    "sg:tags":[
        "consultant"
    ],
    "wof:name":"Geoff Mitchell & Associates",
    "wof:placetype":"venue"
},
  "geometry": {"coordinates":[150.627029419,-26.7432079315],"type":"Point"}
}