{
  "type": "Feature",
  "properties": {
    "addr:full":"Shp4/ 4 Partridge St Glenelg SA 5045",
    "addr:housenumber":"4",
    "addr:postcode":"5045",
    "addr:street":"Partridge St",
    "iso:country":"AU",
    "sg:address":"Shp4/ 4 Partridge St",
    "sg:city":"Glenelg",
    "sg:classifiers":[
        {
            "category":"Shopping",
            "subcategory":"Clothing, Apparel, & Fashions",
            "type":"Retail Goods"
        }
    ],
    "sg:phone":"+61 8 8294 3121",
    "sg:postcode":"5045",
    "sg:province":"SA",
    "sg:tags":[
        "recycled",
        "clothing"
    ],
    "wof:name":"Nadia's House Of Serendipity",
    "wof:placetype":"venue"
},
  "geometry": {"coordinates":[138.51795999999999,-34.980724],"type":"Point"}
}