{
  "type": "Feature",
  "properties": {
    "addr:full":"178 Clarinda St Parkes NSW 2870",
    "addr:housenumber":"178",
    "addr:postcode":"2870",
    "addr:street":"Clarinda St",
    "iso:country":"AU",
    "sg:address":"178 Clarinda St",
    "sg:city":"Parkes",
    "sg:classifiers":[
        {
            "category":"Fast Food",
            "type":"Food & Drink"
        }
    ],
    "sg:phone":"+61 2 6862 2586",
    "sg:postcode":"2870",
    "sg:province":"NSW",
    "sg:tags":[
        "away",
        "take"
    ],
    "wof:name":"Chong Hing Restaurant",
    "wof:placetype":"venue"
},
  "geometry": {"coordinates":[148.175186,-33.139229],"type":"Point"}
}