{
  "type": "Feature",
  "properties": {
    "addr:full":"122 Fairbank Rd Clayton VIC 3168",
    "addr:housenumber":"122",
    "addr:postcode":"3168",
    "addr:street":"Fairbank Rd",
    "iso:country":"AU",
    "sg:address":"122 Fairbank Rd",
    "sg:city":"Clayton",
    "sg:classifiers":[
        {
            "category":"Professional",
            "type":"Services"
        }
    ],
    "sg:phone":"+61 3 9558 0033",
    "sg:postcode":"3168",
    "sg:province":"VIC",
    "sg:tags":[
        "courier"
    ],
    "wof:name":"Allied Express",
    "wof:placetype":"venue"
},
  "geometry": {"coordinates":[145.124755859,-37.899181366],"type":"Point"}
}