{
  "type": "Feature",
  "properties": {
    "addr:full":"9 Gardiner Ave Coffs Harbour NSW 2450",
    "addr:housenumber":"9",
    "addr:postcode":"2450",
    "addr:street":"Gardiner Ave",
    "iso:country":"AU",
    "sg:address":"9 Gardiner Ave",
    "sg:city":"Coffs Harbour",
    "sg:classifiers":[
        {
            "category":"Education",
            "subcategory":"Kindergarten",
            "type":"Public Place"
        }
    ],
    "sg:phone":"+61 2 6652 2121",
    "sg:postcode":"2450",
    "sg:province":"NSW",
    "sg:tags":[
        "pre-schools"
    ],
    "wof:name":"Gardiner Avenue Childrens Centre",
    "wof:placetype":"venue"
},
  "geometry": {"coordinates":[153.108994,-30.300797],"type":"Point"}
}