{
  "type": "Feature",
  "properties": {
    "addr:full":"61 Lucas St North Rockhampton QLD 4701",
    "addr:housenumber":"61",
    "addr:postcode":"4701",
    "addr:street":"Lucas St North",
    "iso:country":"AU",
    "sg:address":"61 Lucas St",
    "sg:city":"North Rockhampton",
    "sg:classifiers":[
        {
            "category":"Retail",
            "subcategory":"Auto Repair",
            "type":"Services"
        }
    ],
    "sg:phone":"+61 7 4922 2945",
    "sg:postcode":"4701",
    "sg:province":"QLD",
    "sg:tags":[
        "repairer",
        "motor",
        "engineer"
    ],
    "wof:name":"Brad's Service Centre",
    "wof:placetype":"venue"
},
  "geometry": {"coordinates":[150.52333068900001,-23.3646678925],"type":"Point"}
}