{
  "type": "Feature",
  "properties": {
    "addr:full":"59 Smith St Warragul VIC 3820",
    "addr:housenumber":"59",
    "addr:postcode":"3820",
    "addr:street":"Smith St",
    "iso:country":"AU",
    "sg:address":"59 Smith St",
    "sg:city":"Warragul",
    "sg:classifiers":[
        {
            "category":"Social Services",
            "subcategory":"Child Care",
            "type":"Services"
        }
    ],
    "sg:phone":"+61 3 5624 2450",
    "sg:postcode":"3820",
    "sg:province":"VIC",
    "sg:tags":[
        "support",
        "health"
    ],
    "wof:name":"Maternal & Child Health Centres",
    "wof:placetype":"venue"
},
  "geometry": {"coordinates":[145.93225100000001,-38.159866],"type":"Point"}
}