{
  "type": "Feature",
  "properties": {
    "addr:full":"61 Byrnes St Mareeba QLD 4880",
    "addr:housenumber":"61",
    "addr:postcode":"4880",
    "addr:street":"Byrnes St",
    "iso:country":"AU",
    "sg:address":"61 Byrnes St",
    "sg:city":"Mareeba",
    "sg:classifiers":[
        {
            "category":"Autos & Motor Vehicles",
            "subcategory":"Fuel & Gas Station",
            "type":"Retail Goods"
        }
    ],
    "sg:phone":"+61 7 4092 1142",
    "sg:postcode":"4880",
    "sg:province":"QLD",
    "wof:name":"Shell Mareeba S/S",
    "wof:placetype":"venue"
},
  "geometry": {"coordinates":[145.42228698700001,-16.9932765961],"type":"Point"}
}