{
  "type": "Feature",
  "properties": {
    "iso:country":"AU",
    "sg:address":"44 Napoleon St",
    "sg:city":"Cottesloe",
    "sg:classifiers":[
        {
            "category":"Food & Beverages",
            "subcategory":"Bakery",
            "type":"Retail Goods"
        }
    ],
    "sg:phone":"+61 8 9384 8628",
    "sg:postcode":"6011",
    "sg:province":"WA",
    "sg:tags":[
        "cake",
        "shop",
        "pastry"
    ],
    "wof:name":"Maid Marions Patisserie & Hot Bread",
    "wof:placetype":"venue"
},
  "geometry": {"coordinates":[115.762733459,-31.9977741241],"type":"Point"}
}