{
  "type": "Feature",
  "properties": {
    "addr:full":"218a Skipton St Ballarat VIC 3350",
    "addr:housenumber":"218a",
    "addr:postcode":"3350",
    "addr:street":"Skipton St",
    "iso:country":"AU",
    "sg:address":"218a Skipton St",
    "sg:city":"Ballarat",
    "sg:classifiers":[
        {
            "category":"Building & Trades",
            "subcategory":"Locksmith",
            "type":"Services"
        }
    ],
    "sg:phone":"+61 408 331 848",
    "sg:postcode":"3350",
    "sg:province":"VIC",
    "sg:tags":[
        "lock"
    ],
    "wof:name":"Ocean Grove South Coast Locksmiths",
    "wof:placetype":"venue"
},
  "geometry": {"coordinates":[143.85115099999999,-37.569508],"type":"Point"}
}