{
  "type": "Feature",
  "properties": {
    "addr:full":"17 Foucart St Rozelle NSW 2039",
    "addr:housenumber":"17",
    "addr:postcode":"2039",
    "addr:street":"Foucart St",
    "iso:country":"AU",
    "sg:address":"17 Foucart St",
    "sg:city":"Rozelle",
    "sg:classifiers":[
        {
            "category":"Arena",
            "subcategory":"Bull Ring",
            "type":"Entertainment"
        }
    ],
    "sg:phone":"+61 2 9810 5604",
    "sg:postcode":"2039",
    "sg:province":"NSW",
    "sg:tags":[
        "club",
        "bushwalking"
    ],
    "wof:name":"W.E.A Ramblers & Naturalists Club",
    "wof:placetype":"venue"
},
  "geometry": {"coordinates":[151.168243408,-33.8692054749],"type":"Point"}
}