{
  "type": "Feature",
  "properties": {
    "addr:full":"9 Humffray St North Ballarat VIC 3350",
    "addr:housenumber":"9",
    "addr:postcode":"3350",
    "addr:street":"Humffray St North",
    "iso:country":"AU",
    "sg:address":"9 Humffray St",
    "sg:city":"North Ballarat",
    "sg:classifiers":[
        {
            "category":"Shopping",
            "subcategory":"Antiques",
            "type":"Retail Goods"
        }
    ],
    "sg:phone":"+61 3 5331 7996",
    "sg:postcode":"3350",
    "sg:province":"VIC",
    "wof:name":"Antiques & Collectables Centre",
    "wof:placetype":"venue"
},
  "geometry": {"coordinates":[143.86700400000001,-37.559891],"type":"Point"}
}