{
  "type": "Feature",
  "properties": {
    "addr:full":"35 Crimea St St Kilda VIC 3182",
    "addr:housenumber":"35",
    "addr:postcode":"3182",
    "addr:street":"Crimea St",
    "iso:country":"AU",
    "sg:address":"35 Crimea St",
    "sg:city":"St Kilda",
    "sg:classifiers":[
        {
            "category":"Education",
            "subcategory":"Kindergarten",
            "type":"Public Place"
        }
    ],
    "sg:phone":"+61 3 9510 3833",
    "sg:postcode":"3182",
    "sg:province":"VIC",
    "sg:tags":[
        "pre-schools"
    ],
    "wof:name":"Kinderclub Child Care Centre",
    "wof:placetype":"venue"
},
  "geometry": {"coordinates":[144.987716675,-37.8602027893],"type":"Point"}
}