{
  "type": "Feature",
  "properties": {
    "iso:country":"AU",
    "sg:address":"94-96 Morgan St",
    "sg:city":"Wagga Wagga",
    "sg:classifiers":[
        {
            "category":"Insurance",
            "subcategory":"Life Insurance",
            "type":"Services"
        }
    ],
    "sg:phone":"+61 2 6921 5566",
    "sg:postcode":"2650",
    "sg:province":"NSW",
    "wof:name":"Bernard Benson Financial Services",
    "wof:placetype":"venue"
},
  "geometry": {"coordinates":[147.36796569800001,-35.1159744263],"type":"Point"}
}