{
  "type": "Feature",
  "properties": {
    "iso:country":"AU",
    "sg:address":"2- 17 Grayling St",
    "sg:city":"Belmont",
    "sg:classifiers":[
        {
            "category":"Commercial Area",
            "type":"Public Place"
        }
    ],
    "sg:phone":"+61 3 5243 6040",
    "sg:postcode":"3216",
    "sg:province":"VIC",
    "sg:tags":[
        "heavy",
        "carrier"
    ],
    "wof:name":"Western Plains Transport",
    "wof:placetype":"venue"
},
  "geometry": {"coordinates":[144.351837158,-38.1836204529],"type":"Point"}
}