{
  "type": "Feature",
  "properties": {
    "iso:country":"AU",
    "sg:address":"15 Hamilton Rd",
    "sg:city":"New Norfolk",
    "sg:classifiers":[
        {
            "category":"Fast Food",
            "type":"Food & Drink"
        }
    ],
    "sg:phone":"+61 3 6261 2780",
    "sg:postcode":"7140",
    "sg:province":"TAS",
    "sg:tags":[
        "away",
        "take"
    ],
    "wof:name":"Eagle Snack Bar",
    "wof:placetype":"venue"
},
  "geometry": {"coordinates":[147.055115,-42.777374],"type":"Point"}
}