{
  "type": "Feature",
  "properties": {
    "addr:full":"Macquarie St George Town TAS 7253",
    "addr:postcode":"7253",
    "addr:street":"Macquarie",
    "iso:country":"AU",
    "sg:address":"Macquarie St",
    "sg:city":"George Town",
    "sg:classifiers":[
        {
            "category":"Autos & Motor Vehicles",
            "subcategory":"Fuel & Gas Station",
            "type":"Retail Goods"
        }
    ],
    "sg:phone":"+61 3 6382 1503",
    "sg:postcode":"7253",
    "sg:province":"TAS",
    "wof:name":"Mobil Oil Aust Pty Ltd",
    "wof:placetype":"venue"
},
  "geometry": {"coordinates":[146.830978394,-41.1040840149],"type":"Point"}
}