{
  "type": "Feature",
  "properties": {
    "addr:full":"333 Pacific Hwy Motto Farm NSW 2324",
    "addr:housenumber":"333",
    "addr:postcode":"2324",
    "addr:street":"Pacific Hwy",
    "iso:country":"AU",
    "sg:address":"333 Pacific Hwy",
    "sg:city":"Motto Farm",
    "sg:classifiers":[
        {
            "category":"Retail",
            "subcategory":"Auto Repair",
            "type":"Services"
        }
    ],
    "sg:phone":"+61 2 4987 4888",
    "sg:postcode":"2324",
    "sg:province":"NSW",
    "sg:tags":[
        "bus",
        "truck"
    ],
    "wof:name":"Trucksmart",
    "wof:placetype":"venue"
},
  "geometry": {"coordinates":[151.72442626899999,-32.7922058105],"type":"Point"}
}