{
  "type": "Feature",
  "properties": {
    "addr:full":"961 Ridgley Hwy Ridgley TAS 7321",
    "addr:housenumber":"961",
    "addr:postcode":"7321",
    "addr:street":"Ridgley Hwy",
    "iso:country":"AU",
    "sg:address":"961 Ridgley Hwy",
    "sg:city":"Ridgley",
    "sg:classifiers":[
        {
            "category":"Retail",
            "subcategory":"Storage",
            "type":"Services"
        }
    ],
    "sg:phone":"+61 439 363 178",
    "sg:postcode":"7321",
    "sg:province":"TAS",
    "sg:tags":[
        "removal",
        "furniture"
    ],
    "wof:name":"Savage Transport",
    "wof:placetype":"venue"
},
  "geometry": {"coordinates":[145.83564799999999,-41.144611],"type":"Point"}
}