{
  "type": "Feature",
  "properties": {
    "addr:full":"135 Hopetoun St Kurri Kurri NSW 2327",
    "addr:housenumber":"135",
    "addr:postcode":"2327",
    "addr:street":"Hopetoun St",
    "iso:country":"AU",
    "sg:address":"135 Hopetoun St",
    "sg:city":"Kurri Kurri",
    "sg:classifiers":[
        {
            "category":"Wholesale",
            "subcategory":"Electrical",
            "type":"Manufacturing & Wholesale Goods"
        }
    ],
    "sg:phone":"+61 2 9651 2400",
    "sg:postcode":"2327",
    "sg:province":"NSW",
    "sg:tags":[
        "control",
        "equipment",
        "switch"
    ],
    "wof:name":"Protection & Monitoring Systems Pty Ltd",
    "wof:placetype":"venue"
},
  "geometry": {"coordinates":[151.482513428,-32.8213806152],"type":"Point"}
}