{
  "type": "Feature",
  "properties": {
    "addr:full":"Shp6/ 119 Koornang Rd Carnegie VIC 3163",
    "addr:housenumber":"119",
    "addr:postcode":"3163",
    "addr:street":"Koornang Rd",
    "iso:country":"AU",
    "sg:address":"Shp6/ 119 Koornang Rd",
    "sg:city":"Carnegie",
    "sg:classifiers":[
        {
            "category":"Food & Beverages",
            "subcategory":"Fruits & Vegetables",
            "type":"Retail Goods"
        }
    ],
    "sg:phone":"+61 3 9572 4933",
    "sg:postcode":"3163",
    "sg:province":"VIC",
    "sg:tags":[
        "greengrocer",
        "fruiterer"
    ],
    "wof:name":"Carnegie Fresh",
    "wof:placetype":"venue"
},
  "geometry": {"coordinates":[145.05705261200001,-37.8883628845],"type":"Point"}
}