{
  "type": "Feature",
  "properties": {
    "addr:full":"239 Whitehorse Rd Balwyn VIC 3103",
    "addr:housenumber":"239",
    "addr:postcode":"3103",
    "addr:street":"Whitehorse Rd",
    "iso:country":"AU",
    "sg:address":"239 Whitehorse Rd",
    "sg:city":"Balwyn",
    "sg:classifiers":[
        {
            "category":"Shopping",
            "subcategory":"Computers & Home Electronics",
            "type":"Retail Goods"
        }
    ],
    "sg:phone":"+61 3 9836 0522",
    "sg:postcode":"3103",
    "sg:province":"VIC",
    "sg:tags":[
        "hi-fi",
        "equipment"
    ],
    "wof:name":"Intersound Hifi",
    "wof:placetype":"venue"
},
  "geometry": {"coordinates":[145.08021545400001,-37.8125457764],"type":"Point"}
}