{
  "type": "Feature",
  "properties": {
    "iso:country":"AU",
    "sg:address":"Lot 8, Whalan Crt",
    "sg:city":"Pyalong",
    "sg:classifiers":[
        {
            "category":"Retail",
            "subcategory":"Auto Repair",
            "type":"Services"
        }
    ],
    "sg:phone":"+61 3 5785 1297",
    "sg:postcode":"3521",
    "sg:province":"VIC",
    "sg:tags":[
        "beater",
        "painter",
        "panel"
    ],
    "wof:name":"Northern Highway Smash Repairs",
    "wof:placetype":"venue"
},
  "geometry": {"coordinates":[144.86685199999999,-37.139576],"type":"Point"}
}