{
  "type": "Feature",
  "properties": {
    "iso:country":"AU",
    "sg:address":"179 Marion St",
    "sg:city":"Leichhardt",
    "sg:classifiers":[
        {
            "category":"Mining & Drilling",
            "type":"Manufacturing & Wholesale Goods"
        }
    ],
    "sg:phone":"+61 2 9568 2986",
    "sg:postcode":"2040",
    "sg:province":"NSW",
    "sg:tags":[
        "concrete",
        "breaking",
        "grinding",
        "sawing"
    ],
    "wof:name":"Ace Wall Chasing",
    "wof:placetype":"venue"
},
  "geometry": {"coordinates":[151.14889500000001,-33.88406],"type":"Point"}
}