{
  "type": "Feature",
  "properties": {
    "iso:country":"AU",
    "sg:address":"The Link Arcade Shop 3b Victoria St",
    "sg:city":"Warragul",
    "sg:classifiers":[
        {
            "category":"Personal",
            "subcategory":"Beauty Salon",
            "type":"Services"
        }
    ],
    "sg:phone":"+61 3 5623 6318",
    "sg:postcode":"3820",
    "sg:province":"VIC",
    "sg:tags":[
        "hairdresser"
    ],
    "wof:name":"Taylor Made Ideas In Hair",
    "wof:placetype":"venue"
},
  "geometry": {"coordinates":[145.93512,-38.152672],"type":"Point"}
}