{
  "type": "Feature",
  "properties": {
    "addr:full":"PO Box 20 Morven QLD 4468",
    "addr:postcode":"4468",
    "iso:country":"AU",
    "sg:address":"PO Box 20",
    "sg:city":"Morven",
    "sg:classifiers":[
        {
            "category":"Professional",
            "subcategory":"Testing Lab",
            "type":"Services"
        }
    ],
    "sg:phone":"+61 7 4654 8183",
    "sg:postcode":"4468",
    "sg:province":"QLD",
    "sg:tags":[
        "inspection"
    ],
    "wof:name":"Australian Fibre Testing Pty Ltd",
    "wof:placetype":"venue"
},
  "geometry": {"coordinates":[147.11898803700001,-26.4132804871],"type":"Point"}
}