{
  "type": "Feature",
  "properties": {
    "addr:full":"40-44 Bennet St Dandenong VIC 3175",
    "addr:housenumber":"40-44",
    "addr:postcode":"3175",
    "addr:street":"Bennet St",
    "iso:country":"AU",
    "sg:address":"40-44 Bennet St",
    "sg:city":"Dandenong",
    "sg:classifiers":[
        {
            "category":"Wholesale",
            "subcategory":"Auto Parts",
            "type":"Manufacturing & Wholesale Goods"
        }
    ],
    "sg:phone":"+61 3 9706 8889",
    "sg:postcode":"3175",
    "sg:province":"VIC",
    "sg:tags":[
        "recyclers"
    ],
    "wof:name":"Sterling Parts (Melbourne)",
    "wof:placetype":"venue"
},
  "geometry": {"coordinates":[145.199127197,-37.9881324768],"type":"Point"}
}