{
  "type": "Feature",
  "properties": {
    "addr:full":"98 Hannell St Wickham NSW 2293",
    "addr:housenumber":"98",
    "addr:postcode":"2293",
    "addr:street":"Hannell St",
    "iso:country":"AU",
    "sg:address":"98 Hannell St",
    "sg:city":"Wickham",
    "sg:classifiers":[
        {
            "category":"Real Estate",
            "subcategory":"Real Estate Services",
            "type":"Services"
        }
    ],
    "sg:phone":"+61 2 4922 0600",
    "sg:postcode":"2293",
    "sg:province":"NSW",
    "sg:tags":[
        "valuer"
    ],
    "wof:name":"Duponts",
    "wof:placetype":"venue"
},
  "geometry": {"coordinates":[151.75950622600001,-32.9191093445],"type":"Point"}
}