{
  "type": "Feature",
  "properties": {
    "addr:full":"Tumoulin Rd Tumoulin QLD 4872",
    "addr:postcode":"4872",
    "addr:street":"Tumoulin Rd",
    "iso:country":"AU",
    "sg:address":"Tumoulin Rd",
    "sg:city":"Tumoulin",
    "sg:classifiers":[
        {
            "category":"Farming",
            "subcategory":"Farm",
            "type":"Manufacturing & Wholesale Goods"
        }
    ],
    "sg:phone":"+61 7 4097 6281",
    "sg:postcode":"4872",
    "sg:province":"QLD",
    "sg:tags":[
        "farmer"
    ],
    "wof:name":"Chester R C",
    "wof:placetype":"venue"
},
  "geometry": {"coordinates":[145.461425781,-17.5868415833],"type":"Point"}
}