{
  "type": "Feature",
  "properties": {
    "addr:full":"34 McNulty Drv Wendouree VIC 3355",
    "addr:housenumber":"34",
    "addr:postcode":"3355",
    "addr:street":"Mcnulty Drv",
    "iso:country":"AU",
    "sg:address":"34 McNulty Drv",
    "sg:city":"Wendouree",
    "sg:classifiers":[
        {
            "category":"Building & Trades",
            "subcategory":"Construction",
            "type":"Services"
        }
    ],
    "sg:phone":"+61 3 5339 3199",
    "sg:postcode":"3355",
    "sg:province":"VIC",
    "sg:tags":[
        "renovation",
        "alterations",
        "extension",
        "contractor"
    ],
    "wof:name":"Top 2 Bottom",
    "wof:placetype":"venue"
},
  "geometry": {"coordinates":[143.81298799999999,-37.526741],"type":"Point"}
}