{
  "type": "Feature",
  "properties": {
    "iso:country":"AU",
    "sg:address":"Studio 2A 108 Moor St",
    "sg:city":"Fitzroy",
    "sg:classifiers":[
        {
            "category":"Organizations",
            "subcategory":"Professional Association",
            "type":"Services"
        }
    ],
    "sg:phone":"+61 3 9415 2333",
    "sg:postcode":"3065",
    "sg:province":"VIC",
    "sg:tags":[
        "web",
        "internet"
    ],
    "wof:name":"Reactive Media",
    "wof:placetype":"venue"
},
  "geometry": {"coordinates":[144.97821044899999,-37.8017501831],"type":"Point"}
}