{
  "type": "Feature",
  "properties": {
    "addr:full":"915 Howitt St Wendouree VIC 3355",
    "addr:housenumber":"915",
    "addr:postcode":"3355",
    "addr:street":"Howitt St",
    "iso:country":"AU",
    "sg:address":"915 Howitt St",
    "sg:city":"Wendouree",
    "sg:classifiers":[
        {
            "category":"Autos & Motor Vehicles",
            "subcategory":"Automobile Sales",
            "type":"Retail Goods"
        }
    ],
    "sg:phone":"+61 3 5339 5323",
    "sg:postcode":"3355",
    "sg:province":"VIC",
    "sg:tags":[
        "car",
        "used"
    ],
    "wof:name":"Stockade Motors",
    "wof:placetype":"venue"
},
  "geometry": {"coordinates":[143.840958,-37.54155],"type":"Point"}
}