{
  "type": "Feature",
  "properties": {
    "addr:full":"23 Vaughan Drv Ormeau QLD 4208",
    "addr:housenumber":"23",
    "addr:postcode":"4208",
    "addr:street":"Vaughan Drv",
    "iso:country":"AU",
    "sg:address":"23 Vaughan Drv",
    "sg:city":"Ormeau",
    "sg:classifiers":[
        {
            "category":"Retail",
            "subcategory":"Auto Rental",
            "type":"Services"
        }
    ],
    "sg:phone":"+61 7 5546 7264",
    "sg:postcode":"4208",
    "sg:province":"QLD",
    "sg:tags":[
        "chauffeur",
        "car",
        "hire",
        "driven",
        "limousine"
    ],
    "wof:name":"Superior Chauffeured Limousines",
    "wof:placetype":"venue"
},
  "geometry": {"coordinates":[153.24949645999999,-27.7809562683],"type":"Point"}
}