{
  "type": "Feature",
  "properties": {
    "addr:full":"11 Corbusier Pl Balcatta WA 6021",
    "addr:housenumber":"11",
    "addr:postcode":"6021",
    "addr:street":"Corbusier Pl",
    "iso:country":"AU",
    "sg:address":"11 Corbusier Pl",
    "sg:city":"Balcatta",
    "sg:classifiers":[
        {
            "category":"Home & Garden",
            "subcategory":"Furniture",
            "type":"Retail Goods"
        }
    ],
    "sg:phone":"+61 8 9345 4800",
    "sg:postcode":"6021",
    "sg:province":"WA",
    "sg:tags":[
        "business"
    ],
    "wof:name":"Creative by Design",
    "wof:placetype":"venue"
},
  "geometry": {"coordinates":[115.813926697,-31.8616638184],"type":"Point"}
}