{
  "type": "Feature",
  "properties": {
    "addr:full":"Un B1/ 27 Fariola St Silverwater NSW 2264",
    "addr:housenumber":"/ 27",
    "addr:postcode":"2264",
    "addr:street":"Fariola St",
    "iso:country":"AU",
    "sg:address":"Un B1/ 27 Fariola St",
    "sg:city":"Silverwater",
    "sg:classifiers":[
        {
            "category":"Autos & Motor Vehicles",
            "subcategory":"Auto Supplies",
            "type":"Retail Goods"
        }
    ],
    "sg:phone":"+61 2 9648 3006",
    "sg:postcode":"2264",
    "sg:province":"NSW",
    "sg:tags":[
        "wheel",
        "four",
        "equipment",
        "drive",
        "accessory"
    ],
    "wof:name":"Sports Range",
    "wof:placetype":"venue"
},
  "geometry": {"coordinates":[151.56300400000001,-33.103519],"type":"Point"}
}