{
  "type": "Feature",
  "properties": {
    "iso:country":"AU",
    "sg:address":"Shp2/ 130 Tingal Rd",
    "sg:city":"Wynnum",
    "sg:classifiers":[
        {
            "category":"Autos & Motor Vehicles",
            "subcategory":"Auto Supplies",
            "type":"Retail Goods"
        }
    ],
    "sg:phone":"+61 7 3393 3633",
    "sg:postcode":"4178",
    "sg:province":"QLD",
    "sg:tags":[
        "part",
        "cycles",
        "accessory"
    ],
    "wof:name":"Wynnum Motorcycle Accessories",
    "wof:placetype":"venue"
},
  "geometry": {"coordinates":[153.17149352999999,-27.4450855255],"type":"Point"}
}