{
  "type": "Feature",
  "properties": {
    "addr:full":"Tidmarsh Rd Fishery Falls QLD 4871",
    "addr:postcode":"4871",
    "addr:street":"Tidmarsh Rd",
    "iso:country":"AU",
    "sg:address":"Tidmarsh Rd",
    "sg:city":"Fishery Falls",
    "sg:classifiers":[
        {
            "category":"Farming",
            "subcategory":"Farm",
            "type":"Manufacturing & Wholesale Goods"
        }
    ],
    "sg:phone":"+61 7 4067 5251",
    "sg:postcode":"4871",
    "sg:province":"QLD",
    "sg:tags":[
        "farmer"
    ],
    "wof:name":"Cini C & M",
    "wof:placetype":"venue"
},
  "geometry": {"coordinates":[145.88482665999999,-17.1792488098],"type":"Point"}
}