{
  "type": "Feature",
  "properties": {
    "addr:full":"C/O Post Office Ledge Point 6043 Ledge Point WA 6043",
    "addr:postcode":"6043;6043",
    "addr:street":"C",
    "iso:country":"AU",
    "sg:address":"C/O Post Office Ledge Point 6043",
    "sg:city":"Ledge Point",
    "sg:classifiers":[
        {
            "category":"Food & Beverages",
            "subcategory":"Meat & Fish",
            "type":"Retail Goods"
        }
    ],
    "sg:phone":"+61 407 384 484",
    "sg:postcode":"6043",
    "sg:province":"WA",
    "sg:tags":[
        "aquaculture"
    ],
    "wof:name":"Pondplan",
    "wof:placetype":"venue"
},
  "geometry": {"coordinates":[115.405548096,-31.0938224792],"type":"Point"}
}