{
  "type": "Feature",
  "properties": {
    "iso:country":"AU",
    "sg:address":"38 Bombala St",
    "sg:city":"Nimmitabel",
    "sg:classifiers":[
        {
            "category":"Personal",
            "type":"Services"
        }
    ],
    "sg:phone":"+61 2 6454 6488",
    "sg:postcode":"2631",
    "sg:province":"NSW",
    "sg:tags":[
        "gift"
    ],
    "wof:name":"Butcher's Hook",
    "wof:placetype":"venue"
},
  "geometry": {"coordinates":[149.280319214,-36.5188179016],"type":"Point"}
}