{
  "type": "Feature",
  "properties": {
    "iso:country":"AU",
    "sg:address":"27 Rowen St",
    "sg:city":"Glen Iris",
    "sg:classifiers":[
        {
            "category":"Education",
            "subcategory":"Kindergarten",
            "type":"Public Place"
        }
    ],
    "sg:phone":"+61 3 9889 7996",
    "sg:postcode":"3146",
    "sg:province":"VIC",
    "sg:tags":[
        "pre-schools"
    ],
    "wof:name":"Rowen Street Kindergarten Inc",
    "wof:placetype":"venue"
},
  "geometry": {"coordinates":[145.08851623499999,-37.8579750061],"type":"Point"}
}