{
  "type": "Feature",
  "properties": {
    "iso:country":"AU",
    "sg:address":"Unit 3/ 11 Attunga Rd",
    "sg:city":"Blaxland",
    "sg:classifiers":[
        {
            "category":"Retail",
            "subcategory":"Auto Repair",
            "type":"Services"
        }
    ],
    "sg:phone":"+61 2 4739 1137",
    "sg:postcode":"2774",
    "sg:province":"NSW",
    "sg:tags":[
        "electrical"
    ],
    "wof:name":"Blaxland Auto Electrics",
    "wof:placetype":"venue"
},
  "geometry": {"coordinates":[150.608932495,-33.7370452881],"type":"Point"}
}