{
  "type": "Feature",
  "properties": {
    "addr:full":"68 Abuklea Rd Eastwood NSW 2122",
    "addr:housenumber":"68",
    "addr:postcode":"2122",
    "addr:street":"Abuklea Rd",
    "iso:country":"AU",
    "sg:address":"68 Abuklea Rd",
    "sg:city":"Eastwood",
    "sg:classifiers":[
        {
            "category":"Utilities",
            "subcategory":"Electric",
            "type":"Services"
        }
    ],
    "sg:phone":"+61 419 206 722",
    "sg:postcode":"2122",
    "sg:province":"NSW",
    "sg:tags":[
        "electrical",
        "contractor"
    ],
    "wof:name":"Zappit Electrical Services",
    "wof:placetype":"venue"
},
  "geometry": {"coordinates":[151.097045898,-33.7796058655],"type":"Point"}
}