{
  "type": "Feature",
  "properties": {
    "addr:full":"Level 1 Suite 15 Corio Village Shopng Cntr Corio VIC 3214",
    "addr:postcode":"3214",
    "addr:street":"Village",
    "iso:country":"AU",
    "sg:address":"Level 1 Suite 15 Corio Village Shopng Cntr",
    "sg:city":"Corio",
    "sg:classifiers":[
        {
            "category":"Organizations",
            "subcategory":"Labor Organization",
            "type":"Services"
        }
    ],
    "sg:phone":"+61 3 5274 2844",
    "sg:postcode":"3214",
    "sg:province":"VIC",
    "sg:tags":[
        "union"
    ],
    "wof:name":"Australian Manufacturing Workers' Union",
    "wof:placetype":"venue"
},
  "geometry": {"coordinates":[144.35643005399999,-38.0738601685],"type":"Point"}
}