{
  "type": "Feature",
  "properties": {
    "addr:full":"39 Riddell St Bingara NSW 2404",
    "addr:housenumber":"39",
    "addr:postcode":"2404",
    "addr:street":"Riddell St",
    "iso:country":"AU",
    "sg:address":"39 Riddell St",
    "sg:city":"Bingara",
    "sg:classifiers":[
        {
            "category":"Professional",
            "subcategory":"Business Services",
            "type":"Services"
        }
    ],
    "sg:phone":"+61 2 6724 1222",
    "sg:postcode":"2404",
    "sg:province":"NSW",
    "sg:tags":[
        "livestock",
        "transport"
    ],
    "wof:name":"Peter J O'Brien Carrier",
    "wof:placetype":"venue"
},
  "geometry": {"coordinates":[150.570556641,-29.8715858459],"type":"Point"}
}