{
  "type": "Feature",
  "properties": {
    "iso:country":"AU",
    "sg:address":"239a Main St",
    "sg:city":"Bairnsdale",
    "sg:classifiers":[
        {
            "category":"Professional",
            "subcategory":"Engineering",
            "type":"Services"
        }
    ],
    "sg:phone":"+61 3 9558 8033",
    "sg:postcode":"3875",
    "sg:province":"VIC",
    "sg:tags":[
        "consulting",
        "engineer"
    ],
    "sg:website":"http://www.gamcorp.com.au",
    "wof:name":"Gamcorp Pty Ltd",
    "wof:placetype":"venue"
},
  "geometry": {"coordinates":[147.827224731,-37.7086296082],"type":"Point"}
}