{
  "type": "Feature",
  "properties": {
    "addr:full":"69 Ninth Ave Joslin SA 5070",
    "addr:housenumber":"69",
    "addr:postcode":"5070",
    "addr:street":"Ninth Ave",
    "iso:country":"AU",
    "sg:address":"69 Ninth Ave",
    "sg:city":"Joslin",
    "sg:classifiers":[
        {
            "category":"Utilities",
            "subcategory":"Electric",
            "type":"Services"
        }
    ],
    "sg:phone":"+61 8 8362 0092",
    "sg:postcode":"5070",
    "sg:province":"SA",
    "sg:tags":[
        "element"
    ],
    "wof:name":"Adda-Heat",
    "wof:placetype":"venue"
},
  "geometry": {"coordinates":[138.62384033199999,-34.8977851868],"type":"Point"}
}