{
  "type": "Feature",
  "properties": {
    "addr:full":"239 High St Northcote VIC 3070",
    "addr:housenumber":"239",
    "addr:postcode":"3070",
    "addr:street":"High St",
    "iso:country":"AU",
    "sg:address":"239 High St",
    "sg:city":"Northcote",
    "sg:classifiers":[
        {
            "category":"Shopping",
            "subcategory":"Clothing, Apparel, & Fashions",
            "type":"Retail Goods"
        }
    ],
    "sg:phone":"+61 3 9482 7157",
    "sg:postcode":"3070",
    "sg:province":"VIC",
    "sg:tags":[
        "boutique"
    ],
    "wof:name":"Cosmonauts Concious Closing & Paraphernalia",
    "wof:placetype":"venue"
},
  "geometry": {"coordinates":[144.99804700000001,-37.773254],"type":"Point"}
}