{
  "type": "Feature",
  "properties": {
    "iso:country":"AU",
    "sg:address":"Morrison Ave",
    "sg:city":"Ceduna",
    "sg:classifiers":[
        {
            "category":"Wholesale",
            "subcategory":"Painting Supplies",
            "type":"Manufacturing & Wholesale Goods"
        }
    ],
    "sg:phone":"+61 8 8625 2772",
    "sg:postcode":"5690",
    "sg:province":"SA",
    "sg:tags":[
        "product",
        "cleaning"
    ],
    "wof:name":"Ceduna Food & Milk Distributors",
    "wof:placetype":"venue"
},
  "geometry": {"coordinates":[133.675216675,-32.1292800903],"type":"Point"}
}