{
  "type": "Feature",
  "properties": {
    "addr:full":"40 Fcarra Crs Acacia Gardens NSW 2763",
    "addr:housenumber":"40",
    "addr:postcode":"2763",
    "addr:street":"Fcarra Crs;Gardens",
    "iso:country":"AU",
    "sg:address":"40 Fcarra Crs",
    "sg:city":"Acacia Gardens",
    "sg:classifiers":[
        {
            "category":"Building & Trades",
            "subcategory":"Cleaning & Sanitation",
            "type":"Services"
        }
    ],
    "sg:phone":"+61 2 9837 7988",
    "sg:postcode":"2763",
    "sg:province":"NSW",
    "sg:tags":[
        "industrial",
        "commercial",
        "contractor"
    ],
    "wof:name":"Denise's Domestic Services",
    "wof:placetype":"venue"
},
  "geometry": {"coordinates":[150.912963867,-33.7327384949],"type":"Point"}
}