{
  "type": "Feature",
  "properties": {
    "addr:full":"U9/ 1 Exchange Pde Smeaton Grange NSW 2567",
    "addr:housenumber":"1",
    "addr:postcode":"2567",
    "addr:street":"U9 /;Exchange Pde",
    "iso:country":"AU",
    "sg:address":"U9/ 1 Exchange Pde",
    "sg:city":"Smeaton Grange",
    "sg:classifiers":[
        {
            "category":"Communications",
            "subcategory":"Film & Video Production",
            "type":"Services"
        }
    ],
    "sg:phone":"+61 2 4636 9150",
    "sg:postcode":"2567",
    "sg:province":"NSW",
    "sg:tags":[
        "information",
        "recorded",
        "telephone"
    ],
    "wof:name":"Phone First Pty Ltd",
    "wof:placetype":"venue"
},
  "geometry": {"coordinates":[150.749145508,-34.0404891968],"type":"Point"}
}