{
  "type": "Feature",
  "properties": {
    "iso:country":"AU",
    "sg:address":"2 Cromwell St",
    "sg:city":"New Lambton",
    "sg:classifiers":[
        {
            "category":"Health Services",
            "subcategory":"Doctor",
            "type":"Services"
        }
    ],
    "sg:phone":"+61 2 4952 8178",
    "sg:postcode":"2305",
    "sg:province":"NSW",
    "sg:tags":[
        "podiatrist"
    ],
    "wof:name":"Cathy Weiss Podiatry",
    "wof:placetype":"venue"
},
  "geometry": {"coordinates":[151.714417,-32.92329],"type":"Point"}
}