{
  "type": "Feature",
  "properties": {
    "iso:country":"AU",
    "sg:address":"Unit G/ 2 Reliance Drv",
    "sg:city":"Tuggerah",
    "sg:classifiers":[
        {
            "category":"Building & Trades",
            "subcategory":"Landscaping Services",
            "type":"Services"
        }
    ],
    "sg:phone":"+61 2 4353 6088",
    "sg:postcode":"2259",
    "sg:province":"NSW",
    "sg:tags":[
        "consultant"
    ],
    "wof:name":"Projectworks Building Design",
    "wof:placetype":"venue"
},
  "geometry": {"coordinates":[151.421142578,-33.3138313293],"type":"Point"}
}