{
  "type": "Feature",
  "properties": {
    "addr:full":"1170 Benetook Ave Mildura VIC 3500",
    "addr:housenumber":"1170",
    "addr:postcode":"3500",
    "addr:street":"Benetook Ave",
    "iso:country":"AU",
    "sg:address":"1170 Benetook Ave",
    "sg:city":"Mildura",
    "sg:classifiers":[
        {
            "category":"Retail",
            "subcategory":"Auto Rental",
            "type":"Services"
        }
    ],
    "sg:phone":"+61 3 5023 4366",
    "sg:postcode":"3500",
    "sg:province":"VIC",
    "sg:tags":[
        "bus",
        "truck"
    ],
    "wof:name":"Benetook Auto Bus Hire",
    "wof:placetype":"venue"
},
  "geometry": {"coordinates":[142.167144775,-34.2061805725],"type":"Point"}
}