{
  "type": "Feature",
  "properties": {
    "addr:full":"18 Windarra St Woree QLD 4868",
    "addr:housenumber":"18",
    "addr:postcode":"4868",
    "addr:street":"Windarra St",
    "iso:country":"AU",
    "sg:address":"18 Windarra St",
    "sg:city":"Woree",
    "sg:classifiers":[
        {
            "category":"Professional",
            "type":"Services"
        }
    ],
    "sg:phone":"+61 418 881 145",
    "sg:postcode":"4868",
    "sg:province":"QLD",
    "sg:tags":[
        "transport"
    ],
    "wof:name":"F.N.Q. Crane Trucks",
    "wof:placetype":"venue"
},
  "geometry": {"coordinates":[145.74061584500001,-16.9593238831],"type":"Point"}
}