{
  "type": "Feature",
  "properties": {
    "iso:country":"AU",
    "sg:address":"10 Wren St",
    "sg:city":"Dianella",
    "sg:classifiers":[
        {
            "category":"Shopping",
            "subcategory":"Computers & Home Electronics",
            "type":"Retail Goods"
        }
    ],
    "sg:phone":"+61 411 479 442",
    "sg:postcode":"6059",
    "sg:province":"WA",
    "sg:tags":[
        "hardware",
        "equipment"
    ],
    "wof:name":"Graf Cadd",
    "wof:placetype":"venue"
},
  "geometry": {"coordinates":[115.846153259,-32.0155982971],"type":"Point"}
}