{
  "type": "Feature",
  "properties": {
    "iso:country":"AU",
    "sg:address":"13 Rowan St",
    "sg:city":"Bendigo",
    "sg:classifiers":[
        {
            "category":"Health Services",
            "subcategory":"Doctor",
            "type":"Services"
        }
    ],
    "sg:phone":"+61 3 5443 4777",
    "sg:postcode":"3550",
    "sg:province":"VIC",
    "sg:tags":[
        "medical",
        "practitioner"
    ],
    "wof:name":"Kiffer John D Dr",
    "wof:placetype":"venue"
},
  "geometry": {"coordinates":[144.27450561500001,-36.757648468],"type":"Point"}
}