{
  "type": "Feature",
  "properties": {
    "addr:full":"179 Bencubbin Ave Coleambally NSW 2707",
    "addr:housenumber":"179",
    "addr:postcode":"2707",
    "addr:street":"Bencubbin Ave",
    "iso:country":"AU",
    "sg:address":"179 Bencubbin Ave",
    "sg:city":"Coleambally",
    "sg:classifiers":[
        {
            "category":"Home & Garden",
            "subcategory":"Garden Supply",
            "type":"Retail Goods"
        }
    ],
    "sg:phone":"+61 2 6954 4235",
    "sg:postcode":"2707",
    "sg:province":"NSW",
    "sg:tags":[
        "fertilizer"
    ],
    "wof:name":"Coly Hifert",
    "wof:placetype":"venue"
},
  "geometry": {"coordinates":[145.904663086,-34.7994117737],"type":"Point"}
}