{
  "type": "Feature",
  "properties": {
    "iso:country":"AU",
    "sg:address":"52a Woyna Ave",
    "sg:city":"Rosebud West",
    "sg:classifiers":[
        {
            "category":"Home & Garden",
            "subcategory":"Carpets & Floor Coverings",
            "type":"Retail Goods"
        }
    ],
    "sg:phone":"+61 3 5982 1683",
    "sg:postcode":"3940",
    "sg:province":"VIC",
    "wof:name":"G & L Pesced Floor Covering Contractors",
    "wof:placetype":"venue"
},
  "geometry": {"coordinates":[144.864501953,-38.367729187],"type":"Point"}
}