{
  "type": "Feature",
  "properties": {
    "addr:full":"Unit 5, 3 Stout Rd Mt Druitt NSW 2770",
    "addr:housenumber":"3",
    "addr:postcode":"2770",
    "addr:street":"Stout Rd",
    "iso:country":"AU",
    "sg:address":"Unit 5, 3 Stout Rd",
    "sg:city":"Mt Druitt",
    "sg:classifiers":[
        {
            "category":"Donuts",
            "subcategory":"None",
            "type":"Food & Drink"
        }
    ],
    "sg:phone":"+61 2 9832 7756",
    "sg:postcode":"2770",
    "sg:province":"NSW",
    "sg:tags":[
        "die",
        "engraver",
        "sinker"
    ],
    "wof:name":"Phanart Engraving & Signs Pty Ltd",
    "wof:placetype":"venue"
},
  "geometry": {"coordinates":[150.81105041500001,-33.7668457031],"type":"Point"}
}