{
  "type": "Feature",
  "properties": {
    "iso:country":"AU",
    "sg:address":"Cnr Bourke & Clinton Sts",
    "sg:city":"Goulburn",
    "sg:classifiers":[
        {
            "category":"Retail",
            "subcategory":"Auto Repair",
            "type":"Services"
        }
    ],
    "sg:phone":"+61 2 4821 4400",
    "sg:postcode":"2580",
    "sg:province":"NSW",
    "sg:tags":[
        "clutch",
        "brake"
    ],
    "wof:name":"Goulburn Transmission Service Pty Ltd",
    "wof:placetype":"venue"
},
  "geometry": {"coordinates":[149.71420288100001,-34.7559318542],"type":"Point"}
}