{
  "type": "Feature",
  "properties": {
    "addr:full":"3/ 61 Walters Drv Osborne Park WA 6017",
    "addr:housenumber":"/ 61",
    "addr:postcode":"6017",
    "addr:street":"Walters Drv",
    "iso:country":"AU",
    "sg:address":"3/ 61 Walters Drv",
    "sg:city":"Osborne Park",
    "sg:classifiers":[
        {
            "category":"Utilities",
            "subcategory":"Mobile Phone",
            "type":"Services"
        }
    ],
    "sg:phone":"+61 8 9242 2848",
    "sg:postcode":"6017",
    "sg:province":"WA",
    "sg:tags":[
        "assembly",
        "part",
        "electronic"
    ],
    "wof:name":"Tri Electronics",
    "wof:placetype":"venue"
},
  "geometry": {"coordinates":[115.81414032000001,-31.9128894806],"type":"Point"}
}