{
  "type": "Feature",
  "properties": {
    "iso:country":"AU",
    "sg:address":"186 Buckley St",
    "sg:city":"Footscray",
    "sg:classifiers":[
        {
            "category":"Education",
            "subcategory":"Music School",
            "type":"Public Place"
        }
    ],
    "sg:phone":"+61 3 9687 6735",
    "sg:postcode":"3011",
    "sg:province":"VIC",
    "sg:tags":[
        "teacher"
    ],
    "wof:name":"Andrios School Of Music",
    "wof:placetype":"venue"
},
  "geometry": {"coordinates":[144.886993408,-37.8021087646],"type":"Point"}
}