{
  "type": "Feature",
  "properties": {
    "iso:country":"AU",
    "sg:address":"124 Weaponess Rd",
    "sg:city":"Wembley Downs",
    "sg:classifiers":[
        {
            "category":"Health Services",
            "subcategory":"Doctor",
            "type":"Services"
        }
    ],
    "sg:phone":"+61 8 9341 8444",
    "sg:postcode":"6019",
    "sg:province":"WA",
    "sg:tags":[
        "medical",
        "practitioner"
    ],
    "wof:name":"Wembley Downs Medical Centre",
    "wof:placetype":"venue"
},
  "geometry": {"coordinates":[115.773513794,-31.9099025726],"type":"Point"}
}