{
  "type": "Feature",
  "properties": {
    "iso:country":"AU",
    "sg:address":"50 East Churchill Ave",
    "sg:city":"Beeliar",
    "sg:classifiers":[
        {
            "category":"Social Services",
            "subcategory":"Adult Care",
            "type":"Services"
        }
    ],
    "sg:phone":"+61 419 921 629",
    "sg:postcode":"6164",
    "sg:province":"WA",
    "sg:tags":[
        "towing"
    ],
    "wof:name":"Basilio Towing Service",
    "wof:placetype":"venue"
},
  "geometry": {"coordinates":[115.79843099999999,-32.134113],"type":"Point"}
}