{
  "type": "Feature",
  "properties": {
    "addr:full":"Shop 7/ 111 Queen St Cleveland QLD 4163",
    "addr:housenumber":"shop 7 / 111",
    "addr:postcode":"4163",
    "addr:street":"Queen St",
    "iso:country":"AU",
    "sg:address":"Shop 7/ 111 Queen St",
    "sg:city":"Cleveland",
    "sg:classifiers":[
        {
            "category":"Wholesale",
            "subcategory":"Medical Equipment & Supplies",
            "type":"Manufacturing & Wholesale Goods"
        }
    ],
    "sg:phone":"+61 1800 653 336",
    "sg:postcode":"4163",
    "sg:province":"QLD",
    "sg:tags":[
        "aids",
        "hearing"
    ],
    "wof:name":"King Hearing Centres",
    "wof:placetype":"venue"
},
  "geometry": {"coordinates":[153.26864624000001,-27.5281600952],"type":"Point"}
}