{
  "type": "Feature",
  "properties": {
    "addr:full":"17 Miles Rd Kewdale WA 6105",
    "addr:housenumber":"17",
    "addr:postcode":"6105",
    "addr:street":"Miles Rd",
    "iso:country":"AU",
    "sg:address":"17 Miles Rd",
    "sg:city":"Kewdale",
    "sg:classifiers":[
        {
            "category":"Professional",
            "type":"Services"
        }
    ],
    "sg:phone":"+61 8 9353 5447",
    "sg:postcode":"6105",
    "sg:province":"WA",
    "sg:tags":[
        "transport"
    ],
    "wof:name":"Goldstar Transport",
    "wof:placetype":"venue"
},
  "geometry": {"coordinates":[115.948959351,-31.9820461273],"type":"Point"}
}