{
  "type": "Feature",
  "properties": {
    "addr:full":"Lvl 7/ 243 Edward St Brisbane QLD 4000",
    "addr:housenumber":"/ 243",
    "addr:postcode":"4000",
    "addr:street":"Edward St",
    "iso:country":"AU",
    "sg:address":"Lvl 7/ 243 Edward St",
    "sg:city":"Brisbane",
    "sg:classifiers":[
        {
            "category":"Professional",
            "subcategory":"Management & Consulting",
            "type":"Services"
        }
    ],
    "sg:phone":"+61 7 3229 2382",
    "sg:postcode":"4000",
    "sg:province":"QLD",
    "sg:tags":[
        "consultant",
        "educational"
    ],
    "wof:name":"Groupogales Australia",
    "wof:placetype":"venue"
},
  "geometry": {"coordinates":[153.026580811,-27.4677467346],"type":"Point"}
}