{
  "type": "Feature",
  "properties": {
    "iso:country":"AU",
    "sg:address":"15 Tripoli Crt",
    "sg:city":"Hallam",
    "sg:classifiers":[
        {
            "category":"Insurance",
            "subcategory":"Insurance Agent",
            "type":"Services"
        }
    ],
    "sg:phone":"+61 3 9703 1044",
    "sg:postcode":"3803",
    "sg:province":"VIC",
    "wof:name":"Heitch A C",
    "wof:placetype":"venue"
},
  "geometry": {"coordinates":[145.26121520999999,-37.998500824],"type":"Point"}
}