{
  "type": "Feature",
  "properties": {
    "addr:full":"2 Old Park Drv Melton VIC 3337",
    "addr:housenumber":"2",
    "addr:postcode":"3337",
    "addr:street":"Old Park Drv",
    "iso:country":"AU",
    "sg:address":"2 Old Park Drv",
    "sg:city":"Melton",
    "sg:classifiers":[
        {
            "category":"Home & Garden",
            "subcategory":"Building Materials",
            "type":"Retail Goods"
        }
    ],
    "sg:phone":"+61 3 9743 7741",
    "sg:postcode":"3337",
    "sg:province":"VIC",
    "sg:tags":[
        "merchant",
        "glass",
        "glazier"
    ],
    "wof:name":"Avenue Glass",
    "wof:placetype":"venue"
},
  "geometry": {"coordinates":[144.60296600000001,-37.680676],"type":"Point"}
}