{
  "type": "Feature",
  "properties": {
    "addr:full":"Unit 1/ 81 Salamanca Pl Hobart TAS 7000",
    "addr:postcode":"7000",
    "addr:street":"Pl",
    "iso:country":"AU",
    "sg:address":"Unit 1/ 81 Salamanca Pl",
    "sg:city":"Hobart",
    "sg:classifiers":[
        {
            "category":"Social Services",
            "subcategory":"Retirement Home",
            "type":"Services"
        }
    ],
    "sg:phone":"+61 438 709 351",
    "sg:postcode":"7000",
    "sg:province":"TAS",
    "sg:tags":[
        "life",
        "coaching"
    ],
    "wof:name":"Johnston Neil",
    "wof:placetype":"venue"
},
  "geometry": {"coordinates":[147.33462524399999,-42.8868370056],"type":"Point"}
}