{
  "type": "Feature",
  "properties": {
    "addr:full":"98 Lake St Cairns QLD 4870",
    "addr:housenumber":"98",
    "addr:postcode":"4870",
    "addr:street":"Lake St",
    "iso:country":"AU",
    "sg:address":"98 Lake St",
    "sg:city":"Cairns",
    "sg:classifiers":[
        {
            "category":"Health Services",
            "subcategory":"Optometrist",
            "type":"Services"
        }
    ],
    "sg:phone":"+61 7 4031 1310",
    "sg:postcode":"4870",
    "sg:province":"QLD",
    "wof:name":"Penrose Optometry",
    "wof:placetype":"venue"
},
  "geometry": {"coordinates":[145.77507019000001,-16.9210205078],"type":"Point"}
}