{
  "type": "Feature",
  "properties": {
    "addr:full":"75 Hastings St Scarborough WA 6019",
    "addr:housenumber":"75",
    "addr:postcode":"6019",
    "addr:street":"Hastings St",
    "iso:country":"AU",
    "sg:address":"75 Hastings St",
    "sg:city":"Scarborough",
    "sg:classifiers":[
        {
            "category":"Building & Trades",
            "subcategory":"Construction",
            "type":"Services"
        }
    ],
    "sg:phone":"+61 417 923 928",
    "sg:postcode":"6019",
    "sg:province":"WA",
    "sg:tags":[
        "earth",
        "excavating",
        "moving",
        "contractor"
    ],
    "wof:name":"Xcavations & Earthmoving",
    "wof:placetype":"venue"
},
  "geometry": {"coordinates":[115.759857178,-31.9006519318],"type":"Point"}
}