{
  "type": "Feature",
  "properties": {
    "addr:full":"22 Belford Rd Lambton NSW 2299",
    "addr:housenumber":"22",
    "addr:postcode":"2299",
    "addr:street":"Belford Rd",
    "iso:country":"AU",
    "sg:address":"22 Belford Rd",
    "sg:city":"Lambton",
    "sg:classifiers":[
        {
            "category":"Education",
            "subcategory":"School",
            "type":"Public Place"
        }
    ],
    "sg:phone":"+61 2 4957 1437",
    "sg:postcode":"2299",
    "sg:province":"NSW",
    "wof:name":"Margaret Jurd Learning Centre",
    "wof:placetype":"venue"
},
  "geometry": {"coordinates":[151.71676635700001,-32.9134025574],"type":"Point"}
}