{
  "type": "Feature",
  "properties": {
    "addr:full":"154 Roberta St Greystanes NSW 2145",
    "addr:housenumber":"154",
    "addr:postcode":"2145",
    "addr:street":"Roberta St",
    "iso:country":"AU",
    "sg:address":"154 Roberta St",
    "sg:city":"Greystanes",
    "sg:classifiers":[
        {
            "category":"Building & Trades",
            "subcategory":"Construction",
            "type":"Services"
        }
    ],
    "sg:phone":"+61 2 9688 3675",
    "sg:postcode":"2145",
    "sg:province":"NSW",
    "sg:tags":[
        "contractor"
    ],
    "wof:name":"Benkovic R",
    "wof:placetype":"venue"
},
  "geometry": {"coordinates":[150.937576294,-33.8244628906],"type":"Point"}
}