{
  "type": "Feature",
  "properties": {
    "addr:full":"Lot 8 Pruden Rd Mundijong WA 6123",
    "addr:postcode":"6123",
    "addr:street":"Pruden Rd",
    "iso:country":"AU",
    "sg:address":"Lot 8 Pruden Rd",
    "sg:city":"Mundijong",
    "sg:classifiers":[
        {
            "category":"Building & Trades",
            "subcategory":"Construction",
            "type":"Services"
        }
    ],
    "sg:phone":"+61 8 9525 5995",
    "sg:postcode":"6123",
    "sg:province":"WA",
    "sg:tags":[
        "joiner",
        "carpenter"
    ],
    "wof:name":"May S F & M",
    "wof:placetype":"venue"
},
  "geometry": {"coordinates":[116.020622253,-32.3012161255],"type":"Point"}
}