{
  "type": "Feature",
  "properties": {
    "addr:full":"400 Maroondah Hwy Ringwood East VIC 3135",
    "addr:housenumber":"400",
    "addr:postcode":"3135",
    "addr:street":"Maroondah Hwy",
    "iso:country":"AU",
    "sg:address":"400 Maroondah Hwy",
    "sg:city":"Ringwood East",
    "sg:classifiers":[
        {
            "category":"Personal",
            "subcategory":"Massage",
            "type":"Services"
        }
    ],
    "sg:phone":"+61 3 9876 8566",
    "sg:postcode":"3135",
    "sg:province":"VIC",
    "sg:tags":[
        "therapy"
    ],
    "wof:name":"Lavender Cottage",
    "wof:placetype":"venue"
},
  "geometry": {"coordinates":[145.25227355999999,-37.79945755],"type":"Point"}
}