{
  "type": "Feature",
  "properties": {
    "addr:full":"179 Claisebrook Rd Perth WA 6000",
    "addr:housenumber":"179",
    "addr:postcode":"6000",
    "addr:street":"Claisebrook Rd",
    "iso:country":"AU",
    "sg:address":"179 Claisebrook Rd",
    "sg:city":"Perth",
    "sg:classifiers":[
        {
            "category":"Utilities",
            "subcategory":"Electric",
            "type":"Services"
        }
    ],
    "sg:phone":"+61 8 9328 9144",
    "sg:postcode":"6000",
    "sg:province":"WA",
    "sg:tags":[
        "electrical",
        "contractor"
    ],
    "wof:name":"Brear & Doonan 1992 Pty Ltd",
    "wof:placetype":"venue"
},
  "geometry": {"coordinates":[115.873222351,-31.9460201263],"type":"Point"}
}