{
  "type": "Feature",
  "properties": {
    "iso:country":"AU",
    "sg:address":"Cnr Dunbar Rd & Rose Ave",
    "sg:city":"Traralgon",
    "sg:classifiers":[
        {
            "category":"Sports & Exercise",
            "subcategory":"Gym",
            "type":"Entertainment"
        }
    ],
    "sg:phone":"+61 3 5176 2852",
    "sg:postcode":"3844",
    "sg:province":"VIC",
    "sg:tags":[
        "health",
        "fitness"
    ],
    "wof:name":"Ezy Trim Traralgon",
    "wof:placetype":"venue"
},
  "geometry": {"coordinates":[146.53057861299999,-38.2071228027],"type":"Point"}
}