{
  "type": "Feature",
  "properties": {
    "addr:full":"Institute Rd Montacute SA 5134",
    "addr:postcode":"5134",
    "addr:street":"Institute Rd",
    "iso:country":"AU",
    "sg:address":"Institute Rd",
    "sg:city":"Montacute",
    "sg:classifiers":[
        {
            "category":"Railroad",
            "type":"Transportation"
        }
    ],
    "sg:phone":"+61 8 8365 4844",
    "sg:postcode":"5134",
    "sg:province":"SA",
    "sg:tags":[
        "equipment",
        "railway",
        "construction",
        "material"
    ],
    "wof:name":"Rexlok Pty Ltd",
    "wof:placetype":"venue"
},
  "geometry": {"coordinates":[138.741912842,-34.8895187378],"type":"Point"}
}