{
  "type": "Feature",
  "properties": {
    "iso:country":"AU",
    "sg:address":"20 Yurong St",
    "sg:city":"East Sydney",
    "sg:classifiers":[
        {
            "category":"Travel",
            "subcategory":"Hotels & Motels",
            "type":"Entertainment"
        }
    ],
    "sg:phone":"+61 2 9380 5537",
    "sg:postcode":"2010",
    "sg:province":"NSW",
    "sg:tags":[
        "accommodation"
    ],
    "wof:name":"Museum Lodge",
    "wof:placetype":"venue"
},
  "geometry": {"coordinates":[151.214477539,-33.8746337891],"type":"Point"}
}