{
  "type": "Feature",
  "properties": {
    "addr:full":"Unit 4/ 172 Evans Rd Salisbury QLD 4107",
    "addr:housenumber":"/ 172",
    "addr:postcode":"4107",
    "addr:street":"Evans Rd",
    "iso:country":"AU",
    "sg:address":"Unit 4/ 172 Evans Rd",
    "sg:city":"Salisbury",
    "sg:classifiers":[
        {
            "category":"Professional",
            "subcategory":"Employment Agencies",
            "type":"Services"
        }
    ],
    "sg:phone":"+61 7 3272 9466",
    "sg:postcode":"4107",
    "sg:province":"QLD",
    "wof:name":"Catalyst Recruitment Systems Ltd",
    "wof:placetype":"venue"
},
  "geometry": {"coordinates":[153.02981567399999,-27.5446567535],"type":"Point"}
}