{
  "type": "Feature",
  "properties": {
    "iso:country":"AU",
    "sg:address":"33 Watland St",
    "sg:city":"Springwood",
    "sg:classifiers":[
        {
            "category":"Retail",
            "subcategory":"Auto Repair",
            "type":"Services"
        }
    ],
    "sg:phone":"+61 7 3808 4299",
    "sg:postcode":"4127",
    "sg:province":"QLD",
    "sg:tags":[
        "repairer",
        "motor",
        "engineer"
    ],
    "wof:name":"Springwood Complete Automotive Services",
    "wof:placetype":"venue"
},
  "geometry": {"coordinates":[153.13276672399999,-27.6251163483],"type":"Point"}
}