{
  "type": "Feature",
  "properties": {
    "addr:full":"17-19 Albion St Warwick QLD 4370",
    "addr:housenumber":"17-19",
    "addr:postcode":"4370",
    "addr:street":"Albion St",
    "iso:country":"AU",
    "sg:address":"17-19 Albion St",
    "sg:city":"Warwick",
    "sg:classifiers":[
        {
            "category":"Travel",
            "subcategory":"Hotels & Motels",
            "type":"Entertainment"
        }
    ],
    "sg:phone":"+61 7 4660 5600",
    "sg:postcode":"4370",
    "sg:province":"QLD",
    "wof:name":"Warwick Motor Inn",
    "wof:placetype":"venue"
},
  "geometry": {"coordinates":[152.035766602,-28.2111968994],"type":"Point"}
}