{
  "type": "Feature",
  "properties": {
    "addr:full":"Unit 3/ 13 Hunter St Hornsby NSW 2077",
    "addr:housenumber":"13",
    "addr:postcode":"2077",
    "addr:street":"Hunter St",
    "iso:country":"AU",
    "sg:address":"Unit 3/ 13 Hunter St",
    "sg:city":"Hornsby",
    "sg:classifiers":[
        {
            "category":"Retail",
            "subcategory":"Repair Shop",
            "type":"Services"
        }
    ],
    "sg:phone":"+61 2 9477 6811",
    "sg:postcode":"2077",
    "sg:province":"NSW",
    "sg:tags":[
        "machine",
        "repairs",
        "part",
        "dryer",
        "washing"
    ],
    "wof:name":"Homesure & Direct Appliance Services",
    "wof:placetype":"venue"
},
  "geometry": {"coordinates":[151.10096740700001,-33.6988945007],"type":"Point"}
}