{
  "type": "Feature",
  "properties": {
    "iso:country":"AU",
    "sg:address":"Cnr Old Burleigh Rd & Charles Ave",
    "sg:city":"Broadbeach",
    "sg:classifiers":[
        {
            "category":"Travel",
            "subcategory":"Hotels & Motels",
            "type":"Entertainment"
        }
    ],
    "sg:phone":"+61 7 5538 4111",
    "sg:postcode":"4218",
    "sg:province":"QLD",
    "sg:tags":[
        "accommodation"
    ],
    "wof:name":"Broadbeach Tavern",
    "wof:placetype":"venue"
},
  "geometry": {"coordinates":[153.433425903,-28.0256958008],"type":"Point"}
}