{
  "type": "Feature",
  "properties": {
    "addr:full":"567 Lower North East Rd Campbelltown SA 5074",
    "addr:housenumber":"567",
    "addr:postcode":"5074",
    "addr:street":"Lower North East Rd",
    "iso:country":"AU",
    "sg:address":"567 Lower North East Rd",
    "sg:city":"Campbelltown",
    "sg:classifiers":[
        {
            "category":"Health Services",
            "subcategory":"Doctor",
            "type":"Services"
        }
    ],
    "sg:phone":"+61 8 8337 1849",
    "sg:postcode":"5074",
    "sg:province":"SA",
    "sg:tags":[
        "medical",
        "practitioner"
    ],
    "wof:name":"North Eastern Medical Clinic",
    "wof:placetype":"venue"
},
  "geometry": {"coordinates":[138.66177368199999,-34.8807830811],"type":"Point"}
}