{
  "type": "Feature",
  "properties": {
    "iso:country":"AU",
    "sg:address":"39 Lemon Ave",
    "sg:city":"Mildura",
    "sg:classifiers":[
        {
            "category":"Education",
            "subcategory":"University",
            "type":"Public Place"
        }
    ],
    "sg:phone":"+61 3 5022 1330",
    "sg:postcode":"3500",
    "sg:province":"VIC",
    "sg:tags":[
        "educational",
        "organisation",
        "cultural"
    ],
    "wof:name":"Sunraysia Contemporary Alevi Cultural Centre",
    "wof:placetype":"venue"
},
  "geometry": {"coordinates":[142.16580200199999,-34.1873664856],"type":"Point"}
}