{
  "type": "Feature",
  "properties": {
    "addr:full":"1 Ace Crs Tuggerah NSW 2259",
    "addr:housenumber":"1",
    "addr:postcode":"2259",
    "addr:street":"Ace Crs",
    "iso:country":"AU",
    "sg:address":"1 Ace Crs",
    "sg:city":"Tuggerah",
    "sg:classifiers":[
        {
            "category":"Professional",
            "subcategory":"Accounting & Tax Preparation",
            "type":"Services"
        }
    ],
    "sg:phone":"+61 2 4353 4599",
    "sg:postcode":"2259",
    "sg:province":"NSW",
    "sg:tags":[
        "jukebox"
    ],
    "sg:website":"http://www.prestigepartyhire.com.au",
    "wof:name":"Prestige Party Hire",
    "wof:placetype":"venue"
},
  "geometry": {"coordinates":[151.420410156,-33.3050003052],"type":"Point"}
}