{
  "type": "Feature",
  "properties": {
    "iso:country":"AU",
    "sg:address":"117 Croydon St",
    "sg:city":"Cronulla",
    "sg:classifiers":[
        {
            "category":"Personal",
            "subcategory":"Beauty Salon",
            "type":"Services"
        }
    ],
    "sg:phone":"+61 2 9523 7219",
    "sg:postcode":"2230",
    "sg:province":"NSW",
    "sg:tags":[
        "hairdresser"
    ],
    "wof:name":"D N Hair Studio",
    "wof:placetype":"venue"
},
  "geometry": {"coordinates":[151.15150451700001,-34.0551643372],"type":"Point"}
}