{
  "type": "Feature",
  "properties": {
    "addr:full":"142 Tynte St North Adelaide SA 5006",
    "addr:housenumber":"142",
    "addr:postcode":"5006",
    "addr:street":"Tynte St",
    "iso:country":"AU",
    "sg:address":"142 Tynte St",
    "sg:city":"North Adelaide",
    "sg:classifiers":[
        {
            "category":"Restaurant",
            "type":"Food & Drink"
        }
    ],
    "sg:phone":"+61 8 8267 4636",
    "sg:postcode":"5006",
    "sg:province":"SA",
    "sg:website":"http://www.manserestaurant.com.au",
    "wof:name":"The Manse Restaurant",
    "wof:placetype":"venue"
},
  "geometry": {"coordinates":[138.59487915,-34.9060707092],"type":"Point"}
}