{
  "type": "Feature",
  "properties": {
    "iso:country":"AU",
    "sg:address":"Cnr Peachey & Westport Rds",
    "sg:city":"Elizabeth West",
    "sg:classifiers":[
        {
            "category":"Fast Food",
            "type":"Food & Drink"
        }
    ],
    "sg:phone":"+61 8 8255 6189",
    "sg:postcode":"5113",
    "sg:province":"SA",
    "sg:tags":[
        "away",
        "take"
    ],
    "wof:name":"Aussie Fare",
    "wof:placetype":"venue"
},
  "geometry": {"coordinates":[138.66395568900001,-34.7029953003],"type":"Point"}
}