{
  "type": "Feature",
  "properties": {
    "addr:full":"421 Port Rd Croydon SA 5008",
    "addr:housenumber":"421",
    "addr:postcode":"5008",
    "addr:street":"Port Rd",
    "iso:country":"AU",
    "sg:address":"421 Port Rd",
    "sg:city":"Croydon",
    "sg:classifiers":[
        {
            "category":"Health Services",
            "subcategory":"Doctor",
            "type":"Services"
        }
    ],
    "sg:phone":"+61 8 8346 6408",
    "sg:postcode":"5008",
    "sg:province":"SA",
    "sg:tags":[
        "medical",
        "practitioner"
    ],
    "wof:name":"Katsaneris Con Dr",
    "wof:placetype":"venue"
},
  "geometry": {"coordinates":[138.56471300000001,-34.899967],"type":"Point"}
}