{
  "type": "Feature",
  "properties": {
    "addr:full":"Farm 1434 Bridge Rd Griffith NSW 2680",
    "addr:housenumber":"1434",
    "addr:postcode":"2680",
    "addr:street":"Bridge Rd",
    "iso:country":"AU",
    "sg:address":"Farm 1434 Bridge Rd",
    "sg:city":"Griffith",
    "sg:classifiers":[
        {
            "category":"Arts & Performance",
            "subcategory":"Art Gallery",
            "type":"Entertainment"
        }
    ],
    "sg:phone":"+61 2 6962 5512",
    "sg:postcode":"2680",
    "sg:province":"NSW",
    "wof:name":"Griffith Cottage Gallery",
    "wof:placetype":"venue"
},
  "geometry": {"coordinates":[146.05079699999999,-34.291828],"type":"Point"}
}