{
  "type": "Feature",
  "properties": {
    "addr:full":"17 Victoria St Paynesville VIC 3880",
    "addr:housenumber":"17",
    "addr:postcode":"3880",
    "addr:street":"Victoria St",
    "iso:country":"AU",
    "sg:address":"17 Victoria St",
    "sg:city":"Paynesville",
    "sg:classifiers":[
        {
            "category":"Real Estate",
            "subcategory":"Real Estate Agent",
            "type":"Services"
        }
    ],
    "sg:phone":"+61 3 5156 0105",
    "sg:postcode":"3880",
    "sg:province":"VIC",
    "wof:name":"Ann Waller Real Estate",
    "wof:placetype":"venue"
},
  "geometry": {"coordinates":[147.72515869099999,-37.9175453186],"type":"Point"}
}