{
  "type": "Feature",
  "properties": {
    "iso:country":"AU",
    "sg:address":"King Arcade, 22- 26 King St",
    "sg:city":"Grafton",
    "sg:classifiers":[
        {
            "category":"Professional",
            "subcategory":"Accounting & Tax Preparation",
            "type":"Services"
        }
    ],
    "sg:phone":"+61 2 6642 7943",
    "sg:postcode":"2460",
    "sg:province":"NSW",
    "sg:tags":[
        "consultant",
        "taxation"
    ],
    "wof:name":"H&R Block",
    "wof:placetype":"venue"
},
  "geometry": {"coordinates":[152.93307495100001,-29.6895503998],"type":"Point"}
}