{
  "type": "Feature",
  "properties": {
    "iso:country":"AU",
    "sg:address":"841 Doncaster Rd",
    "sg:city":"Doncaster",
    "sg:classifiers":[
        {
            "category":"Shopping",
            "subcategory":"Mobile Phones",
            "type":"Retail Goods"
        }
    ],
    "sg:phone":"+61 3 9840 6955",
    "sg:postcode":"3108",
    "sg:province":"VIC",
    "sg:tags":[
        "telephone",
        "accessory"
    ],
    "wof:name":"Phone World (Aust) P/L",
    "wof:placetype":"venue"
},
  "geometry": {"coordinates":[145.14227294899999,-37.7866325378],"type":"Point"}
}