{
  "type": "Feature",
  "properties": {
    "iso:country":"AU",
    "sg:address":"2 Henricks St",
    "sg:city":"Hemmant",
    "sg:classifiers":[
        {
            "category":"Utilities",
            "subcategory":"Natural Gas",
            "type":"Services"
        }
    ],
    "sg:phone":"+61 7 3348 8044",
    "sg:postcode":"4174",
    "sg:province":"QLD",
    "sg:tags":[
        "supplier"
    ],
    "wof:name":"Maxitherm",
    "wof:placetype":"venue"
},
  "geometry": {"coordinates":[153.12362670900001,-27.445142746],"type":"Point"}
}