{
  "type": "Feature",
  "properties": {
    "addr:full":"14 Palmer St Katherine NT 0850",
    "addr:housenumber":"14",
    "addr:postcode":"nt 0850",
    "addr:street":"Palmer St",
    "iso:country":"AU",
    "sg:address":"14 Palmer St",
    "sg:city":"Katherine",
    "sg:classifiers":[
        {
            "category":"Banks & Credit Unions",
            "subcategory":"Financial Services",
            "type":"Services"
        }
    ],
    "sg:phone":"+61 8 8972 3144",
    "sg:postcode":"0850",
    "sg:province":"NT",
    "sg:tags":[
        "equipment",
        "chain"
    ],
    "wof:name":"Mac's Hire Service",
    "wof:placetype":"venue"
},
  "geometry": {"coordinates":[132.29016100000001,-14.477104],"type":"Point"}
}