{
  "type": "Feature",
  "properties": {
    "iso:country":"AU",
    "sg:address":"Barossa Valley Way",
    "sg:city":"Tanunda",
    "sg:classifiers":[
        {
            "category":"Professional",
            "subcategory":"Accounting & Tax Preparation",
            "type":"Services"
        }
    ],
    "sg:phone":"+61 8 8563 2620",
    "sg:postcode":"5352",
    "sg:province":"SA",
    "sg:tags":[
        "consultant",
        "taxation"
    ],
    "wof:name":"How's Business? Pty Ltd",
    "wof:placetype":"venue"
},
  "geometry": {"coordinates":[138.97286987300001,-34.5138664246],"type":"Point"}
}