{
  "type": "Feature",
  "properties": {
    "addr:full":"157 Old Pacific Hwy Oxenford QLD 4210",
    "addr:housenumber":"157",
    "addr:postcode":"4210",
    "addr:street":"Old Pacific Hwy",
    "iso:country":"AU",
    "sg:address":"157 Old Pacific Hwy",
    "sg:city":"Oxenford",
    "sg:classifiers":[
        {
            "category":"Retail",
            "subcategory":"Auto Repair",
            "type":"Services"
        }
    ],
    "sg:phone":"+61 7 5573 3000",
    "sg:postcode":"4210",
    "sg:province":"QLD",
    "sg:tags":[
        "bus",
        "truck"
    ],
    "wof:name":"Coomera River Smash Repairs",
    "wof:placetype":"venue"
},
  "geometry": {"coordinates":[153.31350707999999,-27.8899765015],"type":"Point"}
}