{
  "type": "Feature",
  "properties": {
    "addr:full":"36 Lancaster St Ingleburn NSW 2565",
    "addr:housenumber":"36",
    "addr:postcode":"2565",
    "addr:street":"Lancaster St",
    "iso:country":"AU",
    "sg:address":"36 Lancaster St",
    "sg:city":"Ingleburn",
    "sg:classifiers":[
        {
            "category":"Manufacturing",
            "subcategory":"Motor Vehicles & Parts",
            "type":"Manufacturing & Wholesale Goods"
        }
    ],
    "sg:phone":"+61 2 9605 9977",
    "sg:postcode":"2565",
    "sg:province":"NSW",
    "sg:tags":[
        "replacement"
    ],
    "wof:name":"Bumpers Wholesale Pty Ltd",
    "wof:placetype":"venue"
},
  "geometry": {"coordinates":[150.860595703,-33.9953994751],"type":"Point"}
}