{
  "type": "Feature",
  "properties": {
    "addr:full":"624 Mountain Hwy Bayswater VIC 3153",
    "addr:housenumber":"624",
    "addr:postcode":"3153",
    "addr:street":"Mountain Hwy",
    "iso:country":"AU",
    "sg:address":"624 Mountain Hwy",
    "sg:city":"Bayswater",
    "sg:classifiers":[
        {
            "category":"Food & Beverages",
            "subcategory":"Bakery",
            "type":"Retail Goods"
        }
    ],
    "sg:phone":"+61 3 9720 8202",
    "sg:postcode":"3153",
    "sg:province":"VIC",
    "sg:tags":[
        "baker"
    ],
    "wof:name":"Okka Pies",
    "wof:placetype":"venue"
},
  "geometry": {"coordinates":[145.257568359,-37.8424224854],"type":"Point"}
}