{
  "type": "Feature",
  "properties": {
    "addr:full":"17 Collingwood St Sandringham VIC 3191",
    "addr:housenumber":"17",
    "addr:postcode":"3191",
    "addr:street":"Collingwood St",
    "iso:country":"AU",
    "sg:address":"17 Collingwood St",
    "sg:city":"Sandringham",
    "sg:classifiers":[
        {
            "category":"Building & Trades",
            "subcategory":"Plumbing",
            "type":"Services"
        }
    ],
    "sg:phone":"+61 3 9598 5140",
    "sg:postcode":"3191",
    "sg:province":"VIC",
    "sg:tags":[
        "plumber",
        "gasfitters"
    ],
    "wof:name":"Twin Power Plumbing",
    "wof:placetype":"venue"
},
  "geometry": {"coordinates":[145.01229858400001,-37.9515075684],"type":"Point"}
}