{
  "type": "Feature",
  "properties": {
    "iso:country":"AU",
    "sg:address":"PO Box 888",
    "sg:city":"Port Pirie",
    "sg:classifiers":[
        {
            "category":"Communications",
            "type":"Services"
        }
    ],
    "sg:phone":"+61 8 8633 1230",
    "sg:postcode":"5540",
    "sg:province":"SA",
    "sg:tags":[
        "public",
        "system",
        "address"
    ],
    "wof:name":"Special Event Broadcasters",
    "wof:placetype":"venue"
},
  "geometry": {"coordinates":[138.00396728499999,-33.1668281555],"type":"Point"}
}