{
  "type": "Feature",
  "properties": {
    "addr:full":"82 Horne St Campbellfield VIC 3061",
    "addr:housenumber":"82",
    "addr:postcode":"3061",
    "addr:street":"Horne St",
    "iso:country":"AU",
    "sg:address":"82 Horne St",
    "sg:city":"Campbellfield",
    "sg:classifiers":[
        {
            "category":"Fast Food",
            "type":"Food & Drink"
        }
    ],
    "sg:phone":"+61 3 9359 1497",
    "sg:postcode":"3061",
    "sg:province":"VIC",
    "sg:tags":[
        "away",
        "take"
    ],
    "wof:name":"Lunch Box Campbellfield",
    "wof:placetype":"venue"
},
  "geometry": {"coordinates":[144.96478271500001,-37.6803359985],"type":"Point"}
}