{
  "type": "Feature",
  "properties": {
    "iso:country":"AU",
    "sg:address":"2 Cherry St",
    "sg:city":"Oakey",
    "sg:classifiers":[
        {
            "category":"Health Services",
            "subcategory":"Dentist",
            "type":"Services"
        }
    ],
    "sg:phone":"+61 7 4691 1513",
    "sg:postcode":"4401",
    "sg:province":"QLD",
    "wof:name":"Bernard Kunde",
    "wof:placetype":"venue"
},
  "geometry": {"coordinates":[151.716506958,-27.4325275421],"type":"Point"}
}