{
  "type": "Feature",
  "properties": {
    "addr:full":"11 Garrick St Jundah via Longreach Jundah QLD 4736",
    "addr:housenumber":"11",
    "addr:postcode":"4736",
    "addr:street":"Garrick St Jundah Via Longreach",
    "iso:country":"AU",
    "sg:address":"11 Garrick St Jundah via Longreach",
    "sg:city":"Jundah",
    "sg:classifiers":[
        {
            "category":"Education",
            "subcategory":"School",
            "type":"Public Place"
        }
    ],
    "sg:phone":"+61 7 4658 6121",
    "sg:postcode":"4736",
    "sg:province":"QLD",
    "sg:tags":[
        "state",
        "except",
        "nsw"
    ],
    "wof:name":"Jundah Primary School",
    "wof:placetype":"venue"
},
  "geometry": {"coordinates":[143.06106600000001,-24.833969],"type":"Point"}
}