{
  "type": "Feature",
  "properties": {
    "iso:country":"AU",
    "sg:address":"11 Garrick St Jundah via Longreach",
    "sg:city":"Jundah",
    "sg:classifiers":[
        {
            "category":"Education",
            "subcategory":"School",
            "type":"Public Place"
        }
    ],
    "sg:phone":"+61 7 4658 6121",
    "sg:postcode":"4736",
    "sg:province":"QLD",
    "sg:tags":[
        "state",
        "except",
        "nsw"
    ],
    "wof:name":"Jundah Primary School",
    "wof:placetype":"venue"
},
  "geometry": {"coordinates":[143.061066,-24.833969],"type":"Point"}
}