{
  "type": "Feature",
  "properties": {
    "addr:full":"Shop 6 125 Beach Rd Christies Beach SA 5165",
    "addr:housenumber":"shop 6 125",
    "addr:postcode":"5165",
    "addr:street":"Beach Rd",
    "iso:country":"AU",
    "sg:address":"Shop 6 125 Beach Rd",
    "sg:city":"Christies Beach",
    "sg:classifiers":[
        {
            "category":"Shopping",
            "subcategory":"Discount & Variety Stores",
            "type":"Retail Goods"
        }
    ],
    "sg:phone":"+61 8 8384 4447",
    "sg:postcode":"5165",
    "sg:province":"SA",
    "sg:tags":[
        "shop",
        "adult"
    ],
    "wof:name":"Eros Nightstyle",
    "wof:placetype":"venue"
},
  "geometry": {"coordinates":[138.483444214,-35.1386604309],"type":"Point"}
}