{
  "type": "Feature",
  "properties": {
    "iso:country":"AU",
    "sg:address":"61 Scott St",
    "sg:city":"Newcastle",
    "sg:classifiers":[
        {
            "category":"Organizations",
            "subcategory":"Community Association",
            "type":"Services"
        }
    ],
    "sg:phone":"+61 2 4926 4161",
    "sg:postcode":"2300",
    "sg:province":"NSW",
    "sg:tags":[
        "organisation",
        "family",
        "welfare"
    ],
    "wof:name":"Newcastle Temporary Care Ltd",
    "wof:placetype":"venue"
},
  "geometry": {"coordinates":[151.787125,-32.927494],"type":"Point"}
}