{
  "type": "Feature",
  "properties": {
    "addr:full":"3 St Kilda Rd St Kilda VIC 3182",
    "addr:housenumber":"3",
    "addr:postcode":"3182",
    "addr:street":"St Kilda Rd",
    "iso:country":"AU",
    "sg:address":"3 St Kilda Rd",
    "sg:city":"St Kilda",
    "sg:classifiers":[
        {
            "category":"Real Estate",
            "subcategory":"Developer",
            "type":"Services"
        }
    ],
    "sg:phone":"+61 3 9525 4333",
    "sg:postcode":"3182",
    "sg:province":"VIC",
    "sg:tags":[
        "development"
    ],
    "wof:name":"Assetta Group Pty Ltd",
    "wof:placetype":"venue"
},
  "geometry": {"coordinates":[144.98320007300001,-37.8583602905],"type":"Point"}
}