{
  "type": "Feature",
  "properties": {
    "iso:country":"AU",
    "sg:address":"Jordan St",
    "sg:city":"Waterford",
    "sg:classifiers":[
        {
            "category":"Education",
            "subcategory":"School",
            "type":"Public Place"
        }
    ],
    "sg:phone":"+61 7 3451 8235",
    "sg:postcode":"4133",
    "sg:province":"QLD",
    "sg:tags":[
        "state",
        "except",
        "nsw"
    ],
    "wof:name":"Waterford Preschool",
    "wof:placetype":"venue"
},
  "geometry": {"coordinates":[153.143997192,-27.6971530914],"type":"Point"}
}