{
  "type": "Feature",
  "properties": {
    "addr:full":"10 Gipps St Bradbury NSW 2560",
    "addr:housenumber":"10",
    "addr:postcode":"2560",
    "addr:street":"Gipps St",
    "iso:country":"AU",
    "sg:address":"10 Gipps St",
    "sg:city":"Bradbury",
    "sg:classifiers":[
        {
            "category":"Building & Trades",
            "subcategory":"Pest Control",
            "type":"Services"
        }
    ],
    "sg:phone":"+61 404 815 865",
    "sg:postcode":"2560",
    "sg:province":"NSW",
    "wof:name":"Live No More Pest Control",
    "wof:placetype":"venue"
},
  "geometry": {"coordinates":[150.81829834000001,-34.088218689],"type":"Point"}
}