{
  "type": "Feature",
  "properties": {
    "addr:full":"Fcty4/ 283 Rex Rd Campbellfield VIC 3061",
    "addr:postcode":"3061",
    "addr:street":"Rex Rd",
    "iso:country":"AU",
    "sg:address":"Fcty4/ 283 Rex Rd",
    "sg:city":"Campbellfield",
    "sg:classifiers":[
        {
            "category":"Cafe",
            "type":"Food & Drink"
        }
    ],
    "sg:phone":"+61 3 8339 0123",
    "sg:postcode":"3061",
    "sg:province":"VIC",
    "wof:name":"Kalevu Cafe",
    "wof:placetype":"venue"
},
  "geometry": {"coordinates":[144.96290588400001,-37.6467971802],"type":"Point"}
}