{
  "type": "Feature",
  "properties": {
    "addr:full":"Suite 103/ 283 Alfred St North Sydney NSW 2060",
    "addr:housenumber":"/ 283",
    "addr:postcode":"2060",
    "addr:street":"Alfred St",
    "iso:country":"AU",
    "sg:address":"Suite 103/ 283 Alfred St",
    "sg:city":"North Sydney",
    "sg:classifiers":[
        {
            "category":"Health Services",
            "subcategory":"Doctor",
            "type":"Services"
        }
    ],
    "sg:phone":"+61 1300 304 068",
    "sg:postcode":"2060",
    "sg:province":"NSW",
    "sg:tags":[
        "occupational",
        "safety"
    ],
    "sg:website":"http://www.healthbydesign.com.au",
    "wof:name":"Health By Design",
    "wof:placetype":"venue"
},
  "geometry": {"coordinates":[151.21136474599999,-33.8400726318],"type":"Point"}
}