{
  "type": "Feature",
  "properties": {
    "addr:full":"125 Walker Rd Serpentine WA 6125",
    "addr:housenumber":"125",
    "addr:postcode":"6125",
    "addr:street":"Walker Rd",
    "iso:country":"AU",
    "sg:address":"125 Walker Rd",
    "sg:city":"Serpentine",
    "sg:classifiers":[
        {
            "category":"Home & Garden",
            "subcategory":"Garden Supply",
            "type":"Retail Goods"
        }
    ],
    "sg:phone":"+61 8 9525 2922",
    "sg:postcode":"6125",
    "sg:province":"WA",
    "sg:tags":[
        "landscape"
    ],
    "wof:name":"Serpentine Landscape Supplies",
    "wof:placetype":"venue"
},
  "geometry": {"coordinates":[115.96085357699999,-32.3710289001],"type":"Point"}
}