{
  "type": "Feature",
  "properties": {
    "addr:full":"168 Argent St Broken Hill NSW 2880",
    "addr:housenumber":"168",
    "addr:postcode":"2880",
    "addr:street":"Argent St",
    "iso:country":"AU",
    "sg:address":"168 Argent St",
    "sg:city":"Broken Hill",
    "sg:classifiers":[
        {
            "category":"Organizations",
            "subcategory":"Professional Association",
            "type":"Services"
        }
    ],
    "sg:phone":"+61 8 8087 2236",
    "sg:postcode":"2880",
    "sg:province":"NSW",
    "sg:tags":[
        "organisation",
        "business"
    ],
    "wof:name":"Broken Hill Chamber Of Commerce",
    "wof:placetype":"venue"
},
  "geometry": {"coordinates":[141.462036133,-31.9603214264],"type":"Point"}
}