{
  "type": "Feature",
  "properties": {
    "addr:full":"497 Victoria Rd Gladesville NSW 2111",
    "addr:housenumber":"497",
    "addr:postcode":"2111",
    "addr:street":"Victoria Rd",
    "iso:country":"AU",
    "sg:address":"497 Victoria Rd",
    "sg:city":"Gladesville",
    "sg:classifiers":[
        {
            "category":"Retail",
            "subcategory":"Storage",
            "type":"Services"
        }
    ],
    "sg:phone":"+61 2 9816 4988",
    "sg:postcode":"2111",
    "sg:province":"NSW",
    "wof:name":"Kennards Self Storage",
    "wof:placetype":"venue"
},
  "geometry": {"coordinates":[151.11964416500001,-33.8207931519],"type":"Point"}
}