{
  "type": "Feature",
  "properties": {
    "iso:country":"AU",
    "sg:address":"11 Norton St",
    "sg:city":"Ballina",
    "sg:classifiers":[
        {
            "category":"Health Services",
            "subcategory":"Health Practitioner",
            "type":"Services"
        }
    ],
    "sg:phone":"+61 2 6686 3360",
    "sg:postcode":"2478",
    "sg:province":"NSW",
    "sg:tags":[
        "acupuncture"
    ],
    "wof:name":"Graham, Tony",
    "wof:placetype":"venue"
},
  "geometry": {"coordinates":[153.550857544,-28.8660736084],"type":"Point"}
}