{
  "type": "Feature",
  "properties": {
    "iso:country":"AU",
    "sg:address":"50 Hensman St",
    "sg:city":"South Perth",
    "sg:classifiers":[
        {
            "category":"Professional",
            "subcategory":"Art Services",
            "type":"Services"
        }
    ],
    "sg:phone":"+61 8 9368 2804",
    "sg:postcode":"6151",
    "sg:province":"WA",
    "sg:tags":[
        "interior",
        "designer"
    ],
    "wof:name":"Caldecott Richard",
    "wof:placetype":"venue"
},
  "geometry": {"coordinates":[115.86215199999999,-31.984419],"type":"Point"}
}