{
  "type": "Feature",
  "properties": {
    "addr:full":"7 St Johns Ave Gordon NSW 2072",
    "addr:housenumber":"7",
    "addr:postcode":"2072",
    "addr:street":"St Johns Ave",
    "iso:country":"AU",
    "sg:address":"7 St Johns Ave",
    "sg:city":"Gordon",
    "sg:classifiers":[
        {
            "category":"Personal",
            "subcategory":"Shoe Repair & Shine",
            "type":"Services"
        }
    ],
    "sg:phone":"+61 2 9498 3056",
    "sg:postcode":"2072",
    "sg:province":"NSW",
    "sg:tags":[
        "footwear"
    ],
    "wof:name":"Scardino T",
    "wof:placetype":"venue"
},
  "geometry": {"coordinates":[151.153686523,-33.7561454773],"type":"Point"}
}