{
  "type": "Feature",
  "properties": {
    "addr:full":"Eleven Mile Drv Eglinton NSW 2795",
    "addr:postcode":"2795",
    "addr:street":"Eleven Mile Drv",
    "iso:country":"AU",
    "sg:address":"Eleven Mile Drv",
    "sg:city":"Eglinton",
    "sg:classifiers":[
        {
            "category":"Commercial Area",
            "type":"Public Place"
        }
    ],
    "sg:phone":"+61 2 6337 1655",
    "sg:postcode":"2795",
    "sg:province":"NSW",
    "sg:tags":[
        "heavy",
        "carrier"
    ],
    "wof:name":"Stevens J R & C Transport",
    "wof:placetype":"venue"
},
  "geometry": {"coordinates":[149.55201721200001,-33.3740386963],"type":"Point"}
}