{
  "type": "Feature",
  "properties": {
    "iso:country":"AU",
    "sg:address":"24 Killawarra Rd",
    "sg:city":"Ashgrove",
    "sg:classifiers":[
        {
            "category":"Professional",
            "subcategory":"Management & Consulting",
            "type":"Services"
        }
    ],
    "sg:phone":"+61 419 667 151",
    "sg:postcode":"4060",
    "sg:province":"QLD",
    "sg:tags":[
        "consultant",
        "educational"
    ],
    "wof:name":"GAMSAT Preparation Courses",
    "wof:placetype":"venue"
},
  "geometry": {"coordinates":[152.98330688499999,-27.446231842],"type":"Point"}
}