{
  "type": "Feature",
  "properties": {
    "addr:full":"9 Sunshine Beach Rd Noosa Heads QLD 4567",
    "addr:housenumber":"9",
    "addr:postcode":"4567",
    "addr:street":"Sunshine Beach Rd",
    "iso:country":"AU",
    "sg:address":"9 Sunshine Beach Rd",
    "sg:city":"Noosa Heads",
    "sg:classifiers":[
        {
            "category":"Internet Cafe",
            "subcategory":"None",
            "type":"Food & Drink"
        }
    ],
    "sg:phone":"+61 7 5474 8530",
    "sg:postcode":"4567",
    "sg:province":"QLD",
    "wof:name":"Adventure Travel Bugs",
    "wof:placetype":"venue"
},
  "geometry": {"coordinates":[153.09146118199999,-26.3977680206],"type":"Point"}
}