{
  "type": "Feature",
  "properties": {
    "addr:full":"Unit 10, 17 Tile St Wacol QLD 4076",
    "addr:housenumber":"17",
    "addr:postcode":"4076",
    "addr:street":"Tile St",
    "iso:country":"AU",
    "sg:address":"Unit 10, 17 Tile St",
    "sg:city":"Wacol",
    "sg:classifiers":[
        {
            "category":"Wholesale",
            "subcategory":"Machinery & Supplies",
            "type":"Manufacturing & Wholesale Goods"
        }
    ],
    "sg:phone":"+61 7 3879 3701",
    "sg:postcode":"4076",
    "sg:province":"QLD",
    "sg:tags":[
        "machine",
        "tool",
        "engineer"
    ],
    "wof:name":"Millennium Machining",
    "wof:placetype":"venue"
},
  "geometry": {"coordinates":[152.93252563499999,-27.6040019989],"type":"Point"}
}