{
  "type": "Feature",
  "properties": {
    "addr:full":"39 Douglas St St Ives NSW 2075",
    "addr:housenumber":"39",
    "addr:postcode":"2075",
    "addr:street":"Douglas St",
    "iso:country":"AU",
    "sg:address":"39 Douglas St",
    "sg:city":"St Ives",
    "sg:classifiers":[
        {
            "category":"Building & Trades",
            "subcategory":"Cleaning & Sanitation",
            "type":"Services"
        }
    ],
    "sg:phone":"+61 433 408 918",
    "sg:postcode":"2075",
    "sg:province":"NSW",
    "sg:tags":[
        "wall",
        "brick"
    ],
    "wof:name":"Lilian Brick Cleaning Pyt Ltd",
    "wof:placetype":"venue"
},
  "geometry": {"coordinates":[151.16995239299999,-33.7247123718],"type":"Point"}
}