{
  "type": "Feature",
  "properties": {
    "iso:country":"AU",
    "sg:address":"Stevens St",
    "sg:city":"Yandina",
    "sg:classifiers":[
        {
            "category":"Travel",
            "subcategory":"Hotels & Motels",
            "type":"Entertainment"
        }
    ],
    "sg:phone":"+61 7 5446 7341",
    "sg:postcode":"4561",
    "sg:province":"QLD",
    "sg:tags":[
        "accommodation"
    ],
    "wof:name":"Yandina Hotel",
    "wof:placetype":"venue"
},
  "geometry": {"coordinates":[152.95574951200001,-26.5610656738],"type":"Point"}
}