{
  "type": "Feature",
  "properties": {
    "iso:country":"AU",
    "sg:address":"PO Box 432",
    "sg:city":"Yarra Junction",
    "sg:classifiers":[
        {
            "category":"Utilities",
            "subcategory":"Electric",
            "type":"Services"
        }
    ],
    "sg:phone":"+61 418 103 487",
    "sg:postcode":"3797",
    "sg:province":"VIC",
    "sg:tags":[
        "electrical",
        "contractor"
    ],
    "wof:name":"Valley Electrical & Communications",
    "wof:placetype":"venue"
},
  "geometry": {"coordinates":[145.61239624000001,-37.7815704346],"type":"Point"}
}