{
  "type": "Feature",
  "properties": {
    "addr:full":"Unit 5, 10 Chesapeake Way Currambine WA 6028",
    "addr:housenumber":"10",
    "addr:postcode":"6028",
    "addr:street":"Chesapeake Way",
    "iso:country":"AU",
    "sg:address":"Unit 5, 10",
    "sg:city":"Chesapeake Way Currambine",
    "sg:classifiers":[
        {
            "category":"Health Services",
            "subcategory":"Dentist",
            "type":"Services"
        }
    ],
    "sg:phone":"+61 8 9305 6600",
    "sg:postcode":"6028",
    "sg:province":"WA",
    "wof:name":"Slattery Richard",
    "wof:placetype":"venue"
},
  "geometry": {"coordinates":[115.73815918,-31.7376804352],"type":"Point"}
}