{
  "type": "Feature",
  "properties": {
    "iso:country":"AU",
    "sg:address":"234 St kilda Rd",
    "sg:city":"Southbank",
    "sg:classifiers":[
        {
            "category":"Shopping",
            "subcategory":"Party Supplies",
            "type":"Retail Goods"
        }
    ],
    "sg:phone":"+61 3 9685 9368",
    "sg:postcode":"3006",
    "sg:province":"VIC",
    "sg:tags":[
        "hire",
        "costume"
    ],
    "wof:name":"Victorian College Of Arts Costume Hire",
    "wof:placetype":"venue"
},
  "geometry": {"coordinates":[144.97018432600001,-37.8241958618],"type":"Point"}
}