{
  "type": "Feature",
  "properties": {
    "addr:full":"Shop 4, 2- 4 Beverley Ave Warilla NSW 2528",
    "addr:housenumber":"shop;2 4",
    "addr:postcode":"2528",
    "addr:street":"Beverley Ave",
    "iso:country":"AU",
    "sg:address":"Shop 4, 2- 4 Beverley Ave",
    "sg:city":"Warilla",
    "sg:classifiers":[
        {
            "category":"Manufacturing",
            "subcategory":"Electronics",
            "type":"Manufacturing & Wholesale Goods"
        }
    ],
    "sg:phone":"+61 2 4295 3994",
    "sg:postcode":"2528",
    "sg:province":"NSW",
    "sg:tags":[
        "oven",
        "microwave"
    ],
    "wof:name":"Warilla TV - Video Service",
    "wof:placetype":"venue"
},
  "geometry": {"coordinates":[150.86138915999999,-34.5518455505],"type":"Point"}
}