{
  "type": "Feature",
  "properties": {
    "iso:country":"AU",
    "sg:address":"58 Ebony St",
    "sg:city":"Redlynch",
    "sg:classifiers":[
        {
            "category":"Home & Garden",
            "subcategory":"Carpets & Floor Coverings",
            "type":"Retail Goods"
        }
    ],
    "sg:phone":"+61 407 137 163",
    "sg:postcode":"4870",
    "sg:province":"QLD",
    "sg:tags":[
        "tile",
        "wall"
    ],
    "wof:name":"Slipsafe Tropical North QLD",
    "wof:placetype":"venue"
},
  "geometry": {"coordinates":[145.69236755399999,-16.9059944153],"type":"Point"}
}