{
  "type": "Feature",
  "properties": {
    "iso:country":"AU",
    "sg:address":"1639 Point Nepean Rd",
    "sg:city":"Rosebud West",
    "sg:classifiers":[
        {
            "category":"Health Services",
            "subcategory":"Chiropractor",
            "type":"Services"
        }
    ],
    "sg:phone":"+61 3 5986 5516",
    "sg:postcode":"3940",
    "sg:province":"VIC",
    "wof:name":"Mawby Chiropractic",
    "wof:placetype":"venue"
},
  "geometry": {"coordinates":[144.87597656200001,-38.3637657166],"type":"Point"}
}