{
  "type": "Feature",
  "properties": {
    "addr:full":"Cnr Dunn & Grindle Rds Rocklea QLD 4106",
    "addr:postcode":"4106",
    "iso:country":"AU",
    "sg:address":"Cnr Dunn & Grindle Rds",
    "sg:city":"Rocklea",
    "sg:classifiers":[
        {
            "category":"Home & Garden",
            "subcategory":"Carpets & Floor Coverings",
            "type":"Retail Goods"
        }
    ],
    "sg:phone":"+61 7 3277 0833",
    "sg:postcode":"4106",
    "sg:province":"QLD",
    "sg:tags":[
        "wood"
    ],
    "wof:name":"Gunns Timber",
    "wof:placetype":"venue"
},
  "geometry": {"coordinates":[153.001098633,-27.554775238],"type":"Point"}
}