{
  "type": "Feature",
  "properties": {
    "addr:full":"12a Bushman St Parkes NSW 2870",
    "addr:housenumber":"12a",
    "addr:postcode":"2870",
    "addr:street":"Bushman St",
    "iso:country":"AU",
    "sg:address":"12a Bushman St",
    "sg:city":"Parkes",
    "sg:classifiers":[
        {
            "category":"Retail",
            "subcategory":"Auto Repair",
            "type":"Services"
        }
    ],
    "sg:phone":"+61 2 6862 5999",
    "sg:postcode":"2870",
    "sg:province":"NSW",
    "sg:tags":[
        "clutch",
        "brake"
    ],
    "wof:name":"Idle Rite Mechanical Repairs",
    "wof:placetype":"venue"
},
  "geometry": {"coordinates":[148.17649800000001,-33.133114],"type":"Point"}
}