{
  "type": "Feature",
  "properties": {
    "addr:full":"90 Frankston Gardens Drv Carrum Downs VIC 3201",
    "addr:housenumber":"90",
    "addr:postcode":"3201",
    "addr:street":"Frankston Gardens Drv",
    "iso:country":"AU",
    "sg:address":"90 Frankston Gardens Drv",
    "sg:city":"Carrum Downs",
    "sg:classifiers":[
        {
            "category":"Professional",
            "type":"Services"
        }
    ],
    "sg:phone":"+61 3 9775 0220",
    "sg:postcode":"3201",
    "sg:province":"VIC",
    "sg:tags":[
        "spray",
        "painting"
    ],
    "wof:name":"I.D.C.S Pty Ltd",
    "wof:placetype":"venue"
},
  "geometry": {"coordinates":[145.16021699999999,-38.096214],"type":"Point"}
}