{
  "type": "Feature",
  "properties": {
    "addr:full":"580 St Kilda Rd Melbourne VIC 3001",
    "addr:housenumber":"580",
    "addr:postcode":"3001",
    "addr:street":"St Kilda Rd",
    "iso:country":"AU",
    "sg:address":"580 St Kilda Rd",
    "sg:city":"Melbourne",
    "sg:classifiers":[
        {
            "category":"Professional",
            "subcategory":"Employment Agencies",
            "type":"Services"
        }
    ],
    "sg:phone":"+61 3 9522 2900",
    "sg:postcode":"3001",
    "sg:province":"VIC",
    "sg:tags":[
        "provider",
        "internet"
    ],
    "wof:name":"Web Wombat",
    "wof:placetype":"venue"
},
  "geometry": {"coordinates":[144.97966003400001,-37.8485183716],"type":"Point"}
}