{
  "type": "Feature",
  "properties": {
    "addr:full":"286 Cleveland St Surry Hills NSW 2010",
    "addr:housenumber":"286",
    "addr:postcode":"2010",
    "addr:street":"Cleveland St",
    "iso:country":"AU",
    "sg:address":"286 Cleveland St",
    "sg:city":"Surry Hills",
    "sg:classifiers":[
        {
            "category":"Retail",
            "subcategory":"Laundry & Dry Cleaning",
            "type":"Services"
        }
    ],
    "sg:phone":"+61 2 9698 4114",
    "sg:postcode":"2010",
    "sg:province":"NSW",
    "sg:tags":[
        "ironing"
    ],
    "wof:name":"Comfy Pressing & Dry Cleaning",
    "wof:placetype":"venue"
},
  "geometry": {"coordinates":[151.20860290499999,-33.8900604248],"type":"Point"}
}