{
  "type": "Feature",
  "properties": {
    "addr:full":"16 Railway Rd Mulgrave NSW 2756",
    "addr:housenumber":"16",
    "addr:postcode":"2756",
    "addr:street":"Railway Rd",
    "iso:country":"AU",
    "sg:address":"16 Railway Rd",
    "sg:city":"Mulgrave",
    "sg:classifiers":[
        {
            "category":"Manufacturing",
            "subcategory":"Metals",
            "type":"Manufacturing & Wholesale Goods"
        }
    ],
    "sg:phone":"+61 2 4577 4633",
    "sg:postcode":"2756",
    "sg:province":"NSW",
    "sg:tags":[
        "sheet",
        "worker"
    ],
    "wof:name":"H.Q. Sheetmetal Pty Ltd",
    "wof:placetype":"venue"
},
  "geometry": {"coordinates":[150.831863403,-33.6275062561],"type":"Point"}
}