{
  "type": "Feature",
  "properties": {
    "iso:country":"AU",
    "sg:address":"62 Red Courte Rd",
    "sg:city":"Bakers Hill",
    "sg:classifiers":[
        {
            "category":"Professional",
            "subcategory":"Computer Services",
            "type":"Services"
        }
    ],
    "sg:phone":"+61 8 9574 0200",
    "sg:postcode":"6562",
    "sg:province":"WA",
    "sg:tags":[
        "consultant",
        "system"
    ],
    "wof:name":"It Navigate Pty Ltd",
    "wof:placetype":"venue"
},
  "geometry": {"coordinates":[116.458702,-31.75919],"type":"Point"}
}