{
  "type": "Feature",
  "properties": {
    "addr:full":"34 Grant Rd Somerville VIC 3912",
    "addr:housenumber":"34",
    "addr:postcode":"3912",
    "addr:street":"Grant Rd",
    "iso:country":"AU",
    "sg:address":"34 Grant Rd",
    "sg:city":"Somerville",
    "sg:classifiers":[
        {
            "category":"Retail",
            "subcategory":"Auto Repair",
            "type":"Services"
        }
    ],
    "sg:phone":"+61 402 250 197",
    "sg:postcode":"3912",
    "sg:province":"VIC",
    "sg:tags":[
        "electrical"
    ],
    "wof:name":"Just Recos",
    "wof:placetype":"venue"
},
  "geometry": {"coordinates":[145.176605225,-38.2200698853],"type":"Point"}
}