{
  "type": "Feature",
  "properties": {
    "addr:full":"Wallsend Plaza Cowper St Wallsend NSW 2287",
    "addr:postcode":"2287",
    "addr:street":"Cowper St",
    "iso:country":"AU",
    "sg:address":"Wallsend Plaza Cowper St",
    "sg:city":"Wallsend",
    "sg:classifiers":[
        {
            "category":"Utilities",
            "subcategory":"Mobile Phone",
            "type":"Services"
        }
    ],
    "sg:phone":"+61 2 4956 5757",
    "sg:postcode":"2287",
    "sg:province":"NSW",
    "sg:tags":[
        "repair",
        "telephone"
    ],
    "wof:name":"Network Communications",
    "wof:placetype":"venue"
},
  "geometry": {"coordinates":[151.66819763199999,-32.9037399292],"type":"Point"}
}