{
  "type": "Feature",
  "properties": {
    "iso:country":"AU",
    "sg:address":"1568 Melba Hwy",
    "sg:city":"Dixons Creek",
    "sg:classifiers":[
        {
            "category":"Farming",
            "subcategory":"Vineyard",
            "type":"Manufacturing & Wholesale Goods"
        }
    ],
    "sg:phone":"+61 3 5965 2016",
    "sg:postcode":"3775",
    "sg:province":"VIC",
    "sg:tags":[
        "winery"
    ],
    "wof:name":"Henkell Vineyards",
    "wof:placetype":"venue"
},
  "geometry": {"coordinates":[145.41351299999999,-37.611923],"type":"Point"}
}