{
  "type": "Feature",
  "properties": {
    "iso:country":"AU",
    "sg:address":"51 Victoria St",
    "sg:city":"Dubbo",
    "sg:classifiers":[
        {
            "category":"Retail",
            "subcategory":"Auto Rental",
            "type":"Services"
        }
    ],
    "sg:phone":"+61 2 6884 8688",
    "sg:postcode":"2830",
    "sg:province":"NSW",
    "sg:tags":[
        "car",
        "hire",
        "minibus"
    ],
    "wof:name":"Hertz",
    "wof:placetype":"venue"
},
  "geometry": {"coordinates":[148.59625244099999,-32.2509803772],"type":"Point"}
}