{
  "type": "Feature",
  "properties": {
    "iso:country":"AU",
    "sg:address":"Capalaba Park Shopping Centre, Redland Bay Rd",
    "sg:city":"Capalaba",
    "sg:classifiers":[
        {
            "category":"Shopping",
            "subcategory":"Jewelry",
            "type":"Retail Goods"
        }
    ],
    "sg:phone":"+61 7 3390 3076",
    "sg:postcode":"4157",
    "sg:province":"QLD",
    "sg:tags":[
        "jeweller"
    ],
    "wof:name":"Kleins",
    "wof:placetype":"venue"
},
  "geometry": {"coordinates":[153.2109375,-27.5379753113],"type":"Point"}
}