{
  "type": "Feature",
  "properties": {
    "addr:full":"208 McDougall St Toowoomba QLD 4350",
    "addr:housenumber":"208",
    "addr:postcode":"4350",
    "addr:street":"Mcdougall St",
    "iso:country":"AU",
    "sg:address":"208 McDougall St",
    "sg:city":"Toowoomba",
    "sg:classifiers":[
        {
            "category":"Retail",
            "subcategory":"Auto Repair",
            "type":"Services"
        }
    ],
    "sg:phone":"+61 7 4634 2500",
    "sg:postcode":"4350",
    "sg:province":"QLD",
    "sg:tags":[
        "repairer",
        "motor",
        "engineer"
    ],
    "wof:name":"Full Boar",
    "wof:placetype":"venue"
},
  "geometry": {"coordinates":[151.90744000000001,-27.560272],"type":"Point"}
}