{
  "type": "Feature",
  "properties": {
    "iso:country":"AU",
    "sg:address":"10 McKinnon St",
    "sg:city":"Jandakot",
    "sg:classifiers":[
        {
            "category":"Education",
            "subcategory":"Special Training",
            "type":"Public Place"
        }
    ],
    "sg:phone":"+61 8 9414 9722",
    "sg:postcode":"6164",
    "sg:province":"WA",
    "sg:tags":[
        "development"
    ],
    "wof:name":"Diversified Engineering Corporation Pty Ltd",
    "wof:placetype":"venue"
},
  "geometry": {"coordinates":[115.845848,-32.122726],"type":"Point"}
}