{
  "type": "Feature",
  "properties": {
    "iso:country":"AU",
    "sg:address":"9 Bridle La",
    "sg:city":"Molendinar",
    "sg:classifiers":[
        {
            "category":"Building & Trades",
            "subcategory":"Plumbing",
            "type":"Services"
        }
    ],
    "sg:phone":"+61 411 477 375",
    "sg:postcode":"4214",
    "sg:province":"QLD",
    "sg:tags":[
        "plumber",
        "gasfitters"
    ],
    "wof:name":"Spence Plumbing",
    "wof:placetype":"venue"
},
  "geometry": {"coordinates":[153.36439514200001,-27.9769210815],"type":"Point"}
}