{
  "type": "Feature",
  "properties": {
    "addr:full":"Level 14 33 Berry St North Sydney NSW 2060",
    "addr:housenumber":"33",
    "addr:postcode":"2060",
    "addr:street":"Berry St",
    "iso:country":"AU",
    "sg:address":"Level 14 33 Berry St",
    "sg:city":"North Sydney",
    "sg:classifiers":[
        {
            "category":"Professional",
            "subcategory":"Computer Services",
            "type":"Services"
        }
    ],
    "sg:phone":"+61 2 9959 1939",
    "sg:postcode":"2060",
    "sg:province":"NSW",
    "sg:tags":[
        "consultant",
        "system"
    ],
    "wof:name":"Opticon Australia Pty Ltd",
    "wof:placetype":"venue"
},
  "geometry": {"coordinates":[151.205535889,-33.8368453979],"type":"Point"}
}