{
  "type": "Feature",
  "properties": {
    "iso:country":"AU",
    "sg:address":"2 Grosvenor Pl",
    "sg:city":"Brookvale",
    "sg:classifiers":[
        {
            "category":"Real Estate",
            "subcategory":"Architect",
            "type":"Services"
        }
    ],
    "sg:phone":"+61 2 9938 6199",
    "sg:postcode":"2100",
    "sg:province":"NSW",
    "sg:tags":[
        "naval"
    ],
    "wof:name":"Burness Corlett -Three Quays Aust Pty Ltd",
    "wof:placetype":"venue"
},
  "geometry": {"coordinates":[151.270996094,-33.768283844],"type":"Point"}
}