{
  "type": "Feature",
  "properties": {
    "addr:full":"220 John St Singleton NSW 2330",
    "addr:housenumber":"220",
    "addr:postcode":"2330",
    "addr:street":"John St",
    "iso:country":"AU",
    "sg:address":"220 John St",
    "sg:city":"Singleton",
    "sg:classifiers":[
        {
            "category":"Building & Trades",
            "subcategory":"Construction",
            "type":"Services"
        }
    ],
    "sg:phone":"+61 2 6571 2922",
    "sg:postcode":"2330",
    "sg:province":"NSW",
    "sg:tags":[
        "renovation",
        "alterations",
        "extension",
        "contractor"
    ],
    "wof:name":"Klasen P G & J A",
    "wof:placetype":"venue"
},
  "geometry": {"coordinates":[151.17115799999999,-32.561035],"type":"Point"}
}