{
  "type": "Feature",
  "properties": {
    "iso:country":"AU",
    "sg:address":"332 Cranbourne Rd",
    "sg:city":"Karingal",
    "sg:classifiers":[
        {
            "category":"Home & Garden",
            "subcategory":"Garden Supply",
            "type":"Retail Goods"
        }
    ],
    "sg:phone":"+61 3 9789 9898",
    "sg:postcode":"3199",
    "sg:province":"VIC",
    "sg:tags":[
        "equipment"
    ],
    "wof:name":"Mitre 10 Frankston",
    "wof:placetype":"venue"
},
  "geometry": {"coordinates":[145.165847778,-38.1549224854],"type":"Point"}
}