{
  "type": "Feature",
  "properties": {
    "iso:country":"AU",
    "sg:address":"32 MacKenzie St",
    "sg:city":"Eimeo",
    "sg:classifiers":[
        {
            "category":"Building & Trades",
            "subcategory":"Construction",
            "type":"Services"
        }
    ],
    "sg:phone":"+61 411 387 914",
    "sg:postcode":"4740",
    "sg:province":"QLD",
    "sg:tags":[
        "renovation",
        "alterations",
        "extension",
        "contractor"
    ],
    "wof:name":"Life Design Homes Pty Ltd",
    "wof:placetype":"venue"
},
  "geometry": {"coordinates":[149.178818,-21.038795],"type":"Point"}
}