{
  "type": "Feature",
  "properties": {
    "addr:full":"28 Chivalry St Bray Park QLD 4500",
    "addr:housenumber":"28",
    "addr:postcode":"4500",
    "addr:street":"Chivalry St Bray Park",
    "iso:country":"AU",
    "sg:address":"28 Chivalry St",
    "sg:city":"Bray Park",
    "sg:classifiers":[
        {
            "category":"Shopping",
            "subcategory":"Photographic Equipment",
            "type":"Retail Goods"
        }
    ],
    "sg:phone":"+61 7 3881 0443",
    "sg:postcode":"4500",
    "sg:province":"QLD",
    "sg:tags":[
        "eyelet",
        "eyeletting"
    ],
    "wof:name":"Bud's Eyes",
    "wof:placetype":"venue"
},
  "geometry": {"coordinates":[152.97862243599999,-27.2944431305],"type":"Point"}
}