{
  "type": "Feature",
  "properties": {
    "iso:country":"AU",
    "sg:address":"7 Richard St",
    "sg:city":"Western Junction",
    "sg:classifiers":[
        {
            "category":"Professional",
            "subcategory":"Testing Lab",
            "type":"Services"
        }
    ],
    "sg:phone":"+61 3 6391 8801",
    "sg:postcode":"7212",
    "sg:province":"TAS",
    "sg:tags":[
        "inspection"
    ],
    "wof:name":"Metaserv Pty Ltd",
    "wof:placetype":"venue"
},
  "geometry": {"coordinates":[147.19903600000001,-41.536858],"type":"Point"}
}