{
  "type": "Feature",
  "properties": {
    "addr:full":"Unit 5, 2 Gladstone St Castle Hill NSW 2154",
    "addr:housenumber":"2",
    "addr:postcode":"2154",
    "addr:street":"Gladstone St",
    "iso:country":"AU",
    "sg:address":"Unit 5, 2 Gladstone St",
    "sg:city":"Castle Hill",
    "sg:classifiers":[
        {
            "category":"Retail",
            "subcategory":"Auto Repair",
            "type":"Services"
        }
    ],
    "sg:phone":"+61 2 9899 2522",
    "sg:postcode":"2154",
    "sg:province":"NSW",
    "sg:tags":[
        "electrical"
    ],
    "wof:name":"Garrys Auto Services",
    "wof:placetype":"venue"
},
  "geometry": {"coordinates":[150.97958374000001,-33.7325744629],"type":"Point"}
}