{
  "type": "Feature",
  "properties": {
    "addr:full":"22 Waine St Harbord NSW 2096",
    "addr:housenumber":"22",
    "addr:postcode":"2096",
    "addr:street":"Waine St",
    "iso:country":"AU",
    "sg:address":"22 Waine St",
    "sg:city":"Harbord",
    "sg:classifiers":[
        {
            "category":"Building & Trades",
            "subcategory":"Construction",
            "type":"Services"
        }
    ],
    "sg:phone":"+61 2 9905 1777",
    "sg:postcode":"2096",
    "sg:province":"NSW",
    "sg:tags":[
        "contractor"
    ],
    "wof:name":"Northern Building PTY LTD",
    "wof:placetype":"venue"
},
  "geometry": {"coordinates":[151.27752685600001,-33.7797241211],"type":"Point"}
}