{
  "type": "Feature",
  "properties": {
    "addr:full":"7 Murray St Clayton VIC 3168",
    "addr:housenumber":"7",
    "addr:postcode":"3168",
    "addr:street":"Murray St",
    "iso:country":"AU",
    "sg:address":"7 Murray St",
    "sg:city":"Clayton",
    "sg:classifiers":[
        {
            "category":"Health Services",
            "subcategory":"Health Practitioner",
            "type":"Services"
        }
    ],
    "sg:phone":"+61 1800 233 233",
    "sg:postcode":"3168",
    "sg:province":"VIC",
    "sg:tags":[
        "psychologist"
    ],
    "wof:name":"Centre Of Attention",
    "wof:placetype":"venue"
},
  "geometry": {"coordinates":[145.12203979500001,-37.9181060791],"type":"Point"}
}