{
  "type": "Feature",
  "properties": {
    "addr:full":"46 Kurrajong Ave Leeton NSW 2705",
    "addr:housenumber":"46",
    "addr:postcode":"2705",
    "addr:street":"Kurrajong Ave",
    "iso:country":"AU",
    "sg:address":"46 Kurrajong Ave",
    "sg:city":"Leeton",
    "sg:classifiers":[
        {
            "category":"Shopping",
            "subcategory":"Computers & Home Electronics",
            "type":"Retail Goods"
        }
    ],
    "sg:phone":"+61 2 6953 7679",
    "sg:postcode":"2705",
    "sg:province":"NSW",
    "sg:tags":[
        "small",
        "equipment",
        "business"
    ],
    "wof:name":"W W W Computers Aust",
    "wof:placetype":"venue"
},
  "geometry": {"coordinates":[146.40733337399999,-34.5531654358],"type":"Point"}
}