{
  "type": "Feature",
  "properties": {
    "addr:full":"380 William St Melbourne VIC 3000",
    "addr:housenumber":"380",
    "addr:postcode":"3000",
    "addr:street":"William St",
    "iso:country":"AU",
    "sg:address":"380 William St",
    "sg:city":"Melbourne",
    "sg:classifiers":[
        {
            "category":"Travel",
            "subcategory":"Hotels & Motels",
            "type":"Entertainment"
        }
    ],
    "sg:phone":"+61 3 9322 8000",
    "sg:postcode":"3000",
    "sg:province":"VIC",
    "sg:tags":[
        "accommodation"
    ],
    "wof:name":"Radisson on Flagstaff Gardens Hotel",
    "wof:placetype":"venue"
},
  "geometry": {"coordinates":[144.95596313499999,-37.8103523254],"type":"Point"}
}