{
  "type": "Feature",
  "properties": {
    "iso:country":"AU",
    "sg:address":"915 Bells Line Of Rd",
    "sg:city":"Kurrajong Hills",
    "sg:classifiers":[
        {
            "category":"Professional",
            "subcategory":"Business Services",
            "type":"Services"
        }
    ],
    "sg:phone":"+61 2 4573 1854",
    "sg:postcode":"2758",
    "sg:province":"NSW",
    "sg:tags":[
        "drafting"
    ],
    "wof:name":"Burnside Engineering Services Pty Ltd",
    "wof:placetype":"venue"
},
  "geometry": {"coordinates":[150.64210510300001,-33.5417671204],"type":"Point"}
}