{
  "type": "Feature",
  "properties": {
    "iso:country":"AU",
    "sg:address":"15 Rowood Rd",
    "sg:city":"Prospect",
    "sg:classifiers":[
        {
            "category":"Professional",
            "type":"Services"
        }
    ],
    "sg:phone":"+61 2 9688 2255",
    "sg:postcode":"2148",
    "sg:province":"NSW",
    "sg:tags":[
        "transport"
    ],
    "wof:name":"Marshall Ray Transport Pty Ltd",
    "wof:placetype":"venue"
},
  "geometry": {"coordinates":[150.92340087900001,-33.8018569946],"type":"Point"}
}