{
  "type": "Feature",
  "properties": {
    "iso:country":"AU",
    "sg:address":"Shop 1 Nindaroo Shopping Centre",
    "sg:city":"Nindaroo",
    "sg:classifiers":[
        {
            "category":"Real Estate",
            "subcategory":"Real Estate Agent",
            "type":"Services"
        }
    ],
    "sg:phone":"+61 7 4969 7900",
    "sg:postcode":"4740",
    "sg:province":"QLD",
    "wof:name":"Nexus Realty",
    "wof:placetype":"venue"
},
  "geometry": {"coordinates":[149.132462,-21.06847],"type":"Point"}
}