{
  "type": "Feature",
  "properties": {
    "iso:country":"AU",
    "sg:address":"123 Bamfield Rd",
    "sg:city":"Heidelberg Heights",
    "sg:classifiers":[
        {
            "category":"Building & Trades",
            "subcategory":"Construction",
            "type":"Services"
        }
    ],
    "sg:phone":"+61 3 9459 9566",
    "sg:postcode":"3081",
    "sg:province":"VIC",
    "sg:tags":[
        "fencing",
        "contractor"
    ],
    "wof:name":"Playabout Trampolines",
    "wof:placetype":"venue"
},
  "geometry": {"coordinates":[145.05659484899999,-37.734336853],"type":"Point"}
}