{
  "type": "Feature",
  "properties": {
    "addr:full":"17 O'Brien St Adelaide SA 5000",
    "addr:housenumber":"17",
    "addr:postcode":"5000",
    "addr:street":"O'Brien St",
    "iso:country":"AU",
    "sg:address":"17 O'Brien St",
    "sg:city":"Adelaide",
    "sg:classifiers":[
        {
            "category":"Health Services",
            "subcategory":"Doctor",
            "type":"Services"
        }
    ],
    "sg:phone":"+61 8 8231 4026",
    "sg:postcode":"5000",
    "sg:province":"SA",
    "sg:tags":[
        "medical",
        "practitioner"
    ],
    "wof:name":"Wait Brenton",
    "wof:placetype":"venue"
},
  "geometry": {"coordinates":[138.58969116200001,-34.9341850281],"type":"Point"}
}