{
  "type": "Feature",
  "properties": {
    "addr:full":"363 Kent St Sydney NSW 2000",
    "addr:housenumber":"363",
    "addr:postcode":"2000",
    "addr:street":"Kent St",
    "iso:country":"AU",
    "sg:address":"363 Kent St",
    "sg:city":"Sydney",
    "sg:classifiers":[
        {
            "category":"Banks & Credit Unions",
            "subcategory":"Financial Services",
            "type":"Services"
        }
    ],
    "sg:phone":"+61 2 9249 5600",
    "sg:postcode":"2000",
    "sg:province":"NSW",
    "sg:tags":[
        "planning"
    ],
    "wof:name":"Count Wealth Accountants",
    "wof:placetype":"venue"
},
  "geometry": {"coordinates":[151.20449829099999,-33.8692893982],"type":"Point"}
}