{
  "type": "Feature",
  "properties": {
    "addr:full":"69 Beveridge St Swan Hill VIC 3585",
    "addr:housenumber":"69",
    "addr:postcode":"3585",
    "addr:street":"Beveridge St",
    "iso:country":"AU",
    "sg:address":"69 Beveridge St",
    "sg:city":"Swan Hill",
    "sg:classifiers":[
        {
            "category":"Farming",
            "subcategory":"Farm & Veterinary Services",
            "type":"Manufacturing & Wholesale Goods"
        }
    ],
    "sg:phone":"+61 3 5032 3685",
    "sg:postcode":"3585",
    "sg:province":"VIC",
    "sg:tags":[
        "irrigation",
        "reticulation",
        "system"
    ],
    "wof:name":"Price Merrett Consulting Pty Ltd",
    "wof:placetype":"venue"
},
  "geometry": {"coordinates":[143.55741900000001,-35.336113],"type":"Point"}
}