{
  "type": "Feature",
  "properties": {
    "addr:full":"36 George St Stepney SA 5069",
    "addr:housenumber":"36",
    "addr:postcode":"5069",
    "addr:street":"George St",
    "iso:country":"AU",
    "sg:address":"36 George St",
    "sg:city":"Stepney",
    "sg:classifiers":[
        {
            "category":"Social Services",
            "subcategory":"Retirement Home",
            "type":"Services"
        }
    ],
    "sg:phone":"+61 8 8363 5191",
    "sg:postcode":"5069",
    "sg:province":"SA",
    "sg:tags":[
        "t-shirt",
        "supplier"
    ],
    "wof:name":"TSW Apparel",
    "wof:placetype":"venue"
},
  "geometry": {"coordinates":[138.625442505,-34.912689209],"type":"Point"}
}