{
  "type": "Feature",
  "properties": {
    "addr:full":"Saltwater Macrossan St Port Douglas QLD 4877",
    "addr:postcode":"4877",
    "addr:street":"St",
    "iso:country":"AU",
    "sg:address":"Saltwater Macrossan St",
    "sg:city":"Port Douglas",
    "sg:classifiers":[
        {
            "category":"Shopping",
            "subcategory":"Shoes",
            "type":"Retail Goods"
        }
    ],
    "sg:phone":"+61 7 4099 5831",
    "sg:postcode":"4877",
    "sg:province":"QLD",
    "sg:tags":[
        "footwear"
    ],
    "wof:name":"In Port Shoes",
    "wof:placetype":"venue"
},
  "geometry": {"coordinates":[145.466339111,-16.4843177795],"type":"Point"}
}