{
  "type": "Feature",
  "properties": {
    "addr:full":"Level 7, 9- 19 Elizabeth St Sydney NSW 2000",
    "addr:housenumber":"9 19",
    "addr:postcode":"2000",
    "addr:street":"Elizabeth St",
    "iso:country":"AU",
    "sg:address":"Level 7, 9- 19 Elizabeth St",
    "sg:city":"Sydney",
    "sg:classifiers":[
        {
            "category":"Banks & Credit Unions",
            "subcategory":"Bank",
            "type":"Services"
        }
    ],
    "sg:phone":"+61 13 72 88",
    "sg:postcode":"2000",
    "sg:province":"NSW",
    "wof:name":"Woolworths Ezy Banking",
    "wof:placetype":"venue"
},
  "geometry": {"coordinates":[151.210494995,-33.8671760559],"type":"Point"}
}