{
  "type": "Feature",
  "properties": {
    "addr:full":"35 Earl St Beacon Hill NSW 2100",
    "addr:housenumber":"35",
    "addr:postcode":"2100",
    "addr:street":"Earl St",
    "iso:country":"AU",
    "sg:address":"35 Earl St",
    "sg:city":"Beacon Hill",
    "sg:classifiers":[
        {
            "category":"Education",
            "subcategory":"Special Training",
            "type":"Public Place"
        }
    ],
    "sg:phone":"+61 2 9453 9255",
    "sg:postcode":"2100",
    "sg:province":"NSW",
    "sg:tags":[
        "development"
    ],
    "wof:name":"Personal Development Audio Books",
    "wof:placetype":"venue"
},
  "geometry": {"coordinates":[151.256988525,-33.7540512085],"type":"Point"}
}