{
  "type": "Feature",
  "properties": {
    "addr:full":"Excelsior Pde Toronto NSW 2283",
    "addr:postcode":"2283",
    "addr:street":"Excelsior",
    "iso:country":"AU",
    "sg:address":"Excelsior Pde",
    "sg:city":"Toronto",
    "sg:classifiers":[
        {
            "category":"Manufacturing",
            "subcategory":"Metals",
            "type":"Manufacturing & Wholesale Goods"
        }
    ],
    "sg:phone":"+61 410 797 336",
    "sg:postcode":"2283",
    "sg:province":"NSW",
    "sg:tags":[
        "polisher"
    ],
    "wof:name":"Restoration Metal Polishers",
    "wof:placetype":"venue"
},
  "geometry": {"coordinates":[151.59022522000001,-33.0155982971],"type":"Point"}
}