{
  "type": "Feature",
  "properties": {
    "addr:full":"11 London St Blacktown NSW 2148",
    "addr:housenumber":"11",
    "addr:postcode":"2148",
    "addr:street":"London St",
    "iso:country":"AU",
    "sg:address":"11 London St",
    "sg:city":"Blacktown",
    "sg:classifiers":[
        {
            "category":"Shopping",
            "subcategory":"Computers & Home Electronics",
            "type":"Retail Goods"
        }
    ],
    "sg:phone":"+61 2 9831 2750",
    "sg:postcode":"2148",
    "sg:province":"NSW",
    "sg:tags":[
        "detector",
        "electronic"
    ],
    "wof:name":"On Line Pipe & Cable Locating",
    "wof:placetype":"venue"
},
  "geometry": {"coordinates":[150.88955688499999,-33.7634811401],"type":"Point"}
}