{
  "type": "Feature",
  "properties": {
    "iso:country":"AU",
    "sg:address":"2/ 111",
    "sg:city":"Godfrey Tce Erindale",
    "sg:classifiers":[
        {
            "category":"Banks & Credit Unions",
            "subcategory":"Financial Services",
            "type":"Services"
        }
    ],
    "sg:phone":"+61 8 8333 3960",
    "sg:postcode":"5066",
    "sg:province":"SA",
    "sg:tags":[
        "franchising"
    ],
    "wof:name":"Can Do It",
    "wof:placetype":"venue"
},
  "geometry": {"coordinates":[138.66697692899999,-34.926815033],"type":"Point"}
}