{
  "type": "Feature",
  "properties": {
    "iso:country":"AU",
    "sg:address":"RMB 2023 Portland Nelson Rd",
    "sg:city":"Portland",
    "sg:classifiers":[
        {
            "category":"Professional",
            "subcategory":"Testing Lab",
            "type":"Services"
        }
    ],
    "sg:phone":"+61 3 5523 2986",
    "sg:postcode":"3305",
    "sg:province":"VIC",
    "sg:tags":[
        "inspection"
    ],
    "wof:name":"Australian Wool Testing Authority",
    "wof:placetype":"venue"
},
  "geometry": {"coordinates":[141.582199097,-38.3217010498],"type":"Point"}
}