{
  "type": "Feature",
  "properties": {
    "iso:country":"AU",
    "sg:address":"15- 17 Bibby St",
    "sg:city":"Chiswick",
    "sg:classifiers":[
        {
            "category":"Education",
            "subcategory":"Dance Studio",
            "type":"Public Place"
        }
    ],
    "sg:phone":"+61 2 9712 1822",
    "sg:postcode":"2046",
    "sg:province":"NSW",
    "sg:tags":[
        "venue",
        "tuition"
    ],
    "wof:name":"RGDANCE.com Personal Dance Coaching",
    "wof:placetype":"venue"
},
  "geometry": {"coordinates":[151.137573,-33.850773],"type":"Point"}
}