{
  "type": "Feature",
  "properties": {
    "iso:country":"AU",
    "sg:address":"897 Arthurs Creek Rd",
    "sg:city":"Arthurs Creek",
    "sg:classifiers":[
        {
            "category":"Farming",
            "subcategory":"Nursery",
            "type":"Manufacturing & Wholesale Goods"
        }
    ],
    "sg:phone":"+61 3 9714 8878",
    "sg:postcode":"3099",
    "sg:province":"VIC",
    "wof:name":"Haystack Plants",
    "wof:placetype":"venue"
},
  "geometry": {"coordinates":[145.20257568400001,-37.5795593262],"type":"Point"}
}