{
  "type": "Feature",
  "properties": {
    "iso:country":"AU",
    "sg:address":"140 Percy St",
    "sg:city":"Portland",
    "sg:classifiers":[
        {
            "category":"Autos & Motor Vehicles",
            "subcategory":"Automobile Sales",
            "type":"Retail Goods"
        }
    ],
    "sg:phone":"+61 3 5521 1450",
    "sg:postcode":"3305",
    "sg:province":"VIC",
    "sg:tags":[
        "car",
        "used"
    ],
    "wof:name":"Portland Quality Used Cars",
    "wof:placetype":"venue"
},
  "geometry": {"coordinates":[141.60398864699999,-38.344379425],"type":"Point"}
}