{
  "type": "Feature",
  "properties": {
    "addr:full":"PO Box 5 Turramurra NSW 2074",
    "addr:postcode":"2074",
    "iso:country":"AU",
    "sg:address":"PO Box 5",
    "sg:city":"Turramurra",
    "sg:classifiers":[
        {
            "category":"Building & Trades",
            "subcategory":"Landscaping Services",
            "type":"Services"
        }
    ],
    "sg:phone":"+61 418 615 304",
    "sg:postcode":"2074",
    "sg:province":"NSW",
    "sg:tags":[
        "designer",
        "landscape",
        "contractor"
    ],
    "wof:name":"Equator Landscapes",
    "wof:placetype":"venue"
},
  "geometry": {"coordinates":[151.129196167,-33.7326011658],"type":"Point"}
}