{
  "type": "Feature",
  "properties": {
    "iso:country":"AU",
    "sg:address":"50 Wyndham St",
    "sg:city":"Alexandria",
    "sg:classifiers":[
        {
            "category":"Farming",
            "subcategory":"Orchard",
            "type":"Manufacturing & Wholesale Goods"
        }
    ],
    "sg:phone":"+61 2 8577 6777",
    "sg:postcode":"2015",
    "sg:province":"NSW",
    "sg:tags":[
        "wholesaler",
        "jean",
        "mfrs"
    ],
    "wof:name":"yd. Clothing",
    "wof:placetype":"venue"
},
  "geometry": {"coordinates":[151.19827270499999,-33.8963356018],"type":"Point"}
}