{
  "type": "Feature",
  "properties": {
    "iso:country":"AU",
    "sg:address":"Princess Plaza+14 Annerley Rd",
    "sg:city":"Woolloongabba",
    "sg:classifiers":[
        {
            "category":"Shopping",
            "subcategory":"Computers & Home Electronics",
            "type":"Retail Goods"
        }
    ],
    "sg:phone":"+61 7 3391 2775",
    "sg:postcode":"4102",
    "sg:province":"QLD",
    "sg:tags":[
        "hardware",
        "equipment"
    ],
    "wof:name":"Applecentre",
    "wof:placetype":"venue"
},
  "geometry": {"coordinates":[153.02914428700001,-27.4863777161],"type":"Point"}
}