{
  "type": "Feature",
  "properties": {
    "addr:full":"10- 14 Hawker Rd Burton SA 5110",
    "addr:housenumber":"14",
    "addr:postcode":"5110",
    "addr:street":"Hawker Rd",
    "iso:country":"AU",
    "sg:address":"10- 14 Hawker Rd",
    "sg:city":"Burton",
    "sg:classifiers":[
        {
            "category":"Military Area",
            "subcategory":"Coast Guard Base",
            "type":"Public Place"
        }
    ],
    "sg:phone":"+61 8 8280 6891",
    "sg:postcode":"5110",
    "sg:province":"SA",
    "sg:tags":[
        "vessel",
        "pressure",
        "industrial"
    ],
    "wof:name":"Pipetech Pty Ltd",
    "wof:placetype":"venue"
},
  "geometry": {"coordinates":[138.59982299800001,-34.7331466675],"type":"Point"}
}