{
  "type": "Feature",
  "properties": {
    "iso:country":"AU",
    "sg:address":"35 Macredie St",
    "sg:city":"Nakara",
    "sg:classifiers":[
        {
            "category":"Health Services",
            "subcategory":"Doctor",
            "type":"Services"
        }
    ],
    "sg:phone":"+61 8 8927 1873",
    "sg:postcode":"0810",
    "sg:province":"NT",
    "sg:tags":[
        "medical",
        "practitioner"
    ],
    "wof:name":"Nakara Medical Clinic",
    "wof:placetype":"venue"
},
  "geometry": {"coordinates":[130.875930786,-12.367688179],"type":"Point"}
}