{
  "type": "Feature",
  "properties": {
    "addr:full":"1/ 8 Brant Rd Kelmscott WA 6111",
    "addr:housenumber":"/ 8",
    "addr:postcode":"6111",
    "addr:street":"Brant Rd",
    "iso:country":"AU",
    "sg:address":"1/ 8 Brant Rd",
    "sg:city":"Kelmscott",
    "sg:classifiers":[
        {
            "category":"Sports & Exercise",
            "subcategory":"Athletic Track",
            "type":"Entertainment"
        }
    ],
    "sg:phone":"+61 8 9495 4237",
    "sg:postcode":"6111",
    "sg:province":"WA",
    "sg:tags":[
        "industrial",
        "ceramic",
        "scientific"
    ],
    "wof:name":"Competition And Industrial Coatings",
    "wof:placetype":"venue"
},
  "geometry": {"coordinates":[116.005401611,-32.1291007996],"type":"Point"}
}