{
  "type": "Feature",
  "properties": {
    "addr:full":"50 Howard St Seville VIC 3139",
    "addr:housenumber":"50",
    "addr:postcode":"3139",
    "addr:street":"Howard St",
    "iso:country":"AU",
    "sg:address":"50 Howard St",
    "sg:city":"Seville",
    "sg:classifiers":[
        {
            "category":"Building & Trades",
            "subcategory":"Construction",
            "type":"Services"
        }
    ],
    "sg:phone":"+61 419 556 635",
    "sg:postcode":"3139",
    "sg:province":"VIC",
    "sg:tags":[
        "earth",
        "excavating",
        "moving",
        "contractor"
    ],
    "wof:name":"Reeves S & J",
    "wof:placetype":"venue"
},
  "geometry": {"coordinates":[145.452194214,-37.773639679],"type":"Point"}
}