{
  "type": "Feature",
  "properties": {
    "addr:full":"Shop 9 Murdoch Shopping Centre Murdoch Drv Greenfields WA 6210",
    "addr:housenumber":"shop 9",
    "addr:postcode":"6210",
    "addr:street":"Murdoch Shopping;Murdoch Drv",
    "iso:country":"AU",
    "sg:address":"Shop 9 Murdoch Shopping Centre Murdoch Drv",
    "sg:city":"Greenfields",
    "sg:classifiers":[
        {
            "category":"Food & Beverages",
            "subcategory":"Bakery",
            "type":"Retail Goods"
        }
    ],
    "sg:phone":"+61 8 9534 9480",
    "sg:postcode":"6210",
    "sg:province":"WA",
    "sg:tags":[
        "cake",
        "shop",
        "pastry"
    ],
    "wof:name":"BB's Bakery",
    "wof:placetype":"venue"
},
  "geometry": {"coordinates":[115.749809,-32.52882],"type":"Point"}
}