{
  "type": "Feature",
  "properties": {
    "iso:country":"AU",
    "sg:address":"248- 250 Crown St",
    "sg:city":"Wollongong",
    "sg:classifiers":[
        {
            "category":"Shopping",
            "subcategory":"Pawn Shop",
            "type":"Retail Goods"
        }
    ],
    "sg:phone":"+61 2 4226 5820",
    "sg:postcode":"2500",
    "sg:province":"NSW",
    "sg:tags":[
        "pawnbroker"
    ],
    "wof:name":"Cash-AFX",
    "wof:placetype":"venue"
},
  "geometry": {"coordinates":[150.893539,-34.423679],"type":"Point"}
}