{
  "type": "Feature",
  "properties": {
    "addr:full":"33 Ford St Beechworth VIC 3747",
    "addr:housenumber":"33",
    "addr:postcode":"3747",
    "addr:street":"Ford St",
    "iso:country":"AU",
    "sg:address":"33 Ford St",
    "sg:city":"Beechworth",
    "sg:classifiers":[
        {
            "category":"Arts & Performance",
            "subcategory":"Art Gallery",
            "type":"Entertainment"
        }
    ],
    "sg:phone":"+61 3 5728 1126",
    "sg:postcode":"3747",
    "sg:province":"VIC",
    "wof:name":"Beechworth Fine Art",
    "wof:placetype":"venue"
},
  "geometry": {"coordinates":[146.68504300000001,-36.360653],"type":"Point"}
}