{
  "type": "Feature",
  "properties": {
    "iso:country":"AU",
    "sg:address":"64 Camberwell Rd",
    "sg:city":"Camberwell",
    "sg:classifiers":[
        {
            "category":"Restaurant",
            "type":"Food & Drink"
        }
    ],
    "sg:phone":"+61 3 9882 3160",
    "sg:postcode":"3124",
    "sg:province":"VIC",
    "wof:name":"Celadon Thai Cafe",
    "wof:placetype":"venue"
},
  "geometry": {"coordinates":[145.05073547399999,-37.826385498],"type":"Point"}
}