{
  "type": "Feature",
  "properties": {
    "addr:full":"174 Timor St Warrnambool VIC 3280",
    "addr:housenumber":"174",
    "addr:postcode":"3280",
    "addr:street":"Timor St",
    "iso:country":"AU",
    "sg:address":"174 Timor St",
    "sg:city":"Warrnambool",
    "sg:classifiers":[
        {
            "category":"Real Estate",
            "subcategory":"Real Estate Agent",
            "type":"Services"
        }
    ],
    "sg:phone":"+61 3 5562 2444",
    "sg:postcode":"3280",
    "sg:province":"VIC",
    "wof:name":"Jens Gaunt",
    "wof:placetype":"venue"
},
  "geometry": {"coordinates":[142.48161315900001,-38.3849563599],"type":"Point"}
}