{
  "type": "Feature",
  "properties": {
    "addr:full":"36 Ambrose St Laidley QLD 4341",
    "addr:housenumber":"36",
    "addr:postcode":"4341",
    "addr:street":"Ambrose St",
    "iso:country":"AU",
    "sg:address":"36 Ambrose St",
    "sg:city":"Laidley",
    "sg:classifiers":[
        {
            "category":"Health Services",
            "subcategory":"Doctor",
            "type":"Services"
        }
    ],
    "sg:phone":"+61 7 5465 1388",
    "sg:postcode":"4341",
    "sg:province":"QLD",
    "sg:tags":[
        "medical",
        "practitioner"
    ],
    "wof:name":"Laidley Family Doctors",
    "wof:placetype":"venue"
},
  "geometry": {"coordinates":[152.39643859899999,-27.6301250458],"type":"Point"}
}