{
  "type": "Feature",
  "properties": {
    "addr:full":"PO Box 37 Vasse WA 6280",
    "addr:postcode":"6280",
    "iso:country":"AU",
    "sg:address":"PO Box 37",
    "sg:city":"Vasse",
    "sg:classifiers":[
        {
            "category":"Building & Trades",
            "subcategory":"Landscaping Services",
            "type":"Services"
        }
    ],
    "sg:phone":"+61 8 9755 0637",
    "sg:postcode":"6280",
    "sg:province":"WA",
    "sg:tags":[
        "stump",
        "tree",
        "felling",
        "removal"
    ],
    "wof:name":"A-Cut Tree Service",
    "wof:placetype":"venue"
},
  "geometry": {"coordinates":[115.247558594,-33.677898407],"type":"Point"}
}