{
  "type": "Feature",
  "properties": {
    "addr:full":"10 Brown St Brompton SA 5007",
    "addr:housenumber":"10",
    "addr:postcode":"5007",
    "addr:street":"Brown St",
    "iso:country":"AU",
    "sg:address":"10 Brown St",
    "sg:city":"Brompton",
    "sg:classifiers":[
        {
            "category":"Communications",
            "type":"Services"
        }
    ],
    "sg:phone":"+61 8 8346 3033",
    "sg:postcode":"5007",
    "sg:province":"SA",
    "sg:tags":[
        "public",
        "system",
        "address"
    ],
    "wof:name":"Allpro Audio",
    "wof:placetype":"venue"
},
  "geometry": {"coordinates":[138.57260131800001,-34.9000282288],"type":"Point"}
}