{
  "type": "Feature",
  "properties": {
    "addr:full":"26 Cabbage Tree Ave Avoca Beach NSW 2251",
    "addr:housenumber":"26",
    "addr:postcode":"2251",
    "addr:street":"Cabbage Tree Ave",
    "iso:country":"AU",
    "sg:address":"26 Cabbage Tree Ave",
    "sg:city":"Avoca Beach",
    "sg:classifiers":[
        {
            "category":"Professional",
            "subcategory":"Art Services",
            "type":"Services"
        }
    ],
    "sg:phone":"+61 2 4382 2992",
    "sg:postcode":"2251",
    "sg:province":"NSW",
    "sg:tags":[
        "graphic",
        "designer"
    ],
    "wof:name":"Bluewood Studio",
    "wof:placetype":"venue"
},
  "geometry": {"coordinates":[151.43417358400001,-33.4768943787],"type":"Point"}
}