{
  "type": "Feature",
  "properties": {
    "addr:full":"404 Wagga Rd Albury NSW 2640",
    "addr:housenumber":"404",
    "addr:postcode":"2640",
    "addr:street":"Wagga Rd",
    "iso:country":"AU",
    "sg:address":"404 Wagga Rd",
    "sg:city":"Albury",
    "sg:classifiers":[
        {
            "category":"Travel",
            "subcategory":"Hotels & Motels",
            "type":"Entertainment"
        }
    ],
    "sg:phone":"+61 2 6025 7177",
    "sg:postcode":"2640",
    "sg:province":"NSW",
    "wof:name":"Albury Classic Motel",
    "wof:placetype":"venue"
},
  "geometry": {"coordinates":[146.96340942399999,-35.9506530762],"type":"Point"}
}