{
  "type": "Feature",
  "properties": {
    "addr:full":"Cnr Main St & Civic Way Rouse Hill NSW 2155",
    "addr:postcode":"2155",
    "addr:street":"Cnr Main St & Civic Way",
    "iso:country":"AU",
    "sg:address":"Cnr Main St & Civic Way",
    "sg:city":"Rouse Hill",
    "sg:classifiers":[
        {
            "category":"Autos & Motor Vehicles",
            "subcategory":"Auto Supplies",
            "type":"Retail Goods"
        }
    ],
    "sg:phone":"+61 2 9568 8822",
    "sg:postcode":"2155",
    "sg:province":"NSW",
    "sg:tags":[
        "automotive",
        "stereo",
        "radio"
    ],
    "wof:name":"Ryda",
    "wof:placetype":"venue"
},
  "geometry": {"coordinates":[150.9168396,-33.6841201782],"type":"Point"}
}