{
  "type": "Feature",
  "properties": {
    "iso:country":"AU",
    "sg:address":"51 Adelaide Rd",
    "sg:city":"Mannum",
    "sg:classifiers":[
        {
            "category":"Sports & Exercise",
            "subcategory":"Gym",
            "type":"Entertainment"
        }
    ],
    "sg:phone":"+61 8 8569 0185",
    "sg:postcode":"5238",
    "sg:province":"SA",
    "sg:tags":[
        "health",
        "fitness"
    ],
    "wof:name":"Mannum Leisure Centre",
    "wof:placetype":"venue"
},
  "geometry": {"coordinates":[139.304595947,-34.9156990051],"type":"Point"}
}