{
  "type": "Feature",
  "properties": {
    "addr:full":"Unit 10C, 30 Kalaroo Rd Redhead NSW 2290",
    "addr:housenumber":"30",
    "addr:postcode":"2290",
    "addr:street":"Kalaroo Rd",
    "iso:country":"AU",
    "sg:address":"Unit 10C, 30 Kalaroo Rd",
    "sg:city":"Redhead",
    "sg:classifiers":[
        {
            "category":"Retail",
            "subcategory":"Laundry & Dry Cleaning",
            "type":"Services"
        }
    ],
    "sg:phone":"+61 2 4944 8369",
    "sg:postcode":"2290",
    "sg:province":"NSW",
    "sg:tags":[
        "cloth",
        "supply"
    ],
    "wof:name":"ABC Bags Of Rags",
    "wof:placetype":"venue"
},
  "geometry": {"coordinates":[151.70121765100001,-33.0153045654],"type":"Point"}
}