{
  "type": "Feature",
  "properties": {
    "addr:full":"208 Mt Alexander Rd Travancore VIC 3032",
    "addr:housenumber":"208",
    "addr:postcode":"3032",
    "addr:street":"Mt Alexander Rd",
    "iso:country":"AU",
    "sg:address":"208 Mt Alexander Rd",
    "sg:city":"Travancore",
    "sg:classifiers":[
        {
            "category":"Cafe",
            "type":"Food & Drink"
        }
    ],
    "sg:phone":"+61 3 9376 6643",
    "sg:postcode":"3032",
    "sg:province":"VIC",
    "wof:name":"Shop Cafe Take-Away The",
    "wof:placetype":"venue"
},
  "geometry": {"coordinates":[144.932648,-37.781052],"type":"Point"}
}