{
  "type": "Feature",
  "properties": {
    "addr:full":"17B Nathan Drv Campbellfield VIC 3061",
    "addr:housenumber":"17b",
    "addr:postcode":"3061",
    "addr:street":"Nathan Drv",
    "iso:country":"AU",
    "sg:address":"17B Nathan Drv",
    "sg:city":"Campbellfield",
    "sg:classifiers":[
        {
            "category":"Building & Trades",
            "subcategory":"Plumbing",
            "type":"Services"
        }
    ],
    "sg:phone":"+61 3 8339 0100",
    "sg:postcode":"3061",
    "sg:province":"VIC",
    "sg:tags":[
        "plumber",
        "gasfitters"
    ],
    "wof:name":"Richstone Group",
    "wof:placetype":"venue"
},
  "geometry": {"coordinates":[144.941238403,-37.6502685547],"type":"Point"}
}