{
  "type": "Feature",
  "properties": {
    "addr:full":"8 Ford Rd Pontville TAS 7030",
    "addr:housenumber":"8",
    "addr:postcode":"7030",
    "addr:street":"Ford Rd",
    "iso:country":"AU",
    "sg:address":"8 Ford Rd",
    "sg:city":"Pontville",
    "sg:classifiers":[
        {
            "category":"Manufacturing",
            "subcategory":"Food",
            "type":"Manufacturing & Wholesale Goods"
        }
    ],
    "sg:phone":"+61 3 6268 1725",
    "sg:postcode":"7030",
    "sg:province":"TAS",
    "sg:tags":[
        "function",
        "catering"
    ],
    "wof:name":"Quintessential Catering",
    "wof:placetype":"venue"
},
  "geometry": {"coordinates":[147.265258789,-42.6873893738],"type":"Point"}
}