{
  "type": "Feature",
  "properties": {
    "iso:country":"AU",
    "sg:address":"5 Kings La",
    "sg:city":"East Sydney",
    "sg:classifiers":[
        {
            "category":"Personal",
            "subcategory":"Beauty Salon",
            "type":"Services"
        }
    ],
    "sg:phone":"+61 2 9361 5501",
    "sg:postcode":"2010",
    "sg:province":"NSW",
    "sg:tags":[
        "hairdresser"
    ],
    "wof:name":"Hair By Tina Stergio",
    "wof:placetype":"venue"
},
  "geometry": {"coordinates":[151.216720581,-33.8779144287],"type":"Point"}
}