{
  "type": "Feature",
  "properties": {
    "addr:full":"MacKays Rd Coffs Harbour Baringa Orthopaedic Centre Coff NSW 2450",
    "addr:postcode":"2450",
    "addr:street":"Mackays Rd",
    "iso:country":"AU",
    "sg:address":"MacKays Rd",
    "sg:city":"Coffs Harbour Baringa Orthopaedic Centre Coff",
    "sg:classifiers":[
        {
            "category":"Health Services",
            "subcategory":"Doctor",
            "type":"Services"
        }
    ],
    "sg:phone":"+61 2 6652 6777",
    "sg:postcode":"2450",
    "sg:province":"NSW",
    "sg:tags":[
        "medical",
        "practitioner"
    ],
    "wof:name":"Jovanovic Dr Alex",
    "wof:placetype":"venue"
},
  "geometry": {"coordinates":[153.10295099999999,-30.28406],"type":"Point"}
}