{
  "type": "Feature",
  "properties": {
    "iso:country":"AU",
    "sg:address":"26 Barber Rd",
    "sg:city":"Ferny Hills",
    "sg:classifiers":[
        {
            "category":"Professional",
            "subcategory":"Engineering",
            "type":"Services"
        }
    ],
    "sg:phone":"+61 7 3851 1207",
    "sg:postcode":"4055",
    "sg:province":"QLD",
    "sg:tags":[
        "patternmaker"
    ],
    "wof:name":"Gary Hoffman Pattern Making",
    "wof:placetype":"venue"
},
  "geometry": {"coordinates":[152.93768310600001,-27.3901805878],"type":"Point"}
}