{
  "type": "Feature",
  "properties": {
    "addr:full":"293 Corrigan Rd Keysborough VIC 3173",
    "addr:housenumber":"293",
    "addr:postcode":"3173",
    "addr:street":"Corrigan Rd",
    "iso:country":"AU",
    "sg:address":"293 Corrigan Rd",
    "sg:city":"Keysborough",
    "sg:classifiers":[
        {
            "category":"Restaurant",
            "type":"Food & Drink"
        }
    ],
    "sg:phone":"+61 3 9798 6107",
    "sg:postcode":"3173",
    "sg:province":"VIC",
    "wof:name":"Canton Court Chinese Restaurant",
    "wof:placetype":"venue"
},
  "geometry": {"coordinates":[145.16543579099999,-37.9810600281],"type":"Point"}
}