{
  "type": "Feature",
  "properties": {
    "addr:full":"475 Hellawell Rd Sunnybank Hills QLD 4109",
    "addr:housenumber":"475",
    "addr:postcode":"4109",
    "addr:street":"Hellawell Rd",
    "iso:country":"AU",
    "sg:address":"475 Hellawell Rd",
    "sg:city":"Sunnybank Hills",
    "sg:classifiers":[
        {
            "category":"Professional",
            "subcategory":"Employment Agencies",
            "type":"Services"
        }
    ],
    "sg:phone":"+61 7 3273 3222",
    "sg:postcode":"4109",
    "sg:province":"QLD",
    "wof:name":"Employment Initiatives",
    "wof:placetype":"venue"
},
  "geometry": {"coordinates":[153.041137695,-27.5984287262],"type":"Point"}
}