{
  "type": "Feature",
  "properties": {
    "iso:country":"AU",
    "sg:address":"Flat1/ 277 Clarence St",
    "sg:city":"Howrah",
    "sg:classifiers":[
        {
            "category":"Health Services",
            "subcategory":"Chiropractor",
            "type":"Services"
        }
    ],
    "sg:phone":"+61 3 6247 6241",
    "sg:postcode":"7018",
    "sg:province":"TAS",
    "wof:name":"Hurd Caroline Dr.",
    "wof:placetype":"venue"
},
  "geometry": {"coordinates":[147.406784058,-42.8811225891],"type":"Point"}
}