{
  "type": "Feature",
  "properties": {
    "addr:full":"207 Wallarah Rd Gorokan NSW 2263",
    "addr:housenumber":"207",
    "addr:postcode":"2263",
    "addr:street":"Wallarah Rd",
    "iso:country":"AU",
    "sg:address":"207 Wallarah Rd",
    "sg:city":"Gorokan",
    "sg:classifiers":[
        {
            "category":"Manufacturing",
            "subcategory":"Buildings",
            "type":"Manufacturing & Wholesale Goods"
        }
    ],
    "sg:phone":"+61 2 4393 3833",
    "sg:postcode":"2263",
    "sg:province":"NSW",
    "sg:tags":[
        "transportable",
        "domestic",
        "relocatable"
    ],
    "wof:name":"Oasis Caratel Caravan Park",
    "wof:placetype":"venue"
},
  "geometry": {"coordinates":[151.500519,-33.25486],"type":"Point"}
}