{
  "type": "Feature",
  "properties": {
    "addr:full":"Unit 5 21 Jackson St St Kilda VIC 3182",
    "addr:housenumber":"21",
    "addr:postcode":"3182",
    "addr:street":"Jackson St",
    "iso:country":"AU",
    "sg:address":"Unit 5 21 Jackson St",
    "sg:city":"St Kilda",
    "sg:classifiers":[
        {
            "category":"Professional",
            "subcategory":"Employment Agencies",
            "type":"Services"
        }
    ],
    "sg:phone":"+61 413 579 369",
    "sg:postcode":"3182",
    "sg:province":"VIC",
    "sg:tags":[
        "theatrical",
        "managers",
        "agent",
        "producer"
    ],
    "wof:name":"Toffeesuk",
    "wof:placetype":"venue"
},
  "geometry": {"coordinates":[144.97549438499999,-37.862159729],"type":"Point"}
}