{
  "type": "Feature",
  "properties": {
    "iso:country":"AU",
    "sg:address":"33 Port Wakefield Rd",
    "sg:city":"Gepps Cross",
    "sg:classifiers":[
        {
            "category":"Food & Beverages",
            "subcategory":"Supermarket",
            "type":"Retail Goods"
        }
    ],
    "sg:phone":"+61 8 8300 2200",
    "sg:postcode":"5094",
    "sg:province":"SA",
    "sg:tags":[
        "grocery",
        "store"
    ],
    "wof:name":"Bi-Lo",
    "wof:placetype":"venue"
},
  "geometry": {"coordinates":[138.59954834000001,-34.8435516357],"type":"Point"}
}