{
  "type": "Feature",
  "properties": {
    "iso:country":"AU",
    "sg:address":"117 Hannan St",
    "sg:city":"Williamstown",
    "sg:classifiers":[
        {
            "category":"Building & Trades",
            "subcategory":"Plumbing",
            "type":"Services"
        }
    ],
    "sg:phone":"+61 3 9397 1347",
    "sg:postcode":"3016",
    "sg:province":"VIC",
    "sg:tags":[
        "plumber",
        "gasfitters"
    ],
    "wof:name":"Pine R & S Pty Ltd Plumbers",
    "wof:placetype":"venue"
},
  "geometry": {"coordinates":[144.88766479500001,-37.8593597412],"type":"Point"}
}