{
  "type": "Feature",
  "properties": {
    "addr:full":"219 Barkly Ave Richmond VIC 3121",
    "addr:housenumber":"219",
    "addr:postcode":"3121",
    "addr:street":"Barkly Ave",
    "iso:country":"AU",
    "sg:address":"219 Barkly Ave",
    "sg:city":"Richmond",
    "sg:classifiers":[
        {
            "category":"Government",
            "subcategory":"Court House",
            "type":"Public Place"
        }
    ],
    "sg:phone":"+61 3 9429 1333",
    "sg:postcode":"3121",
    "sg:province":"VIC",
    "sg:tags":[
        "personal",
        "marriage",
        "family",
        "counselling"
    ],
    "wof:name":"Acclaim Emotional Guidance",
    "wof:placetype":"venue"
},
  "geometry": {"coordinates":[145.01007080100001,-37.8304634094],"type":"Point"}
}