{
  "type": "Feature",
  "properties": {
    "addr:full":"1079 Mount Alexander Rd Essendon VIC 3040",
    "addr:housenumber":"1079",
    "addr:postcode":"3040",
    "addr:street":"Mount Alexander Rd",
    "iso:country":"AU",
    "sg:address":"1079 Mount Alexander Rd",
    "sg:city":"Essendon",
    "sg:classifiers":[
        {
            "category":"Food & Beverages",
            "subcategory":"Bakery",
            "type":"Retail Goods"
        }
    ],
    "sg:phone":"+61 3 9379 8311",
    "sg:postcode":"3040",
    "sg:province":"VIC",
    "sg:tags":[
        "baker"
    ],
    "wof:name":"Bakers Delight",
    "wof:placetype":"venue"
},
  "geometry": {"coordinates":[144.91041564899999,-37.7454223633],"type":"Point"}
}