{
  "type": "Feature",
  "properties": {
    "addr:full":"77 Elgin St Maitland NSW 2320",
    "addr:housenumber":"77",
    "addr:postcode":"2320",
    "addr:street":"Elgin St",
    "iso:country":"AU",
    "sg:address":"77 Elgin St",
    "sg:city":"Maitland",
    "sg:classifiers":[
        {
            "category":"Retail",
            "subcategory":"Repair Shop",
            "type":"Services"
        }
    ],
    "sg:phone":"+61 2 4934 5244",
    "sg:postcode":"2320",
    "sg:province":"NSW",
    "sg:tags":[
        "upholsterer"
    ],
    "wof:name":"D & L Car Upholstery",
    "wof:placetype":"venue"
},
  "geometry": {"coordinates":[151.55473327600001,-32.7325019836],"type":"Point"}
}