{
  "type": "Feature",
  "properties": {
    "iso:country":"AU",
    "sg:address":"9 Tourello Rd",
    "sg:city":"Mt Eliza",
    "sg:classifiers":[
        {
            "category":"Organizations",
            "subcategory":"Membership Organization",
            "type":"Services"
        }
    ],
    "sg:phone":"+61 3 9787 0216",
    "sg:postcode":"3930",
    "sg:province":"VIC",
    "sg:tags":[
        "equipment",
        "inter-communication",
        "system"
    ],
    "wof:name":"Pandahcare",
    "wof:placetype":"venue"
},
  "geometry": {"coordinates":[145.07632446299999,-38.1846885681],"type":"Point"}
}