{
  "type": "Feature",
  "properties": {
    "iso:country":"AU",
    "sg:address":"1783 Zimin Drv",
    "sg:city":"Katherine",
    "sg:classifiers":[
        {
            "category":"Professional",
            "type":"Services"
        }
    ],
    "sg:phone":"+61 8 8972 3889",
    "sg:postcode":"0850",
    "sg:province":"NT",
    "sg:tags":[
        "transport"
    ],
    "wof:name":"Nighthawk Couriers",
    "wof:placetype":"venue"
},
  "geometry": {"coordinates":[132.24676500000001,-14.453316],"type":"Point"}
}