{
  "type": "Feature",
  "properties": {
    "addr:full":"Shop 16, Homemaker City Zilmere Rd Aspley QLD 4034",
    "addr:housenumber":"shop 16",
    "addr:postcode":"4034",
    "addr:street":"Homemaker City Zilmere Rd",
    "iso:country":"AU",
    "sg:address":"Shop 16, Homemaker City Zilmere Rd",
    "sg:city":"Aspley",
    "sg:classifiers":[
        {
            "category":"Home & Garden",
            "subcategory":"Home Furnishings",
            "type":"Retail Goods"
        }
    ],
    "sg:phone":"+61 7 3862 7400",
    "sg:postcode":"4034",
    "sg:province":"QLD",
    "sg:tags":[
        "shower",
        "screen"
    ],
    "wof:name":"Regency",
    "wof:placetype":"venue"
},
  "geometry": {"coordinates":[153.01965300000001,-27.36422],"type":"Point"}
}