{
  "type": "Feature",
  "properties": {
    "addr:full":"8 Woodlands Rd Forestville NSW 2087",
    "addr:housenumber":"8",
    "addr:postcode":"2087",
    "addr:street":"Woodlands Rd",
    "iso:country":"AU",
    "sg:address":"8 Woodlands Rd",
    "sg:city":"Forestville",
    "sg:classifiers":[
        {
            "category":"Organizations",
            "subcategory":"Labor Organization",
            "type":"Services"
        }
    ],
    "sg:phone":"+61 416 243 832",
    "sg:postcode":"2087",
    "sg:province":"NSW",
    "sg:tags":[
        "pattern",
        "clothing"
    ],
    "wof:name":"Wendy Palmer",
    "wof:placetype":"venue"
},
  "geometry": {"coordinates":[151.20945739699999,-33.7595863342],"type":"Point"}
}