{
  "type": "Feature",
  "properties": {
    "addr:full":"278 Norton St Leichhardt NSW 2040",
    "addr:housenumber":"278",
    "addr:postcode":"2040",
    "addr:street":"Norton St",
    "iso:country":"AU",
    "sg:address":"278 Norton St",
    "sg:city":"Leichhardt",
    "sg:classifiers":[
        {
            "category":"Real Estate",
            "subcategory":"Real Estate Agent",
            "type":"Services"
        }
    ],
    "sg:phone":"+61 2 9568 8900",
    "sg:postcode":"2040",
    "sg:province":"NSW",
    "wof:name":"Re/Max Property Consultants",
    "wof:placetype":"venue"
},
  "geometry": {"coordinates":[151.15617399999999,-33.877701],"type":"Point"}
}