{
  "type": "Feature",
  "properties": {
    "addr:full":"18 Steane St Wangaratta VIC 3677",
    "addr:housenumber":"18",
    "addr:postcode":"3677",
    "addr:street":"Steane St",
    "iso:country":"AU",
    "sg:address":"18 Steane St",
    "sg:city":"Wangaratta",
    "sg:classifiers":[
        {
            "category":"Commercial Area",
            "type":"Public Place"
        }
    ],
    "sg:phone":"+61 3 5721 4184",
    "sg:postcode":"3677",
    "sg:province":"VIC",
    "sg:tags":[
        "heavy",
        "carrier"
    ],
    "wof:name":"Canny B",
    "wof:placetype":"venue"
},
  "geometry": {"coordinates":[146.30722045900001,-36.35572052],"type":"Point"}
}