{
  "type": "Feature",
  "properties": {
    "addr:full":"20 Ace Crs Tuggerah NSW 2259",
    "addr:housenumber":"20",
    "addr:postcode":"2259",
    "addr:street":"Ace Crs",
    "iso:country":"AU",
    "sg:address":"20 Ace Crs",
    "sg:city":"Tuggerah",
    "sg:classifiers":[
        {
            "category":"Arts & Performance",
            "subcategory":"Music",
            "type":"Entertainment"
        }
    ],
    "sg:phone":"+61 2 4353 4899",
    "sg:postcode":"2259",
    "sg:province":"NSW",
    "sg:tags":[
        "hi-fi",
        "equipment"
    ],
    "wof:name":"Electroversal Australia",
    "wof:placetype":"venue"
},
  "geometry": {"coordinates":[151.420410156,-33.3050003052],"type":"Point"}
}