{
  "type": "Feature",
  "properties": {
    "iso:country":"AU",
    "sg:address":"56 King Rd",
    "sg:city":"Vaucluse",
    "sg:classifiers":[
        {
            "category":"Real Estate",
            "subcategory":"Real Estate Services",
            "type":"Services"
        }
    ],
    "sg:phone":"+61 2 9337 5581",
    "sg:postcode":"2030",
    "sg:province":"NSW",
    "sg:tags":[
        "valuer"
    ],
    "wof:name":"D.C. Realty Valuations",
    "wof:placetype":"venue"
},
  "geometry": {"coordinates":[151.28428649899999,-33.8513450623],"type":"Point"}
}