{
  "type": "Feature",
  "properties": {
    "addr:full":"40 Yougenup Rd Gnowangerup WA 6335",
    "addr:housenumber":"40",
    "addr:postcode":"6335",
    "addr:street":"Yougenup Rd",
    "iso:country":"AU",
    "sg:address":"40 Yougenup Rd",
    "sg:city":"Gnowangerup",
    "sg:classifiers":[
        {
            "category":"Food & Beverages",
            "subcategory":"Fruits & Vegetables",
            "type":"Retail Goods"
        }
    ],
    "sg:phone":"+61 8 9827 1253",
    "sg:postcode":"6335",
    "sg:province":"WA",
    "sg:tags":[
        "greengrocer",
        "fruiterer"
    ],
    "wof:name":"Sumich M & B & Sons",
    "wof:placetype":"venue"
},
  "geometry": {"coordinates":[118.007957459,-33.9369621277],"type":"Point"}
}