{
  "type": "Feature",
  "properties": {
    "iso:country":"AU",
    "sg:address":"953B Marion Rd",
    "sg:city":"Mitchell Park",
    "sg:classifiers":[
        {
            "category":"Retail",
            "subcategory":"Auto Repair",
            "type":"Services"
        }
    ],
    "sg:phone":"+61 8 8298 7688",
    "sg:postcode":"5043",
    "sg:province":"SA",
    "sg:tags":[
        "transmission",
        "automotive",
        "car"
    ],
    "wof:name":"Automatics by Bruce Cussans",
    "wof:placetype":"venue"
},
  "geometry": {"coordinates":[138.55909700000001,-35.017006],"type":"Point"}
}