{
  "type": "Feature",
  "properties": {
    "iso:country":"AU",
    "sg:address":"32 Wilbur St",
    "sg:city":"Woodridge",
    "sg:classifiers":[
        {
            "category":"Food & Beverages",
            "subcategory":"Liquor & Beverages",
            "type":"Retail Goods"
        }
    ],
    "sg:phone":"+61 7 3290 2075",
    "sg:postcode":"4114",
    "sg:province":"QLD",
    "sg:tags":[
        "store"
    ],
    "wof:name":"Action Sellers Woodridge",
    "wof:placetype":"venue"
},
  "geometry": {"coordinates":[153.11167907699999,-27.6420822144],"type":"Point"}
}