{
  "type": "Feature",
  "properties": {
    "addr:full":"105 John St Cabramatta NSW 2166",
    "addr:housenumber":"105",
    "addr:postcode":"2166",
    "addr:street":"John St",
    "iso:country":"AU",
    "sg:address":"105 John St",
    "sg:city":"Cabramatta",
    "sg:classifiers":[
        {
            "category":"Shopping",
            "subcategory":"Clothing, Apparel, & Fashions",
            "type":"Retail Goods"
        }
    ],
    "sg:phone":"+61 2 9728 6457",
    "sg:postcode":"2166",
    "sg:province":"NSW",
    "sg:tags":[
        "lady",
        "wear"
    ],
    "wof:name":"Alley Fashions Pty Ltd",
    "wof:placetype":"venue"
},
  "geometry": {"coordinates":[150.934616089,-33.894744873],"type":"Point"}
}