{
  "type": "Feature",
  "properties": {
    "iso:country":"AU",
    "sg:address":"156B Megalong St",
    "sg:city":"Leura",
    "sg:classifiers":[
        {
            "category":"Home & Garden",
            "subcategory":"Garden Supply",
            "type":"Retail Goods"
        }
    ],
    "sg:phone":"+61 2 4784 3146",
    "sg:postcode":"2780",
    "sg:province":"NSW",
    "sg:tags":[
        "nursery"
    ],
    "wof:name":"Leura Country Gardens",
    "wof:placetype":"venue"
},
  "geometry": {"coordinates":[150.333053589,-33.7142333984],"type":"Point"}
}