{
  "type": "Feature",
  "properties": {
    "addr:full":"247 Rathdowne St Carlton VIC 3053",
    "addr:housenumber":"247",
    "addr:postcode":"3053",
    "addr:street":"Rathdowne St",
    "iso:country":"AU",
    "sg:address":"247 Rathdowne St",
    "sg:city":"Carlton",
    "sg:classifiers":[
        {
            "category":"Professional",
            "subcategory":"Accounting & Tax Preparation",
            "type":"Services"
        }
    ],
    "sg:phone":"+61 3 9671 3177",
    "sg:postcode":"3053",
    "sg:province":"VIC",
    "sg:tags":[
        "accountant",
        "auditor"
    ],
    "wof:name":"Frank Piccolo & Co",
    "wof:placetype":"venue"
},
  "geometry": {"coordinates":[144.96963500999999,-37.80128479],"type":"Point"}
}