{
  "type": "Feature",
  "properties": {
    "addr:full":"41a Sydney Rd Manly NSW 2095",
    "addr:housenumber":"41a",
    "addr:postcode":"2095",
    "addr:street":"Sydney Rd",
    "iso:country":"AU",
    "sg:address":"41a Sydney Rd",
    "sg:city":"Manly",
    "sg:classifiers":[
        {
            "category":"Fast Food",
            "type":"Food & Drink"
        }
    ],
    "sg:phone":"+61 2 9977 4998",
    "sg:postcode":"2095",
    "sg:province":"NSW",
    "sg:tags":[
        "away",
        "take"
    ],
    "wof:name":"Northern Beaches Charcoal Chicken",
    "wof:placetype":"venue"
},
  "geometry": {"coordinates":[151.285690308,-33.7971076965],"type":"Point"}
}