{
  "type": "Feature",
  "properties": {
    "iso:country":"AU",
    "sg:address":"156b Carlisle St",
    "sg:city":"St Kilda",
    "sg:classifiers":[
        {
            "category":"Fast Food",
            "type":"Food & Drink"
        }
    ],
    "sg:phone":"+61 3 9525 3555",
    "sg:postcode":"3182",
    "sg:province":"VIC",
    "sg:tags":[
        "away",
        "take"
    ],
    "wof:name":"Carlisle Pizza",
    "wof:placetype":"venue"
},
  "geometry": {"coordinates":[144.989105225,-37.8680381775],"type":"Point"}
}