{
  "type": "Feature",
  "properties": {
    "iso:country":"AU",
    "sg:address":"1 Mary St",
    "sg:city":"Beaumaris",
    "sg:classifiers":[
        {
            "category":"Professional",
            "subcategory":"Employment Agencies",
            "type":"Services"
        }
    ],
    "sg:phone":"+61 3 9589 7899",
    "sg:postcode":"3193",
    "sg:province":"VIC",
    "wof:name":"D.R.M. Management Services Pty Ltd",
    "wof:placetype":"venue"
},
  "geometry": {"coordinates":[145.02970886200001,-37.9745101929],"type":"Point"}
}