{
  "type": "Feature",
  "properties": {
    "iso:country":"AU",
    "sg:address":"311 Hunter St",
    "sg:city":"Newcastle",
    "sg:classifiers":[
        {
            "category":"Personal",
            "subcategory":"Tanning Parlor",
            "type":"Services"
        }
    ],
    "sg:phone":"+61 2 4929 7155",
    "sg:postcode":"2300",
    "sg:province":"NSW",
    "sg:tags":[
        "solarium"
    ],
    "wof:name":"B&#039;Dazzle Tanning Studio",
    "wof:placetype":"venue"
},
  "geometry": {"coordinates":[151.775116,-32.926792],"type":"Point"}
}