{
  "type": "Feature",
  "properties": {
    "addr:full":"Level 1, 193 Macquarie St Sydney NSW 2000",
    "addr:housenumber":"193",
    "addr:postcode":"2000",
    "addr:street":"Macquarie St",
    "iso:country":"AU",
    "sg:address":"Level 1, 193 Macquarie St",
    "sg:city":"Sydney",
    "sg:classifiers":[
        {
            "category":"Health Services",
            "subcategory":"Chiropractor",
            "type":"Services"
        }
    ],
    "sg:phone":"+61 2 9231 6272",
    "sg:postcode":"2000",
    "sg:province":"NSW",
    "wof:name":"Taylor Ian",
    "wof:placetype":"venue"
},
  "geometry": {"coordinates":[151.212127686,-33.8674278259],"type":"Point"}
}