{
  "type": "Feature",
  "properties": {
    "addr:full":"21 Namatjira St Everton Park QLD 4053",
    "addr:housenumber":"21",
    "addr:postcode":"4053",
    "addr:street":"Namatjira St",
    "iso:country":"AU",
    "sg:address":"21 Namatjira St",
    "sg:city":"Everton Park",
    "sg:classifiers":[
        {
            "category":"Utilities",
            "subcategory":"Electric",
            "type":"Services"
        }
    ],
    "sg:phone":"+61 408 626 100",
    "sg:postcode":"4053",
    "sg:province":"QLD",
    "sg:tags":[
        "electrical",
        "contractor"
    ],
    "wof:name":"Choice Electrical Services",
    "wof:placetype":"venue"
},
  "geometry": {"coordinates":[152.991912842,-27.3974761963],"type":"Point"}
}