{
  "type": "Feature",
  "properties": {
    "addr:full":"9-11 Kimberly Rd Dandenong South VIC 3175",
    "addr:housenumber":"9-11",
    "addr:postcode":"3175",
    "addr:street":"Kimberly Rd",
    "iso:country":"AU",
    "sg:address":"9-11 Kimberly Rd",
    "sg:city":"Dandenong South",
    "sg:classifiers":[
        {
            "category":"Building & Trades",
            "subcategory":"Cleaning & Sanitation",
            "type":"Services"
        }
    ],
    "sg:phone":"+61 3 9706 6969",
    "sg:postcode":"3175",
    "sg:province":"VIC",
    "sg:tags":[
        "cleaner",
        "repairer",
        "roof"
    ],
    "wof:name":"Regent Paints Pty Ltd",
    "wof:placetype":"venue"
},
  "geometry": {"coordinates":[145.20411682100001,-38.031047821],"type":"Point"}
}