{
  "type": "Feature",
  "properties": {
    "addr:full":"81a Morgan St Wagga Wagga NSW 2650",
    "addr:housenumber":"81a",
    "addr:postcode":"2650",
    "addr:street":"Morgan St",
    "iso:country":"AU",
    "sg:address":"81a Morgan St",
    "sg:city":"Wagga Wagga",
    "sg:classifiers":[
        {
            "category":"Cafe",
            "type":"Food & Drink"
        }
    ],
    "sg:phone":"+61 2 6921 5306",
    "sg:postcode":"2650",
    "sg:province":"NSW",
    "wof:name":"Cafe Latte",
    "wof:placetype":"venue"
},
  "geometry": {"coordinates":[147.36898803700001,-35.1158561707],"type":"Point"}
}