{
  "type": "Feature",
  "properties": {
    "iso:country":"AU",
    "sg:address":"48 Churchill St",
    "sg:city":"Childers",
    "sg:classifiers":[
        {
            "category":"Farming",
            "subcategory":"Crops",
            "type":"Manufacturing & Wholesale Goods"
        }
    ],
    "sg:phone":"+61 7 4126 1590",
    "sg:postcode":"4660",
    "sg:province":"QLD",
    "sg:tags":[
        "sugarcane",
        "mill",
        "grower"
    ],
    "wof:name":"B S E S",
    "wof:placetype":"venue"
},
  "geometry": {"coordinates":[152.27967834500001,-25.236328125],"type":"Point"}
}