{
  "type": "Feature",
  "properties": {
    "iso:country":"AU",
    "sg:address":"Unit 1/ 5 Tulagi Rd",
    "sg:city":"Palmerston",
    "sg:classifiers":[
        {
            "category":"Professional",
            "subcategory":"Engineering",
            "type":"Services"
        }
    ],
    "sg:phone":"+61 8 8983 3956",
    "sg:postcode":"0830",
    "sg:province":"NT",
    "sg:tags":[
        "consulting",
        "engineer"
    ],
    "wof:name":"Royal Engineering Pty Ltd",
    "wof:placetype":"venue"
},
  "geometry": {"coordinates":[130.990021,-12.469336],"type":"Point"}
}