{
  "type": "Feature",
  "properties": {
    "iso:country":"AU",
    "sg:address":"250 Ballarat Rd",
    "sg:city":"Footscray",
    "sg:classifiers":[
        {
            "category":"Retail",
            "subcategory":"Auto Repair",
            "type":"Services"
        }
    ],
    "sg:phone":"+61 3 9317 7588",
    "sg:postcode":"3011",
    "sg:province":"VIC",
    "sg:tags":[
        "beater",
        "painter",
        "panel"
    ],
    "wof:name":"Woods Accident Repair Centres",
    "wof:placetype":"venue"
},
  "geometry": {"coordinates":[144.885894775,-37.7895507812],"type":"Point"}
}