{
  "type": "Feature",
  "properties": {
    "iso:country":"AU",
    "sg:address":"PO Box 1369",
    "sg:city":"Hawksburn",
    "sg:classifiers":[
        {
            "category":"Professional",
            "subcategory":"Art Services",
            "type":"Services"
        }
    ],
    "sg:phone":"+61 419 886 414",
    "sg:postcode":"3142",
    "sg:province":"VIC",
    "sg:tags":[
        "interior",
        "decorator"
    ],
    "wof:name":"Indeco",
    "wof:placetype":"venue"
},
  "geometry": {"coordinates":[145.00471496599999,-37.8466186523],"type":"Point"}
}