{
  "type": "Feature",
  "properties": {
    "addr:full":"6 Church St Salisbury SA 5108",
    "addr:housenumber":"6",
    "addr:postcode":"5108",
    "addr:street":"Church St",
    "iso:country":"AU",
    "sg:address":"6 Church St",
    "sg:city":"Salisbury",
    "sg:classifiers":[
        {
            "category":"Building & Trades",
            "subcategory":"Landscaping Services",
            "type":"Services"
        }
    ],
    "sg:phone":"+61 8 8258 1177",
    "sg:postcode":"5108",
    "sg:province":"SA",
    "sg:tags":[
        "consultant"
    ],
    "wof:name":"Dennis Underwood & Associates",
    "wof:placetype":"venue"
},
  "geometry": {"coordinates":[138.64576721200001,-34.7637443542],"type":"Point"}
}