{
  "type": "Feature",
  "properties": {
    "iso:country":"AU",
    "sg:address":"68 Florence St",
    "sg:city":"Port Pirie",
    "sg:classifiers":[
        {
            "category":"Fast Food",
            "type":"Food & Drink"
        }
    ],
    "sg:phone":"+61 8 8632 6188",
    "sg:postcode":"5540",
    "sg:province":"SA",
    "sg:tags":[
        "away",
        "take"
    ],
    "wof:name":"Pirie Pizza",
    "wof:placetype":"venue"
},
  "geometry": {"coordinates":[138.00845336899999,-33.1768035889],"type":"Point"}
}