{
  "type": "Feature",
  "properties": {
    "iso:country":"AU",
    "sg:address":"4 Harmer Crt",
    "sg:city":"Horsham",
    "sg:classifiers":[
        {
            "category":"Building & Trades",
            "subcategory":"Plumbing",
            "type":"Services"
        }
    ],
    "sg:phone":"+61 3 5382 3392",
    "sg:postcode":"3400",
    "sg:province":"VIC",
    "sg:tags":[
        "plumber",
        "gasfitters"
    ],
    "wof:name":"Diwell K & N",
    "wof:placetype":"venue"
},
  "geometry": {"coordinates":[142.17906189000001,-36.7264976501],"type":"Point"}
}