{
  "type": "Feature",
  "properties": {
    "addr:full":"42 Young St Sylvania NSW 2224",
    "addr:housenumber":"42",
    "addr:postcode":"2224",
    "addr:street":"Young St",
    "iso:country":"AU",
    "sg:address":"42 Young St",
    "sg:city":"Sylvania",
    "sg:classifiers":[
        {
            "category":"Building & Trades",
            "subcategory":"Construction",
            "type":"Services"
        }
    ],
    "sg:phone":"+61 2 9522 6871",
    "sg:postcode":"2224",
    "sg:province":"NSW",
    "sg:tags":[
        "repairing",
        "window"
    ],
    "wof:name":"Whittaker K & G",
    "wof:placetype":"venue"
},
  "geometry": {"coordinates":[151.092987061,-34.0106391907],"type":"Point"}
}