{
  "type": "Feature",
  "properties": {
    "addr:full":"1320 Centre Rd Clayton VIC 3168",
    "addr:housenumber":"1320",
    "addr:postcode":"3168",
    "addr:street":"Centre Rd",
    "iso:country":"AU",
    "sg:address":"1320 Centre Rd",
    "sg:city":"Clayton",
    "sg:classifiers":[
        {
            "category":"Health Services",
            "subcategory":"Doctor",
            "type":"Services"
        }
    ],
    "sg:phone":"+61 3 9543 7696",
    "sg:postcode":"3168",
    "sg:province":"VIC",
    "sg:tags":[
        "podiatrist"
    ],
    "wof:name":"Bagiotas Nicholas D",
    "wof:placetype":"venue"
},
  "geometry": {"coordinates":[145.11714172399999,-37.9283981323],"type":"Point"}
}