{
  "type": "Feature",
  "properties": {
    "iso:country":"AU",
    "sg:address":"Lvl 1/ 14 Bay St",
    "sg:city":"Double Bay",
    "sg:classifiers":[
        {
            "category":"Personal",
            "subcategory":"Beauty Salon",
            "type":"Services"
        }
    ],
    "sg:phone":"+61 2 9363 3234",
    "sg:postcode":"2028",
    "sg:province":"NSW",
    "wof:name":"Votre Beaute",
    "wof:placetype":"venue"
},
  "geometry": {"coordinates":[151.24130249000001,-33.8778457642],"type":"Point"}
}