{
  "type": "Feature",
  "properties": {
    "iso:country":"AU",
    "sg:address":"Shop 19, St Clair Shopping Centre Bennett Rd St",
    "sg:city":"Clair",
    "sg:classifiers":[
        {
            "category":"Shopping",
            "subcategory":"Optical Goods",
            "type":"Retail Goods"
        }
    ],
    "sg:phone":"+61 2 9670 4637",
    "sg:postcode":"2759",
    "sg:province":"NSW",
    "sg:tags":[
        "dispenser",
        "prescription"
    ],
    "wof:name":"Optix 2000",
    "wof:placetype":"venue"
},
  "geometry": {"coordinates":[150.790161133,-33.7955169678],"type":"Point"}
}