{
  "type": "Feature",
  "properties": {
    "iso:country":"AU",
    "sg:address":"52 Ingleside Rd",
    "sg:city":"Ingleside",
    "sg:classifiers":[
        {
            "category":"Professional",
            "subcategory":"Engineering",
            "type":"Services"
        }
    ],
    "sg:phone":"+61 2 9970 7775",
    "sg:postcode":"2101",
    "sg:province":"NSW",
    "sg:tags":[
        "electrical",
        "engineer"
    ],
    "wof:name":"Controltec Pty Ltd",
    "wof:placetype":"venue"
},
  "geometry": {"coordinates":[151.279953,-33.696552],"type":"Point"}
}