{
  "type": "Feature",
  "properties": {
    "addr:full":"Suite 3 47 Sydney Rd Manly NSW 2095",
    "addr:housenumber":"47",
    "addr:postcode":"2095",
    "addr:street":"Sydney Rd",
    "iso:country":"AU",
    "sg:address":"Suite 3 47 Sydney Rd",
    "sg:city":"Manly",
    "sg:classifiers":[
        {
            "category":"Professional",
            "subcategory":"Employment Agencies",
            "type":"Services"
        }
    ],
    "sg:phone":"+61 2 9976 5199",
    "sg:postcode":"2095",
    "sg:province":"NSW",
    "wof:name":"EVP Recruitment",
    "wof:placetype":"venue"
},
  "geometry": {"coordinates":[151.285247803,-33.7970237732],"type":"Point"}
}