{
  "type": "Feature",
  "properties": {
    "addr:full":"Cnr Alf O'Rourke Drv & Bryan Jordan Drv Gladstone QLD 4680",
    "addr:postcode":"4680",
    "addr:street":"Cnr Alf O'Rourke Drv & Bryan Jordan Drv",
    "iso:country":"AU",
    "sg:address":"Cnr Alf O'Rourke Drv & Bryan Jordan Drv",
    "sg:city":"Gladstone",
    "sg:classifiers":[
        {
            "category":"Industrial Area",
            "type":"Public Place"
        }
    ],
    "sg:phone":"+61 7 4972 5888",
    "sg:postcode":"4680",
    "sg:province":"QLD",
    "sg:tags":[
        "rural",
        "shed"
    ],
    "wof:name":"Australian Garages & Carports",
    "wof:placetype":"venue"
},
  "geometry": {"coordinates":[151.24734497099999,-23.8442268372],"type":"Point"}
}