{
  "type": "Feature",
  "properties": {
    "iso:country":"AU",
    "sg:address":"Unit 3, 227 Junction Rd",
    "sg:city":"Morningside",
    "sg:classifiers":[
        {
            "category":"Communications",
            "type":"Services"
        }
    ],
    "sg:phone":"+61 7 3899 6799",
    "sg:postcode":"4170",
    "sg:province":"QLD",
    "sg:tags":[
        "data"
    ],
    "wof:name":"Stronglink/CDT Pty Ltd",
    "wof:placetype":"venue"
},
  "geometry": {"coordinates":[153.08583068900001,-27.4584255219],"type":"Point"}
}