{
  "type": "Feature",
  "properties": {
    "iso:country":"AU",
    "sg:address":"Townsend St",
    "sg:city":"Rockingham",
    "sg:classifiers":[
        {
            "category":"Social Services",
            "subcategory":"Child Care",
            "type":"Services"
        }
    ],
    "sg:phone":"+61 8 9592 2051",
    "sg:postcode":"6168",
    "sg:province":"WA",
    "wof:name":"Star of The Sea Out of School Care",
    "wof:placetype":"venue"
},
  "geometry": {"coordinates":[115.732307,-32.286312],"type":"Point"}
}