{
  "type": "Feature",
  "properties": {
    "addr:full":"99 Selwyn St Mayfield East NSW 2304",
    "addr:housenumber":"99",
    "addr:postcode":"2304",
    "addr:street":"Selwyn St",
    "iso:country":"AU",
    "sg:address":"99 Selwyn St",
    "sg:city":"Mayfield East",
    "sg:classifiers":[
        {
            "category":"Organizations",
            "subcategory":"Professional Association",
            "type":"Services"
        }
    ],
    "sg:phone":"+61 2 4969 9600",
    "sg:postcode":"2304",
    "sg:province":"NSW",
    "sg:tags":[
        "organisation",
        "business"
    ],
    "wof:name":"Hunter Business Chamber",
    "wof:placetype":"venue"
},
  "geometry": {"coordinates":[151.759475708,-32.8984260559],"type":"Point"}
}