{
  "type": "Feature",
  "properties": {
    "iso:country":"AU",
    "sg:address":"20 Mcbean St",
    "sg:city":"Yeppoon",
    "sg:classifiers":[
        {
            "category":"Autos & Motor Vehicles",
            "subcategory":"Auto Supplies",
            "type":"Retail Goods"
        }
    ],
    "sg:phone":"+61 7 4939 4119",
    "sg:postcode":"4703",
    "sg:province":"QLD",
    "sg:tags":[
        "tyre"
    ],
    "wof:name":"Keepel Tyre & Mechanical",
    "wof:placetype":"venue"
},
  "geometry": {"coordinates":[150.73643493599999,-23.1397514343],"type":"Point"}
}