{
  "type": "Feature",
  "properties": {
    "iso:country":"AU",
    "sg:address":"9A Adam St",
    "sg:city":"Bendigo",
    "sg:classifiers":[
        {
            "category":"Retail",
            "subcategory":"Auto Repair",
            "type":"Services"
        }
    ],
    "sg:phone":"+61 3 5443 8890",
    "sg:postcode":"3550",
    "sg:province":"VIC",
    "sg:tags":[
        "repairer",
        "motor",
        "engineer"
    ],
    "wof:name":"Bendigo Radiators",
    "wof:placetype":"venue"
},
  "geometry": {"coordinates":[144.27528381400001,-36.7709465027],"type":"Point"}
}