{
  "type": "Feature",
  "properties": {
    "iso:country":"AU",
    "sg:address":"93 Power Rd",
    "sg:city":"Doveton",
    "sg:classifiers":[
        {
            "category":"Professional",
            "type":"Services"
        }
    ],
    "sg:phone":"+61 408 038 768",
    "sg:postcode":"3177",
    "sg:province":"VIC",
    "sg:tags":[
        "control",
        "equipment",
        "traffic"
    ],
    "wof:name":"Victorian Traffic Management (Doveton)",
    "wof:placetype":"venue"
},
  "geometry": {"coordinates":[145.238113403,-37.9876403809],"type":"Point"}
}