{
  "type": "Feature",
  "properties": {
    "addr:full":"Shp1/ 1 Kensington Drv Minyama QLD 4575",
    "addr:housenumber":"1",
    "addr:postcode":"4575",
    "addr:street":"Kensington Drv",
    "iso:country":"AU",
    "sg:address":"Shp1/ 1 Kensington Drv",
    "sg:city":"Minyama",
    "sg:classifiers":[
        {
            "category":"Food & Beverages",
            "subcategory":"Groceries & Convenience Stores",
            "type":"Retail Goods"
        }
    ],
    "sg:phone":"+61 7 5444 6942",
    "sg:postcode":"4575",
    "sg:province":"QLD",
    "wof:name":"FoodWorks Minyama",
    "wof:placetype":"venue"
},
  "geometry": {"coordinates":[153.123535,-26.700809],"type":"Point"}
}