{
  "type": "Feature",
  "properties": {
    "addr:full":"Factory 5 36 Jersey Rd Bayswater VIC 3153",
    "addr:housenumber":"36",
    "addr:postcode":"3153",
    "addr:street":"Jersey Rd",
    "iso:country":"AU",
    "sg:address":"Factory 5 36 Jersey Rd",
    "sg:city":"Bayswater",
    "sg:classifiers":[
        {
            "category":"Professional",
            "subcategory":"Engineering",
            "type":"Services"
        }
    ],
    "sg:phone":"+61 3 9720 4432",
    "sg:postcode":"3153",
    "sg:province":"VIC",
    "sg:tags":[
        "engineer"
    ],
    "wof:name":"JADE Engineering",
    "wof:placetype":"venue"
},
  "geometry": {"coordinates":[145.279022217,-37.843460083],"type":"Point"}
}