{
  "type": "Feature",
  "properties": {
    "addr:full":"19 Centenary Crs Maroochydore QLD 4558",
    "addr:housenumber":"19",
    "addr:postcode":"4558",
    "addr:street":"Centenary Crs",
    "iso:country":"AU",
    "sg:address":"19 Centenary Crs",
    "sg:city":"Maroochydore",
    "sg:classifiers":[
        {
            "category":"Personal",
            "subcategory":"Massage",
            "type":"Services"
        }
    ],
    "sg:phone":"+61 7 5443 1936",
    "sg:postcode":"4558",
    "sg:province":"QLD",
    "sg:tags":[
        "therapy"
    ],
    "wof:name":"Massage Works",
    "wof:placetype":"venue"
},
  "geometry": {"coordinates":[153.06553649899999,-26.6553192139],"type":"Point"}
}