{
  "type": "Feature",
  "properties": {
    "addr:full":"104 Sugar Rd Maroochydore QLD 4558",
    "addr:housenumber":"104",
    "addr:postcode":"4558",
    "addr:street":"Sugar Rd",
    "iso:country":"AU",
    "sg:address":"104 Sugar Rd",
    "sg:city":"Maroochydore",
    "sg:classifiers":[
        {
            "category":"Utilities",
            "subcategory":"Mobile Phone",
            "type":"Services"
        }
    ],
    "sg:phone":"+61 7 5479 1179",
    "sg:postcode":"4558",
    "sg:province":"QLD",
    "sg:tags":[
        "repair",
        "telephone"
    ],
    "wof:name":"Network Communications",
    "wof:placetype":"venue"
},
  "geometry": {"coordinates":[153.09512329099999,-26.6696548462],"type":"Point"}
}