{
  "type": "Feature",
  "properties": {
    "iso:country":"AU",
    "sg:address":"PO Box 313",
    "sg:city":"Merbein",
    "sg:classifiers":[
        {
            "category":"Shopping",
            "subcategory":"Musical Instruments",
            "type":"Retail Goods"
        }
    ],
    "sg:phone":"+61 3 5025 2308",
    "sg:postcode":"3505",
    "sg:province":"VIC",
    "sg:tags":[
        "musician",
        "agent"
    ],
    "wof:name":"Sunraysia Entertainment Agency",
    "wof:placetype":"venue"
},
  "geometry": {"coordinates":[142.05857849099999,-34.1675605774],"type":"Point"}
}