{
  "type": "Feature",
  "properties": {
    "iso:country":"AU",
    "sg:address":"2/ 251 Latrobe Tce",
    "sg:city":"Geelong",
    "sg:classifiers":[
        {
            "category":"Banks & Credit Unions",
            "subcategory":"Financial Services",
            "type":"Services"
        }
    ],
    "sg:phone":"+61 3 5222 2999",
    "sg:postcode":"3220",
    "sg:province":"VIC",
    "sg:tags":[
        "loan",
        "finance",
        "mortgage"
    ],
    "wof:name":"Lifeline Financial Services",
    "wof:placetype":"venue"
},
  "geometry": {"coordinates":[144.35287500000001,-38.147678],"type":"Point"}
}