{
  "type": "Feature",
  "properties": {
    "addr:full":"67a Abundance Rd Medowie NSW 2318",
    "addr:housenumber":"67a",
    "addr:postcode":"2318",
    "addr:street":"Abundance Rd",
    "iso:country":"AU",
    "sg:address":"67a Abundance Rd",
    "sg:city":"Medowie",
    "sg:classifiers":[
        {
            "category":"Farming",
            "subcategory":"Nursery",
            "type":"Manufacturing & Wholesale Goods"
        }
    ],
    "sg:phone":"+61 2 4981 7950",
    "sg:postcode":"2318",
    "sg:province":"NSW",
    "wof:name":"Hunter Region Growers",
    "wof:placetype":"venue"
},
  "geometry": {"coordinates":[151.85434000000001,-32.751343],"type":"Point"}
}