{
  "type": "Feature",
  "properties": {
    "addr:full":"71 Redland Bay Rd Capalaba QLD 4157",
    "addr:housenumber":"71",
    "addr:postcode":"4157",
    "addr:street":"Redland Bay Rd",
    "iso:country":"AU",
    "sg:address":"71 Redland Bay Rd",
    "sg:city":"Capalaba",
    "sg:classifiers":[
        {
            "category":"Retail",
            "subcategory":"Storage",
            "type":"Services"
        }
    ],
    "sg:phone":"+61 1800 682 129",
    "sg:postcode":"4157",
    "sg:province":"QLD",
    "sg:tags":[
        "removal",
        "furniture"
    ],
    "wof:name":"D.J. Lindsay Removals",
    "wof:placetype":"venue"
},
  "geometry": {"coordinates":[153.20782470699999,-27.5357379913],"type":"Point"}
}