{
  "type": "Feature",
  "properties": {
    "addr:full":"Shop 4/ 55 Lavender St Milsons Point NSW 2061",
    "addr:housenumber":"shop 4 / 55",
    "addr:postcode":"2061",
    "addr:street":"Lavender St",
    "iso:country":"AU",
    "sg:address":"Shop 4/ 55 Lavender St",
    "sg:city":"Milsons Point",
    "sg:classifiers":[
        {
            "category":"Travel",
            "subcategory":"Travel Agent",
            "type":"Entertainment"
        }
    ],
    "sg:phone":"+61 2 9929 0111",
    "sg:postcode":"2061",
    "sg:province":"NSW",
    "sg:tags":[
        "consultant"
    ],
    "wof:name":"Alice's Wonderland Corporate Travel",
    "wof:placetype":"venue"
},
  "geometry": {"coordinates":[151.20970153799999,-33.8435440063],"type":"Point"}
}