{
  "type": "Feature",
  "properties": {
    "iso:country":"AU",
    "sg:address":"30 Barwan St",
    "sg:city":"Narrabri",
    "sg:classifiers":[
        {
            "category":"Wholesale",
            "subcategory":"Fruits & Vegetables",
            "type":"Manufacturing & Wholesale Goods"
        }
    ],
    "sg:phone":"+61 2 6792 1433",
    "sg:postcode":"2390",
    "sg:province":"NSW",
    "sg:tags":[
        "produce",
        "grain"
    ],
    "wof:name":"SunPrime Seeds",
    "wof:placetype":"venue"
},
  "geometry": {"coordinates":[149.78596496599999,-30.327703476],"type":"Point"}
}