{
  "type": "Feature",
  "properties": {
    "addr:full":"Cnr Annand & Union Sts Toowoomba QLD 4352",
    "addr:postcode":"4352",
    "addr:street":"Cnr Annand &;Sts",
    "iso:country":"AU",
    "sg:address":"Cnr Annand & Union Sts",
    "sg:city":"Toowoomba",
    "sg:classifiers":[
        {
            "category":"Banks & Credit Unions",
            "subcategory":"Bureau De Change",
            "type":"Services"
        }
    ],
    "sg:phone":"+61 7 4632 3604",
    "sg:postcode":"4352",
    "sg:province":"QLD",
    "sg:tags":[
        "planning",
        "family"
    ],
    "wof:name":"Natural Fertility Services",
    "wof:placetype":"venue"
},
  "geometry": {"coordinates":[151.95422400000001,-27.562162],"type":"Point"}
}