{
  "type": "Feature",
  "properties": {
    "addr:full":"22 Tamborine St Jimboomba QLD 4280",
    "addr:housenumber":"22",
    "addr:postcode":"4280",
    "addr:street":"Tamborine St",
    "iso:country":"AU",
    "sg:address":"22 Tamborine St",
    "sg:city":"Jimboomba",
    "sg:classifiers":[
        {
            "category":"Professional",
            "type":"Services"
        }
    ],
    "sg:phone":"+61 7 5546 9650",
    "sg:postcode":"4280",
    "sg:province":"QLD",
    "sg:tags":[
        "spray",
        "painting"
    ],
    "wof:name":"Jimboomba Smash Repairs",
    "wof:placetype":"venue"
},
  "geometry": {"coordinates":[153.03062399999999,-27.821838],"type":"Point"}
}