{
  "type": "Feature",
  "properties": {
    "addr:full":"Factory 6/8- 9 Gabrielle Crt Bayswater North VIC 3153",
    "addr:housenumber":"/ 8 9",
    "addr:postcode":"3153",
    "addr:street":"Gabrielle Crt",
    "iso:country":"AU",
    "sg:address":"Factory 6/8- 9 Gabrielle Crt",
    "sg:city":"Bayswater North",
    "sg:classifiers":[
        {
            "category":"Retail",
            "subcategory":"Auto Repair",
            "type":"Services"
        }
    ],
    "sg:phone":"+61 3 9761 4549",
    "sg:postcode":"3153",
    "sg:province":"VIC",
    "sg:tags":[
        "repairer",
        "motor",
        "engineer"
    ],
    "wof:name":"Smooth Drive Automotive Services",
    "wof:placetype":"venue"
},
  "geometry": {"coordinates":[145.28607177699999,-37.8236236572],"type":"Point"}
}