{
  "type": "Feature",
  "properties": {
    "iso:country":"AU",
    "sg:address":"McHugh St",
    "sg:city":"Kings Meadows",
    "sg:classifiers":[
        {
            "category":"Health Services",
            "subcategory":"Health Practitioner",
            "type":"Services"
        }
    ],
    "sg:phone":"+61 3 6336 5155",
    "sg:postcode":"7249",
    "sg:province":"TAS",
    "sg:tags":[
        "physiotherapist"
    ],
    "wof:name":"Curl M",
    "wof:placetype":"venue"
},
  "geometry": {"coordinates":[147.16192626899999,-41.467628479],"type":"Point"}
}