{
  "type": "Feature",
  "properties": {
    "iso:country":"AU",
    "sg:address":"27 Deborah St",
    "sg:city":"Bendigo",
    "sg:classifiers":[
        {
            "category":"Wholesale",
            "subcategory":"Machinery & Supplies",
            "type":"Manufacturing & Wholesale Goods"
        }
    ],
    "sg:phone":"+61 3 5441 2662",
    "sg:postcode":"3550",
    "sg:province":"VIC",
    "sg:tags":[
        "engineer"
    ],
    "wof:name":"Blackwood J & Son Ltd",
    "wof:placetype":"venue"
},
  "geometry": {"coordinates":[144.27268981899999,-36.7753715515],"type":"Point"}
}