{
  "type": "Feature",
  "properties": {
    "iso:country":"AU",
    "sg:address":"603 Parramatta Rd",
    "sg:city":"Leichhardt",
    "sg:classifiers":[
        {
            "category":"Retail",
            "subcategory":"Car Wash",
            "type":"Services"
        }
    ],
    "sg:phone":"+61 2 9564 0841",
    "sg:postcode":"2040",
    "sg:province":"NSW",
    "sg:tags":[
        "truck",
        "cleaning"
    ],
    "wof:name":"Avant-Garde Car Detailing",
    "wof:placetype":"venue"
},
  "geometry": {"coordinates":[151.150177,-33.889477],"type":"Point"}
}