{
  "type": "Feature",
  "properties": {
    "iso:country":"AU",
    "sg:address":"32 Penshurst St",
    "sg:city":"Penshurst",
    "sg:classifiers":[
        {
            "category":"Personal",
            "subcategory":"Beauty Salon",
            "type":"Services"
        }
    ],
    "sg:phone":"+61 2 9579 4028",
    "sg:postcode":"2222",
    "sg:province":"NSW",
    "sg:tags":[
        "hairdresser"
    ],
    "wof:name":"Stunners Hair Design Pty Ltd",
    "wof:placetype":"venue"
},
  "geometry": {"coordinates":[151.08843994099999,-33.9650840759],"type":"Point"}
}