{
  "type": "Feature",
  "properties": {
    "addr:full":"Unit 13 405 Bayswater Rd Garbutt QLD 4814",
    "addr:housenumber":"405",
    "addr:postcode":"4814",
    "addr:street":"Bayswater Rd",
    "iso:country":"AU",
    "sg:address":"Unit 13 405 Bayswater Rd",
    "sg:city":"Garbutt",
    "sg:classifiers":[
        {
            "category":"Home & Garden",
            "subcategory":"Home Furnishings",
            "type":"Retail Goods"
        }
    ],
    "sg:phone":"+61 7 4775 5444",
    "sg:postcode":"4814",
    "sg:province":"QLD",
    "sg:tags":[
        "wicker",
        "cane",
        "furniture"
    ],
    "wof:name":"Cane Fix",
    "wof:placetype":"venue"
},
  "geometry": {"coordinates":[146.75578300000001,-19.27244],"type":"Point"}
}