{
  "type": "Feature",
  "properties": {
    "iso:country":"AU",
    "sg:address":"5 Ensenada Rd",
    "sg:city":"Copacabana",
    "sg:classifiers":[
        {
            "category":"Home & Garden",
            "subcategory":"Building Materials",
            "type":"Retail Goods"
        }
    ],
    "sg:phone":"+61 423 571 065",
    "sg:postcode":"2251",
    "sg:province":"NSW",
    "sg:tags":[
        "lawn",
        "cutting",
        "maintenance"
    ],
    "wof:name":"Ozcut",
    "wof:placetype":"venue"
},
  "geometry": {"coordinates":[151.435302734,-33.4872055054],"type":"Point"}
}