{
  "type": "Feature",
  "properties": {
    "addr:full":"Ryans Rd Eltham VIC 3095",
    "addr:postcode":"3095",
    "addr:street":"Ryans Rd",
    "iso:country":"AU",
    "sg:address":"Ryans Rd",
    "sg:city":"Eltham",
    "sg:classifiers":[
        {
            "category":"Personal",
            "subcategory":"Massage",
            "type":"Services"
        }
    ],
    "sg:phone":"+61 414 398 334",
    "sg:postcode":"3095",
    "sg:province":"VIC",
    "sg:tags":[
        "therapy"
    ],
    "wof:name":"Geraldine Turner Remedial Massage Therapy",
    "wof:placetype":"venue"
},
  "geometry": {"coordinates":[145.13841247600001,-37.7141685486],"type":"Point"}
}