{
  "type": "Feature",
  "properties": {
    "addr:full":"Shop 38A Milleara Shopping Centre, Milleara Road Keilor East VIC 3033",
    "addr:housenumber":"38a",
    "addr:postcode":"3033",
    "addr:street":"Milleara;Milleara Road",
    "iso:country":"AU",
    "sg:address":"Shop 38A Milleara Shopping Centre, Milleara Road",
    "sg:city":"Keilor East",
    "sg:classifiers":[
        {
            "category":"Personal",
            "subcategory":"Beauty Salon",
            "type":"Services"
        }
    ],
    "sg:phone":"+61 3 9331 0702",
    "sg:postcode":"3033",
    "sg:province":"VIC",
    "sg:tags":[
        "hairdresser"
    ],
    "wof:name":"Rinaldo Hairdressing",
    "wof:placetype":"venue"
},
  "geometry": {"coordinates":[144.864349,-37.737251],"type":"Point"}
}