{
  "type": "Feature",
  "properties": {
    "iso:country":"AU",
    "sg:address":"405- 409 Nepean Hwy",
    "sg:city":"Frankston",
    "sg:classifiers":[
        {
            "category":"Professional",
            "subcategory":"Employment Agencies",
            "type":"Services"
        }
    ],
    "sg:phone":"+61 3 9781 4442",
    "sg:postcode":"3199",
    "sg:province":"VIC",
    "sg:website":"http://www.pprr.com.au",
    "wof:name":"Peninsula People Recruitment",
    "wof:placetype":"venue"
},
  "geometry": {"coordinates":[145.08453369099999,-38.000831604],"type":"Point"}
}