{
  "type": "Feature",
  "properties": {
    "addr:full":"99 Elimatta Rd Mona Vale NSW 2103",
    "addr:housenumber":"99",
    "addr:postcode":"2103",
    "addr:street":"Elimatta Rd",
    "iso:country":"AU",
    "sg:address":"99 Elimatta Rd",
    "sg:city":"Mona Vale",
    "sg:classifiers":[
        {
            "category":"Travel",
            "subcategory":"Hostel",
            "type":"Entertainment"
        }
    ],
    "sg:phone":"+61 2 9997 5100",
    "sg:postcode":"2103",
    "sg:province":"NSW",
    "sg:tags":[
        "home"
    ],
    "wof:name":"George Mockler House",
    "wof:placetype":"venue"
},
  "geometry": {"coordinates":[151.296875,-33.6802597046],"type":"Point"}
}