{
  "type": "Feature",
  "properties": {
    "addr:full":"44 Lewis St Dee Why NSW 2099",
    "addr:housenumber":"44",
    "addr:postcode":"2099",
    "addr:street":"Lewis St",
    "iso:country":"AU",
    "sg:address":"44 Lewis St",
    "sg:city":"Dee Why",
    "sg:classifiers":[
        {
            "category":"Home & Garden",
            "subcategory":"Household Appliances",
            "type":"Retail Goods"
        }
    ],
    "sg:phone":"+61 414 965 789",
    "sg:postcode":"2099",
    "sg:province":"NSW",
    "sg:tags":[
        "chemical",
        "equipment",
        "steam",
        "cleaning",
        "pressure"
    ],
    "wof:name":"D & E Cleaning Services",
    "wof:placetype":"venue"
},
  "geometry": {"coordinates":[151.28269958499999,-33.7515335083],"type":"Point"}
}