{
  "type": "Feature",
  "properties": {
    "addr:full":"89 Austin St Lane Cove NSW 2066",
    "addr:housenumber":"89",
    "addr:postcode":"2066",
    "addr:street":"Austin St",
    "iso:country":"AU",
    "sg:address":"89 Austin St",
    "sg:city":"Lane Cove",
    "sg:classifiers":[
        {
            "category":"Shopping",
            "subcategory":"Antiques",
            "type":"Retail Goods"
        }
    ],
    "sg:phone":"+61 2 9427 1179",
    "sg:postcode":"2066",
    "sg:province":"NSW",
    "sg:tags":[
        "restoration",
        "reproduction"
    ],
    "wof:name":"Leo Hornak French Polishing",
    "wof:placetype":"venue"
},
  "geometry": {"coordinates":[151.169555664,-33.821685791],"type":"Point"}
}