{
  "type": "Feature",
  "properties": {
    "addr:full":"Granary La Mentone VIC 3194",
    "addr:postcode":"3194",
    "iso:country":"AU",
    "sg:address":"Granary La",
    "sg:city":"Mentone",
    "sg:classifiers":[
        {
            "category":"Education",
            "subcategory":"Special Training",
            "type":"Public Place"
        }
    ],
    "sg:phone":"+61 3 9584 6376",
    "sg:postcode":"3194",
    "sg:province":"VIC",
    "sg:tags":[
        "school",
        "art"
    ],
    "wof:name":"Mentone Mordialloc Art Group Inc",
    "wof:placetype":"venue"
},
  "geometry": {"coordinates":[145.06376648,-37.9819755554],"type":"Point"}
}