{
  "type": "Feature",
  "properties": {
    "addr:full":"370 Darebin Rd Thornbury VIC 3071",
    "addr:housenumber":"370",
    "addr:postcode":"3071",
    "addr:street":"Darebin Rd",
    "iso:country":"AU",
    "sg:address":"370 Darebin Rd",
    "sg:city":"Thornbury",
    "sg:classifiers":[
        {
            "category":"Manufacturing",
            "subcategory":"Rubber & Plastics",
            "type":"Manufacturing & Wholesale Goods"
        }
    ],
    "sg:phone":"+61 3 9490 0111",
    "sg:postcode":"3071",
    "sg:province":"VIC",
    "sg:tags":[
        "wholesaler",
        "product",
        "mfrs"
    ],
    "wof:name":"Leister Hot Air Equipment",
    "wof:placetype":"venue"
},
  "geometry": {"coordinates":[145.02870178200001,-37.7664489746],"type":"Point"}
}