{
  "type": "Feature",
  "properties": {
    "addr:full":"Suite 4 22 Dorothy St Gosnells WA 6110",
    "addr:housenumber":"22",
    "addr:postcode":"6110",
    "addr:street":"Dorothy St",
    "iso:country":"AU",
    "sg:address":"Suite 4 22 Dorothy St",
    "sg:city":"Gosnells",
    "sg:classifiers":[
        {
            "category":"Professional",
            "subcategory":"Business Services",
            "type":"Services"
        }
    ],
    "sg:phone":"+61 8 9398 2139",
    "sg:postcode":"6110",
    "sg:province":"WA",
    "sg:tags":[
        "drafting"
    ],
    "wof:name":"Domestic Drafting Service",
    "wof:placetype":"venue"
},
  "geometry": {"coordinates":[116.00080871599999,-32.0734901428],"type":"Point"}
}