{
  "type": "Feature",
  "properties": {
    "iso:country":"AU",
    "sg:address":"Suite 4, Madison Bldg Hunter St",
    "sg:city":"Hornsby",
    "sg:classifiers":[
        {
            "category":"Health Services",
            "subcategory":"Dentist",
            "type":"Services"
        }
    ],
    "sg:phone":"+61 2 9476 6731",
    "sg:postcode":"2077",
    "sg:province":"NSW",
    "wof:name":"Wong Sunny Dr",
    "wof:placetype":"venue"
},
  "geometry": {"coordinates":[151.10177612300001,-33.6979370117],"type":"Point"}
}