{
  "type": "Feature",
  "properties": {
    "addr:full":"46 The Avenue, Wickham NSW 2293",
    "addr:housenumber":"46",
    "addr:postcode":"2293",
    "addr:street":"The Avenue",
    "iso:country":"AU",
    "sg:address":"46 The Avenue,",
    "sg:city":"Wickham",
    "sg:classifiers":[
        {
            "category":"Shopping",
            "subcategory":"Computers & Home Electronics",
            "type":"Retail Goods"
        }
    ],
    "sg:phone":"+61 2 4961 4679",
    "sg:postcode":"2293",
    "sg:province":"NSW",
    "sg:tags":[
        "hardware",
        "equipment"
    ],
    "wof:name":"Newcastle Onsite IT",
    "wof:placetype":"venue"
},
  "geometry": {"coordinates":[151.755584717,-32.9138450623],"type":"Point"}
}