{
  "type": "Feature",
  "properties": {
    "iso:country":"AU",
    "sg:address":"10 Meldrum Crt",
    "sg:city":"Sunbury",
    "sg:classifiers":[
        {
            "category":"Utilities",
            "type":"Services"
        }
    ],
    "sg:phone":"+61 407 455 669",
    "sg:postcode":"3429",
    "sg:province":"VIC",
    "sg:tags":[
        "refrigeration",
        "industrial",
        "commercial",
        "retail"
    ],
    "wof:name":"Madex Refrigeration",
    "wof:placetype":"venue"
},
  "geometry": {"coordinates":[144.70338439899999,-37.5757255554],"type":"Point"}
}