{
  "type": "Feature",
  "properties": {
    "addr:full":"111 George St Bathurst NSW 2795",
    "addr:housenumber":"111",
    "addr:postcode":"2795",
    "addr:street":"George St",
    "iso:country":"AU",
    "sg:address":"111 George St",
    "sg:city":"Bathurst",
    "sg:classifiers":[
        {
            "category":"Real Estate",
            "subcategory":"Real Estate Agent",
            "type":"Services"
        }
    ],
    "sg:phone":"+61 2 6331 3600",
    "sg:postcode":"2795",
    "sg:province":"NSW",
    "wof:name":"L.J. Hooker",
    "wof:placetype":"venue"
},
  "geometry": {"coordinates":[149.57844543499999,-33.4166870117],"type":"Point"}
}