{
  "type": "Feature",
  "properties": {
    "addr:full":"37 Challis St Newport VIC 3015",
    "addr:housenumber":"37",
    "addr:postcode":"3015",
    "addr:street":"Challis St",
    "iso:country":"AU",
    "sg:address":"37 Challis St",
    "sg:city":"Newport",
    "sg:classifiers":[
        {
            "category":"Health Services",
            "subcategory":"Doctor",
            "type":"Services"
        }
    ],
    "sg:phone":"+61 3 9391 2855",
    "sg:postcode":"3015",
    "sg:province":"VIC",
    "sg:tags":[
        "medical",
        "practitioner"
    ],
    "wof:name":"Tsui, Edward Dr",
    "wof:placetype":"venue"
},
  "geometry": {"coordinates":[144.87257385300001,-37.8458633423],"type":"Point"}
}