{
  "type": "Feature",
  "properties": {
    "addr:full":"7 Hinkler Rd Mordialloc VIC 3195",
    "addr:housenumber":"7",
    "addr:postcode":"3195",
    "addr:street":"Hinkler Rd",
    "iso:country":"AU",
    "sg:address":"7 Hinkler Rd",
    "sg:city":"Mordialloc",
    "sg:classifiers":[
        {
            "category":"Food & Beverages",
            "subcategory":"Supermarket",
            "type":"Retail Goods"
        }
    ],
    "sg:phone":"+61 3 9588 1811",
    "sg:postcode":"3195",
    "sg:province":"VIC",
    "sg:tags":[
        "grocery",
        "store"
    ],
    "wof:name":"Tangola Pty Ltd",
    "wof:placetype":"venue"
},
  "geometry": {"coordinates":[145.09881591800001,-37.9907722473],"type":"Point"}
}