{
  "type": "Feature",
  "properties": {
    "iso:country":"AU",
    "sg:address":"157 Glenhaven Pl",
    "sg:city":"Glenhaven",
    "sg:classifiers":[
        {
            "category":"Utilities",
            "subcategory":"Refuse",
            "type":"Services"
        }
    ],
    "sg:phone":"+61 2 9899 2564",
    "sg:postcode":"2156",
    "sg:province":"NSW",
    "sg:tags":[
        "boiler"
    ],
    "wof:name":"Parsons Boiler & Thermal Design Consultants",
    "wof:placetype":"venue"
},
  "geometry": {"coordinates":[150.99571227999999,-33.6968536377],"type":"Point"}
}