{
  "type": "Feature",
  "properties": {
    "iso:country":"AU",
    "sg:address":"233 Morphett St",
    "sg:city":"Adelaide",
    "sg:classifiers":[
        {
            "category":"Retail",
            "subcategory":"Auto Rental",
            "type":"Services"
        }
    ],
    "sg:phone":"+61 8 8231 2856",
    "sg:postcode":"5000",
    "sg:province":"SA",
    "sg:tags":[
        "car",
        "hire",
        "minibus"
    ],
    "wof:name":"Hertz.",
    "wof:placetype":"venue"
},
  "geometry": {"coordinates":[138.59373474099999,-34.9285926819],"type":"Point"}
}