{
  "type": "Feature",
  "properties": {
    "addr:full":"9- 15 Pembury Pl Rocherlea TAS 7248",
    "addr:housenumber":"15",
    "addr:postcode":"7248",
    "addr:street":"9;Pl",
    "iso:country":"AU",
    "sg:address":"9- 15 Pembury Pl",
    "sg:city":"Rocherlea",
    "sg:classifiers":[
        {
            "category":"Manufacturing",
            "subcategory":"Tools & Machinery",
            "type":"Manufacturing & Wholesale Goods"
        }
    ],
    "sg:phone":"+61 3 6326 3435",
    "sg:postcode":"7248",
    "sg:province":"TAS",
    "sg:tags":[
        "earth",
        "excavating",
        "moving",
        "equipment"
    ],
    "wof:name":"Hitachi",
    "wof:placetype":"venue"
},
  "geometry": {"coordinates":[147.115524292,-41.3737754822],"type":"Point"}
}