{
  "type": "Feature",
  "properties": {
    "iso:country":"AU",
    "sg:address":"Unit 1/ 358 Horsley Rd",
    "sg:city":"Milperra",
    "sg:classifiers":[
        {
            "category":"Wholesale",
            "subcategory":"Machinery & Supplies",
            "type":"Manufacturing & Wholesale Goods"
        }
    ],
    "sg:phone":"+61 2 9774 3222",
    "sg:postcode":"2214",
    "sg:province":"NSW",
    "sg:tags":[
        "equipment",
        "pneumatic"
    ],
    "wof:name":"Nigray Pty Ltd",
    "wof:placetype":"venue"
},
  "geometry": {"coordinates":[150.994522,-33.939007],"type":"Point"}
}