{
  "type": "Feature",
  "properties": {
    "iso:country":"AU",
    "sg:address":"68 Kingsford Smith Pde",
    "sg:city":"Maroochydore",
    "sg:classifiers":[
        {
            "category":"Banks & Credit Unions",
            "subcategory":"Investment Brokerage",
            "type":"Services"
        }
    ],
    "sg:phone":"+61 7 5443 2744",
    "sg:postcode":"4558",
    "sg:province":"QLD",
    "sg:tags":[
        "repairer",
        "typewriter"
    ],
    "wof:name":"Electronic Business Equipment",
    "wof:placetype":"venue"
},
  "geometry": {"coordinates":[153.09762573200001,-26.6586055756],"type":"Point"}
}