{
  "type": "Feature",
  "properties": {
    "iso:country":"AU",
    "sg:address":"4- 6 Johnson Rd",
    "sg:city":"Tuggerah",
    "sg:classifiers":[
        {
            "category":"Manufacturing",
            "subcategory":"Metals",
            "type":"Manufacturing & Wholesale Goods"
        }
    ],
    "sg:phone":"+61 2 4353 8688",
    "sg:postcode":"2259",
    "sg:province":"NSW",
    "sg:tags":[
        "steel",
        "fabricator",
        "mfrs"
    ],
    "wof:name":"Online Fabrications",
    "wof:placetype":"venue"
},
  "geometry": {"coordinates":[151.420776367,-33.294216156],"type":"Point"}
}