{
  "type": "Feature",
  "properties": {
    "addr:full":"French St Dynnyrne TAS 7005",
    "addr:postcode":"7005",
    "addr:street":"French St",
    "iso:country":"AU",
    "sg:address":"French St",
    "sg:city":"Dynnyrne",
    "sg:classifiers":[
        {
            "category":"Government",
            "subcategory":"Court House",
            "type":"Public Place"
        }
    ],
    "sg:phone":"+61 407 904 706",
    "sg:postcode":"7005",
    "sg:province":"TAS",
    "sg:tags":[
        "personal",
        "marriage",
        "family",
        "counselling"
    ],
    "wof:name":"Fisher Susan",
    "wof:placetype":"venue"
},
  "geometry": {"coordinates":[147.320388794,-42.9024085999],"type":"Point"}
}