{
  "type": "Feature",
  "properties": {
    "addr:full":"65 Laurie St Yarrambat VIC 3091",
    "addr:housenumber":"65",
    "addr:postcode":"3091",
    "addr:street":"Laurie St",
    "iso:country":"AU",
    "sg:address":"65 Laurie St",
    "sg:city":"Yarrambat",
    "sg:classifiers":[
        {
            "category":"Retail",
            "subcategory":"Auto Repair",
            "type":"Services"
        }
    ],
    "sg:phone":"+61 418 362 624",
    "sg:postcode":"3091",
    "sg:province":"VIC",
    "sg:tags":[
        "engine",
        "reconditioning"
    ],
    "wof:name":"Classic Rebuilds",
    "wof:placetype":"venue"
},
  "geometry": {"coordinates":[145.142944336,-37.6225547791],"type":"Point"}
}