{
  "type": "Feature",
  "properties": {
    "addr:full":"10 Edgewater Drv Edgewater WA 6027",
    "addr:housenumber":"10",
    "addr:postcode":"6027",
    "addr:street":"Edgewater Drv",
    "iso:country":"AU",
    "sg:address":"10 Edgewater Drv",
    "sg:city":"Edgewater",
    "sg:classifiers":[
        {
            "category":"Home & Garden",
            "subcategory":"Building Materials",
            "type":"Retail Goods"
        }
    ],
    "sg:phone":"+61 8 9405 9686",
    "sg:postcode":"6027",
    "sg:province":"WA",
    "sg:tags":[
        "retaining",
        "wall"
    ],
    "wof:name":"Interpave",
    "wof:placetype":"venue"
},
  "geometry": {"coordinates":[115.789283752,-31.773443222],"type":"Point"}
}