{
  "type": "Feature",
  "properties": {
    "iso:country":"AU",
    "sg:address":"1 Enfield Drv St",
    "sg:city":"Albans",
    "sg:classifiers":[
        {
            "category":"Utilities",
            "subcategory":"Electric",
            "type":"Services"
        }
    ],
    "sg:phone":"+61 3 5248 4792",
    "sg:postcode":"3021",
    "sg:province":"VIC",
    "sg:tags":[
        "electrical",
        "contractor"
    ],
    "wof:name":"Evans Rob",
    "wof:placetype":"venue"
},
  "geometry": {"coordinates":[144.764313,-37.749573],"type":"Point"}
}