{
  "type": "Feature",
  "properties": {
    "addr:full":"168 Great Northern Hwy Bindoon WA 6502",
    "addr:housenumber":"168",
    "addr:postcode":"6502",
    "addr:street":"Great Northern Hwy",
    "iso:country":"AU",
    "sg:address":"168 Great Northern Hwy",
    "sg:city":"Bindoon",
    "sg:classifiers":[
        {
            "category":"Food & Beverages",
            "subcategory":"Bakery",
            "type":"Retail Goods"
        }
    ],
    "sg:phone":"+61 8 9576 0069",
    "sg:postcode":"6502",
    "sg:province":"WA",
    "sg:tags":[
        "baker"
    ],
    "wof:name":"Bindoon Bakery",
    "wof:placetype":"venue"
},
  "geometry": {"coordinates":[116.09644299999999,-31.385597],"type":"Point"}
}