{
  "type": "Feature",
  "properties": {
    "iso:country":"AU",
    "sg:address":"168 Great Northern Hwy",
    "sg:city":"Bindoon",
    "sg:classifiers":[
        {
            "category":"Food & Beverages",
            "subcategory":"Bakery",
            "type":"Retail Goods"
        }
    ],
    "sg:phone":"+61 8 9576 0069",
    "sg:postcode":"6502",
    "sg:province":"WA",
    "sg:tags":[
        "baker"
    ],
    "wof:name":"Bindoon Bakery",
    "wof:placetype":"venue"
},
  "geometry": {"coordinates":[116.096443,-31.385597],"type":"Point"}
}