{
  "type": "Feature",
  "properties": {
    "iso:country":"AU",
    "sg:address":"Locked Bag 028",
    "sg:city":"Crows Nest",
    "sg:classifiers":[
        {
            "category":"Communications",
            "type":"Services"
        }
    ],
    "sg:phone":"+61 1300 304 727",
    "sg:postcode":"1585",
    "sg:province":"NSW",
    "sg:tags":[
        "translation"
    ],
    "wof:name":"SBS Language Services",
    "wof:placetype":"venue"
},
  "geometry": {"coordinates":[151.20094299300001,-33.8342819214],"type":"Point"}
}