{
  "type": "Feature",
  "properties": {
    "addr:full":"1174 Glenhuntly Rd Glen Huntly VIC 3163",
    "addr:housenumber":"1174",
    "addr:postcode":"3163",
    "addr:street":"Glenhuntly Rd",
    "iso:country":"AU",
    "sg:address":"1174 Glenhuntly Rd",
    "sg:city":"Glen Huntly",
    "sg:classifiers":[
        {
            "category":"Shopping",
            "subcategory":"Baby Store",
            "type":"Retail Goods"
        }
    ],
    "sg:phone":"+61 3 9571 9881",
    "sg:postcode":"3163",
    "sg:province":"VIC",
    "sg:tags":[
        "wear"
    ],
    "wof:name":"Glenhuntly Baby Carriages",
    "wof:placetype":"venue"
},
  "geometry": {"coordinates":[145.04309082,-37.8896331787],"type":"Point"}
}