{
  "type": "Feature",
  "properties": {
    "addr:full":"12 Harvey St Macquarie Fields NSW 2564",
    "addr:housenumber":"12",
    "addr:postcode":"2564",
    "addr:street":"Harvey St",
    "iso:country":"AU",
    "sg:address":"12 Harvey St",
    "sg:city":"Macquarie Fields",
    "sg:classifiers":[
        {
            "category":"Professional",
            "subcategory":"Business Services",
            "type":"Services"
        }
    ],
    "sg:phone":"+61 2 9605 3794",
    "sg:postcode":"2564",
    "sg:province":"NSW",
    "sg:tags":[
        "drafting"
    ],
    "wof:name":"Windsor E & A",
    "wof:placetype":"venue"
},
  "geometry": {"coordinates":[150.88931274399999,-33.9856033325],"type":"Point"}
}