{
  "type": "Feature",
  "properties": {
    "iso:country":"AU",
    "sg:address":"Shop 1, Macquarie Plaza William St",
    "sg:city":"Bathurst",
    "sg:classifiers":[
        {
            "category":"Restaurant",
            "type":"Food & Drink"
        }
    ],
    "sg:phone":"+61 2 6331 5522",
    "sg:postcode":"2795",
    "sg:province":"NSW",
    "wof:name":"Cafe Soho",
    "wof:placetype":"venue"
},
  "geometry": {"coordinates":[149.569091797,-33.4260177612],"type":"Point"}
}