{
  "type": "Feature",
  "properties": {
    "addr:full":"195 Bondi Rd Bondi NSW 2026",
    "addr:housenumber":"195",
    "addr:postcode":"2026",
    "addr:street":"Bondi Rd",
    "iso:country":"AU",
    "sg:address":"195 Bondi Rd",
    "sg:city":"Bondi",
    "sg:classifiers":[
        {
            "category":"Restaurant",
            "type":"Food & Drink"
        }
    ],
    "sg:phone":"+61 2 9386 9595",
    "sg:postcode":"2026",
    "sg:province":"NSW",
    "wof:name":"Altar Lounge",
    "wof:placetype":"venue"
},
  "geometry": {"coordinates":[151.264892578,-33.8941955566],"type":"Point"}
}