{
  "type": "Feature",
  "properties": {
    "iso:country":"AU",
    "sg:address":"27 Centenary Pl",
    "sg:city":"Logan Village",
    "sg:classifiers":[
        {
            "category":"Manufacturing",
            "subcategory":"Metals",
            "type":"Manufacturing & Wholesale Goods"
        }
    ],
    "sg:phone":"+61 7 5546 8201",
    "sg:postcode":"4207",
    "sg:province":"QLD",
    "sg:tags":[
        "steel",
        "fabricator",
        "mfrs"
    ],
    "wof:name":"Awon Steel Pty Ltd",
    "wof:placetype":"venue"
},
  "geometry": {"coordinates":[153.10911560100001,-27.7694301605],"type":"Point"}
}