{
  "type": "Feature",
  "properties": {
    "iso:country":"AU",
    "sg:address":"53 Wallis Ave",
    "sg:city":"Strathfield",
    "sg:classifiers":[
        {
            "category":"Banks & Credit Unions",
            "subcategory":"Financial Services",
            "type":"Services"
        }
    ],
    "sg:phone":"+61 2 9642 2225",
    "sg:postcode":"2135",
    "sg:province":"NSW",
    "sg:tags":[
        "advisory",
        "planning",
        "retirement"
    ],
    "wof:name":"P.J.A. Consultants Pty Ltd",
    "wof:placetype":"venue"
},
  "geometry": {"coordinates":[151.07957458499999,-33.8838882446],"type":"Point"}
}