{
  "type": "Feature",
  "properties": {
    "iso:country":"AU",
    "sg:address":"352 Bell St",
    "sg:city":"Preston",
    "sg:classifiers":[
        {
            "category":"Fast Food",
            "type":"Food & Drink"
        }
    ],
    "sg:phone":"+61 3 9484 2228",
    "sg:postcode":"3072",
    "sg:province":"VIC",
    "sg:tags":[
        "away",
        "take"
    ],
    "wof:name":"Major Convenience Stores",
    "wof:placetype":"venue"
},
  "geometry": {"coordinates":[145.000656128,-37.7447166443],"type":"Point"}
}