{
  "type": "Feature",
  "properties": {
    "addr:full":"6 Homestead Rd Wonga Park VIC 3115",
    "addr:housenumber":"6",
    "addr:postcode":"3115",
    "addr:street":"Homestead Rd",
    "iso:country":"AU",
    "sg:address":"6 Homestead Rd",
    "sg:city":"Wonga Park",
    "sg:classifiers":[
        {
            "category":"Communications",
            "subcategory":"Film & Video Production",
            "type":"Services"
        }
    ],
    "sg:phone":"+61 3 9722 1819",
    "sg:postcode":"3115",
    "sg:province":"VIC",
    "sg:tags":[
        "fan",
        "blower"
    ],
    "wof:name":"Medilab Systems",
    "wof:placetype":"venue"
},
  "geometry": {"coordinates":[145.27296447800001,-37.7472305298],"type":"Point"}
}