{
  "type": "Feature",
  "properties": {
    "iso:country":"AU",
    "sg:address":"Unit 31/286- 288 New Line Rd",
    "sg:city":"Dural",
    "sg:classifiers":[
        {
            "category":"Education",
            "subcategory":"Music School",
            "type":"Public Place"
        }
    ],
    "sg:phone":"+61 2 9651 7333",
    "sg:postcode":"2158",
    "sg:province":"NSW",
    "sg:tags":[
        "teacher"
    ],
    "wof:name":"Dural Music Centre",
    "wof:placetype":"venue"
},
  "geometry": {"coordinates":[151.03053283700001,-33.6961517334],"type":"Point"}
}