{
  "type": "Feature",
  "properties": {
    "iso:country":"AU",
    "sg:address":"226A High St",
    "sg:city":"Coffs Harbour",
    "sg:classifiers":[
        {
            "category":"Banks & Credit Unions",
            "subcategory":"Financial Services",
            "type":"Services"
        }
    ],
    "sg:phone":"+61 2 6652 3160",
    "sg:postcode":"2450",
    "sg:province":"NSW",
    "sg:tags":[
        "planning"
    ],
    "wof:name":"BBV Financial Services",
    "wof:placetype":"venue"
},
  "geometry": {"coordinates":[153.109467,-30.295391],"type":"Point"}
}