{
  "type": "Feature",
  "properties": {
    "addr:full":"Maritime Centre Two Rocks Marina Sovereign Drv Two Rocks WA 6037",
    "addr:postcode":"6037",
    "addr:street":"Sovereign Drv",
    "iso:country":"AU",
    "sg:address":"Maritime Centre Two Rocks Marina Sovereign Drv",
    "sg:city":"Two Rocks",
    "sg:classifiers":[
        {
            "category":"Education",
            "subcategory":"Vocational School",
            "type":"Public Place"
        }
    ],
    "sg:phone":"+61 8 9561 6062",
    "sg:postcode":"6037",
    "sg:province":"WA",
    "sg:tags":[
        "tafe",
        "college",
        "training"
    ],
    "wof:name":"South Metropolitan College of TAFE",
    "wof:placetype":"venue"
},
  "geometry": {"coordinates":[115.60796356199999,-31.4892101288],"type":"Point"}
}