{
  "type": "Feature",
  "properties": {
    "addr:full":"PO Box 67 Somerton VIC 3062",
    "addr:postcode":"3062",
    "iso:country":"AU",
    "sg:address":"PO Box 67",
    "sg:city":"Somerton",
    "sg:classifiers":[
        {
            "category":"Wholesale",
            "subcategory":"Durable Goods & Equipment",
            "type":"Manufacturing & Wholesale Goods"
        }
    ],
    "sg:phone":"+61 3 9303 7711",
    "sg:postcode":"3062",
    "sg:province":"VIC",
    "sg:tags":[
        "wholesaler",
        "mfrs",
        "lubrication"
    ],
    "wof:name":"Hydraulic Engineering Pty Ltd",
    "wof:placetype":"venue"
},
  "geometry": {"coordinates":[144.954055786,-37.6336288452],"type":"Point"}
}