{
  "type": "Feature",
  "properties": {
    "iso:country":"AU",
    "sg:address":"Parkmore Shopping Centre Cheltenham Rd",
    "sg:city":"Keysborough",
    "sg:classifiers":[
        {
            "category":"Shopping",
            "subcategory":"Mobile Phones",
            "type":"Retail Goods"
        }
    ],
    "sg:phone":"+61 3 9798 5833",
    "sg:postcode":"3173",
    "sg:province":"VIC",
    "sg:tags":[
        "telephone",
        "accessory"
    ],
    "wof:name":"Fone Zone.",
    "wof:placetype":"venue"
},
  "geometry": {"coordinates":[145.17301940900001,-37.9947357178],"type":"Point"}
}