{
  "type": "Feature",
  "properties": {
    "addr:full":"2 Wildlife Pde Balwyn North VIC 3104",
    "addr:housenumber":"2",
    "addr:postcode":"3104",
    "addr:street":"Wildlife Pde",
    "iso:country":"AU",
    "sg:address":"2 Wildlife Pde",
    "sg:city":"Balwyn North",
    "sg:classifiers":[
        {
            "category":"Health Services",
            "subcategory":"Doctor",
            "type":"Services"
        }
    ],
    "sg:phone":"+61 3 9387 1000",
    "sg:postcode":"3104",
    "sg:province":"VIC",
    "sg:tags":[
        "medical",
        "practitioner"
    ],
    "wof:name":"Vellar Dominic",
    "wof:placetype":"venue"
},
  "geometry": {"coordinates":[145.09661865199999,-37.7990150452],"type":"Point"}
}