{
  "type": "Feature",
  "properties": {
    "addr:full":"Unit 4, 4 Leeway Crt Osborne Park WA 6017",
    "addr:housenumber":"4",
    "addr:postcode":"6017",
    "addr:street":"Leeway Crt",
    "iso:country":"AU",
    "sg:address":"Unit 4, 4 Leeway Crt",
    "sg:city":"Osborne Park",
    "sg:classifiers":[
        {
            "category":"Building & Trades",
            "subcategory":"Construction",
            "type":"Services"
        }
    ],
    "sg:phone":"+61 8 9244 2998",
    "sg:postcode":"6017",
    "sg:province":"WA",
    "sg:tags":[
        "fencing",
        "contractor"
    ],
    "wof:name":"Classic Aluminium",
    "wof:placetype":"venue"
},
  "geometry": {"coordinates":[115.809829712,-31.8987293243],"type":"Point"}
}