{
  "type": "Feature",
  "properties": {
    "addr:full":"17 Reid Drv Coffs Harbour NSW 2450",
    "addr:housenumber":"17",
    "addr:postcode":"2450",
    "addr:street":"Reid Drv",
    "iso:country":"AU",
    "sg:address":"17 Reid Drv",
    "sg:city":"Coffs Harbour",
    "sg:classifiers":[
        {
            "category":"Professional",
            "subcategory":"Business Services",
            "type":"Services"
        }
    ],
    "sg:phone":"+61 2 6651 2288",
    "sg:postcode":"2450",
    "sg:province":"NSW",
    "sg:tags":[
        "broker"
    ],
    "wof:name":"Sercombe John Real Estate Agent",
    "wof:placetype":"venue"
},
  "geometry": {"coordinates":[153.10992400000001,-30.308277],"type":"Point"}
}