{
  "type": "Feature",
  "properties": {
    "iso:country":"AU",
    "sg:address":"17 Reid Drv",
    "sg:city":"Coffs Harbour",
    "sg:classifiers":[
        {
            "category":"Professional",
            "subcategory":"Business Services",
            "type":"Services"
        }
    ],
    "sg:phone":"+61 2 6651 2288",
    "sg:postcode":"2450",
    "sg:province":"NSW",
    "sg:tags":[
        "broker"
    ],
    "wof:name":"Sercombe John Real Estate Agent",
    "wof:placetype":"venue"
},
  "geometry": {"coordinates":[153.109924,-30.308277],"type":"Point"}
}