{
  "type": "Feature",
  "properties": {
    "iso:country":"AU",
    "sg:address":"51 Beadell St",
    "sg:city":"Burton",
    "sg:classifiers":[
        {
            "category":"Professional",
            "subcategory":"Art Services",
            "type":"Services"
        }
    ],
    "sg:phone":"+61 408 088 956",
    "sg:postcode":"5110",
    "sg:province":"SA",
    "sg:tags":[
        "decorator",
        "painter"
    ],
    "wof:name":"Russo Painter & Decorator",
    "wof:placetype":"venue"
},
  "geometry": {"coordinates":[138.61448669399999,-34.735534668],"type":"Point"}
}