{
  "type": "Feature",
  "properties": {
    "addr:full":"6 Gold Creek Rd Nicholls ACT 2913",
    "addr:housenumber":"6",
    "addr:postcode":"2913",
    "addr:street":"Gold Creek Rd",
    "iso:country":"AU",
    "sg:address":"6 Gold Creek Rd",
    "sg:city":"Nicholls",
    "sg:classifiers":[
        {
            "category":"Social Services",
            "subcategory":"Child Care",
            "type":"Services"
        }
    ],
    "sg:phone":"+61 2 6230 9700",
    "sg:postcode":"2913",
    "sg:province":"ACT",
    "wof:name":"Gold Creek Early Learning Centre",
    "wof:placetype":"venue"
},
  "geometry": {"coordinates":[149.08682250999999,-35.1935844421],"type":"Point"}
}