{
  "type": "Feature",
  "properties": {
    "addr:full":"51 George St Forth TAS 7310",
    "addr:housenumber":"51",
    "addr:postcode":"7310",
    "addr:street":"George St",
    "iso:country":"AU",
    "sg:address":"51 George St",
    "sg:city":"Forth",
    "sg:classifiers":[
        {
            "category":"Professional",
            "subcategory":"Art Services",
            "type":"Services"
        }
    ],
    "sg:phone":"+61 3 6428 2675",
    "sg:postcode":"7310",
    "sg:province":"TAS",
    "sg:tags":[
        "artist"
    ],
    "wof:name":"Antonysen Evelyn",
    "wof:placetype":"venue"
},
  "geometry": {"coordinates":[146.257522583,-41.193271637],"type":"Point"}
}