{
  "type": "Feature",
  "properties": {
    "iso:country":"AU",
    "sg:address":"4 Campbell St",
    "sg:city":"Blacktown",
    "sg:classifiers":[
        {
            "category":"Building & Trades",
            "subcategory":"Equipment Rental",
            "type":"Services"
        }
    ],
    "sg:phone":"+61 2 9676 4247",
    "sg:postcode":"2148",
    "sg:province":"NSW",
    "sg:tags":[
        "fitness"
    ],
    "wof:name":"Body Factory Health & Fitness Supplies",
    "wof:placetype":"venue"
},
  "geometry": {"coordinates":[150.909713745,-33.770614624],"type":"Point"}
}