{
  "type": "Feature",
  "properties": {
    "addr:full":"116 French St Hamilton VIC 3300",
    "addr:housenumber":"116",
    "addr:postcode":"3300",
    "addr:street":"French St",
    "iso:country":"AU",
    "sg:address":"116 French St",
    "sg:city":"Hamilton",
    "sg:classifiers":[
        {
            "category":"Autos & Motor Vehicles",
            "subcategory":"Fuel & Gas Station",
            "type":"Retail Goods"
        }
    ],
    "sg:phone":"+61 3 5572 5116",
    "sg:postcode":"3300",
    "sg:province":"VIC",
    "wof:name":"Corcorans Garage",
    "wof:placetype":"venue"
},
  "geometry": {"coordinates":[142.02804565400001,-37.7438049316],"type":"Point"}
}