{
  "type": "Feature",
  "properties": {
    "addr:full":"2/ 9 Enterprise Pl Wetherill Park NSW 2164",
    "addr:housenumber":"/ 9",
    "addr:postcode":"2164",
    "addr:street":"Enterprise Pl",
    "iso:country":"AU",
    "sg:address":"2/ 9 Enterprise Pl",
    "sg:city":"Wetherill Park",
    "sg:classifiers":[
        {
            "category":"Building & Trades",
            "subcategory":"Cleaning & Sanitation",
            "type":"Services"
        }
    ],
    "sg:phone":"+61 2 9756 1622",
    "sg:postcode":"2164",
    "sg:province":"NSW",
    "sg:tags":[
        "sweeping",
        "machine"
    ],
    "wof:name":"MacDonald Johnston Engineering Co. Pty Ltd",
    "wof:placetype":"venue"
},
  "geometry": {"coordinates":[150.88638305699999,-33.8517913818],"type":"Point"}
}