{
  "type": "Feature",
  "properties": {
    "iso:country":"AU",
    "sg:address":"5 Parna Ave",
    "sg:city":"Frankston",
    "sg:classifiers":[
        {
            "category":"Building & Trades",
            "subcategory":"Landscaping Services",
            "type":"Services"
        }
    ],
    "sg:phone":"+61 417 361 749",
    "sg:postcode":"3199",
    "sg:province":"VIC",
    "sg:tags":[
        "designer",
        "landscape",
        "contractor"
    ],
    "wof:name":"Animated Landscapes",
    "wof:placetype":"venue"
},
  "geometry": {"coordinates":[144.68270874000001,-37.8596382141],"type":"Point"}
}