{
  "type": "Feature",
  "properties": {
    "iso:country":"AU",
    "sg:address":"Shp 12/ 37 Main St",
    "sg:city":"Samford",
    "sg:classifiers":[
        {
            "category":"Health Services",
            "subcategory":"Chiropractor",
            "type":"Services"
        }
    ],
    "sg:phone":"+61 7 3289 6618",
    "sg:postcode":"4520",
    "sg:province":"QLD",
    "wof:name":"Geoffrey Jackson",
    "wof:placetype":"venue"
},
  "geometry": {"coordinates":[152.88694799999999,-27.370361],"type":"Point"}
}