{
  "type": "Feature",
  "properties": {
    "iso:country":"AU",
    "sg:address":"14/ 19 Brickfield Rd",
    "sg:city":"Aspley",
    "sg:classifiers":[
        {
            "category":"Wholesale",
            "subcategory":"Furniture",
            "type":"Manufacturing & Wholesale Goods"
        }
    ],
    "sg:phone":"+61 418 881 346",
    "sg:postcode":"4034",
    "sg:province":"QLD",
    "sg:tags":[
        "wholesaler",
        "mfrs"
    ],
    "wof:name":"A Plus Furniture Assemblers",
    "wof:placetype":"venue"
},
  "geometry": {"coordinates":[153.018295,-27.358162],"type":"Point"}
}