{
  "type": "Feature",
  "properties": {
    "addr:full":"122 Sydney Rd Fairlight NSW 2094",
    "addr:housenumber":"122",
    "addr:postcode":"2094",
    "addr:street":"Sydney Rd",
    "iso:country":"AU",
    "sg:address":"122 Sydney Rd",
    "sg:city":"Fairlight",
    "sg:classifiers":[
        {
            "category":"Building & Trades",
            "subcategory":"Construction",
            "type":"Services"
        }
    ],
    "sg:phone":"+61 2 9907 8438",
    "sg:postcode":"2094",
    "sg:province":"NSW",
    "sg:tags":[
        "renovation",
        "alterations",
        "extension",
        "contractor"
    ],
    "wof:name":"Distinctive Additions Pty Ltd",
    "wof:placetype":"venue"
},
  "geometry": {"coordinates":[151.27784729000001,-33.7958335876],"type":"Point"}
}