{
  "type": "Feature",
  "properties": {
    "addr:full":"3 Everage St Moonee Ponds VIC 3039",
    "addr:housenumber":"3",
    "addr:postcode":"3039",
    "addr:street":"Everage St",
    "iso:country":"AU",
    "sg:address":"3 Everage St",
    "sg:city":"Moonee Ponds",
    "sg:classifiers":[
        {
            "category":"Sports & Exercise",
            "subcategory":"Gym",
            "type":"Entertainment"
        }
    ],
    "sg:phone":"+61 407 480 478",
    "sg:postcode":"3039",
    "sg:province":"VIC",
    "sg:tags":[
        "personal",
        "trainer",
        "fitness"
    ],
    "sg:website":"http://www.innerfit.com.au",
    "wof:name":"Inner Fit",
    "wof:placetype":"venue"
},
  "geometry": {"coordinates":[144.921875,-37.765892],"type":"Point"}
}