{
  "type": "Feature",
  "properties": {
    "iso:country":"AU",
    "sg:address":"4 Station St",
    "sg:city":"Weston",
    "sg:classifiers":[
        {
            "category":"Autos & Motor Vehicles",
            "subcategory":"Automobile Sales",
            "type":"Retail Goods"
        }
    ],
    "sg:phone":"+61 2 4936 1183",
    "sg:postcode":"2326",
    "sg:province":"NSW",
    "sg:tags":[
        "car",
        "used"
    ],
    "wof:name":"Stan Lewis Licensed Auto Dealer",
    "wof:placetype":"venue"
},
  "geometry": {"coordinates":[151.458496094,-32.8155288696],"type":"Point"}
}