{
  "type": "Feature",
  "properties": {
    "iso:country":"AU",
    "sg:address":"377 Little Collins St",
    "sg:city":"Melbourne",
    "sg:classifiers":[
        {
            "category":"Shopping",
            "subcategory":"Clothing, Apparel, & Fashions",
            "type":"Retail Goods"
        }
    ],
    "sg:phone":"+61 3 9670 1897",
    "sg:postcode":"3000",
    "sg:province":"VIC",
    "sg:tags":[
        "lady",
        "wear"
    ],
    "wof:name":"Kamikaze",
    "wof:placetype":"venue"
},
  "geometry": {"coordinates":[144.96246337900001,-37.8156814575],"type":"Point"}
}