{
  "type": "Feature",
  "properties": {
    "addr:full":"PO Box 251 Tugun QLD 4224",
    "addr:postcode":"4224",
    "iso:country":"AU",
    "sg:address":"PO Box 251",
    "sg:city":"Tugun",
    "sg:phone":"+61 7 5534 6826",
    "sg:postcode":"4224",
    "sg:province":"QLD",
    "wof:name":"Site Integrity Services Tank Testing",
    "wof:placetype":"venue"
},
  "geometry": {"coordinates":[153.49212646500001,-28.1418399811],"type":"Point"}
}