{
  "type": "Feature",
  "properties": {
    "iso:country":"AU",
    "sg:address":"18 Gloucester Blv",
    "sg:city":"Port Kembla",
    "sg:classifiers":[
        {
            "category":"Education",
            "subcategory":"School",
            "type":"Public Place"
        }
    ],
    "sg:phone":"+61 2 4274 1041",
    "sg:postcode":"2505",
    "sg:province":"NSW",
    "sg:tags":[
        "state",
        "-",
        "nsw"
    ],
    "wof:name":"Port Kembla Public School",
    "wof:placetype":"venue"
},
  "geometry": {"coordinates":[150.901886,-34.479698],"type":"Point"}
}