{
  "type": "Feature",
  "properties": {
    "iso:country":"AU",
    "sg:address":"Ridge St",
    "sg:city":"Nambucca Heads",
    "sg:classifiers":[
        {
            "category":"Education",
            "subcategory":"School",
            "type":"Public Place"
        }
    ],
    "sg:phone":"+61 2 6568 6411",
    "sg:postcode":"2448",
    "sg:province":"NSW",
    "sg:tags":[
        "state",
        "-",
        "nsw"
    ],
    "wof:name":"Nambucca Heads Primary School",
    "wof:placetype":"venue"
},
  "geometry": {"coordinates":[153.00100699999999,-30.642582],"type":"Point"}
}