{
  "type": "Feature",
  "properties": {
    "iso:country":"AU",
    "sg:address":"PO Box 70",
    "sg:city":"Mt Lawley",
    "sg:classifiers":[
        {
            "category":"Professional",
            "subcategory":"Art Services",
            "type":"Services"
        }
    ],
    "sg:phone":"+61 8 9493 7484",
    "sg:postcode":"6929",
    "sg:province":"WA",
    "sg:tags":[
        "interior",
        "designer"
    ],
    "wof:name":"IKA Interior Design",
    "wof:placetype":"venue"
},
  "geometry": {"coordinates":[115.872161865,-31.9344406128],"type":"Point"}
}