{
  "type": "Feature",
  "properties": {
    "iso:country":"AU",
    "sg:address":"38 Jephson St",
    "sg:city":"Toowong",
    "sg:classifiers":[
        {
            "category":"Travel",
            "subcategory":"Hotels & Motels",
            "type":"Entertainment"
        }
    ],
    "sg:phone":"+61 7 3870 3522",
    "sg:postcode":"4066",
    "sg:province":"QLD",
    "sg:website":"http://www.toowongcentral.com",
    "wof:name":"Toowong Central Motel",
    "wof:placetype":"venue"
},
  "geometry": {"coordinates":[152.990966797,-27.4837589264],"type":"Point"}
}