{
  "type": "Feature",
  "properties": {
    "iso:country":"AU",
    "sg:address":"Lara St",
    "sg:city":"Barcaldine",
    "sg:classifiers":[
        {
            "category":"Building & Trades",
            "subcategory":"Landscaping Services",
            "type":"Services"
        }
    ],
    "sg:phone":"+61 7 4651 1619",
    "sg:postcode":"4725",
    "sg:province":"QLD",
    "sg:tags":[
        "grazier"
    ],
    "wof:name":"Pumpa K L",
    "wof:placetype":"venue"
},
  "geometry": {"coordinates":[145.284073,-23.55266],"type":"Point"}
}