{
  "type": "Feature",
  "properties": {
    "addr:full":"Unit 5 & 6, 50 Peachey Rd Davoren Park SA 5113",
    "addr:housenumber":"&;50",
    "addr:postcode":"5113",
    "addr:street":"Peachey Rd",
    "iso:country":"AU",
    "sg:address":"Unit 5 & 6, 50 Peachey Rd",
    "sg:city":"Davoren Park",
    "sg:classifiers":[
        {
            "category":"Professional",
            "subcategory":"Computer Services",
            "type":"Services"
        }
    ],
    "sg:phone":"+61 8 8287 1005",
    "sg:postcode":"5113",
    "sg:province":"SA",
    "sg:tags":[
        "information"
    ],
    "wof:name":"Trust Tenants Information Centre",
    "wof:placetype":"venue"
},
  "geometry": {"coordinates":[138.666946411,-34.695438385],"type":"Point"}
}