{
  "type": "Feature",
  "properties": {
    "iso:country":"AU",
    "sg:address":"73 Strelley St",
    "sg:city":"Busselton",
    "sg:classifiers":[
        {
            "category":"Wholesale",
            "subcategory":"Scrap",
            "type":"Manufacturing & Wholesale Goods"
        }
    ],
    "sg:phone":"+61 8 9752 3795",
    "sg:postcode":"6280",
    "sg:province":"WA",
    "sg:tags":[
        "merchant",
        "metal"
    ],
    "wof:name":"Busselton Salvage",
    "wof:placetype":"venue"
},
  "geometry": {"coordinates":[115.350997925,-33.6577949524],"type":"Point"}
}