{
  "type": "Feature",
  "properties": {
    "addr:full":"92 Glenwood Drv Morayfield QLD 4506",
    "addr:housenumber":"92",
    "addr:postcode":"4506",
    "addr:street":"Glenwood Drv",
    "iso:country":"AU",
    "sg:address":"92 Glenwood Drv",
    "sg:city":"Morayfield",
    "sg:classifiers":[
        {
            "category":"Fast Food",
            "type":"Food & Drink"
        }
    ],
    "sg:phone":"+61 7 5498 7966",
    "sg:postcode":"4506",
    "sg:province":"QLD",
    "sg:tags":[
        "away",
        "take"
    ],
    "wof:name":"Glenwood Seafood & Takeaway",
    "wof:placetype":"venue"
},
  "geometry": {"coordinates":[152.962524414,-27.1148395538],"type":"Point"}
}