{
  "type": "Feature",
  "properties": {
    "addr:full":"Cnr Newland & Ebley Sts Bondi Junction NSW 2022",
    "addr:postcode":"2022",
    "addr:street":"Cnr",
    "iso:country":"AU",
    "sg:address":"Cnr Newland & Ebley Sts",
    "sg:city":"Bondi Junction",
    "sg:classifiers":[
        {
            "category":"Parking",
            "type":"Transportation"
        }
    ],
    "sg:phone":"+61 2 9959 3145",
    "sg:postcode":"2022",
    "sg:province":"NSW",
    "wof:name":"Secure Parking",
    "wof:placetype":"venue"
},
  "geometry": {"coordinates":[151.24720764200001,-33.8928337097],"type":"Point"}
}