{
  "type": "Feature",
  "properties": {
    "iso:country":"AU",
    "sg:address":"(via Wee Waa Rd) 2 Francis St",
    "sg:city":"Narrabri",
    "sg:classifiers":[
        {
            "category":"Home & Garden",
            "subcategory":"Furniture",
            "type":"Retail Goods"
        }
    ],
    "sg:phone":"+61 2 6792 2382",
    "sg:postcode":"2390",
    "sg:province":"NSW",
    "sg:tags":[
        "business"
    ],
    "wof:name":"Fordham Trading Centre",
    "wof:placetype":"venue"
},
  "geometry": {"coordinates":[149.77798461899999,-30.3129329681],"type":"Point"}
}