{
  "type": "Feature",
  "properties": {
    "addr:full":"19 Narambi St The Gap QLD 4061",
    "addr:housenumber":"19",
    "addr:postcode":"4061",
    "addr:street":"Narambi St",
    "iso:country":"AU",
    "sg:address":"19 Narambi St",
    "sg:city":"The Gap",
    "sg:classifiers":[
        {
            "category":"Shopping",
            "subcategory":"Computers & Home Electronics",
            "type":"Retail Goods"
        }
    ],
    "sg:phone":"+61 7 3300 6473",
    "sg:postcode":"4061",
    "sg:province":"QLD",
    "sg:tags":[
        "small",
        "equipment",
        "business"
    ],
    "wof:name":"Summers Young Resources Pty Ltd",
    "wof:placetype":"venue"
},
  "geometry": {"coordinates":[152.94841003400001,-27.4367389679],"type":"Point"}
}