{
  "type": "Feature",
  "properties": {
    "addr:full":"200 South St South Toowoomba QLD 4350",
    "addr:housenumber":"200",
    "addr:postcode":"4350",
    "addr:street":"South St",
    "iso:country":"AU",
    "sg:address":"200 South St",
    "sg:city":"South Toowoomba",
    "sg:classifiers":[
        {
            "category":"Organizations",
            "subcategory":"Membership Organization",
            "type":"Services"
        }
    ],
    "sg:phone":"+61 7 4635 5318",
    "sg:postcode":"4350",
    "sg:province":"QLD",
    "sg:tags":[
        "support",
        "health",
        "organisation"
    ],
    "wof:name":"Mereki Recognised Entity",
    "wof:placetype":"venue"
},
  "geometry": {"coordinates":[151.95451399999999,-27.579048],"type":"Point"}
}