{
  "type": "Feature",
  "properties": {
    "addr:full":"292 Unley Rd Hyde Park SA 5061",
    "addr:housenumber":"292",
    "addr:postcode":"5061",
    "addr:street":"Unley Rd",
    "iso:country":"AU",
    "sg:address":"292 Unley Rd",
    "sg:city":"Hyde Park",
    "sg:classifiers":[
        {
            "category":"Restaurant",
            "type":"Food & Drink"
        }
    ],
    "sg:phone":"+61 8 8373 4404",
    "sg:postcode":"5061",
    "sg:province":"SA",
    "sg:website":"http://www.tandoorioven.com.au",
    "wof:name":"Tandoori Oven",
    "wof:placetype":"venue"
},
  "geometry": {"coordinates":[138.60780334500001,-34.9563140869],"type":"Point"}
}