{
  "type": "Feature",
  "properties": {
    "addr:full":"Suite 4, 8-10 Wharf Rd Gladesville NSW 2111",
    "addr:housenumber":"8-10",
    "addr:postcode":"2111",
    "addr:street":"Wharf Rd",
    "iso:country":"AU",
    "sg:address":"Suite 4, 8-10 Wharf Rd",
    "sg:city":"Gladesville",
    "sg:classifiers":[
        {
            "category":"Personal",
            "subcategory":"Massage",
            "type":"Services"
        }
    ],
    "sg:phone":"+61 2 9817 8766",
    "sg:postcode":"2111",
    "sg:province":"NSW",
    "sg:tags":[
        "therapy"
    ],
    "wof:name":"The Source of Wellness Natural Health Centre",
    "wof:placetype":"venue"
},
  "geometry": {"coordinates":[151.12690734899999,-33.834148407],"type":"Point"}
}