{
  "type": "Feature",
  "properties": {
    "addr:full":"32 Greenway Drv Tweed Heads South QLD 2486",
    "addr:housenumber":"32",
    "addr:postcode":"2486",
    "addr:street":"Greenway Drv",
    "iso:country":"AU",
    "sg:address":"32 Greenway Drv",
    "sg:city":"Tweed Heads South",
    "sg:classifiers":[
        {
            "category":"Home & Garden",
            "subcategory":"Carpets & Floor Coverings",
            "type":"Retail Goods"
        }
    ],
    "sg:phone":"+61 7 5523 2111",
    "sg:postcode":"2486",
    "sg:province":"QLD",
    "sg:tags":[
        "wood"
    ],
    "wof:name":"Solomons Flooring",
    "wof:placetype":"venue"
},
  "geometry": {"coordinates":[153.534332275,-28.2122993469],"type":"Point"}
}