{
  "type": "Feature",
  "properties": {
    "iso:country":"AU",
    "sg:address":"15 Myrtle St",
    "sg:city":"Myrtleford",
    "sg:classifiers":[
        {
            "category":"Farming",
            "subcategory":"Dairy Farm",
            "type":"Manufacturing & Wholesale Goods"
        }
    ],
    "sg:phone":"+61 3 5751 1237",
    "sg:postcode":"3737",
    "sg:province":"VIC",
    "wof:name":"Myrtleford Dairy",
    "wof:placetype":"venue"
},
  "geometry": {"coordinates":[146.72653198200001,-36.5626068115],"type":"Point"}
}