{
  "type": "Feature",
  "properties": {
    "addr:full":"211 Princess Hwy Ulladulla NSW 2539",
    "addr:housenumber":"211",
    "addr:postcode":"2539",
    "addr:street":"Princess Hwy",
    "iso:country":"AU",
    "sg:address":"211 Princess Hwy",
    "sg:city":"Ulladulla",
    "sg:classifiers":[
        {
            "category":"Education",
            "subcategory":"Special Training",
            "type":"Public Place"
        }
    ],
    "sg:phone":"+61 2 4455 3029",
    "sg:postcode":"2539",
    "sg:province":"NSW",
    "sg:tags":[
        "diving",
        "school",
        "scuba"
    ],
    "wof:name":"Ulladulla Dive & Adventure Centre",
    "wof:placetype":"venue"
},
  "geometry": {"coordinates":[150.47065734899999,-35.3671073914],"type":"Point"}
}