{
  "type": "Feature",
  "properties": {
    "iso:country":"AU",
    "sg:address":"Bucasia Rd",
    "sg:city":"Bucasia",
    "sg:classifiers":[
        {
            "category":"Home & Garden",
            "subcategory":"Building Materials",
            "type":"Retail Goods"
        }
    ],
    "sg:phone":"+61 7 4954 8134",
    "sg:postcode":"4750",
    "sg:province":"QLD",
    "sg:tags":[
        "retaining",
        "wall"
    ],
    "wof:name":"Bucasia Gardens & Gifts",
    "wof:placetype":"venue"
},
  "geometry": {"coordinates":[149.15535,-21.04352],"type":"Point"}
}