{
  "type": "Feature",
  "properties": {
    "addr:full":"179 Northern Rd Heidelberg VIC 3084",
    "addr:housenumber":"179",
    "addr:postcode":"3084",
    "addr:street":"Northern Rd",
    "iso:country":"AU",
    "sg:address":"179 Northern Rd",
    "sg:city":"Heidelberg",
    "sg:classifiers":[
        {
            "category":"Health Services",
            "subcategory":"Doctor",
            "type":"Services"
        }
    ],
    "sg:phone":"+61 3 9458 2725",
    "sg:postcode":"3084",
    "sg:province":"VIC",
    "sg:tags":[
        "medical",
        "practitioner"
    ],
    "wof:name":"Gya Devan",
    "wof:placetype":"venue"
},
  "geometry": {"coordinates":[145.06050109899999,-37.7305374146],"type":"Point"}
}