{
  "type": "Feature",
  "properties": {
    "iso:country":"AU",
    "sg:address":"32 Meadowland Rd",
    "sg:city":"Peakhurst",
    "sg:classifiers":[
        {
            "category":"Professional",
            "subcategory":"Art Services",
            "type":"Services"
        }
    ],
    "sg:phone":"+61 2 9584 3180",
    "sg:postcode":"2210",
    "sg:province":"NSW",
    "sg:tags":[
        "decorator",
        "painter"
    ],
    "wof:name":"Acon Painting & Decorating",
    "wof:placetype":"venue"
},
  "geometry": {"coordinates":[151.062149,-33.953583],"type":"Point"}
}