{
  "type": "Feature",
  "properties": {
    "addr:full":"856 Sydney Rd Brunswick VIC 3055",
    "addr:housenumber":"856",
    "addr:postcode":"3055",
    "addr:street":"Sydney Rd",
    "iso:country":"AU",
    "sg:address":"856 Sydney Rd",
    "sg:city":"Brunswick",
    "sg:classifiers":[
        {
            "category":"Professional",
            "subcategory":"Printing & Photocopies",
            "type":"Services"
        }
    ],
    "sg:phone":"+61 1800 622 050",
    "sg:postcode":"3055",
    "sg:province":"VIC",
    "sg:tags":[
        "publishing",
        "desktop"
    ],
    "wof:name":"FontShop Pty Ltd",
    "wof:placetype":"venue"
},
  "geometry": {"coordinates":[144.964080811,-37.7566184998],"type":"Point"}
}