{
  "type": "Feature",
  "properties": {
    "addr:full":"Shp3/ 1534 Wynnum Rd Tingalpa QLD 4173",
    "addr:housenumber":"1534",
    "addr:postcode":"4173",
    "addr:street":"Wynnum Rd",
    "iso:country":"AU",
    "sg:address":"Shp3/ 1534 Wynnum Rd",
    "sg:city":"Tingalpa",
    "sg:classifiers":[
        {
            "category":"Cafe",
            "type":"Food & Drink"
        }
    ],
    "sg:phone":"+61 7 3890 5535",
    "sg:postcode":"4173",
    "sg:province":"QLD",
    "wof:name":"Swish Expresso Cafe",
    "wof:placetype":"venue"
},
  "geometry": {"coordinates":[153.125534058,-27.4744052887],"type":"Point"}
}