{
  "type": "Feature",
  "properties": {
    "addr:full":"2/ 334 Waterworks Rd Ashgrove QLD 4060",
    "addr:housenumber":"/ 334",
    "addr:postcode":"4060",
    "addr:street":"Waterworks Rd",
    "iso:country":"AU",
    "sg:address":"2/ 334 Waterworks Rd",
    "sg:city":"Ashgrove",
    "sg:classifiers":[
        {
            "category":"Building & Trades",
            "subcategory":"Construction",
            "type":"Services"
        }
    ],
    "sg:phone":"+61 7 3366 7258",
    "sg:postcode":"4060",
    "sg:province":"QLD",
    "sg:tags":[
        "roof"
    ],
    "wof:name":"Ramalco Pty Ltd",
    "wof:placetype":"venue"
},
  "geometry": {"coordinates":[152.987915039,-27.4459152222],"type":"Point"}
}