{
  "type": "Feature",
  "properties": {
    "addr:full":"221 Concord Rd North Strathfield NSW 2137",
    "addr:housenumber":"221",
    "addr:postcode":"2137",
    "addr:street":"Concord Rd",
    "iso:country":"AU",
    "sg:address":"221 Concord Rd",
    "sg:city":"North Strathfield",
    "sg:classifiers":[
        {
            "category":"Shopping",
            "subcategory":"Clothing, Apparel, & Fashions",
            "type":"Retail Goods"
        }
    ],
    "sg:phone":"+61 2 9743 5074",
    "sg:postcode":"2137",
    "sg:province":"NSW",
    "sg:tags":[
        "lady",
        "wear"
    ],
    "wof:name":"Victoria D Fashions",
    "wof:placetype":"venue"
},
  "geometry": {"coordinates":[151.091888428,-33.8566551208],"type":"Point"}
}