{
  "type": "Feature",
  "properties": {
    "addr:full":"123 Bunya Rd Arana Hills QLD 4054",
    "addr:housenumber":"123",
    "addr:postcode":"4054",
    "addr:street":"Bunya Rd",
    "iso:country":"AU",
    "sg:address":"123 Bunya Rd",
    "sg:city":"Arana Hills",
    "sg:classifiers":[
        {
            "category":"Education",
            "subcategory":"School",
            "type":"Public Place"
        }
    ],
    "sg:phone":"+61 7 3851 1496",
    "sg:postcode":"4054",
    "sg:province":"QLD",
    "wof:name":"Pine Community School",
    "wof:placetype":"venue"
},
  "geometry": {"coordinates":[152.962036133,-27.3875389099],"type":"Point"}
}