{
  "type": "Feature",
  "properties": {
    "addr:full":"Meadows Rd Moruya NSW 2537",
    "addr:postcode":"2537",
    "addr:street":"Meadows Rd",
    "iso:country":"AU",
    "sg:address":"Meadows Rd",
    "sg:city":"Moruya",
    "sg:classifiers":[
        {
            "category":"Building & Trades",
            "subcategory":"Landscaping Services",
            "type":"Services"
        }
    ],
    "sg:phone":"+61 2 4474 3073",
    "sg:postcode":"2537",
    "sg:province":"NSW",
    "sg:tags":[
        "firebreak",
        "clearing",
        "land",
        "contractor"
    ],
    "wof:name":"Clout J R",
    "wof:placetype":"venue"
},
  "geometry": {"coordinates":[150.05398559599999,-35.8599205017],"type":"Point"}
}