{
  "type": "Feature",
  "properties": {
    "addr:full":"113 Lindrum Rd Frankston VIC 3199",
    "addr:housenumber":"113",
    "addr:postcode":"3199",
    "addr:street":"Lindrum Rd",
    "iso:country":"AU",
    "sg:address":"113 Lindrum Rd",
    "sg:city":"Frankston",
    "sg:classifiers":[
        {
            "category":"Building & Trades",
            "subcategory":"Plumbing",
            "type":"Services"
        }
    ],
    "sg:phone":"+61 3 9789 6877",
    "sg:postcode":"3199",
    "sg:province":"VIC",
    "sg:tags":[
        "plumber",
        "gasfitters"
    ],
    "wof:name":"Mott Plumbing Service Pty Ltd",
    "wof:placetype":"venue"
},
  "geometry": {"coordinates":[145.15377807600001,-38.1501235962],"type":"Point"}
}