{
  "type": "Feature",
  "properties": {
    "addr:full":"Shop 16 Nightcliff Shopping Centre Nightcliff NT 0810",
    "addr:housenumber":"shop 16",
    "addr:postcode":"nt 0810",
    "iso:country":"AU",
    "sg:address":"Shop 16 Nightcliff Shopping Centre",
    "sg:city":"Nightcliff",
    "sg:classifiers":[
        {
            "category":"Personal",
            "subcategory":"Skin Care",
            "type":"Services"
        }
    ],
    "sg:phone":"+61 8 8985 6088",
    "sg:postcode":"0810",
    "sg:province":"NT",
    "sg:tags":[
        "treatment"
    ],
    "wof:name":"Advanced Body Image",
    "wof:placetype":"venue"
},
  "geometry": {"coordinates":[130.85614013700001,-12.3864011765],"type":"Point"}
}