{
  "type": "Feature",
  "properties": {
    "addr:full":"32 Sunrise Ave Budgewoi NSW 2262",
    "addr:housenumber":"32",
    "addr:postcode":"2262",
    "addr:street":"Sunrise Ave",
    "iso:country":"AU",
    "sg:address":"32 Sunrise Ave",
    "sg:city":"Budgewoi",
    "sg:classifiers":[
        {
            "category":"Professional",
            "subcategory":"Employment Agencies",
            "type":"Services"
        }
    ],
    "sg:phone":"+61 2 4390 7094",
    "sg:postcode":"2262",
    "sg:province":"NSW",
    "sg:tags":[
        "entertainer",
        "agent"
    ],
    "wof:name":"Central Coast Shakespeare Company",
    "wof:placetype":"venue"
},
  "geometry": {"coordinates":[151.55299400000001,-33.228596],"type":"Point"}
}