{
  "type": "Feature",
  "properties": {
    "iso:country":"AU",
    "sg:address":"68- 70 Booth St",
    "sg:city":"Annandale",
    "sg:classifiers":[
        {
            "category":"Wholesale",
            "subcategory":"Painting Supplies",
            "type":"Manufacturing & Wholesale Goods"
        }
    ],
    "sg:phone":"+61 2 9660 5000",
    "sg:postcode":"2038",
    "sg:province":"NSW",
    "sg:tags":[
        "product",
        "cleaning"
    ],
    "wof:name":"Chemtest Pty. Ltd.",
    "wof:placetype":"venue"
},
  "geometry": {"coordinates":[151.17083740199999,-33.8815956116],"type":"Point"}
}