{
  "type": "Feature",
  "properties": {
    "iso:country":"AU",
    "sg:address":"21-23 Challis Ave",
    "sg:city":"Potts Point",
    "sg:classifiers":[
        {
            "category":"Travel",
            "subcategory":"Hotels & Motels",
            "type":"Entertainment"
        }
    ],
    "sg:phone":"+61 2 9358 5422",
    "sg:postcode":"2011",
    "sg:province":"NSW",
    "sg:tags":[
        "accommodation"
    ],
    "wof:name":"Challis Lodge",
    "wof:placetype":"venue"
},
  "geometry": {"coordinates":[151.22392273,-33.8688812256],"type":"Point"}
}