{
  "type": "Feature",
  "properties": {
    "iso:country":"AU",
    "sg:address":"Wearing Rd",
    "sg:city":"North Maclean",
    "sg:classifiers":[
        {
            "category":"Retail",
            "subcategory":"Auto Repair",
            "type":"Services"
        }
    ],
    "sg:phone":"+61 7 5547 7569",
    "sg:postcode":"4280",
    "sg:province":"QLD",
    "sg:tags":[
        "repairer",
        "motor",
        "engineer"
    ],
    "wof:name":"Roundhouse Workshop",
    "wof:placetype":"venue"
},
  "geometry": {"coordinates":[153.0168,-27.775677],"type":"Point"}
}