{
  "type": "Feature",
  "properties": {
    "addr:full":"29 Bennett St Harbord NSW 2096",
    "addr:housenumber":"29",
    "addr:postcode":"2096",
    "addr:street":"Bennett St",
    "iso:country":"AU",
    "sg:address":"29 Bennett St",
    "sg:city":"Harbord",
    "sg:classifiers":[
        {
            "category":"Utilities",
            "subcategory":"Refuse",
            "type":"Services"
        }
    ],
    "sg:phone":"+61 2 9939 6561",
    "sg:postcode":"2096",
    "sg:province":"NSW",
    "sg:tags":[
        "remover",
        "rubbish"
    ],
    "wof:name":"Lussick J M",
    "wof:placetype":"venue"
},
  "geometry": {"coordinates":[151.28277587900001,-33.7686386108],"type":"Point"}
}