{
  "type": "Feature",
  "properties": {
    "addr:full":"PO Box 4221 Kingston ACT 2604",
    "addr:postcode":"2604",
    "iso:country":"AU",
    "sg:address":"PO Box 4221",
    "sg:city":"Kingston",
    "sg:classifiers":[
        {
            "category":"Social Services",
            "subcategory":"Job Training",
            "type":"Services"
        }
    ],
    "sg:phone":"+61 2 6290 0986",
    "sg:postcode":"2604",
    "sg:province":"ACT",
    "sg:tags":[
        "equipment",
        "clean",
        "installation",
        "room",
        "maintenance"
    ],
    "wof:name":"Cleanair",
    "wof:placetype":"venue"
},
  "geometry": {"coordinates":[149.14822387699999,-35.3175086975],"type":"Point"}
}