{
  "type": "Feature",
  "properties": {
    "addr:full":"1/ 77 Macleod St Bairnsdale VIC 3875",
    "addr:housenumber":"/ 77",
    "addr:postcode":"3875",
    "addr:street":"Macleod St",
    "iso:country":"AU",
    "sg:address":"1/ 77 Macleod St",
    "sg:city":"Bairnsdale",
    "sg:classifiers":[
        {
            "category":"Autos & Motor Vehicles",
            "subcategory":"Auto Supplies",
            "type":"Retail Goods"
        }
    ],
    "sg:phone":"+61 3 5153 0045",
    "sg:postcode":"3875",
    "sg:province":"VIC",
    "sg:tags":[
        "battery",
        "automotive"
    ],
    "wof:name":"Oz Batteries",
    "wof:placetype":"venue"
},
  "geometry": {"coordinates":[147.631225586,-37.8274765015],"type":"Point"}
}