{
  "type": "Feature",
  "properties": {
    "iso:country":"AU",
    "sg:address":"Shop G16 Woden Plaza 8 Keltie St",
    "sg:city":"Phillip",
    "sg:classifiers":[
        {
            "category":"Shopping",
            "subcategory":"Clothing, Apparel, & Fashions",
            "type":"Retail Goods"
        }
    ],
    "sg:phone":"+61 2 6232 4853",
    "sg:postcode":"2606",
    "sg:province":"ACT",
    "sg:tags":[
        "lady",
        "wear"
    ],
    "wof:name":"Wombat",
    "wof:placetype":"venue"
},
  "geometry": {"coordinates":[149.08462524399999,-35.3454475403],"type":"Point"}
}