{
  "type": "Feature",
  "properties": {
    "addr:full":"Unit 5/ 19 Dominions Rd Ashmore QLD 4214",
    "addr:postcode":"4214",
    "addr:street":"19 Dominions Rd",
    "iso:country":"AU",
    "sg:address":"Unit 5/ 19 Dominions Rd",
    "sg:city":"Ashmore",
    "sg:classifiers":[
        {
            "category":"Manufacturing",
            "subcategory":"Apparel",
            "type":"Manufacturing & Wholesale Goods"
        }
    ],
    "sg:phone":"+61 7 5597 1415",
    "sg:postcode":"4214",
    "sg:province":"QLD",
    "sg:tags":[
        "wholesaler",
        "mfrs",
        "footwear"
    ],
    "wof:name":"House Of Antoni",
    "wof:placetype":"venue"
},
  "geometry": {"coordinates":[153.383712769,-27.9801940918],"type":"Point"}
}