{
  "type": "Feature",
  "properties": {
    "iso:country":"AU",
    "sg:address":"PO Box 15",
    "sg:city":"Pascoe Vale South",
    "sg:classifiers":[
        {
            "category":"Building & Trades",
            "subcategory":"Construction",
            "type":"Services"
        }
    ],
    "sg:phone":"+61 418 176 186",
    "sg:postcode":"3044",
    "sg:province":"VIC",
    "sg:tags":[
        "plasterboard",
        "plasterer",
        "fixer"
    ],
    "wof:name":"J V M Plaster Group Pty Ltd",
    "wof:placetype":"venue"
},
  "geometry": {"coordinates":[144.93988037099999,-37.7414398193],"type":"Point"}
}