{
  "type": "Feature",
  "properties": {
    "addr:full":"116 Bell St Coburg VIC 3058",
    "addr:housenumber":"116",
    "addr:postcode":"3058",
    "addr:street":"Bell St",
    "iso:country":"AU",
    "sg:address":"116 Bell St",
    "sg:city":"Coburg",
    "sg:classifiers":[
        {
            "category":"Retail",
            "subcategory":"Auto Repair",
            "type":"Services"
        }
    ],
    "sg:phone":"+61 3 9350 2599",
    "sg:postcode":"3058",
    "sg:province":"VIC",
    "sg:tags":[
        "repairer",
        "motor",
        "engineer"
    ],
    "wof:name":"Quik Lube",
    "wof:placetype":"venue"
},
  "geometry": {"coordinates":[144.96490478499999,-37.7410163879],"type":"Point"}
}