{
  "type": "Feature",
  "properties": {
    "iso:country":"AU",
    "sg:address":"Level 1/ 101 Nicholson St",
    "sg:city":"Footscray",
    "sg:classifiers":[
        {
            "category":"Professional",
            "subcategory":"Art Services",
            "type":"Services"
        }
    ],
    "sg:phone":"+61 418 518 549",
    "sg:postcode":"3011",
    "sg:province":"VIC",
    "sg:tags":[
        "graphic",
        "designer"
    ],
    "wof:name":"Hoang Tran Nguyen",
    "wof:placetype":"venue"
},
  "geometry": {"coordinates":[144.899124145,-37.8012542725],"type":"Point"}
}