{
  "type": "Feature",
  "properties": {
    "addr:full":"34 Peachtree Rd Penrith NSW 2750",
    "addr:housenumber":"34",
    "addr:postcode":"2750",
    "addr:street":"Peachtree Rd",
    "iso:country":"AU",
    "sg:address":"34 Peachtree Rd",
    "sg:city":"Penrith",
    "sg:classifiers":[
        {
            "category":"Wholesale",
            "subcategory":"Auto Parts",
            "type":"Manufacturing & Wholesale Goods"
        }
    ],
    "sg:phone":"+61 2 4731 2415",
    "sg:postcode":"2750",
    "sg:province":"NSW",
    "sg:tags":[
        "recyclers"
    ],
    "wof:name":"Wreckall",
    "wof:placetype":"venue"
},
  "geometry": {"coordinates":[150.97462463400001,-33.7889289856],"type":"Point"}
}