{
  "type": "Feature",
  "properties": {
    "iso:country":"AU",
    "sg:address":"1 Poole Cl",
    "sg:city":"Empire Bay",
    "sg:classifiers":[
        {
            "category":"Travel",
            "subcategory":"Hotels & Motels",
            "type":"Entertainment"
        }
    ],
    "sg:phone":"+61 2 4369 5840",
    "sg:postcode":"2257",
    "sg:province":"NSW",
    "sg:tags":[
        "accommodation"
    ],
    "wof:name":"Empire Bay Tavern The",
    "wof:placetype":"venue"
},
  "geometry": {"coordinates":[151.372802734,-33.507850647],"type":"Point"}
}