{
  "type": "Feature",
  "properties": {
    "iso:country":"AU",
    "sg:address":"32 Morgan St",
    "sg:city":"Gladstone",
    "sg:classifiers":[
        {
            "category":"Professional",
            "subcategory":"Testing Lab",
            "type":"Services"
        }
    ],
    "sg:phone":"+61 7 4972 6571",
    "sg:postcode":"4680",
    "sg:province":"QLD",
    "sg:tags":[
        "soil",
        "investigation"
    ],
    "wof:name":"Roadtest",
    "wof:placetype":"venue"
},
  "geometry": {"coordinates":[151.242553711,-23.8376731873],"type":"Point"}
}