{
  "type": "Feature",
  "properties": {
    "iso:country":"AU",
    "sg:address":"150 Great North Rd",
    "sg:city":"Five Dock",
    "sg:classifiers":[
        {
            "category":"Health Services",
            "subcategory":"Doctor",
            "type":"Services"
        }
    ],
    "sg:phone":"+61 2 9713 2233",
    "sg:postcode":"2046",
    "sg:province":"NSW",
    "sg:tags":[
        "podiatrist"
    ],
    "wof:name":"Footology Five Dock",
    "wof:placetype":"venue"
},
  "geometry": {"coordinates":[151.13043200000001,-33.865108],"type":"Point"}
}