{
  "type": "Feature",
  "properties": {
    "addr:full":"Lot 1 Remembrance Drv Bargo NSW 2574",
    "addr:postcode":"2574",
    "addr:street":"Remembrance Drv",
    "iso:country":"AU",
    "sg:address":"Lot 1 Remembrance Drv",
    "sg:city":"Bargo",
    "sg:classifiers":[
        {
            "category":"Home & Garden",
            "subcategory":"Garden Supply",
            "type":"Retail Goods"
        }
    ],
    "sg:phone":"+61 2 4684 2312",
    "sg:postcode":"2574",
    "sg:province":"NSW",
    "sg:tags":[
        "landscape"
    ],
    "wof:name":"Bargo Landscape Supplies",
    "wof:placetype":"venue"
},
  "geometry": {"coordinates":[150.57492065400001,-34.3215751648],"type":"Point"}
}