{
  "type": "Feature",
  "properties": {
    "addr:full":"2 Advantage Rd Highett VIC 3190",
    "addr:housenumber":"2",
    "addr:postcode":"3190",
    "addr:street":"Advantage Rd",
    "iso:country":"AU",
    "sg:address":"2 Advantage Rd",
    "sg:city":"Highett",
    "sg:classifiers":[
        {
            "category":"Communications",
            "subcategory":"Film & Video Production",
            "type":"Services"
        }
    ],
    "sg:phone":"+61 3 9532 2865",
    "sg:postcode":"3190",
    "sg:province":"VIC",
    "sg:tags":[
        "fan",
        "blower"
    ],
    "wof:name":"Nu-Con (Aust.) Pty Ltd",
    "wof:placetype":"venue"
},
  "geometry": {"coordinates":[145.02981567399999,-37.9545631409],"type":"Point"}
}