{
  "type": "Feature",
  "properties": {
    "addr:full":"17 Ewart St Marrickville NSW 2204",
    "addr:housenumber":"17",
    "addr:postcode":"2204",
    "addr:street":"Ewart St",
    "iso:country":"AU",
    "sg:address":"17 Ewart St",
    "sg:city":"Marrickville",
    "sg:classifiers":[
        {
            "category":"Building & Trades",
            "subcategory":"Construction",
            "type":"Services"
        }
    ],
    "sg:phone":"+61 412 706 774",
    "sg:postcode":"2204",
    "sg:province":"NSW",
    "sg:tags":[
        "polishing",
        "sanding",
        "floor"
    ],
    "wof:name":"ATF Floor Sanding & Polishing",
    "wof:placetype":"venue"
},
  "geometry": {"coordinates":[151.14248699999999,-33.914017],"type":"Point"}
}