{
  "type": "Feature",
  "properties": {
    "addr:full":"370 William St Northbridge WA 6003",
    "addr:housenumber":"370",
    "addr:postcode":"6003",
    "addr:street":"William St",
    "iso:country":"AU",
    "sg:address":"370 William St",
    "sg:city":"Northbridge",
    "sg:classifiers":[
        {
            "category":"Transit Center",
            "subcategory":"Passenger",
            "type":"Transportation"
        }
    ],
    "sg:phone":"+61 8 9328 5358",
    "sg:postcode":"6003",
    "sg:province":"WA",
    "sg:tags":[
        "frozen",
        "food",
        "retail"
    ],
    "wof:name":"Tian Tian Frozen Foods",
    "wof:placetype":"venue"
},
  "geometry": {"coordinates":[115.861953735,-31.9451274872],"type":"Point"}
}