{
  "type": "Feature",
  "properties": {
    "addr:full":"PO Box 266 Malvern VIC 3144",
    "addr:postcode":"3144",
    "iso:country":"AU",
    "sg:address":"PO Box 266",
    "sg:city":"Malvern",
    "sg:classifiers":[
        {
            "category":"Wholesale",
            "subcategory":"Construction Materials",
            "type":"Manufacturing & Wholesale Goods"
        }
    ],
    "sg:phone":"+61 3 9822 3999",
    "sg:postcode":"3144",
    "sg:province":"VIC",
    "sg:tags":[
        "protective",
        "coating"
    ],
    "wof:name":"21st Century Coatings (Aust)",
    "wof:placetype":"venue"
},
  "geometry": {"coordinates":[145.03689575199999,-37.8525390625],"type":"Point"}
}