{
  "type": "Feature",
  "properties": {
    "iso:country":"AU",
    "sg:address":"5/ 1404 Logan Rd",
    "sg:city":"Mt Gravatt",
    "sg:classifiers":[
        {
            "category":"Professional",
            "subcategory":"Art Services",
            "type":"Services"
        }
    ],
    "sg:phone":"+61 7 3219 2366",
    "sg:postcode":"4122",
    "sg:province":"QLD",
    "sg:tags":[
        "graphic",
        "designer"
    ],
    "wof:name":"Anne-Maree Althaus",
    "wof:placetype":"venue"
},
  "geometry": {"coordinates":[153.07807922399999,-27.5363941193],"type":"Point"}
}