{
  "type": "Feature",
  "properties": {
    "addr:full":"100 Phillip St Pacific Fair QLD 4218",
    "addr:housenumber":"100",
    "addr:postcode":"4218",
    "addr:street":"Phillip St Pacific Fair",
    "iso:country":"AU",
    "sg:address":"100 Phillip St",
    "sg:city":"Pacific Fair",
    "sg:classifiers":[
        {
            "category":"Banks & Credit Unions",
            "subcategory":"Financial Services",
            "type":"Services"
        }
    ],
    "sg:phone":"+61 1300 669 502",
    "sg:postcode":"4218",
    "sg:province":"QLD",
    "sg:tags":[
        "planning"
    ],
    "sg:website":"http://www.fpa.asn.au",
    "wof:name":"Strategic Advice Pty Ltd",
    "wof:placetype":"venue"
},
  "geometry": {"coordinates":[153.433105469,-28.0316562653],"type":"Point"}
}