{
  "type": "Feature",
  "properties": {
    "iso:country":"AU",
    "sg:address":"10 Bloomfield St",
    "sg:city":"Calliope",
    "sg:classifiers":[
        {
            "category":"Home & Garden",
            "subcategory":"Building Materials",
            "type":"Retail Goods"
        }
    ],
    "sg:phone":"+61 7 4975 7475",
    "sg:postcode":"4680",
    "sg:province":"QLD",
    "sg:tags":[
        "fencing"
    ],
    "wof:name":"Calliope Rural Traders",
    "wof:placetype":"venue"
},
  "geometry": {"coordinates":[151.199676514,-24.005777359],"type":"Point"}
}