{
  "type": "Feature",
  "properties": {
    "addr:full":"1/ 1 Stoddart Rd Prospect NSW 2148",
    "addr:housenumber":"/ 1",
    "addr:postcode":"2148",
    "addr:street":"Stoddart Rd",
    "iso:country":"AU",
    "sg:address":"1/ 1 Stoddart Rd",
    "sg:city":"Prospect",
    "sg:classifiers":[
        {
            "category":"Home & Garden",
            "subcategory":"Carpets & Floor Coverings",
            "type":"Retail Goods"
        }
    ],
    "sg:phone":"+61 2 9631 4655",
    "sg:postcode":"2148",
    "sg:province":"NSW",
    "wof:name":"Carpet Court",
    "wof:placetype":"venue"
},
  "geometry": {"coordinates":[150.924026489,-33.8006744385],"type":"Point"}
}