{
  "type": "Feature",
  "properties": {
    "addr:full":"22 Windjana St Harrison ACT 2914",
    "addr:housenumber":"22",
    "addr:postcode":"2914",
    "addr:street":"Windjana St",
    "iso:country":"AU",
    "sg:address":"22 Windjana St",
    "sg:city":"Harrison",
    "sg:classifiers":[
        {
            "category":"Building & Trades",
            "subcategory":"Construction",
            "type":"Services"
        }
    ],
    "sg:phone":"+61 2 6255 0855",
    "sg:postcode":"2914",
    "sg:province":"ACT",
    "sg:tags":[
        "contractor"
    ],
    "wof:name":"Solitaire Homes Pty Ltd",
    "wof:placetype":"venue"
},
  "geometry": {"coordinates":[149.15103149399999,-35.2021865845],"type":"Point"}
}