{
  "type": "Feature",
  "properties": {
    "addr:full":"64 Ferny Ave Surfers Paradise QLD 4217",
    "addr:housenumber":"64",
    "addr:postcode":"4217",
    "addr:street":"Ferny Ave",
    "iso:country":"AU",
    "sg:address":"64 Ferny Ave",
    "sg:city":"Surfers Paradise",
    "sg:classifiers":[
        {
            "category":"Cafe",
            "type":"Food & Drink"
        }
    ],
    "sg:phone":"+61 7 5504 5332",
    "sg:postcode":"4217",
    "sg:province":"QLD",
    "wof:name":"Fix Espresso & Juice Bar",
    "wof:placetype":"venue"
},
  "geometry": {"coordinates":[153.42718505900001,-27.9975376129],"type":"Point"}
}