{
  "type": "Feature",
  "properties": {
    "addr:full":"Unit 4 31 Bond St Maroubra NSW 2035",
    "addr:housenumber":"31",
    "addr:postcode":"2035",
    "addr:street":"Bond St",
    "iso:country":"AU",
    "sg:address":"Unit 4 31 Bond St",
    "sg:city":"Maroubra",
    "sg:classifiers":[
        {
            "category":"Manufacturing",
            "subcategory":"Chemicals & Compounds",
            "type":"Manufacturing & Wholesale Goods"
        }
    ],
    "sg:phone":"+61 2 9314 2397",
    "sg:postcode":"2035",
    "sg:province":"NSW",
    "sg:tags":[
        "industrial"
    ],
    "wof:name":"Telos Technologies",
    "wof:placetype":"venue"
},
  "geometry": {"coordinates":[151.25909423799999,-33.9439964294],"type":"Point"}
}