{
  "type": "Feature",
  "properties": {
    "addr:full":"10 Commercial Rd Sheidow Park SA 5158",
    "addr:housenumber":"10",
    "addr:postcode":"5158",
    "addr:street":"Commercial Rd",
    "iso:country":"AU",
    "sg:address":"10 Commercial Rd",
    "sg:city":"Sheidow Park",
    "sg:classifiers":[
        {
            "category":"Health Services",
            "subcategory":"Health Practitioner",
            "type":"Services"
        }
    ],
    "sg:phone":"+61 8 8322 3559",
    "sg:postcode":"5158",
    "sg:province":"SA",
    "sg:tags":[
        "dietitian"
    ],
    "wof:name":"Kathy Simpson-Gore",
    "wof:placetype":"venue"
},
  "geometry": {"coordinates":[138.52276611299999,-35.0760345459],"type":"Point"}
}