{
  "type": "Feature",
  "properties": {
    "addr:full":"Fiona St Bellbird Park QLD 4300",
    "addr:postcode":"4300",
    "addr:street":"Fiona St",
    "iso:country":"AU",
    "sg:address":"Fiona St",
    "sg:city":"Bellbird Park",
    "sg:classifiers":[
        {
            "category":"Building & Trades",
            "subcategory":"Construction",
            "type":"Services"
        }
    ],
    "sg:phone":"+61 412 607 180",
    "sg:postcode":"4300",
    "sg:province":"QLD",
    "sg:tags":[
        "welding"
    ],
    "wof:name":"Peter Howarth Welding Services",
    "wof:placetype":"venue"
},
  "geometry": {"coordinates":[152.89686584500001,-27.6357765198],"type":"Point"}
}