{
  "type": "Feature",
  "properties": {
    "iso:country":"AU",
    "sg:address":"180 English St",
    "sg:city":"Manunda",
    "sg:classifiers":[
        {
            "category":"Shopping",
            "subcategory":"Computers & Home Electronics",
            "type":"Retail Goods"
        }
    ],
    "sg:phone":"+61 7 4032 2179",
    "sg:postcode":"4870",
    "sg:province":"QLD",
    "sg:tags":[
        "small",
        "equipment",
        "business"
    ],
    "wof:name":"Hybrid Computers",
    "wof:placetype":"venue"
},
  "geometry": {"coordinates":[145.747024536,-16.9160766602],"type":"Point"}
}