{
  "type": "Feature",
  "properties": {
    "addr:full":"International Trade Park 10 International Sq Tullamarine VIC 3043",
    "addr:housenumber":"10",
    "addr:postcode":"3043",
    "addr:street":"International Sq",
    "iso:country":"AU",
    "sg:address":"International Trade Park 10 International Sq",
    "sg:city":"Tullamarine",
    "sg:classifiers":[
        {
            "category":"Professional",
            "subcategory":"Employment Agencies",
            "type":"Services"
        }
    ],
    "sg:phone":"+61 3 9933 1600",
    "sg:postcode":"3043",
    "sg:province":"VIC",
    "sg:tags":[
        "broker",
        "custom"
    ],
    "wof:name":"Schenker Australia Pty Ltd",
    "wof:placetype":"venue"
},
  "geometry": {"coordinates":[144.8699646,-37.6970405579],"type":"Point"}
}