{
  "type": "Feature",
  "properties": {
    "addr:full":"35 Langton St Capella QLD 4702",
    "addr:housenumber":"35",
    "addr:postcode":"4702",
    "addr:street":"Langton St",
    "iso:country":"AU",
    "sg:address":"35 Langton St",
    "sg:city":"Capella",
    "sg:classifiers":[
        {
            "category":"Utilities",
            "subcategory":"Electric",
            "type":"Services"
        }
    ],
    "sg:phone":"+61 7 4986 4986",
    "sg:postcode":"4702",
    "sg:province":"QLD",
    "sg:tags":[
        "electrical",
        "contractor"
    ],
    "wof:name":"Peak Downs Electrical",
    "wof:placetype":"venue"
},
  "geometry": {"coordinates":[147.698364258,-23.417673111],"type":"Point"}
}