{
  "type": "Feature",
  "properties": {
    "addr:full":"23 Talbert Rd Southern River WA 6110",
    "addr:housenumber":"23",
    "addr:postcode":"6110",
    "addr:street":"Talbert Rd",
    "iso:country":"AU",
    "sg:address":"23 Talbert Rd",
    "sg:city":"Southern River",
    "sg:classifiers":[
        {
            "category":"Health Services",
            "subcategory":"Health Practitioner",
            "type":"Services"
        }
    ],
    "sg:phone":"+61 412 510 184",
    "sg:postcode":"6110",
    "sg:province":"WA",
    "sg:tags":[
        "bowen",
        "therapy"
    ],
    "wof:name":"Donna Vatis Simpson",
    "wof:placetype":"venue"
},
  "geometry": {"coordinates":[115.953491211,-32.1203689575],"type":"Point"}
}