{
  "type": "Feature",
  "properties": {
    "addr:full":"6 Mond St Thorneside QLD 4158",
    "addr:housenumber":"6",
    "addr:postcode":"4158",
    "addr:street":"Mond St",
    "iso:country":"AU",
    "sg:address":"6 Mond St",
    "sg:city":"Thorneside",
    "sg:classifiers":[
        {
            "category":"Professional",
            "type":"Services"
        }
    ],
    "sg:phone":"+61 7 3822 1288",
    "sg:postcode":"4158",
    "sg:province":"QLD",
    "sg:tags":[
        "shop",
        "fitting"
    ],
    "sg:website":"http://www.aeshopfitters.com.au",
    "wof:name":"AE Shopfitters",
    "wof:placetype":"venue"
},
  "geometry": {"coordinates":[153.20135498100001,-27.4905471802],"type":"Point"}
}