{
  "type": "Feature",
  "properties": {
    "addr:full":"18 Armstrong St Middle Park VIC 3206",
    "addr:housenumber":"18",
    "addr:postcode":"3206",
    "addr:street":"Armstrong St",
    "iso:country":"AU",
    "sg:address":"18 Armstrong St",
    "sg:city":"Middle Park",
    "sg:classifiers":[
        {
            "category":"Professional",
            "subcategory":"Computer Services",
            "type":"Services"
        }
    ],
    "sg:phone":"+61 3 9682 1511",
    "sg:postcode":"3206",
    "sg:province":"VIC",
    "sg:tags":[
        "package",
        "software"
    ],
    "wof:name":"Ad Systems Pty Ltd",
    "wof:placetype":"venue"
},
  "geometry": {"coordinates":[144.964294,-37.850204],"type":"Point"}
}