{
  "type": "Feature",
  "properties": {
    "iso:country":"AU",
    "sg:address":"17 May Rd",
    "sg:city":"Lalor",
    "sg:classifiers":[
        {
            "category":"Shopping",
            "subcategory":"Clothing, Apparel, & Fashions",
            "type":"Retail Goods"
        }
    ],
    "sg:phone":"+61 3 9464 7444",
    "sg:postcode":"3075",
    "sg:province":"VIC",
    "sg:tags":[
        "lady",
        "wear"
    ],
    "wof:name":"Cowboys Cash & Carry",
    "wof:placetype":"venue"
},
  "geometry": {"coordinates":[145.00486755399999,-37.8471832275],"type":"Point"}
}