{
  "type": "Feature",
  "properties": {
    "addr:full":"Dundas Crt East Phillip ACT 2606",
    "addr:postcode":"2606",
    "addr:street":"Dundas Crt East",
    "iso:country":"AU",
    "sg:address":"Dundas Crt East",
    "sg:city":"Phillip",
    "sg:classifiers":[
        {
            "category":"Retail",
            "subcategory":"Auto Rental",
            "type":"Services"
        }
    ],
    "sg:phone":"+61 2 6282 7272",
    "sg:postcode":"2606",
    "sg:province":"ACT",
    "sg:tags":[
        "car",
        "hire",
        "minibus"
    ],
    "wof:name":"ACT Car Rentals",
    "wof:placetype":"venue"
},
  "geometry": {"coordinates":[149.08926391599999,-35.3536911011],"type":"Point"}
}