{
  "type": "Feature",
  "properties": {
    "iso:country":"AU",
    "sg:address":"Shp 24/ 184 Rokeby Rd",
    "sg:city":"Subiaco",
    "sg:classifiers":[
        {
            "category":"Cafe",
            "type":"Food & Drink"
        }
    ],
    "sg:phone":"+61 8 6380 2261",
    "sg:postcode":"6008",
    "sg:province":"WA",
    "wof:name":"Spring Espresso",
    "wof:placetype":"venue"
},
  "geometry": {"coordinates":[115.824119568,-31.9502658844],"type":"Point"}
}