{
  "type": "Feature",
  "properties": {
    "iso:country":"AU",
    "sg:address":"33 Mountain View Rd",
    "sg:city":"Mt Eliza",
    "sg:classifiers":[
        {
            "category":"Home & Garden",
            "subcategory":"Building Materials",
            "type":"Retail Goods"
        }
    ],
    "sg:phone":"+61 3 5981 0585",
    "sg:postcode":"3930",
    "sg:province":"VIC",
    "sg:tags":[
        "lawn",
        "cutting",
        "maintenance"
    ],
    "wof:name":"Ramdas Hedges & Gardening Service",
    "wof:placetype":"venue"
},
  "geometry": {"coordinates":[145.09568786599999,-38.2047424316],"type":"Point"}
}