{
  "type": "Feature",
  "properties": {
    "addr:full":"32 St Vincent St Port Adelaide SA 5015",
    "addr:housenumber":"32",
    "addr:postcode":"5015",
    "addr:street":"St Vincent St",
    "iso:country":"AU",
    "sg:address":"32 St Vincent St",
    "sg:city":"Port Adelaide",
    "sg:classifiers":[
        {
            "category":"Retail",
            "subcategory":"Repair Shop",
            "type":"Services"
        }
    ],
    "sg:phone":"+61 8 8447 5522",
    "sg:postcode":"5015",
    "sg:province":"SA",
    "sg:tags":[
        "upholsterer"
    ],
    "wof:name":"Jaffers Pty Ltd",
    "wof:placetype":"venue"
},
  "geometry": {"coordinates":[138.49969482399999,-34.8456077576],"type":"Point"}
}