{
  "type": "Feature",
  "properties": {
    "iso:country":"AU",
    "sg:address":"Level 2 130 Queen St",
    "sg:city":"Brisbane",
    "sg:classifiers":[
        {
            "category":"Shopping",
            "subcategory":"Bridal",
            "type":"Retail Goods"
        }
    ],
    "sg:phone":"+61 7 3221 5325",
    "sg:postcode":"4000",
    "sg:province":"QLD",
    "sg:tags":[
        "hire",
        "wear"
    ],
    "wof:name":"Fiorenza Collections For Brides",
    "wof:placetype":"venue"
},
  "geometry": {"coordinates":[153.024993897,-27.4696540833],"type":"Point"}
}