{
  "type": "Feature",
  "properties": {
    "addr:full":"9 Kendon Ave Murwillumbah NSW 2484",
    "addr:housenumber":"9",
    "addr:postcode":"2484",
    "addr:street":"Kendon Ave",
    "iso:country":"AU",
    "sg:address":"9 Kendon Ave",
    "sg:city":"Murwillumbah",
    "sg:classifiers":[
        {
            "category":"Professional",
            "subcategory":"Accounting & Tax Preparation",
            "type":"Services"
        }
    ],
    "sg:phone":"+61 2 6672 8400",
    "sg:postcode":"2484",
    "sg:province":"NSW",
    "sg:tags":[
        "consultant",
        "taxation"
    ],
    "wof:name":"Stone John Murray",
    "wof:placetype":"venue"
},
  "geometry": {"coordinates":[153.37716674800001,-28.3291931152],"type":"Point"}
}