{
  "type": "Feature",
  "properties": {
    "addr:full":"Unit 32/ 19 Lamrock Ave Bondi Beach NSW 2026",
    "addr:housenumber":"/ 19",
    "addr:postcode":"2026",
    "addr:street":"Lamrock Ave",
    "iso:country":"AU",
    "sg:address":"Unit 32/ 19 Lamrock Ave",
    "sg:city":"Bondi Beach",
    "sg:classifiers":[
        {
            "category":"Building & Trades",
            "subcategory":"Construction",
            "type":"Services"
        }
    ],
    "sg:phone":"+61 2 9365 4656",
    "sg:postcode":"2026",
    "sg:province":"NSW",
    "sg:tags":[
        "polishing",
        "sanding",
        "floor"
    ],
    "wof:name":"Viking Floor Sanding",
    "wof:placetype":"venue"
},
  "geometry": {"coordinates":[151.27235412600001,-33.8919372559],"type":"Point"}
}