{
  "type": "Feature",
  "properties": {
    "addr:full":"Cnr Charlotte & Edward St Brisbane QLD 4000",
    "addr:postcode":"4000",
    "addr:street":"St",
    "iso:country":"AU",
    "sg:address":"Cnr Charlotte & Edward St",
    "sg:city":"Brisbane",
    "sg:classifiers":[
        {
            "category":"Retail",
            "subcategory":"Event Space",
            "type":"Services"
        }
    ],
    "sg:phone":"+61 7 3229 3522",
    "sg:postcode":"4000",
    "sg:province":"QLD",
    "sg:tags":[
        "function",
        "organiser"
    ],
    "wof:name":"Exchange Hotel",
    "wof:placetype":"venue"
},
  "geometry": {"coordinates":[153.02789306599999,-27.4702796936],"type":"Point"}
}