{
  "type": "Feature",
  "properties": {
    "iso:country":"AU",
    "sg:address":"504 Bunnerong Rd",
    "sg:city":"Matraville",
    "sg:classifiers":[
        {
            "category":"Deli",
            "type":"Food & Drink"
        }
    ],
    "sg:phone":"+61 2 9661 7717",
    "sg:postcode":"2036",
    "sg:province":"NSW",
    "sg:tags":[
        "delicatessen"
    ],
    "wof:name":"Bons Deli",
    "wof:placetype":"venue"
},
  "geometry": {"coordinates":[151.23098754899999,-33.9582748413],"type":"Point"}
}