{
  "type": "Feature",
  "properties": {
    "iso:country":"AU",
    "sg:address":"12 Lathouras Crt",
    "sg:city":"Bundaberg",
    "sg:classifiers":[
        {
            "category":"Organizations",
            "subcategory":"Professional Association",
            "type":"Services"
        }
    ],
    "sg:phone":"+61 7 4152 4952",
    "sg:postcode":"4670",
    "sg:province":"QLD",
    "sg:tags":[
        "web",
        "internet"
    ],
    "wof:name":"Working Websites",
    "wof:placetype":"venue"
},
  "geometry": {"coordinates":[152.36782836899999,-24.8694915771],"type":"Point"}
}