{
  "type": "Feature",
  "properties": {
    "iso:country":"AU",
    "sg:address":"306- 310 James St",
    "sg:city":"Toowoomba",
    "sg:classifiers":[
        {
            "category":"Social Services",
            "subcategory":"Retirement Home",
            "type":"Services"
        }
    ],
    "sg:phone":"+61 7 4638 5743",
    "sg:postcode":"4350",
    "sg:province":"QLD",
    "sg:tags":[
        "village"
    ],
    "wof:name":"Oxford Crest Toowoomba",
    "wof:placetype":"venue"
},
  "geometry": {"coordinates":[151.932816,-27.566381],"type":"Point"}
}