{
  "type": "Feature",
  "properties": {
    "iso:country":"AU",
    "sg:address":"Buderim Market Pl",
    "sg:city":"Buderim",
    "sg:classifiers":[
        {
            "category":"Health Services",
            "subcategory":"Doctor",
            "type":"Services"
        }
    ],
    "sg:phone":"+61 7 5445 1046",
    "sg:postcode":"4556",
    "sg:province":"QLD",
    "sg:tags":[
        "medical",
        "practitioner"
    ],
    "wof:name":"Aviators-Pilot Medical Examination Centre and Scuba Divers Medical Examination Centre",
    "wof:placetype":"venue"
},
  "geometry": {"coordinates":[153.09902954099999,-26.6743774414],"type":"Point"}
}