{
  "type": "Feature",
  "properties": {
    "addr:full":"13 Airdrie Mews Greenvale VIC 3059",
    "addr:housenumber":"13",
    "addr:postcode":"3059",
    "addr:street":"Airdrie Mews",
    "iso:country":"AU",
    "sg:address":"13 Airdrie Mews",
    "sg:city":"Greenvale",
    "sg:classifiers":[
        {
            "category":"Health Services",
            "subcategory":"Doctor",
            "type":"Services"
        }
    ],
    "sg:phone":"+61 3 9333 1999",
    "sg:postcode":"3059",
    "sg:province":"VIC",
    "sg:tags":[
        "occupational",
        "safety"
    ],
    "wof:name":"Chemdry Professionals",
    "wof:placetype":"venue"
},
  "geometry": {"coordinates":[144.881759644,-37.643825531],"type":"Point"}
}