{
  "type": "Feature",
  "properties": {
    "addr:full":"Cnr Hume Hwy & Grove St Liverpool NSW 2170",
    "addr:postcode":"2170",
    "addr:street":"Cnr Hume Hwy & Grove St",
    "iso:country":"AU",
    "sg:address":"Cnr Hume Hwy & Grove St",
    "sg:city":"Liverpool",
    "sg:classifiers":[
        {
            "category":"Building & Trades",
            "subcategory":"Construction",
            "type":"Services"
        }
    ],
    "sg:phone":"+61 2 9838 0455",
    "sg:postcode":"2170",
    "sg:province":"NSW",
    "sg:tags":[
        "pool",
        "swimming"
    ],
    "wof:name":"Viking Pools Pty Ltd",
    "wof:placetype":"venue"
},
  "geometry": {"coordinates":[150.91700744600001,-33.9320106506],"type":"Point"}
}