{
  "type": "Feature",
  "properties": {
    "addr:full":"Goldfields Plz Nash St Gympie QLD 4570",
    "addr:postcode":"4570",
    "addr:street":"Goldfields Plz Nash St",
    "iso:country":"AU",
    "sg:address":"Goldfields Plz Nash St",
    "sg:city":"Gympie",
    "sg:classifiers":[
        {
            "category":"Building & Trades",
            "subcategory":"Locksmith",
            "type":"Services"
        }
    ],
    "sg:phone":"+61 7 5482 8430",
    "sg:postcode":"4570",
    "sg:province":"QLD",
    "sg:tags":[
        "lock"
    ],
    "wof:name":"Goldfields Plaza Keys & Engraving",
    "wof:placetype":"venue"
},
  "geometry": {"coordinates":[152.659790039,-26.188167572],"type":"Point"}
}