{
  "type": "Feature",
  "properties": {
    "iso:country":"AU",
    "sg:address":"3 Windsor Rd",
    "sg:city":"Berkeley Vale",
    "sg:classifiers":[
        {
            "category":"Professional",
            "subcategory":"Detective & Security Services",
            "type":"Services"
        }
    ],
    "sg:phone":"+61 2 4389 1003",
    "sg:postcode":"2261",
    "sg:province":"NSW",
    "sg:tags":[
        "equipment",
        "window",
        "doors"
    ],
    "wof:name":"Uncles Locksmiths",
    "wof:placetype":"venue"
},
  "geometry": {"coordinates":[151.437973,-33.334999],"type":"Point"}
}