{
  "type": "Feature",
  "properties": {
    "iso:country":"AU",
    "sg:address":"Shop 4 Lalchere St",
    "sg:city":"Curl Curl",
    "sg:classifiers":[
        {
            "category":"Personal",
            "subcategory":"Beauty Salon",
            "type":"Services"
        }
    ],
    "sg:phone":"+61 2 9905 4492",
    "sg:postcode":"2096",
    "sg:province":"NSW",
    "sg:tags":[
        "hairdresser"
    ],
    "wof:name":"Whetstone Hairdressing",
    "wof:placetype":"venue"
},
  "geometry": {"coordinates":[151.2918396,-33.7693023682],"type":"Point"}
}