{
  "type": "Feature",
  "properties": {
    "iso:country":"AU",
    "sg:address":"854 Lorimer St",
    "sg:city":"Port Melbourne",
    "sg:classifiers":[
        {
            "category":"Shopping",
            "subcategory":"Stationery & Office Supplies",
            "type":"Retail Goods"
        }
    ],
    "sg:phone":"+61 1300 362 345",
    "sg:postcode":"3207",
    "sg:province":"VIC",
    "sg:tags":[
        "equipment",
        "facsimile"
    ],
    "wof:name":"Lanier (Australia) Pty Ltd",
    "wof:placetype":"venue"
},
  "geometry": {"coordinates":[144.933243,-37.822292],"type":"Point"}
}