{
  "type": "Feature",
  "properties": {
    "iso:country":"AU",
    "sg:address":"30 Alexander Pde",
    "sg:city":"Clifton Hill",
    "sg:classifiers":[
        {
            "category":"Retail",
            "subcategory":"Auto Repair",
            "type":"Services"
        }
    ],
    "sg:phone":"+61 3 9482 3477",
    "sg:postcode":"3068",
    "sg:province":"VIC",
    "sg:tags":[
        "repairer",
        "motor",
        "engineer"
    ],
    "wof:name":"Gange A Pty Ltd",
    "wof:placetype":"venue"
},
  "geometry": {"coordinates":[144.98666381800001,-37.7937240601],"type":"Point"}
}