{
  "type": "Feature",
  "properties": {
    "addr:full":"62 Woodville Rd Woodville SA 5011",
    "addr:housenumber":"62",
    "addr:postcode":"5011",
    "addr:street":"Woodville Rd",
    "iso:country":"AU",
    "sg:address":"62 Woodville Rd",
    "sg:city":"Woodville",
    "sg:classifiers":[
        {
            "category":"Health Services",
            "subcategory":"Dentist",
            "type":"Services"
        }
    ],
    "sg:phone":"+61 8 8445 1246",
    "sg:postcode":"5011",
    "sg:province":"SA",
    "wof:name":"Mandranis George",
    "wof:placetype":"venue"
},
  "geometry": {"coordinates":[138.536453247,-34.8795700073],"type":"Point"}
}