{
  "type": "Feature",
  "properties": {
    "addr:full":"PO Box 4125 Alexander Heights WA 6064",
    "addr:postcode":"6064",
    "iso:country":"AU",
    "sg:address":"PO Box 4125",
    "sg:city":"Alexander Heights",
    "sg:classifiers":[
        {
            "category":"Banks & Credit Unions",
            "subcategory":"Bank",
            "type":"Services"
        }
    ],
    "sg:phone":"+61 8 9343 0722",
    "sg:postcode":"6064",
    "sg:province":"WA",
    "sg:tags":[
        "broker",
        "mortgage"
    ],
    "wof:name":"Mortgage Choice",
    "wof:placetype":"venue"
},
  "geometry": {"coordinates":[115.853439331,-31.8310508728],"type":"Point"}
}