{
  "type": "Feature",
  "properties": {
    "addr:full":"Shop 10 Panorama Plaza, Scenic Drv Tweed Heads West NSW 2485",
    "addr:housenumber":"shop 10",
    "addr:postcode":"2485",
    "addr:street":"Panorama Plaza Scenic Drv",
    "iso:country":"AU",
    "sg:address":"Shop 10 Panorama Plaza, Scenic Drv",
    "sg:city":"Tweed Heads West",
    "sg:classifiers":[
        {
            "category":"Personal",
            "subcategory":"Beauty Salon",
            "type":"Services"
        }
    ],
    "sg:phone":"+61 7 5599 9672",
    "sg:postcode":"2485",
    "sg:province":"NSW",
    "sg:tags":[
        "hairdresser"
    ],
    "wof:name":"Bella Hair Designs",
    "wof:placetype":"venue"
},
  "geometry": {"coordinates":[153.50115966800001,-28.1972560883],"type":"Point"}
}