{
  "type": "Feature",
  "properties": {
    "iso:country":"AU",
    "sg:address":"Shop 6 The Anchorage 10 Masthead Drv",
    "sg:city":"Raby Bay",
    "sg:classifiers":[
        {
            "category":"Personal",
            "subcategory":"Beauty Salon",
            "type":"Services"
        }
    ],
    "sg:phone":"+61 7 3286 6808",
    "sg:postcode":"4163",
    "sg:province":"QLD",
    "sg:tags":[
        "hairdresser"
    ],
    "wof:name":"Neilson Gilmour",
    "wof:placetype":"venue"
},
  "geometry": {"coordinates":[153.267410278,-27.5215396881],"type":"Point"}
}