{
  "type": "Feature",
  "properties": {
    "addr:full":"2/ 56 Beerburrum Rd Caboolture QLD 4510",
    "addr:housenumber":"/ 56",
    "addr:postcode":"4510",
    "addr:street":"Beerburrum Rd",
    "iso:country":"AU",
    "sg:address":"2/ 56 Beerburrum Rd",
    "sg:city":"Caboolture",
    "sg:classifiers":[
        {
            "category":"Building & Trades",
            "subcategory":"Locksmith",
            "type":"Services"
        }
    ],
    "sg:phone":"+61 7 5495 5000",
    "sg:postcode":"4510",
    "sg:province":"QLD",
    "sg:tags":[
        "lock"
    ],
    "wof:name":"Burpengary Lock & Safe Co.",
    "wof:placetype":"venue"
},
  "geometry": {"coordinates":[152.950424,-27.076624],"type":"Point"}
}