{
  "type": "Feature",
  "properties": {
    "addr:full":"195 Cormack Rd Wingfield SA 5013",
    "addr:housenumber":"195",
    "addr:postcode":"5013",
    "addr:street":"Cormack Rd",
    "iso:country":"AU",
    "sg:address":"195 Cormack Rd",
    "sg:city":"Wingfield",
    "sg:classifiers":[
        {
            "category":"Transit Center",
            "subcategory":"Freight",
            "type":"Transportation"
        }
    ],
    "sg:phone":"+61 8 8349 8699",
    "sg:postcode":"5013",
    "sg:province":"SA",
    "sg:tags":[
        "forklift",
        "truck"
    ],
    "wof:name":"Mitsubishi Forklift Trucks",
    "wof:placetype":"venue"
},
  "geometry": {"coordinates":[138.564208984,-34.8406677246],"type":"Point"}
}