{
  "type": "Feature",
  "properties": {
    "iso:country":"AU",
    "sg:address":"49 Stanley Drv",
    "sg:city":"Somerton",
    "sg:classifiers":[
        {
            "category":"Retail",
            "subcategory":"Auto Repair",
            "type":"Services"
        }
    ],
    "sg:phone":"+61 3 9305 3151",
    "sg:postcode":"3062",
    "sg:province":"VIC",
    "sg:tags":[
        "car",
        "restoration",
        "supply"
    ],
    "wof:name":"Jag E Type Restorations Pty Ltd",
    "wof:placetype":"venue"
},
  "geometry": {"coordinates":[144.94322204599999,-37.6280555725],"type":"Point"}
}