{
  "type": "Feature",
  "properties": {
    "iso:country":"AU",
    "sg:address":"52 Amberley Crs",
    "sg:city":"Dandenong",
    "sg:classifiers":[
        {
            "category":"Utilities",
            "type":"Services"
        }
    ],
    "sg:phone":"+61 1300 888 782",
    "sg:postcode":"3175",
    "sg:province":"VIC",
    "sg:tags":[
        "equipment",
        "towing"
    ],
    "wof:name":"Hayman Reese Prestige Towbars",
    "wof:placetype":"venue"
},
  "geometry": {"coordinates":[145.218215942,-37.9853210449],"type":"Point"}
}