{
  "type": "Feature",
  "properties": {
    "addr:full":"168 Taren Point Rd Taren Point NSW 2229",
    "addr:housenumber":"168",
    "addr:postcode":"2229",
    "addr:street":"Taren Point Rd",
    "iso:country":"AU",
    "sg:address":"168 Taren Point Rd",
    "sg:city":"Taren Point",
    "sg:classifiers":[
        {
            "category":"Manufacturing",
            "subcategory":"Glass & Minerals",
            "type":"Manufacturing & Wholesale Goods"
        }
    ],
    "sg:phone":"+61 2 9525 0006",
    "sg:postcode":"2229",
    "sg:province":"NSW",
    "sg:tags":[
        "repair",
        "fibreglass",
        "product"
    ],
    "wof:name":"Advance Moulding Aero",
    "wof:placetype":"venue"
},
  "geometry": {"coordinates":[151.12103271500001,-34.0246124268],"type":"Point"}
}