{
  "type": "Feature",
  "properties": {
    "addr:full":"70 Donohue St Kings Park NSW 2148",
    "addr:housenumber":"70",
    "addr:postcode":"2148",
    "addr:street":"Donohue St",
    "iso:country":"AU",
    "sg:address":"70 Donohue St",
    "sg:city":"Kings Park",
    "sg:classifiers":[
        {
            "category":"Home & Garden",
            "subcategory":"Carpets & Floor Coverings",
            "type":"Retail Goods"
        }
    ],
    "sg:phone":"+61 438 733 087",
    "sg:postcode":"2148",
    "sg:province":"NSW",
    "sg:tags":[
        "layer",
        "planner"
    ],
    "wof:name":"A1 Shane's Carpet Laying Service",
    "wof:placetype":"venue"
},
  "geometry": {"coordinates":[150.901443481,-33.7371253967],"type":"Point"}
}