{
  "type": "Feature",
  "properties": {
    "addr:full":"318 Rowe St Eastwood NSW 2122",
    "addr:housenumber":"318",
    "addr:postcode":"2122",
    "addr:street":"Rowe St",
    "iso:country":"AU",
    "sg:address":"318 Rowe St",
    "sg:city":"Eastwood",
    "sg:classifiers":[
        {
            "category":"Manufacturing",
            "subcategory":"Glass & Minerals",
            "type":"Manufacturing & Wholesale Goods"
        }
    ],
    "sg:phone":"+61 2 9858 4136",
    "sg:postcode":"2122",
    "sg:province":"NSW",
    "sg:tags":[
        "stained"
    ],
    "wof:name":"Eastwood Stained Glass & Leadlight Repairs",
    "wof:placetype":"venue"
},
  "geometry": {"coordinates":[151.07267761200001,-33.7928466797],"type":"Point"}
}