{
  "type": "Feature",
  "properties": {
    "addr:full":"27 Edmondson St Corinda QLD 4075",
    "addr:housenumber":"27",
    "addr:postcode":"4075",
    "addr:street":"Edmondson St",
    "iso:country":"AU",
    "sg:address":"27 Edmondson St",
    "sg:city":"Corinda",
    "sg:classifiers":[
        {
            "category":"Organizations",
            "subcategory":"Membership Organization",
            "type":"Services"
        }
    ],
    "sg:phone":"+61 7 3278 0249",
    "sg:postcode":"4075",
    "sg:province":"QLD",
    "sg:tags":[
        "support",
        "health",
        "organisation"
    ],
    "wof:name":"e Health Care Solutions",
    "wof:placetype":"venue"
},
  "geometry": {"coordinates":[152.98840332,-27.5486450195],"type":"Point"}
}