{
  "type": "Feature",
  "properties": {
    "iso:country":"AU",
    "sg:address":"Shop 382",
    "sg:city":"Kawana Shoppingworld Buddina",
    "sg:classifiers":[
        {
            "category":"Shopping",
            "subcategory":"Gifts & Souvenirs",
            "type":"Retail Goods"
        }
    ],
    "sg:phone":"+61 7 5444 5066",
    "sg:postcode":"4575",
    "sg:province":"QLD",
    "sg:tags":[
        "print",
        "poster",
        "pictures"
    ],
    "wof:name":"Picture Us Kawana",
    "wof:placetype":"venue"
},
  "geometry": {"coordinates":[153.129639,-26.700609],"type":"Point"}
}