{
  "type": "Feature",
  "properties": {
    "addr:full":"Wilfred St Narembeen WA 6369",
    "addr:postcode":"6369",
    "addr:street":"Wilfred St",
    "iso:country":"AU",
    "sg:address":"Wilfred St",
    "sg:city":"Narembeen",
    "sg:classifiers":[
        {
            "category":"Shopping",
            "type":"Retail Goods"
        }
    ],
    "sg:phone":"+61 8 9064 7201",
    "sg:postcode":"6369",
    "sg:province":"WA",
    "sg:tags":[
        "agent",
        "stock"
    ],
    "wof:name":"O&#039;Neill Agencies Narembeen",
    "wof:placetype":"venue"
},
  "geometry": {"coordinates":[118.395409,-32.064014],"type":"Point"}
}