{
  "type": "Feature",
  "properties": {
    "addr:full":"U5/ 1-3 Carnegie Pl Blacktown NSW 2148",
    "addr:housenumber":"1-3",
    "addr:postcode":"2148",
    "addr:street":"U5 /;Pl",
    "iso:country":"AU",
    "sg:address":"U5/ 1-3 Carnegie Pl",
    "sg:city":"Blacktown",
    "sg:classifiers":[
        {
            "category":"Banks & Credit Unions",
            "subcategory":"Investment Brokerage",
            "type":"Services"
        }
    ],
    "sg:phone":"+61 2 9671 4855",
    "sg:postcode":"2148",
    "sg:province":"NSW",
    "sg:tags":[
        "paint",
        "supply",
        "removal"
    ],
    "wof:name":"Graffiti Off Australia Pty Ltd",
    "wof:placetype":"venue"
},
  "geometry": {"coordinates":[150.90618896500001,-33.7542877197],"type":"Point"}
}