{
  "type": "Feature",
  "properties": {
    "addr:full":"3 Rush Crt Collingwood Park QLD 4301",
    "addr:housenumber":"3",
    "addr:postcode":"4301",
    "addr:street":"Rush Crt",
    "iso:country":"AU",
    "sg:address":"3 Rush Crt",
    "sg:city":"Collingwood Park",
    "sg:classifiers":[
        {
            "category":"Building & Trades",
            "subcategory":"Construction",
            "type":"Services"
        }
    ],
    "sg:phone":"+61 412 983 120",
    "sg:postcode":"4301",
    "sg:province":"QLD",
    "sg:tags":[
        "concrete",
        "contractor"
    ],
    "wof:name":"Keltess Concrete",
    "wof:placetype":"venue"
},
  "geometry": {"coordinates":[152.867797852,-27.6139812469],"type":"Point"}
}