{
  "type": "Feature",
  "properties": {
    "iso:country":"AU",
    "sg:address":"390 Princes Hwy",
    "sg:city":"Rockdale",
    "sg:classifiers":[
        {
            "category":"Shopping",
            "subcategory":"Discount & Variety Stores",
            "type":"Retail Goods"
        }
    ],
    "sg:phone":"+61 2 9556 3566",
    "sg:postcode":"2216",
    "sg:province":"NSW",
    "sg:tags":[
        "register",
        "cash"
    ],
    "wof:name":"Bepoz",
    "wof:placetype":"venue"
},
  "geometry": {"coordinates":[151.139816,-33.94886],"type":"Point"}
}