{
  "type": "Feature",
  "properties": {
    "addr:full":"10th Floor, 111 St Georges Tce Perth WA 6000",
    "addr:housenumber":"111",
    "addr:postcode":"6000",
    "addr:street":"St Georges Tce",
    "iso:country":"AU",
    "sg:address":"10th Floor, 111 St",
    "sg:city":"Georges Tce Perth",
    "sg:classifiers":[
        {
            "category":"Banks & Credit Unions",
            "subcategory":"Financial Services",
            "type":"Services"
        }
    ],
    "sg:phone":"+61 1300 303 086",
    "sg:postcode":"6000",
    "sg:province":"WA",
    "sg:tags":[
        "planning"
    ],
    "wof:name":"AXA Financial Planning",
    "wof:placetype":"venue"
},
  "geometry": {"coordinates":[115.856330872,-31.9547386169],"type":"Point"}
}