{
  "type": "Feature",
  "properties": {
    "addr:full":"PO Box 5171 Mackay Mail Centre QLD 4741",
    "addr:postcode":"4741",
    "iso:country":"AU",
    "sg:address":"PO Box 5171",
    "sg:city":"Mackay Mail Centre",
    "sg:classifiers":[
        {
            "category":"Autos & Motor Vehicles",
            "subcategory":"Auto Supplies",
            "type":"Retail Goods"
        }
    ],
    "sg:phone":"+61 7 4952 1822",
    "sg:postcode":"4741",
    "sg:province":"QLD",
    "sg:tags":[
        "tyre"
    ],
    "wof:name":"Meng Tyre Sales",
    "wof:placetype":"venue"
},
  "geometry": {"coordinates":[148.339584,-21.01993],"type":"Point"}
}