{
  "type": "Feature",
  "properties": {
    "iso:country":"AU",
    "sg:address":"42 Mort St",
    "sg:city":"Balmain",
    "sg:classifiers":[
        {
            "category":"Shopping",
            "subcategory":"Antiques",
            "type":"Retail Goods"
        }
    ],
    "sg:phone":"+61 2 9818 3557",
    "sg:postcode":"2041",
    "sg:province":"NSW",
    "sg:tags":[
        "restoration",
        "reproduction"
    ],
    "wof:name":"The Hardwood & Pine Restoration Co.",
    "wof:placetype":"venue"
},
  "geometry": {"coordinates":[151.182114,-33.855827],"type":"Point"}
}