{
  "type": "Feature",
  "properties": {
    "addr:full":"RSD 537/ Mail Rd Harrogate SA 5244",
    "addr:housenumber":"537 /",
    "addr:postcode":"5244",
    "addr:street":"Mail Rd",
    "iso:country":"AU",
    "sg:address":"RSD 537/ Mail Rd",
    "sg:city":"Harrogate",
    "sg:classifiers":[
        {
            "category":"Real Estate",
            "subcategory":"Surveying",
            "type":"Services"
        }
    ],
    "sg:phone":"+61 8 8538 7000",
    "sg:postcode":"5244",
    "sg:province":"SA",
    "sg:tags":[
        "geophysicist"
    ],
    "wof:name":"Ecophyte Technologies Pty Ltd",
    "wof:placetype":"venue"
},
  "geometry": {"coordinates":[139.01119995100001,-34.9501609802],"type":"Point"}
}