{
  "type": "Feature",
  "properties": {
    "iso:country":"AU",
    "sg:address":"Whitecross Rd",
    "sg:city":"Winmalee",
    "sg:classifiers":[
        {
            "category":"Education",
            "subcategory":"Kindergarten",
            "type":"Public Place"
        }
    ],
    "sg:phone":"+61 2 4754 1737",
    "sg:postcode":"2777",
    "sg:province":"NSW",
    "sg:tags":[
        "pre-schools"
    ],
    "wof:name":"Winmalee & District Pre-School Kindergarten",
    "wof:placetype":"venue"
},
  "geometry": {"coordinates":[150.60940551799999,-33.6720542908],"type":"Point"}
}