{
  "type": "Feature",
  "properties": {
    "iso:country":"AU",
    "sg:address":"Shop 38, Narellan Town Cntr",
    "sg:city":"Narellan",
    "sg:classifiers":[
        {
            "category":"Personal",
            "subcategory":"Tanning Parlor",
            "type":"Services"
        }
    ],
    "sg:phone":"+61 2 4646 1832",
    "sg:postcode":"2567",
    "sg:province":"NSW",
    "sg:tags":[
        "solarium"
    ],
    "wof:name":"The Beauty Base",
    "wof:placetype":"venue"
},
  "geometry": {"coordinates":[150.779296875,-34.0582962036],"type":"Point"}
}