{
  "type": "Feature",
  "properties": {
    "addr:full":"342 Mary St Richmond VIC 3121",
    "addr:housenumber":"342",
    "addr:postcode":"3121",
    "addr:street":"Mary St",
    "iso:country":"AU",
    "sg:address":"342 Mary St",
    "sg:city":"Richmond",
    "sg:classifiers":[
        {
            "category":"Real Estate",
            "subcategory":"Real Estate Services",
            "type":"Services"
        }
    ],
    "sg:phone":"+61 3 9421 0876",
    "sg:postcode":"3121",
    "sg:province":"VIC",
    "sg:tags":[
        "consultant",
        "property"
    ],
    "wof:name":"Christine Hayes",
    "wof:placetype":"venue"
},
  "geometry": {"coordinates":[144.999710083,-37.8329048157],"type":"Point"}
}