{
  "type": "Feature",
  "properties": {
    "iso:country":"AU",
    "sg:address":"8 Jubilee Ave",
    "sg:city":"Brighton",
    "sg:classifiers":[
        {
            "category":"Building & Trades",
            "subcategory":"Cleaning & Sanitation",
            "type":"Services"
        }
    ],
    "sg:phone":"+61 407 124 890",
    "sg:postcode":"7030",
    "sg:province":"TAS",
    "sg:tags":[
        "cleaner",
        "repairer",
        "roof"
    ],
    "wof:name":"Mawhood M & W J",
    "wof:placetype":"venue"
},
  "geometry": {"coordinates":[147.26116943400001,-42.6966362],"type":"Point"}
}