{
  "type": "Feature",
  "properties": {
    "iso:country":"AU",
    "sg:address":"62 Kularoo Drv",
    "sg:city":"Forster",
    "sg:classifiers":[
        {
            "category":"Home & Garden",
            "subcategory":"Building Materials",
            "type":"Retail Goods"
        }
    ],
    "sg:phone":"+61 2 6555 5188",
    "sg:postcode":"2428",
    "sg:province":"NSW",
    "sg:tags":[
        "plaster",
        "plasterboard",
        "supply"
    ],
    "wof:name":"Forster Plastamasta Centre",
    "wof:placetype":"venue"
},
  "geometry": {"coordinates":[152.521469,-32.19746],"type":"Point"}
}