{
  "type": "Feature",
  "properties": {
    "iso:country":"AU",
    "sg:address":"17 Carlton Rd",
    "sg:city":"North Rocks",
    "sg:classifiers":[
        {
            "category":"Building & Trades",
            "subcategory":"Construction",
            "type":"Services"
        }
    ],
    "sg:phone":"+61 2 9872 5531",
    "sg:postcode":"2151",
    "sg:province":"NSW",
    "sg:tags":[
        "contractor"
    ],
    "wof:name":"Biltbeta Construction Pty Ltd",
    "wof:placetype":"venue"
},
  "geometry": {"coordinates":[151.01791381800001,-33.7642478943],"type":"Point"}
}