{
  "type": "Feature",
  "properties": {
    "addr:full":"10 Lombank St Archerfield QLD 4108",
    "addr:housenumber":"10",
    "addr:postcode":"4108",
    "addr:street":"Lombank St",
    "iso:country":"AU",
    "sg:address":"10 Lombank St",
    "sg:city":"Archerfield",
    "sg:classifiers":[
        {
            "category":"Autos & Motor Vehicles",
            "subcategory":"Boat Sales",
            "type":"Retail Goods"
        }
    ],
    "sg:phone":"+61 7 3274 6969",
    "sg:postcode":"4108",
    "sg:province":"QLD",
    "sg:tags":[
        "equipment",
        "yacht"
    ],
    "wof:name":"Boat Trailer Spares",
    "wof:placetype":"venue"
},
  "geometry": {"coordinates":[153.00733947800001,-27.5778656006],"type":"Point"}
}