{
  "type": "Feature",
  "properties": {
    "iso:country":"AU",
    "sg:address":"150 Eagle St",
    "sg:city":"Longreach",
    "sg:classifiers":[
        {
            "category":"Health Services",
            "subcategory":"Doctor",
            "type":"Services"
        }
    ],
    "sg:phone":"+61 7 4658 3156",
    "sg:postcode":"4730",
    "sg:province":"QLD",
    "sg:tags":[
        "nurse",
        "nursing"
    ],
    "wof:name":"Spiritus Care Services",
    "wof:placetype":"venue"
},
  "geometry": {"coordinates":[144.246429,-23.445333],"type":"Point"}
}