{
  "type": "Feature",
  "properties": {
    "addr:full":"U3/ 3-11 Brodie St Rydalmere NSW 2116",
    "addr:housenumber":"3-11",
    "addr:postcode":"2116",
    "addr:street":"U3 /;Brodie St",
    "iso:country":"AU",
    "sg:address":"U3/ 3-11 Brodie St",
    "sg:city":"Rydalmere",
    "sg:classifiers":[
        {
            "category":"Fast Food",
            "type":"Food & Drink"
        }
    ],
    "sg:phone":"+61 2 9638 4525",
    "sg:postcode":"2116",
    "sg:province":"NSW",
    "sg:tags":[
        "away",
        "take"
    ],
    "wof:name":"Angys Gourmet",
    "wof:placetype":"venue"
},
  "geometry": {"coordinates":[151.021286011,-33.9012489319],"type":"Point"}
}