{
  "type": "Feature",
  "properties": {
    "iso:country":"AU",
    "sg:address":"11 Hodgkinson St",
    "sg:city":"Charters Towers",
    "sg:classifiers":[
        {
            "category":"Organizations",
            "subcategory":"Membership Organization",
            "type":"Services"
        }
    ],
    "sg:phone":"+61 7 4787 4286",
    "sg:postcode":"4820",
    "sg:province":"QLD",
    "sg:tags":[
        "support",
        "health",
        "organisation"
    ],
    "wof:name":"60 & Better Program",
    "wof:placetype":"venue"
},
  "geometry": {"coordinates":[146.259033,-20.077332],"type":"Point"}
}