{
  "type": "Feature",
  "properties": {
    "addr:full":"PO Box 97 Stroud NSW 2425",
    "addr:postcode":"2425",
    "iso:country":"AU",
    "sg:address":"PO Box 97",
    "sg:city":"Stroud",
    "sg:classifiers":[
        {
            "category":"Professional",
            "type":"Services"
        }
    ],
    "sg:phone":"+61 414 475 415",
    "sg:postcode":"2425",
    "sg:province":"NSW",
    "sg:tags":[
        "transport"
    ],
    "wof:name":"Stroud General Carriers",
    "wof:placetype":"venue"
},
  "geometry": {"coordinates":[151.96794128400001,-32.404548645],"type":"Point"}
}