{
  "type": "Feature",
  "properties": {
    "addr:full":"2 Charles Ave Minnamurra NSW 2533",
    "addr:housenumber":"2",
    "addr:postcode":"2533",
    "addr:street":"Charles Ave",
    "iso:country":"AU",
    "sg:address":"2 Charles Ave",
    "sg:city":"Minnamurra",
    "sg:classifiers":[
        {
            "category":"Home & Garden",
            "subcategory":"Carpets & Floor Coverings",
            "type":"Retail Goods"
        }
    ],
    "sg:phone":"+61 418 254 078",
    "sg:postcode":"2533",
    "sg:province":"NSW",
    "sg:tags":[
        "tile",
        "wall",
        "layer"
    ],
    "wof:name":"Peter Nevins Wall & Floor Tiling",
    "wof:placetype":"venue"
},
  "geometry": {"coordinates":[150.85618591299999,-34.6300697327],"type":"Point"}
}