{
  "type": "Feature",
  "properties": {
    "addr:full":"Unit 2, 30- 34 Maffra St Coolaroo VIC 3048",
    "addr:housenumber":"30 34",
    "addr:postcode":"3048",
    "addr:street":"St",
    "iso:country":"AU",
    "sg:address":"Unit 2, 30- 34 Maffra St",
    "sg:city":"Coolaroo",
    "sg:classifiers":[
        {
            "category":"Home & Garden",
            "subcategory":"Home Furnishings",
            "type":"Retail Goods"
        }
    ],
    "sg:phone":"+61 3 9302 4100",
    "sg:postcode":"3048",
    "sg:province":"VIC",
    "sg:tags":[
        "shower",
        "screen"
    ],
    "wof:name":"Sunset Aluminium",
    "wof:placetype":"venue"
},
  "geometry": {"coordinates":[144.942307,-37.663536],"type":"Point"}
}