{
  "type": "Feature",
  "properties": {
    "iso:country":"AU",
    "sg:address":"27 Sunningdale Ave",
    "sg:city":"Rochedale South",
    "sg:classifiers":[
        {
            "category":"Utilities",
            "subcategory":"Refuse",
            "type":"Services"
        }
    ],
    "sg:phone":"+61 7 3341 7710",
    "sg:postcode":"4123",
    "sg:province":"QLD",
    "sg:tags":[
        "remover",
        "rubbish"
    ],
    "wof:name":"Big Garden Sacks",
    "wof:placetype":"venue"
},
  "geometry": {"coordinates":[153.12408447300001,-27.5989017487],"type":"Point"}
}