{
  "type": "Feature",
  "properties": {
    "iso:country":"AU",
    "sg:address":"143 Ryrie St",
    "sg:city":"Geelong",
    "sg:classifiers":[
        {
            "category":"Shopping",
            "type":"Retail Goods"
        }
    ],
    "sg:phone":"+61 3 5229 2643",
    "sg:postcode":"3220",
    "sg:province":"VIC",
    "sg:tags":[
        "repair",
        "travel"
    ],
    "wof:name":"Sweeneys Travel Goods",
    "wof:placetype":"venue"
},
  "geometry": {"coordinates":[144.359589,-38.149033],"type":"Point"}
}