{
  "type": "Feature",
  "properties": {
    "addr:full":"Shop 1, 215 Pitt St Merrylands NSW 2160",
    "addr:housenumber":"shop 1 215",
    "addr:postcode":"2160",
    "addr:street":"Pitt St",
    "iso:country":"AU",
    "sg:address":"Shop 1, 215 Pitt St",
    "sg:city":"Merrylands",
    "sg:classifiers":[
        {
            "category":"Banks & Credit Unions",
            "subcategory":"Financial Services",
            "type":"Services"
        }
    ],
    "sg:phone":"+61 2 9637 2811",
    "sg:postcode":"2160",
    "sg:province":"NSW",
    "sg:tags":[
        "loan",
        "finance",
        "mortgage"
    ],
    "wof:name":"RAMS Home Loans",
    "wof:placetype":"venue"
},
  "geometry": {"coordinates":[150.99177551299999,-33.8346366882],"type":"Point"}
}