{
  "type": "Feature",
  "properties": {
    "iso:country":"AU",
    "sg:address":"Unit 10, 117 Albert St",
    "sg:city":"Footscray",
    "sg:classifiers":[
        {
            "category":"Building & Trades",
            "subcategory":"Construction",
            "type":"Services"
        }
    ],
    "sg:phone":"+61 438 233 132",
    "sg:postcode":"3011",
    "sg:province":"VIC",
    "sg:tags":[
        "polishing",
        "sanding",
        "floor"
    ],
    "wof:name":"AST Floors",
    "wof:placetype":"venue"
},
  "geometry": {"coordinates":[144.89710998499999,-37.806552887],"type":"Point"}
}