{
  "type": "Feature",
  "properties": {
    "addr:full":"29 Broome St Katanning WA 6317",
    "addr:housenumber":"29",
    "addr:postcode":"6317",
    "addr:street":"Broome St",
    "iso:country":"AU",
    "sg:address":"29 Broome St",
    "sg:city":"Katanning",
    "sg:classifiers":[
        {
            "category":"Farming",
            "subcategory":"Farm & Veterinary Services",
            "type":"Manufacturing & Wholesale Goods"
        }
    ],
    "sg:phone":"+61 8 9821 2225",
    "sg:postcode":"6317",
    "sg:province":"WA",
    "sg:tags":[
        "shearing",
        "contractor"
    ],
    "wof:name":"Willey Gavin & Kay",
    "wof:placetype":"venue"
},
  "geometry": {"coordinates":[117.555480957,-33.695148468],"type":"Point"}
}