{
  "type": "Feature",
  "properties": {
    "addr:full":"PO Box 132 Toowoomba QLD 4350",
    "addr:postcode":"4350",
    "iso:country":"AU",
    "sg:address":"PO Box 132",
    "sg:city":"Toowoomba",
    "sg:classifiers":[
        {
            "category":"Arena",
            "subcategory":"Sports Club",
            "type":"Entertainment"
        }
    ],
    "sg:phone":"+61 434 012 733",
    "sg:postcode":"4350",
    "sg:province":"QLD",
    "sg:tags":[
        "australian",
        "football",
        "rule"
    ],
    "wof:name":"Toowoomba Tigers Australian Rules Football Club Inc.",
    "wof:placetype":"venue"
},
  "geometry": {"coordinates":[151.875641,-27.55761],"type":"Point"}
}