{
  "type": "Feature",
  "properties": {
    "addr:full":"53 Toongabbie Rd Toongabbie NSW 2146",
    "addr:housenumber":"53",
    "addr:postcode":"2146",
    "addr:street":"Toongabbie Rd",
    "iso:country":"AU",
    "sg:address":"53 Toongabbie Rd",
    "sg:city":"Toongabbie",
    "sg:classifiers":[
        {
            "category":"Building & Trades",
            "subcategory":"Construction",
            "type":"Services"
        }
    ],
    "sg:phone":"+61 2 9897 1620",
    "sg:postcode":"2146",
    "sg:province":"NSW",
    "sg:tags":[
        "plasterboard",
        "plasterer",
        "fixer"
    ],
    "wof:name":"Plaster People The",
    "wof:placetype":"venue"
},
  "geometry": {"coordinates":[150.946136475,-33.7918357849],"type":"Point"}
}