{
  "type": "Feature",
  "properties": {
    "addr:full":"14 Charles Canty Drv Wellington Point QLD 4160",
    "addr:housenumber":"14",
    "addr:postcode":"4160",
    "addr:street":"Charles Canty Drv",
    "iso:country":"AU",
    "sg:address":"14 Charles Canty Drv",
    "sg:city":"Wellington Point",
    "sg:classifiers":[
        {
            "category":"Building & Trades",
            "subcategory":"Construction",
            "type":"Services"
        }
    ],
    "sg:phone":"+61 7 3207 1539",
    "sg:postcode":"4160",
    "sg:province":"QLD",
    "sg:tags":[
        "concrete",
        "contractor"
    ],
    "wof:name":"Creative Concrete Constructions Pty Ltd",
    "wof:placetype":"venue"
},
  "geometry": {"coordinates":[153.24273681599999,-27.5110301971],"type":"Point"}
}