{
  "type": "Feature",
  "properties": {
    "iso:country":"AU",
    "sg:address":"113 Banksia Ave",
    "sg:city":"Engadine",
    "sg:classifiers":[
        {
            "category":"Social Services",
            "subcategory":"Child Care",
            "type":"Services"
        }
    ],
    "sg:phone":"+61 400 853 333",
    "sg:postcode":"2233",
    "sg:province":"NSW",
    "wof:name":"Top Kidz III Preschool & LDCCC",
    "wof:placetype":"venue"
},
  "geometry": {"coordinates":[151.00924682600001,-34.0671691895],"type":"Point"}
}