{
  "type": "Feature",
  "properties": {
    "addr:full":"12A Acacia St Yarrawonga VIC 3730",
    "addr:housenumber":"12a",
    "addr:postcode":"3730",
    "addr:street":"Acacia St",
    "iso:country":"AU",
    "sg:address":"12A Acacia St",
    "sg:city":"Yarrawonga",
    "sg:classifiers":[
        {
            "category":"Farming",
            "subcategory":"Farm & Veterinary Services",
            "type":"Manufacturing & Wholesale Goods"
        }
    ],
    "sg:phone":"+61 3 5743 1900",
    "sg:postcode":"3730",
    "sg:province":"VIC",
    "sg:tags":[
        "agricultural",
        "advisory"
    ],
    "wof:name":"Murray Valley Rural Services",
    "wof:placetype":"venue"
},
  "geometry": {"coordinates":[145.99864196799999,-36.0283622742],"type":"Point"}
}