{
  "type": "Feature",
  "properties": {
    "iso:country":"AU",
    "sg:address":"3 Wayne St",
    "sg:city":"Stafford Heights",
    "sg:classifiers":[
        {
            "category":"Social Services",
            "subcategory":"Child Care",
            "type":"Services"
        }
    ],
    "sg:phone":"+61 7 3311 7743",
    "sg:postcode":"4053",
    "sg:province":"QLD",
    "wof:name":"Tumble Tots Private Day Care",
    "wof:placetype":"venue"
},
  "geometry": {"coordinates":[153.00401306099999,-27.3970394135],"type":"Point"}
}