{
  "type": "Feature",
  "properties": {
    "addr:full":"Anketell St Tuggeranong ACT 2900",
    "addr:postcode":"2900",
    "addr:street":"Anketell St",
    "iso:country":"AU",
    "sg:address":"Anketell St",
    "sg:city":"Tuggeranong",
    "sg:classifiers":[
        {
            "category":"Sports & Exercise",
            "subcategory":"Gym",
            "type":"Entertainment"
        }
    ],
    "sg:phone":"+61 2 6293 3122",
    "sg:postcode":"2900",
    "sg:province":"ACT",
    "sg:tags":[
        "health",
        "fitness"
    ],
    "wof:name":"Lakeside Leisure Centre",
    "wof:placetype":"venue"
},
  "geometry": {"coordinates":[149.06768798799999,-35.4157333374],"type":"Point"}
}