{
  "type": "Feature",
  "properties": {
    "addr:full":"Shop 9 / 95 Waterfield St Coburg VIC 3058",
    "addr:housenumber":"shop 9 / 95",
    "addr:postcode":"3058",
    "addr:street":"Waterfield St",
    "iso:country":"AU",
    "sg:address":"Shop 9 / 95 Waterfield St",
    "sg:city":"Coburg",
    "sg:classifiers":[
        {
            "category":"Wholesale",
            "subcategory":"Medical Equipment & Supplies",
            "type":"Manufacturing & Wholesale Goods"
        }
    ],
    "sg:phone":"+61 3 9350 6200",
    "sg:postcode":"3058",
    "sg:province":"VIC",
    "sg:tags":[
        "aids",
        "hearing"
    ],
    "wof:name":"Hearing Life",
    "wof:placetype":"venue"
},
  "geometry": {"coordinates":[144.96514892600001,-37.7421340942],"type":"Point"}
}