{
  "type": "Feature",
  "properties": {
    "iso:country":"AU",
    "sg:address":"20 Waterloo St",
    "sg:city":"Narrabeen",
    "sg:classifiers":[
        {
            "category":"Real Estate",
            "subcategory":"Real Estate Agent",
            "type":"Services"
        }
    ],
    "sg:phone":"+61 2 9913 3733",
    "sg:postcode":"2101",
    "sg:province":"NSW",
    "wof:name":"Drake Real Estate",
    "wof:placetype":"venue"
},
  "geometry": {"coordinates":[151.298157,-33.71315],"type":"Point"}
}