{
  "type": "Feature",
  "properties": {
    "addr:full":"31 Fernhill Ave Epping NSW 2121",
    "addr:housenumber":"31",
    "addr:postcode":"2121",
    "addr:street":"Fernhill Ave",
    "iso:country":"AU",
    "sg:address":"31 Fernhill Ave",
    "sg:city":"Epping",
    "sg:classifiers":[
        {
            "category":"Farming",
            "subcategory":"Fish & Marine Products",
            "type":"Manufacturing & Wholesale Goods"
        }
    ],
    "sg:phone":"+61 2 9868 3895",
    "sg:postcode":"2121",
    "sg:province":"NSW",
    "sg:tags":[
        "chemical",
        "supplier"
    ],
    "wof:name":"Aristech Chemicals",
    "wof:placetype":"venue"
},
  "geometry": {"coordinates":[151.07565307600001,-33.76720047],"type":"Point"}
}