{
  "type": "Feature",
  "properties": {
    "addr:full":"Princes Hwy Wurruk VIC 3850",
    "addr:postcode":"3850",
    "addr:street":"Princes Hwy",
    "iso:country":"AU",
    "sg:address":"Princes Hwy",
    "sg:city":"Wurruk",
    "sg:classifiers":[
        {
            "category":"Autos & Motor Vehicles",
            "subcategory":"Automobile Sales",
            "type":"Retail Goods"
        }
    ],
    "sg:phone":"+61 3 5144 1311",
    "sg:postcode":"3850",
    "sg:province":"VIC",
    "sg:tags":[
        "car",
        "used"
    ],
    "wof:name":"Causeway Car Sales",
    "wof:placetype":"venue"
},
  "geometry": {"coordinates":[147.02606201200001,-38.1040763855],"type":"Point"}
}