{
  "type": "Feature",
  "properties": {
    "iso:country":"AU",
    "sg:address":"1st FloorSuunybank Corporate 6/18 Torbey St",
    "sg:city":"Sunnybank Hills",
    "sg:classifiers":[
        {
            "category":"Professional",
            "subcategory":"Accounting & Tax Preparation",
            "type":"Services"
        }
    ],
    "sg:phone":"+61 7 3323 1704",
    "sg:postcode":"4109",
    "sg:province":"QLD",
    "sg:tags":[
        "accountant",
        "auditor"
    ],
    "wof:name":"Romar Associates Pty Ltd",
    "wof:placetype":"venue"
},
  "geometry": {"coordinates":[153.05825805699999,-27.5870456696],"type":"Point"}
}