{
  "type": "Feature",
  "properties": {
    "iso:country":"AU",
    "sg:address":"Shp 5/ 155 West Tamar Rd",
    "sg:city":"Trevallyn",
    "sg:classifiers":[
        {
            "category":"Fast Food",
            "type":"Food & Drink"
        }
    ],
    "sg:phone":"+61 3 6327 3225",
    "sg:postcode":"7250",
    "sg:province":"TAS",
    "sg:tags":[
        "away",
        "take"
    ],
    "wof:name":"Kero's Fish Shop",
    "wof:placetype":"venue"
},
  "geometry": {"coordinates":[147.11293029800001,-41.4245376587],"type":"Point"}
}