{
  "type": "Feature",
  "properties": {
    "iso:country":"AU",
    "sg:address":"58-59 Bayside Plaza 376 Bay St",
    "sg:city":"Brighton-le-Sands",
    "sg:classifiers":[
        {
            "category":"Building & Trades",
            "subcategory":"Construction",
            "type":"Services"
        }
    ],
    "sg:phone":"+61 2 9556 3555",
    "sg:postcode":"2216",
    "sg:province":"NSW",
    "sg:tags":[
        "contractor"
    ],
    "wof:name":"Coenco Pty Ltd",
    "wof:placetype":"venue"
},
  "geometry": {"coordinates":[151.156128,-33.960987],"type":"Point"}
}