{
  "type": "Feature",
  "properties": {
    "addr:full":"54 Northumberland Rd Auburn NSW 2144",
    "addr:housenumber":"54",
    "addr:postcode":"2144",
    "addr:street":"Northumberland Rd",
    "iso:country":"AU",
    "sg:address":"54 Northumberland Rd",
    "sg:city":"Auburn",
    "sg:classifiers":[
        {
            "category":"Health Services",
            "subcategory":"Nursing And Care Facility",
            "type":"Services"
        }
    ],
    "sg:phone":"+61 2 9649 7746",
    "sg:postcode":"2144",
    "sg:province":"NSW",
    "sg:tags":[
        "home"
    ],
    "wof:name":"Glen Lynn Nursing Home",
    "wof:placetype":"venue"
},
  "geometry": {"coordinates":[151.03565979000001,-33.8460426331],"type":"Point"}
}