{
  "type": "Feature",
  "properties": {
    "iso:country":"AU",
    "sg:address":"5 Kramer Drv",
    "sg:city":"Berwick",
    "sg:classifiers":[
        {
            "category":"Retail",
            "subcategory":"Driving School",
            "type":"Services"
        }
    ],
    "sg:phone":"+61 3 9707 4719",
    "sg:postcode":"3806",
    "sg:province":"VIC",
    "wof:name":"Kelbrey School Of Motoring",
    "wof:placetype":"venue"
},
  "geometry": {"coordinates":[145.34718322800001,-38.0272598267],"type":"Point"}
}