{
  "type": "Feature",
  "properties": {
    "iso:country":"AU",
    "sg:address":"Level 1, 7 Lydiard St (South)",
    "sg:city":"Ballarat",
    "sg:classifiers":[
        {
            "category":"Banks & Credit Unions",
            "subcategory":"Financial Services",
            "type":"Services"
        }
    ],
    "sg:phone":"+61 3 5331 5077",
    "sg:postcode":"3350",
    "sg:province":"VIC",
    "sg:tags":[
        "planning"
    ],
    "wof:name":"Terry McGuane Financial Services",
    "wof:placetype":"venue"
},
  "geometry": {"coordinates":[143.857834,-37.562401],"type":"Point"}
}