{
  "type": "Feature",
  "properties": {
    "iso:country":"AU",
    "sg:address":"2 Nylander St",
    "sg:city":"Darwin",
    "sg:classifiers":[
        {
            "category":"Organizations",
            "subcategory":"Professional Association",
            "type":"Services"
        }
    ],
    "sg:phone":"+61 8 8941 3177",
    "sg:postcode":"0800",
    "sg:province":"NT",
    "sg:tags":[
        "organisation",
        "business"
    ],
    "wof:name":"Australian Trucking Association N.T.",
    "wof:placetype":"venue"
},
  "geometry": {"coordinates":[130.840896606,-12.4394207001],"type":"Point"}
}