{
  "type": "Feature",
  "properties": {
    "iso:country":"AU",
    "sg:address":"26 Victoria Rd",
    "sg:city":"Pennant Hills",
    "sg:classifiers":[
        {
            "category":"Building & Trades",
            "subcategory":"Construction",
            "type":"Services"
        }
    ],
    "sg:phone":"+61 2 9481 7273",
    "sg:postcode":"2120",
    "sg:province":"NSW",
    "sg:tags":[
        "polishing",
        "sanding",
        "floor"
    ],
    "wof:name":"Alto Floor Sanding",
    "wof:placetype":"venue"
},
  "geometry": {"coordinates":[151.06028747600001,-33.7377510071],"type":"Point"}
}