{
  "type": "Feature",
  "properties": {
    "addr:full":"Unit 1/ 22 Enterprise Ave Tweed Heads South QLD 2486",
    "addr:housenumber":"22",
    "addr:postcode":"2486",
    "addr:street":"Enterprise Ave",
    "iso:country":"AU",
    "sg:address":"Unit 1/ 22 Enterprise Ave",
    "sg:city":"Tweed Heads South",
    "sg:classifiers":[
        {
            "category":"Wholesale",
            "subcategory":"Electrical",
            "type":"Manufacturing & Wholesale Goods"
        }
    ],
    "sg:phone":"+61 7 5523 0455",
    "sg:postcode":"2486",
    "sg:province":"QLD",
    "sg:tags":[
        "wholesaler"
    ],
    "wof:name":"First Stop Electrical",
    "wof:placetype":"venue"
},
  "geometry": {"coordinates":[153.534500122,-28.2069396973],"type":"Point"}
}