{
  "type": "Feature",
  "properties": {
    "addr:full":"6 Bennett St East Perth WA 6004",
    "addr:housenumber":"6",
    "addr:postcode":"6004",
    "addr:street":"Bennett St East",
    "iso:country":"AU",
    "sg:address":"6 Bennett St",
    "sg:city":"East Perth",
    "sg:classifiers":[
        {
            "category":"Banks & Credit Unions",
            "subcategory":"Bank",
            "type":"Services"
        }
    ],
    "sg:phone":"+61 8 6461 5444",
    "sg:postcode":"6004",
    "sg:province":"WA",
    "sg:tags":[
        "broker",
        "mortgage"
    ],
    "wof:name":"The Loan Company",
    "wof:placetype":"venue"
},
  "geometry": {"coordinates":[115.870933533,-31.9608745575],"type":"Point"}
}