{
  "type": "Feature",
  "properties": {
    "iso:country":"AU",
    "sg:address":"45 Archer St",
    "sg:city":"Chatswood",
    "sg:classifiers":[
        {
            "category":"Health Services",
            "subcategory":"Optometrist",
            "type":"Services"
        }
    ],
    "sg:phone":"+61 2 9412 4338",
    "sg:postcode":"2067",
    "sg:province":"NSW",
    "wof:name":"Eye Catchers Optical",
    "wof:placetype":"venue"
},
  "geometry": {"coordinates":[151.18539428700001,-33.795463562],"type":"Point"}
}