{
  "type": "Feature",
  "properties": {
    "addr:full":"237 King St Newtown NSW 2042",
    "addr:housenumber":"237",
    "addr:postcode":"2042",
    "addr:street":"King St",
    "iso:country":"AU",
    "sg:address":"237 King St",
    "sg:city":"Newtown",
    "sg:classifiers":[
        {
            "category":"Shopping",
            "subcategory":"Clothing, Apparel, & Fashions",
            "type":"Retail Goods"
        }
    ],
    "sg:phone":"+61 2 9565 2767",
    "sg:postcode":"2042",
    "sg:province":"NSW",
    "sg:tags":[
        "lingerie",
        "hosiery",
        "sleepwear"
    ],
    "wof:name":"Desire Lingerie",
    "wof:placetype":"venue"
},
  "geometry": {"coordinates":[151.18116800000001,-33.895546],"type":"Point"}
}