{
  "type": "Feature",
  "properties": {
    "iso:country":"AU",
    "sg:address":"1B Mort St",
    "sg:city":"Toowoomba",
    "sg:classifiers":[
        {
            "category":"Retail",
            "subcategory":"Auto Repair",
            "type":"Services"
        }
    ],
    "sg:phone":"+61 7 4634 9077",
    "sg:postcode":"4350",
    "sg:province":"QLD",
    "sg:tags":[
        "engine",
        "reconditioning"
    ],
    "wof:name":"Express Engine Reconditioners",
    "wof:placetype":"venue"
},
  "geometry": {"coordinates":[151.94364899999999,-27.540089],"type":"Point"}
}