{
  "type": "Feature",
  "properties": {
    "addr:full":"Shp 26 Raymond Tce Mktplce 35-39 William St Raymond Terrace NSW 2324",
    "addr:housenumber":"26;35-39",
    "addr:postcode":"2324",
    "addr:street":"Raymond Tce Mktplce;William St",
    "iso:country":"AU",
    "sg:address":"Shp 26 Raymond Tce Mktplce 35-39 William St",
    "sg:city":"Raymond Terrace",
    "sg:classifiers":[
        {
            "category":"Shopping",
            "subcategory":"Jewelry",
            "type":"Retail Goods"
        }
    ],
    "sg:phone":"+61 2 4987 1099",
    "sg:postcode":"2324",
    "sg:province":"NSW",
    "sg:tags":[
        "jeweller"
    ],
    "wof:name":"Prouds The Jewellers",
    "wof:placetype":"venue"
},
  "geometry": {"coordinates":[151.743408203,-32.7619094849],"type":"Point"}
}