{
  "type": "Feature",
  "properties": {
    "iso:country":"AU",
    "sg:address":"31- 33 Barry St",
    "sg:city":"Bungalow",
    "sg:classifiers":[
        {
            "category":"Mining & Drilling",
            "type":"Manufacturing & Wholesale Goods"
        }
    ],
    "sg:phone":"+61 7 4033 7678",
    "sg:postcode":"4870",
    "sg:province":"QLD",
    "sg:tags":[
        "boring",
        "contractor"
    ],
    "wof:name":"Adk Civil Pty Ltd",
    "wof:placetype":"venue"
},
  "geometry": {"coordinates":[145.752243042,-16.9392337799],"type":"Point"}
}