{
  "type": "Feature",
  "properties": {
    "iso:country":"AU",
    "sg:address":"47 Carson Drv",
    "sg:city":"Bunya",
    "sg:classifiers":[
        {
            "category":"Banks & Credit Unions",
            "subcategory":"Financial Services",
            "type":"Services"
        }
    ],
    "sg:phone":"+61 7 3351 1800",
    "sg:postcode":"4055",
    "sg:province":"QLD",
    "sg:tags":[
        "planning"
    ],
    "wof:name":"Russell Van Homrigh Financial Services Pty Ltd",
    "wof:placetype":"venue"
},
  "geometry": {"coordinates":[152.93003845199999,-27.3779754639],"type":"Point"}
}