{
  "type": "Feature",
  "properties": {
    "addr:full":"Shop BD4, 50 Bazaar Street, Robina Town Centre Drive Robin QLD 4230",
    "addr:housenumber":"50",
    "addr:postcode":"4230",
    "addr:street":"Bazaar Street Robina Town Centre Drive Robin",
    "iso:country":"AU",
    "sg:address":"Shop BD4, 50",
    "sg:city":"Bazaar Street, Robina Town Centre Drive Robin",
    "sg:classifiers":[
        {
            "category":"Autos & Motor Vehicles",
            "subcategory":"Auto Supplies",
            "type":"Retail Goods"
        }
    ],
    "sg:phone":"+61 7 5562 5750",
    "sg:postcode":"4230",
    "sg:province":"QLD",
    "sg:tags":[
        "automotive",
        "stereo",
        "radio"
    ],
    "wof:name":"JB HI-FI",
    "wof:placetype":"venue"
},
  "geometry": {"coordinates":[153.38531494099999,-28.0774707794],"type":"Point"}
}