{
  "type": "Feature",
  "properties": {
    "addr:full":"187 Bay Rd Berrilee NSW 2159",
    "addr:housenumber":"187",
    "addr:postcode":"2159",
    "addr:street":"Bay Rd",
    "iso:country":"AU",
    "sg:address":"187 Bay Rd",
    "sg:city":"Berrilee",
    "sg:classifiers":[
        {
            "category":"Farming",
            "subcategory":"Livestock Farm",
            "type":"Manufacturing & Wholesale Goods"
        }
    ],
    "sg:phone":"+61 2 9655 1578",
    "sg:postcode":"2159",
    "sg:province":"NSW",
    "sg:tags":[
        "breeder",
        "horse",
        "stud"
    ],
    "wof:name":"Mulawa Arabian Stud Pty Ltd",
    "wof:placetype":"venue"
},
  "geometry": {"coordinates":[151.11843872099999,-33.6012954712],"type":"Point"}
}