{
  "type": "Feature",
  "properties": {
    "addr:full":"571 Whitehorse Rd Surrey Hills VIC 3127",
    "addr:housenumber":"571",
    "addr:postcode":"3127",
    "addr:street":"Whitehorse Rd",
    "iso:country":"AU",
    "sg:address":"571 Whitehorse Rd",
    "sg:city":"Surrey Hills",
    "sg:classifiers":[
        {
            "category":"Professional",
            "subcategory":"Art Services",
            "type":"Services"
        }
    ],
    "sg:phone":"+61 417 353 212",
    "sg:postcode":"3127",
    "sg:province":"VIC",
    "sg:tags":[
        "decorator",
        "painter"
    ],
    "wof:name":"Robert Maraspin",
    "wof:placetype":"venue"
},
  "geometry": {"coordinates":[145.096237183,-37.8144836426],"type":"Point"}
}