{
  "type": "Feature",
  "properties": {
    "addr:full":"Clarinda St Parkes NSW 2870",
    "addr:postcode":"2870",
    "addr:street":"Clarinda St",
    "iso:country":"AU",
    "sg:address":"Clarinda St",
    "sg:city":"Parkes",
    "sg:classifiers":[
        {
            "category":"Food & Beverages",
            "subcategory":"Supermarket",
            "type":"Retail Goods"
        }
    ],
    "sg:phone":"+61 2 6862 6865",
    "sg:postcode":"2870",
    "sg:province":"NSW",
    "sg:tags":[
        "grocery",
        "store"
    ],
    "wof:name":"Franklins Limited",
    "wof:placetype":"venue"
},
  "geometry": {"coordinates":[148.174622,-33.136879],"type":"Point"}
}