{
  "type": "Feature",
  "properties": {
    "iso:country":"AU",
    "sg:address":"45 Doyle Ave",
    "sg:city":"Unanderra",
    "sg:classifiers":[
        {
            "category":"Mining & Drilling",
            "type":"Manufacturing & Wholesale Goods"
        }
    ],
    "sg:phone":"+61 2 4271 4788",
    "sg:postcode":"2526",
    "sg:province":"NSW",
    "sg:tags":[
        "boring",
        "contractor"
    ],
    "wof:name":"Engineered Floors of Australia",
    "wof:placetype":"venue"
},
  "geometry": {"coordinates":[150.835113525,-34.4691123962],"type":"Point"}
}