{
  "type": "Feature",
  "properties": {
    "addr:full":"Shop 8A , Carillon City Arcade , 207 Murray St Perth WA 6000",
    "addr:housenumber":"shop 8a;207",
    "addr:postcode":"6000",
    "addr:street":"Murray St",
    "iso:country":"AU",
    "sg:address":"Shop 8A , Carillon City Arcade , 207 Murray St",
    "sg:city":"Perth",
    "sg:classifiers":[
        {
            "category":"Shopping",
            "subcategory":"Mobile Phones",
            "type":"Retail Goods"
        }
    ],
    "sg:phone":"+61 8 9324 3777",
    "sg:postcode":"6000",
    "sg:province":"WA",
    "sg:tags":[
        "telephone",
        "accessory"
    ],
    "wof:name":"Phones and More",
    "wof:placetype":"venue"
},
  "geometry": {"coordinates":[115.8543396,-31.9515380859],"type":"Point"}
}