{
  "type": "Feature",
  "properties": {
    "addr:full":"142 Morphett Rd Glengowrie SA 5044",
    "addr:housenumber":"142",
    "addr:postcode":"5044",
    "addr:street":"Morphett Rd",
    "iso:country":"AU",
    "sg:address":"142 Morphett Rd",
    "sg:city":"Glengowrie",
    "sg:classifiers":[
        {
            "category":"Retail",
            "subcategory":"Auto Rental",
            "type":"Services"
        }
    ],
    "sg:phone":"+61 8 8376 5578",
    "sg:postcode":"5044",
    "sg:province":"SA",
    "sg:tags":[
        "car",
        "hire",
        "minibus"
    ],
    "wof:name":"Morphett Road Car Rentals",
    "wof:placetype":"venue"
},
  "geometry": {"coordinates":[138.53890999999999,-34.992874],"type":"Point"}
}