{
  "type": "Feature",
  "properties": {
    "addr:full":"14 West St Brompton SA 5007",
    "addr:housenumber":"14",
    "addr:postcode":"5007",
    "addr:street":"West St",
    "iso:country":"AU",
    "sg:address":"14 West St",
    "sg:city":"Brompton",
    "sg:classifiers":[
        {
            "category":"Building & Trades",
            "subcategory":"Construction",
            "type":"Services"
        }
    ],
    "sg:phone":"+61 8 8340 0144",
    "sg:postcode":"5007",
    "sg:province":"SA",
    "sg:tags":[
        "window",
        "aluminium"
    ],
    "wof:name":"Ace Shopfitters (Nominee) Pty Ltd",
    "wof:placetype":"venue"
},
  "geometry": {"coordinates":[138.572463989,-34.9030227661],"type":"Point"}
}