{
  "type": "Feature",
  "properties": {
    "addr:full":"Lot 9, Mcguinnes Drv Robertson NSW 2577",
    "addr:postcode":"2577",
    "addr:street":"Mcguinnes Drv",
    "iso:country":"AU",
    "sg:address":"Lot 9, Mcguinnes Drv",
    "sg:city":"Robertson",
    "sg:classifiers":[
        {
            "category":"Professional",
            "subcategory":"Employment Agencies",
            "type":"Services"
        }
    ],
    "sg:phone":"+61 2 4885 2792",
    "sg:postcode":"2577",
    "sg:province":"NSW",
    "sg:tags":[
        "theatrical",
        "managers",
        "agent",
        "producer"
    ],
    "wof:name":"Wintergreen Pty Ltd",
    "wof:placetype":"venue"
},
  "geometry": {"coordinates":[150.63296508799999,-34.5587387085],"type":"Point"}
}