{
  "type": "Feature",
  "properties": {
    "addr:full":"PO Box 201 Warabrook NSW 2304",
    "addr:postcode":"2304",
    "iso:country":"AU",
    "sg:address":"PO Box 201",
    "sg:city":"Warabrook",
    "sg:classifiers":[
        {
            "category":"Professional",
            "subcategory":"Detective & Security Services",
            "type":"Services"
        }
    ],
    "sg:phone":"+61 2 4920 1122",
    "sg:postcode":"2304",
    "sg:province":"NSW",
    "sg:tags":[
        "guard",
        "patrol"
    ],
    "wof:name":"Evans Security Services",
    "wof:placetype":"venue"
},
  "geometry": {"coordinates":[151.71446227999999,-32.8858909607],"type":"Point"}
}