{
  "type": "Feature",
  "properties": {
    "addr:full":"Trustee Office Return, Lvl 20, 2 Lonsdale St Melbourne VIC 3000",
    "addr:housenumber":"2",
    "addr:postcode":"3000",
    "addr:street":"Lonsdale St",
    "iso:country":"AU",
    "sg:address":"Trustee Office Return, Lvl 20, 2 Lonsdale St",
    "sg:city":"Melbourne",
    "sg:classifiers":[
        {
            "category":"Banks & Credit Unions",
            "subcategory":"Financial Services",
            "type":"Services"
        }
    ],
    "sg:phone":"+61 3 9663 9199",
    "sg:postcode":"3000",
    "sg:province":"VIC",
    "sg:tags":[
        "annuity",
        "rollover",
        "superannuation",
        "consultant"
    ],
    "wof:name":"HostPlus Superannuation Fund",
    "wof:placetype":"venue"
},
  "geometry": {"coordinates":[144.971969605,-37.809299469],"type":"Point"}
}