{
  "type": "Feature",
  "properties": {
    "iso:country":"AU",
    "sg:address":"45 Dickson St",
    "sg:city":"Brighton",
    "sg:classifiers":[
        {
            "category":"Building & Trades",
            "subcategory":"Construction",
            "type":"Services"
        }
    ],
    "sg:phone":"+61 412 651 600",
    "sg:postcode":"4017",
    "sg:province":"QLD",
    "sg:tags":[
        "joiner",
        "carpenter"
    ],
    "wof:name":"Mcleod Industries",
    "wof:placetype":"venue"
},
  "geometry": {"coordinates":[153.06358337399999,-27.3050746918],"type":"Point"}
}