{
  "type": "Feature",
  "properties": {
    "iso:country":"AU",
    "sg:address":"House 2 Municipal Airport",
    "sg:city":"Wendouree",
    "sg:classifiers":[
        {
            "category":"Wholesale",
            "subcategory":"Drugs",
            "type":"Manufacturing & Wholesale Goods"
        }
    ],
    "sg:phone":"+61 3 5338 1953",
    "sg:postcode":"3355",
    "sg:province":"VIC",
    "sg:tags":[
        "wholesaler",
        "pharmaceutical",
        "product",
        "mfrs"
    ],
    "wof:name":"Rawleigh Products",
    "wof:placetype":"venue"
},
  "geometry": {"coordinates":[143.823654,-37.531689],"type":"Point"}
}