{
  "type": "Feature",
  "properties": {
    "addr:full":"The Marine Centre 453 The Esplanade Manly QLD 4179",
    "addr:housenumber":"453",
    "addr:postcode":"4179",
    "addr:street":"The Esplanade",
    "iso:country":"AU",
    "sg:address":"The Marine Centre 453 The Esplanade",
    "sg:city":"Manly",
    "sg:classifiers":[
        {
            "category":"Autos & Motor Vehicles",
            "subcategory":"Boat Sales",
            "type":"Retail Goods"
        }
    ],
    "sg:phone":"+61 7 3396 3303",
    "sg:postcode":"4179",
    "sg:province":"QLD",
    "sg:tags":[
        "equipment",
        "yacht"
    ],
    "wof:name":"G.P.S. & Autopilots Marine Electronic Specialists",
    "wof:placetype":"venue"
},
  "geometry": {"coordinates":[153.18328857399999,-27.4465255737],"type":"Point"}
}