{
  "type": "Feature",
  "properties": {
    "addr:full":"Shop 69, 235 Forest Lake Blv Forest Lake QLD 4078",
    "addr:housenumber":"shop 69 235",
    "addr:postcode":"4078",
    "addr:street":"Forest Lake Blv",
    "iso:country":"AU",
    "sg:address":"Shop 69, 235 Forest Lake Blv",
    "sg:city":"Forest Lake",
    "sg:classifiers":[
        {
            "category":"Shopping",
            "subcategory":"Pets & Pet Supplies",
            "type":"Retail Goods"
        }
    ],
    "sg:phone":"+61 7 3714 9566",
    "sg:postcode":"4078",
    "sg:province":"QLD",
    "sg:tags":[
        "food"
    ],
    "wof:name":"The Pet Boutique",
    "wof:placetype":"venue"
},
  "geometry": {"coordinates":[152.96864318900001,-27.6256027222],"type":"Point"}
}