{
  "type": "Feature",
  "properties": {
    "iso:country":"AU",
    "sg:address":"6 Monaro Pl",
    "sg:city":"Heckenberg",
    "sg:classifiers":[
        {
            "category":"Professional",
            "subcategory":"Art Services",
            "type":"Services"
        }
    ],
    "sg:phone":"+61 2 9720 9837",
    "sg:postcode":"2168",
    "sg:province":"NSW",
    "sg:tags":[
        "decorator",
        "painter"
    ],
    "wof:name":"Colombi Osvaldo",
    "wof:placetype":"venue"
},
  "geometry": {"coordinates":[150.886795044,-33.9111289978],"type":"Point"}
}