{
  "type": "Feature",
  "properties": {
    "iso:country":"AU",
    "sg:address":"27 Swan St",
    "sg:city":"Henley Brook",
    "sg:classifiers":[
        {
            "category":"Building & Trades",
            "subcategory":"Pest Control",
            "type":"Services"
        }
    ],
    "sg:phone":"+61 8 9201 0074",
    "sg:postcode":"6055",
    "sg:province":"WA",
    "sg:tags":[
        "airport"
    ],
    "wof:name":"Forte Airport Management",
    "wof:placetype":"venue"
},
  "geometry": {"coordinates":[116.008499,-31.802523],"type":"Point"}
}