{
  "type": "Feature",
  "properties": {
    "iso:country":"AU",
    "sg:address":"15 Sowden St",
    "sg:city":"Toowoomba",
    "sg:classifiers":[
        {
            "category":"Farming",
            "subcategory":"Farm & Veterinary Services",
            "type":"Manufacturing & Wholesale Goods"
        }
    ],
    "sg:phone":"+61 7 4630 1818",
    "sg:postcode":"4350",
    "sg:province":"QLD",
    "sg:tags":[
        "blacksmith",
        "farrier"
    ],
    "wof:name":"Bateman Noel Engineering Pty Ltd",
    "wof:placetype":"venue"
},
  "geometry": {"coordinates":[151.919449,-27.590702],"type":"Point"}
}