{
  "type": "Feature",
  "properties": {
    "addr:full":"28 Clarendon St South Melbourne VIC 3205",
    "addr:housenumber":"28",
    "addr:postcode":"3205",
    "addr:street":"Clarendon St",
    "iso:country":"AU",
    "sg:address":"28 Clarendon St",
    "sg:city":"South Melbourne",
    "sg:classifiers":[
        {
            "category":"Professional",
            "subcategory":"Employment Agencies",
            "type":"Services"
        }
    ],
    "sg:phone":"+61 3 9686 2788",
    "sg:postcode":"3205",
    "sg:province":"VIC",
    "wof:name":"Enter Arts Media-Recruitment",
    "wof:placetype":"venue"
},
  "geometry": {"coordinates":[144.96270799999999,-37.835869],"type":"Point"}
}