{
  "type": "Feature",
  "properties": {
    "addr:full":"4 Berry Crt Keysborough VIC 3173",
    "addr:housenumber":"4",
    "addr:postcode":"3173",
    "addr:street":"Berry Crt",
    "iso:country":"AU",
    "sg:address":"4 Berry Crt",
    "sg:city":"Keysborough",
    "sg:classifiers":[
        {
            "category":"Organizations",
            "subcategory":"Professional Association",
            "type":"Services"
        }
    ],
    "sg:phone":"+61 3 9017 1047",
    "sg:postcode":"3173",
    "sg:province":"VIC",
    "sg:tags":[
        "web",
        "internet"
    ],
    "wof:name":"eConcepts",
    "wof:placetype":"venue"
},
  "geometry": {"coordinates":[145.167678833,-37.9961357117],"type":"Point"}
}