{
  "type": "Feature",
  "properties": {
    "addr:full":"2nd Floor, 243 Lonsdale St Dandenong VIC 3175",
    "addr:housenumber":"243",
    "addr:postcode":"3175",
    "addr:street":"Lonsdale St",
    "iso:country":"AU",
    "sg:address":"2nd Floor, 243 Lonsdale St",
    "sg:city":"Dandenong",
    "sg:classifiers":[
        {
            "category":"Education",
            "subcategory":"Dance Studio",
            "type":"Public Place"
        }
    ],
    "sg:phone":"+61 3 9794 5267",
    "sg:postcode":"3175",
    "sg:province":"VIC",
    "sg:tags":[
        "venue",
        "tuition"
    ],
    "wof:name":"Dandenong Academy Ballroom",
    "wof:placetype":"venue"
},
  "geometry": {"coordinates":[145.21405029300001,-37.9879302979],"type":"Point"}
}