{
  "type": "Feature",
  "properties": {
    "addr:full":"27 Higginbotham St Gladesville NSW 2111",
    "addr:housenumber":"27",
    "addr:postcode":"2111",
    "addr:street":"Higginbotham St",
    "iso:country":"AU",
    "sg:address":"27 Higginbotham St",
    "sg:city":"Gladesville",
    "sg:classifiers":[
        {
            "category":"Home & Garden",
            "subcategory":"Household Appliances",
            "type":"Retail Goods"
        }
    ],
    "sg:phone":"+61 2 9809 4066",
    "sg:postcode":"2111",
    "sg:province":"NSW",
    "sg:tags":[
        "thermostat"
    ],
    "wof:name":"Derwent Thermostats Pty Ltd",
    "wof:placetype":"venue"
},
  "geometry": {"coordinates":[151.12445068400001,-33.8172683716],"type":"Point"}
}