{
  "type": "Feature",
  "properties": {
    "iso:country":"AU",
    "sg:address":"7/29- 33 Station St",
    "sg:city":"Mortdale",
    "sg:classifiers":[
        {
            "category":"Travel",
            "subcategory":"Travel Agent",
            "type":"Entertainment"
        }
    ],
    "sg:phone":"+61 2 9548 0222",
    "sg:postcode":"2223",
    "sg:province":"NSW",
    "sg:tags":[
        "consultant"
    ],
    "wof:name":"Mobile Travel Service",
    "wof:placetype":"venue"
},
  "geometry": {"coordinates":[151.076568603,-33.9696998596],"type":"Point"}
}