{
  "type": "Feature",
  "properties": {
    "addr:full":"171 Camboon Rd Malaga WA 6090",
    "addr:housenumber":"171",
    "addr:postcode":"6090",
    "addr:street":"Camboon Rd",
    "iso:country":"AU",
    "sg:address":"171 Camboon Rd",
    "sg:city":"Malaga",
    "sg:classifiers":[
        {
            "category":"Social Services",
            "subcategory":"Retirement Home",
            "type":"Services"
        }
    ],
    "sg:phone":"+61 8 9449 3333",
    "sg:postcode":"6090",
    "sg:province":"WA",
    "sg:tags":[
        "environmental",
        "consultant",
        "pollution"
    ],
    "wof:name":"Cleanaway Technical Services",
    "wof:placetype":"venue"
},
  "geometry": {"coordinates":[115.887672424,-31.8582248688],"type":"Point"}
}