{
  "type": "Feature",
  "properties": {
    "addr:full":"Level 8, 255 George St Sydney NSW 2000",
    "addr:housenumber":"255",
    "addr:postcode":"2000",
    "addr:street":"George St",
    "iso:country":"AU",
    "sg:address":"Level 8, 255 George St",
    "sg:city":"Sydney",
    "sg:classifiers":[
        {
            "category":"Banks & Credit Unions",
            "subcategory":"Financial Services",
            "type":"Services"
        }
    ],
    "sg:phone":"+61 2 8216 6752",
    "sg:postcode":"2000",
    "sg:province":"NSW",
    "sg:tags":[
        "financier"
    ],
    "wof:name":"Ord Minnett Limited",
    "wof:placetype":"venue"
},
  "geometry": {"coordinates":[151.207305908,-33.8637886047],"type":"Point"}
}