{
  "type": "Feature",
  "properties": {
    "addr:full":"PO Box 71 Ulladulla NSW 2539",
    "addr:postcode":"2539",
    "iso:country":"AU",
    "sg:address":"PO Box 71",
    "sg:city":"Ulladulla",
    "sg:classifiers":[
        {
            "category":"Utilities",
            "subcategory":"Water",
            "type":"Services"
        }
    ],
    "sg:phone":"+61 2 4454 0973",
    "sg:postcode":"2539",
    "sg:province":"NSW",
    "sg:tags":[
        "hot",
        "system"
    ],
    "wof:name":"Perrin Shaun",
    "wof:placetype":"venue"
},
  "geometry": {"coordinates":[150.475631714,-35.3509788513],"type":"Point"}
}