{
  "type": "Feature",
  "properties": {
    "addr:full":"16 Ash St Orange NSW 2800",
    "addr:housenumber":"16",
    "addr:postcode":"2800",
    "addr:street":"Ash St",
    "iso:country":"AU",
    "sg:address":"16 Ash St",
    "sg:city":"Orange",
    "sg:classifiers":[
        {
            "category":"Professional",
            "subcategory":"Detective & Security Services",
            "type":"Services"
        }
    ],
    "sg:phone":"+61 2 6362 3633",
    "sg:postcode":"2800",
    "sg:province":"NSW",
    "sg:tags":[
        "equipment",
        "window",
        "doors"
    ],
    "wof:name":"Taberner Glass",
    "wof:placetype":"venue"
},
  "geometry": {"coordinates":[149.10627746599999,-33.3095474243],"type":"Point"}
}