{
  "type": "Feature",
  "properties": {
    "iso:country":"AU",
    "sg:address":"115 Pittwater Rd",
    "sg:city":"Manly",
    "sg:classifiers":[
        {
            "category":"Personal",
            "subcategory":"Massage",
            "type":"Services"
        }
    ],
    "sg:phone":"+61 2 9977 0105",
    "sg:postcode":"2095",
    "sg:province":"NSW",
    "sg:tags":[
        "therapy"
    ],
    "wof:name":"Sympony Treatmrny Clinic",
    "wof:placetype":"venue"
},
  "geometry": {"coordinates":[151.28504943900001,-33.7910270691],"type":"Point"}
}