{
  "type": "Feature",
  "properties": {
    "addr:full":"Unit 4 / 134 Station Rd Blackheath NSW 2785",
    "addr:housenumber":"/ 134",
    "addr:postcode":"2785",
    "addr:street":"Station Rd",
    "iso:country":"AU",
    "sg:address":"Unit 4 / 134 Station Rd",
    "sg:city":"Blackheath",
    "sg:classifiers":[
        {
            "category":"Military Area",
            "subcategory":"Air Force Base",
            "type":"Public Place"
        }
    ],
    "sg:phone":"+61 2 4787 5771",
    "sg:postcode":"2785",
    "sg:province":"NSW",
    "sg:tags":[
        "equipment",
        "climbing",
        "venue",
        "rock"
    ],
    "wof:name":"Blackheath Climb Centre",
    "wof:placetype":"venue"
},
  "geometry": {"coordinates":[150.28390502900001,-33.6342658997],"type":"Point"}
}