{
  "type": "Feature",
  "properties": {
    "addr:full":"2 Kingston Plaza Kingston TAS 7050",
    "addr:housenumber":"2",
    "addr:postcode":"7050",
    "addr:street":"Kingston Plaza",
    "iso:country":"AU",
    "sg:address":"2 Kingston Plaza",
    "sg:city":"Kingston",
    "sg:classifiers":[
        {
            "category":"Health Services",
            "subcategory":"Optometrist",
            "type":"Services"
        }
    ],
    "sg:phone":"+61 3 6229 9911",
    "sg:postcode":"7050",
    "sg:province":"TAS",
    "wof:name":"Optomeyes",
    "wof:placetype":"venue"
},
  "geometry": {"coordinates":[147.310822,-42.975227],"type":"Point"}
}