{
  "type": "Feature",
  "properties": {
    "addr:full":"27- 29 Clark St Ballina NSW 2478",
    "addr:housenumber":"29",
    "addr:postcode":"2478",
    "addr:street":"Clark St",
    "iso:country":"AU",
    "sg:address":"27- 29 Clark St",
    "sg:city":"Ballina",
    "sg:classifiers":[
        {
            "category":"Commercial Area",
            "type":"Public Place"
        }
    ],
    "sg:phone":"+61 2 6686 2933",
    "sg:postcode":"2478",
    "sg:province":"NSW",
    "sg:tags":[
        "heavy",
        "carrier"
    ],
    "wof:name":"M.E.T. Grono Transport",
    "wof:placetype":"venue"
},
  "geometry": {"coordinates":[153.56280517600001,-28.8556575775],"type":"Point"}
}