{
  "type": "Feature",
  "properties": {
    "addr:full":"Unit A, 23 - 25 Thornsborne St Beenleigh QLD 4207",
    "addr:housenumber":"25",
    "addr:postcode":"4207",
    "addr:street":"Thornsborne St",
    "iso:country":"AU",
    "sg:address":"Unit A, 23 - 25 Thornsborne St",
    "sg:city":"Beenleigh",
    "sg:classifiers":[
        {
            "category":"Building & Trades",
            "subcategory":"Construction",
            "type":"Services"
        }
    ],
    "sg:phone":"+61 7 3804 6977",
    "sg:postcode":"4207",
    "sg:province":"QLD",
    "sg:tags":[
        "installation",
        "air conditioning"
    ],
    "sg:website":"http://www.thompsoncooling.com.au",
    "wof:name":"Thompson Cooling",
    "wof:placetype":"venue"
},
  "geometry": {"coordinates":[153.19309997600001,-27.7144832611],"type":"Point"}
}