{
  "type": "Feature",
  "properties": {
    "iso:country":"AU",
    "sg:address":"34 Burwood Rd",
    "sg:city":"Alexandra Hills",
    "sg:classifiers":[
        {
            "category":"Personal",
            "type":"Services"
        }
    ],
    "sg:phone":"+61 7 3824 5890",
    "sg:postcode":"4161",
    "sg:province":"QLD",
    "sg:tags":[
        "introduction",
        "social"
    ],
    "wof:name":"Diannes International Introduction Agency",
    "wof:placetype":"venue"
},
  "geometry": {"coordinates":[153.225875855,-27.5441913605],"type":"Point"}
}