{
  "type": "Feature",
  "properties": {
    "iso:country":"AU",
    "sg:address":"112 Lyndhurst Rd",
    "sg:city":"Boondall",
    "sg:classifiers":[
        {
            "category":"Professional",
            "subcategory":"Art Services",
            "type":"Services"
        }
    ],
    "sg:phone":"+61 7 3265 2040",
    "sg:postcode":"4034",
    "sg:province":"QLD",
    "sg:tags":[
        "decorator",
        "painter"
    ],
    "wof:name":"McDonald Don",
    "wof:placetype":"venue"
},
  "geometry": {"coordinates":[153.061096,-27.3444],"type":"Point"}
}