{
  "type": "Feature",
  "properties": {
    "addr:full":"659 North Rd Ormond VIC 3204",
    "addr:housenumber":"659",
    "addr:postcode":"3204",
    "addr:street":"North Rd",
    "iso:country":"AU",
    "sg:address":"659 North Rd",
    "sg:city":"Ormond",
    "sg:classifiers":[
        {
            "category":"Wholesale",
            "subcategory":"Plants",
            "type":"Manufacturing & Wholesale Goods"
        }
    ],
    "sg:phone":"+61 3 9597 9266",
    "sg:postcode":"3204",
    "sg:province":"VIC",
    "sg:tags":[
        "florist"
    ],
    "wof:name":"Divine Flowers",
    "wof:placetype":"venue"
},
  "geometry": {"coordinates":[145.05291700000001,-37.905396],"type":"Point"}
}