{
  "type": "Feature",
  "properties": {
    "addr:full":"3a Mundford St North Beach WA 6020",
    "addr:housenumber":"3a",
    "addr:postcode":"6020",
    "addr:street":"Mundford St",
    "iso:country":"AU",
    "sg:address":"3a Mundford St",
    "sg:city":"North Beach",
    "sg:classifiers":[
        {
            "category":"Utilities",
            "subcategory":"Electric",
            "type":"Services"
        }
    ],
    "sg:phone":"+61 409 411 946",
    "sg:postcode":"6020",
    "sg:province":"WA",
    "sg:tags":[
        "electrical",
        "contractor"
    ],
    "wof:name":"BMC Electrical",
    "wof:placetype":"venue"
},
  "geometry": {"coordinates":[115.76759338399999,-31.8600349426],"type":"Point"}
}