{
  "type": "Feature",
  "properties": {
    "addr:full":"7 Lurnea Crs Valentine NSW 2280",
    "addr:housenumber":"7",
    "addr:postcode":"2280",
    "addr:street":"Lurnea Crs",
    "iso:country":"AU",
    "sg:address":"7 Lurnea Crs",
    "sg:city":"Valentine",
    "sg:classifiers":[
        {
            "category":"Sports & Exercise",
            "subcategory":"Gym",
            "type":"Entertainment"
        }
    ],
    "sg:phone":"+61 2 4946 7383",
    "sg:postcode":"2280",
    "sg:province":"NSW",
    "sg:tags":[
        "meditation"
    ],
    "wof:name":"Satyananda Yoga",
    "wof:placetype":"venue"
},
  "geometry": {"coordinates":[151.644287109,-33.0118789673],"type":"Point"}
}