{
  "type": "Feature",
  "properties": {
    "addr:full":"Alvaston Drv Carine WA 6020",
    "addr:postcode":"6020",
    "addr:street":"Alvaston Drv",
    "iso:country":"AU",
    "sg:address":"Alvaston Drv",
    "sg:city":"Carine",
    "sg:classifiers":[
        {
            "category":"Education",
            "subcategory":"Kindergarten",
            "type":"Public Place"
        }
    ],
    "sg:phone":"+61 8 9447 0317",
    "sg:postcode":"6020",
    "sg:province":"WA",
    "sg:tags":[
        "pre-schools"
    ],
    "wof:name":"Alvaston Kindergarten",
    "wof:placetype":"venue"
},
  "geometry": {"coordinates":[115.77570342999999,-31.8507575989],"type":"Point"}
}