{
  "type": "Feature",
  "properties": {
    "addr:full":"U1/ 37 Meadow Ave Coopers Plains QLD 4108",
    "addr:housenumber":"37",
    "addr:postcode":"4108",
    "addr:street":"U1 /;Meadow Ave",
    "iso:country":"AU",
    "sg:address":"U1/ 37 Meadow Ave",
    "sg:city":"Coopers Plains",
    "sg:classifiers":[
        {
            "category":"Home & Garden",
            "subcategory":"Household Appliances",
            "type":"Retail Goods"
        }
    ],
    "sg:phone":"+61 7 3272 9118",
    "sg:postcode":"4108",
    "sg:province":"QLD",
    "sg:tags":[
        "chemical",
        "equipment",
        "steam",
        "cleaning",
        "pressure"
    ],
    "wof:name":"J & H Cleaning Equipment Service Pty Ltd",
    "wof:placetype":"venue"
},
  "geometry": {"coordinates":[153.025222778,-27.5659141541],"type":"Point"}
}