{
  "type": "Feature",
  "properties": {
    "addr:full":"Reynolds St Bowen QLD 4805",
    "addr:postcode":"4805",
    "addr:street":"Reynolds St",
    "iso:country":"AU",
    "sg:address":"Reynolds St",
    "sg:city":"Bowen",
    "sg:classifiers":[
        {
            "category":"Autos & Motor Vehicles",
            "subcategory":"Fuel & Gas Station",
            "type":"Retail Goods"
        }
    ],
    "sg:phone":"+61 7 4786 1954",
    "sg:postcode":"4805",
    "sg:province":"QLD",
    "wof:name":"BP Australia Limited",
    "wof:placetype":"venue"
},
  "geometry": {"coordinates":[148.231323242,-20.0117874146],"type":"Point"}
}