{
  "type": "Feature",
  "properties": {
    "addr:full":"42 Great Western Hwy Valley Heights NSW 2777",
    "addr:housenumber":"42",
    "addr:postcode":"2777",
    "addr:street":"Great Western Hwy",
    "iso:country":"AU",
    "sg:address":"42 Great Western Hwy",
    "sg:city":"Valley Heights",
    "sg:classifiers":[
        {
            "category":"Retail",
            "subcategory":"Auto Rental",
            "type":"Services"
        }
    ],
    "sg:phone":"+61 2 4751 8920",
    "sg:postcode":"2777",
    "sg:province":"NSW",
    "sg:tags":[
        "car",
        "hire",
        "minibus"
    ],
    "wof:name":"RediCar Rentals",
    "wof:placetype":"venue"
},
  "geometry": {"coordinates":[150.581863403,-33.7023849487],"type":"Point"}
}