{
  "type": "Feature",
  "properties": {
    "addr:full":"18 Toms Crs Ainslie ACT 2602",
    "addr:housenumber":"18",
    "addr:postcode":"2602",
    "addr:street":"Toms Crs",
    "iso:country":"AU",
    "sg:address":"18 Toms Crs",
    "sg:city":"Ainslie",
    "sg:classifiers":[
        {
            "category":"Farming",
            "subcategory":"Farm & Veterinary Services",
            "type":"Manufacturing & Wholesale Goods"
        }
    ],
    "sg:phone":"+61 412 625 656",
    "sg:postcode":"2602",
    "sg:province":"ACT",
    "sg:tags":[
        "irrigation",
        "reticulation",
        "system"
    ],
    "wof:name":"Aspen Installation & Maintenance",
    "wof:placetype":"venue"
},
  "geometry": {"coordinates":[149.14654540999999,-35.2622108459],"type":"Point"}
}