{
  "type": "Feature",
  "properties": {
    "addr:full":"118 Bayswater Rd Croydon South VIC 3136",
    "addr:housenumber":"118",
    "addr:postcode":"3136",
    "addr:street":"Bayswater Rd",
    "iso:country":"AU",
    "sg:address":"118 Bayswater Rd",
    "sg:city":"Croydon South",
    "sg:classifiers":[
        {
            "category":"Fast Food",
            "type":"Food & Drink"
        }
    ],
    "sg:phone":"+61 3 9723 2539",
    "sg:postcode":"3136",
    "sg:province":"VIC",
    "sg:tags":[
        "away",
        "take"
    ],
    "wof:name":"Chook Stop",
    "wof:placetype":"venue"
},
  "geometry": {"coordinates":[145.26934814399999,-37.8114433289],"type":"Point"}
}