{
  "type": "Feature",
  "properties": {
    "addr:full":"PO Box 1010 Tweed Heads NSW 2485",
    "addr:postcode":"2485",
    "iso:country":"AU",
    "sg:address":"PO Box 1010",
    "sg:city":"Tweed Heads",
    "sg:classifiers":[
        {
            "category":"Utilities",
            "subcategory":"Water",
            "type":"Services"
        }
    ],
    "sg:phone":"+61 408 754 884",
    "sg:postcode":"2485",
    "sg:province":"NSW",
    "sg:tags":[
        "hot",
        "system"
    ],
    "wof:name":"A A1 Electrician",
    "wof:placetype":"venue"
},
  "geometry": {"coordinates":[153.51756286599999,-28.1832504272],"type":"Point"}
}