{
  "type": "Feature",
  "properties": {
    "addr:full":"Shop 32 Whitford City Shopping Centre Whitfords WA 6025",
    "addr:housenumber":"shop 32",
    "addr:postcode":"6025",
    "iso:country":"AU",
    "sg:address":"Shop 32 Whitford City Shopping Centre",
    "sg:city":"Whitfords",
    "sg:classifiers":[
        {
            "category":"Food & Beverages",
            "subcategory":"Specialty",
            "type":"Retail Goods"
        }
    ],
    "sg:phone":"+61 8 9307 6677",
    "sg:postcode":"6025",
    "sg:province":"WA",
    "sg:tags":[
        "product",
        "health"
    ],
    "wof:name":"Good Life Health Stores",
    "wof:placetype":"venue"
},
  "geometry": {"coordinates":[115.758071899,-31.7966384888],"type":"Point"}
}