{
  "type": "Feature",
  "properties": {
    "addr:full":"689a The Horsley Drv Smithfield NSW 2164",
    "addr:housenumber":"689a",
    "addr:postcode":"2164",
    "addr:street":"The Horsley Drv",
    "iso:country":"AU",
    "sg:address":"689a The Horsley Drv",
    "sg:city":"Smithfield",
    "sg:classifiers":[
        {
            "category":"Real Estate",
            "subcategory":"Real Estate Agent",
            "type":"Services"
        }
    ],
    "sg:phone":"+61 2 9604 7577",
    "sg:postcode":"2164",
    "sg:province":"NSW",
    "wof:name":"Centro Property Developments",
    "wof:placetype":"venue"
},
  "geometry": {"coordinates":[150.93940734899999,-33.8531913757],"type":"Point"}
}