{
  "type": "Feature",
  "properties": {
    "iso:country":"AU",
    "sg:address":"10 Long Reef Crs",
    "sg:city":"Woodbine",
    "sg:classifiers":[
        {
            "category":"Building & Trades",
            "subcategory":"Construction",
            "type":"Services"
        }
    ],
    "sg:phone":"+61 2 4626 2347",
    "sg:postcode":"2560",
    "sg:province":"NSW",
    "sg:tags":[
        "earth",
        "excavating",
        "moving",
        "contractor"
    ],
    "wof:name":"Australias Most Wanted Bobcat & Tipper Hire",
    "wof:placetype":"venue"
},
  "geometry": {"coordinates":[150.825042725,-34.0461807251],"type":"Point"}
}