{
  "type": "Feature",
  "properties": {
    "addr:full":"Lot 4219 Stuart Hwy Alice Springs NT 0870",
    "addr:housenumber":"4219",
    "addr:postcode":"nt 0870",
    "addr:street":"Stuart Hwy",
    "iso:country":"AU",
    "sg:address":"Lot 4219 Stuart Hwy",
    "sg:city":"Alice Springs",
    "sg:classifiers":[
        {
            "category":"Wholesale",
            "subcategory":"Machinery & Supplies",
            "type":"Manufacturing & Wholesale Goods"
        }
    ],
    "sg:phone":"+61 8 8952 1788",
    "sg:postcode":"0870",
    "sg:province":"NT",
    "sg:tags":[
        "engineer"
    ],
    "wof:name":"Blackwood J & Son Ltd",
    "wof:placetype":"venue"
},
  "geometry": {"coordinates":[133.86329650900001,-23.7301254272],"type":"Point"}
}