{
  "type": "Feature",
  "properties": {
    "addr:full":"2 Johnson St Birchip VIC 3483",
    "addr:housenumber":"2",
    "addr:postcode":"3483",
    "addr:street":"Johnson St",
    "iso:country":"AU",
    "sg:address":"2 Johnson St",
    "sg:city":"Birchip",
    "sg:classifiers":[
        {
            "category":"Professional",
            "type":"Services"
        }
    ],
    "sg:phone":"+61 3 5492 2430",
    "sg:postcode":"3483",
    "sg:province":"VIC",
    "sg:tags":[
        "transport"
    ],
    "wof:name":"Hogan C F & H C",
    "wof:placetype":"venue"
},
  "geometry": {"coordinates":[142.91308593799999,-35.9832305908],"type":"Point"}
}