{
  "type": "Feature",
  "properties": {
    "addr:full":"Level 1, Suite 4 53- 55 Gladesville Rd Hunters Hill NSW 2110",
    "addr:housenumber":"53 55",
    "addr:postcode":"2110",
    "addr:street":"Gladesville Rd",
    "iso:country":"AU",
    "sg:address":"Level 1, Suite 4 53- 55 Gladesville Rd",
    "sg:city":"Hunters Hill",
    "sg:classifiers":[
        {
            "category":"Health Services",
            "subcategory":"Doctor",
            "type":"Services"
        }
    ],
    "sg:phone":"+61 2 9816 1599",
    "sg:postcode":"2110",
    "sg:province":"NSW",
    "sg:tags":[
        "nurse",
        "nursing"
    ],
    "wof:name":"Home Instead Senior Care",
    "wof:placetype":"venue"
},
  "geometry": {"coordinates":[151.14419555699999,-33.8336105347],"type":"Point"}
}