{
  "type": "Feature",
  "properties": {
    "addr:full":"Warnock Park O&#039;Neill St Guildford NSW 2161",
    "addr:postcode":"2161",
    "addr:street":"Neill St",
    "iso:country":"AU",
    "sg:address":"Warnock Park O&#039;Neill St",
    "sg:city":"Guildford",
    "sg:classifiers":[
        {
            "category":"Social Services",
            "subcategory":"Child Care",
            "type":"Services"
        }
    ],
    "sg:phone":"+61 2 9632 9762",
    "sg:postcode":"2161",
    "sg:province":"NSW",
    "sg:tags":[
        "support",
        "health"
    ],
    "wof:name":"Early Childhood Health Centres",
    "wof:placetype":"venue"
},
  "geometry": {"coordinates":[150.96209716800001,-33.8490257263],"type":"Point"}
}