{
  "type": "Feature",
  "properties": {
    "iso:country":"AU",
    "sg:address":"135 Kathleen Drv",
    "sg:city":"Old Beach",
    "sg:classifiers":[
        {
            "category":"Building & Trades",
            "subcategory":"Construction",
            "type":"Services"
        }
    ],
    "sg:phone":"+61 409 972 134",
    "sg:postcode":"7017",
    "sg:province":"TAS",
    "sg:tags":[
        "earth",
        "excavating",
        "moving",
        "contractor"
    ],
    "wof:name":"AJ & MF Davis Contract Maintenance Services",
    "wof:placetype":"venue"
},
  "geometry": {"coordinates":[147.31468200699999,-42.7477302551],"type":"Point"}
}