{
  "type": "Feature",
  "properties": {
    "addr:full":"103 Whites Rd Manly QLD 4179",
    "addr:housenumber":"103",
    "addr:postcode":"4179",
    "addr:street":"Whites Rd",
    "iso:country":"AU",
    "sg:address":"103 Whites Rd",
    "sg:city":"Manly",
    "sg:classifiers":[
        {
            "category":"Personal",
            "subcategory":"Beauty Salon",
            "type":"Services"
        }
    ],
    "sg:phone":"+61 7 3396 7857",
    "sg:postcode":"4179",
    "sg:province":"QLD",
    "sg:tags":[
        "hairdresser"
    ],
    "wof:name":"Indigo Blue",
    "wof:placetype":"venue"
},
  "geometry": {"coordinates":[153.180084228,-27.462846756],"type":"Point"}
}