{
  "type": "Feature",
  "properties": {
    "addr:full":"660 Mitcham Rd Vermont VIC 3133",
    "addr:housenumber":"660",
    "addr:postcode":"3133",
    "addr:street":"Mitcham Rd",
    "iso:country":"AU",
    "sg:address":"660 Mitcham Rd",
    "sg:city":"Vermont",
    "sg:classifiers":[
        {
            "category":"Health Services",
            "subcategory":"Chiropractor",
            "type":"Services"
        }
    ],
    "sg:phone":"+61 3 9874 4200",
    "sg:postcode":"3133",
    "sg:province":"VIC",
    "wof:name":"Mock W Russell",
    "wof:placetype":"venue"
},
  "geometry": {"coordinates":[145.19490051299999,-37.8336105347],"type":"Point"}
}