{
  "type": "Feature",
  "properties": {
    "addr:full":"Unit 1/ 54 Caswell St East Brisbane QLD 4169",
    "addr:housenumber":"54",
    "addr:postcode":"4169",
    "addr:street":"Caswell St",
    "iso:country":"AU",
    "sg:address":"Unit 1/ 54 Caswell St",
    "sg:city":"East Brisbane",
    "sg:classifiers":[
        {
            "category":"Communications",
            "subcategory":"Film & Video Production",
            "type":"Services"
        }
    ],
    "sg:phone":"+61 7 3391 2311",
    "sg:postcode":"4169",
    "sg:province":"QLD",
    "sg:tags":[
        "television",
        "system",
        "circuit",
        "closed"
    ],
    "wof:name":"Vicam CCTV Systems",
    "wof:placetype":"venue"
},
  "geometry": {"coordinates":[153.04957580600001,-27.4889965057],"type":"Point"}
}