{
  "type": "Feature",
  "properties": {
    "addr:full":"76 Shore St Cleveland QLD 4163",
    "addr:housenumber":"76",
    "addr:postcode":"4163",
    "addr:street":"Shore St",
    "iso:country":"AU",
    "sg:address":"76 Shore St",
    "sg:city":"Cleveland",
    "sg:classifiers":[
        {
            "category":"Building & Trades",
            "subcategory":"Equipment Rental",
            "type":"Services"
        }
    ],
    "sg:phone":"+61 7 3286 3777",
    "sg:postcode":"4163",
    "sg:province":"QLD",
    "sg:tags":[
        "party",
        "hire"
    ],
    "wof:name":"Betta Hire",
    "wof:placetype":"venue"
},
  "geometry": {"coordinates":[153.25833129899999,-27.5244274139],"type":"Point"}
}