{
  "type": "Feature",
  "properties": {
    "iso:country":"AU",
    "sg:address":"96 Redbank Plns School Rd",
    "sg:city":"Redbank Plains",
    "sg:classifiers":[
        {
            "category":"Wholesale",
            "subcategory":"Machinery & Supplies",
            "type":"Manufacturing & Wholesale Goods"
        }
    ],
    "sg:phone":"+61 7 3814 1700",
    "sg:postcode":"4301",
    "sg:province":"QLD",
    "sg:tags":[
        "equipment",
        "hydraulic"
    ],
    "wof:name":"Pirtek (Ipswich) Pty Ltd",
    "wof:placetype":"venue"
},
  "geometry": {"coordinates":[152.83494567899999,-27.6375255585],"type":"Point"}
}