{
  "type": "Feature",
  "properties": {
    "addr:full":"Shp 1.38 The Glen Shopng Cntr 235 Springvale Rd Glen Waverley VIC 3150",
    "addr:housenumber":"235",
    "addr:postcode":"3150",
    "addr:street":"Springvale Rd",
    "iso:country":"AU",
    "sg:address":"Shp 1.38 The Glen Shopng Cntr 235 Springvale Rd",
    "sg:city":"Glen Waverley",
    "sg:classifiers":[
        {
            "category":"Travel",
            "subcategory":"Travel Agent",
            "type":"Entertainment"
        }
    ],
    "sg:phone":"+61 3 9886 8899",
    "sg:postcode":"3150",
    "sg:province":"VIC",
    "sg:tags":[
        "consultant"
    ],
    "wof:name":"Thomas Cook Travel",
    "wof:placetype":"venue"
},
  "geometry": {"coordinates":[145.16653442399999,-37.87449646],"type":"Point"}
}