{
  "type": "Feature",
  "properties": {
    "addr:full":"80 Greenglade Drv Paradise SA 5075",
    "addr:housenumber":"80",
    "addr:postcode":"5075",
    "addr:street":"Greenglade Drv",
    "iso:country":"AU",
    "sg:address":"80 Greenglade Drv",
    "sg:city":"Paradise",
    "sg:classifiers":[
        {
            "category":"Retail",
            "subcategory":"Repair Shop",
            "type":"Services"
        }
    ],
    "sg:phone":"+61 8 8337 9553",
    "sg:postcode":"5075",
    "sg:province":"SA",
    "sg:tags":[
        "leadlights"
    ],
    "wof:name":"Aurora Leadlight",
    "wof:placetype":"venue"
},
  "geometry": {"coordinates":[138.65713500999999,-34.8708457947],"type":"Point"}
}