{
  "type": "Feature",
  "properties": {
    "addr:full":"5 McCartney St Fannie Bay NT 0820",
    "addr:housenumber":"5",
    "addr:postcode":"nt 0820",
    "addr:street":"Mccartney St",
    "iso:country":"AU",
    "sg:address":"5 McCartney St",
    "sg:city":"Fannie Bay",
    "sg:classifiers":[
        {
            "category":"Retail",
            "subcategory":"Auto Rental",
            "type":"Services"
        }
    ],
    "sg:phone":"+61 413 878 692",
    "sg:postcode":"0820",
    "sg:province":"NT",
    "sg:tags":[
        "camper-trailers",
        "caravan",
        "hire"
    ],
    "sg:website":"http://www.pioneercampers.com",
    "wof:name":"All-Road Camper Trailers & Boats",
    "wof:placetype":"venue"
},
  "geometry": {"coordinates":[130.84054565400001,-12.4314107895],"type":"Point"}
}