{
  "type": "Feature",
  "properties": {
    "addr:full":"PO Box 190 Canungra QLD 4275",
    "addr:postcode":"4275",
    "iso:country":"AU",
    "sg:address":"PO Box 190",
    "sg:city":"Canungra",
    "sg:classifiers":[
        {
            "category":"Home & Garden",
            "subcategory":"Hardware",
            "type":"Retail Goods"
        }
    ],
    "sg:phone":"+61 7 5543 5599",
    "sg:postcode":"4275",
    "sg:province":"QLD",
    "sg:tags":[
        "woodworking",
        "machinery"
    ],
    "wof:name":"Felder Qld Pty Ltd",
    "wof:placetype":"venue"
},
  "geometry": {"coordinates":[153.16848754899999,-28.0191307068],"type":"Point"}
}