{
  "type": "Feature",
  "properties": {
    "addr:full":"61 Archer St Chatswood NSW 2067",
    "addr:housenumber":"61",
    "addr:postcode":"2067",
    "addr:street":"Archer St",
    "iso:country":"AU",
    "sg:address":"61 Archer St",
    "sg:city":"Chatswood",
    "sg:classifiers":[
        {
            "category":"Professional",
            "subcategory":"Employment Agencies",
            "type":"Services"
        }
    ],
    "sg:phone":"+61 2 9412 3122",
    "sg:postcode":"2067",
    "sg:province":"NSW",
    "wof:name":"Jobs Australia",
    "wof:placetype":"venue"
},
  "geometry": {"coordinates":[151.18612670900001,-33.7968902588],"type":"Point"}
}