{
  "type": "Feature",
  "properties": {
    "addr:full":"26 Sherwood Ave Happy Valley SA 5159",
    "addr:housenumber":"26",
    "addr:postcode":"5159",
    "addr:street":"Sherwood Ave",
    "iso:country":"AU",
    "sg:address":"26 Sherwood Ave",
    "sg:city":"Happy Valley",
    "sg:classifiers":[
        {
            "category":"Organizations",
            "subcategory":"Community Association",
            "type":"Services"
        }
    ],
    "sg:phone":"+61 8 8387 6973",
    "sg:postcode":"5159",
    "sg:province":"SA",
    "sg:tags":[
        "organisation",
        "family",
        "welfare"
    ],
    "wof:name":"Down To Earth Services",
    "wof:placetype":"venue"
},
  "geometry": {"coordinates":[138.561935425,-35.0857849121],"type":"Point"}
}