{
  "type": "Feature",
  "properties": {
    "addr:full":"16 Beedham St Clontarf QLD 4019",
    "addr:housenumber":"16",
    "addr:postcode":"4019",
    "addr:street":"Beedham St",
    "iso:country":"AU",
    "sg:address":"16 Beedham St",
    "sg:city":"Clontarf",
    "sg:classifiers":[
        {
            "category":"Professional",
            "subcategory":"Art Services",
            "type":"Services"
        }
    ],
    "sg:phone":"+61 7 3283 1783",
    "sg:postcode":"4019",
    "sg:province":"QLD",
    "sg:tags":[
        "decorator",
        "painter"
    ],
    "wof:name":"Melville M N & L K",
    "wof:placetype":"venue"
},
  "geometry": {"coordinates":[153.092895508,-27.2462043762],"type":"Point"}
}