{
  "type": "Feature",
  "properties": {
    "addr:full":"Shop 2b, 8 Station St Indooroopilly QLD 4068",
    "addr:housenumber":"shop 2b 8",
    "addr:postcode":"4068",
    "addr:street":"Station St",
    "iso:country":"AU",
    "sg:address":"Shop 2b, 8 Station St",
    "sg:city":"Indooroopilly",
    "sg:classifiers":[
        {
            "category":"Fast Food",
            "type":"Food & Drink"
        }
    ],
    "sg:phone":"+61 7 3378 1922",
    "sg:postcode":"4068",
    "sg:province":"QLD",
    "sg:tags":[
        "away",
        "take"
    ],
    "wof:name":"Sitar Express Indian Takeaway Indooroopilly",
    "wof:placetype":"venue"
},
  "geometry": {"coordinates":[152.97515869099999,-27.5026283264],"type":"Point"}
}