{
  "type": "Feature",
  "properties": {
    "iso:country":"AU",
    "sg:address":"155 St Leonards Rd",
    "sg:city":"Ascot Vale",
    "sg:classifiers":[
        {
            "category":"Building & Trades",
            "subcategory":"Plumbing",
            "type":"Services"
        }
    ],
    "sg:phone":"+61 3 9370 0854",
    "sg:postcode":"3032",
    "sg:province":"VIC",
    "sg:tags":[
        "plumber",
        "gasfitters"
    ],
    "wof:name":"Arena Plumbing & Co",
    "wof:placetype":"venue"
},
  "geometry": {"coordinates":[144.90992700000001,-37.773365],"type":"Point"}
}