{
  "type": "Feature",
  "properties": {
    "addr:full":"U3/ 100 Lear Jet Drv Caboolture QLD 4510",
    "addr:housenumber":"100",
    "addr:postcode":"4510",
    "addr:street":"U3 /;Jet Drv",
    "iso:country":"AU",
    "sg:address":"U3/ 100 Lear Jet Drv",
    "sg:city":"Caboolture",
    "sg:classifiers":[
        {
            "category":"Recreation",
            "subcategory":"Boat Charter",
            "type":"Entertainment"
        }
    ],
    "sg:phone":"+61 404 029 442",
    "sg:postcode":"4510",
    "sg:province":"QLD",
    "sg:tags":[
        "canopy",
        "motor"
    ],
    "wof:name":"Xtreme Alloy Products",
    "wof:placetype":"venue"
},
  "geometry": {"coordinates":[152.97894299999999,-27.084316],"type":"Point"}
}