{
  "type": "Feature",
  "properties": {
    "iso:country":"AU",
    "sg:address":"349 Bloomfield St",
    "sg:city":"Cleveland",
    "sg:classifiers":[
        {
            "category":"Shopping",
            "subcategory":"Clothing, Apparel, & Fashions",
            "type":"Retail Goods"
        }
    ],
    "sg:phone":"+61 7 3821 1562",
    "sg:postcode":"4163",
    "sg:province":"QLD",
    "sg:tags":[
        "uniform"
    ],
    "wof:name":"All Mobile Apparel",
    "wof:placetype":"venue"
},
  "geometry": {"coordinates":[153.26547241200001,-27.5463314056],"type":"Point"}
}