{
  "type": "Feature",
  "properties": {
    "addr:full":"6 York St Beecroft NSW 2119",
    "addr:housenumber":"6",
    "addr:postcode":"2119",
    "addr:street":"York St",
    "iso:country":"AU",
    "sg:address":"6 York St",
    "sg:city":"Beecroft",
    "sg:classifiers":[
        {
            "category":"Health Services",
            "subcategory":"Doctor",
            "type":"Services"
        }
    ],
    "sg:phone":"+61 2 9980 9189",
    "sg:postcode":"2119",
    "sg:province":"NSW",
    "sg:tags":[
        "medical",
        "practitioner"
    ],
    "wof:name":"Pike Anne",
    "wof:placetype":"venue"
},
  "geometry": {"coordinates":[151.061080933,-33.7493286133],"type":"Point"}
}