{
  "type": "Feature",
  "properties": {
    "addr:full":"340 High St Penrith NSW 2750",
    "addr:housenumber":"340",
    "addr:postcode":"2750",
    "addr:street":"High St",
    "iso:country":"AU",
    "sg:address":"340 High St",
    "sg:city":"Penrith",
    "sg:classifiers":[
        {
            "category":"Organizations",
            "subcategory":"Community Association",
            "type":"Services"
        }
    ],
    "sg:phone":"+61 2 4728 4800",
    "sg:postcode":"2750",
    "sg:province":"NSW",
    "sg:tags":[
        "organisation",
        "family",
        "welfare"
    ],
    "wof:name":"Relationships Australia",
    "wof:placetype":"venue"
},
  "geometry": {"coordinates":[150.91558837900001,-33.8947906494],"type":"Point"}
}