{
  "type": "Feature",
  "properties": {
    "iso:country":"AU",
    "sg:address":"PO Box 114",
    "sg:city":"Potts Point",
    "sg:classifiers":[
        {
            "category":"Communications",
            "subcategory":"News Services",
            "type":"Services"
        }
    ],
    "sg:phone":"+61 2 9357 4566",
    "sg:postcode":"1335",
    "sg:province":"NSW",
    "sg:tags":[
        "information",
        "tourist",
        "attractions"
    ],
    "wof:name":"Sydney Movie Tours",
    "wof:placetype":"venue"
},
  "geometry": {"coordinates":[151.223678589,-33.8665313721],"type":"Point"}
}