{
  "type": "Feature",
  "properties": {
    "iso:country":"AU",
    "sg:address":"Lot 1108 Bradmill Ave",
    "sg:city":"Rutherford",
    "sg:classifiers":[
        {
            "category":"Manufacturing",
            "subcategory":"Metals",
            "type":"Manufacturing & Wholesale Goods"
        }
    ],
    "sg:phone":"+61 2 4932 3666",
    "sg:postcode":"2320",
    "sg:province":"NSW",
    "sg:tags":[
        "sheet",
        "worker"
    ],
    "wof:name":"Gibbs Fabrications Pty Ltd",
    "wof:placetype":"venue"
},
  "geometry": {"coordinates":[151.505325317,-32.7127418518],"type":"Point"}
}