{
  "type": "Feature",
  "properties": {
    "addr:full":"Unit 1, 40- 44 Abbott Rd Hallam VIC 3803",
    "addr:housenumber":"40 44",
    "addr:postcode":"3803",
    "addr:street":"Abbott Rd",
    "iso:country":"AU",
    "sg:address":"Unit 1, 40- 44 Abbott Rd",
    "sg:city":"Hallam",
    "sg:classifiers":[
        {
            "category":"Transit Center",
            "subcategory":"Freight",
            "type":"Transportation"
        }
    ],
    "sg:phone":"+61 3 9708 6523",
    "sg:postcode":"3803",
    "sg:province":"VIC",
    "sg:tags":[
        "forklift",
        "truck"
    ],
    "wof:name":"Budget Forks Pty Ltd",
    "wof:placetype":"venue"
},
  "geometry": {"coordinates":[145.267379761,-38.0101089478],"type":"Point"}
}