{
  "type": "Feature",
  "properties": {
    "iso:country":"AU",
    "sg:address":"59 Roderick St",
    "sg:city":"Ipswich",
    "sg:classifiers":[
        {
            "category":"Banks & Credit Unions",
            "subcategory":"Financial Services",
            "type":"Services"
        }
    ],
    "sg:phone":"+61 7 3812 3755",
    "sg:postcode":"4305",
    "sg:province":"QLD",
    "sg:tags":[
        "advisory",
        "planning",
        "retirement"
    ],
    "wof:name":"Advisor Investment Services Ltd",
    "wof:placetype":"venue"
},
  "geometry": {"coordinates":[152.75779724099999,-27.616979599],"type":"Point"}
}