{
  "type": "Feature",
  "properties": {
    "iso:country":"AU",
    "sg:address":"168 Shoalhaven St",
    "sg:city":"Kiama",
    "sg:classifiers":[
        {
            "category":"Education",
            "subcategory":"Kindergarten",
            "type":"Public Place"
        }
    ],
    "sg:phone":"+61 2 4232 2793",
    "sg:postcode":"2533",
    "sg:province":"NSW",
    "sg:tags":[
        "pre-schools"
    ],
    "wof:name":"Kiama Pre-School",
    "wof:placetype":"venue"
},
  "geometry": {"coordinates":[150.84750366200001,-34.6786231995],"type":"Point"}
}