{
  "type": "Feature",
  "properties": {
    "iso:country":"AU",
    "sg:address":"79 Galatea St",
    "sg:city":"Charleville",
    "sg:classifiers":[
        {
            "category":"Professional",
            "subcategory":"Employment Agencies",
            "type":"Services"
        }
    ],
    "sg:phone":"+61 417 797 576",
    "sg:postcode":"4470",
    "sg:province":"QLD",
    "wof:name":"Jobfind Centre",
    "wof:placetype":"venue"
},
  "geometry": {"coordinates":[146.244674683,-26.3994064331],"type":"Point"}
}