{
  "type": "Feature",
  "properties": {
    "addr:full":"Factory 4, 14-26 Audsley St Clayton VIC 3168",
    "addr:housenumber":"4 14-26",
    "addr:postcode":"3168",
    "addr:street":"Audsley St",
    "iso:country":"AU",
    "sg:address":"Factory 4, 14-26 Audsley St",
    "sg:city":"Clayton",
    "sg:classifiers":[
        {
            "category":"Real Estate",
            "subcategory":"Real Estate Operator",
            "type":"Services"
        }
    ],
    "sg:phone":"+61 3 9544 3166",
    "sg:postcode":"3168",
    "sg:province":"VIC",
    "sg:tags":[
        "concrete",
        "pumping"
    ],
    "wof:name":"McMillan Concrete Pumps (Aust)",
    "wof:placetype":"venue"
},
  "geometry": {"coordinates":[145.124755859,-37.899181366],"type":"Point"}
}