{
  "type": "Feature",
  "properties": {
    "iso:country":"AU",
    "sg:address":"19 Murray St",
    "sg:city":"Thebarton",
    "sg:classifiers":[
        {
            "category":"Utilities",
            "subcategory":"Refuse",
            "type":"Services"
        }
    ],
    "sg:phone":"+61 8 8443 8827",
    "sg:postcode":"5031",
    "sg:province":"SA",
    "sg:tags":[
        "disposal",
        "reduction",
        "waste"
    ],
    "wof:name":"Metropolitan Waste Services Pty Ltd",
    "wof:placetype":"venue"
},
  "geometry": {"coordinates":[138.56956481899999,-34.9120254517],"type":"Point"}
}