{
  "type": "Feature",
  "properties": {
    "addr:full":"83 Percy St Portland VIC 3305",
    "addr:housenumber":"83",
    "addr:postcode":"3305",
    "addr:street":"Percy St",
    "iso:country":"AU",
    "sg:address":"83 Percy St",
    "sg:city":"Portland",
    "sg:classifiers":[
        {
            "category":"Banks & Credit Unions",
            "subcategory":"Bank",
            "type":"Services"
        }
    ],
    "sg:phone":"+61 3 5523 3107",
    "sg:postcode":"3305",
    "sg:province":"VIC",
    "wof:name":"Bendigo Bank",
    "wof:placetype":"venue"
},
  "geometry": {"coordinates":[141.60357665999999,-38.3461532593],"type":"Point"}
}