{
  "type": "Feature",
  "properties": {
    "iso:country":"AU",
    "sg:address":"61 Lords Pl",
    "sg:city":"Warrendine",
    "sg:classifiers":[
        {
            "category":"Building & Trades",
            "subcategory":"Construction",
            "type":"Services"
        }
    ],
    "sg:phone":"+61 2 6361 4408",
    "sg:postcode":"2800",
    "sg:province":"NSW",
    "sg:tags":[
        "contractor"
    ],
    "wof:name":"Crestway Constructions Pty Ltd",
    "wof:placetype":"venue"
},
  "geometry": {"coordinates":[149.098846436,-33.2963981628],"type":"Point"}
}