{
  "type": "Feature",
  "properties": {
    "iso:country":"AU",
    "sg:address":"12 Somer St",
    "sg:city":"Hyde Park",
    "sg:classifiers":[
        {
            "category":"Home & Garden",
            "subcategory":"Building Materials",
            "type":"Retail Goods"
        }
    ],
    "sg:phone":"+61 7 4772 2936",
    "sg:postcode":"4812",
    "sg:province":"QLD",
    "sg:tags":[
        "fitting",
        "door"
    ],
    "wof:name":"The Door Shop",
    "wof:placetype":"venue"
},
  "geometry": {"coordinates":[146.800781,-19.273558],"type":"Point"}
}