{
  "type": "Feature",
  "properties": {
    "iso:country":"AU",
    "sg:address":"14 Edgeworth David Ave",
    "sg:city":"Hornsby",
    "sg:classifiers":[
        {
            "category":"Health Services",
            "subcategory":"Doctor",
            "type":"Services"
        }
    ],
    "sg:phone":"+61 2 9476 5377",
    "sg:postcode":"2077",
    "sg:province":"NSW",
    "sg:tags":[
        "medical",
        "practitioner"
    ],
    "wof:name":"Collett Paul V",
    "wof:placetype":"venue"
},
  "geometry": {"coordinates":[151.099212647,-33.7055358887],"type":"Point"}
}