{
  "type": "Feature",
  "properties": {
    "addr:full":"18 Boulder Rd Malaga WA 6090",
    "addr:housenumber":"18",
    "addr:postcode":"6090",
    "addr:street":"Boulder Rd",
    "iso:country":"AU",
    "sg:address":"18 Boulder Rd",
    "sg:city":"Malaga",
    "sg:classifiers":[
        {
            "category":"Home & Garden",
            "subcategory":"Furniture",
            "type":"Retail Goods"
        }
    ],
    "sg:phone":"+61 8 9249 9500",
    "sg:postcode":"6090",
    "sg:province":"WA",
    "sg:tags":[
        "business"
    ],
    "wof:name":"Furniture Decor",
    "wof:placetype":"venue"
},
  "geometry": {"coordinates":[115.90180206300001,-31.8649406433],"type":"Point"}
}