{
  "type": "Feature",
  "properties": {
    "addr:full":"280 Oakleys Rd Yeo VIC 3249",
    "addr:housenumber":"280",
    "addr:postcode":"3249",
    "addr:street":"Oakleys Rd",
    "iso:country":"AU",
    "sg:address":"280 Oakleys Rd",
    "sg:city":"Yeo",
    "sg:classifiers":[
        {
            "category":"Building & Trades",
            "subcategory":"Construction",
            "type":"Services"
        }
    ],
    "sg:phone":"+61 3 5233 4521",
    "sg:postcode":"3249",
    "sg:province":"VIC",
    "sg:tags":[
        "fencing",
        "contractor"
    ],
    "wof:name":"Potter Fencing",
    "wof:placetype":"venue"
},
  "geometry": {"coordinates":[143.63551330600001,-38.3920707703],"type":"Point"}
}