{
  "type": "Feature",
  "properties": {
    "addr:full":"12 Bent St South Grafton NSW 2460",
    "addr:housenumber":"12",
    "addr:postcode":"2460",
    "addr:street":"Bent St",
    "iso:country":"AU",
    "sg:address":"12 Bent St",
    "sg:city":"South Grafton",
    "sg:classifiers":[
        {
            "category":"Health Services",
            "subcategory":"Nursing And Care Facility",
            "type":"Services"
        }
    ],
    "sg:phone":"+61 2 6642 3255",
    "sg:postcode":"2460",
    "sg:province":"NSW",
    "sg:tags":[
        "home"
    ],
    "wof:name":"Grafton Aged Care Home",
    "wof:placetype":"venue"
},
  "geometry": {"coordinates":[152.94229125999999,-29.7011260986],"type":"Point"}
}