{
  "type": "Feature",
  "properties": {
    "addr:full":"7 Lewisham Crt Birkdale QLD 4159",
    "addr:housenumber":"7",
    "addr:postcode":"4159",
    "addr:street":"Lewisham Crt",
    "iso:country":"AU",
    "sg:address":"7 Lewisham Crt",
    "sg:city":"Birkdale",
    "sg:classifiers":[
        {
            "category":"Utilities",
            "subcategory":"Electric",
            "type":"Services"
        }
    ],
    "sg:phone":"+61 418 886 832",
    "sg:postcode":"4159",
    "sg:province":"QLD",
    "sg:tags":[
        "electrical",
        "contractor"
    ],
    "wof:name":"Stewart Doug",
    "wof:placetype":"venue"
},
  "geometry": {"coordinates":[153.19969177199999,-27.4945983887],"type":"Point"}
}