{
  "type": "Feature",
  "properties": {
    "addr:full":"259 Albany Hwy Bedfordale WA 6112",
    "addr:housenumber":"259",
    "addr:postcode":"6112",
    "addr:street":"Albany Hwy",
    "iso:country":"AU",
    "sg:address":"259 Albany Hwy",
    "sg:city":"Bedfordale",
    "sg:classifiers":[
        {
            "category":"Professional",
            "subcategory":"Engineering",
            "type":"Services"
        }
    ],
    "sg:phone":"+61 417 913 202",
    "sg:postcode":"6112",
    "sg:province":"WA",
    "sg:tags":[
        "consulting",
        "engineer"
    ],
    "wof:name":"M.D.C. Engineers Pty Ltd",
    "wof:placetype":"venue"
},
  "geometry": {"coordinates":[116.084213257,-32.1829872131],"type":"Point"}
}