{
  "type": "Feature",
  "properties": {
    "addr:full":"5 Joyce Ave Wyoming NSW 2250",
    "addr:housenumber":"5",
    "addr:postcode":"2250",
    "addr:street":"Joyce Ave",
    "iso:country":"AU",
    "sg:address":"5 Joyce Ave",
    "sg:city":"Wyoming",
    "sg:classifiers":[
        {
            "category":"Taxi",
            "type":"Transportation"
        }
    ],
    "sg:phone":"+61 2 4329 4641",
    "sg:postcode":"2250",
    "sg:province":"NSW",
    "sg:tags":[
        "truck"
    ],
    "wof:name":"Smooth Riders Removals & Carriers",
    "wof:placetype":"venue"
},
  "geometry": {"coordinates":[151.358810425,-33.402759552],"type":"Point"}
}