{
  "type": "Feature",
  "properties": {
    "addr:full":"6 Gipps St Collingwood VIC 3066",
    "addr:housenumber":"6",
    "addr:postcode":"3066",
    "addr:street":"Gipps St",
    "iso:country":"AU",
    "sg:address":"6 Gipps St",
    "sg:city":"Collingwood",
    "sg:classifiers":[
        {
            "category":"Shopping",
            "subcategory":"Computers & Home Electronics",
            "type":"Retail Goods"
        }
    ],
    "sg:phone":"+61 3 9416 1855",
    "sg:postcode":"3066",
    "sg:province":"VIC",
    "sg:tags":[
        "hardware",
        "equipment"
    ],
    "wof:name":"Carr Marshall Day Associates Pty Ltd",
    "wof:placetype":"venue"
},
  "geometry": {"coordinates":[144.98675537099999,-37.8043212891],"type":"Point"}
}