{
  "type": "Feature",
  "properties": {
    "iso:country":"AU",
    "sg:address":"Orient Rd",
    "sg:city":"Yeronga",
    "sg:classifiers":[
        {
            "category":"Health Services",
            "subcategory":"Health Practitioner",
            "type":"Services"
        }
    ],
    "sg:phone":"+61 7 3342 4258",
    "sg:postcode":"4104",
    "sg:province":"QLD",
    "sg:tags":[
        "psychologist"
    ],
    "wof:name":"Hannah, Jacqueline (Clinical Psychologist)",
    "wof:placetype":"venue"
},
  "geometry": {"coordinates":[153.00747680699999,-27.5082702637],"type":"Point"}
}