{
  "type": "Feature",
  "properties": {
    "addr:full":"448 Flinders St Townsville QLD 4810",
    "addr:housenumber":"448",
    "addr:postcode":"4810",
    "addr:street":"Flinders St",
    "iso:country":"AU",
    "sg:address":"448 Flinders St",
    "sg:city":"Townsville",
    "sg:classifiers":[
        {
            "category":"Organizations",
            "subcategory":"Community Association",
            "type":"Services"
        }
    ],
    "sg:phone":"+61 7 4721 5011",
    "sg:postcode":"4810",
    "sg:province":"QLD",
    "sg:tags":[
        "organisation",
        "family",
        "welfare"
    ],
    "wof:name":"Townsville Housing Resource Unit Inc.",
    "wof:placetype":"venue"
},
  "geometry": {"coordinates":[146.809494,-19.266823],"type":"Point"}
}