{
  "type": "Feature",
  "properties": {
    "addr:full":"72 Nicholson St Dalby QLD 4405",
    "addr:housenumber":"72",
    "addr:postcode":"4405",
    "addr:street":"Nicholson St",
    "iso:country":"AU",
    "sg:address":"72 Nicholson St",
    "sg:city":"Dalby",
    "sg:classifiers":[
        {
            "category":"Personal",
            "subcategory":"Beauty Salon",
            "type":"Services"
        }
    ],
    "sg:phone":"+61 7 4669 6404",
    "sg:postcode":"4405",
    "sg:province":"QLD",
    "sg:tags":[
        "hairdresser"
    ],
    "wof:name":"Beydo Hair & Beauty Salon",
    "wof:placetype":"venue"
},
  "geometry": {"coordinates":[151.24809265100001,-27.1870250702],"type":"Point"}
}