{
  "type": "Feature",
  "properties": {
    "addr:full":"RMB 9275 Lake Sadie North Rd Youngs Siding WA 6330",
    "addr:postcode":"6330",
    "addr:street":"Lake Sadie North Rd",
    "iso:country":"AU",
    "sg:address":"RMB 9275 Lake Sadie North Rd",
    "sg:city":"Youngs Siding",
    "sg:classifiers":[
        {
            "category":"Health Services",
            "subcategory":"Medical Lab",
            "type":"Services"
        }
    ],
    "sg:phone":"+61 8 9845 2072",
    "sg:postcode":"6330",
    "sg:province":"WA",
    "sg:tags":[
        "laboratory",
        "dental"
    ],
    "wof:name":"South Coast Dental Laboratory",
    "wof:placetype":"venue"
},
  "geometry": {"coordinates":[117.867279053,-35.0037002563],"type":"Point"}
}