{
  "type": "Feature",
  "properties": {
    "addr:full":"4 Raaen Rd Rush Creek QLD 4521",
    "addr:housenumber":"4",
    "addr:postcode":"4521",
    "addr:street":"Raaen Rd Rush",
    "iso:country":"AU",
    "sg:address":"4 Raaen Rd",
    "sg:city":"Rush Creek",
    "sg:classifiers":[
        {
            "category":"Home & Garden",
            "subcategory":"Furniture",
            "type":"Retail Goods"
        }
    ],
    "sg:phone":"+61 7 3425 2375",
    "sg:postcode":"4521",
    "sg:province":"QLD",
    "sg:tags":[
        "outdoor"
    ],
    "wof:name":"Platypus Furniture",
    "wof:placetype":"venue"
},
  "geometry": {"coordinates":[152.860107,-27.19253],"type":"Point"}
}