{
  "type": "Feature",
  "properties": {
    "addr:full":"96- 98 Frome St Adelaide SA 5000",
    "addr:housenumber":"98",
    "addr:postcode":"5000",
    "addr:street":"Frome St",
    "iso:country":"AU",
    "sg:address":"96- 98 Frome St",
    "sg:city":"Adelaide",
    "sg:classifiers":[
        {
            "category":"Professional",
            "subcategory":"Employment Agencies",
            "type":"Services"
        }
    ],
    "sg:phone":"+61 13 14 48",
    "sg:postcode":"5000",
    "sg:province":"SA",
    "sg:tags":[
        "hire",
        "labour",
        "contractor"
    ],
    "wof:name":"Drake",
    "wof:placetype":"venue"
},
  "geometry": {"coordinates":[138.60191345199999,-34.9253997803],"type":"Point"}
}