{
  "type": "Feature",
  "properties": {
    "iso:country":"AU",
    "sg:address":"22 Bank St",
    "sg:city":"Cobram",
    "sg:classifiers":[
        {
            "category":"Communications",
            "subcategory":"Film & Video Production",
            "type":"Services"
        }
    ],
    "sg:phone":"+61 3 5871 2500",
    "sg:postcode":"3644",
    "sg:province":"VIC",
    "sg:tags":[
        "dvd",
        "library"
    ],
    "wof:name":"Top Video",
    "wof:placetype":"venue"
},
  "geometry": {"coordinates":[145.650115967,-35.9197158813],"type":"Point"}
}