{
  "type": "Feature",
  "properties": {
    "iso:country":"AU",
    "sg:address":"39 Seven Mile Rd",
    "sg:city":"Trafalgar",
    "sg:classifiers":[
        {
            "category":"Retail",
            "subcategory":"Auto Repair",
            "type":"Services"
        }
    ],
    "sg:phone":"+61 3 5633 1206",
    "sg:postcode":"3824",
    "sg:province":"VIC",
    "sg:tags":[
        "repairer",
        "motor",
        "engineer"
    ],
    "wof:name":"Quigley Autos",
    "wof:placetype":"venue"
},
  "geometry": {"coordinates":[146.15469400000001,-38.217781],"type":"Point"}
}