{
  "type": "Feature",
  "properties": {
    "addr:full":"The Arcade East St Rockhampton QLD 4700",
    "addr:postcode":"4700",
    "addr:street":"East St",
    "iso:country":"AU",
    "sg:address":"The Arcade East St",
    "sg:city":"Rockhampton",
    "sg:classifiers":[
        {
            "category":"Shopping",
            "subcategory":"Clothing, Apparel, & Fashions",
            "type":"Retail Goods"
        }
    ],
    "sg:phone":"+61 7 4922 5587",
    "sg:postcode":"4700",
    "sg:province":"QLD",
    "sg:tags":[
        "lady",
        "wear"
    ],
    "wof:name":"Cooper's Fashions",
    "wof:placetype":"venue"
},
  "geometry": {"coordinates":[150.523925781,-23.3924942017],"type":"Point"}
}