{
  "type": "Feature",
  "properties": {
    "addr:full":"Cnr West Moreland & Phoenix Sts Sunshine VIC 3020",
    "addr:postcode":"3020",
    "addr:street":"Cnr West",
    "iso:country":"AU",
    "sg:address":"Cnr West Moreland & Phoenix Sts",
    "sg:city":"Sunshine",
    "sg:classifiers":[
        {
            "category":"Organizations",
            "subcategory":"Non-profit Organization",
            "type":"Services"
        }
    ],
    "sg:phone":"+61 3 9284 7272",
    "sg:postcode":"3020",
    "sg:province":"VIC",
    "sg:tags":[
        "support",
        "disability",
        "organisation"
    ],
    "wof:name":"WestArc- Early Childhood Intervention Program & Family Resource",
    "wof:placetype":"venue"
},
  "geometry": {"coordinates":[144.841263,-37.776577],"type":"Point"}
}