{
  "type": "Feature",
  "properties": {
    "addr:full":"3- 7 Stoke St Branxholm TAS 7261",
    "addr:housenumber":"7",
    "addr:postcode":"7261",
    "addr:street":"Stoke St",
    "iso:country":"AU",
    "sg:address":"3- 7 Stoke St",
    "sg:city":"Branxholm",
    "sg:classifiers":[
        {
            "category":"Travel",
            "subcategory":"Hotels & Motels",
            "type":"Entertainment"
        }
    ],
    "sg:phone":"+61 3 6354 6121",
    "sg:postcode":"7261",
    "sg:province":"TAS",
    "sg:tags":[
        "accommodation"
    ],
    "wof:name":"Branxholm Hotel",
    "wof:placetype":"venue"
},
  "geometry": {"coordinates":[147.73635864299999,-41.1676483154],"type":"Point"}
}