{
  "type": "Feature",
  "properties": {
    "iso:country":"AU",
    "sg:address":"1362 Old North Rd",
    "sg:city":"Bray Park",
    "sg:classifiers":[
        {
            "category":"Arts & Performance",
            "subcategory":"Dance",
            "type":"Entertainment"
        }
    ],
    "sg:phone":"+61 7 3882 1840",
    "sg:postcode":"4500",
    "sg:province":"QLD",
    "sg:tags":[
        "theatrical",
        "ballet",
        "tuition"
    ],
    "wof:name":"Kathy Gilmour",
    "wof:placetype":"venue"
},
  "geometry": {"coordinates":[152.95628356899999,-27.2941703796],"type":"Point"}
}