{
  "type": "Feature",
  "properties": {
    "iso:country":"AU",
    "sg:address":"46 Mill St",
    "sg:city":"Krambach",
    "sg:classifiers":[
        {
            "category":"Home & Garden",
            "subcategory":"Carpets & Floor Coverings",
            "type":"Retail Goods"
        }
    ],
    "sg:phone":"+61 2 6559 1302",
    "sg:postcode":"2429",
    "sg:province":"NSW",
    "sg:tags":[
        "tile",
        "wall",
        "layer"
    ],
    "wof:name":"John Holtmeulen Wall & Floor Tiling",
    "wof:placetype":"venue"
},
  "geometry": {"coordinates":[152.4142,-31.932096],"type":"Point"}
}