{
  "type": "Feature",
  "properties": {
    "iso:country":"AU",
    "sg:address":"28 Greenway Ave",
    "sg:city":"Shalvey",
    "sg:classifiers":[
        {
            "category":"Retail",
            "subcategory":"Auto Repair",
            "type":"Services"
        }
    ],
    "sg:phone":"+61 407 435 238",
    "sg:postcode":"2770",
    "sg:province":"NSW",
    "sg:tags":[
        "repairer",
        "motor",
        "engineer"
    ],
    "wof:name":"Mobile Auto Surgery",
    "wof:placetype":"venue"
},
  "geometry": {"coordinates":[150.81106567399999,-33.7275543213],"type":"Point"}
}