{
  "type": "Feature",
  "properties": {
    "addr:full":"84 Murdock Rd Wangaratta VIC 3677",
    "addr:housenumber":"84",
    "addr:postcode":"3677",
    "addr:street":"Murdock Rd",
    "iso:country":"AU",
    "sg:address":"84 Murdock Rd",
    "sg:city":"Wangaratta",
    "sg:classifiers":[
        {
            "category":"Retail",
            "subcategory":"Event Space",
            "type":"Services"
        }
    ],
    "sg:phone":"+61 3 5722 4664",
    "sg:postcode":"3677",
    "sg:province":"VIC",
    "sg:tags":[
        "venue",
        "reception",
        "wedding"
    ],
    "wof:name":"Zippis Licensed Catering",
    "wof:placetype":"venue"
},
  "geometry": {"coordinates":[146.32223510700001,-36.3706741333],"type":"Point"}
}