{
  "type": "Feature",
  "properties": {
    "addr:full":"21 Welwyn Ave Manning WA 6152",
    "addr:housenumber":"21",
    "addr:postcode":"6152",
    "addr:street":"Welwyn Ave",
    "iso:country":"AU",
    "sg:address":"21 Welwyn Ave",
    "sg:city":"Manning",
    "sg:classifiers":[
        {
            "category":"Food & Beverages",
            "subcategory":"Bakery",
            "type":"Retail Goods"
        }
    ],
    "sg:phone":"+61 8 9313 4099",
    "sg:postcode":"6152",
    "sg:province":"WA",
    "sg:tags":[
        "baker"
    ],
    "wof:name":"Festival Cafe & Bakery",
    "wof:placetype":"venue"
},
  "geometry": {"coordinates":[115.868584,-32.015095],"type":"Point"}
}