{
  "type": "Feature",
  "properties": {
    "addr:full":"Colonnades Shopping Centre Beach Rd Noarlunga Centre SA 5168",
    "addr:postcode":"5168",
    "addr:street":"Beach Rd",
    "iso:country":"AU",
    "sg:address":"Colonnades Shopping Centre Beach Rd",
    "sg:city":"Noarlunga Centre",
    "sg:classifiers":[
        {
            "category":"Personal",
            "subcategory":"Beauty Salon",
            "type":"Services"
        }
    ],
    "sg:phone":"+61 8 8186 4114",
    "sg:postcode":"5168",
    "sg:province":"SA",
    "wof:name":"Body Magic",
    "wof:placetype":"venue"
},
  "geometry": {"coordinates":[138.49281310999999,-35.1405487061],"type":"Point"}
}