{
  "type": "Feature",
  "properties": {
    "addr:full":"156 Rickertt Rd Ransome QLD 4154",
    "addr:housenumber":"156",
    "addr:postcode":"4154",
    "addr:street":"Rickertt Rd",
    "iso:country":"AU",
    "sg:address":"156 Rickertt Rd",
    "sg:city":"Ransome",
    "sg:classifiers":[
        {
            "category":"Building & Trades",
            "subcategory":"Construction",
            "type":"Services"
        }
    ],
    "sg:phone":"+61 7 3245 7172",
    "sg:postcode":"4154",
    "sg:province":"QLD",
    "sg:tags":[
        "equipment",
        "system",
        "automation"
    ],
    "wof:name":"Hextec Integration Pty Ltd",
    "wof:placetype":"venue"
},
  "geometry": {"coordinates":[153.17645263700001,-27.4856758118],"type":"Point"}
}