{
  "type": "Feature",
  "properties": {
    "addr:full":"Shop 1123, Innaloo Shopping Centre, Scarborough Beach Rd Innaloo WA 6018",
    "addr:housenumber":"1123",
    "addr:postcode":"6018",
    "addr:street":"Innaloo Shopping;Beach Rd",
    "iso:country":"AU",
    "sg:address":"Shop 1123, Innaloo Shopping Centre, Scarborough Beach Rd",
    "sg:city":"Innaloo",
    "sg:classifiers":[
        {
            "category":"Food & Beverages",
            "subcategory":"Bakery",
            "type":"Retail Goods"
        }
    ],
    "sg:phone":"+61 8 9244 9300",
    "sg:postcode":"6018",
    "sg:province":"WA",
    "sg:tags":[
        "baker"
    ],
    "wof:name":"Bakers Delight",
    "wof:placetype":"venue"
},
  "geometry": {"coordinates":[115.78749084499999,-31.8992271423],"type":"Point"}
}