{
  "type": "Feature",
  "properties": {
    "iso:country":"AU",
    "sg:address":"Lvl 2/ 12 Laycock Ave",
    "sg:city":"Cronulla",
    "sg:classifiers":[
        {
            "category":"Sports & Exercise",
            "subcategory":"Gym",
            "type":"Entertainment"
        }
    ],
    "sg:phone":"+61 2 9544 5772",
    "sg:postcode":"2230",
    "sg:province":"NSW",
    "sg:tags":[
        "personal",
        "trainer",
        "fitness"
    ],
    "wof:name":"Cronulla Personal Training Pty Ltd",
    "wof:placetype":"venue"
},
  "geometry": {"coordinates":[151.15238952600001,-34.0568962097],"type":"Point"}
}