{
  "type": "Feature",
  "properties": {
    "addr:full":"179 Prince Edward Ave Culburra NSW 2540",
    "addr:housenumber":"179",
    "addr:postcode":"2540",
    "addr:street":"Prince Edward Ave",
    "iso:country":"AU",
    "sg:address":"179 Prince Edward Ave",
    "sg:city":"Culburra",
    "sg:classifiers":[
        {
            "category":"Health Services",
            "subcategory":"Dentist",
            "type":"Services"
        }
    ],
    "sg:phone":"+61 2 4447 2310",
    "sg:postcode":"2540",
    "sg:province":"NSW",
    "wof:name":"Culburra Dental Clinic",
    "wof:placetype":"venue"
},
  "geometry": {"coordinates":[150.757125855,-34.930721283],"type":"Point"}
}