{
  "type": "Feature",
  "properties": {
    "addr:full":"4 Hunt St Forest Hill QLD 4342",
    "addr:housenumber":"4",
    "addr:postcode":"4342",
    "addr:street":"Hunt St",
    "iso:country":"AU",
    "sg:address":"4 Hunt St",
    "sg:city":"Forest Hill",
    "sg:classifiers":[
        {
            "category":"Building & Trades",
            "subcategory":"Construction",
            "type":"Services"
        }
    ],
    "sg:phone":"+61 7 5465 4228",
    "sg:postcode":"4342",
    "sg:province":"QLD",
    "sg:tags":[
        "fitting",
        "line",
        "electric",
        "power"
    ],
    "wof:name":"Van De Weyer M J & J M",
    "wof:placetype":"venue"
},
  "geometry": {"coordinates":[152.35801696799999,-27.5887203217],"type":"Point"}
}