{
  "type": "Feature",
  "properties": {
    "addr:full":"605 Thompson Rd Lyndhurst VIC 3975",
    "addr:housenumber":"605",
    "addr:postcode":"3975",
    "addr:street":"Thompson Rd",
    "iso:country":"AU",
    "sg:address":"605 Thompson Rd",
    "sg:city":"Lyndhurst",
    "sg:classifiers":[
        {
            "category":"Wholesale",
            "subcategory":"Plants",
            "type":"Manufacturing & Wholesale Goods"
        }
    ],
    "sg:phone":"+61 3 9788 9700",
    "sg:postcode":"3975",
    "sg:province":"VIC",
    "sg:tags":[
        "florist"
    ],
    "wof:name":"Van Wyk Flowers",
    "wof:placetype":"venue"
},
  "geometry": {"coordinates":[145.206863403,-38.0733299255],"type":"Point"}
}