{
  "type": "Feature",
  "properties": {
    "addr:full":"61 Woodroffe Ave Woodroffe NT 0830",
    "addr:housenumber":"61",
    "addr:postcode":"nt 0830",
    "addr:street":"Woodroffe Ave",
    "iso:country":"AU",
    "sg:address":"61 Woodroffe Ave",
    "sg:city":"Woodroffe",
    "sg:classifiers":[
        {
            "category":"Social Services",
            "subcategory":"Child Care",
            "type":"Services"
        }
    ],
    "sg:phone":"+61 8 8932 1861",
    "sg:postcode":"0830",
    "sg:province":"NT",
    "wof:name":"Preeti Kunj Child Care Centre",
    "wof:placetype":"venue"
},
  "geometry": {"coordinates":[130.98026999999999,-12.507801],"type":"Point"}
}