{
  "type": "Feature",
  "properties": {
    "iso:country":"AU",
    "sg:address":"268 Main North Rd",
    "sg:city":"Prospect",
    "sg:classifiers":[
        {
            "category":"Shopping",
            "subcategory":"Pawn Shop",
            "type":"Retail Goods"
        }
    ],
    "sg:phone":"+61 8 8269 2885",
    "sg:postcode":"5082",
    "sg:province":"SA",
    "sg:tags":[
        "pawnbroker"
    ],
    "wof:name":"Ace Pawnbrokers",
    "wof:placetype":"venue"
},
  "geometry": {"coordinates":[138.602386475,-34.8823242188],"type":"Point"}
}