{
  "type": "Feature",
  "properties": {
    "addr:full":"21 Speets Rd Oakville NSW 2765",
    "addr:housenumber":"21",
    "addr:postcode":"2765",
    "addr:street":"Speets Rd",
    "iso:country":"AU",
    "sg:address":"21 Speets Rd",
    "sg:city":"Oakville",
    "sg:classifiers":[
        {
            "category":"Building & Trades",
            "subcategory":"Construction",
            "type":"Services"
        }
    ],
    "sg:phone":"+61 2 9627 5797",
    "sg:postcode":"2765",
    "sg:province":"NSW",
    "sg:tags":[
        "contractor"
    ],
    "wof:name":"Jenny Hanckel Beauty Salon",
    "wof:placetype":"venue"
},
  "geometry": {"coordinates":[150.87971496599999,-33.6259765625],"type":"Point"}
}