{
  "type": "Feature",
  "properties": {
    "iso:country":"AU",
    "sg:address":"47 Hockings St",
    "sg:city":"Clayfield",
    "sg:classifiers":[
        {
            "category":"Health Services",
            "subcategory":"Dentist",
            "type":"Services"
        }
    ],
    "sg:phone":"+61 7 3862 2430",
    "sg:postcode":"4011",
    "sg:province":"QLD",
    "sg:tags":[
        "equipment",
        "dental",
        "repair"
    ],
    "wof:name":"Intronics Pty Ltd",
    "wof:placetype":"venue"
},
  "geometry": {"coordinates":[153.055389,-27.413023],"type":"Point"}
}