{
  "type": "Feature",
  "properties": {
    "addr:full":"Runaway Bay Shopping Village Shop 62 (Coles End) L Runaway Bay QLD 4216",
    "addr:housenumber":"62",
    "addr:postcode":"4216",
    "addr:street":"Coles End L",
    "iso:country":"AU",
    "sg:address":"Runaway Bay Shopping Village Shop 62 (Coles End) L",
    "sg:city":"Runaway Bay",
    "sg:classifiers":[
        {
            "category":"Health Services",
            "subcategory":"Optometrist",
            "type":"Services"
        }
    ],
    "sg:phone":"+61 7 5528 8700",
    "sg:postcode":"4216",
    "sg:province":"QLD",
    "wof:name":"McMahon Christopher Optometrist",
    "wof:placetype":"venue"
},
  "geometry": {"coordinates":[153.397827148,-27.9126167297],"type":"Point"}
}