{
  "type": "Feature",
  "properties": {
    "iso:country":"AU",
    "sg:address":"First Floor 137 Macquarie St",
    "sg:city":"Hobart",
    "sg:classifiers":[
        {
            "category":"Personal",
            "subcategory":"Beauty Salon",
            "type":"Services"
        }
    ],
    "sg:phone":"+61 438 610 920",
    "sg:postcode":"7000",
    "sg:province":"TAS",
    "sg:tags":[
        "wig",
        "hairpiece"
    ],
    "wof:name":"Ken Dowling Hair Fusion & Hair Replacement Centre",
    "wof:placetype":"venue"
},
  "geometry": {"coordinates":[147.32801818900001,-42.8842430115],"type":"Point"}
}