{
  "type": "Feature",
  "properties": {
    "addr:full":"Suite 1, 379 Sydney Rd Balgowlah NSW 2093",
    "addr:housenumber":"379",
    "addr:postcode":"2093",
    "addr:street":"Sydney Rd",
    "iso:country":"AU",
    "sg:address":"Suite 1, 379 Sydney Rd",
    "sg:city":"Balgowlah",
    "sg:classifiers":[
        {
            "category":"Health Services",
            "subcategory":"Doctor",
            "type":"Services"
        }
    ],
    "sg:phone":"+61 2 9907 8588",
    "sg:postcode":"2093",
    "sg:province":"NSW",
    "sg:tags":[
        "medical",
        "practitioner"
    ],
    "wof:name":"Beard David Dr",
    "wof:placetype":"venue"
},
  "geometry": {"coordinates":[151.26417541500001,-33.7943687439],"type":"Point"}
}