{
  "type": "Feature",
  "properties": {
    "iso:country":"AU",
    "sg:address":"41 McKeon St",
    "sg:city":"Maroubra",
    "sg:classifiers":[
        {
            "category":"Personal",
            "subcategory":"Massage",
            "type":"Services"
        }
    ],
    "sg:phone":"+61 2 9344 8999",
    "sg:postcode":"2035",
    "sg:province":"NSW",
    "sg:tags":[
        "therapy"
    ],
    "wof:name":"Angel Face & Body Therapy",
    "wof:placetype":"venue"
},
  "geometry": {"coordinates":[151.256103516,-33.9461746216],"type":"Point"}
}