{
  "type": "Feature",
  "properties": {
    "addr:full":"1/ 18 Endeavour Rd Caringbah NSW 2229",
    "addr:housenumber":"/ 18",
    "addr:postcode":"2229",
    "addr:street":"Endeavour Rd",
    "iso:country":"AU",
    "sg:address":"1/ 18 Endeavour Rd",
    "sg:city":"Caringbah",
    "sg:classifiers":[
        {
            "category":"Building & Trades",
            "subcategory":"Locksmith",
            "type":"Services"
        }
    ],
    "sg:phone":"+61 2 9540 5022",
    "sg:postcode":"2229",
    "sg:province":"NSW",
    "sg:tags":[
        "equipment",
        "operating",
        "door",
        "gate"
    ],
    "wof:name":"Graham Day Garage Doors Pty Ltd",
    "wof:placetype":"venue"
},
  "geometry": {"coordinates":[151.13142395,-34.0340461731],"type":"Point"}
}