{
  "type": "Feature",
  "properties": {
    "iso:country":"AU",
    "sg:address":"433 Beamish St",
    "sg:city":"Campsie",
    "sg:classifiers":[
        {
            "category":"Professional",
            "subcategory":"Accounting & Tax Preparation",
            "type":"Services"
        }
    ],
    "sg:phone":"+61 2 9789 6911",
    "sg:postcode":"2194",
    "sg:province":"NSW",
    "sg:tags":[
        "accountant",
        "auditor"
    ],
    "wof:name":"Velmar Enterprises Pty Ltd",
    "wof:placetype":"venue"
},
  "geometry": {"coordinates":[151.104477,-33.917461],"type":"Point"}
}