{
  "type": "Feature",
  "properties": {
    "addr:full":"39 Hillville Rd Tinonee NSW 2430",
    "addr:housenumber":"39",
    "addr:postcode":"2430",
    "addr:street":"Hillville Rd",
    "iso:country":"AU",
    "sg:address":"39 Hillville Rd",
    "sg:city":"Tinonee",
    "sg:classifiers":[
        {
            "category":"Arts & Performance",
            "subcategory":"Music",
            "type":"Entertainment"
        }
    ],
    "sg:phone":"+61 434 005 406",
    "sg:postcode":"2430",
    "sg:province":"NSW",
    "sg:tags":[
        "mobile",
        "jockey",
        "disc"
    ],
    "wof:name":"Dan&#039;z Mobile Disco",
    "wof:placetype":"venue"
},
  "geometry": {"coordinates":[152.411102,-31.938881],"type":"Point"}
}