{
  "type": "Feature",
  "properties": {
    "addr:full":"57 Whaelan Ave Chipping Norton NSW 2170",
    "addr:housenumber":"57",
    "addr:postcode":"2170",
    "addr:street":"Whaelan Ave",
    "iso:country":"AU",
    "sg:address":"57 Whaelan Ave",
    "sg:city":"Chipping Norton",
    "sg:classifiers":[
        {
            "category":"Manufacturing",
            "subcategory":"Textiles",
            "type":"Manufacturing & Wholesale Goods"
        }
    ],
    "sg:phone":"+61 2 9824 1322",
    "sg:postcode":"2170",
    "sg:province":"NSW",
    "sg:tags":[
        "machinery"
    ],
    "wof:name":"PHM (NSW) Pty Ltd",
    "wof:placetype":"venue"
},
  "geometry": {"coordinates":[150.94464111299999,-33.9249153137],"type":"Point"}
}