{
  "type": "Feature",
  "properties": {
    "iso:country":"AU",
    "sg:address":"507 Crown St",
    "sg:city":"Surry Hills",
    "sg:classifiers":[
        {
            "category":"Banks & Credit Unions",
            "subcategory":"Financial Services",
            "type":"Services"
        }
    ],
    "sg:phone":"+61 2 9319 1322",
    "sg:postcode":"2010",
    "sg:province":"NSW",
    "sg:tags":[
        "loan",
        "finance",
        "mortgage"
    ],
    "wof:name":"Wizard",
    "wof:placetype":"venue"
},
  "geometry": {"coordinates":[151.21321105999999,-33.8886833191],"type":"Point"}
}