{
  "type": "Feature",
  "properties": {
    "addr:full":"1401 Malvern Rd Malvern VIC 3144",
    "addr:housenumber":"1401",
    "addr:postcode":"3144",
    "addr:street":"Malvern Rd",
    "iso:country":"AU",
    "sg:address":"1401 Malvern Rd",
    "sg:city":"Malvern",
    "sg:classifiers":[
        {
            "category":"Shopping",
            "subcategory":"Bicycles & Sporting Goods",
            "type":"Retail Goods"
        }
    ],
    "sg:phone":"+61 3 9822 3200",
    "sg:postcode":"3144",
    "sg:province":"VIC",
    "sg:tags":[
        "chemical",
        "equipment",
        "pool",
        "swimming"
    ],
    "sg:website":"http://www.dpsc.com.au",
    "wof:name":"The Diamond Pool & Spa Co. Pty. Ltd.",
    "wof:placetype":"venue"
},
  "geometry": {"coordinates":[145.04071044899999,-37.8528747559],"type":"Point"}
}