{
  "type": "Feature",
  "properties": {
    "addr:full":"Unit 3/ 12 King Edward Rd Osborne Park WA 6017",
    "addr:housenumber":"12",
    "addr:postcode":"6017",
    "addr:street":"King Edward Rd",
    "iso:country":"AU",
    "sg:address":"Unit 3/ 12 King Edward Rd",
    "sg:city":"Osborne Park",
    "sg:classifiers":[
        {
            "category":"Retail",
            "subcategory":"Auto Repair",
            "type":"Services"
        }
    ],
    "sg:phone":"+61 8 9445 1937",
    "sg:postcode":"6017",
    "sg:province":"WA",
    "sg:tags":[
        "electrical"
    ],
    "wof:name":"Complete Auto Electrics",
    "wof:placetype":"venue"
},
  "geometry": {"coordinates":[115.805160523,-31.9035263062],"type":"Point"}
}