{
  "type": "Feature",
  "properties": {
    "addr:full":"Unit 3, 170 Bannister Rd, Canning Vale WA 6155",
    "addr:housenumber":"170",
    "addr:postcode":"6155",
    "addr:street":"Bannister Rd",
    "iso:country":"AU",
    "sg:address":"Unit 3, 170",
    "sg:city":"Bannister Rd, Canning Vale",
    "sg:classifiers":[
        {
            "category":"Home & Garden",
            "subcategory":"Garden Supply",
            "type":"Retail Goods"
        }
    ],
    "sg:phone":"+61 8 9456 5811",
    "sg:postcode":"6155",
    "sg:province":"WA",
    "sg:tags":[
        "equipment"
    ],
    "wof:name":"Mowfix Mower & Chainsaw Centre",
    "wof:placetype":"venue"
},
  "geometry": {"coordinates":[115.90979,-32.059029],"type":"Point"}
}