{
  "type": "Feature",
  "properties": {
    "iso:country":"AU",
    "sg:address":"27 Westbrook Pde",
    "sg:city":"Gorokan",
    "sg:classifiers":[
        {
            "category":"Utilities",
            "subcategory":"Electric",
            "type":"Services"
        }
    ],
    "sg:phone":"+61 2 4392 2712",
    "sg:postcode":"2263",
    "sg:province":"NSW",
    "sg:tags":[
        "electrical",
        "contractor"
    ],
    "wof:name":"W. McNair Electrical",
    "wof:placetype":"venue"
},
  "geometry": {"coordinates":[151.507126,-33.248684],"type":"Point"}
}