{
  "type": "Feature",
  "properties": {
    "addr:full":"4 Silverwood St Morley WA 6062",
    "addr:housenumber":"4",
    "addr:postcode":"6062",
    "addr:street":"Silverwood St",
    "iso:country":"AU",
    "sg:address":"4 Silverwood St",
    "sg:city":"Morley",
    "sg:classifiers":[
        {
            "category":"Building & Trades",
            "subcategory":"Construction",
            "type":"Services"
        }
    ],
    "sg:phone":"+61 8 9275 4618",
    "sg:postcode":"6062",
    "sg:province":"WA",
    "sg:tags":[
        "earth",
        "excavating",
        "moving",
        "contractor"
    ],
    "wof:name":"Jem Bobcat & Truck Hire",
    "wof:placetype":"venue"
},
  "geometry": {"coordinates":[115.90695953399999,-31.8951721191],"type":"Point"}
}