{
  "type": "Feature",
  "properties": {
    "iso:country":"AU",
    "sg:address":"773 Warrigal Rd",
    "sg:city":"Oakleigh",
    "sg:classifiers":[
        {
            "category":"Organizations",
            "subcategory":"Non-profit Organization",
            "type":"Services"
        }
    ],
    "sg:phone":"+61 3 9569 0603",
    "sg:postcode":"3166",
    "sg:province":"VIC",
    "sg:tags":[
        "support",
        "disability",
        "organisation"
    ],
    "wof:name":"Oakleigh Centre For Intellectually Disabled Citizens",
    "wof:placetype":"venue"
},
  "geometry": {"coordinates":[145.089279175,-37.888874054],"type":"Point"}
}