{
  "type": "Feature",
  "properties": {
    "addr:full":"17- 19 Barber St Gunnedah NSW 2380",
    "addr:housenumber":"19",
    "addr:postcode":"2380",
    "addr:street":"Barber St",
    "iso:country":"AU",
    "sg:address":"17- 19 Barber St",
    "sg:city":"Gunnedah",
    "sg:classifiers":[
        {
            "category":"Home & Garden",
            "subcategory":"Building Materials",
            "type":"Retail Goods"
        }
    ],
    "sg:phone":"+61 1300 306 223",
    "sg:postcode":"2380",
    "sg:province":"NSW",
    "sg:tags":[
        "supply"
    ],
    "wof:name":"Australian Plasterboard Company",
    "wof:placetype":"venue"
},
  "geometry": {"coordinates":[150.246002197,-30.9767627716],"type":"Point"}
}