{
  "type": "Feature",
  "properties": {
    "addr:full":"243 Pyrmont St Pyrmont NSW 2009",
    "addr:housenumber":"243",
    "addr:postcode":"2009",
    "addr:street":"Pyrmont St",
    "iso:country":"AU",
    "sg:address":"243 Pyrmont St",
    "sg:city":"Pyrmont",
    "sg:classifiers":[
        {
            "category":"Fast Food",
            "type":"Food & Drink"
        }
    ],
    "sg:phone":"+61 2 9566 4862",
    "sg:postcode":"2009",
    "sg:province":"NSW",
    "sg:tags":[
        "away",
        "take"
    ],
    "wof:name":"Monteas Coffee",
    "wof:placetype":"venue"
},
  "geometry": {"coordinates":[151.19711303700001,-33.8734931946],"type":"Point"}
}