{
  "type": "Feature",
  "properties": {
    "addr:full":"96-98 Market St South Melbourne VIC 3205",
    "addr:housenumber":"96-98",
    "addr:postcode":"3205",
    "addr:street":"Market St",
    "iso:country":"AU",
    "sg:address":"96-98 Market St",
    "sg:city":"South Melbourne",
    "sg:classifiers":[
        {
            "category":"Professional",
            "subcategory":"Research",
            "type":"Services"
        }
    ],
    "sg:phone":"+61 3 8606 4000",
    "sg:postcode":"3205",
    "sg:province":"VIC",
    "sg:tags":[
        "market"
    ],
    "wof:name":"Nielsen Netratings",
    "wof:placetype":"venue"
},
  "geometry": {"coordinates":[144.95761100000001,-37.829933],"type":"Point"}
}