{
  "type": "Feature",
  "properties": {
    "addr:full":"42 Bulcock St Caloundra QLD 4551",
    "addr:housenumber":"42",
    "addr:postcode":"4551",
    "addr:street":"Bulcock St",
    "iso:country":"AU",
    "sg:address":"42 Bulcock St",
    "sg:city":"Caloundra",
    "sg:classifiers":[
        {
            "category":"Professional",
            "subcategory":"Accounting & Tax Preparation",
            "type":"Services"
        }
    ],
    "sg:phone":"+61 7 5491 1422",
    "sg:postcode":"4551",
    "sg:province":"QLD",
    "sg:tags":[
        "consultant",
        "taxation"
    ],
    "wof:name":"Wardle Partners Pty. Ltd.",
    "wof:placetype":"venue"
},
  "geometry": {"coordinates":[153.12948608400001,-26.8046588898],"type":"Point"}
}