{
  "type": "Feature",
  "properties": {
    "addr:full":"``Tarrenygri&#039;&#039;Woy Woy Rd Kariong NSW 2250",
    "addr:postcode":"2250",
    "addr:street":"Woy Rd",
    "iso:country":"AU",
    "sg:address":"``Tarrenygri&#039;&#039;Woy Woy Rd",
    "sg:city":"Kariong",
    "sg:classifiers":[
        {
            "category":"Building & Trades",
            "subcategory":"Landscaping Services",
            "type":"Services"
        }
    ],
    "sg:phone":"+61 2 4340 1070",
    "sg:postcode":"2250",
    "sg:province":"NSW",
    "sg:tags":[
        "designer",
        "landscape",
        "contractor"
    ],
    "wof:name":"Parry C J",
    "wof:placetype":"venue"
},
  "geometry": {"coordinates":[151.29606628400001,-33.4383354187],"type":"Point"}
}