{
  "type": "Feature",
  "properties": {
    "addr:full":"Cnr Deanmore Rd & Sackville Tce Scarborough WA 6019",
    "addr:postcode":"6019",
    "addr:street":"Cnr Deanmore Rd & Sackville Tce",
    "iso:country":"AU",
    "sg:address":"Cnr Deanmore Rd & Sackville Tce",
    "sg:city":"Scarborough",
    "sg:classifiers":[
        {
            "category":"Education",
            "subcategory":"Dance Studio",
            "type":"Public Place"
        }
    ],
    "sg:phone":"+61 405 457 252",
    "sg:postcode":"6019",
    "sg:province":"WA",
    "sg:tags":[
        "venue",
        "tuition"
    ],
    "wof:name":"Chisholm Dance Studio",
    "wof:placetype":"venue"
},
  "geometry": {"coordinates":[115.76773071300001,-31.8963222504],"type":"Point"}
}