{
  "type": "Feature",
  "properties": {
    "iso:country":"AU",
    "sg:address":"Unit 8, 1 Simms Rd",
    "sg:city":"Hamilton Hill",
    "sg:classifiers":[
        {
            "category":"Social Services",
            "subcategory":"Adult Care",
            "type":"Services"
        }
    ],
    "sg:phone":"+61 8 9331 5447",
    "sg:postcode":"6163",
    "sg:province":"WA",
    "sg:tags":[
        "aged"
    ],
    "wof:name":"Wisdom Activities",
    "wof:placetype":"venue"
},
  "geometry": {"coordinates":[115.781761,-32.075333],"type":"Point"}
}