{
  "type": "Feature",
  "properties": {
    "addr:full":"26 Florence St Hornsby NSW 2077",
    "addr:housenumber":"26",
    "addr:postcode":"2077",
    "addr:street":"Florence St",
    "iso:country":"AU",
    "sg:address":"26 Florence St",
    "sg:city":"Hornsby",
    "sg:classifiers":[
        {
            "category":"Health Services",
            "subcategory":"Doctor",
            "type":"Services"
        }
    ],
    "sg:phone":"+61 2 9482 1822",
    "sg:postcode":"2077",
    "sg:province":"NSW",
    "sg:tags":[
        "medical",
        "practitioner"
    ],
    "wof:name":"Ingle C P",
    "wof:placetype":"venue"
},
  "geometry": {"coordinates":[151.100906372,-33.7041625977],"type":"Point"}
}