{
  "type": "Feature",
  "properties": {
    "iso:country":"AU",
    "sg:address":"Shop 2/ 175",
    "sg:city":"Given Tce Paddington",
    "sg:classifiers":[
        {
            "category":"Banks & Credit Unions",
            "subcategory":"Financial Services",
            "type":"Services"
        }
    ],
    "sg:phone":"+61 7 3368 2020",
    "sg:postcode":"4064",
    "sg:province":"QLD",
    "sg:tags":[
        "loan",
        "finance",
        "mortgage"
    ],
    "wof:name":"Wizard Home Loans",
    "wof:placetype":"venue"
},
  "geometry": {"coordinates":[153.00668335,-27.4619503021],"type":"Point"}
}