{
  "type": "Feature",
  "properties": {
    "iso:country":"AU",
    "sg:address":"112 Bloomfield St",
    "sg:city":"Cleveland",
    "sg:classifiers":[
        {
            "category":"Shopping",
            "subcategory":"Jewelry",
            "type":"Retail Goods"
        }
    ],
    "sg:phone":"+61 7 3821 1921",
    "sg:postcode":"4163",
    "sg:province":"QLD",
    "sg:tags":[
        "jeweller"
    ],
    "wof:name":"John Edwards Cleveland Jewellers",
    "wof:placetype":"venue"
},
  "geometry": {"coordinates":[153.26716613799999,-27.5276470184],"type":"Point"}
}