{
  "type": "Feature",
  "properties": {
    "iso:country":"AU",
    "sg:address":"101 Pine Ave",
    "sg:city":"Leeton",
    "sg:classifiers":[
        {
            "category":"Shopping",
            "subcategory":"Clothing, Apparel, & Fashions",
            "type":"Retail Goods"
        }
    ],
    "sg:phone":"+61 2 6953 5242",
    "sg:postcode":"2705",
    "sg:province":"NSW",
    "sg:tags":[
        "lady",
        "wear"
    ],
    "wof:name":"Joosh&#039;d",
    "wof:placetype":"venue"
},
  "geometry": {"coordinates":[146.40525817899999,-34.5515174866],"type":"Point"}
}