{
  "type": "Feature",
  "properties": {
    "addr:full":"290 Inkerman St (Cnr Hotham St) St Kilda East VIC 3183",
    "addr:housenumber":"290",
    "addr:postcode":"3183",
    "addr:street":"Inkerman St Cnr Hotham St",
    "iso:country":"AU",
    "sg:address":"290 Inkerman St (Cnr Hotham St)",
    "sg:city":"St Kilda East",
    "sg:classifiers":[
        {
            "category":"Health Services",
            "subcategory":"Doctor",
            "type":"Services"
        }
    ],
    "sg:phone":"+61 3 9527 4355",
    "sg:postcode":"3183",
    "sg:province":"VIC",
    "sg:tags":[
        "medical",
        "practitioner"
    ],
    "wof:name":"Goldberg E DR",
    "wof:placetype":"venue"
},
  "geometry": {"coordinates":[144.999832153,-37.8662719727],"type":"Point"}
}