{
  "type": "Feature",
  "properties": {
    "iso:country":"AU",
    "sg:address":"354 Canterbury Rd",
    "sg:city":"Hurlstone Park",
    "sg:classifiers":[
        {
            "category":"Personal",
            "subcategory":"Beauty Salon",
            "type":"Services"
        }
    ],
    "sg:phone":"+61 2 9797 8452",
    "sg:postcode":"2193",
    "sg:province":"NSW",
    "sg:tags":[
        "hairdresser"
    ],
    "wof:name":"Kelly Len Hairdressing",
    "wof:placetype":"venue"
},
  "geometry": {"coordinates":[151.126816,-33.906414],"type":"Point"}
}