{
  "type": "Feature",
  "properties": {
    "addr:full":"Level 1, 224 Swan St Richmond VIC 3121",
    "addr:housenumber":"224",
    "addr:postcode":"3121",
    "addr:street":"Swan St",
    "iso:country":"AU",
    "sg:address":"Level 1, 224 Swan St",
    "sg:city":"Richmond",
    "sg:classifiers":[
        {
            "category":"Health Services",
            "subcategory":"Health Practitioner",
            "type":"Services"
        }
    ],
    "sg:phone":"+61 3 9946 5222",
    "sg:postcode":"3121",
    "sg:province":"VIC",
    "sg:tags":[
        "acupuncture"
    ],
    "wof:name":"Pyers Clare",
    "wof:placetype":"venue"
},
  "geometry": {"coordinates":[144.99708557100001,-37.8257064819],"type":"Point"}
}