{
  "type": "Feature",
  "properties": {
    "iso:country":"AU",
    "sg:address":"24 Edward St",
    "sg:city":"Devonport",
    "sg:classifiers":[
        {
            "category":"Professional",
            "subcategory":"Accounting & Tax Preparation",
            "type":"Services"
        }
    ],
    "sg:phone":"+61 3 6423 1027",
    "sg:postcode":"7310",
    "sg:province":"TAS",
    "sg:tags":[
        "consultant",
        "taxation"
    ],
    "wof:name":"Don Willing & Associates Pty Ltd",
    "wof:placetype":"venue"
},
  "geometry": {"coordinates":[146.360031128,-41.1783638],"type":"Point"}
}