{
  "type": "Feature",
  "properties": {
    "addr:full":"2892 Logan Rd Underwood QLD 4119",
    "addr:housenumber":"2892",
    "addr:postcode":"4119",
    "addr:street":"Logan Rd",
    "iso:country":"AU",
    "sg:address":"2892 Logan Rd",
    "sg:city":"Underwood",
    "sg:classifiers":[
        {
            "category":"Food & Beverages",
            "subcategory":"Fruits & Vegetables",
            "type":"Retail Goods"
        }
    ],
    "sg:phone":"+61 7 3841 1888",
    "sg:postcode":"4119",
    "sg:province":"QLD",
    "sg:tags":[
        "greengrocer",
        "fruiterer"
    ],
    "wof:name":"U.F.M Wholesale Fruit & Vegetable",
    "wof:placetype":"venue"
},
  "geometry": {"coordinates":[153.11575317399999,-27.6111450195],"type":"Point"}
}