{
  "type": "Feature",
  "properties": {
    "iso:country":"AU",
    "sg:address":"41 East Pde",
    "sg:city":"Kingswood",
    "sg:classifiers":[
        {
            "category":"Professional",
            "subcategory":"Business Services",
            "type":"Services"
        }
    ],
    "sg:phone":"+61 411 181 122",
    "sg:postcode":"5062",
    "sg:province":"SA",
    "sg:tags":[
        "management",
        "event"
    ],
    "wof:name":"Brian Gleeson Event Management",
    "wof:placetype":"venue"
},
  "geometry": {"coordinates":[138.61366272000001,-34.9732551575],"type":"Point"}
}