{
  "type": "Feature",
  "properties": {
    "addr:full":"2 Albion St Warwick QLD 4370",
    "addr:housenumber":"2",
    "addr:postcode":"4370",
    "addr:street":"Albion St",
    "iso:country":"AU",
    "sg:address":"2 Albion St",
    "sg:city":"Warwick",
    "sg:classifiers":[
        {
            "category":"Real Estate",
            "subcategory":"Real Estate Agent",
            "type":"Services"
        }
    ],
    "sg:phone":"+61 7 4661 4606",
    "sg:postcode":"4370",
    "sg:province":"QLD",
    "sg:tags":[
        "handyman's",
        "equipment",
        "hire",
        "builders",
        "contractor"
    ],
    "wof:name":"Warwick Rentals",
    "wof:placetype":"venue"
},
  "geometry": {"coordinates":[152.03627014200001,-28.2100868225],"type":"Point"}
}