{
  "type": "Feature",
  "properties": {
    "addr:full":"345 Keira St Wollongong NSW 2500",
    "addr:housenumber":"345",
    "addr:postcode":"2500",
    "addr:street":"Keira St",
    "iso:country":"AU",
    "sg:address":"345 Keira St",
    "sg:city":"Wollongong",
    "sg:classifiers":[
        {
            "category":"Shopping",
            "subcategory":"Computers & Home Electronics",
            "type":"Retail Goods"
        }
    ],
    "sg:phone":"+61 2 4228 6661",
    "sg:postcode":"2500",
    "sg:province":"NSW",
    "sg:tags":[
        "hi-fi",
        "equipment"
    ],
    "wof:name":"Hi Fi House",
    "wof:placetype":"venue"
},
  "geometry": {"coordinates":[150.89239499999999,-34.433708],"type":"Point"}
}