{
  "type": "Feature",
  "properties": {
    "addr:full":"317 Belmont St Alexandria NSW 2015",
    "addr:housenumber":"317",
    "addr:postcode":"2015",
    "addr:street":"Belmont St",
    "iso:country":"AU",
    "sg:address":"317 Belmont St",
    "sg:city":"Alexandria",
    "sg:classifiers":[
        {
            "category":"Professional",
            "subcategory":"Computer Services",
            "type":"Services"
        }
    ],
    "sg:phone":"+61 2 9550 3905",
    "sg:postcode":"2015",
    "sg:province":"NSW",
    "sg:tags":[
        "consultant",
        "system"
    ],
    "wof:name":"Armadillo Applied Computer Technologies",
    "wof:placetype":"venue"
},
  "geometry": {"coordinates":[151.188842773,-33.9066085815],"type":"Point"}
}