{
  "type": "Feature",
  "properties": {
    "addr:full":"Suite 24, 470 High St Penrith NSW 2750",
    "addr:housenumber":"470",
    "addr:postcode":"2750",
    "addr:street":"High St",
    "iso:country":"AU",
    "sg:address":"Suite 24, 470 High St",
    "sg:city":"Penrith",
    "sg:classifiers":[
        {
            "category":"Professional",
            "subcategory":"Employment Agencies",
            "type":"Services"
        }
    ],
    "sg:phone":"+61 2 4731 2807",
    "sg:postcode":"2750",
    "sg:province":"NSW",
    "sg:website":"http://www.penrith-personnel.com.au",
    "wof:name":"Penrith Personnel",
    "wof:placetype":"venue"
},
  "geometry": {"coordinates":[150.915557861,-33.8949584961],"type":"Point"}
}