{
  "type": "Feature",
  "properties": {
    "addr:full":"121 Wharf St Cannington WA 6107",
    "addr:housenumber":"121",
    "addr:postcode":"6107",
    "addr:street":"Wharf St",
    "iso:country":"AU",
    "sg:address":"121 Wharf St",
    "sg:city":"Cannington",
    "sg:classifiers":[
        {
            "category":"Real Estate",
            "subcategory":"Real Estate Agent",
            "type":"Services"
        }
    ],
    "sg:phone":"+61 8 9351 8871",
    "sg:postcode":"6107",
    "sg:province":"WA",
    "wof:name":"Raine & Horne",
    "wof:placetype":"venue"
},
  "geometry": {"coordinates":[115.935111999,-32.0144271851],"type":"Point"}
}