{
  "type": "Feature",
  "properties": {
    "iso:country":"AU",
    "sg:address":"3/ 69 Bungary Rd",
    "sg:city":"Norah Head",
    "sg:classifiers":[
        {
            "category":"Personal",
            "subcategory":"Beauty Salon",
            "type":"Services"
        }
    ],
    "sg:phone":"+61 2 4396 3062",
    "sg:postcode":"2263",
    "sg:province":"NSW",
    "sg:tags":[
        "hairdresser"
    ],
    "wof:name":"Norah Head.The Hair Experience",
    "wof:placetype":"venue"
},
  "geometry": {"coordinates":[151.565903,-33.278835],"type":"Point"}
}