{
  "type": "Feature",
  "properties": {
    "addr:full":"Level 6/ 3350 Pacific Hwy Springwood QLD 4127",
    "addr:housenumber":"/ 3350",
    "addr:postcode":"4127",
    "addr:street":"Pacific Hwy",
    "iso:country":"AU",
    "sg:address":"Level 6/ 3350 Pacific Hwy",
    "sg:city":"Springwood",
    "sg:classifiers":[
        {
            "category":"Insurance",
            "subcategory":"Hazard Insurance",
            "type":"Services"
        }
    ],
    "sg:phone":"+61 1800 700 732",
    "sg:postcode":"4127",
    "sg:province":"QLD",
    "sg:tags":[
        "motor",
        "vehicle"
    ],
    "wof:name":"Roadteam Insurance",
    "wof:placetype":"venue"
},
  "geometry": {"coordinates":[153.126754761,-27.6198043823],"type":"Point"}
}