{
  "type": "Feature",
  "properties": {
    "iso:country":"AU",
    "sg:address":"4 Affleck Rd",
    "sg:city":"Perth Airport",
    "sg:classifiers":[
        {
            "category":"Professional",
            "type":"Services"
        }
    ],
    "sg:phone":"+61 8 9477 6088",
    "sg:postcode":"6105",
    "sg:province":"WA",
    "sg:tags":[
        "forwarding",
        "agent",
        "transport"
    ],
    "wof:name":"Freightshop",
    "wof:placetype":"venue"
},
  "geometry": {"coordinates":[115.976257324,-31.9414615631],"type":"Point"}
}