{
  "type": "Feature",
  "properties": {
    "addr:full":"53 Griffiths Rd Lambton NSW 2299",
    "addr:housenumber":"53",
    "addr:postcode":"2299",
    "addr:street":"Griffiths Rd",
    "iso:country":"AU",
    "sg:address":"53 Griffiths Rd",
    "sg:city":"Lambton",
    "sg:classifiers":[
        {
            "category":"Home & Garden",
            "subcategory":"Hardware",
            "type":"Retail Goods"
        }
    ],
    "sg:phone":"+61 2 4906 7777",
    "sg:postcode":"2299",
    "sg:province":"NSW",
    "sg:tags":[
        "generating",
        "set",
        "generator"
    ],
    "wof:name":"Dunlite",
    "wof:placetype":"venue"
},
  "geometry": {"coordinates":[151.72459411599999,-32.9148712158],"type":"Point"}
}