{
  "type": "Feature",
  "properties": {
    "addr:full":"Princes Hwy Corrimal NSW 2518",
    "addr:postcode":"2518",
    "addr:street":"Princes Hwy",
    "iso:country":"AU",
    "sg:address":"Princes Hwy",
    "sg:city":"Corrimal",
    "sg:classifiers":[
        {
            "category":"Utilities",
            "subcategory":"Electric",
            "type":"Services"
        }
    ],
    "sg:phone":"+61 2 4283 4717",
    "sg:postcode":"2518",
    "sg:province":"NSW",
    "sg:tags":[
        "electrical",
        "contractor"
    ],
    "wof:name":"Lodehaul South Bulli Whgbdge",
    "wof:placetype":"venue"
},
  "geometry": {"coordinates":[150.896683,-34.374073],"type":"Point"}
}