{
  "type": "Feature",
  "properties": {
    "iso:country":"AU",
    "sg:address":"1023 Creek Rd",
    "sg:city":"Carindale",
    "sg:classifiers":[
        {
            "category":"Government",
            "subcategory":"Office",
            "type":"Public Place"
        }
    ],
    "sg:phone":"+61 7 3398 8017",
    "sg:postcode":"4152",
    "sg:province":"QLD",
    "sg:tags":[
        "qld",
        "agency",
        "escort",
        "social"
    ],
    "wof:name":"Adel",
    "wof:placetype":"venue"
},
  "geometry": {"coordinates":[153.09963989299999,-27.5062503815],"type":"Point"}
}