{
  "type": "Feature",
  "properties": {
    "addr:full":"570 Boronia Rd Wantirna VIC 3152",
    "addr:housenumber":"570",
    "addr:postcode":"3152",
    "addr:street":"Boronia Rd",
    "iso:country":"AU",
    "sg:address":"570 Boronia Rd",
    "sg:city":"Wantirna",
    "sg:classifiers":[
        {
            "category":"Autos & Motor Vehicles",
            "subcategory":"Fuel & Gas Station",
            "type":"Retail Goods"
        }
    ],
    "sg:phone":"+61 3 9801 1756",
    "sg:postcode":"3152",
    "sg:province":"VIC",
    "wof:name":"Fast Fuel",
    "wof:placetype":"venue"
},
  "geometry": {"coordinates":[145.2368927,-37.8502120972],"type":"Point"}
}