{
  "type": "Feature",
  "properties": {
    "addr:full":"42 Herbert St Bowen QLD 4805",
    "addr:housenumber":"42",
    "addr:postcode":"4805",
    "addr:street":"Herbert St",
    "iso:country":"AU",
    "sg:address":"42 Herbert St",
    "sg:city":"Bowen",
    "sg:classifiers":[
        {
            "category":"Banks & Credit Unions",
            "subcategory":"Financial Services",
            "type":"Services"
        }
    ],
    "sg:phone":"+61 7 4786 1144",
    "sg:postcode":"4805",
    "sg:province":"QLD",
    "sg:tags":[
        "loan",
        "finance",
        "mortgage"
    ],
    "wof:name":"C B F C Ltd",
    "wof:placetype":"venue"
},
  "geometry": {"coordinates":[148.24090576200001,-20.0033359528],"type":"Point"}
}