{
  "type": "Feature",
  "properties": {
    "addr:full":"Rear 16 Isa St Fyshwick ACT 2609",
    "addr:housenumber":"16",
    "addr:postcode":"2609",
    "addr:street":"Isa St",
    "iso:country":"AU",
    "sg:address":"Rear 16 Isa St",
    "sg:city":"Fyshwick",
    "sg:classifiers":[
        {
            "category":"Autos & Motor Vehicles",
            "subcategory":"Boat Sales",
            "type":"Retail Goods"
        }
    ],
    "sg:phone":"+61 2 6239 1172",
    "sg:postcode":"2609",
    "sg:province":"ACT",
    "sg:tags":[
        "equipment",
        "yacht"
    ],
    "wof:name":"Steve's Car & Boat Upholstery",
    "wof:placetype":"venue"
},
  "geometry": {"coordinates":[149.17202758799999,-35.3270759583],"type":"Point"}
}