{
  "type": "Feature",
  "properties": {
    "addr:full":"Unit 10, 9/ 11 Johnson Rd Tuggerah NSW 2259",
    "addr:housenumber":"9 / 11",
    "addr:postcode":"2259",
    "addr:street":"Johnson Rd",
    "iso:country":"AU",
    "sg:address":"Unit 10, 9/ 11 Johnson Rd",
    "sg:city":"Tuggerah",
    "sg:classifiers":[
        {
            "category":"Retail",
            "subcategory":"Auto Repair",
            "type":"Services"
        }
    ],
    "sg:phone":"+61 2 4351 1103",
    "sg:postcode":"2259",
    "sg:province":"NSW",
    "sg:tags":[
        "muffler",
        "exhaust",
        "system"
    ],
    "wof:name":"Tuggerah Exhaust & Towbar Centre",
    "wof:placetype":"venue"
},
  "geometry": {"coordinates":[151.42013549800001,-33.2944145203],"type":"Point"}
}