{
  "type": "Feature",
  "properties": {
    "addr:full":"11 Huntsmore Rd Minto NSW 2566",
    "addr:housenumber":"11",
    "addr:postcode":"2566",
    "addr:street":"Huntsmore Rd",
    "iso:country":"AU",
    "sg:address":"11 Huntsmore Rd",
    "sg:city":"Minto",
    "sg:classifiers":[
        {
            "category":"Manufacturing",
            "subcategory":"Wood Products",
            "type":"Manufacturing & Wholesale Goods"
        }
    ],
    "sg:phone":"+61 2 9603 4855",
    "sg:postcode":"2566",
    "sg:province":"NSW",
    "sg:tags":[
        "pallet",
        "platform"
    ],
    "wof:name":"Afford Packaging",
    "wof:placetype":"venue"
},
  "geometry": {"coordinates":[150.83786010700001,-34.0363883972],"type":"Point"}
}