{
  "type": "Feature",
  "properties": {
    "iso:country":"AU",
    "sg:address":"18 Watermoor Ave",
    "sg:city":"Kilsyth",
    "sg:classifiers":[
        {
            "category":"Organizations",
            "subcategory":"Professional Association",
            "type":"Services"
        }
    ],
    "sg:phone":"+61 417 014 173",
    "sg:postcode":"3137",
    "sg:province":"VIC",
    "sg:tags":[
        "web",
        "internet"
    ],
    "wof:name":"SitesAlive",
    "wof:placetype":"venue"
},
  "geometry": {"coordinates":[145.303833008,-37.8351707458],"type":"Point"}
}