{
  "type": "Feature",
  "properties": {
    "iso:country":"AU",
    "sg:address":"Berth 2",
    "sg:city":"Lower Promenade Southgate",
    "sg:classifiers":[
        {
            "category":"Recreation",
            "subcategory":"Boat Charter",
            "type":"Entertainment"
        }
    ],
    "sg:phone":"+61 3 9686 0004",
    "sg:postcode":"3006",
    "sg:province":"VIC",
    "wof:name":"Rivers Restaurant Cruises",
    "wof:placetype":"venue"
},
  "geometry": {"coordinates":[144.965667725,-37.8214530945],"type":"Point"}
}