{
  "type": "Feature",
  "properties": {
    "addr:full":"324 Burwood Rd Hawthorn VIC 3122",
    "addr:housenumber":"324",
    "addr:postcode":"3122",
    "addr:street":"Burwood Rd",
    "iso:country":"AU",
    "sg:address":"324 Burwood Rd",
    "sg:city":"Hawthorn",
    "sg:classifiers":[
        {
            "category":"Travel",
            "subcategory":"Hotels & Motels",
            "type":"Entertainment"
        }
    ],
    "sg:phone":"+61 3 9818 6530",
    "sg:postcode":"3122",
    "sg:province":"VIC",
    "wof:name":"Glenferrie Hotel",
    "wof:placetype":"venue"
},
  "geometry": {"coordinates":[145.03440856899999,-37.8225898743],"type":"Point"}
}