{
  "type": "Feature",
  "properties": {
    "addr:full":"72 Harcourt St New Farm QLD 4005",
    "addr:housenumber":"72",
    "addr:postcode":"4005",
    "addr:street":"Harcourt St",
    "iso:country":"AU",
    "sg:address":"72 Harcourt St",
    "sg:city":"New Farm",
    "sg:classifiers":[
        {
            "category":"Sports & Exercise",
            "subcategory":"Gym",
            "type":"Entertainment"
        }
    ],
    "sg:phone":"+61 7 3358 3214",
    "sg:postcode":"4005",
    "sg:province":"QLD",
    "sg:tags":[
        "health",
        "fitness"
    ],
    "wof:name":"Fitnance Australia",
    "wof:placetype":"venue"
},
  "geometry": {"coordinates":[153.04045105,-27.4599761963],"type":"Point"}
}