{
  "type": "Feature",
  "properties": {
    "addr:full":"PO Box 376 Bomaderry NSW 2541",
    "addr:postcode":"2541",
    "iso:country":"AU",
    "sg:address":"PO Box 376",
    "sg:city":"Bomaderry",
    "sg:classifiers":[
        {
            "category":"Utilities",
            "subcategory":"Electric",
            "type":"Services"
        }
    ],
    "sg:phone":"+61 2 4421 3706",
    "sg:postcode":"2541",
    "sg:province":"NSW",
    "sg:tags":[
        "electrical",
        "contractor"
    ],
    "wof:name":"Simply Brilliant Solutions",
    "wof:placetype":"venue"
},
  "geometry": {"coordinates":[150.61088562,-34.850769043],"type":"Point"}
}