{
  "type": "Feature",
  "properties": {
    "iso:country":"AU",
    "sg:address":"489 Peel St",
    "sg:city":"Tamworth",
    "sg:classifiers":[
        {
            "category":"Utilities",
            "subcategory":"Telephone",
            "type":"Services"
        }
    ],
    "sg:phone":"+61 2 6766 3339",
    "sg:postcode":"2340",
    "sg:province":"NSW",
    "sg:tags":[
        "accessory"
    ],
    "wof:name":"Country Talkphones",
    "wof:placetype":"venue"
},
  "geometry": {"coordinates":[150.93295288100001,-31.0942459106],"type":"Point"}
}