{
  "type": "Feature",
  "properties": {
    "iso:country":"AU",
    "sg:address":"Castlefield St",
    "sg:city":"Bondi",
    "sg:classifiers":[
        {
            "category":"Education",
            "subcategory":"Kindergarten",
            "type":"Public Place"
        }
    ],
    "sg:phone":"+61 2 9365 3289",
    "sg:postcode":"2026",
    "sg:province":"NSW",
    "sg:tags":[
        "pre-schools"
    ],
    "wof:name":"Castlefield Kindergarten",
    "wof:placetype":"venue"
},
  "geometry": {"coordinates":[151.267501831,-33.8942527771],"type":"Point"}
}