{
  "type": "Feature",
  "properties": {
    "addr:full":"Unit 2, 356a South St O'Connor WA 6163",
    "addr:housenumber":"356a",
    "addr:postcode":"6163",
    "addr:street":"South St",
    "iso:country":"AU",
    "sg:address":"Unit 2, 356a South St",
    "sg:city":"O'Connor",
    "sg:classifiers":[
        {
            "category":"Professional",
            "type":"Services"
        }
    ],
    "sg:phone":"+61 8 9286 1102",
    "sg:postcode":"6163",
    "sg:province":"WA",
    "sg:tags":[
        "marine",
        "contractor"
    ],
    "wof:name":"Longreach Marine Services",
    "wof:placetype":"venue"
},
  "geometry": {"coordinates":[115.786377,-32.063046],"type":"Point"}
}