{
  "type": "Feature",
  "properties": {
    "iso:country":"AU",
    "sg:address":"501 Whitehorse Rd",
    "sg:city":"Mitcham",
    "sg:classifiers":[
        {
            "category":"Health Services",
            "subcategory":"Health Practitioner",
            "type":"Services"
        }
    ],
    "sg:phone":"+61 3 9873 4848",
    "sg:postcode":"3132",
    "sg:province":"VIC",
    "sg:tags":[
        "acupuncture"
    ],
    "wof:name":"Yan Wo Tong",
    "wof:placetype":"venue"
},
  "geometry": {"coordinates":[145.192825317,-37.8161697388],"type":"Point"}
}