{
  "type": "Feature",
  "properties": {
    "iso:country":"AU",
    "sg:address":"83 Cavanagh St",
    "sg:city":"Cheltenham",
    "sg:classifiers":[
        {
            "category":"Building & Trades",
            "subcategory":"Construction",
            "type":"Services"
        }
    ],
    "sg:phone":"+61 3 9584 8001",
    "sg:postcode":"3192",
    "sg:province":"VIC",
    "sg:tags":[
        "contractor"
    ],
    "wof:name":"Surbar Developments",
    "wof:placetype":"venue"
},
  "geometry": {"coordinates":[145.06619262699999,-37.9581108093],"type":"Point"}
}