{
  "type": "Feature",
  "properties": {
    "addr:full":"61 Sherwood Rd Toowong QLD 4066",
    "addr:housenumber":"61",
    "addr:postcode":"4066",
    "addr:street":"Sherwood Rd",
    "iso:country":"AU",
    "sg:address":"61 Sherwood Rd",
    "sg:city":"Toowong",
    "sg:classifiers":[
        {
            "category":"Insurance",
            "subcategory":"Insurance Agent",
            "type":"Services"
        }
    ],
    "sg:phone":"+61 7 3870 3592",
    "sg:postcode":"4066",
    "sg:province":"QLD",
    "wof:name":"Miller Insurance Services",
    "wof:placetype":"venue"
},
  "geometry": {"coordinates":[152.99012756400001,-27.4850921631],"type":"Point"}
}