{
  "type": "Feature",
  "properties": {
    "addr:full":"341 Belmont Rd Belmont QLD 4153",
    "addr:housenumber":"341",
    "addr:postcode":"4153",
    "addr:street":"Belmont Rd",
    "iso:country":"AU",
    "sg:address":"341 Belmont Rd",
    "sg:city":"Belmont",
    "sg:classifiers":[
        {
            "category":"Professional",
            "subcategory":"Computer Services",
            "type":"Services"
        }
    ],
    "sg:phone":"+61 1800 737 748",
    "sg:postcode":"4153",
    "sg:province":"QLD",
    "sg:tags":[
        "repairs",
        "upgrade",
        "equipment"
    ],
    "wof:name":"Rescue Information Technology",
    "wof:placetype":"venue"
},
  "geometry": {"coordinates":[153.12738037099999,-27.4899349213],"type":"Point"}
}