{
  "type": "Feature",
  "properties": {
    "iso:country":"AU",
    "sg:address":"30 Huntington Pl",
    "sg:city":"Banyo",
    "sg:classifiers":[
        {
            "category":"Wholesale",
            "subcategory":"Electrical",
            "type":"Manufacturing & Wholesale Goods"
        }
    ],
    "sg:phone":"+61 7 3267 1900",
    "sg:postcode":"4014",
    "sg:province":"QLD",
    "sg:tags":[
        "wholesaler"
    ],
    "wof:name":"General Trade Supplies",
    "wof:placetype":"venue"
},
  "geometry": {"coordinates":[153.093826294,-27.3858242035],"type":"Point"}
}