{
  "type": "Feature",
  "properties": {
    "addr:full":"24 Yaralla St Tumut NSW 2720",
    "addr:housenumber":"24",
    "addr:postcode":"2720",
    "addr:street":"Yaralla St",
    "iso:country":"AU",
    "sg:address":"24 Yaralla St",
    "sg:city":"Tumut",
    "sg:classifiers":[
        {
            "category":"Manufacturing",
            "subcategory":"Tools & Machinery",
            "type":"Manufacturing & Wholesale Goods"
        }
    ],
    "sg:phone":"+61 2 6947 4133",
    "sg:postcode":"2720",
    "sg:province":"NSW",
    "sg:tags":[
        "earth",
        "excavating",
        "moving",
        "equipment"
    ],
    "wof:name":"Tumut Sand & Gravel",
    "wof:placetype":"venue"
},
  "geometry": {"coordinates":[148.22036700000001,-35.317764],"type":"Point"}
}