{
  "type": "Feature",
  "properties": {
    "addr:full":"59 Tudhoe St Wagin WA 6315",
    "addr:housenumber":"59",
    "addr:postcode":"6315",
    "addr:street":"Tudhoe St",
    "iso:country":"AU",
    "sg:address":"59 Tudhoe St",
    "sg:city":"Wagin",
    "sg:classifiers":[
        {
            "category":"Industrial Area",
            "type":"Public Place"
        }
    ],
    "sg:phone":"+61 8 9861 2800",
    "sg:postcode":"6315",
    "sg:province":"WA",
    "sg:tags":[
        "rural",
        "shed"
    ],
    "wof:name":"Ranbuild",
    "wof:placetype":"venue"
},
  "geometry": {"coordinates":[117.344436645,-33.3087005615],"type":"Point"}
}