{
  "type": "Feature",
  "properties": {
    "iso:country":"AU",
    "sg:address":"Lot 3 Moorhouse Rd",
    "sg:city":"Port Adelaide",
    "sg:classifiers":[
        {
            "category":"Manufacturing",
            "subcategory":"Metals",
            "type":"Manufacturing & Wholesale Goods"
        }
    ],
    "sg:phone":"+61 8 8240 1822",
    "sg:postcode":"5015",
    "sg:province":"SA",
    "sg:tags":[
        "steel",
        "fabricator",
        "mfrs"
    ],
    "wof:name":"Adelaide Fabrication Services Pty Ltd",
    "wof:placetype":"venue"
},
  "geometry": {"coordinates":[138.50411987300001,-34.8444900513],"type":"Point"}
}