{
  "type": "Feature",
  "properties": {
    "iso:country":"AU",
    "sg:address":"Cnr Woolcock & Duckworth Sts",
    "sg:city":"Townsville",
    "sg:classifiers":[
        {
            "category":"Retail",
            "subcategory":"Auto Rental",
            "type":"Services"
        }
    ],
    "sg:phone":"+61 7 4775 1077",
    "sg:postcode":"4810",
    "sg:province":"QLD",
    "sg:tags":[
        "car",
        "armoured"
    ],
    "wof:name":"Armaguard",
    "wof:placetype":"venue"
},
  "geometry": {"coordinates":[146.760223,-19.267962],"type":"Point"}
}