{
  "type": "Feature",
  "properties": {
    "addr:full":"14 Tanti Ave Mornington VIC 3931",
    "addr:housenumber":"14",
    "addr:postcode":"3931",
    "addr:street":"Tanti Ave",
    "iso:country":"AU",
    "sg:address":"14 Tanti Ave",
    "sg:city":"Mornington",
    "sg:classifiers":[
        {
            "category":"Retail",
            "subcategory":"Event Space",
            "type":"Services"
        }
    ],
    "sg:phone":"+61 3 5975 5990",
    "sg:postcode":"3931",
    "sg:province":"VIC",
    "sg:tags":[
        "function",
        "organiser"
    ],
    "wof:name":"Sutton Grange",
    "wof:placetype":"venue"
},
  "geometry": {"coordinates":[145.04133605999999,-38.2160453796],"type":"Point"}
}