{
  "type": "Feature",
  "properties": {
    "iso:country":"AU",
    "sg:address":"34 Radio Ave",
    "sg:city":"Balgowlah Heights",
    "sg:classifiers":[
        {
            "category":"Professional",
            "subcategory":"Computer Services",
            "type":"Services"
        }
    ],
    "sg:phone":"+61 2 9948 8274",
    "sg:postcode":"2093",
    "sg:province":"NSW",
    "sg:tags":[
        "package",
        "software"
    ],
    "wof:name":"Dominant Software",
    "wof:placetype":"venue"
},
  "geometry": {"coordinates":[151.25973510700001,-33.8042259216],"type":"Point"}
}