{
  "type": "Feature",
  "properties": {
    "addr:full":"Drayton St Dalby QLD 4405",
    "addr:postcode":"4405",
    "addr:street":"Drayton St",
    "iso:country":"AU",
    "sg:address":"Drayton St",
    "sg:city":"Dalby",
    "sg:classifiers":[
        {
            "category":"Fast Food",
            "type":"Food & Drink"
        }
    ],
    "sg:phone":"+61 7 4662 1677",
    "sg:postcode":"4405",
    "sg:province":"QLD",
    "sg:tags":[
        "away",
        "take"
    ],
    "wof:name":"KFC",
    "wof:placetype":"venue"
},
  "geometry": {"coordinates":[151.257446289,-27.1783275604],"type":"Point"}
}