{
  "type": "Feature",
  "properties": {
    "iso:country":"AU",
    "sg:address":"91A Cameron St",
    "sg:city":"Wauchope",
    "sg:classifiers":[
        {
            "category":"Professional",
            "subcategory":"Printing & Photocopies",
            "type":"Services"
        }
    ],
    "sg:phone":"+61 2 6586 4703",
    "sg:postcode":"2446",
    "sg:province":"NSW",
    "sg:tags":[
        "rubber",
        "stamp",
        "metal"
    ],
    "wof:name":"Debs Stamps",
    "wof:placetype":"venue"
},
  "geometry": {"coordinates":[152.732986,-31.462793],"type":"Point"}
}