{
  "type": "Feature",
  "properties": {
    "iso:country":"AU",
    "sg:address":"94a Cardigan Rd",
    "sg:city":"Greenacre",
    "sg:classifiers":[
        {
            "category":"Building & Trades",
            "subcategory":"Plumbing",
            "type":"Services"
        }
    ],
    "sg:phone":"+61 2 9742 6490",
    "sg:postcode":"2190",
    "sg:province":"NSW",
    "sg:tags":[
        "plumber",
        "gasfitters"
    ],
    "wof:name":"John Nakhoul Plumbing Services Pty Ltd",
    "wof:placetype":"venue"
},
  "geometry": {"coordinates":[151.054596,-33.898113],"type":"Point"}
}