{
  "type": "Feature",
  "properties": {
    "iso:country":"AU",
    "sg:address":"44 Manning Rd",
    "sg:city":"Aberfoyle Park",
    "sg:classifiers":[
        {
            "category":"Health Services",
            "subcategory":"Chiropractor",
            "type":"Services"
        }
    ],
    "sg:phone":"+61 8 8358 6044",
    "sg:postcode":"5159",
    "sg:province":"SA",
    "wof:name":"Blackeby Michael",
    "wof:placetype":"venue"
},
  "geometry": {"coordinates":[138.59588623100001,-35.0612869263],"type":"Point"}
}