{
  "type": "Feature",
  "properties": {
    "iso:country":"AU",
    "sg:address":"18 Kent St",
    "sg:city":"Hamilton",
    "sg:classifiers":[
        {
            "category":"Transit Center",
            "subcategory":"Freight",
            "type":"Transportation"
        }
    ],
    "sg:phone":"+61 7 3868 1770",
    "sg:postcode":"4007",
    "sg:province":"QLD",
    "sg:tags":[
        "agent",
        "shipping"
    ],
    "wof:name":"Queensland International Freight Services",
    "wof:placetype":"venue"
},
  "geometry": {"coordinates":[153.06501800000001,-27.435928],"type":"Point"}
}