{
  "type": "Feature",
  "properties": {
    "addr:full":"10 Day St Lansvale NSW 2166",
    "addr:housenumber":"10",
    "addr:postcode":"2166",
    "addr:street":"Day St",
    "iso:country":"AU",
    "sg:address":"10 Day St",
    "sg:city":"Lansvale",
    "sg:classifiers":[
        {
            "category":"Real Estate",
            "subcategory":"Architect",
            "type":"Services"
        }
    ],
    "sg:phone":"+61 2 9755 3305",
    "sg:postcode":"2166",
    "sg:province":"NSW",
    "sg:tags":[
        "raw",
        "material",
        "plastic"
    ],
    "wof:name":"Sims Plastics",
    "wof:placetype":"venue"
},
  "geometry": {"coordinates":[150.96563720699999,-33.8950309753],"type":"Point"}
}