{
  "type": "Feature",
  "properties": {
    "iso:country":"AU",
    "sg:address":"Shop 77, 8th Ave, Carrara Market",
    "sg:city":"Carrara",
    "sg:classifiers":[
        {
            "category":"Food & Beverages",
            "subcategory":"Bakery",
            "type":"Retail Goods"
        }
    ],
    "sg:phone":"+61 7 5578 1139",
    "sg:postcode":"4211",
    "sg:province":"QLD",
    "sg:tags":[
        "baker"
    ],
    "wof:name":"Maurita Authentic Italian Bakery & Patisserie",
    "wof:placetype":"venue"
},
  "geometry": {"coordinates":[153.34231567399999,-27.9982719421],"type":"Point"}
}