{
  "type": "Feature",
  "properties": {
    "addr:full":"1 Currie Rd Forestville NSW 2087",
    "addr:housenumber":"1",
    "addr:postcode":"2087",
    "addr:street":"Currie Rd",
    "iso:country":"AU",
    "sg:address":"1 Currie Rd",
    "sg:city":"Forestville",
    "sg:classifiers":[
        {
            "category":"Arena",
            "subcategory":"Sports Club",
            "type":"Entertainment"
        }
    ],
    "sg:phone":"+61 2 9452 3494",
    "sg:postcode":"2087",
    "sg:province":"NSW",
    "sg:tags":[
        "league",
        "rugby"
    ],
    "wof:name":"Forestville Rugby League Club",
    "wof:placetype":"venue"
},
  "geometry": {"coordinates":[151.219284058,-33.7594413757],"type":"Point"}
}