{
  "type": "Feature",
  "properties": {
    "iso:country":"AU",
    "sg:address":"214 Anakie Rd",
    "sg:city":"Bell Post Hill",
    "sg:classifiers":[
        {
            "category":"Building & Trades",
            "subcategory":"Construction",
            "type":"Services"
        }
    ],
    "sg:phone":"+61 3 5278 3198",
    "sg:postcode":"3215",
    "sg:province":"VIC",
    "sg:tags":[
        "plasterboard",
        "plasterer",
        "fixer"
    ],
    "wof:name":"S.W. Plastering",
    "wof:placetype":"venue"
},
  "geometry": {"coordinates":[144.33419799800001,-38.0979156494],"type":"Point"}
}