{
  "type": "Feature",
  "properties": {
    "addr:full":"2 Willie St Gilgandra NSW 2827",
    "addr:housenumber":"2",
    "addr:postcode":"2827",
    "addr:street":"Willie St",
    "iso:country":"AU",
    "sg:address":"2 Willie St",
    "sg:city":"Gilgandra",
    "sg:classifiers":[
        {
            "category":"Travel",
            "subcategory":"Hotels & Motels",
            "type":"Entertainment"
        }
    ],
    "sg:phone":"+61 2 6847 2241",
    "sg:postcode":"2827",
    "sg:province":"NSW",
    "wof:name":"Three Ways Motel",
    "wof:placetype":"venue"
},
  "geometry": {"coordinates":[148.66293335,-31.7133407593],"type":"Point"}
}