{
  "type": "Feature",
  "properties": {
    "iso:country":"AU",
    "sg:address":"10 Mona Vale Rd",
    "sg:city":"Pymble",
    "sg:classifiers":[
        {
            "category":"Insurance",
            "subcategory":"Insurance Agent",
            "type":"Services"
        }
    ],
    "sg:phone":"+61 2 9449 6599",
    "sg:postcode":"2073",
    "sg:province":"NSW",
    "sg:tags":[
        "broker"
    ],
    "wof:name":"City Acceptance Corp Pty Ltd",
    "wof:placetype":"venue"
},
  "geometry": {"coordinates":[151.14822387699999,-33.7487373352],"type":"Point"}
}