{
  "type": "Feature",
  "properties": {
    "iso:country":"AU",
    "sg:address":"204 Commercial Rd",
    "sg:city":"Prahran",
    "sg:classifiers":[
        {
            "category":"Personal",
            "subcategory":"Shoe Repair & Shine",
            "type":"Services"
        }
    ],
    "sg:phone":"+61 3 9510 2413",
    "sg:postcode":"3181",
    "sg:province":"VIC",
    "sg:tags":[
        "footwear"
    ],
    "wof:name":"Yodgee Footwear",
    "wof:placetype":"venue"
},
  "geometry": {"coordinates":[144.99310302699999,-37.8468437195],"type":"Point"}
}