{
  "type": "Feature",
  "properties": {
    "addr:full":"93 Charles St Seddon VIC 3011",
    "addr:housenumber":"93",
    "addr:postcode":"3011",
    "addr:street":"Charles St",
    "iso:country":"AU",
    "sg:address":"93 Charles St",
    "sg:city":"Seddon",
    "sg:classifiers":[
        {
            "category":"Building & Trades",
            "subcategory":"Construction",
            "type":"Services"
        }
    ],
    "sg:phone":"+61 3 9689 0491",
    "sg:postcode":"3011",
    "sg:province":"VIC",
    "sg:tags":[
        "welding"
    ],
    "wof:name":"Steelwise Pty Ltd",
    "wof:placetype":"venue"
},
  "geometry": {"coordinates":[144.890914917,-37.8066711426],"type":"Point"}
}