{
  "type": "Feature",
  "properties": {
    "addr:full":"1374 Gympie Rd Aspley QLD 4034",
    "addr:housenumber":"1374",
    "addr:postcode":"4034",
    "addr:street":"Gympie Rd",
    "iso:country":"AU",
    "sg:address":"1374 Gympie Rd",
    "sg:city":"Aspley",
    "sg:classifiers":[
        {
            "category":"Fast Food",
            "type":"Food & Drink"
        }
    ],
    "sg:phone":"+61 7 3892 1111",
    "sg:postcode":"4034",
    "sg:province":"QLD",
    "sg:tags":[
        "away",
        "take"
    ],
    "wof:name":"Pizza Hut",
    "wof:placetype":"venue"
},
  "geometry": {"coordinates":[153.016907,-27.36215],"type":"Point"}
}