{
  "type": "Feature",
  "properties": {
    "addr:full":"1 Inverness Pl St Andrews NSW 2566",
    "addr:housenumber":"1",
    "addr:postcode":"2566",
    "addr:street":"Inverness Pl",
    "iso:country":"AU",
    "sg:address":"1 Inverness Pl",
    "sg:city":"St Andrews",
    "sg:classifiers":[
        {
            "category":"Health Services",
            "subcategory":"Dentist",
            "type":"Services"
        }
    ],
    "sg:phone":"+61 2 9603 6269",
    "sg:postcode":"2566",
    "sg:province":"NSW",
    "wof:name":"Boukouvalas C",
    "wof:placetype":"venue"
},
  "geometry": {"coordinates":[150.831542969,-34.0213546753],"type":"Point"}
}