{
  "type": "Feature",
  "properties": {
    "iso:country":"AU",
    "sg:address":"Cnr Beams & Sandgate Rds",
    "sg:city":"Boondall",
    "sg:classifiers":[
        {
            "category":"Health Services",
            "subcategory":"Dentist",
            "type":"Services"
        }
    ],
    "sg:phone":"+61 7 3265 1406",
    "sg:postcode":"4034",
    "sg:province":"QLD",
    "wof:name":"Walsh Ivan M",
    "wof:placetype":"venue"
},
  "geometry": {"coordinates":[153.060547,-27.353319],"type":"Point"}
}