{
  "type": "Feature",
  "properties": {
    "addr:full":"Finucane Rd Alexandra Hills QLD 4161",
    "addr:postcode":"4161",
    "addr:street":"Finucane Rd",
    "iso:country":"AU",
    "sg:address":"Finucane Rd",
    "sg:city":"Alexandra Hills",
    "sg:classifiers":[
        {
            "category":"Fast Food",
            "type":"Food & Drink"
        }
    ],
    "sg:phone":"+61 7 3824 1803",
    "sg:postcode":"4161",
    "sg:province":"QLD",
    "sg:tags":[
        "away",
        "take"
    ],
    "wof:name":"Little Mermaid Seafood",
    "wof:placetype":"venue"
},
  "geometry": {"coordinates":[153.22972106899999,-27.5240459442],"type":"Point"}
}