{
  "type": "Feature",
  "properties": {
    "addr:full":"1/ 21 Hennessy Rd Bunbury WA 6230",
    "addr:housenumber":"/ 21",
    "addr:postcode":"6230",
    "addr:street":"Hennessy Rd",
    "iso:country":"AU",
    "sg:address":"1/ 21 Hennessy Rd",
    "sg:city":"Bunbury",
    "sg:classifiers":[
        {
            "category":"Home & Garden",
            "subcategory":"Garden Supply",
            "type":"Retail Goods"
        }
    ],
    "sg:phone":"+61 8 9721 9033",
    "sg:postcode":"6230",
    "sg:province":"WA",
    "sg:tags":[
        "equipment",
        "hydroponics"
    ],
    "wof:name":"Great Southern Hydroponics",
    "wof:placetype":"venue"
},
  "geometry": {"coordinates":[115.653893,-33.340935],"type":"Point"}
}