{
  "type": "Feature",
  "properties": {
    "iso:country":"AU",
    "sg:address":"The Westbury 221 Darlinghurst Rd",
    "sg:city":"Darlinghurst",
    "sg:classifiers":[
        {
            "category":"Real Estate",
            "subcategory":"Real Estate Agent",
            "type":"Services"
        }
    ],
    "sg:phone":"+61 2 9331 6990",
    "sg:postcode":"2010",
    "sg:province":"NSW",
    "sg:tags":[
        "consultant",
        "heritage"
    ],
    "wof:name":"Heritage Solutions",
    "wof:placetype":"venue"
},
  "geometry": {"coordinates":[151.220413208,-33.8777999878],"type":"Point"}
}