{
  "type": "Feature",
  "properties": {
    "iso:country":"AU",
    "sg:address":"8th Ave",
    "sg:city":"Palm Beach",
    "sg:classifiers":[
        {
            "category":"Personal",
            "subcategory":"Piercing",
            "type":"Services"
        }
    ],
    "sg:phone":"+61 7 5534 3211",
    "sg:postcode":"4221",
    "sg:province":"QLD",
    "sg:tags":[
        "body",
        "ear"
    ],
    "wof:name":"Tattoo Paradise",
    "wof:placetype":"venue"
},
  "geometry": {"coordinates":[153.47105407699999,-28.1184520721],"type":"Point"}
}