{
  "type": "Feature",
  "properties": {
    "iso:country":"AU",
    "sg:address":"7 Frayne Crt",
    "sg:city":"Highton",
    "sg:classifiers":[
        {
            "category":"Real Estate",
            "subcategory":"Real Estate Operator",
            "type":"Services"
        }
    ],
    "sg:phone":"+61 417 379 067",
    "sg:postcode":"3216",
    "sg:province":"VIC",
    "sg:tags":[
        "concrete",
        "pumping"
    ],
    "wof:name":"Highton Concrete Pumping",
    "wof:placetype":"venue"
},
  "geometry": {"coordinates":[144.32170105,-38.1907691956],"type":"Point"}
}