{
  "type": "Feature",
  "properties": {
    "iso:country":"AU",
    "sg:address":"Inverell Rd",
    "sg:city":"Moree",
    "sg:classifiers":[
        {
            "category":"Home & Garden",
            "subcategory":"Garden Supply",
            "type":"Retail Goods"
        }
    ],
    "sg:phone":"+61 2 6752 2154",
    "sg:postcode":"2400",
    "sg:province":"NSW",
    "sg:tags":[
        "landscape"
    ],
    "wof:name":"Johnstone Concrete Pty. Ltd.",
    "wof:placetype":"venue"
},
  "geometry": {"coordinates":[149.859207153,-29.4930229187],"type":"Point"}
}