{
  "type": "Feature",
  "properties": {
    "addr:full":"20 Henry Ave Ultimo NSW 2007",
    "addr:housenumber":"20",
    "addr:postcode":"2007",
    "addr:street":"Henry Ave",
    "iso:country":"AU",
    "sg:address":"20 Henry Ave",
    "sg:city":"Ultimo",
    "sg:classifiers":[
        {
            "category":"Education",
            "subcategory":"Music School",
            "type":"Public Place"
        }
    ],
    "sg:phone":"+61 2 9518 9399",
    "sg:postcode":"2007",
    "sg:province":"NSW",
    "sg:tags":[
        "teacher"
    ],
    "wof:name":"Androse Music",
    "wof:placetype":"venue"
},
  "geometry": {"coordinates":[151.19627380399999,-33.8763961792],"type":"Point"}
}