{
  "type": "Feature",
  "properties": {
    "addr:full":"Sunshine Plaza Ocean St Maroochydore QLD 4558",
    "addr:postcode":"4558",
    "addr:street":"Ocean St",
    "iso:country":"AU",
    "sg:address":"Sunshine Plaza Ocean St",
    "sg:city":"Maroochydore",
    "sg:classifiers":[
        {
            "category":"Banks & Credit Unions",
            "subcategory":"Bank",
            "type":"Services"
        }
    ],
    "sg:phone":"+61 7 5443 6866",
    "sg:postcode":"4558",
    "sg:province":"QLD",
    "wof:name":"Bendigo Bank",
    "wof:placetype":"venue"
},
  "geometry": {"coordinates":[153.09083557100001,-26.6521549225],"type":"Point"}
}