{
  "type": "Feature",
  "properties": {
    "addr:full":"1308 Dornoch Drv Sunbury VIC 3429",
    "addr:housenumber":"1308",
    "addr:postcode":"3429",
    "addr:street":"Dornoch Drv",
    "iso:country":"AU",
    "sg:address":"1308 Dornoch Drv",
    "sg:city":"Sunbury",
    "sg:classifiers":[
        {
            "category":"Health Services",
            "subcategory":"Doctor",
            "type":"Services"
        }
    ],
    "sg:phone":"+61 3 9740 9555",
    "sg:postcode":"3429",
    "sg:province":"VIC",
    "sg:tags":[
        "podiatrist"
    ],
    "wof:name":"Anna Kalajdzic",
    "wof:placetype":"venue"
},
  "geometry": {"coordinates":[144.75006103499999,-37.5789413452],"type":"Point"}
}