{
  "type": "Feature",
  "properties": {
    "iso:country":"AU",
    "sg:address":"Factory 2 72 Hallam Rd",
    "sg:city":"Hallam",
    "sg:classifiers":[
        {
            "category":"Retail",
            "subcategory":"Auto Repair",
            "type":"Services"
        }
    ],
    "sg:phone":"+61 3 9796 5339",
    "sg:postcode":"3803",
    "sg:province":"VIC",
    "sg:tags":[
        "repairer",
        "motor",
        "engineer"
    ],
    "wof:name":"C K Mechanical Repairs",
    "wof:placetype":"venue"
},
  "geometry": {"coordinates":[145.27146911599999,-38.0156784058],"type":"Point"}
}