{
  "type": "Feature",
  "properties": {
    "addr:full":"24 Galway St Seaford VIC 3198",
    "addr:housenumber":"24",
    "addr:postcode":"3198",
    "addr:street":"Galway St",
    "iso:country":"AU",
    "sg:address":"24 Galway St",
    "sg:city":"Seaford",
    "sg:classifiers":[
        {
            "category":"Structure",
            "subcategory":"Building",
            "type":"Public Place"
        }
    ],
    "sg:phone":"+61 411 123 448",
    "sg:postcode":"3198",
    "sg:province":"VIC",
    "sg:tags":[
        "sail",
        "shade"
    ],
    "wof:name":"Slim Shadys",
    "wof:placetype":"venue"
},
  "geometry": {"coordinates":[145.14338684099999,-38.1083831787],"type":"Point"}
}