{
  "type": "Feature",
  "properties": {
    "addr:full":"6 Church St Stanley TAS 7331",
    "addr:housenumber":"6",
    "addr:postcode":"7331",
    "addr:street":"Church St",
    "iso:country":"AU",
    "sg:address":"6 Church St",
    "sg:city":"Stanley",
    "sg:classifiers":[
        {
            "category":"Cafe",
            "type":"Food & Drink"
        }
    ],
    "sg:phone":"+61 3 6458 1202",
    "sg:postcode":"7331",
    "sg:province":"TAS",
    "wof:name":"Stranded Whale Cafe",
    "wof:placetype":"venue"
},
  "geometry": {"coordinates":[145.29640197800001,-40.7614555359],"type":"Point"}
}