{
  "type": "Feature",
  "properties": {
    "addr:full":"111 Rooty Hill Rd North Rooty Hill NSW 2766",
    "addr:housenumber":"111",
    "addr:postcode":"2766",
    "addr:street":"Rooty Hill Rd North Rooty",
    "iso:country":"AU",
    "sg:address":"111 Rooty Hill Rd North",
    "sg:city":"Rooty Hill",
    "sg:classifiers":[
        {
            "category":"Utilities",
            "type":"Services"
        }
    ],
    "sg:phone":"+61 2 9832 3868",
    "sg:postcode":"2766",
    "sg:province":"NSW",
    "sg:tags":[
        "refrigeration",
        "industrial",
        "commercial",
        "retail"
    ],
    "wof:name":"Comet -Refrigeration",
    "wof:placetype":"venue"
},
  "geometry": {"coordinates":[150.83985900900001,-33.7663650513],"type":"Point"}
}