{
  "type": "Feature",
  "properties": {
    "addr:full":"Jolly St Belconnen ACT 2617",
    "addr:postcode":"2617",
    "addr:street":"Jolly St",
    "iso:country":"AU",
    "sg:address":"Jolly St",
    "sg:city":"Belconnen",
    "sg:classifiers":[
        {
            "category":"Professional",
            "type":"Services"
        }
    ],
    "sg:phone":"+61 2 6253 1980",
    "sg:postcode":"2617",
    "sg:province":"ACT",
    "sg:tags":[
        "spray",
        "painting"
    ],
    "wof:name":"Burgins Body works",
    "wof:placetype":"venue"
},
  "geometry": {"coordinates":[149.06002807600001,-35.2407722473],"type":"Point"}
}