{
  "type": "Feature",
  "properties": {
    "addr:full":"4 Isma Crt Mundijong WA 6123",
    "addr:housenumber":"4",
    "addr:postcode":"6123",
    "addr:street":"Isma Crt",
    "iso:country":"AU",
    "sg:address":"4 Isma Crt",
    "sg:city":"Mundijong",
    "sg:classifiers":[
        {
            "category":"Wholesale",
            "subcategory":"Machinery & Supplies",
            "type":"Manufacturing & Wholesale Goods"
        }
    ],
    "sg:phone":"+61 8 9525 5658",
    "sg:postcode":"6123",
    "sg:province":"WA",
    "sg:tags":[
        "equipment",
        "hydraulic"
    ],
    "wof:name":"DG & HM Services",
    "wof:placetype":"venue"
},
  "geometry": {"coordinates":[115.988121033,-32.2859306335],"type":"Point"}
}