{
  "type": "Feature",
  "properties": {
    "addr:full":"PO Box 4008 Auburn South VIC 3122",
    "addr:postcode":"3122",
    "iso:country":"AU",
    "sg:address":"PO Box 4008",
    "sg:city":"Auburn South",
    "sg:classifiers":[
        {
            "category":"Health Services",
            "subcategory":"Health Practitioner",
            "type":"Services"
        }
    ],
    "sg:phone":"+61 3 9882 8982",
    "sg:postcode":"3122",
    "sg:province":"VIC",
    "sg:tags":[
        "psychotherapist"
    ],
    "wof:name":"The Victorian Psychotherapy Service",
    "wof:placetype":"venue"
},
  "geometry": {"coordinates":[145.04258727999999,-37.8319511414],"type":"Point"}
}