{
  "type": "Feature",
  "properties": {
    "addr:full":"Shop 5, 18 Kerta Rd Kincumber NSW 2251",
    "addr:housenumber":"shop;18",
    "addr:postcode":"2251",
    "addr:street":"Kerta Rd",
    "iso:country":"AU",
    "sg:address":"Shop 5, 18 Kerta Rd",
    "sg:city":"Kincumber",
    "sg:classifiers":[
        {
            "category":"Professional",
            "subcategory":"Engineering",
            "type":"Services"
        }
    ],
    "sg:phone":"+61 2 4368 1426",
    "sg:postcode":"2251",
    "sg:province":"NSW",
    "sg:tags":[
        "engineer",
        "mechanical"
    ],
    "wof:name":"Ken's Automotive",
    "wof:placetype":"venue"
},
  "geometry": {"coordinates":[151.39476013199999,-33.4741897583],"type":"Point"}
}