{
  "type": "Feature",
  "properties": {
    "addr:full":"2 Leyland Rd Ferntree Gully VIC 3156",
    "addr:housenumber":"2",
    "addr:postcode":"3156",
    "addr:street":"Leyland Rd",
    "iso:country":"AU",
    "sg:address":"2 Leyland Rd",
    "sg:city":"Ferntree Gully",
    "sg:classifiers":[
        {
            "category":"Education",
            "subcategory":"Dance Studio",
            "type":"Public Place"
        }
    ],
    "sg:phone":"+61 3 9758 1366",
    "sg:postcode":"3156",
    "sg:province":"VIC",
    "sg:tags":[
        "venue",
        "tuition"
    ],
    "wof:name":"Tempo Dance Company",
    "wof:placetype":"venue"
},
  "geometry": {"coordinates":[145.27427673299999,-37.8882446289],"type":"Point"}
}