{
  "type": "Feature",
  "properties": {
    "addr:full":"6 Devon Drv Blackburn VIC 3130",
    "addr:housenumber":"6",
    "addr:postcode":"3130",
    "addr:street":"Devon Drv",
    "iso:country":"AU",
    "sg:address":"6 Devon Drv",
    "sg:city":"Blackburn",
    "sg:classifiers":[
        {
            "category":"Building & Trades",
            "subcategory":"Construction",
            "type":"Services"
        }
    ],
    "sg:phone":"+61 3 9877 4740",
    "sg:postcode":"3130",
    "sg:province":"VIC",
    "sg:tags":[
        "fencing",
        "contractor"
    ],
    "wof:name":"Devon Fencing",
    "wof:placetype":"venue"
},
  "geometry": {"coordinates":[145.16027832,-37.807636261],"type":"Point"}
}