{
  "type": "Feature",
  "properties": {
    "iso:country":"AU",
    "sg:address":"8 Como St",
    "sg:city":"Malvern",
    "sg:classifiers":[
        {
            "category":"Building & Trades",
            "subcategory":"Construction",
            "type":"Services"
        }
    ],
    "sg:phone":"+61 3 9500 1800",
    "sg:postcode":"3144",
    "sg:province":"VIC",
    "sg:tags":[
        "contractor"
    ],
    "wof:name":"May Constructions Pty Ltd",
    "wof:placetype":"venue"
},
  "geometry": {"coordinates":[145.02891540499999,-37.8578605652],"type":"Point"}
}