{
  "type": "Feature",
  "properties": {
    "addr:full":"PO Box 14 Hurstbridge VIC 3099",
    "addr:postcode":"3099",
    "iso:country":"AU",
    "sg:address":"PO Box 14",
    "sg:city":"Hurstbridge",
    "sg:classifiers":[
        {
            "category":"Health Services",
            "subcategory":"Health Practitioner",
            "type":"Services"
        }
    ],
    "sg:phone":"+61 401 490 433",
    "sg:postcode":"3099",
    "sg:province":"VIC",
    "sg:tags":[
        "hypnotherapy"
    ],
    "wof:name":"Reach Counselling",
    "wof:placetype":"venue"
},
  "geometry": {"coordinates":[145.193817139,-37.6382904053],"type":"Point"}
}