{
  "type": "Feature",
  "properties": {
    "iso:country":"AU",
    "sg:address":"4 Nari Drv",
    "sg:city":"Sheidow Park",
    "sg:classifiers":[
        {
            "category":"Home & Garden",
            "subcategory":"Building Materials",
            "type":"Retail Goods"
        }
    ],
    "sg:phone":"+61 8 8414 5269",
    "sg:postcode":"5158",
    "sg:province":"SA",
    "sg:tags":[
        "lawn",
        "cutting",
        "maintenance"
    ],
    "wof:name":"Brians Lawn Service",
    "wof:placetype":"venue"
},
  "geometry": {"coordinates":[138.52752685600001,-35.0719490051],"type":"Point"}
}