{
  "type": "Feature",
  "properties": {
    "iso:country":"AU",
    "sg:address":"340 Main Rd West St",
    "sg:city":"Albans",
    "sg:classifiers":[
        {
            "category":"Real Estate",
            "subcategory":"Real Estate Agent",
            "type":"Services"
        }
    ],
    "sg:phone":"+61 3 9366 8888",
    "sg:postcode":"3021",
    "sg:province":"VIC",
    "wof:name":"Bells Real Estate",
    "wof:placetype":"venue"
},
  "geometry": {"coordinates":[144.77113299999999,-37.741165],"type":"Point"}
}