{
  "type": "Feature",
  "properties": {
    "iso:country":"AU",
    "sg:address":"428 Princes Hwy",
    "sg:city":"Corrimal",
    "sg:classifiers":[
        {
            "category":"Home & Garden",
            "subcategory":"Carpets & Floor Coverings",
            "type":"Retail Goods"
        }
    ],
    "sg:phone":"+61 2 4283 4918",
    "sg:postcode":"2518",
    "sg:province":"NSW",
    "sg:tags":[
        "tile",
        "wall"
    ],
    "wof:name":"Corrimal Ceramic Tiles Pty Ltd",
    "wof:placetype":"venue"
},
  "geometry": {"coordinates":[150.896103,-34.381477],"type":"Point"}
}