{
  "type": "Feature",
  "properties": {
    "addr:full":"Shp105/ 92 Cleveland St Chippendale NSW 2008",
    "addr:housenumber":"92",
    "addr:postcode":"2008",
    "addr:street":"Cleveland St",
    "iso:country":"AU",
    "sg:address":"Shp105/ 92 Cleveland St",
    "sg:city":"Chippendale",
    "sg:classifiers":[
        {
            "category":"Food & Beverages",
            "subcategory":"Supermarket",
            "type":"Retail Goods"
        }
    ],
    "sg:phone":"+61 2 8394 9481",
    "sg:postcode":"2008",
    "sg:province":"NSW",
    "sg:tags":[
        "grocery",
        "store"
    ],
    "wof:name":"Dolphin Square Grocery Store",
    "wof:placetype":"venue"
},
  "geometry": {"coordinates":[151.196868897,-33.8881874084],"type":"Point"}
}