{
  "type": "Feature",
  "properties": {
    "addr:full":"267 - 271 Belgrave - Gembrook Rd Emerald VIC 3782",
    "addr:housenumber":"271",
    "addr:postcode":"3782",
    "addr:street":"Belgrave Gembrook Rd",
    "iso:country":"AU",
    "sg:address":"267 - 271 Belgrave - Gembrook Rd",
    "sg:city":"Emerald",
    "sg:classifiers":[
        {
            "category":"Social Services",
            "subcategory":"Child Care",
            "type":"Services"
        }
    ],
    "sg:phone":"+61 3 5968 5820",
    "sg:postcode":"3782",
    "sg:province":"VIC",
    "wof:name":"Jolly Jumbucks Childcare Centre",
    "wof:placetype":"venue"
},
  "geometry": {"coordinates":[145.43855300000001,-37.931995],"type":"Point"}
}