{
  "type": "Feature",
  "properties": {
    "addr:full":"Unit 2/ 134 Edensor Rd Bonnyrigg NSW 2177",
    "addr:housenumber":"/ 134",
    "addr:postcode":"2177",
    "addr:street":"Edensor Rd",
    "iso:country":"AU",
    "sg:address":"Unit 2/ 134 Edensor Rd",
    "sg:city":"Bonnyrigg",
    "sg:classifiers":[
        {
            "category":"Health Services",
            "subcategory":"Health Practitioner",
            "type":"Services"
        }
    ],
    "sg:phone":"+61 2 8786 1388",
    "sg:postcode":"2177",
    "sg:province":"NSW",
    "sg:tags":[
        "pathologist",
        "speech"
    ],
    "wof:name":"Talking In Steps",
    "wof:placetype":"venue"
},
  "geometry": {"coordinates":[150.89254760700001,-33.8841400146],"type":"Point"}
}