{
  "type": "Feature",
  "properties": {
    "iso:country":"AU",
    "sg:address":"7 Alfrieda St",
    "sg:city":"St Albans",
    "sg:classifiers":[
        {
            "category":"Food & Beverages",
            "subcategory":"Bakery",
            "type":"Retail Goods"
        }
    ],
    "sg:phone":"+61 3 9366 3702",
    "sg:postcode":"3021",
    "sg:province":"VIC",
    "sg:tags":[
        "baker"
    ],
    "wof:name":"Victoria Cake Shop",
    "wof:placetype":"venue"
},
  "geometry": {"coordinates":[144.800415,-37.743973],"type":"Point"}
}