{
  "type": "Feature",
  "properties": {
    "addr:full":"7 Alfrieda St St Albans VIC 3021",
    "addr:housenumber":"7",
    "addr:postcode":"3021",
    "addr:street":"Alfrieda St",
    "iso:country":"AU",
    "sg:address":"7 Alfrieda St",
    "sg:city":"St Albans",
    "sg:classifiers":[
        {
            "category":"Food & Beverages",
            "subcategory":"Bakery",
            "type":"Retail Goods"
        }
    ],
    "sg:phone":"+61 3 9366 3702",
    "sg:postcode":"3021",
    "sg:province":"VIC",
    "sg:tags":[
        "baker"
    ],
    "wof:name":"Victoria Cake Shop",
    "wof:placetype":"venue"
},
  "geometry": {"coordinates":[144.80041499999999,-37.743973],"type":"Point"}
}