{
  "type": "Feature",
  "properties": {
    "addr:full":"57 Hannah St Beecroft NSW 2119",
    "addr:housenumber":"57",
    "addr:postcode":"2119",
    "addr:street":"Hannah St",
    "iso:country":"AU",
    "sg:address":"57 Hannah St",
    "sg:city":"Beecroft",
    "sg:classifiers":[
        {
            "category":"Wholesale",
            "subcategory":"Home Furnishings",
            "type":"Manufacturing & Wholesale Goods"
        }
    ],
    "sg:phone":"+61 2 9484 7218",
    "sg:postcode":"2119",
    "sg:province":"NSW",
    "sg:tags":[
        "wholesaler",
        "curtain",
        "mfrs"
    ],
    "wof:name":"Robyn Morris Soft Furnishings Work Room",
    "wof:placetype":"venue"
},
  "geometry": {"coordinates":[151.058197022,-33.7505950928],"type":"Point"}
}