{
  "type": "Feature",
  "properties": {
    "iso:country":"AU",
    "sg:address":"Carinya Glen Davis Rd",
    "sg:city":"Capertee",
    "sg:classifiers":[
        {
            "category":"Mining & Drilling",
            "type":"Manufacturing & Wholesale Goods"
        }
    ],
    "sg:phone":"+61 2 6359 0103",
    "sg:postcode":"2846",
    "sg:province":"NSW",
    "sg:tags":[
        "colliery"
    ],
    "wof:name":"B P Coal Development Australia Pty Ltd",
    "wof:placetype":"venue"
},
  "geometry": {"coordinates":[149.984634,-33.145355],"type":"Point"}
}