{
  "type": "Feature",
  "properties": {
    "iso:country":"AU",
    "sg:address":"2A Walcott St",
    "sg:city":"Mt Lawley",
    "sg:classifiers":[
        {
            "category":"Banks & Credit Unions",
            "subcategory":"Financial Services",
            "type":"Services"
        }
    ],
    "sg:phone":"+61 8 9473 0225",
    "sg:postcode":"6050",
    "sg:province":"WA",
    "sg:tags":[
        "loan",
        "finance",
        "mortgage"
    ],
    "wof:name":"Perth Mortgage Consulting Pty Ltd",
    "wof:placetype":"venue"
},
  "geometry": {"coordinates":[115.876792908,-31.9381313324],"type":"Point"}
}