{
  "type": "Feature",
  "properties": {
    "addr:full":"70 Princes Hwy Tailem Bend SA 5260",
    "addr:housenumber":"70",
    "addr:postcode":"5260",
    "addr:street":"Princes Hwy",
    "iso:country":"AU",
    "sg:address":"70 Princes Hwy",
    "sg:city":"Tailem Bend",
    "sg:classifiers":[
        {
            "category":"Health Services",
            "subcategory":"Doctor",
            "type":"Services"
        }
    ],
    "sg:phone":"+61 8 8572 3555",
    "sg:postcode":"5260",
    "sg:province":"SA",
    "sg:tags":[
        "medical",
        "practitioner"
    ],
    "wof:name":"Tailem Bend Medical Centre",
    "wof:placetype":"venue"
},
  "geometry": {"coordinates":[139.45367431599999,-35.2555885315],"type":"Point"}
}