{
  "type": "Feature",
  "properties": {
    "addr:full":"Suite 18/ 16 Tryon Rd Lindfield NSW 2070",
    "addr:housenumber":"18 / 16",
    "addr:postcode":"2070",
    "addr:street":"Tryon Rd",
    "iso:country":"AU",
    "sg:address":"Suite 18/ 16 Tryon Rd",
    "sg:city":"Lindfield",
    "sg:classifiers":[
        {
            "category":"Health Services",
            "subcategory":"Health Practitioner",
            "type":"Services"
        }
    ],
    "sg:phone":"+61 412 131 714",
    "sg:postcode":"2070",
    "sg:province":"NSW",
    "sg:tags":[
        "psychologist"
    ],
    "wof:name":"Bartlett Coralee",
    "wof:placetype":"venue"
},
  "geometry": {"coordinates":[151.170776367,-33.774810791],"type":"Point"}
}