{
  "type": "Feature",
  "properties": {
    "iso:country":"AU",
    "sg:address":"Shop 31 Flinders St",
    "sg:city":"(Cnr Waterford Drive West) Hillarys",
    "sg:classifiers":[
        {
            "category":"Health Services",
            "subcategory":"Dentist",
            "type":"Services"
        }
    ],
    "sg:phone":"+61 8 9403 2477",
    "sg:postcode":"6025",
    "sg:province":"WA",
    "sg:tags":[
        "dental",
        "prosthetist"
    ],
    "wof:name":"W.A. Denture Clinics",
    "wof:placetype":"venue"
},
  "geometry": {"coordinates":[115.751953125,-31.8088645935],"type":"Point"}
}