{
  "type": "Feature",
  "properties": {
    "addr:full":"26 Nicholson Pde Cronulla NSW 2230",
    "addr:housenumber":"26",
    "addr:postcode":"2230",
    "addr:street":"Nicholson Pde",
    "iso:country":"AU",
    "sg:address":"26 Nicholson Pde",
    "sg:city":"Cronulla",
    "sg:classifiers":[
        {
            "category":"Food & Beverages",
            "subcategory":"Groceries & Convenience Stores",
            "type":"Retail Goods"
        }
    ],
    "sg:phone":"+61 2 9523 0620",
    "sg:postcode":"2230",
    "sg:province":"NSW",
    "wof:name":"Grocery Plus",
    "wof:placetype":"venue"
},
  "geometry": {"coordinates":[151.151153564,-34.0593109131],"type":"Point"}
}