{
  "type": "Feature",
  "properties": {
    "addr:full":"Shop T/105 Werribee Plaza Cnr Derrimutt Rd & Heath Werribee VIC 3030",
    "addr:housenumber":"105",
    "addr:postcode":"3030",
    "addr:street":"T;Werribee Plaza Cnr Derrimutt Rd & Heath",
    "iso:country":"AU",
    "sg:address":"Shop T/105 Werribee Plaza Cnr Derrimutt Rd & Heath",
    "sg:city":"Werribee",
    "sg:classifiers":[
        {
            "category":"Retail",
            "subcategory":"Repair Shop",
            "type":"Services"
        }
    ],
    "sg:phone":"+61 3 9748 5800",
    "sg:postcode":"3030",
    "sg:province":"VIC",
    "sg:tags":[
        "handbag"
    ],
    "wof:name":"Divine Werribee",
    "wof:placetype":"venue"
},
  "geometry": {"coordinates":[144.64335600000001,-37.887569],"type":"Point"}
}