{
  "type": "Feature",
  "properties": {
    "addr:full":"21 Limestone Ave Reid ACT 2612",
    "addr:housenumber":"21",
    "addr:postcode":"2612",
    "addr:street":"Limestone Ave",
    "iso:country":"AU",
    "sg:address":"21 Limestone Ave",
    "sg:city":"Reid",
    "sg:classifiers":[
        {
            "category":"Health Services",
            "subcategory":"Chiropractor",
            "type":"Services"
        }
    ],
    "sg:phone":"+61 2 6247 2493",
    "sg:postcode":"2612",
    "sg:province":"ACT",
    "wof:name":"Birubi Therapeutic Centre",
    "wof:placetype":"venue"
},
  "geometry": {"coordinates":[149.14474487300001,-35.2785949707],"type":"Point"}
}