{
  "type": "Feature",
  "properties": {
    "iso:country":"AU",
    "sg:address":"99 South Pine Rd",
    "sg:city":"Brendale",
    "sg:classifiers":[
        {
            "category":"Wholesale",
            "subcategory":"Auto Parts",
            "type":"Manufacturing & Wholesale Goods"
        }
    ],
    "sg:phone":"+61 7 3205 3477",
    "sg:postcode":"4500",
    "sg:province":"QLD",
    "sg:tags":[
        "recyclers"
    ],
    "wof:name":"All Auto Recycling",
    "wof:placetype":"venue"
},
  "geometry": {"coordinates":[152.982788086,-27.3267192841],"type":"Point"}
}