{
  "type": "Feature",
  "properties": {
    "addr:full":"1- 4 Linden Crt Morwell VIC 3840",
    "addr:housenumber":"4",
    "addr:postcode":"3840",
    "addr:street":"Linden Crt",
    "iso:country":"AU",
    "sg:address":"1- 4 Linden Crt",
    "sg:city":"Morwell",
    "sg:classifiers":[
        {
            "category":"Travel",
            "subcategory":"Hostel",
            "type":"Entertainment"
        }
    ],
    "sg:phone":"+61 3 5134 8403",
    "sg:postcode":"3840",
    "sg:province":"VIC",
    "sg:tags":[
        "home"
    ],
    "wof:name":"Gracedale Lodge",
    "wof:placetype":"venue"
},
  "geometry": {"coordinates":[146.43119812,-38.232170105],"type":"Point"}
}