{
  "type": "Feature",
  "properties": {
    "addr:full":"22 Aubreen St Collaroy Plateau NSW 2097",
    "addr:housenumber":"22",
    "addr:postcode":"2097",
    "addr:street":"Aubreen St",
    "iso:country":"AU",
    "sg:address":"22 Aubreen St",
    "sg:city":"Collaroy Plateau",
    "sg:classifiers":[
        {
            "category":"Food & Beverages",
            "subcategory":"Groceries & Convenience Stores",
            "type":"Retail Goods"
        }
    ],
    "sg:phone":"+61 2 9971 9647",
    "sg:postcode":"2097",
    "sg:province":"NSW",
    "wof:name":"Plateau Seven Days Food",
    "wof:placetype":"venue"
},
  "geometry": {"coordinates":[151.292572022,-33.7303276062],"type":"Point"}
}