{
  "type": "Feature",
  "properties": {
    "iso:country":"AU",
    "sg:address":"127 Mount Gambier Rd",
    "sg:city":"Millicent",
    "sg:classifiers":[
        {
            "category":"Fast Food",
            "type":"Food & Drink"
        }
    ],
    "sg:phone":"+61 8 8733 3992",
    "sg:postcode":"5280",
    "sg:province":"SA",
    "sg:tags":[
        "away",
        "take"
    ],
    "wof:name":"Millicent Chickenland",
    "wof:placetype":"venue"
},
  "geometry": {"coordinates":[140.364685,-37.60741],"type":"Point"}
}