{
  "type": "Feature",
  "properties": {
    "iso:country":"AU",
    "sg:address":"45 River St",
    "sg:city":"Mackay",
    "sg:classifiers":[
        {
            "category":"Health Services",
            "subcategory":"Health Practitioner",
            "type":"Services"
        }
    ],
    "sg:phone":"+61 428 285 397",
    "sg:postcode":"4740",
    "sg:province":"QLD",
    "sg:tags":[
        "psychologist"
    ],
    "wof:name":"Kate Elliott",
    "wof:placetype":"venue"
},
  "geometry": {"coordinates":[149.184891,-21.138758],"type":"Point"}
}