{
  "type": "Feature",
  "properties": {
    "addr:full":"4 Warneford St South Hobart TAS 7004",
    "addr:housenumber":"4",
    "addr:postcode":"7004",
    "addr:street":"Warneford St",
    "iso:country":"AU",
    "sg:address":"4 Warneford St",
    "sg:city":"South Hobart",
    "sg:classifiers":[
        {
            "category":"Health Services",
            "subcategory":"Doctor",
            "type":"Services"
        }
    ],
    "sg:phone":"+61 3 6224 1926",
    "sg:postcode":"7004",
    "sg:province":"TAS",
    "sg:tags":[
        "medical",
        "practitioner"
    ],
    "wof:name":"Graham S R",
    "wof:placetype":"venue"
},
  "geometry": {"coordinates":[147.32034301799999,-42.8898963928],"type":"Point"}
}