{
  "type": "Feature",
  "properties": {
    "addr:full":"126 Byron St Inverell NSW 2360",
    "addr:housenumber":"126",
    "addr:postcode":"2360",
    "addr:street":"Byron St",
    "iso:country":"AU",
    "sg:address":"126 Byron St",
    "sg:city":"Inverell",
    "sg:classifiers":[
        {
            "category":"Utilities",
            "subcategory":"Water",
            "type":"Services"
        }
    ],
    "sg:phone":"+61 2 6721 1006",
    "sg:postcode":"2360",
    "sg:province":"NSW",
    "sg:tags":[
        "hot",
        "system"
    ],
    "wof:name":"MacIntyre Gas",
    "wof:placetype":"venue"
},
  "geometry": {"coordinates":[151.11712646500001,-29.7697105408],"type":"Point"}
}