{
  "type": "Feature",
  "properties": {
    "addr:full":"10 Mond St Thorneside QLD 4158",
    "addr:housenumber":"10",
    "addr:postcode":"4158",
    "addr:street":"Mond St",
    "iso:country":"AU",
    "sg:address":"10 Mond St",
    "sg:city":"Thorneside",
    "sg:classifiers":[
        {
            "category":"Professional",
            "subcategory":"Engineering",
            "type":"Services"
        }
    ],
    "sg:phone":"+61 7 3822 2500",
    "sg:postcode":"4158",
    "sg:province":"QLD",
    "sg:tags":[
        "engineer"
    ],
    "wof:name":"M.W.F. General Engineering",
    "wof:placetype":"venue"
},
  "geometry": {"coordinates":[153.20121765100001,-27.4901313782],"type":"Point"}
}