{
  "type": "Feature",
  "properties": {
    "addr:full":"10 Milford Rd Ellis Lane NSW 2570",
    "addr:housenumber":"10",
    "addr:postcode":"2570",
    "addr:street":"Milford Rd;Lane",
    "iso:country":"AU",
    "sg:address":"10 Milford Rd",
    "sg:city":"Ellis Lane",
    "sg:classifiers":[
        {
            "category":"Building & Trades",
            "subcategory":"Equipment Rental",
            "type":"Services"
        }
    ],
    "sg:phone":"+61 408 863 862",
    "sg:postcode":"2570",
    "sg:province":"NSW",
    "sg:tags":[
        "demolition",
        "contractor"
    ],
    "wof:name":"Brett Jones Bobcat & Tipper Hire",
    "wof:placetype":"venue"
},
  "geometry": {"coordinates":[150.68867492699999,-34.0894622803],"type":"Point"}
}