{
  "type": "Feature",
  "properties": {
    "iso:country":"AU",
    "sg:address":"Anzac Ave",
    "sg:city":"Yarra Glen",
    "sg:classifiers":[
        {
            "category":"Education",
            "subcategory":"Kindergarten",
            "type":"Public Place"
        }
    ],
    "sg:phone":"+61 3 9730 1490",
    "sg:postcode":"3775",
    "sg:province":"VIC",
    "sg:tags":[
        "pre-schools"
    ],
    "wof:name":"Yarra Glen Pre-School Association",
    "wof:placetype":"venue"
},
  "geometry": {"coordinates":[145.373825,-37.656963],"type":"Point"}
}