{
  "type": "Feature",
  "properties": {
    "addr:full":"25 Freshwater Creek Rd Mango Hill QLD 4509",
    "addr:housenumber":"25",
    "addr:postcode":"4509",
    "addr:street":"Freshwater Creek Rd",
    "iso:country":"AU",
    "sg:address":"25 Freshwater Creek Rd",
    "sg:city":"Mango Hill",
    "sg:classifiers":[
        {
            "category":"Professional",
            "subcategory":"Computer Services",
            "type":"Services"
        }
    ],
    "sg:phone":"+61 7 3886 5273",
    "sg:postcode":"4509",
    "sg:province":"QLD",
    "sg:tags":[
        "package",
        "software"
    ],
    "wof:name":"Matna Services",
    "wof:placetype":"venue"
},
  "geometry": {"coordinates":[153.021087647,-27.2480430603],"type":"Point"}
}