{
  "type": "Feature",
  "properties": {
    "addr:full":"Gormans Hill Rd Bathurst NSW 2795",
    "addr:postcode":"2795",
    "addr:street":"Gormans Hill Rd",
    "iso:country":"AU",
    "sg:address":"Gormans Hill Rd",
    "sg:city":"Bathurst",
    "sg:classifiers":[
        {
            "category":"Health Services",
            "subcategory":"Doctor",
            "type":"Services"
        }
    ],
    "sg:phone":"+61 2 6334 8620",
    "sg:postcode":"2795",
    "sg:province":"NSW",
    "sg:tags":[
        "medical",
        "practitioner"
    ],
    "wof:name":"McClymont Rod Dr",
    "wof:placetype":"venue"
},
  "geometry": {"coordinates":[149.582199097,-33.4737319946],"type":"Point"}
}