{
  "type": "Feature",
  "properties": {
    "iso:country":"AU",
    "sg:address":"1/ 447 Sydney Rd",
    "sg:city":"Balgowlah",
    "sg:classifiers":[
        {
            "category":"Home & Garden",
            "subcategory":"Building Materials",
            "type":"Retail Goods"
        }
    ],
    "sg:phone":"+61 2 9949 5405",
    "sg:postcode":"2093",
    "sg:province":"NSW",
    "sg:tags":[
        "ventilating",
        "equipment",
        "system"
    ],
    "wof:name":"Expella Pty Ltd",
    "wof:placetype":"venue"
},
  "geometry": {"coordinates":[151.258743286,-33.7945518494],"type":"Point"}
}