{
  "type": "Feature",
  "properties": {
    "addr:full":"243 High St Maitland NSW 2320",
    "addr:housenumber":"243",
    "addr:postcode":"2320",
    "addr:street":"High St",
    "iso:country":"AU",
    "sg:address":"243 High St",
    "sg:city":"Maitland",
    "sg:classifiers":[
        {
            "category":"Travel",
            "subcategory":"Hotels & Motels",
            "type":"Entertainment"
        }
    ],
    "sg:phone":"+61 2 4934 5097",
    "sg:postcode":"2320",
    "sg:province":"NSW",
    "sg:tags":[
        "accommodation"
    ],
    "wof:name":"Queens Arms Hotel",
    "wof:placetype":"venue"
},
  "geometry": {"coordinates":[151.55764770499999,-32.7337989807],"type":"Point"}
}