{
  "type": "Feature",
  "properties": {
    "addr:full":"116 Grafton St Cairns QLD 4870",
    "addr:housenumber":"116",
    "addr:postcode":"4870",
    "addr:street":"Grafton St",
    "iso:country":"AU",
    "sg:address":"116 Grafton St",
    "sg:city":"Cairns",
    "sg:classifiers":[
        {
            "category":"Banks & Credit Unions",
            "subcategory":"Bank",
            "type":"Services"
        }
    ],
    "sg:phone":"+61 7 4052 1399",
    "sg:postcode":"4870",
    "sg:province":"QLD",
    "sg:tags":[
        "equipment",
        "sale",
        "point"
    ],
    "wof:name":"Cairns-Copy",
    "wof:placetype":"venue"
},
  "geometry": {"coordinates":[145.77415466299999,-16.9219093323],"type":"Point"}
}