{
  "type": "Feature",
  "properties": {
    "addr:full":"347 Shepparton Rd East Victoria Park WA 6101",
    "addr:housenumber":"347",
    "addr:postcode":"6101",
    "addr:street":"Shepparton Rd",
    "iso:country":"AU",
    "sg:address":"347 Shepparton Rd",
    "sg:city":"East Victoria Park",
    "sg:classifiers":[
        {
            "category":"Fast Food",
            "type":"Food & Drink"
        }
    ],
    "sg:phone":"+61 8 9362 5374",
    "sg:postcode":"6101",
    "sg:province":"WA",
    "sg:tags":[
        "away",
        "take"
    ],
    "wof:name":"Red Rooster",
    "wof:placetype":"venue"
},
  "geometry": {"coordinates":[115.91216278100001,-31.991645813],"type":"Point"}
}