{
  "type": "Feature",
  "properties": {
    "addr:full":"1st Floor 53 Wilson St Burnie TAS 7320",
    "addr:housenumber":"53",
    "addr:postcode":"7320",
    "addr:street":"Wilson St",
    "iso:country":"AU",
    "sg:address":"1st Floor 53 Wilson St",
    "sg:city":"Burnie",
    "sg:classifiers":[
        {
            "category":"Professional",
            "subcategory":"Accounting & Tax Preparation",
            "type":"Services"
        }
    ],
    "sg:phone":"+61 3 6432 1018",
    "sg:postcode":"7320",
    "sg:province":"TAS",
    "sg:tags":[
        "consultant",
        "taxation"
    ],
    "wof:name":"Platinum Accounting",
    "wof:placetype":"venue"
},
  "geometry": {"coordinates":[145.906937,-41.050785],"type":"Point"}
}