{
  "type": "Feature",
  "properties": {
    "iso:country":"AU",
    "sg:address":"11 St Clair Rd",
    "sg:city":"Legana",
    "sg:classifiers":[
        {
            "category":"Building & Trades",
            "subcategory":"Construction",
            "type":"Services"
        }
    ],
    "sg:phone":"+61 3 6330 2942",
    "sg:postcode":"7277",
    "sg:province":"TAS",
    "sg:tags":[
        "renovation",
        "alterations",
        "extension",
        "contractor"
    ],
    "wof:name":"Just Renovations",
    "wof:placetype":"venue"
},
  "geometry": {"coordinates":[147.04811096200001,-41.3580322266],"type":"Point"}
}