{
  "type": "Feature",
  "properties": {
    "addr:full":"89 Zillman Rd Clayfield QLD 4011",
    "addr:housenumber":"89",
    "addr:postcode":"4011",
    "addr:street":"Zillman Rd",
    "iso:country":"AU",
    "sg:address":"89 Zillman Rd",
    "sg:city":"Clayfield",
    "sg:classifiers":[
        {
            "category":"Health Services",
            "subcategory":"Health Practitioner",
            "type":"Services"
        }
    ],
    "sg:phone":"+61 7 3268 2142",
    "sg:postcode":"4011",
    "sg:province":"QLD",
    "sg:tags":[
        "acupuncture"
    ],
    "wof:name":"Best Richard",
    "wof:placetype":"venue"
},
  "geometry": {"coordinates":[153.06426999999999,-27.418489],"type":"Point"}
}