{
  "type": "Feature",
  "properties": {
    "iso:country":"AU",
    "sg:address":"82 Carinya La",
    "sg:city":"Jindabyne",
    "sg:classifiers":[
        {
            "category":"Sports & Exercise",
            "subcategory":"Ski Resort",
            "type":"Entertainment"
        }
    ],
    "sg:phone":"+61 2 6456 2252",
    "sg:postcode":"2627",
    "sg:province":"NSW",
    "sg:tags":[
        "tour",
        "centres"
    ],
    "wof:name":"Carinya Alpine Village",
    "wof:placetype":"venue"
},
  "geometry": {"coordinates":[148.631515503,-36.4704322815],"type":"Point"}
}