{
  "type": "Feature",
  "properties": {
    "addr:full":"110 Shaftesbury St Tarragindi QLD 4121",
    "addr:housenumber":"110",
    "addr:postcode":"4121",
    "addr:street":"Shaftesbury St",
    "iso:country":"AU",
    "sg:address":"110 Shaftesbury St",
    "sg:city":"Tarragindi",
    "sg:classifiers":[
        {
            "category":"Utilities",
            "subcategory":"Electric",
            "type":"Services"
        }
    ],
    "sg:phone":"+61 7 3848 5886",
    "sg:postcode":"4121",
    "sg:province":"QLD",
    "sg:tags":[
        "electrical",
        "contractor"
    ],
    "wof:name":"Thomas K C & J M, Electrical Contractors",
    "wof:placetype":"venue"
},
  "geometry": {"coordinates":[153.04171752900001,-27.5224781036],"type":"Point"}
}