{
  "type": "Feature",
  "properties": {
    "addr:full":"13 Elvina Ave Newport NSW 2106",
    "addr:housenumber":"13",
    "addr:postcode":"2106",
    "addr:street":"Elvina Ave",
    "iso:country":"AU",
    "sg:address":"13 Elvina Ave",
    "sg:city":"Newport",
    "sg:classifiers":[
        {
            "category":"Professional",
            "subcategory":"Management & Consulting",
            "type":"Services"
        }
    ],
    "sg:phone":"+61 2 9979 9492",
    "sg:postcode":"2106",
    "sg:province":"NSW",
    "sg:tags":[
        "consultant"
    ],
    "wof:name":"Daly Research Systems Pty Ltd",
    "wof:placetype":"venue"
},
  "geometry": {"coordinates":[151.30604553200001,-33.6488609314],"type":"Point"}
}