{
  "type": "Feature",
  "properties": {
    "addr:full":"Ste 7, 126-128 Avoca St Randwick NSW 2031",
    "addr:housenumber":"126-128",
    "addr:postcode":"2031",
    "addr:street":"Avoca St",
    "iso:country":"AU",
    "sg:address":"Ste 7, 126-128 Avoca St",
    "sg:city":"Randwick",
    "sg:classifiers":[
        {
            "category":"Health Services",
            "subcategory":"Health Practitioner",
            "type":"Services"
        }
    ],
    "sg:phone":"+61 2 8249 8198",
    "sg:postcode":"2031",
    "sg:province":"NSW",
    "sg:tags":[
        "psychologist"
    ],
    "wof:name":"Randwick Psychology Centre",
    "wof:placetype":"venue"
},
  "geometry": {"coordinates":[151.24180602999999,-33.9133262634],"type":"Point"}
}