{
  "type": "Feature",
  "properties": {
    "iso:country":"AU",
    "sg:address":"11 Walls Rd",
    "sg:city":"Werribee",
    "sg:classifiers":[
        {
            "category":"Building & Trades",
            "subcategory":"Cleaning & Sanitation",
            "type":"Services"
        }
    ],
    "sg:phone":"+61 3 9731 8206",
    "sg:postcode":"3030",
    "sg:province":"VIC",
    "sg:tags":[
        "industrial",
        "commercial",
        "contractor"
    ],
    "wof:name":"Mambourin Cleaning Contractors",
    "wof:placetype":"venue"
},
  "geometry": {"coordinates":[144.637894,-37.897598],"type":"Point"}
}