{
  "type": "Feature",
  "properties": {
    "addr:full":"8 Kalambo Pl St Clair NSW 2759",
    "addr:housenumber":"8",
    "addr:postcode":"2759",
    "addr:street":"Kalambo Pl St",
    "iso:country":"AU",
    "sg:address":"8 Kalambo Pl St",
    "sg:city":"Clair",
    "sg:classifiers":[
        {
            "category":"Professional",
            "subcategory":"Art Services",
            "type":"Services"
        }
    ],
    "sg:phone":"+61 2 9834 4047",
    "sg:postcode":"2759",
    "sg:province":"NSW",
    "sg:tags":[
        "graphic",
        "designer"
    ],
    "wof:name":"Cut &#039;n&#039; Paste Graphics",
    "wof:placetype":"venue"
},
  "geometry": {"coordinates":[150.80113220199999,-33.7933731079],"type":"Point"}
}