{
  "type": "Feature",
  "properties": {
    "addr:full":"Leisure Centre Heaths Rd Mackay QLD 4740",
    "addr:postcode":"4740",
    "addr:street":"Heaths Rd",
    "iso:country":"AU",
    "sg:address":"Leisure Centre Heaths Rd",
    "sg:city":"Mackay",
    "sg:classifiers":[
        {
            "category":"Personal",
            "type":"Services"
        }
    ],
    "sg:phone":"+61 7 4942 0755",
    "sg:postcode":"4740",
    "sg:province":"QLD",
    "sg:tags":[
        "reducing",
        "treatment",
        "weight"
    ],
    "wof:name":"Jenny Craig Weight Loss Centres Pty Ltd",
    "wof:placetype":"venue"
},
  "geometry": {"coordinates":[149.14956699999999,-21.128792],"type":"Point"}
}