{
  "type": "Feature",
  "properties": {
    "addr:full":"PO Box 613 Glen Innes NSW 2370",
    "addr:postcode":"2370",
    "iso:country":"AU",
    "sg:address":"PO Box 613",
    "sg:city":"Glen Innes",
    "sg:classifiers":[
        {
            "category":"Banks & Credit Unions",
            "subcategory":"Investment Brokerage",
            "type":"Services"
        }
    ],
    "sg:phone":"+61 2 6734 5467",
    "sg:postcode":"2370",
    "sg:province":"NSW",
    "sg:tags":[
        "debt",
        "collection"
    ],
    "wof:name":"C.N.P. Commercial Services",
    "wof:placetype":"venue"
},
  "geometry": {"coordinates":[151.733352661,-29.7349205017],"type":"Point"}
}