{
  "type": "Feature",
  "properties": {
    "addr:full":"25 Pound Rd Warrandyte VIC 3113",
    "addr:housenumber":"25",
    "addr:postcode":"3113",
    "addr:street":"Pound Rd",
    "iso:country":"AU",
    "sg:address":"25 Pound Rd",
    "sg:city":"Warrandyte",
    "sg:classifiers":[
        {
            "category":"Industrial Area",
            "type":"Public Place"
        }
    ],
    "sg:phone":"+61 3 9844 1861",
    "sg:postcode":"3113",
    "sg:province":"VIC",
    "sg:tags":[
        "consulting",
        "chemist"
    ],
    "wof:name":"SST Australia Pty Ltd",
    "wof:placetype":"venue"
},
  "geometry": {"coordinates":[145.19705200199999,-37.7465400696],"type":"Point"}
}