{
  "type": "Feature",
  "properties": {
    "addr:full":"Shop 3 , Cleveland Town Square Cleveland QLD 4163",
    "addr:housenumber":"shop 3",
    "addr:postcode":"4163",
    "addr:street":"Town Square",
    "iso:country":"AU",
    "sg:address":"Shop 3",
    "sg:city":", Cleveland Town Square Cleveland",
    "sg:classifiers":[
        {
            "category":"Personal",
            "subcategory":"Beauty Salon",
            "type":"Services"
        }
    ],
    "sg:phone":"+61 7 3821 3566",
    "sg:postcode":"4163",
    "sg:province":"QLD",
    "wof:name":"Beautizone Skin Care & Make Up Clinic",
    "wof:placetype":"venue"
},
  "geometry": {"coordinates":[153.26077270499999,-27.5186653137],"type":"Point"}
}