{
  "type": "Feature",
  "properties": {
    "addr:full":"Shop 1 Urangan Central Shopping Cntr Boat Harbour Urangan QLD 4655",
    "addr:housenumber":"shop 1",
    "addr:postcode":"4655",
    "iso:country":"AU",
    "sg:address":"Shop 1 Urangan Central Shopping Cntr Boat Harbour",
    "sg:city":"Urangan",
    "sg:classifiers":[
        {
            "category":"Communications",
            "subcategory":"Film & Video Production",
            "type":"Services"
        }
    ],
    "sg:phone":"+61 7 4124 9911",
    "sg:postcode":"4655",
    "sg:province":"QLD",
    "sg:tags":[
        "dvd",
        "library"
    ],
    "wof:name":"Video 2000",
    "wof:placetype":"venue"
},
  "geometry": {"coordinates":[152.89634699999999,-25.29294],"type":"Point"}
}