{
  "type": "Feature",
  "properties": {
    "addr:full":"381 King St Newtown NSW 2042",
    "addr:housenumber":"381",
    "addr:postcode":"2042",
    "addr:street":"King St",
    "iso:country":"AU",
    "sg:address":"381 King St",
    "sg:city":"Newtown",
    "sg:classifiers":[
        {
            "category":"Cafe",
            "type":"Food & Drink"
        }
    ],
    "sg:phone":"+61 2 9550 5337",
    "sg:postcode":"2042",
    "sg:province":"NSW",
    "wof:name":"Papaver cafe",
    "wof:placetype":"venue"
},
  "geometry": {"coordinates":[151.177673,-33.899368],"type":"Point"}
}