{
  "type": "Feature",
  "properties": {
    "addr:full":"51- 55 Lockwood Rd Shepparton VIC 3630",
    "addr:housenumber":"55",
    "addr:postcode":"3630",
    "addr:street":"Lockwood Rd",
    "iso:country":"AU",
    "sg:address":"51- 55 Lockwood Rd",
    "sg:city":"Shepparton",
    "sg:classifiers":[
        {
            "category":"Retail",
            "subcategory":"Auto Repair",
            "type":"Services"
        }
    ],
    "sg:phone":"+61 3 5821 9344",
    "sg:postcode":"3630",
    "sg:province":"VIC",
    "sg:tags":[
        "beater",
        "painter",
        "panel"
    ],
    "wof:name":"Heywood's Smash Repairs",
    "wof:placetype":"venue"
},
  "geometry": {"coordinates":[145.41607665999999,-36.3822097778],"type":"Point"}
}