{
  "type": "Feature",
  "properties": {
    "addr:full":"264 Macquarie St Liverpool NSW 2170",
    "addr:housenumber":"264",
    "addr:postcode":"2170",
    "addr:street":"Macquarie St",
    "iso:country":"AU",
    "sg:address":"264 Macquarie St",
    "sg:city":"Liverpool",
    "sg:classifiers":[
        {
            "category":"Personal",
            "subcategory":"Beauty Salon",
            "type":"Services"
        }
    ],
    "sg:phone":"+61 2 9602 5673",
    "sg:postcode":"2170",
    "sg:province":"NSW",
    "sg:tags":[
        "hairdresser"
    ],
    "wof:name":"Sigi's His & Hers Hairdressing",
    "wof:placetype":"venue"
},
  "geometry": {"coordinates":[150.92372131400001,-33.9233818054],"type":"Point"}
}