{
  "type": "Feature",
  "properties": {
    "addr:full":"Nirranda St Concord West NSW 2138",
    "addr:postcode":"2138",
    "addr:street":"Nirranda St",
    "iso:country":"AU",
    "sg:address":"Nirranda St",
    "sg:city":"Concord West",
    "sg:classifiers":[
        {
            "category":"Retail",
            "subcategory":"Event Space",
            "type":"Services"
        }
    ],
    "sg:phone":"+61 2 9743 1308",
    "sg:postcode":"2138",
    "sg:province":"NSW",
    "sg:tags":[
        "function",
        "organiser"
    ],
    "wof:name":"Concord RSL Club Auditorium",
    "wof:placetype":"venue"
},
  "geometry": {"coordinates":[151.090042114,-33.8489074707],"type":"Point"}
}