{
  "type": "Feature",
  "properties": {
    "addr:full":"358 Rokeby Rd Subiaco WA 6008",
    "addr:housenumber":"358",
    "addr:postcode":"6008",
    "addr:street":"Rokeby Rd",
    "iso:country":"AU",
    "sg:address":"358 Rokeby Rd",
    "sg:city":"Subiaco",
    "sg:classifiers":[
        {
            "category":"Banks & Credit Unions",
            "subcategory":"Financial Services",
            "type":"Services"
        }
    ],
    "sg:phone":"+61 8 9388 7007",
    "sg:postcode":"6008",
    "sg:province":"WA",
    "sg:tags":[
        "planning"
    ],
    "wof:name":"Vertex Financial Solutions",
    "wof:placetype":"venue"
},
  "geometry": {"coordinates":[115.824073791,-31.9549541473],"type":"Point"}
}