{
  "type": "Feature",
  "properties": {
    "addr:full":"Shop 7, 130 Main Rd McLaren Vale SA 5171",
    "addr:housenumber":"shop 7 130",
    "addr:postcode":"5171",
    "addr:street":"Main Rd",
    "iso:country":"AU",
    "sg:address":"Shop 7, 130 Main Rd",
    "sg:city":"McLaren Vale",
    "sg:classifiers":[
        {
            "category":"Health Services",
            "subcategory":"Chiropractor",
            "type":"Services"
        }
    ],
    "sg:phone":"+61 8 8323 8696",
    "sg:postcode":"5171",
    "sg:province":"SA",
    "wof:name":"Southern Vales Chiropractic Centre",
    "wof:placetype":"venue"
},
  "geometry": {"coordinates":[138.537200928,-35.2150039673],"type":"Point"}
}