{
  "type": "Feature",
  "properties": {
    "addr:full":"415 New Canterbury Rd Dulwich Hill NSW 2203",
    "addr:housenumber":"415",
    "addr:postcode":"2203",
    "addr:street":"New Canterbury Rd",
    "iso:country":"AU",
    "sg:address":"415 New Canterbury Rd",
    "sg:city":"Dulwich Hill",
    "sg:classifiers":[
        {
            "category":"Home & Garden",
            "subcategory":"Hardware",
            "type":"Retail Goods"
        }
    ],
    "sg:phone":"+61 2 9564 1103",
    "sg:postcode":"2203",
    "sg:province":"NSW",
    "sg:tags":[
        "repair",
        "tool",
        "power"
    ],
    "wof:name":"Sam's Power Tools Pty Ltd",
    "wof:placetype":"venue"
},
  "geometry": {"coordinates":[151.136505,-33.905704],"type":"Point"}
}