{
  "type": "Feature",
  "properties": {
    "addr:full":"Shp1/ 35 Ocean Keys Blv Clarkson WA 6030",
    "addr:housenumber":"35",
    "addr:postcode":"6030",
    "addr:street":"Ocean Keys Blv",
    "iso:country":"AU",
    "sg:address":"Shp1/ 35 Ocean Keys Blv",
    "sg:city":"Clarkson",
    "sg:classifiers":[
        {
            "category":"Fast Food",
            "type":"Food & Drink"
        }
    ],
    "sg:phone":"+61 8 9408 5979",
    "sg:postcode":"6030",
    "sg:province":"WA",
    "sg:tags":[
        "away",
        "take"
    ],
    "wof:name":"Sensation Devine",
    "wof:placetype":"venue"
},
  "geometry": {"coordinates":[115.718139648,-31.6894512177],"type":"Point"}
}