{
  "type": "Feature",
  "properties": {
    "addr:full":"10 Edward St Hastings VIC 3915",
    "addr:housenumber":"10",
    "addr:postcode":"3915",
    "addr:street":"Edward St",
    "iso:country":"AU",
    "sg:address":"10 Edward St",
    "sg:city":"Hastings",
    "sg:classifiers":[
        {
            "category":"Train Station",
            "subcategory":"Light Rail",
            "type":"Transportation"
        }
    ],
    "sg:phone":"+61 419 181 784",
    "sg:postcode":"3915",
    "sg:province":"VIC",
    "sg:tags":[
        "equipment",
        "energy",
        "solar"
    ],
    "wof:name":"Sontech Solar",
    "wof:placetype":"venue"
},
  "geometry": {"coordinates":[145.192504883,-38.3118476868],"type":"Point"}
}