{
  "type": "Feature",
  "properties": {
    "iso:country":"AU",
    "sg:address":"246 Port Elliot Rd",
    "sg:city":"Victor Harbor",
    "sg:classifiers":[
        {
            "category":"Home & Garden",
            "subcategory":"Carpets & Floor Coverings",
            "type":"Retail Goods"
        }
    ],
    "sg:phone":"+61 8 8552 5108",
    "sg:postcode":"5211",
    "sg:province":"SA",
    "sg:tags":[
        "tile",
        "wall"
    ],
    "wof:name":"Beaumont Tiles",
    "wof:placetype":"venue"
},
  "geometry": {"coordinates":[138.64625549300001,-35.5356140137],"type":"Point"}
}