{
  "type": "Feature",
  "properties": {
    "addr:full":"195 McKanes Falls Rd Lithgow NSW 2790",
    "addr:housenumber":"195",
    "addr:postcode":"2790",
    "addr:street":"Mckanes Falls Rd",
    "iso:country":"AU",
    "sg:address":"195 McKanes Falls Rd",
    "sg:city":"Lithgow",
    "sg:classifiers":[
        {
            "category":"Building & Trades",
            "subcategory":"Construction",
            "type":"Services"
        }
    ],
    "sg:phone":"+61 2 6353 1511",
    "sg:postcode":"2790",
    "sg:province":"NSW",
    "sg:tags":[
        "fitting",
        "line",
        "electric",
        "power"
    ],
    "wof:name":"Valley Electrical Services",
    "wof:placetype":"venue"
},
  "geometry": {"coordinates":[150.12782287600001,-33.5328407288],"type":"Point"}
}