{
  "type": "Feature",
  "properties": {
    "iso:country":"AU",
    "sg:address":"345 King St",
    "sg:city":"Newtown",
    "sg:classifiers":[
        {
            "category":"Shopping",
            "subcategory":"Clothing, Apparel, & Fashions",
            "type":"Retail Goods"
        }
    ],
    "sg:phone":"+61 1300 660 810",
    "sg:postcode":"2042",
    "sg:province":"NSW",
    "sg:tags":[
        "lady",
        "wear"
    ],
    "sg:website":"http://www.slimsvintage.com.au",
    "wof:name":"Slims Vintage",
    "wof:placetype":"venue"
},
  "geometry": {"coordinates":[151.17799400000001,-33.898418],"type":"Point"}
}