{
  "type": "Feature",
  "properties": {
    "addr:full":"95 Harrow Rd Auburn NSW 2144",
    "addr:housenumber":"95",
    "addr:postcode":"2144",
    "addr:street":"Harrow Rd",
    "iso:country":"AU",
    "sg:address":"95 Harrow Rd",
    "sg:city":"Auburn",
    "sg:classifiers":[
        {
            "category":"Professional",
            "subcategory":"Art Services",
            "type":"Services"
        }
    ],
    "sg:phone":"+61 413 316 009",
    "sg:postcode":"2144",
    "sg:province":"NSW",
    "sg:tags":[
        "decorator",
        "painter"
    ],
    "wof:name":"Alfrate Painting",
    "wof:placetype":"venue"
},
  "geometry": {"coordinates":[151.029571533,-33.8603973389],"type":"Point"}
}