{
  "type": "Feature",
  "properties": {
    "addr:full":"Munns Rd Woorabinda QLD 4702",
    "addr:postcode":"4702",
    "addr:street":"Munns Rd",
    "iso:country":"AU",
    "sg:address":"Munns Rd",
    "sg:city":"Woorabinda",
    "sg:classifiers":[
        {
            "category":"Fast Food",
            "type":"Food & Drink"
        }
    ],
    "sg:phone":"+61 7 4935 0411",
    "sg:postcode":"4702",
    "sg:province":"QLD",
    "sg:tags":[
        "away",
        "take"
    ],
    "wof:name":"Woorabinda Takeaway",
    "wof:placetype":"venue"
},
  "geometry": {"coordinates":[150.06239318900001,-23.6835422516],"type":"Point"}
}