{
  "type": "Feature",
  "properties": {
    "addr:full":"14 Renwick St Wyoming NSW 2250",
    "addr:housenumber":"14",
    "addr:postcode":"2250",
    "addr:street":"Renwick St",
    "iso:country":"AU",
    "sg:address":"14 Renwick St",
    "sg:city":"Wyoming",
    "sg:classifiers":[
        {
            "category":"Health Services",
            "subcategory":"Doctor",
            "type":"Services"
        }
    ],
    "sg:phone":"+61 2 4329 5940",
    "sg:postcode":"2250",
    "sg:province":"NSW",
    "sg:tags":[
        "podiatrist"
    ],
    "wof:name":"Drysdale Michelle",
    "wof:placetype":"venue"
},
  "geometry": {"coordinates":[151.35166931099999,-33.4034233093],"type":"Point"}
}