{
  "type": "Feature",
  "properties": {
    "addr:full":"Shop 8,Homestead Shopping Centre Roxburgh Park VIC 3064",
    "addr:housenumber":"shop 8",
    "addr:postcode":"3064",
    "iso:country":"AU",
    "sg:address":"Shop 8,Homestead Shopping Centre",
    "sg:city":"Roxburgh Park",
    "sg:classifiers":[
        {
            "category":"Real Estate",
            "subcategory":"Real Estate Agent",
            "type":"Services"
        }
    ],
    "sg:phone":"+61 3 9308 7777",
    "sg:postcode":"3064",
    "sg:province":"VIC",
    "wof:name":"Professionals",
    "wof:placetype":"venue"
},
  "geometry": {"coordinates":[144.932571411,-37.6225013733],"type":"Point"}
}