{
  "type": "Feature",
  "properties": {
    "addr:full":"92 Cessnock Rd Weston NSW 2326",
    "addr:housenumber":"92",
    "addr:postcode":"2326",
    "addr:street":"Cessnock Rd",
    "iso:country":"AU",
    "sg:address":"92 Cessnock Rd",
    "sg:city":"Weston",
    "sg:classifiers":[
        {
            "category":"Shopping",
            "subcategory":"Baby Store",
            "type":"Retail Goods"
        }
    ],
    "sg:phone":"+61 2 4936 4122",
    "sg:postcode":"2326",
    "sg:province":"NSW",
    "sg:tags":[
        "children's",
        "wear"
    ],
    "wof:name":"Jimmy Two Feathers",
    "wof:placetype":"venue"
},
  "geometry": {"coordinates":[151.45628356899999,-32.8145751953],"type":"Point"}
}