{
  "type": "Feature",
  "properties": {
    "iso:country":"AU",
    "sg:address":"21 Willcock St",
    "sg:city":"Ardross",
    "sg:classifiers":[
        {
            "category":"Professional",
            "subcategory":"Art Services",
            "type":"Services"
        }
    ],
    "sg:phone":"+61 8 9364 6420",
    "sg:postcode":"6153",
    "sg:province":"WA",
    "sg:tags":[
        "interior",
        "decorator"
    ],
    "wof:name":"Barbe Interiors",
    "wof:placetype":"venue"
},
  "geometry": {"coordinates":[115.834137,-32.02243],"type":"Point"}
}