{
  "type": "Feature",
  "properties": {
    "iso:country":"AU",
    "sg:address":"378 Clarendon St",
    "sg:city":"South Melbourne",
    "sg:classifiers":[
        {
            "category":"Banks & Credit Unions",
            "subcategory":"Bank",
            "type":"Services"
        }
    ],
    "sg:phone":"+61 3 8699 3700",
    "sg:postcode":"3205",
    "sg:province":"VIC",
    "wof:name":"Bank of Queensland",
    "wof:placetype":"venue"
},
  "geometry": {"coordinates":[144.961655,-37.835735],"type":"Point"}
}