{
  "type": "Feature",
  "properties": {
    "iso:country":"AU",
    "sg:address":"Veitch Rd",
    "sg:city":"Osborne",
    "sg:classifiers":[
        {
            "category":"Ferry Terminal",
            "type":"Transportation"
        }
    ],
    "sg:phone":"+61 8 8440 9770",
    "sg:postcode":"5017",
    "sg:province":"SA",
    "sg:tags":[
        "bulk",
        "storage",
        "liquid"
    ],
    "wof:name":"Terminals Pty Ltd",
    "wof:placetype":"venue"
},
  "geometry": {"coordinates":[138.501495361,-34.789691925],"type":"Point"}
}