{
  "type": "Feature",
  "properties": {
    "iso:country":"AU",
    "sg:address":"157 Welshpool Rd",
    "sg:city":"Welshpool",
    "sg:classifiers":[
        {
            "category":"Utilities",
            "subcategory":"Refuse",
            "type":"Services"
        }
    ],
    "sg:phone":"+61 8 9451 4666",
    "sg:postcode":"6106",
    "sg:province":"WA",
    "sg:tags":[
        "wholesale",
        "glassware",
        "china",
        "earthenware"
    ],
    "wof:name":"Stoneage Ceramics (Aust)",
    "wof:placetype":"venue"
},
  "geometry": {"coordinates":[115.970252991,-32.0027389526],"type":"Point"}
}