{
  "type": "Feature",
  "properties": {
    "iso:country":"AU",
    "sg:address":"40 Illawong St",
    "sg:city":"Lugarno",
    "sg:classifiers":[
        {
            "category":"Wholesale",
            "subcategory":"Non-durable Goods",
            "type":"Manufacturing & Wholesale Goods"
        }
    ],
    "sg:phone":"+61 2 9534 7422",
    "sg:postcode":"2210",
    "sg:province":"NSW",
    "sg:tags":[
        "wholesaler",
        "mfrs",
        "cosmetic"
    ],
    "wof:name":"Down Under Cosmetics",
    "wof:placetype":"venue"
},
  "geometry": {"coordinates":[151.049545,-33.985497],"type":"Point"}
}