{
  "type": "Feature",
  "properties": {
    "iso:country":"AU",
    "sg:address":"193a Imlay St",
    "sg:city":"Eden",
    "sg:classifiers":[
        {
            "category":"Personal",
            "subcategory":"Beauty Salon",
            "type":"Services"
        }
    ],
    "sg:phone":"+61 2 6496 3238",
    "sg:postcode":"2551",
    "sg:province":"NSW",
    "sg:tags":[
        "hairdresser"
    ],
    "wof:name":"Images Hairdressing",
    "wof:placetype":"venue"
},
  "geometry": {"coordinates":[149.91143798799999,-37.0730552673],"type":"Point"}
}