{
  "type": "Feature",
  "properties": {
    "addr:full":"58 Walder Rd Hammondville NSW 2170",
    "addr:housenumber":"58",
    "addr:postcode":"2170",
    "addr:street":"Walder Rd",
    "iso:country":"AU",
    "sg:address":"58 Walder Rd",
    "sg:city":"Hammondville",
    "sg:classifiers":[
        {
            "category":"Food & Beverages",
            "subcategory":"Liquor & Beverages",
            "type":"Retail Goods"
        }
    ],
    "sg:phone":"+61 2 9825 3273",
    "sg:postcode":"2170",
    "sg:province":"NSW",
    "sg:tags":[
        "store"
    ],
    "wof:name":"Hammondville Cellars",
    "wof:placetype":"venue"
},
  "geometry": {"coordinates":[150.95506286599999,-33.9483757019],"type":"Point"}
}