{
  "type": "Feature",
  "properties": {
    "iso:country":"AU",
    "sg:address":"4/ 18 Jacana Ave",
    "sg:city":"Woorim",
    "sg:classifiers":[
        {
            "category":"Retail",
            "subcategory":"Funeral Services",
            "type":"Services"
        }
    ],
    "sg:phone":"+61 7 3408 2568",
    "sg:postcode":"4507",
    "sg:province":"QLD",
    "sg:tags":[
        "director"
    ],
    "wof:name":"Bribie Island Funeral Directors",
    "wof:placetype":"venue"
},
  "geometry": {"coordinates":[153.202194214,-27.0689029694],"type":"Point"}
}