{
  "type": "Feature",
  "properties": {
    "iso:country":"AU",
    "sg:address":"5- 7 Birtwill St",
    "sg:city":"Coolum Beach",
    "sg:classifiers":[
        {
            "category":"Health Services",
            "subcategory":"Dentist",
            "type":"Services"
        }
    ],
    "sg:phone":"+61 7 5446 5888",
    "sg:postcode":"4573",
    "sg:province":"QLD",
    "wof:name":"Nordang Borge Dr Nordang Kerstin Dr",
    "wof:placetype":"venue"
},
  "geometry": {"coordinates":[153.089828,-26.527212],"type":"Point"}
}