{
  "type": "Feature",
  "properties": {
    "addr:full":"PO Box 1650 Kalgoorlie WA 6430",
    "addr:postcode":"6430",
    "iso:country":"AU",
    "sg:address":"PO Box 1650",
    "sg:city":"Kalgoorlie",
    "sg:classifiers":[
        {
            "category":"Building & Trades",
            "subcategory":"Construction",
            "type":"Services"
        }
    ],
    "sg:phone":"+61 8 9022 2218",
    "sg:postcode":"6430",
    "sg:province":"WA",
    "sg:tags":[
        "concrete",
        "contractor"
    ],
    "wof:name":"Industrial Concreting",
    "wof:placetype":"venue"
},
  "geometry": {"coordinates":[121.46343231199999,-30.7528495789],"type":"Point"}
}