{
  "type": "Feature",
  "properties": {
    "iso:country":"AU",
    "sg:address":"Bellevue St",
    "sg:city":"Toowoomba",
    "sg:classifiers":[
        {
            "category":"Government",
            "subcategory":"City Hall",
            "type":"Public Place"
        }
    ],
    "sg:phone":"+61 427 039 101",
    "sg:postcode":"4350",
    "sg:province":"QLD",
    "wof:name":"QRI Toowoomba Hall",
    "wof:placetype":"venue"
},
  "geometry": {"coordinates":[151.950577,-27.554043],"type":"Point"}
}