{
  "type": "Feature",
  "properties": {
    "addr:full":"2 Miller Crt Encounter Bay SA 5211",
    "addr:housenumber":"2",
    "addr:postcode":"5211",
    "addr:street":"Miller Crt",
    "iso:country":"AU",
    "sg:address":"2 Miller Crt",
    "sg:city":"Encounter Bay",
    "sg:classifiers":[
        {
            "category":"Personal",
            "subcategory":"Beauty Salon",
            "type":"Services"
        }
    ],
    "sg:phone":"+61 8 8552 2268",
    "sg:postcode":"5211",
    "sg:province":"SA",
    "sg:tags":[
        "hairdresser"
    ],
    "wof:name":"Studio 2",
    "wof:placetype":"venue"
},
  "geometry": {"coordinates":[138.59124755900001,-35.5866355896],"type":"Point"}
}