{
  "type": "Feature",
  "properties": {
    "addr:full":"23 Taedi Ave Bray Park QLD 4500",
    "addr:housenumber":"23",
    "addr:postcode":"4500",
    "addr:street":"Taedi Ave Bray Park",
    "iso:country":"AU",
    "sg:address":"23 Taedi Ave",
    "sg:city":"Bray Park",
    "sg:classifiers":[
        {
            "category":"Utilities",
            "subcategory":"Electric",
            "type":"Services"
        }
    ],
    "sg:phone":"+61 7 3205 3362",
    "sg:postcode":"4500",
    "sg:province":"QLD",
    "sg:tags":[
        "electrical",
        "contractor"
    ],
    "wof:name":"Kinsela Electrical Pty Ltd",
    "wof:placetype":"venue"
},
  "geometry": {"coordinates":[152.966430664,-27.2951622009],"type":"Point"}
}