{
  "type": "Feature",
  "properties": {
    "addr:full":"135 Vincent Rd Wangaratta VIC 3677",
    "addr:housenumber":"135",
    "addr:postcode":"3677",
    "addr:street":"Vincent Rd",
    "iso:country":"AU",
    "sg:address":"135 Vincent Rd",
    "sg:city":"Wangaratta",
    "sg:classifiers":[
        {
            "category":"Banks & Credit Unions",
            "subcategory":"Investment Brokerage",
            "type":"Services"
        }
    ],
    "sg:phone":"+61 3 5721 3486",
    "sg:postcode":"3677",
    "sg:province":"VIC",
    "sg:tags":[
        "radiator",
        "motor"
    ],
    "wof:name":"Wangaratta Radiators",
    "wof:placetype":"venue"
},
  "geometry": {"coordinates":[146.310455322,-36.3684463501],"type":"Point"}
}