{
  "type": "Feature",
  "properties": {
    "iso:country":"AU",
    "sg:address":"Shop PO7, 100 Market St",
    "sg:city":"Sydney",
    "sg:classifiers":[
        {
            "category":"Shopping",
            "subcategory":"Clothing, Apparel, & Fashions",
            "type":"Retail Goods"
        }
    ],
    "sg:phone":"+61 2 9222 9538",
    "sg:postcode":"2000",
    "sg:province":"NSW",
    "sg:tags":[
        "lady",
        "wear"
    ],
    "wof:name":"Suite Boutique",
    "wof:placetype":"venue"
},
  "geometry": {"coordinates":[151.208374023,-33.8706283569],"type":"Point"}
}