{
  "type": "Feature",
  "properties": {
    "addr:full":"6 Roy St Wangaratta VIC 3677",
    "addr:housenumber":"6",
    "addr:postcode":"3677",
    "addr:street":"Roy St",
    "iso:country":"AU",
    "sg:address":"6 Roy St",
    "sg:city":"Wangaratta",
    "sg:classifiers":[
        {
            "category":"Travel",
            "subcategory":"Hotels & Motels",
            "type":"Entertainment"
        }
    ],
    "sg:phone":"+61 3 5721 5488",
    "sg:postcode":"3677",
    "sg:province":"VIC",
    "wof:name":"Wangaratta Motor Inn",
    "wof:placetype":"venue"
},
  "geometry": {"coordinates":[146.318115234,-36.3581771851],"type":"Point"}
}