{
  "type": "Feature",
  "properties": {
    "addr:full":"61 Selina St Wynnum North QLD 4178",
    "addr:housenumber":"61",
    "addr:postcode":"4178",
    "addr:street":"Selina St",
    "iso:country":"AU",
    "sg:address":"61 Selina St",
    "sg:city":"Wynnum North",
    "sg:classifiers":[
        {
            "category":"Professional",
            "subcategory":"Computer Services",
            "type":"Services"
        }
    ],
    "sg:phone":"+61 7 3393 4084",
    "sg:postcode":"4178",
    "sg:province":"QLD",
    "sg:tags":[
        "package",
        "software"
    ],
    "wof:name":"Dunbar C & J E Records Management",
    "wof:placetype":"venue"
},
  "geometry": {"coordinates":[153.16383361800001,-27.4363193512],"type":"Point"}
}