{
  "type": "Feature",
  "properties": {
    "addr:full":"Unit 6/ 64 Oak Rd Kirrawee NSW 2232",
    "addr:housenumber":"64",
    "addr:postcode":"2232",
    "addr:street":"Oak Rd",
    "iso:country":"AU",
    "sg:address":"Unit 6/ 64 Oak Rd",
    "sg:city":"Kirrawee",
    "sg:classifiers":[
        {
            "category":"Sports & Exercise",
            "subcategory":"Climbing Gym",
            "type":"Entertainment"
        }
    ],
    "sg:phone":"+61 2 9545 6399",
    "sg:postcode":"2232",
    "sg:province":"NSW",
    "sg:tags":[
        "repetition",
        "engineer"
    ],
    "wof:name":"Bulgin Gas Equipment Pty Ltd",
    "wof:placetype":"venue"
},
  "geometry": {"coordinates":[151.07278442399999,-34.0268554688],"type":"Point"}
}