{
  "type": "Feature",
  "properties": {
    "iso:country":"AU",
    "sg:address":"13 Fairlie Crs",
    "sg:city":"Moffat Beach",
    "sg:classifiers":[
        {
            "category":"Manufacturing",
            "subcategory":"Metals",
            "type":"Manufacturing & Wholesale Goods"
        }
    ],
    "sg:phone":"+61 448 608 714",
    "sg:postcode":"4551",
    "sg:province":"QLD",
    "sg:tags":[
        "steel",
        "fabricator",
        "mfrs"
    ],
    "wof:name":"All Style Metal Fabrications",
    "wof:placetype":"venue"
},
  "geometry": {"coordinates":[153.13778686500001,-26.7927207947],"type":"Point"}
}