{
  "type": "Feature",
  "properties": {
    "iso:country":"AU",
    "sg:address":"803 Beaudesert Rd",
    "sg:city":"Coopers Plains",
    "sg:classifiers":[
        {
            "category":"Autos & Motor Vehicles",
            "subcategory":"Auto Supplies",
            "type":"Retail Goods"
        }
    ],
    "sg:phone":"+61 7 3277 7766",
    "sg:postcode":"4108",
    "sg:province":"QLD",
    "sg:tags":[
        "equipment",
        "part",
        "truck"
    ],
    "wof:name":"Motsons Turbo Centres",
    "wof:placetype":"venue"
},
  "geometry": {"coordinates":[153.02081298799999,-27.5588874817],"type":"Point"}
}