{
  "type": "Feature",
  "properties": {
    "addr:full":"281 Lake Rd Glendale NSW 2285",
    "addr:housenumber":"281",
    "addr:postcode":"2285",
    "addr:street":"Lake Rd",
    "iso:country":"AU",
    "sg:address":"281 Lake Rd",
    "sg:city":"Glendale",
    "sg:classifiers":[
        {
            "category":"Health Services",
            "subcategory":"Doctor",
            "type":"Services"
        }
    ],
    "sg:phone":"+61 2 4954 7611",
    "sg:postcode":"2285",
    "sg:province":"NSW",
    "sg:tags":[
        "medical",
        "practitioner"
    ],
    "wof:name":"Kulasekara, Chamila",
    "wof:placetype":"venue"
},
  "geometry": {"coordinates":[151.650466919,-32.9268569946],"type":"Point"}
}