{
  "type": "Feature",
  "properties": {
    "addr:full":"6 Quartz Pl Narre Warren North VIC 3804",
    "addr:housenumber":"6",
    "addr:postcode":"3804",
    "addr:street":"Quartz Pl",
    "iso:country":"AU",
    "sg:address":"6 Quartz Pl",
    "sg:city":"Narre Warren North",
    "sg:classifiers":[
        {
            "category":"Building & Trades",
            "subcategory":"Equipment Rental",
            "type":"Services"
        }
    ],
    "sg:phone":"+61 3 8790 1800",
    "sg:postcode":"3804",
    "sg:province":"VIC",
    "sg:tags":[
        "party",
        "hire"
    ],
    "wof:name":"Marquees For Hire",
    "wof:placetype":"venue"
},
  "geometry": {"coordinates":[145.32044982900001,-37.9987945557],"type":"Point"}
}