{
  "type": "Feature",
  "properties": {
    "iso:country":"AU",
    "sg:address":"6 Florence St",
    "sg:city":"Moonah",
    "sg:classifiers":[
        {
            "category":"Organizations",
            "subcategory":"Membership Organization",
            "type":"Services"
        }
    ],
    "sg:phone":"+61 3 6278 9179",
    "sg:postcode":"7009",
    "sg:province":"TAS",
    "sg:tags":[
        "support",
        "health",
        "organisation"
    ],
    "wof:name":"Eureka Clubhouse",
    "wof:placetype":"venue"
},
  "geometry": {"coordinates":[147.29612731899999,-42.8496322632],"type":"Point"}
}