{
  "type": "Feature",
  "properties": {
    "addr:full":"Unit 9 340 Hoxton Park Rd Hoxton Park NSW 2171",
    "addr:housenumber":"340",
    "addr:postcode":"2171",
    "addr:street":"Hoxton Park Rd",
    "iso:country":"AU",
    "sg:address":"Unit 9 340 Hoxton Park Rd",
    "sg:city":"Hoxton Park",
    "sg:classifiers":[
        {
            "category":"Professional",
            "subcategory":"Detective & Security Services",
            "type":"Services"
        }
    ],
    "sg:phone":"+61 2 9608 9185",
    "sg:postcode":"2171",
    "sg:province":"NSW",
    "sg:tags":[
        "equipment",
        "window",
        "doors"
    ],
    "wof:name":"B & H Security",
    "wof:placetype":"venue"
},
  "geometry": {"coordinates":[150.85159301799999,-33.92552948],"type":"Point"}
}