{
  "type": "Feature",
  "properties": {
    "addr:full":"3 Bombora Pl Lennox Head NSW 2478",
    "addr:housenumber":"3",
    "addr:postcode":"2478",
    "addr:street":"Bombora Pl Lennox",
    "iso:country":"AU",
    "sg:address":"3 Bombora Pl",
    "sg:city":"Lennox Head",
    "sg:classifiers":[
        {
            "category":"Manufacturing",
            "subcategory":"Food",
            "type":"Manufacturing & Wholesale Goods"
        }
    ],
    "sg:phone":"+61 2 6687 6103",
    "sg:postcode":"2478",
    "sg:province":"NSW",
    "sg:tags":[
        "function",
        "catering"
    ],
    "wof:name":"Misaki Byron",
    "wof:placetype":"venue"
},
  "geometry": {"coordinates":[153.58833313,-28.8002967834],"type":"Point"}
}