{
  "type": "Feature",
  "properties": {
    "addr:full":"41 Robe St St Kilda VIC 3182",
    "addr:housenumber":"41",
    "addr:postcode":"3182",
    "addr:street":"Robe St",
    "iso:country":"AU",
    "sg:address":"41 Robe St",
    "sg:city":"St Kilda",
    "sg:classifiers":[
        {
            "category":"Travel",
            "subcategory":"Hostel",
            "type":"Entertainment"
        }
    ],
    "sg:phone":"+61 3 9534 5558",
    "sg:postcode":"3182",
    "sg:province":"VIC",
    "sg:tags":[
        "home"
    ],
    "wof:name":"Sacred Heart Homes",
    "wof:placetype":"venue"
},
  "geometry": {"coordinates":[144.97901916500001,-37.8642730713],"type":"Point"}
}