{
  "type": "Feature",
  "properties": {
    "addr:full":"6 Napier St Rye VIC 3941",
    "addr:housenumber":"6",
    "addr:postcode":"3941",
    "addr:street":"Napier St",
    "iso:country":"AU",
    "sg:address":"6 Napier St",
    "sg:city":"Rye",
    "sg:classifiers":[
        {
            "category":"Retail",
            "subcategory":"Funeral Services",
            "type":"Services"
        }
    ],
    "sg:phone":"+61 3 5985 1356",
    "sg:postcode":"3941",
    "sg:province":"VIC",
    "sg:tags":[
        "director"
    ],
    "wof:name":"Rosebud Funeral Services",
    "wof:placetype":"venue"
},
  "geometry": {"coordinates":[144.821777344,-38.3711700439],"type":"Point"}
}