{
  "type": "Feature",
  "properties": {
    "addr:full":"PO Box 48 Kin Kin QLD 4571",
    "addr:postcode":"4571",
    "iso:country":"AU",
    "sg:address":"PO Box 48",
    "sg:city":"Kin Kin",
    "sg:classifiers":[
        {
            "category":"Professional",
            "subcategory":"Computer Services",
            "type":"Services"
        }
    ],
    "sg:phone":"+61 7 5485 4444",
    "sg:postcode":"4571",
    "sg:province":"QLD",
    "sg:tags":[
        "on-line",
        "provider"
    ],
    "wof:name":"Ezeonline",
    "wof:placetype":"venue"
},
  "geometry": {"coordinates":[152.87886,-26.26355],"type":"Point"}
}