{
  "type": "Feature",
  "properties": {
    "iso:country":"AU",
    "sg:address":"2 Elizabeth St",
    "sg:city":"Berala",
    "sg:classifiers":[
        {
            "category":"Real Estate",
            "subcategory":"Real Estate Agent",
            "type":"Services"
        }
    ],
    "sg:phone":"+61 2 9646 4999",
    "sg:postcode":"2141",
    "sg:province":"NSW",
    "wof:name":"Rodi Realty",
    "wof:placetype":"venue"
},
  "geometry": {"coordinates":[151.02944946299999,-33.873260498],"type":"Point"}
}