{
  "type": "Feature",
  "properties": {
    "addr:full":"Brightview Rd Lowood QLD 4311",
    "addr:postcode":"4311",
    "addr:street":"Brightview Rd",
    "iso:country":"AU",
    "sg:address":"Brightview Rd",
    "sg:city":"Lowood",
    "sg:classifiers":[
        {
            "category":"Farming",
            "subcategory":"Farm",
            "type":"Manufacturing & Wholesale Goods"
        }
    ],
    "sg:phone":"+61 7 5427 9060",
    "sg:postcode":"4311",
    "sg:province":"QLD",
    "sg:tags":[
        "farmer"
    ],
    "wof:name":"Glentate Pty Ltd",
    "wof:placetype":"venue"
},
  "geometry": {"coordinates":[152.536254883,-27.4737510681],"type":"Point"}
}