{
  "type": "Feature",
  "properties": {
    "iso:country":"AU",
    "sg:address":"329 Logan Rd",
    "sg:city":"Stones Corner",
    "sg:classifiers":[
        {
            "category":"Wholesale",
            "subcategory":"Medical Equipment & Supplies",
            "type":"Manufacturing & Wholesale Goods"
        }
    ],
    "sg:phone":"+61 7 3394 3622",
    "sg:postcode":"4120",
    "sg:province":"QLD",
    "sg:tags":[
        "aid",
        "care",
        "health",
        "home"
    ],
    "wof:name":"Stones Corner Medical Centre",
    "wof:placetype":"venue"
},
  "geometry": {"coordinates":[153.04450988799999,-27.4986419678],"type":"Point"}
}