{
  "type": "Feature",
  "properties": {
    "addr:full":"145 Flores Rd Geraldton WA 6530",
    "addr:housenumber":"145",
    "addr:postcode":"6530",
    "addr:street":"Flores Rd",
    "iso:country":"AU",
    "sg:address":"145 Flores Rd",
    "sg:city":"Geraldton",
    "sg:classifiers":[
        {
            "category":"School Buses",
            "type":"Transportation"
        }
    ],
    "sg:phone":"+61 8 9965 2014",
    "sg:postcode":"6530",
    "sg:province":"WA",
    "sg:tags":[
        "brick"
    ],
    "wof:name":"Midland Brick",
    "wof:placetype":"venue"
},
  "geometry": {"coordinates":[114.627120972,-28.7488689423],"type":"Point"}
}