{
  "type": "Feature",
  "properties": {
    "iso:country":"AU",
    "sg:address":"65 Southern Rd",
    "sg:city":"Mentone",
    "sg:classifiers":[
        {
            "category":"Manufacturing",
            "subcategory":"Paper Products",
            "type":"Manufacturing & Wholesale Goods"
        }
    ],
    "sg:phone":"+61 3 9583 4882",
    "sg:postcode":"3194",
    "sg:province":"VIC",
    "sg:tags":[
        "box",
        "fibre",
        "carton",
        "cardboard"
    ],
    "sg:website":"http://www.graphiclam.com.au",
    "wof:name":"Graphic Laminations Pty Ltd",
    "wof:placetype":"venue"
},
  "geometry": {"coordinates":[145.088287353,-37.9777450562],"type":"Point"}
}