{
  "type": "Feature",
  "properties": {
    "addr:full":"117 Junction Rd Nowra NSW 2540",
    "addr:housenumber":"117",
    "addr:postcode":"2540",
    "addr:street":"Junction Rd",
    "iso:country":"AU",
    "sg:address":"117 Junction Rd",
    "sg:city":"Nowra",
    "sg:classifiers":[
        {
            "category":"Shopping",
            "subcategory":"Mobile Phones",
            "type":"Retail Goods"
        }
    ],
    "sg:phone":"+61 2 4423 5038",
    "sg:postcode":"2540",
    "sg:province":"NSW",
    "sg:tags":[
        "telephone",
        "accessory"
    ],
    "wof:name":"Vodafone",
    "wof:placetype":"venue"
},
  "geometry": {"coordinates":[150.602416992,-34.8743934631],"type":"Point"}
}