{
  "type": "Feature",
  "properties": {
    "addr:full":"138- 144 Clarinda St Parkes NSW 2870",
    "addr:housenumber":"144",
    "addr:postcode":"2870",
    "addr:street":"Clarinda St",
    "iso:country":"AU",
    "sg:address":"138- 144 Clarinda St",
    "sg:city":"Parkes",
    "sg:classifiers":[
        {
            "category":"Retail",
            "subcategory":"Auto Repair",
            "type":"Services"
        }
    ],
    "sg:phone":"+61 2 6862 1111",
    "sg:postcode":"2870",
    "sg:province":"NSW",
    "sg:tags":[
        "repairer",
        "motor",
        "engineer"
    ],
    "wof:name":"Parkes Hyundai",
    "wof:placetype":"venue"
},
  "geometry": {"coordinates":[148.17622399999999,-33.140781],"type":"Point"}
}