{
  "type": "Feature",
  "properties": {
    "addr:full":"77 Winbourne Rd Brookvale NSW 2100",
    "addr:housenumber":"77",
    "addr:postcode":"2100",
    "addr:street":"Winbourne Rd",
    "iso:country":"AU",
    "sg:address":"77 Winbourne Rd",
    "sg:city":"Brookvale",
    "sg:classifiers":[
        {
            "category":"Home & Garden",
            "subcategory":"Carpets & Floor Coverings",
            "type":"Retail Goods"
        }
    ],
    "sg:phone":"+61 2 9905 1876",
    "sg:postcode":"2100",
    "sg:province":"NSW",
    "sg:tags":[
        "tile",
        "wall"
    ],
    "wof:name":"Hatria Bathroom Wares",
    "wof:placetype":"venue"
},
  "geometry": {"coordinates":[151.27359008799999,-33.7622718811],"type":"Point"}
}