{
  "type": "Feature",
  "properties": {
    "iso:country":"AU",
    "sg:address":"PO Box 2224",
    "sg:city":"Rose Bay",
    "sg:classifiers":[
        {
            "category":"Home & Garden",
            "subcategory":"Building Materials",
            "type":"Retail Goods"
        }
    ],
    "sg:phone":"+61 2 9388 1562",
    "sg:postcode":"2029",
    "sg:province":"NSW",
    "sg:tags":[
        "lawn",
        "cutting",
        "maintenance"
    ],
    "wof:name":"Deckel Youval",
    "wof:placetype":"venue"
},
  "geometry": {"coordinates":[151.26568603499999,-33.8741912842],"type":"Point"}
}