{
  "type": "Feature",
  "properties": {
    "addr:full":"61 Burns Rd Springwood NSW 2777",
    "addr:housenumber":"61",
    "addr:postcode":"2777",
    "addr:street":"Burns Rd",
    "iso:country":"AU",
    "sg:address":"61 Burns Rd",
    "sg:city":"Springwood",
    "sg:classifiers":[
        {
            "category":"Personal",
            "type":"Services"
        }
    ],
    "sg:phone":"+61 1300 733 933",
    "sg:postcode":"2777",
    "sg:province":"NSW",
    "sg:tags":[
        "gift"
    ],
    "wof:name":"Complete Basketcase The",
    "wof:placetype":"venue"
},
  "geometry": {"coordinates":[150.57344055199999,-33.7076072693],"type":"Point"}
}