{
  "type": "Feature",
  "properties": {
    "addr:full":"Rosevear Pl Dickson ACT 2602",
    "addr:postcode":"2602",
    "addr:street":"Rosevear Pl",
    "iso:country":"AU",
    "sg:address":"Rosevear Pl",
    "sg:city":"Dickson",
    "sg:classifiers":[
        {
            "category":"Social Services",
            "subcategory":"Child Care",
            "type":"Services"
        }
    ],
    "sg:phone":"+61 2 6257 2255",
    "sg:postcode":"2602",
    "sg:province":"ACT",
    "wof:name":"Northside Community Service",
    "wof:placetype":"venue"
},
  "geometry": {"coordinates":[149.14358520499999,-35.2495117188],"type":"Point"}
}