{
  "type": "Feature",
  "properties": {
    "iso:country":"AU",
    "sg:address":"31 Edward St",
    "sg:city":"Bankstown",
    "sg:classifiers":[
        {
            "category":"Professional",
            "subcategory":"Accounting & Tax Preparation",
            "type":"Services"
        }
    ],
    "sg:phone":"+61 2 9708 3988",
    "sg:postcode":"2200",
    "sg:province":"NSW",
    "sg:tags":[
        "jukebox"
    ],
    "wof:name":"Funtastic Jumping Castles Pty Ltd",
    "wof:placetype":"venue"
},
  "geometry": {"coordinates":[151.027313,-33.930084],"type":"Point"}
}