{
  "type": "Feature",
  "properties": {
    "addr:full":"14 King St Doncaster East VIC 3109",
    "addr:housenumber":"14",
    "addr:postcode":"3109",
    "addr:street":"King St",
    "iso:country":"AU",
    "sg:address":"14 King St",
    "sg:city":"Doncaster East",
    "sg:classifiers":[
        {
            "category":"Professional",
            "subcategory":"Art Services",
            "type":"Services"
        }
    ],
    "sg:phone":"+61 3 9848 8898",
    "sg:postcode":"3109",
    "sg:province":"VIC",
    "sg:tags":[
        "decorator",
        "painter"
    ],
    "wof:name":"Pal's Painting Service",
    "wof:placetype":"venue"
},
  "geometry": {"coordinates":[145.147827148,-37.7733421326],"type":"Point"}
}