{
  "type": "Feature",
  "properties": {
    "addr:full":"1 Irving St Niddrie VIC 3042",
    "addr:housenumber":"1",
    "addr:postcode":"3042",
    "addr:street":"Irving St",
    "iso:country":"AU",
    "sg:address":"1 Irving St",
    "sg:city":"Niddrie",
    "sg:classifiers":[
        {
            "category":"Building & Trades",
            "subcategory":"Construction",
            "type":"Services"
        }
    ],
    "sg:phone":"+61 3 9335 4157",
    "sg:postcode":"3042",
    "sg:province":"VIC",
    "sg:tags":[
        "contractor"
    ],
    "wof:name":"Pro Start Constructions Pty Ltd",
    "wof:placetype":"venue"
},
  "geometry": {"coordinates":[144.890716553,-37.7354316711],"type":"Point"}
}