{
  "type": "Feature",
  "properties": {
    "addr:full":"Level 3, 120 Sussex St Sydney NSW 2000",
    "addr:housenumber":"120",
    "addr:postcode":"2000",
    "addr:street":"Sussex St",
    "iso:country":"AU",
    "sg:address":"Level 3, 120 Sussex St",
    "sg:city":"Sydney",
    "sg:classifiers":[
        {
            "category":"Professional",
            "subcategory":"Management & Consulting",
            "type":"Services"
        }
    ],
    "sg:phone":"+61 2 9249 3320",
    "sg:postcode":"2000",
    "sg:province":"NSW",
    "sg:tags":[
        "consultant"
    ],
    "wof:name":"Futurum",
    "wof:placetype":"venue"
},
  "geometry": {"coordinates":[151.203735352,-33.8682365417],"type":"Point"}
}