{
  "type": "Feature",
  "properties": {
    "iso:country":"AU",
    "sg:address":"15 E Ridge St",
    "sg:city":"Nambucca Heads",
    "sg:classifiers":[
        {
            "category":"Shopping",
            "subcategory":"Computers & Home Electronics",
            "type":"Retail Goods"
        }
    ],
    "sg:phone":"+61 2 6568 8833",
    "sg:postcode":"2448",
    "sg:province":"NSW",
    "sg:tags":[
        "hardware",
        "equipment"
    ],
    "wof:name":"Nambucca Valley Computers",
    "wof:placetype":"venue"
},
  "geometry": {"coordinates":[153.003052,-30.642149],"type":"Point"}
}