{
  "type": "Feature",
  "properties": {
    "addr:full":"Queen Elizabeth Drv Ambergate WA 6280",
    "addr:postcode":"6280",
    "addr:street":"Elizabeth Drv",
    "iso:country":"AU",
    "sg:address":"Queen Elizabeth Drv",
    "sg:city":"Ambergate",
    "sg:classifiers":[
        {
            "category":"Farming",
            "subcategory":"Farm",
            "type":"Manufacturing & Wholesale Goods"
        }
    ],
    "sg:phone":"+61 8 9753 1125",
    "sg:postcode":"6280",
    "sg:province":"WA",
    "sg:tags":[
        "farmer"
    ],
    "wof:name":"Sue K A & J M",
    "wof:placetype":"venue"
},
  "geometry": {"coordinates":[115.326210022,-33.7117843628],"type":"Point"}
}