{
  "type": "Feature",
  "properties": {
    "addr:full":"PO Box 48 Jamison Centre ACT 2614",
    "addr:postcode":"2614",
    "iso:country":"AU",
    "sg:address":"PO Box 48",
    "sg:city":"Jamison Centre",
    "sg:classifiers":[
        {
            "category":"Shopping",
            "subcategory":"Crafts & Fabrics",
            "type":"Retail Goods"
        }
    ],
    "sg:phone":"+61 2 6226 8028",
    "sg:postcode":"2614",
    "sg:province":"ACT",
    "sg:tags":[
        "supply"
    ],
    "wof:name":"Kountry Keepsakes",
    "wof:placetype":"venue"
},
  "geometry": {"coordinates":[149.05946350100001,-35.2556686401],"type":"Point"}
}