{
  "type": "Feature",
  "properties": {
    "addr:full":"Shop 26 Runaway Bay Shopping Village Runaway Bay QLD 4216",
    "addr:housenumber":"shop 26",
    "addr:postcode":"4216",
    "iso:country":"AU",
    "sg:address":"Shop 26",
    "sg:city":"Runaway Bay Shopping Village Runaway Bay",
    "sg:classifiers":[
        {
            "category":"Shopping",
            "subcategory":"Jewelry",
            "type":"Retail Goods"
        }
    ],
    "sg:phone":"+61 7 5529 0977",
    "sg:postcode":"4216",
    "sg:province":"QLD",
    "sg:tags":[
        "jeweller"
    ],
    "wof:name":"Wallace Bishop Pty Ltd",
    "wof:placetype":"venue"
},
  "geometry": {"coordinates":[153.37701415999999,-27.8801403046],"type":"Point"}
}