{
  "type": "Feature",
  "properties": {
    "addr:full":"6 Hanover Crt Kilmore VIC 3764",
    "addr:housenumber":"6",
    "addr:postcode":"3764",
    "addr:street":"Hanover Crt",
    "iso:country":"AU",
    "sg:address":"6 Hanover Crt",
    "sg:city":"Kilmore",
    "sg:classifiers":[
        {
            "category":"Retail",
            "subcategory":"Repair Shop",
            "type":"Services"
        }
    ],
    "sg:phone":"+61 3 5782 2015",
    "sg:postcode":"3764",
    "sg:province":"VIC",
    "sg:tags":[
        "cleaner",
        "part",
        "vacuum"
    ],
    "wof:name":"Kilmore Ducted Vacuum Systems",
    "wof:placetype":"venue"
},
  "geometry": {"coordinates":[144.96400451700001,-37.2853355408],"type":"Point"}
}