{
  "type": "Feature",
  "properties": {
    "addr:full":"8 Tova Drv Carrum Downs VIC 3201",
    "addr:housenumber":"8",
    "addr:postcode":"3201",
    "addr:street":"Tova Drv",
    "iso:country":"AU",
    "sg:address":"8 Tova Drv",
    "sg:city":"Carrum Downs",
    "sg:classifiers":[
        {
            "category":"Autos & Motor Vehicles",
            "subcategory":"Automobile Sales",
            "type":"Retail Goods"
        }
    ],
    "sg:phone":"+61 3 9775 0456",
    "sg:postcode":"3201",
    "sg:province":"VIC",
    "sg:tags":[
        "equipment",
        "trailer"
    ],
    "wof:name":"Rowville Horse Trailers",
    "wof:placetype":"venue"
},
  "geometry": {"coordinates":[145.16334499999999,-38.099838],"type":"Point"}
}