{
  "type": "Feature",
  "properties": {
    "iso:country":"AU",
    "sg:address":"34 Brougham St",
    "sg:city":"Geelong",
    "sg:classifiers":[
        {
            "category":"Fast Food",
            "type":"Food & Drink"
        }
    ],
    "sg:phone":"+61 3 5222 6996",
    "sg:postcode":"3220",
    "sg:province":"VIC",
    "sg:tags":[
        "away",
        "take"
    ],
    "wof:name":"Foodworks At The Busport",
    "wof:placetype":"venue"
},
  "geometry": {"coordinates":[144.359543,-38.144722],"type":"Point"}
}