{
  "type": "Feature",
  "properties": {
    "addr:full":"Shop M15, 1 Wilcox Ave Narooma NSW 2546",
    "addr:housenumber":"1",
    "addr:postcode":"2546",
    "addr:street":"M15;Wilcox Ave",
    "iso:country":"AU",
    "sg:address":"Shop M15, 1 Wilcox Ave",
    "sg:city":"Narooma",
    "sg:classifiers":[
        {
            "category":"Building & Trades",
            "subcategory":"Locksmith",
            "type":"Services"
        }
    ],
    "sg:phone":"+61 2 4476 2004",
    "sg:postcode":"2546",
    "sg:province":"NSW",
    "sg:tags":[
        "lock"
    ],
    "wof:name":"Town & Country Locksmiths",
    "wof:placetype":"venue"
},
  "geometry": {"coordinates":[150.132324219,-36.2188415527],"type":"Point"}
}