{
  "type": "Feature",
  "properties": {
    "addr:full":"2 Adeliza Crt Arundel QLD 4214",
    "addr:housenumber":"2",
    "addr:postcode":"4214",
    "addr:street":"Adeliza Crt",
    "iso:country":"AU",
    "sg:address":"2 Adeliza Crt",
    "sg:city":"Arundel",
    "sg:classifiers":[
        {
            "category":"Professional",
            "subcategory":"Printing & Photocopies",
            "type":"Services"
        }
    ],
    "sg:phone":"+61 7 5594 7977",
    "sg:postcode":"4214",
    "sg:province":"QLD",
    "sg:tags":[
        "embroidery"
    ],
    "wof:name":"Axle Productions",
    "wof:placetype":"venue"
},
  "geometry": {"coordinates":[153.38079834000001,-27.9337005615],"type":"Point"}
}