{
  "type": "Feature",
  "properties": {
    "addr:full":"33 Colson Drv Wangaratta South VIC 3678",
    "addr:housenumber":"33",
    "addr:postcode":"3678",
    "addr:street":"Colson Drv",
    "iso:country":"AU",
    "sg:address":"33 Colson Drv",
    "sg:city":"Wangaratta South",
    "sg:classifiers":[
        {
            "category":"Building & Trades",
            "subcategory":"Construction",
            "type":"Services"
        }
    ],
    "sg:phone":"+61 3 5721 3581",
    "sg:postcode":"3678",
    "sg:province":"VIC",
    "sg:tags":[
        "contractor"
    ],
    "wof:name":"Ken Bevan Building Contractor",
    "wof:placetype":"venue"
},
  "geometry": {"coordinates":[146.269729614,-36.3608932495],"type":"Point"}
}