{
  "type": "Feature",
  "properties": {
    "addr:full":"Unit 3-4 17 Robson St Clontarf QLD 4019",
    "addr:housenumber":"17",
    "addr:postcode":"4019",
    "addr:street":"Robson St",
    "iso:country":"AU",
    "sg:address":"Unit 3-4 17 Robson St",
    "sg:city":"Clontarf",
    "sg:classifiers":[
        {
            "category":"Wholesale",
            "subcategory":"Home Furnishings",
            "type":"Manufacturing & Wholesale Goods"
        }
    ],
    "sg:phone":"+61 7 3883 4898",
    "sg:postcode":"4019",
    "sg:province":"QLD",
    "wof:name":"R.A.R Imports",
    "wof:placetype":"venue"
},
  "geometry": {"coordinates":[153.076705933,-27.2401390076],"type":"Point"}
}