{
  "type": "Feature",
  "properties": {
    "iso:country":"AU",
    "sg:address":"Shop 104 Wilsonton Shopping Centre",
    "sg:city":"Wilsonton",
    "sg:classifiers":[
        {
            "category":"Real Estate",
            "subcategory":"Real Estate Agent",
            "type":"Services"
        }
    ],
    "sg:phone":"+61 7 4634 9222",
    "sg:postcode":"4350",
    "sg:province":"QLD",
    "wof:name":"Young Real Estate",
    "wof:placetype":"venue"
},
  "geometry": {"coordinates":[151.913376,-27.539141],"type":"Point"}
}