{
  "type": "Feature",
  "properties": {
    "addr:full":"651 Horseshoe Bend Rd Mt Duneed VIC 3216",
    "addr:housenumber":"651",
    "addr:postcode":"3216",
    "addr:street":"Horseshoe Bend Rd;Duneed",
    "iso:country":"AU",
    "sg:address":"651 Horseshoe Bend Rd",
    "sg:city":"Mt Duneed",
    "sg:classifiers":[
        {
            "category":"Building & Trades",
            "subcategory":"Construction",
            "type":"Services"
        }
    ],
    "sg:phone":"+61 413 615 116",
    "sg:postcode":"3216",
    "sg:province":"VIC",
    "sg:tags":[
        "rendering",
        "cement"
    ],
    "wof:name":"Radical Rendering",
    "wof:placetype":"venue"
},
  "geometry": {"coordinates":[144.34925842300001,-38.259311676],"type":"Point"}
}