{
  "type": "Feature",
  "properties": {
    "addr:full":"35 Henry St Nanango QLD 4615",
    "addr:housenumber":"35",
    "addr:postcode":"4615",
    "addr:street":"Henry St",
    "iso:country":"AU",
    "sg:address":"35 Henry St",
    "sg:city":"Nanango",
    "sg:classifiers":[
        {
            "category":"Fast Food",
            "type":"Food & Drink"
        }
    ],
    "sg:phone":"+61 7 4163 1379",
    "sg:postcode":"4615",
    "sg:province":"QLD",
    "sg:tags":[
        "away",
        "take"
    ],
    "wof:name":"Nobbys Corner Fast Foods",
    "wof:placetype":"venue"
},
  "geometry": {"coordinates":[152.001220703,-26.6713199615],"type":"Point"}
}