{
  "type": "Feature",
  "properties": {
    "addr:full":"Guthrie St Quambatook VIC 3540",
    "addr:postcode":"3540",
    "addr:street":"Guthrie St",
    "iso:country":"AU",
    "sg:address":"Guthrie St",
    "sg:city":"Quambatook",
    "sg:classifiers":[
        {
            "category":"Manufacturing",
            "subcategory":"Tools & Machinery",
            "type":"Manufacturing & Wholesale Goods"
        }
    ],
    "sg:phone":"+61 3 5457 1388",
    "sg:postcode":"3540",
    "sg:province":"VIC",
    "sg:tags":[
        "reconditioners"
    ],
    "wof:name":"White & Coote",
    "wof:placetype":"venue"
},
  "geometry": {"coordinates":[143.52052307100001,-35.849445343],"type":"Point"}
}