{
  "type": "Feature",
  "properties": {
    "addr:full":"391 Maroondah Hwy Ringwood VIC 3134",
    "addr:housenumber":"391",
    "addr:postcode":"3134",
    "addr:street":"Maroondah Hwy",
    "iso:country":"AU",
    "sg:address":"391 Maroondah Hwy",
    "sg:city":"Ringwood",
    "sg:classifiers":[
        {
            "category":"Home & Garden",
            "subcategory":"Garden Supply",
            "type":"Retail Goods"
        }
    ],
    "sg:phone":"+61 3 9879 3222",
    "sg:postcode":"3134",
    "sg:province":"VIC",
    "sg:tags":[
        "equipment"
    ],
    "wof:name":"Supersoil Pty Ltd",
    "wof:placetype":"venue"
},
  "geometry": {"coordinates":[145.24623107900001,-37.8036003113],"type":"Point"}
}