{
  "type": "Feature",
  "properties": {
    "addr:full":"2289 Bells Line Of Rd Bilpin NSW 2758",
    "addr:housenumber":"2289",
    "addr:postcode":"2758",
    "addr:street":"Bells Line Of Rd",
    "iso:country":"AU",
    "sg:address":"2289 Bells Line Of Rd",
    "sg:city":"Bilpin",
    "sg:classifiers":[
        {
            "category":"Building & Trades",
            "subcategory":"Construction",
            "type":"Services"
        }
    ],
    "sg:phone":"+61 2 4567 1145",
    "sg:postcode":"2758",
    "sg:province":"NSW",
    "sg:tags":[
        "contractor"
    ],
    "wof:name":"Ian Muir",
    "wof:placetype":"venue"
},
  "geometry": {"coordinates":[150.53712463400001,-33.502658844],"type":"Point"}
}