{
  "type": "Feature",
  "properties": {
    "iso:country":"AU",
    "sg:address":"50 Coromandel Crs",
    "sg:city":"Knoxfield",
    "sg:classifiers":[
        {
            "category":"Professional",
            "subcategory":"Computer Services",
            "type":"Services"
        }
    ],
    "sg:phone":"+61 3 9778 6899",
    "sg:postcode":"3180",
    "sg:province":"VIC",
    "sg:tags":[
        "package",
        "software"
    ],
    "wof:name":"Taurean Computing Solutions",
    "wof:placetype":"venue"
},
  "geometry": {"coordinates":[145.246658325,-37.8867683411],"type":"Point"}
}