{
  "type": "Feature",
  "properties": {
    "addr:full":"3/ 1031 Whitehorse Rd Box Hill VIC 3128",
    "addr:housenumber":"/ 1031",
    "addr:postcode":"3128",
    "addr:street":"Whitehorse Rd",
    "iso:country":"AU",
    "sg:address":"3/ 1031 Whitehorse Rd",
    "sg:city":"Box Hill",
    "sg:classifiers":[
        {
            "category":"Professional",
            "subcategory":"Printing & Photocopies",
            "type":"Services"
        }
    ],
    "sg:phone":"+61 3 9899 0823",
    "sg:postcode":"3128",
    "sg:province":"VIC",
    "sg:tags":[
        "photocopying"
    ],
    "wof:name":"Kwik Kopy",
    "wof:placetype":"venue"
},
  "geometry": {"coordinates":[145.126586914,-37.8181533813],"type":"Point"}
}