{
  "type": "Feature",
  "properties": {
    "addr:full":"IXL Atrium 27 Hunter St Hobart TAS 7000",
    "addr:housenumber":"27",
    "addr:postcode":"7000",
    "addr:street":"Atrium;Hunter St",
    "iso:country":"AU",
    "sg:address":"IXL Atrium 27 Hunter St",
    "sg:city":"Hobart",
    "sg:classifiers":[
        {
            "category":"Shopping",
            "subcategory":"Clothing, Apparel, & Fashions",
            "type":"Retail Goods"
        }
    ],
    "sg:phone":"+61 3 6231 3445",
    "sg:postcode":"7000",
    "sg:province":"TAS",
    "sg:tags":[
        "menswear"
    ],
    "wof:name":"Ci.Simon",
    "wof:placetype":"venue"
},
  "geometry": {"coordinates":[147.335174561,-42.8813285828],"type":"Point"}
}