{
  "type": "Feature",
  "properties": {
    "addr:full":"264 Victoria Rd Marrickville NSW 2204",
    "addr:housenumber":"264",
    "addr:postcode":"2204",
    "addr:street":"Victoria Rd",
    "iso:country":"AU",
    "sg:address":"264 Victoria Rd",
    "sg:city":"Marrickville",
    "sg:classifiers":[
        {
            "category":"Retail",
            "subcategory":"Funeral Services",
            "type":"Services"
        }
    ],
    "sg:phone":"+61 2 9558 8117",
    "sg:postcode":"2204",
    "sg:province":"NSW",
    "sg:tags":[
        "director"
    ],
    "wof:name":"Andrews T J Funeral Services Pty Ltd",
    "wof:placetype":"venue"
},
  "geometry": {"coordinates":[151.16145299999999,-33.910851],"type":"Point"}
}