{
  "type": "Feature",
  "properties": {
    "addr:full":"McIntyre St Calen QLD 4798",
    "addr:postcode":"4798",
    "addr:street":"Mcintyre St",
    "iso:country":"AU",
    "sg:address":"McIntyre St",
    "sg:city":"Calen",
    "sg:classifiers":[
        {
            "category":"Education",
            "subcategory":"School",
            "type":"Public Place"
        }
    ],
    "sg:phone":"+61 7 4949 7333",
    "sg:postcode":"4798",
    "sg:province":"QLD",
    "sg:tags":[
        "state",
        "except",
        "nsw"
    ],
    "wof:name":"Calen District State College Primary To Year 12 School",
    "wof:placetype":"venue"
},
  "geometry": {"coordinates":[148.765060425,-20.8999156952],"type":"Point"}
}