{
  "type": "Feature",
  "properties": {
    "iso:country":"AU",
    "sg:address":"203 Memorial Ave",
    "sg:city":"Ettalong Beach",
    "sg:classifiers":[
        {
            "category":"Shopping",
            "subcategory":"Clothing, Apparel, & Fashions",
            "type":"Retail Goods"
        }
    ],
    "sg:phone":"+61 2 4341 0474",
    "sg:postcode":"2257",
    "sg:province":"NSW",
    "sg:tags":[
        "lady",
        "wear"
    ],
    "wof:name":"Portias Boutique",
    "wof:placetype":"venue"
},
  "geometry": {"coordinates":[151.33514404300001,-33.514957428],"type":"Point"}
}