{
  "type": "Feature",
  "properties": {
    "addr:full":"41 Joslin St Wayville SA 5034",
    "addr:housenumber":"41",
    "addr:postcode":"5034",
    "addr:street":"Joslin St",
    "iso:country":"AU",
    "sg:address":"41 Joslin St",
    "sg:city":"Wayville",
    "sg:classifiers":[
        {
            "category":"Building & Trades",
            "subcategory":"Landscaping Services",
            "type":"Services"
        }
    ],
    "sg:phone":"+61 438 881 566",
    "sg:postcode":"5034",
    "sg:province":"SA",
    "sg:tags":[
        "designer",
        "landscape",
        "contractor"
    ],
    "wof:name":"Philip Knapp Landscaping",
    "wof:placetype":"venue"
},
  "geometry": {"coordinates":[138.59307861299999,-34.9471092224],"type":"Point"}
}