{
  "type": "Feature",
  "properties": {
    "iso:country":"AU",
    "sg:address":"59 Denison St",
    "sg:city":"Camperdown",
    "sg:classifiers":[
        {
            "category":"Professional",
            "subcategory":"Printing & Photocopies",
            "type":"Services"
        }
    ],
    "sg:phone":"+61 2 9550 3499",
    "sg:postcode":"2050",
    "sg:province":"NSW",
    "sg:tags":[
        "textile",
        "clothing"
    ],
    "wof:name":"Ozart Creative Services Pty Ltd",
    "wof:placetype":"venue"
},
  "geometry": {"coordinates":[151.174362,-33.88953],"type":"Point"}
}