{
  "type": "Feature",
  "properties": {
    "addr:full":"Folland Ave Northgate SA 5085",
    "addr:postcode":"5085",
    "addr:street":"Folland Ave",
    "iso:country":"AU",
    "sg:address":"Folland Ave",
    "sg:city":"Northgate",
    "sg:classifiers":[
        {
            "category":"Building & Trades",
            "subcategory":"Construction",
            "type":"Services"
        }
    ],
    "sg:phone":"+61 434 357 935",
    "sg:postcode":"5085",
    "sg:province":"SA",
    "sg:tags":[
        "contractor"
    ],
    "wof:name":"Heartland Homes",
    "wof:placetype":"venue"
},
  "geometry": {"coordinates":[138.63539123499999,-34.8578071594],"type":"Point"}
}