{
  "type": "Feature",
  "properties": {
    "addr:full":"2 Lewis St Horsham VIC 3400",
    "addr:housenumber":"2",
    "addr:postcode":"3400",
    "addr:street":"Lewis St",
    "iso:country":"AU",
    "sg:address":"2 Lewis St",
    "sg:city":"Horsham",
    "sg:classifiers":[
        {
            "category":"Farming",
            "subcategory":"Farm & Veterinary Services",
            "type":"Manufacturing & Wholesale Goods"
        }
    ],
    "sg:phone":"+61 3 5381 0709",
    "sg:postcode":"3400",
    "sg:province":"VIC",
    "sg:tags":[
        "agricultural",
        "advisory"
    ],
    "wof:name":"FSA Consulting",
    "wof:placetype":"venue"
},
  "geometry": {"coordinates":[142.21232605,-36.7078857422],"type":"Point"}
}