{
  "type": "Feature",
  "properties": {
    "addr:full":"279 Canberra Ave Fyshwick ACT 2609",
    "addr:housenumber":"279",
    "addr:postcode":"2609",
    "addr:street":"Canberra Ave",
    "iso:country":"AU",
    "sg:address":"279 Canberra Ave",
    "sg:city":"Fyshwick",
    "sg:phone":"+61 2 6280 7321",
    "sg:postcode":"2609",
    "sg:province":"ACT",
    "wof:name":"Australian Windscreen Specialists",
    "wof:placetype":"venue"
},
  "geometry": {"coordinates":[149.167694092,-35.3330841064],"type":"Point"}
}