{
  "type": "Feature",
  "properties": {
    "addr:full":"15 Dixon St Hamilton NSW 2303",
    "addr:housenumber":"15",
    "addr:postcode":"2303",
    "addr:street":"Dixon St",
    "iso:country":"AU",
    "sg:address":"15 Dixon St",
    "sg:city":"Hamilton",
    "sg:classifiers":[
        {
            "category":"Real Estate",
            "subcategory":"Architect",
            "type":"Services"
        }
    ],
    "sg:phone":"+61 2 4969 1360",
    "sg:postcode":"2303",
    "sg:province":"NSW",
    "sg:tags":[
        "building",
        "designer"
    ],
    "wof:name":"Easton Ian",
    "wof:placetype":"venue"
},
  "geometry": {"coordinates":[151.74096700000001,-32.924397],"type":"Point"}
}