{
  "type": "Feature",
  "properties": {
    "addr:full":"Shop 3/ 52A Pacific Drv Port Macquarie NSW 2444",
    "addr:housenumber":"shop 3 / 52a",
    "addr:postcode":"2444",
    "addr:street":"Pacific Drv",
    "iso:country":"AU",
    "sg:address":"Shop 3/ 52A Pacific Drv",
    "sg:city":"Port Macquarie",
    "sg:classifiers":[
        {
            "category":"Retail",
            "subcategory":"Laundry & Dry Cleaning",
            "type":"Services"
        }
    ],
    "sg:phone":"+61 2 6583 6206",
    "sg:postcode":"2444",
    "sg:province":"NSW",
    "wof:name":"Flynns Beach Service Laundry",
    "wof:placetype":"venue"
},
  "geometry": {"coordinates":[152.92543000000001,-31.443348],"type":"Point"}
}