{
  "type": "Feature",
  "properties": {
    "addr:full":"PO Box 363 Beverley WA 6304",
    "addr:postcode":"6304",
    "iso:country":"AU",
    "sg:address":"PO Box 363",
    "sg:city":"Beverley",
    "sg:classifiers":[
        {
            "category":"Utilities",
            "subcategory":"Fuel Oil & Lpg",
            "type":"Services"
        }
    ],
    "sg:phone":"+61 8 9647 2024",
    "sg:postcode":"6304",
    "sg:province":"WA",
    "sg:tags":[
        "olive"
    ],
    "wof:name":"Beaming Hill Estate",
    "wof:placetype":"venue"
},
  "geometry": {"coordinates":[116.881851196,-32.0846710205],"type":"Point"}
}