{
  "type": "Feature",
  "properties": {
    "iso:country":"AU",
    "sg:address":"461 Dean St",
    "sg:city":"Albury",
    "sg:classifiers":[
        {
            "category":"Professional",
            "subcategory":"Computer Services",
            "type":"Services"
        }
    ],
    "sg:phone":"+61 2 6023 1191",
    "sg:postcode":"2640",
    "sg:province":"NSW",
    "sg:tags":[
        "consultant",
        "system"
    ],
    "wof:name":"Albury Computers",
    "wof:placetype":"venue"
},
  "geometry": {"coordinates":[146.91206359899999,-36.0803604126],"type":"Point"}
}