{
  "type": "Feature",
  "properties": {
    "addr:full":"Shp1/ 15 Maud St Tugun QLD 4224",
    "addr:housenumber":"15",
    "addr:postcode":"4224",
    "addr:street":"Maud St",
    "iso:country":"AU",
    "sg:address":"Shp1/ 15 Maud St",
    "sg:city":"Tugun",
    "sg:classifiers":[
        {
            "category":"Home & Garden",
            "subcategory":"Furniture",
            "type":"Retail Goods"
        }
    ],
    "sg:phone":"+61 7 5525 6132",
    "sg:postcode":"4224",
    "sg:province":"QLD",
    "sg:tags":[
        "outdoor"
    ],
    "wof:name":"Linda's Place",
    "wof:placetype":"venue"
},
  "geometry": {"coordinates":[153.49250793499999,-28.1432304382],"type":"Point"}
}