{
  "type": "Feature",
  "properties": {
    "addr:full":"107 Haigslea-Amberley Rd Walloon QLD 4306",
    "addr:housenumber":"107",
    "addr:postcode":"4306",
    "addr:street":"Haigslea-Amberley Rd",
    "iso:country":"AU",
    "sg:address":"107 Haigslea-Amberley Rd",
    "sg:city":"Walloon",
    "sg:classifiers":[
        {
            "category":"Utilities",
            "subcategory":"Electric",
            "type":"Services"
        }
    ],
    "sg:phone":"+61 7 5464 5599",
    "sg:postcode":"4306",
    "sg:province":"QLD",
    "sg:tags":[
        "electrical",
        "contractor"
    ],
    "wof:name":"Ware S & K Electrical Contractors",
    "wof:placetype":"venue"
},
  "geometry": {"coordinates":[152.663864136,-27.6060237885],"type":"Point"}
}