{
  "type": "Feature",
  "properties": {
    "iso:country":"AU",
    "sg:address":"2/ 22 Parraweena Rd",
    "sg:city":"Caringbah",
    "sg:classifiers":[
        {
            "category":"Building & Trades",
            "subcategory":"Construction",
            "type":"Services"
        }
    ],
    "sg:phone":"+61 1300 482 566",
    "sg:postcode":"2229",
    "sg:province":"NSW",
    "sg:tags":[
        "contractor"
    ],
    "wof:name":"Talon Projects",
    "wof:placetype":"venue"
},
  "geometry": {"coordinates":[151.12835693400001,-34.0263557434],"type":"Point"}
}