{
  "type": "Feature",
  "properties": {
    "iso:country":"AU",
    "sg:address":"530 Collins St",
    "sg:city":"Melbourne",
    "sg:classifiers":[
        {
            "category":"Cafe",
            "type":"Food & Drink"
        }
    ],
    "sg:phone":"+61 3 9629 6011",
    "sg:postcode":"3000",
    "sg:province":"VIC",
    "wof:name":"Cafe Exchange",
    "wof:placetype":"venue"
},
  "geometry": {"coordinates":[144.95668029800001,-37.8182106018],"type":"Point"}
}