{
  "type": "Feature",
  "properties": {
    "iso:country":"AU",
    "sg:address":"31 Segers Ave",
    "sg:city":"Padstow",
    "sg:classifiers":[
        {
            "category":"Shopping",
            "subcategory":"Pets & Pet Supplies",
            "type":"Retail Goods"
        }
    ],
    "sg:phone":"+61 2 9773 9767",
    "sg:postcode":"2211",
    "sg:province":"NSW",
    "sg:tags":[
        "dog"
    ],
    "wof:name":"Lightweight Show Equipment",
    "wof:placetype":"venue"
},
  "geometry": {"coordinates":[151.031509,-33.954239],"type":"Point"}
}