{
  "type": "Feature",
  "properties": {
    "addr:full":"1 Rowley St Burwood NSW 2134",
    "addr:housenumber":"1",
    "addr:postcode":"2134",
    "addr:street":"Rowley St",
    "iso:country":"AU",
    "sg:address":"1 Rowley St",
    "sg:city":"Burwood",
    "sg:classifiers":[
        {
            "category":"Education",
            "subcategory":"Special Training",
            "type":"Public Place"
        }
    ],
    "sg:phone":"+61 2 8746 6400",
    "sg:postcode":"2134",
    "sg:province":"NSW",
    "sg:tags":[
        "development"
    ],
    "wof:name":"Workplace Australia Group",
    "wof:placetype":"venue"
},
  "geometry": {"coordinates":[151.09963989299999,-33.871383667],"type":"Point"}
}