{
  "type": "Feature",
  "properties": {
    "addr:full":"9/ 194 The Entrance Rd Erina NSW 2250",
    "addr:housenumber":"/ 194",
    "addr:postcode":"2250",
    "addr:street":"The Entrance Rd",
    "iso:country":"AU",
    "sg:address":"9/ 194 The Entrance Rd",
    "sg:city":"Erina",
    "sg:classifiers":[
        {
            "category":"Health Services",
            "subcategory":"Doctor",
            "type":"Services"
        }
    ],
    "sg:phone":"+61 2 4365 1807",
    "sg:postcode":"2250",
    "sg:province":"NSW",
    "sg:tags":[
        "medical",
        "practitioner"
    ],
    "wof:name":"Erina Radiology",
    "wof:placetype":"venue"
},
  "geometry": {"coordinates":[151.385864258,-33.4355773926],"type":"Point"}
}