{
  "type": "Feature",
  "properties": {
    "addr:full":"296 Wanneroo Rd Nollamara WA 6061",
    "addr:housenumber":"296",
    "addr:postcode":"6061",
    "addr:street":"Wanneroo Rd",
    "iso:country":"AU",
    "sg:address":"296 Wanneroo Rd",
    "sg:city":"Nollamara",
    "sg:classifiers":[
        {
            "category":"Health Services",
            "subcategory":"Health Practitioner",
            "type":"Services"
        }
    ],
    "sg:phone":"+61 8 9349 1825",
    "sg:postcode":"6061",
    "sg:province":"WA",
    "sg:tags":[
        "physiotherapist"
    ],
    "wof:name":"Kathryn Rooney",
    "wof:placetype":"venue"
},
  "geometry": {"coordinates":[115.835273743,-31.8818569183],"type":"Point"}
}