{
  "type": "Feature",
  "properties": {
    "addr:full":"37 Jamieson St Moana SA 5169",
    "addr:housenumber":"37",
    "addr:postcode":"5169",
    "addr:street":"Jamieson St",
    "iso:country":"AU",
    "sg:address":"37 Jamieson St",
    "sg:city":"Moana",
    "sg:classifiers":[
        {
            "category":"Professional",
            "subcategory":"Detective & Security Services",
            "type":"Services"
        }
    ],
    "sg:phone":"+61 8 8386 2949",
    "sg:postcode":"5169",
    "sg:province":"SA",
    "sg:tags":[
        "consultant",
        "system"
    ],
    "wof:name":"Exclusive Security",
    "wof:placetype":"venue"
},
  "geometry": {"coordinates":[138.47779846200001,-35.2065162659],"type":"Point"}
}