{
  "type": "Feature",
  "properties": {
    "addr:full":"Unit 4, 4 Magna Crt Lonsdale SA 5160",
    "addr:housenumber":"4",
    "addr:postcode":"5160",
    "addr:street":"Magna Crt",
    "iso:country":"AU",
    "sg:address":"Unit 4, 4 Magna Crt",
    "sg:city":"Lonsdale",
    "sg:classifiers":[
        {
            "category":"Home & Garden",
            "subcategory":"Building Materials",
            "type":"Retail Goods"
        }
    ],
    "sg:phone":"+61 8 8326 0177",
    "sg:postcode":"5160",
    "sg:province":"SA",
    "sg:tags":[
        "fencing"
    ],
    "wof:name":"Rothwell Fencing",
    "wof:placetype":"venue"
},
  "geometry": {"coordinates":[138.49079895,-35.0985603333],"type":"Point"}
}