{
  "type": "Feature",
  "properties": {
    "iso:country":"AU",
    "sg:address":"Shop 4, 86-92 Melbourne St",
    "sg:city":"North Adelaide",
    "sg:classifiers":[
        {
            "category":"Personal",
            "subcategory":"Beauty Salon",
            "type":"Services"
        }
    ],
    "sg:phone":"+61 8 8267 1953",
    "sg:postcode":"5006",
    "sg:province":"SA",
    "sg:tags":[
        "hairdresser"
    ],
    "wof:name":"Taboo Haircutters",
    "wof:placetype":"venue"
},
  "geometry": {"coordinates":[138.60801696799999,-34.9065322876],"type":"Point"}
}