{
  "type": "Feature",
  "properties": {
    "addr:full":"17a Factory St Pomona QLD 4568",
    "addr:housenumber":"17a",
    "addr:postcode":"4568",
    "addr:street":"Factory St",
    "iso:country":"AU",
    "sg:address":"17a Factory St",
    "sg:city":"Pomona",
    "sg:classifiers":[
        {
            "category":"Retail",
            "subcategory":"Auto Repair",
            "type":"Services"
        }
    ],
    "sg:phone":"+61 7 5485 2800",
    "sg:postcode":"4568",
    "sg:province":"QLD",
    "sg:tags":[
        "repairer",
        "motor",
        "engineer"
    ],
    "wof:name":"Central Garage Pomona",
    "wof:placetype":"venue"
},
  "geometry": {"coordinates":[152.85606384299999,-26.3643836975],"type":"Point"}
}