{
  "type": "Feature",
  "properties": {
    "iso:country":"AU",
    "sg:address":"193 The Boulevarde",
    "sg:city":"Miranda",
    "sg:classifiers":[
        {
            "category":"Retail",
            "subcategory":"Driving School",
            "type":"Services"
        }
    ],
    "sg:phone":"+61 2 9524 6339",
    "sg:postcode":"2228",
    "sg:province":"NSW",
    "wof:name":"Barnes Driver Training",
    "wof:placetype":"venue"
},
  "geometry": {"coordinates":[151.10531616200001,-34.0398597717],"type":"Point"}
}