{
  "type": "Feature",
  "properties": {
    "addr:full":"Shop 1, 147 Princes Hwy Ulladulla NSW 2539",
    "addr:housenumber":"shop 1 147",
    "addr:postcode":"2539",
    "addr:street":"Princes Hwy",
    "iso:country":"AU",
    "sg:address":"Shop 1, 147 Princes Hwy",
    "sg:city":"Ulladulla",
    "sg:classifiers":[
        {
            "category":"Professional",
            "subcategory":"Printing & Photocopies",
            "type":"Services"
        }
    ],
    "sg:phone":"+61 2 4455 1521",
    "sg:postcode":"2539",
    "sg:province":"NSW",
    "sg:tags":[
        "embroidery"
    ],
    "wof:name":"Leisure Coast Embroidery",
    "wof:placetype":"venue"
},
  "geometry": {"coordinates":[150.473022461,-35.3625679016],"type":"Point"}
}