{
  "type": "Feature",
  "properties": {
    "addr:full":"5 Amadio Crs Campbelltown SA 5074",
    "addr:housenumber":"5",
    "addr:postcode":"5074",
    "addr:street":"Amadio Crs",
    "iso:country":"AU",
    "sg:address":"5 Amadio Crs",
    "sg:city":"Campbelltown",
    "sg:classifiers":[
        {
            "category":"Building & Trades",
            "subcategory":"Construction",
            "type":"Services"
        }
    ],
    "sg:phone":"+61 418 842 657",
    "sg:postcode":"5074",
    "sg:province":"SA",
    "sg:tags":[
        "renovation",
        "alterations",
        "extension",
        "contractor"
    ],
    "wof:name":"Clairville Constructions Pty Ltd",
    "wof:placetype":"venue"
},
  "geometry": {"coordinates":[138.66169738799999,-34.8811988831],"type":"Point"}
}