{
  "type": "Feature",
  "properties": {
    "addr:full":"U4/ 39 Barrie Rd Tullamarine VIC 3043",
    "addr:housenumber":"39",
    "addr:postcode":"3043",
    "addr:street":"U4 /;Barrie Rd",
    "iso:country":"AU",
    "sg:address":"U4/ 39 Barrie Rd",
    "sg:city":"Tullamarine",
    "sg:classifiers":[
        {
            "category":"Building & Trades",
            "subcategory":"Equipment Rental",
            "type":"Services"
        }
    ],
    "sg:phone":"+61 3 9338 0999",
    "sg:postcode":"3043",
    "sg:province":"VIC",
    "sg:tags":[
        "supply",
        "catering"
    ],
    "wof:name":"A C E Repairs",
    "wof:placetype":"venue"
},
  "geometry": {"coordinates":[144.87388610799999,-37.714138031],"type":"Point"}
}