{
  "type": "Feature",
  "properties": {
    "iso:country":"AU",
    "sg:address":"222 Donnelly St",
    "sg:city":"Armidale",
    "sg:classifiers":[
        {
            "category":"Professional",
            "subcategory":"Computer Services",
            "type":"Services"
        }
    ],
    "sg:phone":"+61 2 6771 2727",
    "sg:postcode":"2350",
    "sg:province":"NSW",
    "sg:tags":[
        "repairs",
        "upgrade",
        "equipment"
    ],
    "wof:name":"Estreich Bob Computer Repairs",
    "wof:placetype":"venue"
},
  "geometry": {"coordinates":[151.65362548799999,-30.5040016174],"type":"Point"}
}