{
  "type": "Feature",
  "properties": {
    "addr:full":"271 Thompsons Rd Lower Templestowe VIC 3107",
    "addr:housenumber":"271",
    "addr:postcode":"3107",
    "addr:street":"Thompsons Rd",
    "iso:country":"AU",
    "sg:address":"271 Thompsons Rd",
    "sg:city":"Lower Templestowe",
    "sg:classifiers":[
        {
            "category":"Social Services",
            "subcategory":"Child Care",
            "type":"Services"
        }
    ],
    "sg:phone":"+61 3 9852 4099",
    "sg:postcode":"3107",
    "sg:province":"VIC",
    "wof:name":"Totalcare For Kids",
    "wof:placetype":"venue"
},
  "geometry": {"coordinates":[145.105392456,-37.7669067383],"type":"Point"}
}