{
  "type": "Feature",
  "properties": {
    "iso:country":"AU",
    "sg:address":"Shp2/ 540 Mt Crosby Rd",
    "sg:city":"Anstead",
    "sg:classifiers":[
        {
            "category":"Wholesale",
            "subcategory":"Farm Supplies",
            "type":"Manufacturing & Wholesale Goods"
        }
    ],
    "sg:phone":"+61 7 3202 8818",
    "sg:postcode":"4070",
    "sg:province":"QLD",
    "sg:tags":[
        "feed",
        "supplement",
        "stock"
    ],
    "wof:name":"In The Paddock",
    "wof:placetype":"venue"
},
  "geometry": {"coordinates":[152.86419677699999,-27.542432785],"type":"Point"}
}