{
  "type": "Feature",
  "properties": {
    "addr:full":"7 McDonagh Rd Tacoma NSW 2259",
    "addr:housenumber":"7",
    "addr:postcode":"2259",
    "addr:street":"Mcdonagh Rd",
    "iso:country":"AU",
    "sg:address":"7 McDonagh Rd",
    "sg:city":"Tacoma",
    "sg:classifiers":[
        {
            "category":"Building & Trades",
            "subcategory":"Construction",
            "type":"Services"
        }
    ],
    "sg:phone":"+61 2 4352 1219",
    "sg:postcode":"2259",
    "sg:province":"NSW",
    "sg:tags":[
        "earth",
        "excavating",
        "moving",
        "contractor"
    ],
    "wof:name":"Merrell H Excavation",
    "wof:placetype":"venue"
},
  "geometry": {"coordinates":[151.45123290999999,-33.2853965759],"type":"Point"}
}