{
  "type": "Feature",
  "properties": {
    "addr:full":"40 Sirius Crs Ebenezer NSW 2756",
    "addr:housenumber":"40",
    "addr:postcode":"2756",
    "addr:street":"Sirius Crs",
    "iso:country":"AU",
    "sg:address":"40 Sirius Crs",
    "sg:city":"Ebenezer",
    "sg:classifiers":[
        {
            "category":"Utilities",
            "subcategory":"Electric",
            "type":"Services"
        }
    ],
    "sg:phone":"+61 2 4579 9400",
    "sg:postcode":"2756",
    "sg:province":"NSW",
    "sg:tags":[
        "electrical",
        "contractor"
    ],
    "wof:name":"Martin Stephens",
    "wof:placetype":"venue"
},
  "geometry": {"coordinates":[150.793624878,-33.6334381104],"type":"Point"}
}