{
  "type": "Feature",
  "properties": {
    "addr:full":"38 Lord St Laurieton NSW 2443",
    "addr:housenumber":"38",
    "addr:postcode":"2443",
    "addr:street":"Lord St",
    "iso:country":"AU",
    "sg:address":"38 Lord St",
    "sg:city":"Laurieton",
    "sg:classifiers":[
        {
            "category":"Farming",
            "subcategory":"Fish & Marine Products",
            "type":"Manufacturing & Wholesale Goods"
        }
    ],
    "sg:phone":"+61 2 6559 6678",
    "sg:postcode":"2443",
    "sg:province":"NSW",
    "sg:tags":[
        "supplier",
        "oyster",
        "farmer"
    ],
    "wof:name":"Camden Haven Oysters Supply",
    "wof:placetype":"venue"
},
  "geometry": {"coordinates":[152.79551699999999,-31.652031],"type":"Point"}
}