{
  "type": "Feature",
  "properties": {
    "iso:country":"AU",
    "sg:address":"Shop 2A/ 360 Mons Rd",
    "sg:city":"Forest Glen",
    "sg:classifiers":[
        {
            "category":"Professional",
            "subcategory":"Computer Services",
            "type":"Services"
        }
    ],
    "sg:phone":"+61 7 5456 1655",
    "sg:postcode":"4556",
    "sg:province":"QLD",
    "sg:tags":[
        "repairs",
        "upgrade",
        "equipment"
    ],
    "wof:name":"Kimnat Computers",
    "wof:placetype":"venue"
},
  "geometry": {"coordinates":[153.00636291500001,-26.6890506744],"type":"Point"}
}