{
  "type": "Feature",
  "properties": {
    "iso:country":"AU",
    "sg:address":"Robinson St",
    "sg:city":"Broome",
    "sg:classifiers":[
        {
            "category":"Travel",
            "subcategory":"Hotels & Motels",
            "type":"Entertainment"
        }
    ],
    "sg:phone":"+61 8 9192 1204",
    "sg:postcode":"6725",
    "sg:province":"WA",
    "wof:name":"Broome-Tropicana Inn",
    "wof:placetype":"venue"
},
  "geometry": {"coordinates":[122.23564910899999,-17.9696750641],"type":"Point"}
}