{
  "type": "Feature",
  "properties": {
    "addr:full":"11 Gimba St Mitchelton QLD 4053",
    "addr:housenumber":"11",
    "addr:postcode":"4053",
    "addr:street":"Gimba St",
    "iso:country":"AU",
    "sg:address":"11 Gimba St",
    "sg:city":"Mitchelton",
    "sg:classifiers":[
        {
            "category":"Home & Garden",
            "subcategory":"Building Materials",
            "type":"Retail Goods"
        }
    ],
    "sg:phone":"+61 416 197 410",
    "sg:postcode":"4053",
    "sg:province":"QLD",
    "sg:tags":[
        "retaining",
        "wall"
    ],
    "wof:name":"A. Complete Bob-Cat Service",
    "wof:placetype":"venue"
},
  "geometry": {"coordinates":[152.97108459500001,-27.4212188721],"type":"Point"}
}