{
  "type": "Feature",
  "properties": {
    "iso:country":"AU",
    "sg:address":"364 Warrigul Rd",
    "sg:city":"Ashburton",
    "sg:classifiers":[
        {
            "category":"Retail",
            "subcategory":"Funeral Services",
            "type":"Services"
        }
    ],
    "sg:phone":"+61 3 9885 5288",
    "sg:postcode":"3147",
    "sg:province":"VIC",
    "sg:tags":[
        "director"
    ],
    "wof:name":"Herbert King & Sons.",
    "wof:placetype":"venue"
},
  "geometry": {"coordinates":[145.09312439000001,-37.8632202148],"type":"Point"}
}