{
  "type": "Feature",
  "properties": {
    "addr:full":"444 Upper Rollands Plains Rd Rollands Plains NSW 2441",
    "addr:housenumber":"444",
    "addr:postcode":"2441",
    "addr:street":"Upper Rollands Plains Rd",
    "iso:country":"AU",
    "sg:address":"444 Upper Rollands Plains Rd",
    "sg:city":"Rollands Plains",
    "sg:classifiers":[
        {
            "category":"Farming",
            "subcategory":"Nursery",
            "type":"Manufacturing & Wholesale Goods"
        }
    ],
    "sg:phone":"+61 2 6585 8155",
    "sg:postcode":"2441",
    "sg:province":"NSW",
    "wof:name":"Branch's Seedlings",
    "wof:placetype":"venue"
},
  "geometry": {"coordinates":[152.65426600000001,-31.251324],"type":"Point"}
}