{
  "type": "Feature",
  "properties": {
    "iso:country":"AU",
    "sg:address":"Cnr Pinelands Rd & Noelana St",
    "sg:city":"Sunnybank Hills",
    "sg:classifiers":[
        {
            "category":"Health Services",
            "subcategory":"Doctor",
            "type":"Services"
        }
    ],
    "sg:phone":"+61 7 3276 0454",
    "sg:postcode":"4109",
    "sg:province":"QLD",
    "sg:tags":[
        "podiatrist"
    ],
    "wof:name":"Jackson Kylie",
    "wof:placetype":"venue"
},
  "geometry": {"coordinates":[153.05856323200001,-27.5986919403],"type":"Point"}
}