{
  "type": "Feature",
  "properties": {
    "iso:country":"AU",
    "sg:address":"17 Towers Drv",
    "sg:city":"Mullumbimby",
    "sg:classifiers":[
        {
            "category":"Manufacturing",
            "subcategory":"Metals",
            "type":"Manufacturing & Wholesale Goods"
        }
    ],
    "sg:phone":"+61 2 6684 2325",
    "sg:postcode":"2482",
    "sg:province":"NSW",
    "sg:tags":[
        "steel",
        "fabricator",
        "mfrs"
    ],
    "wof:name":"Mullumbimby Engineering",
    "wof:placetype":"venue"
},
  "geometry": {"coordinates":[153.49993896500001,-28.5531997681],"type":"Point"}
}