{
  "type": "Feature",
  "properties": {
    "addr:full":"8 Wardley St Capalaba QLD 4157",
    "addr:housenumber":"8",
    "addr:postcode":"4157",
    "addr:street":"Wardley St",
    "iso:country":"AU",
    "sg:address":"8 Wardley St",
    "sg:city":"Capalaba",
    "sg:classifiers":[
        {
            "category":"Building & Trades",
            "subcategory":"Construction",
            "type":"Services"
        }
    ],
    "sg:phone":"+61 7 3823 4537",
    "sg:postcode":"4157",
    "sg:province":"QLD",
    "sg:tags":[
        "contractor"
    ],
    "wof:name":"Liona Constructions Pty Ltd",
    "wof:placetype":"venue"
},
  "geometry": {"coordinates":[153.199508667,-27.5386390686],"type":"Point"}
}