{
  "type": "Feature",
  "properties": {
    "addr:full":"20 Napoleon St Collingwood VIC 3066",
    "addr:housenumber":"20",
    "addr:postcode":"3066",
    "addr:street":"Napoleon St",
    "iso:country":"AU",
    "sg:address":"20 Napoleon St",
    "sg:city":"Collingwood",
    "sg:classifiers":[
        {
            "category":"Retail",
            "subcategory":"Laundry & Dry Cleaning",
            "type":"Services"
        }
    ],
    "sg:phone":"+61 3 9417 6488",
    "sg:postcode":"3066",
    "sg:province":"VIC",
    "sg:tags":[
        "ironing"
    ],
    "wof:name":"Laus Pressing & Fashion Pty Ltd",
    "wof:placetype":"venue"
},
  "geometry": {"coordinates":[144.986526489,-37.8014221191],"type":"Point"}
}