{
  "type": "Feature",
  "properties": {
    "addr:full":"46 Victoria St Robe SA 5276",
    "addr:housenumber":"46",
    "addr:postcode":"5276",
    "addr:street":"Victoria St",
    "iso:country":"AU",
    "sg:address":"46 Victoria St",
    "sg:city":"Robe",
    "sg:classifiers":[
        {
            "category":"Cafe",
            "type":"Food & Drink"
        }
    ],
    "sg:phone":"+61 8 8768 2488",
    "sg:postcode":"5276",
    "sg:province":"SA",
    "wof:name":"Wild Mulberry Licensed Cafe",
    "wof:placetype":"venue"
},
  "geometry": {"coordinates":[139.75941499999999,-37.163956],"type":"Point"}
}