{
  "type": "Feature",
  "properties": {
    "iso:country":"AU",
    "sg:address":"18 Tunks St",
    "sg:city":"Northbridge",
    "sg:classifiers":[
        {
            "category":"Professional",
            "subcategory":"Art Services",
            "type":"Services"
        }
    ],
    "sg:phone":"+61 2 9958 7071",
    "sg:postcode":"2063",
    "sg:province":"NSW",
    "sg:tags":[
        "interior",
        "decorator"
    ],
    "wof:name":"Fiona Gardner",
    "wof:placetype":"venue"
},
  "geometry": {"coordinates":[151.216140747,-33.810043335],"type":"Point"}
}