{
  "type": "Feature",
  "properties": {
    "iso:country":"AU",
    "sg:address":"437 Toorak Rd",
    "sg:city":"Toorak",
    "sg:classifiers":[
        {
            "category":"Health Services",
            "subcategory":"Optometrist",
            "type":"Services"
        }
    ],
    "sg:phone":"+61 3 9826 8809",
    "sg:postcode":"3142",
    "sg:province":"VIC",
    "wof:name":"Maximeyes Optical Victoria Pty Ltd",
    "wof:placetype":"venue"
},
  "geometry": {"coordinates":[145.007568359,-37.8407936096],"type":"Point"}
}