{
  "type": "Feature",
  "properties": {
    "addr:full":"134 Jubilee St Maclean NSW 2463",
    "addr:housenumber":"134",
    "addr:postcode":"2463",
    "addr:street":"Jubilee St",
    "iso:country":"AU",
    "sg:address":"134 Jubilee St",
    "sg:city":"Maclean",
    "sg:classifiers":[
        {
            "category":"Retail",
            "subcategory":"Auto Repair",
            "type":"Services"
        }
    ],
    "sg:phone":"+61 2 6645 1681",
    "sg:postcode":"2463",
    "sg:province":"NSW",
    "sg:tags":[
        "repairer",
        "motor",
        "engineer"
    ],
    "wof:name":"Yamba-Maclean Auto Centre",
    "wof:placetype":"venue"
},
  "geometry": {"coordinates":[153.207321167,-29.4669246674],"type":"Point"}
}