{
  "type": "Feature",
  "properties": {
    "addr:full":"16 Archer St Carlisle WA 6101",
    "addr:housenumber":"16",
    "addr:postcode":"6101",
    "addr:street":"Archer St",
    "iso:country":"AU",
    "sg:address":"16 Archer St",
    "sg:city":"Carlisle",
    "sg:classifiers":[
        {
            "category":"Real Estate",
            "subcategory":"Real Estate Agent",
            "type":"Services"
        }
    ],
    "sg:phone":"+61 8 9362 4489",
    "sg:postcode":"6101",
    "sg:province":"WA",
    "wof:name":"Burswood Property Transactions",
    "wof:placetype":"venue"
},
  "geometry": {"coordinates":[115.91110229500001,-31.9781246185],"type":"Point"}
}