{
  "type": "Feature",
  "properties": {
    "addr:full":"Market Arcade 674-680 Glenferrie Rd Hawthorn VIC 3122",
    "addr:housenumber":"674-680",
    "addr:postcode":"3122",
    "addr:street":"Glenferrie Rd",
    "iso:country":"AU",
    "sg:address":"Market Arcade 674-680 Glenferrie Rd",
    "sg:city":"Hawthorn",
    "sg:classifiers":[
        {
            "category":"Personal",
            "subcategory":"Beauty Salon",
            "type":"Services"
        }
    ],
    "sg:phone":"+61 3 9819 3111",
    "sg:postcode":"3122",
    "sg:province":"VIC",
    "sg:tags":[
        "hairdresser"
    ],
    "wof:name":"Kaya Hair Salon",
    "wof:placetype":"venue"
},
  "geometry": {"coordinates":[145.035842895,-37.8208656311],"type":"Point"}
}