{
  "type": "Feature",
  "properties": {
    "addr:full":"2 Urana St Kilsyth VIC 3137",
    "addr:housenumber":"2",
    "addr:postcode":"3137",
    "addr:street":"Urana St",
    "iso:country":"AU",
    "sg:address":"2 Urana St",
    "sg:city":"Kilsyth",
    "sg:classifiers":[
        {
            "category":"Government",
            "subcategory":"Post Office",
            "type":"Public Place"
        }
    ],
    "sg:phone":"+61 3 9728 3793",
    "sg:postcode":"3137",
    "sg:province":"VIC",
    "sg:tags":[
        "house",
        "doll"
    ],
    "wof:name":"K.V.K. Dolls",
    "wof:placetype":"venue"
},
  "geometry": {"coordinates":[145.316162109,-37.8111228943],"type":"Point"}
}