{
  "type": "Feature",
  "properties": {
    "addr:full":"PO Box 389 Newstead TAS 7250",
    "addr:postcode":"7250",
    "iso:country":"AU",
    "sg:address":"PO Box 389",
    "sg:city":"Newstead",
    "sg:classifiers":[
        {
            "category":"Building & Trades",
            "subcategory":"Construction",
            "type":"Services"
        }
    ],
    "sg:phone":"+61 408 137 424",
    "sg:postcode":"7250",
    "sg:province":"TAS",
    "sg:tags":[
        "contractor"
    ],
    "wof:name":"Yeaman Constructions",
    "wof:placetype":"venue"
},
  "geometry": {"coordinates":[147.092849731,-41.4066505432],"type":"Point"}
}