{
  "type": "Feature",
  "properties": {
    "iso:country":"AU",
    "sg:address":"15 Teton Crt",
    "sg:city":"Highett",
    "sg:classifiers":[
        {
            "category":"Shopping",
            "subcategory":"Computers & Home Electronics",
            "type":"Retail Goods"
        }
    ],
    "sg:phone":"+61 3 9553 7236",
    "sg:postcode":"3190",
    "sg:province":"VIC",
    "sg:tags":[
        "detector",
        "electronic"
    ],
    "wof:name":"Australian Underground Services P/L",
    "wof:placetype":"venue"
},
  "geometry": {"coordinates":[145.05329895,-37.9479141235],"type":"Point"}
}