{
  "type": "Feature",
  "properties": {
    "addr:full":"4 Strathdale St Aspley QLD 4034",
    "addr:housenumber":"4",
    "addr:postcode":"4034",
    "addr:street":"Strathdale St",
    "iso:country":"AU",
    "sg:address":"4 Strathdale St",
    "sg:city":"Aspley",
    "sg:classifiers":[
        {
            "category":"Retail",
            "subcategory":"Storage",
            "type":"Services"
        }
    ],
    "sg:phone":"+61 7 3863 3224",
    "sg:postcode":"4034",
    "sg:province":"QLD",
    "sg:tags":[
        "removal",
        "furniture"
    ],
    "wof:name":"Kobble Vale Carrying Co",
    "wof:placetype":"venue"
},
  "geometry": {"coordinates":[153.023819,-27.358606],"type":"Point"}
}