{
  "type": "Feature",
  "properties": {
    "iso:country":"AU",
    "sg:address":"Shp 102a/ 28 Southside Drv",
    "sg:city":"Hillarys",
    "sg:classifiers":[
        {
            "category":"Professional",
            "subcategory":"Printing & Photocopies",
            "type":"Services"
        }
    ],
    "sg:phone":"+61 8 9203 5633",
    "sg:postcode":"6025",
    "sg:province":"WA",
    "sg:tags":[
        "trophy"
    ],
    "wof:name":"Inner Crystal",
    "wof:placetype":"venue"
},
  "geometry": {"coordinates":[115.741966248,-31.8239994049],"type":"Point"}
}