{
  "type": "Feature",
  "properties": {
    "addr:full":"1 Denmark St Wombarra NSW 2515",
    "addr:housenumber":"1",
    "addr:postcode":"2515",
    "addr:street":"Denmark St",
    "iso:country":"AU",
    "sg:address":"1 Denmark St",
    "sg:city":"Wombarra",
    "sg:classifiers":[
        {
            "category":"Professional",
            "subcategory":"Engineering",
            "type":"Services"
        }
    ],
    "sg:phone":"+61 408 212 055",
    "sg:postcode":"2515",
    "sg:province":"NSW",
    "sg:tags":[
        "electrical",
        "engineer"
    ],
    "wof:name":"Ajcab Control & Electrical Pty Ltd",
    "wof:placetype":"venue"
},
  "geometry": {"coordinates":[150.953003,-34.280888],"type":"Point"}
}