{
  "type": "Feature",
  "properties": {
    "addr:full":"11 Hay St Perth WA 6000",
    "addr:housenumber":"11",
    "addr:postcode":"6000",
    "addr:street":"Hay St",
    "iso:country":"AU",
    "sg:address":"11 Hay St",
    "sg:city":"Perth",
    "sg:classifiers":[
        {
            "category":"Professional",
            "subcategory":"Art Services",
            "type":"Services"
        }
    ],
    "sg:phone":"+61 400 800 504",
    "sg:postcode":"6000",
    "sg:province":"WA",
    "sg:tags":[
        "decorator",
        "painter"
    ],
    "wof:name":"Doran Constructions",
    "wof:placetype":"venue"
},
  "geometry": {"coordinates":[115.8568573,-31.9536037445],"type":"Point"}
}