{
  "type": "Feature",
  "properties": {
    "addr:full":"92 Scamander Ave Scamander TAS 7215",
    "addr:housenumber":"92",
    "addr:postcode":"7215",
    "addr:street":"Scamander Ave",
    "iso:country":"AU",
    "sg:address":"92 Scamander Ave",
    "sg:city":"Scamander",
    "sg:classifiers":[
        {
            "category":"Food & Beverages",
            "subcategory":"Supermarket",
            "type":"Retail Goods"
        }
    ],
    "sg:phone":"+61 3 6372 5125",
    "sg:postcode":"7215",
    "sg:province":"TAS",
    "sg:tags":[
        "grocery",
        "store"
    ],
    "wof:name":"Scamander Supermarket",
    "wof:placetype":"venue"
},
  "geometry": {"coordinates":[148.26307700000001,-41.463867],"type":"Point"}
}