{
  "type": "Feature",
  "properties": {
    "iso:country":"AU",
    "sg:address":"1 Davids Cl",
    "sg:city":"Somersby",
    "sg:classifiers":[
        {
            "category":"Utilities",
            "subcategory":"Refuse",
            "type":"Services"
        }
    ],
    "sg:phone":"+61 402 430 862",
    "sg:postcode":"2250",
    "sg:province":"NSW",
    "sg:tags":[
        "boiler"
    ],
    "sg:website":"http://www.steampro.com.au",
    "wof:name":"Steampro Boiler Services Pty Ltd",
    "wof:placetype":"venue"
},
  "geometry": {"coordinates":[151.27992248499999,-33.3779792786],"type":"Point"}
}