{
  "type": "Feature",
  "properties": {
    "addr:full":"Suite 5 / 30-38 Victoria St Paddington NSW 2021",
    "addr:housenumber":"/ 30-38",
    "addr:postcode":"2021",
    "addr:street":"Victoria St",
    "iso:country":"AU",
    "sg:address":"Suite 5 / 30-38 Victoria St",
    "sg:city":"Paddington",
    "sg:classifiers":[
        {
            "category":"Professional",
            "subcategory":"Management & Consulting",
            "type":"Services"
        }
    ],
    "sg:phone":"+61 2 9331 1170",
    "sg:postcode":"2021",
    "sg:province":"NSW",
    "sg:tags":[
        "consultant"
    ],
    "wof:name":"Hush Communications",
    "wof:placetype":"venue"
},
  "geometry": {"coordinates":[151.230194092,-33.8862876892],"type":"Point"}
}