{
  "type": "Feature",
  "properties": {
    "addr:full":"159 Galloway St Armidale NSW 2350",
    "addr:housenumber":"159",
    "addr:postcode":"2350",
    "addr:street":"Galloway St",
    "iso:country":"AU",
    "sg:address":"159 Galloway St",
    "sg:city":"Armidale",
    "sg:classifiers":[
        {
            "category":"Real Estate",
            "subcategory":"Real Estate Agent",
            "type":"Services"
        }
    ],
    "sg:phone":"+61 2 6771 3141",
    "sg:postcode":"2350",
    "sg:province":"NSW",
    "wof:name":"Schaefer G M",
    "wof:placetype":"venue"
},
  "geometry": {"coordinates":[151.65592956500001,-30.5244178772],"type":"Point"}
}