{
  "type": "Feature",
  "properties": {
    "addr:full":"Shop 2/ 62 Wallarah Rd Gorokan NSW 2263",
    "addr:housenumber":"shop 2 / 62",
    "addr:postcode":"2263",
    "addr:street":"Wallarah Rd",
    "iso:country":"AU",
    "sg:address":"Shop 2/ 62 Wallarah Rd",
    "sg:city":"Gorokan",
    "sg:classifiers":[
        {
            "category":"Fast Food",
            "type":"Food & Drink"
        }
    ],
    "sg:phone":"+61 2 4392 7611",
    "sg:postcode":"2263",
    "sg:province":"NSW",
    "sg:tags":[
        "away",
        "take"
    ],
    "wof:name":"Gorokan Chickens & Salads",
    "wof:placetype":"venue"
},
  "geometry": {"coordinates":[151.511368,-33.258053],"type":"Point"}
}