{
  "type": "Feature",
  "properties": {
    "addr:full":"10a Halifax Dr Bunbury WA 6230",
    "addr:housenumber":"10a",
    "addr:postcode":"6230",
    "addr:street":"Halifax Dr",
    "iso:country":"AU",
    "sg:address":"10a Halifax Dr",
    "sg:city":"Bunbury",
    "sg:classifiers":[
        {
            "category":"Retail",
            "subcategory":"Auto Repair",
            "type":"Services"
        }
    ],
    "sg:phone":"+61 8 9726 0000",
    "sg:postcode":"6230",
    "sg:province":"WA",
    "sg:tags":[
        "engine",
        "reconditioning"
    ],
    "wof:name":"Moyle Engines",
    "wof:placetype":"venue"
},
  "geometry": {"coordinates":[115.66905199999999,-33.359581],"type":"Point"}
}