{
  "type": "Feature",
  "properties": {
    "iso:country":"AU",
    "sg:address":"60 Mocatta St",
    "sg:city":"Goombungee",
    "sg:classifiers":[
        {
            "category":"Travel",
            "subcategory":"Hotels & Motels",
            "type":"Entertainment"
        }
    ],
    "sg:phone":"+61 7 4696 5103",
    "sg:postcode":"4354",
    "sg:province":"QLD",
    "sg:tags":[
        "accommodation"
    ],
    "wof:name":"Pioneer Arms Hotel",
    "wof:placetype":"venue"
},
  "geometry": {"coordinates":[151.851944,-27.302881],"type":"Point"}
}