{
  "type": "Feature",
  "properties": {
    "iso:country":"AU",
    "sg:address":"62 Fleetwood Rd",
    "sg:city":"Eumundi",
    "sg:classifiers":[
        {
            "category":"Arts & Performance",
            "subcategory":"Comedy Club",
            "type":"Entertainment"
        }
    ],
    "sg:phone":"+61 7 5447 0334",
    "sg:postcode":"4562",
    "sg:province":"QLD",
    "sg:tags":[
        "piano",
        "removal"
    ],
    "wof:name":"Brians Furniture Removals",
    "wof:placetype":"venue"
},
  "geometry": {"coordinates":[152.87481689399999,-26.4894752502],"type":"Point"}
}