{
  "type": "Feature",
  "properties": {
    "iso:country":"AU",
    "sg:address":"787 Victoria Rd",
    "sg:city":"Ryde",
    "sg:classifiers":[
        {
            "category":"Health Services",
            "subcategory":"Health Practitioner",
            "type":"Services"
        }
    ],
    "sg:phone":"+61 2 9807 8688",
    "sg:postcode":"2112",
    "sg:province":"NSW",
    "sg:tags":[
        "herbalist"
    ],
    "wof:name":"Chinese Herbal Medicine Centre",
    "wof:placetype":"venue"
},
  "geometry": {"coordinates":[151.10044860799999,-33.8152198792],"type":"Point"}
}