{
  "type": "Feature",
  "properties": {
    "addr:full":"322 Mann St Gosford NSW 2250",
    "addr:housenumber":"322",
    "addr:postcode":"2250",
    "addr:street":"Mann St",
    "iso:country":"AU",
    "sg:address":"322 Mann St",
    "sg:city":"Gosford",
    "sg:classifiers":[
        {
            "category":"Retail",
            "subcategory":"Auto Rental",
            "type":"Services"
        }
    ],
    "sg:phone":"+61 2 4323 2222",
    "sg:postcode":"2250",
    "sg:province":"NSW",
    "sg:tags":[
        "bus",
        "truck"
    ],
    "wof:name":"Avis",
    "wof:placetype":"venue"
},
  "geometry": {"coordinates":[151.343185425,-33.4196548462],"type":"Point"}
}