{
  "type": "Feature",
  "properties": {
    "addr:full":"108 Warrangaree Drv Woronora Heights NSW 2233",
    "addr:housenumber":"108",
    "addr:postcode":"2233",
    "addr:street":"Warrangaree Drv",
    "iso:country":"AU",
    "sg:address":"108 Warrangaree Drv",
    "sg:city":"Woronora Heights",
    "sg:classifiers":[
        {
            "category":"Building & Trades",
            "subcategory":"Plumbing",
            "type":"Services"
        }
    ],
    "sg:phone":"+61 418 674 556",
    "sg:postcode":"2233",
    "sg:province":"NSW",
    "sg:tags":[
        "plumber",
        "gasfitters"
    ],
    "wof:name":"Buckleys Plumbing Service",
    "wof:placetype":"venue"
},
  "geometry": {"coordinates":[151.029495239,-34.0298423767],"type":"Point"}
}