{
  "type": "Feature",
  "properties": {
    "addr:full":"5 Hawthorn Crs Hazelwood Park SA 5066",
    "addr:housenumber":"5",
    "addr:postcode":"5066",
    "addr:street":"Hawthorn Crs",
    "iso:country":"AU",
    "sg:address":"5 Hawthorn Crs",
    "sg:city":"Hazelwood Park",
    "sg:classifiers":[
        {
            "category":"Professional",
            "subcategory":"Engineering",
            "type":"Services"
        }
    ],
    "sg:phone":"+61 8 8331 9499",
    "sg:postcode":"5066",
    "sg:province":"SA",
    "sg:tags":[
        "consulting",
        "engineer"
    ],
    "wof:name":"John Chappell Engineers Pty Ltd",
    "wof:placetype":"venue"
},
  "geometry": {"coordinates":[138.65977477999999,-34.9332199097],"type":"Point"}
}