{
  "type": "Feature",
  "properties": {
    "addr:full":"77 Dover Rd Williamstown VIC 3016",
    "addr:housenumber":"77",
    "addr:postcode":"3016",
    "addr:street":"Dover Rd",
    "iso:country":"AU",
    "sg:address":"77 Dover Rd",
    "sg:city":"Williamstown",
    "sg:classifiers":[
        {
            "category":"Professional",
            "subcategory":"Employment Agencies",
            "type":"Services"
        }
    ],
    "sg:phone":"+61 3 9397 6355",
    "sg:postcode":"3016",
    "sg:province":"VIC",
    "sg:tags":[
        "theatrical",
        "managers",
        "agent",
        "producer"
    ],
    "wof:name":"Two For The Road Promotions",
    "wof:placetype":"venue"
},
  "geometry": {"coordinates":[144.898147583,-37.8536262512],"type":"Point"}
}