{
  "type": "Feature",
  "properties": {
    "addr:full":"57 Rowland St Slacks Creek QLD 4127",
    "addr:housenumber":"57",
    "addr:postcode":"4127",
    "addr:street":"Rowland St",
    "iso:country":"AU",
    "sg:address":"57 Rowland St",
    "sg:city":"Slacks Creek",
    "sg:classifiers":[
        {
            "category":"Train Station",
            "subcategory":"Light Rail",
            "type":"Transportation"
        }
    ],
    "sg:phone":"+61 1800 600 580",
    "sg:postcode":"4127",
    "sg:province":"QLD",
    "sg:tags":[
        "equipment",
        "energy",
        "solar"
    ],
    "sg:website":"http://www.sunbather.com.au",
    "wof:name":"Sunbather Brisbane",
    "wof:placetype":"venue"
},
  "geometry": {"coordinates":[153.12791442899999,-27.6317501068],"type":"Point"}
}