{
  "type": "Feature",
  "properties": {
    "addr:full":"111 Inkerman St St Kilda VIC 3182",
    "addr:housenumber":"111",
    "addr:postcode":"3182",
    "addr:street":"Inkerman St",
    "iso:country":"AU",
    "sg:address":"111 Inkerman St",
    "sg:city":"St Kilda",
    "sg:classifiers":[
        {
            "category":"Home & Garden",
            "subcategory":"Hardware",
            "type":"Retail Goods"
        }
    ],
    "sg:phone":"+61 3 9525 4766",
    "sg:postcode":"3182",
    "sg:province":"VIC",
    "sg:tags":[
        "part",
        "air conditioning"
    ],
    "wof:name":"Barcol Airconditioning Equipment",
    "wof:placetype":"venue"
},
  "geometry": {"coordinates":[144.98677063,-37.8648605347],"type":"Point"}
}