{
  "type": "Feature",
  "properties": {
    "addr:full":"219 Elizabeth St Hobart TAS 7000",
    "addr:housenumber":"219",
    "addr:postcode":"7000",
    "addr:street":"Elizabeth St",
    "iso:country":"AU",
    "sg:address":"219 Elizabeth St",
    "sg:city":"Hobart",
    "sg:classifiers":[
        {
            "category":"Personal",
            "subcategory":"Barber",
            "type":"Services"
        }
    ],
    "sg:phone":"+61 409 970 197",
    "sg:postcode":"7000",
    "sg:province":"TAS",
    "wof:name":"Uptown Barber",
    "wof:placetype":"venue"
},
  "geometry": {"coordinates":[147.321075439,-42.8783683777],"type":"Point"}
}