{
  "type": "Feature",
  "properties": {
    "addr:full":"Shop 2109, Westfield Shopping Centre, Cheltenham Cheltenham VIC 3192",
    "addr:housenumber":"2109",
    "addr:postcode":"3192",
    "addr:street":"Westfield Shopping",
    "iso:country":"AU",
    "sg:address":"Shop 2109, Westfield Shopping Centre, Cheltenham",
    "sg:city":"Cheltenham",
    "sg:classifiers":[
        {
            "category":"Shopping",
            "subcategory":"Clothing, Apparel, & Fashions",
            "type":"Retail Goods"
        }
    ],
    "sg:phone":"+61 3 9583 7100",
    "sg:postcode":"3192",
    "sg:province":"VIC",
    "sg:tags":[
        "boutique"
    ],
    "wof:name":"Glassons Limited",
    "wof:placetype":"venue"
},
  "geometry": {"coordinates":[145.033493042,-37.9687194824],"type":"Point"}
}