{
  "type": "Feature",
  "properties": {
    "addr:full":"1 Anzac Hwy Keswick SA 5035",
    "addr:housenumber":"1",
    "addr:postcode":"5035",
    "addr:street":"Anzac Hwy",
    "iso:country":"AU",
    "sg:address":"1 Anzac Hwy",
    "sg:city":"Keswick",
    "sg:classifiers":[
        {
            "category":"Building & Trades",
            "subcategory":"Electrical",
            "type":"Services"
        }
    ],
    "sg:phone":"+61 8 8404 5667",
    "sg:postcode":"5035",
    "sg:province":"SA",
    "sg:tags":[
        "electricity",
        "distributor"
    ],
    "wof:name":"ETSA Utilities",
    "wof:placetype":"venue"
},
  "geometry": {"coordinates":[138.57882690400001,-34.9466133118],"type":"Point"}
}