{
  "type": "Feature",
  "properties": {
    "iso:country":"AU",
    "sg:address":"15 Bullecourt Ave",
    "sg:city":"Milperra",
    "sg:classifiers":[
        {
            "category":"Social Services",
            "subcategory":"Retirement Home",
            "type":"Services"
        }
    ],
    "sg:phone":"+61 1800 992 442",
    "sg:postcode":"2214",
    "sg:province":"NSW",
    "sg:tags":[
        "environmental",
        "consultant",
        "pollution"
    ],
    "wof:name":"United Air Specialists",
    "wof:placetype":"venue"
},
  "geometry": {"coordinates":[150.98773199999999,-33.93742],"type":"Point"}
}