{
  "type": "Feature",
  "properties": {
    "addr:full":"102 Drayton St Nanango QLD 4615",
    "addr:housenumber":"102",
    "addr:postcode":"4615",
    "addr:street":"Drayton St",
    "iso:country":"AU",
    "sg:address":"102 Drayton St",
    "sg:city":"Nanango",
    "sg:classifiers":[
        {
            "category":"Retail",
            "subcategory":"Auto Repair",
            "type":"Services"
        }
    ],
    "sg:phone":"+61 7 4163 1108",
    "sg:postcode":"4615",
    "sg:province":"QLD",
    "sg:tags":[
        "repairer",
        "motor",
        "engineer"
    ],
    "wof:name":"Nanango Motors Pty Ltd",
    "wof:placetype":"venue"
},
  "geometry": {"coordinates":[151.99919128400001,-26.6706809998],"type":"Point"}
}