{
  "type": "Feature",
  "properties": {
    "addr:full":"The Lodge 14- 20 King William Rd Wayville SA 5034",
    "addr:housenumber":"14 20",
    "addr:postcode":"5034",
    "addr:street":"King William Rd",
    "iso:country":"AU",
    "sg:address":"The Lodge 14- 20 King William Rd",
    "sg:city":"Wayville",
    "sg:classifiers":[
        {
            "category":"Health Services",
            "subcategory":"Nursing And Care Facility",
            "type":"Services"
        }
    ],
    "sg:phone":"+61 8 8357 3833",
    "sg:postcode":"5034",
    "sg:province":"SA",
    "sg:tags":[
        "home"
    ],
    "wof:name":"Eldercare Incorporated",
    "wof:placetype":"venue"
},
  "geometry": {"coordinates":[138.599243164,-34.9457473755],"type":"Point"}
}