{
  "type": "Feature",
  "properties": {
    "addr:full":"137 Moray St South Melbourne VIC 3205",
    "addr:housenumber":"137",
    "addr:postcode":"3205",
    "addr:street":"Moray St",
    "iso:country":"AU",
    "sg:address":"137 Moray St",
    "sg:city":"South Melbourne",
    "sg:classifiers":[
        {
            "category":"Insurance",
            "subcategory":"Insurance Agent",
            "type":"Services"
        }
    ],
    "sg:phone":"+61 3 8699 8888",
    "sg:postcode":"3205",
    "sg:province":"VIC",
    "sg:tags":[
        "broker"
    ],
    "wof:name":"AIS Insurance Brokers",
    "wof:placetype":"venue"
},
  "geometry": {"coordinates":[144.96237199999999,-37.830399],"type":"Point"}
}