{
  "type": "Feature",
  "properties": {
    "addr:full":"50 Enterprise St Kunda Park QLD 4556",
    "addr:housenumber":"50",
    "addr:postcode":"4556",
    "addr:street":"Enterprise St",
    "iso:country":"AU",
    "sg:address":"50 Enterprise St",
    "sg:city":"Kunda Park",
    "sg:classifiers":[
        {
            "category":"Professional",
            "subcategory":"Engineering",
            "type":"Services"
        }
    ],
    "sg:phone":"+61 7 5476 7902",
    "sg:postcode":"4556",
    "sg:province":"QLD",
    "sg:tags":[
        "engineer"
    ],
    "wof:name":"Horsey L R & Co",
    "wof:placetype":"venue"
},
  "geometry": {"coordinates":[153.02992248499999,-26.6664085388],"type":"Point"}
}