{
  "type": "Feature",
  "properties": {
    "iso:country":"AU",
    "sg:address":"244 Coast Rd",
    "sg:city":"Baffle Creek",
    "sg:classifiers":[
        {
            "category":"Food & Beverages",
            "subcategory":"Liquor & Beverages",
            "type":"Retail Goods"
        }
    ],
    "sg:phone":"+61 7 4156 6331",
    "sg:postcode":"4674",
    "sg:province":"QLD",
    "sg:tags":[
        "store"
    ],
    "wof:name":"Ikstrums",
    "wof:placetype":"venue"
},
  "geometry": {"coordinates":[151.926361,-24.49839],"type":"Point"}
}