{
  "type": "Feature",
  "properties": {
    "addr:full":"95 Ardross St Applecross WA 6153",
    "addr:housenumber":"95",
    "addr:postcode":"6153",
    "addr:street":"Ardross St",
    "iso:country":"AU",
    "sg:address":"95 Ardross St",
    "sg:city":"Applecross",
    "sg:classifiers":[
        {
            "category":"Real Estate",
            "subcategory":"Architect",
            "type":"Services"
        }
    ],
    "sg:phone":"+61 418 887 070",
    "sg:postcode":"6153",
    "sg:province":"WA",
    "wof:name":"Goh Alfred",
    "wof:placetype":"venue"
},
  "geometry": {"coordinates":[115.83805099999999,-32.015446],"type":"Point"}
}