{
  "type": "Feature",
  "properties": {
    "addr:full":"303 Logan Rd Stones Corner QLD 4120",
    "addr:housenumber":"303",
    "addr:postcode":"4120",
    "addr:street":"Logan Rd",
    "iso:country":"AU",
    "sg:address":"303 Logan Rd",
    "sg:city":"Stones Corner",
    "sg:classifiers":[
        {
            "category":"Shopping",
            "subcategory":"Jewelry",
            "type":"Retail Goods"
        }
    ],
    "sg:phone":"+61 7 3847 6066",
    "sg:postcode":"4120",
    "sg:province":"QLD",
    "sg:tags":[
        "jeweller"
    ],
    "wof:name":"NT Jewellery",
    "wof:placetype":"venue"
},
  "geometry": {"coordinates":[153.04649352999999,-27.5012989044],"type":"Point"}
}