{
  "type": "Feature",
  "properties": {
    "addr:full":"40 Paris Pde Katoomba NSW 2780",
    "addr:housenumber":"40",
    "addr:postcode":"2780",
    "addr:street":"Paris Pde",
    "iso:country":"AU",
    "sg:address":"40 Paris Pde",
    "sg:city":"Katoomba",
    "sg:classifiers":[
        {
            "category":"Professional",
            "subcategory":"Detective & Security Services",
            "type":"Services"
        }
    ],
    "sg:phone":"+61 413 940 834",
    "sg:postcode":"2780",
    "sg:province":"NSW",
    "sg:tags":[
        "equipment",
        "window",
        "doors"
    ],
    "wof:name":"PK Fittings",
    "wof:placetype":"venue"
},
  "geometry": {"coordinates":[150.31582641599999,-33.6948356628],"type":"Point"}
}