{
  "type": "Feature",
  "properties": {
    "addr:full":"10 Gradwell Dr Lennox Head NSW 2478",
    "addr:housenumber":"10",
    "addr:postcode":"2478",
    "addr:street":"Gradwell Dr",
    "iso:country":"AU",
    "sg:address":"10 Gradwell Dr",
    "sg:city":"Lennox Head",
    "sg:classifiers":[
        {
            "category":"Banks & Credit Unions",
            "subcategory":"Financial Services",
            "type":"Services"
        }
    ],
    "sg:phone":"+61 2 6687 4654",
    "sg:postcode":"2478",
    "sg:province":"NSW",
    "sg:tags":[
        "loan",
        "finance",
        "mortgage"
    ],
    "wof:name":"Mortgage Bureau",
    "wof:placetype":"venue"
},
  "geometry": {"coordinates":[153.58355712900001,-28.8019962311],"type":"Point"}
}