{
  "type": "Feature",
  "properties": {
    "addr:full":"56 Landsborough Pde Caloundra QLD 4551",
    "addr:housenumber":"56",
    "addr:postcode":"4551",
    "addr:street":"Landsborough Pde",
    "iso:country":"AU",
    "sg:address":"56 Landsborough Pde",
    "sg:city":"Caloundra",
    "sg:classifiers":[
        {
            "category":"Health Services",
            "subcategory":"Health Practitioner",
            "type":"Services"
        }
    ],
    "sg:phone":"+61 7 5492 3305",
    "sg:postcode":"4551",
    "sg:province":"QLD",
    "sg:tags":[
        "acupuncture"
    ],
    "wof:name":"Cisneros, Lucille & Wrigley, Tony Suncoast Natural Therapies Clinic Golden Beach",
    "wof:placetype":"venue"
},
  "geometry": {"coordinates":[153.11993408199999,-26.8218784332],"type":"Point"}
}