{
  "type": "Feature",
  "properties": {
    "iso:country":"AU",
    "sg:address":"777 Geelong Rd",
    "sg:city":"Brooklyn",
    "sg:classifiers":[
        {
            "category":"Retail",
            "subcategory":"Auto Rental",
            "type":"Services"
        }
    ],
    "sg:phone":"+61 3 9317 8743",
    "sg:postcode":"3025",
    "sg:province":"VIC",
    "sg:tags":[
        "car",
        "hire",
        "minibus"
    ],
    "wof:name":"Hertz Campervans",
    "wof:placetype":"venue"
},
  "geometry": {"coordinates":[144.83105499999999,-37.822147],"type":"Point"}
}