{
  "type": "Feature",
  "properties": {
    "addr:full":"57a George St Moonta SA 5558",
    "addr:housenumber":"57a",
    "addr:postcode":"5558",
    "addr:street":"George St",
    "iso:country":"AU",
    "sg:address":"57a George St",
    "sg:city":"Moonta",
    "sg:classifiers":[
        {
            "category":"Personal",
            "subcategory":"Beauty Salon",
            "type":"Services"
        }
    ],
    "sg:phone":"+61 8 8825 3001",
    "sg:postcode":"5558",
    "sg:province":"SA",
    "sg:tags":[
        "hairdresser"
    ],
    "wof:name":"Hair Bitz By Wendy",
    "wof:placetype":"venue"
},
  "geometry": {"coordinates":[137.591552734,-34.068561554],"type":"Point"}
}