{
  "type": "Feature",
  "properties": {
    "addr:full":"8 McWilliam St Springvale VIC 3171",
    "addr:housenumber":"8",
    "addr:postcode":"3171",
    "addr:street":"Mcwilliam St",
    "iso:country":"AU",
    "sg:address":"8 McWilliam St",
    "sg:city":"Springvale",
    "sg:classifiers":[
        {
            "category":"Manufacturing",
            "subcategory":"Wood Products",
            "type":"Manufacturing & Wholesale Goods"
        }
    ],
    "sg:phone":"+61 3 9548 5332",
    "sg:postcode":"3171",
    "sg:province":"VIC",
    "sg:tags":[
        "pallet",
        "platform"
    ],
    "wof:name":"Pallet & Case Industries Pty. Ltd.",
    "wof:placetype":"venue"
},
  "geometry": {"coordinates":[145.16644287099999,-37.9386329651],"type":"Point"}
}