{
  "type": "Feature",
  "properties": {
    "iso:country":"AU",
    "sg:address":"5 Sara Gr",
    "sg:city":"Tottenham",
    "sg:classifiers":[
        {
            "category":"Manufacturing",
            "subcategory":"Tools & Machinery",
            "type":"Manufacturing & Wholesale Goods"
        }
    ],
    "sg:phone":"+61 3 9315 2088",
    "sg:postcode":"3012",
    "sg:province":"VIC",
    "sg:tags":[
        "equipment",
        "scale",
        "weighing"
    ],
    "sg:website":"http://www.colonialweighing.com.au",
    "wof:name":"Colonial Weighing Australia Pty Ltd",
    "wof:placetype":"venue"
},
  "geometry": {"coordinates":[144.84938049300001,-37.7993469238],"type":"Point"}
}