{
  "type": "Feature",
  "properties": {
    "addr:full":"4 Varman Crt Nunawading VIC 3131",
    "addr:housenumber":"4",
    "addr:postcode":"3131",
    "addr:street":"Varman Crt",
    "iso:country":"AU",
    "sg:address":"4 Varman Crt",
    "sg:city":"Nunawading",
    "sg:classifiers":[
        {
            "category":"Utilities",
            "subcategory":"Electric",
            "type":"Services"
        }
    ],
    "sg:phone":"+61 3 9877 5955",
    "sg:postcode":"3131",
    "sg:province":"VIC",
    "sg:tags":[
        "electrical",
        "contractor"
    ],
    "wof:name":"Hilite Electrical Contracting",
    "wof:placetype":"venue"
},
  "geometry": {"coordinates":[145.172607422,-37.8189697266],"type":"Point"}
}