{
  "type": "Feature",
  "properties": {
    "addr:full":"84 Scott St Warracknabeal VIC 3393",
    "addr:housenumber":"84",
    "addr:postcode":"3393",
    "addr:street":"Scott St",
    "iso:country":"AU",
    "sg:address":"84 Scott St",
    "sg:city":"Warracknabeal",
    "sg:classifiers":[
        {
            "category":"Personal",
            "subcategory":"Beauty Salon",
            "type":"Services"
        }
    ],
    "sg:phone":"+61 3 5398 2154",
    "sg:postcode":"3393",
    "sg:province":"VIC",
    "sg:tags":[
        "hairdresser"
    ],
    "wof:name":"Salon 84",
    "wof:placetype":"venue"
},
  "geometry": {"coordinates":[142.39483642600001,-36.2499961853],"type":"Point"}
}