{
  "type": "Feature",
  "properties": {
    "addr:full":"60 Endersbee St Merredin WA 6415",
    "addr:housenumber":"60",
    "addr:postcode":"6415",
    "addr:street":"Endersbee St",
    "iso:country":"AU",
    "sg:address":"60 Endersbee St",
    "sg:city":"Merredin",
    "sg:classifiers":[
        {
            "category":"Farming",
            "subcategory":"Farm & Veterinary Services",
            "type":"Manufacturing & Wholesale Goods"
        }
    ],
    "sg:phone":"+61 8 9041 2563",
    "sg:postcode":"6415",
    "sg:province":"WA",
    "sg:tags":[
        "worm"
    ],
    "wof:name":"Merredin Worm & Compost Farms",
    "wof:placetype":"venue"
},
  "geometry": {"coordinates":[118.283401489,-31.4902133942],"type":"Point"}
}