{
  "type": "Feature",
  "properties": {
    "iso:country":"AU",
    "sg:address":"Shop 4, 247 Seacombe Rd",
    "sg:city":"Brighton",
    "sg:classifiers":[
        {
            "category":"Building & Trades",
            "subcategory":"Locksmith",
            "type":"Services"
        }
    ],
    "sg:phone":"+61 8 8296 3838",
    "sg:postcode":"5048",
    "sg:province":"SA",
    "sg:tags":[
        "lock"
    ],
    "wof:name":"A Big Key Locksmiths",
    "wof:placetype":"venue"
},
  "geometry": {"coordinates":[138.526352,-35.029964],"type":"Point"}
}