{
  "type": "Feature",
  "properties": {
    "addr:full":"1 Hillcrest Ave Gladesville NSW 2111",
    "addr:housenumber":"1",
    "addr:postcode":"2111",
    "addr:street":"Hillcrest Ave",
    "iso:country":"AU",
    "sg:address":"1 Hillcrest Ave",
    "sg:city":"Gladesville",
    "sg:classifiers":[
        {
            "category":"Banks & Credit Unions",
            "subcategory":"Investment Brokerage",
            "type":"Services"
        }
    ],
    "sg:phone":"+61 1300 666 416",
    "sg:postcode":"2111",
    "sg:province":"NSW",
    "sg:tags":[
        "testing",
        "licence",
        "boat"
    ],
    "wof:name":"Australian Boating College NSW",
    "wof:placetype":"venue"
},
  "geometry": {"coordinates":[151.12857055699999,-33.8360137939],"type":"Point"}
}