{
  "type": "Feature",
  "properties": {
    "iso:country":"AU",
    "sg:address":"654 Back River Rd",
    "sg:city":"Magra",
    "sg:classifiers":[
        {
            "category":"Recreation",
            "subcategory":"Fishing",
            "type":"Entertainment"
        }
    ],
    "sg:phone":"+61 3 6261 3074",
    "sg:postcode":"7140",
    "sg:province":"TAS",
    "sg:tags":[
        "trip"
    ],
    "wof:name":"Trout Fishing Safaris Of Tasmania",
    "wof:placetype":"venue"
},
  "geometry": {"coordinates":[147.05102500000001,-42.756348],"type":"Point"}
}