{
  "type": "Feature",
  "properties": {
    "iso:country":"AU",
    "sg:address":"Level 2/ 38 Currie St",
    "sg:city":"Adelaide",
    "sg:classifiers":[
        {
            "category":"Professional",
            "subcategory":"Employment Agencies",
            "type":"Services"
        }
    ],
    "sg:phone":"+61 8 8212 6211",
    "sg:postcode":"5000",
    "sg:province":"SA",
    "sg:tags":[
        "model"
    ],
    "wof:name":"Exclusive Models",
    "wof:placetype":"venue"
},
  "geometry": {"coordinates":[138.598953247,-34.924621582],"type":"Point"}
}