{
  "type": "Feature",
  "properties": {
    "iso:country":"AU",
    "sg:address":"17 Fariola St",
    "sg:city":"Silverwater",
    "sg:classifiers":[
        {
            "category":"Home & Garden",
            "subcategory":"Building Materials",
            "type":"Retail Goods"
        }
    ],
    "sg:phone":"+61 2 9748 4422",
    "sg:postcode":"2128",
    "sg:province":"NSW",
    "sg:tags":[
        "roofing"
    ],
    "wof:name":"Silverwater Roofing Supplies",
    "wof:placetype":"venue"
},
  "geometry": {"coordinates":[151.051223755,-33.834854126],"type":"Point"}
}