{
  "type": "Feature",
  "properties": {
    "iso:country":"AU",
    "sg:address":"Cusack La",
    "sg:city":"Jimboomba",
    "sg:classifiers":[
        {
            "category":"Autos & Motor Vehicles",
            "subcategory":"Fuel & Gas Station",
            "type":"Retail Goods"
        }
    ],
    "sg:phone":"+61 7 5546 9677",
    "sg:postcode":"4280",
    "sg:province":"QLD",
    "wof:name":"Ampol Convenience Store & Oil Centre Jimboomba",
    "wof:placetype":"venue"
},
  "geometry": {"coordinates":[153.02641299999999,-27.831095],"type":"Point"}
}