{
  "type": "Feature",
  "properties": {
    "addr:full":"553 Boundary Rd Richlands QLD 4077",
    "addr:housenumber":"553",
    "addr:postcode":"4077",
    "addr:street":"Boundary Rd",
    "iso:country":"AU",
    "sg:address":"553 Boundary Rd",
    "sg:city":"Richlands",
    "sg:classifiers":[
        {
            "category":"Home & Garden",
            "subcategory":"Hardware",
            "type":"Retail Goods"
        }
    ],
    "sg:phone":"+61 7 3375 7011",
    "sg:postcode":"4077",
    "sg:province":"QLD",
    "sg:tags":[
        "nut",
        "bolt"
    ],
    "wof:name":"United Fasteners",
    "wof:placetype":"venue"
},
  "geometry": {"coordinates":[152.95970153799999,-27.5765075684],"type":"Point"}
}