{
  "type": "Feature",
  "properties": {
    "iso:country":"AU",
    "sg:address":"122 Old Prospect Rd",
    "sg:city":"Greystanes",
    "sg:classifiers":[
        {
            "category":"Building & Trades",
            "subcategory":"Pest Control",
            "type":"Services"
        }
    ],
    "sg:phone":"+61 2 9896 8815",
    "sg:postcode":"2145",
    "sg:province":"NSW",
    "wof:name":"L & M Pest Management Pty Ltd",
    "wof:placetype":"venue"
},
  "geometry": {"coordinates":[150.96090698200001,-33.8179893494],"type":"Point"}
}