{
  "type": "Feature",
  "properties": {
    "addr:full":"23 McMahons Rd Nowra North NSW 2541",
    "addr:housenumber":"23",
    "addr:postcode":"2541",
    "addr:street":"Mcmahons Rd",
    "iso:country":"AU",
    "sg:address":"23 McMahons Rd",
    "sg:city":"Nowra North",
    "sg:classifiers":[
        {
            "category":"Health Services",
            "subcategory":"Doctor",
            "type":"Services"
        }
    ],
    "sg:phone":"+61 2 4423 5991",
    "sg:postcode":"2541",
    "sg:province":"NSW",
    "sg:tags":[
        "medical",
        "practitioner"
    ],
    "wof:name":"Allin Paul Dr",
    "wof:placetype":"venue"
},
  "geometry": {"coordinates":[150.58197021500001,-34.8588523865],"type":"Point"}
}