{
  "type": "Feature",
  "properties": {
    "iso:country":"AU",
    "sg:address":"Greenwith Rd",
    "sg:city":"Golden Grove",
    "sg:classifiers":[
        {
            "category":"School Buses",
            "type":"Transportation"
        }
    ],
    "sg:phone":"+61 8 8251 1166",
    "sg:postcode":"5125",
    "sg:province":"SA",
    "sg:tags":[
        "brick"
    ],
    "wof:name":"Austral Bricks",
    "wof:placetype":"venue"
},
  "geometry": {"coordinates":[138.72233600000001,-34.784389],"type":"Point"}
}