{
  "type": "Feature",
  "properties": {
    "addr:full":"131 Ellen St Port Pirie SA 5540",
    "addr:housenumber":"131",
    "addr:postcode":"5540",
    "addr:street":"Ellen St",
    "iso:country":"AU",
    "sg:address":"131 Ellen St",
    "sg:city":"Port Pirie",
    "sg:classifiers":[
        {
            "category":"Real Estate",
            "subcategory":"Real Estate Agent",
            "type":"Services"
        }
    ],
    "sg:phone":"+61 8 8632 4077",
    "sg:postcode":"5540",
    "sg:province":"SA",
    "wof:name":"Century 21 Pirie Properties",
    "wof:placetype":"venue"
},
  "geometry": {"coordinates":[138.01077270499999,-33.1778831482],"type":"Point"}
}