{
  "type": "Feature",
  "properties": {
    "iso:country":"AU",
    "sg:address":"14 Lindsay St",
    "sg:city":"Campsie",
    "sg:classifiers":[
        {
            "category":"Utilities",
            "subcategory":"Electric",
            "type":"Services"
        }
    ],
    "sg:phone":"+61 2 9787 4056",
    "sg:postcode":"2194",
    "sg:province":"NSW",
    "sg:tags":[
        "electrical",
        "contractor"
    ],
    "wof:name":"Local Electric Pty Ltd",
    "wof:placetype":"venue"
},
  "geometry": {"coordinates":[151.109207,-33.90464],"type":"Point"}
}