{
  "type": "Feature",
  "properties": {
    "addr:full":"2 Fitzgerald Rd Laverton North VIC 3026",
    "addr:housenumber":"2",
    "addr:postcode":"3026",
    "addr:street":"Fitzgerald Rd",
    "iso:country":"AU",
    "sg:address":"2 Fitzgerald Rd",
    "sg:city":"Laverton North",
    "sg:classifiers":[
        {
            "category":"Bars & Pubs",
            "subcategory":"Nightclub",
            "type":"Food & Drink"
        }
    ],
    "sg:phone":"+61 3 9369 1324",
    "sg:postcode":"3026",
    "sg:province":"VIC",
    "sg:tags":[
        "discotheque"
    ],
    "wof:name":"The Soundgarden Bar",
    "wof:placetype":"venue"
},
  "geometry": {"coordinates":[144.79179400000001,-37.782146],"type":"Point"}
}