{
  "type": "Feature",
  "properties": {
    "addr:full":"22 Mareeba Crt Arana Hills QLD 4054",
    "addr:housenumber":"22",
    "addr:postcode":"4054",
    "addr:street":"Mareeba Crt",
    "iso:country":"AU",
    "sg:address":"22 Mareeba Crt",
    "sg:city":"Arana Hills",
    "sg:classifiers":[
        {
            "category":"Building & Trades",
            "subcategory":"Construction",
            "type":"Services"
        }
    ],
    "sg:phone":"+61 7 3851 2744",
    "sg:postcode":"4054",
    "sg:province":"QLD",
    "sg:tags":[
        "contractor"
    ],
    "wof:name":"Pippin O J Pty Ltd",
    "wof:placetype":"venue"
},
  "geometry": {"coordinates":[152.954986572,-27.3840179443],"type":"Point"}
}