{
  "type": "Feature",
  "properties": {
    "addr:full":"61 Beanland St Jamboree Heights QLD 4074",
    "addr:housenumber":"61",
    "addr:postcode":"4074",
    "addr:street":"Beanland St",
    "iso:country":"AU",
    "sg:address":"61 Beanland St",
    "sg:city":"Jamboree Heights",
    "sg:classifiers":[
        {
            "category":"Education",
            "subcategory":"Kindergarten",
            "type":"Public Place"
        }
    ],
    "sg:phone":"+61 7 3376 1556",
    "sg:postcode":"4074",
    "sg:province":"QLD",
    "sg:tags":[
        "pre-schools"
    ],
    "wof:name":"Jamboree Community Kindergarten & Pre-School",
    "wof:placetype":"venue"
},
  "geometry": {"coordinates":[152.92909240700001,-27.5541744232],"type":"Point"}
}