{
  "type": "Feature",
  "properties": {
    "iso:country":"AU",
    "sg:address":"300 Arden St",
    "sg:city":"North Melbourne",
    "sg:classifiers":[
        {
            "category":"Professional",
            "subcategory":"Detective & Security Services",
            "type":"Services"
        }
    ],
    "sg:phone":"+61 3 9329 6866",
    "sg:postcode":"3051",
    "sg:province":"VIC",
    "sg:tags":[
        "consultant",
        "system"
    ],
    "wof:name":"Cables Plus (VIC) Pty Ltd",
    "wof:placetype":"venue"
},
  "geometry": {"coordinates":[144.938842773,-37.7995681763],"type":"Point"}
}