{
  "type": "Feature",
  "properties": {
    "iso:country":"AU",
    "sg:address":"161 Como Pde East",
    "sg:city":"Parkdale",
    "sg:classifiers":[
        {
            "category":"Professional",
            "subcategory":"Computer Services",
            "type":"Services"
        }
    ],
    "sg:phone":"+61 3 9580 2100",
    "sg:postcode":"3195",
    "sg:province":"VIC",
    "sg:tags":[
        "consultant",
        "system"
    ],
    "wof:name":"Almost Vertical Software Pty Ltd",
    "wof:placetype":"venue"
},
  "geometry": {"coordinates":[145.07643127399999,-37.9926795959],"type":"Point"}
}