{
  "type": "Feature",
  "properties": {
    "addr:full":"5- 6 Brighton Shopng Cntr Brighton TAS 7030",
    "addr:housenumber":"6",
    "addr:postcode":"7030",
    "addr:street":"Brighton Shopng Cntr",
    "iso:country":"AU",
    "sg:address":"5- 6 Brighton Shopng Cntr",
    "sg:city":"Brighton",
    "sg:classifiers":[
        {
            "category":"Fast Food",
            "type":"Food & Drink"
        }
    ],
    "sg:phone":"+61 3 6268 1045",
    "sg:postcode":"7030",
    "sg:province":"TAS",
    "sg:tags":[
        "away",
        "take"
    ],
    "wof:name":"How Lin Chinese Restaurant",
    "wof:placetype":"venue"
},
  "geometry": {"coordinates":[147.25169372600001,-42.6992988586],"type":"Point"}
}