{
  "type": "Feature",
  "properties": {
    "iso:country":"AU",
    "sg:address":"120 Bourke St",
    "sg:city":"Melbourne",
    "sg:classifiers":[
        {
            "category":"Travel",
            "subcategory":"Travel Agent",
            "type":"Entertainment"
        }
    ],
    "sg:phone":"+61 3 9663 1237",
    "sg:postcode":"3000",
    "sg:province":"VIC",
    "sg:tags":[
        "consultant"
    ],
    "wof:name":"Extragreen Holidays (Aust) Pty Ltd",
    "wof:placetype":"venue"
},
  "geometry": {"coordinates":[144.96963500999999,-37.8122215271],"type":"Point"}
}