{
  "type": "Feature",
  "properties": {
    "addr:full":"Dunn Bay Rd Dunsborough WA 6281",
    "addr:postcode":"6281",
    "addr:street":"Bay Rd",
    "iso:country":"AU",
    "sg:address":"Dunn Bay Rd",
    "sg:city":"Dunsborough",
    "sg:classifiers":[
        {
            "category":"Health Services",
            "subcategory":"Doctor",
            "type":"Services"
        }
    ],
    "sg:phone":"+61 8 9756 8600",
    "sg:postcode":"6281",
    "sg:province":"WA",
    "sg:tags":[
        "medical",
        "practitioner"
    ],
    "wof:name":"Garnett Sally Dr.",
    "wof:placetype":"venue"
},
  "geometry": {"coordinates":[115.102363586,-33.617225647],"type":"Point"}
}