{
  "type": "Feature",
  "properties": {
    "addr:full":"3 Macquarie St Cowra NSW 2794",
    "addr:housenumber":"3",
    "addr:postcode":"2794",
    "addr:street":"Macquarie St",
    "iso:country":"AU",
    "sg:address":"3 Macquarie St",
    "sg:city":"Cowra",
    "sg:classifiers":[
        {
            "category":"Travel",
            "subcategory":"Hotels & Motels",
            "type":"Entertainment"
        }
    ],
    "sg:phone":"+61 2 6342 2011",
    "sg:postcode":"2794",
    "sg:province":"NSW",
    "wof:name":"Cowra Motor Inn",
    "wof:placetype":"venue"
},
  "geometry": {"coordinates":[148.68853759800001,-33.836101532],"type":"Point"}
}