{
  "type": "Feature",
  "properties": {
    "addr:full":"Lot 70 Excelsior St Lisarow NSW 2250",
    "addr:postcode":"2250",
    "addr:street":"Excelsior St",
    "iso:country":"AU",
    "sg:address":"Lot 70 Excelsior St",
    "sg:city":"Lisarow",
    "sg:classifiers":[
        {
            "category":"Building & Trades",
            "subcategory":"Construction",
            "type":"Services"
        }
    ],
    "sg:phone":"+61 408 436 420",
    "sg:postcode":"2250",
    "sg:province":"NSW",
    "sg:tags":[
        "joiner",
        "carpenter"
    ],
    "wof:name":"Hebikale Pty Ltd",
    "wof:placetype":"venue"
},
  "geometry": {"coordinates":[151.36489868199999,-33.3777694702],"type":"Point"}
}