{
  "type": "Feature",
  "properties": {
    "iso:country":"AU",
    "sg:address":"105 Glebe Point Rd",
    "sg:city":"Glebe",
    "sg:classifiers":[
        {
            "category":"Health Services",
            "subcategory":"Chiropractor",
            "type":"Services"
        }
    ],
    "sg:phone":"+61 2 9660 8342",
    "sg:postcode":"2037",
    "sg:province":"NSW",
    "wof:name":"Daniel Edwards Chiropractic",
    "wof:placetype":"venue"
},
  "geometry": {"coordinates":[151.19009399399999,-33.8822174072],"type":"Point"}
}