{
  "type": "Feature",
  "properties": {
    "addr:full":"16 Hauteville St Thurgoona NSW 2640",
    "addr:housenumber":"16",
    "addr:postcode":"2640",
    "addr:street":"Hauteville St",
    "iso:country":"AU",
    "sg:address":"16 Hauteville St",
    "sg:city":"Thurgoona",
    "sg:classifiers":[
        {
            "category":"Personal",
            "subcategory":"Beauty Salon",
            "type":"Services"
        }
    ],
    "sg:phone":"+61 2 6043 1323",
    "sg:postcode":"2640",
    "sg:province":"NSW",
    "sg:tags":[
        "hairdresser"
    ],
    "wof:name":"Top Knots",
    "wof:placetype":"venue"
},
  "geometry": {"coordinates":[146.98283386200001,-36.0444488525],"type":"Point"}
}