{
  "type": "Feature",
  "properties": {
    "addr:full":"King St Campbelltown NSW 2560",
    "addr:postcode":"2560",
    "addr:street":"King St",
    "iso:country":"AU",
    "sg:address":"King St",
    "sg:city":"Campbelltown",
    "sg:classifiers":[
        {
            "category":"Arena",
            "subcategory":"Sports Club",
            "type":"Entertainment"
        }
    ],
    "sg:phone":"+61 2 4628 2144",
    "sg:postcode":"2560",
    "sg:province":"NSW",
    "sg:tags":[
        "union",
        "rugby"
    ],
    "wof:name":"Campbelltown Harlequin Rugby Club",
    "wof:placetype":"venue"
},
  "geometry": {"coordinates":[150.818603516,-34.0633811951],"type":"Point"}
}