{
  "type": "Feature",
  "properties": {
    "addr:full":"702 Canterbury Rd Belmore NSW 2192",
    "addr:housenumber":"702",
    "addr:postcode":"2192",
    "addr:street":"Canterbury Rd",
    "iso:country":"AU",
    "sg:address":"702 Canterbury Rd",
    "sg:city":"Belmore",
    "sg:classifiers":[
        {
            "category":"Manufacturing",
            "subcategory":"Motor Vehicles & Parts",
            "type":"Manufacturing & Wholesale Goods"
        }
    ],
    "sg:phone":"+61 2 9750 4346",
    "sg:postcode":"2192",
    "sg:province":"NSW",
    "sg:tags":[
        "wholesaler",
        "cycle",
        "mfrs",
        "accessory"
    ],
    "wof:name":"Gowanloch Motorcycle",
    "wof:placetype":"venue"
},
  "geometry": {"coordinates":[151.092026,-33.923798],"type":"Point"}
}