{
  "type": "Feature",
  "properties": {
    "addr:full":"82 Baylis St Wagga Wagga NSW 2650",
    "addr:housenumber":"82",
    "addr:postcode":"2650",
    "addr:street":"Baylis St",
    "iso:country":"AU",
    "sg:address":"82 Baylis St",
    "sg:city":"Wagga Wagga",
    "sg:classifiers":[
        {
            "category":"Banks & Credit Unions",
            "subcategory":"Financial Services",
            "type":"Services"
        }
    ],
    "sg:phone":"+61 2 6925 8566",
    "sg:postcode":"2650",
    "sg:province":"NSW",
    "sg:tags":[
        "loan",
        "finance",
        "mortgage"
    ],
    "wof:name":"Wizard",
    "wof:placetype":"venue"
},
  "geometry": {"coordinates":[147.369262695,-35.1156005859],"type":"Point"}
}