{
  "type": "Feature",
  "properties": {
    "addr:full":"68 Orlando St Hampton VIC 3188",
    "addr:housenumber":"68",
    "addr:postcode":"3188",
    "addr:street":"Orlando St",
    "iso:country":"AU",
    "sg:address":"68 Orlando St",
    "sg:city":"Hampton",
    "sg:classifiers":[
        {
            "category":"Building & Trades",
            "subcategory":"Construction",
            "type":"Services"
        }
    ],
    "sg:phone":"+61 3 9598 0909",
    "sg:postcode":"3188",
    "sg:province":"VIC",
    "sg:tags":[
        "waterproofing",
        "contractor"
    ],
    "wof:name":"Protecon",
    "wof:placetype":"venue"
},
  "geometry": {"coordinates":[144.99838256800001,-37.936050415],"type":"Point"}
}