{
  "type": "Feature",
  "properties": {
    "addr:full":"Nairana St Invermay TAS 7248",
    "addr:postcode":"7248",
    "addr:street":"St",
    "iso:country":"AU",
    "sg:address":"Nairana St",
    "sg:city":"Invermay",
    "sg:classifiers":[
        {
            "category":"Professional",
            "type":"Services"
        }
    ],
    "sg:phone":"+61 1300 366 684",
    "sg:postcode":"7248",
    "sg:province":"TAS",
    "sg:tags":[
        "transport"
    ],
    "wof:name":"Toll IPEC",
    "wof:placetype":"venue"
},
  "geometry": {"coordinates":[147.12692260700001,-41.4253005981],"type":"Point"}
}