{
  "type": "Feature",
  "properties": {
    "iso:country":"AU",
    "sg:address":"Unit 3, 66 Garden St",
    "sg:city":"North Narrabeen",
    "sg:classifiers":[
        {
            "category":"Professional",
            "subcategory":"Engineering",
            "type":"Services"
        }
    ],
    "sg:phone":"+61 2 9970 8491",
    "sg:postcode":"2101",
    "sg:province":"NSW",
    "sg:tags":[
        "engineer"
    ],
    "wof:name":"Induserve Industrial Maintenance",
    "wof:placetype":"venue"
},
  "geometry": {"coordinates":[151.29536400000001,-33.701801],"type":"Point"}
}