{
  "type": "Feature",
  "properties": {
    "iso:country":"AU",
    "sg:address":"\"Tooran\" Cantara Rd",
    "sg:city":"Keith",
    "sg:classifiers":[
        {
            "category":"Farming",
            "subcategory":"Farm",
            "type":"Manufacturing & Wholesale Goods"
        }
    ],
    "sg:phone":"+61 8 8755 1542",
    "sg:postcode":"5267",
    "sg:province":"SA",
    "sg:tags":[
        "farmer"
    ],
    "wof:name":"Cunningham A G & M E",
    "wof:placetype":"venue"
},
  "geometry": {"coordinates":[140.354874,-36.098148],"type":"Point"}
}