{
  "type": "Feature",
  "properties": {
    "addr:full":"82 Sorlie Rd Frenchs Forest NSW 2086",
    "addr:housenumber":"82",
    "addr:postcode":"2086",
    "addr:street":"Sorlie Rd",
    "iso:country":"AU",
    "sg:address":"82 Sorlie Rd",
    "sg:city":"Frenchs Forest",
    "sg:classifiers":[
        {
            "category":"Travel",
            "subcategory":"Travel Agent",
            "type":"Entertainment"
        }
    ],
    "sg:phone":"+61 2 9451 7139",
    "sg:postcode":"2086",
    "sg:province":"NSW",
    "sg:tags":[
        "consultant"
    ],
    "wof:name":"Garigal Tour Company Pty Ltd",
    "wof:placetype":"venue"
},
  "geometry": {"coordinates":[151.21388244600001,-33.7451477051],"type":"Point"}
}