{
  "type": "Feature",
  "properties": {
    "iso:country":"AU",
    "sg:address":"7 Hay St",
    "sg:city":"Albany",
    "sg:classifiers":[
        {
            "category":"Food & Beverages",
            "subcategory":"Specialty",
            "type":"Retail Goods"
        }
    ],
    "sg:phone":"+61 8 9842 2747",
    "sg:postcode":"6330",
    "sg:province":"WA",
    "sg:tags":[
        "product",
        "health"
    ],
    "wof:name":"Rawleigh Products",
    "wof:placetype":"venue"
},
  "geometry": {"coordinates":[117.898269653,-35.0214157104],"type":"Point"}
}