{
  "type": "Feature",
  "properties": {
    "addr:full":"470 Rathdowne St Carlton North VIC 3054",
    "addr:housenumber":"470",
    "addr:postcode":"3054",
    "addr:street":"Rathdowne St",
    "iso:country":"AU",
    "sg:address":"470 Rathdowne St",
    "sg:city":"Carlton North",
    "sg:classifiers":[
        {
            "category":"Building & Trades",
            "subcategory":"Landscaping Services",
            "type":"Services"
        }
    ],
    "sg:phone":"+61 3 9347 2385",
    "sg:postcode":"3054",
    "sg:province":"VIC",
    "sg:tags":[
        "designer",
        "landscape",
        "contractor"
    ],
    "wof:name":"GB & MO Sharp",
    "wof:placetype":"venue"
},
  "geometry": {"coordinates":[144.97262573200001,-37.7864074707],"type":"Point"}
}