{
  "type": "Feature",
  "properties": {
    "addr:full":"268 Johnston St Collingwood VIC 3066",
    "addr:housenumber":"268",
    "addr:postcode":"3066",
    "addr:street":"Johnston St",
    "iso:country":"AU",
    "sg:address":"268 Johnston St",
    "sg:city":"Collingwood",
    "sg:classifiers":[
        {
            "category":"Fast Food",
            "type":"Food & Drink"
        }
    ],
    "sg:phone":"+61 3 9417 6248",
    "sg:postcode":"3066",
    "sg:province":"VIC",
    "sg:tags":[
        "away",
        "take"
    ],
    "wof:name":"E J Gourmet",
    "wof:placetype":"venue"
},
  "geometry": {"coordinates":[144.984008789,-37.799041748],"type":"Point"}
}