{
  "type": "Feature",
  "properties": {
    "iso:country":"AU",
    "sg:address":"Uniting Church Hall 10 Turramurra Ave",
    "sg:city":"Turramurra",
    "sg:classifiers":[
        {
            "category":"Arena",
            "subcategory":"Sports Club",
            "type":"Entertainment"
        }
    ],
    "sg:phone":"+61 2 9639 7771",
    "sg:postcode":"2074",
    "sg:province":"NSW",
    "sg:tags":[
        "defence",
        "supply",
        "self",
        "instruction",
        "martial art"
    ],
    "wof:name":"Taekwondo World",
    "wof:placetype":"venue"
},
  "geometry": {"coordinates":[151.13082885700001,-33.7319068909],"type":"Point"}
}