{
  "type": "Feature",
  "properties": {
    "addr:full":"82 South Rd Brighton Beach VIC 3186",
    "addr:housenumber":"82",
    "addr:postcode":"3186",
    "addr:street":"South Rd",
    "iso:country":"AU",
    "sg:address":"82 South Rd",
    "sg:city":"Brighton Beach",
    "sg:classifiers":[
        {
            "category":"Building & Trades",
            "subcategory":"Plumbing",
            "type":"Services"
        }
    ],
    "sg:phone":"+61 3 9598 2207",
    "sg:postcode":"3186",
    "sg:province":"VIC",
    "sg:tags":[
        "plumber",
        "gasfitters"
    ],
    "wof:name":"Drips Plumbing",
    "wof:placetype":"venue"
},
  "geometry": {"coordinates":[145.00180053700001,-37.9292297363],"type":"Point"}
}