{
  "type": "Feature",
  "properties": {
    "addr:full":"22 Campbelltown Rd Denham Court NSW 2565",
    "addr:housenumber":"22",
    "addr:postcode":"2565",
    "addr:street":"Campbelltown Rd;Court",
    "iso:country":"AU",
    "sg:address":"22 Campbelltown Rd",
    "sg:city":"Denham Court",
    "sg:classifiers":[
        {
            "category":"Retail",
            "subcategory":"Auto Repair",
            "type":"Services"
        }
    ],
    "sg:phone":"+61 2 9605 4300",
    "sg:postcode":"2565",
    "sg:province":"NSW",
    "sg:tags":[
        "repairer",
        "motor",
        "engineer"
    ],
    "wof:name":"Denham Court Automotives",
    "wof:placetype":"venue"
},
  "geometry": {"coordinates":[150.84342956500001,-33.9956741333],"type":"Point"}
}