{
  "type": "Feature",
  "properties": {
    "addr:full":"152 Commercial Rd Koroit VIC 3282",
    "addr:housenumber":"152",
    "addr:postcode":"3282",
    "addr:street":"Commercial Rd",
    "iso:country":"AU",
    "sg:address":"152 Commercial Rd",
    "sg:city":"Koroit",
    "sg:classifiers":[
        {
            "category":"Shopping",
            "subcategory":"Antiques",
            "type":"Retail Goods"
        }
    ],
    "sg:phone":"+61 3 5565 8581",
    "sg:postcode":"3282",
    "sg:province":"VIC",
    "wof:name":"Koroit Antiques & Collectables",
    "wof:placetype":"venue"
},
  "geometry": {"coordinates":[142.36366272000001,-38.2915802002],"type":"Point"}
}