{
  "type": "Feature",
  "properties": {
    "addr:full":"Unit 14/ 8 Boorima Pl Cronulla NSW 2230",
    "addr:housenumber":"/ 8",
    "addr:postcode":"2230",
    "addr:street":"Boorima Pl",
    "iso:country":"AU",
    "sg:address":"Unit 14/ 8 Boorima Pl",
    "sg:city":"Cronulla",
    "sg:classifiers":[
        {
            "category":"Banks & Credit Unions",
            "subcategory":"Investment Brokerage",
            "type":"Services"
        }
    ],
    "sg:phone":"+61 2 9544 2392",
    "sg:postcode":"2230",
    "sg:province":"NSW",
    "wof:name":"Prudent Security Investments",
    "wof:placetype":"venue"
},
  "geometry": {"coordinates":[151.156326294,-34.0580482483],"type":"Point"}
}