{
  "type": "Feature",
  "properties": {
    "addr:full":"PO Box 354 Bulimba QLD 4171",
    "addr:postcode":"4171",
    "iso:country":"AU",
    "sg:address":"PO Box 354",
    "sg:city":"Bulimba",
    "sg:classifiers":[
        {
            "category":"Building & Trades",
            "subcategory":"Landscaping Services",
            "type":"Services"
        }
    ],
    "sg:phone":"+61 7 3899 1920",
    "sg:postcode":"4171",
    "sg:province":"QLD",
    "sg:tags":[
        "horticultural",
        "consultant"
    ],
    "wof:name":"Parks Landworks Pty Ltd",
    "wof:placetype":"venue"
},
  "geometry": {"coordinates":[153.05929565400001,-27.4513607025],"type":"Point"}
}