{
  "type": "Feature",
  "properties": {
    "addr:full":"394 Main Rd (West) St St Albans VIC 3021",
    "addr:housenumber":"394",
    "addr:postcode":"3021",
    "addr:street":"Main Rd West St",
    "iso:country":"AU",
    "sg:address":"394 Main Rd (West) St St",
    "sg:city":"Albans",
    "sg:classifiers":[
        {
            "category":"Health Services",
            "subcategory":"Doctor",
            "type":"Services"
        }
    ],
    "sg:phone":"+61 3 9366 1279",
    "sg:postcode":"3021",
    "sg:province":"VIC",
    "sg:tags":[
        "medical",
        "practitioner"
    ],
    "wof:name":"Umrysch B S Dr",
    "wof:placetype":"venue"
},
  "geometry": {"coordinates":[144.79333500000001,-37.74334],"type":"Point"}
}