{
  "type": "Feature",
  "properties": {
    "addr:full":"18 Vincent St Loganholme QLD 4129",
    "addr:housenumber":"18",
    "addr:postcode":"4129",
    "addr:street":"Vincent St",
    "iso:country":"AU",
    "sg:address":"18 Vincent St",
    "sg:city":"Loganholme",
    "sg:classifiers":[
        {
            "category":"Professional",
            "subcategory":"Management & Consulting",
            "type":"Services"
        }
    ],
    "sg:phone":"+61 7 3806 1117",
    "sg:postcode":"4129",
    "sg:province":"QLD",
    "sg:tags":[
        "consultant"
    ],
    "wof:name":"Joe Denis Consulting Services",
    "wof:placetype":"venue"
},
  "geometry": {"coordinates":[153.19761657699999,-27.672077179],"type":"Point"}
}