{
  "type": "Feature",
  "properties": {
    "iso:country":"AU",
    "sg:address":"21 Sydney Rd",
    "sg:city":"Mudgee",
    "sg:classifiers":[
        {
            "category":"Shopping",
            "type":"Retail Goods"
        }
    ],
    "sg:phone":"+61 2 6372 2298",
    "sg:postcode":"2850",
    "sg:province":"NSW",
    "sg:tags":[
        "equipment",
        "safety",
        "accessory"
    ],
    "wof:name":"Cudgegong Engineering & Safety Supplies",
    "wof:placetype":"venue"
},
  "geometry": {"coordinates":[149.58767700199999,-32.5993614197],"type":"Point"}
}