{
  "type": "Feature",
  "properties": {
    "addr:full":"Shp 1/ 51 Jetty Rd Brighton SA 5048",
    "addr:housenumber":"/ 51",
    "addr:postcode":"5048",
    "addr:street":"Jetty Rd",
    "iso:country":"AU",
    "sg:address":"Shp 1/ 51 Jetty Rd",
    "sg:city":"Brighton",
    "sg:classifiers":[
        {
            "category":"Personal",
            "type":"Services"
        }
    ],
    "sg:phone":"+61 8 8296 5460",
    "sg:postcode":"5048",
    "sg:province":"SA",
    "sg:tags":[
        "gift"
    ],
    "wof:name":"Aqua Living",
    "wof:placetype":"venue"
},
  "geometry": {"coordinates":[138.51672400000001,-35.017361],"type":"Point"}
}