{
  "type": "Feature",
  "properties": {
    "addr:full":"66 Darlinghurst Rd Kings Cross NSW 2011",
    "addr:housenumber":"66",
    "addr:postcode":"2011",
    "addr:street":"Darlinghurst Rd",
    "iso:country":"AU",
    "sg:address":"66 Darlinghurst Rd",
    "sg:city":"Kings Cross",
    "sg:classifiers":[
        {
            "category":"Fast Food",
            "type":"Food & Drink"
        }
    ],
    "sg:phone":"+61 2 9357 1996",
    "sg:postcode":"2011",
    "sg:province":"NSW",
    "sg:tags":[
        "away",
        "take"
    ],
    "wof:name":"KFC",
    "wof:placetype":"venue"
},
  "geometry": {"coordinates":[151.22265625,-33.8748474121],"type":"Point"}
}