{
  "type": "Feature",
  "properties": {
    "addr:full":"PO Box 653 Woy Woy NSW 2256",
    "addr:postcode":"2256",
    "iso:country":"AU",
    "sg:address":"PO Box 653",
    "sg:city":"Woy Woy",
    "sg:classifiers":[
        {
            "category":"Building & Trades",
            "subcategory":"Plumbing",
            "type":"Services"
        }
    ],
    "sg:phone":"+61 417 655 182",
    "sg:postcode":"2256",
    "sg:province":"NSW",
    "sg:tags":[
        "plumber",
        "gasfitters"
    ],
    "wof:name":"Tangye Graeme Plumbing",
    "wof:placetype":"venue"
},
  "geometry": {"coordinates":[151.327468872,-33.4929008484],"type":"Point"}
}