{
  "type": "Feature",
  "properties": {
    "addr:full":"PO Box 118 Mt Garnet QLD 4872",
    "addr:postcode":"4872",
    "iso:country":"AU",
    "sg:address":"PO Box 118",
    "sg:city":"Mt Garnet",
    "sg:classifiers":[
        {
            "category":"Manufacturing",
            "subcategory":"Chemicals & Compounds",
            "type":"Manufacturing & Wholesale Goods"
        }
    ],
    "sg:phone":"+61 7 4097 9293",
    "sg:postcode":"4872",
    "sg:province":"QLD",
    "sg:tags":[
        "electroplating"
    ],
    "wof:name":"Chrome Resurrections F.N.Q.",
    "wof:placetype":"venue"
},
  "geometry": {"coordinates":[145.12661743199999,-17.6828651428],"type":"Point"}
}