{
  "type": "Feature",
  "properties": {
    "addr:full":"736 Princes Hwy Kogarah NSW 2217",
    "addr:housenumber":"736",
    "addr:postcode":"2217",
    "addr:street":"Princes Hwy",
    "iso:country":"AU",
    "sg:address":"736 Princes Hwy",
    "sg:city":"Kogarah",
    "sg:classifiers":[
        {
            "category":"Autos & Motor Vehicles",
            "subcategory":"Fuel & Gas Station",
            "type":"Retail Goods"
        }
    ],
    "sg:phone":"+61 2 9553 6000",
    "sg:postcode":"2217",
    "sg:province":"NSW",
    "wof:name":"Mobil Oil Australia Pty Ltd",
    "wof:placetype":"venue"
},
  "geometry": {"coordinates":[151.13729900000001,-33.964245],"type":"Point"}
}