{
  "type": "Feature",
  "properties": {
    "addr:full":"Shop 2 Woodlands Plz Reedy Creek QLD 4228",
    "addr:housenumber":"shop 2",
    "addr:postcode":"4228",
    "addr:street":"Woodlands Plz",
    "iso:country":"AU",
    "sg:address":"Shop 2 Woodlands Plz",
    "sg:city":"Reedy Creek",
    "sg:classifiers":[
        {
            "category":"Personal",
            "subcategory":"Beauty Salon",
            "type":"Services"
        }
    ],
    "sg:phone":"+61 7 5522 0062",
    "sg:postcode":"4228",
    "sg:province":"QLD",
    "sg:tags":[
        "hairdresser"
    ],
    "wof:name":"Essential Looks Hair Studio",
    "wof:placetype":"venue"
},
  "geometry": {"coordinates":[153.403030395,-28.1017894745],"type":"Point"}
}