{
  "type": "Feature",
  "properties": {
    "iso:country":"AU",
    "sg:address":"PO Box 410",
    "sg:city":"Griffith",
    "sg:classifiers":[
        {
            "category":"Retail",
            "subcategory":"Event Space",
            "type":"Services"
        }
    ],
    "sg:phone":"+61 2 6962 1211",
    "sg:postcode":"2680",
    "sg:province":"NSW",
    "sg:tags":[
        "venue",
        "reception",
        "wedding"
    ],
    "wof:name":"Stephen Bortolin (Griffin Ex Servicemans Club)",
    "wof:placetype":"venue"
},
  "geometry": {"coordinates":[146.050323,-34.28944],"type":"Point"}
}