{
  "type": "Feature",
  "properties": {
    "addr:full":"629 Princes Hwy Blakehurst NSW 2221",
    "addr:housenumber":"629",
    "addr:postcode":"2221",
    "addr:street":"Princes Hwy",
    "iso:country":"AU",
    "sg:address":"629 Princes Hwy",
    "sg:city":"Blakehurst",
    "sg:classifiers":[
        {
            "category":"Train Station",
            "subcategory":"Rail",
            "type":"Transportation"
        }
    ],
    "sg:phone":"+61 2 9546 1324",
    "sg:postcode":"2221",
    "sg:province":"NSW",
    "sg:tags":[
        "ship",
        "chandler"
    ],
    "wof:name":"Hunt's Marine Pty Ltd",
    "wof:placetype":"venue"
},
  "geometry": {"coordinates":[151.11187744099999,-33.9885597229],"type":"Point"}
}