{
  "type": "Feature",
  "properties": {
    "addr:full":"15 Kendall St Granville NSW 2142",
    "addr:housenumber":"15",
    "addr:postcode":"2142",
    "addr:street":"Kendall St",
    "iso:country":"AU",
    "sg:address":"15 Kendall St",
    "sg:city":"Granville",
    "sg:classifiers":[
        {
            "category":"Retail",
            "subcategory":"Auto Rental",
            "type":"Services"
        }
    ],
    "sg:phone":"+61 1300 889 626",
    "sg:postcode":"2142",
    "sg:province":"NSW",
    "sg:tags":[
        "chauffeur",
        "car",
        "hire",
        "driven",
        "limousine"
    ],
    "sg:website":"http://www.impressivelimos.com.au",
    "wof:name":"Impressive Limousines",
    "wof:placetype":"venue"
},
  "geometry": {"coordinates":[151.02067565900001,-33.8327445984],"type":"Point"}
}