{
  "type": "Feature",
  "properties": {
    "addr:full":"84 Blackbutt St Wyoming NSW 2250",
    "addr:housenumber":"84",
    "addr:postcode":"2250",
    "addr:street":"Blackbutt St",
    "iso:country":"AU",
    "sg:address":"84 Blackbutt St",
    "sg:city":"Wyoming",
    "sg:classifiers":[
        {
            "category":"Professional",
            "subcategory":"Printing & Photocopies",
            "type":"Services"
        }
    ],
    "sg:phone":"+61 2 4325 4033",
    "sg:postcode":"2250",
    "sg:province":"NSW",
    "sg:tags":[
        "laminating"
    ],
    "wof:name":"Cut Price Laminating",
    "wof:placetype":"venue"
},
  "geometry": {"coordinates":[151.373504639,-33.4086761475],"type":"Point"}
}