{
  "type": "Feature",
  "properties": {
    "iso:country":"AU",
    "sg:address":"Shp 57-58 Runaway Bay Shopng Vlge, Lae Drv",
    "sg:city":"Runaway Bay",
    "sg:classifiers":[
        {
            "category":"Banks & Credit Unions",
            "subcategory":"Bank",
            "type":"Services"
        }
    ],
    "sg:phone":"+61 13 20 32",
    "sg:postcode":"4216",
    "sg:province":"QLD",
    "wof:name":"Westpac",
    "wof:placetype":"venue"
},
  "geometry": {"coordinates":[153.403930664,-27.9242191315],"type":"Point"}
}