{
  "type": "Feature",
  "properties": {
    "iso:country":"AU",
    "sg:address":"45 Farnell Ave",
    "sg:city":"Carlingford",
    "sg:classifiers":[
        {
            "category":"Home & Garden",
            "subcategory":"Building Materials",
            "type":"Retail Goods"
        }
    ],
    "sg:phone":"+61 2 9871 1914",
    "sg:postcode":"2118",
    "sg:province":"NSW",
    "sg:tags":[
        "lawn",
        "cutting",
        "maintenance"
    ],
    "wof:name":"Monk G J",
    "wof:placetype":"venue"
},
  "geometry": {"coordinates":[151.03788757300001,-33.7743682861],"type":"Point"}
}