{
  "type": "Feature",
  "properties": {
    "addr:full":"18 Ley St Como WA 6152",
    "addr:housenumber":"18",
    "addr:postcode":"6152",
    "addr:street":"Ley St",
    "iso:country":"AU",
    "sg:address":"18 Ley St",
    "sg:city":"Como",
    "sg:classifiers":[
        {
            "category":"Social Services",
            "subcategory":"Retirement Home",
            "type":"Services"
        }
    ],
    "sg:phone":"+61 8 9313 1700",
    "sg:postcode":"6152",
    "sg:province":"WA",
    "sg:tags":[
        "accommodation",
        "special"
    ],
    "wof:name":"McDougall Park Nursing Home",
    "wof:placetype":"venue"
},
  "geometry": {"coordinates":[115.864304,-32.008339],"type":"Point"}
}