{
  "type": "Feature",
  "properties": {
    "addr:full":"73 Polo Rd Rossmore NSW 2171",
    "addr:housenumber":"73",
    "addr:postcode":"2171",
    "addr:street":"Polo Rd",
    "iso:country":"AU",
    "sg:address":"73 Polo Rd",
    "sg:city":"Rossmore",
    "sg:classifiers":[
        {
            "category":"Farming",
            "subcategory":"Livestock Farm",
            "type":"Manufacturing & Wholesale Goods"
        }
    ],
    "sg:phone":"+61 2 9606 5002",
    "sg:postcode":"2171",
    "sg:province":"NSW",
    "sg:tags":[
        "breeder",
        "horse",
        "stud"
    ],
    "wof:name":"Warhorse Arabian Stud",
    "wof:placetype":"venue"
},
  "geometry": {"coordinates":[151.05445861800001,-33.92603302],"type":"Point"}
}