{
  "type": "Feature",
  "properties": {
    "addr:full":"81 Cambridge St Paddington NSW 2021",
    "addr:housenumber":"81",
    "addr:postcode":"2021",
    "addr:street":"Cambridge St",
    "iso:country":"AU",
    "sg:address":"81 Cambridge St",
    "sg:city":"Paddington",
    "sg:classifiers":[
        {
            "category":"Health Services",
            "subcategory":"Health Practitioner",
            "type":"Services"
        }
    ],
    "sg:phone":"+61 411 331 400",
    "sg:postcode":"2021",
    "sg:province":"NSW",
    "sg:tags":[
        "physiotherapist"
    ],
    "wof:name":"Koreman Catrina",
    "wof:placetype":"venue"
},
  "geometry": {"coordinates":[151.23078918499999,-33.8801307678],"type":"Point"}
}