{
  "type": "Feature",
  "properties": {
    "addr:full":"111 King George St Cohuna VIC 3568",
    "addr:housenumber":"111",
    "addr:postcode":"3568",
    "addr:street":"King George St",
    "iso:country":"AU",
    "sg:address":"111 King George St",
    "sg:city":"Cohuna",
    "sg:classifiers":[
        {
            "category":"Health Services",
            "subcategory":"Doctor",
            "type":"Services"
        }
    ],
    "sg:phone":"+61 3 5456 2609",
    "sg:postcode":"3568",
    "sg:province":"VIC",
    "sg:tags":[
        "medical",
        "practitioner"
    ],
    "wof:name":"Cohuna Clinic",
    "wof:placetype":"venue"
},
  "geometry": {"coordinates":[144.221099853,-35.8085784912],"type":"Point"}
}