{
  "type": "Feature",
  "properties": {
    "addr:full":"Level 9, 50 Cavill Ave Surfers Paradise QLD 4217",
    "addr:housenumber":"50",
    "addr:postcode":"4217",
    "addr:street":"Cavill Ave",
    "iso:country":"AU",
    "sg:address":"Level 9, 50 Cavill Ave",
    "sg:city":"Surfers Paradise",
    "sg:classifiers":[
        {
            "category":"Banks & Credit Unions",
            "subcategory":"Financial Services",
            "type":"Services"
        }
    ],
    "sg:phone":"+61 7 5561 0077",
    "sg:postcode":"4217",
    "sg:province":"QLD",
    "sg:tags":[
        "loan",
        "finance",
        "mortgage"
    ],
    "wof:name":"Balmain NB Commercial Mortgages Ltd",
    "wof:placetype":"venue"
},
  "geometry": {"coordinates":[153.42672729500001,-28.0016708374],"type":"Point"}
}