{
  "type": "Feature",
  "properties": {
    "iso:country":"AU",
    "sg:address":"13 Catalyst St",
    "sg:city":"Bohle",
    "sg:classifiers":[
        {
            "category":"Building & Trades",
            "subcategory":"Construction",
            "type":"Services"
        }
    ],
    "sg:phone":"+61 7 4774 4441",
    "sg:postcode":"4818",
    "sg:province":"QLD",
    "sg:tags":[
        "welding"
    ],
    "wof:name":"Weldsure",
    "wof:placetype":"venue"
},
  "geometry": {"coordinates":[146.74234000000001,-19.260426],"type":"Point"}
}