{
  "type": "Feature",
  "properties": {
    "iso:country":"AU",
    "sg:address":"80 High St",
    "sg:city":"Berwick",
    "sg:classifiers":[
        {
            "category":"Shopping",
            "subcategory":"Clothing, Apparel, & Fashions",
            "type":"Retail Goods"
        }
    ],
    "sg:phone":"+61 3 9769 9768",
    "sg:postcode":"3806",
    "sg:province":"VIC",
    "sg:tags":[
        "lady",
        "wear"
    ],
    "wof:name":"Country Lifestyle Co Pty Ltd",
    "wof:placetype":"venue"
},
  "geometry": {"coordinates":[145.345336914,-38.0314445496],"type":"Point"}
}