{
  "type": "Feature",
  "properties": {
    "iso:country":"AU",
    "sg:address":"41 Park St",
    "sg:city":"Hyde Park",
    "sg:classifiers":[
        {
            "category":"Professional",
            "subcategory":"Detective & Security Services",
            "type":"Services"
        }
    ],
    "sg:phone":"+61 8 8410 8600",
    "sg:postcode":"5061",
    "sg:province":"SA",
    "sg:tags":[
        "consultant",
        "system"
    ],
    "wof:name":"Fort Knox Security",
    "wof:placetype":"venue"
},
  "geometry": {"coordinates":[138.603713989,-34.9551963806],"type":"Point"}
}