{
  "type": "Feature",
  "properties": {
    "addr:full":"1 Chapel Hill Rd McLaren Vale SA 5171",
    "addr:housenumber":"1",
    "addr:postcode":"5171",
    "addr:street":"Chapel Hill Rd",
    "iso:country":"AU",
    "sg:address":"1 Chapel Hill Rd",
    "sg:city":"McLaren Vale",
    "sg:classifiers":[
        {
            "category":"Farming",
            "subcategory":"Vineyard",
            "type":"Manufacturing & Wholesale Goods"
        }
    ],
    "sg:phone":"+61 8 8323 8429",
    "sg:postcode":"5171",
    "sg:province":"SA",
    "sg:tags":[
        "winery"
    ],
    "wof:name":"Chapel Hill Winery Pty Ltd",
    "wof:placetype":"venue"
},
  "geometry": {"coordinates":[138.56448364299999,-35.1675224304],"type":"Point"}
}