{
  "type": "Feature",
  "properties": {
    "addr:full":"25/ 23a Billyard Ave Elizabeth Bay NSW 2011",
    "addr:housenumber":"25 / 23a",
    "addr:postcode":"2011",
    "addr:street":"Billyard Ave",
    "iso:country":"AU",
    "sg:address":"25/ 23a Billyard Ave",
    "sg:city":"Elizabeth Bay",
    "sg:classifiers":[
        {
            "category":"Professional",
            "subcategory":"Business Services",
            "type":"Services"
        }
    ],
    "sg:phone":"+61 2 9326 9407",
    "sg:postcode":"2011",
    "sg:province":"NSW",
    "sg:tags":[
        "management",
        "event"
    ],
    "wof:name":"Helena Karter Special Events Pty Ltd",
    "wof:placetype":"venue"
},
  "geometry": {"coordinates":[151.226654053,-33.8695487976],"type":"Point"}
}