{
  "type": "Feature",
  "properties": {
    "addr:full":"7- 15 Forest Street Colac VIC 3250",
    "addr:housenumber":"15",
    "addr:postcode":"3250",
    "addr:street":"7;Forest Street",
    "iso:country":"AU",
    "sg:address":"7- 15 Forest Street",
    "sg:city":"Colac",
    "sg:classifiers":[
        {
            "category":"Health Services",
            "subcategory":"Nursing And Care Facility",
            "type":"Services"
        }
    ],
    "sg:phone":"+61 3 5231 9100",
    "sg:postcode":"3250",
    "sg:province":"VIC",
    "sg:tags":[
        "treatment",
        "preservation",
        "timber"
    ],
    "wof:name":"AKD Softwoods",
    "wof:placetype":"venue"
},
  "geometry": {"coordinates":[143.60597200000001,-38.337994],"type":"Point"}
}