{
  "type": "Feature",
  "properties": {
    "addr:full":"18 Hilltop Ave Mt Pritchard NSW 2170",
    "addr:housenumber":"18",
    "addr:postcode":"2170",
    "addr:street":"Hilltop Ave;Pritchard",
    "iso:country":"AU",
    "sg:address":"18 Hilltop Ave",
    "sg:city":"Mt Pritchard",
    "sg:classifiers":[
        {
            "category":"Building & Trades",
            "subcategory":"Construction",
            "type":"Services"
        }
    ],
    "sg:phone":"+61 2 9601 1201",
    "sg:postcode":"2170",
    "sg:province":"NSW",
    "sg:tags":[
        "joiner",
        "carpenter"
    ],
    "wof:name":"Campbell D",
    "wof:placetype":"venue"
},
  "geometry": {"coordinates":[150.90156555199999,-33.9072036743],"type":"Point"}
}