{
  "type": "Feature",
  "properties": {
    "iso:country":"AU",
    "sg:address":"29 Futura Rd",
    "sg:city":"Keysborough",
    "sg:classifiers":[
        {
            "category":"Manufacturing",
            "subcategory":"Paper Products",
            "type":"Manufacturing & Wholesale Goods"
        }
    ],
    "sg:phone":"+61 3 9798 8828",
    "sg:postcode":"3173",
    "sg:province":"VIC",
    "sg:tags":[
        "container",
        "plastic"
    ],
    "wof:name":"Sunrise Containers Victoria Pty Ltd",
    "wof:placetype":"venue"
},
  "geometry": {"coordinates":[145.18942260700001,-37.9853401184],"type":"Point"}
}