{
  "type": "Feature",
  "properties": {
    "addr:full":"PO Box 22 Euroa VIC 3666",
    "addr:postcode":"3666",
    "iso:country":"AU",
    "sg:address":"PO Box 22",
    "sg:city":"Euroa",
    "sg:classifiers":[
        {
            "category":"Health Services",
            "subcategory":"Doctor",
            "type":"Services"
        }
    ],
    "sg:phone":"+61 409 178 561",
    "sg:postcode":"3666",
    "sg:province":"VIC",
    "sg:tags":[
        "occupational",
        "safety"
    ],
    "wof:name":"Bruken, Mark",
    "wof:placetype":"venue"
},
  "geometry": {"coordinates":[145.58433532699999,-36.7453804016],"type":"Point"}
}