{
  "type": "Feature",
  "properties": {
    "iso:country":"AU",
    "sg:address":"472 Burwood Rd",
    "sg:city":"Belmore",
    "sg:classifiers":[
        {
            "category":"Recreation",
            "subcategory":"Fishing",
            "type":"Entertainment"
        }
    ],
    "sg:phone":"+61 2 9740 5501",
    "sg:postcode":"2192",
    "sg:province":"NSW",
    "sg:tags":[
        "tackle"
    ],
    "wof:name":"Belmore Fishing Tackle",
    "wof:placetype":"venue"
},
  "geometry": {"coordinates":[151.089859,-33.921494],"type":"Point"}
}