{
  "type": "Feature",
  "properties": {
    "addr:full":"245 Badgery's Lookout Rd Tallong NSW 2579",
    "addr:housenumber":"245",
    "addr:postcode":"2579",
    "addr:street":"Badgery'S Lookout Rd",
    "iso:country":"AU",
    "sg:address":"245 Badgery's Lookout Rd",
    "sg:city":"Tallong",
    "sg:classifiers":[
        {
            "category":"Commercial Area",
            "type":"Public Place"
        }
    ],
    "sg:phone":"+61 429 077 946",
    "sg:postcode":"2579",
    "sg:province":"NSW",
    "sg:tags":[
        "heavy",
        "carrier"
    ],
    "wof:name":"Marulan Rural Services Pty Ltd",
    "wof:placetype":"venue"
},
  "geometry": {"coordinates":[150.08631897000001,-34.7187004089],"type":"Point"}
}