{
  "type": "Feature",
  "properties": {
    "iso:country":"AU",
    "sg:address":"310a Bay Rd",
    "sg:city":"Cheltenham",
    "sg:classifiers":[
        {
            "category":"Wholesale",
            "subcategory":"Non-durable Goods",
            "type":"Manufacturing & Wholesale Goods"
        }
    ],
    "sg:phone":"+61 3 9584 8061",
    "sg:postcode":"3192",
    "sg:province":"VIC",
    "sg:tags":[
        "textile"
    ],
    "wof:name":"Homeport Pty Ltd",
    "wof:placetype":"venue"
},
  "geometry": {"coordinates":[145.039749145,-37.9560966492],"type":"Point"}
}