{
  "type": "Feature",
  "properties": {
    "addr:full":"Level 1, 64 Ferny Ave Surfers Paradise QLD 4217",
    "addr:housenumber":"64",
    "addr:postcode":"4217",
    "addr:street":"Ferny Ave",
    "iso:country":"AU",
    "sg:address":"Level 1, 64 Ferny Ave",
    "sg:city":"Surfers Paradise",
    "sg:classifiers":[
        {
            "category":"Social Services",
            "subcategory":"Retirement Home",
            "type":"Services"
        }
    ],
    "sg:phone":"+61 7 5592 0057",
    "sg:postcode":"4217",
    "sg:province":"QLD",
    "sg:tags":[
        "environmental",
        "consultant",
        "pollution"
    ],
    "wof:name":"Byrns Lardner Environmental",
    "wof:placetype":"venue"
},
  "geometry": {"coordinates":[153.42718505900001,-27.9975376129],"type":"Point"}
}