{
  "type": "Feature",
  "properties": {
    "iso:country":"AU",
    "sg:address":"Shop 64 West Lakes Mall",
    "sg:city":"West Lakes",
    "sg:classifiers":[
        {
            "category":"Cafe",
            "type":"Food & Drink"
        }
    ],
    "sg:phone":"+61 8 8356 1547",
    "sg:postcode":"5021",
    "sg:province":"SA",
    "wof:name":"The Lakes Cafe",
    "wof:placetype":"venue"
},
  "geometry": {"coordinates":[138.488372803,-34.8727149963],"type":"Point"}
}