{
  "type": "Feature",
  "properties": {
    "iso:country":"AU",
    "sg:address":"4 Burnell Pl",
    "sg:city":"Monash",
    "sg:classifiers":[
        {
            "category":"Building & Trades",
            "subcategory":"Construction",
            "type":"Services"
        }
    ],
    "sg:phone":"+61 409 917 898",
    "sg:postcode":"2904",
    "sg:province":"ACT",
    "sg:tags":[
        "repair",
        "maintenance",
        "contractor"
    ],
    "wof:name":"Tom McAppion Building Services",
    "wof:placetype":"venue"
},
  "geometry": {"coordinates":[149.08746337900001,-35.4116592407],"type":"Point"}
}