{
  "type": "Feature",
  "properties": {
    "addr:full":"815 Riversdale Rd Camberwell VIC 3124",
    "addr:housenumber":"815",
    "addr:postcode":"3124",
    "addr:street":"Riversdale Rd",
    "iso:country":"AU",
    "sg:address":"815 Riversdale Rd",
    "sg:city":"Camberwell",
    "sg:classifiers":[
        {
            "category":"Education",
            "subcategory":"School",
            "type":"Public Place"
        }
    ],
    "sg:phone":"+61 3 9835 0200",
    "sg:postcode":"3124",
    "sg:province":"VIC",
    "sg:tags":[
        "girl"
    ],
    "wof:name":"Siena College",
    "wof:placetype":"venue"
},
  "geometry": {"coordinates":[145.08207702600001,-37.8340606689],"type":"Point"}
}