{
  "type": "Feature",
  "properties": {
    "iso:country":"AU",
    "sg:address":"113 Manning Rd",
    "sg:city":"Bentley",
    "sg:classifiers":[
        {
            "category":"Communications",
            "subcategory":"Film & Video Production",
            "type":"Services"
        }
    ],
    "sg:phone":"+61 8 9458 8081",
    "sg:postcode":"6102",
    "sg:province":"WA",
    "sg:tags":[
        "dvd",
        "library"
    ],
    "wof:name":"Network Video",
    "wof:placetype":"venue"
},
  "geometry": {"coordinates":[115.911987305,-32.0124282837],"type":"Point"}
}