{
  "type": "Feature",
  "properties": {
    "addr:full":"174 Ham Rd Mansfield QLD 4122",
    "addr:housenumber":"174",
    "addr:postcode":"4122",
    "addr:street":"Ham Rd",
    "iso:country":"AU",
    "sg:address":"174 Ham Rd",
    "sg:city":"Mansfield",
    "sg:classifiers":[
        {
            "category":"Education",
            "subcategory":"School",
            "type":"Public Place"
        }
    ],
    "sg:phone":"+61 7 3421 3837",
    "sg:postcode":"4122",
    "sg:province":"QLD",
    "sg:tags":[
        "state",
        "except",
        "nsw"
    ],
    "wof:name":"Mansfield Preschool",
    "wof:placetype":"venue"
},
  "geometry": {"coordinates":[153.10455322300001,-27.5452365875],"type":"Point"}
}