{
  "type": "Feature",
  "properties": {
    "addr:full":"1 Birch Rd Wyoming NSW 2250",
    "addr:housenumber":"1",
    "addr:postcode":"2250",
    "addr:street":"Birch Rd",
    "iso:country":"AU",
    "sg:address":"1 Birch Rd",
    "sg:city":"Wyoming",
    "sg:classifiers":[
        {
            "category":"Health Services",
            "subcategory":"Nursing And Care Facility",
            "type":"Services"
        }
    ],
    "sg:phone":"+61 2 4324 4139",
    "sg:postcode":"2250",
    "sg:province":"NSW",
    "sg:tags":[
        "home"
    ],
    "wof:name":"Adelene Nursing Home",
    "wof:placetype":"venue"
},
  "geometry": {"coordinates":[151.363815308,-33.4097671509],"type":"Point"}
}