{
  "type": "Feature",
  "properties": {
    "addr:full":"78 Wickham St Fortitude Valley Fortitude Valley QLD 4006",
    "addr:housenumber":"78",
    "addr:postcode":"4006",
    "addr:street":"Wickham St",
    "iso:country":"AU",
    "sg:address":"78 Wickham St",
    "sg:city":"Fortitude Valley Fortitude Valley",
    "sg:classifiers":[
        {
            "category":"Personal",
            "subcategory":"Beauty Salon",
            "type":"Services"
        }
    ],
    "sg:phone":"+61 7 3839 7577",
    "sg:postcode":"4006",
    "sg:province":"QLD",
    "sg:tags":[
        "hairdresser"
    ],
    "wof:name":"Odyssey Hair",
    "wof:placetype":"venue"
},
  "geometry": {"coordinates":[153.031448364,-27.4607696533],"type":"Point"}
}