{
  "type": "Feature",
  "properties": {
    "addr:full":"1 Castle St Edwardstown SA 5039",
    "addr:housenumber":"1",
    "addr:postcode":"5039",
    "addr:street":"Castle St",
    "iso:country":"AU",
    "sg:address":"1 Castle St",
    "sg:city":"Edwardstown",
    "sg:classifiers":[
        {
            "category":"Education",
            "subcategory":"School",
            "type":"Public Place"
        }
    ],
    "sg:phone":"+61 8 8293 2532",
    "sg:postcode":"5039",
    "sg:province":"SA",
    "sg:tags":[
        "co-educational"
    ],
    "wof:name":"St Anthony's School",
    "wof:placetype":"venue"
},
  "geometry": {"coordinates":[138.572753906,-34.969909668],"type":"Point"}
}