{
  "type": "Feature",
  "properties": {
    "iso:country":"AU",
    "sg:address":"56- 62 Radley St",
    "sg:city":"Virginia",
    "sg:classifiers":[
        {
            "category":"Transit Center",
            "subcategory":"Passenger",
            "type":"Transportation"
        }
    ],
    "sg:phone":"+61 7 3865 2393",
    "sg:postcode":"4014",
    "sg:province":"QLD",
    "sg:tags":[
        "wood",
        "moulding",
        "plastic"
    ],
    "wof:name":"VSH Timbers",
    "wof:placetype":"venue"
},
  "geometry": {"coordinates":[153.064743042,-27.3662700653],"type":"Point"}
}