{
  "type": "Feature",
  "properties": {
    "iso:country":"AU",
    "sg:address":"2 Russell Avenue",
    "sg:city":"Frenchs Forest",
    "sg:classifiers":[
        {
            "category":"Real Estate",
            "subcategory":"Real Estate Agent",
            "type":"Services"
        }
    ],
    "sg:phone":"+61 2 9451 5900",
    "sg:postcode":"2086",
    "sg:province":"NSW",
    "wof:name":"Smart & McKenzie First National",
    "wof:placetype":"venue"
},
  "geometry": {"coordinates":[151.22332763700001,-33.7491455078],"type":"Point"}
}