{
  "type": "Feature",
  "properties": {
    "iso:country":"AU",
    "sg:address":"57 Phillip Drv",
    "sg:city":"Sunbury",
    "sg:classifiers":[
        {
            "category":"Food & Beverages",
            "subcategory":"Groceries & Convenience Stores",
            "type":"Retail Goods"
        }
    ],
    "sg:phone":"+61 3 9740 8810",
    "sg:postcode":"3429",
    "sg:province":"VIC",
    "wof:name":"Killara Family Store",
    "wof:placetype":"venue"
},
  "geometry": {"coordinates":[144.705535889,-37.5635185242],"type":"Point"}
}