{
  "type": "Feature",
  "properties": {
    "addr:full":"Cnr Brisbane & Benson Sts St Lucia QLD 4067",
    "addr:postcode":"4067",
    "addr:street":"Cnr;Sts",
    "iso:country":"AU",
    "sg:address":"Cnr Brisbane & Benson Sts St",
    "sg:city":"Lucia",
    "sg:classifiers":[
        {
            "category":"Autos & Motor Vehicles",
            "subcategory":"Fuel & Gas Station",
            "type":"Retail Goods"
        }
    ],
    "sg:phone":"+61 7 3870 3805",
    "sg:postcode":"4067",
    "sg:province":"QLD",
    "wof:name":"BP",
    "wof:placetype":"venue"
},
  "geometry": {"coordinates":[153.001663208,-27.4951839447],"type":"Point"}
}