{
  "type": "Feature",
  "properties": {
    "iso:country":"AU",
    "sg:address":"Shop 17 Mt Gravatt Plaza Cnr Logan & Creek Rds",
    "sg:city":"Mt Gravatt",
    "sg:classifiers":[
        {
            "category":"Food & Beverages",
            "subcategory":"Liquor & Beverages",
            "type":"Retail Goods"
        }
    ],
    "sg:phone":"+61 7 3349 0179",
    "sg:postcode":"4122",
    "sg:province":"QLD",
    "sg:tags":[
        "store"
    ],
    "wof:name":"BWS Liquor Stores",
    "wof:placetype":"venue"
},
  "geometry": {"coordinates":[153.078781128,-27.5487670898],"type":"Point"}
}