{
  "type": "Feature",
  "properties": {
    "addr:full":"12 Vine La Glen Osmond SA 5064",
    "addr:housenumber":"12",
    "addr:postcode":"5064",
    "addr:street":"Vine La",
    "iso:country":"AU",
    "sg:address":"12 Vine La",
    "sg:city":"Glen Osmond",
    "sg:classifiers":[
        {
            "category":"Real Estate",
            "subcategory":"Real Estate Agent",
            "type":"Services"
        }
    ],
    "sg:phone":"+61 8 8272 4327",
    "sg:postcode":"5064",
    "sg:province":"SA",
    "wof:name":"East-West Realty Pty Ltd",
    "wof:placetype":"venue"
},
  "geometry": {"coordinates":[138.64231872600001,-34.9597244263],"type":"Point"}
}