{
  "type": "Feature",
  "properties": {
    "addr:full":"15A Arnott Crt Kelmscott WA 6111",
    "addr:housenumber":"15a",
    "addr:postcode":"6111",
    "addr:street":"Arnott Crt",
    "iso:country":"AU",
    "sg:address":"15A Arnott Crt",
    "sg:city":"Kelmscott",
    "sg:classifiers":[
        {
            "category":"Retail",
            "subcategory":"Driving School",
            "type":"Services"
        }
    ],
    "sg:phone":"+61 8 9390 1995",
    "sg:postcode":"6111",
    "sg:province":"WA",
    "wof:name":"Signals Driving School",
    "wof:placetype":"venue"
},
  "geometry": {"coordinates":[116.015830994,-32.1232757568],"type":"Point"}
}