{
  "type": "Feature",
  "properties": {
    "iso:country":"AU",
    "sg:address":"440 High St",
    "sg:city":"Prahran",
    "sg:classifiers":[
        {
            "category":"Shopping",
            "subcategory":"Antiques",
            "type":"Retail Goods"
        }
    ],
    "sg:phone":"+61 3 9510 5833",
    "sg:postcode":"3181",
    "sg:province":"VIC",
    "wof:name":"French Style Pty Ltd",
    "wof:placetype":"venue"
},
  "geometry": {"coordinates":[145.003173828,-37.8532905579],"type":"Point"}
}