{
  "type": "Feature",
  "properties": {
    "addr:full":"24-26 Crown Ave Mordialloc VIC 3195",
    "addr:housenumber":"24-26",
    "addr:postcode":"3195",
    "addr:street":"Crown Ave",
    "iso:country":"AU",
    "sg:address":"24-26 Crown Ave",
    "sg:city":"Mordialloc",
    "sg:classifiers":[
        {
            "category":"Wholesale",
            "subcategory":"Furniture",
            "type":"Manufacturing & Wholesale Goods"
        }
    ],
    "sg:phone":"+61 3 9580 2900",
    "sg:postcode":"3195",
    "sg:province":"VIC",
    "sg:tags":[
        "wholesaler",
        "mfrs"
    ],
    "wof:name":"Perspective Review Australia Pty Ltd",
    "wof:placetype":"venue"
},
  "geometry": {"coordinates":[145.095626831,-38.0067749023],"type":"Point"}
}