{
  "type": "Feature",
  "properties": {
    "iso:country":"AU",
    "sg:address":"10/ 99 Stanley St",
    "sg:city":"East Sydney",
    "sg:classifiers":[
        {
            "category":"Arts & Performance",
            "subcategory":"Art Gallery",
            "type":"Entertainment"
        }
    ],
    "sg:phone":"+61 2 9360 5588",
    "sg:postcode":"2010",
    "sg:province":"NSW",
    "wof:name":"Robert McGarth Photographic Exhibitors",
    "wof:placetype":"venue"
},
  "geometry": {"coordinates":[151.21653747600001,-33.876083374],"type":"Point"}
}