{
  "type": "Feature",
  "properties": {
    "addr:full":"413 Yaamba Rd North Rockhampton QLD 4701",
    "addr:housenumber":"413",
    "addr:postcode":"4701",
    "addr:street":"Yaamba Rd North",
    "iso:country":"AU",
    "sg:address":"413 Yaamba Rd",
    "sg:city":"North Rockhampton",
    "sg:classifiers":[
        {
            "category":"Utilities",
            "subcategory":"Natural Gas",
            "type":"Services"
        }
    ],
    "sg:phone":"+61 7 4926 5370",
    "sg:postcode":"4701",
    "sg:province":"QLD",
    "sg:tags":[
        "supplier"
    ],
    "wof:name":"Elgas Ltd",
    "wof:placetype":"venue"
},
  "geometry": {"coordinates":[150.52081298799999,-23.3440608978],"type":"Point"}
}