{
  "type": "Feature",
  "properties": {
    "iso:country":"AU",
    "sg:address":"Suite 3/ 304 Timor St",
    "sg:city":"Warrnambool",
    "sg:classifiers":[
        {
            "category":"Health Services",
            "subcategory":"Dentist",
            "type":"Services"
        }
    ],
    "sg:phone":"+61 3 5562 6266",
    "sg:postcode":"3280",
    "sg:province":"VIC",
    "wof:name":"Sanderson R J Dr",
    "wof:placetype":"venue"
},
  "geometry": {"coordinates":[142.47425842300001,-38.3816299438],"type":"Point"}
}