{
  "type": "Feature",
  "properties": {
    "addr:full":"55 Cowie St Carseldine QLD 4034",
    "addr:housenumber":"55",
    "addr:postcode":"4034",
    "addr:street":"Cowie St",
    "iso:country":"AU",
    "sg:address":"55 Cowie St",
    "sg:city":"Carseldine",
    "sg:classifiers":[
        {
            "category":"Building & Trades",
            "subcategory":"Construction",
            "type":"Services"
        }
    ],
    "sg:phone":"+61 7 3263 2503",
    "sg:postcode":"4034",
    "sg:province":"QLD",
    "sg:tags":[
        "contractor"
    ],
    "wof:name":"Pixdale",
    "wof:placetype":"venue"
},
  "geometry": {"coordinates":[153.01899700000001,-27.342863],"type":"Point"}
}