{
  "type": "Feature",
  "properties": {
    "addr:full":"Le Galliene Crs Mulgrave VIC 3170",
    "addr:postcode":"3170",
    "addr:street":"Crs",
    "iso:country":"AU",
    "sg:address":"Le Galliene Crs",
    "sg:city":"Mulgrave",
    "sg:classifiers":[
        {
            "category":"Retail",
            "subcategory":"Driving School",
            "type":"Services"
        }
    ],
    "sg:phone":"+61 3 9560 7640",
    "sg:postcode":"3170",
    "sg:province":"VIC",
    "wof:name":"Montgomery K D",
    "wof:placetype":"venue"
},
  "geometry": {"coordinates":[145.165252686,-37.9214286804],"type":"Point"}
}