{
  "type": "Feature",
  "properties": {
    "iso:country":"AU",
    "sg:address":"Tirroan Rd",
    "sg:city":"Tirroan",
    "sg:classifiers":[
        {
            "category":"Travel",
            "subcategory":"Hotels & Motels",
            "type":"Entertainment"
        }
    ],
    "sg:phone":"+61 7 4157 2317",
    "sg:postcode":"4671",
    "sg:province":"QLD",
    "sg:tags":[
        "accommodation"
    ],
    "wof:name":"Tirroan Hotel",
    "wof:placetype":"venue"
},
  "geometry": {"coordinates":[151.92716999999999,-25.002028],"type":"Point"}
}