{
  "type": "Feature",
  "properties": {
    "addr:full":"1467 Dooralong Rd Dooralong NSW 2259",
    "addr:housenumber":"1467",
    "addr:postcode":"2259",
    "addr:street":"Dooralong Rd",
    "iso:country":"AU",
    "sg:address":"1467 Dooralong Rd",
    "sg:city":"Dooralong",
    "sg:classifiers":[
        {
            "category":"Travel",
            "subcategory":"Hotels & Motels",
            "type":"Entertainment"
        }
    ],
    "sg:phone":"+61 2 4351 2611",
    "sg:postcode":"2259",
    "sg:province":"NSW",
    "wof:name":"Jillibys Restaurant",
    "wof:placetype":"venue"
},
  "geometry": {"coordinates":[151.371948242,-33.1785697937],"type":"Point"}
}