{
  "type": "Feature",
  "properties": {
    "addr:full":"57 Fulcrum St Richlands QLD 4077",
    "addr:housenumber":"57",
    "addr:postcode":"4077",
    "addr:street":"Fulcrum St",
    "iso:country":"AU",
    "sg:address":"57 Fulcrum St",
    "sg:city":"Richlands",
    "sg:classifiers":[
        {
            "category":"Transit Center",
            "subcategory":"Freight",
            "type":"Transportation"
        }
    ],
    "sg:phone":"+61 7 3217 0099",
    "sg:postcode":"4077",
    "sg:province":"QLD",
    "sg:tags":[
        "forklift",
        "truck"
    ],
    "wof:name":"Princetown Yale",
    "wof:placetype":"venue"
},
  "geometry": {"coordinates":[152.946136475,-27.5878372192],"type":"Point"}
}