{
  "type": "Feature",
  "properties": {
    "addr:full":"Reedy Lakes Crt Leopold VIC 3224",
    "addr:postcode":"3224",
    "iso:country":"AU",
    "sg:address":"Reedy Lakes Crt",
    "sg:city":"Leopold",
    "sg:classifiers":[
        {
            "category":"Building & Trades",
            "subcategory":"Cleaning & Sanitation",
            "type":"Services"
        }
    ],
    "sg:phone":"+61 3 5250 3368",
    "sg:postcode":"3224",
    "sg:province":"VIC",
    "sg:tags":[
        "industrial",
        "commercial",
        "contractor"
    ],
    "wof:name":"Hamilton Hill Cleaning Service",
    "wof:placetype":"venue"
},
  "geometry": {"coordinates":[144.45529199999999,-38.196251],"type":"Point"}
}