{
  "type": "Feature",
  "properties": {
    "addr:full":"1599 Dandenong Rd Oakleigh VIC 3166",
    "addr:housenumber":"1599",
    "addr:postcode":"3166",
    "addr:street":"Dandenong Rd",
    "iso:country":"AU",
    "sg:address":"1599 Dandenong Rd",
    "sg:city":"Oakleigh",
    "sg:classifiers":[
        {
            "category":"Building & Trades",
            "subcategory":"Construction",
            "type":"Services"
        }
    ],
    "sg:phone":"+61 13 84 68",
    "sg:postcode":"3166",
    "sg:province":"VIC",
    "sg:tags":[
        "window",
        "tinting"
    ],
    "wof:name":"Tint.A.Car",
    "wof:placetype":"venue"
},
  "geometry": {"coordinates":[145.09640502900001,-37.8948478699],"type":"Point"}
}