{
  "type": "Feature",
  "properties": {
    "addr:full":"173 Creek St South Bendigo VIC 3550",
    "addr:housenumber":"173",
    "addr:postcode":"3550",
    "addr:street":"Creek St South",
    "iso:country":"AU",
    "sg:address":"173 Creek St South",
    "sg:city":"Bendigo",
    "sg:classifiers":[
        {
            "category":"Health Services",
            "subcategory":"Doctor",
            "type":"Services"
        }
    ],
    "sg:phone":"+61 3 5442 5642",
    "sg:postcode":"3550",
    "sg:province":"VIC",
    "sg:tags":[
        "medical",
        "practitioner"
    ],
    "wof:name":"Creek St Medical Practice",
    "wof:placetype":"venue"
},
  "geometry": {"coordinates":[144.26754760700001,-36.7684593201],"type":"Point"}
}