{
  "type": "Feature",
  "properties": {
    "iso:country":"AU",
    "sg:address":"Unit 5/ 1 Mulwarree Ave",
    "sg:city":"Randwick",
    "sg:classifiers":[
        {
            "category":"Building & Trades",
            "subcategory":"Cleaning & Sanitation",
            "type":"Services"
        }
    ],
    "sg:phone":"+61 412 204 595",
    "sg:postcode":"2031",
    "sg:province":"NSW",
    "sg:tags":[
        "industrial",
        "commercial",
        "contractor"
    ],
    "wof:name":"Property Care Resources Pty Ltd",
    "wof:placetype":"venue"
},
  "geometry": {"coordinates":[151.23594665499999,-33.9070472717],"type":"Point"}
}