{
  "type": "Feature",
  "properties": {
    "iso:country":"AU",
    "sg:address":"83 Eastfield Rd",
    "sg:city":"Croydon South",
    "sg:classifiers":[
        {
            "category":"Education",
            "subcategory":"Kindergarten",
            "type":"Public Place"
        }
    ],
    "sg:phone":"+61 3 9723 2816",
    "sg:postcode":"3136",
    "sg:province":"VIC",
    "sg:tags":[
        "pre-schools"
    ],
    "wof:name":"Pinjarra Kindergarten Inc.",
    "wof:placetype":"venue"
},
  "geometry": {"coordinates":[145.27107238799999,-37.8108329773],"type":"Point"}
}