{
  "type": "Feature",
  "properties": {
    "iso:country":"AU",
    "sg:address":"760 Logan Reserve Rd",
    "sg:city":"Logan Reserve",
    "sg:classifiers":[
        {
            "category":"Retail",
            "subcategory":"Auto Repair",
            "type":"Services"
        }
    ],
    "sg:phone":"+61 7 5546 3673",
    "sg:postcode":"4133",
    "sg:province":"QLD",
    "sg:tags":[
        "repairer",
        "motor",
        "engineer"
    ],
    "wof:name":"Logan Meadows Mechanical",
    "wof:placetype":"venue"
},
  "geometry": {"coordinates":[153.08950805699999,-27.7344322205],"type":"Point"}
}