{
  "type": "Feature",
  "properties": {
    "addr:full":"McCabe Rd Jambin QLD 4702",
    "addr:postcode":"4702",
    "addr:street":"Mccabe Rd",
    "iso:country":"AU",
    "sg:address":"McCabe Rd",
    "sg:city":"Jambin",
    "sg:classifiers":[
        {
            "category":"Farming",
            "subcategory":"Farm",
            "type":"Manufacturing & Wholesale Goods"
        }
    ],
    "sg:phone":"+61 7 4996 5216",
    "sg:postcode":"4702",
    "sg:province":"QLD",
    "sg:tags":[
        "farmer"
    ],
    "wof:name":"Jordison G R & C D",
    "wof:placetype":"venue"
},
  "geometry": {"coordinates":[151.24261474599999,-23.8440971375],"type":"Point"}
}