{
  "type": "Feature",
  "properties": {
    "iso:country":"AU",
    "sg:address":"1110 Rockingham Rd",
    "sg:city":"Hope Valley",
    "sg:classifiers":[
        {
            "category":"Wholesale",
            "subcategory":"Plants",
            "type":"Manufacturing & Wholesale Goods"
        }
    ],
    "sg:phone":"+61 8 9410 0018",
    "sg:postcode":"6165",
    "sg:province":"WA",
    "sg:tags":[
        "florist"
    ],
    "wof:name":"Flowerland",
    "wof:placetype":"venue"
},
  "geometry": {"coordinates":[115.788307,-32.187237],"type":"Point"}
}