{
  "type": "Feature",
  "properties": {
    "iso:country":"AU",
    "sg:address":"118 Balcombe Rd",
    "sg:city":"Mentone",
    "sg:classifiers":[
        {
            "category":"Health Services",
            "subcategory":"Health Practitioner",
            "type":"Services"
        }
    ],
    "sg:phone":"+61 3 9585 1881",
    "sg:postcode":"3194",
    "sg:province":"VIC",
    "sg:tags":[
        "psychologist"
    ],
    "wof:name":"Jillian Cowan-Monica O'Kelly Collard",
    "wof:placetype":"venue"
},
  "geometry": {"coordinates":[145.064056397,-37.9810333252],"type":"Point"}
}