{
  "type": "Feature",
  "properties": {
    "iso:country":"AU",
    "sg:address":"10 Wright St",
    "sg:city":"Busselton",
    "sg:classifiers":[
        {
            "category":"Building & Trades",
            "subcategory":"Construction",
            "type":"Services"
        }
    ],
    "sg:phone":"+61 8 9752 3733",
    "sg:postcode":"6280",
    "sg:province":"WA",
    "sg:tags":[
        "contractor"
    ],
    "wof:name":"Building South West",
    "wof:placetype":"venue"
},
  "geometry": {"coordinates":[115.347488403,-33.664730072],"type":"Point"}
}