{
  "type": "Feature",
  "properties": {
    "addr:full":"11/ 40 Brookes St Bowen Hills QLD 4006",
    "addr:housenumber":"11 / 40",
    "addr:postcode":"4006",
    "addr:street":"Brookes St",
    "iso:country":"AU",
    "sg:address":"11/ 40 Brookes St",
    "sg:city":"Bowen Hills",
    "sg:classifiers":[
        {
            "category":"Organizations",
            "subcategory":"Labor Organization",
            "type":"Services"
        }
    ],
    "sg:phone":"+61 7 3852 5177",
    "sg:postcode":"4006",
    "sg:province":"QLD",
    "sg:tags":[
        "union"
    ],
    "wof:name":"Childrens Services Employers Association of Queensland",
    "wof:placetype":"venue"
},
  "geometry": {"coordinates":[153.035690308,-27.4507427216],"type":"Point"}
}