{
  "type": "Feature",
  "properties": {
    "iso:country":"AU",
    "sg:address":"340 Findon Rd",
    "sg:city":"Kidman Park",
    "sg:classifiers":[
        {
            "category":"Professional",
            "subcategory":"Computer Services",
            "type":"Services"
        }
    ],
    "sg:phone":"+61 8 8205 3111",
    "sg:postcode":"5025",
    "sg:province":"SA",
    "sg:tags":[
        "consultant",
        "system"
    ],
    "wof:name":"Classic Blue Solutions",
    "wof:placetype":"venue"
},
  "geometry": {"coordinates":[138.53309631400001,-34.9088783264],"type":"Point"}
}