{
  "type": "Feature",
  "properties": {
    "addr:full":"3 Thirlmere Crt Lakelands NSW 2282",
    "addr:housenumber":"3",
    "addr:postcode":"2282",
    "addr:street":"Thirlmere Crt",
    "iso:country":"AU",
    "sg:address":"3 Thirlmere Crt",
    "sg:city":"Lakelands",
    "sg:classifiers":[
        {
            "category":"Health Services",
            "subcategory":"Health Practitioner",
            "type":"Services"
        }
    ],
    "sg:phone":"+61 2 4953 6811",
    "sg:postcode":"2282",
    "sg:province":"NSW",
    "sg:tags":[
        "acupuncture"
    ],
    "wof:name":"O&#039;Connor, Stephen",
    "wof:placetype":"venue"
},
  "geometry": {"coordinates":[151.64689636200001,-32.9619522095],"type":"Point"}
}