{
  "type": "Feature",
  "properties": {
    "addr:full":"61 Brisbane St Launceston TAS 7250",
    "addr:housenumber":"61",
    "addr:postcode":"7250",
    "addr:street":"Brisbane St",
    "iso:country":"AU",
    "sg:address":"61 Brisbane St",
    "sg:city":"Launceston",
    "sg:classifiers":[
        {
            "category":"Health Services",
            "subcategory":"Optometrist",
            "type":"Services"
        }
    ],
    "sg:phone":"+61 3 6331 7153",
    "sg:postcode":"7250",
    "sg:province":"TAS",
    "wof:name":"Petchkov Alex",
    "wof:placetype":"venue"
},
  "geometry": {"coordinates":[147.14097595199999,-41.436214447],"type":"Point"}
}