{
  "type": "Feature",
  "properties": {
    "addr:full":"8/ 18 Lonsdale St Braddon ACT 2612",
    "addr:housenumber":"/ 18",
    "addr:postcode":"2612",
    "addr:street":"Lonsdale St",
    "iso:country":"AU",
    "sg:address":"8/ 18 Lonsdale St",
    "sg:city":"Braddon",
    "sg:classifiers":[
        {
            "category":"Personal",
            "subcategory":"Beauty Salon",
            "type":"Services"
        }
    ],
    "sg:phone":"+61 2 6262 7177",
    "sg:postcode":"2612",
    "sg:province":"ACT",
    "sg:tags":[
        "hairdresser"
    ],
    "wof:name":"Seven Hair Studio",
    "wof:placetype":"venue"
},
  "geometry": {"coordinates":[149.13287353499999,-35.2737350464],"type":"Point"}
}