{
  "type": "Feature",
  "properties": {
    "iso:country":"AU",
    "sg:address":"58 Gladstone St",
    "sg:city":"Mudgee",
    "sg:classifiers":[
        {
            "category":"Personal",
            "subcategory":"Beauty Salon",
            "type":"Services"
        }
    ],
    "sg:phone":"+61 2 6372 6777",
    "sg:postcode":"2850",
    "sg:province":"NSW",
    "sg:tags":[
        "hairdresser"
    ],
    "wof:name":"Kims Kutting House Hair & Beauty",
    "wof:placetype":"venue"
},
  "geometry": {"coordinates":[149.58843999999999,-32.595062],"type":"Point"}
}