{
  "type": "Feature",
  "properties": {
    "iso:country":"AU",
    "sg:address":"60 William St",
    "sg:city":"Melbourne",
    "sg:classifiers":[
        {
            "category":"Professional",
            "subcategory":"Research",
            "type":"Services"
        }
    ],
    "sg:phone":"+61 3 9214 8126",
    "sg:postcode":"3000",
    "sg:province":"VIC",
    "sg:tags":[
        "industrial",
        "scientific"
    ],
    "wof:name":"CRC for International Food Manufacture & Packaging Science",
    "wof:placetype":"venue"
},
  "geometry": {"coordinates":[144.95939636200001,-37.8179092407],"type":"Point"}
}