{
  "type": "Feature",
  "properties": {
    "addr:full":"4/ 1 Boree St Ulladulla NSW 2539",
    "addr:housenumber":"/ 1",
    "addr:postcode":"2539",
    "addr:street":"Boree St",
    "iso:country":"AU",
    "sg:address":"4/ 1 Boree St",
    "sg:city":"Ulladulla",
    "sg:classifiers":[
        {
            "category":"Professional",
            "subcategory":"Management & Consulting",
            "type":"Services"
        }
    ],
    "sg:phone":"+61 2 4455 3831",
    "sg:postcode":"2539",
    "sg:province":"NSW",
    "sg:tags":[
        "consultant",
        "energy"
    ],
    "wof:name":"D & C Ferguson Building Inspection Services Pty Ltd",
    "wof:placetype":"venue"
},
  "geometry": {"coordinates":[150.472747803,-35.3597793579],"type":"Point"}
}