{
  "type": "Feature",
  "properties": {
    "addr:full":"U2/ 1200 Hay St West Perth WA 6005",
    "addr:housenumber":"1200",
    "addr:postcode":"6005",
    "addr:street":"U2 /;Hay St",
    "iso:country":"AU",
    "sg:address":"U2/ 1200 Hay St",
    "sg:city":"West Perth",
    "sg:classifiers":[
        {
            "category":"Cafe",
            "type":"Food & Drink"
        }
    ],
    "sg:phone":"+61 8 9321 6986",
    "sg:postcode":"6005",
    "sg:province":"WA",
    "wof:name":"Paddington Cafe & Take Away",
    "wof:placetype":"venue"
},
  "geometry": {"coordinates":[115.84290313699999,-31.9487953186],"type":"Point"}
}