{
  "type": "Feature",
  "properties": {
    "addr:full":"12 Anderson Rd Kilmore VIC 3764",
    "addr:housenumber":"12",
    "addr:postcode":"3764",
    "addr:street":"Anderson Rd",
    "iso:country":"AU",
    "sg:address":"12 Anderson Rd",
    "sg:city":"Kilmore",
    "sg:classifiers":[
        {
            "category":"Utilities",
            "subcategory":"Electric",
            "type":"Services"
        }
    ],
    "sg:phone":"+61 3 5782 1782",
    "sg:postcode":"3764",
    "sg:province":"VIC",
    "sg:tags":[
        "electrical",
        "contractor"
    ],
    "wof:name":"Breadsell. S",
    "wof:placetype":"venue"
},
  "geometry": {"coordinates":[144.96377563499999,-37.3019142151],"type":"Point"}
}