{
  "type": "Feature",
  "properties": {
    "addr:full":"7 Hoddle St Collingwood VIC 3066",
    "addr:housenumber":"7",
    "addr:postcode":"3066",
    "addr:street":"Hoddle St",
    "iso:country":"AU",
    "sg:address":"7 Hoddle St",
    "sg:city":"Collingwood",
    "sg:classifiers":[
        {
            "category":"Wholesale",
            "subcategory":"Construction Materials",
            "type":"Manufacturing & Wholesale Goods"
        }
    ],
    "sg:phone":"+61 3 9427 0122",
    "sg:postcode":"3066",
    "sg:province":"VIC",
    "sg:tags":[
        "lift"
    ],
    "wof:name":"Easy Living Home Elevators",
    "wof:placetype":"venue"
},
  "geometry": {"coordinates":[144.99119567899999,-37.8089370728],"type":"Point"}
}