{
  "type": "Feature",
  "properties": {
    "addr:full":"PO Box 118 Norton Summit SA 5136",
    "addr:postcode":"5136",
    "iso:country":"AU",
    "sg:address":"PO Box 118",
    "sg:city":"Norton Summit",
    "sg:classifiers":[
        {
            "category":"Building & Trades",
            "subcategory":"Construction",
            "type":"Services"
        }
    ],
    "sg:phone":"+61 8 8390 3600",
    "sg:postcode":"5136",
    "sg:province":"SA",
    "sg:tags":[
        "renovation",
        "alterations",
        "extension",
        "contractor"
    ],
    "wof:name":"Shelton Building Company",
    "wof:placetype":"venue"
},
  "geometry": {"coordinates":[138.73626709000001,-34.9184494019],"type":"Point"}
}