{
  "type": "Feature",
  "properties": {
    "addr:full":"38 Willoughby Rd Crows Nest NSW 2065",
    "addr:housenumber":"38",
    "addr:postcode":"2065",
    "addr:street":"Willoughby Rd",
    "iso:country":"AU",
    "sg:address":"38 Willoughby Rd",
    "sg:city":"Crows Nest",
    "sg:classifiers":[
        {
            "category":"Professional",
            "subcategory":"Engineering",
            "type":"Services"
        }
    ],
    "sg:phone":"+61 2 9490 9600",
    "sg:postcode":"2065",
    "sg:province":"NSW",
    "sg:tags":[
        "engineer"
    ],
    "wof:name":"Richmond & Ross Pty Ltd",
    "wof:placetype":"venue"
},
  "geometry": {"coordinates":[151.20069885300001,-33.8264007568],"type":"Point"}
}