{
  "type": "Feature",
  "properties": {
    "addr:full":"PO Box 635 Sanderson NT 0813",
    "addr:postcode":"nt 0813",
    "iso:country":"AU",
    "sg:address":"PO Box 635",
    "sg:city":"Sanderson",
    "sg:classifiers":[
        {
            "category":"Shopping",
            "subcategory":"Shoes",
            "type":"Retail Goods"
        }
    ],
    "sg:phone":"+61 417 398 476",
    "sg:postcode":"0813",
    "sg:province":"NT",
    "sg:tags":[
        "footwear"
    ],
    "wof:name":"Fruit Of Freedom",
    "wof:placetype":"venue"
},
  "geometry": {"coordinates":[130.89891052199999,-12.3905000687],"type":"Point"}
}