{
  "type": "Feature",
  "properties": {
    "addr:full":"193 Barrington St Bibra Lake WA 6163",
    "addr:housenumber":"193",
    "addr:postcode":"6163",
    "addr:street":"Barrington St",
    "iso:country":"AU",
    "sg:address":"193 Barrington St",
    "sg:city":"Bibra Lake",
    "sg:classifiers":[
        {
            "category":"Manufacturing",
            "subcategory":"Wood Products",
            "type":"Manufacturing & Wholesale Goods"
        }
    ],
    "sg:phone":"+61 8 9434 3935",
    "sg:postcode":"6163",
    "sg:province":"WA",
    "sg:tags":[
        "pallet",
        "platform"
    ],
    "wof:name":"West Coast Pallets",
    "wof:placetype":"venue"
},
  "geometry": {"coordinates":[115.811897,-32.116634],"type":"Point"}
}