{
  "type": "Feature",
  "properties": {
    "iso:country":"AU",
    "sg:address":"25 Erwin St",
    "sg:city":"Peakhurst",
    "sg:classifiers":[
        {
            "category":"Professional",
            "subcategory":"Computer Services",
            "type":"Services"
        }
    ],
    "sg:phone":"+61 2 8205 9644",
    "sg:postcode":"2210",
    "sg:province":"NSW",
    "sg:tags":[
        "consultant",
        "system"
    ],
    "wof:name":"Business Cycle Technology",
    "wof:placetype":"venue"
},
  "geometry": {"coordinates":[151.04435699999999,-33.958752],"type":"Point"}
}