{
  "type": "Feature",
  "properties": {
    "iso:country":"AU",
    "sg:address":"5 Walgen Crt",
    "sg:city":"Wanneroo",
    "sg:classifiers":[
        {
            "category":"Communications",
            "subcategory":"Film & Video Production",
            "type":"Services"
        }
    ],
    "sg:phone":"+61 8 9405 7490",
    "sg:postcode":"6065",
    "sg:province":"WA",
    "sg:tags":[
        "dvd",
        "library"
    ],
    "wof:name":"Network Video",
    "wof:placetype":"venue"
},
  "geometry": {"coordinates":[115.809143066,-31.7609710693],"type":"Point"}
}