{
  "type": "Feature",
  "properties": {
    "addr:full":"Shop F1 Bayside Balmoral, 28 Beach Frankston VIC 3199",
    "addr:housenumber":"f1;28",
    "addr:postcode":"3199",
    "addr:street":"Balmoral;Beach",
    "iso:country":"AU",
    "sg:address":"Shop F1 Bayside Balmoral, 28 Beach",
    "sg:city":"Frankston",
    "sg:classifiers":[
        {
            "category":"Cafe",
            "type":"Food & Drink"
        }
    ],
    "sg:phone":"+61 3 9781 1121",
    "sg:postcode":"3199",
    "sg:province":"VIC",
    "wof:name":"Jamaica Blue",
    "wof:placetype":"venue"
},
  "geometry": {"coordinates":[145.15594482399999,-38.1799278259],"type":"Point"}
}