{
  "type": "Feature",
  "properties": {
    "addr:full":"44 Robinson St Brighton East VIC 3187",
    "addr:housenumber":"44",
    "addr:postcode":"3187",
    "addr:street":"Robinson St",
    "iso:country":"AU",
    "sg:address":"44 Robinson St",
    "sg:city":"Brighton East",
    "sg:classifiers":[
        {
            "category":"Building & Trades",
            "subcategory":"Construction",
            "type":"Services"
        }
    ],
    "sg:phone":"+61 408 557 109",
    "sg:postcode":"3187",
    "sg:province":"VIC",
    "sg:tags":[
        "concrete",
        "contractor"
    ],
    "wof:name":"Brighton Paving",
    "wof:placetype":"venue"
},
  "geometry": {"coordinates":[145.01716613799999,-37.9182701111],"type":"Point"}
}