{
  "type": "Feature",
  "properties": {
    "iso:country":"AU",
    "sg:address":"49 Simpson Drv",
    "sg:city":"Bilambil Heights",
    "sg:classifiers":[
        {
            "category":"Building & Trades",
            "subcategory":"Landscaping Services",
            "type":"Services"
        }
    ],
    "sg:phone":"+61 412 408 450",
    "sg:postcode":"2486",
    "sg:province":"NSW",
    "sg:tags":[
        "slashing",
        "contractor"
    ],
    "wof:name":"Thats Slashing",
    "wof:placetype":"venue"
},
  "geometry": {"coordinates":[153.48739624000001,-28.2148361206],"type":"Point"}
}