{
  "type": "Feature",
  "properties": {
    "addr:full":"23 Delando St Waratah NSW 2298",
    "addr:housenumber":"23",
    "addr:postcode":"2298",
    "addr:street":"Delando St",
    "iso:country":"AU",
    "sg:address":"23 Delando St",
    "sg:city":"Waratah",
    "sg:classifiers":[
        {
            "category":"Organizations",
            "subcategory":"Non-profit Organization",
            "type":"Services"
        }
    ],
    "sg:phone":"+61 2 4968 9392",
    "sg:postcode":"2298",
    "sg:province":"NSW",
    "sg:tags":[
        "support",
        "disability",
        "organisation"
    ],
    "wof:name":"Delando Contract Service",
    "wof:placetype":"venue"
},
  "geometry": {"coordinates":[151.72125244099999,-32.9091567993],"type":"Point"}
}