{
  "type": "Feature",
  "properties": {
    "iso:country":"AU",
    "sg:address":"152 Lambton Rd",
    "sg:city":"Broadmeadow",
    "sg:classifiers":[
        {
            "category":"Building & Trades",
            "subcategory":"Locksmith",
            "type":"Services"
        }
    ],
    "sg:phone":"+61 2 4952 2230",
    "sg:postcode":"2292",
    "sg:province":"NSW",
    "sg:tags":[
        "lock"
    ],
    "wof:name":"Frost Security Locksmiths",
    "wof:placetype":"venue"
},
  "geometry": {"coordinates":[151.72450256400001,-32.9231719971],"type":"Point"}
}