{
  "type": "Feature",
  "properties": {
    "iso:country":"AU",
    "sg:address":"PO Box 268",
    "sg:city":"Beaconsfield",
    "sg:classifiers":[
        {
            "category":"Wholesale",
            "subcategory":"Auto Parts",
            "type":"Manufacturing & Wholesale Goods"
        }
    ],
    "sg:phone":"+61 3 9743 4351",
    "sg:postcode":"3807",
    "sg:province":"VIC",
    "sg:tags":[
        "recyclers"
    ],
    "wof:name":"XU-One Torana Spares and Repairs",
    "wof:placetype":"venue"
},
  "geometry": {"coordinates":[145.36799621599999,-38.0455284119],"type":"Point"}
}