{
  "type": "Feature",
  "properties": {
    "addr:full":"68 Mary St Gympie QLD 4570",
    "addr:housenumber":"68",
    "addr:postcode":"4570",
    "addr:street":"Mary St",
    "iso:country":"AU",
    "sg:address":"68 Mary St",
    "sg:city":"Gympie",
    "sg:classifiers":[
        {
            "category":"Banks & Credit Unions",
            "subcategory":"Bank",
            "type":"Services"
        }
    ],
    "sg:phone":"+61 7 5481 1787",
    "sg:postcode":"4570",
    "sg:province":"QLD",
    "wof:name":"Bendigo Community Bank",
    "wof:placetype":"venue"
},
  "geometry": {"coordinates":[152.66355895999999,-26.1902809143],"type":"Point"}
}