{
  "type": "Feature",
  "properties": {
    "addr:full":"PO Box 1222 Burleigh Heads QLD 4220",
    "addr:postcode":"4220",
    "iso:country":"AU",
    "sg:address":"PO Box 1222",
    "sg:city":"Burleigh Heads",
    "sg:classifiers":[
        {
            "category":"Shopping",
            "subcategory":"Stationery & Office Supplies",
            "type":"Retail Goods"
        }
    ],
    "sg:phone":"+61 7 5522 8402",
    "sg:postcode":"4220",
    "sg:province":"QLD",
    "sg:tags":[
        "partition"
    ],
    "wof:name":"Gold Coast Walls & Ceilings",
    "wof:placetype":"venue"
},
  "geometry": {"coordinates":[153.449752808,-28.0879096985],"type":"Point"}
}