{
  "type": "Feature",
  "properties": {
    "addr:full":"94 Frobisher St Osborne Park WA 6017",
    "addr:housenumber":"94",
    "addr:postcode":"6017",
    "addr:street":"Frobisher St",
    "iso:country":"AU",
    "sg:address":"94 Frobisher St",
    "sg:city":"Osborne Park",
    "sg:classifiers":[
        {
            "category":"Autos & Motor Vehicles",
            "subcategory":"Auto Supplies",
            "type":"Retail Goods"
        }
    ],
    "sg:phone":"+61 8 9444 8044",
    "sg:postcode":"6017",
    "sg:province":"WA",
    "sg:tags":[
        "paint",
        "automotive"
    ],
    "wof:name":"Robayne Distributors",
    "wof:placetype":"venue"
},
  "geometry": {"coordinates":[115.819580078,-31.9054927826],"type":"Point"}
}