{
  "type": "Feature",
  "properties": {
    "iso:country":"AU",
    "sg:address":"Suite1/ 1B Station St",
    "sg:city":"Thornleigh",
    "sg:classifiers":[
        {
            "category":"Building & Trades",
            "subcategory":"Plumbing",
            "type":"Services"
        }
    ],
    "sg:phone":"+61 2 9484 9171",
    "sg:postcode":"2120",
    "sg:province":"NSW",
    "sg:tags":[
        "plumber",
        "gasfitters"
    ],
    "wof:name":"Statewide Plumbing Pty Ltd",
    "wof:placetype":"venue"
},
  "geometry": {"coordinates":[151.079681397,-33.7319602966],"type":"Point"}
}