{
  "type": "Feature",
  "properties": {
    "addr:full":"343 Taylor St Toowoomba QLD 4350",
    "addr:housenumber":"343",
    "addr:postcode":"4350",
    "addr:street":"Taylor St",
    "iso:country":"AU",
    "sg:address":"343 Taylor St",
    "sg:city":"Toowoomba",
    "sg:classifiers":[
        {
            "category":"Autos & Motor Vehicles",
            "subcategory":"Auto Supplies",
            "type":"Retail Goods"
        }
    ],
    "sg:phone":"+61 7 4633 5777",
    "sg:postcode":"4350",
    "sg:province":"QLD",
    "sg:tags":[
        "equipment",
        "part",
        "truck"
    ],
    "wof:name":"Fleetparts Australia Pty Ltd",
    "wof:placetype":"venue"
},
  "geometry": {"coordinates":[151.90974399999999,-27.550905],"type":"Point"}
}