{
  "type": "Feature",
  "properties": {
    "addr:full":"27 Dixon Rd Rockingham WA 6168",
    "addr:housenumber":"27",
    "addr:postcode":"6168",
    "addr:street":"Dixon Rd",
    "iso:country":"AU",
    "sg:address":"27 Dixon Rd",
    "sg:city":"Rockingham",
    "sg:classifiers":[
        {
            "category":"Retail",
            "subcategory":"Auto Repair",
            "type":"Services"
        }
    ],
    "sg:phone":"+61 8 9527 9444",
    "sg:postcode":"6168",
    "sg:province":"WA",
    "sg:tags":[
        "clutch",
        "brake"
    ],
    "wof:name":"One Stop Brakes & Suspension",
    "wof:placetype":"venue"
},
  "geometry": {"coordinates":[115.749657,-32.277042],"type":"Point"}
}