{
  "type": "Feature",
  "properties": {
    "addr:full":"Ste 15/ 45 Ringwood St Ringwood VIC 3134",
    "addr:housenumber":"/ 45",
    "addr:postcode":"3134",
    "addr:street":"Ringwood St",
    "iso:country":"AU",
    "sg:address":"Ste 15/ 45 Ringwood St",
    "sg:city":"Ringwood",
    "sg:classifiers":[
        {
            "category":"Banks & Credit Unions",
            "subcategory":"Financial Services",
            "type":"Services"
        }
    ],
    "sg:phone":"+61 3 9879 6555",
    "sg:postcode":"3134",
    "sg:province":"VIC",
    "sg:tags":[
        "planning"
    ],
    "wof:name":"Townshend & Associates P/L",
    "wof:placetype":"venue"
},
  "geometry": {"coordinates":[145.227172852,-37.8116035461],"type":"Point"}
}