{
  "type": "Feature",
  "properties": {
    "addr:full":"Lvl4/ 162 Goulburn St Sydney NSW 2000",
    "addr:housenumber":"162",
    "addr:postcode":"2000",
    "addr:street":"Goulburn St",
    "iso:country":"AU",
    "sg:address":"Lvl4/ 162 Goulburn St",
    "sg:city":"Sydney",
    "sg:classifiers":[
        {
            "category":"Real Estate",
            "subcategory":"Real Estate Services",
            "type":"Services"
        }
    ],
    "sg:phone":"+61 2 9267 8044",
    "sg:postcode":"2000",
    "sg:province":"NSW",
    "sg:tags":[
        "listing"
    ],
    "wof:name":"CPM Research",
    "wof:placetype":"venue"
},
  "geometry": {"coordinates":[151.21229553200001,-33.8787727356],"type":"Point"}
}