{
  "type": "Feature",
  "properties": {
    "addr:full":"Level 6 380 Queen St Brisbane QLD 4000",
    "addr:housenumber":"380",
    "addr:postcode":"4000",
    "addr:street":"Queen St",
    "iso:country":"AU",
    "sg:address":"Level 6 380 Queen St",
    "sg:city":"Brisbane",
    "sg:classifiers":[
        {
            "category":"Government",
            "subcategory":"Customs House",
            "type":"Public Place"
        }
    ],
    "sg:phone":"+61 7 3229 2044",
    "sg:postcode":"4000",
    "sg:province":"QLD",
    "sg:tags":[
        "title",
        "management",
        "stratum"
    ],
    "wof:name":"BUGT Management Pty Ltd",
    "wof:placetype":"venue"
},
  "geometry": {"coordinates":[153.03007507300001,-27.4657096863],"type":"Point"}
}