{
  "type": "Feature",
  "properties": {
    "iso:country":"AU",
    "sg:address":"21 Oakwood Ave",
    "sg:city":"Meadow Springs",
    "sg:classifiers":[
        {
            "category":"Social Services",
            "subcategory":"Retirement Home",
            "type":"Services"
        }
    ],
    "sg:phone":"+61 8 9581 3811",
    "sg:postcode":"6210",
    "sg:province":"WA",
    "sg:tags":[
        "village"
    ],
    "wof:name":"Settlers Meadow Springs",
    "wof:placetype":"venue"
},
  "geometry": {"coordinates":[115.756767,-32.484806],"type":"Point"}
}