{
  "type": "Feature",
  "properties": {
    "addr:full":"95 Magnus St Nelson Bay NSW 2315",
    "addr:housenumber":"95",
    "addr:postcode":"2315",
    "addr:street":"Magnus St",
    "iso:country":"AU",
    "sg:address":"95 Magnus St",
    "sg:city":"Nelson Bay",
    "sg:classifiers":[
        {
            "category":"Banks & Credit Unions",
            "subcategory":"Financial Services",
            "type":"Services"
        }
    ],
    "sg:phone":"+61 13 19 87",
    "sg:postcode":"2315",
    "sg:province":"NSW",
    "sg:tags":[
        "building",
        "society"
    ],
    "wof:name":"Newcastle Permanent Building Society Ltd",
    "wof:placetype":"venue"
},
  "geometry": {"coordinates":[152.14381399999999,-32.721413],"type":"Point"}
}