{
  "type": "Feature",
  "properties": {
    "addr:full":"1B Victoria St North Geelong VIC 3215",
    "addr:housenumber":"1b",
    "addr:postcode":"3215",
    "addr:street":"Victoria St",
    "iso:country":"AU",
    "sg:address":"1B Victoria St",
    "sg:city":"North Geelong",
    "sg:classifiers":[
        {
            "category":"Education",
            "subcategory":"School",
            "type":"Public Place"
        }
    ],
    "sg:phone":"+61 3 5277 3405",
    "sg:postcode":"3215",
    "sg:province":"VIC",
    "sg:tags":[
        "state",
        "except",
        "nsw"
    ],
    "wof:name":"Nelson Park School Victoria St Annex",
    "wof:placetype":"venue"
},
  "geometry": {"coordinates":[144.35374450699999,-38.1230888367],"type":"Point"}
}