{
  "type": "Feature",
  "properties": {
    "addr:full":"PO Box 465 Jindera NSW 2642",
    "addr:postcode":"2642",
    "iso:country":"AU",
    "sg:address":"PO Box 465",
    "sg:city":"Jindera",
    "sg:classifiers":[
        {
            "category":"Sports & Exercise",
            "subcategory":"Gym",
            "type":"Entertainment"
        }
    ],
    "sg:phone":"+61 2 6026 1704",
    "sg:postcode":"2642",
    "sg:province":"NSW",
    "sg:tags":[
        "personal",
        "trainer",
        "fitness"
    ],
    "wof:name":"Fully Worked",
    "wof:placetype":"venue"
},
  "geometry": {"coordinates":[146.88897705100001,-35.9545898438],"type":"Point"}
}