{
  "type": "Feature",
  "properties": {
    "iso:country":"AU",
    "sg:address":"4 Hosie St",
    "sg:city":"Altona Meadows",
    "sg:classifiers":[
        {
            "category":"Food & Beverages",
            "subcategory":"Specialty",
            "type":"Retail Goods"
        }
    ],
    "sg:phone":"+61 3 9369 7540",
    "sg:postcode":"3028",
    "sg:province":"VIC",
    "sg:tags":[
        "product",
        "health"
    ],
    "wof:name":"Natural Health & Pet Products",
    "wof:placetype":"venue"
},
  "geometry": {"coordinates":[144.784943,-37.888725],"type":"Point"}
}