{
  "type": "Feature",
  "properties": {
    "addr:full":"195 B Boundary St West End (Brisbane) QLD 4101",
    "addr:housenumber":"195 b",
    "addr:postcode":"4101",
    "addr:street":"Boundary St",
    "iso:country":"AU",
    "sg:address":"195 B Boundary St",
    "sg:city":"West End (Brisbane)",
    "sg:classifiers":[
        {
            "category":"Health Services",
            "subcategory":"Dentist",
            "type":"Services"
        }
    ],
    "sg:phone":"+61 7 3844 4447",
    "sg:postcode":"4101",
    "sg:province":"QLD",
    "wof:name":"Ho Kerry Dr",
    "wof:placetype":"venue"
},
  "geometry": {"coordinates":[153.012161255,-27.4802818298],"type":"Point"}
}