{
  "type": "Feature",
  "properties": {
    "iso:country":"AU",
    "sg:address":"PO Box 334",
    "sg:city":"Young",
    "sg:classifiers":[
        {
            "category":"Freight",
            "type":"Transportation"
        }
    ],
    "sg:phone":"+61 407 484 950",
    "sg:postcode":"2594",
    "sg:province":"NSW",
    "sg:tags":[
        "light",
        "carrier"
    ],
    "wof:name":"Young & Country Freight",
    "wof:placetype":"venue"
},
  "geometry": {"coordinates":[148.29434204099999,-34.3139686584],"type":"Point"}
}