{
  "type": "Feature",
  "properties": {
    "iso:country":"AU",
    "sg:address":"399 Bay St",
    "sg:city":"Brighton",
    "sg:classifiers":[
        {
            "category":"Shopping",
            "subcategory":"Baby Store",
            "type":"Retail Goods"
        }
    ],
    "sg:phone":"+61 3 9530 8041",
    "sg:postcode":"3186",
    "sg:province":"VIC",
    "sg:tags":[
        "children's",
        "wear"
    ],
    "wof:name":"Little House Design",
    "wof:placetype":"venue"
},
  "geometry": {"coordinates":[145.00517273,-37.9057197571],"type":"Point"}
}