{
  "type": "Feature",
  "properties": {
    "iso:country":"AU",
    "sg:address":"14 Beach St",
    "sg:city":"Frankston",
    "sg:classifiers":[
        {
            "category":"Fast Food",
            "type":"Food & Drink"
        }
    ],
    "sg:phone":"+61 3 9783 6364",
    "sg:postcode":"3199",
    "sg:province":"VIC",
    "sg:tags":[
        "away",
        "take"
    ],
    "wof:name":"KFC",
    "wof:placetype":"venue"
},
  "geometry": {"coordinates":[144.96676635700001,-38.3328895569],"type":"Point"}
}