{
  "type": "Feature",
  "properties": {
    "iso:country":"AU",
    "sg:address":"5 Dowsett St",
    "sg:city":"Geelong South",
    "sg:classifiers":[
        {
            "category":"Fast Food",
            "type":"Food & Drink"
        }
    ],
    "sg:phone":"+61 3 5222 1310",
    "sg:postcode":"3220",
    "sg:province":"VIC",
    "sg:tags":[
        "away",
        "take"
    ],
    "wof:name":"Bell's Tuck Shop",
    "wof:placetype":"venue"
},
  "geometry": {"coordinates":[144.367691,-38.167297],"type":"Point"}
}