{
  "type": "Feature",
  "properties": {
    "addr:full":"Shop 1058, Carindale Shopping Town (Westfield) Carindale QLD 4152",
    "addr:housenumber":"1058",
    "addr:postcode":"4152",
    "iso:country":"AU",
    "sg:address":"Shop 1058, Carindale Shopping Town (Westfield)",
    "sg:city":"Carindale",
    "sg:classifiers":[
        {
            "category":"Personal",
            "subcategory":"Tanning Parlor",
            "type":"Services"
        }
    ],
    "sg:phone":"+61 7 3398 3330",
    "sg:postcode":"4152",
    "sg:province":"QLD",
    "sg:tags":[
        "solarium"
    ],
    "wof:name":"Body Bronze Carindale",
    "wof:placetype":"venue"
},
  "geometry": {"coordinates":[153.10345459000001,-27.5023994446],"type":"Point"}
}