{
  "type": "Feature",
  "properties": {
    "addr:full":"213 Clayton Rd Clayton VIC 3168",
    "addr:housenumber":"213",
    "addr:postcode":"3168",
    "addr:street":"Clayton Rd",
    "iso:country":"AU",
    "sg:address":"213 Clayton Rd",
    "sg:city":"Clayton",
    "sg:classifiers":[
        {
            "category":"Retail",
            "subcategory":"Repair Shop",
            "type":"Services"
        }
    ],
    "sg:phone":"+61 3 9544 7879",
    "sg:postcode":"3168",
    "sg:province":"VIC",
    "sg:tags":[
        "upholsterer"
    ],
    "wof:name":"Jims Upholstery",
    "wof:placetype":"venue"
},
  "geometry": {"coordinates":[145.12130737300001,-37.9161376953],"type":"Point"}
}