{
  "type": "Feature",
  "properties": {
    "addr:full":"Cnr Windsor Rd & Groves Ave Windsor NSW 2756",
    "addr:postcode":"2756",
    "addr:street":"Cnr Windsor Rd & Groves Ave",
    "iso:country":"AU",
    "sg:address":"Cnr Windsor Rd & Groves Ave",
    "sg:city":"Windsor",
    "sg:classifiers":[
        {
            "category":"Fast Food",
            "type":"Food & Drink"
        }
    ],
    "sg:phone":"+61 2 4577 6777",
    "sg:postcode":"2756",
    "sg:province":"NSW",
    "sg:tags":[
        "away",
        "take"
    ],
    "wof:name":"McDonald's Family Restaurants",
    "wof:placetype":"venue"
},
  "geometry": {"coordinates":[150.82957458499999,-33.6107597351],"type":"Point"}
}