{
  "type": "Feature",
  "properties": {
    "addr:full":"57 Strezlecki Ave Sunshine VIC 3020",
    "addr:housenumber":"57",
    "addr:postcode":"3020",
    "addr:street":"Strezlecki Ave",
    "iso:country":"AU",
    "sg:address":"57 Strezlecki Ave",
    "sg:city":"Sunshine",
    "sg:classifiers":[
        {
            "category":"Manufacturing",
            "subcategory":"Building Materials",
            "type":"Manufacturing & Wholesale Goods"
        }
    ],
    "sg:phone":"+61 3 9364 9495",
    "sg:postcode":"3020",
    "sg:province":"VIC",
    "sg:tags":[
        "equipment",
        "handling"
    ],
    "wof:name":"Morris Powerlec",
    "wof:placetype":"venue"
},
  "geometry": {"coordinates":[144.82565299999999,-37.808823],"type":"Point"}
}