{
  "type": "Feature",
  "properties": {
    "addr:full":"21 Elizabeth St Narrabri NSW 2390",
    "addr:housenumber":"21",
    "addr:postcode":"2390",
    "addr:street":"Elizabeth St",
    "iso:country":"AU",
    "sg:address":"21 Elizabeth St",
    "sg:city":"Narrabri",
    "sg:classifiers":[
        {
            "category":"Shopping",
            "subcategory":"Crafts & Fabrics",
            "type":"Retail Goods"
        }
    ],
    "sg:phone":"+61 2 6792 5881",
    "sg:postcode":"2390",
    "sg:province":"NSW",
    "sg:tags":[
        "quilting"
    ],
    "wof:name":"Quixote Quilting",
    "wof:placetype":"venue"
},
  "geometry": {"coordinates":[149.78012085,-30.3328533173],"type":"Point"}
}