{
  "type": "Feature",
  "properties": {
    "addr:full":"16 Napoleon St Cottesloe WA 6011",
    "addr:housenumber":"16",
    "addr:postcode":"6011",
    "addr:street":"Napoleon St",
    "iso:country":"AU",
    "sg:address":"16 Napoleon St",
    "sg:city":"Cottesloe",
    "sg:classifiers":[
        {
            "category":"Shopping",
            "subcategory":"Clothing, Apparel, & Fashions",
            "type":"Retail Goods"
        }
    ],
    "sg:phone":"+61 8 9385 1352",
    "sg:postcode":"6011",
    "sg:province":"WA",
    "sg:tags":[
        "boutique"
    ],
    "wof:name":"Bagutta",
    "wof:placetype":"venue"
},
  "geometry": {"coordinates":[115.761749268,-31.9977741241],"type":"Point"}
}