{
  "type": "Feature",
  "properties": {
    "iso:country":"AU",
    "sg:address":"Suite 1, Silver Sea 106 Sixth Ave",
    "sg:city":"Maroochydore",
    "sg:classifiers":[
        {
            "category":"Banks & Credit Unions",
            "subcategory":"Financial Services",
            "type":"Services"
        }
    ],
    "sg:phone":"+61 7 5451 1560",
    "sg:postcode":"4558",
    "sg:province":"QLD",
    "sg:tags":[
        "annuity",
        "rollover",
        "superannuation",
        "consultant"
    ],
    "wof:name":"Supa-Funds Management Pty Ltd",
    "wof:placetype":"venue"
},
  "geometry": {"coordinates":[153.102752686,-26.6604557037],"type":"Point"}
}