{
  "type": "Feature",
  "properties": {
    "addr:full":"296 Bay St Brighton North VIC 3186",
    "addr:housenumber":"296",
    "addr:postcode":"3186",
    "addr:street":"Bay St",
    "iso:country":"AU",
    "sg:address":"296 Bay St",
    "sg:city":"Brighton North",
    "sg:classifiers":[
        {
            "category":"Restaurant",
            "type":"Food & Drink"
        }
    ],
    "sg:phone":"+61 3 9596 2294",
    "sg:postcode":"3186",
    "sg:province":"VIC",
    "wof:name":"Baystreet Grill & Pasta Restaurant",
    "wof:placetype":"venue"
},
  "geometry": {"coordinates":[145.00199890100001,-37.9055786133],"type":"Point"}
}