{
  "type": "Feature",
  "properties": {
    "addr:full":"28 Carpenter St Brighton VIC 3186",
    "addr:housenumber":"28",
    "addr:postcode":"3186",
    "addr:street":"Carpenter St",
    "iso:country":"AU",
    "sg:address":"28 Carpenter St",
    "sg:city":"Brighton",
    "sg:classifiers":[
        {
            "category":"Banks & Credit Unions",
            "subcategory":"Financial Services",
            "type":"Services"
        }
    ],
    "sg:phone":"+61 3 9591 0911",
    "sg:postcode":"3186",
    "sg:province":"VIC",
    "sg:tags":[
        "planning"
    ],
    "wof:name":"Richard Salter & Associates Pty Ltd",
    "wof:placetype":"venue"
},
  "geometry": {"coordinates":[144.99435424800001,-37.9146080017],"type":"Point"}
}