{
  "type": "Feature",
  "properties": {
    "addr:full":"7 Leeds St Footscray VIC 3011",
    "addr:housenumber":"7",
    "addr:postcode":"3011",
    "addr:street":"Leeds St",
    "iso:country":"AU",
    "sg:address":"7 Leeds St",
    "sg:city":"Footscray",
    "sg:classifiers":[
        {
            "category":"Professional",
            "subcategory":"Detective & Security Services",
            "type":"Services"
        }
    ],
    "sg:phone":"+61 3 9687 7599",
    "sg:postcode":"3011",
    "sg:province":"VIC",
    "sg:tags":[
        "guard",
        "patrol"
    ],
    "wof:name":"Excell Security Services Pty Ltd",
    "wof:placetype":"venue"
},
  "geometry": {"coordinates":[144.90133667000001,-37.7987480164],"type":"Point"}
}