{
  "type": "Feature",
  "properties": {
    "addr:full":"Level 2/ 57 Queens St St Marys NSW 2760",
    "addr:housenumber":"/ 57",
    "addr:postcode":"2760",
    "addr:street":"Queens St",
    "iso:country":"AU",
    "sg:address":"Level 2/ 57 Queens St",
    "sg:city":"St Marys",
    "sg:classifiers":[
        {
            "category":"Travel",
            "subcategory":"Travel Agent",
            "type":"Entertainment"
        }
    ],
    "sg:phone":"+61 2 9623 0011",
    "sg:postcode":"2760",
    "sg:province":"NSW",
    "sg:tags":[
        "consultant"
    ],
    "wof:name":"Travel Care",
    "wof:placetype":"venue"
},
  "geometry": {"coordinates":[150.77432250999999,-33.7639694214],"type":"Point"}
}