{
  "type": "Feature",
  "properties": {
    "addr:full":"37 Cutler Ave Wagga Wagga NSW 2650",
    "addr:housenumber":"37",
    "addr:postcode":"2650",
    "addr:street":"Cutler Ave",
    "iso:country":"AU",
    "sg:address":"37 Cutler Ave",
    "sg:city":"Wagga Wagga",
    "sg:classifiers":[
        {
            "category":"Professional",
            "subcategory":"Computer Services",
            "type":"Services"
        }
    ],
    "sg:phone":"+61 407 264 526",
    "sg:postcode":"2650",
    "sg:province":"NSW",
    "sg:tags":[
        "repairs",
        "upgrade",
        "equipment"
    ],
    "wof:name":"Housecall Computer Services",
    "wof:placetype":"venue"
},
  "geometry": {"coordinates":[147.381591797,-35.1481933594],"type":"Point"}
}