{
  "type": "Feature",
  "properties": {
    "addr:full":"Level 1, 5 Myrtle St North Sydney NSW 2060",
    "addr:housenumber":"5",
    "addr:postcode":"2060",
    "addr:street":"Myrtle St",
    "iso:country":"AU",
    "sg:address":"Level 1, 5 Myrtle St",
    "sg:city":"North Sydney",
    "sg:classifiers":[
        {
            "category":"Utilities",
            "subcategory":"Telephone",
            "type":"Services"
        }
    ],
    "sg:phone":"+61 2 9959 0770",
    "sg:postcode":"2060",
    "sg:province":"NSW",
    "sg:tags":[
        "equipment",
        "system"
    ],
    "wof:name":"A Aaabout Telephone Systems",
    "wof:placetype":"venue"
},
  "geometry": {"coordinates":[151.20364379899999,-33.8312034607],"type":"Point"}
}