{
  "type": "Feature",
  "properties": {
    "addr:full":"PO Box 90 Dodges Ferry TAS 7173",
    "addr:postcode":"7173",
    "iso:country":"AU",
    "sg:address":"PO Box 90",
    "sg:city":"Dodges Ferry",
    "sg:classifiers":[
        {
            "category":"Building & Trades",
            "subcategory":"Plumbing",
            "type":"Services"
        }
    ],
    "sg:phone":"+61 3 6265 8634",
    "sg:postcode":"7173",
    "sg:province":"TAS",
    "sg:tags":[
        "plumber",
        "gasfitters"
    ],
    "wof:name":"Burn R I",
    "wof:placetype":"venue"
},
  "geometry": {"coordinates":[147.62486267099999,-42.8527107239],"type":"Point"}
}