{
  "type": "Feature",
  "properties": {
    "addr:full":"100 Wilson St Botany NSW 2019",
    "addr:housenumber":"100",
    "addr:postcode":"2019",
    "addr:street":"Wilson St",
    "iso:country":"AU",
    "sg:address":"100 Wilson St",
    "sg:city":"Botany",
    "sg:classifiers":[
        {
            "category":"Recreation",
            "subcategory":"Fishing",
            "type":"Entertainment"
        }
    ],
    "sg:phone":"+61 2 9316 9647",
    "sg:postcode":"2019",
    "sg:province":"NSW",
    "sg:tags":[
        "tackle"
    ],
    "wof:name":"Matthews G A & Co Pty Ltd",
    "wof:placetype":"venue"
},
  "geometry": {"coordinates":[151.206375122,-33.9485931396],"type":"Point"}
}