{
  "type": "Feature",
  "properties": {
    "addr:full":"PO Box 162 Glenorie NSW 2157",
    "addr:postcode":"2157",
    "iso:country":"AU",
    "sg:address":"PO Box 162",
    "sg:city":"Glenorie",
    "sg:classifiers":[
        {
            "category":"Farming",
            "subcategory":"Nursery",
            "type":"Manufacturing & Wholesale Goods"
        }
    ],
    "sg:phone":"+61 2 4566 6177",
    "sg:postcode":"2157",
    "sg:province":"NSW",
    "wof:name":"Colourwise Nursery (NSW) Pty Ltd",
    "wof:placetype":"venue"
},
  "geometry": {"coordinates":[151.00648498499999,-33.5958747864],"type":"Point"}
}