{
  "type": "Feature",
  "properties": {
    "addr:full":"141 Clovelly Rd Randwick NSW 2031",
    "addr:housenumber":"141",
    "addr:postcode":"2031",
    "addr:street":"Clovelly Rd",
    "iso:country":"AU",
    "sg:address":"141 Clovelly Rd",
    "sg:city":"Randwick",
    "sg:classifiers":[
        {
            "category":"Home & Garden",
            "subcategory":"Building Materials",
            "type":"Retail Goods"
        }
    ],
    "sg:phone":"+61 414 560 810",
    "sg:postcode":"2031",
    "sg:province":"NSW",
    "sg:tags":[
        "lawn",
        "cutting",
        "maintenance"
    ],
    "wof:name":"Mr Grass Lawnmowing & Gardening",
    "wof:placetype":"venue"
},
  "geometry": {"coordinates":[151.25120544399999,-33.9100418091],"type":"Point"}
}