{
  "type": "Feature",
  "properties": {
    "addr:full":"38 High St Berwick VIC 3806",
    "addr:housenumber":"38",
    "addr:postcode":"3806",
    "addr:street":"High St",
    "iso:country":"AU",
    "sg:address":"38 High St",
    "sg:city":"Berwick",
    "sg:classifiers":[
        {
            "category":"Personal",
            "subcategory":"Beauty Salon",
            "type":"Services"
        }
    ],
    "sg:phone":"+61 3 9707 4955",
    "sg:postcode":"3806",
    "sg:province":"VIC",
    "wof:name":"Anns Skinsational",
    "wof:placetype":"venue"
},
  "geometry": {"coordinates":[145.34400939899999,-38.0312957764],"type":"Point"}
}