{
  "type": "Feature",
  "properties": {
    "addr:full":"100 Grindle Rd Rocklea QLD 4106",
    "addr:housenumber":"100",
    "addr:postcode":"4106",
    "addr:street":"Grindle Rd",
    "iso:country":"AU",
    "sg:address":"100 Grindle Rd",
    "sg:city":"Rocklea",
    "sg:classifiers":[
        {
            "category":"Shopping",
            "subcategory":"Pets & Pet Supplies",
            "type":"Retail Goods"
        }
    ],
    "sg:phone":"+61 7 3715 4700",
    "sg:postcode":"4106",
    "sg:province":"QLD",
    "sg:tags":[
        "boring",
        "drilling",
        "equipment"
    ],
    "wof:name":"UDR",
    "wof:placetype":"venue"
},
  "geometry": {"coordinates":[153.00074768100001,-27.5544433594],"type":"Point"}
}