{
  "type": "Feature",
  "properties": {
    "addr:full":"9 Emma Ave Warrnambool VIC 3280",
    "addr:housenumber":"9",
    "addr:postcode":"3280",
    "addr:street":"Emma Ave",
    "iso:country":"AU",
    "sg:address":"9 Emma Ave",
    "sg:city":"Warrnambool",
    "sg:classifiers":[
        {
            "category":"Building & Trades",
            "subcategory":"Plumbing",
            "type":"Services"
        }
    ],
    "sg:phone":"+61 3 5562 3052",
    "sg:postcode":"3280",
    "sg:province":"VIC",
    "sg:tags":[
        "plumber",
        "gasfitters"
    ],
    "wof:name":"Brown R B",
    "wof:placetype":"venue"
},
  "geometry": {"coordinates":[142.50386047399999,-38.3884544373],"type":"Point"}
}