{
  "type": "Feature",
  "properties": {
    "addr:full":"9 Graham Rd Broomfield VIC 3364",
    "addr:housenumber":"9",
    "addr:postcode":"3364",
    "addr:street":"Graham Rd",
    "iso:country":"AU",
    "sg:address":"9 Graham Rd",
    "sg:city":"Broomfield",
    "sg:classifiers":[
        {
            "category":"Utilities",
            "subcategory":"Natural Gas",
            "type":"Services"
        }
    ],
    "sg:phone":"+61 417 318 035",
    "sg:postcode":"3364",
    "sg:province":"VIC",
    "sg:tags":[
        "cylinder",
        "testing"
    ],
    "wof:name":"Vic LPG Mobile Cylinder Testing",
    "wof:placetype":"venue"
},
  "geometry": {"coordinates":[143.910766602,-37.383190155],"type":"Point"}
}