{
  "type": "Feature",
  "properties": {
    "addr:full":"PO Box 413 Marden SA 5070",
    "addr:postcode":"5070",
    "iso:country":"AU",
    "sg:address":"PO Box 413",
    "sg:city":"Marden",
    "sg:classifiers":[
        {
            "category":"Professional",
            "subcategory":"Business Services",
            "type":"Services"
        }
    ],
    "sg:phone":"+61 8 8379 4656",
    "sg:postcode":"5070",
    "sg:province":"SA",
    "sg:tags":[
        "drafting"
    ],
    "wof:name":"Glenunga Home Drafting & Design",
    "wof:placetype":"venue"
},
  "geometry": {"coordinates":[138.63870239299999,-34.8968696594],"type":"Point"}
}