{
  "type": "Feature",
  "properties": {
    "addr:full":"Shop 2, 166 Argyle St Camden NSW 2570",
    "addr:housenumber":"shop 2 166",
    "addr:postcode":"2570",
    "addr:street":"Argyle St",
    "iso:country":"AU",
    "sg:address":"Shop 2, 166 Argyle St",
    "sg:city":"Camden",
    "sg:classifiers":[
        {
            "category":"Food & Beverages",
            "subcategory":"Bakery",
            "type":"Retail Goods"
        }
    ],
    "sg:phone":"+61 2 4655 2707",
    "sg:postcode":"2570",
    "sg:province":"NSW",
    "sg:tags":[
        "cake",
        "shop",
        "pastry"
    ],
    "wof:name":"Michel's Patisserie",
    "wof:placetype":"venue"
},
  "geometry": {"coordinates":[150.69436645499999,-34.0553436279],"type":"Point"}
}