{
  "type": "Feature",
  "properties": {
    "addr:full":"Westfield Shopng Cntr, The Avenue Figtree NSW 2525",
    "addr:postcode":"2525",
    "addr:street":"The Avenue",
    "iso:country":"AU",
    "sg:address":"Westfield Shopng Cntr, The Avenue",
    "sg:city":"Figtree",
    "sg:classifiers":[
        {
            "category":"Manufacturing",
            "subcategory":"Food",
            "type":"Manufacturing & Wholesale Goods"
        }
    ],
    "sg:phone":"+61 2 4227 5566",
    "sg:postcode":"2525",
    "sg:province":"NSW",
    "sg:tags":[
        "function",
        "catering"
    ],
    "wof:name":"Mandy's Corporate Catering",
    "wof:placetype":"venue"
},
  "geometry": {"coordinates":[150.86134338400001,-34.4358062744],"type":"Point"}
}