{
  "type": "Feature",
  "properties": {
    "iso:country":"AU",
    "sg:address":"5 Marion Rd",
    "sg:city":"Maddington",
    "sg:classifiers":[
        {
            "category":"Farming",
            "subcategory":"Fish & Marine Products",
            "type":"Manufacturing & Wholesale Goods"
        }
    ],
    "sg:phone":"+61 8 9365 9999",
    "sg:postcode":"6109",
    "sg:province":"WA",
    "sg:tags":[
        "asphalt",
        "supply"
    ],
    "wof:name":"Works Infrastructure",
    "wof:placetype":"venue"
},
  "geometry": {"coordinates":[115.986061096,-32.0398750305],"type":"Point"}
}