{
  "type": "Feature",
  "properties": {
    "iso:country":"AU",
    "sg:address":"119 Racecourse Rd",
    "sg:city":"Ascot",
    "sg:classifiers":[
        {
            "category":"Health Services",
            "subcategory":"Doctor",
            "type":"Services"
        }
    ],
    "sg:phone":"+61 7 3268 1937",
    "sg:postcode":"4007",
    "sg:province":"QLD",
    "sg:tags":[
        "medical",
        "practitioner"
    ],
    "wof:name":"Bartholomeusz D",
    "wof:placetype":"venue"
},
  "geometry": {"coordinates":[153.06547499999999,-27.432884],"type":"Point"}
}