{
  "type": "Feature",
  "properties": {
    "addr:full":"Unit 3/ 4 Yamada Pl Mornington TAS 7018",
    "addr:postcode":"7018",
    "addr:street":"Yamada Pl",
    "iso:country":"AU",
    "sg:address":"Unit 3/ 4 Yamada Pl",
    "sg:city":"Mornington",
    "sg:classifiers":[
        {
            "category":"Manufacturing",
            "subcategory":"Metals",
            "type":"Manufacturing & Wholesale Goods"
        }
    ],
    "sg:phone":"+61 3 6245 1500",
    "sg:postcode":"7018",
    "sg:province":"TAS",
    "sg:tags":[
        "sheet",
        "worker"
    ],
    "wof:name":"Central Roofing Supplies",
    "wof:placetype":"venue"
},
  "geometry": {"coordinates":[147.39987182600001,-42.8628234863],"type":"Point"}
}