{
  "type": "Feature",
  "properties": {
    "iso:country":"AU",
    "sg:address":"16 Carrara Rd",
    "sg:city":"Carrara",
    "sg:classifiers":[
        {
            "category":"Organizations",
            "subcategory":"Non-profit Organization",
            "type":"Services"
        }
    ],
    "sg:phone":"+61 7 5594 5298",
    "sg:postcode":"4211",
    "sg:province":"QLD",
    "sg:tags":[
        "environmental",
        "organisation",
        "conservation"
    ],
    "wof:name":"Australian Conservation Foundation Gold Coast Inc",
    "wof:placetype":"venue"
},
  "geometry": {"coordinates":[153.38565063499999,-28.0166664124],"type":"Point"}
}