{
  "type": "Feature",
  "properties": {
    "iso:country":"AU",
    "sg:address":"31 Thorpe St",
    "sg:city":"Morley",
    "sg:classifiers":[
        {
            "category":"Health Services",
            "subcategory":"Health Practitioner",
            "type":"Services"
        }
    ],
    "sg:phone":"+61 8 9375 1994",
    "sg:postcode":"6062",
    "sg:province":"WA",
    "sg:tags":[
        "alternative"
    ],
    "wof:name":"Ear Candles Australia",
    "wof:placetype":"venue"
},
  "geometry": {"coordinates":[115.891029358,-31.8922748566],"type":"Point"}
}