{
  "type": "Feature",
  "properties": {
    "addr:full":"Paddington Clinic 12 /261 Given Tce Paddington QLD 4064",
    "addr:housenumber":"12 / 261",
    "addr:postcode":"4064",
    "addr:street":"Given Tce",
    "iso:country":"AU",
    "sg:address":"Paddington Clinic 12",
    "sg:city":"/261 Given Tce Paddington",
    "sg:classifiers":[
        {
            "category":"Personal",
            "subcategory":"Massage",
            "type":"Services"
        }
    ],
    "sg:phone":"+61 7 3369 0045",
    "sg:postcode":"4064",
    "sg:province":"QLD",
    "sg:tags":[
        "therapy"
    ],
    "wof:name":"Sue Fittell",
    "wof:placetype":"venue"
},
  "geometry": {"coordinates":[153.00668335,-27.4619503021],"type":"Point"}
}