{
  "type": "Feature",
  "properties": {
    "iso:country":"AU",
    "sg:address":"185 High St",
    "sg:city":"Thomastown",
    "sg:classifiers":[
        {
            "category":"Banks & Credit Unions",
            "subcategory":"Bank",
            "type":"Services"
        }
    ],
    "sg:phone":"+61 3 9466 3479",
    "sg:postcode":"3074",
    "sg:province":"VIC",
    "sg:tags":[
        "society"
    ],
    "wof:name":"Northern Credit Solutions",
    "wof:placetype":"venue"
},
  "geometry": {"coordinates":[145.01361084000001,-37.6805381775],"type":"Point"}
}