{
  "type": "Feature",
  "properties": {
    "addr:full":"36 Lake St Forster NSW 2428",
    "addr:housenumber":"36",
    "addr:postcode":"2428",
    "addr:street":"Lake St",
    "iso:country":"AU",
    "sg:address":"36 Lake St",
    "sg:city":"Forster",
    "sg:classifiers":[
        {
            "category":"Structure",
            "subcategory":"Bridge",
            "type":"Public Place"
        }
    ],
    "sg:phone":"+61 2 6554 6935",
    "sg:postcode":"2428",
    "sg:province":"NSW",
    "sg:tags":[
        "chainsaw",
        "brushcutters"
    ],
    "wof:name":"Barry Austin Lawn Mowers & Chainsaws",
    "wof:placetype":"venue"
},
  "geometry": {"coordinates":[152.52514600000001,-32.183983],"type":"Point"}
}