{
  "type": "Feature",
  "properties": {
    "addr:full":"9350 Pacific Hwy Cooperabung NSW 2441",
    "addr:housenumber":"9350",
    "addr:postcode":"2441",
    "addr:street":"Pacific Hwy",
    "iso:country":"AU",
    "sg:address":"9350 Pacific Hwy",
    "sg:city":"Cooperabung",
    "sg:classifiers":[
        {
            "category":"Home & Garden",
            "subcategory":"Carpets & Floor Coverings",
            "type":"Retail Goods"
        }
    ],
    "sg:phone":"+61 2 6585 0122",
    "sg:postcode":"2441",
    "sg:province":"NSW",
    "sg:tags":[
        "tile",
        "wall",
        "layer"
    ],
    "wof:name":"Floor & Wall Tiler",
    "wof:placetype":"venue"
},
  "geometry": {"coordinates":[152.815155,-31.283718],"type":"Point"}
}