{
  "type": "Feature",
  "properties": {
    "addr:full":"Coolangatta Airport Suite 4 44 Eastern Ave Coolangatta QLD 4225",
    "addr:housenumber":"44",
    "addr:postcode":"4225",
    "addr:street":"Eastern Ave",
    "iso:country":"AU",
    "sg:address":"Coolangatta Airport Suite 4 44 Eastern Ave",
    "sg:city":"Coolangatta",
    "sg:classifiers":[
        {
            "category":"Education",
            "subcategory":"Special Training",
            "type":"Public Place"
        }
    ],
    "sg:phone":"+61 7 5599 5444",
    "sg:postcode":"4225",
    "sg:province":"QLD",
    "sg:tags":[
        "school",
        "flying"
    ],
    "wof:name":"FTC Flight Training Consultancy",
    "wof:placetype":"venue"
},
  "geometry": {"coordinates":[153.51017761200001,-28.1613826752],"type":"Point"}
}