{
  "type": "Feature",
  "properties": {
    "addr:full":"Shp3/ Dickson Pl Dickson ACT 2602",
    "addr:postcode":"2602",
    "iso:country":"AU",
    "sg:address":"Shp3/ Dickson Pl",
    "sg:city":"Dickson",
    "sg:classifiers":[
        {
            "category":"Cafe",
            "type":"Food & Drink"
        }
    ],
    "sg:phone":"+61 2 6247 8283",
    "sg:postcode":"2602",
    "sg:province":"ACT",
    "wof:name":"Deeks Bakery & Cafe",
    "wof:placetype":"venue"
},
  "geometry": {"coordinates":[149.139770508,-35.2509040833],"type":"Point"}
}