{
  "type": "Feature",
  "properties": {
    "addr:full":"6a Chaleyer St Willoughby NSW 2068",
    "addr:housenumber":"6a",
    "addr:postcode":"2068",
    "addr:street":"Chaleyer St",
    "iso:country":"AU",
    "sg:address":"6a Chaleyer St",
    "sg:city":"Willoughby",
    "sg:classifiers":[
        {
            "category":"Wholesale",
            "subcategory":"Drugs",
            "type":"Manufacturing & Wholesale Goods"
        }
    ],
    "sg:phone":"+61 2 9417 0588",
    "sg:postcode":"2068",
    "sg:province":"NSW",
    "sg:tags":[
        "wholesaler",
        "pharmaceutical",
        "product",
        "mfrs"
    ],
    "wof:name":"Mentholatum Australasia Pty Ltd",
    "wof:placetype":"venue"
},
  "geometry": {"coordinates":[151.20335388199999,-33.7916908264],"type":"Point"}
}