{
  "type": "Feature",
  "properties": {
    "addr:full":"11 Denbeigh St Parramatta Park QLD 4870",
    "addr:housenumber":"11",
    "addr:postcode":"4870",
    "addr:street":"Denbeigh St",
    "iso:country":"AU",
    "sg:address":"11 Denbeigh St",
    "sg:city":"Parramatta Park",
    "sg:classifiers":[
        {
            "category":"Professional",
            "subcategory":"Computer Services",
            "type":"Services"
        }
    ],
    "sg:phone":"+61 7 4051 7025",
    "sg:postcode":"4870",
    "sg:province":"QLD",
    "sg:tags":[
        "equipment",
        "networking",
        "installation"
    ],
    "wof:name":"Alcomp Computers",
    "wof:placetype":"venue"
},
  "geometry": {"coordinates":[145.760864258,-16.9184932709],"type":"Point"}
}