{
  "type": "Feature",
  "properties": {
    "iso:country":"AU",
    "sg:address":"37 King St",
    "sg:city":"Scottsdale",
    "sg:classifiers":[
        {
            "category":"Food & Beverages",
            "subcategory":"Liquor & Beverages",
            "type":"Retail Goods"
        }
    ],
    "sg:phone":"+61 3 6352 2411",
    "sg:postcode":"7260",
    "sg:province":"TAS",
    "sg:tags":[
        "store"
    ],
    "wof:name":"Scottsdale Liquor Market",
    "wof:placetype":"venue"
},
  "geometry": {"coordinates":[147.516006,-41.16153],"type":"Point"}
}