{
  "type": "Feature",
  "properties": {
    "addr:full":"Warner Village Shopping Centre, Shop 16 / 383 Samsonvale Rd Warner QLD 4500",
    "addr:housenumber":"shop 16 / 383",
    "addr:postcode":"4500",
    "addr:street":"Samsonvale Rd",
    "iso:country":"AU",
    "sg:address":"Warner Village Shopping Centre, Shop 16 / 383 Samsonvale Rd",
    "sg:city":"Warner",
    "sg:classifiers":[
        {
            "category":"Health Services",
            "subcategory":"Doctor",
            "type":"Services"
        }
    ],
    "sg:phone":"+61 7 3882 2366",
    "sg:postcode":"4500",
    "sg:province":"QLD",
    "sg:tags":[
        "medical",
        "practitioner"
    ],
    "wof:name":"Warnercare 7 Day Medical Practice",
    "wof:placetype":"venue"
},
  "geometry": {"coordinates":[152.95248413100001,-27.2912216187],"type":"Point"}
}