{
  "type": "Feature",
  "properties": {
    "iso:country":"AU",
    "sg:address":"43 Comboyne St",
    "sg:city":"Kendall",
    "sg:classifiers":[
        {
            "category":"Shopping",
            "subcategory":"Antiques",
            "type":"Retail Goods"
        }
    ],
    "sg:phone":"+61 2 6559 4933",
    "sg:postcode":"2439",
    "sg:province":"NSW",
    "sg:tags":[
        "restoration",
        "reproduction"
    ],
    "wof:name":"K & L Olde Re-Store The",
    "wof:placetype":"venue"
},
  "geometry": {"coordinates":[152.70137,-31.629711],"type":"Point"}
}