{
  "type": "Feature",
  "properties": {
    "iso:country":"AU",
    "sg:address":"12 Ogilvie Pl",
    "sg:city":"Garran",
    "sg:classifiers":[
        {
            "category":"Building & Trades",
            "subcategory":"Construction",
            "type":"Services"
        }
    ],
    "sg:phone":"+61 2 6285 4460",
    "sg:postcode":"2605",
    "sg:province":"ACT",
    "sg:tags":[
        "contractor"
    ],
    "wof:name":"Kerwin Constructions Pty Ltd",
    "wof:placetype":"venue"
},
  "geometry": {"coordinates":[149.109298706,-35.3385429382],"type":"Point"}
}