{
  "type": "Feature",
  "properties": {
    "addr:full":"3 Manse St Guyra NSW 2365",
    "addr:housenumber":"3",
    "addr:postcode":"2365",
    "addr:street":"Manse St",
    "iso:country":"AU",
    "sg:address":"3 Manse St",
    "sg:city":"Guyra",
    "sg:classifiers":[
        {
            "category":"Building & Trades",
            "subcategory":"Construction",
            "type":"Services"
        }
    ],
    "sg:phone":"+61 407 305 283",
    "sg:postcode":"2365",
    "sg:province":"NSW",
    "sg:tags":[
        "contractor"
    ],
    "wof:name":"McFarlane R B",
    "wof:placetype":"venue"
},
  "geometry": {"coordinates":[151.68106079099999,-30.2245540619],"type":"Point"}
}