{
  "type": "Feature",
  "properties": {
    "addr:full":"10 Abbott St Fairfield VIC 3078",
    "addr:housenumber":"10",
    "addr:postcode":"3078",
    "addr:street":"Abbott St",
    "iso:country":"AU",
    "sg:address":"10 Abbott St",
    "sg:city":"Fairfield",
    "sg:classifiers":[
        {
            "category":"Manufacturing",
            "subcategory":"Rubber & Plastics",
            "type":"Manufacturing & Wholesale Goods"
        }
    ],
    "sg:phone":"+61 3 9497 2066",
    "sg:postcode":"3078",
    "sg:province":"VIC",
    "sg:tags":[
        "wholesaler",
        "product",
        "mfrs"
    ],
    "wof:name":"Rapid Roller Co.Pty.Ltd.",
    "wof:placetype":"venue"
},
  "geometry": {"coordinates":[145.029205322,-37.7696037292],"type":"Point"}
}