{
  "type": "Feature",
  "properties": {
    "addr:full":"1 High St Shepparton VIC 3630",
    "addr:housenumber":"1",
    "addr:postcode":"3630",
    "addr:street":"High St",
    "iso:country":"AU",
    "sg:address":"1 High St",
    "sg:city":"Shepparton",
    "sg:classifiers":[
        {
            "category":"Shopping",
            "subcategory":"Stationery & Office Supplies",
            "type":"Retail Goods"
        }
    ],
    "sg:phone":"+61 3 5821 5162",
    "sg:postcode":"3630",
    "sg:province":"VIC",
    "wof:name":"Boise Office Solutions",
    "wof:placetype":"venue"
},
  "geometry": {"coordinates":[145.39921569800001,-36.3809089661],"type":"Point"}
}