{
  "type": "Feature",
  "properties": {
    "addr:full":"Mt Dandenong Tourist Rd Mt Dandenong VIC 3767",
    "addr:postcode":"3767",
    "addr:street":"Mt;Tourist Rd",
    "iso:country":"AU",
    "sg:address":"Mt Dandenong Tourist Rd",
    "sg:city":"Mt Dandenong",
    "sg:classifiers":[
        {
            "category":"Education",
            "subcategory":"Kindergarten",
            "type":"Public Place"
        }
    ],
    "sg:phone":"+61 3 9728 1480",
    "sg:postcode":"3767",
    "sg:province":"VIC",
    "sg:tags":[
        "pre-schools"
    ],
    "wof:name":"Mt Dandenong Pre-School Inc",
    "wof:placetype":"venue"
},
  "geometry": {"coordinates":[145.36080932600001,-37.8456535339],"type":"Point"}
}