{
  "type": "Feature",
  "properties": {
    "iso:country":"AU",
    "sg:address":"Day Rd",
    "sg:city":"Rockingham",
    "sg:classifiers":[
        {
            "category":"Arena",
            "subcategory":"Sports Club",
            "type":"Entertainment"
        }
    ],
    "sg:phone":"+61 430 230 441",
    "sg:postcode":"6168",
    "sg:province":"WA",
    "sg:tags":[
        "defence",
        "supply",
        "self",
        "instruction",
        "martial art"
    ],
    "wof:name":"Beston Gracie Brazilian Jiu-Jitsu",
    "wof:placetype":"venue"
},
  "geometry": {"coordinates":[115.7714,-32.278477],"type":"Point"}
}