{
  "type": "Feature",
  "properties": {
    "addr:full":"6 Tim Pl Athelstone SA 5076",
    "addr:housenumber":"6",
    "addr:postcode":"5076",
    "addr:street":"Pl",
    "iso:country":"AU",
    "sg:address":"6 Tim Pl",
    "sg:city":"Athelstone",
    "sg:classifiers":[
        {
            "category":"Building & Trades",
            "subcategory":"Landscaping Services",
            "type":"Services"
        }
    ],
    "sg:phone":"+61 414 914 730",
    "sg:postcode":"5076",
    "sg:province":"SA",
    "sg:tags":[
        "designer",
        "landscape",
        "contractor"
    ],
    "wof:name":"Dingo Solutions",
    "wof:placetype":"venue"
},
  "geometry": {"coordinates":[138.70570373499999,-34.8692016602],"type":"Point"}
}