{
  "type": "Feature",
  "properties": {
    "addr:full":"U4/ 53 Barry St Bayswater VIC 3153",
    "addr:housenumber":"53",
    "addr:postcode":"3153",
    "addr:street":"U4 /;Barry St",
    "iso:country":"AU",
    "sg:address":"U4/ 53 Barry St",
    "sg:city":"Bayswater",
    "sg:classifiers":[
        {
            "category":"Professional",
            "type":"Services"
        }
    ],
    "sg:phone":"+61 3 9762 7070",
    "sg:postcode":"3153",
    "sg:province":"VIC",
    "sg:tags":[
        "transport"
    ],
    "wof:name":"Transport Mangement Soloutions",
    "wof:placetype":"venue"
},
  "geometry": {"coordinates":[145.28128051799999,-37.8475875854],"type":"Point"}
}