{
  "type": "Feature",
  "properties": {
    "iso:country":"AU",
    "sg:address":"2 Victoria Drv",
    "sg:city":"Brooklyn",
    "sg:classifiers":[
        {
            "category":"Manufacturing",
            "subcategory":"Wood Products",
            "type":"Manufacturing & Wholesale Goods"
        }
    ],
    "sg:phone":"+61 3 9316 8111",
    "sg:postcode":"3012",
    "sg:province":"VIC",
    "sg:tags":[
        "pallet",
        "platform"
    ],
    "wof:name":"Brooklyn Pallets",
    "wof:placetype":"venue"
},
  "geometry": {"coordinates":[144.85662841800001,-37.8087081909],"type":"Point"}
}