{
  "type": "Feature",
  "properties": {
    "addr:full":"Five Islands Rd Unanderra NSW 2526",
    "addr:postcode":"2526",
    "addr:street":"Five Islands Rd",
    "iso:country":"AU",
    "sg:address":"Five Islands Rd",
    "sg:city":"Unanderra",
    "sg:classifiers":[
        {
            "category":"Arts & Performance",
            "subcategory":"Art Gallery",
            "type":"Entertainment"
        }
    ],
    "sg:phone":"+61 2 4271 1822",
    "sg:postcode":"2526",
    "sg:province":"NSW",
    "sg:tags":[
        "non-ferrous",
        "metal"
    ],
    "wof:name":"Hydromet Operations Southern Ltd",
    "wof:placetype":"venue"
},
  "geometry": {"coordinates":[150.84930419899999,-34.4498825073],"type":"Point"}
}