{
  "type": "Feature",
  "properties": {
    "addr:full":"Highland Service Centre 227 Old Hume Hwy Mittagong NSW 2575",
    "addr:housenumber":"227",
    "addr:postcode":"2575",
    "addr:street":"Old Hume Hwy",
    "iso:country":"AU",
    "sg:address":"Highland Service Centre 227 Old Hume Hwy",
    "sg:city":"Mittagong",
    "sg:classifiers":[
        {
            "category":"Insurance",
            "subcategory":"Hazard Insurance",
            "type":"Services"
        }
    ],
    "sg:phone":"+61 2 4872 1951",
    "sg:postcode":"2575",
    "sg:province":"NSW",
    "sg:tags":[
        "motor",
        "vehicle"
    ],
    "wof:name":"Greenslip King The",
    "wof:placetype":"venue"
},
  "geometry": {"coordinates":[150.43371582,-34.4468421936],"type":"Point"}
}