{
  "type": "Feature",
  "properties": {
    "iso:country":"AU",
    "sg:address":"1st Fl,Victoria Centre, 45- 47 Victoria St",
    "sg:city":"Hobart",
    "sg:classifiers":[
        {
            "category":"Personal",
            "subcategory":"Massage",
            "type":"Services"
        }
    ],
    "sg:phone":"+61 3 6272 4431",
    "sg:postcode":"7000",
    "sg:province":"TAS",
    "sg:tags":[
        "therapy"
    ],
    "wof:name":"Cross Jillian",
    "wof:placetype":"venue"
},
  "geometry": {"coordinates":[147.32496643100001,-42.8842430115],"type":"Point"}
}