{
  "type": "Feature",
  "properties": {
    "iso:country":"AU",
    "sg:address":"10 Tivoli Ave",
    "sg:city":"Rose Bay",
    "sg:classifiers":[
        {
            "category":"Health Services",
            "subcategory":"Doctor",
            "type":"Services"
        }
    ],
    "sg:phone":"+61 2 9371 6887",
    "sg:postcode":"2029",
    "sg:province":"NSW",
    "sg:tags":[
        "medical",
        "practitioner"
    ],
    "wof:name":"Khurana V K",
    "wof:placetype":"venue"
},
  "geometry": {"coordinates":[151.27151489299999,-33.8655433655],"type":"Point"}
}