{
  "type": "Feature",
  "properties": {
    "addr:full":"14 Roe St Cummins SA 5631",
    "addr:housenumber":"14",
    "addr:postcode":"5631",
    "addr:street":"Roe St",
    "iso:country":"AU",
    "sg:address":"14 Roe St",
    "sg:city":"Cummins",
    "sg:classifiers":[
        {
            "category":"Building & Trades",
            "subcategory":"Construction",
            "type":"Services"
        }
    ],
    "sg:phone":"+61 8 8676 2286",
    "sg:postcode":"5631",
    "sg:province":"SA",
    "sg:tags":[
        "contractor"
    ],
    "wof:name":"Francis N J & J D",
    "wof:placetype":"venue"
},
  "geometry": {"coordinates":[135.721832275,-34.2707862854],"type":"Point"}
}