{
  "type": "Feature",
  "properties": {
    "iso:country":"AU",
    "sg:address":"Aspley Village Shopping Centre 591 Robinson Rd",
    "sg:city":"Aspley",
    "sg:classifiers":[
        {
            "category":"Food & Beverages",
            "subcategory":"Specialty",
            "type":"Retail Goods"
        }
    ],
    "sg:phone":"+61 7 3263 8497",
    "sg:postcode":"4034",
    "sg:province":"QLD",
    "sg:tags":[
        "product",
        "health"
    ],
    "wof:name":"Aspley Village Pharmacy",
    "wof:placetype":"venue"
},
  "geometry": {"coordinates":[153.02392599999999,-27.364723],"type":"Point"}
}