{
  "type": "Feature",
  "properties": {
    "addr:full":"189 Reynolds Rd Doncaster East VIC 3109",
    "addr:housenumber":"189",
    "addr:postcode":"3109",
    "addr:street":"Reynolds Rd",
    "iso:country":"AU",
    "sg:address":"189 Reynolds Rd",
    "sg:city":"Doncaster East",
    "sg:classifiers":[
        {
            "category":"Travel",
            "subcategory":"Hotels & Motels",
            "type":"Entertainment"
        }
    ],
    "sg:phone":"+61 3 9841 8122",
    "sg:postcode":"3109",
    "sg:province":"VIC",
    "sg:tags":[
        "pub"
    ],
    "wof:name":"Cherry Hill Tavern",
    "wof:placetype":"venue"
},
  "geometry": {"coordinates":[145.17030334500001,-37.7637405396],"type":"Point"}
}