{
  "type": "Feature",
  "properties": {
    "addr:full":"64 Faithful St Wangaratta VIC 3677",
    "addr:housenumber":"64",
    "addr:postcode":"3677",
    "addr:street":"Faithful St",
    "iso:country":"AU",
    "sg:address":"64 Faithful St",
    "sg:city":"Wangaratta",
    "sg:classifiers":[
        {
            "category":"Cafe",
            "type":"Food & Drink"
        }
    ],
    "sg:phone":"+61 3 5722 3545",
    "sg:postcode":"3677",
    "sg:province":"VIC",
    "wof:name":"Idyl Book Cafe",
    "wof:placetype":"venue"
},
  "geometry": {"coordinates":[146.327224731,-36.3524475098],"type":"Point"}
}