{
  "type": "Feature",
  "properties": {
    "addr:full":"41 Upton St Bundall QLD 4217",
    "addr:housenumber":"41",
    "addr:postcode":"4217",
    "addr:street":"Upton St",
    "iso:country":"AU",
    "sg:address":"41 Upton St",
    "sg:city":"Bundall",
    "sg:classifiers":[
        {
            "category":"Autos & Motor Vehicles",
            "subcategory":"Auto Supplies",
            "type":"Retail Goods"
        }
    ],
    "sg:phone":"+61 7 5531 6189",
    "sg:postcode":"4217",
    "sg:province":"QLD",
    "sg:tags":[
        "tyre"
    ],
    "wof:name":"Bundall Discount Tyres",
    "wof:placetype":"venue"
},
  "geometry": {"coordinates":[153.41075134299999,-28.0068340302],"type":"Point"}
}