{
  "type": "Feature",
  "properties": {
    "iso:country":"AU",
    "sg:address":"6 Veronica St",
    "sg:city":"Capalaba",
    "sg:classifiers":[
        {
            "category":"Building & Trades",
            "subcategory":"Plumbing",
            "type":"Services"
        }
    ],
    "sg:phone":"+61 7 3823 2455",
    "sg:postcode":"4157",
    "sg:province":"QLD",
    "sg:tags":[
        "equipment",
        "valves"
    ],
    "wof:name":"Armstrong Steam & Engineering Pty Ltd",
    "wof:placetype":"venue"
},
  "geometry": {"coordinates":[153.19818115199999,-27.5284576416],"type":"Point"}
}