{
  "type": "Feature",
  "properties": {
    "iso:country":"AU",
    "sg:address":"727a Pittwater Rd",
    "sg:city":"Dee Why",
    "sg:classifiers":[
        {
            "category":"Health Services",
            "subcategory":"Doctor",
            "type":"Services"
        }
    ],
    "sg:phone":"+61 2 9971 6605",
    "sg:postcode":"2099",
    "sg:province":"NSW",
    "sg:tags":[
        "medical",
        "practitioner"
    ],
    "wof:name":"Hanly Moir Pathology Pty Ltd",
    "wof:placetype":"venue"
},
  "geometry": {"coordinates":[151.28793335,-33.7515106201],"type":"Point"}
}