{
  "type": "Feature",
  "properties": {
    "iso:country":"AU",
    "sg:address":"1a Dickasons Rd",
    "sg:city":"Heathmont",
    "sg:classifiers":[
        {
            "category":"Health Services",
            "subcategory":"Health Practitioner",
            "type":"Services"
        }
    ],
    "sg:phone":"+61 3 9729 2333",
    "sg:postcode":"3135",
    "sg:province":"VIC",
    "sg:tags":[
        "psychologist"
    ],
    "wof:name":"Noble Peter",
    "wof:placetype":"venue"
},
  "geometry": {"coordinates":[145.244506836,-37.8306655884],"type":"Point"}
}