{
  "type": "Feature",
  "properties": {
    "iso:country":"AU",
    "sg:address":"Unit 4M, 32 Sirius Rd",
    "sg:city":"Lane Cove",
    "sg:classifiers":[
        {
            "category":"Building & Trades",
            "subcategory":"Construction",
            "type":"Services"
        }
    ],
    "sg:phone":"+61 2 9418 7639",
    "sg:postcode":"2066",
    "sg:province":"NSW",
    "sg:tags":[
        "contractor"
    ],
    "wof:name":"Omni Management Services Pty Limited",
    "wof:placetype":"venue"
},
  "geometry": {"coordinates":[151.14593505900001,-33.8116493225],"type":"Point"}
}