{
  "type": "Feature",
  "properties": {
    "addr:full":"PO Box 713 Wangaratta VIC 3677",
    "addr:postcode":"3677",
    "iso:country":"AU",
    "sg:address":"PO Box 713",
    "sg:city":"Wangaratta",
    "sg:classifiers":[
        {
            "category":"Utilities",
            "subcategory":"Electric",
            "type":"Services"
        }
    ],
    "sg:phone":"+61 417 776 240",
    "sg:postcode":"3677",
    "sg:province":"VIC",
    "sg:tags":[
        "electrical",
        "contractor"
    ],
    "wof:name":"Baines Electrical",
    "wof:placetype":"venue"
},
  "geometry": {"coordinates":[146.318527222,-36.3704109192],"type":"Point"}
}