{
  "type": "Feature",
  "properties": {
    "iso:country":"AU",
    "sg:address":"22 Donegal Rd",
    "sg:city":"Lonsdale",
    "sg:classifiers":[
        {
            "category":"Retail",
            "subcategory":"Auto Repair",
            "type":"Services"
        }
    ],
    "sg:phone":"+61 8 8326 1711",
    "sg:postcode":"5160",
    "sg:province":"SA",
    "sg:tags":[
        "repairer",
        "motor",
        "engineer"
    ],
    "wof:name":"G-Tek Automotive Repairs",
    "wof:placetype":"venue"
},
  "geometry": {"coordinates":[138.49183654800001,-35.1214904785],"type":"Point"}
}