{
  "type": "Feature",
  "properties": {
    "iso:country":"AU",
    "sg:address":"88 Railway St",
    "sg:city":"Altona",
    "sg:classifiers":[
        {
            "category":"Health Services",
            "subcategory":"Dentist",
            "type":"Services"
        }
    ],
    "sg:phone":"+61 3 9398 2874",
    "sg:postcode":"3018",
    "sg:province":"VIC",
    "wof:name":"Panoussi J",
    "wof:placetype":"venue"
},
  "geometry": {"coordinates":[144.82975769000001,-37.8674354553],"type":"Point"}
}