{
  "type": "Feature",
  "properties": {
    "addr:full":"Unit 7/ 8 Johnson Rd Campbelltown NSW 2560",
    "addr:housenumber":"8",
    "addr:postcode":"2560",
    "addr:street":"Johnson Rd",
    "iso:country":"AU",
    "sg:address":"Unit 7/ 8 Johnson Rd",
    "sg:city":"Campbelltown",
    "sg:classifiers":[
        {
            "category":"Building & Trades",
            "subcategory":"Landscaping Services",
            "type":"Services"
        }
    ],
    "sg:phone":"+61 2 4628 2415",
    "sg:postcode":"2560",
    "sg:province":"NSW",
    "sg:tags":[
        "inspection"
    ],
    "wof:name":"M.L.C Property Inspections",
    "wof:placetype":"venue"
},
  "geometry": {"coordinates":[150.80523681599999,-34.0594787598],"type":"Point"}
}