{
  "type": "Feature",
  "properties": {
    "iso:country":"AU",
    "sg:address":"Cnr Dorking Rd & Trawool St",
    "sg:city":"Box Hill North",
    "sg:classifiers":[
        {
            "category":"Retail",
            "subcategory":"Auto Repair",
            "type":"Services"
        }
    ],
    "sg:phone":"+61 3 9898 9781",
    "sg:postcode":"3129",
    "sg:province":"VIC",
    "sg:tags":[
        "repairer",
        "motor",
        "engineer"
    ],
    "wof:name":"First Choice Automotive Repairs",
    "wof:placetype":"venue"
},
  "geometry": {"coordinates":[145.13304138199999,-37.8062286377],"type":"Point"}
}