{
  "type": "Feature",
  "properties": {
    "addr:full":"Suite 6, Level 1, 163 Commercial Rd South Yarra VIC 3141",
    "addr:housenumber":"163",
    "addr:postcode":"3141",
    "addr:street":"Commercial Rd",
    "iso:country":"AU",
    "sg:address":"Suite 6, Level 1, 163 Commercial Rd",
    "sg:city":"South Yarra",
    "sg:classifiers":[
        {
            "category":"Building & Trades",
            "subcategory":"Construction",
            "type":"Services"
        }
    ],
    "sg:phone":"+61 3 9824 2655",
    "sg:postcode":"3141",
    "sg:province":"VIC",
    "sg:tags":[
        "contractor"
    ],
    "wof:name":"Karl Degering & Associates",
    "wof:placetype":"venue"
},
  "geometry": {"coordinates":[144.99183654800001,-37.846408844],"type":"Point"}
}