{
  "type": "Feature",
  "properties": {
    "addr:full":"1 Trial St South West Rocks NSW 2431",
    "addr:housenumber":"1",
    "addr:postcode":"2431",
    "addr:street":"Trial St South West Rocks",
    "iso:country":"AU",
    "sg:address":"1 Trial St",
    "sg:city":"South West Rocks",
    "sg:classifiers":[
        {
            "category":"Education",
            "subcategory":"Kindergarten",
            "type":"Public Place"
        }
    ],
    "sg:phone":"+61 2 6566 6177",
    "sg:postcode":"2431",
    "sg:province":"NSW",
    "sg:tags":[
        "pre-schools"
    ],
    "wof:name":"South West Rocks Pre-School",
    "wof:placetype":"venue"
},
  "geometry": {"coordinates":[153.04458600000001,-30.887531],"type":"Point"}
}