{
  "type": "Feature",
  "properties": {
    "iso:country":"AU",
    "sg:address":"Braidwood Rd",
    "sg:city":"Goulburn",
    "sg:classifiers":[
        {
            "category":"Sports & Exercise",
            "subcategory":"Sports Center",
            "type":"Entertainment"
        }
    ],
    "sg:phone":"+61 2 4822 2811",
    "sg:postcode":"2580",
    "sg:province":"NSW",
    "sg:tags":[
        "ground"
    ],
    "wof:name":"Wakefield Park Motor Racing Circuit",
    "wof:placetype":"venue"
},
  "geometry": {"coordinates":[149.71473693900001,-34.7633094788],"type":"Point"}
}