{
  "type": "Feature",
  "properties": {
    "addr:full":"3 Bluewater Drv Sandhurst VIC 3977",
    "addr:housenumber":"3",
    "addr:postcode":"3977",
    "addr:street":"Bluewater Drv",
    "iso:country":"AU",
    "sg:address":"3 Bluewater Drv",
    "sg:city":"Sandhurst",
    "sg:classifiers":[
        {
            "category":"Building & Trades",
            "subcategory":"Pest Control",
            "type":"Services"
        }
    ],
    "sg:phone":"+61 437 097 801",
    "sg:postcode":"3977",
    "sg:province":"VIC",
    "wof:name":"The Termite Man",
    "wof:placetype":"venue"
},
  "geometry": {"coordinates":[145.214599609,-38.0797996521],"type":"Point"}
}