{
  "type": "Feature",
  "properties": {
    "iso:country":"AU",
    "sg:address":"339 Swan St",
    "sg:city":"Richmond",
    "sg:classifiers":[
        {
            "category":"Shopping",
            "subcategory":"Antiques",
            "type":"Retail Goods"
        }
    ],
    "sg:phone":"+61 3 9427 1459",
    "sg:postcode":"3121",
    "sg:province":"VIC",
    "sg:tags":[
        "restoration",
        "reproduction"
    ],
    "wof:name":"Junk & Disorderly",
    "wof:placetype":"venue"
},
  "geometry": {"coordinates":[145.004592895,-37.8262519836],"type":"Point"}
}