{
  "type": "Feature",
  "properties": {
    "addr:full":"29 Gap Rd Lockwood South VIC 3551",
    "addr:housenumber":"29",
    "addr:postcode":"3551",
    "addr:street":"Gap Rd",
    "iso:country":"AU",
    "sg:address":"29 Gap Rd",
    "sg:city":"Lockwood South",
    "sg:classifiers":[
        {
            "category":"Manufacturing",
            "subcategory":"Tools & Machinery",
            "type":"Manufacturing & Wholesale Goods"
        }
    ],
    "sg:phone":"+61 407 202 037",
    "sg:postcode":"3551",
    "sg:province":"VIC",
    "sg:tags":[
        "earth",
        "excavating",
        "moving",
        "equipment"
    ],
    "wof:name":"Troy Stevenson",
    "wof:placetype":"venue"
},
  "geometry": {"coordinates":[144.187225342,-36.8275985718],"type":"Point"}
}