{
  "type": "Feature",
  "properties": {
    "iso:country":"AU",
    "sg:address":"Shp 1/ 111 Hunter St",
    "sg:city":"Newcastle",
    "sg:classifiers":[
        {
            "category":"Cafe",
            "type":"Food & Drink"
        }
    ],
    "sg:phone":"+61 2 4929 6604",
    "sg:postcode":"2300",
    "sg:province":"NSW",
    "wof:name":"Jet Espresso & Sandwich Bar",
    "wof:placetype":"venue"
},
  "geometry": {"coordinates":[151.781555,-32.927246],"type":"Point"}
}