{
  "type": "Feature",
  "properties": {
    "addr:full":"140 Karinie St Swan Hill VIC 3585",
    "addr:housenumber":"140",
    "addr:postcode":"3585",
    "addr:street":"Karinie St",
    "iso:country":"AU",
    "sg:address":"140 Karinie St",
    "sg:city":"Swan Hill",
    "sg:classifiers":[
        {
            "category":"Professional",
            "subcategory":"Engineering",
            "type":"Services"
        }
    ],
    "sg:phone":"+61 3 5032 1916",
    "sg:postcode":"3585",
    "sg:province":"VIC",
    "sg:tags":[
        "engineer"
    ],
    "wof:name":"Lusty Australia",
    "wof:placetype":"venue"
},
  "geometry": {"coordinates":[143.535629,-35.325104],"type":"Point"}
}