{
  "type": "Feature",
  "properties": {
    "iso:country":"AU",
    "sg:address":"50 Boorowa St",
    "sg:city":"Young",
    "sg:classifiers":[
        {
            "category":"Shopping",
            "subcategory":"Clothing, Apparel, & Fashions",
            "type":"Retail Goods"
        }
    ],
    "sg:phone":"+61 2 6382 2289",
    "sg:postcode":"2594",
    "sg:province":"NSW",
    "sg:tags":[
        "menswear"
    ],
    "wof:name":"Workwear Centre Young The",
    "wof:placetype":"venue"
},
  "geometry": {"coordinates":[148.286865234,-34.3106384277],"type":"Point"}
}