{
  "type": "Feature",
  "properties": {
    "addr:full":"Level 7,Room 711/ 125 Swanston St Melbourne VIC 3000",
    "addr:housenumber":"711 / 125",
    "addr:postcode":"3000",
    "addr:street":"Room;Swanston St",
    "iso:country":"AU",
    "sg:address":"Level 7,Room 711/ 125 Swanston St",
    "sg:city":"Melbourne",
    "sg:classifiers":[
        {
            "category":"Professional",
            "subcategory":"Accounting & Tax Preparation",
            "type":"Services"
        }
    ],
    "sg:phone":"+61 3 9663 9166",
    "sg:postcode":"3000",
    "sg:province":"VIC",
    "sg:tags":[
        "case",
        "mfrs",
        "jewellery",
        "pad",
        "wholesaler",
        "display"
    ],
    "wof:name":"House Of P & J Displays",
    "wof:placetype":"venue"
},
  "geometry": {"coordinates":[144.966064453,-37.8147964478],"type":"Point"}
}