{
  "type": "Feature",
  "properties": {
    "addr:full":"Kyeamba St Mangoplah NSW 2652",
    "addr:postcode":"2652",
    "addr:street":"Kyeamba St",
    "iso:country":"AU",
    "sg:address":"Kyeamba St",
    "sg:city":"Mangoplah",
    "sg:classifiers":[
        {
            "category":"Home & Garden",
            "subcategory":"Garden Supply",
            "type":"Retail Goods"
        }
    ],
    "sg:phone":"+61 2 6928 5791",
    "sg:postcode":"2652",
    "sg:province":"NSW",
    "sg:tags":[
        "fertilizer"
    ],
    "wof:name":"Mangoplah Farm Centre Pty Ltd",
    "wof:placetype":"venue"
},
  "geometry": {"coordinates":[147.253372192,-35.3771286011],"type":"Point"}
}