{
  "type": "Feature",
  "properties": {
    "iso:country":"AU",
    "sg:address":"175 High St",
    "sg:city":"Heathcote",
    "sg:classifiers":[
        {
            "category":"Food & Beverages",
            "subcategory":"Supermarket",
            "type":"Retail Goods"
        }
    ],
    "sg:phone":"+61 3 5433 2010",
    "sg:postcode":"3523",
    "sg:province":"VIC",
    "sg:tags":[
        "grocery",
        "store"
    ],
    "wof:name":"Heathcote Licensed Supermarket",
    "wof:placetype":"venue"
},
  "geometry": {"coordinates":[144.705826,-36.919285],"type":"Point"}
}