{
  "type": "Feature",
  "properties": {
    "iso:country":"AU",
    "sg:address":"289 Timor St",
    "sg:city":"Warrnambool",
    "sg:classifiers":[
        {
            "category":"Health Services",
            "subcategory":"Doctor",
            "type":"Services"
        }
    ],
    "sg:phone":"+61 3 5561 4266",
    "sg:postcode":"3280",
    "sg:province":"VIC",
    "sg:tags":[
        "nurse",
        "nursing"
    ],
    "wof:name":"Bridge Personnel",
    "wof:placetype":"venue"
},
  "geometry": {"coordinates":[142.47677612300001,-38.38306427],"type":"Point"}
}