{
  "type": "Feature",
  "properties": {
    "iso:country":"AU",
    "sg:address":"165 Bosworth Rd",
    "sg:city":"Bairnsdale",
    "sg:classifiers":[
        {
            "category":"Retail",
            "subcategory":"Auto Repair",
            "type":"Services"
        }
    ],
    "sg:phone":"+61 3 5152 2018",
    "sg:postcode":"3875",
    "sg:province":"VIC",
    "sg:tags":[
        "repairer",
        "motor",
        "engineer"
    ],
    "wof:name":"Leadoux P & R Automotive Repairs",
    "wof:placetype":"venue"
},
  "geometry": {"coordinates":[147.60198974599999,-37.8379173279],"type":"Point"}
}