{
  "type": "Feature",
  "properties": {
    "iso:country":"AU",
    "sg:address":"PO Box 407",
    "sg:city":"Fullarton",
    "sg:classifiers":[
        {
            "category":"Building & Trades",
            "subcategory":"Plumbing",
            "type":"Services"
        }
    ],
    "sg:phone":"+61 419 807 611",
    "sg:postcode":"5063",
    "sg:province":"SA",
    "sg:tags":[
        "plumber",
        "gasfitters"
    ],
    "wof:name":"Norwood Plumbing",
    "wof:placetype":"venue"
},
  "geometry": {"coordinates":[138.62567138700001,-34.9543495178],"type":"Point"}
}