{
  "type": "Feature",
  "properties": {
    "addr:full":"15 Downs Rd Codrington VIC 3285",
    "addr:housenumber":"15",
    "addr:postcode":"3285",
    "addr:street":"Downs Rd",
    "iso:country":"AU",
    "sg:address":"15 Downs Rd",
    "sg:city":"Codrington",
    "sg:classifiers":[
        {
            "category":"Farming",
            "subcategory":"Farm & Veterinary Services",
            "type":"Manufacturing & Wholesale Goods"
        }
    ],
    "sg:phone":"+61 3 5568 4344",
    "sg:postcode":"3285",
    "sg:province":"VIC",
    "sg:tags":[
        "irrigation",
        "reticulation",
        "system"
    ],
    "wof:name":"Codrington Nursery",
    "wof:placetype":"venue"
},
  "geometry": {"coordinates":[141.952194214,-38.2656707764],"type":"Point"}
}