{
  "type": "Feature",
  "properties": {
    "iso:country":"AU",
    "sg:address":"27 Duncan St",
    "sg:city":"Maroubra",
    "sg:classifiers":[
        {
            "category":"Building & Trades",
            "subcategory":"Plumbing",
            "type":"Services"
        }
    ],
    "sg:phone":"+61 2 9349 3566",
    "sg:postcode":"2035",
    "sg:province":"NSW",
    "sg:tags":[
        "plumber",
        "gasfitters"
    ],
    "wof:name":"Barry Varcoe Plumbing",
    "wof:placetype":"venue"
},
  "geometry": {"coordinates":[151.257415772,-33.942325592],"type":"Point"}
}