{
  "type": "Feature",
  "properties": {
    "iso:country":"AU",
    "sg:address":"Level 3, 74 Pitt St",
    "sg:city":"Sydney",
    "sg:classifiers":[
        {
            "category":"Health Services",
            "subcategory":"Chiropractor",
            "type":"Services"
        }
    ],
    "sg:phone":"+61 2 9235 2464",
    "sg:postcode":"2000",
    "sg:province":"NSW",
    "wof:name":"Devoy John",
    "wof:placetype":"venue"
},
  "geometry": {"coordinates":[151.20875549300001,-33.8661460876],"type":"Point"}
}