{
  "type": "Feature",
  "properties": {
    "addr:full":"\"Myilton\" 73 Milne Rd Armidale NSW 2350",
    "addr:housenumber":"73",
    "addr:postcode":"2350",
    "addr:street":"Milne Rd",
    "iso:country":"AU",
    "sg:address":"\"Myilton\" 73 Milne Rd",
    "sg:city":"Armidale",
    "sg:classifiers":[
        {
            "category":"Building & Trades",
            "subcategory":"Construction",
            "type":"Services"
        }
    ],
    "sg:phone":"+61 2 6775 3812",
    "sg:postcode":"2350",
    "sg:province":"NSW",
    "sg:tags":[
        "earth",
        "excavating",
        "moving",
        "contractor"
    ],
    "wof:name":"S D & D M Myhill Bobcat Hire",
    "wof:placetype":"venue"
},
  "geometry": {"coordinates":[151.76910400400001,-30.590051651],"type":"Point"}
}