{
  "type": "Feature",
  "properties": {
    "iso:country":"AU",
    "sg:address":"140 Toongarra Rd",
    "sg:city":"Leichhardt",
    "sg:classifiers":[
        {
            "category":"Wholesale",
            "subcategory":"Meat",
            "type":"Manufacturing & Wholesale Goods"
        }
    ],
    "sg:phone":"+61 7 3202 4528",
    "sg:postcode":"4305",
    "sg:province":"QLD",
    "sg:tags":[
        "packing",
        "exporting"
    ],
    "wof:name":"Comgroup Supplies Pty Ltd T/A Big Country",
    "wof:placetype":"venue"
},
  "geometry": {"coordinates":[152.72393798799999,-27.6167087555],"type":"Point"}
}