{
  "type": "Feature",
  "properties": {
    "iso:country":"AU",
    "sg:address":"2 Patton La",
    "sg:city":"Broken Hill",
    "sg:classifiers":[
        {
            "category":"Education",
            "subcategory":"Kindergarten",
            "type":"Public Place"
        }
    ],
    "sg:phone":"+61 8 8087 2122",
    "sg:postcode":"2880",
    "sg:province":"NSW",
    "sg:tags":[
        "pre-schools"
    ],
    "wof:name":"Rainbow Preschool",
    "wof:placetype":"venue"
},
  "geometry": {"coordinates":[141.45370483400001,-31.9852256775],"type":"Point"}
}