{
  "type": "Feature",
  "properties": {
    "addr:full":"Phillip Market Place, Cnr Hindmarsh Drv & Botany St Phillip ACT 2606",
    "addr:postcode":"2606",
    "addr:street":"Place Cnr Hindmarsh Drv & Botany St",
    "iso:country":"AU",
    "sg:address":"Phillip Market Place, Cnr Hindmarsh Drv & Botany St",
    "sg:city":"Phillip",
    "sg:classifiers":[
        {
            "category":"Communications",
            "subcategory":"Film & Video Production",
            "type":"Services"
        }
    ],
    "sg:phone":"+61 2 6282 8211",
    "sg:postcode":"2606",
    "sg:province":"ACT",
    "sg:tags":[
        "dvd",
        "library"
    ],
    "wof:name":"Blockbuster",
    "wof:placetype":"venue"
},
  "geometry": {"coordinates":[149.08836364699999,-35.3491020203],"type":"Point"}
}