{
  "type": "Feature",
  "properties": {
    "addr:full":"428 Urana Rd Lavington NSW 2641",
    "addr:housenumber":"428",
    "addr:postcode":"2641",
    "addr:street":"Urana Rd",
    "iso:country":"AU",
    "sg:address":"428 Urana Rd",
    "sg:city":"Lavington",
    "sg:classifiers":[
        {
            "category":"Recreation",
            "subcategory":"Boat Charter",
            "type":"Entertainment"
        }
    ],
    "sg:phone":"+61 2 6025 9262",
    "sg:postcode":"2641",
    "sg:province":"NSW",
    "sg:tags":[
        "canopy",
        "motor"
    ],
    "wof:name":"Brown Scott Upholstery",
    "wof:placetype":"venue"
},
  "geometry": {"coordinates":[146.92897033700001,-36.043094635],"type":"Point"}
}