{
  "type": "Feature",
  "properties": {
    "iso:country":"AU",
    "sg:address":"225 Charmen Rd",
    "sg:city":"Cheltenham",
    "sg:classifiers":[
        {
            "category":"Health Services",
            "subcategory":"Dentist",
            "type":"Services"
        }
    ],
    "sg:phone":"+61 3 9589 2165",
    "sg:postcode":"3192",
    "sg:province":"VIC",
    "sg:tags":[
        "dental",
        "prosthetist"
    ],
    "wof:name":"Barbour Mark S",
    "wof:placetype":"venue"
},
  "geometry": {"coordinates":[145.054763794,-37.9694213867],"type":"Point"}
}