{
  "type": "Feature",
  "properties": {
    "addr:full":"Suite 805, Level 8, 3 Waverley St Bondi Junction NSW 2022",
    "addr:housenumber":"3",
    "addr:postcode":"2022",
    "addr:street":"805;Waverley St",
    "iso:country":"AU",
    "sg:address":"Suite 805, Level 8, 3 Waverley St",
    "sg:city":"Bondi Junction",
    "sg:classifiers":[
        {
            "category":"Professional",
            "type":"Services"
        }
    ],
    "sg:phone":"+61 2 9387 1022",
    "sg:postcode":"2022",
    "sg:province":"NSW",
    "sg:tags":[
        "valuer"
    ],
    "wof:name":"Business Valuations & Assessment Services",
    "wof:placetype":"venue"
},
  "geometry": {"coordinates":[151.25172424300001,-33.8927154541],"type":"Point"}
}