{
  "type": "Feature",
  "properties": {
    "addr:full":"197 Roghan Rd Boondall QLD 4034",
    "addr:housenumber":"197",
    "addr:postcode":"4034",
    "addr:street":"Roghan Rd",
    "iso:country":"AU",
    "sg:address":"197 Roghan Rd",
    "sg:city":"Boondall",
    "sg:classifiers":[
        {
            "category":"Communications",
            "type":"Services"
        }
    ],
    "sg:phone":"+61 7 3265 3078",
    "sg:postcode":"4034",
    "sg:province":"QLD",
    "sg:tags":[
        "public",
        "system",
        "address"
    ],
    "wof:name":"Vellco Electric Company",
    "wof:placetype":"venue"
},
  "geometry": {"coordinates":[153.049408,-27.342068],"type":"Point"}
}