{
  "type": "Feature",
  "properties": {
    "addr:full":"52 Reed St Spotswood VIC 3015",
    "addr:housenumber":"52",
    "addr:postcode":"3015",
    "addr:street":"Reed St",
    "iso:country":"AU",
    "sg:address":"52 Reed St",
    "sg:city":"Spotswood",
    "sg:classifiers":[
        {
            "category":"Utilities",
            "subcategory":"Electric",
            "type":"Services"
        }
    ],
    "sg:phone":"+61 3 9391 9684",
    "sg:postcode":"3015",
    "sg:province":"VIC",
    "sg:tags":[
        "electrical",
        "contractor"
    ],
    "wof:name":"Blake Denver",
    "wof:placetype":"venue"
},
  "geometry": {"coordinates":[144.87759399399999,-37.8295898438],"type":"Point"}
}