{
  "type": "Feature",
  "properties": {
    "iso:country":"AU",
    "sg:address":"1136 Mooral Creek Rd",
    "sg:city":"Strathcedar",
    "sg:classifiers":[
        {
            "category":"Building & Trades",
            "subcategory":"Cleaning & Sanitation",
            "type":"Services"
        }
    ],
    "sg:phone":"+61 2 6550 5701",
    "sg:postcode":"2429",
    "sg:province":"NSW",
    "sg:tags":[
        "asbestos",
        "treatment",
        "removal"
    ],
    "wof:name":"De Burca Rory",
    "wof:placetype":"venue"
},
  "geometry": {"coordinates":[152.35754399999999,-31.748652],"type":"Point"}
}