{
  "type": "Feature",
  "properties": {
    "addr:full":"53 Old Cleveland Rd Stones Corner QLD 4120",
    "addr:housenumber":"53",
    "addr:postcode":"4120",
    "addr:street":"Old Cleveland Rd",
    "iso:country":"AU",
    "sg:address":"53 Old Cleveland Rd",
    "sg:city":"Stones Corner",
    "sg:classifiers":[
        {
            "category":"Banks & Credit Unions",
            "subcategory":"Financial Services",
            "type":"Services"
        }
    ],
    "sg:phone":"+61 7 3397 0844",
    "sg:postcode":"4120",
    "sg:province":"QLD",
    "sg:tags":[
        "financier"
    ],
    "wof:name":"AMX Money",
    "wof:placetype":"venue"
},
  "geometry": {"coordinates":[153.04458618199999,-27.4987030029],"type":"Point"}
}