{
  "type": "Feature",
  "properties": {
    "iso:country":"AU",
    "sg:address":"34 Synnot St",
    "sg:city":"Werribee",
    "sg:classifiers":[
        {
            "category":"Personal",
            "subcategory":"Hair Removal",
            "type":"Services"
        }
    ],
    "sg:phone":"+61 3 9741 0639",
    "sg:postcode":"3030",
    "sg:province":"VIC",
    "wof:name":"Tracy's Skin & Body Centre",
    "wof:placetype":"venue"
},
  "geometry": {"coordinates":[144.661819,-37.902348],"type":"Point"}
}