{
  "type": "Feature",
  "properties": {
    "addr:full":"2/ 24 Ocean St Cronulla NSW 2230",
    "addr:housenumber":"/ 24",
    "addr:postcode":"2230",
    "addr:street":"Ocean St",
    "iso:country":"AU",
    "sg:address":"2/ 24 Ocean St",
    "sg:city":"Cronulla",
    "sg:classifiers":[
        {
            "category":"Utilities",
            "subcategory":"Electric",
            "type":"Services"
        }
    ],
    "sg:phone":"+61 412 040 401",
    "sg:postcode":"2230",
    "sg:province":"NSW",
    "sg:tags":[
        "electrical",
        "contractor"
    ],
    "wof:name":"CBD Data & Electrical",
    "wof:placetype":"venue"
},
  "geometry": {"coordinates":[151.150787353,-34.0458869934],"type":"Point"}
}