{
  "type": "Feature",
  "properties": {
    "addr:full":"24 Hanson St Corryong VIC 3707",
    "addr:housenumber":"24",
    "addr:postcode":"3707",
    "addr:street":"Hanson St",
    "iso:country":"AU",
    "sg:address":"24 Hanson St",
    "sg:city":"Corryong",
    "sg:classifiers":[
        {
            "category":"Food & Beverages",
            "subcategory":"Supermarket",
            "type":"Retail Goods"
        }
    ],
    "sg:phone":"+61 2 6076 1286",
    "sg:postcode":"3707",
    "sg:province":"VIC",
    "sg:tags":[
        "grocery",
        "store"
    ],
    "wof:name":"Foodworks",
    "wof:placetype":"venue"
},
  "geometry": {"coordinates":[147.905517578,-36.1952171326],"type":"Point"}
}