{
  "type": "Feature",
  "properties": {
    "iso:country":"AU",
    "sg:address":"Crestwood Rd",
    "sg:city":"Jilliby",
    "sg:classifiers":[
        {
            "category":"Professional",
            "subcategory":"Computer Services",
            "type":"Services"
        }
    ],
    "sg:phone":"+61 2 4353 3250",
    "sg:postcode":"2259",
    "sg:province":"NSW",
    "sg:tags":[
        "consultant",
        "system"
    ],
    "wof:name":"Cardinal Software Solutions Pty Ltd",
    "wof:placetype":"venue"
},
  "geometry": {"coordinates":[151.39976501500001,-33.224521637],"type":"Point"}
}