{
  "type": "Feature",
  "properties": {
    "iso:country":"AU",
    "sg:address":"282 Boundary Rd",
    "sg:city":"Braeside",
    "sg:classifiers":[
        {
            "category":"Autos & Motor Vehicles",
            "subcategory":"Automobile Sales",
            "type":"Retail Goods"
        }
    ],
    "sg:phone":"+61 3 9580 6000",
    "sg:postcode":"3195",
    "sg:province":"VIC",
    "sg:tags":[
        "car",
        "used"
    ],
    "wof:name":"F100 World",
    "wof:placetype":"venue"
},
  "geometry": {"coordinates":[145.10926818900001,-37.9874992371],"type":"Point"}
}