{
  "type": "Feature",
  "properties": {
    "iso:country":"AU",
    "sg:address":"PO Box 228",
    "sg:city":"Chermside South",
    "sg:classifiers":[
        {
            "category":"Professional",
            "subcategory":"Business Services",
            "type":"Services"
        }
    ],
    "sg:phone":"+61 7 3009 9790",
    "sg:postcode":"4032",
    "sg:province":"QLD",
    "sg:tags":[
        "processing",
        "word"
    ],
    "wof:name":"Notarius Transcription Services",
    "wof:placetype":"venue"
},
  "geometry": {"coordinates":[153.03128100000001,-27.39168],"type":"Point"}
}