{
  "type": "Feature",
  "properties": {
    "addr:full":"Shop 2/ 99 High St Hastings VIC 3915",
    "addr:housenumber":"shop 2 / 99",
    "addr:postcode":"3915",
    "addr:street":"High St",
    "iso:country":"AU",
    "sg:address":"Shop 2/ 99 High St",
    "sg:city":"Hastings",
    "sg:classifiers":[
        {
            "category":"Insurance",
            "subcategory":"Insurance Agent",
            "type":"Services"
        }
    ],
    "sg:phone":"+61 3 5979 2757",
    "sg:postcode":"3915",
    "sg:province":"VIC",
    "sg:tags":[
        "broker"
    ],
    "wof:name":"Westhaven Insurance Consultants",
    "wof:placetype":"venue"
},
  "geometry": {"coordinates":[145.190307617,-38.3075714111],"type":"Point"}
}