{
  "type": "Feature",
  "properties": {
    "iso:country":"AU",
    "sg:address":"9 Hodgson Way",
    "sg:city":"Kewdale",
    "sg:classifiers":[
        {
            "category":"Building & Trades",
            "subcategory":"Plumbing",
            "type":"Services"
        }
    ],
    "sg:phone":"+61 8 9352 9900",
    "sg:postcode":"6105",
    "sg:province":"WA",
    "sg:tags":[
        "equipment",
        "valves"
    ],
    "sg:website":"http://www.geographe-energy.com.au",
    "wof:name":"Geographe Energy",
    "wof:placetype":"venue"
},
  "geometry": {"coordinates":[115.950256348,-31.9759407043],"type":"Point"}
}