{
  "type": "Feature",
  "properties": {
    "iso:country":"AU",
    "sg:address":"Suites 3 & 4, 92 Blackwall Rd",
    "sg:city":"Woy Woy",
    "sg:classifiers":[
        {
            "category":"Professional",
            "subcategory":"Employment Agencies",
            "type":"Services"
        }
    ],
    "sg:phone":"+61 2 4344 4262",
    "sg:postcode":"2256",
    "sg:province":"NSW",
    "sg:tags":[
        "provider",
        "internet"
    ],
    "wof:name":"Milestone-Belanova Pty Ltd",
    "wof:placetype":"venue"
},
  "geometry": {"coordinates":[151.32586669899999,-33.4880523682],"type":"Point"}
}