{
  "type": "Feature",
  "properties": {
    "addr:full":"Fcty 9 83 Canterbury Rd Kilsyth VIC 3137",
    "addr:housenumber":"83",
    "addr:postcode":"3137",
    "addr:street":"Canterbury Rd",
    "iso:country":"AU",
    "sg:address":"Fcty 9 83 Canterbury Rd",
    "sg:city":"Kilsyth",
    "sg:classifiers":[
        {
            "category":"Food & Beverages",
            "subcategory":"Bakery",
            "type":"Retail Goods"
        }
    ],
    "sg:phone":"+61 3 9728 6011",
    "sg:postcode":"3137",
    "sg:province":"VIC",
    "sg:tags":[
        "baker"
    ],
    "wof:name":"Blue Lotus Foods Pty Ltd",
    "wof:placetype":"venue"
},
  "geometry": {"coordinates":[145.323120117,-37.8162651062],"type":"Point"}
}