{
  "type": "Feature",
  "properties": {
    "addr:full":"Memorial Drv Forster NSW 2428",
    "addr:postcode":"2428",
    "addr:street":"Memorial Drv",
    "iso:country":"AU",
    "sg:address":"Memorial Drv",
    "sg:city":"Forster",
    "sg:classifiers":[
        {
            "category":"Fast Food",
            "type":"Food & Drink"
        }
    ],
    "sg:phone":"+61 2 6555 6411",
    "sg:postcode":"2428",
    "sg:province":"NSW",
    "sg:tags":[
        "away",
        "take"
    ],
    "wof:name":"Bella Bellissimo",
    "wof:placetype":"venue"
},
  "geometry": {"coordinates":[152.510864,-32.180775],"type":"Point"}
}