{
  "type": "Feature",
  "properties": {
    "addr:full":"Suite 205, 6 Clarke St Crows Nest NSW 2065",
    "addr:housenumber":"6",
    "addr:postcode":"2065",
    "addr:street":"Clarke St",
    "iso:country":"AU",
    "sg:address":"Suite 205, 6 Clarke St",
    "sg:city":"Crows Nest",
    "sg:classifiers":[
        {
            "category":"Professional",
            "subcategory":"Art Services",
            "type":"Services"
        }
    ],
    "sg:phone":"+61 2 9966 5533",
    "sg:postcode":"2065",
    "sg:province":"NSW",
    "sg:tags":[
        "graphic",
        "designer"
    ],
    "wof:name":"Steve Morato",
    "wof:placetype":"venue"
},
  "geometry": {"coordinates":[151.200073242,-33.8259048462],"type":"Point"}
}