{
  "type": "Feature",
  "properties": {
    "iso:country":"AU",
    "sg:address":"8 Fernleigh Dr",
    "sg:city":"Mooroolbark",
    "sg:classifiers":[
        {
            "category":"Building & Trades",
            "subcategory":"Construction",
            "type":"Services"
        }
    ],
    "sg:phone":"+61 417 318 403",
    "sg:postcode":"3138",
    "sg:province":"VIC",
    "sg:tags":[
        "installation",
        "air conditioning"
    ],
    "wof:name":"Mendaria",
    "wof:placetype":"venue"
},
  "geometry": {"coordinates":[145.33363342300001,-37.7959747314],"type":"Point"}
}