{
  "type": "Feature",
  "properties": {
    "iso:country":"AU",
    "sg:address":"47 Furlong Rd",
    "sg:city":"Sunshine",
    "sg:classifiers":[
        {
            "category":"Education",
            "subcategory":"Kindergarten",
            "type":"Public Place"
        }
    ],
    "sg:phone":"+61 3 9311 7613",
    "sg:postcode":"3020",
    "sg:province":"VIC",
    "sg:tags":[
        "pre-schools"
    ],
    "wof:name":"Dorothy Carlton Pre-School Centre",
    "wof:placetype":"venue"
},
  "geometry": {"coordinates":[144.826049805,-37.7621192932],"type":"Point"}
}