{
  "type": "Feature",
  "properties": {
    "iso:country":"AU",
    "sg:address":"11 Owen Rd",
    "sg:city":"Kelmscott",
    "sg:classifiers":[
        {
            "category":"Autos & Motor Vehicles",
            "subcategory":"Auto Supplies",
            "type":"Retail Goods"
        }
    ],
    "sg:phone":"+61 8 9497 2230",
    "sg:postcode":"6111",
    "sg:province":"WA",
    "sg:tags":[
        "wheel",
        "four",
        "equipment",
        "drive",
        "accessory"
    ],
    "wof:name":"Armadale Exhausts & Towbars",
    "wof:placetype":"venue"
},
  "geometry": {"coordinates":[116.008712769,-32.1347618103],"type":"Point"}
}