{
  "type": "Feature",
  "properties": {
    "addr:full":"15/ 29 Cinderella Drv Springwood QLD 4127",
    "addr:housenumber":"15 / 29",
    "addr:postcode":"4127",
    "addr:street":"Cinderella Drv",
    "iso:country":"AU",
    "sg:address":"15/ 29 Cinderella Drv",
    "sg:city":"Springwood",
    "sg:classifiers":[
        {
            "category":"Banks & Credit Unions",
            "subcategory":"Financial Services",
            "type":"Services"
        }
    ],
    "sg:phone":"+61 7 3209 1766",
    "sg:postcode":"4127",
    "sg:province":"QLD",
    "sg:tags":[
        "planning"
    ],
    "wof:name":"Shane Reinke & Associates Pty Ltd",
    "wof:placetype":"venue"
},
  "geometry": {"coordinates":[153.126556397,-27.6122226715],"type":"Point"}
}