{
  "type": "Feature",
  "properties": {
    "addr:full":"433 Scarborough Beach Rd Osborne Park WA 6017",
    "addr:housenumber":"433",
    "addr:postcode":"6017",
    "addr:street":"Scarborough Beach Rd",
    "iso:country":"AU",
    "sg:address":"433 Scarborough Beach Rd",
    "sg:city":"Osborne Park",
    "sg:classifiers":[
        {
            "category":"Shopping",
            "subcategory":"Stationery & Office Supplies",
            "type":"Retail Goods"
        }
    ],
    "sg:phone":"+61 1300 138 870",
    "sg:postcode":"6017",
    "sg:province":"WA",
    "sg:tags":[
        "equipment",
        "facsimile"
    ],
    "wof:name":"Lanier (Australia) Pty Ltd",
    "wof:placetype":"venue"
},
  "geometry": {"coordinates":[115.811500549,-31.9080982208],"type":"Point"}
}