{
  "type": "Feature",
  "properties": {
    "addr:full":"213 Lygon St Carlton VIC 3053",
    "addr:housenumber":"213",
    "addr:postcode":"3053",
    "addr:street":"Lygon St",
    "iso:country":"AU",
    "sg:address":"213 Lygon St",
    "sg:city":"Carlton",
    "sg:classifiers":[
        {
            "category":"Shopping",
            "type":"Retail Goods"
        }
    ],
    "sg:phone":"+61 3 9349 1090",
    "sg:postcode":"3053",
    "sg:province":"VIC",
    "sg:tags":[
        "new age",
        "product"
    ],
    "wof:name":"Crystal Heart",
    "wof:placetype":"venue"
},
  "geometry": {"coordinates":[144.96742248499999,-37.798866272],"type":"Point"}
}