{
  "type": "Feature",
  "properties": {
    "addr:full":"130 Sutton St Cootamundra NSW 2590",
    "addr:housenumber":"130",
    "addr:postcode":"2590",
    "addr:street":"Sutton St",
    "iso:country":"AU",
    "sg:address":"130 Sutton St",
    "sg:city":"Cootamundra",
    "sg:classifiers":[
        {
            "category":"Retail",
            "subcategory":"Auto Repair",
            "type":"Services"
        }
    ],
    "sg:phone":"+61 2 6942 3140",
    "sg:postcode":"2590",
    "sg:province":"NSW",
    "sg:tags":[
        "repairer",
        "motor",
        "engineer"
    ],
    "wof:name":"Kevin Jarrett's Service Centre",
    "wof:placetype":"venue"
},
  "geometry": {"coordinates":[148.02833557100001,-34.640209198],"type":"Point"}
}