{
  "type": "Feature",
  "properties": {
    "addr:full":"Churinga Village 534 Mt Dandenong Rd Kilsyth South VIC 3137",
    "addr:housenumber":"534",
    "addr:postcode":"3137",
    "addr:street":"Mt Dandenong Rd",
    "iso:country":"AU",
    "sg:address":"Churinga Village 534 Mt Dandenong Rd",
    "sg:city":"Kilsyth South",
    "sg:classifiers":[
        {
            "category":"Personal",
            "subcategory":"Beauty Salon",
            "type":"Services"
        }
    ],
    "sg:phone":"+61 3 9723 5247",
    "sg:postcode":"3137",
    "sg:province":"VIC",
    "sg:tags":[
        "hairdresser"
    ],
    "wof:name":"Churinga Village Hair Studio",
    "wof:placetype":"venue"
},
  "geometry": {"coordinates":[145.311767578,-37.8024024963],"type":"Point"}
}