{
  "type": "Feature",
  "properties": {
    "addr:full":"Williams Crs Streaky Bay SA 5680",
    "addr:postcode":"5680",
    "addr:street":"Williams Crs",
    "iso:country":"AU",
    "sg:address":"Williams Crs",
    "sg:city":"Streaky Bay",
    "sg:classifiers":[
        {
            "category":"Health Services",
            "subcategory":"Doctor",
            "type":"Services"
        }
    ],
    "sg:phone":"+61 8 8626 1072",
    "sg:postcode":"5680",
    "sg:province":"SA",
    "sg:tags":[
        "medical",
        "practitioner"
    ],
    "wof:name":"Streaky Bay Medical Clinic",
    "wof:placetype":"venue"
},
  "geometry": {"coordinates":[134.21116638199999,-32.7962875366],"type":"Point"}
}