{
  "type": "Feature",
  "properties": {
    "addr:full":"1 Finley Ave Gosford East NSW 2250",
    "addr:housenumber":"1",
    "addr:postcode":"2250",
    "addr:street":"Finley Ave",
    "iso:country":"AU",
    "sg:address":"1 Finley Ave",
    "sg:city":"Gosford East",
    "sg:classifiers":[
        {
            "category":"Building & Trades",
            "subcategory":"Construction",
            "type":"Services"
        }
    ],
    "sg:phone":"+61 416 293 509",
    "sg:postcode":"2250",
    "sg:province":"NSW",
    "sg:tags":[
        "plasterboard",
        "plasterer",
        "fixer"
    ],
    "wof:name":"Steve Warwick Plastering",
    "wof:placetype":"venue"
},
  "geometry": {"coordinates":[151.35731506400001,-33.4292182922],"type":"Point"}
}