{
  "type": "Feature",
  "properties": {
    "addr:full":"Shp3/ 2 Coral St Urangan QLD 4655",
    "addr:housenumber":"2",
    "addr:postcode":"4655",
    "addr:street":"Coral St",
    "iso:country":"AU",
    "sg:address":"Shp3/ 2 Coral St",
    "sg:city":"Urangan",
    "sg:classifiers":[
        {
            "category":"Travel",
            "subcategory":"Travel Agent",
            "type":"Entertainment"
        }
    ],
    "sg:phone":"+61 7 4125 6295",
    "sg:postcode":"4655",
    "sg:province":"QLD",
    "sg:tags":[
        "tour",
        "holiday",
        "adventure"
    ],
    "wof:name":"Footprints On Fraser",
    "wof:placetype":"venue"
},
  "geometry": {"coordinates":[152.89790300000001,-25.285044],"type":"Point"}
}