{
  "type": "Feature",
  "properties": {
    "iso:country":"AU",
    "sg:address":"Unit 7/ 49 Derby St",
    "sg:city":"Lidcombe",
    "sg:classifiers":[
        {
            "category":"Building & Trades",
            "subcategory":"Construction",
            "type":"Services"
        }
    ],
    "sg:phone":"+61 2 9748 2877",
    "sg:postcode":"2141",
    "sg:province":"NSW",
    "sg:tags":[
        "window",
        "tinting"
    ],
    "wof:name":"Sol-Ace Window Tinting",
    "wof:placetype":"venue"
},
  "geometry": {"coordinates":[151.04904174800001,-33.8382797241],"type":"Point"}
}