{
  "type": "Feature",
  "properties": {
    "addr:full":"66 Wallendoon St Cootamundra NSW 2590",
    "addr:housenumber":"66",
    "addr:postcode":"2590",
    "addr:street":"Wallendoon St",
    "iso:country":"AU",
    "sg:address":"66 Wallendoon St",
    "sg:city":"Cootamundra",
    "sg:classifiers":[
        {
            "category":"Travel",
            "subcategory":"Hotels & Motels",
            "type":"Entertainment"
        }
    ],
    "sg:phone":"+61 2 6942 2688",
    "sg:postcode":"2590",
    "sg:province":"NSW",
    "wof:name":"Wattle Tree Motel",
    "wof:placetype":"venue"
},
  "geometry": {"coordinates":[148.02792358400001,-34.6411056519],"type":"Point"}
}