{
  "type": "Feature",
  "properties": {
    "addr:full":"Lvl 5/ 20 Wharf St Brisbane QLD 4000",
    "addr:housenumber":"/ 20",
    "addr:postcode":"4000",
    "addr:street":"Wharf St",
    "iso:country":"AU",
    "sg:address":"Lvl 5/ 20 Wharf St",
    "sg:city":"Brisbane",
    "sg:classifiers":[
        {
            "category":"Professional",
            "subcategory":"Employment Agencies",
            "type":"Services"
        }
    ],
    "sg:phone":"+61 7 3224 1900",
    "sg:postcode":"4000",
    "sg:province":"QLD",
    "sg:tags":[
        "broker",
        "custom"
    ],
    "wof:name":"Global Logistics Management",
    "wof:placetype":"venue"
},
  "geometry": {"coordinates":[153.029907227,-27.4654884338],"type":"Point"}
}