{
  "type": "Feature",
  "properties": {
    "iso:country":"AU",
    "sg:address":"5 Dalgangal Rd",
    "sg:city":"Gayndah",
    "sg:classifiers":[
        {
            "category":"Professional",
            "type":"Services"
        }
    ],
    "sg:phone":"+61 7 4161 1444",
    "sg:postcode":"4625",
    "sg:province":"QLD",
    "sg:tags":[
        "transport"
    ],
    "wof:name":"Gayndah Transport Services",
    "wof:placetype":"venue"
},
  "geometry": {"coordinates":[151.58291600000001,-25.542709],"type":"Point"}
}