{
  "type": "Feature",
  "properties": {
    "addr:full":"22 Hutchinson St Niddrie VIC 3042",
    "addr:housenumber":"22",
    "addr:postcode":"3042",
    "addr:street":"Hutchinson St",
    "iso:country":"AU",
    "sg:address":"22 Hutchinson St",
    "sg:city":"Niddrie",
    "sg:classifiers":[
        {
            "category":"Organizations",
            "subcategory":"Labor Organization",
            "type":"Services"
        }
    ],
    "sg:phone":"+61 409 257 518",
    "sg:postcode":"3042",
    "sg:province":"VIC",
    "sg:tags":[
        "pattern",
        "clothing"
    ],
    "wof:name":"Markit Apparel Online",
    "wof:placetype":"venue"
},
  "geometry": {"coordinates":[144.88418579099999,-37.7383041382],"type":"Point"}
}