{
  "type": "Feature",
  "properties": {
    "addr:full":"26 Hoffman St McDowall QLD 4053",
    "addr:housenumber":"26",
    "addr:postcode":"4053",
    "addr:street":"Hoffman St",
    "iso:country":"AU",
    "sg:address":"26 Hoffman St",
    "sg:city":"McDowall",
    "sg:classifiers":[
        {
            "category":"Sports & Exercise",
            "subcategory":"Gym",
            "type":"Entertainment"
        }
    ],
    "sg:phone":"+61 7 3353 2536",
    "sg:postcode":"4053",
    "sg:province":"QLD",
    "sg:tags":[
        "health",
        "fitness"
    ],
    "wof:name":"Fitness Advisory Services",
    "wof:placetype":"venue"
},
  "geometry": {"coordinates":[152.997192383,-27.3828601837],"type":"Point"}
}