{
  "type": "Feature",
  "properties": {
    "addr:full":"3/ 63 Winnellie Rd Winnellie NT 0820",
    "addr:housenumber":"/ 63",
    "addr:postcode":"nt 0820",
    "addr:street":"Winnellie Rd",
    "iso:country":"AU",
    "sg:address":"3/ 63 Winnellie Rd",
    "sg:city":"Winnellie",
    "sg:classifiers":[
        {
            "category":"Organizations",
            "subcategory":"Labor Organization",
            "type":"Services"
        }
    ],
    "sg:phone":"+61 8 8947 2455",
    "sg:postcode":"0820",
    "sg:province":"NT",
    "sg:tags":[
        "union"
    ],
    "wof:name":"Australian Services Union",
    "wof:placetype":"venue"
},
  "geometry": {"coordinates":[130.87991332999999,-12.4264888763],"type":"Point"}
}