{
  "type": "Feature",
  "properties": {
    "addr:full":"Shp 10/ 1 Portico Pde Toongabbie NSW 2146",
    "addr:housenumber":"10 / 1",
    "addr:postcode":"2146",
    "addr:street":"Portico Pde",
    "iso:country":"AU",
    "sg:address":"Shp 10/ 1 Portico Pde",
    "sg:city":"Toongabbie",
    "sg:classifiers":[
        {
            "category":"Personal",
            "subcategory":"Beauty Salon",
            "type":"Services"
        }
    ],
    "sg:phone":"+61 2 9896 0069",
    "sg:postcode":"2146",
    "sg:province":"NSW",
    "sg:tags":[
        "hairdresser"
    ],
    "wof:name":"Kim's Hairum",
    "wof:placetype":"venue"
},
  "geometry": {"coordinates":[150.951171875,-33.7883720398],"type":"Point"}
}