{
  "type": "Feature",
  "properties": {
    "addr:full":"No 2 Products Berth off Tom Thumb Rd Port Kembla NSW 2505",
    "addr:housenumber":"berth",
    "addr:postcode":"2505",
    "addr:street":"Thumb Rd",
    "iso:country":"AU",
    "sg:address":"No 2 Products Berth off Tom Thumb Rd",
    "sg:city":"Port Kembla",
    "sg:classifiers":[
        {
            "category":"Professional",
            "type":"Services"
        }
    ],
    "sg:phone":"+61 2 4275 4533",
    "sg:postcode":"2505",
    "sg:province":"NSW",
    "sg:tags":[
        "transport"
    ],
    "wof:name":"Toll Stevedoring",
    "wof:placetype":"venue"
},
  "geometry": {"coordinates":[150.89544699999999,-34.449104],"type":"Point"}
}