{
  "type": "Feature",
  "properties": {
    "addr:full":"82 Edward St Tamworth NSW 2340",
    "addr:housenumber":"82",
    "addr:postcode":"2340",
    "addr:street":"Edward St",
    "iso:country":"AU",
    "sg:address":"82 Edward St",
    "sg:city":"Tamworth",
    "sg:classifiers":[
        {
            "category":"Building & Trades",
            "subcategory":"Cleaning & Sanitation",
            "type":"Services"
        }
    ],
    "sg:phone":"+61 2 6765 4750",
    "sg:postcode":"2340",
    "sg:province":"NSW",
    "sg:tags":[
        "cleaner",
        "repairer",
        "roof"
    ],
    "wof:name":"Tamworth Roof Gutter Cleaning Specialists",
    "wof:placetype":"venue"
},
  "geometry": {"coordinates":[150.91653442399999,-31.120092392],"type":"Point"}
}