{
  "type": "Feature",
  "properties": {
    "addr:full":"345 Doncaster Rd Balwyn North VIC 3104",
    "addr:housenumber":"345",
    "addr:postcode":"3104",
    "addr:street":"Doncaster Rd",
    "iso:country":"AU",
    "sg:address":"345 Doncaster Rd",
    "sg:city":"Balwyn North",
    "sg:classifiers":[
        {
            "category":"Health Services",
            "subcategory":"Doctor",
            "type":"Services"
        }
    ],
    "sg:phone":"+61 3 9857 8947",
    "sg:postcode":"3104",
    "sg:province":"VIC",
    "sg:tags":[
        "medical",
        "practitioner"
    ],
    "wof:name":"Goh T T",
    "wof:placetype":"venue"
},
  "geometry": {"coordinates":[145.09765625,-37.7904014587],"type":"Point"}
}