{
  "type": "Feature",
  "properties": {
    "iso:country":"AU",
    "sg:address":"Turner Drv",
    "sg:city":"West Lakes",
    "sg:classifiers":[
        {
            "category":"Travel",
            "subcategory":"Hotels & Motels",
            "type":"Entertainment"
        }
    ],
    "sg:phone":"+61 8 8244 3244",
    "sg:postcode":"5021",
    "sg:province":"SA",
    "sg:tags":[
        "pub"
    ],
    "wof:name":"Crows Tavern",
    "wof:placetype":"venue"
},
  "geometry": {"coordinates":[138.493774414,-34.8777122498],"type":"Point"}
}