{
  "type": "Feature",
  "properties": {
    "iso:country":"AU",
    "sg:address":"13 Neptune St",
    "sg:city":"Revesby",
    "sg:classifiers":[
        {
            "category":"Social Services",
            "subcategory":"Retirement Home",
            "type":"Services"
        }
    ],
    "sg:phone":"+61 2 9771 2196",
    "sg:postcode":"2212",
    "sg:province":"NSW",
    "sg:tags":[
        "village"
    ],
    "wof:name":"St Vincent De Paul Society Aged Homes",
    "wof:placetype":"venue"
},
  "geometry": {"coordinates":[151.01997399999999,-33.963581],"type":"Point"}
}