{
  "type": "Feature",
  "properties": {
    "addr:full":"Stonyfell Road, Stonyfell SA 5066",
    "addr:postcode":"5066",
    "addr:street":"Stonyfell Road",
    "iso:country":"AU",
    "sg:address":"Stonyfell Road,",
    "sg:city":"Stonyfell",
    "sg:classifiers":[
        {
            "category":"Education",
            "subcategory":"School",
            "type":"Public Place"
        }
    ],
    "sg:phone":"+61 8 8334 2215",
    "sg:postcode":"5066",
    "sg:province":"SA",
    "sg:tags":[
        "girl"
    ],
    "wof:name":"St Peters Collegiate Girls&#039; School",
    "wof:placetype":"venue"
},
  "geometry": {"coordinates":[138.67071533199999,-34.9293708801],"type":"Point"}
}