{
  "type": "Feature",
  "properties": {
    "iso:country":"AU",
    "sg:address":"1A Richardson Pl",
    "sg:city":"North Ryde",
    "sg:classifiers":[
        {
            "category":"Building & Trades",
            "subcategory":"Construction",
            "type":"Services"
        }
    ],
    "sg:phone":"+61 2 9888 2000",
    "sg:postcode":"2113",
    "sg:province":"NSW",
    "sg:tags":[
        "industrial",
        "commercial",
        "air conditioning"
    ],
    "wof:name":"B L Walker Air Conditioning",
    "wof:placetype":"venue"
},
  "geometry": {"coordinates":[151.14454650900001,-33.7969055176],"type":"Point"}
}