{
  "type": "Feature",
  "properties": {
    "addr:full":"89 Meridian Drv Mullaloo WA 6027",
    "addr:housenumber":"89",
    "addr:postcode":"6027",
    "addr:street":"Meridian Drv",
    "iso:country":"AU",
    "sg:address":"89 Meridian Drv",
    "sg:city":"Mullaloo",
    "sg:classifiers":[
        {
            "category":"Retail",
            "subcategory":"Driving School",
            "type":"Services"
        }
    ],
    "sg:phone":"+61 8 9307 9637",
    "sg:postcode":"6027",
    "sg:province":"WA",
    "wof:name":"Autotorque Driving Academy",
    "wof:placetype":"venue"
},
  "geometry": {"coordinates":[115.750061035,-31.7773151398],"type":"Point"}
}