{
  "type": "Feature",
  "properties": {
    "addr:full":"5 Darcy La Kalgoorlie WA 6430",
    "addr:housenumber":"5",
    "addr:postcode":"6430",
    "addr:street":"Darcy La",
    "iso:country":"AU",
    "sg:address":"5 Darcy La",
    "sg:city":"Kalgoorlie",
    "sg:classifiers":[
        {
            "category":"Autos & Motor Vehicles",
            "subcategory":"Automobile Sales",
            "type":"Retail Goods"
        }
    ],
    "sg:phone":"+61 8 9091 4111",
    "sg:postcode":"6430",
    "sg:province":"WA",
    "sg:tags":[
        "equipment",
        "trailer"
    ],
    "wof:name":"Statewide Bearings",
    "wof:placetype":"venue"
},
  "geometry": {"coordinates":[121.436141968,-30.7786922455],"type":"Point"}
}