{
  "type": "Feature",
  "properties": {
    "addr:full":"40 Sydney Rd Manly NSW 2095",
    "addr:housenumber":"40",
    "addr:postcode":"2095",
    "addr:street":"Sydney Rd",
    "iso:country":"AU",
    "sg:address":"40 Sydney Rd",
    "sg:city":"Manly",
    "sg:classifiers":[
        {
            "category":"Shopping",
            "subcategory":"Mobile Phones",
            "type":"Retail Goods"
        }
    ],
    "sg:phone":"+61 2 9934 4111",
    "sg:postcode":"2095",
    "sg:province":"NSW",
    "sg:tags":[
        "telephone",
        "accessory"
    ],
    "wof:name":"Telstra Shops",
    "wof:placetype":"venue"
},
  "geometry": {"coordinates":[151.2862854,-33.7969474792],"type":"Point"}
}