{
  "type": "Feature",
  "properties": {
    "iso:country":"AU",
    "sg:address":"Level 11, 24 Mitchell St",
    "sg:city":"Darwin",
    "sg:classifiers":[
        {
            "category":"Professional",
            "subcategory":"Accounting & Tax Preparation",
            "type":"Services"
        }
    ],
    "sg:phone":"+61 8 8980 3000",
    "sg:postcode":"0800",
    "sg:province":"NT",
    "sg:tags":[
        "consultant",
        "taxation"
    ],
    "wof:name":"Deloitte",
    "wof:placetype":"venue"
},
  "geometry": {"coordinates":[130.84068298299999,-12.4598493576],"type":"Point"}
}