{
  "type": "Feature",
  "properties": {
    "addr:full":"2 Rose St Derby WA 6728",
    "addr:housenumber":"2",
    "addr:postcode":"6728",
    "addr:street":"Rose St",
    "iso:country":"AU",
    "sg:address":"2 Rose St",
    "sg:city":"Derby",
    "sg:classifiers":[
        {
            "category":"Professional",
            "subcategory":"Printing & Photocopies",
            "type":"Services"
        }
    ],
    "sg:phone":"+61 8 9193 1878",
    "sg:postcode":"6728",
    "sg:province":"WA",
    "sg:tags":[
        "trophy"
    ],
    "wof:name":"Kimberley Trophies & Engraving",
    "wof:placetype":"venue"
},
  "geometry": {"coordinates":[123.633071899,-17.3133468628],"type":"Point"}
}