{
  "type": "Feature",
  "properties": {
    "iso:country":"AU",
    "sg:address":"\"Loloma\" Surveyors Creek Rd",
    "sg:city":"Woolbrook",
    "sg:classifiers":[
        {
            "category":"Building & Trades",
            "subcategory":"Construction",
            "type":"Services"
        }
    ],
    "sg:phone":"+61 2 6777 5883",
    "sg:postcode":"2354",
    "sg:province":"NSW",
    "sg:tags":[
        "tennis court",
        "repair"
    ],
    "wof:name":"Master Court Concrete Construction",
    "wof:placetype":"venue"
},
  "geometry": {"coordinates":[151.34852600100001,-30.9729785919],"type":"Point"}
}