{
  "type": "Feature",
  "properties": {
    "addr:full":"6 Mecklem St Strathpine QLD 4500",
    "addr:housenumber":"6",
    "addr:postcode":"4500",
    "addr:street":"Mecklem St",
    "iso:country":"AU",
    "sg:address":"6 Mecklem St",
    "sg:city":"Strathpine",
    "sg:classifiers":[
        {
            "category":"Professional",
            "subcategory":"Business Services",
            "type":"Services"
        }
    ],
    "sg:phone":"+61 7 3881 2033",
    "sg:postcode":"4500",
    "sg:province":"QLD",
    "sg:tags":[
        "drafting"
    ],
    "wof:name":"Strathpine Design & Drafting Centre",
    "wof:placetype":"venue"
},
  "geometry": {"coordinates":[152.991577148,-27.3105926514],"type":"Point"}
}