{
  "type": "Feature",
  "properties": {
    "addr:full":"314 Pascoe Vale Rd Essendon VIC 3040",
    "addr:housenumber":"314",
    "addr:postcode":"3040",
    "addr:street":"Pascoe Vale Rd",
    "iso:country":"AU",
    "sg:address":"314 Pascoe Vale Rd",
    "sg:city":"Essendon",
    "sg:classifiers":[
        {
            "category":"Restaurant",
            "type":"Food & Drink"
        }
    ],
    "sg:phone":"+61 3 9379 3937",
    "sg:postcode":"3040",
    "sg:province":"VIC",
    "wof:name":"Di Roma",
    "wof:placetype":"venue"
},
  "geometry": {"coordinates":[144.926055908,-37.7462272644],"type":"Point"}
}