{
  "type": "Feature",
  "properties": {
    "addr:full":"26 Walworth St Tinana QLD 4650",
    "addr:housenumber":"26",
    "addr:postcode":"4650",
    "addr:street":"Walworth St",
    "iso:country":"AU",
    "sg:address":"26 Walworth St",
    "sg:city":"Tinana",
    "sg:classifiers":[
        {
            "category":"Education",
            "subcategory":"Kindergarten",
            "type":"Public Place"
        }
    ],
    "sg:phone":"+61 7 4122 3608",
    "sg:postcode":"4650",
    "sg:province":"QLD",
    "sg:tags":[
        "pre-schools"
    ],
    "wof:name":"Tinana Kindergarden & Preschool Association",
    "wof:placetype":"venue"
},
  "geometry": {"coordinates":[152.67222599999999,-25.553259],"type":"Point"}
}