{
  "type": "Feature",
  "properties": {
    "addr:full":"Unit 6/ 42 Meacher St Mt Druitt NSW 2770",
    "addr:postcode":"2770",
    "addr:street":"42 Meacher St Mt",
    "iso:country":"AU",
    "sg:address":"Unit 6/ 42 Meacher St",
    "sg:city":"Mt Druitt",
    "sg:classifiers":[
        {
            "category":"Building & Trades",
            "subcategory":"Landscaping Services",
            "type":"Services"
        }
    ],
    "sg:phone":"+61 421 810 514",
    "sg:postcode":"2770",
    "sg:province":"NSW",
    "sg:tags":[
        "designer",
        "landscape",
        "contractor"
    ],
    "wof:name":"Tailored Property Solutions",
    "wof:placetype":"venue"
},
  "geometry": {"coordinates":[150.82301330600001,-33.760219574],"type":"Point"}
}