{
  "type": "Feature",
  "properties": {
    "addr:full":"4 Orchard Rd Brookvale NSW 2100",
    "addr:housenumber":"4",
    "addr:postcode":"2100",
    "addr:street":"Orchard Rd",
    "iso:country":"AU",
    "sg:address":"4 Orchard Rd",
    "sg:city":"Brookvale",
    "sg:classifiers":[
        {
            "category":"Home & Garden",
            "subcategory":"Building Materials",
            "type":"Retail Goods"
        }
    ],
    "sg:phone":"+61 2 9905 4633",
    "sg:postcode":"2100",
    "sg:province":"NSW",
    "sg:tags":[
        "supply"
    ],
    "wof:name":"Hudson Building Supplies",
    "wof:placetype":"venue"
},
  "geometry": {"coordinates":[151.271942139,-33.7650985718],"type":"Point"}
}