{
  "type": "Feature",
  "properties": {
    "addr:full":"Shop 1, 46 Montgomery St Kogarah NSW 2217",
    "addr:housenumber":"shop;46",
    "addr:postcode":"2217",
    "addr:street":"Montgomery St",
    "iso:country":"AU",
    "sg:address":"Shop 1, 46 Montgomery St",
    "sg:city":"Kogarah",
    "sg:classifiers":[
        {
            "category":"Personal",
            "subcategory":"Beauty Salon",
            "type":"Services"
        }
    ],
    "sg:phone":"+61 2 9553 8241",
    "sg:postcode":"2217",
    "sg:province":"NSW",
    "sg:tags":[
        "hairdresser"
    ],
    "wof:name":"Marisa's Cutting Loose Hair Studio",
    "wof:placetype":"venue"
},
  "geometry": {"coordinates":[151.13502500000001,-33.964615],"type":"Point"}
}