{
  "type": "Feature",
  "properties": {
    "iso:country":"AU",
    "sg:address":"148 Deception Bay Rd",
    "sg:city":"Deception Bay",
    "sg:classifiers":[
        {
            "category":"Retail",
            "subcategory":"Event Space",
            "type":"Services"
        }
    ],
    "sg:phone":"+61 7 3888 5544",
    "sg:postcode":"4508",
    "sg:province":"QLD",
    "sg:tags":[
        "function",
        "organiser"
    ],
    "wof:name":"McBrides",
    "wof:placetype":"venue"
},
  "geometry": {"coordinates":[153.01828002900001,-27.1902198792],"type":"Point"}
}