{
  "type": "Feature",
  "properties": {
    "iso:country":"AU",
    "sg:address":"6 Aish Crt",
    "sg:city":"Woodcroft",
    "sg:classifiers":[
        {
            "category":"Professional",
            "subcategory":"Secretarial Services",
            "type":"Services"
        }
    ],
    "sg:phone":"+61 418 894 592",
    "sg:postcode":"5162",
    "sg:province":"SA",
    "sg:tags":[
        "typing"
    ],
    "wof:name":"Top Type Transcription & Secretarial",
    "wof:placetype":"venue"
},
  "geometry": {"coordinates":[138.555053711,-35.0990447998],"type":"Point"}
}