{
  "type": "Feature",
  "properties": {
    "addr:full":"41 Salamanca Pl Hobart TAS 7000",
    "addr:housenumber":"41",
    "addr:postcode":"7000",
    "addr:street":"Salamanca Pl",
    "iso:country":"AU",
    "sg:address":"41 Salamanca Pl",
    "sg:city":"Hobart",
    "sg:classifiers":[
        {
            "category":"Food & Beverages",
            "subcategory":"Fruits & Vegetables",
            "type":"Retail Goods"
        }
    ],
    "sg:phone":"+61 3 6223 2700",
    "sg:postcode":"7000",
    "sg:province":"TAS",
    "sg:tags":[
        "greengrocer",
        "fruiterer"
    ],
    "wof:name":"Salamanca Fruit Market",
    "wof:placetype":"venue"
},
  "geometry": {"coordinates":[147.33216857900001,-42.8868026733],"type":"Point"}
}