{
  "type": "Feature",
  "properties": {
    "addr:full":"Level 1, 463 Church St North Parramatta NSW 2151",
    "addr:housenumber":"463",
    "addr:postcode":"2151",
    "addr:street":"Church St",
    "iso:country":"AU",
    "sg:address":"Level 1, 463 Church St",
    "sg:city":"North Parramatta",
    "sg:classifiers":[
        {
            "category":"Shopping",
            "type":"Retail Goods"
        }
    ],
    "sg:phone":"+61 2 9649 8235",
    "sg:postcode":"2151",
    "sg:province":"NSW",
    "sg:tags":[
        "equipment",
        "safety",
        "accessory"
    ],
    "wof:name":"Flatlite Technology Pty Ltd",
    "wof:placetype":"venue"
},
  "geometry": {"coordinates":[151.005615234,-33.803691864],"type":"Point"}
}