{
  "type": "Feature",
  "properties": {
    "addr:full":"10 Johnson St Dubbo NSW 2830",
    "addr:housenumber":"10",
    "addr:postcode":"2830",
    "addr:street":"Johnson St",
    "iso:country":"AU",
    "sg:address":"10 Johnson St",
    "sg:city":"Dubbo",
    "sg:classifiers":[
        {
            "category":"Commercial Area",
            "type":"Public Place"
        }
    ],
    "sg:phone":"+61 418 611 197",
    "sg:postcode":"2830",
    "sg:province":"NSW",
    "sg:tags":[
        "heavy",
        "carrier"
    ],
    "wof:name":"Tippings Transport Pty Ltd",
    "wof:placetype":"venue"
},
  "geometry": {"coordinates":[148.61453247099999,-32.2325782776],"type":"Point"}
}