{
  "type": "Feature",
  "properties": {
    "addr:full":"10 Violet St Miranda NSW 2228",
    "addr:housenumber":"10",
    "addr:postcode":"2228",
    "addr:street":"Violet St Miranda",
    "iso:country":"AU",
    "sg:address":"10 Violet St",
    "sg:city":"Miranda",
    "sg:classifiers":[
        {
            "category":"Banks & Credit Unions",
            "subcategory":"Financial Services",
            "type":"Services"
        }
    ],
    "sg:phone":"+61 433 054 678",
    "sg:postcode":"2228",
    "sg:province":"NSW",
    "sg:tags":[
        "planning"
    ],
    "wof:name":"Jansam Investments",
    "wof:placetype":"venue"
},
  "geometry": {"coordinates":[151.09611511200001,-34.0261268616],"type":"Point"}
}