{
  "type": "Feature",
  "properties": {
    "iso:country":"AU",
    "sg:address":"205 Hannan St",
    "sg:city":"Kalgoorlie",
    "sg:classifiers":[
        {
            "category":"Health Services",
            "subcategory":"Health Practitioner",
            "type":"Services"
        }
    ],
    "sg:phone":"+61 8 9021 2200",
    "sg:postcode":"6430",
    "sg:province":"WA",
    "sg:tags":[
        "naturopath"
    ],
    "wof:name":"Amcal Kalgoorlie",
    "wof:placetype":"venue"
},
  "geometry": {"coordinates":[121.466636658,-30.7526016235],"type":"Point"}
}