{
  "type": "Feature",
  "properties": {
    "iso:country":"AU",
    "sg:address":"7A Wingate Ave",
    "sg:city":"Hazelmere",
    "sg:classifiers":[
        {
            "category":"Shopping",
            "subcategory":"Party Supplies",
            "type":"Retail Goods"
        }
    ],
    "sg:phone":"+61 8 9374 0653",
    "sg:postcode":"6055",
    "sg:province":"WA",
    "sg:tags":[
        "children's"
    ],
    "wof:name":"Aussie Bounce",
    "wof:placetype":"venue"
},
  "geometry": {"coordinates":[115.99633,-31.901367],"type":"Point"}
}