{
  "type": "Feature",
  "properties": {
    "addr:full":"L1, 197 Clarence St Sydney NSW 2000",
    "addr:housenumber":"197",
    "addr:postcode":"2000",
    "addr:street":"Clarence St",
    "iso:country":"AU",
    "sg:address":"L1, 197 Clarence St",
    "sg:city":"Sydney",
    "sg:classifiers":[
        {
            "category":"Professional",
            "subcategory":"Art Services",
            "type":"Services"
        }
    ],
    "sg:phone":"+61 2 9279 2287",
    "sg:postcode":"2000",
    "sg:province":"NSW",
    "sg:tags":[
        "interior",
        "designer"
    ],
    "wof:name":"Architecture Unlimited",
    "wof:placetype":"venue"
},
  "geometry": {"coordinates":[151.20523071299999,-33.8695068359],"type":"Point"}
}