{
  "type": "Feature",
  "properties": {
    "addr:full":"1/48 Garfield Road (East) Riverstone NSW 2765",
    "addr:housenumber":"/ 48",
    "addr:postcode":"2765",
    "addr:street":"Garfield Road East",
    "iso:country":"AU",
    "sg:address":"1/48 Garfield Road",
    "sg:city":"(East) Riverstone",
    "sg:classifiers":[
        {
            "category":"Real Estate",
            "subcategory":"Real Estate Agent",
            "type":"Services"
        }
    ],
    "sg:phone":"+61 2 9627 1555",
    "sg:postcode":"2765",
    "sg:province":"NSW",
    "wof:name":"Driscoll & Reid First National",
    "wof:placetype":"venue"
},
  "geometry": {"coordinates":[150.862823486,-33.6788711548],"type":"Point"}
}