{
  "type": "Feature",
  "properties": {
    "addr:full":"49 Orontes Ave Bridgewater SA 5155",
    "addr:housenumber":"49",
    "addr:postcode":"5155",
    "addr:street":"Orontes Ave",
    "iso:country":"AU",
    "sg:address":"49 Orontes Ave",
    "sg:city":"Bridgewater",
    "sg:classifiers":[
        {
            "category":"Utilities",
            "subcategory":"Electric",
            "type":"Services"
        }
    ],
    "sg:phone":"+61 8 8370 9438",
    "sg:postcode":"5155",
    "sg:province":"SA",
    "sg:tags":[
        "electrical",
        "contractor"
    ],
    "wof:name":"Engels Electrical",
    "wof:placetype":"venue"
},
  "geometry": {"coordinates":[138.767669678,-35.0124702454],"type":"Point"}
}