{
  "type": "Feature",
  "properties": {
    "iso:country":"AU",
    "sg:address":"9 Renshaw Drv",
    "sg:city":"Dubbo",
    "sg:classifiers":[
        {
            "category":"Building & Trades",
            "subcategory":"Construction",
            "type":"Services"
        }
    ],
    "sg:phone":"+61 2 6884 5532",
    "sg:postcode":"2830",
    "sg:province":"NSW",
    "sg:tags":[
        "joiner",
        "carpenter"
    ],
    "wof:name":"Burge Ian",
    "wof:placetype":"venue"
},
  "geometry": {"coordinates":[148.655349731,-32.2408103943],"type":"Point"}
}