{
  "type": "Feature",
  "properties": {
    "addr:full":"90 Soldiers Rd Jannali NSW 2226",
    "addr:housenumber":"90",
    "addr:postcode":"2226",
    "addr:street":"Soldiers Rd",
    "iso:country":"AU",
    "sg:address":"90 Soldiers Rd",
    "sg:city":"Jannali",
    "sg:classifiers":[
        {
            "category":"Social Services",
            "subcategory":"Child Care",
            "type":"Services"
        }
    ],
    "sg:phone":"+61 2 9528 2855",
    "sg:postcode":"2226",
    "sg:province":"NSW",
    "wof:name":"Djanaba Occasional Care Service",
    "wof:placetype":"venue"
},
  "geometry": {"coordinates":[151.06175231899999,-34.0175895691],"type":"Point"}
}