{
  "type": "Feature",
  "properties": {
    "iso:country":"AU",
    "sg:address":"321 Darling St",
    "sg:city":"Balmain",
    "sg:classifiers":[
        {
            "category":"Food & Beverages",
            "subcategory":"Fruits & Vegetables",
            "type":"Retail Goods"
        }
    ],
    "sg:phone":"+61 2 9810 2847",
    "sg:postcode":"2041",
    "sg:province":"NSW",
    "sg:tags":[
        "greengrocer",
        "fruiterer"
    ],
    "wof:name":"Home Shopping Fruit & Vegetables",
    "wof:placetype":"venue"
},
  "geometry": {"coordinates":[151.179855,-33.85675],"type":"Point"}
}