{
  "type": "Feature",
  "properties": {
    "iso:country":"AU",
    "sg:address":"395 Sydney Rd",
    "sg:city":"Balgowlah",
    "sg:classifiers":[
        {
            "category":"Travel",
            "subcategory":"Travel Agent",
            "type":"Entertainment"
        }
    ],
    "sg:phone":"+61 2 9949 1522",
    "sg:postcode":"2093",
    "sg:province":"NSW",
    "sg:tags":[
        "consultant"
    ],
    "wof:name":"Peninsula Travel Centre Pty Ltd",
    "wof:placetype":"venue"
},
  "geometry": {"coordinates":[151.263473511,-33.7942848206],"type":"Point"}
}