{
  "type": "Feature",
  "properties": {
    "addr:full":"52-64 Currie St Nambour QLD 4560",
    "addr:housenumber":"52-64",
    "addr:postcode":"4560",
    "addr:street":"Currie St",
    "iso:country":"AU",
    "sg:address":"52-64 Currie St",
    "sg:city":"Nambour",
    "sg:classifiers":[
        {
            "category":"Professional",
            "subcategory":"Employment Agencies",
            "type":"Services"
        }
    ],
    "sg:phone":"+61 7 5476 3189",
    "sg:postcode":"4560",
    "sg:province":"QLD",
    "wof:name":"Mission Australia",
    "wof:placetype":"venue"
},
  "geometry": {"coordinates":[152.95860290499999,-26.6258430481],"type":"Point"}
}