{
  "type": "Feature",
  "properties": {
    "addr:full":"13 Bank St Cobram NSW 3644",
    "addr:housenumber":"13",
    "addr:postcode":"3644",
    "addr:street":"Bank St",
    "iso:country":"AU",
    "sg:address":"13 Bank St",
    "sg:city":"Cobram",
    "sg:classifiers":[
        {
            "category":"Health Services",
            "subcategory":"Chiropractor",
            "type":"Services"
        }
    ],
    "sg:phone":"+61 3 5872 1942",
    "sg:postcode":"3644",
    "sg:province":"NSW",
    "wof:name":"Goulburn Valley Chiropractic Clinic",
    "wof:placetype":"venue"
},
  "geometry": {"coordinates":[145.65017700199999,-35.9199829102],"type":"Point"}
}