{
  "type": "Feature",
  "properties": {
    "iso:country":"AU",
    "sg:address":"Lot 206 Gordon Rd",
    "sg:city":"Mandurah",
    "sg:classifiers":[
        {
            "category":"Building & Trades",
            "subcategory":"Construction",
            "type":"Services"
        }
    ],
    "sg:phone":"+61 412 160 454",
    "sg:postcode":"6210",
    "sg:province":"WA",
    "sg:tags":[
        "earth",
        "excavating",
        "moving",
        "contractor"
    ],
    "wof:name":"Ashby Earthmoving",
    "wof:placetype":"venue"
},
  "geometry": {"coordinates":[115.761459,-32.510529],"type":"Point"}
}