{
  "type": "Feature",
  "properties": {
    "addr:full":"3 Williamsons Rd Doncaster VIC 3108",
    "addr:housenumber":"3",
    "addr:postcode":"3108",
    "addr:street":"Williamsons Rd",
    "iso:country":"AU",
    "sg:address":"3 Williamsons Rd",
    "sg:city":"Doncaster",
    "sg:classifiers":[
        {
            "category":"Health Services",
            "subcategory":"Health Practitioner",
            "type":"Services"
        }
    ],
    "sg:phone":"+61 3 9848 3344",
    "sg:postcode":"3108",
    "sg:province":"VIC",
    "sg:tags":[
        "hypnotherapy"
    ],
    "wof:name":"Bruckner Helen",
    "wof:placetype":"venue"
},
  "geometry": {"coordinates":[145.124465942,-37.7865257263],"type":"Point"}
}