{
  "type": "Feature",
  "properties": {
    "addr:full":"Pacific Hwy Coffs Harbour NSW 2450",
    "addr:postcode":"2450",
    "addr:street":"Pacific Hwy",
    "iso:country":"AU",
    "sg:address":"Pacific Hwy",
    "sg:city":"Coffs Harbour",
    "sg:classifiers":[
        {
            "category":"Autos & Motor Vehicles",
            "subcategory":"Fuel & Gas Station",
            "type":"Retail Goods"
        }
    ],
    "sg:phone":"+61 2 6652 1998",
    "sg:postcode":"2450",
    "sg:province":"NSW",
    "wof:name":"Caltex Tourist Centre",
    "wof:placetype":"venue"
},
  "geometry": {"coordinates":[153.114304,-30.295885],"type":"Point"}
}