{
  "type": "Feature",
  "properties": {
    "addr:full":"Rear 28 The Boulevard Malvern East VIC 3145",
    "addr:housenumber":"28",
    "addr:postcode":"3145",
    "addr:street":"The Boulevard",
    "iso:country":"AU",
    "sg:address":"Rear 28",
    "sg:city":"The Boulevard Malvern East",
    "sg:classifiers":[
        {
            "category":"Professional",
            "subcategory":"Art Services",
            "type":"Services"
        }
    ],
    "sg:phone":"+61 3 9530 4168",
    "sg:postcode":"3145",
    "sg:province":"VIC",
    "sg:tags":[
        "graphic",
        "designer"
    ],
    "wof:name":"Eye Design Graphics",
    "wof:placetype":"venue"
},
  "geometry": {"coordinates":[145.04826355,-37.8754501343],"type":"Point"}
}