{
  "type": "Feature",
  "properties": {
    "iso:country":"AU",
    "sg:address":"13 Hawker St",
    "sg:city":"Airport West",
    "sg:classifiers":[
        {
            "category":"Fast Food",
            "type":"Food & Drink"
        }
    ],
    "sg:phone":"+61 3 9330 2047",
    "sg:postcode":"3042",
    "sg:province":"VIC",
    "sg:tags":[
        "away",
        "take"
    ],
    "wof:name":"Gaonis T",
    "wof:placetype":"venue"
},
  "geometry": {"coordinates":[144.890090942,-37.7224807739],"type":"Point"}
}