{
  "type": "Feature",
  "properties": {
    "addr:full":"104 Baxter St Bendigo VIC 3550",
    "addr:housenumber":"104",
    "addr:postcode":"3550",
    "addr:street":"Baxter St",
    "iso:country":"AU",
    "sg:address":"104 Baxter St",
    "sg:city":"Bendigo",
    "sg:classifiers":[
        {
            "category":"Health Services",
            "subcategory":"Doctor",
            "type":"Services"
        }
    ],
    "sg:phone":"+61 3 5443 6155",
    "sg:postcode":"3550",
    "sg:province":"VIC",
    "sg:tags":[
        "medical",
        "practitioner"
    ],
    "wof:name":"Bradshaw A D",
    "wof:placetype":"venue"
},
  "geometry": {"coordinates":[144.28440856899999,-36.7526893616],"type":"Point"}
}