{
  "type": "Feature",
  "properties": {
    "addr:full":"10 Lambert St Tongala VIC 3621",
    "addr:housenumber":"10",
    "addr:postcode":"3621",
    "addr:street":"Lambert St",
    "iso:country":"AU",
    "sg:address":"10 Lambert St",
    "sg:city":"Tongala",
    "sg:classifiers":[
        {
            "category":"Building & Trades",
            "subcategory":"Cleaning & Sanitation",
            "type":"Services"
        }
    ],
    "sg:phone":"+61 407 849 664",
    "sg:postcode":"3621",
    "sg:province":"VIC",
    "sg:tags":[
        "abrasive",
        "blasting"
    ],
    "wof:name":"Tongala Sandblasting",
    "wof:placetype":"venue"
},
  "geometry": {"coordinates":[144.951461792,-36.2463150024],"type":"Point"}
}