{
  "type": "Feature",
  "properties": {
    "addr:full":"3 Evans St Dubbo NSW 2830",
    "addr:housenumber":"3",
    "addr:postcode":"2830",
    "addr:street":"Evans St",
    "iso:country":"AU",
    "sg:address":"3 Evans St",
    "sg:city":"Dubbo",
    "sg:classifiers":[
        {
            "category":"Retail",
            "subcategory":"Repair Shop",
            "type":"Services"
        }
    ],
    "sg:phone":"+61 2 6882 3938",
    "sg:postcode":"2830",
    "sg:province":"NSW",
    "sg:tags":[
        "upholsterer"
    ],
    "wof:name":"Cantrim",
    "wof:placetype":"venue"
},
  "geometry": {"coordinates":[148.608642578,-32.2378845215],"type":"Point"}
}