{
  "type": "Feature",
  "properties": {
    "iso:country":"AU",
    "sg:address":"124 George St",
    "sg:city":"Launceston",
    "sg:classifiers":[
        {
            "category":"Travel",
            "subcategory":"Hotels & Motels",
            "type":"Entertainment"
        }
    ],
    "sg:phone":"+61 3 6331 4015",
    "sg:postcode":"7250",
    "sg:province":"TAS",
    "sg:tags":[
        "accommodation"
    ],
    "wof:name":"O&#039;Keefes Hotel",
    "wof:placetype":"venue"
},
  "geometry": {"coordinates":[147.141311645,-41.4375305176],"type":"Point"}
}