{
  "type": "Feature",
  "properties": {
    "iso:country":"AU",
    "sg:address":"23 Seton Rd",
    "sg:city":"Moorebank",
    "sg:classifiers":[
        {
            "category":"Wholesale",
            "subcategory":"Construction Materials",
            "type":"Manufacturing & Wholesale Goods"
        }
    ],
    "sg:phone":"+61 2 9602 6288",
    "sg:postcode":"2170",
    "sg:province":"NSW",
    "sg:tags":[
        "wholesaler",
        "lighting",
        "mfrs",
        "accessory"
    ],
    "wof:name":"Australume Pty Ltd",
    "wof:placetype":"venue"
},
  "geometry": {"coordinates":[150.938919067,-33.9366416931],"type":"Point"}
}