{
  "type": "Feature",
  "properties": {
    "iso:country":"AU",
    "sg:address":"Shop 2/ 495 Princes Hwy",
    "sg:city":"Rockdale",
    "sg:classifiers":[
        {
            "category":"Personal",
            "subcategory":"Beauty Salon",
            "type":"Services"
        }
    ],
    "sg:phone":"+61 2 9567 2111",
    "sg:postcode":"2216",
    "sg:province":"NSW",
    "sg:tags":[
        "hairdresser"
    ],
    "wof:name":"Lovemores Hair & Beauty Salon",
    "wof:placetype":"venue"
},
  "geometry": {"coordinates":[151.137726,-33.95216],"type":"Point"}
}