{
  "type": "Feature",
  "properties": {
    "addr:full":"Lauren Drv Buderim QLD 4556",
    "addr:postcode":"4556",
    "addr:street":"Lauren Drv",
    "iso:country":"AU",
    "sg:address":"Lauren Drv",
    "sg:city":"Buderim",
    "sg:classifiers":[
        {
            "category":"Building & Trades",
            "subcategory":"Landscaping Services",
            "type":"Services"
        }
    ],
    "sg:phone":"+61 408 190 613",
    "sg:postcode":"4556",
    "sg:province":"QLD",
    "sg:tags":[
        "gardener"
    ],
    "wof:name":"Elemental Gardens",
    "wof:placetype":"venue"
},
  "geometry": {"coordinates":[153.071731567,-26.6910457611],"type":"Point"}
}