{
  "type": "Feature",
  "properties": {
    "addr:full":"496 Main North Rd (Cnr Potts Rd) Evanston SA 5116",
    "addr:housenumber":"496",
    "addr:postcode":"5116",
    "addr:street":"Main North Rd Cnr Potts Rd",
    "iso:country":"AU",
    "sg:address":"496 Main North Rd",
    "sg:city":"(Cnr Potts Rd) Evanston",
    "sg:classifiers":[
        {
            "category":"Autos & Motor Vehicles",
            "subcategory":"Fuel & Gas Station",
            "type":"Retail Goods"
        }
    ],
    "sg:phone":"+61 8 8522 2317",
    "sg:postcode":"5116",
    "sg:province":"SA",
    "wof:name":"Quix Food Stores",
    "wof:placetype":"venue"
},
  "geometry": {"coordinates":[138.740600586,-34.6205024719],"type":"Point"}
}