{
  "type": "Feature",
  "properties": {
    "addr:full":"1620 Ipswich Rd Rocklea QLD 4106",
    "addr:housenumber":"1620",
    "addr:postcode":"4106",
    "addr:street":"Ipswich Rd",
    "iso:country":"AU",
    "sg:address":"1620 Ipswich Rd",
    "sg:city":"Rocklea",
    "sg:classifiers":[
        {
            "category":"Manufacturing",
            "subcategory":"Furniture",
            "type":"Manufacturing & Wholesale Goods"
        }
    ],
    "sg:phone":"+61 7 3272 9555",
    "sg:postcode":"4106",
    "sg:province":"QLD",
    "sg:tags":[
        "builder",
        "designer",
        "custom"
    ],
    "wof:name":"Ascot Lounges",
    "wof:placetype":"venue"
},
  "geometry": {"coordinates":[153.00978088400001,-27.5520248413],"type":"Point"}
}