{
  "type": "Feature",
  "properties": {
    "addr:full":"U2/ 20 Stennett Rd Ingleburn NSW 2565",
    "addr:postcode":"2565",
    "addr:street":"U2 / 20 Stennett Rd",
    "iso:country":"AU",
    "sg:address":"U2/ 20 Stennett Rd",
    "sg:city":"Ingleburn",
    "sg:classifiers":[
        {
            "category":"Shopping",
            "subcategory":"Stationery & Office Supplies",
            "type":"Retail Goods"
        }
    ],
    "sg:phone":"+61 2 9829 5555",
    "sg:postcode":"2565",
    "sg:province":"NSW",
    "sg:tags":[
        "pottery",
        "equipment"
    ],
    "wof:name":"Blackwattle Pottery Ceramic Supplies",
    "wof:placetype":"venue"
},
  "geometry": {"coordinates":[150.84478759800001,-33.983959198],"type":"Point"}
}