{
  "type": "Feature",
  "properties": {
    "iso:country":"AU",
    "sg:address":"111 Denison Rd",
    "sg:city":"Newtown",
    "sg:classifiers":[
        {
            "category":"Retail",
            "subcategory":"Auto Repair",
            "type":"Services"
        }
    ],
    "sg:phone":"+61 2 9519 7438",
    "sg:postcode":"2042",
    "sg:province":"NSW",
    "sg:tags":[
        "muffler",
        "exhaust",
        "system"
    ],
    "wof:name":"Mufflers Galore",
    "wof:placetype":"venue"
},
  "geometry": {"coordinates":[151.175278,-33.891685],"type":"Point"}
}