{
  "type": "Feature",
  "properties": {
    "addr:full":"Unit 3/ 16 Mercator Cl Lake Munmorah NSW 2259",
    "addr:housenumber":"16",
    "addr:postcode":"2259",
    "addr:street":"Mercator Cl Lake",
    "iso:country":"AU",
    "sg:address":"Unit 3/ 16 Mercator Cl",
    "sg:city":"Lake Munmorah",
    "sg:classifiers":[
        {
            "category":"Real Estate",
            "subcategory":"Real Estate Agent",
            "type":"Services"
        }
    ],
    "sg:phone":"+61 2 4358 3355",
    "sg:postcode":"2259",
    "sg:province":"NSW",
    "wof:name":"Securatrend Pty Ltd",
    "wof:placetype":"venue"
},
  "geometry": {"coordinates":[151.48101806599999,-33.1748428345],"type":"Point"}
}