{
  "type": "Feature",
  "properties": {
    "addr:full":"40 Magid Drv Narre Warren VIC 3805",
    "addr:housenumber":"40",
    "addr:postcode":"3805",
    "addr:street":"Magid Drv",
    "iso:country":"AU",
    "sg:address":"40 Magid Drv",
    "sg:city":"Narre Warren",
    "sg:classifiers":[
        {
            "category":"Shopping",
            "subcategory":"Clothing, Apparel, & Fashions",
            "type":"Retail Goods"
        }
    ],
    "sg:phone":"+61 3 9796 0822",
    "sg:postcode":"3805",
    "sg:province":"VIC",
    "sg:tags":[
        "accessory"
    ],
    "wof:name":"Ice Accessories",
    "wof:placetype":"venue"
},
  "geometry": {"coordinates":[145.299576,-38.018589],"type":"Point"}
}