{
  "type": "Feature",
  "properties": {
    "iso:country":"AU",
    "sg:address":"90 George St",
    "sg:city":"Norwood",
    "sg:classifiers":[
        {
            "category":"Building & Trades",
            "subcategory":"Construction",
            "type":"Services"
        }
    ],
    "sg:phone":"+61 8 8333 4333",
    "sg:postcode":"5067",
    "sg:province":"SA",
    "sg:tags":[
        "management"
    ],
    "wof:name":"Gk Structures Pty Ltd",
    "wof:placetype":"venue"
},
  "geometry": {"coordinates":[138.63703918499999,-34.9238967896],"type":"Point"}
}