{
  "type": "Feature",
  "properties": {
    "addr:full":"76 Barney St Armidale NSW 2350",
    "addr:housenumber":"76",
    "addr:postcode":"2350",
    "addr:street":"Barney St",
    "iso:country":"AU",
    "sg:address":"76 Barney St",
    "sg:city":"Armidale",
    "sg:classifiers":[
        {
            "category":"Travel",
            "subcategory":"Hotels & Motels",
            "type":"Entertainment"
        }
    ],
    "sg:phone":"+61 1800 888 100",
    "sg:postcode":"2350",
    "sg:province":"NSW",
    "wof:name":"Abbotsleigh Motor Inn",
    "wof:placetype":"venue"
},
  "geometry": {"coordinates":[151.667526245,-30.5174179077],"type":"Point"}
}