{
  "type": "Feature",
  "properties": {
    "addr:full":"32 Glastonbury Ave Unanderra NSW 2526",
    "addr:housenumber":"32",
    "addr:postcode":"2526",
    "addr:street":"Glastonbury Ave",
    "iso:country":"AU",
    "sg:address":"32 Glastonbury Ave",
    "sg:city":"Unanderra",
    "sg:classifiers":[
        {
            "category":"Wholesale",
            "subcategory":"Durable Goods & Equipment",
            "type":"Manufacturing & Wholesale Goods"
        }
    ],
    "sg:phone":"+61 2 4271 5777",
    "sg:postcode":"2526",
    "sg:province":"NSW",
    "sg:tags":[
        "abrasive",
        "blasting"
    ],
    "wof:name":"M & S Engineering Pty Ltd",
    "wof:placetype":"venue"
},
  "geometry": {"coordinates":[150.85455322300001,-34.4605026245],"type":"Point"}
}