{
  "type": "Feature",
  "properties": {
    "addr:full":"39 Duke St Albany WA 6330",
    "addr:housenumber":"39",
    "addr:postcode":"6330",
    "addr:street":"Duke St",
    "iso:country":"AU",
    "sg:address":"39 Duke St",
    "sg:city":"Albany",
    "sg:classifiers":[
        {
            "category":"Museum",
            "type":"Entertainment"
        }
    ],
    "sg:phone":"+61 8 9841 6174",
    "sg:postcode":"6330",
    "sg:province":"WA",
    "wof:name":"Patrick Taylor Cottage Museum",
    "wof:placetype":"venue"
},
  "geometry": {"coordinates":[117.881332398,-35.0262641907],"type":"Point"}
}