{
  "type": "Feature",
  "properties": {
    "addr:full":"9 Shirlow Ave Rye VIC 3941",
    "addr:housenumber":"9",
    "addr:postcode":"3941",
    "addr:street":"Shirlow Ave",
    "iso:country":"AU",
    "sg:address":"9 Shirlow Ave",
    "sg:city":"Rye",
    "sg:classifiers":[
        {
            "category":"Personal",
            "type":"Services"
        }
    ],
    "sg:phone":"+61 3 5985 8439",
    "sg:postcode":"3941",
    "sg:province":"VIC",
    "sg:tags":[
        "dressmaker"
    ],
    "wof:name":"The Wardrobe Mistress",
    "wof:placetype":"venue"
},
  "geometry": {"coordinates":[144.837524414,-38.3727836609],"type":"Point"}
}