{
  "type": "Feature",
  "properties": {
    "iso:country":"AU",
    "sg:address":"Lot 5 Kylies Rd",
    "sg:city":"Mooball",
    "sg:classifiers":[
        {
            "category":"Farming",
            "subcategory":"Nursery",
            "type":"Manufacturing & Wholesale Goods"
        }
    ],
    "sg:phone":"+61 2 6677 0130",
    "sg:postcode":"2483",
    "sg:province":"NSW",
    "wof:name":"North Coast Wholesale Hibiscus",
    "wof:placetype":"venue"
},
  "geometry": {"coordinates":[153.50378418,-28.4383201599],"type":"Point"}
}