{
  "type": "Feature",
  "properties": {
    "addr:full":"10 Stephens Pl Adelaide SA 5000",
    "addr:housenumber":"10",
    "addr:postcode":"5000",
    "addr:street":"Stephens Pl",
    "iso:country":"AU",
    "sg:address":"10 Stephens Pl",
    "sg:city":"Adelaide",
    "sg:classifiers":[
        {
            "category":"Banks & Credit Unions",
            "subcategory":"Financial Services",
            "type":"Services"
        }
    ],
    "sg:phone":"+61 8 8223 6907",
    "sg:postcode":"5000",
    "sg:province":"SA",
    "sg:tags":[
        "coin"
    ],
    "wof:name":"Dawson Coins & Stamps",
    "wof:placetype":"venue"
},
  "geometry": {"coordinates":[138.60122680699999,-34.9219169617],"type":"Point"}
}