{
  "type": "Feature",
  "properties": {
    "addr:full":"Level 1/ 2 Edward St Brisbane QLD 4000",
    "addr:housenumber":"/ 2",
    "addr:postcode":"4000",
    "addr:street":"Edward St",
    "iso:country":"AU",
    "sg:address":"Level 1/ 2 Edward St",
    "sg:city":"Brisbane",
    "sg:classifiers":[
        {
            "category":"Professional",
            "subcategory":"Computer Services",
            "type":"Services"
        }
    ],
    "sg:phone":"+61 7 3210 6911",
    "sg:postcode":"4000",
    "sg:province":"QLD",
    "sg:tags":[
        "package",
        "software"
    ],
    "wof:name":"Cube Consulting Pty Ltd",
    "wof:placetype":"venue"
},
  "geometry": {"coordinates":[153.03044128400001,-27.4720497131],"type":"Point"}
}