{
  "type": "Feature",
  "properties": {
    "iso:country":"AU",
    "sg:address":"Shp 15, 43- 45 Burns Bay Rd",
    "sg:city":"Lane Cove",
    "sg:classifiers":[
        {
            "category":"Banks & Credit Unions",
            "subcategory":"Bank",
            "type":"Services"
        }
    ],
    "sg:phone":"+61 2 9420 3052",
    "sg:postcode":"2066",
    "sg:province":"NSW",
    "sg:tags":[
        "broker",
        "mortgage"
    ],
    "wof:name":"Mortgage Choice",
    "wof:placetype":"venue"
},
  "geometry": {"coordinates":[151.16802978499999,-33.8143959045],"type":"Point"}
}