{
  "type": "Feature",
  "properties": {
    "iso:country":"AU",
    "sg:address":"Suite 4, 144 Camberwell Rd",
    "sg:city":"Camberwell",
    "sg:classifiers":[
        {
            "category":"Banks & Credit Unions",
            "subcategory":"Financial Services",
            "type":"Services"
        }
    ],
    "sg:phone":"+61 3 9882 0438",
    "sg:postcode":"3124",
    "sg:province":"VIC",
    "sg:tags":[
        "planning"
    ],
    "wof:name":"Albert Financial Services Pty Ltd",
    "wof:placetype":"venue"
},
  "geometry": {"coordinates":[145.053756714,-37.8289375305],"type":"Point"}
}