{
  "type": "Feature",
  "properties": {
    "addr:full":"30 City Pl Sunshine VIC 3020",
    "addr:housenumber":"30",
    "addr:postcode":"3020",
    "addr:street":"City Pl",
    "iso:country":"AU",
    "sg:address":"30 City Pl",
    "sg:city":"Sunshine",
    "sg:classifiers":[
        {
            "category":"Fast Food",
            "type":"Food & Drink"
        }
    ],
    "sg:phone":"+61 3 9312 2559",
    "sg:postcode":"3020",
    "sg:province":"VIC",
    "sg:tags":[
        "away",
        "take"
    ],
    "wof:name":"Sunshine Chicken Bar",
    "wof:placetype":"venue"
},
  "geometry": {"coordinates":[144.83174099999999,-37.78775],"type":"Point"}
}