{
  "type": "Feature",
  "properties": {
    "addr:full":"Unit 3/ 266 Montague Rd West End (Brisbane) QLD 4101",
    "addr:housenumber":"/ 266",
    "addr:postcode":"4101",
    "addr:street":"Montague Rd",
    "iso:country":"AU",
    "sg:address":"Unit 3/ 266 Montague Rd",
    "sg:city":"West End (Brisbane)",
    "sg:classifiers":[
        {
            "category":"Professional",
            "subcategory":"Business Services",
            "type":"Services"
        }
    ],
    "sg:phone":"+61 7 3846 6303",
    "sg:postcode":"4101",
    "sg:province":"QLD",
    "sg:tags":[
        "fashion",
        "agent"
    ],
    "wof:name":"French Babe Fashion",
    "wof:placetype":"venue"
},
  "geometry": {"coordinates":[153.00624084500001,-27.4788532257],"type":"Point"}
}