{
  "type": "Feature",
  "properties": {
    "iso:country":"AU",
    "sg:address":"22 Bellevue Drv",
    "sg:city":"Carlingford",
    "sg:classifiers":[
        {
            "category":"Building & Trades",
            "subcategory":"Construction",
            "type":"Services"
        }
    ],
    "sg:phone":"+61 2 9871 1336",
    "sg:postcode":"2118",
    "sg:province":"NSW",
    "sg:tags":[
        "contractor"
    ],
    "wof:name":"Nicolson R G",
    "wof:placetype":"venue"
},
  "geometry": {"coordinates":[151.035354614,-33.7687683105],"type":"Point"}
}