{
  "type": "Feature",
  "properties": {
    "iso:country":"AU",
    "sg:address":"PO Box 1224",
    "sg:city":"Gawler",
    "sg:classifiers":[
        {
            "category":"Building & Trades",
            "subcategory":"Landscaping Services",
            "type":"Services"
        }
    ],
    "sg:phone":"+61 413 052 124",
    "sg:postcode":"5118",
    "sg:province":"SA",
    "sg:tags":[
        "designer",
        "landscape",
        "contractor"
    ],
    "wof:name":"Turf & Irrigation Waterwide Solutions",
    "wof:placetype":"venue"
},
  "geometry": {"coordinates":[138.72822600000001,-34.596329],"type":"Point"}
}