{
  "type": "Feature",
  "properties": {
    "addr:full":"Suite 5/ 626 Nepean Hwy Carrum VIC 3197",
    "addr:housenumber":"/ 626",
    "addr:postcode":"3197",
    "addr:street":"Nepean Hwy",
    "iso:country":"AU",
    "sg:address":"Suite 5/ 626 Nepean Hwy",
    "sg:city":"Carrum",
    "sg:classifiers":[
        {
            "category":"Health Services",
            "subcategory":"Dentist",
            "type":"Services"
        }
    ],
    "sg:phone":"+61 3 9772 8481",
    "sg:postcode":"3197",
    "sg:province":"VIC",
    "wof:name":"Osmond Robert T & Associates Dr",
    "wof:placetype":"venue"
},
  "geometry": {"coordinates":[145.12208557100001,-38.0753326416],"type":"Point"}
}