{
  "type": "Feature",
  "properties": {
    "addr:full":"170 Parramatta Rd Stanmore NSW 2048",
    "addr:housenumber":"170",
    "addr:postcode":"2048",
    "addr:street":"Parramatta Rd",
    "iso:country":"AU",
    "sg:address":"170 Parramatta Rd",
    "sg:city":"Stanmore",
    "sg:classifiers":[
        {
            "category":"Health Services",
            "subcategory":"Doctor",
            "type":"Services"
        }
    ],
    "sg:phone":"+61 2 9518 0722",
    "sg:postcode":"2048",
    "sg:province":"NSW",
    "sg:tags":[
        "podiatrist"
    ],
    "wof:name":"Dominic Salvemini",
    "wof:placetype":"venue"
},
  "geometry": {"coordinates":[151.167542,-33.888065],"type":"Point"}
}