{
  "type": "Feature",
  "properties": {
    "addr:full":"196 Silverwater Rd Silverwater NSW 2128",
    "addr:housenumber":"196",
    "addr:postcode":"2128",
    "addr:street":"Silverwater Rd",
    "iso:country":"AU",
    "sg:address":"196 Silverwater Rd",
    "sg:city":"Silverwater",
    "sg:classifiers":[
        {
            "category":"Real Estate",
            "subcategory":"Real Estate Agent",
            "type":"Services"
        }
    ],
    "sg:phone":"+61 2 9648 4987",
    "sg:postcode":"2128",
    "sg:province":"NSW",
    "sg:tags":[
        "handyman's",
        "equipment",
        "hire",
        "builders",
        "contractor"
    ],
    "wof:name":"SuperDeck Crane Platforms Pty Limited",
    "wof:placetype":"venue"
},
  "geometry": {"coordinates":[151.050292969,-33.8278541565],"type":"Point"}
}