{
  "type": "Feature",
  "properties": {
    "addr:full":"1 Brisbane St Dubbo NSW 2830",
    "addr:housenumber":"1",
    "addr:postcode":"2830",
    "addr:street":"Brisbane St",
    "iso:country":"AU",
    "sg:address":"1 Brisbane St",
    "sg:city":"Dubbo",
    "sg:classifiers":[
        {
            "category":"Building & Trades",
            "subcategory":"Cleaning & Sanitation",
            "type":"Services"
        }
    ],
    "sg:phone":"+61 2 6882 2628",
    "sg:postcode":"2830",
    "sg:province":"NSW",
    "sg:tags":[
        "cleaner",
        "repairer",
        "roof"
    ],
    "wof:name":"Porters Plumbing & Gas Fitting Service",
    "wof:placetype":"venue"
},
  "geometry": {"coordinates":[148.644699097,-32.2434234619],"type":"Point"}
}