{
  "type": "Feature",
  "properties": {
    "addr:full":"135 Argent St Broken Hill NSW 2880",
    "addr:housenumber":"135",
    "addr:postcode":"2880",
    "addr:street":"Argent St",
    "iso:country":"AU",
    "sg:address":"135 Argent St",
    "sg:city":"Broken Hill",
    "sg:classifiers":[
        {
            "category":"Food & Beverages",
            "subcategory":"Supermarket",
            "type":"Retail Goods"
        }
    ],
    "sg:phone":"+61 8 8087 4806",
    "sg:postcode":"2880",
    "sg:province":"NSW",
    "sg:tags":[
        "grocery",
        "store"
    ],
    "wof:name":"Schinella's Friendly Grocer",
    "wof:placetype":"venue"
},
  "geometry": {"coordinates":[141.46124267600001,-31.9611110687],"type":"Point"}
}