{
  "type": "Feature",
  "properties": {
    "addr:full":"200 Annerley Rd Dutton Park QLD 4102",
    "addr:housenumber":"200",
    "addr:postcode":"4102",
    "addr:street":"Annerley Rd",
    "iso:country":"AU",
    "sg:address":"200 Annerley Rd",
    "sg:city":"Dutton Park",
    "sg:classifiers":[
        {
            "category":"Retail",
            "subcategory":"Auto Repair",
            "type":"Services"
        }
    ],
    "sg:phone":"+61 7 3844 2227",
    "sg:postcode":"4102",
    "sg:province":"QLD",
    "sg:tags":[
        "repairer",
        "motor",
        "engineer"
    ],
    "wof:name":"Formula Automotive",
    "wof:placetype":"venue"
},
  "geometry": {"coordinates":[153.02806091299999,-27.4987182617],"type":"Point"}
}