{
  "type": "Feature",
  "properties": {
    "iso:country":"AU",
    "sg:address":"Creek Rd",
    "sg:city":"Carindale",
    "sg:classifiers":[
        {
            "category":"Shopping",
            "subcategory":"Clothing, Apparel, & Fashions",
            "type":"Retail Goods"
        }
    ],
    "sg:phone":"+61 7 3343 1777",
    "sg:postcode":"4152",
    "sg:province":"QLD",
    "sg:tags":[
        "lady",
        "wear"
    ],
    "wof:name":"etre#",
    "wof:placetype":"venue"
},
  "geometry": {"coordinates":[153.101760864,-27.5173435211],"type":"Point"}
}