{
  "type": "Feature",
  "properties": {
    "iso:country":"AU",
    "sg:address":"209a Doveton St",
    "sg:city":"(Sth) Ballarat",
    "sg:classifiers":[
        {
            "category":"Banks & Credit Unions",
            "subcategory":"Financial Services",
            "type":"Services"
        }
    ],
    "sg:phone":"+61 3 5333 4200",
    "sg:postcode":"3350",
    "sg:province":"VIC",
    "sg:tags":[
        "loan",
        "finance",
        "mortgage"
    ],
    "wof:name":"Reliable Mortgage Services Pty Ltd",
    "wof:placetype":"venue"
},
  "geometry": {"coordinates":[143.85571300000001,-37.555794],"type":"Point"}
}