{
  "type": "Feature",
  "properties": {
    "iso:country":"AU",
    "sg:address":"1/ 17 Pinacle St",
    "sg:city":"Brendale",
    "sg:classifiers":[
        {
            "category":"Wholesale",
            "subcategory":"Painting Supplies",
            "type":"Manufacturing & Wholesale Goods"
        }
    ],
    "sg:phone":"+61 7 3881 3022",
    "sg:postcode":"4500",
    "sg:province":"QLD",
    "sg:tags":[
        "product",
        "polyurethane"
    ],
    "wof:name":"Stak Polymers Pty Ltd",
    "wof:placetype":"venue"
},
  "geometry": {"coordinates":[152.97654724099999,-27.3184738159],"type":"Point"}
}