{
  "type": "Feature",
  "properties": {
    "addr:full":"14 Charlotte St Tocumwal NSW 2714",
    "addr:housenumber":"14",
    "addr:postcode":"2714",
    "addr:street":"Charlotte St",
    "iso:country":"AU",
    "sg:address":"14 Charlotte St",
    "sg:city":"Tocumwal",
    "sg:classifiers":[
        {
            "category":"Commercial Area",
            "type":"Public Place"
        }
    ],
    "sg:phone":"+61 3 5874 2146",
    "sg:postcode":"2714",
    "sg:province":"NSW",
    "sg:tags":[
        "heavy",
        "carrier"
    ],
    "wof:name":"Baldwin AR & MJ Teucking P/L",
    "wof:placetype":"venue"
},
  "geometry": {"coordinates":[145.55955505399999,-35.8089904785],"type":"Point"}
}