{
  "type": "Feature",
  "properties": {
    "addr:full":"10- 22 Hampstead Rd Maidstone VIC 3012",
    "addr:housenumber":"22",
    "addr:postcode":"3012",
    "addr:street":"Hampstead Rd",
    "iso:country":"AU",
    "sg:address":"10- 22 Hampstead Rd",
    "sg:city":"Maidstone",
    "sg:classifiers":[
        {
            "category":"Professional",
            "subcategory":"Art Services",
            "type":"Services"
        }
    ],
    "sg:phone":"+61 1800 111 221",
    "sg:postcode":"3012",
    "sg:province":"VIC",
    "sg:tags":[
        "interior",
        "decorator"
    ],
    "wof:name":"Complete Property Presentations",
    "wof:placetype":"venue"
},
  "geometry": {"coordinates":[144.872512817,-37.7806358337],"type":"Point"}
}