{
  "type": "Feature",
  "properties": {
    "iso:country":"AU",
    "sg:address":"Level 4, 102 Albert Rd",
    "sg:city":"South Melbourne",
    "sg:classifiers":[
        {
            "category":"Education",
            "subcategory":"Special Training",
            "type":"Public Place"
        }
    ],
    "sg:phone":"+61 3 9690 0944",
    "sg:postcode":"3205",
    "sg:province":"VIC",
    "sg:tags":[
        "development"
    ],
    "wof:name":"GeoTrain Asia Pacific Pty Ltd",
    "wof:placetype":"venue"
},
  "geometry": {"coordinates":[144.970108,-37.83569],"type":"Point"}
}