{
  "type": "Feature",
  "properties": {
    "addr:full":"10B Viking Crt Cheltenham VIC 3192",
    "addr:housenumber":"10b",
    "addr:postcode":"3192",
    "addr:street":"Viking Crt",
    "iso:country":"AU",
    "sg:address":"10B Viking Crt",
    "sg:city":"Cheltenham",
    "sg:classifiers":[
        {
            "category":"Structure",
            "subcategory":"Building",
            "type":"Public Place"
        }
    ],
    "sg:phone":"+61 413 111 949",
    "sg:postcode":"3192",
    "sg:province":"VIC",
    "sg:tags":[
        "sail",
        "shade"
    ],
    "wof:name":"Ideal Shade Solutions",
    "wof:placetype":"venue"
},
  "geometry": {"coordinates":[145.06831359899999,-37.9512748718],"type":"Point"}
}