{
  "type": "Feature",
  "properties": {
    "addr:full":"Shop 2/ 240 Victoria St Richmond VIC 3121",
    "addr:housenumber":"shop 2 / 240",
    "addr:postcode":"3121",
    "addr:street":"Victoria St",
    "iso:country":"AU",
    "sg:address":"Shop 2/ 240 Victoria St",
    "sg:city":"Richmond",
    "sg:classifiers":[
        {
            "category":"Food & Beverages",
            "subcategory":"Bakery",
            "type":"Retail Goods"
        }
    ],
    "sg:phone":"+61 3 9427 7580",
    "sg:postcode":"3121",
    "sg:province":"VIC",
    "sg:tags":[
        "baker"
    ],
    "wof:name":"Lee Lee Hot Bread Shop",
    "wof:placetype":"venue"
},
  "geometry": {"coordinates":[144.999145508,-37.8105239868],"type":"Point"}
}