{
  "type": "Feature",
  "properties": {
    "addr:full":"McCauley St Ashby NSW 2463",
    "addr:postcode":"2463",
    "addr:street":"Mccauley St",
    "iso:country":"AU",
    "sg:address":"McCauley St",
    "sg:city":"Ashby",
    "sg:classifiers":[
        {
            "category":"Manufacturing",
            "subcategory":"Lumber",
            "type":"Manufacturing & Wholesale Goods"
        }
    ],
    "sg:phone":"+61 2 6645 3280",
    "sg:postcode":"2463",
    "sg:province":"NSW",
    "sg:tags":[
        "sawmillers"
    ],
    "wof:name":"Ashby Sawmill Pty Ltd",
    "wof:placetype":"venue"
},
  "geometry": {"coordinates":[153.195068359,-29.4360160828],"type":"Point"}
}