{
  "type": "Feature",
  "properties": {
    "addr:full":"4/ 32 Stapleton St Wentworthville NSW 2145",
    "addr:housenumber":"/ 32",
    "addr:postcode":"2145",
    "addr:street":"Stapleton St",
    "iso:country":"AU",
    "sg:address":"4/ 32 Stapleton St",
    "sg:city":"Wentworthville",
    "sg:classifiers":[
        {
            "category":"Professional",
            "subcategory":"Computer Services",
            "type":"Services"
        }
    ],
    "sg:phone":"+61 403 891 940",
    "sg:postcode":"2145",
    "sg:province":"NSW",
    "sg:tags":[
        "repairs",
        "upgrade",
        "equipment"
    ],
    "wof:name":"Aaron Flew",
    "wof:placetype":"venue"
},
  "geometry": {"coordinates":[150.963790894,-33.804851532],"type":"Point"}
}