{
  "type": "Feature",
  "properties": {
    "addr:full":"10 Bulls Rd St Johns Park NSW 2176",
    "addr:housenumber":"10",
    "addr:postcode":"2176",
    "addr:street":"Bulls Rd St",
    "iso:country":"AU",
    "sg:address":"10 Bulls Rd",
    "sg:city":"St Johns Park",
    "sg:classifiers":[
        {
            "category":"Food & Beverages",
            "subcategory":"Bakery",
            "type":"Retail Goods"
        }
    ],
    "sg:phone":"+61 2 9609 3528",
    "sg:postcode":"2176",
    "sg:province":"NSW",
    "sg:tags":[
        "baker"
    ],
    "wof:name":"Hot Bread Shop",
    "wof:placetype":"venue"
},
  "geometry": {"coordinates":[150.91195678700001,-33.8679542542],"type":"Point"}
}