{
  "type": "Feature",
  "properties": {
    "iso:country":"AU",
    "sg:address":"PO Box 5257",
    "sg:city":"Bundaberg West",
    "sg:classifiers":[
        {
            "category":"Shopping",
            "subcategory":"Musical Instruments",
            "type":"Retail Goods"
        }
    ],
    "sg:phone":"+61 413 775 616",
    "sg:postcode":"4670",
    "sg:province":"QLD",
    "sg:tags":[
        "musician",
        "agent"
    ],
    "wof:name":"Frank Marsh",
    "wof:placetype":"venue"
},
  "geometry": {"coordinates":[152.33720398,-24.8693695068],"type":"Point"}
}