{
  "type": "Feature",
  "properties": {
    "iso:country":"AU",
    "sg:address":"49 Wynyard St",
    "sg:city":"Tumut",
    "sg:classifiers":[
        {
            "category":"Professional",
            "subcategory":"Printing & Photocopies",
            "type":"Services"
        }
    ],
    "sg:phone":"+61 2 6947 1395",
    "sg:postcode":"2720",
    "sg:province":"NSW",
    "sg:tags":[
        "embroidery"
    ],
    "wof:name":"Stevensons Workwear & Embroidery",
    "wof:placetype":"venue"
},
  "geometry": {"coordinates":[148.22404499999999,-35.300903],"type":"Point"}
}