{
  "type": "Feature",
  "properties": {
    "addr:full":"Shop 8 , Maritana Mall Kalgoorlie WA 6430",
    "addr:housenumber":"shop 8",
    "addr:postcode":"6430",
    "addr:street":"Maritana Mall",
    "iso:country":"AU",
    "sg:address":"Shop 8",
    "sg:city":", Maritana Mall Kalgoorlie",
    "sg:classifiers":[
        {
            "category":"Shopping",
            "subcategory":"Discount & Variety Stores",
            "type":"Retail Goods"
        }
    ],
    "sg:phone":"+61 8 9021 2575",
    "sg:postcode":"6430",
    "sg:province":"WA",
    "sg:tags":[
        "shop",
        "adult"
    ],
    "wof:name":"Adultshop.com",
    "wof:placetype":"venue"
},
  "geometry": {"coordinates":[121.467689514,-30.7404346466],"type":"Point"}
}