{
  "type": "Feature",
  "properties": {
    "iso:country":"AU",
    "sg:address":"PO Box 272",
    "sg:city":"Wentworth",
    "sg:classifiers":[
        {
            "category":"Building & Trades",
            "subcategory":"Plumbing",
            "type":"Services"
        }
    ],
    "sg:phone":"+61 3 5027 6401",
    "sg:postcode":"2648",
    "sg:province":"NSW",
    "sg:tags":[
        "plumber",
        "gasfitters"
    ],
    "wof:name":"Stockman Plumbing",
    "wof:placetype":"venue"
},
  "geometry": {"coordinates":[141.857544,-33.999481],"type":"Point"}
}