{
  "type": "Feature",
  "properties": {
    "addr:full":"26 Aldershot Rd Lonsdale SA 5160",
    "addr:housenumber":"26",
    "addr:postcode":"5160",
    "addr:street":"Aldershot Rd",
    "iso:country":"AU",
    "sg:address":"26 Aldershot Rd",
    "sg:city":"Lonsdale",
    "sg:classifiers":[
        {
            "category":"Shopping",
            "subcategory":"Stationery & Office Supplies",
            "type":"Retail Goods"
        }
    ],
    "sg:phone":"+61 8 8326 3333",
    "sg:postcode":"5160",
    "sg:province":"SA",
    "sg:tags":[
        "packaging",
        "material"
    ],
    "wof:name":"Chep Australia",
    "wof:placetype":"venue"
},
  "geometry": {"coordinates":[138.507156372,-35.1067962646],"type":"Point"}
}