{
  "type": "Feature",
  "properties": {
    "addr:full":"56 Berry St North Sydney NSW 2060",
    "addr:housenumber":"56",
    "addr:postcode":"2060",
    "addr:street":"Berry St",
    "iso:country":"AU",
    "sg:address":"56 Berry St",
    "sg:city":"North Sydney",
    "sg:classifiers":[
        {
            "category":"Professional",
            "subcategory":"Detective & Security Services",
            "type":"Services"
        }
    ],
    "sg:phone":"+61 2 9972 9241",
    "sg:postcode":"2060",
    "sg:province":"NSW",
    "sg:tags":[
        "investigator"
    ],
    "wof:name":"Caught In The Act Investigations",
    "wof:placetype":"venue"
},
  "geometry": {"coordinates":[151.207855225,-33.8367729187],"type":"Point"}
}