{
  "type": "Feature",
  "properties": {
    "addr:full":"218 High St Wauchope NSW 2446",
    "addr:housenumber":"218",
    "addr:postcode":"2446",
    "addr:street":"High St",
    "iso:country":"AU",
    "sg:address":"218 High St",
    "sg:city":"Wauchope",
    "sg:classifiers":[
        {
            "category":"Professional",
            "subcategory":"Printing & Photocopies",
            "type":"Services"
        }
    ],
    "sg:phone":"+61 2 6585 2514",
    "sg:postcode":"2446",
    "sg:province":"NSW",
    "sg:tags":[
        "screen",
        "printer"
    ],
    "wof:name":"Wauchope Indoor Sports",
    "wof:placetype":"venue"
},
  "geometry": {"coordinates":[152.736435,-31.458208],"type":"Point"}
}