{
  "type": "Feature",
  "properties": {
    "addr:full":"12 Nerang-Broadbeach Rd Nerang QLD 4211",
    "addr:housenumber":"12",
    "addr:postcode":"4211",
    "addr:street":"Nerang-Broadbeach Rd",
    "iso:country":"AU",
    "sg:address":"12 Nerang-Broadbeach Rd",
    "sg:city":"Nerang",
    "sg:classifiers":[
        {
            "category":"Health Services",
            "subcategory":"Optometrist",
            "type":"Services"
        }
    ],
    "sg:phone":"+61 7 5596 3299",
    "sg:postcode":"4211",
    "sg:province":"QLD",
    "wof:name":"Jennifer Dong Optometrists",
    "wof:placetype":"venue"
},
  "geometry": {"coordinates":[153.343139648,-27.9937229156],"type":"Point"}
}