{
  "type": "Feature",
  "properties": {
    "iso:country":"AU",
    "sg:address":"Sturt Reserve Rd",
    "sg:city":"Murray Bridge",
    "sg:classifiers":[
        {
            "category":"Retail",
            "subcategory":"Auto Repair",
            "type":"Services"
        }
    ],
    "sg:phone":"+61 8 8532 3164",
    "sg:postcode":"5253",
    "sg:province":"SA",
    "sg:tags":[
        "muffler",
        "exhaust",
        "system"
    ],
    "wof:name":"Berklee Muffler Stockist",
    "wof:placetype":"venue"
},
  "geometry": {"coordinates":[139.283569336,-35.1204338074],"type":"Point"}
}