{
  "type": "Feature",
  "properties": {
    "addr:full":"31 Research Drv Croydon VIC 3136",
    "addr:housenumber":"31",
    "addr:postcode":"3136",
    "addr:street":"Research Drv",
    "iso:country":"AU",
    "sg:address":"31 Research Drv",
    "sg:city":"Croydon",
    "sg:classifiers":[
        {
            "category":"Manufacturing",
            "subcategory":"Metals",
            "type":"Manufacturing & Wholesale Goods"
        }
    ],
    "sg:phone":"+61 3 9761 5377",
    "sg:postcode":"3136",
    "sg:province":"VIC",
    "sg:tags":[
        "steel",
        "fabricator",
        "mfrs"
    ],
    "wof:name":"Uniweld Engineering",
    "wof:placetype":"venue"
},
  "geometry": {"coordinates":[145.29208374000001,-37.8170623779],"type":"Point"}
}