{
  "type": "Feature",
  "properties": {
    "addr:full":"U7/ 14 Fearn Ave Margaret River WA 6285",
    "addr:housenumber":"14",
    "addr:postcode":"6285",
    "addr:street":"U7 /;Fearn Ave",
    "iso:country":"AU",
    "sg:address":"U7/ 14 Fearn Ave",
    "sg:city":"Margaret River",
    "sg:classifiers":[
        {
            "category":"Farming",
            "subcategory":"Vineyard",
            "type":"Manufacturing & Wholesale Goods"
        }
    ],
    "sg:phone":"+61 8 9757 9522",
    "sg:postcode":"6285",
    "sg:province":"WA",
    "sg:tags":[
        "winery"
    ],
    "wof:name":"Mareeba Park Holdings Pty Ltd",
    "wof:placetype":"venue"
},
  "geometry": {"coordinates":[115.07245636,-33.9508857727],"type":"Point"}
}