{
  "type": "Feature",
  "properties": {
    "iso:country":"AU",
    "sg:address":"52 Pinjarra Rd",
    "sg:city":"Mandurah",
    "sg:classifiers":[
        {
            "category":"Autos & Motor Vehicles",
            "subcategory":"Automobile Sales",
            "type":"Retail Goods"
        }
    ],
    "sg:phone":"+61 8 9531 8906",
    "sg:postcode":"6210",
    "sg:province":"WA",
    "sg:tags":[
        "car",
        "new"
    ],
    "wof:name":"Mandurah Daewoo",
    "wof:placetype":"venue"
},
  "geometry": {"coordinates":[115.723152,-32.53463],"type":"Point"}
}