{
  "type": "Feature",
  "properties": {
    "addr:full":"Lvl2/ 139 Murray St Pyrmont NSW 2009",
    "addr:housenumber":"139",
    "addr:postcode":"2009",
    "addr:street":"Murray St",
    "iso:country":"AU",
    "sg:address":"Lvl2/ 139 Murray St",
    "sg:city":"Pyrmont",
    "sg:classifiers":[
        {
            "category":"Home & Garden",
            "subcategory":"Furniture",
            "type":"Retail Goods"
        }
    ],
    "sg:phone":"+61 2 8570 5700",
    "sg:postcode":"2009",
    "sg:province":"NSW",
    "sg:tags":[
        "business"
    ],
    "wof:name":"Work Arena Pty Ltd",
    "wof:placetype":"venue"
},
  "geometry": {"coordinates":[151.197143555,-33.8727912903],"type":"Point"}
}