{
  "type": "Feature",
  "properties": {
    "iso:country":"AU",
    "sg:address":"PO Box 846",
    "sg:city":"Lutwyche",
    "sg:classifiers":[
        {
            "category":"Shopping",
            "type":"Retail Goods"
        }
    ],
    "sg:phone":"+61 401 172 739",
    "sg:postcode":"4030",
    "sg:province":"QLD",
    "sg:tags":[
        "equipment",
        "safety",
        "accessory"
    ],
    "wof:name":"Soft Landing System",
    "wof:placetype":"venue"
},
  "geometry": {"coordinates":[153.033905,-27.42214],"type":"Point"}
}