{
  "type": "Feature",
  "properties": {
    "iso:country":"AU",
    "sg:address":"333 Blackburn Rd",
    "sg:city":"Burwood East",
    "sg:classifiers":[
        {
            "category":"Health Services",
            "subcategory":"Health Practitioner",
            "type":"Services"
        }
    ],
    "sg:phone":"+61 3 9887 6238",
    "sg:postcode":"3151",
    "sg:province":"VIC",
    "sg:tags":[
        "alternative"
    ],
    "wof:name":"Vibe Therapies",
    "wof:placetype":"venue"
},
  "geometry": {"coordinates":[145.152633667,-37.8505516052],"type":"Point"}
}