{
  "type": "Feature",
  "properties": {
    "iso:country":"AU",
    "sg:address":"Toronto St",
    "sg:city":"Kelso",
    "sg:classifiers":[
        {
            "category":"Professional",
            "type":"Services"
        }
    ],
    "sg:phone":"+61 2 6332 2707",
    "sg:postcode":"2795",
    "sg:province":"NSW",
    "sg:tags":[
        "coating",
        "powder"
    ],
    "wof:name":"Bathurst Custom Powder Coating",
    "wof:placetype":"venue"
},
  "geometry": {"coordinates":[149.60839843799999,-33.4234657288],"type":"Point"}
}