{
  "type": "Feature",
  "properties": {
    "iso:country":"AU",
    "sg:address":"Cozens St",
    "sg:city":"Wangaratta",
    "sg:classifiers":[
        {
            "category":"Building & Trades",
            "subcategory":"Equipment Rental",
            "type":"Services"
        }
    ],
    "sg:phone":"+61 417 500 050",
    "sg:postcode":"3677",
    "sg:province":"VIC",
    "sg:tags":[
        "crane",
        "hire"
    ],
    "wof:name":"Dunns Crane & Access Hire Pty Ltd",
    "wof:placetype":"venue"
},
  "geometry": {"coordinates":[146.31263732900001,-36.3677711487],"type":"Point"}
}