{
  "type": "Feature",
  "properties": {
    "addr:full":"36 Renshaw St Doncaster East VIC 3109",
    "addr:housenumber":"36",
    "addr:postcode":"3109",
    "addr:street":"Renshaw St",
    "iso:country":"AU",
    "sg:address":"36 Renshaw St",
    "sg:city":"Doncaster East",
    "sg:classifiers":[
        {
            "category":"Shopping",
            "subcategory":"Clothing, Apparel, & Fashions",
            "type":"Retail Goods"
        }
    ],
    "sg:phone":"+61 3 9891 8328",
    "sg:postcode":"3109",
    "sg:province":"VIC",
    "sg:tags":[
        "uniform"
    ],
    "wof:name":"Lijian Fashion",
    "wof:placetype":"venue"
},
  "geometry": {"coordinates":[145.14663696299999,-37.7943687439],"type":"Point"}
}