{
  "type": "Feature",
  "properties": {
    "addr:full":"1/ 5 Deering St Ulladulla NSW 2539",
    "addr:housenumber":"/ 5",
    "addr:postcode":"2539",
    "addr:street":"Deering St",
    "iso:country":"AU",
    "sg:address":"1/ 5 Deering St",
    "sg:city":"Ulladulla",
    "sg:classifiers":[
        {
            "category":"Building & Trades",
            "subcategory":"Construction",
            "type":"Services"
        }
    ],
    "sg:phone":"+61 2 4455 3861",
    "sg:postcode":"2539",
    "sg:province":"NSW",
    "sg:tags":[
        "contractor"
    ],
    "wof:name":"Len Watt Building",
    "wof:placetype":"venue"
},
  "geometry": {"coordinates":[150.46556091299999,-35.3611869812],"type":"Point"}
}