{
  "type": "Feature",
  "properties": {
    "addr:full":"112 Giles Rd Redland Bay QLD 4165",
    "addr:housenumber":"112",
    "addr:postcode":"4165",
    "addr:street":"Giles Rd",
    "iso:country":"AU",
    "sg:address":"112 Giles Rd",
    "sg:city":"Redland Bay",
    "sg:classifiers":[
        {
            "category":"Professional",
            "type":"Services"
        }
    ],
    "sg:phone":"+61 7 3206 8633",
    "sg:postcode":"4165",
    "sg:province":"QLD",
    "sg:tags":[
        "transport"
    ],
    "wof:name":"Bay Island Carriers",
    "wof:placetype":"venue"
},
  "geometry": {"coordinates":[153.26377868599999,-27.6118831635],"type":"Point"}
}