{
  "type": "Feature",
  "properties": {
    "iso:country":"AU",
    "sg:address":"92 Ordish Rd",
    "sg:city":"Dandenong South",
    "sg:classifiers":[
        {
            "category":"Utilities",
            "subcategory":"Refuse",
            "type":"Services"
        }
    ],
    "sg:phone":"+61 1300 657 057",
    "sg:postcode":"3175",
    "sg:province":"VIC",
    "sg:tags":[
        "disposal",
        "reduction",
        "waste"
    ],
    "wof:name":"Teris (Aust) Pty Ltd",
    "wof:placetype":"venue"
},
  "geometry": {"coordinates":[145.192504883,-38.0263633728],"type":"Point"}
}