{
  "type": "Feature",
  "properties": {
    "iso:country":"AU",
    "sg:address":"Cnr Grieve Pde & Dohertys Rd",
    "sg:city":"Altona North",
    "sg:classifiers":[
        {
            "category":"Sports & Exercise",
            "subcategory":"Sports Center",
            "type":"Entertainment"
        }
    ],
    "sg:phone":"+61 3 9369 6888",
    "sg:postcode":"3025",
    "sg:province":"VIC",
    "sg:tags":[
        "ground"
    ],
    "wof:name":"Westgate indoor Sports",
    "wof:placetype":"venue"
},
  "geometry": {"coordinates":[144.829193,-37.827606],"type":"Point"}
}