{
  "type": "Feature",
  "properties": {
    "addr:full":"97 Hampton Drv Tannum Sands QLD 4680",
    "addr:housenumber":"97",
    "addr:postcode":"4680",
    "addr:street":"Hampton Drv",
    "iso:country":"AU",
    "sg:address":"97 Hampton Drv",
    "sg:city":"Tannum Sands",
    "sg:classifiers":[
        {
            "category":"Communications",
            "subcategory":"Film & Video Production",
            "type":"Services"
        }
    ],
    "sg:phone":"+61 7 4973 7288",
    "sg:postcode":"4680",
    "sg:province":"QLD",
    "sg:tags":[
        "dvd",
        "library"
    ],
    "wof:name":"C & J Leading Edge Video",
    "wof:placetype":"venue"
},
  "geometry": {"coordinates":[151.36912536599999,-23.9509735107],"type":"Point"}
}