{
  "type": "Feature",
  "properties": {
    "addr:full":"132 Waples Rd Unanderra NSW 2526",
    "addr:housenumber":"132",
    "addr:postcode":"2526",
    "addr:street":"Waples Rd",
    "iso:country":"AU",
    "sg:address":"132 Waples Rd",
    "sg:city":"Unanderra",
    "sg:classifiers":[
        {
            "category":"Building & Trades",
            "subcategory":"Plumbing",
            "type":"Services"
        }
    ],
    "sg:phone":"+61 2 4271 7792",
    "sg:postcode":"2526",
    "sg:province":"NSW",
    "sg:tags":[
        "plumber",
        "gasfitters"
    ],
    "wof:name":"Malone L K & B A",
    "wof:placetype":"venue"
},
  "geometry": {"coordinates":[150.829986572,-34.4554748535],"type":"Point"}
}