{
  "type": "Feature",
  "properties": {
    "addr:full":"6 Bokhara Rd South Caulfield VIC 3162",
    "addr:housenumber":"6",
    "addr:postcode":"3162",
    "addr:street":"Bokhara Rd South",
    "iso:country":"AU",
    "sg:address":"6 Bokhara Rd South",
    "sg:city":"Caulfield",
    "sg:classifiers":[
        {
            "category":"Professional",
            "subcategory":"Business Services",
            "type":"Services"
        }
    ],
    "sg:phone":"+61 412 026 318",
    "sg:postcode":"3162",
    "sg:province":"VIC",
    "sg:tags":[
        "broker"
    ],
    "wof:name":"All Encompasing Business Solutions",
    "wof:placetype":"venue"
},
  "geometry": {"coordinates":[145.028442383,-37.8930625916],"type":"Point"}
}