{
  "type": "Feature",
  "properties": {
    "addr:full":"387 Hamilton Rd Fairfield West NSW 2165",
    "addr:housenumber":"387",
    "addr:postcode":"2165",
    "addr:street":"Hamilton Rd",
    "iso:country":"AU",
    "sg:address":"387 Hamilton Rd",
    "sg:city":"Fairfield West",
    "sg:classifiers":[
        {
            "category":"Retail",
            "subcategory":"Veterinary Services",
            "type":"Services"
        }
    ],
    "sg:phone":"+61 2 9609 3105",
    "sg:postcode":"2165",
    "sg:province":"NSW",
    "sg:tags":[
        "surgeon"
    ],
    "wof:name":"Bajwa H",
    "wof:placetype":"venue"
},
  "geometry": {"coordinates":[150.92221069300001,-33.8690605164],"type":"Point"}
}