{
  "type": "Feature",
  "properties": {
    "iso:country":"AU",
    "sg:address":"U2/ 8a Action St",
    "sg:city":"Noosaville",
    "sg:classifiers":[
        {
            "category":"Professional",
            "subcategory":"Art Services",
            "type":"Services"
        }
    ],
    "sg:phone":"+61 7 5470 2211",
    "sg:postcode":"4566",
    "sg:province":"QLD",
    "sg:tags":[
        "interior",
        "designer"
    ],
    "wof:name":"Skc Design Pty Ltd",
    "wof:placetype":"venue"
},
  "geometry": {"coordinates":[153.04377746599999,-26.4148082733],"type":"Point"}
}