{
  "type": "Feature",
  "properties": {
    "iso:country":"AU",
    "sg:address":"117 Gordon St",
    "sg:city":"Naracoorte",
    "sg:classifiers":[
        {
            "category":"Autos & Motor Vehicles",
            "subcategory":"Fuel & Gas Station",
            "type":"Retail Goods"
        }
    ],
    "sg:phone":"+61 8 8762 1106",
    "sg:postcode":"5271",
    "sg:province":"SA",
    "wof:name":"South Australian Farmers Fuel",
    "wof:placetype":"venue"
},
  "geometry": {"coordinates":[140.739563,-36.969604],"type":"Point"}
}