{
  "type": "Feature",
  "properties": {
    "addr:full":"Unit 1/ 14 Wellington St Acacia Ridge QLD 4110",
    "addr:housenumber":"14",
    "addr:postcode":"4110",
    "addr:street":"Wellington St",
    "iso:country":"AU",
    "sg:address":"Unit 1/ 14 Wellington St",
    "sg:city":"Acacia Ridge",
    "sg:classifiers":[
        {
            "category":"Autos & Motor Vehicles",
            "subcategory":"Automobile Sales",
            "type":"Retail Goods"
        }
    ],
    "sg:phone":"+61 7 3274 2655",
    "sg:postcode":"4110",
    "sg:province":"QLD",
    "sg:tags":[
        "car",
        "new"
    ],
    "wof:name":"Carsales.com.au",
    "wof:placetype":"venue"
},
  "geometry": {"coordinates":[153.02833557100001,-27.5880699158],"type":"Point"}
}