{
  "type": "Feature",
  "properties": {
    "addr:full":"7 Seppelt St Eastern Creek NSW 2766",
    "addr:housenumber":"7",
    "addr:postcode":"2766",
    "addr:street":"Seppelt St",
    "iso:country":"AU",
    "sg:address":"7 Seppelt St",
    "sg:city":"Eastern Creek",
    "sg:classifiers":[
        {
            "category":"Shopping",
            "subcategory":"Stationery & Office Supplies",
            "type":"Retail Goods"
        }
    ],
    "sg:phone":"+61 414 906 801",
    "sg:postcode":"2766",
    "sg:province":"NSW",
    "sg:tags":[
        "packaging",
        "material"
    ],
    "wof:name":"Reel Packaging 2000",
    "wof:placetype":"venue"
},
  "geometry": {"coordinates":[150.84889221200001,-33.7864570618],"type":"Point"}
}