{
  "type": "Feature",
  "properties": {
    "iso:country":"AU",
    "sg:address":"218 Cheltenham Rd",
    "sg:city":"Keysborough",
    "sg:classifiers":[
        {
            "category":"Autos & Motor Vehicles",
            "subcategory":"Auto Supplies",
            "type":"Retail Goods"
        }
    ],
    "sg:phone":"+61 3 9798 6560",
    "sg:postcode":"3173",
    "sg:province":"VIC",
    "sg:tags":[
        "part",
        "cycles",
        "accessory"
    ],
    "wof:name":"Motorcycle Cosmetics",
    "wof:placetype":"venue"
},
  "geometry": {"coordinates":[145.185546875,-37.9945068359],"type":"Point"}
}