{
  "type": "Feature",
  "properties": {
    "addr:full":"160 Beaudesert Rd Moorooka QLD 4105",
    "addr:housenumber":"160",
    "addr:postcode":"4105",
    "addr:street":"Beaudesert Rd",
    "iso:country":"AU",
    "sg:address":"160 Beaudesert Rd",
    "sg:city":"Moorooka",
    "sg:classifiers":[
        {
            "category":"Food & Beverages",
            "subcategory":"Fruits & Vegetables",
            "type":"Retail Goods"
        }
    ],
    "sg:phone":"+61 7 3892 1801",
    "sg:postcode":"4105",
    "sg:province":"QLD",
    "sg:tags":[
        "greengrocer",
        "fruiterer"
    ],
    "wof:name":"Greenvale Fruit Market",
    "wof:placetype":"venue"
},
  "geometry": {"coordinates":[153.02458190900001,-27.5321369171],"type":"Point"}
}