{
  "type": "Feature",
  "properties": {
    "iso:country":"AU",
    "sg:address":"Level 1 / 33 Colbee Crt",
    "sg:city":"Phillip",
    "sg:classifiers":[
        {
            "category":"Health Services",
            "subcategory":"Health Practitioner",
            "type":"Services"
        }
    ],
    "sg:phone":"+61 2 6112 7070",
    "sg:postcode":"2606",
    "sg:province":"ACT",
    "sg:tags":[
        "physiotherapist"
    ],
    "wof:name":"Phillip Physiotherapy Clinic",
    "wof:placetype":"venue"
},
  "geometry": {"coordinates":[149.08949279800001,-35.3516540527],"type":"Point"}
}