{
  "type": "Feature",
  "properties": {
    "addr:full":"Factory 22/55 Graham Crt Hoppers Crossing VIC 3029",
    "addr:housenumber":"22 / 55",
    "addr:postcode":"3029",
    "addr:street":"Graham Crt",
    "iso:country":"AU",
    "sg:address":"Factory 22/55 Graham Crt",
    "sg:city":"Hoppers Crossing",
    "sg:classifiers":[
        {
            "category":"Building & Trades",
            "subcategory":"Construction",
            "type":"Services"
        }
    ],
    "sg:phone":"+61 3 9931 1266",
    "sg:postcode":"3029",
    "sg:province":"VIC",
    "sg:tags":[
        "fencing",
        "contractor"
    ],
    "wof:name":"A-Comfence Pty Ltd",
    "wof:placetype":"venue"
},
  "geometry": {"coordinates":[144.72903400000001,-37.872608],"type":"Point"}
}