{
  "type": "Feature",
  "properties": {
    "iso:country":"AU",
    "sg:address":"Suite 1/ 50 Harrison. St",
    "sg:city":"Cardiff",
    "sg:classifiers":[
        {
            "category":"Health Services",
            "subcategory":"Doctor",
            "type":"Services"
        }
    ],
    "sg:phone":"+61 2 4954 8479",
    "sg:postcode":"2285",
    "sg:province":"NSW",
    "sg:tags":[
        "podiatrist"
    ],
    "wof:name":"Cardiff Podiatry Clinic",
    "wof:placetype":"venue"
},
  "geometry": {"coordinates":[151.617874145,-32.9202575684],"type":"Point"}
}