{
  "type": "Feature",
  "properties": {
    "addr:full":"Wheelers Hill Shopping Centre, Jells Rd Wheelers Hill VIC 3150",
    "addr:postcode":"3150",
    "addr:street":"Jells Rd",
    "iso:country":"AU",
    "sg:address":"Wheelers Hill Shopping Centre, Jells Rd",
    "sg:city":"Wheelers Hill",
    "sg:classifiers":[
        {
            "category":"Food & Beverages",
            "subcategory":"Liquor & Beverages",
            "type":"Retail Goods"
        }
    ],
    "sg:phone":"+61 3 9560 2411",
    "sg:postcode":"3150",
    "sg:province":"VIC",
    "sg:tags":[
        "store"
    ],
    "wof:name":"Safeway Liquor",
    "wof:placetype":"venue"
},
  "geometry": {"coordinates":[145.18919372600001,-37.9060401917],"type":"Point"}
}