{
  "type": "Feature",
  "properties": {
    "addr:full":"Shp 2, 379 Victoria Ave Chatswood NSW 2067",
    "addr:housenumber":"379",
    "addr:postcode":"2067",
    "addr:street":"Victoria Ave",
    "iso:country":"AU",
    "sg:address":"Shp 2, 379 Victoria Ave",
    "sg:city":"Chatswood",
    "sg:classifiers":[
        {
            "category":"Shopping",
            "subcategory":"Clothing, Apparel, & Fashions",
            "type":"Retail Goods"
        }
    ],
    "sg:phone":"+61 2 9415 4866",
    "sg:postcode":"2067",
    "sg:province":"NSW",
    "sg:tags":[
        "lady",
        "wear"
    ],
    "wof:name":"Victoria Cooper",
    "wof:placetype":"venue"
},
  "geometry": {"coordinates":[151.18539428700001,-33.795463562],"type":"Point"}
}