{
  "type": "Feature",
  "properties": {
    "addr:full":"Victoria St Gosford East NSW 2250",
    "addr:postcode":"2250",
    "addr:street":"Victoria St",
    "iso:country":"AU",
    "sg:address":"Victoria St",
    "sg:city":"Gosford East",
    "sg:classifiers":[
        {
            "category":"Education",
            "subcategory":"Music School",
            "type":"Public Place"
        }
    ],
    "sg:phone":"+61 2 4325 5777",
    "sg:postcode":"2250",
    "sg:province":"NSW",
    "sg:tags":[
        "therapy",
        "relaxation"
    ],
    "wof:name":"Jenny Nicholson",
    "wof:placetype":"venue"
},
  "geometry": {"coordinates":[151.35215759299999,-33.436050415],"type":"Point"}
}