{
  "type": "Feature",
  "properties": {
    "iso:country":"AU",
    "sg:address":"Shop 3/ 11 Ocean Grove Ave",
    "sg:city":"Cronulla",
    "sg:classifiers":[
        {
            "category":"Shopping",
            "subcategory":"Shoes",
            "type":"Retail Goods"
        }
    ],
    "sg:phone":"+61 2 9527 0288",
    "sg:postcode":"2230",
    "sg:province":"NSW",
    "sg:tags":[
        "footwear"
    ],
    "wof:name":"Miss Diva",
    "wof:placetype":"venue"
},
  "geometry": {"coordinates":[151.15341186500001,-34.053478241],"type":"Point"}
}