{
  "type": "Feature",
  "properties": {
    "addr:full":"Viewmount Rd Glen Waverley VIC 3150",
    "addr:postcode":"3150",
    "addr:street":"Viewmount Rd",
    "iso:country":"AU",
    "sg:address":"Viewmount Rd",
    "sg:city":"Glen Waverley",
    "sg:classifiers":[
        {
            "category":"Education",
            "subcategory":"Kindergarten",
            "type":"Public Place"
        }
    ],
    "sg:phone":"+61 3 9560 2735",
    "sg:postcode":"3150",
    "sg:province":"VIC",
    "sg:tags":[
        "pre-schools"
    ],
    "wof:name":"Brentwood Pre School",
    "wof:placetype":"venue"
},
  "geometry": {"coordinates":[145.17628479000001,-37.890789032],"type":"Point"}
}