{
  "type": "Feature",
  "properties": {
    "addr:full":"PO Box 2032 Hampton East VIC 3188",
    "addr:postcode":"3188",
    "iso:country":"AU",
    "sg:address":"PO Box 2032",
    "sg:city":"Hampton East",
    "sg:classifiers":[
        {
            "category":"Building & Trades",
            "subcategory":"Construction",
            "type":"Services"
        }
    ],
    "sg:phone":"+61 411 329 084",
    "sg:postcode":"3188",
    "sg:province":"VIC",
    "sg:tags":[
        "fencing",
        "contractor"
    ],
    "wof:name":"Concorde Fences & Gates",
    "wof:placetype":"venue"
},
  "geometry": {"coordinates":[145.025299072,-37.9317817688],"type":"Point"}
}