{
  "type": "Feature",
  "properties": {
    "addr:full":"29 Green Rd Hillarys WA 6025",
    "addr:housenumber":"29",
    "addr:postcode":"6025",
    "addr:street":"Green Rd",
    "iso:country":"AU",
    "sg:address":"29 Green Rd",
    "sg:city":"Hillarys",
    "sg:classifiers":[
        {
            "category":"Health Services",
            "subcategory":"Chiropractor",
            "type":"Services"
        }
    ],
    "sg:phone":"+61 8 9403 4450",
    "sg:postcode":"6025",
    "sg:province":"WA",
    "wof:name":"Whitfords Chiropractic",
    "wof:placetype":"venue"
},
  "geometry": {"coordinates":[115.75057983400001,-31.7986297607],"type":"Point"}
}