{
  "type": "Feature",
  "properties": {
    "addr:full":"243 Belmore Rd Balwyn North VIC 3104",
    "addr:housenumber":"243",
    "addr:postcode":"3104",
    "addr:street":"Belmore Rd",
    "iso:country":"AU",
    "sg:address":"243 Belmore Rd",
    "sg:city":"Balwyn North",
    "sg:classifiers":[
        {
            "category":"Food & Beverages",
            "subcategory":"Liquor & Beverages",
            "type":"Retail Goods"
        }
    ],
    "sg:phone":"+61 3 9859 1111",
    "sg:postcode":"3104",
    "sg:province":"VIC",
    "sg:tags":[
        "store"
    ],
    "wof:name":"Belmore Cellars",
    "wof:placetype":"venue"
},
  "geometry": {"coordinates":[145.082641602,-37.8032569885],"type":"Point"}
}