{
  "type": "Feature",
  "properties": {
    "iso:country":"AU",
    "sg:address":"2 Osier Pl",
    "sg:city":"Cockatoo",
    "sg:classifiers":[
        {
            "category":"Farming",
            "subcategory":"Farm & Veterinary Services",
            "type":"Manufacturing & Wholesale Goods"
        }
    ],
    "sg:phone":"+61 3 5968 0211",
    "sg:postcode":"3781",
    "sg:province":"VIC",
    "sg:tags":[
        "blacksmith",
        "farrier"
    ],
    "wof:name":"Ryder Jamie",
    "wof:placetype":"venue"
},
  "geometry": {"coordinates":[145.50914,-37.925743],"type":"Point"}
}