{
  "type": "Feature",
  "properties": {
    "addr:full":"Shop 45 Burwood Plz Burwood NSW 2134",
    "addr:housenumber":"shop 45",
    "addr:postcode":"2134",
    "addr:street":"Burwood Plz",
    "iso:country":"AU",
    "sg:address":"Shop 45",
    "sg:city":"Burwood Plz Burwood",
    "sg:classifiers":[
        {
            "category":"Shopping",
            "subcategory":"Mobile Phones",
            "type":"Retail Goods"
        }
    ],
    "sg:phone":"+61 2 9715 2400",
    "sg:postcode":"2134",
    "sg:province":"NSW",
    "sg:tags":[
        "telephone",
        "accessory"
    ],
    "wof:name":"Communique Corporation Pty Ltd",
    "wof:placetype":"venue"
},
  "geometry": {"coordinates":[151.1040802,-33.8746261597],"type":"Point"}
}