{
  "type": "Feature",
  "properties": {
    "addr:full":"2 Bellevue Pde Wagga Wagga NSW 2650",
    "addr:housenumber":"2",
    "addr:postcode":"2650",
    "addr:street":"Bellevue Pde",
    "iso:country":"AU",
    "sg:address":"2 Bellevue Pde",
    "sg:city":"Wagga Wagga",
    "sg:classifiers":[
        {
            "category":"Communications",
            "subcategory":"Film & Video Production",
            "type":"Services"
        }
    ],
    "sg:phone":"+61 2 6922 6569",
    "sg:postcode":"2650",
    "sg:province":"NSW",
    "sg:tags":[
        "mirror"
    ],
    "wof:name":"Decorative Framing",
    "wof:placetype":"venue"
},
  "geometry": {"coordinates":[147.37057495100001,-35.1415481567],"type":"Point"}
}