{
  "type": "Feature",
  "properties": {
    "iso:country":"AU",
    "sg:address":"Shop 7, Kardinya Park Shopping Centre, Cnr South & North Lake Rd",
    "sg:city":"Kardinya",
    "sg:classifiers":[
        {
            "category":"Food & Beverages",
            "subcategory":"Bakery",
            "type":"Retail Goods"
        }
    ],
    "sg:phone":"+61 8 9331 3465",
    "sg:postcode":"6163",
    "sg:province":"WA",
    "sg:tags":[
        "baker"
    ],
    "wof:name":"Bakers Delight",
    "wof:placetype":"venue"
},
  "geometry": {"coordinates":[115.818192,-32.059704],"type":"Point"}
}