{
  "type": "Feature",
  "properties": {
    "addr:full":"7 Bentinck St Ballina NSW 2478",
    "addr:housenumber":"7",
    "addr:postcode":"2478",
    "addr:street":"Bentinck St",
    "iso:country":"AU",
    "sg:address":"7 Bentinck St",
    "sg:city":"Ballina",
    "sg:classifiers":[
        {
            "category":"Travel",
            "subcategory":"Hostel",
            "type":"Entertainment"
        }
    ],
    "sg:phone":"+61 2 6686 2383",
    "sg:postcode":"2478",
    "sg:province":"NSW",
    "sg:tags":[
        "home"
    ],
    "wof:name":"Ex- Services Home, Ballina",
    "wof:placetype":"venue"
},
  "geometry": {"coordinates":[153.57049560600001,-28.8672294617],"type":"Point"}
}