{
  "type": "Feature",
  "properties": {
    "iso:country":"AU",
    "sg:address":"L1 991 Whitehorse Rd",
    "sg:city":"Box Hill",
    "sg:classifiers":[
        {
            "category":"Professional",
            "subcategory":"Computer Services",
            "type":"Services"
        }
    ],
    "sg:phone":"+61 3 9899 4681",
    "sg:postcode":"3128",
    "sg:province":"VIC",
    "sg:tags":[
        "package",
        "software"
    ],
    "wof:name":"Cortex I.T. Pty Ltd",
    "wof:placetype":"venue"
},
  "geometry": {"coordinates":[145.12496948200001,-37.8178977966],"type":"Point"}
}