{
  "type": "Feature",
  "properties": {
    "iso:country":"AU",
    "sg:address":"PO Box 286",
    "sg:city":"Ceduna",
    "sg:classifiers":[
        {
            "category":"Utilities",
            "subcategory":"Electric",
            "type":"Services"
        }
    ],
    "sg:phone":"+61 8 8625 2930",
    "sg:postcode":"5690",
    "sg:province":"SA",
    "sg:tags":[
        "electrical",
        "contractor"
    ],
    "wof:name":"JR & DM Cooper",
    "wof:placetype":"venue"
},
  "geometry": {"coordinates":[133.67449951200001,-32.1211509705],"type":"Point"}
}