{
  "type": "Feature",
  "properties": {
    "iso:country":"AU",
    "sg:address":"79 Longhill Rd",
    "sg:city":"Gilston",
    "sg:classifiers":[
        {
            "category":"Building & Trades",
            "subcategory":"Construction",
            "type":"Services"
        }
    ],
    "sg:phone":"+61 7 5533 2544",
    "sg:postcode":"4211",
    "sg:province":"QLD",
    "sg:tags":[
        "contractor"
    ],
    "wof:name":"JaG# Civil Pty Ltd",
    "wof:placetype":"venue"
},
  "geometry": {"coordinates":[153.31022644000001,-28.0246429443],"type":"Point"}
}