{
  "type": "Feature",
  "properties": {
    "iso:country":"AU",
    "sg:address":"18 Boundary Rd",
    "sg:city":"Emerald",
    "sg:classifiers":[
        {
            "category":"Building & Trades",
            "subcategory":"Construction",
            "type":"Services"
        }
    ],
    "sg:phone":"+61 3 5968 6487",
    "sg:postcode":"3782",
    "sg:province":"VIC",
    "sg:tags":[
        "plasterboard",
        "plasterer",
        "fixer"
    ],
    "wof:name":"Grid Commercial Ceilings Pty Ltd",
    "wof:placetype":"venue"
},
  "geometry": {"coordinates":[145.43594400000001,-37.936275],"type":"Point"}
}