{
  "type": "Feature",
  "properties": {
    "iso:country":"AU",
    "sg:address":"200 Gilbert St",
    "sg:city":"Latrobe",
    "sg:classifiers":[
        {
            "category":"Food & Beverages",
            "subcategory":"Groceries & Convenience Stores",
            "type":"Retail Goods"
        }
    ],
    "sg:phone":"+61 3 6426 1595",
    "sg:postcode":"7307",
    "sg:province":"TAS",
    "wof:name":"Top Shop Milk Bar",
    "wof:placetype":"venue"
},
  "geometry": {"coordinates":[146.418182,-41.236607],"type":"Point"}
}