{
  "type": "Feature",
  "properties": {
    "addr:full":"103 Brighton Rd Elwood VIC 3184",
    "addr:housenumber":"103",
    "addr:postcode":"3184",
    "addr:street":"Brighton Rd",
    "iso:country":"AU",
    "sg:address":"103 Brighton Rd",
    "sg:city":"Elwood",
    "sg:classifiers":[
        {
            "category":"Real Estate",
            "subcategory":"Real Estate Agent",
            "type":"Services"
        }
    ],
    "sg:phone":"+61 3 9531 1271",
    "sg:postcode":"3184",
    "sg:province":"VIC",
    "wof:name":"Morleys Body Corporate Management",
    "wof:placetype":"venue"
},
  "geometry": {"coordinates":[144.990036011,-37.8733634949],"type":"Point"}
}