{
  "type": "Feature",
  "properties": {
    "addr:full":"469 Olympic Pde Maiden Gully VIC 3551",
    "addr:housenumber":"469",
    "addr:postcode":"3551",
    "addr:street":"Olympic Pde",
    "iso:country":"AU",
    "sg:address":"469 Olympic Pde",
    "sg:city":"Maiden Gully",
    "sg:classifiers":[
        {
            "category":"Building & Trades",
            "subcategory":"Construction",
            "type":"Services"
        }
    ],
    "sg:phone":"+61 417 591 281",
    "sg:postcode":"3551",
    "sg:province":"VIC",
    "sg:tags":[
        "insulation",
        "contractor"
    ],
    "wof:name":"B Hickmans Supasuk",
    "wof:placetype":"venue"
},
  "geometry": {"coordinates":[144.22105407699999,-36.7557525635],"type":"Point"}
}