{
  "type": "Feature",
  "properties": {
    "iso:country":"AU",
    "sg:address":"PO Box 242",
    "sg:city":"Tuncurry",
    "sg:classifiers":[
        {
            "category":"Building & Trades",
            "subcategory":"Construction",
            "type":"Services"
        }
    ],
    "sg:phone":"+61 2 6559 2957",
    "sg:postcode":"2428",
    "sg:province":"NSW",
    "sg:tags":[
        "contractor"
    ],
    "wof:name":"Cape View Developments Pty. Ltd.",
    "wof:placetype":"venue"
},
  "geometry": {"coordinates":[152.499664,-32.175468],"type":"Point"}
}