{
  "type": "Feature",
  "properties": {
    "iso:country":"AU",
    "sg:address":"PO Box 318",
    "sg:city":"Yass",
    "sg:classifiers":[
        {
            "category":"Building & Trades",
            "subcategory":"Cleaning & Sanitation",
            "type":"Services"
        }
    ],
    "sg:phone":"+61 412 186 187",
    "sg:postcode":"2582",
    "sg:province":"NSW",
    "sg:tags":[
        "grease",
        "trap"
    ],
    "wof:name":"Enviro-Friendly Waste Management Pty Ltd",
    "wof:placetype":"venue"
},
  "geometry": {"coordinates":[148.91308593799999,-34.844291687],"type":"Point"}
}