{
  "type": "Feature",
  "properties": {
    "addr:full":"Factory 2 14 Gibbs St Labrador QLD 4215",
    "addr:housenumber":"14",
    "addr:postcode":"4215",
    "addr:street":"Gibbs St",
    "iso:country":"AU",
    "sg:address":"Factory 2 14 Gibbs St",
    "sg:city":"Labrador",
    "sg:classifiers":[
        {
            "category":"Manufacturing",
            "subcategory":"Glass & Minerals",
            "type":"Manufacturing & Wholesale Goods"
        }
    ],
    "sg:phone":"+61 7 5563 9111",
    "sg:postcode":"4215",
    "sg:province":"QLD",
    "sg:tags":[
        "merchant",
        "granite",
        "marble"
    ],
    "wof:name":"Urban One Marble & Granite",
    "wof:placetype":"venue"
},
  "geometry": {"coordinates":[153.411819458,-27.9736366272],"type":"Point"}
}