{
  "type": "Feature",
  "properties": {
    "addr:full":"U47/ 7 Herbert St St Leonards NSW 2065",
    "addr:housenumber":"7",
    "addr:postcode":"2065",
    "addr:street":"/;Herbert St",
    "iso:country":"AU",
    "sg:address":"U47/ 7 Herbert St St",
    "sg:city":"Leonards",
    "sg:classifiers":[
        {
            "category":"Professional",
            "subcategory":"Management & Consulting",
            "type":"Services"
        }
    ],
    "sg:phone":"+61 2 9460 8266",
    "sg:postcode":"2065",
    "sg:province":"NSW",
    "sg:tags":[
        "consultant",
        "business"
    ],
    "wof:name":"People Strategists International The",
    "wof:placetype":"venue"
},
  "geometry": {"coordinates":[151.19358825699999,-33.8219528198],"type":"Point"}
}