{
  "type": "Feature",
  "properties": {
    "addr:full":"80 Gipps St Smithfield NSW 2164",
    "addr:housenumber":"80",
    "addr:postcode":"2164",
    "addr:street":"Gipps St",
    "iso:country":"AU",
    "sg:address":"80 Gipps St",
    "sg:city":"Smithfield",
    "sg:classifiers":[
        {
            "category":"Home & Garden",
            "subcategory":"Building Materials",
            "type":"Retail Goods"
        }
    ],
    "sg:phone":"+61 2 9604 3917",
    "sg:postcode":"2164",
    "sg:province":"NSW",
    "sg:tags":[
        "supply"
    ],
    "wof:name":"Wilmots Building Suppliers",
    "wof:placetype":"venue"
},
  "geometry": {"coordinates":[150.92190551799999,-33.8515472412],"type":"Point"}
}