{
  "type": "Feature",
  "properties": {
    "addr:full":"Shop 11B 39 Avoca Drv Kincumber NSW 2251",
    "addr:housenumber":"39",
    "addr:postcode":"2251",
    "addr:street":"Shop 11B;Avoca Drv",
    "iso:country":"AU",
    "sg:address":"Shop 11B 39 Avoca Drv",
    "sg:city":"Kincumber",
    "sg:classifiers":[
        {
            "category":"Health Services",
            "subcategory":"Dentist",
            "type":"Services"
        }
    ],
    "sg:phone":"+61 2 4369 5944",
    "sg:postcode":"2251",
    "sg:province":"NSW",
    "sg:tags":[
        "dental",
        "prosthetist"
    ],
    "wof:name":"Dominguez Geoffrey",
    "wof:placetype":"venue"
},
  "geometry": {"coordinates":[151.38166809099999,-33.4675331116],"type":"Point"}
}