{
  "type": "Feature",
  "properties": {
    "iso:country":"AU",
    "sg:address":"2 36 Balaclava Rd",
    "sg:city":"Eastwood",
    "sg:classifiers":[
        {
            "category":"Professional",
            "subcategory":"Art Services",
            "type":"Services"
        }
    ],
    "sg:phone":"+61 2 9874 1624",
    "sg:postcode":"2122",
    "sg:province":"NSW",
    "sg:tags":[
        "graphic",
        "designer"
    ],
    "wof:name":"Vivarium",
    "wof:placetype":"venue"
},
  "geometry": {"coordinates":[151.09078979500001,-33.7853813171],"type":"Point"}
}