{
  "type": "Feature",
  "properties": {
    "iso:country":"AU",
    "sg:address":"38 Tarnett Rd",
    "sg:city":"Werribee",
    "sg:classifiers":[
        {
            "category":"Professional",
            "subcategory":"Detective & Security Services",
            "type":"Services"
        }
    ],
    "sg:phone":"+61 3 9742 5827",
    "sg:postcode":"3030",
    "sg:province":"VIC",
    "sg:tags":[
        "consultant",
        "system"
    ],
    "wof:name":"Anti Theft Security",
    "wof:placetype":"venue"
},
  "geometry": {"coordinates":[144.662933,-37.894062],"type":"Point"}
}