{
  "type": "Feature",
  "properties": {
    "addr:full":"18 Main St Foster VIC 3960",
    "addr:housenumber":"18",
    "addr:postcode":"3960",
    "addr:street":"Main St",
    "iso:country":"AU",
    "sg:address":"18 Main St",
    "sg:city":"Foster",
    "sg:classifiers":[
        {
            "category":"Real Estate",
            "subcategory":"Surveying",
            "type":"Services"
        }
    ],
    "sg:phone":"+61 3 5682 2661",
    "sg:postcode":"3960",
    "sg:province":"VIC",
    "sg:tags":[
        "surveyor",
        "land"
    ],
    "wof:name":"Ken Richardson Surveyors",
    "wof:placetype":"venue"
},
  "geometry": {"coordinates":[146.38706970199999,-38.7091407776],"type":"Point"}
}