{
  "type": "Feature",
  "properties": {
    "iso:country":"AU",
    "sg:address":"Suite 1, 39 - 41 Nerang St",
    "sg:city":"Nerang",
    "sg:classifiers":[
        {
            "category":"Personal",
            "subcategory":"Beauty Salon",
            "type":"Services"
        }
    ],
    "sg:phone":"+61 7 5596 5722",
    "sg:postcode":"4211",
    "sg:province":"QLD",
    "sg:tags":[
        "hairdresser"
    ],
    "wof:name":"Lisa Marie Studio",
    "wof:placetype":"venue"
},
  "geometry": {"coordinates":[153.33700561500001,-27.9907302856],"type":"Point"}
}