{
  "type": "Feature",
  "properties": {
    "iso:country":"AU",
    "sg:address":"87 Nelson St",
    "sg:city":"Wallsend",
    "sg:classifiers":[
        {
            "category":"Health Services",
            "subcategory":"Doctor",
            "type":"Services"
        }
    ],
    "sg:phone":"+61 2 4951 3555",
    "sg:postcode":"2287",
    "sg:province":"NSW",
    "sg:tags":[
        "medical",
        "practitioner"
    ],
    "wof:name":"Khaira T P",
    "wof:placetype":"venue"
},
  "geometry": {"coordinates":[151.66903686500001,-32.9008102417],"type":"Point"}
}