{
  "type": "Feature",
  "properties": {
    "iso:country":"AU",
    "sg:address":"124 Parade Rd",
    "sg:city":"Usher",
    "sg:classifiers":[
        {
            "category":"Health Services",
            "subcategory":"Doctor",
            "type":"Services"
        }
    ],
    "sg:phone":"+61 8 9795 2555",
    "sg:postcode":"6230",
    "sg:province":"WA",
    "sg:tags":[
        "medical",
        "practitioner"
    ],
    "wof:name":"Waycott D J",
    "wof:placetype":"venue"
},
  "geometry": {"coordinates":[115.633904,-33.3755],"type":"Point"}
}