{
  "type": "Feature",
  "properties": {
    "addr:full":"23 Louise St Atherton QLD 4883",
    "addr:housenumber":"23",
    "addr:postcode":"4883",
    "addr:street":"Louise St",
    "iso:country":"AU",
    "sg:address":"23 Louise St",
    "sg:city":"Atherton",
    "sg:classifiers":[
        {
            "category":"Food & Beverages",
            "subcategory":"Supermarket",
            "type":"Retail Goods"
        }
    ],
    "sg:phone":"+61 7 4091 1941",
    "sg:postcode":"4883",
    "sg:province":"QLD",
    "sg:tags":[
        "grocery",
        "store"
    ],
    "wof:name":"Louies Supermarket",
    "wof:placetype":"venue"
},
  "geometry": {"coordinates":[145.48191833499999,-17.2673511505],"type":"Point"}
}