{
  "type": "Feature",
  "properties": {
    "addr:full":"Shop 212 , Castle Towers Shopping Centre, Castle Stree NSW 2154",
    "addr:housenumber":"212",
    "addr:postcode":"2154",
    "addr:street":"Castle;Castle Stree",
    "iso:country":"AU",
    "sg:address":"Shop 212",
    "sg:city":", Castle Towers Shopping Centre, Castle Stree",
    "sg:classifiers":[
        {
            "category":"Shopping",
            "subcategory":"Mobile Phones",
            "type":"Retail Goods"
        }
    ],
    "sg:phone":"+61 2 9894 4311",
    "sg:postcode":"2154",
    "sg:province":"NSW",
    "sg:tags":[
        "telephone",
        "accessory"
    ],
    "wof:name":"Allphones",
    "wof:placetype":"venue"
},
  "geometry": {"coordinates":[151.00462341299999,-33.7314338684],"type":"Point"}
}