{
  "type": "Feature",
  "properties": {
    "addr:full":"361 Victoria St Deniliquin NSW 2710",
    "addr:housenumber":"361",
    "addr:postcode":"2710",
    "addr:street":"Victoria St",
    "iso:country":"AU",
    "sg:address":"361 Victoria St",
    "sg:city":"Deniliquin",
    "sg:classifiers":[
        {
            "category":"Building & Trades",
            "subcategory":"Construction",
            "type":"Services"
        }
    ],
    "sg:phone":"+61 3 5881 3939",
    "sg:postcode":"2710",
    "sg:province":"NSW",
    "sg:tags":[
        "concrete",
        "contractor"
    ],
    "wof:name":"Fisher K J & S C",
    "wof:placetype":"venue"
},
  "geometry": {"coordinates":[144.976852417,-35.5189933777],"type":"Point"}
}