{
  "type": "Feature",
  "properties": {
    "addr:full":"42 Knoll Ave Turrella NSW 2205",
    "addr:housenumber":"42",
    "addr:postcode":"2205",
    "addr:street":"Knoll Ave",
    "iso:country":"AU",
    "sg:address":"42 Knoll Ave",
    "sg:city":"Turrella",
    "sg:classifiers":[
        {
            "category":"Health Services",
            "subcategory":"Doctor",
            "type":"Services"
        }
    ],
    "sg:phone":"+61 2 9567 1565",
    "sg:postcode":"2205",
    "sg:province":"NSW",
    "sg:tags":[
        "occupational",
        "safety"
    ],
    "wof:name":"Safety Improvement Services",
    "wof:placetype":"venue"
},
  "geometry": {"coordinates":[151.14721700000001,-33.930466],"type":"Point"}
}