{
  "type": "Feature",
  "properties": {
    "addr:full":"53 Bayswater Rd Rushcutters Bay NSW 2011",
    "addr:housenumber":"53",
    "addr:postcode":"2011",
    "addr:street":"Bayswater Rd",
    "iso:country":"AU",
    "sg:address":"53 Bayswater Rd",
    "sg:city":"Rushcutters Bay",
    "sg:classifiers":[
        {
            "category":"Personal",
            "subcategory":"Beauty Salon",
            "type":"Services"
        }
    ],
    "sg:phone":"+61 2 9361 6261",
    "sg:postcode":"2011",
    "sg:province":"NSW",
    "sg:tags":[
        "hairdresser"
    ],
    "wof:name":"Bardetta Joe",
    "wof:placetype":"venue"
},
  "geometry": {"coordinates":[151.22456359899999,-33.8753433228],"type":"Point"}
}