{
  "type": "Feature",
  "properties": {
    "addr:full":"21A Redleaf Ave Wahroonga NSW 2076",
    "addr:housenumber":"21a",
    "addr:postcode":"2076",
    "addr:street":"Redleaf Ave",
    "iso:country":"AU",
    "sg:address":"21A Redleaf Ave",
    "sg:city":"Wahroonga",
    "sg:classifiers":[
        {
            "category":"Health Services",
            "subcategory":"Chiropractor",
            "type":"Services"
        }
    ],
    "sg:phone":"+61 2 9487 2607",
    "sg:postcode":"2076",
    "sg:province":"NSW",
    "wof:name":"Filan Andy",
    "wof:placetype":"venue"
},
  "geometry": {"coordinates":[151.11723327600001,-33.7187423706],"type":"Point"}
}