{
  "type": "Feature",
  "properties": {
    "addr:full":"6- 8 Betts St Goulburn NSW 2580",
    "addr:housenumber":"8",
    "addr:postcode":"2580",
    "addr:street":"Betts St",
    "iso:country":"AU",
    "sg:address":"6- 8 Betts St",
    "sg:city":"Goulburn",
    "sg:classifiers":[
        {
            "category":"Utilities",
            "subcategory":"Water",
            "type":"Services"
        }
    ],
    "sg:phone":"+61 418 665 321",
    "sg:postcode":"2580",
    "sg:province":"NSW",
    "sg:tags":[
        "hot",
        "system"
    ],
    "wof:name":"Stephen Hazelton",
    "wof:placetype":"venue"
},
  "geometry": {"coordinates":[149.703125,-34.7532501221],"type":"Point"}
}