{
  "type": "Feature",
  "properties": {
    "addr:full":"5 Front St Mossman QLD 4873",
    "addr:housenumber":"5",
    "addr:postcode":"4873",
    "addr:street":"Front St",
    "iso:country":"AU",
    "sg:address":"5 Front St",
    "sg:city":"Mossman",
    "sg:classifiers":[
        {
            "category":"Cafe",
            "type":"Food & Drink"
        }
    ],
    "sg:phone":"+61 7 4098 1660",
    "sg:postcode":"4873",
    "sg:province":"QLD",
    "wof:name":"Palm Cafe",
    "wof:placetype":"venue"
},
  "geometry": {"coordinates":[145.37351989699999,-16.4594020844],"type":"Point"}
}