{
  "type": "Feature",
  "properties": {
    "iso:country":"AU",
    "sg:address":"PO Box 52",
    "sg:city":"Wycheproof",
    "sg:classifiers":[
        {
            "category":"Building & Trades",
            "subcategory":"Plumbing",
            "type":"Services"
        }
    ],
    "sg:phone":"+61 418 338 758",
    "sg:postcode":"3527",
    "sg:province":"VIC",
    "sg:tags":[
        "plumber",
        "gasfitters"
    ],
    "wof:name":"Stewart Nicholls Plumbing",
    "wof:placetype":"venue"
},
  "geometry": {"coordinates":[143.225494,-36.08107],"type":"Point"}
}