{
  "type": "Feature",
  "properties": {
    "addr:full":"Shop 3/ 10 McLaughlin St Gracemere QLD 4702",
    "addr:housenumber":"shop 3 / 10",
    "addr:postcode":"4702",
    "addr:street":"Mclaughlin St",
    "iso:country":"AU",
    "sg:address":"Shop 3/ 10 McLaughlin St",
    "sg:city":"Gracemere",
    "sg:classifiers":[
        {
            "category":"Real Estate",
            "subcategory":"Developer",
            "type":"Services"
        }
    ],
    "sg:phone":"+61 7 4933 1088",
    "sg:postcode":"4702",
    "sg:province":"QLD",
    "sg:tags":[
        "development"
    ],
    "wof:name":"Kevin Briggs Real Estate",
    "wof:placetype":"venue"
},
  "geometry": {"coordinates":[150.45443725600001,-23.4341583252],"type":"Point"}
}