{
  "type": "Feature",
  "properties": {
    "iso:country":"AU",
    "sg:address":"124 Emmerson Drv",
    "sg:city":"Morphett Vale",
    "sg:classifiers":[
        {
            "category":"Manufacturing",
            "subcategory":"Food",
            "type":"Manufacturing & Wholesale Goods"
        }
    ],
    "sg:phone":"+61 8 8325 2121",
    "sg:postcode":"5162",
    "sg:province":"SA",
    "sg:tags":[
        "function",
        "catering"
    ],
    "wof:name":"McGoos Spitroast & Catering",
    "wof:placetype":"venue"
},
  "geometry": {"coordinates":[138.54542541500001,-35.1174850464],"type":"Point"}
}