{
  "type": "Feature",
  "properties": {
    "iso:country":"AU",
    "sg:address":"196 Johnstone St",
    "sg:city":"Westmeadows",
    "sg:classifiers":[
        {
            "category":"Professional",
            "subcategory":"Engineering",
            "type":"Services"
        }
    ],
    "sg:phone":"+61 3 9314 1109",
    "sg:postcode":"3049",
    "sg:province":"VIC",
    "sg:tags":[
        "civil",
        "engineer"
    ],
    "wof:name":"Boldiston Contractors Pty Ltd",
    "wof:placetype":"venue"
},
  "geometry": {"coordinates":[144.898972,-37.679653],"type":"Point"}
}