{
  "type": "Feature",
  "properties": {
    "iso:country":"AU",
    "sg:address":"Ste 6/ 234 Prospect Hwy",
    "sg:city":"Seven Hills",
    "sg:classifiers":[
        {
            "category":"Health Services",
            "subcategory":"Dentist",
            "type":"Services"
        }
    ],
    "sg:phone":"+61 2 9622 0206",
    "sg:postcode":"2147",
    "sg:province":"NSW",
    "wof:name":"Seven Hills Dental Care",
    "wof:placetype":"venue"
},
  "geometry": {"coordinates":[150.93382263199999,-33.7758178711],"type":"Point"}
}