{
  "type": "Feature",
  "properties": {
    "addr:full":"34a Alford St Kingaroy QLD 4610",
    "addr:housenumber":"34a",
    "addr:postcode":"4610",
    "addr:street":"Alford St",
    "iso:country":"AU",
    "sg:address":"34a Alford St",
    "sg:city":"Kingaroy",
    "sg:classifiers":[
        {
            "category":"Travel",
            "subcategory":"Travel Agent",
            "type":"Entertainment"
        }
    ],
    "sg:phone":"+61 7 4162 1711",
    "sg:postcode":"4610",
    "sg:province":"QLD",
    "sg:tags":[
        "consultant"
    ],
    "wof:name":"Kingaroy Travel",
    "wof:placetype":"venue"
},
  "geometry": {"coordinates":[151.83697509800001,-26.5405540466],"type":"Point"}
}