{
  "type": "Feature",
  "properties": {
    "addr:full":"345 Mullhollands Rd Thirlmere NSW 2572",
    "addr:housenumber":"345",
    "addr:postcode":"2572",
    "addr:street":"Mullhollands Rd",
    "iso:country":"AU",
    "sg:address":"345 Mullhollands Rd",
    "sg:city":"Thirlmere",
    "sg:classifiers":[
        {
            "category":"Building & Trades",
            "subcategory":"Construction",
            "type":"Services"
        }
    ],
    "sg:phone":"+61 428 231 177",
    "sg:postcode":"2572",
    "sg:province":"NSW",
    "sg:tags":[
        "earth",
        "excavating",
        "moving",
        "contractor"
    ],
    "wof:name":"Clear Lake Services",
    "wof:placetype":"venue"
},
  "geometry": {"coordinates":[150.56178283700001,-34.1792259216],"type":"Point"}
}