{
  "type": "Feature",
  "properties": {
    "addr:full":"25 Queen St Corowa NSW 2646",
    "addr:housenumber":"25",
    "addr:postcode":"2646",
    "addr:street":"Queen St",
    "iso:country":"AU",
    "sg:address":"25 Queen St",
    "sg:city":"Corowa",
    "sg:classifiers":[
        {
            "category":"Professional",
            "subcategory":"Accounting & Tax Preparation",
            "type":"Services"
        }
    ],
    "sg:phone":"+61 2 6033 2233",
    "sg:postcode":"2646",
    "sg:province":"NSW",
    "sg:tags":[
        "accountant",
        "auditor"
    ],
    "wof:name":"Potts & Schnelle",
    "wof:placetype":"venue"
},
  "geometry": {"coordinates":[146.38984680199999,-35.9971885681],"type":"Point"}
}