{
  "type": "Feature",
  "properties": {
    "addr:full":"15B Walker St Windsor South NSW 2756",
    "addr:housenumber":"15b",
    "addr:postcode":"2756",
    "addr:street":"Walker St",
    "iso:country":"AU",
    "sg:address":"15B Walker St",
    "sg:city":"Windsor South",
    "sg:classifiers":[
        {
            "category":"Farming",
            "subcategory":"Farm & Veterinary Services",
            "type":"Manufacturing & Wholesale Goods"
        }
    ],
    "sg:phone":"+61 2 4577 5457",
    "sg:postcode":"2756",
    "sg:province":"NSW",
    "sg:tags":[
        "seedsman"
    ],
    "wof:name":"D T Brown Seeds & Bulbs",
    "wof:placetype":"venue"
},
  "geometry": {"coordinates":[150.80990600600001,-33.6230506897],"type":"Point"}
}