{
  "type": "Feature",
  "properties": {
    "addr:full":"109 Dempster St Esperance WA 6450",
    "addr:housenumber":"109",
    "addr:postcode":"6450",
    "addr:street":"Dempster St",
    "iso:country":"AU",
    "sg:address":"109 Dempster St",
    "sg:city":"Esperance",
    "sg:classifiers":[
        {
            "category":"Professional",
            "subcategory":"Accounting & Tax Preparation",
            "type":"Services"
        }
    ],
    "sg:phone":"+61 8 9071 1800",
    "sg:postcode":"6450",
    "sg:province":"WA",
    "sg:tags":[
        "accountant",
        "auditor"
    ],
    "wof:name":"Watts Norval A.",
    "wof:placetype":"venue"
},
  "geometry": {"coordinates":[121.89308929400001,-33.8596191406],"type":"Point"}
}