{
  "type": "Feature",
  "properties": {
    "addr:full":"48 Risdon St Notting Hill VIC 3168",
    "addr:housenumber":"48",
    "addr:postcode":"3168",
    "addr:street":"Risdon St",
    "iso:country":"AU",
    "sg:address":"48 Risdon St",
    "sg:city":"Notting Hill",
    "sg:classifiers":[
        {
            "category":"Building & Trades",
            "subcategory":"Landscaping Services",
            "type":"Services"
        }
    ],
    "sg:phone":"+61 407 729 260",
    "sg:postcode":"3168",
    "sg:province":"VIC",
    "sg:tags":[
        "designer",
        "landscape",
        "contractor"
    ],
    "wof:name":"Aki Japanese Gardens",
    "wof:placetype":"venue"
},
  "geometry": {"coordinates":[145.147537231,-37.9086227417],"type":"Point"}
}