{
  "type": "Feature",
  "properties": {
    "iso:country":"AU",
    "sg:address":"13 Giles St",
    "sg:city":"Katherine",
    "sg:classifiers":[
        {
            "category":"Recreation",
            "type":"Entertainment"
        }
    ],
    "sg:phone":"+61 8 8972 2693",
    "sg:postcode":"0850",
    "sg:province":"NT",
    "sg:tags":[
        "hire",
        "tour",
        "motor",
        "cycle"
    ],
    "wof:name":"R & M Motorcycles",
    "wof:placetype":"venue"
},
  "geometry": {"coordinates":[132.264908,-14.463919],"type":"Point"}
}