{
  "type": "Feature",
  "properties": {
    "addr:full":"146 Railway Parade Leederville WA 6007",
    "addr:housenumber":"146",
    "addr:postcode":"6007",
    "addr:street":"Railway Parade",
    "iso:country":"AU",
    "sg:address":"146 Railway Parade",
    "sg:city":"Leederville",
    "sg:classifiers":[
        {
            "category":"Professional",
            "subcategory":"Printing & Photocopies",
            "type":"Services"
        }
    ],
    "sg:phone":"+61 8 9381 7247",
    "sg:postcode":"6007",
    "sg:province":"WA",
    "sg:tags":[
        "trophy"
    ],
    "wof:name":"Excel Trophies",
    "wof:placetype":"venue"
},
  "geometry": {"coordinates":[115.840637207,-31.9428081512],"type":"Point"}
}