{
  "type": "Feature",
  "properties": {
    "addr:full":"63 Princes Hwy Batemans Bay NSW 2536",
    "addr:housenumber":"63",
    "addr:postcode":"2536",
    "addr:street":"Princes Hwy",
    "iso:country":"AU",
    "sg:address":"63 Princes Hwy",
    "sg:city":"Batemans Bay",
    "sg:classifiers":[
        {
            "category":"Coffee & Tea",
            "type":"Food & Drink"
        }
    ],
    "sg:phone":"+61 2 4472 4333",
    "sg:postcode":"2536",
    "sg:province":"NSW",
    "sg:tags":[
        "kayak",
        "canoe"
    ],
    "wof:name":"South Coast Camping And Outdoors",
    "wof:placetype":"venue"
},
  "geometry": {"coordinates":[150.176605225,-35.7171707153],"type":"Point"}
}