{
  "type": "Feature",
  "properties": {
    "addr:full":"Unit 5, 14 Hector St Osborne Park WA 6017",
    "addr:housenumber":"14",
    "addr:postcode":"6017",
    "addr:street":"Hector St",
    "iso:country":"AU",
    "sg:address":"Unit 5, 14 Hector St",
    "sg:city":"Osborne Park",
    "sg:classifiers":[
        {
            "category":"Manufacturing",
            "subcategory":"Electronics",
            "type":"Manufacturing & Wholesale Goods"
        }
    ],
    "sg:phone":"+61 8 9244 3004",
    "sg:postcode":"6017",
    "sg:province":"WA",
    "sg:tags":[
        "wholesaler",
        "equipment",
        "part",
        "mfrs",
        "refrigeration"
    ],
    "wof:name":"Compro Engineering",
    "wof:placetype":"venue"
},
  "geometry": {"coordinates":[115.813423157,-31.8984737396],"type":"Point"}
}