{
  "type": "Feature",
  "properties": {
    "iso:country":"AU",
    "sg:address":"19 Dustwill St",
    "sg:city":"Eimeo",
    "sg:classifiers":[
        {
            "category":"Home & Garden",
            "subcategory":"Building Materials",
            "type":"Retail Goods"
        }
    ],
    "sg:phone":"+61 418 185 741",
    "sg:postcode":"4740",
    "sg:province":"QLD",
    "sg:tags":[
        "lawn",
        "cutting",
        "maintenance"
    ],
    "wof:name":"K.R. Lawn & Garden Service",
    "wof:placetype":"venue"
},
  "geometry": {"coordinates":[149.166046,-21.056793],"type":"Point"}
}