{
  "type": "Feature",
  "properties": {
    "iso:country":"AU",
    "sg:address":"104 Lawrence Hargrave Drv",
    "sg:city":"Austinmer",
    "sg:classifiers":[
        {
            "category":"Retail",
            "subcategory":"Event Space",
            "type":"Services"
        }
    ],
    "sg:phone":"+61 2 4268 5680",
    "sg:postcode":"2515",
    "sg:province":"NSW",
    "sg:tags":[
        "venue",
        "reception",
        "wedding"
    ],
    "wof:name":"Austi Beach Cafe",
    "wof:placetype":"venue"
},
  "geometry": {"coordinates":[150.934357,-34.306377],"type":"Point"}
}