{
  "type": "Feature",
  "properties": {
    "addr:full":"104 Lawrence Hargrave Drv Austinmer NSW 2515",
    "addr:housenumber":"104",
    "addr:postcode":"2515",
    "addr:street":"Lawrence Hargrave Drv",
    "iso:country":"AU",
    "sg:address":"104 Lawrence Hargrave Drv",
    "sg:city":"Austinmer",
    "sg:classifiers":[
        {
            "category":"Retail",
            "subcategory":"Event Space",
            "type":"Services"
        }
    ],
    "sg:phone":"+61 2 4268 5680",
    "sg:postcode":"2515",
    "sg:province":"NSW",
    "sg:tags":[
        "venue",
        "reception",
        "wedding"
    ],
    "wof:name":"Austi Beach Cafe",
    "wof:placetype":"venue"
},
  "geometry": {"coordinates":[150.93435700000001,-34.306377],"type":"Point"}
}