{
  "type": "Feature",
  "properties": {
    "iso:country":"AU",
    "sg:address":"Unit 2/ 86 Boylond Ave",
    "sg:city":"Coopers Plains",
    "sg:classifiers":[
        {
            "category":"Building & Trades",
            "subcategory":"Construction",
            "type":"Services"
        }
    ],
    "sg:phone":"+61 7 3275 1775",
    "sg:postcode":"4108",
    "sg:province":"QLD",
    "sg:tags":[
        "road",
        "contractor"
    ],
    "sg:website":"http://www.safetsurfaces.com.au",
    "wof:name":"STS Applied Systems (QLD) Pty Ltd",
    "wof:placetype":"venue"
},
  "geometry": {"coordinates":[153.02755737300001,-27.5640697479],"type":"Point"}
}