{
  "type": "Feature",
  "properties": {
    "addr:full":"Business Centre 12 Clementina Drv Port Adelaide SA 5015",
    "addr:housenumber":"12",
    "addr:postcode":"5015",
    "addr:street":"Clementina Drv",
    "iso:country":"AU",
    "sg:address":"Business Centre 12 Clementina Drv",
    "sg:city":"Port Adelaide",
    "sg:classifiers":[
        {
            "category":"Government",
            "subcategory":"Post Office",
            "type":"Public Place"
        }
    ],
    "sg:phone":"+61 13 13 18",
    "sg:postcode":"5015",
    "sg:province":"SA",
    "sg:tags":[
        "postal"
    ],
    "wof:name":"Australia Post",
    "wof:placetype":"venue"
},
  "geometry": {"coordinates":[138.504364014,-34.853225708],"type":"Point"}
}