{
  "type": "Feature",
  "properties": {
    "iso:country":"AU",
    "sg:address":"19 Colleen St",
    "sg:city":"Rostrevor",
    "sg:classifiers":[
        {
            "category":"Building & Trades",
            "subcategory":"Landscaping Services",
            "type":"Services"
        }
    ],
    "sg:phone":"+61 407 393 121",
    "sg:postcode":"5073",
    "sg:province":"SA",
    "sg:tags":[
        "gardener"
    ],
    "wof:name":"Plot Gardens",
    "wof:placetype":"venue"
},
  "geometry": {"coordinates":[138.683105469,-34.8928489685],"type":"Point"}
}