{
  "type": "Feature",
  "properties": {
    "addr:full":"26 Clara St Gosnells WA 6110",
    "addr:housenumber":"26",
    "addr:postcode":"6110",
    "addr:street":"Clara St",
    "iso:country":"AU",
    "sg:address":"26 Clara St",
    "sg:city":"Gosnells",
    "sg:classifiers":[
        {
            "category":"Health Services",
            "subcategory":"Health Practitioner",
            "type":"Services"
        }
    ],
    "sg:phone":"+61 8 9394 0333",
    "sg:postcode":"6110",
    "sg:province":"WA",
    "sg:tags":[
        "bowen",
        "therapy"
    ],
    "wof:name":"Bowen & Remedial Massage Clinic",
    "wof:placetype":"venue"
},
  "geometry": {"coordinates":[116.004470825,-32.0781021118],"type":"Point"}
}