{
  "type": "Feature",
  "properties": {
    "addr:full":"133 Youngman St Kingaroy QLD 4610",
    "addr:housenumber":"133",
    "addr:postcode":"4610",
    "addr:street":"Youngman St",
    "iso:country":"AU",
    "sg:address":"133 Youngman St",
    "sg:city":"Kingaroy",
    "sg:classifiers":[
        {
            "category":"Structure",
            "subcategory":"Building",
            "type":"Public Place"
        }
    ],
    "sg:phone":"+61 7 4162 5922",
    "sg:postcode":"4610",
    "sg:province":"QLD",
    "sg:tags":[
        "sail",
        "shade"
    ],
    "wof:name":"Kingaroy Shadesafe",
    "wof:placetype":"venue"
},
  "geometry": {"coordinates":[151.83108520499999,-26.5480995178],"type":"Point"}
}