{
  "type": "Feature",
  "properties": {
    "addr:full":"3a Darling St Tamworth NSW 2340",
    "addr:housenumber":"3a",
    "addr:postcode":"2340",
    "addr:street":"Darling St",
    "iso:country":"AU",
    "sg:address":"3a Darling St",
    "sg:city":"Tamworth",
    "sg:classifiers":[
        {
            "category":"Health Services",
            "subcategory":"Doctor",
            "type":"Services"
        }
    ],
    "sg:phone":"+61 2 6766 4111",
    "sg:postcode":"2340",
    "sg:province":"NSW",
    "sg:tags":[
        "medical",
        "practitioner"
    ],
    "wof:name":"Hibbard Geoffrey P",
    "wof:placetype":"venue"
},
  "geometry": {"coordinates":[150.92677307100001,-31.086725235],"type":"Point"}
}