{
  "type": "Feature",
  "properties": {
    "addr:full":"53 Federal St North Hobart TAS 7000",
    "addr:housenumber":"53",
    "addr:postcode":"7000",
    "addr:street":"Federal St",
    "iso:country":"AU",
    "sg:address":"53 Federal St",
    "sg:city":"North Hobart",
    "sg:classifiers":[
        {
            "category":"Building & Trades",
            "subcategory":"Equipment Rental",
            "type":"Services"
        }
    ],
    "sg:phone":"+61 1800 993 168",
    "sg:postcode":"7000",
    "sg:province":"TAS",
    "sg:tags":[
        "supply",
        "catering"
    ],
    "wof:name":"Luus Industries Pty Ltd",
    "wof:placetype":"venue"
},
  "geometry": {"coordinates":[147.31755065900001,-42.8701248169],"type":"Point"}
}