{
  "type": "Feature",
  "properties": {
    "addr:full":"Rochedale St Dalby QLD 4405",
    "addr:postcode":"4405",
    "addr:street":"Rochedale St",
    "iso:country":"AU",
    "sg:address":"Rochedale St",
    "sg:city":"Dalby",
    "sg:classifiers":[
        {
            "category":"Retail",
            "subcategory":"Auto Repair",
            "type":"Services"
        }
    ],
    "sg:phone":"+61 7 4662 3010",
    "sg:postcode":"4405",
    "sg:province":"QLD",
    "sg:tags":[
        "beater",
        "painter",
        "panel"
    ],
    "wof:name":"Parker N J & E J",
    "wof:placetype":"venue"
},
  "geometry": {"coordinates":[151.261993408,-27.1743087769],"type":"Point"}
}