{
  "type": "Feature",
  "properties": {
    "addr:full":"159 Parker St Templestowe VIC 3106",
    "addr:housenumber":"159",
    "addr:postcode":"3106",
    "addr:street":"Parker St",
    "iso:country":"AU",
    "sg:address":"159 Parker St",
    "sg:city":"Templestowe",
    "sg:classifiers":[
        {
            "category":"Personal",
            "subcategory":"Beauty Salon",
            "type":"Services"
        }
    ],
    "sg:phone":"+61 3 9846 7755",
    "sg:postcode":"3106",
    "sg:province":"VIC",
    "wof:name":"Templestowe Beauty Retreat",
    "wof:placetype":"venue"
},
  "geometry": {"coordinates":[145.130004883,-37.7578544617],"type":"Point"}
}