{
  "type": "Feature",
  "properties": {
    "addr:full":"1 Treloar Crt Chester Hill NSW 2162",
    "addr:housenumber":"1",
    "addr:postcode":"2162",
    "addr:street":"Treloar Crt",
    "iso:country":"AU",
    "sg:address":"1 Treloar Crt",
    "sg:city":"Chester Hill",
    "sg:classifiers":[
        {
            "category":"Real Estate",
            "subcategory":"Architect",
            "type":"Services"
        }
    ],
    "sg:phone":"+61 2 9786 7783",
    "sg:postcode":"2162",
    "sg:province":"NSW",
    "sg:tags":[
        "building",
        "designer"
    ],
    "wof:name":"Boris Grgurevic & Associates Pty Ltd",
    "wof:placetype":"venue"
},
  "geometry": {"coordinates":[150.99749755900001,-33.871723175],"type":"Point"}
}