{
  "type": "Feature",
  "properties": {
    "addr:full":"3 Napier St Warragul VIC 3820",
    "addr:housenumber":"3",
    "addr:postcode":"3820",
    "addr:street":"Napier St",
    "iso:country":"AU",
    "sg:address":"3 Napier St",
    "sg:city":"Warragul",
    "sg:classifiers":[
        {
            "category":"Professional",
            "subcategory":"Accounting & Tax Preparation",
            "type":"Services"
        }
    ],
    "sg:phone":"+61 3 5622 7500",
    "sg:postcode":"3820",
    "sg:province":"VIC",
    "sg:tags":[
        "consultant",
        "taxation"
    ],
    "wof:name":"Armitage Downie",
    "wof:placetype":"venue"
},
  "geometry": {"coordinates":[145.92915300000001,-38.161736],"type":"Point"}
}