{
  "type": "Feature",
  "properties": {
    "iso:country":"AU",
    "sg:address":"8 Crisp St",
    "sg:city":"Essendon",
    "sg:classifiers":[
        {
            "category":"Real Estate",
            "subcategory":"Architect",
            "type":"Services"
        }
    ],
    "sg:phone":"+61 3 9379 9220",
    "sg:postcode":"3040",
    "sg:province":"VIC",
    "wof:name":"Donald Walker & Associates Pty Ltd",
    "wof:placetype":"venue"
},
  "geometry": {"coordinates":[144.916290283,-37.7457695007],"type":"Point"}
}