{
  "type": "Feature",
  "properties": {
    "addr:full":"Richards Building - University of Queensland St Lucia QLD 4067",
    "addr:postcode":"4067",
    "iso:country":"AU",
    "sg:address":"Richards Building - University of Queensland",
    "sg:city":"St Lucia",
    "sg:classifiers":[
        {
            "category":"Professional",
            "subcategory":"Research",
            "type":"Services"
        }
    ],
    "sg:phone":"+61 7 3365 3473",
    "sg:postcode":"4067",
    "sg:province":"QLD",
    "sg:tags":[
        "industrial",
        "scientific"
    ],
    "wof:name":"W H Bryan Mining Research Centre",
    "wof:placetype":"venue"
},
  "geometry": {"coordinates":[153.004516602,-27.4940605164],"type":"Point"}
}