{
  "type": "Feature",
  "properties": {
    "addr:full":"3/ 42 Cribb St Landsborough QLD 4550",
    "addr:housenumber":"/ 42",
    "addr:postcode":"4550",
    "addr:street":"Cribb St",
    "iso:country":"AU",
    "sg:address":"3/ 42 Cribb St",
    "sg:city":"Landsborough",
    "sg:classifiers":[
        {
            "category":"Banks & Credit Unions",
            "subcategory":"Financial Services",
            "type":"Services"
        }
    ],
    "sg:phone":"+61 7 5494 1731",
    "sg:postcode":"4550",
    "sg:province":"QLD",
    "sg:tags":[
        "building",
        "society"
    ],
    "wof:name":"Heritage Building Society",
    "wof:placetype":"venue"
},
  "geometry": {"coordinates":[152.96571350100001,-26.8085289001],"type":"Point"}
}