{
  "type": "Feature",
  "properties": {
    "addr:full":"PO Box 41 Halls Gap VIC 3381",
    "addr:postcode":"3381",
    "iso:country":"AU",
    "sg:address":"PO Box 41",
    "sg:city":"Halls Gap",
    "sg:classifiers":[
        {
            "category":"Organizations",
            "subcategory":"Professional Association",
            "type":"Services"
        }
    ],
    "sg:phone":"+61 3 5356 4311",
    "sg:postcode":"3381",
    "sg:province":"VIC",
    "sg:tags":[
        "web",
        "internet"
    ],
    "wof:name":"Davpat Designs",
    "wof:placetype":"venue"
},
  "geometry": {"coordinates":[142.52447509800001,-37.1515617371],"type":"Point"}
}