{
  "type": "Feature",
  "properties": {
    "addr:full":"17 Peel St South Brisbane QLD 4101",
    "addr:housenumber":"17",
    "addr:postcode":"4101",
    "addr:street":"Peel St",
    "iso:country":"AU",
    "sg:address":"17 Peel St",
    "sg:city":"South Brisbane",
    "sg:classifiers":[
        {
            "category":"Banks & Credit Unions",
            "subcategory":"Bank",
            "type":"Services"
        }
    ],
    "sg:phone":"+61 7 3255 1900",
    "sg:postcode":"4101",
    "sg:province":"QLD",
    "sg:tags":[
        "equipment",
        "sale",
        "point"
    ],
    "wof:name":"Riva Corporation",
    "wof:placetype":"venue"
},
  "geometry": {"coordinates":[153.01678466800001,-27.4723453522],"type":"Point"}
}