{
  "type": "Feature",
  "properties": {
    "addr:full":"37a Semaphore Rd Semaphore SA 5019",
    "addr:housenumber":"37a",
    "addr:postcode":"5019",
    "addr:street":"Semaphore Rd",
    "iso:country":"AU",
    "sg:address":"37a Semaphore Rd",
    "sg:city":"Semaphore",
    "sg:classifiers":[
        {
            "category":"Personal",
            "subcategory":"Beauty Salon",
            "type":"Services"
        }
    ],
    "sg:phone":"+61 8 8449 6398",
    "sg:postcode":"5019",
    "sg:province":"SA",
    "wof:name":"Semaphore Beauty Therapy",
    "wof:placetype":"venue"
},
  "geometry": {"coordinates":[138.482910156,-34.8384284973],"type":"Point"}
}