{
  "type": "Feature",
  "properties": {
    "addr:full":"188 Harbord Rd Brookvale NSW 2100",
    "addr:housenumber":"188",
    "addr:postcode":"2100",
    "addr:street":"Harbord Rd",
    "iso:country":"AU",
    "sg:address":"188 Harbord Rd",
    "sg:city":"Brookvale",
    "sg:classifiers":[
        {
            "category":"Home & Garden",
            "subcategory":"Home Furnishings",
            "type":"Retail Goods"
        }
    ],
    "sg:phone":"+61 2 9938 2826",
    "sg:postcode":"2100",
    "sg:province":"NSW",
    "sg:tags":[
        "shower",
        "screen"
    ],
    "wof:name":"Bare Shower Screens",
    "wof:placetype":"venue"
},
  "geometry": {"coordinates":[151.279388428,-33.7648162842],"type":"Point"}
}