{
  "type": "Feature",
  "properties": {
    "iso:country":"AU",
    "sg:address":"1/ 69 Clarence St",
    "sg:city":"Bellerive",
    "sg:classifiers":[
        {
            "category":"Restaurant",
            "type":"Food & Drink"
        }
    ],
    "sg:phone":"+61 3 6211 4355",
    "sg:postcode":"7018",
    "sg:province":"TAS",
    "sg:tags":[
        "pizza"
    ],
    "wof:name":"Dominos Pizza",
    "wof:placetype":"venue"
},
  "geometry": {"coordinates":[147.378448486,-42.87550354],"type":"Point"}
}