{
  "type": "Feature",
  "properties": {
    "addr:full":"4/ 63 The Esp Cronulla NSW 2230",
    "addr:housenumber":"/ 63",
    "addr:postcode":"2230",
    "addr:street":"The Esp",
    "iso:country":"AU",
    "sg:address":"4/ 63",
    "sg:city":"The Esp Cronulla",
    "sg:classifiers":[
        {
            "category":"Utilities",
            "subcategory":"Electric",
            "type":"Services"
        }
    ],
    "sg:phone":"+61 418 411 390",
    "sg:postcode":"2230",
    "sg:province":"NSW",
    "sg:tags":[
        "electrical",
        "contractor"
    ],
    "wof:name":"Malcolm Watson Electrical",
    "wof:placetype":"venue"
},
  "geometry": {"coordinates":[151.15489196799999,-34.0638389587],"type":"Point"}
}