{
  "type": "Feature",
  "properties": {
    "addr:full":"13/ 111 Pakington St Geelong West VIC 3218",
    "addr:housenumber":"13 / 111",
    "addr:postcode":"3218",
    "addr:street":"Pakington St",
    "iso:country":"AU",
    "sg:address":"13/ 111 Pakington St",
    "sg:city":"Geelong West",
    "sg:classifiers":[
        {
            "category":"Health Services",
            "subcategory":"Dentist",
            "type":"Services"
        }
    ],
    "sg:phone":"+61 3 5221 5066",
    "sg:postcode":"3218",
    "sg:province":"VIC",
    "wof:name":"Burnett Nigel Dr B.D.S. (Edin.)",
    "wof:placetype":"venue"
},
  "geometry": {"coordinates":[144.34857177699999,-38.1385231018],"type":"Point"}
}