{
  "type": "Feature",
  "properties": {
    "iso:country":"AU",
    "sg:address":"40 Boyd St",
    "sg:city":"Dandenong",
    "sg:classifiers":[
        {
            "category":"Social Services",
            "subcategory":"Adult Care",
            "type":"Services"
        }
    ],
    "sg:phone":"+61 412 358 543",
    "sg:postcode":"3175",
    "sg:province":"VIC",
    "sg:tags":[
        "towing"
    ],
    "wof:name":"Sandford Tilt Tray Services",
    "wof:placetype":"venue"
},
  "geometry": {"coordinates":[145.21748352,-37.9670448303],"type":"Point"}
}