{
  "type": "Feature",
  "properties": {
    "addr:full":"Lvl 4, 379 Kent St Sydney NSW 2000",
    "addr:housenumber":"379",
    "addr:postcode":"2000",
    "addr:street":"Kent St",
    "iso:country":"AU",
    "sg:address":"Lvl 4, 379 Kent St",
    "sg:city":"Sydney",
    "sg:classifiers":[
        {
            "category":"Professional",
            "subcategory":"Accounting & Tax Preparation",
            "type":"Services"
        }
    ],
    "sg:phone":"+61 2 9264 6066",
    "sg:postcode":"2000",
    "sg:province":"NSW",
    "sg:tags":[
        "accountant",
        "auditor"
    ],
    "wof:name":"Cappelletto Robert J Chartered Accountant",
    "wof:placetype":"venue"
},
  "geometry": {"coordinates":[151.20455932600001,-33.8697776794],"type":"Point"}
}