{
  "type": "Feature",
  "properties": {
    "addr:full":"24 Markwell St Kingaroy QLD 4610",
    "addr:housenumber":"24",
    "addr:postcode":"4610",
    "addr:street":"Markwell St",
    "iso:country":"AU",
    "sg:address":"24 Markwell St",
    "sg:city":"Kingaroy",
    "sg:classifiers":[
        {
            "category":"Home & Garden",
            "subcategory":"Building Materials",
            "type":"Retail Goods"
        }
    ],
    "sg:phone":"+61 7 4162 5598",
    "sg:postcode":"4610",
    "sg:province":"QLD",
    "sg:tags":[
        "shutter",
        "roller",
        "grille"
    ],
    "wof:name":"South Burnett Garage & Industrial Door Services",
    "wof:placetype":"venue"
},
  "geometry": {"coordinates":[151.834060669,-26.5371189117],"type":"Point"}
}