{
  "type": "Feature",
  "properties": {
    "addr:full":"251- 257 Scarborough Beach Rd Osborne Park WA 6017",
    "addr:housenumber":"257",
    "addr:postcode":"6017",
    "addr:street":"Scarborough Beach Rd",
    "iso:country":"AU",
    "sg:address":"251- 257 Scarborough Beach Rd",
    "sg:city":"Osborne Park",
    "sg:classifiers":[
        {
            "category":"Professional",
            "subcategory":"Printing & Photocopies",
            "type":"Services"
        }
    ],
    "sg:phone":"+61 8 9202 4444",
    "sg:postcode":"6017",
    "sg:province":"WA",
    "sg:tags":[
        "photocopier"
    ],
    "wof:name":"CDM Photocopiers",
    "wof:placetype":"venue"
},
  "geometry": {"coordinates":[115.808387756,-31.9054355621],"type":"Point"}
}