{
  "type": "Feature",
  "properties": {
    "addr:full":"23 Ferguson Drv Devonport TAS 7310",
    "addr:housenumber":"23",
    "addr:postcode":"7310",
    "addr:street":"Ferguson Drv",
    "iso:country":"AU",
    "sg:address":"23 Ferguson Drv",
    "sg:city":"Devonport",
    "sg:classifiers":[
        {
            "category":"Building & Trades",
            "subcategory":"Construction",
            "type":"Services"
        }
    ],
    "sg:phone":"+61 418 141 612",
    "sg:postcode":"7310",
    "sg:province":"TAS",
    "sg:tags":[
        "ceiling"
    ],
    "wof:name":"Overton R.D. Plastering Pty Ltd",
    "wof:placetype":"venue"
},
  "geometry": {"coordinates":[146.34124755900001,-41.2076148987],"type":"Point"}
}