{
  "type": "Feature",
  "properties": {
    "iso:country":"AU",
    "sg:address":"26 Minilya Rd",
    "sg:city":"Broome",
    "sg:classifiers":[
        {
            "category":"Retail",
            "subcategory":"Auto Repair",
            "type":"Services"
        }
    ],
    "sg:phone":"+61 8 9192 2595",
    "sg:postcode":"6725",
    "sg:province":"WA",
    "sg:tags":[
        "repairer",
        "motor",
        "engineer"
    ],
    "wof:name":"Tropical Motors",
    "wof:placetype":"venue"
},
  "geometry": {"coordinates":[122.240882873,-17.923204422],"type":"Point"}
}