{
  "type": "Feature",
  "properties": {
    "addr:full":"FC 106 Westfield Carousel Albany Hwy Cannington WA 6107",
    "addr:housenumber":"106",
    "addr:postcode":"6107",
    "addr:street":"Westfield Carousel Albany Hwy",
    "iso:country":"AU",
    "sg:address":"FC 106 Westfield Carousel Albany Hwy",
    "sg:city":"Cannington",
    "sg:classifiers":[
        {
            "category":"Fast Food",
            "type":"Food & Drink"
        }
    ],
    "sg:phone":"+61 8 9451 6200",
    "sg:postcode":"6107",
    "sg:province":"WA",
    "sg:tags":[
        "away",
        "take"
    ],
    "wof:name":"Subway Sandwiches & Salads",
    "wof:placetype":"venue"
},
  "geometry": {"coordinates":[115.933120727,-32.016960144],"type":"Point"}
}