{
  "type": "Feature",
  "properties": {
    "iso:country":"AU",
    "sg:address":"243 Pakington St",
    "sg:city":"Newtown",
    "sg:classifiers":[
        {
            "category":"Wholesale",
            "subcategory":"Medical Equipment & Supplies",
            "type":"Manufacturing & Wholesale Goods"
        }
    ],
    "sg:phone":"+61 3 5221 1400",
    "sg:postcode":"3220",
    "sg:province":"VIC",
    "sg:tags":[
        "aids",
        "hearing"
    ],
    "wof:name":"Audicare",
    "wof:placetype":"venue"
},
  "geometry": {"coordinates":[144.346909,-38.147141],"type":"Point"}
}