{
  "type": "Feature",
  "properties": {
    "addr:full":"3/ 10 Kingfisher Drv Peregian Beach QLD 4573",
    "addr:housenumber":"/ 10",
    "addr:postcode":"4573",
    "addr:street":"Kingfisher Drv",
    "iso:country":"AU",
    "sg:address":"3/ 10 Kingfisher Drv",
    "sg:city":"Peregian Beach",
    "sg:classifiers":[
        {
            "category":"Government",
            "subcategory":"Post Office",
            "type":"Public Place"
        }
    ],
    "sg:phone":"+61 7 5448 1147",
    "sg:postcode":"4573",
    "sg:province":"QLD",
    "sg:tags":[
        "postal"
    ],
    "wof:name":"Australia Post",
    "wof:placetype":"venue"
},
  "geometry": {"coordinates":[153.09663399999999,-26.480904],"type":"Point"}
}