{
  "type": "Feature",
  "properties": {
    "iso:country":"AU",
    "sg:address":"1459 Sandgate Rd",
    "sg:city":"Nundah",
    "sg:classifiers":[
        {
            "category":"Health Services",
            "subcategory":"Doctor",
            "type":"Services"
        }
    ],
    "sg:phone":"+61 7 3266 6022",
    "sg:postcode":"4012",
    "sg:province":"QLD",
    "sg:tags":[
        "medical",
        "practitioner"
    ],
    "wof:name":"Hansen Mary-Ellen",
    "wof:placetype":"venue"
},
  "geometry": {"coordinates":[153.05946350100001,-27.3975963593],"type":"Point"}
}