{
  "type": "Feature",
  "properties": {
    "addr:full":"33 Pearce St Wodonga VIC 3690",
    "addr:housenumber":"33",
    "addr:postcode":"3690",
    "addr:street":"Pearce St",
    "iso:country":"AU",
    "sg:address":"33 Pearce St",
    "sg:city":"Wodonga",
    "sg:classifiers":[
        {
            "category":"Professional",
            "subcategory":"Art Services",
            "type":"Services"
        }
    ],
    "sg:phone":"+61 412 505 941",
    "sg:postcode":"3690",
    "sg:province":"VIC",
    "sg:tags":[
        "decorator",
        "painter"
    ],
    "wof:name":"Kiegerl John",
    "wof:placetype":"venue"
},
  "geometry": {"coordinates":[146.88223266599999,-36.1377105713],"type":"Point"}
}