{
  "type": "Feature",
  "properties": {
    "iso:country":"AU",
    "sg:address":"The Carmelite Hall Richardson St",
    "sg:city":"Middle Park",
    "sg:classifiers":[
        {
            "category":"Arena",
            "subcategory":"Sports Club",
            "type":"Entertainment"
        }
    ],
    "sg:phone":"+61 3 9593 1850",
    "sg:postcode":"3206",
    "sg:province":"VIC",
    "sg:tags":[
        "defence",
        "supply",
        "self",
        "instruction",
        "martial art"
    ],
    "wof:name":"South Melbourne Taekwondo Centre",
    "wof:placetype":"venue"
},
  "geometry": {"coordinates":[144.96163899999999,-37.849415],"type":"Point"}
}