{
  "type": "Feature",
  "properties": {
    "addr:full":"108 Jetty Rd Glenelg SA 5045",
    "addr:housenumber":"108",
    "addr:postcode":"5045",
    "addr:street":"Jetty Rd",
    "iso:country":"AU",
    "sg:address":"108 Jetty Rd",
    "sg:city":"Glenelg",
    "sg:classifiers":[
        {
            "category":"Travel",
            "subcategory":"Travel Agent",
            "type":"Entertainment"
        }
    ],
    "sg:phone":"+61 8 8294 5900",
    "sg:postcode":"5045",
    "sg:province":"SA",
    "sg:tags":[
        "consultant"
    ],
    "wof:name":"Jetset Glenelg",
    "wof:placetype":"venue"
},
  "geometry": {"coordinates":[138.51611299999999,-34.980366],"type":"Point"}
}