{
  "type": "Feature",
  "properties": {
    "addr:full":"14 Bray St Coffs Harbour NSW 2450",
    "addr:housenumber":"14",
    "addr:postcode":"2450",
    "addr:street":"Bray St",
    "iso:country":"AU",
    "sg:address":"14 Bray St",
    "sg:city":"Coffs Harbour",
    "sg:classifiers":[
        {
            "category":"Professional",
            "subcategory":"Accounting & Tax Preparation",
            "type":"Services"
        }
    ],
    "sg:phone":"+61 2 6652 6846",
    "sg:postcode":"2450",
    "sg:province":"NSW",
    "sg:tags":[
        "accountant",
        "auditor"
    ],
    "wof:name":"Rodney Fox",
    "wof:placetype":"venue"
},
  "geometry": {"coordinates":[153.12304700000001,-30.282915],"type":"Point"}
}