{
  "type": "Feature",
  "properties": {
    "addr:full":"46 Seaview Pde Dromana VIC 3936",
    "addr:housenumber":"46",
    "addr:postcode":"3936",
    "addr:street":"Seaview Pde",
    "iso:country":"AU",
    "sg:address":"46 Seaview Pde",
    "sg:city":"Dromana",
    "sg:classifiers":[
        {
            "category":"Home & Garden",
            "subcategory":"Building Materials",
            "type":"Retail Goods"
        }
    ],
    "sg:phone":"+61 3 5987 1237",
    "sg:postcode":"3936",
    "sg:province":"VIC",
    "sg:tags":[
        "lawn",
        "cutting",
        "maintenance"
    ],
    "wof:name":"Humphrey G & R",
    "wof:placetype":"venue"
},
  "geometry": {"coordinates":[144.964599609,-38.3414878845],"type":"Point"}
}