{
  "type": "Feature",
  "properties": {
    "addr:full":"5-7 Kirk St Moe VIC 3825",
    "addr:housenumber":"5-7",
    "addr:postcode":"3825",
    "addr:street":"Kirk St",
    "iso:country":"AU",
    "sg:address":"5-7 Kirk St",
    "sg:city":"Moe",
    "sg:classifiers":[
        {
            "category":"Shopping",
            "subcategory":"Shoes",
            "type":"Retail Goods"
        }
    ],
    "sg:phone":"+61 3 5126 2244",
    "sg:postcode":"3825",
    "sg:province":"VIC",
    "sg:tags":[
        "footwear"
    ],
    "wof:name":"Fasinations with Footwear",
    "wof:placetype":"venue"
},
  "geometry": {"coordinates":[146.26345800000001,-38.176105],"type":"Point"}
}