{
  "type": "Feature",
  "properties": {
    "addr:full":"194 High St Cranbourne VIC 3977",
    "addr:housenumber":"194",
    "addr:postcode":"3977",
    "addr:street":"High St",
    "iso:country":"AU",
    "sg:address":"194 High St",
    "sg:city":"Cranbourne",
    "sg:classifiers":[
        {
            "category":"Autos & Motor Vehicles",
            "subcategory":"Auto Supplies",
            "type":"Retail Goods"
        }
    ],
    "sg:phone":"+61 3 5996 4788",
    "sg:postcode":"3977",
    "sg:province":"VIC",
    "sg:tags":[
        "battery",
        "automotive"
    ],
    "wof:name":"Beaurepaires",
    "wof:placetype":"venue"
},
  "geometry": {"coordinates":[145.28233337399999,-38.103931427],"type":"Point"}
}