{
  "type": "Feature",
  "properties": {
    "iso:country":"AU",
    "sg:address":"Cnr Wanneroo & Menchetti Rds 10 Menchetti Rd",
    "sg:city":"Neerabup",
    "sg:classifiers":[
        {
            "category":"Food & Beverages",
            "subcategory":"Fruits & Vegetables",
            "type":"Retail Goods"
        }
    ],
    "sg:phone":"+61 8 9407 5001",
    "sg:postcode":"6031",
    "sg:province":"WA",
    "sg:tags":[
        "greengrocer",
        "fruiterer"
    ],
    "wof:name":"Neerabup Fruit & Vege Supply",
    "wof:placetype":"venue"
},
  "geometry": {"coordinates":[115.770729065,-31.6994628906],"type":"Point"}
}