{
  "type": "Feature",
  "properties": {
    "iso:country":"AU",
    "sg:address":"Studio4/ 5 Elata Drv",
    "sg:city":"Tullamarine",
    "sg:classifiers":[
        {
            "category":"Arts & Performance",
            "subcategory":"Dance",
            "type":"Entertainment"
        }
    ],
    "sg:phone":"+61 3 9335 4343",
    "sg:postcode":"3043",
    "sg:province":"VIC",
    "sg:tags":[
        "theatrical",
        "ballet",
        "tuition"
    ],
    "wof:name":"P M Entertainment",
    "wof:placetype":"venue"
},
  "geometry": {"coordinates":[144.86021423299999,-37.7151107788],"type":"Point"}
}