{
  "type": "Feature",
  "properties": {
    "addr:full":"342 Soldiers Point Rd Salamander Bay NSW 2317",
    "addr:housenumber":"342",
    "addr:postcode":"2317",
    "addr:street":"Soldiers Point Rd",
    "iso:country":"AU",
    "sg:address":"342 Soldiers Point Rd",
    "sg:city":"Salamander Bay",
    "sg:classifiers":[
        {
            "category":"Retail",
            "subcategory":"Storage",
            "type":"Services"
        }
    ],
    "sg:phone":"+61 2 4982 6694",
    "sg:postcode":"2317",
    "sg:province":"NSW",
    "sg:tags":[
        "removal",
        "furniture"
    ],
    "wof:name":"Port Stephens Removals & Storage",
    "wof:placetype":"venue"
},
  "geometry": {"coordinates":[152.080872,-32.728794],"type":"Point"}
}