{
  "type": "Feature",
  "properties": {
    "iso:country":"AU",
    "sg:address":"11 Garran Crt",
    "sg:city":"Loganholme",
    "sg:classifiers":[
        {
            "category":"Arts & Performance",
            "subcategory":"Theater",
            "type":"Entertainment"
        }
    ],
    "sg:phone":"+61 412 881 972",
    "sg:postcode":"4129",
    "sg:province":"QLD",
    "sg:tags":[
        "theatrical",
        "supply"
    ],
    "wof:name":"Performance Lighting & Sound",
    "wof:placetype":"venue"
},
  "geometry": {"coordinates":[153.185012817,-27.6870498657],"type":"Point"}
}