{
  "type": "Feature",
  "properties": {
    "addr:full":"Lot 2 Rockleigh Crt Glenella QLD 4740",
    "addr:postcode":"4740",
    "addr:street":"Rockleigh",
    "iso:country":"AU",
    "sg:address":"Lot 2 Rockleigh Crt",
    "sg:city":"Glenella",
    "sg:classifiers":[
        {
            "category":"Professional",
            "subcategory":"Engineering",
            "type":"Services"
        }
    ],
    "sg:phone":"+61 7 4942 1777",
    "sg:postcode":"4740",
    "sg:province":"QLD",
    "sg:tags":[
        "engineer"
    ],
    "wof:name":"Werner Engineering (QLD) Pty Ltd",
    "wof:placetype":"venue"
},
  "geometry": {"coordinates":[149.14892599999999,-21.129559],"type":"Point"}
}