{
  "type": "Feature",
  "properties": {
    "addr:full":"24 Kahibah St Whitebridge NSW 2290",
    "addr:housenumber":"24",
    "addr:postcode":"2290",
    "addr:street":"Kahibah St",
    "iso:country":"AU",
    "sg:address":"24 Kahibah St",
    "sg:city":"Whitebridge",
    "sg:classifiers":[
        {
            "category":"Building & Trades",
            "subcategory":"Construction",
            "type":"Services"
        }
    ],
    "sg:phone":"+61 2 4944 8402",
    "sg:postcode":"2290",
    "sg:province":"NSW",
    "sg:tags":[
        "contractor"
    ],
    "wof:name":"Adamthwaite John J",
    "wof:placetype":"venue"
},
  "geometry": {"coordinates":[151.71290588400001,-32.9830551147],"type":"Point"}
}