{
  "type": "Feature",
  "properties": {
    "iso:country":"AU",
    "sg:address":"136 Lachlan St",
    "sg:city":"Forbes",
    "sg:classifiers":[
        {
            "category":"Health Services",
            "subcategory":"Health Practitioner",
            "type":"Services"
        }
    ],
    "sg:phone":"+61 2 6851 1991",
    "sg:postcode":"2871",
    "sg:province":"NSW",
    "sg:tags":[
        "psychologist"
    ],
    "wof:name":"Centacare- Family & Community Services",
    "wof:placetype":"venue"
},
  "geometry": {"coordinates":[148.00685100000001,-33.386051],"type":"Point"}
}