{
  "type": "Feature",
  "properties": {
    "addr:full":"U2/ 33 Crescent Rd Waratah NSW 2298",
    "addr:housenumber":"33",
    "addr:postcode":"2298",
    "addr:street":"U2 /;Crescent Rd",
    "iso:country":"AU",
    "sg:address":"U2/ 33 Crescent Rd",
    "sg:city":"Waratah",
    "sg:classifiers":[
        {
            "category":"Education",
            "subcategory":"Special Training",
            "type":"Public Place"
        }
    ],
    "sg:phone":"+61 2 4967 1205",
    "sg:postcode":"2298",
    "sg:province":"NSW",
    "sg:tags":[
        "tuition-educational"
    ],
    "wof:name":"Essential Moves",
    "wof:placetype":"venue"
},
  "geometry": {"coordinates":[151.72567749000001,-32.9029159546],"type":"Point"}
}