{
  "type": "Feature",
  "properties": {
    "addr:full":"5 Carlo Drv Cannonvale QLD 4802",
    "addr:housenumber":"5",
    "addr:postcode":"4802",
    "addr:street":"Carlo Drv",
    "iso:country":"AU",
    "sg:address":"5 Carlo Drv",
    "sg:city":"Cannonvale",
    "sg:classifiers":[
        {
            "category":"Building & Trades",
            "subcategory":"Plumbing",
            "type":"Services"
        }
    ],
    "sg:phone":"+61 7 4946 1455",
    "sg:postcode":"4802",
    "sg:province":"QLD",
    "sg:tags":[
        "plumber",
        "gasfitters"
    ],
    "wof:name":"Ian Roebuck Plumbing & Drainage",
    "wof:placetype":"venue"
},
  "geometry": {"coordinates":[148.673583984,-20.28814888],"type":"Point"}
}