{
  "type": "Feature",
  "properties": {
    "addr:full":"Ste 12/ 185 Military Rd Neutral Bay NSW 2089",
    "addr:housenumber":"/ 185",
    "addr:postcode":"2089",
    "addr:street":"Military Rd",
    "iso:country":"AU",
    "sg:address":"Ste 12/ 185 Military Rd",
    "sg:city":"Neutral Bay",
    "sg:classifiers":[
        {
            "category":"Professional",
            "subcategory":"Management & Consulting",
            "type":"Services"
        }
    ],
    "sg:phone":"+61 2 9953 2555",
    "sg:postcode":"2089",
    "sg:province":"NSW",
    "sg:tags":[
        "consultant"
    ],
    "wof:name":"Alpha 3 Executive Search",
    "wof:placetype":"venue"
},
  "geometry": {"coordinates":[151.22286987300001,-33.8316841125],"type":"Point"}
}