{
  "type": "Feature",
  "properties": {
    "iso:country":"AU",
    "sg:address":"116 Dangar St",
    "sg:city":"Armidale",
    "sg:classifiers":[
        {
            "category":"Shopping",
            "subcategory":"Computers & Home Electronics",
            "type":"Retail Goods"
        }
    ],
    "sg:phone":"+61 2 6772 7299",
    "sg:postcode":"2350",
    "sg:province":"NSW",
    "sg:tags":[
        "hi-fi",
        "equipment"
    ],
    "wof:name":"Thoms Retravision",
    "wof:placetype":"venue"
},
  "geometry": {"coordinates":[151.66490173299999,-30.51404953],"type":"Point"}
}