{
  "type": "Feature",
  "properties": {
    "addr:full":"42 William St Orange NSW 2800",
    "addr:housenumber":"42",
    "addr:postcode":"2800",
    "addr:street":"William St",
    "iso:country":"AU",
    "sg:address":"42 William St",
    "sg:city":"Orange",
    "sg:classifiers":[
        {
            "category":"Autos & Motor Vehicles",
            "subcategory":"Auto Supplies",
            "type":"Retail Goods"
        }
    ],
    "sg:phone":"+61 2 6362 7127",
    "sg:postcode":"2800",
    "sg:province":"NSW",
    "sg:tags":[
        "battery",
        "automotive"
    ],
    "wof:name":"A. AAALL Auto Batteries",
    "wof:placetype":"venue"
},
  "geometry": {"coordinates":[149.105636597,-33.2836799622],"type":"Point"}
}