{
  "type": "Feature",
  "properties": {
    "addr:full":"1 Service St Echuca VIC 3564",
    "addr:housenumber":"1",
    "addr:postcode":"3564",
    "addr:street":"Service St",
    "iso:country":"AU",
    "sg:address":"1 Service St",
    "sg:city":"Echuca",
    "sg:classifiers":[
        {
            "category":"Building & Trades",
            "subcategory":"Construction",
            "type":"Services"
        }
    ],
    "sg:phone":"+61 3 5482 5052",
    "sg:postcode":"3564",
    "sg:province":"VIC",
    "sg:tags":[
        "contractor"
    ],
    "wof:name":"Welch L D & J M",
    "wof:placetype":"venue"
},
  "geometry": {"coordinates":[144.76397705100001,-36.1376152039],"type":"Point"}
}