{
  "type": "Feature",
  "properties": {
    "addr:full":"PO Box 469 Maitland NSW 2320",
    "addr:postcode":"2320",
    "iso:country":"AU",
    "sg:address":"PO Box 469",
    "sg:city":"Maitland",
    "sg:classifiers":[
        {
            "category":"Social Services",
            "subcategory":"Retirement Home",
            "type":"Services"
        }
    ],
    "sg:phone":"+61 2 4930 0288",
    "sg:postcode":"2320",
    "sg:province":"NSW",
    "sg:tags":[
        "environmental",
        "consultant",
        "pollution"
    ],
    "wof:name":"Hill Top Planners",
    "wof:placetype":"venue"
},
  "geometry": {"coordinates":[151.570114136,-32.7078857422],"type":"Point"}
}