{
  "type": "Feature",
  "properties": {
    "iso:country":"AU",
    "sg:address":"Shp3/ 218 Anakie Rd",
    "sg:city":"Bell Park",
    "sg:classifiers":[
        {
            "category":"Fast Food",
            "type":"Food & Drink"
        }
    ],
    "sg:phone":"+61 3 5278 5502",
    "sg:postcode":"3215",
    "sg:province":"VIC",
    "sg:tags":[
        "away",
        "take"
    ],
    "wof:name":"Chars & Juices",
    "wof:placetype":"venue"
},
  "geometry": {"coordinates":[144.334274292,-38.097454071],"type":"Point"}
}