{
  "type": "Feature",
  "properties": {
    "iso:country":"AU",
    "sg:address":"3 Edwards St",
    "sg:city":"Loganlea",
    "sg:classifiers":[
        {
            "category":"Retail",
            "subcategory":"Storage",
            "type":"Services"
        }
    ],
    "sg:phone":"+61 7 3299 7052",
    "sg:postcode":"4131",
    "sg:province":"QLD",
    "sg:tags":[
        "removal",
        "furniture"
    ],
    "wof:name":"Moondy Removals",
    "wof:placetype":"venue"
},
  "geometry": {"coordinates":[153.12440490700001,-27.6699085236],"type":"Point"}
}