{
  "type": "Feature",
  "properties": {
    "addr:full":"Lvl 1 Menai Mrktpl, Allison Cres Menai NSW 2234",
    "addr:postcode":"2234",
    "addr:street":"Allison Cres",
    "iso:country":"AU",
    "sg:address":"Lvl 1 Menai Mrktpl, Allison Cres",
    "sg:city":"Menai",
    "sg:classifiers":[
        {
            "category":"Health Services",
            "subcategory":"Doctor",
            "type":"Services"
        }
    ],
    "sg:phone":"+61 2 8307 0333",
    "sg:postcode":"2234",
    "sg:province":"NSW",
    "sg:tags":[
        "medical",
        "practitioner"
    ],
    "wof:name":"Chen Darren B Dr",
    "wof:placetype":"venue"
},
  "geometry": {"coordinates":[151.013671875,-34.0159759521],"type":"Point"}
}