{
  "type": "Feature",
  "properties": {
    "iso:country":"AU",
    "sg:address":"Level 5/ 434 St Kilda Rd",
    "sg:city":"Melbourne",
    "sg:classifiers":[
        {
            "category":"Professional",
            "subcategory":"Computer Services",
            "type":"Services"
        }
    ],
    "sg:phone":"+61 3 8676 4970",
    "sg:postcode":"3004",
    "sg:province":"VIC",
    "sg:tags":[
        "repairs",
        "upgrade",
        "equipment"
    ],
    "wof:name":"Wireless IT & T",
    "wof:placetype":"venue"
},
  "geometry": {"coordinates":[144.97561645499999,-37.8374557495],"type":"Point"}
}