{
  "type": "Feature",
  "properties": {
    "iso:country":"AU",
    "sg:address":"91 Prospect Hill Rd",
    "sg:city":"Narre Warren",
    "sg:classifiers":[
        {
            "category":"Retail",
            "subcategory":"Driving School",
            "type":"Services"
        }
    ],
    "sg:phone":"+61 3 9704 9020",
    "sg:postcode":"3805",
    "sg:province":"VIC",
    "wof:name":"A To Z New Generation Driving School",
    "wof:placetype":"venue"
},
  "geometry": {"coordinates":[145.30740399999999,-38.010914],"type":"Point"}
}