{
  "type": "Feature",
  "properties": {
    "iso:country":"AU",
    "sg:address":"Colonnades Shopping Centre Beach Rd",
    "sg:city":"Noarlunga",
    "sg:classifiers":[
        {
            "category":"Food & Beverages",
            "subcategory":"Bakery",
            "type":"Retail Goods"
        }
    ],
    "sg:phone":"+61 8 8384 7077",
    "sg:postcode":"5168",
    "sg:province":"SA",
    "sg:tags":[
        "baker"
    ],
    "wof:name":"Bakers Delight(SA)Pty Ltd",
    "wof:placetype":"venue"
},
  "geometry": {"coordinates":[138.50100707999999,-35.1641693115],"type":"Point"}
}