{
  "type": "Feature",
  "properties": {
    "addr:full":"342 Fearnley St Manunda QLD 4870",
    "addr:housenumber":"342",
    "addr:postcode":"4870",
    "addr:street":"Fearnley St",
    "iso:country":"AU",
    "sg:address":"342 Fearnley St",
    "sg:city":"Manunda",
    "sg:classifiers":[
        {
            "category":"Professional",
            "subcategory":"Art Services",
            "type":"Services"
        }
    ],
    "sg:phone":"+61 7 4051 5069",
    "sg:postcode":"4870",
    "sg:province":"QLD",
    "sg:tags":[
        "decorator",
        "painter"
    ],
    "wof:name":"Semken Warwick",
    "wof:placetype":"venue"
},
  "geometry": {"coordinates":[145.752197266,-16.9139919281],"type":"Point"}
}