{
  "type": "Feature",
  "properties": {
    "addr:full":"PO Box 913 Croydon NSW 8674",
    "addr:postcode":"8674",
    "iso:country":"AU",
    "sg:address":"PO Box 913",
    "sg:city":"Croydon",
    "sg:classifiers":[
        {
            "category":"Home & Garden",
            "subcategory":"Household Appliances",
            "type":"Retail Goods"
        }
    ],
    "sg:phone":"+61 3 9726 7986",
    "sg:postcode":"8674",
    "sg:province":"NSW",
    "sg:tags":[
        "equipment",
        "gas"
    ],
    "wof:name":"G & S Gas Appliance Service",
    "wof:placetype":"venue"
},
  "geometry": {"coordinates":[145.279754639,-37.7989196777],"type":"Point"}
}