{
  "type": "Feature",
  "properties": {
    "iso:country":"AU",
    "sg:address":"Anderson Pl",
    "sg:city":"Hume",
    "sg:classifiers":[
        {
            "category":"Retail",
            "subcategory":"Storage",
            "type":"Services"
        }
    ],
    "sg:phone":"+61 2 6242 0092",
    "sg:postcode":"2620",
    "sg:province":"ACT",
    "wof:name":"Capital Self Storage",
    "wof:placetype":"venue"
},
  "geometry": {"coordinates":[149.16217040999999,-35.4014892578],"type":"Point"}
}