{
  "type": "Feature",
  "properties": {
    "iso:country":"AU",
    "sg:address":"93 Alexander Drv",
    "sg:city":"Nerang",
    "sg:classifiers":[
        {
            "category":"Social Services",
            "subcategory":"Child Care",
            "type":"Services"
        }
    ],
    "sg:phone":"+61 7 5574 9222",
    "sg:postcode":"4211",
    "sg:province":"QLD",
    "wof:name":"Fantasyland Kindy.",
    "wof:placetype":"venue"
},
  "geometry": {"coordinates":[153.336395264,-28.0138072968],"type":"Point"}
}