{
  "type": "Feature",
  "properties": {
    "addr:full":"Unit 4, 20 Walker St Windsor South NSW 2756",
    "addr:housenumber":"20",
    "addr:postcode":"2756",
    "addr:street":"Walker St",
    "iso:country":"AU",
    "sg:address":"Unit 4, 20 Walker St",
    "sg:city":"Windsor South",
    "sg:classifiers":[
        {
            "category":"Wholesale",
            "subcategory":"Painting Supplies",
            "type":"Manufacturing & Wholesale Goods"
        }
    ],
    "sg:phone":"+61 2 4587 7869",
    "sg:postcode":"2756",
    "sg:province":"NSW",
    "sg:tags":[
        "wholesaler",
        "paint",
        "mfrs"
    ],
    "wof:name":"Tuhanal",
    "wof:placetype":"venue"
},
  "geometry": {"coordinates":[150.8097229,-33.6238975525],"type":"Point"}
}