{
  "type": "Feature",
  "properties": {
    "addr:full":"172 Victoria St Seddon VIC 3011",
    "addr:housenumber":"172",
    "addr:postcode":"3011",
    "addr:street":"Victoria St",
    "iso:country":"AU",
    "sg:address":"172 Victoria St",
    "sg:city":"Seddon",
    "sg:classifiers":[
        {
            "category":"Shopping",
            "subcategory":"Party Supplies",
            "type":"Retail Goods"
        }
    ],
    "sg:phone":"+61 3 9689 1642",
    "sg:postcode":"3011",
    "sg:province":"VIC",
    "sg:tags":[
        "hire",
        "costume"
    ],
    "wof:name":"Bower Bird Boutique",
    "wof:placetype":"venue"
},
  "geometry": {"coordinates":[144.89176940900001,-37.8058395386],"type":"Point"}
}