{
  "type": "Feature",
  "properties": {
    "iso:country":"AU",
    "sg:address":"Blantyre Ave",
    "sg:city":"Chelsea",
    "sg:classifiers":[
        {
            "category":"Arena",
            "subcategory":"Sports Club",
            "type":"Entertainment"
        }
    ],
    "sg:phone":"+61 3 9772 1541",
    "sg:postcode":"3196",
    "sg:province":"VIC",
    "sg:tags":[
        "australian",
        "football",
        "rule"
    ],
    "wof:name":"Chelsea Football Club",
    "wof:placetype":"venue"
},
  "geometry": {"coordinates":[145.11836242699999,-38.0518341064],"type":"Point"}
}