{
  "type": "Feature",
  "properties": {
    "iso:country":"AU",
    "sg:address":"613 Mair St",
    "sg:city":"Ballarat",
    "sg:classifiers":[
        {
            "category":"Health Services",
            "subcategory":"Dentist",
            "type":"Services"
        }
    ],
    "sg:phone":"+61 3 5331 6600",
    "sg:postcode":"3350",
    "sg:province":"VIC",
    "sg:tags":[
        "state",
        "orthodontist",
        "qld",
        "exc"
    ],
    "wof:name":"Lee Stella Dr",
    "wof:placetype":"venue"
},
  "geometry": {"coordinates":[143.85107400000001,-37.559052],"type":"Point"}
}