{
  "type": "Feature",
  "properties": {
    "addr:full":"476- 478 Victoria St Wetherill Park NSW 2164",
    "addr:housenumber":"478",
    "addr:postcode":"2164",
    "addr:street":"476;Victoria St",
    "iso:country":"AU",
    "sg:address":"476- 478 Victoria St",
    "sg:city":"Wetherill Park",
    "sg:classifiers":[
        {
            "category":"Professional",
            "subcategory":"Printing & Photocopies",
            "type":"Services"
        }
    ],
    "sg:phone":"+61 2 9604 1299",
    "sg:postcode":"2164",
    "sg:province":"NSW",
    "sg:tags":[
        "screen",
        "printer"
    ],
    "wof:name":"GUISEPAK PTY LTD",
    "wof:placetype":"venue"
},
  "geometry": {"coordinates":[150.88845825199999,-33.8437271118],"type":"Point"}
}