{
  "type": "Feature",
  "properties": {
    "iso:country":"AU",
    "sg:address":"6 Clifford Ave",
    "sg:city":"Kurralta Park",
    "sg:classifiers":[
        {
            "category":"Retail",
            "subcategory":"Auto Repair",
            "type":"Services"
        }
    ],
    "sg:phone":"+61 8 8293 4849",
    "sg:postcode":"5037",
    "sg:province":"SA",
    "sg:tags":[
        "repairer",
        "motor",
        "engineer"
    ],
    "wof:name":"Mobile AutoCare Workshop",
    "wof:placetype":"venue"
},
  "geometry": {"coordinates":[138.56478881800001,-34.9476547241],"type":"Point"}
}