{
  "type": "Feature",
  "properties": {
    "iso:country":"AU",
    "sg:address":"2 Edward St",
    "sg:city":"Richmond",
    "sg:classifiers":[
        {
            "category":"Shopping",
            "subcategory":"Antiques",
            "type":"Retail Goods"
        }
    ],
    "sg:phone":"+61 3 6260 2601",
    "sg:postcode":"7025",
    "sg:province":"TAS",
    "wof:name":"Richmond Antiques",
    "wof:placetype":"venue"
},
  "geometry": {"coordinates":[147.43751525900001,-42.7360801697],"type":"Point"}
}