{
  "type": "Feature",
  "properties": {
    "iso:country":"AU",
    "sg:address":"Unit 4, 4 Dawson Crt",
    "sg:city":"Mornington",
    "sg:classifiers":[
        {
            "category":"Education",
            "subcategory":"Music School",
            "type":"Public Place"
        }
    ],
    "sg:phone":"+61 3 6244 5344",
    "sg:postcode":"7018",
    "sg:province":"TAS",
    "sg:tags":[
        "teacher"
    ],
    "wof:name":"Margot Lampkin",
    "wof:placetype":"venue"
},
  "geometry": {"coordinates":[147.38478088400001,-42.8608093262],"type":"Point"}
}