{
  "type": "Feature",
  "properties": {
    "iso:country":"AU",
    "sg:address":"Studio 116, Level 1, 86 Murray St",
    "sg:city":"Hobart",
    "sg:classifiers":[
        {
            "category":"Professional",
            "subcategory":"Employment Agencies",
            "type":"Services"
        }
    ],
    "sg:phone":"+61 400 904 356",
    "sg:postcode":"7000",
    "sg:province":"TAS",
    "sg:tags":[
        "model"
    ],
    "wof:name":"Select Academy",
    "wof:placetype":"venue"
},
  "geometry": {"coordinates":[147.32612609899999,-42.8829994202],"type":"Point"}
}