{
  "type": "Feature",
  "properties": {
    "iso:country":"AU",
    "sg:address":"144 Emu Bay Rd",
    "sg:city":"Deloraine",
    "sg:classifiers":[
        {
            "category":"Travel",
            "subcategory":"Hotels & Motels",
            "type":"Entertainment"
        }
    ],
    "sg:phone":"+61 3 6362 2633",
    "sg:postcode":"7304",
    "sg:province":"TAS",
    "wof:name":"Golden Chain Mountain View Country Inn",
    "wof:placetype":"venue"
},
  "geometry": {"coordinates":[146.641998,-41.52039],"type":"Point"}
}