{
  "type": "Feature",
  "properties": {
    "iso:country":"AU",
    "sg:address":"28 Cork St",
    "sg:city":"Winton",
    "sg:classifiers":[
        {
            "category":"Building & Trades",
            "subcategory":"Construction",
            "type":"Services"
        }
    ],
    "sg:phone":"+61 7 4657 1529",
    "sg:postcode":"4735",
    "sg:province":"QLD",
    "sg:tags":[
        "contractor"
    ],
    "wof:name":"Mann M J",
    "wof:placetype":"venue"
},
  "geometry": {"coordinates":[143.041504,-22.387281],"type":"Point"}
}