{
  "type": "Feature",
  "properties": {
    "addr:full":"10 Mitchell St St Kilda VIC 3182",
    "addr:housenumber":"10",
    "addr:postcode":"3182",
    "addr:street":"Mitchell St",
    "iso:country":"AU",
    "sg:address":"10 Mitchell St",
    "sg:city":"St Kilda",
    "sg:classifiers":[
        {
            "category":"Travel",
            "subcategory":"Hostel",
            "type":"Entertainment"
        }
    ],
    "sg:phone":"+61 3 9534 1602",
    "sg:postcode":"3182",
    "sg:province":"VIC",
    "sg:tags":[
        "home"
    ],
    "wof:name":"Galiamble",
    "wof:placetype":"venue"
},
  "geometry": {"coordinates":[144.98377990700001,-37.8680725098],"type":"Point"}
}