{
  "type": "Feature",
  "properties": {
    "addr:full":"2 Belgrove St Preston VIC 3072",
    "addr:housenumber":"2",
    "addr:postcode":"3072",
    "addr:street":"Belgrove St",
    "iso:country":"AU",
    "sg:address":"2 Belgrove St",
    "sg:city":"Preston",
    "sg:classifiers":[
        {
            "category":"Shopping",
            "subcategory":"Music",
            "type":"Retail Goods"
        }
    ],
    "sg:phone":"+61 3 9416 9521",
    "sg:postcode":"3072",
    "sg:province":"VIC",
    "sg:tags":[
        "instrument",
        "musical"
    ],
    "wof:name":"Drum Partners",
    "wof:placetype":"venue"
},
  "geometry": {"coordinates":[145.01902770999999,-37.7458190918],"type":"Point"}
}