{
  "type": "Feature",
  "properties": {
    "iso:country":"AU",
    "sg:address":"29, Carlingford St",
    "sg:city":"Regents Park",
    "sg:classifiers":[
        {
            "category":"Manufacturing",
            "subcategory":"Printing",
            "type":"Manufacturing & Wholesale Goods"
        }
    ],
    "sg:phone":"+61 2 9645 1822",
    "sg:postcode":"2143",
    "sg:province":"NSW",
    "sg:tags":[
        "encoding",
        "cheque"
    ],
    "wof:name":"Graphic Centre",
    "wof:placetype":"venue"
},
  "geometry": {"coordinates":[151.01832580600001,-33.8856468201],"type":"Point"}
}