{
  "type": "Feature",
  "properties": {
    "iso:country":"AU",
    "sg:address":"1145 Berrimah Rd",
    "sg:city":"Berrimah",
    "sg:classifiers":[
        {
            "category":"Government",
            "subcategory":"Post Office",
            "type":"Public Place"
        }
    ],
    "sg:phone":"+61 8 8984 3020",
    "sg:postcode":"0828",
    "sg:province":"NT",
    "sg:tags":[
        "postal"
    ],
    "wof:name":"Australia Post",
    "wof:placetype":"venue"
},
  "geometry": {"coordinates":[130.92344665499999,-12.4338264465],"type":"Point"}
}