{
  "type": "Feature",
  "properties": {
    "addr:full":"U 3/ 6 Dorsey St Milton QLD 4064",
    "addr:housenumber":"6",
    "addr:postcode":"4064",
    "addr:street":"Dorsey St",
    "iso:country":"AU",
    "sg:address":"U 3/ 6 Dorsey St",
    "sg:city":"Milton",
    "sg:classifiers":[
        {
            "category":"Health Services",
            "subcategory":"Health Practitioner",
            "type":"Services"
        }
    ],
    "sg:phone":"+61 7 3369 3740",
    "sg:postcode":"4064",
    "sg:province":"QLD",
    "sg:tags":[
        "physiotherapist"
    ],
    "wof:name":"Fagan Amy",
    "wof:placetype":"venue"
},
  "geometry": {"coordinates":[153.001495361,-27.4718208313],"type":"Point"}
}