{
  "type": "Feature",
  "properties": {
    "iso:country":"AU",
    "sg:address":"41 Belford St",
    "sg:city":"Broadmeadow",
    "sg:classifiers":[
        {
            "category":"Health Services",
            "subcategory":"Doctor",
            "type":"Services"
        }
    ],
    "sg:phone":"+61 2 4965 3668",
    "sg:postcode":"2292",
    "sg:province":"NSW",
    "sg:tags":[
        "medical",
        "practitioner"
    ],
    "wof:name":"Australasian College Of Phlebology",
    "wof:placetype":"venue"
},
  "geometry": {"coordinates":[151.73770141599999,-32.9243240356],"type":"Point"}
}