{
  "type": "Feature",
  "properties": {
    "iso:country":"AU",
    "sg:address":"34- 36 Bond St",
    "sg:city":"Ringwood",
    "sg:classifiers":[
        {
            "category":"Wholesale",
            "subcategory":"Medical Equipment & Supplies",
            "type":"Manufacturing & Wholesale Goods"
        }
    ],
    "sg:phone":"+61 3 9899 3944",
    "sg:postcode":"3134",
    "sg:province":"VIC",
    "sg:tags":[
        "aids",
        "hearing"
    ],
    "wof:name":"Altidis Hearing Services",
    "wof:placetype":"venue"
},
  "geometry": {"coordinates":[145.223342895,-37.8138465881],"type":"Point"}
}