{
  "type": "Feature",
  "properties": {
    "addr:full":"Lot 2 Grandview Pde Hill Top NSW 2575",
    "addr:postcode":"2575",
    "addr:street":"Pde",
    "iso:country":"AU",
    "sg:address":"Lot 2 Grandview Pde",
    "sg:city":"Hill Top",
    "sg:classifiers":[
        {
            "category":"Building & Trades",
            "subcategory":"Landscaping Services",
            "type":"Services"
        }
    ],
    "sg:phone":"+61 2 4889 8728",
    "sg:postcode":"2575",
    "sg:province":"NSW",
    "sg:tags":[
        "stump",
        "tree",
        "felling",
        "removal"
    ],
    "wof:name":"P & T Stump Grinding Service",
    "wof:placetype":"venue"
},
  "geometry": {"coordinates":[150.495483398,-34.3435058594],"type":"Point"}
}