{
  "type": "Feature",
  "properties": {
    "addr:full":"Kirwin St (Cnr Esplanade St) Cairns QLD 4870",
    "addr:postcode":"4870",
    "addr:street":"Kirwin St Cnr Esplanade St",
    "iso:country":"AU",
    "sg:address":"Kirwin St (Cnr Esplanade St)",
    "sg:city":"Cairns",
    "sg:classifiers":[
        {
            "category":"Retail",
            "subcategory":"Event Space",
            "type":"Services"
        }
    ],
    "sg:phone":"+61 7 4044 9000",
    "sg:postcode":"4870",
    "sg:province":"QLD",
    "sg:tags":[
        "venue",
        "reception",
        "wedding"
    ],
    "wof:name":"Rydges Esplanade Resort Cairns",
    "wof:placetype":"venue"
},
  "geometry": {"coordinates":[145.76937866200001,-16.9136066437],"type":"Point"}
}