{
  "type": "Feature",
  "properties": {
    "iso:country":"AU",
    "sg:address":"200 Mt Alexander Rd",
    "sg:city":"Flemington",
    "sg:classifiers":[
        {
            "category":"Health Services",
            "subcategory":"Doctor",
            "type":"Services"
        }
    ],
    "sg:phone":"+61 3 9376 1844",
    "sg:postcode":"3031",
    "sg:province":"VIC",
    "sg:tags":[
        "occupational",
        "safety"
    ],
    "wof:name":"Ergonomics Consulting Group",
    "wof:placetype":"venue"
},
  "geometry": {"coordinates":[144.932663,-37.781078],"type":"Point"}
}