{
  "type": "Feature",
  "properties": {
    "addr:full":"24/ 18 Mactier St Narrabeen NSW 2101",
    "addr:housenumber":"24 / 18",
    "addr:postcode":"2101",
    "addr:street":"Mactier St",
    "iso:country":"AU",
    "sg:address":"24/ 18 Mactier St",
    "sg:city":"Narrabeen",
    "sg:classifiers":[
        {
            "category":"Professional",
            "subcategory":"Art Services",
            "type":"Services"
        }
    ],
    "sg:phone":"+61 2 9918 6138",
    "sg:postcode":"2101",
    "sg:province":"NSW",
    "sg:tags":[
        "decorator",
        "painter"
    ],
    "wof:name":"Peter Corney",
    "wof:placetype":"venue"
},
  "geometry": {"coordinates":[151.29716500000001,-33.722164],"type":"Point"}
}