{
  "type": "Feature",
  "properties": {
    "addr:full":"104 Wellington St Waterloo NSW 2017",
    "addr:housenumber":"104",
    "addr:postcode":"2017",
    "addr:street":"Wellington St",
    "iso:country":"AU",
    "sg:address":"104 Wellington St",
    "sg:city":"Waterloo",
    "sg:classifiers":[
        {
            "category":"Social Services",
            "subcategory":"Child Care",
            "type":"Services"
        }
    ],
    "sg:phone":"+61 2 9690 1140",
    "sg:postcode":"2017",
    "sg:province":"NSW",
    "wof:name":"SDN Children's Services",
    "wof:placetype":"venue"
},
  "geometry": {"coordinates":[151.202835083,-33.8984489441],"type":"Point"}
}