{
  "type": "Feature",
  "properties": {
    "addr:full":"320 Marrickville Rd Marrickville NSW 2204",
    "addr:housenumber":"320",
    "addr:postcode":"2204",
    "addr:street":"Marrickville Rd",
    "iso:country":"AU",
    "sg:address":"320 Marrickville Rd",
    "sg:city":"Marrickville",
    "sg:classifiers":[
        {
            "category":"Shopping",
            "subcategory":"Pawn Shop",
            "type":"Retail Goods"
        }
    ],
    "sg:phone":"+61 2 9518 1821",
    "sg:postcode":"2204",
    "sg:province":"NSW",
    "sg:tags":[
        "pawnbroker"
    ],
    "wof:name":"Cash & Carry Pawn Brokers Pty Ltd",
    "wof:placetype":"venue"
},
  "geometry": {"coordinates":[151.15477000000001,-33.909916],"type":"Point"}
}