{
  "type": "Feature",
  "properties": {
    "addr:full":"Unit 3 7 Barlow St South Townsville QLD 4810",
    "addr:housenumber":"7",
    "addr:postcode":"4810",
    "addr:street":"Barlow St",
    "iso:country":"AU",
    "sg:address":"Unit 3 7 Barlow St",
    "sg:city":"South Townsville",
    "sg:classifiers":[
        {
            "category":"Real Estate",
            "subcategory":"Architect",
            "type":"Services"
        }
    ],
    "sg:phone":"+61 7 4721 2111",
    "sg:postcode":"4810",
    "sg:province":"QLD",
    "wof:name":"MacCallum & Partners Architects",
    "wof:placetype":"venue"
},
  "geometry": {"coordinates":[146.81686400000001,-19.256733],"type":"Point"}
}