{
  "type": "Feature",
  "properties": {
    "addr:full":"Kmart Shopng Cntr, Lime Ave Mildura VIC 3500",
    "addr:postcode":"3500",
    "addr:street":"Lime Ave",
    "iso:country":"AU",
    "sg:address":"Kmart Shopng Cntr, Lime Ave",
    "sg:city":"Mildura",
    "sg:classifiers":[
        {
            "category":"Retail",
            "subcategory":"Auto Repair",
            "type":"Services"
        }
    ],
    "sg:phone":"+61 3 5023 7049",
    "sg:postcode":"3500",
    "sg:province":"VIC",
    "sg:tags":[
        "repairer",
        "motor",
        "engineer"
    ],
    "wof:name":"Kmart Tyre & Auto Service",
    "wof:placetype":"venue"
},
  "geometry": {"coordinates":[142.15609741200001,-34.1869926453],"type":"Point"}
}