{
  "type": "Feature",
  "properties": {
    "addr:full":"12 Bungaree Crs Ngunnawal ACT 2913",
    "addr:housenumber":"12",
    "addr:postcode":"2913",
    "addr:street":"Bungaree Crs",
    "iso:country":"AU",
    "sg:address":"12 Bungaree Crs",
    "sg:city":"Ngunnawal",
    "sg:classifiers":[
        {
            "category":"Professional",
            "subcategory":"Art Services",
            "type":"Services"
        }
    ],
    "sg:phone":"+61 2 6241 1718",
    "sg:postcode":"2913",
    "sg:province":"ACT",
    "sg:tags":[
        "decorator",
        "painter"
    ],
    "wof:name":"Heritage Painters",
    "wof:placetype":"venue"
},
  "geometry": {"coordinates":[149.108032227,-35.173160553],"type":"Point"}
}