{
  "type": "Feature",
  "properties": {
    "addr:full":"340 Half Chain Rd Koorainghat NSW 2430",
    "addr:housenumber":"340",
    "addr:postcode":"2430",
    "addr:street":"Half Chain Rd",
    "iso:country":"AU",
    "sg:address":"340 Half Chain Rd",
    "sg:city":"Koorainghat",
    "sg:classifiers":[
        {
            "category":"Building & Trades",
            "subcategory":"Construction",
            "type":"Services"
        }
    ],
    "sg:phone":"+61 2 6553 6114",
    "sg:postcode":"2430",
    "sg:province":"NSW",
    "sg:tags":[
        "renovation",
        "alterations",
        "extension",
        "contractor"
    ],
    "wof:name":"John Cross Building Co",
    "wof:placetype":"venue"
},
  "geometry": {"coordinates":[152.50108299999999,-31.969381],"type":"Point"}
}