{
  "type": "Feature",
  "properties": {
    "iso:country":"AU",
    "sg:address":"20 Clarence Rd",
    "sg:city":"Springfield",
    "sg:classifiers":[
        {
            "category":"Freight",
            "type":"Transportation"
        }
    ],
    "sg:phone":"+61 418 239 504",
    "sg:postcode":"2250",
    "sg:province":"NSW",
    "sg:tags":[
        "light",
        "carrier"
    ],
    "wof:name":"Absolute Road Runner Del",
    "wof:placetype":"venue"
},
  "geometry": {"coordinates":[151.38209533700001,-33.432308197],"type":"Point"}
}