{
  "type": "Feature",
  "properties": {
    "addr:full":"34 Beatson St Wollongong NSW 2500",
    "addr:housenumber":"34",
    "addr:postcode":"2500",
    "addr:street":"Beatson St",
    "iso:country":"AU",
    "sg:address":"34 Beatson St",
    "sg:city":"Wollongong",
    "sg:classifiers":[
        {
            "category":"Retail",
            "subcategory":"Auto Repair",
            "type":"Services"
        }
    ],
    "sg:phone":"+61 2 4228 8387",
    "sg:postcode":"2500",
    "sg:province":"NSW",
    "sg:tags":[
        "repairer",
        "motor",
        "engineer"
    ],
    "wof:name":"R & C Automotive",
    "wof:placetype":"venue"
},
  "geometry": {"coordinates":[150.896896,-34.43314],"type":"Point"}
}