{
  "type": "Feature",
  "properties": {
    "addr:full":"Centro Warriewood Jackson Rd Warriewood NSW 2102",
    "addr:postcode":"2102",
    "addr:street":"Jackson Rd",
    "iso:country":"AU",
    "sg:address":"Centro Warriewood Jackson Rd",
    "sg:city":"Warriewood",
    "sg:classifiers":[
        {
            "category":"Shopping",
            "type":"Retail Goods"
        }
    ],
    "sg:phone":"+61 2 9913 2199",
    "sg:postcode":"2102",
    "sg:province":"NSW",
    "sg:tags":[
        "repair",
        "travel"
    ],
    "wof:name":"Strandbags Group Pty Limited",
    "wof:placetype":"venue"
},
  "geometry": {"coordinates":[151.299057,-33.686279],"type":"Point"}
}