{
  "type": "Feature",
  "properties": {
    "iso:country":"AU",
    "sg:address":"80 Frank St",
    "sg:city":"Eltham",
    "sg:classifiers":[
        {
            "category":"Professional",
            "subcategory":"Computer Services",
            "type":"Services"
        }
    ],
    "sg:phone":"+61 400 957 781",
    "sg:postcode":"3095",
    "sg:province":"VIC",
    "sg:tags":[
        "training"
    ],
    "wof:name":"Adaware Pty Ltd",
    "wof:placetype":"venue"
},
  "geometry": {"coordinates":[145.17132568400001,-37.7076454163],"type":"Point"}
}