{
  "type": "Feature",
  "properties": {
    "iso:country":"AU",
    "sg:address":"776 Pacific Pde",
    "sg:city":"Currumbin Beach",
    "sg:classifiers":[
        {
            "category":"Restaurant",
            "type":"Food & Drink"
        }
    ],
    "sg:phone":"+61 7 5598 2133",
    "sg:postcode":"4223",
    "sg:province":"QLD",
    "wof:name":"Elephant Rock Cafe",
    "wof:placetype":"venue"
},
  "geometry": {"coordinates":[153.48826599099999,-28.1316871643],"type":"Point"}
}