{
  "type": "Feature",
  "properties": {
    "addr:full":"205 Star St Welshpool WA 6106",
    "addr:housenumber":"205",
    "addr:postcode":"6106",
    "addr:street":"Star St",
    "iso:country":"AU",
    "sg:address":"205 Star St",
    "sg:city":"Welshpool",
    "sg:classifiers":[
        {
            "category":"Home & Garden",
            "subcategory":"Building Materials",
            "type":"Retail Goods"
        }
    ],
    "sg:phone":"+61 8 9362 4744",
    "sg:postcode":"6106",
    "sg:province":"WA",
    "sg:tags":[
        "fencing"
    ],
    "wof:name":"Johns Building Supplies Pty Ltd",
    "wof:placetype":"venue"
},
  "geometry": {"coordinates":[115.929550171,-31.9878673553],"type":"Point"}
}