{
  "type": "Feature",
  "properties": {
    "addr:full":"249 Glenferrie Rd Malvern VIC 3144",
    "addr:housenumber":"249",
    "addr:postcode":"3144",
    "addr:street":"Glenferrie Rd",
    "iso:country":"AU",
    "sg:address":"249 Glenferrie Rd",
    "sg:city":"Malvern",
    "sg:classifiers":[
        {
            "category":"Fast Food",
            "type":"Food & Drink"
        }
    ],
    "sg:phone":"+61 3 9509 6883",
    "sg:postcode":"3144",
    "sg:province":"VIC",
    "sg:tags":[
        "away",
        "take"
    ],
    "wof:name":"Fortune's Asian Cuisine",
    "wof:placetype":"venue"
},
  "geometry": {"coordinates":[145.02891540499999,-37.8577880859],"type":"Point"}
}