{
  "type": "Feature",
  "properties": {
    "iso:country":"AU",
    "sg:address":"8 Victory Ave",
    "sg:city":"Ballarat",
    "sg:classifiers":[
        {
            "category":"Professional",
            "subcategory":"Detective & Security Services",
            "type":"Services"
        }
    ],
    "sg:phone":"+61 3 5334 1238",
    "sg:postcode":"3350",
    "sg:province":"VIC",
    "sg:tags":[
        "investigator"
    ],
    "wof:name":"Ballarat Investigations",
    "wof:placetype":"venue"
},
  "geometry": {"coordinates":[143.809174,-37.552738],"type":"Point"}
}