{
  "type": "Feature",
  "properties": {
    "addr:full":"8 St Ives Gr Mt Martha VIC 3934",
    "addr:housenumber":"8",
    "addr:postcode":"3934",
    "addr:street":"St;Mt Martha",
    "iso:country":"AU",
    "sg:address":"8 St",
    "sg:city":"Ives Gr Mt Martha",
    "sg:classifiers":[
        {
            "category":"Professional",
            "subcategory":"Accounting & Tax Preparation",
            "type":"Services"
        }
    ],
    "sg:phone":"+61 3 5974 3355",
    "sg:postcode":"3934",
    "sg:province":"VIC",
    "sg:tags":[
        "consultant",
        "taxation"
    ],
    "wof:name":"Robin Whitehead",
    "wof:placetype":"venue"
},
  "geometry": {"coordinates":[145.02494812,-38.2724227905],"type":"Point"}
}