{
  "type": "Feature",
  "properties": {
    "iso:country":"AU",
    "sg:address":"First Ave",
    "sg:city":"Unanderra",
    "sg:classifiers":[
        {
            "category":"Professional",
            "subcategory":"Printing & Photocopies",
            "type":"Services"
        }
    ],
    "sg:phone":"+61 2 4272 2499",
    "sg:postcode":"2526",
    "sg:province":"NSW",
    "sg:tags":[
        "trophy"
    ],
    "wof:name":"Awards Plus",
    "wof:placetype":"venue"
},
  "geometry": {"coordinates":[150.85038757300001,-34.4500312805],"type":"Point"}
}