{
  "type": "Feature",
  "properties": {
    "addr:full":"The Hills Hospital Suite 8 200 Pacific Hwy Crows Nest NSW 2065",
    "addr:housenumber":"200",
    "addr:postcode":"2065",
    "addr:street":"Pacific Hwy",
    "iso:country":"AU",
    "sg:address":"The Hills Hospital Suite 8 200 Pacific Hwy",
    "sg:city":"Crows Nest",
    "sg:classifiers":[
        {
            "category":"Health Services",
            "subcategory":"Doctor",
            "type":"Services"
        }
    ],
    "sg:phone":"+61 414 996 030",
    "sg:postcode":"2065",
    "sg:province":"NSW",
    "sg:tags":[
        "medical",
        "practitioner"
    ],
    "wof:name":"Paul Miriam Dr",
    "wof:placetype":"venue"
},
  "geometry": {"coordinates":[151.19895935100001,-33.8255615234],"type":"Point"}
}