{
  "type": "Feature",
  "properties": {
    "addr:full":"17 Arundel St West Pymble NSW 2073",
    "addr:housenumber":"17",
    "addr:postcode":"2073",
    "addr:street":"Arundel St",
    "iso:country":"AU",
    "sg:address":"17 Arundel St",
    "sg:city":"West Pymble",
    "sg:classifiers":[
        {
            "category":"Professional",
            "subcategory":"Art Services",
            "type":"Services"
        }
    ],
    "sg:phone":"+61 412 216 663",
    "sg:postcode":"2073",
    "sg:province":"NSW",
    "sg:tags":[
        "graphic",
        "designer"
    ],
    "wof:name":"Brent Daisley",
    "wof:placetype":"venue"
},
  "geometry": {"coordinates":[151.124237061,-33.7600975037],"type":"Point"}
}