{
  "type": "Feature",
  "properties": {
    "iso:country":"AU",
    "sg:address":"Shop F/ 53 Racecourse Rd",
    "sg:city":"Hamilton",
    "sg:classifiers":[
        {
            "category":"Health Services",
            "subcategory":"Doctor",
            "type":"Services"
        }
    ],
    "sg:phone":"+61 7 3268 5878",
    "sg:postcode":"4007",
    "sg:province":"QLD",
    "sg:tags":[
        "podiatrist"
    ],
    "sg:website":"http://www.bearfootpodiatry.com.au",
    "wof:name":"Bearfoot Podiatry",
    "wof:placetype":"venue"
},
  "geometry": {"coordinates":[153.064865,-27.436852],"type":"Point"}
}