{
  "type": "Feature",
  "properties": {
    "addr:full":"1/11 853 Nudgee Rd Northgate QLD 4013",
    "addr:housenumber":"/",
    "addr:postcode":"853;4013",
    "addr:street":"11;Nudgee Rd",
    "iso:country":"AU",
    "sg:address":"1/11 853 Nudgee Rd",
    "sg:city":"Northgate",
    "sg:classifiers":[
        {
            "category":"Professional",
            "type":"Services"
        }
    ],
    "sg:phone":"+61 7 3267 1933",
    "sg:postcode":"4013",
    "sg:province":"QLD",
    "sg:tags":[
        "forwarding",
        "agent",
        "transport"
    ],
    "wof:name":"Bell Total Logistics Pty Ltd",
    "wof:placetype":"venue"
},
  "geometry": {"coordinates":[153.081466675,-27.3916015625],"type":"Point"}
}