{
  "type": "Feature",
  "properties": {
    "addr:full":"53 Erindale Rd Balcatta WA 6021",
    "addr:housenumber":"53",
    "addr:postcode":"6021",
    "addr:street":"Erindale Rd",
    "iso:country":"AU",
    "sg:address":"53 Erindale Rd",
    "sg:city":"Balcatta",
    "sg:classifiers":[
        {
            "category":"Autos & Motor Vehicles",
            "subcategory":"Fuel & Gas Station",
            "type":"Retail Goods"
        }
    ],
    "sg:phone":"+61 8 9345 3878",
    "sg:postcode":"6021",
    "sg:province":"WA",
    "wof:name":"BP Erindale Road Self Serve",
    "wof:placetype":"venue"
},
  "geometry": {"coordinates":[115.808067322,-31.8650417328],"type":"Point"}
}