{
  "type": "Feature",
  "properties": {
    "addr:full":"59 Leveson St North Melbourne VIC 3051",
    "addr:housenumber":"59",
    "addr:postcode":"3051",
    "addr:street":"Leveson St",
    "iso:country":"AU",
    "sg:address":"59 Leveson St",
    "sg:city":"North Melbourne",
    "sg:classifiers":[
        {
            "category":"Professional",
            "subcategory":"Computer Services",
            "type":"Services"
        }
    ],
    "sg:phone":"+61 3 9287 7095",
    "sg:postcode":"3051",
    "sg:province":"VIC",
    "sg:tags":[
        "tele-communications",
        "consultant"
    ],
    "wof:name":"Cot Cases Australia",
    "wof:placetype":"venue"
},
  "geometry": {"coordinates":[144.950881958,-37.8034973145],"type":"Point"}
}