{
  "type": "Feature",
  "properties": {
    "iso:country":"AU",
    "sg:address":"Cnr Newbridge Rd",
    "sg:city":"& Pat Devlin Cl Chipping Norton",
    "sg:classifiers":[
        {
            "category":"Marine",
            "type":"Transportation"
        }
    ],
    "sg:phone":"+61 2 9821 4466",
    "sg:postcode":"2170",
    "sg:province":"NSW",
    "sg:tags":[
        "flagpole",
        "mast"
    ],
    "wof:name":"A Flag World",
    "wof:placetype":"venue"
},
  "geometry": {"coordinates":[150.96377563499999,-33.9286346436],"type":"Point"}
}