{
  "type": "Feature",
  "properties": {
    "addr:full":"276 Main Rd Cardiff NSW 2285",
    "addr:housenumber":"276",
    "addr:postcode":"2285",
    "addr:street":"Main Rd",
    "iso:country":"AU",
    "sg:address":"276 Main Rd",
    "sg:city":"Cardiff",
    "sg:classifiers":[
        {
            "category":"Professional",
            "subcategory":"Business Services",
            "type":"Services"
        }
    ],
    "sg:phone":"+61 2 4954 0399",
    "sg:postcode":"2285",
    "sg:province":"NSW",
    "sg:tags":[
        "broker"
    ],
    "wof:name":"Noel Mcfarlane Real Estate",
    "wof:placetype":"venue"
},
  "geometry": {"coordinates":[151.66004943900001,-32.9399833679],"type":"Point"}
}