{
  "type": "Feature",
  "properties": {
    "iso:country":"AU",
    "sg:address":"3 / 13",
    "sg:city":"Bon Mace Cl Tumbi Umbi",
    "sg:classifiers":[
        {
            "category":"Sports & Exercise",
            "subcategory":"Gym",
            "type":"Entertainment"
        }
    ],
    "sg:phone":"+61 2 4389 0888",
    "sg:postcode":"2261",
    "sg:province":"NSW",
    "sg:tags":[
        "health",
        "fitness"
    ],
    "wof:name":"Blackbelt Karate Studios",
    "wof:placetype":"venue"
},
  "geometry": {"coordinates":[151.445847,-33.378651],"type":"Point"}
}