{
  "type": "Feature",
  "properties": {
    "addr:full":"Ferris St Sunshine Beach QLD 4567",
    "addr:postcode":"4567",
    "addr:street":"Ferris St",
    "iso:country":"AU",
    "sg:address":"Ferris St",
    "sg:city":"Sunshine Beach",
    "sg:classifiers":[
        {
            "category":"Professional",
            "subcategory":"Printing & Photocopies",
            "type":"Services"
        }
    ],
    "sg:phone":"+61 7 5474 8522",
    "sg:postcode":"4567",
    "sg:province":"QLD",
    "sg:tags":[
        "publishing",
        "desktop"
    ],
    "wof:name":"Page People",
    "wof:placetype":"venue"
},
  "geometry": {"coordinates":[153.10763549800001,-26.4028720856],"type":"Point"}
}