{
  "type": "Feature",
  "properties": {
    "addr:full":"145. Stirling Hwy Nedlands WA 6009",
    "addr:housenumber":"145",
    "addr:postcode":"6009",
    "addr:street":"Stirling Hwy",
    "iso:country":"AU",
    "sg:address":"145. Stirling Hwy",
    "sg:city":"Nedlands",
    "sg:classifiers":[
        {
            "category":"Health Services",
            "subcategory":"Chiropractor",
            "type":"Services"
        }
    ],
    "sg:phone":"+61 8 9386 4599",
    "sg:postcode":"6009",
    "sg:province":"WA",
    "wof:name":"Bro Charles",
    "wof:placetype":"venue"
},
  "geometry": {"coordinates":[115.815811,-31.976608],"type":"Point"}
}