{
  "type": "Feature",
  "properties": {
    "addr:full":"20 English St Kogarah NSW 2217",
    "addr:housenumber":"20",
    "addr:postcode":"2217",
    "addr:street":"English St",
    "iso:country":"AU",
    "sg:address":"20 English St",
    "sg:city":"Kogarah",
    "sg:classifiers":[
        {
            "category":"Health Services",
            "subcategory":"Doctor",
            "type":"Services"
        }
    ],
    "sg:phone":"+61 2 9533 8895",
    "sg:postcode":"2217",
    "sg:province":"NSW",
    "sg:tags":[
        "medical",
        "practitioner"
    ],
    "wof:name":"South West Sydney Pain Management",
    "wof:placetype":"venue"
},
  "geometry": {"coordinates":[151.128295898,-33.9688835144],"type":"Point"}
}