{
  "type": "Feature",
  "properties": {
    "addr:full":"42 Uralba St Lismore NSW 2480",
    "addr:housenumber":"42",
    "addr:postcode":"2480",
    "addr:street":"Uralba St",
    "iso:country":"AU",
    "sg:address":"42 Uralba St",
    "sg:city":"Lismore",
    "sg:classifiers":[
        {
            "category":"Health Services",
            "subcategory":"Dentist",
            "type":"Services"
        }
    ],
    "sg:phone":"+61 1300 650 641",
    "sg:postcode":"2480",
    "sg:province":"NSW",
    "wof:name":"Darveniza Michael Dr",
    "wof:placetype":"venue"
},
  "geometry": {"coordinates":[153.28811645499999,-28.8095722198],"type":"Point"}
}