{
  "type": "Feature",
  "properties": {
    "addr:full":"1 Smythe St Wodonga VIC 3690",
    "addr:housenumber":"1",
    "addr:postcode":"3690",
    "addr:street":"Smythe St",
    "iso:country":"AU",
    "sg:address":"1 Smythe St",
    "sg:city":"Wodonga",
    "sg:classifiers":[
        {
            "category":"Government",
            "subcategory":"Fire Station",
            "type":"Public Place"
        }
    ],
    "sg:phone":"+61 2 6024 1065",
    "sg:postcode":"3690",
    "sg:province":"VIC",
    "sg:tags":[
        "brigade"
    ],
    "wof:name":"Wodonga Urban Fire Brigade",
    "wof:placetype":"venue"
},
  "geometry": {"coordinates":[146.883255005,-36.122051239],"type":"Point"}
}