{
  "type": "Feature",
  "properties": {
    "addr:full":"1377 Murradoc Rd St Leonards VIC 3223",
    "addr:housenumber":"1377",
    "addr:postcode":"3223",
    "addr:street":"Murradoc Rd",
    "iso:country":"AU",
    "sg:address":"1377 Murradoc Rd",
    "sg:city":"St Leonards",
    "sg:classifiers":[
        {
            "category":"Real Estate",
            "subcategory":"Real Estate Agent",
            "type":"Services"
        }
    ],
    "sg:phone":"+61 3 5257 1778",
    "sg:postcode":"3223",
    "sg:province":"VIC",
    "wof:name":"Neville Richards Real Estate",
    "wof:placetype":"venue"
},
  "geometry": {"coordinates":[144.710815,-38.186768],"type":"Point"}
}