{
  "type": "Feature",
  "properties": {
    "addr:full":"Cnr Belford & Blackall Sts Broadmeadow NSW 2292",
    "addr:postcode":"2292",
    "addr:street":"Cnr Belford & Blackall Sts",
    "iso:country":"AU",
    "sg:address":"Cnr Belford & Blackall Sts",
    "sg:city":"Broadmeadow",
    "sg:classifiers":[
        {
            "category":"Food & Beverages",
            "subcategory":"Liquor & Beverages",
            "type":"Retail Goods"
        }
    ],
    "sg:phone":"+61 2 4961 3761",
    "sg:postcode":"2292",
    "sg:province":"NSW",
    "sg:tags":[
        "store"
    ],
    "wof:name":"Theo's Liquor Markets",
    "wof:placetype":"venue"
},
  "geometry": {"coordinates":[151.738006592,-32.9241065979],"type":"Point"}
}