{
  "type": "Feature",
  "properties": {
    "addr:full":"Maryborough Hervey Bay Rd Hervey Bay QLD 4655",
    "addr:postcode":"4655",
    "addr:street":"Hervey Bay Rd",
    "iso:country":"AU",
    "sg:address":"Maryborough Hervey Bay Rd",
    "sg:city":"Hervey Bay",
    "sg:classifiers":[
        {
            "category":"Communications",
            "subcategory":"News Services",
            "type":"Services"
        }
    ],
    "sg:phone":"+61 7 4128 1180",
    "sg:postcode":"4655",
    "sg:province":"QLD",
    "sg:tags":[
        "information",
        "tourist",
        "attractions"
    ],
    "wof:name":"Hervey Bay Go Kart Track",
    "wof:placetype":"venue"
},
  "geometry": {"coordinates":[152.81778,-25.286242],"type":"Point"}
}