{
  "type": "Feature",
  "properties": {
    "addr:full":"7/ 7 Activity Crs Molendinar QLD 4214",
    "addr:housenumber":"/ 7",
    "addr:postcode":"4214",
    "addr:street":"Activity Crs",
    "iso:country":"AU",
    "sg:address":"7/ 7 Activity Crs",
    "sg:city":"Molendinar",
    "sg:classifiers":[
        {
            "category":"Retail",
            "subcategory":"Auto Repair",
            "type":"Services"
        }
    ],
    "sg:phone":"+61 414 671 671",
    "sg:postcode":"4214",
    "sg:province":"QLD",
    "sg:tags":[
        "body",
        "motor",
        "trimmer"
    ],
    "wof:name":"Goodline Trim",
    "wof:placetype":"venue"
},
  "geometry": {"coordinates":[153.36187744099999,-27.9781703949],"type":"Point"}
}