{
  "type": "Feature",
  "properties": {
    "addr:full":"Palen Creek Rd Rathdowney QLD 4287",
    "addr:postcode":"4287",
    "addr:street":"Palen Creek Rd",
    "iso:country":"AU",
    "sg:address":"Palen Creek Rd",
    "sg:city":"Rathdowney",
    "sg:classifiers":[
        {
            "category":"Farming",
            "subcategory":"Farm",
            "type":"Manufacturing & Wholesale Goods"
        }
    ],
    "sg:phone":"+61 7 5544 1195",
    "sg:postcode":"4287",
    "sg:province":"QLD",
    "sg:tags":[
        "farmer"
    ],
    "wof:name":"Masen H P & K M",
    "wof:placetype":"venue"
},
  "geometry": {"coordinates":[152.81045499999999,-28.258858],"type":"Point"}
}