{
  "type": "Feature",
  "properties": {
    "iso:country":"AU",
    "sg:address":"69 Burwood Drv",
    "sg:city":"Blackmans Bay",
    "sg:classifiers":[
        {
            "category":"Building & Trades",
            "subcategory":"Construction",
            "type":"Services"
        }
    ],
    "sg:phone":"+61 3 6229 2707",
    "sg:postcode":"7052",
    "sg:province":"TAS",
    "sg:tags":[
        "joiner",
        "carpenter"
    ],
    "wof:name":"Craftsmanship Joinery",
    "wof:placetype":"venue"
},
  "geometry": {"coordinates":[147.310532,-42.99995],"type":"Point"}
}