{
  "type": "Feature",
  "properties": {
    "addr:full":"105 Hawthorn Rd Morayfield QLD 4506",
    "addr:housenumber":"105",
    "addr:postcode":"4506",
    "addr:street":"Hawthorn Rd",
    "iso:country":"AU",
    "sg:address":"105 Hawthorn Rd",
    "sg:city":"Morayfield",
    "sg:classifiers":[
        {
            "category":"Industrial Area",
            "type":"Public Place"
        }
    ],
    "sg:phone":"+61 7 3886 8541",
    "sg:postcode":"4506",
    "sg:province":"QLD",
    "sg:tags":[
        "protective",
        "clothing"
    ],
    "wof:name":"Chillin Out Apparel",
    "wof:placetype":"venue"
},
  "geometry": {"coordinates":[152.92704773,-27.1648731232],"type":"Point"}
}