{
  "type": "Feature",
  "properties": {
    "addr:full":"Suite 2, 60 Cecil Ave Castle Hill NSW 2154",
    "addr:housenumber":"60",
    "addr:postcode":"2154",
    "addr:street":"Cecil Ave",
    "iso:country":"AU",
    "sg:address":"Suite 2, 60 Cecil Ave",
    "sg:city":"Castle Hill",
    "sg:classifiers":[
        {
            "category":"Health Services",
            "subcategory":"Doctor",
            "type":"Services"
        }
    ],
    "sg:phone":"+61 2 9634 6364",
    "sg:postcode":"2154",
    "sg:province":"NSW",
    "sg:tags":[
        "medical",
        "practitioner"
    ],
    "wof:name":"Byrne John Dr",
    "wof:placetype":"venue"
},
  "geometry": {"coordinates":[151.001953125,-33.7340660095],"type":"Point"}
}