{
  "type": "Feature",
  "properties": {
    "iso:country":"AU",
    "sg:address":"72 Nelson Rd",
    "sg:city":"Queenscliff",
    "sg:classifiers":[
        {
            "category":"Building & Trades",
            "subcategory":"Cleaning & Sanitation",
            "type":"Services"
        }
    ],
    "sg:phone":"+61 3 5258 3403",
    "sg:postcode":"3225",
    "sg:province":"VIC",
    "sg:tags":[
        "chemical",
        "pressure",
        "steam",
        "contractor"
    ],
    "wof:name":"AA Keith G Davidson Graffiti Removalists",
    "wof:placetype":"venue"
},
  "geometry": {"coordinates":[144.623947,-38.267387],"type":"Point"}
}