{
  "type": "Feature",
  "properties": {
    "addr:full":"Old Blair Athol Rd Clermont QLD 4721",
    "addr:postcode":"4721",
    "addr:street":"Blair Athol Rd",
    "iso:country":"AU",
    "sg:address":"Old Blair Athol Rd",
    "sg:city":"Clermont",
    "sg:classifiers":[
        {
            "category":"Utilities",
            "subcategory":"Fuel Oil & Lpg",
            "type":"Services"
        }
    ],
    "sg:phone":"+61 7 4983 2979",
    "sg:postcode":"4721",
    "sg:province":"QLD",
    "sg:tags":[
        "merchant"
    ],
    "wof:name":"Clermont Haulage",
    "wof:placetype":"venue"
},
  "geometry": {"coordinates":[147.64076232900001,-22.8019790649],"type":"Point"}
}