{
  "type": "Feature",
  "properties": {
    "addr:full":"Cnr March & East Market Sts Richmond NSW 2753",
    "addr:postcode":"2753",
    "addr:street":"Cnr;Sts",
    "iso:country":"AU",
    "sg:address":"Cnr March & East Market Sts",
    "sg:city":"Richmond",
    "sg:classifiers":[
        {
            "category":"Autos & Motor Vehicles",
            "subcategory":"Fuel & Gas Station",
            "type":"Retail Goods"
        }
    ],
    "sg:phone":"+61 2 4588 5827",
    "sg:postcode":"2753",
    "sg:province":"NSW",
    "wof:name":"Ampol",
    "wof:placetype":"venue"
},
  "geometry": {"coordinates":[150.752410889,-33.5984725952],"type":"Point"}
}