{
  "type": "Feature",
  "properties": {
    "iso:country":"AU",
    "sg:address":"Shp 2/ 76 Princes Hwy",
    "sg:city":"Fairy Meadow",
    "sg:classifiers":[
        {
            "category":"Cafe",
            "type":"Food & Drink"
        }
    ],
    "sg:phone":"+61 2 4284 9006",
    "sg:postcode":"2519",
    "sg:province":"NSW",
    "wof:name":"Jam Shop Cafe The",
    "wof:placetype":"venue"
},
  "geometry": {"coordinates":[150.893433,-34.391933],"type":"Point"}
}