{
  "type": "Feature",
  "properties": {
    "addr:full":"Suite 3 1 Rooks Rd Nunawading VIC 3131",
    "addr:housenumber":"1",
    "addr:postcode":"3131",
    "addr:street":"Rooks Rd",
    "iso:country":"AU",
    "sg:address":"Suite 3 1 Rooks Rd",
    "sg:city":"Nunawading",
    "sg:classifiers":[
        {
            "category":"Social Services",
            "subcategory":"Retirement Home",
            "type":"Services"
        }
    ],
    "sg:phone":"+61 3 8873 2600",
    "sg:postcode":"3131",
    "sg:province":"VIC",
    "sg:tags":[
        "environmental",
        "consultant",
        "pollution"
    ],
    "wof:name":"Water & Energy Savers (Vic) Pty Ltd",
    "wof:placetype":"venue"
},
  "geometry": {"coordinates":[145.18559265100001,-37.8182106018],"type":"Point"}
}