{
  "type": "Feature",
  "properties": {
    "iso:country":"AU",
    "sg:address":"PO Box 442",
    "sg:city":"Kingsgrove",
    "sg:classifiers":[
        {
            "category":"Retail",
            "subcategory":"Storage",
            "type":"Services"
        }
    ],
    "sg:phone":"+61 2 9502 4965",
    "sg:postcode":"2208",
    "sg:province":"NSW",
    "sg:tags":[
        "removal",
        "furniture"
    ],
    "wof:name":"A Ace Mick's Cheapest Removals",
    "wof:placetype":"venue"
},
  "geometry": {"coordinates":[151.098938,-33.93948],"type":"Point"}
}