{
  "type": "Feature",
  "properties": {
    "addr:full":"101 Cobalt St Carole Park QLD 4300",
    "addr:housenumber":"101",
    "addr:postcode":"4300",
    "addr:street":"Cobalt St",
    "iso:country":"AU",
    "sg:address":"101 Cobalt St",
    "sg:city":"Carole Park",
    "sg:classifiers":[
        {
            "category":"Manufacturing",
            "subcategory":"Metals",
            "type":"Manufacturing & Wholesale Goods"
        }
    ],
    "sg:phone":"+61 7 3712 3400",
    "sg:postcode":"4300",
    "sg:province":"QLD",
    "sg:tags":[
        "steel",
        "fabricator",
        "mfrs"
    ],
    "wof:name":"HVAC Queensland Pty Ltd",
    "wof:placetype":"venue"
},
  "geometry": {"coordinates":[152.93727111800001,-27.623872757],"type":"Point"}
}