{
  "type": "Feature",
  "properties": {
    "addr:full":"66 Halifax St Adelaide SA 5000",
    "addr:housenumber":"66",
    "addr:postcode":"5000",
    "addr:street":"Halifax St",
    "iso:country":"AU",
    "sg:address":"66 Halifax St",
    "sg:city":"Adelaide",
    "sg:classifiers":[
        {
            "category":"Real Estate",
            "subcategory":"Real Estate Services",
            "type":"Services"
        }
    ],
    "sg:phone":"+61 8 8211 8833",
    "sg:postcode":"5000",
    "sg:province":"SA",
    "sg:tags":[
        "valuer"
    ],
    "wof:name":"WBP Property Valuers",
    "wof:placetype":"venue"
},
  "geometry": {"coordinates":[138.60273742699999,-34.9325675964],"type":"Point"}
}