{
  "type": "Feature",
  "properties": {
    "addr:full":"Suite 13 4 Browne St Campbelltown NSW 2560",
    "addr:housenumber":"4",
    "addr:postcode":"2560",
    "addr:street":"Browne St",
    "iso:country":"AU",
    "sg:address":"Suite 13 4 Browne St",
    "sg:city":"Campbelltown",
    "sg:classifiers":[
        {
            "category":"Health Services",
            "subcategory":"Doctor",
            "type":"Services"
        }
    ],
    "sg:phone":"+61 2 4620 6934",
    "sg:postcode":"2560",
    "sg:province":"NSW",
    "sg:tags":[
        "medical",
        "practitioner"
    ],
    "wof:name":"Fulham Stephen B",
    "wof:placetype":"venue"
},
  "geometry": {"coordinates":[150.816574097,-34.064781189],"type":"Point"}
}