{
  "type": "Feature",
  "properties": {
    "iso:country":"AU",
    "sg:address":"256 Whitehorse Rd",
    "sg:city":"Nunawading",
    "sg:classifiers":[
        {
            "category":"Manufacturing",
            "subcategory":"Building Materials",
            "type":"Manufacturing & Wholesale Goods"
        }
    ],
    "sg:phone":"+61 3 9894 0222",
    "sg:postcode":"3131",
    "sg:province":"VIC",
    "sg:tags":[
        "stone",
        "product",
        "supply"
    ],
    "sg:website":"http://www.australianslateandstone.com.au",
    "wof:name":"Australian Slate & Stone Co Pty Ltd",
    "wof:placetype":"venue"
},
  "geometry": {"coordinates":[145.167892456,-37.8184204102],"type":"Point"}
}