{
  "type": "Feature",
  "properties": {
    "addr:full":"9 Hill Crt Thornlie WA 6108",
    "addr:housenumber":"9",
    "addr:postcode":"6108",
    "addr:street":"Hill Crt",
    "iso:country":"AU",
    "sg:address":"9 Hill Crt",
    "sg:city":"Thornlie",
    "sg:classifiers":[
        {
            "category":"Banks & Credit Unions",
            "subcategory":"Financial Services",
            "type":"Services"
        }
    ],
    "sg:phone":"+61 8 9493 1200",
    "sg:postcode":"6108",
    "sg:province":"WA",
    "sg:tags":[
        "settlement",
        "nt",
        "agent",
        "wa"
    ],
    "wof:name":"Foreman Kate",
    "wof:placetype":"venue"
},
  "geometry": {"coordinates":[115.955993652,-32.0737190247],"type":"Point"}
}