{
  "type": "Feature",
  "properties": {
    "addr:full":"380 Springvale Rd Forest Hill VIC 3131",
    "addr:housenumber":"380",
    "addr:postcode":"3131",
    "addr:street":"Springvale Rd",
    "iso:country":"AU",
    "sg:address":"380 Springvale Rd",
    "sg:city":"Forest Hill",
    "sg:classifiers":[
        {
            "category":"Health Services",
            "subcategory":"Health Practitioner",
            "type":"Services"
        }
    ],
    "sg:phone":"+61 3 9877 5700",
    "sg:postcode":"3131",
    "sg:province":"VIC",
    "sg:tags":[
        "naturopath"
    ],
    "wof:name":"Nina Tepass",
    "wof:placetype":"venue"
},
  "geometry": {"coordinates":[145.171432495,-37.8385658264],"type":"Point"}
}