{
  "type": "Feature",
  "properties": {
    "addr:full":"60 Hawthorn Rd Burwood East VIC 3151",
    "addr:housenumber":"60",
    "addr:postcode":"3151",
    "addr:street":"Hawthorn Rd",
    "iso:country":"AU",
    "sg:address":"60 Hawthorn Rd",
    "sg:city":"Burwood East",
    "sg:classifiers":[
        {
            "category":"Communications",
            "type":"Services"
        }
    ],
    "sg:phone":"+61 3 9802 5773",
    "sg:postcode":"3151",
    "sg:province":"VIC",
    "sg:tags":[
        "translation"
    ],
    "wof:name":"Speed Chinese Communications",
    "wof:placetype":"venue"
},
  "geometry": {"coordinates":[145.160324097,-37.8462982178],"type":"Point"}
}