{
  "type": "Feature",
  "properties": {
    "addr:full":"7 Mitchell St Mt Gambier SA 5290",
    "addr:housenumber":"7",
    "addr:postcode":"5290",
    "addr:street":"Mitchell St",
    "iso:country":"AU",
    "sg:address":"7 Mitchell St",
    "sg:city":"Mt Gambier",
    "sg:classifiers":[
        {
            "category":"Professional",
            "subcategory":"Secretarial Services",
            "type":"Services"
        }
    ],
    "sg:phone":"+61 8 8725 0888",
    "sg:postcode":"5290",
    "sg:province":"SA",
    "sg:tags":[
        "typing"
    ],
    "wof:name":"Hansen Print",
    "wof:placetype":"venue"
},
  "geometry": {"coordinates":[140.78349299999999,-37.827808],"type":"Point"}
}