{
  "type": "Feature",
  "properties": {
    "addr:full":"Shop 414 Victoria Ave Chatswood NSW 2067",
    "addr:housenumber":"414",
    "addr:postcode":"2067",
    "addr:street":"Victoria Ave",
    "iso:country":"AU",
    "sg:address":"Shop 414 Victoria Ave",
    "sg:city":"Chatswood",
    "sg:classifiers":[
        {
            "category":"Shopping",
            "subcategory":"Clothing, Apparel, & Fashions",
            "type":"Retail Goods"
        }
    ],
    "sg:phone":"+61 2 9419 6491",
    "sg:postcode":"2067",
    "sg:province":"NSW",
    "sg:tags":[
        "lady",
        "wear"
    ],
    "wof:name":"Sussan",
    "wof:placetype":"venue"
},
  "geometry": {"coordinates":[151.18208313,-33.7966651917],"type":"Point"}
}