{
  "type": "Feature",
  "properties": {
    "addr:full":"1809- 1811 Ferntree Gully Rd Ferntree Gully VIC 3156",
    "addr:housenumber":"1809 1811",
    "addr:postcode":"3156",
    "addr:street":"Ferntree Gully Rd",
    "iso:country":"AU",
    "sg:address":"1809- 1811 Ferntree Gully Rd",
    "sg:city":"Ferntree Gully",
    "sg:classifiers":[
        {
            "category":"Autos & Motor Vehicles",
            "subcategory":"Auto Supplies",
            "type":"Retail Goods"
        }
    ],
    "sg:phone":"+61 3 9753 5511",
    "sg:postcode":"3156",
    "sg:province":"VIC",
    "sg:tags":[
        "camper-trailers",
        "caravan",
        "equipment"
    ],
    "wof:name":"Australian R.V. Accessories",
    "wof:placetype":"venue"
},
  "geometry": {"coordinates":[145.268676758,-37.8844718933],"type":"Point"}
}