{
  "type": "Feature",
  "properties": {
    "iso:country":"AU",
    "sg:address":"5 Fisher St",
    "sg:city":"Gladstone",
    "sg:classifiers":[
        {
            "category":"Professional",
            "subcategory":"Computer Services",
            "type":"Services"
        }
    ],
    "sg:phone":"+61 427 338 976",
    "sg:postcode":"4680",
    "sg:province":"QLD",
    "sg:tags":[
        "package",
        "software"
    ],
    "wof:name":"The Harrison Company",
    "wof:placetype":"venue"
},
  "geometry": {"coordinates":[151.25694274899999,-23.850736618],"type":"Point"}
}