{
  "type": "Feature",
  "properties": {
    "addr:full":"48 Woods St Darwin NT 0800",
    "addr:housenumber":"48",
    "addr:postcode":"nt 0800",
    "addr:street":"Woods St",
    "iso:country":"AU",
    "sg:address":"48 Woods St",
    "sg:city":"Darwin",
    "sg:classifiers":[
        {
            "category":"Health Services",
            "subcategory":"Health Practitioner",
            "type":"Services"
        }
    ],
    "sg:phone":"+61 8 8981 5124",
    "sg:postcode":"0800",
    "sg:province":"NT",
    "sg:tags":[
        "physiotherapist"
    ],
    "wof:name":"Elphick Elizabeth",
    "wof:placetype":"venue"
},
  "geometry": {"coordinates":[130.84295654300001,-12.4601202011],"type":"Point"}
}