{
  "type": "Feature",
  "properties": {
    "iso:country":"AU",
    "sg:address":"PO Box 20",
    "sg:city":"Koondrook",
    "sg:classifiers":[
        {
            "category":"Manufacturing",
            "subcategory":"Lumber",
            "type":"Manufacturing & Wholesale Goods"
        }
    ],
    "sg:phone":"+61 3 5453 2401",
    "sg:postcode":"3580",
    "sg:province":"VIC",
    "sg:tags":[
        "sawmillers"
    ],
    "wof:name":"Arbuthnot Sawmills Pty Ltd",
    "wof:placetype":"venue"
},
  "geometry": {"coordinates":[144.13209533700001,-35.6436882019],"type":"Point"}
}