{
  "type": "Feature",
  "properties": {
    "addr:full":"8 Edmonstone St Newmarket QLD 4051",
    "addr:housenumber":"8",
    "addr:postcode":"4051",
    "addr:street":"Edmonstone St",
    "iso:country":"AU",
    "sg:address":"8 Edmonstone St",
    "sg:city":"Newmarket",
    "sg:classifiers":[
        {
            "category":"Professional",
            "subcategory":"Printing & Photocopies",
            "type":"Services"
        }
    ],
    "sg:phone":"+61 7 3552 7099",
    "sg:postcode":"4051",
    "sg:province":"QLD",
    "sg:tags":[
        "photocopier"
    ],
    "wof:name":"Tech Services Australia",
    "wof:placetype":"venue"
},
  "geometry": {"coordinates":[153.00804138199999,-27.4379367828],"type":"Point"}
}