{
  "type": "Feature",
  "properties": {
    "addr:full":"49 Walker St Turrella NSW 2205",
    "addr:housenumber":"49",
    "addr:postcode":"2205",
    "addr:street":"Walker St",
    "iso:country":"AU",
    "sg:address":"49 Walker St",
    "sg:city":"Turrella",
    "sg:classifiers":[
        {
            "category":"Social Services",
            "subcategory":"Child Care",
            "type":"Services"
        }
    ],
    "sg:phone":"+61 2 9599 1760",
    "sg:postcode":"2205",
    "sg:province":"NSW",
    "wof:name":"Turrella Children's Centre",
    "wof:placetype":"venue"
},
  "geometry": {"coordinates":[151.148056,-33.929352],"type":"Point"}
}