{
  "type": "Feature",
  "properties": {
    "addr:full":"7 Terrigal St Morisset NSW 2264",
    "addr:housenumber":"7",
    "addr:postcode":"2264",
    "addr:street":"Terrigal St",
    "iso:country":"AU",
    "sg:address":"7 Terrigal St",
    "sg:city":"Morisset",
    "sg:classifiers":[
        {
            "category":"Retail",
            "subcategory":"Funeral Services",
            "type":"Services"
        }
    ],
    "sg:phone":"+61 2 4973 1513",
    "sg:postcode":"2264",
    "sg:province":"NSW",
    "sg:tags":[
        "director"
    ],
    "wof:name":"Barbara King Funeral Director Pty Ltd",
    "wof:placetype":"venue"
},
  "geometry": {"coordinates":[151.488159,-33.103725],"type":"Point"}
}