{
  "type": "Feature",
  "properties": {
    "addr:full":"19 John St Salisbury SA 5108",
    "addr:housenumber":"19",
    "addr:postcode":"5108",
    "addr:street":"John St",
    "iso:country":"AU",
    "sg:address":"19 John St",
    "sg:city":"Salisbury",
    "sg:classifiers":[
        {
            "category":"Personal",
            "subcategory":"Beauty Salon",
            "type":"Services"
        }
    ],
    "sg:phone":"+61 8 8281 4642",
    "sg:postcode":"5108",
    "sg:province":"SA",
    "sg:tags":[
        "hairdresser"
    ],
    "wof:name":"Three Nations Mens Hairdresser",
    "wof:placetype":"venue"
},
  "geometry": {"coordinates":[138.643920898,-34.7629051208],"type":"Point"}
}