{
  "type": "Feature",
  "properties": {
    "addr:full":"510 Olive St Albury NSW 2640",
    "addr:housenumber":"510",
    "addr:postcode":"2640",
    "addr:street":"Olive St",
    "iso:country":"AU",
    "sg:address":"510 Olive St",
    "sg:city":"Albury",
    "sg:classifiers":[
        {
            "category":"Personal",
            "type":"Services"
        }
    ],
    "sg:phone":"+61 2 6021 3103",
    "sg:postcode":"2640",
    "sg:province":"NSW",
    "sg:tags":[
        "gift"
    ],
    "wof:name":"Vines Florist",
    "wof:placetype":"venue"
},
  "geometry": {"coordinates":[146.918624878,-36.0793495178],"type":"Point"}
}