{
  "type": "Feature",
  "properties": {
    "iso:country":"AU",
    "sg:address":"8 Groves Rd",
    "sg:city":"Gympie DC",
    "sg:classifiers":[
        {
            "category":"Building & Trades",
            "subcategory":"Construction",
            "type":"Services"
        }
    ],
    "sg:phone":"+61 7 5482 4820",
    "sg:postcode":"4570",
    "sg:province":"QLD",
    "sg:tags":[
        "renovation",
        "alterations",
        "extension",
        "contractor"
    ],
    "wof:name":"Peter Waldock Builder",
    "wof:placetype":"venue"
},
  "geometry": {"coordinates":[152.66784668,-26.1726722717],"type":"Point"}
}