{
  "type": "Feature",
  "properties": {
    "addr:full":"146-148 Johnston St Collingwood VIC 3066",
    "addr:housenumber":"146-148",
    "addr:postcode":"3066",
    "addr:street":"Johnston St",
    "iso:country":"AU",
    "sg:address":"146-148 Johnston St",
    "sg:city":"Collingwood",
    "sg:classifiers":[
        {
            "category":"Professional",
            "subcategory":"Art Services",
            "type":"Services"
        }
    ],
    "sg:phone":"+61 3 9416 4744",
    "sg:postcode":"3066",
    "sg:province":"VIC",
    "sg:tags":[
        "sculptor"
    ],
    "wof:name":"Coates & Wood",
    "wof:placetype":"venue"
},
  "geometry": {"coordinates":[144.989868164,-37.7993927002],"type":"Point"}
}