{
  "type": "Feature",
  "properties": {
    "addr:full":"1 King Albert Ave Leitchville VIC 3567",
    "addr:housenumber":"1",
    "addr:postcode":"3567",
    "addr:street":"King Albert Ave",
    "iso:country":"AU",
    "sg:address":"1 King Albert Ave",
    "sg:city":"Leitchville",
    "sg:classifiers":[
        {
            "category":"Shopping",
            "subcategory":"Stationery & Office Supplies",
            "type":"Retail Goods"
        }
    ],
    "sg:phone":"+61 3 5456 7444",
    "sg:postcode":"3567",
    "sg:province":"VIC",
    "sg:tags":[
        "equipment",
        "dairy"
    ],
    "wof:name":"Dairyquip Services",
    "wof:placetype":"venue"
},
  "geometry": {"coordinates":[144.30108642600001,-35.9039001465],"type":"Point"}
}