{
  "type": "Feature",
  "properties": {
    "addr:full":"60 Grant St Bairnsdale VIC 3875",
    "addr:housenumber":"60",
    "addr:postcode":"3875",
    "addr:street":"Grant St",
    "iso:country":"AU",
    "sg:address":"60 Grant St",
    "sg:city":"Bairnsdale",
    "sg:classifiers":[
        {
            "category":"Health Services",
            "subcategory":"Dentist",
            "type":"Services"
        }
    ],
    "sg:phone":"+61 3 5152 2398",
    "sg:postcode":"3875",
    "sg:province":"VIC",
    "sg:tags":[
        "dental",
        "prosthetist"
    ],
    "wof:name":"Fietz John",
    "wof:placetype":"venue"
},
  "geometry": {"coordinates":[147.62223815900001,-37.8284225464],"type":"Point"}
}