{
  "type": "Feature",
  "properties": {
    "iso:country":"AU",
    "sg:address":"12/ 5 Prosperity Pde",
    "sg:city":"Warriewood",
    "sg:classifiers":[
        {
            "category":"Home & Garden",
            "subcategory":"Building Materials",
            "type":"Retail Goods"
        }
    ],
    "sg:phone":"+61 2 9979 1544",
    "sg:postcode":"2102",
    "sg:province":"NSW",
    "sg:tags":[
        "merchant",
        "glass",
        "glazier"
    ],
    "wof:name":"Regal Glass",
    "wof:placetype":"venue"
},
  "geometry": {"coordinates":[151.290619,-33.681335],"type":"Point"}
}