{
  "type": "Feature",
  "properties": {
    "addr:full":"120 Campbell St Hobart TAS 7000",
    "addr:housenumber":"120",
    "addr:postcode":"7000",
    "addr:street":"Campbell St",
    "iso:country":"AU",
    "sg:address":"120 Campbell St",
    "sg:city":"Hobart",
    "sg:classifiers":[
        {
            "category":"Autos & Motor Vehicles",
            "subcategory":"Automobile Sales",
            "type":"Retail Goods"
        }
    ],
    "sg:phone":"+61 3 6238 0288",
    "sg:postcode":"7000",
    "sg:province":"TAS",
    "sg:tags":[
        "bus",
        "truck",
        "new"
    ],
    "wof:name":"Iveco Trucks",
    "wof:placetype":"venue"
},
  "geometry": {"coordinates":[147.32594299300001,-42.8763923645],"type":"Point"}
}