{
  "type": "Feature",
  "properties": {
    "addr:full":"41 Mountain View Rd Maleny QLD 4552",
    "addr:housenumber":"41",
    "addr:postcode":"4552",
    "addr:street":"Mountain View Rd",
    "iso:country":"AU",
    "sg:address":"41 Mountain View Rd",
    "sg:city":"Maleny",
    "sg:classifiers":[
        {
            "category":"Communications",
            "subcategory":"News Services",
            "type":"Services"
        }
    ],
    "sg:phone":"+61 7 5499 9907",
    "sg:postcode":"4552",
    "sg:province":"QLD",
    "sg:tags":[
        "information",
        "tourist",
        "attractions"
    ],
    "wof:name":"Mary Cairncross Scenic Reserve Thynne Natural History Education Centre",
    "wof:placetype":"venue"
},
  "geometry": {"coordinates":[152.87425231899999,-26.7812671661],"type":"Point"}
}