{
  "type": "Feature",
  "properties": {
    "iso:country":"AU",
    "sg:address":"481 Flinders St",
    "sg:city":"Townsville",
    "sg:classifiers":[
        {
            "category":"Industrial Area",
            "type":"Public Place"
        }
    ],
    "sg:phone":"+61 7 4771 2292",
    "sg:postcode":"4810",
    "sg:province":"QLD",
    "sg:tags":[
        "protective",
        "clothing"
    ],
    "wof:name":"Town & Country Equestrian & Camping Gear",
    "wof:placetype":"venue"
},
  "geometry": {"coordinates":[146.80943300000001,-19.266857],"type":"Point"}
}