{
  "type": "Feature",
  "properties": {
    "addr:full":"112 Fryers St Shepparton VIC 3630",
    "addr:housenumber":"112",
    "addr:postcode":"3630",
    "addr:street":"Fryers St",
    "iso:country":"AU",
    "sg:address":"112 Fryers St",
    "sg:city":"Shepparton",
    "sg:classifiers":[
        {
            "category":"Personal",
            "subcategory":"Beauty Salon",
            "type":"Services"
        }
    ],
    "sg:phone":"+61 3 5821 3606",
    "sg:postcode":"3630",
    "sg:province":"VIC",
    "sg:tags":[
        "hairdresser"
    ],
    "wof:name":"Mez's Hair & Beauty",
    "wof:placetype":"venue"
},
  "geometry": {"coordinates":[145.40264892600001,-36.3795928955],"type":"Point"}
}