{
  "type": "Feature",
  "properties": {
    "iso:country":"AU",
    "sg:address":"Shop 4/ 26 Princess St",
    "sg:city":"Kew",
    "sg:classifiers":[
        {
            "category":"Cafe",
            "type":"Food & Drink"
        }
    ],
    "sg:phone":"+61 3 9852 8134",
    "sg:postcode":"3101",
    "sg:province":"VIC",
    "wof:name":"Car Park Cafe Kew (CPC)",
    "wof:placetype":"venue"
},
  "geometry": {"coordinates":[145.02911376899999,-37.8061943054],"type":"Point"}
}