{
  "type": "Feature",
  "properties": {
    "addr:full":"15A Stanton Rd Seven Hills NSW 2147",
    "addr:housenumber":"15a",
    "addr:postcode":"2147",
    "addr:street":"Stanton Rd",
    "iso:country":"AU",
    "sg:address":"15A Stanton Rd",
    "sg:city":"Seven Hills",
    "sg:classifiers":[
        {
            "category":"Professional",
            "type":"Services"
        }
    ],
    "sg:phone":"+61 2 9624 7766",
    "sg:postcode":"2147",
    "sg:province":"NSW",
    "sg:tags":[
        "transport"
    ],
    "wof:name":"Baulkham Hills Removals & Storage",
    "wof:placetype":"venue"
},
  "geometry": {"coordinates":[150.952072144,-33.7703552246],"type":"Point"}
}