{
  "type": "Feature",
  "properties": {
    "iso:country":"AU",
    "sg:address":"3481 Pacific Hwy",
    "sg:city":"Springwood",
    "sg:classifiers":[
        {
            "category":"Manufacturing",
            "subcategory":"Motor Vehicles & Parts",
            "type":"Manufacturing & Wholesale Goods"
        }
    ],
    "sg:phone":"+61 7 3290 7888",
    "sg:postcode":"4127",
    "sg:province":"QLD",
    "sg:tags":[
        "replacement"
    ],
    "wof:name":"Nissan Highway",
    "wof:placetype":"venue"
},
  "geometry": {"coordinates":[153.12971496599999,-27.6325721741],"type":"Point"}
}