{
  "type": "Feature",
  "properties": {
    "addr:full":"63 Commissioner St Cooma NSW 2630",
    "addr:housenumber":"63",
    "addr:postcode":"2630",
    "addr:street":"Commissioner St",
    "iso:country":"AU",
    "sg:address":"63 Commissioner St",
    "sg:city":"Cooma",
    "sg:classifiers":[
        {
            "category":"Retail",
            "subcategory":"Auto Repair",
            "type":"Services"
        }
    ],
    "sg:phone":"+61 2 6452 4776",
    "sg:postcode":"2630",
    "sg:province":"NSW",
    "sg:tags":[
        "repairer",
        "motor",
        "engineer"
    ],
    "wof:name":"Total Automotives",
    "wof:placetype":"venue"
},
  "geometry": {"coordinates":[149.12823486299999,-36.2351226807],"type":"Point"}
}