{
  "type": "Feature",
  "properties": {
    "iso:country":"AU",
    "sg:address":"18 Main St",
    "sg:city":"Lobethal",
    "sg:classifiers":[
        {
            "category":"Food & Beverages",
            "subcategory":"Supermarket",
            "type":"Retail Goods"
        }
    ],
    "sg:phone":"+61 8 8389 6280",
    "sg:postcode":"5241",
    "sg:province":"SA",
    "sg:tags":[
        "grocery",
        "store"
    ],
    "wof:name":"Lobethal Foodland",
    "wof:placetype":"venue"
},
  "geometry": {"coordinates":[138.873779297,-34.9075241089],"type":"Point"}
}