{
  "type": "Feature",
  "properties": {
    "addr:full":"Mooney Street Shopping Centre Shop 4, 78 Mooney St Gulliver QLD 4812",
    "addr:housenumber":"shop 4 78",
    "addr:postcode":"4812",
    "addr:street":"Mooney Street;Mooney St",
    "iso:country":"AU",
    "sg:address":"Mooney Street Shopping Centre Shop 4, 78 Mooney St",
    "sg:city":"Gulliver",
    "sg:classifiers":[
        {
            "category":"Manufacturing",
            "subcategory":"Food",
            "type":"Manufacturing & Wholesale Goods"
        }
    ],
    "sg:phone":"+61 7 4728 5455",
    "sg:postcode":"4812",
    "sg:province":"QLD",
    "sg:tags":[
        "function",
        "catering"
    ],
    "wof:name":"Tempting Delights",
    "wof:placetype":"venue"
},
  "geometry": {"coordinates":[146.77174400000001,-19.282518],"type":"Point"}
}