{
  "type": "Feature",
  "properties": {
    "addr:full":"52 Main St North Rockhampton QLD 4701",
    "addr:housenumber":"52",
    "addr:postcode":"4701",
    "addr:street":"Main St North",
    "iso:country":"AU",
    "sg:address":"52 Main St",
    "sg:city":"North Rockhampton",
    "sg:classifiers":[
        {
            "category":"Shopping",
            "subcategory":"Computers & Home Electronics",
            "type":"Retail Goods"
        }
    ],
    "sg:phone":"+61 7 4922 0201",
    "sg:postcode":"4701",
    "sg:province":"QLD",
    "sg:tags":[
        "hardware",
        "equipment"
    ],
    "wof:name":"Rocky Computer Market",
    "wof:placetype":"venue"
},
  "geometry": {"coordinates":[150.51139831500001,-23.3563079834],"type":"Point"}
}