{
  "type": "Feature",
  "properties": {
    "addr:full":"141 Haigslea/Amberley Rd Walloon QLD 4306",
    "addr:housenumber":"141;/ amberley",
    "addr:postcode":"4306",
    "addr:street":"Haigslea;Rd",
    "iso:country":"AU",
    "sg:address":"141 Haigslea/Amberley Rd",
    "sg:city":"Walloon",
    "sg:classifiers":[
        {
            "category":"Home & Garden",
            "subcategory":"Carpets & Floor Coverings",
            "type":"Retail Goods"
        }
    ],
    "sg:phone":"+61 7 5464 5558",
    "sg:postcode":"4306",
    "sg:province":"QLD",
    "sg:tags":[
        "tile",
        "wall",
        "layer"
    ],
    "wof:name":"S.J. Daniells Concreting & Paving",
    "wof:placetype":"venue"
},
  "geometry": {"coordinates":[152.66758727999999,-27.5902347565],"type":"Point"}
}