{
  "type": "Feature",
  "properties": {
    "addr:full":"23 Drevesen Ave Cleveland QLD 4163",
    "addr:housenumber":"23",
    "addr:postcode":"4163",
    "addr:street":"Drevesen Ave",
    "iso:country":"AU",
    "sg:address":"23 Drevesen Ave",
    "sg:city":"Cleveland",
    "sg:classifiers":[
        {
            "category":"Personal",
            "subcategory":"Nail Salon",
            "type":"Services"
        }
    ],
    "sg:phone":"+61 7 3821 6868",
    "sg:postcode":"4163",
    "sg:province":"QLD",
    "sg:tags":[
        "artificial"
    ],
    "wof:name":"Better Nail Care & Beauty",
    "wof:placetype":"venue"
},
  "geometry": {"coordinates":[153.26454162600001,-27.5459709167],"type":"Point"}
}