{
  "type": "Feature",
  "properties": {
    "iso:country":"AU",
    "sg:address":"Shop 1/ 345 Kelvin Grove Rd",
    "sg:city":"Kelvin Grove",
    "sg:classifiers":[
        {
            "category":"Home & Garden",
            "subcategory":"Kitchen Supply",
            "type":"Retail Goods"
        }
    ],
    "sg:phone":"+61 7 3356 9333",
    "sg:postcode":"4059",
    "sg:province":"QLD",
    "sg:tags":[
        "equipment",
        "surveyor"
    ],
    "wof:name":"Nicad Battery Service",
    "wof:placetype":"venue"
},
  "geometry": {"coordinates":[153.01046752900001,-27.4485740662],"type":"Point"}
}