{
  "type": "Feature",
  "properties": {
    "addr:full":"Level 1, 70 Hampden Rd Artarmon NSW 2064",
    "addr:housenumber":"70",
    "addr:postcode":"2064",
    "addr:street":"Hampden Rd",
    "iso:country":"AU",
    "sg:address":"Level 1, 70 Hampden Rd",
    "sg:city":"Artarmon",
    "sg:classifiers":[
        {
            "category":"Manufacturing",
            "subcategory":"Paper Products",
            "type":"Manufacturing & Wholesale Goods"
        }
    ],
    "sg:phone":"+61 2 9419 7100",
    "sg:postcode":"2064",
    "sg:province":"NSW",
    "sg:tags":[
        "container",
        "plastic"
    ],
    "wof:name":"Pacific-Aus. Corp",
    "wof:placetype":"venue"
},
  "geometry": {"coordinates":[151.185012817,-33.8092384338],"type":"Point"}
}