{
  "type": "Feature",
  "properties": {
    "iso:country":"AU",
    "sg:address":"31 Cuthberts Rd",
    "sg:city":"Alfredton",
    "sg:classifiers":[
        {
            "category":"Health Services",
            "subcategory":"Health Practitioner",
            "type":"Services"
        }
    ],
    "sg:phone":"+61 3 5334 2288",
    "sg:postcode":"3350",
    "sg:province":"VIC",
    "sg:tags":[
        "reiki"
    ],
    "wof:name":"Healing Hands",
    "wof:placetype":"venue"
},
  "geometry": {"coordinates":[143.809113,-37.554909],"type":"Point"}
}