{
  "type": "Feature",
  "properties": {
    "iso:country":"AU",
    "sg:address":"57 West Fyans St",
    "sg:city":"Newtown",
    "sg:classifiers":[
        {
            "category":"Food & Beverages",
            "subcategory":"Specialty",
            "type":"Retail Goods"
        }
    ],
    "sg:phone":"+61 3 5221 5757",
    "sg:postcode":"3220",
    "sg:province":"VIC",
    "sg:tags":[
        "product",
        "health"
    ],
    "wof:name":"Van Etten Mark",
    "wof:placetype":"venue"
},
  "geometry": {"coordinates":[144.345505,-38.159721],"type":"Point"}
}