{
  "type": "Feature",
  "properties": {
    "addr:full":"11 Magill Rd Stepney SA 5069",
    "addr:housenumber":"11",
    "addr:postcode":"5069",
    "addr:street":"Magill Rd",
    "iso:country":"AU",
    "sg:address":"11 Magill Rd",
    "sg:city":"Stepney",
    "sg:classifiers":[
        {
            "category":"Shopping",
            "subcategory":"Stationery & Office Supplies",
            "type":"Retail Goods"
        }
    ],
    "sg:phone":"+61 1800 637 628",
    "sg:postcode":"5069",
    "sg:province":"SA",
    "sg:tags":[
        "equipment",
        "display",
        "exhibition"
    ],
    "wof:name":"Rainbow Display Systems Pty Ltd",
    "wof:placetype":"venue"
},
  "geometry": {"coordinates":[138.62402343799999,-34.9154663086],"type":"Point"}
}