{
  "type": "Feature",
  "properties": {
    "addr:full":"850 Sydney Rd Brunswick VIC 3056",
    "addr:housenumber":"850",
    "addr:postcode":"3056",
    "addr:street":"Sydney Rd",
    "iso:country":"AU",
    "sg:address":"850 Sydney Rd",
    "sg:city":"Brunswick",
    "sg:classifiers":[
        {
            "category":"Professional",
            "subcategory":"Art Services",
            "type":"Services"
        }
    ],
    "sg:phone":"+61 3 9383 6733",
    "sg:postcode":"3056",
    "sg:province":"VIC",
    "sg:tags":[
        "interior",
        "decorator"
    ],
    "wof:name":"Wonderwall Interiors",
    "wof:placetype":"venue"
},
  "geometry": {"coordinates":[144.96406555199999,-37.756729126],"type":"Point"}
}