{
  "type": "Feature",
  "properties": {
    "addr:full":"18 McCulloch St North Mackay QLD 4740",
    "addr:housenumber":"18",
    "addr:postcode":"4740",
    "addr:street":"Mcculloch St",
    "iso:country":"AU",
    "sg:address":"18 McCulloch St",
    "sg:city":"North Mackay",
    "sg:classifiers":[
        {
            "category":"Home & Garden",
            "subcategory":"Building Materials",
            "type":"Retail Goods"
        }
    ],
    "sg:phone":"+61 7 4957 7477",
    "sg:postcode":"4740",
    "sg:province":"QLD",
    "sg:tags":[
        "merchant",
        "glass",
        "glazier"
    ],
    "wof:name":"B & N Glass Repairs",
    "wof:placetype":"venue"
},
  "geometry": {"coordinates":[149.195618,-21.11891],"type":"Point"}
}