{
  "type": "Feature",
  "properties": {
    "iso:country":"AU",
    "sg:address":"Shop 10, 205- 209 Oxford St",
    "sg:city":"Bulimba",
    "sg:classifiers":[
        {
            "category":"Health Services",
            "subcategory":"Dentist",
            "type":"Services"
        }
    ],
    "sg:phone":"+61 7 3399 2388",
    "sg:postcode":"4171",
    "sg:province":"QLD",
    "wof:name":"Bulimba Dental Centre",
    "wof:placetype":"venue"
},
  "geometry": {"coordinates":[153.06149292000001,-27.4515190125],"type":"Point"}
}