{
  "type": "Feature",
  "properties": {
    "addr:full":"71 Meroo Rd Bomaderry NSW 2541",
    "addr:housenumber":"71",
    "addr:postcode":"2541",
    "addr:street":"Meroo Rd",
    "iso:country":"AU",
    "sg:address":"71 Meroo Rd",
    "sg:city":"Bomaderry",
    "sg:classifiers":[
        {
            "category":"Building & Trades",
            "subcategory":"Construction",
            "type":"Services"
        }
    ],
    "sg:phone":"+61 2 4423 5964",
    "sg:postcode":"2541",
    "sg:province":"NSW",
    "sg:tags":[
        "fencing",
        "contractor"
    ],
    "wof:name":"Unida Fencing & Gates",
    "wof:placetype":"venue"
},
  "geometry": {"coordinates":[150.61076355,-34.8413352966],"type":"Point"}
}