{
  "type": "Feature",
  "properties": {
    "addr:full":"1/ 15 Wickham Tce Gympie QLD 4570",
    "addr:housenumber":"/ 15",
    "addr:postcode":"4570",
    "addr:street":"Wickham Tce",
    "iso:country":"AU",
    "sg:address":"1/ 15",
    "sg:city":"Wickham Tce Gympie",
    "sg:classifiers":[
        {
            "category":"Professional",
            "subcategory":"Computer Services",
            "type":"Services"
        }
    ],
    "sg:phone":"+61 7 5483 7111",
    "sg:postcode":"4570",
    "sg:province":"QLD",
    "sg:tags":[
        "equipment",
        "networking",
        "installation"
    ],
    "wof:name":"DDK Technology",
    "wof:placetype":"venue"
},
  "geometry": {"coordinates":[152.657592773,-26.1915359497],"type":"Point"}
}