{
  "type": "Feature",
  "properties": {
    "iso:country":"AU",
    "sg:address":"1e Kerr Pde",
    "sg:city":"Auburn",
    "sg:classifiers":[
        {
            "category":"Personal",
            "subcategory":"Beauty Salon",
            "type":"Services"
        }
    ],
    "sg:phone":"+61 2 9643 1261",
    "sg:postcode":"2144",
    "sg:province":"NSW",
    "sg:tags":[
        "hairdresser"
    ],
    "wof:name":"Hair of Elegance",
    "wof:placetype":"venue"
},
  "geometry": {"coordinates":[151.03358459500001,-33.8505210876],"type":"Point"}
}