{
  "type": "Feature",
  "properties": {
    "addr:full":"65 Ocean St Woollahra NSW 2025",
    "addr:housenumber":"65",
    "addr:postcode":"2025",
    "addr:street":"Ocean St",
    "iso:country":"AU",
    "sg:address":"65 Ocean St",
    "sg:city":"Woollahra",
    "sg:classifiers":[
        {
            "category":"Retail",
            "subcategory":"Event Space",
            "type":"Services"
        }
    ],
    "sg:phone":"+61 2 9363 1974",
    "sg:postcode":"2025",
    "sg:province":"NSW",
    "sg:tags":[
        "venue",
        "reception",
        "wedding"
    ],
    "wof:name":"Pruniers Restaurant & Bar",
    "wof:placetype":"venue"
},
  "geometry": {"coordinates":[151.23953247099999,-33.8858413696],"type":"Point"}
}