{
  "type": "Feature",
  "properties": {
    "iso:country":"AU",
    "sg:address":"417 Oxford St",
    "sg:city":"Mt Hawthorn",
    "sg:classifiers":[
        {
            "category":"Professional",
            "subcategory":"Art Services",
            "type":"Services"
        }
    ],
    "sg:phone":"+61 8 9444 0115",
    "sg:postcode":"6016",
    "sg:province":"WA",
    "sg:tags":[
        "picture",
        "frame",
        "framing"
    ],
    "wof:name":"Oxford Gallery & Framing",
    "wof:placetype":"venue"
},
  "geometry": {"coordinates":[115.841072083,-31.9228744507],"type":"Point"}
}