{
  "type": "Feature",
  "properties": {
    "addr:full":"PO Box 11 Clarendon SA 5157",
    "addr:postcode":"5157",
    "iso:country":"AU",
    "sg:address":"PO Box 11",
    "sg:city":"Clarendon",
    "sg:classifiers":[
        {
            "category":"Building & Trades",
            "subcategory":"Landscaping Services",
            "type":"Services"
        }
    ],
    "sg:phone":"+61 419 845 648",
    "sg:postcode":"5157",
    "sg:province":"SA",
    "sg:tags":[
        "designer",
        "landscape",
        "contractor"
    ],
    "wof:name":"Bob The Bobcat Man",
    "wof:placetype":"venue"
},
  "geometry": {"coordinates":[138.63023376500001,-35.1099891663],"type":"Point"}
}