{
  "type": "Feature",
  "properties": {
    "addr:full":"14A 555 Churchill Rd Kilburn SA 5084",
    "addr:housenumber":"14a 555",
    "addr:postcode":"5084",
    "addr:street":"Churchill Rd",
    "iso:country":"AU",
    "sg:address":"14A 555 Churchill Rd",
    "sg:city":"Kilburn",
    "sg:classifiers":[
        {
            "category":"Autos & Motor Vehicles",
            "subcategory":"Automobile Sales",
            "type":"Retail Goods"
        }
    ],
    "sg:phone":"+61 8 8359 4444",
    "sg:postcode":"5084",
    "sg:province":"SA",
    "sg:tags":[
        "equipment",
        "trailer"
    ],
    "wof:name":"Wespac Handling Equipment",
    "wof:placetype":"venue"
},
  "geometry": {"coordinates":[138.58270263700001,-34.8510513306],"type":"Point"}
}