{
  "type": "Feature",
  "properties": {
    "iso:country":"AU",
    "sg:address":"Unit 27/ 72 Percival Rd",
    "sg:city":"Smithfield",
    "sg:classifiers":[
        {
            "category":"Retail",
            "subcategory":"Repair Shop",
            "type":"Services"
        }
    ],
    "sg:phone":"+61 2 9604 3021",
    "sg:postcode":"2164",
    "sg:province":"NSW",
    "sg:tags":[
        "machine",
        "repairs",
        "part",
        "dryer",
        "washing"
    ],
    "wof:name":"ABC",
    "wof:placetype":"venue"
},
  "geometry": {"coordinates":[150.95028686500001,-33.8412094116],"type":"Point"}
}