{
  "type": "Feature",
  "properties": {
    "iso:country":"AU",
    "sg:address":"27- 29 Wellington St",
    "sg:city":"Riverstone",
    "sg:classifiers":[
        {
            "category":"Professional",
            "subcategory":"Detective & Security Services",
            "type":"Services"
        }
    ],
    "sg:phone":"+61 2 9838 2500",
    "sg:postcode":"2765",
    "sg:province":"NSW",
    "sg:tags":[
        "consultant",
        "laser"
    ],
    "sg:website":"http://www.altank.com.au",
    "wof:name":"ASM Manufacturing",
    "wof:placetype":"venue"
},
  "geometry": {"coordinates":[150.85896301299999,-33.6670722961],"type":"Point"}
}