{
  "type": "Feature",
  "properties": {
    "iso:country":"AU",
    "sg:address":"5 Chiswell Crt",
    "sg:city":"Benalla",
    "sg:classifiers":[
        {
            "category":"Building & Trades",
            "subcategory":"Construction",
            "type":"Services"
        }
    ],
    "sg:phone":"+61 3 5762 6629",
    "sg:postcode":"3672",
    "sg:province":"VIC",
    "sg:tags":[
        "renovation",
        "alterations",
        "extension",
        "contractor"
    ],
    "wof:name":"Statewide House Reblocking",
    "wof:placetype":"venue"
},
  "geometry": {"coordinates":[145.983307,-36.541828],"type":"Point"}
}