{
  "type": "Feature",
  "properties": {
    "iso:country":"AU",
    "sg:address":"4 Forward St",
    "sg:city":"Manning",
    "sg:classifiers":[
        {
            "category":"Building & Trades",
            "subcategory":"Construction",
            "type":"Services"
        }
    ],
    "sg:phone":"+61 417 957 606",
    "sg:postcode":"6152",
    "sg:province":"WA",
    "sg:tags":[
        "joiner",
        "carpenter"
    ],
    "wof:name":"Creek's Quality Carpentry",
    "wof:placetype":"venue"
},
  "geometry": {"coordinates":[115.87056,-32.007771],"type":"Point"}
}