{
  "type": "Feature",
  "properties": {
    "addr:full":"Shop 2 /912 David Low Way Marcoola QLD 4564",
    "addr:housenumber":"shop 2 / 912",
    "addr:postcode":"4564",
    "addr:street":"David Low Way",
    "iso:country":"AU",
    "sg:address":"Shop 2",
    "sg:city":"/912 David Low Way Marcoola",
    "sg:classifiers":[
        {
            "category":"Shopping",
            "subcategory":"Clothing, Apparel, & Fashions",
            "type":"Retail Goods"
        }
    ],
    "sg:phone":"+61 7 5450 6922",
    "sg:postcode":"4564",
    "sg:province":"QLD",
    "sg:tags":[
        "lingerie",
        "hosiery",
        "sleepwear"
    ],
    "wof:name":"Tickled Pink The Adult Shop For Lovers",
    "wof:placetype":"venue"
},
  "geometry": {"coordinates":[153.095504761,-26.5990829468],"type":"Point"}
}