{
  "type": "Feature",
  "properties": {
    "addr:full":"434 Belgrave-Hallam Rd Narre Warren North VIC 3804",
    "addr:housenumber":"434",
    "addr:postcode":"3804",
    "addr:street":"Belgrave-Hallam Rd",
    "iso:country":"AU",
    "sg:address":"434 Belgrave-Hallam Rd",
    "sg:city":"Narre Warren North",
    "sg:classifiers":[
        {
            "category":"Communications",
            "subcategory":"News Services",
            "type":"Services"
        }
    ],
    "sg:phone":"+61 3 9796 8481",
    "sg:postcode":"3804",
    "sg:province":"VIC",
    "sg:tags":[
        "information",
        "tourist",
        "attractions"
    ],
    "wof:name":"Campbelltown Railways",
    "wof:placetype":"venue"
},
  "geometry": {"coordinates":[145.315643311,-37.9738578796],"type":"Point"}
}