{
  "type": "Feature",
  "properties": {
    "addr:full":"Unit 18 41- 49 Norcal Rd Nunawading VIC 3131",
    "addr:housenumber":"41 49",
    "addr:postcode":"3131",
    "addr:street":"Norcal Rd",
    "iso:country":"AU",
    "sg:address":"Unit 18 41- 49 Norcal Rd",
    "sg:city":"Nunawading",
    "sg:classifiers":[
        {
            "category":"Wholesale",
            "subcategory":"Construction Materials",
            "type":"Manufacturing & Wholesale Goods"
        }
    ],
    "sg:phone":"+61 3 9874 8288",
    "sg:postcode":"3131",
    "sg:province":"VIC",
    "sg:tags":[
        "wholesaler",
        "lighting",
        "mfrs",
        "accessory"
    ],
    "wof:name":"Technilux Pty Ltd",
    "wof:placetype":"venue"
},
  "geometry": {"coordinates":[145.18138122600001,-37.8227958679],"type":"Point"}
}