{
  "type": "Feature",
  "properties": {
    "iso:country":"AU",
    "sg:address":"Suite 11, Bellevue Terrace, 25 Mary St",
    "sg:city":"Brisbane",
    "sg:classifiers":[
        {
            "category":"Professional",
            "subcategory":"Accounting & Tax Preparation",
            "type":"Services"
        }
    ],
    "sg:phone":"+61 1300 762 247",
    "sg:postcode":"4000",
    "sg:province":"QLD",
    "sg:tags":[
        "accountant",
        "auditor"
    ],
    "wof:name":"Q5 Accounting",
    "wof:placetype":"venue"
},
  "geometry": {"coordinates":[153.02647399899999,-27.4728813171],"type":"Point"}
}