{
  "type": "Feature",
  "properties": {
    "iso:country":"AU",
    "sg:address":"38 Belmore St",
    "sg:city":"North Parramatta",
    "sg:classifiers":[
        {
            "category":"Real Estate",
            "subcategory":"Real Estate Agent",
            "type":"Services"
        }
    ],
    "sg:phone":"+61 2 9890 2989",
    "sg:postcode":"2151",
    "sg:province":"NSW",
    "wof:name":"Butler H R",
    "wof:placetype":"venue"
},
  "geometry": {"coordinates":[151.01307678200001,-33.800453186],"type":"Point"}
}