{
  "type": "Feature",
  "properties": {
    "iso:country":"AU",
    "sg:address":"117 Jasper Rd",
    "sg:city":"Bentleigh",
    "sg:classifiers":[
        {
            "category":"Social Services",
            "subcategory":"Adult Care",
            "type":"Services"
        }
    ],
    "sg:phone":"+61 3 9557 8322",
    "sg:postcode":"3204",
    "sg:province":"VIC",
    "sg:tags":[
        "aged"
    ],
    "wof:name":"Baptcare",
    "wof:placetype":"venue"
},
  "geometry": {"coordinates":[145.040512,-37.924099],"type":"Point"}
}