{
  "type": "Feature",
  "properties": {
    "iso:country":"AU",
    "sg:address":"7 Esplanade St",
    "sg:city":"Yeronga",
    "sg:classifiers":[
        {
            "category":"Personal",
            "subcategory":"Massage",
            "type":"Services"
        }
    ],
    "sg:phone":"+61 7 3255 9417",
    "sg:postcode":"4104",
    "sg:province":"QLD",
    "sg:tags":[
        "therapy"
    ],
    "wof:name":"Murray Neil",
    "wof:placetype":"venue"
},
  "geometry": {"coordinates":[153.00274658199999,-27.514837265],"type":"Point"}
}