{
  "type": "Feature",
  "properties": {
    "addr:full":"123 Lava St Warrnambool VIC 3280",
    "addr:housenumber":"123",
    "addr:postcode":"3280",
    "addr:street":"Lava St",
    "iso:country":"AU",
    "sg:address":"123 Lava St",
    "sg:city":"Warrnambool",
    "sg:classifiers":[
        {
            "category":"Cafe",
            "type":"Food & Drink"
        }
    ],
    "sg:phone":"+61 3 5561 0066",
    "sg:postcode":"3280",
    "sg:province":"VIC",
    "wof:name":"Clocktower Tearooms",
    "wof:placetype":"venue"
},
  "geometry": {"coordinates":[142.48463439899999,-38.381778717],"type":"Point"}
}