{
  "type": "Feature",
  "properties": {
    "addr:full":"228 Marys Bay Rd Euroka NSW 2440",
    "addr:housenumber":"228",
    "addr:postcode":"2440",
    "addr:street":"Marys Bay Rd",
    "iso:country":"AU",
    "sg:address":"228 Marys Bay Rd",
    "sg:city":"Euroka",
    "sg:classifiers":[
        {
            "category":"Farming",
            "subcategory":"Farm",
            "type":"Manufacturing & Wholesale Goods"
        }
    ],
    "sg:phone":"+61 2 6562 4437",
    "sg:postcode":"2440",
    "sg:province":"NSW",
    "sg:tags":[
        "farmer"
    ],
    "wof:name":"Welch R E & Y M Pty Ltd",
    "wof:placetype":"venue"
},
  "geometry": {"coordinates":[152.797821,-31.072729],"type":"Point"}
}