{
  "type": "Feature",
  "properties": {
    "addr:full":"14 Harold St Sandringham VIC 3191",
    "addr:housenumber":"14",
    "addr:postcode":"3191",
    "addr:street":"Harold St",
    "iso:country":"AU",
    "sg:address":"14 Harold St",
    "sg:city":"Sandringham",
    "sg:classifiers":[
        {
            "category":"Building & Trades",
            "subcategory":"Plumbing",
            "type":"Services"
        }
    ],
    "sg:phone":"+61 3 9555 7111",
    "sg:postcode":"3191",
    "sg:province":"VIC",
    "sg:tags":[
        "plumber",
        "gasfitters"
    ],
    "wof:name":"Dinnage R & J Plumbers & Gasfitters",
    "wof:placetype":"venue"
},
  "geometry": {"coordinates":[145.01260375999999,-37.960105896],"type":"Point"}
}