{
  "type": "Feature",
  "properties": {
    "addr:full":"330 Blackwall Rd Woy Woy NSW 2256",
    "addr:housenumber":"330",
    "addr:postcode":"2256",
    "addr:street":"Blackwall Rd",
    "iso:country":"AU",
    "sg:address":"330 Blackwall Rd",
    "sg:city":"Woy Woy",
    "sg:classifiers":[
        {
            "category":"Recreation",
            "subcategory":"Fishing",
            "type":"Entertainment"
        }
    ],
    "sg:phone":"+61 2 4341 6147",
    "sg:postcode":"2256",
    "sg:province":"NSW",
    "sg:tags":[
        "bait"
    ],
    "wof:name":"Blackwall Seafoods",
    "wof:placetype":"venue"
},
  "geometry": {"coordinates":[151.333618164,-33.5031776428],"type":"Point"}
}