{
  "type": "Feature",
  "properties": {
    "addr:full":"21 Glynne Rd Ringwood North VIC 3134",
    "addr:housenumber":"21",
    "addr:postcode":"3134",
    "addr:street":"Glynne Rd",
    "iso:country":"AU",
    "sg:address":"21 Glynne Rd",
    "sg:city":"Ringwood North",
    "sg:classifiers":[
        {
            "category":"Professional",
            "subcategory":"Art Services",
            "type":"Services"
        }
    ],
    "sg:phone":"+61 3 9879 0793",
    "sg:postcode":"3134",
    "sg:province":"VIC",
    "sg:tags":[
        "commercial",
        "artist"
    ],
    "wof:name":"Quikdraw Pty Ltd",
    "wof:placetype":"venue"
},
  "geometry": {"coordinates":[145.237716675,-37.7768325806],"type":"Point"}
}