{
  "type": "Feature",
  "properties": {
    "addr:full":"202 Deakin Ave Mildura VIC 3500",
    "addr:housenumber":"202",
    "addr:postcode":"3500",
    "addr:street":"Deakin Ave",
    "iso:country":"AU",
    "sg:address":"202 Deakin Ave",
    "sg:city":"Mildura",
    "sg:classifiers":[
        {
            "category":"Utilities",
            "subcategory":"Water",
            "type":"Services"
        }
    ],
    "sg:phone":"+61 3 5023 0535",
    "sg:postcode":"3500",
    "sg:province":"VIC",
    "sg:tags":[
        "hot",
        "system"
    ],
    "wof:name":"Leonards Plumbing Pty Ltd",
    "wof:placetype":"venue"
},
  "geometry": {"coordinates":[142.15472412099999,-34.1919822693],"type":"Point"}
}