{
  "type": "Feature",
  "properties": {
    "iso:country":"AU",
    "sg:address":"132 Fulham Rd",
    "sg:city":"Gulliver",
    "sg:classifiers":[
        {
            "category":"Education",
            "subcategory":"Music School",
            "type":"Public Place"
        }
    ],
    "sg:phone":"+61 7 4728 4041",
    "sg:postcode":"4812",
    "sg:province":"QLD",
    "sg:tags":[
        "therapy",
        "relaxation"
    ],
    "wof:name":"Northern Natural Therapy Services",
    "wof:placetype":"venue"
},
  "geometry": {"coordinates":[146.776474,-19.288311],"type":"Point"}
}