{
  "type": "Feature",
  "properties": {
    "addr:full":"Rear 307 Old Northern Rd Castle Hill NSW 2154",
    "addr:housenumber":"307",
    "addr:postcode":"2154",
    "addr:street":"Old Northern Rd",
    "iso:country":"AU",
    "sg:address":"Rear 307 Old Northern Rd",
    "sg:city":"Castle Hill",
    "sg:classifiers":[
        {
            "category":"Building & Trades",
            "subcategory":"Construction",
            "type":"Services"
        }
    ],
    "sg:phone":"+61 2 9680 8935",
    "sg:postcode":"2154",
    "sg:province":"NSW",
    "sg:tags":[
        "window",
        "tinting"
    ],
    "wof:name":"Solartint",
    "wof:placetype":"venue"
},
  "geometry": {"coordinates":[151.00723266599999,-33.7321281433],"type":"Point"}
}