{
  "type": "Feature",
  "properties": {
    "addr:full":"725 Burwood Rd Hawthorn East VIC 3123",
    "addr:housenumber":"725",
    "addr:postcode":"3123",
    "addr:street":"Burwood Rd",
    "iso:country":"AU",
    "sg:address":"725 Burwood Rd",
    "sg:city":"Hawthorn East",
    "sg:classifiers":[
        {
            "category":"Restaurant",
            "type":"Food & Drink"
        }
    ],
    "sg:phone":"+61 3 9882 6833",
    "sg:postcode":"3123",
    "sg:province":"VIC",
    "wof:name":"Cafe India",
    "wof:placetype":"venue"
},
  "geometry": {"coordinates":[145.049926758,-37.8242111206],"type":"Point"}
}