{
  "type": "Feature",
  "properties": {
    "addr:full":"10 Percy St Heidelberg West VIC 3081",
    "addr:housenumber":"10",
    "addr:postcode":"3081",
    "addr:street":"Percy St",
    "iso:country":"AU",
    "sg:address":"10 Percy St",
    "sg:city":"Heidelberg West",
    "sg:classifiers":[
        {
            "category":"Manufacturing",
            "subcategory":"Furniture",
            "type":"Manufacturing & Wholesale Goods"
        }
    ],
    "sg:phone":"+61 3 9459 0681",
    "sg:postcode":"3081",
    "sg:province":"VIC",
    "sg:tags":[
        "builder",
        "designer",
        "custom"
    ],
    "wof:name":"Hardwood Concepts",
    "wof:placetype":"venue"
},
  "geometry": {"coordinates":[145.05157470699999,-37.7314910889],"type":"Point"}
}