{
  "type": "Feature",
  "properties": {
    "addr:full":"Pembroke Rd Mooroolbark VIC 3138",
    "addr:postcode":"3138",
    "addr:street":"Pembroke Rd",
    "iso:country":"AU",
    "sg:address":"Pembroke Rd",
    "sg:city":"Mooroolbark",
    "sg:classifiers":[
        {
            "category":"Education",
            "subcategory":"School",
            "type":"Public Place"
        }
    ],
    "sg:phone":"+61 3 9725 6689",
    "sg:postcode":"3138",
    "sg:province":"VIC",
    "sg:tags":[
        "state",
        "except",
        "nsw"
    ],
    "wof:name":"Pembroke Primary",
    "wof:placetype":"venue"
},
  "geometry": {"coordinates":[145.32951355,-37.7862281799],"type":"Point"}
}