{
  "type": "Feature",
  "properties": {
    "iso:country":"AU",
    "sg:address":"52 Prahran Ave",
    "sg:city":"Frenchs Forest",
    "sg:classifiers":[
        {
            "category":"Professional",
            "subcategory":"Engineering",
            "type":"Services"
        }
    ],
    "sg:phone":"+61 2 9452 5997",
    "sg:postcode":"2086",
    "sg:province":"NSW",
    "sg:tags":[
        "manufacturing",
        "engineer"
    ],
    "wof:name":"W K Engineering Pty Ltd",
    "wof:placetype":"venue"
},
  "geometry": {"coordinates":[151.20565795900001,-33.7469291687],"type":"Point"}
}