{
  "type": "Feature",
  "properties": {
    "addr:full":"Shop 2, 20 Curtis Rd McGraths Hill NSW 2756",
    "addr:housenumber":"shop;20",
    "addr:postcode":"2756",
    "addr:street":"Curtis Rd",
    "iso:country":"AU",
    "sg:address":"Shop 2, 20 Curtis Rd",
    "sg:city":"McGraths Hill",
    "sg:classifiers":[
        {
            "category":"Recreation",
            "subcategory":"Boat Charter",
            "type":"Entertainment"
        }
    ],
    "sg:phone":"+61 2 4577 2721",
    "sg:postcode":"2756",
    "sg:province":"NSW",
    "sg:tags":[
        "canopy",
        "motor"
    ],
    "wof:name":"All Terrain 4wd Services",
    "wof:placetype":"venue"
},
  "geometry": {"coordinates":[150.83604431099999,-33.6229972839],"type":"Point"}
}