{
  "type": "Feature",
  "properties": {
    "iso:country":"AU",
    "sg:address":"29 Overport Rd",
    "sg:city":"Frankston",
    "sg:classifiers":[
        {
            "category":"Education",
            "subcategory":"Kindergarten",
            "type":"Public Place"
        }
    ],
    "sg:phone":"+61 3 9783 2015",
    "sg:postcode":"3199",
    "sg:province":"VIC",
    "sg:tags":[
        "pre-schools"
    ],
    "wof:name":"Delacombe Park Pre-School",
    "wof:placetype":"venue"
},
  "geometry": {"coordinates":[145.12532043499999,-38.1622924805],"type":"Point"}
}