{
  "type": "Feature",
  "properties": {
    "addr:full":"Amy St Regents Park NSW 2143",
    "addr:postcode":"2143",
    "addr:street":"Amy St",
    "iso:country":"AU",
    "sg:address":"Amy St",
    "sg:city":"Regents Park",
    "sg:classifiers":[
        {
            "category":"Social Services",
            "subcategory":"Child Care",
            "type":"Services"
        }
    ],
    "sg:phone":"+61 2 9644 7540",
    "sg:postcode":"2143",
    "sg:province":"NSW",
    "sg:tags":[
        "support",
        "health"
    ],
    "wof:name":"Early Childhood Health Centres",
    "wof:placetype":"venue"
},
  "geometry": {"coordinates":[151.02395629899999,-33.8837623596],"type":"Point"}
}