{
  "type": "Feature",
  "properties": {
    "addr:full":"4 Darri Rd Wyongah NSW 2259",
    "addr:housenumber":"4",
    "addr:postcode":"2259",
    "addr:street":"Darri Rd",
    "iso:country":"AU",
    "sg:address":"4 Darri Rd",
    "sg:city":"Wyongah",
    "sg:classifiers":[
        {
            "category":"Building & Trades",
            "subcategory":"Landscaping Services",
            "type":"Services"
        }
    ],
    "sg:phone":"+61 2 4393 5801",
    "sg:postcode":"2259",
    "sg:province":"NSW",
    "sg:tags":[
        "gardener"
    ],
    "wof:name":"EDIBLE GARDENS FOR YOU",
    "wof:placetype":"venue"
},
  "geometry": {"coordinates":[151.48770141599999,-33.2740592957],"type":"Point"}
}