{
  "type": "Feature",
  "properties": {
    "iso:country":"AU",
    "sg:address":"1 Camfield Drv",
    "sg:city":"Burswood",
    "sg:classifiers":[
        {
            "category":"Retail",
            "subcategory":"Event Space",
            "type":"Services"
        }
    ],
    "sg:phone":"+61 8 9472 0255",
    "sg:postcode":"6100",
    "sg:province":"WA",
    "sg:tags":[
        "venue",
        "reception",
        "wedding"
    ],
    "wof:name":"Burswood On Swan",
    "wof:placetype":"venue"
},
  "geometry": {"coordinates":[115.892028809,-31.9629573822],"type":"Point"}
}