{
  "type": "Feature",
  "properties": {
    "addr:full":"Shop 10/ 3 Dennis Rd Springwood QLD 4127",
    "addr:housenumber":"shop 10 / 3",
    "addr:postcode":"4127",
    "addr:street":"Dennis Rd",
    "iso:country":"AU",
    "sg:address":"Shop 10/ 3 Dennis Rd",
    "sg:city":"Springwood",
    "sg:classifiers":[
        {
            "category":"Health Services",
            "subcategory":"Doctor",
            "type":"Services"
        }
    ],
    "sg:phone":"+61 7 3208 5552",
    "sg:postcode":"4127",
    "sg:province":"QLD",
    "sg:tags":[
        "medical",
        "practitioner"
    ],
    "wof:name":"Landsberg P. Dr",
    "wof:placetype":"venue"
},
  "geometry": {"coordinates":[153.127853394,-27.6215267181],"type":"Point"}
}