{
  "type": "Feature",
  "properties": {
    "addr:full":"RMB 580 Cherry Gardens Rd Cherry Gardens SA 5157",
    "addr:postcode":"5157",
    "addr:street":"Gardens Rd",
    "iso:country":"AU",
    "sg:address":"RMB 580 Cherry Gardens Rd",
    "sg:city":"Cherry Gardens",
    "sg:classifiers":[
        {
            "category":"Farming",
            "subcategory":"Nursery",
            "type":"Manufacturing & Wholesale Goods"
        }
    ],
    "sg:phone":"+61 8 8270 7700",
    "sg:postcode":"5157",
    "sg:province":"SA",
    "wof:name":"Lawrys Nursery",
    "wof:placetype":"venue"
},
  "geometry": {"coordinates":[138.65582275400001,-35.0632324219],"type":"Point"}
}