{
  "type": "Feature",
  "properties": {
    "addr:full":"17a Meyer Rd Lonsdale SA 5160",
    "addr:housenumber":"17a",
    "addr:postcode":"5160",
    "addr:street":"Meyer Rd",
    "iso:country":"AU",
    "sg:address":"17a Meyer Rd",
    "sg:city":"Lonsdale",
    "sg:classifiers":[
        {
            "category":"Real Estate",
            "subcategory":"Architect",
            "type":"Services"
        }
    ],
    "sg:phone":"+61 8 8326 6199",
    "sg:postcode":"5160",
    "sg:province":"SA",
    "sg:tags":[
        "raw",
        "material",
        "plastic"
    ],
    "wof:name":"Adelaide Granulation Industries",
    "wof:placetype":"venue"
},
  "geometry": {"coordinates":[138.494262695,-35.1017036438],"type":"Point"}
}