{
  "type": "Feature",
  "properties": {
    "addr:full":"Unit 7, 171- 173 Cheltenham Rd Dandenong VIC 3175",
    "addr:housenumber":"171 173",
    "addr:postcode":"3175",
    "addr:street":"Cheltenham Rd",
    "iso:country":"AU",
    "sg:address":"Unit 7, 171- 173 Cheltenham Rd",
    "sg:city":"Dandenong",
    "sg:classifiers":[
        {
            "category":"Professional",
            "subcategory":"Computer Services",
            "type":"Services"
        }
    ],
    "sg:phone":"+61 500 557 737",
    "sg:postcode":"3175",
    "sg:province":"VIC",
    "sg:tags":[
        "equipment",
        "networking",
        "installation"
    ],
    "wof:name":"Lynx Computer Services",
    "wof:placetype":"venue"
},
  "geometry": {"coordinates":[145.193893433,-37.9917678833],"type":"Point"}
}