{
  "type": "Feature",
  "properties": {
    "iso:country":"AU",
    "sg:address":"3B Beresford Ave",
    "sg:city":"Beresfield",
    "sg:classifiers":[
        {
            "category":"Personal",
            "type":"Services"
        }
    ],
    "sg:phone":"+61 2 4966 1585",
    "sg:postcode":"2322",
    "sg:province":"NSW",
    "sg:tags":[
        "gift"
    ],
    "wof:name":"Beresfield Florist & Balloons",
    "wof:placetype":"venue"
},
  "geometry": {"coordinates":[151.65756225600001,-32.8010215759],"type":"Point"}
}