{
  "type": "Feature",
  "properties": {
    "addr:full":"324 Military Rd Semaphore Park SA 5019",
    "addr:housenumber":"324",
    "addr:postcode":"5019",
    "addr:street":"Military Rd",
    "iso:country":"AU",
    "sg:address":"324 Military Rd",
    "sg:city":"Semaphore Park",
    "sg:classifiers":[
        {
            "category":"Travel",
            "subcategory":"Hostel",
            "type":"Entertainment"
        }
    ],
    "sg:phone":"+61 8 8449 7066",
    "sg:postcode":"5019",
    "sg:province":"SA",
    "sg:tags":[
        "home"
    ],
    "wof:name":"Wesley House Aged Care Facility",
    "wof:placetype":"venue"
},
  "geometry": {"coordinates":[138.47857665999999,-34.8565406799],"type":"Point"}
}