{
  "type": "Feature",
  "properties": {
    "addr:full":"Level 1/ 2 Hughes St Cabramatta NSW 2166",
    "addr:housenumber":"/ 2",
    "addr:postcode":"2166",
    "addr:street":"Hughes St",
    "iso:country":"AU",
    "sg:address":"Level 1/ 2 Hughes St",
    "sg:city":"Cabramatta",
    "sg:classifiers":[
        {
            "category":"Banks & Credit Unions",
            "subcategory":"Financial Services",
            "type":"Services"
        }
    ],
    "sg:phone":"+61 2 9728 8899",
    "sg:postcode":"2166",
    "sg:province":"NSW",
    "sg:tags":[
        "planning"
    ],
    "wof:name":"BT & Co Pty Ltd",
    "wof:placetype":"venue"
},
  "geometry": {"coordinates":[150.937576294,-33.8937263489],"type":"Point"}
}