{
  "type": "Feature",
  "properties": {
    "addr:full":"8 Denison St Tamworth NSW 2340",
    "addr:housenumber":"8",
    "addr:postcode":"2340",
    "addr:street":"Denison St",
    "iso:country":"AU",
    "sg:address":"8 Denison St",
    "sg:city":"Tamworth",
    "sg:classifiers":[
        {
            "category":"Utilities",
            "subcategory":"Electric",
            "type":"Services"
        }
    ],
    "sg:phone":"+61 2 6762 7111",
    "sg:postcode":"2340",
    "sg:province":"NSW",
    "sg:tags":[
        "electrical",
        "contractor"
    ],
    "wof:name":"Ardina Electrical (Northwest) Pty Ltd",
    "wof:placetype":"venue"
},
  "geometry": {"coordinates":[150.915161133,-31.0866641998],"type":"Point"}
}