{
  "type": "Feature",
  "properties": {
    "addr:full":"34 Webster St Mt Barker WA 6324",
    "addr:housenumber":"34",
    "addr:postcode":"6324",
    "addr:street":"Webster St Mt",
    "iso:country":"AU",
    "sg:address":"34 Webster St",
    "sg:city":"Mt Barker",
    "sg:classifiers":[
        {
            "category":"Utilities",
            "subcategory":"Cable",
            "type":"Services"
        }
    ],
    "sg:phone":"+61 8 9851 1905",
    "sg:postcode":"6324",
    "sg:province":"WA",
    "sg:tags":[
        "mechanical"
    ],
    "wof:name":"MP Cable Jointing Services",
    "wof:placetype":"venue"
},
  "geometry": {"coordinates":[117.671478272,-34.6281356812],"type":"Point"}
}