{
  "type": "Feature",
  "properties": {
    "addr:full":"72 Mercer St Geelong VIC 3220",
    "addr:housenumber":"72",
    "addr:postcode":"3220",
    "addr:street":"Mercer St",
    "iso:country":"AU",
    "sg:address":"72 Mercer St",
    "sg:city":"Geelong",
    "sg:classifiers":[
        {
            "category":"Autos & Motor Vehicles",
            "subcategory":"Auto Supplies",
            "type":"Retail Goods"
        }
    ],
    "sg:phone":"+61 3 5223 2102",
    "sg:postcode":"3220",
    "sg:province":"VIC",
    "sg:tags":[
        "part",
        "cycles",
        "accessory"
    ],
    "wof:name":"Geelong Harley-Davidson",
    "wof:placetype":"venue"
},
  "geometry": {"coordinates":[144.355942,-38.142605],"type":"Point"}
}