{
  "type": "Feature",
  "properties": {
    "iso:country":"AU",
    "sg:address":"362 Port Douglas Rd",
    "sg:city":"Port Douglas",
    "sg:classifiers":[
        {
            "category":"Health Services",
            "subcategory":"Doctor",
            "type":"Services"
        }
    ],
    "sg:phone":"+61 7 4099 1111",
    "sg:postcode":"4877",
    "sg:province":"QLD",
    "sg:tags":[
        "medical",
        "practitioner"
    ],
    "wof:name":"New Horizons For Health",
    "wof:placetype":"venue"
},
  "geometry": {"coordinates":[145.46458435100001,-16.5150279999],"type":"Point"}
}