{
  "type": "Feature",
  "properties": {
    "addr:full":"39 Jamieson St Warrnambool VIC 3280",
    "addr:housenumber":"39",
    "addr:postcode":"3280",
    "addr:street":"Jamieson St",
    "iso:country":"AU",
    "sg:address":"39 Jamieson St",
    "sg:city":"Warrnambool",
    "sg:classifiers":[
        {
            "category":"Health Services",
            "subcategory":"Doctor",
            "type":"Services"
        }
    ],
    "sg:phone":"+61 3 5562 6533",
    "sg:postcode":"3280",
    "sg:province":"VIC",
    "sg:tags":[
        "medical",
        "practitioner"
    ],
    "wof:name":"Oliver P C Dr",
    "wof:placetype":"venue"
},
  "geometry": {"coordinates":[142.48545837399999,-38.3760910034],"type":"Point"}
}