{
  "type": "Feature",
  "properties": {
    "addr:full":"14 Stoneham St Stones Corner QLD 4120",
    "addr:housenumber":"14",
    "addr:postcode":"4120",
    "addr:street":"Stoneham St",
    "iso:country":"AU",
    "sg:address":"14 Stoneham St",
    "sg:city":"Stones Corner",
    "sg:classifiers":[
        {
            "category":"Health Services",
            "subcategory":"Doctor",
            "type":"Services"
        }
    ],
    "sg:phone":"+61 7 3324 2468",
    "sg:postcode":"4120",
    "sg:province":"QLD",
    "sg:tags":[
        "medical",
        "practitioner"
    ],
    "wof:name":"Cartmill Ross A",
    "wof:placetype":"venue"
},
  "geometry": {"coordinates":[153.04579162600001,-27.4988956451],"type":"Point"}
}