{
  "type": "Feature",
  "properties": {
    "addr:full":"1/ 22 Nind St Southport QLD 4215",
    "addr:housenumber":"/ 22",
    "addr:postcode":"4215",
    "addr:street":"Nind St",
    "iso:country":"AU",
    "sg:address":"1/ 22 Nind St",
    "sg:city":"Southport",
    "sg:classifiers":[
        {
            "category":"Real Estate",
            "subcategory":"Real Estate Agent",
            "type":"Services"
        }
    ],
    "sg:phone":"+61 7 5527 0708",
    "sg:postcode":"4215",
    "sg:province":"QLD",
    "wof:name":"Peter Currie Real Estate",
    "wof:placetype":"venue"
},
  "geometry": {"coordinates":[153.41275024399999,-27.9634246826],"type":"Point"}
}