{
  "type": "Feature",
  "properties": {
    "addr:full":"426 Rocky Point Rd Sans Souci NSW 2219",
    "addr:housenumber":"426",
    "addr:postcode":"2219",
    "addr:street":"Rocky Point Rd",
    "iso:country":"AU",
    "sg:address":"426 Rocky Point Rd",
    "sg:city":"Sans Souci",
    "sg:classifiers":[
        {
            "category":"Structure",
            "subcategory":"Bridge",
            "type":"Public Place"
        }
    ],
    "sg:phone":"+61 2 9525 8536",
    "sg:postcode":"2219",
    "sg:province":"NSW",
    "sg:tags":[
        "chainsaw",
        "brushcutters"
    ],
    "wof:name":"Ace Power Products",
    "wof:placetype":"venue"
},
  "geometry": {"coordinates":[151.13445999999999,-33.988773],"type":"Point"}
}