{
  "type": "Feature",
  "properties": {
    "iso:country":"AU",
    "sg:address":"144 Mitchell Drv",
    "sg:city":"Glossodia",
    "sg:classifiers":[
        {
            "category":"Building & Trades",
            "subcategory":"Pest Control",
            "type":"Services"
        }
    ],
    "sg:phone":"+61 1300 136 516",
    "sg:postcode":"2756",
    "sg:province":"NSW",
    "wof:name":"Hoeflake Ged",
    "wof:placetype":"venue"
},
  "geometry": {"coordinates":[150.78166198700001,-33.5241317749],"type":"Point"}
}