{
  "type": "Feature",
  "properties": {
    "iso:country":"AU",
    "sg:address":"Shop 21, 1 Parsons Rd",
    "sg:city":"Lisarow",
    "sg:classifiers":[
        {
            "category":"Health Services",
            "subcategory":"Doctor",
            "type":"Services"
        }
    ],
    "sg:phone":"+61 2 4328 5200",
    "sg:postcode":"2250",
    "sg:province":"NSW",
    "sg:tags":[
        "medical",
        "practitioner"
    ],
    "wof:name":"Chu Dr Clara",
    "wof:placetype":"venue"
},
  "geometry": {"coordinates":[151.366333008,-33.385761261],"type":"Point"}
}