{
  "type": "Feature",
  "properties": {
    "iso:country":"AU",
    "sg:address":"62 Roberts Rd",
    "sg:city":"Main Ridge",
    "sg:classifiers":[
        {
            "category":"Building & Trades",
            "subcategory":"Landscaping Services",
            "type":"Services"
        }
    ],
    "sg:phone":"+61 421 631 701",
    "sg:postcode":"3928",
    "sg:province":"VIC",
    "sg:tags":[
        "fertilizer",
        "spreading",
        "insecticide"
    ],
    "wof:name":"Keswick Arabians & Farm Contracting",
    "wof:placetype":"venue"
},
  "geometry": {"coordinates":[144.98699951200001,-38.3959922791],"type":"Point"}
}