{
  "type": "Feature",
  "properties": {
    "addr:full":"236 Nashua Rd Fernleigh NSW 2479",
    "addr:housenumber":"236",
    "addr:postcode":"2479",
    "addr:street":"Nashua Rd",
    "iso:country":"AU",
    "sg:address":"236 Nashua Rd",
    "sg:city":"Fernleigh",
    "sg:classifiers":[
        {
            "category":"Professional",
            "subcategory":"Art Services",
            "type":"Services"
        }
    ],
    "sg:phone":"+61 2 6629 1616",
    "sg:postcode":"2479",
    "sg:province":"NSW",
    "sg:tags":[
        "sculptor"
    ],
    "wof:name":"Ariel Fine Arts",
    "wof:placetype":"venue"
},
  "geometry": {"coordinates":[153.491943359,-28.7630214691],"type":"Point"}
}