{
  "type": "Feature",
  "properties": {
    "addr:full":"Unit 2A, 4 King Edward St Osborne Park WA 6017",
    "addr:housenumber":"unit 2a 4",
    "addr:postcode":"6017",
    "addr:street":"King Edward St",
    "iso:country":"AU",
    "sg:address":"Unit 2A, 4 King Edward St",
    "sg:city":"Osborne Park",
    "sg:classifiers":[
        {
            "category":"Utilities",
            "subcategory":"Telephone",
            "type":"Services"
        }
    ],
    "sg:phone":"+61 8 9204 1222",
    "sg:postcode":"6017",
    "sg:province":"WA",
    "sg:tags":[
        "equipment",
        "system"
    ],
    "wof:name":"Redsky A Communications Company",
    "wof:placetype":"venue"
},
  "geometry": {"coordinates":[115.804450989,-31.9037075043],"type":"Point"}
}