{
  "type": "Feature",
  "properties": {
    "addr:full":"Cnr Peden & Upper Sts Bega NSW 2550",
    "addr:postcode":"2550",
    "addr:street":"Cnr",
    "iso:country":"AU",
    "sg:address":"Cnr Peden & Upper Sts",
    "sg:city":"Bega",
    "sg:classifiers":[
        {
            "category":"Manufacturing",
            "subcategory":"Retail Goods",
            "type":"Manufacturing & Wholesale Goods"
        }
    ],
    "sg:phone":"+61 2 6492 1179",
    "sg:postcode":"2550",
    "sg:province":"NSW",
    "sg:tags":[
        "merchant",
        "pump",
        "mfrs"
    ],
    "wof:name":"Bega Mower Centre",
    "wof:placetype":"venue"
},
  "geometry": {"coordinates":[149.83937072800001,-36.6744499207],"type":"Point"}
}