{
  "type": "Feature",
  "properties": {
    "addr:full":"11 Marina Drv Ballarat VIC 3350",
    "addr:housenumber":"11",
    "addr:postcode":"3350",
    "addr:street":"Marina Drv",
    "iso:country":"AU",
    "sg:address":"11 Marina Drv",
    "sg:city":"Ballarat",
    "sg:classifiers":[
        {
            "category":"Building & Trades",
            "subcategory":"Plumbing",
            "type":"Services"
        }
    ],
    "sg:phone":"+61 418 519 387",
    "sg:postcode":"3350",
    "sg:province":"VIC",
    "sg:tags":[
        "plumber",
        "gasfitters"
    ],
    "wof:name":"Mooney P J",
    "wof:placetype":"venue"
},
  "geometry": {"coordinates":[143.866165,-37.608421],"type":"Point"}
}