{
  "type": "Feature",
  "properties": {
    "addr:full":"33 Furnace Rd Welshpool WA 6106",
    "addr:housenumber":"33",
    "addr:postcode":"6106",
    "addr:street":"Furnace Rd",
    "iso:country":"AU",
    "sg:address":"33 Furnace Rd",
    "sg:city":"Welshpool",
    "sg:classifiers":[
        {
            "category":"Manufacturing",
            "subcategory":"Paper Products",
            "type":"Manufacturing & Wholesale Goods"
        }
    ],
    "sg:phone":"+61 8 9451 5044",
    "sg:postcode":"6106",
    "sg:province":"WA",
    "sg:tags":[
        "bag"
    ],
    "wof:name":"Pope Packaging",
    "wof:placetype":"venue"
},
  "geometry": {"coordinates":[115.948318481,-31.995470047],"type":"Point"}
}