{
  "type": "Feature",
  "properties": {
    "addr:full":"Cairns Central Shopng Cntr, McLeod St Cairns QLD 4870",
    "addr:postcode":"4870",
    "addr:street":"St",
    "iso:country":"AU",
    "sg:address":"Cairns Central Shopng Cntr, McLeod St",
    "sg:city":"Cairns",
    "sg:classifiers":[
        {
            "category":"Health Services",
            "subcategory":"Optometrist",
            "type":"Services"
        }
    ],
    "sg:phone":"+61 7 4051 1666",
    "sg:postcode":"4870",
    "sg:province":"QLD",
    "wof:name":"OPSM",
    "wof:placetype":"venue"
},
  "geometry": {"coordinates":[145.774169922,-16.926197052],"type":"Point"}
}