{
  "type": "Feature",
  "properties": {
    "iso:country":"AU",
    "sg:address":"1/ 2 Mountain View Dr",
    "sg:city":"Goonellabah",
    "sg:classifiers":[
        {
            "category":"Real Estate",
            "subcategory":"Architect",
            "type":"Services"
        }
    ],
    "sg:phone":"+61 1300 136 214",
    "sg:postcode":"2480",
    "sg:province":"NSW",
    "sg:tags":[
        "building",
        "designer"
    ],
    "wof:name":"Summerland Building Design",
    "wof:placetype":"venue"
},
  "geometry": {"coordinates":[153.30694580100001,-28.8100643158],"type":"Point"}
}