{
  "type": "Feature",
  "properties": {
    "addr:full":"Shop 4 c/- French Quarter 62 Hastings St Noosa Heads QLD 4567",
    "addr:housenumber":"shop 4;62",
    "addr:postcode":"4567",
    "addr:street":"C / French Quarter;St",
    "iso:country":"AU",
    "sg:address":"Shop 4 c/- French Quarter 62 Hastings St",
    "sg:city":"Noosa Heads",
    "sg:classifiers":[
        {
            "category":"Personal",
            "subcategory":"Beauty Salon",
            "type":"Services"
        }
    ],
    "sg:phone":"+61 7 5430 7377",
    "sg:postcode":"4567",
    "sg:province":"QLD",
    "wof:name":"Beau Visage Beauty Salon Pty Ltd",
    "wof:placetype":"venue"
},
  "geometry": {"coordinates":[153.08737182600001,-26.3860473633],"type":"Point"}
}