{
  "type": "Feature",
  "properties": {
    "iso:country":"AU",
    "sg:address":"30 Rosamond Rd",
    "sg:city":"Maribyrnong",
    "sg:classifiers":[
        {
            "category":"Banks & Credit Unions",
            "subcategory":"Atm",
            "type":"Services"
        }
    ],
    "sg:phone":"+61 3 9243 9700",
    "sg:postcode":"3032",
    "sg:province":"VIC",
    "sg:tags":[
        "wholesaler",
        "mfrs",
        "shirt",
        "pyjama"
    ],
    "wof:name":"Pelaco International Pty Ltd",
    "wof:placetype":"venue"
},
  "geometry": {"coordinates":[144.883835,-37.785564],"type":"Point"}
}