{
  "type": "Feature",
  "properties": {
    "iso:country":"AU",
    "sg:address":"9 Angliss Rd",
    "sg:city":"Berrimah",
    "sg:classifiers":[
        {
            "category":"Freight",
            "type":"Transportation"
        }
    ],
    "sg:phone":"+61 8 8947 4040",
    "sg:postcode":"0828",
    "sg:province":"NT",
    "sg:tags":[
        "light",
        "carrier"
    ],
    "wof:name":"Pandion Haulage Pty Ltd",
    "wof:placetype":"venue"
},
  "geometry": {"coordinates":[130.94895935100001,-12.4443044662],"type":"Point"}
}