{
  "type": "Feature",
  "properties": {
    "iso:country":"AU",
    "sg:address":"Shop 7 Marrickville Metro Shopping Centre, 34 Victoria Rd",
    "sg:city":"Marrickville",
    "sg:classifiers":[
        {
            "category":"Insurance",
            "subcategory":"Hazard Insurance",
            "type":"Services"
        }
    ],
    "sg:phone":"+61 13 21 32",
    "sg:postcode":"2204",
    "sg:province":"NSW",
    "sg:tags":[
        "motor",
        "vehicle"
    ],
    "wof:name":"NRMA Insurance",
    "wof:placetype":"venue"
},
  "geometry": {"coordinates":[151.17202800000001,-33.906013],"type":"Point"}
}