{
  "type": "Feature",
  "properties": {
    "addr:full":"Level One 482 Brunswick St Fortitude Valley QLD 4006",
    "addr:housenumber":"482",
    "addr:postcode":"4006",
    "addr:street":"Brunswick St",
    "iso:country":"AU",
    "sg:address":"Level One 482 Brunswick St",
    "sg:city":"Fortitude Valley",
    "sg:classifiers":[
        {
            "category":"Personal",
            "type":"Services"
        }
    ],
    "sg:phone":"+61 7 3358 1930",
    "sg:postcode":"4006",
    "sg:province":"QLD",
    "sg:tags":[
        "dressmaker"
    ],
    "sg:website":"http://www.nuclearthreads.com",
    "wof:name":"Nuclear Threads",
    "wof:placetype":"venue"
},
  "geometry": {"coordinates":[153.03785705600001,-27.4605255127],"type":"Point"}
}