{
  "type": "Feature",
  "properties": {
    "addr:full":"9 Beronia St Evans Head NSW 2473",
    "addr:housenumber":"9",
    "addr:postcode":"2473",
    "addr:street":"Beronia St Evans",
    "iso:country":"AU",
    "sg:address":"9 Beronia St",
    "sg:city":"Evans Head",
    "sg:classifiers":[
        {
            "category":"Wholesale",
            "subcategory":"Seafood",
            "type":"Manufacturing & Wholesale Goods"
        }
    ],
    "sg:phone":"+61 2 6682 5833",
    "sg:postcode":"2473",
    "sg:province":"NSW",
    "sg:tags":[
        "fish"
    ],
    "wof:name":"Forster W & W",
    "wof:placetype":"venue"
},
  "geometry": {"coordinates":[153.42864990199999,-29.1095523834],"type":"Point"}
}