{
  "type": "Feature",
  "properties": {
    "addr:full":"55 Thomas Drv Chevron Island QLD 4217",
    "addr:housenumber":"55",
    "addr:postcode":"4217",
    "addr:street":"Thomas Drv Chevron",
    "iso:country":"AU",
    "sg:address":"55 Thomas Drv",
    "sg:city":"Chevron Island",
    "sg:classifiers":[
        {
            "category":"Food & Beverages",
            "subcategory":"Bakery",
            "type":"Retail Goods"
        }
    ],
    "sg:phone":"+61 7 5538 4895",
    "sg:postcode":"4217",
    "sg:province":"QLD",
    "sg:tags":[
        "cake",
        "shop",
        "pastry"
    ],
    "wof:name":"Goldsteins",
    "wof:placetype":"venue"
},
  "geometry": {"coordinates":[153.41914367699999,-27.9977455139],"type":"Point"}
}