{
  "type": "Feature",
  "properties": {
    "addr:full":"146 Logan Rd Buranda QLD 4102",
    "addr:housenumber":"146",
    "addr:postcode":"4102",
    "addr:street":"Logan Rd",
    "iso:country":"AU",
    "sg:address":"146 Logan Rd",
    "sg:city":"Buranda",
    "sg:classifiers":[
        {
            "category":"Shopping",
            "subcategory":"Computers & Home Electronics",
            "type":"Retail Goods"
        }
    ],
    "sg:phone":"+61 7 3393 0688",
    "sg:postcode":"4102",
    "sg:province":"QLD",
    "sg:tags":[
        "equipment",
        "supply"
    ],
    "wof:name":"Micro Development - CMS",
    "wof:placetype":"venue"
},
  "geometry": {"coordinates":[153.041870117,-27.4970760345],"type":"Point"}
}