{
  "type": "Feature",
  "properties": {
    "iso:country":"AU",
    "sg:address":"10 McIntosh St",
    "sg:city":"Oakleigh",
    "sg:classifiers":[
        {
            "category":"Professional",
            "subcategory":"Art Services",
            "type":"Services"
        }
    ],
    "sg:phone":"+61 400 244 552",
    "sg:postcode":"3166",
    "sg:province":"VIC",
    "sg:tags":[
        "graphic",
        "designer"
    ],
    "wof:name":"Primary Designs",
    "wof:placetype":"venue"
},
  "geometry": {"coordinates":[145.099334717,-37.9109039307],"type":"Point"}
}