{
  "type": "Feature",
  "properties": {
    "addr:full":"80 Scotchmer St Fitzroy North VIC 3068",
    "addr:housenumber":"80",
    "addr:postcode":"3068",
    "addr:street":"Scotchmer St",
    "iso:country":"AU",
    "sg:address":"80 Scotchmer St",
    "sg:city":"Fitzroy North",
    "sg:classifiers":[
        {
            "category":"Building & Trades",
            "subcategory":"Construction",
            "type":"Services"
        }
    ],
    "sg:phone":"+61 3 9481 5000",
    "sg:postcode":"3068",
    "sg:province":"VIC",
    "sg:tags":[
        "renovation",
        "alterations",
        "extension",
        "contractor"
    ],
    "wof:name":"Matos Pty Ltd",
    "wof:placetype":"venue"
},
  "geometry": {"coordinates":[144.98164367699999,-37.7831993103],"type":"Point"}
}