{
  "type": "Feature",
  "properties": {
    "addr:full":"177 Queens Pde Clifton Hill VIC 3068",
    "addr:housenumber":"177",
    "addr:postcode":"3068",
    "addr:street":"Queens Pde",
    "iso:country":"AU",
    "sg:address":"177 Queens Pde",
    "sg:city":"Clifton Hill",
    "sg:classifiers":[
        {
            "category":"Health Services",
            "subcategory":"Health Practitioner",
            "type":"Services"
        }
    ],
    "sg:phone":"+61 3 9482 4062",
    "sg:postcode":"3068",
    "sg:province":"VIC",
    "sg:tags":[
        "psychologist"
    ],
    "wof:name":"Good Mary",
    "wof:placetype":"venue"
},
  "geometry": {"coordinates":[144.992111206,-37.788482666],"type":"Point"}
}