{
  "type": "Feature",
  "properties": {
    "iso:country":"AU",
    "sg:address":"U5/ 57",
    "sg:city":"Marina Blv Cullen Bay",
    "sg:classifiers":[
        {
            "category":"Banks & Credit Unions",
            "subcategory":"Financial Services",
            "type":"Services"
        }
    ],
    "sg:phone":"+61 8 8941 4041",
    "sg:postcode":"0820",
    "sg:province":"NT",
    "sg:tags":[
        "planning"
    ],
    "wof:name":"Pure & Simple Wealth Solutions",
    "wof:placetype":"venue"
},
  "geometry": {"coordinates":[130.822067261,-12.4509429932],"type":"Point"}
}