{
  "type": "Feature",
  "properties": {
    "iso:country":"AU",
    "sg:address":"77 Evans St",
    "sg:city":"Wollongong",
    "sg:classifiers":[
        {
            "category":"Health Services",
            "subcategory":"Chiropractor",
            "type":"Services"
        }
    ],
    "sg:phone":"+61 2 4228 8157",
    "sg:postcode":"2500",
    "sg:province":"NSW",
    "wof:name":"Downie Aron",
    "wof:placetype":"venue"
},
  "geometry": {"coordinates":[150.894623,-34.434368],"type":"Point"}
}