{
  "type": "Feature",
  "properties": {
    "addr:full":"38 Cumberland Ave Nowra South NSW 2541",
    "addr:housenumber":"38",
    "addr:postcode":"2541",
    "addr:street":"Cumberland Ave",
    "iso:country":"AU",
    "sg:address":"38 Cumberland Ave",
    "sg:city":"Nowra South",
    "sg:phone":"+61 2 4422 7700",
    "sg:postcode":"2541",
    "sg:province":"NSW",
    "wof:name":"Nowra Filters",
    "wof:placetype":"venue"
},
  "geometry": {"coordinates":[150.57806396500001,-34.9144973755],"type":"Point"}
}