{
  "type": "Feature",
  "properties": {
    "addr:full":"36 Kosciusko St Bossley Park NSW 2176",
    "addr:housenumber":"36",
    "addr:postcode":"2176",
    "addr:street":"Kosciusko St",
    "iso:country":"AU",
    "sg:address":"36 Kosciusko St",
    "sg:city":"Bossley Park",
    "sg:classifiers":[
        {
            "category":"Communications",
            "type":"Services"
        }
    ],
    "sg:phone":"+61 2 9609 7984",
    "sg:postcode":"2176",
    "sg:province":"NSW",
    "sg:tags":[
        "translation"
    ],
    "wof:name":"Lao Interpreter",
    "wof:placetype":"venue"
},
  "geometry": {"coordinates":[150.89476013199999,-33.8592910767],"type":"Point"}
}