{
  "type": "Feature",
  "properties": {
    "addr:full":"Sherridans Bridge Rd Rutherglen VIC 3685",
    "addr:postcode":"3685",
    "addr:street":"Bridge Rd",
    "iso:country":"AU",
    "sg:address":"Sherridans Bridge Rd",
    "sg:city":"Rutherglen",
    "sg:classifiers":[
        {
            "category":"Education",
            "subcategory":"School",
            "type":"Public Place"
        }
    ],
    "sg:phone":"+61 2 6032 9483",
    "sg:postcode":"3685",
    "sg:province":"VIC",
    "sg:tags":[
        "state",
        "-",
        "nsw"
    ],
    "wof:name":"Rutherglen High School",
    "wof:placetype":"venue"
},
  "geometry": {"coordinates":[146.45228576700001,-36.0631332397],"type":"Point"}
}