{
  "type": "Feature",
  "properties": {
    "addr:full":"44 Deakin St Forestville NSW 2087",
    "addr:housenumber":"44",
    "addr:postcode":"2087",
    "addr:street":"Deakin St",
    "iso:country":"AU",
    "sg:address":"44 Deakin St",
    "sg:city":"Forestville",
    "sg:classifiers":[
        {
            "category":"Building & Trades",
            "subcategory":"Construction",
            "type":"Services"
        }
    ],
    "sg:phone":"+61 2 9905 6542",
    "sg:postcode":"2087",
    "sg:province":"NSW",
    "sg:tags":[
        "joiner",
        "carpenter"
    ],
    "wof:name":"Antaw Gavin Carpentry Builder",
    "wof:placetype":"venue"
},
  "geometry": {"coordinates":[151.21516418499999,-33.7556648254],"type":"Point"}
}