{
  "type": "Feature",
  "properties": {
    "addr:full":"PO Box 211 Ballan VIC 3342",
    "addr:postcode":"3342",
    "iso:country":"AU",
    "sg:address":"PO Box 211",
    "sg:city":"Ballan",
    "sg:classifiers":[
        {
            "category":"Shopping",
            "subcategory":"Crafts & Fabrics",
            "type":"Retail Goods"
        }
    ],
    "sg:phone":"+61 3 5368 2033",
    "sg:postcode":"3342",
    "sg:province":"VIC",
    "sg:tags":[
        "wool",
        "knitting",
        "accessory"
    ],
    "wof:name":"Crafty Ones",
    "wof:placetype":"venue"
},
  "geometry": {"coordinates":[144.22869900000001,-37.60014],"type":"Point"}
}