{
  "type": "Feature",
  "properties": {
    "addr:full":"56 Hutchinson St Mt Barker SA 5251",
    "addr:housenumber":"56",
    "addr:postcode":"5251",
    "addr:street":"Hutchinson St Mt",
    "iso:country":"AU",
    "sg:address":"56 Hutchinson St",
    "sg:city":"Mt Barker",
    "sg:classifiers":[
        {
            "category":"Food & Beverages",
            "subcategory":"Liquor & Beverages",
            "type":"Retail Goods"
        }
    ],
    "sg:phone":"+61 8 8391 1596",
    "sg:postcode":"5251",
    "sg:province":"SA",
    "sg:tags":[
        "store"
    ],
    "wof:name":"BWS Liquor",
    "wof:placetype":"venue"
},
  "geometry": {"coordinates":[138.86068725600001,-35.0672492981],"type":"Point"}
}