{
  "type": "Feature",
  "properties": {
    "addr:full":"Shop 5, 150 Blaxland Arcade Great Western Hwy Blaxland NSW 2774",
    "addr:housenumber":"shop 5",
    "addr:postcode":"150;2774",
    "addr:street":"Great Western Hwy",
    "iso:country":"AU",
    "sg:address":"Shop 5, 150 Blaxland Arcade Great Western Hwy",
    "sg:city":"Blaxland",
    "sg:classifiers":[
        {
            "category":"Personal",
            "subcategory":"Beauty Salon",
            "type":"Services"
        }
    ],
    "sg:phone":"+61 2 4739 0977",
    "sg:postcode":"2774",
    "sg:province":"NSW",
    "sg:tags":[
        "hairdresser"
    ],
    "wof:name":"Ultimate Hair",
    "wof:placetype":"venue"
},
  "geometry": {"coordinates":[150.60711669899999,-33.741859436],"type":"Point"}
}