{
  "type": "Feature",
  "properties": {
    "addr:full":"38 hoskins St Mitchell ACT 2911",
    "addr:housenumber":"38",
    "addr:postcode":"2911",
    "addr:street":"Hoskins St",
    "iso:country":"AU",
    "sg:address":"38 hoskins St",
    "sg:city":"Mitchell",
    "sg:classifiers":[
        {
            "category":"Personal",
            "subcategory":"Adult",
            "type":"Services"
        }
    ],
    "sg:phone":"+61 2 6242 5665",
    "sg:postcode":"2911",
    "sg:province":"ACT",
    "sg:tags":[
        "vic",
        "except",
        "state",
        "escort",
        "social",
        "qld"
    ],
    "wof:name":"Gentlemen Prefer Blondes",
    "wof:placetype":"venue"
},
  "geometry": {"coordinates":[149.13714599599999,-35.2184753418],"type":"Point"}
}