{
  "type": "Feature",
  "properties": {
    "addr:full":"164 Hubert St East Victoria Park WA 6101",
    "addr:housenumber":"164",
    "addr:postcode":"6101",
    "addr:street":"Hubert St",
    "iso:country":"AU",
    "sg:address":"164 Hubert St",
    "sg:city":"East Victoria Park",
    "sg:classifiers":[
        {
            "category":"Real Estate",
            "subcategory":"Architect",
            "type":"Services"
        }
    ],
    "sg:phone":"+61 410 796 014",
    "sg:postcode":"6101",
    "sg:province":"WA",
    "wof:name":"The Design Legacy",
    "wof:placetype":"venue"
},
  "geometry": {"coordinates":[115.910263062,-31.9902439117],"type":"Point"}
}