{
  "type": "Feature",
  "properties": {
    "addr:full":"PO Box 1413 Green Valley NSW 2168",
    "addr:postcode":"2168",
    "iso:country":"AU",
    "sg:address":"PO Box 1413",
    "sg:city":"Green Valley",
    "sg:classifiers":[
        {
            "category":"Arena",
            "subcategory":"Sports Club",
            "type":"Entertainment"
        }
    ],
    "sg:phone":"+61 418 273 420",
    "sg:postcode":"2168",
    "sg:province":"NSW",
    "sg:tags":[
        "defence",
        "supply",
        "self",
        "instruction",
        "martial art"
    ],
    "wof:name":"Okinawa Isshinryu Karate (OIKA)",
    "wof:placetype":"venue"
},
  "geometry": {"coordinates":[150.86651611299999,-33.9027404785],"type":"Point"}
}