{
  "type": "Feature",
  "properties": {
    "addr:full":"Derrimut Rd Hoppers Crossing VIC 3029",
    "addr:postcode":"3029",
    "addr:street":"Derrimut Rd",
    "iso:country":"AU",
    "sg:address":"Derrimut Rd",
    "sg:city":"Hoppers Crossing",
    "sg:classifiers":[
        {
            "category":"Fast Food",
            "type":"Food & Drink"
        }
    ],
    "sg:phone":"+61 3 9748 3664",
    "sg:postcode":"3029",
    "sg:province":"VIC",
    "sg:tags":[
        "away",
        "take"
    ],
    "wof:name":"Big Bite The",
    "wof:placetype":"venue"
},
  "geometry": {"coordinates":[144.68673699999999,-37.862808],"type":"Point"}
}