{
  "type": "Feature",
  "properties": {
    "addr:full":"Shop 7 Eastwood Village Progress Ave Eastwood NSW 2122",
    "addr:housenumber":"shop 7",
    "addr:postcode":"2122",
    "addr:street":"Progress Ave",
    "iso:country":"AU",
    "sg:address":"Shop 7 Eastwood Village Progress Ave",
    "sg:city":"Eastwood",
    "sg:classifiers":[
        {
            "category":"Health Services",
            "subcategory":"Health Practitioner",
            "type":"Services"
        }
    ],
    "sg:phone":"+61 2 9874 9353",
    "sg:postcode":"2122",
    "sg:province":"NSW",
    "sg:tags":[
        "herbalist"
    ],
    "wof:name":"Chinese Herbal Medicine & Grocery",
    "wof:placetype":"venue"
},
  "geometry": {"coordinates":[151.08059692399999,-33.7907524109],"type":"Point"}
}