{
  "type": "Feature",
  "properties": {
    "iso:country":"AU",
    "sg:address":"3016 Gold Coast Hwy cnr Markwell Ave & Surfers Paradise Blvd",
    "sg:city":"Surfers Paradise",
    "sg:classifiers":[
        {
            "category":"Retail",
            "subcategory":"Auto Rental",
            "type":"Services"
        }
    ],
    "sg:phone":"+61 7 5592 0227",
    "sg:postcode":"4217",
    "sg:province":"QLD",
    "sg:tags":[
        "car",
        "hire",
        "minibus"
    ],
    "wof:name":"Queensland Coastal Car & Bus Rentals",
    "wof:placetype":"venue"
},
  "geometry": {"coordinates":[153.42752075199999,-28.0073986053],"type":"Point"}
}