{
  "type": "Feature",
  "properties": {
    "addr:full":"Industrial Estate Connors Rd Paget QLD 4740",
    "addr:postcode":"4740",
    "addr:street":"Connors Rd",
    "iso:country":"AU",
    "sg:address":"Industrial Estate Connors Rd",
    "sg:city":"Paget",
    "sg:phone":"+61 7 4952 1839",
    "sg:postcode":"4740",
    "sg:province":"QLD",
    "wof:name":"Paget Welding & Engineering Co",
    "wof:placetype":"venue"
},
  "geometry": {"coordinates":[149.161179,-21.169504],"type":"Point"}
}