{
  "type": "Feature",
  "properties": {
    "iso:country":"AU",
    "sg:address":"29 Kirrawee Rd",
    "sg:city":"Gosford North",
    "sg:classifiers":[
        {
            "category":"Education",
            "subcategory":"Dance Studio",
            "type":"Public Place"
        }
    ],
    "sg:phone":"+61 2 4324 4696",
    "sg:postcode":"2250",
    "sg:province":"NSW",
    "sg:tags":[
        "venue",
        "tuition"
    ],
    "wof:name":"Gosford City School Of Dance",
    "wof:placetype":"venue"
},
  "geometry": {"coordinates":[151.34332275400001,-33.4104118347],"type":"Point"}
}