{
  "type": "Feature",
  "properties": {
    "iso:country":"AU",
    "sg:address":"Perrin Pl",
    "sg:city":"Salisbury",
    "sg:classifiers":[
        {
            "category":"Autos & Motor Vehicles",
            "subcategory":"Automobile Sales",
            "type":"Retail Goods"
        }
    ],
    "sg:phone":"+61 7 3274 7277",
    "sg:postcode":"4107",
    "sg:province":"QLD",
    "sg:tags":[
        "equipment",
        "trailer"
    ],
    "wof:name":"APT Fleet Services Pty Ltd",
    "wof:placetype":"venue"
},
  "geometry": {"coordinates":[153.030349731,-27.5594329834],"type":"Point"}
}