{
  "type": "Feature",
  "properties": {
    "iso:country":"AU",
    "sg:address":"5 Eveshan Crt",
    "sg:city":"Bella Vista",
    "sg:classifiers":[
        {
            "category":"Building & Trades",
            "subcategory":"Construction",
            "type":"Services"
        }
    ],
    "sg:phone":"+61 414 565 095",
    "sg:postcode":"2153",
    "sg:province":"NSW",
    "sg:tags":[
        "brick",
        "paving"
    ],
    "wof:name":"New Edition Constructions",
    "wof:placetype":"venue"
},
  "geometry": {"coordinates":[150.965530395,-33.7357254028],"type":"Point"}
}