{
  "type": "Feature",
  "properties": {
    "iso:country":"AU",
    "sg:address":"282 George St",
    "sg:city":"Windsor",
    "sg:classifiers":[
        {
            "category":"Health Services",
            "subcategory":"Doctor",
            "type":"Services"
        }
    ],
    "sg:phone":"+61 2 4577 4404",
    "sg:postcode":"2756",
    "sg:province":"NSW",
    "sg:tags":[
        "medical",
        "practitioner"
    ],
    "wof:name":"Noakes J",
    "wof:placetype":"venue"
},
  "geometry": {"coordinates":[150.81736755399999,-33.6090545654],"type":"Point"}
}