{
  "type": "Feature",
  "properties": {
    "addr:full":"Suite 6, 72- 80 Argyle St Picton NSW 2571",
    "addr:housenumber":"72 80",
    "addr:postcode":"2571",
    "addr:street":"Argyle St",
    "iso:country":"AU",
    "sg:address":"Suite 6, 72- 80 Argyle St",
    "sg:city":"Picton",
    "sg:classifiers":[
        {
            "category":"Real Estate",
            "subcategory":"Real Estate Agent",
            "type":"Services"
        }
    ],
    "sg:phone":"+61 2 4677 3507",
    "sg:postcode":"2571",
    "sg:province":"NSW",
    "sg:tags":[
        "consultant",
        "heritage"
    ],
    "wof:name":"Kayandel Archaeological Services",
    "wof:placetype":"venue"
},
  "geometry": {"coordinates":[150.6118927,-34.1686248779],"type":"Point"}
}