{
  "type": "Feature",
  "properties": {
    "iso:country":"AU",
    "sg:address":"56 Ryley St",
    "sg:city":"Wangaratta",
    "sg:classifiers":[
        {
            "category":"Travel",
            "subcategory":"Hotels & Motels",
            "type":"Entertainment"
        }
    ],
    "sg:phone":"+61 3 5721 5655",
    "sg:postcode":"3677",
    "sg:province":"VIC",
    "wof:name":"Merriwa Park Motel",
    "wof:placetype":"venue"
},
  "geometry": {"coordinates":[146.32244873100001,-36.3576469421],"type":"Point"}
}