{
  "type": "Feature",
  "properties": {
    "iso:country":"AU",
    "sg:address":"36 Burdett Rd",
    "sg:city":"Basket Range",
    "sg:classifiers":[
        {
            "category":"Professional",
            "subcategory":"Engineering",
            "type":"Services"
        }
    ],
    "sg:phone":"+61 8 8390 1565",
    "sg:postcode":"5138",
    "sg:province":"SA",
    "sg:tags":[
        "engineer"
    ],
    "wof:name":"Hydro Tech Engineering",
    "wof:placetype":"venue"
},
  "geometry": {"coordinates":[138.76791381800001,-34.9331970215],"type":"Point"}
}