{
  "type": "Feature",
  "properties": {
    "iso:country":"AU",
    "sg:address":"1/ 67 Harrow Rd",
    "sg:city":"Somerton Park",
    "sg:classifiers":[
        {
            "category":"Home & Garden",
            "subcategory":"Building Materials",
            "type":"Retail Goods"
        }
    ],
    "sg:phone":"+61 8 8377 2399",
    "sg:postcode":"5044",
    "sg:province":"SA",
    "sg:tags":[
        "lawn",
        "cutting",
        "maintenance"
    ],
    "wof:name":"Jones Lynton R",
    "wof:placetype":"venue"
},
  "geometry": {"coordinates":[138.514008,-35.000614],"type":"Point"}
}