{
  "type": "Feature",
  "properties": {
    "iso:country":"AU",
    "sg:address":"15- 17 Pakington St St",
    "sg:city":"Kilda",
    "sg:classifiers":[
        {
            "category":"Professional",
            "subcategory":"Employment Agencies",
            "type":"Services"
        }
    ],
    "sg:phone":"+61 3 9593 9555",
    "sg:postcode":"3182",
    "sg:province":"VIC",
    "sg:tags":[
        "hire",
        "labour",
        "contractor"
    ],
    "wof:name":"Contract Drafting Service (C.D.S) Pty Ltd",
    "wof:placetype":"venue"
},
  "geometry": {"coordinates":[144.987182617,-37.8659591675],"type":"Point"}
}