{
  "type": "Feature",
  "properties": {
    "iso:country":"AU",
    "sg:address":"17 Glentanna St",
    "sg:city":"Kedron",
    "sg:classifiers":[
        {
            "category":"Social Services",
            "type":"Services"
        }
    ],
    "sg:phone":"+61 7 3630 5755",
    "sg:postcode":"4031",
    "sg:province":"QLD",
    "sg:tags":[
        "disabled",
        "person",
        "equipment"
    ],
    "wof:name":"Con-Serv Corporation (Aust) Pty Ltd",
    "wof:placetype":"venue"
},
  "geometry": {"coordinates":[153.03007500000001,-27.398766],"type":"Point"}
}