{
  "type": "Feature",
  "properties": {
    "iso:country":"AU",
    "sg:address":"U1/ 401 Oxford St",
    "sg:city":"Mt Hawthorn",
    "sg:classifiers":[
        {
            "category":"Personal",
            "subcategory":"Barber",
            "type":"Services"
        }
    ],
    "sg:phone":"+61 8 9444 2040",
    "sg:postcode":"6016",
    "sg:province":"WA",
    "wof:name":"Top Guys Mens Hair Fashion",
    "wof:placetype":"venue"
},
  "geometry": {"coordinates":[115.841392517,-31.9235515594],"type":"Point"}
}