{
  "type": "Feature",
  "properties": {
    "addr:full":"Level 49, 120 Collins St Melbourne VIC 3000",
    "addr:housenumber":"120",
    "addr:postcode":"3000",
    "addr:street":"Collins St",
    "iso:country":"AU",
    "sg:address":"Level 49, 120 Collins St",
    "sg:city":"Melbourne",
    "sg:classifiers":[
        {
            "category":"Professional",
            "subcategory":"Management & Consulting",
            "type":"Services"
        }
    ],
    "sg:phone":"+61 3 9656 8240",
    "sg:postcode":"3000",
    "sg:province":"VIC",
    "sg:tags":[
        "consultant"
    ],
    "wof:name":"USWeb/CKS",
    "wof:placetype":"venue"
},
  "geometry": {"coordinates":[144.96966552699999,-37.8144378662],"type":"Point"}
}