{
  "type": "Feature",
  "properties": {
    "addr:full":"23 Bligh Pl Lake Cathie NSW 2445",
    "addr:housenumber":"23",
    "addr:postcode":"2445",
    "addr:street":"Bligh Pl Lake",
    "iso:country":"AU",
    "sg:address":"23 Bligh Pl",
    "sg:city":"Lake Cathie",
    "sg:classifiers":[
        {
            "category":"Home & Garden",
            "subcategory":"Carpets & Floor Coverings",
            "type":"Retail Goods"
        }
    ],
    "sg:phone":"+61 2 6586 3273",
    "sg:postcode":"2445",
    "sg:province":"NSW",
    "sg:tags":[
        "wood"
    ],
    "wof:name":"Total Floor Finishes",
    "wof:placetype":"venue"
},
  "geometry": {"coordinates":[152.84515400000001,-31.561337],"type":"Point"}
}