{
  "type": "Feature",
  "properties": {
    "addr:full":"10 Stone St Stafford QLD 4053",
    "addr:housenumber":"10",
    "addr:postcode":"4053",
    "addr:street":"Stone St",
    "iso:country":"AU",
    "sg:address":"10 Stone St",
    "sg:city":"Stafford",
    "sg:classifiers":[
        {
            "category":"Retail",
            "subcategory":"Auto Repair",
            "type":"Services"
        }
    ],
    "sg:phone":"+61 7 3356 2422",
    "sg:postcode":"4053",
    "sg:province":"QLD",
    "sg:tags":[
        "engine",
        "reconditioning"
    ],
    "sg:website":"http://www.enginesdirect.com.au",
    "wof:name":"Engines Direct",
    "wof:placetype":"venue"
},
  "geometry": {"coordinates":[153.01464843799999,-27.4167804718],"type":"Point"}
}