{
  "type": "Feature",
  "properties": {
    "addr:full":"Cnr Aitken Rd & Westwood Drv Bowral NSW 2576",
    "addr:postcode":"2576",
    "addr:street":"Cnr Aitken Rd & Westwood Drv",
    "iso:country":"AU",
    "sg:address":"Cnr Aitken Rd & Westwood Drv",
    "sg:city":"Bowral",
    "sg:classifiers":[
        {
            "category":"Personal",
            "subcategory":"Massage",
            "type":"Services"
        }
    ],
    "sg:phone":"+61 2 4861 3744",
    "sg:postcode":"2576",
    "sg:province":"NSW",
    "sg:tags":[
        "therapy"
    ],
    "wof:name":"Massage At Annesley",
    "wof:placetype":"venue"
},
  "geometry": {"coordinates":[150.42486572300001,-34.4891624451],"type":"Point"}
}