{
  "type": "Feature",
  "properties": {
    "addr:full":"1A Edwardes St Burnie TAS 7320",
    "addr:housenumber":"1a",
    "addr:postcode":"7320",
    "addr:street":"Edwardes St",
    "iso:country":"AU",
    "sg:address":"1A Edwardes St",
    "sg:city":"Burnie",
    "sg:classifiers":[
        {
            "category":"Wholesale",
            "subcategory":"Electrical",
            "type":"Manufacturing & Wholesale Goods"
        }
    ],
    "sg:phone":"+61 3 6431 9844",
    "sg:postcode":"7320",
    "sg:province":"TAS",
    "sg:tags":[
        "wholesaler"
    ],
    "wof:name":"AWM Electrical",
    "wof:placetype":"venue"
},
  "geometry": {"coordinates":[145.91000399999999,-41.059361],"type":"Point"}
}