{
  "type": "Feature",
  "properties": {
    "iso:country":"AU",
    "sg:address":"61 Renwick St",
    "sg:city":"Redfern",
    "sg:classifiers":[
        {
            "category":"Professional",
            "type":"Services"
        }
    ],
    "sg:phone":"+61 2 9699 5299",
    "sg:postcode":"2016",
    "sg:province":"NSW",
    "sg:tags":[
        "forwarding",
        "agent",
        "transport"
    ],
    "wof:name":"OBM Pty Ltd",
    "wof:placetype":"venue"
},
  "geometry": {"coordinates":[151.20184326200001,-33.8909988403],"type":"Point"}
}