{
  "type": "Feature",
  "properties": {
    "addr:full":"suite 7 52 Burelli St Wollongong NSW 2500",
    "addr:housenumber":"52",
    "addr:postcode":"2500",
    "addr:street":"Burelli St",
    "iso:country":"AU",
    "sg:address":"suite 7 52 Burelli St",
    "sg:city":"Wollongong",
    "sg:classifiers":[
        {
            "category":"Shopping",
            "subcategory":"Clothing, Apparel, & Fashions",
            "type":"Retail Goods"
        }
    ],
    "sg:phone":"+61 2 4228 4464",
    "sg:postcode":"2500",
    "sg:province":"NSW",
    "sg:tags":[
        "wholesaler",
        "children's",
        "mfrs",
        "wear"
    ],
    "wof:name":"Petit Aussie",
    "wof:placetype":"venue"
},
  "geometry": {"coordinates":[150.896942,-34.426426],"type":"Point"}
}