{
  "type": "Feature",
  "properties": {
    "addr:full":"103 Great North Rd Five Dock NSW 2046",
    "addr:housenumber":"103",
    "addr:postcode":"2046",
    "addr:street":"Great North Rd",
    "iso:country":"AU",
    "sg:address":"103 Great North Rd",
    "sg:city":"Five Dock",
    "sg:classifiers":[
        {
            "category":"Banks & Credit Unions",
            "subcategory":"Bank",
            "type":"Services"
        }
    ],
    "sg:phone":"+61 13 33 30",
    "sg:postcode":"2046",
    "sg:province":"NSW",
    "wof:name":"St.George Bank Limited",
    "wof:placetype":"venue"
},
  "geometry": {"coordinates":[151.12930299999999,-33.869389],"type":"Point"}
}