{
  "type": "Feature",
  "properties": {
    "addr:full":"PO Box 1077 Dunsborough WA 6281",
    "addr:postcode":"6281",
    "iso:country":"AU",
    "sg:address":"PO Box 1077",
    "sg:city":"Dunsborough",
    "sg:classifiers":[
        {
            "category":"Building & Trades",
            "subcategory":"Construction",
            "type":"Services"
        }
    ],
    "sg:phone":"+61 412 088 630",
    "sg:postcode":"6281",
    "sg:province":"WA",
    "sg:tags":[
        "joiner",
        "carpenter"
    ],
    "wof:name":"CDH Enterprises WA Pty Ltd",
    "wof:placetype":"venue"
},
  "geometry": {"coordinates":[115.102020264,-33.6174812317],"type":"Point"}
}