{
  "type": "Feature",
  "properties": {
    "iso:country":"AU",
    "sg:address":"KPT32 Riverton Forum Sho Cntr",
    "sg:city":"Riverton",
    "sg:classifiers":[
        {
            "category":"Building & Trades",
            "subcategory":"Locksmith",
            "type":"Services"
        }
    ],
    "sg:phone":"+61 8 9354 1978",
    "sg:postcode":"6148",
    "sg:province":"WA",
    "sg:tags":[
        "lock"
    ],
    "wof:name":"Mister Minit",
    "wof:placetype":"venue"
},
  "geometry": {"coordinates":[115.903549,-32.039619],"type":"Point"}
}