{
  "type": "Feature",
  "properties": {
    "iso:country":"AU",
    "sg:address":"325 Sydney Rd",
    "sg:city":"Balgowlah",
    "sg:classifiers":[
        {
            "category":"Health Services",
            "subcategory":"Health Practitioner",
            "type":"Services"
        }
    ],
    "sg:phone":"+61 2 9948 1600",
    "sg:postcode":"2093",
    "sg:province":"NSW",
    "sg:tags":[
        "acupuncture"
    ],
    "wof:name":"Edwards Paul & Scott Melissa",
    "wof:placetype":"venue"
},
  "geometry": {"coordinates":[151.265136719,-33.7944946289],"type":"Point"}
}