{
  "type": "Feature",
  "properties": {
    "addr:full":"41 George St Norwood SA 5067",
    "addr:housenumber":"41",
    "addr:postcode":"5067",
    "addr:street":"George St",
    "iso:country":"AU",
    "sg:address":"41 George St",
    "sg:city":"Norwood",
    "sg:classifiers":[
        {
            "category":"Health Services",
            "subcategory":"Doctor",
            "type":"Services"
        }
    ],
    "sg:phone":"+61 8 8332 1428",
    "sg:postcode":"5067",
    "sg:province":"SA",
    "sg:tags":[
        "medical",
        "practitioner"
    ],
    "wof:name":"Varvounis G N",
    "wof:placetype":"venue"
},
  "geometry": {"coordinates":[138.636352539,-34.9198608398],"type":"Point"}
}