{
  "type": "Feature",
  "properties": {
    "iso:country":"AU",
    "sg:address":"43 Shellcove Rd",
    "sg:city":"Neutral Bay",
    "sg:classifiers":[
        {
            "category":"Autos & Motor Vehicles",
            "subcategory":"Boat Sales",
            "type":"Retail Goods"
        }
    ],
    "sg:phone":"+61 2 9953 6152",
    "sg:postcode":"2089",
    "sg:province":"NSW",
    "sg:tags":[
        "designer",
        "yacht",
        "plan"
    ],
    "wof:name":"Boden Boat Plans",
    "wof:placetype":"venue"
},
  "geometry": {"coordinates":[151.22363281200001,-33.8396644592],"type":"Point"}
}