{
  "type": "Feature",
  "properties": {
    "addr:full":"1852- 1858 Malvern Rd Malvern East VIC 3145",
    "addr:housenumber":"1852 1858",
    "addr:postcode":"3145",
    "addr:street":"Malvern Rd",
    "iso:country":"AU",
    "sg:address":"1852- 1858 Malvern Rd",
    "sg:city":"Malvern East",
    "sg:classifiers":[
        {
            "category":"Retail",
            "subcategory":"Auto Repair",
            "type":"Services"
        }
    ],
    "sg:phone":"+61 3 9572 4800",
    "sg:postcode":"3145",
    "sg:province":"VIC",
    "sg:tags":[
        "beater",
        "painter",
        "panel"
    ],
    "wof:name":"Woods Accident Repair Centres",
    "wof:placetype":"venue"
},
  "geometry": {"coordinates":[145.06129455600001,-37.8703231812],"type":"Point"}
}