{
  "type": "Feature",
  "properties": {
    "iso:country":"AU",
    "sg:address":"30 Darobaoo Drv",
    "sg:city":"Cootharaba",
    "sg:classifiers":[
        {
            "category":"Recreation",
            "subcategory":"Fishing",
            "type":"Entertainment"
        }
    ],
    "sg:phone":"+61 7 5485 3480",
    "sg:postcode":"4565",
    "sg:province":"QLD",
    "sg:tags":[
        "tackle"
    ],
    "wof:name":"Land&#039;em Products",
    "wof:placetype":"venue"
},
  "geometry": {"coordinates":[152.952224731,-26.3203601837],"type":"Point"}
}