{
  "type": "Feature",
  "properties": {
    "iso:country":"AU",
    "sg:address":"198 Bridge St",
    "sg:city":"Muswellbrook",
    "sg:classifiers":[
        {
            "category":"Utilities",
            "subcategory":"Water",
            "type":"Services"
        }
    ],
    "sg:phone":"+61 2 6543 4211",
    "sg:postcode":"2333",
    "sg:province":"NSW",
    "sg:tags":[
        "hot",
        "system"
    ],
    "wof:name":"Betta Electrical",
    "wof:placetype":"venue"
},
  "geometry": {"coordinates":[150.888504028,-32.2638626099],"type":"Point"}
}