{
  "type": "Feature",
  "properties": {
    "iso:country":"AU",
    "sg:address":"PO Box 1819",
    "sg:city":"Byron Bay",
    "sg:classifiers":[
        {
            "category":"Professional",
            "subcategory":"Art Services",
            "type":"Services"
        }
    ],
    "sg:phone":"+61 421 724 255",
    "sg:postcode":"2481",
    "sg:province":"NSW",
    "sg:tags":[
        "decorator",
        "painter"
    ],
    "wof:name":"Eco Applications",
    "wof:placetype":"venue"
},
  "geometry": {"coordinates":[153.612823486,-28.6468906403],"type":"Point"}
}