{
  "type": "Feature",
  "properties": {
    "iso:country":"AU",
    "sg:address":"63 Golden Hind Ave",
    "sg:city":"Cooloola Cove",
    "sg:classifiers":[
        {
            "category":"Manufacturing",
            "subcategory":"Jewelry",
            "type":"Manufacturing & Wholesale Goods"
        }
    ],
    "sg:phone":"+61 429 994 441",
    "sg:postcode":"4580",
    "sg:province":"QLD",
    "sg:tags":[
        "mfrg",
        "jeweller"
    ],
    "wof:name":"Arthy David",
    "wof:placetype":"venue"
},
  "geometry": {"coordinates":[152.98577880900001,-25.9735298157],"type":"Point"}
}