{
  "type": "Feature",
  "properties": {
    "addr:full":"Shop 1 Central Drv Robina QLD 4226",
    "addr:housenumber":"shop 1",
    "addr:postcode":"4226",
    "addr:street":"Central Drv",
    "iso:country":"AU",
    "sg:address":"Shop 1 Central Drv",
    "sg:city":"Robina",
    "sg:classifiers":[
        {
            "category":"Fast Food",
            "type":"Food & Drink"
        }
    ],
    "sg:phone":"+61 7 5593 2680",
    "sg:postcode":"4226",
    "sg:province":"QLD",
    "sg:tags":[
        "away",
        "take"
    ],
    "wof:name":"Subway Sandwiches & Salads",
    "wof:placetype":"venue"
},
  "geometry": {"coordinates":[153.41192626899999,-28.0765514374],"type":"Point"}
}