{
  "type": "Feature",
  "properties": {
    "addr:full":"Shp 110/ Henry Parry Drv Gosford NSW 2250",
    "addr:housenumber":"110 / henry",
    "addr:postcode":"2250",
    "addr:street":"Parry Drv",
    "iso:country":"AU",
    "sg:address":"Shp 110/ Henry Parry Drv",
    "sg:city":"Gosford",
    "sg:classifiers":[
        {
            "category":"Shopping",
            "subcategory":"Clothing, Apparel, & Fashions",
            "type":"Retail Goods"
        }
    ],
    "sg:phone":"+61 2 4322 7924",
    "sg:postcode":"2250",
    "sg:province":"NSW",
    "sg:tags":[
        "lady",
        "wear"
    ],
    "wof:name":"Just Gorgeous",
    "wof:placetype":"venue"
},
  "geometry": {"coordinates":[151.344146728,-33.4268112183],"type":"Point"}
}