{
  "type": "Feature",
  "properties": {
    "addr:full":"745 Rochedale Rd Rochedale QLD 4123",
    "addr:housenumber":"745",
    "addr:postcode":"4123",
    "addr:street":"Rochedale Rd",
    "iso:country":"AU",
    "sg:address":"745 Rochedale Rd",
    "sg:city":"Rochedale",
    "sg:classifiers":[
        {
            "category":"Education",
            "subcategory":"School",
            "type":"Public Place"
        }
    ],
    "sg:phone":"+61 7 3340 8888",
    "sg:postcode":"4123",
    "sg:province":"QLD",
    "wof:name":"Redeemer Lutheran College",
    "wof:placetype":"venue"
},
  "geometry": {"coordinates":[153.123901367,-27.5864276886],"type":"Point"}
}