{
  "type": "Feature",
  "properties": {
    "iso:country":"AU",
    "sg:address":"Shop 7 Camberwell Arcade 600- 606 Burke Rd",
    "sg:city":"Camberwell",
    "sg:classifiers":[
        {
            "category":"Personal",
            "subcategory":"Beauty Salon",
            "type":"Services"
        }
    ],
    "sg:phone":"+61 3 9804 0444",
    "sg:postcode":"3124",
    "sg:province":"VIC",
    "sg:tags":[
        "hairdresser"
    ],
    "wof:name":"Romano's Hairdressing",
    "wof:placetype":"venue"
},
  "geometry": {"coordinates":[145.05711364699999,-37.8299865723],"type":"Point"}
}