{
  "type": "Feature",
  "properties": {
    "iso:country":"AU",
    "sg:address":"2/ 57 Moxon Rd",
    "sg:city":"Punchbowl",
    "sg:classifiers":[
        {
            "category":"Home & Garden",
            "subcategory":"Carpets & Floor Coverings",
            "type":"Retail Goods"
        }
    ],
    "sg:phone":"+61 2 9793 2001",
    "sg:postcode":"2196",
    "sg:province":"NSW",
    "sg:tags":[
        "tile",
        "wall"
    ],
    "wof:name":"S & N Bros Marble & Granite Slab Wholesalers",
    "wof:placetype":"venue"
},
  "geometry": {"coordinates":[151.043427,-33.937424],"type":"Point"}
}