{
  "type": "Feature",
  "properties": {
    "addr:full":"42 Knapman St Port Pirie SA 5540",
    "addr:housenumber":"42",
    "addr:postcode":"5540",
    "addr:street":"Knapman St",
    "iso:country":"AU",
    "sg:address":"42 Knapman St",
    "sg:city":"Port Pirie",
    "sg:classifiers":[
        {
            "category":"Personal",
            "subcategory":"Beauty Salon",
            "type":"Services"
        }
    ],
    "sg:phone":"+61 8 8632 3937",
    "sg:postcode":"5540",
    "sg:province":"SA",
    "wof:name":"Hair Flair",
    "wof:placetype":"venue"
},
  "geometry": {"coordinates":[138.00978088400001,-33.2001838684],"type":"Point"}
}