{
  "type": "Feature",
  "properties": {
    "addr:full":"PO Box 29 Diggers Rest VIC 3427",
    "addr:postcode":"3427",
    "iso:country":"AU",
    "sg:address":"PO Box 29",
    "sg:city":"Diggers Rest",
    "sg:classifiers":[
        {
            "category":"Building & Trades",
            "subcategory":"Locksmith",
            "type":"Services"
        }
    ],
    "sg:phone":"+61 417 853 383",
    "sg:postcode":"3427",
    "sg:province":"VIC",
    "sg:tags":[
        "lock"
    ],
    "wof:name":"PMB Locksmiths",
    "wof:placetype":"venue"
},
  "geometry": {"coordinates":[144.70118713400001,-37.6138801575],"type":"Point"}
}