{
  "type": "Feature",
  "properties": {
    "addr:full":"18 Evans St Goolwa Beach SA 5214",
    "addr:housenumber":"18",
    "addr:postcode":"5214",
    "addr:street":"Evans St",
    "iso:country":"AU",
    "sg:address":"18 Evans St",
    "sg:city":"Goolwa Beach",
    "sg:classifiers":[
        {
            "category":"Professional",
            "subcategory":"Printing & Photocopies",
            "type":"Services"
        }
    ],
    "sg:phone":"+61 8 8555 1640",
    "sg:postcode":"5214",
    "sg:province":"SA",
    "sg:tags":[
        "trophy"
    ],
    "wof:name":"M & M Trophies",
    "wof:placetype":"venue"
},
  "geometry": {"coordinates":[138.77401733400001,-35.5108261108],"type":"Point"}
}