{
  "type": "Feature",
  "properties": {
    "addr:full":"PO Box 174 Epping VIC 3076",
    "addr:postcode":"3076",
    "iso:country":"AU",
    "sg:address":"PO Box 174",
    "sg:city":"Epping",
    "sg:classifiers":[
        {
            "category":"Building & Trades",
            "subcategory":"Landscaping Services",
            "type":"Services"
        }
    ],
    "sg:phone":"+61 412 333 119",
    "sg:postcode":"3076",
    "sg:province":"VIC",
    "sg:tags":[
        "designer",
        "landscape",
        "contractor"
    ],
    "wof:name":"AP Earthscapes",
    "wof:placetype":"venue"
},
  "geometry": {"coordinates":[145.009490967,-37.6383590698],"type":"Point"}
}