{
  "type": "Feature",
  "properties": {
    "iso:country":"AU",
    "sg:address":"42 Leslie St",
    "sg:city":"East Ipswich",
    "sg:classifiers":[
        {
            "category":"Professional",
            "subcategory":"Art Services",
            "type":"Services"
        }
    ],
    "sg:phone":"+61 7 3812 9229",
    "sg:postcode":"4305",
    "sg:province":"QLD",
    "sg:tags":[
        "graphic",
        "designer"
    ],
    "wof:name":"Dexrix Web Design",
    "wof:placetype":"venue"
},
  "geometry": {"coordinates":[152.77619934099999,-27.6031150818],"type":"Point"}
}