{
  "type": "Feature",
  "properties": {
    "addr:full":"Suite 303, 55 Lime St, King St Wharf Sydney NSW 2000",
    "addr:housenumber":"55",
    "addr:postcode":"2000",
    "addr:street":"Lime St King St",
    "iso:country":"AU",
    "sg:address":"Suite 303, 55 Lime St, King St",
    "sg:city":"Wharf Sydney",
    "sg:classifiers":[
        {
            "category":"Professional",
            "subcategory":"Employment Agencies",
            "type":"Services"
        }
    ],
    "sg:phone":"+61 2 8270 7500",
    "sg:postcode":"2000",
    "sg:province":"NSW",
    "wof:name":"Radar Recruitment",
    "wof:placetype":"venue"
},
  "geometry": {"coordinates":[151.20187377900001,-33.8686485291],"type":"Point"}
}