{
  "type": "Feature",
  "properties": {
    "addr:full":"Shop 157 Bayside North Shopng Cntr Beach St Frankston VIC 3199",
    "addr:housenumber":"157",
    "addr:postcode":"3199",
    "addr:street":"Bayside North Shopng Cntr Beach St",
    "iso:country":"AU",
    "sg:address":"Shop 157 Bayside North Shopng Cntr Beach St",
    "sg:city":"Frankston",
    "sg:classifiers":[
        {
            "category":"Cafe",
            "type":"Food & Drink"
        }
    ],
    "sg:phone":"+61 3 9769 6830",
    "sg:postcode":"3199",
    "sg:province":"VIC",
    "wof:name":"Gloria Jean's Coffees",
    "wof:placetype":"venue"
},
  "geometry": {"coordinates":[145.12179565400001,-38.1415710449],"type":"Point"}
}