{
  "type": "Feature",
  "properties": {
    "iso:country":"AU",
    "sg:address":"`Bilagal' 55 Whiteley Rd",
    "sg:city":"Oberon",
    "sg:classifiers":[
        {
            "category":"Professional",
            "subcategory":"Management & Consulting",
            "type":"Services"
        }
    ],
    "sg:phone":"+61 2 6336 0239",
    "sg:postcode":"2787",
    "sg:province":"NSW",
    "sg:tags":[
        "consultant",
        "economic"
    ],
    "wof:name":"Economic Strategies Pty Ltd",
    "wof:placetype":"venue"
},
  "geometry": {"coordinates":[149.89613342300001,-33.7309265137],"type":"Point"}
}