{
  "type": "Feature",
  "properties": {
    "addr:full":"Lvl 1, 91 Northbourne Ave Turner ACT 2612",
    "addr:housenumber":"91",
    "addr:postcode":"2612",
    "addr:street":"Northbourne Ave",
    "iso:country":"AU",
    "sg:address":"Lvl 1, 91 Northbourne Ave",
    "sg:city":"Turner",
    "sg:classifiers":[
        {
            "category":"Professional",
            "subcategory":"Management & Consulting",
            "type":"Services"
        }
    ],
    "sg:phone":"+61 2 6229 9600",
    "sg:postcode":"2612",
    "sg:province":"ACT",
    "sg:tags":[
        "consultant",
        "economic"
    ],
    "wof:name":"URS Australia",
    "wof:placetype":"venue"
},
  "geometry": {"coordinates":[149.12974548299999,-35.2727394104],"type":"Point"}
}