{
  "type": "Feature",
  "properties": {
    "addr:full":"6 Hare St Echuca VIC 3564",
    "addr:housenumber":"6",
    "addr:postcode":"3564",
    "addr:street":"Hare St",
    "iso:country":"AU",
    "sg:address":"6 Hare St",
    "sg:city":"Echuca",
    "sg:classifiers":[
        {
            "category":"Retail",
            "subcategory":"Auto Repair",
            "type":"Services"
        }
    ],
    "sg:phone":"+61 3 5480 2677",
    "sg:postcode":"3564",
    "sg:province":"VIC",
    "sg:tags":[
        "muffler",
        "exhaust",
        "system"
    ],
    "wof:name":"Echuca Exhaust Centre",
    "wof:placetype":"venue"
},
  "geometry": {"coordinates":[144.75291442899999,-36.1403121948],"type":"Point"}
}