{
  "type": "Feature",
  "properties": {
    "addr:full":"615 Mt Pleasant Rd Research VIC 3095",
    "addr:housenumber":"615",
    "addr:postcode":"3095",
    "addr:street":"Mt Pleasant Rd",
    "iso:country":"AU",
    "sg:address":"615 Mt Pleasant Rd",
    "sg:city":"Research",
    "sg:classifiers":[
        {
            "category":"Building & Trades",
            "subcategory":"Plumbing",
            "type":"Services"
        }
    ],
    "sg:phone":"+61 3 9437 1285",
    "sg:postcode":"3095",
    "sg:province":"VIC",
    "sg:tags":[
        "plumber",
        "gasfitters"
    ],
    "wof:name":"Clear Water Plumbing",
    "wof:placetype":"venue"
},
  "geometry": {"coordinates":[145.192230225,-37.7147026062],"type":"Point"}
}