{
  "type": "Feature",
  "properties": {
    "addr:full":"Petrie Medical Centre 4 Dayboro Rd Petrie QLD 4502",
    "addr:housenumber":"4",
    "addr:postcode":"4502",
    "addr:street":"Dayboro Rd",
    "iso:country":"AU",
    "sg:address":"Petrie Medical Centre 4 Dayboro Rd",
    "sg:city":"Petrie",
    "sg:classifiers":[
        {
            "category":"Health Services",
            "subcategory":"Doctor",
            "type":"Services"
        }
    ],
    "sg:phone":"+61 7 3285 5311",
    "sg:postcode":"4502",
    "sg:province":"QLD",
    "sg:tags":[
        "medical",
        "practitioner"
    ],
    "wof:name":"Hansen B W",
    "wof:placetype":"venue"
},
  "geometry": {"coordinates":[152.974487305,-27.2682857513],"type":"Point"}
}