{
  "type": "Feature",
  "properties": {
    "iso:country":"AU",
    "sg:address":"24 Ramsay Rd",
    "sg:city":"Five Dock",
    "sg:classifiers":[
        {
            "category":"Education",
            "subcategory":"Music School",
            "type":"Public Place"
        }
    ],
    "sg:phone":"+61 1300 853 566",
    "sg:postcode":"2046",
    "sg:province":"NSW",
    "sg:tags":[
        "teacher"
    ],
    "wof:name":"My Guitar School",
    "wof:placetype":"venue"
},
  "geometry": {"coordinates":[151.132172,-33.871147],"type":"Point"}
}