{
  "type": "Feature",
  "properties": {
    "addr:full":"158 Duckworth St Garbutt QLD 4814",
    "addr:housenumber":"158",
    "addr:postcode":"4814",
    "addr:street":"Duckworth St",
    "iso:country":"AU",
    "sg:address":"158 Duckworth St",
    "sg:city":"Garbutt",
    "sg:classifiers":[
        {
            "category":"Recreation",
            "subcategory":"Fishing",
            "type":"Entertainment"
        }
    ],
    "sg:phone":"+61 7 4779 8399",
    "sg:postcode":"4814",
    "sg:province":"QLD",
    "sg:tags":[
        "tackle"
    ],
    "wof:name":"Fishing Warehouse",
    "wof:placetype":"venue"
},
  "geometry": {"coordinates":[146.75921600000001,-19.279299],"type":"Point"}
}