{
  "type": "Feature",
  "properties": {
    "addr:full":"Shop 137b Fern St Gerringong NSW 2534",
    "addr:housenumber":"137b",
    "addr:postcode":"2534",
    "addr:street":"Fern St",
    "iso:country":"AU",
    "sg:address":"Shop 137b Fern St",
    "sg:city":"Gerringong",
    "sg:classifiers":[
        {
            "category":"Personal",
            "subcategory":"Massage",
            "type":"Services"
        }
    ],
    "sg:phone":"+61 2 4234 0347",
    "sg:postcode":"2534",
    "sg:province":"NSW",
    "sg:tags":[
        "therapy"
    ],
    "wof:name":"Jindaleespa - Gerringong",
    "wof:placetype":"venue"
},
  "geometry": {"coordinates":[150.82704162600001,-34.7470932007],"type":"Point"}
}