{
  "type": "Feature",
  "properties": {
    "addr:full":"16 Gratten Rd Montrose VIC 3765",
    "addr:housenumber":"16",
    "addr:postcode":"3765",
    "addr:street":"Gratten Rd",
    "iso:country":"AU",
    "sg:address":"16 Gratten Rd",
    "sg:city":"Montrose",
    "sg:classifiers":[
        {
            "category":"Professional",
            "subcategory":"Art Services",
            "type":"Services"
        }
    ],
    "sg:phone":"+61 3 9728 3694",
    "sg:postcode":"3765",
    "sg:province":"VIC",
    "sg:tags":[
        "artist"
    ],
    "wof:name":"Marquardt K H",
    "wof:placetype":"venue"
},
  "geometry": {"coordinates":[145.337234497,-37.8130683899],"type":"Point"}
}