{
  "type": "Feature",
  "properties": {
    "addr:full":"Lvl 1/ 2 Curtis Rd Balmain NSW 2041",
    "addr:housenumber":"/ 2",
    "addr:postcode":"2041",
    "addr:street":"Curtis Rd",
    "iso:country":"AU",
    "sg:address":"Lvl 1/ 2 Curtis Rd",
    "sg:city":"Balmain",
    "sg:classifiers":[
        {
            "category":"Real Estate",
            "subcategory":"Architect",
            "type":"Services"
        }
    ],
    "sg:phone":"+61 2 9555 1655",
    "sg:postcode":"2041",
    "sg:province":"NSW",
    "wof:name":"Atom Design Group Pty Ltd",
    "wof:placetype":"venue"
},
  "geometry": {"coordinates":[151.18414300000001,-33.857971],"type":"Point"}
}