{
  "type": "Feature",
  "properties": {
    "iso:country":"AU",
    "sg:address":"24 Thompson St",
    "sg:city":"Bundeena",
    "sg:classifiers":[
        {
            "category":"Education",
            "subcategory":"Kindergarten",
            "type":"Public Place"
        }
    ],
    "sg:phone":"+61 2 9527 1200",
    "sg:postcode":"2230",
    "sg:province":"NSW",
    "sg:tags":[
        "pre-schools"
    ],
    "wof:name":"Goanna Patch Kindergarten",
    "wof:placetype":"venue"
},
  "geometry": {"coordinates":[151.14584350600001,-34.0838737488],"type":"Point"}
}