{
  "type": "Feature",
  "properties": {
    "addr:full":"202 Creswick Rd Ballarat VIC 3350",
    "addr:housenumber":"202",
    "addr:postcode":"3350",
    "addr:street":"Creswick Rd",
    "iso:country":"AU",
    "sg:address":"202 Creswick Rd",
    "sg:city":"Ballarat",
    "sg:classifiers":[
        {
            "category":"Home & Garden",
            "subcategory":"Garden Supply",
            "type":"Retail Goods"
        }
    ],
    "sg:phone":"+61 3 5332 1040",
    "sg:postcode":"3350",
    "sg:province":"VIC",
    "sg:tags":[
        "landscape"
    ],
    "wof:name":"S&S Outdoor Living",
    "wof:placetype":"venue"
},
  "geometry": {"coordinates":[143.85333299999999,-37.553459],"type":"Point"}
}