{
  "type": "Feature",
  "properties": {
    "addr:full":"193 Waradgery Drv Rowville VIC 3178",
    "addr:housenumber":"193",
    "addr:postcode":"3178",
    "addr:street":"Waradgery Drv",
    "iso:country":"AU",
    "sg:address":"193 Waradgery Drv",
    "sg:city":"Rowville",
    "sg:classifiers":[
        {
            "category":"Professional",
            "type":"Services"
        }
    ],
    "sg:phone":"+61 3 9764 4900",
    "sg:postcode":"3178",
    "sg:province":"VIC",
    "sg:tags":[
        "quality",
        "assurance"
    ],
    "wof:name":"QA/QC Consulting",
    "wof:placetype":"venue"
},
  "geometry": {"coordinates":[145.232025147,-37.9249534607],"type":"Point"}
}