{
  "type": "Feature",
  "properties": {
    "iso:country":"AU",
    "sg:address":"2 Winslow St",
    "sg:city":"Milsons Point",
    "sg:classifiers":[
        {
            "category":"Real Estate",
            "subcategory":"Surveying",
            "type":"Services"
        }
    ],
    "sg:phone":"+61 2 9929 6233",
    "sg:postcode":"2061",
    "sg:province":"NSW",
    "sg:tags":[
        "surveyor",
        "land"
    ],
    "wof:name":"Mason A P",
    "wof:placetype":"venue"
},
  "geometry": {"coordinates":[151.213088989,-33.8452186584],"type":"Point"}
}