{
  "type": "Feature",
  "properties": {
    "iso:country":"AU",
    "sg:address":"Shop 18/ 74",
    "sg:city":"The Corso Manly",
    "sg:classifiers":[
        {
            "category":"Shopping",
            "subcategory":"Beauty & Cosmetics",
            "type":"Retail Goods"
        }
    ],
    "sg:phone":"+61 2 8966 9616",
    "sg:postcode":"2095",
    "sg:province":"NSW",
    "sg:tags":[
        "equipment",
        "salon",
        "supply"
    ],
    "wof:name":"Salus Per Aquum Spa & Beauty Salon",
    "wof:placetype":"venue"
},
  "geometry": {"coordinates":[151.28695678700001,-33.7979469299],"type":"Point"}
}