{
  "type": "Feature",
  "properties": {
    "addr:full":"7 Woolwich Rd Hunters Hill NSW 2110",
    "addr:housenumber":"7",
    "addr:postcode":"2110",
    "addr:street":"Woolwich Rd",
    "iso:country":"AU",
    "sg:address":"7 Woolwich Rd",
    "sg:city":"Hunters Hill",
    "sg:classifiers":[
        {
            "category":"Professional",
            "subcategory":"Computer Services",
            "type":"Services"
        }
    ],
    "sg:phone":"+61 2 9817 8033",
    "sg:postcode":"2110",
    "sg:province":"NSW",
    "sg:tags":[
        "consultant",
        "system"
    ],
    "wof:name":"DFI Consulting Australia Pty Ltd",
    "wof:placetype":"venue"
},
  "geometry": {"coordinates":[151.15687560999999,-33.8380584717],"type":"Point"}
}