{
  "type": "Feature",
  "properties": {
    "addr:full":"78 Currie St Adelaide SA 5000",
    "addr:housenumber":"78",
    "addr:postcode":"5000",
    "addr:street":"Currie St",
    "iso:country":"AU",
    "sg:address":"78 Currie St",
    "sg:city":"Adelaide",
    "sg:classifiers":[
        {
            "category":"Real Estate",
            "subcategory":"Real Estate Agent",
            "type":"Services"
        }
    ],
    "sg:phone":"+61 8 8237 5099",
    "sg:postcode":"5000",
    "sg:province":"SA",
    "wof:name":"Byvan",
    "wof:placetype":"venue"
},
  "geometry": {"coordinates":[138.596755981,-34.9242897034],"type":"Point"}
}