{
  "type": "Feature",
  "properties": {
    "addr:full":"4 Croft St Huntingdale VIC 3166",
    "addr:housenumber":"4",
    "addr:postcode":"3166",
    "addr:street":"Croft St",
    "iso:country":"AU",
    "sg:address":"4 Croft St",
    "sg:city":"Huntingdale",
    "sg:classifiers":[
        {
            "category":"Manufacturing",
            "subcategory":"Printing",
            "type":"Manufacturing & Wholesale Goods"
        }
    ],
    "sg:phone":"+61 3 9563 4588",
    "sg:postcode":"3166",
    "sg:province":"VIC",
    "sg:tags":[
        "wholesaler",
        "mfrs",
        "greeting",
        "card"
    ],
    "wof:name":"Artwrap Pty Ltd",
    "wof:placetype":"venue"
},
  "geometry": {"coordinates":[145.103515625,-37.9079437256],"type":"Point"}
}