{
  "type": "Feature",
  "properties": {
    "addr:full":"Unit 7, 44 Flora St Kirrawee NSW 2232",
    "addr:housenumber":"44",
    "addr:postcode":"2232",
    "addr:street":"Flora St",
    "iso:country":"AU",
    "sg:address":"Unit 7, 44 Flora St",
    "sg:city":"Kirrawee",
    "sg:classifiers":[
        {
            "category":"Retail",
            "subcategory":"Auto Repair",
            "type":"Services"
        }
    ],
    "sg:phone":"+61 2 9545 1915",
    "sg:postcode":"2232",
    "sg:province":"NSW",
    "sg:tags":[
        "repairer",
        "motor",
        "engineer"
    ],
    "wof:name":"Ron Spink Automotive",
    "wof:placetype":"venue"
},
  "geometry": {"coordinates":[151.07148742699999,-34.0338821411],"type":"Point"}
}