{
  "type": "Feature",
  "properties": {
    "addr:full":"Level 11 101 Grenfell St Adelaide SA 5000",
    "addr:housenumber":"101",
    "addr:postcode":"5000",
    "addr:street":"Grenfell St",
    "iso:country":"AU",
    "sg:address":"Level 11 101 Grenfell St",
    "sg:city":"Adelaide",
    "sg:classifiers":[
        {
            "category":"Professional",
            "subcategory":"Engineering",
            "type":"Services"
        }
    ],
    "sg:phone":"+61 8 8228 9200",
    "sg:postcode":"5000",
    "sg:province":"SA",
    "sg:tags":[
        "consulting",
        "engineer"
    ],
    "wof:name":"Lincolne Scott Consulting Engineers",
    "wof:placetype":"venue"
},
  "geometry": {"coordinates":[138.60340881400001,-34.9244155884],"type":"Point"}
}