{
  "type": "Feature",
  "properties": {
    "iso:country":"AU",
    "sg:address":"147 Northcoate St",
    "sg:city":"Brighton",
    "sg:classifiers":[
        {
            "category":"Manufacturing",
            "subcategory":"Food",
            "type":"Manufacturing & Wholesale Goods"
        }
    ],
    "sg:phone":"+61 7 3869 4982",
    "sg:postcode":"4017",
    "sg:province":"QLD",
    "sg:tags":[
        "function",
        "catering"
    ],
    "wof:name":"Bribanes Bbq's To Banquets Catering",
    "wof:placetype":"venue"
},
  "geometry": {"coordinates":[153.060379028,-27.3029518127],"type":"Point"}
}