{
  "type": "Feature",
  "properties": {
    "addr:full":"Caltex Main Rd George Town TAS 7253",
    "addr:postcode":"7253",
    "addr:street":"Main Rd",
    "iso:country":"AU",
    "sg:address":"Caltex Main Rd",
    "sg:city":"George Town",
    "sg:classifiers":[
        {
            "category":"Professional",
            "subcategory":"Art Services",
            "type":"Services"
        }
    ],
    "sg:phone":"+61 3 6382 3430",
    "sg:postcode":"7253",
    "sg:province":"TAS",
    "sg:tags":[
        "decorator",
        "painter"
    ],
    "wof:name":"Art Painting & Signs",
    "wof:placetype":"venue"
},
  "geometry": {"coordinates":[146.82826232900001,-41.106590271],"type":"Point"}
}