{
  "type": "Feature",
  "properties": {
    "addr:full":"239 Oliver Ave Goonellabah NSW 2480",
    "addr:housenumber":"239",
    "addr:postcode":"2480",
    "addr:street":"Oliver Ave",
    "iso:country":"AU",
    "sg:address":"239 Oliver Ave",
    "sg:city":"Goonellabah",
    "sg:classifiers":[
        {
            "category":"Retail",
            "subcategory":"Auto Repair",
            "type":"Services"
        }
    ],
    "sg:phone":"+61 2 6624 4548",
    "sg:postcode":"2480",
    "sg:province":"NSW",
    "sg:tags":[
        "beater",
        "painter",
        "panel"
    ],
    "wof:name":"Gonzo's Panel Beating",
    "wof:placetype":"venue"
},
  "geometry": {"coordinates":[153.34800720199999,-28.8220176697],"type":"Point"}
}