{
  "type": "Feature",
  "properties": {
    "addr:full":"30 Chandlers Crs Malak NT 0812",
    "addr:housenumber":"30",
    "addr:postcode":"nt 0812",
    "addr:street":"Chandlers Crs",
    "iso:country":"AU",
    "sg:address":"30 Chandlers Crs",
    "sg:city":"Malak",
    "sg:classifiers":[
        {
            "category":"Manufacturing",
            "subcategory":"Glass & Minerals",
            "type":"Manufacturing & Wholesale Goods"
        }
    ],
    "sg:phone":"+61 412 527 745",
    "sg:postcode":"0812",
    "sg:province":"NT",
    "sg:tags":[
        "repair",
        "fibreglass",
        "product"
    ],
    "wof:name":"JJ's Fibreglass",
    "wof:placetype":"venue"
},
  "geometry": {"coordinates":[130.90194700000001,-12.39768],"type":"Point"}
}