{
  "type": "Feature",
  "properties": {
    "addr:full":"Corner of Exhibition 2 Fletcher Rd Mt Barker SA 5251",
    "addr:housenumber":"2",
    "addr:postcode":"5251",
    "addr:street":"Corner;Fletcher Rd",
    "iso:country":"AU",
    "sg:address":"Corner of Exhibition 2 Fletcher Rd",
    "sg:city":"Mt Barker",
    "sg:classifiers":[
        {
            "category":"Farming",
            "subcategory":"Nursery",
            "type":"Manufacturing & Wholesale Goods"
        }
    ],
    "sg:phone":"+61 8 8391 1971",
    "sg:postcode":"5251",
    "sg:province":"SA",
    "wof:name":"Mt Barker Woodlots & Wildflower Nursery - Australian Plants",
    "wof:placetype":"venue"
},
  "geometry": {"coordinates":[138.86366272000001,-35.0709838867],"type":"Point"}
}