{
  "type": "Feature",
  "properties": {
    "addr:full":"Suite 1/ 134 Fitzmaurice St Wagga Wagga NSW 2650",
    "addr:housenumber":"/ 134",
    "addr:postcode":"2650",
    "addr:street":"Fitzmaurice St",
    "iso:country":"AU",
    "sg:address":"Suite 1/ 134 Fitzmaurice St",
    "sg:city":"Wagga Wagga",
    "sg:classifiers":[
        {
            "category":"Sports & Exercise",
            "subcategory":"Gym",
            "type":"Entertainment"
        }
    ],
    "sg:phone":"+61 2 6971 7974",
    "sg:postcode":"2650",
    "sg:province":"NSW",
    "sg:tags":[
        "health",
        "fitness"
    ],
    "sg:website":"http://www.curves.com",
    "wof:name":"Curves Wagga Wagga",
    "wof:placetype":"venue"
},
  "geometry": {"coordinates":[147.37384033199999,-35.1143493652],"type":"Point"}
}