{
  "type": "Feature",
  "properties": {
    "iso:country":"AU",
    "sg:address":"12 Rosehill St",
    "sg:city":"Parramatta",
    "sg:classifiers":[
        {
            "category":"Home & Garden",
            "subcategory":"Garden Supply",
            "type":"Retail Goods"
        }
    ],
    "sg:phone":"+61 2 9633 2955",
    "sg:postcode":"2150",
    "sg:province":"NSW",
    "sg:tags":[
        "landscape"
    ],
    "wof:name":"E. Venetos",
    "wof:placetype":"venue"
},
  "geometry": {"coordinates":[150.999099731,-33.8243408203],"type":"Point"}
}