{
  "type": "Feature",
  "properties": {
    "addr:full":"7 Factory St Pomona QLD 4568",
    "addr:housenumber":"7",
    "addr:postcode":"4568",
    "addr:street":"Factory St",
    "iso:country":"AU",
    "sg:address":"7 Factory St",
    "sg:city":"Pomona",
    "sg:classifiers":[
        {
            "category":"Health Services",
            "subcategory":"Health Practitioner",
            "type":"Services"
        }
    ],
    "sg:phone":"+61 7 5485 2556",
    "sg:postcode":"4568",
    "sg:province":"QLD",
    "sg:tags":[
        "psychologist"
    ],
    "wof:name":"Patty Shaw",
    "wof:placetype":"venue"
},
  "geometry": {"coordinates":[152.85697937,-26.3653278351],"type":"Point"}
}