{
  "type": "Feature",
  "properties": {
    "addr:full":"746 Victoria Rd Ermington NSW 2115",
    "addr:housenumber":"746",
    "addr:postcode":"2115",
    "addr:street":"Victoria Rd",
    "iso:country":"AU",
    "sg:address":"746 Victoria Rd",
    "sg:city":"Ermington",
    "sg:classifiers":[
        {
            "category":"Fast Food",
            "type":"Food & Drink"
        }
    ],
    "sg:phone":"+61 2 9874 6660",
    "sg:postcode":"2115",
    "sg:province":"NSW",
    "sg:tags":[
        "away",
        "take"
    ],
    "wof:name":"KFC",
    "wof:placetype":"venue"
},
  "geometry": {"coordinates":[151.088165283,-33.8078269958],"type":"Point"}
}