{
  "type": "Feature",
  "properties": {
    "addr:full":"Ewing Rd Woodridge QLD 4114",
    "addr:postcode":"4114",
    "addr:street":"Ewing Rd",
    "iso:country":"AU",
    "sg:address":"Ewing Rd",
    "sg:city":"Woodridge",
    "sg:classifiers":[
        {
            "category":"Fast Food",
            "type":"Food & Drink"
        }
    ],
    "sg:phone":"+61 7 3808 5469",
    "sg:postcode":"4114",
    "sg:province":"QLD",
    "sg:tags":[
        "away",
        "take"
    ],
    "wof:name":"Ewing Road Takeaway",
    "wof:placetype":"venue"
},
  "geometry": {"coordinates":[153.10952758799999,-27.6287326813],"type":"Point"}
}