{
  "type": "Feature",
  "properties": {
    "addr:full":"Lot 31 Pacific Hwy Coopernook NSW 2426",
    "addr:postcode":"2426",
    "addr:street":"Pacific Hwy",
    "iso:country":"AU",
    "sg:address":"Lot 31 Pacific Hwy",
    "sg:city":"Coopernook",
    "sg:classifiers":[
        {
            "category":"Utilities",
            "subcategory":"Electric",
            "type":"Services"
        }
    ],
    "sg:phone":"+61 2 6556 3157",
    "sg:postcode":"2426",
    "sg:province":"NSW",
    "sg:tags":[
        "electrical",
        "contractor"
    ],
    "wof:name":"Cuneo D J",
    "wof:placetype":"venue"
},
  "geometry": {"coordinates":[152.61187699999999,-31.826172],"type":"Point"}
}