{
  "type": "Feature",
  "properties": {
    "addr:full":"6 Brannigan St Tully QLD 4854",
    "addr:housenumber":"6",
    "addr:postcode":"4854",
    "addr:street":"Brannigan St",
    "iso:country":"AU",
    "sg:address":"6 Brannigan St",
    "sg:city":"Tully",
    "sg:classifiers":[
        {
            "category":"Organizations",
            "subcategory":"Professional Association",
            "type":"Services"
        }
    ],
    "sg:phone":"+61 7 4068 2049",
    "sg:postcode":"4854",
    "sg:province":"QLD",
    "sg:tags":[
        "rural",
        "organisation",
        "production",
        "primary"
    ],
    "wof:name":"Tully & District Show Society",
    "wof:placetype":"venue"
},
  "geometry": {"coordinates":[145.921386719,-17.9311962128],"type":"Point"}
}