{
  "type": "Feature",
  "properties": {
    "addr:full":"Shop 6, Mitcham Shopping Centre 119 Belair Rd, Torrens Park SA 5062",
    "addr:housenumber":"shop 6;119",
    "addr:postcode":"5062",
    "addr:street":"Mitcham Shopping;Belair Rd",
    "iso:country":"AU",
    "sg:address":"Shop 6, Mitcham Shopping Centre 119",
    "sg:city":"Belair Rd, Torrens Park",
    "sg:classifiers":[
        {
            "category":"Building & Trades",
            "subcategory":"Locksmith",
            "type":"Services"
        }
    ],
    "sg:phone":"+61 8 8338 2928",
    "sg:postcode":"5062",
    "sg:province":"SA",
    "sg:tags":[
        "lock"
    ],
    "wof:name":"AAA Locksmiths",
    "wof:placetype":"venue"
},
  "geometry": {"coordinates":[138.60960388199999,-34.9762954712],"type":"Point"}
}