{
  "type": "Feature",
  "properties": {
    "addr:full":"50 Channel Crt Kingston TAS 7050",
    "addr:housenumber":"50",
    "addr:postcode":"7050",
    "addr:street":"Channel Crt",
    "iso:country":"AU",
    "sg:address":"50 Channel Crt",
    "sg:city":"Kingston",
    "sg:classifiers":[
        {
            "category":"Shopping",
            "subcategory":"Jewelry",
            "type":"Retail Goods"
        }
    ],
    "sg:phone":"+61 3 6229 2916",
    "sg:postcode":"7050",
    "sg:province":"TAS",
    "sg:tags":[
        "jeweller"
    ],
    "wof:name":"Bertoz Jewellers",
    "wof:placetype":"venue"
},
  "geometry": {"coordinates":[147.30613700000001,-42.975582],"type":"Point"}
}