{
  "type": "Feature",
  "properties": {
    "addr:full":"Level 29 221 St Georges Terrace Perth WA 6000",
    "addr:housenumber":"221",
    "addr:postcode":"6000",
    "addr:street":"St Georges Terrace",
    "iso:country":"AU",
    "sg:address":"Level 29 221 St Georges Terrace",
    "sg:city":"Perth WA",
    "sg:classifiers":[
        {
            "category":"Professional",
            "subcategory":"Computer Services",
            "type":"Services"
        }
    ],
    "sg:postcode":"6000",
    "sg:tags":[
        "google-enterprise",
        "google-search-appliance",
        "google-apps",
        "google-mini",
        "gsa",
        "google-maps-premier",
        "google-earth-enterprise",
        "google-earth-pro",
        "google-collaboration",
        "postini",
        "google-enterprise-search",
        "google-enterprise-geospatial"
    ],
    "sg:website":"http://www.hedloc.com.au",
    "wof:name":"HEDLOC",
    "wof:placetype":"venue"
},
  "geometry": {"coordinates":[115.849689,-31.968149],"type":"Point"}
}