{
  "type": "Feature",
  "properties": {
    "iso:country":"AU",
    "sg:address":"Suite 1, 289 The Entrance Rd",
    "sg:city":"Erina",
    "sg:classifiers":[
        {
            "category":"Professional",
            "subcategory":"Detective & Security Services",
            "type":"Services"
        }
    ],
    "sg:phone":"+61 2 4367 8266",
    "sg:postcode":"2250",
    "sg:province":"NSW",
    "sg:tags":[
        "consultant",
        "system"
    ],
    "wof:name":"Astral Security & Patrol Services Pty Ltd",
    "wof:placetype":"venue"
},
  "geometry": {"coordinates":[151.39117431599999,-33.4323539734],"type":"Point"}
}