{
  "type": "Feature",
  "properties": {
    "addr:full":"22 Expansion St Molendinar QLD 4214",
    "addr:housenumber":"22",
    "addr:postcode":"4214",
    "addr:street":"Expansion St",
    "iso:country":"AU",
    "sg:address":"22 Expansion St",
    "sg:city":"Molendinar",
    "sg:classifiers":[
        {
            "category":"Professional",
            "type":"Services"
        }
    ],
    "sg:phone":"+61 7 5539 6177",
    "sg:postcode":"4214",
    "sg:province":"QLD",
    "sg:tags":[
        "coating",
        "powder"
    ],
    "wof:name":"Bundall-Nerang Powder Coating & Sandblasting",
    "wof:placetype":"venue"
},
  "geometry": {"coordinates":[153.35679626500001,-27.9775829315],"type":"Point"}
}