{
  "type": "Feature",
  "properties": {
    "addr:full":"9 Lanark St Sellicks Beach SA 5174",
    "addr:housenumber":"9",
    "addr:postcode":"5174",
    "addr:street":"Lanark St",
    "iso:country":"AU",
    "sg:address":"9 Lanark St",
    "sg:city":"Sellicks Beach",
    "sg:phone":"+61 439 550 319",
    "sg:postcode":"5174",
    "sg:province":"SA",
    "wof:name":"Triangle Filtration",
    "wof:placetype":"venue"
},
  "geometry": {"coordinates":[138.469573975,-35.325176239],"type":"Point"}
}