{
  "type": "Feature",
  "properties": {
    "iso:country":"AU",
    "sg:address":"Suite 5 3- 5 Station Rd",
    "sg:city":"Auburn",
    "sg:classifiers":[
        {
            "category":"Professional",
            "subcategory":"Accounting & Tax Preparation",
            "type":"Services"
        }
    ],
    "sg:phone":"+61 2 9649 4417",
    "sg:postcode":"2144",
    "sg:province":"NSW",
    "sg:tags":[
        "accountant",
        "auditor"
    ],
    "wof:name":"Auburn Accounting & Taxation Services",
    "wof:placetype":"venue"
},
  "geometry": {"coordinates":[151.03468322800001,-33.8501358032],"type":"Point"}
}