{
  "type": "Feature",
  "properties": {
    "addr:full":"Mooroondu Rd Thorneside QLD 4158",
    "addr:postcode":"4158",
    "addr:street":"Mooroondu Rd",
    "iso:country":"AU",
    "sg:address":"Mooroondu Rd",
    "sg:city":"Thorneside",
    "sg:classifiers":[
        {
            "category":"Building & Trades",
            "subcategory":"Cleaning & Sanitation",
            "type":"Services"
        }
    ],
    "sg:phone":"+61 417 640 720",
    "sg:postcode":"4158",
    "sg:province":"QLD",
    "sg:tags":[
        "commercial",
        "maintenance"
    ],
    "wof:name":"Speedy Maintenance",
    "wof:placetype":"venue"
},
  "geometry": {"coordinates":[153.203125,-27.4808979034],"type":"Point"}
}