{
  "type": "Feature",
  "properties": {
    "iso:country":"AU",
    "sg:address":"9 Warwick St",
    "sg:city":"Hobart",
    "sg:classifiers":[
        {
            "category":"Real Estate",
            "subcategory":"Surveying",
            "type":"Services"
        }
    ],
    "sg:phone":"+61 412 170 970",
    "sg:postcode":"7000",
    "sg:province":"TAS",
    "sg:tags":[
        "surveyor",
        "land"
    ],
    "wof:name":"Potter D G J",
    "wof:placetype":"venue"
},
  "geometry": {"coordinates":[147.32369995100001,-42.874168396],"type":"Point"}
}