{
  "type": "Feature",
  "properties": {
    "addr:full":"16 Morton Crs Davistown NSW 2251",
    "addr:housenumber":"16",
    "addr:postcode":"2251",
    "addr:street":"Morton Crs",
    "iso:country":"AU",
    "sg:address":"16 Morton Crs",
    "sg:city":"Davistown",
    "sg:classifiers":[
        {
            "category":"Retail",
            "subcategory":"Repair Shop",
            "type":"Services"
        }
    ],
    "sg:phone":"+61 2 4369 3381",
    "sg:postcode":"2251",
    "sg:province":"NSW",
    "sg:tags":[
        "machine",
        "repairs",
        "part",
        "dryer",
        "washing"
    ],
    "wof:name":"Hull John Electrics",
    "wof:placetype":"venue"
},
  "geometry": {"coordinates":[151.36065673799999,-33.4849281311],"type":"Point"}
}