{
  "type": "Feature",
  "properties": {
    "iso:country":"AU",
    "sg:address":"96 Fairy St",
    "sg:city":"Warrnambool",
    "sg:classifiers":[
        {
            "category":"Shopping",
            "subcategory":"Clothing, Apparel, & Fashions",
            "type":"Retail Goods"
        }
    ],
    "sg:phone":"+61 3 5562 2594",
    "sg:postcode":"3280",
    "sg:province":"VIC",
    "sg:tags":[
        "lady",
        "wear"
    ],
    "wof:name":"Gwenyth Louise Fashions",
    "wof:placetype":"venue"
},
  "geometry": {"coordinates":[142.47946167000001,-38.3813438416],"type":"Point"}
}