{
  "type": "Feature",
  "properties": {
    "addr:full":"Lot 567 Laurie St Mt Magnet WA 6638",
    "addr:postcode":"6638",
    "addr:street":"Laurie St Mt Magnet",
    "iso:country":"AU",
    "sg:address":"Lot 567 Laurie St",
    "sg:city":"Mt Magnet",
    "sg:classifiers":[
        {
            "category":"Autos & Motor Vehicles",
            "subcategory":"Auto Supplies",
            "type":"Retail Goods"
        }
    ],
    "sg:phone":"+61 8 9963 4455",
    "sg:postcode":"6638",
    "sg:province":"WA",
    "sg:tags":[
        "tyre"
    ],
    "wof:name":"Murchison Tyre Centre",
    "wof:placetype":"venue"
},
  "geometry": {"coordinates":[117.845413208,-28.0666103363],"type":"Point"}
}