{
  "type": "Feature",
  "properties": {
    "iso:country":"AU",
    "sg:address":"4 Hopkins St",
    "sg:city":"Footscray",
    "sg:classifiers":[
        {
            "category":"Autos & Motor Vehicles",
            "subcategory":"Automobile Sales",
            "type":"Retail Goods"
        }
    ],
    "sg:phone":"+61 3 9689 2944",
    "sg:postcode":"3011",
    "sg:province":"VIC",
    "sg:tags":[
        "car",
        "new"
    ],
    "wof:name":"Le Mans Toyota",
    "wof:placetype":"venue"
},
  "geometry": {"coordinates":[144.90858459500001,-37.8006286621],"type":"Point"}
}