{
  "type": "Feature",
  "properties": {
    "iso:country":"AU",
    "sg:address":"1 Decker Pl",
    "sg:city":"Huntingwood",
    "sg:classifiers":[
        {
            "category":"Professional",
            "subcategory":"Employment Agencies",
            "type":"Services"
        }
    ],
    "sg:phone":"+61 2 8808 3088",
    "sg:postcode":"2148",
    "sg:province":"NSW",
    "wof:name":"Adecco",
    "wof:placetype":"venue"
},
  "geometry": {"coordinates":[150.88497924800001,-33.797794342],"type":"Point"}
}