{
  "type": "Feature",
  "properties": {
    "addr:full":"Unit 6B, 14 Abbott Rd Seven Hills NSW 2147",
    "addr:housenumber":"unit 6b 14",
    "addr:postcode":"2147",
    "addr:street":"Abbott Rd",
    "iso:country":"AU",
    "sg:address":"Unit 6B, 14 Abbott Rd",
    "sg:city":"Seven Hills",
    "sg:classifiers":[
        {
            "category":"Building & Trades",
            "subcategory":"Construction",
            "type":"Services"
        }
    ],
    "sg:phone":"+61 2 9620 5930",
    "sg:postcode":"2147",
    "sg:province":"NSW",
    "sg:tags":[
        "home",
        "air conditioning"
    ],
    "wof:name":"Majestic Air Conditioning Pty Ltd",
    "wof:placetype":"venue"
},
  "geometry": {"coordinates":[150.948455811,-33.767490387],"type":"Point"}
}