{
  "type": "Feature",
  "properties": {
    "iso:country":"AU",
    "sg:address":"Unit 6/ 95 Riverside Pl",
    "sg:city":"Morningside",
    "sg:classifiers":[
        {
            "category":"Wholesale",
            "subcategory":"Furniture",
            "type":"Manufacturing & Wholesale Goods"
        }
    ],
    "sg:phone":"+61 7 3899 0899",
    "sg:postcode":"4170",
    "sg:province":"QLD",
    "sg:tags":[
        "wholesaler",
        "mfrs"
    ],
    "wof:name":"Allstyle Furniture",
    "wof:placetype":"venue"
},
  "geometry": {"coordinates":[153.079803467,-27.4513778687],"type":"Point"}
}