{
  "type": "Feature",
  "properties": {
    "iso:country":"AU",
    "sg:address":"Cnr Thomas St & Gibson Rd",
    "sg:city":"Noosaville",
    "sg:classifiers":[
        {
            "category":"Health Services",
            "subcategory":"Optometrist",
            "type":"Services"
        }
    ],
    "sg:phone":"+61 7 5473 0008",
    "sg:postcode":"4566",
    "sg:province":"QLD",
    "wof:name":"Rostron Steve",
    "wof:placetype":"venue"
},
  "geometry": {"coordinates":[153.061813355,-26.4007301331],"type":"Point"}
}