{
  "type": "Feature",
  "properties": {
    "addr:full":"Shop 3 158 Henley Beach Rd Torrensville SA 5031",
    "addr:housenumber":"shop 3 158",
    "addr:postcode":"5031",
    "addr:street":"Henley Beach Rd",
    "iso:country":"AU",
    "sg:address":"Shop 3 158 Henley Beach Rd",
    "sg:city":"Torrensville",
    "sg:classifiers":[
        {
            "category":"Food & Beverages",
            "subcategory":"Bakery",
            "type":"Retail Goods"
        }
    ],
    "sg:phone":"+61 8 8443 9333",
    "sg:postcode":"5031",
    "sg:province":"SA",
    "sg:tags":[
        "cake",
        "shop",
        "pastry"
    ],
    "wof:name":"Kalymnos Pastries",
    "wof:placetype":"venue"
},
  "geometry": {"coordinates":[138.56341552699999,-34.9238510132],"type":"Point"}
}