{
  "type": "Feature",
  "properties": {
    "iso:country":"AU",
    "sg:address":"PO Box 151",
    "sg:city":"Woodford",
    "sg:classifiers":[
        {
            "category":"Real Estate",
            "subcategory":"Architect",
            "type":"Services"
        }
    ],
    "sg:phone":"+61 500 511 554",
    "sg:postcode":"2778",
    "sg:province":"NSW",
    "sg:tags":[
        "building",
        "designer"
    ],
    "wof:name":"Rod Marjanac",
    "wof:placetype":"venue"
},
  "geometry": {"coordinates":[150.47720336899999,-33.7344589233],"type":"Point"}
}