{
  "type": "Feature",
  "properties": {
    "addr:full":"438 Belgrave-Gembrook Rd Avonsleigh VIC 3782",
    "addr:housenumber":"438",
    "addr:postcode":"3782",
    "addr:street":"Belgrave-Gembrook Rd",
    "iso:country":"AU",
    "sg:address":"438 Belgrave-Gembrook Rd",
    "sg:city":"Avonsleigh",
    "sg:classifiers":[
        {
            "category":"Personal",
            "subcategory":"Beauty Salon",
            "type":"Services"
        }
    ],
    "sg:phone":"+61 3 5968 4539",
    "sg:postcode":"3782",
    "sg:province":"VIC",
    "sg:tags":[
        "hairdresser"
    ],
    "wof:name":"Avonsleigh Hair Barn",
    "wof:placetype":"venue"
},
  "geometry": {"coordinates":[145.468887,-37.921707],"type":"Point"}
}