{
  "type": "Feature",
  "properties": {
    "addr:full":"178 Main Rd Moonah TAS 7009",
    "addr:housenumber":"178",
    "addr:postcode":"7009",
    "addr:street":"Main Rd",
    "iso:country":"AU",
    "sg:address":"178 Main Rd",
    "sg:city":"Moonah",
    "sg:classifiers":[
        {
            "category":"Restaurant",
            "type":"Food & Drink"
        }
    ],
    "sg:phone":"+61 3 6273 2095",
    "sg:postcode":"7009",
    "sg:province":"TAS",
    "wof:name":"China Diner",
    "wof:placetype":"venue"
},
  "geometry": {"coordinates":[147.29132080100001,-42.8419685364],"type":"Point"}
}