{
  "type": "Feature",
  "properties": {
    "addr:full":"2 Dyer Rd Bassendean WA 6054",
    "addr:housenumber":"2",
    "addr:postcode":"6054",
    "addr:street":"Dyer Rd",
    "iso:country":"AU",
    "sg:address":"2 Dyer Rd",
    "sg:city":"Bassendean",
    "sg:classifiers":[
        {
            "category":"Autos & Motor Vehicles",
            "subcategory":"Automobile Sales",
            "type":"Retail Goods"
        }
    ],
    "sg:phone":"+61 8 9377 8400",
    "sg:postcode":"6054",
    "sg:province":"WA",
    "sg:tags":[
        "car",
        "new"
    ],
    "wof:name":"Hyundai Motor Company Australia",
    "wof:placetype":"venue"
},
  "geometry": {"coordinates":[115.937362671,-31.907623291],"type":"Point"}
}