{
  "type": "Feature",
  "properties": {
    "addr:full":"PO Box 3312 Brisbane QLD 4001",
    "addr:postcode":"4001",
    "iso:country":"AU",
    "sg:address":"PO Box 3312",
    "sg:city":"Brisbane",
    "sg:classifiers":[
        {
            "category":"Banks & Credit Unions",
            "subcategory":"Investment Brokerage",
            "type":"Services"
        }
    ],
    "sg:phone":"+61 1300 664 949",
    "sg:postcode":"4001",
    "sg:province":"QLD",
    "sg:tags":[
        "debt",
        "collection"
    ],
    "wof:name":"DIY Debt Collection",
    "wof:placetype":"venue"
},
  "geometry": {"coordinates":[153.02789306599999,-27.4675807953],"type":"Point"}
}