{
  "type": "Feature",
  "properties": {
    "iso:country":"AU",
    "sg:address":"Lvl 2, 40 Chandos St St",
    "sg:city":"Leonards",
    "sg:classifiers":[
        {
            "category":"Professional",
            "subcategory":"Employment Agencies",
            "type":"Services"
        }
    ],
    "sg:phone":"+61 2 9432 3333",
    "sg:postcode":"2065",
    "sg:province":"NSW",
    "wof:name":"Techstaff",
    "wof:placetype":"venue"
},
  "geometry": {"coordinates":[151.196777344,-33.8218841553],"type":"Point"}
}