{
  "type": "Feature",
  "properties": {
    "iso:country":"AU",
    "sg:address":"272 Oxford St",
    "sg:city":"Paddington",
    "sg:classifiers":[
        {
            "category":"Shopping",
            "subcategory":"Clothing, Apparel, & Fashions",
            "type":"Retail Goods"
        }
    ],
    "sg:phone":"+61 2 9361 5333",
    "sg:postcode":"2021",
    "sg:province":"NSW",
    "sg:tags":[
        "lady",
        "wear"
    ],
    "wof:name":"Deborah Hill",
    "wof:placetype":"venue"
},
  "geometry": {"coordinates":[151.22776794399999,-33.8851203918],"type":"Point"}
}