{
  "type": "Feature",
  "properties": {
    "iso:country":"AU",
    "sg:address":"23 Agnes Ave",
    "sg:city":"Queanbeyan",
    "sg:classifiers":[
        {
            "category":"Building & Trades",
            "subcategory":"Landscaping Services",
            "type":"Services"
        }
    ],
    "sg:phone":"+61 417 453 209",
    "sg:postcode":"2620",
    "sg:province":"ACT",
    "sg:tags":[
        "designer",
        "landscape",
        "contractor"
    ],
    "wof:name":"Design Construct",
    "wof:placetype":"venue"
},
  "geometry": {"coordinates":[149.22271728499999,-35.3501091003],"type":"Point"}
}