{
  "type": "Feature",
  "properties": {
    "addr:full":"Aberfoyle St Kenmore QLD 4069",
    "addr:postcode":"4069",
    "addr:street":"Aberfoyle St",
    "iso:country":"AU",
    "sg:address":"Aberfoyle St",
    "sg:city":"Kenmore",
    "sg:classifiers":[
        {
            "category":"Organizations",
            "subcategory":"Professional Association",
            "type":"Services"
        }
    ],
    "sg:phone":"+61 413 997 284",
    "sg:postcode":"4069",
    "sg:province":"QLD",
    "sg:tags":[
        "web",
        "internet"
    ],
    "wof:name":"M&#039;khala",
    "wof:placetype":"venue"
},
  "geometry": {"coordinates":[152.94059753400001,-27.5162601471],"type":"Point"}
}