{
  "type": "Feature",
  "properties": {
    "iso:country":"AU",
    "sg:address":"813 Doncaster Rd",
    "sg:city":"Doncaster",
    "sg:classifiers":[
        {
            "category":"Health Services",
            "subcategory":"Health Practitioner",
            "type":"Services"
        }
    ],
    "sg:phone":"+61 3 9848 4488",
    "sg:postcode":"3108",
    "sg:province":"VIC",
    "sg:tags":[
        "psychologist"
    ],
    "wof:name":"Stevenson Debbi",
    "wof:placetype":"venue"
},
  "geometry": {"coordinates":[145.139404297,-37.7863273621],"type":"Point"}
}