{
  "type": "Feature",
  "properties": {
    "addr:full":"318 Goodwood Rd Clarence Park SA 5034",
    "addr:housenumber":"318",
    "addr:postcode":"5034",
    "addr:street":"Goodwood Rd",
    "iso:country":"AU",
    "sg:address":"318 Goodwood Rd",
    "sg:city":"Clarence Park",
    "sg:classifiers":[
        {
            "category":"Education",
            "subcategory":"Dance Studio",
            "type":"Public Place"
        }
    ],
    "sg:phone":"+61 8 8297 3351",
    "sg:postcode":"5034",
    "sg:province":"SA",
    "sg:tags":[
        "venue",
        "tuition"
    ],
    "wof:name":"Flamenco - Studio Flamenco Performers",
    "wof:placetype":"venue"
},
  "geometry": {"coordinates":[138.59051513700001,-34.9644241333],"type":"Point"}
}