{
  "type": "Feature",
  "properties": {
    "iso:country":"AU",
    "sg:address":"273 Wakefield St",
    "sg:city":"Adelaide",
    "sg:classifiers":[
        {
            "category":"Health Services",
            "subcategory":"Doctor",
            "type":"Services"
        }
    ],
    "sg:phone":"+61 417 141 004",
    "sg:postcode":"5000",
    "sg:province":"SA",
    "sg:tags":[
        "medical",
        "practitioner"
    ],
    "wof:name":"Fischer Dr. T P",
    "wof:placetype":"venue"
},
  "geometry": {"coordinates":[138.611053467,-34.9282989502],"type":"Point"}
}