{
  "type": "Feature",
  "properties": {
    "iso:country":"AU",
    "sg:address":"32 Maritana Rd",
    "sg:city":"Kallaroo",
    "sg:classifiers":[
        {
            "category":"Personal",
            "subcategory":"Beauty Salon",
            "type":"Services"
        }
    ],
    "sg:phone":"+61 412 679 560",
    "sg:postcode":"6025",
    "sg:province":"WA",
    "wof:name":"Peta's Total Body Care",
    "wof:placetype":"venue"
},
  "geometry": {"coordinates":[115.750991821,-31.7890701294],"type":"Point"}
}