{
  "type": "Feature",
  "properties": {
    "addr:full":"Shop 5,University Hall,281- 285 Parramatta Rd Glebe NSW 2037",
    "addr:housenumber":"shop 5;281 285",
    "addr:postcode":"2037",
    "addr:street":"University;Parramatta Rd",
    "iso:country":"AU",
    "sg:address":"Shop 5,University Hall,281- 285 Parramatta Rd",
    "sg:city":"Glebe",
    "sg:classifiers":[
        {
            "category":"Real Estate",
            "subcategory":"Real Estate Agent",
            "type":"Services"
        }
    ],
    "sg:phone":"+61 2 9660 4155",
    "sg:postcode":"2037",
    "sg:province":"NSW",
    "wof:name":"Australian Property & Management Pty Ltd",
    "wof:placetype":"venue"
},
  "geometry": {"coordinates":[151.19195556599999,-33.884552002],"type":"Point"}
}