{
  "type": "Feature",
  "properties": {
    "addr:full":"13 Lotus St Woolloongabba QLD 4102",
    "addr:housenumber":"13",
    "addr:postcode":"4102",
    "addr:street":"Lotus St",
    "iso:country":"AU",
    "sg:address":"13 Lotus St",
    "sg:city":"Woolloongabba",
    "sg:classifiers":[
        {
            "category":"Professional",
            "subcategory":"Printing & Photocopies",
            "type":"Services"
        }
    ],
    "sg:phone":"+61 7 3391 3409",
    "sg:postcode":"4102",
    "sg:province":"QLD",
    "sg:tags":[
        "screen",
        "printer"
    ],
    "wof:name":"Mack Signs Pty Ltd",
    "wof:placetype":"venue"
},
  "geometry": {"coordinates":[153.040527344,-27.4901714325],"type":"Point"}
}