{
  "type": "Feature",
  "properties": {
    "addr:full":"Ste 109/ 320 Victoria Pde East Melbourne VIC 3002",
    "addr:housenumber":"/ 320",
    "addr:postcode":"3002",
    "addr:street":"Victoria Pde",
    "iso:country":"AU",
    "sg:address":"Ste 109/ 320 Victoria Pde",
    "sg:city":"East Melbourne",
    "sg:classifiers":[
        {
            "category":"Health Services",
            "subcategory":"Doctor",
            "type":"Services"
        }
    ],
    "sg:phone":"+61 3 9419 6619",
    "sg:postcode":"3002",
    "sg:province":"VIC",
    "sg:tags":[
        "medical",
        "practitioner"
    ],
    "wof:name":"Henderson Jeanette",
    "wof:placetype":"venue"
},
  "geometry": {"coordinates":[144.99124145499999,-37.8136367798],"type":"Point"}
}