{
  "type": "Feature",
  "properties": {
    "addr:full":"10/ 2 Ash Rd Prestons NSW 2170",
    "addr:housenumber":"10 / 2",
    "addr:postcode":"2170",
    "addr:street":"Ash Rd",
    "iso:country":"AU",
    "sg:address":"10/ 2 Ash Rd",
    "sg:city":"Prestons",
    "sg:classifiers":[
        {
            "category":"Wholesale",
            "subcategory":"Machinery & Supplies",
            "type":"Manufacturing & Wholesale Goods"
        }
    ],
    "sg:phone":"+61 2 9608 3833",
    "sg:postcode":"2170",
    "sg:province":"NSW",
    "sg:tags":[
        "agricultural"
    ],
    "wof:name":"Bepco Australasia",
    "wof:placetype":"venue"
},
  "geometry": {"coordinates":[150.873214722,-33.9544754028],"type":"Point"}
}