{
  "type": "Feature",
  "properties": {
    "addr:full":"PO Box 605 Greenacre NSW 2190",
    "addr:postcode":"2190",
    "iso:country":"AU",
    "sg:address":"PO Box 605",
    "sg:city":"Greenacre",
    "sg:classifiers":[
        {
            "category":"Shopping",
            "subcategory":"Antiques",
            "type":"Retail Goods"
        }
    ],
    "sg:phone":"+61 2 9758 0400",
    "sg:postcode":"2190",
    "sg:province":"NSW",
    "sg:tags":[
        "collectable",
        "memorabilia"
    ],
    "wof:name":"Fiorano Mania",
    "wof:placetype":"venue"
},
  "geometry": {"coordinates":[151.06634500000001,-33.895401],"type":"Point"}
}