{
  "type": "Feature",
  "properties": {
    "addr:full":"78 Ford St Ganmain NSW 2702",
    "addr:housenumber":"78",
    "addr:postcode":"2702",
    "addr:street":"Ford St",
    "iso:country":"AU",
    "sg:address":"78 Ford St",
    "sg:city":"Ganmain",
    "sg:classifiers":[
        {
            "category":"Professional",
            "subcategory":"Accounting & Tax Preparation",
            "type":"Services"
        }
    ],
    "sg:phone":"+61 2 6927 6161",
    "sg:postcode":"2702",
    "sg:province":"NSW",
    "sg:tags":[
        "accountant",
        "auditor"
    ],
    "wof:name":"Twomey Patterson",
    "wof:placetype":"venue"
},
  "geometry": {"coordinates":[147.03892517099999,-34.7932662964],"type":"Point"}
}