{
  "type": "Feature",
  "properties": {
    "addr:full":"Shop B2 Tenancy 4B (1) 99 Spencer Street Docklands VIC 3008",
    "addr:housenumber":"4b 1 99",
    "addr:postcode":"3008",
    "addr:street":"Tenancy;Spencer Street",
    "iso:country":"AU",
    "sg:address":"Shop B2 Tenancy 4B (1) 99",
    "sg:city":"Spencer Street Docklands",
    "sg:classifiers":[
        {
            "category":"Food & Beverages",
            "subcategory":"Groceries & Convenience Stores",
            "type":"Retail Goods"
        }
    ],
    "sg:phone":"+61 3 9640 0962",
    "sg:postcode":"3008",
    "sg:province":"VIC",
    "wof:name":"7 Eleven Stores Pty Ltd",
    "wof:placetype":"venue"
},
  "geometry": {"coordinates":[144.95370483400001,-37.8184661865],"type":"Point"}
}