{
  "type": "Feature",
  "properties": {
    "iso:country":"AU",
    "sg:address":"2 John St",
    "sg:city":"Dandenong",
    "sg:classifiers":[
        {
            "category":"Manufacturing",
            "subcategory":"Buildings",
            "type":"Manufacturing & Wholesale Goods"
        }
    ],
    "sg:phone":"+61 411 227 640",
    "sg:postcode":"3175",
    "sg:province":"VIC",
    "sg:tags":[
        "transportable",
        "domestic",
        "relocatable"
    ],
    "wof:name":"Paradise Cabins",
    "wof:placetype":"venue"
},
  "geometry": {"coordinates":[145.21739196799999,-37.9985466003],"type":"Point"}
}