{
  "type": "Feature",
  "properties": {
    "addr:full":"23 Park St Bacchus Marsh VIC 3340",
    "addr:housenumber":"23",
    "addr:postcode":"3340",
    "addr:street":"Park St",
    "iso:country":"AU",
    "sg:address":"23 Park St",
    "sg:city":"Bacchus Marsh",
    "sg:classifiers":[
        {
            "category":"Retail",
            "subcategory":"Auto Repair",
            "type":"Services"
        }
    ],
    "sg:phone":"+61 3 5367 6500",
    "sg:postcode":"3340",
    "sg:province":"VIC",
    "sg:tags":[
        "repairer",
        "motor",
        "engineer"
    ],
    "wof:name":"J.F. Motors",
    "wof:placetype":"venue"
},
  "geometry": {"coordinates":[144.44184899999999,-37.686695],"type":"Point"}
}