{
  "type": "Feature",
  "properties": {
    "iso:country":"AU",
    "sg:address":"23 Park St",
    "sg:city":"Bacchus Marsh",
    "sg:classifiers":[
        {
            "category":"Retail",
            "subcategory":"Auto Repair",
            "type":"Services"
        }
    ],
    "sg:phone":"+61 3 5367 6500",
    "sg:postcode":"3340",
    "sg:province":"VIC",
    "sg:tags":[
        "repairer",
        "motor",
        "engineer"
    ],
    "wof:name":"J.F. Motors",
    "wof:placetype":"venue"
},
  "geometry": {"coordinates":[144.441849,-37.686695],"type":"Point"}
}