{
  "type": "Feature",
  "properties": {
    "addr:full":"317a Montague St Albert Park VIC 3206",
    "addr:housenumber":"317a",
    "addr:postcode":"3206",
    "addr:street":"Montague St",
    "iso:country":"AU",
    "sg:address":"317a Montague St",
    "sg:city":"Albert Park",
    "sg:classifiers":[
        {
            "category":"Personal",
            "subcategory":"Beauty Salon",
            "type":"Services"
        }
    ],
    "sg:phone":"+61 3 9696 4332",
    "sg:postcode":"3206",
    "sg:province":"VIC",
    "wof:name":"Absolute Therapy Centre",
    "wof:placetype":"venue"
},
  "geometry": {"coordinates":[144.95611600000001,-37.841244],"type":"Point"}
}