{
  "type": "Feature",
  "properties": {
    "addr:full":"61 Bungary Rd Norah Head NSW 2263",
    "addr:housenumber":"61",
    "addr:postcode":"2263",
    "addr:street":"Bungary Rd",
    "iso:country":"AU",
    "sg:address":"61 Bungary Rd",
    "sg:city":"Norah Head",
    "sg:classifiers":[
        {
            "category":"Building & Trades",
            "subcategory":"Pest Control",
            "type":"Services"
        }
    ],
    "sg:phone":"+61 2 4340 1270",
    "sg:postcode":"2263",
    "sg:province":"NSW",
    "sg:tags":[
        "herbicide",
        "insecticides",
        "fungicide"
    ],
    "wof:name":"A-Bill Pest Services",
    "wof:placetype":"venue"
},
  "geometry": {"coordinates":[151.565414,-33.278179],"type":"Point"}
}