{
  "type": "Feature",
  "properties": {
    "addr:full":"26 Padbury St Esperance WA 6450",
    "addr:housenumber":"26",
    "addr:postcode":"6450",
    "addr:street":"Padbury St",
    "iso:country":"AU",
    "sg:address":"26 Padbury St",
    "sg:city":"Esperance",
    "sg:classifiers":[
        {
            "category":"Retail",
            "subcategory":"Storage",
            "type":"Services"
        }
    ],
    "sg:phone":"+61 8 9071 1614",
    "sg:postcode":"6450",
    "sg:province":"WA",
    "sg:tags":[
        "removal",
        "furniture"
    ],
    "wof:name":"Esperance Removals",
    "wof:placetype":"venue"
},
  "geometry": {"coordinates":[121.885467529,-33.859462738],"type":"Point"}
}