{
  "type": "Feature",
  "properties": {
    "iso:country":"AU",
    "sg:address":"Shop 7-8 418 Bell St",
    "sg:city":"Pascoe Vale South",
    "sg:classifiers":[
        {
            "category":"Autos & Motor Vehicles",
            "subcategory":"Auto Supplies",
            "type":"Retail Goods"
        }
    ],
    "sg:phone":"+61 3 9350 4433",
    "sg:postcode":"3044",
    "sg:province":"VIC",
    "sg:tags":[
        "accessory"
    ],
    "wof:name":"Spoilers Galore Pty Ltd",
    "wof:placetype":"venue"
},
  "geometry": {"coordinates":[144.94427490199999,-37.7388763428],"type":"Point"}
}