{
  "type": "Feature",
  "properties": {
    "addr:full":"Suite 201, Second Floor 250 Pitt St Sydney NSW 2000",
    "addr:housenumber":"250",
    "addr:postcode":"2000",
    "addr:street":"Pitt St",
    "iso:country":"AU",
    "sg:address":"Suite 201, Second Floor 250 Pitt St",
    "sg:city":"Sydney",
    "sg:classifiers":[
        {
            "category":"Recreation",
            "subcategory":"Sailing Club",
            "type":"Entertainment"
        }
    ],
    "sg:phone":"+61 2 9267 7133",
    "sg:postcode":"2000",
    "sg:province":"NSW",
    "sg:tags":[
        "merchant",
        "diamond"
    ],
    "wof:name":"Diamond Traders City",
    "wof:placetype":"venue"
},
  "geometry": {"coordinates":[151.20828247099999,-33.8728370667],"type":"Point"}
}