{
  "type": "Feature",
  "properties": {
    "addr:full":"Lower Level 17 Rosny Mall Rosny Park TAS 7018",
    "addr:housenumber":"17",
    "addr:postcode":"7018",
    "addr:street":"Rosny Mall",
    "iso:country":"AU",
    "sg:address":"Lower Level 17",
    "sg:city":"Rosny Mall Rosny Park",
    "sg:classifiers":[
        {
            "category":"Shopping",
            "subcategory":"Clothing, Apparel, & Fashions",
            "type":"Retail Goods"
        }
    ],
    "sg:phone":"+61 3 6244 2222",
    "sg:postcode":"7018",
    "sg:province":"TAS",
    "sg:tags":[
        "hire",
        "men's",
        "wear",
        "formal"
    ],
    "wof:name":"Hadrills Hire & Alterations",
    "wof:placetype":"venue"
},
  "geometry": {"coordinates":[147.36541748100001,-42.8666763306],"type":"Point"}
}