{
  "type": "Feature",
  "properties": {
    "iso:country":"AU",
    "sg:address":"42 Grafton St",
    "sg:city":"Cairns",
    "sg:classifiers":[
        {
            "category":"Shopping",
            "subcategory":"Optical Goods",
            "type":"Retail Goods"
        }
    ],
    "sg:phone":"+61 7 4031 6164",
    "sg:postcode":"4870",
    "sg:province":"QLD",
    "sg:tags":[
        "dispenser",
        "prescription"
    ],
    "wof:name":"A.J. Hannan Optical Pty Ltd",
    "wof:placetype":"venue"
},
  "geometry": {"coordinates":[145.77163696299999,-16.9189453125],"type":"Point"}
}