{
  "type": "Feature",
  "properties": {
    "iso:country":"AU",
    "sg:address":"16 Gladstone St",
    "sg:city":"Nairne",
    "sg:classifiers":[
        {
            "category":"Professional",
            "subcategory":"Business Services",
            "type":"Services"
        }
    ],
    "sg:phone":"+61 8 8388 0020",
    "sg:postcode":"5252",
    "sg:province":"SA",
    "sg:tags":[
        "broker"
    ],
    "wof:name":"Sweeting & Associates",
    "wof:placetype":"venue"
},
  "geometry": {"coordinates":[138.899200439,-35.0283126831],"type":"Point"}
}