{
  "type": "Feature",
  "properties": {
    "addr:full":"117 Prince St Grafton NSW 2460",
    "addr:housenumber":"117",
    "addr:postcode":"2460",
    "addr:street":"Prince St",
    "iso:country":"AU",
    "sg:address":"117 Prince St",
    "sg:city":"Grafton",
    "sg:classifiers":[
        {
            "category":"Autos & Motor Vehicles",
            "subcategory":"Auto Supplies",
            "type":"Retail Goods"
        }
    ],
    "sg:phone":"+61 2 6642 3085",
    "sg:postcode":"2460",
    "sg:province":"NSW",
    "sg:tags":[
        "accessory"
    ],
    "wof:name":"Hession Auto Accessories",
    "wof:placetype":"venue"
},
  "geometry": {"coordinates":[152.93536376899999,-29.6885318756],"type":"Point"}
}