{
  "type": "Feature",
  "properties": {
    "addr:full":"29 Lacka Wang St Wollongong NSW 2500",
    "addr:housenumber":"29",
    "addr:postcode":"2500",
    "addr:street":"Lacka Wang St",
    "iso:country":"AU",
    "sg:address":"29 Lacka Wang St",
    "sg:city":"Wollongong",
    "sg:classifiers":[
        {
            "category":"Mining & Drilling",
            "type":"Manufacturing & Wholesale Goods"
        }
    ],
    "sg:phone":"+61 418 863 739",
    "sg:postcode":"2500",
    "sg:province":"NSW",
    "sg:tags":[
        "concrete",
        "breaking",
        "grinding",
        "sawing"
    ],
    "wof:name":"ABC Concrete Cutting Services",
    "wof:placetype":"venue"
},
  "geometry": {"coordinates":[150.868088,-34.470306],"type":"Point"}
}