{
  "type": "Feature",
  "properties": {
    "addr:full":"Lvl 1, Ste 1 408 Gladesville Rd Gladesville NSW 2111",
    "addr:housenumber":"408",
    "addr:postcode":"2111",
    "addr:street":"Gladesville Rd",
    "iso:country":"AU",
    "sg:address":"Lvl 1, Ste 1 408 Gladesville Rd",
    "sg:city":"Gladesville",
    "sg:classifiers":[
        {
            "category":"Banks & Credit Unions",
            "subcategory":"Bank",
            "type":"Services"
        }
    ],
    "sg:phone":"+61 1300 886 803",
    "sg:postcode":"2111",
    "sg:province":"NSW",
    "sg:tags":[
        "broker",
        "mortgage"
    ],
    "wof:name":"Mortgage Choice",
    "wof:placetype":"venue"
},
  "geometry": {"coordinates":[151.13856506400001,-33.8328666687],"type":"Point"}
}