{
  "type": "Feature",
  "properties": {
    "addr:full":"&#034;Lilyholes&#034; North Dulacca Rd Bogandilla QLD 4425",
    "addr:postcode":"4425",
    "addr:street":"North Dulacca Rd",
    "iso:country":"AU",
    "sg:address":"&#034;Lilyholes&#034; North Dulacca Rd",
    "sg:city":"Bogandilla",
    "sg:classifiers":[
        {
            "category":"Building & Trades",
            "subcategory":"Landscaping Services",
            "type":"Services"
        }
    ],
    "sg:phone":"+61 7 4627 6316",
    "sg:postcode":"4425",
    "sg:province":"QLD",
    "sg:tags":[
        "grazier"
    ],
    "wof:name":"Rush J B & Sons",
    "wof:placetype":"venue"
},
  "geometry": {"coordinates":[149.78123474099999,-26.5195960999],"type":"Point"}
}