{
  "type": "Feature",
  "properties": {
    "iso:country":"AU",
    "sg:address":"993 South Rd",
    "sg:city":"Melrose Park",
    "sg:phone":"+61 8 8277 8655",
    "sg:postcode":"5039",
    "sg:province":"SA",
    "wof:name":"The Rainwater Tank Centre",
    "wof:placetype":"venue"
},
  "geometry": {"coordinates":[138.57426452600001,-34.9820785522],"type":"Point"}
}