{
  "type": "Feature",
  "properties": {
    "iso:country":"AU",
    "sg:address":"17 Newcastle Drv",
    "sg:city":"Toormina",
    "sg:classifiers":[
        {
            "category":"Manufacturing",
            "subcategory":"Furniture",
            "type":"Manufacturing & Wholesale Goods"
        }
    ],
    "sg:phone":"+61 2 6658 6002",
    "sg:postcode":"2452",
    "sg:province":"NSW",
    "sg:tags":[
        "builder",
        "designer",
        "custom"
    ],
    "wof:name":"Country Clover Collection",
    "wof:placetype":"venue"
},
  "geometry": {"coordinates":[153.091888,-30.36219],"type":"Point"}
}