{
  "type": "Feature",
  "properties": {
    "addr:full":"13 Toonburra St Bundaberg QLD 4670",
    "addr:housenumber":"13",
    "addr:postcode":"4670",
    "addr:street":"Toonburra St",
    "iso:country":"AU",
    "sg:address":"13 Toonburra St",
    "sg:city":"Bundaberg",
    "sg:classifiers":[
        {
            "category":"Wholesale",
            "subcategory":"Machinery & Supplies",
            "type":"Manufacturing & Wholesale Goods"
        }
    ],
    "sg:phone":"+61 7 4152 7611",
    "sg:postcode":"4670",
    "sg:province":"QLD",
    "sg:tags":[
        "equipment",
        "hydraulic"
    ],
    "wof:name":"Berendsen Fluid Power Pty Ltd",
    "wof:placetype":"venue"
},
  "geometry": {"coordinates":[152.35694885300001,-24.8657913208],"type":"Point"}
}