{
  "type": "Feature",
  "properties": {
    "addr:full":"95a Fitzmaurice St Wagga Wagga NSW 2650",
    "addr:housenumber":"95a",
    "addr:postcode":"2650",
    "addr:street":"Fitzmaurice St",
    "iso:country":"AU",
    "sg:address":"95a Fitzmaurice St",
    "sg:city":"Wagga Wagga",
    "sg:classifiers":[
        {
            "category":"Organizations",
            "subcategory":"Professional Association",
            "type":"Services"
        }
    ],
    "sg:phone":"+61 2 6921 3577",
    "sg:postcode":"2650",
    "sg:province":"NSW",
    "sg:tags":[
        "organisation",
        "business"
    ],
    "wof:name":"Chamber of Commerce & Industry",
    "wof:placetype":"venue"
},
  "geometry": {"coordinates":[147.36958313,-35.1051292419],"type":"Point"}
}