{
  "type": "Feature",
  "properties": {
    "iso:country":"AU",
    "sg:address":"12 Huxley Crt",
    "sg:city":"Bayswater",
    "sg:classifiers":[
        {
            "category":"Building & Trades",
            "subcategory":"Construction",
            "type":"Services"
        }
    ],
    "sg:phone":"+61 417 603 739",
    "sg:postcode":"3153",
    "sg:province":"VIC",
    "sg:tags":[
        "polishing",
        "sanding",
        "floor"
    ],
    "wof:name":"Carefree Floors",
    "wof:placetype":"venue"
},
  "geometry": {"coordinates":[145.26252746599999,-37.8576126099],"type":"Point"}
}