{
  "type": "Feature",
  "properties": {
    "addr:full":"46- 50 Freight Drv Somerton VIC 3062",
    "addr:postcode":"3062",
    "addr:street":"Freight Drv",
    "iso:country":"AU",
    "sg:address":"46- 50 Freight Drv",
    "sg:city":"Somerton",
    "sg:classifiers":[
        {
            "category":"Building & Trades",
            "subcategory":"Pest Control",
            "type":"Services"
        }
    ],
    "sg:phone":"+61 3 9308 9688",
    "sg:postcode":"3062",
    "sg:province":"VIC",
    "wof:name":"Animal Control Technologies Pty Ltd",
    "wof:placetype":"venue"
},
  "geometry": {"coordinates":[144.964401245,-37.6404800415],"type":"Point"}
}