{
  "type": "Feature",
  "properties": {
    "iso:country":"AU",
    "sg:address":"52 Macauley St",
    "sg:city":"Williamstown",
    "sg:classifiers":[
        {
            "category":"Building & Trades",
            "subcategory":"Cleaning & Sanitation",
            "type":"Services"
        }
    ],
    "sg:phone":"+61 3 9397 2055",
    "sg:postcode":"3016",
    "sg:province":"VIC",
    "sg:tags":[
        "cleaner",
        "repairer",
        "roof"
    ],
    "wof:name":"Roof Service Company Pty Ltd",
    "wof:placetype":"venue"
},
  "geometry": {"coordinates":[144.86697387699999,-37.8501739502],"type":"Point"}
}