{
  "type": "Feature",
  "properties": {
    "addr:full":"27 Harker St Maldon VIC 3463",
    "addr:housenumber":"27",
    "addr:postcode":"3463",
    "addr:street":"Harker St",
    "iso:country":"AU",
    "sg:address":"27 Harker St",
    "sg:city":"Maldon",
    "sg:classifiers":[
        {
            "category":"Personal",
            "subcategory":"Beauty Salon",
            "type":"Services"
        }
    ],
    "sg:phone":"+61 3 5475 2400",
    "sg:postcode":"3463",
    "sg:province":"VIC",
    "sg:tags":[
        "hairdresser"
    ],
    "wof:name":"Debbie's Salon",
    "wof:placetype":"venue"
},
  "geometry": {"coordinates":[144.06918335,-36.9896621704],"type":"Point"}
}