{
  "type": "Feature",
  "properties": {
    "addr:full":"31A Hutchinson St Mt Barker SA 5251",
    "addr:housenumber":"31a",
    "addr:postcode":"5251",
    "addr:street":"Hutchinson St Mt",
    "iso:country":"AU",
    "sg:address":"31A Hutchinson St",
    "sg:city":"Mt Barker",
    "sg:classifiers":[
        {
            "category":"Shopping",
            "subcategory":"Party Supplies",
            "type":"Retail Goods"
        }
    ],
    "sg:phone":"+61 8 8398 3411",
    "sg:postcode":"5251",
    "sg:province":"SA",
    "wof:name":"Clown Around Party Shop",
    "wof:placetype":"venue"
},
  "geometry": {"coordinates":[138.85289001500001,-35.0617103577],"type":"Point"}
}