{
  "type": "Feature",
  "properties": {
    "addr:full":"Dee Why Square 26 Oaks Ave Dee Why NSW 2099",
    "addr:housenumber":"26",
    "addr:postcode":"2099",
    "addr:street":"Oaks Ave",
    "iso:country":"AU",
    "sg:address":"Dee Why Square 26 Oaks Ave",
    "sg:city":"Dee Why",
    "sg:classifiers":[
        {
            "category":"Health Services",
            "subcategory":"Doctor",
            "type":"Services"
        }
    ],
    "sg:phone":"+61 2 9982 5555",
    "sg:postcode":"2099",
    "sg:province":"NSW",
    "sg:tags":[
        "medical",
        "practitioner"
    ],
    "wof:name":"Turner Catherine M",
    "wof:placetype":"venue"
},
  "geometry": {"coordinates":[151.288375855,-33.7536239624],"type":"Point"}
}