{
  "type": "Feature",
  "properties": {
    "addr:full":"U1/ 9 Coane St Oakleigh East VIC 3166",
    "addr:postcode":"3166",
    "addr:street":"U1 / 9 Coane St",
    "iso:country":"AU",
    "sg:address":"U1/ 9 Coane St",
    "sg:city":"Oakleigh East",
    "sg:classifiers":[
        {
            "category":"Professional",
            "subcategory":"Engineering",
            "type":"Services"
        }
    ],
    "sg:phone":"+61 3 9543 5034",
    "sg:postcode":"3166",
    "sg:province":"VIC",
    "sg:tags":[
        "consulting",
        "engineer"
    ],
    "wof:name":"Rolyn Pty Ltd",
    "wof:placetype":"venue"
},
  "geometry": {"coordinates":[145.116363525,-37.9109344482],"type":"Point"}
}