{
  "type": "Feature",
  "properties": {
    "addr:full":"Drummond St Oakleigh VIC 3166",
    "addr:postcode":"3166",
    "addr:street":"Drummond St",
    "iso:country":"AU",
    "sg:address":"Drummond St",
    "sg:city":"Oakleigh",
    "sg:classifiers":[
        {
            "category":"Arena",
            "subcategory":"Sports Club",
            "type":"Entertainment"
        }
    ],
    "sg:phone":"+61 3 9563 0284",
    "sg:postcode":"3166",
    "sg:province":"VIC",
    "sg:tags":[
        "defence",
        "supply",
        "self",
        "instruction",
        "martial art"
    ],
    "wof:name":"Kung Fu - Wing Chun",
    "wof:placetype":"venue"
},
  "geometry": {"coordinates":[145.08978271500001,-37.8984184265],"type":"Point"}
}