{
  "type": "Feature",
  "properties": {
    "iso:country":"AU",
    "sg:address":"23 Quinlan St",
    "sg:city":"Wongan Hills",
    "sg:classifiers":[
        {
            "category":"Building & Trades",
            "subcategory":"Plumbing",
            "type":"Services"
        }
    ],
    "sg:phone":"+61 8 9671 1042",
    "sg:postcode":"6603",
    "sg:province":"WA",
    "sg:tags":[
        "plumber",
        "gasfitters"
    ],
    "wof:name":"Follett C",
    "wof:placetype":"venue"
},
  "geometry": {"coordinates":[116.720237732,-30.8924331665],"type":"Point"}
}