{
  "type": "Feature",
  "properties": {
    "iso:country":"AU",
    "sg:address":"40 Winfield St",
    "sg:city":"Morawa",
    "sg:classifiers":[
        {
            "category":"Food & Beverages",
            "subcategory":"Supermarket",
            "type":"Retail Goods"
        }
    ],
    "sg:phone":"+61 8 9971 1220",
    "sg:postcode":"6623",
    "sg:province":"WA",
    "sg:tags":[
        "grocery",
        "store"
    ],
    "wof:name":"IGA Supermarkets",
    "wof:placetype":"venue"
},
  "geometry": {"coordinates":[116.00907898,-29.2109661102],"type":"Point"}
}