{
  "type": "Feature",
  "properties": {
    "addr:full":"224 Beechworth Rd Wodonga VIC 3690",
    "addr:housenumber":"224",
    "addr:postcode":"3690",
    "addr:street":"Beechworth Rd",
    "iso:country":"AU",
    "sg:address":"224 Beechworth Rd",
    "sg:city":"Wodonga",
    "sg:classifiers":[
        {
            "category":"Health Services",
            "subcategory":"Doctor",
            "type":"Services"
        }
    ],
    "sg:phone":"+61 2 6024 3233",
    "sg:postcode":"3690",
    "sg:province":"VIC",
    "sg:tags":[
        "medical",
        "practitioner"
    ],
    "wof:name":"Central Medical Group",
    "wof:placetype":"venue"
},
  "geometry": {"coordinates":[146.88772582999999,-36.1280555725],"type":"Point"}
}