{
  "type": "Feature",
  "properties": {
    "addr:full":"PO Box 7101 Dandenong VIC 3175",
    "addr:postcode":"3175",
    "iso:country":"AU",
    "sg:address":"PO Box 7101",
    "sg:city":"Dandenong",
    "sg:classifiers":[
        {
            "category":"Autos & Motor Vehicles",
            "subcategory":"Auto Supplies",
            "type":"Retail Goods"
        }
    ],
    "sg:phone":"+61 3 9544 0000",
    "sg:postcode":"3175",
    "sg:province":"VIC",
    "sg:tags":[
        "oil",
        "spirit"
    ],
    "wof:name":"Mini-Tankers Australia Pty Ltd",
    "wof:placetype":"venue"
},
  "geometry": {"coordinates":[145.218215942,-37.9853210449],"type":"Point"}
}