{
  "type": "Feature",
  "properties": {
    "addr:full":"Unit 1/ 718 Woodville Rd Villawood NSW 2163",
    "addr:housenumber":"/ 718",
    "addr:postcode":"2163",
    "addr:street":"Woodville Rd",
    "iso:country":"AU",
    "sg:address":"Unit 1/ 718 Woodville Rd",
    "sg:city":"Villawood",
    "sg:classifiers":[
        {
            "category":"Professional",
            "subcategory":"Advertising",
            "type":"Services"
        }
    ],
    "sg:phone":"+61 2 9755 7772",
    "sg:postcode":"2163",
    "sg:province":"NSW",
    "sg:tags":[
        "balloon",
        "novelty"
    ],
    "wof:name":"A Balloon Event",
    "wof:placetype":"venue"
},
  "geometry": {"coordinates":[150.97346496599999,-33.8886680603],"type":"Point"}
}