{
  "type": "Feature",
  "properties": {
    "iso:country":"AU",
    "sg:address":"86 Byng St",
    "sg:city":"Orange",
    "sg:classifiers":[
        {
            "category":"Health Services",
            "subcategory":"Doctor",
            "type":"Services"
        }
    ],
    "sg:phone":"+61 2 6361 7880",
    "sg:postcode":"2800",
    "sg:province":"NSW",
    "sg:tags":[
        "occupational",
        "safety"
    ],
    "wof:name":"Konekt Australia Pty Ltd",
    "wof:placetype":"venue"
},
  "geometry": {"coordinates":[149.09452819800001,-33.2808036804],"type":"Point"}
}