{
  "type": "Feature",
  "properties": {
    "addr:full":"803 Boundary Rd Coopers Plains QLD 4108",
    "addr:housenumber":"803",
    "addr:postcode":"4108",
    "addr:street":"Boundary Rd",
    "iso:country":"AU",
    "sg:address":"803 Boundary Rd",
    "sg:city":"Coopers Plains",
    "sg:classifiers":[
        {
            "category":"Retail",
            "subcategory":"Auto Repair",
            "type":"Services"
        }
    ],
    "sg:phone":"+61 7 3277 9333",
    "sg:postcode":"4108",
    "sg:province":"QLD",
    "sg:tags":[
        "wheel",
        "balancing",
        "alignment"
    ],
    "wof:name":"M & D Mechanical",
    "wof:placetype":"venue"
},
  "geometry": {"coordinates":[153.029006958,-27.5692863464],"type":"Point"}
}