{
  "type": "Feature",
  "properties": {
    "addr:full":"16 Elderslie St Winton QLD 4735",
    "addr:housenumber":"16",
    "addr:postcode":"4735",
    "addr:street":"Elderslie St",
    "iso:country":"AU",
    "sg:address":"16 Elderslie St",
    "sg:city":"Winton",
    "sg:classifiers":[
        {
            "category":"Travel",
            "subcategory":"Hotels & Motels",
            "type":"Entertainment"
        }
    ],
    "sg:phone":"+61 7 4657 1211",
    "sg:postcode":"4735",
    "sg:province":"QLD",
    "wof:name":"Boulder Opal Motor Inn",
    "wof:placetype":"venue"
},
  "geometry": {"coordinates":[143.04104599999999,-22.390299],"type":"Point"}
}