{
  "type": "Feature",
  "properties": {
    "addr:full":"27 Alistair Ave Forresters Beach NSW 2260",
    "addr:housenumber":"27",
    "addr:postcode":"2260",
    "addr:street":"Alistair Ave",
    "iso:country":"AU",
    "sg:address":"27 Alistair Ave",
    "sg:city":"Forresters Beach",
    "sg:classifiers":[
        {
            "category":"Building & Trades",
            "subcategory":"Plumbing",
            "type":"Services"
        }
    ],
    "sg:phone":"+61 2 4384 3413",
    "sg:postcode":"2260",
    "sg:province":"NSW",
    "sg:tags":[
        "plumber",
        "gasfitters"
    ],
    "wof:name":"McNeill Darren Plumbing & Metal Roofing",
    "wof:placetype":"venue"
},
  "geometry": {"coordinates":[151.46972700000001,-33.405277],"type":"Point"}
}