{
  "type": "Feature",
  "properties": {
    "iso:country":"AU",
    "sg:address":"Lvl 2/ 403 Elizabeth St",
    "sg:city":"Sydney",
    "sg:classifiers":[
        {
            "category":"Internet Cafe",
            "subcategory":"None",
            "type":"Food & Drink"
        }
    ],
    "sg:phone":"+61 2 9212 2877",
    "sg:postcode":"2000",
    "sg:province":"NSW",
    "wof:name":"Megapass",
    "wof:placetype":"venue"
},
  "geometry": {"coordinates":[151.20912170400001,-33.8784866333],"type":"Point"}
}