{
  "type": "Feature",
  "properties": {
    "addr:full":"266 Smiths Creek Rd Kundabung NSW 2441",
    "addr:housenumber":"266",
    "addr:postcode":"2441",
    "addr:street":"Smiths Creek Rd",
    "iso:country":"AU",
    "sg:address":"266 Smiths Creek Rd",
    "sg:city":"Kundabung",
    "sg:classifiers":[
        {
            "category":"Building & Trades",
            "subcategory":"Locksmith",
            "type":"Services"
        }
    ],
    "sg:phone":"+61 427 929 975",
    "sg:postcode":"2441",
    "sg:province":"NSW",
    "sg:tags":[
        "equipment",
        "operating",
        "door",
        "gate"
    ],
    "wof:name":"Kevin Walker Garage Doors",
    "wof:placetype":"venue"
},
  "geometry": {"coordinates":[152.79333500000001,-31.200979],"type":"Point"}
}