{
  "type": "Feature",
  "properties": {
    "addr:full":"19 Richardson St Pacific Paradise QLD 4564",
    "addr:housenumber":"19",
    "addr:postcode":"4564",
    "addr:street":"Richardson St",
    "iso:country":"AU",
    "sg:address":"19 Richardson St",
    "sg:city":"Pacific Paradise",
    "sg:classifiers":[
        {
            "category":"Professional",
            "subcategory":"Employment Agencies",
            "type":"Services"
        }
    ],
    "sg:phone":"+61 411 362 725",
    "sg:postcode":"4564",
    "sg:province":"QLD",
    "sg:tags":[
        "entertainer",
        "agent"
    ],
    "wof:name":"ABC and Y Not Fireworks & Entertainment",
    "wof:placetype":"venue"
},
  "geometry": {"coordinates":[153.078125,-26.6150341034],"type":"Point"}
}