{
  "type": "Feature",
  "properties": {
    "addr:full":"9 Hillcrest Rd Gunnedah NSW 2380",
    "addr:housenumber":"9",
    "addr:postcode":"2380",
    "addr:street":"Hillcrest Rd",
    "iso:country":"AU",
    "sg:address":"9 Hillcrest Rd",
    "sg:city":"Gunnedah",
    "sg:classifiers":[
        {
            "category":"Shopping",
            "type":"Retail Goods"
        }
    ],
    "sg:phone":"+61 2 6742 2977",
    "sg:postcode":"2380",
    "sg:province":"NSW",
    "sg:tags":[
        "agent",
        "stock"
    ],
    "wof:name":"Brady Livestock Pty Ltd",
    "wof:placetype":"venue"
},
  "geometry": {"coordinates":[150.2552948,-30.9783115387],"type":"Point"}
}