{
  "type": "Feature",
  "properties": {
    "iso:country":"AU",
    "sg:address":"842 Fifteenth St",
    "sg:city":"Mildura",
    "sg:classifiers":[
        {
            "category":"Building & Trades",
            "subcategory":"Pest Control",
            "type":"Services"
        }
    ],
    "sg:phone":"+61 3 5022 1822",
    "sg:postcode":"3500",
    "sg:province":"VIC",
    "wof:name":"Abrey's Pest Control",
    "wof:placetype":"venue"
},
  "geometry": {"coordinates":[142.13861084000001,-34.2086753845],"type":"Point"}
}