{
  "type": "Feature",
  "properties": {
    "iso:country":"AU",
    "sg:address":"Woods La",
    "sg:city":"Eungai Creek",
    "sg:classifiers":[
        {
            "category":"Utilities",
            "subcategory":"Electric",
            "type":"Services"
        }
    ],
    "sg:phone":"+61 2 6569 9339",
    "sg:postcode":"2441",
    "sg:province":"NSW",
    "sg:tags":[
        "electrical",
        "contractor"
    ],
    "wof:name":"Hardwick K",
    "wof:placetype":"venue"
},
  "geometry": {"coordinates":[153.002579,-30.643332],"type":"Point"}
}