{
  "type": "Feature",
  "properties": {
    "addr:full":"195 Merrylands Rd Merrylands NSW 2160",
    "addr:housenumber":"195",
    "addr:postcode":"2160",
    "addr:street":"Merrylands Rd",
    "iso:country":"AU",
    "sg:address":"195 Merrylands Rd",
    "sg:city":"Merrylands",
    "sg:classifiers":[
        {
            "category":"Food & Beverages",
            "subcategory":"Groceries & Convenience Stores",
            "type":"Retail Goods"
        }
    ],
    "sg:phone":"+61 2 9637 9062",
    "sg:postcode":"2160",
    "sg:province":"NSW",
    "wof:name":"Rainbow Cafe Merrylands",
    "wof:placetype":"venue"
},
  "geometry": {"coordinates":[150.98956298799999,-33.8362884521],"type":"Point"}
}