{
  "type": "Feature",
  "properties": {
    "addr:full":"78 Mangans Rd Lilydale VIC 3140",
    "addr:housenumber":"78",
    "addr:postcode":"3140",
    "addr:street":"Mangans Rd",
    "iso:country":"AU",
    "sg:address":"78 Mangans Rd",
    "sg:city":"Lilydale",
    "sg:classifiers":[
        {
            "category":"Wholesale",
            "subcategory":"Machinery & Supplies",
            "type":"Manufacturing & Wholesale Goods"
        }
    ],
    "sg:phone":"+61 3 9735 0899",
    "sg:postcode":"3140",
    "sg:province":"VIC",
    "sg:tags":[
        "agricultural"
    ],
    "wof:name":"Graham Shaw Tractors & Farm Machinery",
    "wof:placetype":"venue"
},
  "geometry": {"coordinates":[145.37260437,-37.7568626404],"type":"Point"}
}