{
  "type": "Feature",
  "properties": {
    "addr:full":"9-12 Narrandra St Lake Cargelligo NSW 2672",
    "addr:housenumber":"9-12",
    "addr:postcode":"2672",
    "addr:street":"Narrandra St",
    "iso:country":"AU",
    "sg:address":"9-12 Narrandra St",
    "sg:city":"Lake Cargelligo",
    "sg:phone":"+61 1800 626 002",
    "sg:postcode":"2672",
    "sg:province":"NSW",
    "wof:name":"Durapoly",
    "wof:placetype":"venue"
},
  "geometry": {"coordinates":[146.37254333499999,-33.3050537109],"type":"Point"}
}