{
  "type": "Feature",
  "properties": {
    "addr:full":"Smith Rd Telopea Downs VIC 3419",
    "addr:postcode":"3419",
    "addr:street":"Smith Rd",
    "iso:country":"AU",
    "sg:address":"Smith Rd",
    "sg:city":"Telopea Downs",
    "sg:classifiers":[
        {
            "category":"Building & Trades",
            "subcategory":"Landscaping Services",
            "type":"Services"
        }
    ],
    "sg:phone":"+61 3 5393 9528",
    "sg:postcode":"3419",
    "sg:province":"VIC",
    "sg:tags":[
        "grazier"
    ],
    "wof:name":"Glenalpine Pty Ltd",
    "wof:placetype":"venue"
},
  "geometry": {"coordinates":[141.249557495,-36.3976593018],"type":"Point"}
}