{
  "type": "Feature",
  "properties": {
    "iso:country":"AU",
    "sg:address":"Heber St",
    "sg:city":"Moree",
    "sg:classifiers":[
        {
            "category":"Wholesale",
            "subcategory":"Fruits & Vegetables",
            "type":"Manufacturing & Wholesale Goods"
        }
    ],
    "sg:phone":"+61 2 6752 1277",
    "sg:postcode":"2400",
    "sg:province":"NSW",
    "sg:tags":[
        "produce",
        "grain"
    ],
    "wof:name":"Seed & Grain Sales Pty Ltd",
    "wof:placetype":"venue"
},
  "geometry": {"coordinates":[149.84193420400001,-29.4629707336],"type":"Point"}
}