{
  "type": "Feature",
  "properties": {
    "addr:full":"Shp 24a Bathurst Cntr Bathurst NSW 2795",
    "addr:housenumber":"24a",
    "addr:postcode":"2795",
    "addr:street":"Bathurst Cntr",
    "iso:country":"AU",
    "sg:address":"Shp 24a Bathurst Cntr",
    "sg:city":"Bathurst",
    "sg:classifiers":[
        {
            "category":"Shopping",
            "subcategory":"Clothing, Apparel, & Fashions",
            "type":"Retail Goods"
        }
    ],
    "sg:phone":"+61 2 6331 9840",
    "sg:postcode":"2795",
    "sg:province":"NSW",
    "sg:tags":[
        "jean"
    ],
    "wof:name":"Just Jeans Pty Ltd",
    "wof:placetype":"venue"
},
  "geometry": {"coordinates":[149.54786682100001,-33.4906997681],"type":"Point"}
}