{
  "type": "Feature",
  "properties": {
    "addr:full":"85 Rosevears Drv Rosevears TAS 7277",
    "addr:housenumber":"85",
    "addr:postcode":"7277",
    "addr:street":"Rosevears Drv",
    "iso:country":"AU",
    "sg:address":"85 Rosevears Drv",
    "sg:city":"Rosevears",
    "sg:classifiers":[
        {
            "category":"Transit Center",
            "subcategory":"Freight",
            "type":"Transportation"
        }
    ],
    "sg:phone":"+61 3 6330 1744",
    "sg:postcode":"7277",
    "sg:province":"TAS",
    "sg:tags":[
        "turner",
        "wood"
    ],
    "wof:name":"&#034;Tamar House&#034; Wood Turning",
    "wof:placetype":"venue"
},
  "geometry": {"coordinates":[147.026519775,-41.3433570862],"type":"Point"}
}