{
  "type": "Feature",
  "properties": {
    "addr:full":"1 York St Prahran VIC 3181",
    "addr:housenumber":"1",
    "addr:postcode":"3181",
    "addr:street":"York St",
    "iso:country":"AU",
    "sg:address":"1 York St",
    "sg:city":"Prahran",
    "sg:classifiers":[
        {
            "category":"Professional",
            "subcategory":"Business Services",
            "type":"Services"
        }
    ],
    "sg:phone":"+61 3 9529 4044",
    "sg:postcode":"3181",
    "sg:province":"VIC",
    "sg:tags":[
        "exporter"
    ],
    "wof:name":"Sharma Bros Pty Ltd",
    "wof:placetype":"venue"
},
  "geometry": {"coordinates":[144.997756958,-37.8523368835],"type":"Point"}
}