{
  "type": "Feature",
  "properties": {
    "addr:full":"PO Box 10 Glen Forrest WA 6071",
    "addr:postcode":"6071",
    "addr:street":"Glen",
    "iso:country":"AU",
    "sg:address":"PO Box 10",
    "sg:city":"Glen Forrest",
    "sg:classifiers":[
        {
            "category":"Professional",
            "subcategory":"Detective & Security Services",
            "type":"Services"
        }
    ],
    "sg:phone":"+61 419 040 409",
    "sg:postcode":"6071",
    "sg:province":"WA",
    "sg:tags":[
        "consultant",
        "system"
    ],
    "wof:name":"S.G.P. Electrical",
    "wof:placetype":"venue"
},
  "geometry": {"coordinates":[116.104270935,-31.9034500122],"type":"Point"}
}