{
  "type": "Feature",
  "properties": {
    "addr:full":"Unit 9- 60 Lillee Crs Tullamarine VIC 3043",
    "addr:housenumber":"60",
    "addr:postcode":"3043",
    "addr:street":"Lillee Crs",
    "iso:country":"AU",
    "sg:address":"Unit 9- 60 Lillee Crs",
    "sg:city":"Tullamarine",
    "sg:classifiers":[
        {
            "category":"Farming",
            "subcategory":"Farm & Veterinary Services",
            "type":"Manufacturing & Wholesale Goods"
        }
    ],
    "sg:phone":"+61 1800 001 599",
    "sg:postcode":"3043",
    "sg:province":"VIC",
    "sg:tags":[
        "agricultural",
        "advisory"
    ],
    "wof:name":"BCF Ultrasound Australasia",
    "wof:placetype":"venue"
},
  "geometry": {"coordinates":[144.917404175,-37.6747131348],"type":"Point"}
}