{
  "type": "Feature",
  "properties": {
    "addr:full":"RMB 7055 Wangandary Rd Wangaratta VIC 3677",
    "addr:postcode":"3677",
    "addr:street":"Wangandary Rd",
    "iso:country":"AU",
    "sg:address":"RMB 7055 Wangandary Rd",
    "sg:city":"Wangaratta",
    "sg:classifiers":[
        {
            "category":"Education",
            "subcategory":"Vocational School",
            "type":"Public Place"
        }
    ],
    "sg:phone":"+61 408 010 670",
    "sg:postcode":"3677",
    "sg:province":"VIC",
    "sg:tags":[
        "cake",
        "decorating",
        "decorator"
    ],
    "wof:name":"Forgoodness Cakes",
    "wof:placetype":"venue"
},
  "geometry": {"coordinates":[146.29571533199999,-36.3364372253],"type":"Point"}
}