{
  "type": "Feature",
  "properties": {
    "addr:full":"Reynell Rd Happy Valley SA 5159",
    "addr:postcode":"5159",
    "addr:street":"Reynell Rd",
    "iso:country":"AU",
    "sg:address":"Reynell Rd",
    "sg:city":"Happy Valley",
    "sg:classifiers":[
        {
            "category":"Retail",
            "subcategory":"Event Space",
            "type":"Services"
        }
    ],
    "sg:phone":"+61 8 8381 3300",
    "sg:postcode":"5159",
    "sg:province":"SA",
    "sg:tags":[
        "venue",
        "reception",
        "wedding"
    ],
    "wof:name":"The Vines Golf Club of Reynella",
    "wof:placetype":"venue"
},
  "geometry": {"coordinates":[138.57159423799999,-35.0923233032],"type":"Point"}
}