{
  "type": "Feature",
  "properties": {
    "addr:full":"Unit 5/8 Yampi Way Willetton WA 6155",
    "addr:housenumber":"8",
    "addr:postcode":"6155",
    "addr:street":"Yampi Way",
    "iso:country":"AU",
    "sg:address":"Unit 5/8 Yampi Way",
    "sg:city":"Willetton",
    "sg:classifiers":[
        {
            "category":"Retail",
            "subcategory":"Self-service Laundry",
            "type":"Services"
        }
    ],
    "sg:phone":"+61 8 9457 2277",
    "sg:postcode":"6155",
    "sg:province":"WA",
    "wof:name":"Ace Professional Dry Cleaners",
    "wof:placetype":"venue"
},
  "geometry": {"coordinates":[115.885582,-32.040684],"type":"Point"}
}