{
  "type": "Feature",
  "properties": {
    "addr:full":"58 Evans St Wagga Wagga NSW 2650",
    "addr:housenumber":"58",
    "addr:postcode":"2650",
    "addr:street":"Evans St",
    "iso:country":"AU",
    "sg:address":"58 Evans St",
    "sg:city":"Wagga Wagga",
    "sg:classifiers":[
        {
            "category":"Social Services",
            "subcategory":"Child Care",
            "type":"Services"
        }
    ],
    "sg:phone":"+61 2 6921 1686",
    "sg:postcode":"2650",
    "sg:province":"NSW",
    "wof:name":"Central Wagga Pre-School Long Day Care Early Learning Centre",
    "wof:placetype":"venue"
},
  "geometry": {"coordinates":[147.350341797,-35.1060333252],"type":"Point"}
}