{
  "type": "Feature",
  "properties": {
    "iso:country":"AU",
    "sg:address":"Queen Victoria St",
    "sg:city":"Bexley",
    "sg:classifiers":[
        {
            "category":"Education",
            "subcategory":"Special Training",
            "type":"Public Place"
        }
    ],
    "sg:phone":"+61 2 9588 9887",
    "sg:postcode":"2207",
    "sg:province":"NSW",
    "sg:tags":[
        "development"
    ],
    "wof:name":"K & L Training & Consultancy Pty Ltd",
    "wof:placetype":"venue"
},
  "geometry": {"coordinates":[151.123245,-33.95306],"type":"Point"}
}