{
  "type": "Feature",
  "properties": {
    "addr:full":"Shop 5/ 11 Birtwill St Coolum Beach QLD 4573",
    "addr:housenumber":"shop 5 / 11",
    "addr:postcode":"4573",
    "addr:street":"Birtwill St",
    "iso:country":"AU",
    "sg:address":"Shop 5/ 11 Birtwill St",
    "sg:city":"Coolum Beach",
    "sg:classifiers":[
        {
            "category":"Food & Beverages",
            "subcategory":"Specialty",
            "type":"Retail Goods"
        }
    ],
    "sg:phone":"+61 7 5471 7755",
    "sg:postcode":"4573",
    "sg:province":"QLD",
    "sg:tags":[
        "product",
        "health"
    ],
    "wof:name":"Coolum Health Foods & Healing Centre",
    "wof:placetype":"venue"
},
  "geometry": {"coordinates":[153.08947800000001,-26.527159],"type":"Point"}
}