{
  "type": "Feature",
  "properties": {
    "addr:full":"5- 7 Post Office Pl Glenroy VIC 3046",
    "addr:housenumber":"7",
    "addr:postcode":"3046",
    "addr:street":"Post Office Pl",
    "iso:country":"AU",
    "sg:address":"5- 7 Post Office Pl",
    "sg:city":"Glenroy",
    "sg:classifiers":[
        {
            "category":"Food & Beverages",
            "subcategory":"Fruits & Vegetables",
            "type":"Retail Goods"
        }
    ],
    "sg:phone":"+61 3 9306 8116",
    "sg:postcode":"3046",
    "sg:province":"VIC",
    "sg:tags":[
        "greengrocer",
        "fruiterer"
    ],
    "wof:name":"Glenroy Fruit Supply Pty Ltd",
    "wof:placetype":"venue"
},
  "geometry": {"coordinates":[144.916213989,-37.7046051025],"type":"Point"}
}