{
  "type": "Feature",
  "properties": {
    "addr:full":"64 Darley St Mona Vale NSW 2103",
    "addr:housenumber":"64",
    "addr:postcode":"2103",
    "addr:street":"Darley St",
    "iso:country":"AU",
    "sg:address":"64 Darley St",
    "sg:city":"Mona Vale",
    "sg:classifiers":[
        {
            "category":"Industrial Area",
            "type":"Public Place"
        }
    ],
    "sg:phone":"+61 2 9997 4144",
    "sg:postcode":"2103",
    "sg:province":"NSW",
    "sg:tags":[
        "protective",
        "clothing"
    ],
    "wof:name":"John Wayne Workgear",
    "wof:placetype":"venue"
},
  "geometry": {"coordinates":[151.30682373100001,-33.6753768921],"type":"Point"}
}