{
  "type": "Feature",
  "properties": {
    "addr:full":"Unit 1, 31 Harvey St North Eagle Farm QLD 4009",
    "addr:housenumber":"31",
    "addr:postcode":"4009",
    "addr:street":"Harvey St North",
    "iso:country":"AU",
    "sg:address":"Unit 1, 31 Harvey St",
    "sg:city":"North Eagle Farm",
    "sg:classifiers":[
        {
            "category":"Utilities",
            "subcategory":"Electric",
            "type":"Services"
        }
    ],
    "sg:phone":"+61 7 3868 9000",
    "sg:postcode":"4009",
    "sg:province":"QLD",
    "sg:tags":[
        "tube",
        "lamps",
        "globe"
    ],
    "wof:name":"Ideal Electrical Suppliers",
    "wof:placetype":"venue"
},
  "geometry": {"coordinates":[153.09112548799999,-27.431142807],"type":"Point"}
}