{
  "type": "Feature",
  "properties": {
    "addr:full":"PO Box 7 Waverley NSW 2024",
    "addr:postcode":"2024",
    "iso:country":"AU",
    "sg:address":"PO Box 7",
    "sg:city":"Waverley",
    "sg:classifiers":[
        {
            "category":"Building & Trades",
            "subcategory":"Landscaping Services",
            "type":"Services"
        }
    ],
    "sg:phone":"+61 419 959 564",
    "sg:postcode":"2024",
    "sg:province":"NSW",
    "sg:tags":[
        "consultant"
    ],
    "wof:name":"J.P.H. Architectural Drafting",
    "wof:placetype":"venue"
},
  "geometry": {"coordinates":[151.253814697,-33.8993492126],"type":"Point"}
}