{
  "type": "Feature",
  "properties": {
    "addr:full":"86 Gipps St Wollongong NSW 2500",
    "addr:housenumber":"86",
    "addr:postcode":"2500",
    "addr:street":"Gipps St",
    "iso:country":"AU",
    "sg:address":"86 Gipps St",
    "sg:city":"Wollongong",
    "sg:classifiers":[
        {
            "category":"Retail",
            "subcategory":"Auto Repair",
            "type":"Services"
        }
    ],
    "sg:phone":"+61 2 4229 9899",
    "sg:postcode":"2500",
    "sg:province":"NSW",
    "sg:tags":[
        "engine",
        "reconditioning"
    ],
    "wof:name":"Martins Engine Reconditioning Pty. Ltd.",
    "wof:placetype":"venue"
},
  "geometry": {"coordinates":[150.89175399999999,-34.41703],"type":"Point"}
}