{
  "type": "Feature",
  "properties": {
    "iso:country":"AU",
    "sg:address":"Unit 3, 60 Keane St",
    "sg:city":"Currajong",
    "sg:classifiers":[
        {
            "category":"Home & Garden",
            "subcategory":"Carpets & Floor Coverings",
            "type":"Retail Goods"
        }
    ],
    "sg:phone":"+61 7 4728 8644",
    "sg:postcode":"4812",
    "sg:province":"QLD",
    "sg:tags":[
        "tile",
        "wall"
    ],
    "wof:name":"MJS Floorcoverings",
    "wof:placetype":"venue"
},
  "geometry": {"coordinates":[146.775543,-19.271448],"type":"Point"}
}