{
  "type": "Feature",
  "properties": {
    "addr:full":"18 Ingram Rd Wahroonga NSW 2076",
    "addr:housenumber":"18",
    "addr:postcode":"2076",
    "addr:street":"Ingram Rd",
    "iso:country":"AU",
    "sg:address":"18 Ingram Rd",
    "sg:city":"Wahroonga",
    "sg:classifiers":[
        {
            "category":"Travel",
            "subcategory":"Hotels & Motels",
            "type":"Entertainment"
        }
    ],
    "sg:phone":"+61 2 9487 3355",
    "sg:postcode":"2076",
    "sg:province":"NSW",
    "wof:name":"Ascot Motor Inn",
    "wof:placetype":"venue"
},
  "geometry": {"coordinates":[151.10919189399999,-33.7155075073],"type":"Point"}
}