{
  "type": "Feature",
  "properties": {
    "addr:full":"Pioneer Village Shop 7 Albany Hwy Armadale WA 6112",
    "addr:housenumber":"7",
    "addr:postcode":"6112",
    "addr:street":"Albany Hwy",
    "iso:country":"AU",
    "sg:address":"Pioneer Village Shop 7 Albany Hwy",
    "sg:city":"Armadale",
    "sg:classifiers":[
        {
            "category":"Personal",
            "subcategory":"Beauty Salon",
            "type":"Services"
        }
    ],
    "sg:phone":"+61 8 9497 1134",
    "sg:postcode":"6112",
    "sg:province":"WA",
    "sg:tags":[
        "hairdresser"
    ],
    "wof:name":"Art Of Hair",
    "wof:placetype":"venue"
},
  "geometry": {"coordinates":[116.020248413,-32.1499824524],"type":"Point"}
}