{
  "type": "Feature",
  "properties": {
    "addr:full":"Cnr Madeline & May Sts Condobolin NSW 2877",
    "addr:postcode":"2877",
    "addr:street":"Cnr Madeline &;Sts",
    "iso:country":"AU",
    "sg:address":"Cnr Madeline & May Sts",
    "sg:city":"Condobolin",
    "sg:classifiers":[
        {
            "category":"Wholesale",
            "subcategory":"Fruits & Vegetables",
            "type":"Manufacturing & Wholesale Goods"
        }
    ],
    "sg:phone":"+61 2 6895 2270",
    "sg:postcode":"2877",
    "sg:province":"NSW",
    "sg:tags":[
        "produce",
        "grain"
    ],
    "wof:name":"Hassan's Mill & Produce",
    "wof:placetype":"venue"
},
  "geometry": {"coordinates":[147.14515700000001,-33.086819],"type":"Point"}
}