{
  "type": "Feature",
  "properties": {
    "addr:full":"98 Commercial Drv Thomastown VIC 3074",
    "addr:housenumber":"98",
    "addr:postcode":"3074",
    "addr:street":"Commercial Drv",
    "iso:country":"AU",
    "sg:address":"98 Commercial Drv",
    "sg:city":"Thomastown",
    "sg:classifiers":[
        {
            "category":"Farming",
            "subcategory":"Fish & Marine Products",
            "type":"Manufacturing & Wholesale Goods"
        }
    ],
    "sg:phone":"+61 3 9466 4144",
    "sg:postcode":"3074",
    "sg:province":"VIC",
    "sg:tags":[
        "wholesaler",
        "mfrs",
        "swimwear"
    ],
    "wof:name":"Coral Reef Australia",
    "wof:placetype":"venue"
},
  "geometry": {"coordinates":[145.039718628,-37.6892662048],"type":"Point"}
}