{
  "type": "Feature",
  "properties": {
    "addr:full":"10 Mollison St South Brisbane QLD 4101",
    "addr:housenumber":"10",
    "addr:postcode":"4101",
    "addr:street":"Mollison St",
    "iso:country":"AU",
    "sg:address":"10 Mollison St",
    "sg:city":"South Brisbane",
    "sg:classifiers":[
        {
            "category":"Building & Trades",
            "subcategory":"Cleaning & Sanitation",
            "type":"Services"
        }
    ],
    "sg:phone":"+61 7 3844 0050",
    "sg:postcode":"4101",
    "sg:province":"QLD",
    "sg:tags":[
        "commercial",
        "maintenance"
    ],
    "wof:name":"Diverse Worx",
    "wof:placetype":"venue"
},
  "geometry": {"coordinates":[153.00999450699999,-27.4760036469],"type":"Point"}
}