{
  "type": "Feature",
  "properties": {
    "addr:full":"GPO Box 215 , Burwood NSW 1805",
    "addr:postcode":"1805",
    "iso:country":"AU",
    "sg:address":"GPO Box 215",
    "sg:city":", Burwood",
    "sg:classifiers":[
        {
            "category":"Health Services",
            "subcategory":"Clinic",
            "type":"Services"
        }
    ],
    "sg:phone":"+61 2 9715 6622",
    "sg:postcode":"1805",
    "sg:province":"NSW",
    "sg:tags":[
        "aromatherapy"
    ],
    "wof:name":"International Federation Of Aromatherapists",
    "wof:placetype":"venue"
},
  "geometry": {"coordinates":[151.10221899999999,-33.884087],"type":"Point"}
}