{
  "type": "Feature",
  "properties": {
    "addr:full":"PO Box 241 Joondalup DC WA 6919",
    "addr:postcode":"6919",
    "iso:country":"AU",
    "sg:address":"PO Box 241",
    "sg:city":"Joondalup DC",
    "sg:classifiers":[
        {
            "category":"Manufacturing",
            "subcategory":"Apparel",
            "type":"Manufacturing & Wholesale Goods"
        }
    ],
    "sg:phone":"+61 8 9305 6665",
    "sg:postcode":"6919",
    "sg:province":"WA",
    "sg:tags":[
        "wholesaler",
        "mfrs",
        "footwear"
    ],
    "wof:name":"Bata Shoe Company Of Australia Pty Ltd",
    "wof:placetype":"venue"
},
  "geometry": {"coordinates":[115.769889831,-31.7465190887],"type":"Point"}
}