{
  "type": "Feature",
  "properties": {
    "iso:country":"AU",
    "sg:address":"60 Lake Rd",
    "sg:city":"Port Macquarie",
    "sg:classifiers":[
        {
            "category":"Health Services",
            "subcategory":"Doctor",
            "type":"Services"
        }
    ],
    "sg:phone":"+61 2 6584 2111",
    "sg:postcode":"2444",
    "sg:province":"NSW",
    "sg:tags":[
        "medical",
        "practitioner"
    ],
    "wof:name":"Knight Julie Dr",
    "wof:placetype":"venue"
},
  "geometry": {"coordinates":[152.90921,-31.439814],"type":"Point"}
}