{
  "type": "Feature",
  "properties": {
    "iso:country":"AU",
    "sg:address":"654 Ipswich Rd",
    "sg:city":"Annerley",
    "sg:classifiers":[
        {
            "category":"Professional",
            "subcategory":"Printing & Photocopies",
            "type":"Services"
        }
    ],
    "sg:phone":"+61 7 3255 9233",
    "sg:postcode":"4103",
    "sg:province":"QLD",
    "sg:tags":[
        "equipment",
        "plan"
    ],
    "wof:name":"Cost less Copies",
    "wof:placetype":"venue"
},
  "geometry": {"coordinates":[153.02981567399999,-27.5178470612],"type":"Point"}
}