{
  "type": "Feature",
  "properties": {
    "addr:full":"524 Ross Hwy Alice Springs NT 0870",
    "addr:housenumber":"524",
    "addr:postcode":"nt 0870",
    "addr:street":"Ross Hwy",
    "iso:country":"AU",
    "sg:address":"524 Ross Hwy",
    "sg:city":"Alice Springs",
    "sg:classifiers":[
        {
            "category":"Farming",
            "subcategory":"Berry Farm",
            "type":"Manufacturing & Wholesale Goods"
        }
    ],
    "sg:phone":"+61 8 8953 1570",
    "sg:postcode":"0870",
    "sg:province":"NT",
    "sg:tags":[
        "fruit",
        "grower"
    ],
    "wof:name":"Desert Fruit Company The",
    "wof:placetype":"venue"
},
  "geometry": {"coordinates":[133.86741638199999,-23.7375392914],"type":"Point"}
}