{
  "type": "Feature",
  "properties": {
    "addr:full":"7- 13 Cressall Rd Balcatta WA 6021",
    "addr:housenumber":"13",
    "addr:postcode":"6021",
    "addr:street":"7;Cressall Rd",
    "iso:country":"AU",
    "sg:address":"7- 13 Cressall Rd",
    "sg:city":"Balcatta",
    "sg:classifiers":[
        {
            "category":"Professional",
            "subcategory":"Art Services",
            "type":"Services"
        }
    ],
    "sg:phone":"+61 8 9345 3977",
    "sg:postcode":"6021",
    "sg:province":"WA",
    "sg:tags":[
        "picture",
        "frame",
        "framing"
    ],
    "wof:name":"Picture Framers Guild Of W.A. Inc.",
    "wof:placetype":"venue"
},
  "geometry": {"coordinates":[115.811668396,-31.8615875244],"type":"Point"}
}