{
  "type": "Feature",
  "properties": {
    "iso:country":"AU",
    "sg:address":"Palm City Oasis Shopping Centre Suite 23",
    "sg:city":",15 Temple Terrace Palmerston",
    "sg:classifiers":[
        {
            "category":"Real Estate",
            "subcategory":"Real Estate Agent",
            "type":"Services"
        }
    ],
    "sg:phone":"+61 8 8939 0888",
    "sg:postcode":"0830",
    "sg:province":"NT",
    "wof:name":"Colliers International",
    "wof:placetype":"venue"
},
  "geometry": {"coordinates":[130.984634,-12.483643],"type":"Point"}
}