{
  "type": "Feature",
  "properties": {
    "iso:country":"AU",
    "sg:address":"220 High St",
    "sg:city":"Northcote",
    "sg:classifiers":[
        {
            "category":"Personal",
            "subcategory":"Beauty Salon",
            "type":"Services"
        }
    ],
    "sg:phone":"+61 3 9486 6582",
    "sg:postcode":"3070",
    "sg:province":"VIC",
    "sg:tags":[
        "hairdresser"
    ],
    "wof:name":"Natasha Varga",
    "wof:placetype":"venue"
},
  "geometry": {"coordinates":[144.99830600000001,-37.773628],"type":"Point"}
}