{
  "type": "Feature",
  "properties": {
    "addr:full":"Crowe St Kalangadoo SA 5278",
    "addr:postcode":"5278",
    "addr:street":"Crowe St",
    "iso:country":"AU",
    "sg:address":"Crowe St",
    "sg:city":"Kalangadoo",
    "sg:classifiers":[
        {
            "category":"Home & Garden",
            "subcategory":"Building Materials",
            "type":"Retail Goods"
        }
    ],
    "sg:phone":"+61 8 8739 2524",
    "sg:postcode":"5278",
    "sg:province":"SA",
    "sg:tags":[
        "fencing"
    ],
    "wof:name":"Auspine Limited",
    "wof:placetype":"venue"
},
  "geometry": {"coordinates":[140.69662500000001,-37.564751],"type":"Point"}
}