{
  "type": "Feature",
  "properties": {
    "iso:country":"AU",
    "sg:address":"69 Dalton Rd",
    "sg:city":"Thomastown",
    "sg:classifiers":[
        {
            "category":"Retail",
            "subcategory":"Storage",
            "type":"Services"
        }
    ],
    "sg:phone":"+61 3 9465 7799",
    "sg:postcode":"3074",
    "sg:province":"VIC",
    "wof:name":"Fort Knox Self Storage",
    "wof:placetype":"venue"
},
  "geometry": {"coordinates":[145.029586792,-37.6838874817],"type":"Point"}
}