{
  "type": "Feature",
  "properties": {
    "iso:country":"AU",
    "sg:address":"160 Gladstone St",
    "sg:city":"Fyshwick",
    "sg:classifiers":[
        {
            "category":"Building & Trades",
            "subcategory":"Construction",
            "type":"Services"
        }
    ],
    "sg:phone":"+61 1300 728 985",
    "sg:postcode":"2609",
    "sg:province":"ACT",
    "sg:tags":[
        "insulation",
        "contractor"
    ],
    "wof:name":"Insulco",
    "wof:placetype":"venue"
},
  "geometry": {"coordinates":[149.18484497099999,-35.3273963928],"type":"Point"}
}