{
  "type": "Feature",
  "properties": {
    "addr:full":"63 Secam St Mansfield QLD 4122",
    "addr:housenumber":"63",
    "addr:postcode":"4122",
    "addr:street":"Secam St",
    "iso:country":"AU",
    "sg:address":"63 Secam St",
    "sg:city":"Mansfield",
    "sg:classifiers":[
        {
            "category":"Organizations",
            "subcategory":"Professional Association",
            "type":"Services"
        }
    ],
    "sg:phone":"+61 1300 889 179",
    "sg:postcode":"4122",
    "sg:province":"QLD",
    "sg:tags":[
        "web",
        "internet"
    ],
    "wof:name":"Webscore.com.au",
    "wof:placetype":"venue"
},
  "geometry": {"coordinates":[153.09892273,-27.5291042328],"type":"Point"}
}