{
  "type": "Feature",
  "properties": {
    "addr:full":"16 Topaz Crs Seven Hills NSW 2147",
    "addr:housenumber":"16",
    "addr:postcode":"2147",
    "addr:street":"Topaz Crs",
    "iso:country":"AU",
    "sg:address":"16 Topaz Crs",
    "sg:city":"Seven Hills",
    "sg:classifiers":[
        {
            "category":"Manufacturing",
            "subcategory":"Building Materials",
            "type":"Manufacturing & Wholesale Goods"
        }
    ],
    "sg:phone":"+61 2 9831 4388",
    "sg:postcode":"2147",
    "sg:province":"NSW",
    "sg:tags":[
        "equipment",
        "handling"
    ],
    "wof:name":"Equipsafe",
    "wof:placetype":"venue"
},
  "geometry": {"coordinates":[150.933883667,-33.775970459],"type":"Point"}
}