{
  "type": "Feature",
  "properties": {
    "iso:country":"AU",
    "sg:address":"PO Box 191",
    "sg:city":"Harlaxton",
    "sg:classifiers":[
        {
            "category":"Professional",
            "subcategory":"Detective & Security Services",
            "type":"Services"
        }
    ],
    "sg:phone":"+61 1300 653 007",
    "sg:postcode":"4350",
    "sg:province":"QLD",
    "sg:tags":[
        "training"
    ],
    "wof:name":"Security Institute",
    "wof:placetype":"venue"
},
  "geometry": {"coordinates":[151.95391799999999,-27.541321],"type":"Point"}
}