{
  "type": "Feature",
  "properties": {
    "addr:full":"12 Archimedes St Darra QLD 4076",
    "addr:housenumber":"12",
    "addr:postcode":"4076",
    "addr:street":"Archimedes St",
    "iso:country":"AU",
    "sg:address":"12 Archimedes St",
    "sg:city":"Darra",
    "sg:classifiers":[
        {
            "category":"Professional",
            "subcategory":"Detective & Security Services",
            "type":"Services"
        }
    ],
    "sg:phone":"+61 7 3375 1431",
    "sg:postcode":"4076",
    "sg:province":"QLD",
    "sg:tags":[
        "consultant",
        "laser"
    ],
    "wof:name":"Technofast Laser",
    "wof:placetype":"venue"
},
  "geometry": {"coordinates":[152.95260620100001,-27.5763607025],"type":"Point"}
}