{
  "type": "Feature",
  "properties": {
    "iso:country":"AU",
    "sg:address":"62 North St",
    "sg:city":"Nowra",
    "sg:classifiers":[
        {
            "category":"Insurance",
            "subcategory":"Hazard Insurance",
            "type":"Services"
        }
    ],
    "sg:phone":"+61 2 4423 6133",
    "sg:postcode":"2541",
    "sg:province":"NSW",
    "sg:tags":[
        "fire",
        "accident",
        "marine"
    ],
    "wof:name":"CGU",
    "wof:placetype":"venue"
},
  "geometry": {"coordinates":[150.601104736,-34.8724746704],"type":"Point"}
}