{
  "type": "Feature",
  "properties": {
    "addr:full":"119 Mountain St Mt Gravatt QLD 4122",
    "addr:housenumber":"119",
    "addr:postcode":"4122",
    "addr:street":"Mountain St",
    "iso:country":"AU",
    "sg:address":"119 Mountain St",
    "sg:city":"Mt Gravatt",
    "sg:classifiers":[
        {
            "category":"Health Services",
            "subcategory":"Health Practitioner",
            "type":"Services"
        }
    ],
    "sg:phone":"+61 412 565 935",
    "sg:postcode":"4122",
    "sg:province":"QLD",
    "sg:tags":[
        "pathologist",
        "speech"
    ],
    "wof:name":"Heather Pedley",
    "wof:placetype":"venue"
},
  "geometry": {"coordinates":[153.07156372099999,-27.538734436],"type":"Point"}
}