{
  "type": "Feature",
  "properties": {
    "addr:full":"29 Morts Rd Mortdale NSW 2223",
    "addr:housenumber":"29",
    "addr:postcode":"2223",
    "addr:street":"Morts Rd",
    "iso:country":"AU",
    "sg:address":"29 Morts Rd",
    "sg:city":"Mortdale",
    "sg:classifiers":[
        {
            "category":"Cafe",
            "type":"Food & Drink"
        }
    ],
    "sg:phone":"+61 2 9579 5922",
    "sg:postcode":"2223",
    "sg:province":"NSW",
    "wof:name":"Mortdale Grind Cafe",
    "wof:placetype":"venue"
},
  "geometry": {"coordinates":[151.07908630399999,-33.9695625305],"type":"Point"}
}