{
  "type": "Feature",
  "properties": {
    "iso:country":"AU",
    "sg:address":"109 Archer St",
    "sg:city":"Shepparton",
    "sg:classifiers":[
        {
            "category":"Professional",
            "subcategory":"Detective & Security Services",
            "type":"Services"
        }
    ],
    "sg:phone":"+61 3 5821 5120",
    "sg:postcode":"3630",
    "sg:province":"VIC",
    "sg:tags":[
        "equipment",
        "window",
        "doors"
    ],
    "wof:name":"G. V. Security Doors & Screens",
    "wof:placetype":"venue"
},
  "geometry": {"coordinates":[145.412277222,-36.3864746094],"type":"Point"}
}