{
  "type": "Feature",
  "properties": {
    "addr:full":"1/ 544 Valencia Way Maddington WA 6109",
    "addr:housenumber":"/ 544",
    "addr:postcode":"6109",
    "addr:street":"Valencia Way",
    "iso:country":"AU",
    "sg:address":"1/ 544",
    "sg:city":"Valencia Way Maddington",
    "sg:classifiers":[
        {
            "category":"Wholesale",
            "subcategory":"Durable Goods & Equipment",
            "type":"Manufacturing & Wholesale Goods"
        }
    ],
    "sg:phone":"+61 8 9452 1112",
    "sg:postcode":"6109",
    "sg:province":"WA",
    "sg:tags":[
        "wholesaler",
        "mfrs",
        "lubrication"
    ],
    "wof:name":"DM Breaker Lube Systems P/L",
    "wof:placetype":"venue"
},
  "geometry": {"coordinates":[115.995849609,-32.0350723267],"type":"Point"}
}