{
  "type": "Feature",
  "properties": {
    "iso:country":"AU",
    "sg:address":"219 Canning Hwy",
    "sg:city":"South Perth",
    "sg:classifiers":[
        {
            "category":"Organizations",
            "subcategory":"Professional Association",
            "type":"Services"
        }
    ],
    "sg:phone":"+61 8 9368 8750",
    "sg:postcode":"6151",
    "sg:province":"WA",
    "sg:tags":[
        "rural",
        "organisation",
        "production",
        "primary"
    ],
    "wof:name":"Export Grains Centre Ltd",
    "wof:placetype":"venue"
},
  "geometry": {"coordinates":[115.871803,-31.987234],"type":"Point"}
}