{
  "type": "Feature",
  "properties": {
    "addr:full":"PO Box 5008 Hughesdale VIC 3166",
    "addr:postcode":"3166",
    "iso:country":"AU",
    "sg:address":"PO Box 5008",
    "sg:city":"Hughesdale",
    "sg:classifiers":[
        {
            "category":"Shopping",
            "subcategory":"Clothing, Apparel, & Fashions",
            "type":"Retail Goods"
        }
    ],
    "sg:phone":"+61 3 9568 2300",
    "sg:postcode":"3166",
    "sg:province":"VIC",
    "sg:tags":[
        "textile",
        "designer"
    ],
    "wof:name":"Arctic Blast",
    "wof:placetype":"venue"
},
  "geometry": {"coordinates":[145.080841064,-37.900188446],"type":"Point"}
}