{
  "type": "Feature",
  "properties": {
    "iso:country":"AU",
    "sg:address":"Cherry Crs",
    "sg:city":"Braybrook",
    "sg:classifiers":[
        {
            "category":"Education",
            "subcategory":"Kindergarten",
            "type":"Public Place"
        }
    ],
    "sg:phone":"+61 3 9311 2207",
    "sg:postcode":"3019",
    "sg:province":"VIC",
    "sg:tags":[
        "pre-schools"
    ],
    "wof:name":"Cherry Crescent Pre-School",
    "wof:placetype":"venue"
},
  "geometry": {"coordinates":[144.85386657699999,-37.7846488953],"type":"Point"}
}