{
  "type": "Feature",
  "properties": {
    "iso:country":"AU",
    "sg:address":"U1/ 89 McNamara Ave",
    "sg:city":"Airport West",
    "sg:classifiers":[
        {
            "category":"Personal",
            "subcategory":"Beauty Salon",
            "type":"Services"
        }
    ],
    "sg:phone":"+61 3 9338 5443",
    "sg:postcode":"3042",
    "sg:province":"VIC",
    "sg:tags":[
        "hairdresser"
    ],
    "wof:name":"Funked Hair-Studio",
    "wof:placetype":"venue"
},
  "geometry": {"coordinates":[144.88145446799999,-37.7240333557],"type":"Point"}
}