{
  "type": "Feature",
  "properties": {
    "iso:country":"AU",
    "sg:address":"Hazeldean Rd",
    "sg:city":"Cloverlea",
    "sg:classifiers":[
        {
            "category":"Shopping",
            "type":"Retail Goods"
        }
    ],
    "sg:phone":"+61 3 5627 8419",
    "sg:postcode":"3822",
    "sg:province":"VIC",
    "sg:tags":[
        "agent",
        "stock"
    ],
    "wof:name":"Peachey D W & E C",
    "wof:placetype":"venue"
},
  "geometry": {"coordinates":[146.00376900000001,-38.244041],"type":"Point"}
}