{
  "type": "Feature",
  "properties": {
    "iso:country":"AU",
    "sg:address":"4 Foambark Crt",
    "sg:city":"Eatons Hill",
    "sg:classifiers":[
        {
            "category":"Professional",
            "subcategory":"Accounting & Tax Preparation",
            "type":"Services"
        }
    ],
    "sg:phone":"+61 433 928 277",
    "sg:postcode":"4037",
    "sg:province":"QLD",
    "sg:tags":[
        "bookkeeping"
    ],
    "wof:name":"Abacus Admin Services",
    "wof:placetype":"venue"
},
  "geometry": {"coordinates":[152.943115,-27.342466],"type":"Point"}
}