{
  "type": "Feature",
  "properties": {
    "iso:country":"AU",
    "sg:address":"7 Bilkurra St",
    "sg:city":"Tamworth",
    "sg:classifiers":[
        {
            "category":"Shopping",
            "subcategory":"Crafts & Fabrics",
            "type":"Retail Goods"
        }
    ],
    "sg:phone":"+61 2 6762 5849",
    "sg:postcode":"2340",
    "sg:province":"NSW",
    "sg:tags":[
        "supply"
    ],
    "wof:name":"Little Angel Country Craft",
    "wof:placetype":"venue"
},
  "geometry": {"coordinates":[150.92424011200001,-31.1157131195],"type":"Point"}
}