{
  "type": "Feature",
  "properties": {
    "addr:full":"35 Jilliby Rd Jilliby NSW 2259",
    "addr:housenumber":"35",
    "addr:postcode":"2259",
    "addr:street":"Jilliby Rd",
    "iso:country":"AU",
    "sg:address":"35 Jilliby Rd",
    "sg:city":"Jilliby",
    "sg:classifiers":[
        {
            "category":"Professional",
            "subcategory":"Engineering",
            "type":"Services"
        }
    ],
    "sg:phone":"+61 2 4351 2624",
    "sg:postcode":"2259",
    "sg:province":"NSW",
    "sg:tags":[
        "electrical",
        "engineer"
    ],
    "wof:name":"Greg Hocking Electrical",
    "wof:placetype":"venue"
},
  "geometry": {"coordinates":[151.384109497,-33.255821228],"type":"Point"}
}