{
  "type": "Feature",
  "properties": {
    "addr:full":"1 June St Coffs Harbour NSW 2450",
    "addr:housenumber":"1",
    "addr:postcode":"2450",
    "addr:street":"June St",
    "iso:country":"AU",
    "sg:address":"1 June St",
    "sg:city":"Coffs Harbour",
    "sg:classifiers":[
        {
            "category":"Autos & Motor Vehicles",
            "subcategory":"Fuel & Gas Station",
            "type":"Retail Goods"
        }
    ],
    "sg:phone":"+61 2 6652 4700",
    "sg:postcode":"2450",
    "sg:province":"NSW",
    "wof:name":"Bob Gately Mechanical Repairs Pty Ltd",
    "wof:placetype":"venue"
},
  "geometry": {"coordinates":[153.11523399999999,-30.290306],"type":"Point"}
}