{
  "type": "Feature",
  "properties": {
    "addr:full":"Croydon Rd Karratha WA 6714",
    "addr:postcode":"6714",
    "addr:street":"Croydon Rd",
    "iso:country":"AU",
    "sg:address":"Croydon Rd",
    "sg:city":"Karratha",
    "sg:classifiers":[
        {
            "category":"Building & Trades",
            "subcategory":"Construction",
            "type":"Services"
        }
    ],
    "sg:phone":"+61 8 9185 2252",
    "sg:postcode":"6714",
    "sg:province":"WA",
    "sg:tags":[
        "window",
        "aluminium"
    ],
    "wof:name":"P.A.F. Aluminium Fabrications",
    "wof:placetype":"venue"
},
  "geometry": {"coordinates":[116.860931397,-20.7708683014],"type":"Point"}
}