{
  "type": "Feature",
  "properties": {
    "addr:full":"Unit 3, 98 Payten Ave Roselands NSW 2196",
    "addr:housenumber":"98",
    "addr:postcode":"2196",
    "addr:street":"Payten Ave Roselands",
    "iso:country":"AU",
    "sg:address":"Unit 3, 98 Payten Ave",
    "sg:city":"Roselands",
    "sg:classifiers":[
        {
            "category":"Manufacturing",
            "subcategory":"Metals",
            "type":"Manufacturing & Wholesale Goods"
        }
    ],
    "sg:phone":"+61 2 9740 6166",
    "sg:postcode":"2196",
    "sg:province":"NSW",
    "sg:tags":[
        "fabricator",
        "aluminium"
    ],
    "wof:name":"Davis Aluminium Architectural",
    "wof:placetype":"venue"
},
  "geometry": {"coordinates":[151.06568899999999,-33.934212],"type":"Point"}
}