{
  "type": "Feature",
  "properties": {
    "iso:country":"AU",
    "sg:address":"2/ 516 Alexander Drv",
    "sg:city":"Malaga",
    "sg:classifiers":[
        {
            "category":"Home & Garden",
            "subcategory":"Hardware",
            "type":"Retail Goods"
        }
    ],
    "sg:phone":"+61 8 9209 3599",
    "sg:postcode":"6090",
    "sg:province":"WA",
    "sg:tags":[
        "repair",
        "tool",
        "power"
    ],
    "wof:name":"Glenfords Discounts Tool Centres",
    "wof:placetype":"venue"
},
  "geometry": {"coordinates":[115.878929138,-31.8616886139],"type":"Point"}
}