{
  "type": "Feature",
  "properties": {
    "iso:country":"AU",
    "sg:address":"Cape Hawk Drv",
    "sg:city":"Forster",
    "sg:classifiers":[
        {
            "category":"Social Services",
            "subcategory":"Retirement Home",
            "type":"Services"
        }
    ],
    "sg:phone":"+61 2 6555 4444",
    "sg:postcode":"2428",
    "sg:province":"NSW",
    "sg:tags":[
        "village"
    ],
    "wof:name":"Golden Ponds",
    "wof:placetype":"venue"
},
  "geometry": {"coordinates":[152.527237,-32.213783],"type":"Point"}
}