{
  "type": "Feature",
  "properties": {
    "addr:full":"18 Main St Arthurton SA 5572",
    "addr:housenumber":"18",
    "addr:postcode":"5572",
    "addr:street":"Main St",
    "iso:country":"AU",
    "sg:address":"18 Main St",
    "sg:city":"Arthurton",
    "sg:classifiers":[
        {
            "category":"Commercial Area",
            "type":"Public Place"
        }
    ],
    "sg:phone":"+61 428 351 261",
    "sg:postcode":"5572",
    "sg:province":"SA",
    "sg:tags":[
        "heavy",
        "carrier"
    ],
    "wof:name":"Willmott R L & H J",
    "wof:placetype":"venue"
},
  "geometry": {"coordinates":[137.756591797,-34.2587013245],"type":"Point"}
}