{
  "type": "Feature",
  "properties": {
    "addr:full":"23 Peel St Toukley NSW 2263",
    "addr:housenumber":"23",
    "addr:postcode":"2263",
    "addr:street":"Peel St",
    "iso:country":"AU",
    "sg:address":"23 Peel St",
    "sg:city":"Toukley",
    "sg:classifiers":[
        {
            "category":"Building & Trades",
            "subcategory":"Construction",
            "type":"Services"
        }
    ],
    "sg:phone":"+61 417 411 596",
    "sg:postcode":"2263",
    "sg:province":"NSW",
    "sg:tags":[
        "contractor"
    ],
    "wof:name":"Glenryan Constructions Pty Ltd",
    "wof:placetype":"venue"
},
  "geometry": {"coordinates":[151.53947400000001,-33.261662],"type":"Point"}
}