{
  "type": "Feature",
  "properties": {
    "iso:country":"AU",
    "sg:address":"134 Centre Dandenong Rd",
    "sg:city":"Dingley",
    "sg:classifiers":[
        {
            "category":"Health Services",
            "subcategory":"Dentist",
            "type":"Services"
        }
    ],
    "sg:phone":"+61 3 9552 5521",
    "sg:postcode":"3172",
    "sg:province":"VIC",
    "sg:tags":[
        "dental",
        "prosthetist"
    ],
    "wof:name":"Tibballs Warwick",
    "wof:placetype":"venue"
},
  "geometry": {"coordinates":[145.130859375,-37.9828224182],"type":"Point"}
}