{
  "type": "Feature",
  "properties": {
    "iso:country":"AU",
    "sg:address":"PO Box 105",
    "sg:city":"Bundanoon",
    "sg:classifiers":[
        {
            "category":"Shopping",
            "subcategory":"Antiques",
            "type":"Retail Goods"
        }
    ],
    "sg:phone":"+61 412 203 155",
    "sg:postcode":"2578",
    "sg:province":"NSW",
    "wof:name":"Maree's Collection",
    "wof:placetype":"venue"
},
  "geometry": {"coordinates":[150.2996521,-34.6564483643],"type":"Point"}
}