{
  "type": "Feature",
  "properties": {
    "addr:full":"12 Regent St Melrose Park SA 5039",
    "addr:housenumber":"12",
    "addr:postcode":"5039",
    "addr:street":"Regent St",
    "iso:country":"AU",
    "sg:address":"12 Regent St",
    "sg:city":"Melrose Park",
    "sg:classifiers":[
        {
            "category":"Professional",
            "type":"Services"
        }
    ],
    "sg:phone":"+61 8 8276 2352",
    "sg:postcode":"5039",
    "sg:province":"SA",
    "sg:tags":[
        "shop",
        "fitting"
    ],
    "wof:name":"Weepers Alan R",
    "wof:placetype":"venue"
},
  "geometry": {"coordinates":[138.57473754899999,-34.981754303],"type":"Point"}
}