{
  "type": "Feature",
  "properties": {
    "addr:full":"193 Brisbane Rd Mooloolaba QLD 4557",
    "addr:housenumber":"193",
    "addr:postcode":"4557",
    "addr:street":"Brisbane Rd",
    "iso:country":"AU",
    "sg:address":"193 Brisbane Rd",
    "sg:city":"Mooloolaba",
    "sg:classifiers":[
        {
            "category":"Autos & Motor Vehicles",
            "subcategory":"Automobile Sales",
            "type":"Retail Goods"
        }
    ],
    "sg:phone":"+61 7 5478 0833",
    "sg:postcode":"4557",
    "sg:province":"QLD",
    "sg:tags":[
        "car",
        "used"
    ],
    "wof:name":"Henderson Cars",
    "wof:placetype":"venue"
},
  "geometry": {"coordinates":[153.115234375,-26.6936683655],"type":"Point"}
}