{
  "type": "Feature",
  "properties": {
    "addr:full":"6 St Michaels Drv Tarneit VIC 3029",
    "addr:housenumber":"6",
    "addr:postcode":"3029",
    "addr:street":"St Michaels Drv",
    "iso:country":"AU",
    "sg:address":"6 St Michaels Drv",
    "sg:city":"Tarneit",
    "sg:classifiers":[
        {
            "category":"Building & Trades",
            "subcategory":"Construction",
            "type":"Services"
        }
    ],
    "sg:phone":"+61 3 9748 5155",
    "sg:postcode":"3029",
    "sg:province":"VIC",
    "sg:tags":[
        "contractor"
    ],
    "wof:name":"Zadun Homes",
    "wof:placetype":"venue"
},
  "geometry": {"coordinates":[144.71064799999999,-37.849705],"type":"Point"}
}