{
  "type": "Feature",
  "properties": {
    "addr:full":"U 9/ 40 Charles St St Marys NSW 2760",
    "addr:housenumber":"40",
    "addr:postcode":"2760",
    "addr:street":"Charles St",
    "iso:country":"AU",
    "sg:address":"U 9/ 40 Charles St St",
    "sg:city":"Marys",
    "sg:classifiers":[
        {
            "category":"Shopping",
            "subcategory":"Computers & Home Electronics",
            "type":"Retail Goods"
        }
    ],
    "sg:phone":"+61 2 9623 5423",
    "sg:postcode":"2760",
    "sg:province":"NSW",
    "sg:tags":[
        "equipment",
        "supply"
    ],
    "wof:name":"CDS Computer Source",
    "wof:placetype":"venue"
},
  "geometry": {"coordinates":[150.76893615700001,-33.744052887],"type":"Point"}
}