{
  "type": "Feature",
  "properties": {
    "addr:full":"57 Bay St Balcolyn NSW 2264",
    "addr:housenumber":"57",
    "addr:postcode":"2264",
    "addr:street":"Bay St",
    "iso:country":"AU",
    "sg:address":"57 Bay St",
    "sg:city":"Balcolyn",
    "sg:classifiers":[
        {
            "category":"Personal",
            "subcategory":"Massage",
            "type":"Services"
        }
    ],
    "sg:phone":"+61 2 4973 1433",
    "sg:postcode":"2264",
    "sg:province":"NSW",
    "sg:tags":[
        "therapy"
    ],
    "wof:name":"Eastern Massage",
    "wof:placetype":"venue"
},
  "geometry": {"coordinates":[151.50282300000001,-33.085026],"type":"Point"}
}