{
  "type": "Feature",
  "properties": {
    "iso:country":"AU",
    "sg:address":"Cnr Ascot & Dana Sts",
    "sg:city":"Ballarat",
    "sg:classifiers":[
        {
            "category":"Travel",
            "subcategory":"Hostel",
            "type":"Entertainment"
        }
    ],
    "sg:phone":"+61 3 5320 3619",
    "sg:postcode":"3350",
    "sg:province":"VIC",
    "sg:tags":[
        "home"
    ],
    "wof:name":"Hailey House (Q.E.G.B.)",
    "wof:placetype":"venue"
},
  "geometry": {"coordinates":[143.85737599999999,-37.581841],"type":"Point"}
}