{
  "type": "Feature",
  "properties": {
    "addr:full":"101 Mary St Gympie QLD 4570",
    "addr:housenumber":"101",
    "addr:postcode":"4570",
    "addr:street":"Mary St",
    "iso:country":"AU",
    "sg:address":"101 Mary St",
    "sg:city":"Gympie",
    "sg:classifiers":[
        {
            "category":"Professional",
            "subcategory":"Accounting & Tax Preparation",
            "type":"Services"
        }
    ],
    "sg:phone":"+61 7 5482 2855",
    "sg:postcode":"4570",
    "sg:province":"QLD",
    "sg:tags":[
        "consultant",
        "taxation"
    ],
    "wof:name":"Schuh & Company",
    "wof:placetype":"venue"
},
  "geometry": {"coordinates":[152.66262817399999,-26.1900691986],"type":"Point"}
}