{
  "type": "Feature",
  "properties": {
    "addr:full":"7 Newton Crt Seaholme VIC 3018",
    "addr:housenumber":"7",
    "addr:postcode":"3018",
    "addr:street":"Newton Crt",
    "iso:country":"AU",
    "sg:address":"7 Newton Crt",
    "sg:city":"Seaholme",
    "sg:classifiers":[
        {
            "category":"Shopping",
            "subcategory":"Computers & Home Electronics",
            "type":"Retail Goods"
        }
    ],
    "sg:phone":"+61 411 817 962",
    "sg:postcode":"3018",
    "sg:province":"VIC",
    "sg:tags":[
        "hi-fi",
        "equipment"
    ],
    "wof:name":"Audio Improvement",
    "wof:placetype":"venue"
},
  "geometry": {"coordinates":[144.844802856,-37.8592681885],"type":"Point"}
}