{
  "type": "Feature",
  "properties": {
    "iso:country":"AU",
    "sg:address":"Ste 1/ 45 Ringwood St",
    "sg:city":"Ringwood",
    "sg:classifiers":[
        {
            "category":"Building & Trades",
            "subcategory":"Landscaping Services",
            "type":"Services"
        }
    ],
    "sg:phone":"+61 3 9879 4935",
    "sg:postcode":"3134",
    "sg:province":"VIC",
    "sg:tags":[
        "consultant"
    ],
    "wof:name":"Build Assess",
    "wof:placetype":"venue"
},
  "geometry": {"coordinates":[145.227172852,-37.8116035461],"type":"Point"}
}