{
  "type": "Feature",
  "properties": {
    "iso:country":"AU",
    "sg:address":"181 Greville St",
    "sg:city":"Prahran",
    "sg:classifiers":[
        {
            "category":"Shopping",
            "subcategory":"Jewelry",
            "type":"Retail Goods"
        }
    ],
    "sg:phone":"+61 3 9510 1480",
    "sg:postcode":"3181",
    "sg:province":"VIC",
    "sg:tags":[
        "jeweller"
    ],
    "wof:name":"Palm Beads",
    "wof:placetype":"venue"
},
  "geometry": {"coordinates":[144.99290466299999,-37.849319458],"type":"Point"}
}