{
  "type": "Feature",
  "properties": {
    "iso:country":"AU",
    "sg:address":"1/1 Male St Cnr Well St",
    "sg:city":"Brighton",
    "sg:classifiers":[
        {
            "category":"Health Services",
            "subcategory":"Doctor",
            "type":"Services"
        }
    ],
    "sg:phone":"+61 3 9592 9000",
    "sg:postcode":"3186",
    "sg:province":"VIC",
    "sg:tags":[
        "podiatrist"
    ],
    "wof:name":"A Caring Practice",
    "wof:placetype":"venue"
},
  "geometry": {"coordinates":[144.992675781,-37.9140167236],"type":"Point"}
}