{
  "type": "Feature",
  "properties": {
    "addr:full":"Shop 10, 53 Old Perth Rd Bassendean WA 6054",
    "addr:housenumber":"shop 10 53",
    "addr:postcode":"6054",
    "addr:street":"Old Perth Rd",
    "iso:country":"AU",
    "sg:address":"Shop 10, 53 Old Perth Rd",
    "sg:city":"Bassendean",
    "sg:classifiers":[
        {
            "category":"Communications",
            "subcategory":"Film & Video Production",
            "type":"Services"
        }
    ],
    "sg:phone":"+61 8 9279 6626",
    "sg:postcode":"6054",
    "sg:province":"WA",
    "sg:tags":[
        "dvd",
        "library"
    ],
    "wof:name":"Bassendean Video Library",
    "wof:placetype":"venue"
},
  "geometry": {"coordinates":[115.950622559,-31.9046344757],"type":"Point"}
}