{
  "type": "Feature",
  "properties": {
    "addr:full":"258 Seabrook Rd Somerset TAS 7322",
    "addr:housenumber":"258",
    "addr:postcode":"7322",
    "addr:street":"Seabrook Rd",
    "iso:country":"AU",
    "sg:address":"258 Seabrook Rd",
    "sg:city":"Somerset",
    "sg:classifiers":[
        {
            "category":"Farming",
            "subcategory":"Farm",
            "type":"Manufacturing & Wholesale Goods"
        }
    ],
    "sg:phone":"+61 3 6435 1379",
    "sg:postcode":"7322",
    "sg:province":"TAS",
    "sg:tags":[
        "farmer"
    ],
    "wof:name":"Paul C L",
    "wof:placetype":"venue"
},
  "geometry": {"coordinates":[145.786407,-41.051113],"type":"Point"}
}