{
  "type": "Feature",
  "properties": {
    "addr:full":"30 Gloucester Rd Epping NSW 2121",
    "addr:housenumber":"30",
    "addr:postcode":"2121",
    "addr:street":"Gloucester Rd",
    "iso:country":"AU",
    "sg:address":"30 Gloucester Rd",
    "sg:city":"Epping",
    "sg:classifiers":[
        {
            "category":"Professional",
            "subcategory":"Management & Consulting",
            "type":"Services"
        }
    ],
    "sg:phone":"+61 2 9876 2994",
    "sg:postcode":"2121",
    "sg:province":"NSW",
    "sg:tags":[
        "consultant",
        "industrial",
        "relation"
    ],
    "wof:name":"Richardson Keith",
    "wof:placetype":"venue"
},
  "geometry": {"coordinates":[151.09364318900001,-33.7682189941],"type":"Point"}
}