{
  "type": "Feature",
  "properties": {
    "iso:country":"AU",
    "sg:address":"Cnr Alexander Drv & Illawarra Crs",
    "sg:city":"Ballajura",
    "sg:classifiers":[
        {
            "category":"Autos & Motor Vehicles",
            "subcategory":"Fuel & Gas Station",
            "type":"Retail Goods"
        }
    ],
    "sg:phone":"+61 8 9249 1317",
    "sg:postcode":"6066",
    "sg:province":"WA",
    "wof:name":"BP",
    "wof:placetype":"venue"
},
  "geometry": {"coordinates":[116.125228882,-32.0877494812],"type":"Point"}
}