{
  "type": "Feature",
  "properties": {
    "addr:full":"Unit 10/ 615 Seventeen Mile Rocks Rd Seventeen Mile Rocks QLD 4073",
    "addr:housenumber":"/ 615",
    "addr:postcode":"4073",
    "addr:street":"Seventeen Mile Rocks Rd",
    "iso:country":"AU",
    "sg:address":"Unit 10/ 615 Seventeen Mile Rocks Rd",
    "sg:city":"Seventeen Mile Rocks",
    "sg:classifiers":[
        {
            "category":"Professional",
            "subcategory":"Accounting & Tax Preparation",
            "type":"Services"
        }
    ],
    "sg:phone":"+61 7 3376 3711",
    "sg:postcode":"4073",
    "sg:province":"QLD",
    "sg:tags":[
        "accountant",
        "auditor"
    ],
    "wof:name":"Chiverall & Bulley",
    "wof:placetype":"venue"
},
  "geometry": {"coordinates":[152.953811645,-27.5398235321],"type":"Point"}
}