{
  "type": "Feature",
  "properties": {
    "iso:country":"AU",
    "sg:address":"PO Box 107",
    "sg:city":"Gordonvale",
    "sg:classifiers":[
        {
            "category":"Building & Trades",
            "subcategory":"Construction",
            "type":"Services"
        }
    ],
    "sg:phone":"+61 418 770 749",
    "sg:postcode":"4865",
    "sg:province":"QLD",
    "sg:tags":[
        "contractor"
    ],
    "wof:name":"Morris WT & Sons Pty Ltd",
    "wof:placetype":"venue"
},
  "geometry": {"coordinates":[145.78074645999999,-17.0994606018],"type":"Point"}
}