{
  "type": "Feature",
  "properties": {
    "iso:country":"AU",
    "sg:address":"739 Raglan Pde",
    "sg:city":"Warrnambool",
    "sg:classifiers":[
        {
            "category":"Food & Beverages",
            "subcategory":"Bakery",
            "type":"Retail Goods"
        }
    ],
    "sg:phone":"+61 3 5562 7927",
    "sg:postcode":"3280",
    "sg:province":"VIC",
    "sg:tags":[
        "baker"
    ],
    "wof:name":"Reeves Bakery",
    "wof:placetype":"venue"
},
  "geometry": {"coordinates":[142.48138427699999,-38.3780288696],"type":"Point"}
}