{
  "type": "Feature",
  "properties": {
    "iso:country":"AU",
    "sg:address":"17/ 11 Macrossan St",
    "sg:city":"Port Douglas",
    "sg:classifiers":[
        {
            "category":"Health Services",
            "subcategory":"Doctor",
            "type":"Services"
        }
    ],
    "sg:phone":"+61 7 4099 5043",
    "sg:postcode":"4877",
    "sg:province":"QLD",
    "sg:tags":[
        "medical",
        "practitioner"
    ],
    "wof:name":"Port Village Medical Centre",
    "wof:placetype":"venue"
},
  "geometry": {"coordinates":[145.46788024899999,-16.4853153229],"type":"Point"}
}