{
  "type": "Feature",
  "properties": {
    "addr:full":"236 Mickleham Rd Gladstone Park VIC 3043",
    "addr:housenumber":"236",
    "addr:postcode":"3043",
    "addr:street":"Mickleham Rd",
    "iso:country":"AU",
    "sg:address":"236 Mickleham Rd",
    "sg:city":"Gladstone Park",
    "sg:classifiers":[
        {
            "category":"Personal",
            "subcategory":"Hair Removal",
            "type":"Services"
        }
    ],
    "sg:phone":"+61 3 9310 3108",
    "sg:postcode":"3043",
    "sg:province":"VIC",
    "wof:name":"Manhattan Laser & Aesthetic Centre",
    "wof:placetype":"venue"
},
  "geometry": {"coordinates":[144.883377075,-37.6846389771],"type":"Point"}
}