{
  "type": "Feature",
  "properties": {
    "addr:full":"333 Sydney Rd Balgowlah NSW 2093",
    "addr:housenumber":"333",
    "addr:postcode":"2093",
    "addr:street":"Sydney Rd",
    "iso:country":"AU",
    "sg:address":"333 Sydney Rd",
    "sg:city":"Balgowlah",
    "sg:classifiers":[
        {
            "category":"Personal",
            "subcategory":"Beauty Salon",
            "type":"Services"
        }
    ],
    "sg:phone":"+61 2 9948 3922",
    "sg:postcode":"2093",
    "sg:province":"NSW",
    "sg:tags":[
        "hairdresser"
    ],
    "wof:name":"Cutting Company The",
    "wof:placetype":"venue"
},
  "geometry": {"coordinates":[151.26510620100001,-33.7944869995],"type":"Point"}
}