{
  "type": "Feature",
  "properties": {
    "iso:country":"AU",
    "sg:address":"670 Goulburn Valley Hwy",
    "sg:city":"Congupna",
    "sg:classifiers":[
        {
            "category":"Communications",
            "type":"Services"
        }
    ],
    "sg:phone":"+61 3 5821 5637",
    "sg:postcode":"3633",
    "sg:province":"VIC",
    "sg:tags":[
        "public",
        "system",
        "address"
    ],
    "wof:name":"Hi Class Sound Hire",
    "wof:placetype":"venue"
},
  "geometry": {"coordinates":[145.47361755399999,-36.2877388],"type":"Point"}
}