{
  "type": "Feature",
  "properties": {
    "addr:full":"PO Box 3155 Bracken Ridge QLD 4017",
    "addr:postcode":"4017",
    "iso:country":"AU",
    "sg:address":"PO Box 3155",
    "sg:city":"Bracken Ridge",
    "sg:classifiers":[
        {
            "category":"Professional",
            "subcategory":"Employment Agencies",
            "type":"Services"
        }
    ],
    "sg:phone":"+61 408 076 874",
    "sg:postcode":"4017",
    "sg:province":"QLD",
    "sg:tags":[
        "occupational",
        "therapist"
    ],
    "wof:name":"Amanda Lee",
    "wof:placetype":"venue"
},
  "geometry": {"coordinates":[153.026245117,-27.3311405182],"type":"Point"}
}