{
  "type": "Feature",
  "properties": {
    "addr:full":"Unit 5/ 5 Commerce Crt Noosaville QLD 4566",
    "addr:postcode":"4566",
    "addr:street":"Commerce Crt",
    "iso:country":"AU",
    "sg:address":"Unit 5/ 5 Commerce Crt",
    "sg:city":"Noosaville",
    "sg:classifiers":[
        {
            "category":"Health Services",
            "subcategory":"Doctor",
            "type":"Services"
        }
    ],
    "sg:phone":"+61 7 5440 5678",
    "sg:postcode":"4566",
    "sg:province":"QLD",
    "sg:tags":[
        "occupational",
        "safety"
    ],
    "wof:name":"Safetywave",
    "wof:placetype":"venue"
},
  "geometry": {"coordinates":[153.04600524899999,-26.4116668701],"type":"Point"}
}