{
  "type": "Feature",
  "properties": {
    "addr:full":"Unit 3 937 Marion Rd Mitchell Park SA 5043",
    "addr:housenumber":"937",
    "addr:postcode":"5043",
    "addr:street":"Marion Rd",
    "iso:country":"AU",
    "sg:address":"Unit 3 937 Marion Rd",
    "sg:city":"Mitchell Park",
    "sg:classifiers":[
        {
            "category":"Home & Garden",
            "subcategory":"Hardware",
            "type":"Retail Goods"
        }
    ],
    "sg:phone":"+61 414 400 596",
    "sg:postcode":"5043",
    "sg:province":"SA",
    "sg:tags":[
        "repair",
        "tool",
        "power"
    ],
    "wof:name":"Electric Air Services",
    "wof:placetype":"venue"
},
  "geometry": {"coordinates":[138.55873099999999,-35.013737],"type":"Point"}
}