{
  "type": "Feature",
  "properties": {
    "addr:full":"50 Meera St Cornubia QLD 4130",
    "addr:housenumber":"50",
    "addr:postcode":"4130",
    "addr:street":"Meera St",
    "iso:country":"AU",
    "sg:address":"50 Meera St",
    "sg:city":"Cornubia",
    "sg:classifiers":[
        {
            "category":"Building & Trades",
            "subcategory":"Cleaning & Sanitation",
            "type":"Services"
        }
    ],
    "sg:phone":"+61 413 693 316",
    "sg:postcode":"4130",
    "sg:province":"QLD",
    "sg:tags":[
        "industrial",
        "commercial",
        "contractor"
    ],
    "wof:name":"Advanced Pizza Oven Cleaning",
    "wof:placetype":"venue"
},
  "geometry": {"coordinates":[153.20130920400001,-27.6645412445],"type":"Point"}
}