{
  "type": "Feature",
  "properties": {
    "addr:full":"Bongaree Amcal Pharmacy, 85 Welsby Pde Bribie Island QLD 4507",
    "addr:housenumber":"85",
    "addr:postcode":"4507",
    "addr:street":"Welsby Pde",
    "iso:country":"AU",
    "sg:address":"Bongaree Amcal Pharmacy, 85 Welsby Pde",
    "sg:city":"Bribie Island",
    "sg:classifiers":[
        {
            "category":"Banks & Credit Unions",
            "subcategory":"Financial Services",
            "type":"Services"
        }
    ],
    "sg:phone":"+61 7 3408 4700",
    "sg:postcode":"4507",
    "sg:province":"QLD",
    "sg:tags":[
        "building",
        "society"
    ],
    "wof:name":"Heritage Building Society",
    "wof:placetype":"venue"
},
  "geometry": {"coordinates":[153.15388488799999,-27.0646896362],"type":"Point"}
}