{
  "type": "Feature",
  "properties": {
    "addr:full":"Postcode 258 Port Melbourne VIC 3207",
    "addr:housenumber":"258",
    "addr:postcode":"3207",
    "addr:street":"Postcode",
    "iso:country":"AU",
    "sg:address":"Postcode 258",
    "sg:city":"Port Melbourne",
    "sg:classifiers":[
        {
            "category":"Retail",
            "subcategory":"Storage",
            "type":"Services"
        }
    ],
    "sg:phone":"+61 1300 887 440",
    "sg:postcode":"3207",
    "sg:province":"VIC",
    "sg:tags":[
        "removal",
        "furniture"
    ],
    "wof:name":"Allen Moving & Storage",
    "wof:placetype":"venue"
},
  "geometry": {"coordinates":[144.90086400000001,-37.829887],"type":"Point"}
}