{
  "type": "Feature",
  "properties": {
    "iso:country":"AU",
    "sg:address":"155-159 William St",
    "sg:city":"Darlinghurst",
    "sg:classifiers":[
        {
            "category":"Autos & Motor Vehicles",
            "subcategory":"Automobile Sales",
            "type":"Retail Goods"
        }
    ],
    "sg:phone":"+61 2 9360 2177",
    "sg:postcode":"2010",
    "sg:province":"NSW",
    "sg:tags":[
        "car",
        "new"
    ],
    "wof:name":"Travel Wheels",
    "wof:placetype":"venue"
},
  "geometry": {"coordinates":[151.21870422399999,-33.8748931885],"type":"Point"}
}