{
  "type": "Feature",
  "properties": {
    "addr:full":"550 Brushfields Rd Bellbrae VIC 3228",
    "addr:housenumber":"550",
    "addr:postcode":"3228",
    "addr:street":"Brushfields Rd",
    "iso:country":"AU",
    "sg:address":"550 Brushfields Rd",
    "sg:city":"Bellbrae",
    "sg:classifiers":[
        {
            "category":"Retail",
            "subcategory":"Storage",
            "type":"Services"
        }
    ],
    "sg:phone":"+61 3 5261 3610",
    "sg:postcode":"3228",
    "sg:province":"VIC",
    "wof:name":"All-Undercover",
    "wof:placetype":"venue"
},
  "geometry": {"coordinates":[144.241455,-38.333248],"type":"Point"}
}