{
  "type": "Feature",
  "properties": {
    "addr:full":"80 Roscommon Rd Boondall QLD 4034",
    "addr:housenumber":"80",
    "addr:postcode":"4034",
    "addr:street":"Roscommon Rd",
    "iso:country":"AU",
    "sg:address":"80 Roscommon Rd",
    "sg:city":"Boondall",
    "sg:classifiers":[
        {
            "category":"Personal",
            "subcategory":"Massage",
            "type":"Services"
        }
    ],
    "sg:phone":"+61 7 3881 2233",
    "sg:postcode":"4034",
    "sg:province":"QLD",
    "sg:tags":[
        "therapy"
    ],
    "wof:name":"Mette's Institute Of Body Work & Personal Development",
    "wof:placetype":"venue"
},
  "geometry": {"coordinates":[153.06127900000001,-27.352949],"type":"Point"}
}