{
  "type": "Feature",
  "properties": {
    "addr:full":"Suite 25, Colonial Arcade 25-27 Hay St Port Macquarie NSW 2444",
    "addr:housenumber":"25-27",
    "addr:postcode":"2444",
    "addr:street":"Hay St",
    "iso:country":"AU",
    "sg:address":"Suite 25, Colonial Arcade 25-27 Hay St",
    "sg:city":"Port Macquarie",
    "sg:classifiers":[
        {
            "category":"Government",
            "subcategory":"Customs House",
            "type":"Public Place"
        }
    ],
    "sg:phone":"+61 2 6584 9266",
    "sg:postcode":"2444",
    "sg:province":"NSW",
    "sg:tags":[
        "title",
        "management",
        "stratum"
    ],
    "wof:name":"Vincent Duggan Pty Ltd",
    "wof:placetype":"venue"
},
  "geometry": {"coordinates":[152.90939299999999,-31.430124],"type":"Point"}
}