{
  "type": "Feature",
  "properties": {
    "addr:full":"South Coast Head Office 215 Princes Hwy Albion Park Rail NSW 2527",
    "addr:housenumber":"215",
    "addr:postcode":"2527",
    "addr:street":"South;Princes Hwy Albion",
    "iso:country":"AU",
    "sg:address":"South Coast Head Office 215 Princes Hwy",
    "sg:city":"Albion Park Rail",
    "sg:classifiers":[
        {
            "category":"Building & Trades",
            "subcategory":"Construction",
            "type":"Services"
        }
    ],
    "sg:phone":"+61 2 4256 1500",
    "sg:postcode":"2527",
    "sg:province":"NSW",
    "sg:tags":[
        "contractor"
    ],
    "wof:name":"Masterton Homes Pty Ltd",
    "wof:placetype":"venue"
},
  "geometry": {"coordinates":[150.800384522,-34.5656890869],"type":"Point"}
}