{
  "type": "Feature",
  "properties": {
    "addr:full":"24 Savannah Drv Leanyer NT 0812",
    "addr:housenumber":"24",
    "addr:postcode":"nt 0812",
    "addr:street":"Savannah Drv",
    "iso:country":"AU",
    "sg:address":"24 Savannah Drv",
    "sg:city":"Leanyer",
    "sg:classifiers":[
        {
            "category":"Building & Trades",
            "subcategory":"Construction",
            "type":"Services"
        }
    ],
    "sg:phone":"+61 407 277 036",
    "sg:postcode":"0812",
    "sg:province":"NT",
    "sg:tags":[
        "concrete",
        "contractor"
    ],
    "wof:name":"Kurbis Building & Contracting Pty Ltd",
    "wof:placetype":"venue"
},
  "geometry": {"coordinates":[130.89970400000001,-12.380012],"type":"Point"}
}