{
  "type": "Feature",
  "properties": {
    "addr:full":"54- 62 Worland Rd Wangaratta VIC 3677",
    "addr:housenumber":"62",
    "addr:postcode":"3677",
    "addr:street":"Worland Rd",
    "iso:country":"AU",
    "sg:address":"54- 62 Worland Rd",
    "sg:city":"Wangaratta",
    "sg:classifiers":[
        {
            "category":"Building & Trades",
            "subcategory":"Landscaping Services",
            "type":"Services"
        }
    ],
    "sg:phone":"+61 3 5721 3141",
    "sg:postcode":"3677",
    "sg:province":"VIC",
    "sg:tags":[
        "stump",
        "tree",
        "felling",
        "removal"
    ],
    "wof:name":"Mick Lloyd Tree Lopping & Stump Removal",
    "wof:placetype":"venue"
},
  "geometry": {"coordinates":[146.28782653799999,-36.3519325256],"type":"Point"}
}