{
  "type": "Feature",
  "properties": {
    "iso:country":"AU",
    "sg:address":"Cnr Brown & French St",
    "sg:city":"Hamilton",
    "sg:classifiers":[
        {
            "category":"Autos & Motor Vehicles",
            "subcategory":"Fuel & Gas Station",
            "type":"Retail Goods"
        }
    ],
    "sg:phone":"+61 3 5572 3679",
    "sg:postcode":"3300",
    "sg:province":"VIC",
    "wof:name":"Robco Petroleum Distributors",
    "wof:placetype":"venue"
},
  "geometry": {"coordinates":[142.0234375,-37.7460441589],"type":"Point"}
}