{
  "type": "Feature",
  "properties": {
    "addr:full":"Cnr Showground Rd & Murray Rose Ave Sydney Olympic Park NSW 2127",
    "addr:postcode":"2127",
    "addr:street":"Showground Rd &;Rose Ave",
    "iso:country":"AU",
    "sg:address":"Cnr Showground Rd & Murray Rose Ave",
    "sg:city":"Sydney Olympic Park",
    "sg:classifiers":[
        {
            "category":"Communications",
            "subcategory":"News Services",
            "type":"Services"
        }
    ],
    "sg:phone":"+61 2 9714 7888",
    "sg:postcode":"2127",
    "sg:province":"NSW",
    "sg:tags":[
        "information",
        "tourist",
        "attractions"
    ],
    "wof:name":"Sydney Olympic Park",
    "wof:placetype":"venue"
},
  "geometry": {"coordinates":[151.06755065900001,-33.8468475342],"type":"Point"}
}