{
  "type": "Feature",
  "properties": {
    "iso:country":"AU",
    "sg:address":"67- 101 Macarthur Drv",
    "sg:city":"Annandale",
    "sg:classifiers":[
        {
            "category":"Fast Food",
            "type":"Food & Drink"
        }
    ],
    "sg:phone":"+61 7 4755 0111",
    "sg:postcode":"4814",
    "sg:province":"QLD",
    "sg:tags":[
        "away",
        "take"
    ],
    "wof:name":"Hungry Jacks Pty Ltd",
    "wof:placetype":"venue"
},
  "geometry": {"coordinates":[146.79037500000001,-19.314672],"type":"Point"}
}