{
  "type": "Feature",
  "properties": {
    "addr:full":"39 Pathfinder Rd Padbury WA 6025",
    "addr:housenumber":"39",
    "addr:postcode":"6025",
    "addr:street":"Pathfinder Rd",
    "iso:country":"AU",
    "sg:address":"39 Pathfinder Rd",
    "sg:city":"Padbury",
    "sg:classifiers":[
        {
            "category":"Utilities",
            "subcategory":"Electric",
            "type":"Services"
        }
    ],
    "sg:phone":"+61 410 414 528",
    "sg:postcode":"6025",
    "sg:province":"WA",
    "sg:tags":[
        "electrical",
        "contractor"
    ],
    "wof:name":"Peter Richards Electrical",
    "wof:placetype":"venue"
},
  "geometry": {"coordinates":[115.77217102,-31.8080654144],"type":"Point"}
}