{
  "type": "Feature",
  "properties": {
    "addr:full":"6- 10 Traders Way Currumbin QLD 4223",
    "addr:housenumber":"10",
    "addr:postcode":"4223",
    "addr:street":"6;Traders Way",
    "iso:country":"AU",
    "sg:address":"6- 10",
    "sg:city":"Traders Way Currumbin",
    "sg:classifiers":[
        {
            "category":"Manufacturing",
            "subcategory":"Motor Vehicles & Parts",
            "type":"Manufacturing & Wholesale Goods"
        }
    ],
    "sg:phone":"+61 7 5598 1888",
    "sg:postcode":"4223",
    "sg:province":"QLD",
    "sg:tags":[
        "wholesaler",
        "mfrs",
        "radiator"
    ],
    "wof:name":"K & J Thermal Products",
    "wof:placetype":"venue"
},
  "geometry": {"coordinates":[153.47080993599999,-28.1423492432],"type":"Point"}
}