{
  "type": "Feature",
  "properties": {
    "addr:full":"12 Lambert Rd Indooroopilly QLD 4068",
    "addr:housenumber":"12",
    "addr:postcode":"4068",
    "addr:street":"Lambert Rd",
    "iso:country":"AU",
    "sg:address":"12 Lambert Rd",
    "sg:city":"Indooroopilly",
    "sg:classifiers":[
        {
            "category":"Personal",
            "subcategory":"Beauty Salon",
            "type":"Services"
        }
    ],
    "sg:phone":"+61 7 3870 8500",
    "sg:postcode":"4068",
    "sg:province":"QLD",
    "sg:tags":[
        "hairdresser"
    ],
    "wof:name":"Tony Mitchell Hair",
    "wof:placetype":"venue"
},
  "geometry": {"coordinates":[152.9765625,-27.503194809],"type":"Point"}
}