{
  "type": "Feature",
  "properties": {
    "addr:full":"Kiosk 4 Morayfield Shopng Cntr 165 Morayfield Rd Morayfield QLD 4506",
    "addr:housenumber":"165",
    "addr:postcode":"4506",
    "addr:street":"Morayfield Rd",
    "iso:country":"AU",
    "sg:address":"Kiosk 4 Morayfield Shopng Cntr 165 Morayfield Rd",
    "sg:city":"Morayfield",
    "sg:classifiers":[
        {
            "category":"Fast Food",
            "type":"Food & Drink"
        }
    ],
    "sg:phone":"+61 7 5499 4294",
    "sg:postcode":"4506",
    "sg:province":"QLD",
    "sg:tags":[
        "away",
        "take"
    ],
    "wof:name":"Donut King",
    "wof:placetype":"venue"
},
  "geometry": {"coordinates":[152.950683594,-27.1112518311],"type":"Point"}
}