{
  "type": "Feature",
  "properties": {
    "addr:full":"PO Box 150 Mt Magnet WA 6638",
    "addr:postcode":"6638",
    "iso:country":"AU",
    "sg:address":"PO Box 150",
    "sg:city":"Mt Magnet",
    "sg:classifiers":[
        {
            "category":"Utilities",
            "subcategory":"Water",
            "type":"Services"
        }
    ],
    "sg:phone":"+61 8 9963 4275",
    "sg:postcode":"6638",
    "sg:province":"WA",
    "sg:tags":[
        "cartage"
    ],
    "wof:name":"M.T.F. Services",
    "wof:placetype":"venue"
},
  "geometry": {"coordinates":[117.84941864,-28.0653305054],"type":"Point"}
}