{
  "type": "Feature",
  "properties": {
    "iso:country":"AU",
    "sg:address":"PO Box 1059",
    "sg:city":"Kenmore",
    "sg:classifiers":[
        {
            "category":"Utilities",
            "subcategory":"Electric",
            "type":"Services"
        }
    ],
    "sg:phone":"+61 412 441 318",
    "sg:postcode":"4069",
    "sg:province":"QLD",
    "sg:tags":[
        "electrical",
        "contractor"
    ],
    "wof:name":"Energy Right",
    "wof:placetype":"venue"
},
  "geometry": {"coordinates":[152.93849182100001,-27.508430481],"type":"Point"}
}