{
  "type": "Feature",
  "properties": {
    "addr:full":"Level 5, 152 Elizabeth St Melbourne VIC 3000",
    "addr:housenumber":"152",
    "addr:postcode":"3000",
    "addr:street":"Elizabeth St",
    "iso:country":"AU",
    "sg:address":"Level 5, 152 Elizabeth St",
    "sg:city":"Melbourne",
    "sg:classifiers":[
        {
            "category":"Education",
            "subcategory":"Junior College",
            "type":"Public Place"
        }
    ],
    "sg:phone":"+61 3 9654 5099",
    "sg:postcode":"3000",
    "sg:province":"VIC",
    "sg:tags":[
        "business"
    ],
    "wof:name":"Chalmers Business College",
    "wof:placetype":"venue"
},
  "geometry": {"coordinates":[144.96348571799999,-37.8145675659],"type":"Point"}
}