{
  "type": "Feature",
  "properties": {
    "addr:full":"652 Forest Rd Bexley NSW 2207",
    "addr:housenumber":"652",
    "addr:postcode":"2207",
    "addr:street":"Forest Rd",
    "iso:country":"AU",
    "sg:address":"652 Forest Rd",
    "sg:city":"Bexley",
    "sg:classifiers":[
        {
            "category":"Health Services",
            "subcategory":"Doctor",
            "type":"Services"
        }
    ],
    "sg:phone":"+61 2 9588 6763",
    "sg:postcode":"2207",
    "sg:province":"NSW",
    "sg:tags":[
        "medical",
        "practitioner"
    ],
    "wof:name":"Ng Paul K S",
    "wof:placetype":"venue"
},
  "geometry": {"coordinates":[151.117783,-33.957531],"type":"Point"}
}