{
  "type": "Feature",
  "properties": {
    "addr:full":"33 Mein St Spring Hill QLD 4000",
    "addr:housenumber":"33",
    "addr:postcode":"4000",
    "addr:street":"Mein St",
    "iso:country":"AU",
    "sg:address":"33 Mein St",
    "sg:city":"Spring Hill",
    "sg:classifiers":[
        {
            "category":"Government",
            "subcategory":"Customs House",
            "type":"Public Place"
        }
    ],
    "sg:phone":"+61 7 3831 5832",
    "sg:postcode":"4000",
    "sg:province":"QLD",
    "sg:tags":[
        "title",
        "management",
        "stratum"
    ],
    "wof:name":"Ernst Body Corporate Management Pty Ltd",
    "wof:placetype":"venue"
},
  "geometry": {"coordinates":[153.028274536,-27.4620285034],"type":"Point"}
}