{
  "type": "Feature",
  "properties": {
    "addr:full":"5/52 Kent St Cannington WA 6107",
    "addr:housenumber":"/ 52",
    "addr:postcode":"6107",
    "addr:street":"Kent St",
    "iso:country":"AU",
    "sg:address":"5/52 Kent St",
    "sg:city":"Cannington",
    "sg:classifiers":[
        {
            "category":"Home & Garden",
            "subcategory":"Building Materials",
            "type":"Retail Goods"
        }
    ],
    "sg:phone":"+61 8 9258 3899",
    "sg:postcode":"6107",
    "sg:province":"WA",
    "sg:tags":[
        "fencing"
    ],
    "wof:name":"Ibolt Palisade Fencing Systems",
    "wof:placetype":"venue"
},
  "geometry": {"coordinates":[115.926437378,-32.0157394409],"type":"Point"}
}