{
  "type": "Feature",
  "properties": {
    "addr:full":"36 Hutton St Osborne Park WA 6017",
    "addr:housenumber":"36",
    "addr:postcode":"6017",
    "addr:street":"Hutton St",
    "iso:country":"AU",
    "sg:address":"36 Hutton St",
    "sg:city":"Osborne Park",
    "sg:classifiers":[
        {
            "category":"Wholesale",
            "subcategory":"Furniture",
            "type":"Manufacturing & Wholesale Goods"
        }
    ],
    "sg:phone":"+61 8 9446 7121",
    "sg:postcode":"6017",
    "sg:province":"WA",
    "sg:tags":[
        "wholesaler",
        "mfrs"
    ],
    "wof:name":"Biltfirm Furniture Pty Ltd",
    "wof:placetype":"venue"
},
  "geometry": {"coordinates":[115.818367004,-31.9035491943],"type":"Point"}
}