{
  "type": "Feature",
  "properties": {
    "addr:full":"46 Bridge St Kensington SA 5068",
    "addr:housenumber":"46",
    "addr:postcode":"5068",
    "addr:street":"Bridge St",
    "iso:country":"AU",
    "sg:address":"46 Bridge St",
    "sg:city":"Kensington",
    "sg:classifiers":[
        {
            "category":"Education",
            "subcategory":"School",
            "type":"Public Place"
        }
    ],
    "sg:phone":"+61 8 8364 0877",
    "sg:postcode":"5068",
    "sg:province":"SA",
    "sg:tags":[
        "co-educational"
    ],
    "wof:name":"St Joseph's Memorial School",
    "wof:placetype":"venue"
},
  "geometry": {"coordinates":[138.643875122,-34.9252586365],"type":"Point"}
}