{
  "type": "Feature",
  "properties": {
    "iso:country":"AU",
    "sg:address":"2291 Albany Hwy",
    "sg:city":"Gosnells",
    "sg:classifiers":[
        {
            "category":"Retail",
            "subcategory":"Auto Repair",
            "type":"Services"
        }
    ],
    "sg:phone":"+61 8 9490 3579",
    "sg:postcode":"6110",
    "sg:province":"WA",
    "sg:tags":[
        "repairer",
        "motor",
        "engineer"
    ],
    "wof:name":"C & S Automotive Repairs",
    "wof:placetype":"venue"
},
  "geometry": {"coordinates":[116.00425720200001,-32.0736541748],"type":"Point"}
}