{
  "type": "Feature",
  "properties": {
    "addr:full":"Walhalla Rd Tyers VIC 3844",
    "addr:postcode":"3844",
    "addr:street":"Walhalla Rd",
    "iso:country":"AU",
    "sg:address":"Walhalla Rd",
    "sg:city":"Tyers",
    "sg:classifiers":[
        {
            "category":"Building & Trades",
            "subcategory":"Landscaping Services",
            "type":"Services"
        }
    ],
    "sg:phone":"+61 3 5191 8238",
    "sg:postcode":"3844",
    "sg:province":"VIC",
    "sg:tags":[
        "slashing",
        "contractor"
    ],
    "wof:name":"F.W. Ahlers",
    "wof:placetype":"venue"
},
  "geometry": {"coordinates":[146.514205933,-38.1895065308],"type":"Point"}
}