{
  "type": "Feature",
  "properties": {
    "addr:full":"30 Rathluba Crs East Maitland NSW 2323",
    "addr:housenumber":"30",
    "addr:postcode":"2323",
    "addr:street":"Rathluba Crs",
    "iso:country":"AU",
    "sg:address":"30 Rathluba Crs",
    "sg:city":"East Maitland",
    "sg:classifiers":[
        {
            "category":"Utilities",
            "subcategory":"Electric",
            "type":"Services"
        }
    ],
    "sg:phone":"+61 418 492 838",
    "sg:postcode":"2323",
    "sg:province":"NSW",
    "sg:tags":[
        "electrical",
        "contractor"
    ],
    "wof:name":"Tenambit Electrical Services",
    "wof:placetype":"venue"
},
  "geometry": {"coordinates":[151.58555602999999,-32.753780365],"type":"Point"}
}