{
  "type": "Feature",
  "properties": {
    "addr:full":"25 Hawk St Bald Hills QLD 4036",
    "addr:housenumber":"25",
    "addr:postcode":"4036",
    "addr:street":"Hawk St",
    "iso:country":"AU",
    "sg:address":"25 Hawk St",
    "sg:city":"Bald Hills",
    "sg:classifiers":[
        {
            "category":"Building & Trades",
            "subcategory":"Plumbing",
            "type":"Services"
        }
    ],
    "sg:phone":"+61 7 3261 5553",
    "sg:postcode":"4036",
    "sg:province":"QLD",
    "sg:tags":[
        "plumber",
        "gasfitters"
    ],
    "wof:name":"Benzie Alan",
    "wof:placetype":"venue"
},
  "geometry": {"coordinates":[153.0128479,-27.320608139],"type":"Point"}
}