{
  "type": "Feature",
  "properties": {
    "iso:country":"AU",
    "sg:address":"Jacaranda Ave",
    "sg:city":"Figtree",
    "sg:classifiers":[
        {
            "category":"Education",
            "subcategory":"School",
            "type":"Public Place"
        }
    ],
    "sg:phone":"+61 2 4226 3867",
    "sg:postcode":"2525",
    "sg:province":"NSW",
    "sg:tags":[
        "state",
        "-",
        "nsw"
    ],
    "wof:name":"Nareena Hills Public School",
    "wof:placetype":"venue"
},
  "geometry": {"coordinates":[150.84892273,-34.4312362671],"type":"Point"}
}