{
  "type": "Feature",
  "properties": {
    "iso:country":"AU",
    "sg:address":"5/ 2812 Logan Rd",
    "sg:city":"Underwood",
    "sg:classifiers":[
        {
            "category":"Home & Garden",
            "subcategory":"Building Materials",
            "type":"Retail Goods"
        }
    ],
    "sg:phone":"+61 13 15 46",
    "sg:postcode":"4119",
    "sg:province":"QLD",
    "sg:tags":[
        "lawn",
        "cutting",
        "maintenance"
    ],
    "wof:name":"Jims Mowing",
    "wof:placetype":"venue"
},
  "geometry": {"coordinates":[153.115722656,-27.611125946],"type":"Point"}
}