{
  "type": "Feature",
  "properties": {
    "addr:full":"37 Patterson Pde Queanbeyan ACT 2620",
    "addr:housenumber":"37",
    "addr:postcode":"2620",
    "addr:street":"Patterson Pde",
    "iso:country":"AU",
    "sg:address":"37 Patterson Pde",
    "sg:city":"Queanbeyan",
    "sg:classifiers":[
        {
            "category":"Retail",
            "subcategory":"Driving School",
            "type":"Services"
        }
    ],
    "sg:phone":"+61 2 6232 9363",
    "sg:postcode":"2620",
    "sg:province":"ACT",
    "wof:name":"Arthur Mee",
    "wof:placetype":"venue"
},
  "geometry": {"coordinates":[149.20585632300001,-35.3512535095],"type":"Point"}
}