{
  "type": "Feature",
  "properties": {
    "addr:full":"850 Sydney Rd Coburg VIC 3058",
    "addr:housenumber":"850",
    "addr:postcode":"3058",
    "addr:street":"Sydney Rd",
    "iso:country":"AU",
    "sg:address":"850 Sydney Rd",
    "sg:city":"Coburg",
    "sg:classifiers":[
        {
            "category":"Building & Trades",
            "subcategory":"Construction",
            "type":"Services"
        }
    ],
    "sg:phone":"+61 3 9350 5722",
    "sg:postcode":"3058",
    "sg:province":"VIC",
    "sg:tags":[
        "window",
        "tinting"
    ],
    "wof:name":"ARMA Protection Systems",
    "wof:placetype":"venue"
},
  "geometry": {"coordinates":[144.96406555199999,-37.756729126],"type":"Point"}
}