{
  "type": "Feature",
  "properties": {
    "iso:country":"AU",
    "sg:address":"118A Albury St",
    "sg:city":"Holbrook",
    "sg:classifiers":[
        {
            "category":"Social Services",
            "type":"Services"
        }
    ],
    "sg:phone":"+61 2 6036 2772",
    "sg:postcode":"2644",
    "sg:province":"NSW",
    "sg:tags":[
        "domestic",
        "help"
    ],
    "wof:name":"Home Care Service of NSW",
    "wof:placetype":"venue"
},
  "geometry": {"coordinates":[147.31758117699999,-35.7186012268],"type":"Point"}
}