{
  "type": "Feature",
  "properties": {
    "addr:full":"159 Henley Beach Rd Mile End SA 5031",
    "addr:housenumber":"159",
    "addr:postcode":"5031",
    "addr:street":"Henley Beach Rd",
    "iso:country":"AU",
    "sg:address":"159 Henley Beach Rd",
    "sg:city":"Mile End",
    "sg:classifiers":[
        {
            "category":"Government",
            "subcategory":"Post Office",
            "type":"Public Place"
        }
    ],
    "sg:phone":"+61 13 13 18",
    "sg:postcode":"5031",
    "sg:province":"SA",
    "sg:tags":[
        "postal"
    ],
    "wof:name":"Australia Post",
    "wof:placetype":"venue"
},
  "geometry": {"coordinates":[138.56265258799999,-34.9242706299],"type":"Point"}
}