{
  "type": "Feature",
  "properties": {
    "iso:country":"AU",
    "sg:address":"501 Lower North East Rd",
    "sg:city":"Felixstow",
    "sg:classifiers":[
        {
            "category":"Health Services",
            "subcategory":"Dentist",
            "type":"Services"
        }
    ],
    "sg:phone":"+61 8 8337 4887",
    "sg:postcode":"5070",
    "sg:province":"SA",
    "wof:name":"Potter David A Dr",
    "wof:placetype":"venue"
},
  "geometry": {"coordinates":[138.656982422,-34.8889045715],"type":"Point"}
}