{
  "type": "Feature",
  "properties": {
    "addr:full":"441 Bay St Brighton VIC 3186",
    "addr:housenumber":"441",
    "addr:postcode":"3186",
    "addr:street":"Bay St",
    "iso:country":"AU",
    "sg:address":"441 Bay St",
    "sg:city":"Brighton",
    "sg:classifiers":[
        {
            "category":"Health Services",
            "subcategory":"Health Practitioner",
            "type":"Services"
        }
    ],
    "sg:phone":"+61 3 9596 7211",
    "sg:postcode":"3186",
    "sg:province":"VIC",
    "sg:tags":[
        "psychologist"
    ],
    "wof:name":"R. E. Postlethwaite",
    "wof:placetype":"venue"
},
  "geometry": {"coordinates":[145.00677490199999,-37.9059028625],"type":"Point"}
}