{
  "type": "Feature",
  "properties": {
    "addr:full":"10 Wharf St Ipswich QLD 4305",
    "addr:housenumber":"10",
    "addr:postcode":"4305",
    "addr:street":"Wharf St",
    "iso:country":"AU",
    "sg:address":"10 Wharf St",
    "sg:city":"Ipswich",
    "sg:classifiers":[
        {
            "category":"Shopping",
            "subcategory":"Baby Store",
            "type":"Retail Goods"
        }
    ],
    "sg:phone":"+61 7 3202 1747",
    "sg:postcode":"4305",
    "sg:province":"QLD",
    "sg:tags":[
        "wear"
    ],
    "wof:name":"Tiny Treasures",
    "wof:placetype":"venue"
},
  "geometry": {"coordinates":[152.76194763199999,-27.6139717102],"type":"Point"}
}