{
  "type": "Feature",
  "properties": {
    "addr:full":"Blunder Rd Oxley QLD 4075",
    "addr:postcode":"4075",
    "addr:street":"Blunder Rd",
    "iso:country":"AU",
    "sg:address":"Blunder Rd",
    "sg:city":"Oxley",
    "sg:classifiers":[
        {
            "category":"Manufacturing",
            "subcategory":"Tools & Machinery",
            "type":"Manufacturing & Wholesale Goods"
        }
    ],
    "sg:phone":"+61 7 3379 9419",
    "sg:postcode":"4075",
    "sg:province":"QLD",
    "sg:tags":[
        "earth",
        "excavating",
        "moving",
        "equipment"
    ],
    "wof:name":"Cobra Equipment Sales Pty Ltd",
    "wof:placetype":"venue"
},
  "geometry": {"coordinates":[152.980072022,-27.5675354004],"type":"Point"}
}