{
  "type": "Feature",
  "properties": {
    "addr:full":"Suite 1, 3 Telopea St Telopea NSW 2117",
    "addr:housenumber":"3",
    "addr:postcode":"2117",
    "addr:street":"Telopea St",
    "iso:country":"AU",
    "sg:address":"Suite 1, 3 Telopea St",
    "sg:city":"Telopea",
    "sg:classifiers":[
        {
            "category":"Health Services",
            "subcategory":"Dentist",
            "type":"Services"
        }
    ],
    "sg:phone":"+61 2 9871 5242",
    "sg:postcode":"2117",
    "sg:province":"NSW",
    "wof:name":"Ho Marietta Dr",
    "wof:placetype":"venue"
},
  "geometry": {"coordinates":[151.04095459000001,-33.7937049866],"type":"Point"}
}