{
  "type": "Feature",
  "properties": {
    "iso:country":"AU",
    "sg:address":"U 6/ 237 Bunnerong Rd",
    "sg:city":"Maroubra",
    "sg:classifiers":[
        {
            "category":"Building & Trades",
            "subcategory":"Cleaning & Sanitation",
            "type":"Services"
        }
    ],
    "sg:phone":"+61 2 9349 6555",
    "sg:postcode":"2035",
    "sg:province":"NSW",
    "sg:tags":[
        "industrial",
        "commercial",
        "contractor"
    ],
    "wof:name":"Guru Cleaning Services (GCS)",
    "wof:placetype":"venue"
},
  "geometry": {"coordinates":[151.22959899899999,-33.9378700256],"type":"Point"}
}