{
  "type": "Feature",
  "properties": {
    "addr:full":"Prairievale Rd Prairiewood NSW 2176",
    "addr:postcode":"2176",
    "addr:street":"Prairievale Rd",
    "iso:country":"AU",
    "sg:address":"Prairievale Rd",
    "sg:city":"Prairiewood",
    "sg:classifiers":[
        {
            "category":"Personal",
            "type":"Services"
        }
    ],
    "sg:phone":"+61 2 9616 8800",
    "sg:postcode":"2176",
    "sg:province":"NSW",
    "sg:tags":[
        "counselling",
        "alcohol",
        "drug"
    ],
    "wof:name":"Corella Drug Treatment Service",
    "wof:placetype":"venue"
},
  "geometry": {"coordinates":[150.90423584000001,-33.857624054],"type":"Point"}
}