{
  "type": "Feature",
  "properties": {
    "iso:country":"AU",
    "sg:address":"383 West Maurice Rd",
    "sg:city":"Ringarooma",
    "sg:classifiers":[
        {
            "category":"Professional",
            "subcategory":"Accounting & Tax Preparation",
            "type":"Services"
        }
    ],
    "sg:phone":"+61 3 6353 2114",
    "sg:postcode":"7263",
    "sg:province":"TAS",
    "sg:tags":[
        "accountant",
        "auditor"
    ],
    "wof:name":"Wade J R & S L",
    "wof:placetype":"venue"
},
  "geometry": {"coordinates":[147.719055,-41.250488],"type":"Point"}
}