{
  "type": "Feature",
  "properties": {
    "iso:country":"AU",
    "sg:address":"121 Keira St",
    "sg:city":"Wollongong",
    "sg:classifiers":[
        {
            "category":"Banks & Credit Unions",
            "subcategory":"Investment Brokerage",
            "type":"Services"
        }
    ],
    "sg:phone":"+61 2 4229 8244",
    "sg:postcode":"2500",
    "sg:province":"NSW",
    "sg:tags":[
        "management",
        "property"
    ],
    "wof:name":"Dougmal Real Estate Network",
    "wof:placetype":"venue"
},
  "geometry": {"coordinates":[150.89389,-34.422054],"type":"Point"}
}