{
  "type": "Feature",
  "properties": {
    "iso:country":"AU",
    "sg:address":"56 Byre Ave",
    "sg:city":"Somerton Park",
    "sg:classifiers":[
        {
            "category":"Shopping",
            "subcategory":"Pets & Pet Supplies",
            "type":"Retail Goods"
        }
    ],
    "sg:phone":"+61 8 8294 0722",
    "sg:postcode":"5044",
    "sg:province":"SA",
    "sg:tags":[
        "shop",
        "supplier"
    ],
    "wof:name":"Pet Pacific Pty Ltd",
    "wof:placetype":"venue"
},
  "geometry": {"coordinates":[138.528198,-34.997704],"type":"Point"}
}