{
  "type": "Feature",
  "properties": {
    "addr:full":"56 Chisholm Rd Auburn NSW 2144",
    "addr:housenumber":"56",
    "addr:postcode":"2144",
    "addr:street":"Chisholm Rd",
    "iso:country":"AU",
    "sg:address":"56 Chisholm Rd",
    "sg:city":"Auburn",
    "sg:classifiers":[
        {
            "category":"Recreation",
            "subcategory":"Water Park",
            "type":"Entertainment"
        }
    ],
    "sg:phone":"+61 2 9637 9617",
    "sg:postcode":"2144",
    "sg:province":"NSW",
    "sg:tags":[
        "control",
        "seepage"
    ],
    "wof:name":"MMB Enterprises",
    "wof:placetype":"venue"
},
  "geometry": {"coordinates":[151.02137756400001,-33.8495483398],"type":"Point"}
}