{
  "type": "Feature",
  "properties": {
    "addr:full":"39 Glen Eira Rd Ripponlea VIC 3185",
    "addr:housenumber":"39",
    "addr:postcode":"3185",
    "addr:street":"Glen Eira Rd",
    "iso:country":"AU",
    "sg:address":"39 Glen Eira Rd",
    "sg:city":"Ripponlea",
    "sg:classifiers":[
        {
            "category":"Food & Beverages",
            "subcategory":"Supermarket",
            "type":"Retail Goods"
        }
    ],
    "sg:phone":"+61 3 9528 4303",
    "sg:postcode":"3185",
    "sg:province":"VIC",
    "sg:tags":[
        "grocery",
        "store"
    ],
    "wof:name":"IGA Express Ripponlea",
    "wof:placetype":"venue"
},
  "geometry": {"coordinates":[144.99641418499999,-37.8765792847],"type":"Point"}
}