{
  "type": "Feature",
  "properties": {
    "addr:full":"32 Crescent Head Rd Kempsey NSW 2440",
    "addr:housenumber":"32",
    "addr:postcode":"2440",
    "addr:street":"Crescent Head Rd",
    "iso:country":"AU",
    "sg:address":"32 Crescent Head Rd",
    "sg:city":"Kempsey",
    "sg:classifiers":[
        {
            "category":"Professional",
            "subcategory":"Detective & Security Services",
            "type":"Services"
        }
    ],
    "sg:phone":"+61 2 6562 8634",
    "sg:postcode":"2440",
    "sg:province":"NSW",
    "sg:tags":[
        "equipment",
        "window",
        "doors"
    ],
    "wof:name":"C & M Glass & Aluminium",
    "wof:placetype":"venue"
},
  "geometry": {"coordinates":[152.87069700000001,-31.119593],"type":"Point"}
}