{
  "type": "Feature",
  "properties": {
    "addr:full":"52 Christie St St Marys NSW 2760",
    "addr:housenumber":"52",
    "addr:postcode":"2760",
    "addr:street":"Christie St",
    "iso:country":"AU",
    "sg:address":"52 Christie St",
    "sg:city":"St Marys",
    "sg:classifiers":[
        {
            "category":"Retail",
            "subcategory":"Auto Repair",
            "type":"Services"
        }
    ],
    "sg:phone":"+61 2 9833 1724",
    "sg:postcode":"2760",
    "sg:province":"NSW",
    "sg:tags":[
        "repairer",
        "motor",
        "engineer"
    ],
    "wof:name":"Glendenning Auto Repairs",
    "wof:placetype":"venue"
},
  "geometry": {"coordinates":[150.76976013199999,-33.7472229004],"type":"Point"}
}