{
  "type": "Feature",
  "properties": {
    "iso:country":"AU",
    "sg:address":"40 Fergusson St",
    "sg:city":"Casino",
    "sg:classifiers":[
        {
            "category":"Professional",
            "subcategory":"Art Services",
            "type":"Services"
        }
    ],
    "sg:phone":"+61 2 6662 2332",
    "sg:postcode":"2470",
    "sg:province":"NSW",
    "sg:tags":[
        "decorator",
        "painter"
    ],
    "wof:name":"Transton D L & L M",
    "wof:placetype":"venue"
},
  "geometry": {"coordinates":[153.03114318900001,-28.8588199615],"type":"Point"}
}