{
  "type": "Feature",
  "properties": {
    "addr:full":"6 Seventh St Murray Bridge SA 5253",
    "addr:housenumber":"6",
    "addr:postcode":"5253",
    "addr:street":"Seventh St",
    "iso:country":"AU",
    "sg:address":"6 Seventh St",
    "sg:city":"Murray Bridge",
    "sg:classifiers":[
        {
            "category":"Education",
            "subcategory":"Special Training",
            "type":"Public Place"
        }
    ],
    "sg:phone":"+61 8 8531 1733",
    "sg:postcode":"5253",
    "sg:province":"SA",
    "sg:tags":[
        "development"
    ],
    "wof:name":"Murraylands Training & Employment Assoc. Of SA Inc.",
    "wof:placetype":"venue"
},
  "geometry": {"coordinates":[139.274856567,-35.1185646057],"type":"Point"}
}