{
  "type": "Feature",
  "properties": {
    "addr:full":"25 Federal Pl Robina QLD 4226",
    "addr:housenumber":"25",
    "addr:postcode":"4226",
    "addr:street":"Federal Pl",
    "iso:country":"AU",
    "sg:address":"25 Federal Pl",
    "sg:city":"Robina",
    "sg:classifiers":[
        {
            "category":"Banks & Credit Unions",
            "subcategory":"Investment Brokerage",
            "type":"Services"
        }
    ],
    "sg:phone":"+61 1300 661 413",
    "sg:postcode":"4226",
    "sg:province":"QLD",
    "sg:tags":[
        "finance",
        "broker"
    ],
    "wof:name":"Q Finance",
    "wof:placetype":"venue"
},
  "geometry": {"coordinates":[153.39465332,-28.0757904053],"type":"Point"}
}