{
  "type": "Feature",
  "properties": {
    "iso:country":"AU",
    "sg:address":"152 Main St",
    "sg:city":"Mornington",
    "sg:classifiers":[
        {
            "category":"Manufacturing",
            "subcategory":"Jewelry",
            "type":"Manufacturing & Wholesale Goods"
        }
    ],
    "sg:phone":"+61 3 5975 2439",
    "sg:postcode":"3931",
    "sg:province":"VIC",
    "sg:tags":[
        "designer",
        "jewellery"
    ],
    "sg:website":"http://www.minzenmays.com.au",
    "wof:name":"Minzenmays",
    "wof:placetype":"venue"
},
  "geometry": {"coordinates":[145.03953552199999,-38.2205314636],"type":"Point"}
}