{
  "type": "Feature",
  "properties": {
    "addr:full":"113 Edgar St Junee NSW 2663",
    "addr:housenumber":"113",
    "addr:postcode":"2663",
    "addr:street":"Edgar St",
    "iso:country":"AU",
    "sg:address":"113 Edgar St",
    "sg:city":"Junee",
    "sg:classifiers":[
        {
            "category":"Utilities",
            "subcategory":"Water",
            "type":"Services"
        }
    ],
    "sg:phone":"+61 2 6924 2380",
    "sg:postcode":"2663",
    "sg:province":"NSW",
    "sg:tags":[
        "hot",
        "system"
    ],
    "wof:name":"Ray Taylor Plumbing Service",
    "wof:placetype":"venue"
},
  "geometry": {"coordinates":[147.58306884800001,-34.8746871948],"type":"Point"}
}