{
  "type": "Feature",
  "properties": {
    "addr:full":"29 Dalgety St Oakleigh VIC 3166",
    "addr:housenumber":"29",
    "addr:postcode":"3166",
    "addr:street":"Dalgety St",
    "iso:country":"AU",
    "sg:address":"29 Dalgety St",
    "sg:city":"Oakleigh",
    "sg:phone":"+61 3 9462 3585",
    "sg:postcode":"3166",
    "sg:province":"VIC",
    "wof:name":"Blue H2o Filtration Pty Ltd",
    "wof:placetype":"venue"
},
  "geometry": {"coordinates":[145.09211730999999,-37.8919067383],"type":"Point"}
}