{
  "type": "Feature",
  "properties": {
    "iso:country":"AU",
    "sg:address":"405a Sturt St",
    "sg:city":"Ballarat",
    "sg:classifiers":[
        {
            "category":"Food & Beverages",
            "subcategory":"Specialty",
            "type":"Retail Goods"
        }
    ],
    "sg:phone":"+61 3 5332 1739",
    "sg:postcode":"3350",
    "sg:province":"VIC",
    "sg:tags":[
        "product",
        "health"
    ],
    "wof:name":"Ballarat Health Foods",
    "wof:placetype":"venue"
},
  "geometry": {"coordinates":[143.854431,-37.561859],"type":"Point"}
}