{
  "type": "Feature",
  "properties": {
    "addr:full":"39 Lewington St Wagga Wagga NSW 2650",
    "addr:housenumber":"39",
    "addr:postcode":"2650",
    "addr:street":"Lewington St",
    "iso:country":"AU",
    "sg:address":"39 Lewington St",
    "sg:city":"Wagga Wagga",
    "sg:classifiers":[
        {
            "category":"Professional",
            "type":"Services"
        }
    ],
    "sg:phone":"+61 2 6921 9899",
    "sg:postcode":"2650",
    "sg:province":"NSW",
    "sg:tags":[
        "buyer",
        "merchant",
        "wool"
    ],
    "wof:name":"P Lyons & Co",
    "wof:placetype":"venue"
},
  "geometry": {"coordinates":[147.409988403,-35.0716247559],"type":"Point"}
}