{
  "type": "Feature",
  "properties": {
    "addr:full":"6 Curtis Ave South Hobart TAS 7004",
    "addr:housenumber":"6",
    "addr:postcode":"7004",
    "addr:street":"Curtis Ave",
    "iso:country":"AU",
    "sg:address":"6 Curtis Ave",
    "sg:city":"South Hobart",
    "sg:classifiers":[
        {
            "category":"Government",
            "subcategory":"Post Office",
            "type":"Public Place"
        }
    ],
    "sg:phone":"+61 3 6239 1822",
    "sg:postcode":"7004",
    "sg:province":"TAS",
    "sg:tags":[
        "yoga"
    ],
    "wof:name":"Catharine Errey",
    "wof:placetype":"venue"
},
  "geometry": {"coordinates":[147.26705932600001,-42.9133682251],"type":"Point"}
}