{
  "type": "Feature",
  "properties": {
    "addr:full":"Shop 8/ 162 Golden Valley Drv Glossodia NSW 2756",
    "addr:housenumber":"shop 8 / 162",
    "addr:postcode":"2756",
    "addr:street":"Golden Valley Drv",
    "iso:country":"AU",
    "sg:address":"Shop 8/ 162 Golden Valley Drv",
    "sg:city":"Glossodia",
    "sg:classifiers":[
        {
            "category":"Health Services",
            "subcategory":"Doctor",
            "type":"Services"
        }
    ],
    "sg:phone":"+61 2 4576 6166",
    "sg:postcode":"2756",
    "sg:province":"NSW",
    "sg:tags":[
        "medical",
        "practitioner"
    ],
    "wof:name":"Campbell David",
    "wof:placetype":"venue"
},
  "geometry": {"coordinates":[150.76724243199999,-33.5317001343],"type":"Point"}
}