{
  "type": "Feature",
  "properties": {
    "addr:full":"Lot 2 Stapylton-Jacobs Well Rd Alberton QLD 4207",
    "addr:postcode":"4207",
    "addr:street":"Well Rd",
    "iso:country":"AU",
    "sg:address":"Lot 2 Stapylton-Jacobs Well Rd",
    "sg:city":"Alberton",
    "sg:classifiers":[
        {
            "category":"Home & Garden",
            "subcategory":"Building Materials",
            "type":"Retail Goods"
        }
    ],
    "sg:phone":"+61 7 3807 2007",
    "sg:postcode":"4207",
    "sg:province":"QLD",
    "sg:tags":[
        "fencing"
    ],
    "wof:name":"A C Fencing Supplies",
    "wof:placetype":"venue"
},
  "geometry": {"coordinates":[153.324783325,-27.7461166382],"type":"Point"}
}