{
  "type": "Feature",
  "properties": {
    "addr:full":"79- 85 Winton Rd Joondalup WA 6027",
    "addr:housenumber":"85",
    "addr:postcode":"6027",
    "addr:street":"Winton Rd",
    "iso:country":"AU",
    "sg:address":"79- 85 Winton Rd",
    "sg:city":"Joondalup",
    "sg:classifiers":[
        {
            "category":"Building & Trades",
            "subcategory":"Construction",
            "type":"Services"
        }
    ],
    "sg:phone":"+61 8 9300 2880",
    "sg:postcode":"6027",
    "sg:province":"WA",
    "sg:tags":[
        "pool",
        "swimming"
    ],
    "wof:name":"Aqua Technics",
    "wof:placetype":"venue"
},
  "geometry": {"coordinates":[115.759742737,-31.744682312],"type":"Point"}
}