{
  "type": "Feature",
  "properties": {
    "addr:full":"3 Bourke St Bunbury WA 6230",
    "addr:housenumber":"3",
    "addr:postcode":"6230",
    "addr:street":"Bourke St",
    "iso:country":"AU",
    "sg:address":"3 Bourke St",
    "sg:city":"Bunbury",
    "sg:classifiers":[
        {
            "category":"Autos & Motor Vehicles",
            "subcategory":"Auto Supplies",
            "type":"Retail Goods"
        }
    ],
    "sg:phone":"+61 8 9721 4343",
    "sg:postcode":"6230",
    "sg:province":"WA",
    "sg:tags":[
        "automotive",
        "stereo",
        "radio"
    ],
    "wof:name":"Prins Radio Service",
    "wof:placetype":"venue"
},
  "geometry": {"coordinates":[115.642639,-33.332455],"type":"Point"}
}