{
  "type": "Feature",
  "properties": {
    "addr:full":"10 Mountview Crs Gatton QLD 4343",
    "addr:housenumber":"10",
    "addr:postcode":"4343",
    "addr:street":"Mountview Crs",
    "iso:country":"AU",
    "sg:address":"10 Mountview Crs",
    "sg:city":"Gatton",
    "sg:classifiers":[
        {
            "category":"Commercial Area",
            "type":"Public Place"
        }
    ],
    "sg:phone":"+61 408 072 013",
    "sg:postcode":"4343",
    "sg:province":"QLD",
    "sg:tags":[
        "heavy",
        "carrier"
    ],
    "wof:name":"GJ Transport (Qld) Pty Ltd",
    "wof:placetype":"venue"
},
  "geometry": {"coordinates":[152.26986694300001,-27.7063407898],"type":"Point"}
}