{
  "type": "Feature",
  "properties": {
    "addr:full":"38 Siandra Crs Geilston Bay TAS 7015",
    "addr:housenumber":"38",
    "addr:postcode":"7015",
    "addr:street":"Siandra Crs",
    "iso:country":"AU",
    "sg:address":"38 Siandra Crs",
    "sg:city":"Geilston Bay",
    "sg:classifiers":[
        {
            "category":"Professional",
            "subcategory":"Art Services",
            "type":"Services"
        }
    ],
    "sg:phone":"+61 3 6243 6695",
    "sg:postcode":"7015",
    "sg:province":"TAS",
    "sg:tags":[
        "graphic",
        "designer"
    ],
    "wof:name":"Romic Pajak Graphic Design",
    "wof:placetype":"venue"
},
  "geometry": {"coordinates":[147.35154724099999,-42.83852005],"type":"Point"}
}