{
  "type": "Feature",
  "properties": {
    "addr:full":"225 Campbell St Hobart TAS 7000",
    "addr:housenumber":"225",
    "addr:postcode":"7000",
    "addr:street":"Campbell St",
    "iso:country":"AU",
    "sg:address":"225 Campbell St",
    "sg:city":"Hobart",
    "sg:classifiers":[
        {
            "category":"Professional",
            "subcategory":"Detective & Security Services",
            "type":"Services"
        }
    ],
    "sg:phone":"+61 3 6231 1543",
    "sg:postcode":"7000",
    "sg:province":"TAS",
    "sg:tags":[
        "consultant",
        "system"
    ],
    "wof:name":"R N H Audio & Video",
    "wof:placetype":"venue"
},
  "geometry": {"coordinates":[147.32273864699999,-42.8737716675],"type":"Point"}
}