{
  "type": "Feature",
  "properties": {
    "addr:full":"14 Wayne Crt Dandenong VIC 3175",
    "addr:housenumber":"14",
    "addr:postcode":"3175",
    "addr:street":"Wayne Crt",
    "iso:country":"AU",
    "sg:address":"14 Wayne Crt",
    "sg:city":"Dandenong",
    "sg:classifiers":[
        {
            "category":"Professional",
            "subcategory":"Business Services",
            "type":"Services"
        }
    ],
    "sg:phone":"+61 3 9793 9233",
    "sg:postcode":"3175",
    "sg:province":"VIC",
    "sg:tags":[
        "coaters",
        "plastic"
    ],
    "wof:name":"Australian Product Finishing Pty Ltd",
    "wof:placetype":"venue"
},
  "geometry": {"coordinates":[145.195114136,-37.9888496399],"type":"Point"}
}