{
  "type": "Feature",
  "properties": {
    "iso:country":"AU",
    "sg:address":"22 Bimbadeen St",
    "sg:city":"Burnside",
    "sg:classifiers":[
        {
            "category":"Building & Trades",
            "subcategory":"Plumbing",
            "type":"Services"
        }
    ],
    "sg:phone":"+61 412 903 038",
    "sg:postcode":"3023",
    "sg:province":"VIC",
    "sg:tags":[
        "plumber",
        "gasfitters"
    ],
    "wof:name":"Burnside Plumbing Services",
    "wof:placetype":"venue"
},
  "geometry": {"coordinates":[144.753204,-37.74976],"type":"Point"}
}