{
  "type": "Feature",
  "properties": {
    "iso:country":"AU",
    "sg:address":"41 Coogee St",
    "sg:city":"Albany",
    "sg:classifiers":[
        {
            "category":"Utilities",
            "subcategory":"Electric",
            "type":"Services"
        }
    ],
    "sg:phone":"+61 8 9841 7873",
    "sg:postcode":"6330",
    "sg:province":"WA",
    "sg:tags":[
        "electrical",
        "contractor"
    ],
    "wof:name":"Burvill Electrical",
    "wof:placetype":"venue"
},
  "geometry": {"coordinates":[117.860961914,-34.9889450073],"type":"Point"}
}