{
  "type": "Feature",
  "properties": {
    "iso:country":"AU",
    "sg:address":"4 Lanyon St",
    "sg:city":"Dandenong",
    "sg:classifiers":[
        {
            "category":"Manufacturing",
            "subcategory":"Motor Vehicles & Parts",
            "type":"Manufacturing & Wholesale Goods"
        }
    ],
    "sg:phone":"+61 3 9552 9950",
    "sg:postcode":"3175",
    "sg:province":"VIC",
    "sg:tags":[
        "die",
        "casting"
    ],
    "wof:name":"Hot Flo Diecasting",
    "wof:placetype":"venue"
},
  "geometry": {"coordinates":[145.221801758,-38.0160446167],"type":"Point"}
}