{
  "type": "Feature",
  "properties": {
    "addr:full":"Fcty 27/ 7 Dunstans Crt Reservoir VIC 3073",
    "addr:housenumber":"27 / 7",
    "addr:postcode":"3073",
    "addr:street":"Dunstans Crt",
    "iso:country":"AU",
    "sg:address":"Fcty 27/ 7 Dunstans Crt",
    "sg:city":"Reservoir",
    "sg:classifiers":[
        {
            "category":"Manufacturing",
            "subcategory":"Glass & Minerals",
            "type":"Manufacturing & Wholesale Goods"
        }
    ],
    "sg:phone":"+61 3 9462 2098",
    "sg:postcode":"3073",
    "sg:province":"VIC",
    "sg:tags":[
        "merchant",
        "granite",
        "marble"
    ],
    "wof:name":"Artistic Stone",
    "wof:placetype":"venue"
},
  "geometry": {"coordinates":[145.02090454099999,-37.6944656372],"type":"Point"}
}