{
  "type": "Feature",
  "properties": {
    "iso:country":"AU",
    "sg:address":"Highfields News & Mini Mart New England Hwy",
    "sg:city":"Highfields",
    "sg:classifiers":[
        {
            "category":"Government",
            "subcategory":"Post Office",
            "type":"Public Place"
        }
    ],
    "sg:phone":"+61 7 4630 8110",
    "sg:postcode":"4352",
    "sg:province":"QLD",
    "sg:tags":[
        "postal"
    ],
    "wof:name":"Australia Post",
    "wof:placetype":"venue"
},
  "geometry": {"coordinates":[151.95332300000001,-27.464439],"type":"Point"}
}