{
  "type": "Feature",
  "properties": {
    "iso:country":"AU",
    "sg:address":"50 Kalang Rd",
    "sg:city":"Elanora Heights",
    "sg:classifiers":[
        {
            "category":"Shopping",
            "subcategory":"Clothing, Apparel, & Fashions",
            "type":"Retail Goods"
        }
    ],
    "sg:phone":"+61 2 9970 8762",
    "sg:postcode":"2101",
    "sg:province":"NSW",
    "sg:tags":[
        "lady",
        "wear"
    ],
    "wof:name":"Jan Jolly",
    "wof:placetype":"venue"
},
  "geometry": {"coordinates":[151.2798,-33.695873],"type":"Point"}
}