{
  "type": "Feature",
  "properties": {
    "addr:full":"50 Kalang Rd Elanora Heights NSW 2101",
    "addr:housenumber":"50",
    "addr:postcode":"2101",
    "addr:street":"Kalang Rd",
    "iso:country":"AU",
    "sg:address":"50 Kalang Rd",
    "sg:city":"Elanora Heights",
    "sg:classifiers":[
        {
            "category":"Shopping",
            "subcategory":"Clothing, Apparel, & Fashions",
            "type":"Retail Goods"
        }
    ],
    "sg:phone":"+61 2 9970 8762",
    "sg:postcode":"2101",
    "sg:province":"NSW",
    "sg:tags":[
        "lady",
        "wear"
    ],
    "wof:name":"Jan Jolly",
    "wof:placetype":"venue"
},
  "geometry": {"coordinates":[151.27979999999999,-33.695873],"type":"Point"}
}