{
  "type": "Feature",
  "properties": {
    "addr:full":"538 Williamstwon Rd Port Melbourne VIC 3207",
    "addr:housenumber":"538",
    "addr:postcode":"3207",
    "addr:street":"Williamstwon Rd",
    "iso:country":"AU",
    "sg:address":"538 Williamstwon Rd",
    "sg:city":"Port Melbourne",
    "sg:classifiers":[
        {
            "category":"Manufacturing",
            "subcategory":"Building Materials",
            "type":"Manufacturing & Wholesale Goods"
        }
    ],
    "sg:phone":"+61 3 9417 4191",
    "sg:postcode":"3207",
    "sg:province":"VIC",
    "sg:tags":[
        "adhesive",
        "tape"
    ],
    "wof:name":"C P Supplies",
    "wof:placetype":"venue"
},
  "geometry": {"coordinates":[144.94253499999999,-37.831722],"type":"Point"}
}