{
  "type": "Feature",
  "properties": {
    "iso:country":"AU",
    "sg:address":"538 Williamstwon Rd",
    "sg:city":"Port Melbourne",
    "sg:classifiers":[
        {
            "category":"Manufacturing",
            "subcategory":"Building Materials",
            "type":"Manufacturing & Wholesale Goods"
        }
    ],
    "sg:phone":"+61 3 9417 4191",
    "sg:postcode":"3207",
    "sg:province":"VIC",
    "sg:tags":[
        "adhesive",
        "tape"
    ],
    "wof:name":"C P Supplies",
    "wof:placetype":"venue"
},
  "geometry": {"coordinates":[144.942535,-37.831722],"type":"Point"}
}