{
  "type": "Feature",
  "properties": {
    "addr:full":"10E Bilinga Rd Kincumber NSW 2251",
    "addr:postcode":"2251",
    "addr:street":"Bilinga Rd",
    "iso:country":"AU",
    "sg:address":"10E Bilinga Rd",
    "sg:city":"Kincumber",
    "sg:classifiers":[
        {
            "category":"Professional",
            "subcategory":"Art Services",
            "type":"Services"
        }
    ],
    "sg:phone":"+61 2 4368 2000",
    "sg:postcode":"2251",
    "sg:province":"NSW",
    "sg:tags":[
        "interior",
        "decorator"
    ],
    "wof:name":"Adek Blinds & Curtains",
    "wof:placetype":"venue"
},
  "geometry": {"coordinates":[151.390136719,-33.473400116],"type":"Point"}
}