{
  "type": "Feature",
  "properties": {
    "addr:full":"Suite 203 &#034;Stanhill&#034;, 34 Queens Rd Melbourne VIC 3000",
    "addr:housenumber":"34",
    "addr:postcode":"3000",
    "addr:street":"203;Queens Rd",
    "iso:country":"AU",
    "sg:address":"Suite 203 &#034;Stanhill&#034;, 34 Queens Rd",
    "sg:city":"Melbourne",
    "sg:classifiers":[
        {
            "category":"Personal",
            "subcategory":"Beauty Salon",
            "type":"Services"
        }
    ],
    "sg:phone":"+61 3 9867 6255",
    "sg:postcode":"3000",
    "sg:province":"VIC",
    "sg:tags":[
        "hair",
        "treatment",
        "replacement"
    ],
    "wof:name":"The Shiell Knudsen Clinic",
    "wof:placetype":"venue"
},
  "geometry": {"coordinates":[144.97622680699999,-37.8440322876],"type":"Point"}
}