{
  "type": "Feature",
  "properties": {
    "iso:country":"AU",
    "sg:address":"198 Charles Ave",
    "sg:city":"Minnamurra",
    "sg:classifiers":[
        {
            "category":"Wholesale",
            "subcategory":"Painting Supplies",
            "type":"Manufacturing & Wholesale Goods"
        }
    ],
    "sg:phone":"+61 2 4237 7873",
    "sg:postcode":"2533",
    "sg:province":"NSW",
    "sg:tags":[
        "product",
        "cleaning"
    ],
    "wof:name":"Amway Of Australia Pty Ltd",
    "wof:placetype":"venue"
},
  "geometry": {"coordinates":[150.855392456,-34.6322097778],"type":"Point"}
}