{
  "type": "Feature",
  "properties": {
    "addr:full":"28 Albert St Warrnambool VIC 3280",
    "addr:housenumber":"28",
    "addr:postcode":"3280",
    "addr:street":"Albert St",
    "iso:country":"AU",
    "sg:address":"28 Albert St",
    "sg:city":"Warrnambool",
    "sg:classifiers":[
        {
            "category":"Social Services",
            "subcategory":"Adult Care",
            "type":"Services"
        }
    ],
    "sg:phone":"+61 3 5562 7476",
    "sg:postcode":"3280",
    "sg:province":"VIC",
    "sg:tags":[
        "towing"
    ],
    "wof:name":"Des Coopers Panel Works",
    "wof:placetype":"venue"
},
  "geometry": {"coordinates":[142.46014404300001,-38.3713722229],"type":"Point"}
}