{
  "type": "Feature",
  "properties": {
    "addr:full":"165 Manilla St Manilla NSW 2346",
    "addr:housenumber":"165",
    "addr:postcode":"2346",
    "addr:street":"Manilla St",
    "iso:country":"AU",
    "sg:address":"165 Manilla St",
    "sg:city":"Manilla",
    "sg:classifiers":[
        {
            "category":"Food & Beverages",
            "subcategory":"Supermarket",
            "type":"Retail Goods"
        }
    ],
    "sg:phone":"+61 2 6785 1104",
    "sg:postcode":"2346",
    "sg:province":"NSW",
    "sg:tags":[
        "grocery",
        "store"
    ],
    "wof:name":"Manilla Supermarket",
    "wof:placetype":"venue"
},
  "geometry": {"coordinates":[150.72000122099999,-30.7467308044],"type":"Point"}
}