{
  "type": "Feature",
  "properties": {
    "iso:country":"AU",
    "sg:address":"Conness St",
    "sg:city":"Chiltern",
    "sg:classifiers":[
        {
            "category":"Communications",
            "subcategory":"News Services",
            "type":"Services"
        }
    ],
    "sg:phone":"+61 3 5726 1476",
    "sg:postcode":"3683",
    "sg:province":"VIC",
    "sg:tags":[
        "information",
        "tourist",
        "attractions"
    ],
    "wof:name":"National Trust Of Australia (Victoria)",
    "wof:placetype":"venue"
},
  "geometry": {"coordinates":[146.60772700000001,-36.151257],"type":"Point"}
}