{
  "type": "Feature",
  "properties": {
    "addr:full":"39 Christensen St Machans Beach QLD 4878",
    "addr:housenumber":"39",
    "addr:postcode":"4878",
    "addr:street":"Christensen St",
    "iso:country":"AU",
    "sg:address":"39 Christensen St",
    "sg:city":"Machans Beach",
    "sg:classifiers":[
        {
            "category":"Retail",
            "subcategory":"Auto Repair",
            "type":"Services"
        }
    ],
    "sg:phone":"+61 411 613 999",
    "sg:postcode":"4878",
    "sg:province":"QLD",
    "sg:tags":[
        "repairer",
        "motor",
        "engineer"
    ],
    "wof:name":"Ganes Power-Steering & Mechanical Repairs",
    "wof:placetype":"venue"
},
  "geometry": {"coordinates":[145.745162964,-16.8563632965],"type":"Point"}
}