{
  "type": "Feature",
  "properties": {
    "iso:country":"AU",
    "sg:address":"163 King St",
    "sg:city":"Sydney",
    "sg:classifiers":[
        {
            "category":"Restaurant",
            "type":"Food & Drink"
        }
    ],
    "sg:phone":"+61 2 9231 0013",
    "sg:postcode":"2000",
    "sg:province":"NSW",
    "wof:name":"Element Bistro",
    "wof:placetype":"venue"
},
  "geometry": {"coordinates":[151.210479736,-33.8693084717],"type":"Point"}
}