{
  "type": "Feature",
  "properties": {
    "addr:full":"2/411- 417 Mcquarie St Liverpool NSW 2170",
    "addr:housenumber":"/ 411 417",
    "addr:postcode":"2170",
    "addr:street":"Mcquarie St",
    "iso:country":"AU",
    "sg:address":"2/411- 417 Mcquarie St",
    "sg:city":"Liverpool",
    "sg:classifiers":[
        {
            "category":"Autos & Motor Vehicles",
            "subcategory":"Auto Supplies",
            "type":"Retail Goods"
        }
    ],
    "sg:phone":"+61 2 9600 6480",
    "sg:postcode":"2170",
    "sg:province":"NSW",
    "sg:tags":[
        "part",
        "cycles",
        "accessory"
    ],
    "wof:name":"Motorcross Madness",
    "wof:placetype":"venue"
},
  "geometry": {"coordinates":[150.91903686500001,-33.9276161194],"type":"Point"}
}