{
  "type": "Feature",
  "properties": {
    "addr:full":"36 Denistone Rd Eastwood NSW 2122",
    "addr:housenumber":"36",
    "addr:postcode":"2122",
    "addr:street":"Denistone Rd",
    "iso:country":"AU",
    "sg:address":"36 Denistone Rd",
    "sg:city":"Eastwood",
    "sg:classifiers":[
        {
            "category":"Health Services",
            "subcategory":"Doctor",
            "type":"Services"
        }
    ],
    "sg:phone":"+61 2 9874 6307",
    "sg:postcode":"2122",
    "sg:province":"NSW",
    "sg:tags":[
        "medical",
        "practitioner"
    ],
    "wof:name":"Lane-Brown Malcolm",
    "wof:placetype":"venue"
},
  "geometry": {"coordinates":[151.08998107900001,-33.7943000793],"type":"Point"}
}