{
  "type": "Feature",
  "properties": {
    "addr:full":"1 Ireland St Ringwood VIC 3134",
    "addr:housenumber":"1",
    "addr:postcode":"3134",
    "addr:street":"Ireland St",
    "iso:country":"AU",
    "sg:address":"1 Ireland St",
    "sg:city":"Ringwood",
    "sg:classifiers":[
        {
            "category":"Building & Trades",
            "subcategory":"Construction",
            "type":"Services"
        }
    ],
    "sg:phone":"+61 3 9870 6084",
    "sg:postcode":"3134",
    "sg:province":"VIC",
    "sg:tags":[
        "concrete",
        "paving"
    ],
    "wof:name":"Gay Concrete & Paving Co",
    "wof:placetype":"venue"
},
  "geometry": {"coordinates":[145.22892761200001,-37.8221130371],"type":"Point"}
}