{
  "type": "Feature",
  "properties": {
    "addr:full":"Araluen Rd \"Deva River\" via Moruya NSW 2537",
    "addr:postcode":"2537",
    "addr:street":"Araluen Rd;Via Moruya",
    "iso:country":"AU",
    "sg:address":"Araluen Rd \"Deva River\" via",
    "sg:city":"Moruya",
    "sg:classifiers":[
        {
            "category":"Manufacturing",
            "subcategory":"Pottery",
            "type":"Manufacturing & Wholesale Goods"
        }
    ],
    "sg:phone":"+61 2 4478 8361",
    "sg:postcode":"2537",
    "sg:province":"NSW",
    "wof:name":"Deua River Pottery The",
    "wof:placetype":"venue"
},
  "geometry": {"coordinates":[150.06135559099999,-35.9144172668],"type":"Point"}
}