{
  "type": "Feature",
  "properties": {
    "addr:full":"232 Melbourne St North Adelaide SA 5006",
    "addr:housenumber":"232",
    "addr:postcode":"5006",
    "addr:street":"Melbourne St",
    "iso:country":"AU",
    "sg:address":"232 Melbourne St",
    "sg:city":"North Adelaide",
    "sg:classifiers":[
        {
            "category":"Building & Trades",
            "subcategory":"Construction",
            "type":"Services"
        }
    ],
    "sg:phone":"+61 8 8239 1511",
    "sg:postcode":"5006",
    "sg:province":"SA",
    "sg:tags":[
        "contractor"
    ],
    "wof:name":"Genworth Construction",
    "wof:placetype":"venue"
},
  "geometry": {"coordinates":[138.60362243599999,-34.908946991],"type":"Point"}
}