{
  "type": "Feature",
  "properties": {
    "addr:full":"330 Mann St Gosford NSW 2250",
    "addr:housenumber":"330",
    "addr:postcode":"2250",
    "addr:street":"Mann St",
    "iso:country":"AU",
    "sg:address":"330 Mann St",
    "sg:city":"Gosford",
    "sg:classifiers":[
        {
            "category":"Retail",
            "subcategory":"Auto Repair",
            "type":"Services"
        }
    ],
    "sg:phone":"+61 2 4324 1752",
    "sg:postcode":"2250",
    "sg:province":"NSW",
    "sg:tags":[
        "repairer",
        "motor",
        "engineer"
    ],
    "wof:name":"Repco Authorised Service",
    "wof:placetype":"venue"
},
  "geometry": {"coordinates":[151.34324645999999,-33.4193382263],"type":"Point"}
}