{
  "type": "Feature",
  "properties": {
    "addr:full":"243 Carrington St Adelaide SA 5000",
    "addr:housenumber":"243",
    "addr:postcode":"5000",
    "addr:street":"Carrington St",
    "iso:country":"AU",
    "sg:address":"243 Carrington St",
    "sg:city":"Adelaide",
    "sg:classifiers":[
        {
            "category":"Real Estate",
            "subcategory":"Real Estate Agent",
            "type":"Services"
        }
    ],
    "sg:phone":"+61 8 8232 1566",
    "sg:postcode":"5000",
    "sg:province":"SA",
    "sg:tags":[
        "motel",
        "hotel",
        "broker"
    ],
    "wof:name":"Hotel Brokers Steele & Associates",
    "wof:placetype":"venue"
},
  "geometry": {"coordinates":[138.609207153,-34.9311904907],"type":"Point"}
}