{
  "type": "Feature",
  "properties": {
    "iso:country":"AU",
    "sg:address":"178 Orrong Rd",
    "sg:city":"Caulfield",
    "sg:classifiers":[
        {
            "category":"Health Services",
            "subcategory":"Doctor",
            "type":"Services"
        }
    ],
    "sg:phone":"+61 3 9527 7357",
    "sg:postcode":"3162",
    "sg:province":"VIC",
    "sg:tags":[
        "medical",
        "practitioner"
    ],
    "wof:name":"Pakula Shyrla Dr",
    "wof:placetype":"venue"
},
  "geometry": {"coordinates":[145.00784301799999,-37.8755264282],"type":"Point"}
}