{
  "type": "Feature",
  "properties": {
    "iso:country":"AU",
    "sg:address":"38 Roseberry St",
    "sg:city":"Gladstone",
    "sg:classifiers":[
        {
            "category":"Building & Trades",
            "subcategory":"Construction",
            "type":"Services"
        }
    ],
    "sg:phone":"+61 7 4979 0000",
    "sg:postcode":"4680",
    "sg:province":"QLD",
    "sg:tags":[
        "contractor"
    ],
    "wof:name":"Craig Christensen Finest Homes",
    "wof:placetype":"venue"
},
  "geometry": {"coordinates":[151.25364685100001,-23.842634201],"type":"Point"}
}