{
  "type": "Feature",
  "properties": {
    "addr:full":"4 Elfrida St Mosman NSW 2088",
    "addr:housenumber":"4",
    "addr:postcode":"2088",
    "addr:street":"Elfrida St",
    "iso:country":"AU",
    "sg:address":"4 Elfrida St",
    "sg:city":"Mosman",
    "sg:classifiers":[
        {
            "category":"Real Estate",
            "subcategory":"Architect",
            "type":"Services"
        }
    ],
    "sg:phone":"+61 2 9968 1072",
    "sg:postcode":"2088",
    "sg:province":"NSW",
    "wof:name":"Mazaraki J J Newlin",
    "wof:placetype":"venue"
},
  "geometry": {"coordinates":[151.24171447800001,-33.8371315002],"type":"Point"}
}