{
  "type": "Feature",
  "properties": {
    "addr:full":"14 Melrose St Sandringham VIC 3191",
    "addr:housenumber":"14",
    "addr:postcode":"3191",
    "addr:street":"Melrose St",
    "iso:country":"AU",
    "sg:address":"14 Melrose St",
    "sg:city":"Sandringham",
    "sg:classifiers":[
        {
            "category":"Personal",
            "subcategory":"Beauty Salon",
            "type":"Services"
        }
    ],
    "sg:phone":"+61 3 9598 3877",
    "sg:postcode":"3191",
    "sg:province":"VIC",
    "sg:tags":[
        "hairdresser"
    ],
    "wof:name":"Hair Brigade",
    "wof:placetype":"venue"
},
  "geometry": {"coordinates":[145.00332641599999,-37.951007843],"type":"Point"}
}