{
  "type": "Feature",
  "properties": {
    "addr:full":"1388 Huntingdale Rd Oakleigh South VIC 3167",
    "addr:housenumber":"1388",
    "addr:postcode":"3167",
    "addr:street":"Huntingdale Rd",
    "iso:country":"AU",
    "sg:address":"1388 Huntingdale Rd",
    "sg:city":"Oakleigh South",
    "sg:classifiers":[
        {
            "category":"Retail",
            "subcategory":"Auto Repair",
            "type":"Services"
        }
    ],
    "sg:phone":"+61 1300 665 987",
    "sg:postcode":"3167",
    "sg:province":"VIC",
    "sg:tags":[
        "beater",
        "painter",
        "panel"
    ],
    "wof:name":"Everlast Automotive Group Australia Pty Ltd",
    "wof:placetype":"venue"
},
  "geometry": {"coordinates":[145.10336303700001,-37.9124336243],"type":"Point"}
}