{
  "type": "Feature",
  "properties": {
    "addr:full":"200 North Rd Eastwood NSW 2122",
    "addr:housenumber":"200",
    "addr:postcode":"2122",
    "addr:street":"North Rd",
    "iso:country":"AU",
    "sg:address":"200 North Rd",
    "sg:city":"Eastwood",
    "sg:classifiers":[
        {
            "category":"Organizations",
            "subcategory":"Professional Association",
            "type":"Services"
        }
    ],
    "sg:phone":"+61 2 9802 9373",
    "sg:postcode":"2122",
    "sg:province":"NSW",
    "sg:tags":[
        "web",
        "internet"
    ],
    "wof:name":"FormingIT Pty Ltd",
    "wof:placetype":"venue"
},
  "geometry": {"coordinates":[151.099777222,-33.7885131836],"type":"Point"}
}