{
  "type": "Feature",
  "properties": {
    "addr:full":"Mimosa Rd St Johns Park NSW 2176",
    "addr:postcode":"2176",
    "addr:street":"Mimosa Rd",
    "iso:country":"AU",
    "sg:address":"Mimosa Rd",
    "sg:city":"St Johns Park",
    "sg:classifiers":[
        {
            "category":"Education",
            "subcategory":"School",
            "type":"Public Place"
        }
    ],
    "sg:phone":"+61 2 9610 8035",
    "sg:postcode":"2176",
    "sg:province":"NSW",
    "sg:tags":[
        "state",
        "-",
        "nsw"
    ],
    "wof:name":"St Johns Park High School",
    "wof:placetype":"venue"
},
  "geometry": {"coordinates":[150.89253234899999,-33.8768196106],"type":"Point"}
}