{
  "type": "Feature",
  "properties": {
    "iso:country":"AU",
    "sg:address":"755 Geelong Rd",
    "sg:city":"Brooklyn",
    "sg:classifiers":[
        {
            "category":"Autos & Motor Vehicles",
            "subcategory":"Auto Supplies",
            "type":"Retail Goods"
        }
    ],
    "sg:phone":"+61 3 9318 0699",
    "sg:postcode":"3012",
    "sg:province":"VIC",
    "sg:tags":[
        "transmission",
        "equipment",
        "power"
    ],
    "wof:name":"SKF Bearing Supplies Pty Ltd",
    "wof:placetype":"venue"
},
  "geometry": {"coordinates":[144.882736206,-37.8040008545],"type":"Point"}
}