{
  "type": "Feature",
  "properties": {
    "addr:full":"Shop 13 Terrace Plaza Glenelg St Raymond Terrace NSW 2324",
    "addr:housenumber":"shop 13",
    "addr:postcode":"2324",
    "addr:street":"Terrace Plaza Glenelg St",
    "iso:country":"AU",
    "sg:address":"Shop 13 Terrace Plaza Glenelg St",
    "sg:city":"Raymond Terrace",
    "sg:classifiers":[
        {
            "category":"Shopping",
            "subcategory":"Clothing, Apparel, & Fashions",
            "type":"Retail Goods"
        }
    ],
    "sg:phone":"+61 2 4987 3134",
    "sg:postcode":"2324",
    "sg:province":"NSW",
    "sg:tags":[
        "lady",
        "wear"
    ],
    "wof:name":"Suzanne Grae",
    "wof:placetype":"venue"
},
  "geometry": {"coordinates":[151.744674683,-32.766544342],"type":"Point"}
}