{
  "type": "Feature",
  "properties": {
    "addr:full":"107 Beauchamp Rd Matraville NSW 2036",
    "addr:housenumber":"107",
    "addr:postcode":"2036",
    "addr:street":"Beauchamp Rd",
    "iso:country":"AU",
    "sg:address":"107 Beauchamp Rd",
    "sg:city":"Matraville",
    "sg:classifiers":[
        {
            "category":"Manufacturing",
            "subcategory":"Motor Vehicles & Parts",
            "type":"Manufacturing & Wholesale Goods"
        }
    ],
    "sg:phone":"+61 2 9316 8786",
    "sg:postcode":"2036",
    "sg:province":"NSW",
    "sg:tags":[
        "replacement"
    ],
    "wof:name":"Matraville Spare Parts & Car Sales Pty Ltd",
    "wof:placetype":"venue"
},
  "geometry": {"coordinates":[151.22280883799999,-33.9586639404],"type":"Point"}
}