{
  "type": "Feature",
  "properties": {
    "addr:full":"Shop 30 Southlands Shopng Cntr Willetton WA 6155",
    "addr:housenumber":"shop 30",
    "addr:postcode":"6155",
    "addr:street":"Southlands Shopng Cntr",
    "iso:country":"AU",
    "sg:address":"Shop 30",
    "sg:city":"Southlands Shopng Cntr Willetton",
    "sg:classifiers":[
        {
            "category":"Personal",
            "subcategory":"Beauty Salon",
            "type":"Services"
        }
    ],
    "sg:phone":"+61 8 9332 3370",
    "sg:postcode":"6155",
    "sg:province":"WA",
    "sg:tags":[
        "hairdresser"
    ],
    "wof:name":"Southlands Hair Design",
    "wof:placetype":"venue"
},
  "geometry": {"coordinates":[115.88915299999999,-32.052361],"type":"Point"}
}