{
  "type": "Feature",
  "properties": {
    "addr:full":"Shop 209, Broadway Shopping Centre 1 Bay St Broadway NSW 2007",
    "addr:housenumber":"209;1",
    "addr:postcode":"2007",
    "addr:street":"Broadway Shopping;Bay St",
    "iso:country":"AU",
    "sg:address":"Shop 209, Broadway Shopping Centre 1 Bay St",
    "sg:city":"Broadway",
    "sg:classifiers":[
        {
            "category":"Shopping",
            "subcategory":"Computers & Home Electronics",
            "type":"Retail Goods"
        }
    ],
    "sg:phone":"+61 2 9211 3777",
    "sg:postcode":"2007",
    "sg:province":"NSW",
    "sg:tags":[
        "small",
        "equipment",
        "business"
    ],
    "wof:name":"Dick Smith Electronics",
    "wof:placetype":"venue"
},
  "geometry": {"coordinates":[151.1953125,-33.8842582703],"type":"Point"}
}