{
  "type": "Feature",
  "properties": {
    "addr:full":"44 Mc Intosh St Shepparton VIC 3630",
    "addr:housenumber":"44",
    "addr:postcode":"3630",
    "addr:street":"Mc Intosh St",
    "iso:country":"AU",
    "sg:address":"44 Mc Intosh St",
    "sg:city":"Shepparton",
    "sg:classifiers":[
        {
            "category":"Food & Beverages",
            "subcategory":"Groceries & Convenience Stores",
            "type":"Retail Goods"
        }
    ],
    "sg:phone":"+61 3 5822 2400",
    "sg:postcode":"3630",
    "sg:province":"VIC",
    "wof:name":"Macintosh Street Milk Bar",
    "wof:placetype":"venue"
},
  "geometry": {"coordinates":[145.388397217,-36.3832092285],"type":"Point"}
}