{
  "type": "Feature",
  "properties": {
    "iso:country":"AU",
    "sg:address":"52 Jacaranda Ave",
    "sg:city":"Boronia Heights",
    "sg:classifiers":[
        {
            "category":"Retail",
            "subcategory":"Auto Repair",
            "type":"Services"
        }
    ],
    "sg:phone":"+61 417 726 415",
    "sg:postcode":"4124",
    "sg:province":"QLD",
    "sg:tags":[
        "camper-trailers",
        "caravan",
        "servicing"
    ],
    "wof:name":"Mobile Caravan Service",
    "wof:placetype":"venue"
},
  "geometry": {"coordinates":[153.012176514,-27.6828956604],"type":"Point"}
}