{
  "type": "Feature",
  "properties": {
    "addr:full":"3 Bowman Crt Wodonga VIC 3689",
    "addr:housenumber":"3",
    "addr:postcode":"3689",
    "addr:street":"Bowman Crt",
    "iso:country":"AU",
    "sg:address":"3 Bowman Crt",
    "sg:city":"Wodonga",
    "sg:classifiers":[
        {
            "category":"Travel",
            "subcategory":"Hostel",
            "type":"Entertainment"
        }
    ],
    "sg:phone":"+61 2 6059 3333",
    "sg:postcode":"3689",
    "sg:province":"VIC",
    "sg:tags":[
        "home"
    ],
    "wof:name":"Westmont Aged Care Services Ltd",
    "wof:placetype":"venue"
},
  "geometry": {"coordinates":[146.86265599999999,-36.129963],"type":"Point"}
}