{
  "type": "Feature",
  "properties": {
    "iso:country":"AU",
    "sg:address":"3 Bowman Crt",
    "sg:city":"Wodonga",
    "sg:classifiers":[
        {
            "category":"Travel",
            "subcategory":"Hostel",
            "type":"Entertainment"
        }
    ],
    "sg:phone":"+61 2 6059 3333",
    "sg:postcode":"3689",
    "sg:province":"VIC",
    "sg:tags":[
        "home"
    ],
    "wof:name":"Westmont Aged Care Services Ltd",
    "wof:placetype":"venue"
},
  "geometry": {"coordinates":[146.862656,-36.129963],"type":"Point"}
}