{
  "type": "Feature",
  "properties": {
    "addr:full":"Shop 11 Macquarie Place Elizabeth Drv Liverpool NSW 2170",
    "addr:housenumber":"shop 11",
    "addr:postcode":"2170",
    "addr:street":"Macquarie Place Elizabeth Drv",
    "iso:country":"AU",
    "sg:address":"Shop 11 Macquarie Place Elizabeth Drv",
    "sg:city":"Liverpool",
    "sg:classifiers":[
        {
            "category":"Deli",
            "type":"Food & Drink"
        }
    ],
    "sg:phone":"+61 2 9601 8516",
    "sg:postcode":"2170",
    "sg:province":"NSW",
    "sg:tags":[
        "delicatessen"
    ],
    "wof:name":"Continental Deli Euro",
    "wof:placetype":"venue"
},
  "geometry": {"coordinates":[150.918243408,-33.9284934998],"type":"Point"}
}