{
  "type": "Feature",
  "properties": {
    "addr:full":"15 Hanrahan St Thomastown VIC 3074",
    "addr:housenumber":"15",
    "addr:postcode":"3074",
    "addr:street":"Hanrahan St",
    "iso:country":"AU",
    "sg:address":"15 Hanrahan St",
    "sg:city":"Thomastown",
    "sg:classifiers":[
        {
            "category":"Retail",
            "subcategory":"Auto Repair",
            "type":"Services"
        }
    ],
    "sg:phone":"+61 3 9464 1500",
    "sg:postcode":"3074",
    "sg:province":"VIC",
    "sg:tags":[
        "beater",
        "painter",
        "panel"
    ],
    "wof:name":"Hightrax Body Works Pty Ltd",
    "wof:placetype":"venue"
},
  "geometry": {"coordinates":[145.026321411,-37.6940765381],"type":"Point"}
}