{
  "type": "Feature",
  "properties": {
    "iso:country":"AU",
    "sg:address":"Unit 7/ 156 Bay St",
    "sg:city":"Port Melbourne",
    "sg:classifiers":[
        {
            "category":"Professional",
            "subcategory":"Art Services",
            "type":"Services"
        }
    ],
    "sg:phone":"+61 3 9681 9499",
    "sg:postcode":"3207",
    "sg:province":"VIC",
    "sg:tags":[
        "graphic",
        "designer"
    ],
    "wof:name":"Outsource Design",
    "wof:placetype":"venue"
},
  "geometry": {"coordinates":[144.941147,-37.840092],"type":"Point"}
}