{
  "type": "Feature",
  "properties": {
    "addr:full":"Factory 2/ 271 Wells Rd Chelsea Heights VIC 3196",
    "addr:housenumber":"/ 271",
    "addr:postcode":"3196",
    "addr:street":"Wells Rd",
    "iso:country":"AU",
    "sg:address":"Factory 2/ 271 Wells Rd",
    "sg:city":"Chelsea Heights",
    "sg:classifiers":[
        {
            "category":"Utilities",
            "type":"Services"
        }
    ],
    "sg:phone":"+61 3 9772 0311",
    "sg:postcode":"3196",
    "sg:province":"VIC",
    "sg:tags":[
        "equipment",
        "towing"
    ],
    "wof:name":"Longbeach Exhaust & Autocare",
    "wof:placetype":"venue"
},
  "geometry": {"coordinates":[145.14344787600001,-38.0508384705],"type":"Point"}
}