{
  "type": "Feature",
  "properties": {
    "iso:country":"AU",
    "sg:address":"7 Belgrave Ave",
    "sg:city":"Cockatoo",
    "sg:classifiers":[
        {
            "category":"Banks & Credit Unions",
            "subcategory":"Financial Services",
            "type":"Services"
        }
    ],
    "sg:phone":"+61 3 5968 8508",
    "sg:postcode":"3781",
    "sg:province":"VIC",
    "sg:tags":[
        "annuity",
        "rollover",
        "superannuation",
        "consultant"
    ],
    "wof:name":"Financial Answers Pty Ltd",
    "wof:placetype":"venue"
},
  "geometry": {"coordinates":[145.49653599999999,-37.929043],"type":"Point"}
}