{
  "type": "Feature",
  "properties": {
    "addr:full":"PO Box 112 Bega NSW 2550",
    "addr:postcode":"2550",
    "iso:country":"AU",
    "sg:address":"PO Box 112",
    "sg:city":"Bega",
    "sg:classifiers":[
        {
            "category":"Shopping",
            "subcategory":"Music",
            "type":"Retail Goods"
        }
    ],
    "sg:phone":"+61 2 6492 0017",
    "sg:postcode":"2550",
    "sg:province":"NSW",
    "sg:tags":[
        "instrument",
        "musical"
    ],
    "wof:name":"Chulkdust Records",
    "wof:placetype":"venue"
},
  "geometry": {"coordinates":[149.84138488799999,-36.6739883423],"type":"Point"}
}