{
  "type": "Feature",
  "properties": {
    "iso:country":"AU",
    "sg:address":"Cnr Alfrieda & Williams Sts",
    "sg:city":"St Albans",
    "sg:classifiers":[
        {
            "category":"Organizations",
            "subcategory":"Community Association",
            "type":"Services"
        }
    ],
    "sg:phone":"+61 3 9366 7981",
    "sg:postcode":"3021",
    "sg:province":"VIC",
    "sg:tags":[
        "club",
        "senior",
        "citizen"
    ],
    "wof:name":"St Albans Senior Citizens Centre",
    "wof:placetype":"venue"
},
  "geometry": {"coordinates":[144.80072000000001,-37.743229],"type":"Point"}
}