{
  "type": "Feature",
  "properties": {
    "iso:country":"AU",
    "sg:address":"Martin Rd",
    "sg:city":"Albany",
    "sg:classifiers":[
        {
            "category":"Education",
            "subcategory":"School",
            "type":"Public Place"
        }
    ],
    "sg:phone":"+61 8 9844 0222",
    "sg:postcode":"6330",
    "sg:province":"WA",
    "wof:name":"St Joseph's College",
    "wof:placetype":"venue"
},
  "geometry": {"coordinates":[117.903236389,-34.984916687],"type":"Point"}
}