{
  "type": "Feature",
  "properties": {
    "addr:full":"59 Barrabool Rd Belmont VIC 3216",
    "addr:housenumber":"59",
    "addr:postcode":"3216",
    "addr:street":"Barrabool Rd",
    "iso:country":"AU",
    "sg:address":"59 Barrabool Rd",
    "sg:city":"Belmont",
    "sg:classifiers":[
        {
            "category":"Cafe",
            "type":"Food & Drink"
        }
    ],
    "sg:phone":"+61 3 5244 2044",
    "sg:postcode":"3216",
    "sg:province":"VIC",
    "wof:name":"Riverview Coffee House",
    "wof:placetype":"venue"
},
  "geometry": {"coordinates":[144.337158203,-38.1661186218],"type":"Point"}
}