{
  "type": "Feature",
  "properties": {
    "addr:full":"88b Station St Fairfield VIC 3078",
    "addr:housenumber":"88b",
    "addr:postcode":"3078",
    "addr:street":"Station St",
    "iso:country":"AU",
    "sg:address":"88b Station St",
    "sg:city":"Fairfield",
    "sg:classifiers":[
        {
            "category":"Manufacturing",
            "subcategory":"Tools & Machinery",
            "type":"Manufacturing & Wholesale Goods"
        }
    ],
    "sg:phone":"+61 3 9486 8033",
    "sg:postcode":"3078",
    "sg:province":"VIC",
    "sg:tags":[
        "wholesaler",
        "lingerie",
        "mfrs",
        "sleepwear"
    ],
    "wof:name":"Schiaparelli",
    "wof:placetype":"venue"
},
  "geometry": {"coordinates":[145.018341064,-37.7787094116],"type":"Point"}
}