{
  "type": "Feature",
  "properties": {
    "addr:full":"48 Lakeside Cct Dubbo NSW 2830",
    "addr:housenumber":"48",
    "addr:postcode":"2830",
    "addr:street":"Lakeside Cct",
    "iso:country":"AU",
    "sg:address":"48 Lakeside Cct",
    "sg:city":"Dubbo",
    "sg:classifiers":[
        {
            "category":"Building & Trades",
            "subcategory":"Plumbing",
            "type":"Services"
        }
    ],
    "sg:phone":"+61 419 464 300",
    "sg:postcode":"2830",
    "sg:province":"NSW",
    "sg:tags":[
        "plumber",
        "gasfitters"
    ],
    "wof:name":"Beahan G",
    "wof:placetype":"venue"
},
  "geometry": {"coordinates":[148.57594299300001,-32.2609176636],"type":"Point"}
}