{
  "type": "Feature",
  "properties": {
    "addr:full":"Shop 361 Westfields Hurstville NSW 2220",
    "addr:housenumber":"361",
    "addr:postcode":"2220",
    "addr:street":"Westfields",
    "iso:country":"AU",
    "sg:address":"Shop 361 Westfields",
    "sg:city":"Hurstville",
    "sg:classifiers":[
        {
            "category":"Shopping",
            "subcategory":"Clothing, Apparel, & Fashions",
            "type":"Retail Goods"
        }
    ],
    "sg:phone":"+61 2 9585 9933",
    "sg:postcode":"2220",
    "sg:province":"NSW",
    "sg:tags":[
        "menswear"
    ],
    "wof:name":"Reuben F Scarf",
    "wof:placetype":"venue"
},
  "geometry": {"coordinates":[151.10104370100001,-33.9671897888],"type":"Point"}
}