{
  "type": "Feature",
  "properties": {
    "addr:full":"15 Tullaroop Rd Maryborough VIC 3465",
    "addr:housenumber":"15",
    "addr:postcode":"3465",
    "addr:street":"Tullaroop Rd",
    "iso:country":"AU",
    "sg:address":"15 Tullaroop Rd",
    "sg:city":"Maryborough",
    "sg:classifiers":[
        {
            "category":"Commercial Area",
            "type":"Public Place"
        }
    ],
    "sg:phone":"+61 3 5460 4455",
    "sg:postcode":"3465",
    "sg:province":"VIC",
    "sg:tags":[
        "heavy",
        "carrier"
    ],
    "wof:name":"Central Victorian Transporters P/L",
    "wof:placetype":"venue"
},
  "geometry": {"coordinates":[143.749343872,-37.0335464478],"type":"Point"}
}