{
  "type": "Feature",
  "properties": {
    "iso:country":"AU",
    "sg:address":"1/ 34 Pilkington St",
    "sg:city":"Garbutt",
    "sg:classifiers":[
        {
            "category":"Utilities",
            "subcategory":"Telephone",
            "type":"Services"
        }
    ],
    "sg:phone":"+61 7 4725 5666",
    "sg:postcode":"4814",
    "sg:province":"QLD",
    "sg:tags":[
        "installation",
        "system",
        "maintenance"
    ],
    "wof:name":"Fortel Communications Pty Ltd",
    "wof:placetype":"venue"
},
  "geometry": {"coordinates":[146.767517,-19.267975],"type":"Point"}
}