{
  "type": "Feature",
  "properties": {
    "addr:full":"72 Queen St Berry NSW 2535",
    "addr:housenumber":"72",
    "addr:postcode":"2535",
    "addr:street":"Queen St",
    "iso:country":"AU",
    "sg:address":"72 Queen St",
    "sg:city":"Berry",
    "sg:classifiers":[
        {
            "category":"Travel",
            "subcategory":"Hotels & Motels",
            "type":"Entertainment"
        }
    ],
    "sg:phone":"+61 2 4464 3570",
    "sg:postcode":"2535",
    "sg:province":"NSW",
    "wof:name":"Berry Village Boutique Motel",
    "wof:placetype":"venue"
},
  "geometry": {"coordinates":[150.692993164,-34.7750205994],"type":"Point"}
}