{
  "type": "Feature",
  "properties": {
    "addr:full":"4 Robertson St Kalgoorlie WA 6430",
    "addr:housenumber":"4",
    "addr:postcode":"6430",
    "addr:street":"Robertson St",
    "iso:country":"AU",
    "sg:address":"4 Robertson St",
    "sg:city":"Kalgoorlie",
    "sg:classifiers":[
        {
            "category":"Utilities",
            "subcategory":"Electric",
            "type":"Services"
        }
    ],
    "sg:phone":"+61 408 935 314",
    "sg:postcode":"6430",
    "sg:province":"WA",
    "sg:tags":[
        "electrical",
        "contractor"
    ],
    "wof:name":"Tony Free Electrical",
    "wof:placetype":"venue"
},
  "geometry": {"coordinates":[121.472793579,-30.7581958771],"type":"Point"}
}