{
  "type": "Feature",
  "properties": {
    "iso:country":"AU",
    "sg:address":"9 Logan St",
    "sg:city":"Glenroy",
    "sg:classifiers":[
        {
            "category":"Building & Trades",
            "subcategory":"Construction",
            "type":"Services"
        }
    ],
    "sg:phone":"+61 3 9306 6989",
    "sg:postcode":"3046",
    "sg:province":"VIC",
    "sg:tags":[
        "contractor"
    ],
    "wof:name":"Coiro A S",
    "wof:placetype":"venue"
},
  "geometry": {"coordinates":[144.92445373499999,-37.7050552368],"type":"Point"}
}