{
  "type": "Feature",
  "properties": {
    "addr:full":"170 Tarleton St Devonport East TAS 7310",
    "addr:housenumber":"170",
    "addr:postcode":"7310",
    "addr:street":"Tarleton St",
    "iso:country":"AU",
    "sg:address":"170 Tarleton St",
    "sg:city":"Devonport East",
    "sg:classifiers":[
        {
            "category":"Autos & Motor Vehicles",
            "subcategory":"Auto Supplies",
            "type":"Retail Goods"
        }
    ],
    "sg:phone":"+61 3 6427 8368",
    "sg:postcode":"7310",
    "sg:province":"TAS",
    "sg:tags":[
        "battery",
        "automotive"
    ],
    "wof:name":"Morse W. J. & K. J. Auto Electrical",
    "wof:placetype":"venue"
},
  "geometry": {"coordinates":[146.370697022,-41.1887626648],"type":"Point"}
}