{
  "type": "Feature",
  "properties": {
    "addr:full":"Shop 6, 68 Barkly St Mornington VIC 3931",
    "addr:housenumber":"shop;68",
    "addr:postcode":"3931",
    "addr:street":"Barkly St",
    "iso:country":"AU",
    "sg:address":"Shop 6, 68 Barkly St",
    "sg:city":"Mornington",
    "sg:classifiers":[
        {
            "category":"Personal",
            "subcategory":"Beauty Salon",
            "type":"Services"
        }
    ],
    "sg:phone":"+61 3 5975 6266",
    "sg:postcode":"3931",
    "sg:province":"VIC",
    "sg:tags":[
        "hairdresser"
    ],
    "wof:name":"Hair Generation",
    "wof:placetype":"venue"
},
  "geometry": {"coordinates":[145.04826355,-38.2174415588],"type":"Point"}
}