{
  "type": "Feature",
  "properties": {
    "iso:country":"AU",
    "sg:address":"200 Midland Hwy",
    "sg:city":"Elaine",
    "sg:classifiers":[
        {
            "category":"Home & Garden",
            "subcategory":"Building Materials",
            "type":"Retail Goods"
        }
    ],
    "sg:phone":"+61 3 5341 5500",
    "sg:postcode":"3334",
    "sg:province":"VIC",
    "sg:tags":[
        "fitting",
        "door"
    ],
    "wof:name":"Lara Glass & Glazing Pty Ltd",
    "wof:placetype":"venue"
},
  "geometry": {"coordinates":[144.027176,-37.774944],"type":"Point"}
}