{
  "type": "Feature",
  "properties": {
    "addr:full":"20 Yass Rd Cootamundra NSW 2590",
    "addr:housenumber":"20",
    "addr:postcode":"2590",
    "addr:street":"Yass Rd",
    "iso:country":"AU",
    "sg:address":"20 Yass Rd",
    "sg:city":"Cootamundra",
    "sg:classifiers":[
        {
            "category":"Mining & Drilling",
            "type":"Manufacturing & Wholesale Goods"
        }
    ],
    "sg:phone":"+61 2 6942 2994",
    "sg:postcode":"2590",
    "sg:province":"NSW",
    "sg:tags":[
        "boring",
        "contractor"
    ],
    "wof:name":"Radnedge K & M",
    "wof:placetype":"venue"
},
  "geometry": {"coordinates":[148.02609252900001,-34.6400413513],"type":"Point"}
}