{
  "type": "Feature",
  "properties": {
    "addr:full":"8- 12 Mayfield Rd Moorooka QLD 4105",
    "addr:housenumber":"12",
    "addr:postcode":"4105",
    "addr:street":"8;Mayfield Rd",
    "iso:country":"AU",
    "sg:address":"8- 12 Mayfield Rd",
    "sg:city":"Moorooka",
    "sg:classifiers":[
        {
            "category":"Professional",
            "subcategory":"Employment Agencies",
            "type":"Services"
        }
    ],
    "sg:phone":"+61 7 3373 0800",
    "sg:postcode":"4105",
    "sg:province":"QLD",
    "wof:name":"Salvation Army Employment Plus The",
    "wof:placetype":"venue"
},
  "geometry": {"coordinates":[153.025787353,-27.5327701569],"type":"Point"}
}