{
  "type": "Feature",
  "properties": {
    "iso:country":"AU",
    "sg:address":"56 Grafton St",
    "sg:city":"Warwick",
    "sg:classifiers":[
        {
            "category":"Building & Trades",
            "subcategory":"Plumbing",
            "type":"Services"
        }
    ],
    "sg:phone":"+61 7 4661 1644",
    "sg:postcode":"4370",
    "sg:province":"QLD",
    "sg:tags":[
        "pump",
        "repairer"
    ],
    "wof:name":"McCracken's Water Services",
    "wof:placetype":"venue"
},
  "geometry": {"coordinates":[152.036865234,-28.2168960571],"type":"Point"}
}