{
  "type": "Feature",
  "properties": {
    "addr:full":"PO Box 176 Yorkeys Knob QLD 4878",
    "addr:postcode":"4878",
    "iso:country":"AU",
    "sg:address":"PO Box 176",
    "sg:city":"Yorkeys Knob",
    "sg:classifiers":[
        {
            "category":"Health Services",
            "subcategory":"Health Practitioner",
            "type":"Services"
        }
    ],
    "sg:phone":"+61 7 4055 8378",
    "sg:postcode":"4878",
    "sg:province":"QLD",
    "sg:tags":[
        "psychologist"
    ],
    "wof:name":"Nicki Gazis",
    "wof:placetype":"venue"
},
  "geometry": {"coordinates":[145.72073364299999,-16.8127193451],"type":"Point"}
}