{
  "type": "Feature",
  "properties": {
    "addr:full":"16 Smart Crs Cronulla NSW 2230",
    "addr:housenumber":"16",
    "addr:postcode":"2230",
    "addr:street":"Smart Crs",
    "iso:country":"AU",
    "sg:address":"16 Smart Crs",
    "sg:city":"Cronulla",
    "sg:classifiers":[
        {
            "category":"Social Services",
            "subcategory":"Retirement Home",
            "type":"Services"
        }
    ],
    "sg:phone":"+61 2 9523 5716",
    "sg:postcode":"2230",
    "sg:province":"NSW",
    "sg:tags":[
        "village"
    ],
    "wof:name":"Mount St Vincent Home For Aged",
    "wof:placetype":"venue"
},
  "geometry": {"coordinates":[151.153366089,-34.055229187],"type":"Point"}
}