{
  "type": "Feature",
  "properties": {
    "addr:full":"56 Newcastle St Stockton NSW 2295",
    "addr:housenumber":"56",
    "addr:postcode":"2295",
    "addr:street":"Newcastle St",
    "iso:country":"AU",
    "sg:address":"56 Newcastle St",
    "sg:city":"Stockton",
    "sg:classifiers":[
        {
            "category":"Building & Trades",
            "subcategory":"Plumbing",
            "type":"Services"
        }
    ],
    "sg:phone":"+61 412 688 495",
    "sg:postcode":"2295",
    "sg:province":"NSW",
    "sg:tags":[
        "plumber",
        "gasfitters"
    ],
    "wof:name":"Hartigan Stephen Plumbing Services",
    "wof:placetype":"venue"
},
  "geometry": {"coordinates":[151.786987305,-32.9142112732],"type":"Point"}
}