{
  "type": "Feature",
  "properties": {
    "addr:full":"Warrego Hwy Dulacca QLD 4425",
    "addr:postcode":"4425",
    "addr:street":"Warrego Hwy",
    "iso:country":"AU",
    "sg:address":"Warrego Hwy",
    "sg:city":"Dulacca",
    "sg:classifiers":[
        {
            "category":"Autos & Motor Vehicles",
            "subcategory":"Auto Supplies",
            "type":"Retail Goods"
        }
    ],
    "sg:phone":"+61 7 4627 6171",
    "sg:postcode":"4425",
    "sg:province":"QLD",
    "sg:tags":[
        "oil",
        "spirit"
    ],
    "wof:name":"BP Oil",
    "wof:placetype":"venue"
},
  "geometry": {"coordinates":[149.76890564000001,-26.6443786621],"type":"Point"}
}