{
  "type": "Feature",
  "properties": {
    "addr:full":"3 Short St Chatswood NSW 2067",
    "addr:housenumber":"3",
    "addr:postcode":"2067",
    "addr:street":"Short St",
    "iso:country":"AU",
    "sg:address":"3 Short St",
    "sg:city":"Chatswood",
    "sg:classifiers":[
        {
            "category":"Professional",
            "subcategory":"Detective & Security Services",
            "type":"Services"
        }
    ],
    "sg:phone":"+61 2 9417 7870",
    "sg:postcode":"2067",
    "sg:province":"NSW",
    "sg:tags":[
        "consultant",
        "laser"
    ],
    "wof:name":"Excel Laser Cutting Pty Ltd",
    "wof:placetype":"venue"
},
  "geometry": {"coordinates":[151.19720459000001,-33.7860565186],"type":"Point"}
}