{
  "type": "Feature",
  "properties": {
    "addr:full":"Unit 2, 345 Victoria Rd Malaga WA 6090",
    "addr:housenumber":"345",
    "addr:postcode":"6090",
    "addr:street":"Victoria Rd",
    "iso:country":"AU",
    "sg:address":"Unit 2, 345 Victoria Rd",
    "sg:city":"Malaga",
    "sg:classifiers":[
        {
            "category":"Building & Trades",
            "subcategory":"Construction",
            "type":"Services"
        }
    ],
    "sg:phone":"+61 1800 245 235",
    "sg:postcode":"6090",
    "sg:province":"WA",
    "sg:tags":[
        "insulation",
        "contractor"
    ],
    "wof:name":"Woolstore Insulation",
    "wof:placetype":"venue"
},
  "geometry": {"coordinates":[115.89057159399999,-31.8614044189],"type":"Point"}
}