{
  "type": "Feature",
  "properties": {
    "iso:country":"AU",
    "sg:address":"118 Morrison Rd",
    "sg:city":"Gladesville",
    "sg:classifiers":[
        {
            "category":"Building & Trades",
            "subcategory":"Cleaning & Sanitation",
            "type":"Services"
        }
    ],
    "sg:phone":"+61 2 9817 4057",
    "sg:postcode":"2111",
    "sg:province":"NSW",
    "sg:tags":[
        "cleaner",
        "repairer",
        "roof"
    ],
    "wof:name":"Brown R & W",
    "wof:placetype":"venue"
},
  "geometry": {"coordinates":[151.116744995,-33.8274497986],"type":"Point"}
}