{
  "type": "Feature",
  "properties": {
    "iso:country":"AU",
    "sg:address":"265 Mickleham Rd",
    "sg:city":"Tullamarine",
    "sg:classifiers":[
        {
            "category":"Retail",
            "subcategory":"Event Space",
            "type":"Services"
        }
    ],
    "sg:phone":"+61 3 9335 2340",
    "sg:postcode":"3043",
    "sg:province":"VIC",
    "sg:tags":[
        "venue",
        "reception",
        "wedding"
    ],
    "wof:name":"Digbys Restaurant",
    "wof:placetype":"venue"
},
  "geometry": {"coordinates":[144.88287353499999,-37.6826820374],"type":"Point"}
}