{
  "type": "Feature",
  "properties": {
    "addr:full":"PO Box 130 Boyanup WA 6237",
    "addr:postcode":"6237",
    "iso:country":"AU",
    "sg:address":"PO Box 130",
    "sg:city":"Boyanup",
    "sg:classifiers":[
        {
            "category":"Building & Trades",
            "subcategory":"Plumbing",
            "type":"Services"
        }
    ],
    "sg:phone":"+61 428 565 302",
    "sg:postcode":"6237",
    "sg:province":"WA",
    "sg:tags":[
        "plumber",
        "gasfitters"
    ],
    "wof:name":"Boyanup Plumbing & Gas",
    "wof:placetype":"venue"
},
  "geometry": {"coordinates":[115.727707,-33.482281],"type":"Point"}
}