{
  "type": "Feature",
  "properties": {
    "addr:full":"46 Gap Rd Sunbury VIC 3429",
    "addr:housenumber":"46",
    "addr:postcode":"3429",
    "addr:street":"Gap Rd",
    "iso:country":"AU",
    "sg:address":"46 Gap Rd",
    "sg:city":"Sunbury",
    "sg:classifiers":[
        {
            "category":"Health Services",
            "subcategory":"Health Practitioner",
            "type":"Services"
        }
    ],
    "sg:phone":"+61 3 9740 4429",
    "sg:postcode":"3429",
    "sg:province":"VIC",
    "sg:tags":[
        "physiotherapist"
    ],
    "wof:name":"Backfocus Physiotherapy",
    "wof:placetype":"venue"
},
  "geometry": {"coordinates":[144.72267150900001,-37.5796203613],"type":"Point"}
}