{
  "type": "Feature",
  "properties": {
    "addr:full":"49a Majors Bay Rd Concord NSW 2137",
    "addr:housenumber":"49a",
    "addr:postcode":"2137",
    "addr:street":"Majors Bay Rd",
    "iso:country":"AU",
    "sg:address":"49a Majors Bay Rd",
    "sg:city":"Concord",
    "sg:classifiers":[
        {
            "category":"Health Services",
            "subcategory":"Optometrist",
            "type":"Services"
        }
    ],
    "sg:phone":"+61 2 9743 0898",
    "sg:postcode":"2137",
    "sg:province":"NSW",
    "wof:name":"Wilson Elizabeth",
    "wof:placetype":"venue"
},
  "geometry": {"coordinates":[151.10348510700001,-33.856590271],"type":"Point"}
}