{
  "type": "Feature",
  "properties": {
    "addr:full":"10 Gibson St Belmont NSW 2280",
    "addr:housenumber":"10",
    "addr:postcode":"2280",
    "addr:street":"Gibson St",
    "iso:country":"AU",
    "sg:address":"10 Gibson St",
    "sg:city":"Belmont",
    "sg:classifiers":[
        {
            "category":"Social Services",
            "subcategory":"Retirement Home",
            "type":"Services"
        }
    ],
    "sg:phone":"+61 2 4945 0300",
    "sg:postcode":"2280",
    "sg:province":"NSW",
    "sg:tags":[
        "village"
    ],
    "wof:name":"Lake Macquarie Retirement Village",
    "wof:placetype":"venue"
},
  "geometry": {"coordinates":[151.66523742699999,-33.0363464355],"type":"Point"}
}