{
  "type": "Feature",
  "properties": {
    "iso:country":"AU",
    "sg:address":"22 Bauhinia Drv",
    "sg:city":"Hervey Bay",
    "sg:classifiers":[
        {
            "category":"Building & Trades",
            "subcategory":"Construction",
            "type":"Services"
        }
    ],
    "sg:phone":"+61 7 4124 1982",
    "sg:postcode":"4655",
    "sg:province":"QLD",
    "sg:tags":[
        "pool",
        "swimming"
    ],
    "wof:name":"Bay Pools & Landscaping",
    "wof:placetype":"venue"
},
  "geometry": {"coordinates":[152.847336,-25.300552],"type":"Point"}
}