{
  "type": "Feature",
  "properties": {
    "addr:full":"32 Taralga Rd Goulburn NSW 2580",
    "addr:housenumber":"32",
    "addr:postcode":"2580",
    "addr:street":"Taralga Rd",
    "iso:country":"AU",
    "sg:address":"32 Taralga Rd",
    "sg:city":"Goulburn",
    "sg:classifiers":[
        {
            "category":"Building & Trades",
            "subcategory":"Construction",
            "type":"Services"
        }
    ],
    "sg:phone":"+61 2 4821 7164",
    "sg:postcode":"2580",
    "sg:province":"NSW",
    "sg:tags":[
        "contractor"
    ],
    "wof:name":"Harris J & V",
    "wof:placetype":"venue"
},
  "geometry": {"coordinates":[149.7368927,-34.7300949097],"type":"Point"}
}