{
  "type": "Feature",
  "properties": {
    "iso:country":"AU",
    "sg:address":"PO Box 4",
    "sg:city":"Mansfield Park",
    "sg:classifiers":[
        {
            "category":"Shopping",
            "subcategory":"Pawn Shop",
            "type":"Retail Goods"
        }
    ],
    "sg:phone":"+61 400 500 150",
    "sg:postcode":"5012",
    "sg:province":"SA",
    "sg:tags":[
        "pawnbroker"
    ],
    "wof:name":"Reddi Cash",
    "wof:placetype":"venue"
},
  "geometry": {"coordinates":[138.548217773,-34.8562088013],"type":"Point"}
}