{
  "type": "Feature",
  "properties": {
    "addr:full":"Lot 10 Pony Crt Table Top NSW 2640",
    "addr:postcode":"2640",
    "addr:street":"Pony Crt",
    "iso:country":"AU",
    "sg:address":"Lot 10 Pony Crt",
    "sg:city":"Table Top",
    "sg:classifiers":[
        {
            "category":"Home & Garden",
            "subcategory":"Carpets & Floor Coverings",
            "type":"Retail Goods"
        }
    ],
    "sg:phone":"+61 2 6026 2301",
    "sg:postcode":"2640",
    "sg:province":"NSW",
    "sg:tags":[
        "wood"
    ],
    "wof:name":"Pioneer Floor Sanding",
    "wof:placetype":"venue"
},
  "geometry": {"coordinates":[146.96327209500001,-35.9735450745],"type":"Point"}
}