{
  "type": "Feature",
  "properties": {
    "addr:full":"3/ 26 Leda Blv Morayfield QLD 4506",
    "addr:housenumber":"/ 26",
    "addr:postcode":"4506",
    "addr:street":"Leda Blv",
    "iso:country":"AU",
    "sg:address":"3/ 26 Leda Blv",
    "sg:city":"Morayfield",
    "sg:classifiers":[
        {
            "category":"Personal",
            "subcategory":"Beauty Salon",
            "type":"Services"
        }
    ],
    "sg:phone":"+61 7 5495 2447",
    "sg:postcode":"4506",
    "sg:province":"QLD",
    "sg:tags":[
        "hairdresser"
    ],
    "wof:name":"Designer Styles Hair & Beauty Salon",
    "wof:placetype":"venue"
},
  "geometry": {"coordinates":[152.94900512699999,-27.10414505],"type":"Point"}
}