{
  "type": "Feature",
  "properties": {
    "addr:full":"2/ 92 Brush Rd Ourimbah NSW 2258",
    "addr:housenumber":"/ 92",
    "addr:postcode":"2258",
    "addr:street":"Brush Rd",
    "iso:country":"AU",
    "sg:address":"2/ 92 Brush Rd",
    "sg:city":"Ourimbah",
    "sg:classifiers":[
        {
            "category":"Professional",
            "subcategory":"Computer Services",
            "type":"Services"
        }
    ],
    "sg:phone":"+61 417 742 718",
    "sg:postcode":"2258",
    "sg:province":"NSW",
    "sg:tags":[
        "training"
    ],
    "wof:name":"Computer Confidence For Women",
    "wof:placetype":"venue"
},
  "geometry": {"coordinates":[151.386184692,-33.364490509],"type":"Point"}
}