{
  "type": "Feature",
  "properties": {
    "addr:full":"2a George St Pennington SA 5013",
    "addr:housenumber":"2a",
    "addr:postcode":"5013",
    "addr:street":"George St",
    "iso:country":"AU",
    "sg:address":"2a George St",
    "sg:city":"Pennington",
    "sg:classifiers":[
        {
            "category":"Building & Trades",
            "subcategory":"Construction",
            "type":"Services"
        }
    ],
    "sg:phone":"+61 416 084 587",
    "sg:postcode":"5013",
    "sg:province":"SA",
    "sg:tags":[
        "polishing",
        "sanding",
        "floor"
    ],
    "wof:name":"Ace Floor Sanding",
    "wof:placetype":"venue"
},
  "geometry": {"coordinates":[138.529495239,-34.8604316711],"type":"Point"}
}