{
  "type": "Feature",
  "properties": {
    "iso:country":"AU",
    "sg:address":"74 Waterview St",
    "sg:city":"Shelly Beach",
    "sg:classifiers":[
        {
            "category":"Home & Garden",
            "subcategory":"Carpets & Floor Coverings",
            "type":"Retail Goods"
        }
    ],
    "sg:phone":"+61 2 4334 7718",
    "sg:postcode":"2261",
    "sg:province":"NSW",
    "sg:tags":[
        "tile",
        "wall",
        "layer"
    ],
    "wof:name":"Duggan Michael",
    "wof:placetype":"venue"
},
  "geometry": {"coordinates":[151.487854,-33.366745],"type":"Point"}
}