{
  "type": "Feature",
  "properties": {
    "iso:country":"AU",
    "sg:address":"Lot 2 Rankins La",
    "sg:city":"Monegeetta",
    "sg:classifiers":[
        {
            "category":"Mining & Drilling",
            "type":"Manufacturing & Wholesale Goods"
        }
    ],
    "sg:phone":"+61 3 5429 6637",
    "sg:postcode":"3433",
    "sg:province":"VIC",
    "sg:tags":[
        "geologist"
    ],
    "wof:name":"Phipps Resources Pty Ltd",
    "wof:placetype":"venue"
},
  "geometry": {"coordinates":[144.771759033,-37.3932304382],"type":"Point"}
}