{
  "type": "Feature",
  "properties": {
    "addr:full":"18 Carrington St Guildford NSW 2161",
    "addr:housenumber":"18",
    "addr:postcode":"2161",
    "addr:street":"Carrington St",
    "iso:country":"AU",
    "sg:address":"18 Carrington St",
    "sg:city":"Guildford",
    "sg:classifiers":[
        {
            "category":"Autos & Motor Vehicles",
            "subcategory":"Fuel & Gas Station",
            "type":"Retail Goods"
        }
    ],
    "sg:phone":"+61 2 9632 8342",
    "sg:postcode":"2161",
    "sg:province":"NSW",
    "wof:name":"L P Motors Pty Ltd",
    "wof:placetype":"venue"
},
  "geometry": {"coordinates":[150.97848510700001,-33.8585853577],"type":"Point"}
}