{
  "type": "Feature",
  "properties": {
    "iso:country":"AU",
    "sg:address":"118 Bourbong St",
    "sg:city":"Bundaberg",
    "sg:classifiers":[
        {
            "category":"Manufacturing",
            "subcategory":"Jewelry",
            "type":"Manufacturing & Wholesale Goods"
        }
    ],
    "sg:phone":"+61 7 4153 6232",
    "sg:postcode":"4670",
    "sg:province":"QLD",
    "sg:tags":[
        "mfrg",
        "jeweller"
    ],
    "wof:name":"Riviera Classic Productions",
    "wof:placetype":"venue"
},
  "geometry": {"coordinates":[152.349517822,-24.8661212921],"type":"Point"}
}