{
  "type": "Feature",
  "properties": {
    "addr:full":"3 Wilson St Southport QLD 4215",
    "addr:housenumber":"3",
    "addr:postcode":"4215",
    "addr:street":"Wilson St",
    "iso:country":"AU",
    "sg:address":"3 Wilson St",
    "sg:city":"Southport",
    "sg:classifiers":[
        {
            "category":"Social Services",
            "type":"Services"
        }
    ],
    "sg:phone":"+61 7 5531 4980",
    "sg:postcode":"4215",
    "sg:province":"QLD",
    "sg:tags":[
        "disabled",
        "person",
        "equipment"
    ],
    "wof:name":"Seal - Tight Waterproofing",
    "wof:placetype":"venue"
},
  "geometry": {"coordinates":[153.39877319300001,-27.9557037354],"type":"Point"}
}