{
  "type": "Feature",
  "properties": {
    "addr:full":"71- 75 Francis St Narrabri NSW 2390",
    "addr:housenumber":"75",
    "addr:postcode":"2390",
    "addr:street":"Francis St",
    "iso:country":"AU",
    "sg:address":"71- 75 Francis St",
    "sg:city":"Narrabri",
    "sg:classifiers":[
        {
            "category":"Building & Trades",
            "subcategory":"Construction",
            "type":"Services"
        }
    ],
    "sg:phone":"+61 2 6792 3500",
    "sg:postcode":"2390",
    "sg:province":"NSW",
    "sg:tags":[
        "welding"
    ],
    "wof:name":"David Briggs Engineering Pty Ltd-Narrabri",
    "wof:placetype":"venue"
},
  "geometry": {"coordinates":[149.77952575699999,-30.312297821],"type":"Point"}
}