{
  "type": "Feature",
  "properties": {
    "addr:full":"166 Unley Rd Unley SA 5061",
    "addr:housenumber":"166",
    "addr:postcode":"5061",
    "addr:street":"Unley Rd",
    "iso:country":"AU",
    "sg:address":"166 Unley Rd",
    "sg:city":"Unley",
    "sg:classifiers":[
        {
            "category":"Restaurant",
            "type":"Food & Drink"
        }
    ],
    "sg:phone":"+61 8 8271 2815",
    "sg:postcode":"5061",
    "sg:province":"SA",
    "wof:name":"Barzaar",
    "wof:placetype":"venue"
},
  "geometry": {"coordinates":[138.607177734,-34.9492912292],"type":"Point"}
}