{
  "type": "Feature",
  "properties": {
    "addr:full":"10 Willawa St Balgowlah Heights NSW 2093",
    "addr:housenumber":"10",
    "addr:postcode":"2093",
    "addr:street":"Willawa St",
    "iso:country":"AU",
    "sg:address":"10 Willawa St",
    "sg:city":"Balgowlah Heights",
    "sg:classifiers":[
        {
            "category":"Personal",
            "type":"Services"
        }
    ],
    "sg:phone":"+61 404 883 236",
    "sg:postcode":"2093",
    "sg:province":"NSW",
    "sg:tags":[
        "career",
        "counselling"
    ],
    "wof:name":"Miles Joanna",
    "wof:placetype":"venue"
},
  "geometry": {"coordinates":[151.2631073,-33.8087425232],"type":"Point"}
}