{
  "type": "Feature",
  "properties": {
    "addr:full":"39 Cameron St Alice Springs NT 0870",
    "addr:housenumber":"39",
    "addr:postcode":"nt 0870",
    "addr:street":"Cameron St",
    "iso:country":"AU",
    "sg:address":"39 Cameron St",
    "sg:city":"Alice Springs",
    "sg:classifiers":[
        {
            "category":"Building & Trades",
            "subcategory":"Construction",
            "type":"Services"
        }
    ],
    "sg:phone":"+61 8 8952 6688",
    "sg:postcode":"0870",
    "sg:province":"NT",
    "sg:tags":[
        "road",
        "contractor"
    ],
    "wof:name":"Territory Roadmarking Auspray Pty Ltd",
    "wof:placetype":"venue"
},
  "geometry": {"coordinates":[133.8646698,-23.6709575653],"type":"Point"}
}