{
  "type": "Feature",
  "properties": {
    "iso:country":"AU",
    "sg:address":"12 Tanis St",
    "sg:city":"Eight Mile Plains",
    "sg:classifiers":[
        {
            "category":"Building & Trades",
            "subcategory":"Construction",
            "type":"Services"
        }
    ],
    "sg:phone":"+61 7 3341 9708",
    "sg:postcode":"4113",
    "sg:province":"QLD",
    "sg:tags":[
        "contractor"
    ],
    "wof:name":"Winch P O & P J",
    "wof:placetype":"venue"
},
  "geometry": {"coordinates":[153.08619689899999,-27.5801029205],"type":"Point"}
}