{
  "type": "Feature",
  "properties": {
    "addr:full":"193 Windang Rd Windang NSW 2528",
    "addr:housenumber":"193",
    "addr:postcode":"2528",
    "addr:street":"Windang Rd",
    "iso:country":"AU",
    "sg:address":"193 Windang Rd",
    "sg:city":"Windang",
    "sg:classifiers":[
        {
            "category":"Travel",
            "subcategory":"Hotels & Motels",
            "type":"Entertainment"
        }
    ],
    "sg:phone":"+61 2 4296 1565",
    "sg:postcode":"2528",
    "sg:province":"NSW",
    "sg:tags":[
        "accommodation"
    ],
    "wof:name":"Lake Illawarra Hotel",
    "wof:placetype":"venue"
},
  "geometry": {"coordinates":[150.86936950699999,-34.5292892456],"type":"Point"}
}