{
  "type": "Feature",
  "properties": {
    "iso:country":"AU",
    "sg:address":"27 Waratah Ave",
    "sg:city":"Selby",
    "sg:classifiers":[
        {
            "category":"Shopping",
            "subcategory":"Computers & Home Electronics",
            "type":"Retail Goods"
        }
    ],
    "sg:phone":"+61 3 9752 6411",
    "sg:postcode":"3159",
    "sg:province":"VIC",
    "sg:tags":[
        "equipment",
        "part",
        "electronic"
    ],
    "wof:name":"Phoenix Electronics",
    "wof:placetype":"venue"
},
  "geometry": {"coordinates":[145.36419677699999,-37.917881012],"type":"Point"}
}