{
  "type": "Feature",
  "properties": {
    "addr:full":"PO Box 268 Sans Souci NSW 2219",
    "addr:postcode":"2219",
    "iso:country":"AU",
    "sg:address":"PO Box 268",
    "sg:city":"Sans Souci",
    "sg:classifiers":[
        {
            "category":"Utilities",
            "type":"Services"
        }
    ],
    "sg:phone":"+61 408 203 002",
    "sg:postcode":"2219",
    "sg:province":"NSW",
    "sg:tags":[
        "refrigeration",
        "industrial",
        "commercial",
        "retail"
    ],
    "wof:name":"Aspen Refrigeration",
    "wof:placetype":"venue"
},
  "geometry": {"coordinates":[151.132172,-33.992779],"type":"Point"}
}