{
  "type": "Feature",
  "properties": {
    "addr:full":"46 Millrose Drv Malaga WA 6090",
    "addr:housenumber":"46",
    "addr:postcode":"6090",
    "addr:street":"Millrose Drv",
    "iso:country":"AU",
    "sg:address":"46 Millrose Drv",
    "sg:city":"Malaga",
    "sg:classifiers":[
        {
            "category":"Shopping",
            "subcategory":"Discount & Variety Stores",
            "type":"Retail Goods"
        }
    ],
    "sg:phone":"+61 8 9249 2944",
    "sg:postcode":"6090",
    "sg:province":"WA",
    "sg:tags":[
        "mixing",
        "equipment",
        "industrial"
    ],
    "wof:name":"Mixtec Philadelphia",
    "wof:placetype":"venue"
},
  "geometry": {"coordinates":[115.899131775,-31.8662128448],"type":"Point"}
}