{
  "type": "Feature",
  "properties": {
    "addr:full":"14 Dickersons La Denver VIC 3461",
    "addr:housenumber":"14",
    "addr:postcode":"3461",
    "addr:street":"Dickersons La",
    "iso:country":"AU",
    "sg:address":"14 Dickersons La",
    "sg:city":"Denver",
    "sg:classifiers":[
        {
            "category":"Building & Trades",
            "subcategory":"Plumbing",
            "type":"Services"
        }
    ],
    "sg:phone":"+61 418 195 965",
    "sg:postcode":"3461",
    "sg:province":"VIC",
    "sg:tags":[
        "plumber",
        "gasfitters"
    ],
    "wof:name":"Pagem. Services Pty Ltd",
    "wof:placetype":"venue"
},
  "geometry": {"coordinates":[144.29847717300001,-37.2757644653],"type":"Point"}
}