{
  "type": "Feature",
  "properties": {
    "iso:country":"AU",
    "sg:address":"18 Grosvenor St",
    "sg:city":"Neutral Bay",
    "sg:classifiers":[
        {
            "category":"Professional",
            "subcategory":"Art Services",
            "type":"Services"
        }
    ],
    "sg:phone":"+61 2 9953 9288",
    "sg:postcode":"2089",
    "sg:province":"NSW",
    "sg:tags":[
        "graphic",
        "designer"
    ],
    "wof:name":"Ys Communication Pty Ltd",
    "wof:placetype":"venue"
},
  "geometry": {"coordinates":[151.22093200699999,-33.8295898438],"type":"Point"}
}