{
  "type": "Feature",
  "properties": {
    "addr:full":"34 King Edward Rd Osborne Park WA 6017",
    "addr:housenumber":"34",
    "addr:postcode":"6017",
    "addr:street":"King Edward Rd",
    "iso:country":"AU",
    "sg:address":"34 King Edward Rd",
    "sg:city":"Osborne Park",
    "sg:classifiers":[
        {
            "category":"Manufacturing",
            "subcategory":"Motor Vehicles & Parts",
            "type":"Manufacturing & Wholesale Goods"
        }
    ],
    "sg:phone":"+61 8 9446 8888",
    "sg:postcode":"6017",
    "sg:province":"WA",
    "sg:tags":[
        "replacement"
    ],
    "wof:name":"Conventrys",
    "wof:placetype":"venue"
},
  "geometry": {"coordinates":[115.805130005,-31.9032039642],"type":"Point"}
}