{
  "type": "Feature",
  "properties": {
    "addr:full":"U9/ 47 Peninslua Drv Surfers Paradise QLD 4217",
    "addr:postcode":"4217",
    "addr:street":"U9 / 47 Peninslua Drv",
    "iso:country":"AU",
    "sg:address":"U9/ 47 Peninslua Drv",
    "sg:city":"Surfers Paradise",
    "sg:classifiers":[
        {
            "category":"Personal",
            "subcategory":"Massage",
            "type":"Services"
        }
    ],
    "sg:phone":"+61 422 132 590",
    "sg:postcode":"4217",
    "sg:province":"QLD",
    "sg:tags":[
        "therapy"
    ],
    "wof:name":"Andrea Hulena",
    "wof:placetype":"venue"
},
  "geometry": {"coordinates":[153.42440795900001,-28.0041751862],"type":"Point"}
}