{
  "type": "Feature",
  "properties": {
    "addr:full":"140 Pakington St Geelong West VIC 3218",
    "addr:housenumber":"140",
    "addr:postcode":"3218",
    "addr:street":"Pakington St",
    "iso:country":"AU",
    "sg:address":"140 Pakington St",
    "sg:city":"Geelong West",
    "sg:classifiers":[
        {
            "category":"Cafe",
            "type":"Food & Drink"
        }
    ],
    "sg:phone":"+61 3 5222 2889",
    "sg:postcode":"3218",
    "sg:province":"VIC",
    "wof:name":"Tarts on Pakington",
    "wof:placetype":"venue"
},
  "geometry": {"coordinates":[144.34863281200001,-38.1397819519],"type":"Point"}
}