{
  "type": "Feature",
  "properties": {
    "addr:full":"123 Margaret St Orange NSW 2800",
    "addr:housenumber":"123",
    "addr:postcode":"2800",
    "addr:street":"Margaret St",
    "iso:country":"AU",
    "sg:address":"123 Margaret St",
    "sg:city":"Orange",
    "sg:classifiers":[
        {
            "category":"Professional",
            "subcategory":"Computer Services",
            "type":"Services"
        }
    ],
    "sg:phone":"+61 2 5310 6005",
    "sg:postcode":"2800",
    "sg:province":"NSW",
    "sg:tags":[
        "repairs",
        "upgrade",
        "equipment"
    ],
    "wof:name":"Orange Computer Doctors",
    "wof:placetype":"venue"
},
  "geometry": {"coordinates":[149.098052978,-33.2705688477],"type":"Point"}
}