{
  "type": "Feature",
  "properties": {
    "addr:full":"Shp 123/ West Lakes Westfield West Lakes SA 5021",
    "addr:housenumber":"123 / west",
    "addr:postcode":"5021",
    "addr:street":"Lakes Westfield",
    "iso:country":"AU",
    "sg:address":"Shp 123/ West Lakes Westfield",
    "sg:city":"West Lakes",
    "sg:classifiers":[
        {
            "category":"Shopping",
            "subcategory":"Clothing, Apparel, & Fashions",
            "type":"Retail Goods"
        }
    ],
    "sg:phone":"+61 8 8355 4365",
    "sg:postcode":"5021",
    "sg:province":"SA",
    "sg:tags":[
        "jean"
    ],
    "wof:name":"Globalize",
    "wof:placetype":"venue"
},
  "geometry": {"coordinates":[138.501708984,-34.8476600647],"type":"Point"}
}