{
  "type": "Feature",
  "properties": {
    "iso:country":"AU",
    "sg:address":"10 Mackay St",
    "sg:city":"Port Augusta",
    "sg:classifiers":[
        {
            "category":"Real Estate",
            "subcategory":"Real Estate Agent",
            "type":"Services"
        }
    ],
    "sg:phone":"+61 8 8642 3322",
    "sg:postcode":"5700",
    "sg:province":"SA",
    "wof:name":"Century 21 Myles Pearce (Port Augusta)",
    "wof:placetype":"venue"
},
  "geometry": {"coordinates":[137.764602661,-32.4903144836],"type":"Point"}
}