{
  "type": "Feature",
  "properties": {
    "addr:full":"192 Holt Pde Thomastown VIC 3074",
    "addr:housenumber":"192",
    "addr:postcode":"3074",
    "addr:street":"Holt Pde",
    "iso:country":"AU",
    "sg:address":"192 Holt Pde",
    "sg:city":"Thomastown",
    "sg:classifiers":[
        {
            "category":"Ice Cream",
            "type":"Food & Drink"
        }
    ],
    "sg:phone":"+61 3 9464 3811",
    "sg:postcode":"3074",
    "sg:province":"VIC",
    "sg:tags":[
        "specialised",
        "fitting",
        "lady",
        "wear"
    ],
    "wof:name":"Stock City Australia Pty Ltd",
    "wof:placetype":"venue"
},
  "geometry": {"coordinates":[145.030593872,-37.6960906982],"type":"Point"}
}