{
  "type": "Feature",
  "properties": {
    "addr:full":"PO Box 243 Calliope QLD 4680",
    "addr:postcode":"4680",
    "iso:country":"AU",
    "sg:address":"PO Box 243",
    "sg:city":"Calliope",
    "sg:classifiers":[
        {
            "category":"Building & Trades",
            "subcategory":"Landscaping Services",
            "type":"Services"
        }
    ],
    "sg:phone":"+61 7 4975 7745",
    "sg:postcode":"4680",
    "sg:province":"QLD",
    "sg:tags":[
        "slashing",
        "contractor"
    ],
    "wof:name":"Gladstone Slashing",
    "wof:placetype":"venue"
},
  "geometry": {"coordinates":[151.21209716800001,-23.9871997833],"type":"Point"}
}