{
  "type": "Feature",
  "properties": {
    "addr:full":"Crisparkle Drv Ambarvale NSW 2560",
    "addr:postcode":"2560",
    "addr:street":"Crisparkle Drv",
    "iso:country":"AU",
    "sg:address":"Crisparkle Drv",
    "sg:city":"Ambarvale",
    "sg:classifiers":[
        {
            "category":"Social Services",
            "subcategory":"Child Care",
            "type":"Services"
        }
    ],
    "sg:phone":"+61 2 4628 1674",
    "sg:postcode":"2560",
    "sg:province":"NSW",
    "wof:name":"Amber Cottage Child Care Centre",
    "wof:placetype":"venue"
},
  "geometry": {"coordinates":[150.79142761200001,-34.0872116089],"type":"Point"}
}