{
  "type": "Feature",
  "properties": {
    "addr:full":"270 McLennan St Mooroopna VIC 3629",
    "addr:housenumber":"270",
    "addr:postcode":"3629",
    "addr:street":"Mclennan St",
    "iso:country":"AU",
    "sg:address":"270 McLennan St",
    "sg:city":"Mooroopna",
    "sg:classifiers":[
        {
            "category":"Professional",
            "type":"Services"
        }
    ],
    "sg:phone":"+61 3 5825 3077",
    "sg:postcode":"3629",
    "sg:province":"VIC",
    "sg:tags":[
        "transport"
    ],
    "wof:name":"Jayway Industries",
    "wof:placetype":"venue"
},
  "geometry": {"coordinates":[145.33972168,-36.3971061707],"type":"Point"}
}