{
  "type": "Feature",
  "properties": {
    "addr:full":"Level 2, Block F, Brisbane Market Sherwood Rd Rocklea QLD 4106",
    "addr:housenumber":"block f",
    "addr:postcode":"4106",
    "addr:street":"Market Sherwood Rd",
    "iso:country":"AU",
    "sg:address":"Level 2, Block F, Brisbane Market Sherwood Rd",
    "sg:city":"Rocklea",
    "sg:classifiers":[
        {
            "category":"Home & Garden",
            "subcategory":"Carpets & Floor Coverings",
            "type":"Retail Goods"
        }
    ],
    "sg:phone":"+61 7 3278 4786",
    "sg:postcode":"4106",
    "sg:province":"QLD",
    "sg:tags":[
        "banana",
        "grower"
    ],
    "wof:name":"Australian Banana Growers' Council Inc",
    "wof:placetype":"venue"
},
  "geometry": {"coordinates":[152.999343872,-27.5341892242],"type":"Point"}
}