{
  "type": "Feature",
  "properties": {
    "addr:full":"Cnr High St & Oakover Rd Preston VIC 3072",
    "addr:postcode":"3072",
    "addr:street":"High St & Oakover Rd",
    "iso:country":"AU",
    "sg:address":"Cnr High St & Oakover Rd",
    "sg:city":"Preston",
    "sg:classifiers":[
        {
            "category":"Retail",
            "subcategory":"Event Space",
            "type":"Services"
        }
    ],
    "sg:phone":"+61 3 9480 4266",
    "sg:postcode":"3072",
    "sg:province":"VIC",
    "sg:tags":[
        "venue",
        "reception",
        "wedding"
    ],
    "wof:name":"Oakville Receptions",
    "wof:placetype":"venue"
},
  "geometry": {"coordinates":[145.003540039,-37.740814209],"type":"Point"}
}