{
  "type": "Feature",
  "properties": {
    "addr:full":"29 Michael St North Richmond NSW 2754",
    "addr:housenumber":"29",
    "addr:postcode":"2754",
    "addr:street":"Michael St",
    "iso:country":"AU",
    "sg:address":"29 Michael St",
    "sg:city":"North Richmond",
    "sg:classifiers":[
        {
            "category":"Banks & Credit Unions",
            "subcategory":"Financial Services",
            "type":"Services"
        }
    ],
    "sg:phone":"+61 2 4571 1512",
    "sg:postcode":"2754",
    "sg:province":"NSW",
    "sg:tags":[
        "surge",
        "protection",
        "lightning"
    ],
    "wof:name":"Malbec Electrics",
    "wof:placetype":"venue"
},
  "geometry": {"coordinates":[150.70967102,-33.5839729309],"type":"Point"}
}