{
  "type": "Feature",
  "properties": {
    "addr:full":"376 South Pine Rd Everton Park QLD 4053",
    "addr:housenumber":"376",
    "addr:postcode":"4053",
    "addr:street":"South Pine Rd",
    "iso:country":"AU",
    "sg:address":"376 South Pine Rd",
    "sg:city":"Everton Park",
    "sg:classifiers":[
        {
            "category":"Health Services",
            "subcategory":"Health Practitioner",
            "type":"Services"
        }
    ],
    "sg:phone":"+61 7 3864 3617",
    "sg:postcode":"4053",
    "sg:province":"QLD",
    "sg:tags":[
        "hypnotherapy"
    ],
    "wof:name":"Dillon P",
    "wof:placetype":"venue"
},
  "geometry": {"coordinates":[152.97019958499999,-27.3912773132],"type":"Point"}
}