{
  "type": "Feature",
  "properties": {
    "addr:full":"33 Walters Drv Osborne Park WA 6017",
    "addr:housenumber":"33",
    "addr:postcode":"6017",
    "addr:street":"Walters Drv",
    "iso:country":"AU",
    "sg:address":"33 Walters Drv",
    "sg:city":"Osborne Park",
    "sg:classifiers":[
        {
            "category":"Real Estate",
            "subcategory":"Real Estate Agent",
            "type":"Services"
        }
    ],
    "sg:phone":"+61 8 9244 9182",
    "sg:postcode":"6017",
    "sg:province":"WA",
    "wof:name":"Ray White Special Projects",
    "wof:placetype":"venue"
},
  "geometry": {"coordinates":[115.810409546,-31.9100017548],"type":"Point"}
}