{
  "type": "Feature",
  "properties": {
    "iso:country":"AU",
    "sg:address":"Findlay Ave",
    "sg:city":"Port Macquarie",
    "sg:classifiers":[
        {
            "category":"Building & Trades",
            "subcategory":"Landscaping Services",
            "type":"Services"
        }
    ],
    "sg:phone":"+61 418 654 401",
    "sg:postcode":"2444",
    "sg:province":"NSW",
    "sg:tags":[
        "market"
    ],
    "wof:name":"Port Macquarie Markets",
    "wof:placetype":"venue"
},
  "geometry": {"coordinates":[152.896011,-31.433447],"type":"Point"}
}