{
  "type": "Feature",
  "properties": {
    "iso:country":"AU",
    "sg:address":"Shop 25-26 Lismore Shopping Square+ Uralba St",
    "sg:city":"Lismore",
    "sg:classifiers":[
        {
            "category":"Shopping",
            "subcategory":"Shoes",
            "type":"Retail Goods"
        }
    ],
    "sg:phone":"+61 2 6621 4506",
    "sg:postcode":"2480",
    "sg:province":"NSW",
    "sg:tags":[
        "footwear"
    ],
    "wof:name":"Mathers Shoes",
    "wof:placetype":"venue"
},
  "geometry": {"coordinates":[153.28341674800001,-28.8090324402],"type":"Point"}
}