{
  "type": "Feature",
  "properties": {
    "iso:country":"AU",
    "sg:address":"Berkshire Valley Rd",
    "sg:city":"Moora",
    "sg:classifiers":[
        {
            "category":"Farming",
            "subcategory":"Farm & Veterinary Services",
            "type":"Manufacturing & Wholesale Goods"
        }
    ],
    "sg:phone":"+61 8 9651 1069",
    "sg:postcode":"6510",
    "sg:province":"WA",
    "sg:tags":[
        "seedsman"
    ],
    "wof:name":"Moora Seed Works",
    "wof:placetype":"venue"
},
  "geometry": {"coordinates":[116.009598,-30.638844],"type":"Point"}
}