{
  "type": "Feature",
  "properties": {
    "addr:full":"36- 38 Curlewis St Swan Hill NSW 3585",
    "addr:housenumber":"38",
    "addr:postcode":"3585",
    "addr:street":"Curlewis St",
    "iso:country":"AU",
    "sg:address":"36- 38 Curlewis St",
    "sg:city":"Swan Hill",
    "sg:classifiers":[
        {
            "category":"Transit Center",
            "subcategory":"Freight",
            "type":"Transportation"
        }
    ],
    "sg:phone":"+61 1300 255 367",
    "sg:postcode":"3585",
    "sg:province":"NSW",
    "sg:tags":[
        "forklift",
        "truck"
    ],
    "wof:name":"Allforks Aust P/L",
    "wof:placetype":"venue"
},
  "geometry": {"coordinates":[143.55645799999999,-35.330723],"type":"Point"}
}