{
  "type": "Feature",
  "properties": {
    "addr:full":"175 Great North Rd Five Dock NSW 2046",
    "addr:housenumber":"175",
    "addr:postcode":"2046",
    "addr:street":"Great North Rd",
    "iso:country":"AU",
    "sg:address":"175 Great North Rd",
    "sg:city":"Five Dock",
    "sg:classifiers":[
        {
            "category":"Arts & Performance",
            "subcategory":"Dance",
            "type":"Entertainment"
        }
    ],
    "sg:phone":"+61 2 9712 4274",
    "sg:postcode":"2046",
    "sg:province":"NSW",
    "sg:tags":[
        "theatrical",
        "ballet",
        "tuition"
    ],
    "wof:name":"RGDANCE.COM",
    "wof:placetype":"venue"
},
  "geometry": {"coordinates":[151.129898,-33.866741],"type":"Point"}
}