{
  "type": "Feature",
  "properties": {
    "addr:full":"Floor 1/ 74 Burwood Rd Burwood NSW 2134",
    "addr:housenumber":"/ 74",
    "addr:postcode":"2134",
    "addr:street":"Burwood Rd",
    "iso:country":"AU",
    "sg:address":"Floor 1/ 74 Burwood Rd",
    "sg:city":"Burwood",
    "sg:classifiers":[
        {
            "category":"Banks & Credit Unions",
            "subcategory":"Bank",
            "type":"Services"
        }
    ],
    "sg:phone":"+61 2 8741 0344",
    "sg:postcode":"2134",
    "sg:province":"NSW",
    "wof:name":"Mercantile Lending",
    "wof:placetype":"venue"
},
  "geometry": {"coordinates":[151.104736328,-33.8729286194],"type":"Point"}
}