{
  "type": "Feature",
  "properties": {
    "addr:full":"PO Box 3468 North Mackay QLD 4740",
    "addr:postcode":"4740",
    "iso:country":"AU",
    "sg:address":"PO Box 3468",
    "sg:city":"North Mackay",
    "sg:classifiers":[
        {
            "category":"Building & Trades",
            "subcategory":"Construction",
            "type":"Services"
        }
    ],
    "sg:phone":"+61 409 266 828",
    "sg:postcode":"4740",
    "sg:province":"QLD",
    "sg:tags":[
        "contractor"
    ],
    "wof:name":"Beachside Building",
    "wof:placetype":"venue"
},
  "geometry": {"coordinates":[149.18963600000001,-21.120611],"type":"Point"}
}