{
  "type": "Feature",
  "properties": {
    "addr:full":"878 Whitehorse Rd Box Hill VIC 3128",
    "addr:housenumber":"878",
    "addr:postcode":"3128",
    "addr:street":"Whitehorse Rd",
    "iso:country":"AU",
    "sg:address":"878 Whitehorse Rd",
    "sg:city":"Box Hill",
    "sg:classifiers":[
        {
            "category":"Communications",
            "type":"Services"
        }
    ],
    "sg:phone":"+61 402 388 967",
    "sg:postcode":"3128",
    "sg:province":"VIC",
    "sg:tags":[
        "equipment",
        "satellite"
    ],
    "wof:name":"Star Vision Satelite System",
    "wof:placetype":"venue"
},
  "geometry": {"coordinates":[145.12130737300001,-37.8180770874],"type":"Point"}
}