{
  "type": "Feature",
  "properties": {
    "addr:full":"597 Anzac Hwy Glenelg SA 5045",
    "addr:housenumber":"597",
    "addr:postcode":"5045",
    "addr:street":"Anzac Hwy",
    "iso:country":"AU",
    "sg:address":"597 Anzac Hwy",
    "sg:city":"Glenelg",
    "sg:classifiers":[
        {
            "category":"Retail",
            "subcategory":"Veterinary Services",
            "type":"Services"
        }
    ],
    "sg:phone":"+61 8 8295 1312",
    "sg:postcode":"5045",
    "sg:province":"SA",
    "sg:tags":[
        "surgeon"
    ],
    "wof:name":"Glenelg Veterinary Clinic",
    "wof:placetype":"venue"
},
  "geometry": {"coordinates":[138.51828,-34.976177],"type":"Point"}
}