{
  "type": "Feature",
  "properties": {
    "addr:full":"Suite 2 & 3, 49 Kiora Rd Miranda NSW 2228",
    "addr:housenumber":"&;49",
    "addr:postcode":"2228",
    "addr:street":"3;Kiora Rd",
    "iso:country":"AU",
    "sg:address":"Suite 2 & 3, 49 Kiora Rd",
    "sg:city":"Miranda",
    "sg:classifiers":[
        {
            "category":"Health Services",
            "subcategory":"Dentist",
            "type":"Services"
        }
    ],
    "sg:phone":"+61 2 9531 4888",
    "sg:postcode":"2228",
    "sg:province":"NSW",
    "wof:name":"Tsetong Blanche Dr",
    "wof:placetype":"venue"
},
  "geometry": {"coordinates":[151.10194397000001,-34.0349388123],"type":"Point"}
}