{
  "type": "Feature",
  "properties": {
    "iso:country":"AU",
    "sg:address":"82 Enmore Rd",
    "sg:city":"Newtown",
    "sg:classifiers":[
        {
            "category":"Shopping",
            "subcategory":"Discount & Variety Stores",
            "type":"Retail Goods"
        }
    ],
    "sg:phone":"+61 2 9517 4500",
    "sg:postcode":"2042",
    "sg:province":"NSW",
    "sg:tags":[
        "shop",
        "adult"
    ],
    "wof:name":"Reactor Rubber Wear",
    "wof:placetype":"venue"
},
  "geometry": {"coordinates":[151.17503400000001,-33.898808],"type":"Point"}
}