{
  "type": "Feature",
  "properties": {
    "addr:full":"Newburn Rd High Wycombe WA 6057",
    "addr:postcode":"6057",
    "addr:street":"Newburn Rd",
    "iso:country":"AU",
    "sg:address":"Newburn Rd",
    "sg:city":"High Wycombe",
    "sg:classifiers":[
        {
            "category":"Education",
            "subcategory":"School",
            "type":"Public Place"
        }
    ],
    "sg:phone":"+61 8 9454 5280",
    "sg:postcode":"6057",
    "sg:province":"WA",
    "sg:tags":[
        "state",
        "except",
        "nsw"
    ],
    "wof:name":"High Wycombe Primary",
    "wof:placetype":"venue"
},
  "geometry": {"coordinates":[116.005981445,-31.9369258881],"type":"Point"}
}