{
  "type": "Feature",
  "properties": {
    "addr:full":"Unit 8, 120- 126 Taren Point Rd Taren Point NSW 2229",
    "addr:housenumber":"120 126",
    "addr:postcode":"2229",
    "addr:street":"Taren Point Rd",
    "iso:country":"AU",
    "sg:address":"Unit 8, 120- 126 Taren Point Rd",
    "sg:city":"Taren Point",
    "sg:classifiers":[
        {
            "category":"Shopping",
            "subcategory":"Party Supplies",
            "type":"Retail Goods"
        }
    ],
    "sg:phone":"+61 2 9526 6811",
    "sg:postcode":"2229",
    "sg:province":"NSW",
    "sg:tags":[
        "children's"
    ],
    "wof:name":"Funz Play City",
    "wof:placetype":"venue"
},
  "geometry": {"coordinates":[151.121826172,-34.0204048157],"type":"Point"}
}