{
  "type": "Feature",
  "properties": {
    "iso:country":"AU",
    "sg:address":"145 Darling St",
    "sg:city":"Balmain",
    "sg:classifiers":[
        {
            "category":"Arts & Performance",
            "subcategory":"Theater",
            "type":"Entertainment"
        }
    ],
    "sg:phone":"+61 2 9352 3313",
    "sg:postcode":"2041",
    "sg:province":"NSW",
    "sg:tags":[
        "agency",
        "booking",
        "theatre"
    ],
    "wof:name":"Visa Preferred Seating",
    "wof:placetype":"venue"
},
  "geometry": {"coordinates":[151.188049,-33.858013],"type":"Point"}
}