{
  "type": "Feature",
  "properties": {
    "addr:full":"30 Crown St Crookwell NSW 2583",
    "addr:housenumber":"30",
    "addr:postcode":"2583",
    "addr:street":"Crown St",
    "iso:country":"AU",
    "sg:address":"30 Crown St",
    "sg:city":"Crookwell",
    "sg:classifiers":[
        {
            "category":"Professional",
            "subcategory":"Accounting & Tax Preparation",
            "type":"Services"
        }
    ],
    "sg:phone":"+61 427 106 580",
    "sg:postcode":"2583",
    "sg:province":"NSW",
    "sg:tags":[
        "bookkeeping"
    ],
    "wof:name":"DHM Bookkeeping Services",
    "wof:placetype":"venue"
},
  "geometry": {"coordinates":[149.46343994099999,-34.451007843],"type":"Point"}
}