{
  "type": "Feature",
  "properties": {
    "addr:full":"122 Sturt St Townsville QLD 4810",
    "addr:housenumber":"122",
    "addr:postcode":"4810",
    "addr:street":"Sturt St",
    "iso:country":"AU",
    "sg:address":"122 Sturt St",
    "sg:city":"Townsville",
    "sg:classifiers":[
        {
            "category":"Retail",
            "subcategory":"Event Space",
            "type":"Services"
        }
    ],
    "sg:phone":"+61 7 4771 3074",
    "sg:postcode":"4810",
    "sg:province":"QLD",
    "sg:tags":[
        "tab's"
    ],
    "wof:name":"T.A.B.",
    "wof:placetype":"venue"
},
  "geometry": {"coordinates":[146.81419399999999,-19.261385],"type":"Point"}
}