{
  "type": "Feature",
  "properties": {
    "addr:full":"12 Lewis St Geraldton WA 6530",
    "addr:housenumber":"12",
    "addr:postcode":"6530",
    "addr:street":"Lewis St",
    "iso:country":"AU",
    "sg:address":"12 Lewis St",
    "sg:city":"Geraldton",
    "sg:classifiers":[
        {
            "category":"Taxi",
            "type":"Transportation"
        }
    ],
    "sg:phone":"+61 13 10 08",
    "sg:postcode":"6530",
    "sg:province":"WA",
    "sg:tags":[
        "cab"
    ],
    "wof:name":"Geraldton Associated Taxis",
    "wof:placetype":"venue"
},
  "geometry": {"coordinates":[114.61528015099999,-28.7699222565],"type":"Point"}
}