{
  "type": "Feature",
  "properties": {
    "addr:full":"6/ 492 Christine Ave Robina QLD 4226",
    "addr:housenumber":"/ 492",
    "addr:postcode":"4226",
    "addr:street":"Christine Ave",
    "iso:country":"AU",
    "sg:address":"6/ 492 Christine Ave",
    "sg:city":"Robina",
    "sg:classifiers":[
        {
            "category":"Professional",
            "subcategory":"Accounting & Tax Preparation",
            "type":"Services"
        }
    ],
    "sg:phone":"+61 7 5593 2499",
    "sg:postcode":"4226",
    "sg:province":"QLD",
    "sg:tags":[
        "consultant",
        "taxation"
    ],
    "wof:name":"Box Noel",
    "wof:placetype":"venue"
},
  "geometry": {"coordinates":[153.394165039,-28.0847816467],"type":"Point"}
}