{
  "type": "Feature",
  "properties": {
    "addr:full":"PO Box 72 Kairi QLD 4872",
    "addr:postcode":"4872",
    "iso:country":"AU",
    "sg:address":"PO Box 72",
    "sg:city":"Kairi",
    "sg:classifiers":[
        {
            "category":"Building & Trades",
            "subcategory":"Construction",
            "type":"Services"
        }
    ],
    "sg:phone":"+61 7 4059 8778",
    "sg:postcode":"4872",
    "sg:province":"QLD",
    "sg:tags":[
        "contractor"
    ],
    "wof:name":"Bob The Builder",
    "wof:placetype":"venue"
},
  "geometry": {"coordinates":[145.54374694800001,-17.2151298523],"type":"Point"}
}