{
  "type": "Feature",
  "properties": {
    "iso:country":"AU",
    "sg:address":"1/ 19 Carlingford Rd",
    "sg:city":"Epping",
    "sg:classifiers":[
        {
            "category":"Health Services",
            "subcategory":"Health Practitioner",
            "type":"Services"
        }
    ],
    "sg:phone":"+61 2 9876 3415",
    "sg:postcode":"2121",
    "sg:province":"NSW",
    "sg:tags":[
        "psychologist"
    ],
    "wof:name":"Kennett Barbara",
    "wof:placetype":"venue"
},
  "geometry": {"coordinates":[151.07786560100001,-33.771774292],"type":"Point"}
}