{
  "type": "Feature",
  "properties": {
    "addr:full":"Shp2/ 2237 Gold Coast Hwy Mermaid Beach QLD 4218",
    "addr:housenumber":"2237",
    "addr:postcode":"4218",
    "addr:street":"Gold Coast Hwy",
    "iso:country":"AU",
    "sg:address":"Shp2/ 2237 Gold Coast Hwy",
    "sg:city":"Mermaid Beach",
    "sg:classifiers":[
        {
            "category":"Real Estate",
            "subcategory":"Real Estate Agent",
            "type":"Services"
        }
    ],
    "sg:phone":"+61 7 5527 7599",
    "sg:postcode":"4218",
    "sg:province":"QLD",
    "wof:name":"Raine & Horne - Mermaid/Kae Beadman",
    "wof:placetype":"venue"
},
  "geometry": {"coordinates":[153.438598633,-28.0588264465],"type":"Point"}
}