{
  "type": "Feature",
  "properties": {
    "addr:full":"215 North Rd Caulfield South VIC 3162",
    "addr:housenumber":"215",
    "addr:postcode":"3162",
    "addr:street":"North Rd",
    "iso:country":"AU",
    "sg:address":"215 North Rd",
    "sg:city":"Caulfield South",
    "sg:classifiers":[
        {
            "category":"Building & Trades",
            "subcategory":"Construction",
            "type":"Services"
        }
    ],
    "sg:phone":"+61 3 9596 1426",
    "sg:postcode":"3162",
    "sg:province":"VIC",
    "sg:tags":[
        "joiner",
        "carpenter"
    ],
    "wof:name":"O&#039;Connell P H & A",
    "wof:placetype":"venue"
},
  "geometry": {"coordinates":[145.014129639,-37.9005966187],"type":"Point"}
}