{
  "type": "Feature",
  "properties": {
    "addr:full":"21 Boundary Rd Thornlands QLD 4164",
    "addr:housenumber":"21",
    "addr:postcode":"4164",
    "addr:street":"Boundary Rd",
    "iso:country":"AU",
    "sg:address":"21 Boundary Rd",
    "sg:city":"Thornlands",
    "sg:classifiers":[
        {
            "category":"Home & Garden",
            "subcategory":"Garden Supply",
            "type":"Retail Goods"
        }
    ],
    "sg:phone":"+61 7 3206 0888",
    "sg:postcode":"4164",
    "sg:province":"QLD",
    "sg:tags":[
        "equipment"
    ],
    "wof:name":"Rainforest Seclusion",
    "wof:placetype":"venue"
},
  "geometry": {"coordinates":[153.27207946799999,-27.576789856],"type":"Point"}
}