{
  "type": "Feature",
  "properties": {
    "addr:full":"405 Princes Hwy Narre Warren VIC 3805",
    "addr:housenumber":"405",
    "addr:postcode":"3805",
    "addr:street":"Princes Hwy",
    "iso:country":"AU",
    "sg:address":"405 Princes Hwy",
    "sg:city":"Narre Warren",
    "sg:classifiers":[
        {
            "category":"Health Services",
            "subcategory":"Doctor",
            "type":"Services"
        }
    ],
    "sg:phone":"+61 3 9704 7244",
    "sg:postcode":"3805",
    "sg:province":"VIC",
    "sg:tags":[
        "medical",
        "practitioner"
    ],
    "wof:name":"Micrey Medical Centre",
    "wof:placetype":"venue"
},
  "geometry": {"coordinates":[145.29885899999999,-38.021172],"type":"Point"}
}