{
  "type": "Feature",
  "properties": {
    "addr:full":"Boyd St Tugun QLD 4224",
    "addr:postcode":"4224",
    "addr:street":"Boyd St",
    "iso:country":"AU",
    "sg:address":"Boyd St",
    "sg:city":"Tugun",
    "sg:classifiers":[
        {
            "category":"Utilities",
            "subcategory":"Recycling",
            "type":"Services"
        }
    ],
    "sg:phone":"+61 419 739 764",
    "sg:postcode":"4224",
    "sg:province":"QLD",
    "wof:name":"Flano's Recycling",
    "wof:placetype":"venue"
},
  "geometry": {"coordinates":[153.49902343799999,-28.1515522003],"type":"Point"}
}