{
  "type": "Feature",
  "properties": {
    "addr:full":"Unit 1 & 2, 20 Northumberland Rd Taren Point NSW 2229",
    "addr:housenumber":"&;20",
    "addr:postcode":"2229",
    "addr:street":"Northumberland Rd",
    "iso:country":"AU",
    "sg:address":"Unit 1 & 2, 20 Northumberland Rd",
    "sg:city":"Taren Point",
    "sg:classifiers":[
        {
            "category":"Professional",
            "subcategory":"Employment Agencies",
            "type":"Services"
        }
    ],
    "sg:phone":"+61 2 8536 7555",
    "sg:postcode":"2229",
    "sg:province":"NSW",
    "sg:tags":[
        "broker",
        "custom"
    ],
    "wof:name":"Commercial Freight & Logistics Pty Ltd",
    "wof:placetype":"venue"
},
  "geometry": {"coordinates":[151.13177490199999,-34.0295372009],"type":"Point"}
}