{
  "type": "Feature",
  "properties": {
    "addr:full":"3 Crimp Crs Leschenault WA 6230",
    "addr:housenumber":"3",
    "addr:postcode":"6230",
    "addr:street":"Crimp Crs",
    "iso:country":"AU",
    "sg:address":"3 Crimp Crs",
    "sg:city":"Leschenault",
    "sg:classifiers":[
        {
            "category":"Organizations",
            "subcategory":"Membership Organization",
            "type":"Services"
        }
    ],
    "sg:phone":"+61 8 9725 9389",
    "sg:postcode":"6230",
    "sg:province":"WA",
    "sg:tags":[
        "club",
        "car"
    ],
    "wof:name":"Southwest Touring Car Club (Inc)",
    "wof:placetype":"venue"
},
  "geometry": {"coordinates":[115.66783100000001,-33.331493],"type":"Point"}
}