{
  "type": "Feature",
  "properties": {
    "addr:full":"Kinnairds Rd Numurkah VIC 3636",
    "addr:postcode":"3636",
    "addr:street":"Kinnairds Rd",
    "iso:country":"AU",
    "sg:address":"Kinnairds Rd",
    "sg:city":"Numurkah",
    "sg:classifiers":[
        {
            "category":"Farming",
            "subcategory":"Dairy Farm",
            "type":"Manufacturing & Wholesale Goods"
        }
    ],
    "sg:phone":"+61 3 5862 3463",
    "sg:postcode":"3636",
    "sg:province":"VIC",
    "wof:name":"Murray Park Dairy Pty Ltd",
    "wof:placetype":"venue"
},
  "geometry": {"coordinates":[145.45916748100001,-36.0865821838],"type":"Point"}
}