{
  "type": "Feature",
  "properties": {
    "addr:full":"5 Archimedes St Darra QLD 4076",
    "addr:housenumber":"5",
    "addr:postcode":"4076",
    "addr:street":"Archimedes St",
    "iso:country":"AU",
    "sg:address":"5 Archimedes St",
    "sg:city":"Darra",
    "sg:phone":"+61 7 3879 1511",
    "sg:postcode":"4076",
    "sg:province":"QLD",
    "wof:name":"ACE Pty Ltd",
    "wof:placetype":"venue"
},
  "geometry": {"coordinates":[152.952224731,-27.5755767822],"type":"Point"}
}