{
  "type": "Feature",
  "properties": {
    "addr:full":"6 Kelso Pl Wantirna VIC 3152",
    "addr:housenumber":"6",
    "addr:postcode":"3152",
    "addr:street":"Kelso Pl",
    "iso:country":"AU",
    "sg:address":"6 Kelso Pl",
    "sg:city":"Wantirna",
    "sg:classifiers":[
        {
            "category":"Building & Trades",
            "subcategory":"Plumbing",
            "type":"Services"
        }
    ],
    "sg:phone":"+61 425 733 724",
    "sg:postcode":"3152",
    "sg:province":"VIC",
    "sg:tags":[
        "plumber",
        "gasfitters"
    ],
    "wof:name":"Stephen Calder",
    "wof:placetype":"venue"
},
  "geometry": {"coordinates":[145.23939514200001,-37.8476257324],"type":"Point"}
}