{
  "type": "Feature",
  "properties": {
    "addr:full":"130 Long Rd \"Gallery Walk\" Tamborine Mountain QLD 4272",
    "addr:housenumber":"130",
    "addr:postcode":"4272",
    "addr:street":"Long Rd",
    "iso:country":"AU",
    "sg:address":"130 Long Rd \"Gallery Walk\"",
    "sg:city":"Tamborine Mountain",
    "sg:classifiers":[
        {
            "category":"Arts & Performance",
            "subcategory":"Art Gallery",
            "type":"Entertainment"
        }
    ],
    "sg:phone":"+61 7 5545 1873",
    "sg:postcode":"4272",
    "sg:province":"QLD",
    "wof:name":"Vallard House Art Gallery",
    "wof:placetype":"venue"
},
  "geometry": {"coordinates":[153.184616089,-27.9589214325],"type":"Point"}
}