{
  "type": "Feature",
  "properties": {
    "iso:country":"AU",
    "sg:address":"570 Smithfield Rd",
    "sg:city":"Greenfield Park",
    "sg:classifiers":[
        {
            "category":"Health Services",
            "subcategory":"Health Practitioner",
            "type":"Services"
        }
    ],
    "sg:phone":"+61 2 9610 1497",
    "sg:postcode":"2176",
    "sg:province":"NSW",
    "sg:tags":[
        "physiotherapist"
    ],
    "wof:name":"Weinzettel Andrew",
    "wof:placetype":"venue"
},
  "geometry": {"coordinates":[150.88789367699999,-33.8824043274],"type":"Point"}
}