{
  "type": "Feature",
  "properties": {
    "addr:full":"615 Wisemans Ferry Rd Gunderman NSW 2775",
    "addr:housenumber":"615",
    "addr:postcode":"2775",
    "addr:street":"Wisemans Ferry Rd",
    "iso:country":"AU",
    "sg:address":"615 Wisemans Ferry Rd",
    "sg:city":"Gunderman",
    "sg:classifiers":[
        {
            "category":"Cafe",
            "type":"Food & Drink"
        }
    ],
    "sg:phone":"+61 2 4566 3331",
    "sg:postcode":"2775",
    "sg:province":"NSW",
    "wof:name":"Wombat Cafe",
    "wof:placetype":"venue"
},
  "geometry": {"coordinates":[151.03440856899999,-33.4212188721],"type":"Point"}
}