{
  "type": "Feature",
  "properties": {
    "addr:full":"Shp3, 922 Howitt St Wendouree VIC 3355",
    "addr:housenumber":"922",
    "addr:postcode":"3355",
    "addr:street":"Howitt St",
    "iso:country":"AU",
    "sg:address":"Shp3, 922 Howitt St",
    "sg:city":"Wendouree",
    "sg:classifiers":[
        {
            "category":"Personal",
            "subcategory":"Beauty Salon",
            "type":"Services"
        }
    ],
    "sg:phone":"+61 3 5339 6446",
    "sg:postcode":"3355",
    "sg:province":"VIC",
    "sg:tags":[
        "hairdresser"
    ],
    "wof:name":"The Stag Salon",
    "wof:placetype":"venue"
},
  "geometry": {"coordinates":[143.84063699999999,-37.541084],"type":"Point"}
}