{
  "type": "Feature",
  "properties": {
    "addr:full":"335- 339 Point Nepean Rd Dromana VIC 3936",
    "addr:housenumber":"339",
    "addr:postcode":"3936",
    "addr:street":"Point Nepean Rd",
    "iso:country":"AU",
    "sg:address":"335- 339 Point Nepean Rd",
    "sg:city":"Dromana",
    "sg:classifiers":[
        {
            "category":"Autos & Motor Vehicles",
            "subcategory":"Fuel & Gas Station",
            "type":"Retail Goods"
        }
    ],
    "sg:phone":"+61 3 5987 0666",
    "sg:postcode":"3936",
    "sg:province":"VIC",
    "wof:name":"Fuel City - Dromana",
    "wof:placetype":"venue"
},
  "geometry": {"coordinates":[144.95967102,-38.3353118896],"type":"Point"}
}