{
  "type": "Feature",
  "properties": {
    "addr:full":"9/ 44 Hampden Ave East Wahroonga NSW 2076",
    "addr:housenumber":"/ 44",
    "addr:postcode":"2076",
    "addr:street":"Hampden Ave East",
    "iso:country":"AU",
    "sg:address":"9/ 44 Hampden Ave",
    "sg:city":"East Wahroonga",
    "sg:classifiers":[
        {
            "category":"Food & Beverages",
            "subcategory":"Liquor & Beverages",
            "type":"Retail Goods"
        }
    ],
    "sg:phone":"+61 2 9489 5043",
    "sg:postcode":"2076",
    "sg:province":"NSW",
    "sg:tags":[
        "store"
    ],
    "wof:name":"Liquorstop",
    "wof:placetype":"venue"
},
  "geometry": {"coordinates":[151.13742065400001,-33.7113418579],"type":"Point"}
}