{
  "type": "Feature",
  "properties": {
    "addr:full":"301 Forest Rd Hurstville NSW 2220",
    "addr:housenumber":"301",
    "addr:postcode":"2220",
    "addr:street":"Forest Rd",
    "iso:country":"AU",
    "sg:address":"301 Forest Rd",
    "sg:city":"Hurstville",
    "sg:classifiers":[
        {
            "category":"Shopping",
            "subcategory":"Jewelry",
            "type":"Retail Goods"
        }
    ],
    "sg:phone":"+61 2 9580 8784",
    "sg:postcode":"2220",
    "sg:province":"NSW",
    "sg:tags":[
        "jeweller"
    ],
    "wof:name":"Kentson Jewellery",
    "wof:placetype":"venue"
},
  "geometry": {"coordinates":[151.10067749000001,-33.9655189514],"type":"Point"}
}