{
  "type": "Feature",
  "properties": {
    "iso:country":"AU",
    "sg:address":"Shop 1, 97 Tamar St",
    "sg:city":"Ballina",
    "sg:classifiers":[
        {
            "category":"Transit Center",
            "subcategory":"Freight",
            "type":"Transportation"
        }
    ],
    "sg:phone":"+61 2 6681 4266",
    "sg:postcode":"2478",
    "sg:province":"NSW",
    "sg:tags":[
        "building",
        "information"
    ],
    "wof:name":"Master Builders Association of NSW",
    "wof:placetype":"venue"
},
  "geometry": {"coordinates":[153.56239318900001,-28.8568706512],"type":"Point"}
}