{
  "type": "Feature",
  "properties": {
    "addr:full":"80 Elder St Lambton NSW 2299",
    "addr:housenumber":"80",
    "addr:postcode":"2299",
    "addr:street":"Elder St",
    "iso:country":"AU",
    "sg:address":"80 Elder St",
    "sg:city":"Lambton",
    "sg:classifiers":[
        {
            "category":"Banks & Credit Unions",
            "subcategory":"Financial Services",
            "type":"Services"
        }
    ],
    "sg:phone":"+61 2 4952 9033",
    "sg:postcode":"2299",
    "sg:province":"NSW",
    "sg:tags":[
        "annuity",
        "rollover",
        "superannuation",
        "consultant"
    ],
    "wof:name":"Dome Financial Group",
    "wof:placetype":"venue"
},
  "geometry": {"coordinates":[151.70950317399999,-32.9115715027],"type":"Point"}
}