{
  "type": "Feature",
  "properties": {
    "addr:full":"106 Bedford Rd Ringwood East VIC 3135",
    "addr:housenumber":"106",
    "addr:postcode":"3135",
    "addr:street":"Bedford Rd",
    "iso:country":"AU",
    "sg:address":"106 Bedford Rd",
    "sg:city":"Ringwood East",
    "sg:classifiers":[
        {
            "category":"Professional",
            "subcategory":"Art Services",
            "type":"Services"
        }
    ],
    "sg:phone":"+61 3 9847 0141",
    "sg:postcode":"3135",
    "sg:province":"VIC",
    "sg:tags":[
        "product",
        "industrial",
        "designer"
    ],
    "wof:name":"Creative Interface",
    "wof:placetype":"venue"
},
  "geometry": {"coordinates":[145.24424743599999,-37.8196487427],"type":"Point"}
}