{
  "type": "Feature",
  "properties": {
    "iso:country":"AU",
    "sg:address":"152 Marion Rd",
    "sg:city":"Richmond",
    "sg:classifiers":[
        {
            "category":"Real Estate",
            "subcategory":"Real Estate Services",
            "type":"Services"
        }
    ],
    "sg:phone":"+61 8 8352 3444",
    "sg:postcode":"5033",
    "sg:province":"SA",
    "sg:tags":[
        "consultant",
        "property"
    ],
    "wof:name":"Real Estate Professionals Richmond",
    "wof:placetype":"venue"
},
  "geometry": {"coordinates":[138.55279540999999,-34.9385871887],"type":"Point"}
}