{
  "type": "Feature",
  "properties": {
    "addr:full":"66 Jambanis Rd Wanneroo WA 6065",
    "addr:housenumber":"66",
    "addr:postcode":"6065",
    "addr:street":"Jambanis Rd",
    "iso:country":"AU",
    "sg:address":"66 Jambanis Rd",
    "sg:city":"Wanneroo",
    "sg:classifiers":[
        {
            "category":"Home & Garden",
            "subcategory":"Garden Supply",
            "type":"Retail Goods"
        }
    ],
    "sg:phone":"+61 8 9306 3028",
    "sg:postcode":"6065",
    "sg:province":"WA",
    "sg:tags":[
        "equipment",
        "hydroponics"
    ],
    "wof:name":"Isabella's Hydroponic Nursery",
    "wof:placetype":"venue"
},
  "geometry": {"coordinates":[115.838493347,-31.765411377],"type":"Point"}
}