{
  "type": "Feature",
  "properties": {
    "addr:full":"5/ 22 Nagle St Wagga Wagga NSW 2650",
    "addr:housenumber":"/ 22",
    "addr:postcode":"2650",
    "addr:street":"Nagle St",
    "iso:country":"AU",
    "sg:address":"5/ 22 Nagle St",
    "sg:city":"Wagga Wagga",
    "sg:phone":"+61 2 6931 7111",
    "sg:postcode":"2650",
    "sg:province":"NSW",
    "wof:name":"Wagga Filter Cleaning",
    "wof:placetype":"venue"
},
  "geometry": {"coordinates":[147.38226318400001,-35.1236419678],"type":"Point"}
}