{
  "type": "Feature",
  "properties": {
    "addr:full":"144 Goulburn St Sydney NSW 2000",
    "addr:housenumber":"144",
    "addr:postcode":"2000",
    "addr:street":"Goulburn St",
    "iso:country":"AU",
    "sg:address":"144 Goulburn St",
    "sg:city":"Sydney",
    "sg:classifiers":[
        {
            "category":"Travel",
            "subcategory":"Travel Agent",
            "type":"Entertainment"
        }
    ],
    "sg:phone":"+61 2 9261 3051",
    "sg:postcode":"2000",
    "sg:province":"NSW",
    "sg:tags":[
        "tour",
        "holiday",
        "adventure"
    ],
    "wof:name":"Australian Outback Four Wheel Drive Company Pty Ltd",
    "wof:placetype":"venue"
},
  "geometry": {"coordinates":[151.211700439,-33.8785743713],"type":"Point"}
}