{
  "type": "Feature",
  "properties": {
    "addr:full":"1372 Gold Coast Hwy Palm Beach QLD 4221",
    "addr:housenumber":"1372",
    "addr:postcode":"4221",
    "addr:street":"Gold Coast Hwy",
    "iso:country":"AU",
    "sg:address":"1372 Gold Coast Hwy",
    "sg:city":"Palm Beach",
    "sg:classifiers":[
        {
            "category":"Health Services",
            "subcategory":"Doctor",
            "type":"Services"
        }
    ],
    "sg:phone":"+61 7 5576 0288",
    "sg:postcode":"4221",
    "sg:province":"QLD",
    "sg:tags":[
        "medical",
        "practitioner"
    ],
    "wof:name":"Barry Stephen W",
    "wof:placetype":"venue"
},
  "geometry": {"coordinates":[153.465133667,-28.1080112457],"type":"Point"}
}