{
  "type": "Feature",
  "properties": {
    "addr:full":"7 Pease St Manunda QLD 4870",
    "addr:housenumber":"7",
    "addr:postcode":"4870",
    "addr:street":"Pease St",
    "iso:country":"AU",
    "sg:address":"7 Pease St",
    "sg:city":"Manunda",
    "sg:classifiers":[
        {
            "category":"Retail",
            "subcategory":"Funeral Services",
            "type":"Services"
        }
    ],
    "sg:phone":"+61 7 4053 7499",
    "sg:postcode":"4870",
    "sg:province":"QLD",
    "sg:tags":[
        "director"
    ],
    "wof:name":"Cairns Funeral Directors",
    "wof:placetype":"venue"
},
  "geometry": {"coordinates":[145.74159240700001,-16.9112052917],"type":"Point"}
}