{
  "type": "Feature",
  "properties": {
    "iso:country":"AU",
    "sg:address":"27 Loddon St",
    "sg:city":"Kaleen",
    "sg:classifiers":[
        {
            "category":"Building & Trades",
            "subcategory":"Construction",
            "type":"Services"
        }
    ],
    "sg:phone":"+61 2 6241 8639",
    "sg:postcode":"2617",
    "sg:province":"ACT",
    "sg:tags":[
        "brick",
        "paving"
    ],
    "wof:name":"Wizard Landscaping",
    "wof:placetype":"venue"
},
  "geometry": {"coordinates":[149.09982299800001,-35.2284698486],"type":"Point"}
}