{
  "type": "Feature",
  "properties": {
    "addr:full":"Shp 33 Marketplace Muswellbrook NSW 2333",
    "addr:housenumber":"33",
    "addr:postcode":"2333",
    "addr:street":"Marketplace",
    "iso:country":"AU",
    "sg:address":"Shp 33 Marketplace",
    "sg:city":"Muswellbrook",
    "sg:classifiers":[
        {
            "category":"Manufacturing",
            "subcategory":"Jewelry",
            "type":"Manufacturing & Wholesale Goods"
        }
    ],
    "sg:phone":"+61 2 6543 1122",
    "sg:postcode":"2333",
    "sg:province":"NSW",
    "sg:tags":[
        "mfrg",
        "jeweller"
    ],
    "wof:name":"Matthews Jewellers",
    "wof:placetype":"venue"
},
  "geometry": {"coordinates":[150.88752746599999,-32.2689208984],"type":"Point"}
}