{
  "type": "Feature",
  "properties": {
    "iso:country":"AU",
    "sg:address":"7 Blanche Ave",
    "sg:city":"Parkdale",
    "sg:classifiers":[
        {
            "category":"Personal",
            "subcategory":"Massage",
            "type":"Services"
        }
    ],
    "sg:phone":"+61 500 833 749",
    "sg:postcode":"3195",
    "sg:province":"VIC",
    "sg:tags":[
        "therapy"
    ],
    "wof:name":"Aliveness Unlimited",
    "wof:placetype":"venue"
},
  "geometry": {"coordinates":[145.08033752399999,-37.993309021],"type":"Point"}
}