{
  "type": "Feature",
  "properties": {
    "iso:country":"AU",
    "sg:address":"74 Elder St",
    "sg:city":"Alice Springs",
    "sg:classifiers":[
        {
            "category":"Wholesale",
            "subcategory":"Farm Supplies",
            "type":"Manufacturing & Wholesale Goods"
        }
    ],
    "sg:phone":"+61 8 8952 8611",
    "sg:postcode":"0870",
    "sg:province":"NT",
    "sg:tags":[
        "feed",
        "supplement",
        "stock"
    ],
    "wof:name":"Laucke Mills Alice Springs Pty Ltd",
    "wof:placetype":"venue"
},
  "geometry": {"coordinates":[133.86329650900001,-23.6945762634],"type":"Point"}
}