{
  "type": "Feature",
  "properties": {
    "iso:country":"AU",
    "sg:address":"8 Hinkler St",
    "sg:city":"Mt Martha",
    "sg:classifiers":[
        {
            "category":"Travel",
            "subcategory":"Hotels & Motels",
            "type":"Entertainment"
        }
    ],
    "sg:phone":"+61 419 342 150",
    "sg:postcode":"3934",
    "sg:province":"VIC",
    "sg:tags":[
        "accommodation"
    ],
    "wof:name":"Hideaway On Hinkler",
    "wof:placetype":"venue"
},
  "geometry": {"coordinates":[145.026580811,-38.2552337646],"type":"Point"}
}