{
  "type": "Feature",
  "properties": {
    "addr:full":"966 Dandenong Rd Carnegie VIC 3163",
    "addr:housenumber":"966",
    "addr:postcode":"3163",
    "addr:street":"Dandenong Rd",
    "iso:country":"AU",
    "sg:address":"966 Dandenong Rd",
    "sg:city":"Carnegie",
    "sg:phone":"+61 3 9571 0177",
    "sg:postcode":"3163",
    "sg:province":"VIC",
    "wof:name":"Bremner W. & Sons",
    "wof:placetype":"venue"
},
  "geometry": {"coordinates":[145.050704956,-37.8824081421],"type":"Point"}
}