{
  "type": "Feature",
  "properties": {
    "iso:country":"AU",
    "sg:address":"9 Vendale Drv",
    "sg:city":"Flagstaff Hill",
    "sg:classifiers":[
        {
            "category":"Professional",
            "subcategory":"Business Services",
            "type":"Services"
        }
    ],
    "sg:phone":"+61 8 8298 6997",
    "sg:postcode":"5159",
    "sg:province":"SA",
    "sg:tags":[
        "drafting"
    ],
    "wof:name":"Bacho Homes Pty Ltd",
    "wof:placetype":"venue"
},
  "geometry": {"coordinates":[138.569702148,-35.0449409485],"type":"Point"}
}