{
  "type": "Feature",
  "properties": {
    "addr:full":"145 Camden Rd Douglas Park NSW 2569",
    "addr:housenumber":"145",
    "addr:postcode":"2569",
    "addr:street":"Camden Rd",
    "iso:country":"AU",
    "sg:address":"145 Camden Rd",
    "sg:city":"Douglas Park",
    "sg:classifiers":[
        {
            "category":"Autos & Motor Vehicles",
            "subcategory":"Fuel & Gas Station",
            "type":"Retail Goods"
        }
    ],
    "sg:phone":"+61 2 4632 7436",
    "sg:postcode":"2569",
    "sg:province":"NSW",
    "wof:name":"Douglas Park Cellars & Service Station",
    "wof:placetype":"venue"
},
  "geometry": {"coordinates":[150.711105347,-34.1824455261],"type":"Point"}
}