{
  "type": "Feature",
  "properties": {
    "addr:full":"PO Box 419 Monbulk VIC 3793",
    "addr:postcode":"3793",
    "iso:country":"AU",
    "sg:address":"PO Box 419",
    "sg:city":"Monbulk",
    "sg:classifiers":[
        {
            "category":"Education",
            "subcategory":"Music School",
            "type":"Public Place"
        }
    ],
    "sg:phone":"+61 3 9752 1811",
    "sg:postcode":"3793",
    "sg:province":"VIC",
    "sg:tags":[
        "choir",
        "bands",
        "orchestra"
    ],
    "wof:name":"Jazz Antics",
    "wof:placetype":"venue"
},
  "geometry": {"coordinates":[145.42523193400001,-37.8750305176],"type":"Point"}
}