{
  "type": "Feature",
  "properties": {
    "iso:country":"AU",
    "sg:address":"14 Queen St",
    "sg:city":"Woollahra",
    "sg:classifiers":[
        {
            "category":"Retail",
            "subcategory":"Event Space",
            "type":"Services"
        }
    ],
    "sg:phone":"+61 2 9363 4863",
    "sg:postcode":"2025",
    "sg:province":"NSW",
    "sg:tags":[
        "venue",
        "reception",
        "wedding"
    ],
    "wof:name":"Hughenden Boutique Hotel",
    "wof:placetype":"venue"
},
  "geometry": {"coordinates":[151.23345947300001,-33.8890075684],"type":"Point"}
}