{
  "type": "Feature",
  "properties": {
    "iso:country":"AU",
    "sg:address":"156 Church St",
    "sg:city":"Mudgee",
    "sg:classifiers":[
        {
            "category":"Building & Trades",
            "subcategory":"Construction",
            "type":"Services"
        }
    ],
    "sg:phone":"+61 2 6372 4493",
    "sg:postcode":"2850",
    "sg:province":"NSW",
    "sg:tags":[
        "contractor"
    ],
    "wof:name":"Ian Birchall Constructions Pty. Limited",
    "wof:placetype":"venue"
},
  "geometry": {"coordinates":[149.585037,-32.608185],"type":"Point"}
}