{
  "type": "Feature",
  "properties": {
    "addr:full":"Unit 1/ 8 Neumann Crt Kunda Park QLD 4556",
    "addr:postcode":"4556",
    "addr:street":"Neumann Crt",
    "iso:country":"AU",
    "sg:address":"Unit 1/ 8 Neumann Crt",
    "sg:city":"Kunda Park",
    "sg:classifiers":[
        {
            "category":"Banks & Credit Unions",
            "subcategory":"Investment Brokerage",
            "type":"Services"
        }
    ],
    "sg:phone":"+61 7 5453 7835",
    "sg:postcode":"4556",
    "sg:province":"QLD",
    "sg:tags":[
        "radiator",
        "motor"
    ],
    "wof:name":"Kunda Park Radiators",
    "wof:placetype":"venue"
},
  "geometry": {"coordinates":[153.03616332999999,-26.6605968475],"type":"Point"}
}