{
  "type": "Feature",
  "properties": {
    "addr:full":"Russart St Lyndhurst NSW 2797",
    "addr:postcode":"2797",
    "addr:street":"St",
    "iso:country":"AU",
    "sg:address":"Russart St",
    "sg:city":"Lyndhurst",
    "sg:classifiers":[
        {
            "category":"Education",
            "subcategory":"School",
            "type":"Public Place"
        }
    ],
    "sg:phone":"+61 2 6367 5016",
    "sg:postcode":"2797",
    "sg:province":"NSW",
    "sg:tags":[
        "state",
        "-",
        "nsw"
    ],
    "wof:name":"Lyndhurst Public School",
    "wof:placetype":"venue"
},
  "geometry": {"coordinates":[149.045166016,-33.6726837158],"type":"Point"}
}