{
  "type": "Feature",
  "properties": {
    "addr:full":"17 Olympus Drv St Clair NSW 2759",
    "addr:housenumber":"17",
    "addr:postcode":"2759",
    "addr:street":"Olympus Drv",
    "iso:country":"AU",
    "sg:address":"17 Olympus Drv",
    "sg:city":"St Clair",
    "sg:classifiers":[
        {
            "category":"Professional",
            "subcategory":"Accounting & Tax Preparation",
            "type":"Services"
        }
    ],
    "sg:phone":"+61 2 9670 6891",
    "sg:postcode":"2759",
    "sg:province":"NSW",
    "sg:tags":[
        "accountant",
        "auditor"
    ],
    "wof:name":"M. ALvarez & Co",
    "wof:placetype":"venue"
},
  "geometry": {"coordinates":[150.77206420900001,-33.7923240662],"type":"Point"}
}