{
  "type": "Feature",
  "properties": {
    "iso:country":"AU",
    "sg:address":"86 Prospect Rd",
    "sg:city":"Prospect",
    "sg:classifiers":[
        {
            "category":"Restaurant",
            "type":"Food & Drink"
        }
    ],
    "sg:phone":"+61 8 8342 1222",
    "sg:postcode":"5082",
    "sg:province":"SA",
    "wof:name":"BaBanusa Restaurant",
    "wof:placetype":"venue"
},
  "geometry": {"coordinates":[138.59400939899999,-34.8893585205],"type":"Point"}
}