{
  "type": "Feature",
  "properties": {
    "iso:country":"AU",
    "sg:address":"Healthville Medical Centre 317 319 High St",
    "sg:city":"Thomastown",
    "sg:classifiers":[
        {
            "category":"Health Services",
            "subcategory":"Health Practitioner",
            "type":"Services"
        }
    ],
    "sg:phone":"+61 3 9465 0007",
    "sg:postcode":"3074",
    "sg:province":"VIC",
    "sg:tags":[
        "alternative"
    ],
    "wof:name":"Connie Cantiani Holistic Therapy Practitioner",
    "wof:placetype":"venue"
},
  "geometry": {"coordinates":[145.01454162600001,-37.6757011414],"type":"Point"}
}