{
  "type": "Feature",
  "properties": {
    "addr:full":"305 Pier St Perth WA 6000",
    "addr:housenumber":"305",
    "addr:postcode":"6000",
    "addr:street":"Pier St",
    "iso:country":"AU",
    "sg:address":"305 Pier St",
    "sg:city":"Perth",
    "sg:classifiers":[
        {
            "category":"Banks & Credit Unions",
            "subcategory":"Financial Services",
            "type":"Services"
        }
    ],
    "sg:phone":"+61 8 9228 2833",
    "sg:postcode":"6000",
    "sg:province":"WA",
    "sg:tags":[
        "planning"
    ],
    "wof:name":"Perth Financial Services",
    "wof:placetype":"venue"
},
  "geometry": {"coordinates":[115.868171692,-31.9459838867],"type":"Point"}
}