{
  "type": "Feature",
  "properties": {
    "addr:full":"264 Illawarra Rd Marrickville NSW 2204",
    "addr:housenumber":"264",
    "addr:postcode":"2204",
    "addr:street":"Illawarra Rd",
    "iso:country":"AU",
    "sg:address":"264 Illawarra Rd",
    "sg:city":"Marrickville",
    "sg:classifiers":[
        {
            "category":"Shopping",
            "subcategory":"Clothing, Apparel, & Fashions",
            "type":"Retail Goods"
        }
    ],
    "sg:phone":"+61 2 9558 9345",
    "sg:postcode":"2204",
    "sg:province":"NSW",
    "sg:tags":[
        "boutique"
    ],
    "wof:name":"Vans Fashion",
    "wof:placetype":"venue"
},
  "geometry": {"coordinates":[151.15542600000001,-33.911301],"type":"Point"}
}