{
  "type": "Feature",
  "properties": {
    "addr:full":"Townsend St Finley NSW 2713",
    "addr:postcode":"2713",
    "addr:street":"Townsend St",
    "iso:country":"AU",
    "sg:address":"Townsend St",
    "sg:city":"Finley",
    "sg:classifiers":[
        {
            "category":"Retail",
            "subcategory":"Auto Repair",
            "type":"Services"
        }
    ],
    "sg:phone":"+61 3 5883 1442",
    "sg:postcode":"2713",
    "sg:province":"NSW",
    "sg:tags":[
        "bus",
        "truck"
    ],
    "wof:name":"Bickleys Bus Service Finley",
    "wof:placetype":"venue"
},
  "geometry": {"coordinates":[145.573974609,-35.6471481323],"type":"Point"}
}