{
  "type": "Feature",
  "properties": {
    "addr:full":"Shop 31-32 Narellan Town Centre Narellan NSW 2567",
    "addr:housenumber":"31-32",
    "addr:postcode":"2567",
    "addr:street":"Narellan",
    "iso:country":"AU",
    "sg:address":"Shop 31-32 Narellan Town Centre",
    "sg:city":"Narellan",
    "sg:classifiers":[
        {
            "category":"Shopping",
            "subcategory":"Clothing, Apparel, & Fashions",
            "type":"Retail Goods"
        }
    ],
    "sg:phone":"+61 2 4647 4664",
    "sg:postcode":"2567",
    "sg:province":"NSW",
    "sg:tags":[
        "lady",
        "wear"
    ],
    "wof:name":"Miller's Fashion Club",
    "wof:placetype":"venue"
},
  "geometry": {"coordinates":[150.779098511,-34.057434082],"type":"Point"}
}