{
  "type": "Feature",
  "properties": {
    "addr:full":"19 Carroll St Toowoomba QLD 4350",
    "addr:housenumber":"19",
    "addr:postcode":"4350",
    "addr:street":"Carroll St",
    "iso:country":"AU",
    "sg:address":"19 Carroll St",
    "sg:city":"Toowoomba",
    "sg:classifiers":[
        {
            "category":"Professional",
            "subcategory":"Art Services",
            "type":"Services"
        }
    ],
    "sg:phone":"+61 7 4634 1486",
    "sg:postcode":"4350",
    "sg:province":"QLD",
    "sg:tags":[
        "interior",
        "designer"
    ],
    "wof:name":"Euroka Kitchens & Joinery",
    "wof:placetype":"venue"
},
  "geometry": {"coordinates":[151.90765400000001,-27.543219],"type":"Point"}
}