{
  "type": "Feature",
  "properties": {
    "addr:full":"Proctor Rd Yundi SA 5172",
    "addr:postcode":"5172",
    "addr:street":"Proctor Rd",
    "iso:country":"AU",
    "sg:address":"Proctor Rd",
    "sg:city":"Yundi",
    "sg:classifiers":[
        {
            "category":"Farming",
            "subcategory":"Farm",
            "type":"Manufacturing & Wholesale Goods"
        }
    ],
    "sg:phone":"+61 8 8556 0232",
    "sg:postcode":"5172",
    "sg:province":"SA",
    "sg:tags":[
        "farmer"
    ],
    "wof:name":"Warner Brian J P & M E",
    "wof:placetype":"venue"
},
  "geometry": {"coordinates":[138.62249755900001,-35.3248825073],"type":"Point"}
}