{
  "type": "Feature",
  "properties": {
    "iso:country":"AU",
    "sg:address":"Fern St",
    "sg:city":"Gympie",
    "sg:classifiers":[
        {
            "category":"Organizations",
            "subcategory":"Community Association",
            "type":"Services"
        }
    ],
    "sg:phone":"+61 7 5482 3342",
    "sg:postcode":"4570",
    "sg:province":"QLD",
    "sg:tags":[
        "organisation",
        "family",
        "welfare"
    ],
    "wof:name":"Meals On Wheels",
    "wof:placetype":"venue"
},
  "geometry": {"coordinates":[152.66569519000001,-26.1873569489],"type":"Point"}
}