{
  "type": "Feature",
  "properties": {
    "iso:country":"AU",
    "sg:address":"\"Flinders Few\" 177 Exchange Rd",
    "sg:city":"Lower Broughton",
    "sg:classifiers":[
        {
            "category":"Farming",
            "subcategory":"Farm",
            "type":"Manufacturing & Wholesale Goods"
        }
    ],
    "sg:phone":"+61 8 8634 2229",
    "sg:postcode":"5540",
    "sg:province":"SA",
    "sg:tags":[
        "farmer"
    ],
    "wof:name":"Baker G J",
    "wof:placetype":"venue"
},
  "geometry": {"coordinates":[137.96635437,-33.2300682068],"type":"Point"}
}