{
  "type": "Feature",
  "properties": {
    "iso:country":"AU",
    "sg:address":"35 Hammond St",
    "sg:city":"Hamilton",
    "sg:classifiers":[
        {
            "category":"Building & Trades",
            "subcategory":"Construction",
            "type":"Services"
        }
    ],
    "sg:phone":"+61 3 5571 1760",
    "sg:postcode":"3300",
    "sg:province":"VIC",
    "sg:tags":[
        "window",
        "aluminium"
    ],
    "wof:name":"WD Windows & Doors",
    "wof:placetype":"venue"
},
  "geometry": {"coordinates":[142.00592040999999,-37.7283210754],"type":"Point"}
}