{
  "type": "Feature",
  "properties": {
    "iso:country":"AU",
    "sg:address":"43 Notar Drv",
    "sg:city":"Ormeau",
    "sg:classifiers":[
        {
            "category":"Home & Garden",
            "subcategory":"Hardware",
            "type":"Retail Goods"
        }
    ],
    "sg:phone":"+61 7 5540 6480",
    "sg:postcode":"4208",
    "sg:province":"QLD",
    "sg:tags":[
        "repair",
        "tool",
        "power"
    ],
    "wof:name":"Tradetools Direct",
    "wof:placetype":"venue"
},
  "geometry": {"coordinates":[153.250274658,-27.7621898651],"type":"Point"}
}