{
  "type": "Feature",
  "properties": {
    "iso:country":"AU",
    "sg:address":"PO Box 34",
    "sg:city":"Gundagai",
    "sg:classifiers":[
        {
            "category":"Farming",
            "subcategory":"Vineyard",
            "type":"Manufacturing & Wholesale Goods"
        }
    ],
    "sg:phone":"+61 2 6944 1226",
    "sg:postcode":"2722",
    "sg:province":"NSW",
    "sg:tags":[
        "saleyards"
    ],
    "wof:name":"Saleyard Operators Association of NSW",
    "wof:placetype":"venue"
},
  "geometry": {"coordinates":[148.101227,-35.06179],"type":"Point"}
}