{
  "type": "Feature",
  "properties": {
    "iso:country":"AU",
    "sg:address":"21 Belbowrie Ave",
    "sg:city":"Narara",
    "sg:classifiers":[
        {
            "category":"Retail",
            "subcategory":"Event Space",
            "type":"Services"
        }
    ],
    "sg:phone":"+61 2 4323 2442",
    "sg:postcode":"2250",
    "sg:province":"NSW",
    "sg:tags":[
        "function",
        "organiser"
    ],
    "wof:name":"Lerida Gardens",
    "wof:placetype":"venue"
},
  "geometry": {"coordinates":[151.34317016599999,-33.4032211304],"type":"Point"}
}