{
  "type": "Feature",
  "properties": {
    "addr:full":"24 George St Earlville QLD 4870",
    "addr:housenumber":"24",
    "addr:postcode":"4870",
    "addr:street":"George St",
    "iso:country":"AU",
    "sg:address":"24 George St",
    "sg:city":"Earlville",
    "sg:classifiers":[
        {
            "category":"Transit Center",
            "subcategory":"Freight",
            "type":"Transportation"
        }
    ],
    "sg:phone":"+61 428 745 354",
    "sg:postcode":"4870",
    "sg:province":"QLD",
    "sg:tags":[
        "forklift",
        "truck"
    ],
    "wof:name":"Sol-lift Hire",
    "wof:placetype":"venue"
},
  "geometry": {"coordinates":[145.73245239299999,-16.945350647],"type":"Point"}
}