{
  "type": "Feature",
  "properties": {
    "addr:full":"Cooper St Cootamundra NSW 2590",
    "addr:postcode":"2590",
    "addr:street":"Cooper St",
    "iso:country":"AU",
    "sg:address":"Cooper St",
    "sg:city":"Cootamundra",
    "sg:classifiers":[
        {
            "category":"Education",
            "subcategory":"School",
            "type":"Public Place"
        }
    ],
    "sg:phone":"+61 2 6942 1402",
    "sg:postcode":"2590",
    "sg:province":"NSW",
    "sg:tags":[
        "state",
        "-",
        "nsw"
    ],
    "wof:name":"Cootamundra Primary School",
    "wof:placetype":"venue"
},
  "geometry": {"coordinates":[148.02442932100001,-34.6402702332],"type":"Point"}
}