{
  "type": "Feature",
  "properties": {
    "iso:country":"AU",
    "sg:address":"3 Whel St",
    "sg:city":"Mt Gambier",
    "sg:classifiers":[
        {
            "category":"Wholesale",
            "subcategory":"Painting Supplies",
            "type":"Manufacturing & Wholesale Goods"
        }
    ],
    "sg:phone":"+61 427 838 742",
    "sg:postcode":"5290",
    "sg:province":"SA",
    "sg:tags":[
        "equipment",
        "spraying"
    ],
    "wof:name":"C J Airless Spray",
    "wof:placetype":"venue"
},
  "geometry": {"coordinates":[140.782745,-37.809669],"type":"Point"}
}