{
  "type": "Feature",
  "properties": {
    "iso:country":"AU",
    "sg:address":"72 McMeekin Rd",
    "sg:city":"Warrnambool",
    "sg:classifiers":[
        {
            "category":"Professional",
            "subcategory":"Computer Services",
            "type":"Services"
        }
    ],
    "sg:phone":"+61 3 5561 3020",
    "sg:postcode":"3280",
    "sg:province":"VIC",
    "sg:tags":[
        "consultant",
        "system"
    ],
    "wof:name":"Regan D O & J",
    "wof:placetype":"venue"
},
  "geometry": {"coordinates":[142.454421997,-38.3748664856],"type":"Point"}
}