{
  "type": "Feature",
  "properties": {
    "addr:full":"12 Rennies Rd Indooroopilly QLD 4068",
    "addr:housenumber":"12",
    "addr:postcode":"4068",
    "addr:street":"Rennies Rd",
    "iso:country":"AU",
    "sg:address":"12 Rennies Rd",
    "sg:city":"Indooroopilly",
    "sg:classifiers":[
        {
            "category":"Taxi",
            "type":"Transportation"
        }
    ],
    "sg:phone":"+61 7 3398 2723",
    "sg:postcode":"4068",
    "sg:province":"QLD",
    "sg:tags":[
        "truck"
    ],
    "wof:name":"St Lucia Removals",
    "wof:placetype":"venue"
},
  "geometry": {"coordinates":[152.96255493199999,-27.5052890778],"type":"Point"}
}