{
  "type": "Feature",
  "properties": {
    "addr:full":"80 Manton Rd Clayton VIC 3168",
    "addr:housenumber":"80",
    "addr:postcode":"3168",
    "addr:street":"Manton Rd",
    "iso:country":"AU",
    "sg:address":"80 Manton Rd",
    "sg:city":"Clayton",
    "sg:classifiers":[
        {
            "category":"Professional",
            "subcategory":"Computer Services",
            "type":"Services"
        }
    ],
    "sg:phone":"+61 419 882 800",
    "sg:postcode":"3168",
    "sg:province":"VIC",
    "sg:tags":[
        "training"
    ],
    "wof:name":"QUICKBOOKS Accredited Trainer",
    "wof:placetype":"venue"
},
  "geometry": {"coordinates":[145.11770629899999,-37.9153022766],"type":"Point"}
}