{
  "type": "Feature",
  "properties": {
    "addr:full":"85 Hoffmans Rd Niddrie VIC 3042",
    "addr:housenumber":"85",
    "addr:postcode":"3042",
    "addr:street":"Hoffmans Rd",
    "iso:country":"AU",
    "sg:address":"85 Hoffmans Rd",
    "sg:city":"Niddrie",
    "sg:classifiers":[
        {
            "category":"Health Services",
            "subcategory":"Health Practitioner",
            "type":"Services"
        }
    ],
    "sg:phone":"+61 3 9337 4123",
    "sg:postcode":"3042",
    "sg:province":"VIC",
    "sg:tags":[
        "dietitian"
    ],
    "wof:name":"Ireland Paul Dr APD",
    "wof:placetype":"venue"
},
  "geometry": {"coordinates":[144.89117431599999,-37.7437362671],"type":"Point"}
}