{
  "type": "Feature",
  "properties": {
    "addr:full":"35 Chapman St Fairy Meadow NSW 2519",
    "addr:housenumber":"35",
    "addr:postcode":"2519",
    "addr:street":"Chapman St",
    "iso:country":"AU",
    "sg:address":"35 Chapman St",
    "sg:city":"Fairy Meadow",
    "sg:classifiers":[
        {
            "category":"Retail",
            "subcategory":"Auto Repair",
            "type":"Services"
        }
    ],
    "sg:phone":"+61 2 4284 6674",
    "sg:postcode":"2519",
    "sg:province":"NSW",
    "sg:tags":[
        "repairer",
        "motor",
        "engineer"
    ],
    "wof:name":"Leisure Coast Carburettor Services Pty Ltd",
    "wof:placetype":"venue"
},
  "geometry": {"coordinates":[150.895554,-34.387302],"type":"Point"}
}