{
  "type": "Feature",
  "properties": {
    "addr:full":"25 Brisbane Rd Bundamba QLD 4304",
    "addr:housenumber":"25",
    "addr:postcode":"4304",
    "addr:street":"Brisbane Rd",
    "iso:country":"AU",
    "sg:address":"25 Brisbane Rd",
    "sg:city":"Bundamba",
    "sg:classifiers":[
        {
            "category":"Autos & Motor Vehicles",
            "subcategory":"Motorcycle Sales",
            "type":"Retail Goods"
        }
    ],
    "sg:phone":"+61 7 3282 4888",
    "sg:postcode":"4304",
    "sg:province":"QLD",
    "sg:tags":[
        "part",
        "recyclers",
        "cycle"
    ],
    "wof:name":"Motorcycle Recyclers",
    "wof:placetype":"venue"
},
  "geometry": {"coordinates":[152.81013488799999,-27.6090507507],"type":"Point"}
}