{
  "type": "Feature",
  "properties": {
    "iso:country":"AU",
    "sg:address":"8- 10 Riverside Rd",
    "sg:city":"Chipping Norton",
    "sg:classifiers":[
        {
            "category":"Manufacturing",
            "subcategory":"Glass & Minerals",
            "type":"Manufacturing & Wholesale Goods"
        }
    ],
    "sg:phone":"+61 2 9755 3836",
    "sg:postcode":"2170",
    "sg:province":"NSW",
    "sg:tags":[
        "repair",
        "fibreglass",
        "product"
    ],
    "wof:name":"PQ Australia Pty Ltd",
    "wof:placetype":"venue"
},
  "geometry": {"coordinates":[150.96842956500001,-33.9140739441],"type":"Point"}
}