{
  "type": "Feature",
  "properties": {
    "addr:full":"4 Adams Rd Yarrawonga NT 0830",
    "addr:housenumber":"4",
    "addr:postcode":"nt 0830",
    "addr:street":"Adams Rd",
    "iso:country":"AU",
    "sg:address":"4 Adams Rd",
    "sg:city":"Yarrawonga",
    "sg:classifiers":[
        {
            "category":"Farming",
            "subcategory":"Vineyard",
            "type":"Manufacturing & Wholesale Goods"
        }
    ],
    "sg:phone":"+61 8 8931 1166",
    "sg:postcode":"0830",
    "sg:province":"NT",
    "sg:tags":[
        "winery"
    ],
    "wof:name":"Kakadu Winery",
    "wof:placetype":"venue"
},
  "geometry": {"coordinates":[130.98756399999999,-12.476108],"type":"Point"}
}