{
  "type": "Feature",
  "properties": {
    "addr:full":"Suite 16, Cooloola Centre 97 Poinciana Ave Tewantin QLD 4565",
    "addr:housenumber":"97",
    "addr:postcode":"4565",
    "addr:street":"Poinciana Ave",
    "iso:country":"AU",
    "sg:address":"Suite 16, Cooloola Centre 97 Poinciana Ave",
    "sg:city":"Tewantin",
    "sg:classifiers":[
        {
            "category":"Banks & Credit Unions",
            "subcategory":"Financial Services",
            "type":"Services"
        }
    ],
    "sg:phone":"+61 7 5449 8622",
    "sg:postcode":"4565",
    "sg:province":"QLD",
    "sg:tags":[
        "annuity",
        "rollover",
        "superannuation",
        "consultant"
    ],
    "wof:name":"McFarlane Orr & Co",
    "wof:placetype":"venue"
},
  "geometry": {"coordinates":[153.03791809099999,-26.3917503357],"type":"Point"}
}