{
  "type": "Feature",
  "properties": {
    "iso:country":"AU",
    "sg:address":"20 Docker St",
    "sg:city":"Wagga Wagga",
    "sg:classifiers":[
        {
            "category":"Health Services",
            "subcategory":"Doctor",
            "type":"Services"
        }
    ],
    "sg:phone":"+61 2 6925 3999",
    "sg:postcode":"2650",
    "sg:province":"NSW",
    "sg:tags":[
        "medical",
        "practitioner"
    ],
    "wof:name":"Carroll G E",
    "wof:placetype":"venue"
},
  "geometry": {"coordinates":[147.35548400900001,-35.1202468872],"type":"Point"}
}