{
  "type": "Feature",
  "properties": {
    "iso:country":"AU",
    "sg:address":"7 Finch Pl",
    "sg:city":"St Clair",
    "sg:classifiers":[
        {
            "category":"Manufacturing",
            "subcategory":"Glass & Minerals",
            "type":"Manufacturing & Wholesale Goods"
        }
    ],
    "sg:phone":"+61 417 209 341",
    "sg:postcode":"2759",
    "sg:province":"NSW",
    "sg:tags":[
        "merchant",
        "granite",
        "marble"
    ],
    "wof:name":"J & M Stone",
    "wof:placetype":"venue"
},
  "geometry": {"coordinates":[150.77229309099999,-33.7947463989],"type":"Point"}
}