{
  "type": "Feature",
  "properties": {
    "iso:country":"AU",
    "sg:address":"380 Princes Hwy",
    "sg:city":"Woonona",
    "sg:classifiers":[
        {
            "category":"Health Services",
            "subcategory":"Doctor",
            "type":"Services"
        }
    ],
    "sg:phone":"+61 2 4283 3433",
    "sg:postcode":"2517",
    "sg:province":"NSW",
    "sg:tags":[
        "medical",
        "practitioner"
    ],
    "wof:name":"Charles Michael+Woonona Medical Practice",
    "wof:placetype":"venue"
},
  "geometry": {"coordinates":[150.906403,-34.341141],"type":"Point"}
}