{
  "type": "Feature",
  "properties": {
    "addr:full":"37 Bay St Broadway NSW 2007",
    "addr:housenumber":"37",
    "addr:postcode":"2007",
    "addr:street":"Bay St",
    "iso:country":"AU",
    "sg:address":"37 Bay St",
    "sg:city":"Broadway",
    "sg:classifiers":[
        {
            "category":"Health Services",
            "subcategory":"Doctor",
            "type":"Services"
        }
    ],
    "sg:phone":"+61 2 9552 6277",
    "sg:postcode":"2007",
    "sg:province":"NSW",
    "sg:tags":[
        "medical",
        "practitioner"
    ],
    "wof:name":"Madirazza John Dr.",
    "wof:placetype":"venue"
},
  "geometry": {"coordinates":[151.19473266599999,-33.882598877],"type":"Point"}
}