{
  "type": "Feature",
  "properties": {
    "addr:full":"2/ 2 Jamieson Pl Glendenning NSW 2761",
    "addr:housenumber":"/ 2",
    "addr:postcode":"2761",
    "addr:street":"Jamieson Pl",
    "iso:country":"AU",
    "sg:address":"2/ 2 Jamieson Pl",
    "sg:city":"Glendenning",
    "sg:classifiers":[
        {
            "category":"Retail",
            "subcategory":"Storage",
            "type":"Services"
        }
    ],
    "sg:phone":"+61 13 72 25",
    "sg:postcode":"2761",
    "sg:province":"NSW",
    "sg:tags":[
        "shelving",
        "system"
    ],
    "wof:name":"Acerack Pty Ltd",
    "wof:placetype":"venue"
},
  "geometry": {"coordinates":[150.85295099999999,-33.757542],"type":"Point"}
}