{
  "type": "Feature",
  "properties": {
    "iso:country":"AU",
    "sg:address":"21 Greenbank Drv",
    "sg:city":"Glenhaven",
    "sg:classifiers":[
        {
            "category":"Government",
            "subcategory":"Court House",
            "type":"Public Place"
        }
    ],
    "sg:phone":"+61 2 8850 3984",
    "sg:postcode":"2156",
    "sg:province":"NSW",
    "sg:tags":[
        "personal",
        "marriage",
        "family",
        "counselling"
    ],
    "wof:name":"Pamela Hoy Counselling Service",
    "wof:placetype":"venue"
},
  "geometry": {"coordinates":[151.003143311,-33.7089157104],"type":"Point"}
}