{
  "type": "Feature",
  "properties": {
    "iso:country":"AU",
    "sg:address":"192 Harbord Rd",
    "sg:city":"Brookvale",
    "sg:classifiers":[
        {
            "category":"Autos & Motor Vehicles",
            "subcategory":"Auto Supplies",
            "type":"Retail Goods"
        }
    ],
    "sg:phone":"+61 2 9905 4330",
    "sg:postcode":"2100",
    "sg:province":"NSW",
    "sg:tags":[
        "tyre"
    ],
    "wof:name":"Goodspanner",
    "wof:placetype":"venue"
},
  "geometry": {"coordinates":[151.27947998100001,-33.7643814087],"type":"Point"}
}