{
  "type": "Feature",
  "properties": {
    "iso:country":"AU",
    "sg:address":"23 Norfolk Cl",
    "sg:city":"Tuncurry",
    "sg:classifiers":[
        {
            "category":"Parking",
            "type":"Transportation"
        }
    ],
    "sg:phone":"+61 2 6554 7339",
    "sg:postcode":"2428",
    "sg:province":"NSW",
    "sg:tags":[
        "equipment",
        "system"
    ],
    "wof:name":"Tyter Doors",
    "wof:placetype":"venue"
},
  "geometry": {"coordinates":[152.51608300000001,-32.18552],"type":"Point"}
}