{
  "type": "Feature",
  "properties": {
    "iso:country":"AU",
    "sg:address":"62 Guthrie St",
    "sg:city":"Osborne Park",
    "sg:classifiers":[
        {
            "category":"Professional",
            "subcategory":"Detective & Security Services",
            "type":"Services"
        }
    ],
    "sg:phone":"+61 8 9445 7333",
    "sg:postcode":"6017",
    "sg:province":"WA",
    "sg:tags":[
        "equipment",
        "window",
        "doors"
    ],
    "sg:website":"http://www.clearviewsecurity.com.au",
    "wof:name":"Clearview Security",
    "wof:placetype":"venue"
},
  "geometry": {"coordinates":[115.814208984,-31.9046611786],"type":"Point"}
}