{
  "type": "Feature",
  "properties": {
    "addr:full":"PO Box 156 Northmead NSW 2152",
    "addr:postcode":"2152",
    "iso:country":"AU",
    "sg:address":"PO Box 156",
    "sg:city":"Northmead",
    "sg:classifiers":[
        {
            "category":"Real Estate",
            "subcategory":"Real Estate Services",
            "type":"Services"
        }
    ],
    "sg:phone":"+61 2 9630 5085",
    "sg:postcode":"2152",
    "sg:province":"NSW",
    "sg:tags":[
        "consultant",
        "property"
    ],
    "wof:name":"Hamilton Gray Property Services",
    "wof:placetype":"venue"
},
  "geometry": {"coordinates":[150.994338989,-33.7838516235],"type":"Point"}
}