{
  "type": "Feature",
  "properties": {
    "iso:country":"AU",
    "sg:address":"Ste2/ 15 Kildare Rd",
    "sg:city":"Blacktown",
    "sg:classifiers":[
        {
            "category":"Personal",
            "subcategory":"Nail Salon",
            "type":"Services"
        }
    ],
    "sg:phone":"+61 2 9621 3469",
    "sg:postcode":"2148",
    "sg:province":"NSW",
    "sg:tags":[
        "artificial"
    ],
    "wof:name":"Digits Nail Studio",
    "wof:placetype":"venue"
},
  "geometry": {"coordinates":[150.90524292000001,-33.7687721252],"type":"Point"}
}