{
  "type": "Feature",
  "properties": {
    "addr:full":"25 Caporn St Bullsbrook WA 6084",
    "addr:housenumber":"25",
    "addr:postcode":"6084",
    "addr:street":"Caporn St",
    "iso:country":"AU",
    "sg:address":"25 Caporn St",
    "sg:city":"Bullsbrook",
    "sg:classifiers":[
        {
            "category":"Social Services",
            "subcategory":"Child Care",
            "type":"Services"
        }
    ],
    "sg:phone":"+61 8 9571 1141",
    "sg:postcode":"6084",
    "sg:province":"WA",
    "wof:name":"Child Health Services",
    "wof:placetype":"venue"
},
  "geometry": {"coordinates":[116.02964782700001,-31.6627368927],"type":"Point"}
}