{
  "type": "Feature",
  "properties": {
    "addr:full":"51 Shannon Pde Berkeley Vale NSW 2261",
    "addr:housenumber":"51",
    "addr:postcode":"2261",
    "addr:street":"Shannon Pde",
    "iso:country":"AU",
    "sg:address":"51 Shannon Pde",
    "sg:city":"Berkeley Vale",
    "sg:classifiers":[
        {
            "category":"Retail",
            "subcategory":"Repair Shop",
            "type":"Services"
        }
    ],
    "sg:phone":"+61 425 246 703",
    "sg:postcode":"2261",
    "sg:province":"NSW",
    "sg:tags":[
        "machine",
        "repairs",
        "part",
        "dryer",
        "washing"
    ],
    "wof:name":"Eurocoast Appliances Pty Ltd",
    "wof:placetype":"venue"
},
  "geometry": {"coordinates":[151.43353300000001,-33.34848],"type":"Point"}
}