{
  "type": "Feature",
  "properties": {
    "addr:full":"34 Douglas Pde Williamstown VIC 3016",
    "addr:housenumber":"34",
    "addr:postcode":"3016",
    "addr:street":"Douglas Pde",
    "iso:country":"AU",
    "sg:address":"34 Douglas Pde",
    "sg:city":"Williamstown",
    "sg:classifiers":[
        {
            "category":"Shopping",
            "subcategory":"Clothing, Apparel, & Fashions",
            "type":"Retail Goods"
        }
    ],
    "sg:phone":"+61 3 9397 7330",
    "sg:postcode":"3016",
    "sg:province":"VIC",
    "sg:tags":[
        "sportswear"
    ],
    "wof:name":"SportsPower Williamstown",
    "wof:placetype":"venue"
},
  "geometry": {"coordinates":[144.89805602999999,-37.8578491211],"type":"Point"}
}