{
  "type": "Feature",
  "properties": {
    "addr:full":"243 Victoria Ave Margate QLD 4019",
    "addr:housenumber":"243",
    "addr:postcode":"4019",
    "addr:street":"Victoria Ave",
    "iso:country":"AU",
    "sg:address":"243 Victoria Ave",
    "sg:city":"Margate",
    "sg:classifiers":[
        {
            "category":"Wholesale",
            "subcategory":"Photographic Equipment",
            "type":"Manufacturing & Wholesale Goods"
        }
    ],
    "sg:phone":"+61 7 3284 1588",
    "sg:postcode":"4019",
    "sg:province":"QLD",
    "sg:tags":[
        "wholesaler",
        "mfrs",
        "supply"
    ],
    "wof:name":"F 16 Camera Service",
    "wof:placetype":"venue"
},
  "geometry": {"coordinates":[153.10025024399999,-27.2372970581],"type":"Point"}
}