{
  "type": "Feature",
  "properties": {
    "addr:full":"12 Parraweena Ave Baulkham Hills NSW 2153",
    "addr:housenumber":"12",
    "addr:postcode":"2153",
    "addr:street":"Parraweena Ave",
    "iso:country":"AU",
    "sg:address":"12 Parraweena Ave",
    "sg:city":"Baulkham Hills",
    "sg:classifiers":[
        {
            "category":"Communications",
            "type":"Services"
        }
    ],
    "sg:phone":"+61 2 9686 2065",
    "sg:postcode":"2153",
    "sg:province":"NSW",
    "sg:tags":[
        "public",
        "system",
        "address"
    ],
    "wof:name":"Wireless Sound",
    "wof:placetype":"venue"
},
  "geometry": {"coordinates":[151.002197266,-33.7535476685],"type":"Point"}
}