{
  "type": "Feature",
  "properties": {
    "iso:country":"AU",
    "sg:address":"122 Rea St",
    "sg:city":"Shepparton",
    "sg:classifiers":[
        {
            "category":"Professional",
            "subcategory":"Accounting & Tax Preparation",
            "type":"Services"
        }
    ],
    "sg:phone":"+61 3 5822 4283",
    "sg:postcode":"3630",
    "sg:province":"VIC",
    "sg:tags":[
        "accountant",
        "auditor"
    ],
    "wof:name":"Woolstencroft R",
    "wof:placetype":"venue"
},
  "geometry": {"coordinates":[145.41392517099999,-36.3717956543],"type":"Point"}
}