{
  "type": "Feature",
  "properties": {
    "addr:full":"Unit 5 Warton & Spencer Rds Huntingdale WA 6110",
    "addr:postcode":"6110",
    "iso:country":"AU",
    "sg:address":"Unit 5 Warton & Spencer Rds",
    "sg:city":"Huntingdale",
    "sg:classifiers":[
        {
            "category":"Health Services",
            "subcategory":"Doctor",
            "type":"Services"
        }
    ],
    "sg:phone":"+61 8 9439 2406",
    "sg:postcode":"6110",
    "sg:province":"WA",
    "sg:tags":[
        "medical",
        "practitioner"
    ],
    "wof:name":"Uniradiology",
    "wof:placetype":"venue"
},
  "geometry": {"coordinates":[115.953468323,-32.081577301],"type":"Point"}
}