{
  "type": "Feature",
  "properties": {
    "addr:full":"Pelton St Aspley QLD 4034",
    "addr:postcode":"4034",
    "addr:street":"Pelton St",
    "iso:country":"AU",
    "sg:address":"Pelton St",
    "sg:city":"Aspley",
    "sg:classifiers":[
        {
            "category":"Building & Trades",
            "subcategory":"Construction",
            "type":"Services"
        }
    ],
    "sg:phone":"+61 419 669 501",
    "sg:postcode":"4034",
    "sg:province":"QLD",
    "sg:tags":[
        "contractor"
    ],
    "wof:name":"Sherry Building Services",
    "wof:placetype":"venue"
},
  "geometry": {"coordinates":[153.02032500000001,-27.366486],"type":"Point"}
}