{
  "type": "Feature",
  "properties": {
    "addr:full":"9 - 11 Fraser St Shepparton VIC 3630",
    "addr:housenumber":"11",
    "addr:postcode":"3630",
    "addr:street":"9;Fraser St",
    "iso:country":"AU",
    "sg:address":"9 - 11 Fraser St",
    "sg:city":"Shepparton",
    "sg:classifiers":[
        {
            "category":"Education",
            "subcategory":"Vocational School",
            "type":"Public Place"
        }
    ],
    "sg:phone":"+61 3 5822 0499",
    "sg:postcode":"3630",
    "sg:province":"VIC",
    "sg:tags":[
        "beauty"
    ],
    "wof:name":"The Australian College Of Hair Design & Beauty The",
    "wof:placetype":"venue"
},
  "geometry": {"coordinates":[145.39987182600001,-36.3800048828],"type":"Point"}
}