{
  "type": "Feature",
  "properties": {
    "iso:country":"AU",
    "sg:address":"32 Rowan St",
    "sg:city":"Wangaratta",
    "sg:classifiers":[
        {
            "category":"Real Estate",
            "subcategory":"Real Estate Services",
            "type":"Services"
        }
    ],
    "sg:phone":"+61 3 5722 3144",
    "sg:postcode":"3677",
    "sg:province":"VIC",
    "sg:tags":[
        "valuer"
    ],
    "wof:name":"Alistair W. Male & Associates",
    "wof:placetype":"venue"
},
  "geometry": {"coordinates":[146.322143555,-36.3525161743],"type":"Point"}
}