{
  "type": "Feature",
  "properties": {
    "iso:country":"AU",
    "sg:address":"350 Middleton Rd",
    "sg:city":"Albany",
    "sg:classifiers":[
        {
            "category":"Fast Food",
            "type":"Food & Drink"
        }
    ],
    "sg:phone":"+61 8 9841 5490",
    "sg:postcode":"6330",
    "sg:province":"WA",
    "sg:tags":[
        "away",
        "take"
    ],
    "wof:name":"Rodellas Fish&#039;N&#039;Chips",
    "wof:placetype":"venue"
},
  "geometry": {"coordinates":[117.884429932,-35.0200576782],"type":"Point"}
}