{
  "type": "Feature",
  "properties": {
    "addr:full":"Factory 1/ 25 Brett Drv Carrum Downs VIC 3201",
    "addr:housenumber":"/ 25",
    "addr:postcode":"3201",
    "addr:street":"Brett Drv",
    "iso:country":"AU",
    "sg:address":"Factory 1/ 25 Brett Drv",
    "sg:city":"Carrum Downs",
    "sg:classifiers":[
        {
            "category":"Wholesale",
            "subcategory":"Chemicals & Plastics",
            "type":"Manufacturing & Wholesale Goods"
        }
    ],
    "sg:phone":"+61 3 9775 0786",
    "sg:postcode":"3201",
    "sg:province":"VIC",
    "sg:tags":[
        "bag"
    ],
    "wof:name":"Siupak Plastic Bags",
    "wof:placetype":"venue"
},
  "geometry": {"coordinates":[145.16329999999999,-38.095512],"type":"Point"}
}