{
  "type": "Feature",
  "properties": {
    "addr:full":"198 Mona Vale Rd St Ives NSW 2075",
    "addr:housenumber":"198",
    "addr:postcode":"2075",
    "addr:street":"Mona Vale Rd",
    "iso:country":"AU",
    "sg:address":"198 Mona Vale Rd",
    "sg:city":"St Ives",
    "sg:classifiers":[
        {
            "category":"Health Services",
            "subcategory":"Dentist",
            "type":"Services"
        }
    ],
    "sg:phone":"+61 2 9440 8352",
    "sg:postcode":"2075",
    "sg:province":"NSW",
    "wof:name":"Golchin K",
    "wof:placetype":"venue"
},
  "geometry": {"coordinates":[151.160690308,-33.7299880981],"type":"Point"}
}