{
  "type": "Feature",
  "properties": {
    "iso:country":"AU",
    "sg:address":"Palmyra Primary School 60 McKimmie Rd",
    "sg:city":"Palmyra",
    "sg:classifiers":[
        {
            "category":"Education",
            "subcategory":"School",
            "type":"Public Place"
        }
    ],
    "sg:phone":"+61 8 9339 1911",
    "sg:postcode":"6157",
    "sg:province":"WA",
    "sg:tags":[
        "state",
        "except",
        "nsw"
    ],
    "wof:name":"Schools Government (Public)",
    "wof:placetype":"venue"
},
  "geometry": {"coordinates":[115.784508,-32.042717],"type":"Point"}
}