{
  "type": "Feature",
  "properties": {
    "addr:full":"Shop 1066 Westfield North Lakes QLD 4509",
    "addr:housenumber":"1066",
    "addr:postcode":"4509",
    "addr:street":"Westfield",
    "iso:country":"AU",
    "sg:address":"Shop 1066 Westfield",
    "sg:city":"North Lakes",
    "sg:classifiers":[
        {
            "category":"Health Services",
            "subcategory":"Optometrist",
            "type":"Services"
        }
    ],
    "sg:phone":"+61 7 3480 5600",
    "sg:postcode":"4509",
    "sg:province":"QLD",
    "wof:name":"Medispecs Optical North Lakes",
    "wof:placetype":"venue"
},
  "geometry": {"coordinates":[153.024124145,-27.2228527069],"type":"Point"}
}