{
  "type": "Feature",
  "properties": {
    "addr:full":"24 Goorawahl Av La Perouse NSW 2036",
    "addr:housenumber":"24",
    "addr:postcode":"2036",
    "addr:street":"Goorawahl Av La",
    "iso:country":"AU",
    "sg:address":"24 Goorawahl Av",
    "sg:city":"La Perouse",
    "sg:classifiers":[
        {
            "category":"Real Estate",
            "subcategory":"Surveying",
            "type":"Services"
        }
    ],
    "sg:phone":"+61 2 9345 5408",
    "sg:postcode":"2036",
    "sg:province":"NSW",
    "sg:tags":[
        "surveyor",
        "marine",
        "cargo"
    ],
    "wof:name":"Marine Tech Australia",
    "wof:placetype":"venue"
},
  "geometry": {"coordinates":[151.23283386200001,-33.9878540039],"type":"Point"}
}