{
  "type": "Feature",
  "properties": {
    "iso:country":"AU",
    "sg:address":"125 Maxwell St",
    "sg:city":"Penrith South",
    "sg:classifiers":[
        {
            "category":"Health Services",
            "subcategory":"Dentist",
            "type":"Services"
        }
    ],
    "sg:phone":"+61 2 4732 2588",
    "sg:postcode":"2750",
    "sg:province":"NSW",
    "wof:name":"Drs Margaret Phoebe & Mary Foley",
    "wof:placetype":"venue"
},
  "geometry": {"coordinates":[150.69325256400001,-33.7730331421],"type":"Point"}
}