{
  "type": "Feature",
  "properties": {
    "addr:full":"9 Jones Rd Cannonvale QLD 4802",
    "addr:housenumber":"9",
    "addr:postcode":"4802",
    "addr:street":"Jones Rd",
    "iso:country":"AU",
    "sg:address":"9 Jones Rd",
    "sg:city":"Cannonvale",
    "sg:classifiers":[
        {
            "category":"Recreation",
            "type":"Entertainment"
        }
    ],
    "sg:phone":"+61 7 4946 6869",
    "sg:postcode":"4802",
    "sg:province":"QLD",
    "sg:tags":[
        "recreational",
        "diver"
    ],
    "wof:name":"Downunder Dive",
    "wof:placetype":"venue"
},
  "geometry": {"coordinates":[148.706466675,-20.2737064362],"type":"Point"}
}