{
  "type": "Feature",
  "properties": {
    "iso:country":"AU",
    "sg:address":"31 Alexander Ave",
    "sg:city":"Taren Point",
    "sg:classifiers":[
        {
            "category":"Wholesale",
            "subcategory":"Painting Supplies",
            "type":"Manufacturing & Wholesale Goods"
        }
    ],
    "sg:phone":"+61 2 9530 8119",
    "sg:postcode":"2229",
    "sg:province":"NSW",
    "sg:tags":[
        "product",
        "cleaning"
    ],
    "wof:name":"Hubble Cleaning Products",
    "wof:placetype":"venue"
},
  "geometry": {"coordinates":[151.123809814,-34.0212593079],"type":"Point"}
}