{
  "type": "Feature",
  "properties": {
    "addr:full":"Unit 1 99 Bell St Preston VIC 3072",
    "addr:housenumber":"99",
    "addr:postcode":"3072",
    "addr:street":"Bell St",
    "iso:country":"AU",
    "sg:address":"Unit 1 99 Bell St",
    "sg:city":"Preston",
    "sg:classifiers":[
        {
            "category":"Recreation",
            "subcategory":"Amusement Park",
            "type":"Entertainment"
        }
    ],
    "sg:phone":"+61 3 9416 9444",
    "sg:postcode":"3072",
    "sg:province":"VIC",
    "wof:name":"Breakers 8 Ball Centre",
    "wof:placetype":"venue"
},
  "geometry": {"coordinates":[145.02331543,-37.7477264404],"type":"Point"}
}