{
  "type": "Feature",
  "properties": {
    "addr:full":"96 Jubilee Hwy East Mt Gambier SA 5290",
    "addr:housenumber":"96",
    "addr:postcode":"5290",
    "addr:street":"Jubilee Hwy East Mt",
    "iso:country":"AU",
    "sg:address":"96 Jubilee Hwy East",
    "sg:city":"Mt Gambier",
    "sg:classifiers":[
        {
            "category":"Travel",
            "subcategory":"Hotels & Motels",
            "type":"Entertainment"
        }
    ],
    "sg:phone":"+61 8 8725 4311",
    "sg:postcode":"5290",
    "sg:province":"SA",
    "wof:name":"Limestone Coast Motor Inn",
    "wof:placetype":"venue"
},
  "geometry": {"coordinates":[140.79832500000001,-37.833092],"type":"Point"}
}