{
  "type": "Feature",
  "properties": {
    "addr:full":"301 Bobs Creek Rd Herons Creek NSW 2443",
    "addr:housenumber":"301",
    "addr:postcode":"2443",
    "addr:street":"Bobs Creek Rd",
    "iso:country":"AU",
    "sg:address":"301 Bobs Creek Rd",
    "sg:city":"Herons Creek",
    "sg:classifiers":[
        {
            "category":"Building & Trades",
            "subcategory":"Construction",
            "type":"Services"
        }
    ],
    "sg:phone":"+61 2 6585 7066",
    "sg:postcode":"2443",
    "sg:province":"NSW",
    "sg:tags":[
        "earth",
        "excavating",
        "moving",
        "contractor"
    ],
    "wof:name":"David Latham Earthworks",
    "wof:placetype":"venue"
},
  "geometry": {"coordinates":[152.73173499999999,-31.57785],"type":"Point"}
}