{
  "type": "Feature",
  "properties": {
    "iso:country":"AU",
    "sg:address":"23 Seabeach Ave",
    "sg:city":"Mermaid Beach",
    "sg:classifiers":[
        {
            "category":"Airport",
            "subcategory":"International",
            "type":"Transportation"
        }
    ],
    "sg:phone":"+61 7 5572 5807",
    "sg:postcode":"4218",
    "sg:province":"QLD",
    "sg:tags":[
        "diving",
        "commercial"
    ],
    "wof:name":"Tropic Diving Services",
    "wof:placetype":"venue"
},
  "geometry": {"coordinates":[153.43698120100001,-28.048620224],"type":"Point"}
}