{
  "type": "Feature",
  "properties": {
    "iso:country":"AU",
    "sg:address":"10 Radford Crt",
    "sg:city":"Hoppers Crossing",
    "sg:classifiers":[
        {
            "category":"Building & Trades",
            "subcategory":"Plumbing",
            "type":"Services"
        }
    ],
    "sg:phone":"+61 3 9749 1884",
    "sg:postcode":"3029",
    "sg:province":"VIC",
    "sg:tags":[
        "plumber",
        "gasfitters"
    ],
    "wof:name":"Atkin N",
    "wof:placetype":"venue"
},
  "geometry": {"coordinates":[144.692917,-37.859303],"type":"Point"}
}