{
  "type": "Feature",
  "properties": {
    "iso:country":"AU",
    "sg:address":"1A Hall St",
    "sg:city":"Brunswick",
    "sg:classifiers":[
        {
            "category":"Building & Trades",
            "subcategory":"Construction",
            "type":"Services"
        }
    ],
    "sg:phone":"+61 418 543 788",
    "sg:postcode":"3056",
    "sg:province":"VIC",
    "sg:tags":[
        "contractor"
    ],
    "wof:name":"Rodin Nominees Pty Ltd",
    "wof:placetype":"venue"
},
  "geometry": {"coordinates":[144.95046997099999,-37.7626228333],"type":"Point"}
}