{
  "type": "Feature",
  "properties": {
    "addr:full":"229 Chapel St Prahran VIC 3181",
    "addr:housenumber":"229",
    "addr:postcode":"3181",
    "addr:street":"Chapel St",
    "iso:country":"AU",
    "sg:address":"229 Chapel St",
    "sg:city":"Prahran",
    "sg:classifiers":[
        {
            "category":"Bars & Pubs",
            "subcategory":"Nightclub",
            "type":"Food & Drink"
        }
    ],
    "sg:phone":"+61 3 9521 5985",
    "sg:postcode":"3181",
    "sg:province":"VIC",
    "sg:tags":[
        "discotheque"
    ],
    "wof:name":"Revolver Upstairs",
    "wof:placetype":"venue"
},
  "geometry": {"coordinates":[144.99339294399999,-37.8505439758],"type":"Point"}
}