{
  "type": "Feature",
  "properties": {
    "iso:country":"AU",
    "sg:address":"26 Pamela Pde",
    "sg:city":"Leonay",
    "sg:classifiers":[
        {
            "category":"Utilities",
            "subcategory":"Electric",
            "type":"Services"
        }
    ],
    "sg:phone":"+61 1300 304 991",
    "sg:postcode":"2750",
    "sg:province":"NSW",
    "sg:tags":[
        "electrical",
        "contractor"
    ],
    "wof:name":"M & K Dunn Electrical",
    "wof:placetype":"venue"
},
  "geometry": {"coordinates":[150.65467834500001,-33.7633018494],"type":"Point"}
}