{
  "type": "Feature",
  "properties": {
    "addr:full":"Kingsgrove Rd Kingsgrove NSW 2208",
    "addr:postcode":"2208",
    "addr:street":"Kingsgrove Rd",
    "iso:country":"AU",
    "sg:address":"Kingsgrove Rd",
    "sg:city":"Kingsgrove",
    "sg:classifiers":[
        {
            "category":"Retail",
            "subcategory":"Auto Repair",
            "type":"Services"
        }
    ],
    "sg:phone":"+61 2 9502 1609",
    "sg:postcode":"2208",
    "sg:province":"NSW",
    "sg:tags":[
        "beater",
        "painter",
        "panel"
    ],
    "wof:name":"G.T. Body Repairs",
    "wof:placetype":"venue"
},
  "geometry": {"coordinates":[151.100784,-33.939339],"type":"Point"}
}