{
  "type": "Feature",
  "properties": {
    "iso:country":"AU",
    "sg:address":"932 Victoria Rd",
    "sg:city":"West Ryde",
    "sg:classifiers":[
        {
            "category":"Retail",
            "subcategory":"Auto Repair",
            "type":"Services"
        }
    ],
    "sg:phone":"+61 2 9808 3033",
    "sg:postcode":"2114",
    "sg:province":"NSW",
    "sg:tags":[
        "beater",
        "painter",
        "panel"
    ],
    "wof:name":"West Ryde Smash Repairs Pty Ltd",
    "wof:placetype":"venue"
},
  "geometry": {"coordinates":[151.08804321299999,-33.8078155518],"type":"Point"}
}