{
  "type": "Feature",
  "properties": {
    "addr:full":"Scobies Business Centre 380 Cambridge St Mornington TAS 7018",
    "addr:housenumber":"380",
    "addr:postcode":"7018",
    "addr:street":"Cambridge St",
    "iso:country":"AU",
    "sg:address":"Scobies Business Centre 380 Cambridge St",
    "sg:city":"Mornington",
    "sg:classifiers":[
        {
            "category":"Building & Trades",
            "subcategory":"Construction",
            "type":"Services"
        }
    ],
    "sg:phone":"+61 1300 789 987",
    "sg:postcode":"7018",
    "sg:province":"TAS",
    "sg:tags":[
        "roof"
    ],
    "wof:name":"Select Roofing + Guttering Pty Ltd",
    "wof:placetype":"venue"
},
  "geometry": {"coordinates":[147.40110778799999,-42.8560791016],"type":"Point"}
}