{
  "type": "Feature",
  "properties": {
    "addr:full":"Unit 2/ 5 Vuko Pl Warriewood NSW 2102",
    "addr:housenumber":"5",
    "addr:postcode":"2102",
    "addr:street":"Vuko Pl",
    "iso:country":"AU",
    "sg:address":"Unit 2/ 5 Vuko Pl",
    "sg:city":"Warriewood",
    "sg:classifiers":[
        {
            "category":"Professional",
            "subcategory":"Computer Services",
            "type":"Services"
        }
    ],
    "sg:phone":"+61 2 9986 0135",
    "sg:postcode":"2102",
    "sg:province":"NSW",
    "sg:tags":[
        "equipment",
        "networking",
        "installation"
    ],
    "wof:name":"Island Computer Services Pty Ltd",
    "wof:placetype":"venue"
},
  "geometry": {"coordinates":[151.301727,-33.692806],"type":"Point"}
}