{
  "type": "Feature",
  "properties": {
    "iso:country":"AU",
    "sg:address":"423 Campbell St",
    "sg:city":"Swan Hill",
    "sg:classifiers":[
        {
            "category":"Retail",
            "subcategory":"Event Space",
            "type":"Services"
        }
    ],
    "sg:phone":"+61 3 5032 2017",
    "sg:postcode":"3585",
    "sg:province":"VIC",
    "sg:tags":[
        "function",
        "organiser"
    ],
    "wof:name":"Carriages Restaurant",
    "wof:placetype":"venue"
},
  "geometry": {"coordinates":[143.56221,-35.347866],"type":"Point"}
}