{
  "type": "Feature",
  "properties": {
    "iso:country":"AU",
    "sg:address":"248 Grand Junction Rd",
    "sg:city":"Athol Park",
    "sg:classifiers":[
        {
            "category":"Farming",
            "subcategory":"Fish & Marine Products",
            "type":"Manufacturing & Wholesale Goods"
        }
    ],
    "sg:phone":"+61 8 8341 1538",
    "sg:postcode":"5012",
    "sg:province":"SA",
    "sg:tags":[
        "production",
        "seafood",
        "processing"
    ],
    "wof:name":"Fish Factory Famazos Pty Ltd The",
    "wof:placetype":"venue"
},
  "geometry": {"coordinates":[138.540283203,-34.8510894775],"type":"Point"}
}