{
  "type": "Feature",
  "properties": {
    "addr:full":"219 Beach St Frankston East VIC 3199",
    "addr:housenumber":"219",
    "addr:postcode":"3199",
    "addr:street":"Beach St",
    "iso:country":"AU",
    "sg:address":"219 Beach St",
    "sg:city":"Frankston East",
    "sg:classifiers":[
        {
            "category":"Professional",
            "subcategory":"Accounting & Tax Preparation",
            "type":"Services"
        }
    ],
    "sg:phone":"+61 3 9776 5100",
    "sg:postcode":"3199",
    "sg:province":"VIC",
    "sg:tags":[
        "accountant",
        "auditor"
    ],
    "wof:name":"Gilbert Marc P A",
    "wof:placetype":"venue"
},
  "geometry": {"coordinates":[145.14523315400001,-38.1483192444],"type":"Point"}
}