{
  "type": "Feature",
  "properties": {
    "iso:country":"AU",
    "sg:address":"10 Kenoma Pl",
    "sg:city":"Arndell Park",
    "sg:classifiers":[
        {
            "category":"Building & Trades",
            "subcategory":"Construction",
            "type":"Services"
        }
    ],
    "sg:phone":"+61 2 9672 7055",
    "sg:postcode":"2148",
    "sg:province":"NSW",
    "sg:tags":[
        "contractor"
    ],
    "wof:name":"Allcastle Homes Pty Ltd",
    "wof:placetype":"venue"
},
  "geometry": {"coordinates":[150.88206481899999,-33.789730072],"type":"Point"}
}