{
  "type": "Feature",
  "properties": {
    "addr:full":"Shop 2/ 826 David St Albury NSW 2640",
    "addr:housenumber":"shop 2 / 826",
    "addr:postcode":"2640",
    "addr:street":"David St",
    "iso:country":"AU",
    "sg:address":"Shop 2/ 826 David St",
    "sg:city":"Albury",
    "sg:classifiers":[
        {
            "category":"Wholesale",
            "subcategory":"Medical Equipment & Supplies",
            "type":"Manufacturing & Wholesale Goods"
        }
    ],
    "sg:phone":"+61 2 6041 1037",
    "sg:postcode":"2640",
    "sg:province":"NSW",
    "sg:tags":[
        "aid",
        "care",
        "health",
        "home"
    ],
    "wof:name":"Lifestyle & Rehab",
    "wof:placetype":"venue"
},
  "geometry": {"coordinates":[146.92460632300001,-36.0648193359],"type":"Point"}
}