{
  "type": "Feature",
  "properties": {
    "addr:full":"PO Box 1352 Noosaville QLD 4566",
    "addr:postcode":"4566",
    "iso:country":"AU",
    "sg:address":"PO Box 1352",
    "sg:city":"Noosaville",
    "sg:classifiers":[
        {
            "category":"Real Estate",
            "subcategory":"Architect",
            "type":"Services"
        }
    ],
    "sg:phone":"+61 7 5474 0877",
    "sg:postcode":"4566",
    "sg:province":"QLD",
    "wof:name":"Middap & Ditchfield Pty Ltd Architects",
    "wof:placetype":"venue"
},
  "geometry": {"coordinates":[153.05047607399999,-26.4029693604],"type":"Point"}
}