{
  "type": "Feature",
  "properties": {
    "addr:full":"60 Smith St Merewether NSW 2291",
    "addr:housenumber":"60",
    "addr:postcode":"2291",
    "addr:street":"Smith St",
    "iso:country":"AU",
    "sg:address":"60 Smith St",
    "sg:city":"Merewether",
    "sg:classifiers":[
        {
            "category":"Health Services",
            "subcategory":"Health Practitioner",
            "type":"Services"
        }
    ],
    "sg:phone":"+61 2 4962 2225",
    "sg:postcode":"2291",
    "sg:province":"NSW",
    "sg:tags":[
        "naturopath"
    ],
    "wof:name":"Cullen Jane",
    "wof:placetype":"venue"
},
  "geometry": {"coordinates":[151.754440308,-32.9375801086],"type":"Point"}
}