{
  "type": "Feature",
  "properties": {
    "iso:country":"AU",
    "sg:address":"Level 46, Governor Phillip Twr 1 Farrer Pl",
    "sg:city":"Sydney",
    "sg:classifiers":[
        {
            "category":"Professional",
            "subcategory":"Computer Services",
            "type":"Services"
        }
    ],
    "sg:phone":"+61 2 9947 9788",
    "sg:postcode":"2000",
    "sg:province":"NSW",
    "sg:tags":[
        "package",
        "software"
    ],
    "wof:name":"Software of Excellence Australia",
    "wof:placetype":"venue"
},
  "geometry": {"coordinates":[151.21072387699999,-33.8643341064],"type":"Point"}
}