{
  "type": "Feature",
  "properties": {
    "addr:full":"235 North West Arm Rd Grays Point NSW 2232",
    "addr:housenumber":"235",
    "addr:postcode":"2232",
    "addr:street":"North West Arm Rd",
    "iso:country":"AU",
    "sg:address":"235 North West Arm Rd",
    "sg:city":"Grays Point",
    "sg:classifiers":[
        {
            "category":"Organizations",
            "subcategory":"Non-profit Organization",
            "type":"Services"
        }
    ],
    "sg:phone":"+61 2 9525 6238",
    "sg:postcode":"2232",
    "sg:province":"NSW",
    "sg:tags":[
        "support",
        "disability",
        "organisation"
    ],
    "wof:name":"Prader-Willi Syndrome Association of NSW (Aust Inc)",
    "wof:placetype":"venue"
},
  "geometry": {"coordinates":[151.076293945,-34.0557365417],"type":"Point"}
}