{
  "type": "Feature",
  "properties": {
    "iso:country":"AU",
    "sg:address":"246 Loganlea Rd",
    "sg:city":"Meadowbrook",
    "sg:classifiers":[
        {
            "category":"Autos & Motor Vehicles",
            "subcategory":"Fuel & Gas Station",
            "type":"Retail Goods"
        }
    ],
    "sg:phone":"+61 7 3805 8149",
    "sg:postcode":"4131",
    "sg:province":"QLD",
    "wof:name":"United Loganlea",
    "wof:placetype":"venue"
},
  "geometry": {"coordinates":[153.13923645,-27.6679000854],"type":"Point"}
}