{
  "type": "Feature",
  "properties": {
    "iso:country":"AU",
    "sg:address":"3 Delton St",
    "sg:city":"Kingston",
    "sg:classifiers":[
        {
            "category":"Professional",
            "type":"Services"
        }
    ],
    "sg:phone":"+61 7 3139 0303",
    "sg:postcode":"4114",
    "sg:province":"QLD",
    "sg:tags":[
        "transport"
    ],
    "wof:name":"Firstchoice Logistics",
    "wof:placetype":"venue"
},
  "geometry": {"coordinates":[153.133499145,-27.6525726318],"type":"Point"}
}