{
  "type": "Feature",
  "properties": {
    "addr:full":"13/ 14 Rothcote Crt Burleigh Heads QLD 4220",
    "addr:housenumber":"13 / 14",
    "addr:postcode":"4220",
    "addr:street":"Rothcote Crt",
    "iso:country":"AU",
    "sg:address":"13/ 14 Rothcote Crt",
    "sg:city":"Burleigh Heads",
    "sg:classifiers":[
        {
            "category":"Manufacturing",
            "subcategory":"Signs",
            "type":"Manufacturing & Wholesale Goods"
        }
    ],
    "sg:phone":"+61 7 5522 1618",
    "sg:postcode":"4220",
    "sg:province":"QLD",
    "sg:tags":[
        "traffic",
        "safety"
    ],
    "wof:name":"Safe Signs Australia",
    "wof:placetype":"venue"
},
  "geometry": {"coordinates":[153.418334961,-28.1018295288],"type":"Point"}
}