{
  "type": "Feature",
  "properties": {
    "iso:country":"AU",
    "sg:address":"PO Box 3493",
    "sg:city":"Success",
    "sg:classifiers":[
        {
            "category":"Personal",
            "subcategory":"Beauty Salon",
            "type":"Services"
        }
    ],
    "sg:phone":"+61 409 376 066",
    "sg:postcode":"6964",
    "sg:province":"WA",
    "sg:tags":[
        "supply",
        "artist",
        "make-up"
    ],
    "wof:name":"Unforgettable Artistry",
    "wof:placetype":"venue"
},
  "geometry": {"coordinates":[115.846428,-32.15659],"type":"Point"}
}