{
  "type": "Feature",
  "properties": {
    "iso:country":"AU",
    "sg:address":"9 Kamerunga Rd",
    "sg:city":"Stratford",
    "sg:classifiers":[
        {
            "category":"Fast Food",
            "type":"Food & Drink"
        }
    ],
    "sg:phone":"+61 7 4055 2716",
    "sg:postcode":"4870",
    "sg:province":"QLD",
    "sg:tags":[
        "away",
        "take"
    ],
    "wof:name":"Pepper Box Cafe",
    "wof:placetype":"venue"
},
  "geometry": {"coordinates":[145.73321533199999,-16.8754711151],"type":"Point"}
}