{
  "type": "Feature",
  "properties": {
    "addr:full":"7 Fox St Wagga Wagga NSW 2650",
    "addr:housenumber":"7",
    "addr:postcode":"2650",
    "addr:street":"Fox St",
    "iso:country":"AU",
    "sg:address":"7 Fox St",
    "sg:city":"Wagga Wagga",
    "sg:classifiers":[
        {
            "category":"Wholesale",
            "subcategory":"Music Publishers",
            "type":"Manufacturing & Wholesale Goods"
        }
    ],
    "sg:phone":"+61 2 6921 5618",
    "sg:postcode":"2650",
    "sg:province":"NSW",
    "sg:tags":[
        "wholesaler",
        "dvd",
        "mfrs",
        "cd"
    ],
    "wof:name":"Tabbita Record Company",
    "wof:placetype":"venue"
},
  "geometry": {"coordinates":[147.36453247099999,-35.118106842],"type":"Point"}
}