{
  "type": "Feature",
  "properties": {
    "iso:country":"AU",
    "sg:address":"2 Stonehaven Pl",
    "sg:city":"Derwent Park",
    "sg:classifiers":[
        {
            "category":"Commercial Area",
            "type":"Public Place"
        }
    ],
    "sg:phone":"+61 3 6272 4121",
    "sg:postcode":"7009",
    "sg:province":"TAS",
    "sg:tags":[
        "heavy",
        "carrier"
    ],
    "wof:name":"Wilderness Transport",
    "wof:placetype":"venue"
},
  "geometry": {"coordinates":[147.29745483400001,-42.8318519592],"type":"Point"}
}