{
  "type": "Feature",
  "properties": {
    "addr:full":"Unit 3/ 30 McCotter St Acacia Ridge QLD 4110",
    "addr:postcode":"4110",
    "addr:street":"30 Mccotter St",
    "iso:country":"AU",
    "sg:address":"Unit 3/ 30 McCotter St",
    "sg:city":"Acacia Ridge",
    "sg:classifiers":[
        {
            "category":"Communications",
            "subcategory":"Television Station",
            "type":"Services"
        }
    ],
    "sg:phone":"+61 7 3272 3691",
    "sg:postcode":"4110",
    "sg:province":"QLD",
    "sg:tags":[
        "wholesaler",
        "wire",
        "mfrs",
        "electric",
        "cable"
    ],
    "wof:name":"ElectCables",
    "wof:placetype":"venue"
},
  "geometry": {"coordinates":[153.03448486299999,-27.597026825],"type":"Point"}
}