{
  "type": "Feature",
  "properties": {
    "addr:full":"79a Queen St Norwood SA 5067",
    "addr:housenumber":"79a",
    "addr:postcode":"5067",
    "addr:street":"Queen St",
    "iso:country":"AU",
    "sg:address":"79a Queen St",
    "sg:city":"Norwood",
    "sg:classifiers":[
        {
            "category":"Building & Trades",
            "subcategory":"Construction",
            "type":"Services"
        }
    ],
    "sg:phone":"+61 409 401 802",
    "sg:postcode":"5067",
    "sg:province":"SA",
    "sg:tags":[
        "contractor"
    ],
    "wof:name":"Crawford Digby",
    "wof:placetype":"venue"
},
  "geometry": {"coordinates":[138.63885498100001,-34.9233322144],"type":"Point"}
}