{
  "type": "Feature",
  "properties": {
    "addr:full":"17 Phillip St Tanunda SA 5352",
    "addr:housenumber":"17",
    "addr:postcode":"5352",
    "addr:street":"Phillip St",
    "iso:country":"AU",
    "sg:address":"17 Phillip St",
    "sg:city":"Tanunda",
    "sg:classifiers":[
        {
            "category":"Retail",
            "subcategory":"Auto Rental",
            "type":"Services"
        }
    ],
    "sg:phone":"+61 8 8563 2258",
    "sg:postcode":"5352",
    "sg:province":"SA",
    "sg:tags":[
        "chauffeur",
        "car",
        "hire",
        "driven",
        "limousine"
    ],
    "wof:name":"Barossa & Light Chauffeured Limousine Service",
    "wof:placetype":"venue"
},
  "geometry": {"coordinates":[138.97529602,-34.515335083],"type":"Point"}
}