{
  "type": "Feature",
  "properties": {
    "addr:full":"24 Windsor Rd Croydon VIC 3136",
    "addr:housenumber":"24",
    "addr:postcode":"3136",
    "addr:street":"Windsor Rd",
    "iso:country":"AU",
    "sg:address":"24 Windsor Rd",
    "sg:city":"Croydon",
    "sg:classifiers":[
        {
            "category":"Retail",
            "subcategory":"Storage",
            "type":"Services"
        }
    ],
    "sg:phone":"+61 3 9761 5323",
    "sg:postcode":"3136",
    "sg:province":"VIC",
    "sg:tags":[
        "removal",
        "furniture"
    ],
    "wof:name":"Maroondah Removals & Storage",
    "wof:placetype":"venue"
},
  "geometry": {"coordinates":[145.285766602,-37.7941741943],"type":"Point"}
}