{
  "type": "Feature",
  "properties": {
    "iso:country":"AU",
    "sg:address":"Shop 4, Yeppoon Central Shopping Centre, 17 James St",
    "sg:city":"Yeppoon",
    "sg:classifiers":[
        {
            "category":"Personal",
            "subcategory":"Beauty Salon",
            "type":"Services"
        }
    ],
    "sg:phone":"+61 7 4939 4855",
    "sg:postcode":"4703",
    "sg:province":"QLD",
    "sg:tags":[
        "hairdresser"
    ],
    "wof:name":"Cydelle Jensen Hairdressing",
    "wof:placetype":"venue"
},
  "geometry": {"coordinates":[150.745803833,-23.1288757324],"type":"Point"}
}