{
  "type": "Feature",
  "properties": {
    "addr:full":"21 Bareena St Jindalee QLD 4074",
    "addr:housenumber":"21",
    "addr:postcode":"4074",
    "addr:street":"Bareena St",
    "iso:country":"AU",
    "sg:address":"21 Bareena St",
    "sg:city":"Jindalee",
    "sg:classifiers":[
        {
            "category":"Professional",
            "subcategory":"Detective & Security Services",
            "type":"Services"
        }
    ],
    "sg:phone":"+61 7 3376 5845",
    "sg:postcode":"4074",
    "sg:province":"QLD",
    "sg:tags":[
        "consultant",
        "system"
    ],
    "wof:name":"Centronics Security",
    "wof:placetype":"venue"
},
  "geometry": {"coordinates":[152.93107605,-27.531835556],"type":"Point"}
}