{
  "type": "Feature",
  "properties": {
    "addr:full":"89 Macquarie St Hobart TAS 7000",
    "addr:housenumber":"89",
    "addr:postcode":"7000",
    "addr:street":"Macquarie St",
    "iso:country":"AU",
    "sg:address":"89 Macquarie St",
    "sg:city":"Hobart",
    "sg:classifiers":[
        {
            "category":"Health Services",
            "subcategory":"Doctor",
            "type":"Services"
        }
    ],
    "sg:phone":"+61 3 6234 1735",
    "sg:postcode":"7000",
    "sg:province":"TAS",
    "sg:tags":[
        "medical",
        "practitioner"
    ],
    "wof:name":"Campbell Sam",
    "wof:placetype":"venue"
},
  "geometry": {"coordinates":[147.33076477,-42.8821182251],"type":"Point"}
}