{
  "type": "Feature",
  "properties": {
    "addr:full":"31 Cairns St Kangaroo Point QLD 4169",
    "addr:housenumber":"31",
    "addr:postcode":"4169",
    "addr:street":"Cairns St",
    "iso:country":"AU",
    "sg:address":"31 Cairns St",
    "sg:city":"Kangaroo Point",
    "sg:classifiers":[
        {
            "category":"Banks & Credit Unions",
            "subcategory":"Investment Brokerage",
            "type":"Services"
        }
    ],
    "sg:phone":"+61 7 3217 4667",
    "sg:postcode":"4169",
    "sg:province":"QLD",
    "sg:tags":[
        "finance",
        "broker"
    ],
    "wof:name":"Discover Finance",
    "wof:placetype":"venue"
},
  "geometry": {"coordinates":[153.03712463400001,-27.4733886719],"type":"Point"}
}