{
  "type": "Feature",
  "properties": {
    "iso:country":"AU",
    "sg:address":"Unit 21, 634 Mitcham Rd",
    "sg:city":"Vermont",
    "sg:classifiers":[
        {
            "category":"Shopping",
            "type":"Retail Goods"
        }
    ],
    "sg:phone":"+61 3 9872 3886",
    "sg:postcode":"3133",
    "sg:province":"VIC",
    "sg:tags":[
        "new age",
        "product"
    ],
    "wof:name":"Crystal & Jewellery Warehouse",
    "wof:placetype":"venue"
},
  "geometry": {"coordinates":[145.19483947800001,-37.8323249817],"type":"Point"}
}