{
  "type": "Feature",
  "properties": {
    "addr:full":"136 Sydney Rd Fairlight NSW 2094",
    "addr:housenumber":"136",
    "addr:postcode":"2094",
    "addr:street":"Sydney Rd",
    "iso:country":"AU",
    "sg:address":"136 Sydney Rd",
    "sg:city":"Fairlight",
    "sg:classifiers":[
        {
            "category":"Retail",
            "subcategory":"Self-service Laundry",
            "type":"Services"
        }
    ],
    "sg:phone":"+61 2 9949 2531",
    "sg:postcode":"2094",
    "sg:province":"NSW",
    "wof:name":"Fairlight Laundromat",
    "wof:placetype":"venue"
},
  "geometry": {"coordinates":[151.276245117,-33.7957115173],"type":"Point"}
}