{
  "type": "Feature",
  "properties": {
    "addr:full":"4 Patricia Drv Mildura VIC 3500",
    "addr:housenumber":"4",
    "addr:postcode":"3500",
    "addr:street":"Patricia Drv",
    "iso:country":"AU",
    "sg:address":"4 Patricia Drv",
    "sg:city":"Mildura",
    "sg:classifiers":[
        {
            "category":"Organizations",
            "subcategory":"Non-profit Organization",
            "type":"Services"
        }
    ],
    "sg:phone":"+61 3 5023 3549",
    "sg:postcode":"3500",
    "sg:province":"VIC",
    "sg:tags":[
        "support",
        "disability",
        "organisation"
    ],
    "wof:name":"Headway Sunraysia",
    "wof:placetype":"venue"
},
  "geometry": {"coordinates":[142.136550903,-34.1971359253],"type":"Point"}
}