{
  "type": "Feature",
  "properties": {
    "iso:country":"AU",
    "sg:address":"Ste 101B, 2 Holden St",
    "sg:city":"Ashfield",
    "sg:classifiers":[
        {
            "category":"Health Services",
            "subcategory":"Health Practitioner",
            "type":"Services"
        }
    ],
    "sg:phone":"+61 2 9716 0609",
    "sg:postcode":"2131",
    "sg:province":"NSW",
    "sg:tags":[
        "physiotherapist"
    ],
    "wof:name":"Brandt's Physiotherapy Clinic",
    "wof:placetype":"venue"
},
  "geometry": {"coordinates":[151.126052856,-33.8897209167],"type":"Point"}
}