{
  "type": "Feature",
  "properties": {
    "addr:full":"PO Box 3123 Mt Gambier SA 5290",
    "addr:postcode":"5290",
    "iso:country":"AU",
    "sg:address":"PO Box 3123",
    "sg:city":"Mt Gambier",
    "sg:classifiers":[
        {
            "category":"Building & Trades",
            "subcategory":"Construction",
            "type":"Services"
        }
    ],
    "sg:phone":"+61 8 8723 1130",
    "sg:postcode":"5290",
    "sg:province":"SA",
    "sg:tags":[
        "fencing",
        "contractor"
    ],
    "wof:name":"Interline",
    "wof:placetype":"venue"
},
  "geometry": {"coordinates":[140.78329500000001,-37.826321],"type":"Point"}
}