{
  "type": "Feature",
  "properties": {
    "addr:full":"6 Murragong Ave Bundoora VIC 3083",
    "addr:housenumber":"6",
    "addr:postcode":"3083",
    "addr:street":"Murragong Ave",
    "iso:country":"AU",
    "sg:address":"6 Murragong Ave",
    "sg:city":"Bundoora",
    "sg:classifiers":[
        {
            "category":"Professional",
            "subcategory":"Computer Services",
            "type":"Services"
        }
    ],
    "sg:phone":"+61 411 172 915",
    "sg:postcode":"3083",
    "sg:province":"VIC",
    "sg:tags":[
        "consultant",
        "system"
    ],
    "wof:name":"Telmark Computing Pty Ltd",
    "wof:placetype":"venue"
},
  "geometry": {"coordinates":[145.067016602,-37.703163147],"type":"Point"}
}