{
  "type": "Feature",
  "properties": {
    "iso:country":"AU",
    "sg:address":"Shop 8 Glasshouse Country Centre, Beerwah Pde",
    "sg:city":"Beerwah",
    "sg:classifiers":[
        {
            "category":"Health Services",
            "subcategory":"Health Practitioner",
            "type":"Services"
        }
    ],
    "sg:phone":"+61 7 5494 0028",
    "sg:postcode":"4519",
    "sg:province":"QLD",
    "sg:tags":[
        "acupuncture"
    ],
    "wof:name":"Leonard Erlinda",
    "wof:placetype":"venue"
},
  "geometry": {"coordinates":[152.958954,-26.857759],"type":"Point"}
}