{
  "type": "Feature",
  "properties": {
    "addr:full":"34 Toongahra Cct Goonellabah NSW 2480",
    "addr:housenumber":"34",
    "addr:postcode":"2480",
    "addr:street":"Toongahra Cct",
    "iso:country":"AU",
    "sg:address":"34 Toongahra Cct",
    "sg:city":"Goonellabah",
    "sg:classifiers":[
        {
            "category":"Home & Garden",
            "subcategory":"Hardware",
            "type":"Retail Goods"
        }
    ],
    "sg:phone":"+61 1800 074 577",
    "sg:postcode":"2480",
    "sg:province":"NSW",
    "sg:tags":[
        "product",
        "treatment",
        "floor"
    ],
    "sg:website":"http://www.slipsafe.com.au",
    "wof:name":"Slipsafe Northern Rivers",
    "wof:placetype":"venue"
},
  "geometry": {"coordinates":[153.35293579099999,-28.8129749298],"type":"Point"}
}