{
  "type": "Feature",
  "properties": {
    "iso:country":"AU",
    "sg:address":"PO Box 348",
    "sg:city":"Avalon Beach",
    "sg:classifiers":[
        {
            "category":"Building & Trades",
            "subcategory":"Cleaning & Sanitation",
            "type":"Services"
        }
    ],
    "sg:phone":"+61 2 9114 6911",
    "sg:postcode":"2107",
    "sg:province":"NSW",
    "sg:tags":[
        "window"
    ],
    "wof:name":"New View Window Cleaning",
    "wof:placetype":"venue"
},
  "geometry": {"coordinates":[151.33059692399999,-33.6363182068],"type":"Point"}
}