{
  "type": "Feature",
  "properties": {
    "addr:full":"22 Queen St Fremantle WA 6160",
    "addr:housenumber":"22",
    "addr:postcode":"6160",
    "addr:street":"Queen St",
    "iso:country":"AU",
    "sg:address":"22 Queen St",
    "sg:city":"Fremantle",
    "sg:classifiers":[
        {
            "category":"Personal",
            "subcategory":"Day Spa",
            "type":"Services"
        }
    ],
    "sg:phone":"+61 8 9430 6800",
    "sg:postcode":"6160",
    "sg:province":"WA",
    "wof:name":"Keturah Spa + Skin Care + Hair",
    "wof:placetype":"venue"
},
  "geometry": {"coordinates":[115.74839,-32.053131],"type":"Point"}
}