{
  "type": "Feature",
  "properties": {
    "iso:country":"AU",
    "sg:address":"12 Havelock St",
    "sg:city":"Dunolly",
    "sg:classifiers":[
        {
            "category":"Health Services",
            "subcategory":"Doctor",
            "type":"Services"
        }
    ],
    "sg:phone":"+61 3 5468 1850",
    "sg:postcode":"3472",
    "sg:province":"VIC",
    "sg:tags":[
        "medical",
        "practitioner"
    ],
    "wof:name":"Brady P J",
    "wof:placetype":"venue"
},
  "geometry": {"coordinates":[143.735275269,-36.8566055298],"type":"Point"}
}