{
  "type": "Feature",
  "properties": {
    "iso:country":"AU",
    "sg:address":"166 Main St",
    "sg:city":"Pakenham",
    "sg:classifiers":[
        {
            "category":"Shopping",
            "subcategory":"Clothing, Apparel, & Fashions",
            "type":"Retail Goods"
        }
    ],
    "sg:phone":"+61 3 5941 4343",
    "sg:postcode":"3810",
    "sg:province":"VIC",
    "sg:tags":[
        "recycled",
        "clothing"
    ],
    "wof:name":"Brotherhood Of St Laurence",
    "wof:placetype":"venue"
},
  "geometry": {"coordinates":[145.483337,-38.078918],"type":"Point"}
}