{
  "type": "Feature",
  "properties": {
    "addr:full":"PO Box 171 South Hobart TAS 7004",
    "addr:postcode":"7004",
    "iso:country":"AU",
    "sg:address":"PO Box 171",
    "sg:city":"South Hobart",
    "sg:classifiers":[
        {
            "category":"Shopping",
            "subcategory":"Crafts & Fabrics",
            "type":"Retail Goods"
        }
    ],
    "sg:phone":"+61 3 6224 3043",
    "sg:postcode":"7004",
    "sg:province":"TAS",
    "sg:tags":[
        "adhesive"
    ],
    "wof:name":"Fixco Plus Adhesive",
    "wof:placetype":"venue"
},
  "geometry": {"coordinates":[147.31483459500001,-42.895160675],"type":"Point"}
}