{
  "type": "Feature",
  "properties": {
    "addr:full":"21 Vivian Ave Mont Albert North VIC 3129",
    "addr:housenumber":"21",
    "addr:postcode":"3129",
    "addr:street":"Vivian Ave",
    "iso:country":"AU",
    "sg:address":"21 Vivian Ave",
    "sg:city":"Mont Albert North",
    "sg:classifiers":[
        {
            "category":"Professional",
            "subcategory":"Secretarial Services",
            "type":"Services"
        }
    ],
    "sg:phone":"+61 417 224 658",
    "sg:postcode":"3129",
    "sg:province":"VIC",
    "sg:tags":[
        "typing"
    ],
    "wof:name":"Emphatic Enterprises",
    "wof:placetype":"venue"
},
  "geometry": {"coordinates":[145.11224365199999,-37.7984046936],"type":"Point"}
}