{
  "type": "Feature",
  "properties": {
    "iso:country":"AU",
    "sg:address":"PO Box 77",
    "sg:city":"Punchbowl",
    "sg:classifiers":[
        {
            "category":"Manufacturing",
            "subcategory":"Tools & Machinery",
            "type":"Manufacturing & Wholesale Goods"
        }
    ],
    "sg:phone":"+61 418 222 202",
    "sg:postcode":"2196",
    "sg:province":"NSW",
    "sg:tags":[
        "earth",
        "excavating",
        "moving",
        "equipment"
    ],
    "wof:name":"Pro Demolition & Excavation",
    "wof:placetype":"venue"
},
  "geometry": {"coordinates":[151.053741,-33.92585],"type":"Point"}
}