{
  "type": "Feature",
  "properties": {
    "addr:full":"606 Stanley St South Brisbane QLD 4101",
    "addr:housenumber":"606",
    "addr:postcode":"4101",
    "addr:street":"Stanley St",
    "iso:country":"AU",
    "sg:address":"606 Stanley St",
    "sg:city":"South Brisbane",
    "sg:classifiers":[
        {
            "category":"Real Estate",
            "subcategory":"Architect",
            "type":"Services"
        }
    ],
    "sg:phone":"+61 7 3844 0553",
    "sg:postcode":"4101",
    "sg:province":"QLD",
    "wof:name":"Wiltshire Stevens Pty Ltd",
    "wof:placetype":"venue"
},
  "geometry": {"coordinates":[153.02961730999999,-27.4853858948],"type":"Point"}
}