{
  "type": "Feature",
  "properties": {
    "iso:country":"AU",
    "sg:address":"3 Thomas Pl",
    "sg:city":"MacGregor",
    "sg:classifiers":[
        {
            "category":"Personal",
            "subcategory":"Nail Salon",
            "type":"Services"
        }
    ],
    "sg:phone":"+61 2 6255 1951",
    "sg:postcode":"2615",
    "sg:province":"ACT",
    "sg:tags":[
        "artificial"
    ],
    "wof:name":"Affections",
    "wof:placetype":"venue"
},
  "geometry": {"coordinates":[149.01002502399999,-35.2104301453],"type":"Point"}
}