{
  "type": "Feature",
  "properties": {
    "iso:country":"AU",
    "sg:address":"PO Box 250",
    "sg:city":"Manilla",
    "sg:classifiers":[
        {
            "category":"Building & Trades",
            "subcategory":"Plumbing",
            "type":"Services"
        }
    ],
    "sg:phone":"+61 2 6785 1558",
    "sg:postcode":"2346",
    "sg:province":"NSW",
    "sg:tags":[
        "plumber",
        "gasfitters"
    ],
    "wof:name":"Thrift Plumbing Services",
    "wof:placetype":"venue"
},
  "geometry": {"coordinates":[150.71905517600001,-30.7519607544],"type":"Point"}
}