{
  "type": "Feature",
  "properties": {
    "iso:country":"AU",
    "sg:address":"PO Box 623",
    "sg:city":"Samford",
    "sg:classifiers":[
        {
            "category":"Professional",
            "subcategory":"Employment Agencies",
            "type":"Services"
        }
    ],
    "sg:phone":"+61 7 3354 1981",
    "sg:postcode":"4520",
    "sg:province":"QLD",
    "wof:name":"Classic Recruitment",
    "wof:placetype":"venue"
},
  "geometry": {"coordinates":[152.88664199999999,-27.373671],"type":"Point"}
}