{
  "type": "Feature",
  "properties": {
    "addr:full":"Suite 2a 32 Fisher Rd Dee Why NSW 2099",
    "addr:housenumber":"32",
    "addr:postcode":"2099",
    "addr:street":"Fisher Rd",
    "iso:country":"AU",
    "sg:address":"Suite 2a 32 Fisher Rd",
    "sg:city":"Dee Why",
    "sg:classifiers":[
        {
            "category":"Professional",
            "subcategory":"Art Services",
            "type":"Services"
        }
    ],
    "sg:phone":"+61 2 9984 0955",
    "sg:postcode":"2099",
    "sg:province":"NSW",
    "sg:tags":[
        "interior",
        "decorator"
    ],
    "wof:name":"Blue Nexus designs",
    "wof:placetype":"venue"
},
  "geometry": {"coordinates":[151.28483581500001,-33.7524642944],"type":"Point"}
}