{
  "type": "Feature",
  "properties": {
    "addr:full":"Tower St Leonora WA 6438",
    "addr:postcode":"6438",
    "addr:street":"Tower St",
    "iso:country":"AU",
    "sg:address":"Tower St",
    "sg:city":"Leonora",
    "sg:classifiers":[
        {
            "category":"Travel",
            "subcategory":"Hotels & Motels",
            "type":"Entertainment"
        }
    ],
    "sg:phone":"+61 8 9037 6168",
    "sg:postcode":"6438",
    "sg:province":"WA",
    "sg:tags":[
        "accommodation"
    ],
    "wof:name":"White House Hotel",
    "wof:placetype":"venue"
},
  "geometry": {"coordinates":[121.330848694,-28.8841381073],"type":"Point"}
}