{
  "type": "Feature",
  "properties": {
    "addr:full":"16 Freighter Ave Toowoomba QLD 4350",
    "addr:housenumber":"16",
    "addr:postcode":"4350",
    "addr:street":"Freighter Ave",
    "iso:country":"AU",
    "sg:address":"16 Freighter Ave",
    "sg:city":"Toowoomba",
    "sg:classifiers":[
        {
            "category":"Building & Trades",
            "subcategory":"Pest Control",
            "type":"Services"
        }
    ],
    "sg:phone":"+61 1800 814 199",
    "sg:postcode":"4350",
    "sg:province":"QLD",
    "wof:name":"Bug Shop The",
    "wof:placetype":"venue"
},
  "geometry": {"coordinates":[151.90914900000001,-27.538782],"type":"Point"}
}