{
  "type": "Feature",
  "properties": {
    "addr:full":"Unit 3/ 84 Grange Rd Welland SA 5007",
    "addr:housenumber":"84",
    "addr:postcode":"5007",
    "addr:street":"Grange Rd",
    "iso:country":"AU",
    "sg:address":"Unit 3/ 84 Grange Rd",
    "sg:city":"Welland",
    "sg:classifiers":[
        {
            "category":"Building & Trades",
            "subcategory":"Cleaning & Sanitation",
            "type":"Services"
        }
    ],
    "sg:phone":"+61 1800 004 234",
    "sg:postcode":"5007",
    "sg:province":"SA",
    "sg:tags":[
        "industrial",
        "commercial",
        "contractor"
    ],
    "wof:name":"N&B Cleaning Services",
    "wof:placetype":"venue"
},
  "geometry": {"coordinates":[138.558303833,-34.9042892456],"type":"Point"}
}