{
  "type": "Feature",
  "properties": {
    "iso:country":"AU",
    "sg:address":"Unit 5, 18 Redland Drv",
    "sg:city":"Mitcham",
    "sg:classifiers":[
        {
            "category":"Professional",
            "subcategory":"Research",
            "type":"Services"
        }
    ],
    "sg:phone":"+61 3 9874 1988",
    "sg:postcode":"3132",
    "sg:province":"VIC",
    "sg:tags":[
        "analyst"
    ],
    "wof:name":"Leeder Consulting Pty Ltd",
    "wof:placetype":"venue"
},
  "geometry": {"coordinates":[145.191162109,-37.8301467896],"type":"Point"}
}