{
  "type": "Feature",
  "properties": {
    "addr:full":"163 Aitken St Williamstown VIC 3016",
    "addr:housenumber":"163",
    "addr:postcode":"3016",
    "addr:street":"Aitken St",
    "iso:country":"AU",
    "sg:address":"163 Aitken St",
    "sg:city":"Williamstown",
    "sg:classifiers":[
        {
            "category":"Professional",
            "subcategory":"Art Services",
            "type":"Services"
        }
    ],
    "sg:phone":"+61 3 9399 9468",
    "sg:postcode":"3016",
    "sg:province":"VIC",
    "sg:tags":[
        "graphic",
        "designer"
    ],
    "wof:name":"Blank T",
    "wof:placetype":"venue"
},
  "geometry": {"coordinates":[144.90057373100001,-37.8599128723],"type":"Point"}
}