{
  "type": "Feature",
  "properties": {
    "iso:country":"AU",
    "sg:address":"16 Frederick St",
    "sg:city":"Gosford",
    "sg:classifiers":[
        {
            "category":"Education",
            "subcategory":"Dance Studio",
            "type":"Public Place"
        }
    ],
    "sg:phone":"+61 2 4324 1716",
    "sg:postcode":"2250",
    "sg:province":"NSW",
    "sg:tags":[
        "venue",
        "tuition"
    ],
    "wof:name":"Janelle & Keryl Smith School of Dance",
    "wof:placetype":"venue"
},
  "geometry": {"coordinates":[151.34556579599999,-33.4392700195],"type":"Point"}
}