{
  "type": "Feature",
  "properties": {
    "addr:full":"Unit 1 60 Northlink Pl Virginia QLD 4014",
    "addr:housenumber":"60",
    "addr:postcode":"4014",
    "addr:street":"Northlink Pl",
    "iso:country":"AU",
    "sg:address":"Unit 1 60 Northlink Pl",
    "sg:city":"Virginia",
    "sg:classifiers":[
        {
            "category":"Professional",
            "type":"Services"
        }
    ],
    "sg:phone":"+61 7 3260 7774",
    "sg:postcode":"4014",
    "sg:province":"QLD",
    "sg:tags":[
        "control",
        "equipment",
        "traffic"
    ],
    "wof:name":"Evolution Traffic Control",
    "wof:placetype":"venue"
},
  "geometry": {"coordinates":[153.07035827600001,-27.3849086761],"type":"Point"}
}