{
  "type": "Feature",
  "properties": {
    "addr:full":"3 Albany St Fyshwick ACT 2609",
    "addr:housenumber":"3",
    "addr:postcode":"2609",
    "addr:street":"Albany St",
    "iso:country":"AU",
    "sg:address":"3 Albany St",
    "sg:city":"Fyshwick",
    "sg:classifiers":[
        {
            "category":"Retail",
            "subcategory":"Auto Repair",
            "type":"Services"
        }
    ],
    "sg:phone":"+61 2 6239 1477",
    "sg:postcode":"2609",
    "sg:province":"ACT",
    "sg:tags":[
        "automotive",
        "air conditioning"
    ],
    "wof:name":"Barrett Bros. Smash Repairs",
    "wof:placetype":"venue"
},
  "geometry": {"coordinates":[149.18101501500001,-35.3272399902],"type":"Point"}
}