{
  "type": "Feature",
  "properties": {
    "iso:country":"AU",
    "sg:address":"Dudgeon's La",
    "sg:city":"Bangalow",
    "sg:classifiers":[
        {
            "category":"Wholesale",
            "subcategory":"Farm Supplies",
            "type":"Manufacturing & Wholesale Goods"
        }
    ],
    "sg:phone":"+61 2 6687 1452",
    "sg:postcode":"2479",
    "sg:province":"NSW",
    "sg:tags":[
        "equipment"
    ],
    "wof:name":"Eden Country Store",
    "wof:placetype":"venue"
},
  "geometry": {"coordinates":[153.50747680699999,-28.6969985962],"type":"Point"}
}