{
  "type": "Feature",
  "properties": {
    "addr:full":"Shop 102, Morayfield Shopng Cntr, Morayfield Rd Morayfield QLD 4506",
    "addr:housenumber":"102",
    "addr:postcode":"4506",
    "addr:street":"Morayfield Shopng Cntr Morayfield Rd",
    "iso:country":"AU",
    "sg:address":"Shop 102, Morayfield Shopng Cntr, Morayfield Rd",
    "sg:city":"Morayfield",
    "sg:classifiers":[
        {
            "category":"Shopping",
            "subcategory":"Mobile Phones",
            "type":"Retail Goods"
        }
    ],
    "sg:phone":"+61 7 5499 4266",
    "sg:postcode":"4506",
    "sg:province":"QLD",
    "sg:tags":[
        "telephone",
        "accessory"
    ],
    "wof:name":"Vodafone",
    "wof:placetype":"venue"
},
  "geometry": {"coordinates":[152.95010375999999,-27.1104488373],"type":"Point"}
}