{
  "type": "Feature",
  "properties": {
    "addr:full":"185 Tenth Ave Austral NSW 2171",
    "addr:housenumber":"185",
    "addr:postcode":"2171",
    "addr:street":"Tenth Ave Austral",
    "iso:country":"AU",
    "sg:address":"185 Tenth Ave",
    "sg:city":"Austral",
    "sg:classifiers":[
        {
            "category":"Utilities",
            "subcategory":"Refuse",
            "type":"Services"
        }
    ],
    "sg:phone":"+61 2 9606 0008",
    "sg:postcode":"2171",
    "sg:province":"NSW",
    "sg:tags":[
        "disposal",
        "reduction",
        "waste"
    ],
    "wof:name":"Alley Cat Waste Disposal",
    "wof:placetype":"venue"
},
  "geometry": {"coordinates":[150.80393981899999,-33.9318237305],"type":"Point"}
}