{
  "type": "Feature",
  "properties": {
    "iso:country":"AU",
    "sg:address":"1 Scott Ave",
    "sg:city":"Dungog",
    "sg:classifiers":[
        {
            "category":"Autos & Motor Vehicles",
            "subcategory":"Fuel & Gas Station",
            "type":"Retail Goods"
        }
    ],
    "sg:phone":"+61 2 4992 1923",
    "sg:postcode":"2420",
    "sg:province":"NSW",
    "wof:name":"Dowlings Service Station",
    "wof:placetype":"venue"
},
  "geometry": {"coordinates":[151.746826,-32.399055],"type":"Point"}
}