{
  "type": "Feature",
  "properties": {
    "addr:full":"11 Bertram Rd Caversham WA 6055",
    "addr:housenumber":"11",
    "addr:postcode":"6055",
    "addr:street":"Bertram Rd",
    "iso:country":"AU",
    "sg:address":"11 Bertram Rd",
    "sg:city":"Caversham",
    "sg:classifiers":[
        {
            "category":"Farming",
            "subcategory":"Vineyard",
            "type":"Manufacturing & Wholesale Goods"
        }
    ],
    "sg:phone":"+61 8 9250 1119",
    "sg:postcode":"6055",
    "sg:province":"WA",
    "sg:tags":[
        "winery"
    ],
    "wof:name":"Fish Tail Wines",
    "wof:placetype":"venue"
},
  "geometry": {"coordinates":[115.981934,-31.871473],"type":"Point"}
}