{
  "type": "Feature",
  "properties": {
    "iso:country":"AU",
    "sg:address":"U2/ 24 Elouera Cl",
    "sg:city":"Lilli Pilli",
    "sg:classifiers":[
        {
            "category":"Real Estate",
            "subcategory":"Real Estate Agent",
            "type":"Services"
        }
    ],
    "sg:phone":"+61 2 4471 2409",
    "sg:postcode":"2536",
    "sg:province":"NSW",
    "wof:name":"Tom & Melissa Franzen",
    "wof:placetype":"venue"
},
  "geometry": {"coordinates":[150.229736328,-35.7766494751],"type":"Point"}
}