{
  "type": "Feature",
  "properties": {
    "addr:full":"PO Box 948 New Farm QLD 4005",
    "addr:postcode":"4005",
    "iso:country":"AU",
    "sg:address":"PO Box 948",
    "sg:city":"New Farm",
    "sg:classifiers":[
        {
            "category":"Building & Trades",
            "subcategory":"Construction",
            "type":"Services"
        }
    ],
    "sg:phone":"+61 438 374 029",
    "sg:postcode":"4005",
    "sg:province":"QLD",
    "sg:tags":[
        "earth",
        "excavating",
        "moving",
        "contractor"
    ],
    "wof:name":"Adkra Earthworks Pty Ltd",
    "wof:placetype":"venue"
},
  "geometry": {"coordinates":[153.04450988799999,-27.4659004211],"type":"Point"}
}