{
  "type": "Feature",
  "properties": {
    "addr:full":"Shop 252A Macquarie St Westfield Shoppingtown Liverpool NSW 2170",
    "addr:housenumber":"252a",
    "addr:postcode":"2170",
    "addr:street":"Macquarie St",
    "iso:country":"AU",
    "sg:address":"Shop 252A Macquarie St Westfield Shoppingtown",
    "sg:city":"Liverpool",
    "sg:classifiers":[
        {
            "category":"Fast Food",
            "type":"Food & Drink"
        }
    ],
    "sg:phone":"+61 2 9602 3210",
    "sg:postcode":"2170",
    "sg:province":"NSW",
    "sg:tags":[
        "away",
        "take"
    ],
    "wof:name":"Red Rooster",
    "wof:placetype":"venue"
},
  "geometry": {"coordinates":[150.92376709000001,-33.9232177734],"type":"Point"}
}