{
  "type": "Feature",
  "properties": {
    "iso:country":"AU",
    "sg:address":"10 - 12 Essington St",
    "sg:city":"Mitchell",
    "sg:classifiers":[
        {
            "category":"Retail",
            "subcategory":"Storage",
            "type":"Services"
        }
    ],
    "sg:phone":"+61 2 6241 6170",
    "sg:postcode":"2911",
    "sg:province":"ACT",
    "wof:name":"Oz Stor",
    "wof:placetype":"venue"
},
  "geometry": {"coordinates":[149.14146423299999,-35.2138328552],"type":"Point"}
}