{
  "type": "Feature",
  "properties": {
    "iso:country":"AU",
    "sg:address":"PO Box 1805",
    "sg:city":"Gawler",
    "sg:classifiers":[
        {
            "category":"Shopping",
            "subcategory":"Discount & Variety Stores",
            "type":"Retail Goods"
        }
    ],
    "sg:phone":"+61 8 8524 2158",
    "sg:postcode":"5118",
    "sg:province":"SA",
    "sg:tags":[
        "mixing",
        "equipment",
        "industrial"
    ],
    "wof:name":"Drum-Mates",
    "wof:placetype":"venue"
},
  "geometry": {"coordinates":[138.728226,-34.596329],"type":"Point"}
}