{
  "type": "Feature",
  "properties": {
    "iso:country":"AU",
    "sg:address":"U9/ 29 Adam St",
    "sg:city":"Hindmarsh",
    "sg:classifiers":[
        {
            "category":"Building & Trades",
            "subcategory":"Construction",
            "type":"Services"
        }
    ],
    "sg:phone":"+61 8 8340 3232",
    "sg:postcode":"5007",
    "sg:province":"SA",
    "sg:tags":[
        "stonework",
        "stone",
        "mason"
    ],
    "wof:name":"Granite & Marble Solutions Hindmarsh",
    "wof:placetype":"venue"
},
  "geometry": {"coordinates":[138.566604614,-34.9104576111],"type":"Point"}
}