{
  "type": "Feature",
  "properties": {
    "iso:country":"AU",
    "sg:address":"38- 40 Howard St",
    "sg:city":"North Melbourne",
    "sg:classifiers":[
        {
            "category":"Building & Trades",
            "subcategory":"Construction",
            "type":"Services"
        }
    ],
    "sg:phone":"+61 3 9326 9944",
    "sg:postcode":"3051",
    "sg:province":"VIC",
    "sg:tags":[
        "window",
        "aluminium"
    ],
    "sg:website":"http://www.austview.com.au",
    "wof:name":"Austview- Sashless Windows",
    "wof:placetype":"venue"
},
  "geometry": {"coordinates":[144.95408630399999,-37.8042602539],"type":"Point"}
}