{
  "type": "Feature",
  "properties": {
    "addr:full":"Cnr Drake St & Montague Rd West End (Brisbane) QLD 4101",
    "addr:postcode":"4101",
    "addr:street":"Cnr Drake St & Montague Rd",
    "iso:country":"AU",
    "sg:address":"Cnr Drake St & Montague Rd",
    "sg:city":"West End (Brisbane)",
    "sg:classifiers":[
        {
            "category":"Education",
            "subcategory":"Music School",
            "type":"Public Place"
        }
    ],
    "sg:phone":"+61 7 3844 5599",
    "sg:postcode":"4101",
    "sg:province":"QLD",
    "sg:tags":[
        "choir",
        "bands",
        "orchestra"
    ],
    "wof:name":"Queensland Philharmonic Orchestra",
    "wof:placetype":"venue"
},
  "geometry": {"coordinates":[153.00257873499999,-27.4867763519],"type":"Point"}
}