{
  "type": "Feature",
  "properties": {
    "addr:full":"Level 7, 100 George St Parramatta NSW 2150",
    "addr:housenumber":"100",
    "addr:postcode":"2150",
    "addr:street":"George St",
    "iso:country":"AU",
    "sg:address":"Level 7, 100 George St",
    "sg:city":"Parramatta",
    "sg:classifiers":[
        {
            "category":"Real Estate",
            "subcategory":"Real Estate Agent",
            "type":"Services"
        }
    ],
    "sg:phone":"+61 2 9891 1200",
    "sg:postcode":"2150",
    "sg:province":"NSW",
    "wof:name":"Chesterton International",
    "wof:placetype":"venue"
},
  "geometry": {"coordinates":[150.97657775900001,-33.8501548767],"type":"Point"}
}