{
  "type": "Feature",
  "properties": {
    "iso:country":"AU",
    "sg:address":"3/ 205 Melbourne Rd",
    "sg:city":"Wodonga",
    "sg:classifiers":[
        {
            "category":"Building & Trades",
            "subcategory":"Construction",
            "type":"Services"
        }
    ],
    "sg:phone":"+61 2 6056 6455",
    "sg:postcode":"3690",
    "sg:province":"VIC",
    "sg:tags":[
        "pool",
        "swimming"
    ],
    "wof:name":"North East Pools & Spas",
    "wof:placetype":"venue"
},
  "geometry": {"coordinates":[146.86436462399999,-36.1122779846],"type":"Point"}
}