{
  "type": "Feature",
  "properties": {
    "addr:full":"3 Errard St North Ballarat VIC 3350",
    "addr:housenumber":"3",
    "addr:postcode":"3350",
    "addr:street":"Errard St North",
    "iso:country":"AU",
    "sg:address":"3 Errard St",
    "sg:city":"North Ballarat",
    "sg:classifiers":[
        {
            "category":"Travel",
            "subcategory":"Hotels & Motels",
            "type":"Entertainment"
        }
    ],
    "sg:phone":"+61 418 503 820",
    "sg:postcode":"3350",
    "sg:province":"VIC",
    "sg:tags":[
        "accommodation"
    ],
    "wof:name":"Tulips Executive Apartments",
    "wof:placetype":"venue"
},
  "geometry": {"coordinates":[143.848816,-37.560608],"type":"Point"}
}