{
  "type": "Feature",
  "properties": {
    "addr:full":"Level 2, 491-495 King St West Melbourne VIC 3003",
    "addr:housenumber":"491-495",
    "addr:postcode":"3003",
    "addr:street":"King St",
    "iso:country":"AU",
    "sg:address":"Level 2, 491-495 King St",
    "sg:city":"West Melbourne",
    "sg:classifiers":[
        {
            "category":"Organizations",
            "subcategory":"Membership Organization",
            "type":"Services"
        }
    ],
    "sg:phone":"+61 3 9329 2622",
    "sg:postcode":"3003",
    "sg:province":"VIC",
    "sg:tags":[
        "support",
        "health",
        "organisation"
    ],
    "wof:name":"Asthma Foundations Australia",
    "wof:placetype":"venue"
},
  "geometry": {"coordinates":[144.95164489699999,-37.8082771301],"type":"Point"}
}