{
  "type": "Feature",
  "properties": {
    "iso:country":"AU",
    "sg:address":"11 Fairview Pl",
    "sg:city":"Bridgeman Downs",
    "sg:classifiers":[
        {
            "category":"Social Services",
            "subcategory":"Retirement Home",
            "type":"Services"
        }
    ],
    "sg:phone":"+61 7 3353 0544",
    "sg:postcode":"4035",
    "sg:province":"QLD",
    "sg:tags":[
        "environmental",
        "consultant",
        "pollution"
    ],
    "wof:name":"Packer Environmental Services Pty Ltd",
    "wof:placetype":"venue"
},
  "geometry": {"coordinates":[152.98277300000001,-27.360258],"type":"Point"}
}