{
  "type": "Feature",
  "properties": {
    "addr:full":"40 Princes Hwy Beaconsfield VIC 3807",
    "addr:housenumber":"40",
    "addr:postcode":"3807",
    "addr:street":"Princes Hwy",
    "iso:country":"AU",
    "sg:address":"40 Princes Hwy",
    "sg:city":"Beaconsfield",
    "sg:classifiers":[
        {
            "category":"Retail",
            "subcategory":"Repair Shop",
            "type":"Services"
        }
    ],
    "sg:phone":"+61 1300 651 730",
    "sg:postcode":"3807",
    "sg:province":"VIC",
    "sg:tags":[
        "leadlights"
    ],
    "sg:website":"http://www.paterleadlights.com.au",
    "wof:name":"Pater Leadlights Pty Ltd",
    "wof:placetype":"venue"
},
  "geometry": {"coordinates":[145.36827087399999,-38.0465087891],"type":"Point"}
}