{
  "type": "Feature",
  "properties": {
    "addr:full":"7- 11 Northern Hwy Echuca VIC 3564",
    "addr:housenumber":"11",
    "addr:postcode":"3564",
    "addr:street":"7;Northern Hwy",
    "iso:country":"AU",
    "sg:address":"7- 11 Northern Hwy",
    "sg:city":"Echuca",
    "sg:classifiers":[
        {
            "category":"Shopping",
            "subcategory":"Mobile Phones",
            "type":"Retail Goods"
        }
    ],
    "sg:phone":"+61 3 5482 1010",
    "sg:postcode":"3564",
    "sg:province":"VIC",
    "sg:tags":[
        "telephone",
        "accessory"
    ],
    "wof:name":"Livewires Car Audio",
    "wof:placetype":"venue"
},
  "geometry": {"coordinates":[144.729537964,-36.1413764954],"type":"Point"}
}