{
  "type": "Feature",
  "properties": {
    "iso:country":"AU",
    "sg:address":"2- 13 Indy Crt",
    "sg:city":"Nerang",
    "sg:classifiers":[
        {
            "category":"Retail",
            "subcategory":"Auto Repair",
            "type":"Services"
        }
    ],
    "sg:phone":"+61 1300 722 522",
    "sg:postcode":"4211",
    "sg:province":"QLD",
    "sg:tags":[
        "repairer",
        "motor",
        "engineer"
    ],
    "sg:website":"http://www.surefixmechanical.com.au",
    "wof:name":"Surefix Mechanical",
    "wof:placetype":"venue"
},
  "geometry": {"coordinates":[153.34771728499999,-28.011259079],"type":"Point"}
}