{
  "type": "Feature",
  "properties": {
    "iso:country":"AU",
    "sg:address":"401 Sussex St",
    "sg:city":"Sydney",
    "sg:classifiers":[
        {
            "category":"Social Services",
            "subcategory":"Adult Care",
            "type":"Services"
        }
    ],
    "sg:phone":"+61 401 973 527",
    "sg:postcode":"2000",
    "sg:province":"NSW",
    "sg:tags":[
        "towing"
    ],
    "wof:name":"Affordable Sydney Towing",
    "wof:placetype":"venue"
},
  "geometry": {"coordinates":[151.20463562,-33.8782501221],"type":"Point"}
}