{
  "type": "Feature",
  "properties": {
    "iso:country":"AU",
    "sg:address":"Suite 27 Level 1 7 Narabang Way",
    "sg:city":"Belrose",
    "sg:classifiers":[
        {
            "category":"Professional",
            "subcategory":"Business Services",
            "type":"Services"
        }
    ],
    "sg:phone":"+61 2 9844 5496",
    "sg:postcode":"2085",
    "sg:province":"NSW",
    "sg:tags":[
        "consultant",
        "system"
    ],
    "wof:name":"Monitor Business Machines Pty Ltd",
    "wof:placetype":"venue"
},
  "geometry": {"coordinates":[151.212356567,-33.70520401],"type":"Point"}
}