{
  "type": "Feature",
  "properties": {
    "iso:country":"AU",
    "sg:address":"7 Rawson St",
    "sg:city":"Auburn",
    "sg:classifiers":[
        {
            "category":"Retail",
            "subcategory":"Auto Rental",
            "type":"Services"
        }
    ],
    "sg:phone":"+61 2 9315 5860",
    "sg:postcode":"2144",
    "sg:province":"NSW",
    "sg:tags":[
        "car",
        "hire",
        "minibus"
    ],
    "wof:name":"Red Spot Rentals",
    "wof:placetype":"venue"
},
  "geometry": {"coordinates":[151.03456115700001,-33.8497238159],"type":"Point"}
}