{
  "type": "Feature",
  "properties": {
    "addr:full":"Craigmont St Tarragindi QLD 4121",
    "addr:postcode":"4121",
    "addr:street":"Craigmont St",
    "iso:country":"AU",
    "sg:address":"Craigmont St",
    "sg:city":"Tarragindi",
    "sg:classifiers":[
        {
            "category":"Professional",
            "subcategory":"Detective & Security Services",
            "type":"Services"
        }
    ],
    "sg:phone":"+61 418 783 161",
    "sg:postcode":"4121",
    "sg:province":"QLD",
    "sg:tags":[
        "equipment",
        "window",
        "doors"
    ],
    "wof:name":"M & L Security",
    "wof:placetype":"venue"
},
  "geometry": {"coordinates":[153.05067443900001,-27.5331745148],"type":"Point"}
}