{
  "type": "Feature",
  "properties": {
    "addr:full":"warner village shopping centre Shop 1 Samsonvale Rd Warner QLD 4500",
    "addr:housenumber":"shop 1",
    "addr:postcode":"4500",
    "addr:street":"Samsonvale Rd",
    "iso:country":"AU",
    "sg:address":"warner village shopping centre Shop 1 Samsonvale Rd",
    "sg:city":"Warner",
    "sg:classifiers":[
        {
            "category":"Fast Food",
            "type":"Food & Drink"
        }
    ],
    "sg:phone":"+61 7 3882 2377",
    "sg:postcode":"4500",
    "sg:province":"QLD",
    "sg:tags":[
        "away",
        "take"
    ],
    "wof:name":"Hooked On Fish",
    "wof:placetype":"venue"
},
  "geometry": {"coordinates":[152.962600708,-27.2928085327],"type":"Point"}
}