{
  "type": "Feature",
  "properties": {
    "addr:full":"5 Bishop Crs Armidale NSW 2350",
    "addr:housenumber":"5",
    "addr:postcode":"2350",
    "addr:street":"Bishop Crs",
    "iso:country":"AU",
    "sg:address":"5 Bishop Crs",
    "sg:city":"Armidale",
    "sg:classifiers":[
        {
            "category":"Insurance",
            "subcategory":"Insurance Agent",
            "type":"Services"
        }
    ],
    "sg:phone":"+61 2 6772 4580",
    "sg:postcode":"2350",
    "sg:province":"NSW",
    "sg:tags":[
        "wool",
        "broker"
    ],
    "wof:name":"Schute Bell Badgery Lumby",
    "wof:placetype":"venue"
},
  "geometry": {"coordinates":[151.74203491200001,-30.6037902832],"type":"Point"}
}