{
  "type": "Feature",
  "properties": {
    "addr:full":"8 Gordon St Balgowlah Heights NSW 2093",
    "addr:housenumber":"8",
    "addr:postcode":"2093",
    "addr:street":"Gordon St",
    "iso:country":"AU",
    "sg:address":"8 Gordon St",
    "sg:city":"Balgowlah Heights",
    "sg:classifiers":[
        {
            "category":"Health Services",
            "subcategory":"Doctor",
            "type":"Services"
        }
    ],
    "sg:phone":"+61 2 9948 8154",
    "sg:postcode":"2093",
    "sg:province":"NSW",
    "sg:tags":[
        "medical",
        "practitioner"
    ],
    "wof:name":"Gillies John F",
    "wof:placetype":"venue"
},
  "geometry": {"coordinates":[151.25559997600001,-33.8055419922],"type":"Point"}
}