{
  "type": "Feature",
  "properties": {
    "addr:full":"Shop 4, 24 Hornibrook Esp Clontarf QLD 4019",
    "addr:housenumber":"shop;24",
    "addr:postcode":"4019",
    "addr:street":"Hornibrook",
    "iso:country":"AU",
    "sg:address":"Shop 4, 24",
    "sg:city":"Hornibrook Esp Clontarf",
    "sg:classifiers":[
        {
            "category":"Home & Garden",
            "subcategory":"Garden Supply",
            "type":"Retail Goods"
        }
    ],
    "sg:phone":"+61 7 3283 4021",
    "sg:postcode":"4019",
    "sg:province":"QLD",
    "sg:tags":[
        "equipment",
        "hydroponics"
    ],
    "wof:name":"Professional Hydroponics",
    "wof:placetype":"venue"
},
  "geometry": {"coordinates":[153.08317565900001,-27.2585220337],"type":"Point"}
}