{
  "type": "Feature",
  "properties": {
    "iso:country":"AU",
    "sg:address":"18 Stirling Hwy",
    "sg:city":"Nedlands",
    "sg:classifiers":[
        {
            "category":"Professional",
            "subcategory":"Accounting & Tax Preparation",
            "type":"Services"
        }
    ],
    "sg:phone":"+61 8 9386 9266",
    "sg:postcode":"6009",
    "sg:province":"WA",
    "sg:tags":[
        "accountant",
        "auditor"
    ],
    "wof:name":"Owenell Partners",
    "wof:placetype":"venue"
},
  "geometry": {"coordinates":[115.81398,-31.977015],"type":"Point"}
}