{
  "type": "Feature",
  "properties": {
    "iso:country":"AU",
    "sg:address":"1133 Frankston - Dandenong Rd",
    "sg:city":"Carrum Downs",
    "sg:classifiers":[
        {
            "category":"Social Services",
            "subcategory":"Retirement Home",
            "type":"Services"
        }
    ],
    "sg:phone":"+61 3 9707 4331",
    "sg:postcode":"3201",
    "sg:province":"VIC",
    "sg:tags":[
        "village"
    ],
    "wof:name":"Carrum Downs Retirement Village",
    "wof:placetype":"venue"
},
  "geometry": {"coordinates":[145.177429,-38.094055],"type":"Point"}
}