{
  "type": "Feature",
  "properties": {
    "iso:country":"AU",
    "sg:address":"481 Napier St",
    "sg:city":"White Hills",
    "sg:classifiers":[
        {
            "category":"Personal",
            "type":"Services"
        }
    ],
    "sg:phone":"+61 3 5443 8755",
    "sg:postcode":"3550",
    "sg:province":"VIC",
    "sg:tags":[
        "dressmaker"
    ],
    "wof:name":"You Tear, I Repair",
    "wof:placetype":"venue"
},
  "geometry": {"coordinates":[144.30499267600001,-36.7310562134],"type":"Point"}
}