{
  "type": "Feature",
  "properties": {
    "iso:country":"AU",
    "sg:address":"394 B North East Rd",
    "sg:city":"Windsor Gardens",
    "sg:classifiers":[
        {
            "category":"Health Services",
            "subcategory":"Dentist",
            "type":"Services"
        }
    ],
    "sg:phone":"+61 8 8266 5665",
    "sg:postcode":"5087",
    "sg:province":"SA",
    "wof:name":"Barva Melinda Dr",
    "wof:placetype":"venue"
},
  "geometry": {"coordinates":[138.650634766,-34.8610115051],"type":"Point"}
}