{
  "type": "Feature",
  "properties": {
    "iso:country":"AU",
    "sg:address":"2/ 15 Carrington Rd",
    "sg:city":"Castle Hill",
    "sg:classifiers":[
        {
            "category":"Food & Beverages",
            "subcategory":"Specialty",
            "type":"Retail Goods"
        }
    ],
    "sg:phone":"+61 2 9634 3122",
    "sg:postcode":"2154",
    "sg:province":"NSW",
    "sg:tags":[
        "product",
        "health"
    ],
    "wof:name":"Eagle Pharmaceuticals Pty Ltd",
    "wof:placetype":"venue"
},
  "geometry": {"coordinates":[150.97482299800001,-33.7295227051],"type":"Point"}
}