{
  "type": "Feature",
  "properties": {
    "addr:full":"Shop 8, 80 Pacific Hwy North Sydney NSW 2055",
    "addr:housenumber":"shop;80",
    "addr:postcode":"2055",
    "addr:street":"Pacific Hwy",
    "iso:country":"AU",
    "sg:address":"Shop 8, 80 Pacific Hwy",
    "sg:city":"North Sydney",
    "sg:classifiers":[
        {
            "category":"Shopping",
            "subcategory":"Jewelry",
            "type":"Retail Goods"
        }
    ],
    "sg:phone":"+61 2 9955 8880",
    "sg:postcode":"2055",
    "sg:province":"NSW",
    "sg:tags":[
        "jeweller"
    ],
    "wof:name":"Jade's Idea",
    "wof:placetype":"venue"
},
  "geometry": {"coordinates":[151.208237,-33.840591],"type":"Point"}
}