{
  "type": "Feature",
  "properties": {
    "iso:country":"AU",
    "sg:address":"Yambo St",
    "sg:city":"Morisset",
    "sg:classifiers":[
        {
            "category":"Education",
            "subcategory":"School",
            "type":"Public Place"
        }
    ],
    "sg:phone":"+61 2 4973 4073",
    "sg:postcode":"2264",
    "sg:province":"NSW",
    "wof:name":"Schools Catholic",
    "wof:placetype":"venue"
},
  "geometry": {"coordinates":[151.48793,-33.107452],"type":"Point"}
}