{
  "type": "Feature",
  "properties": {
    "iso:country":"AU",
    "sg:address":"591 King St",
    "sg:city":"Newtown",
    "sg:classifiers":[
        {
            "category":"Shopping",
            "subcategory":"Crafts & Fabrics",
            "type":"Retail Goods"
        }
    ],
    "sg:phone":"+61 2 9517 2054",
    "sg:postcode":"2042",
    "sg:province":"NSW",
    "sg:tags":[
        "material",
        "dress"
    ],
    "wof:name":"A Indian Sarees,Braids & Beeds",
    "wof:placetype":"venue"
},
  "geometry": {"coordinates":[151.18077099999999,-33.905624],"type":"Point"}
}