{
  "type": "Feature",
  "properties": {
    "addr:full":"Joondalup Health Campus Cnr Grand Blvd & Shenton A Joondalup WA 6027",
    "addr:postcode":"6027",
    "addr:street":"Cnr Grand Blvd & Shenton",
    "iso:country":"AU",
    "sg:address":"Joondalup Health Campus Cnr Grand Blvd & Shenton A",
    "sg:city":"Joondalup",
    "sg:classifiers":[
        {
            "category":"Health Services",
            "subcategory":"Doctor",
            "type":"Services"
        }
    ],
    "sg:phone":"+61 8 9400 9810",
    "sg:postcode":"6027",
    "sg:province":"WA",
    "sg:tags":[
        "medical",
        "practitioner"
    ],
    "wof:name":"Western Diagnostic Pathology",
    "wof:placetype":"venue"
},
  "geometry": {"coordinates":[115.759986877,-31.7324905396],"type":"Point"}
}