{
  "type": "Feature",
  "properties": {
    "iso:country":"AU",
    "sg:address":"39 Relbia Rd",
    "sg:city":"Relbia",
    "sg:classifiers":[
        {
            "category":"Professional",
            "type":"Services"
        }
    ],
    "sg:phone":"+61 3 6343 3384",
    "sg:postcode":"7258",
    "sg:province":"TAS",
    "sg:tags":[
        "shop",
        "fitting"
    ],
    "wof:name":"Linger Joinery Pty Ltd",
    "wof:placetype":"venue"
},
  "geometry": {"coordinates":[147.17095947300001,-41.4925346375],"type":"Point"}
}