{
  "type": "Feature",
  "properties": {
    "addr:full":"20 Albert Ave Broadbeach QLD 4218",
    "addr:housenumber":"20",
    "addr:postcode":"4218",
    "addr:street":"Albert Ave",
    "iso:country":"AU",
    "sg:address":"20 Albert Ave",
    "sg:city":"Broadbeach",
    "sg:classifiers":[
        {
            "category":"Health Services",
            "subcategory":"Health Practitioner",
            "type":"Services"
        }
    ],
    "sg:phone":"+61 7 5526 7777",
    "sg:postcode":"4218",
    "sg:province":"QLD",
    "sg:tags":[
        "hypnotherapy"
    ],
    "wof:name":"Hysterics",
    "wof:placetype":"venue"
},
  "geometry": {"coordinates":[153.432174683,-28.0283222198],"type":"Point"}
}