{
  "type": "Feature",
  "properties": {
    "iso:country":"AU",
    "sg:address":"15 Deloraine Drv",
    "sg:city":"Leonay",
    "sg:classifiers":[
        {
            "category":"Personal",
            "subcategory":"Beauty Salon",
            "type":"Services"
        }
    ],
    "sg:phone":"+61 2 4735 3614",
    "sg:postcode":"2750",
    "sg:province":"NSW",
    "sg:tags":[
        "supply",
        "artist",
        "make-up"
    ],
    "wof:name":"Simply Skin",
    "wof:placetype":"venue"
},
  "geometry": {"coordinates":[150.64533996599999,-33.7643814087],"type":"Point"}
}