{
  "type": "Feature",
  "properties": {
    "addr:full":"Shop 14, Tahmoor Town Centre, Cnr Rememberance Drv & Thirlmere Way Tahmoor NSW 2573",
    "addr:housenumber":"shop 14",
    "addr:postcode":"2573",
    "addr:street":"Cnr Rememberance Drv & Thirlmere Way",
    "iso:country":"AU",
    "sg:address":"Shop 14, Tahmoor Town Centre, Cnr Rememberance Drv & Thirlmere Way",
    "sg:city":"Tahmoor",
    "sg:classifiers":[
        {
            "category":"Food & Beverages",
            "subcategory":"Bakery",
            "type":"Retail Goods"
        }
    ],
    "sg:phone":"+61 2 4681 0455",
    "sg:postcode":"2573",
    "sg:province":"NSW",
    "sg:tags":[
        "cake",
        "shop",
        "pastry"
    ],
    "wof:name":"Michel's Patisserie",
    "wof:placetype":"venue"
},
  "geometry": {"coordinates":[150.591796875,-34.2220726013],"type":"Point"}
}