{
  "type": "Feature",
  "properties": {
    "addr:full":"4 Hume Crt Benalla VIC 3672",
    "addr:housenumber":"4",
    "addr:postcode":"3672",
    "addr:street":"Hume Crt",
    "iso:country":"AU",
    "sg:address":"4 Hume Crt",
    "sg:city":"Benalla",
    "sg:classifiers":[
        {
            "category":"Building & Trades",
            "subcategory":"Construction",
            "type":"Services"
        }
    ],
    "sg:phone":"+61 3 5762 2590",
    "sg:postcode":"3672",
    "sg:province":"VIC",
    "sg:tags":[
        "installation",
        "air conditioning"
    ],
    "wof:name":"Airconditioning 4 U",
    "wof:placetype":"venue"
},
  "geometry": {"coordinates":[145.96075400000001,-36.556915],"type":"Point"}
}