{
  "type": "Feature",
  "properties": {
    "iso:country":"AU",
    "sg:address":"PO Box 9037 MARCOOLA",
    "sg:city":"Pacific Paradise",
    "sg:classifiers":[
        {
            "category":"Manufacturing",
            "subcategory":"Jewelry",
            "type":"Manufacturing & Wholesale Goods"
        }
    ],
    "sg:phone":"+61 7 5450 6199",
    "sg:postcode":"4564",
    "sg:province":"QLD",
    "sg:tags":[
        "mfrg",
        "jeweller"
    ],
    "wof:name":"North Shore Jewellery Repairs",
    "wof:placetype":"venue"
},
  "geometry": {"coordinates":[153.070404053,-26.6245994568],"type":"Point"}
}