{
  "type": "Feature",
  "properties": {
    "iso:country":"AU",
    "sg:address":"PO Box 3037",
    "sg:city":"Ripponlea",
    "sg:classifiers":[
        {
            "category":"Arts & Performance",
            "subcategory":"Art Gallery",
            "type":"Entertainment"
        }
    ],
    "sg:phone":"+61 3 9532 9034",
    "sg:postcode":"3185",
    "sg:province":"VIC",
    "wof:name":"Kennedy & Co The Gallery",
    "wof:placetype":"venue"
},
  "geometry": {"coordinates":[144.99494934099999,-37.8765411377],"type":"Point"}
}