{
  "type": "Feature",
  "properties": {
    "addr:full":"4/ 69 Cowper St Wallsend NSW 2287",
    "addr:housenumber":"/ 69",
    "addr:postcode":"2287",
    "addr:street":"Cowper St",
    "iso:country":"AU",
    "sg:address":"4/ 69 Cowper St",
    "sg:city":"Wallsend",
    "sg:classifiers":[
        {
            "category":"Real Estate",
            "subcategory":"Architect",
            "type":"Services"
        }
    ],
    "sg:phone":"+61 2 4955 0388",
    "sg:postcode":"2287",
    "sg:province":"NSW",
    "sg:tags":[
        "building",
        "designer"
    ],
    "wof:name":"Halmac Building Design",
    "wof:placetype":"venue"
},
  "geometry": {"coordinates":[151.67060852,-32.9027709961],"type":"Point"}
}