{
  "type": "Feature",
  "properties": {
    "addr:full":"Suite 307, 220 Pacific Hwy Crows Nest NSW 2065",
    "addr:housenumber":"220",
    "addr:postcode":"2065",
    "addr:street":"Pacific Hwy",
    "iso:country":"AU",
    "sg:address":"Suite 307, 220 Pacific Hwy",
    "sg:city":"Crows Nest",
    "sg:classifiers":[
        {
            "category":"Insurance",
            "subcategory":"Insurance Agent",
            "type":"Services"
        }
    ],
    "sg:phone":"+61 2 9460 2288",
    "sg:postcode":"2065",
    "sg:province":"NSW",
    "sg:tags":[
        "broker"
    ],
    "wof:name":"Insurance Advisernet Australia Pty Limited",
    "wof:placetype":"venue"
},
  "geometry": {"coordinates":[151.198928833,-33.8255310059],"type":"Point"}
}