{
  "type": "Feature",
  "properties": {
    "iso:country":"AU",
    "sg:address":"Shp2/ 8 Farrell St",
    "sg:city":"Yandina",
    "sg:classifiers":[
        {
            "category":"Shopping",
            "subcategory":"Clothing, Apparel, & Fashions",
            "type":"Retail Goods"
        }
    ],
    "sg:phone":"+61 7 5472 7976",
    "sg:postcode":"4561",
    "sg:province":"QLD",
    "sg:tags":[
        "maternity",
        "wear"
    ],
    "wof:name":"Eden Maternity",
    "wof:placetype":"venue"
},
  "geometry": {"coordinates":[152.95582580600001,-26.5619316101],"type":"Point"}
}