{
  "type": "Feature",
  "properties": {
    "iso:country":"AU",
    "sg:address":"Shop 4/ 4 Partridge St",
    "sg:city":"Glenelg",
    "sg:classifiers":[
        {
            "category":"Professional",
            "subcategory":"Printing & Photocopies",
            "type":"Services"
        }
    ],
    "sg:phone":"+61 8 8295 7522",
    "sg:postcode":"5045",
    "sg:province":"SA",
    "sg:tags":[
        "photocopying"
    ],
    "wof:name":"Copies and More",
    "wof:placetype":"venue"
},
  "geometry": {"coordinates":[138.51795999999999,-34.980724],"type":"Point"}
}