{
  "type": "Feature",
  "properties": {
    "addr:full":"6/ 50 Parraweena Rd Gwandalan NSW 2259",
    "addr:housenumber":"/ 50",
    "addr:postcode":"2259",
    "addr:street":"Parraweena Rd",
    "iso:country":"AU",
    "sg:address":"6/ 50 Parraweena Rd",
    "sg:city":"Gwandalan",
    "sg:classifiers":[
        {
            "category":"Fast Food",
            "type":"Food & Drink"
        }
    ],
    "sg:phone":"+61 2 4972 6166",
    "sg:postcode":"2259",
    "sg:province":"NSW",
    "sg:tags":[
        "away",
        "take"
    ],
    "wof:name":"Tuckerbox The",
    "wof:placetype":"venue"
},
  "geometry": {"coordinates":[151.58012390100001,-33.1458282471],"type":"Point"}
}