{
  "type": "Feature",
  "properties": {
    "addr:full":"PO Box 553 Kalamunda WA 6076",
    "addr:postcode":"6076",
    "iso:country":"AU",
    "sg:address":"PO Box 553",
    "sg:city":"Kalamunda",
    "sg:classifiers":[
        {
            "category":"Arena",
            "subcategory":"Sports Club",
            "type":"Entertainment"
        }
    ],
    "sg:phone":"+61 8 9293 2706",
    "sg:postcode":"6076",
    "sg:province":"WA",
    "sg:tags":[
        "organisation",
        "sporting"
    ],
    "wof:name":"Billiards & Snooker Association Of WA Inc",
    "wof:placetype":"venue"
},
  "geometry": {"coordinates":[116.153198242,-32.0055885315],"type":"Point"}
}