{
  "type": "Feature",
  "properties": {
    "iso:country":"AU",
    "sg:address":"60 Karalta Rd",
    "sg:city":"Erina",
    "sg:classifiers":[
        {
            "category":"Personal",
            "subcategory":"Massage",
            "type":"Services"
        }
    ],
    "sg:phone":"+61 2 4365 6563",
    "sg:postcode":"2250",
    "sg:province":"NSW",
    "sg:tags":[
        "therapy"
    ],
    "wof:name":"R n R Massage",
    "wof:placetype":"venue"
},
  "geometry": {"coordinates":[151.38926696799999,-33.4393081665],"type":"Point"}
}