{
  "type": "Feature",
  "properties": {
    "addr:full":"40 Brown St Bronte NSW 2024",
    "addr:housenumber":"40",
    "addr:postcode":"2024",
    "addr:street":"Brown St",
    "iso:country":"AU",
    "sg:address":"40 Brown St",
    "sg:city":"Bronte",
    "sg:classifiers":[
        {
            "category":"Communications",
            "type":"Services"
        }
    ],
    "sg:phone":"+61 2 9389 6341",
    "sg:postcode":"2024",
    "sg:province":"NSW",
    "sg:tags":[
        "translation"
    ],
    "wof:name":"Czech English Translation Service",
    "wof:placetype":"venue"
},
  "geometry": {"coordinates":[151.25851440400001,-33.9000167847],"type":"Point"}
}