{
  "type": "Feature",
  "properties": {
    "iso:country":"AU",
    "sg:address":"7 Macpherson St",
    "sg:city":"O'Connor",
    "sg:classifiers":[
        {
            "category":"Health Services",
            "subcategory":"Doctor",
            "type":"Services"
        }
    ],
    "sg:phone":"+61 2 6249 1711",
    "sg:postcode":"2602",
    "sg:province":"ACT",
    "sg:tags":[
        "medical",
        "practitioner"
    ],
    "wof:name":"Fonseka K Dr",
    "wof:placetype":"venue"
},
  "geometry": {"coordinates":[149.121704102,-35.264213562],"type":"Point"}
}