{
  "type": "Feature",
  "properties": {
    "addr:full":"161 St Leonards Rd Launceston TAS 7250",
    "addr:housenumber":"161",
    "addr:postcode":"7250",
    "addr:street":"St Leonards Rd",
    "iso:country":"AU",
    "sg:address":"161 St Leonards Rd",
    "sg:city":"Launceston",
    "sg:classifiers":[
        {
            "category":"Freight",
            "type":"Transportation"
        }
    ],
    "sg:phone":"+61 3 6331 4200",
    "sg:postcode":"7250",
    "sg:province":"TAS",
    "sg:tags":[
        "light",
        "carrier"
    ],
    "wof:name":"Suncoast Express Incorporating St Helens Transport",
    "wof:placetype":"venue"
},
  "geometry": {"coordinates":[147.185668945,-41.446472168],"type":"Point"}
}