{
  "type": "Feature",
  "properties": {
    "iso:country":"AU",
    "sg:address":"Commissioners Flat La",
    "sg:city":"Heathcote",
    "sg:classifiers":[
        {
            "category":"Shopping",
            "subcategory":"Clothing, Apparel, & Fashions",
            "type":"Retail Goods"
        }
    ],
    "sg:phone":"+61 3 5433 4006",
    "sg:postcode":"3523",
    "sg:province":"VIC",
    "sg:tags":[
        "accessory"
    ],
    "wof:name":"Made In Aussie by Adriana & Jackie",
    "wof:placetype":"venue"
},
  "geometry": {"coordinates":[144.69700599999999,-36.926933],"type":"Point"}
}