{
  "type": "Feature",
  "properties": {
    "addr:full":"Cnr Strelitzia Ave & Hale Rd Forrestfield WA 6058",
    "addr:postcode":"6058",
    "addr:street":"Cnr Strelitzia Ave & Hale Rd",
    "iso:country":"AU",
    "sg:address":"Cnr Strelitzia Ave & Hale Rd",
    "sg:city":"Forrestfield",
    "sg:classifiers":[
        {
            "category":"Autos & Motor Vehicles",
            "subcategory":"Fuel & Gas Station",
            "type":"Retail Goods"
        }
    ],
    "sg:phone":"+61 8 9453 6088",
    "sg:postcode":"6058",
    "sg:province":"WA",
    "wof:name":"Shell Forrestfield",
    "wof:placetype":"venue"
},
  "geometry": {"coordinates":[116.005363464,-31.9813594818],"type":"Point"}
}