{
  "type": "Feature",
  "properties": {
    "addr:full":"304 Carella St Tranmere TAS 7018",
    "addr:housenumber":"304",
    "addr:postcode":"7018",
    "addr:street":"Carella St",
    "iso:country":"AU",
    "sg:address":"304 Carella St",
    "sg:city":"Tranmere",
    "sg:classifiers":[
        {
            "category":"Arena",
            "subcategory":"Sports Club",
            "type":"Entertainment"
        }
    ],
    "sg:phone":"+61 3 6247 7116",
    "sg:postcode":"7018",
    "sg:province":"TAS",
    "sg:tags":[
        "tour",
        "holiday"
    ],
    "wof:name":"Total Tennis Tuition",
    "wof:placetype":"venue"
},
  "geometry": {"coordinates":[147.41949462900001,-42.9082603455],"type":"Point"}
}