{
  "type": "Feature",
  "properties": {
    "addr:full":"99 Charles St Footscray VIC 3011",
    "addr:housenumber":"99",
    "addr:postcode":"3011",
    "addr:street":"Charles St",
    "iso:country":"AU",
    "sg:address":"99 Charles St",
    "sg:city":"Footscray",
    "sg:classifiers":[
        {
            "category":"Fast Food",
            "type":"Food & Drink"
        }
    ],
    "sg:phone":"+61 3 9687 5606",
    "sg:postcode":"3011",
    "sg:province":"VIC",
    "sg:tags":[
        "away",
        "take"
    ],
    "wof:name":"McManos Chicken Bar",
    "wof:placetype":"venue"
},
  "geometry": {"coordinates":[144.89068603499999,-37.8066444397],"type":"Point"}
}