{
  "type": "Feature",
  "properties": {
    "addr:full":"21 Menana Rd Glenroy VIC 3046",
    "addr:housenumber":"21",
    "addr:postcode":"3046",
    "addr:street":"Menana Rd",
    "iso:country":"AU",
    "sg:address":"21 Menana Rd",
    "sg:city":"Glenroy",
    "sg:classifiers":[
        {
            "category":"Building & Trades",
            "subcategory":"Construction",
            "type":"Services"
        }
    ],
    "sg:phone":"+61 418 325 165",
    "sg:postcode":"3046",
    "sg:province":"VIC",
    "sg:tags":[
        "earth",
        "excavating",
        "moving",
        "contractor"
    ],
    "wof:name":"Diggem Earth Works",
    "wof:placetype":"venue"
},
  "geometry": {"coordinates":[144.90789794899999,-37.7101898193],"type":"Point"}
}