{
  "type": "Feature",
  "properties": {
    "addr:full":"Shop 3, 27 Main Rd Olinda VIC 3788",
    "addr:housenumber":"shop;27",
    "addr:postcode":"3788",
    "addr:street":"Main Rd",
    "iso:country":"AU",
    "sg:address":"Shop 3, 27 Main Rd",
    "sg:city":"Olinda",
    "sg:classifiers":[
        {
            "category":"Personal",
            "subcategory":"Beauty Salon",
            "type":"Services"
        }
    ],
    "sg:phone":"+61 3 9751 2294",
    "sg:postcode":"3788",
    "sg:province":"VIC",
    "sg:tags":[
        "hairdresser"
    ],
    "wof:name":"The Mill Hair Studio",
    "wof:placetype":"venue"
},
  "geometry": {"coordinates":[145.35876500000001,-37.841629],"type":"Point"}
}