{
  "type": "Feature",
  "properties": {
    "addr:full":"69 Main St Pialba QLD 4655",
    "addr:housenumber":"69",
    "addr:postcode":"4655",
    "addr:street":"Main St",
    "iso:country":"AU",
    "sg:address":"69 Main St",
    "sg:city":"Pialba",
    "sg:classifiers":[
        {
            "category":"Wholesale",
            "subcategory":"Medical Equipment & Supplies",
            "type":"Manufacturing & Wholesale Goods"
        }
    ],
    "sg:phone":"+61 7 4124 7117",
    "sg:postcode":"4655",
    "sg:province":"QLD",
    "sg:tags":[
        "aid",
        "care",
        "health",
        "home"
    ],
    "wof:name":"Totally Mobile",
    "wof:placetype":"venue"
},
  "geometry": {"coordinates":[152.844223,-25.294889],"type":"Point"}
}