{
  "type": "Feature",
  "properties": {
    "iso:country":"AU",
    "sg:address":"21- 23 Ann St",
    "sg:city":"Mooroopna",
    "sg:classifiers":[
        {
            "category":"Social Services",
            "subcategory":"Child Care",
            "type":"Services"
        }
    ],
    "sg:phone":"+61 3 5825 3933",
    "sg:postcode":"3629",
    "sg:province":"VIC",
    "wof:name":"Ann Street Child Care",
    "wof:placetype":"venue"
},
  "geometry": {"coordinates":[145.35250854500001,-36.3956413269],"type":"Point"}
}