{
  "type": "Feature",
  "properties": {
    "addr:full":"Suite 3, Level 3, 159 High Street Prahran VIC 3181",
    "addr:housenumber":"159",
    "addr:postcode":"3181",
    "addr:street":"High Street",
    "iso:country":"AU",
    "sg:address":"Suite 3, Level 3, 159 High Street",
    "sg:city":"Prahran",
    "sg:classifiers":[
        {
            "category":"Professional",
            "subcategory":"Employment Agencies",
            "type":"Services"
        }
    ],
    "sg:phone":"+61 3 9529 2866",
    "sg:postcode":"3181",
    "sg:province":"VIC",
    "wof:name":"Job Futures",
    "wof:placetype":"venue"
},
  "geometry": {"coordinates":[144.99313354500001,-37.8516731262],"type":"Point"}
}