{
  "type": "Feature",
  "properties": {
    "addr:full":"Unit 2/ 107 Highbury Rd Burwood VIC 3125",
    "addr:housenumber":"/ 107",
    "addr:postcode":"3125",
    "addr:street":"Highbury Rd",
    "iso:country":"AU",
    "sg:address":"Unit 2/ 107 Highbury Rd",
    "sg:city":"Burwood",
    "sg:classifiers":[
        {
            "category":"Professional",
            "subcategory":"Art Services",
            "type":"Services"
        }
    ],
    "sg:phone":"+61 3 9808 1399",
    "sg:postcode":"3125",
    "sg:province":"VIC",
    "sg:tags":[
        "product",
        "industrial",
        "designer"
    ],
    "wof:name":"Ideation Design",
    "wof:placetype":"venue"
},
  "geometry": {"coordinates":[145.10559082,-37.8544006348],"type":"Point"}
}