{
  "type": "Feature",
  "properties": {
    "addr:full":"U9/ 8 Young St East Maitland NSW 2323",
    "addr:housenumber":"8",
    "addr:postcode":"2323",
    "addr:street":"U9 /;Young St",
    "iso:country":"AU",
    "sg:address":"U9/ 8 Young St",
    "sg:city":"East Maitland",
    "sg:classifiers":[
        {
            "category":"Government",
            "subcategory":"Fire Station",
            "type":"Public Place"
        }
    ],
    "sg:phone":"+61 2 4933 2009",
    "sg:postcode":"2323",
    "sg:province":"NSW",
    "sg:tags":[
        "burner",
        "gas",
        "equipment"
    ],
    "wof:name":"Flame Safe Gas Repairs",
    "wof:placetype":"venue"
},
  "geometry": {"coordinates":[151.59896850600001,-32.7532157898],"type":"Point"}
}