{
  "type": "Feature",
  "properties": {
    "addr:full":"95 Jeffrey St Armidale NSW 2350",
    "addr:housenumber":"95",
    "addr:postcode":"2350",
    "addr:street":"Jeffrey St",
    "iso:country":"AU",
    "sg:address":"95 Jeffrey St",
    "sg:city":"Armidale",
    "sg:classifiers":[
        {
            "category":"Building & Trades",
            "subcategory":"Plumbing",
            "type":"Services"
        }
    ],
    "sg:phone":"+61 438 713 924",
    "sg:postcode":"2350",
    "sg:province":"NSW",
    "sg:tags":[
        "plumber",
        "gasfitters"
    ],
    "wof:name":"Michael Saint Plumbing",
    "wof:placetype":"venue"
},
  "geometry": {"coordinates":[151.67616272000001,-30.5080375671],"type":"Point"}
}