{
  "type": "Feature",
  "properties": {
    "iso:country":"AU",
    "sg:address":"44 Hutton St",
    "sg:city":"Osborne Park",
    "sg:classifiers":[
        {
            "category":"Professional",
            "subcategory":"Accounting & Tax Preparation",
            "type":"Services"
        }
    ],
    "sg:phone":"+61 8 9242 3688",
    "sg:postcode":"6017",
    "sg:province":"WA",
    "sg:tags":[
        "accountant",
        "auditor"
    ],
    "wof:name":"Pearce & Cook",
    "wof:placetype":"venue"
},
  "geometry": {"coordinates":[115.819297791,-31.9029083252],"type":"Point"}
}