{
  "type": "Feature",
  "properties": {
    "addr:full":"Cnr Youngman & Alford Sts Kingaroy QLD 4610",
    "addr:postcode":"4610",
    "addr:street":"Cnr",
    "iso:country":"AU",
    "sg:address":"Cnr Youngman & Alford Sts",
    "sg:city":"Kingaroy",
    "sg:classifiers":[
        {
            "category":"Shopping",
            "subcategory":"Jewelry",
            "type":"Retail Goods"
        }
    ],
    "sg:phone":"+61 7 4162 7386",
    "sg:postcode":"4610",
    "sg:province":"QLD",
    "sg:tags":[
        "jeweller"
    ],
    "wof:name":"Kleins Jewellery",
    "wof:placetype":"venue"
},
  "geometry": {"coordinates":[151.836181641,-26.5406093597],"type":"Point"}
}