{
  "type": "Feature",
  "properties": {
    "iso:country":"AU",
    "sg:address":"28 Helvetia Ave",
    "sg:city":"Berowra",
    "sg:classifiers":[
        {
            "category":"Building & Trades",
            "subcategory":"Cleaning & Sanitation",
            "type":"Services"
        }
    ],
    "sg:phone":"+61 2 9456 3070",
    "sg:postcode":"2081",
    "sg:province":"NSW",
    "sg:tags":[
        "industrial",
        "commercial",
        "contractor"
    ],
    "wof:name":"Mr Dustbuster Cleaning & Maintenance",
    "wof:placetype":"venue"
},
  "geometry": {"coordinates":[151.14643859899999,-33.6335411072],"type":"Point"}
}