{
  "type": "Feature",
  "properties": {
    "iso:country":"AU",
    "sg:address":"8- 10 Palmer St",
    "sg:city":"Parramatta",
    "sg:classifiers":[
        {
            "category":"Health Services",
            "subcategory":"Health Practitioner",
            "type":"Services"
        }
    ],
    "sg:phone":"+61 2 9630 0911",
    "sg:postcode":"2150",
    "sg:province":"NSW",
    "sg:tags":[
        "psychologist"
    ],
    "wof:name":"Baddeley Mark",
    "wof:placetype":"venue"
},
  "geometry": {"coordinates":[150.96832275400001,-33.8454666138],"type":"Point"}
}