{
  "type": "Feature",
  "properties": {
    "iso:country":"AU",
    "sg:address":"67 Quail St",
    "sg:city":"St Helens",
    "sg:classifiers":[
        {
            "category":"Retail",
            "subcategory":"Veterinary Services",
            "type":"Services"
        }
    ],
    "sg:phone":"+61 3 6376 1577",
    "sg:postcode":"7216",
    "sg:province":"TAS",
    "sg:tags":[
        "surgeon"
    ],
    "wof:name":"East Coast Veterinary Clinic",
    "wof:placetype":"venue"
},
  "geometry": {"coordinates":[148.245422,-41.321255],"type":"Point"}
}