{
  "type": "Feature",
  "properties": {
    "addr:full":"23 Kenyon St Launceston TAS 7250",
    "addr:housenumber":"23",
    "addr:postcode":"7250",
    "addr:street":"Kenyon St",
    "iso:country":"AU",
    "sg:address":"23 Kenyon St",
    "sg:city":"Launceston",
    "sg:classifiers":[
        {
            "category":"Professional",
            "subcategory":"Business Services",
            "type":"Services"
        }
    ],
    "sg:phone":"+61 3 6334 7433",
    "sg:postcode":"7250",
    "sg:province":"TAS",
    "sg:tags":[
        "management",
        "event"
    ],
    "wof:name":"BE Enterprises Pty Ltd",
    "wof:placetype":"venue"
},
  "geometry": {"coordinates":[147.15696716299999,-41.4422912598],"type":"Point"}
}