{
  "type": "Feature",
  "properties": {
    "addr:full":"32 Red Gum Drv Dandenong VIC 3175",
    "addr:housenumber":"32",
    "addr:postcode":"3175",
    "addr:street":"Red Gum Drv",
    "iso:country":"AU",
    "sg:address":"32 Red Gum Drv",
    "sg:city":"Dandenong",
    "sg:classifiers":[
        {
            "category":"Social Services",
            "subcategory":"Adult Care",
            "type":"Services"
        }
    ],
    "sg:phone":"+61 13 69 13",
    "sg:postcode":"3175",
    "sg:province":"VIC",
    "sg:tags":[
        "towing"
    ],
    "wof:name":"Bea-Lyne Towing",
    "wof:placetype":"venue"
},
  "geometry": {"coordinates":[145.197723389,-38.0246543884],"type":"Point"}
}