{
  "type": "Feature",
  "properties": {
    "addr:full":"2 Blackdown St Rocklea QLD 4106",
    "addr:housenumber":"2",
    "addr:postcode":"4106",
    "addr:street":"Blackdown St",
    "iso:country":"AU",
    "sg:address":"2 Blackdown St",
    "sg:city":"Rocklea",
    "sg:classifiers":[
        {
            "category":"Autos & Motor Vehicles",
            "subcategory":"Auto Supplies",
            "type":"Retail Goods"
        }
    ],
    "sg:phone":"+61 7 3277 5966",
    "sg:postcode":"4106",
    "sg:province":"QLD",
    "sg:tags":[
        "equipment",
        "part",
        "truck"
    ],
    "wof:name":"Don Kyatt Spare Parts (Qld) Pty. Ltd.",
    "wof:placetype":"venue"
},
  "geometry": {"coordinates":[152.99974060100001,-27.5612716675],"type":"Point"}
}