{
  "type": "Feature",
  "properties": {
    "addr:full":"Shop 9/ 26 Tedder Ave Main Beach QLD 4217",
    "addr:housenumber":"shop 9 / 26",
    "addr:postcode":"4217",
    "addr:street":"Tedder Ave",
    "iso:country":"AU",
    "sg:address":"Shop 9/ 26 Tedder Ave",
    "sg:city":"Main Beach",
    "sg:classifiers":[
        {
            "category":"Shopping",
            "subcategory":"Clothing, Apparel, & Fashions",
            "type":"Retail Goods"
        }
    ],
    "sg:phone":"+61 7 5531 4400",
    "sg:postcode":"4217",
    "sg:province":"QLD",
    "sg:tags":[
        "lady",
        "wear"
    ],
    "wof:name":"Leaf Boutique",
    "wof:placetype":"venue"
},
  "geometry": {"coordinates":[153.42489624000001,-27.97864151],"type":"Point"}
}