{
  "type": "Feature",
  "properties": {
    "addr:full":"186 High St Doncaster VIC 3108",
    "addr:housenumber":"186",
    "addr:postcode":"3108",
    "addr:street":"High St",
    "iso:country":"AU",
    "sg:address":"186 High St",
    "sg:city":"Doncaster",
    "sg:classifiers":[
        {
            "category":"Health Services",
            "subcategory":"Health Practitioner",
            "type":"Services"
        }
    ],
    "sg:phone":"+61 3 9887 7117",
    "sg:postcode":"3108",
    "sg:province":"VIC",
    "sg:tags":[
        "pathologist",
        "speech"
    ],
    "wof:name":"Liu Gladys",
    "wof:placetype":"venue"
},
  "geometry": {"coordinates":[145.11419677699999,-37.7747688293],"type":"Point"}
}