{
  "type": "Feature",
  "properties": {
    "addr:full":"1 Mitchell St Parafield Gardens SA 5107",
    "addr:housenumber":"1",
    "addr:postcode":"5107",
    "addr:street":"Mitchell St",
    "iso:country":"AU",
    "sg:address":"1 Mitchell St",
    "sg:city":"Parafield Gardens",
    "sg:classifiers":[
        {
            "category":"Military Area",
            "subcategory":"Army Base",
            "type":"Public Place"
        }
    ],
    "sg:phone":"+61 8 8258 8441",
    "sg:postcode":"5107",
    "sg:province":"SA",
    "sg:tags":[
        "concrete",
        "slab",
        "floor"
    ],
    "wof:name":"Solid Concrete Constructions Pty Ltd",
    "wof:placetype":"venue"
},
  "geometry": {"coordinates":[138.61265564000001,-34.7858543396],"type":"Point"}
}