{
  "type": "Feature",
  "properties": {
    "iso:country":"AU",
    "sg:address":"Level 6 252 Collins St",
    "sg:city":"Melbourne",
    "sg:classifiers":[
        {
            "category":"Health Services",
            "subcategory":"Dentist",
            "type":"Services"
        }
    ],
    "sg:phone":"+61 3 9654 6667",
    "sg:postcode":"3000",
    "sg:province":"VIC",
    "sg:website":"http://www.dimosdental.com.au",
    "wof:name":"Dimos Dental",
    "wof:placetype":"venue"
},
  "geometry": {"coordinates":[144.96536254899999,-37.8156967163],"type":"Point"}
}