{
  "type": "Feature",
  "properties": {
    "iso:country":"AU",
    "sg:address":"PO Box 130",
    "sg:city":"Leura",
    "sg:classifiers":[
        {
            "category":"Professional",
            "subcategory":"Art Services",
            "type":"Services"
        }
    ],
    "sg:phone":"+61 2 4759 1737",
    "sg:postcode":"2780",
    "sg:province":"NSW",
    "sg:tags":[
        "interior",
        "decorator"
    ],
    "wof:name":"Camellia Room Interiors",
    "wof:placetype":"venue"
},
  "geometry": {"coordinates":[150.33132934599999,-33.7115707397],"type":"Point"}
}