{
  "type": "Feature",
  "properties": {
    "addr:full":"16 Melrose Pl Werribee VIC 3030",
    "addr:housenumber":"16",
    "addr:postcode":"3030",
    "addr:street":"Melrose Pl",
    "iso:country":"AU",
    "sg:address":"16 Melrose Pl",
    "sg:city":"Werribee",
    "sg:classifiers":[
        {
            "category":"Professional",
            "subcategory":"Engineering",
            "type":"Services"
        }
    ],
    "sg:phone":"+61 3 9741 3022",
    "sg:postcode":"3030",
    "sg:province":"VIC",
    "sg:tags":[
        "civil",
        "engineer"
    ],
    "wof:name":"Kirkbride John D",
    "wof:placetype":"venue"
},
  "geometry": {"coordinates":[144.67746,-37.906193],"type":"Point"}
}