{
  "type": "Feature",
  "properties": {
    "addr:full":"32 Kananook Crs Belmont North NSW 2280",
    "addr:housenumber":"32",
    "addr:postcode":"2280",
    "addr:street":"Kananook Crs",
    "iso:country":"AU",
    "sg:address":"32 Kananook Crs",
    "sg:city":"Belmont North",
    "sg:classifiers":[
        {
            "category":"Building & Trades",
            "subcategory":"Construction",
            "type":"Services"
        }
    ],
    "sg:phone":"+61 2 4945 9706",
    "sg:postcode":"2280",
    "sg:province":"NSW",
    "sg:tags":[
        "rendering",
        "cement"
    ],
    "wof:name":"Peter Bell Building Contractors Pty Ltd",
    "wof:placetype":"venue"
},
  "geometry": {"coordinates":[151.66792297399999,-33.0193481445],"type":"Point"}
}