{
  "type": "Feature",
  "properties": {
    "addr:full":"Byron St Mullumbimby NSW 2482",
    "addr:postcode":"2482",
    "addr:street":"Byron St",
    "iso:country":"AU",
    "sg:address":"Byron St",
    "sg:city":"Mullumbimby",
    "sg:classifiers":[
        {
            "category":"Sports & Exercise",
            "subcategory":"Sports Center",
            "type":"Entertainment"
        }
    ],
    "sg:phone":"+61 403 841 241",
    "sg:postcode":"2482",
    "sg:province":"NSW",
    "sg:tags":[
        "coach",
        "tennis"
    ],
    "wof:name":"Justin De Candia",
    "wof:placetype":"venue"
},
  "geometry": {"coordinates":[153.49717712399999,-28.5578765869],"type":"Point"}
}