{
  "type": "Feature",
  "properties": {
    "iso:country":"AU",
    "sg:address":"Wheaton Rd",
    "sg:city":"McLaren Vale",
    "sg:classifiers":[
        {
            "category":"Utilities",
            "subcategory":"Refuse",
            "type":"Services"
        }
    ],
    "sg:phone":"+61 8 8386 0273",
    "sg:postcode":"5171",
    "sg:province":"SA",
    "sg:tags":[
        "disposal",
        "reduction",
        "waste"
    ],
    "wof:name":"Pedler Creek Waste Disposal Depot",
    "wof:placetype":"venue"
},
  "geometry": {"coordinates":[138.513397217,-35.2000465393],"type":"Point"}
}