{
  "type": "Feature",
  "properties": {
    "addr:full":"1 Yeats Ave Killarney Heights NSW 2087",
    "addr:housenumber":"1",
    "addr:postcode":"2087",
    "addr:street":"Yeats Ave",
    "iso:country":"AU",
    "sg:address":"1 Yeats Ave",
    "sg:city":"Killarney Heights",
    "sg:classifiers":[
        {
            "category":"Utilities",
            "subcategory":"Electric",
            "type":"Services"
        }
    ],
    "sg:phone":"+61 2 9975 3475",
    "sg:postcode":"2087",
    "sg:province":"NSW",
    "sg:tags":[
        "electrical",
        "contractor"
    ],
    "wof:name":"Techlec Pty Ltd",
    "wof:placetype":"venue"
},
  "geometry": {"coordinates":[151.223709106,-33.7748374939],"type":"Point"}
}