{
  "type": "Feature",
  "properties": {
    "iso:country":"AU",
    "sg:address":"110 Canterbury Rd",
    "sg:city":"Heathmont",
    "sg:classifiers":[
        {
            "category":"Real Estate",
            "subcategory":"Real Estate Agent",
            "type":"Services"
        }
    ],
    "sg:phone":"+61 3 9722 7166",
    "sg:postcode":"3135",
    "sg:province":"VIC",
    "wof:name":"Barry Plant Real Estate",
    "wof:placetype":"venue"
},
  "geometry": {"coordinates":[145.246170044,-37.8289413452],"type":"Point"}
}