{
  "type": "Feature",
  "properties": {
    "iso:country":"AU",
    "sg:address":"11 Garnkirk Rd",
    "sg:city":"Greenwood",
    "sg:classifiers":[
        {
            "category":"Building & Trades",
            "subcategory":"Pest Control",
            "type":"Services"
        }
    ],
    "sg:phone":"+61 8 9447 9861",
    "sg:postcode":"6024",
    "sg:province":"WA",
    "wof:name":"Feral & Vermin Culling Services",
    "wof:placetype":"venue"
},
  "geometry": {"coordinates":[115.788108826,-31.8246135712],"type":"Point"}
}