{
  "type": "Feature",
  "properties": {
    "iso:country":"AU",
    "sg:address":"Cnr Mountain Creek Rd & Kiewa Valley Hwy",
    "sg:city":"Mt Beauty",
    "sg:classifiers":[
        {
            "category":"Travel",
            "subcategory":"Hotels & Motels",
            "type":"Entertainment"
        }
    ],
    "sg:phone":"+61 3 5754 4247",
    "sg:postcode":"3699",
    "sg:province":"VIC",
    "wof:name":"Mountain Creek Motel",
    "wof:placetype":"venue"
},
  "geometry": {"coordinates":[147.16761779800001,-36.7428894043],"type":"Point"}
}