{
  "type": "Feature",
  "properties": {
    "addr:full":"7 Meehan Pl Campbelltown NSW 2560",
    "addr:housenumber":"7",
    "addr:postcode":"2560",
    "addr:street":"Meehan Pl",
    "iso:country":"AU",
    "sg:address":"7 Meehan Pl",
    "sg:city":"Campbelltown",
    "sg:classifiers":[
        {
            "category":"Building & Trades",
            "subcategory":"Landscaping Services",
            "type":"Services"
        }
    ],
    "sg:phone":"+61 2 9751 1515",
    "sg:postcode":"2560",
    "sg:province":"NSW",
    "sg:tags":[
        "stump",
        "tree",
        "felling",
        "removal"
    ],
    "wof:name":"Fred Barrass Tree Service",
    "wof:placetype":"venue"
},
  "geometry": {"coordinates":[150.81489563,-34.0764884949],"type":"Point"}
}