{
  "type": "Feature",
  "properties": {
    "iso:country":"AU",
    "sg:address":"L1/ 167- 171 Collins St",
    "sg:city":"Melbourne",
    "sg:classifiers":[
        {
            "category":"Banks & Credit Unions",
            "subcategory":"Financial Services",
            "type":"Services"
        }
    ],
    "sg:phone":"+61 1800 262 449",
    "sg:postcode":"3000",
    "sg:province":"VIC",
    "sg:tags":[
        "planning"
    ],
    "wof:name":"E.I.C.A Pty Ltd",
    "wof:placetype":"venue"
},
  "geometry": {"coordinates":[144.96815490700001,-37.8151321411],"type":"Point"}
}