{
  "type": "Feature",
  "properties": {
    "addr:full":"23 Brisbane Ave Barton ACT 2600",
    "addr:housenumber":"23",
    "addr:postcode":"2600",
    "addr:street":"Brisbane Ave",
    "iso:country":"AU",
    "sg:address":"23 Brisbane Ave",
    "sg:city":"Barton",
    "sg:classifiers":[
        {
            "category":"Fast Food",
            "type":"Food & Drink"
        }
    ],
    "sg:phone":"+61 2 6273 2702",
    "sg:postcode":"2600",
    "sg:province":"ACT",
    "sg:tags":[
        "away",
        "take"
    ],
    "wof:name":"Lachlan Court Cafe",
    "wof:placetype":"venue"
},
  "geometry": {"coordinates":[149.133834839,-35.3094444275],"type":"Point"}
}