{
  "type": "Feature",
  "properties": {
    "iso:country":"AU",
    "sg:address":"54c Fairfield Rd",
    "sg:city":"Guildford West",
    "sg:classifiers":[
        {
            "category":"Transit Center",
            "subcategory":"Freight",
            "type":"Transportation"
        }
    ],
    "sg:phone":"+61 412 628 577",
    "sg:postcode":"2161",
    "sg:province":"NSW",
    "sg:tags":[
        "forklift",
        "truck"
    ],
    "wof:name":"R & H Forklifts Pty Ltd",
    "wof:placetype":"venue"
},
  "geometry": {"coordinates":[150.962646484,-33.8456077576],"type":"Point"}
}