{
  "type": "Feature",
  "properties": {
    "addr:full":"23 Riviera Ave Avalon NSW 2107",
    "addr:housenumber":"23",
    "addr:postcode":"2107",
    "addr:street":"Riviera Ave",
    "iso:country":"AU",
    "sg:address":"23 Riviera Ave",
    "sg:city":"Avalon",
    "sg:classifiers":[
        {
            "category":"Building & Trades",
            "subcategory":"Landscaping Services",
            "type":"Services"
        }
    ],
    "sg:phone":"+61 2 9918 6963",
    "sg:postcode":"2107",
    "sg:province":"NSW",
    "sg:tags":[
        "stump",
        "tree",
        "felling",
        "removal"
    ],
    "wof:name":"Treeforce",
    "wof:placetype":"venue"
},
  "geometry": {"coordinates":[151.32395935100001,-33.6286621094],"type":"Point"}
}