{
  "type": "Feature",
  "properties": {
    "addr:full":"1605 Glenrowan-Myrtleford Rd Milawa VIC 3678",
    "addr:housenumber":"1605",
    "addr:postcode":"3678",
    "addr:street":"Glenrowan-Myrtleford Rd",
    "iso:country":"AU",
    "sg:address":"1605 Glenrowan-Myrtleford Rd",
    "sg:city":"Milawa",
    "sg:classifiers":[
        {
            "category":"Utilities",
            "subcategory":"Fuel Oil & Lpg",
            "type":"Services"
        }
    ],
    "sg:phone":"+61 3 5727 3887",
    "sg:postcode":"3678",
    "sg:province":"VIC",
    "sg:tags":[
        "olive"
    ],
    "wof:name":"The Olive Shop",
    "wof:placetype":"venue"
},
  "geometry": {"coordinates":[146.433227539,-36.4494857788],"type":"Point"}
}