{
  "type": "Feature",
  "properties": {
    "addr:full":"PO Box 5046 Maroochydore BC QLD 4558",
    "addr:postcode":"qld 4558",
    "iso:country":"AU",
    "sg:address":"PO Box 5046",
    "sg:city":"Maroochydore BC",
    "sg:classifiers":[
        {
            "category":"Building & Trades",
            "subcategory":"Construction",
            "type":"Services"
        }
    ],
    "sg:phone":"+61 7 5443 3738",
    "sg:postcode":"4558",
    "sg:province":"QLD",
    "sg:tags":[
        "decking",
        "contractor"
    ],
    "wof:name":"Brian Creese Renovations Pty Ltd",
    "wof:placetype":"venue"
},
  "geometry": {"coordinates":[153.09274292000001,-26.6657295227],"type":"Point"}
}