{
  "type": "Feature",
  "properties": {
    "iso:country":"AU",
    "sg:address":"1 Hill St",
    "sg:city":"Lobethal",
    "sg:classifiers":[
        {
            "category":"Home & Garden",
            "subcategory":"Carpets & Floor Coverings",
            "type":"Retail Goods"
        }
    ],
    "sg:phone":"+61 8 8389 6320",
    "sg:postcode":"5241",
    "sg:province":"SA",
    "sg:tags":[
        "tile",
        "wall",
        "layer"
    ],
    "wof:name":"Creative Tile Works Pty Ltd",
    "wof:placetype":"venue"
},
  "geometry": {"coordinates":[138.87875366200001,-34.9031028748],"type":"Point"}
}