{
  "type": "Feature",
  "properties": {
    "addr:full":"25 Moate St Georgetown NSW 2298",
    "addr:housenumber":"25",
    "addr:postcode":"2298",
    "addr:street":"Moate St",
    "iso:country":"AU",
    "sg:address":"25 Moate St",
    "sg:city":"Georgetown",
    "sg:classifiers":[
        {
            "category":"Utilities",
            "subcategory":"Electric",
            "type":"Services"
        }
    ],
    "sg:phone":"+61 2 4967 5277",
    "sg:postcode":"2298",
    "sg:province":"NSW",
    "sg:tags":[
        "advisory",
        "lighting",
        "power"
    ],
    "wof:name":"Godbee Electrical Pty Ltd",
    "wof:placetype":"venue"
},
  "geometry": {"coordinates":[151.73098754899999,-32.9085426331],"type":"Point"}
}