{
  "type": "Feature",
  "properties": {
    "addr:full":"4/ 18 Morley Ave Kingswood NSW 2747",
    "addr:housenumber":"/ 18",
    "addr:postcode":"2747",
    "addr:street":"Morley Ave",
    "iso:country":"AU",
    "sg:address":"4/ 18 Morley Ave",
    "sg:city":"Kingswood",
    "sg:classifiers":[
        {
            "category":"Retail",
            "subcategory":"Auto Repair",
            "type":"Services"
        }
    ],
    "sg:phone":"+61 2 4736 4752",
    "sg:postcode":"2747",
    "sg:province":"NSW",
    "sg:tags":[
        "repairer",
        "motor",
        "engineer"
    ],
    "wof:name":"Brown Ivan",
    "wof:placetype":"venue"
},
  "geometry": {"coordinates":[150.72836303700001,-33.7593727112],"type":"Point"}
}