{
  "type": "Feature",
  "properties": {
    "addr:full":"197 Union Rd Ascot Vale VIC 3032",
    "addr:housenumber":"197",
    "addr:postcode":"3032",
    "addr:street":"Union Rd",
    "iso:country":"AU",
    "sg:address":"197 Union Rd",
    "sg:city":"Ascot Vale",
    "sg:classifiers":[
        {
            "category":"Health Services",
            "subcategory":"Optometrist",
            "type":"Services"
        }
    ],
    "sg:phone":"+61 3 9375 3111",
    "sg:postcode":"3032",
    "sg:province":"VIC",
    "wof:name":"Nearchou Christine",
    "wof:placetype":"venue"
},
  "geometry": {"coordinates":[144.915817,-37.773067],"type":"Point"}
}