{
  "type": "Feature",
  "properties": {
    "addr:full":"Factory 9/ 100 New St Ringwood VIC 3134",
    "addr:housenumber":"/ 100",
    "addr:postcode":"3134",
    "addr:street":"New St",
    "iso:country":"AU",
    "sg:address":"Factory 9/ 100 New St",
    "sg:city":"Ringwood",
    "sg:classifiers":[
        {
            "category":"Social Services",
            "subcategory":"Job Training",
            "type":"Services"
        }
    ],
    "sg:phone":"+61 3 9879 7622",
    "sg:postcode":"3134",
    "sg:province":"VIC",
    "sg:tags":[
        "hire",
        "computer",
        "leasing"
    ],
    "wof:name":"Sun Short Term Rentals Pty Ltd",
    "wof:placetype":"venue"
},
  "geometry": {"coordinates":[145.220306397,-37.8212242126],"type":"Point"}
}