{
  "type": "Feature",
  "properties": {
    "iso:country":"AU",
    "sg:address":"2741 Gold Coast Hwy",
    "sg:city":"Broadbeach",
    "sg:classifiers":[
        {
            "category":"Government",
            "subcategory":"Court House",
            "type":"Public Place"
        }
    ],
    "sg:phone":"+61 7 5579 6000",
    "sg:postcode":"4218",
    "sg:province":"QLD",
    "sg:tags":[
        "personal",
        "marriage",
        "family",
        "counselling"
    ],
    "wof:name":"Lifeline Gold Coast",
    "wof:placetype":"venue"
},
  "geometry": {"coordinates":[153.42945861800001,-28.0259685516],"type":"Point"}
}