{
  "type": "Feature",
  "properties": {
    "iso:country":"AU",
    "sg:address":"124 Wray Ave",
    "sg:city":"Fremantle",
    "sg:classifiers":[
        {
            "category":"Health Services",
            "subcategory":"Health Practitioner",
            "type":"Services"
        }
    ],
    "sg:phone":"+61 8 9335 7733",
    "sg:postcode":"6160",
    "sg:province":"WA",
    "sg:tags":[
        "physiotherapist"
    ],
    "wof:name":"Vocare Physiotherapy",
    "wof:placetype":"venue"
},
  "geometry": {"coordinates":[115.758049,-32.062149],"type":"Point"}
}