{
  "type": "Feature",
  "properties": {
    "addr:full":"23 Bridge St Korumburra VIC 3950",
    "addr:housenumber":"23",
    "addr:postcode":"3950",
    "addr:street":"Bridge St",
    "iso:country":"AU",
    "sg:address":"23 Bridge St",
    "sg:city":"Korumburra",
    "sg:classifiers":[
        {
            "category":"Building & Trades",
            "subcategory":"Pest Control",
            "type":"Services"
        }
    ],
    "sg:phone":"+61 3 5655 1349",
    "sg:postcode":"3950",
    "sg:province":"VIC",
    "wof:name":"Strzelecki Pest Management",
    "wof:placetype":"venue"
},
  "geometry": {"coordinates":[145.82403564399999,-38.4342155457],"type":"Point"}
}