{
  "type": "Feature",
  "properties": {
    "addr:full":"135 Allan St Kyabram VIC 3620",
    "addr:housenumber":"135",
    "addr:postcode":"3620",
    "addr:street":"Allan St",
    "iso:country":"AU",
    "sg:address":"135 Allan St",
    "sg:city":"Kyabram",
    "sg:classifiers":[
        {
            "category":"Food & Beverages",
            "subcategory":"Bakery",
            "type":"Retail Goods"
        }
    ],
    "sg:phone":"+61 3 5852 1208",
    "sg:postcode":"3620",
    "sg:province":"VIC",
    "sg:tags":[
        "cake",
        "shop",
        "pastry"
    ],
    "wof:name":"Kyabram Bakery",
    "wof:placetype":"venue"
},
  "geometry": {"coordinates":[145.045684814,-36.3133125305],"type":"Point"}
}