{
  "type": "Feature",
  "properties": {
    "addr:full":"23 Windsor Rd Richmond NSW 2753",
    "addr:housenumber":"23",
    "addr:postcode":"2753",
    "addr:street":"Windsor Rd",
    "iso:country":"AU",
    "sg:address":"23 Windsor Rd",
    "sg:city":"Richmond",
    "sg:classifiers":[
        {
            "category":"Building & Trades",
            "subcategory":"Plumbing",
            "type":"Services"
        }
    ],
    "sg:phone":"+61 2 4578 3871",
    "sg:postcode":"2753",
    "sg:province":"NSW",
    "sg:tags":[
        "plumber",
        "gasfitters"
    ],
    "wof:name":"K.M.T. Drainage Pty Ltd",
    "wof:placetype":"venue"
},
  "geometry": {"coordinates":[150.760665894,-33.6010284424],"type":"Point"}
}