{
  "type": "Feature",
  "properties": {
    "iso:country":"AU",
    "sg:address":"6 Avoca Crt",
    "sg:city":"Croydon North",
    "sg:classifiers":[
        {
            "category":"Shopping",
            "subcategory":"Computers & Home Electronics",
            "type":"Retail Goods"
        }
    ],
    "sg:phone":"+61 3 9727 2868",
    "sg:postcode":"3136",
    "sg:province":"VIC",
    "sg:tags":[
        "cleaning"
    ],
    "wof:name":"CompuCare Eastern Pty Ltd",
    "wof:placetype":"venue"
},
  "geometry": {"coordinates":[145.29049682600001,-37.7667427063],"type":"Point"}
}