{
  "type": "Feature",
  "properties": {
    "addr:full":"Shop 1, 156 King William Rd Hyde Park SA 5061",
    "addr:housenumber":"shop 1 156",
    "addr:postcode":"5061",
    "addr:street":"King William Rd",
    "iso:country":"AU",
    "sg:address":"Shop 1, 156 King William Rd",
    "sg:city":"Hyde Park",
    "sg:classifiers":[
        {
            "category":"Cafe",
            "type":"Food & Drink"
        }
    ],
    "sg:phone":"+61 8 8299 9661",
    "sg:postcode":"5061",
    "sg:province":"SA",
    "wof:name":"Cibo Espresso",
    "wof:placetype":"venue"
},
  "geometry": {"coordinates":[138.599884033,-34.954410553],"type":"Point"}
}