{
  "type": "Feature",
  "properties": {
    "addr:full":"109 Toolooa St Gladstone QLD 4680",
    "addr:housenumber":"109",
    "addr:postcode":"4680",
    "addr:street":"Toolooa St",
    "iso:country":"AU",
    "sg:address":"109 Toolooa St",
    "sg:city":"Gladstone",
    "sg:classifiers":[
        {
            "category":"Shopping",
            "subcategory":"Pets & Pet Supplies",
            "type":"Retail Goods"
        }
    ],
    "sg:phone":"+61 7 4972 2332",
    "sg:postcode":"4680",
    "sg:province":"QLD",
    "sg:tags":[
        "food"
    ],
    "wof:name":"Gladstone Aquaria",
    "wof:placetype":"venue"
},
  "geometry": {"coordinates":[151.26893615700001,-23.8557186127],"type":"Point"}
}