{
  "type": "Feature",
  "properties": {
    "addr:full":"Unit 5, 202 Harbord Rd Brookvale NSW 2100",
    "addr:housenumber":"202",
    "addr:postcode":"2100",
    "addr:street":"Harbord Rd",
    "iso:country":"AU",
    "sg:address":"Unit 5, 202 Harbord Rd",
    "sg:city":"Brookvale",
    "sg:classifiers":[
        {
            "category":"Home & Garden",
            "subcategory":"Carpets & Floor Coverings",
            "type":"Retail Goods"
        }
    ],
    "sg:phone":"+61 2 9939 4015",
    "sg:postcode":"2100",
    "sg:province":"NSW",
    "sg:tags":[
        "laying",
        "supply"
    ],
    "wof:name":"Australian Flooring Supplies",
    "wof:placetype":"venue"
},
  "geometry": {"coordinates":[151.27981567399999,-33.7626457214],"type":"Point"}
}