{
  "type": "Feature",
  "properties": {
    "iso:country":"AU",
    "sg:address":"1 Main St",
    "sg:city":"Eildon",
    "sg:classifiers":[
        {
            "category":"Fast Food",
            "type":"Food & Drink"
        }
    ],
    "sg:phone":"+61 3 5774 2144",
    "sg:postcode":"3713",
    "sg:province":"VIC",
    "sg:tags":[
        "away",
        "take"
    ],
    "wof:name":"Eildon Billabong Take-Away",
    "wof:placetype":"venue"
},
  "geometry": {"coordinates":[145.90846252399999,-37.2340431213],"type":"Point"}
}