{
  "type": "Feature",
  "properties": {
    "addr:full":"6 Percival St Rosebud West VIC 3940",
    "addr:housenumber":"6",
    "addr:postcode":"3940",
    "addr:street":"Percival St",
    "iso:country":"AU",
    "sg:address":"6 Percival St",
    "sg:city":"Rosebud West",
    "sg:classifiers":[
        {
            "category":"Social Services",
            "subcategory":"Child Care",
            "type":"Services"
        }
    ],
    "sg:phone":"+61 3 5981 1609",
    "sg:postcode":"3940",
    "sg:province":"VIC",
    "sg:tags":[
        "baby",
        "sitter"
    ],
    "wof:name":"Southern Peninsula Babysitting & Home Help Agency",
    "wof:placetype":"venue"
},
  "geometry": {"coordinates":[144.88044738799999,-38.3631019592],"type":"Point"}
}