{
  "type": "Feature",
  "properties": {
    "iso:country":"AU",
    "sg:address":"4 Swan Ave",
    "sg:city":"Flinders Park",
    "sg:classifiers":[
        {
            "category":"Home & Garden",
            "subcategory":"Hardware",
            "type":"Retail Goods"
        }
    ],
    "sg:phone":"+61 411 697 246",
    "sg:postcode":"5025",
    "sg:province":"SA",
    "sg:tags":[
        "pumping",
        "contractor"
    ],
    "wof:name":"Flinders Park Concrete Pumps S.A. Pty Ltd",
    "wof:placetype":"venue"
},
  "geometry": {"coordinates":[138.535766602,-34.9124107361],"type":"Point"}
}