{
  "type": "Feature",
  "properties": {
    "iso:country":"AU",
    "sg:address":"90 Sparkes Rd",
    "sg:city":"Bray Park",
    "sg:classifiers":[
        {
            "category":"Shopping",
            "subcategory":"Party Supplies",
            "type":"Retail Goods"
        }
    ],
    "sg:phone":"+61 7 3889 8820",
    "sg:postcode":"4500",
    "sg:province":"QLD",
    "sg:tags":[
        "selling",
        "plan"
    ],
    "wof:name":"Hush-Hush",
    "wof:placetype":"venue"
},
  "geometry": {"coordinates":[152.972824097,-27.2933578491],"type":"Point"}
}