{
  "type": "Feature",
  "properties": {
    "addr:full":"159-163 Midland Hwy Epsom VIC 3551",
    "addr:housenumber":"159-163",
    "addr:postcode":"3551",
    "addr:street":"Midland Hwy",
    "iso:country":"AU",
    "sg:address":"159-163 Midland Hwy",
    "sg:city":"Epsom",
    "sg:classifiers":[
        {
            "category":"Wholesale",
            "subcategory":"Machinery & Supplies",
            "type":"Manufacturing & Wholesale Goods"
        }
    ],
    "sg:phone":"+61 3 5448 4455",
    "sg:postcode":"3551",
    "sg:province":"VIC",
    "sg:tags":[
        "agricultural"
    ],
    "wof:name":"K.V. Equipment Pty Ltd",
    "wof:placetype":"venue"
},
  "geometry": {"coordinates":[144.315750122,-36.7063446045],"type":"Point"}
}