{
  "type": "Feature",
  "properties": {
    "iso:country":"AU",
    "sg:address":"MC Box 121 Eastern Mail Cntr",
    "sg:city":"Nunawading",
    "sg:classifiers":[
        {
            "category":"Professional",
            "subcategory":"Detective & Security Services",
            "type":"Services"
        }
    ],
    "sg:phone":"+61 411 198 435",
    "sg:postcode":"3131",
    "sg:province":"VIC",
    "sg:tags":[
        "domestic",
        "alarm",
        "commercial",
        "burglar"
    ],
    "wof:name":"P.F.M. Antennas",
    "wof:placetype":"venue"
},
  "geometry": {"coordinates":[145.17576599099999,-37.8192710876],"type":"Point"}
}