{
  "type": "Feature",
  "properties": {
    "addr:full":"356 Orange Grove Rd Salisbury QLD 4107",
    "addr:housenumber":"356",
    "addr:postcode":"4107",
    "addr:street":"Orange Grove Rd",
    "iso:country":"AU",
    "sg:address":"356 Orange Grove Rd",
    "sg:city":"Salisbury",
    "sg:classifiers":[
        {
            "category":"Retail",
            "subcategory":"Auto Rental",
            "type":"Services"
        }
    ],
    "sg:phone":"+61 7 3277 4866",
    "sg:postcode":"4107",
    "sg:province":"QLD",
    "sg:tags":[
        "bus",
        "truck"
    ],
    "wof:name":"Handy Utes & Cars",
    "wof:placetype":"venue"
},
  "geometry": {"coordinates":[153.041183472,-27.5536022186],"type":"Point"}
}