{
  "type": "Feature",
  "properties": {
    "addr:full":"Century 21 House 5- 21 Carter Rd Menai NSW 2234",
    "addr:housenumber":"5 21",
    "addr:postcode":"2234",
    "addr:street":"Carter Rd",
    "iso:country":"AU",
    "sg:address":"Century 21 House 5- 21 Carter Rd",
    "sg:city":"Menai",
    "sg:classifiers":[
        {
            "category":"Real Estate",
            "subcategory":"Real Estate Agent",
            "type":"Services"
        }
    ],
    "sg:phone":"+61 2 9543 2111",
    "sg:postcode":"2234",
    "sg:province":"NSW",
    "wof:name":"Century 21 Realty One (Menai)",
    "wof:placetype":"venue"
},
  "geometry": {"coordinates":[151.01243591299999,-34.0167121887],"type":"Point"}
}