{
  "type": "Feature",
  "properties": {
    "iso:country":"AU",
    "sg:address":"11 Wilson St",
    "sg:city":"Colac",
    "sg:classifiers":[
        {
            "category":"Wholesale",
            "subcategory":"Machinery & Supplies",
            "type":"Manufacturing & Wholesale Goods"
        }
    ],
    "sg:phone":"+61 3 5231 5719",
    "sg:postcode":"3250",
    "sg:province":"VIC",
    "sg:tags":[
        "agricultural"
    ],
    "wof:name":"Colac Tractor Wreckers",
    "wof:placetype":"venue"
},
  "geometry": {"coordinates":[143.60386700000001,-38.34502],"type":"Point"}
}