{
  "type": "Feature",
  "properties": {
    "iso:country":"AU",
    "sg:address":"1320 Pittwater Rd",
    "sg:city":"Narrabeen",
    "sg:classifiers":[
        {
            "category":"Shopping",
            "subcategory":"Optical Goods",
            "type":"Retail Goods"
        }
    ],
    "sg:phone":"+61 2 9913 8745",
    "sg:postcode":"2101",
    "sg:province":"NSW",
    "sg:tags":[
        "dispenser",
        "prescription"
    ],
    "wof:name":"Tom O&#039;Neill Optical Dispenser",
    "wof:placetype":"venue"
},
  "geometry": {"coordinates":[151.29718,-33.715328],"type":"Point"}
}