{
  "type": "Feature",
  "properties": {
    "addr:full":"68 Melville Rd Brunswick West VIC 3055",
    "addr:housenumber":"68",
    "addr:postcode":"3055",
    "addr:street":"Melville Rd",
    "iso:country":"AU",
    "sg:address":"68 Melville Rd",
    "sg:city":"Brunswick West",
    "sg:classifiers":[
        {
            "category":"Health Services",
            "subcategory":"Chiropractor",
            "type":"Services"
        }
    ],
    "sg:phone":"+61 3 9380 8099",
    "sg:postcode":"3055",
    "sg:province":"VIC",
    "wof:name":"Roumel V. Dr MCAA",
    "wof:placetype":"venue"
},
  "geometry": {"coordinates":[144.94424438499999,-37.7631530762],"type":"Point"}
}