{
  "type": "Feature",
  "properties": {
    "iso:country":"AU",
    "sg:address":"24 Alexandra Pl",
    "sg:city":"Murarrie",
    "sg:classifiers":[
        {
            "category":"Autos & Motor Vehicles",
            "subcategory":"Automobile Sales",
            "type":"Retail Goods"
        }
    ],
    "sg:phone":"+61 7 3390 7007",
    "sg:postcode":"4172",
    "sg:province":"QLD",
    "sg:tags":[
        "equipment",
        "trailer"
    ],
    "wof:name":"Tefco Trailers (QLD) Pty Ltd",
    "wof:placetype":"venue"
},
  "geometry": {"coordinates":[153.10739135700001,-27.4590053558],"type":"Point"}
}