{
  "type": "Feature",
  "properties": {
    "iso:country":"AU",
    "sg:address":"10 Swanston St",
    "sg:city":"Preston",
    "sg:classifiers":[
        {
            "category":"Building & Trades",
            "subcategory":"Construction",
            "type":"Services"
        }
    ],
    "sg:phone":"+61 3 9484 0586",
    "sg:postcode":"3072",
    "sg:province":"VIC",
    "sg:tags":[
        "rendering",
        "cement"
    ],
    "wof:name":"Multitex Corporation Pty Ltd",
    "wof:placetype":"venue"
},
  "geometry": {"coordinates":[145.03321838400001,-37.7479095459],"type":"Point"}
}