{
  "type": "Feature",
  "properties": {
    "addr:full":"185 Macquarie St Sydney NSW 2000",
    "addr:housenumber":"185",
    "addr:postcode":"2000",
    "addr:street":"Macquarie St",
    "iso:country":"AU",
    "sg:address":"185 Macquarie St",
    "sg:city":"Sydney",
    "sg:classifiers":[
        {
            "category":"Insurance",
            "subcategory":"Hazard Insurance",
            "type":"Services"
        }
    ],
    "sg:phone":"+61 2 9221 1155",
    "sg:postcode":"2000",
    "sg:province":"NSW",
    "sg:tags":[
        "fire",
        "accident",
        "marine"
    ],
    "wof:name":"FAI Workers Compensation (NSW) Ltd",
    "wof:placetype":"venue"
},
  "geometry": {"coordinates":[151.21220398,-33.8671035767],"type":"Point"}
}