{
  "type": "Feature",
  "properties": {
    "iso:country":"AU",
    "sg:address":"16 Forrest St",
    "sg:city":"Subiaco",
    "sg:classifiers":[
        {
            "category":"Shopping",
            "subcategory":"Clothing, Apparel, & Fashions",
            "type":"Retail Goods"
        }
    ],
    "sg:phone":"+61 8 9388 1992",
    "sg:postcode":"6008",
    "sg:province":"WA",
    "sg:tags":[
        "maternity",
        "wear"
    ],
    "sg:website":"http://www.aurawoman.com.au",
    "wof:name":"Aura Woman",
    "wof:placetype":"venue"
},
  "geometry": {"coordinates":[115.82247924799999,-31.9477787018],"type":"Point"}
}