{
  "type": "Feature",
  "properties": {
    "addr:full":"60 Clive Rd Birkdale QLD 4159",
    "addr:housenumber":"60",
    "addr:postcode":"4159",
    "addr:street":"Clive Rd",
    "iso:country":"AU",
    "sg:address":"60 Clive Rd",
    "sg:city":"Birkdale",
    "sg:classifiers":[
        {
            "category":"Communications",
            "subcategory":"Film & Video Production",
            "type":"Services"
        }
    ],
    "sg:phone":"+61 7 3822 4707",
    "sg:postcode":"4159",
    "sg:province":"QLD",
    "sg:tags":[
        "fan",
        "blower"
    ],
    "wof:name":"Turbo Air Technology Pty Ltd",
    "wof:placetype":"venue"
},
  "geometry": {"coordinates":[153.202194214,-27.497625351],"type":"Point"}
}