{
  "type": "Feature",
  "properties": {
    "addr:full":"Showground Shopping Centre 157 Mulgrave Road Cairns QLD 4870",
    "addr:housenumber":"157",
    "addr:postcode":"4870",
    "addr:street":"Mulgrave Road",
    "iso:country":"AU",
    "sg:address":"Showground Shopping Centre 157 Mulgrave Road",
    "sg:city":"Cairns",
    "sg:classifiers":[
        {
            "category":"Health Services",
            "subcategory":"Doctor",
            "type":"Services"
        }
    ],
    "sg:phone":"+61 7 4051 5199",
    "sg:postcode":"4870",
    "sg:province":"QLD",
    "sg:tags":[
        "podiatrist"
    ],
    "wof:name":"Jeffrey Dowdle",
    "wof:placetype":"venue"
},
  "geometry": {"coordinates":[145.74366760300001,-16.9398193359],"type":"Point"}
}