{
  "type": "Feature",
  "properties": {
    "iso:country":"AU",
    "sg:address":"217b Kororoit Creek Rd",
    "sg:city":"Williamstown",
    "sg:classifiers":[
        {
            "category":"Retail",
            "subcategory":"Repair Shop",
            "type":"Services"
        }
    ],
    "sg:phone":"+61 3 9391 6324",
    "sg:postcode":"3016",
    "sg:province":"VIC",
    "sg:tags":[
        "upholsterer"
    ],
    "wof:name":"Robert The Chair Doctor",
    "wof:placetype":"venue"
},
  "geometry": {"coordinates":[144.859771728,-37.8545379639],"type":"Point"}
}