{
  "type": "Feature",
  "properties": {
    "addr:full":"Shp98a/ 43 Yirrigan Drv Mirrabooka WA 6061",
    "addr:postcode":"6061",
    "addr:street":"Yirrigan Drv",
    "iso:country":"AU",
    "sg:address":"Shp98a/ 43 Yirrigan Drv",
    "sg:city":"Mirrabooka",
    "sg:classifiers":[
        {
            "category":"Shopping",
            "subcategory":"Baby Store",
            "type":"Retail Goods"
        }
    ],
    "sg:phone":"+61 8 9344 6770",
    "sg:postcode":"6061",
    "sg:province":"WA",
    "sg:tags":[
        "children's",
        "wear"
    ],
    "wof:name":"Cute Kids Boutique",
    "wof:placetype":"venue"
},
  "geometry": {"coordinates":[115.85492706300001,-31.853061676],"type":"Point"}
}