{
  "type": "Feature",
  "properties": {
    "iso:country":"AU",
    "sg:address":"Suite 5, Level 1, 119 Newton Rd",
    "sg:city":"Wetherill Park",
    "sg:classifiers":[
        {
            "category":"Real Estate",
            "subcategory":"Real Estate Agent",
            "type":"Services"
        }
    ],
    "sg:phone":"+61 2 9756 5518",
    "sg:postcode":"2164",
    "sg:province":"NSW",
    "wof:name":"Coldwell Banker Commercial Bellevue",
    "wof:placetype":"venue"
},
  "geometry": {"coordinates":[150.893432617,-33.8448944092],"type":"Point"}
}