{
  "type": "Feature",
  "properties": {
    "iso:country":"AU",
    "sg:address":"49 Pinetree Gully Rd",
    "sg:city":"Willetton",
    "sg:classifiers":[
        {
            "category":"Building & Trades",
            "subcategory":"Construction",
            "type":"Services"
        }
    ],
    "sg:phone":"+61 8 9457 4046",
    "sg:postcode":"6155",
    "sg:province":"WA",
    "sg:tags":[
        "contractor"
    ],
    "wof:name":"KCB Construction",
    "wof:placetype":"venue"
},
  "geometry": {"coordinates":[115.88414,-32.053387],"type":"Point"}
}