{
  "type": "Feature",
  "properties": {
    "iso:country":"AU",
    "sg:address":"Shp T409 Robina Town Centre Drv",
    "sg:city":"Robina",
    "sg:classifiers":[
        {
            "category":"Personal",
            "type":"Services"
        }
    ],
    "sg:phone":"+61 7 5580 8788",
    "sg:postcode":"4226",
    "sg:province":"QLD",
    "sg:tags":[
        "gift"
    ],
    "wof:name":"Perfume Direct",
    "wof:placetype":"venue"
},
  "geometry": {"coordinates":[153.38783264200001,-28.0696353912],"type":"Point"}
}