{
  "type": "Feature",
  "properties": {
    "addr:full":"11 Enterprise St Anula NT 0812",
    "addr:housenumber":"11",
    "addr:postcode":"nt 0812",
    "addr:street":"Enterprise St",
    "iso:country":"AU",
    "sg:address":"11 Enterprise St",
    "sg:city":"Anula",
    "sg:classifiers":[
        {
            "category":"Utilities",
            "subcategory":"Electric",
            "type":"Services"
        }
    ],
    "sg:phone":"+61 418 807 715",
    "sg:postcode":"0812",
    "sg:province":"NT",
    "sg:tags":[
        "electrical",
        "contractor"
    ],
    "wof:name":"GSM Contracting (NT) Pty Ltd",
    "wof:placetype":"venue"
},
  "geometry": {"coordinates":[130.896118,-12.392905],"type":"Point"}
}