{
  "type": "Feature",
  "properties": {
    "iso:country":"AU",
    "sg:address":"44 Jannali Rd",
    "sg:city":"Alonnah",
    "sg:classifiers":[
        {
            "category":"Building & Trades",
            "subcategory":"Plumbing",
            "type":"Services"
        }
    ],
    "sg:phone":"+61 3 6293 1322",
    "sg:postcode":"7150",
    "sg:province":"TAS",
    "sg:tags":[
        "plumber",
        "gasfitters"
    ],
    "wof:name":"Bruny Island Plumbing",
    "wof:placetype":"venue"
},
  "geometry": {"coordinates":[147.25042724599999,-43.3098220825],"type":"Point"}
}