{
  "type": "Feature",
  "properties": {
    "addr:full":"32 Warkil St Cobram NSW 3644",
    "addr:housenumber":"32",
    "addr:postcode":"3644",
    "addr:street":"Warkil St",
    "iso:country":"AU",
    "sg:address":"32 Warkil St",
    "sg:city":"Cobram",
    "sg:classifiers":[
        {
            "category":"Utilities",
            "subcategory":"Electric",
            "type":"Services"
        }
    ],
    "sg:phone":"+61 428 565 747",
    "sg:postcode":"3644",
    "sg:province":"NSW",
    "sg:tags":[
        "electrical",
        "contractor"
    ],
    "wof:name":"BEC Group Pty Ltd",
    "wof:placetype":"venue"
},
  "geometry": {"coordinates":[145.65467834500001,-35.913848877],"type":"Point"}
}