{
  "type": "Feature",
  "properties": {
    "iso:country":"AU",
    "sg:address":"62 Aldam Rd",
    "sg:city":"Seaford",
    "sg:classifiers":[
        {
            "category":"Building & Trades",
            "subcategory":"Construction",
            "type":"Services"
        }
    ],
    "sg:phone":"+61 8 8386 0489",
    "sg:postcode":"5169",
    "sg:province":"SA",
    "sg:tags":[
        "concrete",
        "contractor"
    ],
    "wof:name":"Pete Westerhoff Concreting Service",
    "wof:placetype":"venue"
},
  "geometry": {"coordinates":[138.469650269,-35.1777839661],"type":"Point"}
}