{
  "type": "Feature",
  "properties": {
    "iso:country":"AU",
    "sg:address":"129 Storey St",
    "sg:city":"Maroubra",
    "sg:classifiers":[
        {
            "category":"Building & Trades",
            "subcategory":"Construction",
            "type":"Services"
        }
    ],
    "sg:phone":"+61 2 9344 5201",
    "sg:postcode":"2035",
    "sg:province":"NSW",
    "sg:tags":[
        "renovation",
        "alterations",
        "extension",
        "contractor"
    ],
    "wof:name":"W R Building & Maintenance",
    "wof:placetype":"venue"
},
  "geometry": {"coordinates":[151.23948669399999,-33.9371948242],"type":"Point"}
}