{
  "type": "Feature",
  "properties": {
    "addr:full":"83 Freeth St Ormiston QLD 4160",
    "addr:housenumber":"83",
    "addr:postcode":"4160",
    "addr:street":"Freeth St",
    "iso:country":"AU",
    "sg:address":"83 Freeth St",
    "sg:city":"Ormiston",
    "sg:classifiers":[
        {
            "category":"Social Services",
            "subcategory":"Retirement Home",
            "type":"Services"
        }
    ],
    "sg:phone":"+61 7 3821 1080",
    "sg:postcode":"4160",
    "sg:province":"QLD",
    "sg:tags":[
        "village"
    ],
    "wof:name":"Aveo Cleveland Gardens",
    "wof:placetype":"venue"
},
  "geometry": {"coordinates":[153.255569458,-27.5217037201],"type":"Point"}
}