{
  "type": "Feature",
  "properties": {
    "addr:full":"39 McMeekin Rd Warrnambool VIC 3280",
    "addr:housenumber":"39",
    "addr:postcode":"3280",
    "addr:street":"Mcmeekin Rd",
    "iso:country":"AU",
    "sg:address":"39 McMeekin Rd",
    "sg:city":"Warrnambool",
    "sg:classifiers":[
        {
            "category":"Retail",
            "subcategory":"Auto Repair",
            "type":"Services"
        }
    ],
    "sg:phone":"+61 3 5561 3959",
    "sg:postcode":"3280",
    "sg:province":"VIC",
    "sg:tags":[
        "repairer",
        "motor",
        "engineer"
    ],
    "wof:name":"Warrnambool Automatics",
    "wof:placetype":"venue"
},
  "geometry": {"coordinates":[142.459594727,-38.3741912842],"type":"Point"}
}