{
  "type": "Feature",
  "properties": {
    "addr:full":"Shop 58, Munno Para Sh/Ctr, Main North Rd Smithfield SA 5114",
    "addr:housenumber":"shop 58",
    "addr:postcode":"5114",
    "addr:street":"Main North Rd",
    "iso:country":"AU",
    "sg:address":"Shop 58, Munno Para Sh/Ctr, Main North Rd",
    "sg:city":"Smithfield",
    "sg:classifiers":[
        {
            "category":"Food & Beverages",
            "subcategory":"Bakery",
            "type":"Retail Goods"
        }
    ],
    "sg:phone":"+61 8 8284 0633",
    "sg:postcode":"5114",
    "sg:province":"SA",
    "sg:tags":[
        "cake",
        "shop",
        "pastry"
    ],
    "wof:name":"The Cheesecake Shop",
    "wof:placetype":"venue"
},
  "geometry": {"coordinates":[138.69218444800001,-34.6852340698],"type":"Point"}
}