{
  "type": "Feature",
  "properties": {
    "addr:full":"43-47 St Pauls St Randwick NSW 2031",
    "addr:housenumber":"43-47",
    "addr:postcode":"2031",
    "addr:street":"St Pauls St",
    "iso:country":"AU",
    "sg:address":"43-47 St Pauls St",
    "sg:city":"Randwick",
    "sg:classifiers":[
        {
            "category":"Cinema",
            "subcategory":"Movie Theater",
            "type":"Entertainment"
        }
    ],
    "sg:phone":"+61 2 9399 5722",
    "sg:postcode":"2031",
    "sg:province":"NSW",
    "wof:name":"Ritz Cinema",
    "wof:placetype":"venue"
},
  "geometry": {"coordinates":[151.243606567,-33.9202041626],"type":"Point"}
}