{
  "type": "Feature",
  "properties": {
    "iso:country":"AU",
    "sg:address":"1/ 22 Chestnut St",
    "sg:city":"Surrey Hills",
    "sg:classifiers":[
        {
            "category":"Building & Trades",
            "subcategory":"Landscaping Services",
            "type":"Services"
        }
    ],
    "sg:phone":"+61 411 463 292",
    "sg:postcode":"3127",
    "sg:province":"VIC",
    "sg:tags":[
        "designer",
        "landscape",
        "contractor"
    ],
    "wof:name":"Simon Huxtable Horticultrual Services",
    "wof:placetype":"venue"
},
  "geometry": {"coordinates":[145.11088562,-37.8345146179],"type":"Point"}
}