{
  "type": "Feature",
  "properties": {
    "iso:country":"AU",
    "sg:address":"1 & 2/ 17- 21 Hunter St",
    "sg:city":"Parramatta",
    "sg:classifiers":[
        {
            "category":"Health Services",
            "subcategory":"Dentist",
            "type":"Services"
        }
    ],
    "sg:phone":"+61 2 9635 4222",
    "sg:postcode":"1740",
    "sg:province":"NSW",
    "wof:name":"Paton Guy, Tino Mercado & Fiona Little DRs",
    "wof:placetype":"venue"
},
  "geometry": {"coordinates":[151.03553772000001,-33.8424835205],"type":"Point"}
}