{
  "type": "Feature",
  "properties": {
    "addr:full":"7 Shelley Crt Andergrove QLD 4740",
    "addr:housenumber":"7",
    "addr:postcode":"4740",
    "addr:street":"Shelley Crt",
    "iso:country":"AU",
    "sg:address":"7 Shelley Crt",
    "sg:city":"Andergrove",
    "sg:classifiers":[
        {
            "category":"Personal",
            "type":"Services"
        }
    ],
    "sg:phone":"+61 7 4955 2041",
    "sg:postcode":"4740",
    "sg:province":"QLD",
    "sg:tags":[
        "dressmaker"
    ],
    "wof:name":"Glitz &#039;n&#039; Glamour",
    "wof:placetype":"venue"
},
  "geometry": {"coordinates":[149.183899,-21.101645],"type":"Point"}
}