{
  "type": "Feature",
  "properties": {
    "addr:full":"10 Crouch St Ararat VIC 3377",
    "addr:housenumber":"10",
    "addr:postcode":"3377",
    "addr:street":"Crouch St",
    "iso:country":"AU",
    "sg:address":"10 Crouch St",
    "sg:city":"Ararat",
    "sg:classifiers":[
        {
            "category":"Retail",
            "subcategory":"Repair Shop",
            "type":"Services"
        }
    ],
    "sg:phone":"+61 3 5352 3556",
    "sg:postcode":"3377",
    "sg:province":"VIC",
    "sg:tags":[
        "upholsterer"
    ],
    "wof:name":"Ararat Upholstery",
    "wof:placetype":"venue"
},
  "geometry": {"coordinates":[142.924102783,-37.289276123],"type":"Point"}
}