{
  "type": "Feature",
  "properties": {
    "addr:full":"Cnr Lathlain & Cohen Sts Belconnen ACT 2617",
    "addr:postcode":"2617",
    "addr:street":"Cnr",
    "iso:country":"AU",
    "sg:address":"Cnr Lathlain & Cohen Sts",
    "sg:city":"Belconnen",
    "sg:classifiers":[
        {
            "category":"Home & Garden",
            "subcategory":"Carpets & Floor Coverings",
            "type":"Retail Goods"
        }
    ],
    "sg:phone":"+61 2 6251 2444",
    "sg:postcode":"2617",
    "sg:province":"ACT",
    "sg:tags":[
        "wood"
    ],
    "wof:name":"Canberra Carpet Choice",
    "wof:placetype":"venue"
},
  "geometry": {"coordinates":[149.063552856,-35.2397499084],"type":"Point"}
}