{
  "type": "Feature",
  "properties": {
    "addr:full":"37 Lake St Laurieton NSW 2443",
    "addr:housenumber":"37",
    "addr:postcode":"2443",
    "addr:street":"Lake St",
    "iso:country":"AU",
    "sg:address":"37 Lake St",
    "sg:city":"Laurieton",
    "sg:classifiers":[
        {
            "category":"Health Services",
            "subcategory":"Health Practitioner",
            "type":"Services"
        }
    ],
    "sg:phone":"+61 2 6559 8076",
    "sg:postcode":"2443",
    "sg:province":"NSW",
    "sg:tags":[
        "physiotherapist"
    ],
    "wof:name":"Job Wendy",
    "wof:placetype":"venue"
},
  "geometry": {"coordinates":[152.79832500000001,-31.64497],"type":"Point"}
}