{
  "type": "Feature",
  "properties": {
    "addr:full":"581 Milton Rd Toowong QLD 4066",
    "addr:housenumber":"581",
    "addr:postcode":"4066",
    "addr:street":"Milton Rd",
    "iso:country":"AU",
    "sg:address":"581 Milton Rd",
    "sg:city":"Toowong",
    "sg:classifiers":[
        {
            "category":"Autos & Motor Vehicles",
            "subcategory":"Fuel & Gas Station",
            "type":"Retail Goods"
        }
    ],
    "sg:phone":"+61 7 3870 7838",
    "sg:postcode":"4066",
    "sg:province":"QLD",
    "wof:name":"Caltex Toowong",
    "wof:placetype":"venue"
},
  "geometry": {"coordinates":[152.98597717300001,-27.4784526825],"type":"Point"}
}