{
  "type": "Feature",
  "properties": {
    "iso:country":"AU",
    "sg:address":"39 Galgabba St",
    "sg:city":"Swansea",
    "sg:classifiers":[
        {
            "category":"Professional",
            "subcategory":"Accounting & Tax Preparation",
            "type":"Services"
        }
    ],
    "sg:phone":"+61 2 4971 5880",
    "sg:postcode":"2281",
    "sg:province":"NSW",
    "sg:tags":[
        "bookkeeping"
    ],
    "wof:name":"Specific Bookkeeping Services",
    "wof:placetype":"venue"
},
  "geometry": {"coordinates":[151.634887695,-33.0848770142],"type":"Point"}
}