{
  "type": "Feature",
  "properties": {
    "addr:full":"25 Finnegan St Rothwell QLD 4022",
    "addr:housenumber":"25",
    "addr:postcode":"4022",
    "addr:street":"Finnegan St",
    "iso:country":"AU",
    "sg:address":"25 Finnegan St",
    "sg:city":"Rothwell",
    "sg:classifiers":[
        {
            "category":"Professional",
            "subcategory":"Art Services",
            "type":"Services"
        }
    ],
    "sg:phone":"+61 7 3203 3480",
    "sg:postcode":"4022",
    "sg:province":"QLD",
    "sg:tags":[
        "decorator",
        "painter"
    ],
    "wof:name":"Vellnagel R J & B R",
    "wof:placetype":"venue"
},
  "geometry": {"coordinates":[153.045883,-27.219553],"type":"Point"}
}