{
  "type": "Feature",
  "properties": {
    "addr:full":"7- 9 Perry St Matraville NSW 2036",
    "addr:housenumber":"9",
    "addr:postcode":"2036",
    "addr:street":"Perry St",
    "iso:country":"AU",
    "sg:address":"7- 9 Perry St",
    "sg:city":"Matraville",
    "sg:classifiers":[
        {
            "category":"Retail",
            "subcategory":"Auto Repair",
            "type":"Services"
        }
    ],
    "sg:phone":"+61 2 9212 3566",
    "sg:postcode":"2036",
    "sg:province":"NSW",
    "sg:tags":[
        "beater",
        "painter",
        "panel"
    ],
    "wof:name":"Scientific Motor Body Works L P",
    "wof:placetype":"venue"
},
  "geometry": {"coordinates":[151.205474853,-33.9233093262],"type":"Point"}
}