{
  "type": "Feature",
  "properties": {
    "iso:country":"AU",
    "sg:address":"75 Madeley St",
    "sg:city":"Ocean Grove",
    "sg:classifiers":[
        {
            "category":"Food & Beverages",
            "subcategory":"Groceries & Convenience Stores",
            "type":"Retail Goods"
        }
    ],
    "sg:phone":"+61 3 5255 4563",
    "sg:postcode":"3226",
    "sg:province":"VIC",
    "wof:name":"Madeley St Mixed Business",
    "wof:placetype":"venue"
},
  "geometry": {"coordinates":[144.53024292000001,-38.2623023987],"type":"Point"}
}