{
  "type": "Feature",
  "properties": {
    "iso:country":"AU",
    "sg:address":"195 Bryants Rd",
    "sg:city":"Loganholme",
    "sg:classifiers":[
        {
            "category":"Building & Trades",
            "subcategory":"Construction",
            "type":"Services"
        }
    ],
    "sg:phone":"+61 7 3209 8970",
    "sg:postcode":"4129",
    "sg:province":"QLD",
    "sg:tags":[
        "earth",
        "excavating",
        "moving",
        "contractor"
    ],
    "wof:name":"Bryant G J & J A",
    "wof:placetype":"venue"
},
  "geometry": {"coordinates":[153.19284057600001,-27.6699771881],"type":"Point"}
}