{
  "type": "Feature",
  "properties": {
    "addr:full":"4/ 355 South Gippsland Hwy Dandenong VIC 3175",
    "addr:housenumber":"/ 355",
    "addr:postcode":"3175",
    "addr:street":"South Gippsland Hwy",
    "iso:country":"AU",
    "sg:address":"4/ 355 South Gippsland Hwy",
    "sg:city":"Dandenong",
    "sg:classifiers":[
        {
            "category":"Wholesale",
            "subcategory":"Medical Equipment & Supplies",
            "type":"Manufacturing & Wholesale Goods"
        }
    ],
    "sg:phone":"+61 1300 622 633",
    "sg:postcode":"3175",
    "sg:province":"VIC",
    "sg:tags":[
        "scooter",
        "mobility"
    ],
    "wof:name":"Scooters Australia",
    "wof:placetype":"venue"
},
  "geometry": {"coordinates":[145.24472045900001,-38.0287094116],"type":"Point"}
}