{
  "type": "Feature",
  "properties": {
    "iso:country":"AU",
    "sg:address":"146 Langtree Ave",
    "sg:city":"Mildura",
    "sg:classifiers":[
        {
            "category":"Professional",
            "subcategory":"Accounting & Tax Preparation",
            "type":"Services"
        }
    ],
    "sg:phone":"+61 3 5023 0357",
    "sg:postcode":"3500",
    "sg:province":"VIC",
    "sg:tags":[
        "accountant",
        "auditor"
    ],
    "wof:name":"Musgrove G R",
    "wof:placetype":"venue"
},
  "geometry": {"coordinates":[142.15724182100001,-34.1878890991],"type":"Point"}
}