{
  "type": "Feature",
  "properties": {
    "addr:full":"Collingwood Drv Redbank QLD 4301",
    "addr:postcode":"4301",
    "addr:street":"Collingwood Drv",
    "iso:country":"AU",
    "sg:address":"Collingwood Drv",
    "sg:city":"Redbank",
    "sg:classifiers":[
        {
            "category":"Shopping",
            "subcategory":"Clothing, Apparel, & Fashions",
            "type":"Retail Goods"
        }
    ],
    "sg:phone":"+61 7 3818 6332",
    "sg:postcode":"4301",
    "sg:province":"QLD",
    "sg:tags":[
        "lady",
        "wear"
    ],
    "wof:name":"Suzanne Grae",
    "wof:placetype":"venue"
},
  "geometry": {"coordinates":[152.86929321299999,-27.6029090881],"type":"Point"}
}