{
  "type": "Feature",
  "properties": {
    "addr:full":"132 Silverdale Rd Silverdale NSW 2752",
    "addr:housenumber":"132",
    "addr:postcode":"2752",
    "addr:street":"Silverdale Rd",
    "iso:country":"AU",
    "sg:address":"132 Silverdale Rd",
    "sg:city":"Silverdale",
    "sg:classifiers":[
        {
            "category":"Government",
            "subcategory":"Court House",
            "type":"Public Place"
        }
    ],
    "sg:phone":"+61 2 4774 2958",
    "sg:postcode":"2752",
    "sg:province":"NSW",
    "sg:tags":[
        "personal",
        "marriage",
        "family",
        "counselling"
    ],
    "wof:name":"Willomee Healing Sanctuary",
    "wof:placetype":"venue"
},
  "geometry": {"coordinates":[150.60452270499999,-33.9080963135],"type":"Point"}
}