{
  "type": "Feature",
  "properties": {
    "addr:full":"PO Box 97 Rockingham WA 6168",
    "addr:postcode":"6168",
    "iso:country":"AU",
    "sg:address":"PO Box 97",
    "sg:city":"Rockingham",
    "sg:classifiers":[
        {
            "category":"Utilities",
            "subcategory":"Refuse",
            "type":"Services"
        }
    ],
    "sg:phone":"+61 8 9527 4775",
    "sg:postcode":"6168",
    "sg:province":"WA",
    "sg:tags":[
        "remover",
        "rubbish"
    ],
    "wof:name":"Hills Garden Bags",
    "wof:placetype":"venue"
},
  "geometry": {"coordinates":[115.741028,-32.280399],"type":"Point"}
}