{
  "type": "Feature",
  "properties": {
    "addr:full":"4/ 83 Roscoe St Bondi Beach NSW 2026",
    "addr:housenumber":"/ 83",
    "addr:postcode":"2026",
    "addr:street":"Roscoe St",
    "iso:country":"AU",
    "sg:address":"4/ 83 Roscoe St",
    "sg:city":"Bondi Beach",
    "sg:classifiers":[
        {
            "category":"Professional",
            "subcategory":"Accounting & Tax Preparation",
            "type":"Services"
        }
    ],
    "sg:phone":"+61 2 9300 8011",
    "sg:postcode":"2026",
    "sg:province":"NSW",
    "sg:tags":[
        "bookkeeping"
    ],
    "wof:name":"Sergio Pineiro",
    "wof:placetype":"venue"
},
  "geometry": {"coordinates":[151.273513794,-33.8897819519],"type":"Point"}
}