{
  "type": "Feature",
  "properties": {
    "addr:full":"PO Box 568 Donnybrook WA 6239",
    "addr:postcode":"6239",
    "iso:country":"AU",
    "sg:address":"PO Box 568",
    "sg:city":"Donnybrook",
    "sg:classifiers":[
        {
            "category":"Professional",
            "subcategory":"Art Services",
            "type":"Services"
        }
    ],
    "sg:phone":"+61 8 9731 0356",
    "sg:postcode":"6239",
    "sg:province":"WA",
    "sg:tags":[
        "decorator",
        "painter"
    ],
    "wof:name":"Southern Pride Painting Services",
    "wof:placetype":"venue"
},
  "geometry": {"coordinates":[115.823013,-33.570419],"type":"Point"}
}