{
  "type": "Feature",
  "properties": {
    "addr:full":"1/ 23 Hollydale Pl Prospect NSW 2148",
    "addr:housenumber":"/ 23",
    "addr:postcode":"2148",
    "addr:street":"Hollydale Pl",
    "iso:country":"AU",
    "sg:address":"1/ 23 Hollydale Pl",
    "sg:city":"Prospect",
    "sg:classifiers":[
        {
            "category":"Shopping",
            "subcategory":"Gifts & Souvenirs",
            "type":"Retail Goods"
        }
    ],
    "sg:phone":"+61 2 9676 2881",
    "sg:postcode":"2148",
    "sg:province":"NSW",
    "sg:tags":[
        "shop",
        "supply"
    ],
    "wof:name":"Dreams By Design",
    "wof:placetype":"venue"
},
  "geometry": {"coordinates":[150.920013428,-33.7945022583],"type":"Point"}
}