{
  "type": "Feature",
  "properties": {
    "addr:full":"11 Evans St Burwood VIC 3125",
    "addr:housenumber":"11",
    "addr:postcode":"3125",
    "addr:street":"Evans St",
    "iso:country":"AU",
    "sg:address":"11 Evans St",
    "sg:city":"Burwood",
    "sg:classifiers":[
        {
            "category":"Personal",
            "subcategory":"Skin Care",
            "type":"Services"
        }
    ],
    "sg:phone":"+61 425 855 420",
    "sg:postcode":"3125",
    "sg:province":"VIC",
    "sg:tags":[
        "hair",
        "product"
    ],
    "wof:name":"Neon Nits Australia",
    "wof:placetype":"venue"
},
  "geometry": {"coordinates":[145.10153198200001,-37.8524208069],"type":"Point"}
}