{
  "type": "Feature",
  "properties": {
    "addr:full":"U2/ 154 Halifax Rd Adelaide SA 5000",
    "addr:housenumber":"154",
    "addr:postcode":"5000",
    "addr:street":"U2 /;Halifax Rd",
    "iso:country":"AU",
    "sg:address":"U2/ 154 Halifax Rd",
    "sg:city":"Adelaide",
    "sg:classifiers":[
        {
            "category":"Professional",
            "subcategory":"Business Services",
            "type":"Services"
        }
    ],
    "sg:phone":"+61 8 8232 8933",
    "sg:postcode":"5000",
    "sg:province":"SA",
    "sg:tags":[
        "drafting"
    ],
    "wof:name":"Measure-Tec Drafting Services",
    "wof:placetype":"venue"
},
  "geometry": {"coordinates":[138.607696533,-34.9323883057],"type":"Point"}
}