{
  "type": "Feature",
  "properties": {
    "addr:full":"595 South St Toowoomba QLD 4350",
    "addr:housenumber":"595",
    "addr:postcode":"4350",
    "addr:street":"South St",
    "iso:country":"AU",
    "sg:address":"595 South St",
    "sg:city":"Toowoomba",
    "sg:classifiers":[
        {
            "category":"Building & Trades",
            "subcategory":"Construction",
            "type":"Services"
        }
    ],
    "sg:phone":"+61 7 4634 4109",
    "sg:postcode":"4350",
    "sg:province":"QLD",
    "sg:tags":[
        "fencing",
        "contractor"
    ],
    "wof:name":"George Leicht Fencing Pty Ltd",
    "wof:placetype":"venue"
},
  "geometry": {"coordinates":[151.90559400000001,-27.57144],"type":"Point"}
}