{
  "type": "Feature",
  "properties": {
    "iso:country":"AU",
    "sg:address":"139 Murrindal Drv",
    "sg:city":"Rowville",
    "sg:classifiers":[
        {
            "category":"Personal",
            "subcategory":"Beauty Salon",
            "type":"Services"
        }
    ],
    "sg:phone":"+61 3 9752 8487",
    "sg:postcode":"3178",
    "sg:province":"VIC",
    "wof:name":"Rowville Waxing & Nails",
    "wof:placetype":"venue"
},
  "geometry": {"coordinates":[145.26751709000001,-37.9107246399],"type":"Point"}
}