{
  "type": "Feature",
  "properties": {
    "addr:full":"1- 3 Church St Hepburn Springs VIC 3461",
    "addr:housenumber":"3",
    "addr:postcode":"3461",
    "addr:street":"Church St Hepburn Springs",
    "iso:country":"AU",
    "sg:address":"1- 3 Church St",
    "sg:city":"Hepburn Springs",
    "sg:classifiers":[
        {
            "category":"Travel",
            "subcategory":"Hotels & Motels",
            "type":"Entertainment"
        }
    ],
    "sg:phone":"+61 3 5348 8500",
    "sg:postcode":"3461",
    "sg:province":"VIC",
    "sg:tags":[
        "accommodation"
    ],
    "wof:name":"The Grande",
    "wof:placetype":"venue"
},
  "geometry": {"coordinates":[144.23794555699999,-37.2982330322],"type":"Point"}
}