{
  "type": "Feature",
  "properties": {
    "addr:full":"3/ 41 Holland St Goonellabah NSW 2480",
    "addr:housenumber":"/ 41",
    "addr:postcode":"2480",
    "addr:street":"Holland St",
    "iso:country":"AU",
    "sg:address":"3/ 41 Holland St",
    "sg:city":"Goonellabah",
    "sg:classifiers":[
        {
            "category":"Retail",
            "subcategory":"Auto Repair",
            "type":"Services"
        }
    ],
    "sg:phone":"+61 2 6624 7800",
    "sg:postcode":"2480",
    "sg:province":"NSW",
    "sg:tags":[
        "repairer",
        "motor",
        "engineer"
    ],
    "wof:name":"Mick Scully Motors",
    "wof:placetype":"venue"
},
  "geometry": {"coordinates":[153.34608459500001,-28.8222770691],"type":"Point"}
}