{
  "type": "Feature",
  "properties": {
    "addr:full":"Berth 1 , Pier F, Sanctuary Cove Marina Sanctuary Cov QLD 4212",
    "addr:housenumber":"1",
    "addr:postcode":"4212",
    "addr:street":"Pier F Sanctuary Cove;Sanctuary Cov",
    "iso:country":"AU",
    "sg:address":"Berth 1",
    "sg:city":", Pier F, Sanctuary Cove Marina Sanctuary Cov",
    "sg:classifiers":[
        {
            "category":"Real Estate",
            "subcategory":"Real Estate Services",
            "type":"Services"
        }
    ],
    "sg:phone":"+61 7 5577 8808",
    "sg:postcode":"4212",
    "sg:province":"QLD",
    "sg:tags":[
        "house",
        "hire",
        "boat"
    ],
    "wof:name":"Fantaseas Houseboat Holidays",
    "wof:placetype":"venue"
},
  "geometry": {"coordinates":[153.37884521500001,-27.9003162384],"type":"Point"}
}