{
  "type": "Feature",
  "properties": {
    "iso:country":"AU",
    "sg:address":"52 Illawarra Ave",
    "sg:city":"Hove",
    "sg:classifiers":[
        {
            "category":"Professional",
            "subcategory":"Computer Services",
            "type":"Services"
        }
    ],
    "sg:phone":"+61 419 807 323",
    "sg:postcode":"5048",
    "sg:province":"SA",
    "sg:tags":[
        "consultant",
        "system"
    ],
    "wof:name":"Ark Desktop Computing",
    "wof:placetype":"venue"
},
  "geometry": {"coordinates":[138.527283,-35.010487],"type":"Point"}
}