{
  "type": "Feature",
  "properties": {
    "addr:full":"Unit 5/ 2 Albert St Goodna QLD 4300",
    "addr:housenumber":"2",
    "addr:postcode":"4300",
    "addr:street":"Albert St",
    "iso:country":"AU",
    "sg:address":"Unit 5/ 2 Albert St",
    "sg:city":"Goodna",
    "sg:classifiers":[
        {
            "category":"Utilities",
            "subcategory":"Mobile Phone",
            "type":"Services"
        }
    ],
    "sg:phone":"+61 7 3818 7300",
    "sg:postcode":"4300",
    "sg:province":"QLD",
    "sg:tags":[
        "assembly",
        "part",
        "electronic"
    ],
    "wof:name":"QPA Electronics Pty Ltd",
    "wof:placetype":"venue"
},
  "geometry": {"coordinates":[152.894607544,-27.6062068939],"type":"Point"}
}