{
  "type": "Feature",
  "properties": {
    "addr:full":"PO Box 2153 Mansfield Business Centre QLD 4122",
    "addr:postcode":"4122",
    "iso:country":"AU",
    "sg:address":"PO Box 2153",
    "sg:city":"Mansfield Business Centre",
    "sg:classifiers":[
        {
            "category":"Health Services",
            "subcategory":"Doctor",
            "type":"Services"
        }
    ],
    "sg:phone":"+61 7 3213 7304",
    "sg:postcode":"4122",
    "sg:province":"QLD",
    "sg:tags":[
        "nurse",
        "nursing"
    ],
    "wof:name":"Blue Nursing Service-Brisbane Central Region",
    "wof:placetype":"venue"
},
  "geometry": {"coordinates":[153.110473633,-27.5458850861],"type":"Point"}
}