{
  "type": "Feature",
  "properties": {
    "addr:full":"1 Church St Morphett Vale SA 5162",
    "addr:housenumber":"1",
    "addr:postcode":"5162",
    "addr:street":"Church St",
    "iso:country":"AU",
    "sg:address":"1 Church St",
    "sg:city":"Morphett Vale",
    "sg:classifiers":[
        {
            "category":"Wholesale",
            "subcategory":"Non-durable Goods",
            "type":"Manufacturing & Wholesale Goods"
        }
    ],
    "sg:phone":"+61 8 8326 0833",
    "sg:postcode":"5162",
    "sg:province":"SA",
    "sg:tags":[
        "wholesaler",
        "craft",
        "mfrs"
    ],
    "wof:name":"OLAF BEADWORK Pty Ltd",
    "wof:placetype":"venue"
},
  "geometry": {"coordinates":[138.52362060600001,-35.1210632324],"type":"Point"}
}