{
  "type": "Feature",
  "properties": {
    "iso:country":"AU",
    "sg:address":"106 Prospect Rd",
    "sg:city":"Prospect",
    "sg:classifiers":[
        {
            "category":"Shopping",
            "subcategory":"Gifts & Souvenirs",
            "type":"Retail Goods"
        }
    ],
    "sg:phone":"+61 8 8269 1437",
    "sg:postcode":"5082",
    "sg:province":"SA",
    "sg:tags":[
        "print",
        "poster",
        "pictures"
    ],
    "wof:name":"Thousand Words Picture Framing",
    "wof:placetype":"venue"
},
  "geometry": {"coordinates":[138.593917847,-34.8877983093],"type":"Point"}
}