{
  "type": "Feature",
  "properties": {
    "addr:full":"1/ 504 Spencer St Melbourne VIC 3000",
    "addr:housenumber":"/ 504",
    "addr:postcode":"3000",
    "addr:street":"Spencer St",
    "iso:country":"AU",
    "sg:address":"1/ 504 Spencer St",
    "sg:city":"Melbourne",
    "sg:classifiers":[
        {
            "category":"Professional",
            "subcategory":"Employment Agencies",
            "type":"Services"
        }
    ],
    "sg:phone":"+61 3 9326 4455",
    "sg:postcode":"3000",
    "sg:province":"VIC",
    "sg:tags":[
        "entertainer",
        "agent"
    ],
    "wof:name":"International Performance Bureau",
    "wof:placetype":"venue"
},
  "geometry": {"coordinates":[144.948944092,-37.8084983826],"type":"Point"}
}