{
  "type": "Feature",
  "properties": {
    "iso:country":"AU",
    "sg:address":"4 Moseley St",
    "sg:city":"Glenelg",
    "sg:classifiers":[
        {
            "category":"Cafe",
            "type":"Food & Drink"
        }
    ],
    "sg:phone":"+61 8 8376 0049",
    "sg:postcode":"5045",
    "sg:province":"SA",
    "wof:name":"Nonios",
    "wof:placetype":"venue"
},
  "geometry": {"coordinates":[138.51332099999999,-34.980728],"type":"Point"}
}