{
  "type": "Feature",
  "properties": {
    "addr:full":"32 Walker St North Sydney NSW 2060",
    "addr:housenumber":"32",
    "addr:postcode":"2060",
    "addr:street":"Walker St",
    "iso:country":"AU",
    "sg:address":"32 Walker St",
    "sg:city":"North Sydney",
    "sg:classifiers":[
        {
            "category":"Travel",
            "subcategory":"Hotels & Motels",
            "type":"Entertainment"
        }
    ],
    "sg:phone":"+61 2 9923 2055",
    "sg:postcode":"2060",
    "sg:province":"NSW",
    "sg:tags":[
        "pub"
    ],
    "wof:name":"Station Tavern North Sydney",
    "wof:placetype":"venue"
},
  "geometry": {"coordinates":[151.20840454099999,-33.8401641846],"type":"Point"}
}