{
  "type": "Feature",
  "properties": {
    "iso:country":"AU",
    "sg:address":"Hobbs Rd",
    "sg:city":"Kendenup",
    "sg:classifiers":[
        {
            "category":"Farming",
            "subcategory":"Farm",
            "type":"Manufacturing & Wholesale Goods"
        }
    ],
    "sg:phone":"+61 8 9851 4178",
    "sg:postcode":"6323",
    "sg:province":"WA",
    "sg:tags":[
        "farmer"
    ],
    "wof:name":"Frost K W & C",
    "wof:placetype":"venue"
},
  "geometry": {"coordinates":[117.601737976,-34.5288124084],"type":"Point"}
}