{
  "type": "Feature",
  "properties": {
    "iso:country":"AU",
    "sg:address":"29 Jubilee Hwy",
    "sg:city":"W Mt Gambier",
    "sg:classifiers":[
        {
            "category":"Professional",
            "subcategory":"Printing & Photocopies",
            "type":"Services"
        }
    ],
    "sg:phone":"+61 8 8725 7942",
    "sg:postcode":"5290",
    "sg:province":"SA",
    "sg:tags":[
        "embroidery"
    ],
    "wof:name":"Stitched by Susan",
    "wof:placetype":"venue"
},
  "geometry": {"coordinates":[140.76068100000001,-37.816467],"type":"Point"}
}