{
  "type": "Feature",
  "properties": {
    "iso:country":"AU",
    "sg:address":"PO Box 968",
    "sg:city":"Byron Bay",
    "sg:classifiers":[
        {
            "category":"Professional",
            "subcategory":"Art Services",
            "type":"Services"
        }
    ],
    "sg:phone":"+61 2 6686 2841",
    "sg:postcode":"2481",
    "sg:province":"NSW",
    "sg:tags":[
        "graphic",
        "designer"
    ],
    "wof:name":"Karyn Gillespie Designs",
    "wof:placetype":"venue"
},
  "geometry": {"coordinates":[153.612823486,-28.6468906403],"type":"Point"}
}