{
  "type": "Feature",
  "properties": {
    "addr:full":"313 Kensington Rd Kensington Park SA 5068",
    "addr:housenumber":"313",
    "addr:postcode":"5068",
    "addr:street":"Kensington Rd",
    "iso:country":"AU",
    "sg:address":"313 Kensington Rd",
    "sg:city":"Kensington Park",
    "sg:classifiers":[
        {
            "category":"Professional",
            "subcategory":"Art Services",
            "type":"Services"
        }
    ],
    "sg:phone":"+61 8 8331 0750",
    "sg:postcode":"5068",
    "sg:province":"SA",
    "sg:tags":[
        "artist"
    ],
    "wof:name":"Michelle White Portraits",
    "wof:placetype":"venue"
},
  "geometry": {"coordinates":[138.65623474099999,-34.9260482788],"type":"Point"}
}