{
  "type": "Feature",
  "properties": {
    "addr:full":"236 Macauley St Albury NSW 2640",
    "addr:housenumber":"236",
    "addr:postcode":"2640",
    "addr:street":"Macauley St",
    "iso:country":"AU",
    "sg:address":"236 Macauley St",
    "sg:city":"Albury",
    "sg:classifiers":[
        {
            "category":"Social Services",
            "subcategory":"Adult Care",
            "type":"Services"
        }
    ],
    "sg:phone":"+61 2 6021 4175",
    "sg:postcode":"2640",
    "sg:province":"NSW",
    "sg:tags":[
        "towing"
    ],
    "wof:name":"Albury Auto Body Repairs",
    "wof:placetype":"venue"
},
  "geometry": {"coordinates":[146.91970825199999,-36.0946006775],"type":"Point"}
}