{
  "type": "Feature",
  "properties": {
    "addr:full":"14 Sherman Drv Upper Coomera QLD 4209",
    "addr:housenumber":"14",
    "addr:postcode":"4209",
    "addr:street":"Sherman Drv",
    "iso:country":"AU",
    "sg:address":"14 Sherman Drv",
    "sg:city":"Upper Coomera",
    "sg:classifiers":[
        {
            "category":"Professional",
            "subcategory":"Employment Agencies",
            "type":"Services"
        }
    ],
    "sg:phone":"+61 7 5573 6353",
    "sg:postcode":"4209",
    "sg:province":"QLD",
    "wof:name":"XV Degrees Pty Ltd",
    "wof:placetype":"venue"
},
  "geometry": {"coordinates":[153.289520264,-27.9033031464],"type":"Point"}
}