{
  "type": "Feature",
  "properties": {
    "iso:country":"AU",
    "sg:address":"Bowden St",
    "sg:city":"Jabuk",
    "sg:classifiers":[
        {
            "category":"Fast Food",
            "type":"Food & Drink"
        }
    ],
    "sg:phone":"+61 8 8577 1600",
    "sg:postcode":"5301",
    "sg:province":"SA",
    "sg:tags":[
        "away",
        "take"
    ],
    "wof:name":"Jabuk Store",
    "wof:placetype":"venue"
},
  "geometry": {"coordinates":[140.07574462900001,-35.3806114197],"type":"Point"}
}