{
  "type": "Feature",
  "properties": {
    "addr:full":"14 Katarama Rd Fairview Park SA 5126",
    "addr:housenumber":"14",
    "addr:postcode":"5126",
    "addr:street":"Katarama Rd",
    "iso:country":"AU",
    "sg:address":"14 Katarama Rd",
    "sg:city":"Fairview Park",
    "sg:classifiers":[
        {
            "category":"Manufacturing",
            "subcategory":"Tools & Machinery",
            "type":"Manufacturing & Wholesale Goods"
        }
    ],
    "sg:phone":"+61 410 406 919",
    "sg:postcode":"5126",
    "sg:province":"SA",
    "sg:tags":[
        "earth",
        "excavating",
        "moving",
        "equipment"
    ],
    "wof:name":"Dingo Power Excavation",
    "wof:placetype":"venue"
},
  "geometry": {"coordinates":[138.73167419399999,-34.799041748],"type":"Point"}
}