{
  "type": "Feature",
  "properties": {
    "addr:full":"35 Labouchere Rd South Perth WA 6151",
    "addr:housenumber":"35",
    "addr:postcode":"6151",
    "addr:street":"Labouchere Rd",
    "iso:country":"AU",
    "sg:address":"35 Labouchere Rd",
    "sg:city":"South Perth",
    "sg:classifiers":[
        {
            "category":"Real Estate",
            "subcategory":"Real Estate Agent",
            "type":"Services"
        }
    ],
    "sg:phone":"+61 8 9368 6702",
    "sg:postcode":"6151",
    "sg:province":"WA",
    "wof:name":"L J Hooker",
    "wof:placetype":"venue"
},
  "geometry": {"coordinates":[115.851448,-31.975161],"type":"Point"}
}