{
  "type": "Feature",
  "properties": {
    "addr:full":"62 Bolam St Garbutt QLD 4814",
    "addr:housenumber":"62",
    "addr:postcode":"4814",
    "addr:street":"Bolam St",
    "iso:country":"AU",
    "sg:address":"62 Bolam St",
    "sg:city":"Garbutt",
    "sg:classifiers":[
        {
            "category":"Farming",
            "subcategory":"Dairy Farm",
            "type":"Manufacturing & Wholesale Goods"
        }
    ],
    "sg:phone":"+61 7 4727 5930",
    "sg:postcode":"4814",
    "sg:province":"QLD",
    "sg:tags":[
        "wholesaler",
        "product",
        "mfrs"
    ],
    "wof:name":"Dairy Farmers",
    "wof:placetype":"venue"
},
  "geometry": {"coordinates":[146.77479600000001,-19.266199],"type":"Point"}
}