{
  "type": "Feature",
  "properties": {
    "addr:full":"209- 211 Commercial Rd Morwell VIC 3840",
    "addr:housenumber":"211",
    "addr:postcode":"3840",
    "addr:street":"Commercial Rd",
    "iso:country":"AU",
    "sg:address":"209- 211 Commercial Rd",
    "sg:city":"Morwell",
    "sg:classifiers":[
        {
            "category":"Home & Garden",
            "subcategory":"Furniture",
            "type":"Retail Goods"
        }
    ],
    "sg:phone":"+61 3 5134 5277",
    "sg:postcode":"3840",
    "sg:province":"VIC",
    "sg:tags":[
        "business"
    ],
    "wof:name":"MTM Office Equipment Pty Ltd",
    "wof:placetype":"venue"
},
  "geometry": {"coordinates":[146.397415161,-38.2371673584],"type":"Point"}
}