{
  "type": "Feature",
  "properties": {
    "addr:full":"19 Powerdrill Rd Hoxton Park NSW 2171",
    "addr:housenumber":"19",
    "addr:postcode":"2171",
    "addr:street":"Powerdrill Rd",
    "iso:country":"AU",
    "sg:address":"19 Powerdrill Rd",
    "sg:city":"Hoxton Park",
    "sg:classifiers":[
        {
            "category":"Professional",
            "type":"Services"
        }
    ],
    "sg:phone":"+61 2 9607 5811",
    "sg:postcode":"2171",
    "sg:province":"NSW",
    "sg:tags":[
        "transport"
    ],
    "wof:name":"Universal Logistics Pty Ltd",
    "wof:placetype":"venue"
},
  "geometry": {"coordinates":[150.84803772000001,-33.9280090332],"type":"Point"}
}