{
  "type": "Feature",
  "properties": {
    "addr:full":"152 Haly St Kingaroy QLD 4610",
    "addr:housenumber":"152",
    "addr:postcode":"4610",
    "addr:street":"Haly St",
    "iso:country":"AU",
    "sg:address":"152 Haly St",
    "sg:city":"Kingaroy",
    "sg:classifiers":[
        {
            "category":"Personal",
            "subcategory":"Beauty Salon",
            "type":"Services"
        }
    ],
    "sg:phone":"+61 7 4162 3033",
    "sg:postcode":"4610",
    "sg:province":"QLD",
    "sg:tags":[
        "hairdresser"
    ],
    "wof:name":"Kingaroy Studio J",
    "wof:placetype":"venue"
},
  "geometry": {"coordinates":[151.838500977,-26.5390739441],"type":"Point"}
}