{
  "type": "Feature",
  "properties": {
    "iso:country":"AU",
    "sg:address":"Elizabeth Mall 59-61 Elizabeth St",
    "sg:city":"Hobart",
    "sg:classifiers":[
        {
            "category":"Shopping",
            "subcategory":"Clothing, Apparel, & Fashions",
            "type":"Retail Goods"
        }
    ],
    "sg:phone":"+61 3 6231 2425",
    "sg:postcode":"7000",
    "sg:province":"TAS",
    "sg:tags":[
        "recycled",
        "clothing"
    ],
    "wof:name":"Salvation Army",
    "wof:placetype":"venue"
},
  "geometry": {"coordinates":[147.32780456500001,-42.8814544678],"type":"Point"}
}