{
  "type": "Feature",
  "properties": {
    "addr:full":"40 Miguel Rd Bibra Lake WA 6163",
    "addr:housenumber":"40",
    "addr:postcode":"6163",
    "addr:street":"Miguel Rd",
    "iso:country":"AU",
    "sg:address":"40 Miguel Rd",
    "sg:city":"Bibra Lake",
    "sg:classifiers":[
        {
            "category":"Manufacturing",
            "subcategory":"Building Materials",
            "type":"Manufacturing & Wholesale Goods"
        }
    ],
    "sg:phone":"+61 8 9236 5350",
    "sg:postcode":"6163",
    "sg:province":"WA",
    "sg:tags":[
        "equipment",
        "handling"
    ],
    "wof:name":"Bulkwest Engineering Pty Ltd",
    "wof:placetype":"venue"
},
  "geometry": {"coordinates":[115.810883,-32.115353],"type":"Point"}
}