{
  "type": "Feature",
  "properties": {
    "addr:full":"4 Greenfinch Crt Jacobs Well QLD 4208",
    "addr:housenumber":"4",
    "addr:postcode":"4208",
    "addr:street":"Greenfinch Crt",
    "iso:country":"AU",
    "sg:address":"4 Greenfinch Crt",
    "sg:city":"Jacobs Well",
    "sg:classifiers":[
        {
            "category":"Building & Trades",
            "subcategory":"Construction",
            "type":"Services"
        }
    ],
    "sg:phone":"+61 7 5546 2191",
    "sg:postcode":"4208",
    "sg:province":"QLD",
    "sg:tags":[
        "road",
        "contractor"
    ],
    "wof:name":"McFaul Constructions Pty Ltd",
    "wof:placetype":"venue"
},
  "geometry": {"coordinates":[153.355758667,-27.7738838196],"type":"Point"}
}