{
  "type": "Feature",
  "properties": {
    "addr:full":"PO Box 387 Ermington NSW 2115",
    "addr:postcode":"2115",
    "iso:country":"AU",
    "sg:address":"PO Box 387",
    "sg:city":"Ermington",
    "sg:classifiers":[
        {
            "category":"Building & Trades",
            "subcategory":"Plumbing",
            "type":"Services"
        }
    ],
    "sg:phone":"+61 418 862 848",
    "sg:postcode":"2115",
    "sg:province":"NSW",
    "sg:tags":[
        "plumber",
        "gasfitters"
    ],
    "wof:name":"S.J. Wilson Plumbing Pty Ltd",
    "wof:placetype":"venue"
},
  "geometry": {"coordinates":[151.057571411,-33.8100204468],"type":"Point"}
}