{
  "type": "Feature",
  "properties": {
    "addr:full":"6a Graves St Kadina SA 5554",
    "addr:housenumber":"6a",
    "addr:postcode":"5554",
    "addr:street":"Graves St",
    "iso:country":"AU",
    "sg:address":"6a Graves St",
    "sg:city":"Kadina",
    "sg:classifiers":[
        {
            "category":"Real Estate",
            "subcategory":"Real Estate Agent",
            "type":"Services"
        }
    ],
    "sg:phone":"+61 8 8821 3666",
    "sg:postcode":"5554",
    "sg:province":"SA",
    "wof:name":"Warmington Bros First National",
    "wof:placetype":"venue"
},
  "geometry": {"coordinates":[137.71232605,-33.9641189575],"type":"Point"}
}