{
  "type": "Feature",
  "properties": {
    "iso:country":"AU",
    "sg:address":"61 Mine Rd",
    "sg:city":"Korumburra",
    "sg:classifiers":[
        {
            "category":"Building & Trades",
            "subcategory":"Construction",
            "type":"Services"
        }
    ],
    "sg:phone":"+61 3 5655 2216",
    "sg:postcode":"3950",
    "sg:province":"VIC",
    "sg:tags":[
        "plasterboard",
        "plasterer",
        "fixer"
    ],
    "wof:name":"Hopkins Lee",
    "wof:placetype":"venue"
},
  "geometry": {"coordinates":[145.83026123100001,-38.437625885],"type":"Point"}
}