{
  "type": "Feature",
  "properties": {
    "iso:country":"AU",
    "sg:address":"161 Forest Rd",
    "sg:city":"Arncliffe",
    "sg:classifiers":[
        {
            "category":"Home & Garden",
            "subcategory":"Building Materials",
            "type":"Retail Goods"
        }
    ],
    "sg:phone":"+61 2 9567 8581",
    "sg:postcode":"2205",
    "sg:province":"NSW",
    "sg:tags":[
        "restoration",
        "supply"
    ],
    "wof:name":"Goldberg Heritage",
    "wof:placetype":"venue"
},
  "geometry": {"coordinates":[151.13725299999999,-33.94051],"type":"Point"}
}