{
  "type": "Feature",
  "properties": {
    "addr:full":"113 Quarry Rd Ryde NSW 2112",
    "addr:housenumber":"113",
    "addr:postcode":"2112",
    "addr:street":"Quarry Rd",
    "iso:country":"AU",
    "sg:address":"113 Quarry Rd",
    "sg:city":"Ryde",
    "sg:classifiers":[
        {
            "category":"Real Estate",
            "subcategory":"Surveying",
            "type":"Services"
        }
    ],
    "sg:phone":"+61 419 952 002",
    "sg:postcode":"2112",
    "sg:province":"NSW",
    "sg:tags":[
        "surveyor",
        "land"
    ],
    "wof:name":"DJ Barrington & Associates Pty Ltd",
    "wof:placetype":"venue"
},
  "geometry": {"coordinates":[151.11555480999999,-33.8052597046],"type":"Point"}
}