{
  "type": "Feature",
  "properties": {
    "addr:full":"161 Brunswick St Fortitude Valley QLD 4006",
    "addr:housenumber":"161",
    "addr:postcode":"4006",
    "addr:street":"Brunswick St",
    "iso:country":"AU",
    "sg:address":"161 Brunswick St",
    "sg:city":"Fortitude Valley",
    "sg:classifiers":[
        {
            "category":"Real Estate",
            "subcategory":"Architect",
            "type":"Services"
        }
    ],
    "sg:phone":"+61 7 3852 3103",
    "sg:postcode":"4006",
    "sg:province":"QLD",
    "wof:name":"EKO Architects",
    "wof:placetype":"venue"
},
  "geometry": {"coordinates":[153.031417847,-27.4558601379],"type":"Point"}
}