{
  "type": "Feature",
  "properties": {
    "iso:country":"AU",
    "sg:address":"115 Auburn Rd",
    "sg:city":"Auburn",
    "sg:classifiers":[
        {
            "category":"Health Services",
            "subcategory":"Optometrist",
            "type":"Services"
        }
    ],
    "sg:phone":"+61 2 9649 7460",
    "sg:postcode":"2144",
    "sg:province":"NSW",
    "wof:name":"Halass Steven",
    "wof:placetype":"venue"
},
  "geometry": {"coordinates":[151.03211975100001,-33.8539619446],"type":"Point"}
}