{
  "type": "Feature",
  "properties": {
    "addr:full":"130 Elizabeth St Hobart TAS 7000",
    "addr:housenumber":"130",
    "addr:postcode":"7000",
    "addr:street":"Elizabeth St",
    "iso:country":"AU",
    "sg:address":"130 Elizabeth St",
    "sg:city":"Hobart",
    "sg:classifiers":[
        {
            "category":"Personal",
            "subcategory":"Beauty Salon",
            "type":"Services"
        }
    ],
    "sg:phone":"+61 3 6236 9110",
    "sg:postcode":"7000",
    "sg:province":"TAS",
    "sg:tags":[
        "hairdresser"
    ],
    "wof:name":"Storm Hairdressers",
    "wof:placetype":"venue"
},
  "geometry": {"coordinates":[147.324127197,-42.8799743652],"type":"Point"}
}