{
  "type": "Feature",
  "properties": {
    "addr:full":"138 Fullarton Rd Rose Park SA 5067",
    "addr:housenumber":"138",
    "addr:postcode":"5067",
    "addr:street":"Fullarton Rd Rose",
    "iso:country":"AU",
    "sg:address":"138 Fullarton Rd",
    "sg:city":"Rose Park",
    "sg:classifiers":[
        {
            "category":"Health Services",
            "subcategory":"Doctor",
            "type":"Services"
        }
    ],
    "sg:phone":"+61 8 8431 6244",
    "sg:postcode":"5067",
    "sg:province":"SA",
    "sg:tags":[
        "medical",
        "practitioner"
    ],
    "wof:name":"Kristall Henry",
    "wof:placetype":"venue"
},
  "geometry": {"coordinates":[138.62396240199999,-34.9288406372],"type":"Point"}
}