{
  "type": "Feature",
  "properties": {
    "addr:full":"51 Penshurst Rd Macarthur VIC 3286",
    "addr:housenumber":"51",
    "addr:postcode":"3286",
    "addr:street":"Penshurst Rd",
    "iso:country":"AU",
    "sg:address":"51 Penshurst Rd",
    "sg:city":"Macarthur",
    "sg:classifiers":[
        {
            "category":"Building & Trades",
            "subcategory":"Landscaping Services",
            "type":"Services"
        }
    ],
    "sg:phone":"+61 3 5576 1074",
    "sg:postcode":"3286",
    "sg:province":"VIC",
    "sg:tags":[
        "firebreak",
        "clearing",
        "land",
        "contractor"
    ],
    "wof:name":"Cowland R B & J C",
    "wof:placetype":"venue"
},
  "geometry": {"coordinates":[142.00137329099999,-38.0338592529],"type":"Point"}
}