{
  "type": "Feature",
  "properties": {
    "iso:country":"AU",
    "sg:address":"Unit 12/ 33 Livingstone Rd",
    "sg:city":"Petersham",
    "sg:classifiers":[
        {
            "category":"Wholesale",
            "subcategory":"Home Furnishings",
            "type":"Manufacturing & Wholesale Goods"
        }
    ],
    "sg:phone":"+61 2 9569 4024",
    "sg:postcode":"2049",
    "sg:province":"NSW",
    "sg:tags":[
        "wholesaler",
        "curtain",
        "mfrs"
    ],
    "wof:name":"Jaymax Curtains & Soft Furnishings",
    "wof:placetype":"venue"
},
  "geometry": {"coordinates":[151.153442,-33.898426],"type":"Point"}
}