{
  "type": "Feature",
  "properties": {
    "addr:full":"37- 39 Crissane Rd Heidelberg West VIC 3081",
    "addr:housenumber":"39",
    "addr:postcode":"3081",
    "addr:street":"Crissane Rd",
    "iso:country":"AU",
    "sg:address":"37- 39 Crissane Rd",
    "sg:city":"Heidelberg West",
    "sg:classifiers":[
        {
            "category":"Building & Trades",
            "subcategory":"Cleaning & Sanitation",
            "type":"Services"
        }
    ],
    "sg:phone":"+61 3 9455 1366",
    "sg:postcode":"3081",
    "sg:province":"VIC",
    "sg:tags":[
        "abrasive",
        "blasting"
    ],
    "wof:name":"Blast Off",
    "wof:placetype":"venue"
},
  "geometry": {"coordinates":[145.046478272,-37.7283325195],"type":"Point"}
}