{
  "type": "Feature",
  "properties": {
    "addr:full":"32- 34 Wellington St Collingwood VIC 3066",
    "addr:housenumber":"34",
    "addr:postcode":"3066",
    "addr:street":"Wellington St",
    "iso:country":"AU",
    "sg:address":"32- 34 Wellington St",
    "sg:city":"Collingwood",
    "sg:classifiers":[
        {
            "category":"Arts & Performance",
            "subcategory":"Art Gallery",
            "type":"Entertainment"
        }
    ],
    "sg:phone":"+61 3 9710 1657",
    "sg:postcode":"3066",
    "sg:province":"VIC",
    "wof:name":"Ochre Gallery - Aboriginal Art",
    "wof:placetype":"venue"
},
  "geometry": {"coordinates":[144.98599243199999,-37.8079872131],"type":"Point"}
}