{
  "type": "Feature",
  "properties": {
    "addr:full":"Cnr Seelaf Sq & Vipont St Footscray VIC 3011",
    "addr:postcode":"3011",
    "addr:street":"Cnr Seelaf Sq & Vipont St",
    "iso:country":"AU",
    "sg:address":"Cnr Seelaf Sq & Vipont St",
    "sg:city":"Footscray",
    "sg:classifiers":[
        {
            "category":"Social Services",
            "subcategory":"Child Care",
            "type":"Services"
        }
    ],
    "sg:phone":"+61 3 9689 9844",
    "sg:postcode":"3011",
    "sg:province":"VIC",
    "wof:name":"Angliss Childrens Centre",
    "wof:placetype":"venue"
},
  "geometry": {"coordinates":[144.906814575,-37.7965202332],"type":"Point"}
}