{
  "type": "Feature",
  "properties": {
    "iso:country":"AU",
    "sg:address":"1051 Burwood Hwy",
    "sg:city":"Ferntree Gully",
    "sg:classifiers":[
        {
            "category":"Fast Food",
            "type":"Food & Drink"
        }
    ],
    "sg:phone":"+61 3 9294 8400",
    "sg:postcode":"3156",
    "sg:province":"VIC",
    "sg:tags":[
        "away",
        "take"
    ],
    "wof:name":"Dominos Pizza",
    "wof:placetype":"venue"
},
  "geometry": {"coordinates":[145.29344177199999,-37.8885345459],"type":"Point"}
}