{
  "type": "Feature",
  "properties": {
    "addr:full":"95 Merrigang St Bowral NSW 2576",
    "addr:housenumber":"95",
    "addr:postcode":"2576",
    "addr:street":"Merrigang St",
    "iso:country":"AU",
    "sg:address":"95 Merrigang St",
    "sg:city":"Bowral",
    "sg:classifiers":[
        {
            "category":"Building & Trades",
            "subcategory":"Plumbing",
            "type":"Services"
        }
    ],
    "sg:phone":"+61 2 4862 3574",
    "sg:postcode":"2576",
    "sg:province":"NSW",
    "sg:tags":[
        "plumber",
        "gasfitters"
    ],
    "wof:name":"Pisano Plumbing",
    "wof:placetype":"venue"
},
  "geometry": {"coordinates":[150.425979614,-34.478717804],"type":"Point"}
}