{
  "type": "Feature",
  "properties": {
    "iso:country":"AU",
    "sg:address":"2/ 35 Benison Rd",
    "sg:city":"Winnellie",
    "sg:classifiers":[
        {
            "category":"Manufacturing",
            "subcategory":"Glass & Minerals",
            "type":"Manufacturing & Wholesale Goods"
        }
    ],
    "sg:phone":"+61 439 895 171",
    "sg:postcode":"0820",
    "sg:province":"NT",
    "sg:tags":[
        "merchant",
        "granite",
        "marble"
    ],
    "wof:name":"Northern Stone Solutions",
    "wof:placetype":"venue"
},
  "geometry": {"coordinates":[130.86520385700001,-12.4303884506],"type":"Point"}
}