{
  "type": "Feature",
  "properties": {
    "addr:full":"35a Walker St Bundaberg QLD 4670",
    "addr:housenumber":"35a",
    "addr:postcode":"4670",
    "addr:street":"Walker St",
    "iso:country":"AU",
    "sg:address":"35a Walker St",
    "sg:city":"Bundaberg",
    "sg:classifiers":[
        {
            "category":"Retail",
            "subcategory":"Veterinary Services",
            "type":"Services"
        }
    ],
    "sg:phone":"+61 7 4152 3255",
    "sg:postcode":"4670",
    "sg:province":"QLD",
    "sg:tags":[
        "surgeon"
    ],
    "wof:name":"Bronson Small Animal Veterinary Clinic",
    "wof:placetype":"venue"
},
  "geometry": {"coordinates":[152.35707092300001,-24.8777599335],"type":"Point"}
}