{
  "type": "Feature",
  "properties": {
    "addr:full":"5 Birch Rd Lutana TAS 7009",
    "addr:housenumber":"5",
    "addr:postcode":"7009",
    "addr:street":"Birch Rd",
    "iso:country":"AU",
    "sg:address":"5 Birch Rd",
    "sg:city":"Lutana",
    "sg:classifiers":[
        {
            "category":"Utilities",
            "subcategory":"Water",
            "type":"Services"
        }
    ],
    "sg:phone":"+61 3 6272 5596",
    "sg:postcode":"7009",
    "sg:province":"TAS",
    "sg:tags":[
        "hot",
        "system"
    ],
    "wof:name":"C. Frendo Plumbing",
    "wof:placetype":"venue"
},
  "geometry": {"coordinates":[147.311737061,-42.8356819153],"type":"Point"}
}