{
  "type": "Feature",
  "properties": {
    "addr:full":"160 South Gippsland Hwy Dandenong VIC 3175",
    "addr:housenumber":"160",
    "addr:postcode":"3175",
    "addr:street":"South Gippsland Hwy",
    "iso:country":"AU",
    "sg:address":"160 South Gippsland Hwy",
    "sg:city":"Dandenong",
    "sg:classifiers":[
        {
            "category":"Shopping",
            "subcategory":"Discount & Variety Stores",
            "type":"Retail Goods"
        }
    ],
    "sg:phone":"+61 1300 661 606",
    "sg:postcode":"3175",
    "sg:province":"VIC",
    "sg:tags":[
        "mixing",
        "equipment",
        "industrial"
    ],
    "wof:name":"Sardik Mixers",
    "wof:placetype":"venue"
},
  "geometry": {"coordinates":[145.23175048799999,-38.0142402649],"type":"Point"}
}