{
  "type": "Feature",
  "properties": {
    "addr:full":"127 Mc Gregors Rd Greendale NSW 2745",
    "addr:housenumber":"127",
    "addr:postcode":"2745",
    "addr:street":"Mc Gregors Rd",
    "iso:country":"AU",
    "sg:address":"127 Mc Gregors Rd",
    "sg:city":"Greendale",
    "sg:classifiers":[
        {
            "category":"Professional",
            "subcategory":"Accounting & Tax Preparation",
            "type":"Services"
        }
    ],
    "sg:phone":"+61 2 6492 7117",
    "sg:postcode":"2745",
    "sg:province":"NSW",
    "sg:tags":[
        "bookkeeping"
    ],
    "wof:name":"Peter Kunzli",
    "wof:placetype":"venue"
},
  "geometry": {"coordinates":[150.679199219,-33.926109314],"type":"Point"}
}