{
  "type": "Feature",
  "properties": {
    "addr:full":"31 Hill St Camden NSW 2570",
    "addr:housenumber":"31",
    "addr:postcode":"2570",
    "addr:street":"Hill St",
    "iso:country":"AU",
    "sg:address":"31 Hill St",
    "sg:city":"Camden",
    "sg:classifiers":[
        {
            "category":"Health Services",
            "subcategory":"Doctor",
            "type":"Services"
        }
    ],
    "sg:phone":"+61 2 4655 7944",
    "sg:postcode":"2570",
    "sg:province":"NSW",
    "sg:tags":[
        "medical",
        "practitioner"
    ],
    "wof:name":"Camden Nuclear Medicine",
    "wof:placetype":"venue"
},
  "geometry": {"coordinates":[150.69769287099999,-34.0554885864],"type":"Point"}
}