{
  "type": "Feature",
  "properties": {
    "addr:full":"PO Box 427 Torrensville Plaza SA 5031",
    "addr:postcode":"5031",
    "iso:country":"AU",
    "sg:address":"PO Box 427",
    "sg:city":"Torrensville Plaza",
    "sg:classifiers":[
        {
            "category":"Professional",
            "subcategory":"Computer Services",
            "type":"Services"
        }
    ],
    "sg:phone":"+61 419 265 427",
    "sg:postcode":"5031",
    "sg:province":"SA",
    "sg:tags":[
        "equipment",
        "networking",
        "installation"
    ],
    "wof:name":"Torqueflite Connections",
    "wof:placetype":"venue"
},
  "geometry": {"coordinates":[138.562942505,-34.9230804443],"type":"Point"}
}