{
  "type": "Feature",
  "properties": {
    "addr:full":"79 Merimbula Drv Merimbula NSW 2548",
    "addr:housenumber":"79",
    "addr:postcode":"2548",
    "addr:street":"Merimbula Drv",
    "iso:country":"AU",
    "sg:address":"79 Merimbula Drv",
    "sg:city":"Merimbula",
    "sg:classifiers":[
        {
            "category":"Professional",
            "subcategory":"Art Services",
            "type":"Services"
        }
    ],
    "sg:phone":"+61 2 6495 4515",
    "sg:postcode":"2548",
    "sg:province":"NSW",
    "sg:tags":[
        "interior",
        "designer"
    ],
    "wof:name":"Envy Interiors",
    "wof:placetype":"venue"
},
  "geometry": {"coordinates":[149.90367126500001,-36.8895225525],"type":"Point"}
}