{
  "type": "Feature",
  "properties": {
    "iso:country":"AU",
    "sg:address":"Coonambula Rd",
    "sg:city":"Mundubbera",
    "sg:classifiers":[
        {
            "category":"Farming",
            "subcategory":"Orchard",
            "type":"Manufacturing & Wholesale Goods"
        }
    ],
    "sg:phone":"+61 7 4165 4755",
    "sg:postcode":"4626",
    "sg:province":"QLD",
    "sg:tags":[
        "citrus",
        "fruit",
        "grower"
    ],
    "wof:name":"Trott B J & J E & Sons",
    "wof:placetype":"venue"
},
  "geometry": {"coordinates":[151.28201300000001,-25.587931],"type":"Point"}
}