{
  "type": "Feature",
  "properties": {
    "iso:country":"AU",
    "sg:address":"9 Point Rd",
    "sg:city":"Northwood",
    "sg:classifiers":[
        {
            "category":"Health Services",
            "subcategory":"Doctor",
            "type":"Services"
        }
    ],
    "sg:phone":"+61 2 9418 3356",
    "sg:postcode":"2066",
    "sg:province":"NSW",
    "sg:tags":[
        "medical",
        "practitioner"
    ],
    "wof:name":"Alexander Stella Dr",
    "wof:placetype":"venue"
},
  "geometry": {"coordinates":[151.17942810100001,-33.8314323425],"type":"Point"}
}