{
  "type": "Feature",
  "properties": {
    "addr:full":"70 Mitchell St Bendigo VIC 3550",
    "addr:housenumber":"70",
    "addr:postcode":"3550",
    "addr:street":"Mitchell St",
    "iso:country":"AU",
    "sg:address":"70 Mitchell St",
    "sg:city":"Bendigo",
    "sg:classifiers":[
        {
            "category":"Food & Beverages",
            "subcategory":"Specialty",
            "type":"Retail Goods"
        }
    ],
    "sg:phone":"+61 3 5443 1910",
    "sg:postcode":"3550",
    "sg:province":"VIC",
    "sg:tags":[
        "product",
        "health"
    ],
    "wof:name":"Bendigo Health Foods & Organic Greengrocer",
    "wof:placetype":"venue"
},
  "geometry": {"coordinates":[144.28060913100001,-36.76171875],"type":"Point"}
}