{
  "type": "Feature",
  "properties": {
    "addr:full":"10 Green Rd Hope Valley SA 5090",
    "addr:housenumber":"10",
    "addr:postcode":"5090",
    "addr:street":"Green Rd",
    "iso:country":"AU",
    "sg:address":"10 Green Rd",
    "sg:city":"Hope Valley",
    "sg:classifiers":[
        {
            "category":"Home & Garden",
            "subcategory":"Carpets & Floor Coverings",
            "type":"Retail Goods"
        }
    ],
    "sg:phone":"+61 8 8395 2838",
    "sg:postcode":"5090",
    "sg:province":"SA",
    "sg:tags":[
        "tile",
        "wall",
        "layer"
    ],
    "wof:name":"R & H Ovan Floor & Wall Tiling",
    "wof:placetype":"venue"
},
  "geometry": {"coordinates":[138.712982178,-34.8465499878],"type":"Point"}
}