{
  "type": "Feature",
  "properties": {
    "addr:full":"Shop 8 St. Clair Shopping CTR 155 Bennett Rd St Clair NSW 2759",
    "addr:housenumber":"shop 8;155",
    "addr:postcode":"2759",
    "addr:street":"Shopping;Bennett Rd",
    "iso:country":"AU",
    "sg:address":"Shop 8 St. Clair Shopping CTR 155 Bennett Rd",
    "sg:city":"St Clair",
    "sg:classifiers":[
        {
            "category":"Personal",
            "subcategory":"Beauty Salon",
            "type":"Services"
        }
    ],
    "sg:phone":"+61 2 9834 5441",
    "sg:postcode":"2759",
    "sg:province":"NSW",
    "sg:tags":[
        "hairdresser"
    ],
    "wof:name":"Elies Hair & Beauty",
    "wof:placetype":"venue"
},
  "geometry": {"coordinates":[150.79020690900001,-33.7936706543],"type":"Point"}
}