{
  "type": "Feature",
  "properties": {
    "addr:full":"1/ 18 Broadwater Ave Hope Island QLD 4212",
    "addr:housenumber":"/ 18",
    "addr:postcode":"4212",
    "addr:street":"Broadwater Ave",
    "iso:country":"AU",
    "sg:address":"1/ 18 Broadwater Ave",
    "sg:city":"Hope Island",
    "sg:classifiers":[
        {
            "category":"Real Estate",
            "subcategory":"Real Estate Agent",
            "type":"Services"
        }
    ],
    "sg:phone":"+61 7 5510 8999",
    "sg:postcode":"4212",
    "sg:province":"QLD",
    "wof:name":"Century 21 First Impressions",
    "wof:placetype":"venue"
},
  "geometry": {"coordinates":[153.37286376899999,-27.8779201508],"type":"Point"}
}