{
  "type": "Feature",
  "properties": {
    "addr:full":"133 South Pine Rd Enoggera QLD 4051",
    "addr:housenumber":"133",
    "addr:postcode":"4051",
    "addr:street":"South Pine Rd",
    "iso:country":"AU",
    "sg:address":"133 South Pine Rd",
    "sg:city":"Enoggera",
    "sg:classifiers":[
        {
            "category":"Social Services",
            "subcategory":"Retirement Home",
            "type":"Services"
        }
    ],
    "sg:phone":"+61 7 3855 2252",
    "sg:postcode":"4051",
    "sg:province":"QLD",
    "sg:tags":[
        "village"
    ],
    "wof:name":"Mount Olivet Community Services Ltd -+Caritas Care",
    "wof:placetype":"venue"
},
  "geometry": {"coordinates":[152.99964904800001,-27.4205684662],"type":"Point"}
}