{
  "type": "Feature",
  "properties": {
    "addr:full":"Slatyer Ave Southport QLD 4215",
    "addr:postcode":"4215",
    "addr:street":"Slatyer Ave",
    "iso:country":"AU",
    "sg:address":"Slatyer Ave",
    "sg:city":"Southport",
    "sg:classifiers":[
        {
            "category":"Retail",
            "subcategory":"Event Space",
            "type":"Services"
        }
    ],
    "sg:phone":"+61 7 5532 1577",
    "sg:postcode":"4215",
    "sg:province":"QLD",
    "sg:tags":[
        "venue",
        "reception",
        "wedding"
    ],
    "wof:name":"Southport Golf Club",
    "wof:placetype":"venue"
},
  "geometry": {"coordinates":[153.41392517099999,-27.997543335],"type":"Point"}
}