{
  "type": "Feature",
  "properties": {
    "iso:country":"AU",
    "sg:address":"85 Lobb St",
    "sg:city":"Churchill",
    "sg:classifiers":[
        {
            "category":"Retail",
            "subcategory":"Auto Repair",
            "type":"Services"
        }
    ],
    "sg:phone":"+61 7 3812 3588",
    "sg:postcode":"4305",
    "sg:province":"QLD",
    "sg:tags":[
        "bus",
        "truck"
    ],
    "wof:name":"QPH Diesel Services",
    "wof:placetype":"venue"
},
  "geometry": {"coordinates":[152.747879028,-27.6316680908],"type":"Point"}
}