{
  "type": "Feature",
  "properties": {
    "addr:full":"PO Box 47 Bairnsdale VIC 3875",
    "addr:postcode":"3875",
    "iso:country":"AU",
    "sg:address":"PO Box 47",
    "sg:city":"Bairnsdale",
    "sg:classifiers":[
        {
            "category":"Farming",
            "subcategory":"Nursery",
            "type":"Manufacturing & Wholesale Goods"
        }
    ],
    "sg:phone":"+61 3 5152 4060",
    "sg:postcode":"3875",
    "sg:province":"VIC",
    "wof:name":"Goodman C J Pty Ltd",
    "wof:placetype":"venue"
},
  "geometry": {"coordinates":[147.61129760700001,-37.8314208984],"type":"Point"}
}