{
  "type": "Feature",
  "properties": {
    "addr:full":"551 Elizabeth St Surry Hills NSW 2010",
    "addr:housenumber":"551",
    "addr:postcode":"2010",
    "addr:street":"Elizabeth St",
    "iso:country":"AU",
    "sg:address":"551 Elizabeth St",
    "sg:city":"Surry Hills",
    "sg:classifiers":[
        {
            "category":"Real Estate",
            "subcategory":"Real Estate Agent",
            "type":"Services"
        }
    ],
    "sg:phone":"+61 2 9310 4222",
    "sg:postcode":"2010",
    "sg:province":"NSW",
    "wof:name":"Nationwide Realty Surry Hills",
    "wof:placetype":"venue"
},
  "geometry": {"coordinates":[151.20782470699999,-33.8893203735],"type":"Point"}
}