{
  "type": "Feature",
  "properties": {
    "addr:full":"10 Grice St Clontarf QLD 4019",
    "addr:housenumber":"10",
    "addr:postcode":"4019",
    "addr:street":"Grice St",
    "iso:country":"AU",
    "sg:address":"10 Grice St",
    "sg:city":"Clontarf",
    "sg:classifiers":[
        {
            "category":"Retail",
            "subcategory":"Auto Repair",
            "type":"Services"
        }
    ],
    "sg:phone":"+61 7 3889 3113",
    "sg:postcode":"4019",
    "sg:province":"QLD",
    "sg:tags":[
        "repairer",
        "motor",
        "engineer"
    ],
    "wof:name":"GKR Brakes & Suspension",
    "wof:placetype":"venue"
},
  "geometry": {"coordinates":[153.08001709000001,-27.2399940491],"type":"Point"}
}