{
  "type": "Feature",
  "properties": {
    "addr:full":"River Rd Murchison VIC 3610",
    "addr:postcode":"3610",
    "addr:street":"River Rd",
    "iso:country":"AU",
    "sg:address":"River Rd",
    "sg:city":"Murchison",
    "sg:classifiers":[
        {
            "category":"Arena",
            "subcategory":"Sports Club",
            "type":"Entertainment"
        }
    ],
    "sg:phone":"+61 3 5826 2560",
    "sg:postcode":"3610",
    "sg:province":"VIC",
    "sg:tags":[
        "australian",
        "football",
        "rule"
    ],
    "wof:name":"Murchison Football Club",
    "wof:placetype":"venue"
},
  "geometry": {"coordinates":[145.215606689,-36.6145324707],"type":"Point"}
}