{
  "type": "Feature",
  "properties": {
    "iso:country":"AU",
    "sg:address":"Cnr Ewar St & Exley Drv",
    "sg:city":"Moorabbin",
    "sg:classifiers":[
        {
            "category":"Retail",
            "subcategory":"Auto Repair",
            "type":"Services"
        }
    ],
    "sg:phone":"+61 3 9555 2262",
    "sg:postcode":"3189",
    "sg:province":"VIC",
    "sg:tags":[
        "repairer",
        "motor",
        "engineer"
    ],
    "wof:name":"Rod Finn Motors",
    "wof:placetype":"venue"
},
  "geometry": {"coordinates":[145.03695678700001,-37.9379768372],"type":"Point"}
}