{
  "type": "Feature",
  "properties": {
    "addr:full":"172 Sydney Rd Brunswick VIC 3056",
    "addr:housenumber":"172",
    "addr:postcode":"3056",
    "addr:street":"Sydney Rd",
    "iso:country":"AU",
    "sg:address":"172 Sydney Rd",
    "sg:city":"Brunswick",
    "sg:classifiers":[
        {
            "category":"Professional",
            "subcategory":"Management & Consulting",
            "type":"Services"
        }
    ],
    "sg:phone":"+61 3 9380 6663",
    "sg:postcode":"3056",
    "sg:province":"VIC",
    "sg:tags":[
        "consultant",
        "migration"
    ],
    "wof:name":"Australia Alien Migration",
    "wof:placetype":"venue"
},
  "geometry": {"coordinates":[144.9609375,-37.7731056213],"type":"Point"}
}