{
  "type": "Feature",
  "properties": {
    "addr:full":"200 Cobalt St Carole Park QLD 4300",
    "addr:housenumber":"200",
    "addr:postcode":"4300",
    "addr:street":"Cobalt St",
    "iso:country":"AU",
    "sg:address":"200 Cobalt St",
    "sg:city":"Carole Park",
    "sg:classifiers":[
        {
            "category":"Professional",
            "type":"Services"
        }
    ],
    "sg:phone":"+61 7 3216 7840",
    "sg:postcode":"4300",
    "sg:province":"QLD",
    "sg:tags":[
        "transport"
    ],
    "wof:name":"Marchetti Transport",
    "wof:placetype":"venue"
},
  "geometry": {"coordinates":[152.93763732900001,-27.6337661743],"type":"Point"}
}