{
  "type": "Feature",
  "properties": {
    "iso:country":"AU",
    "sg:address":"Unit 9/ 102 Norma Rd",
    "sg:city":"Myaree",
    "sg:classifiers":[
        {
            "category":"Retail",
            "subcategory":"Auto Repair",
            "type":"Services"
        }
    ],
    "sg:phone":"+61 8 9329 9000",
    "sg:postcode":"6154",
    "sg:province":"WA",
    "sg:tags":[
        "beater",
        "painter",
        "panel"
    ],
    "wof:name":"BRB Smash Repairs",
    "wof:placetype":"venue"
},
  "geometry": {"coordinates":[115.82215100000001,-32.043125],"type":"Point"}
}