{
  "type": "Feature",
  "properties": {
    "addr:full":"27 Ben Lexen Crt Gladstone QLD 4680",
    "addr:housenumber":"27",
    "addr:postcode":"4680",
    "addr:street":"Ben Lexen Crt",
    "iso:country":"AU",
    "sg:address":"27 Ben Lexen Crt",
    "sg:city":"Gladstone",
    "sg:classifiers":[
        {
            "category":"Recreation",
            "subcategory":"Boat Charter",
            "type":"Entertainment"
        }
    ],
    "sg:phone":"+61 7 4978 1342",
    "sg:postcode":"4680",
    "sg:province":"QLD",
    "wof:name":"M.V. Tura Charter Services",
    "wof:placetype":"venue"
},
  "geometry": {"coordinates":[151.25355529800001,-23.8438205719],"type":"Point"}
}