{
  "type": "Feature",
  "properties": {
    "addr:full":"35a Roberts St Footscray West VIC 3012",
    "addr:housenumber":"35a",
    "addr:postcode":"3012",
    "addr:street":"Roberts St",
    "iso:country":"AU",
    "sg:address":"35a Roberts St",
    "sg:city":"Footscray West",
    "sg:classifiers":[
        {
            "category":"Education",
            "subcategory":"Kindergarten",
            "type":"Public Place"
        }
    ],
    "sg:phone":"+61 3 9315 2008",
    "sg:postcode":"3012",
    "sg:province":"VIC",
    "sg:tags":[
        "pre-schools"
    ],
    "wof:name":"Kingsville Kindergarten",
    "wof:placetype":"venue"
},
  "geometry": {"coordinates":[144.87123107900001,-37.8038520813],"type":"Point"}
}