{
  "type": "Feature",
  "properties": {
    "addr:full":"1 Cawley Rd Brooklyn VIC 3012",
    "addr:housenumber":"1",
    "addr:postcode":"3012",
    "addr:street":"Cawley Rd",
    "iso:country":"AU",
    "sg:address":"1 Cawley Rd",
    "sg:city":"Brooklyn",
    "sg:classifiers":[
        {
            "category":"Professional",
            "subcategory":"Employment Agencies",
            "type":"Services"
        }
    ],
    "sg:phone":"+61 3 9314 0369",
    "sg:postcode":"3012",
    "sg:province":"VIC",
    "wof:name":"Credo Group",
    "wof:placetype":"venue"
},
  "geometry": {"coordinates":[144.86033630399999,-37.8202285767],"type":"Point"}
}