{
  "type": "Feature",
  "properties": {
    "addr:full":"948 Canterbury Rd Roselands NSW 2196",
    "addr:housenumber":"948",
    "addr:postcode":"2196",
    "addr:street":"Canterbury Rd",
    "iso:country":"AU",
    "sg:address":"948 Canterbury Rd",
    "sg:city":"Roselands",
    "sg:classifiers":[
        {
            "category":"Autos & Motor Vehicles",
            "subcategory":"Fuel & Gas Station",
            "type":"Retail Goods"
        }
    ],
    "sg:phone":"+61 2 9759 3662",
    "sg:postcode":"2196",
    "sg:province":"NSW",
    "wof:name":"United Roselands NSW",
    "wof:placetype":"venue"
},
  "geometry": {"coordinates":[151.078033,-33.928169],"type":"Point"}
}