{
  "type": "Feature",
  "properties": {
    "iso:country":"AU",
    "sg:address":"171 Collins St",
    "sg:city":"Melbourne",
    "sg:classifiers":[
        {
            "category":"Personal",
            "subcategory":"Day Spa",
            "type":"Services"
        }
    ],
    "sg:phone":"+61 3 9923 8888",
    "sg:postcode":"3000",
    "sg:province":"VIC",
    "wof:name":"Elly Lukas Skin & Bodycare",
    "wof:placetype":"venue"
},
  "geometry": {"coordinates":[144.96815490700001,-37.8151321411],"type":"Point"}
}