{
  "type": "Feature",
  "properties": {
    "addr:full":"1/ 17 Dundas Crt Phillip ACT 2606",
    "addr:housenumber":"/ 17",
    "addr:postcode":"2606",
    "addr:street":"Dundas Crt",
    "iso:country":"AU",
    "sg:address":"1/ 17 Dundas Crt",
    "sg:city":"Phillip",
    "sg:classifiers":[
        {
            "category":"Shopping",
            "subcategory":"Beauty & Cosmetics",
            "type":"Retail Goods"
        }
    ],
    "sg:phone":"+61 2 6282 7117",
    "sg:postcode":"2606",
    "sg:province":"ACT",
    "sg:tags":[
        "equipment",
        "salon",
        "supply"
    ],
    "wof:name":"Norris Hair & Beauty Plus",
    "wof:placetype":"venue"
},
  "geometry": {"coordinates":[149.089187622,-35.3535804749],"type":"Point"}
}