{
  "type": "Feature",
  "properties": {
    "addr:full":"70 Box Rd Taren Point NSW 2229",
    "addr:housenumber":"70",
    "addr:postcode":"2229",
    "addr:street":"Box Rd",
    "iso:country":"AU",
    "sg:address":"70 Box Rd",
    "sg:city":"Taren Point",
    "sg:classifiers":[
        {
            "category":"Shopping",
            "subcategory":"Gifts & Souvenirs",
            "type":"Retail Goods"
        }
    ],
    "sg:phone":"+61 2 9540 3666",
    "sg:postcode":"2229",
    "sg:province":"NSW",
    "sg:tags":[
        "shop",
        "supply"
    ],
    "wof:name":"For Arts Sake Pty Ltd",
    "wof:placetype":"venue"
},
  "geometry": {"coordinates":[151.118942261,-34.0240631104],"type":"Point"}
}