{
  "type": "Feature",
  "properties": {
    "iso:country":"AU",
    "sg:address":"46 Frazer St",
    "sg:city":"Dulwich Hill",
    "sg:classifiers":[
        {
            "category":"Manufacturing",
            "subcategory":"Metals",
            "type":"Manufacturing & Wholesale Goods"
        }
    ],
    "sg:phone":"+61 2 9560 1542",
    "sg:postcode":"2203",
    "sg:province":"NSW",
    "sg:tags":[
        "steel",
        "fabricator",
        "mfrs"
    ],
    "wof:name":"G H Metalwork Pty Ltd",
    "wof:placetype":"venue"
},
  "geometry": {"coordinates":[151.14846800000001,-33.901104],"type":"Point"}
}