{
  "type": "Feature",
  "properties": {
    "addr:full":"116 Rundle St Kent Town SA 5067",
    "addr:housenumber":"116",
    "addr:postcode":"5067",
    "addr:street":"Rundle St",
    "iso:country":"AU",
    "sg:address":"116 Rundle St",
    "sg:city":"Kent Town",
    "sg:classifiers":[
        {
            "category":"Shopping",
            "subcategory":"Computers & Home Electronics",
            "type":"Retail Goods"
        }
    ],
    "sg:phone":"+61 8 8363 8366",
    "sg:postcode":"5067",
    "sg:province":"SA",
    "sg:tags":[
        "equipment",
        "multimedia"
    ],
    "wof:name":"Clinic Design & New Media",
    "wof:placetype":"venue"
},
  "geometry": {"coordinates":[138.62263488799999,-34.9183959961],"type":"Point"}
}