{
  "type": "Feature",
  "properties": {
    "addr:full":"8 Hurstfield St Findon SA 5023",
    "addr:housenumber":"8",
    "addr:postcode":"5023",
    "addr:street":"Hurstfield St",
    "iso:country":"AU",
    "sg:address":"8 Hurstfield St",
    "sg:city":"Findon",
    "sg:classifiers":[
        {
            "category":"Building & Trades",
            "subcategory":"Plumbing",
            "type":"Services"
        }
    ],
    "sg:phone":"+61 412 338 930",
    "sg:postcode":"5023",
    "sg:province":"SA",
    "sg:tags":[
        "plumber",
        "gasfitters"
    ],
    "wof:name":"Mark White Plumbing",
    "wof:placetype":"venue"
},
  "geometry": {"coordinates":[138.53883361800001,-34.9009170532],"type":"Point"}
}