{
  "type": "Feature",
  "properties": {
    "addr:full":"5 Chislehurst Crt Narre Warren VIC 3805",
    "addr:housenumber":"5",
    "addr:postcode":"3805",
    "addr:street":"Chislehurst Crt",
    "iso:country":"AU",
    "sg:address":"5 Chislehurst Crt",
    "sg:city":"Narre Warren",
    "sg:classifiers":[
        {
            "category":"Shopping",
            "subcategory":"Computers & Home Electronics",
            "type":"Retail Goods"
        }
    ],
    "sg:phone":"+61 3 9796 6700",
    "sg:postcode":"3805",
    "sg:province":"VIC",
    "sg:tags":[
        "equipment",
        "multimedia"
    ],
    "wof:name":"A J Web Design",
    "wof:placetype":"venue"
},
  "geometry": {"coordinates":[145.29235800000001,-38.056103],"type":"Point"}
}