{
  "type": "Feature",
  "properties": {
    "addr:full":"490 Victoria St North Melbourne VIC 3051",
    "addr:housenumber":"490",
    "addr:postcode":"3051",
    "addr:street":"Victoria St",
    "iso:country":"AU",
    "sg:address":"490 Victoria St",
    "sg:city":"North Melbourne",
    "sg:classifiers":[
        {
            "category":"Wholesale",
            "subcategory":"Non-durable Goods",
            "type":"Manufacturing & Wholesale Goods"
        }
    ],
    "sg:phone":"+61 3 9326 7777",
    "sg:postcode":"3051",
    "sg:province":"VIC",
    "sg:tags":[
        "wholesaler",
        "mfrs",
        "cosmetic"
    ],
    "wof:name":"Creotech Pty Ltd",
    "wof:placetype":"venue"
},
  "geometry": {"coordinates":[144.949829102,-37.8050575256],"type":"Point"}
}