{
  "type": "Feature",
  "properties": {
    "addr:full":"80 Fullarton Rd Norwood SA 5067",
    "addr:housenumber":"80",
    "addr:postcode":"5067",
    "addr:street":"Fullarton Rd",
    "iso:country":"AU",
    "sg:address":"80 Fullarton Rd",
    "sg:city":"Norwood",
    "sg:classifiers":[
        {
            "category":"Shopping",
            "subcategory":"Computers & Home Electronics",
            "type":"Retail Goods"
        }
    ],
    "sg:phone":"+61 8 8363 1227",
    "sg:postcode":"5067",
    "sg:province":"SA",
    "sg:tags":[
        "equipment",
        "supply"
    ],
    "wof:name":"Laserline Supplies",
    "wof:placetype":"venue"
},
  "geometry": {"coordinates":[138.62348938,-34.9235115051],"type":"Point"}
}