{
  "type": "Feature",
  "properties": {
    "addr:full":"Hawdon St Barmera SA 5345",
    "addr:postcode":"5345",
    "addr:street":"Hawdon St",
    "iso:country":"AU",
    "sg:address":"Hawdon St",
    "sg:city":"Barmera",
    "sg:classifiers":[
        {
            "category":"Health Services",
            "subcategory":"Doctor",
            "type":"Services"
        }
    ],
    "sg:phone":"+61 8 8588 2040",
    "sg:postcode":"5345",
    "sg:province":"SA",
    "sg:tags":[
        "medical",
        "practitioner"
    ],
    "wof:name":"Newson A",
    "wof:placetype":"venue"
},
  "geometry": {"coordinates":[140.47184753400001,-34.2516365051],"type":"Point"}
}