{
  "type": "Feature",
  "properties": {
    "addr:full":"1/ 42a Bayview Crs Black Rock VIC 3193",
    "addr:housenumber":"/ 42a",
    "addr:postcode":"3193",
    "addr:street":"Bayview Crs",
    "iso:country":"AU",
    "sg:address":"1/ 42a Bayview Crs",
    "sg:city":"Black Rock",
    "sg:classifiers":[
        {
            "category":"Building & Trades",
            "subcategory":"Construction",
            "type":"Services"
        }
    ],
    "sg:phone":"+61 419 880 583",
    "sg:postcode":"3193",
    "sg:province":"VIC",
    "sg:tags":[
        "renovation",
        "alterations",
        "extension",
        "contractor"
    ],
    "wof:name":"Hemlock Carpentry And Joinery",
    "wof:placetype":"venue"
},
  "geometry": {"coordinates":[145.03994750999999,-37.9773483276],"type":"Point"}
}