{
  "type": "Feature",
  "properties": {
    "addr:full":"Shop 4/ 105A Tangerine St Fairfield NSW 2165",
    "addr:housenumber":"shop 4 / 105a",
    "addr:postcode":"2165",
    "addr:street":"Tangerine St",
    "iso:country":"AU",
    "sg:address":"Shop 4/ 105A Tangerine St",
    "sg:city":"Fairfield",
    "sg:classifiers":[
        {
            "category":"Autos & Motor Vehicles",
            "subcategory":"Auto Supplies",
            "type":"Retail Goods"
        }
    ],
    "sg:phone":"+61 2 9727 6128",
    "sg:postcode":"2165",
    "sg:province":"NSW",
    "sg:tags":[
        "accessory"
    ],
    "wof:name":"Autopro",
    "wof:placetype":"venue"
},
  "geometry": {"coordinates":[150.968994141,-33.8762969971],"type":"Point"}
}