{
  "type": "Feature",
  "properties": {
    "addr:full":"106 Church St Penola SA 5277",
    "addr:housenumber":"106",
    "addr:postcode":"5277",
    "addr:street":"Church St",
    "iso:country":"AU",
    "sg:address":"106 Church St",
    "sg:city":"Penola",
    "sg:classifiers":[
        {
            "category":"Autos & Motor Vehicles",
            "subcategory":"Fuel & Gas Station",
            "type":"Retail Goods"
        }
    ],
    "sg:phone":"+61 8 8737 2356",
    "sg:postcode":"5277",
    "sg:province":"SA",
    "wof:name":"Mobil Oil Australia Pty Ltd",
    "wof:placetype":"venue"
},
  "geometry": {"coordinates":[140.837006,-37.373077],"type":"Point"}
}