{
  "type": "Feature",
  "properties": {
    "addr:full":"1 Yarra St Hawthorn VIC 3122",
    "addr:housenumber":"1",
    "addr:postcode":"3122",
    "addr:street":"Yarra St",
    "iso:country":"AU",
    "sg:address":"1 Yarra St",
    "sg:city":"Hawthorn",
    "sg:classifiers":[
        {
            "category":"Real Estate",
            "subcategory":"Architect",
            "type":"Services"
        }
    ],
    "sg:phone":"+61 3 9818 3177",
    "sg:postcode":"3122",
    "sg:province":"VIC",
    "wof:name":"Archedg Pty Ltd",
    "wof:placetype":"venue"
},
  "geometry": {"coordinates":[145.02093505900001,-37.8211135864],"type":"Point"}
}