{
  "type": "Feature",
  "properties": {
    "addr:full":"628- 632 Smith St Clifton Hill VIC 3068",
    "addr:housenumber":"632",
    "addr:postcode":"3068",
    "addr:street":"Smith St",
    "iso:country":"AU",
    "sg:address":"628- 632 Smith St",
    "sg:city":"Clifton Hill",
    "sg:classifiers":[
        {
            "category":"Food & Beverages",
            "subcategory":"Liquor & Beverages",
            "type":"Retail Goods"
        }
    ],
    "sg:phone":"+61 3 9489 9011",
    "sg:postcode":"3068",
    "sg:province":"VIC",
    "sg:tags":[
        "merchant",
        "spirit",
        "wine"
    ],
    "wof:name":"Cantarella & Co (Victoria) Pty Ltd",
    "wof:placetype":"venue"
},
  "geometry": {"coordinates":[144.985595703,-37.7923088074],"type":"Point"}
}