{
  "type": "Feature",
  "properties": {
    "iso:country":"AU",
    "sg:address":"Fletcher Rd",
    "sg:city":"Frankston",
    "sg:classifiers":[
        {
            "category":"Sports & Exercise",
            "subcategory":"Gym",
            "type":"Entertainment"
        }
    ],
    "sg:phone":"+61 3 9238 8295",
    "sg:postcode":"3199",
    "sg:province":"VIC",
    "sg:tags":[
        "health",
        "fitness"
    ],
    "wof:name":"Chisolm Fitness Centre",
    "wof:placetype":"venue"
},
  "geometry": {"coordinates":[145.12179565400001,-38.1415710449],"type":"Point"}
}