{
  "type": "Feature",
  "properties": {
    "addr:full":"34 Goggs Rd Jindalee QLD 4074",
    "addr:housenumber":"34",
    "addr:postcode":"4074",
    "addr:street":"Goggs Rd",
    "iso:country":"AU",
    "sg:address":"34 Goggs Rd",
    "sg:city":"Jindalee",
    "sg:classifiers":[
        {
            "category":"Sports & Exercise",
            "subcategory":"Gym",
            "type":"Entertainment"
        }
    ],
    "sg:phone":"+61 7 3376 8488",
    "sg:postcode":"4074",
    "sg:province":"QLD",
    "sg:tags":[
        "health",
        "fitness"
    ],
    "wof:name":"Kids Spot",
    "wof:placetype":"venue"
},
  "geometry": {"coordinates":[152.948974609,-27.5351352692],"type":"Point"}
}