{
  "type": "Feature",
  "properties": {
    "iso:country":"AU",
    "sg:address":"Unit 4, 590- 594 Hovell St",
    "sg:city":"Albury",
    "sg:classifiers":[
        {
            "category":"Building & Trades",
            "subcategory":"Construction",
            "type":"Services"
        }
    ],
    "sg:phone":"+61 2 6025 0552",
    "sg:postcode":"2640",
    "sg:province":"NSW",
    "sg:tags":[
        "rendering",
        "cement"
    ],
    "wof:name":"MAC Render & Texture Coatings",
    "wof:placetype":"venue"
},
  "geometry": {"coordinates":[146.909988403,-36.0862045288],"type":"Point"}
}