{
  "type": "Feature",
  "properties": {
    "iso:country":"AU",
    "sg:address":"13 Broughton St",
    "sg:city":"Bundanoon",
    "sg:classifiers":[
        {
            "category":"Professional",
            "subcategory":"Art Services",
            "type":"Services"
        }
    ],
    "sg:phone":"+61 2 4883 6171",
    "sg:postcode":"2578",
    "sg:province":"NSW",
    "sg:tags":[
        "interior",
        "designer"
    ],
    "wof:name":"David Lorimer",
    "wof:placetype":"venue"
},
  "geometry": {"coordinates":[150.30921935999999,-34.6537818909],"type":"Point"}
}