{
  "type": "Feature",
  "properties": {
    "addr:full":"14/ 8-12 Deadman Rd Moorebank NSW 2170",
    "addr:housenumber":"14 / 8-12",
    "addr:postcode":"2170",
    "addr:street":"Deadman Rd",
    "iso:country":"AU",
    "sg:address":"14/ 8-12 Deadman Rd",
    "sg:city":"Moorebank",
    "sg:classifiers":[
        {
            "category":"Retail",
            "subcategory":"Auto Repair",
            "type":"Services"
        }
    ],
    "sg:phone":"+61 2 9602 9400",
    "sg:postcode":"2170",
    "sg:province":"NSW",
    "sg:tags":[
        "wheel",
        "balancing",
        "alignment"
    ],
    "wof:name":"Align Steering & Suspension",
    "wof:placetype":"venue"
},
  "geometry": {"coordinates":[150.936157227,-33.9325752258],"type":"Point"}
}