{
  "type": "Feature",
  "properties": {
    "iso:country":"AU",
    "sg:address":"866 Beachmere Rd",
    "sg:city":"Beachmere",
    "sg:classifiers":[
        {
            "category":"Restaurant",
            "type":"Food & Drink"
        }
    ],
    "sg:phone":"+61 7 5496 2228",
    "sg:postcode":"4510",
    "sg:province":"QLD",
    "wof:name":"Beachmere Chinese Restaurant",
    "wof:placetype":"venue"
},
  "geometry": {"coordinates":[153.050842,-27.128738],"type":"Point"}
}