{
  "type": "Feature",
  "properties": {
    "addr:full":"32 Percy Crs Chapman ACT 2611",
    "addr:housenumber":"32",
    "addr:postcode":"2611",
    "addr:street":"Percy Crs",
    "iso:country":"AU",
    "sg:address":"32 Percy Crs",
    "sg:city":"Chapman",
    "sg:classifiers":[
        {
            "category":"Shopping",
            "subcategory":"Pets & Pet Supplies",
            "type":"Retail Goods"
        }
    ],
    "sg:phone":"+61 2 6287 1339",
    "sg:postcode":"2611",
    "sg:province":"ACT",
    "sg:tags":[
        "equipment",
        "pre-stressing"
    ],
    "wof:name":"Australian Post Tensioning Systems Pty Ltd",
    "wof:placetype":"venue"
},
  "geometry": {"coordinates":[149.04078674300001,-35.3561592102],"type":"Point"}
}