{
  "type": "Feature",
  "properties": {
    "addr:full":"312a Pennant Hills Rd Carlingford NSW 2118",
    "addr:housenumber":"312a",
    "addr:postcode":"2118",
    "addr:street":"Pennant Hills Rd",
    "iso:country":"AU",
    "sg:address":"312a Pennant Hills Rd",
    "sg:city":"Carlingford",
    "sg:classifiers":[
        {
            "category":"Wholesale",
            "subcategory":"Painting Supplies",
            "type":"Manufacturing & Wholesale Goods"
        }
    ],
    "sg:phone":"+61 2 9873 3077",
    "sg:postcode":"2118",
    "sg:province":"NSW",
    "sg:tags":[
        "painter"
    ],
    "wof:name":"Carlingford 3D Paint Store",
    "wof:placetype":"venue"
},
  "geometry": {"coordinates":[151.04652404800001,-33.7832374573],"type":"Point"}
}