{
  "type": "Feature",
  "properties": {
    "addr:full":"72 McLachlan Ave Rushcutters Bay NSW 2011",
    "addr:housenumber":"72",
    "addr:postcode":"2011",
    "addr:street":"Mclachlan Ave",
    "iso:country":"AU",
    "sg:address":"72 McLachlan Ave",
    "sg:city":"Rushcutters Bay",
    "sg:classifiers":[
        {
            "category":"Wholesale",
            "subcategory":"Meat",
            "type":"Manufacturing & Wholesale Goods"
        }
    ],
    "sg:phone":"+61 2 9360 2822",
    "sg:postcode":"2011",
    "sg:province":"NSW",
    "sg:tags":[
        "packing",
        "exporting"
    ],
    "wof:name":"Pastoral Industries Pty Ltd",
    "wof:placetype":"venue"
},
  "geometry": {"coordinates":[151.228607178,-33.8764648438],"type":"Point"}
}