{
  "type": "Feature",
  "properties": {
    "iso:country":"AU",
    "sg:address":"1 Portsmouth Crt",
    "sg:city":"Gillman",
    "sg:classifiers":[
        {
            "category":"Utilities",
            "subcategory":"Electric",
            "type":"Services"
        }
    ],
    "sg:phone":"+61 414 813 666",
    "sg:postcode":"5013",
    "sg:province":"SA",
    "sg:tags":[
        "electrical",
        "contractor"
    ],
    "wof:name":"ERML Electrical Services",
    "wof:placetype":"venue"
},
  "geometry": {"coordinates":[138.526947022,-34.8422737122],"type":"Point"}
}