{
  "type": "Feature",
  "properties": {
    "addr:full":"PO Box 85 Kulin WA 6365",
    "addr:postcode":"6365",
    "iso:country":"AU",
    "sg:address":"PO Box 85",
    "sg:city":"Kulin",
    "sg:classifiers":[
        {
            "category":"Building & Trades",
            "subcategory":"Equipment Rental",
            "type":"Services"
        }
    ],
    "sg:phone":"+61 8 9889 0064",
    "sg:postcode":"6365",
    "sg:province":"WA",
    "sg:tags":[
        "party",
        "hire"
    ],
    "wof:name":"Cooks Marqee Hire",
    "wof:placetype":"venue"
},
  "geometry": {"coordinates":[118.158783,-32.667912],"type":"Point"}
}