{
  "type": "Feature",
  "properties": {
    "addr:full":"174 Warrigal Rd Burwood VIC 3125",
    "addr:housenumber":"174",
    "addr:postcode":"3125",
    "addr:street":"Warrigal Rd",
    "iso:country":"AU",
    "sg:address":"174 Warrigal Rd",
    "sg:city":"Burwood",
    "sg:classifiers":[
        {
            "category":"Professional",
            "subcategory":"Management & Consulting",
            "type":"Services"
        }
    ],
    "sg:phone":"+61 3 9808 4831",
    "sg:postcode":"3125",
    "sg:province":"VIC",
    "sg:tags":[
        "consultant"
    ],
    "wof:name":"Saturn Corporate Resources Pty Ltd",
    "wof:placetype":"venue"
},
  "geometry": {"coordinates":[145.096725464,-37.8435058594],"type":"Point"}
}