{
  "type": "Feature",
  "properties": {
    "addr:full":"81 Old Winsdor Rd Kellyville NSW 2155",
    "addr:housenumber":"81",
    "addr:postcode":"2155",
    "addr:street":"Old Winsdor Rd",
    "iso:country":"AU",
    "sg:address":"81 Old Winsdor Rd",
    "sg:city":"Kellyville",
    "sg:classifiers":[
        {
            "category":"Professional",
            "subcategory":"Detective & Security Services",
            "type":"Services"
        }
    ],
    "sg:phone":"+61 2 9833 2955",
    "sg:postcode":"2155",
    "sg:province":"NSW",
    "sg:tags":[
        "consultant",
        "system"
    ],
    "wof:name":"Advance Alarms NSW Pty Ltd",
    "wof:placetype":"venue"
},
  "geometry": {"coordinates":[150.937957764,-33.7204742432],"type":"Point"}
}