{
  "type": "Feature",
  "properties": {
    "addr:full":"72 Grafton St Cairns QLD 4870",
    "addr:housenumber":"72",
    "addr:postcode":"4870",
    "addr:street":"Grafton St",
    "iso:country":"AU",
    "sg:address":"72 Grafton St",
    "sg:city":"Cairns",
    "sg:classifiers":[
        {
            "category":"Manufacturing",
            "subcategory":"Food",
            "type":"Manufacturing & Wholesale Goods"
        }
    ],
    "sg:phone":"+61 7 4051 9565",
    "sg:postcode":"4870",
    "sg:province":"QLD",
    "sg:tags":[
        "function",
        "catering"
    ],
    "wof:name":"The Lillipad Caf\ufffd",
    "wof:placetype":"venue"
},
  "geometry": {"coordinates":[145.775390625,-16.9233455658],"type":"Point"}
}