{
  "type": "Feature",
  "properties": {
    "iso:country":"AU",
    "sg:address":"Sherbrook Rd",
    "sg:city":"Hornsby",
    "sg:classifiers":[
        {
            "category":"Building & Trades",
            "subcategory":"Plumbing",
            "type":"Services"
        }
    ],
    "sg:phone":"+61 2 9476 6550",
    "sg:postcode":"2077",
    "sg:province":"NSW",
    "sg:tags":[
        "plumber",
        "gasfitters"
    ],
    "wof:name":"A Team Plumbing",
    "wof:placetype":"venue"
},
  "geometry": {"coordinates":[151.10940551799999,-33.6891593933],"type":"Point"}
}