{
  "type": "Feature",
  "properties": {
    "addr:full":"34 Thompson Rd Beerwah QLD 4519",
    "addr:housenumber":"34",
    "addr:postcode":"4519",
    "addr:street":"Thompson Rd",
    "iso:country":"AU",
    "sg:address":"34 Thompson Rd",
    "sg:city":"Beerwah",
    "sg:classifiers":[
        {
            "category":"Wholesale",
            "subcategory":"Plants",
            "type":"Manufacturing & Wholesale Goods"
        }
    ],
    "sg:phone":"+61 7 5439 9300",
    "sg:postcode":"4519",
    "sg:province":"QLD",
    "sg:tags":[
        "florist"
    ],
    "wof:name":"Suncoast Wholesale Flowers",
    "wof:placetype":"venue"
},
  "geometry": {"coordinates":[152.95152300000001,-26.826288],"type":"Point"}
}