{
  "type": "Feature",
  "properties": {
    "iso:country":"AU",
    "sg:address":"287 King St",
    "sg:city":"Mascot",
    "sg:classifiers":[
        {
            "category":"Professional",
            "type":"Services"
        }
    ],
    "sg:phone":"+61 2 9669 3222",
    "sg:postcode":"2020",
    "sg:province":"NSW",
    "sg:tags":[
        "spray",
        "painting"
    ],
    "wof:name":"Just Paint Me",
    "wof:placetype":"venue"
},
  "geometry": {"coordinates":[151.18609619099999,-33.9282569885],"type":"Point"}
}