{
  "type": "Feature",
  "properties": {
    "iso:country":"AU",
    "sg:address":"251 Soldiers Point Rd",
    "sg:city":"Salamander Bay",
    "sg:classifiers":[
        {
            "category":"Professional",
            "subcategory":"Printing & Photocopies",
            "type":"Services"
        }
    ],
    "sg:phone":"+61 2 4982 0022",
    "sg:postcode":"2317",
    "sg:province":"NSW",
    "sg:tags":[
        "laminating"
    ],
    "wof:name":"Salamander Video Hire",
    "wof:placetype":"venue"
},
  "geometry": {"coordinates":[152.082886,-32.73333],"type":"Point"}
}