{
  "type": "Feature",
  "properties": {
    "iso:country":"AU",
    "sg:address":"296 Grimshaw St",
    "sg:city":"Watsonia",
    "sg:classifiers":[
        {
            "category":"Health Services",
            "subcategory":"Health Practitioner",
            "type":"Services"
        }
    ],
    "sg:phone":"+61 404 615 885",
    "sg:postcode":"3087",
    "sg:province":"VIC",
    "sg:tags":[
        "naturopath"
    ],
    "sg:website":"http://www.atms.com.au",
    "wof:name":"Herbal Healing",
    "wof:placetype":"venue"
},
  "geometry": {"coordinates":[145.084381103,-37.7023696899],"type":"Point"}
}