{
  "type": "Feature",
  "properties": {
    "addr:full":"Level 3, 43 Salamanca Sq Hobart TAS 7000",
    "addr:housenumber":"43",
    "addr:postcode":"7000",
    "addr:street":"Salamanca Sq",
    "iso:country":"AU",
    "sg:address":"Level 3, 43",
    "sg:city":"Salamanca Sq Hobart",
    "sg:classifiers":[
        {
            "category":"Professional",
            "subcategory":"Employment Agencies",
            "type":"Services"
        }
    ],
    "sg:phone":"+61 3 6223 1279",
    "sg:postcode":"7000",
    "sg:province":"TAS",
    "sg:website":"http://www.tcplacements.com",
    "wof:name":"TC Placements",
    "wof:placetype":"venue"
},
  "geometry": {"coordinates":[147.33277893100001,-42.8872337341],"type":"Point"}
}