{
  "type": "Feature",
  "properties": {
    "addr:full":"Nelson St Bridgetown WA 6255",
    "addr:postcode":"6255",
    "addr:street":"Nelson St",
    "iso:country":"AU",
    "sg:address":"Nelson St",
    "sg:city":"Bridgetown",
    "sg:classifiers":[
        {
            "category":"Arts & Performance",
            "subcategory":"Theater",
            "type":"Entertainment"
        }
    ],
    "sg:phone":"+61 8 9761 1207",
    "sg:postcode":"6255",
    "sg:province":"WA",
    "sg:tags":[
        "theatre"
    ],
    "wof:name":"Bridgetown Repertory Club (Inc)",
    "wof:placetype":"venue"
},
  "geometry": {"coordinates":[116.136810303,-33.9548568726],"type":"Point"}
}