{
  "type": "Feature",
  "properties": {
    "addr:full":"14 Transport Ave Netley SA 5037",
    "addr:housenumber":"14",
    "addr:postcode":"5037",
    "addr:street":"Transport Ave",
    "iso:country":"AU",
    "sg:address":"14 Transport Ave",
    "sg:city":"Netley",
    "sg:classifiers":[
        {
            "category":"Manufacturing",
            "subcategory":"Tools & Machinery",
            "type":"Manufacturing & Wholesale Goods"
        }
    ],
    "sg:phone":"+61 8 8443 7311",
    "sg:postcode":"5037",
    "sg:province":"SA",
    "sg:tags":[
        "toolmaker"
    ],
    "wof:name":"Australian Tooling Services",
    "wof:placetype":"venue"
},
  "geometry": {"coordinates":[138.54884338400001,-34.9455032349],"type":"Point"}
}