{
  "type": "Feature",
  "properties": {
    "iso:country":"AU",
    "sg:address":"89 Blyth St",
    "sg:city":"Altona",
    "sg:classifiers":[
        {
            "category":"Education",
            "subcategory":"Kindergarten",
            "type":"Public Place"
        }
    ],
    "sg:phone":"+61 3 9398 2839",
    "sg:postcode":"3018",
    "sg:province":"VIC",
    "sg:tags":[
        "pre-schools"
    ],
    "wof:name":"Altona Pre School Centre",
    "wof:placetype":"venue"
},
  "geometry": {"coordinates":[144.825561523,-37.8677024841],"type":"Point"}
}