{
  "type": "Feature",
  "properties": {
    "addr:full":"55 Smart St Fairfield NSW 2165",
    "addr:housenumber":"55",
    "addr:postcode":"2165",
    "addr:street":"Smart St",
    "iso:country":"AU",
    "sg:address":"55 Smart St",
    "sg:city":"Fairfield",
    "sg:classifiers":[
        {
            "category":"Shopping",
            "subcategory":"Clothing, Apparel, & Fashions",
            "type":"Retail Goods"
        }
    ],
    "sg:phone":"+61 2 9727 4602",
    "sg:postcode":"2165",
    "sg:province":"NSW",
    "sg:tags":[
        "boutique"
    ],
    "wof:name":"Vicky Mar Fashions",
    "wof:placetype":"venue"
},
  "geometry": {"coordinates":[150.953125,-33.8655891418],"type":"Point"}
}