{
  "type": "Feature",
  "properties": {
    "iso:country":"AU",
    "sg:address":"12 Cole St",
    "sg:city":"Laverton",
    "sg:classifiers":[
        {
            "category":"Shopping",
            "subcategory":"Computers & Home Electronics",
            "type":"Retail Goods"
        }
    ],
    "sg:phone":"+61 3 9369 0444",
    "sg:postcode":"3028",
    "sg:province":"VIC",
    "sg:tags":[
        "small",
        "equipment",
        "business"
    ],
    "wof:name":"Ezy Computers",
    "wof:placetype":"venue"
},
  "geometry": {"coordinates":[144.77124,-37.852684],"type":"Point"}
}