{
  "type": "Feature",
  "properties": {
    "addr:full":"3/ 34 Stennett Rd Ingleburn NSW 2565",
    "addr:housenumber":"/ 34",
    "addr:postcode":"2565",
    "addr:street":"Stennett Rd",
    "iso:country":"AU",
    "sg:address":"3/ 34 Stennett Rd",
    "sg:city":"Ingleburn",
    "sg:classifiers":[
        {
            "category":"Manufacturing",
            "subcategory":"Electronics",
            "type":"Manufacturing & Wholesale Goods"
        }
    ],
    "sg:phone":"+61 2 4627 9661",
    "sg:postcode":"2565",
    "sg:province":"NSW",
    "sg:tags":[
        "wholesaler",
        "equipment",
        "part",
        "mfrs",
        "refrigeration"
    ],
    "wof:name":"Refrigeration Equipment Sales",
    "wof:placetype":"venue"
},
  "geometry": {"coordinates":[150.85293579099999,-34.0022125244],"type":"Point"}
}