{
  "type": "Feature",
  "properties": {
    "iso:country":"AU",
    "sg:address":"PO Box 231",
    "sg:city":"Kilcoy",
    "sg:classifiers":[
        {
            "category":"Professional",
            "subcategory":"Art Services",
            "type":"Services"
        }
    ],
    "sg:phone":"+61 7 5422 0127",
    "sg:postcode":"4515",
    "sg:province":"QLD",
    "sg:tags":[
        "decorator",
        "painter"
    ],
    "wof:name":"G & L Cannon",
    "wof:placetype":"venue"
},
  "geometry": {"coordinates":[152.560608,-26.94767],"type":"Point"}
}