{
  "type": "Feature",
  "properties": {
    "addr:full":"3 / 10 Wittenberg Drv Canning Vale WA 6155",
    "addr:housenumber":"/ 10",
    "addr:postcode":"6155",
    "addr:street":"Wittenberg Drv",
    "iso:country":"AU",
    "sg:address":"3 / 10 Wittenberg Drv",
    "sg:city":"Canning Vale",
    "sg:classifiers":[
        {
            "category":"Transit Center",
            "subcategory":"Passenger",
            "type":"Transportation"
        }
    ],
    "sg:phone":"+61 8 9256 4155",
    "sg:postcode":"6155",
    "sg:province":"WA",
    "sg:tags":[
        "packing",
        "gasket"
    ],
    "wof:name":"Effective Sealing Solutions",
    "wof:placetype":"venue"
},
  "geometry": {"coordinates":[115.927048,-32.064831],"type":"Point"}
}