{
  "type": "Feature",
  "properties": {
    "iso:country":"AU",
    "sg:address":"13 Bentley St",
    "sg:city":"Wetherill Park",
    "sg:classifiers":[
        {
            "category":"Wholesale",
            "subcategory":"Home Furnishings",
            "type":"Manufacturing & Wholesale Goods"
        }
    ],
    "sg:phone":"+61 2 9604 8082",
    "sg:postcode":"2164",
    "sg:province":"NSW",
    "sg:tags":[
        "wholesaler",
        "mfrs",
        "manchester"
    ],
    "wof:name":"Kingtex International Pty Ltd",
    "wof:placetype":"venue"
},
  "geometry": {"coordinates":[150.883255005,-33.8471031189],"type":"Point"}
}