{
  "type": "Feature",
  "properties": {
    "iso:country":"AU",
    "sg:address":"27 Carrington St",
    "sg:city":"Nedlands",
    "sg:classifiers":[
        {
            "category":"Retail",
            "subcategory":"Auto Repair",
            "type":"Services"
        }
    ],
    "sg:phone":"+61 8 9386 7458",
    "sg:postcode":"6009",
    "sg:province":"WA",
    "sg:tags":[
        "electrical"
    ],
    "wof:name":"Nedlands Auto Electrics",
    "wof:placetype":"venue"
},
  "geometry": {"coordinates":[115.796227,-31.975542],"type":"Point"}
}