{
  "type": "Feature",
  "properties": {
    "addr:full":"PO Box 72 Holbrook NSW 2644",
    "addr:postcode":"2644",
    "iso:country":"AU",
    "sg:address":"PO Box 72",
    "sg:city":"Holbrook",
    "sg:classifiers":[
        {
            "category":"Organizations",
            "subcategory":"Professional Association",
            "type":"Services"
        }
    ],
    "sg:phone":"+61 2 6036 2545",
    "sg:postcode":"2644",
    "sg:province":"NSW",
    "sg:tags":[
        "rural",
        "organisation",
        "production",
        "primary"
    ],
    "wof:name":"Holbrook Show Socy",
    "wof:placetype":"venue"
},
  "geometry": {"coordinates":[147.31758117699999,-35.7186012268],"type":"Point"}
}