{
  "type": "Feature",
  "properties": {
    "iso:country":"AU",
    "sg:address":"Shop 8 Murray Sq",
    "sg:city":"Colac",
    "sg:classifiers":[
        {
            "category":"Shopping",
            "subcategory":"Music",
            "type":"Retail Goods"
        }
    ],
    "sg:phone":"+61 3 5231 2178",
    "sg:postcode":"3250",
    "sg:province":"VIC",
    "sg:tags":[
        "store"
    ],
    "wof:name":"Leading Edge Music",
    "wof:placetype":"venue"
},
  "geometry": {"coordinates":[143.591858,-38.339642],"type":"Point"}
}