{
  "type": "Feature",
  "properties": {
    "addr:full":"57 Chetwynd St Loganholme QLD 4129",
    "addr:housenumber":"57",
    "addr:postcode":"4129",
    "addr:street":"Chetwynd St",
    "iso:country":"AU",
    "sg:address":"57 Chetwynd St",
    "sg:city":"Loganholme",
    "sg:classifiers":[
        {
            "category":"Shopping",
            "subcategory":"Pets & Pet Supplies",
            "type":"Retail Goods"
        }
    ],
    "sg:phone":"+61 7 3801 1488",
    "sg:postcode":"4129",
    "sg:province":"QLD",
    "sg:tags":[
        "boring",
        "drilling",
        "equipment"
    ],
    "wof:name":"Engineered Components Pty Ltd",
    "wof:placetype":"venue"
},
  "geometry": {"coordinates":[153.19337463400001,-27.6796283722],"type":"Point"}
}