{
  "type": "Feature",
  "properties": {
    "iso:country":"AU",
    "sg:address":"92 Tourist Rd",
    "sg:city":"Toowoomba",
    "sg:classifiers":[
        {
            "category":"Travel",
            "subcategory":"Hotels & Motels",
            "type":"Entertainment"
        }
    ],
    "sg:phone":"+61 7 4635 8394",
    "sg:postcode":"4350",
    "sg:province":"QLD",
    "wof:name":"Jacaranda Grove Bed And Breakfast",
    "wof:placetype":"venue"
},
  "geometry": {"coordinates":[151.979095,-27.574162],"type":"Point"}
}