{
  "type": "Feature",
  "properties": {
    "iso:country":"AU",
    "sg:address":"2 Mallet St",
    "sg:city":"Kunda Park Maroochydore",
    "sg:classifiers":[
        {
            "category":"Professional",
            "type":"Services"
        }
    ],
    "sg:phone":"+61 7 5477 0866",
    "sg:postcode":"4558",
    "sg:province":"QLD",
    "sg:tags":[
        "shop",
        "fitting"
    ],
    "wof:name":"AQF Windows & Doors",
    "wof:placetype":"venue"
},
  "geometry": {"coordinates":[153.03202819800001,-26.6660327911],"type":"Point"}
}