{
  "type": "Feature",
  "properties": {
    "iso:country":"AU",
    "sg:address":"Parry St",
    "sg:city":"North Fremantle",
    "sg:classifiers":[
        {
            "category":"Arts & Performance",
            "subcategory":"Dance",
            "type":"Entertainment"
        }
    ],
    "sg:phone":"+61 416 642 490",
    "sg:postcode":"6159",
    "sg:province":"WA",
    "sg:tags":[
        "theatrical",
        "ballet",
        "tuition"
    ],
    "wof:name":"Organikdance",
    "wof:placetype":"venue"
},
  "geometry": {"coordinates":[115.754959,-32.035515],"type":"Point"}
}