{
  "type": "Feature",
  "properties": {
    "addr:full":"PO Box 197 Burra SA 5417",
    "addr:postcode":"5417",
    "iso:country":"AU",
    "sg:address":"PO Box 197",
    "sg:city":"Burra",
    "sg:classifiers":[
        {
            "category":"Communications",
            "subcategory":"News Services",
            "type":"Services"
        }
    ],
    "sg:phone":"+61 8 8892 2944",
    "sg:postcode":"5417",
    "sg:province":"SA",
    "sg:tags":[
        "information",
        "tourist",
        "attractions"
    ],
    "wof:name":"The Visitors Monthly For The Barossa, Clare Valley & Copper Country (Includes Yorke Peninsula)",
    "wof:placetype":"venue"
},
  "geometry": {"coordinates":[138.92662048299999,-33.6695594788],"type":"Point"}
}