{
  "type": "Feature",
  "properties": {
    "addr:full":"155 Burke Rd Glen Iris VIC 3146",
    "addr:housenumber":"155",
    "addr:postcode":"3146",
    "addr:street":"Burke Rd",
    "iso:country":"AU",
    "sg:address":"155 Burke Rd",
    "sg:city":"Glen Iris",
    "sg:classifiers":[
        {
            "category":"Food & Beverages",
            "subcategory":"Liquor & Beverages",
            "type":"Retail Goods"
        }
    ],
    "sg:phone":"+61 3 9509 7936",
    "sg:postcode":"3146",
    "sg:province":"VIC",
    "sg:tags":[
        "store"
    ],
    "wof:name":"Chaucer Cellars",
    "wof:placetype":"venue"
},
  "geometry": {"coordinates":[145.05023193400001,-37.8643074036],"type":"Point"}
}