{
  "type": "Feature",
  "properties": {
    "iso:country":"AU",
    "sg:address":"6/ 816 Hay St",
    "sg:city":"Perth",
    "sg:classifiers":[
        {
            "category":"Professional",
            "subcategory":"Business Services",
            "type":"Services"
        }
    ],
    "sg:phone":"+61 8 9481 0222",
    "sg:postcode":"6000",
    "sg:province":"WA",
    "sg:tags":[
        "drafting"
    ],
    "wof:name":"CADgraphics WA",
    "wof:placetype":"venue"
},
  "geometry": {"coordinates":[115.84956359900001,-31.9512615204],"type":"Point"}
}