{
  "type": "Feature",
  "properties": {
    "iso:country":"AU",
    "sg:address":"9 Beech St",
    "sg:city":"Marcoola",
    "sg:classifiers":[
        {
            "category":"Real Estate",
            "subcategory":"Real Estate Operator",
            "type":"Services"
        }
    ],
    "sg:phone":"+61 7 5450 5327",
    "sg:postcode":"4564",
    "sg:province":"QLD",
    "sg:tags":[
        "concrete",
        "pumping"
    ],
    "wof:name":"Meale's Concrete Pumping",
    "wof:placetype":"venue"
},
  "geometry": {"coordinates":[153.084274292,-26.6083106995],"type":"Point"}
}