{
  "type": "Feature",
  "properties": {
    "addr:full":"6 Dingley Ave Dandenong VIC 3175",
    "addr:housenumber":"6",
    "addr:postcode":"3175",
    "addr:street":"Dingley Ave",
    "iso:country":"AU",
    "sg:address":"6 Dingley Ave",
    "sg:city":"Dandenong",
    "sg:classifiers":[
        {
            "category":"Home & Garden",
            "subcategory":"Furniture",
            "type":"Retail Goods"
        }
    ],
    "sg:phone":"+61 3 9706 9706",
    "sg:postcode":"3175",
    "sg:province":"VIC",
    "sg:tags":[
        "business"
    ],
    "wof:name":"J D K Furniture",
    "wof:placetype":"venue"
},
  "geometry": {"coordinates":[145.19589233400001,-37.992855072],"type":"Point"}
}