{
  "type": "Feature",
  "properties": {
    "addr:full":"28 Rose St Ashfield NSW 2131",
    "addr:housenumber":"28",
    "addr:postcode":"2131",
    "addr:street":"Rose St",
    "iso:country":"AU",
    "sg:address":"28 Rose St",
    "sg:city":"Ashfield",
    "sg:classifiers":[
        {
            "category":"Banks & Credit Unions",
            "subcategory":"Investment Brokerage",
            "type":"Services"
        }
    ],
    "sg:phone":"+61 2 9797 6573",
    "sg:postcode":"2131",
    "sg:province":"NSW",
    "sg:tags":[
        "management",
        "property"
    ],
    "wof:name":"Fiddly Bits Property Maintenance",
    "wof:placetype":"venue"
},
  "geometry": {"coordinates":[151.124725342,-33.8914909363],"type":"Point"}
}