{
  "type": "Feature",
  "properties": {
    "addr:full":"19 Streeter Ave Glossop SA 5344",
    "addr:housenumber":"19",
    "addr:postcode":"5344",
    "addr:street":"Streeter Ave",
    "iso:country":"AU",
    "sg:address":"19 Streeter Ave",
    "sg:city":"Glossop",
    "sg:classifiers":[
        {
            "category":"Building & Trades",
            "subcategory":"Construction",
            "type":"Services"
        }
    ],
    "sg:phone":"+61 408 839 843",
    "sg:postcode":"5344",
    "sg:province":"SA",
    "sg:tags":[
        "concrete",
        "contractor"
    ],
    "wof:name":"Firli T & C A",
    "wof:placetype":"venue"
},
  "geometry": {"coordinates":[140.528442383,-34.2702865601],"type":"Point"}
}