{
  "type": "Feature",
  "properties": {
    "addr:full":"Bayliss St Jurien WA 6516",
    "addr:postcode":"6516",
    "addr:street":"Bayliss St",
    "iso:country":"AU",
    "sg:address":"Bayliss St",
    "sg:city":"Jurien",
    "sg:classifiers":[
        {
            "category":"Social Services",
            "subcategory":"Child Care",
            "type":"Services"
        }
    ],
    "sg:phone":"+61 8 9652 1808",
    "sg:postcode":"6516",
    "sg:province":"WA",
    "wof:name":"Coastal Kids Care Inc",
    "wof:placetype":"venue"
},
  "geometry": {"coordinates":[115.03780399999999,-30.307379],"type":"Point"}
}