{
  "type": "Feature",
  "properties": {
    "addr:full":"28 Marion St Brighton VIC 3186",
    "addr:housenumber":"28",
    "addr:postcode":"3186",
    "addr:street":"Marion St",
    "iso:country":"AU",
    "sg:address":"28 Marion St",
    "sg:city":"Brighton",
    "sg:classifiers":[
        {
            "category":"Real Estate",
            "subcategory":"Architect",
            "type":"Services"
        }
    ],
    "sg:phone":"+61 3 9503 1818",
    "sg:postcode":"3186",
    "sg:province":"VIC",
    "wof:name":"One20 Group Building Design",
    "wof:placetype":"venue"
},
  "geometry": {"coordinates":[145.00306701700001,-37.9063835144],"type":"Point"}
}