{
  "type": "Feature",
  "properties": {
    "iso:country":"AU",
    "sg:address":"St George St",
    "sg:city":"Mungindi",
    "sg:classifiers":[
        {
            "category":"Food & Beverages",
            "subcategory":"Supermarket",
            "type":"Retail Goods"
        }
    ],
    "sg:phone":"+61 2 6753 2083",
    "sg:postcode":"2406",
    "sg:province":"NSW",
    "sg:tags":[
        "grocery",
        "store"
    ],
    "wof:name":"Sykes W J & H M",
    "wof:placetype":"venue"
},
  "geometry": {"coordinates":[148.99902343799999,-28.9779453278],"type":"Point"}
}