{
  "type": "Feature",
  "properties": {
    "iso:country":"AU",
    "sg:address":"42 Bundall Rd",
    "sg:city":"Bundall",
    "sg:classifiers":[
        {
            "category":"Professional",
            "subcategory":"Art Services",
            "type":"Services"
        }
    ],
    "sg:phone":"+61 7 5538 6555",
    "sg:postcode":"4217",
    "sg:province":"QLD",
    "sg:tags":[
        "interior",
        "decorator"
    ],
    "wof:name":"Redelman Fabrics",
    "wof:placetype":"venue"
},
  "geometry": {"coordinates":[153.41184997600001,-28.0108375549],"type":"Point"}
}