{
  "type": "Feature",
  "properties": {
    "addr:full":"U2/ 18 Bearing Rd Seven Hills NSW 2147",
    "addr:housenumber":"18",
    "addr:postcode":"2147",
    "addr:street":"U2 /;Bearing Rd",
    "iso:country":"AU",
    "sg:address":"U2/ 18 Bearing Rd",
    "sg:city":"Seven Hills",
    "sg:classifiers":[
        {
            "category":"Food & Beverages",
            "subcategory":"Groceries & Convenience Stores",
            "type":"Retail Goods"
        }
    ],
    "sg:phone":"+61 2 9674 6202",
    "sg:postcode":"2147",
    "sg:province":"NSW",
    "wof:name":"Bearing Road Food Spot",
    "wof:placetype":"venue"
},
  "geometry": {"coordinates":[150.95715332,-33.7729797363],"type":"Point"}
}