{
  "type": "Feature",
  "properties": {
    "iso:country":"AU",
    "sg:address":"Gross St",
    "sg:city":"Carrington",
    "sg:classifiers":[
        {
            "category":"Utilities",
            "subcategory":"Natural Gas",
            "type":"Services"
        }
    ],
    "sg:phone":"+61 2 4962 2966",
    "sg:postcode":"2294",
    "sg:province":"NSW",
    "sg:tags":[
        "supplier"
    ],
    "wof:name":"Boral Energy",
    "wof:placetype":"venue"
},
  "geometry": {"coordinates":[151.760955811,-32.9049263],"type":"Point"}
}