{
  "type": "Feature",
  "properties": {
    "addr:full":"Lot 3/ Vixies Rd Wonga QLD 4873",
    "addr:housenumber":"3 / vixies",
    "addr:postcode":"4873",
    "addr:street":"Rd",
    "iso:country":"AU",
    "sg:address":"Lot 3/ Vixies Rd",
    "sg:city":"Wonga",
    "sg:classifiers":[
        {
            "category":"Food & Beverages",
            "subcategory":"Meat & Fish",
            "type":"Retail Goods"
        }
    ],
    "sg:phone":"+61 7 4098 7259",
    "sg:postcode":"4873",
    "sg:province":"QLD",
    "sg:tags":[
        "aquaculture"
    ],
    "wof:name":"Daintree Saltwater Barramundi",
    "wof:placetype":"venue"
},
  "geometry": {"coordinates":[145.41380310100001,-16.3301048279],"type":"Point"}
}