{
  "type": "Feature",
  "properties": {
    "addr:full":"77- 79 Dart St Oberon NSW 2787",
    "addr:housenumber":"79",
    "addr:postcode":"2787",
    "addr:street":"Dart St",
    "iso:country":"AU",
    "sg:address":"77- 79 Dart St",
    "sg:city":"Oberon",
    "sg:classifiers":[
        {
            "category":"Travel",
            "subcategory":"Hotels & Motels",
            "type":"Entertainment"
        }
    ],
    "sg:phone":"+61 2 6336 1866",
    "sg:postcode":"2787",
    "sg:province":"NSW",
    "wof:name":"Highlands Motor Inn",
    "wof:placetype":"venue"
},
  "geometry": {"coordinates":[149.855224609,-33.702507019],"type":"Point"}
}