{
  "type": "Feature",
  "properties": {
    "addr:full":"Suite 6, 35- 59 Main St Greensborough VIC 3088",
    "addr:housenumber":"35 59",
    "addr:postcode":"3088",
    "addr:street":"Main St",
    "iso:country":"AU",
    "sg:address":"Suite 6, 35- 59 Main St",
    "sg:city":"Greensborough",
    "sg:classifiers":[
        {
            "category":"Health Services",
            "subcategory":"Health Practitioner",
            "type":"Services"
        }
    ],
    "sg:phone":"+61 3 9434 3310",
    "sg:postcode":"3088",
    "sg:province":"VIC",
    "sg:tags":[
        "psychologist"
    ],
    "wof:name":"Kardaras Claudia",
    "wof:placetype":"venue"
},
  "geometry": {"coordinates":[145.10438537600001,-37.703163147],"type":"Point"}
}