{
  "type": "Feature",
  "properties": {
    "addr:full":"33 Roberts Crs Newnham TAS 7248",
    "addr:housenumber":"33",
    "addr:postcode":"7248",
    "addr:street":"Roberts Crs",
    "iso:country":"AU",
    "sg:address":"33 Roberts Crs",
    "sg:city":"Newnham",
    "sg:classifiers":[
        {
            "category":"Building & Trades",
            "subcategory":"Construction",
            "type":"Services"
        }
    ],
    "sg:phone":"+61 408 123 537",
    "sg:postcode":"7248",
    "sg:province":"TAS",
    "sg:tags":[
        "earth",
        "excavating",
        "moving",
        "contractor"
    ],
    "wof:name":"Josh Beauchamp Excavations",
    "wof:placetype":"venue"
},
  "geometry": {"coordinates":[147.12570190400001,-41.3921699524],"type":"Point"}
}