{
  "type": "Feature",
  "properties": {
    "addr:full":"227 Longwood Rd Heathfield SA 5153",
    "addr:housenumber":"227",
    "addr:postcode":"5153",
    "addr:street":"Longwood Rd",
    "iso:country":"AU",
    "sg:address":"227 Longwood Rd",
    "sg:city":"Heathfield",
    "sg:classifiers":[
        {
            "category":"Health Services",
            "subcategory":"Health Practitioner",
            "type":"Services"
        }
    ],
    "sg:phone":"+61 8 8388 5707",
    "sg:postcode":"5153",
    "sg:province":"SA",
    "sg:tags":[
        "physiotherapist"
    ],
    "wof:name":"Feldenkrais Practitioner",
    "wof:placetype":"venue"
},
  "geometry": {"coordinates":[138.72744750999999,-35.0341300964],"type":"Point"}
}