{
  "type": "Feature",
  "properties": {
    "addr:full":"764 Pacific Hwy Gordon NSW 2072",
    "addr:housenumber":"764",
    "addr:postcode":"2072",
    "addr:street":"Pacific Hwy",
    "iso:country":"AU",
    "sg:address":"764 Pacific Hwy",
    "sg:city":"Gordon",
    "sg:classifiers":[
        {
            "category":"Health Services",
            "subcategory":"Doctor",
            "type":"Services"
        }
    ],
    "sg:phone":"+61 2 9498 1088",
    "sg:postcode":"2072",
    "sg:province":"NSW",
    "sg:tags":[
        "medical",
        "practitioner"
    ],
    "wof:name":"Horgan T J",
    "wof:placetype":"venue"
},
  "geometry": {"coordinates":[151.15284729000001,-33.7562446594],"type":"Point"}
}