{
  "type": "Feature",
  "properties": {
    "iso:country":"AU",
    "sg:address":"491 Abernethy Rd",
    "sg:city":"Kewdale",
    "sg:classifiers":[
        {
            "category":"Manufacturing",
            "subcategory":"Motor Vehicles & Parts",
            "type":"Manufacturing & Wholesale Goods"
        }
    ],
    "sg:phone":"+61 8 9353 1533",
    "sg:postcode":"6105",
    "sg:province":"WA",
    "sg:tags":[
        "engine",
        "equipment",
        "diesel"
    ],
    "wof:name":"Stiles & Hicks",
    "wof:placetype":"venue"
},
  "geometry": {"coordinates":[115.950157166,-31.9740123749],"type":"Point"}
}