{
  "type": "Feature",
  "properties": {
    "addr:full":"Lot 2334 Angove La Moonta SA 5558",
    "addr:housenumber":"2334",
    "addr:postcode":"5558",
    "addr:street":"Angove La",
    "iso:country":"AU",
    "sg:address":"Lot 2334 Angove La",
    "sg:city":"Moonta",
    "sg:classifiers":[
        {
            "category":"Building & Trades",
            "subcategory":"Construction",
            "type":"Services"
        }
    ],
    "sg:phone":"+61 409 782 908",
    "sg:postcode":"5558",
    "sg:province":"SA",
    "sg:tags":[
        "welding"
    ],
    "wof:name":"N.Y.P. Mobile Welding Services",
    "wof:placetype":"venue"
},
  "geometry": {"coordinates":[137.60392761200001,-34.0603256226],"type":"Point"}
}