{
  "type": "Feature",
  "properties": {
    "iso:country":"AU",
    "sg:address":"93 Matthews Ave",
    "sg:city":"Airport West",
    "sg:classifiers":[
        {
            "category":"Wholesale",
            "subcategory":"Auto Parts",
            "type":"Manufacturing & Wholesale Goods"
        }
    ],
    "sg:phone":"+61 3 9338 1522",
    "sg:postcode":"3042",
    "sg:province":"VIC",
    "sg:tags":[
        "recyclers"
    ],
    "wof:name":"Airport West Car Parts",
    "wof:placetype":"venue"
},
  "geometry": {"coordinates":[144.89097595199999,-37.71484375],"type":"Point"}
}