{
  "type": "Feature",
  "properties": {
    "addr:full":"3 Donaldson St Manunda QLD 4870",
    "addr:housenumber":"3",
    "addr:postcode":"4870",
    "addr:street":"Donaldson St",
    "iso:country":"AU",
    "sg:address":"3 Donaldson St",
    "sg:city":"Manunda",
    "sg:classifiers":[
        {
            "category":"Building & Trades",
            "subcategory":"Cleaning & Sanitation",
            "type":"Services"
        }
    ],
    "sg:phone":"+61 7 4031 1930",
    "sg:postcode":"4870",
    "sg:province":"QLD",
    "sg:tags":[
        "industrial",
        "commercial",
        "contractor"
    ],
    "wof:name":"Northern Detailers",
    "wof:placetype":"venue"
},
  "geometry": {"coordinates":[145.75228881800001,-16.9149665833],"type":"Point"}
}