{
  "type": "Feature",
  "properties": {
    "addr:full":"6 Northern Rd Heidelberg West VIC 3081",
    "addr:housenumber":"6",
    "addr:postcode":"3081",
    "addr:street":"Northern Rd",
    "iso:country":"AU",
    "sg:address":"6 Northern Rd",
    "sg:city":"Heidelberg West",
    "sg:classifiers":[
        {
            "category":"Manufacturing",
            "subcategory":"Paper Products",
            "type":"Manufacturing & Wholesale Goods"
        }
    ],
    "sg:phone":"+61 3 9457 5222",
    "sg:postcode":"3081",
    "sg:province":"VIC",
    "sg:tags":[
        "disposable"
    ],
    "wof:name":"Harris Paper Pty Ltd",
    "wof:placetype":"venue"
},
  "geometry": {"coordinates":[145.043731689,-37.7290496826],"type":"Point"}
}