{
  "type": "Feature",
  "properties": {
    "iso:country":"AU",
    "sg:address":"Logan Rd",
    "sg:city":"Thursday Island",
    "sg:classifiers":[
        {
            "category":"Organizations",
            "subcategory":"Professional Association",
            "type":"Services"
        }
    ],
    "sg:phone":"+61 7 4069 1943",
    "sg:postcode":"4875",
    "sg:province":"QLD",
    "sg:tags":[
        "rural",
        "organisation",
        "production",
        "primary"
    ],
    "wof:name":"Q.C.W.A.",
    "wof:placetype":"venue"
},
  "geometry": {"coordinates":[142.22085571299999,-10.5806503296],"type":"Point"}
}