{
  "type": "Feature",
  "properties": {
    "iso:country":"AU",
    "sg:address":"18 Nimala Ave",
    "sg:city":"Koolewong",
    "sg:classifiers":[
        {
            "category":"Health Services",
            "subcategory":"Health Practitioner",
            "type":"Services"
        }
    ],
    "sg:phone":"+61 2 4343 1481",
    "sg:postcode":"2256",
    "sg:province":"NSW",
    "sg:tags":[
        "homoeopath"
    ],
    "wof:name":"Diane Hill",
    "wof:placetype":"venue"
},
  "geometry": {"coordinates":[151.31578064000001,-33.4645996094],"type":"Point"}
}