{
  "type": "Feature",
  "properties": {
    "addr:full":"Depot Daphne St Violet Town VIC 3669",
    "addr:postcode":"3669",
    "addr:street":"Daphne St",
    "iso:country":"AU",
    "sg:address":"Depot Daphne St",
    "sg:city":"Violet Town",
    "sg:classifiers":[
        {
            "category":"Home & Garden",
            "subcategory":"Garden Supply",
            "type":"Retail Goods"
        }
    ],
    "sg:phone":"+61 3 5795 2870",
    "sg:postcode":"3669",
    "sg:province":"VIC",
    "sg:tags":[
        "fertilizer"
    ],
    "wof:name":"Violet Town Fertilisers",
    "wof:placetype":"venue"
},
  "geometry": {"coordinates":[145.72117614699999,-36.6366729736],"type":"Point"}
}