{
  "type": "Feature",
  "properties": {
    "addr:full":"33 Downs St North Ipswich QLD 4305",
    "addr:housenumber":"33",
    "addr:postcode":"4305",
    "addr:street":"Downs St",
    "iso:country":"AU",
    "sg:address":"33 Downs St",
    "sg:city":"North Ipswich",
    "sg:classifiers":[
        {
            "category":"Autos & Motor Vehicles",
            "subcategory":"Automobile Sales",
            "type":"Retail Goods"
        }
    ],
    "sg:phone":"+61 7 3812 1214",
    "sg:postcode":"4305",
    "sg:province":"QLD",
    "sg:tags":[
        "car",
        "used"
    ],
    "wof:name":"Helland's Wholesale Cars",
    "wof:placetype":"venue"
},
  "geometry": {"coordinates":[152.76133727999999,-27.6044273376],"type":"Point"}
}