{
  "type": "Feature",
  "properties": {
    "addr:full":"20 Windsor Rd Croydon VIC 3136",
    "addr:housenumber":"20",
    "addr:postcode":"3136",
    "addr:street":"Windsor Rd",
    "iso:country":"AU",
    "sg:address":"20 Windsor Rd",
    "sg:city":"Croydon",
    "sg:classifiers":[
        {
            "category":"Autos & Motor Vehicles",
            "subcategory":"Auto Supplies",
            "type":"Retail Goods"
        }
    ],
    "sg:phone":"+61 3 9725 1166",
    "sg:postcode":"3136",
    "sg:province":"VIC",
    "sg:tags":[
        "tyre"
    ],
    "wof:name":"Tyres Plus",
    "wof:placetype":"venue"
},
  "geometry": {"coordinates":[145.285690308,-37.7944145203],"type":"Point"}
}