{
  "type": "Feature",
  "properties": {
    "addr:full":"GD K290 Sunshine Plaza Cnr Horton Pde & Maroochydore Rd Maroochydore QLD 4558",
    "addr:housenumber":"k290",
    "addr:postcode":"4558",
    "addr:street":"Sunshine Plaza Cnr Horton;Rd",
    "iso:country":"AU",
    "sg:address":"GD K290 Sunshine Plaza Cnr Horton Pde & Maroochydore Rd",
    "sg:city":"Maroochydore",
    "sg:classifiers":[
        {
            "category":"Cafe",
            "type":"Food & Drink"
        }
    ],
    "sg:phone":"+61 7 5443 6351",
    "sg:postcode":"4558",
    "sg:province":"QLD",
    "wof:name":"Gloria Jean's Coffees",
    "wof:placetype":"venue"
},
  "geometry": {"coordinates":[153.08952331500001,-26.6529693604],"type":"Point"}
}