{
  "type": "Feature",
  "properties": {
    "iso:country":"AU",
    "sg:address":"Holy Spirit Medical Centre, Rode Rd",
    "sg:city":"Chermside",
    "sg:classifiers":[
        {
            "category":"Health Services",
            "subcategory":"Doctor",
            "type":"Services"
        }
    ],
    "sg:phone":"+61 7 3621 3111",
    "sg:postcode":"4032",
    "sg:province":"QLD",
    "sg:tags":[
        "medical",
        "practitioner"
    ],
    "wof:name":"Adsett Michael",
    "wof:placetype":"venue"
},
  "geometry": {"coordinates":[153.031677,-27.393438],"type":"Point"}
}