{
  "type": "Feature",
  "properties": {
    "addr:full":"Australian Arcade Fitzmaurice St Wagga Wagga NSW 2650",
    "addr:postcode":"2650",
    "addr:street":"Fitzmaurice St",
    "iso:country":"AU",
    "sg:address":"Australian Arcade Fitzmaurice St",
    "sg:city":"Wagga Wagga",
    "sg:classifiers":[
        {
            "category":"Food & Beverages",
            "subcategory":"Specialty",
            "type":"Retail Goods"
        }
    ],
    "sg:phone":"+61 2 6921 4333",
    "sg:postcode":"2650",
    "sg:province":"NSW",
    "sg:tags":[
        "delicacy"
    ],
    "wof:name":"Tavenders Gourmet Produce",
    "wof:placetype":"venue"
},
  "geometry": {"coordinates":[147.37068176299999,-35.1078605652],"type":"Point"}
}