{
  "type": "Feature",
  "properties": {
    "addr:full":"191 Flinders St Adelaide SA 5000",
    "addr:housenumber":"191",
    "addr:postcode":"5000",
    "addr:street":"Flinders St",
    "iso:country":"AU",
    "sg:address":"191 Flinders St",
    "sg:city":"Adelaide",
    "sg:classifiers":[
        {
            "category":"Professional",
            "subcategory":"Accounting & Tax Preparation",
            "type":"Services"
        }
    ],
    "sg:phone":"+61 8 8407 1301",
    "sg:postcode":"5000",
    "sg:province":"SA",
    "sg:tags":[
        "consultant",
        "taxation"
    ],
    "wof:name":"Cleland McFarlane Selth Pty Ltd",
    "wof:placetype":"venue"
},
  "geometry": {"coordinates":[138.607879639,-34.9268798828],"type":"Point"}
}