{
  "type": "Feature",
  "properties": {
    "iso:country":"AU",
    "sg:address":"177- 179 Main South Rd",
    "sg:city":"Morphett Vale",
    "sg:classifiers":[
        {
            "category":"Professional",
            "subcategory":"Accounting & Tax Preparation",
            "type":"Services"
        }
    ],
    "sg:phone":"+61 8 8382 0175",
    "sg:postcode":"5162",
    "sg:province":"SA",
    "sg:tags":[
        "consultant",
        "taxation"
    ],
    "wof:name":"Morphett Vale Management & Income Tax Consultants Pty Ltd",
    "wof:placetype":"venue"
},
  "geometry": {"coordinates":[138.52288818400001,-35.1200447083],"type":"Point"}
}