{
  "type": "Feature",
  "properties": {
    "addr:full":"6 Apex Crt Thomastown VIC 3074",
    "addr:housenumber":"6",
    "addr:postcode":"3074",
    "addr:street":"Apex Crt",
    "iso:country":"AU",
    "sg:address":"6 Apex Crt",
    "sg:city":"Thomastown",
    "sg:classifiers":[
        {
            "category":"Professional",
            "subcategory":"Art Services",
            "type":"Services"
        }
    ],
    "sg:phone":"+61 3 9464 4668",
    "sg:postcode":"3074",
    "sg:province":"VIC",
    "sg:tags":[
        "picture",
        "frame",
        "framing"
    ],
    "wof:name":"Taylor Made Prints",
    "wof:placetype":"venue"
},
  "geometry": {"coordinates":[145.034988403,-37.6952552795],"type":"Point"}
}