{
  "type": "Feature",
  "properties": {
    "addr:full":"68 Gilbert St Latrobe TAS 7307",
    "addr:housenumber":"68",
    "addr:postcode":"7307",
    "addr:street":"Gilbert St",
    "iso:country":"AU",
    "sg:address":"68 Gilbert St",
    "sg:city":"Latrobe",
    "sg:classifiers":[
        {
            "category":"Fast Food",
            "type":"Food & Drink"
        }
    ],
    "sg:phone":"+61 3 6426 1744",
    "sg:postcode":"7307",
    "sg:province":"TAS",
    "sg:tags":[
        "away",
        "take"
    ],
    "wof:name":"McBain Milkbar & Takeaway",
    "wof:placetype":"venue"
},
  "geometry": {"coordinates":[146.40901199999999,-41.235313],"type":"Point"}
}