{
  "type": "Feature",
  "properties": {
    "iso:country":"AU",
    "sg:address":"87 High St",
    "sg:city":"Doncaster",
    "sg:classifiers":[
        {
            "category":"Health Services",
            "subcategory":"Doctor",
            "type":"Services"
        }
    ],
    "sg:phone":"+61 3 9857 5943",
    "sg:postcode":"3108",
    "sg:province":"VIC",
    "sg:tags":[
        "medical",
        "practitioner"
    ],
    "wof:name":"Doncaster Supercare Family Medical Centre",
    "wof:placetype":"venue"
},
  "geometry": {"coordinates":[145.110229492,-37.7818603516],"type":"Point"}
}