{
  "type": "Feature",
  "properties": {
    "iso:country":"AU",
    "sg:address":"151 Lachlan St",
    "sg:city":"Forbes",
    "sg:classifiers":[
        {
            "category":"Banks & Credit Unions",
            "subcategory":"Financial Services",
            "type":"Services"
        }
    ],
    "sg:phone":"+61 2 6852 1412",
    "sg:postcode":"2871",
    "sg:province":"NSW",
    "sg:tags":[
        "annuity",
        "rollover",
        "superannuation",
        "consultant"
    ],
    "wof:name":"Investor Financial Planning",
    "wof:placetype":"venue"
},
  "geometry": {"coordinates":[148.006653,-33.385841],"type":"Point"}
}