{
  "type": "Feature",
  "properties": {
    "iso:country":"AU",
    "sg:address":"14 St Johns St",
    "sg:city":"Adelaide",
    "sg:classifiers":[
        {
            "category":"Health Services",
            "subcategory":"Health Practitioner",
            "type":"Services"
        }
    ],
    "sg:phone":"+61 409 673 866",
    "sg:postcode":"5000",
    "sg:province":"SA",
    "sg:tags":[
        "psychotherapist"
    ],
    "wof:name":"Helen Phillips",
    "wof:placetype":"venue"
},
  "geometry": {"coordinates":[138.61558532699999,-34.932346344],"type":"Point"}
}