{
  "type": "Feature",
  "properties": {
    "addr:full":"7 Glass St Essendon VIC 3040",
    "addr:housenumber":"7",
    "addr:postcode":"3040",
    "addr:street":"Glass St",
    "iso:country":"AU",
    "sg:address":"7 Glass St",
    "sg:city":"Essendon",
    "sg:classifiers":[
        {
            "category":"Banks & Credit Unions",
            "subcategory":"Financial Services",
            "type":"Services"
        }
    ],
    "sg:phone":"+61 3 9379 4033",
    "sg:postcode":"3040",
    "sg:province":"VIC",
    "sg:tags":[
        "planning"
    ],
    "wof:name":"Adrian McConnell",
    "wof:placetype":"venue"
},
  "geometry": {"coordinates":[144.92047119099999,-37.7471389771],"type":"Point"}
}