{
  "type": "Feature",
  "properties": {
    "addr:full":"15 Loffs Rd Mt Ommaney QLD 4074",
    "addr:housenumber":"15",
    "addr:postcode":"4074",
    "addr:street":"Loffs Rd;Ommaney",
    "iso:country":"AU",
    "sg:address":"15 Loffs Rd",
    "sg:city":"Mt Ommaney",
    "sg:classifiers":[
        {
            "category":"Health Services",
            "subcategory":"Health Practitioner",
            "type":"Services"
        }
    ],
    "sg:phone":"+61 7 3376 7874",
    "sg:postcode":"4074",
    "sg:province":"QLD",
    "sg:tags":[
        "pathologist",
        "speech"
    ],
    "wof:name":"Price Lynne D",
    "wof:placetype":"venue"
},
  "geometry": {"coordinates":[152.905395508,-27.5474967957],"type":"Point"}
}