{
  "type": "Feature",
  "properties": {
    "iso:country":"AU",
    "sg:address":"Factory 16/ 10 Norton Drv",
    "sg:city":"Melton",
    "sg:classifiers":[
        {
            "category":"Building & Trades",
            "subcategory":"Locksmith",
            "type":"Services"
        }
    ],
    "sg:phone":"+61 3 9747 6455",
    "sg:postcode":"3337",
    "sg:province":"VIC",
    "sg:tags":[
        "equipment",
        "operating",
        "door",
        "gate"
    ],
    "wof:name":"Austin & Watson Pty Ltd",
    "wof:placetype":"venue"
},
  "geometry": {"coordinates":[144.601791,-37.691059],"type":"Point"}
}