{
  "type": "Feature",
  "properties": {
    "addr:full":"Rear 70 Prince St Grafton NSW 2460",
    "addr:housenumber":"70",
    "addr:postcode":"2460",
    "addr:street":"Prince St",
    "iso:country":"AU",
    "sg:address":"Rear 70 Prince St",
    "sg:city":"Grafton",
    "sg:classifiers":[
        {
            "category":"Cafe",
            "type":"Food & Drink"
        }
    ],
    "sg:phone":"+61 2 6643 4450",
    "sg:postcode":"2460",
    "sg:province":"NSW",
    "wof:name":"Grafton Central Coffee Shop",
    "wof:placetype":"venue"
},
  "geometry": {"coordinates":[152.93429565400001,-29.6902732849],"type":"Point"}
}