{
  "type": "Feature",
  "properties": {
    "addr:full":"Unit 4/ 312 West St Toowoomba QLD 4350",
    "addr:housenumber":"/ 312",
    "addr:postcode":"4350",
    "addr:street":"West St",
    "iso:country":"AU",
    "sg:address":"Unit 4/ 312 West St",
    "sg:city":"Toowoomba",
    "sg:classifiers":[
        {
            "category":"Personal",
            "subcategory":"Beauty Salon",
            "type":"Services"
        }
    ],
    "sg:phone":"+61 7 4635 7196",
    "sg:postcode":"4350",
    "sg:province":"QLD",
    "sg:tags":[
        "hairdresser"
    ],
    "wof:name":"Hairdressing-Your Home",
    "wof:placetype":"venue"
},
  "geometry": {"coordinates":[151.93826300000001,-27.589891],"type":"Point"}
}