{
  "type": "Feature",
  "properties": {
    "iso:country":"AU",
    "sg:address":"Harris Rd",
    "sg:city":"Edmonton",
    "sg:classifiers":[
        {
            "category":"Farming",
            "subcategory":"Farm",
            "type":"Manufacturing & Wholesale Goods"
        }
    ],
    "sg:phone":"+61 7 4055 4106",
    "sg:postcode":"4869",
    "sg:province":"QLD",
    "sg:tags":[
        "farmer"
    ],
    "wof:name":"Ligasacchi M",
    "wof:placetype":"venue"
},
  "geometry": {"coordinates":[145.76858520499999,-17.0399436951],"type":"Point"}
}