{
  "type": "Feature",
  "properties": {
    "iso:country":"AU",
    "sg:address":"976 Waterworks Rd",
    "sg:city":"The Gap",
    "sg:classifiers":[
        {
            "category":"Health Services",
            "subcategory":"Doctor",
            "type":"Services"
        }
    ],
    "sg:phone":"+61 7 3300 1900",
    "sg:postcode":"4061",
    "sg:province":"QLD",
    "sg:tags":[
        "medical",
        "practitioner"
    ],
    "wof:name":"Skoien Cathy",
    "wof:placetype":"venue"
},
  "geometry": {"coordinates":[152.95262145999999,-27.4448108673],"type":"Point"}
}