{
  "type": "Feature",
  "properties": {
    "iso:country":"AU",
    "sg:address":"7 Hotham St",
    "sg:city":"Chatswood",
    "sg:classifiers":[
        {
            "category":"Professional",
            "subcategory":"Engineering",
            "type":"Services"
        }
    ],
    "sg:phone":"+61 2 9419 6214",
    "sg:postcode":"2067",
    "sg:province":"NSW",
    "sg:tags":[
        "consulting",
        "engineer"
    ],
    "wof:name":"Shelley G J & Associates Pty Ltd",
    "wof:placetype":"venue"
},
  "geometry": {"coordinates":[151.17945861800001,-33.7903823853],"type":"Point"}
}