{
  "type": "Feature",
  "properties": {
    "iso:country":"AU",
    "sg:address":"3 Mountain Drv",
    "sg:city":"Mooroolbark",
    "sg:classifiers":[
        {
            "category":"Train Station",
            "subcategory":"Light Rail",
            "type":"Transportation"
        }
    ],
    "sg:phone":"+61 3 9728 4008",
    "sg:postcode":"3138",
    "sg:province":"VIC",
    "sg:tags":[
        "equipment",
        "energy",
        "solar"
    ],
    "wof:name":"Sunsational Solar Heating",
    "wof:placetype":"venue"
},
  "geometry": {"coordinates":[145.33375549300001,-37.7940368652],"type":"Point"}
}