{
  "type": "Feature",
  "properties": {
    "addr:full":"4 Hillview St Dulwich SA 5065",
    "addr:housenumber":"4",
    "addr:postcode":"5065",
    "addr:street":"Hillview St",
    "iso:country":"AU",
    "sg:address":"4 Hillview St",
    "sg:city":"Dulwich",
    "sg:classifiers":[
        {
            "category":"Education",
            "subcategory":"Dance Studio",
            "type":"Public Place"
        }
    ],
    "sg:phone":"+61 8 8333 1312",
    "sg:postcode":"5065",
    "sg:province":"SA",
    "sg:tags":[
        "instruction",
        "language"
    ],
    "sg:website":"http://www.barbara-baldwin.com.au",
    "wof:name":"Advanced SpeechCraft",
    "wof:placetype":"venue"
},
  "geometry": {"coordinates":[138.63304138199999,-34.9384422302],"type":"Point"}
}