{
  "type": "Feature",
  "properties": {
    "addr:full":"3 Dunbar St Silverdale NSW 2752",
    "addr:housenumber":"3",
    "addr:postcode":"2752",
    "addr:street":"Dunbar St",
    "iso:country":"AU",
    "sg:address":"3 Dunbar St",
    "sg:city":"Silverdale",
    "sg:classifiers":[
        {
            "category":"Utilities",
            "type":"Services"
        }
    ],
    "sg:phone":"+61 2 4774 0180",
    "sg:postcode":"2752",
    "sg:province":"NSW",
    "sg:tags":[
        "refrigeration",
        "industrial",
        "commercial",
        "retail"
    ],
    "wof:name":"Senses Refrigeration and Air Conditioning Pty Ltd",
    "wof:placetype":"venue"
},
  "geometry": {"coordinates":[150.60943603499999,-33.9082870483],"type":"Point"}
}