{
  "type": "Feature",
  "properties": {
    "iso:country":"AU",
    "sg:address":"15 Brookes St",
    "sg:city":"Thornleigh",
    "sg:classifiers":[
        {
            "category":"Utilities",
            "subcategory":"Electric",
            "type":"Services"
        }
    ],
    "sg:phone":"+61 2 9651 3663",
    "sg:postcode":"2120",
    "sg:province":"NSW",
    "sg:tags":[
        "electrical",
        "contractor"
    ],
    "wof:name":"TN Electrical Pty Ltd",
    "wof:placetype":"venue"
},
  "geometry": {"coordinates":[151.088546753,-33.7171211243],"type":"Point"}
}