{
  "type": "Feature",
  "properties": {
    "iso:country":"AU",
    "sg:address":"47 York St",
    "sg:city":"Sydney",
    "sg:classifiers":[
        {
            "category":"Health Services",
            "subcategory":"Health Practitioner",
            "type":"Services"
        }
    ],
    "sg:phone":"+61 2 9262 4955",
    "sg:postcode":"2000",
    "sg:province":"NSW",
    "sg:tags":[
        "osteopath"
    ],
    "wof:name":"City Health Osteopath",
    "wof:placetype":"venue"
},
  "geometry": {"coordinates":[151.205688477,-33.8668670654],"type":"Point"}
}