{
  "type": "Feature",
  "properties": {
    "iso:country":"AU",
    "sg:address":"Shop 5 718C Burwood Hwy",
    "sg:city":"Ferntree Gully",
    "sg:classifiers":[
        {
            "category":"Fast Food",
            "type":"Food & Drink"
        }
    ],
    "sg:phone":"+61 3 9758 3268",
    "sg:postcode":"3156",
    "sg:province":"VIC",
    "sg:tags":[
        "away",
        "take"
    ],
    "wof:name":"House Of Lee Take Away",
    "wof:placetype":"venue"
},
  "geometry": {"coordinates":[145.30081176799999,-37.8911094666],"type":"Point"}
}