{
  "type": "Feature",
  "properties": {
    "addr:full":"5 Melbourne St Rocklea QLD 4106",
    "addr:housenumber":"5",
    "addr:postcode":"4106",
    "addr:street":"Melbourne St",
    "iso:country":"AU",
    "sg:address":"5 Melbourne St",
    "sg:city":"Rocklea",
    "sg:classifiers":[
        {
            "category":"Food & Beverages",
            "subcategory":"Fruits & Vegetables",
            "type":"Retail Goods"
        }
    ],
    "sg:phone":"+61 7 3217 1076",
    "sg:postcode":"4106",
    "sg:province":"QLD",
    "sg:tags":[
        "greengrocer",
        "fruiterer"
    ],
    "wof:name":"Ciobo Produce",
    "wof:placetype":"venue"
},
  "geometry": {"coordinates":[153.008346558,-27.5410366058],"type":"Point"}
}