{
  "type": "Feature",
  "properties": {
    "iso:country":"AU",
    "sg:address":"Ground Flr/ 318- 320 Burns Bay Rd",
    "sg:city":"Lane Cove",
    "sg:classifiers":[
        {
            "category":"Organizations",
            "subcategory":"Professional Association",
            "type":"Services"
        }
    ],
    "sg:phone":"+61 2 9428 6100",
    "sg:postcode":"2066",
    "sg:province":"NSW",
    "sg:tags":[
        "rural",
        "organisation",
        "production",
        "primary"
    ],
    "wof:name":"Australian Wool Exchange Limited",
    "wof:placetype":"venue"
},
  "geometry": {"coordinates":[151.14996337900001,-33.8214950562],"type":"Point"}
}