{
  "type": "Feature",
  "properties": {
    "addr:full":"13 Lachlan St Liverpool NSW 2170",
    "addr:housenumber":"13",
    "addr:postcode":"2170",
    "addr:street":"Lachlan St",
    "iso:country":"AU",
    "sg:address":"13 Lachlan St",
    "sg:city":"Liverpool",
    "sg:classifiers":[
        {
            "category":"Health Services",
            "subcategory":"Doctor",
            "type":"Services"
        }
    ],
    "sg:phone":"+61 2 9602 2488",
    "sg:postcode":"2170",
    "sg:province":"NSW",
    "sg:tags":[
        "medical",
        "practitioner"
    ],
    "wof:name":"Bakhit Dr Nader",
    "wof:placetype":"venue"
},
  "geometry": {"coordinates":[150.93063354500001,-33.9161071777],"type":"Point"}
}