{
  "type": "Feature",
  "properties": {
    "iso:country":"AU",
    "sg:address":"253 Camberwell Rd",
    "sg:city":"Camberwell",
    "sg:classifiers":[
        {
            "category":"Retail",
            "subcategory":"Repair Shop",
            "type":"Services"
        }
    ],
    "sg:phone":"+61 3 9882 7990",
    "sg:postcode":"3124",
    "sg:province":"VIC",
    "sg:tags":[
        "mending",
        "clothing",
        "alteration"
    ],
    "wof:name":"Giannopoulos The Gentleman's Tailor",
    "wof:placetype":"venue"
},
  "geometry": {"coordinates":[145.057174683,-37.8315124512],"type":"Point"}
}