{
  "type": "Feature",
  "properties": {
    "iso:country":"AU",
    "sg:address":"903 Botany Rd",
    "sg:city":"Rosebery",
    "sg:classifiers":[
        {
            "category":"Professional",
            "subcategory":"Computer Services",
            "type":"Services"
        }
    ],
    "sg:phone":"+61 2 9667 2004",
    "sg:postcode":"2018",
    "sg:province":"NSW",
    "sg:tags":[
        "consultant",
        "system"
    ],
    "wof:name":"Ecomm IT Consultants Pty Ltd",
    "wof:placetype":"venue"
},
  "geometry": {"coordinates":[151.19639587399999,-33.9219169617],"type":"Point"}
}