{
  "type": "Feature",
  "properties": {
    "addr:full":"529 Middleborough Rd Box Hill North VIC 3129",
    "addr:housenumber":"529",
    "addr:postcode":"3129",
    "addr:street":"Middleborough Rd",
    "iso:country":"AU",
    "sg:address":"529 Middleborough Rd",
    "sg:city":"Box Hill North",
    "sg:classifiers":[
        {
            "category":"Food & Beverages",
            "subcategory":"Bakery",
            "type":"Retail Goods"
        }
    ],
    "sg:phone":"+61 3 9898 8128",
    "sg:postcode":"3129",
    "sg:province":"VIC",
    "sg:tags":[
        "baker"
    ],
    "wof:name":"Kerrimuir Bakery",
    "wof:placetype":"venue"
},
  "geometry": {"coordinates":[145.14027404800001,-37.8084869385],"type":"Point"}
}