{
  "type": "Feature",
  "properties": {
    "addr:full":"111 Eyles Drv East Ballina NSW 2478",
    "addr:housenumber":"111",
    "addr:postcode":"2478",
    "addr:street":"Eyles Drv",
    "iso:country":"AU",
    "sg:address":"111 Eyles Drv",
    "sg:city":"East Ballina",
    "sg:classifiers":[
        {
            "category":"Building & Trades",
            "subcategory":"Cleaning & Sanitation",
            "type":"Services"
        }
    ],
    "sg:phone":"+61 2 6686 4710",
    "sg:postcode":"2478",
    "sg:province":"NSW",
    "sg:tags":[
        "window"
    ],
    "wof:name":"Allan Masters",
    "wof:placetype":"venue"
},
  "geometry": {"coordinates":[153.58076477,-28.8504772186],"type":"Point"}
}