{
  "type": "Feature",
  "properties": {
    "iso:country":"AU",
    "sg:address":"Blake St",
    "sg:city":"Ararat",
    "sg:classifiers":[
        {
            "category":"Professional",
            "subcategory":"Engineering",
            "type":"Services"
        }
    ],
    "sg:phone":"+61 3 5352 2151",
    "sg:postcode":"3377",
    "sg:province":"VIC",
    "sg:tags":[
        "manufacturing",
        "engineer"
    ],
    "wof:name":"A.F. Gason Pty Ltd",
    "wof:placetype":"venue"
},
  "geometry": {"coordinates":[142.936569214,-37.2735214233],"type":"Point"}
}