{
  "type": "Feature",
  "properties": {
    "addr:full":"2 William St Brookvale NSW 2100",
    "addr:housenumber":"2",
    "addr:postcode":"2100",
    "addr:street":"William St",
    "iso:country":"AU",
    "sg:address":"2 William St",
    "sg:city":"Brookvale",
    "sg:classifiers":[
        {
            "category":"Shopping",
            "subcategory":"Party Supplies",
            "type":"Retail Goods"
        }
    ],
    "sg:phone":"+61 2 9905 9945",
    "sg:postcode":"2100",
    "sg:province":"NSW",
    "sg:tags":[
        "hire",
        "costume"
    ],
    "wof:name":"Mischief Costume Hire",
    "wof:placetype":"venue"
},
  "geometry": {"coordinates":[151.26838684099999,-33.7679634094],"type":"Point"}
}