{
  "type": "Feature",
  "properties": {
    "addr:full":"16 Jusfrute Drv Gosford West NSW 2250",
    "addr:housenumber":"16",
    "addr:postcode":"2250",
    "addr:street":"Jusfrute Drv",
    "iso:country":"AU",
    "sg:address":"16 Jusfrute Drv",
    "sg:city":"Gosford West",
    "sg:classifiers":[
        {
            "category":"Shopping",
            "subcategory":"Antiques",
            "type":"Retail Goods"
        }
    ],
    "sg:phone":"+61 2 4323 9512",
    "sg:postcode":"2250",
    "sg:province":"NSW",
    "wof:name":"Remember When Antiques & Collectables",
    "wof:placetype":"venue"
},
  "geometry": {"coordinates":[151.312591553,-33.4278869629],"type":"Point"}
}