{
  "type": "Feature",
  "properties": {
    "addr:full":"Schwab Rd Yenda NSW 2681",
    "addr:postcode":"2681",
    "addr:street":"Schwab Rd",
    "iso:country":"AU",
    "sg:address":"Schwab Rd",
    "sg:city":"Yenda",
    "sg:classifiers":[
        {
            "category":"Farming",
            "subcategory":"Farm & Veterinary Services",
            "type":"Manufacturing & Wholesale Goods"
        }
    ],
    "sg:phone":"+61 2 6968 1466",
    "sg:postcode":"2681",
    "sg:province":"NSW",
    "sg:tags":[
        "contracting"
    ],
    "wof:name":"Gooda J C & V M",
    "wof:placetype":"venue"
},
  "geometry": {"coordinates":[146.18907200000001,-34.243065],"type":"Point"}
}