{
  "type": "Feature",
  "properties": {
    "iso:country":"AU",
    "sg:address":"2- 4 Chapman St",
    "sg:city":"Fairy Meadow",
    "sg:classifiers":[
        {
            "category":"Manufacturing",
            "subcategory":"Metals",
            "type":"Manufacturing & Wholesale Goods"
        }
    ],
    "sg:phone":"+61 2 4285 2722",
    "sg:postcode":"2519",
    "sg:province":"NSW",
    "sg:tags":[
        "steel",
        "tube"
    ],
    "wof:name":"Rapid Exhaust Systems",
    "wof:placetype":"venue"
},
  "geometry": {"coordinates":[150.89859,-34.387466],"type":"Point"}
}