{
  "type": "Feature",
  "properties": {
    "iso:country":"AU",
    "sg:address":"120a Eagle St",
    "sg:city":"Longreach",
    "sg:classifiers":[
        {
            "category":"Personal",
            "subcategory":"Beauty Salon",
            "type":"Services"
        }
    ],
    "sg:phone":"+61 7 4658 2492",
    "sg:postcode":"4730",
    "sg:province":"QLD",
    "sg:tags":[
        "hairdresser"
    ],
    "wof:name":"Studio Exclusive",
    "wof:placetype":"venue"
},
  "geometry": {"coordinates":[144.24865700000001,-23.442806],"type":"Point"}
}