{
  "type": "Feature",
  "properties": {
    "addr:full":"310 Bayswater Rd Garbutt QLD 4814",
    "addr:housenumber":"310",
    "addr:postcode":"4814",
    "addr:street":"Bayswater Rd",
    "iso:country":"AU",
    "sg:address":"310 Bayswater Rd",
    "sg:city":"Garbutt",
    "sg:classifiers":[
        {
            "category":"Food & Beverages",
            "subcategory":"Liquor & Beverages",
            "type":"Retail Goods"
        }
    ],
    "sg:phone":"+61 7 4779 6344",
    "sg:postcode":"4814",
    "sg:province":"QLD",
    "sg:tags":[
        "store"
    ],
    "wof:name":"BWS Liquor Stores",
    "wof:placetype":"venue"
},
  "geometry": {"coordinates":[146.76634200000001,-19.27376],"type":"Point"}
}