{
  "type": "Feature",
  "properties": {
    "iso:country":"AU",
    "sg:address":"4 Barker Ave",
    "sg:city":"Como",
    "sg:classifiers":[
        {
            "category":"Health Services",
            "subcategory":"Dentist",
            "type":"Services"
        }
    ],
    "sg:phone":"+61 8 9368 6288",
    "sg:postcode":"6152",
    "sg:province":"WA",
    "wof:name":"Lifetime Dental Care",
    "wof:placetype":"venue"
},
  "geometry": {"coordinates":[115.864998,-31.996941],"type":"Point"}
}