{
  "type": "Feature",
  "properties": {
    "addr:full":"U1/ 12a Freight Drv Somerton VIC 3062",
    "addr:housenumber":"12a",
    "addr:postcode":"3062",
    "addr:street":"U1 /;Freight Drv",
    "iso:country":"AU",
    "sg:address":"U1/ 12a Freight Drv",
    "sg:city":"Somerton",
    "sg:classifiers":[
        {
            "category":"Retail",
            "subcategory":"Auto Repair",
            "type":"Services"
        }
    ],
    "sg:phone":"+61 3 8339 0636",
    "sg:postcode":"3062",
    "sg:province":"VIC",
    "sg:tags":[
        "repairer",
        "motor",
        "engineer"
    ],
    "wof:name":"Motorcraft Automotive",
    "wof:placetype":"venue"
},
  "geometry": {"coordinates":[144.96380615199999,-37.6441307068],"type":"Point"}
}