{
  "type": "Feature",
  "properties": {
    "addr:full":"1/ 40 Terrence Rd Brendale QLD 4500",
    "addr:housenumber":"/ 40",
    "addr:postcode":"4500",
    "addr:street":"Terrence Rd",
    "iso:country":"AU",
    "sg:address":"1/ 40 Terrence Rd",
    "sg:city":"Brendale",
    "sg:classifiers":[
        {
            "category":"Donuts",
            "subcategory":"None",
            "type":"Food & Drink"
        }
    ],
    "sg:phone":"+61 7 3881 1339",
    "sg:postcode":"4500",
    "sg:province":"QLD",
    "sg:tags":[
        "die",
        "engraver",
        "sinker"
    ],
    "wof:name":"Bunya Signs",
    "wof:placetype":"venue"
},
  "geometry": {"coordinates":[152.98088073700001,-27.3200359344],"type":"Point"}
}