{
  "type": "Feature",
  "properties": {
    "addr:full":"Dunearn Rd Dandenong North VIC 3175",
    "addr:postcode":"3175",
    "addr:street":"Dunearn Rd",
    "iso:country":"AU",
    "sg:address":"Dunearn Rd",
    "sg:city":"Dandenong North",
    "sg:classifiers":[
        {
            "category":"Professional",
            "subcategory":"Printing & Photocopies",
            "type":"Services"
        }
    ],
    "sg:phone":"+61 3 9701 3613",
    "sg:postcode":"3175",
    "sg:province":"VIC",
    "sg:tags":[
        "trophy"
    ],
    "wof:name":"Henwood Trophy Centre",
    "wof:placetype":"venue"
},
  "geometry": {"coordinates":[145.202636719,-37.9668464661],"type":"Point"}
}