{
  "type": "Feature",
  "properties": {
    "addr:full":"Coastwatcher Shopping Centre, Trinity Beach Rd Trinity Beach QLD 4879",
    "addr:postcode":"4879",
    "addr:street":"Trinity Beach Rd",
    "iso:country":"AU",
    "sg:address":"Coastwatcher Shopping Centre, Trinity Beach Rd",
    "sg:city":"Trinity Beach",
    "sg:classifiers":[
        {
            "category":"Real Estate",
            "subcategory":"Real Estate Agent",
            "type":"Services"
        }
    ],
    "sg:phone":"+61 7 4057 9111",
    "sg:postcode":"4879",
    "sg:province":"QLD",
    "wof:name":"Ray White Cairns Beaches",
    "wof:placetype":"venue"
},
  "geometry": {"coordinates":[145.699127197,-16.7855091095],"type":"Point"}
}