{
  "type": "Feature",
  "properties": {
    "addr:full":"74 Stanley St Sydney NSW 2000",
    "addr:housenumber":"74",
    "addr:postcode":"2000",
    "addr:street":"Stanley St",
    "iso:country":"AU",
    "sg:address":"74 Stanley St",
    "sg:city":"Sydney",
    "sg:classifiers":[
        {
            "category":"Restaurant",
            "type":"Food & Drink"
        }
    ],
    "sg:phone":"+61 2 9360 4702",
    "sg:postcode":"2000",
    "sg:province":"NSW",
    "wof:name":"Bill & Toni Italian Restaurant",
    "wof:placetype":"venue"
},
  "geometry": {"coordinates":[151.215499878,-33.875667572],"type":"Point"}
}