{
  "type": "Feature",
  "properties": {
    "addr:full":"15 Dadchick Drv Burleigh Waters QLD 4220",
    "addr:housenumber":"15",
    "addr:postcode":"4220",
    "addr:street":"Dadchick Drv",
    "iso:country":"AU",
    "sg:address":"15 Dadchick Drv",
    "sg:city":"Burleigh Waters",
    "sg:classifiers":[
        {
            "category":"Building & Trades",
            "subcategory":"Cleaning & Sanitation",
            "type":"Services"
        }
    ],
    "sg:phone":"+61 7 5576 4864",
    "sg:postcode":"4220",
    "sg:province":"QLD",
    "sg:tags":[
        "chemical",
        "pressure",
        "steam",
        "contractor"
    ],
    "wof:name":"A Aarons Roof Repairs",
    "wof:placetype":"venue"
},
  "geometry": {"coordinates":[153.43966674800001,-28.0907783508],"type":"Point"}
}