{
  "type": "Feature",
  "properties": {
    "addr:full":"34 Fourth St Minlaton SA 5575",
    "addr:housenumber":"34",
    "addr:postcode":"5575",
    "addr:street":"Fourth St",
    "iso:country":"AU",
    "sg:address":"34 Fourth St",
    "sg:city":"Minlaton",
    "sg:classifiers":[
        {
            "category":"Building & Trades",
            "subcategory":"Cleaning & Sanitation",
            "type":"Services"
        }
    ],
    "sg:phone":"+61 8 8853 2885",
    "sg:postcode":"5575",
    "sg:province":"SA",
    "sg:tags":[
        "tank",
        "septic"
    ],
    "wof:name":"Minlaton Septic Pumping Service",
    "wof:placetype":"venue"
},
  "geometry": {"coordinates":[137.59812927199999,-34.7718925476],"type":"Point"}
}