{
  "type": "Feature",
  "properties": {
    "addr:full":"Wolsten Holme Drv Sorell TAS 7172",
    "addr:postcode":"7172",
    "addr:street":"Holme Drv",
    "iso:country":"AU",
    "sg:address":"Wolsten Holme Drv",
    "sg:city":"Sorell",
    "sg:classifiers":[
        {
            "category":"Farming",
            "subcategory":"Nursery",
            "type":"Manufacturing & Wholesale Goods"
        }
    ],
    "sg:phone":"+61 3 6265 1886",
    "sg:postcode":"7172",
    "sg:province":"TAS",
    "wof:name":"Greenscapes",
    "wof:placetype":"venue"
},
  "geometry": {"coordinates":[147.54960632300001,-42.7805366516],"type":"Point"}
}