{
  "type": "Feature",
  "properties": {
    "addr:full":"Homer St Narrogin WA 6312",
    "addr:postcode":"6312",
    "addr:street":"Homer St",
    "iso:country":"AU",
    "sg:address":"Homer St",
    "sg:city":"Narrogin",
    "sg:classifiers":[
        {
            "category":"Education",
            "subcategory":"School",
            "type":"Public Place"
        }
    ],
    "sg:phone":"+61 8 9881 1581",
    "sg:postcode":"6312",
    "sg:province":"WA",
    "sg:tags":[
        "state",
        "except",
        "nsw"
    ],
    "wof:name":"East Narrogin Primary School",
    "wof:placetype":"venue"
},
  "geometry": {"coordinates":[117.18258667000001,-32.9363327026],"type":"Point"}
}