{
  "type": "Feature",
  "properties": {
    "addr:full":"63 Blaxland Rd Campbelltown NSW 2560",
    "addr:housenumber":"63",
    "addr:postcode":"2560",
    "addr:street":"Blaxland Rd",
    "iso:country":"AU",
    "sg:address":"63 Blaxland Rd",
    "sg:city":"Campbelltown",
    "sg:classifiers":[
        {
            "category":"Autos & Motor Vehicles",
            "subcategory":"Auto Supplies",
            "type":"Retail Goods"
        }
    ],
    "sg:phone":"+61 2 4627 7866",
    "sg:postcode":"2560",
    "sg:province":"NSW",
    "sg:tags":[
        "tyre"
    ],
    "wof:name":"Budget Wheels & Tyres",
    "wof:placetype":"venue"
},
  "geometry": {"coordinates":[150.810302734,-34.061542511],"type":"Point"}
}