{
  "type": "Feature",
  "properties": {
    "addr:full":"24 Hugh Ryan Drv Garbutt QLD 4814",
    "addr:housenumber":"24",
    "addr:postcode":"4814",
    "addr:street":"Hugh Ryan Drv",
    "iso:country":"AU",
    "sg:address":"24 Hugh Ryan Drv",
    "sg:city":"Garbutt",
    "sg:classifiers":[
        {
            "category":"Freight",
            "type":"Transportation"
        }
    ],
    "sg:phone":"+61 13 15 31",
    "sg:postcode":"4814",
    "sg:province":"QLD",
    "sg:tags":[
        "light",
        "carrier"
    ],
    "wof:name":"Wards Skyroad",
    "wof:placetype":"venue"
},
  "geometry": {"coordinates":[146.76391599999999,-19.27162],"type":"Point"}
}