{
  "type": "Feature",
  "properties": {
    "iso:country":"AU",
    "sg:address":"57B Eighth Ave",
    "sg:city":"Maylands",
    "sg:classifiers":[
        {
            "category":"Personal",
            "subcategory":"Beauty Salon",
            "type":"Services"
        }
    ],
    "sg:phone":"+61 8 9272 2132",
    "sg:postcode":"6051",
    "sg:province":"WA",
    "sg:tags":[
        "hairdresser"
    ],
    "wof:name":"Flair Today Hair And Beauty",
    "wof:placetype":"venue"
},
  "geometry": {"coordinates":[115.892723,-31.929548],"type":"Point"}
}