{
  "type": "Feature",
  "properties": {
    "addr:full":"214 Quay St Rockhampton QLD 4700",
    "addr:housenumber":"214",
    "addr:postcode":"4700",
    "addr:street":"Quay St",
    "iso:country":"AU",
    "sg:address":"214 Quay St",
    "sg:city":"Rockhampton",
    "sg:classifiers":[
        {
            "category":"Professional",
            "subcategory":"Business Services",
            "type":"Services"
        }
    ],
    "sg:phone":"+61 7 4922 6906",
    "sg:postcode":"4700",
    "sg:province":"QLD",
    "sg:tags":[
        "small",
        "advisory"
    ],
    "wof:name":"Rockhampton Enterprise Centre Inc",
    "wof:placetype":"venue"
},
  "geometry": {"coordinates":[150.52520751899999,-23.3921394348],"type":"Point"}
}