{
  "type": "Feature",
  "properties": {
    "addr:full":"33 Hansen Rd Boronia VIC 3155",
    "addr:housenumber":"33",
    "addr:postcode":"3155",
    "addr:street":"Hansen Rd",
    "iso:country":"AU",
    "sg:address":"33 Hansen Rd",
    "sg:city":"Boronia",
    "sg:classifiers":[
        {
            "category":"Shopping",
            "subcategory":"Computers & Home Electronics",
            "type":"Retail Goods"
        }
    ],
    "sg:phone":"+61 3 9761 3719",
    "sg:postcode":"3155",
    "sg:province":"VIC",
    "sg:tags":[
        "equipment",
        "multimedia"
    ],
    "wof:name":"Media Guise",
    "wof:placetype":"venue"
},
  "geometry": {"coordinates":[145.300857544,-37.8642234802],"type":"Point"}
}