{
  "type": "Feature",
  "properties": {
    "addr:full":"25 Elizabeth St Campsie NSW 2194",
    "addr:housenumber":"25",
    "addr:postcode":"2194",
    "addr:street":"Elizabeth St",
    "iso:country":"AU",
    "sg:address":"25 Elizabeth St",
    "sg:city":"Campsie",
    "sg:classifiers":[
        {
            "category":"Professional",
            "subcategory":"Accounting & Tax Preparation",
            "type":"Services"
        }
    ],
    "sg:phone":"+61 2 9718 7677",
    "sg:postcode":"2194",
    "sg:province":"NSW",
    "sg:tags":[
        "broom",
        "brush"
    ],
    "wof:name":"P.F. Brady Pty. Ltd.",
    "wof:placetype":"venue"
},
  "geometry": {"coordinates":[151.100662,-33.92408],"type":"Point"}
}