{
  "type": "Feature",
  "properties": {
    "addr:full":"Spring Creek Drv Dalby QLD 4405",
    "addr:postcode":"4405",
    "addr:street":"Spring Creek Drv",
    "iso:country":"AU",
    "sg:address":"Spring Creek Drv",
    "sg:city":"Dalby",
    "sg:classifiers":[
        {
            "category":"Home & Garden",
            "subcategory":"Household Appliances",
            "type":"Retail Goods"
        }
    ],
    "sg:phone":"+61 7 4662 3661",
    "sg:postcode":"4405",
    "sg:province":"QLD",
    "sg:tags":[
        "equipment",
        "gas"
    ],
    "wof:name":"Milford P.M.(Peter) & C F",
    "wof:placetype":"venue"
},
  "geometry": {"coordinates":[151.23562622099999,-27.1757621765],"type":"Point"}
}