{
  "type": "Feature",
  "properties": {
    "iso:country":"AU",
    "sg:address":"315 Mimosa Rd",
    "sg:city":"Greenfield Park",
    "sg:classifiers":[
        {
            "category":"Autos & Motor Vehicles",
            "subcategory":"Auto Supplies",
            "type":"Retail Goods"
        }
    ],
    "sg:phone":"+61 2 9823 8090",
    "sg:postcode":"2176",
    "sg:province":"NSW",
    "sg:tags":[
        "automotive",
        "stereo",
        "radio"
    ],
    "wof:name":"Simply Electronics",
    "wof:placetype":"venue"
},
  "geometry": {"coordinates":[150.89295959500001,-33.8774833679],"type":"Point"}
}