{
  "type": "Feature",
  "properties": {
    "addr:full":"PO Box 232N Cairns North QLD 4870",
    "addr:postcode":"4870",
    "iso:country":"AU",
    "sg:address":"PO Box 232N",
    "sg:city":"Cairns North",
    "sg:classifiers":[
        {
            "category":"Cafe",
            "type":"Food & Drink"
        }
    ],
    "sg:phone":"+61 7 4051 9565",
    "sg:postcode":"4870",
    "sg:province":"QLD",
    "wof:name":"The Lillipad Cafe",
    "wof:placetype":"venue"
},
  "geometry": {"coordinates":[145.759002686,-16.9041805267],"type":"Point"}
}