{
  "type": "Feature",
  "properties": {
    "addr:full":"8 Newport Drv Scarborough QLD 4020",
    "addr:housenumber":"8",
    "addr:postcode":"4020",
    "addr:street":"Newport Drv",
    "iso:country":"AU",
    "sg:address":"8 Newport Drv",
    "sg:city":"Scarborough",
    "sg:classifiers":[
        {
            "category":"Military Area",
            "subcategory":"Air Force Base",
            "type":"Public Place"
        }
    ],
    "sg:phone":"+61 3 9729 9777",
    "sg:postcode":"4020",
    "sg:province":"QLD",
    "sg:tags":[
        "wholesaler",
        "bag",
        "mfrs",
        "sack"
    ],
    "wof:name":"Bulk Handling Australia Pty Ltd",
    "wof:placetype":"venue"
},
  "geometry": {"coordinates":[153.10063199999999,-27.20701],"type":"Point"}
}