{
  "type": "Feature",
  "properties": {
    "addr:full":"10 Northern Rd Heidelberg West VIC 3081",
    "addr:housenumber":"10",
    "addr:postcode":"3081",
    "addr:street":"Northern Rd",
    "iso:country":"AU",
    "sg:address":"10 Northern Rd",
    "sg:city":"Heidelberg West",
    "sg:classifiers":[
        {
            "category":"Banks & Credit Unions",
            "subcategory":"Financial Services",
            "type":"Services"
        }
    ],
    "sg:phone":"+61 3 9457 6066",
    "sg:postcode":"3081",
    "sg:province":"VIC",
    "sg:tags":[
        "equipment",
        "chain"
    ],
    "wof:name":"Davo Chains",
    "wof:placetype":"venue"
},
  "geometry": {"coordinates":[145.044845581,-37.7291297913],"type":"Point"}
}