{
  "type": "Feature",
  "properties": {
    "addr:full":"266 Victoria St Wetherill Park NSW 2164",
    "addr:housenumber":"266",
    "addr:postcode":"2164",
    "addr:street":"Victoria St",
    "iso:country":"AU",
    "sg:address":"266 Victoria St",
    "sg:city":"Wetherill Park",
    "sg:classifiers":[
        {
            "category":"Autos & Motor Vehicles",
            "subcategory":"Automobile Sales",
            "type":"Retail Goods"
        }
    ],
    "sg:phone":"+61 2 9828 9122",
    "sg:postcode":"2164",
    "sg:province":"NSW",
    "sg:tags":[
        "car",
        "new"
    ],
    "wof:name":"Subaru Vehicle Storage & Distribution",
    "wof:placetype":"venue"
},
  "geometry": {"coordinates":[150.90403747600001,-33.8458023071],"type":"Point"}
}