{
  "type": "Feature",
  "properties": {
    "iso:country":"AU",
    "sg:address":"61 Buddock St",
    "sg:city":"Belgian Gardens",
    "sg:classifiers":[
        {
            "category":"Government",
            "subcategory":"Court House",
            "type":"Public Place"
        }
    ],
    "sg:phone":"+61 415 989 896",
    "sg:postcode":"4810",
    "sg:province":"QLD",
    "sg:tags":[
        "personal",
        "marriage",
        "family",
        "counselling"
    ],
    "wof:name":"Interactive Solutions",
    "wof:placetype":"venue"
},
  "geometry": {"coordinates":[146.794464,-19.245872],"type":"Point"}
}