{
  "type": "Feature",
  "properties": {
    "addr:full":"Shop 6 Corner Karri St & Maltarra Rd Munno Para SA 5115",
    "addr:housenumber":"shop 6",
    "addr:postcode":"5115",
    "addr:street":"Corner Karri St & Maltarra Rd",
    "iso:country":"AU",
    "sg:address":"Shop 6 Corner Karri St & Maltarra Rd",
    "sg:city":"Munno Para",
    "sg:classifiers":[
        {
            "category":"Fast Food",
            "type":"Food & Drink"
        }
    ],
    "sg:phone":"+61 8 8254 6133",
    "sg:postcode":"5115",
    "sg:province":"SA",
    "sg:tags":[
        "away",
        "take"
    ],
    "wof:name":"Johnny's Dial A Pizza",
    "wof:placetype":"venue"
},
  "geometry": {"coordinates":[138.69859314000001,-34.6671829224],"type":"Point"}
}