{
  "type": "Feature",
  "properties": {
    "addr:full":"Shop 226, Lvl 2 Castle Towers Castle Hills Rd Castle Hill NSW 2154",
    "addr:postcode":"2154",
    "addr:street":"Castle Hills Rd",
    "iso:country":"AU",
    "sg:address":"Shop 226, Lvl 2 Castle Towers Castle Hills Rd",
    "sg:city":"Castle Hill",
    "sg:classifiers":[
        {
            "category":"Health Services",
            "subcategory":"Doctor",
            "type":"Services"
        }
    ],
    "sg:phone":"+61 2 9659 8820",
    "sg:postcode":"2154",
    "sg:province":"NSW",
    "sg:tags":[
        "medical",
        "practitioner"
    ],
    "wof:name":"Mirzadeh Jamileh Dr",
    "wof:placetype":"venue"
},
  "geometry": {"coordinates":[151.003814697,-33.7317695618],"type":"Point"}
}