{
  "type": "Feature",
  "properties": {
    "addr:full":"5 Dobney Ave Wagga Wagga NSW 2650",
    "addr:housenumber":"5",
    "addr:postcode":"2650",
    "addr:street":"Dobney Ave",
    "iso:country":"AU",
    "sg:address":"5 Dobney Ave",
    "sg:city":"Wagga Wagga",
    "sg:classifiers":[
        {
            "category":"Recreation",
            "subcategory":"Fishing",
            "type":"Entertainment"
        }
    ],
    "sg:phone":"+61 2 6922 6409",
    "sg:postcode":"2650",
    "sg:province":"NSW",
    "sg:tags":[
        "tackle"
    ],
    "wof:name":"Rods Custom Rods",
    "wof:placetype":"venue"
},
  "geometry": {"coordinates":[147.34913635300001,-35.1163864136],"type":"Point"}
}