{
  "type": "Feature",
  "properties": {
    "iso:country":"AU",
    "sg:address":"PO Box 243",
    "sg:city":"Keilor",
    "sg:classifiers":[
        {
            "category":"Home & Garden",
            "subcategory":"Garden Supply",
            "type":"Retail Goods"
        }
    ],
    "sg:phone":"+61 1300 792 508",
    "sg:postcode":"3036",
    "sg:province":"VIC",
    "sg:tags":[
        "turf",
        "lawn"
    ],
    "wof:name":"It's Grass Pty Ltd",
    "wof:placetype":"venue"
},
  "geometry": {"coordinates":[144.830963,-37.717381],"type":"Point"}
}