{
  "type": "Feature",
  "properties": {
    "addr:full":"83 Ontario Ave Mildura VIC 3500",
    "addr:housenumber":"83",
    "addr:postcode":"3500",
    "addr:street":"Ontario Ave",
    "iso:country":"AU",
    "sg:address":"83 Ontario Ave",
    "sg:city":"Mildura",
    "sg:classifiers":[
        {
            "category":"Fast Food",
            "type":"Food & Drink"
        }
    ],
    "sg:phone":"+61 3 5023 3305",
    "sg:postcode":"3500",
    "sg:province":"VIC",
    "sg:tags":[
        "away",
        "take"
    ],
    "wof:name":"Ontario Ave General Store",
    "wof:placetype":"venue"
},
  "geometry": {"coordinates":[142.15252685600001,-34.176815033],"type":"Point"}
}