{
  "type": "Feature",
  "properties": {
    "iso:country":"AU",
    "sg:address":"22 Rowley St",
    "sg:city":"Camperdown",
    "sg:classifiers":[
        {
            "category":"Professional",
            "subcategory":"Computer Services",
            "type":"Services"
        }
    ],
    "sg:phone":"+61 2 9557 1908",
    "sg:postcode":"2050",
    "sg:province":"NSW",
    "sg:tags":[
        "consultant",
        "system"
    ],
    "wof:name":"Mechtron Systems",
    "wof:placetype":"venue"
},
  "geometry": {"coordinates":[151.173416,-33.893215],"type":"Point"}
}