{
  "type": "Feature",
  "properties": {
    "addr:full":"55 Buckingham Ave Springvale VIC 3171",
    "addr:housenumber":"55",
    "addr:postcode":"3171",
    "addr:street":"Buckingham Ave",
    "iso:country":"AU",
    "sg:address":"55 Buckingham Ave",
    "sg:city":"Springvale",
    "sg:classifiers":[
        {
            "category":"Health Services",
            "subcategory":"Dentist",
            "type":"Services"
        }
    ],
    "sg:phone":"+61 1300 360 054",
    "sg:postcode":"3171",
    "sg:province":"VIC",
    "wof:name":"School Dental Service",
    "wof:placetype":"venue"
},
  "geometry": {"coordinates":[145.150787353,-37.9538383484],"type":"Point"}
}