{
  "type": "Feature",
  "properties": {
    "addr:full":"200 Richmond Rd Richmond SA 5033",
    "addr:housenumber":"200",
    "addr:postcode":"5033",
    "addr:street":"Richmond Rd",
    "iso:country":"AU",
    "sg:address":"200 Richmond Rd",
    "sg:city":"Richmond",
    "sg:classifiers":[
        {
            "category":"Retail",
            "subcategory":"Self-service Laundry",
            "type":"Services"
        }
    ],
    "sg:phone":"+61 439 368 119",
    "sg:postcode":"5033",
    "sg:province":"SA",
    "wof:name":"Adelaide Welcome Wash",
    "wof:placetype":"venue"
},
  "geometry": {"coordinates":[138.562942505,-34.9426383972],"type":"Point"}
}