{
  "type": "Feature",
  "properties": {
    "iso:country":"AU",
    "sg:address":"Cnr Rowellyn Ave & Earnshaw St",
    "sg:city":"Carrum Downs",
    "sg:classifiers":[
        {
            "category":"Food & Beverages",
            "subcategory":"Groceries & Convenience Stores",
            "type":"Retail Goods"
        }
    ],
    "sg:phone":"+61 3 9782 1004",
    "sg:postcode":"3201",
    "sg:province":"VIC",
    "wof:name":"Rowellyn Convenience Store",
    "wof:placetype":"venue"
},
  "geometry": {"coordinates":[145.193192,-38.106167],"type":"Point"}
}