{
  "type": "Feature",
  "properties": {
    "addr:full":"21 Colray Ave Osborne Park WA 6017",
    "addr:housenumber":"21",
    "addr:postcode":"6017",
    "addr:street":"Colray Ave",
    "iso:country":"AU",
    "sg:address":"21 Colray Ave",
    "sg:city":"Osborne Park",
    "sg:classifiers":[
        {
            "category":"Building & Trades",
            "subcategory":"Construction",
            "type":"Services"
        }
    ],
    "sg:phone":"+61 8 9443 5774",
    "sg:postcode":"6017",
    "sg:province":"WA",
    "sg:tags":[
        "contractor"
    ],
    "wof:name":"Central Building & Maintenance Pty Ltd",
    "wof:placetype":"venue"
},
  "geometry": {"coordinates":[115.818557739,-31.9085578918],"type":"Point"}
}