{
  "type": "Feature",
  "properties": {
    "iso:country":"AU",
    "sg:address":"Shop R33 Woodgrove Shopping Centre 553-555 High St",
    "sg:city":"Melton",
    "sg:classifiers":[
        {
            "category":"Communications",
            "subcategory":"Film & Video Production",
            "type":"Services"
        }
    ],
    "sg:phone":"+61 3 9747 3577",
    "sg:postcode":"3337",
    "sg:province":"VIC",
    "sg:tags":[
        "dvd",
        "library"
    ],
    "wof:name":"Video Busters",
    "wof:placetype":"venue"
},
  "geometry": {"coordinates":[144.56102000000001,-37.684948],"type":"Point"}
}