{
  "type": "Feature",
  "properties": {
    "addr:full":"Units A & B, 44 Hunter St Riverstone NSW 2765",
    "addr:housenumber":"44",
    "addr:postcode":"2765",
    "addr:street":"Hunter St",
    "iso:country":"AU",
    "sg:address":"Units A & B, 44 Hunter St",
    "sg:city":"Riverstone",
    "sg:classifiers":[
        {
            "category":"Landmark",
            "subcategory":"Scenic View",
            "type":"Public Place"
        }
    ],
    "sg:phone":"+61 2 9627 4543",
    "sg:postcode":"2765",
    "sg:province":"NSW",
    "sg:tags":[
        "staircase",
        "handrail"
    ],
    "wof:name":"A Cut Price Stair Pty Ltd",
    "wof:placetype":"venue"
},
  "geometry": {"coordinates":[150.86422729500001,-33.6816864014],"type":"Point"}
}