{
  "type": "Feature",
  "properties": {
    "addr:full":"Suite 142/ 1 Queens Rd Melbourne VIC 3004",
    "addr:housenumber":"/ 1",
    "addr:postcode":"3004",
    "addr:street":"Queens Rd",
    "iso:country":"AU",
    "sg:address":"Suite 142/ 1 Queens Rd",
    "sg:city":"Melbourne",
    "sg:classifiers":[
        {
            "category":"Sports & Exercise",
            "subcategory":"Gym",
            "type":"Entertainment"
        }
    ],
    "sg:phone":"+61 1300 137 422",
    "sg:postcode":"3004",
    "sg:province":"VIC",
    "sg:tags":[
        "personal",
        "trainer",
        "fitness"
    ],
    "sg:website":"http://www.trewhealth.com.au",
    "wof:name":"Trewhealth",
    "wof:placetype":"venue"
},
  "geometry": {"coordinates":[144.97369384800001,-37.8357315063],"type":"Point"}
}