{
  "type": "Feature",
  "properties": {
    "addr:full":"21 Mavis Rd Morayfield QLD 4506",
    "addr:housenumber":"21",
    "addr:postcode":"4506",
    "addr:street":"Mavis Rd",
    "iso:country":"AU",
    "sg:address":"21 Mavis Rd",
    "sg:city":"Morayfield",
    "sg:classifiers":[
        {
            "category":"Personal",
            "subcategory":"Beauty Salon",
            "type":"Services"
        }
    ],
    "sg:phone":"+61 414 335 014",
    "sg:postcode":"4506",
    "sg:province":"QLD",
    "wof:name":"Bella Una IPL Studio",
    "wof:placetype":"venue"
},
  "geometry": {"coordinates":[152.94349670400001,-27.1379699707],"type":"Point"}
}