{
  "type": "Feature",
  "properties": {
    "addr:full":"34 Burke St Victor Harbor SA 5211",
    "addr:housenumber":"34",
    "addr:postcode":"5211",
    "addr:street":"Burke St",
    "iso:country":"AU",
    "sg:address":"34 Burke St",
    "sg:city":"Victor Harbor",
    "sg:classifiers":[
        {
            "category":"Personal",
            "subcategory":"Beauty Salon",
            "type":"Services"
        }
    ],
    "sg:phone":"+61 8 8552 6008",
    "sg:postcode":"5211",
    "sg:province":"SA",
    "sg:tags":[
        "hairdresser"
    ],
    "wof:name":"Anna's Hair Connection",
    "wof:placetype":"venue"
},
  "geometry": {"coordinates":[138.61924743599999,-35.5555725098],"type":"Point"}
}