{
  "type": "Feature",
  "properties": {
    "addr:full":"10 Eastmead Rd Croydon VIC 3136",
    "addr:housenumber":"10",
    "addr:postcode":"3136",
    "addr:street":"Eastmead Rd",
    "iso:country":"AU",
    "sg:address":"10 Eastmead Rd",
    "sg:city":"Croydon",
    "sg:classifiers":[
        {
            "category":"Professional",
            "type":"Services"
        }
    ],
    "sg:phone":"+61 3 9733 2220",
    "sg:postcode":"3136",
    "sg:province":"VIC",
    "sg:tags":[
        "quality",
        "assurance"
    ],
    "wof:name":"Notewell Pty Ltd",
    "wof:placetype":"venue"
},
  "geometry": {"coordinates":[145.279754639,-37.7989196777],"type":"Point"}
}