{
  "type": "Feature",
  "properties": {
    "addr:full":"Cunningham Hwy Amberley QLD 4306",
    "addr:postcode":"4306",
    "addr:street":"Cunningham Hwy",
    "iso:country":"AU",
    "sg:address":"Cunningham Hwy",
    "sg:city":"Amberley",
    "sg:classifiers":[
        {
            "category":"Autos & Motor Vehicles",
            "subcategory":"Fuel & Gas Station",
            "type":"Retail Goods"
        }
    ],
    "sg:phone":"+61 7 5464 3222",
    "sg:postcode":"4306",
    "sg:province":"QLD",
    "wof:name":"Burmah Fuels (Queensland) Pty Limited",
    "wof:placetype":"venue"
},
  "geometry": {"coordinates":[152.70053100600001,-27.6578464508],"type":"Point"}
}