{
  "type": "Feature",
  "properties": {
    "iso:country":"AU",
    "sg:address":"221 Graham Rd",
    "sg:city":"Marom Creek",
    "sg:classifiers":[
        {
            "category":"Farming",
            "subcategory":"Farm & Veterinary Services",
            "type":"Manufacturing & Wholesale Goods"
        }
    ],
    "sg:phone":"+61 2 6629 8466",
    "sg:postcode":"2480",
    "sg:province":"NSW",
    "sg:tags":[
        "irrigation",
        "reticulation",
        "system"
    ],
    "wof:name":"Rainbeater Pty Ltd",
    "wof:placetype":"venue"
},
  "geometry": {"coordinates":[153.36253356899999,-28.8740272522],"type":"Point"}
}