{
  "type": "Feature",
  "properties": {
    "iso:country":"AU",
    "sg:address":"61 Merlin St",
    "sg:city":"The Oaks",
    "sg:classifiers":[
        {
            "category":"Building & Trades",
            "subcategory":"Construction",
            "type":"Services"
        }
    ],
    "sg:phone":"+61 427 706 266",
    "sg:postcode":"2570",
    "sg:province":"NSW",
    "sg:tags":[
        "fencing",
        "contractor"
    ],
    "wof:name":"Camden Rural Services",
    "wof:placetype":"venue"
},
  "geometry": {"coordinates":[150.57267761200001,-34.080165863],"type":"Point"}
}