{
  "type": "Feature",
  "properties": {
    "addr:full":"88 Main St Balhannah SA 5242",
    "addr:housenumber":"88",
    "addr:postcode":"5242",
    "addr:street":"Main St",
    "iso:country":"AU",
    "sg:address":"88 Main St",
    "sg:city":"Balhannah",
    "sg:classifiers":[
        {
            "category":"Health Services",
            "subcategory":"Dentist",
            "type":"Services"
        }
    ],
    "sg:phone":"+61 8 8388 4488",
    "sg:postcode":"5242",
    "sg:province":"SA",
    "wof:name":"Dr Ashleigh Thomson",
    "wof:placetype":"venue"
},
  "geometry": {"coordinates":[138.82699585,-34.9902992249],"type":"Point"}
}