{
  "type": "Feature",
  "properties": {
    "iso:country":"AU",
    "sg:address":"1343 Main South Rd",
    "sg:city":"Bedford Park",
    "sg:classifiers":[
        {
            "category":"Autos & Motor Vehicles",
            "subcategory":"Automobile Sales",
            "type":"Retail Goods"
        }
    ],
    "sg:phone":"+61 8 8357 5899",
    "sg:postcode":"5042",
    "sg:province":"SA",
    "sg:tags":[
        "car",
        "used"
    ],
    "wof:name":"T.T.C. Car sales (Traditional Transportation Company)",
    "wof:placetype":"venue"
},
  "geometry": {"coordinates":[138.57373,-35.013504],"type":"Point"}
}