{
  "type": "Feature",
  "properties": {
    "addr:full":"2 Kembla St Fyshwick ACT 2609",
    "addr:housenumber":"2",
    "addr:postcode":"2609",
    "addr:street":"Kembla St",
    "iso:country":"AU",
    "sg:address":"2 Kembla St",
    "sg:city":"Fyshwick",
    "sg:classifiers":[
        {
            "category":"Retail",
            "subcategory":"Auto Repair",
            "type":"Services"
        }
    ],
    "sg:phone":"+61 2 6221 5300",
    "sg:postcode":"2609",
    "sg:province":"ACT",
    "sg:tags":[
        "repairer",
        "motor",
        "engineer"
    ],
    "wof:name":"Capital Subaru",
    "wof:placetype":"venue"
},
  "geometry": {"coordinates":[149.179077148,-35.3255500793],"type":"Point"}
}