{
  "type": "Feature",
  "properties": {
    "addr:full":"11 Currie Rd Forestville NSW 2087",
    "addr:housenumber":"11",
    "addr:postcode":"2087",
    "addr:street":"Currie Rd",
    "iso:country":"AU",
    "sg:address":"11 Currie Rd",
    "sg:city":"Forestville",
    "sg:classifiers":[
        {
            "category":"Education",
            "subcategory":"School",
            "type":"Public Place"
        }
    ],
    "sg:phone":"+61 2 9972 7311",
    "sg:postcode":"2087",
    "sg:province":"NSW",
    "wof:name":"Our Lady of Good Counsel School",
    "wof:placetype":"venue"
},
  "geometry": {"coordinates":[151.22059631400001,-33.7596588135],"type":"Point"}
}