{
  "type": "Feature",
  "properties": {
    "addr:full":"893 A Riversdale Rd Camberwell VIC 3124",
    "addr:housenumber":"893",
    "addr:postcode":"3124",
    "addr:street":"A Riversdale Rd",
    "iso:country":"AU",
    "sg:address":"893 A Riversdale Rd",
    "sg:city":"Camberwell",
    "sg:classifiers":[
        {
            "category":"Health Services",
            "subcategory":"Dentist",
            "type":"Services"
        }
    ],
    "sg:phone":"+61 417 350 242",
    "sg:postcode":"3124",
    "sg:province":"VIC",
    "sg:tags":[
        "dental",
        "prosthetist"
    ],
    "wof:name":"Graeme Robertson",
    "wof:placetype":"venue"
},
  "geometry": {"coordinates":[145.07643127399999,-37.8336029053],"type":"Point"}
}