{
  "type": "Feature",
  "properties": {
    "addr:full":"PO Box 330 Taigum QLD 4018",
    "addr:postcode":"4018",
    "iso:country":"AU",
    "sg:address":"PO Box 330",
    "sg:city":"Taigum",
    "sg:classifiers":[
        {
            "category":"Professional",
            "subcategory":"Computer Services",
            "type":"Services"
        }
    ],
    "sg:phone":"+61 1800 225 142",
    "sg:postcode":"4018",
    "sg:province":"QLD",
    "sg:tags":[
        "training"
    ],
    "wof:name":"ACT Specialists",
    "wof:placetype":"venue"
},
  "geometry": {"coordinates":[153.04629499999999,-27.35043],"type":"Point"}
}