{
  "type": "Feature",
  "properties": {
    "iso:country":"AU",
    "sg:address":"154a Maine Rd",
    "sg:city":"Clontarf",
    "sg:classifiers":[
        {
            "category":"Health Services",
            "subcategory":"Health Practitioner",
            "type":"Services"
        }
    ],
    "sg:phone":"+61 7 3284 1058",
    "sg:postcode":"4019",
    "sg:province":"QLD",
    "sg:tags":[
        "pathologist",
        "speech"
    ],
    "wof:name":"Melinda Cassells",
    "wof:placetype":"venue"
},
  "geometry": {"coordinates":[153.095306397,-27.25248909],"type":"Point"}
}