{
  "type": "Feature",
  "properties": {
    "addr:full":"Cnr Hector St & Waldron Rd Sefton NSW 2162",
    "addr:postcode":"2162",
    "addr:street":"Cnr Hector St & Waldron Rd",
    "iso:country":"AU",
    "sg:address":"Cnr Hector St & Waldron Rd",
    "sg:city":"Sefton",
    "sg:classifiers":[
        {
            "category":"Autos & Motor Vehicles",
            "subcategory":"Fuel & Gas Station",
            "type":"Retail Goods"
        }
    ],
    "sg:phone":"+61 2 9644 4277",
    "sg:postcode":"2162",
    "sg:province":"NSW",
    "wof:name":"Caltex Ampol Service Station",
    "wof:placetype":"venue"
},
  "geometry": {"coordinates":[151.005691528,-33.8892822266],"type":"Point"}
}