{
  "type": "Feature",
  "properties": {
    "iso:country":"AU",
    "sg:address":"Ipswich Rd",
    "sg:city":"Wacol",
    "sg:classifiers":[
        {
            "category":"Professional",
            "type":"Services"
        }
    ],
    "sg:phone":"+61 402 186 963",
    "sg:postcode":"4076",
    "sg:province":"QLD",
    "sg:tags":[
        "transport"
    ],
    "wof:name":"Astek Transport & Cranes",
    "wof:placetype":"venue"
},
  "geometry": {"coordinates":[152.926635742,-27.5885372162],"type":"Point"}
}