{
  "type": "Feature",
  "properties": {
    "iso:country":"AU",
    "sg:address":"6 Ashley Pl",
    "sg:city":"Ridleyton",
    "sg:classifiers":[
        {
            "category":"Personal",
            "type":"Services"
        }
    ],
    "sg:phone":"+61 8 8411 0202",
    "sg:postcode":"5008",
    "sg:province":"SA",
    "sg:tags":[
        "reducing",
        "treatment",
        "weight"
    ],
    "wof:name":"Herbalife Australasia Pty Ltd",
    "wof:placetype":"venue"
},
  "geometry": {"coordinates":[138.57128900000001,-34.896152],"type":"Point"}
}