{
  "type": "Feature",
  "properties": {
    "iso:country":"AU",
    "sg:address":"Gate 16a Ross Smith Drv",
    "sg:city":"Mascot",
    "sg:classifiers":[
        {
            "category":"Professional",
            "subcategory":"Detective & Security Services",
            "type":"Services"
        }
    ],
    "sg:phone":"+61 1300 135 756",
    "sg:postcode":"2020",
    "sg:province":"NSW",
    "sg:tags":[
        "consultant",
        "system"
    ],
    "wof:name":"Shodan Security",
    "wof:placetype":"venue"
},
  "geometry": {"coordinates":[151.18775939899999,-33.9333152771],"type":"Point"}
}