{
  "type": "Feature",
  "properties": {
    "addr:full":"Unit C Day Ave Ashford SA 5035",
    "addr:postcode":"5035",
    "addr:street":"Day Ave",
    "iso:country":"AU",
    "sg:address":"Unit C Day Ave",
    "sg:city":"Ashford",
    "sg:classifiers":[
        {
            "category":"Shopping",
            "subcategory":"Crafts & Fabrics",
            "type":"Retail Goods"
        }
    ],
    "sg:phone":"+61 8 8371 3511",
    "sg:postcode":"5035",
    "sg:province":"SA",
    "sg:tags":[
        "adhesive"
    ],
    "wof:name":"Davco Construction Materials Pty Ltd",
    "wof:placetype":"venue"
},
  "geometry": {"coordinates":[138.57740783700001,-34.9461288452],"type":"Point"}
}