{
  "type": "Feature",
  "properties": {
    "addr:full":"101 Beach St Port Melbourne VIC 3207",
    "addr:housenumber":"101",
    "addr:postcode":"3207",
    "addr:street":"Beach St",
    "iso:country":"AU",
    "sg:address":"101 Beach St",
    "sg:city":"Port Melbourne",
    "sg:classifiers":[
        {
            "category":"Health Services",
            "subcategory":"Health Practitioner",
            "type":"Services"
        }
    ],
    "sg:phone":"+61 3 9645 2183",
    "sg:postcode":"3207",
    "sg:province":"VIC",
    "sg:tags":[
        "physiotherapist"
    ],
    "wof:name":"Fennell Sue",
    "wof:placetype":"venue"
},
  "geometry": {"coordinates":[144.933044,-37.840466],"type":"Point"}
}