{
  "type": "Feature",
  "properties": {
    "iso:country":"AU",
    "sg:address":"Unit 4/ 37 Osborne Rd",
    "sg:city":"East Fremantle",
    "sg:classifiers":[
        {
            "category":"Arts & Performance",
            "subcategory":"Music",
            "type":"Entertainment"
        }
    ],
    "sg:phone":"+61 8 9319 3292",
    "sg:postcode":"6158",
    "sg:province":"WA",
    "sg:tags":[
        "mobile",
        "jockey",
        "disc"
    ],
    "wof:name":"Fremantle DJ",
    "wof:placetype":"venue"
},
  "geometry": {"coordinates":[115.769302,-32.037968],"type":"Point"}
}