{
  "type": "Feature",
  "properties": {
    "addr:full":"Cnr Badham & Woolley Sts Dickson ACT 2602",
    "addr:postcode":"2602",
    "addr:street":"Cnr",
    "iso:country":"AU",
    "sg:address":"Cnr Badham & Woolley Sts",
    "sg:city":"Dickson",
    "sg:classifiers":[
        {
            "category":"Banks & Credit Unions",
            "subcategory":"Bank",
            "type":"Services"
        }
    ],
    "sg:phone":"+61 13 20 32",
    "sg:postcode":"2602",
    "sg:province":"ACT",
    "wof:name":"Westpac",
    "wof:placetype":"venue"
},
  "geometry": {"coordinates":[149.13775634800001,-35.2508201599],"type":"Point"}
}