{
  "type": "Feature",
  "properties": {
    "addr:full":"34 Mountbatten Drv Dubbo NSW 2830",
    "addr:housenumber":"34",
    "addr:postcode":"2830",
    "addr:street":"Mountbatten Drv",
    "iso:country":"AU",
    "sg:address":"34 Mountbatten Drv",
    "sg:city":"Dubbo",
    "sg:classifiers":[
        {
            "category":"Wholesale",
            "subcategory":"Scrap",
            "type":"Manufacturing & Wholesale Goods"
        }
    ],
    "sg:phone":"+61 2 6882 1033",
    "sg:postcode":"2830",
    "sg:province":"NSW",
    "sg:tags":[
        "merchant",
        "metal"
    ],
    "wof:name":"Matthews Metal Management",
    "wof:placetype":"venue"
},
  "geometry": {"coordinates":[148.640090942,-32.2500724792],"type":"Point"}
}