{
  "type": "Feature",
  "properties": {
    "iso:country":"AU",
    "sg:address":"38 Hill St",
    "sg:city":"Austinmer",
    "sg:classifiers":[
        {
            "category":"Professional",
            "subcategory":"Engineering",
            "type":"Services"
        }
    ],
    "sg:phone":"+61 2 4267 4480",
    "sg:postcode":"2515",
    "sg:province":"NSW",
    "sg:tags":[
        "patternmaker"
    ],
    "wof:name":"H Phipps Patternmakers Pty Ltd",
    "wof:placetype":"venue"
},
  "geometry": {"coordinates":[150.92510999999999,-34.306126],"type":"Point"}
}