{
  "type": "Feature",
  "properties": {
    "iso:country":"AU",
    "sg:address":"4 Malcomson St",
    "sg:city":"North Mackay",
    "sg:classifiers":[
        {
            "category":"Professional",
            "subcategory":"Computer Services",
            "type":"Services"
        }
    ],
    "sg:phone":"+61 7 4957 8522",
    "sg:postcode":"4740",
    "sg:province":"QLD",
    "sg:tags":[
        "repairs",
        "upgrade",
        "equipment"
    ],
    "wof:name":"CRC Computers",
    "wof:placetype":"venue"
},
  "geometry": {"coordinates":[149.18673699999999,-21.123735],"type":"Point"}
}