{
  "type": "Feature",
  "properties": {
    "addr:full":"20 Calder Hwy Ouyen VIC 3490",
    "addr:housenumber":"20",
    "addr:postcode":"3490",
    "addr:street":"Calder Hwy",
    "iso:country":"AU",
    "sg:address":"20 Calder Hwy",
    "sg:city":"Ouyen",
    "sg:classifiers":[
        {
            "category":"Travel",
            "subcategory":"Hotels & Motels",
            "type":"Entertainment"
        }
    ],
    "sg:phone":"+61 3 5092 1410",
    "sg:postcode":"3490",
    "sg:province":"VIC",
    "wof:name":"Hilltop Motel",
    "wof:placetype":"venue"
},
  "geometry": {"coordinates":[142.31878662099999,-35.0663414001],"type":"Point"}
}