{
  "type": "Feature",
  "properties": {
    "addr:full":"Lvl2/ 19 Creek St Redcliffe QLD 4020",
    "addr:housenumber":"19",
    "addr:postcode":"4020",
    "addr:street":"Creek St",
    "iso:country":"AU",
    "sg:address":"Lvl2/ 19 Creek St",
    "sg:city":"Redcliffe",
    "sg:classifiers":[
        {
            "category":"Professional",
            "subcategory":"Computer Services",
            "type":"Services"
        }
    ],
    "sg:phone":"+61 7 3283 6215",
    "sg:postcode":"4020",
    "sg:province":"QLD",
    "sg:tags":[
        "package",
        "software"
    ],
    "wof:name":"FlowBiz Pty Ltd",
    "wof:placetype":"venue"
},
  "geometry": {"coordinates":[153.11335800000001,-27.227289],"type":"Point"}
}