{
  "type": "Feature",
  "properties": {
    "addr:full":"800 Glenhuntly Rd Caulfield VIC 3162",
    "addr:housenumber":"800",
    "addr:postcode":"3162",
    "addr:street":"Glenhuntly Rd",
    "iso:country":"AU",
    "sg:address":"800 Glenhuntly Rd",
    "sg:city":"Caulfield",
    "sg:classifiers":[
        {
            "category":"Travel",
            "subcategory":"Travel Agent",
            "type":"Entertainment"
        }
    ],
    "sg:phone":"+61 3 9530 0888",
    "sg:postcode":"3162",
    "sg:province":"VIC",
    "sg:tags":[
        "consultant"
    ],
    "wof:name":"Danube Travel",
    "wof:placetype":"venue"
},
  "geometry": {"coordinates":[145.022415161,-37.887046814],"type":"Point"}
}