{
  "type": "Feature",
  "properties": {
    "addr:full":"16 Lakeview Rd Morayfield QLD 4506",
    "addr:housenumber":"16",
    "addr:postcode":"4506",
    "addr:street":"Lakeview Rd",
    "iso:country":"AU",
    "sg:address":"16 Lakeview Rd",
    "sg:city":"Morayfield",
    "sg:classifiers":[
        {
            "category":"Farming",
            "subcategory":"Nursery",
            "type":"Manufacturing & Wholesale Goods"
        }
    ],
    "sg:phone":"+61 7 5428 6778",
    "sg:postcode":"4506",
    "sg:province":"QLD",
    "wof:name":"Lakeview Nursery",
    "wof:placetype":"venue"
},
  "geometry": {"coordinates":[152.94380188,-27.1241130829],"type":"Point"}
}