{
  "type": "Feature",
  "properties": {
    "addr:full":"PO Box 717 , Bowral NSW 2576",
    "addr:postcode":"2576",
    "iso:country":"AU",
    "sg:address":"PO Box 717",
    "sg:city":", Bowral",
    "sg:classifiers":[
        {
            "category":"Home & Garden",
            "subcategory":"Household Appliances",
            "type":"Retail Goods"
        }
    ],
    "sg:phone":"+61 2 4861 3740",
    "sg:postcode":"2576",
    "sg:province":"NSW",
    "sg:tags":[
        "heating",
        "system"
    ],
    "wof:name":"Price Plumbing",
    "wof:placetype":"venue"
},
  "geometry": {"coordinates":[150.385894775,-34.4550590515],"type":"Point"}
}