{
  "type": "Feature",
  "properties": {
    "addr:full":"28 Railway Pde Liverpool NSW 2170",
    "addr:housenumber":"28",
    "addr:postcode":"2170",
    "addr:street":"Railway Pde",
    "iso:country":"AU",
    "sg:address":"28 Railway Pde",
    "sg:city":"Liverpool",
    "sg:classifiers":[
        {
            "category":"Shopping",
            "subcategory":"Baby Store",
            "type":"Retail Goods"
        }
    ],
    "sg:phone":"+61 2 9821 4014",
    "sg:postcode":"2170",
    "sg:province":"NSW",
    "sg:tags":[
        "children's",
        "wear"
    ],
    "wof:name":"Belinda Children's Wear",
    "wof:placetype":"venue"
},
  "geometry": {"coordinates":[150.92544555699999,-33.9243621826],"type":"Point"}
}