{
  "type": "Feature",
  "properties": {
    "addr:full":"64 Otho St Inverell NSW 2360",
    "addr:housenumber":"64",
    "addr:postcode":"2360",
    "addr:street":"Otho St",
    "iso:country":"AU",
    "sg:address":"64 Otho St",
    "sg:city":"Inverell",
    "sg:classifiers":[
        {
            "category":"Personal",
            "subcategory":"Beauty Salon",
            "type":"Services"
        }
    ],
    "sg:phone":"+61 2 6721 1100",
    "sg:postcode":"2360",
    "sg:province":"NSW",
    "sg:tags":[
        "hairdresser"
    ],
    "wof:name":"Look Sharp Hair Studio",
    "wof:placetype":"venue"
},
  "geometry": {"coordinates":[151.112716675,-29.7745571136],"type":"Point"}
}