{
  "type": "Feature",
  "properties": {
    "addr:full":"83 Nelson St Wallsend NSW 2287",
    "addr:housenumber":"83",
    "addr:postcode":"2287",
    "addr:street":"Nelson St",
    "iso:country":"AU",
    "sg:address":"83 Nelson St",
    "sg:city":"Wallsend",
    "sg:classifiers":[
        {
            "category":"Restaurant",
            "type":"Food & Drink"
        }
    ],
    "sg:phone":"+61 2 4955 0220",
    "sg:postcode":"2287",
    "sg:province":"NSW",
    "wof:name":"Anna Cafe Italian Trattoria",
    "wof:placetype":"venue"
},
  "geometry": {"coordinates":[151.66900634800001,-32.9007530212],"type":"Point"}
}