{
  "type": "Feature",
  "properties": {
    "addr:full":"Lot1017/ Wattle Rd Casula NSW 2170",
    "addr:postcode":"2170",
    "addr:street":"Wattle Rd",
    "iso:country":"AU",
    "sg:address":"Lot1017/ Wattle Rd",
    "sg:city":"Casula",
    "sg:classifiers":[
        {
            "category":"Professional",
            "subcategory":"Accounting & Tax Preparation",
            "type":"Services"
        }
    ],
    "sg:phone":"+61 2 9607 5206",
    "sg:postcode":"2170",
    "sg:province":"NSW",
    "sg:tags":[
        "consultant",
        "taxation"
    ],
    "wof:name":"R M Financial Services Pty Ltd",
    "wof:placetype":"venue"
},
  "geometry": {"coordinates":[150.88871765100001,-33.9560699463],"type":"Point"}
}