{
  "type": "Feature",
  "properties": {
    "iso:country":"AU",
    "sg:address":"67 Bulcock St",
    "sg:city":"Caloundra",
    "sg:classifiers":[
        {
            "category":"Ice Cream",
            "type":"Food & Drink"
        }
    ],
    "sg:phone":"+61 7 5491 7788",
    "sg:postcode":"4551",
    "sg:province":"QLD",
    "sg:tags":[
        "specialised",
        "fitting",
        "lady",
        "wear"
    ],
    "wof:name":"Front Covergirl Boutique",
    "wof:placetype":"venue"
},
  "geometry": {"coordinates":[153.129074097,-26.8046283722],"type":"Point"}
}