{
  "type": "Feature",
  "properties": {
    "addr:full":"Suite 110, 283 Alfred St North Sydney NSW 2060",
    "addr:housenumber":"283",
    "addr:postcode":"2060",
    "addr:street":"Alfred St",
    "iso:country":"AU",
    "sg:address":"Suite 110, 283 Alfred St",
    "sg:city":"North Sydney",
    "sg:classifiers":[
        {
            "category":"Insurance",
            "subcategory":"Insurance Agent",
            "type":"Services"
        }
    ],
    "sg:phone":"+61 2 9929 9969",
    "sg:postcode":"2060",
    "sg:province":"NSW",
    "sg:tags":[
        "broker"
    ],
    "wof:name":"Surety & General Brokers",
    "wof:placetype":"venue"
},
  "geometry": {"coordinates":[151.21136474599999,-33.8400726318],"type":"Point"}
}