{
  "type": "Feature",
  "properties": {
    "addr:full":"118 Canterbury Rd Blackburn South VIC 3130",
    "addr:housenumber":"118",
    "addr:postcode":"3130",
    "addr:street":"Canterbury Rd",
    "iso:country":"AU",
    "sg:address":"118 Canterbury Rd",
    "sg:city":"Blackburn South",
    "sg:classifiers":[
        {
            "category":"Real Estate",
            "subcategory":"Real Estate Agent",
            "type":"Services"
        }
    ],
    "sg:phone":"+61 3 9877 3111",
    "sg:postcode":"3130",
    "sg:province":"VIC",
    "wof:name":"Foster & Co Estate Agents",
    "wof:placetype":"venue"
},
  "geometry": {"coordinates":[145.14726257300001,-37.8319244385],"type":"Point"}
}