{
  "type": "Feature",
  "properties": {
    "addr:full":"52 Blair St North Bondi NSW 2026",
    "addr:housenumber":"52",
    "addr:postcode":"2026",
    "addr:street":"Blair St",
    "iso:country":"AU",
    "sg:address":"52 Blair St",
    "sg:city":"North Bondi",
    "sg:classifiers":[
        {
            "category":"Communications",
            "subcategory":"Film & Video Production",
            "type":"Services"
        }
    ],
    "sg:phone":"+61 2 9365 0280",
    "sg:postcode":"2026",
    "sg:province":"NSW",
    "sg:tags":[
        "dvd",
        "library"
    ],
    "wof:name":"Home Pics Video",
    "wof:placetype":"venue"
},
  "geometry": {"coordinates":[151.2762146,-33.8856887817],"type":"Point"}
}