{
  "type": "Feature",
  "properties": {
    "addr:full":"28 Hayward St Stafford QLD 4053",
    "addr:housenumber":"28",
    "addr:postcode":"4053",
    "addr:street":"Hayward St",
    "iso:country":"AU",
    "sg:address":"28 Hayward St",
    "sg:city":"Stafford",
    "sg:classifiers":[
        {
            "category":"Autos & Motor Vehicles",
            "subcategory":"Auto Supplies",
            "type":"Retail Goods"
        }
    ],
    "sg:phone":"+61 7 3356 4044",
    "sg:postcode":"4053",
    "sg:province":"QLD",
    "sg:tags":[
        "wheel",
        "four",
        "equipment",
        "drive",
        "accessory"
    ],
    "wof:name":"Custom Off-Road Components Pty Ltd",
    "wof:placetype":"venue"
},
  "geometry": {"coordinates":[153.01411438,-27.4153556824],"type":"Point"}
}