{
  "type": "Feature",
  "properties": {
    "addr:full":"196 Sladen St Cranbourne VIC 3977",
    "addr:housenumber":"196",
    "addr:postcode":"3977",
    "addr:street":"Sladen St",
    "iso:country":"AU",
    "sg:address":"196 Sladen St",
    "sg:city":"Cranbourne",
    "sg:classifiers":[
        {
            "category":"Building & Trades",
            "subcategory":"Construction",
            "type":"Services"
        }
    ],
    "sg:phone":"+61 3 5996 4100",
    "sg:postcode":"3977",
    "sg:province":"VIC",
    "sg:tags":[
        "contractor"
    ],
    "wof:name":"Cooper Homes Builders",
    "wof:placetype":"venue"
},
  "geometry": {"coordinates":[145.28651428200001,-38.1136512756],"type":"Point"}
}