{
  "type": "Feature",
  "properties": {
    "iso:country":"AU",
    "sg:address":"Railway St",
    "sg:city":"Kurri Kurri",
    "sg:classifiers":[
        {
            "category":"Travel",
            "subcategory":"Hotels & Motels",
            "type":"Entertainment"
        }
    ],
    "sg:phone":"+61 2 4937 1006",
    "sg:postcode":"2327",
    "sg:province":"NSW",
    "sg:tags":[
        "accommodation"
    ],
    "wof:name":"Empire Tavern",
    "wof:placetype":"venue"
},
  "geometry": {"coordinates":[151.48515319800001,-32.8245925903],"type":"Point"}
}