{
  "type": "Feature",
  "properties": {
    "iso:country":"AU",
    "sg:address":"19- 21 Victoria St",
    "sg:city":"Gosford East",
    "sg:classifiers":[
        {
            "category":"Social Services",
            "subcategory":"Retirement Home",
            "type":"Services"
        }
    ],
    "sg:phone":"+61 2 4323 2668",
    "sg:postcode":"2250",
    "sg:province":"NSW",
    "sg:tags":[
        "village"
    ],
    "wof:name":"Presbyterian Aged Care Gosford",
    "wof:placetype":"venue"
},
  "geometry": {"coordinates":[151.32798767099999,-33.4495162964],"type":"Point"}
}