{
  "type": "Feature",
  "properties": {
    "addr:full":"12 Lay St Mt Gravatt QLD 4122",
    "addr:housenumber":"12",
    "addr:postcode":"4122",
    "addr:street":"Lay St",
    "iso:country":"AU",
    "sg:address":"12 Lay St",
    "sg:city":"Mt Gravatt",
    "sg:classifiers":[
        {
            "category":"Communications",
            "subcategory":"Film & Video Production",
            "type":"Services"
        }
    ],
    "sg:phone":"+61 412 211 690",
    "sg:postcode":"4122",
    "sg:province":"QLD",
    "sg:tags":[
        "cost",
        "estimator"
    ],
    "wof:name":"Structural Steel Estimators",
    "wof:placetype":"venue"
},
  "geometry": {"coordinates":[153.08682250999999,-27.5431270599],"type":"Point"}
}