{
  "type": "Feature",
  "properties": {
    "addr:full":"276 Hodgins Rd Hastings VIC 3915",
    "addr:housenumber":"276",
    "addr:postcode":"3915",
    "addr:street":"Hodgins Rd",
    "iso:country":"AU",
    "sg:address":"276 Hodgins Rd",
    "sg:city":"Hastings",
    "sg:classifiers":[
        {
            "category":"Retail",
            "subcategory":"Auto Rental",
            "type":"Services"
        }
    ],
    "sg:phone":"+61 3 5979 8155",
    "sg:postcode":"3915",
    "sg:province":"VIC",
    "sg:tags":[
        "car",
        "wedding"
    ],
    "wof:name":"Belle Warren Carriages",
    "wof:placetype":"venue"
},
  "geometry": {"coordinates":[145.146392822,-38.2999572754],"type":"Point"}
}