{
  "type": "Feature",
  "properties": {
    "iso:country":"AU",
    "sg:address":"884 Brunswick St",
    "sg:city":"New Farm",
    "sg:classifiers":[
        {
            "category":"Social Services",
            "subcategory":"Adult Care",
            "type":"Services"
        }
    ],
    "sg:phone":"+61 7 3254 1881",
    "sg:postcode":"4005",
    "sg:province":"QLD",
    "sg:tags":[
        "disadvantaged",
        "aid",
        "organisation",
        "group"
    ],
    "wof:name":"A.R.A.F.M.I. (Bris) Inc",
    "wof:placetype":"venue"
},
  "geometry": {"coordinates":[153.046218872,-27.4670257568],"type":"Point"}
}