{
  "type": "Feature",
  "properties": {
    "iso:country":"AU",
    "sg:address":"1 Eustace St",
    "sg:city":"Dartmouth",
    "sg:classifiers":[
        {
            "category":"Travel",
            "subcategory":"Hotels & Motels",
            "type":"Entertainment"
        }
    ],
    "sg:phone":"+61 2 6072 4233",
    "sg:postcode":"3701",
    "sg:province":"VIC",
    "wof:name":"Dartmouth Motor Inn",
    "wof:placetype":"venue"
},
  "geometry": {"coordinates":[147.494598389,-36.5324630737],"type":"Point"}
}