{
  "type": "Feature",
  "properties": {
    "addr:full":"Woodville Rd Old Guildford NSW 2161",
    "addr:postcode":"2161",
    "addr:street":"Woodville Rd",
    "iso:country":"AU",
    "sg:address":"Woodville Rd",
    "sg:city":"Old Guildford",
    "sg:classifiers":[
        {
            "category":"Education",
            "subcategory":"School",
            "type":"Public Place"
        }
    ],
    "sg:phone":"+61 2 9632 8286",
    "sg:postcode":"2161",
    "sg:province":"NSW",
    "sg:tags":[
        "state",
        "-",
        "nsw"
    ],
    "wof:name":"Old Guildford Public School",
    "wof:placetype":"venue"
},
  "geometry": {"coordinates":[150.98677063,-33.8685836792],"type":"Point"}
}