{
  "type": "Feature",
  "properties": {
    "addr:full":"39 Victoria St Toowoomba QLD 4350",
    "addr:housenumber":"39",
    "addr:postcode":"4350",
    "addr:street":"Victoria St",
    "iso:country":"AU",
    "sg:address":"39 Victoria St",
    "sg:city":"Toowoomba",
    "sg:classifiers":[
        {
            "category":"Social Services",
            "subcategory":"Adult Care",
            "type":"Services"
        }
    ],
    "sg:phone":"+61 7 4639 1915",
    "sg:postcode":"4350",
    "sg:province":"QLD",
    "sg:tags":[
        "aged"
    ],
    "wof:name":"Senior Citizens Day Respite Centre",
    "wof:placetype":"venue"
},
  "geometry": {"coordinates":[151.95126300000001,-27.561199],"type":"Point"}
}