{
  "type": "Feature",
  "properties": {
    "addr:full":"St Andrews VIC 3761",
    "addr:postcode":"3761",
    "iso:country":"AU",
    "sg:address":"St",
    "sg:city":"Andrews",
    "sg:classifiers":[
        {
            "category":"Building & Trades",
            "subcategory":"Landscaping Services",
            "type":"Services"
        }
    ],
    "sg:phone":"+61 3 9435 9900",
    "sg:postcode":"3761",
    "sg:province":"VIC",
    "sg:tags":[
        "stump",
        "tree",
        "felling",
        "removal"
    ],
    "wof:name":"Out On A Limb Tree Services",
    "wof:placetype":"venue"
},
  "geometry": {"coordinates":[145.28773498499999,-37.5787086487],"type":"Point"}
}