{
  "type": "Feature",
  "properties": {
    "iso:country":"AU",
    "sg:address":"2/ 34 Park Ave",
    "sg:city":"Coffs Harbour",
    "sg:classifiers":[
        {
            "category":"Professional",
            "subcategory":"Employment Agencies",
            "type":"Services"
        }
    ],
    "sg:phone":"+61 2 6699 3418",
    "sg:postcode":"2450",
    "sg:province":"NSW",
    "sg:tags":[
        "provider",
        "internet"
    ],
    "wof:name":"Wirefree Networks",
    "wof:placetype":"venue"
},
  "geometry": {"coordinates":[153.115997314,-30.2993507385],"type":"Point"}
}