{
  "type": "Feature",
  "properties": {
    "addr:full":"DFO Extension, Cnr Bulla Rd & Tullamarine Fwy Essendon North VIC 3041",
    "addr:postcode":"3041",
    "addr:street":"Dfo;Cnr Bulla Rd & Tullamarine Fwy",
    "iso:country":"AU",
    "sg:address":"DFO Extension, Cnr Bulla Rd & Tullamarine Fwy",
    "sg:city":"Essendon North",
    "sg:classifiers":[
        {
            "category":"Wholesale",
            "subcategory":"Farm Supplies",
            "type":"Manufacturing & Wholesale Goods"
        }
    ],
    "sg:phone":"+61 3 9374 2277",
    "sg:postcode":"3041",
    "sg:province":"VIC",
    "sg:tags":[
        "feed",
        "supplement",
        "stock"
    ],
    "wof:name":"Pet, Horse & Farm",
    "wof:placetype":"venue"
},
  "geometry": {"coordinates":[144.905197144,-37.7369384766],"type":"Point"}
}