{
  "type": "Feature",
  "properties": {
    "addr:full":"4 Kagra St Eight Mile Plains QLD 4113",
    "addr:housenumber":"4",
    "addr:postcode":"4113",
    "addr:street":"Kagra St",
    "iso:country":"AU",
    "sg:address":"4 Kagra St",
    "sg:city":"Eight Mile Plains",
    "sg:classifiers":[
        {
            "category":"Real Estate",
            "subcategory":"Real Estate Agent",
            "type":"Services"
        }
    ],
    "sg:phone":"+61 7 3341 5111",
    "sg:postcode":"4113",
    "sg:province":"QLD",
    "wof:name":"Wishart Realty",
    "wof:placetype":"venue"
},
  "geometry": {"coordinates":[153.099212647,-27.5721569061],"type":"Point"}
}