{
  "type": "Feature",
  "properties": {
    "addr:full":"445 Victoria Ave Chatswood NSW 2057",
    "addr:housenumber":"445",
    "addr:postcode":"2057",
    "addr:street":"Victoria Ave",
    "iso:country":"AU",
    "sg:address":"445 Victoria Ave",
    "sg:city":"Chatswood",
    "sg:classifiers":[
        {
            "category":"Health Services",
            "subcategory":"Health Practitioner",
            "type":"Services"
        }
    ],
    "sg:phone":"+61 2 9796 3242",
    "sg:postcode":"2057",
    "sg:province":"NSW",
    "sg:tags":[
        "consultant",
        "conservation",
        "hearing"
    ],
    "wof:name":"Audio Clinic National Hearing Aids",
    "wof:placetype":"venue"
},
  "geometry": {"coordinates":[151.18255600000001,-33.796246],"type":"Point"}
}