{
  "type": "Feature",
  "properties": {
    "iso:country":"AU",
    "sg:address":"22 McCallum St",
    "sg:city":"Swan Hill",
    "sg:classifiers":[
        {
            "category":"Professional",
            "subcategory":"Accounting & Tax Preparation",
            "type":"Services"
        }
    ],
    "sg:phone":"+61 3 5032 9906",
    "sg:postcode":"3585",
    "sg:province":"NSW",
    "sg:tags":[
        "consultant",
        "taxation"
    ],
    "wof:name":"Logan & Hall Pty Ltd",
    "wof:placetype":"venue"
},
  "geometry": {"coordinates":[143.55969200000001,-35.338226],"type":"Point"}
}