{
  "type": "Feature",
  "properties": {
    "addr:full":"Orana St Grafton NSW 2460",
    "addr:postcode":"2460",
    "addr:street":"Orana St",
    "iso:country":"AU",
    "sg:address":"Orana St",
    "sg:city":"Grafton",
    "sg:classifiers":[
        {
            "category":"Autos & Motor Vehicles",
            "subcategory":"Fuel & Gas Station",
            "type":"Retail Goods"
        }
    ],
    "sg:phone":"+61 2 6642 1397",
    "sg:postcode":"2460",
    "sg:province":"NSW",
    "wof:name":"BP Australia Limited",
    "wof:placetype":"venue"
},
  "geometry": {"coordinates":[152.91894531200001,-29.6710071564],"type":"Point"}
}