{
  "type": "Feature",
  "properties": {
    "addr:full":"SHop 56 , Castletown Shopping World Hyde Park QLD 4812",
    "addr:housenumber":"shop 56",
    "addr:postcode":"4812",
    "addr:street":"Castletown Shopping",
    "iso:country":"AU",
    "sg:address":"SHop 56",
    "sg:city":", Castletown Shopping World Hyde Park",
    "sg:classifiers":[
        {
            "category":"Banks & Credit Unions",
            "subcategory":"Bank",
            "type":"Services"
        }
    ],
    "sg:phone":"+61 13 20 32",
    "sg:postcode":"4812",
    "sg:province":"QLD",
    "wof:name":"Westpac",
    "wof:placetype":"venue"
},
  "geometry": {"coordinates":[146.79513499999999,-19.27693],"type":"Point"}
}