{
  "type": "Feature",
  "properties": {
    "addr:full":"Level 2 1 South St Kogarah NSW 2217",
    "addr:housenumber":"1",
    "addr:postcode":"2217",
    "addr:street":"South St",
    "iso:country":"AU",
    "sg:address":"Level 2 1 South St",
    "sg:city":"Kogarah",
    "sg:classifiers":[
        {
            "category":"Health Services",
            "subcategory":"Doctor",
            "type":"Services"
        }
    ],
    "sg:phone":"+61 2 9598 5488",
    "sg:postcode":"2217",
    "sg:province":"NSW",
    "sg:tags":[
        "medical",
        "practitioner"
    ],
    "wof:name":"St George Private Hospital Nuclear Medicine",
    "wof:placetype":"venue"
},
  "geometry": {"coordinates":[151.135651,-33.966125],"type":"Point"}
}