{
  "type": "Feature",
  "properties": {
    "addr:full":"Suite 3, 2 Salisbury St Richmond VIC 3121",
    "addr:housenumber":"2",
    "addr:postcode":"3121",
    "addr:street":"Salisbury St",
    "iso:country":"AU",
    "sg:address":"Suite 3, 2 Salisbury St",
    "sg:city":"Richmond",
    "sg:classifiers":[
        {
            "category":"Real Estate",
            "subcategory":"Real Estate Services",
            "type":"Services"
        }
    ],
    "sg:phone":"+61 3 9429 3333",
    "sg:postcode":"3121",
    "sg:province":"VIC",
    "sg:tags":[
        "consultant",
        "property"
    ],
    "wof:name":"Point Property Group Pty Ltd",
    "wof:placetype":"venue"
},
  "geometry": {"coordinates":[144.99005126899999,-37.8215904236],"type":"Point"}
}