{
  "type": "Feature",
  "properties": {
    "addr:full":"26 Daniel Crt Warranwood VIC 3134",
    "addr:housenumber":"26",
    "addr:postcode":"3134",
    "addr:street":"Daniel Crt",
    "iso:country":"AU",
    "sg:address":"26 Daniel Crt",
    "sg:city":"Warranwood",
    "sg:classifiers":[
        {
            "category":"Building & Trades",
            "subcategory":"Construction",
            "type":"Services"
        }
    ],
    "sg:phone":"+61 418 318 883",
    "sg:postcode":"3134",
    "sg:province":"VIC",
    "sg:tags":[
        "joiner",
        "carpenter"
    ],
    "wof:name":"Horley Constructions",
    "wof:placetype":"venue"
},
  "geometry": {"coordinates":[145.240036011,-37.7789344788],"type":"Point"}
}