{
  "type": "Feature",
  "properties": {
    "addr:full":"72 Strattman St Mareeba QLD 4880",
    "addr:housenumber":"72",
    "addr:postcode":"4880",
    "addr:street":"Strattman St",
    "iso:country":"AU",
    "sg:address":"72 Strattman St",
    "sg:city":"Mareeba",
    "sg:classifiers":[
        {
            "category":"Arts & Performance",
            "subcategory":"Art Gallery",
            "type":"Entertainment"
        }
    ],
    "sg:phone":"+61 7 4092 3783",
    "sg:postcode":"4880",
    "sg:province":"QLD",
    "wof:name":"Verandah Gallery The",
    "wof:placetype":"venue"
},
  "geometry": {"coordinates":[145.42091369600001,-16.9985427856],"type":"Point"}
}