{
  "type": "Feature",
  "properties": {
    "iso:country":"AU",
    "sg:address":"31 Varden St",
    "sg:city":"Kalgoorlie",
    "sg:classifiers":[
        {
            "category":"Health Services",
            "subcategory":"Doctor",
            "type":"Services"
        }
    ],
    "sg:phone":"+61 8 9091 7210",
    "sg:postcode":"6430",
    "sg:province":"WA",
    "sg:tags":[
        "medical",
        "practitioner"
    ],
    "wof:name":"Jeffries-Stokes Christine Dr",
    "wof:placetype":"venue"
},
  "geometry": {"coordinates":[121.464920044,-30.7388057709],"type":"Point"}
}