{
  "type": "Feature",
  "properties": {
    "addr:full":"453 Draper St Parramatta Park QLD 4870",
    "addr:housenumber":"453",
    "addr:postcode":"4870",
    "addr:street":"Draper St",
    "iso:country":"AU",
    "sg:address":"453 Draper St",
    "sg:city":"Parramatta Park",
    "sg:classifiers":[
        {
            "category":"Shopping",
            "subcategory":"Discount & Variety Stores",
            "type":"Retail Goods"
        }
    ],
    "sg:phone":"+61 7 4051 6448",
    "sg:postcode":"4870",
    "sg:province":"QLD",
    "sg:tags":[
        "register",
        "cash"
    ],
    "wof:name":"Northern Scales Service",
    "wof:placetype":"venue"
},
  "geometry": {"coordinates":[145.75990295400001,-16.9164638519],"type":"Point"}
}