{
  "type": "Feature",
  "properties": {
    "addr:full":"Target Shopping Centre, 447 - 465 Tapleys Hills Rd Fulham Gardens SA 5024",
    "addr:housenumber":"447 465",
    "addr:postcode":"5024",
    "addr:street":"Tapleys Hills Rd",
    "iso:country":"AU",
    "sg:address":"Target Shopping Centre, 447 - 465 Tapleys Hills Rd",
    "sg:city":"Fulham Gardens",
    "sg:classifiers":[
        {
            "category":"Food & Beverages",
            "subcategory":"Bakery",
            "type":"Retail Goods"
        }
    ],
    "sg:phone":"+61 8 8353 8900",
    "sg:postcode":"5024",
    "sg:province":"SA",
    "sg:tags":[
        "baker"
    ],
    "wof:name":"Bakers Delight(SA)Pty Ltd",
    "wof:placetype":"venue"
},
  "geometry": {"coordinates":[138.51707458499999,-34.9244499207],"type":"Point"}
}