{
  "type": "Feature",
  "properties": {
    "iso:country":"AU",
    "sg:address":"Shop 7/ 318 Wardell St",
    "sg:city":"Enoggera",
    "sg:classifiers":[
        {
            "category":"Banks & Credit Unions",
            "subcategory":"Bank",
            "type":"Services"
        }
    ],
    "sg:phone":"+61 7 3855 8122",
    "sg:postcode":"4051",
    "sg:province":"QLD",
    "sg:tags":[
        "broker",
        "mortgage"
    ],
    "wof:name":"Homeloan Connexion",
    "wof:placetype":"venue"
},
  "geometry": {"coordinates":[152.99046325699999,-27.4230060577],"type":"Point"}
}