{
  "type": "Feature",
  "properties": {
    "addr:full":"6 Gawler St Portland VIC 3305",
    "addr:housenumber":"6",
    "addr:postcode":"3305",
    "addr:street":"Gawler St",
    "iso:country":"AU",
    "sg:address":"6 Gawler St",
    "sg:city":"Portland",
    "sg:classifiers":[
        {
            "category":"Autos & Motor Vehicles",
            "subcategory":"Fuel & Gas Station",
            "type":"Retail Goods"
        }
    ],
    "sg:phone":"+61 3 5523 2808",
    "sg:postcode":"3305",
    "sg:province":"VIC",
    "wof:name":"BP Seaport Service Station",
    "wof:placetype":"venue"
},
  "geometry": {"coordinates":[141.60577392600001,-38.3504562378],"type":"Point"}
}