{
  "type": "Feature",
  "properties": {
    "addr:full":"22 Chittick Ave Nowra North NSW 2541",
    "addr:housenumber":"22",
    "addr:postcode":"2541",
    "addr:street":"Chittick Ave",
    "iso:country":"AU",
    "sg:address":"22 Chittick Ave",
    "sg:city":"Nowra North",
    "sg:classifiers":[
        {
            "category":"Building & Trades",
            "subcategory":"Construction",
            "type":"Services"
        }
    ],
    "sg:phone":"+61 2 4421 7713",
    "sg:postcode":"2541",
    "sg:province":"NSW",
    "sg:tags":[
        "rendering",
        "cement"
    ],
    "sg:website":"http://www.conceptcoatings.com.au",
    "wof:name":"Concept Coatings",
    "wof:placetype":"venue"
},
  "geometry": {"coordinates":[150.574310303,-34.8479385376],"type":"Point"}
}