{
  "type": "Feature",
  "properties": {
    "addr:full":"644 Grange Rd Henley Beach SA 5022",
    "addr:housenumber":"644",
    "addr:postcode":"5022",
    "addr:street":"Grange Rd",
    "iso:country":"AU",
    "sg:address":"644 Grange Rd",
    "sg:city":"Henley Beach",
    "sg:classifiers":[
        {
            "category":"Sports & Exercise",
            "subcategory":"Sports Center",
            "type":"Entertainment"
        }
    ],
    "sg:phone":"+61 418 858 672",
    "sg:postcode":"5022",
    "sg:province":"SA",
    "sg:tags":[
        "physiologist"
    ],
    "wof:name":"EPS Exercise Physiology Services",
    "wof:placetype":"venue"
},
  "geometry": {"coordinates":[138.49418640100001,-34.9061203003],"type":"Point"}
}