{
  "type": "Feature",
  "properties": {
    "iso:country":"AU",
    "sg:address":"14 Cobb Rd",
    "sg:city":"Burpengary",
    "sg:classifiers":[
        {
            "category":"Health Services",
            "subcategory":"Health Practitioner",
            "type":"Services"
        }
    ],
    "sg:phone":"+61 7 5497 8680",
    "sg:postcode":"4505",
    "sg:province":"QLD",
    "sg:tags":[
        "reiki"
    ],
    "wof:name":"Abask In Reiki",
    "wof:placetype":"venue"
},
  "geometry": {"coordinates":[152.98797607399999,-27.1304664612],"type":"Point"}
}