{
  "type": "Feature",
  "properties": {
    "addr:full":"1-3 King St (Cnr Mathews Ave) Airport West VIC 3042",
    "addr:housenumber":"1-3",
    "addr:postcode":"3042",
    "addr:street":"King St Cnr Mathews Ave",
    "iso:country":"AU",
    "sg:address":"1-3 King St (Cnr Mathews Ave)",
    "sg:city":"Airport West",
    "sg:classifiers":[
        {
            "category":"Shopping",
            "subcategory":"Computers & Home Electronics",
            "type":"Retail Goods"
        }
    ],
    "sg:phone":"+61 3 9338 6866",
    "sg:postcode":"3042",
    "sg:province":"VIC",
    "sg:tags":[
        "equipment",
        "supply"
    ],
    "sg:website":"http://www.renaissancecc.com.au",
    "wof:name":"Renaissance Computers",
    "wof:placetype":"venue"
},
  "geometry": {"coordinates":[144.89059448200001,-37.7236824036],"type":"Point"}
}