{
  "type": "Feature",
  "properties": {
    "addr:full":"24 Hutcheson St Monash ACT 2904",
    "addr:housenumber":"24",
    "addr:postcode":"2904",
    "addr:street":"Hutcheson St",
    "iso:country":"AU",
    "sg:address":"24 Hutcheson St",
    "sg:city":"Monash",
    "sg:classifiers":[
        {
            "category":"Retail",
            "subcategory":"Driving School",
            "type":"Services"
        }
    ],
    "sg:phone":"+61 408 484 371",
    "sg:postcode":"2904",
    "sg:province":"ACT",
    "wof:name":"A Southside Driving School",
    "wof:placetype":"venue"
},
  "geometry": {"coordinates":[149.09889221200001,-35.4156341553],"type":"Point"}
}