{
  "type": "Feature",
  "properties": {
    "iso:country":"AU",
    "sg:address":"Tufnell Rd",
    "sg:city":"Banyo",
    "sg:classifiers":[
        {
            "category":"Fast Food",
            "type":"Food & Drink"
        }
    ],
    "sg:phone":"+61 7 3267 8388",
    "sg:postcode":"4014",
    "sg:province":"QLD",
    "sg:tags":[
        "away",
        "take"
    ],
    "wof:name":"Fortress Chinese Take Away",
    "wof:placetype":"venue"
},
  "geometry": {"coordinates":[153.07824707,-27.3760871887],"type":"Point"}
}