{
  "type": "Feature",
  "properties": {
    "iso:country":"AU",
    "sg:address":"3 Second Ave",
    "sg:city":"Eastwood",
    "sg:classifiers":[
        {
            "category":"Wholesale",
            "subcategory":"Motor Vehicles",
            "type":"Manufacturing & Wholesale Goods"
        }
    ],
    "sg:phone":"+61 2 9874 7444",
    "sg:postcode":"2122",
    "sg:province":"NSW",
    "sg:tags":[
        "turbine"
    ],
    "wof:name":"World Energy Pty Ltd",
    "wof:placetype":"venue"
},
  "geometry": {"coordinates":[151.08651733400001,-33.7927932739],"type":"Point"}
}