{
  "type": "Feature",
  "properties": {
    "addr:full":"3 Tamara St Belmont North NSW 2280",
    "addr:housenumber":"3",
    "addr:postcode":"2280",
    "addr:street":"Tamara St",
    "iso:country":"AU",
    "sg:address":"3 Tamara St",
    "sg:city":"Belmont North",
    "sg:classifiers":[
        {
            "category":"Home & Garden",
            "subcategory":"Carpets & Floor Coverings",
            "type":"Retail Goods"
        }
    ],
    "sg:phone":"+61 2 4946 0700",
    "sg:postcode":"2280",
    "sg:province":"NSW",
    "sg:tags":[
        "flooring",
        "parquet"
    ],
    "wof:name":"Bowerman Steve",
    "wof:placetype":"venue"
},
  "geometry": {"coordinates":[151.676544189,-33.0156135559],"type":"Point"}
}