{
  "type": "Feature",
  "properties": {
    "addr:full":"East/West Hwy Norseman WA 6443",
    "addr:postcode":"6443",
    "addr:street":"Hwy",
    "iso:country":"AU",
    "sg:address":"East/West Hwy",
    "sg:city":"Norseman",
    "sg:classifiers":[
        {
            "category":"Autos & Motor Vehicles",
            "subcategory":"Fuel & Gas Station",
            "type":"Retail Goods"
        }
    ],
    "sg:phone":"+61 8 9039 1163",
    "sg:postcode":"6443",
    "sg:province":"WA",
    "wof:name":"Ampol",
    "wof:placetype":"venue"
},
  "geometry": {"coordinates":[121.778839111,-32.1954307556],"type":"Point"}
}