{
  "type": "Feature",
  "properties": {
    "addr:full":"1 Balmain Crs Acton ACT 2601",
    "addr:housenumber":"1",
    "addr:postcode":"2601",
    "addr:street":"Balmain Crs",
    "iso:country":"AU",
    "sg:address":"1 Balmain Crs",
    "sg:city":"Acton",
    "sg:classifiers":[
        {
            "category":"Restaurant",
            "type":"Food & Drink"
        }
    ],
    "sg:phone":"+61 2 6125 5285",
    "sg:postcode":"2601",
    "sg:province":"ACT",
    "wof:name":"Boffins",
    "wof:placetype":"venue"
},
  "geometry": {"coordinates":[149.11830139200001,-35.285610199],"type":"Point"}
}