{
  "type": "Feature",
  "properties": {
    "addr:full":"U5/ 27 Victoria St Smithfield NSW 2164",
    "addr:housenumber":"27",
    "addr:postcode":"2164",
    "addr:street":"U5 /;Victoria St",
    "iso:country":"AU",
    "sg:address":"U5/ 27 Victoria St",
    "sg:city":"Smithfield",
    "sg:classifiers":[
        {
            "category":"Building & Trades",
            "subcategory":"Electrical",
            "type":"Services"
        }
    ],
    "sg:phone":"+61 2 9729 2553",
    "sg:postcode":"2164",
    "sg:province":"NSW",
    "sg:tags":[
        "repair",
        "generator",
        "electric",
        "motor"
    ],
    "wof:name":"D C Motor Repair Services",
    "wof:placetype":"venue"
},
  "geometry": {"coordinates":[150.94122314399999,-33.8516082764],"type":"Point"}
}