{
  "type": "Feature",
  "properties": {
    "iso:country":"AU",
    "sg:address":"147 Darby St",
    "sg:city":"Cooks Hill",
    "sg:classifiers":[
        {
            "category":"Health Services",
            "subcategory":"Doctor",
            "type":"Services"
        }
    ],
    "sg:phone":"+61 2 4929 2718",
    "sg:postcode":"2300",
    "sg:province":"NSW",
    "sg:tags":[
        "medical",
        "practitioner"
    ],
    "wof:name":"MacDonald Andrew",
    "wof:placetype":"venue"
},
  "geometry": {"coordinates":[151.77151499999999,-32.93185],"type":"Point"}
}