{
  "type": "Feature",
  "properties": {
    "addr:full":"Level1, 480 Dorset Rd Croydon VIC 3136",
    "addr:housenumber":"480",
    "addr:postcode":"3136",
    "addr:street":"Level1;Dorset Rd",
    "iso:country":"AU",
    "sg:address":"Level1, 480 Dorset Rd",
    "sg:city":"Croydon",
    "sg:classifiers":[
        {
            "category":"Real Estate",
            "subcategory":"Real Estate Agent",
            "type":"Services"
        }
    ],
    "sg:phone":"+61 3 9725 1777",
    "sg:postcode":"3136",
    "sg:province":"VIC",
    "sg:tags":[
        "motel",
        "hotel",
        "broker"
    ],
    "wof:name":"Conway Commercial",
    "wof:placetype":"venue"
},
  "geometry": {"coordinates":[145.28741455100001,-37.8162765503],"type":"Point"}
}