{
  "type": "Feature",
  "properties": {
    "iso:country":"AU",
    "sg:address":"8 Falls Pl",
    "sg:city":"Kellyville Ridge",
    "sg:classifiers":[
        {
            "category":"Professional",
            "subcategory":"Art Services",
            "type":"Services"
        }
    ],
    "sg:phone":"+61 402 226 022",
    "sg:postcode":"2155",
    "sg:province":"NSW",
    "sg:tags":[
        "picture",
        "frame",
        "framing"
    ],
    "wof:name":"Orlando Frames",
    "wof:placetype":"venue"
},
  "geometry": {"coordinates":[150.918243408,-33.7061462402],"type":"Point"}
}