{
  "type": "Feature",
  "properties": {
    "addr:full":"46 Elder St Alice Springs NT 0870",
    "addr:housenumber":"46",
    "addr:postcode":"nt 0870",
    "addr:street":"Elder St",
    "iso:country":"AU",
    "sg:address":"46 Elder St",
    "sg:city":"Alice Springs",
    "sg:classifiers":[
        {
            "category":"Wholesale",
            "subcategory":"Machinery & Supplies",
            "type":"Manufacturing & Wholesale Goods"
        }
    ],
    "sg:phone":"+61 8 8952 1132",
    "sg:postcode":"0870",
    "sg:province":"NT",
    "sg:tags":[
        "equipment",
        "hydraulic"
    ],
    "wof:name":"Enzed Service Centre Alice Springs",
    "wof:placetype":"venue"
},
  "geometry": {"coordinates":[133.86706543,-23.6957855225],"type":"Point"}
}