{
  "type": "Feature",
  "properties": {
    "addr:full":"1 Lemon Pl Mildura VIC 3500",
    "addr:housenumber":"1",
    "addr:postcode":"3500",
    "addr:street":"Lemon Pl",
    "iso:country":"AU",
    "sg:address":"1 Lemon Pl",
    "sg:city":"Mildura",
    "sg:classifiers":[
        {
            "category":"Retail",
            "subcategory":"Auto Repair",
            "type":"Services"
        }
    ],
    "sg:phone":"+61 3 5023 3714",
    "sg:postcode":"3500",
    "sg:province":"VIC",
    "sg:tags":[
        "repairer",
        "motor",
        "engineer"
    ],
    "wof:name":"Brake Muffler & Dynatune Pty Ltd",
    "wof:placetype":"venue"
},
  "geometry": {"coordinates":[142.16665649399999,-34.1864585876],"type":"Point"}
}