{
  "type": "Feature",
  "properties": {
    "iso:country":"AU",
    "sg:address":"180 Elizabeth St",
    "sg:city":"Hobart",
    "sg:classifiers":[
        {
            "category":"Organizations",
            "subcategory":"Community Association",
            "type":"Services"
        }
    ],
    "sg:phone":"+61 3 6231 5440",
    "sg:postcode":"7000",
    "sg:province":"TAS",
    "sg:tags":[
        "organisation",
        "family",
        "welfare"
    ],
    "wof:name":"Salvation Army",
    "wof:placetype":"venue"
},
  "geometry": {"coordinates":[147.32211303700001,-42.8791618347],"type":"Point"}
}