{
  "type": "Feature",
  "properties": {
    "iso:country":"AU",
    "sg:address":"Kalang Rd",
    "sg:city":"Elanora Heights",
    "sg:classifiers":[
        {
            "category":"Education",
            "subcategory":"Kindergarten",
            "type":"Public Place"
        }
    ],
    "sg:phone":"+61 2 9913 9423",
    "sg:postcode":"2101",
    "sg:province":"NSW",
    "sg:tags":[
        "pre-schools"
    ],
    "wof:name":"Elanora Heights Community Centre Kindergarten",
    "wof:placetype":"venue"
},
  "geometry": {"coordinates":[151.280136,-33.699894],"type":"Point"}
}