{
  "type": "Feature",
  "properties": {
    "iso:country":"AU",
    "sg:address":"105B Mornington Rd",
    "sg:city":"Mornington",
    "sg:classifiers":[
        {
            "category":"Wholesale",
            "subcategory":"Seafood",
            "type":"Manufacturing & Wholesale Goods"
        }
    ],
    "sg:phone":"+61 3 6244 7411",
    "sg:postcode":"7018",
    "sg:province":"TAS",
    "sg:tags":[
        "fish"
    ],
    "wof:name":"Sin-Tas Seafoods",
    "wof:placetype":"venue"
},
  "geometry": {"coordinates":[147.402709961,-42.861000061],"type":"Point"}
}