{
  "type": "Feature",
  "properties": {
    "addr:full":"29 Kremzow Rd Brendale QLD 4500",
    "addr:housenumber":"29",
    "addr:postcode":"4500",
    "addr:street":"Kremzow Rd",
    "iso:country":"AU",
    "sg:address":"29 Kremzow Rd",
    "sg:city":"Brendale",
    "sg:classifiers":[
        {
            "category":"Autos & Motor Vehicles",
            "subcategory":"Automobile Sales",
            "type":"Retail Goods"
        }
    ],
    "sg:phone":"+61 7 3881 3935",
    "sg:postcode":"4500",
    "sg:province":"QLD",
    "sg:tags":[
        "equipment",
        "trailer"
    ],
    "wof:name":"Victory Horse Floats & Goosenecks",
    "wof:placetype":"venue"
},
  "geometry": {"coordinates":[152.98786926299999,-27.3247623444],"type":"Point"}
}