{
  "type": "Feature",
  "properties": {
    "addr:full":"Ste1/ 2 James St Cairns North QLD 4870",
    "addr:housenumber":"2",
    "addr:postcode":"4870",
    "addr:street":"James St",
    "iso:country":"AU",
    "sg:address":"Ste1/ 2 James St",
    "sg:city":"Cairns North",
    "sg:classifiers":[
        {
            "category":"Real Estate",
            "subcategory":"Developer",
            "type":"Services"
        }
    ],
    "sg:phone":"+61 7 4041 6909",
    "sg:postcode":"4870",
    "sg:province":"QLD",
    "sg:tags":[
        "development"
    ],
    "wof:name":"Laurie Potter",
    "wof:placetype":"venue"
},
  "geometry": {"coordinates":[145.760498047,-16.9085769653],"type":"Point"}
}