{
  "type": "Feature",
  "properties": {
    "addr:full":"42- 54 Pacific Hwy Waitara NSW 2077",
    "addr:housenumber":"54",
    "addr:postcode":"2077",
    "addr:street":"Pacific Hwy",
    "iso:country":"AU",
    "sg:address":"42- 54 Pacific Hwy",
    "sg:city":"Waitara",
    "sg:classifiers":[
        {
            "category":"Autos & Motor Vehicles",
            "subcategory":"Automobile Sales",
            "type":"Retail Goods"
        }
    ],
    "sg:phone":"+61 2 9488 2188",
    "sg:postcode":"2077",
    "sg:province":"NSW",
    "sg:tags":[
        "car",
        "new"
    ],
    "wof:name":"Phil McCarroll Toyota",
    "wof:placetype":"venue"
},
  "geometry": {"coordinates":[151.10653686500001,-33.7117347717],"type":"Point"}
}