{
  "type": "Feature",
  "properties": {
    "iso:country":"AU",
    "sg:address":"Cnr Anzac Ave & Wattle Rd",
    "sg:city":"Rothwell",
    "sg:classifiers":[
        {
            "category":"Social Services",
            "subcategory":"Retirement Home",
            "type":"Services"
        }
    ],
    "sg:phone":"+61 1800 243 103",
    "sg:postcode":"4022",
    "sg:province":"QLD",
    "sg:tags":[
        "village"
    ],
    "wof:name":"Peninsula Park Retirement Estate",
    "wof:placetype":"venue"
},
  "geometry": {"coordinates":[153.050858,-27.215578],"type":"Point"}
}