{
  "type": "Feature",
  "properties": {
    "iso:country":"AU",
    "sg:address":"17 Laura St",
    "sg:city":"West Launceston",
    "sg:classifiers":[
        {
            "category":"Professional",
            "subcategory":"Detective & Security Services",
            "type":"Services"
        }
    ],
    "sg:phone":"+61 3 6334 6464",
    "sg:postcode":"7250",
    "sg:province":"TAS",
    "sg:tags":[
        "consultant",
        "system"
    ],
    "wof:name":"Stephen Oliver Electrical",
    "wof:placetype":"venue"
},
  "geometry": {"coordinates":[147.13418579099999,-41.4503059387],"type":"Point"}
}