{
  "type": "Feature",
  "properties": {
    "addr:full":"1678 Sandgate Rd Virginia QLD 4014",
    "addr:housenumber":"1678",
    "addr:postcode":"4014",
    "addr:street":"Sandgate Rd",
    "iso:country":"AU",
    "sg:address":"1678 Sandgate Rd",
    "sg:city":"Virginia",
    "sg:classifiers":[
        {
            "category":"Education",
            "subcategory":"School",
            "type":"Public Place"
        }
    ],
    "sg:phone":"+61 7 3621 6222",
    "sg:postcode":"4014",
    "sg:province":"QLD",
    "sg:tags":[
        "state",
        "except",
        "nsw"
    ],
    "wof:name":"Virginia Primary",
    "wof:placetype":"venue"
},
  "geometry": {"coordinates":[153.061309814,-27.3856334686],"type":"Point"}
}