{
  "type": "Feature",
  "properties": {
    "addr:full":"8 McGregor Pl Mudgee NSW 2850",
    "addr:housenumber":"8",
    "addr:postcode":"2850",
    "addr:street":"Mcgregor Pl",
    "iso:country":"AU",
    "sg:address":"8 McGregor Pl",
    "sg:city":"Mudgee",
    "sg:classifiers":[
        {
            "category":"Real Estate",
            "subcategory":"Architect",
            "type":"Services"
        }
    ],
    "sg:phone":"+61 2 6372 2556",
    "sg:postcode":"2850",
    "sg:province":"NSW",
    "sg:tags":[
        "building",
        "designer"
    ],
    "wof:name":"Building Designers Association - Central West Branch",
    "wof:placetype":"venue"
},
  "geometry": {"coordinates":[149.589935,-32.613235],"type":"Point"}
}