{
  "type": "Feature",
  "properties": {
    "iso:country":"AU",
    "sg:address":"169 Greens Rd",
    "sg:city":"Dandenong South",
    "sg:classifiers":[
        {
            "category":"Manufacturing",
            "subcategory":"Pottery",
            "type":"Manufacturing & Wholesale Goods"
        }
    ],
    "sg:phone":"+61 1300 727 678",
    "sg:postcode":"3164",
    "sg:province":"VIC",
    "wof:name":"Paddington Pots",
    "wof:placetype":"venue"
},
  "geometry": {"coordinates":[145.20668029800001,-38.0133857727],"type":"Point"}
}