{
  "type": "Feature",
  "properties": {
    "addr:full":"19 White Pl Williamstown VIC 3016",
    "addr:housenumber":"19",
    "addr:postcode":"3016",
    "addr:street":"White Pl",
    "iso:country":"AU",
    "sg:address":"19 White Pl",
    "sg:city":"Williamstown",
    "sg:classifiers":[
        {
            "category":"Professional",
            "subcategory":"Detective & Security Services",
            "type":"Services"
        }
    ],
    "sg:phone":"+61 413 536 807",
    "sg:postcode":"3016",
    "sg:province":"VIC",
    "sg:tags":[
        "consultant",
        "system"
    ],
    "wof:name":"Kilowatt Electrical Contractors Pty Ltd",
    "wof:placetype":"venue"
},
  "geometry": {"coordinates":[144.89002990700001,-37.8509407043],"type":"Point"}
}