{
  "type": "Feature",
  "properties": {
    "iso:country":"AU",
    "sg:address":"23 Armstrong St",
    "sg:city":"Toowoomba",
    "sg:classifiers":[
        {
            "category":"Retail",
            "subcategory":"Auto Rental",
            "type":"Services"
        }
    ],
    "sg:phone":"+61 7 4634 2387",
    "sg:postcode":"4350",
    "sg:province":"QLD",
    "sg:tags":[
        "camper-trailers",
        "caravan",
        "hire"
    ],
    "wof:name":"Kennedy Campers",
    "wof:placetype":"venue"
},
  "geometry": {"coordinates":[151.908737,-27.536486],"type":"Point"}
}