{
  "type": "Feature",
  "properties": {
    "addr:full":"25 Steel St Jesmond NSW 2299",
    "addr:housenumber":"25",
    "addr:postcode":"2299",
    "addr:street":"Steel St",
    "iso:country":"AU",
    "sg:address":"25 Steel St",
    "sg:city":"Jesmond",
    "sg:classifiers":[
        {
            "category":"Building & Trades",
            "subcategory":"Cleaning & Sanitation",
            "type":"Services"
        }
    ],
    "sg:phone":"+61 2 4952 7496",
    "sg:postcode":"2299",
    "sg:province":"NSW",
    "sg:tags":[
        "industrial",
        "commercial",
        "contractor"
    ],
    "wof:name":"My-Clean Cleaning & Property Maintenance",
    "wof:placetype":"venue"
},
  "geometry": {"coordinates":[151.697799683,-32.9056167603],"type":"Point"}
}