{
  "type": "Feature",
  "properties": {
    "addr:full":"6 Webb St Caulfield VIC 3162",
    "addr:housenumber":"6",
    "addr:postcode":"3162",
    "addr:street":"Webb St",
    "iso:country":"AU",
    "sg:address":"6 Webb St",
    "sg:city":"Caulfield",
    "sg:classifiers":[
        {
            "category":"Professional",
            "subcategory":"Employment Agencies",
            "type":"Services"
        }
    ],
    "sg:phone":"+61 3 9528 5797",
    "sg:postcode":"3162",
    "sg:province":"VIC",
    "sg:tags":[
        "entertainer",
        "agent"
    ],
    "wof:name":"Field Peter",
    "wof:placetype":"venue"
},
  "geometry": {"coordinates":[145.02586364699999,-37.8809394836],"type":"Point"}
}