{
  "type": "Feature",
  "properties": {
    "iso:country":"AU",
    "sg:address":"Shop 3, 108 Stuart St",
    "sg:city":"Mullumbimby",
    "sg:classifiers":[
        {
            "category":"Professional",
            "subcategory":"Computer Services",
            "type":"Services"
        }
    ],
    "sg:phone":"+61 2 6684 3399",
    "sg:postcode":"2482",
    "sg:province":"NSW",
    "sg:tags":[
        "repairs",
        "upgrade",
        "equipment"
    ],
    "wof:name":"Infologic Designs",
    "wof:placetype":"venue"
},
  "geometry": {"coordinates":[153.500823975,-28.5541343689],"type":"Point"}
}