{
  "type": "Feature",
  "properties": {
    "addr:full":"282 Beatty Rd Archerfield QLD 4108",
    "addr:housenumber":"282",
    "addr:postcode":"4108",
    "addr:street":"Beatty Rd",
    "iso:country":"AU",
    "sg:address":"282 Beatty Rd",
    "sg:city":"Archerfield",
    "sg:classifiers":[
        {
            "category":"Autos & Motor Vehicles",
            "subcategory":"Auto Supplies",
            "type":"Retail Goods"
        }
    ],
    "sg:phone":"+61 7 3853 1900",
    "sg:postcode":"4108",
    "sg:province":"QLD",
    "sg:tags":[
        "transmission",
        "equipment",
        "power"
    ],
    "wof:name":"SKF Bearing Supplies Pty Ltd",
    "wof:placetype":"venue"
},
  "geometry": {"coordinates":[153.015167236,-27.5678672791],"type":"Point"}
}