{
  "type": "Feature",
  "properties": {
    "iso:country":"AU",
    "sg:address":"PO Box 515",
    "sg:city":"Annerley",
    "sg:classifiers":[
        {
            "category":"Building & Trades",
            "subcategory":"Construction",
            "type":"Services"
        }
    ],
    "sg:phone":"+61 411 597 197",
    "sg:postcode":"4103",
    "sg:province":"QLD",
    "sg:tags":[
        "concrete",
        "contractor"
    ],
    "wof:name":"AAA Stencil Co",
    "wof:placetype":"venue"
},
  "geometry": {"coordinates":[153.031784058,-27.5140094757],"type":"Point"}
}