{
  "type": "Feature",
  "properties": {
    "addr:full":"Block A, Shop 1 Kotara Homebase Centre, 108 Park Avenue Kotara NSW 2289",
    "addr:housenumber":"1;108",
    "addr:postcode":"2289",
    "addr:street":"Park Avenue",
    "iso:country":"AU",
    "sg:address":"Block A, Shop 1 Kotara Homebase Centre, 108 Park Avenue",
    "sg:city":"Kotara",
    "sg:classifiers":[
        {
            "category":"Home & Garden",
            "subcategory":"Carpets & Floor Coverings",
            "type":"Retail Goods"
        }
    ],
    "sg:phone":"+61 2 4965 5233",
    "sg:postcode":"2289",
    "sg:province":"NSW",
    "sg:tags":[
        "mattress"
    ],
    "wof:name":"Forty Winks",
    "wof:placetype":"venue"
},
  "geometry": {"coordinates":[151.69630432100001,-32.9428291321],"type":"Point"}
}