{
  "type": "Feature",
  "properties": {
    "iso:country":"AU",
    "sg:address":"PO Box 224",
    "sg:city":"Mt Beauty",
    "sg:classifiers":[
        {
            "category":"Professional",
            "subcategory":"Art Services",
            "type":"Services"
        }
    ],
    "sg:phone":"+61 3 5754 4900",
    "sg:postcode":"3699",
    "sg:province":"VIC",
    "sg:tags":[
        "decorator",
        "painter"
    ],
    "wof:name":"Gardam L J & C F",
    "wof:placetype":"venue"
},
  "geometry": {"coordinates":[147.17123413100001,-36.7416343689],"type":"Point"}
}