{
  "type": "Feature",
  "properties": {
    "addr:full":"2 Station St Oakleigh VIC 3166",
    "addr:housenumber":"2",
    "addr:postcode":"3166",
    "addr:street":"Station St",
    "iso:country":"AU",
    "sg:address":"2 Station St",
    "sg:city":"Oakleigh",
    "sg:classifiers":[
        {
            "category":"Health Services",
            "subcategory":"Dentist",
            "type":"Services"
        }
    ],
    "sg:phone":"+61 3 9568 8142",
    "sg:postcode":"3166",
    "sg:province":"VIC",
    "wof:name":"Soh Selina Dr",
    "wof:placetype":"venue"
},
  "geometry": {"coordinates":[145.08888244600001,-37.8987197876],"type":"Point"}
}