{
  "type": "Feature",
  "properties": {
    "iso:country":"AU",
    "sg:address":"85c Beechboro Rd",
    "sg:city":"Bayswater",
    "sg:classifiers":[
        {
            "category":"Home & Garden",
            "subcategory":"Hardware",
            "type":"Retail Goods"
        }
    ],
    "sg:phone":"+61 8 9271 6122",
    "sg:postcode":"6053",
    "sg:province":"WA",
    "sg:tags":[
        "generating",
        "set",
        "generator"
    ],
    "wof:name":"Camden Sales & Service",
    "wof:placetype":"venue"
},
  "geometry": {"coordinates":[115.913513184,-31.9082660675],"type":"Point"}
}