{
  "type": "Feature",
  "properties": {
    "addr:full":"19 Stanley St Collinsville QLD 4804",
    "addr:housenumber":"19",
    "addr:postcode":"4804",
    "addr:street":"Stanley St",
    "iso:country":"AU",
    "sg:address":"19 Stanley St",
    "sg:city":"Collinsville",
    "sg:classifiers":[
        {
            "category":"Shopping",
            "subcategory":"Crafts & Fabrics",
            "type":"Retail Goods"
        }
    ],
    "sg:phone":"+61 7 4785 6266",
    "sg:postcode":"4804",
    "sg:province":"QLD",
    "sg:tags":[
        "draper"
    ],
    "wof:name":"Bowen Evans & Co",
    "wof:placetype":"venue"
},
  "geometry": {"coordinates":[147.84405517600001,-20.5542430878],"type":"Point"}
}