{
  "type": "Feature",
  "properties": {
    "addr:full":"49 Bair St Leongatha VIC 3953",
    "addr:housenumber":"49",
    "addr:postcode":"3953",
    "addr:street":"Bair St",
    "iso:country":"AU",
    "sg:address":"49 Bair St",
    "sg:city":"Leongatha",
    "sg:classifiers":[
        {
            "category":"Health Services",
            "subcategory":"Health Practitioner",
            "type":"Services"
        }
    ],
    "sg:phone":"+61 1300 550 351",
    "sg:postcode":"3953",
    "sg:province":"VIC",
    "sg:tags":[
        "physiotherapist"
    ],
    "wof:name":"Travis J Hampson",
    "wof:placetype":"venue"
},
  "geometry": {"coordinates":[145.947021484,-38.4776992798],"type":"Point"}
}