{
  "type": "Feature",
  "properties": {
    "iso:country":"AU",
    "sg:address":"3 Boneo Rd",
    "sg:city":"Rosebud",
    "sg:classifiers":[
        {
            "category":"Shopping",
            "subcategory":"Computers & Home Electronics",
            "type":"Retail Goods"
        }
    ],
    "sg:phone":"+61 3 5986 3134",
    "sg:postcode":"3939",
    "sg:province":"VIC",
    "sg:tags":[
        "equipment",
        "part",
        "electronic"
    ],
    "wof:name":"B & T Electronics",
    "wof:placetype":"venue"
},
  "geometry": {"coordinates":[144.88984680199999,-38.3605537415],"type":"Point"}
}