{
  "type": "Feature",
  "properties": {
    "addr:full":"95 Great Eastern Hwy Rivervale WA 6103",
    "addr:housenumber":"95",
    "addr:postcode":"6103",
    "addr:street":"Great Eastern Hwy",
    "iso:country":"AU",
    "sg:address":"95 Great Eastern Hwy",
    "sg:city":"Rivervale",
    "sg:classifiers":[
        {
            "category":"Autos & Motor Vehicles",
            "subcategory":"Auto Supplies",
            "type":"Retail Goods"
        }
    ],
    "sg:phone":"+61 8 9470 7600",
    "sg:postcode":"6103",
    "sg:province":"WA",
    "sg:tags":[
        "transmission",
        "equipment",
        "power"
    ],
    "wof:name":"SKF Bearing Supplies Pty Ltd",
    "wof:placetype":"venue"
},
  "geometry": {"coordinates":[115.91146850600001,-31.9541397095],"type":"Point"}
}