{
  "type": "Feature",
  "properties": {
    "iso:country":"AU",
    "sg:address":"U3/ 5 Daintree Pl",
    "sg:city":"West Gosford",
    "sg:classifiers":[
        {
            "category":"Retail",
            "subcategory":"Auto Repair",
            "type":"Services"
        }
    ],
    "sg:phone":"+61 409 908 216",
    "sg:postcode":"2250",
    "sg:province":"NSW",
    "sg:tags":[
        "beater",
        "painter",
        "panel"
    ],
    "wof:name":"Tyre Specialists The",
    "wof:placetype":"venue"
},
  "geometry": {"coordinates":[151.32696533199999,-33.4116134644],"type":"Point"}
}