{
  "type": "Feature",
  "properties": {
    "addr:full":"34 Wannan St Highett VIC 3190",
    "addr:housenumber":"34",
    "addr:postcode":"3190",
    "addr:street":"Wannan St",
    "iso:country":"AU",
    "sg:address":"34 Wannan St",
    "sg:city":"Highett",
    "sg:classifiers":[
        {
            "category":"Manufacturing",
            "subcategory":"Rubber & Plastics",
            "type":"Manufacturing & Wholesale Goods"
        }
    ],
    "sg:phone":"+61 3 9555 4616",
    "sg:postcode":"3190",
    "sg:province":"VIC",
    "sg:tags":[
        "product",
        "retail"
    ],
    "wof:name":"Retail Rubber",
    "wof:placetype":"venue"
},
  "geometry": {"coordinates":[145.05255126899999,-37.9472084045],"type":"Point"}
}