{
  "type": "Feature",
  "properties": {
    "addr:full":"PO Box 424 Donvale VIC 3111",
    "addr:postcode":"3111",
    "iso:country":"AU",
    "sg:address":"PO Box 424",
    "sg:city":"Donvale",
    "sg:classifiers":[
        {
            "category":"Banks & Credit Unions",
            "subcategory":"Bank",
            "type":"Services"
        }
    ],
    "sg:phone":"+61 403 533 657",
    "sg:postcode":"3111",
    "sg:province":"VIC",
    "sg:tags":[
        "broker",
        "mortgage"
    ],
    "wof:name":"Farrell Financial Solutions",
    "wof:placetype":"venue"
},
  "geometry": {"coordinates":[145.19453430199999,-37.7867012024],"type":"Point"}
}