{
  "type": "Feature",
  "properties": {
    "addr:full":"38 Warrigal Rd Mentone VIC 3194",
    "addr:housenumber":"38",
    "addr:postcode":"3194",
    "addr:street":"Warrigal Rd",
    "iso:country":"AU",
    "sg:address":"38 Warrigal Rd",
    "sg:city":"Mentone",
    "sg:classifiers":[
        {
            "category":"Health Services",
            "subcategory":"Health Practitioner",
            "type":"Services"
        }
    ],
    "sg:phone":"+61 3 9580 8513",
    "sg:postcode":"3194",
    "sg:province":"VIC",
    "sg:tags":[
        "psychologist"
    ],
    "wof:name":"Scannell Evelyn Dr",
    "wof:placetype":"venue"
},
  "geometry": {"coordinates":[145.07000732399999,-37.990070343],"type":"Point"}
}