{
  "type": "Feature",
  "properties": {
    "iso:country":"AU",
    "sg:address":"526 Toorak Rd",
    "sg:city":"Toorak",
    "sg:classifiers":[
        {
            "category":"Professional",
            "subcategory":"Art Services",
            "type":"Services"
        }
    ],
    "sg:phone":"+61 3 9826 8220",
    "sg:postcode":"3142",
    "sg:province":"VIC",
    "sg:tags":[
        "interior",
        "designer"
    ],
    "wof:name":"Design For Living",
    "wof:placetype":"venue"
},
  "geometry": {"coordinates":[145.017944336,-37.842250824],"type":"Point"}
}