{
  "type": "Feature",
  "properties": {
    "iso:country":"AU",
    "sg:address":"Cnr Corrina & Bradley Sts, Woden Plz",
    "sg:city":"Phillip",
    "sg:classifiers":[
        {
            "category":"Shopping",
            "subcategory":"Computers & Home Electronics",
            "type":"Retail Goods"
        }
    ],
    "sg:phone":"+61 2 6232 4974",
    "sg:postcode":"2606",
    "sg:province":"ACT",
    "sg:tags":[
        "equipment",
        "part",
        "electronic"
    ],
    "wof:name":"Dick Smith Powerhouse",
    "wof:placetype":"venue"
},
  "geometry": {"coordinates":[149.086959839,-35.3455085754],"type":"Point"}
}