{
  "type": "Feature",
  "properties": {
    "addr:full":"335 Asco Vale Rd Moonee Ponds VIC 3039",
    "addr:housenumber":"335",
    "addr:postcode":"3039",
    "addr:street":"Asco Vale Rd",
    "iso:country":"AU",
    "sg:address":"335 Asco Vale Rd",
    "sg:city":"Moonee Ponds",
    "sg:classifiers":[
        {
            "category":"Building & Trades",
            "subcategory":"Construction",
            "type":"Services"
        }
    ],
    "sg:phone":"+61 3 9370 8833",
    "sg:postcode":"3039",
    "sg:province":"VIC",
    "sg:tags":[
        "contractor"
    ],
    "wof:name":"Canteri Brothers Construction Pty Ltd",
    "wof:placetype":"venue"
},
  "geometry": {"coordinates":[144.92442299999999,-37.768261],"type":"Point"}
}