{
  "type": "Feature",
  "properties": {
    "addr:full":"85b St Bernards Rd Magill SA 5072",
    "addr:housenumber":"85b",
    "addr:postcode":"5072",
    "addr:street":"St Bernards Rd",
    "iso:country":"AU",
    "sg:address":"85b St Bernards Rd",
    "sg:city":"Magill",
    "sg:classifiers":[
        {
            "category":"Farming",
            "subcategory":"Fish & Marine Products",
            "type":"Manufacturing & Wholesale Goods"
        }
    ],
    "sg:phone":"+61 8 8364 1699",
    "sg:postcode":"5072",
    "sg:province":"SA",
    "sg:tags":[
        "organic"
    ],
    "wof:name":"Organically Grown",
    "wof:placetype":"venue"
},
  "geometry": {"coordinates":[138.675506592,-34.903377533],"type":"Point"}
}