{
  "type": "Feature",
  "properties": {
    "addr:full":"347 Bong Bong St Bowral NSW 2576",
    "addr:housenumber":"347",
    "addr:postcode":"2576",
    "addr:street":"Bong Bong St",
    "iso:country":"AU",
    "sg:address":"347 Bong Bong St",
    "sg:city":"Bowral",
    "sg:classifiers":[
        {
            "category":"Health Services",
            "subcategory":"Health Practitioner",
            "type":"Services"
        }
    ],
    "sg:phone":"+61 2 4861 6333",
    "sg:postcode":"2576",
    "sg:province":"NSW",
    "sg:tags":[
        "naturopath"
    ],
    "wof:name":"Chris Nuruddin Masuak",
    "wof:placetype":"venue"
},
  "geometry": {"coordinates":[150.417694092,-34.4804382324],"type":"Point"}
}