{
  "type": "Feature",
  "properties": {
    "iso:country":"AU",
    "sg:address":"11/ 97 Dorset Rd",
    "sg:city":"Ferntree Gully",
    "sg:classifiers":[
        {
            "category":"Retail",
            "subcategory":"Auto Repair",
            "type":"Services"
        }
    ],
    "sg:phone":"+61 3 9758 4795",
    "sg:postcode":"3156",
    "sg:province":"VIC",
    "sg:tags":[
        "transmission",
        "automotive",
        "car"
    ],
    "wof:name":"Ferntree Gully Automatic Transmission Specialists Pty Ltd",
    "wof:placetype":"venue"
},
  "geometry": {"coordinates":[145.28483581500001,-37.8741378784],"type":"Point"}
}