{
  "type": "Feature",
  "properties": {
    "addr:full":"685 Old Northern Rd Dural NSW 2158",
    "addr:housenumber":"685",
    "addr:postcode":"2158",
    "addr:street":"Old Northern Rd",
    "iso:country":"AU",
    "sg:address":"685 Old Northern Rd",
    "sg:city":"Dural",
    "sg:classifiers":[
        {
            "category":"Government",
            "subcategory":"Court House",
            "type":"Public Place"
        }
    ],
    "sg:phone":"+61 2 9651 6863",
    "sg:postcode":"2158",
    "sg:province":"NSW",
    "sg:tags":[
        "personal",
        "marriage",
        "family",
        "counselling"
    ],
    "wof:name":"Aarminique Counselling",
    "wof:placetype":"venue"
},
  "geometry": {"coordinates":[151.01902770999999,-33.6941299438],"type":"Point"}
}