{
  "type": "Feature",
  "properties": {
    "addr:full":"Variety Arcade (Near Millers) 48 Market St Merimbula NSW 2548",
    "addr:housenumber":"48",
    "addr:postcode":"2548",
    "addr:street":"Millers;Market St",
    "iso:country":"AU",
    "sg:address":"Variety Arcade (Near Millers) 48 Market St",
    "sg:city":"Merimbula",
    "sg:classifiers":[
        {
            "category":"Shopping",
            "subcategory":"Party Supplies",
            "type":"Retail Goods"
        }
    ],
    "sg:phone":"+61 2 6495 3605",
    "sg:postcode":"2548",
    "sg:province":"NSW",
    "wof:name":"The Party Shop",
    "wof:placetype":"venue"
},
  "geometry": {"coordinates":[149.91046142600001,-36.8885345459],"type":"Point"}
}