{
  "type": "Feature",
  "properties": {
    "iso:country":"AU",
    "sg:address":"U14/ 128 Canterbury Rd",
    "sg:city":"Kilsyth",
    "sg:classifiers":[
        {
            "category":"Cafe",
            "type":"Food & Drink"
        }
    ],
    "sg:phone":"+61 3 9761 4270",
    "sg:postcode":"3137",
    "sg:province":"VIC",
    "wof:name":"Milton Park Cafe",
    "wof:placetype":"venue"
},
  "geometry": {"coordinates":[145.31568908700001,-37.8186340332],"type":"Point"}
}