{
  "type": "Feature",
  "properties": {
    "iso:country":"AU",
    "sg:address":"16-24 Hannah St",
    "sg:city":"Beecroft",
    "sg:classifiers":[
        {
            "category":"Health Services",
            "subcategory":"Optometrist",
            "type":"Services"
        }
    ],
    "sg:phone":"+61 2 9980 5351",
    "sg:postcode":"2119",
    "sg:province":"NSW",
    "sg:website":"http://www.oaansw.com.au",
    "wof:name":"Harold Savitz Optometrist",
    "wof:placetype":"venue"
},
  "geometry": {"coordinates":[151.06486511200001,-33.7493400574],"type":"Point"}
}