{
  "type": "Feature",
  "properties": {
    "addr:full":"Lot 203 Stock Rd Parklands WA 6210",
    "addr:postcode":"6210",
    "addr:street":"Stock Rd",
    "iso:country":"AU",
    "sg:address":"Lot 203 Stock Rd",
    "sg:city":"Parklands",
    "sg:classifiers":[
        {
            "category":"Manufacturing",
            "subcategory":"Metals",
            "type":"Manufacturing & Wholesale Goods"
        }
    ],
    "sg:phone":"+61 8 9581 7625",
    "sg:postcode":"6210",
    "sg:province":"WA",
    "sg:tags":[
        "steel",
        "fabricator",
        "mfrs"
    ],
    "wof:name":"Longship Engineering",
    "wof:placetype":"venue"
},
  "geometry": {"coordinates":[115.78346999999999,-32.488911],"type":"Point"}
}