{
  "type": "Feature",
  "properties": {
    "iso:country":"AU",
    "sg:address":"\"Four Mile\" Woodstock Rd",
    "sg:city":"Woodstock",
    "sg:classifiers":[
        {
            "category":"Building & Trades",
            "subcategory":"Landscaping Services",
            "type":"Services"
        }
    ],
    "sg:phone":"+61 7 4778 8557",
    "sg:postcode":"4816",
    "sg:province":"QLD",
    "sg:tags":[
        "grazier"
    ],
    "wof:name":"Watson R A & D",
    "wof:placetype":"venue"
},
  "geometry": {"coordinates":[146.249863,-18.634216],"type":"Point"}
}