{
  "type": "Feature",
  "properties": {
    "iso:country":"AU",
    "sg:address":"Shop 4 Goldman La",
    "sg:city":"Double Bay",
    "sg:classifiers":[
        {
            "category":"Health Services",
            "subcategory":"Health Practitioner",
            "type":"Services"
        }
    ],
    "sg:phone":"+61 1300 134 327",
    "sg:postcode":"2028",
    "sg:province":"NSW",
    "sg:tags":[
        "audiologists"
    ],
    "wof:name":"Kelsey Bruce",
    "wof:placetype":"venue"
},
  "geometry": {"coordinates":[151.243087769,-33.8790588379],"type":"Point"}
}