{
  "type": "Feature",
  "properties": {
    "addr:full":"18 Tolmer Rd Woodside SA 5244",
    "addr:housenumber":"18",
    "addr:postcode":"5244",
    "addr:street":"Tolmer Rd",
    "iso:country":"AU",
    "sg:address":"18 Tolmer Rd",
    "sg:city":"Woodside",
    "sg:classifiers":[
        {
            "category":"Social Services",
            "subcategory":"Retirement Home",
            "type":"Services"
        }
    ],
    "sg:phone":"+61 8 8389 9656",
    "sg:postcode":"5244",
    "sg:province":"SA",
    "sg:tags":[
        "village"
    ],
    "wof:name":"KeyInvest Retirement Living",
    "wof:placetype":"venue"
},
  "geometry": {"coordinates":[138.88185119600001,-34.9549980164],"type":"Point"}
}