{
  "type": "Feature",
  "properties": {
    "addr:full":"347 Sheridan St Cairns North QLD 4870",
    "addr:housenumber":"347",
    "addr:postcode":"4870",
    "addr:street":"Sheridan St",
    "iso:country":"AU",
    "sg:address":"347 Sheridan St",
    "sg:city":"Cairns North",
    "sg:classifiers":[
        {
            "category":"Health Services",
            "subcategory":"Chiropractor",
            "type":"Services"
        }
    ],
    "sg:phone":"+61 7 4031 4173",
    "sg:postcode":"4870",
    "sg:province":"QLD",
    "wof:name":"Paul Mellish",
    "wof:placetype":"venue"
},
  "geometry": {"coordinates":[145.75852966299999,-16.9050064087],"type":"Point"}
}