{
  "type": "Feature",
  "properties": {
    "addr:full":"Lot 455, St Albans Rd Baldivis WA 6171",
    "addr:postcode":"6171",
    "addr:street":"St Albans Rd",
    "iso:country":"AU",
    "sg:address":"Lot 455, St Albans Rd",
    "sg:city":"Baldivis",
    "sg:classifiers":[
        {
            "category":"Home & Garden",
            "subcategory":"Garden Supply",
            "type":"Retail Goods"
        }
    ],
    "sg:phone":"+61 8 9524 1909",
    "sg:postcode":"6171",
    "sg:province":"WA",
    "sg:tags":[
        "equipment"
    ],
    "wof:name":"Earth And Stone Outdoor Centre",
    "wof:placetype":"venue"
},
  "geometry": {"coordinates":[115.84699999999999,-32.31263],"type":"Point"}
}