{
  "type": "Feature",
  "properties": {
    "iso:country":"AU",
    "sg:address":"13 Catamaran Drv",
    "sg:city":"Fountaindale",
    "sg:classifiers":[
        {
            "category":"Shopping",
            "subcategory":"Stationery & Office Supplies",
            "type":"Retail Goods"
        }
    ],
    "sg:phone":"+61 2 4388 6324",
    "sg:postcode":"2259",
    "sg:province":"NSW",
    "sg:tags":[
        "screen",
        "printing"
    ],
    "wof:name":"Impact Plastics Pty Ltd",
    "wof:placetype":"venue"
},
  "geometry": {"coordinates":[151.42291259800001,-33.1819992065],"type":"Point"}
}