{
  "type": "Feature",
  "properties": {
    "iso:country":"AU",
    "sg:address":"18 Madsen St",
    "sg:city":"Keperra",
    "sg:classifiers":[
        {
            "category":"Home & Garden",
            "subcategory":"Building Materials",
            "type":"Retail Goods"
        }
    ],
    "sg:phone":"+61 7 3355 2658",
    "sg:postcode":"4054",
    "sg:province":"QLD",
    "sg:tags":[
        "lawn",
        "cutting",
        "maintenance"
    ],
    "wof:name":"Matts Mowing",
    "wof:placetype":"venue"
},
  "geometry": {"coordinates":[152.95787048299999,-27.4070415497],"type":"Point"}
}