{
  "type": "Feature",
  "properties": {
    "addr:full":"17 Government Rd Barnsley NSW 2278",
    "addr:housenumber":"17",
    "addr:postcode":"2278",
    "addr:street":"Government Rd",
    "iso:country":"AU",
    "sg:address":"17 Government Rd",
    "sg:city":"Barnsley",
    "sg:classifiers":[
        {
            "category":"Manufacturing",
            "subcategory":"Leather Goods",
            "type":"Manufacturing & Wholesale Goods"
        }
    ],
    "sg:phone":"+61 2 4955 4294",
    "sg:postcode":"2278",
    "sg:province":"NSW",
    "sg:tags":[
        "wholesaler",
        "mfrs"
    ],
    "wof:name":"John The Cobbler",
    "wof:placetype":"venue"
},
  "geometry": {"coordinates":[151.58729600000001,-32.928608],"type":"Point"}
}