{
  "type": "Feature",
  "properties": {
    "addr:full":"16 Dorahy St Dundas NSW 2117",
    "addr:housenumber":"16",
    "addr:postcode":"2117",
    "addr:street":"Dorahy St",
    "iso:country":"AU",
    "sg:address":"16 Dorahy St",
    "sg:city":"Dundas",
    "sg:classifiers":[
        {
            "category":"Education",
            "subcategory":"University",
            "type":"Public Place"
        }
    ],
    "sg:phone":"+61 2 9638 3282",
    "sg:postcode":"2117",
    "sg:province":"NSW",
    "sg:tags":[
        "educational",
        "organisation",
        "cultural"
    ],
    "wof:name":"Institute For Type Development",
    "wof:placetype":"venue"
},
  "geometry": {"coordinates":[151.050323486,-33.8010025024],"type":"Point"}
}