{
  "type": "Feature",
  "properties": {
    "addr:full":"19 Bremer Pde Basin Pocket QLD 4305",
    "addr:housenumber":"19",
    "addr:postcode":"4305",
    "addr:street":"Bremer Pde",
    "iso:country":"AU",
    "sg:address":"19 Bremer Pde",
    "sg:city":"Basin Pocket",
    "sg:classifiers":[
        {
            "category":"Freight",
            "type":"Transportation"
        }
    ],
    "sg:phone":"+61 7 3281 7285",
    "sg:postcode":"4305",
    "sg:province":"QLD",
    "sg:tags":[
        "transport",
        "refrigerated"
    ],
    "wof:name":"Ribdeen Pty Ltd",
    "wof:placetype":"venue"
},
  "geometry": {"coordinates":[152.77180480999999,-27.5976600647],"type":"Point"}
}