{
  "type": "Feature",
  "properties": {
    "iso:country":"AU",
    "sg:address":"Factory 2, 73 Main Rd",
    "sg:city":"Clayton South",
    "sg:classifiers":[
        {
            "category":"Communications",
            "subcategory":"Film & Video Production",
            "type":"Services"
        }
    ],
    "sg:phone":"+61 3 9546 6072",
    "sg:postcode":"3169",
    "sg:province":"VIC",
    "sg:tags":[
        "fan",
        "blower"
    ],
    "wof:name":"Fan & Mechanical Services",
    "wof:placetype":"venue"
},
  "geometry": {"coordinates":[145.12673950199999,-37.9394416809],"type":"Point"}
}