{
  "type": "Feature",
  "properties": {
    "addr:full":"13 Laurence Rd Walliston WA 6076",
    "addr:housenumber":"13",
    "addr:postcode":"6076",
    "addr:street":"Laurence Rd",
    "iso:country":"AU",
    "sg:address":"13 Laurence Rd",
    "sg:city":"Walliston",
    "sg:classifiers":[
        {
            "category":"Building & Trades",
            "subcategory":"Cleaning & Sanitation",
            "type":"Services"
        }
    ],
    "sg:phone":"+61 8 9291 9806",
    "sg:postcode":"6076",
    "sg:province":"WA",
    "sg:tags":[
        "tank",
        "septic"
    ],
    "wof:name":"Kalamunda Septics",
    "wof:placetype":"venue"
},
  "geometry": {"coordinates":[116.073318481,-31.9943656921],"type":"Point"}
}