{
  "type": "Feature",
  "properties": {
    "addr:full":"5 Lind St Strathmore VIC 3041",
    "addr:housenumber":"5",
    "addr:postcode":"3041",
    "addr:street":"Lind St",
    "iso:country":"AU",
    "sg:address":"5 Lind St",
    "sg:city":"Strathmore",
    "sg:classifiers":[
        {
            "category":"Health Services",
            "subcategory":"Doctor",
            "type":"Services"
        }
    ],
    "sg:phone":"+61 3 9374 2161",
    "sg:postcode":"3041",
    "sg:province":"VIC",
    "sg:tags":[
        "medical",
        "practitioner"
    ],
    "wof:name":"Armour J M",
    "wof:placetype":"venue"
},
  "geometry": {"coordinates":[144.92291259800001,-37.7324256897],"type":"Point"}
}