{
  "type": "Feature",
  "properties": {
    "addr:full":"15 Eastern Rd Traralgon VIC 3844",
    "addr:housenumber":"15",
    "addr:postcode":"3844",
    "addr:street":"Eastern Rd",
    "iso:country":"AU",
    "sg:address":"15 Eastern Rd",
    "sg:city":"Traralgon",
    "sg:classifiers":[
        {
            "category":"Manufacturing",
            "subcategory":"Metals",
            "type":"Manufacturing & Wholesale Goods"
        }
    ],
    "sg:phone":"+61 3 5174 4299",
    "sg:postcode":"3844",
    "sg:province":"VIC",
    "sg:tags":[
        "sheet",
        "worker"
    ],
    "wof:name":"Traralgon Insulations and Sheet Metal Fabrication",
    "wof:placetype":"venue"
},
  "geometry": {"coordinates":[146.56246948200001,-38.1884498596],"type":"Point"}
}