{
  "type": "Feature",
  "properties": {
    "addr:full":"94a Prospect Rd Prospect SA 5082",
    "addr:housenumber":"94a",
    "addr:postcode":"5082",
    "addr:street":"Prospect Rd",
    "iso:country":"AU",
    "sg:address":"94a Prospect Rd",
    "sg:city":"Prospect",
    "sg:classifiers":[
        {
            "category":"Industrial Area",
            "type":"Public Place"
        }
    ],
    "sg:phone":"+61 8 8344 1128",
    "sg:postcode":"5082",
    "sg:province":"SA",
    "sg:tags":[
        "protective",
        "clothing"
    ],
    "wof:name":"A S Horne Consolidated P/L",
    "wof:placetype":"venue"
},
  "geometry": {"coordinates":[138.593994141,-34.8886451721],"type":"Point"}
}