{
  "type": "Feature",
  "properties": {
    "addr:full":"265 Shute Harbour Rd Airlie Beach QLD 4802",
    "addr:housenumber":"265",
    "addr:postcode":"4802",
    "addr:street":"Shute Harbour Rd",
    "iso:country":"AU",
    "sg:address":"265 Shute Harbour Rd",
    "sg:city":"Airlie Beach",
    "sg:classifiers":[
        {
            "category":"Travel",
            "subcategory":"Travel Agent",
            "type":"Entertainment"
        }
    ],
    "sg:phone":"+61 7 4946 6224",
    "sg:postcode":"4802",
    "sg:province":"QLD",
    "sg:tags":[
        "consultant"
    ],
    "wof:name":"Whitsunday Travel Centre",
    "wof:placetype":"venue"
},
  "geometry": {"coordinates":[148.717193603,-20.2680053711],"type":"Point"}
}