{
  "type": "Feature",
  "properties": {
    "addr:full":"235 Bridge Rd Richmond VIC 3121",
    "addr:housenumber":"235",
    "addr:postcode":"3121",
    "addr:street":"Bridge Rd",
    "iso:country":"AU",
    "sg:address":"235 Bridge Rd",
    "sg:city":"Richmond",
    "sg:classifiers":[
        {
            "category":"Shopping",
            "subcategory":"Clothing, Apparel, & Fashions",
            "type":"Retail Goods"
        }
    ],
    "sg:phone":"+61 3 9428 6329",
    "sg:postcode":"3121",
    "sg:province":"VIC",
    "sg:tags":[
        "lady",
        "wear"
    ],
    "wof:name":"Table 8 Clearance",
    "wof:placetype":"venue"
},
  "geometry": {"coordinates":[144.99752807600001,-37.8182563782],"type":"Point"}
}