{
  "type": "Feature",
  "properties": {
    "addr:full":"34 Moss St Slacks Creek QLD 4127",
    "addr:housenumber":"34",
    "addr:postcode":"4127",
    "addr:street":"Moss St",
    "iso:country":"AU",
    "sg:address":"34 Moss St",
    "sg:city":"Slacks Creek",
    "sg:classifiers":[
        {
            "category":"Government",
            "subcategory":"Fire Station",
            "type":"Public Place"
        }
    ],
    "sg:phone":"+61 7 3808 2073",
    "sg:postcode":"4127",
    "sg:province":"QLD",
    "sg:tags":[
        "spring",
        "shock",
        "absorbers",
        "suspension"
    ],
    "wof:name":"Pedders Suspension",
    "wof:placetype":"venue"
},
  "geometry": {"coordinates":[153.12071227999999,-27.62292099],"type":"Point"}
}