{
  "type": "Feature",
  "properties": {
    "addr:full":"Clyburn St Canowindra NSW 2804",
    "addr:postcode":"2804",
    "addr:street":"Clyburn St",
    "iso:country":"AU",
    "sg:address":"Clyburn St",
    "sg:city":"Canowindra",
    "sg:classifiers":[
        {
            "category":"Wholesale",
            "subcategory":"Fruits & Vegetables",
            "type":"Manufacturing & Wholesale Goods"
        }
    ],
    "sg:phone":"+61 2 6344 1504",
    "sg:postcode":"2804",
    "sg:province":"NSW",
    "sg:tags":[
        "produce",
        "grain"
    ],
    "wof:name":"Canowindra Produce Co Pty Ltd",
    "wof:placetype":"venue"
},
  "geometry": {"coordinates":[148.66557312,-33.5565338135],"type":"Point"}
}