{
  "type": "Feature",
  "properties": {
    "iso:country":"AU",
    "sg:address":"31 Atoll Crt",
    "sg:city":"Mullaloo",
    "sg:classifiers":[
        {
            "category":"Home & Garden",
            "subcategory":"Hardware",
            "type":"Retail Goods"
        }
    ],
    "sg:phone":"+61 8 9337 4344",
    "sg:postcode":"6027",
    "sg:province":"WA",
    "sg:tags":[
        "pipe",
        "fitting",
        "plastic"
    ],
    "wof:name":"Plasson Australia Pty Ltd",
    "wof:placetype":"venue"
},
  "geometry": {"coordinates":[115.73448944099999,-31.7777385712],"type":"Point"}
}