{
  "type": "Feature",
  "properties": {
    "iso:country":"AU",
    "sg:address":"2 Aurora St",
    "sg:city":"Eugowra",
    "sg:classifiers":[
        {
            "category":"Health Services",
            "subcategory":"Health Practitioner",
            "type":"Services"
        }
    ],
    "sg:phone":"+61 2 6859 2433",
    "sg:postcode":"2806",
    "sg:province":"NSW",
    "sg:tags":[
        "naturopath"
    ],
    "wof:name":"Crowe L",
    "wof:placetype":"venue"
},
  "geometry": {"coordinates":[148.377487183,-33.4304008484],"type":"Point"}
}