{
  "type": "Feature",
  "properties": {
    "addr:full":"142 George St Hornsby NSW 2077",
    "addr:housenumber":"142",
    "addr:postcode":"2077",
    "addr:street":"George St",
    "iso:country":"AU",
    "sg:address":"142 George St",
    "sg:city":"Hornsby",
    "sg:classifiers":[
        {
            "category":"Retail",
            "subcategory":"Auto Rental",
            "type":"Services"
        }
    ],
    "sg:phone":"+61 2 9450 7670",
    "sg:postcode":"2077",
    "sg:province":"NSW",
    "sg:tags":[
        "car",
        "hire",
        "minibus"
    ],
    "wof:name":"Europcar",
    "wof:placetype":"venue"
},
  "geometry": {"coordinates":[151.10052490199999,-33.6985015869],"type":"Point"}
}