{
  "type": "Feature",
  "properties": {
    "addr:full":"Unit 3, 1A McHenry St Murray Bridge SA 5253",
    "addr:housenumber":"1a",
    "addr:postcode":"5253",
    "addr:street":"Mchenry St",
    "iso:country":"AU",
    "sg:address":"Unit 3, 1A McHenry St",
    "sg:city":"Murray Bridge",
    "sg:classifiers":[
        {
            "category":"Shopping",
            "type":"Retail Goods"
        }
    ],
    "sg:phone":"+61 8 8532 6097",
    "sg:postcode":"5253",
    "sg:province":"SA",
    "sg:tags":[
        "new age",
        "product"
    ],
    "wof:name":"Natural Step &#039;n&#039; Stones",
    "wof:placetype":"venue"
},
  "geometry": {"coordinates":[139.27154540999999,-35.1201782227],"type":"Point"}
}