{
  "type": "Feature",
  "properties": {
    "iso:country":"AU",
    "sg:address":"5/ 11 Foden Ave",
    "sg:city":"Campbellfield",
    "sg:classifiers":[
        {
            "category":"Retail",
            "subcategory":"Auto Repair",
            "type":"Services"
        }
    ],
    "sg:phone":"+61 3 9305 3377",
    "sg:postcode":"3061",
    "sg:province":"VIC",
    "sg:tags":[
        "repairer",
        "motor",
        "engineer"
    ],
    "wof:name":"Northern City Car Care",
    "wof:placetype":"venue"
},
  "geometry": {"coordinates":[144.94459533700001,-37.6484985352],"type":"Point"}
}