{
  "type": "Feature",
  "properties": {
    "iso:country":"AU",
    "sg:address":"1 / 68 Shelley Drv",
    "sg:city":"Byron Bay",
    "sg:classifiers":[
        {
            "category":"Personal",
            "subcategory":"Massage",
            "type":"Services"
        }
    ],
    "sg:phone":"+61 416 219 973",
    "sg:postcode":"2481",
    "sg:province":"NSW",
    "sg:tags":[
        "therapy"
    ],
    "wof:name":"Harris, Kim",
    "wof:placetype":"venue"
},
  "geometry": {"coordinates":[153.618606567,-28.6557121277],"type":"Point"}
}