{
  "type": "Feature",
  "properties": {
    "iso:country":"AU",
    "sg:address":"24 Lords Rd",
    "sg:city":"Leichhardt",
    "sg:classifiers":[
        {
            "category":"Retail",
            "subcategory":"Auto Repair",
            "type":"Services"
        }
    ],
    "sg:phone":"+61 2 9560 7260",
    "sg:postcode":"2040",
    "sg:province":"NSW",
    "sg:tags":[
        "repairer",
        "motor",
        "engineer"
    ],
    "wof:name":"M A Motor Garage",
    "wof:placetype":"venue"
},
  "geometry": {"coordinates":[151.15649400000001,-33.887833],"type":"Point"}
}