{
  "type": "Feature",
  "properties": {
    "iso:country":"AU",
    "sg:address":"79 Princes Hwy",
    "sg:city":"Trafalgar",
    "sg:classifiers":[
        {
            "category":"Real Estate",
            "subcategory":"Real Estate Agent",
            "type":"Services"
        }
    ],
    "sg:phone":"+61 3 5633 1666",
    "sg:postcode":"3824",
    "sg:province":"VIC",
    "wof:name":"Jolly R R & H C (Real Estate) Pty Ltd",
    "wof:placetype":"venue"
},
  "geometry": {"coordinates":[146.15443400000001,-38.208179],"type":"Point"}
}