{
  "type": "Feature",
  "properties": {
    "addr:full":"Albury St Harden NSW 2587",
    "addr:postcode":"2587",
    "addr:street":"Albury St",
    "iso:country":"AU",
    "sg:address":"Albury St",
    "sg:city":"Harden",
    "sg:classifiers":[
        {
            "category":"Home & Garden",
            "subcategory":"Building Materials",
            "type":"Retail Goods"
        }
    ],
    "sg:phone":"+61 2 6386 4500",
    "sg:postcode":"2587",
    "sg:province":"NSW",
    "sg:tags":[
        "pre-mixed",
        "concrete"
    ],
    "wof:name":"Vision Concrete",
    "wof:placetype":"venue"
},
  "geometry": {"coordinates":[148.361618042,-34.5526275635],"type":"Point"}
}