{
  "type": "Feature",
  "properties": {
    "iso:country":"AU",
    "sg:address":"14 Roberts Rd",
    "sg:city":"Kunda Park",
    "sg:classifiers":[
        {
            "category":"Home & Garden",
            "subcategory":"Carpets & Floor Coverings",
            "type":"Retail Goods"
        }
    ],
    "sg:phone":"+61 7 5445 4454",
    "sg:postcode":"4556",
    "sg:province":"QLD",
    "sg:tags":[
        "tile",
        "wall"
    ],
    "wof:name":"Beaumont Tiles",
    "wof:placetype":"venue"
},
  "geometry": {"coordinates":[153.043457031,-26.6637191772],"type":"Point"}
}