{
  "type": "Feature",
  "properties": {
    "addr:full":"1 Jetty St Grange SA 5022",
    "addr:housenumber":"1",
    "addr:postcode":"5022",
    "addr:street":"Jetty St",
    "iso:country":"AU",
    "sg:address":"1 Jetty St",
    "sg:city":"Grange",
    "sg:classifiers":[
        {
            "category":"Cafe",
            "type":"Food & Drink"
        }
    ],
    "sg:phone":"+61 8 8235 9566",
    "sg:postcode":"5022",
    "sg:province":"SA",
    "wof:name":"Jetty Street Cafe",
    "wof:placetype":"venue"
},
  "geometry": {"coordinates":[138.490997314,-34.9025421143],"type":"Point"}
}