{
  "type": "Feature",
  "properties": {
    "addr:full":"135 Lawes St East Maitland NSW 2323",
    "addr:housenumber":"135",
    "addr:postcode":"2323",
    "addr:street":"Lawes St",
    "iso:country":"AU",
    "sg:address":"135 Lawes St",
    "sg:city":"East Maitland",
    "sg:classifiers":[
        {
            "category":"Health Services",
            "subcategory":"Dentist",
            "type":"Services"
        }
    ],
    "sg:phone":"+61 2 4933 7988",
    "sg:postcode":"2323",
    "sg:province":"NSW",
    "sg:tags":[
        "dental",
        "emergency"
    ],
    "wof:name":"Abrahams Alex",
    "wof:placetype":"venue"
},
  "geometry": {"coordinates":[151.590454102,-32.7518997192],"type":"Point"}
}