{
  "type": "Feature",
  "properties": {
    "addr:full":"5 Elfreda Ave Sorrento WA 6020",
    "addr:housenumber":"5",
    "addr:postcode":"6020",
    "addr:street":"Elfreda Ave",
    "iso:country":"AU",
    "sg:address":"5 Elfreda Ave",
    "sg:city":"Sorrento",
    "sg:classifiers":[
        {
            "category":"Professional",
            "subcategory":"Art Services",
            "type":"Services"
        }
    ],
    "sg:phone":"+61 8 9448 4058",
    "sg:postcode":"6020",
    "sg:province":"WA",
    "sg:tags":[
        "decorator",
        "painter"
    ],
    "wof:name":"G N & T Painting Services",
    "wof:placetype":"venue"
},
  "geometry": {"coordinates":[115.776611328,-31.8511104584],"type":"Point"}
}