{
  "type": "Feature",
  "properties": {
    "addr:full":"17 Maple Ave Mapleton QLD 4560",
    "addr:housenumber":"17",
    "addr:postcode":"4560",
    "addr:street":"Maple Ave",
    "iso:country":"AU",
    "sg:address":"17 Maple Ave",
    "sg:city":"Mapleton",
    "sg:classifiers":[
        {
            "category":"Building & Trades",
            "subcategory":"Construction",
            "type":"Services"
        }
    ],
    "sg:phone":"+61 7 5478 6544",
    "sg:postcode":"4560",
    "sg:province":"QLD",
    "sg:tags":[
        "contractor"
    ],
    "wof:name":"Wellgrove Pty Ltd",
    "wof:placetype":"venue"
},
  "geometry": {"coordinates":[152.87141418499999,-26.6343688965],"type":"Point"}
}