{
  "type": "Feature",
  "properties": {
    "iso:country":"AU",
    "sg:address":"36 Russell St",
    "sg:city":"South Brisbane",
    "sg:classifiers":[
        {
            "category":"Utilities",
            "subcategory":"Electric",
            "type":"Services"
        }
    ],
    "sg:phone":"+61 7 3846 2725",
    "sg:postcode":"4101",
    "sg:province":"QLD",
    "sg:tags":[
        "electrical",
        "contractor"
    ],
    "wof:name":"Tooma P.K.",
    "wof:placetype":"venue"
},
  "geometry": {"coordinates":[153.01373290999999,-27.4790287018],"type":"Point"}
}