{
  "type": "Feature",
  "properties": {
    "addr:full":"Shp 17/ 54-58 Cliff Rd North Wollongong NSW 2500",
    "addr:housenumber":"17 / 54-58",
    "addr:postcode":"2500",
    "addr:street":"Cliff Rd North",
    "iso:country":"AU",
    "sg:address":"Shp 17/ 54-58 Cliff Rd",
    "sg:city":"North Wollongong",
    "sg:classifiers":[
        {
            "category":"Restaurant",
            "type":"Food & Drink"
        }
    ],
    "sg:phone":"+61 2 4225 9888",
    "sg:postcode":"2500",
    "sg:province":"NSW",
    "wof:name":"Aqua Restaurant",
    "wof:placetype":"venue"
},
  "geometry": {"coordinates":[150.90223700000001,-34.418373],"type":"Point"}
}