{
  "type": "Feature",
  "properties": {
    "iso:country":"AU",
    "sg:address":"PO Box 83",
    "sg:city":"Hallam",
    "sg:classifiers":[
        {
            "category":"Building & Trades",
            "subcategory":"Construction",
            "type":"Services"
        }
    ],
    "sg:phone":"+61 3 9736 2448",
    "sg:postcode":"3803",
    "sg:province":"VIC",
    "sg:tags":[
        "insulation",
        "contractor"
    ],
    "wof:name":"Coat-O-Foam Pty Ltd",
    "wof:placetype":"venue"
},
  "geometry": {"coordinates":[145.269256592,-38.0042991638],"type":"Point"}
}