{
  "type": "Feature",
  "properties": {
    "addr:full":"174 Annesley St Echuca VIC 3564",
    "addr:housenumber":"174",
    "addr:postcode":"3564",
    "addr:street":"Annesley St",
    "iso:country":"AU",
    "sg:address":"174 Annesley St",
    "sg:city":"Echuca",
    "sg:classifiers":[
        {
            "category":"Professional",
            "subcategory":"Engineering",
            "type":"Services"
        }
    ],
    "sg:phone":"+61 3 5482 2155",
    "sg:postcode":"3564",
    "sg:province":"VIC",
    "sg:tags":[
        "refrigeration",
        "engineer"
    ],
    "wof:name":"Vincent's Retravision",
    "wof:placetype":"venue"
},
  "geometry": {"coordinates":[144.752029419,-36.1277580261],"type":"Point"}
}