{
  "type": "Feature",
  "properties": {
    "addr:full":"Castle Towers Shpng Cntr Castle St Castle Hill NSW 2154",
    "addr:postcode":"2154",
    "addr:street":"Castle St",
    "iso:country":"AU",
    "sg:address":"Castle Towers Shpng Cntr Castle St",
    "sg:city":"Castle Hill",
    "sg:classifiers":[
        {
            "category":"Shopping",
            "subcategory":"Mobile Phones",
            "type":"Retail Goods"
        }
    ],
    "sg:phone":"+61 2 9659 7777",
    "sg:postcode":"2154",
    "sg:province":"NSW",
    "sg:tags":[
        "telephone",
        "accessory"
    ],
    "wof:name":"Optus World",
    "wof:placetype":"venue"
},
  "geometry": {"coordinates":[151.00462341299999,-33.7314338684],"type":"Point"}
}