{
  "type": "Feature",
  "properties": {
    "iso:country":"AU",
    "sg:address":"Malvern Central School Gymnasium, Spring Rd",
    "sg:city":"Malvern",
    "sg:classifiers":[
        {
            "category":"Arena",
            "subcategory":"Sports Club",
            "type":"Entertainment"
        }
    ],
    "sg:phone":"+61 407 689 070",
    "sg:postcode":"3144",
    "sg:province":"VIC",
    "sg:tags":[
        "defence",
        "supply",
        "self",
        "instruction",
        "martial art"
    ],
    "wof:name":"Samurai Karate Malvern",
    "wof:placetype":"venue"
},
  "geometry": {"coordinates":[145.03474426299999,-37.8524894714],"type":"Point"}
}