{
  "type": "Feature",
  "properties": {
    "iso:country":"AU",
    "sg:address":"PO Box 7057",
    "sg:city":"GCMC Bundall BC",
    "sg:classifiers":[
        {
            "category":"Building & Trades",
            "subcategory":"Landscaping Services",
            "type":"Services"
        }
    ],
    "sg:phone":"+61 7 5532 1307",
    "sg:postcode":"4217",
    "sg:province":"QLD",
    "sg:tags":[
        "designer",
        "landscape",
        "contractor"
    ],
    "wof:name":"Australian Retaining Walls",
    "wof:placetype":"venue"
},
  "geometry": {"coordinates":[153.41252136200001,-28.0032291412],"type":"Point"}
}