{
  "type": "Feature",
  "properties": {
    "addr:full":"10- 12 Westwood Drv Deer Park VIC 3023",
    "addr:housenumber":"12",
    "addr:postcode":"3023",
    "addr:street":"Westwood Drv",
    "iso:country":"AU",
    "sg:address":"10- 12 Westwood Drv",
    "sg:city":"Deer Park",
    "sg:classifiers":[
        {
            "category":"Manufacturing",
            "subcategory":"Buildings",
            "type":"Manufacturing & Wholesale Goods"
        }
    ],
    "sg:phone":"+61 3 9363 0077",
    "sg:postcode":"3023",
    "sg:province":"VIC",
    "sg:tags":[
        "transportable",
        "domestic",
        "relocatable"
    ],
    "wof:name":"T P Transportable Homes",
    "wof:placetype":"venue"
},
  "geometry": {"coordinates":[144.755447,-37.760059],"type":"Point"}
}