{
  "type": "Feature",
  "properties": {
    "addr:full":"Shop 12 Shores Bay St Port Macquarie NSW 2444",
    "addr:housenumber":"shop 12",
    "addr:postcode":"2444",
    "addr:street":"Shores Bay St",
    "iso:country":"AU",
    "sg:address":"Shop 12 Shores Bay St",
    "sg:city":"Port Macquarie",
    "sg:classifiers":[
        {
            "category":"Retail",
            "subcategory":"Repair Shop",
            "type":"Services"
        }
    ],
    "sg:phone":"+61 2 6584 2433",
    "sg:postcode":"2444",
    "sg:province":"NSW",
    "sg:tags":[
        "machine",
        "repairs",
        "part",
        "dryer",
        "washing"
    ],
    "wof:name":"Midcoast Appliance Service",
    "wof:placetype":"venue"
},
  "geometry": {"coordinates":[152.89631700000001,-31.427816],"type":"Point"}
}