{
  "type": "Feature",
  "properties": {
    "addr:full":"4/45- 47 Nealdon Drv Meadowbrook QLD 4131",
    "addr:housenumber":"/;47",
    "addr:postcode":"4131",
    "addr:street":"45;Nealdon Drv",
    "iso:country":"AU",
    "sg:address":"4/45- 47 Nealdon Drv",
    "sg:city":"Meadowbrook",
    "sg:classifiers":[
        {
            "category":"Home & Garden",
            "subcategory":"Mobile Homes",
            "type":"Retail Goods"
        }
    ],
    "sg:phone":"+61 7 3805 4510",
    "sg:postcode":"4131",
    "sg:province":"QLD",
    "sg:tags":[
        "motor",
        "campervans"
    ],
    "wof:name":"Caravan Services (C.R.S.)",
    "wof:placetype":"venue"
},
  "geometry": {"coordinates":[153.134857178,-27.6665897369],"type":"Point"}
}