{
  "type": "Feature",
  "properties": {
    "iso:country":"AU",
    "sg:address":"Shp8/ 146 Waterloo Rd",
    "sg:city":"Greenacre",
    "sg:classifiers":[
        {
            "category":"Personal",
            "subcategory":"Beauty Salon",
            "type":"Services"
        }
    ],
    "sg:phone":"+61 2 9750 0036",
    "sg:postcode":"2190",
    "sg:province":"NSW",
    "sg:tags":[
        "hairdresser"
    ],
    "wof:name":"Emulsify",
    "wof:placetype":"venue"
},
  "geometry": {"coordinates":[151.058212,-33.901943],"type":"Point"}
}