{
  "type": "Feature",
  "properties": {
    "iso:country":"AU",
    "sg:address":"2 Seacrest Ave",
    "sg:city":"Blackmans Bay",
    "sg:classifiers":[
        {
            "category":"Building & Trades",
            "subcategory":"Construction",
            "type":"Services"
        }
    ],
    "sg:phone":"+61 3 6229 9892",
    "sg:postcode":"7052",
    "sg:province":"TAS",
    "sg:tags":[
        "contractor"
    ],
    "wof:name":"New Era Constructions",
    "wof:placetype":"venue"
},
  "geometry": {"coordinates":[147.323746,-43.010036],"type":"Point"}
}