{
  "type": "Feature",
  "properties": {
    "addr:full":"2/ 78 Railside Ave Bargo NSW 2574",
    "addr:housenumber":"/ 78",
    "addr:postcode":"2574",
    "addr:street":"Railside Ave",
    "iso:country":"AU",
    "sg:address":"2/ 78 Railside Ave",
    "sg:city":"Bargo",
    "sg:classifiers":[
        {
            "category":"Food & Beverages",
            "subcategory":"Supermarket",
            "type":"Retail Goods"
        }
    ],
    "sg:phone":"+61 2 4684 1671",
    "sg:postcode":"2574",
    "sg:province":"NSW",
    "sg:tags":[
        "grocery",
        "store"
    ],
    "wof:name":"IGA X-press",
    "wof:placetype":"venue"
},
  "geometry": {"coordinates":[150.580001831,-34.2924499512],"type":"Point"}
}