{
  "type": "Feature",
  "properties": {
    "addr:full":"U 41/ 2 Hoyle Ave Castle Hill NSW 2154",
    "addr:housenumber":"41 / 2",
    "addr:postcode":"2154",
    "addr:street":"Hoyle Ave",
    "iso:country":"AU",
    "sg:address":"U 41/ 2 Hoyle Ave",
    "sg:city":"Castle Hill",
    "sg:classifiers":[
        {
            "category":"Autos & Motor Vehicles",
            "subcategory":"Boat Sales",
            "type":"Retail Goods"
        }
    ],
    "sg:phone":"+61 2 9680 2577",
    "sg:postcode":"2154",
    "sg:province":"NSW",
    "sg:tags":[
        "yacht"
    ],
    "wof:name":"Walsh Craft",
    "wof:placetype":"venue"
},
  "geometry": {"coordinates":[150.98088073700001,-33.7322158813],"type":"Point"}
}