{
  "type": "Feature",
  "properties": {
    "iso:country":"AU",
    "sg:address":"Suite 3 Level 1/ 930 Anzac Pde",
    "sg:city":"Maroubra",
    "sg:classifiers":[
        {
            "category":"Sports & Exercise",
            "subcategory":"Gym",
            "type":"Entertainment"
        }
    ],
    "sg:phone":"+61 2 9314 3488",
    "sg:postcode":"2035",
    "sg:province":"NSW",
    "sg:tags":[
        "health",
        "fitness"
    ],
    "wof:name":"Just For Ladies",
    "wof:placetype":"venue"
},
  "geometry": {"coordinates":[151.24012756400001,-33.9430923462],"type":"Point"}
}