{
  "type": "Feature",
  "properties": {
    "addr:full":"631 High St Kew East VIC 3102",
    "addr:housenumber":"631",
    "addr:postcode":"3102",
    "addr:street":"High St",
    "iso:country":"AU",
    "sg:address":"631 High St",
    "sg:city":"Kew East",
    "sg:classifiers":[
        {
            "category":"Shopping",
            "subcategory":"Clothing, Apparel, & Fashions",
            "type":"Retail Goods"
        }
    ],
    "sg:phone":"+61 3 9859 0033",
    "sg:postcode":"3102",
    "sg:province":"VIC",
    "sg:tags":[
        "boutique"
    ],
    "wof:name":"Bonnie Lawrence",
    "wof:placetype":"venue"
},
  "geometry": {"coordinates":[145.05119323700001,-37.7989120483],"type":"Point"}
}