{
  "type": "Feature",
  "properties": {
    "addr:full":"PO Box 806 Goulburn NSW 2580",
    "addr:postcode":"2580",
    "iso:country":"AU",
    "sg:address":"PO Box 806",
    "sg:city":"Goulburn",
    "sg:classifiers":[
        {
            "category":"Professional",
            "subcategory":"Business Services",
            "type":"Services"
        }
    ],
    "sg:phone":"+61 2 4822 0009",
    "sg:postcode":"2580",
    "sg:province":"NSW",
    "sg:tags":[
        "drafting"
    ],
    "wof:name":"Acom Design",
    "wof:placetype":"venue"
},
  "geometry": {"coordinates":[149.71841430699999,-34.7470092773],"type":"Point"}
}