{
  "type": "Feature",
  "properties": {
    "addr:full":"Cnr Bunda & Hartley Sts Cairns QLD 4870",
    "addr:postcode":"4870",
    "iso:country":"AU",
    "sg:address":"Cnr Bunda & Hartley Sts",
    "sg:city":"Cairns",
    "sg:classifiers":[
        {
            "category":"Autos & Motor Vehicles",
            "subcategory":"Fuel & Gas Station",
            "type":"Retail Goods"
        }
    ],
    "sg:phone":"+61 7 4051 3329",
    "sg:postcode":"4870",
    "sg:province":"QLD",
    "sg:tags":[
        "petrol",
        "marketing",
        "pump",
        "equipment"
    ],
    "wof:name":"Meisenhelter & Co. Pty Ltd",
    "wof:placetype":"venue"
},
  "geometry": {"coordinates":[145.775512695,-16.9311943054],"type":"Point"}
}