{
  "type": "Feature",
  "properties": {
    "iso:country":"AU",
    "sg:address":"29 President Ave",
    "sg:city":"Kogarah",
    "sg:classifiers":[
        {
            "category":"Retail",
            "subcategory":"Auto Rental",
            "type":"Services"
        }
    ],
    "sg:phone":"+61 2 9553 8989",
    "sg:postcode":"2217",
    "sg:province":"NSW",
    "sg:tags":[
        "car",
        "hire",
        "minibus"
    ],
    "wof:name":"Exel Car Rental",
    "wof:placetype":"venue"
},
  "geometry": {"coordinates":[151.141159,-33.965],"type":"Point"}
}