{
  "type": "Feature",
  "properties": {
    "addr:full":"362-370 Cormack Road Wingfield SA 5013",
    "addr:postcode":"362-370;5013",
    "addr:street":"Cormack Road",
    "iso:country":"AU",
    "sg:address":"362-370 Cormack Road",
    "sg:city":"Wingfield",
    "sg:classifiers":[
        {
            "category":"Wholesale",
            "subcategory":"Drugs",
            "type":"Manufacturing & Wholesale Goods"
        }
    ],
    "sg:phone":"+61 8 8368 0700",
    "sg:postcode":"5013",
    "sg:province":"SA",
    "sg:tags":[
        "wholesaler",
        "pharmaceutical",
        "product",
        "mfrs"
    ],
    "wof:name":"Clifford Hallam Healthcare",
    "wof:placetype":"venue"
},
  "geometry": {"coordinates":[138.57301330600001,-34.8400001526],"type":"Point"}
}