{
  "type": "Feature",
  "properties": {
    "iso:country":"AU",
    "sg:address":"Clark Rd",
    "sg:city":"Toukley",
    "sg:classifiers":[
        {
            "category":"Building & Trades",
            "subcategory":"Pest Control",
            "type":"Services"
        }
    ],
    "sg:phone":"+61 2 4397 2129",
    "sg:postcode":"2263",
    "sg:province":"NSW",
    "sg:tags":[
        "breastfeeding",
        "support"
    ],
    "wof:name":"Australian Breastfeeding Association",
    "wof:placetype":"venue"
},
  "geometry": {"coordinates":[151.551895,-33.26495],"type":"Point"}
}