{
  "type": "Feature",
  "properties": {
    "addr:full":"24 Nanima Crs Wellington NSW 2820",
    "addr:housenumber":"24",
    "addr:postcode":"2820",
    "addr:street":"Nanima Crs",
    "iso:country":"AU",
    "sg:address":"24 Nanima Crs",
    "sg:city":"Wellington",
    "sg:classifiers":[
        {
            "category":"Retail",
            "subcategory":"Funeral Services",
            "type":"Services"
        }
    ],
    "sg:phone":"+61 2 6845 2322",
    "sg:postcode":"2820",
    "sg:province":"NSW",
    "sg:tags":[
        "director"
    ],
    "wof:name":"Wellington Funeral Home",
    "wof:placetype":"venue"
},
  "geometry": {"coordinates":[148.942962647,-32.5556411743],"type":"Point"}
}