{
  "type": "Feature",
  "properties": {
    "addr:full":"15 Wright St Wulguru QLD 4811",
    "addr:housenumber":"15",
    "addr:postcode":"4811",
    "addr:street":"Wright St",
    "iso:country":"AU",
    "sg:address":"15 Wright St",
    "sg:city":"Wulguru",
    "sg:classifiers":[
        {
            "category":"Retail",
            "subcategory":"Repair Shop",
            "type":"Services"
        }
    ],
    "sg:phone":"+61 408 787 674",
    "sg:postcode":"4811",
    "sg:province":"QLD",
    "sg:tags":[
        "upholsterer"
    ],
    "wof:name":"A1 Motor Cycle Seat Restoration",
    "wof:placetype":"venue"
},
  "geometry": {"coordinates":[146.81796299999999,-19.325834],"type":"Point"}
}