{
  "type": "Feature",
  "properties": {
    "iso:country":"AU",
    "sg:address":"31 Gracemar Ave",
    "sg:city":"Panania",
    "sg:classifiers":[
        {
            "category":"Building & Trades",
            "subcategory":"Construction",
            "type":"Services"
        }
    ],
    "sg:phone":"+61 2 9773 7777",
    "sg:postcode":"2213",
    "sg:province":"NSW",
    "sg:tags":[
        "fencing",
        "contractor"
    ],
    "wof:name":"Urban Fencing",
    "wof:placetype":"venue"
},
  "geometry": {"coordinates":[150.994064,-33.962936],"type":"Point"}
}