{
  "type": "Feature",
  "properties": {
    "addr:full":"7 Kingtel Pl Geebung QLD 4034",
    "addr:housenumber":"7",
    "addr:postcode":"4034",
    "addr:street":"Kingtel Pl",
    "iso:country":"AU",
    "sg:address":"7 Kingtel Pl",
    "sg:city":"Geebung",
    "sg:classifiers":[
        {
            "category":"Shopping",
            "subcategory":"Crafts & Fabrics",
            "type":"Retail Goods"
        }
    ],
    "sg:phone":"+61 7 3265 1688",
    "sg:postcode":"4034",
    "sg:province":"QLD",
    "sg:tags":[
        "material",
        "dress"
    ],
    "wof:name":"Remnant Shop Bramkos Warehouse",
    "wof:placetype":"venue"
},
  "geometry": {"coordinates":[153.051773,-27.366566],"type":"Point"}
}