{
  "type": "Feature",
  "properties": {
    "addr:full":"33 Cross St Double Bay NSW 2028",
    "addr:housenumber":"33",
    "addr:postcode":"2028",
    "addr:street":"Cross St",
    "iso:country":"AU",
    "sg:address":"33 Cross St",
    "sg:city":"Double Bay",
    "sg:classifiers":[
        {
            "category":"Shopping",
            "subcategory":"Clothing, Apparel, & Fashions",
            "type":"Retail Goods"
        }
    ],
    "sg:phone":"+61 2 9328 6766",
    "sg:postcode":"2028",
    "sg:province":"NSW",
    "sg:tags":[
        "lady",
        "wear"
    ],
    "wof:name":"Great Australian Jumper Company Pty Ltd",
    "wof:placetype":"venue"
},
  "geometry": {"coordinates":[151.243087769,-33.8760986328],"type":"Point"}
}