{
  "type": "Feature",
  "properties": {
    "addr:full":"32 Clementson St Broome WA 6725",
    "addr:housenumber":"32",
    "addr:postcode":"6725",
    "addr:street":"Clementson St",
    "iso:country":"AU",
    "sg:address":"32 Clementson St",
    "sg:city":"Broome",
    "sg:classifiers":[
        {
            "category":"Shopping",
            "subcategory":"Bicycles & Sporting Goods",
            "type":"Retail Goods"
        }
    ],
    "sg:phone":"+61 8 9192 1933",
    "sg:postcode":"6725",
    "sg:province":"WA",
    "sg:tags":[
        "chemical",
        "equipment",
        "pool",
        "swimming"
    ],
    "wof:name":"Cable Beach Pool Supplies & Maintenance",
    "wof:placetype":"venue"
},
  "geometry": {"coordinates":[122.222267151,-17.9715805054],"type":"Point"}
}