{
  "type": "Feature",
  "properties": {
    "iso:country":"AU",
    "sg:address":"PO Box 3013",
    "sg:city":"Newmarket",
    "sg:classifiers":[
        {
            "category":"Education",
            "subcategory":"Special Training",
            "type":"Public Place"
        }
    ],
    "sg:phone":"+61 412 930 457",
    "sg:postcode":"4051",
    "sg:province":"QLD",
    "sg:tags":[
        "development"
    ],
    "wof:name":"Sports Education & Learning Australia",
    "wof:placetype":"venue"
},
  "geometry": {"coordinates":[153.01040649399999,-27.4312591553],"type":"Point"}
}