{
  "type": "Feature",
  "properties": {
    "iso:country":"AU",
    "sg:address":"241 Highfield Rd",
    "sg:city":"Burwood",
    "sg:classifiers":[
        {
            "category":"Professional",
            "subcategory":"Accounting & Tax Preparation",
            "type":"Services"
        }
    ],
    "sg:phone":"+61 3 9889 0349",
    "sg:postcode":"3125",
    "sg:province":"VIC",
    "sg:tags":[
        "accountant",
        "auditor"
    ],
    "wof:name":"Marset Pty Ltd",
    "wof:placetype":"venue"
},
  "geometry": {"coordinates":[145.08238220199999,-37.8472747803],"type":"Point"}
}