{
  "type": "Feature",
  "properties": {
    "addr:full":"92 Wentworth Ave Surry Hills NSW 2010",
    "addr:housenumber":"92",
    "addr:postcode":"2010",
    "addr:street":"Wentworth Ave",
    "iso:country":"AU",
    "sg:address":"92 Wentworth Ave",
    "sg:city":"Surry Hills",
    "sg:classifiers":[
        {
            "category":"Shopping",
            "subcategory":"Optical Goods",
            "type":"Retail Goods"
        }
    ],
    "sg:phone":"+61 2 9211 1606",
    "sg:postcode":"2010",
    "sg:province":"NSW",
    "sg:tags":[
        "supply"
    ],
    "wof:name":"York Optical Company",
    "wof:placetype":"venue"
},
  "geometry": {"coordinates":[151.20941162099999,-33.8797264099],"type":"Point"}
}