{
  "type": "Feature",
  "properties": {
    "addr:full":"9 Kurda Pl Westminster WA 6061",
    "addr:housenumber":"9",
    "addr:postcode":"6061",
    "addr:street":"Kurda Pl",
    "iso:country":"AU",
    "sg:address":"9 Kurda Pl",
    "sg:city":"Westminster",
    "sg:classifiers":[
        {
            "category":"Mining & Drilling",
            "type":"Manufacturing & Wholesale Goods"
        }
    ],
    "sg:phone":"+61 8 9349 3879",
    "sg:postcode":"6061",
    "sg:province":"WA",
    "sg:tags":[
        "boring",
        "contractor"
    ],
    "wof:name":"Hall L",
    "wof:placetype":"venue"
},
  "geometry": {"coordinates":[115.83589172400001,-31.8729457855],"type":"Point"}
}