{
  "type": "Feature",
  "properties": {
    "iso:country":"AU",
    "sg:address":"23- 27 Langton St",
    "sg:city":"Garbutt",
    "sg:classifiers":[
        {
            "category":"Wholesale",
            "subcategory":"Machinery & Supplies",
            "type":"Manufacturing & Wholesale Goods"
        }
    ],
    "sg:phone":"+61 7 4779 0077",
    "sg:postcode":"4814",
    "sg:province":"QLD",
    "sg:tags":[
        "agricultural"
    ],
    "wof:name":"Primemovers (NQ) Pty Ltd",
    "wof:placetype":"venue"
},
  "geometry": {"coordinates":[146.771637,-19.268526],"type":"Point"}
}