{
  "type": "Feature",
  "properties": {
    "addr:full":"PO Box 2341 Mansfield Delivery Centre QLD 4122",
    "addr:postcode":"4122",
    "iso:country":"AU",
    "sg:address":"PO Box 2341",
    "sg:city":"Mansfield Delivery Centre",
    "sg:classifiers":[
        {
            "category":"Health Services",
            "subcategory":"Health Practitioner",
            "type":"Services"
        }
    ],
    "sg:phone":"+61 410 572 045",
    "sg:postcode":"4122",
    "sg:province":"QLD",
    "sg:tags":[
        "reiki"
    ],
    "wof:name":"Boris Sefer- Accredited Practitioner",
    "wof:placetype":"venue"
},
  "geometry": {"coordinates":[153.110473633,-27.5458850861],"type":"Point"}
}