{
  "type": "Feature",
  "properties": {
    "addr:full":"16 Penda Crt Cabarita Beach NSW 2488",
    "addr:housenumber":"16",
    "addr:postcode":"2488",
    "addr:street":"Penda Crt",
    "iso:country":"AU",
    "sg:address":"16 Penda Crt",
    "sg:city":"Cabarita Beach",
    "sg:classifiers":[
        {
            "category":"Building & Trades",
            "subcategory":"Construction",
            "type":"Services"
        }
    ],
    "sg:phone":"+61 412 757 778",
    "sg:postcode":"2488",
    "sg:province":"NSW",
    "sg:tags":[
        "renovation",
        "alterations",
        "extension",
        "contractor"
    ],
    "wof:name":"Van De Wakker Ken",
    "wof:placetype":"venue"
},
  "geometry": {"coordinates":[153.56471300000001,-28.338602],"type":"Point"}
}