{
  "type": "Feature",
  "properties": {
    "iso:country":"AU",
    "sg:address":"Montebello Apiaries RSD 67 Flinders Chase SE",
    "sg:city":"Kingscote",
    "sg:classifiers":[
        {
            "category":"Food & Beverages",
            "subcategory":"Farmers Market",
            "type":"Retail Goods"
        }
    ],
    "sg:phone":"+61 8 8559 7228",
    "sg:postcode":"5223",
    "sg:province":"SA",
    "sg:tags":[
        "beekeeper"
    ],
    "wof:name":"Kangaroo Island Honey",
    "wof:placetype":"venue"
},
  "geometry": {"coordinates":[137.62710571299999,-35.6572952271],"type":"Point"}
}