{
  "type": "Feature",
  "properties": {
    "iso:country":"AU",
    "sg:address":"4 Pavilion Pl",
    "sg:city":"Cardiff",
    "sg:classifiers":[
        {
            "category":"Manufacturing",
            "subcategory":"Tools & Machinery",
            "type":"Manufacturing & Wholesale Goods"
        }
    ],
    "sg:phone":"+61 2 4956 6334",
    "sg:postcode":"2285",
    "sg:province":"NSW",
    "sg:tags":[
        "fastener",
        "industrial"
    ],
    "wof:name":"Mowing Fasteners",
    "wof:placetype":"venue"
},
  "geometry": {"coordinates":[151.644363403,-32.9403991699],"type":"Point"}
}