{
  "type": "Feature",
  "properties": {
    "addr:full":"45 Beecroft Rd Epping NSW 2121",
    "addr:housenumber":"45",
    "addr:postcode":"2121",
    "addr:street":"Beecroft Rd",
    "iso:country":"AU",
    "sg:address":"45 Beecroft Rd",
    "sg:city":"Epping",
    "sg:classifiers":[
        {
            "category":"Fast Food",
            "type":"Food & Drink"
        }
    ],
    "sg:phone":"+61 2 9876 2648",
    "sg:postcode":"2121",
    "sg:province":"NSW",
    "sg:tags":[
        "away",
        "take"
    ],
    "wof:name":"Epping Seafood",
    "wof:placetype":"venue"
},
  "geometry": {"coordinates":[151.08172607399999,-33.7732887268],"type":"Point"}
}