{
  "type": "Feature",
  "properties": {
    "addr:full":"1 Link Rd Rosebery NSW 2018",
    "addr:housenumber":"1",
    "addr:postcode":"2018",
    "addr:street":"Link Rd",
    "iso:country":"AU",
    "sg:address":"1 Link Rd",
    "sg:city":"Rosebery",
    "sg:classifiers":[
        {
            "category":"Autos & Motor Vehicles",
            "subcategory":"Automobile Sales",
            "type":"Retail Goods"
        }
    ],
    "sg:phone":"+61 2 9315 9600",
    "sg:postcode":"2018",
    "sg:province":"NSW",
    "sg:tags":[
        "car",
        "new"
    ],
    "wof:name":"Sydney City Kia",
    "wof:placetype":"venue"
},
  "geometry": {"coordinates":[151.21191406200001,-33.9112586975],"type":"Point"}
}