{
  "type": "Feature",
  "properties": {
    "addr:full":"Level 7, 191 Clarence St Sydney NSW 2000",
    "addr:housenumber":"191",
    "addr:postcode":"2000",
    "addr:street":"Clarence St",
    "iso:country":"AU",
    "sg:address":"Level 7, 191 Clarence St",
    "sg:city":"Sydney",
    "sg:classifiers":[
        {
            "category":"Professional",
            "subcategory":"Employment Agencies",
            "type":"Services"
        }
    ],
    "sg:phone":"+61 2 9278 5100",
    "sg:postcode":"2000",
    "sg:province":"NSW",
    "sg:website":"http://www.inplacerecruitment.com.au",
    "wof:name":"inPlace Recruitment",
    "wof:placetype":"venue"
},
  "geometry": {"coordinates":[151.20521545400001,-33.8693466187],"type":"Point"}
}