{
  "type": "Feature",
  "properties": {
    "addr:full":"U1/ 33 Avalon Pde Avalon NSW 2107",
    "addr:housenumber":"33",
    "addr:postcode":"2107",
    "addr:street":"U1 /;Avalon Pde",
    "iso:country":"AU",
    "sg:address":"U1/ 33 Avalon Pde",
    "sg:city":"Avalon",
    "sg:classifiers":[
        {
            "category":"Building & Trades",
            "subcategory":"Landscaping Services",
            "type":"Services"
        }
    ],
    "sg:phone":"+61 2 9973 3797",
    "sg:postcode":"2107",
    "sg:province":"NSW",
    "sg:tags":[
        "designer",
        "landscape",
        "contractor"
    ],
    "wof:name":"Volker Klemm Landscape Design & Construction",
    "wof:placetype":"venue"
},
  "geometry": {"coordinates":[151.32933044399999,-33.6365585327],"type":"Point"}
}