{
  "type": "Feature",
  "properties": {
    "addr:full":"35 Mary St Hawthorn VIC 3122",
    "addr:housenumber":"35",
    "addr:postcode":"3122",
    "addr:street":"Mary St",
    "iso:country":"AU",
    "sg:address":"35 Mary St",
    "sg:city":"Hawthorn",
    "sg:classifiers":[
        {
            "category":"Health Services",
            "subcategory":"Doctor",
            "type":"Services"
        }
    ],
    "sg:phone":"+61 3 9818 1875",
    "sg:postcode":"3122",
    "sg:province":"VIC",
    "sg:tags":[
        "medical",
        "practitioner"
    ],
    "wof:name":"Harvey Jenny Dr",
    "wof:placetype":"venue"
},
  "geometry": {"coordinates":[145.03187560999999,-37.8176040649],"type":"Point"}
}