{
  "type": "Feature",
  "properties": {
    "addr:full":"7 Ballantyne Rd Kewdale WA 6105",
    "addr:housenumber":"7",
    "addr:postcode":"6105",
    "addr:street":"Ballantyne Rd",
    "iso:country":"AU",
    "sg:address":"7 Ballantyne Rd",
    "sg:city":"Kewdale",
    "sg:classifiers":[
        {
            "category":"Home & Garden",
            "subcategory":"Hardware",
            "type":"Retail Goods"
        }
    ],
    "sg:phone":"+61 8 9458 4588",
    "sg:postcode":"6105",
    "sg:province":"WA",
    "sg:tags":[
        "nut",
        "bolt"
    ],
    "wof:name":"Boltmakers W.A.",
    "wof:placetype":"venue"
},
  "geometry": {"coordinates":[115.93675994900001,-31.9854431152],"type":"Point"}
}