{
  "type": "Feature",
  "properties": {
    "addr:full":"Suite 8, Level 8, 229 -231 Macquarie Street Sydney NSW 2000",
    "addr:housenumber":"229 -231",
    "addr:postcode":"2000",
    "addr:street":"Level;Macquarie Street",
    "iso:country":"AU",
    "sg:address":"Suite 8, Level 8, 229",
    "sg:city":"-231 Macquarie Street Sydney",
    "sg:classifiers":[
        {
            "category":"Professional",
            "subcategory":"Accounting & Tax Preparation",
            "type":"Services"
        }
    ],
    "sg:phone":"+61 405 267 868",
    "sg:postcode":"2000",
    "sg:province":"NSW",
    "sg:tags":[
        "accountant",
        "auditor"
    ],
    "wof:name":"Firm Financial & Accounting",
    "wof:placetype":"venue"
},
  "geometry": {"coordinates":[151.21191406200001,-33.8690872192],"type":"Point"}
}