{
  "type": "Feature",
  "properties": {
    "iso:country":"AU",
    "sg:address":"30 Gibbs Rd",
    "sg:city":"Yarra Glen",
    "sg:classifiers":[
        {
            "category":"Landmark",
            "subcategory":"Scenic View",
            "type":"Public Place"
        }
    ],
    "sg:phone":"+61 411 511 999",
    "sg:postcode":"3775",
    "sg:province":"VIC",
    "sg:tags":[
        "staircase",
        "handrail"
    ],
    "wof:name":"A 1 Staircase & Building Services",
    "wof:placetype":"venue"
},
  "geometry": {"coordinates":[145.377945,-37.635498],"type":"Point"}
}