{
  "type": "Feature",
  "properties": {
    "addr:full":"Rural Drv Sandgate NSW 2304",
    "addr:postcode":"2304",
    "addr:street":"Rural Drv",
    "iso:country":"AU",
    "sg:address":"Rural Drv",
    "sg:city":"Sandgate",
    "sg:classifiers":[
        {
            "category":"Food & Beverages",
            "subcategory":"Fruits & Vegetables",
            "type":"Retail Goods"
        }
    ],
    "sg:phone":"+61 2 4923 3800",
    "sg:postcode":"2304",
    "sg:province":"NSW",
    "sg:tags":[
        "wholesale"
    ],
    "wof:name":"Select Fruit Distributors",
    "wof:placetype":"venue"
},
  "geometry": {"coordinates":[151.706863403,-32.8721199036],"type":"Point"}
}