{
  "type": "Feature",
  "properties": {
    "addr:full":"Lot 19 South Trees Drv Gladstone QLD 4680",
    "addr:postcode":"4680",
    "addr:street":"South Trees Drv",
    "iso:country":"AU",
    "sg:address":"Lot 19 South Trees Drv",
    "sg:city":"Gladstone",
    "sg:classifiers":[
        {
            "category":"Utilities",
            "subcategory":"Recycling",
            "type":"Services"
        }
    ],
    "sg:phone":"+61 408 458 923",
    "sg:postcode":"4680",
    "sg:province":"QLD",
    "wof:name":"Hancock R L & D L",
    "wof:placetype":"venue"
},
  "geometry": {"coordinates":[151.289352417,-23.9026546478],"type":"Point"}
}