{
  "type": "Feature",
  "properties": {
    "addr:full":"93 Gurwood St Wagga Wagga NSW 2650",
    "addr:housenumber":"93",
    "addr:postcode":"2650",
    "addr:street":"Gurwood St",
    "iso:country":"AU",
    "sg:address":"93 Gurwood St",
    "sg:city":"Wagga Wagga",
    "sg:classifiers":[
        {
            "category":"Government",
            "subcategory":"Court House",
            "type":"Public Place"
        }
    ],
    "sg:phone":"+61 2 6921 7266",
    "sg:postcode":"2650",
    "sg:province":"NSW",
    "sg:tags":[
        "personal",
        "marriage",
        "family",
        "counselling"
    ],
    "wof:name":"Dynamic Counselling Services",
    "wof:placetype":"venue"
},
  "geometry": {"coordinates":[147.36985778799999,-35.1064567566],"type":"Point"}
}