{
  "type": "Feature",
  "properties": {
    "iso:country":"AU",
    "sg:address":"16 Irwin St",
    "sg:city":"Perth",
    "sg:classifiers":[
        {
            "category":"Cafe",
            "type":"Food & Drink"
        }
    ],
    "sg:phone":"+61 8 9221 5807",
    "sg:postcode":"6000",
    "sg:province":"WA",
    "wof:name":"Jules Coffee House",
    "wof:placetype":"venue"
},
  "geometry": {"coordinates":[115.863372803,-31.9562931061],"type":"Point"}
}