{
  "type": "Feature",
  "properties": {
    "addr:full":"Hunt Road, PO Box 86 Mt Barker SA 5251",
    "addr:postcode":"5251",
    "addr:street":"Hunt Road",
    "iso:country":"AU",
    "sg:address":"Hunt Road, PO Box 86",
    "sg:city":"Mt Barker",
    "sg:classifiers":[
        {
            "category":"Home & Garden",
            "subcategory":"Garden Supply",
            "type":"Retail Goods"
        }
    ],
    "sg:phone":"+61 8 8391 1880",
    "sg:postcode":"5251",
    "sg:province":"SA",
    "sg:tags":[
        "equipment",
        "hydroponics"
    ],
    "wof:name":"Hydro Heaven",
    "wof:placetype":"venue"
},
  "geometry": {"coordinates":[138.85289001500001,-35.0617103577],"type":"Point"}
}