{
  "type": "Feature",
  "properties": {
    "iso:country":"AU",
    "sg:address":"839 Barkley St",
    "sg:city":"Mt Pleasant",
    "sg:classifiers":[
        {
            "category":"Personal",
            "type":"Services"
        }
    ],
    "sg:phone":"+61 408 509 936",
    "sg:postcode":"3350",
    "sg:province":"VIC",
    "sg:tags":[
        "wallpapering",
        "wallcovering"
    ],
    "wof:name":"Esposito Painting& Decorating",
    "wof:placetype":"venue"
},
  "geometry": {"coordinates":[143.852615,-37.577831],"type":"Point"}
}