{
  "type": "Feature",
  "properties": {
    "iso:country":"AU",
    "sg:address":"15 Porters Rd",
    "sg:city":"Wesburn",
    "sg:classifiers":[
        {
            "category":"Building & Trades",
            "subcategory":"Landscaping Services",
            "type":"Services"
        }
    ],
    "sg:phone":"+61 3 5967 1212",
    "sg:postcode":"3799",
    "sg:province":"VIC",
    "sg:tags":[
        "slashing",
        "contractor"
    ],
    "wof:name":"Yarra Ranges Contracting Pty Ltd",
    "wof:placetype":"venue"
},
  "geometry": {"coordinates":[145.64451599099999,-37.7734489441],"type":"Point"}
}