{
  "type": "Feature",
  "properties": {
    "addr:full":"4/ 63 Donald St Nelson Bay NSW 2315",
    "addr:housenumber":"/ 63",
    "addr:postcode":"2315",
    "addr:street":"Donald St",
    "iso:country":"AU",
    "sg:address":"4/ 63 Donald St",
    "sg:city":"Nelson Bay",
    "sg:classifiers":[
        {
            "category":"Real Estate",
            "subcategory":"Surveying",
            "type":"Services"
        }
    ],
    "sg:phone":"+61 2 4981 3501",
    "sg:postcode":"2315",
    "sg:province":"NSW",
    "sg:tags":[
        "surveyor",
        "land"
    ],
    "wof:name":"Fagan Mather Duggan Pty Ltd",
    "wof:placetype":"venue"
},
  "geometry": {"coordinates":[152.14207500000001,-32.721828],"type":"Point"}
}