{
  "type": "Feature",
  "properties": {
    "iso:country":"AU",
    "sg:address":"10 Church St",
    "sg:city":"Kingston",
    "sg:classifiers":[
        {
            "category":"Professional",
            "type":"Services"
        }
    ],
    "sg:phone":"+61 419 773 374",
    "sg:postcode":"7050",
    "sg:province":"TAS",
    "sg:tags":[
        "courier"
    ],
    "wof:name":"Apace Couriers",
    "wof:placetype":"venue"
},
  "geometry": {"coordinates":[147.311966,-42.977013],"type":"Point"}
}