{
  "type": "Feature",
  "properties": {
    "addr:full":"18 Bowden St Ryde NSW 2112",
    "addr:housenumber":"18",
    "addr:postcode":"2112",
    "addr:street":"Bowden St",
    "iso:country":"AU",
    "sg:address":"18 Bowden St",
    "sg:city":"Ryde",
    "sg:classifiers":[
        {
            "category":"Retail",
            "subcategory":"Auto Repair",
            "type":"Services"
        }
    ],
    "sg:phone":"+61 419 227 167",
    "sg:postcode":"2112",
    "sg:province":"NSW",
    "sg:tags":[
        "repairer",
        "motor",
        "engineer"
    ],
    "wof:name":"Mechani-Calls",
    "wof:placetype":"venue"
},
  "geometry": {"coordinates":[151.098098755,-33.8120918274],"type":"Point"}
}