{
  "type": "Feature",
  "properties": {
    "iso:country":"AU",
    "sg:address":"2 Dean Rd",
    "sg:city":"Eumundi",
    "sg:classifiers":[
        {
            "category":"Shopping",
            "subcategory":"Party Supplies",
            "type":"Retail Goods"
        }
    ],
    "sg:phone":"+61 7 5449 1991",
    "sg:postcode":"4562",
    "sg:province":"QLD",
    "sg:tags":[
        "hire",
        "costume"
    ],
    "wof:name":"Elisabeths Hiring Service",
    "wof:placetype":"venue"
},
  "geometry": {"coordinates":[152.99092102,-26.4704875946],"type":"Point"}
}