{
  "type": "Feature",
  "properties": {
    "addr:full":"Federal St Culcairn NSW 2660",
    "addr:postcode":"2660",
    "addr:street":"Federal St",
    "iso:country":"AU",
    "sg:address":"Federal St",
    "sg:city":"Culcairn",
    "sg:classifiers":[
        {
            "category":"Education",
            "subcategory":"Kindergarten",
            "type":"Public Place"
        }
    ],
    "sg:phone":"+61 2 6029 8654",
    "sg:postcode":"2660",
    "sg:province":"NSW",
    "sg:tags":[
        "pre-schools"
    ],
    "wof:name":"Culcairn Early Childhood Centre",
    "wof:placetype":"venue"
},
  "geometry": {"coordinates":[147.045684814,-35.6683425903],"type":"Point"}
}