{
  "type": "Feature",
  "properties": {
    "addr:full":"187 Queen St St Marys NSW 2760",
    "addr:housenumber":"187",
    "addr:postcode":"2760",
    "addr:street":"Queen St",
    "iso:country":"AU",
    "sg:address":"187 Queen St",
    "sg:city":"St Marys",
    "sg:classifiers":[
        {
            "category":"Shopping",
            "subcategory":"Party Supplies",
            "type":"Retail Goods"
        }
    ],
    "sg:phone":"+61 2 9833 7483",
    "sg:postcode":"2760",
    "sg:province":"NSW",
    "wof:name":"Party Pit Stop",
    "wof:placetype":"venue"
},
  "geometry": {"coordinates":[150.773727417,-33.7676048279],"type":"Point"}
}