{
  "type": "Feature",
  "properties": {
    "addr:full":"128 Stafford St Penrith NSW 2750",
    "addr:housenumber":"128",
    "addr:postcode":"2750",
    "addr:street":"Stafford St",
    "iso:country":"AU",
    "sg:address":"128 Stafford St",
    "sg:city":"Penrith",
    "sg:classifiers":[
        {
            "category":"Health Services",
            "subcategory":"Doctor",
            "type":"Services"
        }
    ],
    "sg:phone":"+61 2 4732 1677",
    "sg:postcode":"2750",
    "sg:province":"NSW",
    "sg:tags":[
        "medical",
        "practitioner"
    ],
    "wof:name":"Penrith Cosmetic & Plastic Surgery Centre",
    "wof:placetype":"venue"
},
  "geometry": {"coordinates":[150.70704650900001,-33.7618865967],"type":"Point"}
}