{
  "type": "Feature",
  "properties": {
    "iso:country":"AU",
    "sg:address":"U8/ 280 Bannister Rd",
    "sg:city":"Canning Vale",
    "sg:classifiers":[
        {
            "category":"Fast Food",
            "type":"Food & Drink"
        }
    ],
    "sg:phone":"+61 8 9456 2239",
    "sg:postcode":"6155",
    "sg:province":"WA",
    "sg:tags":[
        "away",
        "take"
    ],
    "wof:name":"Azmar Kebabs",
    "wof:placetype":"venue"
},
  "geometry": {"coordinates":[115.895592,-32.070065],"type":"Point"}
}