{
  "type": "Feature",
  "properties": {
    "addr:full":"Unit 12, 210 Winton Rd Joondalup WA 6027",
    "addr:housenumber":"210",
    "addr:postcode":"6027",
    "addr:street":"Winton Rd",
    "iso:country":"AU",
    "sg:address":"Unit 12, 210 Winton Rd",
    "sg:city":"Joondalup",
    "sg:classifiers":[
        {
            "category":"Autos & Motor Vehicles",
            "subcategory":"Auto Supplies",
            "type":"Retail Goods"
        }
    ],
    "sg:phone":"+61 8 9301 1660",
    "sg:postcode":"6027",
    "sg:province":"WA",
    "sg:tags":[
        "part",
        "cycles",
        "accessory"
    ],
    "wof:name":"Scootamoto",
    "wof:placetype":"venue"
},
  "geometry": {"coordinates":[115.763931274,-31.7489376068],"type":"Point"}
}