{
  "type": "Feature",
  "properties": {
    "iso:country":"AU",
    "sg:address":"10 Broadmeadow Rd",
    "sg:city":"Broadmeadow",
    "sg:classifiers":[
        {
            "category":"Building & Trades",
            "subcategory":"Construction",
            "type":"Services"
        }
    ],
    "sg:phone":"+61 2 4962 1155",
    "sg:postcode":"2292",
    "sg:province":"NSW",
    "sg:tags":[
        "home",
        "air conditioning"
    ],
    "wof:name":"Temperzone Quality Air Conditioning",
    "wof:placetype":"venue"
},
  "geometry": {"coordinates":[151.73283386200001,-32.9127426147],"type":"Point"}
}