{
  "type": "Feature",
  "properties": {
    "addr:full":"96 Crown St East Sydney NSW 2010",
    "addr:housenumber":"96",
    "addr:postcode":"2010",
    "addr:street":"Crown St East",
    "iso:country":"AU",
    "sg:address":"96 Crown St",
    "sg:city":"East Sydney",
    "sg:classifiers":[
        {
            "category":"Building & Trades",
            "subcategory":"Construction",
            "type":"Services"
        }
    ],
    "sg:phone":"+61 2 9331 7999",
    "sg:postcode":"2010",
    "sg:province":"NSW",
    "sg:tags":[
        "contractor"
    ],
    "wof:name":"Hutcherson Raymond (NSW) Pty Ltd",
    "wof:placetype":"venue"
},
  "geometry": {"coordinates":[151.216064453,-33.8747367859],"type":"Point"}
}