{
  "type": "Feature",
  "properties": {
    "addr:full":"11 Nevis Crt Endeavour Hills VIC 3802",
    "addr:housenumber":"11",
    "addr:postcode":"3802",
    "addr:street":"Nevis Crt",
    "iso:country":"AU",
    "sg:address":"11 Nevis Crt",
    "sg:city":"Endeavour Hills",
    "sg:classifiers":[
        {
            "category":"Professional",
            "subcategory":"Art Services",
            "type":"Services"
        }
    ],
    "sg:phone":"+61 3 9700 7519",
    "sg:postcode":"3802",
    "sg:province":"VIC",
    "sg:tags":[
        "decorator",
        "painter"
    ],
    "wof:name":"Oxford Painting",
    "wof:placetype":"venue"
},
  "geometry": {"coordinates":[145.26727294899999,-37.9650497437],"type":"Point"}
}