{
  "type": "Feature",
  "properties": {
    "iso:country":"AU",
    "sg:address":"46 Cameron St",
    "sg:city":"Launceston",
    "sg:classifiers":[
        {
            "category":"Professional",
            "subcategory":"Employment Agencies",
            "type":"Services"
        }
    ],
    "sg:phone":"+61 3 6337 9999",
    "sg:postcode":"7250",
    "sg:province":"TAS",
    "wof:name":"Findstaff.biz",
    "wof:placetype":"venue"
},
  "geometry": {"coordinates":[147.138763428,-41.4349861145],"type":"Point"}
}