{
  "type": "Feature",
  "properties": {
    "iso:country":"AU",
    "sg:address":"14 Helm Crt",
    "sg:city":"Mermaid Waters",
    "sg:classifiers":[
        {
            "category":"Building & Trades",
            "subcategory":"Landscaping Services",
            "type":"Services"
        }
    ],
    "sg:phone":"+61 413 668 958",
    "sg:postcode":"4218",
    "sg:province":"QLD",
    "sg:tags":[
        "designer",
        "landscape",
        "contractor"
    ],
    "wof:name":"Environmental Renovations",
    "wof:placetype":"venue"
},
  "geometry": {"coordinates":[153.43185424800001,-28.0579128265],"type":"Point"}
}