{
  "type": "Feature",
  "properties": {
    "iso:country":"AU",
    "sg:address":"Eltoro Industrial Estate Unit 10b Homepride Ave",
    "sg:city":"Warwick Farm",
    "sg:classifiers":[
        {
            "category":"Retail",
            "subcategory":"Auto Repair",
            "type":"Services"
        }
    ],
    "sg:phone":"+61 2 9602 9541",
    "sg:postcode":"2170",
    "sg:province":"NSW",
    "sg:tags":[
        "engine",
        "reconditioning"
    ],
    "wof:name":"Les Noyce Engine Reconditioning",
    "wof:placetype":"venue"
},
  "geometry": {"coordinates":[150.92384338400001,-33.9102516174],"type":"Point"}
}