{
  "type": "Feature",
  "properties": {
    "iso:country":"AU",
    "sg:address":"540 Boundary Rd",
    "sg:city":"Coopers Plains",
    "sg:classifiers":[
        {
            "category":"Professional",
            "type":"Services"
        }
    ],
    "sg:phone":"+61 7 3274 4377",
    "sg:postcode":"4108",
    "sg:province":"QLD",
    "sg:tags":[
        "transport"
    ],
    "wof:name":"Trans Commercial Refrigeration Hire",
    "wof:placetype":"venue"
},
  "geometry": {"coordinates":[153.01824951200001,-27.5673007965],"type":"Point"}
}