{
  "type": "Feature",
  "properties": {
    "addr:full":"Level 1, 25 Playne St Frankston VIC 3199",
    "addr:housenumber":"25",
    "addr:postcode":"3199",
    "addr:street":"Playne St",
    "iso:country":"AU",
    "sg:address":"Level 1, 25 Playne St",
    "sg:city":"Frankston",
    "sg:classifiers":[
        {
            "category":"Banks & Credit Unions",
            "subcategory":"Financial Services",
            "type":"Services"
        }
    ],
    "sg:phone":"+61 3 9783 8900",
    "sg:postcode":"3199",
    "sg:province":"VIC",
    "sg:tags":[
        "planning"
    ],
    "wof:name":"David Brook Financial Services Pty Ltd",
    "wof:placetype":"venue"
},
  "geometry": {"coordinates":[145.12213134800001,-38.1446838379],"type":"Point"}
}