{
  "type": "Feature",
  "properties": {
    "addr:full":"107 Melbourne St Mulwala NSW 2647",
    "addr:housenumber":"107",
    "addr:postcode":"2647",
    "addr:street":"Melbourne St",
    "iso:country":"AU",
    "sg:address":"107 Melbourne St",
    "sg:city":"Mulwala",
    "sg:classifiers":[
        {
            "category":"Food & Beverages",
            "subcategory":"Bakery",
            "type":"Retail Goods"
        }
    ],
    "sg:phone":"+61 3 5744 3459",
    "sg:postcode":"2647",
    "sg:province":"NSW",
    "sg:tags":[
        "baker"
    ],
    "wof:name":"Lake Mulwala Bakery",
    "wof:placetype":"venue"
},
  "geometry": {"coordinates":[146.00138855,-35.9947776794],"type":"Point"}
}