{
  "type": "Feature",
  "properties": {
    "addr:full":"Unit 5 3 Central Ave Thornleigh NSW 2120",
    "addr:housenumber":"3",
    "addr:postcode":"2120",
    "addr:street":"Central Ave",
    "iso:country":"AU",
    "sg:address":"Unit 5 3 Central Ave",
    "sg:city":"Thornleigh",
    "sg:classifiers":[
        {
            "category":"Professional",
            "subcategory":"Management & Consulting",
            "type":"Services"
        }
    ],
    "sg:phone":"+61 2 9484 9423",
    "sg:postcode":"2120",
    "sg:province":"NSW",
    "sg:tags":[
        "consultant"
    ],
    "wof:name":"Conform Health Group Pty Ltd",
    "wof:placetype":"venue"
},
  "geometry": {"coordinates":[151.08096313499999,-33.7303466797],"type":"Point"}
}