{
  "type": "Feature",
  "properties": {
    "addr:full":"79 Loftus St Katoomba NSW 2780",
    "addr:housenumber":"79",
    "addr:postcode":"2780",
    "addr:street":"Loftus St",
    "iso:country":"AU",
    "sg:address":"79 Loftus St",
    "sg:city":"Katoomba",
    "sg:classifiers":[
        {
            "category":"Real Estate",
            "subcategory":"Architect",
            "type":"Services"
        }
    ],
    "sg:phone":"+61 2 4782 1559",
    "sg:postcode":"2780",
    "sg:province":"NSW",
    "wof:name":"Ross Young Architect",
    "wof:placetype":"venue"
},
  "geometry": {"coordinates":[150.30511474599999,-33.7235717773],"type":"Point"}
}