{
  "type": "Feature",
  "properties": {
    "addr:full":"220 Brisbane Rd Monkland QLD 4570",
    "addr:housenumber":"220",
    "addr:postcode":"4570",
    "addr:street":"Brisbane Rd",
    "iso:country":"AU",
    "sg:address":"220 Brisbane Rd",
    "sg:city":"Monkland",
    "sg:classifiers":[
        {
            "category":"Education",
            "subcategory":"School",
            "type":"Public Place"
        }
    ],
    "sg:phone":"+61 7 5489 8855",
    "sg:postcode":"4570",
    "sg:province":"QLD",
    "sg:tags":[
        "state",
        "except",
        "nsw"
    ],
    "wof:name":"Monkland Preschool",
    "wof:placetype":"venue"
},
  "geometry": {"coordinates":[152.68382263199999,-26.2113437653],"type":"Point"}
}