{
  "type": "Feature",
  "properties": {
    "addr:full":"8 Press Rd Brooklyn Park SA 5032",
    "addr:housenumber":"8",
    "addr:postcode":"5032",
    "addr:street":"Press Rd",
    "iso:country":"AU",
    "sg:address":"8 Press Rd",
    "sg:city":"Brooklyn Park",
    "sg:classifiers":[
        {
            "category":"Real Estate",
            "subcategory":"Architect",
            "type":"Services"
        }
    ],
    "sg:phone":"+61 8 8352 6239",
    "sg:postcode":"5032",
    "sg:province":"SA",
    "sg:tags":[
        "building",
        "designer"
    ],
    "wof:name":"Val Design",
    "wof:placetype":"venue"
},
  "geometry": {"coordinates":[138.551223755,-34.9345664978],"type":"Point"}
}