{
  "type": "Feature",
  "properties": {
    "addr:full":"Shop 44 Cairns Central Shopping Centre McLeod St Cairns QLD 4870",
    "addr:housenumber":"shop 44",
    "addr:postcode":"4870",
    "addr:street":"Mcleod St",
    "iso:country":"AU",
    "sg:address":"Shop 44 Cairns Central Shopping Centre McLeod St",
    "sg:city":"Cairns",
    "sg:classifiers":[
        {
            "category":"Health Services",
            "subcategory":"Dentist",
            "type":"Services"
        }
    ],
    "sg:phone":"+61 7 4031 2134",
    "sg:postcode":"4870",
    "sg:province":"QLD",
    "wof:name":"The Smile Centre",
    "wof:placetype":"venue"
},
  "geometry": {"coordinates":[145.774169922,-16.926197052],"type":"Point"}
}