{
  "type": "Feature",
  "properties": {
    "iso:country":"AU",
    "sg:address":"65 Hardys Rd",
    "sg:city":"Underdale",
    "sg:classifiers":[
        {
            "category":"Building & Trades",
            "subcategory":"Construction",
            "type":"Services"
        }
    ],
    "sg:phone":"+61 8 8354 6300",
    "sg:postcode":"5032",
    "sg:province":"SA",
    "sg:tags":[
        "industrial",
        "commercial",
        "air conditioning"
    ],
    "wof:name":"Haden Engineering Pty Limited",
    "wof:placetype":"venue"
},
  "geometry": {"coordinates":[138.553634644,-34.9177627563],"type":"Point"}
}