{
  "type": "Feature",
  "properties": {
    "addr:full":"U5 - 90 Wanneroo Rd Yokine WA 6060",
    "addr:housenumber":"90",
    "addr:postcode":"6060",
    "addr:street":"U5;Wanneroo Rd",
    "iso:country":"AU",
    "sg:address":"U5 - 90 Wanneroo Rd",
    "sg:city":"Yokine",
    "sg:classifiers":[
        {
            "category":"Communications",
            "type":"Services"
        }
    ],
    "sg:phone":"+61 8 9444 7873",
    "sg:postcode":"6060",
    "sg:province":"WA",
    "sg:tags":[
        "public",
        "system",
        "address"
    ],
    "wof:name":"DC Productions",
    "wof:placetype":"venue"
},
  "geometry": {"coordinates":[115.84323883099999,-31.9026527405],"type":"Point"}
}