{
  "type": "Feature",
  "properties": {
    "iso:country":"AU",
    "sg:address":"71 Bruton St",
    "sg:city":"Casino",
    "sg:classifiers":[
        {
            "category":"Building & Trades",
            "subcategory":"Construction",
            "type":"Services"
        }
    ],
    "sg:phone":"+61 2 6662 2094",
    "sg:postcode":"2470",
    "sg:province":"NSW",
    "sg:tags":[
        "contractor"
    ],
    "wof:name":"Newby J T & B J Pty Ltd",
    "wof:placetype":"venue"
},
  "geometry": {"coordinates":[153.02798461899999,-28.8529338837],"type":"Point"}
}