{
  "type": "Feature",
  "properties": {
    "iso:country":"AU",
    "sg:address":"1-5 Cottage St",
    "sg:city":"Werrington",
    "sg:classifiers":[
        {
            "category":"Social Services",
            "subcategory":"Child Care",
            "type":"Services"
        }
    ],
    "sg:phone":"+61 2 4731 4572",
    "sg:postcode":"2747",
    "sg:province":"NSW",
    "wof:name":"Yoorami Cottage Before & After School Care",
    "wof:placetype":"venue"
},
  "geometry": {"coordinates":[150.739135742,-33.7560310364],"type":"Point"}
}