{
  "type": "Feature",
  "properties": {
    "iso:country":"AU",
    "sg:address":"539 Lane St",
    "sg:city":"Broken Hill",
    "sg:classifiers":[
        {
            "category":"Building & Trades",
            "subcategory":"Pest Control",
            "type":"Services"
        }
    ],
    "sg:phone":"+61 447 824 014",
    "sg:postcode":"2880",
    "sg:province":"NSW",
    "wof:name":"West Darling Pest Control",
    "wof:placetype":"venue"
},
  "geometry": {"coordinates":[141.46972656200001,-31.9473953247],"type":"Point"}
}