{
  "type": "Feature",
  "properties": {
    "addr:full":"Midwestern Hwy Blayney NSW 2799",
    "addr:postcode":"2799",
    "addr:street":"Midwestern Hwy",
    "iso:country":"AU",
    "sg:address":"Midwestern Hwy",
    "sg:city":"Blayney",
    "sg:classifiers":[
        {
            "category":"Freight",
            "type":"Transportation"
        }
    ],
    "sg:phone":"+61 2 6368 2201",
    "sg:postcode":"2799",
    "sg:province":"NSW",
    "sg:tags":[
        "transport",
        "refrigerated"
    ],
    "wof:name":"Nixon's Transport Pty Ltd",
    "wof:placetype":"venue"
},
  "geometry": {"coordinates":[149.25495900000001,-33.533897],"type":"Point"}
}