{
  "type": "Feature",
  "properties": {
    "iso:country":"AU",
    "sg:address":"26 Wilson St",
    "sg:city":"Maryborough",
    "sg:classifiers":[
        {
            "category":"Organizations",
            "subcategory":"Non-profit Organization",
            "type":"Services"
        }
    ],
    "sg:phone":"+61 7 4121 5222",
    "sg:postcode":"4650",
    "sg:province":"QLD",
    "sg:tags":[
        "support",
        "disability",
        "organisation"
    ],
    "wof:name":"Kathleen Costello Centre For the Deaf Incorporated",
    "wof:placetype":"venue"
},
  "geometry": {"coordinates":[152.705658,-25.521585],"type":"Point"}
}