{
  "type": "Feature",
  "properties": {
    "iso:country":"AU",
    "sg:address":"35 Tate St",
    "sg:city":"Bentley",
    "sg:classifiers":[
        {
            "category":"Retail",
            "subcategory":"Auto Repair",
            "type":"Services"
        }
    ],
    "sg:phone":"+61 8 9258 3119",
    "sg:postcode":"6102",
    "sg:province":"WA",
    "sg:tags":[
        "muffler",
        "exhaust",
        "system"
    ],
    "wof:name":"Supertec Automotive",
    "wof:placetype":"venue"
},
  "geometry": {"coordinates":[115.920448303,-31.9974994659],"type":"Point"}
}