{
  "type": "Feature",
  "properties": {
    "addr:full":"17A Baker St Wangaratta VIC 3677",
    "addr:housenumber":"17a",
    "addr:postcode":"3677",
    "addr:street":"Baker St",
    "iso:country":"AU",
    "sg:address":"17A Baker St",
    "sg:city":"Wangaratta",
    "sg:classifiers":[
        {
            "category":"Professional",
            "subcategory":"Printing & Photocopies",
            "type":"Services"
        }
    ],
    "sg:phone":"+61 3 5721 9277",
    "sg:postcode":"3677",
    "sg:province":"VIC",
    "sg:tags":[
        "photocopier"
    ],
    "wof:name":"Daro Business Machines Pty Ltd",
    "wof:placetype":"venue"
},
  "geometry": {"coordinates":[146.32273864699999,-36.3532981873],"type":"Point"}
}