{
  "type": "Feature",
  "properties": {
    "addr:full":"8 Post Pl Lake Albert NSW 2650",
    "addr:housenumber":"8",
    "addr:postcode":"2650",
    "addr:street":"Post Pl",
    "iso:country":"AU",
    "sg:address":"8 Post Pl",
    "sg:city":"Lake Albert",
    "sg:classifiers":[
        {
            "category":"Building & Trades",
            "subcategory":"Construction",
            "type":"Services"
        }
    ],
    "sg:phone":"+61 2 6922 3358",
    "sg:postcode":"2650",
    "sg:province":"NSW",
    "sg:tags":[
        "contractor"
    ],
    "wof:name":"Post D & K Constructions",
    "wof:placetype":"venue"
},
  "geometry": {"coordinates":[147.38169860799999,-35.1666793823],"type":"Point"}
}