{
  "type": "Feature",
  "properties": {
    "addr:full":"8 Eleanor St Mt Gambier SA 5290",
    "addr:housenumber":"8",
    "addr:postcode":"5290",
    "addr:street":"Eleanor St",
    "iso:country":"AU",
    "sg:address":"8 Eleanor St",
    "sg:city":"Mt Gambier",
    "sg:classifiers":[
        {
            "category":"Professional",
            "subcategory":"Printing & Photocopies",
            "type":"Services"
        }
    ],
    "sg:phone":"+61 8 8723 0770",
    "sg:postcode":"5290",
    "sg:province":"SA",
    "sg:tags":[
        "photocopier"
    ],
    "wof:name":"Dial-A-Toner & Ribbon Service",
    "wof:placetype":"venue"
},
  "geometry": {"coordinates":[140.77432300000001,-37.829529],"type":"Point"}
}