{
  "type": "Feature",
  "properties": {
    "iso:country":"AU",
    "sg:address":"Shop G27, Roselands Shopping Ctr Roselands Ave",
    "sg:city":"Roselands",
    "sg:classifiers":[
        {
            "category":"Shopping",
            "subcategory":"Shoes",
            "type":"Retail Goods"
        }
    ],
    "sg:phone":"+61 2 9740 9942",
    "sg:postcode":"2196",
    "sg:province":"NSW",
    "sg:tags":[
        "footwear"
    ],
    "wof:name":"Colorado",
    "wof:placetype":"venue"
},
  "geometry": {"coordinates":[151.07344055199999,-33.936756134],"type":"Point"}
}