{
  "type": "Feature",
  "properties": {
    "addr:full":"6 Currajong Rd Parkes NSW 2870",
    "addr:housenumber":"6",
    "addr:postcode":"2870",
    "addr:street":"Currajong Rd",
    "iso:country":"AU",
    "sg:address":"6 Currajong Rd",
    "sg:city":"Parkes",
    "sg:classifiers":[
        {
            "category":"Building & Trades",
            "subcategory":"Plumbing",
            "type":"Services"
        }
    ],
    "sg:phone":"+61 2 6863 4347",
    "sg:postcode":"2870",
    "sg:province":"NSW",
    "sg:tags":[
        "plumber",
        "gasfitters"
    ],
    "wof:name":"Garry Wilkie Plumbing Service",
    "wof:placetype":"venue"
},
  "geometry": {"coordinates":[148.17448400000001,-33.125263],"type":"Point"}
}