{
  "type": "Feature",
  "properties": {
    "addr:full":"75 Cowper St Hillston NSW 2675",
    "addr:housenumber":"75",
    "addr:postcode":"2675",
    "addr:street":"Cowper St",
    "iso:country":"AU",
    "sg:address":"75 Cowper St",
    "sg:city":"Hillston",
    "sg:classifiers":[
        {
            "category":"Autos & Motor Vehicles",
            "subcategory":"Auto Supplies",
            "type":"Retail Goods"
        }
    ],
    "sg:phone":"+61 2 6967 2380",
    "sg:postcode":"2675",
    "sg:province":"NSW",
    "sg:tags":[
        "oil",
        "spirit"
    ],
    "wof:name":"Westoil Petroleum Pty Ltd",
    "wof:placetype":"venue"
},
  "geometry": {"coordinates":[145.53901672399999,-33.4861984253],"type":"Point"}
}