{
  "type": "Feature",
  "properties": {
    "addr:full":"8 Lillian St North Geelong VIC 3215",
    "addr:housenumber":"8",
    "addr:postcode":"3215",
    "addr:street":"Lillian St",
    "iso:country":"AU",
    "sg:address":"8 Lillian St",
    "sg:city":"North Geelong",
    "sg:classifiers":[
        {
            "category":"Shopping",
            "subcategory":"Antiques",
            "type":"Retail Goods"
        }
    ],
    "sg:phone":"+61 3 5278 4571",
    "sg:postcode":"3215",
    "sg:province":"VIC",
    "sg:tags":[
        "restoration",
        "reproduction"
    ],
    "wof:name":"The Polishers Pad",
    "wof:placetype":"venue"
},
  "geometry": {"coordinates":[144.347366333,-38.1009254456],"type":"Point"}
}