{
  "type": "Feature",
  "properties": {
    "addr:full":"Tavern Shopping Cnter Shop 4 162 Barrett St Bracken Ridge QLD 4017",
    "addr:housenumber":"4 162",
    "addr:postcode":"4017",
    "addr:street":"Barrett St",
    "iso:country":"AU",
    "sg:address":"Tavern Shopping Cnter Shop 4 162 Barrett St",
    "sg:city":"Bracken Ridge",
    "sg:classifiers":[
        {
            "category":"Health Services",
            "subcategory":"Dentist",
            "type":"Services"
        }
    ],
    "sg:phone":"+61 7 3269 7047",
    "sg:postcode":"4017",
    "sg:province":"QLD",
    "wof:name":"Kruger Glen Dr",
    "wof:placetype":"venue"
},
  "geometry": {"coordinates":[153.040359497,-27.3192615509],"type":"Point"}
}