{
  "type": "Feature",
  "properties": {
    "addr:full":"Shop 49E 6 Seven Hills Rd Baulkham Hills NSW 2153",
    "addr:housenumber":"49e 6",
    "addr:postcode":"2153",
    "addr:street":"Seven Hills Rd",
    "iso:country":"AU",
    "sg:address":"Shop 49E 6 Seven Hills Rd",
    "sg:city":"Baulkham Hills",
    "sg:classifiers":[
        {
            "category":"Fast Food",
            "type":"Food & Drink"
        }
    ],
    "sg:phone":"+61 2 9865 1422",
    "sg:postcode":"2153",
    "sg:province":"NSW",
    "sg:tags":[
        "away",
        "take"
    ],
    "wof:name":"Domino's Pizza",
    "wof:placetype":"venue"
},
  "geometry": {"coordinates":[150.944290161,-33.7672309875],"type":"Point"}
}