{
  "type": "Feature",
  "properties": {
    "addr:full":"221 East St Rockhampton QLD 4700",
    "addr:housenumber":"221",
    "addr:postcode":"4700",
    "addr:street":"East St",
    "iso:country":"AU",
    "sg:address":"221 East St",
    "sg:city":"Rockhampton",
    "sg:classifiers":[
        {
            "category":"Building & Trades",
            "subcategory":"Cleaning & Sanitation",
            "type":"Services"
        }
    ],
    "sg:phone":"+61 7 4927 5553",
    "sg:postcode":"4700",
    "sg:province":"QLD",
    "sg:tags":[
        "chemical",
        "pressure",
        "steam",
        "contractor"
    ],
    "wof:name":"Auto Shine",
    "wof:placetype":"venue"
},
  "geometry": {"coordinates":[150.52171325699999,-23.3897247314],"type":"Point"}
}