{
  "type": "Feature",
  "properties": {
    "iso:country":"AU",
    "sg:address":"110 Ingrams Rd",
    "sg:city":"Research",
    "sg:classifiers":[
        {
            "category":"Health Services",
            "subcategory":"Health Practitioner",
            "type":"Services"
        }
    ],
    "sg:phone":"+61 3 9496 5187",
    "sg:postcode":"3095",
    "sg:province":"VIC",
    "sg:tags":[
        "psychologist"
    ],
    "wof:name":"Milgrom J",
    "wof:placetype":"venue"
},
  "geometry": {"coordinates":[145.179031372,-37.6930351257],"type":"Point"}
}