{
  "type": "Feature",
  "properties": {
    "addr:full":"1 Export Drv Ulverstone TAS 7315",
    "addr:housenumber":"1",
    "addr:postcode":"7315",
    "addr:street":"Export Drv",
    "iso:country":"AU",
    "sg:address":"1 Export Drv",
    "sg:city":"Ulverstone",
    "sg:classifiers":[
        {
            "category":"Professional",
            "subcategory":"Detective & Security Services",
            "type":"Services"
        }
    ],
    "sg:phone":"+61 3 6425 5599",
    "sg:postcode":"7315",
    "sg:province":"TAS",
    "sg:tags":[
        "inspector",
        "boiler"
    ],
    "wof:name":"Gleeson & Associates Pty Ltd",
    "wof:placetype":"venue"
},
  "geometry": {"coordinates":[146.200927734,-41.1555709839],"type":"Point"}
}