{
  "type": "Feature",
  "properties": {
    "iso:country":"AU",
    "sg:address":"11 Leven St",
    "sg:city":"Coopers Plains",
    "sg:classifiers":[
        {
            "category":"Health Services",
            "subcategory":"Health Practitioner",
            "type":"Services"
        }
    ],
    "sg:phone":"+61 7 3345 7472",
    "sg:postcode":"4108",
    "sg:province":"QLD",
    "sg:tags":[
        "physiotherapist"
    ],
    "wof:name":"Stephen Lam & Yvonne Yau",
    "wof:placetype":"venue"
},
  "geometry": {"coordinates":[153.04705810600001,-27.5663528442],"type":"Point"}
}