{
  "type": "Feature",
  "properties": {
    "addr:full":"Suite 8 31 Lathlain St Belconnen ACT 2617",
    "addr:housenumber":"31",
    "addr:postcode":"2617",
    "addr:street":"Lathlain St",
    "iso:country":"AU",
    "sg:address":"Suite 8 31 Lathlain St",
    "sg:city":"Belconnen",
    "sg:classifiers":[
        {
            "category":"Health Services",
            "subcategory":"Dentist",
            "type":"Services"
        }
    ],
    "sg:phone":"+61 2 6251 1311",
    "sg:postcode":"2617",
    "sg:province":"ACT",
    "sg:tags":[
        "technician",
        "dental"
    ],
    "wof:name":"Bryant Glenn",
    "wof:placetype":"venue"
},
  "geometry": {"coordinates":[149.06402587900001,-35.2418022156],"type":"Point"}
}