{
  "type": "Feature",
  "properties": {
    "iso:country":"AU",
    "sg:address":"Shop 5 Ackers St",
    "sg:city":"Hermit Park",
    "sg:classifiers":[
        {
            "category":"Personal",
            "subcategory":"Tanning Parlor",
            "type":"Services"
        }
    ],
    "sg:phone":"+61 7 4723 2238",
    "sg:postcode":"4812",
    "sg:province":"QLD",
    "sg:tags":[
        "solarium"
    ],
    "wof:name":"Bronzone",
    "wof:placetype":"venue"
},
  "geometry": {"coordinates":[146.800995,-19.277542],"type":"Point"}
}