{
  "type": "Feature",
  "properties": {
    "addr:full":"102 Glenayr Ave Bondi NSW 2026",
    "addr:housenumber":"102",
    "addr:postcode":"2026",
    "addr:street":"Glenayr Ave",
    "iso:country":"AU",
    "sg:address":"102 Glenayr Ave",
    "sg:city":"Bondi",
    "sg:classifiers":[
        {
            "category":"Shopping",
            "subcategory":"Clothing, Apparel, & Fashions",
            "type":"Retail Goods"
        }
    ],
    "sg:phone":"+61 2 9130 8984",
    "sg:postcode":"2026",
    "sg:province":"NSW",
    "sg:tags":[
        "recycled",
        "clothing"
    ],
    "wof:name":"Puf&#039;N More Stuff Vintage Clothing",
    "wof:placetype":"venue"
},
  "geometry": {"coordinates":[151.273345947,-33.886100769],"type":"Point"}
}