{
  "type": "Feature",
  "properties": {
    "addr:full":"PO Box 145 Eden NSW 2551",
    "addr:postcode":"2551",
    "iso:country":"AU",
    "sg:address":"PO Box 145",
    "sg:city":"Eden",
    "sg:classifiers":[
        {
            "category":"Education",
            "subcategory":"Dance Studio",
            "type":"Public Place"
        }
    ],
    "sg:phone":"+61 419 833 839",
    "sg:postcode":"2551",
    "sg:province":"NSW",
    "sg:tags":[
        "venue",
        "tuition"
    ],
    "wof:name":"Kha&#039;ra Distinguished Middle Eastern Dance",
    "wof:placetype":"venue"
},
  "geometry": {"coordinates":[149.90425109899999,-37.0629806519],"type":"Point"}
}