{
  "type": "Feature",
  "properties": {
    "addr:full":"170 Colburn Ave Victoria Point QLD 4165",
    "addr:housenumber":"170",
    "addr:postcode":"4165",
    "addr:street":"Colburn Ave",
    "iso:country":"AU",
    "sg:address":"170 Colburn Ave",
    "sg:city":"Victoria Point",
    "sg:classifiers":[
        {
            "category":"Building & Trades",
            "subcategory":"Pest Control",
            "type":"Services"
        }
    ],
    "sg:phone":"+61 7 3398 6114",
    "sg:postcode":"4165",
    "sg:province":"QLD",
    "wof:name":"Axis Termite & Pest Services",
    "wof:placetype":"venue"
},
  "geometry": {"coordinates":[153.304321289,-27.5876026154],"type":"Point"}
}