{
  "type": "Feature",
  "properties": {
    "addr:full":"U 3/ 11 Rocklea Dr Port Melbourne VIC 3207",
    "addr:housenumber":"11",
    "addr:postcode":"3207",
    "addr:street":"Rocklea Dr",
    "iso:country":"AU",
    "sg:address":"U 3/ 11 Rocklea Dr",
    "sg:city":"Port Melbourne",
    "sg:classifiers":[
        {
            "category":"Manufacturing",
            "subcategory":"Apparel",
            "type":"Manufacturing & Wholesale Goods"
        }
    ],
    "sg:phone":"+61 3 9646 3996",
    "sg:postcode":"3207",
    "sg:province":"VIC",
    "sg:tags":[
        "wholesaler",
        "mfrs",
        "footwear"
    ],
    "wof:name":"Shoes On Line Enterprises Pty Ltd",
    "wof:placetype":"venue"
},
  "geometry": {"coordinates":[144.92053200000001,-37.830978],"type":"Point"}
}