{
  "type": "Feature",
  "properties": {
    "addr:full":"4 Stewart St Mareeba QLD 4880",
    "addr:housenumber":"4",
    "addr:postcode":"4880",
    "addr:street":"Stewart St",
    "iso:country":"AU",
    "sg:address":"4 Stewart St",
    "sg:city":"Mareeba",
    "sg:classifiers":[
        {
            "category":"Education",
            "subcategory":"Kindergarten",
            "type":"Public Place"
        }
    ],
    "sg:phone":"+61 7 4092 2559",
    "sg:postcode":"4880",
    "sg:province":"QLD",
    "sg:tags":[
        "pre-schools"
    ],
    "wof:name":"C&K Mareeba Community Kindergarten",
    "wof:placetype":"venue"
},
  "geometry": {"coordinates":[145.417800903,-16.998462677],"type":"Point"}
}