{
  "type": "Feature",
  "properties": {
    "iso:country":"AU",
    "sg:address":"PO Box 1446",
    "sg:city":"Subiaco Private Boxes",
    "sg:classifiers":[
        {
            "category":"Building & Trades",
            "subcategory":"Cleaning & Sanitation",
            "type":"Services"
        }
    ],
    "sg:phone":"+61 418 959 541",
    "sg:postcode":"6904",
    "sg:province":"WA",
    "sg:tags":[
        "industrial",
        "commercial",
        "contractor"
    ],
    "wof:name":"Services Rendered",
    "wof:placetype":"venue"
},
  "geometry": {"coordinates":[115.829773,-31.943567],"type":"Point"}
}