{
  "type": "Feature",
  "properties": {
    "addr:full":"128 Norrie Ave Whyalla SA 5600",
    "addr:housenumber":"128",
    "addr:postcode":"5600",
    "addr:street":"Norrie Ave",
    "iso:country":"AU",
    "sg:address":"128 Norrie Ave",
    "sg:city":"Whyalla",
    "sg:classifiers":[
        {
            "category":"Autos & Motor Vehicles",
            "subcategory":"Auto Supplies",
            "type":"Retail Goods"
        }
    ],
    "sg:phone":"+61 8 8645 0666",
    "sg:postcode":"5600",
    "sg:province":"SA",
    "sg:tags":[
        "transmission",
        "equipment",
        "power"
    ],
    "wof:name":"David Brown",
    "wof:placetype":"venue"
},
  "geometry": {"coordinates":[137.55166600000001,-33.021339],"type":"Point"}
}