{
  "type": "Feature",
  "properties": {
    "addr:full":"Factory 24, 29 Kirkham Rd West Keysborough VIC 3173",
    "addr:housenumber":"29",
    "addr:postcode":"3173",
    "addr:street":"Kirkham Rd West",
    "iso:country":"AU",
    "sg:address":"Factory 24, 29 Kirkham Rd West",
    "sg:city":"Keysborough",
    "sg:classifiers":[
        {
            "category":"Manufacturing",
            "subcategory":"Petroleum Products",
            "type":"Manufacturing & Wholesale Goods"
        }
    ],
    "sg:phone":"+61 3 9701 5221",
    "sg:postcode":"3173",
    "sg:province":"VIC",
    "sg:tags":[
        "lubricant"
    ],
    "wof:name":"Cyclo Automotive Chemicals",
    "wof:placetype":"venue"
},
  "geometry": {"coordinates":[145.18510437,-37.9956130981],"type":"Point"}
}