{
  "type": "Feature",
  "properties": {
    "iso:country":"AU",
    "sg:address":"21 Old Creswick Rd",
    "sg:city":"Ballarat",
    "sg:classifiers":[
        {
            "category":"Manufacturing",
            "subcategory":"Signs",
            "type":"Manufacturing & Wholesale Goods"
        }
    ],
    "sg:phone":"+61 3 5338 2255",
    "sg:postcode":"3350",
    "sg:province":"VIC",
    "sg:tags":[
        "traffic",
        "safety"
    ],
    "wof:name":"Coppens Signs",
    "wof:placetype":"venue"
},
  "geometry": {"coordinates":[143.849304,-37.525589],"type":"Point"}
}