{
  "type": "Feature",
  "properties": {
    "iso:country":"AU",
    "sg:address":"19 High St South, Cnr Henry St",
    "sg:city":"Kew",
    "sg:classifiers":[
        {
            "category":"Health Services",
            "subcategory":"Health Practitioner",
            "type":"Services"
        }
    ],
    "sg:phone":"+61 3 9853 8070",
    "sg:postcode":"3101",
    "sg:province":"VIC",
    "sg:tags":[
        "physiotherapist"
    ],
    "wof:name":"Ma Wilson",
    "wof:placetype":"venue"
},
  "geometry": {"coordinates":[145.02456665,-37.8118095398],"type":"Point"}
}