{
  "type": "Feature",
  "properties": {
    "addr:full":"Bell St Gladstone QLD 4680",
    "addr:postcode":"4680",
    "addr:street":"Bell St",
    "iso:country":"AU",
    "sg:address":"Bell St",
    "sg:city":"Gladstone",
    "sg:classifiers":[
        {
            "category":"Sports & Exercise",
            "subcategory":"Sports Center",
            "type":"Entertainment"
        }
    ],
    "sg:phone":"+61 7 4972 2244",
    "sg:postcode":"4680",
    "sg:province":"QLD",
    "sg:tags":[
        "ground"
    ],
    "wof:name":"Yaralla Sports Club Inc",
    "wof:placetype":"venue"
},
  "geometry": {"coordinates":[151.27171325699999,-23.8566951752],"type":"Point"}
}