{
  "type": "Feature",
  "properties": {
    "addr:full":"134 West Lakes Blv West Lakes SA 5021",
    "addr:housenumber":"134",
    "addr:postcode":"5021",
    "addr:street":"West Lakes Blv",
    "iso:country":"AU",
    "sg:address":"134 West Lakes Blv",
    "sg:city":"West Lakes",
    "sg:classifiers":[
        {
            "category":"Health Services",
            "subcategory":"Dentist",
            "type":"Services"
        }
    ],
    "sg:phone":"+61 8 8449 9777",
    "sg:postcode":"5021",
    "sg:province":"SA",
    "sg:website":"http://www.hobbysmilecentre.com.au",
    "wof:name":"Island Dental",
    "wof:placetype":"venue"
},
  "geometry": {"coordinates":[138.487823486,-34.8722686768],"type":"Point"}
}