{
  "type": "Feature",
  "properties": {
    "addr:full":"41 Boronia Ave Nedlands WA 6009",
    "addr:housenumber":"41",
    "addr:postcode":"6009",
    "addr:street":"Boronia Ave",
    "iso:country":"AU",
    "sg:address":"41 Boronia Ave",
    "sg:city":"Nedlands",
    "sg:classifiers":[
        {
            "category":"Building & Trades",
            "subcategory":"Construction",
            "type":"Services"
        }
    ],
    "sg:phone":"+61 8 9386 7886",
    "sg:postcode":"6009",
    "sg:province":"WA",
    "sg:tags":[
        "polishing",
        "sanding",
        "floor"
    ],
    "wof:name":"Heritage Floor Sanding",
    "wof:placetype":"venue"
},
  "geometry": {"coordinates":[115.803551,-31.978016],"type":"Point"}
}