{
  "type": "Feature",
  "properties": {
    "addr:full":"1015 Mair St Ballarat VIC 3350",
    "addr:housenumber":"1015",
    "addr:postcode":"3350",
    "addr:street":"Mair St",
    "iso:country":"AU",
    "sg:address":"1015 Mair St",
    "sg:city":"Ballarat",
    "sg:classifiers":[
        {
            "category":"Health Services",
            "subcategory":"Doctor",
            "type":"Services"
        }
    ],
    "sg:phone":"+61 3 5333 5088",
    "sg:postcode":"3350",
    "sg:province":"VIC",
    "sg:tags":[
        "medical",
        "practitioner"
    ],
    "wof:name":"Monga Deepika Dr",
    "wof:placetype":"venue"
},
  "geometry": {"coordinates":[143.840271,-37.5602],"type":"Point"}
}