{
  "type": "Feature",
  "properties": {
    "iso:country":"AU",
    "sg:address":"105 Woodlands Drv",
    "sg:city":"Braeside",
    "sg:classifiers":[
        {
            "category":"Home & Garden",
            "subcategory":"Hardware",
            "type":"Retail Goods"
        }
    ],
    "sg:phone":"+61 3 9586 5000",
    "sg:postcode":"3195",
    "sg:province":"VIC",
    "sg:tags":[
        "generating",
        "set",
        "generator"
    ],
    "wof:name":"Aggreko Generator Rentals",
    "wof:placetype":"venue"
},
  "geometry": {"coordinates":[145.119796753,-37.9957885742],"type":"Point"}
}