{
  "type": "Feature",
  "properties": {
    "iso:country":"AU",
    "sg:address":"9 Hackney Rd",
    "sg:city":"Hackney",
    "sg:classifiers":[
        {
            "category":"Building & Trades",
            "subcategory":"Construction",
            "type":"Services"
        }
    ],
    "sg:phone":"+61 8 8363 4978",
    "sg:postcode":"5069",
    "sg:province":"SA",
    "sg:tags":[
        "contractor"
    ],
    "wof:name":"Najjar Bros Pty Ltd",
    "wof:placetype":"venue"
},
  "geometry": {"coordinates":[138.615066528,-34.9183616638],"type":"Point"}
}