{
  "type": "Feature",
  "properties": {
    "addr:full":"Level 1, 977 Wellington St West Perth WA 6005",
    "addr:housenumber":"977",
    "addr:postcode":"6005",
    "addr:street":"Wellington St",
    "iso:country":"AU",
    "sg:address":"Level 1, 977 Wellington St",
    "sg:city":"West Perth",
    "sg:classifiers":[
        {
            "category":"Professional",
            "subcategory":"Computer Services",
            "type":"Services"
        }
    ],
    "sg:phone":"+61 8 9485 2855",
    "sg:postcode":"6005",
    "sg:province":"WA",
    "sg:tags":[
        "consultant",
        "system"
    ],
    "wof:name":"Health Systems Intergration",
    "wof:placetype":"venue"
},
  "geometry": {"coordinates":[115.844322205,-31.9465713501],"type":"Point"}
}