{
  "type": "Feature",
  "properties": {
    "iso:country":"AU",
    "sg:address":"20 Oxley St",
    "sg:city":"Chatham",
    "sg:classifiers":[
        {
            "category":"Travel",
            "subcategory":"Hotels & Motels",
            "type":"Entertainment"
        }
    ],
    "sg:phone":"+61 2 6552 3116",
    "sg:postcode":"2430",
    "sg:province":"NSW",
    "sg:tags":[
        "accommodation"
    ],
    "wof:name":"Manning River Hotel/Motel",
    "wof:placetype":"venue"
},
  "geometry": {"coordinates":[152.47688299999999,-31.90328],"type":"Point"}
}