{
  "type": "Feature",
  "properties": {
    "iso:country":"AU",
    "sg:address":"Shop 4, Robert Street Shopping Village",
    "sg:city":"Tamworth",
    "sg:classifiers":[
        {
            "category":"Personal",
            "subcategory":"Beauty Salon",
            "type":"Services"
        }
    ],
    "sg:phone":"+61 2 6765 8691",
    "sg:postcode":"2340",
    "sg:province":"NSW",
    "sg:tags":[
        "hairdresser"
    ],
    "wof:name":"Trend Set",
    "wof:placetype":"venue"
},
  "geometry": {"coordinates":[150.91792297399999,-31.1085834503],"type":"Point"}
}