{
  "type": "Feature",
  "properties": {
    "iso:country":"AU",
    "sg:address":"PO Box 7374",
    "sg:city":"Redland Bay",
    "sg:classifiers":[
        {
            "category":"Building & Trades",
            "subcategory":"Construction",
            "type":"Services"
        }
    ],
    "sg:phone":"+61 1300 784 231",
    "sg:postcode":"4165",
    "sg:province":"QLD",
    "sg:tags":[
        "roof"
    ],
    "wof:name":"Playone Pty Ltd",
    "wof:placetype":"venue"
},
  "geometry": {"coordinates":[153.29371643100001,-27.6093597412],"type":"Point"}
}