{
  "type": "Feature",
  "properties": {
    "addr:full":"127 Howe St Osborne Park WA 6017",
    "addr:housenumber":"127",
    "addr:postcode":"6017",
    "addr:street":"Howe St",
    "iso:country":"AU",
    "sg:address":"127 Howe St",
    "sg:city":"Osborne Park",
    "sg:classifiers":[
        {
            "category":"Building & Trades",
            "subcategory":"Cleaning & Sanitation",
            "type":"Services"
        }
    ],
    "sg:phone":"+61 8 9444 4446",
    "sg:postcode":"6017",
    "sg:province":"WA",
    "sg:tags":[
        "abrasive",
        "blasting"
    ],
    "wof:name":"WS Coating Services",
    "wof:placetype":"venue"
},
  "geometry": {"coordinates":[115.818321228,-31.9107723236],"type":"Point"}
}