{
  "type": "Feature",
  "properties": {
    "addr:full":"Princes Hwy Mogo NSW 2536",
    "addr:postcode":"2536",
    "addr:street":"Princes Hwy",
    "iso:country":"AU",
    "sg:address":"Princes Hwy",
    "sg:city":"Mogo",
    "sg:classifiers":[
        {
            "category":"Autos & Motor Vehicles",
            "subcategory":"Fuel & Gas Station",
            "type":"Retail Goods"
        }
    ],
    "sg:phone":"+61 2 4471 7201",
    "sg:postcode":"2536",
    "sg:province":"NSW",
    "wof:name":"Mobil Oil Australia Limited",
    "wof:placetype":"venue"
},
  "geometry": {"coordinates":[150.141479492,-35.7847480774],"type":"Point"}
}