{
  "type": "Feature",
  "properties": {
    "iso:country":"AU",
    "sg:address":"Centre For Neurological Support - The Niche Suite B, 11 Aberdare Rd",
    "sg:city":"Nedlands",
    "sg:classifiers":[
        {
            "category":"Organizations",
            "subcategory":"Non-profit Organization",
            "type":"Services"
        }
    ],
    "sg:phone":"+61 8 9346 7522",
    "sg:postcode":"6009",
    "sg:province":"WA",
    "sg:tags":[
        "support",
        "disability",
        "organisation"
    ],
    "wof:name":"Australasian Spinal Research Trust",
    "wof:placetype":"venue"
},
  "geometry": {"coordinates":[115.816978,-31.96452],"type":"Point"}
}