{
  "type": "Feature",
  "properties": {
    "iso:country":"AU",
    "sg:address":"56 Maitland Rd",
    "sg:city":"Branxton",
    "sg:classifiers":[
        {
            "category":"Food & Beverages",
            "subcategory":"Supermarket",
            "type":"Retail Goods"
        }
    ],
    "sg:phone":"+61 2 4938 1232",
    "sg:postcode":"2335",
    "sg:province":"NSW",
    "sg:tags":[
        "grocery",
        "store"
    ],
    "wof:name":"Welcome Mart",
    "wof:placetype":"venue"
},
  "geometry": {"coordinates":[151.35267639200001,-32.6560821533],"type":"Point"}
}