{
  "type": "Feature",
  "properties": {
    "iso:country":"AU",
    "sg:address":"759 Sandgate Rd",
    "sg:city":"Clayfield",
    "sg:classifiers":[
        {
            "category":"Health Services",
            "subcategory":"Dentist",
            "type":"Services"
        }
    ],
    "sg:phone":"+61 7 3862 1702",
    "sg:postcode":"4011",
    "sg:province":"QLD",
    "wof:name":"Close Paul K",
    "wof:placetype":"venue"
},
  "geometry": {"coordinates":[153.056625,-27.417711],"type":"Point"}
}