{
  "type": "Feature",
  "properties": {
    "iso:country":"AU",
    "sg:address":"Park Rd",
    "sg:city":"Elmore",
    "sg:classifiers":[
        {
            "category":"Commercial Area",
            "type":"Public Place"
        }
    ],
    "sg:phone":"+61 3 5432 6387",
    "sg:postcode":"3558",
    "sg:province":"VIC",
    "sg:tags":[
        "heavy",
        "carrier"
    ],
    "wof:name":"Lonsdale Contracting",
    "wof:placetype":"venue"
},
  "geometry": {"coordinates":[144.60447692899999,-36.4940872192],"type":"Point"}
}