{
  "type": "Feature",
  "properties": {
    "addr:full":"158 Main St Blacktown NSW 2148",
    "addr:housenumber":"158",
    "addr:postcode":"2148",
    "addr:street":"Main St",
    "iso:country":"AU",
    "sg:address":"158 Main St",
    "sg:city":"Blacktown",
    "sg:classifiers":[
        {
            "category":"Retail",
            "subcategory":"Auto Repair",
            "type":"Services"
        }
    ],
    "sg:phone":"+61 2 9622 1032",
    "sg:postcode":"2148",
    "sg:province":"NSW",
    "sg:tags":[
        "electrical"
    ],
    "wof:name":"Blacktown Auto Electrical",
    "wof:placetype":"venue"
},
  "geometry": {"coordinates":[150.91363525400001,-33.773059845],"type":"Point"}
}