{
  "type": "Feature",
  "properties": {
    "iso:country":"AU",
    "sg:address":"Shop 1, Salty's Arcade 47 Bourbong St",
    "sg:city":"Bundaberg",
    "sg:classifiers":[
        {
            "category":"Banks & Credit Unions",
            "subcategory":"Investment Brokerage",
            "type":"Services"
        }
    ],
    "sg:phone":"+61 7 4154 3944",
    "sg:postcode":"4670",
    "sg:province":"QLD",
    "sg:tags":[
        "cashing",
        "cheque"
    ],
    "wof:name":"AMX Money",
    "wof:placetype":"venue"
},
  "geometry": {"coordinates":[152.35028076200001,-24.8654918671],"type":"Point"}
}