{
  "type": "Feature",
  "properties": {
    "addr:full":"104 Elizabeth St Launceston TAS 7250",
    "addr:housenumber":"104",
    "addr:postcode":"7250",
    "addr:street":"Elizabeth St",
    "iso:country":"AU",
    "sg:address":"104 Elizabeth St",
    "sg:city":"Launceston",
    "sg:classifiers":[
        {
            "category":"Home & Garden",
            "subcategory":"Building Materials",
            "type":"Retail Goods"
        }
    ],
    "sg:phone":"+61 408 649 832",
    "sg:postcode":"7250",
    "sg:province":"TAS",
    "sg:tags":[
        "lawn",
        "cutting",
        "maintenance"
    ],
    "wof:name":"Caretaker Property Maintenance",
    "wof:placetype":"venue"
},
  "geometry": {"coordinates":[147.13824462900001,-41.4405937195],"type":"Point"}
}