{
  "type": "Feature",
  "properties": {
    "iso:country":"AU",
    "sg:address":"990 Wanneroo Rd",
    "sg:city":"Wanneroo",
    "sg:classifiers":[
        {
            "category":"Education",
            "subcategory":"Kindergarten",
            "type":"Public Place"
        }
    ],
    "sg:phone":"+61 8 9405 1816",
    "sg:postcode":"6065",
    "sg:province":"WA",
    "sg:tags":[
        "pre-schools"
    ],
    "wof:name":"Catholic Church",
    "wof:placetype":"venue"
},
  "geometry": {"coordinates":[115.78511047400001,-31.7216510773],"type":"Point"}
}