{
  "type": "Feature",
  "properties": {
    "addr:full":"Southside Diagnostic Services Group 74 Old Cleveland Rd Capalaba QLD 4157",
    "addr:housenumber":"74",
    "addr:postcode":"4157",
    "addr:street":"Old Cleveland Rd",
    "iso:country":"AU",
    "sg:address":"Southside Diagnostic Services Group 74 Old Cleveland Rd",
    "sg:city":"Capalaba",
    "sg:classifiers":[
        {
            "category":"Health Services",
            "subcategory":"Doctor",
            "type":"Services"
        }
    ],
    "sg:phone":"+61 7 3245 2110",
    "sg:postcode":"4157",
    "sg:province":"QLD",
    "sg:tags":[
        "medical",
        "practitioner"
    ],
    "wof:name":"Thorn Murray Dr",
    "wof:placetype":"venue"
},
  "geometry": {"coordinates":[153.19778442399999,-27.521150589],"type":"Point"}
}