{
  "type": "Feature",
  "properties": {
    "addr:full":"Southwest Sports Centre, 1 Rotary Drv, Hay Park Bunbury WA 6230",
    "addr:housenumber":"1",
    "addr:postcode":"6230",
    "addr:street":"Rotary Drv Hay Park",
    "iso:country":"AU",
    "sg:address":"Southwest Sports Centre, 1",
    "sg:city":"Rotary Drv, Hay Park Bunbury",
    "sg:classifiers":[
        {
            "category":"Health Services",
            "subcategory":"Health Practitioner",
            "type":"Services"
        }
    ],
    "sg:phone":"+61 8 9795 4111",
    "sg:postcode":"6230",
    "sg:province":"WA",
    "sg:tags":[
        "alternative"
    ],
    "wof:name":"Bunbury Naturopathic Medicine & Health Services",
    "wof:placetype":"venue"
},
  "geometry": {"coordinates":[115.645348,-33.380112],"type":"Point"}
}