{
  "type": "Feature",
  "properties": {
    "iso:country":"AU",
    "sg:address":"Shop 2030 Westfield Shoppingtown",
    "sg:city":"Hornsby",
    "sg:classifiers":[
        {
            "category":"Cafe",
            "type":"Food & Drink"
        }
    ],
    "sg:phone":"+61 2 9987 1160",
    "sg:postcode":"2077",
    "sg:province":"NSW",
    "wof:name":"Cafe Florence",
    "wof:placetype":"venue"
},
  "geometry": {"coordinates":[151.09991455100001,-33.7072372437],"type":"Point"}
}