{
  "type": "Feature",
  "properties": {
    "iso:country":"AU",
    "sg:address":"Shop 12 Erica Ave",
    "sg:city":"Boronia",
    "sg:classifiers":[
        {
            "category":"Personal",
            "subcategory":"Beauty Salon",
            "type":"Services"
        }
    ],
    "sg:phone":"+61 3 9762 6706",
    "sg:postcode":"3155",
    "sg:province":"VIC",
    "sg:tags":[
        "hairdresser"
    ],
    "wof:name":"Hair Today",
    "wof:placetype":"venue"
},
  "geometry": {"coordinates":[145.28417968799999,-37.8612365723],"type":"Point"}
}