{
  "type": "Feature",
  "properties": {
    "iso:country":"AU",
    "sg:address":"16A Mitchell St",
    "sg:city":"Merredin",
    "sg:classifiers":[
        {
            "category":"Professional",
            "subcategory":"Accounting & Tax Preparation",
            "type":"Services"
        }
    ],
    "sg:phone":"+61 8 9041 1022",
    "sg:postcode":"6415",
    "sg:province":"WA",
    "sg:tags":[
        "consultant",
        "taxation"
    ],
    "wof:name":"Byfields",
    "wof:placetype":"venue"
},
  "geometry": {"coordinates":[118.27660369900001,-31.4809646606],"type":"Point"}
}