{
  "type": "Feature",
  "properties": {
    "addr:full":"73 Murray St Tanunda SA 5352",
    "addr:housenumber":"73",
    "addr:postcode":"5352",
    "addr:street":"Murray St",
    "iso:country":"AU",
    "sg:address":"73 Murray St",
    "sg:city":"Tanunda",
    "sg:classifiers":[
        {
            "category":"Travel",
            "subcategory":"Hotels & Motels",
            "type":"Entertainment"
        }
    ],
    "sg:phone":"+61 8 8563 2039",
    "sg:postcode":"5352",
    "sg:province":"SA",
    "wof:name":"Valley Hotel Motel",
    "wof:placetype":"venue"
},
  "geometry": {"coordinates":[138.969512939,-34.5168914795],"type":"Point"}
}