{
  "type": "Feature",
  "properties": {
    "iso:country":"AU",
    "sg:address":"234 New Town Rd",
    "sg:city":"New Town",
    "sg:classifiers":[
        {
            "category":"Retail",
            "subcategory":"Auto Rental",
            "type":"Services"
        }
    ],
    "sg:phone":"+61 418 126 357",
    "sg:postcode":"7008",
    "sg:province":"TAS",
    "sg:tags":[
        "chauffeur",
        "car",
        "hire",
        "driven",
        "limousine"
    ],
    "wof:name":"S.V.R. International Marketing",
    "wof:placetype":"venue"
},
  "geometry": {"coordinates":[147.30035400400001,-42.8533363342],"type":"Point"}
}