{
  "type": "Feature",
  "properties": {
    "addr:full":"PO Box 156 Hurlstone Park NSW 2193",
    "addr:postcode":"2193",
    "iso:country":"AU",
    "sg:address":"PO Box 156",
    "sg:city":"Hurlstone Park",
    "sg:classifiers":[
        {
            "category":"Professional",
            "subcategory":"Accounting & Tax Preparation",
            "type":"Services"
        }
    ],
    "sg:phone":"+61 413 511 570",
    "sg:postcode":"2193",
    "sg:province":"NSW",
    "sg:tags":[
        "bookkeeping"
    ],
    "wof:name":"Dorgrow Pty Ltd",
    "wof:placetype":"venue"
},
  "geometry": {"coordinates":[151.12794500000001,-33.906818],"type":"Point"}
}