{
  "type": "Feature",
  "properties": {
    "addr:full":"149 Old Cleveland Rd Capalaba QLD 4157",
    "addr:housenumber":"149",
    "addr:postcode":"4157",
    "addr:street":"Old Cleveland Rd",
    "iso:country":"AU",
    "sg:address":"149 Old Cleveland Rd",
    "sg:city":"Capalaba",
    "sg:classifiers":[
        {
            "category":"Personal",
            "subcategory":"Hair Removal",
            "type":"Services"
        }
    ],
    "sg:phone":"+61 7 3245 5247",
    "sg:postcode":"4157",
    "sg:province":"QLD",
    "wof:name":"Simply Beautiful Skin And Beauty Clinic",
    "wof:placetype":"venue"
},
  "geometry": {"coordinates":[153.19944763199999,-27.5217285156],"type":"Point"}
}