{
  "type": "Feature",
  "properties": {
    "iso:country":"AU",
    "sg:address":"Ste 2/ 75 Main St",
    "sg:city":"Alstonville",
    "sg:classifiers":[
        {
            "category":"Shopping",
            "subcategory":"Clothing, Apparel, & Fashions",
            "type":"Retail Goods"
        }
    ],
    "sg:phone":"+61 2 6628 6335",
    "sg:postcode":"2477",
    "sg:province":"NSW",
    "sg:tags":[
        "accessory"
    ],
    "wof:name":"Candy Lane",
    "wof:placetype":"venue"
},
  "geometry": {"coordinates":[153.435943603,-28.8380241394],"type":"Point"}
}