{
  "type": "Feature",
  "properties": {
    "iso:country":"AU",
    "sg:address":"4 Azolla Crt",
    "sg:city":"Coogee",
    "sg:classifiers":[
        {
            "category":"Professional",
            "subcategory":"Testing Lab",
            "type":"Services"
        }
    ],
    "sg:phone":"+61 8 9437 4123",
    "sg:postcode":"6166",
    "sg:province":"WA",
    "sg:tags":[
        "inspection"
    ],
    "wof:name":"Torque Testers",
    "wof:placetype":"venue"
},
  "geometry": {"coordinates":[115.774651,-32.124947],"type":"Point"}
}