{
  "type": "Feature",
  "properties": {
    "iso:country":"AU",
    "sg:address":"Level 7, 220 George St",
    "sg:city":"Sydney",
    "sg:classifiers":[
        {
            "category":"Professional",
            "subcategory":"Employment Agencies",
            "type":"Services"
        }
    ],
    "sg:phone":"+61 2 9240 6666",
    "sg:postcode":"2000",
    "sg:province":"NSW",
    "wof:name":"Brooklyn Group Pty Ltd",
    "wof:placetype":"venue"
},
  "geometry": {"coordinates":[151.20780944800001,-33.8624191284],"type":"Point"}
}