{
  "type": "Feature",
  "properties": {
    "iso:country":"AU",
    "sg:address":"496 Guildford Rd",
    "sg:city":"Bayswater",
    "sg:classifiers":[
        {
            "category":"Recreation",
            "subcategory":"Amusement Park",
            "type":"Entertainment"
        }
    ],
    "sg:phone":"+61 8 9279 8233",
    "sg:postcode":"6053",
    "sg:province":"WA",
    "wof:name":"Bingo Centre The",
    "wof:placetype":"venue"
},
  "geometry": {"coordinates":[115.921318054,-31.9237937927],"type":"Point"}
}