{
  "type": "Feature",
  "properties": {
    "iso:country":"AU",
    "sg:address":"20 Lakeside Drv",
    "sg:city":"Burwood East",
    "sg:classifiers":[
        {
            "category":"Professional",
            "subcategory":"Computer Services",
            "type":"Services"
        }
    ],
    "sg:phone":"+61 3 9887 7770",
    "sg:postcode":"3151",
    "sg:province":"VIC",
    "sg:tags":[
        "package",
        "software"
    ],
    "wof:name":"Pronto Software Pty Ltd",
    "wof:placetype":"venue"
},
  "geometry": {"coordinates":[145.166381836,-37.8559303284],"type":"Point"}
}