{
  "type": "Feature",
  "properties": {
    "addr:full":"48 Archbold Rd Long Jetty NSW 2261",
    "addr:housenumber":"48",
    "addr:postcode":"2261",
    "addr:street":"Archbold Rd",
    "iso:country":"AU",
    "sg:address":"48 Archbold Rd",
    "sg:city":"Long Jetty",
    "sg:classifiers":[
        {
            "category":"Building & Trades",
            "subcategory":"Construction",
            "type":"Services"
        }
    ],
    "sg:phone":"+61 439 889 229",
    "sg:postcode":"2261",
    "sg:province":"NSW",
    "sg:tags":[
        "earth",
        "excavating",
        "moving",
        "contractor"
    ],
    "wof:name":"K.O Mini Excavations",
    "wof:placetype":"venue"
},
  "geometry": {"coordinates":[151.49302700000001,-33.357254],"type":"Point"}
}