{
  "type": "Feature",
  "properties": {
    "iso:country":"AU",
    "sg:address":"514 Miller St",
    "sg:city":"Cammeray",
    "sg:classifiers":[
        {
            "category":"Professional",
            "subcategory":"Engineering",
            "type":"Services"
        }
    ],
    "sg:phone":"+61 2 9922 3855",
    "sg:postcode":"2062",
    "sg:province":"NSW",
    "sg:tags":[
        "consulting",
        "engineer"
    ],
    "wof:name":"Taylor Lauder Bersten Pty Ltd",
    "wof:placetype":"venue"
},
  "geometry": {"coordinates":[151.210372925,-33.8214645386],"type":"Point"}
}