{
  "type": "Feature",
  "properties": {
    "iso:country":"AU",
    "sg:address":"Shop 5 248 Carp St",
    "sg:city":"Bega",
    "sg:classifiers":[
        {
            "category":"Retail",
            "subcategory":"Repair Shop",
            "type":"Services"
        }
    ],
    "sg:phone":"+61 2 6492 2872",
    "sg:postcode":"2550",
    "sg:province":"NSW",
    "sg:tags":[
        "machine",
        "sewing"
    ],
    "wof:name":"Country Crafts & Cottons",
    "wof:placetype":"venue"
},
  "geometry": {"coordinates":[149.84379577600001,-36.6742935181],"type":"Point"}
}