{
  "type": "Feature",
  "properties": {
    "iso:country":"AU",
    "sg:address":"Shop 23, Lisarow Plaza Pacific Hwy",
    "sg:city":"Lisarow",
    "sg:classifiers":[
        {
            "category":"Health Services",
            "subcategory":"Health Practitioner",
            "type":"Services"
        }
    ],
    "sg:phone":"+61 2 4328 4100",
    "sg:postcode":"2250",
    "sg:province":"NSW",
    "sg:tags":[
        "physiotherapist"
    ],
    "wof:name":"Silcock John",
    "wof:placetype":"venue"
},
  "geometry": {"coordinates":[151.37428283700001,-33.379070282],"type":"Point"}
}