{
  "type": "Feature",
  "properties": {
    "addr:full":"Shop 1/ 1 Short St Broome WA 6725",
    "addr:housenumber":"shop 1 / 1",
    "addr:postcode":"6725",
    "addr:street":"Short St",
    "iso:country":"AU",
    "sg:address":"Shop 1/ 1 Short St",
    "sg:city":"Broome",
    "sg:classifiers":[
        {
            "category":"Manufacturing",
            "subcategory":"Jewelry",
            "type":"Manufacturing & Wholesale Goods"
        }
    ],
    "sg:phone":"+61 8 9192 7300",
    "sg:postcode":"6725",
    "sg:province":"WA",
    "sg:tags":[
        "designer",
        "jewellery"
    ],
    "wof:name":"Camdons Fine Jewellery",
    "wof:placetype":"venue"
},
  "geometry": {"coordinates":[122.244430542,-17.9533729553],"type":"Point"}
}