{
  "type": "Feature",
  "properties": {
    "addr:full":"2/ 18 William St Gatton QLD 4343",
    "addr:housenumber":"/ 18",
    "addr:postcode":"4343",
    "addr:street":"William St",
    "iso:country":"AU",
    "sg:address":"2/ 18 William St",
    "sg:city":"Gatton",
    "sg:classifiers":[
        {
            "category":"Shopping",
            "subcategory":"Stationery & Office Supplies",
            "type":"Retail Goods"
        }
    ],
    "sg:phone":"+61 448 525 199",
    "sg:postcode":"4343",
    "sg:province":"QLD",
    "wof:name":"Office Essentials Plus",
    "wof:placetype":"venue"
},
  "geometry": {"coordinates":[152.27830505399999,-27.5594272614],"type":"Point"}
}