{
  "type": "Feature",
  "properties": {
    "addr:full":"19 Governor King Drv Caboolture QLD 4510",
    "addr:housenumber":"19",
    "addr:postcode":"4510",
    "addr:street":"Governor King Drv",
    "iso:country":"AU",
    "sg:address":"19 Governor King Drv",
    "sg:city":"Caboolture",
    "sg:classifiers":[
        {
            "category":"Professional",
            "subcategory":"Business Services",
            "type":"Services"
        }
    ],
    "sg:phone":"+61 7 5495 2948",
    "sg:postcode":"4510",
    "sg:province":"QLD",
    "sg:tags":[
        "drafting"
    ],
    "wof:name":"Caboolture Building Designers",
    "wof:placetype":"venue"
},
  "geometry": {"coordinates":[152.937927,-27.089273],"type":"Point"}
}