{
  "type": "Feature",
  "properties": {
    "addr:full":"Barker St Kensington NSW 2033",
    "addr:postcode":"2033",
    "addr:street":"Barker St",
    "iso:country":"AU",
    "sg:address":"Barker St",
    "sg:city":"Kensington",
    "sg:classifiers":[
        {
            "category":"Recreation",
            "subcategory":"Amusement Park",
            "type":"Entertainment"
        }
    ],
    "sg:phone":"+61 2 9663 2538",
    "sg:postcode":"2033",
    "sg:province":"NSW",
    "wof:name":"Kensington Oval",
    "wof:placetype":"venue"
},
  "geometry": {"coordinates":[151.22169500000001,-33.91951],"type":"Point"}
}