{
  "type": "Feature",
  "properties": {
    "iso:country":"AU",
    "sg:address":"49 John St",
    "sg:city":"Oakleigh",
    "sg:classifiers":[
        {
            "category":"Professional",
            "type":"Services"
        }
    ],
    "sg:phone":"+61 3 9569 6900",
    "sg:postcode":"3166",
    "sg:province":"VIC",
    "sg:tags":[
        "transport"
    ],
    "wof:name":"LDJ Distribution Pty Ltd",
    "wof:placetype":"venue"
},
  "geometry": {"coordinates":[145.100463867,-37.9051246643],"type":"Point"}
}