{
  "type": "Feature",
  "properties": {
    "addr:full":"Level 2/ 393 George St Sydney NSW 2000",
    "addr:housenumber":"/ 393",
    "addr:postcode":"2000",
    "addr:street":"George St",
    "iso:country":"AU",
    "sg:address":"Level 2/ 393 George St",
    "sg:city":"Sydney",
    "sg:classifiers":[
        {
            "category":"Shopping",
            "subcategory":"Bridal",
            "type":"Retail Goods"
        }
    ],
    "sg:phone":"+61 2 9262 4090",
    "sg:postcode":"2000",
    "sg:province":"NSW",
    "sg:tags":[
        "hire",
        "wear"
    ],
    "sg:website":"http://www.millanibridal.com.au",
    "wof:name":"Millani Bridal Boutique",
    "wof:placetype":"venue"
},
  "geometry": {"coordinates":[151.206787109,-33.8695068359],"type":"Point"}
}