{
  "type": "Feature",
  "properties": {
    "addr:full":"PO Box 446 South Melbourne VIC 3205",
    "addr:postcode":"3205",
    "iso:country":"AU",
    "sg:address":"PO Box 446",
    "sg:city":"South Melbourne",
    "sg:classifiers":[
        {
            "category":"Professional",
            "subcategory":"Research",
            "type":"Services"
        }
    ],
    "sg:phone":"+61 3 9509 1244",
    "sg:postcode":"3205",
    "sg:province":"VIC",
    "sg:tags":[
        "market"
    ],
    "wof:name":"The Key Response",
    "wof:placetype":"venue"
},
  "geometry": {"coordinates":[144.95585632300001,-37.8338813782],"type":"Point"}
}