{
  "type": "Feature",
  "properties": {
    "iso:country":"AU",
    "sg:address":"6 Burton Rd",
    "sg:city":"Margaret River",
    "sg:classifiers":[
        {
            "category":"Retail",
            "subcategory":"Auto Repair",
            "type":"Services"
        }
    ],
    "sg:phone":"+61 8 9757 2917",
    "sg:postcode":"6285",
    "sg:province":"WA",
    "sg:tags":[
        "electrical"
    ],
    "wof:name":"Margaret River/Augusta Auto Electrics",
    "wof:placetype":"venue"
},
  "geometry": {"coordinates":[115.07170105,-33.9652519226],"type":"Point"}
}