{
  "type": "Feature",
  "properties": {
    "addr:full":"45 Stanley St West Melbourne VIC 3003",
    "addr:housenumber":"45",
    "addr:postcode":"3003",
    "addr:street":"Stanley St",
    "iso:country":"AU",
    "sg:address":"45 Stanley St",
    "sg:city":"West Melbourne",
    "sg:classifiers":[
        {
            "category":"Retail",
            "subcategory":"Auto Repair",
            "type":"Services"
        }
    ],
    "sg:phone":"+61 3 9326 3611",
    "sg:postcode":"3003",
    "sg:province":"VIC",
    "sg:tags":[
        "beater",
        "painter",
        "panel"
    ],
    "wof:name":"Gladstone Motor & Panel Pty Ltd",
    "wof:placetype":"venue"
},
  "geometry": {"coordinates":[144.94972229000001,-37.8079986572],"type":"Point"}
}