{
  "type": "Feature",
  "properties": {
    "iso:country":"AU",
    "sg:address":"PO Box 7041",
    "sg:city":"Bondi Beach",
    "sg:classifiers":[
        {
            "category":"Retail",
            "subcategory":"Repair Shop",
            "type":"Services"
        }
    ],
    "sg:phone":"+61 2 9130 3575",
    "sg:postcode":"2026",
    "sg:province":"NSW",
    "sg:tags":[
        "maintenance",
        "pool",
        "swimming"
    ],
    "wof:name":"Sydney Central Pool Service",
    "wof:placetype":"venue"
},
  "geometry": {"coordinates":[151.277786255,-33.8887290955],"type":"Point"}
}