{
  "type": "Feature",
  "properties": {
    "addr:full":"858a Pittwater Rd Dee Why NSW 2099",
    "addr:housenumber":"858a",
    "addr:postcode":"2099",
    "addr:street":"Pittwater Rd",
    "iso:country":"AU",
    "sg:address":"858a Pittwater Rd",
    "sg:city":"Dee Why",
    "sg:classifiers":[
        {
            "category":"Shopping",
            "subcategory":"Party Supplies",
            "type":"Retail Goods"
        }
    ],
    "sg:phone":"+61 2 9982 7714",
    "sg:postcode":"2099",
    "sg:province":"NSW",
    "sg:tags":[
        "children's"
    ],
    "wof:name":"Xtopia Xbox Game Centre",
    "wof:placetype":"venue"
},
  "geometry": {"coordinates":[151.28518676799999,-33.7539520264],"type":"Point"}
}