{
  "type": "Feature",
  "properties": {
    "iso:country":"AU",
    "sg:address":"659 Geelong Rd",
    "sg:city":"Brooklyn",
    "sg:classifiers":[
        {
            "category":"Professional",
            "subcategory":"Engineering",
            "type":"Services"
        }
    ],
    "sg:phone":"+61 3 9314 7368",
    "sg:postcode":"3025",
    "sg:province":"VIC",
    "sg:tags":[
        "engineer"
    ],
    "wof:name":"Matthews N R",
    "wof:placetype":"venue"
},
  "geometry": {"coordinates":[144.839905,-37.819664],"type":"Point"}
}