{
  "type": "Feature",
  "properties": {
    "iso:country":"AU",
    "sg:address":"52 Venn St",
    "sg:city":"North Perth",
    "sg:classifiers":[
        {
            "category":"Real Estate",
            "subcategory":"Architect",
            "type":"Services"
        }
    ],
    "sg:phone":"+61 419 835 838",
    "sg:postcode":"6006",
    "sg:province":"WA",
    "wof:name":"Babich Paula",
    "wof:placetype":"venue"
},
  "geometry": {"coordinates":[115.859703064,-31.9278640747],"type":"Point"}
}