{
  "type": "Feature",
  "properties": {
    "iso:country":"AU",
    "sg:address":"80 Oxley Rd",
    "sg:city":"Chelmer",
    "sg:classifiers":[
        {
            "category":"Home & Garden",
            "subcategory":"Furniture",
            "type":"Retail Goods"
        }
    ],
    "sg:phone":"+61 7 3379 7294",
    "sg:postcode":"4068",
    "sg:province":"QLD",
    "sg:tags":[
        "business"
    ],
    "wof:name":"Ascot Office System",
    "wof:placetype":"venue"
},
  "geometry": {"coordinates":[152.97703552199999,-27.514541626],"type":"Point"}
}