{
  "type": "Feature",
  "properties": {
    "iso:country":"AU",
    "sg:address":"Shop 58 Morayfield Shopng Cntr Morayfield Rd",
    "sg:city":"Morayfield",
    "sg:classifiers":[
        {
            "category":"Personal",
            "subcategory":"Skin Care",
            "type":"Services"
        }
    ],
    "sg:phone":"+61 7 5498 9177",
    "sg:postcode":"4506",
    "sg:province":"QLD",
    "sg:tags":[
        "hair",
        "product"
    ],
    "wof:name":"Price Attack",
    "wof:placetype":"venue"
},
  "geometry": {"coordinates":[152.94964599599999,-27.1097755432],"type":"Point"}
}