{
  "type": "Feature",
  "properties": {
    "addr:full":"134 Knees Rd Park Orchards VIC 3114",
    "addr:housenumber":"134",
    "addr:postcode":"3114",
    "addr:street":"Knees Rd",
    "iso:country":"AU",
    "sg:address":"134 Knees Rd",
    "sg:city":"Park Orchards",
    "sg:classifiers":[
        {
            "category":"Building & Trades",
            "subcategory":"Construction",
            "type":"Services"
        }
    ],
    "sg:phone":"+61 3 9844 2136",
    "sg:postcode":"3114",
    "sg:province":"VIC",
    "sg:tags":[
        "contractor"
    ],
    "wof:name":"Wilson Bros F&J",
    "wof:placetype":"venue"
},
  "geometry": {"coordinates":[145.21890258799999,-37.764415741],"type":"Point"}
}