{
  "type": "Feature",
  "properties": {
    "addr:full":"83 Delaney Drv Baulkham Hills NSW 2153",
    "addr:housenumber":"83",
    "addr:postcode":"2153",
    "addr:street":"Delaney Drv",
    "iso:country":"AU",
    "sg:address":"83 Delaney Drv",
    "sg:city":"Baulkham Hills",
    "sg:classifiers":[
        {
            "category":"Professional",
            "subcategory":"Accounting & Tax Preparation",
            "type":"Services"
        }
    ],
    "sg:phone":"+61 2 9899 4104",
    "sg:postcode":"2153",
    "sg:province":"NSW",
    "sg:tags":[
        "accountant",
        "auditor"
    ],
    "wof:name":"Anchor Accounting Services",
    "wof:placetype":"venue"
},
  "geometry": {"coordinates":[150.98245239299999,-33.7384147644],"type":"Point"}
}