{
  "type": "Feature",
  "properties": {
    "addr:full":"Shop A - Unit 2/ 11 Timms Crt Underwood QLD 4119",
    "addr:housenumber":"2 / 11",
    "addr:postcode":"4119",
    "addr:street":"Timms Crt",
    "iso:country":"AU",
    "sg:address":"Shop A - Unit 2/ 11 Timms Crt",
    "sg:city":"Underwood",
    "sg:classifiers":[
        {
            "category":"Building & Trades",
            "subcategory":"Pest Control",
            "type":"Services"
        }
    ],
    "sg:phone":"+61 419 558 033",
    "sg:postcode":"4119",
    "sg:province":"QLD",
    "sg:tags":[
        "technical",
        "consultant"
    ],
    "wof:name":"J-Tech Engineering",
    "wof:placetype":"venue"
},
  "geometry": {"coordinates":[153.10700988799999,-27.620349884],"type":"Point"}
}