{
  "type": "Feature",
  "properties": {
    "addr:full":"10 Archer St West Midland WA 6056",
    "addr:housenumber":"10",
    "addr:postcode":"6056",
    "addr:street":"Archer St West",
    "iso:country":"AU",
    "sg:address":"10 Archer St",
    "sg:city":"West Midland",
    "sg:classifiers":[
        {
            "category":"Education",
            "subcategory":"School",
            "type":"Public Place"
        }
    ],
    "sg:phone":"+61 8 9274 2778",
    "sg:postcode":"6056",
    "sg:province":"WA",
    "sg:tags":[
        "state",
        "except",
        "nsw"
    ],
    "wof:name":"West Midland Primary",
    "wof:placetype":"venue"
},
  "geometry": {"coordinates":[115.99624633800001,-31.893245697],"type":"Point"}
}