{
  "type": "Feature",
  "properties": {
    "addr:full":"160 Ipswich Rd Woolloongabba QLD 4102",
    "addr:housenumber":"160",
    "addr:postcode":"4102",
    "addr:street":"Ipswich Rd",
    "iso:country":"AU",
    "sg:address":"160 Ipswich Rd",
    "sg:city":"Woolloongabba",
    "sg:classifiers":[
        {
            "category":"Insurance",
            "subcategory":"Hazard Insurance",
            "type":"Services"
        }
    ],
    "sg:phone":"+61 418 235 267",
    "sg:postcode":"4102",
    "sg:province":"QLD",
    "sg:tags":[
        "loss",
        "adjuster",
        "assessor"
    ],
    "wof:name":"Saunair Insurance Risk Management Advice Co www.saunair.com.au",
    "wof:placetype":"venue"
},
  "geometry": {"coordinates":[153.03468322800001,-27.4943256378],"type":"Point"}
}