{
  "type": "Feature",
  "properties": {
    "iso:country":"AU",
    "sg:address":"13 Poppel St",
    "sg:city":"Gladstone",
    "sg:classifiers":[
        {
            "category":"Manufacturing",
            "subcategory":"Signs",
            "type":"Manufacturing & Wholesale Goods"
        }
    ],
    "sg:phone":"+61 417 648 302",
    "sg:postcode":"4680",
    "sg:province":"QLD",
    "sg:tags":[
        "traffic",
        "safety"
    ],
    "wof:name":"Gladstone Sign Service",
    "wof:placetype":"venue"
},
  "geometry": {"coordinates":[151.250076294,-23.8737430573],"type":"Point"}
}