{
  "type": "Feature",
  "properties": {
    "addr:full":"Unit 1, 34 Deepdene Rd Balwyn VIC 3103",
    "addr:housenumber":"34",
    "addr:postcode":"3103",
    "addr:street":"Deepdene Rd",
    "iso:country":"AU",
    "sg:address":"Unit 1, 34 Deepdene Rd",
    "sg:city":"Balwyn",
    "sg:classifiers":[
        {
            "category":"Real Estate",
            "subcategory":"Surveying",
            "type":"Services"
        }
    ],
    "sg:phone":"+61 3 9817 6293",
    "sg:postcode":"3103",
    "sg:province":"VIC",
    "sg:tags":[
        "surveyor",
        "land"
    ],
    "wof:name":"BT Surveys Pty Ltd",
    "wof:placetype":"venue"
},
  "geometry": {"coordinates":[145.061965942,-37.813419342],"type":"Point"}
}