{
  "type": "Feature",
  "properties": {
    "iso:country":"AU",
    "sg:address":"14 Clarenden St",
    "sg:city":"East Brisbane",
    "sg:classifiers":[
        {
            "category":"Autos & Motor Vehicles",
            "subcategory":"Fuel & Gas Station",
            "type":"Retail Goods"
        }
    ],
    "sg:phone":"+61 7 3358 3407",
    "sg:postcode":"4169",
    "sg:province":"QLD",
    "wof:name":"Vitanza Vince Enterprises Pty Ltd",
    "wof:placetype":"venue"
},
  "geometry": {"coordinates":[153.047897339,-27.4833755493],"type":"Point"}
}