{
  "type": "Feature",
  "properties": {
    "addr:full":"189 Graham St Wonthaggi VIC 3995",
    "addr:housenumber":"189",
    "addr:postcode":"3995",
    "addr:street":"Graham St",
    "iso:country":"AU",
    "sg:address":"189 Graham St",
    "sg:city":"Wonthaggi",
    "sg:classifiers":[
        {
            "category":"Health Services",
            "subcategory":"Dentist",
            "type":"Services"
        }
    ],
    "sg:phone":"+61 3 5672 1026",
    "sg:postcode":"3995",
    "sg:province":"VIC",
    "wof:name":"Supreme Dental Surgery",
    "wof:placetype":"venue"
},
  "geometry": {"coordinates":[145.58854700000001,-38.605999],"type":"Point"}
}