{
  "type": "Feature",
  "properties": {
    "iso:country":"AU",
    "sg:address":"18a Channel Crt",
    "sg:city":"Kingston",
    "sg:classifiers":[
        {
            "category":"Fast Food",
            "type":"Food & Drink"
        }
    ],
    "sg:phone":"+61 3 6229 5033",
    "sg:postcode":"7050",
    "sg:province":"TAS",
    "sg:tags":[
        "away",
        "take"
    ],
    "wof:name":"La'Venezia Pizza Cafe",
    "wof:placetype":"venue"
},
  "geometry": {"coordinates":[147.310654,-42.975513],"type":"Point"}
}