{
  "type": "Feature",
  "properties": {
    "iso:country":"AU",
    "sg:address":"41 Semaphore Rd",
    "sg:city":"Semaphore",
    "sg:classifiers":[
        {
            "category":"Real Estate",
            "subcategory":"Real Estate Agent",
            "type":"Services"
        }
    ],
    "sg:phone":"+61 8 8449 1144",
    "sg:postcode":"5019",
    "sg:province":"SA",
    "wof:name":"Grace Real Estate",
    "wof:placetype":"venue"
},
  "geometry": {"coordinates":[138.483154297,-34.8384628296],"type":"Point"}
}