{
  "type": "Feature",
  "properties": {
    "iso:country":"AU",
    "sg:address":"107 Victoria St",
    "sg:city":"St George",
    "sg:classifiers":[
        {
            "category":"Personal",
            "subcategory":"Beauty Salon",
            "type":"Services"
        }
    ],
    "sg:phone":"+61 7 4625 3482",
    "sg:postcode":"4487",
    "sg:province":"QLD",
    "sg:tags":[
        "hairdresser"
    ],
    "wof:name":"Magic Mirror The",
    "wof:placetype":"venue"
},
  "geometry": {"coordinates":[148.58111572300001,-28.0357227325],"type":"Point"}
}