{
  "type": "Feature",
  "properties": {
    "addr:full":"14 Causarina Crt Canning Vale WA 6155",
    "addr:housenumber":"14",
    "addr:postcode":"6155",
    "addr:street":"Causarina Crt",
    "iso:country":"AU",
    "sg:address":"14 Causarina Crt",
    "sg:city":"Canning Vale",
    "sg:classifiers":[
        {
            "category":"Professional",
            "type":"Services"
        }
    ],
    "sg:phone":"+61 409 082 618",
    "sg:postcode":"6155",
    "sg:province":"WA",
    "sg:tags":[
        "transport"
    ],
    "wof:name":"Top Gear Transport Pty Ltd",
    "wof:placetype":"venue"
},
  "geometry": {"coordinates":[115.918449,-32.078934],"type":"Point"}
}