{
  "type": "Feature",
  "properties": {
    "addr:full":"15 Trebonne St The Gap QLD 4061",
    "addr:housenumber":"15",
    "addr:postcode":"4061",
    "addr:street":"Trebonne St",
    "iso:country":"AU",
    "sg:address":"15 Trebonne St",
    "sg:city":"The Gap",
    "sg:classifiers":[
        {
            "category":"Professional",
            "subcategory":"Secretarial Services",
            "type":"Services"
        }
    ],
    "sg:phone":"+61 7 3300 2412",
    "sg:postcode":"4061",
    "sg:province":"QLD",
    "sg:tags":[
        "typing"
    ],
    "wof:name":"KEF Business Services",
    "wof:placetype":"venue"
},
  "geometry": {"coordinates":[152.945022583,-27.4378929138],"type":"Point"}
}