{
  "type": "Feature",
  "properties": {
    "addr:full":"Unit 2, 17 Moss St Slacks Creek QLD 4127",
    "addr:housenumber":"17",
    "addr:postcode":"4127",
    "addr:street":"Moss St",
    "iso:country":"AU",
    "sg:address":"Unit 2, 17 Moss St",
    "sg:city":"Slacks Creek",
    "sg:classifiers":[
        {
            "category":"Retail",
            "subcategory":"Repair Shop",
            "type":"Services"
        }
    ],
    "sg:phone":"+61 7 3208 6055",
    "sg:postcode":"4127",
    "sg:province":"QLD",
    "sg:tags":[
        "windscreen"
    ],
    "wof:name":"Instant Windscreens",
    "wof:placetype":"venue"
},
  "geometry": {"coordinates":[153.11863708499999,-27.6245307922],"type":"Point"}
}