{
  "type": "Feature",
  "properties": {
    "addr:full":"925 Canterbury Rd Lakemba NSW 2195",
    "addr:housenumber":"925",
    "addr:postcode":"2195",
    "addr:street":"Canterbury Rd",
    "iso:country":"AU",
    "sg:address":"925 Canterbury Rd",
    "sg:city":"Lakemba",
    "sg:classifiers":[
        {
            "category":"Retail",
            "subcategory":"Event Space",
            "type":"Services"
        }
    ],
    "sg:phone":"+61 2 9758 9993",
    "sg:postcode":"2195",
    "sg:province":"NSW",
    "sg:tags":[
        "function",
        "organiser"
    ],
    "wof:name":"White Castle Receptions",
    "wof:placetype":"venue"
},
  "geometry": {"coordinates":[151.08308400000001,-33.926407],"type":"Point"}
}