{
  "type": "Feature",
  "properties": {
    "addr:full":"9 Flight Drv Tullamarine VIC 3043",
    "addr:housenumber":"9",
    "addr:postcode":"3043",
    "addr:street":"Flight Drv",
    "iso:country":"AU",
    "sg:address":"9 Flight Drv",
    "sg:city":"Tullamarine",
    "sg:classifiers":[
        {
            "category":"Manufacturing",
            "subcategory":"Building Materials",
            "type":"Manufacturing & Wholesale Goods"
        }
    ],
    "sg:phone":"+61 3 9330 0473",
    "sg:postcode":"3043",
    "sg:province":"VIC",
    "sg:tags":[
        "adhesive",
        "tape"
    ],
    "wof:name":"Syrom Australia",
    "wof:placetype":"venue"
},
  "geometry": {"coordinates":[144.85580444300001,-37.7098884583],"type":"Point"}
}