{
  "type": "Feature",
  "properties": {
    "addr:full":"Shellharbour Super Centre, Lake Entrance Rd Shellharbour NSW 2529",
    "addr:postcode":"2529",
    "addr:street":"Lake Entrance Rd",
    "iso:country":"AU",
    "sg:address":"Shellharbour Super Centre, Lake Entrance Rd",
    "sg:city":"Shellharbour",
    "sg:classifiers":[
        {
            "category":"Building & Trades",
            "subcategory":"Equipment Rental",
            "type":"Services"
        }
    ],
    "sg:phone":"+61 2 4297 6199",
    "sg:postcode":"2529",
    "sg:province":"NSW",
    "sg:tags":[
        "fitness"
    ],
    "wof:name":"Amart All Sports",
    "wof:placetype":"venue"
},
  "geometry": {"coordinates":[150.82241821299999,-34.5697593689],"type":"Point"}
}