{
  "type": "Feature",
  "properties": {
    "addr:full":"29 Grace St Mont Albert VIC 3127",
    "addr:housenumber":"29",
    "addr:postcode":"3127",
    "addr:street":"Grace St",
    "iso:country":"AU",
    "sg:address":"29 Grace St",
    "sg:city":"Mont Albert",
    "sg:classifiers":[
        {
            "category":"Communications",
            "type":"Services"
        }
    ],
    "sg:phone":"+61 3 9898 3233",
    "sg:postcode":"3127",
    "sg:province":"VIC",
    "sg:tags":[
        "equipment",
        "radio"
    ],
    "wof:name":"EM Solutions Pty Ltd",
    "wof:placetype":"venue"
},
  "geometry": {"coordinates":[145.10447692899999,-37.8123893738],"type":"Point"}
}