{
  "type": "Feature",
  "properties": {
    "iso:country":"AU",
    "sg:address":"7 Daisy St",
    "sg:city":"Fairy Meadow",
    "sg:classifiers":[
        {
            "category":"Wholesale",
            "subcategory":"Seafood",
            "type":"Manufacturing & Wholesale Goods"
        }
    ],
    "sg:phone":"+61 2 4284 7177",
    "sg:postcode":"2519",
    "sg:province":"NSW",
    "sg:tags":[
        "fish"
    ],
    "wof:name":"Harley & John Seafoods",
    "wof:placetype":"venue"
},
  "geometry": {"coordinates":[150.893921,-34.392281],"type":"Point"}
}