{
  "type": "Feature",
  "properties": {
    "addr:full":"89 Regent St New Lambton NSW 2305",
    "addr:housenumber":"89",
    "addr:postcode":"2305",
    "addr:street":"Regent St",
    "iso:country":"AU",
    "sg:address":"89 Regent St",
    "sg:city":"New Lambton",
    "sg:classifiers":[
        {
            "category":"Cafe",
            "type":"Food & Drink"
        }
    ],
    "sg:phone":"+61 2 4952 5484",
    "sg:postcode":"2305",
    "sg:province":"NSW",
    "wof:name":"Chaddies on Regent",
    "wof:placetype":"venue"
},
  "geometry": {"coordinates":[151.713593,-32.92284],"type":"Point"}
}