{
  "type": "Feature",
  "properties": {
    "addr:full":"808- 810 Old Princes Hwy Sutherland NSW 2232",
    "addr:housenumber":"810",
    "addr:postcode":"2232",
    "addr:street":"Old Princes Hwy",
    "iso:country":"AU",
    "sg:address":"808- 810 Old Princes Hwy",
    "sg:city":"Sutherland",
    "sg:classifiers":[
        {
            "category":"Travel",
            "subcategory":"Hotels & Motels",
            "type":"Entertainment"
        }
    ],
    "sg:phone":"+61 2 9521 2315",
    "sg:postcode":"2232",
    "sg:province":"NSW",
    "sg:tags":[
        "accommodation"
    ],
    "sg:website":"http://www.boylessutherland.com.au",
    "wof:name":"Boyles Sutherland Hotel",
    "wof:placetype":"venue"
},
  "geometry": {"coordinates":[151.05708313,-34.0328407288],"type":"Point"}
}