{
  "type": "Feature",
  "properties": {
    "addr:full":"317 Glenmore Rd Paddington NSW 2021",
    "addr:housenumber":"317",
    "addr:postcode":"2021",
    "addr:street":"Glenmore Rd",
    "iso:country":"AU",
    "sg:address":"317 Glenmore Rd",
    "sg:city":"Paddington",
    "sg:classifiers":[
        {
            "category":"Health Services",
            "subcategory":"Health Practitioner",
            "type":"Services"
        }
    ],
    "sg:phone":"+61 2 9332 2562",
    "sg:postcode":"2021",
    "sg:province":"NSW",
    "sg:tags":[
        "physiotherapist"
    ],
    "wof:name":"Paddington Sports Injury & Physiotherapy Centre",
    "wof:placetype":"venue"
},
  "geometry": {"coordinates":[151.22999572800001,-33.8807945251],"type":"Point"}
}