{
  "type": "Feature",
  "properties": {
    "iso:country":"AU",
    "sg:address":"13 Halcyon Crt",
    "sg:city":"Doncaster East",
    "sg:classifiers":[
        {
            "category":"Utilities",
            "subcategory":"Natural Gas",
            "type":"Services"
        }
    ],
    "sg:phone":"+61 409 186 116",
    "sg:postcode":"3109",
    "sg:province":"VIC",
    "sg:tags":[
        "solid",
        "plasterer"
    ],
    "wof:name":"Cerantola M G",
    "wof:placetype":"venue"
},
  "geometry": {"coordinates":[145.16534423799999,-37.7749710083],"type":"Point"}
}