{
  "type": "Feature",
  "properties": {
    "addr:full":"40 Murray St Hobart TAS 7000",
    "addr:housenumber":"40",
    "addr:postcode":"7000",
    "addr:street":"Murray St",
    "iso:country":"AU",
    "sg:address":"40 Murray St",
    "sg:city":"Hobart",
    "sg:classifiers":[
        {
            "category":"Travel",
            "subcategory":"Travel Agent",
            "type":"Entertainment"
        }
    ],
    "sg:phone":"+61 3 6234 2699",
    "sg:postcode":"7000",
    "sg:province":"TAS",
    "sg:tags":[
        "consultant"
    ],
    "wof:name":"Harvey World Travel",
    "wof:placetype":"venue"
},
  "geometry": {"coordinates":[147.327880859,-42.8838119507],"type":"Point"}
}