{
  "type": "Feature",
  "properties": {
    "iso:country":"AU",
    "sg:address":"PO Box 191",
    "sg:city":"Murrumbateman",
    "sg:classifiers":[
        {
            "category":"Professional",
            "subcategory":"Management & Consulting",
            "type":"Services"
        }
    ],
    "sg:phone":"+61 417 269 947",
    "sg:postcode":"2582",
    "sg:province":"NSW",
    "sg:tags":[
        "consultant",
        "relocation"
    ],
    "wof:name":"Karen Heldon Consulting",
    "wof:placetype":"venue"
},
  "geometry": {"coordinates":[149.02377319300001,-34.9941482544],"type":"Point"}
}