{
  "type": "Feature",
  "properties": {
    "addr:full":"Bendall Rd Donnybrook WA 6239",
    "addr:postcode":"6239",
    "addr:street":"Bendall Rd",
    "iso:country":"AU",
    "sg:address":"Bendall Rd",
    "sg:city":"Donnybrook",
    "sg:classifiers":[
        {
            "category":"Farming",
            "subcategory":"Farm & Veterinary Services",
            "type":"Manufacturing & Wholesale Goods"
        }
    ],
    "sg:phone":"+61 8 9731 1494",
    "sg:postcode":"6239",
    "sg:province":"WA",
    "sg:tags":[
        "contracting"
    ],
    "wof:name":"Polkinghorne K.A. & M.H.",
    "wof:placetype":"venue"
},
  "geometry": {"coordinates":[115.797791,-33.55521],"type":"Point"}
}