{
  "type": "Feature",
  "properties": {
    "addr:full":"60 Hillwood Ave Warwick WA 6024",
    "addr:housenumber":"60",
    "addr:postcode":"6024",
    "addr:street":"Hillwood Ave",
    "iso:country":"AU",
    "sg:address":"60 Hillwood Ave",
    "sg:city":"Warwick",
    "sg:classifiers":[
        {
            "category":"Health Services",
            "subcategory":"Health Practitioner",
            "type":"Services"
        }
    ],
    "sg:phone":"+61 8 9447 5914",
    "sg:postcode":"6024",
    "sg:province":"WA",
    "sg:tags":[
        "naturopath"
    ],
    "wof:name":"Elston Colin & Elizabeth",
    "wof:placetype":"venue"
},
  "geometry": {"coordinates":[115.803062439,-31.83477211],"type":"Point"}
}