{
  "type": "Feature",
  "properties": {
    "addr:full":"13 George St Morwell VIC 3840",
    "addr:housenumber":"13",
    "addr:postcode":"3840",
    "addr:street":"George St",
    "iso:country":"AU",
    "sg:address":"13 George St",
    "sg:city":"Morwell",
    "sg:classifiers":[
        {
            "category":"Health Services",
            "subcategory":"Optometrist",
            "type":"Services"
        }
    ],
    "sg:phone":"+61 3 5134 2555",
    "sg:postcode":"3840",
    "sg:province":"VIC",
    "wof:name":"McCabe M",
    "wof:placetype":"venue"
},
  "geometry": {"coordinates":[146.397674561,-38.2383918762],"type":"Point"}
}