{
  "type": "Feature",
  "properties": {
    "addr:full":"61 c Edgeworth David Ave Waitara NSW 2077",
    "addr:housenumber":"61",
    "addr:postcode":"2077",
    "addr:street":"C Edgeworth David Ave",
    "iso:country":"AU",
    "sg:address":"61 c Edgeworth David Ave",
    "sg:city":"Waitara",
    "sg:classifiers":[
        {
            "category":"Fast Food",
            "type":"Food & Drink"
        }
    ],
    "sg:phone":"+61 2 9477 4383",
    "sg:postcode":"2077",
    "sg:province":"NSW",
    "sg:tags":[
        "away",
        "take"
    ],
    "wof:name":"Gina's Gourmet Takeaway",
    "wof:placetype":"venue"
},
  "geometry": {"coordinates":[151.10585022000001,-33.7063140869],"type":"Point"}
}