{
  "type": "Feature",
  "properties": {
    "addr:full":"Kianga Forest Rd Narooma North NSW 2546",
    "addr:postcode":"2546",
    "addr:street":"Forest Rd",
    "iso:country":"AU",
    "sg:address":"Kianga Forest Rd",
    "sg:city":"Narooma North",
    "sg:classifiers":[
        {
            "category":"Building & Trades",
            "subcategory":"Construction",
            "type":"Services"
        }
    ],
    "sg:phone":"+61 2 4476 2761",
    "sg:postcode":"2546",
    "sg:province":"NSW",
    "sg:tags":[
        "earth",
        "excavating",
        "moving",
        "contractor"
    ],
    "wof:name":"Narooma Bobcat Contractors Pty Ltd",
    "wof:placetype":"venue"
},
  "geometry": {"coordinates":[150.08653259299999,-36.201751709],"type":"Point"}
}