{
  "type": "Feature",
  "properties": {
    "addr:full":"PO Box 5381 Torquay QLD 4655",
    "addr:postcode":"4655",
    "iso:country":"AU",
    "sg:address":"PO Box 5381",
    "sg:city":"Torquay",
    "sg:classifiers":[
        {
            "category":"Building & Trades",
            "subcategory":"Plumbing",
            "type":"Services"
        }
    ],
    "sg:phone":"+61 418 789 563",
    "sg:postcode":"4655",
    "sg:province":"QLD",
    "sg:tags":[
        "consultant"
    ],
    "wof:name":"Clive Ring & Associates",
    "wof:placetype":"venue"
},
  "geometry": {"coordinates":[152.86926299999999,-25.291929],"type":"Point"}
}