{
  "type": "Feature",
  "properties": {
    "addr:full":"209 Rocky Point Rd Ramsgate NSW 2217",
    "addr:housenumber":"209",
    "addr:postcode":"2217",
    "addr:street":"Rocky Point Rd",
    "iso:country":"AU",
    "sg:address":"209 Rocky Point Rd",
    "sg:city":"Ramsgate",
    "sg:classifiers":[
        {
            "category":"Personal",
            "type":"Services"
        }
    ],
    "sg:phone":"+61 2 9529 8911",
    "sg:postcode":"2217",
    "sg:province":"NSW",
    "sg:tags":[
        "dressmaker"
    ],
    "wof:name":"EMODA Couture",
    "wof:placetype":"venue"
},
  "geometry": {"coordinates":[151.13618500000001,-33.983906],"type":"Point"}
}