{
  "type": "Feature",
  "properties": {
    "addr:full":"139a Westall Rd Clayton South VIC 3169",
    "addr:housenumber":"139a",
    "addr:postcode":"3169",
    "addr:street":"Westall Rd",
    "iso:country":"AU",
    "sg:address":"139a Westall Rd",
    "sg:city":"Clayton South",
    "sg:classifiers":[
        {
            "category":"Retail",
            "subcategory":"Auto Repair",
            "type":"Services"
        }
    ],
    "sg:phone":"+61 3 9546 1244",
    "sg:postcode":"3169",
    "sg:province":"VIC",
    "sg:tags":[
        "repairer",
        "motor",
        "engineer"
    ],
    "wof:name":"Autocommerce Pty Ltd",
    "wof:placetype":"venue"
},
  "geometry": {"coordinates":[145.137771606,-37.9516906738],"type":"Point"}
}