{
  "type": "Feature",
  "properties": {
    "addr:full":"394 Bell St Pascoe Vale South VIC 3044",
    "addr:housenumber":"394",
    "addr:postcode":"3044",
    "addr:street":"Bell St",
    "iso:country":"AU",
    "sg:address":"394 Bell St",
    "sg:city":"Pascoe Vale South",
    "sg:classifiers":[
        {
            "category":"Personal",
            "subcategory":"Beauty Salon",
            "type":"Services"
        }
    ],
    "sg:phone":"+61 3 9350 4091",
    "sg:postcode":"3044",
    "sg:province":"VIC",
    "wof:name":"New Age Therapy & Day Spa",
    "wof:placetype":"venue"
},
  "geometry": {"coordinates":[144.944290161,-37.7388763428],"type":"Point"}
}