{
  "type": "Feature",
  "properties": {
    "iso:country":"AU",
    "sg:address":"8 William St",
    "sg:city":"Balaclava",
    "sg:classifiers":[
        {
            "category":"Manufacturing",
            "subcategory":"Paper Products",
            "type":"Manufacturing & Wholesale Goods"
        }
    ],
    "sg:phone":"+61 3 9527 1776",
    "sg:postcode":"3183",
    "sg:province":"VIC",
    "sg:tags":[
        "bag"
    ],
    "wof:name":"Astoria Paper Products",
    "wof:placetype":"venue"
},
  "geometry": {"coordinates":[144.994506836,-37.869102478],"type":"Point"}
}