{
  "type": "Feature",
  "properties": {
    "iso:country":"AU",
    "sg:address":"175 Collins St",
    "sg:city":"Hobart",
    "sg:classifiers":[
        {
            "category":"Insurance",
            "subcategory":"Title Insurance",
            "type":"Services"
        }
    ],
    "sg:phone":"+61 3 6231 1333",
    "sg:postcode":"7000",
    "sg:province":"TAS",
    "sg:tags":[
        "searcher"
    ],
    "wof:name":"Brooks Lark & Carrick",
    "wof:placetype":"venue"
},
  "geometry": {"coordinates":[147.324752808,-42.8851699829],"type":"Point"}
}