{
  "type": "Feature",
  "properties": {
    "addr:full":"133 Reservoir St Surry Hills NSW 2010",
    "addr:housenumber":"133",
    "addr:postcode":"2010",
    "addr:street":"Reservoir St",
    "iso:country":"AU",
    "sg:address":"133 Reservoir St",
    "sg:city":"Surry Hills",
    "sg:classifiers":[
        {
            "category":"Professional",
            "subcategory":"Employment Agencies",
            "type":"Services"
        }
    ],
    "sg:phone":"+61 2 9211 4233",
    "sg:postcode":"2010",
    "sg:province":"NSW",
    "sg:tags":[
        "broker",
        "custom"
    ],
    "wof:name":"Wards International Pty Ltd",
    "wof:placetype":"venue"
},
  "geometry": {"coordinates":[151.21284484899999,-33.8815536499],"type":"Point"}
}