{
  "type": "Feature",
  "properties": {
    "addr:full":"90 Oxford St Mitchell QLD 4465",
    "addr:housenumber":"90",
    "addr:postcode":"4465",
    "addr:street":"Oxford St",
    "iso:country":"AU",
    "sg:address":"90 Oxford St",
    "sg:city":"Mitchell",
    "sg:classifiers":[
        {
            "category":"Commercial Area",
            "type":"Public Place"
        }
    ],
    "sg:phone":"+61 7 4630 9577",
    "sg:postcode":"4465",
    "sg:province":"QLD",
    "sg:tags":[
        "heavy",
        "carrier"
    ],
    "wof:name":"Mitchell Freighters",
    "wof:placetype":"venue"
},
  "geometry": {"coordinates":[147.96684265100001,-26.4885787964],"type":"Point"}
}