{
  "type": "Feature",
  "properties": {
    "iso:country":"AU",
    "sg:address":"16- 18 Sandalwood Crt",
    "sg:city":"Jimboomba",
    "sg:classifiers":[
        {
            "category":"Building & Trades",
            "subcategory":"Landscaping Services",
            "type":"Services"
        }
    ],
    "sg:phone":"+61 423 402 581",
    "sg:postcode":"4280",
    "sg:province":"QLD",
    "sg:tags":[
        "slashing",
        "contractor"
    ],
    "wof:name":"Astral Home Services",
    "wof:placetype":"venue"
},
  "geometry": {"coordinates":[152.96101400000001,-27.806808],"type":"Point"}
}