{
  "type": "Feature",
  "properties": {
    "addr:full":"16 Queen St Yeppoon QLD 4703",
    "addr:housenumber":"16",
    "addr:postcode":"4703",
    "addr:street":"Queen St",
    "iso:country":"AU",
    "sg:address":"16 Queen St",
    "sg:city":"Yeppoon",
    "sg:classifiers":[
        {
            "category":"Banks & Credit Unions",
            "subcategory":"Investment Brokerage",
            "type":"Services"
        }
    ],
    "sg:phone":"+61 7 4939 3021",
    "sg:postcode":"4703",
    "sg:province":"QLD",
    "wof:name":"ABN AMRO Morgans",
    "wof:placetype":"venue"
},
  "geometry": {"coordinates":[150.74760437,-23.1304569244],"type":"Point"}
}