{
  "type": "Feature",
  "properties": {
    "iso:country":"AU",
    "sg:address":"29 Wickes Rd",
    "sg:city":"Bywong",
    "sg:classifiers":[
        {
            "category":"Communications",
            "subcategory":"Film & Video Production",
            "type":"Services"
        }
    ],
    "sg:phone":"+61 1300 655 525",
    "sg:postcode":"2621",
    "sg:province":"NSW",
    "sg:tags":[
        "trestle",
        "ladders",
        "steps",
        "accessory"
    ],
    "wof:name":"Attic Ladders",
    "wof:placetype":"venue"
},
  "geometry": {"coordinates":[149.32196044899999,-35.1524963379],"type":"Point"}
}