{
  "type": "Feature",
  "properties": {
    "addr:full":"Fact. 1/ 8 Colchester Rd Rosebud VIC 3939",
    "addr:housenumber":"1 / 8",
    "addr:postcode":"3939",
    "addr:street":"Fact.;Colchester Rd",
    "iso:country":"AU",
    "sg:address":"Fact. 1/ 8 Colchester Rd",
    "sg:city":"Rosebud",
    "sg:classifiers":[
        {
            "category":"Retail",
            "subcategory":"Auto Repair",
            "type":"Services"
        }
    ],
    "sg:phone":"+61 3 5982 0615",
    "sg:postcode":"3939",
    "sg:province":"VIC",
    "sg:tags":[
        "automotive",
        "air conditioning"
    ],
    "wof:name":"Rosebud Airconditioning",
    "wof:placetype":"venue"
},
  "geometry": {"coordinates":[144.88710022000001,-38.379108429],"type":"Point"}
}