{
  "type": "Feature",
  "properties": {
    "addr:full":"653 High St Preston VIC 3072",
    "addr:housenumber":"653",
    "addr:postcode":"3072",
    "addr:street":"High St",
    "iso:country":"AU",
    "sg:address":"653 High St",
    "sg:city":"Preston",
    "sg:classifiers":[
        {
            "category":"Real Estate",
            "subcategory":"Architect",
            "type":"Services"
        }
    ],
    "sg:phone":"+61 3 9470 1144",
    "sg:postcode":"3072",
    "sg:province":"VIC",
    "sg:tags":[
        "building",
        "designer"
    ],
    "wof:name":"Beyond Design Group Pty Ltd",
    "wof:placetype":"venue"
},
  "geometry": {"coordinates":[145.00468444800001,-37.7328338623],"type":"Point"}
}