{
  "type": "Feature",
  "properties": {
    "addr:full":"143 Murray St Hobart TAS 7000",
    "addr:housenumber":"143",
    "addr:postcode":"7000",
    "addr:street":"Murray St",
    "iso:country":"AU",
    "sg:address":"143 Murray St",
    "sg:city":"Hobart",
    "sg:classifiers":[
        {
            "category":"Banks & Credit Unions",
            "subcategory":"Bank",
            "type":"Services"
        }
    ],
    "sg:phone":"+61 3 6231 2034",
    "sg:postcode":"7000",
    "sg:province":"TAS",
    "sg:tags":[
        "broker",
        "mortgage"
    ],
    "wof:name":"Financial Advisory Services Pty Ltd",
    "wof:placetype":"venue"
},
  "geometry": {"coordinates":[147.32225036599999,-42.8807296753],"type":"Point"}
}