{
  "type": "Feature",
  "properties": {
    "addr:full":"Bine St Horsham VIC 3400",
    "addr:postcode":"3400",
    "addr:street":"Bine St",
    "iso:country":"AU",
    "sg:address":"Bine St",
    "sg:city":"Horsham",
    "sg:classifiers":[
        {
            "category":"Professional",
            "type":"Services"
        }
    ],
    "sg:phone":"+61 3 5382 6628",
    "sg:postcode":"3400",
    "sg:province":"VIC",
    "sg:tags":[
        "transport"
    ],
    "wof:name":"Toll-Ipec",
    "wof:placetype":"venue"
},
  "geometry": {"coordinates":[142.19619750999999,-36.7172393799],"type":"Point"}
}