{
  "type": "Feature",
  "properties": {
    "iso:country":"AU",
    "sg:address":"6 Lillian St",
    "sg:city":"Brunswick",
    "sg:classifiers":[
        {
            "category":"Organizations",
            "subcategory":"Non-profit Organization",
            "type":"Services"
        }
    ],
    "sg:phone":"+61 3 9383 5848",
    "sg:postcode":"3056",
    "sg:province":"VIC",
    "sg:tags":[
        "support",
        "disability",
        "organisation"
    ],
    "wof:name":"Disability Assist",
    "wof:placetype":"venue"
},
  "geometry": {"coordinates":[144.966033936,-37.7606773376],"type":"Point"}
}