{
  "type": "Feature",
  "properties": {
    "addr:full":"RMB 4263 Irrewillipe Rd Colac VIC 3250",
    "addr:postcode":"3250",
    "addr:street":"Irrewillipe Rd",
    "iso:country":"AU",
    "sg:address":"RMB 4263 Irrewillipe Rd",
    "sg:city":"Colac",
    "sg:classifiers":[
        {
            "category":"Building & Trades",
            "subcategory":"Construction",
            "type":"Services"
        }
    ],
    "sg:phone":"+61 418 523 447",
    "sg:postcode":"3250",
    "sg:province":"VIC",
    "sg:tags":[
        "joinery"
    ],
    "wof:name":"Paton A K & J A",
    "wof:placetype":"venue"
},
  "geometry": {"coordinates":[143.57345599999999,-38.359451],"type":"Point"}
}