{
  "type": "Feature",
  "properties": {
    "iso:country":"AU",
    "sg:address":"8a Andrews Rd",
    "sg:city":"Emerald",
    "sg:classifiers":[
        {
            "category":"Professional",
            "subcategory":"Engineering",
            "type":"Services"
        }
    ],
    "sg:phone":"+61 417 874 044",
    "sg:postcode":"4720",
    "sg:province":"QLD",
    "sg:tags":[
        "consultant",
        "geotechnical",
        "engineer"
    ],
    "wof:name":"SCT Operations Pty Ltd",
    "wof:placetype":"venue"
},
  "geometry": {"coordinates":[148.169296,-23.544199],"type":"Point"}
}