{
  "type": "Feature",
  "properties": {
    "addr:full":"387 Hunter St Newcastle NSW 2300",
    "addr:housenumber":"387",
    "addr:postcode":"2300",
    "addr:street":"Hunter St",
    "iso:country":"AU",
    "sg:address":"387 Hunter St",
    "sg:city":"Newcastle",
    "sg:classifiers":[
        {
            "category":"Banks & Credit Unions",
            "subcategory":"Bank",
            "type":"Services"
        }
    ],
    "sg:phone":"+61 2 4929 6134",
    "sg:postcode":"2300",
    "sg:province":"NSW",
    "sg:tags":[
        "society"
    ],
    "wof:name":"Hunter United Employees Credit Union",
    "wof:placetype":"venue"
},
  "geometry": {"coordinates":[151.77171300000001,-32.927147],"type":"Point"}
}