{
  "type": "Feature",
  "properties": {
    "addr:full":"72 Lascelles St Hopetoun VIC 3396",
    "addr:housenumber":"72",
    "addr:postcode":"3396",
    "addr:street":"Lascelles St",
    "iso:country":"AU",
    "sg:address":"72 Lascelles St",
    "sg:city":"Hopetoun",
    "sg:classifiers":[
        {
            "category":"Travel",
            "subcategory":"Hotels & Motels",
            "type":"Entertainment"
        }
    ],
    "sg:phone":"+61 3 5083 3021",
    "sg:postcode":"3396",
    "sg:province":"VIC",
    "sg:tags":[
        "accommodation"
    ],
    "wof:name":"Club Hotel",
    "wof:placetype":"venue"
},
  "geometry": {"coordinates":[142.36500549300001,-35.7272911072],"type":"Point"}
}