{
  "type": "Feature",
  "properties": {
    "iso:country":"AU",
    "sg:address":"51- 53 North St",
    "sg:city":"Kempsey",
    "sg:classifiers":[
        {
            "category":"Social Services",
            "subcategory":"Child Care",
            "type":"Services"
        }
    ],
    "sg:phone":"+61 2 6562 8144",
    "sg:postcode":"2440",
    "sg:province":"NSW",
    "wof:name":"The Kindergarten",
    "wof:placetype":"venue"
},
  "geometry": {"coordinates":[152.87150600000001,-31.035883],"type":"Point"}
}