{
  "type": "Feature",
  "properties": {
    "addr:full":"27 Miller St Brunswick East VIC 3057",
    "addr:housenumber":"27",
    "addr:postcode":"3057",
    "addr:street":"Miller St",
    "iso:country":"AU",
    "sg:address":"27 Miller St",
    "sg:city":"Brunswick East",
    "sg:classifiers":[
        {
            "category":"Retail",
            "subcategory":"Repair Shop",
            "type":"Services"
        }
    ],
    "sg:phone":"+61 418 333 133",
    "sg:postcode":"3057",
    "sg:province":"VIC",
    "sg:tags":[
        "restorer",
        "repairer",
        "carpet"
    ],
    "wof:name":"Kool Kleen",
    "wof:placetype":"venue"
},
  "geometry": {"coordinates":[144.97770690900001,-37.7759590149],"type":"Point"}
}