{
  "type": "Feature",
  "properties": {
    "addr:full":"386 Upper Burringbar Rd Burringbar NSW 2483",
    "addr:housenumber":"386",
    "addr:postcode":"2483",
    "addr:street":"Upper Burringbar Rd",
    "iso:country":"AU",
    "sg:address":"386 Upper Burringbar Rd",
    "sg:city":"Burringbar",
    "sg:classifiers":[
        {
            "category":"Building & Trades",
            "subcategory":"Construction",
            "type":"Services"
        }
    ],
    "sg:phone":"+61 2 6677 1522",
    "sg:postcode":"2483",
    "sg:province":"NSW",
    "sg:tags":[
        "welding"
    ],
    "wof:name":"Jim Allard Mobile Welding",
    "wof:placetype":"venue"
},
  "geometry": {"coordinates":[153.436737061,-28.445186615],"type":"Point"}
}