{
  "type": "Feature",
  "properties": {
    "iso:country":"AU",
    "sg:address":"6-8 Sandown Drv",
    "sg:city":"Mildura",
    "sg:classifiers":[
        {
            "category":"Professional",
            "type":"Services"
        }
    ],
    "sg:phone":"+61 3 5023 7855",
    "sg:postcode":"3500",
    "sg:province":"VIC",
    "sg:tags":[
        "transport"
    ],
    "wof:name":"MOTTs Sunraysia Bulk Transport",
    "wof:placetype":"venue"
},
  "geometry": {"coordinates":[142.17405700699999,-34.2062492371],"type":"Point"}
}