{
  "type": "Feature",
  "properties": {
    "addr:full":"Lot 9 Cramsie Rd Longreach QLD 4730",
    "addr:postcode":"4730",
    "addr:street":"Cramsie Rd",
    "iso:country":"AU",
    "sg:address":"Lot 9 Cramsie Rd",
    "sg:city":"Longreach",
    "sg:classifiers":[
        {
            "category":"Professional",
            "subcategory":"Business Services",
            "type":"Services"
        }
    ],
    "sg:phone":"+61 7 4658 0444",
    "sg:postcode":"4730",
    "sg:province":"QLD",
    "sg:tags":[
        "livestock",
        "transport"
    ],
    "wof:name":"Johnson Bros Transport",
    "wof:placetype":"venue"
},
  "geometry": {"coordinates":[144.254807,-23.44071],"type":"Point"}
}