{
  "type": "Feature",
  "properties": {
    "addr:full":"Knox Towerpoint Centre 3- 5 Rezes St Wantirna South VIC 3152",
    "addr:housenumber":"3 5",
    "addr:postcode":"3152",
    "addr:street":"Rezes St",
    "iso:country":"AU",
    "sg:address":"Knox Towerpoint Centre 3- 5 Rezes St",
    "sg:city":"Wantirna South",
    "sg:classifiers":[
        {
            "category":"Health Services",
            "subcategory":"Dentist",
            "type":"Services"
        }
    ],
    "sg:phone":"+61 3 9887 0805",
    "sg:postcode":"3152",
    "sg:province":"VIC",
    "wof:name":"Luu Richard Dr",
    "wof:placetype":"venue"
},
  "geometry": {"coordinates":[145.24333190900001,-37.8709220886],"type":"Point"}
}