{
  "type": "Feature",
  "properties": {
    "addr:full":"15 Main St Cleve SA 5640",
    "addr:housenumber":"15",
    "addr:postcode":"5640",
    "addr:street":"Main St",
    "iso:country":"AU",
    "sg:address":"15 Main St",
    "sg:city":"Cleve",
    "sg:classifiers":[
        {
            "category":"Health Services",
            "subcategory":"Doctor",
            "type":"Services"
        }
    ],
    "sg:phone":"+61 8 8628 2003",
    "sg:postcode":"5640",
    "sg:province":"SA",
    "sg:tags":[
        "medical",
        "practitioner"
    ],
    "wof:name":"Cleve Health & Welfare Centre",
    "wof:placetype":"venue"
},
  "geometry": {"coordinates":[136.494750977,-33.7018928528],"type":"Point"}
}