{
  "type": "Feature",
  "properties": {
    "addr:full":"1 Frangipanni Ave Scarness QLD 4655",
    "addr:housenumber":"1",
    "addr:postcode":"4655",
    "addr:street":"Frangipanni Ave",
    "iso:country":"AU",
    "sg:address":"1 Frangipanni Ave",
    "sg:city":"Scarness",
    "sg:classifiers":[
        {
            "category":"Structure",
            "subcategory":"Office Building",
            "type":"Public Place"
        }
    ],
    "sg:phone":"+61 7 4124 4687",
    "sg:postcode":"4655",
    "sg:province":"QLD",
    "sg:tags":[
        "tie",
        "concrete",
        "formwork",
        "form",
        "accessory"
    ],
    "wof:name":"Maahs Concreting (QLD) Pty Ltd",
    "wof:placetype":"venue"
},
  "geometry": {"coordinates":[152.849762,-25.295988],"type":"Point"}
}