{
  "type": "Feature",
  "properties": {
    "addr:full":"U4/ 8 St Aubins Ave Caulfield North VIC 3161",
    "addr:postcode":"3161",
    "addr:street":"U4 / 8 St Aubins Ave",
    "iso:country":"AU",
    "sg:address":"U4/ 8 St Aubins Ave",
    "sg:city":"Caulfield North",
    "sg:classifiers":[
        {
            "category":"Industrial Area",
            "type":"Public Place"
        }
    ],
    "sg:phone":"+61 3 9527 7840",
    "sg:postcode":"3161",
    "sg:province":"VIC",
    "sg:tags":[
        "protective",
        "clothing"
    ],
    "wof:name":"Working Class Man Pty Ltd",
    "wof:placetype":"venue"
},
  "geometry": {"coordinates":[145.01014709500001,-37.8738098145],"type":"Point"}
}