{
  "type": "Feature",
  "properties": {
    "iso:country":"AU",
    "sg:address":"Suite 7/ 57 Labouchere Rd",
    "sg:city":"South Perth",
    "sg:classifiers":[
        {
            "category":"Real Estate",
            "subcategory":"Architect",
            "type":"Services"
        }
    ],
    "sg:phone":"+61 8 9368 0799",
    "sg:postcode":"6151",
    "sg:province":"WA",
    "wof:name":"rad architecture",
    "wof:placetype":"venue"
},
  "geometry": {"coordinates":[115.881882,-31.978163],"type":"Point"}
}