{
  "type": "Feature",
  "properties": {
    "addr:full":"340 Tapleys Hill Rd Seaton SA 5023",
    "addr:housenumber":"340",
    "addr:postcode":"5023",
    "addr:street":"Tapleys Hill Rd",
    "iso:country":"AU",
    "sg:address":"340 Tapleys Hill Rd",
    "sg:city":"Seaton",
    "sg:classifiers":[
        {
            "category":"Organizations",
            "subcategory":"Non-profit Organization",
            "type":"Services"
        }
    ],
    "sg:phone":"+61 8 8355 3500",
    "sg:postcode":"5023",
    "sg:province":"SA",
    "sg:tags":[
        "support",
        "disability",
        "organisation"
    ],
    "wof:name":"Homecare Plus",
    "wof:placetype":"venue"
},
  "geometry": {"coordinates":[138.51411438,-34.8997497559],"type":"Point"}
}