{
  "type": "Feature",
  "properties": {
    "addr:full":"Kalymnos Drv Karama NT 0812",
    "addr:postcode":"nt 0812",
    "addr:street":"Kalymnos Drv",
    "iso:country":"AU",
    "sg:address":"Kalymnos Drv",
    "sg:city":"Karama",
    "sg:classifiers":[
        {
            "category":"Fast Food",
            "type":"Food & Drink"
        }
    ],
    "sg:phone":"+61 8 8945 1146",
    "sg:postcode":"0812",
    "sg:province":"NT",
    "sg:tags":[
        "away",
        "take"
    ],
    "wof:name":"Red Rooster",
    "wof:placetype":"venue"
},
  "geometry": {"coordinates":[130.916168,-12.40159],"type":"Point"}
}