{
  "type": "Feature",
  "properties": {
    "addr:full":"80 Audley St Petersham NSW 2049",
    "addr:housenumber":"80",
    "addr:postcode":"2049",
    "addr:street":"Audley St",
    "iso:country":"AU",
    "sg:address":"80 Audley St",
    "sg:city":"Petersham",
    "sg:classifiers":[
        {
            "category":"Shopping",
            "subcategory":"Mobile Phones",
            "type":"Retail Goods"
        }
    ],
    "sg:phone":"+61 2 9572 6979",
    "sg:postcode":"2049",
    "sg:province":"NSW",
    "sg:tags":[
        "telephone",
        "accessory"
    ],
    "wof:name":"Satcom Enterprises",
    "wof:placetype":"venue"
},
  "geometry": {"coordinates":[151.153976,-33.89603],"type":"Point"}
}