{
  "type": "Feature",
  "properties": {
    "addr:full":"Cnr Fifteenth Ave & Edmondson Ave West Hoxton NSW 2171",
    "addr:postcode":"2171",
    "addr:street":"Cnr Fifteenth Ave & Edmondson Ave West",
    "iso:country":"AU",
    "sg:address":"Cnr Fifteenth Ave & Edmondson Ave",
    "sg:city":"West Hoxton",
    "sg:classifiers":[
        {
            "category":"Home & Garden",
            "subcategory":"Garden Supply",
            "type":"Retail Goods"
        }
    ],
    "sg:phone":"+61 2 9606 0349",
    "sg:postcode":"2171",
    "sg:province":"NSW",
    "sg:tags":[
        "landscape"
    ],
    "wof:name":"Liverpool Sand & Soil Supplies",
    "wof:placetype":"venue"
},
  "geometry": {"coordinates":[150.83609008799999,-33.9216194153],"type":"Point"}
}