{
  "type": "Feature",
  "properties": {
    "iso:country":"AU",
    "sg:address":"5- 7 Young St",
    "sg:city":"Circular Quay",
    "sg:classifiers":[
        {
            "category":"Education",
            "subcategory":"University",
            "type":"Public Place"
        }
    ],
    "sg:phone":"+61 1800 251 866",
    "sg:postcode":"2000",
    "sg:province":"NSW",
    "sg:tags":[
        "educational",
        "organisation",
        "cultural"
    ],
    "wof:name":"EF High School Year Overseas",
    "wof:placetype":"venue"
},
  "geometry": {"coordinates":[151.21099853499999,-33.862613678],"type":"Point"}
}