{
  "type": "Feature",
  "properties": {
    "addr:full":"900 Mt Dandenong Rd Montrose VIC 3765",
    "addr:housenumber":"900",
    "addr:postcode":"3765",
    "addr:street":"Mt Dandenong Rd",
    "iso:country":"AU",
    "sg:address":"900 Mt Dandenong Rd",
    "sg:city":"Montrose",
    "sg:classifiers":[
        {
            "category":"Retail",
            "subcategory":"Auto Repair",
            "type":"Services"
        }
    ],
    "sg:phone":"+61 3 9728 6977",
    "sg:postcode":"3765",
    "sg:province":"VIC",
    "sg:tags":[
        "repairer",
        "motor",
        "engineer"
    ],
    "wof:name":"Repco Authorised Service",
    "wof:placetype":"venue"
},
  "geometry": {"coordinates":[145.34222412099999,-37.810218811],"type":"Point"}
}