{
  "type": "Feature",
  "properties": {
    "addr:full":"Suite 2, 4 King St Warners Bay NSW 2282",
    "addr:housenumber":"4",
    "addr:postcode":"2282",
    "addr:street":"King St",
    "iso:country":"AU",
    "sg:address":"Suite 2, 4 King St",
    "sg:city":"Warners Bay",
    "sg:classifiers":[
        {
            "category":"Sports & Exercise",
            "subcategory":"Gym",
            "type":"Entertainment"
        }
    ],
    "sg:phone":"+61 2 4948 9310",
    "sg:postcode":"2282",
    "sg:province":"NSW",
    "sg:tags":[
        "pilate",
        "method"
    ],
    "wof:name":"Lifestyle Pilates And Rehabilation Studio",
    "wof:placetype":"venue"
},
  "geometry": {"coordinates":[151.64695739699999,-32.9752731323],"type":"Point"}
}