{
  "type": "Feature",
  "properties": {
    "addr:full":"Cnr Cowra Drive & Newman Rd Newman WA 6753",
    "addr:postcode":"6753",
    "addr:street":"Cowra;Rd",
    "iso:country":"AU",
    "sg:address":"Cnr Cowra Drive & Newman Rd",
    "sg:city":"Newman",
    "sg:classifiers":[
        {
            "category":"Autos & Motor Vehicles",
            "subcategory":"Fuel & Gas Station",
            "type":"Retail Goods"
        }
    ],
    "sg:phone":"+61 8 9177 8023",
    "sg:postcode":"6753",
    "sg:province":"WA",
    "wof:name":"B P Whaleback Roadhouse",
    "wof:placetype":"venue"
},
  "geometry": {"coordinates":[119.742752075,-23.3513507843],"type":"Point"}
}