{
  "type": "Feature",
  "properties": {
    "iso:country":"AU",
    "sg:address":"11 Kadina St",
    "sg:city":"The Gap",
    "sg:classifiers":[
        {
            "category":"Professional",
            "subcategory":"Engineering",
            "type":"Services"
        }
    ],
    "sg:phone":"+61 7 3300 6652",
    "sg:postcode":"4061",
    "sg:province":"QLD",
    "sg:tags":[
        "chemical",
        "engineer"
    ],
    "wof:name":"T P M Pty Ltd",
    "wof:placetype":"venue"
},
  "geometry": {"coordinates":[152.94834899899999,-27.4393310547],"type":"Point"}
}