{
  "type": "Feature",
  "properties": {
    "addr:full":"Level 1 Cnr Beach Rd & Orient St Batemans Bay NSW 2536",
    "addr:postcode":"2536",
    "addr:street":"Cnr Beach Rd & Orient St",
    "iso:country":"AU",
    "sg:address":"Level 1 Cnr Beach Rd & Orient St",
    "sg:city":"Batemans Bay",
    "sg:classifiers":[
        {
            "category":"Professional",
            "subcategory":"Accounting & Tax Preparation",
            "type":"Services"
        }
    ],
    "sg:phone":"+61 2 4472 9142",
    "sg:postcode":"2536",
    "sg:province":"NSW",
    "sg:tags":[
        "accountant",
        "auditor"
    ],
    "wof:name":"Donald and Ralston",
    "wof:placetype":"venue"
},
  "geometry": {"coordinates":[150.177612305,-35.7083778381],"type":"Point"}
}