{
  "type": "Feature",
  "properties": {
    "iso:country":"AU",
    "sg:address":"106 Union Rd",
    "sg:city":"Surrey Hills",
    "sg:classifiers":[
        {
            "category":"Fast Food",
            "type":"Food & Drink"
        }
    ],
    "sg:phone":"+61 3 9836 8638",
    "sg:postcode":"3127",
    "sg:province":"VIC",
    "sg:tags":[
        "away",
        "take"
    ],
    "wof:name":"Union Road Take Away & Fish Shop",
    "wof:placetype":"venue"
},
  "geometry": {"coordinates":[145.09718322800001,-37.8253326416],"type":"Point"}
}