{
  "type": "Feature",
  "properties": {
    "addr:full":"16 Alma Ave Woy Woy NSW 2256",
    "addr:housenumber":"16",
    "addr:postcode":"2256",
    "addr:street":"Alma Ave",
    "iso:country":"AU",
    "sg:address":"16 Alma Ave",
    "sg:city":"Woy Woy",
    "sg:classifiers":[
        {
            "category":"Sports & Exercise",
            "subcategory":"Ski Resort",
            "type":"Entertainment"
        }
    ],
    "sg:phone":"+61 2 4341 1175",
    "sg:postcode":"2256",
    "sg:province":"NSW",
    "sg:tags":[
        "propelled",
        "jet"
    ],
    "wof:name":"X-treme Marine",
    "wof:placetype":"venue"
},
  "geometry": {"coordinates":[151.32440185600001,-33.5040512085],"type":"Point"}
}