{
  "type": "Feature",
  "properties": {
    "iso:country":"AU",
    "sg:address":"Suite 1 12a Oatley Pde",
    "sg:city":"Oatley",
    "sg:classifiers":[
        {
            "category":"Health Services",
            "subcategory":"Dentist",
            "type":"Services"
        }
    ],
    "sg:phone":"+61 2 9580 6027",
    "sg:postcode":"2223",
    "sg:province":"NSW",
    "wof:name":"Latham D W",
    "wof:placetype":"venue"
},
  "geometry": {"coordinates":[151.079421997,-33.9797363281],"type":"Point"}
}