{
  "type": "Feature",
  "properties": {
    "iso:country":"AU",
    "sg:address":"19 Yaringa Rd",
    "sg:city":"Castle Hill",
    "sg:classifiers":[
        {
            "category":"Education",
            "subcategory":"Music School",
            "type":"Public Place"
        }
    ],
    "sg:phone":"+61 408 024 771",
    "sg:postcode":"2154",
    "sg:province":"NSW",
    "sg:tags":[
        "teacher"
    ],
    "wof:name":"Wainwright C A",
    "wof:placetype":"venue"
},
  "geometry": {"coordinates":[151.000854492,-33.7179946899],"type":"Point"}
}