{
  "type": "Feature",
  "properties": {
    "addr:full":"22 A Essington St Wentworthville NSW 2145",
    "addr:housenumber":"22 a",
    "addr:postcode":"2145",
    "addr:street":"Essington St",
    "iso:country":"AU",
    "sg:address":"22 A Essington St",
    "sg:city":"Wentworthville",
    "sg:classifiers":[
        {
            "category":"Building & Trades",
            "subcategory":"Construction",
            "type":"Services"
        }
    ],
    "sg:phone":"+61 2 9635 6595",
    "sg:postcode":"2145",
    "sg:province":"NSW",
    "sg:tags":[
        "renovation",
        "alterations",
        "extension",
        "contractor"
    ],
    "wof:name":"Perfection Building Services",
    "wof:placetype":"venue"
},
  "geometry": {"coordinates":[150.97711181599999,-33.8155860901],"type":"Point"}
}