{
  "type": "Feature",
  "properties": {
    "addr:full":"59-63 Spring St Geelong West VIC 3218",
    "addr:housenumber":"59-63",
    "addr:postcode":"3218",
    "addr:street":"Spring St",
    "iso:country":"AU",
    "sg:address":"59-63 Spring St",
    "sg:city":"Geelong West",
    "sg:classifiers":[
        {
            "category":"Professional",
            "subcategory":"Art Services",
            "type":"Services"
        }
    ],
    "sg:phone":"+61 3 5229 3633",
    "sg:postcode":"3218",
    "sg:province":"VIC",
    "sg:tags":[
        "graphic",
        "designer"
    ],
    "wof:name":"New Direction Design Concepts",
    "wof:placetype":"venue"
},
  "geometry": {"coordinates":[144.348953247,-38.1447067261],"type":"Point"}
}