{
  "type": "Feature",
  "properties": {
    "iso:country":"AU",
    "sg:address":"242 Denison St",
    "sg:city":"Rockhampton",
    "sg:classifiers":[
        {
            "category":"Professional",
            "subcategory":"Accounting & Tax Preparation",
            "type":"Services"
        }
    ],
    "sg:phone":"+61 7 4927 8788",
    "sg:postcode":"4700",
    "sg:province":"QLD",
    "sg:tags":[
        "bookkeeping"
    ],
    "wof:name":"Better Tax Service",
    "wof:placetype":"venue"
},
  "geometry": {"coordinates":[150.519607544,-23.3935089111],"type":"Point"}
}