{
  "type": "Feature",
  "properties": {
    "addr:full":"29 Railway St Stanthorpe QLD 4380",
    "addr:housenumber":"29",
    "addr:postcode":"4380",
    "addr:street":"Railway St",
    "iso:country":"AU",
    "sg:address":"29 Railway St",
    "sg:city":"Stanthorpe",
    "sg:classifiers":[
        {
            "category":"Health Services",
            "subcategory":"Dentist",
            "type":"Services"
        }
    ],
    "sg:phone":"+61 7 4681 2033",
    "sg:postcode":"4380",
    "sg:province":"QLD",
    "wof:name":"Asamoah Ken Dr",
    "wof:placetype":"venue"
},
  "geometry": {"coordinates":[151.93092300000001,-28.655199],"type":"Point"}
}