{
  "type": "Feature",
  "properties": {
    "addr:full":"Un 1/ 10 Euphemia St Jimboomba QLD 4280",
    "addr:housenumber":"10",
    "addr:postcode":"4280",
    "addr:street":"Euphemia St",
    "iso:country":"AU",
    "sg:address":"Un 1/ 10 Euphemia St",
    "sg:city":"Jimboomba",
    "sg:classifiers":[
        {
            "category":"Retail",
            "subcategory":"Auto Repair",
            "type":"Services"
        }
    ],
    "sg:phone":"+61 7 5546 0635",
    "sg:postcode":"4280",
    "sg:province":"QLD",
    "sg:tags":[
        "repairer",
        "motor",
        "engineer"
    ],
    "wof:name":"Jimboomba Mechanical",
    "wof:placetype":"venue"
},
  "geometry": {"coordinates":[153.031113,-27.82378],"type":"Point"}
}