{
  "type": "Feature",
  "properties": {
    "addr:full":"Old Melbourne Rd Lara VIC 3212",
    "addr:postcode":"3212",
    "addr:street":"Old Melbourne Rd",
    "iso:country":"AU",
    "sg:address":"Old Melbourne Rd",
    "sg:city":"Lara",
    "sg:classifiers":[
        {
            "category":"Arena",
            "subcategory":"Sports Club",
            "type":"Entertainment"
        }
    ],
    "sg:phone":"+61 3 5282 2352",
    "sg:postcode":"3212",
    "sg:province":"VIC",
    "sg:tags":[
        "organisation",
        "sporting"
    ],
    "wof:name":"Avalon International Raceway",
    "wof:placetype":"venue"
},
  "geometry": {"coordinates":[144.4324646,-38.0267753601],"type":"Point"}
}