{
  "type": "Feature",
  "properties": {
    "addr:full":"54 Victoria St St George QLD 4487",
    "addr:housenumber":"54",
    "addr:postcode":"4487",
    "addr:street":"Victoria St",
    "iso:country":"AU",
    "sg:address":"54 Victoria St St",
    "sg:city":"George",
    "sg:classifiers":[
        {
            "category":"Travel",
            "subcategory":"Hotels & Motels",
            "type":"Entertainment"
        }
    ],
    "sg:phone":"+61 1800 819 862",
    "sg:postcode":"4487",
    "sg:province":"QLD",
    "wof:name":"Balonne Motel",
    "wof:placetype":"venue"
},
  "geometry": {"coordinates":[148.586624145,-28.0332355499],"type":"Point"}
}