{
  "type": "Feature",
  "properties": {
    "addr:full":"1st Floor 75 Railway Rd Blackburn VIC 3130",
    "addr:housenumber":"75",
    "addr:postcode":"3130",
    "addr:street":"Railway Rd",
    "iso:country":"AU",
    "sg:address":"1st Floor 75 Railway Rd",
    "sg:city":"Blackburn",
    "sg:classifiers":[
        {
            "category":"Professional",
            "subcategory":"Employment Agencies",
            "type":"Services"
        }
    ],
    "sg:phone":"+61 3 9877 5800",
    "sg:postcode":"3130",
    "sg:province":"VIC",
    "sg:tags":[
        "provider",
        "internet"
    ],
    "wof:name":"Rainbow Ad Services",
    "wof:placetype":"venue"
},
  "geometry": {"coordinates":[145.15350341800001,-37.8193397522],"type":"Point"}
}