{
  "type": "Feature",
  "properties": {
    "addr:full":"3/ 40 Douglas St Milton QLD 4064",
    "addr:housenumber":"/ 40",
    "addr:postcode":"4064",
    "addr:street":"Douglas St",
    "iso:country":"AU",
    "sg:address":"3/ 40 Douglas St",
    "sg:city":"Milton",
    "sg:classifiers":[
        {
            "category":"Arts & Performance",
            "subcategory":"Art Gallery",
            "type":"Entertainment"
        }
    ],
    "sg:phone":"+61 7 3369 9305",
    "sg:postcode":"4064",
    "sg:province":"QLD",
    "wof:name":"Victor Mace Fine Art Gallery",
    "wof:placetype":"venue"
},
  "geometry": {"coordinates":[153.00367736800001,-27.4718093872],"type":"Point"}
}