{
  "type": "Feature",
  "properties": {
    "iso:country":"AU",
    "sg:address":"Lvl 2/ 102 Glover St",
    "sg:city":"Cremorne",
    "sg:classifiers":[
        {
            "category":"Insurance",
            "subcategory":"Hazard Insurance",
            "type":"Services"
        }
    ],
    "sg:phone":"+61 2 9953 9034",
    "sg:postcode":"2090",
    "sg:province":"NSW",
    "sg:tags":[
        "fire",
        "accident",
        "marine"
    ],
    "wof:name":"Renaissance Underwriting Agency Pty Ltd",
    "wof:placetype":"venue"
},
  "geometry": {"coordinates":[151.230957031,-33.8282470703],"type":"Point"}
}