{
  "type": "Feature",
  "properties": {
    "iso:country":"AU",
    "sg:address":"Unit 8/ 89 Guthrie St",
    "sg:city":"Osborne Park",
    "sg:classifiers":[
        {
            "category":"Retail",
            "subcategory":"Car Wash",
            "type":"Services"
        }
    ],
    "sg:phone":"+61 8 9242 8052",
    "sg:postcode":"6017",
    "sg:province":"WA",
    "sg:tags":[
        "truck",
        "cleaning"
    ],
    "wof:name":"Aspire Auto Detailers",
    "wof:placetype":"venue"
},
  "geometry": {"coordinates":[115.816940308,-31.9069137573],"type":"Point"}
}