{
  "type": "Feature",
  "properties": {
    "addr:full":"Shop 5, Princess Arcade 6 Merimbula Drive Merimbula NSW 2548",
    "addr:housenumber":"shop 5;6",
    "addr:postcode":"2548",
    "addr:street":"Princess Arcade;Merimbula Drive",
    "iso:country":"AU",
    "sg:address":"Shop 5, Princess Arcade 6 Merimbula Drive",
    "sg:city":"Merimbula",
    "sg:classifiers":[
        {
            "category":"Professional",
            "subcategory":"Computer Services",
            "type":"Services"
        }
    ],
    "sg:phone":"+61 2 6495 2882",
    "sg:postcode":"2548",
    "sg:province":"NSW",
    "sg:tags":[
        "repairs",
        "upgrade",
        "equipment"
    ],
    "wof:name":"Neo-Computers",
    "wof:placetype":"venue"
},
  "geometry": {"coordinates":[149.90382385300001,-36.8897476196],"type":"Point"}
}