{
  "type": "Feature",
  "properties": {
    "addr:full":"428-440 High St Learmonth VIC 3352",
    "addr:housenumber":"428-440",
    "addr:postcode":"3352",
    "addr:street":"High St Learmonth",
    "iso:country":"AU",
    "sg:address":"428-440 High St",
    "sg:city":"Learmonth",
    "sg:classifiers":[
        {
            "category":"Travel",
            "subcategory":"Hotels & Motels",
            "type":"Entertainment"
        }
    ],
    "sg:phone":"+61 3 5343 2214",
    "sg:postcode":"3352",
    "sg:province":"VIC",
    "sg:tags":[
        "accommodation"
    ],
    "wof:name":"Stag Hotel",
    "wof:placetype":"venue"
},
  "geometry": {"coordinates":[143.71592699999999,-37.422211],"type":"Point"}
}