{
  "type": "Feature",
  "properties": {
    "addr:full":"339 Warrigal Rd Burwood VIC 3125",
    "addr:housenumber":"339",
    "addr:postcode":"3125",
    "addr:street":"Warrigal Rd",
    "iso:country":"AU",
    "sg:address":"339 Warrigal Rd",
    "sg:city":"Burwood",
    "sg:classifiers":[
        {
            "category":"Retail",
            "subcategory":"Funeral Services",
            "type":"Services"
        }
    ],
    "sg:phone":"+61 3 9808 8888",
    "sg:postcode":"3125",
    "sg:province":"VIC",
    "sg:tags":[
        "director"
    ],
    "wof:name":"Sleights Of Melbourne",
    "wof:placetype":"venue"
},
  "geometry": {"coordinates":[145.09559631400001,-37.8515090942],"type":"Point"}
}