{
  "type": "Feature",
  "properties": {
    "addr:full":"Unit 2, 91 Champion Drv Kelmscott WA 6111",
    "addr:housenumber":"91",
    "addr:postcode":"6111",
    "addr:street":"Champion Drv",
    "iso:country":"AU",
    "sg:address":"Unit 2, 91 Champion Drv",
    "sg:city":"Kelmscott",
    "sg:classifiers":[
        {
            "category":"Retail",
            "subcategory":"Auto Repair",
            "type":"Services"
        }
    ],
    "sg:phone":"+61 8 9495 1764",
    "sg:postcode":"6111",
    "sg:province":"WA",
    "sg:tags":[
        "engine",
        "reconditioning"
    ],
    "wof:name":"AK Cylinder Heads",
    "wof:placetype":"venue"
},
  "geometry": {"coordinates":[115.994369507,-32.1245803833],"type":"Point"}
}