{
  "type": "Feature",
  "properties": {
    "addr:full":"82 Imperial Pde Labrador QLD 4215",
    "addr:housenumber":"82",
    "addr:postcode":"4215",
    "addr:street":"Imperial Pde",
    "iso:country":"AU",
    "sg:address":"82 Imperial Pde",
    "sg:city":"Labrador",
    "sg:classifiers":[
        {
            "category":"Shopping",
            "subcategory":"Crafts & Fabrics",
            "type":"Retail Goods"
        }
    ],
    "sg:phone":"+61 7 5529 0016",
    "sg:postcode":"4215",
    "sg:province":"QLD",
    "sg:tags":[
        "wool",
        "knitting",
        "accessory"
    ],
    "wof:name":"Crafty Hands",
    "wof:placetype":"venue"
},
  "geometry": {"coordinates":[153.402053833,-27.9434013367],"type":"Point"}
}