{
  "type": "Feature",
  "properties": {
    "iso:country":"AU",
    "sg:address":"Suite 5, Ground Floor Macquarie House 169 Macquari",
    "sg:city":"Parramatta",
    "sg:classifiers":[
        {
            "category":"Professional",
            "subcategory":"Employment Agencies",
            "type":"Services"
        }
    ],
    "sg:phone":"+61 2 9687 8688",
    "sg:postcode":"2124",
    "sg:province":"NSW",
    "wof:name":"H & H Accredited Training",
    "wof:placetype":"venue"
},
  "geometry": {"coordinates":[151.05711364699999,-33.9092903137],"type":"Point"}
}