{
  "type": "Feature",
  "properties": {
    "iso:country":"AU",
    "sg:address":"Shop 5,Grace Arcade, 386 Victoria Ave",
    "sg:city":"Chatswood",
    "sg:classifiers":[
        {
            "category":"Professional",
            "subcategory":"Advertising",
            "type":"Services"
        }
    ],
    "sg:phone":"+61 2 9412 1200",
    "sg:postcode":"2067",
    "sg:province":"NSW",
    "sg:tags":[
        "balloon",
        "novelty"
    ],
    "wof:name":"Balloonarama",
    "wof:placetype":"venue"
},
  "geometry": {"coordinates":[151.182907105,-33.7963981628],"type":"Point"}
}