{
  "type": "Feature",
  "properties": {
    "iso:country":"AU",
    "sg:address":"1337 Ipswich Rd",
    "sg:city":"Rocklea",
    "sg:classifiers":[
        {
            "category":"Food & Beverages",
            "subcategory":"Liquor & Beverages",
            "type":"Retail Goods"
        }
    ],
    "sg:phone":"+61 7 3848 1608",
    "sg:postcode":"4106",
    "sg:province":"QLD",
    "sg:tags":[
        "store"
    ],
    "wof:name":"Rocklea Hotel",
    "wof:placetype":"venue"
},
  "geometry": {"coordinates":[153.01091003400001,-27.5433330536],"type":"Point"}
}