{
  "type": "Feature",
  "properties": {
    "addr:full":"U1/ 15 Dover St Burleigh Heads QLD 4220",
    "addr:housenumber":"15",
    "addr:postcode":"4220",
    "addr:street":"U1 /;Dover St",
    "iso:country":"AU",
    "sg:address":"U1/ 15 Dover St",
    "sg:city":"Burleigh Heads",
    "sg:classifiers":[
        {
            "category":"Organizations",
            "subcategory":"Professional Association",
            "type":"Services"
        }
    ],
    "sg:phone":"+61 7 5592 4244",
    "sg:postcode":"4220",
    "sg:province":"QLD",
    "sg:tags":[
        "web",
        "internet"
    ],
    "wof:name":"Gold Coast Info Link",
    "wof:placetype":"venue"
},
  "geometry": {"coordinates":[153.42692565900001,-28.103105545],"type":"Point"}
}