{
  "type": "Feature",
  "properties": {
    "iso:country":"AU",
    "sg:address":"78 Berwick St",
    "sg:city":"Fortitude Valley",
    "sg:classifiers":[
        {
            "category":"Professional",
            "subcategory":"Computer Services",
            "type":"Services"
        }
    ],
    "sg:phone":"+61 1300 851 313",
    "sg:postcode":"4006",
    "sg:province":"QLD",
    "sg:tags":[
        "consultant",
        "system"
    ],
    "wof:name":"ComputerCORP#",
    "wof:placetype":"venue"
},
  "geometry": {"coordinates":[153.037399292,-27.4583396912],"type":"Point"}
}