{
  "type": "Feature",
  "properties": {
    "iso:country":"AU",
    "sg:address":"83 Carlingford St",
    "sg:city":"Sefton",
    "sg:classifiers":[
        {
            "category":"Home & Garden",
            "subcategory":"Furniture",
            "type":"Retail Goods"
        }
    ],
    "sg:phone":"+61 2 9738 5066",
    "sg:postcode":"2162",
    "sg:province":"NSW",
    "sg:tags":[
        "business"
    ],
    "wof:name":"Commercial Furnishers Manufacturing",
    "wof:placetype":"venue"
},
  "geometry": {"coordinates":[151.01466369600001,-33.8850975037],"type":"Point"}
}