{
  "type": "Feature",
  "properties": {
    "addr:full":"65 Vineyard St Mona Vale NSW 2103",
    "addr:housenumber":"65",
    "addr:postcode":"2103",
    "addr:street":"Vineyard St",
    "iso:country":"AU",
    "sg:address":"65 Vineyard St",
    "sg:city":"Mona Vale",
    "sg:classifiers":[
        {
            "category":"Building & Trades",
            "subcategory":"Construction",
            "type":"Services"
        }
    ],
    "sg:phone":"+61 2 9997 1488",
    "sg:postcode":"2103",
    "sg:province":"NSW",
    "sg:tags":[
        "earth",
        "excavating",
        "moving",
        "contractor"
    ],
    "wof:name":"Len Hughes Earthmoving Pty Ltd",
    "wof:placetype":"venue"
},
  "geometry": {"coordinates":[151.29371643100001,-33.679233551],"type":"Point"}
}