{
  "type": "Feature",
  "properties": {
    "iso:country":"AU",
    "sg:address":"222 Baylis St",
    "sg:city":"Wagga Wagga",
    "sg:classifiers":[
        {
            "category":"Shopping",
            "subcategory":"Crafts & Fabrics",
            "type":"Retail Goods"
        }
    ],
    "sg:phone":"+61 2 6921 7566",
    "sg:postcode":"2650",
    "sg:province":"NSW",
    "sg:tags":[
        "material",
        "dress"
    ],
    "wof:name":"Spotlight Stores",
    "wof:placetype":"venue"
},
  "geometry": {"coordinates":[147.37017822300001,-35.1107978821],"type":"Point"}
}