{
  "type": "Feature",
  "properties": {
    "addr:full":"11 Bruce St Leongatha VIC 3953",
    "addr:housenumber":"11",
    "addr:postcode":"3953",
    "addr:street":"Bruce St",
    "iso:country":"AU",
    "sg:address":"11 Bruce St",
    "sg:city":"Leongatha",
    "sg:classifiers":[
        {
            "category":"Health Services",
            "subcategory":"Health Practitioner",
            "type":"Services"
        }
    ],
    "sg:phone":"+61 425 741 056",
    "sg:postcode":"3953",
    "sg:province":"VIC",
    "sg:tags":[
        "naturopath"
    ],
    "wof:name":"Gippsland Spinal & Health Therapies",
    "wof:placetype":"venue"
},
  "geometry": {"coordinates":[145.94609069800001,-38.4797592163],"type":"Point"}
}