{
  "type": "Feature",
  "properties": {
    "iso:country":"AU",
    "sg:address":"MS 1318",
    "sg:city":"Yungaburra",
    "sg:classifiers":[
        {
            "category":"Food & Beverages",
            "subcategory":"Meat & Fish",
            "type":"Retail Goods"
        }
    ],
    "sg:phone":"+61 7 4095 3824",
    "sg:postcode":"4872",
    "sg:province":"QLD",
    "sg:tags":[
        "aquaculture"
    ],
    "wof:name":"Betta Barra Tropical Fish Hatchery & Technology",
    "wof:placetype":"venue"
},
  "geometry": {"coordinates":[145.1068573,-17.9841003418],"type":"Point"}
}