{
  "type": "Feature",
  "properties": {
    "iso:country":"AU",
    "sg:address":"24 Donegal Rd",
    "sg:city":"Lonsdale",
    "sg:classifiers":[
        {
            "category":"Manufacturing",
            "subcategory":"Motor Vehicles & Parts",
            "type":"Manufacturing & Wholesale Goods"
        }
    ],
    "sg:phone":"+61 8 8326 5855",
    "sg:postcode":"5160",
    "sg:province":"SA",
    "sg:tags":[
        "replacement"
    ],
    "wof:name":"Toyoland Auto Recyclers",
    "wof:placetype":"venue"
},
  "geometry": {"coordinates":[138.49403381400001,-35.1185684204],"type":"Point"}
}