{
  "type": "Feature",
  "properties": {
    "addr:full":"3 Elton St Greenmount QLD 4359",
    "addr:housenumber":"3",
    "addr:postcode":"4359",
    "addr:street":"Elton St",
    "iso:country":"AU",
    "sg:address":"3 Elton St",
    "sg:city":"Greenmount",
    "sg:classifiers":[
        {
            "category":"Professional",
            "subcategory":"Computer Services",
            "type":"Services"
        }
    ],
    "sg:phone":"+61 7 4697 1800",
    "sg:postcode":"4359",
    "sg:province":"QLD",
    "sg:tags":[
        "repairs",
        "upgrade",
        "equipment"
    ],
    "wof:name":"Home Computer Services",
    "wof:placetype":"venue"
},
  "geometry": {"coordinates":[151.900757,-27.784075],"type":"Point"}
}