{
  "type": "Feature",
  "properties": {
    "addr:full":"Bromfield St Colac VIC 3250",
    "addr:postcode":"3250",
    "addr:street":"Bromfield St",
    "iso:country":"AU",
    "sg:address":"Bromfield St",
    "sg:city":"Colac",
    "sg:classifiers":[
        {
            "category":"Autos & Motor Vehicles",
            "subcategory":"Fuel & Gas Station",
            "type":"Retail Goods"
        }
    ],
    "sg:phone":"+61 3 5231 1352",
    "sg:postcode":"3250",
    "sg:province":"VIC",
    "wof:name":"BP Australia Limited",
    "wof:placetype":"venue"
},
  "geometry": {"coordinates":[143.58544900000001,-38.340927],"type":"Point"}
}