{
  "type": "Feature",
  "properties": {
    "addr:full":"Suite 6 & 7 2nd Floor London Court, 58 St Georges Tce Perth WA 6000",
    "addr:housenumber":"& 7;58",
    "addr:postcode":"6000",
    "addr:street":"St Georges Tce",
    "iso:country":"AU",
    "sg:address":"Suite 6 & 7 2nd Floor London Court, 58 St",
    "sg:city":"Georges Tce Perth",
    "sg:classifiers":[
        {
            "category":"Health Services",
            "subcategory":"Dentist",
            "type":"Services"
        }
    ],
    "sg:phone":"+61 8 9325 4175",
    "sg:postcode":"6000",
    "sg:province":"WA",
    "wof:name":"London Court Dental Clinic",
    "wof:placetype":"venue"
},
  "geometry": {"coordinates":[115.858482361,-31.9552078247],"type":"Point"}
}