{
  "type": "Feature",
  "properties": {
    "addr:full":"Shop 1/ 467 Golden Four Drv Tugun QLD 4224",
    "addr:housenumber":"shop 1 / 467",
    "addr:postcode":"4224",
    "addr:street":"Golden Four Drv",
    "iso:country":"AU",
    "sg:address":"Shop 1/ 467 Golden Four Drv",
    "sg:city":"Tugun",
    "sg:classifiers":[
        {
            "category":"Personal",
            "subcategory":"Beauty Salon",
            "type":"Services"
        }
    ],
    "sg:phone":"+61 7 5598 3411",
    "sg:postcode":"4224",
    "sg:province":"QLD",
    "sg:tags":[
        "hairdresser"
    ],
    "wof:name":"Sanctuary Hair Face Body",
    "wof:placetype":"venue"
},
  "geometry": {"coordinates":[153.49356079099999,-28.1425457001],"type":"Point"}
}