{
  "type": "Feature",
  "properties": {
    "addr:full":"84 Elder St Lambton NSW 2299",
    "addr:housenumber":"84",
    "addr:postcode":"2299",
    "addr:street":"Elder St",
    "iso:country":"AU",
    "sg:address":"84 Elder St",
    "sg:city":"Lambton",
    "sg:classifiers":[
        {
            "category":"Real Estate",
            "subcategory":"Real Estate Agent",
            "type":"Services"
        }
    ],
    "sg:phone":"+61 2 4952 6111",
    "sg:postcode":"2299",
    "sg:province":"NSW",
    "wof:name":"Global Property International",
    "wof:placetype":"venue"
},
  "geometry": {"coordinates":[151.70904540999999,-32.9115104675],"type":"Point"}
}