{
  "type": "Feature",
  "properties": {
    "addr:full":"Noonamah Tavern Stuart Hwy Noonamah NT 0837",
    "addr:postcode":"nt 0837",
    "addr:street":"Stuart Hwy",
    "iso:country":"AU",
    "sg:address":"Noonamah Tavern Stuart Hwy",
    "sg:city":"Noonamah",
    "sg:classifiers":[
        {
            "category":"Food & Beverages",
            "subcategory":"Liquor & Beverages",
            "type":"Retail Goods"
        }
    ],
    "sg:phone":"+61 8 8988 1054",
    "sg:postcode":"0837",
    "sg:province":"NT",
    "sg:tags":[
        "store"
    ],
    "wof:name":"Liquorwise",
    "wof:placetype":"venue"
},
  "geometry": {"coordinates":[131.0737,-12.63364],"type":"Point"}
}