{
  "type": "Feature",
  "properties": {
    "addr:full":"35 Cinderella Drv Springwood QLD 4127",
    "addr:housenumber":"35",
    "addr:postcode":"4127",
    "addr:street":"Cinderella Drv",
    "iso:country":"AU",
    "sg:address":"35 Cinderella Drv",
    "sg:city":"Springwood",
    "sg:classifiers":[
        {
            "category":"Health Services",
            "subcategory":"Health Practitioner",
            "type":"Services"
        }
    ],
    "sg:phone":"+61 7 3808 6633",
    "sg:postcode":"4127",
    "sg:province":"QLD",
    "sg:tags":[
        "acupuncture"
    ],
    "wof:name":"Min Wu Acupuncture Chinese Herbal Medicine Clinic",
    "wof:placetype":"venue"
},
  "geometry": {"coordinates":[153.12692260700001,-27.6123828888],"type":"Point"}
}