{
  "type": "Feature",
  "properties": {
    "addr:full":"176 Bank St South Melbourne VIC 3205",
    "addr:housenumber":"176",
    "addr:postcode":"3205",
    "addr:street":"Bank St",
    "iso:country":"AU",
    "sg:address":"176 Bank St",
    "sg:city":"South Melbourne",
    "sg:classifiers":[
        {
            "category":"Shopping",
            "subcategory":"Computers & Home Electronics",
            "type":"Retail Goods"
        }
    ],
    "sg:phone":"+61 1800 706 000",
    "sg:postcode":"3205",
    "sg:province":"VIC",
    "sg:tags":[
        "equipment",
        "multimedia"
    ],
    "sg:website":"http://www.digitalpictures.com.au",
    "wof:name":"Digital Pictures",
    "wof:placetype":"venue"
},
  "geometry": {"coordinates":[144.96191400000001,-37.83374],"type":"Point"}
}