{
  "type": "Feature",
  "properties": {
    "addr:full":"525 Marmion St Booragoon WA 6154",
    "addr:housenumber":"525",
    "addr:postcode":"6154",
    "addr:street":"Marmion St",
    "iso:country":"AU",
    "sg:address":"525 Marmion St",
    "sg:city":"Booragoon",
    "sg:classifiers":[
        {
            "category":"Social Services",
            "subcategory":"Child Care",
            "type":"Services"
        }
    ],
    "sg:phone":"+61 8 9316 1253",
    "sg:postcode":"6154",
    "sg:province":"WA",
    "wof:name":"Booragoon Occasional Child Care Centre",
    "wof:placetype":"venue"
},
  "geometry": {"coordinates":[115.827957,-32.038933],"type":"Point"}
}