{
  "type": "Feature",
  "properties": {
    "addr:full":"23 Tarrabool St Amaroo ACT 2914",
    "addr:housenumber":"23",
    "addr:postcode":"2914",
    "addr:street":"Tarrabool St",
    "iso:country":"AU",
    "sg:address":"23 Tarrabool St",
    "sg:city":"Amaroo",
    "sg:classifiers":[
        {
            "category":"Professional",
            "type":"Services"
        }
    ],
    "sg:phone":"+61 414 756 560",
    "sg:postcode":"2914",
    "sg:province":"ACT",
    "sg:tags":[
        "courier"
    ],
    "wof:name":"DNM Xpress",
    "wof:placetype":"venue"
},
  "geometry": {"coordinates":[149.133499145,-35.1719512939],"type":"Point"}
}