{
  "type": "Feature",
  "properties": {
    "iso:country":"AU",
    "sg:address":"102 Uduc Rd",
    "sg:city":"Harvey",
    "sg:classifiers":[
        {
            "category":"Government",
            "subcategory":"Department Of Motor Vehicles",
            "type":"Public Place"
        }
    ],
    "sg:phone":"+61 8 9729 0300",
    "sg:postcode":"6220",
    "sg:province":"WA",
    "sg:tags":[
        "organisation",
        "local"
    ],
    "wof:name":"Harvey Shire Of",
    "wof:placetype":"venue"
},
  "geometry": {"coordinates":[115.894028,-33.079945],"type":"Point"}
}