{
  "type": "Feature",
  "properties": {
    "iso:country":"AU",
    "sg:address":"Lvl 1 893",
    "sg:city":"Stanley Street E. Woolloongabba",
    "sg:classifiers":[
        {
            "category":"Professional",
            "subcategory":"Art Services",
            "type":"Services"
        }
    ],
    "sg:phone":"+61 7 3891 1844",
    "sg:postcode":"4102",
    "sg:province":"QLD",
    "sg:tags":[
        "product",
        "industrial",
        "designer"
    ],
    "wof:name":"Infinity Design + Development",
    "wof:placetype":"venue"
},
  "geometry": {"coordinates":[153.04815673799999,-27.488325119],"type":"Point"}
}