{
  "type": "Feature",
  "properties": {
    "addr:full":"Shop 16, Nundah Village SC, 87 Buckland & Sandgate Rds Nundah QLD 4012",
    "addr:housenumber":"shop 16;87",
    "addr:postcode":"4012",
    "addr:street":"Sc",
    "iso:country":"AU",
    "sg:address":"Shop 16, Nundah Village SC, 87 Buckland & Sandgate Rds",
    "sg:city":"Nundah",
    "sg:classifiers":[
        {
            "category":"Food & Beverages",
            "subcategory":"Liquor & Beverages",
            "type":"Retail Goods"
        }
    ],
    "sg:phone":"+61 7 3266 2981",
    "sg:postcode":"4012",
    "sg:province":"QLD",
    "sg:tags":[
        "store"
    ],
    "wof:name":"BWS Liquor Stores",
    "wof:placetype":"venue"
},
  "geometry": {"coordinates":[153.05946350100001,-27.4032802582],"type":"Point"}
}