{
  "type": "Feature",
  "properties": {
    "addr:full":"8 Baker Pde Ashburton VIC 3147",
    "addr:housenumber":"8",
    "addr:postcode":"3147",
    "addr:street":"Baker Pde",
    "iso:country":"AU",
    "sg:address":"8 Baker Pde",
    "sg:city":"Ashburton",
    "sg:classifiers":[
        {
            "category":"Travel",
            "subcategory":"Travel Agent",
            "type":"Entertainment"
        }
    ],
    "sg:phone":"+61 3 9885 8138",
    "sg:postcode":"3147",
    "sg:province":"VIC",
    "sg:tags":[
        "consultant"
    ],
    "wof:name":"Literature Comes To Life Tours",
    "wof:placetype":"venue"
},
  "geometry": {"coordinates":[145.08354187,-37.860458374],"type":"Point"}
}