{
  "type": "Feature",
  "properties": {
    "iso:country":"AU",
    "sg:address":"312 South Rd",
    "sg:city":"Hampton East",
    "sg:classifiers":[
        {
            "category":"Wholesale",
            "subcategory":"Home Furnishings",
            "type":"Manufacturing & Wholesale Goods"
        }
    ],
    "sg:phone":"+61 3 9532 1758",
    "sg:postcode":"3188",
    "sg:province":"VIC",
    "sg:tags":[
        "terrazzo"
    ],
    "sg:website":"http://www.mirrorimagemarble.com.au",
    "wof:name":"Mirror Image Marble Pty Ltd",
    "wof:placetype":"venue"
},
  "geometry": {"coordinates":[145.02992248499999,-37.9326591492],"type":"Point"}
}