{
  "type": "Feature",
  "properties": {
    "addr:full":"Hakea St Red Cliffs VIC 3496",
    "addr:postcode":"3496",
    "addr:street":"Hakea St",
    "iso:country":"AU",
    "sg:address":"Hakea St",
    "sg:city":"Red Cliffs",
    "sg:classifiers":[
        {
            "category":"Farming",
            "subcategory":"Farm & Veterinary Services",
            "type":"Manufacturing & Wholesale Goods"
        }
    ],
    "sg:phone":"+61 3 5024 3201",
    "sg:postcode":"3496",
    "sg:province":"VIC",
    "sg:tags":[
        "worm"
    ],
    "wof:name":"Neils Worm Farm",
    "wof:placetype":"venue"
},
  "geometry": {"coordinates":[142.18652343799999,-34.3077087402],"type":"Point"}
}