{
  "type": "Feature",
  "properties": {
    "addr:full":"Lisbon St Mt Druitt NSW 2770",
    "addr:postcode":"2770",
    "addr:street":"Lisbon St Mt",
    "iso:country":"AU",
    "sg:address":"Lisbon St",
    "sg:city":"Mt Druitt",
    "sg:classifiers":[
        {
            "category":"Building & Trades",
            "subcategory":"Construction",
            "type":"Services"
        }
    ],
    "sg:phone":"+61 411 344 448",
    "sg:postcode":"2770",
    "sg:province":"NSW",
    "sg:tags":[
        "contractor"
    ],
    "wof:name":"Dalvar Homes",
    "wof:placetype":"venue"
},
  "geometry": {"coordinates":[150.817306519,-33.759059906],"type":"Point"}
}