{
  "type": "Feature",
  "properties": {
    "addr:full":"33- 47 Dohertys Rd Laverton North VIC 3026",
    "addr:housenumber":"47",
    "addr:postcode":"3026",
    "addr:street":"Dohertys Rd",
    "iso:country":"AU",
    "sg:address":"33- 47 Dohertys Rd",
    "sg:city":"Laverton North",
    "sg:classifiers":[
        {
            "category":"Professional",
            "type":"Services"
        }
    ],
    "sg:phone":"+61 1300 668 105",
    "sg:postcode":"3026",
    "sg:province":"VIC",
    "sg:tags":[
        "transport"
    ],
    "wof:name":"Toll AutoLogistics",
    "wof:placetype":"venue"
},
  "geometry": {"coordinates":[144.80633499999999,-37.829819],"type":"Point"}
}