{
  "type": "Feature",
  "properties": {
    "addr:full":"150 Burton Rd Esperance WA 6450",
    "addr:housenumber":"150",
    "addr:postcode":"6450",
    "addr:street":"Burton Rd",
    "iso:country":"AU",
    "sg:address":"150 Burton Rd",
    "sg:city":"Esperance",
    "sg:classifiers":[
        {
            "category":"Commercial Area",
            "type":"Public Place"
        }
    ],
    "sg:phone":"+61 8 9071 7077",
    "sg:postcode":"6450",
    "sg:province":"WA",
    "sg:tags":[
        "heavy",
        "carrier"
    ],
    "wof:name":"Transearth Australia",
    "wof:placetype":"venue"
},
  "geometry": {"coordinates":[121.91401672400001,-33.8292160034],"type":"Point"}
}