{
  "type": "Feature",
  "properties": {
    "addr:full":"5 Logan River Rd Beenleigh QLD 4207",
    "addr:housenumber":"5",
    "addr:postcode":"4207",
    "addr:street":"Logan River Rd",
    "iso:country":"AU",
    "sg:address":"5 Logan River Rd",
    "sg:city":"Beenleigh",
    "sg:classifiers":[
        {
            "category":"Retail",
            "subcategory":"Auto Repair",
            "type":"Services"
        }
    ],
    "sg:phone":"+61 7 3287 5270",
    "sg:postcode":"4207",
    "sg:province":"QLD",
    "sg:tags":[
        "repairer",
        "motor",
        "engineer"
    ],
    "wof:name":"Precise Automatics",
    "wof:placetype":"venue"
},
  "geometry": {"coordinates":[153.19203185999999,-27.7144393921],"type":"Point"}
}