{
  "type": "Feature",
  "properties": {
    "iso:country":"AU",
    "sg:address":"73 Kendall St",
    "sg:city":"West Pymble",
    "sg:classifiers":[
        {
            "category":"Health Services",
            "subcategory":"Doctor",
            "type":"Services"
        }
    ],
    "sg:phone":"+61 2 9499 2000",
    "sg:postcode":"2073",
    "sg:province":"NSW",
    "sg:tags":[
        "medical",
        "practitioner"
    ],
    "wof:name":"Shapiro Elaine Dr",
    "wof:placetype":"venue"
},
  "geometry": {"coordinates":[151.129562378,-33.7610588074],"type":"Point"}
}