{
  "type": "Feature",
  "properties": {
    "iso:country":"AU",
    "sg:address":"3 William St",
    "sg:city":"Berri",
    "sg:classifiers":[
        {
            "category":"Fast Food",
            "type":"Food & Drink"
        }
    ],
    "sg:phone":"+61 8 8582 1888",
    "sg:postcode":"5343",
    "sg:province":"SA",
    "sg:tags":[
        "away",
        "take"
    ],
    "wof:name":"Tony's Yiros & Seafood Bar",
    "wof:placetype":"venue"
},
  "geometry": {"coordinates":[140.600341797,-34.2860565186],"type":"Point"}
}