{
  "type": "Feature",
  "properties": {
    "addr:full":"102 Prospect Rd Summer Hill (Sydney) NSW 2130",
    "addr:housenumber":"102",
    "addr:postcode":"2130",
    "addr:street":"Prospect Rd",
    "iso:country":"AU",
    "sg:address":"102 Prospect Rd",
    "sg:city":"Summer Hill (Sydney)",
    "sg:classifiers":[
        {
            "category":"Health Services",
            "subcategory":"Nursing And Care Facility",
            "type":"Services"
        }
    ],
    "sg:phone":"+61 2 9799 8800",
    "sg:postcode":"2130",
    "sg:province":"NSW",
    "sg:tags":[
        "home"
    ],
    "wof:name":"East West Health Care",
    "wof:placetype":"venue"
},
  "geometry": {"coordinates":[151.13723754899999,-33.8934707642],"type":"Point"}
}