{
  "type": "Feature",
  "properties": {
    "addr:full":"34 Ashburton Ave Turramurra NSW 2074",
    "addr:housenumber":"34",
    "addr:postcode":"2074",
    "addr:street":"Ashburton Ave",
    "iso:country":"AU",
    "sg:address":"34 Ashburton Ave",
    "sg:city":"Turramurra",
    "sg:classifiers":[
        {
            "category":"Wholesale",
            "subcategory":"Machinery & Supplies",
            "type":"Manufacturing & Wholesale Goods"
        }
    ],
    "sg:phone":"+61 2 9440 2866",
    "sg:postcode":"2074",
    "sg:province":"NSW",
    "sg:tags":[
        "machine",
        "tool",
        "engineer"
    ],
    "wof:name":"Asher Smith Agencies",
    "wof:placetype":"venue"
},
  "geometry": {"coordinates":[151.108932495,-33.7606048584],"type":"Point"}
}