{
  "type": "Feature",
  "properties": {
    "addr:full":"5/ 77 Dee Why Pde Dee Why NSW 2099",
    "addr:housenumber":"/ 77",
    "addr:postcode":"2099",
    "addr:street":"Dee Why Pde",
    "iso:country":"AU",
    "sg:address":"5/ 77 Dee Why Pde",
    "sg:city":"Dee Why",
    "sg:classifiers":[
        {
            "category":"Health Services",
            "subcategory":"Doctor",
            "type":"Services"
        }
    ],
    "sg:phone":"+61 2 9972 2285",
    "sg:postcode":"2099",
    "sg:province":"NSW",
    "sg:tags":[
        "nurse",
        "nursing"
    ],
    "wof:name":"Mothercraft & Family Care",
    "wof:placetype":"venue"
},
  "geometry": {"coordinates":[151.29522705100001,-33.752658844],"type":"Point"}
}