{
  "type": "Feature",
  "properties": {
    "iso:country":"AU",
    "sg:address":"Unit 4 3 Stoke Pl",
    "sg:city":"Morley",
    "sg:classifiers":[
        {
            "category":"Professional",
            "type":"Services"
        }
    ],
    "sg:phone":"+61 8 9279 7181",
    "sg:postcode":"6062",
    "sg:province":"WA",
    "sg:tags":[
        "spray",
        "painting"
    ],
    "wof:name":"Pooles Spray Painting",
    "wof:placetype":"venue"
},
  "geometry": {"coordinates":[115.9245224,-31.8933544159],"type":"Point"}
}