{
  "type": "Feature",
  "properties": {
    "addr:full":"Ingle Farm Shopping Centre Montague Rd Ingle Farm SA 5098",
    "addr:postcode":"5098",
    "addr:street":"Montague Rd",
    "iso:country":"AU",
    "sg:address":"Ingle Farm Shopping Centre Montague Rd",
    "sg:city":"Ingle Farm",
    "sg:classifiers":[
        {
            "category":"Health Services",
            "subcategory":"Dentist",
            "type":"Services"
        }
    ],
    "sg:phone":"+61 8 8264 5959",
    "sg:postcode":"5098",
    "sg:province":"SA",
    "wof:name":"Schuurmans Angela",
    "wof:placetype":"venue"
},
  "geometry": {"coordinates":[138.650756836,-34.828704834],"type":"Point"}
}