{
  "type": "Feature",
  "properties": {
    "addr:full":"96 Nicholson St Orbost VIC 3888",
    "addr:housenumber":"96",
    "addr:postcode":"3888",
    "addr:street":"Nicholson St",
    "iso:country":"AU",
    "sg:address":"96 Nicholson St",
    "sg:city":"Orbost",
    "sg:classifiers":[
        {
            "category":"Shopping",
            "subcategory":"Crafts & Fabrics",
            "type":"Retail Goods"
        }
    ],
    "sg:phone":"+61 3 5154 3114",
    "sg:postcode":"3888",
    "sg:province":"VIC",
    "sg:tags":[
        "supply"
    ],
    "wof:name":"Classic Country Crafts",
    "wof:placetype":"venue"
},
  "geometry": {"coordinates":[148.45851135300001,-37.6923179626],"type":"Point"}
}