{
  "type": "Feature",
  "properties": {
    "iso:country":"AU",
    "sg:address":"Dunn Ave",
    "sg:city":"Leeton",
    "sg:classifiers":[
        {
            "category":"Manufacturing",
            "subcategory":"Building Materials",
            "type":"Manufacturing & Wholesale Goods"
        }
    ],
    "sg:phone":"+61 2 6953 5555",
    "sg:postcode":"2705",
    "sg:province":"NSW",
    "sg:tags":[
        "aggregate",
        "concrete"
    ],
    "wof:name":"Area Pre-Mix",
    "wof:placetype":"venue"
},
  "geometry": {"coordinates":[146.395874023,-34.5529136658],"type":"Point"}
}