{
  "type": "Feature",
  "properties": {
    "addr:full":"Shop 1, 2- 4 Club Drv Shearwater TAS 7307",
    "addr:housenumber":"shop;2 4",
    "addr:postcode":"7307",
    "addr:street":"Club Drv",
    "iso:country":"AU",
    "sg:address":"Shop 1, 2- 4 Club Drv",
    "sg:city":"Shearwater",
    "sg:classifiers":[
        {
            "category":"Real Estate",
            "subcategory":"Real Estate Agent",
            "type":"Services"
        }
    ],
    "sg:phone":"+61 3 6428 7399",
    "sg:postcode":"7307",
    "sg:province":"TAS",
    "wof:name":"LJ Hooker Shearwater",
    "wof:placetype":"venue"
},
  "geometry": {"coordinates":[146.54075599999999,-41.160412],"type":"Point"}
}