{
  "type": "Feature",
  "properties": {
    "iso:country":"AU",
    "sg:address":"17- 19 Anglo Rd",
    "sg:city":"Campsie",
    "sg:classifiers":[
        {
            "category":"Health Services",
            "subcategory":"Dentist",
            "type":"Services"
        }
    ],
    "sg:phone":"+61 2 9787 9874",
    "sg:postcode":"2194",
    "sg:province":"NSW",
    "wof:name":"Primary Dental Campsie",
    "wof:placetype":"venue"
},
  "geometry": {"coordinates":[151.102737,-33.911201],"type":"Point"}
}