{
  "type": "Feature",
  "properties": {
    "addr:full":"365 Pitt Town Dural Rd Maraylya NSW 2765",
    "addr:housenumber":"365",
    "addr:postcode":"2765",
    "addr:street":"Pitt;Dural Rd",
    "iso:country":"AU",
    "sg:address":"365 Pitt Town Dural Rd",
    "sg:city":"Maraylya",
    "sg:classifiers":[
        {
            "category":"Home & Garden",
            "subcategory":"Household Appliances",
            "type":"Retail Goods"
        }
    ],
    "sg:phone":"+61 2 4573 6404",
    "sg:postcode":"2765",
    "sg:province":"NSW",
    "sg:tags":[
        "chemical",
        "equipment",
        "steam",
        "cleaning",
        "pressure"
    ],
    "wof:name":"Lavorwash (NSW)",
    "wof:placetype":"venue"
},
  "geometry": {"coordinates":[150.909469605,-33.5871276855],"type":"Point"}
}