{
  "type": "Feature",
  "properties": {
    "iso:country":"AU",
    "sg:address":"40 Raymond Terrace Rd",
    "sg:city":"East Maitland",
    "sg:classifiers":[
        {
            "category":"Personal",
            "subcategory":"Massage",
            "type":"Services"
        }
    ],
    "sg:phone":"+61 2 4933 5329",
    "sg:postcode":"2323",
    "sg:province":"NSW",
    "sg:tags":[
        "therapy"
    ],
    "wof:name":"Hawaiian Massage Centre East Maitland",
    "wof:placetype":"venue"
},
  "geometry": {"coordinates":[151.58555602999999,-32.753780365],"type":"Point"}
}