{
  "type": "Feature",
  "properties": {
    "addr:full":"101 Monmouth St Morningside QLD 4170",
    "addr:housenumber":"101",
    "addr:postcode":"4170",
    "addr:street":"Monmouth St",
    "iso:country":"AU",
    "sg:address":"101 Monmouth St",
    "sg:city":"Morningside",
    "sg:classifiers":[
        {
            "category":"Organizations",
            "subcategory":"Professional Association",
            "type":"Services"
        }
    ],
    "sg:phone":"+61 7 3901 5593",
    "sg:postcode":"4170",
    "sg:province":"QLD",
    "sg:tags":[
        "web",
        "internet"
    ],
    "wof:name":"BlueLily Web Solutions",
    "wof:placetype":"venue"
},
  "geometry": {"coordinates":[153.06842040999999,-27.4662628174],"type":"Point"}
}