{
  "type": "Feature",
  "properties": {
    "addr:full":"33 Gillies St Benalla VIC 3672",
    "addr:housenumber":"33",
    "addr:postcode":"3672",
    "addr:street":"Gillies St",
    "iso:country":"AU",
    "sg:address":"33 Gillies St",
    "sg:city":"Benalla",
    "sg:classifiers":[
        {
            "category":"Farming",
            "subcategory":"Farm & Veterinary Services",
            "type":"Manufacturing & Wholesale Goods"
        }
    ],
    "sg:phone":"+61 3 5762 5548",
    "sg:postcode":"3672",
    "sg:province":"VIC",
    "sg:tags":[
        "seedsman"
    ],
    "wof:name":"Mirfak Pty Ltd",
    "wof:placetype":"venue"
},
  "geometry": {"coordinates":[145.987213,-36.539429],"type":"Point"}
}