{
  "type": "Feature",
  "properties": {
    "addr:full":"Unit 1 9 Greenhills Ave Moorebank NSW 2170",
    "addr:housenumber":"9",
    "addr:postcode":"2170",
    "addr:street":"Greenhills Ave",
    "iso:country":"AU",
    "sg:address":"Unit 1 9 Greenhills Ave",
    "sg:city":"Moorebank",
    "sg:classifiers":[
        {
            "category":"Professional",
            "subcategory":"Engineering",
            "type":"Services"
        }
    ],
    "sg:phone":"+61 2 9822 4841",
    "sg:postcode":"2170",
    "sg:province":"NSW",
    "sg:tags":[
        "engineer"
    ],
    "wof:name":"Oxford R & R Pty Ltd",
    "wof:placetype":"venue"
},
  "geometry": {"coordinates":[150.93208313,-33.9375114441],"type":"Point"}
}