{
  "type": "Feature",
  "properties": {
    "addr:full":"14 Cooper St Smithfield NSW 2164",
    "addr:housenumber":"14",
    "addr:postcode":"2164",
    "addr:street":"Cooper St",
    "iso:country":"AU",
    "sg:address":"14 Cooper St",
    "sg:city":"Smithfield",
    "sg:classifiers":[
        {
            "category":"Manufacturing",
            "subcategory":"Metals",
            "type":"Manufacturing & Wholesale Goods"
        }
    ],
    "sg:phone":"+61 2 9756 5727",
    "sg:postcode":"2164",
    "sg:province":"NSW",
    "sg:tags":[
        "sheet",
        "worker"
    ],
    "wof:name":"Kavanagh Industries Pty Ltd",
    "wof:placetype":"venue"
},
  "geometry": {"coordinates":[150.93632507300001,-33.838508606],"type":"Point"}
}