{
  "type": "Feature",
  "properties": {
    "addr:full":"7 Plummer Rd Laverton North VIC 3026",
    "addr:housenumber":"7",
    "addr:postcode":"3026",
    "addr:street":"Plummer Rd",
    "iso:country":"AU",
    "sg:address":"7 Plummer Rd",
    "sg:city":"Laverton North",
    "sg:classifiers":[
        {
            "category":"Manufacturing",
            "subcategory":"Motor Vehicles & Parts",
            "type":"Manufacturing & Wholesale Goods"
        }
    ],
    "sg:phone":"+61 3 9314 1622",
    "sg:postcode":"3026",
    "sg:province":"VIC",
    "sg:tags":[
        "replacement"
    ],
    "sg:website":"http://www.toyotsrus.com.au",
    "wof:name":"Toyots R Us",
    "wof:placetype":"venue"
},
  "geometry": {"coordinates":[144.812164,-37.816814],"type":"Point"}
}