{
  "type": "Feature",
  "properties": {
    "addr:full":"Shop 203, Gosford Market Place Gosford NSW 2250",
    "addr:housenumber":"203",
    "addr:postcode":"2250",
    "addr:street":"Gosford Market Place",
    "iso:country":"AU",
    "sg:address":"Shop 203, Gosford Market Place",
    "sg:city":"Gosford",
    "sg:classifiers":[
        {
            "category":"Cafe",
            "type":"Food & Drink"
        }
    ],
    "sg:phone":"+61 2 4323 6745",
    "sg:postcode":"2250",
    "sg:province":"NSW",
    "wof:name":"DCM Coffee & Donuts",
    "wof:placetype":"venue"
},
  "geometry": {"coordinates":[151.32798767099999,-33.4495162964],"type":"Point"}
}