{
  "type": "Feature",
  "properties": {
    "addr:full":"40 Ernest Ave Chipping Norton NSW 2170",
    "addr:housenumber":"40",
    "addr:postcode":"2170",
    "addr:street":"Ernest Ave",
    "iso:country":"AU",
    "sg:address":"40 Ernest Ave",
    "sg:city":"Chipping Norton",
    "sg:classifiers":[
        {
            "category":"Fast Food",
            "type":"Food & Drink"
        }
    ],
    "sg:phone":"+61 2 9755 4081",
    "sg:postcode":"2170",
    "sg:province":"NSW",
    "sg:tags":[
        "away",
        "take"
    ],
    "wof:name":"Chippos at Lakeside",
    "wof:placetype":"venue"
},
  "geometry": {"coordinates":[150.961700439,-33.913482666],"type":"Point"}
}