{
  "type": "Feature",
  "properties": {
    "addr:full":"568 Hampton St Hampton VIC 3188",
    "addr:housenumber":"568",
    "addr:postcode":"3188",
    "addr:street":"Hampton St",
    "iso:country":"AU",
    "sg:address":"568 Hampton St",
    "sg:city":"Hampton",
    "sg:classifiers":[
        {
            "category":"Shopping",
            "subcategory":"Party Supplies",
            "type":"Retail Goods"
        }
    ],
    "sg:phone":"+61 3 9533 5528",
    "sg:postcode":"3188",
    "sg:province":"VIC",
    "sg:tags":[
        "children's"
    ],
    "wof:name":"All Fired Up Ceramic Cafe",
    "wof:placetype":"venue"
},
  "geometry": {"coordinates":[145.00372314399999,-37.9317245483],"type":"Point"}
}