{
  "type": "Feature",
  "properties": {
    "addr:full":"5 Nathan St Heatley QLD 4814",
    "addr:housenumber":"5",
    "addr:postcode":"4814",
    "addr:street":"Nathan St",
    "iso:country":"AU",
    "sg:address":"5 Nathan St",
    "sg:city":"Heatley",
    "sg:classifiers":[
        {
            "category":"Building & Trades",
            "subcategory":"Construction",
            "type":"Services"
        }
    ],
    "sg:phone":"+61 7 4779 1111",
    "sg:postcode":"4814",
    "sg:province":"QLD",
    "sg:tags":[
        "contractor"
    ],
    "wof:name":"Calam Rode Residential",
    "wof:placetype":"venue"
},
  "geometry": {"coordinates":[146.75950599999999,-19.282225],"type":"Point"}
}