{
  "type": "Feature",
  "properties": {
    "addr:full":"330 Goodwood Rd Clarence Park SA 5034",
    "addr:housenumber":"330",
    "addr:postcode":"5034",
    "addr:street":"Goodwood Rd",
    "iso:country":"AU",
    "sg:address":"330 Goodwood Rd",
    "sg:city":"Clarence Park",
    "sg:classifiers":[
        {
            "category":"Structure",
            "subcategory":"Bridge",
            "type":"Public Place"
        }
    ],
    "sg:phone":"+61 8 8271 2044",
    "sg:postcode":"5034",
    "sg:province":"SA",
    "sg:tags":[
        "chainsaw",
        "brushcutters"
    ],
    "wof:name":"Mowers&more",
    "wof:placetype":"venue"
},
  "geometry": {"coordinates":[138.59056091299999,-34.9651908875],"type":"Point"}
}