{
  "type": "Feature",
  "properties": {
    "iso:country":"AU",
    "sg:address":"Andersons Rd",
    "sg:city":"Mt Moriac",
    "sg:classifiers":[
        {
            "category":"Building & Trades",
            "subcategory":"Construction",
            "type":"Services"
        }
    ],
    "sg:phone":"+61 3 5266 1233",
    "sg:postcode":"3240",
    "sg:province":"VIC",
    "sg:tags":[
        "contractor"
    ],
    "wof:name":"Glengarry Developments Pty Ltd",
    "wof:placetype":"venue"
},
  "geometry": {"coordinates":[144.205352783,-38.2042694092],"type":"Point"}
}