{
  "type": "Feature",
  "properties": {
    "addr:full":"PO Box 5486 Cairns QLD 4870",
    "addr:postcode":"4870",
    "iso:country":"AU",
    "sg:address":"PO Box 5486",
    "sg:city":"Cairns",
    "sg:classifiers":[
        {
            "category":"Communications",
            "type":"Services"
        }
    ],
    "sg:phone":"+61 7 4055 6266",
    "sg:postcode":"4870",
    "sg:province":"QLD",
    "sg:tags":[
        "translation"
    ],
    "wof:name":"Languagehelp",
    "wof:placetype":"venue"
},
  "geometry": {"coordinates":[145.66958618199999,-17.0185699463],"type":"Point"}
}