{
  "type": "Feature",
  "properties": {
    "iso:country":"AU",
    "sg:address":"PO Box 719",
    "sg:city":"Wodonga",
    "sg:classifiers":[
        {
            "category":"Utilities",
            "subcategory":"Sewage",
            "type":"Services"
        }
    ],
    "sg:phone":"+61 412 866 888",
    "sg:postcode":"3689",
    "sg:province":"VIC",
    "sg:tags":[
        "water",
        "waste",
        "treatment"
    ],
    "wof:name":"Water Recycling Solutions",
    "wof:placetype":"venue"
},
  "geometry": {"coordinates":[146.88806199999999,-36.125542],"type":"Point"}
}