{
  "type": "Feature",
  "properties": {
    "addr:full":"Cnr Hempenstall & Farm Sts North Rockhampton QLD 4701",
    "addr:postcode":"4701",
    "addr:street":"Cnr Hempenstall;Sts North",
    "iso:country":"AU",
    "sg:address":"Cnr Hempenstall & Farm Sts",
    "sg:city":"North Rockhampton",
    "sg:classifiers":[
        {
            "category":"Autos & Motor Vehicles",
            "subcategory":"Auto Supplies",
            "type":"Retail Goods"
        }
    ],
    "sg:phone":"+61 7 4928 2455",
    "sg:postcode":"4701",
    "sg:province":"QLD",
    "sg:tags":[
        "accessory"
    ],
    "wof:name":"Autopro",
    "wof:placetype":"venue"
},
  "geometry": {"coordinates":[150.51205444300001,-23.3392353058],"type":"Point"}
}