{
  "type": "Feature",
  "properties": {
    "iso:country":"AU",
    "sg:address":"Ste3/ 49 Wadham Pde",
    "sg:city":"Mt Waverley",
    "sg:classifiers":[
        {
            "category":"Social Services",
            "subcategory":"Adult Care",
            "type":"Services"
        }
    ],
    "sg:phone":"+61 1300 884 665",
    "sg:postcode":"3149",
    "sg:province":"VIC",
    "sg:tags":[
        "advocate"
    ],
    "wof:name":"Elder Abuse Prevention Association",
    "wof:placetype":"venue"
},
  "geometry": {"coordinates":[145.12652587900001,-37.874294281],"type":"Point"}
}