{
  "type": "Feature",
  "properties": {
    "addr:full":"U2/ 33 Victor Ave Paradise Point QLD 4216",
    "addr:housenumber":"33",
    "addr:postcode":"4216",
    "addr:street":"U2 /;Victor Ave",
    "iso:country":"AU",
    "sg:address":"U2/ 33 Victor Ave",
    "sg:city":"Paradise Point",
    "sg:classifiers":[
        {
            "category":"Shopping",
            "subcategory":"Clothing, Apparel, & Fashions",
            "type":"Retail Goods"
        }
    ],
    "sg:phone":"+61 7 5564 2622",
    "sg:postcode":"4216",
    "sg:province":"QLD",
    "sg:tags":[
        "lady",
        "wear"
    ],
    "wof:name":"Funki Bizaar",
    "wof:placetype":"venue"
},
  "geometry": {"coordinates":[153.39280700699999,-27.8836097717],"type":"Point"}
}