{
  "type": "Feature",
  "properties": {
    "addr:full":"26a Rosemead Rd Hornsby NSW 2077",
    "addr:housenumber":"26a",
    "addr:postcode":"2077",
    "addr:street":"Rosemead Rd",
    "iso:country":"AU",
    "sg:address":"26a Rosemead Rd",
    "sg:city":"Hornsby",
    "sg:classifiers":[
        {
            "category":"Building & Trades",
            "subcategory":"Construction",
            "type":"Services"
        }
    ],
    "sg:phone":"+61 2 9482 1000",
    "sg:postcode":"2077",
    "sg:province":"NSW",
    "sg:tags":[
        "contractor"
    ],
    "wof:name":"Olsen M L Construction Pty Ltd",
    "wof:placetype":"venue"
},
  "geometry": {"coordinates":[151.08824157699999,-33.7038764954],"type":"Point"}
}