{
  "type": "Feature",
  "properties": {
    "addr:full":"5 Denbigh Drv Bowral NSW 2576",
    "addr:housenumber":"5",
    "addr:postcode":"2576",
    "addr:street":"Denbigh Drv",
    "iso:country":"AU",
    "sg:address":"5 Denbigh Drv",
    "sg:city":"Bowral",
    "sg:classifiers":[
        {
            "category":"Utilities",
            "subcategory":"Electric",
            "type":"Services"
        }
    ],
    "sg:phone":"+61 417 414 628",
    "sg:postcode":"2576",
    "sg:province":"NSW",
    "sg:tags":[
        "electrical",
        "contractor"
    ],
    "wof:name":"Mat's Electrical",
    "wof:placetype":"venue"
},
  "geometry": {"coordinates":[150.450119019,-34.4940490723],"type":"Point"}
}