{
  "type": "Feature",
  "properties": {
    "iso:country":"AU",
    "sg:address":"76 Doncaster Rd",
    "sg:city":"Balwyn North",
    "sg:classifiers":[
        {
            "category":"Communications",
            "subcategory":"Film & Video Production",
            "type":"Services"
        }
    ],
    "sg:phone":"+61 3 9859 1031",
    "sg:postcode":"3104",
    "sg:province":"VIC",
    "sg:tags":[
        "dvd",
        "library"
    ],
    "wof:name":"Video Busters",
    "wof:placetype":"venue"
},
  "geometry": {"coordinates":[145.071502686,-37.7928733826],"type":"Point"}
}