{
  "type": "Feature",
  "properties": {
    "addr:full":"PO Box 742 Lane Cove NSW 2066",
    "addr:postcode":"2066",
    "iso:country":"AU",
    "sg:address":"PO Box 742",
    "sg:city":"Lane Cove",
    "sg:classifiers":[
        {
            "category":"Mining & Drilling",
            "type":"Manufacturing & Wholesale Goods"
        }
    ],
    "sg:phone":"+61 2 9428 3444",
    "sg:postcode":"2066",
    "sg:province":"NSW",
    "sg:tags":[
        "boring",
        "contractor"
    ],
    "wof:name":"Australian Drilling Industry Training Committee Ltd",
    "wof:placetype":"venue"
},
  "geometry": {"coordinates":[151.16998290999999,-33.8138999939],"type":"Point"}
}