{
  "type": "Feature",
  "properties": {
    "addr:full":"111 - 113 Main Street Sheffield TAS 7306",
    "addr:housenumber":"113",
    "addr:postcode":"7306",
    "addr:street":"Main Street",
    "iso:country":"AU",
    "sg:address":"111 - 113",
    "sg:city":"Main Street Sheffield",
    "sg:classifiers":[
        {
            "category":"Food & Beverages",
            "subcategory":"Farmers Market",
            "type":"Retail Goods"
        }
    ],
    "sg:phone":"+61 3 6491 1167",
    "sg:postcode":"7306",
    "sg:province":"TAS",
    "sg:tags":[
        "beekeeper"
    ],
    "wof:name":"Barrington Apiaries",
    "wof:placetype":"venue"
},
  "geometry": {"coordinates":[146.33067299999999,-41.384228],"type":"Point"}
}