{
  "type": "Feature",
  "properties": {
    "addr:full":"7 Monte St Slacks Creek QLD 4127",
    "addr:housenumber":"7",
    "addr:postcode":"4127",
    "addr:street":"Monte St",
    "iso:country":"AU",
    "sg:address":"7 Monte St",
    "sg:city":"Slacks Creek",
    "sg:classifiers":[
        {
            "category":"Retail",
            "subcategory":"Auto Repair",
            "type":"Services"
        }
    ],
    "sg:phone":"+61 7 3299 2666",
    "sg:postcode":"4127",
    "sg:province":"QLD",
    "sg:tags":[
        "bus",
        "truck"
    ],
    "wof:name":"Fleet Repairs (QLD) Pty Ltd",
    "wof:placetype":"venue"
},
  "geometry": {"coordinates":[153.11796569800001,-27.6235370636],"type":"Point"}
}