{
  "type": "Feature",
  "properties": {
    "addr:full":"155 Avoca St Randwick NSW 2031",
    "addr:housenumber":"155",
    "addr:postcode":"2031",
    "addr:street":"Avoca St",
    "iso:country":"AU",
    "sg:address":"155 Avoca St",
    "sg:city":"Randwick",
    "sg:classifiers":[
        {
            "category":"Retail",
            "subcategory":"Auto Rental",
            "type":"Services"
        }
    ],
    "sg:phone":"+61 2 9398 5773",
    "sg:postcode":"2031",
    "sg:province":"NSW",
    "sg:tags":[
        "bus",
        "truck"
    ],
    "wof:name":"Avoca Auto Electrical & Mechanical Services",
    "wof:placetype":"venue"
},
  "geometry": {"coordinates":[151.24206543,-33.9136314392],"type":"Point"}
}