{
  "type": "Feature",
  "properties": {
    "addr:full":"24 Bruxner Hwy Wollongbar NSW 2477",
    "addr:housenumber":"24",
    "addr:postcode":"2477",
    "addr:street":"Bruxner Hwy",
    "iso:country":"AU",
    "sg:address":"24 Bruxner Hwy",
    "sg:city":"Wollongbar",
    "sg:classifiers":[
        {
            "category":"Autos & Motor Vehicles",
            "subcategory":"Fuel & Gas Station",
            "type":"Retail Goods"
        }
    ],
    "sg:phone":"+61 2 6628 6433",
    "sg:postcode":"2477",
    "sg:province":"NSW",
    "wof:name":"Wollongbar Service Centre",
    "wof:placetype":"venue"
},
  "geometry": {"coordinates":[153.41368102999999,-28.8253154755],"type":"Point"}
}