{
  "type": "Feature",
  "properties": {
    "iso:country":"AU",
    "sg:address":"265 Canterbury Rd",
    "sg:city":"Bankstown",
    "sg:classifiers":[
        {
            "category":"Shopping",
            "subcategory":"Computers & Home Electronics",
            "type":"Retail Goods"
        }
    ],
    "sg:phone":"+61 2 9773 1444",
    "sg:postcode":"2200",
    "sg:province":"NSW",
    "sg:tags":[
        "hardware",
        "equipment"
    ],
    "wof:name":"A.R. Visual Computer Services",
    "wof:placetype":"venue"
},
  "geometry": {"coordinates":[151.055588,-33.931709],"type":"Point"}
}