{
  "type": "Feature",
  "properties": {
    "iso:country":"AU",
    "sg:address":"3/ 8 Finsbury St",
    "sg:city":"Newmarket",
    "sg:classifiers":[
        {
            "category":"Shopping",
            "subcategory":"Computers & Home Electronics",
            "type":"Retail Goods"
        }
    ],
    "sg:phone":"+61 7 3352 7666",
    "sg:postcode":"4051",
    "sg:province":"QLD",
    "sg:tags":[
        "hardware",
        "equipment"
    ],
    "wof:name":"K H Distribution Pty Ltd",
    "wof:placetype":"venue"
},
  "geometry": {"coordinates":[153.01449585,-27.4359951019],"type":"Point"}
}