{
  "type": "Feature",
  "properties": {
    "addr:full":"Unit 2 15 Halley Rd Balcatta WA 6021",
    "addr:housenumber":"15",
    "addr:postcode":"6021",
    "addr:street":"Halley Rd",
    "iso:country":"AU",
    "sg:address":"Unit 2 15 Halley Rd",
    "sg:city":"Balcatta",
    "sg:classifiers":[
        {
            "category":"Real Estate",
            "subcategory":"Architect",
            "type":"Services"
        }
    ],
    "sg:phone":"+61 438 345 477",
    "sg:postcode":"6021",
    "sg:province":"WA",
    "sg:tags":[
        "fuel",
        "equipment",
        "pump",
        "carburettor"
    ],
    "wof:name":"Balcatta Carburettors & Tuning Services",
    "wof:placetype":"venue"
},
  "geometry": {"coordinates":[115.824668884,-31.861782074],"type":"Point"}
}