{
  "type": "Feature",
  "properties": {
    "addr:full":"Suite 1/ 44 Mary St Noosaville QLD 4566",
    "addr:housenumber":"44",
    "addr:postcode":"4566",
    "addr:street":"Mary St",
    "iso:country":"AU",
    "sg:address":"Suite 1/ 44 Mary St",
    "sg:city":"Noosaville",
    "sg:classifiers":[
        {
            "category":"Banks & Credit Unions",
            "subcategory":"Investment Brokerage",
            "type":"Services"
        }
    ],
    "sg:phone":"+61 7 5449 9511",
    "sg:postcode":"4566",
    "sg:province":"QLD",
    "sg:tags":[
        "share",
        "broker",
        "stock"
    ],
    "wof:name":"ABN AMRO Morgans",
    "wof:placetype":"venue"
},
  "geometry": {"coordinates":[153.06736755399999,-26.4004096985],"type":"Point"}
}