{
  "type": "Feature",
  "properties": {
    "iso:country":"AU",
    "sg:address":"70 Dalmeny Ave",
    "sg:city":"Rosebery",
    "sg:classifiers":[
        {
            "category":"Fast Food",
            "type":"Food & Drink"
        }
    ],
    "sg:phone":"+61 2 9663 4281",
    "sg:postcode":"2018",
    "sg:province":"NSW",
    "sg:tags":[
        "away",
        "take"
    ],
    "wof:name":"Theonie's Sandwich Shop",
    "wof:placetype":"venue"
},
  "geometry": {"coordinates":[151.20773315400001,-33.9173812866],"type":"Point"}
}