{
  "type": "Feature",
  "properties": {
    "addr:full":"40 Cobram St Tocumwal NSW 2714",
    "addr:housenumber":"40",
    "addr:postcode":"2714",
    "addr:street":"Cobram St",
    "iso:country":"AU",
    "sg:address":"40 Cobram St",
    "sg:city":"Tocumwal",
    "sg:classifiers":[
        {
            "category":"Wholesale",
            "subcategory":"Farm Supplies",
            "type":"Manufacturing & Wholesale Goods"
        }
    ],
    "sg:phone":"+61 3 5874 2498",
    "sg:postcode":"2714",
    "sg:province":"NSW",
    "sg:tags":[
        "feed",
        "supplement",
        "stock"
    ],
    "wof:name":"C M Hicks & C Perryman",
    "wof:placetype":"venue"
},
  "geometry": {"coordinates":[145.575515747,-35.8184089661],"type":"Point"}
}