{
  "type": "Feature",
  "properties": {
    "iso:country":"AU",
    "sg:address":"308 Pulteney St",
    "sg:city":"Adelaide",
    "sg:classifiers":[
        {
            "category":"Shopping",
            "subcategory":"Music",
            "type":"Retail Goods"
        }
    ],
    "sg:phone":"+61 8 8223 3844",
    "sg:postcode":"5000",
    "sg:province":"SA",
    "sg:tags":[
        "instrument",
        "musical"
    ],
    "wof:name":"Rock Music",
    "wof:placetype":"venue"
},
  "geometry": {"coordinates":[138.60635375999999,-34.9308700562],"type":"Point"}
}