{
  "type": "Feature",
  "properties": {
    "addr:full":"21 Barclay St Heywood VIC 3304",
    "addr:housenumber":"21",
    "addr:postcode":"3304",
    "addr:street":"Barclay St",
    "iso:country":"AU",
    "sg:address":"21 Barclay St",
    "sg:city":"Heywood",
    "sg:classifiers":[
        {
            "category":"Health Services",
            "subcategory":"Doctor",
            "type":"Services"
        }
    ],
    "sg:phone":"+61 3 5527 1155",
    "sg:postcode":"3304",
    "sg:province":"VIC",
    "sg:tags":[
        "medical",
        "practitioner"
    ],
    "wof:name":"Fox Family Medicine",
    "wof:placetype":"venue"
},
  "geometry": {"coordinates":[141.62513732900001,-38.1366958618],"type":"Point"}
}