{
  "type": "Feature",
  "properties": {
    "addr:full":"Shop 9 Cottage Lane Arcade 444 High St Penrith NSW 2750",
    "addr:housenumber":"shop 9;444",
    "addr:postcode":"2750",
    "addr:street":"Cottage Lane Arcade;High St",
    "iso:country":"AU",
    "sg:address":"Shop 9 Cottage Lane Arcade 444 High St",
    "sg:city":"Penrith",
    "sg:classifiers":[
        {
            "category":"Personal",
            "subcategory":"Massage",
            "type":"Services"
        }
    ],
    "sg:phone":"+61 2 4732 1870",
    "sg:postcode":"2750",
    "sg:province":"NSW",
    "sg:tags":[
        "therapy"
    ],
    "wof:name":"Heavens Power Health & Beauty Therapy",
    "wof:placetype":"venue"
},
  "geometry": {"coordinates":[150.91557312,-33.8949241638],"type":"Point"}
}