{
  "type": "Feature",
  "properties": {
    "addr:full":"Argyle Mall Shopping Centre Cnr Clifford & Auburn Goulburn NSW 2580",
    "addr:postcode":"2580",
    "addr:street":"Cnr",
    "iso:country":"AU",
    "sg:address":"Argyle Mall Shopping Centre Cnr Clifford & Auburn",
    "sg:city":"Goulburn",
    "sg:classifiers":[
        {
            "category":"Shopping",
            "subcategory":"Department Store",
            "type":"Retail Goods"
        }
    ],
    "sg:phone":"+61 2 4821 7267",
    "sg:postcode":"2580",
    "sg:province":"NSW",
    "wof:name":"KMART",
    "wof:placetype":"venue"
},
  "geometry": {"coordinates":[149.71624755900001,-34.7571868896],"type":"Point"}
}