{
  "type": "Feature",
  "properties": {
    "addr:full":"U15/ 11- 21 Underwood Rd Homebush NSW 2140",
    "addr:housenumber":"21",
    "addr:postcode":"2140",
    "addr:street":"/ 11;Underwood Rd",
    "iso:country":"AU",
    "sg:address":"U15/ 11- 21 Underwood Rd",
    "sg:city":"Homebush",
    "sg:classifiers":[
        {
            "category":"Professional",
            "subcategory":"Computer Services",
            "type":"Services"
        }
    ],
    "sg:phone":"+61 2 9746 8299",
    "sg:postcode":"2140",
    "sg:province":"NSW",
    "sg:tags":[
        "package",
        "software"
    ],
    "wof:name":"Advanced Computer Software Supplies",
    "wof:placetype":"venue"
},
  "geometry": {"coordinates":[151.08128356899999,-33.8585929871],"type":"Point"}
}