{
  "type": "Feature",
  "properties": {
    "addr:full":"Valley View Rd Bateau Bay NSW 2261",
    "addr:postcode":"2261",
    "addr:street":"Valley View Rd",
    "iso:country":"AU",
    "sg:address":"Valley View Rd",
    "sg:city":"Bateau Bay",
    "sg:classifiers":[
        {
            "category":"Travel",
            "subcategory":"Hotels & Motels",
            "type":"Entertainment"
        }
    ],
    "sg:phone":"+61 2 4334 6285",
    "sg:postcode":"2261",
    "sg:province":"NSW",
    "sg:tags":[
        "accommodation"
    ],
    "wof:name":"B B's Bistro Bateau Bay Hotel",
    "wof:placetype":"venue"
},
  "geometry": {"coordinates":[151.471283,-33.38879],"type":"Point"}
}