{
  "type": "Feature",
  "properties": {
    "iso:country":"AU",
    "sg:address":"390 Canterbury (Cnr Princess St) Rd",
    "sg:city":"Hurlstone Park",
    "sg:classifiers":[
        {
            "category":"Wholesale",
            "subcategory":"Electrical",
            "type":"Manufacturing & Wholesale Goods"
        }
    ],
    "sg:phone":"+61 2 9799 3838",
    "sg:postcode":"2193",
    "sg:province":"NSW",
    "sg:tags":[
        "wholesaler"
    ],
    "wof:name":"Excel Electrical Wholesalers",
    "wof:placetype":"venue"
},
  "geometry": {"coordinates":[151.1259,-33.907433],"type":"Point"}
}