{
  "type": "Feature",
  "properties": {
    "addr:full":"464 Malvern Rd Prahran VIC 3181",
    "addr:housenumber":"464",
    "addr:postcode":"3181",
    "addr:street":"Malvern Rd",
    "iso:country":"AU",
    "sg:address":"464 Malvern Rd",
    "sg:city":"Prahran",
    "sg:classifiers":[
        {
            "category":"Professional",
            "subcategory":"Art Services",
            "type":"Services"
        }
    ],
    "sg:phone":"+61 3 9510 0588",
    "sg:postcode":"3181",
    "sg:province":"VIC",
    "sg:tags":[
        "interior",
        "decorator"
    ],
    "wof:name":"Ak Gallery",
    "wof:placetype":"venue"
},
  "geometry": {"coordinates":[145.00193786599999,-37.8480415344],"type":"Point"}
}