{
  "type": "Feature",
  "properties": {
    "addr:full":"14 Young Crt Delahey VIC 3037",
    "addr:housenumber":"14",
    "addr:postcode":"3037",
    "addr:street":"Young Crt",
    "iso:country":"AU",
    "sg:address":"14 Young Crt",
    "sg:city":"Delahey",
    "sg:classifiers":[
        {
            "category":"Retail",
            "subcategory":"Auto Rental",
            "type":"Services"
        }
    ],
    "sg:phone":"+61 3 9364 5200",
    "sg:postcode":"3037",
    "sg:province":"VIC",
    "sg:tags":[
        "chauffeur",
        "car",
        "hire",
        "driven",
        "limousine"
    ],
    "wof:name":"A Ace Chauffeured Limousines",
    "wof:placetype":"venue"
},
  "geometry": {"coordinates":[144.77543600000001,-37.720867],"type":"Point"}
}