{
  "type": "Feature",
  "properties": {
    "addr:full":"Level 6 122 Arthur St North Sydney NSW 2060",
    "addr:housenumber":"122",
    "addr:postcode":"2060",
    "addr:street":"Arthur St",
    "iso:country":"AU",
    "sg:address":"Level 6 122 Arthur St",
    "sg:city":"North Sydney",
    "sg:classifiers":[
        {
            "category":"Arts & Performance",
            "subcategory":"Theater",
            "type":"Entertainment"
        }
    ],
    "sg:phone":"+61 2 9966 1723",
    "sg:postcode":"2060",
    "sg:province":"NSW",
    "sg:tags":[
        "agency",
        "booking",
        "theatre"
    ],
    "wof:name":"Halftix.Com.Au",
    "wof:placetype":"venue"
},
  "geometry": {"coordinates":[151.21002197300001,-33.8385162354],"type":"Point"}
}