{
  "type": "Feature",
  "properties": {
    "iso:country":"AU",
    "sg:address":"57 Mooltan St",
    "sg:city":"Flemington",
    "sg:classifiers":[
        {
            "category":"Professional",
            "subcategory":"Research",
            "type":"Services"
        }
    ],
    "sg:phone":"+61 3 9376 7496",
    "sg:postcode":"3031",
    "sg:province":"VIC",
    "sg:tags":[
        "historical"
    ],
    "wof:name":"Historica Cultural Heritage Projects",
    "wof:placetype":"venue"
},
  "geometry": {"coordinates":[144.937317,-37.781509],"type":"Point"}
}