{
  "type": "Feature",
  "properties": {
    "addr:full":"63 May Rd Narraweena NSW 2099",
    "addr:housenumber":"63",
    "addr:postcode":"2099",
    "addr:street":"May Rd",
    "iso:country":"AU",
    "sg:address":"63 May Rd",
    "sg:city":"Narraweena",
    "sg:classifiers":[
        {
            "category":"Health Services",
            "subcategory":"Doctor",
            "type":"Services"
        }
    ],
    "sg:phone":"+61 2 9981 1911",
    "sg:postcode":"2099",
    "sg:province":"NSW",
    "sg:tags":[
        "medical",
        "practitioner"
    ],
    "wof:name":"Croft R B & M Drs",
    "wof:placetype":"venue"
},
  "geometry": {"coordinates":[151.276046753,-33.7555541992],"type":"Point"}
}