{
  "type": "Feature",
  "properties": {
    "addr:full":"Leahy St Dalwallinu WA 6609",
    "addr:postcode":"6609",
    "addr:street":"Leahy St",
    "iso:country":"AU",
    "sg:address":"Leahy St",
    "sg:city":"Dalwallinu",
    "sg:classifiers":[
        {
            "category":"Manufacturing",
            "subcategory":"Rubber & Plastics",
            "type":"Manufacturing & Wholesale Goods"
        }
    ],
    "sg:phone":"+61 1800 646 277",
    "sg:postcode":"6609",
    "sg:province":"WA",
    "sg:tags":[
        "wholesaler",
        "product",
        "mfrs"
    ],
    "wof:name":"Rapid Plastics W A",
    "wof:placetype":"venue"
},
  "geometry": {"coordinates":[116.668937683,-30.2794780731],"type":"Point"}
}