{
  "type": "Feature",
  "properties": {
    "iso:country":"AU",
    "sg:address":"Shp14/ 26-51 River St",
    "sg:city":"Ballina",
    "sg:classifiers":[
        {
            "category":"Cafe",
            "type":"Food & Drink"
        }
    ],
    "sg:phone":"+61 2 6681 4095",
    "sg:postcode":"2478",
    "sg:province":"NSW",
    "wof:name":"Evolution Cafe & Wine Bar",
    "wof:placetype":"venue"
},
  "geometry": {"coordinates":[153.563323975,-28.871799469],"type":"Point"}
}