{
  "type": "Feature",
  "properties": {
    "addr:full":"Unit 51 537 William St Mt Lawley WA 6050",
    "addr:housenumber":"537",
    "addr:postcode":"6050",
    "addr:street":"William St",
    "iso:country":"AU",
    "sg:address":"Unit 51 537 William St",
    "sg:city":"Mt Lawley",
    "sg:classifiers":[
        {
            "category":"Building & Trades",
            "subcategory":"Landscaping Services",
            "type":"Services"
        }
    ],
    "sg:phone":"+61 8 9227 9900",
    "sg:postcode":"6050",
    "sg:province":"WA",
    "sg:tags":[
        "consultant"
    ],
    "wof:name":"Makulbek",
    "wof:placetype":"venue"
},
  "geometry": {"coordinates":[115.866249084,-31.93608284],"type":"Point"}
}