{
  "type": "Feature",
  "properties": {
    "iso:country":"AU",
    "sg:address":"Lvl4/ 10 Quay St",
    "sg:city":"Haymarket",
    "sg:classifiers":[
        {
            "category":"Education",
            "subcategory":"Dance Studio",
            "type":"Public Place"
        }
    ],
    "sg:phone":"+61 2 9211 4161",
    "sg:postcode":"1236",
    "sg:province":"NSW",
    "sg:tags":[
        "instruction",
        "language"
    ],
    "wof:name":"A G Mate Academy Pty Ltd",
    "wof:placetype":"venue"
},
  "geometry": {"coordinates":[151.202957,-33.88065],"type":"Point"}
}