{
  "type": "Feature",
  "properties": {
    "iso:country":"AU",
    "sg:address":"43 Eastlake Drv",
    "sg:city":"Wagga Wagga",
    "sg:classifiers":[
        {
            "category":"Building & Trades",
            "subcategory":"Landscaping Services",
            "type":"Services"
        }
    ],
    "sg:phone":"+61 417 232 772",
    "sg:postcode":"2650",
    "sg:province":"NSW",
    "sg:tags":[
        "control",
        "weed"
    ],
    "wof:name":"Grant Rhys Contract Spraying",
    "wof:placetype":"venue"
},
  "geometry": {"coordinates":[147.378829956,-35.1711502075],"type":"Point"}
}