{
  "type": "Feature",
  "properties": {
    "addr:full":"160 Churchill Rd (North) Cavan SA 5094",
    "addr:housenumber":"160",
    "addr:postcode":"5094",
    "addr:street":"Churchill Rd North",
    "iso:country":"AU",
    "sg:address":"160 Churchill Rd (North)",
    "sg:city":"Cavan",
    "sg:classifiers":[
        {
            "category":"Real Estate",
            "subcategory":"Real Estate Agent",
            "type":"Services"
        }
    ],
    "sg:phone":"+61 8 8447 2800",
    "sg:postcode":"5094",
    "sg:province":"SA",
    "sg:tags":[
        "handyman's",
        "equipment",
        "hire",
        "builders",
        "contractor"
    ],
    "wof:name":"Royal Wolf Container Hire, Sales & Modifications",
    "wof:placetype":"venue"
},
  "geometry": {"coordinates":[138.59426879899999,-34.8316993713],"type":"Point"}
}