{
  "type": "Feature",
  "properties": {
    "addr:full":"1st Flr/ 265 Illawarra Rd Marrickville NSW 2204",
    "addr:housenumber":"/ 265",
    "addr:postcode":"2204",
    "addr:street":"Illawarra Rd",
    "iso:country":"AU",
    "sg:address":"1st Flr/ 265 Illawarra Rd",
    "sg:city":"Marrickville",
    "sg:classifiers":[
        {
            "category":"Banks & Credit Unions",
            "subcategory":"Investment Brokerage",
            "type":"Services"
        }
    ],
    "sg:phone":"+61 2 9558 9666",
    "sg:postcode":"2204",
    "sg:province":"NSW",
    "sg:tags":[
        "finance",
        "broker"
    ],
    "wof:name":"Universal Finance Corporation Pty Ltd",
    "wof:placetype":"venue"
},
  "geometry": {"coordinates":[151.15980500000001,-33.907028],"type":"Point"}
}