{
  "type": "Feature",
  "properties": {
    "addr:full":"20 James Ave Aspendale VIC 3195",
    "addr:housenumber":"20",
    "addr:postcode":"3195",
    "addr:street":"James Ave",
    "iso:country":"AU",
    "sg:address":"20 James Ave",
    "sg:city":"Aspendale",
    "sg:classifiers":[
        {
            "category":"Building & Trades",
            "subcategory":"Plumbing",
            "type":"Services"
        }
    ],
    "sg:phone":"+61 3 9588 1110",
    "sg:postcode":"3195",
    "sg:province":"VIC",
    "sg:tags":[
        "plumber",
        "gasfitters"
    ],
    "wof:name":"Ecowave Plumbing & Maintenance",
    "wof:placetype":"venue"
},
  "geometry": {"coordinates":[145.09657287600001,-38.0152931213],"type":"Point"}
}