{
  "type": "Feature",
  "properties": {
    "addr:full":"18 Theodore St Curtin ACT 2605",
    "addr:housenumber":"18",
    "addr:postcode":"2605",
    "addr:street":"Theodore St",
    "iso:country":"AU",
    "sg:address":"18 Theodore St",
    "sg:city":"Curtin",
    "sg:classifiers":[
        {
            "category":"Education",
            "subcategory":"School",
            "type":"Public Place"
        }
    ],
    "sg:phone":"+61 2 6281 4811",
    "sg:postcode":"2605",
    "sg:province":"ACT",
    "wof:name":"Holy Trinity Primary School",
    "wof:placetype":"venue"
},
  "geometry": {"coordinates":[149.08198547399999,-35.3280220032],"type":"Point"}
}