{
  "type": "Feature",
  "properties": {
    "addr:full":"Shop2, 40 Aplin St Cairns QLD 4870",
    "addr:housenumber":"40",
    "addr:postcode":"4870",
    "addr:street":"Aplin St",
    "iso:country":"AU",
    "sg:address":"Shop2, 40 Aplin St",
    "sg:city":"Cairns",
    "sg:classifiers":[
        {
            "category":"Manufacturing",
            "subcategory":"Food",
            "type":"Manufacturing & Wholesale Goods"
        }
    ],
    "sg:phone":"+61 7 4051 1024",
    "sg:postcode":"4870",
    "sg:province":"QLD",
    "sg:tags":[
        "function",
        "catering"
    ],
    "wof:name":"Patrices Delicatessen",
    "wof:placetype":"venue"
},
  "geometry": {"coordinates":[145.77198791500001,-16.9220943451],"type":"Point"}
}