{
  "type": "Feature",
  "properties": {
    "addr:full":"359 North Rocks Rd North Rocks NSW 2151",
    "addr:housenumber":"359",
    "addr:postcode":"2151",
    "addr:street":"North Rocks Rd",
    "iso:country":"AU",
    "sg:address":"359 North Rocks Rd",
    "sg:city":"North Rocks",
    "sg:classifiers":[
        {
            "category":"Education",
            "subcategory":"School",
            "type":"Public Place"
        }
    ],
    "sg:phone":"+61 2 9871 1772",
    "sg:postcode":"2151",
    "sg:province":"NSW",
    "sg:tags":[
        "state",
        "-",
        "nsw"
    ],
    "wof:name":"North Rocks Public School",
    "wof:placetype":"venue"
},
  "geometry": {"coordinates":[151.02650451700001,-33.7695045471],"type":"Point"}
}