{
  "type": "Feature",
  "properties": {
    "addr:full":"River Rd Markwood VIC 3678",
    "addr:postcode":"3678",
    "addr:street":"River Rd",
    "iso:country":"AU",
    "sg:address":"River Rd",
    "sg:city":"Markwood",
    "sg:classifiers":[
        {
            "category":"Home & Garden",
            "subcategory":"Furniture",
            "type":"Retail Goods"
        }
    ],
    "sg:phone":"+61 417 548 439",
    "sg:postcode":"3678",
    "sg:province":"VIC",
    "sg:tags":[
        "outdoor"
    ],
    "wof:name":"Darumeer P/L",
    "wof:placetype":"venue"
},
  "geometry": {"coordinates":[146.45274352999999,-36.4070014954],"type":"Point"}
}