{
  "type": "Feature",
  "properties": {
    "addr:full":"393 Payneham Rd Marden SA 5070",
    "addr:housenumber":"393",
    "addr:postcode":"5070",
    "addr:street":"Payneham Rd",
    "iso:country":"AU",
    "sg:address":"393 Payneham Rd",
    "sg:city":"Marden",
    "sg:classifiers":[
        {
            "category":"Government",
            "subcategory":"City Hall",
            "type":"Public Place"
        }
    ],
    "sg:phone":"+61 8 8337 7974",
    "sg:postcode":"5070",
    "sg:province":"SA",
    "wof:name":"Payneham Masonic Hall Trust Incorporated",
    "wof:placetype":"venue"
},
  "geometry": {"coordinates":[138.641082764,-34.8954696655],"type":"Point"}
}