{
  "type": "Feature",
  "properties": {
    "addr:full":"335 - 351 Eastbourne Rd Rosebud West VIC 3940",
    "addr:housenumber":"351",
    "addr:postcode":"3940",
    "addr:street":"Eastbourne Rd",
    "iso:country":"AU",
    "sg:address":"335 - 351 Eastbourne Rd",
    "sg:city":"Rosebud West",
    "sg:classifiers":[
        {
            "category":"Social Services",
            "subcategory":"Retirement Home",
            "type":"Services"
        }
    ],
    "sg:phone":"+61 3 5986 4455",
    "sg:postcode":"3940",
    "sg:province":"VIC",
    "sg:tags":[
        "village"
    ],
    "sg:website":"http://www.villageglen.com.au",
    "wof:name":"The Village Glen",
    "wof:placetype":"venue"
},
  "geometry": {"coordinates":[144.878372192,-38.3672943115],"type":"Point"}
}