{
  "type": "Feature",
  "properties": {
    "iso:country":"AU",
    "sg:address":"PO Box 64",
    "sg:city":"Mackay",
    "sg:classifiers":[
        {
            "category":"Manufacturing",
            "subcategory":"Food",
            "type":"Manufacturing & Wholesale Goods"
        }
    ],
    "sg:phone":"+61 1300 654 465",
    "sg:postcode":"4740",
    "sg:province":"QLD",
    "sg:tags":[
        "function",
        "catering"
    ],
    "wof:name":"Coast To Coast The Golden Roast",
    "wof:placetype":"venue"
},
  "geometry": {"coordinates":[149.11184692399999,-21.1551895142],"type":"Point"}
}