{
  "type": "Feature",
  "properties": {
    "iso:country":"AU",
    "sg:address":"101 Parramatta Rd",
    "sg:city":"Camperdown",
    "sg:classifiers":[
        {
            "category":"Shopping",
            "subcategory":"Party Supplies",
            "type":"Retail Goods"
        }
    ],
    "sg:phone":"+61 2 9519 4848",
    "sg:postcode":"2050",
    "sg:province":"NSW",
    "sg:tags":[
        "children's"
    ],
    "wof:name":"Kidstuff",
    "wof:placetype":"venue"
},
  "geometry": {"coordinates":[151.17610199999999,-33.887005],"type":"Point"}
}