{
  "type": "Feature",
  "properties": {
    "iso:country":"AU",
    "sg:address":"77 Darghan St",
    "sg:city":"Glebe",
    "sg:classifiers":[
        {
            "category":"Professional",
            "subcategory":"Engineering",
            "type":"Services"
        }
    ],
    "sg:phone":"+61 2 9660 5603",
    "sg:postcode":"2037",
    "sg:province":"NSW",
    "sg:tags":[
        "consulting",
        "engineer"
    ],
    "wof:name":"Advanced Coal Processing Pty Ltd",
    "wof:placetype":"venue"
},
  "geometry": {"coordinates":[151.18971252399999,-33.8768920898],"type":"Point"}
}