{
  "type": "Feature",
  "properties": {
    "iso:country":"AU",
    "sg:address":"173a Derby St",
    "sg:city":"Pascoe Vale",
    "sg:classifiers":[
        {
            "category":"Fast Food",
            "type":"Food & Drink"
        }
    ],
    "sg:phone":"+61 3 9350 7399",
    "sg:postcode":"3044",
    "sg:province":"VIC",
    "sg:tags":[
        "away",
        "take"
    ],
    "wof:name":"Derby's Rooster",
    "wof:placetype":"venue"
},
  "geometry": {"coordinates":[144.94694519000001,-37.7237434387],"type":"Point"}
}