{
  "type": "Feature",
  "properties": {
    "addr:full":"(Bilo Carpark) Shop 2/ 65 Winnima Way Berkeley NSW 2506",
    "addr:housenumber":"2 / 65",
    "addr:postcode":"2506",
    "addr:street":"Winnima Way",
    "iso:country":"AU",
    "sg:address":"(Bilo Carpark) Shop 2/ 65 Winnima Way",
    "sg:city":"Berkeley",
    "sg:classifiers":[
        {
            "category":"Food & Beverages",
            "subcategory":"Bakery",
            "type":"Retail Goods"
        }
    ],
    "sg:phone":"+61 2 4272 7779",
    "sg:postcode":"2506",
    "sg:province":"NSW",
    "sg:tags":[
        "baker"
    ],
    "wof:name":"Berkeley Cakes & Pies",
    "wof:placetype":"venue"
},
  "geometry": {"coordinates":[150.84637499999999,-34.480167],"type":"Point"}
}