{
  "type": "Feature",
  "properties": {
    "iso:country":"AU",
    "sg:address":"47 Berriman Drv",
    "sg:city":"Wangara",
    "sg:classifiers":[
        {
            "category":"Autos & Motor Vehicles",
            "subcategory":"Boat Sales",
            "type":"Retail Goods"
        }
    ],
    "sg:phone":"+61 8 9309 3480",
    "sg:postcode":"6065",
    "sg:province":"WA",
    "sg:tags":[
        "yacht"
    ],
    "wof:name":"Sundowner Technologies",
    "wof:placetype":"venue"
},
  "geometry": {"coordinates":[115.82539367699999,-31.7934322357],"type":"Point"}
}