{
  "type": "Feature",
  "properties": {
    "addr:full":"6 Merrang Crt Glen Waverley VIC 3150",
    "addr:housenumber":"6",
    "addr:postcode":"3150",
    "addr:street":"Merrang Crt",
    "iso:country":"AU",
    "sg:address":"6 Merrang Crt",
    "sg:city":"Glen Waverley",
    "sg:classifiers":[
        {
            "category":"Autos & Motor Vehicles",
            "subcategory":"Auto Supplies",
            "type":"Retail Goods"
        }
    ],
    "sg:phone":"+61 3 9560 2581",
    "sg:postcode":"3150",
    "sg:province":"VIC",
    "sg:tags":[
        "camper-trailers",
        "caravan",
        "equipment"
    ],
    "wof:name":"Slingshot Sleeper Company",
    "wof:placetype":"venue"
},
  "geometry": {"coordinates":[145.176437378,-37.9036407471],"type":"Point"}
}