{
  "type": "Feature",
  "properties": {
    "addr:full":"17- 19 Stockton St Nelson Bay NSW 2315",
    "addr:housenumber":"19",
    "addr:postcode":"2315",
    "addr:street":"Stockton St",
    "iso:country":"AU",
    "sg:address":"17- 19 Stockton St",
    "sg:city":"Nelson Bay",
    "sg:classifiers":[
        {
            "category":"Health Services",
            "subcategory":"Optometrist",
            "type":"Services"
        }
    ],
    "sg:phone":"+61 2 4984 4077",
    "sg:postcode":"2315",
    "sg:province":"NSW",
    "wof:name":"Chapman Rick",
    "wof:placetype":"venue"
},
  "geometry": {"coordinates":[152.14369199999999,-32.721798],"type":"Point"}
}