{
  "type": "Feature",
  "properties": {
    "addr:full":"73 Clifton Beach Rd Clifton Beach TAS 7020",
    "addr:housenumber":"73",
    "addr:postcode":"7020",
    "addr:street":"Clifton Beach Rd",
    "iso:country":"AU",
    "sg:address":"73 Clifton Beach Rd",
    "sg:city":"Clifton Beach",
    "sg:classifiers":[
        {
            "category":"Food & Beverages",
            "subcategory":"Meat & Fish",
            "type":"Retail Goods"
        }
    ],
    "sg:phone":"+61 438 589 955",
    "sg:postcode":"7020",
    "sg:province":"TAS",
    "sg:tags":[
        "aquaculture"
    ],
    "wof:name":"Phycotec Aquaculture Environmental Management",
    "wof:placetype":"venue"
},
  "geometry": {"coordinates":[147.50643920900001,-42.9679718018],"type":"Point"}
}