{
  "type": "Feature",
  "properties": {
    "addr:full":"214 Dawson St Brunswick West VIC 3055",
    "addr:housenumber":"214",
    "addr:postcode":"3055",
    "addr:street":"Dawson St",
    "iso:country":"AU",
    "sg:address":"214 Dawson St",
    "sg:city":"Brunswick West",
    "sg:classifiers":[
        {
            "category":"Professional",
            "subcategory":"Management & Consulting",
            "type":"Services"
        }
    ],
    "sg:phone":"+61 3 9387 5533",
    "sg:postcode":"3055",
    "sg:province":"VIC",
    "sg:tags":[
        "consultant"
    ],
    "wof:name":"D R Management Consultants",
    "wof:placetype":"venue"
},
  "geometry": {"coordinates":[144.939849853,-37.7687530518],"type":"Point"}
}