{
  "type": "Feature",
  "properties": {
    "iso:country":"AU",
    "sg:address":"490 Dean St",
    "sg:city":"Albury",
    "sg:classifiers":[
        {
            "category":"Shopping",
            "subcategory":"Computers & Home Electronics",
            "type":"Retail Goods"
        }
    ],
    "sg:phone":"+61 2 6021 0133",
    "sg:postcode":"2640",
    "sg:province":"NSW",
    "sg:tags":[
        "global",
        "positioning",
        "system"
    ],
    "wof:name":"Mountain Designs",
    "wof:placetype":"venue"
},
  "geometry": {"coordinates":[146.91856384299999,-36.0808868408],"type":"Point"}
}