{
  "type": "Feature",
  "properties": {
    "iso:country":"AU",
    "sg:address":"Arthur Hwy",
    "sg:city":"Dunalley",
    "sg:classifiers":[
        {
            "category":"Professional",
            "subcategory":"Art Services",
            "type":"Services"
        }
    ],
    "sg:phone":"+61 419 335 735",
    "sg:postcode":"7177",
    "sg:province":"TAS",
    "sg:tags":[
        "interior",
        "decorator"
    ],
    "wof:name":"von Schroeder Fine Arts",
    "wof:placetype":"venue"
},
  "geometry": {"coordinates":[147.80749499999999,-42.889317],"type":"Point"}
}