{
  "type": "Feature",
  "properties": {
    "addr:full":"32 Bay St Brighton VIC 3186",
    "addr:housenumber":"32",
    "addr:postcode":"3186",
    "addr:street":"Bay St",
    "iso:country":"AU",
    "sg:address":"32 Bay St",
    "sg:city":"Brighton",
    "sg:classifiers":[
        {
            "category":"Health Services",
            "subcategory":"Health Practitioner",
            "type":"Services"
        }
    ],
    "sg:phone":"+61 3 9596 9633",
    "sg:postcode":"3186",
    "sg:province":"VIC",
    "sg:tags":[
        "acupuncture"
    ],
    "wof:name":"Beatrice Michael Arcangelo",
    "wof:placetype":"venue"
},
  "geometry": {"coordinates":[144.98806762699999,-37.9038734436],"type":"Point"}
}