{
  "type": "Feature",
  "properties": {
    "addr:full":"7 Jomary Crt Berwick VIC 3806",
    "addr:housenumber":"7",
    "addr:postcode":"3806",
    "addr:street":"Jomary Crt",
    "iso:country":"AU",
    "sg:address":"7 Jomary Crt",
    "sg:city":"Berwick",
    "sg:classifiers":[
        {
            "category":"Building & Trades",
            "subcategory":"Landscaping Services",
            "type":"Services"
        }
    ],
    "sg:phone":"+61 3 9769 5352",
    "sg:postcode":"3806",
    "sg:province":"VIC",
    "sg:tags":[
        "designer",
        "landscape",
        "contractor"
    ],
    "wof:name":"Woodbridge Landscape Developments",
    "wof:placetype":"venue"
},
  "geometry": {"coordinates":[145.35235595699999,-38.0366973877],"type":"Point"}
}