{
  "type": "Feature",
  "properties": {
    "addr:full":"58 Dower St Mandurah WA 6210",
    "addr:housenumber":"58",
    "addr:postcode":"6210",
    "addr:street":"Dower St",
    "iso:country":"AU",
    "sg:address":"58 Dower St",
    "sg:city":"Mandurah",
    "sg:classifiers":[
        {
            "category":"Shopping",
            "subcategory":"Computers & Home Electronics",
            "type":"Retail Goods"
        }
    ],
    "sg:phone":"+61 8 9534 7777",
    "sg:postcode":"6210",
    "sg:province":"WA",
    "sg:tags":[
        "hardware",
        "equipment"
    ],
    "sg:website":"http://www.eosit.com.au",
    "wof:name":"EOS Computer Specialists",
    "wof:placetype":"venue"
},
  "geometry": {"coordinates":[115.740341,-32.527435],"type":"Point"}
}