{
  "type": "Feature",
  "properties": {
    "addr:full":"176 Parramatta Rd Ashfield NSW 2131",
    "addr:housenumber":"176",
    "addr:postcode":"2131",
    "addr:street":"Parramatta Rd",
    "iso:country":"AU",
    "sg:address":"176 Parramatta Rd",
    "sg:city":"Ashfield",
    "sg:classifiers":[
        {
            "category":"Wholesale",
            "subcategory":"Apparel",
            "type":"Manufacturing & Wholesale Goods"
        }
    ],
    "sg:phone":"+61 2 9799 1240",
    "sg:postcode":"2131",
    "sg:province":"NSW",
    "sg:tags":[
        "wholesaler",
        "mfrs",
        "sportswear",
        "women's"
    ],
    "wof:name":"Debbie Bennett Sportswear",
    "wof:placetype":"venue"
},
  "geometry": {"coordinates":[151.13340759299999,-33.8828048706],"type":"Point"}
}