{
  "type": "Feature",
  "properties": {
    "addr:full":"144 Burren St Newtown NSW 2042",
    "addr:housenumber":"144",
    "addr:postcode":"2042",
    "addr:street":"Burren St",
    "iso:country":"AU",
    "sg:address":"144 Burren St",
    "sg:city":"Newtown",
    "sg:classifiers":[
        {
            "category":"Education",
            "subcategory":"University",
            "type":"Public Place"
        }
    ],
    "sg:phone":"+61 2 9351 0000",
    "sg:postcode":"2042",
    "sg:province":"NSW",
    "sg:tags":[
        "college",
        "tertiary"
    ],
    "wof:name":"University Of Sydney Graduate School Of Business",
    "wof:placetype":"venue"
},
  "geometry": {"coordinates":[151.18483000000001,-33.895958],"type":"Point"}
}