{
  "type": "Feature",
  "properties": {
    "addr:full":"109 Gaffney St Coburg VIC 3058",
    "addr:housenumber":"109",
    "addr:postcode":"3058",
    "addr:street":"Gaffney St",
    "iso:country":"AU",
    "sg:address":"109 Gaffney St",
    "sg:city":"Coburg",
    "sg:classifiers":[
        {
            "category":"Fast Food",
            "type":"Food & Drink"
        }
    ],
    "sg:phone":"+61 3 9350 4762",
    "sg:postcode":"3058",
    "sg:province":"VIC",
    "sg:tags":[
        "away",
        "take"
    ],
    "wof:name":"Garwah Chinese Cafe",
    "wof:placetype":"venue"
},
  "geometry": {"coordinates":[144.958694458,-37.7334823608],"type":"Point"}
}