{
  "type": "Feature",
  "properties": {
    "addr:full":"PO Box 195W Westcourt QLD 4870",
    "addr:postcode":"4870",
    "iso:country":"AU",
    "sg:address":"PO Box 195W",
    "sg:city":"Westcourt",
    "sg:classifiers":[
        {
            "category":"Shopping",
            "type":"Retail Goods"
        }
    ],
    "sg:phone":"+61 7 4031 1738",
    "sg:postcode":"4870",
    "sg:province":"QLD",
    "sg:tags":[
        "equipment",
        "safety",
        "accessory"
    ],
    "sg:website":"http://www.norstate.com.au",
    "wof:name":"Norstate Gas Supplies",
    "wof:placetype":"venue"
},
  "geometry": {"coordinates":[145.77450561500001,-16.9298095703],"type":"Point"}
}