{
  "type": "Feature",
  "properties": {
    "addr:full":"10 Irvine Crt Wodonga VIC 3690",
    "addr:housenumber":"10",
    "addr:postcode":"3690",
    "addr:street":"Irvine Crt",
    "iso:country":"AU",
    "sg:address":"10 Irvine Crt",
    "sg:city":"Wodonga",
    "sg:classifiers":[
        {
            "category":"Wholesale",
            "subcategory":"Medical Equipment & Supplies",
            "type":"Manufacturing & Wholesale Goods"
        }
    ],
    "sg:phone":"+61 412 690 585",
    "sg:postcode":"3690",
    "sg:province":"VIC",
    "sg:tags":[
        "plastering"
    ],
    "wof:name":"Bob Adams Plastering Specialists",
    "wof:placetype":"venue"
},
  "geometry": {"coordinates":[146.84574890100001,-36.1350021362],"type":"Point"}
}