{
  "type": "Feature",
  "properties": {
    "iso:country":"AU",
    "sg:address":"Shop 14, Sanctuary Lakes Shopping Centre, Point Co",
    "sg:city":"Point Cook",
    "sg:classifiers":[
        {
            "category":"Food & Beverages",
            "subcategory":"Bakery",
            "type":"Retail Goods"
        }
    ],
    "sg:phone":"+61 3 9395 3255",
    "sg:postcode":"3030",
    "sg:province":"VIC",
    "sg:tags":[
        "baker"
    ],
    "wof:name":"Bakers Delight Ltd",
    "wof:placetype":"venue"
},
  "geometry": {"coordinates":[144.754135,-37.896065],"type":"Point"}
}