{
  "type": "Feature",
  "properties": {
    "addr:full":"Battersby Rd Greenhead WA 6514",
    "addr:postcode":"6514",
    "addr:street":"Battersby Rd",
    "iso:country":"AU",
    "sg:address":"Battersby Rd",
    "sg:city":"Greenhead",
    "sg:classifiers":[
        {
            "category":"Sports & Exercise",
            "subcategory":"Golf",
            "type":"Entertainment"
        }
    ],
    "sg:phone":"+61 8 9953 1223",
    "sg:postcode":"6514",
    "sg:province":"WA",
    "sg:tags":[
        "club"
    ],
    "wof:name":"Greenhead Golf & Sporting Club Inc",
    "wof:placetype":"venue"
},
  "geometry": {"coordinates":[114.971649,-30.068432],"type":"Point"}
}