{
  "type": "Feature",
  "properties": {
    "addr:full":"Shop 352, Westfield Eastgardens NSW 2036",
    "addr:housenumber":"352",
    "addr:postcode":"2036",
    "addr:street":"Westfield Eastgardens",
    "iso:country":"AU",
    "sg:address":"Shop 352, Westfield",
    "sg:city":"Eastgardens",
    "sg:classifiers":[
        {
            "category":"Travel",
            "subcategory":"Travel Agent",
            "type":"Entertainment"
        }
    ],
    "sg:phone":"+61 2 9314 3808",
    "sg:postcode":"2036",
    "sg:province":"NSW",
    "sg:tags":[
        "consultant"
    ],
    "wof:name":"Travel Advantage",
    "wof:placetype":"venue"
},
  "geometry": {"coordinates":[151.227172852,-33.9459495544],"type":"Point"}
}