{
  "type": "Feature",
  "properties": {
    "addr:full":"Un 1/ 76 St Andrews St Brighton VIC 3186",
    "addr:postcode":"3186",
    "addr:street":"76 St Andrews St",
    "iso:country":"AU",
    "sg:address":"Un 1/ 76 St Andrews St",
    "sg:city":"Brighton",
    "sg:classifiers":[
        {
            "category":"Building & Trades",
            "subcategory":"Construction",
            "type":"Services"
        }
    ],
    "sg:phone":"+61 3 9592 0866",
    "sg:postcode":"3186",
    "sg:province":"VIC",
    "sg:tags":[
        "contractor"
    ],
    "wof:name":"Sommer Constructions (Vic) Pty Ltd",
    "wof:placetype":"venue"
},
  "geometry": {"coordinates":[144.99488830600001,-37.9124832153],"type":"Point"}
}