{
  "type": "Feature",
  "properties": {
    "iso:country":"AU",
    "sg:address":"4 Woosters La",
    "sg:city":"Nabiac",
    "sg:classifiers":[
        {
            "category":"Professional",
            "type":"Services"
        }
    ],
    "sg:phone":"+61 2 6554 1999",
    "sg:postcode":"2312",
    "sg:province":"NSW",
    "sg:tags":[
        "transport"
    ],
    "wof:name":"Great Lakes Freightlines Pty Ltd",
    "wof:placetype":"venue"
},
  "geometry": {"coordinates":[152.388611,-32.093891],"type":"Point"}
}