{
  "type": "Feature",
  "properties": {
    "addr:full":"Anzac Ave Toowoomba QLD 4350",
    "addr:postcode":"4350",
    "addr:street":"Anzac Ave",
    "iso:country":"AU",
    "sg:address":"Anzac Ave",
    "sg:city":"Toowoomba",
    "sg:classifiers":[
        {
            "category":"Retail",
            "subcategory":"Auto Repair",
            "type":"Services"
        }
    ],
    "sg:phone":"+61 7 4630 1977",
    "sg:postcode":"4350",
    "sg:province":"QLD",
    "sg:tags":[
        "bus",
        "truck"
    ],
    "wof:name":"Queensland Truck Centre",
    "wof:placetype":"venue"
},
  "geometry": {"coordinates":[151.91757200000001,-27.585888],"type":"Point"}
}