{
  "type": "Feature",
  "properties": {
    "addr:full":"31a Cape Three Points Rd Avoca Beach NSW 2251",
    "addr:housenumber":"31a",
    "addr:postcode":"2251",
    "addr:street":"Cape Three Points Rd",
    "iso:country":"AU",
    "sg:address":"31a Cape Three Points Rd",
    "sg:city":"Avoca Beach",
    "sg:phone":"+61 2 4382 3326",
    "sg:postcode":"2251",
    "sg:province":"NSW",
    "wof:name":"O&#039;Grady, David Plumbing & Draining",
    "wof:placetype":"venue"
},
  "geometry": {"coordinates":[151.43130493199999,-33.4668464661],"type":"Point"}
}