{
  "type": "Feature",
  "properties": {
    "addr:full":"20 Brunker Rd Broadmeadow NSW 2292",
    "addr:housenumber":"20",
    "addr:postcode":"2292",
    "addr:street":"Brunker Rd",
    "iso:country":"AU",
    "sg:address":"20 Brunker Rd",
    "sg:city":"Broadmeadow",
    "sg:classifiers":[
        {
            "category":"Landmark",
            "subcategory":"Scenic View",
            "type":"Public Place"
        }
    ],
    "sg:phone":"+61 2 4961 6313",
    "sg:postcode":"2292",
    "sg:province":"NSW",
    "sg:tags":[
        "staircase",
        "handrail"
    ],
    "wof:name":"Skydome Skylight Systems",
    "wof:placetype":"venue"
},
  "geometry": {"coordinates":[151.73594665499999,-32.9255561829],"type":"Point"}
}