{
  "type": "Feature",
  "properties": {
    "addr:full":"PO Box 2148 Ivanhoe East VIC 3079",
    "addr:postcode":"3079",
    "iso:country":"AU",
    "sg:address":"PO Box 2148",
    "sg:city":"Ivanhoe East",
    "sg:classifiers":[
        {
            "category":"Banks & Credit Unions",
            "subcategory":"Financial Services",
            "type":"Services"
        }
    ],
    "sg:phone":"+61 3 9689 9998",
    "sg:postcode":"3079",
    "sg:province":"VIC",
    "sg:tags":[
        "finance",
        "motor",
        "vehicle"
    ],
    "wof:name":"World of Finance",
    "wof:placetype":"venue"
},
  "geometry": {"coordinates":[145.05833435100001,-37.7727012634],"type":"Point"}
}