{
  "type": "Feature",
  "properties": {
    "addr:full":"Shiell Rd Berri SA 5343",
    "addr:postcode":"5343",
    "addr:street":"Shiell Rd",
    "iso:country":"AU",
    "sg:address":"Shiell Rd",
    "sg:city":"Berri",
    "sg:classifiers":[
        {
            "category":"Sports & Exercise",
            "subcategory":"Golf",
            "type":"Entertainment"
        }
    ],
    "sg:phone":"+61 8 8582 3666",
    "sg:postcode":"5343",
    "sg:province":"SA",
    "sg:tags":[
        "club"
    ],
    "wof:name":"Berri Golf Club Inc",
    "wof:placetype":"venue"
},
  "geometry": {"coordinates":[140.604415894,-34.26745224],"type":"Point"}
}