{
  "type": "Feature",
  "properties": {
    "iso:country":"AU",
    "sg:address":"2/ 81 Bassett St",
    "sg:city":"Mona Vale",
    "sg:classifiers":[
        {
            "category":"Marine",
            "type":"Transportation"
        }
    ],
    "sg:phone":"+61 1300 888 231",
    "sg:postcode":"2103",
    "sg:province":"NSW",
    "sg:tags":[
        "flagpole",
        "mast"
    ],
    "wof:name":"A AAFlagpoles",
    "wof:placetype":"venue"
},
  "geometry": {"coordinates":[151.30584716800001,-33.6707038879],"type":"Point"}
}