{
  "type": "Feature",
  "properties": {
    "addr:full":"27 Little Myers St (Opp. Australia Post) Geelong VIC 3220",
    "addr:housenumber":"27",
    "addr:postcode":"3220",
    "addr:street":"Little Myers St Opp.",
    "iso:country":"AU",
    "sg:address":"27 Little Myers St",
    "sg:city":"(Opp. Australia Post) Geelong",
    "sg:classifiers":[
        {
            "category":"Government",
            "subcategory":"Court House",
            "type":"Public Place"
        }
    ],
    "sg:phone":"+61 3 5221 0358",
    "sg:postcode":"3220",
    "sg:province":"VIC",
    "sg:tags":[
        "personal",
        "marriage",
        "family",
        "counselling"
    ],
    "wof:name":"Connections Geelong",
    "wof:placetype":"venue"
},
  "geometry": {"coordinates":[144.355728,-38.151497],"type":"Point"}
}