{
  "type": "Feature",
  "properties": {
    "addr:full":"Somerville Rd Hampton Park VIC 3976",
    "addr:postcode":"3976",
    "addr:street":"Somerville Rd",
    "iso:country":"AU",
    "sg:address":"Somerville Rd",
    "sg:city":"Hampton Park",
    "sg:classifiers":[
        {
            "category":"Fast Food",
            "type":"Food & Drink"
        }
    ],
    "sg:phone":"+61 3 9799 6679",
    "sg:postcode":"3976",
    "sg:province":"VIC",
    "sg:tags":[
        "away",
        "take"
    ],
    "wof:name":"Gourmet Kebab King Pty Ltd",
    "wof:placetype":"venue"
},
  "geometry": {"coordinates":[145.25935363799999,-38.028881073],"type":"Point"}
}