{
  "type": "Feature",
  "properties": {
    "addr:full":"7 Fielder St Gosford West NSW 2250",
    "addr:housenumber":"7",
    "addr:postcode":"2250",
    "addr:street":"Fielder St",
    "iso:country":"AU",
    "sg:address":"7 Fielder St",
    "sg:city":"Gosford West",
    "sg:classifiers":[
        {
            "category":"Education",
            "subcategory":"Dance Studio",
            "type":"Public Place"
        }
    ],
    "sg:phone":"+61 2 4332 1453",
    "sg:postcode":"2250",
    "sg:province":"NSW",
    "sg:tags":[
        "venue",
        "tuition"
    ],
    "wof:name":"Central Coast Premier Dance Academy",
    "wof:placetype":"venue"
},
  "geometry": {"coordinates":[151.330688477,-33.4265060425],"type":"Point"}
}