{
  "type": "Feature",
  "properties": {
    "iso:country":"AU",
    "sg:address":"98H Bellevue Rd",
    "sg:city":"Bellevue Hill",
    "sg:classifiers":[
        {
            "category":"Building & Trades",
            "subcategory":"Cleaning & Sanitation",
            "type":"Services"
        }
    ],
    "sg:phone":"+61 419 270 524",
    "sg:postcode":"2023",
    "sg:province":"NSW",
    "sg:tags":[
        "window"
    ],
    "wof:name":"Metro City Cleaning",
    "wof:placetype":"venue"
},
  "geometry": {"coordinates":[151.25199890100001,-33.8823242188],"type":"Point"}
}