{
  "type": "Feature",
  "properties": {
    "iso:country":"AU",
    "sg:address":"130 Scarborough St",
    "sg:city":"Southport",
    "sg:classifiers":[
        {
            "category":"Professional",
            "subcategory":"Employment Agencies",
            "type":"Services"
        }
    ],
    "sg:phone":"+61 7 5555 1111",
    "sg:postcode":"4215",
    "sg:province":"QLD",
    "wof:name":"Chandler Macleod",
    "wof:placetype":"venue"
},
  "geometry": {"coordinates":[153.412353516,-27.965045929],"type":"Point"}
}