{
  "type": "Feature",
  "properties": {
    "iso:country":"AU",
    "sg:address":"U3/ 3 Nesbitt St",
    "sg:city":"Wagga Wagga",
    "sg:classifiers":[
        {
            "category":"Autos & Motor Vehicles",
            "subcategory":"Auto Supplies",
            "type":"Retail Goods"
        }
    ],
    "sg:phone":"+61 1300 667 117",
    "sg:postcode":"2650",
    "sg:province":"NSW",
    "sg:tags":[
        "accessory"
    ],
    "wof:name":"Barjo Manufacturing",
    "wof:placetype":"venue"
},
  "geometry": {"coordinates":[147.38429260300001,-35.1212234497],"type":"Point"}
}