{
  "type": "Feature",
  "properties": {
    "addr:full":"20 Venning St Morphett Vale SA 5162",
    "addr:housenumber":"20",
    "addr:postcode":"5162",
    "addr:street":"Venning St",
    "iso:country":"AU",
    "sg:address":"20 Venning St",
    "sg:city":"Morphett Vale",
    "sg:classifiers":[
        {
            "category":"Education",
            "subcategory":"Kindergarten",
            "type":"Public Place"
        }
    ],
    "sg:phone":"+61 8 8382 1597",
    "sg:postcode":"5162",
    "sg:province":"SA",
    "sg:tags":[
        "pre-schools"
    ],
    "wof:name":"Morphett Vale Preschool Kindergarten",
    "wof:placetype":"venue"
},
  "geometry": {"coordinates":[138.52407836899999,-35.1155586243],"type":"Point"}
}