{
  "type": "Feature",
  "properties": {
    "addr:full":"88 Reserve Rd Artarmon NSW 2064",
    "addr:housenumber":"88",
    "addr:postcode":"2064",
    "addr:street":"Reserve Rd",
    "iso:country":"AU",
    "sg:address":"88 Reserve Rd",
    "sg:city":"Artarmon",
    "sg:classifiers":[
        {
            "category":"Home & Garden",
            "subcategory":"Building Materials",
            "type":"Retail Goods"
        }
    ],
    "sg:phone":"+61 2 9906 8395",
    "sg:postcode":"2064",
    "sg:province":"NSW",
    "sg:tags":[
        "pre-mixed",
        "concrete"
    ],
    "wof:name":"Boral Concrete Laboratory",
    "wof:placetype":"venue"
},
  "geometry": {"coordinates":[151.18702697800001,-33.8163299561],"type":"Point"}
}