{
  "type": "Feature",
  "properties": {
    "addr:full":"Ballantyne Rd Waikerie SA 5330",
    "addr:postcode":"5330",
    "addr:street":"Ballantyne Rd",
    "iso:country":"AU",
    "sg:address":"Ballantyne Rd",
    "sg:city":"Waikerie",
    "sg:classifiers":[
        {
            "category":"Farming",
            "subcategory":"Berry Farm",
            "type":"Manufacturing & Wholesale Goods"
        }
    ],
    "sg:phone":"+61 8 8541 2220",
    "sg:postcode":"5330",
    "sg:province":"SA",
    "sg:tags":[
        "fruit",
        "grower"
    ],
    "wof:name":"Sperling J M & J",
    "wof:placetype":"venue"
},
  "geometry": {"coordinates":[139.951934814,-34.1994361877],"type":"Point"}
}