{
  "type": "Feature",
  "properties": {
    "addr:full":"PO Box 125 Haberfield NSW 2045",
    "addr:postcode":"2045",
    "iso:country":"AU",
    "sg:address":"PO Box 125",
    "sg:city":"Haberfield",
    "sg:classifiers":[
        {
            "category":"Banks & Credit Unions",
            "subcategory":"Financial Services",
            "type":"Services"
        }
    ],
    "sg:phone":"+61 2 9797 7468",
    "sg:postcode":"2045",
    "sg:province":"NSW",
    "sg:tags":[
        "planning"
    ],
    "wof:name":"Finesse School of Financial Awareness",
    "wof:placetype":"venue"
},
  "geometry": {"coordinates":[151.13926699999999,-33.881031],"type":"Point"}
}