{
  "type": "Feature",
  "properties": {
    "iso:country":"AU",
    "sg:address":"U1/ 23 Veronica St",
    "sg:city":"Capalaba",
    "sg:classifiers":[
        {
            "category":"Wholesale",
            "subcategory":"Electrical",
            "type":"Manufacturing & Wholesale Goods"
        }
    ],
    "sg:phone":"+61 7 3245 2210",
    "sg:postcode":"4157",
    "sg:province":"QLD",
    "sg:tags":[
        "wholesaler"
    ],
    "wof:name":"CRS Electric",
    "wof:placetype":"venue"
},
  "geometry": {"coordinates":[153.19810485799999,-27.5267906189],"type":"Point"}
}