{
  "type": "Feature",
  "properties": {
    "addr:full":"71 Hamilton St Eglinton NSW 2795",
    "addr:housenumber":"71",
    "addr:postcode":"2795",
    "addr:street":"Hamilton St",
    "iso:country":"AU",
    "sg:address":"71 Hamilton St",
    "sg:city":"Eglinton",
    "sg:classifiers":[
        {
            "category":"Personal",
            "subcategory":"Massage",
            "type":"Services"
        }
    ],
    "sg:phone":"+61 2 6337 1757",
    "sg:postcode":"2795",
    "sg:province":"NSW",
    "sg:tags":[
        "therapy"
    ],
    "wof:name":"Nelson Barry",
    "wof:placetype":"venue"
},
  "geometry": {"coordinates":[149.54722595199999,-33.3737182617],"type":"Point"}
}