{
  "type": "Feature",
  "properties": {
    "iso:country":"AU",
    "sg:address":"Mandurama Rd",
    "sg:city":"Woodstock",
    "sg:classifiers":[
        {
            "category":"Building & Trades",
            "subcategory":"Landscaping Services",
            "type":"Services"
        }
    ],
    "sg:phone":"+61 2 6345 0465",
    "sg:postcode":"2793",
    "sg:province":"NSW",
    "sg:tags":[
        "grazier"
    ],
    "wof:name":"Corrie Vale Pastoral Co Pty Ltd",
    "wof:placetype":"venue"
},
  "geometry": {"coordinates":[148.84800720199999,-33.7448692322],"type":"Point"}
}