{
  "type": "Feature",
  "properties": {
    "addr:full":"Hincks Ave Whyalla Norrie SA 5608",
    "addr:postcode":"5608",
    "addr:street":"Hincks Ave",
    "iso:country":"AU",
    "sg:address":"Hincks Ave",
    "sg:city":"Whyalla Norrie",
    "sg:classifiers":[
        {
            "category":"Education",
            "subcategory":"Kindergarten",
            "type":"Public Place"
        }
    ],
    "sg:phone":"+61 8 8645 5240",
    "sg:postcode":"5608",
    "sg:province":"SA",
    "sg:tags":[
        "pre-schools"
    ],
    "wof:name":"Hincks Avenue Childrens Centre",
    "wof:placetype":"venue"
},
  "geometry": {"coordinates":[137.54817199999999,-33.015488],"type":"Point"}
}