{
  "type": "Feature",
  "properties": {
    "iso:country":"AU",
    "sg:address":"Ste 1, 103- 107 Yarra St",
    "sg:city":"Geelong",
    "sg:classifiers":[
        {
            "category":"Banks & Credit Unions",
            "subcategory":"Financial Services",
            "type":"Services"
        }
    ],
    "sg:phone":"+61 3 5222 7222",
    "sg:postcode":"3220",
    "sg:province":"VIC",
    "sg:tags":[
        "loan",
        "finance",
        "mortgage"
    ],
    "wof:name":"Wizard",
    "wof:placetype":"venue"
},
  "geometry": {"coordinates":[144.36204499999999,-38.151009],"type":"Point"}
}