{
  "type": "Feature",
  "properties": {
    "addr:full":"356 Blackshaws Rd Altona North VIC 3025",
    "addr:housenumber":"356",
    "addr:postcode":"3025",
    "addr:street":"Blackshaws Rd",
    "iso:country":"AU",
    "sg:address":"356 Blackshaws Rd",
    "sg:city":"Altona North",
    "sg:classifiers":[
        {
            "category":"Health Services",
            "subcategory":"Health Practitioner",
            "type":"Services"
        }
    ],
    "sg:phone":"+61 3 9399 1554",
    "sg:postcode":"3025",
    "sg:province":"VIC",
    "sg:tags":[
        "physiotherapist"
    ],
    "wof:name":"Brewer Matthew",
    "wof:placetype":"venue"
},
  "geometry": {"coordinates":[144.849808,-37.831238],"type":"Point"}
}