{
  "type": "Feature",
  "properties": {
    "addr:full":"6 Fort St Petersham NSW 2049",
    "addr:housenumber":"6",
    "addr:postcode":"2049",
    "addr:street":"Fort St",
    "iso:country":"AU",
    "sg:address":"6 Fort St",
    "sg:city":"Petersham",
    "sg:classifiers":[
        {
            "category":"Real Estate",
            "subcategory":"Architect",
            "type":"Services"
        }
    ],
    "sg:phone":"+61 2 9560 5618",
    "sg:postcode":"2049",
    "sg:province":"NSW",
    "wof:name":"Stuart Richard",
    "wof:placetype":"venue"
},
  "geometry": {"coordinates":[151.15801999999999,-33.889805],"type":"Point"}
}