{
  "type": "Feature",
  "properties": {
    "addr:full":"Shop 1062, Westfield Shopping Centre, Kotara Rd Kotara NSW 2289",
    "addr:housenumber":"1062",
    "addr:postcode":"2289",
    "addr:street":"Westfield Shopping;Kotara Rd",
    "iso:country":"AU",
    "sg:address":"Shop 1062, Westfield Shopping Centre, Kotara Rd",
    "sg:city":"Kotara",
    "sg:classifiers":[
        {
            "category":"Shopping",
            "subcategory":"Mobile Phones",
            "type":"Retail Goods"
        }
    ],
    "sg:phone":"+61 2 4957 1111",
    "sg:postcode":"2289",
    "sg:province":"NSW",
    "sg:tags":[
        "telephone",
        "accessory"
    ],
    "wof:name":"Vodafone",
    "wof:placetype":"venue"
},
  "geometry": {"coordinates":[151.699386597,-32.9403076172],"type":"Point"}
}