{
  "type": "Feature",
  "properties": {
    "iso:country":"AU",
    "sg:address":"6 Trott Pl",
    "sg:city":"Keilor East",
    "sg:classifiers":[
        {
            "category":"Travel",
            "subcategory":"Hostel",
            "type":"Entertainment"
        }
    ],
    "sg:phone":"+61 3 9331 5366",
    "sg:postcode":"3033",
    "sg:province":"VIC",
    "sg:tags":[
        "home"
    ],
    "wof:name":"Mekong Senior Citizens Hostel",
    "wof:placetype":"venue"
},
  "geometry": {"coordinates":[144.857224,-37.736195],"type":"Point"}
}