{
  "type": "Feature",
  "properties": {
    "iso:country":"AU",
    "sg:address":"2 Yarran St",
    "sg:city":"Leeton",
    "sg:classifiers":[
        {
            "category":"Retail",
            "subcategory":"Repair Shop",
            "type":"Services"
        }
    ],
    "sg:phone":"+61 412 533 056",
    "sg:postcode":"2705",
    "sg:province":"NSW",
    "sg:tags":[
        "leadlights"
    ],
    "wof:name":"Leetoria Leadlighting",
    "wof:placetype":"venue"
},
  "geometry": {"coordinates":[146.40240478499999,-34.550655365],"type":"Point"}
}