{
  "type": "Feature",
  "properties": {
    "addr:full":"48 Brighton St Bundeena NSW 2230",
    "addr:housenumber":"48",
    "addr:postcode":"2230",
    "addr:street":"Brighton St",
    "iso:country":"AU",
    "sg:address":"48 Brighton St",
    "sg:city":"Bundeena",
    "sg:classifiers":[
        {
            "category":"Cafe",
            "type":"Food & Drink"
        }
    ],
    "sg:phone":"+61 2 9527 6555",
    "sg:postcode":"2230",
    "sg:province":"NSW",
    "wof:name":"Bundeena Greengrocer & Passionfruit Cafe",
    "wof:placetype":"venue"
},
  "geometry": {"coordinates":[151.15127563499999,-34.085735321],"type":"Point"}
}