{
  "type": "Feature",
  "properties": {
    "addr:full":"14 Pike St Rydalmere NSW 2116",
    "addr:housenumber":"14",
    "addr:postcode":"2116",
    "addr:street":"Pike St",
    "iso:country":"AU",
    "sg:address":"14 Pike St",
    "sg:city":"Rydalmere",
    "sg:classifiers":[
        {
            "category":"Professional",
            "subcategory":"Printing & Photocopies",
            "type":"Services"
        }
    ],
    "sg:phone":"+61 2 9898 0500",
    "sg:postcode":"2116",
    "sg:province":"NSW",
    "sg:tags":[
        "screen",
        "printer"
    ],
    "wof:name":"Allprint Graphics Pty Ltd",
    "wof:placetype":"venue"
},
  "geometry": {"coordinates":[151.03697204599999,-33.8160552979],"type":"Point"}
}