{
  "type": "Feature",
  "properties": {
    "addr:full":"PO Box 1584 Noosaville DC QLD 4566",
    "addr:postcode":"4566",
    "iso:country":"AU",
    "sg:address":"PO Box 1584",
    "sg:city":"Noosaville DC",
    "sg:classifiers":[
        {
            "category":"Building & Trades",
            "subcategory":"Construction",
            "type":"Services"
        }
    ],
    "sg:phone":"+61 7 5471 1684",
    "sg:postcode":"4566",
    "sg:province":"QLD",
    "sg:tags":[
        "earth",
        "excavating",
        "moving",
        "contractor"
    ],
    "wof:name":"RHA Queensland",
    "wof:placetype":"venue"
},
  "geometry": {"coordinates":[153.05848693900001,-26.4247493744],"type":"Point"}
}