{
  "type": "Feature",
  "properties": {
    "addr:full":"Cnr Elizabeth Drv & Woodlands Rd Liverpool NSW 2170",
    "addr:postcode":"2170",
    "addr:street":"Cnr Elizabeth Drv & Woodlands Rd",
    "iso:country":"AU",
    "sg:address":"Cnr Elizabeth Drv & Woodlands Rd",
    "sg:city":"Liverpool",
    "sg:classifiers":[
        {
            "category":"Health Services",
            "subcategory":"Doctor",
            "type":"Services"
        }
    ],
    "sg:phone":"+61 2 8724 6300",
    "sg:postcode":"2170",
    "sg:province":"NSW",
    "sg:tags":[
        "medical",
        "practitioner"
    ],
    "wof:name":"Sundrasingham V H L & Linkins R H",
    "wof:placetype":"venue"
},
  "geometry": {"coordinates":[150.91453552199999,-33.9148254395],"type":"Point"}
}