{
  "type": "Feature",
  "properties": {
    "addr:full":"52 Henley St Coopers Plains QLD 4108",
    "addr:housenumber":"52",
    "addr:postcode":"4108",
    "addr:street":"Henley St",
    "iso:country":"AU",
    "sg:address":"52 Henley St",
    "sg:city":"Coopers Plains",
    "sg:classifiers":[
        {
            "category":"Health Services",
            "subcategory":"Dentist",
            "type":"Services"
        }
    ],
    "sg:phone":"+61 7 3345 1099",
    "sg:postcode":"4108",
    "sg:province":"QLD",
    "wof:name":"Logan Mark J Dr",
    "wof:placetype":"venue"
},
  "geometry": {"coordinates":[153.036087036,-27.5689525604],"type":"Point"}
}