{
  "type": "Feature",
  "properties": {
    "iso:country":"AU",
    "sg:address":"52 Pine Ave",
    "sg:city":"Leeton",
    "sg:classifiers":[
        {
            "category":"Insurance",
            "subcategory":"Insurance Agent",
            "type":"Services"
        }
    ],
    "sg:phone":"+61 2 6953 6002",
    "sg:postcode":"2705",
    "sg:province":"NSW",
    "wof:name":"Brown Don",
    "wof:placetype":"venue"
},
  "geometry": {"coordinates":[146.404953003,-34.5515174866],"type":"Point"}
}