{
  "type": "Feature",
  "properties": {
    "addr:full":"72-74 Anne St Campbelltown SA 5074",
    "addr:housenumber":"72-74",
    "addr:postcode":"5074",
    "addr:street":"Anne St",
    "iso:country":"AU",
    "sg:address":"72-74 Anne St",
    "sg:city":"Campbelltown",
    "sg:classifiers":[
        {
            "category":"Building & Trades",
            "subcategory":"Construction",
            "type":"Services"
        }
    ],
    "sg:phone":"+61 8 8365 1464",
    "sg:postcode":"5074",
    "sg:province":"SA",
    "sg:tags":[
        "ceiling"
    ],
    "wof:name":"Panella E",
    "wof:placetype":"venue"
},
  "geometry": {"coordinates":[138.65257263199999,-34.8737182617],"type":"Point"}
}