{
  "type": "Feature",
  "properties": {
    "iso:country":"AU",
    "sg:address":"2-3 / 5 Narabang Wy",
    "sg:city":"Belrose",
    "sg:classifiers":[
        {
            "category":"Professional",
            "subcategory":"Art Services",
            "type":"Services"
        }
    ],
    "sg:phone":"+61 2 9450 2070",
    "sg:postcode":"2085",
    "sg:province":"NSW",
    "sg:tags":[
        "interior",
        "designer"
    ],
    "wof:name":"Micheal Fountain Architects Pty Ltd",
    "wof:placetype":"venue"
},
  "geometry": {"coordinates":[151.21234130900001,-33.7051696777],"type":"Point"}
}