{
  "type": "Feature",
  "properties": {
    "iso:country":"AU",
    "sg:address":"Rosamond Rd",
    "sg:city":"Maribyrnong",
    "sg:classifiers":[
        {
            "category":"Shopping",
            "subcategory":"Department Store",
            "type":"Retail Goods"
        }
    ],
    "sg:phone":"+61 3 9319 7100",
    "sg:postcode":"3032",
    "sg:province":"VIC",
    "wof:name":"Myer Highpoint",
    "wof:placetype":"venue"
},
  "geometry": {"coordinates":[144.886322,-37.771435],"type":"Point"}
}