{
  "type": "Feature",
  "properties": {
    "addr:full":"276 Illawarra Rd Marrickville NSW 2204",
    "addr:housenumber":"276",
    "addr:postcode":"2204",
    "addr:street":"Illawarra Rd",
    "iso:country":"AU",
    "sg:address":"276 Illawarra Rd",
    "sg:city":"Marrickville",
    "sg:classifiers":[
        {
            "category":"Food & Beverages",
            "subcategory":"Meat & Fish",
            "type":"Retail Goods"
        }
    ],
    "sg:phone":"+61 2 9558 0297",
    "sg:postcode":"2204",
    "sg:province":"NSW",
    "sg:tags":[
        "seafood"
    ],
    "wof:name":"Phuoc Hai Seafood",
    "wof:placetype":"venue"
},
  "geometry": {"coordinates":[151.15505999999999,-33.911667],"type":"Point"}
}