{
  "type": "Feature",
  "properties": {
    "addr:full":"31 Burke St Coorparoo QLD 4151",
    "addr:housenumber":"31",
    "addr:postcode":"4151",
    "addr:street":"Burke St",
    "iso:country":"AU",
    "sg:address":"31 Burke St",
    "sg:city":"Coorparoo",
    "sg:classifiers":[
        {
            "category":"Professional",
            "subcategory":"Art Services",
            "type":"Services"
        }
    ],
    "sg:phone":"+61 7 3394 3337",
    "sg:postcode":"4151",
    "sg:province":"QLD",
    "sg:tags":[
        "picture",
        "frame",
        "framing"
    ],
    "wof:name":"Vance Carlilie Picture Framing",
    "wof:placetype":"venue"
},
  "geometry": {"coordinates":[153.06283569300001,-27.4909095764],"type":"Point"}
}