{
  "type": "Feature",
  "properties": {
    "iso:country":"AU",
    "sg:address":"5 Allan St",
    "sg:city":"Gatton",
    "sg:classifiers":[
        {
            "category":"Building & Trades",
            "subcategory":"Cleaning & Sanitation",
            "type":"Services"
        }
    ],
    "sg:phone":"+61 413 662 253",
    "sg:postcode":"4343",
    "sg:province":"QLD",
    "sg:tags":[
        "industrial",
        "commercial",
        "contractor"
    ],
    "wof:name":"Terrys Home Maintenance",
    "wof:placetype":"venue"
},
  "geometry": {"coordinates":[152.281326294,-27.5550727844],"type":"Point"}
}