{
  "type": "Feature",
  "properties": {
    "iso:country":"AU",
    "sg:address":"12 Kenworth Pl",
    "sg:city":"Brendale",
    "sg:classifiers":[
        {
            "category":"Shopping",
            "subcategory":"Mobile Phones",
            "type":"Retail Goods"
        }
    ],
    "sg:phone":"+61 7 3881 3618",
    "sg:postcode":"4500",
    "sg:province":"QLD",
    "sg:tags":[
        "wholesaler",
        "mfrs",
        "electrical",
        "switchboard"
    ],
    "wof:name":"Epac",
    "wof:placetype":"venue"
},
  "geometry": {"coordinates":[152.988449097,-27.3249740601],"type":"Point"}
}