{
  "type": "Feature",
  "properties": {
    "addr:full":"53 Clarendon St Maryborough VIC 3465",
    "addr:housenumber":"53",
    "addr:postcode":"3465",
    "addr:street":"Clarendon St",
    "iso:country":"AU",
    "sg:address":"53 Clarendon St",
    "sg:city":"Maryborough",
    "sg:classifiers":[
        {
            "category":"Health Services",
            "subcategory":"Dentist",
            "type":"Services"
        }
    ],
    "sg:phone":"+61 3 5461 1155",
    "sg:postcode":"3465",
    "sg:province":"VIC",
    "wof:name":"Clarendon Street Dental Practice",
    "wof:placetype":"venue"
},
  "geometry": {"coordinates":[143.73529052699999,-37.0474700928],"type":"Point"}
}