{
  "type": "Feature",
  "properties": {
    "iso:country":"AU",
    "sg:address":"400 Shute Harbour Rd",
    "sg:city":"Airlie Beach",
    "sg:classifiers":[
        {
            "category":"Real Estate",
            "subcategory":"Real Estate Agent",
            "type":"Services"
        }
    ],
    "sg:phone":"+61 7 4948 7888",
    "sg:postcode":"4802",
    "sg:province":"QLD",
    "wof:name":"CPQ Real Estate",
    "wof:placetype":"venue"
},
  "geometry": {"coordinates":[148.720626831,-20.2697525024],"type":"Point"}
}