{
  "type": "Feature",
  "properties": {
    "addr:full":"PO Box 113 Galston NSW 2159",
    "addr:postcode":"2159",
    "iso:country":"AU",
    "sg:address":"PO Box 113",
    "sg:city":"Galston",
    "sg:classifiers":[
        {
            "category":"Health Services",
            "subcategory":"Health Practitioner",
            "type":"Services"
        }
    ],
    "sg:phone":"+61 2 9653 3600",
    "sg:postcode":"2159",
    "sg:province":"NSW",
    "sg:tags":[
        "alternative"
    ],
    "wof:name":"Aromatherapy in the Raw",
    "wof:placetype":"venue"
},
  "geometry": {"coordinates":[151.045013428,-33.6529197693],"type":"Point"}
}