{
  "type": "Feature",
  "properties": {
    "addr:full":"12 Main St Upwey VIC 3158",
    "addr:housenumber":"12",
    "addr:postcode":"3158",
    "addr:street":"Main St",
    "iso:country":"AU",
    "sg:address":"12 Main St",
    "sg:city":"Upwey",
    "sg:classifiers":[
        {
            "category":"Cafe",
            "type":"Food & Drink"
        }
    ],
    "sg:phone":"+61 3 9754 4690",
    "sg:postcode":"3158",
    "sg:province":"VIC",
    "wof:name":"Cafe Have Ya Bean",
    "wof:placetype":"venue"
},
  "geometry": {"coordinates":[145.32977294899999,-37.902973175],"type":"Point"}
}