{
  "type": "Feature",
  "properties": {
    "addr:full":"24 Braddon St St Marys NSW 2760",
    "addr:housenumber":"24",
    "addr:postcode":"2760",
    "addr:street":"Braddon St",
    "iso:country":"AU",
    "sg:address":"24 Braddon St",
    "sg:city":"St Marys",
    "sg:classifiers":[
        {
            "category":"Building & Trades",
            "subcategory":"Construction",
            "type":"Services"
        }
    ],
    "sg:phone":"+61 2 9623 2601",
    "sg:postcode":"2760",
    "sg:province":"NSW",
    "sg:tags":[
        "concrete",
        "contractor"
    ],
    "wof:name":"Cignarella V & R Pty Ltd",
    "wof:placetype":"venue"
},
  "geometry": {"coordinates":[150.791015625,-33.766620636],"type":"Point"}
}