{
  "type": "Feature",
  "properties": {
    "iso:country":"AU",
    "sg:address":"176 Hartley Valley Rd",
    "sg:city":"Lithgow",
    "sg:classifiers":[
        {
            "category":"Building & Trades",
            "subcategory":"Cleaning & Sanitation",
            "type":"Services"
        }
    ],
    "sg:phone":"+61 2 6353 1248",
    "sg:postcode":"2790",
    "sg:province":"NSW",
    "sg:tags":[
        "grease",
        "trap"
    ],
    "wof:name":"Sita Environmental Solutions",
    "wof:placetype":"venue"
},
  "geometry": {"coordinates":[150.174880981,-33.4792518616],"type":"Point"}
}