{
  "type": "Feature",
  "properties": {
    "iso:country":"AU",
    "sg:address":"30b Percy St",
    "sg:city":"Devonport",
    "sg:classifiers":[
        {
            "category":"Personal",
            "subcategory":"Beauty Salon",
            "type":"Services"
        }
    ],
    "sg:phone":"+61 3 6423 2200",
    "sg:postcode":"7310",
    "sg:province":"TAS",
    "wof:name":"Karizma Hair Design",
    "wof:placetype":"venue"
},
  "geometry": {"coordinates":[146.34254455600001,-41.1762695312],"type":"Point"}
}