{
  "type": "Feature",
  "properties": {
    "addr:full":"Unit 2, 17 Pearson Way Osborne Park WA 6017",
    "addr:housenumber":"17",
    "addr:postcode":"6017",
    "addr:street":"Pearson Way",
    "iso:country":"AU",
    "sg:address":"Unit 2, 17",
    "sg:city":"Pearson Way Osborne Park",
    "sg:classifiers":[
        {
            "category":"Home & Garden",
            "subcategory":"Carpets & Floor Coverings",
            "type":"Retail Goods"
        }
    ],
    "sg:phone":"+61 8 9204 3888",
    "sg:postcode":"6017",
    "sg:province":"WA",
    "sg:tags":[
        "flooring",
        "parquet"
    ],
    "wof:name":"Java Accents",
    "wof:placetype":"venue"
},
  "geometry": {"coordinates":[115.802131653,-31.9081611633],"type":"Point"}
}