{
  "type": "Feature",
  "properties": {
    "addr:full":"Shop 2 Dalton Centre, 1 Newspaper Place Maroochydore QLD 4558",
    "addr:housenumber":"shop 2;1",
    "addr:postcode":"4558",
    "addr:street":"Dalton Centre;Newspaper Place",
    "iso:country":"AU",
    "sg:address":"Shop 2 Dalton Centre, 1",
    "sg:city":"Newspaper Place Maroochydore",
    "sg:classifiers":[
        {
            "category":"Professional",
            "type":"Services"
        }
    ],
    "sg:phone":"+61 7 5452 7911",
    "sg:postcode":"4558",
    "sg:province":"QLD",
    "sg:tags":[
        "courier"
    ],
    "wof:name":"Pack & Send",
    "wof:placetype":"venue"
},
  "geometry": {"coordinates":[153.09136962900001,-26.6669864655],"type":"Point"}
}