{
  "type": "Feature",
  "properties": {
    "iso:country":"AU",
    "sg:address":"16 Hatch Crt",
    "sg:city":"Forrestdale",
    "sg:classifiers":[
        {
            "category":"Building & Trades",
            "subcategory":"Construction",
            "type":"Services"
        }
    ],
    "sg:phone":"+61 407 767 855",
    "sg:postcode":"6112",
    "sg:province":"WA",
    "sg:tags":[
        "earth",
        "excavating",
        "moving",
        "contractor"
    ],
    "wof:name":"W & J Bobcat Services & Truck Hire",
    "wof:placetype":"venue"
},
  "geometry": {"coordinates":[115.93946838399999,-32.1117897034],"type":"Point"}
}