{
  "type": "Feature",
  "properties": {
    "iso:country":"AU",
    "sg:address":"37- 39 George St",
    "sg:city":"Launceston",
    "sg:classifiers":[
        {
            "category":"Banks & Credit Unions",
            "subcategory":"Financial Services",
            "type":"Services"
        }
    ],
    "sg:phone":"+61 3 6334 1477",
    "sg:postcode":"7250",
    "sg:province":"TAS",
    "sg:tags":[
        "loan",
        "finance",
        "mortgage"
    ],
    "wof:name":"BFA Finance Pty Ltd",
    "wof:placetype":"venue"
},
  "geometry": {"coordinates":[147.13958740199999,-41.4349327087],"type":"Point"}
}