{
  "type": "Feature",
  "properties": {
    "addr:full":"136A Haines Rd Banksia Park SA 5091",
    "addr:housenumber":"136a",
    "addr:postcode":"5091",
    "addr:street":"Haines Rd",
    "iso:country":"AU",
    "sg:address":"136A Haines Rd",
    "sg:city":"Banksia Park",
    "sg:classifiers":[
        {
            "category":"Home & Garden",
            "subcategory":"Building Materials",
            "type":"Retail Goods"
        }
    ],
    "sg:phone":"+61 8 8251 2413",
    "sg:postcode":"5091",
    "sg:province":"SA",
    "sg:tags":[
        "lawn",
        "cutting",
        "maintenance"
    ],
    "wof:name":"Andrews R & R",
    "wof:placetype":"venue"
},
  "geometry": {"coordinates":[138.73020935100001,-34.8062896729],"type":"Point"}
}