{
  "type": "Feature",
  "properties": {
    "addr:full":"12 Marsden St Camperdown NSW 2050",
    "addr:housenumber":"12",
    "addr:postcode":"2050",
    "addr:street":"Marsden St",
    "iso:country":"AU",
    "sg:address":"12 Marsden St",
    "sg:city":"Camperdown",
    "sg:classifiers":[
        {
            "category":"Wholesale",
            "subcategory":"Apparel",
            "type":"Manufacturing & Wholesale Goods"
        }
    ],
    "sg:phone":"+61 2 9519 5600",
    "sg:postcode":"2050",
    "sg:province":"NSW",
    "sg:tags":[
        "wholesaler",
        "mfrs",
        "sportswear",
        "women's"
    ],
    "wof:name":"La Donna Fashions Pty Ltd",
    "wof:placetype":"venue"
},
  "geometry": {"coordinates":[151.17950400000001,-33.887058],"type":"Point"}
}