{
  "type": "Feature",
  "properties": {
    "addr:full":"7/ 201 Main South Rd Morphett Vale SA 5162",
    "addr:housenumber":"/ 201",
    "addr:postcode":"5162",
    "addr:street":"Main South Rd",
    "iso:country":"AU",
    "sg:address":"7/ 201 Main South Rd",
    "sg:city":"Morphett Vale",
    "sg:classifiers":[
        {
            "category":"Fast Food",
            "type":"Food & Drink"
        }
    ],
    "sg:phone":"+61 8 8186 6077",
    "sg:postcode":"5162",
    "sg:province":"SA",
    "sg:tags":[
        "away",
        "take"
    ],
    "wof:name":"K.W. Coffee & Snax",
    "wof:placetype":"venue"
},
  "geometry": {"coordinates":[138.522827148,-35.1193656921],"type":"Point"}
}