{
  "type": "Feature",
  "properties": {
    "addr:full":"1 Baroota Ave Rostrevor SA 5073",
    "addr:housenumber":"1",
    "addr:postcode":"5073",
    "addr:street":"Baroota Ave",
    "iso:country":"AU",
    "sg:address":"1 Baroota Ave",
    "sg:city":"Rostrevor",
    "sg:classifiers":[
        {
            "category":"Education",
            "subcategory":"Special Training",
            "type":"Public Place"
        }
    ],
    "sg:phone":"+61 8 8337 2894",
    "sg:postcode":"5073",
    "sg:province":"SA",
    "sg:tags":[
        "tuition-educational"
    ],
    "wof:name":"Anthony's Quality Tuition",
    "wof:placetype":"venue"
},
  "geometry": {"coordinates":[138.6925354,-34.8940162659],"type":"Point"}
}