{
  "type": "Feature",
  "properties": {
    "addr:full":"438 Beach Rd Batemans Bay NSW 2536",
    "addr:housenumber":"438",
    "addr:postcode":"2536",
    "addr:street":"Beach Rd",
    "iso:country":"AU",
    "sg:address":"438 Beach Rd",
    "sg:city":"Batemans Bay",
    "sg:classifiers":[
        {
            "category":"Recreation",
            "subcategory":"Fishing",
            "type":"Entertainment"
        }
    ],
    "sg:phone":"+61 2 4472 4258",
    "sg:postcode":"2536",
    "sg:province":"NSW",
    "sg:tags":[
        "trip"
    ],
    "wof:name":"Batemans Bay Fishing",
    "wof:placetype":"venue"
},
  "geometry": {"coordinates":[150.20265197800001,-35.7324943542],"type":"Point"}
}