{
  "type": "Feature",
  "properties": {
    "iso:country":"AU",
    "sg:address":"24 Sunset Ave",
    "sg:city":"Barrack Heights",
    "sg:classifiers":[
        {
            "category":"Shopping",
            "subcategory":"Computers & Home Electronics",
            "type":"Retail Goods"
        }
    ],
    "sg:phone":"+61 2 4297 2476",
    "sg:postcode":"2528",
    "sg:province":"NSW",
    "sg:tags":[
        "global",
        "positioning",
        "system"
    ],
    "wof:name":"T-Track Australia",
    "wof:placetype":"venue"
},
  "geometry": {"coordinates":[150.85650634800001,-34.5596504211],"type":"Point"}
}