{
  "type": "Feature",
  "properties": {
    "addr:full":"113 Denham St Rockhampton QLD 4700",
    "addr:housenumber":"113",
    "addr:postcode":"4700",
    "addr:street":"Denham St",
    "iso:country":"AU",
    "sg:address":"113 Denham St",
    "sg:city":"Rockhampton",
    "sg:classifiers":[
        {
            "category":"Education",
            "subcategory":"Junior College",
            "type":"Public Place"
        }
    ],
    "sg:phone":"+61 7 4927 9322",
    "sg:postcode":"4700",
    "sg:province":"QLD",
    "sg:tags":[
        "wholesaler",
        "school",
        "mfrs",
        "uniform"
    ],
    "wof:name":"Ys School Uniforms",
    "wof:placetype":"venue"
},
  "geometry": {"coordinates":[150.49847412099999,-23.3877162933],"type":"Point"}
}