{
  "type": "Feature",
  "properties": {
    "addr:full":"Shop 6 Aspley Hypermarket Albany Creek Rd Aspley QLD 4034",
    "addr:housenumber":"shop 6",
    "addr:postcode":"4034",
    "addr:street":"Albany Creek Rd",
    "iso:country":"AU",
    "sg:address":"Shop 6 Aspley Hypermarket Albany Creek Rd",
    "sg:city":"Aspley",
    "sg:classifiers":[
        {
            "category":"Health Services",
            "subcategory":"Optometrist",
            "type":"Services"
        }
    ],
    "sg:phone":"+61 7 3263 9699",
    "sg:postcode":"4034",
    "sg:province":"QLD",
    "wof:name":"Kamaile Shirley",
    "wof:placetype":"venue"
},
  "geometry": {"coordinates":[153.01719700000001,-27.365219],"type":"Point"}
}