{
  "type": "Feature",
  "properties": {
    "iso:country":"AU",
    "sg:address":"597 Malvern Rd",
    "sg:city":"Toorak",
    "sg:classifiers":[
        {
            "category":"Shopping",
            "subcategory":"Antiques",
            "type":"Retail Goods"
        }
    ],
    "sg:phone":"+61 3 9804 8599",
    "sg:postcode":"3142",
    "sg:province":"VIC",
    "sg:tags":[
        "restoration",
        "reproduction"
    ],
    "wof:name":"Brown Robert",
    "wof:placetype":"venue"
},
  "geometry": {"coordinates":[145.006057739,-37.8483123779],"type":"Point"}
}