{
  "type": "Feature",
  "properties": {
    "iso:country":"AU",
    "sg:address":"Unit 2/ 6 Muir Pl",
    "sg:city":"Wetherill Park",
    "sg:classifiers":[
        {
            "category":"Building & Trades",
            "subcategory":"Construction",
            "type":"Services"
        }
    ],
    "sg:phone":"+61 2 9609 6542",
    "sg:postcode":"2164",
    "sg:province":"NSW",
    "sg:tags":[
        "joinery"
    ],
    "wof:name":"Mirage Kitchens Pty Ltd",
    "wof:placetype":"venue"
},
  "geometry": {"coordinates":[150.90284729000001,-33.8362312317],"type":"Point"}
}