{
  "type": "Feature",
  "properties": {
    "addr:full":"PO Box 977 Glen Waverley VIC 3150",
    "addr:postcode":"3150",
    "iso:country":"AU",
    "sg:address":"PO Box 977",
    "sg:city":"Glen Waverley",
    "sg:classifiers":[
        {
            "category":"Education",
            "subcategory":"Music School",
            "type":"Public Place"
        }
    ],
    "sg:phone":"+61 3 9802 2981",
    "sg:postcode":"3150",
    "sg:province":"VIC",
    "sg:tags":[
        "choir",
        "bands",
        "orchestra"
    ],
    "wof:name":"Maroondah Singers",
    "wof:placetype":"venue"
},
  "geometry": {"coordinates":[145.176269531,-37.8902015686],"type":"Point"}
}