{
  "type": "Feature",
  "properties": {
    "iso:country":"AU",
    "sg:address":"Shop 3 Lighthouse Beach Shopping Centre",
    "sg:city":"Port Macquarie",
    "sg:classifiers":[
        {
            "category":"Food & Beverages",
            "subcategory":"Liquor & Beverages",
            "type":"Retail Goods"
        }
    ],
    "sg:phone":"+61 2 6582 0658",
    "sg:postcode":"2444",
    "sg:province":"NSW",
    "sg:tags":[
        "store"
    ],
    "wof:name":"Celebrations at Lighthouse Beach",
    "wof:placetype":"venue"
},
  "geometry": {"coordinates":[152.93551600000001,-31.472239],"type":"Point"}
}