{
  "type": "Feature",
  "properties": {
    "iso:country":"AU",
    "sg:address":"134 Polding St",
    "sg:city":"Fairfield",
    "sg:classifiers":[
        {
            "category":"Social Services",
            "subcategory":"Child Care",
            "type":"Services"
        }
    ],
    "sg:phone":"+61 2 9728 1009",
    "sg:postcode":"2165",
    "sg:province":"NSW",
    "wof:name":"Kids World Kindy Long Day Care Centre",
    "wof:placetype":"venue"
},
  "geometry": {"coordinates":[150.94024658199999,-33.8619804382],"type":"Point"}
}