{
  "type": "Feature",
  "properties": {
    "addr:full":"Shop 0 280 Flinders Mall Townsville QLD 4810",
    "addr:housenumber":"shop 0 280",
    "addr:postcode":"4810",
    "addr:street":"Flinders Mall",
    "iso:country":"AU",
    "sg:address":"Shop 0 280",
    "sg:city":"Flinders Mall Townsville",
    "sg:classifiers":[
        {
            "category":"Shopping",
            "subcategory":"Mobile Phones",
            "type":"Retail Goods"
        }
    ],
    "sg:phone":"+61 7 4772 3316",
    "sg:postcode":"4810",
    "sg:province":"QLD",
    "sg:tags":[
        "telephone",
        "accessory"
    ],
    "wof:name":"Optus",
    "wof:placetype":"venue"
},
  "geometry": {"coordinates":[146.81788599999999,-19.258825],"type":"Point"}
}