{
  "type": "Feature",
  "properties": {
    "addr:full":"Opera Quays Shop 9 2 East Circular Quay NSW 2000",
    "addr:housenumber":"9 2",
    "addr:postcode":"2000",
    "addr:street":"East Circular Quay",
    "iso:country":"AU",
    "sg:address":"Opera Quays Shop 9 2 East",
    "sg:city":"Circular Quay",
    "sg:classifiers":[
        {
            "category":"Cinema",
            "subcategory":"Movie Theater",
            "type":"Entertainment"
        }
    ],
    "sg:phone":"+61 2 9247 3800",
    "sg:postcode":"2000",
    "sg:province":"NSW",
    "wof:name":"Dendy Cinemas",
    "wof:placetype":"venue"
},
  "geometry": {"coordinates":[151.210693359,-33.8634605408],"type":"Point"}
}