{
  "type": "Feature",
  "properties": {
    "iso:country":"AU",
    "sg:address":"1 Oakes Pl",
    "sg:city":"North Bondi",
    "sg:classifiers":[
        {
            "category":"Wholesale",
            "subcategory":"Apparel",
            "type":"Manufacturing & Wholesale Goods"
        }
    ],
    "sg:phone":"+61 2 9130 2014",
    "sg:postcode":"2026",
    "sg:province":"NSW",
    "sg:tags":[
        "wholesaler",
        "mfrs",
        "dress"
    ],
    "wof:name":"Karina's Knitting Mills Pty Ltd",
    "wof:placetype":"venue"
},
  "geometry": {"coordinates":[151.280853272,-33.8819503784],"type":"Point"}
}