{
  "type": "Feature",
  "properties": {
    "addr:full":"16 Boronia St Klemzig SA 5087",
    "addr:housenumber":"16",
    "addr:postcode":"5087",
    "addr:street":"Boronia St",
    "iso:country":"AU",
    "sg:address":"16 Boronia St",
    "sg:city":"Klemzig",
    "sg:classifiers":[
        {
            "category":"Retail",
            "subcategory":"Auto Repair",
            "type":"Services"
        }
    ],
    "sg:phone":"+61 8 8369 3044",
    "sg:postcode":"5087",
    "sg:province":"SA",
    "sg:tags":[
        "repairer",
        "motor",
        "engineer"
    ],
    "wof:name":"Motorossi",
    "wof:placetype":"venue"
},
  "geometry": {"coordinates":[138.633270264,-34.8814811707],"type":"Point"}
}