{
  "type": "Feature",
  "properties": {
    "addr:full":"Factory 2 14 Elsum Ave Bayswater VIC 3153",
    "addr:housenumber":"14",
    "addr:postcode":"3153",
    "addr:street":"Elsum Ave",
    "iso:country":"AU",
    "sg:address":"Factory 2 14 Elsum Ave",
    "sg:city":"Bayswater",
    "sg:classifiers":[
        {
            "category":"Transit Center",
            "subcategory":"Passenger",
            "type":"Transportation"
        }
    ],
    "sg:phone":"+61 3 9729 7011",
    "sg:postcode":"3153",
    "sg:province":"VIC",
    "sg:tags":[
        "packing",
        "gasket"
    ],
    "wof:name":"Trade Gasket & Washer Co Pty Ltd",
    "wof:placetype":"venue"
},
  "geometry": {"coordinates":[145.28074645999999,-37.8232383728],"type":"Point"}
}