{
  "type": "Feature",
  "properties": {
    "iso:country":"AU",
    "sg:address":"11 Cross Keys Rd",
    "sg:city":"Salisbury",
    "sg:classifiers":[
        {
            "category":"Retail",
            "subcategory":"Auto Repair",
            "type":"Services"
        }
    ],
    "sg:phone":"+61 8 8281 3155",
    "sg:postcode":"5108",
    "sg:province":"SA",
    "sg:tags":[
        "repairer",
        "motor",
        "engineer"
    ],
    "wof:name":"Bowey Autogas Conversions",
    "wof:placetype":"venue"
},
  "geometry": {"coordinates":[138.65127563499999,-34.7689285278],"type":"Point"}
}