{
  "type": "Feature",
  "properties": {
    "addr:full":"U 3/ 7 Levanswell Rd Moorabbin VIC 3189",
    "addr:housenumber":"7",
    "addr:postcode":"3189",
    "addr:street":"Levanswell Rd",
    "iso:country":"AU",
    "sg:address":"U 3/ 7 Levanswell Rd",
    "sg:city":"Moorabbin",
    "sg:classifiers":[
        {
            "category":"Military Area",
            "subcategory":"Air Force Base",
            "type":"Public Place"
        }
    ],
    "sg:phone":"+61 3 9532 1937",
    "sg:postcode":"3189",
    "sg:province":"VIC",
    "sg:tags":[
        "wholesaler",
        "travel",
        "good",
        "mfrs"
    ],
    "wof:name":"Dyna Leather Goods",
    "wof:placetype":"venue"
},
  "geometry": {"coordinates":[145.06198120100001,-37.9441299438],"type":"Point"}
}