{
  "type": "Feature",
  "properties": {
    "addr:full":"Shp7/ 136 Bazaar St Maryborough QLD 4650",
    "addr:housenumber":"136",
    "addr:postcode":"4650",
    "addr:street":"Bazaar St",
    "iso:country":"AU",
    "sg:address":"Shp7/ 136 Bazaar St",
    "sg:city":"Maryborough",
    "sg:classifiers":[
        {
            "category":"Health Services",
            "subcategory":"Health Practitioner",
            "type":"Services"
        }
    ],
    "sg:phone":"+61 7 4123 6661",
    "sg:postcode":"4650",
    "sg:province":"QLD",
    "sg:tags":[
        "physiotherapist"
    ],
    "wof:name":"Physikal Health Services Pty Ltd",
    "wof:placetype":"venue"
},
  "geometry": {"coordinates":[152.703766,-25.538258],"type":"Point"}
}