{
  "type": "Feature",
  "properties": {
    "addr:full":"Shp1063/ 4 Westfield Shopping Town Oaklands Park SA 5046",
    "addr:housenumber":"4",
    "addr:postcode":"5046",
    "addr:street":"Westfield",
    "iso:country":"AU",
    "sg:address":"Shp1063/ 4 Westfield Shopping Town",
    "sg:city":"Oaklands Park",
    "sg:classifiers":[
        {
            "category":"Shopping",
            "subcategory":"Shoes",
            "type":"Retail Goods"
        }
    ],
    "sg:phone":"+61 8 8377 3677",
    "sg:postcode":"5046",
    "sg:province":"SA",
    "sg:tags":[
        "footwear"
    ],
    "wof:name":"Joanne Mercer Footwear",
    "wof:placetype":"venue"
},
  "geometry": {"coordinates":[138.54598999999999,-35.01244],"type":"Point"}
}