{
  "type": "Feature",
  "properties": {
    "iso:country":"AU",
    "sg:address":"21 Glen Ave",
    "sg:city":"Randwick",
    "sg:classifiers":[
        {
            "category":"Real Estate",
            "subcategory":"Real Estate Agent",
            "type":"Services"
        }
    ],
    "sg:phone":"+61 409 616 900",
    "sg:postcode":"2031",
    "sg:province":"NSW",
    "wof:name":"Personal Realty (Aust)",
    "wof:placetype":"venue"
},
  "geometry": {"coordinates":[151.24873352,-33.9125518799],"type":"Point"}
}