{
  "type": "Feature",
  "properties": {
    "addr:full":"10 Industrial Ave Notting Hill VIC 3168",
    "addr:housenumber":"10",
    "addr:postcode":"3168",
    "addr:street":"Industrial Ave",
    "iso:country":"AU",
    "sg:address":"10 Industrial Ave",
    "sg:city":"Notting Hill",
    "sg:classifiers":[
        {
            "category":"Professional",
            "subcategory":"Printing & Photocopies",
            "type":"Services"
        }
    ],
    "sg:phone":"+61 3 9593 6411",
    "sg:postcode":"3168",
    "sg:province":"VIC",
    "sg:tags":[
        "photocopier"
    ],
    "wof:name":"Rent-A-Fax",
    "wof:placetype":"venue"
},
  "geometry": {"coordinates":[145.13017273,-37.9042205811],"type":"Point"}
}