{
  "type": "Feature",
  "properties": {
    "addr:full":"60 Wyatt Rd Bayswater WA 6053",
    "addr:housenumber":"60",
    "addr:postcode":"6053",
    "addr:street":"Wyatt Rd",
    "iso:country":"AU",
    "sg:address":"60 Wyatt Rd",
    "sg:city":"Bayswater",
    "sg:classifiers":[
        {
            "category":"Professional",
            "subcategory":"Art Services",
            "type":"Services"
        }
    ],
    "sg:phone":"+61 8 9271 5090",
    "sg:postcode":"6053",
    "sg:province":"WA",
    "sg:tags":[
        "decorator",
        "painter"
    ],
    "wof:name":"Ian Andri",
    "wof:placetype":"venue"
},
  "geometry": {"coordinates":[115.92990112299999,-31.9257659912],"type":"Point"}
}