{
  "type": "Feature",
  "properties": {
    "addr:full":"PO Box 528 Kingscote SA 5223",
    "addr:postcode":"5223",
    "iso:country":"AU",
    "sg:address":"PO Box 528",
    "sg:city":"Kingscote",
    "sg:classifiers":[
        {
            "category":"Professional",
            "type":"Services"
        }
    ],
    "sg:phone":"+61 8 8553 9041",
    "sg:postcode":"5223",
    "sg:province":"SA",
    "sg:tags":[
        "transport"
    ],
    "wof:name":"Ugly Dog Transport",
    "wof:placetype":"venue"
},
  "geometry": {"coordinates":[137.62815856899999,-35.6524391174],"type":"Point"}
}