{
  "type": "Feature",
  "properties": {
    "addr:full":"3 Rivergum Drv Mill Park VIC 3082",
    "addr:housenumber":"3",
    "addr:postcode":"3082",
    "addr:street":"Rivergum Drv",
    "iso:country":"AU",
    "sg:address":"3 Rivergum Drv",
    "sg:city":"Mill Park",
    "sg:classifiers":[
        {
            "category":"Health Services",
            "subcategory":"Doctor",
            "type":"Services"
        }
    ],
    "sg:phone":"+61 3 9436 0700",
    "sg:postcode":"3082",
    "sg:province":"VIC",
    "sg:tags":[
        "medical",
        "practitioner"
    ],
    "wof:name":"Alexander Hala Dr",
    "wof:placetype":"venue"
},
  "geometry": {"coordinates":[145.07432556099999,-37.6633377075],"type":"Point"}
}