{
  "type": "Feature",
  "properties": {
    "addr:full":"28 Orchid Drv Mt Cotton QLD 4165",
    "addr:housenumber":"28",
    "addr:postcode":"4165",
    "addr:street":"Orchid Drv Mt Cotton",
    "iso:country":"AU",
    "sg:address":"28 Orchid Drv",
    "sg:city":"Mt Cotton",
    "sg:classifiers":[
        {
            "category":"Retail",
            "subcategory":"Car Wash",
            "type":"Services"
        }
    ],
    "sg:phone":"+61 7 3206 6997",
    "sg:postcode":"4165",
    "sg:province":"QLD",
    "sg:tags":[
        "truck",
        "cleaning"
    ],
    "wof:name":"MV Auto Detaling",
    "wof:placetype":"venue"
},
  "geometry": {"coordinates":[153.24180602999999,-27.6400527954],"type":"Point"}
}