{
  "type": "Feature",
  "properties": {
    "addr:full":"Shop4, 52 French St Pimlico QLD 4812",
    "addr:housenumber":"52",
    "addr:postcode":"4812",
    "addr:street":"French St",
    "iso:country":"AU",
    "sg:address":"Shop4, 52 French St",
    "sg:city":"Pimlico",
    "sg:classifiers":[
        {
            "category":"Organizations",
            "subcategory":"Membership Organization",
            "type":"Services"
        }
    ],
    "sg:phone":"+61 7 4775 2303",
    "sg:postcode":"4812",
    "sg:province":"QLD",
    "sg:tags":[
        "support",
        "health",
        "organisation"
    ],
    "wof:name":"North Queensland Ostomy Association Inc.",
    "wof:placetype":"venue"
},
  "geometry": {"coordinates":[146.789795,-19.281507],"type":"Point"}
}