{
  "type": "Feature",
  "properties": {
    "iso:country":"AU",
    "sg:address":"1136 Heatherton Rd",
    "sg:city":"Noble Park",
    "sg:classifiers":[
        {
            "category":"Professional",
            "subcategory":"Accounting & Tax Preparation",
            "type":"Services"
        }
    ],
    "sg:phone":"+61 3 9574 1100",
    "sg:postcode":"3174",
    "sg:province":"VIC",
    "sg:tags":[
        "consultant",
        "taxation"
    ],
    "wof:name":"Badrudeen Haneef",
    "wof:placetype":"venue"
},
  "geometry": {"coordinates":[145.18205261200001,-37.9661216736],"type":"Point"}
}