{
  "type": "Feature",
  "properties": {
    "iso:country":"AU",
    "sg:address":"12 Tristan St",
    "sg:city":"Seymour",
    "sg:classifiers":[
        {
            "category":"Personal",
            "subcategory":"Massage",
            "type":"Services"
        }
    ],
    "sg:phone":"+61 3 5799 0175",
    "sg:postcode":"3660",
    "sg:province":"VIC",
    "sg:tags":[
        "therapy"
    ],
    "wof:name":"Merrilyn Sanderson Masseur",
    "wof:placetype":"venue"
},
  "geometry": {"coordinates":[145.13865661599999,-37.0225906372],"type":"Point"}
}