{
  "type": "Feature",
  "properties": {
    "addr:full":"15 Sandringham Ave Cambridge Park NSW 2747",
    "addr:housenumber":"15",
    "addr:postcode":"2747",
    "addr:street":"Sandringham Ave Cambridge",
    "iso:country":"AU",
    "sg:address":"15 Sandringham Ave",
    "sg:city":"Cambridge Park",
    "sg:classifiers":[
        {
            "category":"Retail",
            "subcategory":"Driving School",
            "type":"Services"
        }
    ],
    "sg:phone":"+61 2 4722 3731",
    "sg:postcode":"2747",
    "sg:province":"NSW",
    "wof:name":"2XL Driving School",
    "wof:placetype":"venue"
},
  "geometry": {"coordinates":[150.72377014200001,-33.7527275085],"type":"Point"}
}