{
  "type": "Feature",
  "properties": {
    "addr:full":"PO Box 826 Newport NSW 2106",
    "addr:postcode":"2106",
    "iso:country":"AU",
    "sg:address":"PO Box 826",
    "sg:city":"Newport",
    "sg:classifiers":[
        {
            "category":"Professional",
            "subcategory":"Computer Services",
            "type":"Services"
        }
    ],
    "sg:phone":"+61 2 9918 4311",
    "sg:postcode":"2106",
    "sg:province":"NSW",
    "sg:tags":[
        "package",
        "software"
    ],
    "wof:name":"Mymate Software",
    "wof:placetype":"venue"
},
  "geometry": {"coordinates":[151.32327270499999,-33.650970459],"type":"Point"}
}