{
  "type": "Feature",
  "properties": {
    "addr:full":"34 Gardenvale Rd Caulfield South VIC 3162",
    "addr:housenumber":"34",
    "addr:postcode":"3162",
    "addr:street":"Gardenvale Rd",
    "iso:country":"AU",
    "sg:address":"34 Gardenvale Rd",
    "sg:city":"Caulfield South",
    "sg:classifiers":[
        {
            "category":"Sports & Exercise",
            "subcategory":"Gym",
            "type":"Entertainment"
        }
    ],
    "sg:phone":"+61 409 133 021",
    "sg:postcode":"3162",
    "sg:province":"VIC",
    "sg:tags":[
        "personal",
        "trainer",
        "fitness"
    ],
    "wof:name":"Summit Mobile Health and Fitness",
    "wof:placetype":"venue"
},
  "geometry": {"coordinates":[145.01593017600001,-37.8987770081],"type":"Point"}
}