{
  "type": "Feature",
  "properties": {
    "addr:full":"State Border WA/SA, Eyre Hwy Norseman WA 6443",
    "addr:postcode":"6443",
    "addr:street":"Eyre Hwy",
    "iso:country":"AU",
    "sg:address":"State Border WA/SA, Eyre Hwy",
    "sg:city":"Norseman",
    "sg:classifiers":[
        {
            "category":"Travel",
            "subcategory":"Hotels & Motels",
            "type":"Entertainment"
        }
    ],
    "sg:phone":"+61 8 9039 3474",
    "sg:postcode":"6443",
    "sg:province":"WA",
    "wof:name":"Border Village Hotel Motel",
    "wof:placetype":"venue"
},
  "geometry": {"coordinates":[121.779388428,-32.1851043701],"type":"Point"}
}