{
  "type": "Feature",
  "properties": {
    "iso:country":"AU",
    "sg:address":"Moorebank Shopping Cntr, 22- 23 Stockton Ave",
    "sg:city":"Moorebank",
    "sg:classifiers":[
        {
            "category":"Shopping",
            "subcategory":"Stationery & Office Supplies",
            "type":"Retail Goods"
        }
    ],
    "sg:phone":"+61 2 9602 1412",
    "sg:postcode":"2170",
    "sg:province":"NSW",
    "wof:name":"Officesmart",
    "wof:placetype":"venue"
},
  "geometry": {"coordinates":[150.94749450699999,-33.9380378723],"type":"Point"}
}