{
  "type": "Feature",
  "properties": {
    "addr:full":"11 Bolong Crs Ferny Hills QLD 4055",
    "addr:housenumber":"11",
    "addr:postcode":"4055",
    "addr:street":"Bolong Crs",
    "iso:country":"AU",
    "sg:address":"11 Bolong Crs",
    "sg:city":"Ferny Hills",
    "sg:classifiers":[
        {
            "category":"Professional",
            "subcategory":"Art Services",
            "type":"Services"
        }
    ],
    "sg:phone":"+61 7 3851 0145",
    "sg:postcode":"4055",
    "sg:province":"QLD",
    "sg:tags":[
        "graphic",
        "designer"
    ],
    "wof:name":"Aerial Media",
    "wof:placetype":"venue"
},
  "geometry": {"coordinates":[152.93775939899999,-27.4006195068],"type":"Point"}
}