{
  "type": "Feature",
  "properties": {
    "addr:full":"98- 100 Torkington Rd Londonderry NSW 2753",
    "addr:housenumber":"100",
    "addr:postcode":"2753",
    "addr:street":"98;Torkington Rd",
    "iso:country":"AU",
    "sg:address":"98- 100 Torkington Rd",
    "sg:city":"Londonderry",
    "sg:classifiers":[
        {
            "category":"Building & Trades",
            "subcategory":"Construction",
            "type":"Services"
        }
    ],
    "sg:phone":"+61 2 4588 6877",
    "sg:postcode":"2753",
    "sg:province":"NSW",
    "sg:tags":[
        "contractor"
    ],
    "wof:name":"Panther Constructions Pty Ltd",
    "wof:placetype":"venue"
},
  "geometry": {"coordinates":[150.72456359899999,-33.6445198059],"type":"Point"}
}