{
  "type": "Feature",
  "properties": {
    "iso:country":"AU",
    "sg:address":"24 Rose Ave",
    "sg:city":"Norlane",
    "sg:classifiers":[
        {
            "category":"Food & Beverages",
            "subcategory":"Groceries & Convenience Stores",
            "type":"Retail Goods"
        }
    ],
    "sg:phone":"+61 3 5275 1321",
    "sg:postcode":"3214",
    "sg:province":"VIC",
    "wof:name":"Rose Ave Milk Bar",
    "wof:placetype":"venue"
},
  "geometry": {"coordinates":[144.360198975,-38.0877113342],"type":"Point"}
}