{
  "type": "Feature",
  "properties": {
    "addr:full":"1 Kel Lemon Crt Mt Martha VIC 3934",
    "addr:housenumber":"1",
    "addr:postcode":"3934",
    "addr:street":"Kel Lemon Crt Mt Martha",
    "iso:country":"AU",
    "sg:address":"1 Kel Lemon Crt",
    "sg:city":"Mt Martha",
    "sg:classifiers":[
        {
            "category":"Utilities",
            "subcategory":"Electric",
            "type":"Services"
        }
    ],
    "sg:phone":"+61 418 148 719",
    "sg:postcode":"3934",
    "sg:province":"VIC",
    "sg:tags":[
        "electrical",
        "contractor"
    ],
    "wof:name":"A -Line Electrics",
    "wof:placetype":"venue"
},
  "geometry": {"coordinates":[145.030197144,-38.2686233521],"type":"Point"}
}