{
  "type": "Feature",
  "properties": {
    "addr:full":"87 Nicholson St Brunswick VIC 3055",
    "addr:housenumber":"87",
    "addr:postcode":"3055",
    "addr:street":"Nicholson St",
    "iso:country":"AU",
    "sg:address":"87 Nicholson St",
    "sg:city":"Brunswick",
    "sg:classifiers":[
        {
            "category":"Retail",
            "subcategory":"Auto Repair",
            "type":"Services"
        }
    ],
    "sg:phone":"+61 3 9387 7777",
    "sg:postcode":"3055",
    "sg:province":"VIC",
    "sg:tags":[
        "repairer",
        "motor",
        "engineer"
    ],
    "wof:name":"R.P.M. Engine Centre",
    "wof:placetype":"venue"
},
  "geometry": {"coordinates":[144.97653198200001,-37.7507019043],"type":"Point"}
}