{
  "type": "Feature",
  "properties": {
    "addr:full":"45 Arthur St Carlton NSW 2218",
    "addr:housenumber":"45",
    "addr:postcode":"2218",
    "addr:street":"Arthur St",
    "iso:country":"AU",
    "sg:address":"45 Arthur St",
    "sg:city":"Carlton",
    "sg:classifiers":[
        {
            "category":"Shopping",
            "subcategory":"Party Supplies",
            "type":"Retail Goods"
        }
    ],
    "sg:phone":"+61 401 527 910",
    "sg:postcode":"2218",
    "sg:province":"NSW",
    "sg:tags":[
        "children's"
    ],
    "wof:name":"Party Faces",
    "wof:placetype":"venue"
},
  "geometry": {"coordinates":[151.12164300000001,-33.976158],"type":"Point"}
}