{
  "type": "Feature",
  "properties": {
    "addr:full":"15 Bundall Rd Surfers Paradise QLD 4217",
    "addr:housenumber":"15",
    "addr:postcode":"4217",
    "addr:street":"Bundall Rd",
    "iso:country":"AU",
    "sg:address":"15 Bundall Rd",
    "sg:city":"Surfers Paradise",
    "sg:classifiers":[
        {
            "category":"Building & Trades",
            "subcategory":"Construction",
            "type":"Services"
        }
    ],
    "sg:phone":"+61 423 842 942",
    "sg:postcode":"4217",
    "sg:province":"QLD",
    "sg:tags":[
        "waterproofing",
        "contractor"
    ],
    "wof:name":"Gold Coast Waterproofing",
    "wof:placetype":"venue"
},
  "geometry": {"coordinates":[153.41166687,-28.0137786865],"type":"Point"}
}