{
  "type": "Feature",
  "properties": {
    "iso:country":"AU",
    "sg:address":"77 Stoney Creek Rd",
    "sg:city":"Beverly Hills",
    "sg:classifiers":[
        {
            "category":"Wholesale",
            "subcategory":"Machinery & Supplies",
            "type":"Manufacturing & Wholesale Goods"
        }
    ],
    "sg:phone":"+61 2 9580 2691",
    "sg:postcode":"2209",
    "sg:province":"NSW",
    "sg:tags":[
        "machine",
        "tool",
        "engineer"
    ],
    "wof:name":"M.S.S. Worldwide Machinery",
    "wof:placetype":"venue"
},
  "geometry": {"coordinates":[151.07576,-33.95713],"type":"Point"}
}