{
  "type": "Feature",
  "properties": {
    "addr:full":"98 Buckley St Footscray VIC 3011",
    "addr:housenumber":"98",
    "addr:postcode":"3011",
    "addr:street":"Buckley St",
    "iso:country":"AU",
    "sg:address":"98 Buckley St",
    "sg:city":"Footscray",
    "sg:classifiers":[
        {
            "category":"Retail",
            "subcategory":"Auto Repair",
            "type":"Services"
        }
    ],
    "sg:phone":"+61 3 9687 5725",
    "sg:postcode":"3011",
    "sg:province":"VIC",
    "sg:tags":[
        "repairer",
        "motor",
        "engineer"
    ],
    "wof:name":"Aussie Tune Car Care Centre",
    "wof:placetype":"venue"
},
  "geometry": {"coordinates":[144.89395141599999,-37.8033866882],"type":"Point"}
}