{
  "type": "Feature",
  "properties": {
    "addr:full":"Midland Hwy Lethbridge VIC 3332",
    "addr:postcode":"3332",
    "addr:street":"Midland Hwy",
    "iso:country":"AU",
    "sg:address":"Midland Hwy",
    "sg:city":"Lethbridge",
    "sg:classifiers":[
        {
            "category":"Education",
            "subcategory":"School",
            "type":"Public Place"
        }
    ],
    "sg:phone":"+61 3 5281 7214",
    "sg:postcode":"3332",
    "sg:province":"VIC",
    "sg:tags":[
        "state",
        "except",
        "nsw"
    ],
    "wof:name":"Lethbridge Primary School",
    "wof:placetype":"venue"
},
  "geometry": {"coordinates":[144.12109375,-37.9357337952],"type":"Point"}
}