{
  "type": "Feature",
  "properties": {
    "iso:country":"AU",
    "sg:address":"PO Box 243",
    "sg:city":"Narangba",
    "sg:classifiers":[
        {
            "category":"Professional",
            "subcategory":"Secretarial Services",
            "type":"Services"
        }
    ],
    "sg:phone":"+61 418 685 164",
    "sg:postcode":"4504",
    "sg:province":"QLD",
    "sg:tags":[
        "typing"
    ],
    "wof:name":"Mytech Virtual Secretary Services",
    "wof:placetype":"venue"
},
  "geometry": {"coordinates":[152.92854309099999,-27.1869602203],"type":"Point"}
}