{
  "type": "Feature",
  "properties": {
    "addr:full":"4/ 115 River Rd Gympie QLD 4570",
    "addr:housenumber":"/ 115",
    "addr:postcode":"4570",
    "addr:street":"River Rd",
    "iso:country":"AU",
    "sg:address":"4/ 115 River Rd",
    "sg:city":"Gympie",
    "sg:classifiers":[
        {
            "category":"Food & Beverages",
            "subcategory":"Supermarket",
            "type":"Retail Goods"
        }
    ],
    "sg:phone":"+61 7 5482 9889",
    "sg:postcode":"4570",
    "sg:province":"QLD",
    "sg:tags":[
        "grocery",
        "store"
    ],
    "wof:name":"The 24 Hr Shop",
    "wof:placetype":"venue"
},
  "geometry": {"coordinates":[152.666503906,-26.1994094849],"type":"Point"}
}