{
  "type": "Feature",
  "properties": {
    "addr:full":"152 Croziers Rd Berry NSW 2535",
    "addr:housenumber":"152",
    "addr:postcode":"2535",
    "addr:street":"Croziers Rd",
    "iso:country":"AU",
    "sg:address":"152 Croziers Rd",
    "sg:city":"Berry",
    "sg:classifiers":[
        {
            "category":"Farming",
            "subcategory":"Vineyard",
            "type":"Manufacturing & Wholesale Goods"
        }
    ],
    "sg:phone":"+61 2 4464 1596",
    "sg:postcode":"2535",
    "sg:province":"NSW",
    "sg:tags":[
        "winery"
    ],
    "wof:name":"JASPER VALLEY WINES",
    "wof:placetype":"venue"
},
  "geometry": {"coordinates":[150.65602111800001,-34.7868156433],"type":"Point"}
}