{
  "type": "Feature",
  "properties": {
    "addr:full":"12 Queen St Pingelly WA 6308",
    "addr:housenumber":"12",
    "addr:postcode":"6308",
    "addr:street":"Queen St",
    "iso:country":"AU",
    "sg:address":"12 Queen St",
    "sg:city":"Pingelly",
    "sg:classifiers":[
        {
            "category":"Professional",
            "subcategory":"Engineering",
            "type":"Services"
        }
    ],
    "sg:phone":"+61 8 9887 1162",
    "sg:postcode":"6308",
    "sg:province":"WA",
    "sg:tags":[
        "manufacturing",
        "engineer"
    ],
    "wof:name":"Pingelly Engineering",
    "wof:placetype":"venue"
},
  "geometry": {"coordinates":[117.08261108400001,-32.5317878723],"type":"Point"}
}