{
  "type": "Feature",
  "properties": {
    "addr:full":"78 Princes Hwy Dandenong VIC 3175",
    "addr:housenumber":"78",
    "addr:postcode":"3175",
    "addr:street":"Princes Hwy",
    "iso:country":"AU",
    "sg:address":"78 Princes Hwy",
    "sg:city":"Dandenong",
    "sg:classifiers":[
        {
            "category":"Professional",
            "subcategory":"Business Services",
            "type":"Services"
        }
    ],
    "sg:phone":"+61 3 9792 2640",
    "sg:postcode":"3175",
    "sg:province":"VIC",
    "sg:tags":[
        "drafting"
    ],
    "wof:name":"Conte & Cosentino",
    "wof:placetype":"venue"
},
  "geometry": {"coordinates":[145.20996093799999,-37.9804077148],"type":"Point"}
}