{
  "type": "Feature",
  "properties": {
    "addr:full":"5 Bramall St East Perth WA 6004",
    "addr:housenumber":"5",
    "addr:postcode":"6004",
    "addr:street":"Bramall St East",
    "iso:country":"AU",
    "sg:address":"5 Bramall St",
    "sg:city":"East Perth",
    "sg:classifiers":[
        {
            "category":"Manufacturing",
            "subcategory":"Apparel",
            "type":"Manufacturing & Wholesale Goods"
        }
    ],
    "sg:phone":"+61 8 9228 3088",
    "sg:postcode":"6004",
    "sg:province":"WA",
    "sg:tags":[
        "wholesaler",
        "mfrs",
        "belt"
    ],
    "wof:name":"M & C Agencies",
    "wof:placetype":"venue"
},
  "geometry": {"coordinates":[115.87875366199999,-31.9442462921],"type":"Point"}
}