{
  "type": "Feature",
  "properties": {
    "addr:full":"Shop 7 Boyne Plaza Boyne Island QLD 4680",
    "addr:housenumber":"shop 7",
    "addr:postcode":"4680",
    "addr:street":"Boyne Plaza",
    "iso:country":"AU",
    "sg:address":"Shop 7 Boyne Plaza",
    "sg:city":"Boyne Island",
    "sg:classifiers":[
        {
            "category":"Personal",
            "subcategory":"Beauty Salon",
            "type":"Services"
        }
    ],
    "sg:phone":"+61 7 4973 7555",
    "sg:postcode":"4680",
    "sg:province":"QLD",
    "sg:tags":[
        "hairdresser"
    ],
    "wof:name":"Flava's For Hair",
    "wof:placetype":"venue"
},
  "geometry": {"coordinates":[151.30718994099999,-23.9703407288],"type":"Point"}
}