{
  "type": "Feature",
  "properties": {
    "addr:full":"105 Bellambi La Corrimal NSW 2518",
    "addr:housenumber":"105",
    "addr:postcode":"2518",
    "addr:street":"Bellambi La",
    "iso:country":"AU",
    "sg:address":"105 Bellambi La",
    "sg:city":"Corrimal",
    "sg:classifiers":[
        {
            "category":"Autos & Motor Vehicles",
            "subcategory":"Automobile Sales",
            "type":"Retail Goods"
        }
    ],
    "sg:phone":"+61 2 4285 8400",
    "sg:postcode":"2518",
    "sg:province":"NSW",
    "sg:tags":[
        "equipment",
        "trailer"
    ],
    "wof:name":"Truck Parts Australia Pty Ltd",
    "wof:placetype":"venue"
},
  "geometry": {"coordinates":[150.899734,-34.361107],"type":"Point"}
}