{
  "type": "Feature",
  "properties": {
    "addr:full":"432 William St West Melbourne VIC 3003",
    "addr:housenumber":"432",
    "addr:postcode":"3003",
    "addr:street":"William St",
    "iso:country":"AU",
    "sg:address":"432 William St",
    "sg:city":"West Melbourne",
    "sg:classifiers":[
        {
            "category":"Organizations",
            "subcategory":"Professional Association",
            "type":"Services"
        }
    ],
    "sg:phone":"+61 3 9320 2600",
    "sg:postcode":"3003",
    "sg:province":"VIC",
    "sg:tags":[
        "organisation",
        "business"
    ],
    "wof:name":"Australian Toy Association Ltd",
    "wof:placetype":"venue"
},
  "geometry": {"coordinates":[144.95413207999999,-37.8064155579],"type":"Point"}
}