{
  "type": "Feature",
  "properties": {
    "addr:full":"5 Dendle St Grovedale VIC 3216",
    "addr:housenumber":"5",
    "addr:postcode":"3216",
    "addr:street":"Dendle St",
    "iso:country":"AU",
    "sg:address":"5 Dendle St",
    "sg:city":"Grovedale",
    "sg:classifiers":[
        {
            "category":"Retail",
            "subcategory":"Auto Repair",
            "type":"Services"
        }
    ],
    "sg:phone":"+61 3 5244 0477",
    "sg:postcode":"3216",
    "sg:province":"VIC",
    "sg:tags":[
        "repairer",
        "motor",
        "engineer"
    ],
    "wof:name":"Belgrove Automotive Services",
    "wof:placetype":"venue"
},
  "geometry": {"coordinates":[144.345458984,-38.1952552795],"type":"Point"}
}