{
  "type": "Feature",
  "properties": {
    "addr:full":"103 Ashmore Rd Bundall QLD 4217",
    "addr:housenumber":"103",
    "addr:postcode":"4217",
    "addr:street":"Ashmore Rd",
    "iso:country":"AU",
    "sg:address":"103 Ashmore Rd",
    "sg:city":"Bundall",
    "sg:classifiers":[
        {
            "category":"Professional",
            "subcategory":"Printing & Photocopies",
            "type":"Services"
        }
    ],
    "sg:phone":"+61 7 5538 1300",
    "sg:postcode":"4217",
    "sg:province":"QLD",
    "sg:tags":[
        "photocopying"
    ],
    "wof:name":"Xerox Shop Copy Centre",
    "wof:placetype":"venue"
},
  "geometry": {"coordinates":[153.40109252900001,-28.0094203949],"type":"Point"}
}