{
  "type": "Feature",
  "properties": {
    "iso:country":"AU",
    "sg:address":"24 Runcorn St",
    "sg:city":"St Johns Park",
    "sg:classifiers":[
        {
            "category":"Travel",
            "subcategory":"Hostel",
            "type":"Entertainment"
        }
    ],
    "sg:phone":"+61 2 9823 3855",
    "sg:postcode":"2176",
    "sg:province":"NSW",
    "sg:tags":[
        "home"
    ],
    "wof:name":"Cardinal Stepinac Village",
    "wof:placetype":"venue"
},
  "geometry": {"coordinates":[150.902175903,-33.8771743774],"type":"Point"}
}