{
  "type": "Feature",
  "properties": {
    "iso:country":"AU",
    "sg:address":"203 Barker St",
    "sg:city":"Castlemaine",
    "sg:classifiers":[
        {
            "category":"Cafe",
            "type":"Food & Drink"
        }
    ],
    "sg:phone":"+61 3 5472 3656",
    "sg:postcode":"3450",
    "sg:province":"VIC",
    "wof:name":"Tilleys Tea Room",
    "wof:placetype":"venue"
},
  "geometry": {"coordinates":[144.22198486299999,-37.0486412048],"type":"Point"}
}