{
  "type": "Feature",
  "properties": {
    "addr:full":"lot 15 Thomas Mitchell Drv Muswellbrook NSW 2333",
    "addr:postcode":"2333",
    "addr:street":"Thomas Mitchell Drv",
    "iso:country":"AU",
    "sg:address":"lot 15 Thomas Mitchell Drv",
    "sg:city":"Muswellbrook",
    "sg:classifiers":[
        {
            "category":"Manufacturing",
            "subcategory":"Metals",
            "type":"Manufacturing & Wholesale Goods"
        }
    ],
    "sg:phone":"+61 2 6541 3919",
    "sg:postcode":"2333",
    "sg:province":"NSW",
    "sg:tags":[
        "steel",
        "fabricator",
        "mfrs"
    ],
    "wof:name":"NBM Sheetmetal & Maintenance",
    "wof:placetype":"venue"
},
  "geometry": {"coordinates":[150.897583008,-32.3303375244],"type":"Point"}
}