{
  "type": "Feature",
  "properties": {
    "iso:country":"AU",
    "sg:address":"125 Bayswater Rd",
    "sg:city":"Rushcutters Bay",
    "sg:classifiers":[
        {
            "category":"Food & Beverages",
            "subcategory":"Liquor & Beverages",
            "type":"Retail Goods"
        }
    ],
    "sg:phone":"+61 2 9331 3223",
    "sg:postcode":"2011",
    "sg:province":"NSW",
    "sg:tags":[
        "store"
    ],
    "wof:name":"Vintage Cellars",
    "wof:placetype":"venue"
},
  "geometry": {"coordinates":[151.22747802699999,-33.8763771057],"type":"Point"}
}