{
  "type": "Feature",
  "properties": {
    "addr:full":"Unit 3-4/ 7 Ween Rd Pooraka SA 5095",
    "addr:housenumber":"/ 7",
    "addr:postcode":"5095",
    "addr:street":"Ween Rd",
    "iso:country":"AU",
    "sg:address":"Unit 3-4/ 7 Ween Rd",
    "sg:city":"Pooraka",
    "sg:classifiers":[
        {
            "category":"Bars & Pubs",
            "subcategory":"Gay Bar",
            "type":"Food & Drink"
        }
    ],
    "sg:phone":"+61 8 8359 1088",
    "sg:postcode":"5095",
    "sg:province":"SA",
    "sg:tags":[
        "plywood",
        "veneer"
    ],
    "wof:name":"Designer Veneers Ltd",
    "wof:placetype":"venue"
},
  "geometry": {"coordinates":[138.638015747,-34.8203010559],"type":"Point"}
}