{
  "type": "Feature",
  "properties": {
    "addr:full":"77 Salamanca Pl Hobart TAS 7000",
    "addr:housenumber":"77",
    "addr:postcode":"7000",
    "addr:street":"Salamanca Pl",
    "iso:country":"AU",
    "sg:address":"77 Salamanca Pl",
    "sg:city":"Hobart",
    "sg:classifiers":[
        {
            "category":"Arts & Performance",
            "subcategory":"Art Gallery",
            "type":"Entertainment"
        }
    ],
    "sg:phone":"+61 3 6223 3839",
    "sg:postcode":"7000",
    "sg:province":"TAS",
    "wof:name":"Artefacts",
    "wof:placetype":"venue"
},
  "geometry": {"coordinates":[147.334274292,-42.8868370056],"type":"Point"}
}