{
  "type": "Feature",
  "properties": {
    "addr:full":"324 Princes Hwy Rockdale NSW 2216",
    "addr:housenumber":"324",
    "addr:postcode":"2216",
    "addr:street":"Princes Hwy",
    "iso:country":"AU",
    "sg:address":"324 Princes Hwy",
    "sg:city":"Rockdale",
    "sg:classifiers":[
        {
            "category":"Shopping",
            "subcategory":"Mobile Phones",
            "type":"Retail Goods"
        }
    ],
    "sg:phone":"+61 2 9556 1888",
    "sg:postcode":"2216",
    "sg:province":"NSW",
    "sg:tags":[
        "telephone",
        "accessory"
    ],
    "wof:name":"MLC Mobile Phones",
    "wof:placetype":"venue"
},
  "geometry": {"coordinates":[151.14125100000001,-33.946121],"type":"Point"}
}