{
  "type": "Feature",
  "properties": {
    "addr:full":"322 South Pine Rd Brendale QLD 4500",
    "addr:housenumber":"322",
    "addr:postcode":"4500",
    "addr:street":"South Pine Rd",
    "iso:country":"AU",
    "sg:address":"322 South Pine Rd",
    "sg:city":"Brendale",
    "sg:classifiers":[
        {
            "category":"Autos & Motor Vehicles",
            "subcategory":"Auto Supplies",
            "type":"Retail Goods"
        }
    ],
    "sg:phone":"+61 7 3205 6606",
    "sg:postcode":"4500",
    "sg:province":"QLD",
    "sg:tags":[
        "tyre"
    ],
    "wof:name":"Tyre & Wheel Solutions",
    "wof:placetype":"venue"
},
  "geometry": {"coordinates":[152.98733520499999,-27.3244781494],"type":"Point"}
}