{
  "type": "Feature",
  "properties": {
    "addr:full":"18 Macquarie St Windsor NSW 2756",
    "addr:housenumber":"18",
    "addr:postcode":"2756",
    "addr:street":"Macquarie St",
    "iso:country":"AU",
    "sg:address":"18 Macquarie St",
    "sg:city":"Windsor",
    "sg:classifiers":[
        {
            "category":"Retail",
            "subcategory":"Auto Repair",
            "type":"Services"
        }
    ],
    "sg:phone":"+61 2 4577 4077",
    "sg:postcode":"2756",
    "sg:province":"NSW",
    "sg:tags":[
        "repairer",
        "motor",
        "engineer"
    ],
    "wof:name":"Holden",
    "wof:placetype":"venue"
},
  "geometry": {"coordinates":[150.823394775,-33.6062355042],"type":"Point"}
}