{
  "type": "Feature",
  "properties": {
    "addr:full":"Bexley Rd Campsie NSW 2194",
    "addr:postcode":"2194",
    "addr:street":"Bexley Rd",
    "iso:country":"AU",
    "sg:address":"Bexley Rd",
    "sg:city":"Campsie",
    "sg:classifiers":[
        {
            "category":"Professional",
            "subcategory":"Art Services",
            "type":"Services"
        }
    ],
    "sg:phone":"+61 415 643 415",
    "sg:postcode":"2194",
    "sg:province":"NSW",
    "sg:tags":[
        "decorator",
        "painter"
    ],
    "wof:name":"Inati Painting",
    "wof:placetype":"venue"
},
  "geometry": {"coordinates":[151.10493500000001,-33.918419],"type":"Point"}
}