{
  "type": "Feature",
  "properties": {
    "addr:full":"10 Morton Crs Davistown NSW 2251",
    "addr:housenumber":"10",
    "addr:postcode":"2251",
    "addr:street":"Morton Crs",
    "iso:country":"AU",
    "sg:address":"10 Morton Crs",
    "sg:city":"Davistown",
    "sg:classifiers":[
        {
            "category":"Professional",
            "subcategory":"Management & Consulting",
            "type":"Services"
        }
    ],
    "sg:phone":"+61 419 803 838",
    "sg:postcode":"2251",
    "sg:province":"NSW",
    "sg:tags":[
        "consultant"
    ],
    "wof:name":"Malwall Fabrications Pty Ltd",
    "wof:placetype":"venue"
},
  "geometry": {"coordinates":[151.36065673799999,-33.4849281311],"type":"Point"}
}