{
  "type": "Feature",
  "properties": {
    "addr:full":"55 Kylie Crs Batemans Bay NSW 2536",
    "addr:housenumber":"55",
    "addr:postcode":"2536",
    "addr:street":"Kylie Crs",
    "iso:country":"AU",
    "sg:address":"55 Kylie Crs",
    "sg:city":"Batemans Bay",
    "sg:classifiers":[
        {
            "category":"Building & Trades",
            "subcategory":"Cleaning & Sanitation",
            "type":"Services"
        }
    ],
    "sg:phone":"+61 429 848 646",
    "sg:postcode":"2536",
    "sg:province":"NSW",
    "sg:tags":[
        "cleaner",
        "repairer",
        "roof"
    ],
    "wof:name":"Terraferma Roofing",
    "wof:placetype":"venue"
},
  "geometry": {"coordinates":[150.17732238799999,-35.7084007263],"type":"Point"}
}