{
  "type": "Feature",
  "properties": {
    "addr:full":"10 Redgum Drv Dandenong South VIC 3175",
    "addr:housenumber":"10",
    "addr:postcode":"3175",
    "addr:street":"Redgum Drv",
    "iso:country":"AU",
    "sg:address":"10 Redgum Drv",
    "sg:city":"Dandenong South",
    "sg:classifiers":[
        {
            "category":"Professional",
            "subcategory":"Engineering",
            "type":"Services"
        }
    ],
    "sg:phone":"+61 3 9706 6481",
    "sg:postcode":"3175",
    "sg:province":"VIC",
    "sg:tags":[
        "manufacturing",
        "engineer"
    ],
    "wof:name":"Bacopea Pty Ltd",
    "wof:placetype":"venue"
},
  "geometry": {"coordinates":[145.20191955600001,-38.0249633789],"type":"Point"}
}