{
  "type": "Feature",
  "properties": {
    "addr:full":"27 Nariel St Albion QLD 4010",
    "addr:housenumber":"27",
    "addr:postcode":"4010",
    "addr:street":"Nariel St",
    "iso:country":"AU",
    "sg:address":"27 Nariel St",
    "sg:city":"Albion",
    "sg:classifiers":[
        {
            "category":"Taxi",
            "type":"Transportation"
        }
    ],
    "sg:phone":"+61 7 3262 9300",
    "sg:postcode":"4010",
    "sg:province":"QLD",
    "sg:tags":[
        "cab"
    ],
    "wof:name":"Taxi Management Brisbane",
    "wof:placetype":"venue"
},
  "geometry": {"coordinates":[153.043823242,-27.439081192],"type":"Point"}
}