{
  "type": "Feature",
  "properties": {
    "addr:full":"21 Daniel St Caloundra QLD 4551",
    "addr:housenumber":"21",
    "addr:postcode":"4551",
    "addr:street":"Daniel St",
    "iso:country":"AU",
    "sg:address":"21 Daniel St",
    "sg:city":"Caloundra",
    "sg:classifiers":[
        {
            "category":"Retail",
            "subcategory":"Auto Rental",
            "type":"Services"
        }
    ],
    "sg:phone":"+61 7 5492 5400",
    "sg:postcode":"4551",
    "sg:province":"QLD",
    "sg:tags":[
        "bus",
        "truck"
    ],
    "wof:name":"Budget",
    "wof:placetype":"venue"
},
  "geometry": {"coordinates":[153.109283447,-26.7940063477],"type":"Point"}
}