{
  "type": "Feature",
  "properties": {
    "addr:full":"82 Cosgrove Rd South Strathfield NSW 2136",
    "addr:housenumber":"82",
    "addr:postcode":"2136",
    "addr:street":"Cosgrove Rd South",
    "iso:country":"AU",
    "sg:address":"82 Cosgrove Rd",
    "sg:city":"South Strathfield",
    "sg:classifiers":[
        {
            "category":"Real Estate",
            "subcategory":"Real Estate Agent",
            "type":"Services"
        }
    ],
    "sg:phone":"+61 2 9642 6635",
    "sg:postcode":"2136",
    "sg:province":"NSW",
    "sg:tags":[
        "handyman's",
        "equipment",
        "hire",
        "builders",
        "contractor"
    ],
    "wof:name":"Construction Rentals Pty Ltd",
    "wof:placetype":"venue"
},
  "geometry": {"coordinates":[151.07395935100001,-33.8957824707],"type":"Point"}
}