{
  "type": "Feature",
  "properties": {
    "addr:full":"PO Box 7171 Garbutt Business Centre QLD 4814",
    "addr:postcode":"4814",
    "iso:country":"AU",
    "sg:address":"PO Box 7171",
    "sg:city":"Garbutt Business Centre",
    "sg:classifiers":[
        {
            "category":"Wholesale",
            "subcategory":"Machinery & Supplies",
            "type":"Manufacturing & Wholesale Goods"
        }
    ],
    "sg:phone":"+61 7 4774 5250",
    "sg:postcode":"4814",
    "sg:province":"QLD",
    "sg:tags":[
        "equipment",
        "welding"
    ],
    "wof:name":"Australian Welder Technology",
    "wof:placetype":"venue"
},
  "geometry": {"coordinates":[146.76252700000001,-19.292179],"type":"Point"}
}