{
  "type": "Feature",
  "properties": {
    "addr:full":"108 Dangerfield Drv Elermore Vale NSW 2287",
    "addr:housenumber":"108",
    "addr:postcode":"2287",
    "addr:street":"Dangerfield Drv",
    "iso:country":"AU",
    "sg:address":"108 Dangerfield Drv",
    "sg:city":"Elermore Vale",
    "sg:classifiers":[
        {
            "category":"Professional",
            "subcategory":"Art Services",
            "type":"Services"
        }
    ],
    "sg:phone":"+61 417 201 994",
    "sg:postcode":"2287",
    "sg:province":"NSW",
    "sg:tags":[
        "decorator",
        "painter"
    ],
    "wof:name":"Brogan Terry",
    "wof:placetype":"venue"
},
  "geometry": {"coordinates":[151.681274414,-32.9157524109],"type":"Point"}
}