{
  "type": "Feature",
  "properties": {
    "addr:full":"Stockland Shopping Centre Bowman Rd Caloundra QLD 4551",
    "addr:postcode":"4551",
    "addr:street":"Bowman Rd",
    "iso:country":"AU",
    "sg:address":"Stockland Shopping Centre Bowman Rd",
    "sg:city":"Caloundra",
    "sg:classifiers":[
        {
            "category":"Manufacturing",
            "subcategory":"Jewelry",
            "type":"Manufacturing & Wholesale Goods"
        }
    ],
    "sg:phone":"+61 7 5491 2692",
    "sg:postcode":"4551",
    "sg:province":"QLD",
    "sg:tags":[
        "designer",
        "jewellery"
    ],
    "wof:name":"Hourglass Jewellers",
    "wof:placetype":"venue"
},
  "geometry": {"coordinates":[153.129669189,-26.8004722595],"type":"Point"}
}