{
  "type": "Feature",
  "properties": {
    "addr:full":"1- 13 Anniversary Pl Coffs Harbour NSW 2450",
    "addr:housenumber":"13",
    "addr:postcode":"2450",
    "addr:street":"1;Pl",
    "iso:country":"AU",
    "sg:address":"1- 13 Anniversary Pl",
    "sg:city":"Coffs Harbour",
    "sg:classifiers":[
        {
            "category":"Taxi",
            "type":"Transportation"
        }
    ],
    "sg:phone":"+61 408 408 401",
    "sg:postcode":"2450",
    "sg:province":"NSW",
    "sg:tags":[
        "cab"
    ],
    "wof:name":"Drive Wise",
    "wof:placetype":"venue"
},
  "geometry": {"coordinates":[153.096878,-30.299328],"type":"Point"}
}