{
  "type": "Feature",
  "properties": {
    "addr:full":"Unit 3/ 26 June St Coffs Harbour NSW 2450",
    "addr:postcode":"2450",
    "addr:street":"26 June St",
    "iso:country":"AU",
    "sg:address":"Unit 3/ 26 June St",
    "sg:city":"Coffs Harbour",
    "sg:classifiers":[
        {
            "category":"Retail",
            "subcategory":"Auto Repair",
            "type":"Services"
        }
    ],
    "sg:phone":"+61 2 6652 9420",
    "sg:postcode":"2450",
    "sg:province":"NSW",
    "sg:tags":[
        "beater",
        "painter",
        "panel"
    ],
    "wof:name":"Edge Panel & Paint",
    "wof:placetype":"venue"
},
  "geometry": {"coordinates":[153.118683,-30.289885],"type":"Point"}
}