{
  "type": "Feature",
  "properties": {
    "iso:country":"AU",
    "sg:address":"Lot 19/ 20 Smith St",
    "sg:city":"Emu Plains",
    "sg:classifiers":[
        {
            "category":"Retail",
            "subcategory":"Car Wash",
            "type":"Services"
        }
    ],
    "sg:phone":"+61 2 4735 6696",
    "sg:postcode":"2750",
    "sg:province":"NSW",
    "sg:tags":[
        "truck",
        "cleaning"
    ],
    "wof:name":"Panther Detailing Services",
    "wof:placetype":"venue"
},
  "geometry": {"coordinates":[150.67086792000001,-33.74401474],"type":"Point"}
}