{
  "type": "Feature",
  "properties": {
    "iso:country":"AU",
    "sg:address":"Shop 16B Hibiscus Shopping Town",
    "sg:city":"Leanyer",
    "sg:classifiers":[
        {
            "category":"Shopping",
            "subcategory":"Clothing, Apparel, & Fashions",
            "type":"Retail Goods"
        }
    ],
    "sg:phone":"+61 8 8945 6867",
    "sg:postcode":"0812",
    "sg:province":"NT",
    "sg:tags":[
        "maternity",
        "wear"
    ],
    "wof:name":"Mums 'n Bubs Maternity Wear",
    "wof:placetype":"venue"
},
  "geometry": {"coordinates":[130.895065,-12.378151],"type":"Point"}
}