{
  "type": "Feature",
  "properties": {
    "iso:country":"AU",
    "sg:address":"4 Glenbrae St",
    "sg:city":"The Gap",
    "sg:classifiers":[
        {
            "category":"Professional",
            "subcategory":"Art Services",
            "type":"Services"
        }
    ],
    "sg:phone":"+61 7 3300 5354",
    "sg:postcode":"4061",
    "sg:province":"QLD",
    "sg:tags":[
        "graphic",
        "designer"
    ],
    "wof:name":"Spot Art",
    "wof:placetype":"venue"
},
  "geometry": {"coordinates":[152.94593810999999,-27.4551811218],"type":"Point"}
}