{
  "type": "Feature",
  "properties": {
    "iso:country":"AU",
    "sg:address":"5/2- 4 Onslow St",
    "sg:city":"Rose Bay",
    "sg:classifiers":[
        {
            "category":"Shopping",
            "subcategory":"Stationery & Office Supplies",
            "type":"Retail Goods"
        }
    ],
    "sg:phone":"+61 2 9388 3380",
    "sg:postcode":"2029",
    "sg:province":"NSW",
    "sg:tags":[
        "packaging",
        "material"
    ],
    "wof:name":"Associated Packaging Pty Ltd",
    "wof:placetype":"venue"
},
  "geometry": {"coordinates":[151.272247314,-33.8759689331],"type":"Point"}
}