{
  "type": "Feature",
  "properties": {
    "iso:country":"AU",
    "sg:address":"44 Moira Ave",
    "sg:city":"West Ryde",
    "sg:classifiers":[
        {
            "category":"Health Services",
            "subcategory":"Health Practitioner",
            "type":"Services"
        }
    ],
    "sg:phone":"+61 2 9874 6880",
    "sg:postcode":"2114",
    "sg:province":"NSW",
    "sg:tags":[
        "technique",
        "alexander"
    ],
    "wof:name":"Australian Society of Teachers of the Alexander Technique (AUSTAT)",
    "wof:placetype":"venue"
},
  "geometry": {"coordinates":[151.07859802199999,-33.8026046753],"type":"Point"}
}