{
  "type": "Feature",
  "properties": {
    "addr:full":"Jacaranda St Red Cliffs VIC 3496",
    "addr:postcode":"3496",
    "addr:street":"Jacaranda St",
    "iso:country":"AU",
    "sg:address":"Jacaranda St",
    "sg:city":"Red Cliffs",
    "sg:classifiers":[
        {
            "category":"Autos & Motor Vehicles",
            "subcategory":"Fuel & Gas Station",
            "type":"Retail Goods"
        }
    ],
    "sg:phone":"+61 3 5024 3892",
    "sg:postcode":"3496",
    "sg:province":"VIC",
    "wof:name":"Caltex Oil (Aust) Pty Ltd",
    "wof:placetype":"venue"
},
  "geometry": {"coordinates":[142.18652343799999,-34.3077430725],"type":"Point"}
}