{
  "type": "Feature",
  "properties": {
    "iso:country":"AU",
    "sg:address":"28 Canterbury Rd",
    "sg:city":"Albert Park",
    "sg:classifiers":[
        {
            "category":"Health Services",
            "subcategory":"Doctor",
            "type":"Services"
        }
    ],
    "sg:phone":"+61 3 9690 1006",
    "sg:postcode":"3206",
    "sg:province":"VIC",
    "sg:tags":[
        "medical",
        "practitioner"
    ],
    "wof:name":"James Oldham Dr",
    "wof:placetype":"venue"
},
  "geometry": {"coordinates":[144.96049500000001,-37.84465],"type":"Point"}
}