{
  "type": "Feature",
  "properties": {
    "addr:full":"162 Liverpool Rd Enfield NSW 2136",
    "addr:housenumber":"162",
    "addr:postcode":"2136",
    "addr:street":"Liverpool Rd",
    "iso:country":"AU",
    "sg:address":"162 Liverpool Rd",
    "sg:city":"Enfield",
    "sg:classifiers":[
        {
            "category":"Fast Food",
            "type":"Food & Drink"
        }
    ],
    "sg:phone":"+61 2 9747 3560",
    "sg:postcode":"2136",
    "sg:province":"NSW",
    "sg:tags":[
        "away",
        "take"
    ],
    "wof:name":"Enfield Takeaway",
    "wof:placetype":"venue"
},
  "geometry": {"coordinates":[151.09759521500001,-33.8870429993],"type":"Point"}
}