{
  "type": "Feature",
  "properties": {
    "addr:full":"Yanchep Beach Rd Yanchep WA 6035",
    "addr:postcode":"6035",
    "addr:street":"Beach Rd",
    "iso:country":"AU",
    "sg:address":"Yanchep Beach Rd",
    "sg:city":"Yanchep",
    "sg:classifiers":[
        {
            "category":"Communications",
            "subcategory":"News Services",
            "type":"Services"
        }
    ],
    "sg:phone":"+61 8 9561 1061",
    "sg:postcode":"6035",
    "sg:province":"WA",
    "sg:tags":[
        "information",
        "tourist",
        "attractions"
    ],
    "wof:name":"Perth Outback Camels",
    "wof:placetype":"venue"
},
  "geometry": {"coordinates":[115.67224883999999,-31.5505142212],"type":"Point"}
}