{
  "type": "Feature",
  "properties": {
    "iso:country":"AU",
    "sg:address":"U705b/ 65 Bay St",
    "sg:city":"Port Melbourne",
    "sg:classifiers":[
        {
            "category":"Shopping",
            "subcategory":"Clothing, Apparel, & Fashions",
            "type":"Retail Goods"
        }
    ],
    "sg:phone":"+61 3 9681 7598",
    "sg:postcode":"3207",
    "sg:province":"VIC",
    "sg:tags":[
        "lady",
        "wear"
    ],
    "wof:name":"Kinkikoko Pty Ltd",
    "wof:placetype":"venue"
},
  "geometry": {"coordinates":[144.939468,-37.841469],"type":"Point"}
}