{
  "type": "Feature",
  "properties": {
    "iso:country":"AU",
    "sg:address":"6 Dumaresq St",
    "sg:city":"Campbelltown",
    "sg:classifiers":[
        {
            "category":"Health Services",
            "subcategory":"Doctor",
            "type":"Services"
        }
    ],
    "sg:phone":"+61 2 4628 3766",
    "sg:postcode":"2560",
    "sg:province":"NSW",
    "sg:tags":[
        "medical",
        "practitioner"
    ],
    "wof:name":"Symbion Imaging",
    "wof:placetype":"venue"
},
  "geometry": {"coordinates":[150.812103272,-34.0667114258],"type":"Point"}
}