{
  "type": "Feature",
  "properties": {
    "iso:country":"AU",
    "sg:address":"53 - 55 Gover St",
    "sg:city":"North Adelaide",
    "sg:classifiers":[
        {
            "category":"Health Services",
            "subcategory":"Health Practitioner",
            "type":"Services"
        }
    ],
    "sg:phone":"+61 8 8361 9888",
    "sg:postcode":"5006",
    "sg:province":"SA",
    "sg:tags":[
        "physiotherapist"
    ],
    "wof:name":"Tania Pradun",
    "wof:placetype":"venue"
},
  "geometry": {"coordinates":[138.59779357900001,-34.9042167664],"type":"Point"}
}