{
  "type": "Feature",
  "properties": {
    "iso:country":"AU",
    "sg:address":"PO Box 206",
    "sg:city":"Holland Park",
    "sg:classifiers":[
        {
            "category":"Military Area",
            "subcategory":"Air Force Base",
            "type":"Public Place"
        }
    ],
    "sg:phone":"+61 7 3397 1750",
    "sg:postcode":"4121",
    "sg:province":"QLD",
    "sg:tags":[
        "fibre",
        "optic"
    ],
    "wof:name":"Astech Industries",
    "wof:placetype":"venue"
},
  "geometry": {"coordinates":[153.062942505,-27.516582489],"type":"Point"}
}