{
  "type": "Feature",
  "properties": {
    "addr:full":"429 Monbulk-Silvan Rd Monbulk VIC 3793",
    "addr:housenumber":"429",
    "addr:postcode":"3793",
    "addr:street":"Monbulk-Silvan Rd",
    "iso:country":"AU",
    "sg:address":"429 Monbulk-Silvan Rd",
    "sg:city":"Monbulk",
    "sg:classifiers":[
        {
            "category":"Farming",
            "subcategory":"Nursery",
            "type":"Manufacturing & Wholesale Goods"
        }
    ],
    "sg:phone":"+61 3 9756 6086",
    "sg:postcode":"3793",
    "sg:province":"VIC",
    "wof:name":"A To Z Bonsai Starters",
    "wof:placetype":"venue"
},
  "geometry": {"coordinates":[145.41558837900001,-37.858997345],"type":"Point"}
}