{
  "type": "Feature",
  "properties": {
    "addr:full":"Lot 487 Criddle St Mt Magnet WA 6638",
    "addr:postcode":"6638",
    "addr:street":"Criddle St Mt Magnet",
    "iso:country":"AU",
    "sg:address":"Lot 487 Criddle St",
    "sg:city":"Mt Magnet",
    "sg:classifiers":[
        {
            "category":"Building & Trades",
            "subcategory":"Construction",
            "type":"Services"
        }
    ],
    "sg:phone":"+61 8 9963 4462",
    "sg:postcode":"6638",
    "sg:province":"WA",
    "sg:tags":[
        "earth",
        "excavating",
        "moving",
        "contractor"
    ],
    "wof:name":"Malibu Nominees Pty Ltd",
    "wof:placetype":"venue"
},
  "geometry": {"coordinates":[117.845046997,-28.0584583282],"type":"Point"}
}