{
  "type": "Feature",
  "properties": {
    "addr:full":"78 Junction St Nowra NSW 2541",
    "addr:housenumber":"78",
    "addr:postcode":"2541",
    "addr:street":"Junction St",
    "iso:country":"AU",
    "sg:address":"78 Junction St",
    "sg:city":"Nowra",
    "sg:classifiers":[
        {
            "category":"Shopping",
            "subcategory":"Jewelry",
            "type":"Retail Goods"
        }
    ],
    "sg:phone":"+61 2 4422 1342",
    "sg:postcode":"2541",
    "sg:province":"NSW",
    "sg:tags":[
        "jeweller"
    ],
    "wof:name":"The Nowra Jeweller",
    "wof:placetype":"venue"
},
  "geometry": {"coordinates":[150.600952148,-34.8744354248],"type":"Point"}
}