{
  "type": "Feature",
  "properties": {
    "addr:full":"5 Redman Rd Dee Why NSW 2099",
    "addr:housenumber":"5",
    "addr:postcode":"2099",
    "addr:street":"Redman Rd",
    "iso:country":"AU",
    "sg:address":"5 Redman Rd",
    "sg:city":"Dee Why",
    "sg:classifiers":[
        {
            "category":"Retail",
            "subcategory":"Self-service Laundry",
            "type":"Services"
        }
    ],
    "sg:phone":"+61 2 9982 5838",
    "sg:postcode":"2099",
    "sg:province":"NSW",
    "wof:name":"D.Y. Laundry",
    "wof:placetype":"venue"
},
  "geometry": {"coordinates":[151.28395080600001,-33.7535476685],"type":"Point"}
}