{
  "type": "Feature",
  "properties": {
    "addr:full":"Cnr Princes Hwy & Nolan St Unanderra NSW 2526",
    "addr:postcode":"2526",
    "addr:street":"Cnr Princes Hwy & Nolan St",
    "iso:country":"AU",
    "sg:address":"Cnr Princes Hwy & Nolan St",
    "sg:city":"Unanderra",
    "sg:classifiers":[
        {
            "category":"Retail",
            "subcategory":"Auto Repair",
            "type":"Services"
        }
    ],
    "sg:phone":"+61 2 4272 4326",
    "sg:postcode":"2526",
    "sg:province":"NSW",
    "sg:tags":[
        "wheel",
        "balancing",
        "alignment"
    ],
    "wof:name":"DP Tyres",
    "wof:placetype":"venue"
},
  "geometry": {"coordinates":[150.838500977,-34.4618988037],"type":"Point"}
}