{
  "type": "Feature",
  "properties": {
    "addr:full":"Level 1 Australia Fair Shopng Cntr Scarborough St Southport QLD 4215",
    "addr:postcode":"4215",
    "addr:street":"St",
    "iso:country":"AU",
    "sg:address":"Level 1 Australia Fair Shopng Cntr Scarborough St",
    "sg:city":"Southport",
    "sg:classifiers":[
        {
            "category":"Cinema",
            "subcategory":"Movie Theater",
            "type":"Entertainment"
        }
    ],
    "sg:phone":"+61 7 5531 2200",
    "sg:postcode":"4215",
    "sg:province":"QLD",
    "wof:name":"Birch Carroll & Coyle",
    "wof:placetype":"venue"
},
  "geometry": {"coordinates":[153.413406372,-27.9661636353],"type":"Point"}
}