{
  "type": "Feature",
  "properties": {
    "addr:full":"18 Doonside Drv Lilydale VIC 3140",
    "addr:housenumber":"18",
    "addr:postcode":"3140",
    "addr:street":"Doonside Drv",
    "iso:country":"AU",
    "sg:address":"18 Doonside Drv",
    "sg:city":"Lilydale",
    "sg:classifiers":[
        {
            "category":"Building & Trades",
            "subcategory":"Landscaping Services",
            "type":"Services"
        }
    ],
    "sg:phone":"+61 412 534 400",
    "sg:postcode":"3140",
    "sg:province":"VIC",
    "sg:tags":[
        "designer",
        "landscape",
        "contractor"
    ],
    "wof:name":"Venus Landscaping & Maintenance",
    "wof:placetype":"venue"
},
  "geometry": {"coordinates":[145.358276367,-37.7723884583],"type":"Point"}
}