{
  "type": "Feature",
  "properties": {
    "iso:country":"AU",
    "sg:address":"Suite 302/ 3 Chester St",
    "sg:city":"Oakleigh",
    "sg:classifiers":[
        {
            "category":"Health Services",
            "subcategory":"Doctor",
            "type":"Services"
        }
    ],
    "sg:phone":"+61 3 9569 5077",
    "sg:postcode":"3166",
    "sg:province":"VIC",
    "sg:tags":[
        "medical",
        "practitioner"
    ],
    "wof:name":"Greater South Eastern Division Of General Practice",
    "wof:placetype":"venue"
},
  "geometry": {"coordinates":[145.087646484,-37.8990859985],"type":"Point"}
}