{
  "type": "Feature",
  "properties": {
    "addr:full":"153 Leichhardt St Spring Hill QLD 4000",
    "addr:housenumber":"153",
    "addr:postcode":"4000",
    "addr:street":"Leichhardt St",
    "iso:country":"AU",
    "sg:address":"153 Leichhardt St",
    "sg:city":"Spring Hill",
    "sg:classifiers":[
        {
            "category":"Shopping",
            "subcategory":"Music",
            "type":"Retail Goods"
        }
    ],
    "sg:phone":"+61 7 3831 0283",
    "sg:postcode":"4000",
    "sg:province":"QLD",
    "sg:tags":[
        "instrument",
        "musical"
    ],
    "wof:name":"Allans Academy of Music",
    "wof:placetype":"venue"
},
  "geometry": {"coordinates":[153.025466919,-27.462688446],"type":"Point"}
}