{
  "type": "Feature",
  "properties": {
    "addr:full":"21 Memorial Ave Liverpool NSW 2170",
    "addr:housenumber":"21",
    "addr:postcode":"2170",
    "addr:street":"Memorial Ave",
    "iso:country":"AU",
    "sg:address":"21 Memorial Ave",
    "sg:city":"Liverpool",
    "sg:classifiers":[
        {
            "category":"Professional",
            "subcategory":"Business Services",
            "type":"Services"
        }
    ],
    "sg:phone":"+61 2 9821 2399",
    "sg:postcode":"2170",
    "sg:province":"NSW",
    "sg:tags":[
        "broker"
    ],
    "wof:name":"Macfarlanes Business Advisors",
    "wof:placetype":"venue"
},
  "geometry": {"coordinates":[150.92265319800001,-33.9246520996],"type":"Point"}
}