{
  "type": "Feature",
  "properties": {
    "iso:country":"AU",
    "sg:address":"Cnr Rode & Webster Rds",
    "sg:city":"Chermside",
    "sg:classifiers":[
        {
            "category":"Health Services",
            "subcategory":"Chiropractor",
            "type":"Services"
        }
    ],
    "sg:phone":"+61 7 3256 4500",
    "sg:postcode":"4032",
    "sg:province":"QLD",
    "wof:name":"First Choice Chiropractic",
    "wof:placetype":"venue"
},
  "geometry": {"coordinates":[153.022186,-27.383383],"type":"Point"}
}