{
  "type": "Feature",
  "properties": {
    "addr:full":"8 Forster St Bungendore ACT 2621",
    "addr:housenumber":"8",
    "addr:postcode":"2621",
    "addr:street":"Forster St",
    "iso:country":"AU",
    "sg:address":"8 Forster St",
    "sg:city":"Bungendore",
    "sg:classifiers":[
        {
            "category":"Social Services",
            "subcategory":"Child Care",
            "type":"Services"
        }
    ],
    "sg:phone":"+61 2 6238 1315",
    "sg:postcode":"2621",
    "sg:province":"ACT",
    "wof:name":"Bungendore Kids Zone Pre-School & Long Day Care",
    "wof:placetype":"venue"
},
  "geometry": {"coordinates":[149.437942505,-35.2596664429],"type":"Point"}
}