{
  "type": "Feature",
  "properties": {
    "addr:full":"230 Liverpool St Enfield NSW 2136",
    "addr:housenumber":"230",
    "addr:postcode":"2136",
    "addr:street":"Liverpool St",
    "iso:country":"AU",
    "sg:address":"230 Liverpool St",
    "sg:city":"Enfield",
    "sg:classifiers":[
        {
            "category":"Shopping",
            "subcategory":"Computers & Home Electronics",
            "type":"Retail Goods"
        }
    ],
    "sg:phone":"+61 2 9745 0877",
    "sg:postcode":"2136",
    "sg:province":"NSW",
    "sg:tags":[
        "hardware",
        "equipment"
    ],
    "wof:name":"Umart International Pty Ltd",
    "wof:placetype":"venue"
},
  "geometry": {"coordinates":[151.09596252399999,-33.8863563538],"type":"Point"}
}