{
  "type": "Feature",
  "properties": {
    "iso:country":"AU",
    "sg:address":"45 Raglan Ave",
    "sg:city":"Edwardstown",
    "sg:classifiers":[
        {
            "category":"Professional",
            "subcategory":"Printing & Photocopies",
            "type":"Services"
        }
    ],
    "sg:phone":"+61 8 8297 1099",
    "sg:postcode":"5039",
    "sg:province":"SA",
    "sg:tags":[
        "screen",
        "printer"
    ],
    "wof:name":"Australian Screenprinted Advertising Products Pty Limited",
    "wof:placetype":"venue"
},
  "geometry": {"coordinates":[138.56956481899999,-34.9799461365],"type":"Point"}
}