{
  "type": "Feature",
  "properties": {
    "addr:full":"137 Bridge Rd Richmond VIC 3121",
    "addr:housenumber":"137",
    "addr:postcode":"3121",
    "addr:street":"Bridge Rd",
    "iso:country":"AU",
    "sg:address":"137 Bridge Rd",
    "sg:city":"Richmond",
    "sg:classifiers":[
        {
            "category":"Shopping",
            "subcategory":"Clothing, Apparel, & Fashions",
            "type":"Retail Goods"
        }
    ],
    "sg:phone":"+61 3 9428 2131",
    "sg:postcode":"3121",
    "sg:province":"VIC",
    "sg:tags":[
        "lady",
        "wear"
    ],
    "wof:name":"Ink Clothing",
    "wof:placetype":"venue"
},
  "geometry": {"coordinates":[144.99444580100001,-37.8178977966],"type":"Point"}
}