{
  "type": "Feature",
  "properties": {
    "addr:full":"Macleay St Wagga Wagga NSW 2650",
    "addr:postcode":"2650",
    "addr:street":"Macleay St",
    "iso:country":"AU",
    "sg:address":"Macleay St",
    "sg:city":"Wagga Wagga",
    "sg:classifiers":[
        {
            "category":"Cafe",
            "type":"Food & Drink"
        }
    ],
    "sg:phone":"+61 2 6925 3883",
    "sg:postcode":"2650",
    "sg:province":"NSW",
    "wof:name":"Park Cafe The",
    "wof:placetype":"venue"
},
  "geometry": {"coordinates":[147.36204528799999,-35.1351051331],"type":"Point"}
}