{
  "type": "Feature",
  "properties": {
    "iso:country":"AU",
    "sg:address":"107 Cambridge St",
    "sg:city":"Granville",
    "sg:classifiers":[
        {
            "category":"Retail",
            "subcategory":"Auto Repair",
            "type":"Services"
        }
    ],
    "sg:phone":"+61 7 4123 0040",
    "sg:postcode":"4650",
    "sg:province":"QLD",
    "sg:tags":[
        "clutch",
        "brake"
    ],
    "wof:name":"G & P Mechanical Repairs",
    "wof:placetype":"venue"
},
  "geometry": {"coordinates":[152.720779,-25.543489],"type":"Point"}
}