{
  "type": "Feature",
  "properties": {
    "addr:full":"40 Belvedere St Belmont WA 6104",
    "addr:housenumber":"40",
    "addr:postcode":"6104",
    "addr:street":"Belvedere St",
    "iso:country":"AU",
    "sg:address":"40 Belvedere St",
    "sg:city":"Belmont",
    "sg:classifiers":[
        {
            "category":"Government",
            "subcategory":"Post Office",
            "type":"Public Place"
        }
    ],
    "sg:phone":"+61 8 9277 2784",
    "sg:postcode":"6104",
    "sg:province":"WA",
    "sg:tags":[
        "postal"
    ],
    "wof:name":"Australia Post",
    "wof:placetype":"venue"
},
  "geometry": {"coordinates":[115.940086365,-31.9465484619],"type":"Point"}
}