{
  "type": "Feature",
  "properties": {
    "addr:full":"98 Marquis St Gunnedah NSW 2380",
    "addr:housenumber":"98",
    "addr:postcode":"2380",
    "addr:street":"Marquis St",
    "iso:country":"AU",
    "sg:address":"98 Marquis St",
    "sg:city":"Gunnedah",
    "sg:classifiers":[
        {
            "category":"Shopping",
            "subcategory":"Clothing, Apparel, & Fashions",
            "type":"Retail Goods"
        }
    ],
    "sg:phone":"+61 2 6742 1449",
    "sg:postcode":"2380",
    "sg:province":"NSW",
    "sg:tags":[
        "lady",
        "wear"
    ],
    "wof:name":"Nunee Boutique",
    "wof:placetype":"venue"
},
  "geometry": {"coordinates":[150.252975464,-30.9778423309],"type":"Point"}
}