{
  "type": "Feature",
  "properties": {
    "addr:full":"Unit 1/ 93 Rushdale St Knoxfield VIC 3180",
    "addr:housenumber":"93",
    "addr:postcode":"3180",
    "addr:street":"Rushdale St",
    "iso:country":"AU",
    "sg:address":"Unit 1/ 93 Rushdale St",
    "sg:city":"Knoxfield",
    "sg:classifiers":[
        {
            "category":"Professional",
            "subcategory":"Art Services",
            "type":"Services"
        }
    ],
    "sg:phone":"+61 3 9764 9555",
    "sg:postcode":"3180",
    "sg:province":"VIC",
    "sg:tags":[
        "graphic",
        "designer"
    ],
    "wof:name":"Kwik Kopy Printing Centre Knoxfield",
    "wof:placetype":"venue"
},
  "geometry": {"coordinates":[145.255661011,-37.8955802917],"type":"Point"}
}