{
  "type": "Feature",
  "properties": {
    "iso:country":"AU",
    "sg:address":"41 Dobney Ave",
    "sg:city":"Wagga Wagga",
    "sg:classifiers":[
        {
            "category":"Wholesale",
            "subcategory":"Office Equipment",
            "type":"Manufacturing & Wholesale Goods"
        }
    ],
    "sg:phone":"+61 2 6925 5966",
    "sg:postcode":"2650",
    "sg:province":"NSW",
    "sg:tags":[
        "nail",
        "nailing"
    ],
    "wof:name":"David Brand Builders Supplies",
    "wof:placetype":"venue"
},
  "geometry": {"coordinates":[147.346099853,-35.1193656921],"type":"Point"}
}