{
  "type": "Feature",
  "properties": {
    "addr:full":"36 Main St Palmwoods QLD 4555",
    "addr:housenumber":"36",
    "addr:postcode":"4555",
    "addr:street":"Main St",
    "iso:country":"AU",
    "sg:address":"36 Main St",
    "sg:city":"Palmwoods",
    "sg:classifiers":[
        {
            "category":"Professional",
            "subcategory":"Computer Services",
            "type":"Services"
        }
    ],
    "sg:phone":"+61 7 5445 0990",
    "sg:postcode":"4555",
    "sg:province":"QLD",
    "sg:tags":[
        "consultant",
        "system"
    ],
    "wof:name":"Go Computer Company",
    "wof:placetype":"venue"
},
  "geometry": {"coordinates":[152.96002197300001,-26.6890983582],"type":"Point"}
}