{
  "type": "Feature",
  "properties": {
    "iso:country":"AU",
    "sg:address":"54 McGregor St",
    "sg:city":"Deakin",
    "sg:classifiers":[
        {
            "category":"Education",
            "subcategory":"Music School",
            "type":"Public Place"
        }
    ],
    "sg:phone":"+61 2 6281 6108",
    "sg:postcode":"2600",
    "sg:province":"ACT",
    "sg:tags":[
        "teacher"
    ],
    "wof:name":"Corvini Jennifer",
    "wof:placetype":"venue"
},
  "geometry": {"coordinates":[149.10580444300001,-35.3163986206],"type":"Point"}
}