{
  "type": "Feature",
  "properties": {
    "iso:country":"AU",
    "sg:address":"691-695 Fig Tree Pocket Rd",
    "sg:city":"Fig Tree Pocket",
    "sg:classifiers":[
        {
            "category":"Education",
            "subcategory":"Kindergarten",
            "type":"Public Place"
        }
    ],
    "sg:phone":"+61 7 3378 9233",
    "sg:postcode":"4069",
    "sg:province":"QLD",
    "sg:tags":[
        "pre-schools"
    ],
    "wof:name":"C&K Gan Gani Community Preschool & Kindergarten (Qld Jewish Kindergarten Assoc.)",
    "wof:placetype":"venue"
},
  "geometry": {"coordinates":[152.96366882300001,-27.532245636],"type":"Point"}
}