{
  "type": "Feature",
  "properties": {
    "iso:country":"AU",
    "sg:address":"Cnr Canterbury & Wills Sts",
    "sg:city":"Yarraville",
    "sg:classifiers":[
        {
            "category":"Government",
            "subcategory":"City Hall",
            "type":"Public Place"
        }
    ],
    "sg:phone":"+61 3 9687 5450",
    "sg:postcode":"3013",
    "sg:province":"VIC",
    "wof:name":"Masonic Centre",
    "wof:placetype":"venue"
},
  "geometry": {"coordinates":[144.88812255900001,-37.8158493042],"type":"Point"}
}