{
  "type": "Feature",
  "properties": {
    "addr:full":"PO Box 613 Punchbowl NSW 2196",
    "addr:postcode":"2196",
    "iso:country":"AU",
    "sg:address":"PO Box 613",
    "sg:city":"Punchbowl",
    "sg:classifiers":[
        {
            "category":"Structure",
            "subcategory":"Office Building",
            "type":"Public Place"
        }
    ],
    "sg:phone":"+61 405 262 292",
    "sg:postcode":"2196",
    "sg:province":"NSW",
    "sg:tags":[
        "tie",
        "concrete",
        "formwork",
        "form",
        "accessory"
    ],
    "wof:name":"Top Class Formwork & Steel Fixing Pty Ltd",
    "wof:placetype":"venue"
},
  "geometry": {"coordinates":[151.053741,-33.92585],"type":"Point"}
}