{
  "type": "Feature",
  "properties": {
    "iso:country":"AU",
    "sg:address":"Lot 6 Dunne Bay Rd",
    "sg:city":"Dunsborough",
    "sg:classifiers":[
        {
            "category":"Real Estate",
            "subcategory":"Real Estate Agent",
            "type":"Services"
        }
    ],
    "sg:phone":"+61 8 9756 8888",
    "sg:postcode":"6281",
    "sg:province":"WA",
    "wof:name":"Professionals Real Estate Group The",
    "wof:placetype":"venue"
},
  "geometry": {"coordinates":[115.11013794,-33.6140823364],"type":"Point"}
}