{
  "type": "Feature",
  "properties": {
    "addr:full":"2 Johnsons Rd Mullumbimby NSW 2482",
    "addr:housenumber":"2",
    "addr:postcode":"2482",
    "addr:street":"Johnsons Rd",
    "iso:country":"AU",
    "sg:address":"2 Johnsons Rd",
    "sg:city":"Mullumbimby",
    "sg:classifiers":[
        {
            "category":"Professional",
            "subcategory":"Testing Lab",
            "type":"Services"
        }
    ],
    "sg:phone":"+61 2 6684 0494",
    "sg:postcode":"2482",
    "sg:province":"NSW",
    "sg:tags":[
        "soil",
        "investigation"
    ],
    "wof:name":"Aungle Rob & Associates",
    "wof:placetype":"venue"
},
  "geometry": {"coordinates":[153.460174561,-28.5344581604],"type":"Point"}
}