{
  "type": "Feature",
  "properties": {
    "addr:full":"6 Clarke St Guildford NSW 2161",
    "addr:housenumber":"6",
    "addr:postcode":"2161",
    "addr:street":"Clarke St",
    "iso:country":"AU",
    "sg:address":"6 Clarke St",
    "sg:city":"Guildford",
    "sg:classifiers":[
        {
            "category":"Retail",
            "subcategory":"Auto Repair",
            "type":"Services"
        }
    ],
    "sg:phone":"+61 2 9632 8355",
    "sg:postcode":"2161",
    "sg:province":"NSW",
    "sg:tags":[
        "repairer",
        "motor",
        "engineer"
    ],
    "wof:name":"Trojan Automotive",
    "wof:placetype":"venue"
},
  "geometry": {"coordinates":[150.977172852,-33.8608474731],"type":"Point"}
}