{
  "type": "Feature",
  "properties": {
    "addr:full":"107A Murphy St Wangaratta VIC 3677",
    "addr:housenumber":"107a",
    "addr:postcode":"3677",
    "addr:street":"Murphy St",
    "iso:country":"AU",
    "sg:address":"107A Murphy St",
    "sg:city":"Wangaratta",
    "sg:classifiers":[
        {
            "category":"Education",
            "subcategory":"Dance Studio",
            "type":"Public Place"
        }
    ],
    "sg:phone":"+61 3 5721 8200",
    "sg:postcode":"3677",
    "sg:province":"VIC",
    "sg:tags":[
        "venue",
        "tuition"
    ],
    "wof:name":"Wangaratta District Studio Of Dance",
    "wof:placetype":"venue"
},
  "geometry": {"coordinates":[146.32786560100001,-36.354309082],"type":"Point"}
}