{
  "type": "Feature",
  "properties": {
    "addr:full":"643 Macauley St Albury NSW 2640",
    "addr:housenumber":"643",
    "addr:postcode":"2640",
    "addr:street":"Macauley St",
    "iso:country":"AU",
    "sg:address":"643 Macauley St",
    "sg:city":"Albury",
    "sg:classifiers":[
        {
            "category":"Professional",
            "subcategory":"Art Services",
            "type":"Services"
        }
    ],
    "sg:phone":"+61 2 6021 1826",
    "sg:postcode":"2640",
    "sg:province":"NSW",
    "sg:tags":[
        "interior",
        "decorator"
    ],
    "wof:name":"Clever Colour & Design",
    "wof:placetype":"venue"
},
  "geometry": {"coordinates":[146.92340087900001,-36.0741882324],"type":"Point"}
}