{
  "type": "Feature",
  "properties": {
    "addr:full":"37 Brett St Georgetown NSW 2298",
    "addr:housenumber":"37",
    "addr:postcode":"2298",
    "addr:street":"Brett St",
    "iso:country":"AU",
    "sg:address":"37 Brett St",
    "sg:city":"Georgetown",
    "sg:classifiers":[
        {
            "category":"Building & Trades",
            "subcategory":"Plumbing",
            "type":"Services"
        }
    ],
    "sg:phone":"+61 2 4967 4020",
    "sg:postcode":"2298",
    "sg:province":"NSW",
    "sg:tags":[
        "plumber",
        "gasfitters"
    ],
    "wof:name":"Stanwell G.J. & L.M.",
    "wof:placetype":"venue"
},
  "geometry": {"coordinates":[151.73478698700001,-32.9094963074],"type":"Point"}
}