{
  "type": "Feature",
  "properties": {
    "addr:full":"118 Main Rd Clayton VIC 3168",
    "addr:housenumber":"118",
    "addr:postcode":"3168",
    "addr:street":"Main Rd",
    "iso:country":"AU",
    "sg:address":"118 Main Rd",
    "sg:city":"Clayton",
    "sg:classifiers":[
        {
            "category":"Wholesale",
            "subcategory":"Auto Parts",
            "type":"Manufacturing & Wholesale Goods"
        }
    ],
    "sg:phone":"+61 3 9551 7111",
    "sg:postcode":"3168",
    "sg:province":"VIC",
    "sg:tags":[
        "recyclers"
    ],
    "wof:name":"Toyaparts",
    "wof:placetype":"venue"
},
  "geometry": {"coordinates":[145.124755859,-37.899181366],"type":"Point"}
}