{
  "type": "Feature",
  "properties": {
    "addr:full":"380 Russell St Melbourne VIC 3000",
    "addr:housenumber":"380",
    "addr:postcode":"3000",
    "addr:street":"Russell St",
    "iso:country":"AU",
    "sg:address":"380 Russell St",
    "sg:city":"Melbourne",
    "sg:classifiers":[
        {
            "category":"Travel",
            "subcategory":"Hostel",
            "type":"Entertainment"
        }
    ],
    "sg:phone":"+61 3 9662 3888",
    "sg:postcode":"3000",
    "sg:province":"VIC",
    "sg:tags":[
        "home"
    ],
    "wof:name":"Victoria Hall Accommodation",
    "wof:placetype":"venue"
},
  "geometry": {"coordinates":[144.96592712399999,-37.807674408],"type":"Point"}
}