{
  "type": "Feature",
  "properties": {
    "addr:full":"43 Greens Rd Wyndham Vale VIC 3024",
    "addr:housenumber":"43",
    "addr:postcode":"3024",
    "addr:street":"Greens Rd",
    "iso:country":"AU",
    "sg:address":"43 Greens Rd",
    "sg:city":"Wyndham Vale",
    "sg:classifiers":[
        {
            "category":"Building & Trades",
            "subcategory":"Construction",
            "type":"Services"
        }
    ],
    "sg:phone":"+61 412 846 980",
    "sg:postcode":"3024",
    "sg:province":"VIC",
    "sg:tags":[
        "earth",
        "excavating",
        "moving",
        "contractor"
    ],
    "wof:name":"Woody's Bobcat and Tip Truck Hire",
    "wof:placetype":"venue"
},
  "geometry": {"coordinates":[144.624268,-37.889751],"type":"Point"}
}