{
  "type": "Feature",
  "properties": {
    "addr:full":"2 Main St Currie TAS 7256",
    "addr:housenumber":"2",
    "addr:postcode":"7256",
    "addr:street":"Main St",
    "iso:country":"AU",
    "sg:address":"2 Main St",
    "sg:city":"Currie",
    "sg:classifiers":[
        {
            "category":"Government",
            "subcategory":"Post Office",
            "type":"Public Place"
        }
    ],
    "sg:phone":"+61 3 6462 1792",
    "sg:postcode":"7256",
    "sg:province":"TAS",
    "sg:tags":[
        "postal"
    ],
    "wof:name":"Australia Post",
    "wof:placetype":"venue"
},
  "geometry": {"coordinates":[143.85075378400001,-39.930896759],"type":"Point"}
}