{
  "type": "Feature",
  "properties": {
    "iso:country":"AU",
    "sg:address":"Shp10/ 6 Feilman Drv",
    "sg:city":"Leda",
    "sg:classifiers":[
        {
            "category":"Food & Beverages",
            "subcategory":"Bakery",
            "type":"Retail Goods"
        }
    ],
    "sg:phone":"+61 8 9419 1114",
    "sg:postcode":"6170",
    "sg:province":"WA",
    "sg:tags":[
        "baker"
    ],
    "wof:name":"Sarah Patisseries",
    "wof:placetype":"venue"
},
  "geometry": {"coordinates":[115.806129,-32.259853],"type":"Point"}
}