{
  "type": "Feature",
  "properties": {
    "iso:country":"AU",
    "sg:address":"15 Kendall St",
    "sg:city":"Mt Waverley",
    "sg:classifiers":[
        {
            "category":"Professional",
            "subcategory":"Advertising",
            "type":"Services"
        }
    ],
    "sg:phone":"+61 3 9803 5354",
    "sg:postcode":"3149",
    "sg:province":"VIC",
    "sg:tags":[
        "balloon",
        "novelty"
    ],
    "wof:name":"K.D.J. Enterprises",
    "wof:placetype":"venue"
},
  "geometry": {"coordinates":[145.14930725100001,-37.8622093201],"type":"Point"}
}