{
  "type": "Feature",
  "properties": {
    "iso:country":"AU",
    "sg:address":"246 Lower Heidelberg Rd",
    "sg:city":"Ivanhoe",
    "sg:classifiers":[
        {
            "category":"Professional",
            "subcategory":"Accounting & Tax Preparation",
            "type":"Services"
        }
    ],
    "sg:phone":"+61 3 9499 7138",
    "sg:postcode":"3079",
    "sg:province":"VIC",
    "sg:tags":[
        "consultant",
        "taxation"
    ],
    "wof:name":"EGC Accountants & Advisors",
    "wof:placetype":"venue"
},
  "geometry": {"coordinates":[145.05921935999999,-37.7729187012],"type":"Point"}
}