{
  "type": "Feature",
  "properties": {
    "addr:full":"414 Dynon Rd West Melbourne VIC 3003",
    "addr:housenumber":"414",
    "addr:postcode":"3003",
    "addr:street":"Dynon Rd",
    "iso:country":"AU",
    "sg:address":"414 Dynon Rd",
    "sg:city":"West Melbourne",
    "sg:classifiers":[
        {
            "category":"Shopping",
            "subcategory":"Optical Goods",
            "type":"Retail Goods"
        }
    ],
    "sg:phone":"+61 3 9687 7750",
    "sg:postcode":"3003",
    "sg:province":"VIC",
    "sg:tags":[
        "supply"
    ],
    "wof:name":"Saxon Binoculars & Telescopes",
    "wof:placetype":"venue"
},
  "geometry": {"coordinates":[144.914306641,-37.8013038635],"type":"Point"}
}