{
  "type": "Feature",
  "properties": {
    "addr:full":"359 Gardeners Rd Rosebery NSW 2018",
    "addr:housenumber":"359",
    "addr:postcode":"2018",
    "addr:street":"Gardeners Rd",
    "iso:country":"AU",
    "sg:address":"359 Gardeners Rd",
    "sg:city":"Rosebery",
    "sg:classifiers":[
        {
            "category":"Real Estate",
            "subcategory":"Real Estate Agent",
            "type":"Services"
        }
    ],
    "sg:phone":"+61 2 9667 0881",
    "sg:postcode":"2018",
    "sg:province":"NSW",
    "wof:name":"Raine & Horne Mascot/Rosebery",
    "wof:placetype":"venue"
},
  "geometry": {"coordinates":[151.20423889200001,-33.9226608276],"type":"Point"}
}