{
  "type": "Feature",
  "properties": {
    "addr:full":"Frenchs Forest Rd Frenchs Forest NSW 2086",
    "addr:postcode":"2086",
    "addr:street":"Frenchs Forest Rd",
    "iso:country":"AU",
    "sg:address":"Frenchs Forest Rd",
    "sg:city":"Frenchs Forest",
    "sg:classifiers":[
        {
            "category":"Military Area",
            "subcategory":"Armory",
            "type":"Public Place"
        }
    ],
    "sg:phone":"+61 2 9452 2222",
    "sg:postcode":"2086",
    "sg:province":"NSW",
    "sg:tags":[
        "teleconferencing"
    ],
    "wof:name":"Sky Channel Business Television",
    "wof:placetype":"venue"
},
  "geometry": {"coordinates":[151.234283447,-33.7498092651],"type":"Point"}
}