{
  "type": "Feature",
  "properties": {
    "addr:full":"60 Strathallen Ave Northbridge NSW 2063",
    "addr:housenumber":"60",
    "addr:postcode":"2063",
    "addr:street":"Strathallen Ave",
    "iso:country":"AU",
    "sg:address":"60 Strathallen Ave",
    "sg:city":"Northbridge",
    "sg:classifiers":[
        {
            "category":"Real Estate",
            "subcategory":"Architect",
            "type":"Services"
        }
    ],
    "sg:phone":"+61 2 9958 0488",
    "sg:postcode":"2063",
    "sg:province":"NSW",
    "wof:name":"Mayoh P D Pty Ltd",
    "wof:placetype":"venue"
},
  "geometry": {"coordinates":[151.2109375,-33.811126709],"type":"Point"}
}