{
  "type": "Feature",
  "properties": {
    "iso:country":"AU",
    "sg:address":"24 Evans St",
    "sg:city":"Woodside",
    "sg:classifiers":[
        {
            "category":"Manufacturing",
            "subcategory":"Paper Products",
            "type":"Manufacturing & Wholesale Goods"
        }
    ],
    "sg:phone":"+61 8 8389 7464",
    "sg:postcode":"5244",
    "sg:province":"SA",
    "sg:tags":[
        "metal",
        "non-ferrous",
        "foundry"
    ],
    "wof:name":"Castalite Castings",
    "wof:placetype":"venue"
},
  "geometry": {"coordinates":[138.884857178,-34.936832428],"type":"Point"}
}