{
  "type": "Feature",
  "properties": {
    "iso:country":"AU",
    "sg:address":"Jose St",
    "sg:city":"Murray Bridge",
    "sg:classifiers":[
        {
            "category":"Retail",
            "subcategory":"Auto Repair",
            "type":"Services"
        }
    ],
    "sg:phone":"+61 8 8532 6966",
    "sg:postcode":"5253",
    "sg:province":"SA",
    "sg:tags":[
        "wheel",
        "balancing",
        "alignment"
    ],
    "wof:name":"Murray Bridge Tyrepower",
    "wof:placetype":"venue"
},
  "geometry": {"coordinates":[139.25587463400001,-35.1272087097],"type":"Point"}
}