{
  "type": "Feature",
  "properties": {
    "addr:full":"12 / 24 Edensor St Epping NSW 2121",
    "addr:housenumber":"12 / 24",
    "addr:postcode":"2121",
    "addr:street":"Edensor St",
    "iso:country":"AU",
    "sg:address":"12 / 24 Edensor St",
    "sg:city":"Epping",
    "sg:classifiers":[
        {
            "category":"Personal",
            "subcategory":"Skin Care",
            "type":"Services"
        }
    ],
    "sg:phone":"+61 2 9868 2770",
    "sg:postcode":"2121",
    "sg:province":"NSW",
    "sg:tags":[
        "information",
        "treatment",
        "smoker"
    ],
    "wof:name":"Eagle View Coaching",
    "wof:placetype":"venue"
},
  "geometry": {"coordinates":[151.08070373499999,-33.7666549683],"type":"Point"}
}