{
  "type": "Feature",
  "properties": {
    "addr:full":"Dick Ward Drv Coconut Grove NT 0810",
    "addr:postcode":"0810",
    "addr:street":"Ward Drv",
    "iso:country":"AU",
    "sg:address":"Dick Ward Drv",
    "sg:city":"Coconut Grove",
    "sg:classifiers":[
        {
            "category":"Home & Garden",
            "subcategory":"Garden Supply",
            "type":"Retail Goods"
        }
    ],
    "sg:phone":"+61 8 8985 2544",
    "sg:postcode":"0810",
    "sg:province":"NT",
    "sg:tags":[
        "equipment"
    ],
    "wof:name":"U-Cart Concrete",
    "wof:placetype":"venue"
},
  "geometry": {"coordinates":[130.852294922,-12.3901700974],"type":"Point"}
}