{
  "type": "Feature",
  "properties": {
    "addr:full":"Shed 5/ 120 Raglan St Roma QLD 4455",
    "addr:housenumber":"5 / 120",
    "addr:postcode":"4455",
    "addr:street":"Raglan St",
    "iso:country":"AU",
    "sg:address":"Shed 5/ 120 Raglan St",
    "sg:city":"Roma",
    "sg:classifiers":[
        {
            "category":"Professional",
            "subcategory":"Engineering",
            "type":"Services"
        }
    ],
    "sg:phone":"+61 7 4622 8833",
    "sg:postcode":"4455",
    "sg:province":"QLD",
    "sg:tags":[
        "engineer"
    ],
    "wof:name":"Rayham Pty Ltd",
    "wof:placetype":"venue"
},
  "geometry": {"coordinates":[148.784103394,-26.581073761],"type":"Point"}
}