{
  "type": "Feature",
  "properties": {
    "iso:country":"AU",
    "sg:address":"PO Box 74",
    "sg:city":"Thorpdale",
    "sg:classifiers":[
        {
            "category":"Food & Beverages",
            "subcategory":"Fruits & Vegetables",
            "type":"Retail Goods"
        }
    ],
    "sg:phone":"+61 3 5634 6466",
    "sg:postcode":"3835",
    "sg:province":"VIC",
    "sg:tags":[
        "grower",
        "potato"
    ],
    "wof:name":"Alannon Produce Co Pty Ltd",
    "wof:placetype":"venue"
},
  "geometry": {"coordinates":[146.17465200000001,-38.305519],"type":"Point"}
}