{
  "type": "Feature",
  "properties": {
    "addr:full":"33 Olive St Hendra QLD 4011",
    "addr:housenumber":"33",
    "addr:postcode":"4011",
    "addr:street":"Olive St",
    "iso:country":"AU",
    "sg:address":"33 Olive St",
    "sg:city":"Hendra",
    "sg:classifiers":[
        {
            "category":"Real Estate",
            "subcategory":"Architect",
            "type":"Services"
        }
    ],
    "sg:phone":"+61 7 3868 4808",
    "sg:postcode":"4011",
    "sg:province":"QLD",
    "wof:name":"Collins J.T.",
    "wof:placetype":"venue"
},
  "geometry": {"coordinates":[153.07148699999999,-27.419847],"type":"Point"}
}