{
  "type": "Feature",
  "properties": {
    "iso:country":"AU",
    "sg:address":"330 cheltenham Rd",
    "sg:city":"Keysborough",
    "sg:classifiers":[
        {
            "category":"Communications",
            "subcategory":"Film & Video Production",
            "type":"Services"
        }
    ],
    "sg:phone":"+61 3 9798 8558",
    "sg:postcode":"3173",
    "sg:province":"VIC",
    "sg:tags":[
        "dvd",
        "library"
    ],
    "wof:name":"Video Ezy",
    "wof:placetype":"venue"
},
  "geometry": {"coordinates":[145.17282104500001,-37.9944190979],"type":"Point"}
}