{
  "type": "Feature",
  "properties": {
    "addr:full":"230 Cabramatta Road, Cabramatta NSW 2166",
    "addr:housenumber":"230",
    "addr:postcode":"2166",
    "addr:street":"Cabramatta Road",
    "iso:country":"AU",
    "sg:address":"230 Cabramatta Road,",
    "sg:city":"Cabramatta",
    "sg:classifiers":[
        {
            "category":"Personal",
            "subcategory":"Skin Care",
            "type":"Services"
        }
    ],
    "sg:phone":"+61 2 9728 1972",
    "sg:postcode":"2166",
    "sg:province":"NSW",
    "sg:tags":[
        "treatment"
    ],
    "wof:name":"Nuevo Cosmetic Clinic",
    "wof:placetype":"venue"
},
  "geometry": {"coordinates":[150.93557739299999,-33.8960113525],"type":"Point"}
}