{
  "type": "Feature",
  "properties": {
    "addr:full":"Lvl 2, 4- 8 Woodville St Hurstville NSW 2220",
    "addr:housenumber":"4 8",
    "addr:postcode":"2220",
    "addr:street":"Woodville St",
    "iso:country":"AU",
    "sg:address":"Lvl 2, 4- 8 Woodville St",
    "sg:city":"Hurstville",
    "sg:classifiers":[
        {
            "category":"Professional",
            "subcategory":"Employment Agencies",
            "type":"Services"
        }
    ],
    "sg:phone":"+61 2 9580 8355",
    "sg:postcode":"2220",
    "sg:province":"NSW",
    "sg:tags":[
        "hire",
        "labour",
        "contractor"
    ],
    "wof:name":"Hays Office Support",
    "wof:placetype":"venue"
},
  "geometry": {"coordinates":[151.10354614299999,-33.9649353027],"type":"Point"}
}