{
  "type": "Feature",
  "properties": {
    "addr:full":"100 Queen St Beaconsfield NSW 2015",
    "addr:housenumber":"100",
    "addr:postcode":"2015",
    "addr:street":"Queen St",
    "iso:country":"AU",
    "sg:address":"100 Queen St",
    "sg:city":"Beaconsfield",
    "sg:classifiers":[
        {
            "category":"Professional",
            "subcategory":"Detective & Security Services",
            "type":"Services"
        }
    ],
    "sg:phone":"+61 2 9698 0177",
    "sg:postcode":"2015",
    "sg:province":"NSW",
    "sg:tags":[
        "consultant",
        "system"
    ],
    "wof:name":"Australian Light Towers",
    "wof:placetype":"venue"
},
  "geometry": {"coordinates":[151.19973754899999,-33.9116325378],"type":"Point"}
}