{
  "type": "Feature",
  "properties": {
    "addr:full":"15 Joffre Rd Trigg WA 6029",
    "addr:housenumber":"15",
    "addr:postcode":"6029",
    "addr:street":"Joffre Rd",
    "iso:country":"AU",
    "sg:address":"15 Joffre Rd",
    "sg:city":"Trigg",
    "sg:classifiers":[
        {
            "category":"Professional",
            "subcategory":"Accounting & Tax Preparation",
            "type":"Services"
        }
    ],
    "sg:phone":"+61 8 9246 5760",
    "sg:postcode":"6029",
    "sg:province":"WA",
    "sg:tags":[
        "bookkeeping"
    ],
    "wof:name":"Solution 42 Bookkeeping",
    "wof:placetype":"venue"
},
  "geometry": {"coordinates":[115.756690979,-31.876871109],"type":"Point"}
}