{
  "type": "Feature",
  "properties": {
    "iso:country":"AU",
    "sg:address":"43 Endurance Ave",
    "sg:city":"Queanbeyan",
    "sg:classifiers":[
        {
            "category":"Building & Trades",
            "subcategory":"Construction",
            "type":"Services"
        }
    ],
    "sg:phone":"+61 2 6284 2799",
    "sg:postcode":"2620",
    "sg:province":"NSW",
    "sg:tags":[
        "window",
        "aluminium"
    ],
    "wof:name":"Taylors Window Supplies",
    "wof:placetype":"venue"
},
  "geometry": {"coordinates":[149.24948120100001,-35.3399200439],"type":"Point"}
}