{
  "type": "Feature",
  "properties": {
    "addr:full":"Shop 5 47- 69 Main South Rd O'Halloran Hill SA 5158",
    "addr:housenumber":"shop;47 69",
    "addr:postcode":"5158",
    "addr:street":"Main South Rd O'Halloran",
    "iso:country":"AU",
    "sg:address":"Shop 5 47- 69 Main South Rd",
    "sg:city":"O'Halloran Hill",
    "sg:classifiers":[
        {
            "category":"Fast Food",
            "type":"Food & Drink"
        }
    ],
    "sg:phone":"+61 8 8387 6060",
    "sg:postcode":"5158",
    "sg:province":"SA",
    "sg:tags":[
        "away",
        "take"
    ],
    "wof:name":"Pedro's Pizza",
    "wof:placetype":"venue"
},
  "geometry": {"coordinates":[138.555419922,-35.0662956238],"type":"Point"}
}