{
  "type": "Feature",
  "properties": {
    "addr:full":"210 Charters Towers Rd Hermit Park QLD 4812",
    "addr:housenumber":"210",
    "addr:postcode":"4812",
    "addr:street":"Charters Towers Rd",
    "iso:country":"AU",
    "sg:address":"210 Charters Towers Rd",
    "sg:city":"Hermit Park",
    "sg:classifiers":[
        {
            "category":"Shopping",
            "subcategory":"Beauty & Cosmetics",
            "type":"Retail Goods"
        }
    ],
    "sg:phone":"+61 7 4779 4666",
    "sg:postcode":"4812",
    "sg:province":"QLD",
    "wof:name":"Amcal Chemist Hermit Park",
    "wof:placetype":"venue"
},
  "geometry": {"coordinates":[146.797653,-19.284258],"type":"Point"}
}