{
  "type": "Feature",
  "properties": {
    "iso:country":"AU",
    "sg:address":"36a Brougham St",
    "sg:city":"Fairfield",
    "sg:classifiers":[
        {
            "category":"Manufacturing",
            "subcategory":"Apparel",
            "type":"Manufacturing & Wholesale Goods"
        }
    ],
    "sg:phone":"+61 7 3255 3565",
    "sg:postcode":"4103",
    "sg:province":"QLD",
    "sg:tags":[
        "makers-up",
        "clothing"
    ],
    "wof:name":"Sew Kwik",
    "wof:placetype":"venue"
},
  "geometry": {"coordinates":[153.026153564,-27.5084056854],"type":"Point"}
}