{
  "type": "Feature",
  "properties": {
    "addr:full":"PO Box 800 Mitcham Shopping Centre SA 5062",
    "addr:postcode":"5062",
    "iso:country":"AU",
    "sg:address":"PO Box 800",
    "sg:city":"Mitcham Shopping Centre",
    "sg:classifiers":[
        {
            "category":"Building & Trades",
            "subcategory":"Landscaping Services",
            "type":"Services"
        }
    ],
    "sg:phone":"+61 408 836 886",
    "sg:postcode":"5062",
    "sg:province":"SA",
    "sg:tags":[
        "designer",
        "landscape",
        "contractor"
    ],
    "wof:name":"New Eden Garden Design",
    "wof:placetype":"venue"
},
  "geometry": {"coordinates":[138.60972595199999,-34.9752883911],"type":"Point"}
}