{
  "type": "Feature",
  "properties": {
    "addr:full":"PO Box 74 Kent Town SA 5071",
    "addr:postcode":"5071",
    "iso:country":"AU",
    "sg:address":"PO Box 74",
    "sg:city":"Kent Town",
    "sg:classifiers":[
        {
            "category":"Bars & Pubs",
            "subcategory":"Sports Bar",
            "type":"Food & Drink"
        }
    ],
    "sg:phone":"+61 8 8370 2466",
    "sg:postcode":"5071",
    "sg:province":"SA",
    "sg:tags":[
        "club",
        "diving",
        "scuba"
    ],
    "wof:name":"Underwater Explorers Club Of S.A. Incorporated",
    "wof:placetype":"venue"
},
  "geometry": {"coordinates":[138.616363525,-34.9215393066],"type":"Point"}
}