{
  "type": "Feature",
  "properties": {
    "addr:full":"5 Mitchell Rd Brookvale NSW 2100",
    "addr:housenumber":"5",
    "addr:postcode":"2100",
    "addr:street":"Mitchell Rd",
    "iso:country":"AU",
    "sg:address":"5 Mitchell Rd",
    "sg:city":"Brookvale",
    "sg:classifiers":[
        {
            "category":"Retail",
            "subcategory":"Auto Repair",
            "type":"Services"
        }
    ],
    "sg:phone":"+61 2 9939 7085",
    "sg:postcode":"2100",
    "sg:province":"NSW",
    "sg:tags":[
        "clutch",
        "brake"
    ],
    "wof:name":"Warringah Clutch Service",
    "wof:placetype":"venue"
},
  "geometry": {"coordinates":[151.274856567,-33.7622032166],"type":"Point"}
}