{
  "type": "Feature",
  "properties": {
    "addr:full":"86 Overton St Kurrajong NSW 2758",
    "addr:housenumber":"86",
    "addr:postcode":"2758",
    "addr:street":"Overton St",
    "iso:country":"AU",
    "sg:address":"86 Overton St",
    "sg:city":"Kurrajong",
    "sg:classifiers":[
        {
            "category":"Building & Trades",
            "subcategory":"Construction",
            "type":"Services"
        }
    ],
    "sg:phone":"+61 2 4573 2039",
    "sg:postcode":"2758",
    "sg:province":"NSW",
    "sg:tags":[
        "earth",
        "excavating",
        "moving",
        "contractor"
    ],
    "wof:name":"J & C Cook Pty Ltd",
    "wof:placetype":"venue"
},
  "geometry": {"coordinates":[150.69012451200001,-33.5292663574],"type":"Point"}
}