{
  "type": "Feature",
  "properties": {
    "addr:full":"Lot 5 Verrierdale Rd Eumundi QLD 4562",
    "addr:postcode":"4562",
    "addr:street":"Verrierdale Rd",
    "iso:country":"AU",
    "sg:address":"Lot 5 Verrierdale Rd",
    "sg:city":"Eumundi",
    "sg:classifiers":[
        {
            "category":"Farming",
            "subcategory":"Livestock Farm",
            "type":"Manufacturing & Wholesale Goods"
        }
    ],
    "sg:phone":"+61 7 5449 1801",
    "sg:postcode":"4562",
    "sg:province":"QLD",
    "sg:tags":[
        "breeder",
        "horse",
        "stud"
    ],
    "wof:name":"Jacobsen Blood Stock Pty Ltd",
    "wof:placetype":"venue"
},
  "geometry": {"coordinates":[153.02830505399999,-26.4825763702],"type":"Point"}
}