{
  "type": "Feature",
  "properties": {
    "iso:country":"AU",
    "sg:address":"Read St",
    "sg:city":"Newtown",
    "sg:classifiers":[
        {
            "category":"Arena",
            "subcategory":"Sports Club",
            "type":"Entertainment"
        }
    ],
    "sg:phone":"+61 3 5222 2848",
    "sg:postcode":"3220",
    "sg:province":"VIC",
    "sg:tags":[
        "australian",
        "football",
        "rule"
    ],
    "wof:name":"Newtown & Chilwell Football Club",
    "wof:placetype":"venue"
},
  "geometry": {"coordinates":[144.32884200000001,-38.143085],"type":"Point"}
}