{
  "type": "Feature",
  "properties": {
    "iso:country":"AU",
    "sg:address":"207 Spencer St",
    "sg:city":"Bunbury",
    "sg:classifiers":[
        {
            "category":"Health Services",
            "subcategory":"Doctor",
            "type":"Services"
        }
    ],
    "sg:phone":"+61 8 9792 2666",
    "sg:postcode":"6230",
    "sg:province":"WA",
    "sg:tags":[
        "medical",
        "practitioner"
    ],
    "wof:name":"Bairstow P K",
    "wof:placetype":"venue"
},
  "geometry": {"coordinates":[115.64147199999999,-33.346062],"type":"Point"}
}