{
  "type": "Feature",
  "properties": {
    "addr:full":"16 Walden St Tanunda SA 5352",
    "addr:housenumber":"16",
    "addr:postcode":"5352",
    "addr:street":"Walden St",
    "iso:country":"AU",
    "sg:address":"16 Walden St",
    "sg:city":"Tanunda",
    "sg:classifiers":[
        {
            "category":"Retail",
            "subcategory":"Auto Repair",
            "type":"Services"
        }
    ],
    "sg:phone":"+61 8 8563 0502",
    "sg:postcode":"5352",
    "sg:province":"SA",
    "sg:tags":[
        "repairer",
        "motor",
        "engineer"
    ],
    "wof:name":"Strength Mechanical Services",
    "wof:placetype":"venue"
},
  "geometry": {"coordinates":[138.967086792,-34.5234718323],"type":"Point"}
}