{
  "type": "Feature",
  "properties": {
    "iso:country":"AU",
    "sg:address":"Factory 6, 43 Greenway Drive (Cnr. Corporation Circuit)",
    "sg:city":"Tweed Heads South",
    "sg:classifiers":[
        {
            "category":"Professional",
            "subcategory":"Art Services",
            "type":"Services"
        }
    ],
    "sg:phone":"+61 7 5524 5500",
    "sg:postcode":"2486",
    "sg:province":"NSW",
    "sg:tags":[
        "graphic",
        "designer"
    ],
    "wof:name":"Twin Towns Printery",
    "wof:placetype":"venue"
},
  "geometry": {"coordinates":[153.53596496599999,-28.2051811218],"type":"Point"}
}