{
  "type": "Feature",
  "properties": {
    "iso:country":"AU",
    "sg:address":"111- 123 Hampton St",
    "sg:city":"Toowoomba",
    "sg:classifiers":[
        {
            "category":"Commercial Area",
            "type":"Public Place"
        }
    ],
    "sg:phone":"+61 7 4699 9500",
    "sg:postcode":"4350",
    "sg:province":"QLD",
    "sg:tags":[
        "heavy",
        "carrier"
    ],
    "sg:website":"http://www.simon.com.au",
    "wof:name":"Simon National Carriers",
    "wof:placetype":"venue"
},
  "geometry": {"coordinates":[151.92138700000001,-27.572533],"type":"Point"}
}