{
  "type": "Feature",
  "properties": {
    "iso:country":"AU",
    "sg:address":"21- 27 Bass Hwy",
    "sg:city":"Burnie",
    "sg:classifiers":[
        {
            "category":"Real Estate",
            "subcategory":"Real Estate Agent",
            "type":"Services"
        }
    ],
    "sg:phone":"+61 3 6431 3122",
    "sg:postcode":"7320",
    "sg:province":"TAS",
    "sg:tags":[
        "handyman's",
        "equipment",
        "hire",
        "builders",
        "contractor"
    ],
    "wof:name":"Wreckair",
    "wof:placetype":"venue"
},
  "geometry": {"coordinates":[145.892639,-41.045738],"type":"Point"}
}