{
  "type": "Feature",
  "properties": {
    "iso:country":"AU",
    "sg:address":"443 Whitehorse Rd",
    "sg:city":"Mitcham",
    "sg:classifiers":[
        {
            "category":"Fast Food",
            "type":"Food & Drink"
        }
    ],
    "sg:phone":"+61 3 9874 6308",
    "sg:postcode":"3132",
    "sg:province":"VIC",
    "sg:tags":[
        "away",
        "take"
    ],
    "wof:name":"Cafe Mitch",
    "wof:placetype":"venue"
},
  "geometry": {"coordinates":[145.18809509299999,-37.8168182373],"type":"Point"}
}