{
  "type": "Feature",
  "properties": {
    "iso:country":"AU",
    "sg:address":"4 Ross Pl",
    "sg:city":"South Melbourne",
    "sg:classifiers":[
        {
            "category":"Organizations",
            "subcategory":"Professional Association",
            "type":"Services"
        }
    ],
    "sg:phone":"+61 3 8696 4999",
    "sg:postcode":"3205",
    "sg:province":"VIC",
    "sg:tags":[
        "web",
        "internet"
    ],
    "wof:name":"Thinkred Pty Ltd",
    "wof:placetype":"venue"
},
  "geometry": {"coordinates":[144.959045,-37.830162],"type":"Point"}
}