{
  "type": "Feature",
  "properties": {
    "addr:full":"55 Cowell St Dora Creek NSW 2264",
    "addr:housenumber":"55",
    "addr:postcode":"2264",
    "addr:street":"Cowell St Dora",
    "iso:country":"AU",
    "sg:address":"55 Cowell St",
    "sg:city":"Dora Creek",
    "sg:classifiers":[
        {
            "category":"Professional",
            "subcategory":"Art Services",
            "type":"Services"
        }
    ],
    "sg:phone":"+61 418 226 546",
    "sg:postcode":"2264",
    "sg:province":"NSW",
    "sg:tags":[
        "decorator",
        "painter"
    ],
    "wof:name":"Lifestyle Painters & Decorators Pty Ltd",
    "wof:placetype":"venue"
},
  "geometry": {"coordinates":[151.50389100000001,-33.087929],"type":"Point"}
}