{
  "type": "Feature",
  "properties": {
    "addr:full":"2/ 32 Lawrence St Freshwater NSW 2096",
    "addr:housenumber":"/ 32",
    "addr:postcode":"2096",
    "addr:street":"Lawrence St",
    "iso:country":"AU",
    "sg:address":"2/ 32 Lawrence St",
    "sg:city":"Freshwater",
    "sg:classifiers":[
        {
            "category":"Health Services",
            "subcategory":"Chiropractor",
            "type":"Services"
        }
    ],
    "sg:phone":"+61 2 9939 8817",
    "sg:postcode":"2096",
    "sg:province":"NSW",
    "wof:name":"Fitzgerald Aaron",
    "wof:placetype":"venue"
},
  "geometry": {"coordinates":[151.28364563,-33.7789077759],"type":"Point"}
}