{
  "type": "Feature",
  "properties": {
    "addr:full":"Shop 132 Cairns Central Shopng Cntr Cairns QLD 4870",
    "addr:housenumber":"132",
    "addr:postcode":"4870",
    "iso:country":"AU",
    "sg:address":"Shop 132 Cairns Central Shopng Cntr",
    "sg:city":"Cairns",
    "sg:classifiers":[
        {
            "category":"Shopping",
            "subcategory":"Clothing, Apparel, & Fashions",
            "type":"Retail Goods"
        }
    ],
    "sg:phone":"+61 7 4031 5916",
    "sg:postcode":"4870",
    "sg:province":"QLD",
    "sg:tags":[
        "menswear"
    ],
    "wof:name":"Lowes Menswear",
    "wof:placetype":"venue"
},
  "geometry": {"coordinates":[145.77328491200001,-16.9223003387],"type":"Point"}
}