{
  "type": "Feature",
  "properties": {
    "iso:country":"AU",
    "sg:address":"8 Central St",
    "sg:city":"Mt Morgan",
    "sg:classifiers":[
        {
            "category":"Retail",
            "subcategory":"Storage",
            "type":"Services"
        }
    ],
    "sg:phone":"+61 7 4938 2607",
    "sg:postcode":"4714",
    "sg:province":"QLD",
    "wof:name":"A B Really Cheap Storage",
    "wof:placetype":"venue"
},
  "geometry": {"coordinates":[150.38723754899999,-23.6446056366],"type":"Point"}
}