{
  "type": "Feature",
  "properties": {
    "addr:full":"42 Spit Rd Mosman NSW 2088",
    "addr:housenumber":"42",
    "addr:postcode":"2088",
    "addr:street":"Spit Rd",
    "iso:country":"AU",
    "sg:address":"42 Spit Rd",
    "sg:city":"Mosman",
    "sg:classifiers":[
        {
            "category":"Home & Garden",
            "subcategory":"Building Materials",
            "type":"Retail Goods"
        }
    ],
    "sg:phone":"+61 2 9969 7031",
    "sg:postcode":"2088",
    "sg:province":"NSW",
    "sg:tags":[
        "merchant",
        "glass",
        "glazier"
    ],
    "wof:name":"Mosman Glass",
    "wof:placetype":"venue"
},
  "geometry": {"coordinates":[151.241912842,-33.8236694336],"type":"Point"}
}