{
  "type": "Feature",
  "properties": {
    "iso:country":"AU",
    "sg:address":"The Dome Centre, 1190 Burragorang Rd",
    "sg:city":"The Oaks",
    "sg:classifiers":[
        {
            "category":"Health Services",
            "subcategory":"Health Practitioner",
            "type":"Services"
        }
    ],
    "sg:phone":"+61 2 4657 2863",
    "sg:postcode":"2570",
    "sg:province":"NSW",
    "sg:tags":[
        "alternative"
    ],
    "wof:name":"Artscope Music & Management",
    "wof:placetype":"venue"
},
  "geometry": {"coordinates":[150.53692626899999,-34.0753822327],"type":"Point"}
}