{
  "type": "Feature",
  "properties": {
    "addr:full":"1/ 302 Victoria Rd Malaga WA 6090",
    "addr:housenumber":"/ 302",
    "addr:postcode":"6090",
    "addr:street":"Victoria Rd",
    "iso:country":"AU",
    "sg:address":"1/ 302 Victoria Rd",
    "sg:city":"Malaga",
    "sg:classifiers":[
        {
            "category":"Home & Garden",
            "subcategory":"Hardware",
            "type":"Retail Goods"
        }
    ],
    "sg:phone":"+61 8 9248 3838",
    "sg:postcode":"6090",
    "sg:province":"WA",
    "sg:tags":[
        "supply",
        "maker",
        "cabinet"
    ],
    "wof:name":"Artform Industries",
    "wof:placetype":"venue"
},
  "geometry": {"coordinates":[115.88938140899999,-31.8616752625],"type":"Point"}
}