{
  "type": "Feature",
  "properties": {
    "addr:full":"Factory 1, 23 Peel St Eltham VIC 3095",
    "addr:housenumber":"23",
    "addr:postcode":"3095",
    "addr:street":"Peel St",
    "iso:country":"AU",
    "sg:address":"Factory 1, 23 Peel St",
    "sg:city":"Eltham",
    "sg:classifiers":[
        {
            "category":"Retail",
            "subcategory":"Auto Repair",
            "type":"Services"
        }
    ],
    "sg:phone":"+61 3 9439 1819",
    "sg:postcode":"3095",
    "sg:province":"VIC",
    "sg:tags":[
        "repairer",
        "motor",
        "engineer"
    ],
    "wof:name":"Cochrane John R Motors",
    "wof:placetype":"venue"
},
  "geometry": {"coordinates":[145.140426636,-37.7200012207],"type":"Point"}
}