{
  "type": "Feature",
  "properties": {
    "addr:full":"3234 Mt Mee Rd Dayboro QLD 4521",
    "addr:housenumber":"3234",
    "addr:postcode":"4521",
    "addr:street":"Mt Mee Rd",
    "iso:country":"AU",
    "sg:address":"3234 Mt Mee Rd",
    "sg:city":"Dayboro",
    "sg:classifiers":[
        {
            "category":"Retail",
            "subcategory":"Event Space",
            "type":"Services"
        }
    ],
    "sg:phone":"+61 7 3425 1299",
    "sg:postcode":"4521",
    "sg:province":"QLD",
    "sg:tags":[
        "venue",
        "reception",
        "wedding"
    ],
    "wof:name":"Glengariff Historic Estate",
    "wof:placetype":"venue"
},
  "geometry": {"coordinates":[152.826187,-27.175556],"type":"Point"}
}