{
  "type": "Feature",
  "properties": {
    "iso:country":"AU",
    "sg:address":"3/ 113 Boat Harbour Drv",
    "sg:city":"Hervey Bay",
    "sg:classifiers":[
        {
            "category":"Autos & Motor Vehicles",
            "subcategory":"Automobile Sales",
            "type":"Retail Goods"
        }
    ],
    "sg:phone":"+61 7 4128 1336",
    "sg:postcode":"4655",
    "sg:province":"QLD",
    "sg:tags":[
        "car",
        "used"
    ],
    "wof:name":"Francos Cars & Commercials",
    "wof:placetype":"venue"
},
  "geometry": {"coordinates":[152.841553,-25.28878],"type":"Point"}
}