{
  "type": "Feature",
  "properties": {
    "addr:full":"DFO Centre, 1 Underwood Rd Homebush NSW 2140",
    "addr:housenumber":"1",
    "addr:postcode":"2140",
    "addr:street":"Underwood Rd",
    "iso:country":"AU",
    "sg:address":"DFO Centre, 1 Underwood Rd",
    "sg:city":"Homebush",
    "sg:classifiers":[
        {
            "category":"Shopping",
            "type":"Retail Goods"
        }
    ],
    "sg:phone":"+61 2 9764 6158",
    "sg:postcode":"2140",
    "sg:province":"NSW",
    "sg:tags":[
        "clearance",
        "factory",
        "outlet"
    ],
    "wof:name":"Seafolly Factory Outlet",
    "wof:placetype":"venue"
},
  "geometry": {"coordinates":[151.07786560100001,-33.8547363281],"type":"Point"}
}