{
  "type": "Feature",
  "properties": {
    "addr:full":"Buckaroo La Mudgee NSW 2850",
    "addr:postcode":"2850",
    "addr:street":"Buckaroo",
    "iso:country":"AU",
    "sg:address":"Buckaroo La",
    "sg:city":"Mudgee",
    "sg:classifiers":[
        {
            "category":"Manufacturing",
            "subcategory":"Rubber & Plastics",
            "type":"Manufacturing & Wholesale Goods"
        }
    ],
    "sg:phone":"+61 2 6373 3939",
    "sg:postcode":"2850",
    "sg:province":"NSW",
    "sg:tags":[
        "lime"
    ],
    "wof:name":"Mudgee Dolomite & Lime Pty Ltd",
    "wof:placetype":"venue"
},
  "geometry": {"coordinates":[149.63342299999999,-32.55899],"type":"Point"}
}