{
  "type": "Feature",
  "properties": {
    "addr:full":"3 Bearing Ave Warana QLD 4575",
    "addr:housenumber":"3",
    "addr:postcode":"4575",
    "addr:street":"Bearing Ave",
    "iso:country":"AU",
    "sg:address":"3 Bearing Ave",
    "sg:city":"Warana",
    "sg:classifiers":[
        {
            "category":"Professional",
            "subcategory":"Testing Lab",
            "type":"Services"
        }
    ],
    "sg:phone":"+61 7 5493 1733",
    "sg:postcode":"4575",
    "sg:province":"QLD",
    "sg:tags":[
        "soil",
        "investigation"
    ],
    "wof:name":"Geotech (S.C.) Pty Ltd",
    "wof:placetype":"venue"
},
  "geometry": {"coordinates":[153.12730400000001,-26.727613],"type":"Point"}
}