{
  "type": "Feature",
  "properties": {
    "iso:country":"AU",
    "sg:address":"Unit 2/ 132 Ross River Rd",
    "sg:city":"Mundingburra",
    "sg:classifiers":[
        {
            "category":"Health Services",
            "subcategory":"Doctor",
            "type":"Services"
        }
    ],
    "sg:phone":"+61 7 4728 3999",
    "sg:postcode":"4812",
    "sg:province":"QLD",
    "sg:tags":[
        "medical",
        "practitioner"
    ],
    "wof:name":"John Maguire",
    "wof:placetype":"venue"
},
  "geometry": {"coordinates":[146.782715,-19.295406],"type":"Point"}
}