{
  "type": "Feature",
  "properties": {
    "addr:full":"17 Brunel St Malvern East VIC 3145",
    "addr:housenumber":"17",
    "addr:postcode":"3145",
    "addr:street":"Brunel St",
    "iso:country":"AU",
    "sg:address":"17 Brunel St",
    "sg:city":"Malvern East",
    "sg:classifiers":[
        {
            "category":"Banks & Credit Unions",
            "subcategory":"Investment Brokerage",
            "type":"Services"
        }
    ],
    "sg:phone":"+61 3 9813 8875",
    "sg:postcode":"3145",
    "sg:province":"VIC",
    "sg:tags":[
        "management",
        "property"
    ],
    "wof:name":"Elyco Nominees Pty Ltd",
    "wof:placetype":"venue"
},
  "geometry": {"coordinates":[145.051513672,-37.869354248],"type":"Point"}
}