{
  "type": "Feature",
  "properties": {
    "iso:country":"AU",
    "sg:address":"265 Hunter St",
    "sg:city":"Newcastle",
    "sg:classifiers":[
        {
            "category":"Fast Food",
            "type":"Food & Drink"
        }
    ],
    "sg:phone":"+61 2 4926 3555",
    "sg:postcode":"2300",
    "sg:province":"NSW",
    "sg:tags":[
        "away",
        "take"
    ],
    "wof:name":"Surtaj Indian Restaurant",
    "wof:placetype":"venue"
},
  "geometry": {"coordinates":[151.77638200000001,-32.926662],"type":"Point"}
}