{
  "type": "Feature",
  "properties": {
    "addr:full":"Cnr Bermuda & Makeri Sts Mermaid Waters QLD 4218",
    "addr:postcode":"4218",
    "addr:street":"Cnr",
    "iso:country":"AU",
    "sg:address":"Cnr Bermuda & Makeri Sts",
    "sg:city":"Mermaid Waters",
    "sg:classifiers":[
        {
            "category":"Food & Beverages",
            "subcategory":"Supermarket",
            "type":"Retail Goods"
        }
    ],
    "sg:phone":"+61 7 5575 6839",
    "sg:postcode":"4218",
    "sg:province":"QLD",
    "sg:tags":[
        "grocery",
        "store"
    ],
    "wof:name":"Action Supermarkets",
    "wof:placetype":"venue"
},
  "geometry": {"coordinates":[153.408737183,-28.0359382629],"type":"Point"}
}