{
  "type": "Feature",
  "properties": {
    "iso:country":"AU",
    "sg:address":"105 Miller St",
    "sg:city":"North Sydney",
    "sg:classifiers":[
        {
            "category":"Fast Food",
            "type":"Food & Drink"
        }
    ],
    "sg:phone":"+61 2 9481 1111",
    "sg:postcode":"2059",
    "sg:province":"NSW",
    "sg:tags":[
        "away",
        "take"
    ],
    "wof:name":"Pizza Hut",
    "wof:placetype":"venue"
},
  "geometry": {"coordinates":[151.207077,-33.838749],"type":"Point"}
}