{
  "type": "Feature",
  "properties": {
    "addr:full":"Toniazzo's La Myrtleford VIC 3737",
    "addr:postcode":"3737",
    "iso:country":"AU",
    "sg:address":"Toniazzo's La",
    "sg:city":"Myrtleford",
    "sg:classifiers":[
        {
            "category":"Wholesale",
            "subcategory":"Tobacco Products",
            "type":"Manufacturing & Wholesale Goods"
        }
    ],
    "sg:phone":"+61 3 5752 1515",
    "sg:postcode":"3737",
    "sg:province":"VIC",
    "sg:tags":[
        "grower"
    ],
    "wof:name":"Sella Enrico&Caterina",
    "wof:placetype":"venue"
},
  "geometry": {"coordinates":[146.703811645,-36.5637931824],"type":"Point"}
}