{
  "type": "Feature",
  "properties": {
    "addr:full":"PO Box 304 Herberton QLD 4872",
    "addr:postcode":"4872",
    "iso:country":"AU",
    "sg:address":"PO Box 304",
    "sg:city":"Herberton",
    "sg:classifiers":[
        {
            "category":"Manufacturing",
            "subcategory":"Tools & Machinery",
            "type":"Manufacturing & Wholesale Goods"
        }
    ],
    "sg:phone":"+61 7 4096 2737",
    "sg:postcode":"4872",
    "sg:province":"QLD",
    "sg:tags":[
        "earth",
        "excavating",
        "moving",
        "equipment"
    ],
    "wof:name":"Roscos Backoe Tipper Hire",
    "wof:placetype":"venue"
},
  "geometry": {"coordinates":[145.1068573,-17.9841003418],"type":"Point"}
}