{
  "type": "Feature",
  "properties": {
    "iso:country":"AU",
    "sg:address":"67 Main Rd",
    "sg:city":"Lower Plenty",
    "sg:classifiers":[
        {
            "category":"Food & Beverages",
            "subcategory":"Groceries & Convenience Stores",
            "type":"Retail Goods"
        }
    ],
    "sg:phone":"+61 3 9435 4256",
    "sg:postcode":"3093",
    "sg:province":"VIC",
    "wof:name":"Lower Plenty Milkbar & Post Office",
    "wof:placetype":"venue"
},
  "geometry": {"coordinates":[145.11204528799999,-37.727596283],"type":"Point"}
}