{
  "type": "Feature",
  "properties": {
    "addr:full":"18 Burleigh St Burwood NSW 2134",
    "addr:housenumber":"18",
    "addr:postcode":"2134",
    "addr:street":"Burleigh St",
    "iso:country":"AU",
    "sg:address":"18 Burleigh St",
    "sg:city":"Burwood",
    "sg:classifiers":[
        {
            "category":"Health Services",
            "subcategory":"Health Practitioner",
            "type":"Services"
        }
    ],
    "sg:phone":"+61 2 9747 2100",
    "sg:postcode":"2134",
    "sg:province":"NSW",
    "sg:tags":[
        "psychologist"
    ],
    "wof:name":"Khabbaz Antoine",
    "wof:placetype":"venue"
},
  "geometry": {"coordinates":[151.104736328,-33.878452301],"type":"Point"}
}