{
  "type": "Feature",
  "properties": {
    "iso:country":"AU",
    "sg:address":"PO Box 1293",
    "sg:city":"Geelong",
    "sg:classifiers":[
        {
            "category":"Utilities",
            "subcategory":"Water",
            "type":"Services"
        }
    ],
    "sg:phone":"+61 419 521 301",
    "sg:postcode":"3220",
    "sg:province":"VIC",
    "sg:tags":[
        "hot",
        "system"
    ],
    "wof:name":"McKillop Plumbing & Gas Fitting",
    "wof:placetype":"venue"
},
  "geometry": {"coordinates":[144.346054,-38.157108],"type":"Point"}
}