{
  "type": "Feature",
  "properties": {
    "addr:full":"Unit 64, 47 Neridah St Chatswood NSW 2057",
    "addr:housenumber":"47",
    "addr:postcode":"2057",
    "addr:street":"Neridah St",
    "iso:country":"AU",
    "sg:address":"Unit 64, 47 Neridah St",
    "sg:city":"Chatswood",
    "sg:classifiers":[
        {
            "category":"Education",
            "subcategory":"University",
            "type":"Public Place"
        }
    ],
    "sg:phone":"+61 2 9412 3217",
    "sg:postcode":"2057",
    "sg:province":"NSW",
    "sg:tags":[
        "sewing",
        "dressmaking",
        "tuition"
    ],
    "wof:name":"The Janome Shop",
    "wof:placetype":"venue"
},
  "geometry": {"coordinates":[151.18768299999999,-33.796474],"type":"Point"}
}