{
  "type": "Feature",
  "properties": {
    "addr:full":"57 Duchess St Busselton WA 6280",
    "addr:housenumber":"57",
    "addr:postcode":"6280",
    "addr:street":"Duchess St",
    "iso:country":"AU",
    "sg:address":"57 Duchess St",
    "sg:city":"Busselton",
    "sg:classifiers":[
        {
            "category":"Banks & Credit Unions",
            "subcategory":"Financial Services",
            "type":"Services"
        }
    ],
    "sg:phone":"+61 8 9754 1003",
    "sg:postcode":"6280",
    "sg:province":"WA",
    "sg:tags":[
        "settlement",
        "nt",
        "agent",
        "wa"
    ],
    "wof:name":"Naturaliste Settlements",
    "wof:placetype":"venue"
},
  "geometry": {"coordinates":[115.344398498,-33.6487007141],"type":"Point"}
}