{
  "type": "Feature",
  "properties": {
    "iso:country":"AU",
    "sg:address":"21 Andy Poole Drv",
    "sg:city":"Tathra",
    "sg:classifiers":[
        {
            "category":"Building & Trades",
            "subcategory":"Construction",
            "type":"Services"
        }
    ],
    "sg:phone":"+61 417 203 464",
    "sg:postcode":"2550",
    "sg:province":"NSW",
    "sg:tags":[
        "pool",
        "swimming"
    ],
    "wof:name":"Tathra Concrete Pools",
    "wof:placetype":"venue"
},
  "geometry": {"coordinates":[149.97807312,-36.7234191895],"type":"Point"}
}