{
  "type": "Feature",
  "properties": {
    "iso:country":"AU",
    "sg:address":"83 Regent St",
    "sg:city":"New Lambton",
    "sg:classifiers":[
        {
            "category":"Health Services",
            "subcategory":"Doctor",
            "type":"Services"
        }
    ],
    "sg:phone":"+61 2 4957 3822",
    "sg:postcode":"2305",
    "sg:province":"NSW",
    "sg:tags":[
        "medical",
        "practitioner"
    ],
    "wof:name":"Ho Mary",
    "wof:placetype":"venue"
},
  "geometry": {"coordinates":[151.713577,-32.923069],"type":"Point"}
}