{
  "type": "Feature",
  "properties": {
    "iso:country":"AU",
    "sg:address":"97 Farrell St",
    "sg:city":"Perenjori",
    "sg:classifiers":[
        {
            "category":"Farming",
            "subcategory":"Farm & Veterinary Services",
            "type":"Manufacturing & Wholesale Goods"
        }
    ],
    "sg:phone":"+61 8 9973 1111",
    "sg:postcode":"6620",
    "sg:province":"WA",
    "sg:tags":[
        "contracting"
    ],
    "wof:name":"NDL Cropspraying",
    "wof:placetype":"venue"
},
  "geometry": {"coordinates":[116.28842926,-29.443359375],"type":"Point"}
}