{
  "type": "Feature",
  "properties": {
    "iso:country":"AU",
    "sg:address":"4/ 370 George St",
    "sg:city":"Brisbane",
    "sg:classifiers":[
        {
            "category":"Manufacturing",
            "subcategory":"Paper Products",
            "type":"Manufacturing & Wholesale Goods"
        }
    ],
    "sg:phone":"+61 7 3236 5066",
    "sg:postcode":"4000",
    "sg:province":"QLD",
    "sg:tags":[
        "machine",
        "shredding",
        "cutting"
    ],
    "wof:name":"Business Machinery Rentals Inc. Stott & Underwood",
    "wof:placetype":"venue"
},
  "geometry": {"coordinates":[153.02134704599999,-27.4688720703],"type":"Point"}
}