{
  "type": "Feature",
  "properties": {
    "addr:full":"Shop 48/ 14 James Pl Adelaide SA 5000",
    "addr:housenumber":"shop 48 / 14",
    "addr:postcode":"5000",
    "addr:street":"James Pl",
    "iso:country":"AU",
    "sg:address":"Shop 48/ 14 James Pl",
    "sg:city":"Adelaide",
    "sg:classifiers":[
        {
            "category":"Personal",
            "subcategory":"Beauty Salon",
            "type":"Services"
        }
    ],
    "sg:phone":"+61 8 8231 0031",
    "sg:postcode":"5000",
    "sg:province":"SA",
    "wof:name":"Citi Nails & Beauty",
    "wof:placetype":"venue"
},
  "geometry": {"coordinates":[138.60081481899999,-34.9232673645],"type":"Point"}
}