{
  "type": "Feature",
  "properties": {
    "iso:country":"AU",
    "sg:address":"27 Fadden St",
    "sg:city":"Walkerston",
    "sg:classifiers":[
        {
            "category":"Utilities",
            "subcategory":"Electric",
            "type":"Services"
        }
    ],
    "sg:phone":"+61 7 4959 2435",
    "sg:postcode":"4751",
    "sg:province":"QLD",
    "sg:tags":[
        "electrical",
        "contractor"
    ],
    "wof:name":"Hamilton J A & J M",
    "wof:placetype":"venue"
},
  "geometry": {"coordinates":[149.060059,-21.159367],"type":"Point"}
}