{
  "type": "Feature",
  "properties": {
    "iso:country":"AU",
    "sg:address":"49 Prince St",
    "sg:city":"Goulburn",
    "sg:classifiers":[
        {
            "category":"Home & Garden",
            "subcategory":"Carpets & Floor Coverings",
            "type":"Retail Goods"
        }
    ],
    "sg:phone":"+61 2 4821 9251",
    "sg:postcode":"2580",
    "sg:province":"NSW",
    "sg:tags":[
        "tile",
        "wall",
        "layer"
    ],
    "wof:name":"G & B Sully Tiling",
    "wof:placetype":"venue"
},
  "geometry": {"coordinates":[149.71675109899999,-34.7419166565],"type":"Point"}
}