{
  "type": "Feature",
  "properties": {
    "addr:full":"Lot 1 Kettering TAS 7155",
    "addr:postcode":"7155",
    "iso:country":"AU",
    "sg:address":"Lot 1",
    "sg:city":"Kettering",
    "sg:classifiers":[
        {
            "category":"Autos & Motor Vehicles",
            "subcategory":"Boat Sales",
            "type":"Retail Goods"
        }
    ],
    "sg:phone":"+61 413 765 984",
    "sg:postcode":"7155",
    "sg:province":"TAS",
    "sg:tags":[
        "builder",
        "yacht",
        "repairer"
    ],
    "wof:name":"Denman Marine Pty Ltd",
    "wof:placetype":"venue"
},
  "geometry": {"coordinates":[147.232254028,-43.1274108887],"type":"Point"}
}