{
  "type": "Feature",
  "properties": {
    "addr:full":"32 Union St Brunswick VIC 3056",
    "addr:housenumber":"32",
    "addr:postcode":"3056",
    "addr:street":"Union St",
    "iso:country":"AU",
    "sg:address":"32 Union St",
    "sg:city":"Brunswick",
    "sg:classifiers":[
        {
            "category":"Professional",
            "subcategory":"Printing & Photocopies",
            "type":"Services"
        }
    ],
    "sg:phone":"+61 3 9380 2411",
    "sg:postcode":"3056",
    "sg:province":"VIC",
    "sg:tags":[
        "publishing",
        "desktop"
    ],
    "wof:name":"P M S Lithography Pty Ltd",
    "wof:placetype":"venue"
},
  "geometry": {"coordinates":[144.95924377399999,-37.7739105225],"type":"Point"}
}