{
  "type": "Feature",
  "properties": {
    "iso:country":"AU",
    "sg:address":"321 Moreland Rd",
    "sg:city":"Coburg",
    "sg:classifiers":[
        {
            "category":"Home & Garden",
            "subcategory":"Building Materials",
            "type":"Retail Goods"
        }
    ],
    "sg:phone":"+61 3 9383 1408",
    "sg:postcode":"3058",
    "sg:province":"VIC",
    "sg:tags":[
        "merchant",
        "glass",
        "glazier"
    ],
    "wof:name":"George's K Glass Repairs",
    "wof:placetype":"venue"
},
  "geometry": {"coordinates":[144.954315186,-37.7541236877],"type":"Point"}
}