{
  "type": "Feature",
  "properties": {
    "addr:full":"15 Woodvale Rd Boronia VIC 3155",
    "addr:housenumber":"15",
    "addr:postcode":"3155",
    "addr:street":"Woodvale Rd",
    "iso:country":"AU",
    "sg:address":"15 Woodvale Rd",
    "sg:city":"Boronia",
    "sg:classifiers":[
        {
            "category":"Building & Trades",
            "subcategory":"Construction",
            "type":"Services"
        }
    ],
    "sg:phone":"+61 3 9779 0041",
    "sg:postcode":"3155",
    "sg:province":"VIC",
    "sg:tags":[
        "contractor"
    ],
    "wof:name":"Homestyle Extensions",
    "wof:placetype":"venue"
},
  "geometry": {"coordinates":[145.276687622,-37.864200592],"type":"Point"}
}