{
  "type": "Feature",
  "properties": {
    "iso:country":"AU",
    "sg:address":"9 Rutherford St",
    "sg:city":"Swan Hill",
    "sg:classifiers":[
        {
            "category":"Utilities",
            "subcategory":"Natural Gas",
            "type":"Services"
        }
    ],
    "sg:phone":"+61 3 5032 9333",
    "sg:postcode":"3585",
    "sg:province":"VIC",
    "sg:tags":[
        "supplier"
    ],
    "wof:name":"Mid-Murray Gas & Outdoor",
    "wof:placetype":"venue"
},
  "geometry": {"coordinates":[143.561172,-35.342865],"type":"Point"}
}