{
  "type": "Feature",
  "properties": {
    "addr:full":"Fernvale-Marburg Rd Fernvale QLD 4306",
    "addr:postcode":"4306",
    "addr:street":"Fernvale-Marburg Rd",
    "iso:country":"AU",
    "sg:address":"Fernvale-Marburg Rd",
    "sg:city":"Fernvale",
    "sg:classifiers":[
        {
            "category":"Home & Garden",
            "subcategory":"Garden Supply",
            "type":"Retail Goods"
        }
    ],
    "sg:phone":"+61 7 5426 6155",
    "sg:postcode":"4306",
    "sg:province":"QLD",
    "sg:tags":[
        "landscape"
    ],
    "wof:name":"Country Turf Supplies Pty Ltd",
    "wof:placetype":"venue"
},
  "geometry": {"coordinates":[152.62654113799999,-27.511346817],"type":"Point"}
}