{
  "type": "Feature",
  "properties": {
    "addr:full":"Bayswater Rd Mt Louisa QLD 4814",
    "addr:postcode":"4814",
    "addr:street":"Bayswater Rd",
    "iso:country":"AU",
    "sg:address":"Bayswater Rd",
    "sg:city":"Mt Louisa",
    "sg:classifiers":[
        {
            "category":"Government",
            "subcategory":"City Hall",
            "type":"Public Place"
        }
    ],
    "sg:phone":"+61 7 4774 7192",
    "sg:postcode":"4814",
    "sg:province":"QLD",
    "wof:name":"Brothers TSV Football Club Inc",
    "wof:placetype":"venue"
},
  "geometry": {"coordinates":[146.74156199999999,-19.271032],"type":"Point"}
}