{
  "type": "Feature",
  "properties": {
    "iso:country":"AU",
    "sg:address":"PO Box 5005",
    "sg:city":"Heathwood",
    "sg:classifiers":[
        {
            "category":"Education",
            "subcategory":"Special Training",
            "type":"Public Place"
        }
    ],
    "sg:phone":"+61 3 9887 5555",
    "sg:postcode":"3134",
    "sg:province":"VIC",
    "sg:tags":[
        "development"
    ],
    "wof:name":"Savante Sales Solutions",
    "wof:placetype":"venue"
},
  "geometry": {"coordinates":[145.225540161,-37.8326301575],"type":"Point"}
}