{
  "type": "Feature",
  "properties": {
    "iso:country":"AU",
    "sg:address":"Level 1 264 King St",
    "sg:city":"Newtown",
    "sg:classifiers":[
        {
            "category":"Shopping",
            "subcategory":"Discount & Variety Stores",
            "type":"Retail Goods"
        }
    ],
    "sg:phone":"+61 2 9557 0122",
    "sg:postcode":"2042",
    "sg:province":"NSW",
    "sg:tags":[
        "shop",
        "adult"
    ],
    "wof:name":"MaXXX Black",
    "wof:placetype":"venue"
},
  "geometry": {"coordinates":[151.181,-33.896042],"type":"Point"}
}