{
  "type": "Feature",
  "properties": {
    "addr:full":"31 Cara Rd Highton VIC 3216",
    "addr:housenumber":"31",
    "addr:postcode":"3216",
    "addr:street":"Cara Rd",
    "iso:country":"AU",
    "sg:address":"31 Cara Rd",
    "sg:city":"Highton",
    "sg:classifiers":[
        {
            "category":"Taxi",
            "type":"Transportation"
        }
    ],
    "sg:phone":"+61 415 345 000",
    "sg:postcode":"3216",
    "sg:province":"VIC",
    "sg:tags":[
        "truck"
    ],
    "wof:name":"Midland Mini Freight",
    "wof:placetype":"venue"
},
  "geometry": {"coordinates":[144.32307434099999,-38.164981842],"type":"Point"}
}