{
  "type": "Feature",
  "properties": {
    "iso:country":"AU",
    "sg:address":"375 Yaamba Rd",
    "sg:city":"North Rockhampton",
    "sg:classifiers":[
        {
            "category":"Home & Garden",
            "subcategory":"Carpets & Floor Coverings",
            "type":"Retail Goods"
        }
    ],
    "sg:phone":"+61 7 4926 2622",
    "sg:postcode":"4701",
    "sg:province":"QLD",
    "sg:tags":[
        "mattress"
    ],
    "wof:name":"Snooze",
    "wof:placetype":"venue"
},
  "geometry": {"coordinates":[150.522018433,-23.3469104767],"type":"Point"}
}