{
  "type": "Feature",
  "properties": {
    "iso:country":"AU",
    "sg:address":"4 Lyndoch Crs",
    "sg:city":"Duncraig",
    "sg:classifiers":[
        {
            "category":"Building & Trades",
            "subcategory":"Construction",
            "type":"Services"
        }
    ],
    "sg:phone":"+61 8 9447 8409",
    "sg:postcode":"6023",
    "sg:province":"WA",
    "sg:tags":[
        "contractor"
    ],
    "wof:name":"Stambulich Chas",
    "wof:placetype":"venue"
},
  "geometry": {"coordinates":[115.778648377,-31.8311500549],"type":"Point"}
}