{
  "type": "Feature",
  "properties": {
    "addr:full":"262 Belmore Rd Riverwood NSW 2210",
    "addr:housenumber":"262",
    "addr:postcode":"2210",
    "addr:street":"Belmore Rd",
    "iso:country":"AU",
    "sg:address":"262 Belmore Rd",
    "sg:city":"Riverwood",
    "sg:classifiers":[
        {
            "category":"Autos & Motor Vehicles",
            "subcategory":"Auto Supplies",
            "type":"Retail Goods"
        }
    ],
    "sg:phone":"+61 2 9534 4188",
    "sg:postcode":"2210",
    "sg:province":"NSW",
    "sg:tags":[
        "accessory"
    ],
    "wof:name":"Autopro",
    "wof:placetype":"venue"
},
  "geometry": {"coordinates":[151.05264299999999,-33.949764],"type":"Point"}
}