{
  "type": "Feature",
  "properties": {
    "iso:country":"AU",
    "sg:address":"2 Grose St",
    "sg:city":"Leura",
    "sg:classifiers":[
        {
            "category":"Social Services",
            "type":"Services"
        }
    ],
    "sg:phone":"+61 2 4784 3971",
    "sg:postcode":"2780",
    "sg:province":"NSW",
    "sg:tags":[
        "disabled",
        "person",
        "equipment"
    ],
    "wof:name":"Megalong Positioning Service",
    "wof:placetype":"venue"
},
  "geometry": {"coordinates":[150.333374023,-33.712310791],"type":"Point"}
}