{
  "type": "Feature",
  "properties": {
    "addr:full":"286 South Cathedral La Buxton VIC 3711",
    "addr:housenumber":"286",
    "addr:postcode":"3711",
    "addr:street":"South Cathedral La",
    "iso:country":"AU",
    "sg:address":"286 South Cathedral La",
    "sg:city":"Buxton",
    "sg:classifiers":[
        {
            "category":"Farming",
            "subcategory":"Farm",
            "type":"Manufacturing & Wholesale Goods"
        }
    ],
    "sg:phone":"+61 3 5774 7316",
    "sg:postcode":"3711",
    "sg:province":"VIC",
    "sg:tags":[
        "farmer"
    ],
    "wof:name":"Cureton P",
    "wof:placetype":"venue"
},
  "geometry": {"coordinates":[145.72525024399999,-37.4128494263],"type":"Point"}
}