{
  "type": "Feature",
  "properties": {
    "addr:full":"14 Alpin St Cairns QLD 4870",
    "addr:housenumber":"14",
    "addr:postcode":"4870",
    "addr:street":"Alpin St",
    "iso:country":"AU",
    "sg:address":"14 Alpin St",
    "sg:city":"Cairns",
    "sg:classifiers":[
        {
            "category":"Personal",
            "type":"Services"
        }
    ],
    "sg:phone":"+61 7 4031 7144",
    "sg:postcode":"4870",
    "sg:province":"QLD",
    "sg:tags":[
        "career",
        "counselling"
    ],
    "wof:name":"Neato Employment Services",
    "wof:placetype":"venue"
},
  "geometry": {"coordinates":[145.77339172399999,-16.9209842682],"type":"Point"}
}