{
  "type": "Feature",
  "properties": {
    "iso:country":"AU",
    "sg:address":"28 Elizabeth St",
    "sg:city":"Paddington",
    "sg:classifiers":[
        {
            "category":"Manufacturing",
            "subcategory":"Wood Products",
            "type":"Manufacturing & Wholesale Goods"
        }
    ],
    "sg:phone":"+61 2 9331 3843",
    "sg:postcode":"2021",
    "sg:province":"NSW",
    "sg:tags":[
        "polisher",
        "french"
    ],
    "wof:name":"E J White French Polishing",
    "wof:placetype":"venue"
},
  "geometry": {"coordinates":[151.23124694800001,-33.8870124817],"type":"Point"}
}