{
  "type": "Feature",
  "properties": {
    "addr:full":"35 Markwell St Auchenflower QLD 4066",
    "addr:housenumber":"35",
    "addr:postcode":"4066",
    "addr:street":"Markwell St",
    "iso:country":"AU",
    "sg:address":"35 Markwell St",
    "sg:city":"Auchenflower",
    "sg:classifiers":[
        {
            "category":"Real Estate",
            "subcategory":"Architect",
            "type":"Services"
        }
    ],
    "sg:phone":"+61 7 3871 2133",
    "sg:postcode":"4066",
    "sg:province":"QLD",
    "wof:name":"Steffen Tuck Interior Architecture",
    "wof:placetype":"venue"
},
  "geometry": {"coordinates":[152.990356445,-27.4751834869],"type":"Point"}
}