{
  "type": "Feature",
  "properties": {
    "addr:full":"19 Main Rd Hahndorf SA 5245",
    "addr:housenumber":"19",
    "addr:postcode":"5245",
    "addr:street":"Main Rd",
    "iso:country":"AU",
    "sg:address":"19 Main Rd",
    "sg:city":"Hahndorf",
    "sg:classifiers":[
        {
            "category":"Shopping",
            "subcategory":"Jewelry",
            "type":"Retail Goods"
        }
    ],
    "sg:phone":"+61 8 8388 7343",
    "sg:postcode":"5245",
    "sg:province":"SA",
    "sg:tags":[
        "fashion",
        "jewellery"
    ],
    "wof:name":"Indira's Cottage Emporium",
    "wof:placetype":"venue"
},
  "geometry": {"coordinates":[138.80992126500001,-35.029296875],"type":"Point"}
}