{
  "type": "Feature",
  "properties": {
    "addr:full":"Guilford Drv Doncaster East VIC 3109",
    "addr:postcode":"3109",
    "addr:street":"Guilford Drv",
    "iso:country":"AU",
    "sg:address":"Guilford Drv",
    "sg:city":"Doncaster East",
    "sg:classifiers":[
        {
            "category":"Government",
            "subcategory":"Court House",
            "type":"Public Place"
        }
    ],
    "sg:phone":"+61 419 554 854",
    "sg:postcode":"3109",
    "sg:province":"VIC",
    "sg:tags":[
        "personal",
        "marriage",
        "family",
        "counselling"
    ],
    "wof:name":"Mirella's Adult & Children's Counselling",
    "wof:placetype":"venue"
},
  "geometry": {"coordinates":[145.17706298799999,-37.7618637085],"type":"Point"}
}