{
  "type": "Feature",
  "properties": {
    "iso:country":"AU",
    "sg:address":"23 Bricknell Rd",
    "sg:city":"Attadale",
    "sg:classifiers":[
        {
            "category":"Shopping",
            "subcategory":"Clothing, Apparel, & Fashions",
            "type":"Retail Goods"
        }
    ],
    "sg:phone":"+61 8 9330 9963",
    "sg:postcode":"6156",
    "sg:province":"WA",
    "sg:tags":[
        "sample",
        "second",
        "clothing"
    ],
    "wof:name":"Sinnott, Gillian",
    "wof:placetype":"venue"
},
  "geometry": {"coordinates":[115.80783099999999,-32.028561],"type":"Point"}
}