{
  "type": "Feature",
  "properties": {
    "addr:full":"69 Remington Drv Dandenong VIC 3175",
    "addr:housenumber":"69",
    "addr:postcode":"3175",
    "addr:street":"Remington Drv",
    "iso:country":"AU",
    "sg:address":"69 Remington Drv",
    "sg:city":"Dandenong",
    "sg:classifiers":[
        {
            "category":"Commercial Area",
            "type":"Public Place"
        }
    ],
    "sg:phone":"+61 1300 372 662",
    "sg:postcode":"3175",
    "sg:province":"VIC",
    "sg:tags":[
        "heavy",
        "carrier"
    ],
    "wof:name":"Clayton Mobile Cranes Pty Ltd",
    "wof:placetype":"venue"
},
  "geometry": {"coordinates":[145.23028564399999,-38.0297889709],"type":"Point"}
}