{
  "type": "Feature",
  "properties": {
    "addr:full":"15 Brunswick Rd Mitcham VIC 3132",
    "addr:housenumber":"15",
    "addr:postcode":"3132",
    "addr:street":"Brunswick Rd",
    "iso:country":"AU",
    "sg:address":"15 Brunswick Rd",
    "sg:city":"Mitcham",
    "sg:classifiers":[
        {
            "category":"Social Services",
            "subcategory":"Child Care",
            "type":"Services"
        }
    ],
    "sg:phone":"+61 3 9872 3246",
    "sg:postcode":"3132",
    "sg:province":"VIC",
    "wof:name":"Mitcham Childrens Centre",
    "wof:placetype":"venue"
},
  "geometry": {"coordinates":[145.19590759299999,-37.8180274963],"type":"Point"}
}