{
  "type": "Feature",
  "properties": {
    "iso:country":"AU",
    "sg:address":"Suite 3/ 11 Railway St",
    "sg:city":"Chatswood",
    "sg:classifiers":[
        {
            "category":"Organizations",
            "subcategory":"Professional Association",
            "type":"Services"
        }
    ],
    "sg:phone":"+61 2 9415 1199",
    "sg:postcode":"2067",
    "sg:province":"NSW",
    "sg:tags":[
        "organisation",
        "business"
    ],
    "wof:name":"Liquor Merchants Association Of Australia Ltd",
    "wof:placetype":"venue"
},
  "geometry": {"coordinates":[151.180145264,-33.7937698364],"type":"Point"}
}