{
  "type": "Feature",
  "properties": {
    "iso:country":"AU",
    "sg:address":"520 Boorhaman Rd",
    "sg:city":"Dockers Plains",
    "sg:classifiers":[
        {
            "category":"Farming",
            "subcategory":"Farm",
            "type":"Manufacturing & Wholesale Goods"
        }
    ],
    "sg:phone":"+61 3 5721 5974",
    "sg:postcode":"3678",
    "sg:province":"VIC",
    "sg:tags":[
        "farmer"
    ],
    "wof:name":"Mc Donald B & A",
    "wof:placetype":"venue"
},
  "geometry": {"coordinates":[146.35078430199999,-36.3258285522],"type":"Point"}
}