{
  "type": "Feature",
  "properties": {
    "addr:full":"659 Old South Head St Rose Bay North NSW 2030",
    "addr:housenumber":"659",
    "addr:postcode":"2030",
    "addr:street":"Old South Head St",
    "iso:country":"AU",
    "sg:address":"659 Old South Head St",
    "sg:city":"Rose Bay North",
    "sg:classifiers":[
        {
            "category":"Food & Beverages",
            "subcategory":"Liquor & Beverages",
            "type":"Retail Goods"
        }
    ],
    "sg:phone":"+61 2 9371 6274",
    "sg:postcode":"2030",
    "sg:province":"NSW",
    "sg:tags":[
        "store"
    ],
    "wof:name":"Rose Bay North Cellars",
    "wof:placetype":"venue"
},
  "geometry": {"coordinates":[151.27838134800001,-33.8652458191],"type":"Point"}
}