{
  "type": "Feature",
  "properties": {
    "addr:full":"31 Anthony St Ormond VIC 3204",
    "addr:housenumber":"31",
    "addr:postcode":"3204",
    "addr:street":"Anthony St",
    "iso:country":"AU",
    "sg:address":"31 Anthony St",
    "sg:city":"Ormond",
    "sg:classifiers":[
        {
            "category":"Professional",
            "subcategory":"Engineering",
            "type":"Services"
        }
    ],
    "sg:phone":"+61 3 9576 9755",
    "sg:postcode":"3204",
    "sg:province":"VIC",
    "sg:tags":[
        "electronic",
        "engineer"
    ],
    "wof:name":"NF Communications Pty Ltd",
    "wof:placetype":"venue"
},
  "geometry": {"coordinates":[145.03689600000001,-37.904984],"type":"Point"}
}