{
  "type": "Feature",
  "properties": {
    "iso:country":"AU",
    "sg:address":"PO Box 1005",
    "sg:city":"Gympie",
    "sg:classifiers":[
        {
            "category":"Military Area",
            "subcategory":"Army Base",
            "type":"Public Place"
        }
    ],
    "sg:phone":"+61 415 708 568",
    "sg:postcode":"4570",
    "sg:province":"QLD",
    "sg:tags":[
        "concrete",
        "slab",
        "floor"
    ],
    "wof:name":"Cutdrill Concrete Services",
    "wof:placetype":"venue"
},
  "geometry": {"coordinates":[152.65736389200001,-26.1891593933],"type":"Point"}
}