{
  "type": "Feature",
  "properties": {
    "iso:country":"AU",
    "sg:address":"64 Dudley St",
    "sg:city":"Wallan",
    "sg:classifiers":[
        {
            "category":"Shopping",
            "subcategory":"Antiques",
            "type":"Retail Goods"
        }
    ],
    "sg:phone":"+61 410 070 636",
    "sg:postcode":"3756",
    "sg:province":"VIC",
    "sg:tags":[
        "restoration",
        "reproduction"
    ],
    "wof:name":"Frew & Son Antique Restoration & Furniture Polishing",
    "wof:placetype":"venue"
},
  "geometry": {"coordinates":[144.973862,-37.41293],"type":"Point"}
}