{
  "type": "Feature",
  "properties": {
    "iso:country":"AU",
    "sg:address":"7 Brigantine Pl",
    "sg:city":"Caves Beach",
    "sg:classifiers":[
        {
            "category":"Health Services",
            "subcategory":"Health Practitioner",
            "type":"Services"
        }
    ],
    "sg:phone":"+61 412 497 163",
    "sg:postcode":"2281",
    "sg:province":"NSW",
    "sg:tags":[
        "dietitian"
    ],
    "wof:name":"Intake Nutrition",
    "wof:placetype":"venue"
},
  "geometry": {"coordinates":[151.647750855,-33.101600647],"type":"Point"}
}