{
  "type": "Feature",
  "properties": {
    "iso:country":"AU",
    "sg:address":"124 McDowall St",
    "sg:city":"Roma",
    "sg:classifiers":[
        {
            "category":"Banks & Credit Unions",
            "subcategory":"Financial Services",
            "type":"Services"
        }
    ],
    "sg:phone":"+61 7 4622 6260",
    "sg:postcode":"4455",
    "sg:province":"QLD",
    "sg:tags":[
        "planning"
    ],
    "wof:name":"Hillross",
    "wof:placetype":"venue"
},
  "geometry": {"coordinates":[148.787353516,-26.5714511871],"type":"Point"}
}