{
  "type": "Feature",
  "properties": {
    "addr:full":"Shp6b/ 3 Ingleburn Rd Ingleburn NSW 2565",
    "addr:postcode":"2565",
    "addr:street":"Ingleburn Rd",
    "iso:country":"AU",
    "sg:address":"Shp6b/ 3 Ingleburn Rd",
    "sg:city":"Ingleburn",
    "sg:classifiers":[
        {
            "category":"Retail",
            "subcategory":"Laundry & Dry Cleaning",
            "type":"Services"
        }
    ],
    "sg:phone":"+61 2 9618 3777",
    "sg:postcode":"2565",
    "sg:province":"NSW",
    "sg:tags":[
        "manicurist"
    ],
    "wof:name":"Rose Nails",
    "wof:placetype":"venue"
},
  "geometry": {"coordinates":[150.86750793499999,-33.9958763123],"type":"Point"}
}