{
  "type": "Feature",
  "properties": {
    "iso:country":"AU",
    "sg:address":"27- 33 Park Rd",
    "sg:city":"Cheltenham",
    "sg:classifiers":[
        {
            "category":"Home & Garden",
            "subcategory":"Building Materials",
            "type":"Retail Goods"
        }
    ],
    "sg:phone":"+61 3 9584 4899",
    "sg:postcode":"3192",
    "sg:province":"VIC",
    "sg:tags":[
        "fitting",
        "door"
    ],
    "wof:name":"Spence Door Products",
    "wof:placetype":"venue"
},
  "geometry": {"coordinates":[145.041015625,-37.9634284973],"type":"Point"}
}