{
  "type": "Feature",
  "properties": {
    "iso:country":"AU",
    "sg:address":"ZFactory 3/96 98 Hallam South Rd",
    "sg:city":"Hallam",
    "sg:classifiers":[
        {
            "category":"Home & Garden",
            "subcategory":"Building Materials",
            "type":"Retail Goods"
        }
    ],
    "sg:phone":"+61 3 9705 8881",
    "sg:postcode":"3803",
    "sg:province":"VIC",
    "sg:tags":[
        "merchant",
        "glass",
        "glazier"
    ],
    "wof:name":"Clear View Glass & Glazing",
    "wof:placetype":"venue"
},
  "geometry": {"coordinates":[145.27069091800001,-38.0193061829],"type":"Point"}
}