{
  "type": "Feature",
  "properties": {
    "addr:full":"1385 Sydney Rd Fawkner VIC 3060",
    "addr:housenumber":"1385",
    "addr:postcode":"3060",
    "addr:street":"Sydney Rd",
    "iso:country":"AU",
    "sg:address":"1385 Sydney Rd",
    "sg:city":"Fawkner",
    "sg:classifiers":[
        {
            "category":"Autos & Motor Vehicles",
            "subcategory":"Automobile Sales",
            "type":"Retail Goods"
        }
    ],
    "sg:phone":"+61 3 9357 4447",
    "sg:postcode":"3060",
    "sg:province":"VIC",
    "sg:tags":[
        "car",
        "used"
    ],
    "wof:name":"Wagon Wheel Motors",
    "wof:placetype":"venue"
},
  "geometry": {"coordinates":[144.958526611,-37.6936798096],"type":"Point"}
}