{
  "type": "Feature",
  "properties": {
    "addr:full":"4 John Cawley Crs Woonona NSW 2517",
    "addr:housenumber":"4",
    "addr:postcode":"2517",
    "addr:street":"John Cawley Crs",
    "iso:country":"AU",
    "sg:address":"4 John Cawley Crs",
    "sg:city":"Woonona",
    "sg:classifiers":[
        {
            "category":"Building & Trades",
            "subcategory":"Construction",
            "type":"Services"
        }
    ],
    "sg:phone":"+61 2 4284 4227",
    "sg:postcode":"2517",
    "sg:province":"NSW",
    "sg:tags":[
        "contractor"
    ],
    "wof:name":"John Walker Building Contractors",
    "wof:placetype":"venue"
},
  "geometry": {"coordinates":[150.917236,-34.364635],"type":"Point"}
}