{
  "type": "Feature",
  "properties": {
    "iso:country":"AU",
    "sg:address":"128 Bishopsgate St",
    "sg:city":"Carlisle",
    "sg:classifiers":[
        {
            "category":"Education",
            "subcategory":"Special Training",
            "type":"Public Place"
        }
    ],
    "sg:phone":"+61 8 9470 2662",
    "sg:postcode":"6101",
    "sg:province":"WA",
    "sg:tags":[
        "development"
    ],
    "wof:name":"Realisations Consultancy Pty Ltd",
    "wof:placetype":"venue"
},
  "geometry": {"coordinates":[115.915290833,-31.9803695679],"type":"Point"}
}