{
  "type": "Feature",
  "properties": {
    "iso:country":"AU",
    "sg:address":"31 Stanley St",
    "sg:city":"Peakhurst",
    "sg:classifiers":[
        {
            "category":"Building & Trades",
            "subcategory":"Equipment Rental",
            "type":"Services"
        }
    ],
    "sg:phone":"+61 2 9533 9522",
    "sg:postcode":"2210",
    "sg:province":"NSW",
    "sg:tags":[
        "supply",
        "catering"
    ],
    "wof:name":"W & P Reedy Pty Ltd",
    "wof:placetype":"venue"
},
  "geometry": {"coordinates":[151.06337,-33.962482],"type":"Point"}
}