{
  "type": "Feature",
  "properties": {
    "addr:full":"234 Lygon St Brunswick East VIC 3057",
    "addr:housenumber":"234",
    "addr:postcode":"3057",
    "addr:street":"Lygon St",
    "iso:country":"AU",
    "sg:address":"234 Lygon St",
    "sg:city":"Brunswick East",
    "sg:classifiers":[
        {
            "category":"Retail",
            "subcategory":"Repair Shop",
            "type":"Services"
        }
    ],
    "sg:phone":"+61 3 9380 2999",
    "sg:postcode":"3057",
    "sg:province":"VIC",
    "sg:tags":[
        "upholsterer"
    ],
    "wof:name":"Clifton Upholstery",
    "wof:placetype":"venue"
},
  "geometry": {"coordinates":[144.97198486299999,-37.77110672],"type":"Point"}
}