{
  "type": "Feature",
  "properties": {
    "addr:full":"Lot 16, Tuggerah Corporate Cntr, 1 Bounty Cl Tuggerah NSW 2259",
    "addr:housenumber":"1",
    "addr:postcode":"2259",
    "addr:street":"Bounty Cl",
    "iso:country":"AU",
    "sg:address":"Lot 16, Tuggerah Corporate Cntr, 1 Bounty Cl",
    "sg:city":"Tuggerah",
    "sg:classifiers":[
        {
            "category":"Government",
            "subcategory":"Customs House",
            "type":"Public Place"
        }
    ],
    "sg:phone":"+61 2 4351 9699",
    "sg:postcode":"2259",
    "sg:province":"NSW",
    "sg:tags":[
        "title",
        "management",
        "stratum"
    ],
    "sg:website":"http://www.allstrataservices.com.au",
    "wof:name":"All Strata Services",
    "wof:placetype":"venue"
},
  "geometry": {"coordinates":[151.42619323700001,-33.3206825256],"type":"Point"}
}