{
  "type": "Feature",
  "properties": {
    "addr:full":"6 Ingestre Ave Shoalhaven Heads NSW 2535",
    "addr:housenumber":"6",
    "addr:postcode":"2535",
    "addr:street":"Ingestre Ave;Heads",
    "iso:country":"AU",
    "sg:address":"6 Ingestre Ave",
    "sg:city":"Shoalhaven Heads",
    "sg:classifiers":[
        {
            "category":"Building & Trades",
            "subcategory":"Construction",
            "type":"Services"
        }
    ],
    "sg:phone":"+61 2 4448 7360",
    "sg:postcode":"2535",
    "sg:province":"NSW",
    "sg:tags":[
        "contractor"
    ],
    "wof:name":"Urquhart G J & A S C",
    "wof:placetype":"venue"
},
  "geometry": {"coordinates":[150.737915039,-34.8502426147],"type":"Point"}
}