{
  "type": "Feature",
  "properties": {
    "iso:country":"AU",
    "sg:address":"Shop 4 Northam Blv",
    "sg:city":"Northam",
    "sg:classifiers":[
        {
            "category":"Fast Food",
            "type":"Food & Drink"
        }
    ],
    "sg:phone":"+61 8 9622 8200",
    "sg:postcode":"6401",
    "sg:province":"WA",
    "sg:tags":[
        "away",
        "take"
    ],
    "wof:name":"Subway Northam",
    "wof:placetype":"venue"
},
  "geometry": {"coordinates":[116.672973633,-31.6523208618],"type":"Point"}
}