{
  "type": "Feature",
  "properties": {
    "addr:full":"Shp23/ 60 Railway St Mudgeeraba QLD 4213",
    "addr:housenumber":"60",
    "addr:postcode":"4213",
    "addr:street":"Railway St",
    "iso:country":"AU",
    "sg:address":"Shp23/ 60 Railway St",
    "sg:city":"Mudgeeraba",
    "sg:classifiers":[
        {
            "category":"Professional",
            "subcategory":"Accounting & Tax Preparation",
            "type":"Services"
        }
    ],
    "sg:phone":"+61 7 5530 3011",
    "sg:postcode":"4213",
    "sg:province":"QLD",
    "sg:tags":[
        "accountant",
        "auditor"
    ],
    "wof:name":"A G Norman & Associates",
    "wof:placetype":"venue"
},
  "geometry": {"coordinates":[153.36526489299999,-28.0786247253],"type":"Point"}
}