{
  "type": "Feature",
  "properties": {
    "addr:full":"165 Franklin St Adelaide SA 5000",
    "addr:housenumber":"165",
    "addr:postcode":"5000",
    "addr:street":"Franklin St",
    "iso:country":"AU",
    "sg:address":"165 Franklin St",
    "sg:city":"Adelaide",
    "sg:classifiers":[
        {
            "category":"Organizations",
            "subcategory":"Professional Association",
            "type":"Services"
        }
    ],
    "sg:phone":"+61 8 8410 1938",
    "sg:postcode":"5000",
    "sg:province":"SA",
    "sg:tags":[
        "web",
        "internet"
    ],
    "sg:website":"http://www.dbgtechnologies.com.au",
    "wof:name":"DBG Technologies",
    "wof:placetype":"venue"
},
  "geometry": {"coordinates":[138.592926025,-34.9276504517],"type":"Point"}
}