{
  "type": "Feature",
  "properties": {
    "addr:full":"50 Whitney St Gladstone QLD 4680",
    "addr:housenumber":"50",
    "addr:postcode":"4680",
    "addr:street":"Whitney St",
    "iso:country":"AU",
    "sg:address":"50 Whitney St",
    "sg:city":"Gladstone",
    "sg:classifiers":[
        {
            "category":"Building & Trades",
            "subcategory":"Construction",
            "type":"Services"
        }
    ],
    "sg:phone":"+61 7 4979 3838",
    "sg:postcode":"4680",
    "sg:province":"QLD",
    "sg:tags":[
        "fencing",
        "contractor"
    ],
    "wof:name":"TJ's Fencing Qld Pty Ltd",
    "wof:placetype":"venue"
},
  "geometry": {"coordinates":[151.25355529800001,-23.8438205719],"type":"Point"}
}