{
  "type": "Feature",
  "properties": {
    "iso:country":"AU",
    "sg:address":"40 Scarborough St",
    "sg:city":"Monterey",
    "sg:classifiers":[
        {
            "category":"Shopping",
            "subcategory":"Computers & Home Electronics",
            "type":"Retail Goods"
        }
    ],
    "sg:phone":"+61 2 9588 1711",
    "sg:postcode":"2217",
    "sg:province":"NSW",
    "sg:tags":[
        "equipment",
        "multimedia"
    ],
    "wof:name":"Marvmedia",
    "wof:placetype":"venue"
},
  "geometry": {"coordinates":[151.147171,-33.975121],"type":"Point"}
}