{
  "type": "Feature",
  "properties": {
    "iso:country":"AU",
    "sg:address":"8 Peachtree Rd",
    "sg:city":"Penrith",
    "sg:classifiers":[
        {
            "category":"Manufacturing",
            "subcategory":"Rubber & Plastics",
            "type":"Manufacturing & Wholesale Goods"
        }
    ],
    "sg:phone":"+61 2 4731 5386",
    "sg:postcode":"2750",
    "sg:province":"NSW",
    "sg:tags":[
        "fabricator"
    ],
    "wof:name":"Cain's Glass Service Pty Ltd",
    "wof:placetype":"venue"
},
  "geometry": {"coordinates":[150.97265625,-33.7878074646],"type":"Point"}
}