{
  "type": "Feature",
  "properties": {
    "addr:full":"6 Kooluna Crt Frankston VIC 3199",
    "addr:housenumber":"6",
    "addr:postcode":"3199",
    "addr:street":"Kooluna Crt",
    "iso:country":"AU",
    "sg:address":"6 Kooluna Crt",
    "sg:city":"Frankston",
    "sg:classifiers":[
        {
            "category":"Home & Garden",
            "subcategory":"Building Materials",
            "type":"Retail Goods"
        }
    ],
    "sg:phone":"+61 3 9789 7890",
    "sg:postcode":"3199",
    "sg:province":"VIC",
    "sg:tags":[
        "restoration",
        "supply"
    ],
    "wof:name":"Burton Paul Tuckpointer",
    "wof:placetype":"venue"
},
  "geometry": {"coordinates":[145.164306641,-38.1353874207],"type":"Point"}
}