{
  "type": "Feature",
  "properties": {
    "addr:full":"4/35 O&#039;Malley St Osborne Park WA 6017",
    "addr:housenumber":"/ 35 o",
    "addr:postcode":"6017",
    "addr:street":"Malley St",
    "iso:country":"AU",
    "sg:address":"4/35 O&#039;Malley St",
    "sg:city":"Osborne Park",
    "sg:classifiers":[
        {
            "category":"Structure",
            "subcategory":"Tunnel",
            "type":"Public Place"
        }
    ],
    "sg:phone":"+61 8 9244 4050",
    "sg:postcode":"6017",
    "sg:province":"WA",
    "sg:tags":[
        "cleaner",
        "industrial",
        "vacuum"
    ],
    "wof:name":"Industrial Cleaning Equipment",
    "wof:placetype":"venue"
},
  "geometry": {"coordinates":[115.811706543,-31.9017314911],"type":"Point"}
}