{
  "type": "Feature",
  "properties": {
    "addr:full":"15 Wattle St West Ryde NSW 2114",
    "addr:housenumber":"15",
    "addr:postcode":"2114",
    "addr:street":"Wattle St",
    "iso:country":"AU",
    "sg:address":"15 Wattle St",
    "sg:city":"West Ryde",
    "sg:classifiers":[
        {
            "category":"Retail",
            "subcategory":"Car Wash",
            "type":"Services"
        }
    ],
    "sg:phone":"+61 414 343 986",
    "sg:postcode":"2114",
    "sg:province":"NSW",
    "sg:tags":[
        "truck",
        "cleaning"
    ],
    "wof:name":"Meguiars Trained Professional Car Detailer",
    "wof:placetype":"venue"
},
  "geometry": {"coordinates":[151.09323120100001,-33.8064994812],"type":"Point"}
}