{
  "type": "Feature",
  "properties": {
    "addr:full":"Toonang Drv Tea Gardens NSW 2324",
    "addr:postcode":"2324",
    "addr:street":"Toonang Drv",
    "iso:country":"AU",
    "sg:address":"Toonang Drv",
    "sg:city":"Tea Gardens",
    "sg:classifiers":[
        {
            "category":"Building & Trades",
            "subcategory":"Landscaping Services",
            "type":"Services"
        }
    ],
    "sg:phone":"+61 2 4997 1228",
    "sg:postcode":"2324",
    "sg:province":"NSW",
    "sg:tags":[
        "firebreak",
        "clearing",
        "land",
        "contractor"
    ],
    "wof:name":"Everitt B W",
    "wof:placetype":"venue"
},
  "geometry": {"coordinates":[152.14976501500001,-32.6414451599],"type":"Point"}
}