{
  "type": "Feature",
  "properties": {
    "iso:country":"AU",
    "sg:address":"340 Marmion St",
    "sg:city":"Melville",
    "sg:classifiers":[
        {
            "category":"Health Services",
            "subcategory":"Health Practitioner",
            "type":"Services"
        }
    ],
    "sg:phone":"+61 8 9330 6100",
    "sg:postcode":"6156",
    "sg:province":"WA",
    "sg:tags":[
        "physiotherapist"
    ],
    "wof:name":"Move Well Physiotherapy",
    "wof:placetype":"venue"
},
  "geometry": {"coordinates":[115.79921,-32.04385],"type":"Point"}
}