{
  "type": "Feature",
  "properties": {
    "addr:full":"310 Crown St Darlinghurst NSW 2010",
    "addr:housenumber":"310",
    "addr:postcode":"2010",
    "addr:street":"Crown St",
    "iso:country":"AU",
    "sg:address":"310 Crown St",
    "sg:city":"Darlinghurst",
    "sg:classifiers":[
        {
            "category":"Food & Beverages",
            "subcategory":"Bakery",
            "type":"Retail Goods"
        }
    ],
    "sg:phone":"+61 2 9361 6942",
    "sg:postcode":"2010",
    "sg:province":"NSW",
    "sg:tags":[
        "cake",
        "shop",
        "pastry"
    ],
    "wof:name":"Maltese Pastizzi Cafe",
    "wof:placetype":"venue"
},
  "geometry": {"coordinates":[151.21507263199999,-33.8806419373],"type":"Point"}
}