{
  "type": "Feature",
  "properties": {
    "addr:full":"3 Kenny Crt Legana TAS 7277",
    "addr:housenumber":"3",
    "addr:postcode":"7277",
    "addr:street":"Kenny Crt",
    "iso:country":"AU",
    "sg:address":"3 Kenny Crt",
    "sg:city":"Legana",
    "sg:classifiers":[
        {
            "category":"Shopping",
            "subcategory":"Computers & Home Electronics",
            "type":"Retail Goods"
        }
    ],
    "sg:phone":"+61 407 729 084",
    "sg:postcode":"7277",
    "sg:province":"TAS",
    "sg:tags":[
        "hardware",
        "equipment"
    ],
    "wof:name":"SG Speedy Computing",
    "wof:placetype":"venue"
},
  "geometry": {"coordinates":[147.03953552199999,-41.3653297424],"type":"Point"}
}