{
  "type": "Feature",
  "properties": {
    "addr:full":"6/ 47 Wyanbah Rd Cronulla NSW 2230",
    "addr:housenumber":"/ 47",
    "addr:postcode":"2230",
    "addr:street":"Wyanbah Rd",
    "iso:country":"AU",
    "sg:address":"6/ 47 Wyanbah Rd",
    "sg:city":"Cronulla",
    "sg:classifiers":[
        {
            "category":"Professional",
            "subcategory":"Art Services",
            "type":"Services"
        }
    ],
    "sg:phone":"+61 2 9527 7755",
    "sg:postcode":"2230",
    "sg:province":"NSW",
    "sg:tags":[
        "product",
        "industrial",
        "designer"
    ],
    "wof:name":"MPV Design",
    "wof:placetype":"venue"
},
  "geometry": {"coordinates":[151.15341186500001,-34.0472297668],"type":"Point"}
}