{
  "type": "Feature",
  "properties": {
    "addr:full":"5/ 61 Ourimbah Rd Tweed Heads NSW 2485",
    "addr:housenumber":"/ 61",
    "addr:postcode":"2485",
    "addr:street":"Ourimbah Rd",
    "iso:country":"AU",
    "sg:address":"5/ 61 Ourimbah Rd",
    "sg:city":"Tweed Heads",
    "sg:classifiers":[
        {
            "category":"Retail",
            "subcategory":"Storage",
            "type":"Services"
        }
    ],
    "sg:phone":"+61 7 5599 1600",
    "sg:postcode":"2485",
    "sg:province":"NSW",
    "sg:tags":[
        "removal",
        "furniture"
    ],
    "wof:name":"Tweed Valley Removals",
    "wof:placetype":"venue"
},
  "geometry": {"coordinates":[153.52813720699999,-28.1762237549],"type":"Point"}
}