{
  "type": "Feature",
  "properties": {
    "addr:full":"Wilson St Kalgoorlie WA 6430",
    "addr:postcode":"6430",
    "addr:street":"Wilson St",
    "iso:country":"AU",
    "sg:address":"Wilson St",
    "sg:city":"Kalgoorlie",
    "sg:classifiers":[
        {
            "category":"Education",
            "subcategory":"University",
            "type":"Public Place"
        }
    ],
    "sg:phone":"+61 8 9088 6600",
    "sg:postcode":"6430",
    "sg:province":"WA",
    "sg:tags":[
        "college",
        "tertiary"
    ],
    "wof:name":"Agricola Residential College",
    "wof:placetype":"venue"
},
  "geometry": {"coordinates":[121.468826294,-30.7478981018],"type":"Point"}
}