{
  "type": "Feature",
  "properties": {
    "addr:full":"Jamieson St Cardwell QLD 4849",
    "addr:postcode":"4849",
    "addr:street":"Jamieson St",
    "iso:country":"AU",
    "sg:address":"Jamieson St",
    "sg:city":"Cardwell",
    "sg:classifiers":[
        {
            "category":"Travel",
            "subcategory":"Hostel",
            "type":"Entertainment"
        }
    ],
    "sg:phone":"+61 7 4066 8518",
    "sg:postcode":"4849",
    "sg:province":"QLD",
    "sg:tags":[
        "home"
    ],
    "wof:name":"Rockingham Aged Care Facility",
    "wof:placetype":"venue"
},
  "geometry": {"coordinates":[146.01812699999999,-18.25412],"type":"Point"}
}