{
  "type": "Feature",
  "properties": {
    "iso:country":"AU",
    "sg:address":"27 Third Ave",
    "sg:city":"Jannali",
    "sg:classifiers":[
        {
            "category":"Building & Trades",
            "subcategory":"Plumbing",
            "type":"Services"
        }
    ],
    "sg:phone":"+61 2 9528 7715",
    "sg:postcode":"2226",
    "sg:province":"NSW",
    "sg:tags":[
        "plumber",
        "gasfitters"
    ],
    "wof:name":"Maidment J & D",
    "wof:placetype":"venue"
},
  "geometry": {"coordinates":[151.06890869099999,-34.0124778748],"type":"Point"}
}