{
  "type": "Feature",
  "properties": {
    "addr:full":"30 South Pine Rd Alderley QLD 4051",
    "addr:housenumber":"30",
    "addr:postcode":"4051",
    "addr:street":"South Pine Rd",
    "iso:country":"AU",
    "sg:address":"30 South Pine Rd",
    "sg:city":"Alderley",
    "sg:classifiers":[
        {
            "category":"Real Estate",
            "subcategory":"Real Estate Agent",
            "type":"Services"
        }
    ],
    "sg:phone":"+61 7 3366 0200",
    "sg:postcode":"4051",
    "sg:province":"QLD",
    "wof:name":"Anthony Storry Real Estate",
    "wof:placetype":"venue"
},
  "geometry": {"coordinates":[153.00030517600001,-27.4241867065],"type":"Point"}
}