{
  "type": "Feature",
  "properties": {
    "addr:full":"134 Parramatta Rd Camperdown NSW 2050",
    "addr:housenumber":"134",
    "addr:postcode":"2050",
    "addr:street":"Parramatta Rd",
    "iso:country":"AU",
    "sg:address":"134 Parramatta Rd",
    "sg:city":"Camperdown",
    "sg:classifiers":[
        {
            "category":"Utilities",
            "subcategory":"Electric",
            "type":"Services"
        }
    ],
    "sg:phone":"+61 2 9517 2888",
    "sg:postcode":"2050",
    "sg:province":"NSW",
    "sg:tags":[
        "electrical",
        "contractor"
    ],
    "wof:name":"Federal Electrical Pty Ltd",
    "wof:placetype":"venue"
},
  "geometry": {"coordinates":[151.17759699999999,-33.886414],"type":"Point"}
}