{
  "type": "Feature",
  "properties": {
    "addr:full":"9/840 Cnr Wembley Rd & Browns Plains Rd Browns Plains QLD 4118",
    "addr:housenumber":"/ 840",
    "addr:postcode":"4118",
    "addr:street":"Cnr Wembley Rd & Browns Plains Rd",
    "iso:country":"AU",
    "sg:address":"9/840 Cnr Wembley Rd & Browns Plains Rd",
    "sg:city":"Browns Plains",
    "sg:classifiers":[
        {
            "category":"Health Services",
            "subcategory":"Dentist",
            "type":"Services"
        }
    ],
    "sg:phone":"+61 1300 783 020",
    "sg:postcode":"4118",
    "sg:province":"QLD",
    "sg:tags":[
        "technician",
        "dental"
    ],
    "wof:name":"pro oral Dental Laboratory",
    "wof:placetype":"venue"
},
  "geometry": {"coordinates":[153.062576294,-27.6631603241],"type":"Point"}
}