{
  "type": "Feature",
  "properties": {
    "iso:country":"AU",
    "sg:address":"Ste402b/ 410 Elizabeth St",
    "sg:city":"Surry Hills",
    "sg:classifiers":[
        {
            "category":"Professional",
            "subcategory":"Engineering",
            "type":"Services"
        }
    ],
    "sg:phone":"+61 2 9281 6704",
    "sg:postcode":"2010",
    "sg:province":"NSW",
    "sg:tags":[
        "consulting",
        "engineer"
    ],
    "wof:name":"Outside The Square Engineers (OTSE)",
    "wof:placetype":"venue"
},
  "geometry": {"coordinates":[151.20840454099999,-33.8862571716],"type":"Point"}
}