{
  "type": "Feature",
  "properties": {
    "iso:country":"AU",
    "sg:address":"46 Robert St",
    "sg:city":"Rozelle",
    "sg:classifiers":[
        {
            "category":"Home & Garden",
            "subcategory":"Carpets & Floor Coverings",
            "type":"Retail Goods"
        }
    ],
    "sg:phone":"+61 413 834 805",
    "sg:postcode":"2039",
    "sg:province":"NSW",
    "sg:tags":[
        "material",
        "waterproofing"
    ],
    "wof:name":"Research Applied Technologies Pty Ltd",
    "wof:placetype":"venue"
},
  "geometry": {"coordinates":[151.178863525,-33.8651313782],"type":"Point"}
}