{
  "type": "Feature",
  "properties": {
    "addr:full":"204 Mason St Newport VIC 3015",
    "addr:housenumber":"204",
    "addr:postcode":"3015",
    "addr:street":"Mason St",
    "iso:country":"AU",
    "sg:address":"204 Mason St",
    "sg:city":"Newport",
    "sg:classifiers":[
        {
            "category":"Wholesale",
            "subcategory":"Machinery & Supplies",
            "type":"Manufacturing & Wholesale Goods"
        }
    ],
    "sg:phone":"+61 3 9391 7800",
    "sg:postcode":"3015",
    "sg:province":"VIC",
    "sg:tags":[
        "engineer"
    ],
    "wof:name":"A.S.A.P. Engineering Supplies Co Pty Ltd",
    "wof:placetype":"venue"
},
  "geometry": {"coordinates":[144.86555480999999,-37.8404083252],"type":"Point"}
}