{
  "type": "Feature",
  "properties": {
    "addr:full":"224 Queen St Southport QLD 4215",
    "addr:housenumber":"224",
    "addr:postcode":"4215",
    "addr:street":"Queen St",
    "iso:country":"AU",
    "sg:address":"224 Queen St",
    "sg:city":"Southport",
    "sg:classifiers":[
        {
            "category":"Social Services",
            "subcategory":"Child Care",
            "type":"Services"
        }
    ],
    "sg:phone":"+61 7 5528 6003",
    "sg:postcode":"4215",
    "sg:province":"QLD",
    "sg:website":"http://www.mykindy.net.au",
    "wof:name":"My Kindy",
    "wof:placetype":"venue"
},
  "geometry": {"coordinates":[153.39955139200001,-27.9709720612],"type":"Point"}
}