{
  "type": "Feature",
  "properties": {
    "addr:full":"259 Maitland Rd Cessnock NSW 2325",
    "addr:housenumber":"259",
    "addr:postcode":"2325",
    "addr:street":"Maitland Rd",
    "iso:country":"AU",
    "sg:address":"259 Maitland Rd",
    "sg:city":"Cessnock",
    "sg:classifiers":[
        {
            "category":"Health Services",
            "subcategory":"Doctor",
            "type":"Services"
        }
    ],
    "sg:phone":"+61 2 4991 4422",
    "sg:postcode":"2325",
    "sg:province":"NSW",
    "sg:tags":[
        "medical",
        "practitioner"
    ],
    "wof:name":"Dobler K",
    "wof:placetype":"venue"
},
  "geometry": {"coordinates":[151.36070251500001,-32.8297958374],"type":"Point"}
}