{
  "type": "Feature",
  "properties": {
    "iso:country":"AU",
    "sg:address":"45 Giddings St",
    "sg:city":"Geelong North",
    "sg:classifiers":[
        {
            "category":"Professional",
            "subcategory":"Engineering",
            "type":"Services"
        }
    ],
    "sg:phone":"+61 3 5278 5178",
    "sg:postcode":"3215",
    "sg:province":"VIC",
    "sg:tags":[
        "engineer"
    ],
    "wof:name":"Central Machining",
    "wof:placetype":"venue"
},
  "geometry": {"coordinates":[144.34535217300001,-38.1178703308],"type":"Point"}
}