{
  "type": "Feature",
  "properties": {
    "addr:full":"2 Foy Ave Figtree NSW 2525",
    "addr:housenumber":"2",
    "addr:postcode":"2525",
    "addr:street":"Foy Ave",
    "iso:country":"AU",
    "sg:address":"2 Foy Ave",
    "sg:city":"Figtree",
    "sg:classifiers":[
        {
            "category":"Real Estate",
            "subcategory":"Surveying",
            "type":"Services"
        }
    ],
    "sg:phone":"+61 409 287 315",
    "sg:postcode":"2525",
    "sg:province":"NSW",
    "sg:tags":[
        "surveyor",
        "land"
    ],
    "wof:name":"Andon Surveys",
    "wof:placetype":"venue"
},
  "geometry": {"coordinates":[150.844238281,-34.4320907593],"type":"Point"}
}