{
  "type": "Feature",
  "properties": {
    "addr:full":"Lot 2062 Rowlands Rd Collie WA 6225",
    "addr:housenumber":"2062",
    "addr:postcode":"6225",
    "addr:street":"Rowlands Rd",
    "iso:country":"AU",
    "sg:address":"Lot 2062 Rowlands Rd",
    "sg:city":"Collie",
    "sg:classifiers":[
        {
            "category":"Manufacturing",
            "subcategory":"Metals",
            "type":"Manufacturing & Wholesale Goods"
        }
    ],
    "sg:phone":"+61 8 9734 4141",
    "sg:postcode":"6225",
    "sg:province":"WA",
    "sg:tags":[
        "steel",
        "fabricator",
        "mfrs"
    ],
    "wof:name":"Collie Metal Fabrication Pty Ltd",
    "wof:placetype":"venue"
},
  "geometry": {"coordinates":[116.141899,-33.345821],"type":"Point"}
}