{
  "type": "Feature",
  "properties": {
    "iso:country":"AU",
    "sg:address":"11 Royal St",
    "sg:city":"Osborne Park",
    "sg:classifiers":[
        {
            "category":"Government",
            "subcategory":"City Hall",
            "type":"Public Place"
        }
    ],
    "sg:phone":"+61 8 9205 7600",
    "sg:postcode":"6017",
    "sg:province":"WA",
    "wof:name":"City of Stirling Community Recreation Centres",
    "wof:placetype":"venue"
},
  "geometry": {"coordinates":[115.82923889200001,-31.8964347839],"type":"Point"}
}