{
  "type": "Feature",
  "properties": {
    "addr:full":"68 School Rd Victoria Point QLD 4165",
    "addr:housenumber":"68",
    "addr:postcode":"4165",
    "addr:street":"School Rd",
    "iso:country":"AU",
    "sg:address":"68 School Rd",
    "sg:city":"Victoria Point",
    "sg:classifiers":[
        {
            "category":"Professional",
            "subcategory":"Employment Agencies",
            "type":"Services"
        }
    ],
    "sg:phone":"+61 7 3207 0777",
    "sg:postcode":"4165",
    "sg:province":"QLD",
    "sg:tags":[
        "entertainer",
        "agent"
    ],
    "wof:name":"AAA1 Victor The Great",
    "wof:placetype":"venue"
},
  "geometry": {"coordinates":[153.29782104500001,-27.576839447],"type":"Point"}
}