{
  "type": "Feature",
  "properties": {
    "iso:country":"AU",
    "sg:address":"57c Aerodrome Rd",
    "sg:city":"Maroochydore",
    "sg:classifiers":[
        {
            "category":"Sports & Exercise",
            "subcategory":"Gym",
            "type":"Entertainment"
        }
    ],
    "sg:phone":"+61 7 5451 0102",
    "sg:postcode":"4558",
    "sg:province":"QLD",
    "sg:tags":[
        "health",
        "fitness"
    ],
    "sg:website":"http://www.io-nz.com.au",
    "wof:name":"io Maroochydore",
    "wof:placetype":"venue"
},
  "geometry": {"coordinates":[153.099487305,-26.6597137451],"type":"Point"}
}