{
  "type": "Feature",
  "properties": {
    "iso:country":"AU",
    "sg:address":"Nebula St",
    "sg:city":"Sunshine Beach",
    "sg:classifiers":[
        {
            "category":"Building & Trades",
            "subcategory":"Construction",
            "type":"Services"
        }
    ],
    "sg:phone":"+61 7 5447 2241",
    "sg:postcode":"4567",
    "sg:province":"QLD",
    "sg:tags":[
        "ceiling"
    ],
    "wof:name":"Noosa Plasterers Pty Ltd",
    "wof:placetype":"venue"
},
  "geometry": {"coordinates":[153.104415894,-26.4020309448],"type":"Point"}
}