{
  "type": "Feature",
  "properties": {
    "iso:country":"AU",
    "sg:address":"PO Box 1609",
    "sg:city":"Toombul",
    "sg:classifiers":[
        {
            "category":"Building & Trades",
            "subcategory":"Construction",
            "type":"Services"
        }
    ],
    "sg:phone":"+61 7 3204 8438",
    "sg:postcode":"4012",
    "sg:province":"QLD",
    "sg:tags":[
        "polishing",
        "sanding",
        "floor"
    ],
    "wof:name":"O.M. (Gint) Smith",
    "wof:placetype":"venue"
},
  "geometry": {"coordinates":[153.05982971200001,-27.4076595306],"type":"Point"}
}