{
  "type": "Feature",
  "properties": {
    "addr:full":"5 Welsh Pl Landsdale WA 6065",
    "addr:housenumber":"5",
    "addr:postcode":"6065",
    "addr:street":"Welsh Pl",
    "iso:country":"AU",
    "sg:address":"5 Welsh Pl",
    "sg:city":"Landsdale",
    "sg:classifiers":[
        {
            "category":"Building & Trades",
            "subcategory":"Construction",
            "type":"Services"
        }
    ],
    "sg:phone":"+61 8 9302 1181",
    "sg:postcode":"6065",
    "sg:province":"WA",
    "sg:tags":[
        "scaffolding"
    ],
    "wof:name":"Scafmart",
    "wof:placetype":"venue"
},
  "geometry": {"coordinates":[115.845596313,-31.8032493591],"type":"Point"}
}