{
  "type": "Feature",
  "properties": {
    "addr:full":"14 Ada Ave Brookvale NSW 2100",
    "addr:housenumber":"14",
    "addr:postcode":"2100",
    "addr:street":"Ada Ave",
    "iso:country":"AU",
    "sg:address":"14 Ada Ave",
    "sg:city":"Brookvale",
    "sg:classifiers":[
        {
            "category":"Food & Beverages",
            "subcategory":"Bakery",
            "type":"Retail Goods"
        }
    ],
    "sg:phone":"+61 2 9905 7115",
    "sg:postcode":"2100",
    "sg:province":"NSW",
    "sg:tags":[
        "cake",
        "shop",
        "pastry"
    ],
    "wof:name":"Inter-Desserts",
    "wof:placetype":"venue"
},
  "geometry": {"coordinates":[151.27671814000001,-33.7668800354],"type":"Point"}
}