{
  "type": "Feature",
  "properties": {
    "iso:country":"AU",
    "sg:address":"37 Canopus St",
    "sg:city":"Southern Cross",
    "sg:classifiers":[
        {
            "category":"Fast Food",
            "type":"Food & Drink"
        }
    ],
    "sg:phone":"+61 8 9049 1339",
    "sg:postcode":"6426",
    "sg:province":"WA",
    "sg:tags":[
        "away",
        "take"
    ],
    "wof:name":"Southern Cross Roadhouse And Video",
    "wof:placetype":"venue"
},
  "geometry": {"coordinates":[119.32251,-31.232733],"type":"Point"}
}