{
  "type": "Feature",
  "properties": {
    "addr:full":"5/ 7 Expansion St Ashmore QLD 4214",
    "addr:housenumber":"/ 7",
    "addr:postcode":"4214",
    "addr:street":"Expansion St",
    "iso:country":"AU",
    "sg:address":"5/ 7 Expansion St",
    "sg:city":"Ashmore",
    "sg:classifiers":[
        {
            "category":"Building & Trades",
            "subcategory":"Construction",
            "type":"Services"
        }
    ],
    "sg:phone":"+61 7 5539 3696",
    "sg:postcode":"4214",
    "sg:province":"QLD",
    "sg:tags":[
        "contractor"
    ],
    "wof:name":"Burling Contracting Pty Ltd",
    "wof:placetype":"venue"
},
  "geometry": {"coordinates":[153.358764648,-27.9755382538],"type":"Point"}
}