{
  "type": "Feature",
  "properties": {
    "iso:country":"AU",
    "sg:address":"13 jeffro Pl",
    "sg:city":"Elermore Vale",
    "sg:classifiers":[
        {
            "category":"Commercial Area",
            "type":"Public Place"
        }
    ],
    "sg:phone":"+61 421 322 906",
    "sg:postcode":"2287",
    "sg:province":"NSW",
    "sg:tags":[
        "heavy",
        "carrier"
    ],
    "wof:name":"Compas Transport",
    "wof:placetype":"venue"
},
  "geometry": {"coordinates":[151.67257690400001,-32.9234657288],"type":"Point"}
}