{
  "type": "Feature",
  "properties": {
    "iso:country":"AU",
    "sg:address":"Level 2/ 30 Atchison St St",
    "sg:city":"Leonards",
    "sg:classifiers":[
        {
            "category":"Professional",
            "subcategory":"Accounting & Tax Preparation",
            "type":"Services"
        }
    ],
    "sg:phone":"+61 2 9439 4077",
    "sg:postcode":"2065",
    "sg:province":"NSW",
    "sg:tags":[
        "accountant",
        "auditor"
    ],
    "wof:name":"Fisher International Pty Ltd",
    "wof:placetype":"venue"
},
  "geometry": {"coordinates":[151.197463989,-33.8227577209],"type":"Point"}
}