{
  "type": "Feature",
  "properties": {
    "addr:full":"58 Wilgah St Balaclava VIC 3183",
    "addr:housenumber":"58",
    "addr:postcode":"3183",
    "addr:street":"Wilgah St",
    "iso:country":"AU",
    "sg:address":"58 Wilgah St",
    "sg:city":"Balaclava",
    "sg:classifiers":[
        {
            "category":"Professional",
            "subcategory":"Accounting & Tax Preparation",
            "type":"Services"
        }
    ],
    "sg:phone":"+61 3 9527 5770",
    "sg:postcode":"3183",
    "sg:province":"VIC",
    "sg:tags":[
        "consultant",
        "taxation"
    ],
    "wof:name":"Yoni Stein & Co",
    "wof:placetype":"venue"
},
  "geometry": {"coordinates":[145.00486755399999,-37.8634262085],"type":"Point"}
}