{
  "type": "Feature",
  "properties": {
    "iso:country":"AU",
    "sg:address":"5 Jayelem Crs",
    "sg:city":"Padstow",
    "sg:classifiers":[
        {
            "category":"Manufacturing",
            "subcategory":"Glass & Minerals",
            "type":"Manufacturing & Wholesale Goods"
        }
    ],
    "sg:phone":"+61 2 9792 7850",
    "sg:postcode":"2211",
    "sg:province":"NSW",
    "sg:tags":[
        "merchant",
        "granite",
        "marble"
    ],
    "wof:name":"Michael Marble & Granite Pty Ltd",
    "wof:placetype":"venue"
},
  "geometry": {"coordinates":[151.032394,-33.952171],"type":"Point"}
}