{
  "type": "Feature",
  "properties": {
    "iso:country":"AU",
    "sg:address":"Un 5, 38 Tennyson Memorial Ave",
    "sg:city":"Yeerongpilly",
    "sg:classifiers":[
        {
            "category":"Building & Trades",
            "subcategory":"Construction",
            "type":"Services"
        }
    ],
    "sg:phone":"+61 7 3255 9911",
    "sg:postcode":"4105",
    "sg:province":"QLD",
    "sg:tags":[
        "contractor"
    ],
    "wof:name":"Concorde Projects",
    "wof:placetype":"venue"
},
  "geometry": {"coordinates":[153.01101684599999,-27.5270233154],"type":"Point"}
}