{
  "type": "Feature",
  "properties": {
    "addr:full":"2/ 35 Sydenham Rd Brookvale NSW 2100",
    "addr:housenumber":"/ 35",
    "addr:postcode":"2100",
    "addr:street":"Sydenham Rd",
    "iso:country":"AU",
    "sg:address":"2/ 35 Sydenham Rd",
    "sg:city":"Brookvale",
    "sg:classifiers":[
        {
            "category":"Building & Trades",
            "subcategory":"Construction",
            "type":"Services"
        }
    ],
    "sg:phone":"+61 2 9907 3818",
    "sg:postcode":"2100",
    "sg:province":"NSW",
    "sg:tags":[
        "fencing",
        "contractor"
    ],
    "wof:name":"HQ Fencing",
    "wof:placetype":"venue"
},
  "geometry": {"coordinates":[151.27479553200001,-33.7643737793],"type":"Point"}
}