{
  "type": "Feature",
  "properties": {
    "addr:full":"74 Pascoe St Rochester VIC 3561",
    "addr:housenumber":"74",
    "addr:postcode":"3561",
    "addr:street":"Pascoe St",
    "iso:country":"AU",
    "sg:address":"74 Pascoe St",
    "sg:city":"Rochester",
    "sg:classifiers":[
        {
            "category":"Retail",
            "subcategory":"Auto Repair",
            "type":"Services"
        }
    ],
    "sg:phone":"+61 3 5484 2333",
    "sg:postcode":"3561",
    "sg:province":"VIC",
    "sg:tags":[
        "electrical"
    ],
    "wof:name":"Rochester Auto Electrics",
    "wof:placetype":"venue"
},
  "geometry": {"coordinates":[144.71774292000001,-36.3654022217],"type":"Point"}
}