{
  "type": "Feature",
  "properties": {
    "addr:full":"Shop 23, Gateway SV 230 Cranbourne Rd Langwarrin VIC 3910",
    "addr:housenumber":"shop 23;230",
    "addr:postcode":"3910",
    "addr:street":"Sv;Cranbourne Rd",
    "iso:country":"AU",
    "sg:address":"Shop 23, Gateway SV 230 Cranbourne Rd",
    "sg:city":"Langwarrin",
    "sg:classifiers":[
        {
            "category":"Health Services",
            "subcategory":"Optometrist",
            "type":"Services"
        }
    ],
    "sg:phone":"+61 3 9776 7702",
    "sg:postcode":"3910",
    "sg:province":"VIC",
    "wof:name":"Vision One Eyecare",
    "wof:placetype":"venue"
},
  "geometry": {"coordinates":[145.19543457,-38.1506347656],"type":"Point"}
}