{
  "type": "Feature",
  "properties": {
    "addr:full":"76 Palm Crest Heights Palm Meadow Drv Carrara QLD 4211",
    "addr:housenumber":"76",
    "addr:postcode":"4211",
    "addr:street":"Palm Crest Heights Palm Meadow Drv",
    "iso:country":"AU",
    "sg:address":"76 Palm Crest Heights Palm Meadow Drv",
    "sg:city":"Carrara",
    "sg:classifiers":[
        {
            "category":"Home & Garden",
            "subcategory":"Carpets & Floor Coverings",
            "type":"Retail Goods"
        }
    ],
    "sg:phone":"+61 7 5594 5810",
    "sg:postcode":"4211",
    "sg:province":"QLD",
    "sg:tags":[
        "layer",
        "planner"
    ],
    "wof:name":"A J Carpet Repairs",
    "wof:placetype":"venue"
},
  "geometry": {"coordinates":[153.36398315400001,-28.0106391907],"type":"Point"}
}