{
  "type": "Feature",
  "properties": {
    "iso:country":"AU",
    "sg:address":"50 Chapman St",
    "sg:city":"Swan Hill",
    "sg:classifiers":[
        {
            "category":"Education",
            "subcategory":"Kindergarten",
            "type":"Public Place"
        }
    ],
    "sg:phone":"+61 3 5032 3600",
    "sg:postcode":"3585",
    "sg:province":"VIC",
    "sg:tags":[
        "pre-schools"
    ],
    "wof:name":"Kunawaa Pre School",
    "wof:placetype":"venue"
},
  "geometry": {"coordinates":[143.55398600000001,-35.332973],"type":"Point"}
}