{
  "type": "Feature",
  "properties": {
    "addr:full":"2 Broad St Footscray West VIC 3012",
    "addr:housenumber":"2",
    "addr:postcode":"3012",
    "addr:street":"Broad St",
    "iso:country":"AU",
    "sg:address":"2 Broad St",
    "sg:city":"Footscray West",
    "sg:classifiers":[
        {
            "category":"Personal",
            "subcategory":"Beauty Salon",
            "type":"Services"
        }
    ],
    "sg:phone":"+61 3 9687 3747",
    "sg:postcode":"3012",
    "sg:province":"VIC",
    "sg:tags":[
        "hairdresser"
    ],
    "wof:name":"Amdies For Hair",
    "wof:placetype":"venue"
},
  "geometry": {"coordinates":[144.874801636,-37.7955818176],"type":"Point"}
}