{
  "type": "Feature",
  "properties": {
    "iso:country":"AU",
    "sg:address":"116 Crawford St",
    "sg:city":"Queanbeyan",
    "sg:classifiers":[
        {
            "category":"Professional",
            "subcategory":"Accounting & Tax Preparation",
            "type":"Services"
        }
    ],
    "sg:phone":"+61 2 6299 6210",
    "sg:postcode":"2620",
    "sg:province":"NSW",
    "sg:tags":[
        "accountant",
        "auditor"
    ],
    "wof:name":"Oliver Ian & Co",
    "wof:placetype":"venue"
},
  "geometry": {"coordinates":[149.229278564,-35.3464698792],"type":"Point"}
}