{
  "type": "Feature",
  "properties": {
    "addr:full":"Brookside Rd Athelstone SA 5076",
    "addr:postcode":"5076",
    "addr:street":"Brookside Rd",
    "iso:country":"AU",
    "sg:address":"Brookside Rd",
    "sg:city":"Athelstone",
    "sg:classifiers":[
        {
            "category":"Education",
            "subcategory":"School",
            "type":"Public Place"
        }
    ],
    "sg:phone":"+61 8 8337 3300",
    "sg:postcode":"5076",
    "sg:province":"SA",
    "sg:tags":[
        "state",
        "except",
        "nsw"
    ],
    "wof:name":"Athelstone Schools",
    "wof:placetype":"venue"
},
  "geometry": {"coordinates":[138.70094299300001,-34.8697547913],"type":"Point"}
}