{
  "type": "Feature",
  "properties": {
    "addr:full":"Walker Rd Wilga WA 6243",
    "addr:postcode":"6243",
    "addr:street":"Walker Rd",
    "iso:country":"AU",
    "sg:address":"Walker Rd",
    "sg:city":"Wilga",
    "sg:classifiers":[
        {
            "category":"Farming",
            "subcategory":"Farm",
            "type":"Manufacturing & Wholesale Goods"
        }
    ],
    "sg:phone":"+61 8 9766 1030",
    "sg:postcode":"6243",
    "sg:province":"WA",
    "sg:tags":[
        "farmer"
    ],
    "wof:name":"Charteris E N & P C",
    "wof:placetype":"venue"
},
  "geometry": {"coordinates":[116.229606628,-33.6950340271],"type":"Point"}
}