{
  "type": "Feature",
  "properties": {
    "addr:full":"47 Pearl St Kingscliff NSW 2487",
    "addr:housenumber":"47",
    "addr:postcode":"2487",
    "addr:street":"Pearl St",
    "iso:country":"AU",
    "sg:address":"47 Pearl St",
    "sg:city":"Kingscliff",
    "sg:classifiers":[
        {
            "category":"Real Estate",
            "subcategory":"Surveying",
            "type":"Services"
        }
    ],
    "sg:phone":"+61 2 6674 1891",
    "sg:postcode":"2487",
    "sg:province":"NSW",
    "sg:tags":[
        "surveyor",
        "land"
    ],
    "wof:name":"Buckman Mark",
    "wof:placetype":"venue"
},
  "geometry": {"coordinates":[153.574020386,-28.254108429],"type":"Point"}
}