{
  "type": "Feature",
  "properties": {
    "iso:country":"AU",
    "sg:address":"64 Newcastle St",
    "sg:city":"Morisset",
    "sg:classifiers":[
        {
            "category":"Personal",
            "subcategory":"Skin Care",
            "type":"Services"
        }
    ],
    "sg:phone":"+61 2 4973 1388",
    "sg:postcode":"2264",
    "sg:province":"NSW",
    "sg:tags":[
        "information",
        "treatment",
        "smoker"
    ],
    "wof:name":"Narelle Gordon",
    "wof:placetype":"venue"
},
  "geometry": {"coordinates":[151.48524499999999,-33.107578],"type":"Point"}
}