{
  "type": "Feature",
  "properties": {
    "iso:country":"AU",
    "sg:address":"Suite 10/ 205 Montague Rd",
    "sg:city":"South Brisbane",
    "sg:classifiers":[
        {
            "category":"Social Services",
            "subcategory":"Retirement Home",
            "type":"Services"
        }
    ],
    "sg:phone":"+61 7 3846 5133",
    "sg:postcode":"4101",
    "sg:province":"QLD",
    "sg:tags":[
        "environmental",
        "consultant",
        "pollution"
    ],
    "wof:name":"Water Technology Pty Ltd",
    "wof:placetype":"venue"
},
  "geometry": {"coordinates":[153.008422852,-27.4763660431],"type":"Point"}
}