{
  "type": "Feature",
  "properties": {
    "addr:full":"287 Main Rd Toukley NSW 2263",
    "addr:housenumber":"287",
    "addr:postcode":"2263",
    "addr:street":"Main Rd",
    "iso:country":"AU",
    "sg:address":"287 Main Rd",
    "sg:city":"Toukley",
    "sg:classifiers":[
        {
            "category":"Autos & Motor Vehicles",
            "subcategory":"Auto Supplies",
            "type":"Retail Goods"
        }
    ],
    "sg:phone":"+61 2 4396 3253",
    "sg:postcode":"2263",
    "sg:province":"NSW",
    "sg:tags":[
        "battery",
        "automotive"
    ],
    "wof:name":"Mobil Toukley",
    "wof:placetype":"venue"
},
  "geometry": {"coordinates":[151.54600500000001,-33.264843],"type":"Point"}
}