{
  "type": "Feature",
  "properties": {
    "addr:full":"4 Mayfield St Murwillumbah NSW 2484",
    "addr:housenumber":"4",
    "addr:postcode":"2484",
    "addr:street":"Mayfield St",
    "iso:country":"AU",
    "sg:address":"4 Mayfield St",
    "sg:city":"Murwillumbah",
    "sg:classifiers":[
        {
            "category":"Professional",
            "subcategory":"Engineering",
            "type":"Services"
        }
    ],
    "sg:phone":"+61 2 6672 1533",
    "sg:postcode":"2484",
    "sg:province":"NSW",
    "sg:tags":[
        "manufacturing",
        "engineer"
    ],
    "wof:name":"Dormer Engineering",
    "wof:placetype":"venue"
},
  "geometry": {"coordinates":[153.40985107399999,-28.3282337189],"type":"Point"}
}