{
  "type": "Feature",
  "properties": {
    "addr:full":"U4/ 17 Norwich Rd Ingleburn NSW 2565",
    "addr:housenumber":"17",
    "addr:postcode":"2565",
    "addr:street":"U4 /;Norwich Rd",
    "iso:country":"AU",
    "sg:address":"U4/ 17 Norwich Rd",
    "sg:city":"Ingleburn",
    "sg:classifiers":[
        {
            "category":"Professional",
            "type":"Services"
        }
    ],
    "sg:phone":"+61 2 9605 1200",
    "sg:postcode":"2565",
    "sg:province":"NSW",
    "sg:tags":[
        "coating",
        "powder"
    ],
    "wof:name":"C & D Powder Coating",
    "wof:placetype":"venue"
},
  "geometry": {"coordinates":[150.860305786,-33.9965705872],"type":"Point"}
}