{
  "type": "Feature",
  "properties": {
    "addr:full":"Shop 1, 64 Hunter St Brassall QLD 4305",
    "addr:housenumber":"shop;64",
    "addr:postcode":"4305",
    "addr:street":"Hunter St",
    "iso:country":"AU",
    "sg:address":"Shop 1, 64 Hunter St",
    "sg:city":"Brassall",
    "sg:classifiers":[
        {
            "category":"Food & Beverages",
            "subcategory":"Liquor & Beverages",
            "type":"Retail Goods"
        }
    ],
    "sg:phone":"+61 7 3201 4311",
    "sg:postcode":"4305",
    "sg:province":"QLD",
    "sg:tags":[
        "store"
    ],
    "wof:name":"Brassall Bottle Shop",
    "wof:placetype":"venue"
},
  "geometry": {"coordinates":[152.74603271500001,-27.593334198],"type":"Point"}
}