{
  "type": "Feature",
  "properties": {
    "addr:full":"17 Hazeldean Crt Hampton Park VIC 3976",
    "addr:housenumber":"17",
    "addr:postcode":"3976",
    "addr:street":"Hazeldean Crt",
    "iso:country":"AU",
    "sg:address":"17 Hazeldean Crt",
    "sg:city":"Hampton Park",
    "sg:classifiers":[
        {
            "category":"Building & Trades",
            "subcategory":"Cleaning & Sanitation",
            "type":"Services"
        }
    ],
    "sg:phone":"+61 3 9799 6701",
    "sg:postcode":"3976",
    "sg:province":"VIC",
    "sg:tags":[
        "industrial",
        "commercial",
        "contractor"
    ],
    "wof:name":"Equinox Cleaning Services",
    "wof:placetype":"venue"
},
  "geometry": {"coordinates":[145.256988525,-38.0234336853],"type":"Point"}
}