{
  "type": "Feature",
  "properties": {
    "addr:full":"22 Munibung Rd Cardiff NSW 2285",
    "addr:housenumber":"22",
    "addr:postcode":"2285",
    "addr:street":"Munibung Rd",
    "iso:country":"AU",
    "sg:address":"22 Munibung Rd",
    "sg:city":"Cardiff",
    "sg:classifiers":[
        {
            "category":"Building & Trades",
            "subcategory":"Construction",
            "type":"Services"
        }
    ],
    "sg:phone":"+61 2 4954 7466",
    "sg:postcode":"2285",
    "sg:province":"NSW",
    "sg:tags":[
        "window",
        "aluminium"
    ],
    "wof:name":"Hi-Point Windows",
    "wof:placetype":"venue"
},
  "geometry": {"coordinates":[151.65110778799999,-32.9434089661],"type":"Point"}
}