{
  "type": "Feature",
  "properties": {
    "iso:country":"AU",
    "sg:address":"Shp 13/ 72 Ellen St",
    "sg:city":"Port Pirie",
    "sg:classifiers":[
        {
            "category":"Cafe",
            "type":"Food & Drink"
        }
    ],
    "sg:phone":"+61 8 8633 4490",
    "sg:postcode":"5540",
    "sg:province":"SA",
    "wof:name":"Flinders Arcade Cafe",
    "wof:placetype":"venue"
},
  "geometry": {"coordinates":[138.009933472,-33.1763916016],"type":"Point"}
}