{
  "type": "Feature",
  "properties": {
    "addr:full":"17 Shearer St Nambour QLD 4560",
    "addr:housenumber":"17",
    "addr:postcode":"4560",
    "addr:street":"Shearer St",
    "iso:country":"AU",
    "sg:address":"17 Shearer St",
    "sg:city":"Nambour",
    "sg:classifiers":[
        {
            "category":"Health Services",
            "subcategory":"Chiropractor",
            "type":"Services"
        }
    ],
    "sg:phone":"+61 7 5441 7844",
    "sg:postcode":"4560",
    "sg:province":"QLD",
    "wof:name":"Moeliker Chiropractic Centre",
    "wof:placetype":"venue"
},
  "geometry": {"coordinates":[152.96432495100001,-26.6275444031],"type":"Point"}
}