{
  "type": "Feature",
  "properties": {
    "addr:full":"28 Tomsey Crt Adelaide SA 5000",
    "addr:housenumber":"28",
    "addr:postcode":"5000",
    "addr:street":"Tomsey Crt",
    "iso:country":"AU",
    "sg:address":"28 Tomsey Crt",
    "sg:city":"Adelaide",
    "sg:classifiers":[
        {
            "category":"Manufacturing",
            "subcategory":"Jewelry",
            "type":"Manufacturing & Wholesale Goods"
        }
    ],
    "sg:phone":"+61 8 8232 7244",
    "sg:postcode":"5000",
    "sg:province":"SA",
    "sg:tags":[
        "mfrg",
        "jeweller"
    ],
    "wof:name":"Palas",
    "wof:placetype":"venue"
},
  "geometry": {"coordinates":[138.615722656,-34.931602478],"type":"Point"}
}