{
  "type": "Feature",
  "properties": {
    "addr:full":"Shop G2, 1 Martin Pl Sydney NSW 2000",
    "addr:housenumber":"1",
    "addr:postcode":"2000",
    "addr:street":"G2;Pl",
    "iso:country":"AU",
    "sg:address":"Shop G2, 1 Martin Pl",
    "sg:city":"Sydney",
    "sg:classifiers":[
        {
            "category":"Shopping",
            "subcategory":"Clothing, Apparel, & Fashions",
            "type":"Retail Goods"
        }
    ],
    "sg:phone":"+61 2 9233 5011",
    "sg:postcode":"2000",
    "sg:province":"NSW",
    "sg:tags":[
        "menswear"
    ],
    "wof:name":"Xile Boutique",
    "wof:placetype":"venue"
},
  "geometry": {"coordinates":[151.207763672,-33.8676071167],"type":"Point"}
}