{
  "type": "Feature",
  "properties": {
    "iso:country":"AU",
    "sg:address":"PO Box 2916",
    "sg:city":"Port Lincoln",
    "sg:classifiers":[
        {
            "category":"Organizations",
            "subcategory":"Non-profit Organization",
            "type":"Services"
        }
    ],
    "sg:phone":"+61 8 8682 5655",
    "sg:postcode":"5606",
    "sg:province":"SA",
    "sg:tags":[
        "environmental",
        "organisation",
        "conservation"
    ],
    "wof:name":"Eyre Peninsula Catchment Water Management Board",
    "wof:placetype":"venue"
},
  "geometry": {"coordinates":[135.852036,-34.728481],"type":"Point"}
}