{
  "type": "Feature",
  "properties": {
    "addr:full":"Unit 1, 75 New South Head Rd Vaucluse NSW 2030",
    "addr:housenumber":"75",
    "addr:postcode":"2030",
    "addr:street":"New South Head Rd",
    "iso:country":"AU",
    "sg:address":"Unit 1, 75 New South Head Rd",
    "sg:city":"Vaucluse",
    "sg:classifiers":[
        {
            "category":"Health Services",
            "subcategory":"Dentist",
            "type":"Services"
        }
    ],
    "sg:phone":"+61 2 9337 1703",
    "sg:postcode":"2030",
    "sg:province":"NSW",
    "wof:name":"Dr Hymie Munitz",
    "wof:placetype":"venue"
},
  "geometry": {"coordinates":[151.27772522000001,-33.8596382141],"type":"Point"}
}