{
  "type": "Feature",
  "properties": {
    "iso:country":"AU",
    "sg:address":"33 Hartnett Drv",
    "sg:city":"Seaford",
    "sg:classifiers":[
        {
            "category":"Home & Garden",
            "subcategory":"Carpets & Floor Coverings",
            "type":"Retail Goods"
        }
    ],
    "sg:phone":"+61 3 9782 4288",
    "sg:postcode":"3198",
    "sg:province":"VIC",
    "sg:tags":[
        "double",
        "window",
        "glazed"
    ],
    "wof:name":"RYLOCK WINDOWS-FRANKSTON",
    "wof:placetype":"venue"
},
  "geometry": {"coordinates":[145.14175415,-38.1138954163],"type":"Point"}
}