{
  "type": "Feature",
  "properties": {
    "iso:country":"AU",
    "sg:address":"Shp3/ 10 Ebert Pde",
    "sg:city":"Lawnton",
    "sg:classifiers":[
        {
            "category":"Shopping",
            "subcategory":"Computers & Home Electronics",
            "type":"Retail Goods"
        }
    ],
    "sg:phone":"+61 7 3285 2397",
    "sg:postcode":"4501",
    "sg:province":"QLD",
    "sg:tags":[
        "hire",
        "video",
        "game"
    ],
    "wof:name":"Gamerz",
    "wof:placetype":"venue"
},
  "geometry": {"coordinates":[152.980545044,-27.2825641632],"type":"Point"}
}