{
  "type": "Feature",
  "properties": {
    "addr:full":"MacFarlane St Ext. Cessnock NSW 2325",
    "addr:postcode":"2325",
    "addr:street":"Macfarlane St Ext.",
    "iso:country":"AU",
    "sg:address":"MacFarlane St Ext.",
    "sg:city":"Cessnock",
    "sg:classifiers":[
        {
            "category":"Retail",
            "subcategory":"Driving School",
            "type":"Services"
        }
    ],
    "sg:phone":"+61 1300 365 400",
    "sg:postcode":"2325",
    "sg:province":"NSW",
    "wof:name":"DECA Training",
    "wof:placetype":"venue"
},
  "geometry": {"coordinates":[151.35496520999999,-32.8447494507],"type":"Point"}
}