{
  "type": "Feature",
  "properties": {
    "addr:full":"321 Sheridan St Cairns QLD 4870",
    "addr:housenumber":"321",
    "addr:postcode":"4870",
    "addr:street":"Sheridan St",
    "iso:country":"AU",
    "sg:address":"321 Sheridan St",
    "sg:city":"Cairns",
    "sg:classifiers":[
        {
            "category":"Professional",
            "subcategory":"Detective & Security Services",
            "type":"Services"
        }
    ],
    "sg:phone":"+61 7 4051 3646",
    "sg:postcode":"4870",
    "sg:province":"QLD",
    "sg:tags":[
        "consultant",
        "system"
    ],
    "wof:name":"Camsafe",
    "wof:placetype":"venue"
},
  "geometry": {"coordinates":[145.75950622600001,-16.9065666199],"type":"Point"}
}