{
  "type": "Feature",
  "properties": {
    "addr:full":"2/ 174a Corrimal St Wollongong NSW 2500",
    "addr:housenumber":"/ 174a",
    "addr:postcode":"2500",
    "addr:street":"Corrimal St",
    "iso:country":"AU",
    "sg:address":"2/ 174a Corrimal St",
    "sg:city":"Wollongong",
    "sg:classifiers":[
        {
            "category":"Utilities",
            "subcategory":"Water",
            "type":"Services"
        }
    ],
    "sg:phone":"+61 2 4229 6284",
    "sg:postcode":"2500",
    "sg:province":"NSW",
    "sg:tags":[
        "hot",
        "system"
    ],
    "wof:name":"Hocking Water Heaters Co Pty Ltd",
    "wof:placetype":"venue"
},
  "geometry": {"coordinates":[150.89863600000001,-34.430649],"type":"Point"}
}