{
  "type": "Feature",
  "properties": {
    "addr:full":"Aplin Rd Thursday Island QLD 4875",
    "addr:postcode":"4875",
    "addr:street":"Aplin Rd",
    "iso:country":"AU",
    "sg:address":"Aplin Rd",
    "sg:city":"Thursday Island",
    "sg:classifiers":[
        {
            "category":"Education",
            "subcategory":"University",
            "type":"Public Place"
        }
    ],
    "sg:phone":"+61 7 4069 1723",
    "sg:postcode":"4875",
    "sg:province":"QLD",
    "sg:tags":[
        "college",
        "tertiary"
    ],
    "wof:name":"Open Learning Centre",
    "wof:placetype":"venue"
},
  "geometry": {"coordinates":[142.21598815900001,-10.5758695602],"type":"Point"}
}