{
  "type": "Feature",
  "properties": {
    "addr:full":"Shop 7/ 4 Barker St Griffith ACT 2603",
    "addr:housenumber":"shop 7 / 4",
    "addr:postcode":"2603",
    "addr:street":"Barker St",
    "iso:country":"AU",
    "sg:address":"Shop 7/ 4 Barker St",
    "sg:city":"Griffith",
    "sg:classifiers":[
        {
            "category":"Personal",
            "subcategory":"Day Spa",
            "type":"Services"
        }
    ],
    "sg:phone":"+61 2 6295 0276",
    "sg:postcode":"2603",
    "sg:province":"ACT",
    "wof:name":"Essence Beauty & Body Care",
    "wof:placetype":"venue"
},
  "geometry": {"coordinates":[149.14279174800001,-35.3283653259],"type":"Point"}
}