{
  "type": "Feature",
  "properties": {
    "addr:full":"63 Bottles Rd Plumpton NSW 2761",
    "addr:housenumber":"63",
    "addr:postcode":"2761",
    "addr:street":"Bottles Rd",
    "iso:country":"AU",
    "sg:address":"63 Bottles Rd",
    "sg:city":"Plumpton",
    "sg:classifiers":[
        {
            "category":"Social Services",
            "subcategory":"Child Care",
            "type":"Services"
        }
    ],
    "sg:phone":"+61 2 9625 9462",
    "sg:postcode":"2761",
    "sg:province":"NSW",
    "wof:name":"Plumpton Long Day Care Centre",
    "wof:placetype":"venue"
},
  "geometry": {"coordinates":[150.84011799999999,-33.749481],"type":"Point"}
}