{
  "type": "Feature",
  "properties": {
    "addr:full":"165 Hopetoun Rd Rutherglen VIC 3685",
    "addr:housenumber":"165",
    "addr:postcode":"3685",
    "addr:street":"Hopetoun Rd",
    "iso:country":"AU",
    "sg:address":"165 Hopetoun Rd",
    "sg:city":"Rutherglen",
    "sg:classifiers":[
        {
            "category":"Utilities",
            "subcategory":"Fuel Oil & Lpg",
            "type":"Services"
        }
    ],
    "sg:phone":"+61 2 6032 7022",
    "sg:postcode":"3685",
    "sg:province":"VIC",
    "sg:tags":[
        "olive"
    ],
    "wof:name":"Wicked Virgin Olives",
    "wof:placetype":"venue"
},
  "geometry": {"coordinates":[146.468353272,-36.0503883362],"type":"Point"}
}