{
  "type": "Feature",
  "properties": {
    "addr:full":"Cnr Cheltenham Drv & Ron Penhaligon Way Robina QLD 4226",
    "addr:postcode":"4226",
    "addr:street":"Cnr Cheltenham Drv &;Penhaligon Way",
    "iso:country":"AU",
    "sg:address":"Cnr Cheltenham Drv & Ron Penhaligon Way",
    "sg:city":"Robina",
    "sg:classifiers":[
        {
            "category":"Food & Beverages",
            "subcategory":"Liquor & Beverages",
            "type":"Retail Goods"
        }
    ],
    "sg:phone":"+61 7 5593 2600",
    "sg:postcode":"4226",
    "sg:province":"QLD",
    "sg:tags":[
        "store"
    ],
    "wof:name":"Robina Tavern Liquor Barn & Drive Thru",
    "wof:placetype":"venue"
},
  "geometry": {"coordinates":[153.40284729000001,-28.0674743652],"type":"Point"}
}