{
  "type": "Feature",
  "properties": {
    "addr:full":"17 Massey St Gladesville NSW 2111",
    "addr:housenumber":"17",
    "addr:postcode":"2111",
    "addr:street":"Massey St",
    "iso:country":"AU",
    "sg:address":"17 Massey St",
    "sg:city":"Gladesville",
    "sg:classifiers":[
        {
            "category":"Health Services",
            "subcategory":"Doctor",
            "type":"Services"
        }
    ],
    "sg:phone":"+61 2 9817 5511",
    "sg:postcode":"2111",
    "sg:province":"NSW",
    "sg:tags":[
        "medical",
        "practitioner"
    ],
    "wof:name":"Abercrombie Charles",
    "wof:placetype":"venue"
},
  "geometry": {"coordinates":[151.12855529800001,-33.830329895],"type":"Point"}
}