{
  "type": "Feature",
  "properties": {
    "iso:country":"AU",
    "sg:address":"Shp11a/ 824 Beeliar Drv",
    "sg:city":"Success",
    "sg:classifiers":[
        {
            "category":"Food & Beverages",
            "subcategory":"Groceries & Convenience Stores",
            "type":"Retail Goods"
        }
    ],
    "sg:phone":"+61 8 9414 5816",
    "sg:postcode":"6164",
    "sg:province":"WA",
    "wof:name":"Ace Asian Mini Mart",
    "wof:placetype":"venue"
},
  "geometry": {"coordinates":[115.837631,-32.125263],"type":"Point"}
}