{
  "type": "Feature",
  "properties": {
    "iso:country":"AU",
    "sg:address":"13 Lambrook Crt",
    "sg:city":"Alexandra",
    "sg:classifiers":[
        {
            "category":"Utilities",
            "subcategory":"Electric",
            "type":"Services"
        }
    ],
    "sg:phone":"+61 7 4954 5437",
    "sg:postcode":"4740",
    "sg:province":"QLD",
    "sg:tags":[
        "electrical",
        "contractor"
    ],
    "sg:website":"http://www.soscontracting.com.au",
    "wof:name":"SOS Electrical & Communications",
    "wof:placetype":"venue"
},
  "geometry": {"coordinates":[149.097244,-21.16386],"type":"Point"}
}