{
  "type": "Feature",
  "properties": {
    "addr:full":"17- 25 Stuart Hwy Stuart Park NT 0820",
    "addr:housenumber":"25",
    "addr:postcode":"nt 0820",
    "addr:street":"Stuart Hwy Stuart",
    "iso:country":"AU",
    "sg:address":"17- 25 Stuart Hwy",
    "sg:city":"Stuart Park",
    "sg:classifiers":[
        {
            "category":"Autos & Motor Vehicles",
            "subcategory":"Automobile Sales",
            "type":"Retail Goods"
        }
    ],
    "sg:phone":"+61 8 8980 8081",
    "sg:postcode":"0820",
    "sg:province":"NT",
    "sg:tags":[
        "car",
        "new"
    ],
    "wof:name":"Kerry Daihatsu",
    "wof:placetype":"venue"
},
  "geometry": {"coordinates":[130.84078979500001,-12.4505348206],"type":"Point"}
}