{
  "type": "Feature",
  "properties": {
    "iso:country":"AU",
    "sg:address":"Dover Rd",
    "sg:city":"Rose Bay",
    "sg:classifiers":[
        {
            "category":"Education",
            "subcategory":"Kindergarten",
            "type":"Public Place"
        }
    ],
    "sg:phone":"+61 2 9371 9364",
    "sg:postcode":"2029",
    "sg:province":"NSW",
    "sg:tags":[
        "pre-schools"
    ],
    "wof:name":"Bo-Peep Kindergarten",
    "wof:placetype":"venue"
},
  "geometry": {"coordinates":[151.27093505900001,-33.870765686],"type":"Point"}
}