{
  "type": "Feature",
  "properties": {
    "addr:full":"6 Furnell Crt Toorak VIC 3142",
    "addr:housenumber":"6",
    "addr:postcode":"3142",
    "addr:street":"Furnell Crt",
    "iso:country":"AU",
    "sg:address":"6 Furnell Crt",
    "sg:city":"Toorak",
    "sg:classifiers":[
        {
            "category":"Personal",
            "subcategory":"Massage",
            "type":"Services"
        }
    ],
    "sg:phone":"+61 3 9826 0992",
    "sg:postcode":"3142",
    "sg:province":"VIC",
    "sg:tags":[
        "therapy"
    ],
    "wof:name":"Focus Health Management",
    "wof:placetype":"venue"
},
  "geometry": {"coordinates":[145.01091003400001,-37.8443527222],"type":"Point"}
}