{
  "type": "Feature",
  "properties": {
    "addr:full":"38 Hams Rd Waurn Ponds VIC 3216",
    "addr:housenumber":"38",
    "addr:postcode":"3216",
    "addr:street":"Hams Rd",
    "iso:country":"AU",
    "sg:address":"38 Hams Rd",
    "sg:city":"Waurn Ponds",
    "sg:classifiers":[
        {
            "category":"Building & Trades",
            "subcategory":"Construction",
            "type":"Services"
        }
    ],
    "sg:phone":"+61 3 5241 8370",
    "sg:postcode":"3216",
    "sg:province":"VIC",
    "sg:tags":[
        "plasterboard",
        "plasterer",
        "fixer"
    ],
    "wof:name":"Aztec Plaster",
    "wof:placetype":"venue"
},
  "geometry": {"coordinates":[144.29664611800001,-38.2144432068],"type":"Point"}
}