{
  "type": "Feature",
  "properties": {
    "iso:country":"AU",
    "sg:address":"55 Brunswick St",
    "sg:city":"Fortitude Valley",
    "sg:classifiers":[
        {
            "category":"Travel",
            "subcategory":"Hotels & Motels",
            "type":"Entertainment"
        }
    ],
    "sg:phone":"+61 7 3252 1338",
    "sg:postcode":"4006",
    "sg:province":"QLD",
    "wof:name":"City Palms Motel",
    "wof:placetype":"venue"
},
  "geometry": {"coordinates":[153.02932739299999,-27.4537467957],"type":"Point"}
}