{
  "type": "Feature",
  "properties": {
    "iso:country":"AU",
    "sg:address":"141 Bridge Rd",
    "sg:city":"Glebe",
    "sg:classifiers":[
        {
            "category":"Wholesale",
            "subcategory":"Home Furnishings",
            "type":"Manufacturing & Wholesale Goods"
        }
    ],
    "sg:phone":"+61 2 9552 1121",
    "sg:postcode":"2037",
    "sg:province":"NSW",
    "wof:name":"Garner Agencies",
    "wof:placetype":"venue"
},
  "geometry": {"coordinates":[151.18768310600001,-33.8792533875],"type":"Point"}
}