{
  "type": "Feature",
  "properties": {
    "addr:full":"Shop 51, Stockland Shopping Centre, Mulgrave Road Cairns QLD 4870",
    "addr:housenumber":"shop 51",
    "addr:postcode":"4870",
    "addr:street":"Mulgrave Road",
    "iso:country":"AU",
    "sg:address":"Shop 51, Stockland Shopping Centre, Mulgrave Road",
    "sg:city":"Cairns",
    "sg:classifiers":[
        {
            "category":"Personal",
            "subcategory":"Beauty Salon",
            "type":"Services"
        }
    ],
    "sg:phone":"+61 7 4033 6081",
    "sg:postcode":"4870",
    "sg:province":"QLD",
    "wof:name":"Ella Bach",
    "wof:placetype":"venue"
},
  "geometry": {"coordinates":[145.746780395,-16.9546756744],"type":"Point"}
}