{
  "type": "Feature",
  "properties": {
    "iso:country":"AU",
    "sg:address":"71- 73 Overseas Drv",
    "sg:city":"Noble Park",
    "sg:classifiers":[
        {
            "category":"Autos & Motor Vehicles",
            "subcategory":"Auto Supplies",
            "type":"Retail Goods"
        }
    ],
    "sg:phone":"+61 3 9790 5911",
    "sg:postcode":"3174",
    "sg:province":"VIC",
    "sg:tags":[
        "transmission",
        "equipment",
        "power"
    ],
    "wof:name":"Malco Engineering Pty Limited",
    "wof:placetype":"venue"
},
  "geometry": {"coordinates":[145.18490600600001,-37.9563293457],"type":"Point"}
}