{
  "type": "Feature",
  "properties": {
    "addr:full":"1 Nicholls Crt Plenty VIC 3090",
    "addr:housenumber":"1",
    "addr:postcode":"3090",
    "addr:street":"Nicholls Crt",
    "iso:country":"AU",
    "sg:address":"1 Nicholls Crt",
    "sg:city":"Plenty",
    "sg:classifiers":[
        {
            "category":"Retail",
            "subcategory":"Auto Repair",
            "type":"Services"
        }
    ],
    "sg:phone":"+61 3 9436 1655",
    "sg:postcode":"3090",
    "sg:province":"VIC",
    "sg:tags":[
        "repairer",
        "motor",
        "engineer"
    ],
    "wof:name":"Northern Tuning Service",
    "wof:placetype":"venue"
},
  "geometry": {"coordinates":[145.110137939,-37.6573753357],"type":"Point"}
}