{
  "type": "Feature",
  "properties": {
    "iso:country":"AU",
    "sg:address":"4- 8 Greenaway St",
    "sg:city":"Bulleen",
    "sg:classifiers":[
        {
            "category":"Banks & Credit Unions",
            "subcategory":"Financial Services",
            "type":"Services"
        }
    ],
    "sg:phone":"+61 3 9852 1833",
    "sg:postcode":"3105",
    "sg:province":"VIC",
    "sg:tags":[
        "finance",
        "motor",
        "vehicle"
    ],
    "wof:name":"Money Lenders The",
    "wof:placetype":"venue"
},
  "geometry": {"coordinates":[145.08277893100001,-37.7610359192],"type":"Point"}
}