{
  "type": "Feature",
  "properties": {
    "addr:full":"431- 439 Sussex St Haymarket NSW 2000",
    "addr:housenumber":"439",
    "addr:postcode":"2000",
    "addr:street":"Sussex St",
    "iso:country":"AU",
    "sg:address":"431- 439 Sussex St",
    "sg:city":"Haymarket",
    "sg:classifiers":[
        {
            "category":"Professional",
            "subcategory":"Management & Consulting",
            "type":"Services"
        }
    ],
    "sg:phone":"+61 2 9281 8133",
    "sg:postcode":"2000",
    "sg:province":"NSW",
    "sg:tags":[
        "consultant",
        "educational"
    ],
    "wof:name":"Advisory Centre For Australian Education",
    "wof:placetype":"venue"
},
  "geometry": {"coordinates":[151.20472717300001,-33.8790397644],"type":"Point"}
}