{
  "type": "Feature",
  "properties": {
    "iso:country":"AU",
    "sg:address":"1 Darlot St",
    "sg:city":"Port Hedland",
    "sg:classifiers":[
        {
            "category":"Real Estate",
            "subcategory":"Real Estate Agent",
            "type":"Services"
        }
    ],
    "sg:phone":"+61 8 9173 1055",
    "sg:postcode":"6721",
    "sg:province":"WA",
    "sg:tags":[
        "handyman's",
        "equipment",
        "hire",
        "builders",
        "contractor"
    ],
    "wof:name":"National Hire Trading Pty Ltd",
    "wof:placetype":"venue"
},
  "geometry": {"coordinates":[118.58341217,-20.3116645813],"type":"Point"}
}