{
  "type": "Feature",
  "properties": {
    "iso:country":"AU",
    "sg:address":"10 Mowla Ave",
    "sg:city":"Penrith",
    "sg:classifiers":[
        {
            "category":"Shopping",
            "subcategory":"Computers & Home Electronics",
            "type":"Retail Goods"
        }
    ],
    "sg:phone":"+61 2 4733 3580",
    "sg:postcode":"2750",
    "sg:province":"NSW",
    "sg:tags":[
        "wholesaler",
        "mfrs",
        "part",
        "electronic"
    ],
    "wof:name":"Dakpro Pty Ltd",
    "wof:placetype":"venue"
},
  "geometry": {"coordinates":[150.676635742,-33.773765564],"type":"Point"}
}