{
  "type": "Feature",
  "properties": {
    "iso:country":"AU",
    "sg:address":"274 Swanston St",
    "sg:city":"Melbourne",
    "sg:classifiers":[
        {
            "category":"Shopping",
            "subcategory":"Computers & Home Electronics",
            "type":"Retail Goods"
        }
    ],
    "sg:phone":"+61 3 9639 8888",
    "sg:postcode":"3000",
    "sg:province":"VIC",
    "sg:tags":[
        "hardware",
        "equipment"
    ],
    "wof:name":"Easytone Hand Held Specialist",
    "wof:placetype":"venue"
},
  "geometry": {"coordinates":[144.964935303,-37.8116493225],"type":"Point"}
}