{
  "type": "Feature",
  "properties": {
    "addr:full":"59 Cromwell St Collingwood VIC 3066",
    "addr:housenumber":"59",
    "addr:postcode":"3066",
    "addr:street":"Cromwell St",
    "iso:country":"AU",
    "sg:address":"59 Cromwell St",
    "sg:city":"Collingwood",
    "sg:classifiers":[
        {
            "category":"Personal",
            "subcategory":"Day Spa",
            "type":"Services"
        }
    ],
    "sg:phone":"+61 3 9419 0268",
    "sg:postcode":"3066",
    "sg:province":"VIC",
    "wof:name":"Japanese Bath House The",
    "wof:placetype":"venue"
},
  "geometry": {"coordinates":[144.98968505900001,-37.8071899414],"type":"Point"}
}