{
  "type": "Feature",
  "properties": {
    "addr:full":"2 Spencer St Leongatha VIC 3953",
    "addr:housenumber":"2",
    "addr:postcode":"3953",
    "addr:street":"Spencer St",
    "iso:country":"AU",
    "sg:address":"2 Spencer St",
    "sg:city":"Leongatha",
    "sg:classifiers":[
        {
            "category":"Education",
            "subcategory":"Special Training",
            "type":"Public Place"
        }
    ],
    "sg:phone":"+61 3 5662 5606",
    "sg:postcode":"3953",
    "sg:province":"VIC",
    "sg:tags":[
        "tuition-educational"
    ],
    "wof:name":"Kip McGrath Education Centres",
    "wof:placetype":"venue"
},
  "geometry": {"coordinates":[145.95214843799999,-38.4847679138],"type":"Point"}
}