{
  "type": "Feature",
  "properties": {
    "addr:full":"849 Burwood Rd Hawthorn East VIC 3123",
    "addr:housenumber":"849",
    "addr:postcode":"3123",
    "addr:street":"Burwood Rd",
    "iso:country":"AU",
    "sg:address":"849 Burwood Rd",
    "sg:city":"Hawthorn East",
    "sg:classifiers":[
        {
            "category":"Sports & Exercise",
            "subcategory":"Gym",
            "type":"Entertainment"
        }
    ],
    "sg:phone":"+61 3 9882 2201",
    "sg:postcode":"3123",
    "sg:province":"VIC",
    "sg:tags":[
        "personal",
        "trainer",
        "fitness"
    ],
    "sg:website":"http://www.bodyworld.com.au",
    "wof:name":"Body World Camberwell",
    "wof:placetype":"venue"
},
  "geometry": {"coordinates":[145.05763244600001,-37.8251724243],"type":"Point"}
}