{
  "type": "Feature",
  "properties": {
    "addr:full":"Suite 30, 21 Aristoc Rd Glen Waverley VIC 3150",
    "addr:housenumber":"21",
    "addr:postcode":"3150",
    "addr:street":"Aristoc Rd",
    "iso:country":"AU",
    "sg:address":"Suite 30, 21 Aristoc Rd",
    "sg:city":"Glen Waverley",
    "sg:classifiers":[
        {
            "category":"Professional",
            "subcategory":"Employment Agencies",
            "type":"Services"
        }
    ],
    "sg:phone":"+61 3 9550 1888",
    "sg:postcode":"3150",
    "sg:province":"VIC",
    "wof:name":"Just Recruitment",
    "wof:placetype":"venue"
},
  "geometry": {"coordinates":[145.15765380900001,-37.8871078491],"type":"Point"}
}