{
  "type": "Feature",
  "properties": {
    "iso:country":"AU",
    "sg:address":"Governor Macquarie Drv",
    "sg:city":"Chipping Norton",
    "sg:classifiers":[
        {
            "category":"Home & Garden",
            "subcategory":"Furniture",
            "type":"Retail Goods"
        }
    ],
    "sg:phone":"+61 2 9821 4653",
    "sg:postcode":"2170",
    "sg:province":"NSW",
    "sg:tags":[
        "business"
    ],
    "wof:name":"Allgood Interiors",
    "wof:placetype":"venue"
},
  "geometry": {"coordinates":[150.961761475,-33.9171180725],"type":"Point"}
}