{
  "type": "Feature",
  "properties": {
    "addr:full":"1 Coolamon Rd Taroona TAS 7053",
    "addr:housenumber":"1",
    "addr:postcode":"7053",
    "addr:street":"Coolamon Rd",
    "iso:country":"AU",
    "sg:address":"1 Coolamon Rd",
    "sg:city":"Taroona",
    "sg:classifiers":[
        {
            "category":"Professional",
            "subcategory":"Art Services",
            "type":"Services"
        }
    ],
    "sg:phone":"+61 403 448 655",
    "sg:postcode":"7053",
    "sg:province":"TAS",
    "sg:tags":[
        "decorator",
        "painter"
    ],
    "wof:name":"Primary Colours",
    "wof:placetype":"venue"
},
  "geometry": {"coordinates":[147.34861799999999,-42.946812],"type":"Point"}
}