{
  "type": "Feature",
  "properties": {
    "iso:country":"AU",
    "sg:address":"93 York St",
    "sg:city":"South Melbourne",
    "sg:classifiers":[
        {
            "category":"Personal",
            "subcategory":"Beauty Salon",
            "type":"Services"
        }
    ],
    "sg:phone":"+61 3 9699 8133",
    "sg:postcode":"3205",
    "sg:province":"VIC",
    "sg:tags":[
        "hairdresser"
    ],
    "wof:name":"Miyabi Hairdressing",
    "wof:placetype":"venue"
},
  "geometry": {"coordinates":[144.959457,-37.830936],"type":"Point"}
}