{
  "type": "Feature",
  "properties": {
    "addr:full":"The Stables, 14 Marfell Rd Warrnambool VIC 3280",
    "addr:housenumber":"14",
    "addr:postcode":"3280",
    "addr:street":"Marfell Rd",
    "iso:country":"AU",
    "sg:address":"The Stables, 14 Marfell Rd",
    "sg:city":"Warrnambool",
    "sg:classifiers":[
        {
            "category":"Shopping",
            "subcategory":"Bicycles & Sporting Goods",
            "type":"Retail Goods"
        }
    ],
    "sg:phone":"+61 3 5561 6142",
    "sg:postcode":"3280",
    "sg:province":"VIC",
    "sg:tags":[
        "chemical",
        "equipment",
        "pool",
        "swimming"
    ],
    "wof:name":"Air & Water Technologies",
    "wof:placetype":"venue"
},
  "geometry": {"coordinates":[142.50814819300001,-38.396282196],"type":"Point"}
}