{
  "type": "Feature",
  "properties": {
    "iso:country":"AU",
    "sg:address":"347 Hunter St",
    "sg:city":"Newcastle",
    "sg:classifiers":[
        {
            "category":"Travel",
            "subcategory":"Hotels & Motels",
            "type":"Entertainment"
        }
    ],
    "sg:phone":"+61 2 4927 0966",
    "sg:postcode":"2300",
    "sg:province":"NSW",
    "sg:tags":[
        "accommodation"
    ],
    "wof:name":"Clarendon Hotel",
    "wof:placetype":"venue"
},
  "geometry": {"coordinates":[151.77420000000001,-32.926891],"type":"Point"}
}