{
  "type": "Feature",
  "properties": {
    "addr:full":"617 Mitchell Hwy Bathurst NSW 2795",
    "addr:housenumber":"617",
    "addr:postcode":"2795",
    "addr:street":"Mitchell Hwy",
    "iso:country":"AU",
    "sg:address":"617 Mitchell Hwy",
    "sg:city":"Bathurst",
    "sg:classifiers":[
        {
            "category":"Farming",
            "subcategory":"Fish & Marine Products",
            "type":"Manufacturing & Wholesale Goods"
        }
    ],
    "sg:phone":"+61 2 6332 4289",
    "sg:postcode":"2795",
    "sg:province":"NSW",
    "sg:tags":[
        "bitumen"
    ],
    "wof:name":"Aussie Digger",
    "wof:placetype":"venue"
},
  "geometry": {"coordinates":[149.528533936,-33.4117240906],"type":"Point"}
}