{
  "type": "Feature",
  "properties": {
    "addr:full":"2/ 1191 Anzac Pde Malabar NSW 2036",
    "addr:housenumber":"/ 1191",
    "addr:postcode":"2036",
    "addr:street":"Anzac Pde",
    "iso:country":"AU",
    "sg:address":"2/ 1191 Anzac Pde",
    "sg:city":"Malabar",
    "sg:classifiers":[
        {
            "category":"Government",
            "subcategory":"Post Office",
            "type":"Public Place"
        }
    ],
    "sg:phone":"+61 2 9345 5275",
    "sg:postcode":"2036",
    "sg:province":"NSW",
    "sg:tags":[
        "yoga"
    ],
    "wof:name":"The Light Of Yoga",
    "wof:placetype":"venue"
},
  "geometry": {"coordinates":[151.24615478499999,-33.961566925],"type":"Point"}
}