{
  "type": "Feature",
  "properties": {
    "addr:full":"21- 29 Global Drv Westmeadows VIC 3049",
    "addr:housenumber":"29",
    "addr:postcode":"3049",
    "addr:street":"Global Drv",
    "iso:country":"AU",
    "sg:address":"21- 29 Global Drv",
    "sg:city":"Westmeadows",
    "sg:classifiers":[
        {
            "category":"Professional",
            "type":"Services"
        }
    ],
    "sg:phone":"+61 1300 551 127",
    "sg:postcode":"3049",
    "sg:province":"VIC",
    "sg:tags":[
        "transport"
    ],
    "wof:name":"B & K Express Freight Australia",
    "wof:placetype":"venue"
},
  "geometry": {"coordinates":[144.87768600000001,-37.683548],"type":"Point"}
}