{
  "type": "Feature",
  "properties": {
    "iso:country":"AU",
    "sg:address":"26 Mozaleuca Crs",
    "sg:city":"Langwarrin",
    "sg:classifiers":[
        {
            "category":"Building & Trades",
            "subcategory":"Construction",
            "type":"Services"
        }
    ],
    "sg:phone":"+61 3 9775 8254",
    "sg:postcode":"3910",
    "sg:province":"VIC",
    "sg:tags":[
        "contractor"
    ],
    "wof:name":"Farm Houses Of Australia P/L",
    "wof:placetype":"venue"
},
  "geometry": {"coordinates":[145.20420837399999,-38.1449012756],"type":"Point"}
}