{
  "type": "Feature",
  "properties": {
    "addr:full":"3 The Palms, Church St Terrigal NSW 2260",
    "addr:housenumber":"3",
    "addr:postcode":"2260",
    "addr:street":"The Palms Church St",
    "iso:country":"AU",
    "sg:address":"3 The Palms, Church St",
    "sg:city":"Terrigal",
    "sg:classifiers":[
        {
            "category":"Shopping",
            "subcategory":"Antiques",
            "type":"Retail Goods"
        }
    ],
    "sg:phone":"+61 2 4384 3421",
    "sg:postcode":"2260",
    "sg:province":"NSW",
    "wof:name":"Felicity Of Terrigal",
    "wof:placetype":"venue"
},
  "geometry": {"coordinates":[151.44404599999999,-33.447678],"type":"Point"}
}