{
  "type": "Feature",
  "properties": {
    "addr:full":"16 Sunnyside Ave Dandenong VIC 3175",
    "addr:housenumber":"16",
    "addr:postcode":"3175",
    "addr:street":"Sunnyside Ave",
    "iso:country":"AU",
    "sg:address":"16 Sunnyside Ave",
    "sg:city":"Dandenong",
    "sg:classifiers":[
        {
            "category":"Real Estate",
            "subcategory":"Architect",
            "type":"Services"
        }
    ],
    "sg:phone":"+61 3 9793 6618",
    "sg:postcode":"3175",
    "sg:province":"VIC",
    "wof:name":"Lester Vander Straaten Architect",
    "wof:placetype":"venue"
},
  "geometry": {"coordinates":[145.223022461,-37.9819831848],"type":"Point"}
}