{
  "type": "Feature",
  "properties": {
    "addr:full":"Lvl2/ 106 Boundary St Paddington NSW 2021",
    "addr:housenumber":"106",
    "addr:postcode":"2021",
    "addr:street":"Boundary St",
    "iso:country":"AU",
    "sg:address":"Lvl2/ 106 Boundary St",
    "sg:city":"Paddington",
    "sg:classifiers":[
        {
            "category":"Professional",
            "subcategory":"Accounting & Tax Preparation",
            "type":"Services"
        }
    ],
    "sg:phone":"+61 2 9360 8712",
    "sg:postcode":"2021",
    "sg:province":"NSW",
    "sg:tags":[
        "accountant",
        "auditor"
    ],
    "wof:name":"Karan & Co",
    "wof:placetype":"venue"
},
  "geometry": {"coordinates":[151.22210693400001,-33.8810997009],"type":"Point"}
}