{
  "type": "Feature",
  "properties": {
    "addr:full":"Office 2 'Sun Pictures', 8 Canarvon St Broome WA 6725",
    "addr:postcode":"6725",
    "addr:street":"Canarvon St",
    "iso:country":"AU",
    "sg:address":"Office 2 'Sun Pictures', 8 Canarvon St",
    "sg:city":"Broome",
    "sg:classifiers":[
        {
            "category":"Professional",
            "subcategory":"Accounting & Tax Preparation",
            "type":"Services"
        }
    ],
    "sg:phone":"+61 8 9192 3211",
    "sg:postcode":"6725",
    "sg:province":"WA",
    "sg:tags":[
        "accountant",
        "auditor"
    ],
    "wof:name":"Kimberley Integrated Commercial Services",
    "wof:placetype":"venue"
},
  "geometry": {"coordinates":[122.677589416,-18.2141704559],"type":"Point"}
}