{
  "type": "Feature",
  "properties": {
    "iso:country":"AU",
    "sg:address":"85 Macquarie St",
    "sg:city":"Parramatta",
    "sg:classifiers":[
        {
            "category":"Autos & Motor Vehicles",
            "subcategory":"Automobile Sales",
            "type":"Retail Goods"
        }
    ],
    "sg:phone":"+61 2 9687 9555",
    "sg:postcode":"2150",
    "sg:province":"NSW",
    "sg:tags":[
        "car",
        "used"
    ],
    "wof:name":"Arc Motors Pty Ltd",
    "wof:placetype":"venue"
},
  "geometry": {"coordinates":[151.04385375999999,-33.862663269],"type":"Point"}
}