{
  "type": "Feature",
  "properties": {
    "addr:full":"Level 49, 525 Collins St Melbourne VIC 3000",
    "addr:housenumber":"525",
    "addr:postcode":"3000",
    "addr:street":"Collins St",
    "iso:country":"AU",
    "sg:address":"Level 49, 525 Collins St",
    "sg:city":"Melbourne",
    "sg:classifiers":[
        {
            "category":"Banks & Credit Unions",
            "subcategory":"Bank",
            "type":"Services"
        }
    ],
    "sg:phone":"+61 3 9629 3555",
    "sg:postcode":"3000",
    "sg:province":"VIC",
    "sg:tags":[
        "broker",
        "mortgage"
    ],
    "wof:name":"Home Loan Centre Australia Pty Ltd",
    "wof:placetype":"venue"
},
  "geometry": {"coordinates":[144.95716857900001,-37.8183326721],"type":"Point"}
}