{
  "type": "Feature",
  "properties": {
    "iso:country":"AU",
    "sg:address":"2 Foster St",
    "sg:city":"Railton",
    "sg:classifiers":[
        {
            "category":"Government",
            "subcategory":"Post Office",
            "type":"Public Place"
        }
    ],
    "sg:phone":"+61 3 6496 1259",
    "sg:postcode":"7305",
    "sg:province":"TAS",
    "sg:tags":[
        "postal"
    ],
    "wof:name":"Australia Post",
    "wof:placetype":"venue"
},
  "geometry": {"coordinates":[146.42353800000001,-41.345192],"type":"Point"}
}