{
  "type": "Feature",
  "properties": {
    "addr:full":"2/ 2 Seabrook Way Medina WA 6167",
    "addr:housenumber":"/ 2",
    "addr:postcode":"6167",
    "addr:street":"Seabrook Way",
    "iso:country":"AU",
    "sg:address":"2/ 2 Seabrook Way",
    "sg:city":"Medina",
    "sg:classifiers":[
        {
            "category":"Professional",
            "subcategory":"Computer Services",
            "type":"Services"
        }
    ],
    "sg:phone":"+61 8 9419 4100",
    "sg:postcode":"6167",
    "sg:province":"WA",
    "sg:tags":[
        "consultant",
        "system"
    ],
    "wof:name":"Operational Solutions Management Pty Ltd",
    "wof:placetype":"venue"
},
  "geometry": {"coordinates":[115.801537,-32.241425],"type":"Point"}
}