{
  "type": "Feature",
  "properties": {
    "addr:full":"1165 Logan Rd Holland Park West QLD 4121",
    "addr:housenumber":"1165",
    "addr:postcode":"4121",
    "addr:street":"Logan Rd",
    "iso:country":"AU",
    "sg:address":"1165 Logan Rd",
    "sg:city":"Holland Park West",
    "sg:classifiers":[
        {
            "category":"Travel",
            "subcategory":"Hotels & Motels",
            "type":"Entertainment"
        }
    ],
    "sg:phone":"+61 7 3849 4849",
    "sg:postcode":"4121",
    "sg:province":"QLD",
    "wof:name":"Mt Gravatt Colonial Motor Inn",
    "wof:placetype":"venue"
},
  "geometry": {"coordinates":[153.07037353499999,-27.5280761719],"type":"Point"}
}