{
  "type": "Feature",
  "properties": {
    "addr:full":"Metro Quays 86 Ogden St Townsville QLD 4810",
    "addr:housenumber":"86",
    "addr:postcode":"4810",
    "addr:street":"Quays;Ogden St",
    "iso:country":"AU",
    "sg:address":"Metro Quays 86 Ogden St",
    "sg:city":"Townsville",
    "sg:classifiers":[
        {
            "category":"Health Services",
            "subcategory":"Health Practitioner",
            "type":"Services"
        }
    ],
    "sg:phone":"+61 7 4724 0654",
    "sg:postcode":"4810",
    "sg:province":"QLD",
    "sg:tags":[
        "physiotherapist"
    ],
    "wof:name":"Sports Med",
    "wof:placetype":"venue"
},
  "geometry": {"coordinates":[146.81750500000001,-19.260292],"type":"Point"}
}