{
  "type": "Feature",
  "properties": {
    "addr:full":"Gaymards La Forbes NSW 2871",
    "addr:postcode":"2871",
    "iso:country":"AU",
    "sg:address":"Gaymards La",
    "sg:city":"Forbes",
    "sg:classifiers":[
        {
            "category":"Farming",
            "subcategory":"Poultry Farm",
            "type":"Manufacturing & Wholesale Goods"
        }
    ],
    "sg:phone":"+61 2 6852 2084",
    "sg:postcode":"2871",
    "sg:province":"NSW",
    "sg:tags":[
        "farmer"
    ],
    "wof:name":"Girot Margaret",
    "wof:placetype":"venue"
},
  "geometry": {"coordinates":[147.96002200000001,-33.39204],"type":"Point"}
}