{
  "type": "Feature",
  "properties": {
    "addr:full":"PO Box 139 Currumbin QLD 4223",
    "addr:postcode":"4223",
    "iso:country":"AU",
    "sg:address":"PO Box 139",
    "sg:city":"Currumbin",
    "sg:classifiers":[
        {
            "category":"Building & Trades",
            "subcategory":"Construction",
            "type":"Services"
        }
    ],
    "sg:phone":"+61 7 5598 8318",
    "sg:postcode":"4223",
    "sg:province":"QLD",
    "sg:tags":[
        "waterproofing",
        "contractor"
    ],
    "wof:name":"Dolphin Waterproofing",
    "wof:placetype":"venue"
},
  "geometry": {"coordinates":[153.47454834000001,-28.1377792358],"type":"Point"}
}