{
  "type": "Feature",
  "properties": {
    "addr:full":"295 Bay St Port Melbourne VIC 3207",
    "addr:housenumber":"295",
    "addr:postcode":"3207",
    "addr:street":"Bay St",
    "iso:country":"AU",
    "sg:address":"295 Bay St",
    "sg:city":"Port Melbourne",
    "sg:classifiers":[
        {
            "category":"Shopping",
            "subcategory":"Clothing, Apparel, & Fashions",
            "type":"Retail Goods"
        }
    ],
    "sg:phone":"+61 3 9646 2214",
    "sg:postcode":"3207",
    "sg:province":"VIC",
    "sg:tags":[
        "recycled",
        "clothing"
    ],
    "wof:name":"Silk Pirate",
    "wof:placetype":"venue"
},
  "geometry": {"coordinates":[144.94364899999999,-37.836937],"type":"Point"}
}