{
  "type": "Feature",
  "properties": {
    "addr:full":"868- 872 Main North Rd Pooraka SA 5095",
    "addr:housenumber":"872",
    "addr:postcode":"5095",
    "addr:street":"Main North Rd",
    "iso:country":"AU",
    "sg:address":"868- 872 Main North Rd",
    "sg:city":"Pooraka",
    "sg:classifiers":[
        {
            "category":"Manufacturing",
            "subcategory":"Metals",
            "type":"Manufacturing & Wholesale Goods"
        }
    ],
    "sg:phone":"+61 8 8300 2500",
    "sg:postcode":"5095",
    "sg:province":"SA",
    "sg:tags":[
        "wholesaler",
        "aluminium",
        "mfrs"
    ],
    "wof:name":"Ullrich Aluminium",
    "wof:placetype":"venue"
},
  "geometry": {"coordinates":[138.61927795400001,-34.8222846985],"type":"Point"}
}