{
  "type": "Feature",
  "properties": {
    "addr:full":"Cnr Edington & Musgrave Sts North Rockhampton QLD 4701",
    "addr:postcode":"4701",
    "addr:street":"Cnr;North",
    "iso:country":"AU",
    "sg:address":"Cnr Edington & Musgrave Sts",
    "sg:city":"North Rockhampton",
    "sg:classifiers":[
        {
            "category":"Organizations",
            "subcategory":"Professional Association",
            "type":"Services"
        }
    ],
    "sg:phone":"+61 7 4922 6665",
    "sg:postcode":"4701",
    "sg:province":"QLD",
    "sg:tags":[
        "web",
        "internet"
    ],
    "wof:name":"Pro Computers",
    "wof:placetype":"venue"
},
  "geometry": {"coordinates":[150.538040161,-23.3629817963],"type":"Point"}
}