{
  "type": "Feature",
  "properties": {
    "addr:full":"Cnr Blacktown Rd & St Martin Cres Blacktown NSW 2148",
    "addr:postcode":"2148",
    "addr:street":"Cnr Blacktown Rd & St Martin Cres",
    "iso:country":"AU",
    "sg:address":"Cnr Blacktown Rd & St Martin Cres",
    "sg:city":"Blacktown",
    "sg:classifiers":[
        {
            "category":"Manufacturing",
            "subcategory":"Motor Vehicles & Parts",
            "type":"Manufacturing & Wholesale Goods"
        }
    ],
    "sg:phone":"+61 2 9622 7666",
    "sg:postcode":"2148",
    "sg:province":"NSW",
    "sg:tags":[
        "replacement"
    ],
    "wof:name":"Repco",
    "wof:placetype":"venue"
},
  "geometry": {"coordinates":[150.91949462900001,-33.7883148193],"type":"Point"}
}