{
  "type": "Feature",
  "properties": {
    "addr:full":"Shop 8 Johnny Chi La Broome WA 6725",
    "addr:housenumber":"shop 8",
    "addr:postcode":"6725",
    "addr:street":"Johnny Chi La",
    "iso:country":"AU",
    "sg:address":"Shop 8 Johnny Chi La",
    "sg:city":"Broome",
    "sg:classifiers":[
        {
            "category":"Shopping",
            "subcategory":"Clothing, Apparel, & Fashions",
            "type":"Retail Goods"
        }
    ],
    "sg:phone":"+61 8 9193 6880",
    "sg:postcode":"6725",
    "sg:province":"WA",
    "sg:tags":[
        "uniform"
    ],
    "wof:name":"Longys Clothes Basket",
    "wof:placetype":"venue"
},
  "geometry": {"coordinates":[122.677589416,-18.2141704559],"type":"Point"}
}