{
  "type": "Feature",
  "properties": {
    "addr:full":"Level 18, 175 Eagle St Brisbane QLD 4000",
    "addr:housenumber":"175",
    "addr:postcode":"4000",
    "addr:street":"Eagle St",
    "iso:country":"AU",
    "sg:address":"Level 18, 175 Eagle St",
    "sg:city":"Brisbane",
    "sg:classifiers":[
        {
            "category":"Professional",
            "subcategory":"Management & Consulting",
            "type":"Services"
        }
    ],
    "sg:phone":"+61 7 3832 0911",
    "sg:postcode":"4000",
    "sg:province":"QLD",
    "sg:tags":[
        "consultant"
    ],
    "wof:name":"SMS Management & Technology",
    "wof:placetype":"venue"
},
  "geometry": {"coordinates":[153.03050231899999,-27.4658794403],"type":"Point"}
}