{
  "type": "Feature",
  "properties": {
    "addr:full":"286 Carlisle St Balaclava VIC 3183",
    "addr:housenumber":"286",
    "addr:postcode":"3183",
    "addr:street":"Carlisle St",
    "iso:country":"AU",
    "sg:address":"286 Carlisle St",
    "sg:city":"Balaclava",
    "sg:classifiers":[
        {
            "category":"Food & Beverages",
            "subcategory":"Meat & Fish",
            "type":"Retail Goods"
        }
    ],
    "sg:phone":"+61 3 9534 5213",
    "sg:postcode":"3183",
    "sg:province":"VIC",
    "sg:tags":[
        "seafood"
    ],
    "wof:name":"Carlisle Seafoods",
    "wof:placetype":"venue"
},
  "geometry": {"coordinates":[144.99343872099999,-37.8686065674],"type":"Point"}
}