{
  "type": "Feature",
  "properties": {
    "addr:full":"1/ 518 Maroochydore Rd Kunda Park QLD 4556",
    "addr:housenumber":"/ 518",
    "addr:postcode":"4556",
    "addr:street":"Maroochydore Rd",
    "iso:country":"AU",
    "sg:address":"1/ 518 Maroochydore Rd",
    "sg:city":"Kunda Park",
    "sg:classifiers":[
        {
            "category":"Commercial Area",
            "type":"Public Place"
        }
    ],
    "sg:phone":"+61 7 5476 8322",
    "sg:postcode":"4556",
    "sg:province":"QLD",
    "sg:tags":[
        "heavy",
        "carrier"
    ],
    "wof:name":"East Coast Freight Distribution",
    "wof:placetype":"venue"
},
  "geometry": {"coordinates":[153.00274658199999,-26.6734771729],"type":"Point"}
}