{
  "type": "Feature",
  "properties": {
    "iso:country":"AU",
    "sg:address":"160 Dunmore St",
    "sg:city":"Wentworthville",
    "sg:classifiers":[
        {
            "category":"Health Services",
            "subcategory":"Doctor",
            "type":"Services"
        }
    ],
    "sg:phone":"+61 2 9636 3535",
    "sg:postcode":"2145",
    "sg:province":"NSW",
    "sg:tags":[
        "medical",
        "practitioner"
    ],
    "wof:name":"Soo Ida",
    "wof:placetype":"venue"
},
  "geometry": {"coordinates":[150.96368408199999,-33.8059997559],"type":"Point"}
}