{
  "type": "Feature",
  "properties": {
    "addr:full":"2 Truman St Hurstville NSW 2220",
    "addr:housenumber":"2",
    "addr:postcode":"2220",
    "addr:street":"Truman St",
    "iso:country":"AU",
    "sg:address":"2 Truman St",
    "sg:city":"Hurstville",
    "sg:classifiers":[
        {
            "category":"Building & Trades",
            "subcategory":"Cleaning & Sanitation",
            "type":"Services"
        }
    ],
    "sg:phone":"+61 2 9570 2401",
    "sg:postcode":"2220",
    "sg:province":"NSW",
    "sg:tags":[
        "sweeping",
        "machine"
    ],
    "wof:name":"Australian Brush Co",
    "wof:placetype":"venue"
},
  "geometry": {"coordinates":[151.09971618599999,-33.9747505188],"type":"Point"}
}