{
  "type": "Feature",
  "properties": {
    "addr:full":"30 Alambi Ave Broadbeach Waters QLD 4218",
    "addr:housenumber":"30",
    "addr:postcode":"4218",
    "addr:street":"Alambi Ave",
    "iso:country":"AU",
    "sg:address":"30 Alambi Ave",
    "sg:city":"Broadbeach Waters",
    "sg:classifiers":[
        {
            "category":"Building & Trades",
            "subcategory":"Construction",
            "type":"Services"
        }
    ],
    "sg:phone":"+61 418 757 267",
    "sg:postcode":"4218",
    "sg:province":"QLD",
    "sg:tags":[
        "contractor"
    ],
    "wof:name":"Dunn P C",
    "wof:placetype":"venue"
},
  "geometry": {"coordinates":[153.42320251500001,-28.0227165222],"type":"Point"}
}