{
  "type": "Feature",
  "properties": {
    "iso:country":"AU",
    "sg:address":"Deer Park 192 Spooners Ave",
    "sg:city":"Kempsey West",
    "sg:classifiers":[
        {
            "category":"Communications",
            "subcategory":"News Services",
            "type":"Services"
        }
    ],
    "sg:phone":"+61 2 6563 1056",
    "sg:postcode":"2440",
    "sg:province":"NSW",
    "sg:tags":[
        "information",
        "tourist",
        "attractions"
    ],
    "wof:name":"Mesopotamia Lodge",
    "wof:placetype":"venue"
},
  "geometry": {"coordinates":[152.824234,-31.015129],"type":"Point"}
}