{
  "type": "Feature",
  "properties": {
    "iso:country":"AU",
    "sg:address":"2 Kable Ave",
    "sg:city":"Tamworth",
    "sg:classifiers":[
        {
            "category":"Retail",
            "subcategory":"Auto Repair",
            "type":"Services"
        }
    ],
    "sg:phone":"+61 2 6766 3688",
    "sg:postcode":"2340",
    "sg:province":"NSW",
    "sg:tags":[
        "automotive",
        "air conditioning"
    ],
    "wof:name":"Bowers Max Auto Service Centre",
    "wof:placetype":"venue"
},
  "geometry": {"coordinates":[150.92791748100001,-31.0905723572],"type":"Point"}
}