{
  "type": "Feature",
  "properties": {
    "iso:country":"AU",
    "sg:address":"6 16 Hearne St",
    "sg:city":"Mortdale",
    "sg:classifiers":[
        {
            "category":"Shopping",
            "subcategory":"Crafts & Fabrics",
            "type":"Retail Goods"
        }
    ],
    "sg:phone":"+61 2 9533 6444",
    "sg:postcode":"2223",
    "sg:province":"NSW",
    "sg:tags":[
        "upholstering",
        "supply"
    ],
    "wof:name":"K S Furniture",
    "wof:placetype":"venue"
},
  "geometry": {"coordinates":[151.066894531,-33.9654579163],"type":"Point"}
}