{
  "type": "Feature",
  "properties": {
    "addr:full":"38 Grant Ave Gisborne VIC 3437",
    "addr:housenumber":"38",
    "addr:postcode":"3437",
    "addr:street":"Grant Ave",
    "iso:country":"AU",
    "sg:address":"38 Grant Ave",
    "sg:city":"Gisborne",
    "sg:classifiers":[
        {
            "category":"Shopping",
            "subcategory":"Party Supplies",
            "type":"Retail Goods"
        }
    ],
    "sg:phone":"+61 3 5428 3247",
    "sg:postcode":"3437",
    "sg:province":"VIC",
    "sg:tags":[
        "selling",
        "plan"
    ],
    "wof:name":"Pats Gift Parties",
    "wof:placetype":"venue"
},
  "geometry": {"coordinates":[144.59539794899999,-37.4957847595],"type":"Point"}
}