{
  "type": "Feature",
  "properties": {
    "addr:full":"181 Paramatta Rd Annandale NSW 2038",
    "addr:housenumber":"181",
    "addr:postcode":"2038",
    "addr:street":"Paramatta Rd",
    "iso:country":"AU",
    "sg:address":"181 Paramatta Rd",
    "sg:city":"Annandale",
    "sg:classifiers":[
        {
            "category":"Home & Garden",
            "subcategory":"Building Materials",
            "type":"Retail Goods"
        }
    ],
    "sg:phone":"+61 2 9327 7410",
    "sg:postcode":"2038",
    "sg:province":"NSW",
    "sg:tags":[
        "insulation"
    ],
    "wof:name":"Soundblock Solutions",
    "wof:placetype":"venue"
},
  "geometry": {"coordinates":[151.16503906200001,-33.8880119324],"type":"Point"}
}