{
  "type": "Feature",
  "properties": {
    "addr:full":"18 Kookaburra St Bundaberg QLD 4670",
    "addr:housenumber":"18",
    "addr:postcode":"4670",
    "addr:street":"Kookaburra St",
    "iso:country":"AU",
    "sg:address":"18 Kookaburra St",
    "sg:city":"Bundaberg",
    "sg:classifiers":[
        {
            "category":"Building & Trades",
            "subcategory":"Construction",
            "type":"Services"
        }
    ],
    "sg:phone":"+61 7 4153 1108",
    "sg:postcode":"4670",
    "sg:province":"QLD",
    "sg:tags":[
        "contractor"
    ],
    "wof:name":"Collard S L",
    "wof:placetype":"venue"
},
  "geometry": {"coordinates":[152.35621643100001,-24.8267555237],"type":"Point"}
}