{
  "type": "Feature",
  "properties": {
    "addr:full":"62 Gilbert Rd Windsor QLD 4030",
    "addr:housenumber":"62",
    "addr:postcode":"4030",
    "addr:street":"Gilbert Rd",
    "iso:country":"AU",
    "sg:address":"62 Gilbert Rd",
    "sg:city":"Windsor",
    "sg:classifiers":[
        {
            "category":"Education",
            "subcategory":"Special Training",
            "type":"Public Place"
        }
    ],
    "sg:phone":"+61 7 3352 5666",
    "sg:postcode":"4030",
    "sg:province":"QLD",
    "sg:tags":[
        "tuition-educational"
    ],
    "wof:name":"Rockwood Craft Studio",
    "wof:placetype":"venue"
},
  "geometry": {"coordinates":[153.02409399999999,-27.424543],"type":"Point"}
}