{
  "type": "Feature",
  "properties": {
    "addr:full":"U2/ 26 Gow St Padstow NSW 2211",
    "addr:postcode":"2211",
    "addr:street":"U2 / 26 Gow St",
    "iso:country":"AU",
    "sg:address":"U2/ 26 Gow St",
    "sg:city":"Padstow",
    "sg:classifiers":[
        {
            "category":"Wholesale",
            "subcategory":"Office Equipment",
            "type":"Manufacturing & Wholesale Goods"
        }
    ],
    "sg:phone":"+61 2 9709 8269",
    "sg:postcode":"2211",
    "sg:province":"NSW",
    "sg:tags":[
        "packaging",
        "consultant"
    ],
    "wof:name":"GGM Specialised Distributior",
    "wof:placetype":"venue"
},
  "geometry": {"coordinates":[151.036697,-33.937553],"type":"Point"}
}