{
  "type": "Feature",
  "properties": {
    "addr:full":"Cnr University Ave & Koullias Lane Palmerston NT 0830",
    "addr:postcode":"nt 0830",
    "addr:street":"University Ave & Koullias Lane",
    "iso:country":"AU",
    "sg:address":"Cnr University Ave & Koullias Lane",
    "sg:city":"Palmerston",
    "sg:classifiers":[
        {
            "category":"Autos & Motor Vehicles",
            "subcategory":"Auto Supplies",
            "type":"Retail Goods"
        }
    ],
    "sg:phone":"+61 8 8932 7177",
    "sg:postcode":"0830",
    "sg:province":"NT",
    "sg:tags":[
        "battery",
        "automotive"
    ],
    "wof:name":"Beaurepaires",
    "wof:placetype":"venue"
},
  "geometry": {"coordinates":[130.98535200000001,-12.475826],"type":"Point"}
}