{
  "type": "Feature",
  "properties": {
    "addr:full":"Unit 5/ 22 Ironbark Cl Warabrook NSW 2304",
    "addr:housenumber":"22",
    "addr:postcode":"2304",
    "addr:street":"Ironbark Cl",
    "iso:country":"AU",
    "sg:address":"Unit 5/ 22 Ironbark Cl",
    "sg:city":"Warabrook",
    "sg:classifiers":[
        {
            "category":"Building & Trades",
            "subcategory":"Landscaping Services",
            "type":"Services"
        }
    ],
    "sg:phone":"+61 2 4968 9810",
    "sg:postcode":"2304",
    "sg:province":"NSW",
    "sg:tags":[
        "inspection"
    ],
    "wof:name":"Superior Pest Management",
    "wof:placetype":"venue"
},
  "geometry": {"coordinates":[151.80911254899999,-32.8621902466],"type":"Point"}
}