{
  "type": "Feature",
  "properties": {
    "iso:country":"AU",
    "sg:address":"Crn Macarthur & Raymond St",
    "sg:city":"Sale",
    "sg:classifiers":[
        {
            "category":"Professional",
            "subcategory":"Computer Services",
            "type":"Services"
        }
    ],
    "sg:phone":"+61 3 5144 7022",
    "sg:postcode":"3850",
    "sg:province":"VIC",
    "sg:tags":[
        "repairs",
        "upgrade",
        "equipment"
    ],
    "wof:name":"Leading Edge Computers",
    "wof:placetype":"venue"
},
  "geometry": {"coordinates":[147.081787109,-38.1047897339],"type":"Point"}
}