{
  "type": "Feature",
  "properties": {
    "addr:full":"Centro Warwick Shopping Centre Warwick WA 6024",
    "addr:postcode":"6024",
    "iso:country":"AU",
    "sg:address":"Centro Warwick Shopping Centre",
    "sg:city":"Warwick",
    "sg:classifiers":[
        {
            "category":"Personal",
            "subcategory":"Beauty Salon",
            "type":"Services"
        }
    ],
    "sg:phone":"+61 8 9448 6399",
    "sg:postcode":"6024",
    "sg:province":"WA",
    "sg:website":"http://www.ellaexpress.com.au",
    "wof:name":"Ella Express Ella Bache",
    "wof:placetype":"venue"
},
  "geometry": {"coordinates":[115.80857849100001,-31.8337993622],"type":"Point"}
}