{
  "type": "Feature",
  "properties": {
    "iso:country":"AU",
    "sg:address":"PO Box Clifton Hill 3068",
    "sg:city":"Clifton Hill",
    "sg:classifiers":[
        {
            "category":"Social Services",
            "subcategory":"Retirement Home",
            "type":"Services"
        }
    ],
    "sg:phone":"+61 3 9859 7403",
    "sg:postcode":"3068",
    "sg:province":"VIC",
    "sg:tags":[
        "environmental",
        "consultant",
        "pollution"
    ],
    "wof:name":"S Brizga & Associates Pty Ltd",
    "wof:placetype":"venue"
},
  "geometry": {"coordinates":[144.994598389,-37.7913017273],"type":"Point"}
}