{
  "type": "Feature",
  "properties": {
    "addr:full":"15 Dirk Hartog Rd Bullcreek WA 6149",
    "addr:housenumber":"15",
    "addr:postcode":"6149",
    "addr:street":"Dirk Hartog Rd",
    "iso:country":"AU",
    "sg:address":"15 Dirk Hartog Rd",
    "sg:city":"Bullcreek",
    "sg:classifiers":[
        {
            "category":"Recreation",
            "subcategory":"Fishing",
            "type":"Entertainment"
        }
    ],
    "sg:phone":"+61 8 9310 2280",
    "sg:postcode":"6149",
    "sg:province":"WA",
    "sg:tags":[
        "tackle"
    ],
    "wof:name":"Ozflex Australia",
    "wof:placetype":"venue"
},
  "geometry": {"coordinates":[115.85562899999999,-32.059116],"type":"Point"}
}