{
  "type": "Feature",
  "properties": {
    "addr:full":"Ground Floor 8 Cliff St Milsons Point NSW 2061",
    "addr:housenumber":"8",
    "addr:postcode":"2061",
    "addr:street":"Cliff St",
    "iso:country":"AU",
    "sg:address":"Ground Floor 8 Cliff St",
    "sg:city":"Milsons Point",
    "sg:classifiers":[
        {
            "category":"Shopping",
            "subcategory":"Computers & Home Electronics",
            "type":"Retail Goods"
        }
    ],
    "sg:phone":"+61 1300 301 015",
    "sg:postcode":"2061",
    "sg:province":"NSW",
    "sg:tags":[
        "equipment",
        "multimedia"
    ],
    "wof:name":"Webtrader Pty Ltd",
    "wof:placetype":"venue"
},
  "geometry": {"coordinates":[151.210449219,-33.8457946777],"type":"Point"}
}