{
  "type": "Feature",
  "properties": {
    "addr:full":"2 Mount View Ave Hallam VIC 3803",
    "addr:housenumber":"2",
    "addr:postcode":"3803",
    "addr:street":"Mount View Ave",
    "iso:country":"AU",
    "sg:address":"2 Mount View Ave",
    "sg:city":"Hallam",
    "sg:classifiers":[
        {
            "category":"Personal",
            "subcategory":"Beauty Salon",
            "type":"Services"
        }
    ],
    "sg:phone":"+61 3 9796 3437",
    "sg:postcode":"3803",
    "sg:province":"VIC",
    "sg:tags":[
        "hairdresser"
    ],
    "wof:name":"J L's Hair Design",
    "wof:placetype":"venue"
},
  "geometry": {"coordinates":[145.270553589,-38.0011978149],"type":"Point"}
}