{
  "type": "Feature",
  "properties": {
    "iso:country":"AU",
    "sg:address":"5 Jennaberring Rd",
    "sg:city":"Quairading",
    "sg:classifiers":[
        {
            "category":"Autos & Motor Vehicles",
            "subcategory":"Auto Supplies",
            "type":"Retail Goods"
        }
    ],
    "sg:phone":"+61 8 9645 1206",
    "sg:postcode":"6383",
    "sg:province":"WA",
    "sg:tags":[
        "tyre"
    ],
    "wof:name":"Quairading Tyre & Battery Supplies",
    "wof:placetype":"venue"
},
  "geometry": {"coordinates":[117.401611,-32.009628],"type":"Point"}
}