{
  "type": "Feature",
  "properties": {
    "addr:full":"Main St Coorow WA 6515",
    "addr:postcode":"6515",
    "addr:street":"Main St",
    "iso:country":"AU",
    "sg:address":"Main St",
    "sg:city":"Coorow",
    "sg:classifiers":[
        {
            "category":"Government",
            "subcategory":"Post Office",
            "type":"Public Place"
        }
    ],
    "sg:phone":"+61 8 9952 1133",
    "sg:postcode":"6515",
    "sg:province":"WA",
    "sg:tags":[
        "postal"
    ],
    "wof:name":"Australia Post",
    "wof:placetype":"venue"
},
  "geometry": {"coordinates":[116.022171,-29.882086],"type":"Point"}
}