{
  "type": "Feature",
  "properties": {
    "addr:full":"11 Freeling St Naracoorte SA 5271",
    "addr:housenumber":"11",
    "addr:postcode":"5271",
    "addr:street":"Freeling St",
    "iso:country":"AU",
    "sg:address":"11 Freeling St",
    "sg:city":"Naracoorte",
    "sg:classifiers":[
        {
            "category":"Health Services",
            "subcategory":"Health Practitioner",
            "type":"Services"
        }
    ],
    "sg:phone":"+61 427 617 988",
    "sg:postcode":"5271",
    "sg:province":"SA",
    "sg:tags":[
        "bowen",
        "therapy"
    ],
    "wof:name":"Dianne Downward",
    "wof:placetype":"venue"
},
  "geometry": {"coordinates":[140.732529,-36.953323],"type":"Point"}
}