{
  "type": "Feature",
  "properties": {
    "iso:country":"AU",
    "sg:address":"90- 92 Queen St",
    "sg:city":"Busselton",
    "sg:classifiers":[
        {
            "category":"Shopping",
            "subcategory":"Clothing, Apparel, & Fashions",
            "type":"Retail Goods"
        }
    ],
    "sg:phone":"+61 8 9752 1192",
    "sg:postcode":"6280",
    "sg:province":"WA",
    "sg:tags":[
        "menswear"
    ],
    "wof:name":"Mensland",
    "wof:placetype":"venue"
},
  "geometry": {"coordinates":[115.344833374,-33.6514778137],"type":"Point"}
}