{
  "type": "Feature",
  "properties": {
    "addr:full":"81 Torrens Rd Brompton SA 5007",
    "addr:housenumber":"81",
    "addr:postcode":"5007",
    "addr:street":"Torrens Rd",
    "iso:country":"AU",
    "sg:address":"81 Torrens Rd",
    "sg:city":"Brompton",
    "sg:classifiers":[
        {
            "category":"Bars & Pubs",
            "subcategory":"Lounge",
            "type":"Food & Drink"
        }
    ],
    "sg:phone":"+61 8 8340 4344",
    "sg:postcode":"5007",
    "sg:province":"SA",
    "sg:tags":[
        "water",
        "filter",
        "drinking"
    ],
    "sg:website":"http://www.crystalclearaustralia.com",
    "wof:name":"Crystal Clear Purification Systems",
    "wof:placetype":"venue"
},
  "geometry": {"coordinates":[138.57948303200001,-34.8938980103],"type":"Point"}
}