{
  "type": "Feature",
  "properties": {
    "addr:full":"Unit 1 173 Finch St Glen Iris VIC 3146",
    "addr:housenumber":"173",
    "addr:postcode":"3146",
    "addr:street":"Finch St",
    "iso:country":"AU",
    "sg:address":"Unit 1 173 Finch St",
    "sg:city":"Glen Iris",
    "sg:classifiers":[
        {
            "category":"Food & Beverages",
            "subcategory":"Meat & Fish",
            "type":"Retail Goods"
        }
    ],
    "sg:phone":"+61 414 576 189",
    "sg:postcode":"3146",
    "sg:province":"VIC",
    "sg:tags":[
        "aquaculture"
    ],
    "wof:name":"Southern Aquaculture Corporation Pty Ltd",
    "wof:placetype":"venue"
},
  "geometry": {"coordinates":[145.04530334500001,-37.8598976135],"type":"Point"}
}