{
  "type": "Feature",
  "properties": {
    "iso:country":"AU",
    "sg:address":"Suite E/ 42 Upper Heidelberg Rd",
    "sg:city":"Ivanhoe",
    "sg:classifiers":[
        {
            "category":"Building & Trades",
            "subcategory":"Construction",
            "type":"Services"
        }
    ],
    "sg:phone":"+61 1300 660 001",
    "sg:postcode":"3079",
    "sg:province":"VIC",
    "sg:tags":[
        "earth",
        "excavating",
        "moving",
        "contractor"
    ],
    "wof:name":"Ground Hog Earthmoving",
    "wof:placetype":"venue"
},
  "geometry": {"coordinates":[145.04090881400001,-37.7712516785],"type":"Point"}
}