{
  "type": "Feature",
  "properties": {
    "iso:country":"AU",
    "sg:address":"Horizon Drv",
    "sg:city":"Ballina",
    "sg:classifiers":[
        {
            "category":"Education",
            "subcategory":"School",
            "type":"Public Place"
        }
    ],
    "sg:phone":"+61 2 6681 5054",
    "sg:postcode":"2478",
    "sg:province":"NSW",
    "wof:name":"Emmanuel Anglican College",
    "wof:placetype":"venue"
},
  "geometry": {"coordinates":[153.53640747099999,-28.8592376709],"type":"Point"}
}