{
  "type": "Feature",
  "properties": {
    "addr:full":"2/ 282-282 Guildford Rd Guildford NSW 2161",
    "addr:housenumber":"/ 282-282",
    "addr:postcode":"2161",
    "addr:street":"Guildford Rd",
    "iso:country":"AU",
    "sg:address":"2/ 282-282 Guildford Rd",
    "sg:city":"Guildford",
    "sg:classifiers":[
        {
            "category":"Personal",
            "subcategory":"Hair Removal",
            "type":"Services"
        }
    ],
    "sg:phone":"+61 2 9786 4566",
    "sg:postcode":"2161",
    "sg:province":"NSW",
    "wof:name":"Guildford Laser Clinic",
    "wof:placetype":"venue"
},
  "geometry": {"coordinates":[150.987457275,-33.8543777466],"type":"Point"}
}