{
  "type": "Feature",
  "properties": {
    "addr:full":"Unit 2A, Lot 33 Beddingfield St Bunbury WA 6230",
    "addr:housenumber":"unit 2a lot 33",
    "addr:postcode":"6230",
    "addr:street":"Beddingfield St",
    "iso:country":"AU",
    "sg:address":"Unit 2A, Lot 33 Beddingfield St",
    "sg:city":"Bunbury",
    "sg:classifiers":[
        {
            "category":"Building & Trades",
            "subcategory":"Cleaning & Sanitation",
            "type":"Services"
        }
    ],
    "sg:phone":"+61 8 9725 2525",
    "sg:postcode":"6230",
    "sg:province":"WA",
    "sg:tags":[
        "cleaner",
        "repairer",
        "roof"
    ],
    "wof:name":"South West Roof Painters Pty Ltd",
    "wof:placetype":"venue"
},
  "geometry": {"coordinates":[115.67717,-33.35651],"type":"Point"}
}