{
  "type": "Feature",
  "properties": {
    "iso:country":"AU",
    "sg:address":"1st Floor 5 Walker St",
    "sg:city":"Helensburgh",
    "sg:classifiers":[
        {
            "category":"Professional",
            "subcategory":"Accounting & Tax Preparation",
            "type":"Services"
        }
    ],
    "sg:phone":"+61 2 4294 3320",
    "sg:postcode":"2508",
    "sg:province":"NSW",
    "sg:tags":[
        "consultant",
        "taxation"
    ],
    "wof:name":"Helensburgh Taxation Services",
    "wof:placetype":"venue"
},
  "geometry": {"coordinates":[150.982193,-34.190876],"type":"Point"}
}