{
  "type": "Feature",
  "properties": {
    "addr:full":"Beenak Rd Hoddles Creek VIC 3139",
    "addr:postcode":"3139",
    "addr:street":"Beenak Rd",
    "iso:country":"AU",
    "sg:address":"Beenak Rd",
    "sg:city":"Hoddles Creek",
    "sg:classifiers":[
        {
            "category":"Food & Beverages",
            "subcategory":"Fruits & Vegetables",
            "type":"Retail Goods"
        }
    ],
    "sg:phone":"+61 3 5967 4206",
    "sg:postcode":"3139",
    "sg:province":"VIC",
    "sg:tags":[
        "grower"
    ],
    "wof:name":"Bazzocco J",
    "wof:placetype":"venue"
},
  "geometry": {"coordinates":[145.60801696799999,-37.8839263916],"type":"Point"}
}