{
  "type": "Feature",
  "properties": {
    "addr:full":"Suite 1 1623 Botany Rd Botany NSW 2019",
    "addr:housenumber":"1623",
    "addr:postcode":"2019",
    "addr:street":"Botany Rd",
    "iso:country":"AU",
    "sg:address":"Suite 1 1623 Botany Rd",
    "sg:city":"Botany",
    "sg:classifiers":[
        {
            "category":"Professional",
            "subcategory":"Accounting & Tax Preparation",
            "type":"Services"
        }
    ],
    "sg:phone":"+61 2 9695 1195",
    "sg:postcode":"2019",
    "sg:province":"NSW",
    "sg:tags":[
        "accountant",
        "auditor"
    ],
    "wof:name":"Total Accounting Services",
    "wof:placetype":"venue"
},
  "geometry": {"coordinates":[151.20387268100001,-33.9539909363],"type":"Point"}
}