{
  "type": "Feature",
  "properties": {
    "addr:full":"PO Box 139 Kallista VIC 3791",
    "addr:postcode":"3791",
    "iso:country":"AU",
    "sg:address":"PO Box 139",
    "sg:city":"Kallista",
    "sg:classifiers":[
        {
            "category":"Building & Trades",
            "subcategory":"Cleaning & Sanitation",
            "type":"Services"
        }
    ],
    "sg:phone":"+61 3 9755 3317",
    "sg:postcode":"3791",
    "sg:province":"VIC",
    "sg:tags":[
        "cleaner",
        "repairer",
        "roof"
    ],
    "wof:name":"Aus-tech Roofing",
    "wof:placetype":"venue"
},
  "geometry": {"coordinates":[145.39094543499999,-37.8978004456],"type":"Point"}
}