{
  "type": "Feature",
  "properties": {
    "addr:full":"75 Crown St Sydney NSW 2000",
    "addr:housenumber":"75",
    "addr:postcode":"2000",
    "addr:street":"Crown St",
    "iso:country":"AU",
    "sg:address":"75 Crown St",
    "sg:city":"Sydney",
    "sg:classifiers":[
        {
            "category":"Autos & Motor Vehicles",
            "subcategory":"Automobile Sales",
            "type":"Retail Goods"
        }
    ],
    "sg:phone":"+61 2 9331 5000",
    "sg:postcode":"2000",
    "sg:province":"NSW",
    "sg:tags":[
        "car",
        "new"
    ],
    "wof:name":"Sydney City Ford",
    "wof:placetype":"venue"
},
  "geometry": {"coordinates":[151.216262817,-33.8737869263],"type":"Point"}
}