{
  "type": "Feature",
  "properties": {
    "addr:full":"Shop 80 Runaway Bay Shopping Centre Runaway Bay QLD 4216",
    "addr:housenumber":"shop 80",
    "addr:postcode":"4216",
    "iso:country":"AU",
    "sg:address":"Shop 80 Runaway Bay Shopping Centre",
    "sg:city":"Runaway Bay",
    "sg:classifiers":[
        {
            "category":"Shopping",
            "subcategory":"Clothing, Apparel, & Fashions",
            "type":"Retail Goods"
        }
    ],
    "sg:phone":"+61 7 5528 8067",
    "sg:postcode":"4216",
    "sg:province":"QLD",
    "sg:tags":[
        "lady",
        "wear"
    ],
    "wof:name":"Wombat Boutique",
    "wof:placetype":"venue"
},
  "geometry": {"coordinates":[153.404174805,-27.9105949402],"type":"Point"}
}