{
  "type": "Feature",
  "properties": {
    "iso:country":"AU",
    "sg:address":"Cnr Salesyards & Edgecombe Rds",
    "sg:city":"Kyneton",
    "sg:classifiers":[
        {
            "category":"Home & Garden",
            "subcategory":"Building Materials",
            "type":"Retail Goods"
        }
    ],
    "sg:phone":"+61 3 5422 3796",
    "sg:postcode":"3444",
    "sg:province":"VIC",
    "sg:tags":[
        "fencing"
    ],
    "wof:name":"Pritchard & Dettmann CRT Kyneton",
    "wof:placetype":"venue"
},
  "geometry": {"coordinates":[144.456954956,-37.2511405945],"type":"Point"}
}