{
  "type": "Feature",
  "properties": {
    "iso:country":"AU",
    "sg:address":"Suite 7, Level 1 247 Bayview St",
    "sg:city":"Runaway Bay",
    "sg:classifiers":[
        {
            "category":"Manufacturing",
            "subcategory":"Rubber & Plastics",
            "type":"Manufacturing & Wholesale Goods"
        }
    ],
    "sg:phone":"+61 7 5577 4577",
    "sg:postcode":"4216",
    "sg:province":"QLD",
    "sg:tags":[
        "equipment",
        "card"
    ],
    "wof:name":"Schmick Cards",
    "wof:placetype":"venue"
},
  "geometry": {"coordinates":[153.40415954599999,-27.9216747284],"type":"Point"}
}