{
  "type": "Feature",
  "properties": {
    "addr:full":"The Boulevarde Centre, Suite 7, 68 Jessica Blvde Minyama QLD 4575",
    "addr:housenumber":"68",
    "addr:postcode":"4575",
    "addr:street":"The Boulevarde Centre;Jessica Blvde",
    "iso:country":"AU",
    "sg:address":"The Boulevarde Centre, Suite 7, 68 Jessica Blvde",
    "sg:city":"Minyama",
    "sg:classifiers":[
        {
            "category":"Health Services",
            "subcategory":"Doctor",
            "type":"Services"
        }
    ],
    "sg:phone":"+61 7 5444 5133",
    "sg:postcode":"4575",
    "sg:province":"QLD",
    "sg:tags":[
        "medical",
        "practitioner"
    ],
    "wof:name":"SkinSure",
    "wof:placetype":"venue"
},
  "geometry": {"coordinates":[153.12390099999999,-26.699591],"type":"Point"}
}