{
  "type": "Feature",
  "properties": {
    "iso:country":"AU",
    "sg:address":"25 Brisbane Rd",
    "sg:city":"Bundamba",
    "sg:classifiers":[
        {
            "category":"Autos & Motor Vehicles",
            "subcategory":"Auto Supplies",
            "type":"Retail Goods"
        }
    ],
    "sg:phone":"+61 7 3282 5484",
    "sg:postcode":"4304",
    "sg:province":"QLD",
    "sg:tags":[
        "part",
        "cycles",
        "accessory"
    ],
    "wof:name":"Yamaha West",
    "wof:placetype":"venue"
},
  "geometry": {"coordinates":[152.81013488799999,-27.6090507507],"type":"Point"}
}