{
  "type": "Feature",
  "properties": {
    "addr:full":"3 Advantage Drv Dandenong South VIC 3175",
    "addr:housenumber":"3",
    "addr:postcode":"3175",
    "addr:street":"Advantage Drv",
    "iso:country":"AU",
    "sg:address":"3 Advantage Drv",
    "sg:city":"Dandenong South",
    "sg:classifiers":[
        {
            "category":"Retail",
            "subcategory":"Auto Repair",
            "type":"Services"
        }
    ],
    "sg:phone":"+61 3 9793 9044",
    "sg:postcode":"3175",
    "sg:province":"VIC",
    "sg:tags":[
        "body",
        "builder",
        "motor"
    ],
    "wof:name":"VTB International Pty Ltd",
    "wof:placetype":"venue"
},
  "geometry": {"coordinates":[145.22567749000001,-38.0189819336],"type":"Point"}
}