{
  "type": "Feature",
  "properties": {
    "iso:country":"AU",
    "sg:address":"10 Kerri Crt",
    "sg:city":"Sunbury",
    "sg:classifiers":[
        {
            "category":"Real Estate",
            "subcategory":"Real Estate Services",
            "type":"Services"
        }
    ],
    "sg:phone":"+61 3 9740 7005",
    "sg:postcode":"3429",
    "sg:province":"VIC",
    "sg:tags":[
        "valuer"
    ],
    "wof:name":"Philip Thomas & Associates",
    "wof:placetype":"venue"
},
  "geometry": {"coordinates":[144.71546935999999,-37.5703392029],"type":"Point"}
}