{
  "type": "Feature",
  "properties": {
    "addr:full":"173 St Johns Rd Glebe NSW 2037",
    "addr:housenumber":"173",
    "addr:postcode":"2037",
    "addr:street":"St Johns Rd",
    "iso:country":"AU",
    "sg:address":"173 St Johns Rd",
    "sg:city":"Glebe",
    "sg:classifiers":[
        {
            "category":"Health Services",
            "subcategory":"Health Practitioner",
            "type":"Services"
        }
    ],
    "sg:phone":"+61 2 9552 2934",
    "sg:postcode":"2037",
    "sg:province":"NSW",
    "sg:tags":[
        "psychologist"
    ],
    "wof:name":"Lee Alan R",
    "wof:placetype":"venue"
},
  "geometry": {"coordinates":[151.183395386,-33.8830337524],"type":"Point"}
}