{
  "type": "Feature",
  "properties": {
    "iso:country":"AU",
    "sg:address":"Shop 4, 2- 8 Burwood Hwy",
    "sg:city":"Burwood East",
    "sg:classifiers":[
        {
            "category":"Personal",
            "subcategory":"Beauty Salon",
            "type":"Services"
        }
    ],
    "sg:phone":"+61 3 9808 3334",
    "sg:postcode":"3151",
    "sg:province":"VIC",
    "sg:tags":[
        "hairdresser"
    ],
    "wof:name":"Ultimate Hairworks & Beauty",
    "wof:placetype":"venue"
},
  "geometry": {"coordinates":[145.095794678,-37.850528717],"type":"Point"}
}