{
  "type": "Feature",
  "properties": {
    "iso:country":"AU",
    "sg:address":"Cnr Lincoln & Winton Rds",
    "sg:city":"Joondalup",
    "sg:classifiers":[
        {
            "category":"Retail",
            "subcategory":"Auto Repair",
            "type":"Services"
        }
    ],
    "sg:phone":"+61 8 9300 2555",
    "sg:postcode":"6027",
    "sg:province":"WA",
    "sg:tags":[
        "electrical"
    ],
    "wof:name":"Autoelec Direct",
    "wof:placetype":"venue"
},
  "geometry": {"coordinates":[115.76342010499999,-31.7523574829],"type":"Point"}
}