{
  "type": "Feature",
  "properties": {
    "iso:country":"AU",
    "sg:address":"Suite 4 8- 10 The Avenue",
    "sg:city":"Hurstville",
    "sg:classifiers":[
        {
            "category":"Real Estate",
            "subcategory":"Surveying",
            "type":"Services"
        }
    ],
    "sg:phone":"+61 2 9586 4401",
    "sg:postcode":"2220",
    "sg:province":"NSW",
    "sg:tags":[
        "surveyor",
        "quantity"
    ],
    "wof:name":"Archi-QS",
    "wof:placetype":"venue"
},
  "geometry": {"coordinates":[151.107345581,-33.9662857056],"type":"Point"}
}