{
  "type": "Feature",
  "properties": {
    "iso:country":"AU",
    "sg:address":"225 - 227 John St",
    "sg:city":"Singleton",
    "sg:classifiers":[
        {
            "category":"Farming",
            "subcategory":"Farm & Veterinary Services",
            "type":"Manufacturing & Wholesale Goods"
        }
    ],
    "sg:phone":"+61 2 6571 3486",
    "sg:postcode":"2330",
    "sg:province":"NSW",
    "sg:tags":[
        "irrigation",
        "reticulation",
        "system"
    ],
    "wof:name":"Brooks Water Solutions",
    "wof:placetype":"venue"
},
  "geometry": {"coordinates":[151.171524,-32.561077],"type":"Point"}
}