{
  "type": "Feature",
  "properties": {
    "addr:full":"45- 47 Blaxland Rd Campbelltown NSW 2560",
    "addr:housenumber":"47",
    "addr:postcode":"2560",
    "addr:street":"Blaxland Rd",
    "iso:country":"AU",
    "sg:address":"45- 47 Blaxland Rd",
    "sg:city":"Campbelltown",
    "sg:classifiers":[
        {
            "category":"Autos & Motor Vehicles",
            "subcategory":"Automobile Sales",
            "type":"Retail Goods"
        }
    ],
    "sg:phone":"+61 1800 353 576",
    "sg:postcode":"2560",
    "sg:province":"NSW",
    "sg:tags":[
        "car",
        "new"
    ],
    "wof:name":"Saxon Used Cars",
    "wof:placetype":"venue"
},
  "geometry": {"coordinates":[150.81364440900001,-34.0595245361],"type":"Point"}
}