{
  "type": "Feature",
  "properties": {
    "addr:full":"11 Lawrenny Crt Barwon Heads VIC 3227",
    "addr:housenumber":"11",
    "addr:postcode":"3227",
    "addr:street":"Lawrenny Crt",
    "iso:country":"AU",
    "sg:address":"11 Lawrenny Crt",
    "sg:city":"Barwon Heads",
    "sg:classifiers":[
        {
            "category":"Building & Trades",
            "subcategory":"Plumbing",
            "type":"Services"
        }
    ],
    "sg:phone":"+61 417 529 261",
    "sg:postcode":"3227",
    "sg:province":"VIC",
    "sg:tags":[
        "plumber",
        "gasfitters"
    ],
    "wof:name":"Izatt J W",
    "wof:placetype":"venue"
},
  "geometry": {"coordinates":[144.484543,-38.280201],"type":"Point"}
}