{
  "type": "Feature",
  "properties": {
    "addr:full":"Beresford Rd Lilydale VIC 3140",
    "addr:postcode":"3140",
    "addr:street":"Beresford Rd",
    "iso:country":"AU",
    "sg:address":"Beresford Rd",
    "sg:city":"Lilydale",
    "sg:classifiers":[
        {
            "category":"Retail",
            "subcategory":"Auto Repair",
            "type":"Services"
        }
    ],
    "sg:phone":"+61 3 9739 7222",
    "sg:postcode":"3140",
    "sg:province":"VIC",
    "sg:tags":[
        "electrical"
    ],
    "wof:name":"A. Emergency On-Site Auto Electrics",
    "wof:placetype":"venue"
},
  "geometry": {"coordinates":[145.35198974599999,-37.7515144348],"type":"Point"}
}