{
  "type": "Feature",
  "properties": {
    "addr:full":"518 Murphy St Lavington NSW 2641",
    "addr:housenumber":"518",
    "addr:postcode":"2641",
    "addr:street":"Murphy St",
    "iso:country":"AU",
    "sg:address":"518 Murphy St",
    "sg:city":"Lavington",
    "sg:phone":"+61 2 6040 1919",
    "sg:postcode":"2641",
    "sg:province":"NSW",
    "wof:name":"Grace Glass",
    "wof:placetype":"venue"
},
  "geometry": {"coordinates":[146.935302734,-36.0299797058],"type":"Point"}
}