{
  "type": "Feature",
  "properties": {
    "iso:country":"AU",
    "sg:address":"83 Station St",
    "sg:city":"Fairfield",
    "sg:classifiers":[
        {
            "category":"Personal",
            "subcategory":"Tanning Parlor",
            "type":"Services"
        }
    ],
    "sg:phone":"+61 3 9481 1141",
    "sg:postcode":"3078",
    "sg:province":"VIC",
    "sg:tags":[
        "solarium"
    ],
    "wof:name":"Love And Beauty",
    "wof:placetype":"venue"
},
  "geometry": {"coordinates":[145.01824951200001,-37.7793502808],"type":"Point"}
}