{
  "type": "Feature",
  "properties": {
    "addr:full":"PO Box 316 Gembrook VIC 3783",
    "addr:postcode":"3783",
    "iso:country":"AU",
    "sg:address":"PO Box 316",
    "sg:city":"Gembrook",
    "sg:classifiers":[
        {
            "category":"Utilities",
            "subcategory":"Electric",
            "type":"Services"
        }
    ],
    "sg:phone":"+61 409 681 659",
    "sg:postcode":"3783",
    "sg:province":"VIC",
    "sg:tags":[
        "electrical",
        "contractor"
    ],
    "wof:name":"L R K Electrics",
    "wof:placetype":"venue"
},
  "geometry": {"coordinates":[145.60986299999999,-37.983158],"type":"Point"}
}