{
  "type": "Feature",
  "properties": {
    "iso:country":"AU",
    "sg:address":"608 Fishery Pt Rd",
    "sg:city":"Morisset",
    "sg:classifiers":[
        {
            "category":"Autos & Motor Vehicles",
            "subcategory":"Auto Supplies",
            "type":"Retail Goods"
        }
    ],
    "sg:phone":"+61 2 4973 4772",
    "sg:postcode":"2264",
    "sg:province":"NSW",
    "sg:tags":[
        "tyre"
    ],
    "wof:name":"Smartfix Automotive",
    "wof:placetype":"venue"
},
  "geometry": {"coordinates":[151.503189,-33.109833],"type":"Point"}
}