{
  "type": "Feature",
  "properties": {
    "addr:full":"Level 2 243- 249 Crown St Wollongong NSW 2500",
    "addr:housenumber":"243 249",
    "addr:postcode":"2500",
    "addr:street":"Crown St",
    "iso:country":"AU",
    "sg:address":"Level 2 243- 249 Crown St",
    "sg:city":"Wollongong",
    "sg:classifiers":[
        {
            "category":"Insurance",
            "subcategory":"Hazard Insurance",
            "type":"Services"
        }
    ],
    "sg:phone":"+61 13 15 32",
    "sg:postcode":"2500",
    "sg:province":"NSW",
    "sg:tags":[
        "fire",
        "accident",
        "marine"
    ],
    "wof:name":"CGU",
    "wof:placetype":"venue"
},
  "geometry": {"coordinates":[150.891785,-34.425278],"type":"Point"}
}