{
  "type": "Feature",
  "properties": {
    "addr:full":"Unit 1/ 51 Lusher Rd Croydon VIC 3136",
    "addr:postcode":"3136",
    "addr:street":"51 Lusher Rd",
    "iso:country":"AU",
    "sg:address":"Unit 1/ 51 Lusher Rd",
    "sg:city":"Croydon",
    "sg:classifiers":[
        {
            "category":"Wholesale",
            "subcategory":"Medical Equipment & Supplies",
            "type":"Manufacturing & Wholesale Goods"
        }
    ],
    "sg:phone":"+61 3 9725 6577",
    "sg:postcode":"3136",
    "sg:province":"VIC",
    "sg:tags":[
        "aid",
        "care",
        "health",
        "home"
    ],
    "wof:name":"Victorian Home Health Equipment",
    "wof:placetype":"venue"
},
  "geometry": {"coordinates":[145.27830505399999,-37.8046302795],"type":"Point"}
}