{
  "type": "Feature",
  "properties": {
    "addr:full":"7 Mann St Nambucca Heads NSW 2448",
    "addr:housenumber":"7",
    "addr:postcode":"2448",
    "addr:street":"Mann St",
    "iso:country":"AU",
    "sg:address":"7 Mann St",
    "sg:city":"Nambucca Heads",
    "sg:classifiers":[
        {
            "category":"Professional",
            "subcategory":"Accounting & Tax Preparation",
            "type":"Services"
        }
    ],
    "sg:phone":"+61 2 6568 6197",
    "sg:postcode":"2448",
    "sg:province":"NSW",
    "sg:tags":[
        "accountant",
        "auditor"
    ],
    "wof:name":"Hooykaas Lawry Valjan",
    "wof:placetype":"venue"
},
  "geometry": {"coordinates":[153.00024400000001,-30.641163],"type":"Point"}
}