{
  "type": "Feature",
  "properties": {
    "iso:country":"AU",
    "sg:address":"Castle Towers Cnr Old Northern & Castle Hill Rds",
    "sg:city":"Castle Hill",
    "sg:classifiers":[
        {
            "category":"Food & Beverages",
            "subcategory":"Liquor & Beverages",
            "type":"Retail Goods"
        }
    ],
    "sg:phone":"+61 2 9899 6941",
    "sg:postcode":"2154",
    "sg:province":"NSW",
    "sg:tags":[
        "store"
    ],
    "wof:name":"Vintage Cellars",
    "wof:placetype":"venue"
},
  "geometry": {"coordinates":[151.005249023,-33.7326927185],"type":"Point"}
}