{
  "type": "Feature",
  "properties": {
    "iso:country":"AU",
    "sg:address":"122 Brent St",
    "sg:city":"Glenorchy",
    "sg:classifiers":[
        {
            "category":"Banks & Credit Unions",
            "subcategory":"Bank",
            "type":"Services"
        }
    ],
    "sg:phone":"+61 411 047 727",
    "sg:postcode":"7010",
    "sg:province":"TAS",
    "sg:tags":[
        "equipment",
        "sale",
        "point"
    ],
    "wof:name":"Retail Systems Service",
    "wof:placetype":"venue"
},
  "geometry": {"coordinates":[147.25448608400001,-42.833530426],"type":"Point"}
}