{
  "type": "Feature",
  "properties": {
    "iso:country":"AU",
    "sg:address":"94 Moruya Drv",
    "sg:city":"Grovedale",
    "sg:classifiers":[
        {
            "category":"Retail",
            "subcategory":"Event Space",
            "type":"Services"
        }
    ],
    "sg:phone":"+61 414 584 552",
    "sg:postcode":"3216",
    "sg:province":"VIC",
    "sg:tags":[
        "venue",
        "reception",
        "wedding"
    ],
    "wof:name":"Quality Catering",
    "wof:placetype":"venue"
},
  "geometry": {"coordinates":[144.31735229500001,-38.207824707],"type":"Point"}
}