{
  "type": "Feature",
  "properties": {
    "addr:full":"12 Azalea St Vermont VIC 3133",
    "addr:housenumber":"12",
    "addr:postcode":"3133",
    "addr:street":"Azalea St",
    "iso:country":"AU",
    "sg:address":"12 Azalea St",
    "sg:city":"Vermont",
    "sg:classifiers":[
        {
            "category":"Manufacturing",
            "subcategory":"Rubber & Plastics",
            "type":"Manufacturing & Wholesale Goods"
        }
    ],
    "sg:phone":"+61 3 9872 3355",
    "sg:postcode":"3133",
    "sg:province":"VIC",
    "sg:tags":[
        "fabricator"
    ],
    "wof:name":"Electroweld Engineering Pty Ltd",
    "wof:placetype":"venue"
},
  "geometry": {"coordinates":[145.18411254899999,-37.8342285156],"type":"Point"}
}