{
  "type": "Feature",
  "properties": {
    "addr:full":"687c Brighton Rd Seacliff SA 5049",
    "addr:housenumber":"687c",
    "addr:postcode":"5049",
    "addr:street":"Brighton Rd",
    "iso:country":"AU",
    "sg:address":"687c Brighton Rd",
    "sg:city":"Seacliff",
    "sg:classifiers":[
        {
            "category":"Shopping",
            "subcategory":"Music",
            "type":"Retail Goods"
        }
    ],
    "sg:phone":"+61 8 8358 4161",
    "sg:postcode":"5049",
    "sg:province":"SA",
    "sg:tags":[
        "store"
    ],
    "wof:name":"Resident Records",
    "wof:placetype":"venue"
},
  "geometry": {"coordinates":[138.52441400000001,-35.036964],"type":"Point"}
}