{
  "type": "Feature",
  "properties": {
    "addr:full":"29 Glenwood Drv Croydon VIC 3136",
    "addr:housenumber":"29",
    "addr:postcode":"3136",
    "addr:street":"Glenwood Drv",
    "iso:country":"AU",
    "sg:address":"29 Glenwood Drv",
    "sg:city":"Croydon",
    "sg:classifiers":[
        {
            "category":"Organizations",
            "subcategory":"Professional Association",
            "type":"Services"
        }
    ],
    "sg:phone":"+61 3 9779 9482",
    "sg:postcode":"3136",
    "sg:province":"VIC",
    "sg:tags":[
        "web",
        "internet"
    ],
    "wof:name":"Borosoft",
    "wof:placetype":"venue"
},
  "geometry": {"coordinates":[145.26800537099999,-37.8027153015],"type":"Point"}
}