{
  "type": "Feature",
  "properties": {
    "addr:full":"Comrie St Erindale Centre ACT 2903",
    "addr:postcode":"2903",
    "addr:street":"Comrie St",
    "iso:country":"AU",
    "sg:address":"Comrie St",
    "sg:city":"Erindale Centre",
    "sg:classifiers":[
        {
            "category":"Food & Beverages",
            "subcategory":"Supermarket",
            "type":"Retail Goods"
        }
    ],
    "sg:phone":"+61 2 6231 4711",
    "sg:postcode":"2903",
    "sg:province":"ACT",
    "sg:tags":[
        "grocery",
        "store"
    ],
    "wof:name":"Woolworths Ltd",
    "wof:placetype":"venue"
},
  "geometry": {"coordinates":[149.099121094,-35.40209198],"type":"Point"}
}