{
  "type": "Feature",
  "properties": {
    "addr:full":"28 Moani St Eleebana NSW 2282",
    "addr:housenumber":"28",
    "addr:postcode":"2282",
    "addr:street":"Moani St",
    "iso:country":"AU",
    "sg:address":"28 Moani St",
    "sg:city":"Eleebana",
    "sg:classifiers":[
        {
            "category":"Health Services",
            "subcategory":"Health Practitioner",
            "type":"Services"
        }
    ],
    "sg:phone":"+61 2 4942 7874",
    "sg:postcode":"2282",
    "sg:province":"NSW",
    "sg:tags":[
        "homoeopath"
    ],
    "wof:name":"Mistry Jagruti",
    "wof:placetype":"venue"
},
  "geometry": {"coordinates":[151.63819885300001,-32.9950027466],"type":"Point"}
}