{
  "type": "Feature",
  "properties": {
    "iso:country":"AU",
    "sg:address":"14 Strathaird Rd",
    "sg:city":"Bundall",
    "sg:classifiers":[
        {
            "category":"Retail",
            "subcategory":"Auto Repair",
            "type":"Services"
        }
    ],
    "sg:phone":"+61 7 5538 8266",
    "sg:postcode":"4217",
    "sg:province":"QLD",
    "sg:tags":[
        "beater",
        "painter",
        "panel"
    ],
    "sg:website":"http://www.markmchugh.com.au",
    "wof:name":"Mark McHugh Body Works",
    "wof:placetype":"venue"
},
  "geometry": {"coordinates":[153.403396606,-28.0089588165],"type":"Point"}
}