{
  "type": "Feature",
  "properties": {
    "iso:country":"AU",
    "sg:address":"46 Anna St",
    "sg:city":"Beaudesert",
    "sg:classifiers":[
        {
            "category":"Personal",
            "subcategory":"Nail Salon",
            "type":"Services"
        }
    ],
    "sg:phone":"+61 409 640 281",
    "sg:postcode":"4285",
    "sg:province":"QLD",
    "sg:tags":[
        "artificial"
    ],
    "wof:name":"Sue Watt",
    "wof:placetype":"venue"
},
  "geometry": {"coordinates":[152.998459,-27.988379],"type":"Point"}
}