{
  "type": "Feature",
  "properties": {
    "addr:full":"90-112 Queen St Mall Brisbane QLD 4000",
    "addr:housenumber":"90-112",
    "addr:postcode":"4000",
    "addr:street":"Queen St Mall",
    "iso:country":"AU",
    "sg:address":"90-112 Queen St",
    "sg:city":"Mall Brisbane",
    "sg:classifiers":[
        {
            "category":"Building & Trades",
            "subcategory":"Equipment Rental",
            "type":"Services"
        }
    ],
    "sg:phone":"+61 7 3405 2977",
    "sg:postcode":"4000",
    "sg:province":"QLD",
    "sg:tags":[
        "fitness"
    ],
    "wof:name":"Amart All Sports",
    "wof:placetype":"venue"
},
  "geometry": {"coordinates":[153.02471923799999,-27.4698524475],"type":"Point"}
}