{
  "type": "Feature",
  "properties": {
    "addr:full":"208 Bell St Preston VIC 3072",
    "addr:housenumber":"208",
    "addr:postcode":"3072",
    "addr:street":"Bell St",
    "iso:country":"AU",
    "sg:address":"208 Bell St",
    "sg:city":"Preston",
    "sg:classifiers":[
        {
            "category":"Retail",
            "subcategory":"Auto Repair",
            "type":"Services"
        }
    ],
    "sg:phone":"+61 3 9480 3662",
    "sg:postcode":"3072",
    "sg:province":"VIC",
    "sg:tags":[
        "repairer",
        "motor",
        "engineer"
    ],
    "wof:name":"Alway Automotive",
    "wof:placetype":"venue"
},
  "geometry": {"coordinates":[145.016387939,-37.7464675903],"type":"Point"}
}