{
  "type": "Feature",
  "properties": {
    "addr:full":"1444 Pittwater Rd North Narrabeen NSW 2101",
    "addr:housenumber":"1444",
    "addr:postcode":"2101",
    "addr:street":"Pittwater Rd",
    "iso:country":"AU",
    "sg:address":"1444 Pittwater Rd",
    "sg:city":"North Narrabeen",
    "sg:classifiers":[
        {
            "category":"Shopping",
            "subcategory":"Pets & Pet Supplies",
            "type":"Retail Goods"
        }
    ],
    "sg:phone":"+61 2 9970 7091",
    "sg:postcode":"2101",
    "sg:province":"NSW",
    "sg:tags":[
        "food"
    ],
    "wof:name":"Peninsula Pet Supplies",
    "wof:placetype":"venue"
},
  "geometry": {"coordinates":[151.29705799999999,-33.712868],"type":"Point"}
}