{
  "type": "Feature",
  "properties": {
    "addr:full":"Shop 2/ 447 Little Collins St Melbourne VIC 3000",
    "addr:housenumber":"shop 2 / 447",
    "addr:postcode":"3000",
    "addr:street":"Little Collins St",
    "iso:country":"AU",
    "sg:address":"Shop 2/ 447 Little Collins St",
    "sg:city":"Melbourne",
    "sg:classifiers":[
        {
            "category":"Retail",
            "subcategory":"Repair Shop",
            "type":"Services"
        }
    ],
    "sg:phone":"+61 3 9670 2558",
    "sg:postcode":"3000",
    "sg:province":"VIC",
    "sg:tags":[
        "mending",
        "clothing",
        "alteration"
    ],
    "wof:name":"Deniz Alterations",
    "wof:placetype":"venue"
},
  "geometry": {"coordinates":[144.95993042000001,-37.8164215088],"type":"Point"}
}