{
  "type": "Feature",
  "properties": {
    "addr:full":"Glenelg Specialist Centre, 1 st Floor Glenelg SA 5045",
    "addr:housenumber":"1",
    "addr:postcode":"5045",
    "addr:street":"St",
    "iso:country":"AU",
    "sg:address":"Glenelg Specialist Centre, 1",
    "sg:city":"st Floor Glenelg",
    "sg:classifiers":[
        {
            "category":"Health Services",
            "subcategory":"Doctor",
            "type":"Services"
        }
    ],
    "sg:phone":"+61 8 8376 3800",
    "sg:postcode":"5045",
    "sg:province":"SA",
    "sg:tags":[
        "medical",
        "practitioner"
    ],
    "wof:name":"Hokin J A B",
    "wof:placetype":"venue"
},
  "geometry": {"coordinates":[138.52011100000001,-34.979038],"type":"Point"}
}