{
  "type": "Feature",
  "properties": {
    "iso:country":"AU",
    "sg:address":"193 Kings Rd",
    "sg:city":"Pimlico",
    "sg:classifiers":[
        {
            "category":"Food & Beverages",
            "subcategory":"Groceries & Convenience Stores",
            "type":"Retail Goods"
        }
    ],
    "sg:phone":"+61 7 4779 1829",
    "sg:postcode":"4812",
    "sg:province":"QLD",
    "wof:name":"Walkers Corner",
    "wof:placetype":"venue"
},
  "geometry": {"coordinates":[146.790726,-19.287449],"type":"Point"}
}