{
  "type": "Feature",
  "properties": {
    "addr:full":"45 Murphy St Wangaratta VIC 3677",
    "addr:housenumber":"45",
    "addr:postcode":"3677",
    "addr:street":"Murphy St",
    "iso:country":"AU",
    "sg:address":"45 Murphy St",
    "sg:city":"Wangaratta",
    "sg:classifiers":[
        {
            "category":"Fast Food",
            "type":"Food & Drink"
        }
    ],
    "sg:phone":"+61 3 5721 4026",
    "sg:postcode":"3677",
    "sg:province":"VIC",
    "sg:tags":[
        "away",
        "take"
    ],
    "wof:name":"Centre Takeaway",
    "wof:placetype":"venue"
},
  "geometry": {"coordinates":[146.32574462900001,-36.35572052],"type":"Point"}
}