{
  "type": "Feature",
  "properties": {
    "iso:country":"AU",
    "sg:address":"60 Park St",
    "sg:city":"South Melbourne",
    "sg:classifiers":[
        {
            "category":"Professional",
            "subcategory":"Computer Services",
            "type":"Services"
        }
    ],
    "sg:phone":"+61 3 9674 8888",
    "sg:postcode":"3205",
    "sg:province":"VIC",
    "sg:tags":[
        "package",
        "software"
    ],
    "wof:name":"Tricom Group",
    "wof:placetype":"venue"
},
  "geometry": {"coordinates":[144.969055,-37.83292],"type":"Point"}
}