{
  "type": "Feature",
  "properties": {
    "addr:full":"3 George Pearse Pl East Ballina NSW 2478",
    "addr:housenumber":"3",
    "addr:postcode":"2478",
    "addr:street":"George Pearse Pl",
    "iso:country":"AU",
    "sg:address":"3 George Pearse Pl",
    "sg:city":"East Ballina",
    "sg:classifiers":[
        {
            "category":"Building & Trades",
            "subcategory":"Plumbing",
            "type":"Services"
        }
    ],
    "sg:phone":"+61 2 6686 6544",
    "sg:postcode":"2478",
    "sg:province":"NSW",
    "sg:tags":[
        "plumber",
        "gasfitters"
    ],
    "wof:name":"Court Jim Plumbing",
    "wof:placetype":"venue"
},
  "geometry": {"coordinates":[153.57623290999999,-28.847158432],"type":"Point"}
}