{
  "type": "Feature",
  "properties": {
    "addr:full":"5/ 15 Raine St Woollahra NSW 2025",
    "addr:housenumber":"/ 15",
    "addr:postcode":"2025",
    "addr:street":"Raine St",
    "iso:country":"AU",
    "sg:address":"5/ 15 Raine St",
    "sg:city":"Woollahra",
    "sg:classifiers":[
        {
            "category":"Building & Trades",
            "subcategory":"Cleaning & Sanitation",
            "type":"Services"
        }
    ],
    "sg:phone":"+61 2 9389 1258",
    "sg:postcode":"2025",
    "sg:province":"NSW",
    "sg:tags":[
        "chemical",
        "pressure",
        "steam",
        "contractor"
    ],
    "wof:name":"Panarama Commercial Cleaning Services",
    "wof:placetype":"venue"
},
  "geometry": {"coordinates":[151.25494384800001,-33.8880119324],"type":"Point"}
}