{
  "type": "Feature",
  "properties": {
    "addr:full":"103 Elizabeth St Hobart TAS 7000",
    "addr:housenumber":"103",
    "addr:postcode":"7000",
    "addr:street":"Elizabeth St",
    "iso:country":"AU",
    "sg:address":"103 Elizabeth St",
    "sg:city":"Hobart",
    "sg:classifiers":[
        {
            "category":"Communications",
            "type":"Services"
        }
    ],
    "sg:phone":"+61 3 6231 5578",
    "sg:postcode":"7000",
    "sg:province":"TAS",
    "sg:tags":[
        "public",
        "system",
        "address"
    ],
    "wof:name":"Hobart Music Centre",
    "wof:placetype":"venue"
},
  "geometry": {"coordinates":[147.326416016,-42.8807029724],"type":"Point"}
}