{
  "type": "Feature",
  "properties": {
    "addr:full":"Shop15, 1 Parsons Rd Lisarow NSW 2250",
    "addr:housenumber":"1",
    "addr:postcode":"2250",
    "addr:street":"Parsons Rd",
    "iso:country":"AU",
    "sg:address":"Shop15, 1 Parsons Rd",
    "sg:city":"Lisarow",
    "sg:classifiers":[
        {
            "category":"Health Services",
            "subcategory":"Dentist",
            "type":"Services"
        }
    ],
    "sg:phone":"+61 2 4328 4333",
    "sg:postcode":"2250",
    "sg:province":"NSW",
    "wof:name":"Lisarow Dental Care",
    "wof:placetype":"venue"
},
  "geometry": {"coordinates":[151.366333008,-33.385761261],"type":"Point"}
}