{
  "type": "Feature",
  "properties": {
    "iso:country":"AU",
    "sg:address":"5 Bay St",
    "sg:city":"Tweed Heads",
    "sg:classifiers":[
        {
            "category":"Professional",
            "subcategory":"Detective & Security Services",
            "type":"Services"
        }
    ],
    "sg:phone":"+61 7 5599 1188",
    "sg:postcode":"2485",
    "sg:province":"NSW",
    "sg:tags":[
        "consultant",
        "system"
    ],
    "wof:name":"Combined Electrical Services",
    "wof:placetype":"venue"
},
  "geometry": {"coordinates":[153.54441833499999,-28.1713581085],"type":"Point"}
}