{
  "type": "Feature",
  "properties": {
    "addr:full":"Pacific Hwy Knockrow NSW 2479",
    "addr:postcode":"2479",
    "addr:street":"Pacific Hwy",
    "iso:country":"AU",
    "sg:address":"Pacific Hwy",
    "sg:city":"Knockrow",
    "sg:classifiers":[
        {
            "category":"Manufacturing",
            "subcategory":"Food",
            "type":"Manufacturing & Wholesale Goods"
        }
    ],
    "sg:phone":"+61 2 6687 8432",
    "sg:postcode":"2479",
    "sg:province":"NSW",
    "sg:tags":[
        "product",
        "nut",
        "edible"
    ],
    "wof:name":"The Macadamia Castle",
    "wof:placetype":"venue"
},
  "geometry": {"coordinates":[153.53497314399999,-28.760892868],"type":"Point"}
}