{
  "type": "Feature",
  "properties": {
    "addr:full":"110 Aerodrome Rd Maroochydore QLD 4558",
    "addr:housenumber":"110",
    "addr:postcode":"4558",
    "addr:street":"Aerodrome Rd",
    "iso:country":"AU",
    "sg:address":"110 Aerodrome Rd",
    "sg:city":"Maroochydore",
    "sg:classifiers":[
        {
            "category":"Food & Beverages",
            "subcategory":"Bakery",
            "type":"Retail Goods"
        }
    ],
    "sg:phone":"+61 7 5443 3303",
    "sg:postcode":"4558",
    "sg:province":"QLD",
    "sg:tags":[
        "cake",
        "shop",
        "pastry"
    ],
    "wof:name":"Gold Star Bakery",
    "wof:placetype":"venue"
},
  "geometry": {"coordinates":[153.09471130399999,-26.657913208],"type":"Point"}
}