{
  "type": "Feature",
  "properties": {
    "iso:country":"AU",
    "sg:address":"Unit 15 115 Robinson Rd (East)",
    "sg:city":"Geebung",
    "sg:classifiers":[
        {
            "category":"Building & Trades",
            "subcategory":"Plumbing",
            "type":"Services"
        }
    ],
    "sg:phone":"+61 7 3216 5855",
    "sg:postcode":"4034",
    "sg:province":"QLD",
    "sg:tags":[
        "plumber",
        "gasfitters"
    ],
    "wof:name":"Bathrooms Are Us",
    "wof:placetype":"venue"
},
  "geometry": {"coordinates":[153.056625,-27.369617],"type":"Point"}
}