{
  "type": "Feature",
  "properties": {
    "addr:full":"Shop 20, Winthrop Village Shopng Cntr Winthrop WA 6150",
    "addr:housenumber":"shop 20",
    "addr:postcode":"6150",
    "addr:street":"Winthrop Village Shopng Cntr",
    "iso:country":"AU",
    "sg:address":"Shop 20, Winthrop Village Shopng Cntr",
    "sg:city":"Winthrop",
    "sg:classifiers":[
        {
            "category":"Cafe",
            "type":"Food & Drink"
        }
    ],
    "sg:phone":"+61 8 9310 5515",
    "sg:postcode":"6150",
    "sg:province":"WA",
    "wof:name":"Hawker's Cafe",
    "wof:placetype":"venue"
},
  "geometry": {"coordinates":[115.825378,-32.048622],"type":"Point"}
}