{
  "type": "Feature",
  "properties": {
    "iso:country":"AU",
    "sg:address":"PO Box 985",
    "sg:city":"Slacks Creek",
    "sg:classifiers":[
        {
            "category":"Farming",
            "subcategory":"Crops",
            "type":"Manufacturing & Wholesale Goods"
        }
    ],
    "sg:phone":"+61 7 3875 2800",
    "sg:postcode":"4127",
    "sg:province":"QLD",
    "sg:tags":[
        "warehousing"
    ],
    "wof:name":"Malcolm Janke Transport",
    "wof:placetype":"venue"
},
  "geometry": {"coordinates":[153.12637329099999,-27.6395797729],"type":"Point"}
}