{
  "type": "Feature",
  "properties": {
    "addr:full":"102 Sunnyholt Rd Blacktown NSW 2148",
    "addr:housenumber":"102",
    "addr:postcode":"2148",
    "addr:street":"Sunnyholt Rd",
    "iso:country":"AU",
    "sg:address":"102 Sunnyholt Rd",
    "sg:city":"Blacktown",
    "sg:classifiers":[
        {
            "category":"Autos & Motor Vehicles",
            "subcategory":"Automobile Sales",
            "type":"Retail Goods"
        }
    ],
    "sg:phone":"+61 2 9831 1566",
    "sg:postcode":"2148",
    "sg:province":"NSW",
    "sg:tags":[
        "car",
        "new"
    ],
    "wof:name":"Blacktown Daihatsu",
    "wof:placetype":"venue"
},
  "geometry": {"coordinates":[150.91421508799999,-33.7577972412],"type":"Point"}
}