{
  "type": "Feature",
  "properties": {
    "addr:full":"Shop 2/ 332 Guildford Rd Guildford NSW 2161",
    "addr:housenumber":"shop 2 / 332",
    "addr:postcode":"2161",
    "addr:street":"Guildford Rd",
    "iso:country":"AU",
    "sg:address":"Shop 2/ 332 Guildford Rd",
    "sg:city":"Guildford",
    "sg:classifiers":[
        {
            "category":"Food & Beverages",
            "subcategory":"Fruits & Vegetables",
            "type":"Retail Goods"
        }
    ],
    "sg:phone":"+61 2 9681 7695",
    "sg:postcode":"2161",
    "sg:province":"NSW",
    "sg:tags":[
        "greengrocer",
        "fruiterer"
    ],
    "wof:name":"All Seasons Market",
    "wof:placetype":"venue"
},
  "geometry": {"coordinates":[150.986038208,-33.8541107178],"type":"Point"}
}