{
  "type": "Feature",
  "properties": {
    "iso:country":"AU",
    "sg:address":"1/ 378 High St",
    "sg:city":"Maitland",
    "sg:classifiers":[
        {
            "category":"Shopping",
            "subcategory":"Jewelry",
            "type":"Retail Goods"
        }
    ],
    "sg:phone":"+61 2 4934 4500",
    "sg:postcode":"2320",
    "sg:province":"NSW",
    "sg:tags":[
        "jeweller"
    ],
    "wof:name":"Maitland City Jewellers",
    "wof:placetype":"venue"
},
  "geometry": {"coordinates":[151.55345153799999,-32.7311172485],"type":"Point"}
}