{
  "type": "Feature",
  "properties": {
    "iso:country":"AU",
    "sg:address":"16 Kiama Pl",
    "sg:city":"Blackmans Bay",
    "sg:classifiers":[
        {
            "category":"Arena",
            "subcategory":"Sports Club",
            "type":"Entertainment"
        }
    ],
    "sg:phone":"+61 1300 888 713",
    "sg:postcode":"7052",
    "sg:province":"TAS",
    "sg:tags":[
        "organisation",
        "sporting"
    ],
    "wof:name":"Tasmanian Little Athletics Association",
    "wof:placetype":"venue"
},
  "geometry": {"coordinates":[147.32124300000001,-42.993576],"type":"Point"}
}