{
  "type": "Feature",
  "properties": {
    "addr:full":"Shop 3/ 176 Seacombe Rd Seaview Downs SA 5049",
    "addr:housenumber":"shop 3 / 176",
    "addr:postcode":"5049",
    "addr:street":"Seacombe Rd",
    "iso:country":"AU",
    "sg:address":"Shop 3/ 176 Seacombe Rd",
    "sg:city":"Seaview Downs",
    "sg:classifiers":[
        {
            "category":"Personal",
            "subcategory":"Beauty Salon",
            "type":"Services"
        }
    ],
    "sg:phone":"+61 8 8377 5157",
    "sg:postcode":"5049",
    "sg:province":"SA",
    "wof:name":"Reflections Of Beauty",
    "wof:placetype":"venue"
},
  "geometry": {"coordinates":[138.53907799999999,-35.029556],"type":"Point"}
}