{
  "type": "Feature",
  "properties": {
    "iso:country":"AU",
    "sg:address":"351 Plummer St",
    "sg:city":"Port Melbourne",
    "sg:classifiers":[
        {
            "category":"Home & Garden",
            "subcategory":"Hardware",
            "type":"Retail Goods"
        }
    ],
    "sg:phone":"+61 3 9646 1081",
    "sg:postcode":"3207",
    "sg:province":"VIC",
    "sg:tags":[
        "supply",
        "maker",
        "cabinet"
    ],
    "wof:name":"Australian Furniture Timbers",
    "wof:placetype":"venue"
},
  "geometry": {"coordinates":[144.92152400000001,-37.833187],"type":"Point"}
}