{
  "type": "Feature",
  "properties": {
    "addr:full":"Shp 3/ 521 Bridge Rd Para Hills SA 5096",
    "addr:housenumber":"/ 521",
    "addr:postcode":"5096",
    "addr:street":"Bridge Rd",
    "iso:country":"AU",
    "sg:address":"Shp 3/ 521 Bridge Rd",
    "sg:city":"Para Hills",
    "sg:classifiers":[
        {
            "category":"Fast Food",
            "type":"Food & Drink"
        }
    ],
    "sg:phone":"+61 8 8250 4328",
    "sg:postcode":"5096",
    "sg:province":"SA",
    "sg:tags":[
        "away",
        "take"
    ],
    "wof:name":"Select Chickens",
    "wof:placetype":"venue"
},
  "geometry": {"coordinates":[138.65666198700001,-34.7988166809],"type":"Point"}
}