{
  "type": "Feature",
  "properties": {
    "addr:full":"Shop 3, 21 Campbell St Blacktown NSW 2148",
    "addr:housenumber":"shop;21",
    "addr:postcode":"2148",
    "addr:street":"Campbell St",
    "iso:country":"AU",
    "sg:address":"Shop 3, 21 Campbell St",
    "sg:city":"Blacktown",
    "sg:classifiers":[
        {
            "category":"Health Services",
            "subcategory":"Health Practitioner",
            "type":"Services"
        }
    ],
    "sg:phone":"+61 2 9622 3115",
    "sg:postcode":"2148",
    "sg:province":"NSW",
    "sg:tags":[
        "homoeopath"
    ],
    "wof:name":"Lynne Castellari",
    "wof:placetype":"venue"
},
  "geometry": {"coordinates":[150.90927124000001,-33.7714271545],"type":"Point"}
}