{
  "type": "Feature",
  "properties": {
    "iso:country":"AU",
    "sg:address":"84 George St",
    "sg:city":"Launceston",
    "sg:classifiers":[
        {
            "category":"Home & Garden",
            "subcategory":"Kitchen Supply",
            "type":"Retail Goods"
        }
    ],
    "sg:phone":"+61 3 6331 7677",
    "sg:postcode":"7250",
    "sg:province":"TAS",
    "sg:tags":[
        "equipment",
        "diving"
    ],
    "wof:name":"Anchor Wet Suits",
    "wof:placetype":"venue"
},
  "geometry": {"coordinates":[147.13990783700001,-41.4358253479],"type":"Point"}
}