{
  "type": "Feature",
  "properties": {
    "iso:country":"AU",
    "sg:address":"5 Tointon St",
    "sg:city":"Toowoomba",
    "sg:classifiers":[
        {
            "category":"Professional",
            "subcategory":"Testing Lab",
            "type":"Services"
        }
    ],
    "sg:phone":"+61 7 4638 7366",
    "sg:postcode":"4350",
    "sg:province":"QLD",
    "sg:tags":[
        "inspection"
    ],
    "wof:name":"Excel Power",
    "wof:placetype":"venue"
},
  "geometry": {"coordinates":[151.94564800000001,-27.56498],"type":"Point"}
}