{
  "type": "Feature",
  "properties": {
    "iso:country":"AU",
    "sg:address":"76 Outram St",
    "sg:city":"West Perth",
    "sg:classifiers":[
        {
            "category":"Professional",
            "subcategory":"Accounting & Tax Preparation",
            "type":"Services"
        }
    ],
    "sg:phone":"+61 8 9321 3275",
    "sg:postcode":"6005",
    "sg:province":"WA",
    "sg:tags":[
        "accountant",
        "auditor"
    ],
    "wof:name":"Kimberley David Accounting",
    "wof:placetype":"venue"
},
  "geometry": {"coordinates":[115.84036254900001,-31.9467906952],"type":"Point"}
}