{
  "type": "Feature",
  "properties": {
    "iso:country":"AU",
    "sg:address":"139B Wynyard St",
    "sg:city":"Tumut",
    "sg:classifiers":[
        {
            "category":"Shopping",
            "subcategory":"Computers & Home Electronics",
            "type":"Retail Goods"
        }
    ],
    "sg:phone":"+61 1300 843 663",
    "sg:postcode":"2720",
    "sg:province":"NSW",
    "sg:tags":[
        "equipment",
        "part",
        "electronic"
    ],
    "wof:name":"ReConnect Communications",
    "wof:placetype":"venue"
},
  "geometry": {"coordinates":[148.22067300000001,-35.302296],"type":"Point"}
}