{
  "type": "Feature",
  "properties": {
    "iso:country":"AU",
    "sg:address":"227 McKinnon Rd",
    "sg:city":"McKinnon",
    "sg:classifiers":[
        {
            "category":"Health Services",
            "subcategory":"Doctor",
            "type":"Services"
        }
    ],
    "sg:phone":"+61 3 9578 3232",
    "sg:postcode":"3204",
    "sg:province":"VIC",
    "sg:tags":[
        "medical",
        "practitioner"
    ],
    "wof:name":"Janko George",
    "wof:placetype":"venue"
},
  "geometry": {"coordinates":[145.041092,-37.911247],"type":"Point"}
}