{
  "type": "Feature",
  "properties": {
    "iso:country":"AU",
    "sg:address":"79 Gt Ocean Rd",
    "sg:city":"Anglesea",
    "sg:classifiers":[
        {
            "category":"Real Estate",
            "subcategory":"Real Estate Services",
            "type":"Services"
        }
    ],
    "sg:phone":"+61 418 526 320",
    "sg:postcode":"3230",
    "sg:province":"VIC",
    "sg:tags":[
        "auctioneer"
    ],
    "wof:name":"Grant Powell",
    "wof:placetype":"venue"
},
  "geometry": {"coordinates":[144.19030799999999,-38.404747],"type":"Point"}
}