{
  "type": "Feature",
  "properties": {
    "iso:country":"AU",
    "sg:address":"1692 Princes Hwy",
    "sg:city":"Clayton",
    "sg:classifiers":[
        {
            "category":"Home & Garden",
            "subcategory":"Hardware",
            "type":"Retail Goods"
        }
    ],
    "sg:phone":"+61 3 9543 7766",
    "sg:postcode":"3168",
    "sg:province":"VIC",
    "sg:tags":[
        "plumber",
        "supply"
    ],
    "wof:name":"Homebase Swan",
    "wof:placetype":"venue"
},
  "geometry": {"coordinates":[145.12121582,-37.9111213684],"type":"Point"}
}