{
  "type": "Feature",
  "properties": {
    "addr:full":"Shop 14A Gladstone Park Drv Tullamarine VIC 3043",
    "addr:housenumber":"14a",
    "addr:postcode":"3043",
    "addr:street":"Gladstone Park Drv",
    "iso:country":"AU",
    "sg:address":"Shop 14A Gladstone Park Drv",
    "sg:city":"Tullamarine",
    "sg:classifiers":[
        {
            "category":"Food & Beverages",
            "subcategory":"Supermarket",
            "type":"Retail Goods"
        }
    ],
    "sg:phone":"+61 3 9338 7898",
    "sg:postcode":"3043",
    "sg:province":"VIC",
    "sg:tags":[
        "grocery",
        "store"
    ],
    "wof:name":"Winying Australia",
    "wof:placetype":"venue"
},
  "geometry": {"coordinates":[144.88438415499999,-37.6890563965],"type":"Point"}
}