{
  "type": "Feature",
  "properties": {
    "addr:full":"80 Mitchell St North Ward QLD 4810",
    "addr:housenumber":"80",
    "addr:postcode":"4810",
    "addr:street":"Mitchell St",
    "iso:country":"AU",
    "sg:address":"80 Mitchell St",
    "sg:city":"North Ward",
    "sg:classifiers":[
        {
            "category":"Travel",
            "subcategory":"Hotels & Motels",
            "type":"Entertainment"
        }
    ],
    "sg:phone":"+61 7 4721 1990",
    "sg:postcode":"4810",
    "sg:province":"QLD",
    "wof:name":"A & A Holiday Apartments",
    "wof:placetype":"venue"
},
  "geometry": {"coordinates":[146.81146200000001,-19.248302],"type":"Point"}
}