{
  "type": "Feature",
  "properties": {
    "addr:full":"Shp 22 Floreat Forum Shpng Cntr Floreat WA 6014",
    "addr:housenumber":"22",
    "addr:postcode":"6014",
    "iso:country":"AU",
    "sg:address":"Shp 22",
    "sg:city":"Floreat Forum Shpng Cntr Floreat",
    "sg:classifiers":[
        {
            "category":"Banks & Credit Unions",
            "subcategory":"Bank",
            "type":"Services"
        }
    ],
    "sg:phone":"+61 13 20 32",
    "sg:postcode":"6014",
    "sg:province":"WA",
    "wof:name":"Westpac",
    "wof:placetype":"venue"
},
  "geometry": {"coordinates":[115.793533325,-31.9379558563],"type":"Point"}
}