{
  "type": "Feature",
  "properties": {
    "iso:country":"AU",
    "sg:address":"215 Power Rd",
    "sg:city":"Endeavour Hills",
    "sg:classifiers":[
        {
            "category":"Professional",
            "subcategory":"Accounting & Tax Preparation",
            "type":"Services"
        }
    ],
    "sg:phone":"+61 3 9886 1025",
    "sg:postcode":"3802",
    "sg:province":"VIC",
    "sg:tags":[
        "accountant",
        "auditor"
    ],
    "wof:name":"S. Bala Chartered Accountant",
    "wof:placetype":"venue"
},
  "geometry": {"coordinates":[145.24197387699999,-37.9753990173],"type":"Point"}
}