{
  "type": "Feature",
  "properties": {
    "iso:country":"AU",
    "sg:address":"37 Moller Drv",
    "sg:city":"Sawtell",
    "sg:classifiers":[
        {
            "category":"Utilities",
            "subcategory":"Electric",
            "type":"Services"
        }
    ],
    "sg:phone":"+61 428 654 241",
    "sg:postcode":"2452",
    "sg:province":"NSW",
    "sg:tags":[
        "electrical",
        "contractor"
    ],
    "wof:name":"Jenkin Phil",
    "wof:placetype":"venue"
},
  "geometry": {"coordinates":[153.08157299999999,-30.374521],"type":"Point"}
}