{
  "type": "Feature",
  "properties": {
    "addr:full":"PO Box 1032 Orange NSW 2800",
    "addr:postcode":"2800",
    "iso:country":"AU",
    "sg:address":"PO Box 1032",
    "sg:city":"Orange",
    "sg:classifiers":[
        {
            "category":"Building & Trades",
            "subcategory":"Construction",
            "type":"Services"
        }
    ],
    "sg:phone":"+61 2 6362 4188",
    "sg:postcode":"2800",
    "sg:province":"NSW",
    "sg:tags":[
        "scaffolding"
    ],
    "wof:name":"Branscaff",
    "wof:placetype":"venue"
},
  "geometry": {"coordinates":[149.09507751500001,-33.2829017639],"type":"Point"}
}