{
  "type": "Feature",
  "properties": {
    "iso:country":"AU",
    "sg:address":"56 High St",
    "sg:city":"Wauchope",
    "sg:classifiers":[
        {
            "category":"Real Estate",
            "subcategory":"Real Estate Agent",
            "type":"Services"
        }
    ],
    "sg:phone":"+61 2 6586 1111",
    "sg:postcode":"2446",
    "sg:province":"NSW",
    "wof:name":"Raine & Horne Wauchope",
    "wof:placetype":"venue"
},
  "geometry": {"coordinates":[152.731705,-31.457432],"type":"Point"}
}