{
  "type": "Feature",
  "properties": {
    "addr:full":"37 Lalina Ave Tweed Heads West NSW 2485",
    "addr:housenumber":"37",
    "addr:postcode":"2485",
    "addr:street":"Lalina Ave;Heads",
    "iso:country":"AU",
    "sg:address":"37 Lalina Ave",
    "sg:city":"Tweed Heads West",
    "sg:classifiers":[
        {
            "category":"Utilities",
            "subcategory":"Electric",
            "type":"Services"
        }
    ],
    "sg:phone":"+61 7 5599 7734",
    "sg:postcode":"2485",
    "sg:province":"NSW",
    "sg:tags":[
        "electrical",
        "contractor"
    ],
    "wof:name":"Saunders Lindsay",
    "wof:placetype":"venue"
},
  "geometry": {"coordinates":[153.50100707999999,-28.1901302338],"type":"Point"}
}