{
  "type": "Feature",
  "properties": {
    "iso:country":"AU",
    "sg:address":"Reynolds St",
    "sg:city":"Mareeba",
    "sg:classifiers":[
        {
            "category":"Home & Garden",
            "subcategory":"Building Materials",
            "type":"Retail Goods"
        }
    ],
    "sg:phone":"+61 7 4092 2086",
    "sg:postcode":"4880",
    "sg:province":"QLD",
    "sg:tags":[
        "supply"
    ],
    "wof:name":"Tableland Concrete Blocks",
    "wof:placetype":"venue"
},
  "geometry": {"coordinates":[145.41966247600001,-17.0052185059],"type":"Point"}
}