{
  "type": "Feature",
  "properties": {
    "iso:country":"AU",
    "sg:address":"RMB 3741 McCreery Rd",
    "sg:city":"Kalannie",
    "sg:classifiers":[
        {
            "category":"Farming",
            "subcategory":"Farm",
            "type":"Manufacturing & Wholesale Goods"
        }
    ],
    "sg:phone":"+61 8 9666 2015",
    "sg:postcode":"6468",
    "sg:province":"WA",
    "sg:tags":[
        "farmer"
    ],
    "wof:name":"McCreery T B & S M",
    "wof:placetype":"venue"
},
  "geometry": {"coordinates":[117.044273377,-30.3411903381],"type":"Point"}
}