{
  "type": "Feature",
  "properties": {
    "iso:country":"AU",
    "sg:address":"291 Lygon St",
    "sg:city":"Brunswick East",
    "sg:classifiers":[
        {
            "category":"Fast Food",
            "type":"Food & Drink"
        }
    ],
    "sg:phone":"+61 3 9380 5601",
    "sg:postcode":"3057",
    "sg:province":"VIC",
    "sg:tags":[
        "away",
        "take"
    ],
    "wof:name":"Stak Snak",
    "wof:placetype":"venue"
},
  "geometry": {"coordinates":[144.97195434599999,-37.7694892883],"type":"Point"}
}