{
  "type": "Feature",
  "properties": {
    "iso:country":"AU",
    "sg:address":"4 Jacaranda Ave",
    "sg:city":"Tweed Heads West",
    "sg:classifiers":[
        {
            "category":"Building & Trades",
            "subcategory":"Construction",
            "type":"Services"
        }
    ],
    "sg:phone":"+61 7 5599 9918",
    "sg:postcode":"2485",
    "sg:province":"NSW",
    "sg:tags":[
        "mural"
    ],
    "wof:name":"Col Edwards Signs & Murals",
    "wof:placetype":"venue"
},
  "geometry": {"coordinates":[153.510162353,-28.1923599243],"type":"Point"}
}