{
  "type": "Feature",
  "properties": {
    "addr:full":"239- 241 Hampshire Rd Sunshine VIC 3020",
    "addr:housenumber":"241",
    "addr:postcode":"3020",
    "addr:street":"Hampshire Rd",
    "iso:country":"AU",
    "sg:address":"239- 241 Hampshire Rd",
    "sg:city":"Sunshine",
    "sg:classifiers":[
        {
            "category":"Real Estate",
            "subcategory":"Real Estate Agent",
            "type":"Services"
        }
    ],
    "sg:phone":"+61 3 9312 6666",
    "sg:postcode":"3020",
    "sg:province":"VIC",
    "sg:website":"http://www.johnkontek.com.au",
    "wof:name":"John Kontek Real Estate",
    "wof:placetype":"venue"
},
  "geometry": {"coordinates":[144.83187899999999,-37.784935],"type":"Point"}
}