{
  "type": "Feature",
  "properties": {
    "iso:country":"AU",
    "sg:address":"Unit 2, 13 Ovata Drv",
    "sg:city":"Tullamarine",
    "sg:classifiers":[
        {
            "category":"Freight",
            "type":"Transportation"
        }
    ],
    "sg:phone":"+61 3 9338 0488",
    "sg:postcode":"3043",
    "sg:province":"VIC",
    "sg:tags":[
        "cargo",
        "air"
    ],
    "wof:name":"Trans Global Freight Services",
    "wof:placetype":"venue"
},
  "geometry": {"coordinates":[144.86561584500001,-37.7102012634],"type":"Point"}
}