{
  "type": "Feature",
  "properties": {
    "iso:country":"AU",
    "sg:address":"130 Morayfield Rd",
    "sg:city":"Morayfield",
    "sg:classifiers":[
        {
            "category":"Retail",
            "subcategory":"Storage",
            "type":"Services"
        }
    ],
    "sg:phone":"+61 7 5428 0988",
    "sg:postcode":"4506",
    "sg:province":"QLD",
    "wof:name":"National Storage",
    "wof:placetype":"venue"
},
  "geometry": {"coordinates":[152.95036315900001,-27.1108055115],"type":"Point"}
}