{
  "type": "Feature",
  "properties": {
    "iso:country":"AU",
    "sg:address":"Kings Rd",
    "sg:city":"Parafield Airport",
    "sg:classifiers":[
        {
            "category":"Food & Beverages",
            "subcategory":"Liquor & Beverages",
            "type":"Retail Goods"
        }
    ],
    "sg:phone":"+61 8 8258 7844",
    "sg:postcode":"5106",
    "sg:province":"SA",
    "sg:tags":[
        "store"
    ],
    "wof:name":"Parafield Airport Liquor Store",
    "wof:placetype":"venue"
},
  "geometry": {"coordinates":[138.640808,-34.787975],"type":"Point"}
}