{
  "type": "Feature",
  "properties": {
    "addr:full":"Shop 137 Westfield West Lakes West Lakes SA 5021",
    "addr:housenumber":"137",
    "addr:postcode":"5021",
    "addr:street":"Westfield",
    "iso:country":"AU",
    "sg:address":"Shop 137 Westfield West Lakes",
    "sg:city":"West Lakes",
    "sg:classifiers":[
        {
            "category":"Shopping",
            "subcategory":"Jewelry",
            "type":"Retail Goods"
        }
    ],
    "sg:phone":"+61 8 8235 2699",
    "sg:postcode":"5021",
    "sg:province":"SA",
    "sg:tags":[
        "jeweller"
    ],
    "wof:name":"Grahams",
    "wof:placetype":"venue"
},
  "geometry": {"coordinates":[138.487823486,-34.8722686768],"type":"Point"}
}