{
  "type": "Feature",
  "properties": {
    "addr:full":"Unit 4/ 62 Lara Way Campbellfield VIC 3061",
    "addr:postcode":"3061",
    "addr:street":"62 Lara Way",
    "iso:country":"AU",
    "sg:address":"Unit 4/ 62 Lara Way",
    "sg:city":"Campbellfield",
    "sg:classifiers":[
        {
            "category":"Building & Trades",
            "subcategory":"Cleaning & Sanitation",
            "type":"Services"
        }
    ],
    "sg:phone":"+61 411 748 881",
    "sg:postcode":"3061",
    "sg:province":"VIC",
    "sg:tags":[
        "abrasive",
        "blasting"
    ],
    "sg:website":"http://www.multiblast.com.au",
    "wof:name":"A Multiblast",
    "wof:placetype":"venue"
},
  "geometry": {"coordinates":[144.967987061,-37.6636428833],"type":"Point"}
}