{
  "type": "Feature",
  "properties": {
    "iso:country":"AU",
    "sg:address":"Cnr Beams & Costin Sts",
    "sg:city":"Mareeba",
    "sg:classifiers":[
        {
            "category":"Commercial Area",
            "type":"Public Place"
        }
    ],
    "sg:phone":"+61 417 162 103",
    "sg:postcode":"4880",
    "sg:province":"QLD",
    "sg:tags":[
        "heavy",
        "carrier"
    ],
    "wof:name":"Dent's Transport",
    "wof:placetype":"venue"
},
  "geometry": {"coordinates":[145.42449951200001,-17.0090675354],"type":"Point"}
}