{
  "type": "Feature",
  "properties": {
    "addr:full":"Shp4/ 53 York St Beenleigh QLD 4207",
    "addr:housenumber":"53",
    "addr:postcode":"4207",
    "addr:street":"York St",
    "iso:country":"AU",
    "sg:address":"Shp4/ 53 York St",
    "sg:city":"Beenleigh",
    "sg:classifiers":[
        {
            "category":"Building & Trades",
            "subcategory":"Construction",
            "type":"Services"
        }
    ],
    "sg:phone":"+61 7 3382 7193",
    "sg:postcode":"4207",
    "sg:province":"QLD",
    "sg:tags":[
        "industrial",
        "commercial",
        "air conditioning"
    ],
    "wof:name":"Van Kris Air Pty Ltd",
    "wof:placetype":"venue"
},
  "geometry": {"coordinates":[153.20132446299999,-27.713722229],"type":"Point"}
}