{
  "type": "Feature",
  "properties": {
    "addr:full":"38 Canley Vale Rd Canley Vale NSW 2166",
    "addr:housenumber":"38",
    "addr:postcode":"2166",
    "addr:street":"Canley Vale Rd",
    "iso:country":"AU",
    "sg:address":"38 Canley Vale Rd",
    "sg:city":"Canley Vale",
    "sg:classifiers":[
        {
            "category":"Autos & Motor Vehicles",
            "subcategory":"Auto Supplies",
            "type":"Retail Goods"
        }
    ],
    "sg:phone":"+61 2 9727 7518",
    "sg:postcode":"2166",
    "sg:province":"NSW",
    "sg:tags":[
        "automotive",
        "stereo",
        "radio"
    ],
    "wof:name":"Kim Car Radio",
    "wof:placetype":"venue"
},
  "geometry": {"coordinates":[150.94192504899999,-33.8869667053],"type":"Point"}
}