{
  "type": "Feature",
  "properties": {
    "addr:full":"Bronzewing Ave Buderim QLD 4556",
    "addr:postcode":"4556",
    "addr:street":"Bronzewing Ave",
    "iso:country":"AU",
    "sg:address":"Bronzewing Ave",
    "sg:city":"Buderim",
    "sg:classifiers":[
        {
            "category":"Health Services",
            "subcategory":"Doctor",
            "type":"Services"
        }
    ],
    "sg:phone":"+61 7 5444 5877",
    "sg:postcode":"4556",
    "sg:province":"QLD",
    "sg:tags":[
        "medical",
        "practitioner"
    ],
    "wof:name":"Northcoast Nuclear Medicine",
    "wof:placetype":"venue"
},
  "geometry": {"coordinates":[153.089935303,-26.6820869446],"type":"Point"}
}