{
  "type": "Feature",
  "properties": {
    "iso:country":"AU",
    "sg:address":"Shp3/ 38 Moolyeen Rd",
    "sg:city":"Mt Pleasant",
    "sg:classifiers":[
        {
            "category":"Shopping",
            "subcategory":"Clothing, Apparel, & Fashions",
            "type":"Retail Goods"
        }
    ],
    "sg:phone":"+61 8 9315 3077",
    "sg:postcode":"6153",
    "sg:province":"WA",
    "sg:tags":[
        "recycled",
        "clothing"
    ],
    "wof:name":"Devoted Designs",
    "wof:placetype":"venue"
},
  "geometry": {"coordinates":[115.84864,-32.040573],"type":"Point"}
}