{
  "type": "Feature",
  "properties": {
    "addr:full":"132 Captain Cook Drv Barrack Heights NSW 2528",
    "addr:housenumber":"132",
    "addr:postcode":"2528",
    "addr:street":"Captain Cook Drv",
    "iso:country":"AU",
    "sg:address":"132 Captain Cook Drv",
    "sg:city":"Barrack Heights",
    "sg:classifiers":[
        {
            "category":"Professional",
            "subcategory":"Art Services",
            "type":"Services"
        }
    ],
    "sg:phone":"+61 412 521 874",
    "sg:postcode":"2528",
    "sg:province":"NSW",
    "sg:tags":[
        "decorator",
        "painter"
    ],
    "wof:name":"Mangos D",
    "wof:placetype":"venue"
},
  "geometry": {"coordinates":[150.84762573200001,-34.5588951111],"type":"Point"}
}