{
  "type": "Feature",
  "properties": {
    "addr:full":"216 Macquarie Rd Warners Bay NSW 2282",
    "addr:housenumber":"216",
    "addr:postcode":"2282",
    "addr:street":"Macquarie Rd",
    "iso:country":"AU",
    "sg:address":"216 Macquarie Rd",
    "sg:city":"Warners Bay",
    "sg:classifiers":[
        {
            "category":"Social Services",
            "subcategory":"Retirement Home",
            "type":"Services"
        }
    ],
    "sg:phone":"+61 2 4978 5050",
    "sg:postcode":"2282",
    "sg:province":"NSW",
    "sg:tags":[
        "environmental",
        "consultant",
        "pollution"
    ],
    "wof:name":"Ecobiological",
    "wof:placetype":"venue"
},
  "geometry": {"coordinates":[151.65281677199999,-32.9658317566],"type":"Point"}
}