{
  "type": "Feature",
  "properties": {
    "addr:full":"1 Brittainy St Petrie QLD 4502",
    "addr:housenumber":"1",
    "addr:postcode":"4502",
    "addr:street":"Brittainy St",
    "iso:country":"AU",
    "sg:address":"1 Brittainy St",
    "sg:city":"Petrie",
    "sg:classifiers":[
        {
            "category":"Health Services",
            "subcategory":"Health Practitioner",
            "type":"Services"
        }
    ],
    "sg:phone":"+61 7 3285 6626",
    "sg:postcode":"4502",
    "sg:province":"QLD",
    "sg:tags":[
        "naturopath"
    ],
    "wof:name":"Helen Davies",
    "wof:placetype":"venue"
},
  "geometry": {"coordinates":[152.97416687,-27.2664966583],"type":"Point"}
}