{
  "type": "Feature",
  "properties": {
    "addr:full":"63 Hanson Rd Gladstone QLD 4680",
    "addr:housenumber":"63",
    "addr:postcode":"4680",
    "addr:street":"Hanson Rd",
    "iso:country":"AU",
    "sg:address":"63 Hanson Rd",
    "sg:city":"Gladstone",
    "sg:classifiers":[
        {
            "category":"Autos & Motor Vehicles",
            "subcategory":"Auto Supplies",
            "type":"Retail Goods"
        }
    ],
    "sg:phone":"+61 7 4972 1833",
    "sg:postcode":"4680",
    "sg:province":"QLD",
    "sg:tags":[
        "oil",
        "spirit"
    ],
    "wof:name":"Sungold Petroleum",
    "wof:placetype":"venue"
},
  "geometry": {"coordinates":[151.246551514,-23.8410301208],"type":"Point"}
}