{
  "type": "Feature",
  "properties": {
    "addr:full":"700 Gympie Rd Lawnton QLD 4501",
    "addr:housenumber":"700",
    "addr:postcode":"4501",
    "addr:street":"Gympie Rd",
    "iso:country":"AU",
    "sg:address":"700 Gympie Rd",
    "sg:city":"Lawnton",
    "sg:classifiers":[
        {
            "category":"Autos & Motor Vehicles",
            "subcategory":"Auto Supplies",
            "type":"Retail Goods"
        }
    ],
    "sg:phone":"+61 13 23 81",
    "sg:postcode":"4501",
    "sg:province":"QLD",
    "sg:tags":[
        "tyre"
    ],
    "wof:name":"Beaurepaires",
    "wof:placetype":"venue"
},
  "geometry": {"coordinates":[152.98246765100001,-27.2801055908],"type":"Point"}
}