{
  "type": "Feature",
  "properties": {
    "iso:country":"AU",
    "sg:address":"Shop 5 Henzells Plaza Cnr Minchinton St & Bulcock",
    "sg:city":"Caloundra",
    "sg:classifiers":[
        {
            "category":"Health Services",
            "subcategory":"Health Practitioner",
            "type":"Services"
        }
    ],
    "sg:phone":"+61 7 5492 6939",
    "sg:postcode":"4551",
    "sg:province":"QLD",
    "sg:tags":[
        "consultant",
        "conservation",
        "hearing"
    ],
    "wof:name":"Shepherd Hearing Care",
    "wof:placetype":"venue"
},
  "geometry": {"coordinates":[153.13250732399999,-26.804643631],"type":"Point"}
}