{
  "type": "Feature",
  "properties": {
    "addr:full":"Unit 1, Jetty Healing Centre, 364 A High St Coffs Harbour NSW 2450",
    "addr:housenumber":"364 a",
    "addr:postcode":"2450",
    "addr:street":"High St",
    "iso:country":"AU",
    "sg:address":"Unit 1, Jetty Healing Centre, 364 A High St",
    "sg:city":"Coffs Harbour",
    "sg:classifiers":[
        {
            "category":"Health Services",
            "subcategory":"Health Practitioner",
            "type":"Services"
        }
    ],
    "sg:phone":"+61 2 6652 3141",
    "sg:postcode":"2450",
    "sg:province":"NSW",
    "sg:tags":[
        "homoeopath"
    ],
    "wof:name":"Coffs Harbour Homoeopathic Clinic",
    "wof:placetype":"venue"
},
  "geometry": {"coordinates":[153.11364699999999,-30.295994],"type":"Point"}
}