{
  "type": "Feature",
  "properties": {
    "iso:country":"AU",
    "sg:address":"9 Point St",
    "sg:city":"Fremantle",
    "sg:classifiers":[
        {
            "category":"Health Services",
            "subcategory":"Optometrist",
            "type":"Services"
        }
    ],
    "sg:phone":"+61 8 9335 5866",
    "sg:postcode":"6959",
    "sg:province":"WA",
    "wof:name":"Eyecare Plus Associated Optometrists",
    "wof:placetype":"venue"
},
  "geometry": {"coordinates":[115.74858856199999,-32.0518875122],"type":"Point"}
}