{
  "type": "Feature",
  "properties": {
    "iso:country":"AU",
    "sg:address":"U 4/ 7 Orchard Rd",
    "sg:city":"Brookvale",
    "sg:classifiers":[
        {
            "category":"Professional",
            "subcategory":"Printing & Photocopies",
            "type":"Services"
        }
    ],
    "sg:phone":"+61 2 9939 3422",
    "sg:postcode":"2100",
    "sg:province":"NSW",
    "sg:tags":[
        "laminating"
    ],
    "wof:name":"Ant Art Displays",
    "wof:placetype":"venue"
},
  "geometry": {"coordinates":[151.27206420900001,-33.7651138306],"type":"Point"}
}