{
  "type": "Feature",
  "properties": {
    "addr:full":"5 Darcy Ave Lidcombe NSW 2141",
    "addr:housenumber":"5",
    "addr:postcode":"2141",
    "addr:street":"Darcy Ave",
    "iso:country":"AU",
    "sg:address":"5 Darcy Ave",
    "sg:city":"Lidcombe",
    "sg:classifiers":[
        {
            "category":"Building & Trades",
            "subcategory":"Construction",
            "type":"Services"
        }
    ],
    "sg:phone":"+61 419 128 113",
    "sg:postcode":"2141",
    "sg:province":"NSW",
    "sg:tags":[
        "rendering",
        "cement"
    ],
    "wof:name":"z.s Cement Rendering",
    "wof:placetype":"venue"
},
  "geometry": {"coordinates":[151.043258667,-33.8704872131],"type":"Point"}
}