{
  "type": "Feature",
  "properties": {
    "addr:full":"44 Lovell St Young NSW 2594",
    "addr:housenumber":"44",
    "addr:postcode":"2594",
    "addr:street":"Lovell St",
    "iso:country":"AU",
    "sg:address":"44 Lovell St",
    "sg:city":"Young",
    "sg:classifiers":[
        {
            "category":"Wholesale",
            "subcategory":"Farm Supplies",
            "type":"Manufacturing & Wholesale Goods"
        }
    ],
    "sg:phone":"+61 2 6382 1799",
    "sg:postcode":"2594",
    "sg:province":"NSW",
    "sg:tags":[
        "equipment"
    ],
    "wof:name":"CRT Ltd",
    "wof:placetype":"venue"
},
  "geometry": {"coordinates":[148.29263305699999,-34.310874939],"type":"Point"}
}