{
  "type": "Feature",
  "properties": {
    "addr:full":"Lot 21 Meadows-Macclesfield Rd Bull Knob SA 5157",
    "addr:postcode":"5157",
    "addr:street":"Meadows-Macclesfield Rd",
    "iso:country":"AU",
    "sg:address":"Lot 21 Meadows-Macclesfield Rd",
    "sg:city":"Bull Knob",
    "sg:classifiers":[
        {
            "category":"Organizations",
            "subcategory":"Professional Association",
            "type":"Services"
        }
    ],
    "sg:phone":"+61 8 8388 9344",
    "sg:postcode":"5157",
    "sg:province":"SA",
    "sg:tags":[
        "rural",
        "organisation",
        "production",
        "primary"
    ],
    "wof:name":"Smith K R & H C",
    "wof:placetype":"venue"
},
  "geometry": {"coordinates":[138.76942443900001,-35.1813659668],"type":"Point"}
}