{
  "type": "Feature",
  "properties": {
    "addr:full":"1279 Swan Bay - New Italy Rd New Italy NSW 2472",
    "addr:housenumber":"1279",
    "addr:postcode":"2472",
    "addr:street":"Swan Bay;Italy Rd",
    "iso:country":"AU",
    "sg:address":"1279 Swan Bay - New Italy Rd",
    "sg:city":"New Italy",
    "sg:classifiers":[
        {
            "category":"Manufacturing",
            "subcategory":"Soap",
            "type":"Manufacturing & Wholesale Goods"
        }
    ],
    "sg:phone":"+61 2 6682 2617",
    "sg:postcode":"2472",
    "sg:province":"NSW",
    "sg:tags":[
        "detergent"
    ],
    "wof:name":"Wunday Naturals",
    "wof:placetype":"venue"
},
  "geometry": {"coordinates":[153.299682617,-29.1529827118],"type":"Point"}
}