{
  "type": "Feature",
  "properties": {
    "addr:full":"Shop 5, 206 West St Umina Beach NSW 2257",
    "addr:housenumber":"shop 5 206",
    "addr:postcode":"2257",
    "addr:street":"West St",
    "iso:country":"AU",
    "sg:address":"Shop 5, 206 West St",
    "sg:city":"Umina Beach",
    "sg:classifiers":[
        {
            "category":"Banks & Credit Unions",
            "subcategory":"Financial Services",
            "type":"Services"
        }
    ],
    "sg:phone":"+61 2 4342 2666",
    "sg:postcode":"2257",
    "sg:province":"NSW",
    "sg:tags":[
        "annuity",
        "rollover",
        "superannuation",
        "consultant"
    ],
    "wof:name":"Imagine Financial Services",
    "wof:placetype":"venue"
},
  "geometry": {"coordinates":[151.32281494099999,-33.5220184326],"type":"Point"}
}