{
  "type": "Feature",
  "properties": {
    "iso:country":"AU",
    "sg:address":"135 Edward St",
    "sg:city":"Melrose Park",
    "sg:classifiers":[
        {
            "category":"Social Services",
            "subcategory":"Child Care",
            "type":"Services"
        }
    ],
    "sg:phone":"+61 8 8351 2266",
    "sg:postcode":"5039",
    "sg:province":"SA",
    "wof:name":"Melrose Park Child Care",
    "wof:placetype":"venue"
},
  "geometry": {"coordinates":[138.57742309599999,-34.9780883789],"type":"Point"}
}