{
  "type": "Feature",
  "properties": {
    "addr:full":"194 High St Ashburton VIC 3147",
    "addr:housenumber":"194",
    "addr:postcode":"3147",
    "addr:street":"High St",
    "iso:country":"AU",
    "sg:address":"194 High St",
    "sg:city":"Ashburton",
    "sg:classifiers":[
        {
            "category":"Shopping",
            "subcategory":"Clothing, Apparel, & Fashions",
            "type":"Retail Goods"
        }
    ],
    "sg:phone":"+61 3 9885 1727",
    "sg:postcode":"3147",
    "sg:province":"VIC",
    "sg:tags":[
        "hire",
        "men's",
        "wear",
        "formal"
    ],
    "wof:name":"Formal Wear Of Malvern",
    "wof:placetype":"venue"
},
  "geometry": {"coordinates":[145.07850647000001,-37.8633918762],"type":"Point"}
}