{
  "type": "Feature",
  "properties": {
    "addr:full":"295 Stoney Camp Rd Greenbank QLD 4124",
    "addr:housenumber":"295",
    "addr:postcode":"4124",
    "addr:street":"Stoney Camp Rd",
    "iso:country":"AU",
    "sg:address":"295 Stoney Camp Rd",
    "sg:city":"Greenbank",
    "sg:classifiers":[
        {
            "category":"Building & Trades",
            "subcategory":"Plumbing",
            "type":"Services"
        }
    ],
    "sg:phone":"+61 7 3200 0368",
    "sg:postcode":"4124",
    "sg:province":"QLD",
    "sg:tags":[
        "plumber",
        "gasfitters"
    ],
    "wof:name":"Birchvale Pty Ltd",
    "wof:placetype":"venue"
},
  "geometry": {"coordinates":[152.99981689399999,-27.722366333],"type":"Point"}
}