{
  "type": "Feature",
  "properties": {
    "addr:full":"Suite 3, Bangor Cntr Bangor NSW 2234",
    "addr:postcode":"2234",
    "iso:country":"AU",
    "sg:address":"Suite 3, Bangor Cntr",
    "sg:city":"Bangor",
    "sg:classifiers":[
        {
            "category":"Health Services",
            "subcategory":"Dentist",
            "type":"Services"
        }
    ],
    "sg:phone":"+61 2 9543 1897",
    "sg:postcode":"2234",
    "sg:province":"NSW",
    "wof:name":"Purcell L R",
    "wof:placetype":"venue"
},
  "geometry": {"coordinates":[151.02886962900001,-34.0212745667],"type":"Point"}
}