{
  "type": "Feature",
  "properties": {
    "addr:full":"Isa Square\" Shp 7/ 27 Simpson St Mt Isa QLD 4825",
    "addr:housenumber":"7 / 27",
    "addr:postcode":"4825",
    "addr:street":"Simpson St",
    "iso:country":"AU",
    "sg:address":"Isa Square\" Shp 7/ 27 Simpson St",
    "sg:city":"Mt Isa",
    "sg:classifiers":[
        {
            "category":"Shopping",
            "subcategory":"Clothing, Apparel, & Fashions",
            "type":"Retail Goods"
        }
    ],
    "sg:phone":"+61 7 4743 7913",
    "sg:postcode":"4825",
    "sg:province":"QLD",
    "sg:tags":[
        "lady",
        "wear"
    ],
    "wof:name":"Freckletons Country World",
    "wof:placetype":"venue"
},
  "geometry": {"coordinates":[139.485657,-20.727497],"type":"Point"}
}