{
  "type": "Feature",
  "properties": {
    "addr:full":"PO Box 75 Menai NSW 2234",
    "addr:postcode":"2234",
    "iso:country":"AU",
    "sg:address":"PO Box 75",
    "sg:city":"Menai",
    "sg:classifiers":[
        {
            "category":"Professional",
            "subcategory":"Research",
            "type":"Services"
        }
    ],
    "sg:phone":"+61 2 9532 1331",
    "sg:postcode":"2234",
    "sg:province":"NSW",
    "sg:tags":[
        "industrial",
        "scientific"
    ],
    "wof:name":"Silex Systems Ltd",
    "wof:placetype":"venue"
},
  "geometry": {"coordinates":[151.01176452600001,-34.0151901245],"type":"Point"}
}