{
  "type": "Feature",
  "properties": {
    "addr:full":"319 Montacute St Athelstone SA 5076",
    "addr:housenumber":"319",
    "addr:postcode":"5076",
    "addr:street":"Montacute St",
    "iso:country":"AU",
    "sg:address":"319 Montacute St",
    "sg:city":"Athelstone",
    "sg:classifiers":[
        {
            "category":"Real Estate",
            "subcategory":"Real Estate Agent",
            "type":"Services"
        }
    ],
    "sg:phone":"+61 407 606 798",
    "sg:postcode":"5076",
    "sg:province":"SA",
    "wof:name":"Profile Real Estate",
    "wof:placetype":"venue"
},
  "geometry": {"coordinates":[138.704025269,-34.885017395],"type":"Point"}
}