{
  "type": "Feature",
  "properties": {
    "addr:full":"2 bank St Mowbray TAS 7248",
    "addr:housenumber":"2",
    "addr:postcode":"7248",
    "addr:street":"Bank St",
    "iso:country":"AU",
    "sg:address":"2 bank St",
    "sg:city":"Mowbray",
    "sg:classifiers":[
        {
            "category":"Building & Trades",
            "subcategory":"Landscaping Services",
            "type":"Services"
        }
    ],
    "sg:phone":"+61 408 647 133",
    "sg:postcode":"7248",
    "sg:province":"TAS",
    "sg:tags":[
        "gardener"
    ],
    "wof:name":"Belladonna Garden Care",
    "wof:placetype":"venue"
},
  "geometry": {"coordinates":[147.136062622,-41.4176902771],"type":"Point"}
}