{
  "type": "Feature",
  "properties": {
    "addr:full":"Level 4, 55 Lavender St North Sydney NSW 2060",
    "addr:housenumber":"55",
    "addr:postcode":"2060",
    "addr:street":"Lavender St",
    "iso:country":"AU",
    "sg:address":"Level 4, 55 Lavender St",
    "sg:city":"North Sydney",
    "sg:classifiers":[
        {
            "category":"Professional",
            "subcategory":"Computer Services",
            "type":"Services"
        }
    ],
    "sg:phone":"+61 2 9954 1736",
    "sg:postcode":"2060",
    "sg:province":"NSW",
    "sg:tags":[
        "consultant",
        "system"
    ],
    "wof:name":"RHO Transformation Technologies Pty Ltd",
    "wof:placetype":"venue"
},
  "geometry": {"coordinates":[151.20970153799999,-33.8435440063],"type":"Point"}
}