{
  "type": "Feature",
  "properties": {
    "iso:country":"AU",
    "sg:address":"Unit 6, 103- 105 Spencer Rd",
    "sg:city":"Nerang",
    "sg:classifiers":[
        {
            "category":"Manufacturing",
            "subcategory":"Motor Vehicles & Parts",
            "type":"Manufacturing & Wholesale Goods"
        }
    ],
    "sg:phone":"+61 7 5596 7775",
    "sg:postcode":"4211",
    "sg:province":"QLD",
    "sg:tags":[
        "engine",
        "equipment",
        "diesel"
    ],
    "wof:name":"Diesel Engine Rebuilding Aust",
    "wof:placetype":"venue"
},
  "geometry": {"coordinates":[153.34608459500001,-28.0088233948],"type":"Point"}
}