{
  "type": "Feature",
  "properties": {
    "addr:full":"2 Cockburn Rd North Lake WA 6163",
    "addr:housenumber":"2",
    "addr:postcode":"6163",
    "addr:street":"Cockburn Rd",
    "iso:country":"AU",
    "sg:address":"2 Cockburn Rd",
    "sg:city":"North Lake",
    "sg:classifiers":[
        {
            "category":"Restaurant",
            "type":"Food & Drink"
        }
    ],
    "sg:phone":"+61 8 9335 3006",
    "sg:postcode":"6163",
    "sg:province":"WA",
    "wof:name":"Alegrias Bistro",
    "wof:placetype":"venue"
},
  "geometry": {"coordinates":[115.76106299999999,-32.078613],"type":"Point"}
}