{
  "type": "Feature",
  "properties": {
    "addr:full":"Shop B 27, Carnes Hill M-Place, Cnr Cowpasture & K Carnes Hill NSW 2171",
    "addr:housenumber":"27",
    "addr:postcode":"2171",
    "addr:street":"Carnes Hill M-Place Cnr Cowpasture &",
    "iso:country":"AU",
    "sg:address":"Shop B 27, Carnes Hill M-Place, Cnr Cowpasture & K",
    "sg:city":"Carnes Hill",
    "sg:classifiers":[
        {
            "category":"Shopping",
            "subcategory":"Computers & Home Electronics",
            "type":"Retail Goods"
        }
    ],
    "sg:phone":"+61 2 9608 9177",
    "sg:postcode":"2171",
    "sg:province":"NSW",
    "sg:tags":[
        "equipment",
        "part",
        "electronic"
    ],
    "wof:name":"Dick Smith Electronics",
    "wof:placetype":"venue"
},
  "geometry": {"coordinates":[150.83998107900001,-33.940864563],"type":"Point"}
}