{
  "type": "Feature",
  "properties": {
    "iso:country":"AU",
    "sg:address":"136 Stirling Hwy",
    "sg:city":"Nedlands",
    "sg:classifiers":[
        {
            "category":"Real Estate",
            "subcategory":"Surveying",
            "type":"Services"
        }
    ],
    "sg:phone":"+61 8 9389 7322",
    "sg:postcode":"6009",
    "sg:province":"WA",
    "sg:tags":[
        "surveyor",
        "land"
    ],
    "wof:name":"FM Surveys",
    "wof:placetype":"venue"
},
  "geometry": {"coordinates":[115.796951,-31.98041],"type":"Point"}
}