{
  "type": "Feature",
  "properties": {
    "addr:full":"269 Cordeaux Rd Mt Kembla NSW 2526",
    "addr:housenumber":"269",
    "addr:postcode":"2526",
    "addr:street":"Cordeaux Rd",
    "iso:country":"AU",
    "sg:address":"269 Cordeaux Rd",
    "sg:city":"Mt Kembla",
    "sg:classifiers":[
        {
            "category":"Health Services",
            "subcategory":"Doctor",
            "type":"Services"
        }
    ],
    "sg:phone":"+61 2 4272 7376",
    "sg:postcode":"2526",
    "sg:province":"NSW",
    "sg:tags":[
        "medical",
        "practitioner"
    ],
    "wof:name":"Hittmann G B",
    "wof:placetype":"venue"
},
  "geometry": {"coordinates":[150.82183837900001,-34.4317855835],"type":"Point"}
}