{
  "type": "Feature",
  "properties": {
    "addr:full":"103 Gordon St Naracoorte SA 5271",
    "addr:housenumber":"103",
    "addr:postcode":"5271",
    "addr:street":"Gordon St",
    "iso:country":"AU",
    "sg:address":"103 Gordon St",
    "sg:city":"Naracoorte",
    "sg:classifiers":[
        {
            "category":"Utilities",
            "type":"Services"
        }
    ],
    "sg:phone":"+61 8 8762 4101",
    "sg:postcode":"5271",
    "sg:province":"SA",
    "sg:tags":[
        "refrigeration",
        "industrial",
        "commercial",
        "retail"
    ],
    "wof:name":"ACD Refrigeration",
    "wof:placetype":"venue"
},
  "geometry": {"coordinates":[140.73988342300001,-36.9683952332],"type":"Point"}
}