{
  "type": "Feature",
  "properties": {
    "iso:country":"AU",
    "sg:address":"1st Floor, 218 William St",
    "sg:city":"Northbridge",
    "sg:classifiers":[
        {
            "category":"Real Estate",
            "subcategory":"Architect",
            "type":"Services"
        }
    ],
    "sg:phone":"+61 8 9227 6211",
    "sg:postcode":"6003",
    "sg:province":"WA",
    "sg:tags":[
        "building",
        "designer"
    ],
    "wof:name":"Rechichi Architects",
    "wof:placetype":"venue"
},
  "geometry": {"coordinates":[115.85965728799999,-31.9487838745],"type":"Point"}
}