{
  "type": "Feature",
  "properties": {
    "iso:country":"AU",
    "sg:address":"4 Park Ave",
    "sg:city":"Gordon",
    "sg:classifiers":[
        {
            "category":"Government",
            "subcategory":"Court House",
            "type":"Public Place"
        }
    ],
    "sg:phone":"+61 2 9498 8805",
    "sg:postcode":"2072",
    "sg:province":"NSW",
    "sg:tags":[
        "personal",
        "marriage",
        "family",
        "counselling"
    ],
    "wof:name":"Hornsby Ku-Ring-Gai Lifeline & Community Aid",
    "wof:placetype":"venue"
},
  "geometry": {"coordinates":[151.15330505399999,-33.7538070679],"type":"Point"}
}