{
  "type": "Feature",
  "properties": {
    "addr:full":"20 Surrey St Mornington VIC 3931",
    "addr:housenumber":"20",
    "addr:postcode":"3931",
    "addr:street":"Surrey St",
    "iso:country":"AU",
    "sg:address":"20 Surrey St",
    "sg:city":"Mornington",
    "sg:classifiers":[
        {
            "category":"Manufacturing",
            "subcategory":"Retail Goods",
            "type":"Manufacturing & Wholesale Goods"
        }
    ],
    "sg:phone":"+61 412 003 828",
    "sg:postcode":"3931",
    "sg:province":"VIC",
    "sg:tags":[
        "merchant",
        "pump",
        "mfrs"
    ],
    "wof:name":"P G Consulting Services",
    "wof:placetype":"venue"
},
  "geometry": {"coordinates":[145.04142761200001,-38.2282676697],"type":"Point"}
}