{
  "type": "Feature",
  "properties": {
    "addr:full":"54 Darlinghurst Rd Kings Cross NSW 2011",
    "addr:housenumber":"54",
    "addr:postcode":"2011",
    "addr:street":"Darlinghurst Rd",
    "iso:country":"AU",
    "sg:address":"54 Darlinghurst Rd",
    "sg:city":"Kings Cross",
    "sg:classifiers":[
        {
            "category":"Banks & Credit Unions",
            "subcategory":"Investment Brokerage",
            "type":"Services"
        }
    ],
    "sg:phone":"+61 2 9283 8118",
    "sg:postcode":"2011",
    "sg:province":"NSW",
    "wof:name":"Rising Sun Holdings Pty Ltd",
    "wof:placetype":"venue"
},
  "geometry": {"coordinates":[151.223144531,-33.8743553162],"type":"Point"}
}