{
  "type": "Feature",
  "properties": {
    "addr:full":"162 Parramatta Rd Ashfield NSW 2131",
    "addr:housenumber":"162",
    "addr:postcode":"2131",
    "addr:street":"Parramatta Rd",
    "iso:country":"AU",
    "sg:address":"162 Parramatta Rd",
    "sg:city":"Ashfield",
    "sg:classifiers":[
        {
            "category":"Home & Garden",
            "subcategory":"Building Materials",
            "type":"Retail Goods"
        }
    ],
    "sg:phone":"+61 2 9798 7075",
    "sg:postcode":"2131",
    "sg:province":"NSW",
    "sg:tags":[
        "tile",
        "roofing"
    ],
    "wof:name":"DJ Daisley & Sons",
    "wof:placetype":"venue"
},
  "geometry": {"coordinates":[151.13398742699999,-33.8835449219],"type":"Point"}
}