{
  "type": "Feature",
  "properties": {
    "addr:full":"Harold Park Paceway Ross St Glebe NSW 2037",
    "addr:postcode":"2037",
    "addr:street":"Ross St",
    "iso:country":"AU",
    "sg:address":"Harold Park Paceway Ross St",
    "sg:city":"Glebe",
    "sg:classifiers":[
        {
            "category":"Wholesale",
            "subcategory":"Farm Supplies",
            "type":"Manufacturing & Wholesale Goods"
        }
    ],
    "sg:phone":"+61 2 9571 6144",
    "sg:postcode":"2037",
    "sg:province":"NSW",
    "sg:tags":[
        "feed",
        "supplement",
        "stock"
    ],
    "wof:name":"Garrard's Horse and Hound",
    "wof:placetype":"venue"
},
  "geometry": {"coordinates":[151.18031310999999,-33.8796157837],"type":"Point"}
}