{
  "type": "Feature",
  "properties": {
    "iso:country":"AU",
    "sg:address":"Suite 240, 45 Glenferrie Rd",
    "sg:city":"Malvern",
    "sg:classifiers":[
        {
            "category":"Professional",
            "subcategory":"Business Services",
            "type":"Services"
        }
    ],
    "sg:phone":"+61 3 9576 2902",
    "sg:postcode":"3144",
    "sg:province":"VIC",
    "sg:tags":[
        "small",
        "advisory"
    ],
    "wof:name":"Ajmal Bajawray & Associates",
    "wof:placetype":"venue"
},
  "geometry": {"coordinates":[145.02792358400001,-37.8638496399],"type":"Point"}
}