{
  "type": "Feature",
  "properties": {
    "addr:full":"3/ 122 Gardenvale Rd Gardenvale VIC 3185",
    "addr:housenumber":"/ 122",
    "addr:postcode":"3185",
    "addr:street":"Gardenvale Rd",
    "iso:country":"AU",
    "sg:address":"3/ 122 Gardenvale Rd",
    "sg:city":"Gardenvale",
    "sg:classifiers":[
        {
            "category":"Professional",
            "subcategory":"Computer Services",
            "type":"Services"
        }
    ],
    "sg:phone":"+61 3 9596 2989",
    "sg:postcode":"3185",
    "sg:province":"VIC",
    "sg:tags":[
        "consultant",
        "system"
    ],
    "wof:name":"Watershed Systems Pty Ltd",
    "wof:placetype":"venue"
},
  "geometry": {"coordinates":[145.00657653799999,-37.8975753784],"type":"Point"}
}