{
  "type": "Feature",
  "properties": {
    "iso:country":"AU",
    "sg:address":"11 Barolin St",
    "sg:city":"Bundaberg",
    "sg:classifiers":[
        {
            "category":"Health Services",
            "subcategory":"Dentist",
            "type":"Services"
        }
    ],
    "sg:phone":"+61 7 4153 1088",
    "sg:postcode":"4670",
    "sg:province":"QLD",
    "wof:name":"Stockham P T",
    "wof:placetype":"venue"
},
  "geometry": {"coordinates":[152.34898376500001,-24.8671379089],"type":"Point"}
}