{
  "type": "Feature",
  "properties": {
    "addr:full":"76 John St Camden NSW 2570",
    "addr:housenumber":"76",
    "addr:postcode":"2570",
    "addr:street":"John St",
    "iso:country":"AU",
    "sg:address":"76 John St",
    "sg:city":"Camden",
    "sg:classifiers":[
        {
            "category":"Utilities",
            "subcategory":"Telephone",
            "type":"Services"
        }
    ],
    "sg:phone":"+61 1300 559 669",
    "sg:postcode":"2570",
    "sg:province":"NSW",
    "sg:tags":[
        "equipment",
        "system"
    ],
    "sg:website":"http://www.customtel.net",
    "wof:name":"CustomTel (NSW)",
    "wof:placetype":"venue"
},
  "geometry": {"coordinates":[150.696655273,-34.0557365417],"type":"Point"}
}