{
  "type": "Feature",
  "properties": {
    "iso:country":"AU",
    "sg:address":"Shop 3, 7 Gawler St",
    "sg:city":"Nuriootpa",
    "sg:classifiers":[
        {
            "category":"Home & Garden",
            "subcategory":"Carpets & Floor Coverings",
            "type":"Retail Goods"
        }
    ],
    "sg:phone":"+61 8 8568 6017",
    "sg:postcode":"5355",
    "sg:province":"SA",
    "sg:tags":[
        "wood"
    ],
    "wof:name":"Carpet Court",
    "wof:placetype":"venue"
},
  "geometry": {"coordinates":[138.995727539,-34.4733543396],"type":"Point"}
}