{
  "type": "Feature",
  "properties": {
    "iso:country":"AU",
    "sg:address":"17 Lawley St",
    "sg:city":"North Beach",
    "sg:classifiers":[
        {
            "category":"Health Services",
            "subcategory":"Doctor",
            "type":"Services"
        }
    ],
    "sg:phone":"+61 8 9447 1233",
    "sg:postcode":"6020",
    "sg:province":"WA",
    "sg:tags":[
        "medical",
        "practitioner"
    ],
    "wof:name":"Clarke Susan Dr",
    "wof:placetype":"venue"
},
  "geometry": {"coordinates":[115.754348755,-31.8544273376],"type":"Point"}
}