{
  "type": "Feature",
  "properties": {
    "addr:full":"748 Lawrence Hargrave Drv Coledale NSW 2515",
    "addr:housenumber":"748",
    "addr:postcode":"2515",
    "addr:street":"Lawrence Hargrave Drv",
    "iso:country":"AU",
    "sg:address":"748 Lawrence Hargrave Drv",
    "sg:city":"Coledale",
    "sg:classifiers":[
        {
            "category":"Cafe",
            "type":"Food & Drink"
        }
    ],
    "sg:phone":"+61 2 4268 3000",
    "sg:postcode":"2515",
    "sg:province":"NSW",
    "wof:name":"Chedos Cafe",
    "wof:placetype":"venue"
},
  "geometry": {"coordinates":[150.94439700000001,-34.291481],"type":"Point"}
}