{
  "type": "Feature",
  "properties": {
    "iso:country":"AU",
    "sg:address":"107 Walker St",
    "sg:city":"North Sydney",
    "sg:classifiers":[
        {
            "category":"Professional",
            "subcategory":"Printing & Photocopies",
            "type":"Services"
        }
    ],
    "sg:phone":"+61 2 9954 0288",
    "sg:postcode":"2060",
    "sg:province":"NSW",
    "sg:tags":[
        "publishing",
        "desktop"
    ],
    "wof:name":"Desktype Conversions",
    "wof:placetype":"venue"
},
  "geometry": {"coordinates":[151.20887756400001,-33.8395881653],"type":"Point"}
}