{
  "type": "Feature",
  "properties": {
    "iso:country":"AU",
    "sg:address":"7 Lake Rd",
    "sg:city":"Tuggerah",
    "sg:classifiers":[
        {
            "category":"Retail",
            "subcategory":"Auto Repair",
            "type":"Services"
        }
    ],
    "sg:phone":"+61 2 4352 2215",
    "sg:postcode":"2259",
    "sg:province":"NSW",
    "sg:tags":[
        "repairer",
        "motor",
        "engineer"
    ],
    "wof:name":"Lewis Motorcycles",
    "wof:placetype":"venue"
},
  "geometry": {"coordinates":[151.423736572,-33.3080329895],"type":"Point"}
}