{
  "type": "Feature",
  "properties": {
    "iso:country":"AU",
    "sg:address":"213 - 217 Queen St",
    "sg:city":"Ayr",
    "sg:classifiers":[
        {
            "category":"Wholesale",
            "subcategory":"Machinery & Supplies",
            "type":"Manufacturing & Wholesale Goods"
        }
    ],
    "sg:phone":"+61 7 4783 2344",
    "sg:postcode":"4807",
    "sg:province":"QLD",
    "sg:tags":[
        "agricultural"
    ],
    "wof:name":"Honeycombes Sales & Service Pty Ltd",
    "wof:placetype":"venue"
},
  "geometry": {"coordinates":[147.400634766,-19.5809860229],"type":"Point"}
}