{
  "type": "Feature",
  "properties": {
    "addr:full":"Unit 2/ 10 Pipeclay Ave Thornton NSW 2322",
    "addr:postcode":"2322",
    "addr:street":"10 Pipeclay Ave",
    "iso:country":"AU",
    "sg:address":"Unit 2/ 10 Pipeclay Ave",
    "sg:city":"Thornton",
    "sg:classifiers":[
        {
            "category":"Retail",
            "subcategory":"Auto Repair",
            "type":"Services"
        }
    ],
    "sg:phone":"+61 2 4966 1235",
    "sg:postcode":"2322",
    "sg:province":"NSW",
    "sg:tags":[
        "repairer",
        "motor",
        "engineer"
    ],
    "wof:name":"R X Engineering",
    "wof:placetype":"venue"
},
  "geometry": {"coordinates":[151.634643555,-32.7881851196],"type":"Point"}
}