{
  "type": "Feature",
  "properties": {
    "addr:full":"PO Box 235 Bullsbrook WA 6084",
    "addr:postcode":"6084",
    "iso:country":"AU",
    "sg:address":"PO Box 235",
    "sg:city":"Bullsbrook",
    "sg:classifiers":[
        {
            "category":"Utilities",
            "subcategory":"Refuse",
            "type":"Services"
        }
    ],
    "sg:phone":"+61 427 000 634",
    "sg:postcode":"6084",
    "sg:province":"WA",
    "sg:tags":[
        "remover",
        "rubbish"
    ],
    "wof:name":"Bullsbrook Bins",
    "wof:placetype":"venue"
},
  "geometry": {"coordinates":[116.031517029,-31.6714401245],"type":"Point"}
}