{
  "type": "Feature",
  "properties": {
    "iso:country":"AU",
    "sg:address":"217 Boundary Rd",
    "sg:city":"South Mackay",
    "sg:classifiers":[
        {
            "category":"Manufacturing",
            "subcategory":"Tools & Machinery",
            "type":"Manufacturing & Wholesale Goods"
        }
    ],
    "sg:phone":"+61 7 4952 4994",
    "sg:postcode":"4740",
    "sg:province":"QLD",
    "sg:tags":[
        "earth",
        "excavating",
        "moving",
        "equipment"
    ],
    "wof:name":"Liebherr-Australia Pty Ltd",
    "wof:placetype":"venue"
},
  "geometry": {"coordinates":[149.17425499999999,-21.177053],"type":"Point"}
}