{
  "type": "Feature",
  "properties": {
    "iso:country":"AU",
    "sg:address":"43 Barkly Hwy",
    "sg:city":"Mt Isa",
    "sg:classifiers":[
        {
            "category":"Building & Trades",
            "subcategory":"Construction",
            "type":"Services"
        }
    ],
    "sg:phone":"+61 7 4743 4633",
    "sg:postcode":"4825",
    "sg:province":"QLD",
    "sg:tags":[
        "earth",
        "excavating",
        "moving",
        "contractor"
    ],
    "wof:name":"Miccon Pty Ltd",
    "wof:placetype":"venue"
},
  "geometry": {"coordinates":[139.486099,-20.714483],"type":"Point"}
}