{
  "type": "Feature",
  "properties": {
    "addr:full":"3 Frayne St Stawell VIC 3380",
    "addr:housenumber":"3",
    "addr:postcode":"3380",
    "addr:street":"Frayne St",
    "iso:country":"AU",
    "sg:address":"3 Frayne St",
    "sg:city":"Stawell",
    "sg:classifiers":[
        {
            "category":"Retail",
            "subcategory":"Repair Shop",
            "type":"Services"
        }
    ],
    "sg:phone":"+61 3 5358 3620",
    "sg:postcode":"3380",
    "sg:province":"VIC",
    "sg:tags":[
        "upholsterer"
    ],
    "wof:name":"Mussett Upholstery & Saddlery",
    "wof:placetype":"venue"
},
  "geometry": {"coordinates":[142.77207946799999,-37.0577430725],"type":"Point"}
}