{
  "type": "Feature",
  "properties": {
    "addr:full":"11- 13 Herberte Crt Wurruk VIC 3850",
    "addr:housenumber":"13",
    "addr:postcode":"3850",
    "addr:street":"Herberte Crt",
    "iso:country":"AU",
    "sg:address":"11- 13 Herberte Crt",
    "sg:city":"Wurruk",
    "sg:classifiers":[
        {
            "category":"Wholesale",
            "subcategory":"Machinery & Supplies",
            "type":"Manufacturing & Wholesale Goods"
        }
    ],
    "sg:phone":"+61 3 5144 1088",
    "sg:postcode":"3850",
    "sg:province":"VIC",
    "sg:tags":[
        "rigging",
        "equipment",
        "hoisting"
    ],
    "wof:name":"Alpha Rigging Service Pty Ltd",
    "wof:placetype":"venue"
},
  "geometry": {"coordinates":[147.030807495,-38.101524353],"type":"Point"}
}