{
  "type": "Feature",
  "properties": {
    "addr:full":"PO Box 1159 Park Ridge QLD 4125",
    "addr:postcode":"4125",
    "iso:country":"AU",
    "sg:address":"PO Box 1159",
    "sg:city":"Park Ridge",
    "sg:classifiers":[
        {
            "category":"Travel",
            "subcategory":"Travel Agent",
            "type":"Entertainment"
        }
    ],
    "sg:phone":"+61 7 3297 0853",
    "sg:postcode":"4125",
    "sg:province":"QLD",
    "sg:tags":[
        "tour",
        "holiday",
        "adventure"
    ],
    "wof:name":"Four Wheel Drive Adventures",
    "wof:placetype":"venue"
},
  "geometry": {"coordinates":[153.06152343799999,-27.703950882],"type":"Point"}
}