{
  "type": "Feature",
  "properties": {
    "iso:country":"AU",
    "sg:address":"PO Box 230",
    "sg:city":"North Adelaide",
    "sg:classifiers":[
        {
            "category":"Banks & Credit Unions",
            "subcategory":"Financial Services",
            "type":"Services"
        }
    ],
    "sg:phone":"+61 8 8361 7178",
    "sg:postcode":"5006",
    "sg:province":"SA",
    "sg:tags":[
        "finance",
        "factoring"
    ],
    "wof:name":"Metro Factors & Co",
    "wof:placetype":"venue"
},
  "geometry": {"coordinates":[138.59492492699999,-34.9090194702],"type":"Point"}
}