{
  "type": "Feature",
  "properties": {
    "iso:country":"AU",
    "sg:address":"96a Railway St",
    "sg:city":"Rockdale",
    "sg:classifiers":[
        {
            "category":"Health Services",
            "subcategory":"Doctor",
            "type":"Services"
        }
    ],
    "sg:phone":"+61 2 9567 2060",
    "sg:postcode":"2216",
    "sg:province":"NSW",
    "sg:tags":[
        "medical",
        "practitioner"
    ],
    "wof:name":"Makarie W",
    "wof:placetype":"venue"
},
  "geometry": {"coordinates":[151.13587999999999,-33.952473],"type":"Point"}
}