{
  "type": "Feature",
  "properties": {
    "iso:country":"AU",
    "sg:address":"9 Rylston Crt",
    "sg:city":"Mt Eliza",
    "sg:classifiers":[
        {
            "category":"Education",
            "subcategory":"Special Training",
            "type":"Public Place"
        }
    ],
    "sg:phone":"+61 3 9708 8158",
    "sg:postcode":"3930",
    "sg:province":"VIC",
    "sg:tags":[
        "development"
    ],
    "wof:name":"Sole Reality",
    "wof:placetype":"venue"
},
  "geometry": {"coordinates":[145.10635375999999,-38.1936378479],"type":"Point"}
}