{
  "type": "Feature",
  "properties": {
    "iso:country":"AU",
    "sg:address":"Shop 3 &#034;The Gallery&#034; 50 Hastings St",
    "sg:city":"Noosa Heads",
    "sg:classifiers":[
        {
            "category":"Communications",
            "subcategory":"News Services",
            "type":"Services"
        }
    ],
    "sg:phone":"+61 7 5449 7024",
    "sg:postcode":"4567",
    "sg:province":"QLD",
    "sg:tags":[
        "information",
        "tourist",
        "attractions"
    ],
    "wof:name":"Fraser Island Explorer 4WD Day Tours",
    "wof:placetype":"venue"
},
  "geometry": {"coordinates":[153.08737182600001,-26.3860454559],"type":"Point"}
}