{
  "type": "Feature",
  "properties": {
    "addr:full":"90 Lear Jet Drv Caboolture QLD 4510",
    "addr:housenumber":"90",
    "addr:postcode":"4510",
    "addr:street":"Lear Jet Drv",
    "iso:country":"AU",
    "sg:address":"90 Lear Jet Drv",
    "sg:city":"Caboolture",
    "sg:classifiers":[
        {
            "category":"Home & Garden",
            "subcategory":"Hardware",
            "type":"Retail Goods"
        }
    ],
    "sg:phone":"+61 7 5432 4882",
    "sg:postcode":"4510",
    "sg:province":"QLD",
    "sg:tags":[
        "repair",
        "tool",
        "power"
    ],
    "wof:name":"Tradetools Direct Pty Ltd",
    "wof:placetype":"venue"
},
  "geometry": {"coordinates":[152.979004,-27.084063],"type":"Point"}
}