{
  "type": "Feature",
  "properties": {
    "addr:full":"Level 3 47 Salamanca Pl Hobart TAS 7000",
    "addr:housenumber":"47",
    "addr:postcode":"7000",
    "addr:street":"Pl",
    "iso:country":"AU",
    "sg:address":"Level 3 47 Salamanca Pl",
    "sg:city":"Hobart",
    "sg:classifiers":[
        {
            "category":"Personal",
            "subcategory":"Massage",
            "type":"Services"
        }
    ],
    "sg:phone":"+61 1300 551 209",
    "sg:postcode":"7000",
    "sg:province":"TAS",
    "sg:tags":[
        "therapy"
    ],
    "wof:name":"Relaxperts",
    "wof:placetype":"venue"
},
  "geometry": {"coordinates":[147.332519531,-42.8868026733],"type":"Point"}
}