{
  "type": "Feature",
  "properties": {
    "addr:full":"177 High St Charlton VIC 3525",
    "addr:housenumber":"177",
    "addr:postcode":"3525",
    "addr:street":"High St",
    "iso:country":"AU",
    "sg:address":"177 High St",
    "sg:city":"Charlton",
    "sg:classifiers":[
        {
            "category":"Wholesale",
            "subcategory":"Painting Supplies",
            "type":"Manufacturing & Wholesale Goods"
        }
    ],
    "sg:phone":"+61 3 5491 1611",
    "sg:postcode":"3525",
    "sg:province":"VIC",
    "sg:tags":[
        "equipment",
        "spraying"
    ],
    "wof:name":"Charlton AG Supplies",
    "wof:placetype":"venue"
},
  "geometry": {"coordinates":[143.34852599999999,-36.267815],"type":"Point"}
}