{
  "type": "Feature",
  "properties": {
    "addr:full":"65 Devereux Rd Linden Park SA 5065",
    "addr:housenumber":"65",
    "addr:postcode":"5065",
    "addr:street":"Devereux Rd",
    "iso:country":"AU",
    "sg:address":"65 Devereux Rd",
    "sg:city":"Linden Park",
    "sg:classifiers":[
        {
            "category":"Professional",
            "subcategory":"Business Services",
            "type":"Services"
        }
    ],
    "sg:phone":"+61 8 8379 8222",
    "sg:postcode":"5065",
    "sg:province":"SA",
    "sg:tags":[
        "management",
        "event"
    ],
    "wof:name":"Plevin & Associates",
    "wof:placetype":"venue"
},
  "geometry": {"coordinates":[138.65182495100001,-34.9462165833],"type":"Point"}
}