{
  "type": "Feature",
  "properties": {
    "addr:full":"Ambrose St Tennant Creek NT 0860",
    "addr:postcode":"nt 0860",
    "addr:street":"Ambrose St",
    "iso:country":"AU",
    "sg:address":"Ambrose St",
    "sg:city":"Tennant Creek",
    "sg:classifiers":[
        {
            "category":"Building & Trades",
            "subcategory":"Construction",
            "type":"Services"
        }
    ],
    "sg:phone":"+61 8 8962 2450",
    "sg:postcode":"0860",
    "sg:province":"NT",
    "sg:tags":[
        "contractor"
    ],
    "wof:name":"Van Den Hoek A J Pty Ltd",
    "wof:placetype":"venue"
},
  "geometry": {"coordinates":[134.19117700000001,-19.649193],"type":"Point"}
}