{
  "type": "Feature",
  "properties": {
    "addr:full":"9 Sayer St Midland WA 6056",
    "addr:housenumber":"9",
    "addr:postcode":"6056",
    "addr:street":"Sayer St",
    "iso:country":"AU",
    "sg:address":"9 Sayer St",
    "sg:city":"Midland",
    "sg:classifiers":[
        {
            "category":"Education",
            "subcategory":"School",
            "type":"Public Place"
        }
    ],
    "sg:phone":"+61 8 9264 6411",
    "sg:postcode":"6056",
    "sg:province":"WA",
    "wof:name":"Swan Christian Education Associations Inc",
    "wof:placetype":"venue"
},
  "geometry": {"coordinates":[116.00994873,-31.8923339844],"type":"Point"}
}