{
  "type": "Feature",
  "properties": {
    "addr:full":"89 High St Broadford VIC 3658",
    "addr:housenumber":"89",
    "addr:postcode":"3658",
    "addr:street":"High St",
    "iso:country":"AU",
    "sg:address":"89 High St",
    "sg:city":"Broadford",
    "sg:classifiers":[
        {
            "category":"Food & Beverages",
            "subcategory":"Groceries & Convenience Stores",
            "type":"Retail Goods"
        }
    ],
    "sg:phone":"+61 3 5784 1950",
    "sg:postcode":"3658",
    "sg:province":"VIC",
    "wof:name":"Broadford Corner Milk-Bar",
    "wof:placetype":"venue"
},
  "geometry": {"coordinates":[145.04708862300001,-37.2040748596],"type":"Point"}
}