{
  "type": "Feature",
  "properties": {
    "iso:country":"AU",
    "sg:address":"1/ 42 Kay St",
    "sg:city":"Traralgon",
    "sg:classifiers":[
        {
            "category":"Organizations",
            "subcategory":"Community Association",
            "type":"Services"
        }
    ],
    "sg:phone":"+61 3 5175 9500",
    "sg:postcode":"3844",
    "sg:province":"VIC",
    "sg:tags":[
        "organisation",
        "family",
        "welfare"
    ],
    "wof:name":"Relationships Australia",
    "wof:placetype":"venue"
},
  "geometry": {"coordinates":[146.533203125,-38.1937866211],"type":"Point"}
}