{
  "type": "Feature",
  "properties": {
    "addr:full":"45 Magpie St Singleton NSW 2330",
    "addr:housenumber":"45",
    "addr:postcode":"2330",
    "addr:street":"Magpie St",
    "iso:country":"AU",
    "sg:address":"45 Magpie St",
    "sg:city":"Singleton",
    "sg:classifiers":[
        {
            "category":"Community Center",
            "subcategory":"Youth",
            "type":"Public Place"
        }
    ],
    "sg:phone":"+61 2 6572 2578",
    "sg:postcode":"2330",
    "sg:province":"NSW",
    "sg:tags":[
        "workshop",
        "sheltered"
    ],
    "wof:name":"Witmore Enterprises Inc",
    "wof:placetype":"venue"
},
  "geometry": {"coordinates":[151.179123,-32.564014],"type":"Point"}
}