{
  "type": "Feature",
  "properties": {
    "iso:country":"AU",
    "sg:address":"405 Burke St",
    "sg:city":"Melbourne",
    "sg:classifiers":[
        {
            "category":"Travel",
            "subcategory":"Travel Agent",
            "type":"Entertainment"
        }
    ],
    "sg:phone":"+61 1300 738 833",
    "sg:postcode":"3000",
    "sg:province":"VIC",
    "sg:tags":[
        "consultant"
    ],
    "wof:name":"Queensland Travel Centre",
    "wof:placetype":"venue"
},
  "geometry": {"coordinates":[144.96220398,-37.8146591187],"type":"Point"}
}