{
  "type": "Feature",
  "properties": {
    "addr:full":"440 Smith St Collingwood VIC 3066",
    "addr:housenumber":"440",
    "addr:postcode":"3066",
    "addr:street":"Smith St",
    "iso:country":"AU",
    "sg:address":"440 Smith St",
    "sg:city":"Collingwood",
    "sg:classifiers":[
        {
            "category":"Wholesale",
            "subcategory":"Medical Equipment & Supplies",
            "type":"Manufacturing & Wholesale Goods"
        }
    ],
    "sg:phone":"+61 3 9416 3998",
    "sg:postcode":"3066",
    "sg:province":"VIC",
    "sg:tags":[
        "alternative",
        "health"
    ],
    "wof:name":"Beauty Treatment Couches",
    "wof:placetype":"venue"
},
  "geometry": {"coordinates":[144.98504638700001,-37.7954597473],"type":"Point"}
}