{
  "type": "Feature",
  "properties": {
    "iso:country":"AU",
    "sg:address":"32 Stuart St",
    "sg:city":"Noble Park",
    "sg:classifiers":[
        {
            "category":"Education",
            "subcategory":"Special Training",
            "type":"Public Place"
        }
    ],
    "sg:phone":"+61 3 8502 6817",
    "sg:postcode":"3174",
    "sg:province":"VIC",
    "sg:tags":[
        "tuition-educational"
    ],
    "wof:name":"RRR Tutorials",
    "wof:placetype":"venue"
},
  "geometry": {"coordinates":[145.17666625999999,-37.9709701538],"type":"Point"}
}