{
  "type": "Feature",
  "properties": {
    "iso:country":"AU",
    "sg:address":"33a Fussell Pl",
    "sg:city":"Alberton",
    "sg:classifiers":[
        {
            "category":"Food & Beverages",
            "subcategory":"Supermarket",
            "type":"Retail Goods"
        }
    ],
    "sg:phone":"+61 8 8341 2575",
    "sg:postcode":"5014",
    "sg:province":"SA",
    "sg:tags":[
        "grocery",
        "store"
    ],
    "wof:name":"IGA Food Stores",
    "wof:placetype":"venue"
},
  "geometry": {"coordinates":[138.51919555699999,-34.8592567444],"type":"Point"}
}