{
  "type": "Feature",
  "properties": {
    "addr:full":"4 Glendale Crt Lake Wendouree VIC 3355",
    "addr:housenumber":"4",
    "addr:postcode":"3355",
    "addr:street":"Glendale Crt",
    "iso:country":"AU",
    "sg:address":"4 Glendale Crt",
    "sg:city":"Lake Wendouree",
    "sg:classifiers":[
        {
            "category":"Utilities",
            "subcategory":"Electric",
            "type":"Services"
        }
    ],
    "sg:phone":"+61 3 5339 4431",
    "sg:postcode":"3355",
    "sg:province":"VIC",
    "sg:tags":[
        "electrical",
        "contractor"
    ],
    "wof:name":"Dickinson Ron",
    "wof:placetype":"venue"
},
  "geometry": {"coordinates":[143.83725000000001,-37.542496],"type":"Point"}
}