{
  "type": "Feature",
  "properties": {
    "addr:full":"9 Gordon St Elsternwick VIC 3185",
    "addr:housenumber":"9",
    "addr:postcode":"3185",
    "addr:street":"Gordon St",
    "iso:country":"AU",
    "sg:address":"9 Gordon St",
    "sg:city":"Elsternwick",
    "sg:classifiers":[
        {
            "category":"Cinema",
            "subcategory":"Movie Theater",
            "type":"Entertainment"
        }
    ],
    "sg:phone":"+61 3 9524 7900",
    "sg:postcode":"3185",
    "sg:province":"VIC",
    "wof:name":"Classic Cinema.",
    "wof:placetype":"venue"
},
  "geometry": {"coordinates":[145.000534058,-37.8836898804],"type":"Point"}
}