{
  "type": "Feature",
  "properties": {
    "addr:full":"113 Mcevoy St Warwick QLD 4370",
    "addr:housenumber":"113",
    "addr:postcode":"4370",
    "addr:street":"Mcevoy St",
    "iso:country":"AU",
    "sg:address":"113 Mcevoy St",
    "sg:city":"Warwick",
    "sg:classifiers":[
        {
            "category":"Food & Beverages",
            "subcategory":"Meat & Fish",
            "type":"Retail Goods"
        }
    ],
    "sg:phone":"+61 7 4661 9310",
    "sg:postcode":"4370",
    "sg:province":"QLD",
    "sg:tags":[
        "seafood"
    ],
    "wof:name":"R & K's Fork & Take Away",
    "wof:placetype":"venue"
},
  "geometry": {"coordinates":[152.03817749000001,-28.2319507599],"type":"Point"}
}