{
  "type": "Feature",
  "properties": {
    "addr:full":"684 The Horsley Drv Smithfield NSW 2164",
    "addr:housenumber":"684",
    "addr:postcode":"2164",
    "addr:street":"The Horsley Drv",
    "iso:country":"AU",
    "sg:address":"684 The Horsley Drv",
    "sg:city":"Smithfield",
    "sg:classifiers":[
        {
            "category":"Professional",
            "subcategory":"Printing & Photocopies",
            "type":"Services"
        }
    ],
    "sg:phone":"+61 2 9757 2704",
    "sg:postcode":"2164",
    "sg:province":"NSW",
    "sg:tags":[
        "textile",
        "clothing"
    ],
    "wof:name":"Brand FX Promotional Products",
    "wof:placetype":"venue"
},
  "geometry": {"coordinates":[150.93963623100001,-33.8534851074],"type":"Point"}
}