{
  "type": "Feature",
  "properties": {
    "addr:full":"54 Beach Rd Noarlunga Centre SA 5168",
    "addr:housenumber":"54",
    "addr:postcode":"5168",
    "addr:street":"Beach Rd",
    "iso:country":"AU",
    "sg:address":"54 Beach Rd",
    "sg:city":"Noarlunga Centre",
    "sg:classifiers":[
        {
            "category":"Insurance",
            "subcategory":"Health Insurance",
            "type":"Services"
        }
    ],
    "sg:phone":"+61 8 8384 4836",
    "sg:postcode":"5168",
    "sg:province":"SA",
    "wof:name":"Mutual Community Ltd",
    "wof:placetype":"venue"
},
  "geometry": {"coordinates":[138.49559020999999,-35.1383094788],"type":"Point"}
}