{
  "type": "Feature",
  "properties": {
    "iso:country":"AU",
    "sg:address":"11 Vulcan Rd",
    "sg:city":"Canning Vale",
    "sg:classifiers":[
        {
            "category":"Wholesale",
            "subcategory":"Painting Supplies",
            "type":"Manufacturing & Wholesale Goods"
        }
    ],
    "sg:phone":"+61 1800 357 467",
    "sg:postcode":"6155",
    "sg:province":"WA",
    "sg:tags":[
        "wholesaler",
        "paint",
        "mfrs"
    ],
    "wof:name":"Vale Paints",
    "wof:placetype":"venue"
},
  "geometry": {"coordinates":[115.928864,-32.058613],"type":"Point"}
}