{
  "type": "Feature",
  "properties": {
    "iso:country":"AU",
    "sg:address":"265 Maroondah Hwy",
    "sg:city":"Ringwood",
    "sg:classifiers":[
        {
            "category":"Real Estate",
            "subcategory":"Real Estate Agent",
            "type":"Services"
        }
    ],
    "sg:phone":"+61 3 9879 4422",
    "sg:postcode":"3134",
    "sg:province":"VIC",
    "wof:name":"Treeby First National",
    "wof:placetype":"venue"
},
  "geometry": {"coordinates":[145.23373413100001,-37.8131484985],"type":"Point"}
}