{
  "type": "Feature",
  "properties": {
    "addr:full":"Unit 5/ 7 Pearl St Cooroy QLD 4563",
    "addr:housenumber":"7",
    "addr:postcode":"4563",
    "addr:street":"Pearl St",
    "iso:country":"AU",
    "sg:address":"Unit 5/ 7 Pearl St",
    "sg:city":"Cooroy",
    "sg:classifiers":[
        {
            "category":"Professional",
            "subcategory":"Accounting & Tax Preparation",
            "type":"Services"
        }
    ],
    "sg:phone":"+61 7 5447 6377",
    "sg:postcode":"4563",
    "sg:province":"QLD",
    "sg:tags":[
        "accountant",
        "auditor"
    ],
    "wof:name":"Brian V. McMichan",
    "wof:placetype":"venue"
},
  "geometry": {"coordinates":[152.91192626899999,-26.4153747559],"type":"Point"}
}