{
  "type": "Feature",
  "properties": {
    "addr:full":"Family Training Institute Wilson St South Kalgoorlie WA 6430",
    "addr:postcode":"6430",
    "addr:street":"Wilson St South",
    "iso:country":"AU",
    "sg:address":"Family Training Institute Wilson St",
    "sg:city":"South Kalgoorlie",
    "sg:classifiers":[
        {
            "category":"Wholesale",
            "subcategory":"Medical Equipment & Supplies",
            "type":"Manufacturing & Wholesale Goods"
        }
    ],
    "sg:phone":"+61 8 9091 7260",
    "sg:postcode":"6430",
    "sg:province":"WA",
    "sg:tags":[
        "aid",
        "care",
        "health",
        "home"
    ],
    "wof:name":"Desert Mobility",
    "wof:placetype":"venue"
},
  "geometry": {"coordinates":[121.482566834,-30.7589950562],"type":"Point"}
}