{
  "type": "Feature",
  "properties": {
    "addr:full":"Short St Beaudesert QLD 4285",
    "addr:postcode":"4285",
    "addr:street":"Short St",
    "iso:country":"AU",
    "sg:address":"Short St",
    "sg:city":"Beaudesert",
    "sg:classifiers":[
        {
            "category":"Professional",
            "subcategory":"Printing & Photocopies",
            "type":"Services"
        }
    ],
    "sg:phone":"+61 7 5541 1388",
    "sg:postcode":"4285",
    "sg:province":"QLD",
    "sg:tags":[
        "photocopying"
    ],
    "wof:name":"&#034;Beaudesert Times&#034; Pty Ltd",
    "wof:placetype":"venue"
},
  "geometry": {"coordinates":[152.99498,-27.987495],"type":"Point"}
}