{
  "type": "Feature",
  "properties": {
    "iso:country":"AU",
    "sg:address":"Ovens St",
    "sg:city":"Wangtta Wangaratta",
    "sg:classifiers":[
        {
            "category":"Health Services",
            "subcategory":"Medical Lab",
            "type":"Services"
        }
    ],
    "sg:phone":"+61 3 5722 9120",
    "sg:postcode":"3676",
    "sg:province":"VIC",
    "sg:tags":[
        "laboratory",
        "pathology"
    ],
    "wof:name":"Gribbles Pathology",
    "wof:placetype":"venue"
},
  "geometry": {"coordinates":[146.32453899999999,-36.354008],"type":"Point"}
}