{
  "type": "Feature",
  "properties": {
    "addr:full":"Suite 10/42-44 Urunga Parade Miranda NSW 2228",
    "addr:housenumber":"10 / 42-44",
    "addr:postcode":"2228",
    "addr:street":"Urunga Parade Miranda",
    "iso:country":"AU",
    "sg:address":"Suite 10/42-44 Urunga Parade",
    "sg:city":"Miranda",
    "sg:classifiers":[
        {
            "category":"Health Services",
            "subcategory":"Doctor",
            "type":"Services"
        }
    ],
    "sg:phone":"+61 2 9525 1800",
    "sg:postcode":"2228",
    "sg:province":"NSW",
    "sg:tags":[
        "medical",
        "practitioner"
    ],
    "wof:name":"Ridhalgh Mark Dr",
    "wof:placetype":"venue"
},
  "geometry": {"coordinates":[151.103027344,-34.035900116],"type":"Point"}
}