{
  "type": "Feature",
  "properties": {
    "addr:full":"121 Herries St Toowoomba QLD 4350",
    "addr:housenumber":"121",
    "addr:postcode":"4350",
    "addr:street":"Herries St",
    "iso:country":"AU",
    "sg:address":"121 Herries St",
    "sg:city":"Toowoomba",
    "sg:classifiers":[
        {
            "category":"Professional",
            "subcategory":"Accounting & Tax Preparation",
            "type":"Services"
        }
    ],
    "sg:phone":"+61 7 4638 1100",
    "sg:postcode":"4350",
    "sg:province":"QLD",
    "sg:tags":[
        "accountant",
        "auditor"
    ],
    "wof:name":"Cheesman Applegarth & Partners",
    "wof:placetype":"venue"
},
  "geometry": {"coordinates":[151.93722500000001,-27.562164],"type":"Point"}
}