{
  "type": "Feature",
  "properties": {
    "iso:country":"AU",
    "sg:address":"121 Herries St",
    "sg:city":"Toowoomba",
    "sg:classifiers":[
        {
            "category":"Professional",
            "subcategory":"Accounting & Tax Preparation",
            "type":"Services"
        }
    ],
    "sg:phone":"+61 7 4638 1100",
    "sg:postcode":"4350",
    "sg:province":"QLD",
    "sg:tags":[
        "accountant",
        "auditor"
    ],
    "wof:name":"Cheesman Applegarth & Partners",
    "wof:placetype":"venue"
},
  "geometry": {"coordinates":[151.937225,-27.562164],"type":"Point"}
}