{
  "type": "Feature",
  "properties": {
    "addr:full":"Lot 50 Port Drv Broome WA 6725",
    "addr:postcode":"6725",
    "addr:street":"Port Drv",
    "iso:country":"AU",
    "sg:address":"Lot 50 Port Drv",
    "sg:city":"Broome",
    "sg:classifiers":[
        {
            "category":"Wholesale",
            "subcategory":"Metals & Minerals",
            "type":"Manufacturing & Wholesale Goods"
        }
    ],
    "sg:phone":"+61 8 9192 6262",
    "sg:postcode":"6725",
    "sg:province":"WA",
    "sg:tags":[
        "steel",
        "merchant"
    ],
    "wof:name":"B & J Building Consultants & Steel Supplies",
    "wof:placetype":"venue"
},
  "geometry": {"coordinates":[122.677589416,-18.2141704559],"type":"Point"}
}