{
  "type": "Feature",
  "properties": {
    "addr:full":"1/ 21 Governor Macquarie Drv Chipping Norton NSW 2170",
    "addr:housenumber":"/ 21",
    "addr:postcode":"2170",
    "addr:street":"Governor Macquarie Drv",
    "iso:country":"AU",
    "sg:address":"1/ 21 Governor Macquarie Drv",
    "sg:city":"Chipping Norton",
    "sg:classifiers":[
        {
            "category":"Building & Trades",
            "subcategory":"Construction",
            "type":"Services"
        }
    ],
    "sg:phone":"+61 2 9755 1249",
    "sg:postcode":"2170",
    "sg:province":"NSW",
    "sg:tags":[
        "pool",
        "swimming"
    ],
    "wof:name":"Alliance Swimming Pools",
    "wof:placetype":"venue"
},
  "geometry": {"coordinates":[150.96244812,-33.9259223938],"type":"Point"}
}