{
  "type": "Feature",
  "properties": {
    "addr:full":"7/55 Victoria St Brunswick East VIC 3057",
    "addr:housenumber":"/ 55",
    "addr:postcode":"3057",
    "addr:street":"Victoria St",
    "iso:country":"AU",
    "sg:address":"7/55 Victoria St",
    "sg:city":"Brunswick East",
    "sg:classifiers":[
        {
            "category":"Health Services",
            "subcategory":"Health Practitioner",
            "type":"Services"
        }
    ],
    "sg:phone":"+61 403 740 064",
    "sg:postcode":"3057",
    "sg:province":"VIC",
    "sg:tags":[
        "homoeopath"
    ],
    "wof:name":"Alana Kidd",
    "wof:placetype":"venue"
},
  "geometry": {"coordinates":[144.97833251899999,-37.7686004639],"type":"Point"}
}