{
  "type": "Feature",
  "properties": {
    "addr:full":"Shop 22, Anzac Sq Arcade, 265 Edward Brisbane City QLD 4000",
    "addr:housenumber":"shop 22;265",
    "addr:postcode":"4000",
    "addr:street":"Anzac Sq Arcade;Edward Brisbane",
    "iso:country":"AU",
    "sg:address":"Shop 22, Anzac Sq Arcade, 265",
    "sg:city":"Edward Brisbane City",
    "sg:classifiers":[
        {
            "category":"Health Services",
            "subcategory":"Dentist",
            "type":"Services"
        }
    ],
    "sg:phone":"+61 7 3229 4300",
    "sg:postcode":"4000",
    "sg:province":"QLD",
    "wof:name":"Arnaldo J. Avenia",
    "wof:placetype":"venue"
},
  "geometry": {"coordinates":[153.026412964,-27.4666996002],"type":"Point"}
}