{
  "type": "Feature",
  "properties": {
    "iso:country":"AU",
    "sg:address":"16/ 28 Research Rd",
    "sg:city":"Pooraka",
    "sg:classifiers":[
        {
            "category":"Retail",
            "subcategory":"Auto Repair",
            "type":"Services"
        }
    ],
    "sg:phone":"+61 8 8262 6888",
    "sg:postcode":"5095",
    "sg:province":"SA",
    "sg:tags":[
        "repairer",
        "motor",
        "engineer"
    ],
    "wof:name":"Image Classic Cars",
    "wof:placetype":"venue"
},
  "geometry": {"coordinates":[138.634933472,-34.8163108826],"type":"Point"}
}