{
  "type": "Feature",
  "properties": {
    "addr:full":"Unit 3 / 5 Wadell Rd Gympie QLD 4570",
    "addr:housenumber":"5",
    "addr:postcode":"4570",
    "addr:street":"Wadell Rd",
    "iso:country":"AU",
    "sg:address":"Unit 3 / 5 Wadell Rd",
    "sg:city":"Gympie",
    "sg:classifiers":[
        {
            "category":"Professional",
            "subcategory":"Engineering",
            "type":"Services"
        }
    ],
    "sg:phone":"+61 7 5483 8138",
    "sg:postcode":"4570",
    "sg:province":"QLD",
    "sg:tags":[
        "manufacturing",
        "engineer"
    ],
    "wof:name":"Cooloola Precision Maintenance",
    "wof:placetype":"venue"
},
  "geometry": {"coordinates":[152.646682739,-26.1707019806],"type":"Point"}
}