{
  "type": "Feature",
  "properties": {
    "addr:full":"318 Robinson St Carnarvon WA 6701",
    "addr:housenumber":"318",
    "addr:postcode":"6701",
    "addr:street":"Robinson St",
    "iso:country":"AU",
    "sg:address":"318 Robinson St",
    "sg:city":"Carnarvon",
    "sg:classifiers":[
        {
            "category":"Retail",
            "subcategory":"Veterinary Services",
            "type":"Services"
        }
    ],
    "sg:phone":"+61 8 9941 1886",
    "sg:postcode":"6701",
    "sg:province":"WA",
    "sg:tags":[
        "surgeon"
    ],
    "wof:name":"Carnarvon Veterinary Clinic",
    "wof:placetype":"venue"
},
  "geometry": {"coordinates":[113.656608581,-24.8846607208],"type":"Point"}
}