{
  "type": "Feature",
  "properties": {
    "addr:full":"24 Central Crt Browns Plains QLD 4118",
    "addr:housenumber":"24",
    "addr:postcode":"4118",
    "addr:street":"Central Crt",
    "iso:country":"AU",
    "sg:address":"24 Central Crt",
    "sg:city":"Browns Plains",
    "sg:classifiers":[
        {
            "category":"Building & Trades",
            "subcategory":"Pest Control",
            "type":"Services"
        }
    ],
    "sg:phone":"+61 7 3806 8400",
    "sg:postcode":"4118",
    "sg:province":"QLD",
    "sg:tags":[
        "equipment",
        "abattoir",
        "machinery"
    ],
    "wof:name":"Kentmaster Equipment (Aust) Pty Ltd",
    "wof:placetype":"venue"
},
  "geometry": {"coordinates":[153.03521728499999,-27.6614742279],"type":"Point"}
}