{
  "type": "Feature",
  "properties": {
    "addr:full":"10 Duranbah Drv Huskisson NSW 2540",
    "addr:housenumber":"10",
    "addr:postcode":"2540",
    "addr:street":"Duranbah Drv",
    "iso:country":"AU",
    "sg:address":"10 Duranbah Drv",
    "sg:city":"Huskisson",
    "sg:classifiers":[
        {
            "category":"Autos & Motor Vehicles",
            "subcategory":"Motorcycle Sales",
            "type":"Retail Goods"
        }
    ],
    "sg:phone":"+61 2 4441 8990",
    "sg:postcode":"2540",
    "sg:province":"NSW",
    "sg:tags":[
        "outboard"
    ],
    "wof:name":"Husky Marine",
    "wof:placetype":"venue"
},
  "geometry": {"coordinates":[150.65965270999999,-35.0288696289],"type":"Point"}
}