{
  "type": "Feature",
  "properties": {
    "iso:country":"AU",
    "sg:address":"10 Loane Pl",
    "sg:city":"Dubbo",
    "sg:classifiers":[
        {
            "category":"Communications",
            "subcategory":"News Services",
            "type":"Services"
        }
    ],
    "sg:phone":"+61 2 6881 6001",
    "sg:postcode":"2830",
    "sg:province":"NSW",
    "sg:tags":[
        "information",
        "tourist",
        "attractions"
    ],
    "wof:name":"Amigos Spearfishing & Free Diving Adventures",
    "wof:placetype":"venue"
},
  "geometry": {"coordinates":[148.65017700199999,-32.2348098755],"type":"Point"}
}