{
  "type": "Feature",
  "properties": {
    "addr:full":"5 Pejaro Crt Knoxfield VIC 3180",
    "addr:housenumber":"5",
    "addr:postcode":"3180",
    "addr:street":"Pejaro Crt",
    "iso:country":"AU",
    "sg:address":"5 Pejaro Crt",
    "sg:city":"Knoxfield",
    "sg:classifiers":[
        {
            "category":"Utilities",
            "subcategory":"Refuse",
            "type":"Services"
        }
    ],
    "sg:phone":"+61 3 9558 2705",
    "sg:postcode":"3180",
    "sg:province":"VIC",
    "sg:tags":[
        "remover",
        "rubbish"
    ],
    "wof:name":"Busy Bin Hire",
    "wof:placetype":"venue"
},
  "geometry": {"coordinates":[145.24859619099999,-37.8904266357],"type":"Point"}
}