{
  "type": "Feature",
  "properties": {
    "addr:full":"Shop 6B Cnr Nicklin Way & Bellara Drv Currimundi QLD 4551",
    "addr:housenumber":"shop 6b",
    "addr:postcode":"4551",
    "addr:street":"Cnr Nicklin Way & Bellara Drv",
    "iso:country":"AU",
    "sg:address":"Shop 6B Cnr Nicklin Way & Bellara Drv",
    "sg:city":"Currimundi",
    "sg:classifiers":[
        {
            "category":"Travel",
            "subcategory":"Travel Agent",
            "type":"Entertainment"
        }
    ],
    "sg:phone":"+61 13 18 66",
    "sg:postcode":"4551",
    "sg:province":"QLD",
    "sg:tags":[
        "consultant"
    ],
    "wof:name":"Flight Centre",
    "wof:placetype":"venue"
},
  "geometry": {"coordinates":[153.12217712399999,-26.7688045502],"type":"Point"}
}