{
  "type": "Feature",
  "properties": {
    "addr:full":"5466 Great Alpine Rd Ovens VIC 3738",
    "addr:housenumber":"5466",
    "addr:postcode":"3738",
    "addr:street":"Great Alpine Rd",
    "iso:country":"AU",
    "sg:address":"5466 Great Alpine Rd",
    "sg:city":"Ovens",
    "sg:classifiers":[
        {
            "category":"Farming",
            "subcategory":"Farm",
            "type":"Manufacturing & Wholesale Goods"
        }
    ],
    "sg:phone":"+61 3 5752 1717",
    "sg:postcode":"3738",
    "sg:province":"VIC",
    "sg:tags":[
        "farmer"
    ],
    "wof:name":"Browne Clive & Anne",
    "wof:placetype":"venue"
},
  "geometry": {"coordinates":[146.79652404800001,-36.6071434021],"type":"Point"}
}