{
  "type": "Feature",
  "properties": {
    "iso:country":"AU",
    "sg:address":"11 Fitzroy St",
    "sg:city":"Warwick",
    "sg:classifiers":[
        {
            "category":"Health Services",
            "subcategory":"Health Practitioner",
            "type":"Services"
        }
    ],
    "sg:phone":"+61 7 4661 9982",
    "sg:postcode":"4370",
    "sg:province":"QLD",
    "sg:tags":[
        "alternative"
    ],
    "wof:name":"McLaren Photonic Therapy",
    "wof:placetype":"venue"
},
  "geometry": {"coordinates":[152.04574585,-28.2157974243],"type":"Point"}
}