{
  "type": "Feature",
  "properties": {
    "addr:full":"34 McEvoy St Waterloo NSW 2017",
    "addr:housenumber":"34",
    "addr:postcode":"2017",
    "addr:street":"Mcevoy St",
    "iso:country":"AU",
    "sg:address":"34 McEvoy St",
    "sg:city":"Waterloo",
    "sg:classifiers":[
        {
            "category":"Home & Garden",
            "subcategory":"Building Materials",
            "type":"Retail Goods"
        }
    ],
    "sg:phone":"+61 2 9319 6629",
    "sg:postcode":"2017",
    "sg:province":"NSW",
    "sg:tags":[
        "skylight"
    ],
    "wof:name":"Roofing Supermarket",
    "wof:placetype":"venue"
},
  "geometry": {"coordinates":[151.204177856,-33.9008369446],"type":"Point"}
}