{
  "type": "Feature",
  "properties": {
    "iso:country":"AU",
    "sg:address":"Cnr Lords Rd & Flood St",
    "sg:city":"Leichhardt",
    "sg:classifiers":[
        {
            "category":"Education",
            "subcategory":"Vocational School",
            "type":"Public Place"
        }
    ],
    "sg:phone":"+61 2 9569 5043",
    "sg:postcode":"2040",
    "sg:province":"NSW",
    "sg:tags":[
        "beauty"
    ],
    "wof:name":"Cosmetic Tattoo Dianne K Clinic",
    "wof:placetype":"venue"
},
  "geometry": {"coordinates":[151.149139,-33.885796],"type":"Point"}
}