{
  "type": "Feature",
  "properties": {
    "addr:full":"3 Trappers Drv Woodvale WA 6026",
    "addr:housenumber":"3",
    "addr:postcode":"6026",
    "addr:street":"Trappers Drv",
    "iso:country":"AU",
    "sg:address":"3 Trappers Drv",
    "sg:city":"Woodvale",
    "sg:classifiers":[
        {
            "category":"Health Services",
            "subcategory":"Dentist",
            "type":"Services"
        }
    ],
    "sg:phone":"+61 8 9309 2339",
    "sg:postcode":"6026",
    "sg:province":"WA",
    "wof:name":"Afonso Fernando",
    "wof:placetype":"venue"
},
  "geometry": {"coordinates":[115.795791626,-31.7979793549],"type":"Point"}
}