{
  "type": "Feature",
  "properties": {
    "addr:full":"Unit 2/ 9 Cleaver St West Perth WA 6005",
    "addr:housenumber":"9",
    "addr:postcode":"6005",
    "addr:street":"Cleaver St",
    "iso:country":"AU",
    "sg:address":"Unit 2/ 9 Cleaver St",
    "sg:city":"West Perth",
    "sg:classifiers":[
        {
            "category":"Banks & Credit Unions",
            "subcategory":"Bank",
            "type":"Services"
        }
    ],
    "sg:phone":"+61 8 9228 1000",
    "sg:postcode":"6005",
    "sg:province":"WA",
    "sg:tags":[
        "broker",
        "mortgage"
    ],
    "wof:name":"Independent Mortgage & Finance Services (IMFS)",
    "wof:placetype":"venue"
},
  "geometry": {"coordinates":[115.847991943,-31.9404468536],"type":"Point"}
}