{
  "type": "Feature",
  "properties": {
    "iso:country":"AU",
    "sg:address":"7/ 17 Orchid Ave",
    "sg:city":"Surfers Paradise",
    "sg:classifiers":[
        {
            "category":"Professional",
            "subcategory":"Management & Consulting",
            "type":"Services"
        }
    ],
    "sg:phone":"+61 7 5539 8377",
    "sg:postcode":"4217",
    "sg:province":"QLD",
    "sg:tags":[
        "consultant",
        "educational"
    ],
    "wof:name":"Asa Australian Studies Advice",
    "wof:placetype":"venue"
},
  "geometry": {"coordinates":[153.429763794,-28.0006523132],"type":"Point"}
}