{
  "type": "Feature",
  "properties": {
    "addr:full":"433 Upper Edward St Spring Hill QLD 4000",
    "addr:housenumber":"433",
    "addr:postcode":"4000",
    "addr:street":"Upper Edward St",
    "iso:country":"AU",
    "sg:address":"433 Upper Edward St",
    "sg:city":"Spring Hill",
    "sg:classifiers":[
        {
            "category":"Banks & Credit Unions",
            "subcategory":"Bank",
            "type":"Services"
        }
    ],
    "sg:phone":"+61 7 3831 8206",
    "sg:postcode":"4000",
    "sg:province":"QLD",
    "wof:name":"Bank of Queensland",
    "wof:placetype":"venue"
},
  "geometry": {"coordinates":[153.024490356,-27.4637947083],"type":"Point"}
}