{
  "type": "Feature",
  "properties": {
    "iso:country":"AU",
    "sg:address":"250 Old Prospect Rd",
    "sg:city":"Greystanes",
    "sg:classifiers":[
        {
            "category":"Health Services",
            "subcategory":"Doctor",
            "type":"Services"
        }
    ],
    "sg:phone":"+61 2 9636 6244",
    "sg:postcode":"2145",
    "sg:province":"NSW",
    "sg:tags":[
        "medical",
        "practitioner"
    ],
    "wof:name":"Singh M.",
    "wof:placetype":"venue"
},
  "geometry": {"coordinates":[150.941680908,-33.8190879822],"type":"Point"}
}