{
  "type": "Feature",
  "properties": {
    "addr:full":"5/ 12 Sewell Ave Crafers SA 5152",
    "addr:housenumber":"/ 12",
    "addr:postcode":"5152",
    "addr:street":"Sewell Ave",
    "iso:country":"AU",
    "sg:address":"5/ 12 Sewell Ave",
    "sg:city":"Crafers",
    "sg:classifiers":[
        {
            "category":"Government",
            "subcategory":"Court House",
            "type":"Public Place"
        }
    ],
    "sg:phone":"+61 8 8339 5745",
    "sg:postcode":"5152",
    "sg:province":"SA",
    "sg:tags":[
        "personal",
        "marriage",
        "family",
        "counselling"
    ],
    "wof:name":"Coombe Jenny",
    "wof:placetype":"venue"
},
  "geometry": {"coordinates":[138.70338439899999,-34.9972000122],"type":"Point"}
}