{
  "type": "Feature",
  "properties": {
    "iso:country":"AU",
    "sg:address":"713 Plenty Rd",
    "sg:city":"Reservoir",
    "sg:classifiers":[
        {
            "category":"Communications",
            "type":"Services"
        }
    ],
    "sg:phone":"+61 3 9478 9604",
    "sg:postcode":"3073",
    "sg:province":"VIC",
    "sg:tags":[
        "translation"
    ],
    "wof:name":"Dittes",
    "wof:placetype":"venue"
},
  "geometry": {"coordinates":[145.078033447,-37.6570358276],"type":"Point"}
}