{
  "type": "Feature",
  "properties": {
    "iso:country":"AU",
    "sg:address":"120 Blair St",
    "sg:city":"Bunbury",
    "sg:classifiers":[
        {
            "category":"Retail",
            "subcategory":"Auto Repair",
            "type":"Services"
        }
    ],
    "sg:phone":"+61 8 9791 1108",
    "sg:postcode":"6230",
    "sg:province":"WA",
    "sg:tags":[
        "repairer",
        "motor",
        "engineer"
    ],
    "wof:name":"Kmart Tyre & Auto Service",
    "wof:placetype":"venue"
},
  "geometry": {"coordinates":[115.643593,-33.332756],"type":"Point"}
}