{
  "type": "Feature",
  "properties": {
    "addr:full":"16 Crestview Pl Gosford East NSW 2250",
    "addr:housenumber":"16",
    "addr:postcode":"2250",
    "addr:street":"Crestview Pl",
    "iso:country":"AU",
    "sg:address":"16 Crestview Pl",
    "sg:city":"Gosford East",
    "sg:classifiers":[
        {
            "category":"Banks & Credit Unions",
            "subcategory":"Financial Services",
            "type":"Services"
        }
    ],
    "sg:phone":"+61 2 4362 8099",
    "sg:postcode":"2250",
    "sg:province":"NSW",
    "sg:tags":[
        "planning"
    ],
    "wof:name":"Materials Cost Management",
    "wof:placetype":"venue"
},
  "geometry": {"coordinates":[151.38101196299999,-33.3823661804],"type":"Point"}
}