{
  "type": "Feature",
  "properties": {
    "iso:country":"AU",
    "sg:address":"116/118, Unit 1, Kelvin Rd",
    "sg:city":"Maddington",
    "sg:classifiers":[
        {
            "category":"Manufacturing",
            "subcategory":"Paper Products",
            "type":"Manufacturing & Wholesale Goods"
        }
    ],
    "sg:phone":"+61 8 9493 6101",
    "sg:postcode":"6109",
    "sg:province":"WA",
    "sg:tags":[
        "building",
        "fibre",
        "cement"
    ],
    "wof:name":"C & L Ceilings",
    "wof:placetype":"venue"
},
  "geometry": {"coordinates":[116.006492615,-32.0293312073],"type":"Point"}
}