{
  "type": "Feature",
  "properties": {
    "addr:full":"440 Romani Drv Lavington NSW 2641",
    "addr:housenumber":"440",
    "addr:postcode":"2641",
    "addr:street":"Romani Drv",
    "iso:country":"AU",
    "sg:address":"440 Romani Drv",
    "sg:city":"Lavington",
    "sg:classifiers":[
        {
            "category":"Utilities",
            "subcategory":"Water",
            "type":"Services"
        }
    ],
    "sg:phone":"+61 418 572 633",
    "sg:postcode":"2641",
    "sg:province":"NSW",
    "sg:tags":[
        "hot",
        "system"
    ],
    "wof:name":"Spalding Mark",
    "wof:placetype":"venue"
},
  "geometry": {"coordinates":[146.942138672,-36.0370941162],"type":"Point"}
}