{
  "type": "Feature",
  "properties": {
    "iso:country":"AU",
    "sg:address":"Central Business Park, Durgadin Drv",
    "sg:city":"Albion Park Rail",
    "sg:classifiers":[
        {
            "category":"Utilities",
            "type":"Services"
        }
    ],
    "sg:phone":"+61 2 4256 1100",
    "sg:postcode":"2527",
    "sg:province":"NSW",
    "sg:tags":[
        "equipment",
        "towing"
    ],
    "wof:name":"Coastal Bullbars",
    "wof:placetype":"venue"
},
  "geometry": {"coordinates":[150.81629943900001,-34.5719108582],"type":"Point"}
}