{
  "type": "Feature",
  "properties": {
    "addr:full":"Level 29 2 Chifley Sq Sydney NSW 2000",
    "addr:housenumber":"2",
    "addr:postcode":"2000",
    "addr:street":"Chifley Sq",
    "iso:country":"AU",
    "sg:address":"Level 29 2 Chifley Sq",
    "sg:city":"Sydney",
    "sg:classifiers":[
        {
            "category":"Real Estate",
            "subcategory":"Real Estate Services",
            "type":"Services"
        }
    ],
    "sg:phone":"+61 2 9375 2152",
    "sg:postcode":"2000",
    "sg:province":"NSW",
    "sg:tags":[
        "consultant",
        "property"
    ],
    "wof:name":"Equity Development Corporation",
    "wof:placetype":"venue"
},
  "geometry": {"coordinates":[151.21148681599999,-33.8661117554],"type":"Point"}
}