{
  "type": "Feature",
  "properties": {
    "addr:full":"Lvl 12, 220 George St Sydney NSW 2000",
    "addr:housenumber":"220",
    "addr:postcode":"2000",
    "addr:street":"George St",
    "iso:country":"AU",
    "sg:address":"Lvl 12, 220 George St",
    "sg:city":"Sydney",
    "sg:classifiers":[
        {
            "category":"Professional",
            "subcategory":"Management & Consulting",
            "type":"Services"
        }
    ],
    "sg:phone":"+61 2 9251 4072",
    "sg:postcode":"2000",
    "sg:province":"NSW",
    "sg:tags":[
        "consultant"
    ],
    "wof:name":"Next Energy",
    "wof:placetype":"venue"
},
  "geometry": {"coordinates":[151.20767211899999,-33.8631782532],"type":"Point"}
}