{
  "type": "Feature",
  "properties": {
    "iso:country":"AU",
    "sg:address":"1 High St",
    "sg:city":"Belmont",
    "sg:classifiers":[
        {
            "category":"Health Services",
            "subcategory":"Optometrist",
            "type":"Services"
        }
    ],
    "sg:phone":"+61 3 5245 7600",
    "sg:postcode":"3216",
    "sg:province":"VIC",
    "wof:name":"Nguyen Kevin",
    "wof:placetype":"venue"
},
  "geometry": {"coordinates":[144.35015869099999,-38.168258667],"type":"Point"}
}