{
  "type": "Feature",
  "properties": {
    "iso:country":"AU",
    "sg:address":"Unit 3, 31 Chapel St",
    "sg:city":"Marrickville",
    "sg:classifiers":[
        {
            "category":"Shopping",
            "type":"Retail Goods"
        }
    ],
    "sg:phone":"+61 2 9519 5122",
    "sg:postcode":"2204",
    "sg:province":"NSW",
    "sg:tags":[
        "equipment",
        "safety",
        "accessory"
    ],
    "sg:website":"http://www.shss.com.au",
    "wof:name":"Sydney Height Safety Solutions",
    "wof:placetype":"venue"
},
  "geometry": {"coordinates":[151.165161,-33.907146],"type":"Point"}
}