{
  "type": "Feature",
  "properties": {
    "addr:full":"Shop 1/ 413 Banna Ave Griffith NSW 2680",
    "addr:housenumber":"shop 1 / 413",
    "addr:postcode":"2680",
    "addr:street":"Banna Ave",
    "iso:country":"AU",
    "sg:address":"Shop 1/ 413 Banna Ave",
    "sg:city":"Griffith",
    "sg:classifiers":[
        {
            "category":"Personal",
            "subcategory":"Beauty Salon",
            "type":"Services"
        }
    ],
    "sg:phone":"+61 2 6964 7711",
    "sg:postcode":"2680",
    "sg:province":"NSW",
    "sg:tags":[
        "hairdresser"
    ],
    "wof:name":"The Avenue Art of Hair",
    "wof:placetype":"venue"
},
  "geometry": {"coordinates":[146.04208399999999,-34.287186],"type":"Point"}
}