{
  "type": "Feature",
  "properties": {
    "addr:full":"Shp2/ 15 Clarence St Yamba NSW 2464",
    "addr:housenumber":"15",
    "addr:postcode":"2464",
    "addr:street":"Clarence St",
    "iso:country":"AU",
    "sg:address":"Shp2/ 15 Clarence St",
    "sg:city":"Yamba",
    "sg:classifiers":[
        {
            "category":"Restaurant",
            "type":"Food & Drink"
        }
    ],
    "sg:phone":"+61 2 6646 9929",
    "sg:postcode":"2464",
    "sg:province":"NSW",
    "wof:name":"Coyotes Cantina",
    "wof:placetype":"venue"
},
  "geometry": {"coordinates":[153.36268615700001,-29.4351615906],"type":"Point"}
}