{
  "type": "Feature",
  "properties": {
    "addr:full":"26a Victoria St Warragul VIC 3820",
    "addr:housenumber":"26a",
    "addr:postcode":"3820",
    "addr:street":"Victoria St",
    "iso:country":"AU",
    "sg:address":"26a Victoria St",
    "sg:city":"Warragul",
    "sg:classifiers":[
        {
            "category":"Shopping",
            "subcategory":"Music",
            "type":"Retail Goods"
        }
    ],
    "sg:phone":"+61 3 5623 1651",
    "sg:postcode":"3820",
    "sg:province":"VIC",
    "sg:tags":[
        "store"
    ],
    "wof:name":"Leading Edge Music",
    "wof:placetype":"venue"
},
  "geometry": {"coordinates":[145.930634,-38.16177],"type":"Point"}
}