{
  "type": "Feature",
  "properties": {
    "addr:full":"1 Brierbank St Underwood QLD 4119",
    "addr:housenumber":"1",
    "addr:postcode":"4119",
    "addr:street":"Brierbank St",
    "iso:country":"AU",
    "sg:address":"1 Brierbank St",
    "sg:city":"Underwood",
    "sg:classifiers":[
        {
            "category":"Professional",
            "subcategory":"Computer Services",
            "type":"Services"
        }
    ],
    "sg:phone":"+61 7 3219 0200",
    "sg:postcode":"4119",
    "sg:province":"QLD",
    "sg:tags":[
        "training"
    ],
    "wof:name":"Kickstart Computer & Software Services Training",
    "wof:placetype":"venue"
},
  "geometry": {"coordinates":[153.109619141,-27.6129741669],"type":"Point"}
}