{
  "type": "Feature",
  "properties": {
    "addr:full":"Hannans Boulevard Shopping Centre Graeme St Kalgoorlie WA 6430",
    "addr:postcode":"6430",
    "addr:street":"Graeme St",
    "iso:country":"AU",
    "sg:address":"Hannans Boulevard Shopping Centre Graeme St",
    "sg:city":"Kalgoorlie",
    "sg:classifiers":[
        {
            "category":"Communications",
            "subcategory":"Film & Video Production",
            "type":"Services"
        }
    ],
    "sg:phone":"+61 8 9091 1868",
    "sg:postcode":"6430",
    "sg:province":"WA",
    "sg:tags":[
        "dvd",
        "library"
    ],
    "wof:name":"Civic Video Hannans",
    "wof:placetype":"venue"
},
  "geometry": {"coordinates":[121.46408844,-30.7382259369],"type":"Point"}
}