{
  "type": "Feature",
  "properties": {
    "iso:country":"AU",
    "sg:address":"7 Oak St",
    "sg:city":"Evans Head",
    "sg:classifiers":[
        {
            "category":"Food & Beverages",
            "subcategory":"Supermarket",
            "type":"Retail Goods"
        }
    ],
    "sg:phone":"+61 2 6682 4757",
    "sg:postcode":"2473",
    "sg:province":"NSW",
    "sg:tags":[
        "grocery",
        "store"
    ],
    "wof:name":"Farmer Charlies",
    "wof:placetype":"venue"
},
  "geometry": {"coordinates":[153.43106079099999,-29.1177501678],"type":"Point"}
}