{
  "type": "Feature",
  "properties": {
    "addr:full":"Kendall La The Rocks NSW 2000",
    "addr:postcode":"2000",
    "addr:street":"Kendall La",
    "iso:country":"AU",
    "sg:address":"Kendall La",
    "sg:city":"The Rocks",
    "sg:classifiers":[
        {
            "category":"Communications",
            "subcategory":"News Services",
            "type":"Services"
        }
    ],
    "sg:phone":"+61 2 9240 8680",
    "sg:postcode":"2000",
    "sg:province":"NSW",
    "sg:tags":[
        "information",
        "tourist",
        "attractions"
    ],
    "wof:name":"The Rocks Discovery Museum",
    "wof:placetype":"venue"
},
  "geometry": {"coordinates":[151.20854187,-33.8587722778],"type":"Point"}
}