{
  "type": "Feature",
  "properties": {
    "iso:country":"AU",
    "sg:address":"1- 2 Badgerys Crs",
    "sg:city":"Lawson",
    "sg:classifiers":[
        {
            "category":"Shopping",
            "subcategory":"Antiques",
            "type":"Retail Goods"
        }
    ],
    "sg:phone":"+61 2 4759 3199",
    "sg:postcode":"2783",
    "sg:province":"NSW",
    "wof:name":"Badgerys Attic",
    "wof:placetype":"venue"
},
  "geometry": {"coordinates":[150.43429565400001,-33.718170166],"type":"Point"}
}