{
  "type": "Feature",
  "properties": {
    "iso:country":"AU",
    "sg:address":"Suite 4 107 Cambridge St",
    "sg:city":"Collingwood",
    "sg:classifiers":[
        {
            "category":"Wholesale",
            "subcategory":"Non-durable Goods",
            "type":"Manufacturing & Wholesale Goods"
        }
    ],
    "sg:phone":"+61 3 9416 1107",
    "sg:postcode":"3066",
    "sg:province":"VIC",
    "sg:tags":[
        "textile"
    ],
    "wof:name":"Cooper Watkinson Textile Pty Ltd",
    "wof:placetype":"venue"
},
  "geometry": {"coordinates":[144.985275269,-37.8050460815],"type":"Point"}
}