{
  "type": "Feature",
  "properties": {
    "iso:country":"AU",
    "sg:address":"20 Henry St",
    "sg:city":"Fremantle",
    "sg:classifiers":[
        {
            "category":"Personal",
            "subcategory":"Tattoo Parlor",
            "type":"Services"
        }
    ],
    "sg:phone":"+61 8 9430 5843",
    "sg:postcode":"6160",
    "sg:province":"WA",
    "sg:tags":[
        "tattooing"
    ],
    "wof:name":"Tattoo WA Ink",
    "wof:placetype":"venue"
},
  "geometry": {"coordinates":[115.744049,-32.055382],"type":"Point"}
}