{
  "type": "Feature",
  "properties": {
    "addr:full":"934- 936 Botany Rd Mascot NSW 2020",
    "addr:housenumber":"936",
    "addr:postcode":"2020",
    "addr:street":"Botany Rd",
    "iso:country":"AU",
    "sg:address":"934- 936 Botany Rd",
    "sg:city":"Mascot",
    "sg:classifiers":[
        {
            "category":"Health Services",
            "subcategory":"Doctor",
            "type":"Services"
        }
    ],
    "sg:phone":"+61 2 9317 4222",
    "sg:postcode":"2020",
    "sg:province":"NSW",
    "sg:tags":[
        "medical",
        "practitioner"
    ],
    "wof:name":"Vo Peter",
    "wof:placetype":"venue"
},
  "geometry": {"coordinates":[151.194381714,-33.9301338196],"type":"Point"}
}