{
  "type": "Feature",
  "properties": {
    "addr:full":"695A Old South Head Rd Vaucluse NSW 2030",
    "addr:housenumber":"695a",
    "addr:postcode":"2030",
    "addr:street":"Old South Head Rd",
    "iso:country":"AU",
    "sg:address":"695A Old South Head Rd",
    "sg:city":"Vaucluse",
    "sg:classifiers":[
        {
            "category":"Health Services",
            "subcategory":"Health Practitioner",
            "type":"Services"
        }
    ],
    "sg:phone":"+61 2 9337 4533",
    "sg:postcode":"2030",
    "sg:province":"NSW",
    "sg:tags":[
        "acupuncture"
    ],
    "wof:name":"MacDonald John",
    "wof:placetype":"venue"
},
  "geometry": {"coordinates":[151.27859497099999,-33.8630943298],"type":"Point"}
}