{
  "type": "Feature",
  "properties": {
    "addr:full":"468 Macquarie St South Hobart TAS 7004",
    "addr:housenumber":"468",
    "addr:postcode":"7004",
    "addr:street":"Macquarie St",
    "iso:country":"AU",
    "sg:address":"468 Macquarie St",
    "sg:city":"South Hobart",
    "sg:classifiers":[
        {
            "category":"Food & Beverages",
            "subcategory":"Supermarket",
            "type":"Retail Goods"
        }
    ],
    "sg:phone":"+61 3 6223 6138",
    "sg:postcode":"7004",
    "sg:province":"TAS",
    "sg:tags":[
        "grocery",
        "store"
    ],
    "wof:name":"South Hobart Riteway Supermarket",
    "wof:placetype":"venue"
},
  "geometry": {"coordinates":[147.30914306599999,-42.8947143555],"type":"Point"}
}