{
  "type": "Feature",
  "properties": {
    "addr:full":"26 Gatwick St Deeragun QLD 4818",
    "addr:housenumber":"26",
    "addr:postcode":"4818",
    "addr:street":"Gatwick St",
    "iso:country":"AU",
    "sg:address":"26 Gatwick St",
    "sg:city":"Deeragun",
    "sg:classifiers":[
        {
            "category":"Building & Trades",
            "subcategory":"Construction",
            "type":"Services"
        }
    ],
    "sg:phone":"+61 438 689 152",
    "sg:postcode":"4818",
    "sg:province":"QLD",
    "sg:tags":[
        "renovation",
        "alterations",
        "extension",
        "contractor"
    ],
    "wof:name":"Ray Gaites Renovations",
    "wof:placetype":"venue"
},
  "geometry": {"coordinates":[146.68424999999999,-19.245413],"type":"Point"}
}