{
  "type": "Feature",
  "properties": {
    "iso:country":"AU",
    "sg:address":"17 Furley St",
    "sg:city":"Aspley",
    "sg:classifiers":[
        {
            "category":"Professional",
            "subcategory":"Employment Agencies",
            "type":"Services"
        }
    ],
    "sg:phone":"+61 7 3263 8249",
    "sg:postcode":"4034",
    "sg:province":"QLD",
    "sg:tags":[
        "occupational",
        "therapist"
    ],
    "wof:name":"Coralee Lawrence",
    "wof:placetype":"venue"
},
  "geometry": {"coordinates":[153.018875,-27.365484],"type":"Point"}
}