{
  "type": "Feature",
  "properties": {
    "iso:country":"AU",
    "sg:address":"14 Watt St",
    "sg:city":"Newcastle",
    "sg:classifiers":[
        {
            "category":"Health Services",
            "subcategory":"Doctor",
            "type":"Services"
        }
    ],
    "sg:phone":"+61 2 4926 1241",
    "sg:postcode":"2300",
    "sg:province":"NSW",
    "sg:tags":[
        "medical",
        "practitioner"
    ],
    "wof:name":"Graham Dr John",
    "wof:placetype":"venue"
},
  "geometry": {"coordinates":[151.784454,-32.927967],"type":"Point"}
}