{
  "type": "Feature",
  "properties": {
    "addr:full":"17 Adelaide Rd Mt Barker SA 5251",
    "addr:housenumber":"17",
    "addr:postcode":"5251",
    "addr:street":"Adelaide Rd",
    "iso:country":"AU",
    "sg:address":"17 Adelaide Rd",
    "sg:city":"Mt Barker",
    "sg:classifiers":[
        {
            "category":"Cinema",
            "subcategory":"Movie Theater",
            "type":"Entertainment"
        }
    ],
    "sg:phone":"+61 8 8391 2777",
    "sg:postcode":"5251",
    "sg:province":"SA",
    "wof:name":"Mt Barker Cinema",
    "wof:placetype":"venue"
},
  "geometry": {"coordinates":[138.857177734,-35.0676689148],"type":"Point"}
}