{
  "type": "Feature",
  "properties": {
    "addr:full":"262 Spence St Bungalow QLD 4870",
    "addr:housenumber":"262",
    "addr:postcode":"4870",
    "addr:street":"Spence St",
    "iso:country":"AU",
    "sg:address":"262 Spence St",
    "sg:city":"Bungalow",
    "sg:classifiers":[
        {
            "category":"Building & Trades",
            "subcategory":"Locksmith",
            "type":"Services"
        }
    ],
    "sg:phone":"+61 418 774 287",
    "sg:postcode":"4870",
    "sg:province":"QLD",
    "sg:tags":[
        "lock"
    ],
    "wof:name":"Peter J Rhodes",
    "wof:placetype":"venue"
},
  "geometry": {"coordinates":[145.75942993199999,-16.9373836517],"type":"Point"}
}