{
  "type": "Feature",
  "properties": {
    "addr:full":"Lot 43 Smyth Rd Howard Springs NT 0835",
    "addr:postcode":"nt 0835",
    "addr:street":"Smyth Rd",
    "iso:country":"AU",
    "sg:address":"Lot 43 Smyth Rd",
    "sg:city":"Howard Springs",
    "sg:classifiers":[
        {
            "category":"Retail",
            "subcategory":"Veterinary Services",
            "type":"Services"
        }
    ],
    "sg:phone":"+61 8 8983 1458",
    "sg:postcode":"0835",
    "sg:province":"NT",
    "sg:tags":[
        "surgeon"
    ],
    "wof:name":"Farebrother Jamin",
    "wof:placetype":"venue"
},
  "geometry": {"coordinates":[131.04423499999999,-12.500773],"type":"Point"}
}