{
  "type": "Feature",
  "properties": {
    "addr:full":"210 Were St Brighton East VIC 3187",
    "addr:housenumber":"210",
    "addr:postcode":"3187",
    "addr:street":"Were St",
    "iso:country":"AU",
    "sg:address":"210 Were St",
    "sg:city":"Brighton East",
    "sg:classifiers":[
        {
            "category":"Building & Trades",
            "subcategory":"Landscaping Services",
            "type":"Services"
        }
    ],
    "sg:phone":"+61 3 9592 9172",
    "sg:postcode":"3187",
    "sg:province":"VIC",
    "sg:tags":[
        "designer",
        "landscape",
        "contractor"
    ],
    "wof:name":"Mark Pedley Professional Landscaping",
    "wof:placetype":"venue"
},
  "geometry": {"coordinates":[145.00872802699999,-37.9266204834],"type":"Point"}
}