{
  "type": "Feature",
  "properties": {
    "addr:full":"15 James St Brunswick West VIC 3055",
    "addr:housenumber":"15",
    "addr:postcode":"3055",
    "addr:street":"James St",
    "iso:country":"AU",
    "sg:address":"15 James St",
    "sg:city":"Brunswick West",
    "sg:classifiers":[
        {
            "category":"Professional",
            "subcategory":"Art Services",
            "type":"Services"
        }
    ],
    "sg:phone":"+61 408 364 752",
    "sg:postcode":"3055",
    "sg:province":"VIC",
    "sg:tags":[
        "graphic",
        "designer"
    ],
    "wof:name":"Jacqueline Campbell Graphic Design",
    "wof:placetype":"venue"
},
  "geometry": {"coordinates":[144.94332885700001,-37.7621650696],"type":"Point"}
}