{
  "type": "Feature",
  "properties": {
    "addr:full":"40 Lipton Drv Thomastown VIC 3074",
    "addr:housenumber":"40",
    "addr:postcode":"3074",
    "addr:street":"Lipton Drv",
    "iso:country":"AU",
    "sg:address":"40 Lipton Drv",
    "sg:city":"Thomastown",
    "sg:classifiers":[
        {
            "category":"Manufacturing",
            "subcategory":"Motor Vehicles & Parts",
            "type":"Manufacturing & Wholesale Goods"
        }
    ],
    "sg:phone":"+61 3 9462 2920",
    "sg:postcode":"3074",
    "sg:province":"VIC",
    "sg:tags":[
        "replacement"
    ],
    "wof:name":"Early Bird Falcon Parts",
    "wof:placetype":"venue"
},
  "geometry": {"coordinates":[144.99681091299999,-37.6889419556],"type":"Point"}
}