{
  "type": "Feature",
  "properties": {
    "addr:full":"20 Holt St McMahons Point NSW 2060",
    "addr:housenumber":"20",
    "addr:postcode":"2060",
    "addr:street":"Holt St",
    "iso:country":"AU",
    "sg:address":"20 Holt St",
    "sg:city":"McMahons Point",
    "sg:classifiers":[
        {
            "category":"Commercial Area",
            "type":"Public Place"
        }
    ],
    "sg:phone":"+61 2 9922 7712",
    "sg:postcode":"2060",
    "sg:province":"NSW",
    "sg:tags":[
        "bar",
        "domestic"
    ],
    "wof:name":"Speedpour Bar Industry Services",
    "wof:placetype":"venue"
},
  "geometry": {"coordinates":[151.20439148,-33.8429641724],"type":"Point"}
}