{
  "type": "Feature",
  "properties": {
    "iso:country":"AU",
    "sg:address":"237 Marrickville Rd",
    "sg:city":"Marrickville",
    "sg:classifiers":[
        {
            "category":"Shopping",
            "subcategory":"Discount & Variety Stores",
            "type":"Retail Goods"
        }
    ],
    "sg:phone":"+61 2 9518 3999",
    "sg:postcode":"2204",
    "sg:province":"NSW",
    "sg:tags":[
        "shop",
        "adult"
    ],
    "wof:name":"Marrickville Adult Book Exchange",
    "wof:placetype":"venue"
},
  "geometry": {"coordinates":[151.156723,-33.910534],"type":"Point"}
}