{
  "type": "Feature",
  "properties": {
    "addr:full":"Cnr Ocean Beach Rd & Lone Pine Ave Umina NSW 2257",
    "addr:postcode":"2257",
    "addr:street":"Cnr Ocean Beach Rd & Lone;Ave",
    "iso:country":"AU",
    "sg:address":"Cnr Ocean Beach Rd & Lone Pine Ave",
    "sg:city":"Umina",
    "sg:classifiers":[
        {
            "category":"Wholesale",
            "subcategory":"Medical Equipment & Supplies",
            "type":"Manufacturing & Wholesale Goods"
        }
    ],
    "sg:phone":"+61 2 4341 6906",
    "sg:postcode":"2257",
    "sg:province":"NSW",
    "sg:tags":[
        "aid",
        "care",
        "health",
        "home"
    ],
    "wof:name":"Pearses Chemmart Pharmacy Umina",
    "wof:placetype":"venue"
},
  "geometry": {"coordinates":[151.318084717,-33.5131378174],"type":"Point"}
}