{
  "type": "Feature",
  "properties": {
    "addr:full":"5 Maritana St Kalgoorlie WA 6430",
    "addr:housenumber":"5",
    "addr:postcode":"6430",
    "addr:street":"Maritana St",
    "iso:country":"AU",
    "sg:address":"5 Maritana St",
    "sg:city":"Kalgoorlie",
    "sg:classifiers":[
        {
            "category":"Retail",
            "subcategory":"Auto Repair",
            "type":"Services"
        }
    ],
    "sg:phone":"+61 8 9091 9679",
    "sg:postcode":"6430",
    "sg:province":"WA",
    "sg:tags":[
        "repairer",
        "motor",
        "engineer"
    ],
    "wof:name":"Neill Auto Repairs",
    "wof:placetype":"venue"
},
  "geometry": {"coordinates":[121.467727661,-30.7404689789],"type":"Point"}
}