{
  "type": "Feature",
  "properties": {
    "addr:full":"22 Flora St Kirrawee NSW 2232",
    "addr:housenumber":"22",
    "addr:postcode":"2232",
    "addr:street":"Flora St",
    "iso:country":"AU",
    "sg:address":"22 Flora St",
    "sg:city":"Kirrawee",
    "sg:classifiers":[
        {
            "category":"Retail",
            "subcategory":"Auto Repair",
            "type":"Services"
        }
    ],
    "sg:phone":"+61 2 9521 4099",
    "sg:postcode":"2232",
    "sg:province":"NSW",
    "sg:tags":[
        "repairer",
        "motor",
        "engineer"
    ],
    "wof:name":"Carlden Automotive",
    "wof:placetype":"venue"
},
  "geometry": {"coordinates":[151.07359314000001,-34.0341415405],"type":"Point"}
}