{
  "type": "Feature",
  "properties": {
    "addr:full":"PO Box 20 Goondiwindi QLD 4390",
    "addr:postcode":"4390",
    "iso:country":"AU",
    "sg:address":"PO Box 20",
    "sg:city":"Goondiwindi",
    "sg:classifiers":[
        {
            "category":"Government",
            "subcategory":"Post Office",
            "type":"Public Place"
        }
    ],
    "sg:phone":"+61 419 731 035",
    "sg:postcode":"4390",
    "sg:province":"QLD",
    "sg:tags":[
        "silo"
    ],
    "wof:name":"AhrensM&S",
    "wof:placetype":"venue"
},
  "geometry": {"coordinates":[150.32357788100001,-28.5492191315],"type":"Point"}
}