{
  "type": "Feature",
  "properties": {
    "addr:full":"Palmeston Hwy Millaa Millaa QLD 4886",
    "addr:postcode":"4886",
    "addr:street":"Palmeston Hwy",
    "iso:country":"AU",
    "sg:address":"Palmeston Hwy",
    "sg:city":"Millaa Millaa",
    "sg:classifiers":[
        {
            "category":"Farming",
            "subcategory":"Farm",
            "type":"Manufacturing & Wholesale Goods"
        }
    ],
    "sg:phone":"+61 7 4097 2162",
    "sg:postcode":"4886",
    "sg:province":"QLD",
    "sg:tags":[
        "farmer"
    ],
    "wof:name":"Hartin R J & C J",
    "wof:placetype":"venue"
},
  "geometry": {"coordinates":[145.62872314399999,-17.5042476654],"type":"Point"}
}