{
  "type": "Feature",
  "properties": {
    "addr:full":"Shop 12, Middle Ridge Shopping Centre, Cnr Spring Toowoomba QLD 4350",
    "addr:housenumber":"shop 12",
    "addr:postcode":"4350",
    "addr:street":"Cnr Spring",
    "iso:country":"AU",
    "sg:address":"Shop 12, Middle Ridge Shopping Centre, Cnr Spring",
    "sg:city":"Toowoomba",
    "sg:classifiers":[
        {
            "category":"Sports & Exercise",
            "subcategory":"Gym",
            "type":"Entertainment"
        }
    ],
    "sg:phone":"+61 7 4636 1100",
    "sg:postcode":"4350",
    "sg:province":"QLD",
    "sg:tags":[
        "personal",
        "trainer",
        "fitness"
    ],
    "wof:name":"Queensland Personal Training Studios",
    "wof:placetype":"venue"
},
  "geometry": {"coordinates":[151.96459999999999,-27.572927],"type":"Point"}
}