{
  "type": "Feature",
  "properties": {
    "addr:full":"1095A Mate St Albury North NSW 2640",
    "addr:housenumber":"1095a",
    "addr:postcode":"2640",
    "addr:street":"Mate St",
    "iso:country":"AU",
    "sg:address":"1095A Mate St",
    "sg:city":"Albury North",
    "sg:classifiers":[
        {
            "category":"Professional",
            "subcategory":"Employment Agencies",
            "type":"Services"
        }
    ],
    "sg:phone":"+61 2 6025 2444",
    "sg:postcode":"2640",
    "sg:province":"NSW",
    "sg:tags":[
        "provider",
        "internet"
    ],
    "wof:name":"Complete Computers",
    "wof:placetype":"venue"
},
  "geometry": {"coordinates":[146.93327331500001,-36.0532608032],"type":"Point"}
}