{
  "type": "Feature",
  "properties": {
    "addr:full":"51 Archer St Carlisle WA 6101",
    "addr:housenumber":"51",
    "addr:postcode":"6101",
    "addr:street":"Archer St",
    "iso:country":"AU",
    "sg:address":"51 Archer St",
    "sg:city":"Carlisle",
    "sg:classifiers":[
        {
            "category":"Restaurant",
            "type":"Food & Drink"
        }
    ],
    "sg:phone":"+61 8 9472 5300",
    "sg:postcode":"6101",
    "sg:province":"WA",
    "wof:name":"Bella Rosa Cafe",
    "wof:placetype":"venue"
},
  "geometry": {"coordinates":[115.90435791,-31.9867706299],"type":"Point"}
}