{
  "type": "Feature",
  "properties": {
    "addr:full":"2/ 225 Cabramatta Rd Cabramatta NSW 2166",
    "addr:housenumber":"/ 225",
    "addr:postcode":"2166",
    "addr:street":"Cabramatta Rd",
    "iso:country":"AU",
    "sg:address":"2/ 225 Cabramatta Rd",
    "sg:city":"Cabramatta",
    "sg:classifiers":[
        {
            "category":"Parking",
            "subcategory":"Garage",
            "type":"Transportation"
        }
    ],
    "sg:phone":"+61 2 9755 9937",
    "sg:postcode":"2166",
    "sg:province":"NSW",
    "sg:tags":[
        "radiographer"
    ],
    "wof:name":"Trans X-Ray Centre",
    "wof:placetype":"venue"
},
  "geometry": {"coordinates":[150.93585205100001,-33.8959960938],"type":"Point"}
}