{
  "type": "Feature",
  "properties": {
    "addr:full":"31- 33 Albert Rd Melbourne VIC 3000",
    "addr:housenumber":"33",
    "addr:postcode":"3000",
    "addr:street":"Albert Rd",
    "iso:country":"AU",
    "sg:address":"31- 33 Albert Rd",
    "sg:city":"Melbourne",
    "sg:classifiers":[
        {
            "category":"Personal",
            "type":"Services"
        }
    ],
    "sg:phone":"+61 3 9256 8311",
    "sg:postcode":"3000",
    "sg:province":"VIC",
    "sg:tags":[
        "counselling",
        "alcohol",
        "drug"
    ],
    "wof:name":"Albert Road Clinic",
    "wof:placetype":"venue"
},
  "geometry": {"coordinates":[144.97169494600001,-37.8346977234],"type":"Point"}
}