{
  "type": "Feature",
  "properties": {
    "iso:country":"AU",
    "sg:address":"29 Clarence Ave",
    "sg:city":"Bendigo",
    "sg:classifiers":[
        {
            "category":"Sports & Exercise",
            "subcategory":"Gym",
            "type":"Entertainment"
        }
    ],
    "sg:phone":"+61 414 496 529",
    "sg:postcode":"3550",
    "sg:province":"VIC",
    "sg:tags":[
        "health",
        "fitness"
    ],
    "wof:name":"Karen Fleming",
    "wof:placetype":"venue"
},
  "geometry": {"coordinates":[144.30096435600001,-36.7680282593],"type":"Point"}
}