{
  "type": "Feature",
  "properties": {
    "addr:full":"Burrows St Darkan WA 6392",
    "addr:postcode":"6392",
    "addr:street":"Burrows St",
    "iso:country":"AU",
    "sg:address":"Burrows St",
    "sg:city":"Darkan",
    "sg:classifiers":[
        {
            "category":"Education",
            "subcategory":"School",
            "type":"Public Place"
        }
    ],
    "sg:phone":"+61 8 9736 1387",
    "sg:postcode":"6392",
    "sg:province":"WA",
    "sg:tags":[
        "state",
        "except",
        "nsw"
    ],
    "wof:name":"Darkan Pre-Primary",
    "wof:placetype":"venue"
},
  "geometry": {"coordinates":[116.740730286,-33.3366012573],"type":"Point"}
}