{
  "type": "Feature",
  "properties": {
    "iso:country":"AU",
    "sg:address":"330 Warra Creek Rd",
    "sg:city":"Didcot",
    "sg:classifiers":[
        {
            "category":"Building & Trades",
            "subcategory":"Landscaping Services",
            "type":"Services"
        }
    ],
    "sg:phone":"+61 7 4161 6171",
    "sg:postcode":"4621",
    "sg:province":"QLD",
    "sg:tags":[
        "grazier"
    ],
    "wof:name":"Keen C R & D B",
    "wof:placetype":"venue"
},
  "geometry": {"coordinates":[151.862503,-25.479179],"type":"Point"}
}