{
  "type": "Feature",
  "properties": {
    "addr:full":"509 Station St Carrum VIC 3197",
    "addr:housenumber":"509",
    "addr:postcode":"3197",
    "addr:street":"Station St",
    "iso:country":"AU",
    "sg:address":"509 Station St",
    "sg:city":"Carrum",
    "sg:classifiers":[
        {
            "category":"Health Services",
            "subcategory":"Doctor",
            "type":"Services"
        }
    ],
    "sg:phone":"+61 3 9772 9325",
    "sg:postcode":"3197",
    "sg:province":"VIC",
    "sg:tags":[
        "medical",
        "practitioner"
    ],
    "wof:name":"Carrum Clinic",
    "wof:placetype":"venue"
},
  "geometry": {"coordinates":[145.12315368599999,-38.0756645203],"type":"Point"}
}