{
  "type": "Feature",
  "properties": {
    "iso:country":"AU",
    "sg:address":"St Martins Vlge",
    "sg:city":"Blacktown",
    "sg:classifiers":[
        {
            "category":"Food & Beverages",
            "subcategory":"Supermarket",
            "type":"Retail Goods"
        }
    ],
    "sg:phone":"+61 2 9831 6971",
    "sg:postcode":"2148",
    "sg:province":"NSW",
    "sg:tags":[
        "grocery",
        "store"
    ],
    "wof:name":"Franklins Stores",
    "wof:placetype":"venue"
},
  "geometry": {"coordinates":[150.90814209000001,-33.7725982666],"type":"Point"}
}