{
  "type": "Feature",
  "properties": {
    "iso:country":"AU",
    "sg:address":"1/ 5 Tavern St",
    "sg:city":"Kirwan",
    "sg:classifiers":[
        {
            "category":"Personal",
            "subcategory":"Beauty Salon",
            "type":"Services"
        }
    ],
    "sg:phone":"+61 7 4755 1239",
    "sg:postcode":"4817",
    "sg:province":"QLD",
    "sg:tags":[
        "hairdresser"
    ],
    "wof:name":"Shaeta Hair",
    "wof:placetype":"venue"
},
  "geometry": {"coordinates":[146.734833,-19.302206],"type":"Point"}
}