{
  "type": "Feature",
  "properties": {
    "iso:country":"AU",
    "sg:address":"48 Governor Macquarie Drv",
    "sg:city":"Chipping Norton",
    "sg:classifiers":[
        {
            "category":"Personal",
            "subcategory":"Beauty Salon",
            "type":"Services"
        }
    ],
    "sg:phone":"+61 2 9755 9209",
    "sg:postcode":"2170",
    "sg:province":"NSW",
    "sg:tags":[
        "hairdresser"
    ],
    "wof:name":"Naughty Hair",
    "wof:placetype":"venue"
},
  "geometry": {"coordinates":[150.96200561500001,-33.9239616394],"type":"Point"}
}