{
  "type": "Feature",
  "properties": {
    "addr:full":"9 Edinburgh St Oakleigh South VIC 3167",
    "addr:housenumber":"9",
    "addr:postcode":"3167",
    "addr:street":"Edinburgh St",
    "iso:country":"AU",
    "sg:address":"9 Edinburgh St",
    "sg:city":"Oakleigh South",
    "sg:classifiers":[
        {
            "category":"Building & Trades",
            "subcategory":"Construction",
            "type":"Services"
        }
    ],
    "sg:phone":"+61 3 9543 7119",
    "sg:postcode":"3167",
    "sg:province":"VIC",
    "sg:tags":[
        "stonework",
        "stone",
        "mason"
    ],
    "wof:name":"Bosoar Stone",
    "wof:placetype":"venue"
},
  "geometry": {"coordinates":[145.11000060999999,-37.9150123596],"type":"Point"}
}