{
  "type": "Feature",
  "properties": {
    "addr:full":"2 Moon St Moolap VIC 3221",
    "addr:housenumber":"2",
    "addr:postcode":"3221",
    "addr:street":"Moon St",
    "iso:country":"AU",
    "sg:address":"2 Moon St",
    "sg:city":"Moolap",
    "sg:classifiers":[
        {
            "category":"Professional",
            "subcategory":"Engineering",
            "type":"Services"
        }
    ],
    "sg:phone":"+61 3 5248 2440",
    "sg:postcode":"3221",
    "sg:province":"VIC",
    "sg:tags":[
        "engineer"
    ],
    "wof:name":"Atex Steel",
    "wof:placetype":"venue"
},
  "geometry": {"coordinates":[144.413757,-38.164467],"type":"Point"}
}