{
  "type": "Feature",
  "properties": {
    "iso:country":"AU",
    "sg:address":"Lane St",
    "sg:city":"Wentworthville",
    "sg:classifiers":[
        {
            "category":"Retail",
            "subcategory":"Event Space",
            "type":"Services"
        }
    ],
    "sg:phone":"+61 2 9840 9900",
    "sg:postcode":"2145",
    "sg:province":"NSW",
    "sg:tags":[
        "venue",
        "reception",
        "wedding"
    ],
    "wof:name":"Redgum Function Centre",
    "wof:placetype":"venue"
},
  "geometry": {"coordinates":[150.97323608400001,-33.8085289001],"type":"Point"}
}