{
  "type": "Feature",
  "properties": {
    "iso:country":"AU",
    "sg:address":"25 Urawa St",
    "sg:city":"Geraldton",
    "sg:classifiers":[
        {
            "category":"Building & Trades",
            "subcategory":"Cleaning & Sanitation",
            "type":"Services"
        }
    ],
    "sg:phone":"+61 8 9964 1137",
    "sg:postcode":"6530",
    "sg:province":"WA",
    "sg:tags":[
        "industrial",
        "commercial",
        "contractor"
    ],
    "wof:name":"ChemDry Power Carpet and Upholstery Cleaning",
    "wof:placetype":"venue"
},
  "geometry": {"coordinates":[114.62644195599999,-28.8069210052],"type":"Point"}
}