{
  "type": "Feature",
  "properties": {
    "addr:full":"245 Keilor Rd Essendon North VIC 3041",
    "addr:housenumber":"245",
    "addr:postcode":"3041",
    "addr:street":"Keilor Rd",
    "iso:country":"AU",
    "sg:address":"245 Keilor Rd",
    "sg:city":"Essendon North",
    "sg:classifiers":[
        {
            "category":"Health Services",
            "subcategory":"Health Practitioner",
            "type":"Services"
        }
    ],
    "sg:phone":"+61 3 9379 4199",
    "sg:postcode":"3041",
    "sg:province":"VIC",
    "sg:tags":[
        "osteopath"
    ],
    "wof:name":"Essendon Osteopathic Health Care",
    "wof:placetype":"venue"
},
  "geometry": {"coordinates":[144.897140503,-37.7393264771],"type":"Point"}
}