{
  "type": "Feature",
  "properties": {
    "iso:country":"AU",
    "sg:address":"1656 South Gippsland Hwy",
    "sg:city":"Cranbourne",
    "sg:classifiers":[
        {
            "category":"Professional",
            "subcategory":"Art Services",
            "type":"Services"
        }
    ],
    "sg:phone":"+61 3 5996 1232",
    "sg:postcode":"3977",
    "sg:province":"VIC",
    "sg:tags":[
        "artist"
    ],
    "wof:name":"Trembath E A",
    "wof:placetype":"venue"
},
  "geometry": {"coordinates":[145.29591369600001,-38.1331939697],"type":"Point"}
}