{
  "type": "Feature",
  "properties": {
    "iso:country":"AU",
    "sg:address":"Cnr Newcastle Drive & Hulberts Rd",
    "sg:city":"Toormina",
    "sg:classifiers":[
        {
            "category":"Home & Garden",
            "subcategory":"Garden Supply",
            "type":"Retail Goods"
        }
    ],
    "sg:phone":"+61 2 6653 3055",
    "sg:postcode":"2452",
    "sg:province":"NSW",
    "sg:tags":[
        "equipment"
    ],
    "wof:name":"Toormina Landscape Centre",
    "wof:placetype":"venue"
},
  "geometry": {"coordinates":[153.091721,-30.362101],"type":"Point"}
}