{
  "type": "Feature",
  "properties": {
    "addr:full":"120 Johnston St Fitzroy VIC 3065",
    "addr:housenumber":"120",
    "addr:postcode":"3065",
    "addr:street":"Johnston St",
    "iso:country":"AU",
    "sg:address":"120 Johnston St",
    "sg:city":"Fitzroy",
    "sg:classifiers":[
        {
            "category":"Bars & Pubs",
            "subcategory":"Nightclub",
            "type":"Food & Drink"
        }
    ],
    "sg:phone":"+61 3 9416 1220",
    "sg:postcode":"3065",
    "sg:province":"VIC",
    "sg:tags":[
        "discotheque"
    ],
    "wof:name":"One Twenty Bar",
    "wof:placetype":"venue"
},
  "geometry": {"coordinates":[144.978607178,-37.7984657288],"type":"Point"}
}