{
  "type": "Feature",
  "properties": {
    "iso:country":"AU",
    "sg:address":"15 Acanthus Rd",
    "sg:city":"Willetton",
    "sg:classifiers":[
        {
            "category":"Professional",
            "subcategory":"Business Services",
            "type":"Services"
        }
    ],
    "sg:phone":"+61 418 930 143",
    "sg:postcode":"6155",
    "sg:province":"WA",
    "sg:tags":[
        "drafting"
    ],
    "wof:name":"M C T Piping & Mechanical Drafting",
    "wof:placetype":"venue"
},
  "geometry": {"coordinates":[115.875,-32.043522],"type":"Point"}
}