{
  "type": "Feature",
  "properties": {
    "addr:full":"17 Grenville Rd Gooseberry Hill WA 6076",
    "addr:housenumber":"17",
    "addr:postcode":"6076",
    "addr:street":"Grenville Rd",
    "iso:country":"AU",
    "sg:address":"17 Grenville Rd",
    "sg:city":"Gooseberry Hill",
    "sg:classifiers":[
        {
            "category":"Professional",
            "subcategory":"Art Services",
            "type":"Services"
        }
    ],
    "sg:phone":"+61 8 9454 8930",
    "sg:postcode":"6076",
    "sg:province":"WA",
    "sg:tags":[
        "interior",
        "designer"
    ],
    "wof:name":"Adele Silcox Interior Design",
    "wof:placetype":"venue"
},
  "geometry": {"coordinates":[116.036872864,-31.9533786774],"type":"Point"}
}