{
  "type": "Feature",
  "properties": {
    "addr:full":"618 Somerville Rd Sunshine VIC 3020",
    "addr:housenumber":"618",
    "addr:postcode":"3020",
    "addr:street":"Somerville Rd",
    "iso:country":"AU",
    "sg:address":"618 Somerville Rd",
    "sg:city":"Sunshine",
    "sg:classifiers":[
        {
            "category":"Wholesale",
            "subcategory":"Machinery & Supplies",
            "type":"Manufacturing & Wholesale Goods"
        }
    ],
    "sg:phone":"+61 3 9300 9600",
    "sg:postcode":"3020",
    "sg:province":"VIC",
    "sg:tags":[
        "engineer"
    ],
    "wof:name":"Thomas Warburton Pty Ltd",
    "wof:placetype":"venue"
},
  "geometry": {"coordinates":[144.81959499999999,-37.805618],"type":"Point"}
}