{
  "type": "Feature",
  "properties": {
    "iso:country":"AU",
    "sg:address":"7 King Richard Drv",
    "sg:city":"Shepparton",
    "sg:classifiers":[
        {
            "category":"Health Services",
            "subcategory":"Doctor",
            "type":"Services"
        }
    ],
    "sg:phone":"+61 3 5822 1568",
    "sg:postcode":"3630",
    "sg:province":"VIC",
    "sg:tags":[
        "nurse",
        "nursing"
    ],
    "wof:name":"Goulburn Valley Nurse Call Pty Ltd",
    "wof:placetype":"venue"
},
  "geometry": {"coordinates":[145.41679382300001,-36.3614578247],"type":"Point"}
}