{
  "type": "Feature",
  "properties": {
    "addr:full":"412 Ferntree Gully Rd Notting Hill VIC 3168",
    "addr:housenumber":"412",
    "addr:postcode":"3168",
    "addr:street":"Ferntree Gully Rd",
    "iso:country":"AU",
    "sg:address":"412 Ferntree Gully Rd",
    "sg:city":"Notting Hill",
    "sg:classifiers":[
        {
            "category":"Shopping",
            "type":"Retail Goods"
        }
    ],
    "sg:phone":"+61 3 9560 4755",
    "sg:postcode":"3168",
    "sg:province":"VIC",
    "sg:tags":[
        "equipment",
        "safety",
        "accessory"
    ],
    "wof:name":"Active Safety Supplies Pty Ltd",
    "wof:placetype":"venue"
},
  "geometry": {"coordinates":[145.14369201700001,-37.901424408],"type":"Point"}
}