{
  "type": "Feature",
  "properties": {
    "addr:full":"Coles Level 2, Margaret St Entrance Grand Central Shopng Cntr Toowoomba QLD 4350",
    "addr:housenumber":"2",
    "addr:postcode":"4350",
    "addr:street":"Margaret St",
    "iso:country":"AU",
    "sg:address":"Coles Level 2, Margaret St Entrance Grand Central Shopng Cntr",
    "sg:city":"Toowoomba",
    "sg:classifiers":[
        {
            "category":"Personal",
            "subcategory":"Hair Removal",
            "type":"Services"
        }
    ],
    "sg:phone":"+61 7 4638 3821",
    "sg:postcode":"4350",
    "sg:province":"QLD",
    "wof:name":"Skin Sensations",
    "wof:placetype":"venue"
},
  "geometry": {"coordinates":[151.95579499999999,-27.48114],"type":"Point"}
}