{
  "type": "Feature",
  "properties": {
    "addr:full":"Suite 2 471 Golden Four Drv Tugun QLD 4224",
    "addr:housenumber":"471",
    "addr:postcode":"4224",
    "addr:street":"Golden Four Drv",
    "iso:country":"AU",
    "sg:address":"Suite 2 471 Golden Four Drv",
    "sg:city":"Tugun",
    "sg:classifiers":[
        {
            "category":"Professional",
            "subcategory":"Art Services",
            "type":"Services"
        }
    ],
    "sg:phone":"+61 7 5534 7477",
    "sg:postcode":"4224",
    "sg:province":"QLD",
    "sg:tags":[
        "interior",
        "designer"
    ],
    "wof:name":"Pru Grant Interior Design Consultants",
    "wof:placetype":"venue"
},
  "geometry": {"coordinates":[153.49343872099999,-28.1423339844],"type":"Point"}
}