{
  "type": "Feature",
  "properties": {
    "iso:country":"AU",
    "sg:address":"Units 4 & 5/ 411 West Botany St",
    "sg:city":"Rockdale",
    "sg:classifiers":[
        {
            "category":"Professional",
            "subcategory":"Art Services",
            "type":"Services"
        }
    ],
    "sg:phone":"+61 2 9567 2355",
    "sg:postcode":"2216",
    "sg:province":"NSW",
    "sg:tags":[
        "picture",
        "frame",
        "framing"
    ],
    "wof:name":"Visual Art Reproductions",
    "wof:placetype":"venue"
},
  "geometry": {"coordinates":[151.14595,-33.958775],"type":"Point"}
}