{
  "type": "Feature",
  "properties": {
    "addr:full":"129 Cornie Ave Penrith NSW 2750",
    "addr:housenumber":"129",
    "addr:postcode":"2750",
    "addr:street":"Cornie Ave",
    "iso:country":"AU",
    "sg:address":"129 Cornie Ave",
    "sg:city":"Penrith",
    "sg:classifiers":[
        {
            "category":"Home & Garden",
            "subcategory":"Building Materials",
            "type":"Retail Goods"
        }
    ],
    "sg:phone":"+61 414 718 228",
    "sg:postcode":"2750",
    "sg:province":"NSW",
    "sg:tags":[
        "supply"
    ],
    "wof:name":"Trademaster",
    "wof:placetype":"venue"
},
  "geometry": {"coordinates":[150.93362426799999,-33.793346405],"type":"Point"}
}