{
  "type": "Feature",
  "properties": {
    "addr:full":"55 Carbeen Ave St Ives NSW 2075",
    "addr:housenumber":"55",
    "addr:postcode":"2075",
    "addr:street":"Carbeen Ave",
    "iso:country":"AU",
    "sg:address":"55 Carbeen Ave St",
    "sg:city":"Ives",
    "sg:classifiers":[
        {
            "category":"Health Services",
            "subcategory":"Health Practitioner",
            "type":"Services"
        }
    ],
    "sg:phone":"+61 2 9440 0024",
    "sg:postcode":"2075",
    "sg:province":"NSW",
    "sg:tags":[
        "psychologist"
    ],
    "wof:name":"Needs Based Psychological & Training Services",
    "wof:placetype":"venue"
},
  "geometry": {"coordinates":[151.15672302199999,-33.7205162048],"type":"Point"}
}