{
  "type": "Feature",
  "properties": {
    "addr:full":"Unit 6, 153 Beauchamp Rd Matraville NSW 2036",
    "addr:housenumber":"153",
    "addr:postcode":"2036",
    "addr:street":"Beauchamp Rd",
    "iso:country":"AU",
    "sg:address":"Unit 6, 153 Beauchamp Rd",
    "sg:city":"Matraville",
    "sg:classifiers":[
        {
            "category":"Wholesale",
            "subcategory":"Construction Materials",
            "type":"Manufacturing & Wholesale Goods"
        }
    ],
    "sg:phone":"+61 2 9666 3922",
    "sg:postcode":"2036",
    "sg:province":"NSW",
    "sg:tags":[
        "lift"
    ],
    "wof:name":"Liftronic Pty Limited",
    "wof:placetype":"venue"
},
  "geometry": {"coordinates":[151.22674560600001,-33.9563560486],"type":"Point"}
}