{
  "type": "Feature",
  "properties": {
    "addr:full":"84 Bells Line Of Rd North Richmond NSW 2754",
    "addr:housenumber":"84",
    "addr:postcode":"2754",
    "addr:street":"Bells Line Of Rd",
    "iso:country":"AU",
    "sg:address":"84 Bells Line Of Rd",
    "sg:city":"North Richmond",
    "sg:classifiers":[
        {
            "category":"Retail",
            "subcategory":"Repair Shop",
            "type":"Services"
        }
    ],
    "sg:phone":"+61 2 4571 1964",
    "sg:postcode":"2754",
    "sg:province":"NSW",
    "sg:tags":[
        "maintenance",
        "pool",
        "swimming"
    ],
    "wof:name":"Aqualab Pool Care Centre",
    "wof:placetype":"venue"
},
  "geometry": {"coordinates":[150.71777343799999,-33.5778236389],"type":"Point"}
}