{
  "type": "Feature",
  "properties": {
    "iso:country":"AU",
    "sg:address":"7-21 Egan Drv",
    "sg:city":"Bulleen",
    "sg:classifiers":[
        {
            "category":"Education",
            "subcategory":"School",
            "type":"Public Place"
        }
    ],
    "sg:phone":"+61 3 9850 1216",
    "sg:postcode":"3105",
    "sg:province":"VIC",
    "sg:tags":[
        "co-educational"
    ],
    "wof:name":"St Clement of Rome Primary",
    "wof:placetype":"venue"
},
  "geometry": {"coordinates":[145.09091186500001,-37.7677001953],"type":"Point"}
}