{
  "type": "Feature",
  "properties": {
    "iso:country":"AU",
    "sg:address":"5 Smart Pl",
    "sg:city":"Evatt",
    "sg:classifiers":[
        {
            "category":"Retail",
            "subcategory":"Auto Repair",
            "type":"Services"
        }
    ],
    "sg:phone":"+61 410 582 734",
    "sg:postcode":"2617",
    "sg:province":"ACT",
    "sg:tags":[
        "repairer",
        "motor",
        "engineer"
    ],
    "wof:name":"Ray Shepherd Automotive",
    "wof:placetype":"venue"
},
  "geometry": {"coordinates":[149.07154846200001,-35.2020225525],"type":"Point"}
}