{
  "type": "Feature",
  "properties": {
    "iso:country":"AU",
    "sg:address":"7 Poplar Rd",
    "sg:city":"Risdon Vale",
    "sg:classifiers":[
        {
            "category":"Building & Trades",
            "subcategory":"Plumbing",
            "type":"Services"
        }
    ],
    "sg:phone":"+61 3 6243 6570",
    "sg:postcode":"7016",
    "sg:province":"TAS",
    "sg:tags":[
        "plumber",
        "gasfitters"
    ],
    "wof:name":"Long D P",
    "wof:placetype":"venue"
},
  "geometry": {"coordinates":[147.359771728,-42.8121490479],"type":"Point"}
}