{
  "type": "Feature",
  "properties": {
    "iso:country":"AU",
    "sg:address":"Russell St",
    "sg:city":"Macarthur",
    "sg:classifiers":[
        {
            "category":"Education",
            "subcategory":"School",
            "type":"Public Place"
        }
    ],
    "sg:phone":"+61 3 5576 1245",
    "sg:postcode":"3286",
    "sg:province":"VIC",
    "sg:tags":[
        "state",
        "except",
        "nsw"
    ],
    "wof:name":"Macarthur Primary School",
    "wof:placetype":"venue"
},
  "geometry": {"coordinates":[142.00372314399999,-38.0341835022],"type":"Point"}
}