{
  "type": "Feature",
  "properties": {
    "addr:full":"14 Hughes St Berri SA 5343",
    "addr:housenumber":"14",
    "addr:postcode":"5343",
    "addr:street":"Hughes St",
    "iso:country":"AU",
    "sg:address":"14 Hughes St",
    "sg:city":"Berri",
    "sg:classifiers":[
        {
            "category":"Government",
            "subcategory":"Fire Station",
            "type":"Public Place"
        }
    ],
    "sg:phone":"+61 8 8582 2853",
    "sg:postcode":"5343",
    "sg:province":"SA",
    "sg:tags":[
        "spring",
        "shock",
        "absorbers",
        "suspension"
    ],
    "wof:name":"Ken's Exhaust Systems - Berri",
    "wof:placetype":"venue"
},
  "geometry": {"coordinates":[140.60124206500001,-34.2713279724],"type":"Point"}
}