{
  "type": "Feature",
  "properties": {
    "iso:country":"AU",
    "sg:address":"23 Main St",
    "sg:city":"Upwey",
    "sg:classifiers":[
        {
            "category":"Personal",
            "subcategory":"Beauty Salon",
            "type":"Services"
        }
    ],
    "sg:phone":"+61 3 9754 5361",
    "sg:postcode":"3158",
    "sg:province":"VIC",
    "sg:tags":[
        "hairdresser"
    ],
    "wof:name":"Shear Expression Hair Care Salon",
    "wof:placetype":"venue"
},
  "geometry": {"coordinates":[145.330245972,-37.9031257629],"type":"Point"}
}