{
  "type": "Feature",
  "properties": {
    "iso:country":"AU",
    "sg:address":"127 Watsonia Rd",
    "sg:city":"Watsonia",
    "sg:classifiers":[
        {
            "category":"Health Services",
            "subcategory":"Doctor",
            "type":"Services"
        }
    ],
    "sg:phone":"+61 3 9432 1677",
    "sg:postcode":"3087",
    "sg:province":"VIC",
    "sg:tags":[
        "medical",
        "practitioner"
    ],
    "wof:name":"Burns Kenneth",
    "wof:placetype":"venue"
},
  "geometry": {"coordinates":[145.08320617699999,-37.7068901062],"type":"Point"}
}