{
  "type": "Feature",
  "properties": {
    "addr:full":"12 Wharf St Woody Point QLD 4019",
    "addr:housenumber":"12",
    "addr:postcode":"4019",
    "addr:street":"Wharf St",
    "iso:country":"AU",
    "sg:address":"12 Wharf St",
    "sg:city":"Woody Point",
    "sg:classifiers":[
        {
            "category":"Professional",
            "subcategory":"Art Services",
            "type":"Services"
        }
    ],
    "sg:phone":"+61 7 3885 4458",
    "sg:postcode":"4019",
    "sg:province":"QLD",
    "sg:tags":[
        "decorator",
        "painter"
    ],
    "wof:name":"Rods Repaints",
    "wof:placetype":"venue"
},
  "geometry": {"coordinates":[153.09913635300001,-27.254655838],"type":"Point"}
}