{
  "type": "Feature",
  "properties": {
    "addr:full":"39 Park St Glenbrook NSW 2773",
    "addr:housenumber":"39",
    "addr:postcode":"2773",
    "addr:street":"Park St",
    "iso:country":"AU",
    "sg:address":"39 Park St",
    "sg:city":"Glenbrook",
    "sg:classifiers":[
        {
            "category":"Travel",
            "subcategory":"Travel Agent",
            "type":"Entertainment"
        }
    ],
    "sg:phone":"+61 2 4739 6599",
    "sg:postcode":"2773",
    "sg:province":"NSW",
    "sg:tags":[
        "consultant"
    ],
    "wof:name":"Jetset Blue Mountains",
    "wof:placetype":"venue"
},
  "geometry": {"coordinates":[150.622802734,-33.7668838501],"type":"Point"}
}