{
  "type": "Feature",
  "properties": {
    "addr:full":"PO Box 629 Narrabri NSW 2390",
    "addr:postcode":"2390",
    "iso:country":"AU",
    "sg:address":"PO Box 629",
    "sg:city":"Narrabri",
    "sg:classifiers":[
        {
            "category":"Commercial Area",
            "type":"Public Place"
        }
    ],
    "sg:phone":"+61 428 652 023",
    "sg:postcode":"2390",
    "sg:province":"NSW",
    "sg:tags":[
        "heavy",
        "carrier"
    ],
    "wof:name":"Bourke Excavations Pty Ltd",
    "wof:placetype":"venue"
},
  "geometry": {"coordinates":[149.766845703,-30.3389701843],"type":"Point"}
}