{
  "type": "Feature",
  "properties": {
    "addr:full":"Level 1, 1451 Pittwater Rd North Narrabeen NSW 2101",
    "addr:housenumber":"1451",
    "addr:postcode":"2101",
    "addr:street":"Pittwater Rd",
    "iso:country":"AU",
    "sg:address":"Level 1, 1451 Pittwater Rd",
    "sg:city":"North Narrabeen",
    "sg:classifiers":[
        {
            "category":"Health Services",
            "subcategory":"Dentist",
            "type":"Services"
        }
    ],
    "sg:phone":"+61 2 9913 7453",
    "sg:postcode":"2101",
    "sg:province":"NSW",
    "wof:name":"United Dental",
    "wof:placetype":"venue"
},
  "geometry": {"coordinates":[151.29707300000001,-33.712528],"type":"Point"}
}