{
  "type": "Feature",
  "properties": {
    "addr:full":"1374 Centre Rd Clayton VIC 3168",
    "addr:housenumber":"1374",
    "addr:postcode":"3168",
    "addr:street":"Centre Rd",
    "iso:country":"AU",
    "sg:address":"1374 Centre Rd",
    "sg:city":"Clayton",
    "sg:classifiers":[
        {
            "category":"Organizations",
            "subcategory":"Community Association",
            "type":"Services"
        }
    ],
    "sg:phone":"+61 3 9239 1400",
    "sg:postcode":"3168",
    "sg:province":"VIC",
    "sg:tags":[
        "organisation",
        "family",
        "welfare"
    ],
    "wof:name":"Berry Street Victoria",
    "wof:placetype":"venue"
},
  "geometry": {"coordinates":[145.122024536,-37.9290084839],"type":"Point"}
}