{
  "type": "Feature",
  "properties": {
    "addr:full":"12 Pirie St Adelaide SA 5000",
    "addr:housenumber":"12",
    "addr:postcode":"5000",
    "addr:street":"Pirie St",
    "iso:country":"AU",
    "sg:address":"12 Pirie St",
    "sg:city":"Adelaide",
    "sg:classifiers":[
        {
            "category":"Banks & Credit Unions",
            "subcategory":"Investment Brokerage",
            "type":"Services"
        }
    ],
    "sg:phone":"+61 8 8217 3900",
    "sg:postcode":"5000",
    "sg:province":"SA",
    "sg:tags":[
        "share",
        "broker",
        "stock"
    ],
    "wof:name":"Taylor James C",
    "wof:placetype":"venue"
},
  "geometry": {"coordinates":[138.60008239699999,-34.9256324768],"type":"Point"}
}