{
  "type": "Feature",
  "properties": {
    "addr:full":"Shop 2, 282-290 Forest Rd Hurstville NSW 2220",
    "addr:housenumber":"shop 2",
    "addr:postcode":"282-290;2220",
    "addr:street":"Forest Rd",
    "iso:country":"AU",
    "sg:address":"Shop 2, 282-290 Forest Rd",
    "sg:city":"Hurstville",
    "sg:classifiers":[
        {
            "category":"Shopping",
            "subcategory":"Clothing, Apparel, & Fashions",
            "type":"Retail Goods"
        }
    ],
    "sg:phone":"+61 2 9585 2767",
    "sg:postcode":"2220",
    "sg:province":"NSW",
    "sg:tags":[
        "lady",
        "wear"
    ],
    "wof:name":"Giordano (Australia) Pty Ltd",
    "wof:placetype":"venue"
},
  "geometry": {"coordinates":[151.10287475600001,-33.9667434692],"type":"Point"}
}