{
  "type": "Feature",
  "properties": {
    "iso:country":"AU",
    "sg:address":"Cnr Blair Street and Forrest Ave",
    "sg:city":"Bunbury",
    "sg:classifiers":[
        {
            "category":"Government",
            "subcategory":"Court House",
            "type":"Public Place"
        }
    ],
    "sg:phone":"+61 409 778 338",
    "sg:postcode":"6230",
    "sg:province":"WA",
    "sg:tags":[
        "personal",
        "marriage",
        "family",
        "counselling"
    ],
    "wof:name":"Gibson Therapy Centre",
    "wof:placetype":"venue"
},
  "geometry": {"coordinates":[115.642151,-33.352398],"type":"Point"}
}