{
  "type": "Feature",
  "properties": {
    "addr:full":"69 Cowper St Wallsend NSW 2287",
    "addr:housenumber":"69",
    "addr:postcode":"2287",
    "addr:street":"Cowper St",
    "iso:country":"AU",
    "sg:address":"69 Cowper St",
    "sg:city":"Wallsend",
    "sg:classifiers":[
        {
            "category":"Professional",
            "subcategory":"Secretarial Services",
            "type":"Services"
        }
    ],
    "sg:phone":"+61 2 4965 6690",
    "sg:postcode":"2287",
    "sg:province":"NSW",
    "sg:tags":[
        "typing"
    ],
    "wof:name":"HTK Clerical & Bookkeeping Services",
    "wof:placetype":"venue"
},
  "geometry": {"coordinates":[151.67060852,-32.9027709961],"type":"Point"}
}