{
  "type": "Feature",
  "properties": {
    "addr:full":"Westfield Shoppingtown Gympie & Hamiltons Rds Chermside QLD 4032",
    "addr:postcode":"qld 4032",
    "iso:country":"AU",
    "sg:address":"Westfield Shoppingtown Gympie & Hamiltons Rds",
    "sg:city":"Chermside",
    "sg:classifiers":[
        {
            "category":"Shopping",
            "subcategory":"Beauty & Cosmetics",
            "type":"Retail Goods"
        }
    ],
    "sg:phone":"+61 7 3350 4791",
    "sg:postcode":"4032",
    "sg:province":"QLD",
    "wof:name":"Body Shop The",
    "wof:placetype":"venue"
},
  "geometry": {"coordinates":[153.031113,-27.386387],"type":"Point"}
}