{
  "type": "Feature",
  "properties": {
    "addr:full":"1- 5 Rothray Ave Sunshine North VIC 3020",
    "addr:housenumber":"5",
    "addr:postcode":"3020",
    "addr:street":"Rothray Ave",
    "iso:country":"AU",
    "sg:address":"1- 5 Rothray Ave",
    "sg:city":"Sunshine North",
    "sg:phone":"+61 3 9312 2322",
    "sg:postcode":"3020",
    "sg:province":"VIC",
    "sg:website":"http://www.expertglass.com.au",
    "wof:name":"Expert Glass Co. Pty Ltd",
    "wof:placetype":"venue"
},
  "geometry": {"coordinates":[144.83216899999999,-37.759968],"type":"Point"}
}