{
  "type": "Feature",
  "properties": {
    "addr:full":"1050 Hay St West Perth WA 6005",
    "addr:housenumber":"1050",
    "addr:postcode":"6005",
    "addr:street":"Hay St",
    "iso:country":"AU",
    "sg:address":"1050 Hay St",
    "sg:city":"West Perth",
    "sg:classifiers":[
        {
            "category":"Insurance",
            "subcategory":"Hazard Insurance",
            "type":"Services"
        }
    ],
    "sg:phone":"+61 8 9322 1722",
    "sg:postcode":"6005",
    "sg:province":"WA",
    "sg:tags":[
        "fire",
        "accident",
        "marine"
    ],
    "wof:name":"CHU",
    "wof:placetype":"venue"
},
  "geometry": {"coordinates":[115.848258972,-31.9505653381],"type":"Point"}
}