{
  "type": "Feature",
  "properties": {
    "addr:full":"43-47 Northgate Drv Thomastown VIC 3074",
    "addr:housenumber":"43-47",
    "addr:postcode":"3074",
    "addr:street":"Northgate Drv",
    "iso:country":"AU",
    "sg:address":"43-47 Northgate Drv",
    "sg:city":"Thomastown",
    "sg:classifiers":[
        {
            "category":"Utilities",
            "type":"Services"
        }
    ],
    "sg:phone":"+61 3 9465 0099",
    "sg:postcode":"3074",
    "sg:province":"VIC",
    "sg:tags":[
        "refrigeration",
        "industrial",
        "commercial",
        "retail"
    ],
    "wof:name":"Tri Tech Refrigeration",
    "wof:placetype":"venue"
},
  "geometry": {"coordinates":[145.03968810999999,-37.6903800964],"type":"Point"}
}