{
  "type": "Feature",
  "properties": {
    "addr:full":"9 Murray St Gawler SA 5118",
    "addr:housenumber":"9",
    "addr:postcode":"5118",
    "addr:street":"Murray St",
    "iso:country":"AU",
    "sg:address":"9 Murray St",
    "sg:city":"Gawler",
    "sg:classifiers":[
        {
            "category":"Fast Food",
            "type":"Food & Drink"
        }
    ],
    "sg:phone":"+61 8 8523 1551",
    "sg:postcode":"5118",
    "sg:province":"SA",
    "sg:tags":[
        "away",
        "take"
    ],
    "wof:name":"Bamboo Hut Bistro",
    "wof:placetype":"venue"
},
  "geometry": {"coordinates":[138.74923699999999,-34.596748],"type":"Point"}
}