{
  "type": "Feature",
  "properties": {
    "addr:full":"10 Fletcher St Essendon VIC 3040",
    "addr:housenumber":"10",
    "addr:postcode":"3040",
    "addr:street":"Fletcher St",
    "iso:country":"AU",
    "sg:address":"10 Fletcher St",
    "sg:city":"Essendon",
    "sg:classifiers":[
        {
            "category":"Health Services",
            "subcategory":"Nursing And Care Facility",
            "type":"Services"
        }
    ],
    "sg:phone":"+61 3 9375 2933",
    "sg:postcode":"3040",
    "sg:province":"VIC",
    "sg:tags":[
        "home"
    ],
    "wof:name":"Essendon Private Nursing Home Pty Ltd",
    "wof:placetype":"venue"
},
  "geometry": {"coordinates":[144.92489624000001,-37.7555847168],"type":"Point"}
}