{
  "type": "Feature",
  "properties": {
    "addr:full":"14 Havelock St Wodonga VIC 3690",
    "addr:housenumber":"14",
    "addr:postcode":"3690",
    "addr:street":"Havelock St",
    "iso:country":"AU",
    "sg:address":"14 Havelock St",
    "sg:city":"Wodonga",
    "sg:classifiers":[
        {
            "category":"Professional",
            "subcategory":"Accounting & Tax Preparation",
            "type":"Services"
        }
    ],
    "sg:phone":"+61 2 6024 6775",
    "sg:postcode":"3690",
    "sg:province":"VIC",
    "sg:tags":[
        "pregnancy",
        "related",
        "counselling"
    ],
    "wof:name":"Pregnancy Support Albury Wodonga Inc",
    "wof:placetype":"venue"
},
  "geometry": {"coordinates":[146.890426636,-36.123840332],"type":"Point"}
}