{
  "type": "Feature",
  "properties": {
    "iso:country":"AU",
    "sg:address":"15 Davies Ave",
    "sg:city":"Sunshine North",
    "sg:classifiers":[
        {
            "category":"Manufacturing",
            "subcategory":"Furniture",
            "type":"Manufacturing & Wholesale Goods"
        }
    ],
    "sg:phone":"+61 3 9356 4260",
    "sg:postcode":"3020",
    "sg:province":"VIC",
    "sg:tags":[
        "builder",
        "designer",
        "custom"
    ],
    "wof:name":"Pine Corp Pty Ltd",
    "wof:placetype":"venue"
},
  "geometry": {"coordinates":[144.835464,-37.756538],"type":"Point"}
}