{
  "type": "Feature",
  "properties": {
    "addr:full":"Suite 6A/ 247 King St Mascot NSW 2020",
    "addr:housenumber":"6a / 247",
    "addr:postcode":"2020",
    "addr:street":"King St",
    "iso:country":"AU",
    "sg:address":"Suite 6A/ 247 King St",
    "sg:city":"Mascot",
    "sg:classifiers":[
        {
            "category":"Professional",
            "subcategory":"Employment Agencies",
            "type":"Services"
        }
    ],
    "sg:phone":"+61 2 9669 5544",
    "sg:postcode":"2020",
    "sg:province":"NSW",
    "sg:tags":[
        "broker",
        "custom"
    ],
    "wof:name":"Interforwarding International Pty Ltd",
    "wof:placetype":"venue"
},
  "geometry": {"coordinates":[151.18783569300001,-33.9285125732],"type":"Point"}
}