{
  "type": "Feature",
  "properties": {
    "addr:full":"Unit 4/ 1 Welch St Underwood QLD 4119",
    "addr:housenumber":"1",
    "addr:postcode":"4119",
    "addr:street":"Welch St",
    "iso:country":"AU",
    "sg:address":"Unit 4/ 1 Welch St",
    "sg:city":"Underwood",
    "sg:classifiers":[
        {
            "category":"Building & Trades",
            "subcategory":"Landscaping Services",
            "type":"Services"
        }
    ],
    "sg:phone":"+61 7 3841 8211",
    "sg:postcode":"4119",
    "sg:province":"QLD",
    "sg:tags":[
        "inspection"
    ],
    "wof:name":"Matrix Certification Services",
    "wof:placetype":"venue"
},
  "geometry": {"coordinates":[153.116577148,-27.6108951569],"type":"Point"}
}