{
  "type": "Feature",
  "properties": {
    "addr:full":"6 Wedge Crt Glen Waverley VIC 3150",
    "addr:housenumber":"6",
    "addr:postcode":"3150",
    "addr:street":"Wedge Crt",
    "iso:country":"AU",
    "sg:address":"6 Wedge Crt",
    "sg:city":"Glen Waverley",
    "sg:classifiers":[
        {
            "category":"Autos & Motor Vehicles",
            "subcategory":"Auto Supplies",
            "type":"Retail Goods"
        }
    ],
    "sg:phone":"+61 3 9886 1551",
    "sg:postcode":"3150",
    "sg:province":"VIC",
    "sg:tags":[
        "garage",
        "equipment"
    ],
    "wof:name":"Flo Dynamics ATF 2000",
    "wof:placetype":"venue"
},
  "geometry": {"coordinates":[145.147705078,-37.8837242126],"type":"Point"}
}