{
  "type": "Feature",
  "properties": {
    "addr:full":"PO Box 7601 Sutton NSW 2620",
    "addr:postcode":"2620",
    "iso:country":"AU",
    "sg:address":"PO Box 7601",
    "sg:city":"Sutton",
    "sg:classifiers":[
        {
            "category":"Real Estate",
            "subcategory":"Surveying",
            "type":"Services"
        }
    ],
    "sg:phone":"+61 2 6230 3577",
    "sg:postcode":"2620",
    "sg:province":"NSW",
    "sg:tags":[
        "surveyor",
        "land"
    ],
    "wof:name":"Capital Surveys",
    "wof:placetype":"venue"
},
  "geometry": {"coordinates":[149.253051758,-35.161781311],"type":"Point"}
}