{
  "type": "Feature",
  "properties": {
    "iso:country":"AU",
    "sg:address":"Unit 4/ 22 Scott Pl",
    "sg:city":"Orange",
    "sg:classifiers":[
        {
            "category":"Building & Trades",
            "subcategory":"Construction",
            "type":"Services"
        }
    ],
    "sg:phone":"+61 2 6361 1180",
    "sg:postcode":"2800",
    "sg:province":"NSW",
    "sg:tags":[
        "installation",
        "air conditioning"
    ],
    "wof:name":"Longley Mechanical Services",
    "wof:placetype":"venue"
},
  "geometry": {"coordinates":[149.10366821299999,-33.3074684143],"type":"Point"}
}