{
  "type": "Feature",
  "properties": {
    "iso:country":"AU",
    "sg:address":"433 Wondall Rd",
    "sg:city":"Tingalpa",
    "sg:classifiers":[
        {
            "category":"Landmark",
            "subcategory":"Scenic View",
            "type":"Public Place"
        }
    ],
    "sg:phone":"+61 7 3390 7362",
    "sg:postcode":"4173",
    "sg:province":"QLD",
    "sg:tags":[
        "staircase",
        "handrail"
    ],
    "sg:website":"http://www.forsythromano.com.au",
    "wof:name":"Forsyth & Romano Pty Ltd",
    "wof:placetype":"venue"
},
  "geometry": {"coordinates":[153.15142822300001,-27.4685668945],"type":"Point"}
}