{
  "type": "Feature",
  "properties": {
    "addr:full":"Unit 2, 44-46 Grimwade St Mitchell ACT 2911",
    "addr:housenumber":"44-46",
    "addr:postcode":"2911",
    "addr:street":"Grimwade St",
    "iso:country":"AU",
    "sg:address":"Unit 2, 44-46 Grimwade St",
    "sg:city":"Mitchell",
    "sg:classifiers":[
        {
            "category":"Retail",
            "subcategory":"Auto Repair",
            "type":"Services"
        }
    ],
    "sg:phone":"+61 2 6241 5147",
    "sg:postcode":"2911",
    "sg:province":"ACT",
    "sg:tags":[
        "beater",
        "painter",
        "panel"
    ],
    "wof:name":"Autoart Body Refinishers",
    "wof:placetype":"venue"
},
  "geometry": {"coordinates":[149.138183594,-35.2173614502],"type":"Point"}
}