{
  "type": "Feature",
  "properties": {
    "iso:country":"AU",
    "sg:address":"Glover Rd",
    "sg:city":"Dayboro",
    "sg:classifiers":[
        {
            "category":"Wholesale",
            "subcategory":"Fruits & Vegetables",
            "type":"Manufacturing & Wholesale Goods"
        }
    ],
    "sg:phone":"+61 7 3425 1322",
    "sg:postcode":"4521",
    "sg:province":"QLD",
    "sg:tags":[
        "produce",
        "grain"
    ],
    "wof:name":"Mataranka Grains Pty Ltd",
    "wof:placetype":"venue"
},
  "geometry": {"coordinates":[152.808044,-27.205772],"type":"Point"}
}