{
  "type": "Feature",
  "properties": {
    "addr:full":"Shop 5 22 St Quentin Ave Claremont WA 6010",
    "addr:housenumber":"shop;22",
    "addr:postcode":"6010",
    "addr:street":"St Quentin Ave",
    "iso:country":"AU",
    "sg:address":"Shop 5 22 St Quentin Ave",
    "sg:city":"Claremont",
    "sg:classifiers":[
        {
            "category":"Museum",
            "subcategory":"Art Museum",
            "type":"Entertainment"
        }
    ],
    "sg:phone":"+61 8 9384 9473",
    "sg:postcode":"6010",
    "sg:province":"WA",
    "sg:tags":[
        "antique",
        "fine",
        "valuer"
    ],
    "wof:name":"Church Lane Antiques",
    "wof:placetype":"venue"
},
  "geometry": {"coordinates":[115.779899597,-31.9827709198],"type":"Point"}
}