{
  "type": "Feature",
  "properties": {
    "iso:country":"AU",
    "sg:address":"PO Box 408",
    "sg:city":"South Melbourne",
    "sg:classifiers":[
        {
            "category":"Real Estate",
            "subcategory":"Real Estate Services",
            "type":"Services"
        }
    ],
    "sg:phone":"+61 419 559 577",
    "sg:postcode":"3205",
    "sg:province":"VIC",
    "sg:tags":[
        "consultant",
        "property"
    ],
    "wof:name":"The House Scout",
    "wof:placetype":"venue"
},
  "geometry": {"coordinates":[144.955856,-37.833881],"type":"Point"}
}