{
  "type": "Feature",
  "properties": {
    "addr:full":"45 Lannercost St Ingham QLD 4850",
    "addr:housenumber":"45",
    "addr:postcode":"4850",
    "addr:street":"Lannercost St",
    "iso:country":"AU",
    "sg:address":"45 Lannercost St",
    "sg:city":"Ingham",
    "sg:classifiers":[
        {
            "category":"Cafe",
            "type":"Food & Drink"
        }
    ],
    "sg:phone":"+61 7 4776 5166",
    "sg:postcode":"4850",
    "sg:province":"QLD",
    "wof:name":"The Olive Tree Coffee Lounge",
    "wof:placetype":"venue"
},
  "geometry": {"coordinates":[146.15362548799999,-18.650686264],"type":"Point"}
}