{
  "type": "Feature",
  "properties": {
    "addr:full":"Frankland Cranbrook Rd Frankland River WA 6396",
    "addr:postcode":"6396",
    "addr:street":"Cranbrook Rd",
    "iso:country":"AU",
    "sg:address":"Frankland Cranbrook Rd",
    "sg:city":"Frankland River",
    "sg:classifiers":[
        {
            "category":"Food & Beverages",
            "subcategory":"Groceries & Convenience Stores",
            "type":"Retail Goods"
        }
    ],
    "sg:phone":"+61 8 9855 2265",
    "sg:postcode":"6396",
    "sg:province":"WA",
    "wof:name":"Frankland General Store",
    "wof:placetype":"venue"
},
  "geometry": {"coordinates":[117.083488464,-34.3626403809],"type":"Point"}
}