{
  "type": "Feature",
  "properties": {
    "addr:full":"Top Yard Bellevue St Tempe NSW 2044",
    "addr:postcode":"2044",
    "addr:street":"Bellevue St",
    "iso:country":"AU",
    "sg:address":"Top Yard Bellevue St",
    "sg:city":"Tempe",
    "sg:classifiers":[
        {
            "category":"Freight",
            "type":"Transportation"
        }
    ],
    "sg:phone":"+61 2 9557 3484",
    "sg:postcode":"2044",
    "sg:province":"NSW",
    "sg:tags":[
        "cargo",
        "container"
    ],
    "wof:name":"Tyne Container Services Pty Ltd",
    "wof:placetype":"venue"
},
  "geometry": {"coordinates":[151.16888399999999,-33.921383],"type":"Point"}
}