{
  "type": "Feature",
  "properties": {
    "addr:full":"Shop 266 Sunshine Plaza Horton Pde Maroochydore QLD 4558",
    "addr:housenumber":"266",
    "addr:postcode":"4558",
    "addr:street":"Sunshine Plaza Horton Pde",
    "iso:country":"AU",
    "sg:address":"Shop 266 Sunshine Plaza Horton Pde",
    "sg:city":"Maroochydore",
    "sg:classifiers":[
        {
            "category":"Travel",
            "subcategory":"Travel Agent",
            "type":"Entertainment"
        }
    ],
    "sg:phone":"+61 13 18 66",
    "sg:postcode":"4558",
    "sg:province":"QLD",
    "sg:tags":[
        "consultant"
    ],
    "wof:name":"Flight Centre",
    "wof:placetype":"venue"
},
  "geometry": {"coordinates":[153.089675903,-26.6531066895],"type":"Point"}
}