{
  "type": "Feature",
  "properties": {
    "iso:country":"AU",
    "sg:address":"45 Civic Pde",
    "sg:city":"Altona",
    "sg:classifiers":[
        {
            "category":"Food & Beverages",
            "subcategory":"Fruits & Vegetables",
            "type":"Retail Goods"
        }
    ],
    "sg:phone":"+61 3 9398 4681",
    "sg:postcode":"3018",
    "sg:province":"VIC",
    "sg:tags":[
        "greengrocer",
        "fruiterer"
    ],
    "wof:name":"Altona Fruit Ilicious",
    "wof:placetype":"venue"
},
  "geometry": {"coordinates":[144.838134766,-37.8651275635],"type":"Point"}
}