{
  "type": "Feature",
  "properties": {
    "addr:full":"214 Grange Rd Flinders Park SA 5025",
    "addr:housenumber":"214",
    "addr:postcode":"5025",
    "addr:street":"Grange Rd",
    "iso:country":"AU",
    "sg:address":"214 Grange Rd",
    "sg:city":"Flinders Park",
    "sg:classifiers":[
        {
            "category":"Organizations",
            "subcategory":"Non-profit Organization",
            "type":"Services"
        }
    ],
    "sg:phone":"+61 8 8234 7255",
    "sg:postcode":"5025",
    "sg:province":"SA",
    "sg:tags":[
        "environmental",
        "organisation",
        "conservation"
    ],
    "wof:name":"KESAB (Keep S.A. Beautiful)",
    "wof:placetype":"venue"
},
  "geometry": {"coordinates":[138.54359435999999,-34.9050483704],"type":"Point"}
}