{
  "type": "Feature",
  "properties": {
    "addr:full":"9 Lennon St Clare SA 5453",
    "addr:housenumber":"9",
    "addr:postcode":"5453",
    "addr:street":"Lennon St",
    "iso:country":"AU",
    "sg:address":"9 Lennon St",
    "sg:city":"Clare",
    "sg:classifiers":[
        {
            "category":"Retail",
            "subcategory":"Auto Repair",
            "type":"Services"
        }
    ],
    "sg:phone":"+61 8 8842 2062",
    "sg:postcode":"5453",
    "sg:province":"SA",
    "sg:tags":[
        "beater",
        "painter",
        "panel"
    ],
    "wof:name":"Edwards Phil",
    "wof:placetype":"venue"
},
  "geometry": {"coordinates":[138.616455,-33.835632],"type":"Point"}
}