{
  "type": "Feature",
  "properties": {
    "addr:full":"Cnr Robinson St & Camel La Carnarvon WA 6701",
    "addr:postcode":"6701",
    "addr:street":"Cnr Robinson St & Camel La",
    "iso:country":"AU",
    "sg:address":"Cnr Robinson St & Camel La",
    "sg:city":"Carnarvon",
    "sg:classifiers":[
        {
            "category":"Cinema",
            "subcategory":"Movie Theater",
            "type":"Entertainment"
        }
    ],
    "sg:phone":"+61 8 9941 4200",
    "sg:postcode":"6701",
    "sg:province":"WA",
    "wof:name":"Carnarvon Civic Centre",
    "wof:placetype":"venue"
},
  "geometry": {"coordinates":[113.65939331,-24.8811073303],"type":"Point"}
}