{
  "type": "Feature",
  "properties": {
    "iso:country":"AU",
    "sg:address":"Jones Rd",
    "sg:city":"Drouin",
    "sg:classifiers":[
        {
            "category":"Farming",
            "subcategory":"Farm",
            "type":"Manufacturing & Wholesale Goods"
        }
    ],
    "sg:phone":"+61 3 5625 1994",
    "sg:postcode":"3818",
    "sg:province":"VIC",
    "sg:tags":[
        "farmer"
    ],
    "wof:name":"McLeish N R & J M",
    "wof:placetype":"venue"
},
  "geometry": {"coordinates":[145.873779,-38.148003],"type":"Point"}
}