{
  "type": "Feature",
  "properties": {
    "addr:full":"39 Bannister Rd Boddington WA 6390",
    "addr:housenumber":"39",
    "addr:postcode":"6390",
    "addr:street":"Bannister Rd",
    "iso:country":"AU",
    "sg:address":"39 Bannister Rd",
    "sg:city":"Boddington",
    "sg:classifiers":[
        {
            "category":"Government",
            "subcategory":"Department Of Motor Vehicles",
            "type":"Public Place"
        }
    ],
    "sg:phone":"+61 8 9883 4999",
    "sg:postcode":"6390",
    "sg:province":"WA",
    "sg:tags":[
        "organisation",
        "local"
    ],
    "wof:name":"Boddington Shire Of",
    "wof:placetype":"venue"
},
  "geometry": {"coordinates":[116.474876404,-32.8023376465],"type":"Point"}
}