{
  "type": "Feature",
  "properties": {
    "iso:country":"AU",
    "sg:address":"Canane St",
    "sg:city":"Smithtown",
    "sg:classifiers":[
        {
            "category":"Education",
            "subcategory":"School",
            "type":"Public Place"
        }
    ],
    "sg:phone":"+61 2 6567 4529",
    "sg:postcode":"2440",
    "sg:province":"NSW",
    "sg:tags":[
        "state",
        "-",
        "nsw"
    ],
    "wof:name":"Smithtown Public School",
    "wof:placetype":"venue"
},
  "geometry": {"coordinates":[152.94288599999999,-31.017536],"type":"Point"}
}