{
  "type": "Feature",
  "properties": {
    "iso:country":"AU",
    "sg:address":"Cnr Nelson & Victoria Sts",
    "sg:city":"Mackay",
    "sg:classifiers":[
        {
            "category":"Shopping",
            "subcategory":"Crafts & Fabrics",
            "type":"Retail Goods"
        }
    ],
    "sg:phone":"+61 13 11 63",
    "sg:postcode":"4740",
    "sg:province":"QLD",
    "sg:tags":[
        "material",
        "dress"
    ],
    "wof:name":"Spotlight Stores Pty Ltd",
    "wof:placetype":"venue"
},
  "geometry": {"coordinates":[149.176743,-21.140074],"type":"Point"}
}