{
  "type": "Feature",
  "properties": {
    "addr:full":"182 Camboon Rd Malaga WA 6090",
    "addr:housenumber":"182",
    "addr:postcode":"6090",
    "addr:street":"Camboon Rd",
    "iso:country":"AU",
    "sg:address":"182 Camboon Rd",
    "sg:city":"Malaga",
    "sg:classifiers":[
        {
            "category":"Wholesale",
            "subcategory":"Scrap",
            "type":"Manufacturing & Wholesale Goods"
        }
    ],
    "sg:phone":"+61 8 9249 3177",
    "sg:postcode":"6090",
    "sg:province":"WA",
    "sg:tags":[
        "merchant",
        "metal"
    ],
    "wof:name":"A1 Malaga Auto Dismantlers",
    "wof:placetype":"venue"
},
  "geometry": {"coordinates":[115.88868713399999,-31.8640079498],"type":"Point"}
}