{
  "type": "Feature",
  "properties": {
    "iso:country":"AU",
    "sg:address":"U 5 26c Cohn St",
    "sg:city":"Carlisle",
    "sg:classifiers":[
        {
            "category":"Building & Trades",
            "subcategory":"Plumbing",
            "type":"Services"
        }
    ],
    "sg:phone":"+61 8 9470 1655",
    "sg:postcode":"6101",
    "sg:province":"WA",
    "sg:tags":[
        "plumber",
        "gasfitters"
    ],
    "wof:name":"Plumbers WA & CO",
    "wof:placetype":"venue"
},
  "geometry": {"coordinates":[115.923927307,-31.9837093353],"type":"Point"}
}