{
  "type": "Feature",
  "properties": {
    "iso:country":"AU",
    "sg:address":"130 Walter Rd",
    "sg:city":"Bedford",
    "sg:classifiers":[
        {
            "category":"Health Services",
            "subcategory":"Dentist",
            "type":"Services"
        }
    ],
    "sg:phone":"+61 8 9276 6900",
    "sg:postcode":"6052",
    "sg:province":"WA",
    "wof:name":"Foster Jeremy Dr",
    "wof:placetype":"venue"
},
  "geometry": {"coordinates":[115.884773254,-31.9042549133],"type":"Point"}
}