{
  "type": "Feature",
  "properties": {
    "iso:country":"AU",
    "sg:address":"96- 100 Hay St",
    "sg:city":"Haymarket",
    "sg:classifiers":[
        {
            "category":"Fast Food",
            "type":"Food & Drink"
        }
    ],
    "sg:phone":"+61 2 9211 2135",
    "sg:postcode":"2000",
    "sg:province":"NSW",
    "sg:tags":[
        "away",
        "take"
    ],
    "wof:name":"Emperor Garden Restaurant",
    "wof:placetype":"venue"
},
  "geometry": {"coordinates":[151.204055786,-33.8793182373],"type":"Point"}
}