{
  "type": "Feature",
  "properties": {
    "addr:full":"75 Best St Devonport TAS 7310",
    "addr:housenumber":"75",
    "addr:postcode":"7310",
    "addr:street":"Best St",
    "iso:country":"AU",
    "sg:address":"75 Best St",
    "sg:city":"Devonport",
    "sg:classifiers":[
        {
            "category":"Health Services",
            "subcategory":"Health Practitioner",
            "type":"Services"
        }
    ],
    "sg:phone":"+61 3 6424 7511",
    "sg:postcode":"7310",
    "sg:province":"TAS",
    "sg:tags":[
        "physiotherapist"
    ],
    "wof:name":"Pearson Lisel",
    "wof:placetype":"venue"
},
  "geometry": {"coordinates":[146.35313415499999,-41.1774520874],"type":"Point"}
}