{
  "type": "Feature",
  "properties": {
    "iso:country":"AU",
    "sg:address":"320 Heaths Rd",
    "sg:city":"Hoppers Crossing",
    "sg:classifiers":[
        {
            "category":"Health Services",
            "subcategory":"Chiropractor",
            "type":"Services"
        }
    ],
    "sg:phone":"+61 3 9974 1991",
    "sg:postcode":"3029",
    "sg:province":"VIC",
    "wof:name":"Potter Chiropractic Centre",
    "wof:placetype":"venue"
},
  "geometry": {"coordinates":[144.67190600000001,-37.876144],"type":"Point"}
}