{
  "type": "Feature",
  "properties": {
    "addr:full":"Level 1 / 344 Queen St Brisbane QLD 4000",
    "addr:housenumber":"/ 344",
    "addr:postcode":"4000",
    "addr:street":"Queen St",
    "iso:country":"AU",
    "sg:address":"Level 1 / 344 Queen St",
    "sg:city":"Brisbane",
    "sg:classifiers":[
        {
            "category":"Government",
            "subcategory":"Court House",
            "type":"Public Place"
        }
    ],
    "sg:phone":"+61 1300 134 080",
    "sg:postcode":"4000",
    "sg:province":"QLD",
    "sg:tags":[
        "personal",
        "marriage",
        "family",
        "counselling"
    ],
    "wof:name":"Ashby Allan Institute",
    "wof:placetype":"venue"
},
  "geometry": {"coordinates":[153.029006958,-27.4665374756],"type":"Point"}
}