{
  "type": "Feature",
  "properties": {
    "addr:full":"320- 324 Parramatta Rd Burwood NSW 2134",
    "addr:housenumber":"320 324",
    "addr:postcode":"2134",
    "addr:street":"Parramatta Rd",
    "iso:country":"AU",
    "sg:address":"320- 324 Parramatta Rd",
    "sg:city":"Burwood",
    "sg:classifiers":[
        {
            "category":"Autos & Motor Vehicles",
            "subcategory":"Auto Supplies",
            "type":"Retail Goods"
        }
    ],
    "sg:phone":"+61 2 9744 6877",
    "sg:postcode":"2134",
    "sg:province":"NSW",
    "sg:tags":[
        "car",
        "alarm"
    ],
    "wof:name":"Black Widow",
    "wof:placetype":"venue"
},
  "geometry": {"coordinates":[151.10697937,-33.8692550659],"type":"Point"}
}