{
  "type": "Feature",
  "properties": {
    "iso:country":"AU",
    "sg:address":"8 Pylara St",
    "sg:city":"Fig Tree Pocket",
    "sg:classifiers":[
        {
            "category":"Farming",
            "subcategory":"Nursery",
            "type":"Manufacturing & Wholesale Goods"
        }
    ],
    "sg:phone":"+61 7 3378 1572",
    "sg:postcode":"4069",
    "sg:province":"QLD",
    "wof:name":"Pylara Nurseries",
    "wof:placetype":"venue"
},
  "geometry": {"coordinates":[152.956756592,-27.5256843567],"type":"Point"}
}