{
  "type": "Feature",
  "properties": {
    "iso:country":"AU",
    "sg:address":"45 Murray St",
    "sg:city":"Perth",
    "sg:classifiers":[
        {
            "category":"Arts & Performance",
            "subcategory":"Music",
            "type":"Entertainment"
        }
    ],
    "sg:phone":"+61 411 881 071",
    "sg:postcode":"6000",
    "sg:province":"WA",
    "sg:tags":[
        "mobile",
        "jockey",
        "disc"
    ],
    "wof:name":"Gilkison Sound & Entertainment",
    "wof:placetype":"venue"
},
  "geometry": {"coordinates":[115.854782105,-31.951669693],"type":"Point"}
}