{
  "type": "Feature",
  "properties": {
    "addr:full":"214 Surrey Rd Kewdale WA 6105",
    "addr:housenumber":"214",
    "addr:postcode":"6105",
    "addr:street":"Surrey Rd",
    "iso:country":"AU",
    "sg:address":"214 Surrey Rd",
    "sg:city":"Kewdale",
    "sg:classifiers":[
        {
            "category":"Building & Trades",
            "subcategory":"Construction",
            "type":"Services"
        }
    ],
    "sg:phone":"+61 409 925 629",
    "sg:postcode":"6105",
    "sg:province":"WA",
    "sg:tags":[
        "earth",
        "excavating",
        "moving",
        "contractor"
    ],
    "wof:name":"Louis Plant Hire",
    "wof:placetype":"venue"
},
  "geometry": {"coordinates":[115.923179627,-31.9726676941],"type":"Point"}
}