{
  "type": "Feature",
  "properties": {
    "iso:country":"AU",
    "sg:address":"PO Box 305",
    "sg:city":"Drayton North",
    "sg:classifiers":[
        {
            "category":"Retail",
            "subcategory":"Auto Repair",
            "type":"Services"
        }
    ],
    "sg:phone":"+61 408 064 063",
    "sg:postcode":"4350",
    "sg:province":"QLD",
    "sg:tags":[
        "beater",
        "painter",
        "panel"
    ],
    "wof:name":"Dent Systems Australia",
    "wof:placetype":"venue"
},
  "geometry": {"coordinates":[151.915955,-27.589491],"type":"Point"}
}