{
  "type": "Feature",
  "properties": {
    "iso:country":"AU",
    "sg:address":"67 Randell St",
    "sg:city":"Mannum",
    "sg:classifiers":[
        {
            "category":"Real Estate",
            "subcategory":"Real Estate Agent",
            "type":"Services"
        }
    ],
    "sg:phone":"+61 8 8569 1361",
    "sg:postcode":"5238",
    "sg:province":"SA",
    "wof:name":"First National Real Estate",
    "wof:placetype":"venue"
},
  "geometry": {"coordinates":[139.312133789,-34.9140014648],"type":"Point"}
}