{
  "type": "Feature",
  "properties": {
    "addr:full":"30 Eucalyptus Pl Meadow Heights VIC 3048",
    "addr:housenumber":"30",
    "addr:postcode":"3048",
    "addr:street":"Eucalyptus Pl",
    "iso:country":"AU",
    "sg:address":"30 Eucalyptus Pl",
    "sg:city":"Meadow Heights",
    "sg:classifiers":[
        {
            "category":"Building & Trades",
            "subcategory":"Construction",
            "type":"Services"
        }
    ],
    "sg:phone":"+61 419 335 622",
    "sg:postcode":"3048",
    "sg:province":"VIC",
    "sg:tags":[
        "contractor"
    ],
    "wof:name":"Edge Building & Developments Pty Ltd",
    "wof:placetype":"venue"
},
  "geometry": {"coordinates":[144.92013499999999,-37.641953],"type":"Point"}
}