{
  "type": "Feature",
  "properties": {
    "iso:country":"AU",
    "sg:address":"30 Eucalyptus Pl",
    "sg:city":"Meadow Heights",
    "sg:classifiers":[
        {
            "category":"Building & Trades",
            "subcategory":"Construction",
            "type":"Services"
        }
    ],
    "sg:phone":"+61 419 335 622",
    "sg:postcode":"3048",
    "sg:province":"VIC",
    "sg:tags":[
        "contractor"
    ],
    "wof:name":"Edge Building & Developments Pty Ltd",
    "wof:placetype":"venue"
},
  "geometry": {"coordinates":[144.920135,-37.641953],"type":"Point"}
}