{
  "type": "Feature",
  "properties": {
    "iso:country":"AU",
    "sg:address":"440a Burwood Hwy",
    "sg:city":"Wantirna South",
    "sg:classifiers":[
        {
            "category":"Personal",
            "subcategory":"Tattoo Parlor",
            "type":"Services"
        }
    ],
    "sg:phone":"+61 3 9800 5470",
    "sg:postcode":"3152",
    "sg:province":"VIC",
    "sg:tags":[
        "tattooing"
    ],
    "wof:name":"Tattoo Connection",
    "wof:placetype":"venue"
},
  "geometry": {"coordinates":[145.23860168499999,-37.870426178],"type":"Point"}
}