{
  "type": "Feature",
  "properties": {
    "addr:full":"4707 / 393 Pitt St Sydney NSW 2000",
    "addr:housenumber":"4707 / 393",
    "addr:postcode":"2000",
    "addr:street":"Pitt St",
    "iso:country":"AU",
    "sg:address":"4707 / 393 Pitt St",
    "sg:city":"Sydney",
    "sg:classifiers":[
        {
            "category":"Building & Trades",
            "subcategory":"Cleaning & Sanitation",
            "type":"Services"
        }
    ],
    "sg:phone":"+61 2 9283 5040",
    "sg:postcode":"2000",
    "sg:province":"NSW",
    "sg:tags":[
        "commercial",
        "maintenance"
    ],
    "wof:name":"Ecoram Constructions",
    "wof:placetype":"venue"
},
  "geometry": {"coordinates":[151.20753479000001,-33.8771629333],"type":"Point"}
}