{
  "type": "Feature",
  "properties": {
    "iso:country":"AU",
    "sg:address":"71 Ocean St",
    "sg:city":"Dudley",
    "sg:classifiers":[
        {
            "category":"Government",
            "subcategory":"Post Office",
            "type":"Public Place"
        }
    ],
    "sg:phone":"+61 2 4943 4900",
    "sg:postcode":"2290",
    "sg:province":"NSW",
    "sg:tags":[
        "yoga"
    ],
    "wof:name":"Hatha Yoga",
    "wof:placetype":"venue"
},
  "geometry": {"coordinates":[151.72102355999999,-32.9895858765],"type":"Point"}
}