{
  "type": "Feature",
  "properties": {
    "addr:full":"Leith Rd Montrose VIC 3765",
    "addr:postcode":"3765",
    "addr:street":"Leith Rd",
    "iso:country":"AU",
    "sg:address":"Leith Rd",
    "sg:city":"Montrose",
    "sg:classifiers":[
        {
            "category":"Social Services",
            "subcategory":"Child Care",
            "type":"Services"
        }
    ],
    "sg:phone":"+61 3 9728 3500",
    "sg:postcode":"3765",
    "sg:province":"VIC",
    "sg:tags":[
        "support",
        "health"
    ],
    "wof:name":"Maternal & Child Health Centres",
    "wof:placetype":"venue"
},
  "geometry": {"coordinates":[145.34327697800001,-37.8096313477],"type":"Point"}
}