{
  "type": "Feature",
  "properties": {
    "addr:full":"41 Bradley St Goulburn NSW 2580",
    "addr:housenumber":"41",
    "addr:postcode":"2580",
    "addr:street":"Bradley St",
    "iso:country":"AU",
    "sg:address":"41 Bradley St",
    "sg:city":"Goulburn",
    "sg:classifiers":[
        {
            "category":"Autos & Motor Vehicles",
            "subcategory":"Automobile Sales",
            "type":"Retail Goods"
        }
    ],
    "sg:phone":"+61 2 4822 2266",
    "sg:postcode":"2580",
    "sg:province":"NSW",
    "sg:tags":[
        "car",
        "used"
    ],
    "wof:name":"Flood Autos",
    "wof:placetype":"venue"
},
  "geometry": {"coordinates":[149.71926879899999,-34.747718811],"type":"Point"}
}