{
  "type": "Feature",
  "properties": {
    "addr:full":"146 Balcatta Rd Balcatta WA 6021",
    "addr:housenumber":"146",
    "addr:postcode":"6021",
    "addr:street":"Balcatta Rd",
    "iso:country":"AU",
    "sg:address":"146 Balcatta Rd",
    "sg:city":"Balcatta",
    "sg:classifiers":[
        {
            "category":"Shopping",
            "subcategory":"Computers & Home Electronics",
            "type":"Retail Goods"
        }
    ],
    "sg:phone":"+61 8 9240 2233",
    "sg:postcode":"6021",
    "sg:province":"WA",
    "sg:tags":[
        "wholesaler",
        "mfrs",
        "part",
        "electronic"
    ],
    "wof:name":"Westec Electronics Pty Ltd",
    "wof:placetype":"venue"
},
  "geometry": {"coordinates":[115.81649017300001,-31.8622608185],"type":"Point"}
}