{
  "type": "Feature",
  "properties": {
    "addr:full":"3/ 64 Meadow Ave Coopers Plains QLD 4108",
    "addr:housenumber":"/ 64",
    "addr:postcode":"4108",
    "addr:street":"Meadow Ave",
    "iso:country":"AU",
    "sg:address":"3/ 64 Meadow Ave",
    "sg:city":"Coopers Plains",
    "sg:classifiers":[
        {
            "category":"Food & Beverages",
            "subcategory":"Fruits & Vegetables",
            "type":"Retail Goods"
        }
    ],
    "sg:phone":"+61 7 3275 2555",
    "sg:postcode":"4108",
    "sg:province":"QLD",
    "sg:tags":[
        "consultant",
        "catering"
    ],
    "wof:name":"The Diet Factory",
    "wof:placetype":"venue"
},
  "geometry": {"coordinates":[153.02636718799999,-27.5657978058],"type":"Point"}
}