{
  "type": "Feature",
  "properties": {
    "addr:full":"130 Crockford St Northgate QLD 4013",
    "addr:housenumber":"130",
    "addr:postcode":"4013",
    "addr:street":"Crockford St",
    "iso:country":"AU",
    "sg:address":"130 Crockford St",
    "sg:city":"Northgate",
    "sg:classifiers":[
        {
            "category":"Wholesale",
            "subcategory":"Office Equipment",
            "type":"Manufacturing & Wholesale Goods"
        }
    ],
    "sg:phone":"+61 1300 365 800",
    "sg:postcode":"4013",
    "sg:province":"QLD",
    "sg:tags":[
        "nail",
        "nailing"
    ],
    "wof:name":"National Nails",
    "wof:placetype":"venue"
},
  "geometry": {"coordinates":[153.08021545400001,-27.3893013],"type":"Point"}
}