{
  "type": "Feature",
  "properties": {
    "addr:full":"Ground Floor 165 Grenfell St Adelaide SA 5000",
    "addr:housenumber":"165",
    "addr:postcode":"5000",
    "addr:street":"Grenfell St",
    "iso:country":"AU",
    "sg:address":"Ground Floor 165 Grenfell St",
    "sg:city":"Adelaide",
    "sg:classifiers":[
        {
            "category":"Professional",
            "subcategory":"Employment Agencies",
            "type":"Services"
        }
    ],
    "sg:phone":"+61 8 8306 8282",
    "sg:postcode":"5000",
    "sg:province":"SA",
    "wof:name":"Icon Recruitment Pty Ltd",
    "wof:placetype":"venue"
},
  "geometry": {"coordinates":[138.60780334500001,-34.9241027832],"type":"Point"}
}