{
  "type": "Feature",
  "properties": {
    "addr:full":"12 Kathryn Drv Goonellabah NSW 2480",
    "addr:housenumber":"12",
    "addr:postcode":"2480",
    "addr:street":"Kathryn Drv",
    "iso:country":"AU",
    "sg:address":"12 Kathryn Drv",
    "sg:city":"Goonellabah",
    "sg:classifiers":[
        {
            "category":"Building & Trades",
            "subcategory":"Plumbing",
            "type":"Services"
        }
    ],
    "sg:phone":"+61 400 368 231",
    "sg:postcode":"2480",
    "sg:province":"NSW",
    "sg:tags":[
        "pump",
        "repairer"
    ],
    "wof:name":"Maccas Pumps",
    "wof:placetype":"venue"
},
  "geometry": {"coordinates":[153.30778503400001,-28.8255195618],"type":"Point"}
}