{
  "type": "Feature",
  "properties": {
    "iso:country":"AU",
    "sg:address":"Aerodrome Avro Crt",
    "sg:city":"Townsville",
    "sg:classifiers":[
        {
            "category":"Airline",
            "type":"Transportation"
        }
    ],
    "sg:phone":"+61 7 4779 2060",
    "sg:postcode":"4810",
    "sg:province":"QLD",
    "sg:tags":[
        "aircraft",
        "rental",
        "charter"
    ],
    "wof:name":"Pagani Air",
    "wof:placetype":"venue"
},
  "geometry": {"coordinates":[146.772156,-19.255005],"type":"Point"}
}