{
  "type": "Feature",
  "properties": {
    "addr:full":"95 Nicholson St Bairnsdale VIC 3875",
    "addr:housenumber":"95",
    "addr:postcode":"3875",
    "addr:street":"Nicholson St",
    "iso:country":"AU",
    "sg:address":"95 Nicholson St",
    "sg:city":"Bairnsdale",
    "sg:classifiers":[
        {
            "category":"Shopping",
            "subcategory":"Shoes",
            "type":"Retail Goods"
        }
    ],
    "sg:phone":"+61 3 5152 3412",
    "sg:postcode":"3875",
    "sg:province":"VIC",
    "sg:tags":[
        "footwear"
    ],
    "wof:name":"Hi Strollin",
    "wof:placetype":"venue"
},
  "geometry": {"coordinates":[147.62928772000001,-37.8251724243],"type":"Point"}
}