{
  "type": "Feature",
  "properties": {
    "iso:country":"AU",
    "sg:address":"Gilbert Pl",
    "sg:city":"Emerald",
    "sg:classifiers":[
        {
            "category":"Retail",
            "subcategory":"Auto Rental",
            "type":"Services"
        }
    ],
    "sg:phone":"+61 7 4982 3591",
    "sg:postcode":"4720",
    "sg:province":"QLD",
    "sg:tags":[
        "chauffeur",
        "car",
        "hire",
        "driven",
        "limousine"
    ],
    "wof:name":"Limousine Class Private Hire Cars",
    "wof:placetype":"venue"
},
  "geometry": {"coordinates":[148.167892,-23.509983],"type":"Point"}
}