{
  "type": "Feature",
  "properties": {
    "addr:full":"10 Cleaver St West Perth WA 6005",
    "addr:housenumber":"10",
    "addr:postcode":"6005",
    "addr:street":"Cleaver St",
    "iso:country":"AU",
    "sg:address":"10 Cleaver St",
    "sg:city":"West Perth",
    "sg:classifiers":[
        {
            "category":"Manufacturing",
            "subcategory":"Glass & Minerals",
            "type":"Manufacturing & Wholesale Goods"
        }
    ],
    "sg:phone":"+61 8 9328 2879",
    "sg:postcode":"6005",
    "sg:province":"WA",
    "sg:tags":[
        "stained"
    ],
    "wof:name":"Western Australian Art Glass Guild Inc",
    "wof:placetype":"venue"
},
  "geometry": {"coordinates":[115.848228455,-31.9405956268],"type":"Point"}
}