{
  "type": "Feature",
  "properties": {
    "addr:full":"Unit 135 45 Gilby Rd Mt Waverley VIC 3149",
    "addr:housenumber":"45",
    "addr:postcode":"3149",
    "addr:street":"Gilby Rd",
    "iso:country":"AU",
    "sg:address":"Unit 135 45 Gilby Rd",
    "sg:city":"Mt Waverley",
    "sg:classifiers":[
        {
            "category":"Professional",
            "subcategory":"Engineering",
            "type":"Services"
        }
    ],
    "sg:phone":"+61 3 9558 9924",
    "sg:postcode":"3149",
    "sg:province":"VIC",
    "sg:tags":[
        "electronic",
        "engineer"
    ],
    "wof:name":"Niksar Pty Ltd",
    "wof:placetype":"venue"
},
  "geometry": {"coordinates":[145.13653564399999,-37.8993797302],"type":"Point"}
}