{
  "type": "Feature",
  "properties": {
    "addr:full":"Shop 3, 595 Melton Hwy Hillside VIC 3037",
    "addr:housenumber":"shop 3 595",
    "addr:postcode":"3037",
    "addr:street":"Melton Hwy",
    "iso:country":"AU",
    "sg:address":"Shop 3, 595 Melton Hwy",
    "sg:city":"Hillside",
    "sg:classifiers":[
        {
            "category":"Communications",
            "subcategory":"Film & Video Production",
            "type":"Services"
        }
    ],
    "sg:phone":"+61 3 9449 2449",
    "sg:postcode":"3037",
    "sg:province":"VIC",
    "sg:tags":[
        "dvd",
        "library"
    ],
    "wof:name":"Video Ezy",
    "wof:placetype":"venue"
},
  "geometry": {"coordinates":[144.754379,-37.693535],"type":"Point"}
}