{
  "type": "Feature",
  "properties": {
    "addr:full":"Level 2, 210 Albert Rd South Melbourne VIC 3205",
    "addr:housenumber":"210",
    "addr:postcode":"3205",
    "addr:street":"Albert Rd",
    "iso:country":"AU",
    "sg:address":"Level 2, 210 Albert Rd",
    "sg:city":"South Melbourne",
    "sg:classifiers":[
        {
            "category":"Banks & Credit Unions",
            "subcategory":"Financial Services",
            "type":"Services"
        }
    ],
    "sg:phone":"+61 3 9697 2500",
    "sg:postcode":"3205",
    "sg:province":"VIC",
    "sg:tags":[
        "financier"
    ],
    "wof:name":"GE Finance and Insurance",
    "wof:placetype":"venue"
},
  "geometry": {"coordinates":[144.96693400000001,-37.837311],"type":"Point"}
}