{
  "type": "Feature",
  "properties": {
    "addr:full":"Cnr Fairbrother & Fisher St Belmont WA 6984",
    "addr:postcode":"6984",
    "addr:street":"Cnr;St",
    "iso:country":"AU",
    "sg:address":"Cnr Fairbrother & Fisher St",
    "sg:city":"Belmont",
    "sg:classifiers":[
        {
            "category":"Farming",
            "subcategory":"Farm & Veterinary Services",
            "type":"Manufacturing & Wholesale Goods"
        }
    ],
    "sg:phone":"+61 8 9477 2095",
    "sg:postcode":"6984",
    "sg:province":"WA",
    "sg:tags":[
        "irrigation",
        "reticulation",
        "system"
    ],
    "wof:name":"Total Eden Watering Systems",
    "wof:placetype":"venue"
},
  "geometry": {"coordinates":[115.928223,-31.951885],"type":"Point"}
}