{
  "type": "Feature",
  "properties": {
    "addr:full":"Main North Rd Hillbank SA 5112",
    "addr:postcode":"5112",
    "addr:street":"Main North Rd",
    "iso:country":"AU",
    "sg:address":"Main North Rd",
    "sg:city":"Hillbank",
    "sg:classifiers":[
        {
            "category":"Autos & Motor Vehicles",
            "subcategory":"Fuel & Gas Station",
            "type":"Retail Goods"
        }
    ],
    "sg:phone":"+61 8 8255 2270",
    "sg:postcode":"5112",
    "sg:province":"SA",
    "wof:name":"Quix Food Store",
    "wof:placetype":"venue"
},
  "geometry": {"coordinates":[138.677658081,-34.7488059998],"type":"Point"}
}