{
  "type": "Feature",
  "properties": {
    "iso:country":"AU",
    "sg:address":"242 Bawlis St",
    "sg:city":"Wagga Wagga",
    "sg:classifiers":[
        {
            "category":"Manufacturing",
            "subcategory":"Food",
            "type":"Manufacturing & Wholesale Goods"
        }
    ],
    "sg:phone":"+61 2 6931 9131",
    "sg:postcode":"2650",
    "sg:province":"NSW",
    "sg:tags":[
        "function",
        "catering"
    ],
    "wof:name":"H D Cake Decorators",
    "wof:placetype":"venue"
},
  "geometry": {"coordinates":[147.36949157699999,-35.1098709106],"type":"Point"}
}