{
  "type": "Feature",
  "properties": {
    "iso:country":"AU",
    "sg:address":"Hanover Drv",
    "sg:city":"Pialba",
    "sg:classifiers":[
        {
            "category":"Building & Trades",
            "subcategory":"Construction",
            "type":"Services"
        }
    ],
    "sg:phone":"+61 7 4128 3126",
    "sg:postcode":"4655",
    "sg:province":"QLD",
    "sg:tags":[
        "plasterboard",
        "plasterer",
        "fixer"
    ],
    "wof:name":"Brown Joe",
    "wof:placetype":"venue"
},
  "geometry": {"coordinates":[152.81518600000001,-25.306074],"type":"Point"}
}