{
  "type": "Feature",
  "properties": {
    "iso:country":"AU",
    "sg:address":"Hampden St",
    "sg:city":"Dubbo",
    "sg:classifiers":[
        {
            "category":"Education",
            "subcategory":"Kindergarten",
            "type":"Public Place"
        }
    ],
    "sg:phone":"+61 2 6882 2691",
    "sg:postcode":"2830",
    "sg:province":"NSW",
    "sg:tags":[
        "pre-schools"
    ],
    "wof:name":"Dubbo & District Pre-School",
    "wof:placetype":"venue"
},
  "geometry": {"coordinates":[148.617385864,-32.2517814636],"type":"Point"}
}