{
  "type": "Feature",
  "properties": {
    "iso:country":"AU",
    "sg:address":"15 Fitzmaurice St",
    "sg:city":"Kaleen",
    "sg:classifiers":[
        {
            "category":"Health Services",
            "subcategory":"Health Practitioner",
            "type":"Services"
        }
    ],
    "sg:phone":"+61 2 6241 5193",
    "sg:postcode":"2617",
    "sg:province":"ACT",
    "sg:tags":[
        "naturopath"
    ],
    "wof:name":"Irene Hess-Oates",
    "wof:placetype":"venue"
},
  "geometry": {"coordinates":[149.106811523,-35.2312850952],"type":"Point"}
}