{
  "type": "Feature",
  "properties": {
    "iso:country":"AU",
    "sg:address":"PO Box 1784",
    "sg:city":"Wangara",
    "sg:classifiers":[
        {
            "category":"Mining & Drilling",
            "type":"Manufacturing & Wholesale Goods"
        }
    ],
    "sg:phone":"+61 438 099 663",
    "sg:postcode":"6065",
    "sg:province":"WA",
    "sg:tags":[
        "boring",
        "contractor"
    ],
    "wof:name":"Aussie Horizontal Boring",
    "wof:placetype":"venue"
},
  "geometry": {"coordinates":[115.830238342,-31.7956504822],"type":"Point"}
}