{
  "type": "Feature",
  "properties": {
    "addr:full":"206 William St St Albans VIC 3021",
    "addr:housenumber":"206",
    "addr:postcode":"3021",
    "addr:street":"William St",
    "iso:country":"AU",
    "sg:address":"206 William St",
    "sg:city":"St Albans",
    "sg:classifiers":[
        {
            "category":"Retail",
            "subcategory":"Auto Repair",
            "type":"Services"
        }
    ],
    "sg:phone":"+61 3 9366 6409",
    "sg:postcode":"3021",
    "sg:province":"VIC",
    "sg:tags":[
        "beater",
        "painter",
        "panel"
    ],
    "wof:name":"St Albans Panels",
    "wof:placetype":"venue"
},
  "geometry": {"coordinates":[144.79748499999999,-37.735146],"type":"Point"}
}