{
  "type": "Feature",
  "properties": {
    "addr:full":"Shop 2D Sunnybank Hills Shopping Centre Sunnybank Hills QLD 4109",
    "addr:housenumber":"2d",
    "addr:postcode":"4109",
    "iso:country":"AU",
    "sg:address":"Shop 2D Sunnybank Hills Shopping Centre",
    "sg:city":"Sunnybank Hills",
    "sg:classifiers":[
        {
            "category":"Personal",
            "subcategory":"Massage",
            "type":"Services"
        }
    ],
    "sg:phone":"+61 7 3272 5044",
    "sg:postcode":"4109",
    "sg:province":"QLD",
    "sg:tags":[
        "therapy"
    ],
    "wof:name":"Ying Lu",
    "wof:placetype":"venue"
},
  "geometry": {"coordinates":[153.06634521500001,-27.5968093872],"type":"Point"}
}