{
  "type": "Feature",
  "properties": {
    "iso:country":"AU",
    "sg:address":"Unit 2, 6 St James Place,",
    "sg:city":"Seven Hills",
    "sg:classifiers":[
        {
            "category":"Building & Trades",
            "subcategory":"Construction",
            "type":"Services"
        }
    ],
    "sg:phone":"+61 1300 768 995",
    "sg:postcode":"2147",
    "sg:province":"NSW",
    "sg:tags":[
        "fencing",
        "contractor"
    ],
    "wof:name":"A.S.S. Fencing",
    "wof:placetype":"venue"
},
  "geometry": {"coordinates":[150.95300293,-33.7742118835],"type":"Point"}
}