{
  "type": "Feature",
  "properties": {
    "addr:full":"Unit 6 / 2 Garling Rd Kings Park NSW 2148",
    "addr:housenumber":"2",
    "addr:postcode":"2148",
    "addr:street":"Garling Rd",
    "iso:country":"AU",
    "sg:address":"Unit 6 / 2 Garling Rd",
    "sg:city":"Kings Park",
    "sg:classifiers":[
        {
            "category":"Retail",
            "subcategory":"Auto Rental",
            "type":"Services"
        }
    ],
    "sg:phone":"+61 2 9672 3860",
    "sg:postcode":"2148",
    "sg:province":"NSW",
    "sg:tags":[
        "chauffeur",
        "car",
        "hire",
        "driven",
        "limousine"
    ],
    "sg:website":"http://www.aaalimousines.com",
    "wof:name":"AAA Limousines",
    "wof:placetype":"venue"
},
  "geometry": {"coordinates":[150.91604614299999,-33.745475769],"type":"Point"}
}