{
  "type": "Feature",
  "properties": {
    "addr:full":"Cnr Seabeach Pde & Madden Ave North Shore VIC 3214",
    "addr:postcode":"3214",
    "addr:street":"Cnr Seabeach;Ave",
    "iso:country":"AU",
    "sg:address":"Cnr Seabeach Pde & Madden Ave",
    "sg:city":"North Shore",
    "sg:classifiers":[
        {
            "category":"Utilities",
            "subcategory":"Cable",
            "type":"Services"
        }
    ],
    "sg:phone":"+61 3 5228 1281",
    "sg:postcode":"3214",
    "sg:province":"VIC",
    "sg:tags":[
        "wholesaler",
        "wire",
        "mfrs"
    ],
    "wof:name":"Onesteel Wire Pty Limited",
    "wof:placetype":"venue"
},
  "geometry": {"coordinates":[144.371780395,-38.0998306274],"type":"Point"}
}