{
  "type": "Feature",
  "properties": {
    "iso:country":"AU",
    "sg:address":"Unit1/ 62 Shelley Rd",
    "sg:city":"Moruya",
    "sg:classifiers":[
        {
            "category":"Building & Trades",
            "subcategory":"Construction",
            "type":"Services"
        }
    ],
    "sg:phone":"+61 2 4474 5507",
    "sg:postcode":"2537",
    "sg:province":"NSW",
    "sg:tags":[
        "builder",
        "designer",
        "room",
        "cool"
    ],
    "wof:name":"James Coolrooms",
    "wof:placetype":"venue"
},
  "geometry": {"coordinates":[150.08912658700001,-35.8778572083],"type":"Point"}
}