{
  "type": "Feature",
  "properties": {
    "addr:full":"PO Box 223 Heathcote Junction VIC 3758",
    "addr:postcode":"3758",
    "iso:country":"AU",
    "sg:address":"PO Box 223",
    "sg:city":"Heathcote Junction",
    "sg:classifiers":[
        {
            "category":"Industrial Area",
            "type":"Public Place"
        }
    ],
    "sg:phone":"+61 3 5787 1744",
    "sg:postcode":"3758",
    "sg:province":"VIC",
    "sg:tags":[
        "protective",
        "clothing"
    ],
    "wof:name":"Brewer Designs",
    "wof:placetype":"venue"
},
  "geometry": {"coordinates":[145.026276,-37.369041],"type":"Point"}
}