{
  "type": "Feature",
  "properties": {
    "addr:full":"54c Fairfield Rd Guildford West NSW 2161",
    "addr:housenumber":"54c",
    "addr:postcode":"2161",
    "addr:street":"Fairfield Rd",
    "iso:country":"AU",
    "sg:address":"54c Fairfield Rd",
    "sg:city":"Guildford West",
    "sg:classifiers":[
        {
            "category":"Autos & Motor Vehicles",
            "subcategory":"Fuel & Gas Station",
            "type":"Retail Goods"
        }
    ],
    "sg:phone":"+61 2 9632 9075",
    "sg:postcode":"2161",
    "sg:province":"NSW",
    "wof:name":"Gas On Line",
    "wof:placetype":"venue"
},
  "geometry": {"coordinates":[150.962646484,-33.8456077576],"type":"Point"}
}