{
  "type": "Feature",
  "properties": {
    "addr:full":"38 Wattle Park Ave Moolap VIC 3221",
    "addr:housenumber":"38",
    "addr:postcode":"3221",
    "addr:street":"Wattle Park Ave",
    "iso:country":"AU",
    "sg:address":"38 Wattle Park Ave",
    "sg:city":"Moolap",
    "sg:classifiers":[
        {
            "category":"Wholesale",
            "subcategory":"Auto Parts",
            "type":"Manufacturing & Wholesale Goods"
        }
    ],
    "sg:phone":"+61 3 5248 1221",
    "sg:postcode":"3221",
    "sg:province":"VIC",
    "sg:tags":[
        "recyclers"
    ],
    "wof:name":"Wattle Park Auto Wreckers",
    "wof:placetype":"venue"
},
  "geometry": {"coordinates":[144.40879799999999,-38.166256],"type":"Point"}
}