{
  "type": "Feature",
  "properties": {
    "addr:full":"18 Inala Crt Lemon Tree Passage NSW 2319",
    "addr:housenumber":"18",
    "addr:postcode":"2319",
    "addr:street":"Inala Crt",
    "iso:country":"AU",
    "sg:address":"18 Inala Crt",
    "sg:city":"Lemon Tree Passage",
    "sg:classifiers":[
        {
            "category":"Shopping",
            "subcategory":"Computers & Home Electronics",
            "type":"Retail Goods"
        }
    ],
    "sg:phone":"+61 2 4984 5407",
    "sg:postcode":"2319",
    "sg:province":"NSW",
    "sg:tags":[
        "hire",
        "video",
        "game"
    ],
    "wof:name":"Races Edge",
    "wof:placetype":"venue"
},
  "geometry": {"coordinates":[152.03671299999999,-32.729294],"type":"Point"}
}