{
  "type": "Feature",
  "properties": {
    "iso:country":"AU",
    "sg:address":"83 Wright St",
    "sg:city":"Middle Park",
    "sg:classifiers":[
        {
            "category":"Building & Trades",
            "subcategory":"Pest Control",
            "type":"Services"
        }
    ],
    "sg:phone":"+61 3 9686 1611",
    "sg:postcode":"3206",
    "sg:province":"VIC",
    "wof:name":"Specialized White Ant Control",
    "wof:placetype":"venue"
},
  "geometry": {"coordinates":[144.95820599999999,-37.849609],"type":"Point"}
}