{
  "type": "Feature",
  "properties": {
    "addr:full":"2 Watkins St Aspendale VIC 3195",
    "addr:housenumber":"2",
    "addr:postcode":"3195",
    "addr:street":"Watkins St",
    "iso:country":"AU",
    "sg:address":"2 Watkins St",
    "sg:city":"Aspendale",
    "sg:classifiers":[
        {
            "category":"Arts & Performance",
            "subcategory":"Theater",
            "type":"Entertainment"
        }
    ],
    "sg:phone":"+61 3 9587 6967",
    "sg:postcode":"3195",
    "sg:province":"VIC",
    "sg:tags":[
        "theatrical",
        "supply"
    ],
    "wof:name":"Custom Crewing",
    "wof:placetype":"venue"
},
  "geometry": {"coordinates":[145.09075927699999,-38.0137557983],"type":"Point"}
}