{
  "type": "Feature",
  "properties": {
    "addr:full":"34 William St Devonport TAS 7310",
    "addr:housenumber":"34",
    "addr:postcode":"7310",
    "addr:street":"William St",
    "iso:country":"AU",
    "sg:address":"34 William St",
    "sg:city":"Devonport",
    "sg:classifiers":[
        {
            "category":"Retail",
            "subcategory":"Self-service Laundry",
            "type":"Services"
        }
    ],
    "sg:phone":"+61 3 6424 4453",
    "sg:postcode":"7310",
    "sg:province":"TAS",
    "wof:name":"Devonport Laundromat",
    "wof:placetype":"venue"
},
  "geometry": {"coordinates":[146.34889221200001,-41.186580658],"type":"Point"}
}