{
  "type": "Feature",
  "properties": {
    "iso:country":"AU",
    "sg:address":"Noosa Blue Resort 16 Noosa Drv",
    "sg:city":"Noosa Heads",
    "sg:classifiers":[
        {
            "category":"Sports & Exercise",
            "subcategory":"Gym",
            "type":"Entertainment"
        }
    ],
    "sg:phone":"+61 1300 556 192",
    "sg:postcode":"4567",
    "sg:province":"QLD",
    "sg:tags":[
        "health",
        "fitness"
    ],
    "wof:name":"FIT Noosa",
    "wof:placetype":"venue"
},
  "geometry": {"coordinates":[153.08963012699999,-26.3924446106],"type":"Point"}
}