{
  "type": "Feature",
  "properties": {
    "iso:country":"AU",
    "sg:address":"676 Old Barnawartha Rd",
    "sg:city":"null",
    "sg:classifiers":[
        {
            "category":"Home & Garden",
            "subcategory":"Carpets & Floor Coverings",
            "type":"Retail Goods"
        }
    ],
    "sg:phone":"+61 419 478 465",
    "sg:postcode":"3688",
    "sg:province":"VIC",
    "sg:tags":[
        "layer",
        "planner"
    ],
    "wof:name":"HJ & RJ Smith",
    "wof:placetype":"venue"
},
  "geometry": {"coordinates":[146.775512695,-36.0793762207],"type":"Point"}
}