{
  "type": "Feature",
  "properties": {
    "addr:full":"Jones Ave Deniliquin NSW 2710",
    "addr:postcode":"2710",
    "addr:street":"Jones Ave",
    "iso:country":"AU",
    "sg:address":"Jones Ave",
    "sg:city":"Deniliquin",
    "sg:classifiers":[
        {
            "category":"Retail",
            "subcategory":"Auto Repair",
            "type":"Services"
        }
    ],
    "sg:phone":"+61 3 5881 7855",
    "sg:postcode":"2710",
    "sg:province":"NSW",
    "sg:tags":[
        "repairer",
        "motor",
        "engineer"
    ],
    "wof:name":"Expert Air & Mechanical Repairs",
    "wof:placetype":"venue"
},
  "geometry": {"coordinates":[144.97430419899999,-35.5281944275],"type":"Point"}
}