{
  "type": "Feature",
  "properties": {
    "addr:full":"42 Kimberley Crs Fairfield West NSW 2165",
    "addr:housenumber":"42",
    "addr:postcode":"2165",
    "addr:street":"Kimberley Crs",
    "iso:country":"AU",
    "sg:address":"42 Kimberley Crs",
    "sg:city":"Fairfield West",
    "sg:classifiers":[
        {
            "category":"Insurance",
            "subcategory":"Insurance Agent",
            "type":"Services"
        }
    ],
    "sg:phone":"+61 411 858 765",
    "sg:postcode":"2165",
    "sg:province":"NSW",
    "sg:tags":[
        "bloodstock"
    ],
    "wof:name":"Tried & True",
    "wof:placetype":"venue"
},
  "geometry": {"coordinates":[150.92300415,-33.8691596985],"type":"Point"}
}