{
  "type": "Feature",
  "properties": {
    "iso:country":"AU",
    "sg:address":"48 Nerang St",
    "sg:city":"Southport",
    "sg:classifiers":[
        {
            "category":"Food & Beverages",
            "subcategory":"Bakery",
            "type":"Retail Goods"
        }
    ],
    "sg:phone":"+61 7 5532 2633",
    "sg:postcode":"4215",
    "sg:province":"QLD",
    "sg:tags":[
        "cake",
        "shop",
        "pastry"
    ],
    "wof:name":"Southport Home Bakery",
    "wof:placetype":"venue"
},
  "geometry": {"coordinates":[153.413574219,-27.9679546356],"type":"Point"}
}