{
  "type": "Feature",
  "properties": {
    "addr:full":"7 Park St Coffs Harbour NSW 2450",
    "addr:housenumber":"7",
    "addr:postcode":"2450",
    "addr:street":"Park St",
    "iso:country":"AU",
    "sg:address":"7 Park St",
    "sg:city":"Coffs Harbour",
    "sg:classifiers":[
        {
            "category":"Food & Beverages",
            "subcategory":"Liquor & Beverages",
            "type":"Retail Goods"
        }
    ],
    "sg:phone":"+61 2 6652 6866",
    "sg:postcode":"2450",
    "sg:province":"NSW",
    "sg:tags":[
        "store"
    ],
    "wof:name":"Macs Liquor",
    "wof:placetype":"venue"
},
  "geometry": {"coordinates":[153.10218810999999,-30.3733119965],"type":"Point"}
}