{
  "type": "Feature",
  "properties": {
    "iso:country":"AU",
    "sg:address":"Shp4/ 176 Seacombe Rd",
    "sg:city":"Seaview Downs",
    "sg:classifiers":[
        {
            "category":"Personal",
            "subcategory":"Beauty Salon",
            "type":"Services"
        }
    ],
    "sg:phone":"+61 8 8377 2115",
    "sg:postcode":"5049",
    "sg:province":"SA",
    "sg:tags":[
        "hairdresser"
    ],
    "wof:name":"Tigers Eye Hair",
    "wof:placetype":"venue"
},
  "geometry": {"coordinates":[138.53907799999999,-35.029556],"type":"Point"}
}