{
  "type": "Feature",
  "properties": {
    "addr:full":"223 South Rd Brighton East VIC 3187",
    "addr:housenumber":"223",
    "addr:postcode":"3187",
    "addr:street":"South Rd",
    "iso:country":"AU",
    "sg:address":"223 South Rd",
    "sg:city":"Brighton East",
    "sg:classifiers":[
        {
            "category":"Social Services",
            "type":"Services"
        }
    ],
    "sg:phone":"+61 3 9592 8039",
    "sg:postcode":"3187",
    "sg:province":"VIC",
    "sg:tags":[
        "kinesiology"
    ],
    "wof:name":"Mooney Jacqu\ufffd",
    "wof:placetype":"venue"
},
  "geometry": {"coordinates":[145.01324462900001,-37.9301605225],"type":"Point"}
}