{
  "type": "Feature",
  "properties": {
    "iso:country":"AU",
    "sg:address":"255 - 257 Boundary Rd",
    "sg:city":"Braeside",
    "sg:classifiers":[
        {
            "category":"Manufacturing",
            "subcategory":"Building Materials",
            "type":"Manufacturing & Wholesale Goods"
        }
    ],
    "sg:phone":"+61 3 9580 3911",
    "sg:postcode":"3195",
    "sg:province":"VIC",
    "sg:tags":[
        "machinery",
        "secondhand"
    ],
    "wof:name":"Southern Cross Compressors",
    "wof:placetype":"venue"
},
  "geometry": {"coordinates":[145.10627746599999,-37.9937705994],"type":"Point"}
}