{
  "type": "Feature",
  "properties": {
    "addr:full":"Cnr Heatherton Rd & James Cook Drv Endeavour Hills VIC 3802",
    "addr:postcode":"3802",
    "addr:street":"Cnr Heatherton Rd & James Cook Drv",
    "iso:country":"AU",
    "sg:address":"Cnr Heatherton Rd & James Cook Drv",
    "sg:city":"Endeavour Hills",
    "sg:classifiers":[
        {
            "category":"Health Services",
            "subcategory":"Chiropractor",
            "type":"Services"
        }
    ],
    "sg:phone":"+61 3 9700 2145",
    "sg:postcode":"3802",
    "sg:province":"VIC",
    "wof:name":"Missakian Vahe Dr",
    "wof:placetype":"venue"
},
  "geometry": {"coordinates":[145.25526428200001,-37.9744415283],"type":"Point"}
}