{
  "type": "Feature",
  "properties": {
    "addr:full":"Camford Sqr, Unit 2/ 10 Dorsey St Milton QLD 4064",
    "addr:housenumber":"10",
    "addr:postcode":"4064",
    "addr:street":"Camford Sqr;Dorsey St",
    "iso:country":"AU",
    "sg:address":"Camford Sqr, Unit 2/ 10 Dorsey St",
    "sg:city":"Milton",
    "sg:classifiers":[
        {
            "category":"Wholesale",
            "subcategory":"Home Furnishings",
            "type":"Manufacturing & Wholesale Goods"
        }
    ],
    "sg:phone":"+61 7 3217 6114",
    "sg:postcode":"4064",
    "sg:province":"QLD",
    "sg:tags":[
        "tile",
        "wholesaler",
        "mfrs",
        "carpet"
    ],
    "wof:name":"Tuftmaster Carpets Pty Ltd",
    "wof:placetype":"venue"
},
  "geometry": {"coordinates":[153.00163269000001,-27.4720916748],"type":"Point"}
}