{
  "type": "Feature",
  "properties": {
    "addr:full":"561-573 Doncaster Rd Doncaster VIC 3108",
    "addr:housenumber":"561-573",
    "addr:postcode":"3108",
    "addr:street":"Doncaster Rd",
    "iso:country":"AU",
    "sg:address":"561-573 Doncaster Rd",
    "sg:city":"Doncaster",
    "sg:classifiers":[
        {
            "category":"Manufacturing",
            "subcategory":"Motor Vehicles & Parts",
            "type":"Manufacturing & Wholesale Goods"
        }
    ],
    "sg:phone":"+61 3 9848 9000",
    "sg:postcode":"3108",
    "sg:province":"VIC",
    "sg:tags":[
        "replacement"
    ],
    "wof:name":"Bentley Lance Dixon",
    "wof:placetype":"venue"
},
  "geometry": {"coordinates":[145.12083435100001,-37.7878761292],"type":"Point"}
}