{
  "type": "Feature",
  "properties": {
    "iso:country":"AU",
    "sg:address":"129 Wright St",
    "sg:city":"Devonport",
    "sg:classifiers":[
        {
            "category":"Professional",
            "subcategory":"Printing & Photocopies",
            "type":"Services"
        }
    ],
    "sg:phone":"+61 3 6427 9655",
    "sg:postcode":"7310",
    "sg:province":"TAS",
    "sg:tags":[
        "screen",
        "printer"
    ],
    "wof:name":"The Signmakers",
    "wof:placetype":"venue"
},
  "geometry": {"coordinates":[146.36907959000001,-41.1857795715],"type":"Point"}
}