{
  "type": "Feature",
  "properties": {
    "addr:full":"1132 Burke Rd Balwyn North VIC 3104",
    "addr:housenumber":"1132",
    "addr:postcode":"3104",
    "addr:street":"Burke Rd",
    "iso:country":"AU",
    "sg:address":"1132 Burke Rd",
    "sg:city":"Balwyn North",
    "sg:classifiers":[
        {
            "category":"Autos & Motor Vehicles",
            "subcategory":"Auto Supplies",
            "type":"Retail Goods"
        }
    ],
    "sg:phone":"+61 3 9859 5444",
    "sg:postcode":"3104",
    "sg:province":"VIC",
    "sg:tags":[
        "transmission",
        "equipment",
        "power"
    ],
    "wof:name":"Fuji Electric",
    "wof:placetype":"venue"
},
  "geometry": {"coordinates":[145.063995361,-37.794090271],"type":"Point"}
}