{
  "type": "Feature",
  "properties": {
    "addr:full":"36 Pegasus Ave Eatons Hill QLD 4037",
    "addr:housenumber":"36",
    "addr:postcode":"4037",
    "addr:street":"Pegasus Ave",
    "iso:country":"AU",
    "sg:address":"36 Pegasus Ave",
    "sg:city":"Eatons Hill",
    "sg:classifiers":[
        {
            "category":"Building & Trades",
            "subcategory":"Plumbing",
            "type":"Services"
        }
    ],
    "sg:phone":"+61 411 600 217",
    "sg:postcode":"4037",
    "sg:province":"QLD",
    "sg:tags":[
        "plumber",
        "gasfitters"
    ],
    "wof:name":"N E Plumbing Pty Ltd",
    "wof:placetype":"venue"
},
  "geometry": {"coordinates":[152.95416299999999,-27.33779],"type":"Point"}
}