{
  "type": "Feature",
  "properties": {
    "iso:country":"AU",
    "sg:address":"King St",
    "sg:city":"Myrtleford",
    "sg:classifiers":[
        {
            "category":"Food & Beverages",
            "subcategory":"Specialty",
            "type":"Retail Goods"
        }
    ],
    "sg:phone":"+61 3 5752 1350",
    "sg:postcode":"3737",
    "sg:province":"VIC",
    "sg:tags":[
        "ice",
        "supply"
    ],
    "wof:name":"Bynon's Party Ice",
    "wof:placetype":"venue"
},
  "geometry": {"coordinates":[146.720306397,-36.5595664978],"type":"Point"}
}