{
  "type": "Feature",
  "properties": {
    "addr:full":"7 Newcastle Rd Bayswater VIC 3153",
    "addr:housenumber":"7",
    "addr:postcode":"3153",
    "addr:street":"Newcastle Rd",
    "iso:country":"AU",
    "sg:address":"7 Newcastle Rd",
    "sg:city":"Bayswater",
    "sg:classifiers":[
        {
            "category":"Professional",
            "subcategory":"Engineering",
            "type":"Services"
        }
    ],
    "sg:phone":"+61 3 9720 7992",
    "sg:postcode":"3153",
    "sg:province":"VIC",
    "sg:tags":[
        "engineer"
    ],
    "wof:name":"C.N.C. Solutions Pty Ltd",
    "wof:placetype":"venue"
},
  "geometry": {"coordinates":[145.28306579599999,-37.8439178467],"type":"Point"}
}