{
  "type": "Feature",
  "properties": {
    "iso:country":"AU",
    "sg:address":"613 Mount Cottrell Rd",
    "sg:city":"Rockbank",
    "sg:classifiers":[
        {
            "category":"Building & Trades",
            "subcategory":"Construction",
            "type":"Services"
        }
    ],
    "sg:phone":"+61 3 9747 9683",
    "sg:postcode":"3335",
    "sg:province":"VIC",
    "sg:tags":[
        "plasterboard",
        "plasterer",
        "fixer"
    ],
    "wof:name":"C & S Kimpton",
    "wof:placetype":"venue"
},
  "geometry": {"coordinates":[144.62262000000001,-37.692692],"type":"Point"}
}