{
  "type": "Feature",
  "properties": {
    "addr:full":"PO Box 258 Maryborough QLD 4650",
    "addr:postcode":"4650",
    "iso:country":"AU",
    "sg:address":"PO Box 258",
    "sg:city":"Maryborough",
    "sg:classifiers":[
        {
            "category":"Arena",
            "subcategory":"Sports Club",
            "type":"Entertainment"
        }
    ],
    "sg:phone":"+61 7 4129 2507",
    "sg:postcode":"4650",
    "sg:province":"QLD",
    "sg:tags":[
        "australian",
        "football",
        "rule"
    ],
    "wof:name":"Maryborough Australian Rules Football Club",
    "wof:placetype":"venue"
},
  "geometry": {"coordinates":[152.69215399999999,-25.535271],"type":"Point"}
}