{
  "type": "Feature",
  "properties": {
    "addr:full":"200 Main Rd Toukley NSW 2263",
    "addr:housenumber":"200",
    "addr:postcode":"2263",
    "addr:street":"Main Rd",
    "iso:country":"AU",
    "sg:address":"200 Main Rd",
    "sg:city":"Toukley",
    "sg:classifiers":[
        {
            "category":"Travel",
            "subcategory":"Hotels & Motels",
            "type":"Entertainment"
        }
    ],
    "sg:phone":"+61 1800 621 696",
    "sg:postcode":"2263",
    "sg:province":"NSW",
    "wof:name":"Beachcomber The",
    "wof:placetype":"venue"
},
  "geometry": {"coordinates":[151.54319799999999,-33.264225],"type":"Point"}
}