{
  "type": "Feature",
  "properties": {
    "addr:full":"8 Levanswell Rd Moorabbin VIC 3189",
    "addr:housenumber":"8",
    "addr:postcode":"3189",
    "addr:street":"Levanswell Rd",
    "iso:country":"AU",
    "sg:address":"8 Levanswell Rd",
    "sg:city":"Moorabbin",
    "sg:classifiers":[
        {
            "category":"Shopping",
            "subcategory":"Clothing, Apparel, & Fashions",
            "type":"Retail Goods"
        }
    ],
    "sg:phone":"+61 3 9532 5777",
    "sg:postcode":"3189",
    "sg:province":"VIC",
    "sg:tags":[
        "menswear"
    ],
    "wof:name":"Bravado",
    "wof:placetype":"venue"
},
  "geometry": {"coordinates":[145.06123352,-37.944316864],"type":"Point"}
}