{
  "type": "Feature",
  "properties": {
    "addr:full":"89 Flinders La Melbourne VIC 3000",
    "addr:housenumber":"89",
    "addr:postcode":"3000",
    "addr:street":"Flinders La",
    "iso:country":"AU",
    "sg:address":"89 Flinders La",
    "sg:city":"Melbourne",
    "sg:classifiers":[
        {
            "category":"Conference Center",
            "type":"Public Place"
        }
    ],
    "sg:phone":"+61 3 9650 1196",
    "sg:postcode":"3000",
    "sg:province":"VIC",
    "sg:tags":[
        "venue",
        "convention"
    ],
    "wof:name":"Swiss Club Of Victoria",
    "wof:placetype":"venue"
},
  "geometry": {"coordinates":[144.971359253,-37.8153114319],"type":"Point"}
}