{
  "type": "Feature",
  "properties": {
    "iso:country":"AU",
    "sg:address":"144 Burns Bay Rd",
    "sg:city":"Lane Cove",
    "sg:classifiers":[
        {
            "category":"Health Services",
            "subcategory":"Dentist",
            "type":"Services"
        }
    ],
    "sg:phone":"+61 2 9420 2888",
    "sg:postcode":"2066",
    "sg:province":"NSW",
    "wof:name":"O'Brien, Cassandra",
    "wof:placetype":"venue"
},
  "geometry": {"coordinates":[151.15872192399999,-33.8144302368],"type":"Point"}
}