{
  "type": "Feature",
  "properties": {
    "iso:country":"AU",
    "sg:address":"31 Thomson St",
    "sg:city":"Belmont",
    "sg:classifiers":[
        {
            "category":"Personal",
            "subcategory":"Massage",
            "type":"Services"
        }
    ],
    "sg:phone":"+61 409 014 871",
    "sg:postcode":"3216",
    "sg:province":"VIC",
    "sg:tags":[
        "therapy"
    ],
    "wof:name":"Sandi Dwyer",
    "wof:placetype":"venue"
},
  "geometry": {"coordinates":[144.34231567399999,-38.1733856201],"type":"Point"}
}