{
  "type": "Feature",
  "properties": {
    "addr:full":"67 Links Ave North Eagle Farm QLD 4009",
    "addr:housenumber":"67",
    "addr:postcode":"4009",
    "addr:street":"Links Ave North",
    "iso:country":"AU",
    "sg:address":"67 Links Ave North",
    "sg:city":"Eagle Farm",
    "sg:classifiers":[
        {
            "category":"Shopping",
            "subcategory":"Mobile Phones",
            "type":"Retail Goods"
        }
    ],
    "sg:phone":"+61 7 3868 6000",
    "sg:postcode":"4009",
    "sg:province":"QLD",
    "sg:tags":[
        "telephone",
        "accessory"
    ],
    "wof:name":"Fone Zone",
    "wof:placetype":"venue"
},
  "geometry": {"coordinates":[153.08755493199999,-27.4342288971],"type":"Point"}
}