{
  "type": "Feature",
  "properties": {
    "addr:full":"168 Macquarie St Dubbo NSW 2830",
    "addr:housenumber":"168",
    "addr:postcode":"2830",
    "addr:street":"Macquarie St",
    "iso:country":"AU",
    "sg:address":"168 Macquarie St",
    "sg:city":"Dubbo",
    "sg:classifiers":[
        {
            "category":"Banks & Credit Unions",
            "subcategory":"Bank",
            "type":"Services"
        }
    ],
    "sg:phone":"+61 13 24 40",
    "sg:postcode":"2830",
    "sg:province":"NSW",
    "sg:tags":[
        "society"
    ],
    "wof:name":"Reliance Credit Union Ltd",
    "wof:placetype":"venue"
},
  "geometry": {"coordinates":[148.601272583,-32.2482681274],"type":"Point"}
}