{
  "type": "Feature",
  "properties": {
    "addr:full":"42 Outram St West Perth WA 6005",
    "addr:housenumber":"42",
    "addr:postcode":"6005",
    "addr:street":"Outram St",
    "iso:country":"AU",
    "sg:address":"42 Outram St",
    "sg:city":"West Perth",
    "sg:classifiers":[
        {
            "category":"Health Services",
            "subcategory":"Doctor",
            "type":"Services"
        }
    ],
    "sg:phone":"+61 8 9321 5923",
    "sg:postcode":"6005",
    "sg:province":"WA",
    "sg:tags":[
        "medical",
        "practitioner"
    ],
    "wof:name":"Anastas N C",
    "wof:placetype":"venue"
},
  "geometry": {"coordinates":[115.839569092,-31.9491710663],"type":"Point"}
}