{
  "type": "Feature",
  "properties": {
    "addr:full":"Exchange Pde Narellan NSW 2567",
    "addr:postcode":"2567",
    "addr:street":"Exchange",
    "iso:country":"AU",
    "sg:address":"Exchange Pde",
    "sg:city":"Narellan",
    "sg:classifiers":[
        {
            "category":"Personal",
            "subcategory":"Beauty Salon",
            "type":"Services"
        }
    ],
    "sg:phone":"+61 2 4647 9711",
    "sg:postcode":"2567",
    "sg:province":"NSW",
    "sg:tags":[
        "supply",
        "artist",
        "make-up"
    ],
    "wof:name":"About Face",
    "wof:placetype":"venue"
},
  "geometry": {"coordinates":[150.748703003,-34.0394439697],"type":"Point"}
}