{
  "type": "Feature",
  "properties": {
    "iso:country":"AU",
    "sg:address":"29 Scrivener St",
    "sg:city":"Warwick Farm",
    "sg:classifiers":[
        {
            "category":"Professional",
            "subcategory":"Art Services",
            "type":"Services"
        }
    ],
    "sg:phone":"+61 2 9600 9730",
    "sg:postcode":"2170",
    "sg:province":"NSW",
    "sg:tags":[
        "interior",
        "decorator"
    ],
    "wof:name":"Interior Soft Furnishings",
    "wof:placetype":"venue"
},
  "geometry": {"coordinates":[150.93768310600001,-33.9185371399],"type":"Point"}
}