{
  "type": "Feature",
  "properties": {
    "iso:country":"AU",
    "sg:address":"Albatross Rd",
    "sg:city":"Nowra",
    "sg:classifiers":[
        {
            "category":"Education",
            "subcategory":"Special Training",
            "type":"Public Place"
        }
    ],
    "sg:phone":"+61 2 4421 0878",
    "sg:postcode":"2540",
    "sg:province":"NSW",
    "sg:tags":[
        "development"
    ],
    "wof:name":"Aerospace Training Services",
    "wof:placetype":"venue"
},
  "geometry": {"coordinates":[150.55670165999999,-34.9359397888],"type":"Point"}
}