{
  "type": "Feature",
  "properties": {
    "iso:country":"AU",
    "sg:address":"116 Military Rd",
    "sg:city":"Neutral Bay",
    "sg:classifiers":[
        {
            "category":"Professional",
            "subcategory":"Art Services",
            "type":"Services"
        }
    ],
    "sg:phone":"+61 2 9953 0055",
    "sg:postcode":"2089",
    "sg:province":"NSW",
    "sg:tags":[
        "graphic",
        "designer"
    ],
    "wof:name":"Big Bear Car Clinic",
    "wof:placetype":"venue"
},
  "geometry": {"coordinates":[151.219314575,-33.830242157],"type":"Point"}
}