{
  "type": "Feature",
  "properties": {
    "addr:full":"Pacific Hwy Taree NSW 2430",
    "addr:postcode":"2430",
    "addr:street":"Pacific Hwy",
    "iso:country":"AU",
    "sg:address":"Pacific Hwy",
    "sg:city":"Taree",
    "sg:classifiers":[
        {
            "category":"Health Services",
            "subcategory":"Doctor",
            "type":"Services"
        }
    ],
    "sg:phone":"+61 2 6552 2154",
    "sg:postcode":"2430",
    "sg:province":"NSW",
    "sg:tags":[
        "medical",
        "practitioner"
    ],
    "wof:name":"Great Lakes/Manning Aboriginal Childrens Service",
    "wof:placetype":"venue"
},
  "geometry": {"coordinates":[152.48384100000001,-31.936878],"type":"Point"}
}