{
  "type": "Feature",
  "properties": {
    "iso:country":"AU",
    "sg:address":"45 York St",
    "sg:city":"Beenleigh",
    "sg:classifiers":[
        {
            "category":"Health Services",
            "subcategory":"Nursing And Care Facility",
            "type":"Services"
        }
    ],
    "sg:phone":"+61 7 3287 2700",
    "sg:postcode":"4207",
    "sg:province":"QLD",
    "sg:tags":[
        "home"
    ],
    "wof:name":"Beenleigh Nursing Home",
    "wof:placetype":"venue"
},
  "geometry": {"coordinates":[153.20149230999999,-27.7128562927],"type":"Point"}
}