{
  "type": "Feature",
  "properties": {
    "addr:full":"Level 2, 20 Queens Rd Melbourne VIC 3000",
    "addr:housenumber":"20",
    "addr:postcode":"3000",
    "addr:street":"Queens Rd",
    "iso:country":"AU",
    "sg:address":"Level 2, 20 Queens Rd",
    "sg:city":"Melbourne",
    "sg:classifiers":[
        {
            "category":"Professional",
            "subcategory":"Art Services",
            "type":"Services"
        }
    ],
    "sg:phone":"+61 3 9866 3380",
    "sg:postcode":"3000",
    "sg:province":"VIC",
    "sg:tags":[
        "graphic",
        "designer"
    ],
    "wof:name":"Richard McKellar Design",
    "wof:placetype":"venue"
},
  "geometry": {"coordinates":[144.97482299800001,-37.84034729],"type":"Point"}
}