{
  "type": "Feature",
  "properties": {
    "iso:country":"AU",
    "sg:address":"140 Bentons Rd",
    "sg:city":"Mt Martha",
    "sg:classifiers":[
        {
            "category":"Social Services",
            "subcategory":"Child Care",
            "type":"Services"
        }
    ],
    "sg:phone":"+61 3 5976 2811",
    "sg:postcode":"3934",
    "sg:province":"VIC",
    "wof:name":"ABC Learning Centres",
    "wof:placetype":"venue"
},
  "geometry": {"coordinates":[145.04991149899999,-38.2473526001],"type":"Point"}
}