{
  "type": "Feature",
  "properties": {
    "addr:full":"21 Stockton Rd Nelson Bay NSW 2315",
    "addr:housenumber":"21",
    "addr:postcode":"2315",
    "addr:street":"Stockton Rd",
    "iso:country":"AU",
    "sg:address":"21 Stockton Rd",
    "sg:city":"Nelson Bay",
    "sg:classifiers":[
        {
            "category":"Recreation",
            "subcategory":"Fishing",
            "type":"Entertainment"
        }
    ],
    "sg:phone":"+61 2 4981 4445",
    "sg:postcode":"2315",
    "sg:province":"NSW",
    "sg:tags":[
        "tackle"
    ],
    "wof:name":"Steadys Tackle & Bait",
    "wof:placetype":"venue"
},
  "geometry": {"coordinates":[152.14361600000001,-32.722137],"type":"Point"}
}