{
  "type": "Feature",
  "properties": {
    "addr:full":"1/116 Gardenvale Rd Elsternwick VIC 3185",
    "addr:housenumber":"/ 116",
    "addr:postcode":"3185",
    "addr:street":"Gardenvale Rd",
    "iso:country":"AU",
    "sg:address":"1/116 Gardenvale Rd",
    "sg:city":"Elsternwick",
    "sg:classifiers":[
        {
            "category":"Professional",
            "subcategory":"Accounting & Tax Preparation",
            "type":"Services"
        }
    ],
    "sg:phone":"+61 3 9532 4280",
    "sg:postcode":"3185",
    "sg:province":"VIC",
    "sg:tags":[
        "consultant",
        "taxation"
    ],
    "wof:name":"I.T.P. The Income Tax Professionals",
    "wof:placetype":"venue"
},
  "geometry": {"coordinates":[145.00685119600001,-37.8976020813],"type":"Point"}
}