{
  "type": "Feature",
  "properties": {
    "addr:full":"117 Clayton St Ballarat VIC 3350",
    "addr:housenumber":"117",
    "addr:postcode":"3350",
    "addr:street":"Clayton St",
    "iso:country":"AU",
    "sg:address":"117 Clayton St",
    "sg:city":"Ballarat",
    "sg:classifiers":[
        {
            "category":"Building & Trades",
            "subcategory":"Construction",
            "type":"Services"
        }
    ],
    "sg:phone":"+61 419 537 721",
    "sg:postcode":"3350",
    "sg:province":"VIC",
    "sg:tags":[
        "home",
        "air conditioning"
    ],
    "wof:name":"Sasair",
    "wof:placetype":"venue"
},
  "geometry": {"coordinates":[143.87286399999999,-37.57193],"type":"Point"}
}