{
  "type": "Feature",
  "properties": {
    "addr:full":"26/ 11 Gilbert St Dover Heights NSW 2030",
    "addr:housenumber":"26 / 11",
    "addr:postcode":"2030",
    "addr:street":"Gilbert St Dover",
    "iso:country":"AU",
    "sg:address":"26/ 11 Gilbert St",
    "sg:city":"Dover Heights",
    "sg:classifiers":[
        {
            "category":"Real Estate",
            "subcategory":"Real Estate Operator",
            "type":"Services"
        }
    ],
    "sg:phone":"+61 409 995 204",
    "sg:postcode":"2030",
    "sg:province":"NSW",
    "sg:tags":[
        "concrete",
        "pumping"
    ],
    "wof:name":"No Barrows Concrete Pumping Pty Ltd",
    "wof:placetype":"venue"
},
  "geometry": {"coordinates":[151.278366089,-33.8708152771],"type":"Point"}
}