{
  "type": "Feature",
  "properties": {
    "addr:full":"172 Roden St West Melbourne VIC 3003",
    "addr:housenumber":"172",
    "addr:postcode":"3003",
    "addr:street":"Roden St",
    "iso:country":"AU",
    "sg:address":"172 Roden St",
    "sg:city":"West Melbourne",
    "sg:classifiers":[
        {
            "category":"Autos & Motor Vehicles",
            "subcategory":"Auto Supplies",
            "type":"Retail Goods"
        }
    ],
    "sg:phone":"+61 3 9329 8200",
    "sg:postcode":"3003",
    "sg:province":"VIC",
    "sg:tags":[
        "wheel",
        "four",
        "equipment",
        "drive",
        "accessory"
    ],
    "wof:name":"Don Kyatt Spare Parts Pty Ltd",
    "wof:placetype":"venue"
},
  "geometry": {"coordinates":[144.946411133,-37.8086585999],"type":"Point"}
}