{
  "type": "Feature",
  "properties": {
    "addr:full":"Rear Of 51 Burwood Rd Burwood NSW 2134",
    "addr:housenumber":"rear of 51",
    "addr:postcode":"2134",
    "addr:street":"Burwood Rd",
    "iso:country":"AU",
    "sg:address":"Rear Of 51 Burwood Rd",
    "sg:city":"Burwood",
    "sg:classifiers":[
        {
            "category":"Health Services",
            "subcategory":"Doctor",
            "type":"Services"
        }
    ],
    "sg:phone":"+61 2 9747 6611",
    "sg:postcode":"2134",
    "sg:province":"NSW",
    "sg:tags":[
        "medical",
        "practitioner"
    ],
    "wof:name":"Attia Magdy",
    "wof:placetype":"venue"
},
  "geometry": {"coordinates":[151.104049683,-33.8748016357],"type":"Point"}
}