{
  "type": "Feature",
  "properties": {
    "addr:full":"59 Stanton St Doncaster VIC 3108",
    "addr:housenumber":"59",
    "addr:postcode":"3108",
    "addr:street":"Stanton St",
    "iso:country":"AU",
    "sg:address":"59 Stanton St",
    "sg:city":"Doncaster",
    "sg:classifiers":[
        {
            "category":"Manufacturing",
            "subcategory":"Leather Goods",
            "type":"Manufacturing & Wholesale Goods"
        }
    ],
    "sg:phone":"+61 3 9848 9690",
    "sg:postcode":"3108",
    "sg:province":"VIC",
    "sg:tags":[
        "wholesaler",
        "mfrs"
    ],
    "wof:name":"J.A.M. Handbag Design & Production",
    "wof:placetype":"venue"
},
  "geometry": {"coordinates":[145.11026000999999,-37.7933311462],"type":"Point"}
}