{
  "type": "Feature",
  "properties": {
    "addr:full":"5 Commercial St Korumburra VIC 3950",
    "addr:housenumber":"5",
    "addr:postcode":"3950",
    "addr:street":"Commercial St",
    "iso:country":"AU",
    "sg:address":"5 Commercial St",
    "sg:city":"Korumburra",
    "sg:classifiers":[
        {
            "category":"Communications",
            "subcategory":"Film & Video Production",
            "type":"Services"
        }
    ],
    "sg:phone":"+61 3 5655 2299",
    "sg:postcode":"3950",
    "sg:province":"VIC",
    "sg:tags":[
        "mirror"
    ],
    "wof:name":"Jenny's Picture This Framed",
    "wof:placetype":"venue"
},
  "geometry": {"coordinates":[145.82281494099999,-38.4323501587],"type":"Point"}
}