{
  "type": "Feature",
  "properties": {
    "addr:full":"62 Waterloo Rd Greenacre NSW 2190",
    "addr:housenumber":"62",
    "addr:postcode":"2190",
    "addr:street":"Waterloo Rd",
    "iso:country":"AU",
    "sg:address":"62 Waterloo Rd",
    "sg:city":"Greenacre",
    "sg:classifiers":[
        {
            "category":"Real Estate",
            "subcategory":"Real Estate Operator",
            "type":"Services"
        }
    ],
    "sg:phone":"+61 413 603 720",
    "sg:postcode":"2190",
    "sg:province":"NSW",
    "sg:tags":[
        "concrete",
        "pumping"
    ],
    "wof:name":"H & T Concrete Pumping",
    "wof:placetype":"venue"
},
  "geometry": {"coordinates":[151.05810500000001,-33.9025],"type":"Point"}
}