{
  "type": "Feature",
  "properties": {
    "addr:full":"6 Bruce St Box Hill VIC 3128",
    "addr:housenumber":"6",
    "addr:postcode":"3128",
    "addr:street":"Bruce St",
    "iso:country":"AU",
    "sg:address":"6 Bruce St",
    "sg:city":"Box Hill",
    "sg:classifiers":[
        {
            "category":"Health Services",
            "subcategory":"Doctor",
            "type":"Services"
        }
    ],
    "sg:phone":"+61 3 9890 0781",
    "sg:postcode":"3128",
    "sg:province":"VIC",
    "sg:tags":[
        "medical",
        "practitioner"
    ],
    "wof:name":"Low G",
    "wof:placetype":"venue"
},
  "geometry": {"coordinates":[145.122192383,-37.8170166016],"type":"Point"}
}