{
  "type": "Feature",
  "properties": {
    "addr:full":"92-100 Middle St Cleveland QLD 4163",
    "addr:housenumber":"92-100",
    "addr:postcode":"4163",
    "addr:street":"Middle St",
    "iso:country":"AU",
    "sg:address":"92-100 Middle St",
    "sg:city":"Cleveland",
    "sg:classifiers":[
        {
            "category":"Cafe",
            "type":"Food & Drink"
        }
    ],
    "sg:phone":"+61 7 3286 7771",
    "sg:postcode":"4163",
    "sg:province":"QLD",
    "wof:name":"Coffee Club The",
    "wof:placetype":"venue"
},
  "geometry": {"coordinates":[153.26922607399999,-27.5258216858],"type":"Point"}
}