{
  "type": "Feature",
  "properties": {
    "addr:full":"39 Mckail Crs Stirling ACT 2611",
    "addr:housenumber":"39",
    "addr:postcode":"2611",
    "addr:street":"Mckail Crs",
    "iso:country":"AU",
    "sg:address":"39 Mckail Crs",
    "sg:city":"Stirling",
    "sg:classifiers":[
        {
            "category":"Building & Trades",
            "subcategory":"Construction",
            "type":"Services"
        }
    ],
    "sg:phone":"+61 418 620 550",
    "sg:postcode":"2611",
    "sg:province":"ACT",
    "sg:tags":[
        "contractor"
    ],
    "wof:name":"Cappuccio Andrew",
    "wof:placetype":"venue"
},
  "geometry": {"coordinates":[149.04867553700001,-35.3445243835],"type":"Point"}
}