{
  "type": "Feature",
  "properties": {
    "iso:country":"AU",
    "sg:address":"Unit 3 74 EastField Rd",
    "sg:city":"Croydon South",
    "sg:classifiers":[
        {
            "category":"Building & Trades",
            "subcategory":"Construction",
            "type":"Services"
        }
    ],
    "sg:phone":"+61 417 102 985",
    "sg:postcode":"3136",
    "sg:province":"VIC",
    "sg:tags":[
        "earth",
        "excavating",
        "moving",
        "contractor"
    ],
    "wof:name":"East West Earth Moving",
    "wof:placetype":"venue"
},
  "geometry": {"coordinates":[145.26889038100001,-37.8105239868],"type":"Point"}
}