{
  "type": "Feature",
  "properties": {
    "addr:full":"351 Lower Plateau Rd Bilgola Plateau NSW 2107",
    "addr:housenumber":"351",
    "addr:postcode":"2107",
    "addr:street":"Lower Plateau Rd",
    "iso:country":"AU",
    "sg:address":"351 Lower Plateau Rd",
    "sg:city":"Bilgola Plateau",
    "sg:classifiers":[
        {
            "category":"Organizations",
            "subcategory":"Professional Association",
            "type":"Services"
        }
    ],
    "sg:phone":"+61 402 137 147",
    "sg:postcode":"2107",
    "sg:province":"NSW",
    "sg:tags":[
        "web",
        "internet"
    ],
    "wof:name":"E-Street Design Studio",
    "wof:placetype":"venue"
},
  "geometry": {"coordinates":[151.31236267099999,-33.6397743225],"type":"Point"}
}