{
  "type": "Feature",
  "properties": {
    "addr:full":"Cnr Shakespeare & Brisbane Sts Mackay QLD 4740",
    "addr:postcode":"4740",
    "iso:country":"AU",
    "sg:address":"Cnr Shakespeare & Brisbane Sts",
    "sg:city":"Mackay",
    "sg:classifiers":[
        {
            "category":"Professional",
            "subcategory":"Employment Agencies",
            "type":"Services"
        }
    ],
    "sg:phone":"+61 7 4953 5757",
    "sg:postcode":"4740",
    "sg:province":"QLD",
    "sg:tags":[
        "hire",
        "labour",
        "contractor"
    ],
    "wof:name":"Mackay Engineering Solutions Pty Ltd",
    "wof:placetype":"venue"
},
  "geometry": {"coordinates":[149.16734299999999,-21.14513],"type":"Point"}
}