{
  "type": "Feature",
  "properties": {
    "addr:full":"788 Old Illawarra Rd Menai NSW 2234",
    "addr:housenumber":"788",
    "addr:postcode":"2234",
    "addr:street":"Old Illawarra Rd",
    "iso:country":"AU",
    "sg:address":"788 Old Illawarra Rd",
    "sg:city":"Menai",
    "sg:classifiers":[
        {
            "category":"Autos & Motor Vehicles",
            "subcategory":"Auto Supplies",
            "type":"Retail Goods"
        }
    ],
    "sg:phone":"+61 2 9543 9020",
    "sg:postcode":"2234",
    "sg:province":"NSW",
    "sg:tags":[
        "accessory"
    ],
    "wof:name":"Menai Auto Parts",
    "wof:placetype":"venue"
},
  "geometry": {"coordinates":[151.0103302,-34.0179252625],"type":"Point"}
}