{
  "type": "Feature",
  "properties": {
    "iso:country":"AU",
    "sg:address":"61 Vagabond St",
    "sg:city":"McKellar",
    "sg:classifiers":[
        {
            "category":"Building & Trades",
            "subcategory":"Construction",
            "type":"Services"
        }
    ],
    "sg:phone":"+61 2 6258 9393",
    "sg:postcode":"2617",
    "sg:province":"ACT",
    "sg:tags":[
        "earth",
        "excavating",
        "moving",
        "contractor"
    ],
    "wof:name":"E.C. Excavations Pty Ltd",
    "wof:placetype":"venue"
},
  "geometry": {"coordinates":[149.07247924800001,-35.2152709961],"type":"Point"}
}