{
  "type": "Feature",
  "properties": {
    "addr:full":"147 Neale Rd Deer Park VIC 3023",
    "addr:housenumber":"147",
    "addr:postcode":"3023",
    "addr:street":"Neale Rd",
    "iso:country":"AU",
    "sg:address":"147 Neale Rd",
    "sg:city":"Deer Park",
    "sg:classifiers":[
        {
            "category":"Retail",
            "subcategory":"Event Space",
            "type":"Services"
        }
    ],
    "sg:phone":"+61 3 8390 2148",
    "sg:postcode":"3023",
    "sg:province":"VIC",
    "sg:tags":[
        "function",
        "organiser"
    ],
    "wof:name":"Oceana Cruisers",
    "wof:placetype":"venue"
},
  "geometry": {"coordinates":[144.75947600000001,-37.750755],"type":"Point"}
}