{
  "type": "Feature",
  "properties": {
    "addr:full":"37 Front St Mossman QLD 4873",
    "addr:housenumber":"37",
    "addr:postcode":"4873",
    "addr:street":"Front St",
    "iso:country":"AU",
    "sg:address":"37 Front St",
    "sg:city":"Mossman",
    "sg:classifiers":[
        {
            "category":"Health Services",
            "subcategory":"Doctor",
            "type":"Services"
        }
    ],
    "sg:phone":"+61 7 4098 1248",
    "sg:postcode":"4873",
    "sg:province":"QLD",
    "sg:tags":[
        "medical",
        "practitioner"
    ],
    "wof:name":"Mossman Medical Centre",
    "wof:placetype":"venue"
},
  "geometry": {"coordinates":[145.37336730999999,-16.4622573853],"type":"Point"}
}