{
  "type": "Feature",
  "properties": {
    "iso:country":"AU",
    "sg:address":"PO Box 2477",
    "sg:city":"North Parramatta Prvt Boxes",
    "sg:classifiers":[
        {
            "category":"Professional",
            "subcategory":"Computer Services",
            "type":"Services"
        }
    ],
    "sg:phone":"+61 2 9676 2477",
    "sg:postcode":"1750",
    "sg:province":"NSW",
    "sg:tags":[
        "package",
        "software"
    ],
    "wof:name":"Sysgen Pty Ltd",
    "wof:placetype":"venue"
},
  "geometry": {"coordinates":[151.010712,-33.798038],"type":"Point"}
}