{
  "type": "Feature",
  "properties": {
    "iso:country":"AU",
    "sg:address":"Shop 3/ 275 South Rd (Cnr Overland Rd)",
    "sg:city":"Croydon Park",
    "sg:classifiers":[
        {
            "category":"Personal",
            "subcategory":"Beauty Salon",
            "type":"Services"
        }
    ],
    "sg:phone":"+61 8 8241 7676",
    "sg:postcode":"5008",
    "sg:province":"SA",
    "sg:tags":[
        "hairdresser"
    ],
    "wof:name":"Shergis Hairdressing",
    "wof:placetype":"venue"
},
  "geometry": {"coordinates":[138.571716,-34.885406],"type":"Point"}
}