{
  "type": "Feature",
  "properties": {
    "addr:full":"170 York St South Melbourne VIC 3205",
    "addr:housenumber":"170",
    "addr:postcode":"3205",
    "addr:street":"York St",
    "iso:country":"AU",
    "sg:address":"170 York St",
    "sg:city":"South Melbourne",
    "sg:classifiers":[
        {
            "category":"Manufacturing",
            "subcategory":"Electronics",
            "type":"Manufacturing & Wholesale Goods"
        }
    ],
    "sg:phone":"+61 3 9483 4634",
    "sg:postcode":"3205",
    "sg:province":"VIC",
    "sg:tags":[
        "oven",
        "microwave"
    ],
    "wof:name":"All Western Suburbs Microwave Oven Service",
    "wof:placetype":"venue"
},
  "geometry": {"coordinates":[144.956299,-37.831562],"type":"Point"}
}