{
  "type": "Feature",
  "properties": {
    "addr:full":"142 Prince Edward Park Rd Woronora NSW 2232",
    "addr:housenumber":"142",
    "addr:postcode":"2232",
    "addr:street":"Prince;Park Rd",
    "iso:country":"AU",
    "sg:address":"142 Prince Edward Park Rd",
    "sg:city":"Woronora",
    "sg:classifiers":[
        {
            "category":"Arts & Performance",
            "subcategory":"Music",
            "type":"Entertainment"
        }
    ],
    "sg:phone":"+61 2 9576 6320",
    "sg:postcode":"2232",
    "sg:province":"NSW",
    "sg:tags":[
        "mobile",
        "jockey",
        "disc"
    ],
    "wof:name":"Mr DJ",
    "wof:placetype":"venue"
},
  "geometry": {"coordinates":[151.03973388700001,-34.0292243958],"type":"Point"}
}