{
  "type": "Feature",
  "properties": {
    "addr:full":"PO Box 6270 Edensor Park NSW 2176",
    "addr:postcode":"2176",
    "iso:country":"AU",
    "sg:address":"PO Box 6270",
    "sg:city":"Edensor Park",
    "sg:classifiers":[
        {
            "category":"Building & Trades",
            "subcategory":"Construction",
            "type":"Services"
        }
    ],
    "sg:phone":"+61 425 296 739",
    "sg:postcode":"2176",
    "sg:province":"NSW",
    "sg:tags":[
        "contractor"
    ],
    "wof:name":"M & J Holdings Pty Ltd",
    "wof:placetype":"venue"
},
  "geometry": {"coordinates":[150.87254333499999,-33.8778800964],"type":"Point"}
}