{
  "type": "Feature",
  "properties": {
    "addr:full":"71 Military Rd Neutral Bay NSW 2089",
    "addr:housenumber":"71",
    "addr:postcode":"2089",
    "addr:street":"Military Rd",
    "iso:country":"AU",
    "sg:address":"71 Military Rd",
    "sg:city":"Neutral Bay",
    "sg:classifiers":[
        {
            "category":"Arts & Performance",
            "subcategory":"Music",
            "type":"Entertainment"
        }
    ],
    "sg:phone":"+61 2 9953 6001",
    "sg:postcode":"2089",
    "sg:province":"NSW",
    "sg:tags":[
        "hi-fi",
        "equipment"
    ],
    "wof:name":"Audio One",
    "wof:placetype":"venue"
},
  "geometry": {"coordinates":[151.21897888199999,-33.8303794861],"type":"Point"}
}