{
  "type": "Feature",
  "properties": {
    "iso:country":"AU",
    "sg:address":"U5/ 13 George St",
    "sg:city":"Marrickville",
    "sg:classifiers":[
        {
            "category":"Building & Trades",
            "subcategory":"Plumbing",
            "type":"Services"
        }
    ],
    "sg:phone":"+61 418 202 073",
    "sg:postcode":"2204",
    "sg:province":"NSW",
    "sg:tags":[
        "plumber",
        "gasfitters"
    ],
    "wof:name":"McCarthy Thomas Plumbing",
    "wof:placetype":"venue"
},
  "geometry": {"coordinates":[151.149246,-33.905018],"type":"Point"}
}