{
  "type": "Feature",
  "properties": {
    "iso:country":"AU",
    "sg:address":"310 Port Elliot Rd",
    "sg:city":"Victor Harbor",
    "sg:classifiers":[
        {
            "category":"Autos & Motor Vehicles",
            "subcategory":"Fuel & Gas Station",
            "type":"Retail Goods"
        }
    ],
    "sg:phone":"+61 8 8552 3929",
    "sg:postcode":"5211",
    "sg:province":"SA",
    "wof:name":"BP Victor Harbor",
    "wof:placetype":"venue"
},
  "geometry": {"coordinates":[138.63955688499999,-35.5365905762],"type":"Point"}
}