{
  "type": "Feature",
  "properties": {
    "addr:full":"74 Dandaloo St Narromine NSW 2821",
    "addr:housenumber":"74",
    "addr:postcode":"2821",
    "addr:street":"Dandaloo St",
    "iso:country":"AU",
    "sg:address":"74 Dandaloo St",
    "sg:city":"Narromine",
    "sg:classifiers":[
        {
            "category":"Government",
            "subcategory":"Post Office",
            "type":"Public Place"
        }
    ],
    "sg:phone":"+61 2 6889 1110",
    "sg:postcode":"2821",
    "sg:province":"NSW",
    "sg:tags":[
        "postal"
    ],
    "wof:name":"Australia Post",
    "wof:placetype":"venue"
},
  "geometry": {"coordinates":[148.23919677699999,-32.2350120544],"type":"Point"}
}