{
  "type": "Feature",
  "properties": {
    "iso:country":"AU",
    "sg:address":"16 Garth St",
    "sg:city":"Edgeworth",
    "sg:classifiers":[
        {
            "category":"Manufacturing",
            "subcategory":"Tools & Machinery",
            "type":"Manufacturing & Wholesale Goods"
        }
    ],
    "sg:phone":"+61 412 275 575",
    "sg:postcode":"2285",
    "sg:province":"NSW",
    "sg:tags":[
        "earth",
        "excavating",
        "moving",
        "equipment"
    ],
    "wof:name":"Nova Quarry & Mining Supplies",
    "wof:placetype":"venue"
},
  "geometry": {"coordinates":[151.61558532699999,-32.9257965088],"type":"Point"}
}