{
  "type": "Feature",
  "properties": {
    "addr:full":"2 Telegraph Rd East Bundaberg QLD 4670",
    "addr:housenumber":"2",
    "addr:postcode":"4670",
    "addr:street":"Telegraph Rd",
    "iso:country":"AU",
    "sg:address":"2 Telegraph Rd",
    "sg:city":"East Bundaberg",
    "sg:classifiers":[
        {
            "category":"Retail",
            "subcategory":"Storage",
            "type":"Services"
        }
    ],
    "sg:phone":"+61 7 4153 6089",
    "sg:postcode":"4670",
    "sg:province":"QLD",
    "wof:name":"Telegraph Rd Storage Sheds",
    "wof:placetype":"venue"
},
  "geometry": {"coordinates":[152.37791442899999,-24.8628921509],"type":"Point"}
}