{
  "type": "Feature",
  "properties": {
    "addr:full":"Level 9, 168 Walker St North Sydney NSW 2060",
    "addr:housenumber":"168",
    "addr:postcode":"2060",
    "addr:street":"Walker St",
    "iso:country":"AU",
    "sg:address":"Level 9, 168 Walker St",
    "sg:city":"North Sydney",
    "sg:classifiers":[
        {
            "category":"Banks & Credit Unions",
            "subcategory":"Investment Brokerage",
            "type":"Services"
        }
    ],
    "sg:phone":"+61 2 9954 3423",
    "sg:postcode":"2060",
    "sg:province":"NSW",
    "sg:tags":[
        "debt",
        "collection"
    ],
    "wof:name":"Telecheck Payment Systems Ltd",
    "wof:placetype":"venue"
},
  "geometry": {"coordinates":[151.209472656,-33.8349761963],"type":"Point"}
}