{
  "type": "Feature",
  "properties": {
    "iso:country":"AU",
    "sg:address":"60 Crawford Rd",
    "sg:city":"Cooranbong",
    "sg:classifiers":[
        {
            "category":"Home & Garden",
            "subcategory":"Garden Supply",
            "type":"Retail Goods"
        }
    ],
    "sg:phone":"+61 2 4977 2344",
    "sg:postcode":"2265",
    "sg:province":"NSW",
    "sg:tags":[
        "nursery"
    ],
    "wof:name":"Plantcare",
    "wof:placetype":"venue"
},
  "geometry": {"coordinates":[151.458176,-33.100407],"type":"Point"}
}