{
  "type": "Feature",
  "properties": {
    "addr:full":"24 Forge Creek Rd Eagle Point VIC 3878",
    "addr:housenumber":"24",
    "addr:postcode":"3878",
    "addr:street":"Forge Creek Rd",
    "iso:country":"AU",
    "sg:address":"24 Forge Creek Rd",
    "sg:city":"Eagle Point",
    "sg:classifiers":[
        {
            "category":"Retail",
            "subcategory":"Repair Shop",
            "type":"Services"
        }
    ],
    "sg:phone":"+61 3 5156 7928",
    "sg:postcode":"3878",
    "sg:province":"VIC",
    "sg:tags":[
        "machine",
        "sewing"
    ],
    "wof:name":"Geoff Carr Sewing Machines",
    "wof:placetype":"venue"
},
  "geometry": {"coordinates":[147.67442321799999,-37.8929824829],"type":"Point"}
}