{
  "type": "Feature",
  "properties": {
    "iso:country":"AU",
    "sg:address":"54 Wall Rd",
    "sg:city":"Gorokan",
    "sg:classifiers":[
        {
            "category":"Professional",
            "subcategory":"Engineering",
            "type":"Services"
        }
    ],
    "sg:phone":"+61 2 4392 4904",
    "sg:postcode":"2263",
    "sg:province":"NSW",
    "sg:tags":[
        "precision",
        "engineer"
    ],
    "wof:name":"G.T.S. Plastics",
    "wof:placetype":"venue"
},
  "geometry": {"coordinates":[151.50285299999999,-33.25732],"type":"Point"}
}