{
  "type": "Feature",
  "properties": {
    "addr:full":"Cnr Summerleas Rd & Channel Hwy Kingston TAS 7050",
    "addr:postcode":"7050",
    "addr:street":"Cnr Summerleas Rd & Channel Hwy",
    "iso:country":"AU",
    "sg:address":"Cnr Summerleas Rd & Channel Hwy",
    "sg:city":"Kingston",
    "sg:classifiers":[
        {
            "category":"Fast Food",
            "type":"Food & Drink"
        }
    ],
    "sg:phone":"+61 3 6229 1355",
    "sg:postcode":"7050",
    "sg:province":"TAS",
    "sg:tags":[
        "away",
        "take"
    ],
    "wof:name":"McDonald's Family Restaurants",
    "wof:placetype":"venue"
},
  "geometry": {"coordinates":[147.30392499999999,-42.975609],"type":"Point"}
}