{
  "type": "Feature",
  "properties": {
    "addr:full":"24 Bradford Ave Greenvale VIC 3059",
    "addr:housenumber":"24",
    "addr:postcode":"3059",
    "addr:street":"Bradford Ave",
    "iso:country":"AU",
    "sg:address":"24 Bradford Ave",
    "sg:city":"Greenvale",
    "sg:classifiers":[
        {
            "category":"Social Services",
            "subcategory":"Child Care",
            "type":"Services"
        }
    ],
    "sg:phone":"+61 3 9333 2240",
    "sg:postcode":"3059",
    "sg:province":"VIC",
    "sg:tags":[
        "support",
        "health"
    ],
    "wof:name":"Maternal & Child Health Centres",
    "wof:placetype":"venue"
},
  "geometry": {"coordinates":[144.88656616200001,-37.6394233704],"type":"Point"}
}