{
  "type": "Feature",
  "properties": {
    "addr:full":"Studio1/ 2 Fielding St Collaroy NSW 2097",
    "addr:housenumber":"2",
    "addr:postcode":"2097",
    "addr:street":"Fielding St",
    "iso:country":"AU",
    "sg:address":"Studio1/ 2 Fielding St",
    "sg:city":"Collaroy",
    "sg:classifiers":[
        {
            "category":"Professional",
            "subcategory":"Art Services",
            "type":"Services"
        }
    ],
    "sg:phone":"+61 2 9971 9111",
    "sg:postcode":"2097",
    "sg:province":"NSW",
    "sg:tags":[
        "interior",
        "designer"
    ],
    "wof:name":"Lonngren- Hall About Design",
    "wof:placetype":"venue"
},
  "geometry": {"coordinates":[151.30044555699999,-33.7309455872],"type":"Point"}
}