{
  "type": "Feature",
  "properties": {
    "iso:country":"AU",
    "sg:address":"Shop 4 32 Denham St",
    "sg:city":"Rockhampton",
    "sg:classifiers":[
        {
            "category":"Wholesale",
            "subcategory":"Apparel",
            "type":"Manufacturing & Wholesale Goods"
        }
    ],
    "sg:phone":"+61 7 4921 3773",
    "sg:postcode":"4700",
    "sg:province":"QLD",
    "sg:tags":[
        "wholesaler",
        "mfrs",
        "uniform"
    ],
    "wof:name":"Power Jam",
    "wof:placetype":"venue"
},
  "geometry": {"coordinates":[150.498809814,-23.3875083923],"type":"Point"}
}