{
  "type": "Feature",
  "properties": {
    "addr:full":"2 Glenere Drv Modbury SA 5092",
    "addr:housenumber":"2",
    "addr:postcode":"5092",
    "addr:street":"Glenere Drv",
    "iso:country":"AU",
    "sg:address":"2 Glenere Drv",
    "sg:city":"Modbury",
    "sg:classifiers":[
        {
            "category":"Social Services",
            "subcategory":"Child Care",
            "type":"Services"
        }
    ],
    "sg:phone":"+61 8 8265 6605",
    "sg:postcode":"5092",
    "sg:province":"SA",
    "wof:name":"Kidz Club Childcare Centre",
    "wof:placetype":"venue"
},
  "geometry": {"coordinates":[138.68107605,-34.8355751038],"type":"Point"}
}