{
  "type": "Feature",
  "properties": {
    "addr:full":"154 Rokeby Rd Subiaco WA 6008",
    "addr:housenumber":"154",
    "addr:postcode":"6008",
    "addr:street":"Rokeby Rd",
    "iso:country":"AU",
    "sg:address":"154 Rokeby Rd",
    "sg:city":"Subiaco",
    "sg:classifiers":[
        {
            "category":"Shopping",
            "subcategory":"Jewelry",
            "type":"Retail Goods"
        }
    ],
    "sg:phone":"+61 8 9388 6944",
    "sg:postcode":"6008",
    "sg:province":"WA",
    "sg:tags":[
        "jeweller"
    ],
    "sg:website":"http://www.kitalepearls.com",
    "wof:name":"Kitale Pearls",
    "wof:placetype":"venue"
},
  "geometry": {"coordinates":[115.824142456,-31.9493656158],"type":"Point"}
}