{
  "type": "Feature",
  "properties": {
    "addr:full":"252 Charman Rd Cheltenham VIC 3192",
    "addr:housenumber":"252",
    "addr:postcode":"3192",
    "addr:street":"Charman Rd",
    "iso:country":"AU",
    "sg:address":"252 Charman Rd",
    "sg:city":"Cheltenham",
    "sg:classifiers":[
        {
            "category":"Shopping",
            "subcategory":"Bicycles & Sporting Goods",
            "type":"Retail Goods"
        }
    ],
    "sg:phone":"+61 3 9583 6322",
    "sg:postcode":"3192",
    "sg:province":"VIC",
    "sg:tags":[
        "chemical",
        "equipment",
        "pool",
        "swimming"
    ],
    "wof:name":"Kreepy Krauly",
    "wof:placetype":"venue"
},
  "geometry": {"coordinates":[145.055252075,-37.9687042236],"type":"Point"}
}