{
  "type": "Feature",
  "properties": {
    "iso:country":"AU",
    "sg:address":"47 Vergulde Rd",
    "sg:city":"Browns Plains",
    "sg:classifiers":[
        {
            "category":"Building & Trades",
            "subcategory":"Construction",
            "type":"Services"
        }
    ],
    "sg:phone":"+61 7 3809 4600",
    "sg:postcode":"4118",
    "sg:province":"QLD",
    "sg:tags":[
        "contractor"
    ],
    "wof:name":"P M R Constructions",
    "wof:placetype":"venue"
},
  "geometry": {"coordinates":[153.038406372,-27.6703014374],"type":"Point"}
}