{
  "type": "Feature",
  "properties": {
    "addr:full":"Shop 11/ 20 Avalon Pde Avalon Beach NSW 2107",
    "addr:housenumber":"shop 11 / 20",
    "addr:postcode":"2107",
    "addr:street":"Avalon Pde",
    "iso:country":"AU",
    "sg:address":"Shop 11/ 20 Avalon Pde",
    "sg:city":"Avalon Beach",
    "sg:classifiers":[
        {
            "category":"Shopping",
            "subcategory":"Shoes",
            "type":"Retail Goods"
        }
    ],
    "sg:phone":"+61 2 9973 1708",
    "sg:postcode":"2107",
    "sg:province":"NSW",
    "sg:tags":[
        "footwear"
    ],
    "wof:name":"Coelho Shoes",
    "wof:placetype":"venue"
},
  "geometry": {"coordinates":[151.336395264,-33.6273536682],"type":"Point"}
}