{
  "type": "Feature",
  "properties": {
    "addr:full":"6/ 41 Shelley St Elwood VIC 3184",
    "addr:housenumber":"/ 41",
    "addr:postcode":"3184",
    "addr:street":"Shelley St",
    "iso:country":"AU",
    "sg:address":"6/ 41 Shelley St",
    "sg:city":"Elwood",
    "sg:classifiers":[
        {
            "category":"Professional",
            "subcategory":"Art Services",
            "type":"Services"
        }
    ],
    "sg:phone":"+61 3 9531 4929",
    "sg:postcode":"3184",
    "sg:province":"VIC",
    "sg:tags":[
        "graphic",
        "designer"
    ],
    "wof:name":"Sabatini Belle Creative",
    "wof:placetype":"venue"
},
  "geometry": {"coordinates":[144.983276367,-37.8808898926],"type":"Point"}
}