{
  "type": "Feature",
  "properties": {
    "addr:full":"86 Candowie Crs Karana Downs QLD 4306",
    "addr:housenumber":"86",
    "addr:postcode":"4306",
    "addr:street":"Candowie Crs",
    "iso:country":"AU",
    "sg:address":"86 Candowie Crs",
    "sg:city":"Karana Downs",
    "sg:classifiers":[
        {
            "category":"Building & Trades",
            "subcategory":"Cleaning & Sanitation",
            "type":"Services"
        }
    ],
    "sg:phone":"+61 7 3201 1161",
    "sg:postcode":"4306",
    "sg:province":"QLD",
    "sg:tags":[
        "cleaner",
        "repairer",
        "roof"
    ],
    "wof:name":"All Property Roofing",
    "wof:placetype":"venue"
},
  "geometry": {"coordinates":[152.86137390100001,-27.6611709595],"type":"Point"}
}