{
  "type": "Feature",
  "properties": {
    "addr:full":"48 Kremzow Rd Brendale QLD 4500",
    "addr:housenumber":"48",
    "addr:postcode":"4500",
    "addr:street":"Kremzow Rd",
    "iso:country":"AU",
    "sg:address":"48 Kremzow Rd",
    "sg:city":"Brendale",
    "sg:classifiers":[
        {
            "category":"Manufacturing",
            "subcategory":"Metals",
            "type":"Manufacturing & Wholesale Goods"
        }
    ],
    "sg:phone":"+61 7 3205 2996",
    "sg:postcode":"4500",
    "sg:province":"QLD",
    "sg:tags":[
        "steel",
        "fabricator",
        "mfrs"
    ],
    "wof:name":"Reynolds L & B Steel Fabricators",
    "wof:placetype":"venue"
},
  "geometry": {"coordinates":[152.985473633,-27.3179550171],"type":"Point"}
}