{
  "type": "Feature",
  "properties": {
    "iso:country":"AU",
    "sg:address":"5A High St",
    "sg:city":"Bayswater",
    "sg:classifiers":[
        {
            "category":"Food & Beverages",
            "subcategory":"Fruits & Vegetables",
            "type":"Retail Goods"
        }
    ],
    "sg:phone":"+61 3 9729 1462",
    "sg:postcode":"3153",
    "sg:province":"VIC",
    "sg:tags":[
        "greengrocer",
        "fruiterer"
    ],
    "wof:name":"Bayswater Fruit Supply",
    "wof:placetype":"venue"
},
  "geometry": {"coordinates":[145.265533447,-37.8415679932],"type":"Point"}
}