{
  "type": "Feature",
  "properties": {
    "addr:full":"Canning Vale College 26 Dumbarton Rd Canning Vale WA 6155",
    "addr:housenumber":"26",
    "addr:postcode":"6155",
    "addr:street":"Dumbarton Rd",
    "iso:country":"AU",
    "sg:address":"Canning Vale College 26 Dumbarton Rd",
    "sg:city":"Canning Vale",
    "sg:classifiers":[
        {
            "category":"Education",
            "subcategory":"School",
            "type":"Public Place"
        }
    ],
    "sg:phone":"+61 8 9334 9000",
    "sg:postcode":"6155",
    "sg:province":"WA",
    "sg:tags":[
        "state",
        "except",
        "nsw"
    ],
    "wof:name":"Schools Government (Public)",
    "wof:placetype":"venue"
},
  "geometry": {"coordinates":[115.922691,-32.083817],"type":"Point"}
}