{
  "type": "Feature",
  "properties": {
    "addr:full":"Unit 4/ 34 Forrest Pde Bakewell NT 0832",
    "addr:housenumber":"34",
    "addr:postcode":"nt 0832",
    "addr:street":"Forrest Pde",
    "iso:country":"AU",
    "sg:address":"Unit 4/ 34 Forrest Pde",
    "sg:city":"Bakewell",
    "sg:classifiers":[
        {
            "category":"Professional",
            "subcategory":"Business Services",
            "type":"Services"
        }
    ],
    "sg:phone":"+61 8 8931 0961",
    "sg:postcode":"0832",
    "sg:province":"NT",
    "sg:tags":[
        "drafting"
    ],
    "wof:name":"QT Drawings",
    "wof:placetype":"venue"
},
  "geometry": {"coordinates":[130.992706,-12.496585],"type":"Point"}
}