{
  "type": "Feature",
  "properties": {
    "iso:country":"AU",
    "sg:address":"20 Porter Ave",
    "sg:city":"Kirwan",
    "sg:classifiers":[
        {
            "category":"Building & Trades",
            "subcategory":"Construction",
            "type":"Services"
        }
    ],
    "sg:phone":"+61 7 4773 5635",
    "sg:postcode":"4817",
    "sg:province":"QLD",
    "sg:tags":[
        "earth",
        "excavating",
        "moving",
        "contractor"
    ],
    "wof:name":"Weight Excavations",
    "wof:placetype":"venue"
},
  "geometry": {"coordinates":[146.725388,-19.310612],"type":"Point"}
}