{
  "type": "Feature",
  "properties": {
    "addr:full":"Unit 1/ 53 Innovation Cct Wangara WA 6065",
    "addr:housenumber":"53",
    "addr:postcode":"6065",
    "addr:street":"Innovation Cct",
    "iso:country":"AU",
    "sg:address":"Unit 1/ 53 Innovation Cct",
    "sg:city":"Wangara",
    "sg:classifiers":[
        {
            "category":"Retail",
            "subcategory":"Auto Repair",
            "type":"Services"
        }
    ],
    "sg:phone":"+61 8 9303 4990",
    "sg:postcode":"6065",
    "sg:province":"WA",
    "sg:tags":[
        "muffler",
        "exhaust",
        "system"
    ],
    "wof:name":"Carline Mufflers",
    "wof:placetype":"venue"
},
  "geometry": {"coordinates":[115.83310699499999,-31.8020267487],"type":"Point"}
}