{
  "type": "Feature",
  "properties": {
    "addr:full":"14 Union St Brunswick VIC 3056",
    "addr:housenumber":"14",
    "addr:postcode":"3056",
    "addr:street":"Union St",
    "iso:country":"AU",
    "sg:address":"14 Union St",
    "sg:city":"Brunswick",
    "sg:classifiers":[
        {
            "category":"Building & Trades",
            "subcategory":"Cleaning & Sanitation",
            "type":"Services"
        }
    ],
    "sg:phone":"+61 402 144 881",
    "sg:postcode":"3056",
    "sg:province":"VIC",
    "sg:tags":[
        "window"
    ],
    "wof:name":"Aders Window Cleaning",
    "wof:placetype":"venue"
},
  "geometry": {"coordinates":[144.960006714,-37.7739982605],"type":"Point"}
}