{
  "type": "Feature",
  "properties": {
    "iso:country":"AU",
    "sg:address":"14 Jillian Ave",
    "sg:city":"Highett",
    "sg:classifiers":[
        {
            "category":"Building & Trades",
            "subcategory":"Construction",
            "type":"Services"
        }
    ],
    "sg:phone":"+61 418 334 308",
    "sg:postcode":"3190",
    "sg:province":"VIC",
    "sg:tags":[
        "contractor"
    ],
    "wof:name":"C.P.N. Constructions",
    "wof:placetype":"venue"
},
  "geometry": {"coordinates":[145.023834228,-37.9474525452],"type":"Point"}
}