{
  "type": "Feature",
  "properties": {
    "addr:full":"268 Springvale Rd Springvale VIC 3171",
    "addr:housenumber":"268",
    "addr:postcode":"3171",
    "addr:street":"Springvale Rd",
    "iso:country":"AU",
    "sg:address":"268 Springvale Rd",
    "sg:city":"Springvale",
    "sg:classifiers":[
        {
            "category":"Shopping",
            "subcategory":"Bridal",
            "type":"Retail Goods"
        }
    ],
    "sg:phone":"+61 3 9547 0011",
    "sg:postcode":"3171",
    "sg:province":"VIC",
    "sg:tags":[
        "hire",
        "wear"
    ],
    "wof:name":"Kims Bridal & Fashion",
    "wof:placetype":"venue"
},
  "geometry": {"coordinates":[145.15222168,-37.95129776],"type":"Point"}
}