{
  "type": "Feature",
  "properties": {
    "iso:country":"AU",
    "sg:address":"Unit 2/ 51 Berriman Drv",
    "sg:city":"Wangara",
    "sg:classifiers":[
        {
            "category":"Building & Trades",
            "subcategory":"Locksmith",
            "type":"Services"
        }
    ],
    "sg:phone":"+61 402 327 080",
    "sg:postcode":"6065",
    "sg:province":"WA",
    "sg:tags":[
        "lock"
    ],
    "wof:name":"Advanced Lock & Key",
    "wof:placetype":"venue"
},
  "geometry": {"coordinates":[115.826309204,-31.7928638458],"type":"Point"}
}