{
  "type": "Feature",
  "properties": {
    "addr:full":"Leawarra Ave Warilla NSW 2528",
    "addr:postcode":"2528",
    "addr:street":"Leawarra Ave",
    "iso:country":"AU",
    "sg:address":"Leawarra Ave",
    "sg:city":"Warilla",
    "sg:classifiers":[
        {
            "category":"Education",
            "subcategory":"School",
            "type":"Public Place"
        }
    ],
    "sg:phone":"+61 2 4295 1867",
    "sg:postcode":"2528",
    "sg:province":"NSW",
    "sg:tags":[
        "state",
        "-",
        "nsw"
    ],
    "wof:name":"Warilla Public School",
    "wof:placetype":"venue"
},
  "geometry": {"coordinates":[150.853393555,-34.5549087524],"type":"Point"}
}