{
  "type": "Feature",
  "properties": {
    "addr:full":"30 Oramzi Rd Girraween NSW 2145",
    "addr:housenumber":"30",
    "addr:postcode":"2145",
    "addr:street":"Oramzi Rd",
    "iso:country":"AU",
    "sg:address":"30 Oramzi Rd",
    "sg:city":"Girraween",
    "sg:classifiers":[
        {
            "category":"Manufacturing",
            "subcategory":"Metals",
            "type":"Manufacturing & Wholesale Goods"
        }
    ],
    "sg:phone":"+61 2 9769 0455",
    "sg:postcode":"2145",
    "sg:province":"NSW",
    "sg:tags":[
        "sheet",
        "worker"
    ],
    "wof:name":"Western Sheetmetals",
    "wof:placetype":"venue"
},
  "geometry": {"coordinates":[150.942993164,-33.7949256897],"type":"Point"}
}