{
  "type": "Feature",
  "properties": {
    "addr:full":"Cnr Ballarto & Taylors Rds Skye VIC 3977",
    "addr:postcode":"3977",
    "addr:street":"Cnr",
    "iso:country":"AU",
    "sg:address":"Cnr Ballarto & Taylors Rds",
    "sg:city":"Skye",
    "sg:classifiers":[
        {
            "category":"Sports & Exercise",
            "subcategory":"Golf",
            "type":"Entertainment"
        }
    ],
    "sg:phone":"+61 3 9782 2599",
    "sg:postcode":"3977",
    "sg:province":"VIC",
    "sg:tags":[
        "club"
    ],
    "wof:name":"Skye Public Golf Course & Driving Range",
    "wof:placetype":"venue"
},
  "geometry": {"coordinates":[145.195404053,-38.1172676086],"type":"Point"}
}