{
  "type": "Feature",
  "properties": {
    "addr:full":"278a Great North Rd Abbotsford NSW 2046",
    "addr:housenumber":"278a",
    "addr:postcode":"2046",
    "addr:street":"Great North Rd",
    "iso:country":"AU",
    "sg:address":"278a Great North Rd",
    "sg:city":"Abbotsford",
    "sg:classifiers":[
        {
            "category":"Banks & Credit Unions",
            "subcategory":"Financial Services",
            "type":"Services"
        }
    ],
    "sg:phone":"+61 2 9713 5299",
    "sg:postcode":"2046",
    "sg:province":"NSW",
    "sg:tags":[
        "planning"
    ],
    "wof:name":"Prosper Wealth Solutions Pty Ltd",
    "wof:placetype":"venue"
},
  "geometry": {"coordinates":[151.131012,-33.857281],"type":"Point"}
}