{
  "type": "Feature",
  "properties": {
    "addr:full":"28 Fisher Ave Pennant Hills NSW 2120",
    "addr:housenumber":"28",
    "addr:postcode":"2120",
    "addr:street":"Fisher Ave",
    "iso:country":"AU",
    "sg:address":"28 Fisher Ave",
    "sg:city":"Pennant Hills",
    "sg:classifiers":[
        {
            "category":"Health Services",
            "subcategory":"Dentist",
            "type":"Services"
        }
    ],
    "sg:phone":"+61 2 9484 5154",
    "sg:postcode":"2120",
    "sg:province":"NSW",
    "wof:name":"Vickers Daniel",
    "wof:placetype":"venue"
},
  "geometry": {"coordinates":[151.06781005900001,-33.7385559082],"type":"Point"}
}