{
  "type": "Feature",
  "properties": {
    "addr:full":"20 Roland St Wetherill Park NSW 2164",
    "addr:housenumber":"20",
    "addr:postcode":"2164",
    "addr:street":"Roland St",
    "iso:country":"AU",
    "sg:address":"20 Roland St",
    "sg:city":"Wetherill Park",
    "sg:classifiers":[
        {
            "category":"Building & Trades",
            "subcategory":"Cleaning & Sanitation",
            "type":"Services"
        }
    ],
    "sg:phone":"+61 2 9963 2403",
    "sg:postcode":"2164",
    "sg:province":"NSW",
    "sg:tags":[
        "industrial",
        "commercial",
        "contractor"
    ],
    "wof:name":"Galeway Cleaning Pty Ltd",
    "wof:placetype":"venue"
},
  "geometry": {"coordinates":[150.89468383799999,-33.8542404175],"type":"Point"}
}