{
  "type": "Feature",
  "properties": {
    "addr:full":"20 Mark St Hunters Hill NSW 2110",
    "addr:housenumber":"20",
    "addr:postcode":"2110",
    "addr:street":"Mark St",
    "iso:country":"AU",
    "sg:address":"20 Mark St",
    "sg:city":"Hunters Hill",
    "sg:classifiers":[
        {
            "category":"Health Services",
            "subcategory":"Health Practitioner",
            "type":"Services"
        }
    ],
    "sg:phone":"+61 2 9879 4865",
    "sg:postcode":"2110",
    "sg:province":"NSW",
    "sg:tags":[
        "naturopath"
    ],
    "wof:name":"Hicks Shirley",
    "wof:placetype":"venue"
},
  "geometry": {"coordinates":[151.13554382300001,-33.830078125],"type":"Point"}
}