{
  "type": "Feature",
  "properties": {
    "addr:full":"525 Stirling Hwy Cottesloe WA 6011",
    "addr:housenumber":"525",
    "addr:postcode":"6011",
    "addr:street":"Stirling Hwy",
    "iso:country":"AU",
    "sg:address":"525 Stirling Hwy",
    "sg:city":"Cottesloe",
    "sg:classifiers":[
        {
            "category":"Health Services",
            "subcategory":"Health Practitioner",
            "type":"Services"
        }
    ],
    "sg:phone":"+61 8 9384 3269",
    "sg:postcode":"6011",
    "sg:province":"WA",
    "sg:tags":[
        "physiotherapist"
    ],
    "wof:name":"Kirby Pippa",
    "wof:placetype":"venue"
},
  "geometry": {"coordinates":[115.760269165,-32.0032272339],"type":"Point"}
}