{
  "type": "Feature",
  "properties": {
    "addr:full":"Suite 1 , Gallery Level Lake Macquarie Fair Mt Hutton NSW 2290",
    "addr:postcode":"2290",
    "iso:country":"AU",
    "sg:address":"Suite 1",
    "sg:city":", Gallery Level Lake Macquarie Fair Mt Hutton",
    "sg:classifiers":[
        {
            "category":"Banks & Credit Unions",
            "subcategory":"Financial Services",
            "type":"Services"
        }
    ],
    "sg:phone":"+61 2 4948 9715",
    "sg:postcode":"2290",
    "sg:province":"NSW",
    "sg:tags":[
        "loan",
        "finance",
        "mortgage"
    ],
    "wof:name":"Choice Home Loans",
    "wof:placetype":"venue"
},
  "geometry": {"coordinates":[151.692626953,-32.984954834],"type":"Point"}
}