{
  "type": "Feature",
  "properties": {
    "addr:full":"485 Hammond Rd Dandenong South VIC 3175",
    "addr:housenumber":"485",
    "addr:postcode":"3175",
    "addr:street":"Hammond Rd",
    "iso:country":"AU",
    "sg:address":"485 Hammond Rd",
    "sg:city":"Dandenong South",
    "sg:classifiers":[
        {
            "category":"Wholesale",
            "subcategory":"Machinery & Supplies",
            "type":"Manufacturing & Wholesale Goods"
        }
    ],
    "sg:phone":"+61 3 9706 4088",
    "sg:postcode":"3175",
    "sg:province":"VIC",
    "sg:tags":[
        "agricultural"
    ],
    "wof:name":"FAE Australia Pacific Pty Ltd",
    "wof:placetype":"venue"
},
  "geometry": {"coordinates":[145.20242309599999,-38.0312080383],"type":"Point"}
}