{
  "type": "Feature",
  "properties": {
    "addr:full":"3 Dysons La Ulverstone TAS 7315",
    "addr:housenumber":"3",
    "addr:postcode":"7315",
    "addr:street":"Dysons La",
    "iso:country":"AU",
    "sg:address":"3 Dysons La",
    "sg:city":"Ulverstone",
    "sg:classifiers":[
        {
            "category":"Manufacturing",
            "subcategory":"Motor Vehicles & Parts",
            "type":"Manufacturing & Wholesale Goods"
        }
    ],
    "sg:phone":"+61 3 6425 6506",
    "sg:postcode":"7315",
    "sg:province":"TAS",
    "sg:tags":[
        "replacement"
    ],
    "wof:name":"Ulverstone Radiator Service",
    "wof:placetype":"venue"
},
  "geometry": {"coordinates":[146.19003295900001,-41.1591491699],"type":"Point"}
}