{
  "type": "Feature",
  "properties": {
    "iso:country":"AU",
    "sg:address":"87 Crebert St",
    "sg:city":"Mayfield",
    "sg:classifiers":[
        {
            "category":"Travel",
            "subcategory":"Hostel",
            "type":"Entertainment"
        }
    ],
    "sg:phone":"+61 2 4968 3777",
    "sg:postcode":"2304",
    "sg:province":"NSW",
    "sg:tags":[
        "home"
    ],
    "wof:name":"Mayfield Residential",
    "wof:placetype":"venue"
},
  "geometry": {"coordinates":[151.73840332,-32.8943443298],"type":"Point"}
}