{
  "type": "Feature",
  "properties": {
    "addr:full":"18 Beckett Ave Keilor East VIC 3033",
    "addr:housenumber":"18",
    "addr:postcode":"3033",
    "addr:street":"Beckett Ave",
    "iso:country":"AU",
    "sg:address":"18 Beckett Ave",
    "sg:city":"Keilor East",
    "sg:classifiers":[
        {
            "category":"Manufacturing",
            "subcategory":"Tools & Machinery",
            "type":"Manufacturing & Wholesale Goods"
        }
    ],
    "sg:phone":"+61 3 9336 1961",
    "sg:postcode":"3033",
    "sg:province":"VIC",
    "sg:tags":[
        "abrasive"
    ],
    "wof:name":"Abrasive Blasting Service & Supplies Pty Ltd",
    "wof:placetype":"venue"
},
  "geometry": {"coordinates":[144.858093,-37.730827],"type":"Point"}
}