{
  "type": "Feature",
  "properties": {
    "iso:country":"AU",
    "sg:address":"147 Sherwood Rd",
    "sg:city":"Aldavilla",
    "sg:classifiers":[
        {
            "category":"Health Services",
            "subcategory":"Health Practitioner",
            "type":"Services"
        }
    ],
    "sg:phone":"+61 2 6562 6758",
    "sg:postcode":"2440",
    "sg:province":"NSW",
    "sg:tags":[
        "alternative"
    ],
    "wof:name":"A & M Tout",
    "wof:placetype":"venue"
},
  "geometry": {"coordinates":[152.754333,-31.058119],"type":"Point"}
}