{
  "type": "Feature",
  "properties": {
    "addr:full":"9 Lockhart Drv Rosebud VIC 3939",
    "addr:housenumber":"9",
    "addr:postcode":"3939",
    "addr:street":"Lockhart Drv",
    "iso:country":"AU",
    "sg:address":"9 Lockhart Drv",
    "sg:city":"Rosebud",
    "sg:classifiers":[
        {
            "category":"Retail",
            "subcategory":"Auto Rental",
            "type":"Services"
        }
    ],
    "sg:phone":"+61 3 5982 2788",
    "sg:postcode":"3939",
    "sg:province":"VIC",
    "sg:tags":[
        "car",
        "wedding"
    ],
    "wof:name":"Port Phillip V.I.P. Limousines Pty Ltd",
    "wof:placetype":"venue"
},
  "geometry": {"coordinates":[144.89561462399999,-38.3760795593],"type":"Point"}
}