{
  "type": "Feature",
  "properties": {
    "addr:full":"14 Barkala Crt Ocean Shores NSW 2483",
    "addr:housenumber":"14",
    "addr:postcode":"2483",
    "addr:street":"Barkala Crt",
    "iso:country":"AU",
    "sg:address":"14 Barkala Crt",
    "sg:city":"Ocean Shores",
    "sg:classifiers":[
        {
            "category":"Utilities",
            "subcategory":"Telephone",
            "type":"Services"
        }
    ],
    "sg:phone":"+61 2 6680 2022",
    "sg:postcode":"2483",
    "sg:province":"NSW",
    "sg:tags":[
        "installation",
        "system",
        "maintenance"
    ],
    "wof:name":"Cooper Communications",
    "wof:placetype":"venue"
},
  "geometry": {"coordinates":[153.546112061,-28.4919223785],"type":"Point"}
}