{
  "type": "Feature",
  "properties": {
    "addr:full":"Shp1/ 73 Glen Osmond Rd Eastwood SA 5063",
    "addr:housenumber":"73",
    "addr:postcode":"5063",
    "addr:street":"Glen Osmond Rd",
    "iso:country":"AU",
    "sg:address":"Shp1/ 73 Glen Osmond Rd",
    "sg:city":"Eastwood",
    "sg:classifiers":[
        {
            "category":"Shopping",
            "subcategory":"Shoes",
            "type":"Retail Goods"
        }
    ],
    "sg:phone":"+61 8 8272 9309",
    "sg:postcode":"5063",
    "sg:province":"SA",
    "sg:tags":[
        "footwear"
    ],
    "wof:name":"Lily Shoes",
    "wof:placetype":"venue"
},
  "geometry": {"coordinates":[138.62112426799999,-34.9437255859],"type":"Point"}
}