{
  "type": "Feature",
  "properties": {
    "addr:full":"104 Princes Hwy Nowra South NSW 2541",
    "addr:housenumber":"104",
    "addr:postcode":"2541",
    "addr:street":"Princes Hwy",
    "iso:country":"AU",
    "sg:address":"104 Princes Hwy",
    "sg:city":"Nowra South",
    "sg:classifiers":[
        {
            "category":"Professional",
            "subcategory":"Detective & Security Services",
            "type":"Services"
        }
    ],
    "sg:phone":"+61 2 4421 4777",
    "sg:postcode":"2541",
    "sg:province":"NSW",
    "sg:tags":[
        "protective",
        "rustproofing"
    ],
    "wof:name":"Nowra Toyota",
    "wof:placetype":"venue"
},
  "geometry": {"coordinates":[150.60215759299999,-34.9022216797],"type":"Point"}
}