{
  "type": "Feature",
  "properties": {
    "iso:country":"AU",
    "sg:address":"11 Hampton Ave",
    "sg:city":"Sunshine",
    "sg:classifiers":[
        {
            "category":"Home & Garden",
            "subcategory":"Building Materials",
            "type":"Retail Goods"
        }
    ],
    "sg:phone":"+61 3 9312 1311",
    "sg:postcode":"3020",
    "sg:province":"VIC",
    "sg:tags":[
        "fitting",
        "door"
    ],
    "wof:name":"Velux",
    "wof:placetype":"venue"
},
  "geometry": {"coordinates":[144.83261100000001,-37.796799],"type":"Point"}
}