{
  "type": "Feature",
  "properties": {
    "iso:country":"AU",
    "sg:address":"191 Loftus Ave",
    "sg:city":"Loftus",
    "sg:classifiers":[
        {
            "category":"Home & Garden",
            "subcategory":"Furniture",
            "type":"Retail Goods"
        }
    ],
    "sg:phone":"+61 2 9542 3387",
    "sg:postcode":"2232",
    "sg:province":"NSW",
    "sg:tags":[
        "business"
    ],
    "wof:name":"Complete Office Installations Pty Ltd",
    "wof:placetype":"venue"
},
  "geometry": {"coordinates":[151.04847717300001,-34.0518417358],"type":"Point"}
}