{
  "type": "Feature",
  "properties": {
    "addr:full":"16 Prosser Ave Norwood SA 5067",
    "addr:housenumber":"16",
    "addr:postcode":"5067",
    "addr:street":"Prosser Ave",
    "iso:country":"AU",
    "sg:address":"16 Prosser Ave",
    "sg:city":"Norwood",
    "sg:classifiers":[
        {
            "category":"Professional",
            "subcategory":"Secretarial Services",
            "type":"Services"
        }
    ],
    "sg:phone":"+61 8 8431 2124",
    "sg:postcode":"5067",
    "sg:province":"SA",
    "sg:tags":[
        "typing"
    ],
    "wof:name":"Your Type",
    "wof:placetype":"venue"
},
  "geometry": {"coordinates":[138.638946533,-34.9170188904],"type":"Point"}
}