{
  "type": "Feature",
  "properties": {
    "addr:full":"Wasiu St Bamaga QLD 4876",
    "addr:postcode":"4876",
    "iso:country":"AU",
    "sg:address":"Wasiu St",
    "sg:city":"Bamaga",
    "sg:classifiers":[
        {
            "category":"Education",
            "subcategory":"School",
            "type":"Public Place"
        }
    ],
    "sg:phone":"+61 7 4069 3125",
    "sg:postcode":"4876",
    "sg:province":"QLD",
    "sg:tags":[
        "state",
        "except",
        "nsw"
    ],
    "wof:name":"Northern Peninsula Area State College Preschool",
    "wof:placetype":"venue"
},
  "geometry": {"coordinates":[142.388748169,-10.8885908127],"type":"Point"}
}