{
  "type": "Feature",
  "properties": {
    "addr:full":"21 Passchendaele St Tarragindi QLD 4121",
    "addr:housenumber":"21",
    "addr:postcode":"4121",
    "addr:street":"Passchendaele St",
    "iso:country":"AU",
    "sg:address":"21 Passchendaele St",
    "sg:city":"Tarragindi",
    "sg:classifiers":[
        {
            "category":"Real Estate",
            "subcategory":"Architect",
            "type":"Services"
        }
    ],
    "sg:phone":"+61 7 3892 1608",
    "sg:postcode":"4121",
    "sg:province":"QLD",
    "wof:name":"Bradley Briggs Architect",
    "wof:placetype":"venue"
},
  "geometry": {"coordinates":[153.056930542,-27.5363922119],"type":"Point"}
}