{
  "type": "Feature",
  "properties": {
    "addr:full":"18 Owsten Crt Banjup WA 6164",
    "addr:housenumber":"18",
    "addr:postcode":"6164",
    "addr:street":"Owsten Crt",
    "iso:country":"AU",
    "sg:address":"18 Owsten Crt",
    "sg:city":"Banjup",
    "sg:classifiers":[
        {
            "category":"Wholesale",
            "subcategory":"Machinery & Supplies",
            "type":"Manufacturing & Wholesale Goods"
        }
    ],
    "sg:phone":"+61 8 9397 0303",
    "sg:postcode":"6164",
    "sg:province":"WA",
    "sg:tags":[
        "instrument",
        "scientific"
    ],
    "wof:name":"Precision Balances Pty Ltd",
    "wof:placetype":"venue"
},
  "geometry": {"coordinates":[115.90411400000001,-32.113998],"type":"Point"}
}