{
  "type": "Feature",
  "properties": {
    "addr:full":"58 Recreation St Tweed Heads NSW 2485",
    "addr:housenumber":"58",
    "addr:postcode":"2485",
    "addr:street":"Recreation St",
    "iso:country":"AU",
    "sg:address":"58 Recreation St",
    "sg:city":"Tweed Heads",
    "sg:classifiers":[
        {
            "category":"Real Estate",
            "subcategory":"Real Estate Agent",
            "type":"Services"
        }
    ],
    "sg:phone":"+61 7 5536 8844",
    "sg:postcode":"2485",
    "sg:province":"NSW",
    "sg:tags":[
        "handyman's",
        "equipment",
        "hire",
        "builders",
        "contractor"
    ],
    "wof:name":"Wreckair",
    "wof:placetype":"venue"
},
  "geometry": {"coordinates":[153.53817749000001,-28.1807975769],"type":"Point"}
}