{
  "type": "Feature",
  "properties": {
    "iso:country":"AU",
    "sg:address":"32 Precision St",
    "sg:city":"Salisbury",
    "sg:classifiers":[
        {
            "category":"Manufacturing",
            "subcategory":"Metals",
            "type":"Manufacturing & Wholesale Goods"
        }
    ],
    "sg:phone":"+61 7 3274 6600",
    "sg:postcode":"4107",
    "sg:province":"QLD",
    "sg:tags":[
        "steel",
        "fabricator",
        "mfrs"
    ],
    "wof:name":"Steelworks Construction Pty Ltd",
    "wof:placetype":"venue"
},
  "geometry": {"coordinates":[153.02932739299999,-27.5468902588],"type":"Point"}
}