{
  "type": "Feature",
  "properties": {
    "addr:full":"69 Rooke St Mall Devonport TAS 7310",
    "addr:housenumber":"69",
    "addr:postcode":"7310",
    "addr:street":"Rooke St Mall",
    "iso:country":"AU",
    "sg:address":"69 Rooke St",
    "sg:city":"Mall Devonport",
    "sg:classifiers":[
        {
            "category":"Utilities",
            "subcategory":"Telephone",
            "type":"Services"
        }
    ],
    "sg:phone":"+61 3 6424 1788",
    "sg:postcode":"7310",
    "sg:province":"TAS",
    "sg:tags":[
        "accessory"
    ],
    "wof:name":"Total Communications",
    "wof:placetype":"venue"
},
  "geometry": {"coordinates":[146.361236572,-41.1775627136],"type":"Point"}
}