{
  "type": "Feature",
  "properties": {
    "addr:full":"133 Lamberth Rd Regents Park QLD 4118",
    "addr:housenumber":"133",
    "addr:postcode":"4118",
    "addr:street":"Lamberth Rd",
    "iso:country":"AU",
    "sg:address":"133 Lamberth Rd",
    "sg:city":"Regents Park",
    "sg:classifiers":[
        {
            "category":"Education",
            "subcategory":"Kindergarten",
            "type":"Public Place"
        }
    ],
    "sg:phone":"+61 7 3806 7788",
    "sg:postcode":"4118",
    "sg:province":"QLD",
    "sg:tags":[
        "pre-schools"
    ],
    "wof:name":"Regents Park Child Care",
    "wof:placetype":"venue"
},
  "geometry": {"coordinates":[153.041549683,-27.6803417206],"type":"Point"}
}