{
  "type": "Feature",
  "properties": {
    "iso:country":"AU",
    "sg:address":"2/ 45 Sanders St",
    "sg:city":"Upper Mt Gravatt",
    "sg:classifiers":[
        {
            "category":"Professional",
            "subcategory":"Management & Consulting",
            "type":"Services"
        }
    ],
    "sg:phone":"+61 7 3420 0066",
    "sg:postcode":"4122",
    "sg:province":"QLD",
    "sg:tags":[
        "consultant",
        "educational"
    ],
    "wof:name":"Lifetime Learners Pty Ltd",
    "wof:placetype":"venue"
},
  "geometry": {"coordinates":[153.08198547399999,-27.5584850311],"type":"Point"}
}