{
  "type": "Feature",
  "properties": {
    "addr:full":"Cnr Gladstone Rd & Victoria Ave Castle Hill NSW 2154",
    "addr:postcode":"2154",
    "addr:street":"Cnr Gladstone Rd & Victoria Ave",
    "iso:country":"AU",
    "sg:address":"Cnr Gladstone Rd & Victoria Ave",
    "sg:city":"Castle Hill",
    "sg:classifiers":[
        {
            "category":"Banks & Credit Unions",
            "subcategory":"Investment Brokerage",
            "type":"Services"
        }
    ],
    "sg:phone":"+61 2 9894 6660",
    "sg:postcode":"2154",
    "sg:province":"NSW",
    "sg:tags":[
        "shutter",
        "louvre"
    ],
    "sg:website":"http://www.setimber.com.au",
    "wof:name":"SE Timber",
    "wof:placetype":"venue"
},
  "geometry": {"coordinates":[150.980392456,-33.7331504822],"type":"Point"}
}