{
  "type": "Feature",
  "properties": {
    "iso:country":"AU",
    "sg:address":"16 Alexander St",
    "sg:city":"Mt Waverley",
    "sg:classifiers":[
        {
            "category":"Health Services",
            "subcategory":"Doctor",
            "type":"Services"
        }
    ],
    "sg:phone":"+61 3 9807 9911",
    "sg:postcode":"3149",
    "sg:province":"VIC",
    "sg:tags":[
        "medical",
        "practitioner"
    ],
    "wof:name":"Leong Weng-ee Dr",
    "wof:placetype":"venue"
},
  "geometry": {"coordinates":[145.12652587900001,-37.8770561218],"type":"Point"}
}