{
  "type": "Feature",
  "properties": {
    "iso:country":"AU",
    "sg:address":"339 Scoresby Rd",
    "sg:city":"Ferntree Gully",
    "sg:classifiers":[
        {
            "category":"Professional",
            "subcategory":"Art Services",
            "type":"Services"
        }
    ],
    "sg:phone":"+61 402 007 853",
    "sg:postcode":"3156",
    "sg:province":"VIC",
    "sg:tags":[
        "decorator",
        "painter"
    ],
    "wof:name":"PJ Renovators",
    "wof:placetype":"venue"
},
  "geometry": {"coordinates":[145.26060485799999,-37.8710403442],"type":"Point"}
}