{
  "type": "Feature",
  "properties": {
    "addr:full":"36 Barnett Ave Glynde SA 5070",
    "addr:housenumber":"36",
    "addr:postcode":"5070",
    "addr:street":"Barnett Ave",
    "iso:country":"AU",
    "sg:address":"36 Barnett Ave",
    "sg:city":"Glynde",
    "sg:classifiers":[
        {
            "category":"Wholesale",
            "subcategory":"Apparel",
            "type":"Manufacturing & Wholesale Goods"
        }
    ],
    "sg:phone":"+61 8 8336 1245",
    "sg:postcode":"5070",
    "sg:province":"SA",
    "sg:tags":[
        "wholesaler",
        "men's",
        "mfrs",
        "sportswear"
    ],
    "wof:name":"Tanglewood Imports Pty Ltd",
    "wof:placetype":"venue"
},
  "geometry": {"coordinates":[138.65443420400001,-34.8941497803],"type":"Point"}
}