{
  "type": "Feature",
  "properties": {
    "iso:country":"AU",
    "sg:address":"120 Rupert St",
    "sg:city":"Footscray West",
    "sg:classifiers":[
        {
            "category":"Home & Garden",
            "subcategory":"Building Materials",
            "type":"Retail Goods"
        }
    ],
    "sg:phone":"+61 419 878 559",
    "sg:postcode":"3012",
    "sg:province":"VIC",
    "sg:tags":[
        "merchant",
        "glass",
        "glazier"
    ],
    "wof:name":"Aatcall Glass",
    "wof:placetype":"venue"
},
  "geometry": {"coordinates":[144.86831665,-37.7981987],"type":"Point"}
}