{
  "type": "Feature",
  "properties": {
    "addr:full":"Shop 20 Bellbowrie Plaza, Birkin Rd Bellbowrie QLD 4070",
    "addr:housenumber":"shop 20",
    "addr:postcode":"4070",
    "addr:street":"Bellbowrie Plaza Birkin Rd",
    "iso:country":"AU",
    "sg:address":"Shop 20 Bellbowrie Plaza, Birkin Rd",
    "sg:city":"Bellbowrie",
    "sg:classifiers":[
        {
            "category":"Communications",
            "subcategory":"Film & Video Production",
            "type":"Services"
        }
    ],
    "sg:phone":"+61 7 3202 7132",
    "sg:postcode":"4070",
    "sg:province":"QLD",
    "sg:tags":[
        "dvd",
        "library"
    ],
    "wof:name":"Blockbuster",
    "wof:placetype":"venue"
},
  "geometry": {"coordinates":[152.886810303,-27.5619678497],"type":"Point"}
}