{
  "type": "Feature",
  "properties": {
    "iso:country":"AU",
    "sg:address":"453 Nepean Hwy",
    "sg:city":"Chelsea",
    "sg:classifiers":[
        {
            "category":"Fast Food",
            "type":"Food & Drink"
        }
    ],
    "sg:phone":"+61 3 9773 0599",
    "sg:postcode":"3196",
    "sg:province":"VIC",
    "sg:tags":[
        "away",
        "take"
    ],
    "wof:name":"Thai Shore Thai Restaurant",
    "wof:placetype":"venue"
},
  "geometry": {"coordinates":[145.117095947,-38.0550956726],"type":"Point"}
}