{
  "type": "Feature",
  "properties": {
    "addr:full":"42 Gardeners Rd Kingsford NSW 2032",
    "addr:housenumber":"42",
    "addr:postcode":"2032",
    "addr:street":"Gardeners Rd",
    "iso:country":"AU",
    "sg:address":"42 Gardeners Rd",
    "sg:city":"Kingsford",
    "sg:classifiers":[
        {
            "category":"Shopping",
            "subcategory":"Bridal",
            "type":"Retail Goods"
        }
    ],
    "sg:phone":"+61 2 9313 8909",
    "sg:postcode":"2032",
    "sg:province":"NSW",
    "sg:tags":[
        "hire",
        "wear"
    ],
    "wof:name":"Leni Design",
    "wof:placetype":"venue"
},
  "geometry": {"coordinates":[151.225906372,-33.9251022339],"type":"Point"}
}