{
  "type": "Feature",
  "properties": {
    "addr:full":"34- 36 Puckle St Moonee Ponds VIC 3039",
    "addr:housenumber":"36",
    "addr:postcode":"3039",
    "addr:street":"Puckle St",
    "iso:country":"AU",
    "sg:address":"34- 36 Puckle St",
    "sg:city":"Moonee Ponds",
    "sg:classifiers":[
        {
            "category":"Shopping",
            "subcategory":"Clothing, Apparel, & Fashions",
            "type":"Retail Goods"
        }
    ],
    "sg:phone":"+61 3 9375 1760",
    "sg:postcode":"3039",
    "sg:province":"VIC",
    "sg:tags":[
        "lady",
        "wear"
    ],
    "wof:name":"Sportsgirl",
    "wof:placetype":"venue"
},
  "geometry": {"coordinates":[144.923248,-37.766788],"type":"Point"}
}