{
  "type": "Feature",
  "properties": {
    "addr:full":"47 Whitehorse Rd Deepdene VIC 3103",
    "addr:housenumber":"47",
    "addr:postcode":"3103",
    "addr:street":"Whitehorse Rd",
    "iso:country":"AU",
    "sg:address":"47 Whitehorse Rd",
    "sg:city":"Deepdene",
    "sg:classifiers":[
        {
            "category":"Health Services",
            "subcategory":"Health Practitioner",
            "type":"Services"
        }
    ],
    "sg:phone":"+61 3 9817 1544",
    "sg:postcode":"3103",
    "sg:province":"VIC",
    "sg:tags":[
        "physiotherapist"
    ],
    "wof:name":"Benger Hand Therapy",
    "wof:placetype":"venue"
},
  "geometry": {"coordinates":[145.064529419,-37.8106651306],"type":"Point"}
}