{
  "type": "Feature",
  "properties": {
    "addr:full":"Un 20, 84 Stanbel Rd Salisbury Plain SA 5109",
    "addr:housenumber":"84",
    "addr:postcode":"5109",
    "addr:street":"Stanbel Rd",
    "iso:country":"AU",
    "sg:address":"Un 20, 84 Stanbel Rd",
    "sg:city":"Salisbury Plain",
    "sg:classifiers":[
        {
            "category":"Manufacturing",
            "subcategory":"Metals",
            "type":"Manufacturing & Wholesale Goods"
        }
    ],
    "sg:phone":"+61 8 8182 4068",
    "sg:postcode":"5109",
    "sg:province":"SA",
    "sg:tags":[
        "fabricator",
        "aluminium"
    ],
    "wof:name":"E & S Aluminum Windows",
    "wof:placetype":"venue"
},
  "geometry": {"coordinates":[138.66156005900001,-34.7706108093],"type":"Point"}
}