{
  "type": "Feature",
  "properties": {
    "addr:full":"26 Swan St Longreach QLD 4730",
    "addr:housenumber":"26",
    "addr:postcode":"4730",
    "addr:street":"Swan St",
    "iso:country":"AU",
    "sg:address":"26 Swan St",
    "sg:city":"Longreach",
    "sg:classifiers":[
        {
            "category":"Home & Garden",
            "subcategory":"Hardware",
            "type":"Retail Goods"
        }
    ],
    "sg:phone":"+61 7 4658 1732",
    "sg:postcode":"4730",
    "sg:province":"QLD",
    "sg:tags":[
        "generating",
        "set",
        "generator"
    ],
    "wof:name":"Tas Mini Motors",
    "wof:placetype":"venue"
},
  "geometry": {"coordinates":[144.250641,-23.444574],"type":"Point"}
}