{
  "type": "Feature",
  "properties": {
    "addr:full":"Brady St Midway Point TAS 7171",
    "addr:postcode":"7171",
    "addr:street":"Brady St",
    "iso:country":"AU",
    "sg:address":"Brady St",
    "sg:city":"Midway Point",
    "sg:classifiers":[
        {
            "category":"Recreation",
            "subcategory":"Sailing Club",
            "type":"Entertainment"
        }
    ],
    "sg:phone":"+61 3 6265 2078",
    "sg:postcode":"7171",
    "sg:province":"TAS",
    "sg:tags":[
        "yacht"
    ],
    "wof:name":"Midway Point Yacht Club",
    "wof:placetype":"venue"
},
  "geometry": {"coordinates":[147.52818298299999,-42.8008117676],"type":"Point"}
}