{
  "type": "Feature",
  "properties": {
    "addr:full":"133 Belgrave-Gembrook Rd Selby VIC 3159",
    "addr:housenumber":"133",
    "addr:postcode":"3159",
    "addr:street":"Belgrave-Gembrook Rd",
    "iso:country":"AU",
    "sg:address":"133 Belgrave-Gembrook Rd",
    "sg:city":"Selby",
    "sg:classifiers":[
        {
            "category":"Retail",
            "subcategory":"Auto Repair",
            "type":"Services"
        }
    ],
    "sg:phone":"+61 3 9754 5544",
    "sg:postcode":"3159",
    "sg:province":"VIC",
    "sg:tags":[
        "muffler",
        "exhaust",
        "system"
    ],
    "wof:name":"T J R Motors",
    "wof:placetype":"venue"
},
  "geometry": {"coordinates":[145.41839599599999,-37.9344711304],"type":"Point"}
}