{
  "type": "Feature",
  "properties": {
    "iso:country":"AU",
    "sg:address":"``Taramayne'' Profkes Rd",
    "sg:city":"Mt Tarampa",
    "sg:classifiers":[
        {
            "category":"Farming",
            "subcategory":"Farm",
            "type":"Manufacturing & Wholesale Goods"
        }
    ],
    "sg:phone":"+61 7 5427 9900",
    "sg:postcode":"4311",
    "sg:province":"QLD",
    "sg:tags":[
        "farmer"
    ],
    "wof:name":"Mayne Ray & Di",
    "wof:placetype":"venue"
},
  "geometry": {"coordinates":[152.49067688,-27.4520587921],"type":"Point"}
}