{
  "type": "Feature",
  "properties": {
    "iso:country":"AU",
    "sg:address":"24 Mawby Rd",
    "sg:city":"Bentleigh East",
    "sg:classifiers":[
        {
            "category":"Utilities",
            "subcategory":"Electric",
            "type":"Services"
        }
    ],
    "sg:phone":"+61 3 9563 9604",
    "sg:postcode":"3165",
    "sg:province":"VIC",
    "sg:tags":[
        "electrical",
        "contractor"
    ],
    "wof:name":"Humphries Electrics Pty Ltd",
    "wof:placetype":"venue"
},
  "geometry": {"coordinates":[145.05203247099999,-37.9290657043],"type":"Point"}
}