{
  "type": "Feature",
  "properties": {
    "iso:country":"AU",
    "sg:address":"Level 3, 19- 25 Raglan St",
    "sg:city":"South Melbourne",
    "sg:classifiers":[
        {
            "category":"Professional",
            "subcategory":"Employment Agencies",
            "type":"Services"
        }
    ],
    "sg:phone":"+61 3 9686 9881",
    "sg:postcode":"3205",
    "sg:province":"VIC",
    "wof:name":"Burnden Consulting Pty Ltd",
    "wof:placetype":"venue"
},
  "geometry": {"coordinates":[144.96566799999999,-37.836693],"type":"Point"}
}