{
  "type": "Feature",
  "properties": {
    "addr:full":"8006 Melbourne Rd Shepparton South VIC 3630",
    "addr:housenumber":"8006",
    "addr:postcode":"3630",
    "addr:street":"Melbourne Rd",
    "iso:country":"AU",
    "sg:address":"8006 Melbourne Rd",
    "sg:city":"Shepparton South",
    "sg:classifiers":[
        {
            "category":"Building & Trades",
            "subcategory":"Construction",
            "type":"Services"
        }
    ],
    "sg:phone":"+61 3 5823 1590",
    "sg:postcode":"3630",
    "sg:province":"VIC",
    "sg:tags":[
        "window",
        "tinting"
    ],
    "wof:name":"Tint King",
    "wof:placetype":"venue"
},
  "geometry": {"coordinates":[145.39349365199999,-36.4104118347],"type":"Point"}
}