{
  "type": "Feature",
  "properties": {
    "iso:country":"AU",
    "sg:address":"Cnr Caloundra St & Trevally St",
    "sg:city":"Manly West",
    "sg:classifiers":[
        {
            "category":"Food & Beverages",
            "subcategory":"Liquor & Beverages",
            "type":"Retail Goods"
        }
    ],
    "sg:phone":"+61 7 3348 3211",
    "sg:postcode":"4179",
    "sg:province":"QLD",
    "sg:tags":[
        "store"
    ],
    "wof:name":"Manly West Cellars",
    "wof:placetype":"venue"
},
  "geometry": {"coordinates":[153.17816162099999,-27.4578819275],"type":"Point"}
}