{
  "type": "Feature",
  "properties": {
    "addr:full":"Elfreda Ave Sorrento WA 6020",
    "addr:postcode":"6020",
    "addr:street":"Elfreda Ave",
    "iso:country":"AU",
    "sg:address":"Elfreda Ave",
    "sg:city":"Sorrento",
    "sg:classifiers":[
        {
            "category":"Education",
            "subcategory":"School",
            "type":"Public Place"
        }
    ],
    "sg:phone":"+61 8 9447 7488",
    "sg:postcode":"6020",
    "sg:province":"WA",
    "sg:tags":[
        "state",
        "except",
        "nsw"
    ],
    "wof:name":"Sorrento Primary",
    "wof:placetype":"venue"
},
  "geometry": {"coordinates":[115.760887146,-31.8304920197],"type":"Point"}
}