{
  "type": "Feature",
  "properties": {
    "iso:country":"AU",
    "sg:address":"61 High St",
    "sg:city":"Broadford",
    "sg:classifiers":[
        {
            "category":"Personal",
            "subcategory":"Beauty Salon",
            "type":"Services"
        }
    ],
    "sg:phone":"+61 3 5784 4260",
    "sg:postcode":"3658",
    "sg:province":"VIC",
    "sg:tags":[
        "hairdresser"
    ],
    "wof:name":"Studio 61 Hair Design",
    "wof:placetype":"venue"
},
  "geometry": {"coordinates":[145.04550170900001,-37.2049789429],"type":"Point"}
}