{
  "type": "Feature",
  "properties": {
    "iso:country":"AU",
    "sg:address":"Shop 16",
    "sg:city":"B Sunny Park Shopping Cntr Sunnybank South",
    "sg:classifiers":[
        {
            "category":"Real Estate",
            "subcategory":"Real Estate Agent",
            "type":"Services"
        }
    ],
    "sg:phone":"+61 7 3345 9288",
    "sg:postcode":"4109",
    "sg:province":"QLD",
    "wof:name":"Raine & Horne (Qld) Pty Ltd",
    "wof:placetype":"venue"
},
  "geometry": {"coordinates":[153.04458618199999,-27.5935344696],"type":"Point"}
}