{
  "type": "Feature",
  "properties": {
    "addr:full":"143 Bukulla St Wacol QLD 4076",
    "addr:housenumber":"143",
    "addr:postcode":"4076",
    "addr:street":"Bukulla St",
    "iso:country":"AU",
    "sg:address":"143 Bukulla St",
    "sg:city":"Wacol",
    "sg:classifiers":[
        {
            "category":"Commercial Area",
            "type":"Public Place"
        }
    ],
    "sg:phone":"+61 418 878 214",
    "sg:postcode":"4076",
    "sg:province":"QLD",
    "sg:tags":[
        "heavy",
        "carrier"
    ],
    "wof:name":"Performance Transport",
    "wof:placetype":"venue"
},
  "geometry": {"coordinates":[152.93951415999999,-27.590839386],"type":"Point"}
}