{
  "type": "Feature",
  "properties": {
    "iso:country":"AU",
    "sg:address":"10a McDowell Crs",
    "sg:city":"Kingsley",
    "sg:classifiers":[
        {
            "category":"Professional",
            "subcategory":"Art Services",
            "type":"Services"
        }
    ],
    "sg:phone":"+61 8 9409 2038",
    "sg:postcode":"6026",
    "sg:province":"WA",
    "sg:tags":[
        "decorator",
        "painter"
    ],
    "wof:name":"Prout's Painting Service",
    "wof:placetype":"venue"
},
  "geometry": {"coordinates":[115.803192139,-31.8136672974],"type":"Point"}
}