{
  "type": "Feature",
  "properties": {
    "addr:full":"The Dawn, Holding Rd Gympie QLD 4570",
    "addr:postcode":"4570",
    "addr:street":"Holding Rd",
    "iso:country":"AU",
    "sg:address":"The Dawn, Holding Rd",
    "sg:city":"Gympie",
    "sg:classifiers":[
        {
            "category":"Building & Trades",
            "subcategory":"Construction",
            "type":"Services"
        }
    ],
    "sg:phone":"+61 427 832 878",
    "sg:postcode":"4570",
    "sg:province":"QLD",
    "sg:tags":[
        "fencing",
        "contractor"
    ],
    "wof:name":"BJ Busiko Fencing",
    "wof:placetype":"venue"
},
  "geometry": {"coordinates":[152.68255615199999,-26.2461738586],"type":"Point"}
}