{
  "type": "Feature",
  "properties": {
    "iso:country":"AU",
    "sg:address":"14 Kiama Rd",
    "sg:city":"Flemington",
    "sg:classifiers":[
        {
            "category":"Professional",
            "subcategory":"Computer Services",
            "type":"Services"
        }
    ],
    "sg:phone":"+61 3 9372 5177",
    "sg:postcode":"3031",
    "sg:province":"VIC",
    "sg:tags":[
        "package",
        "software"
    ],
    "wof:name":"Passionelle Pty Ltd",
    "wof:placetype":"venue"
},
  "geometry": {"coordinates":[144.92631499999999,-37.785313],"type":"Point"}
}