{
  "type": "Feature",
  "properties": {
    "addr:full":"42 Mabel St Atherton QLD 4883",
    "addr:housenumber":"42",
    "addr:postcode":"4883",
    "addr:street":"Mabel St",
    "iso:country":"AU",
    "sg:address":"42 Mabel St",
    "sg:city":"Atherton",
    "sg:classifiers":[
        {
            "category":"Health Services",
            "subcategory":"Health Practitioner",
            "type":"Services"
        }
    ],
    "sg:phone":"+61 7 4091 1277",
    "sg:postcode":"4883",
    "sg:province":"QLD",
    "sg:tags":[
        "alternative"
    ],
    "wof:name":"Transformational Healing Centre",
    "wof:placetype":"venue"
},
  "geometry": {"coordinates":[145.47642517099999,-17.2677650452],"type":"Point"}
}