{
  "type": "Feature",
  "properties": {
    "iso:country":"AU",
    "sg:address":"70 Fenwick St",
    "sg:city":"Clifton Hill",
    "sg:classifiers":[
        {
            "category":"Personal",
            "type":"Services"
        }
    ],
    "sg:phone":"+61 407 177 457",
    "sg:postcode":"3068",
    "sg:province":"VIC",
    "sg:tags":[
        "career",
        "counselling"
    ],
    "wof:name":"Peter Hille Careers Counsellor",
    "wof:placetype":"venue"
},
  "geometry": {"coordinates":[144.99969482399999,-37.786441803],"type":"Point"}
}