{
  "type": "Feature",
  "properties": {
    "iso:country":"AU",
    "sg:address":"33 Royal Pde",
    "sg:city":"Banyo",
    "sg:classifiers":[
        {
            "category":"Personal",
            "subcategory":"Beauty Salon",
            "type":"Services"
        }
    ],
    "sg:phone":"+61 7 3267 7626",
    "sg:postcode":"4014",
    "sg:province":"QLD",
    "wof:name":"Mi Salon",
    "wof:placetype":"venue"
},
  "geometry": {"coordinates":[153.07664489699999,-27.3753147125],"type":"Point"}
}