{
  "type": "Feature",
  "properties": {
    "addr:full":"12 Langs Rd Langwarrin VIC 3910",
    "addr:housenumber":"12",
    "addr:postcode":"3910",
    "addr:street":"Langs Rd",
    "iso:country":"AU",
    "sg:address":"12 Langs Rd",
    "sg:city":"Langwarrin",
    "sg:classifiers":[
        {
            "category":"Home & Garden",
            "subcategory":"Building Materials",
            "type":"Retail Goods"
        }
    ],
    "sg:phone":"+61 3 9776 7418",
    "sg:postcode":"3910",
    "sg:province":"VIC",
    "sg:tags":[
        "merchant",
        "glass",
        "glazier"
    ],
    "wof:name":"Banks Glass",
    "wof:placetype":"venue"
},
  "geometry": {"coordinates":[145.191574097,-38.1561737061],"type":"Point"}
}