{
  "type": "Feature",
  "properties": {
    "iso:country":"AU",
    "sg:address":"17 Rock St",
    "sg:city":"Yagoona",
    "sg:classifiers":[
        {
            "category":"Professional",
            "subcategory":"Management & Consulting",
            "type":"Services"
        }
    ],
    "sg:phone":"+61 419 621 992",
    "sg:postcode":"2199",
    "sg:province":"NSW",
    "sg:tags":[
        "consultant"
    ],
    "wof:name":"J G Quality Consulting",
    "wof:placetype":"venue"
},
  "geometry": {"coordinates":[151.011505,-33.903339],"type":"Point"}
}