{
  "type": "Feature",
  "properties": {
    "iso:country":"AU",
    "sg:address":"79 Gairloch St",
    "sg:city":"Mt Pleasant",
    "sg:classifiers":[
        {
            "category":"Military Area",
            "subcategory":"Air Force Base",
            "type":"Public Place"
        }
    ],
    "sg:phone":"+61 8 9364 1189",
    "sg:postcode":"6153",
    "sg:province":"WA",
    "sg:tags":[
        "men's",
        "tailor"
    ],
    "wof:name":"Marzo R J",
    "wof:placetype":"venue"
},
  "geometry": {"coordinates":[115.840721,-32.017075],"type":"Point"}
}