{
  "type": "Feature",
  "properties": {
    "addr:full":"62 Hawthorn St Dubbo NSW 2830",
    "addr:housenumber":"62",
    "addr:postcode":"2830",
    "addr:street":"Hawthorn St",
    "iso:country":"AU",
    "sg:address":"62 Hawthorn St",
    "sg:city":"Dubbo",
    "sg:classifiers":[
        {
            "category":"Home & Garden",
            "subcategory":"Carpets & Floor Coverings",
            "type":"Retail Goods"
        }
    ],
    "sg:phone":"+61 2 6882 8911",
    "sg:postcode":"2830",
    "sg:province":"NSW",
    "sg:tags":[
        "layer",
        "planner"
    ],
    "wof:name":"Crampton Bob",
    "wof:placetype":"venue"
},
  "geometry": {"coordinates":[148.62388610799999,-32.263130188],"type":"Point"}
}