{
  "type": "Feature",
  "properties": {
    "addr:full":"2 Alexander St Dundas NSW 2117",
    "addr:housenumber":"2",
    "addr:postcode":"2117",
    "addr:street":"Alexander St",
    "iso:country":"AU",
    "sg:address":"2 Alexander St",
    "sg:city":"Dundas",
    "sg:classifiers":[
        {
            "category":"Health Services",
            "subcategory":"Dentist",
            "type":"Services"
        }
    ],
    "sg:phone":"+61 2 9871 1110",
    "sg:postcode":"2117",
    "sg:province":"NSW",
    "wof:name":"Cheung J",
    "wof:placetype":"venue"
},
  "geometry": {"coordinates":[151.05659484899999,-33.7941894531],"type":"Point"}
}