{
  "type": "Feature",
  "properties": {
    "iso:country":"AU",
    "sg:address":"108 St Georges Rd",
    "sg:city":"Beaconsfield Upper",
    "sg:classifiers":[
        {
            "category":"Retail",
            "subcategory":"Auto Repair",
            "type":"Services"
        }
    ],
    "sg:phone":"+61 3 5944 4502",
    "sg:postcode":"3808",
    "sg:province":"VIC",
    "sg:tags":[
        "repairer",
        "motor",
        "engineer"
    ],
    "wof:name":"Berwick Four Wheel Drive Centre",
    "wof:placetype":"venue"
},
  "geometry": {"coordinates":[145.390457,-37.990017],"type":"Point"}
}