{
  "type": "Feature",
  "properties": {
    "iso:country":"AU",
    "sg:address":"Cnr Russell & Merrivale Sts",
    "sg:city":"Tumut",
    "sg:classifiers":[
        {
            "category":"Autos & Motor Vehicles",
            "subcategory":"Automobile Sales",
            "type":"Retail Goods"
        }
    ],
    "sg:phone":"+61 2 6947 1133",
    "sg:postcode":"2720",
    "sg:province":"NSW",
    "sg:tags":[
        "car",
        "new"
    ],
    "wof:name":"Parktown Autos Tumut",
    "wof:placetype":"venue"
},
  "geometry": {"coordinates":[148.208603,-35.299],"type":"Point"}
}