{
  "type": "Feature",
  "properties": {
    "iso:country":"AU",
    "sg:address":"24 Newman St",
    "sg:city":"Wangaratta",
    "sg:classifiers":[
        {
            "category":"Building & Trades",
            "subcategory":"Construction",
            "type":"Services"
        }
    ],
    "sg:phone":"+61 3 5722 1040",
    "sg:postcode":"3676",
    "sg:province":"VIC",
    "sg:tags":[
        "insulation",
        "contractor"
    ],
    "wof:name":"North East Insulation Service",
    "wof:placetype":"venue"
},
  "geometry": {"coordinates":[146.31088299999999,-36.366138],"type":"Point"}
}