{
  "type": "Feature",
  "properties": {
    "iso:country":"AU",
    "sg:address":"Sport & Recreation House 10 Selfs Point Rd",
    "sg:city":"Cornelian Bay",
    "sg:classifiers":[
        {
            "category":"Organizations",
            "subcategory":"Non-profit Organization",
            "type":"Services"
        }
    ],
    "sg:phone":"+61 3 6278 7299",
    "sg:postcode":"7008",
    "sg:province":"TAS",
    "sg:tags":[
        "support",
        "disability",
        "organisation"
    ],
    "wof:name":"Brain Injury Association of Tasmania",
    "wof:placetype":"venue"
},
  "geometry": {"coordinates":[147.315963745,-42.8503761292],"type":"Point"}
}