{
  "type": "Feature",
  "properties": {
    "addr:full":"7 Light St Fortitude Valley QLD 4006",
    "addr:housenumber":"7",
    "addr:postcode":"4006",
    "addr:street":"Light St",
    "iso:country":"AU",
    "sg:address":"7 Light St",
    "sg:city":"Fortitude Valley",
    "sg:classifiers":[
        {
            "category":"Home & Garden",
            "subcategory":"Carpets & Floor Coverings",
            "type":"Retail Goods"
        }
    ],
    "sg:phone":"+61 412 135 111",
    "sg:postcode":"4006",
    "sg:province":"QLD",
    "sg:tags":[
        "tile",
        "wall"
    ],
    "wof:name":"Tileform",
    "wof:placetype":"venue"
},
  "geometry": {"coordinates":[153.03895568900001,-27.4513092041],"type":"Point"}
}