{
  "type": "Feature",
  "properties": {
    "iso:country":"AU",
    "sg:address":"199 Pacific Hwy",
    "sg:city":"Charlestown",
    "sg:classifiers":[
        {
            "category":"Real Estate",
            "subcategory":"Real Estate Agent",
            "type":"Services"
        }
    ],
    "sg:phone":"+61 2 4943 4446",
    "sg:postcode":"2290",
    "sg:province":"NSW",
    "wof:name":"Creer Property",
    "wof:placetype":"venue"
},
  "geometry": {"coordinates":[151.69720459000001,-32.9613761902],"type":"Point"}
}