{
  "type": "Feature",
  "properties": {
    "addr:full":"8- 12 Bannister St Fremantle WA 6160",
    "addr:housenumber":"12",
    "addr:postcode":"6160",
    "addr:street":"8;Bannister St",
    "iso:country":"AU",
    "sg:address":"8- 12 Bannister St",
    "sg:city":"Fremantle",
    "sg:classifiers":[
        {
            "category":"Arts & Performance",
            "subcategory":"Art Gallery",
            "type":"Entertainment"
        }
    ],
    "sg:phone":"+61 8 9336 2035",
    "sg:postcode":"6160",
    "sg:province":"WA",
    "wof:name":"Bannister St Craftworks",
    "wof:placetype":"venue"
},
  "geometry": {"coordinates":[115.746109,-32.055267],"type":"Point"}
}