{
  "type": "Feature",
  "properties": {
    "iso:country":"AU",
    "sg:address":"29 Cowie St",
    "sg:city":"Geelong North",
    "sg:classifiers":[
        {
            "category":"Professional",
            "type":"Services"
        }
    ],
    "sg:phone":"+61 3 5277 9001",
    "sg:postcode":"3215",
    "sg:province":"VIC",
    "sg:tags":[
        "transport"
    ],
    "wof:name":"National Network Removals",
    "wof:placetype":"venue"
},
  "geometry": {"coordinates":[144.349365234,-38.1058998108],"type":"Point"}
}