{
  "type": "Feature",
  "properties": {
    "addr:full":"58 Church St Penola SA 5277",
    "addr:housenumber":"58",
    "addr:postcode":"5277",
    "addr:street":"Church St",
    "iso:country":"AU",
    "sg:address":"58 Church St",
    "sg:city":"Penola",
    "sg:classifiers":[
        {
            "category":"Travel",
            "subcategory":"Hotels & Motels",
            "type":"Entertainment"
        }
    ],
    "sg:phone":"+61 8 8737 2402",
    "sg:postcode":"5277",
    "sg:province":"SA",
    "wof:name":"Prince Of Wales Hotel Motel",
    "wof:placetype":"venue"
},
  "geometry": {"coordinates":[140.83665500000001,-37.377773],"type":"Point"}
}