{
  "type": "Feature",
  "properties": {
    "iso:country":"AU",
    "sg:address":"21 Shepherd St",
    "sg:city":"Marrickville",
    "sg:classifiers":[
        {
            "category":"Professional",
            "subcategory":"Printing & Photocopies",
            "type":"Services"
        }
    ],
    "sg:phone":"+61 2 9569 3250",
    "sg:postcode":"2204",
    "sg:province":"NSW",
    "sg:tags":[
        "textile",
        "clothing"
    ],
    "wof:name":"X S Grades",
    "wof:placetype":"venue"
},
  "geometry": {"coordinates":[151.164001,-33.903671],"type":"Point"}
}