{
  "type": "Feature",
  "properties": {
    "iso:country":"AU",
    "sg:address":"2 Bellion Drv",
    "sg:city":"Hamilton Hill",
    "sg:classifiers":[
        {
            "category":"Professional",
            "type":"Services"
        }
    ],
    "sg:phone":"+61 8 9335 3468",
    "sg:postcode":"6163",
    "sg:province":"WA",
    "sg:tags":[
        "spray",
        "painting"
    ],
    "wof:name":"Geoff Murphy Automotives",
    "wof:placetype":"venue"
},
  "geometry": {"coordinates":[115.761421,-32.081764],"type":"Point"}
}