{
  "type": "Feature",
  "properties": {
    "addr:full":"484 The Entrance Rd Erina Heights NSW 2260",
    "addr:housenumber":"484",
    "addr:postcode":"2260",
    "addr:street":"The Entrance Rd",
    "iso:country":"AU",
    "sg:address":"484 The Entrance Rd",
    "sg:city":"Erina Heights",
    "sg:classifiers":[
        {
            "category":"Professional",
            "subcategory":"Accounting & Tax Preparation",
            "type":"Services"
        }
    ],
    "sg:phone":"+61 2 4365 6789",
    "sg:postcode":"2260",
    "sg:province":"NSW",
    "sg:tags":[
        "consultant",
        "taxation"
    ],
    "wof:name":"Freeman Kennedy",
    "wof:placetype":"venue"
},
  "geometry": {"coordinates":[151.41213999999999,-33.426113],"type":"Point"}
}