{
  "type": "Feature",
  "properties": {
    "addr:full":"8 Heald Rd Ingleburn NSW 2565",
    "addr:housenumber":"8",
    "addr:postcode":"2565",
    "addr:street":"Heald Rd",
    "iso:country":"AU",
    "sg:address":"8 Heald Rd",
    "sg:city":"Ingleburn",
    "sg:classifiers":[
        {
            "category":"Utilities",
            "subcategory":"Refuse",
            "type":"Services"
        }
    ],
    "sg:phone":"+61 1300 662 114",
    "sg:postcode":"2565",
    "sg:province":"NSW",
    "sg:tags":[
        "disposal",
        "reduction",
        "waste"
    ],
    "wof:name":"Skip Master Waste Management",
    "wof:placetype":"venue"
},
  "geometry": {"coordinates":[150.85533142099999,-34.002155304],"type":"Point"}
}