{
  "type": "Feature",
  "properties": {
    "iso:country":"AU",
    "sg:address":"31 Errol Ave",
    "sg:city":"Paradise Point",
    "sg:classifiers":[
        {
            "category":"Utilities",
            "subcategory":"Electric",
            "type":"Services"
        }
    ],
    "sg:phone":"+61 408 967 322",
    "sg:postcode":"4216",
    "sg:province":"QLD",
    "sg:tags":[
        "electrical",
        "contractor"
    ],
    "wof:name":"Kane Duncan Electrical Contractor",
    "wof:placetype":"venue"
},
  "geometry": {"coordinates":[153.394256592,-27.8882637024],"type":"Point"}
}