{
  "type": "Feature",
  "properties": {
    "iso:country":"AU",
    "sg:address":"U 4/ 12 Devon St",
    "sg:city":"Lonsdale",
    "sg:classifiers":[
        {
            "category":"Retail",
            "subcategory":"Storage",
            "type":"Services"
        }
    ],
    "sg:phone":"+61 8 8186 4100",
    "sg:postcode":"5160",
    "sg:province":"SA",
    "sg:tags":[
        "shelving",
        "system"
    ],
    "wof:name":"Unique Shopfitters",
    "wof:placetype":"venue"
},
  "geometry": {"coordinates":[138.501022339,-35.1166191101],"type":"Point"}
}