{
  "type": "Feature",
  "properties": {
    "addr:full":"58 Booker Bay Rd Booker Bay NSW 2257",
    "addr:housenumber":"58",
    "addr:postcode":"2257",
    "addr:street":"Booker Bay Rd",
    "iso:country":"AU",
    "sg:address":"58 Booker Bay Rd",
    "sg:city":"Booker Bay",
    "sg:classifiers":[
        {
            "category":"Retail",
            "subcategory":"Auto Repair",
            "type":"Services"
        }
    ],
    "sg:phone":"+61 2 4344 6344",
    "sg:postcode":"2257",
    "sg:province":"NSW",
    "sg:tags":[
        "engine",
        "reconditioning"
    ],
    "wof:name":"All Metal Welding Pty Ltd",
    "wof:placetype":"venue"
},
  "geometry": {"coordinates":[151.344284058,-33.5105667114],"type":"Point"}
}