{
  "type": "Feature",
  "properties": {
    "addr:full":"18 Vasey St Bentleigh East VIC 3165",
    "addr:housenumber":"18",
    "addr:postcode":"3165",
    "addr:street":"Vasey St",
    "iso:country":"AU",
    "sg:address":"18 Vasey St",
    "sg:city":"Bentleigh East",
    "sg:classifiers":[
        {
            "category":"Utilities",
            "subcategory":"Water",
            "type":"Services"
        }
    ],
    "sg:phone":"+61 418 397 739",
    "sg:postcode":"3165",
    "sg:province":"VIC",
    "sg:tags":[
        "equipment",
        "treatment"
    ],
    "wof:name":"Aquacool Water Purifiers",
    "wof:placetype":"venue"
},
  "geometry": {"coordinates":[145.063552856,-37.934753418],"type":"Point"}
}