{
  "type": "Feature",
  "properties": {
    "addr:full":"37 Leyshon Crt Bonogin QLD 4213",
    "addr:housenumber":"37",
    "addr:postcode":"4213",
    "addr:street":"Leyshon Crt",
    "iso:country":"AU",
    "sg:address":"37 Leyshon Crt",
    "sg:city":"Bonogin",
    "sg:classifiers":[
        {
            "category":"Building & Trades",
            "subcategory":"Construction",
            "type":"Services"
        }
    ],
    "sg:phone":"+61 7 5525 1250",
    "sg:postcode":"4213",
    "sg:province":"QLD",
    "sg:tags":[
        "contractor"
    ],
    "wof:name":"Fenton Ian",
    "wof:placetype":"venue"
},
  "geometry": {"coordinates":[153.349533081,-28.1194725037],"type":"Point"}
}