{
  "type": "Feature",
  "properties": {
    "addr:full":"11 Wason St Ulladulla NSW 2539",
    "addr:housenumber":"11",
    "addr:postcode":"2539",
    "addr:street":"Wason St",
    "iso:country":"AU",
    "sg:address":"11 Wason St",
    "sg:city":"Ulladulla",
    "sg:classifiers":[
        {
            "category":"Shopping",
            "subcategory":"Clothing, Apparel, & Fashions",
            "type":"Retail Goods"
        }
    ],
    "sg:phone":"+61 2 4455 3015",
    "sg:postcode":"2539",
    "sg:province":"NSW",
    "sg:tags":[
        "lady",
        "wear"
    ],
    "wof:name":"Pipi's of Ulladulla",
    "wof:placetype":"venue"
},
  "geometry": {"coordinates":[150.47419738799999,-35.3582038879],"type":"Point"}
}