{
  "type": "Feature",
  "properties": {
    "addr:full":"57 Edden St Cessnock NSW 2325",
    "addr:housenumber":"57",
    "addr:postcode":"2325",
    "addr:street":"Edden St",
    "iso:country":"AU",
    "sg:address":"57 Edden St",
    "sg:city":"Cessnock",
    "sg:classifiers":[
        {
            "category":"Wholesale",
            "subcategory":"Painting Supplies",
            "type":"Manufacturing & Wholesale Goods"
        }
    ],
    "sg:phone":"+61 2 4991 1880",
    "sg:postcode":"2325",
    "sg:province":"NSW",
    "sg:tags":[
        "painter"
    ],
    "wof:name":"Bower Brush & Roller Co",
    "wof:placetype":"venue"
},
  "geometry": {"coordinates":[151.30758667000001,-32.8579788208],"type":"Point"}
}