{
  "type": "Feature",
  "properties": {
    "iso:country":"AU",
    "sg:address":"2 Post Office St",
    "sg:city":"Pymble",
    "sg:classifiers":[
        {
            "category":"Personal",
            "subcategory":"Beauty Salon",
            "type":"Services"
        }
    ],
    "sg:phone":"+61 2 9488 7173",
    "sg:postcode":"2073",
    "sg:province":"NSW",
    "sg:tags":[
        "hairdresser"
    ],
    "wof:name":"Troy Tanner Hair Design",
    "wof:placetype":"venue"
},
  "geometry": {"coordinates":[151.141311645,-33.7440452576],"type":"Point"}
}