{
  "type": "Feature",
  "properties": {
    "iso:country":"AU",
    "sg:address":"15 Kerr St",
    "sg:city":"Ballina",
    "sg:classifiers":[
        {
            "category":"Shopping",
            "subcategory":"Computers & Home Electronics",
            "type":"Retail Goods"
        }
    ],
    "sg:phone":"+61 2 6686 6638",
    "sg:postcode":"2478",
    "sg:province":"NSW",
    "sg:tags":[
        "equipment",
        "supply"
    ],
    "wof:name":"Cartridge World",
    "wof:placetype":"venue"
},
  "geometry": {"coordinates":[153.55540466299999,-28.8673152924],"type":"Point"}
}