{
  "type": "Feature",
  "properties": {
    "iso:country":"AU",
    "sg:address":"1/ 4 First Ave",
    "sg:city":"Sawtell",
    "sg:classifiers":[
        {
            "category":"Arts & Performance",
            "subcategory":"Art Gallery",
            "type":"Entertainment"
        }
    ],
    "sg:phone":"+61 412 399 242",
    "sg:postcode":"2452",
    "sg:province":"NSW",
    "wof:name":"Cooinda Gallery Aboriginal Desert Art",
    "wof:placetype":"venue"
},
  "geometry": {"coordinates":[153.099854,-30.369825],"type":"Point"}
}