{
  "type": "Feature",
  "properties": {
    "addr:full":"26 Swan Rd Morwell VIC 3840",
    "addr:housenumber":"26",
    "addr:postcode":"3840",
    "addr:street":"Swan Rd",
    "iso:country":"AU",
    "sg:address":"26 Swan Rd",
    "sg:city":"Morwell",
    "sg:classifiers":[
        {
            "category":"Building & Trades",
            "subcategory":"Construction",
            "type":"Services"
        }
    ],
    "sg:phone":"+61 3 5128 5879",
    "sg:postcode":"3840",
    "sg:province":"VIC",
    "sg:tags":[
        "window",
        "aluminium"
    ],
    "wof:name":"Valley Windows",
    "wof:placetype":"venue"
},
  "geometry": {"coordinates":[146.443634033,-38.2397232056],"type":"Point"}
}