{
  "type": "Feature",
  "properties": {
    "addr:full":"33 Gordon St Mt Gambier SA 5290",
    "addr:housenumber":"33",
    "addr:postcode":"5290",
    "addr:street":"Gordon St",
    "iso:country":"AU",
    "sg:address":"33 Gordon St",
    "sg:city":"Mt Gambier",
    "sg:classifiers":[
        {
            "category":"Professional",
            "subcategory":"Printing & Photocopies",
            "type":"Services"
        }
    ],
    "sg:phone":"+61 8 8724 9311",
    "sg:postcode":"5290",
    "sg:province":"SA",
    "sg:tags":[
        "trophy"
    ],
    "wof:name":"Pulfords Prize Products",
    "wof:placetype":"venue"
},
  "geometry": {"coordinates":[140.76431299999999,-37.819752],"type":"Point"}
}