{
  "type": "Feature",
  "properties": {
    "iso:country":"AU",
    "sg:address":"147 Lyons St",
    "sg:city":"Bungalow",
    "sg:classifiers":[
        {
            "category":"Home & Garden",
            "subcategory":"Hardware",
            "type":"Retail Goods"
        }
    ],
    "sg:phone":"+61 7 4041 1988",
    "sg:postcode":"4870",
    "sg:province":"QLD",
    "sg:tags":[
        "plumber",
        "supply"
    ],
    "wof:name":"Reece Pty. Ltd.",
    "wof:placetype":"venue"
},
  "geometry": {"coordinates":[145.755737305,-16.9395008087],"type":"Point"}
}