{
  "type": "Feature",
  "properties": {
    "addr:full":"115 West High St Coffs Harbour NSW 2450",
    "addr:housenumber":"115",
    "addr:postcode":"2450",
    "addr:street":"West High St",
    "iso:country":"AU",
    "sg:address":"115 West High St",
    "sg:city":"Coffs Harbour",
    "sg:classifiers":[
        {
            "category":"Home & Garden",
            "subcategory":"Furniture",
            "type":"Retail Goods"
        }
    ],
    "sg:phone":"+61 2 6651 1540",
    "sg:postcode":"2450",
    "sg:province":"NSW",
    "sg:tags":[
        "business"
    ],
    "wof:name":"OfficeMax Australia Ltd",
    "wof:placetype":"venue"
},
  "geometry": {"coordinates":[153.111984253,-30.2956771851],"type":"Point"}
}