{
  "type": "Feature",
  "properties": {
    "addr:full":"Princes Hwy Kembla Grange NSW 2526",
    "addr:postcode":"2526",
    "addr:street":"Princes Hwy",
    "iso:country":"AU",
    "sg:address":"Princes Hwy",
    "sg:city":"Kembla Grange",
    "sg:classifiers":[
        {
            "category":"Retail",
            "subcategory":"Event Space",
            "type":"Services"
        }
    ],
    "sg:phone":"+61 2 4261 1647",
    "sg:postcode":"2526",
    "sg:province":"NSW",
    "sg:tags":[
        "venue",
        "reception",
        "wedding"
    ],
    "wof:name":"Grange Golf Club Limited The",
    "wof:placetype":"venue"
},
  "geometry": {"coordinates":[150.80335998499999,-34.4817581177],"type":"Point"}
}