{
  "type": "Feature",
  "properties": {
    "addr:full":"Suite 3, 27 Watt St Newcastle NSW 2300",
    "addr:housenumber":"27",
    "addr:postcode":"2300",
    "addr:street":"Watt St",
    "iso:country":"AU",
    "sg:address":"Suite 3, 27 Watt St",
    "sg:city":"Newcastle",
    "sg:classifiers":[
        {
            "category":"Health Services",
            "subcategory":"Health Practitioner",
            "type":"Services"
        }
    ],
    "sg:phone":"+61 2 4942 0596",
    "sg:postcode":"2300",
    "sg:province":"NSW",
    "sg:tags":[
        "psychologist"
    ],
    "wof:name":"Specialist Psychological Services Pty Ltd",
    "wof:placetype":"venue"
},
  "geometry": {"coordinates":[151.78436300000001,-32.928207],"type":"Point"}
}