{
  "type": "Feature",
  "properties": {
    "addr:full":"cnr Greenhill Rd & Devereux Rd Linden Park SA 5065",
    "addr:postcode":"5065",
    "addr:street":"Greenhill Rd & Devereux Rd",
    "iso:country":"AU",
    "sg:address":"cnr Greenhill Rd & Devereux Rd",
    "sg:city":"Linden Park",
    "sg:classifiers":[
        {
            "category":"Restaurant",
            "type":"Food & Drink"
        }
    ],
    "sg:phone":"+61 8 8379 6888",
    "sg:postcode":"5065",
    "sg:province":"SA",
    "wof:name":"East Asian Bistro",
    "wof:placetype":"venue"
},
  "geometry": {"coordinates":[138.643844605,-34.939163208],"type":"Point"}
}