{
  "type": "Feature",
  "properties": {
    "iso:country":"AU",
    "sg:address":"Unit26/ 168 Guildford Rd",
    "sg:city":"Maylands",
    "sg:classifiers":[
        {
            "category":"Professional",
            "subcategory":"Computer Services",
            "type":"Services"
        }
    ],
    "sg:phone":"+61 8 9370 4084",
    "sg:postcode":"6051",
    "sg:province":"WA",
    "sg:tags":[
        "equipment",
        "networking",
        "installation"
    ],
    "wof:name":"Carrington Compuserv",
    "wof:placetype":"venue"
},
  "geometry": {"coordinates":[115.895058,-31.930023],"type":"Point"}
}