{
  "type": "Feature",
  "properties": {
    "iso:country":"AU",
    "sg:address":"Shop 29, Ashmore Plaza, Cotlew St",
    "sg:city":"Ashmore",
    "sg:classifiers":[
        {
            "category":"Personal",
            "subcategory":"Shoe Repair & Shine",
            "type":"Services"
        }
    ],
    "sg:phone":"+61 7 5539 2327",
    "sg:postcode":"4214",
    "sg:province":"QLD",
    "sg:tags":[
        "footwear"
    ],
    "wof:name":"Daves Services",
    "wof:placetype":"venue"
},
  "geometry": {"coordinates":[153.382720947,-27.9863300323],"type":"Point"}
}