{
  "type": "Feature",
  "properties": {
    "iso:country":"AU",
    "sg:address":"PO Box 1286",
    "sg:city":"East Victoria Park",
    "sg:classifiers":[
        {
            "category":"Professional",
            "subcategory":"Art Services",
            "type":"Services"
        }
    ],
    "sg:phone":"+61 414 747 755",
    "sg:postcode":"6981",
    "sg:province":"WA",
    "sg:tags":[
        "interior",
        "decorator"
    ],
    "wof:name":"Victoria's Interior Design & Decorating",
    "wof:placetype":"venue"
},
  "geometry": {"coordinates":[115.90284,-31.98424],"type":"Point"}
}