{
  "type": "Feature",
  "properties": {
    "addr:full":"Terang Rd Cobden VIC 3266",
    "addr:postcode":"3266",
    "addr:street":"Terang Rd",
    "iso:country":"AU",
    "sg:address":"Terang Rd",
    "sg:city":"Cobden",
    "sg:classifiers":[
        {
            "category":"Building & Trades",
            "subcategory":"Construction",
            "type":"Services"
        }
    ],
    "sg:phone":"+61 3 5595 1135",
    "sg:postcode":"3266",
    "sg:province":"VIC",
    "sg:tags":[
        "contractor"
    ],
    "wof:name":"Hinkley M D & S A",
    "wof:placetype":"venue"
},
  "geometry": {"coordinates":[143.080245972,-38.3289299011],"type":"Point"}
}