{
  "type": "Feature",
  "properties": {
    "addr:full":"1st Floor, 110 Kippax St Surry Hills NSW 2010",
    "addr:housenumber":"110",
    "addr:postcode":"2010",
    "addr:street":"Kippax St",
    "iso:country":"AU",
    "sg:address":"1st Floor, 110 Kippax St",
    "sg:city":"Surry Hills",
    "sg:classifiers":[
        {
            "category":"Professional",
            "subcategory":"Business Services",
            "type":"Services"
        }
    ],
    "sg:phone":"+61 2 9211 8377",
    "sg:postcode":"2010",
    "sg:province":"NSW",
    "sg:tags":[
        "fashion",
        "agent"
    ],
    "wof:name":"Mode World",
    "wof:placetype":"venue"
},
  "geometry": {"coordinates":[151.21173095699999,-33.8854484558],"type":"Point"}
}