{
  "type": "Feature",
  "properties": {
    "iso:country":"AU",
    "sg:address":"4 Jennings St",
    "sg:city":"Kyneton",
    "sg:classifiers":[
        {
            "category":"Personal",
            "subcategory":"Beauty Salon",
            "type":"Services"
        }
    ],
    "sg:phone":"+61 3 5422 1110",
    "sg:postcode":"3444",
    "sg:province":"VIC",
    "wof:name":"Rebalance Beauty Therapy",
    "wof:placetype":"venue"
},
  "geometry": {"coordinates":[144.452636719,-37.2477722168],"type":"Point"}
}