{
  "type": "Feature",
  "properties": {
    "addr:full":"73 Elphinstone St Rockhampton QLD 4702",
    "addr:housenumber":"73",
    "addr:postcode":"4702",
    "addr:street":"Elphinstone St",
    "iso:country":"AU",
    "sg:address":"73 Elphinstone St",
    "sg:city":"Rockhampton",
    "sg:classifiers":[
        {
            "category":"Professional",
            "subcategory":"Employment Agencies",
            "type":"Services"
        }
    ],
    "sg:phone":"+61 1800 001 699",
    "sg:postcode":"4702",
    "sg:province":"QLD",
    "wof:name":"Work For The Dole",
    "wof:placetype":"venue"
},
  "geometry": {"coordinates":[150.52447509800001,-23.3631343842],"type":"Point"}
}