{
  "type": "Feature",
  "properties": {
    "addr:full":"15 Fullarton Rd Kent Town SA 5067",
    "addr:housenumber":"15",
    "addr:postcode":"5067",
    "addr:street":"Fullarton Rd",
    "iso:country":"AU",
    "sg:address":"15 Fullarton Rd",
    "sg:city":"Kent Town",
    "sg:classifiers":[
        {
            "category":"Health Services",
            "subcategory":"Doctor",
            "type":"Services"
        }
    ],
    "sg:phone":"+61 8 8363 2867",
    "sg:postcode":"5067",
    "sg:province":"SA",
    "sg:tags":[
        "medical",
        "practitioner"
    ],
    "wof:name":"Gramp A A",
    "wof:placetype":"venue"
},
  "geometry": {"coordinates":[138.623291016,-34.9204826355],"type":"Point"}
}