{
  "type": "Feature",
  "properties": {
    "addr:full":"62 Lodge Crs Berwick VIC 3806",
    "addr:housenumber":"62",
    "addr:postcode":"3806",
    "addr:street":"Lodge Crs",
    "iso:country":"AU",
    "sg:address":"62 Lodge Crs",
    "sg:city":"Berwick",
    "sg:classifiers":[
        {
            "category":"Home & Garden",
            "subcategory":"Building Materials",
            "type":"Retail Goods"
        }
    ],
    "sg:phone":"+61 3 9707 4075",
    "sg:postcode":"3806",
    "sg:province":"VIC",
    "sg:tags":[
        "lawn",
        "cutting",
        "maintenance"
    ],
    "wof:name":"Letts Lawn & Garden Care",
    "wof:placetype":"venue"
},
  "geometry": {"coordinates":[145.34732055699999,-38.0306282043],"type":"Point"}
}