{
  "type": "Feature",
  "properties": {
    "addr:full":"1745 Warburton Hwy Woori Yallock VIC 3139",
    "addr:housenumber":"1745",
    "addr:postcode":"3139",
    "addr:street":"Warburton Hwy",
    "iso:country":"AU",
    "sg:address":"1745 Warburton Hwy",
    "sg:city":"Woori Yallock",
    "sg:classifiers":[
        {
            "category":"Fast Food",
            "type":"Food & Drink"
        }
    ],
    "sg:phone":"+61 3 5964 7404",
    "sg:postcode":"3139",
    "sg:province":"VIC",
    "sg:tags":[
        "away",
        "take"
    ],
    "wof:name":"Hillcrest Little Store Great Food",
    "wof:placetype":"venue"
},
  "geometry": {"coordinates":[145.54266357399999,-37.7835083008],"type":"Point"}
}