{
  "type": "Feature",
  "properties": {
    "addr:full":"250 Liverpool St Hobart TAS 7000",
    "addr:housenumber":"250",
    "addr:postcode":"7000",
    "addr:street":"Liverpool St",
    "iso:country":"AU",
    "sg:address":"250 Liverpool St",
    "sg:city":"Hobart",
    "sg:classifiers":[
        {
            "category":"Organizations",
            "subcategory":"Community Association",
            "type":"Services"
        }
    ],
    "sg:phone":"+61 3 6231 1345",
    "sg:postcode":"7000",
    "sg:province":"TAS",
    "sg:tags":[
        "organisation",
        "family",
        "welfare"
    ],
    "wof:name":"Salvation Army",
    "wof:placetype":"venue"
},
  "geometry": {"coordinates":[147.322463989,-42.8858146667],"type":"Point"}
}