{
  "type": "Feature",
  "properties": {
    "iso:country":"AU",
    "sg:address":"24 Gibney St",
    "sg:city":"Cottesloe",
    "sg:classifiers":[
        {
            "category":"Professional",
            "subcategory":"Engineering",
            "type":"Services"
        }
    ],
    "sg:phone":"+61 8 9384 4529",
    "sg:postcode":"6011",
    "sg:province":"WA",
    "sg:tags":[
        "electronic",
        "engineer"
    ],
    "wof:name":"Transalley",
    "wof:placetype":"venue"
},
  "geometry": {"coordinates":[115.75505065900001,-32.0084266663],"type":"Point"}
}