{
  "type": "Feature",
  "properties": {
    "addr:full":"38a Stoney Creek Rd Bexley NSW 2207",
    "addr:housenumber":"38a",
    "addr:postcode":"2207",
    "addr:street":"Stoney Creek Rd",
    "iso:country":"AU",
    "sg:address":"38a Stoney Creek Rd",
    "sg:city":"Bexley",
    "sg:classifiers":[
        {
            "category":"Government",
            "subcategory":"Post Office",
            "type":"Public Place"
        }
    ],
    "sg:phone":"+61 2 9150 0266",
    "sg:postcode":"2207",
    "sg:province":"NSW",
    "sg:tags":[
        "house",
        "doll"
    ],
    "wof:name":"The Doll Shoppe",
    "wof:placetype":"venue"
},
  "geometry": {"coordinates":[151.12336730999999,-33.9496688843],"type":"Point"}
}