{
  "type": "Feature",
  "properties": {
    "iso:country":"AU",
    "sg:address":"PO Box 515",
    "sg:city":"Yarraville",
    "sg:classifiers":[
        {
            "category":"Home & Garden",
            "subcategory":"Carpets & Floor Coverings",
            "type":"Retail Goods"
        }
    ],
    "sg:phone":"+61 419 552 257",
    "sg:postcode":"3013",
    "sg:province":"VIC",
    "sg:tags":[
        "tile",
        "wall"
    ],
    "wof:name":"McLandscapes",
    "wof:placetype":"venue"
},
  "geometry": {"coordinates":[144.882202148,-37.8180885315],"type":"Point"}
}