{
  "type": "Feature",
  "properties": {
    "iso:country":"AU",
    "sg:address":"48 Malga Ave",
    "sg:city":"Roseville",
    "sg:classifiers":[
        {
            "category":"Building & Trades",
            "subcategory":"Landscaping Services",
            "type":"Services"
        }
    ],
    "sg:phone":"+61 2 9417 2946",
    "sg:postcode":"2069",
    "sg:province":"NSW",
    "sg:tags":[
        "consultant"
    ],
    "wof:name":"A AAMorton & Bae Building Consultants",
    "wof:placetype":"venue"
},
  "geometry": {"coordinates":[151.19932556099999,-33.7765655518],"type":"Point"}
}