{
  "type": "Feature",
  "properties": {
    "iso:country":"AU",
    "sg:address":"358 Cressy St",
    "sg:city":"Deniliquin",
    "sg:classifiers":[
        {
            "category":"Travel",
            "subcategory":"Travel Agent",
            "type":"Entertainment"
        }
    ],
    "sg:phone":"+61 3 5881 7744",
    "sg:postcode":"2710",
    "sg:province":"NSW",
    "sg:tags":[
        "consultant"
    ],
    "wof:name":"Travelscene Deniliquin",
    "wof:placetype":"venue"
},
  "geometry": {"coordinates":[144.96148681599999,-35.5275650024],"type":"Point"}
}