{
  "type": "Feature",
  "properties": {
    "addr:full":"1 Prosperity Pde Warriewood NSW 2102",
    "addr:housenumber":"1",
    "addr:postcode":"2102",
    "addr:street":"Prosperity Pde",
    "iso:country":"AU",
    "sg:address":"1 Prosperity Pde",
    "sg:city":"Warriewood",
    "sg:classifiers":[
        {
            "category":"Home & Garden",
            "subcategory":"Hardware",
            "type":"Retail Goods"
        }
    ],
    "sg:phone":"+61 2 9997 2200",
    "sg:postcode":"2102",
    "sg:province":"NSW",
    "sg:tags":[
        "generating",
        "set",
        "generator"
    ],
    "wof:name":"T.S.F. Engineering Pty Ltd",
    "wof:placetype":"venue"
},
  "geometry": {"coordinates":[151.28997799999999,-33.680859],"type":"Point"}
}