{
  "type": "Feature",
  "properties": {
    "addr:full":"3 Tipping Pl McKellar ACT 2617",
    "addr:housenumber":"3",
    "addr:postcode":"2617",
    "addr:street":"Tipping Pl",
    "iso:country":"AU",
    "sg:address":"3 Tipping Pl",
    "sg:city":"McKellar",
    "sg:classifiers":[
        {
            "category":"Professional",
            "subcategory":"Management & Consulting",
            "type":"Services"
        }
    ],
    "sg:phone":"+61 2 6259 1516",
    "sg:postcode":"2617",
    "sg:province":"ACT",
    "sg:tags":[
        "consultant"
    ],
    "wof:name":"Ardath Management Services",
    "wof:placetype":"venue"
},
  "geometry": {"coordinates":[149.07276916500001,-35.22057724],"type":"Point"}
}