{
  "type": "Feature",
  "properties": {
    "addr:full":"Shp 4/ 489 Creek Rd Mt Gravatt East QLD 4122",
    "addr:housenumber":"/ 489",
    "addr:postcode":"4122",
    "addr:street":"Creek Rd",
    "iso:country":"AU",
    "sg:address":"Shp 4/ 489 Creek Rd",
    "sg:city":"Mt Gravatt East",
    "sg:classifiers":[
        {
            "category":"Personal",
            "type":"Services"
        }
    ],
    "sg:phone":"+61 7 3349 5335",
    "sg:postcode":"4122",
    "sg:province":"QLD",
    "sg:tags":[
        "reducing",
        "treatment",
        "weight"
    ],
    "wof:name":"Silhoutte Body Toning Spa",
    "wof:placetype":"venue"
},
  "geometry": {"coordinates":[153.095703125,-27.5272216797],"type":"Point"}
}