{
  "type": "Feature",
  "properties": {
    "addr:full":"26 Hamilton St Horsham Forward VIC 3401",
    "addr:housenumber":"26",
    "addr:postcode":"3401",
    "addr:street":"Hamilton St",
    "iso:country":"AU",
    "sg:address":"26 Hamilton St",
    "sg:city":"Horsham Forward",
    "sg:classifiers":[
        {
            "category":"Retail",
            "subcategory":"Auto Repair",
            "type":"Services"
        }
    ],
    "sg:phone":"+61 428 810 526",
    "sg:postcode":"3401",
    "sg:province":"VIC",
    "sg:tags":[
        "bus",
        "truck"
    ],
    "wof:name":"Wimmera Truck & Bus Centre",
    "wof:placetype":"venue"
},
  "geometry": {"coordinates":[142.206344605,-36.7176628113],"type":"Point"}
}