{
  "type": "Feature",
  "properties": {
    "iso:country":"AU",
    "sg:address":"221 Scarborough Beach Rd",
    "sg:city":"Mt Hawthorn",
    "sg:classifiers":[
        {
            "category":"Deli",
            "type":"Food & Drink"
        }
    ],
    "sg:phone":"+61 8 9242 2877",
    "sg:postcode":"6016",
    "sg:province":"WA",
    "sg:tags":[
        "delicatessen"
    ],
    "wof:name":"Hawthorn Super Deli",
    "wof:placetype":"venue"
},
  "geometry": {"coordinates":[115.834609985,-31.9186248779],"type":"Point"}
}