{
  "type": "Feature",
  "properties": {
    "iso:country":"AU",
    "sg:address":"Shop 3, 698 Darling St",
    "sg:city":"Rozelle",
    "sg:classifiers":[
        {
            "category":"Health Services",
            "subcategory":"Health Practitioner",
            "type":"Services"
        }
    ],
    "sg:phone":"+61 2 9818 8517",
    "sg:postcode":"2039",
    "sg:province":"NSW",
    "sg:tags":[
        "acupuncture"
    ],
    "wof:name":"Mehmet Jann",
    "wof:placetype":"venue"
},
  "geometry": {"coordinates":[151.169464111,-33.8644332886],"type":"Point"}
}