{
  "type": "Feature",
  "properties": {
    "addr:full":"42 Claremont Rd Burwood Heights NSW 2136",
    "addr:housenumber":"42",
    "addr:postcode":"2136",
    "addr:street":"Claremont Rd",
    "iso:country":"AU",
    "sg:address":"42 Claremont Rd",
    "sg:city":"Burwood Heights",
    "sg:classifiers":[
        {
            "category":"Shopping",
            "subcategory":"Computers & Home Electronics",
            "type":"Retail Goods"
        }
    ],
    "sg:phone":"+61 2 9744 6667",
    "sg:postcode":"2136",
    "sg:province":"NSW",
    "sg:tags":[
        "hardware",
        "equipment"
    ],
    "wof:name":"Australia Computer Online",
    "wof:placetype":"venue"
},
  "geometry": {"coordinates":[151.10647582999999,-33.8906898499],"type":"Point"}
}