{
  "type": "Feature",
  "properties": {
    "addr:full":"34 Burwood Rd Burwood NSW 2134",
    "addr:housenumber":"34",
    "addr:postcode":"2134",
    "addr:street":"Burwood Rd",
    "iso:country":"AU",
    "sg:address":"34 Burwood Rd",
    "sg:city":"Burwood",
    "sg:classifiers":[
        {
            "category":"Health Services",
            "subcategory":"Health Practitioner",
            "type":"Services"
        }
    ],
    "sg:phone":"+61 2 9745 2002",
    "sg:postcode":"2134",
    "sg:province":"NSW",
    "sg:tags":[
        "pathologist",
        "speech"
    ],
    "wof:name":"Burwood Speech Pathology",
    "wof:placetype":"venue"
},
  "geometry": {"coordinates":[151.105102539,-33.8709526062],"type":"Point"}
}