{
  "type": "Feature",
  "properties": {
    "iso:country":"AU",
    "sg:address":"397 Smith St",
    "sg:city":"Collingwood",
    "sg:classifiers":[
        {
            "category":"Shopping",
            "subcategory":"Clothing, Apparel, & Fashions",
            "type":"Retail Goods"
        }
    ],
    "sg:phone":"+61 3 9415 9736",
    "sg:postcode":"3066",
    "sg:province":"VIC",
    "sg:tags":[
        "lady",
        "wear"
    ],
    "wof:name":"Emillo Designs",
    "wof:placetype":"venue"
},
  "geometry": {"coordinates":[144.98443603499999,-37.7970085144],"type":"Point"}
}