{
  "type": "Feature",
  "properties": {
    "addr:full":"9 Karri Ave Karana Downs QLD 4306",
    "addr:housenumber":"9",
    "addr:postcode":"4306",
    "addr:street":"Karri Ave",
    "iso:country":"AU",
    "sg:address":"9 Karri Ave",
    "sg:city":"Karana Downs",
    "sg:classifiers":[
        {
            "category":"Building & Trades",
            "subcategory":"Construction",
            "type":"Services"
        }
    ],
    "sg:phone":"+61 7 3201 0887",
    "sg:postcode":"4306",
    "sg:province":"QLD",
    "sg:tags":[
        "equipment",
        "balancing"
    ],
    "wof:name":"BVE Pty Ltd",
    "wof:placetype":"venue"
},
  "geometry": {"coordinates":[152.836502075,-27.5424003601],"type":"Point"}
}