{
  "type": "Feature",
  "properties": {
    "addr:full":"Suite C5, 225 Bagot Rd Subiaco WA 6008",
    "addr:housenumber":"225",
    "addr:postcode":"6008",
    "addr:street":"Bagot Rd",
    "iso:country":"AU",
    "sg:address":"Suite C5, 225 Bagot Rd",
    "sg:city":"Subiaco",
    "sg:classifiers":[
        {
            "category":"Real Estate",
            "subcategory":"Architect",
            "type":"Services"
        }
    ],
    "sg:phone":"+61 8 9388 9963",
    "sg:postcode":"6008",
    "sg:province":"WA",
    "sg:tags":[
        "building",
        "designer"
    ],
    "wof:name":"Fryer Peter Design",
    "wof:placetype":"venue"
},
  "geometry": {"coordinates":[115.824806213,-31.9505348206],"type":"Point"}
}