{
  "type": "Feature",
  "properties": {
    "addr:full":"9 Hollylea Rd Leumeah NSW 2560",
    "addr:housenumber":"9",
    "addr:postcode":"2560",
    "addr:street":"Hollylea Rd",
    "iso:country":"AU",
    "sg:address":"9 Hollylea Rd",
    "sg:city":"Leumeah",
    "sg:classifiers":[
        {
            "category":"Home & Garden",
            "subcategory":"Building Materials",
            "type":"Retail Goods"
        }
    ],
    "sg:phone":"+61 2 4628 9980",
    "sg:postcode":"2560",
    "sg:province":"NSW",
    "sg:tags":[
        "fencing"
    ],
    "wof:name":"Hudson Building Supplies",
    "wof:placetype":"venue"
},
  "geometry": {"coordinates":[150.82612609899999,-34.0525093079],"type":"Point"}
}