{
  "type": "Feature",
  "properties": {
    "iso:country":"AU",
    "sg:address":"197- 199 Keira St",
    "sg:city":"Wollongong",
    "sg:classifiers":[
        {
            "category":"Arts & Performance",
            "subcategory":"Theater",
            "type":"Entertainment"
        }
    ],
    "sg:phone":"+61 2 4225 9106",
    "sg:postcode":"2500",
    "sg:province":"NSW",
    "sg:tags":[
        "agency",
        "booking",
        "theatre"
    ],
    "wof:name":"Regent Theatre Wollongong",
    "wof:placetype":"venue"
},
  "geometry": {"coordinates":[150.893326,-34.424767],"type":"Point"}
}