{
  "type": "Feature",
  "properties": {
    "iso:country":"AU",
    "sg:address":"25 Susella Crs",
    "sg:city":"Tuncurry",
    "sg:classifiers":[
        {
            "category":"Real Estate",
            "subcategory":"Architect",
            "type":"Services"
        }
    ],
    "sg:phone":"+61 2 6554 8638",
    "sg:postcode":"2428",
    "sg:province":"NSW",
    "sg:tags":[
        "building",
        "designer"
    ],
    "wof:name":"Davies C J",
    "wof:placetype":"venue"
},
  "geometry": {"coordinates":[152.499664,-32.175468],"type":"Point"}
}