{
  "type": "Feature",
  "properties": {
    "addr:full":"219 O'Connell St North Adelaide SA 5006",
    "addr:housenumber":"219",
    "addr:postcode":"5006",
    "addr:street":"O'Connell St",
    "iso:country":"AU",
    "sg:address":"219 O'Connell St",
    "sg:city":"North Adelaide",
    "sg:classifiers":[
        {
            "category":"Restaurant",
            "type":"Food & Drink"
        }
    ],
    "sg:phone":"+61 8 8267 1375",
    "sg:postcode":"5006",
    "sg:province":"SA",
    "sg:website":"http://www.caledonianhotel.com.au",
    "wof:name":"Barton's At The Caledonian Hotel",
    "wof:placetype":"venue"
},
  "geometry": {"coordinates":[138.59637451200001,-34.9079818726],"type":"Point"}
}