{
  "type": "Feature",
  "properties": {
    "addr:full":"8 Cowper Pl Barden Ridge NSW 2234",
    "addr:housenumber":"8",
    "addr:postcode":"2234",
    "addr:street":"Cowper Pl",
    "iso:country":"AU",
    "sg:address":"8 Cowper Pl",
    "sg:city":"Barden Ridge",
    "sg:classifiers":[
        {
            "category":"Sports & Exercise",
            "subcategory":"Gym",
            "type":"Entertainment"
        }
    ],
    "sg:phone":"+61 2 9543 9543",
    "sg:postcode":"2234",
    "sg:province":"NSW",
    "sg:tags":[
        "health",
        "fitness"
    ],
    "wof:name":"The Edith Parsons School Of Physical Culture",
    "wof:placetype":"venue"
},
  "geometry": {"coordinates":[151.00999450699999,-34.0324745178],"type":"Point"}
}