{
  "type": "Feature",
  "properties": {
    "addr:full":"North West Coastal Hwy Carnarvon North WA 6701",
    "addr:postcode":"6701",
    "addr:street":"North West Coastal Hwy;North",
    "iso:country":"AU",
    "sg:address":"North West Coastal Hwy",
    "sg:city":"Carnarvon North",
    "sg:classifiers":[
        {
            "category":"Parking",
            "subcategory":"Lot",
            "type":"Transportation"
        }
    ],
    "sg:phone":"+61 8 9941 9991",
    "sg:postcode":"6701",
    "sg:province":"WA",
    "sg:tags":[
        "vegetable",
        "packing",
        "fruit",
        "pack"
    ],
    "wof:name":"Gascoyne Gold Pty Ltd",
    "wof:placetype":"venue"
},
  "geometry": {"coordinates":[114.024238586,-24.3558063507],"type":"Point"}
}