{
  "type": "Feature",
  "properties": {
    "addr:full":"80 Seville St Fairfield NSW 2165",
    "addr:housenumber":"80",
    "addr:postcode":"2165",
    "addr:street":"Seville St",
    "iso:country":"AU",
    "sg:address":"80 Seville St",
    "sg:city":"Fairfield",
    "sg:classifiers":[
        {
            "category":"Fast Food",
            "type":"Food & Drink"
        }
    ],
    "sg:phone":"+61 2 9727 8362",
    "sg:postcode":"2165",
    "sg:province":"NSW",
    "sg:tags":[
        "away",
        "take"
    ],
    "wof:name":"Cafeart",
    "wof:placetype":"venue"
},
  "geometry": {"coordinates":[150.97300720199999,-33.8725700378],"type":"Point"}
}