{
  "type": "Feature",
  "properties": {
    "iso:country":"AU",
    "sg:address":"2 Forest Rd",
    "sg:city":"Warriewood",
    "sg:classifiers":[
        {
            "category":"Shopping",
            "subcategory":"Computers & Home Electronics",
            "type":"Retail Goods"
        }
    ],
    "sg:phone":"+61 2 9999 0223",
    "sg:postcode":"2102",
    "sg:province":"NSW",
    "sg:tags":[
        "small",
        "equipment",
        "business"
    ],
    "wof:name":"Imprimis Data Systems",
    "wof:placetype":"venue"
},
  "geometry": {"coordinates":[151.28663599999999,-33.682892],"type":"Point"}
}