{
  "type": "Feature",
  "properties": {
    "addr:full":"200- 202 James St Toowoomba QLD 4350",
    "addr:housenumber":"202",
    "addr:postcode":"4350",
    "addr:street":"James St",
    "iso:country":"AU",
    "sg:address":"200- 202 James St",
    "sg:city":"Toowoomba",
    "sg:classifiers":[
        {
            "category":"Travel",
            "subcategory":"Hotels & Motels",
            "type":"Entertainment"
        }
    ],
    "sg:phone":"+61 7 4659 5555",
    "sg:postcode":"4350",
    "sg:province":"QLD",
    "wof:name":"Asters On James Motor Inn",
    "wof:placetype":"venue"
},
  "geometry": {"coordinates":[151.94546508799999,-27.567937851],"type":"Point"}
}