{
  "type": "Feature",
  "properties": {
    "addr:full":"Westfield Chermside, Gympie Rd Chermside QLD 4032",
    "addr:postcode":"qld 4032",
    "addr:street":"Gympie Rd",
    "iso:country":"AU",
    "sg:address":"Westfield Chermside, Gympie Rd",
    "sg:city":"Chermside",
    "sg:classifiers":[
        {
            "category":"Professional",
            "subcategory":"Accounting & Tax Preparation",
            "type":"Services"
        }
    ],
    "sg:phone":"+61 7 3359 8199",
    "sg:postcode":"4032",
    "sg:province":"QLD",
    "sg:tags":[
        "consultant",
        "taxation"
    ],
    "wof:name":"ITP Income Tax Professionals",
    "wof:placetype":"venue"
},
  "geometry": {"coordinates":[153.031113,-27.386387],"type":"Point"}
}