{
  "type": "Feature",
  "properties": {
    "addr:full":"133 Amaroo Drv Chelsea Heights VIC 3196",
    "addr:housenumber":"133",
    "addr:postcode":"3196",
    "addr:street":"Amaroo Drv",
    "iso:country":"AU",
    "sg:address":"133 Amaroo Drv",
    "sg:city":"Chelsea Heights",
    "sg:classifiers":[
        {
            "category":"Building & Trades",
            "subcategory":"Construction",
            "type":"Services"
        }
    ],
    "sg:phone":"+61 3 9773 3763",
    "sg:postcode":"3196",
    "sg:province":"VIC",
    "sg:tags":[
        "home",
        "air conditioning"
    ],
    "wof:name":"Terry Burt Refrigeration",
    "wof:placetype":"venue"
},
  "geometry": {"coordinates":[145.135894775,-38.038848877],"type":"Point"}
}