{
  "type": "Feature",
  "properties": {
    "iso:country":"AU",
    "sg:address":"8 Hillview Pl",
    "sg:city":"Berwick",
    "sg:classifiers":[
        {
            "category":"Home & Garden",
            "subcategory":"Building Materials",
            "type":"Retail Goods"
        }
    ],
    "sg:phone":"+61 409 000 026",
    "sg:postcode":"3806",
    "sg:province":"VIC",
    "sg:tags":[
        "gate"
    ],
    "wof:name":"South Eastern Remote Controls",
    "wof:placetype":"venue"
},
  "geometry": {"coordinates":[145.33462524399999,-38.025592804],"type":"Point"}
}