{
  "type": "Feature",
  "properties": {
    "addr:full":"2C Margaret St Hunters Hill NSW 2110",
    "addr:housenumber":"2c",
    "addr:postcode":"2110",
    "addr:street":"Margaret St",
    "iso:country":"AU",
    "sg:address":"2C Margaret St",
    "sg:city":"Hunters Hill",
    "sg:classifiers":[
        {
            "category":"Recreation",
            "subcategory":"Boat Charter",
            "type":"Entertainment"
        }
    ],
    "sg:phone":"+61 414 228 715",
    "sg:postcode":"2110",
    "sg:province":"NSW",
    "wof:name":"River Princess",
    "wof:placetype":"venue"
},
  "geometry": {"coordinates":[151.16893005399999,-33.8423233032],"type":"Point"}
}