{
  "type": "Feature",
  "properties": {
    "iso:country":"AU",
    "sg:address":"149 St John St",
    "sg:city":"Launceston",
    "sg:classifiers":[
        {
            "category":"Personal",
            "subcategory":"Beauty Salon",
            "type":"Services"
        }
    ],
    "sg:phone":"+61 3 6334 8233",
    "sg:postcode":"7250",
    "sg:province":"TAS",
    "sg:tags":[
        "hairdresser"
    ],
    "wof:name":"Harmony Hairdressing",
    "wof:placetype":"venue"
},
  "geometry": {"coordinates":[147.140716553,-41.4394416809],"type":"Point"}
}