{
  "type": "Feature",
  "properties": {
    "addr:full":"60 - 62 Gray Tce Gillman SA 5013",
    "addr:housenumber":"62",
    "addr:postcode":"5013",
    "addr:street":"Gray Tce",
    "iso:country":"AU",
    "sg:address":"60 - 62 Gray Tce",
    "sg:city":"Gillman",
    "sg:classifiers":[
        {
            "category":"Professional",
            "subcategory":"Testing Lab",
            "type":"Services"
        }
    ],
    "sg:phone":"+61 8 8240 1299",
    "sg:postcode":"5013",
    "sg:province":"SA",
    "sg:tags":[
        "inspection"
    ],
    "wof:name":"Metlabs",
    "wof:placetype":"venue"
},
  "geometry": {"coordinates":[138.525268555,-34.8129806519],"type":"Point"}
}