{
  "type": "Feature",
  "properties": {
    "addr:full":"46 Davallia Rd Duncraig WA 6023",
    "addr:housenumber":"46",
    "addr:postcode":"6023",
    "addr:street":"Davallia Rd",
    "iso:country":"AU",
    "sg:address":"46 Davallia Rd",
    "sg:city":"Duncraig",
    "sg:classifiers":[
        {
            "category":"Shopping",
            "subcategory":"Clothing, Apparel, & Fashions",
            "type":"Retail Goods"
        }
    ],
    "sg:phone":"+61 8 9448 5502",
    "sg:postcode":"6023",
    "sg:province":"WA",
    "sg:tags":[
        "textile",
        "designer"
    ],
    "wof:name":"Jolanta Art & Fashion",
    "wof:placetype":"venue"
},
  "geometry": {"coordinates":[115.785873413,-31.8413658142],"type":"Point"}
}