{
  "type": "Feature",
  "properties": {
    "addr:full":"Suite 2/ 154 Bentinck St Bathurst NSW 2795",
    "addr:housenumber":"/ 154",
    "addr:postcode":"2795",
    "addr:street":"Bentinck St",
    "iso:country":"AU",
    "sg:address":"Suite 2/ 154 Bentinck St",
    "sg:city":"Bathurst",
    "sg:classifiers":[
        {
            "category":"Professional",
            "type":"Services"
        }
    ],
    "sg:phone":"+61 2 6331 3322",
    "sg:postcode":"2795",
    "sg:province":"NSW",
    "sg:tags":[
        "transport"
    ],
    "wof:name":"Bathurst Community Transport Group",
    "wof:placetype":"venue"
},
  "geometry": {"coordinates":[149.58558654800001,-33.4213638306],"type":"Point"}
}