{
  "type": "Feature",
  "properties": {
    "addr:full":"22 Railway Ave Thornton NSW 2322",
    "addr:housenumber":"22",
    "addr:postcode":"2322",
    "addr:street":"Railway Ave",
    "iso:country":"AU",
    "sg:address":"22 Railway Ave",
    "sg:city":"Thornton",
    "sg:classifiers":[
        {
            "category":"Shopping",
            "subcategory":"Bicycles & Sporting Goods",
            "type":"Retail Goods"
        }
    ],
    "sg:phone":"+61 2 4966 8425",
    "sg:postcode":"2322",
    "sg:province":"NSW",
    "sg:tags":[
        "chemical",
        "equipment",
        "pool",
        "swimming"
    ],
    "wof:name":"Thornton Pool Shop",
    "wof:placetype":"venue"
},
  "geometry": {"coordinates":[151.64198303200001,-32.7830696106],"type":"Point"}
}