{
  "type": "Feature",
  "properties": {
    "addr:full":"80B Main Rd Monbulk VIC 3793",
    "addr:housenumber":"80b",
    "addr:postcode":"3793",
    "addr:street":"Main Rd",
    "iso:country":"AU",
    "sg:address":"80B Main Rd",
    "sg:city":"Monbulk",
    "sg:classifiers":[
        {
            "category":"Cafe",
            "type":"Food & Drink"
        }
    ],
    "sg:phone":"+61 3 9756 7802",
    "sg:postcode":"3793",
    "sg:province":"VIC",
    "wof:name":"Blue Gum Deli",
    "wof:placetype":"venue"
},
  "geometry": {"coordinates":[145.407470703,-37.8749809265],"type":"Point"}
}