{
  "type": "Feature",
  "properties": {
    "addr:full":"23- 25 Simpson St Mt Isa QLD 4825",
    "addr:housenumber":"25",
    "addr:postcode":"4825",
    "addr:street":"Simpson St",
    "iso:country":"AU",
    "sg:address":"23- 25 Simpson St",
    "sg:city":"Mt Isa",
    "sg:classifiers":[
        {
            "category":"Banks & Credit Unions",
            "subcategory":"Bank",
            "type":"Services"
        }
    ],
    "sg:phone":"+61 13 20 32",
    "sg:postcode":"4825",
    "sg:province":"QLD",
    "wof:name":"Westpac",
    "wof:placetype":"venue"
},
  "geometry": {"coordinates":[139.494247,-20.726271],"type":"Point"}
}