{
  "type": "Feature",
  "properties": {
    "iso:country":"AU",
    "sg:address":"Cnr Wood & Hanrahan Sts",
    "sg:city":"Thomastown",
    "sg:classifiers":[
        {
            "category":"Manufacturing",
            "subcategory":"Glass & Minerals",
            "type":"Manufacturing & Wholesale Goods"
        }
    ],
    "sg:phone":"+61 3 9466 4799",
    "sg:postcode":"3074",
    "sg:province":"VIC",
    "sg:tags":[
        "merchant",
        "granite",
        "marble"
    ],
    "sg:website":"http://www.cerdomus.com",
    "wof:name":"San Marco Ceramics Pty Ltd",
    "wof:placetype":"venue"
},
  "geometry": {"coordinates":[145.02653503400001,-37.6937408447],"type":"Point"}
}