{
  "type": "Feature",
  "properties": {
    "addr:full":"Cottage No 1 Glen Morrison NSW 2354",
    "addr:postcode":"2354",
    "iso:country":"AU",
    "sg:address":"Cottage No 1",
    "sg:city":"Glen Morrison",
    "sg:classifiers":[
        {
            "category":"Building & Trades",
            "subcategory":"Landscaping Services",
            "type":"Services"
        }
    ],
    "sg:phone":"+61 2 6777 6459",
    "sg:postcode":"2354",
    "sg:province":"NSW",
    "sg:tags":[
        "grazier"
    ],
    "wof:name":"Wauch Peter S",
    "wof:placetype":"venue"
},
  "geometry": {"coordinates":[151.524658203,-31.1868801117],"type":"Point"}
}