{
  "type": "Feature",
  "properties": {
    "iso:country":"AU",
    "sg:address":"Unit 2/ 14 Catherine Helen Spence St",
    "sg:city":"Adelaide",
    "sg:classifiers":[
        {
            "category":"Professional",
            "subcategory":"Art Services",
            "type":"Services"
        }
    ],
    "sg:phone":"+61 8 8227 2466",
    "sg:postcode":"5000",
    "sg:province":"SA",
    "sg:tags":[
        "graphic",
        "designer"
    ],
    "wof:name":"eyepea design",
    "wof:placetype":"venue"
},
  "geometry": {"coordinates":[138.60319519000001,-34.9332885742],"type":"Point"}
}