{
  "type": "Feature",
  "properties": {
    "iso:country":"AU",
    "sg:address":"149 Bryants Rd",
    "sg:city":"Loganholme",
    "sg:classifiers":[
        {
            "category":"Social Services",
            "subcategory":"Retirement Home",
            "type":"Services"
        }
    ],
    "sg:phone":"+61 7 3801 3762",
    "sg:postcode":"4129",
    "sg:province":"QLD",
    "sg:tags":[
        "environmental",
        "consultant",
        "pollution"
    ],
    "wof:name":"Airlabs Pty Ltd",
    "wof:placetype":"venue"
},
  "geometry": {"coordinates":[153.18653869600001,-27.666185379],"type":"Point"}
}