{
  "type": "Feature",
  "properties": {
    "iso:country":"AU",
    "sg:address":"29 Ingram Rd",
    "sg:city":"Baldivis",
    "sg:classifiers":[
        {
            "category":"Home & Garden",
            "subcategory":"Garden Supply",
            "type":"Retail Goods"
        }
    ],
    "sg:phone":"+61 8 9524 2087",
    "sg:postcode":"6171",
    "sg:province":"WA",
    "sg:tags":[
        "fertilizer"
    ],
    "wof:name":"Vermiculture Ventures",
    "wof:placetype":"venue"
},
  "geometry": {"coordinates":[115.819344,-32.313889],"type":"Point"}
}