{
  "type": "Feature",
  "properties": {
    "addr:full":"U 1/ 7160 Great Eastern Hwy Mundaring WA 6073",
    "addr:housenumber":"/ 7160",
    "addr:postcode":"6073",
    "addr:street":"Great Eastern Hwy",
    "iso:country":"AU",
    "sg:address":"U 1/ 7160 Great Eastern Hwy",
    "sg:city":"Mundaring",
    "sg:classifiers":[
        {
            "category":"Cafe",
            "type":"Food & Drink"
        }
    ],
    "sg:phone":"+61 8 9295 3358",
    "sg:postcode":"6073",
    "sg:province":"WA",
    "wof:name":"A Patch Of Countries",
    "wof:placetype":"venue"
},
  "geometry": {"coordinates":[116.16805267300001,-31.902223587],"type":"Point"}
}