{
  "type": "Feature",
  "properties": {
    "iso:country":"AU",
    "sg:address":"Cnr Freedman Rd & Plantation St",
    "sg:city":"Menora",
    "sg:classifiers":[
        {
            "category":"Food & Beverages",
            "subcategory":"Bakery",
            "type":"Retail Goods"
        }
    ],
    "sg:phone":"+61 8 9370 3311",
    "sg:postcode":"6050",
    "sg:province":"WA",
    "sg:tags":[
        "baker"
    ],
    "wof:name":"Kosher Bakery",
    "wof:placetype":"venue"
},
  "geometry": {"coordinates":[115.863288879,-31.9174594879],"type":"Point"}
}