{
  "type": "Feature",
  "properties": {
    "addr:full":"320 Pennant Hills Rd Carlingford NSW 2118",
    "addr:housenumber":"320",
    "addr:postcode":"2118",
    "addr:street":"Pennant Hills Rd",
    "iso:country":"AU",
    "sg:address":"320 Pennant Hills Rd",
    "sg:city":"Carlingford",
    "sg:classifiers":[
        {
            "category":"Shopping",
            "subcategory":"Music",
            "type":"Retail Goods"
        }
    ],
    "sg:phone":"+61 2 9873 2333",
    "sg:postcode":"2118",
    "sg:province":"NSW",
    "sg:tags":[
        "instrument",
        "musical"
    ],
    "sg:website":"http://www.carlingfordmusic.com.au",
    "wof:name":"Carlingford Music Centre",
    "wof:placetype":"venue"
},
  "geometry": {"coordinates":[151.04713439899999,-33.7831916809],"type":"Point"}
}