{
  "type": "Feature",
  "properties": {
    "addr:full":"9a Foundry Rd Seven Hills NSW 2147",
    "addr:housenumber":"9a",
    "addr:postcode":"2147",
    "addr:street":"Foundry Rd",
    "iso:country":"AU",
    "sg:address":"9a Foundry Rd",
    "sg:city":"Seven Hills",
    "sg:classifiers":[
        {
            "category":"Home & Garden",
            "subcategory":"Garden Supply",
            "type":"Retail Goods"
        }
    ],
    "sg:phone":"+61 2 9838 9111",
    "sg:postcode":"2147",
    "sg:province":"NSW",
    "sg:tags":[
        "fertilizer"
    ],
    "wof:name":"Zadco",
    "wof:placetype":"venue"
},
  "geometry": {"coordinates":[150.95605468799999,-33.7672538757],"type":"Point"}
}