{
  "type": "Feature",
  "properties": {
    "addr:full":"114 Connaught St Sandgate QLD 4017",
    "addr:housenumber":"114",
    "addr:postcode":"4017",
    "addr:street":"Connaught St",
    "iso:country":"AU",
    "sg:address":"114 Connaught St",
    "sg:city":"Sandgate",
    "sg:classifiers":[
        {
            "category":"Retail",
            "subcategory":"Auto Repair",
            "type":"Services"
        }
    ],
    "sg:phone":"+61 7 3869 0648",
    "sg:postcode":"4017",
    "sg:province":"QLD",
    "sg:tags":[
        "beater",
        "painter",
        "panel"
    ],
    "wof:name":"Sandgate Body Works",
    "wof:placetype":"venue"
},
  "geometry": {"coordinates":[153.05697631800001,-27.3186817169],"type":"Point"}
}