{
  "type": "Feature",
  "properties": {
    "addr:full":"87 Pakington St Geelong West VIC 3218",
    "addr:housenumber":"87",
    "addr:postcode":"3218",
    "addr:street":"Pakington St",
    "iso:country":"AU",
    "sg:address":"87 Pakington St",
    "sg:city":"Geelong West",
    "sg:classifiers":[
        {
            "category":"Building & Trades",
            "subcategory":"Landscaping Services",
            "type":"Services"
        }
    ],
    "sg:phone":"+61 3 5221 8029",
    "sg:postcode":"3218",
    "sg:province":"VIC",
    "sg:tags":[
        "inspection"
    ],
    "wof:name":"Archicentre",
    "wof:placetype":"venue"
},
  "geometry": {"coordinates":[144.34881591800001,-38.1371040344],"type":"Point"}
}