{
  "type": "Feature",
  "properties": {
    "iso:country":"AU",
    "sg:address":"69 Mulgrave St",
    "sg:city":"Gin Gin",
    "sg:classifiers":[
        {
            "category":"Real Estate",
            "subcategory":"Real Estate Agent",
            "type":"Services"
        }
    ],
    "sg:phone":"+61 7 4157 2666",
    "sg:postcode":"4671",
    "sg:province":"QLD",
    "wof:name":"Gin Gin Realty",
    "wof:placetype":"venue"
},
  "geometry": {"coordinates":[151.963089,-24.993813],"type":"Point"}
}