{
  "type": "Feature",
  "properties": {
    "addr:full":"82 Farnham Rd Quakers Hill NSW 2763",
    "addr:housenumber":"82",
    "addr:postcode":"2763",
    "addr:street":"Farnham Rd",
    "iso:country":"AU",
    "sg:address":"82 Farnham Rd",
    "sg:city":"Quakers Hill",
    "sg:classifiers":[
        {
            "category":"Health Services",
            "subcategory":"Health Practitioner",
            "type":"Services"
        }
    ],
    "sg:phone":"+61 2 9837 7543",
    "sg:postcode":"2763",
    "sg:province":"NSW",
    "sg:tags":[
        "physiotherapist"
    ],
    "wof:name":"Complex Pain Management",
    "wof:placetype":"venue"
},
  "geometry": {"coordinates":[150.89573669399999,-33.7231369019],"type":"Point"}
}