{
  "type": "Feature",
  "properties": {
    "addr:full":"14 Hume Drv Lysterfield VIC 3156",
    "addr:housenumber":"14",
    "addr:postcode":"3156",
    "addr:street":"Hume Drv",
    "iso:country":"AU",
    "sg:address":"14 Hume Drv",
    "sg:city":"Lysterfield",
    "sg:classifiers":[
        {
            "category":"Building & Trades",
            "subcategory":"Plumbing",
            "type":"Services"
        }
    ],
    "sg:phone":"+61 408 548 822",
    "sg:postcode":"3156",
    "sg:province":"VIC",
    "sg:tags":[
        "plumber",
        "gasfitters"
    ],
    "wof:name":"Plumbing & Excavation Contractors Pty Ltd",
    "wof:placetype":"venue"
},
  "geometry": {"coordinates":[145.28826904300001,-37.9163284302],"type":"Point"}
}