{
  "type": "Feature",
  "properties": {
    "iso:country":"AU",
    "sg:address":"Unit 2/ 110 Bayswater Rd",
    "sg:city":"Pimlico",
    "sg:classifiers":[
        {
            "category":"Professional",
            "subcategory":"Detective & Security Services",
            "type":"Services"
        }
    ],
    "sg:phone":"+61 7 4725 6990",
    "sg:postcode":"4812",
    "sg:province":"QLD",
    "sg:tags":[
        "protective",
        "rustproofing"
    ],
    "wof:name":"Elite Window Tinting",
    "wof:placetype":"venue"
},
  "geometry": {"coordinates":[146.790527,-19.276548],"type":"Point"}
}