{
  "type": "Feature",
  "properties": {
    "addr:full":"3/ 20 Malcolm Rd Braeside VIC 3195",
    "addr:housenumber":"/ 20",
    "addr:postcode":"3195",
    "addr:street":"Malcolm Rd",
    "iso:country":"AU",
    "sg:address":"3/ 20 Malcolm Rd",
    "sg:city":"Braeside",
    "sg:classifiers":[
        {
            "category":"Shopping",
            "subcategory":"Stationery & Office Supplies",
            "type":"Retail Goods"
        }
    ],
    "sg:phone":"+61 3 9580 3822",
    "sg:postcode":"3195",
    "sg:province":"VIC",
    "sg:tags":[
        "packaging",
        "material"
    ],
    "wof:name":"Protective Packagings Pty Ltd",
    "wof:placetype":"venue"
},
  "geometry": {"coordinates":[145.10710144000001,-38.0006332397],"type":"Point"}
}