{
  "type": "Feature",
  "properties": {
    "addr:full":"52 Webb St Narre Warren VIC 3805",
    "addr:housenumber":"52",
    "addr:postcode":"3805",
    "addr:street":"Webb St",
    "iso:country":"AU",
    "sg:address":"52 Webb St",
    "sg:city":"Narre Warren",
    "sg:classifiers":[
        {
            "category":"Social Services",
            "subcategory":"Child Care",
            "type":"Services"
        }
    ],
    "sg:phone":"+61 3 9704 9033",
    "sg:postcode":"3805",
    "sg:province":"VIC",
    "wof:name":"City of Casey Child Care Complex Long Day Care",
    "wof:placetype":"venue"
},
  "geometry": {"coordinates":[145.30632019000001,-38.0239982605],"type":"Point"}
}