{
  "type": "Feature",
  "properties": {
    "iso:country":"AU",
    "sg:address":"6 Toorak Ave",
    "sg:city":"Lenah Valley",
    "sg:classifiers":[
        {
            "category":"Professional",
            "subcategory":"Management & Consulting",
            "type":"Services"
        }
    ],
    "sg:phone":"+61 3 6278 1177",
    "sg:postcode":"7008",
    "sg:province":"TAS",
    "sg:tags":[
        "consultant"
    ],
    "wof:name":"Noga Stephen & Associates Pty Ltd",
    "wof:placetype":"venue"
},
  "geometry": {"coordinates":[147.30381774899999,-42.8672637939],"type":"Point"}
}