{
  "type": "Feature",
  "properties": {
    "addr:full":"200 Bridge St Benalla VIC 3672",
    "addr:housenumber":"200",
    "addr:postcode":"3672",
    "addr:street":"Bridge St",
    "iso:country":"AU",
    "sg:address":"200 Bridge St",
    "sg:city":"Benalla",
    "sg:classifiers":[
        {
            "category":"Home & Garden",
            "subcategory":"Household Appliances",
            "type":"Retail Goods"
        }
    ],
    "sg:phone":"+61 3 5762 1735",
    "sg:postcode":"3672",
    "sg:province":"VIC",
    "sg:tags":[
        "heating",
        "system"
    ],
    "wof:name":"Trewin Plumbing & Pumps",
    "wof:placetype":"venue"
},
  "geometry": {"coordinates":[145.99580399999999,-36.549007],"type":"Point"}
}