{
  "type": "Feature",
  "properties": {
    "addr:full":"Oliver St Binalong NSW 2584",
    "addr:postcode":"2584",
    "addr:street":"Oliver St",
    "iso:country":"AU",
    "sg:address":"Oliver St",
    "sg:city":"Binalong",
    "sg:classifiers":[
        {
            "category":"Sports & Exercise",
            "subcategory":"Golf",
            "type":"Entertainment"
        }
    ],
    "sg:phone":"+61 2 6227 4241",
    "sg:postcode":"2584",
    "sg:province":"NSW",
    "sg:tags":[
        "club"
    ],
    "wof:name":"Binalong Golf Club",
    "wof:placetype":"venue"
},
  "geometry": {"coordinates":[148.63844299300001,-34.6791381836],"type":"Point"}
}