{
  "type": "Feature",
  "properties": {
    "addr:full":"31 High St Toowong QLD 4066",
    "addr:housenumber":"31",
    "addr:postcode":"4066",
    "addr:street":"High St",
    "iso:country":"AU",
    "sg:address":"31 High St",
    "sg:city":"Toowong",
    "sg:classifiers":[
        {
            "category":"Food & Beverages",
            "subcategory":"Supermarket",
            "type":"Retail Goods"
        }
    ],
    "sg:phone":"+61 7 3870 9284",
    "sg:postcode":"4066",
    "sg:province":"QLD",
    "sg:tags":[
        "grocery",
        "store"
    ],
    "wof:name":"Woolworths Limited",
    "wof:placetype":"venue"
},
  "geometry": {"coordinates":[152.99183654800001,-27.4860954285],"type":"Point"}
}