{
  "type": "Feature",
  "properties": {
    "addr:full":"PO Box 552 Warwick QLD 4370",
    "addr:postcode":"4370",
    "iso:country":"AU",
    "sg:address":"PO Box 552",
    "sg:city":"Warwick",
    "sg:classifiers":[
        {
            "category":"Building & Trades",
            "subcategory":"Plumbing",
            "type":"Services"
        }
    ],
    "sg:phone":"+61 7 4661 7363",
    "sg:postcode":"4370",
    "sg:province":"QLD",
    "sg:tags":[
        "plumber",
        "gasfitters"
    ],
    "wof:name":"Peter Stephens Plumbing",
    "wof:placetype":"venue"
},
  "geometry": {"coordinates":[152.03465270999999,-28.2181301117],"type":"Point"}
}