{
  "type": "Feature",
  "properties": {
    "addr:full":"5 Waterdale Rd Ivanhoe VIC 3079",
    "addr:housenumber":"5",
    "addr:postcode":"3079",
    "addr:street":"Waterdale Rd",
    "iso:country":"AU",
    "sg:address":"5 Waterdale Rd",
    "sg:city":"Ivanhoe",
    "sg:classifiers":[
        {
            "category":"Building & Trades",
            "subcategory":"Plumbing",
            "type":"Services"
        }
    ],
    "sg:phone":"+61 412 772 222",
    "sg:postcode":"3079",
    "sg:province":"VIC",
    "sg:tags":[
        "plumber",
        "gasfitters"
    ],
    "wof:name":"Challenge Plumbing",
    "wof:placetype":"venue"
},
  "geometry": {"coordinates":[145.040618897,-37.7812194824],"type":"Point"}
}