{
  "type": "Feature",
  "properties": {
    "addr:full":"49 Cowles Rd Mosman NSW 2088",
    "addr:housenumber":"49",
    "addr:postcode":"2088",
    "addr:street":"Cowles Rd",
    "iso:country":"AU",
    "sg:address":"49 Cowles Rd",
    "sg:city":"Mosman",
    "sg:classifiers":[
        {
            "category":"Professional",
            "subcategory":"Computer Services",
            "type":"Services"
        }
    ],
    "sg:phone":"+61 2 9960 1763",
    "sg:postcode":"2088",
    "sg:province":"NSW",
    "sg:tags":[
        "package",
        "software"
    ],
    "wof:name":"Bass Software Pty Ltd",
    "wof:placetype":"venue"
},
  "geometry": {"coordinates":[151.23841857900001,-33.8234710693],"type":"Point"}
}