{
  "type": "Feature",
  "properties": {
    "addr:full":"22 Davison St Mitcham VIC 3132",
    "addr:housenumber":"22",
    "addr:postcode":"3132",
    "addr:street":"Davison St",
    "iso:country":"AU",
    "sg:address":"22 Davison St",
    "sg:city":"Mitcham",
    "sg:classifiers":[
        {
            "category":"Organizations",
            "subcategory":"Membership Organization",
            "type":"Services"
        }
    ],
    "sg:phone":"+61 3 9873 3038",
    "sg:postcode":"3132",
    "sg:province":"VIC",
    "sg:tags":[
        "club",
        "car"
    ],
    "wof:name":"Austin 1800 Car Club",
    "wof:placetype":"venue"
},
  "geometry": {"coordinates":[145.20672607399999,-37.8279838562],"type":"Point"}
}