{
  "type": "Feature",
  "properties": {
    "addr:full":"1st Flr Carindale Shopng Cntr Creek Rd Carindale QLD 4152",
    "addr:postcode":"4152",
    "addr:street":"Creek Rd",
    "iso:country":"AU",
    "sg:address":"1st Flr Carindale Shopng Cntr Creek Rd",
    "sg:city":"Carindale",
    "sg:classifiers":[
        {
            "category":"Personal",
            "type":"Services"
        }
    ],
    "sg:phone":"+61 7 3843 2597",
    "sg:postcode":"4152",
    "sg:province":"QLD",
    "sg:tags":[
        "reducing",
        "treatment",
        "weight"
    ],
    "wof:name":"Jenny Craig",
    "wof:placetype":"venue"
},
  "geometry": {"coordinates":[153.10316467300001,-27.5040683746],"type":"Point"}
}