{
  "type": "Feature",
  "properties": {
    "iso:country":"AU",
    "sg:address":"14 Crawford St",
    "sg:city":"Katherine",
    "sg:classifiers":[
        {
            "category":"Wholesale",
            "subcategory":"Machinery & Supplies",
            "type":"Manufacturing & Wholesale Goods"
        }
    ],
    "sg:phone":"+61 8 8972 2333",
    "sg:postcode":"0850",
    "sg:province":"NT",
    "sg:tags":[
        "agricultural"
    ],
    "wof:name":"Wildkat Spares (Aust) Pty Ltd",
    "wof:placetype":"venue"
},
  "geometry": {"coordinates":[132.286621,-14.475357],"type":"Point"}
}