{
  "type": "Feature",
  "properties": {
    "addr:full":"56 Channel Hwy Kingston TAS 7050",
    "addr:housenumber":"56",
    "addr:postcode":"7050",
    "addr:street":"Channel Hwy",
    "iso:country":"AU",
    "sg:address":"56 Channel Hwy",
    "sg:city":"Kingston",
    "sg:classifiers":[
        {
            "category":"Shopping",
            "subcategory":"Computers & Home Electronics",
            "type":"Retail Goods"
        }
    ],
    "sg:phone":"+61 3 6227 1255",
    "sg:postcode":"7050",
    "sg:province":"TAS",
    "sg:tags":[
        "equipment",
        "supply"
    ],
    "wof:name":"Cartridge World",
    "wof:placetype":"venue"
},
  "geometry": {"coordinates":[147.305542,-42.975597],"type":"Point"}
}