{
  "type": "Feature",
  "properties": {
    "addr:full":"Unit 5, 321 Kelvin Grove Rd Kelvin Grove QLD 4059",
    "addr:housenumber":"321",
    "addr:postcode":"4059",
    "addr:street":"Kelvin Grove Rd",
    "iso:country":"AU",
    "sg:address":"Unit 5, 321 Kelvin Grove Rd",
    "sg:city":"Kelvin Grove",
    "sg:classifiers":[
        {
            "category":"Health Services",
            "subcategory":"Chiropractor",
            "type":"Services"
        }
    ],
    "sg:phone":"+61 7 3856 6996",
    "sg:postcode":"4059",
    "sg:province":"QLD",
    "wof:name":"Parker Brian Dr",
    "wof:placetype":"venue"
},
  "geometry": {"coordinates":[153.00793457,-27.4446811676],"type":"Point"}
}