{
  "type": "Feature",
  "properties": {
    "iso:country":"AU",
    "sg:address":"60 Tambourine Bay Rd",
    "sg:city":"Lane Cove",
    "sg:classifiers":[
        {
            "category":"Health Services",
            "subcategory":"Doctor",
            "type":"Services"
        }
    ],
    "sg:phone":"+61 2 9420 1102",
    "sg:postcode":"2066",
    "sg:province":"NSW",
    "sg:tags":[
        "medical",
        "practitioner"
    ],
    "wof:name":"Papadopoulos Tim Dr",
    "wof:placetype":"venue"
},
  "geometry": {"coordinates":[151.16514587399999,-33.8197402954],"type":"Point"}
}