{
  "type": "Feature",
  "properties": {
    "addr:full":"14A Hearne St Mortdale NSW 2223",
    "addr:housenumber":"14a",
    "addr:postcode":"2223",
    "addr:street":"Hearne St",
    "iso:country":"AU",
    "sg:address":"14A Hearne St",
    "sg:city":"Mortdale",
    "sg:classifiers":[
        {
            "category":"Government",
            "subcategory":"Department Of Motor Vehicles",
            "type":"Public Place"
        }
    ],
    "sg:phone":"+61 2 9533 6565",
    "sg:postcode":"2223",
    "sg:province":"NSW",
    "sg:tags":[
        "body",
        "supply",
        "trimmer"
    ],
    "wof:name":"Kolesnyk Convertible Tops",
    "wof:placetype":"venue"
},
  "geometry": {"coordinates":[151.067138672,-33.9653549194],"type":"Point"}
}