{
  "type": "Feature",
  "properties": {
    "iso:country":"AU",
    "sg:address":"15 Raven Crt",
    "sg:city":"Wynn Vale",
    "sg:classifiers":[
        {
            "category":"Building & Trades",
            "subcategory":"Landscaping Services",
            "type":"Services"
        }
    ],
    "sg:phone":"+61 8 8251 3519",
    "sg:postcode":"5127",
    "sg:province":"SA",
    "sg:tags":[
        "designer",
        "landscape",
        "contractor"
    ],
    "wof:name":"Phil's Fine Finish Paving & Landscape Service",
    "wof:placetype":"venue"
},
  "geometry": {"coordinates":[138.69685363799999,-34.7978286743],"type":"Point"}
}