{
  "type": "Feature",
  "properties": {
    "addr:full":"20 King&#039;s Park Rd West Perth WA 6005",
    "addr:housenumber":"20",
    "addr:postcode":"6005",
    "addr:street":"King &;039 S Park Rd",
    "iso:country":"AU",
    "sg:address":"20 King&#039;s Park Rd",
    "sg:city":"West Perth",
    "sg:classifiers":[
        {
            "category":"Insurance",
            "subcategory":"Hazard Insurance",
            "type":"Services"
        }
    ],
    "sg:phone":"+61 8 9320 5900",
    "sg:postcode":"6005",
    "sg:province":"WA",
    "sg:tags":[
        "fire",
        "accident",
        "marine"
    ],
    "wof:name":"Associated Marine Insurers Agents Pty Ltd",
    "wof:placetype":"venue"
},
  "geometry": {"coordinates":[115.83177947999999,-31.9497432709],"type":"Point"}
}