{
  "type": "Feature",
  "properties": {
    "addr:full":"867 D'Aguilar Hwy Wamuran QLD 4512",
    "addr:housenumber":"867",
    "addr:postcode":"4512",
    "addr:street":"D'Aguilar Hwy",
    "iso:country":"AU",
    "sg:address":"867 D'Aguilar Hwy",
    "sg:city":"Wamuran",
    "sg:classifiers":[
        {
            "category":"Retail",
            "subcategory":"Veterinary Services",
            "type":"Services"
        }
    ],
    "sg:phone":"+61 7 5496 6566",
    "sg:postcode":"4512",
    "sg:province":"QLD",
    "sg:tags":[
        "surgeon"
    ],
    "wof:name":"Chiro Vet Services",
    "wof:placetype":"venue"
},
  "geometry": {"coordinates":[152.86144999999999,-27.039864],"type":"Point"}
}