{
  "type": "Feature",
  "properties": {
    "addr:full":"C/o Post Office Narrung 5259 Narrung SA 5259",
    "addr:postcode":"5259;5259",
    "addr:street":"C;Narrung",
    "iso:country":"AU",
    "sg:address":"C/o Post Office Narrung 5259",
    "sg:city":"Narrung",
    "sg:classifiers":[
        {
            "category":"Communications",
            "subcategory":"News Services",
            "type":"Services"
        }
    ],
    "sg:phone":"+61 8 8574 0037",
    "sg:postcode":"5259",
    "sg:province":"SA",
    "sg:tags":[
        "information",
        "tourist",
        "attractions"
    ],
    "wof:name":"Coorong Nature Tours",
    "wof:placetype":"venue"
},
  "geometry": {"coordinates":[139.22419738799999,-35.5725440979],"type":"Point"}
}