{
  "type": "Feature",
  "properties": {
    "addr:full":"39 Macquarie St Merewether NSW 2291",
    "addr:housenumber":"39",
    "addr:postcode":"2291",
    "addr:street":"Macquarie St",
    "iso:country":"AU",
    "sg:address":"39 Macquarie St",
    "sg:city":"Merewether",
    "sg:classifiers":[
        {
            "category":"Building & Trades",
            "subcategory":"Construction",
            "type":"Services"
        }
    ],
    "sg:phone":"+61 2 4963 6292",
    "sg:postcode":"2291",
    "sg:province":"NSW",
    "sg:tags":[
        "concrete",
        "contractor"
    ],
    "wof:name":"Complete Computer Services",
    "wof:placetype":"venue"
},
  "geometry": {"coordinates":[151.742675781,-32.9388046265],"type":"Point"}
}