{
  "type": "Feature",
  "properties": {
    "addr:full":"88 Bent St Neutral Bay NSW 2089",
    "addr:housenumber":"88",
    "addr:postcode":"2089",
    "addr:street":"Bent St",
    "iso:country":"AU",
    "sg:address":"88 Bent St",
    "sg:city":"Neutral Bay",
    "sg:classifiers":[
        {
            "category":"Building & Trades",
            "subcategory":"Cleaning & Sanitation",
            "type":"Services"
        }
    ],
    "sg:phone":"+61 2 9908 2759",
    "sg:postcode":"2089",
    "sg:province":"NSW",
    "sg:tags":[
        "window"
    ],
    "wof:name":"Lancaster & Lancaster Window Cleaning Services",
    "wof:placetype":"venue"
},
  "geometry": {"coordinates":[151.21653747600001,-33.8304901123],"type":"Point"}
}