{
  "type": "Feature",
  "properties": {
    "iso:country":"AU",
    "sg:address":"21 Black St",
    "sg:city":"Brighton",
    "sg:classifiers":[
        {
            "category":"Health Services",
            "subcategory":"Dentist",
            "type":"Services"
        }
    ],
    "sg:phone":"+61 3 9592 7584",
    "sg:postcode":"3186",
    "sg:province":"VIC",
    "wof:name":"Pearson John R",
    "wof:placetype":"venue"
},
  "geometry": {"coordinates":[144.99574279800001,-37.9131889343],"type":"Point"}
}