{
  "type": "Feature",
  "properties": {
    "addr:full":"1 Lovett Drv Avondale Heights VIC 3034",
    "addr:housenumber":"1",
    "addr:postcode":"3034",
    "addr:street":"Lovett Drv",
    "iso:country":"AU",
    "sg:address":"1 Lovett Drv",
    "sg:city":"Avondale Heights",
    "sg:classifiers":[
        {
            "category":"Retail",
            "subcategory":"Animal Services",
            "type":"Services"
        }
    ],
    "sg:phone":"+61 3 9337 3387",
    "sg:postcode":"3034",
    "sg:province":"VIC",
    "sg:tags":[
        "breeder",
        "sheep",
        "stud",
        "cattle"
    ],
    "wof:name":"Jolimont Alpaca",
    "wof:placetype":"venue"
},
  "geometry": {"coordinates":[144.87408400000001,-37.755135],"type":"Point"}
}