{
  "type": "Feature",
  "properties": {
    "addr:full":"36 William St Gol Gol NSW 2738",
    "addr:housenumber":"36",
    "addr:postcode":"2738",
    "addr:street":"William St",
    "iso:country":"AU",
    "sg:address":"36 William St",
    "sg:city":"Gol Gol",
    "sg:classifiers":[
        {
            "category":"Personal",
            "subcategory":"Massage",
            "type":"Services"
        }
    ],
    "sg:phone":"+61 3 5024 8689",
    "sg:postcode":"2738",
    "sg:province":"NSW",
    "sg:tags":[
        "therapy"
    ],
    "wof:name":"Margaret Davidson",
    "wof:placetype":"venue"
},
  "geometry": {"coordinates":[142.22363300000001,-34.178894],"type":"Point"}
}