{
  "type": "Feature",
  "properties": {
    "iso:country":"AU",
    "sg:address":"17 White Rd",
    "sg:city":"Gepps Cross",
    "sg:classifiers":[
        {
            "category":"Structure",
            "subcategory":"Office Building",
            "type":"Public Place"
        }
    ],
    "sg:phone":"+61 8 8359 7522",
    "sg:postcode":"5094",
    "sg:province":"SA",
    "sg:tags":[
        "fire",
        "window",
        "door"
    ],
    "wof:name":"Australian Timber Doors",
    "wof:placetype":"venue"
},
  "geometry": {"coordinates":[138.59297180199999,-34.8427467346],"type":"Point"}
}