{
  "type": "Feature",
  "properties": {
    "addr:full":"222 Glenmore Rd Paddington NSW 2021",
    "addr:housenumber":"222",
    "addr:postcode":"2021",
    "addr:street":"Glenmore Rd",
    "iso:country":"AU",
    "sg:address":"222 Glenmore Rd",
    "sg:city":"Paddington",
    "sg:classifiers":[
        {
            "category":"Fast Food",
            "type":"Food & Drink"
        }
    ],
    "sg:phone":"+61 2 9360 6796",
    "sg:postcode":"2021",
    "sg:province":"NSW",
    "sg:tags":[
        "away",
        "take"
    ],
    "wof:name":"Christos Five Ways Pizzeria",
    "wof:placetype":"venue"
},
  "geometry": {"coordinates":[151.22796630900001,-33.8820991516],"type":"Point"}
}