{
  "type": "Feature",
  "properties": {
    "addr:full":"Main St North Rockhampton QLD 4701",
    "addr:postcode":"4701",
    "addr:street":"Main St North",
    "iso:country":"AU",
    "sg:address":"Main St",
    "sg:city":"North Rockhampton",
    "sg:classifiers":[
        {
            "category":"Education",
            "subcategory":"School",
            "type":"Public Place"
        }
    ],
    "sg:phone":"+61 7 4931 1111",
    "sg:postcode":"4701",
    "sg:province":"QLD",
    "sg:tags":[
        "state",
        "except",
        "nsw"
    ],
    "wof:name":"Park Avenue Primary School",
    "wof:placetype":"venue"
},
  "geometry": {"coordinates":[150.52311706500001,-23.348865509],"type":"Point"}
}