{
  "type": "Feature",
  "properties": {
    "iso:country":"AU",
    "sg:address":"80 Violet St",
    "sg:city":"Revesby",
    "sg:classifiers":[
        {
            "category":"Utilities",
            "subcategory":"Refuse",
            "type":"Services"
        }
    ],
    "sg:phone":"+61 2 9642 3849",
    "sg:postcode":"2212",
    "sg:province":"NSW",
    "sg:tags":[
        "disposal",
        "reduction",
        "waste"
    ],
    "wof:name":"Westside Waste Service",
    "wof:placetype":"venue"
},
  "geometry": {"coordinates":[151.00590500000001,-33.936195],"type":"Point"}
}