{
  "type": "Feature",
  "properties": {
    "iso:country":"AU",
    "sg:address":"8 Oxley Crs",
    "sg:city":"Ivanhoe",
    "sg:classifiers":[
        {
            "category":"Education",
            "subcategory":"Kindergarten",
            "type":"Public Place"
        }
    ],
    "sg:phone":"+61 2 6995 1349",
    "sg:postcode":"2878",
    "sg:province":"NSW",
    "sg:tags":[
        "pre-schools"
    ],
    "wof:name":"Ivanhoe Preschool",
    "wof:placetype":"venue"
},
  "geometry": {"coordinates":[144.298477,-32.897362],"type":"Point"}
}