{
  "type": "Feature",
  "properties": {
    "addr:full":"227 Flinders St Beauty Point TAS 7270",
    "addr:housenumber":"227",
    "addr:postcode":"7270",
    "addr:street":"Flinders St",
    "iso:country":"AU",
    "sg:address":"227 Flinders St",
    "sg:city":"Beauty Point",
    "sg:classifiers":[
        {
            "category":"Autos & Motor Vehicles",
            "subcategory":"Fuel & Gas Station",
            "type":"Retail Goods"
        }
    ],
    "sg:phone":"+61 3 6383 4379",
    "sg:postcode":"7270",
    "sg:province":"TAS",
    "wof:name":"Shell Beauty Point",
    "wof:placetype":"venue"
},
  "geometry": {"coordinates":[146.81890869099999,-41.1485328674],"type":"Point"}
}