{
  "type": "Feature",
  "properties": {
    "iso:country":"AU",
    "sg:address":"Lot 3, 192 Wonga Rd",
    "sg:city":"Ringwood",
    "sg:classifiers":[
        {
            "category":"Utilities",
            "subcategory":"Refuse",
            "type":"Services"
        }
    ],
    "sg:phone":"+61 3 9876 1611",
    "sg:postcode":"3134",
    "sg:province":"VIC",
    "sg:tags":[
        "remover",
        "rubbish"
    ],
    "wof:name":"Eastern Crane Skips",
    "wof:placetype":"venue"
},
  "geometry": {"coordinates":[145.24957275400001,-37.7794189453],"type":"Point"}
}