{
  "type": "Feature",
  "properties": {
    "iso:country":"AU",
    "sg:address":"259 High St",
    "sg:city":"Northcote",
    "sg:classifiers":[
        {
            "category":"Shopping",
            "subcategory":"Clothing, Apparel, & Fashions",
            "type":"Retail Goods"
        }
    ],
    "sg:phone":"+61 3 9481 8858",
    "sg:postcode":"3070",
    "sg:province":"VIC",
    "sg:tags":[
        "lady",
        "wear"
    ],
    "wof:name":"I Dream A Highway",
    "wof:placetype":"venue"
},
  "geometry": {"coordinates":[144.998154,-37.77277],"type":"Point"}
}