{
  "type": "Feature",
  "properties": {
    "addr:full":"94 John St Cabramatta NSW 2166",
    "addr:housenumber":"94",
    "addr:postcode":"2166",
    "addr:street":"John St",
    "iso:country":"AU",
    "sg:address":"94 John St",
    "sg:city":"Cabramatta",
    "sg:classifiers":[
        {
            "category":"Restaurant",
            "type":"Food & Drink"
        }
    ],
    "sg:phone":"+61 2 9726 5703",
    "sg:postcode":"2166",
    "sg:province":"NSW",
    "wof:name":"Barluck Restaurant",
    "wof:placetype":"venue"
},
  "geometry": {"coordinates":[150.93406677199999,-33.8949356079],"type":"Point"}
}