{
  "type": "Feature",
  "properties": {
    "addr:full":"Lake Rd Coffs Harbour NSW 2450",
    "addr:postcode":"2450",
    "addr:street":"Lake Rd",
    "iso:country":"AU",
    "sg:address":"Lake Rd",
    "sg:city":"Coffs Harbour",
    "sg:classifiers":[
        {
            "category":"Mining & Drilling",
            "type":"Manufacturing & Wholesale Goods"
        }
    ],
    "sg:phone":"+61 419 423 338",
    "sg:postcode":"2450",
    "sg:province":"NSW",
    "sg:tags":[
        "boring",
        "contractor"
    ],
    "wof:name":"Coffs Coast Under Road Boring",
    "wof:placetype":"venue"
},
  "geometry": {"coordinates":[153.091644,-30.306608],"type":"Point"}
}