{
  "type": "Feature",
  "properties": {
    "addr:full":"13 Roebuck Ave Canning Vale WA 6155",
    "addr:housenumber":"13",
    "addr:postcode":"6155",
    "addr:street":"Roebuck Ave",
    "iso:country":"AU",
    "sg:address":"13 Roebuck Ave",
    "sg:city":"Canning Vale",
    "sg:classifiers":[
        {
            "category":"Professional",
            "subcategory":"Art Services",
            "type":"Services"
        }
    ],
    "sg:phone":"+61 8 9456 0302",
    "sg:postcode":"6155",
    "sg:province":"WA",
    "sg:tags":[
        "decorator",
        "painter"
    ],
    "wof:name":"Parkwood Painting Service",
    "wof:placetype":"venue"
},
  "geometry": {"coordinates":[115.928337,-32.101604],"type":"Point"}
}