{
  "type": "Feature",
  "properties": {
    "addr:full":"Bogong Pl Tumut NSW 2720",
    "addr:postcode":"2720",
    "addr:street":"Pl",
    "iso:country":"AU",
    "sg:address":"Bogong Pl",
    "sg:city":"Tumut",
    "sg:classifiers":[
        {
            "category":"Education",
            "subcategory":"School",
            "type":"Public Place"
        }
    ],
    "sg:phone":"+61 2 6947 1077",
    "sg:postcode":"2720",
    "sg:province":"NSW",
    "sg:tags":[
        "state",
        "-",
        "nsw"
    ],
    "wof:name":"Tumut High School",
    "wof:placetype":"venue"
},
  "geometry": {"coordinates":[148.21785,-35.312202],"type":"Point"}
}