{
  "type": "Feature",
  "properties": {
    "addr:full":"7 Clarendon St Derby WA 6728",
    "addr:housenumber":"7",
    "addr:postcode":"6728",
    "addr:street":"Clarendon St",
    "iso:country":"AU",
    "sg:address":"7 Clarendon St",
    "sg:city":"Derby",
    "sg:classifiers":[
        {
            "category":"Retail",
            "subcategory":"Auto Repair",
            "type":"Services"
        }
    ],
    "sg:phone":"+61 8 9193 1180",
    "sg:postcode":"6728",
    "sg:province":"WA",
    "sg:tags":[
        "electrical"
    ],
    "wof:name":"Mangrove Auto Electrics",
    "wof:placetype":"venue"
},
  "geometry": {"coordinates":[123.625587463,-17.3024272919],"type":"Point"}
}