{
  "type": "Feature",
  "properties": {
    "addr:full":"1 Senna Rd Wingfield SA 5013",
    "addr:housenumber":"1",
    "addr:postcode":"5013",
    "addr:street":"Senna Rd",
    "iso:country":"AU",
    "sg:address":"1 Senna Rd",
    "sg:city":"Wingfield",
    "sg:classifiers":[
        {
            "category":"Autos & Motor Vehicles",
            "subcategory":"Auto Supplies",
            "type":"Retail Goods"
        }
    ],
    "sg:phone":"+61 8 8260 4388",
    "sg:postcode":"5013",
    "sg:province":"SA",
    "sg:tags":[
        "tyre"
    ],
    "wof:name":"Tyre Choice",
    "wof:placetype":"venue"
},
  "geometry": {"coordinates":[138.56449890100001,-34.8421516418],"type":"Point"}
}