{
  "type": "Feature",
  "properties": {
    "addr:full":"76 Carrington Rd Waverley NSW 2024",
    "addr:housenumber":"76",
    "addr:postcode":"2024",
    "addr:street":"Carrington Rd",
    "iso:country":"AU",
    "sg:address":"76 Carrington Rd",
    "sg:city":"Waverley",
    "sg:classifiers":[
        {
            "category":"Building & Trades",
            "subcategory":"Construction",
            "type":"Services"
        }
    ],
    "sg:phone":"+61 2 9389 8100",
    "sg:postcode":"2024",
    "sg:province":"NSW",
    "sg:tags":[
        "contractor"
    ],
    "wof:name":"Carrington (Constructions) Pty Ltd",
    "wof:placetype":"venue"
},
  "geometry": {"coordinates":[151.25387573200001,-33.8999481201],"type":"Point"}
}