{
  "type": "Feature",
  "properties": {
    "addr:full":"1 Hemmant Rd Hemmant QLD 4174",
    "addr:housenumber":"1",
    "addr:postcode":"4174",
    "addr:street":"Hemmant Rd",
    "iso:country":"AU",
    "sg:address":"1 Hemmant Rd",
    "sg:city":"Hemmant",
    "sg:classifiers":[
        {
            "category":"Building & Trades",
            "subcategory":"Plumbing",
            "type":"Services"
        }
    ],
    "sg:phone":"+61 7 3890 3122",
    "sg:postcode":"4174",
    "sg:province":"QLD",
    "sg:tags":[
        "equipment",
        "valves"
    ],
    "wof:name":"ValvesOnline#",
    "wof:placetype":"venue"
},
  "geometry": {"coordinates":[153.12521362300001,-27.4454364777],"type":"Point"}
}