{
  "type": "Feature",
  "properties": {
    "addr:full":"8/ 29 Letitia St Oatley NSW 2223",
    "addr:housenumber":"/ 29",
    "addr:postcode":"2223",
    "addr:street":"Letitia St",
    "iso:country":"AU",
    "sg:address":"8/ 29 Letitia St",
    "sg:city":"Oatley",
    "sg:classifiers":[
        {
            "category":"Professional",
            "subcategory":"Art Services",
            "type":"Services"
        }
    ],
    "sg:phone":"+61 431 161 178",
    "sg:postcode":"2223",
    "sg:province":"NSW",
    "sg:tags":[
        "graphic",
        "designer"
    ],
    "wof:name":"Deep Fried",
    "wof:placetype":"venue"
},
  "geometry": {"coordinates":[151.08128356899999,-33.9823303223],"type":"Point"}
}