{
  "type": "Feature",
  "properties": {
    "addr:full":"Gate 3 Olympia St Tottenham VIC 3012",
    "addr:housenumber":"3",
    "addr:postcode":"3012",
    "addr:street":"Gate;Olympia St",
    "iso:country":"AU",
    "sg:address":"Gate 3 Olympia St",
    "sg:city":"Tottenham",
    "sg:classifiers":[
        {
            "category":"Shopping",
            "subcategory":"Clothing, Apparel, & Fashions",
            "type":"Retail Goods"
        }
    ],
    "sg:phone":"+61 3 9315 1666",
    "sg:postcode":"3012",
    "sg:province":"VIC",
    "sg:tags":[
        "jean"
    ],
    "wof:name":"Westco Jeans (Aust) Pty Ltd",
    "wof:placetype":"venue"
},
  "geometry": {"coordinates":[144.85710144000001,-37.803981781],"type":"Point"}
}