{
  "type": "Feature",
  "properties": {
    "iso:country":"AU",
    "sg:address":"56 Duerdin St",
    "sg:city":"Clayton",
    "sg:classifiers":[
        {
            "category":"Manufacturing",
            "subcategory":"Tools & Machinery",
            "type":"Manufacturing & Wholesale Goods"
        }
    ],
    "sg:phone":"+61 3 9562 1511",
    "sg:postcode":"3168",
    "sg:province":"VIC",
    "sg:tags":[
        "machine",
        "knife"
    ],
    "sg:website":"http://www.blakeley.com.au",
    "wof:name":"Blakeley W H Industrial Knives Pty Ltd",
    "wof:placetype":"venue"
},
  "geometry": {"coordinates":[145.14610290499999,-37.9104614258],"type":"Point"}
}