{
  "type": "Feature",
  "properties": {
    "addr:full":"93 George St Fitzroy VIC 3065",
    "addr:housenumber":"93",
    "addr:postcode":"3065",
    "addr:street":"George St",
    "iso:country":"AU",
    "sg:address":"93 George St",
    "sg:city":"Fitzroy",
    "sg:classifiers":[
        {
            "category":"Personal",
            "type":"Services"
        }
    ],
    "sg:phone":"+61 3 9419 0023",
    "sg:postcode":"3065",
    "sg:province":"VIC",
    "sg:tags":[
        "gift"
    ],
    "wof:name":"Hampering Around",
    "wof:placetype":"venue"
},
  "geometry": {"coordinates":[144.98046875,-37.8059997559],"type":"Point"}
}