{
  "type": "Feature",
  "properties": {
    "addr:full":"Progress St Quinalow QLD 4403",
    "addr:postcode":"4403",
    "addr:street":"Progress St",
    "iso:country":"AU",
    "sg:address":"Progress St",
    "sg:city":"Quinalow",
    "sg:classifiers":[
        {
            "category":"Education",
            "subcategory":"School",
            "type":"Public Place"
        }
    ],
    "sg:phone":"+61 7 4692 9321",
    "sg:postcode":"4403",
    "sg:province":"QLD",
    "sg:tags":[
        "state",
        "except",
        "nsw"
    ],
    "wof:name":"Quinalow Preschool",
    "wof:placetype":"venue"
},
  "geometry": {"coordinates":[151.62266540499999,-27.1109008789],"type":"Point"}
}