{
  "type": "Feature",
  "properties": {
    "addr:full":"Windarra Pl Castle Hill NSW 2154",
    "addr:postcode":"2154",
    "addr:street":"Pl",
    "iso:country":"AU",
    "sg:address":"Windarra Pl",
    "sg:city":"Castle Hill",
    "sg:classifiers":[
        {
            "category":"Banks & Credit Unions",
            "subcategory":"Bank",
            "type":"Services"
        }
    ],
    "sg:phone":"+61 2 9680 8822",
    "sg:postcode":"2154",
    "sg:province":"NSW",
    "sg:tags":[
        "broker",
        "mortgage"
    ],
    "wof:name":"C.F Services",
    "wof:placetype":"venue"
},
  "geometry": {"coordinates":[150.98141479500001,-33.7142181396],"type":"Point"}
}