{
  "type": "Feature",
  "properties": {
    "addr:full":"Shop 186 Bayside North Shopping Centre, 15 Beach St Frankston VIC 3199",
    "addr:housenumber":"186;15",
    "addr:postcode":"3199",
    "addr:street":"Bayside North Shopping;Beach St",
    "iso:country":"AU",
    "sg:address":"Shop 186 Bayside North Shopping Centre, 15 Beach St",
    "sg:city":"Frankston",
    "sg:classifiers":[
        {
            "category":"Travel",
            "subcategory":"Travel Agent",
            "type":"Entertainment"
        }
    ],
    "sg:phone":"+61 3 9293 7177",
    "sg:postcode":"3199",
    "sg:province":"VIC",
    "sg:tags":[
        "consultant"
    ],
    "wof:name":"Escape Travel",
    "wof:placetype":"venue"
},
  "geometry": {"coordinates":[145.122650147,-38.3894042969],"type":"Point"}
}