{
  "type": "Feature",
  "properties": {
    "addr:full":"Gundy Rd Scone NSW 2337",
    "addr:postcode":"2337",
    "addr:street":"Gundy Rd",
    "iso:country":"AU",
    "sg:address":"Gundy Rd",
    "sg:city":"Scone",
    "sg:classifiers":[
        {
            "category":"Travel",
            "subcategory":"Hotels & Motels",
            "type":"Entertainment"
        }
    ],
    "sg:phone":"+61 2 6546 1156",
    "sg:postcode":"2337",
    "sg:province":"NSW",
    "sg:tags":[
        "accommodation"
    ],
    "wof:name":"Belltrees Country House",
    "wof:placetype":"venue"
},
  "geometry": {"coordinates":[150.86993408199999,-32.0558586121],"type":"Point"}
}