{
  "type": "Feature",
  "properties": {
    "addr:full":"28 Bodley St Beaumaris VIC 3193",
    "addr:housenumber":"28",
    "addr:postcode":"3193",
    "addr:street":"Bodley St",
    "iso:country":"AU",
    "sg:address":"28 Bodley St",
    "sg:city":"Beaumaris",
    "sg:classifiers":[
        {
            "category":"Social Services",
            "subcategory":"Child Care",
            "type":"Services"
        }
    ],
    "sg:phone":"+61 3 9589 4615",
    "sg:postcode":"3193",
    "sg:province":"VIC",
    "sg:tags":[
        "support",
        "health"
    ],
    "wof:name":"Maternal & Child Health Centres",
    "wof:placetype":"venue"
},
  "geometry": {"coordinates":[145.040771484,-37.9907150269],"type":"Point"}
}