{
  "type": "Feature",
  "properties": {
    "addr:full":"6 Colonna Pl Quinns Rocks WA 6030",
    "addr:housenumber":"6",
    "addr:postcode":"6030",
    "addr:street":"Pl",
    "iso:country":"AU",
    "sg:address":"6 Colonna Pl",
    "sg:city":"Quinns Rocks",
    "sg:classifiers":[
        {
            "category":"Professional",
            "subcategory":"Management & Consulting",
            "type":"Services"
        }
    ],
    "sg:phone":"+61 8 9304 3611",
    "sg:postcode":"6030",
    "sg:province":"WA",
    "sg:tags":[
        "consultant"
    ],
    "wof:name":"Amberley Management Pty Ltd",
    "wof:placetype":"venue"
},
  "geometry": {"coordinates":[115.69644165,-31.6623325348],"type":"Point"}
}