{
  "type": "Feature",
  "properties": {
    "addr:full":"39 Tank St Gladstone QLD 4680",
    "addr:housenumber":"39",
    "addr:postcode":"4680",
    "addr:street":"Tank St",
    "iso:country":"AU",
    "sg:address":"39 Tank St",
    "sg:city":"Gladstone",
    "sg:classifiers":[
        {
            "category":"Health Services",
            "subcategory":"Doctor",
            "type":"Services"
        }
    ],
    "sg:phone":"+61 7 4972 3454",
    "sg:postcode":"4680",
    "sg:province":"QLD",
    "sg:tags":[
        "medical",
        "practitioner"
    ],
    "wof:name":"Lynch T B Dr",
    "wof:placetype":"venue"
},
  "geometry": {"coordinates":[151.26031494099999,-23.8485603333],"type":"Point"}
}