{
  "type": "Feature",
  "properties": {
    "iso:country":"AU",
    "sg:address":"859 Lytton Rd",
    "sg:city":"Murarrie",
    "sg:classifiers":[
        {
            "category":"Professional",
            "subcategory":"Detective & Security Services",
            "type":"Services"
        }
    ],
    "sg:phone":"+61 1300 877 482",
    "sg:postcode":"4172",
    "sg:province":"QLD",
    "sg:tags":[
        "consultant",
        "system"
    ],
    "wof:name":"Executive Protection Services Pty Ltd",
    "wof:placetype":"venue"
},
  "geometry": {"coordinates":[153.10430908199999,-27.456823349],"type":"Point"}
}