{
  "type": "Feature",
  "properties": {
    "addr:full":"6 Tennant St Fyshwick ACT 2609",
    "addr:housenumber":"6",
    "addr:postcode":"2609",
    "addr:street":"Tennant St",
    "iso:country":"AU",
    "sg:address":"6 Tennant St",
    "sg:city":"Fyshwick",
    "sg:classifiers":[
        {
            "category":"Home & Garden",
            "subcategory":"Building Materials",
            "type":"Retail Goods"
        }
    ],
    "sg:phone":"+61 2 6239 1255",
    "sg:postcode":"2609",
    "sg:province":"ACT",
    "sg:tags":[
        "retaining",
        "wall"
    ],
    "wof:name":"C & M Bricks Pty Ltd",
    "wof:placetype":"venue"
},
  "geometry": {"coordinates":[149.18069457999999,-35.3305282593],"type":"Point"}
}