{
  "type": "Feature",
  "properties": {
    "addr:full":"42- 44 Dampier St Tamworth NSW 2340",
    "addr:housenumber":"44",
    "addr:postcode":"2340",
    "addr:street":"Dampier St",
    "iso:country":"AU",
    "sg:address":"42- 44 Dampier St",
    "sg:city":"Tamworth",
    "sg:classifiers":[
        {
            "category":"Home & Garden",
            "subcategory":"Building Materials",
            "type":"Retail Goods"
        }
    ],
    "sg:phone":"+61 2 6762 4324",
    "sg:postcode":"2340",
    "sg:province":"NSW",
    "sg:tags":[
        "supply"
    ],
    "wof:name":"Trussframe Pty Ltd",
    "wof:placetype":"venue"
},
  "geometry": {"coordinates":[150.91226196299999,-31.0900878906],"type":"Point"}
}