{
  "type": "Feature",
  "properties": {
    "addr:full":"69 Redcliffe Pde Redcliffe QLD 4020",
    "addr:housenumber":"69",
    "addr:postcode":"4020",
    "addr:street":"Redcliffe Pde",
    "iso:country":"AU",
    "sg:address":"69 Redcliffe Pde",
    "sg:city":"Redcliffe",
    "sg:classifiers":[
        {
            "category":"Real Estate",
            "subcategory":"Real Estate Agent",
            "type":"Services"
        }
    ],
    "sg:phone":"+61 7 3883 2111",
    "sg:postcode":"4020",
    "sg:province":"QLD",
    "wof:name":"Raine & Horne (Qld) Pty Ltd",
    "wof:placetype":"venue"
},
  "geometry": {"coordinates":[153.115295,-27.22826],"type":"Point"}
}