{
  "type": "Feature",
  "properties": {
    "iso:country":"AU",
    "sg:address":"16 Croatia Pl",
    "sg:city":"Quakers Hill",
    "sg:classifiers":[
        {
            "category":"Professional",
            "subcategory":"Art Services",
            "type":"Services"
        }
    ],
    "sg:phone":"+61 2 9837 1187",
    "sg:postcode":"2763",
    "sg:province":"NSW",
    "sg:tags":[
        "decorator",
        "painter"
    ],
    "wof:name":"Beato A & F M",
    "wof:placetype":"venue"
},
  "geometry": {"coordinates":[150.89389038100001,-33.719783783],"type":"Point"}
}