{
  "type": "Feature",
  "properties": {
    "addr:full":"McCourt Rd Moss Vale NSW 2577",
    "addr:postcode":"2577",
    "addr:street":"Mccourt Rd",
    "iso:country":"AU",
    "sg:address":"McCourt Rd",
    "sg:city":"Moss Vale",
    "sg:classifiers":[
        {
            "category":"Retail",
            "subcategory":"Storage",
            "type":"Services"
        }
    ],
    "sg:phone":"+61 2 4868 3355",
    "sg:postcode":"2577",
    "sg:province":"NSW",
    "sg:tags":[
        "removal",
        "furniture"
    ],
    "wof:name":"Moss Vale Removals & Storage",
    "wof:placetype":"venue"
},
  "geometry": {"coordinates":[150.37525939899999,-34.5411338806],"type":"Point"}
}