{
  "type": "Feature",
  "properties": {
    "iso:country":"AU",
    "sg:address":"PO Box 182",
    "sg:city":"Inglewood",
    "sg:classifiers":[
        {
            "category":"Home & Garden",
            "subcategory":"Building Materials",
            "type":"Retail Goods"
        }
    ],
    "sg:phone":"+61 8 9370 1157",
    "sg:postcode":"6932",
    "sg:province":"WA",
    "sg:tags":[
        "shutter",
        "roller",
        "grille"
    ],
    "wof:name":"Dial A Roller Shutter",
    "wof:placetype":"venue"
},
  "geometry": {"coordinates":[115.885520935,-31.9217605591],"type":"Point"}
}