{
  "type": "Feature",
  "properties": {
    "addr:full":"Cnr Sherbourne & Rattray Rds Montmorency VIC 3094",
    "addr:postcode":"3094",
    "iso:country":"AU",
    "sg:address":"Cnr Sherbourne & Rattray Rds",
    "sg:city":"Montmorency",
    "sg:classifiers":[
        {
            "category":"Food & Beverages",
            "subcategory":"Groceries & Convenience Stores",
            "type":"Retail Goods"
        }
    ],
    "sg:phone":"+61 3 9439 6133",
    "sg:postcode":"3094",
    "sg:province":"VIC",
    "wof:name":"7-Eleven Stores Pty Ltd",
    "wof:placetype":"venue"
},
  "geometry": {"coordinates":[145.131759644,-37.7125434875],"type":"Point"}
}