{
  "type": "Feature",
  "properties": {
    "addr:full":"15 - 17 Northview St Mermaid Beach QLD 4218",
    "addr:housenumber":"17",
    "addr:postcode":"4218",
    "addr:street":"Northview St",
    "iso:country":"AU",
    "sg:address":"15 - 17 Northview St",
    "sg:city":"Mermaid Beach",
    "sg:classifiers":[
        {
            "category":"Retail",
            "subcategory":"Auto Repair",
            "type":"Services"
        }
    ],
    "sg:phone":"+61 7 5575 2588",
    "sg:postcode":"4218",
    "sg:province":"QLD",
    "sg:tags":[
        "beater",
        "painter",
        "panel"
    ],
    "wof:name":"Alpine Accident Repair Centre",
    "wof:placetype":"venue"
},
  "geometry": {"coordinates":[153.431732178,-28.0408916473],"type":"Point"}
}