{
  "type": "Feature",
  "properties": {
    "addr:full":"Cnr Kingaroy & Knight Sts Kingaroy QLD 4610",
    "addr:postcode":"4610",
    "addr:street":"Cnr",
    "iso:country":"AU",
    "sg:address":"Cnr Kingaroy & Knight Sts",
    "sg:city":"Kingaroy",
    "sg:classifiers":[
        {
            "category":"Fast Food",
            "type":"Food & Drink"
        }
    ],
    "sg:phone":"+61 7 4162 4624",
    "sg:postcode":"4610",
    "sg:province":"QLD",
    "sg:tags":[
        "away",
        "take"
    ],
    "wof:name":"Red Rooster",
    "wof:placetype":"venue"
},
  "geometry": {"coordinates":[151.835845947,-26.5428390503],"type":"Point"}
}