{
  "type": "Feature",
  "properties": {
    "addr:full":"26 Leighton Crs Deer Park VIC 3023",
    "addr:housenumber":"26",
    "addr:postcode":"3023",
    "addr:street":"Leighton Crs",
    "iso:country":"AU",
    "sg:address":"26 Leighton Crs",
    "sg:city":"Deer Park",
    "sg:classifiers":[
        {
            "category":"Home & Garden",
            "subcategory":"Carpets & Floor Coverings",
            "type":"Retail Goods"
        }
    ],
    "sg:phone":"+61 3 9363 1880",
    "sg:postcode":"3023",
    "sg:province":"VIC",
    "sg:tags":[
        "tile",
        "wall"
    ],
    "wof:name":"Jacobsen Jorgen",
    "wof:placetype":"venue"
},
  "geometry": {"coordinates":[144.774857,-37.76955],"type":"Point"}
}