{
  "type": "Feature",
  "properties": {
    "addr:full":"26 Oliver St Lyneham ACT 2602",
    "addr:housenumber":"26",
    "addr:postcode":"2602",
    "addr:street":"Oliver St",
    "iso:country":"AU",
    "sg:address":"26 Oliver St",
    "sg:city":"Lyneham",
    "sg:classifiers":[
        {
            "category":"Education",
            "subcategory":"Special Training",
            "type":"Public Place"
        }
    ],
    "sg:phone":"+61 2 6257 1030",
    "sg:postcode":"2602",
    "sg:province":"ACT",
    "sg:tags":[
        "development"
    ],
    "wof:name":"Distance Learning Australia",
    "wof:placetype":"venue"
},
  "geometry": {"coordinates":[149.13197326700001,-35.2487983704],"type":"Point"}
}