{
  "type": "Feature",
  "properties": {
    "iso:country":"AU",
    "sg:address":"70 Meroo Rd",
    "sg:city":"Bomaderry",
    "sg:classifiers":[
        {
            "category":"Manufacturing",
            "subcategory":"Wood Products",
            "type":"Manufacturing & Wholesale Goods"
        }
    ],
    "sg:phone":"+61 2 4421 2935",
    "sg:postcode":"2541",
    "sg:province":"NSW",
    "sg:tags":[
        "pallet",
        "platform"
    ],
    "wof:name":"Box Built Pty Ltd",
    "wof:placetype":"venue"
},
  "geometry": {"coordinates":[150.60899352999999,-34.8348655701],"type":"Point"}
}