{
  "type": "Feature",
  "properties": {
    "addr:full":"Albert St Moree NSW 2400",
    "addr:postcode":"2400",
    "addr:street":"Albert St",
    "iso:country":"AU",
    "sg:address":"Albert St",
    "sg:city":"Moree",
    "sg:classifiers":[
        {
            "category":"Education",
            "subcategory":"School",
            "type":"Public Place"
        }
    ],
    "sg:phone":"+61 2 6752 1913",
    "sg:postcode":"2400",
    "sg:province":"NSW",
    "sg:tags":[
        "state",
        "-",
        "nsw"
    ],
    "wof:name":"Moree Primary School",
    "wof:placetype":"venue"
},
  "geometry": {"coordinates":[149.84201049800001,-29.4653892517],"type":"Point"}
}