{
  "type": "Feature",
  "properties": {
    "addr:full":"PO Box 684 MSC Torrens Park SA 5062",
    "addr:postcode":"5062",
    "iso:country":"AU",
    "sg:address":"PO Box 684",
    "sg:city":"MSC Torrens Park",
    "sg:classifiers":[
        {
            "category":"Shopping",
            "subcategory":"Crafts & Fabrics",
            "type":"Retail Goods"
        }
    ],
    "sg:phone":"+61 8 8271 6874",
    "sg:postcode":"5062",
    "sg:province":"SA",
    "sg:tags":[
        "wool",
        "classers"
    ],
    "wof:name":"Woolclassers&#039; Association Of Australia",
    "wof:placetype":"venue"
},
  "geometry": {"coordinates":[138.61331176799999,-34.9766387939],"type":"Point"}
}