{
  "type": "Feature",
  "properties": {
    "iso:country":"AU",
    "sg:address":"49 Victoria St",
    "sg:city":"Warragul",
    "sg:classifiers":[
        {
            "category":"Health Services",
            "subcategory":"Dentist",
            "type":"Services"
        }
    ],
    "sg:phone":"+61 3 5623 5588",
    "sg:postcode":"3820",
    "sg:province":"VIC",
    "wof:name":"Bishop Lindsay J Dr",
    "wof:placetype":"venue"
},
  "geometry": {"coordinates":[145.929947,-38.161152],"type":"Point"}
}