{
  "type": "Feature",
  "properties": {
    "addr:full":"55 Elgin St Gunnedah NSW 2380",
    "addr:housenumber":"55",
    "addr:postcode":"2380",
    "addr:street":"Elgin St",
    "iso:country":"AU",
    "sg:address":"55 Elgin St",
    "sg:city":"Gunnedah",
    "sg:classifiers":[
        {
            "category":"Real Estate",
            "subcategory":"Real Estate Agent",
            "type":"Services"
        }
    ],
    "sg:phone":"+61 2 6742 3274",
    "sg:postcode":"2380",
    "sg:province":"NSW",
    "wof:name":"Porters For Property Gunnedah",
    "wof:placetype":"venue"
},
  "geometry": {"coordinates":[150.25538635300001,-30.9789123535],"type":"Point"}
}