{
  "type": "Feature",
  "properties": {
    "iso:country":"AU",
    "sg:address":"44 Thomas St",
    "sg:city":"Cardiff",
    "sg:classifiers":[
        {
            "category":"Health Services",
            "subcategory":"Doctor",
            "type":"Services"
        }
    ],
    "sg:phone":"+61 2 4953 7155",
    "sg:postcode":"2285",
    "sg:province":"NSW",
    "sg:tags":[
        "medical",
        "practitioner"
    ],
    "wof:name":"Proietto Anthony",
    "wof:placetype":"venue"
},
  "geometry": {"coordinates":[151.660644531,-32.941696167],"type":"Point"}
}