{
  "type": "Feature",
  "properties": {
    "addr:full":"89 Hoare St Manunda QLD 4870",
    "addr:housenumber":"89",
    "addr:postcode":"4870",
    "addr:street":"Hoare St",
    "iso:country":"AU",
    "sg:address":"89 Hoare St",
    "sg:city":"Manunda",
    "sg:classifiers":[
        {
            "category":"Health Services",
            "subcategory":"Health Practitioner",
            "type":"Services"
        }
    ],
    "sg:phone":"+61 7 4053 7495",
    "sg:postcode":"4870",
    "sg:province":"QLD",
    "sg:tags":[
        "psychologist"
    ],
    "wof:name":"Cecilia Gilders",
    "wof:placetype":"venue"
},
  "geometry": {"coordinates":[145.77441406200001,-16.920633316],"type":"Point"}
}