{
  "type": "Feature",
  "properties": {
    "addr:full":"83 Isabella St Wingham NSW 2429",
    "addr:housenumber":"83",
    "addr:postcode":"2429",
    "addr:street":"Isabella St",
    "iso:country":"AU",
    "sg:address":"83 Isabella St",
    "sg:city":"Wingham",
    "sg:classifiers":[
        {
            "category":"Shopping",
            "subcategory":"Jewelry",
            "type":"Retail Goods"
        }
    ],
    "sg:phone":"+61 2 6553 4393",
    "sg:postcode":"2429",
    "sg:province":"NSW",
    "sg:tags":[
        "jeweller"
    ],
    "wof:name":"Allen Family Jewellers",
    "wof:placetype":"venue"
},
  "geometry": {"coordinates":[152.373749,-31.868809],"type":"Point"}
}