{
  "type": "Feature",
  "properties": {
    "addr:full":"U6/ 104 Norma Rd Booragoon WA 6154",
    "addr:housenumber":"104",
    "addr:postcode":"6154",
    "addr:street":"U6 /;Norma Rd",
    "iso:country":"AU",
    "sg:address":"U6/ 104 Norma Rd",
    "sg:city":"Booragoon",
    "sg:classifiers":[
        {
            "category":"Building & Trades",
            "subcategory":"Construction",
            "type":"Services"
        }
    ],
    "sg:phone":"+61 8 9330 8066",
    "sg:postcode":"6154",
    "sg:province":"WA",
    "sg:tags":[
        "industrial",
        "commercial",
        "air conditioning"
    ],
    "wof:name":"Airconditioning & Electrical Services",
    "wof:placetype":"venue"
},
  "geometry": {"coordinates":[115.82254,-32.045067],"type":"Point"}
}