{
  "type": "Feature",
  "properties": {
    "addr:full":"Level 3 159 Kent St Sydney NSW 2000",
    "addr:housenumber":"159",
    "addr:postcode":"2000",
    "addr:street":"Kent St",
    "iso:country":"AU",
    "sg:address":"Level 3 159 Kent St",
    "sg:city":"Sydney",
    "sg:classifiers":[
        {
            "category":"Professional",
            "subcategory":"Engineering",
            "type":"Services"
        }
    ],
    "sg:phone":"+61 417 080 363",
    "sg:postcode":"2000",
    "sg:province":"NSW",
    "sg:tags":[
        "engineer",
        "structural"
    ],
    "wof:name":"Northwood Pty Ltd",
    "wof:placetype":"venue"
},
  "geometry": {"coordinates":[151.20370483400001,-33.8622322083],"type":"Point"}
}