{
  "type": "Feature",
  "properties": {
    "addr:full":"102 Erskineville Rd Erskineville NSW 2043",
    "addr:housenumber":"102",
    "addr:postcode":"2043",
    "addr:street":"Erskineville Rd",
    "iso:country":"AU",
    "sg:address":"102 Erskineville Rd",
    "sg:city":"Erskineville",
    "sg:classifiers":[
        {
            "category":"Travel",
            "subcategory":"Hotels & Motels",
            "type":"Entertainment"
        }
    ],
    "sg:phone":"+61 2 9565 1608",
    "sg:postcode":"2043",
    "sg:province":"NSW",
    "sg:tags":[
        "accommodation"
    ],
    "wof:name":"Erskineville Hotel",
    "wof:placetype":"venue"
},
  "geometry": {"coordinates":[151.18345600000001,-33.899277],"type":"Point"}
}