{
  "type": "Feature",
  "properties": {
    "addr:full":"50 James St Burleigh Heads QLD 4220",
    "addr:housenumber":"50",
    "addr:postcode":"4220",
    "addr:street":"James St",
    "iso:country":"AU",
    "sg:address":"50 James St",
    "sg:city":"Burleigh Heads",
    "sg:classifiers":[
        {
            "category":"Real Estate",
            "subcategory":"Surveying",
            "type":"Services"
        }
    ],
    "sg:phone":"+61 7 5535 6041",
    "sg:postcode":"4220",
    "sg:province":"QLD",
    "sg:tags":[
        "surveyor",
        "land"
    ],
    "wof:name":"Hanger & Kelly Pty Ltd",
    "wof:placetype":"venue"
},
  "geometry": {"coordinates":[153.449676514,-28.0892753601],"type":"Point"}
}