{
  "type": "Feature",
  "properties": {
    "addr:full":"286 Cowper St Warrawong NSW 2502",
    "addr:housenumber":"286",
    "addr:postcode":"2502",
    "addr:street":"Cowper St",
    "iso:country":"AU",
    "sg:address":"286 Cowper St",
    "sg:city":"Warrawong",
    "sg:classifiers":[
        {
            "category":"Health Services",
            "subcategory":"Doctor",
            "type":"Services"
        }
    ],
    "sg:phone":"+61 2 4274 6313",
    "sg:postcode":"2502",
    "sg:province":"NSW",
    "sg:tags":[
        "medical",
        "practitioner"
    ],
    "wof:name":"Lakhany Zak",
    "wof:placetype":"venue"
},
  "geometry": {"coordinates":[150.88414,-34.485542],"type":"Point"}
}