{
  "type": "Feature",
  "properties": {
    "iso:country":"AU",
    "sg:address":"35 Battunga Rd",
    "sg:city":"Meadows",
    "sg:classifiers":[
        {
            "category":"Health Services",
            "subcategory":"Doctor",
            "type":"Services"
        }
    ],
    "sg:phone":"+61 8 8388 3344",
    "sg:postcode":"5201",
    "sg:province":"SA",
    "sg:tags":[
        "medical",
        "practitioner"
    ],
    "wof:name":"Meadows Surgery",
    "wof:placetype":"venue"
},
  "geometry": {"coordinates":[138.75608825699999,-35.177230835],"type":"Point"}
}