{
  "type": "Feature",
  "properties": {
    "iso:country":"AU",
    "sg:address":"PO Box 680",
    "sg:city":"Virginia",
    "sg:classifiers":[
        {
            "category":"Shopping",
            "subcategory":"Party Supplies",
            "type":"Retail Goods"
        }
    ],
    "sg:phone":"+61 8 8380 8633",
    "sg:postcode":"5120",
    "sg:province":"SA",
    "wof:name":"SA Party Hire",
    "wof:placetype":"venue"
},
  "geometry": {"coordinates":[138.56080627399999,-34.6675415039],"type":"Point"}
}