{
  "type": "Feature",
  "properties": {
    "iso:country":"AU",
    "sg:address":"Unit 3, 348 Melton Rd",
    "sg:city":"Northgate",
    "sg:classifiers":[
        {
            "category":"Autos & Motor Vehicles",
            "subcategory":"Auto Supplies",
            "type":"Retail Goods"
        }
    ],
    "sg:phone":"+61 7 3266 3852",
    "sg:postcode":"4013",
    "sg:province":"QLD",
    "sg:tags":[
        "part",
        "cycles",
        "accessory"
    ],
    "wof:name":"Poppa Wheelies Hog Shop",
    "wof:placetype":"venue"
},
  "geometry": {"coordinates":[153.07090759299999,-27.3935451508],"type":"Point"}
}