{
  "type": "Feature",
  "properties": {
    "iso:country":"AU",
    "sg:address":"21 Barton Rd",
    "sg:city":"Hawthorne",
    "sg:classifiers":[
        {
            "category":"Building & Trades",
            "subcategory":"Construction",
            "type":"Services"
        }
    ],
    "sg:phone":"+61 7 3399 5278",
    "sg:postcode":"4171",
    "sg:province":"QLD",
    "sg:tags":[
        "contractor"
    ],
    "wof:name":"Innovare Pty Ltd",
    "wof:placetype":"venue"
},
  "geometry": {"coordinates":[153.062225342,-27.4593582153],"type":"Point"}
}