{
  "type": "Feature",
  "properties": {
    "addr:full":"PO Box 3070 North Rockhampton QLD 4701",
    "addr:postcode":"4701",
    "addr:street":"North",
    "iso:country":"AU",
    "sg:address":"PO Box 3070",
    "sg:city":"North Rockhampton",
    "sg:classifiers":[
        {
            "category":"Building & Trades",
            "subcategory":"Construction",
            "type":"Services"
        }
    ],
    "sg:phone":"+61 7 4934 4688",
    "sg:postcode":"4701",
    "sg:province":"QLD",
    "sg:tags":[
        "renovation",
        "alterations",
        "extension",
        "contractor"
    ],
    "wof:name":"Bruce Robson Builders",
    "wof:placetype":"venue"
},
  "geometry": {"coordinates":[150.54896545400001,-23.3510398865],"type":"Point"}
}