{
  "type": "Feature",
  "properties": {
    "addr:full":"19 Ricketts Rd Mt Waverley VIC 3149",
    "addr:housenumber":"19",
    "addr:postcode":"3149",
    "addr:street":"Ricketts Rd",
    "iso:country":"AU",
    "sg:address":"19 Ricketts Rd",
    "sg:city":"Mt Waverley",
    "sg:classifiers":[
        {
            "category":"Wholesale",
            "subcategory":"Machinery & Supplies",
            "type":"Manufacturing & Wholesale Goods"
        }
    ],
    "sg:phone":"+61 3 9562 8800",
    "sg:postcode":"3149",
    "sg:province":"VIC",
    "sg:tags":[
        "equipment",
        "hydraulic"
    ],
    "wof:name":"PT Hydraulics Australia Pty Ltd",
    "wof:placetype":"venue"
},
  "geometry": {"coordinates":[145.13594055199999,-37.8946990967],"type":"Point"}
}