{
  "type": "Feature",
  "properties": {
    "addr:full":"177 Brisbane St Beaudesert QLD 4285",
    "addr:housenumber":"177",
    "addr:postcode":"4285",
    "addr:street":"Brisbane St",
    "iso:country":"AU",
    "sg:address":"177 Brisbane St",
    "sg:city":"Beaudesert",
    "sg:classifiers":[
        {
            "category":"Retail",
            "subcategory":"Funeral Services",
            "type":"Services"
        }
    ],
    "sg:phone":"+61 7 5541 2511",
    "sg:postcode":"4285",
    "sg:province":"QLD",
    "sg:tags":[
        "director"
    ],
    "sg:website":"http://www.beaudesertfunerals.com.au",
    "wof:name":"Beaudesert Funerals",
    "wof:placetype":"venue"
},
  "geometry": {"coordinates":[152.99482699999999,-27.980932],"type":"Point"}
}