{
  "type": "Feature",
  "properties": {
    "addr:full":"208 Sterling Drv Keilor East VIC 3033",
    "addr:housenumber":"208",
    "addr:postcode":"3033",
    "addr:street":"Sterling Drv",
    "iso:country":"AU",
    "sg:address":"208 Sterling Drv",
    "sg:city":"Keilor East",
    "sg:classifiers":[
        {
            "category":"Professional",
            "subcategory":"Art Services",
            "type":"Services"
        }
    ],
    "sg:phone":"+61 3 9337 3362",
    "sg:postcode":"3033",
    "sg:province":"VIC",
    "sg:tags":[
        "decorator",
        "painter"
    ],
    "wof:name":"E & D Painters (Vic) Pty Ltd",
    "wof:placetype":"venue"
},
  "geometry": {"coordinates":[144.84896900000001,-37.746792],"type":"Point"}
}