{
  "type": "Feature",
  "properties": {
    "iso:country":"AU",
    "sg:address":"35 Old Mica Creek Rd",
    "sg:city":"Mt Isa",
    "sg:classifiers":[
        {
            "category":"Utilities",
            "subcategory":"Electric",
            "type":"Services"
        }
    ],
    "sg:phone":"+61 7 4743 6255",
    "sg:postcode":"4825",
    "sg:province":"QLD",
    "sg:tags":[
        "electrical",
        "contractor"
    ],
    "wof:name":"Norris Stork",
    "wof:placetype":"venue"
},
  "geometry": {"coordinates":[139.48968500000001,-20.750654],"type":"Point"}
}