{
  "type": "Feature",
  "properties": {
    "addr:full":"Kays Rd McLaren Vale SA 5171",
    "addr:postcode":"5171",
    "addr:street":"Kays Rd",
    "iso:country":"AU",
    "sg:address":"Kays Rd",
    "sg:city":"McLaren Vale",
    "sg:classifiers":[
        {
            "category":"Shopping",
            "subcategory":"Beauty & Cosmetics",
            "type":"Retail Goods"
        }
    ],
    "sg:phone":"+61 8 8323 7523",
    "sg:postcode":"5171",
    "sg:province":"SA",
    "wof:name":"McLaren Vale Lavender",
    "wof:placetype":"venue"
},
  "geometry": {"coordinates":[138.557174683,-35.1871948242],"type":"Point"}
}