{
  "type": "Feature",
  "properties": {
    "addr:full":"14 Ribbon Crt Frankston North VIC 3200",
    "addr:housenumber":"14",
    "addr:postcode":"3200",
    "addr:street":"Ribbon Crt",
    "iso:country":"AU",
    "sg:address":"14 Ribbon Crt",
    "sg:city":"Frankston North",
    "sg:classifiers":[
        {
            "category":"Health Services",
            "subcategory":"Health Practitioner",
            "type":"Services"
        }
    ],
    "sg:phone":"+61 3 9776 8991",
    "sg:postcode":"3200",
    "sg:province":"VIC",
    "sg:tags":[
        "hypnotherapy"
    ],
    "wof:name":"Australian College of Clinical Hypnotherapy The",
    "wof:placetype":"venue"
},
  "geometry": {"coordinates":[145.15583799999999,-38.123211],"type":"Point"}
}