{
  "type": "Feature",
  "properties": {
    "addr:full":"18 Tupia Pl Kings Langley NSW 2147",
    "addr:housenumber":"18",
    "addr:postcode":"2147",
    "addr:street":"Tupia Pl",
    "iso:country":"AU",
    "sg:address":"18 Tupia Pl",
    "sg:city":"Kings Langley",
    "sg:classifiers":[
        {
            "category":"Building & Trades",
            "subcategory":"Construction",
            "type":"Services"
        }
    ],
    "sg:phone":"+61 2 9624 8051",
    "sg:postcode":"2147",
    "sg:province":"NSW",
    "sg:tags":[
        "contractor"
    ],
    "wof:name":"Dereson Constructions Pty Ltd",
    "wof:placetype":"venue"
},
  "geometry": {"coordinates":[150.937255859,-33.7476997375],"type":"Point"}
}