{
  "type": "Feature",
  "properties": {
    "addr:full":"45 Flanders St Salisbury QLD 4107",
    "addr:housenumber":"45",
    "addr:postcode":"4107",
    "addr:street":"Flanders St",
    "iso:country":"AU",
    "sg:address":"45 Flanders St",
    "sg:city":"Salisbury",
    "sg:classifiers":[
        {
            "category":"Retail",
            "subcategory":"Auto Repair",
            "type":"Services"
        }
    ],
    "sg:phone":"+61 7 3277 6833",
    "sg:postcode":"4107",
    "sg:province":"QLD",
    "sg:tags":[
        "testing",
        "inspection",
        "motor",
        "vehicle"
    ],
    "wof:name":"Jomaine Motors",
    "wof:placetype":"venue"
},
  "geometry": {"coordinates":[153.03761291500001,-27.5421180725],"type":"Point"}
}