{
  "type": "Feature",
  "properties": {
    "addr:full":"304 Gibbs Rd Banjup WA 6164",
    "addr:housenumber":"304",
    "addr:postcode":"6164",
    "addr:street":"Gibbs Rd",
    "iso:country":"AU",
    "sg:address":"304 Gibbs Rd",
    "sg:city":"Banjup",
    "sg:classifiers":[
        {
            "category":"Building & Trades",
            "subcategory":"Cleaning & Sanitation",
            "type":"Services"
        }
    ],
    "sg:phone":"+61 400 999 133",
    "sg:postcode":"6164",
    "sg:province":"WA",
    "sg:tags":[
        "chemical",
        "pressure",
        "steam",
        "contractor"
    ],
    "wof:name":"Kleen Seal",
    "wof:placetype":"venue"
},
  "geometry": {"coordinates":[115.88082900000001,-32.157295],"type":"Point"}
}