{
  "type": "Feature",
  "properties": {
    "addr:full":"PO Box 565 Edmonton QLD 4869",
    "addr:postcode":"4869",
    "iso:country":"AU",
    "sg:address":"PO Box 565",
    "sg:city":"Edmonton",
    "sg:classifiers":[
        {
            "category":"Real Estate",
            "subcategory":"Real Estate Agent",
            "type":"Services"
        }
    ],
    "sg:phone":"+61 438 771 162",
    "sg:postcode":"4869",
    "sg:province":"QLD",
    "sg:tags":[
        "handyman's",
        "equipment",
        "hire",
        "builders",
        "contractor"
    ],
    "wof:name":"Brian Tuni Truck & Bobcat Hire",
    "wof:placetype":"venue"
},
  "geometry": {"coordinates":[145.734008789,-17.0219402313],"type":"Point"}
}