{
  "type": "Feature",
  "properties": {
    "iso:country":"AU",
    "sg:address":"1342 Grand Junction Rd",
    "sg:city":"Hope Valley",
    "sg:classifiers":[
        {
            "category":"Commercial Area",
            "type":"Public Place"
        }
    ],
    "sg:phone":"+61 8 8264 3804",
    "sg:postcode":"5090",
    "sg:province":"SA",
    "sg:tags":[
        "heavy",
        "carrier"
    ],
    "wof:name":"Schwartz D R&C J",
    "wof:placetype":"venue"
},
  "geometry": {"coordinates":[138.713348389,-34.840461731],"type":"Point"}
}