{
  "type": "Feature",
  "properties": {
    "addr:full":"3 Lang Crt Happy Valley SA 5159",
    "addr:housenumber":"3",
    "addr:postcode":"5159",
    "addr:street":"Lang Crt",
    "iso:country":"AU",
    "sg:address":"3 Lang Crt",
    "sg:city":"Happy Valley",
    "sg:classifiers":[
        {
            "category":"Building & Trades",
            "subcategory":"Construction",
            "type":"Services"
        }
    ],
    "sg:phone":"+61 8 8381 6022",
    "sg:postcode":"5159",
    "sg:province":"SA",
    "sg:tags":[
        "contractor"
    ],
    "wof:name":"Happy Valley Homes & Improvements",
    "wof:placetype":"venue"
},
  "geometry": {"coordinates":[138.58714294399999,-35.0842971802],"type":"Point"}
}