{
  "type": "Feature",
  "properties": {
    "iso:country":"AU",
    "sg:address":"19 Sturt Ave",
    "sg:city":"Narrabundah",
    "sg:classifiers":[
        {
            "category":"Professional",
            "subcategory":"Employment Agencies",
            "type":"Services"
        }
    ],
    "sg:phone":"+61 2 6295 2100",
    "sg:postcode":"2604",
    "sg:province":"ACT",
    "sg:tags":[
        "model"
    ],
    "wof:name":"Star Modelling Agency",
    "wof:placetype":"venue"
},
  "geometry": {"coordinates":[149.149093628,-35.3269271851],"type":"Point"}
}