{
  "type": "Feature",
  "properties": {
    "addr:full":"12 Williamson Rd Maribyrnong VIC 3032",
    "addr:housenumber":"12",
    "addr:postcode":"3032",
    "addr:street":"Williamson Rd",
    "iso:country":"AU",
    "sg:address":"12 Williamson Rd",
    "sg:city":"Maribyrnong",
    "sg:classifiers":[
        {
            "category":"Retail",
            "subcategory":"Auto Repair",
            "type":"Services"
        }
    ],
    "sg:phone":"+61 3 9317 8000",
    "sg:postcode":"3032",
    "sg:province":"VIC",
    "sg:tags":[
        "testing",
        "inspection",
        "motor",
        "vehicle"
    ],
    "wof:name":"One Star Motors Pty Ltd",
    "wof:placetype":"venue"
},
  "geometry": {"coordinates":[144.883804,-37.775154],"type":"Point"}
}