{
  "type": "Feature",
  "properties": {
    "addr:full":"1 Bruce St Greensborough VIC 3088",
    "addr:housenumber":"1",
    "addr:postcode":"3088",
    "addr:street":"Bruce St",
    "iso:country":"AU",
    "sg:address":"1 Bruce St",
    "sg:city":"Greensborough",
    "sg:classifiers":[
        {
            "category":"Health Services",
            "subcategory":"Health Practitioner",
            "type":"Services"
        }
    ],
    "sg:phone":"+61 3 9432 2500",
    "sg:postcode":"3088",
    "sg:province":"VIC",
    "sg:tags":[
        "physiotherapist"
    ],
    "wof:name":"Essential New Age Health Care",
    "wof:placetype":"venue"
},
  "geometry": {"coordinates":[145.11524963400001,-37.6967773438],"type":"Point"}
}