{
  "type": "Feature",
  "properties": {
    "iso:country":"AU",
    "sg:address":"109- 111 Northcorp Blv",
    "sg:city":"Broadmeadows",
    "sg:classifiers":[
        {
            "category":"Manufacturing",
            "subcategory":"Rubber & Plastics",
            "type":"Manufacturing & Wholesale Goods"
        }
    ],
    "sg:phone":"+61 3 9357 2366",
    "sg:postcode":"3047",
    "sg:province":"VIC",
    "sg:tags":[
        "wholesaler",
        "product",
        "mfrs"
    ],
    "sg:website":"http://www.ormistonrubber.com.au",
    "wof:name":"Ormiston Industrial Rubber",
    "wof:placetype":"venue"
},
  "geometry": {"coordinates":[144.949417114,-37.6808128357],"type":"Point"}
}