{
  "type": "Feature",
  "properties": {
    "iso:country":"AU",
    "sg:address":"28 Firetail Crt",
    "sg:city":"Morayfield",
    "sg:classifiers":[
        {
            "category":"Building & Trades",
            "subcategory":"Construction",
            "type":"Services"
        }
    ],
    "sg:phone":"+61 7 5498 7994",
    "sg:postcode":"4506",
    "sg:province":"QLD",
    "sg:tags":[
        "plasterboard",
        "plasterer",
        "fixer"
    ],
    "wof:name":"Project Plastering",
    "wof:placetype":"venue"
},
  "geometry": {"coordinates":[152.93556213400001,-27.1197853088],"type":"Point"}
}