{
  "type": "Feature",
  "properties": {
    "iso:country":"AU",
    "sg:address":"2 Stockton Ave",
    "sg:city":"Moorebank",
    "sg:classifiers":[
        {
            "category":"Health Services",
            "subcategory":"Doctor",
            "type":"Services"
        }
    ],
    "sg:phone":"+61 2 9822 2780",
    "sg:postcode":"2170",
    "sg:province":"NSW",
    "sg:tags":[
        "podiatrist"
    ],
    "wof:name":"Boudville Paul",
    "wof:placetype":"venue"
},
  "geometry": {"coordinates":[150.94830322300001,-33.9294013977],"type":"Point"}
}