{
  "type": "Feature",
  "properties": {
    "addr:full":"7 Birkett Pl South Geelong VIC 3220",
    "addr:housenumber":"7",
    "addr:postcode":"3220",
    "addr:street":"Birkett Pl",
    "iso:country":"AU",
    "sg:address":"7 Birkett Pl",
    "sg:city":"South Geelong",
    "sg:classifiers":[
        {
            "category":"Building & Trades",
            "subcategory":"Construction",
            "type":"Services"
        }
    ],
    "sg:phone":"+61 3 5248 7799",
    "sg:postcode":"3220",
    "sg:province":"VIC",
    "sg:tags":[
        "window",
        "timber"
    ],
    "sg:website":"http://www.mouldright.com.au",
    "wof:name":"Mouldright Joinery",
    "wof:placetype":"venue"
},
  "geometry": {"coordinates":[144.36634799999999,-38.173279],"type":"Point"}
}