{
  "type": "Feature",
  "properties": {
    "iso:country":"AU",
    "sg:address":"Great Northern Hwy",
    "sg:city":"Bindoon",
    "sg:classifiers":[
        {
            "category":"Building & Trades",
            "subcategory":"Construction",
            "type":"Services"
        }
    ],
    "sg:phone":"+61 8 9576 1066",
    "sg:postcode":"6502",
    "sg:province":"WA",
    "sg:tags":[
        "earth",
        "excavating",
        "moving",
        "contractor"
    ],
    "wof:name":"Bindoon Agencies Pty Ltd",
    "wof:placetype":"venue"
},
  "geometry": {"coordinates":[116.09580200000001,-31.384584],"type":"Point"}
}