{
  "type": "Feature",
  "properties": {
    "iso:country":"AU",
    "sg:address":"87 McDonald Street",
    "sg:city":"Erskineville",
    "sg:classifiers":[
        {
            "category":"Arts & Performance",
            "subcategory":"Theater",
            "type":"Entertainment"
        }
    ],
    "sg:phone":"+61 2 9550 3459",
    "sg:postcode":"2043",
    "sg:province":"NSW",
    "sg:tags":[
        "theatrical",
        "supply"
    ],
    "wof:name":"Megadeck",
    "wof:placetype":"venue"
},
  "geometry": {"coordinates":[151.185593,-33.90414],"type":"Point"}
}