{
  "type": "Feature",
  "properties": {
    "iso:country":"AU",
    "sg:address":"Lot 5 Hunter Rd",
    "sg:city":"Healesville",
    "sg:classifiers":[
        {
            "category":"Manufacturing",
            "subcategory":"Motor Vehicles & Parts",
            "type":"Manufacturing & Wholesale Goods"
        }
    ],
    "sg:phone":"+61 3 5962 4871",
    "sg:postcode":"3777",
    "sg:province":"VIC",
    "sg:tags":[
        "die",
        "casting"
    ],
    "wof:name":"Trejay Pty Ltd",
    "wof:placetype":"venue"
},
  "geometry": {"coordinates":[145.507416,-37.65855],"type":"Point"}
}