{
  "type": "Feature",
  "properties": {
    "addr:full":"13 Beachview Ave Berrara NSW 2540",
    "addr:housenumber":"13",
    "addr:postcode":"2540",
    "addr:street":"Beachview Ave",
    "iso:country":"AU",
    "sg:address":"13 Beachview Ave",
    "sg:city":"Berrara",
    "sg:classifiers":[
        {
            "category":"Building & Trades",
            "subcategory":"Construction",
            "type":"Services"
        }
    ],
    "sg:phone":"+61 2 4441 2542",
    "sg:postcode":"2540",
    "sg:province":"NSW",
    "sg:tags":[
        "contractor"
    ],
    "wof:name":"Beachview Constructions Pty Ltd",
    "wof:placetype":"venue"
},
  "geometry": {"coordinates":[150.54699707,-35.2043762207],"type":"Point"}
}