{
  "type": "Feature",
  "properties": {
    "addr:full":"Shop 70 (Near Kmart) West Lakes Mall West Lakes SA 5021",
    "addr:housenumber":"shop 70",
    "addr:postcode":"5021",
    "addr:street":"Near Kmart",
    "iso:country":"AU",
    "sg:address":"Shop 70",
    "sg:city":"(Near Kmart) West Lakes Mall West Lakes",
    "sg:classifiers":[
        {
            "category":"Health Services",
            "subcategory":"Doctor",
            "type":"Services"
        }
    ],
    "sg:phone":"+61 8 8355 3577",
    "sg:postcode":"5021",
    "sg:province":"SA",
    "sg:tags":[
        "medical",
        "practitioner"
    ],
    "wof:name":"Permanent Make-Up",
    "wof:placetype":"venue"
},
  "geometry": {"coordinates":[138.48832702600001,-34.8726768494],"type":"Point"}
}