{
  "type": "Feature",
  "properties": {
    "iso:country":"AU",
    "sg:address":"Level 1/ 10 Cameron St",
    "sg:city":"Launceston",
    "sg:classifiers":[
        {
            "category":"Professional",
            "subcategory":"Management & Consulting",
            "type":"Services"
        }
    ],
    "sg:phone":"+61 3 6334 2970",
    "sg:postcode":"7250",
    "sg:province":"TAS",
    "sg:tags":[
        "consultant",
        "business"
    ],
    "wof:name":"Blue Carrara Pty Ltd",
    "wof:placetype":"venue"
},
  "geometry": {"coordinates":[147.14120483400001,-41.4338531494],"type":"Point"}
}