{
  "type": "Feature",
  "properties": {
    "addr:full":"Quadrant Building 1 William St Perth WA 6000",
    "addr:postcode":"6000",
    "addr:street":"William St",
    "iso:country":"AU",
    "sg:address":"Quadrant Building 1 William St",
    "sg:city":"Perth",
    "sg:classifiers":[
        {
            "category":"Military Area",
            "subcategory":"Armory",
            "type":"Public Place"
        }
    ],
    "sg:phone":"+61 1800 624 367",
    "sg:postcode":"6000",
    "sg:province":"WA",
    "sg:tags":[
        "teleconferencing"
    ],
    "wof:name":"Administrative Appeals Tribunal",
    "wof:placetype":"venue"
},
  "geometry": {"coordinates":[115.85584258999999,-31.9557971954],"type":"Point"}
}