{
  "type": "Feature",
  "properties": {
    "addr:full":"309 Kent St Sydney NSW 2000",
    "addr:housenumber":"309",
    "addr:postcode":"2000",
    "addr:street":"Kent St",
    "iso:country":"AU",
    "sg:address":"309 Kent St",
    "sg:city":"Sydney",
    "sg:classifiers":[
        {
            "category":"Professional",
            "subcategory":"Art Services",
            "type":"Services"
        }
    ],
    "sg:phone":"+61 2 9262 1404",
    "sg:postcode":"2000",
    "sg:province":"NSW",
    "sg:tags":[
        "graphic",
        "designer"
    ],
    "wof:name":"Imatec Pty Ltd",
    "wof:placetype":"venue"
},
  "geometry": {"coordinates":[151.20428466800001,-33.8672561646],"type":"Point"}
}