{
  "type": "Feature",
  "properties": {
    "iso:country":"AU",
    "sg:address":"13 Caulfield Drv",
    "sg:city":"North Haven",
    "sg:classifiers":[
        {
            "category":"Professional",
            "subcategory":"Printing & Photocopies",
            "type":"Services"
        }
    ],
    "sg:phone":"+61 8 8248 0593",
    "sg:postcode":"5018",
    "sg:province":"SA",
    "sg:tags":[
        "publishing",
        "desktop"
    ],
    "wof:name":"Fazakerley Rob",
    "wof:placetype":"venue"
},
  "geometry": {"coordinates":[138.497680664,-34.7853164673],"type":"Point"}
}