{
  "type": "Feature",
  "properties": {
    "iso:country":"AU",
    "sg:address":"Deuter Rd",
    "sg:city":"Burton",
    "sg:classifiers":[
        {
            "category":"Retail",
            "subcategory":"Auto Repair",
            "type":"Services"
        }
    ],
    "sg:phone":"+61 8 8280 6699",
    "sg:postcode":"5110",
    "sg:province":"SA",
    "sg:tags":[
        "beater",
        "painter",
        "panel"
    ],
    "wof:name":"Restorations Plus",
    "wof:placetype":"venue"
},
  "geometry": {"coordinates":[138.59193420400001,-34.7468032837],"type":"Point"}
}