{
  "type": "Feature",
  "properties": {
    "addr:full":"1 Breckenridge Crt Thornlands QLD 4164",
    "addr:housenumber":"1",
    "addr:postcode":"4164",
    "addr:street":"Breckenridge Crt",
    "iso:country":"AU",
    "sg:address":"1 Breckenridge Crt",
    "sg:city":"Thornlands",
    "sg:classifiers":[
        {
            "category":"Building & Trades",
            "subcategory":"Construction",
            "type":"Services"
        }
    ],
    "sg:phone":"+61 408 748 675",
    "sg:postcode":"4164",
    "sg:province":"QLD",
    "sg:tags":[
        "pool",
        "swimming"
    ],
    "wof:name":"J & L Pools & Paving",
    "wof:placetype":"venue"
},
  "geometry": {"coordinates":[153.26957702600001,-27.5770282745],"type":"Point"}
}