{
  "type": "Feature",
  "properties": {
    "addr:full":"Unit 1 7 Smith St Port Melbourne VIC 3207",
    "addr:housenumber":"7",
    "addr:postcode":"3207",
    "addr:street":"Smith St",
    "iso:country":"AU",
    "sg:address":"Unit 1 7 Smith St",
    "sg:city":"Port Melbourne",
    "sg:classifiers":[
        {
            "category":"Professional",
            "type":"Services"
        }
    ],
    "sg:phone":"+61 3 9314 5666",
    "sg:postcode":"3207",
    "sg:province":"VIC",
    "sg:tags":[
        "forwarding",
        "agent",
        "transport"
    ],
    "wof:name":"Distribution Solutions",
    "wof:placetype":"venue"
},
  "geometry": {"coordinates":[144.92211900000001,-37.834946],"type":"Point"}
}