{
  "type": "Feature",
  "properties": {
    "iso:country":"AU",
    "sg:address":"34 Bayview St",
    "sg:city":"Arncliffe",
    "sg:classifiers":[
        {
            "category":"Health Services",
            "subcategory":"Nursing And Care Facility",
            "type":"Services"
        }
    ],
    "sg:phone":"+61 2 9567 6375",
    "sg:postcode":"2205",
    "sg:province":"NSW",
    "sg:tags":[
        "home"
    ],
    "wof:name":"Alloa Nursing Home",
    "wof:placetype":"venue"
},
  "geometry": {"coordinates":[151.13827499999999,-33.942028],"type":"Point"}
}