{
  "type": "Feature",
  "properties": {
    "addr:full":"Level 4, 372 Albert St East Melbourne VIC 3002",
    "addr:housenumber":"372",
    "addr:postcode":"3002",
    "addr:street":"Albert St",
    "iso:country":"AU",
    "sg:address":"Level 4, 372 Albert St",
    "sg:city":"East Melbourne",
    "sg:classifiers":[
        {
            "category":"Personal",
            "subcategory":"Beauty Salon",
            "type":"Services"
        }
    ],
    "sg:phone":"+61 3 9486 9394",
    "sg:postcode":"3002",
    "sg:province":"VIC",
    "sg:tags":[
        "hair",
        "treatment",
        "replacement"
    ],
    "wof:name":"Sim Alan Dr",
    "wof:placetype":"venue"
},
  "geometry": {"coordinates":[144.978683472,-37.8096847534],"type":"Point"}
}