{
  "type": "Feature",
  "properties": {
    "iso:country":"AU",
    "sg:address":"17 North St",
    "sg:city":"Gatton",
    "sg:classifiers":[
        {
            "category":"Arts & Performance",
            "subcategory":"Art Gallery",
            "type":"Entertainment"
        }
    ],
    "sg:phone":"+61 7 5462 1252",
    "sg:postcode":"4343",
    "sg:province":"QLD",
    "wof:name":"Gatton Mercury Theatre",
    "wof:placetype":"venue"
},
  "geometry": {"coordinates":[152.27871704099999,-27.5575504303],"type":"Point"}
}