{
  "type": "Feature",
  "properties": {
    "iso:country":"AU",
    "sg:address":"Unit 8/ 195 Bannistern Rd",
    "sg:city":"Canning Vale",
    "sg:classifiers":[
        {
            "category":"Manufacturing",
            "subcategory":"Rubber & Plastics",
            "type":"Manufacturing & Wholesale Goods"
        }
    ],
    "sg:phone":"+61 8 9314 7292",
    "sg:postcode":"6155",
    "sg:province":"WA",
    "sg:tags":[
        "wholesaler",
        "product",
        "mfrs"
    ],
    "wof:name":"Eden Park",
    "wof:placetype":"venue"
},
  "geometry": {"coordinates":[115.904694,-32.061836],"type":"Point"}
}