{
  "type": "Feature",
  "properties": {
    "iso:country":"AU",
    "sg:address":"320 Sarahs Crs",
    "sg:city":"Wauchope",
    "sg:classifiers":[
        {
            "category":"Shopping",
            "subcategory":"Mobile Phones",
            "type":"Retail Goods"
        }
    ],
    "sg:phone":"+61 2 6585 1110",
    "sg:postcode":"2446",
    "sg:province":"NSW",
    "sg:tags":[
        "wholesaler",
        "mfrs",
        "electrical",
        "switchboard"
    ],
    "wof:name":"PHE Switchboards",
    "wof:placetype":"venue"
},
  "geometry": {"coordinates":[152.73371900000001,-31.45739],"type":"Point"}
}