{
  "type": "Feature",
  "properties": {
    "iso:country":"AU",
    "sg:address":"96 Florence St",
    "sg:city":"Wynnum Central",
    "sg:classifiers":[
        {
            "category":"Shopping",
            "subcategory":"Clothing, Apparel, & Fashions",
            "type":"Retail Goods"
        }
    ],
    "sg:phone":"+61 7 3396 8517",
    "sg:postcode":"4178",
    "sg:province":"QLD",
    "sg:tags":[
        "recycled",
        "clothing"
    ],
    "wof:name":"Association for Pre-School Education of Deaf Children Thrift Shop",
    "wof:placetype":"venue"
},
  "geometry": {"coordinates":[153.17276000999999,-27.4444541931],"type":"Point"}
}