{
  "type": "Feature",
  "properties": {
    "addr:full":"75 Bolton Rd Selby VIC 3159",
    "addr:housenumber":"75",
    "addr:postcode":"3159",
    "addr:street":"Bolton Rd",
    "iso:country":"AU",
    "sg:address":"75 Bolton Rd",
    "sg:city":"Selby",
    "sg:classifiers":[
        {
            "category":"Home & Garden",
            "subcategory":"Household Appliances",
            "type":"Retail Goods"
        }
    ],
    "sg:phone":"+61 3 9754 8486",
    "sg:postcode":"3159",
    "sg:province":"VIC",
    "sg:tags":[
        "equipment",
        "gas"
    ],
    "wof:name":"Cardinia Heating & Plumbing",
    "wof:placetype":"venue"
},
  "geometry": {"coordinates":[145.37440490700001,-37.9238739014],"type":"Point"}
}