{
  "type": "Feature",
  "properties": {
    "iso:country":"AU",
    "sg:address":"146- 150 Gordon St",
    "sg:city":"Port Macquarie",
    "sg:classifiers":[
        {
            "category":"Building & Trades",
            "subcategory":"Locksmith",
            "type":"Services"
        }
    ],
    "sg:phone":"+61 2 6583 3256",
    "sg:postcode":"2444",
    "sg:province":"NSW",
    "sg:tags":[
        "lock"
    ],
    "wof:name":"Port City Locksmith",
    "wof:placetype":"venue"
},
  "geometry": {"coordinates":[152.90104700000001,-31.434927],"type":"Point"}
}