{
  "type": "Feature",
  "properties": {
    "addr:full":"33 Bucknor Drv Deception Bay QLD 4508",
    "addr:housenumber":"33",
    "addr:postcode":"4508",
    "addr:street":"Bucknor Drv",
    "iso:country":"AU",
    "sg:address":"33 Bucknor Drv",
    "sg:city":"Deception Bay",
    "sg:classifiers":[
        {
            "category":"Building & Trades",
            "subcategory":"Construction",
            "type":"Services"
        }
    ],
    "sg:phone":"+61 7 3293 1553",
    "sg:postcode":"4508",
    "sg:province":"QLD",
    "sg:tags":[
        "repair",
        "maintenance",
        "contractor"
    ],
    "wof:name":"D R Palmer",
    "wof:placetype":"venue"
},
  "geometry": {"coordinates":[153.014129639,-27.184343338],"type":"Point"}
}