{
  "type": "Feature",
  "properties": {
    "addr:full":"88 Sanger St Corowa NSW 2646",
    "addr:housenumber":"88",
    "addr:postcode":"2646",
    "addr:street":"Sanger St",
    "iso:country":"AU",
    "sg:address":"88 Sanger St",
    "sg:city":"Corowa",
    "sg:classifiers":[
        {
            "category":"Communications",
            "subcategory":"News Services",
            "type":"Services"
        }
    ],
    "sg:phone":"+61 2 6033 3221",
    "sg:postcode":"2646",
    "sg:province":"NSW",
    "sg:tags":[
        "information",
        "tourist",
        "attractions"
    ],
    "wof:name":"Corowa Visitor Information Centre",
    "wof:placetype":"venue"
},
  "geometry": {"coordinates":[146.391357422,-35.9951553345],"type":"Point"}
}