{
  "type": "Feature",
  "properties": {
    "iso:country":"AU",
    "sg:address":"228 Franklin St",
    "sg:city":"Adelaide",
    "sg:classifiers":[
        {
            "category":"Shopping",
            "subcategory":"Stationery & Office Supplies",
            "type":"Retail Goods"
        }
    ],
    "sg:phone":"+61 8 8212 2922",
    "sg:postcode":"5000",
    "sg:province":"SA",
    "sg:tags":[
        "equipment",
        "facsimile"
    ],
    "wof:name":"Optus World Adelaide",
    "wof:placetype":"venue"
},
  "geometry": {"coordinates":[138.590698242,-34.9274902344],"type":"Point"}
}