{
  "type": "Feature",
  "properties": {
    "addr:full":"Unit 2/ 46 Collingwood St Osborne Park WA 6017",
    "addr:housenumber":"46",
    "addr:postcode":"6017",
    "addr:street":"Collingwood St",
    "iso:country":"AU",
    "sg:address":"Unit 2/ 46 Collingwood St",
    "sg:city":"Osborne Park",
    "sg:classifiers":[
        {
            "category":"Professional",
            "type":"Services"
        }
    ],
    "sg:phone":"+61 8 9383 5670",
    "sg:postcode":"6017",
    "sg:province":"WA",
    "sg:tags":[
        "quality",
        "assurance"
    ],
    "wof:name":"Western Power Metering Services",
    "wof:placetype":"venue"
},
  "geometry": {"coordinates":[115.81523132300001,-31.9029064178],"type":"Point"}
}