{
  "type": "Feature",
  "properties": {
    "iso:country":"AU",
    "sg:address":"Lot 84 Roxburgh Crs",
    "sg:city":"Stanhope Gardens",
    "sg:classifiers":[
        {
            "category":"Building & Trades",
            "subcategory":"Construction",
            "type":"Services"
        }
    ],
    "sg:phone":"+61 2 8824 3543",
    "sg:postcode":"2768",
    "sg:province":"NSW",
    "sg:tags":[
        "contractor"
    ],
    "wof:name":"Mervac Homes Newbury Display Village",
    "wof:placetype":"venue"
},
  "geometry": {"coordinates":[150.92074600000001,-33.71899],"type":"Point"}
}