{
  "type": "Feature",
  "properties": {
    "addr:full":"74 Southern River Rd Gosnells WA 6110",
    "addr:housenumber":"74",
    "addr:postcode":"6110",
    "addr:street":"Southern River Rd",
    "iso:country":"AU",
    "sg:address":"74 Southern River Rd",
    "sg:city":"Gosnells",
    "sg:classifiers":[
        {
            "category":"Professional",
            "subcategory":"Computer Services",
            "type":"Services"
        }
    ],
    "sg:phone":"+61 8 9490 2021",
    "sg:postcode":"6110",
    "sg:province":"WA",
    "sg:tags":[
        "repairs",
        "upgrade",
        "equipment"
    ],
    "wof:name":"Greg's Computers",
    "wof:placetype":"venue"
},
  "geometry": {"coordinates":[115.982757568,-32.0850257874],"type":"Point"}
}