{
  "type": "Feature",
  "properties": {
    "iso:country":"AU",
    "sg:address":"41 Fullerton St",
    "sg:city":"Stockton",
    "sg:classifiers":[
        {
            "category":"Autos & Motor Vehicles",
            "subcategory":"Fuel & Gas Station",
            "type":"Retail Goods"
        }
    ],
    "sg:phone":"+61 2 4928 1170",
    "sg:postcode":"2295",
    "sg:province":"NSW",
    "wof:name":"Linstrom N",
    "wof:placetype":"venue"
},
  "geometry": {"coordinates":[151.78027343799999,-32.9143714905],"type":"Point"}
}