{
  "type": "Feature",
  "properties": {
    "iso:country":"AU",
    "sg:address":"49 Albion St",
    "sg:city":"Warwick",
    "sg:classifiers":[
        {
            "category":"Landmark",
            "subcategory":"Tourist Information",
            "type":"Public Place"
        }
    ],
    "sg:phone":"+61 7 4661 3122",
    "sg:postcode":"4370",
    "sg:province":"QLD",
    "sg:tags":[
        "bureau"
    ],
    "wof:name":"Southern Downs Tourist Association",
    "wof:placetype":"venue"
},
  "geometry": {"coordinates":[152.035430908,-28.2147102356],"type":"Point"}
}