{
  "type": "Feature",
  "properties": {
    "iso:country":"AU",
    "sg:address":"456 South Rd",
    "sg:city":"Marleston",
    "sg:classifiers":[
        {
            "category":"Shopping",
            "subcategory":"Optical Goods",
            "type":"Retail Goods"
        }
    ],
    "sg:phone":"+61 8 8351 4755",
    "sg:postcode":"5033",
    "sg:province":"SA",
    "sg:tags":[
        "supply"
    ],
    "wof:name":"Younger Optics Australia Pty ltd",
    "wof:placetype":"venue"
},
  "geometry": {"coordinates":[138.57110595699999,-34.9454345703],"type":"Point"}
}