{
  "type": "Feature",
  "properties": {
    "iso:country":"AU",
    "sg:address":"Cnr Great North & Lyons Rds",
    "sg:city":"Five Dock",
    "sg:classifiers":[
        {
            "category":"Autos & Motor Vehicles",
            "subcategory":"Auto Supplies",
            "type":"Retail Goods"
        }
    ],
    "sg:phone":"+61 2 9712 5074",
    "sg:postcode":"2046",
    "sg:province":"NSW",
    "sg:tags":[
        "battery",
        "automotive"
    ],
    "wof:name":"Five Dock Batteries",
    "wof:placetype":"venue"
},
  "geometry": {"coordinates":[151.12872300000001,-33.871029],"type":"Point"}
}