{
  "type": "Feature",
  "properties": {
    "addr:full":"Unit 17/ 202 McCormack St Manunda QLD 4870",
    "addr:housenumber":"/ 202",
    "addr:postcode":"4870",
    "addr:street":"Mccormack St",
    "iso:country":"AU",
    "sg:address":"Unit 17/ 202 McCormack St",
    "sg:city":"Manunda",
    "sg:classifiers":[
        {
            "category":"Building & Trades",
            "subcategory":"Construction",
            "type":"Services"
        }
    ],
    "sg:phone":"+61 7 4053 5853",
    "sg:postcode":"4870",
    "sg:province":"QLD",
    "sg:tags":[
        "welding"
    ],
    "wof:name":"All Aluminium Welding",
    "wof:placetype":"venue"
},
  "geometry": {"coordinates":[145.74517822300001,-16.916469574],"type":"Point"}
}