{
  "type": "Feature",
  "properties": {
    "iso:country":"AU",
    "sg:address":"Suite 1, 197",
    "sg:city":"Wickham Tce Brisbane",
    "sg:classifiers":[
        {
            "category":"Health Services",
            "subcategory":"Doctor",
            "type":"Services"
        }
    ],
    "sg:phone":"+61 7 3832 6361",
    "sg:postcode":"4000",
    "sg:province":"QLD",
    "sg:tags":[
        "medical",
        "practitioner"
    ],
    "wof:name":"Rejuvenation Clinics",
    "wof:placetype":"venue"
},
  "geometry": {"coordinates":[153.02340698200001,-27.4655208588],"type":"Point"}
}