{
  "type": "Feature",
  "properties": {
    "addr:full":"Factory 2 22 Redland Drv Mitcham VIC 3132",
    "addr:housenumber":"22",
    "addr:postcode":"3132",
    "addr:street":"Redland Drv",
    "iso:country":"AU",
    "sg:address":"Factory 2 22 Redland Drv",
    "sg:city":"Mitcham",
    "sg:classifiers":[
        {
            "category":"Shopping",
            "subcategory":"Pets & Pet Supplies",
            "type":"Retail Goods"
        }
    ],
    "sg:phone":"+61 3 9874 8777",
    "sg:postcode":"3132",
    "sg:province":"VIC",
    "sg:tags":[
        "dog"
    ],
    "wof:name":"Pet Network",
    "wof:placetype":"venue"
},
  "geometry": {"coordinates":[145.19015502900001,-37.8301277161],"type":"Point"}
}