{
  "type": "Feature",
  "properties": {
    "iso:country":"AU",
    "sg:address":"PO Box 38",
    "sg:city":"Malmsbury",
    "sg:classifiers":[
        {
            "category":"Professional",
            "subcategory":"Accounting & Tax Preparation",
            "type":"Services"
        }
    ],
    "sg:phone":"+61 3 5423 9374",
    "sg:postcode":"3446",
    "sg:province":"VIC",
    "sg:tags":[
        "bookkeeping"
    ],
    "wof:name":"Goodwin",
    "wof:placetype":"venue"
},
  "geometry": {"coordinates":[144.39096069300001,-37.189540863],"type":"Point"}
}