{
  "type": "Feature",
  "properties": {
    "iso:country":"AU",
    "sg:address":"15 Econo Pl",
    "sg:city":"Silverdale",
    "sg:classifiers":[
        {
            "category":"Utilities",
            "subcategory":"Sewage",
            "type":"Services"
        }
    ],
    "sg:phone":"+61 1800 808 135",
    "sg:postcode":"2752",
    "sg:province":"NSW",
    "sg:tags":[
        "water",
        "waste",
        "treatment"
    ],
    "wof:name":"Econocycle",
    "wof:placetype":"venue"
},
  "geometry": {"coordinates":[150.614044189,-33.8925437927],"type":"Point"}
}