{
  "type": "Feature",
  "properties": {
    "addr:full":"22/ 22 Northumberland Rd Caringbah NSW 2229",
    "addr:housenumber":"22 / 22",
    "addr:postcode":"2229",
    "addr:street":"Northumberland Rd",
    "iso:country":"AU",
    "sg:address":"22/ 22 Northumberland Rd",
    "sg:city":"Caringbah",
    "sg:classifiers":[
        {
            "category":"Home & Garden",
            "subcategory":"Hardware",
            "type":"Retail Goods"
        }
    ],
    "sg:phone":"+61 2 9526 6358",
    "sg:postcode":"2229",
    "sg:province":"NSW",
    "sg:tags":[
        "compressor",
        "air"
    ],
    "wof:name":"Link Rich Pty Ltd",
    "wof:placetype":"venue"
},
  "geometry": {"coordinates":[151.13189697300001,-34.0298461914],"type":"Point"}
}