{
  "type": "Feature",
  "properties": {
    "addr:full":"84 Bowen Rd Townsville QLD 4810",
    "addr:housenumber":"84",
    "addr:postcode":"4810",
    "addr:street":"Bowen Rd",
    "iso:country":"AU",
    "sg:address":"84 Bowen Rd",
    "sg:city":"Townsville",
    "sg:classifiers":[
        {
            "category":"Health Services",
            "subcategory":"Podiatrist",
            "type":"Services"
        }
    ],
    "sg:phone":"+61 7 4779 1570",
    "sg:postcode":"4810",
    "sg:province":"QLD",
    "sg:tags":[
        "cap",
        "hat",
        "renovation",
        "retail"
    ],
    "wof:name":"Saddleworld",
    "wof:placetype":"venue"
},
  "geometry": {"coordinates":[146.799713,-19.299601],"type":"Point"}
}