{
  "type": "Feature",
  "properties": {
    "addr:full":"17 Allara Ave Turramurra NSW 2074",
    "addr:housenumber":"17",
    "addr:postcode":"2074",
    "addr:street":"Allara Ave",
    "iso:country":"AU",
    "sg:address":"17 Allara Ave",
    "sg:city":"Turramurra",
    "sg:classifiers":[
        {
            "category":"Building & Trades",
            "subcategory":"Construction",
            "type":"Services"
        }
    ],
    "sg:phone":"+61 2 9488 7636",
    "sg:postcode":"2074",
    "sg:province":"NSW",
    "sg:tags":[
        "contractor"
    ],
    "wof:name":"Quika-Floor Pty Ltd",
    "wof:placetype":"venue"
},
  "geometry": {"coordinates":[151.14895629899999,-33.7163848877],"type":"Point"}
}