{
  "type": "Feature",
  "properties": {
    "addr:full":"Ste3/ 262 Macquarie St Liverpool NSW 2170",
    "addr:housenumber":"262",
    "addr:postcode":"2170",
    "addr:street":"Macquarie St",
    "iso:country":"AU",
    "sg:address":"Ste3/ 262 Macquarie St",
    "sg:city":"Liverpool",
    "sg:classifiers":[
        {
            "category":"Professional",
            "subcategory":"Accounting & Tax Preparation",
            "type":"Services"
        }
    ],
    "sg:phone":"+61 2 9824 3688",
    "sg:postcode":"2170",
    "sg:province":"NSW",
    "sg:tags":[
        "consultant",
        "taxation"
    ],
    "wof:name":"R M Financial Services Pty Ltd",
    "wof:placetype":"venue"
},
  "geometry": {"coordinates":[150.92149352999999,-33.9262008667],"type":"Point"}
}