{
  "type": "Feature",
  "properties": {
    "addr:full":"2 Lardner Pl Leongatha VIC 3953",
    "addr:housenumber":"2",
    "addr:postcode":"3953",
    "addr:street":"Lardner Pl",
    "iso:country":"AU",
    "sg:address":"2 Lardner Pl",
    "sg:city":"Leongatha",
    "sg:classifiers":[
        {
            "category":"Health Services",
            "subcategory":"Doctor",
            "type":"Services"
        }
    ],
    "sg:phone":"+61 3 5662 0899",
    "sg:postcode":"3953",
    "sg:province":"VIC",
    "sg:tags":[
        "podiatrist"
    ],
    "wof:name":"Gippsland Foot Clinic",
    "wof:placetype":"venue"
},
  "geometry": {"coordinates":[145.947021484,-38.4776992798],"type":"Point"}
}