{
  "type": "Feature",
  "properties": {
    "addr:full":"Shop 1 Gray Shopping Centre 18/20 Essington Ave Gray NT 0830",
    "addr:housenumber":"shop 1;18 / 20",
    "addr:postcode":"nt 0830",
    "addr:street":"Gray Shopping;Essington Ave",
    "iso:country":"AU",
    "sg:address":"Shop 1 Gray Shopping Centre 18/20 Essington Ave",
    "sg:city":"Gray",
    "sg:classifiers":[
        {
            "category":"Food & Beverages",
            "subcategory":"Fruits & Vegetables",
            "type":"Retail Goods"
        }
    ],
    "sg:phone":"+61 8 8931 1911",
    "sg:postcode":"0830",
    "sg:province":"NT",
    "sg:tags":[
        "consultant",
        "catering"
    ],
    "wof:name":"Part-eze",
    "wof:placetype":"venue"
},
  "geometry": {"coordinates":[130.98190299999999,-12.487611],"type":"Point"}
}