{
  "type": "Feature",
  "properties": {
    "iso:country":"AU",
    "sg:address":"49 King St",
    "sg:city":"Ashbury",
    "sg:classifiers":[
        {
            "category":"Shopping",
            "subcategory":"Clothing, Apparel, & Fashions",
            "type":"Retail Goods"
        }
    ],
    "sg:phone":"+61 2 9799 7742",
    "sg:postcode":"2193",
    "sg:province":"NSW",
    "sg:tags":[
        "lady",
        "wear"
    ],
    "wof:name":"Blushing Pink",
    "wof:placetype":"venue"
},
  "geometry": {"coordinates":[151.120056,-33.900612],"type":"Point"}
}