{
  "type": "Feature",
  "properties": {
    "addr:full":"Factory 2/ 252 Boundary Rd Braeside VIC 3195",
    "addr:housenumber":"/ 252",
    "addr:postcode":"3195",
    "addr:street":"Boundary Rd",
    "iso:country":"AU",
    "sg:address":"Factory 2/ 252 Boundary Rd",
    "sg:city":"Braeside",
    "sg:classifiers":[
        {
            "category":"Retail",
            "subcategory":"Auto Repair",
            "type":"Services"
        }
    ],
    "sg:phone":"+61 3 9587 0774",
    "sg:postcode":"3195",
    "sg:province":"VIC",
    "sg:tags":[
        "repairer",
        "motor",
        "engineer"
    ],
    "wof:name":"A & J Braeside Car Care",
    "wof:placetype":"venue"
},
  "geometry": {"coordinates":[145.10763549800001,-37.9905014038],"type":"Point"}
}