{
  "type": "Feature",
  "properties": {
    "addr:full":"865 Frankston-Flinders Rd Somerville VIC 3912",
    "addr:housenumber":"865",
    "addr:postcode":"3912",
    "addr:street":"Frankston-Flinders Rd",
    "iso:country":"AU",
    "sg:address":"865 Frankston-Flinders Rd",
    "sg:city":"Somerville",
    "sg:classifiers":[
        {
            "category":"Retail",
            "subcategory":"Auto Repair",
            "type":"Services"
        }
    ],
    "sg:phone":"+61 3 5977 7880",
    "sg:postcode":"3912",
    "sg:province":"VIC",
    "sg:tags":[
        "repairer",
        "motor",
        "engineer"
    ],
    "wof:name":"A. Agar's Mobile Mechanical Repairs",
    "wof:placetype":"venue"
},
  "geometry": {"coordinates":[145.165359497,-38.2086448669],"type":"Point"}
}