{
  "type": "Feature",
  "properties": {
    "addr:full":"52 Loch St Maryborough VIC 3465",
    "addr:housenumber":"52",
    "addr:postcode":"3465",
    "addr:street":"Loch St",
    "iso:country":"AU",
    "sg:address":"52 Loch St",
    "sg:city":"Maryborough",
    "sg:classifiers":[
        {
            "category":"Retail",
            "subcategory":"Auto Repair",
            "type":"Services"
        }
    ],
    "sg:phone":"+61 3 5461 1449",
    "sg:postcode":"3465",
    "sg:province":"VIC",
    "sg:tags":[
        "repairer",
        "motor",
        "engineer"
    ],
    "wof:name":"Collicoat N J & J M",
    "wof:placetype":"venue"
},
  "geometry": {"coordinates":[143.73643493599999,-37.0618095398],"type":"Point"}
}