{
  "type": "Feature",
  "properties": {
    "iso:country":"AU",
    "sg:address":"Forest Plain Rd",
    "sg:city":"Allora",
    "sg:classifiers":[
        {
            "category":"Building & Trades",
            "subcategory":"Construction",
            "type":"Services"
        }
    ],
    "sg:phone":"+61 7 4666 3226",
    "sg:postcode":"4362",
    "sg:province":"QLD",
    "sg:tags":[
        "welding"
    ],
    "wof:name":"B.T. & A.L. Glass Welding & Steel Fabrication",
    "wof:placetype":"venue"
},
  "geometry": {"coordinates":[151.992477417,-28.0334835052],"type":"Point"}
}