{
  "type": "Feature",
  "properties": {
    "addr:full":"16 Pelmet Crs Thomastown VIC 3074",
    "addr:housenumber":"16",
    "addr:postcode":"3074",
    "addr:street":"Pelmet Crs",
    "iso:country":"AU",
    "sg:address":"16 Pelmet Crs",
    "sg:city":"Thomastown",
    "sg:classifiers":[
        {
            "category":"Professional",
            "subcategory":"Engineering",
            "type":"Services"
        }
    ],
    "sg:phone":"+61 3 9469 2738",
    "sg:postcode":"3074",
    "sg:province":"VIC",
    "sg:tags":[
        "engineer"
    ],
    "wof:name":"DND Engineering Pty Ltd",
    "wof:placetype":"venue"
},
  "geometry": {"coordinates":[145.01148986800001,-37.6832199097],"type":"Point"}
}