{
  "type": "Feature",
  "properties": {
    "iso:country":"AU",
    "sg:address":"370 Bay St",
    "sg:city":"Port Melbourne",
    "sg:classifiers":[
        {
            "category":"Home & Garden",
            "subcategory":"Building Materials",
            "type":"Retail Goods"
        }
    ],
    "sg:phone":"+61 3 9270 8800",
    "sg:postcode":"3207",
    "sg:province":"VIC",
    "sg:tags":[
        "merchant",
        "glass",
        "glazier"
    ],
    "wof:name":"O&#039;Brien Glass",
    "wof:placetype":"venue"
},
  "geometry": {"coordinates":[144.945053,-37.835819],"type":"Point"}
}