{
  "type": "Feature",
  "properties": {
    "addr:full":"68 Conadilly St Gunnedah NSW 2380",
    "addr:housenumber":"68",
    "addr:postcode":"2380",
    "addr:street":"Conadilly St",
    "iso:country":"AU",
    "sg:address":"68 Conadilly St",
    "sg:city":"Gunnedah",
    "sg:classifiers":[
        {
            "category":"Home & Garden",
            "subcategory":"Hardware",
            "type":"Retail Goods"
        }
    ],
    "sg:phone":"+61 2 6742 4227",
    "sg:postcode":"2380",
    "sg:province":"NSW",
    "sg:tags":[
        "nut",
        "bolt"
    ],
    "wof:name":"Ag-Ware Pty Ltd (Gunnedah)",
    "wof:placetype":"venue"
},
  "geometry": {"coordinates":[150.24734497099999,-30.9747009277],"type":"Point"}
}