{
  "type": "Feature",
  "properties": {
    "iso:country":"AU",
    "sg:address":"Chilton Rd",
    "sg:city":"Berri",
    "sg:classifiers":[
        {
            "category":"Farming",
            "subcategory":"Berry Farm",
            "type":"Manufacturing & Wholesale Goods"
        }
    ],
    "sg:phone":"+61 8 8582 1610",
    "sg:postcode":"5343",
    "sg:province":"SA",
    "sg:tags":[
        "fruit",
        "grower"
    ],
    "wof:name":"Koutouzis G",
    "wof:placetype":"venue"
},
  "geometry": {"coordinates":[140.613739014,-34.2823143005],"type":"Point"}
}