{
  "type": "Feature",
  "properties": {
    "addr:full":"232 Cumberland Rd Auburn NSW 2144",
    "addr:housenumber":"232",
    "addr:postcode":"2144",
    "addr:street":"Cumberland Rd",
    "iso:country":"AU",
    "sg:address":"232 Cumberland Rd",
    "sg:city":"Auburn",
    "sg:classifiers":[
        {
            "category":"Professional",
            "subcategory":"Art Services",
            "type":"Services"
        }
    ],
    "sg:phone":"+61 410 064 548",
    "sg:postcode":"2144",
    "sg:province":"NSW",
    "sg:tags":[
        "interior",
        "decorator"
    ],
    "wof:name":"Your Walls Will Talk",
    "wof:placetype":"venue"
},
  "geometry": {"coordinates":[151.02565002399999,-33.8502006531],"type":"Point"}
}