{
  "type": "Feature",
  "properties": {
    "iso:country":"AU",
    "sg:address":"Level 5, HSBC Centre 580 George St",
    "sg:city":"Sydney",
    "sg:classifiers":[
        {
            "category":"Professional",
            "subcategory":"Management & Consulting",
            "type":"Services"
        }
    ],
    "sg:phone":"+61 2 9286 3799",
    "sg:postcode":"2000",
    "sg:province":"NSW",
    "sg:tags":[
        "consultant",
        "educational"
    ],
    "wof:name":"Australian College Information Centre - ACIC",
    "wof:placetype":"venue"
},
  "geometry": {"coordinates":[151.20680236800001,-33.8751754761],"type":"Point"}
}