{
  "type": "Feature",
  "properties": {
    "addr:full":"Suite 8 - 400 St Kilda Rd St Kilda VIC 3182",
    "addr:housenumber":"400",
    "addr:postcode":"3182",
    "addr:street":"St Kilda Rd",
    "iso:country":"AU",
    "sg:address":"Suite 8 - 400 St Kilda Rd",
    "sg:city":"St Kilda",
    "sg:classifiers":[
        {
            "category":"Professional",
            "subcategory":"Art Services",
            "type":"Services"
        }
    ],
    "sg:phone":"+61 3 9593 9222",
    "sg:postcode":"3182",
    "sg:province":"VIC",
    "sg:tags":[
        "graphic",
        "designer"
    ],
    "sg:website":"http://www.inhousemad.com",
    "wof:name":"Inhouse M A D",
    "wof:placetype":"venue"
},
  "geometry": {"coordinates":[144.98707580600001,-37.867313385],"type":"Point"}
}