{
  "type": "Feature",
  "properties": {
    "iso:country":"AU",
    "sg:address":"Shop 4, 37- 39 Bulje St",
    "sg:city":"Dubbo",
    "sg:classifiers":[
        {
            "category":"Fast Food",
            "type":"Food & Drink"
        }
    ],
    "sg:phone":"+61 2 6882 6769",
    "sg:postcode":"2830",
    "sg:province":"NSW",
    "sg:tags":[
        "away",
        "take"
    ],
    "wof:name":"Relish Salad Bar & Takeaway",
    "wof:placetype":"venue"
},
  "geometry": {"coordinates":[148.60272216800001,-32.2511672974],"type":"Point"}
}