{
  "type": "Feature",
  "properties": {
    "addr:full":"289 Princes Hwy Werribee VIC 3030",
    "addr:housenumber":"289",
    "addr:postcode":"3030",
    "addr:street":"Princes Hwy",
    "iso:country":"AU",
    "sg:address":"289 Princes Hwy",
    "sg:city":"Werribee",
    "sg:classifiers":[
        {
            "category":"Banks & Credit Unions",
            "subcategory":"Financial Services",
            "type":"Services"
        }
    ],
    "sg:phone":"+61 3 9326 2666",
    "sg:postcode":"3030",
    "sg:province":"VIC",
    "sg:tags":[
        "surgeon",
        "oral",
        "dental",
        "maxillofacial"
    ],
    "wof:name":"Wright Dr Graeme W",
    "wof:placetype":"venue"
},
  "geometry": {"coordinates":[144.69418300000001,-37.887035],"type":"Point"}
}