{
  "type": "Feature",
  "properties": {
    "addr:full":"1st Floor 553 Hay St Perth WA 6000",
    "addr:housenumber":"553",
    "addr:postcode":"6000",
    "addr:street":"Hay St",
    "iso:country":"AU",
    "sg:address":"1st Floor 553 Hay St",
    "sg:city":"Perth",
    "sg:classifiers":[
        {
            "category":"Health Services",
            "subcategory":"Dentist",
            "type":"Services"
        }
    ],
    "sg:phone":"+61 8 9221 5454",
    "sg:postcode":"6000",
    "sg:province":"WA",
    "wof:name":"Dr Mun",
    "wof:placetype":"venue"
},
  "geometry": {"coordinates":[115.855476379,-31.9531841278],"type":"Point"}
}