{
  "type": "Feature",
  "properties": {
    "addr:full":"75 Barber St Gunnedah NSW 2380",
    "addr:housenumber":"75",
    "addr:postcode":"2380",
    "addr:street":"Barber St",
    "iso:country":"AU",
    "sg:address":"75 Barber St",
    "sg:city":"Gunnedah",
    "sg:classifiers":[
        {
            "category":"Retail",
            "subcategory":"Auto Repair",
            "type":"Services"
        }
    ],
    "sg:phone":"+61 2 6742 2950",
    "sg:postcode":"2380",
    "sg:province":"NSW",
    "sg:tags":[
        "beater",
        "painter",
        "panel"
    ],
    "wof:name":"West End Panel Service Pty Ltd",
    "wof:placetype":"venue"
},
  "geometry": {"coordinates":[150.250442505,-30.9787311554],"type":"Point"}
}