{
  "type": "Feature",
  "properties": {
    "addr:full":"PO Box 30 Hay NSW 2711",
    "addr:postcode":"2711",
    "iso:country":"AU",
    "sg:address":"PO Box 30",
    "sg:city":"Hay",
    "sg:classifiers":[
        {
            "category":"Utilities",
            "subcategory":"Electric",
            "type":"Services"
        }
    ],
    "sg:phone":"+61 408 962 972",
    "sg:postcode":"2711",
    "sg:province":"NSW",
    "sg:tags":[
        "electrical",
        "contractor"
    ],
    "wof:name":"Cid Electrics Pty Ltd",
    "wof:placetype":"venue"
},
  "geometry": {"coordinates":[144.843948364,-34.5069885254],"type":"Point"}
}