{
  "type": "Feature",
  "properties": {
    "iso:country":"AU",
    "sg:address":"254 Canning Hwy",
    "sg:city":"East Fremantle",
    "sg:classifiers":[
        {
            "category":"Personal",
            "subcategory":"Massage",
            "type":"Services"
        }
    ],
    "sg:phone":"+61 8 9319 3511",
    "sg:postcode":"6158",
    "sg:province":"WA",
    "sg:tags":[
        "therapy"
    ],
    "wof:name":"Paula Atkinson",
    "wof:placetype":"venue"
},
  "geometry": {"coordinates":[115.763397,-32.0411],"type":"Point"}
}