{
  "type": "Feature",
  "properties": {
    "addr:full":"185 Baillie St Horsham VIC 3400",
    "addr:housenumber":"185",
    "addr:postcode":"3400",
    "addr:street":"Baillie St",
    "iso:country":"AU",
    "sg:address":"185 Baillie St",
    "sg:city":"Horsham",
    "sg:classifiers":[
        {
            "category":"Government",
            "subcategory":"Court House",
            "type":"Public Place"
        }
    ],
    "sg:phone":"+61 3 5382 6789",
    "sg:postcode":"3400",
    "sg:province":"VIC",
    "sg:tags":[
        "personal",
        "marriage",
        "family",
        "counselling"
    ],
    "wof:name":"Wimmera Uniting Care Counselling Services",
    "wof:placetype":"venue"
},
  "geometry": {"coordinates":[142.197875977,-36.7118453979],"type":"Point"}
}