{
  "type": "Feature",
  "properties": {
    "addr:full":"Tuggeranong Chiropractic+4 Hanlon Crs Fadden ACT 2904",
    "addr:postcode":"2904",
    "addr:street":"Hanlon Crs",
    "iso:country":"AU",
    "sg:address":"Tuggeranong Chiropractic+4 Hanlon Crs",
    "sg:city":"Fadden",
    "sg:classifiers":[
        {
            "category":"Health Services",
            "subcategory":"Health Practitioner",
            "type":"Services"
        }
    ],
    "sg:phone":"+61 2 6292 7344",
    "sg:postcode":"2904",
    "sg:province":"ACT",
    "sg:tags":[
        "naturopath"
    ],
    "wof:name":"Hashmi Kerri",
    "wof:placetype":"venue"
},
  "geometry": {"coordinates":[149.117919922,-35.4052085876],"type":"Point"}
}