{
  "type": "Feature",
  "properties": {
    "addr:full":"175 Gertrude St Fitzroy VIC 3065",
    "addr:housenumber":"175",
    "addr:postcode":"3065",
    "addr:street":"Gertrude St",
    "iso:country":"AU",
    "sg:address":"175 Gertrude St",
    "sg:city":"Fitzroy",
    "sg:classifiers":[
        {
            "category":"Manufacturing",
            "subcategory":"Glass & Minerals",
            "type":"Manufacturing & Wholesale Goods"
        }
    ],
    "sg:phone":"+61 3 9417 5000",
    "sg:postcode":"3065",
    "sg:province":"VIC",
    "sg:tags":[
        "case",
        "counter",
        "show"
    ],
    "sg:website":"http://www.displaydesign.com.au",
    "wof:name":"Display Design Aust Pty Ltd",
    "wof:placetype":"venue"
},
  "geometry": {"coordinates":[144.98034668,-37.805934906],"type":"Point"}
}