{
  "type": "Feature",
  "properties": {
    "addr:full":"Fortune St Balcatta WA 6021",
    "addr:postcode":"6021",
    "addr:street":"Fortune St",
    "iso:country":"AU",
    "sg:address":"Fortune St",
    "sg:city":"Balcatta",
    "sg:classifiers":[
        {
            "category":"Retail",
            "subcategory":"Event Space",
            "type":"Services"
        }
    ],
    "sg:phone":"+61 8 9344 3336",
    "sg:postcode":"6021",
    "sg:province":"WA",
    "sg:tags":[
        "venue",
        "reception",
        "wedding"
    ],
    "wof:name":"Siciliani Assoc Of WA",
    "wof:placetype":"venue"
},
  "geometry": {"coordinates":[115.82450103799999,-31.884973526],"type":"Point"}
}