{
  "type": "Feature",
  "properties": {
    "addr:full":"Dubbo City Bowling Club Wingewarra St Dubbo NSW 2830",
    "addr:postcode":"2830",
    "addr:street":"St",
    "iso:country":"AU",
    "sg:address":"Dubbo City Bowling Club Wingewarra St",
    "sg:city":"Dubbo",
    "sg:classifiers":[
        {
            "category":"Fast Food",
            "type":"Food & Drink"
        }
    ],
    "sg:phone":"+61 2 6882 2113",
    "sg:postcode":"2830",
    "sg:province":"NSW",
    "sg:tags":[
        "away",
        "take"
    ],
    "wof:name":"Jaya Raya",
    "wof:placetype":"venue"
},
  "geometry": {"coordinates":[148.600067139,-32.248840332],"type":"Point"}
}