{
  "type": "Feature",
  "properties": {
    "iso:country":"AU",
    "sg:address":"46 Spence St",
    "sg:city":"Cairns",
    "sg:classifiers":[
        {
            "category":"Professional",
            "subcategory":"Management & Consulting",
            "type":"Services"
        }
    ],
    "sg:phone":"+61 7 4051 8788",
    "sg:postcode":"4870",
    "sg:province":"QLD",
    "sg:tags":[
        "consultant",
        "migration"
    ],
    "wof:name":"Carol Shipway",
    "wof:placetype":"venue"
},
  "geometry": {"coordinates":[145.75405883799999,-16.941608429],"type":"Point"}
}