{
  "type": "Feature",
  "properties": {
    "addr:full":"578 Malvern Rd Prahran VIC 3181",
    "addr:housenumber":"578",
    "addr:postcode":"3181",
    "addr:street":"Malvern Rd",
    "iso:country":"AU",
    "sg:address":"578 Malvern Rd",
    "sg:city":"Prahran",
    "sg:classifiers":[
        {
            "category":"Cafe",
            "type":"Food & Drink"
        }
    ],
    "sg:phone":"+61 3 9533 2008",
    "sg:postcode":"3181",
    "sg:province":"VIC",
    "wof:name":"At Beba's",
    "wof:placetype":"venue"
},
  "geometry": {"coordinates":[145.005584717,-37.8485145569],"type":"Point"}
}