{
  "type": "Feature",
  "properties": {
    "addr:full":"8 Bedford Crt Rosanna VIC 3084",
    "addr:housenumber":"8",
    "addr:postcode":"3084",
    "addr:street":"Bedford Crt",
    "iso:country":"AU",
    "sg:address":"8 Bedford Crt",
    "sg:city":"Rosanna",
    "sg:classifiers":[
        {
            "category":"Home & Garden",
            "subcategory":"Building Materials",
            "type":"Retail Goods"
        }
    ],
    "sg:phone":"+61 411 619 797",
    "sg:postcode":"3084",
    "sg:province":"VIC",
    "sg:tags":[
        "lawn",
        "cutting",
        "maintenance"
    ],
    "wof:name":"Breese Garden Management",
    "wof:placetype":"venue"
},
  "geometry": {"coordinates":[145.084747314,-37.7455673218],"type":"Point"}
}