{
  "type": "Feature",
  "properties": {
    "addr:full":"Level 3/ 2 Glen St Milsons Point NSW 2061",
    "addr:housenumber":"/ 2",
    "addr:postcode":"2061",
    "addr:street":"Glen St",
    "iso:country":"AU",
    "sg:address":"Level 3/ 2 Glen St",
    "sg:city":"Milsons Point",
    "sg:classifiers":[
        {
            "category":"Professional",
            "subcategory":"Management & Consulting",
            "type":"Services"
        }
    ],
    "sg:phone":"+61 2 9929 0944",
    "sg:postcode":"2061",
    "sg:province":"NSW",
    "sg:tags":[
        "consultant"
    ],
    "wof:name":"INFORM-Objective Risk Management",
    "wof:placetype":"venue"
},
  "geometry": {"coordinates":[151.210540772,-33.8478355408],"type":"Point"}
}