{
  "type": "Feature",
  "properties": {
    "addr:full":"1 Dolomite St Runcorn QLD 4113",
    "addr:housenumber":"1",
    "addr:postcode":"4113",
    "addr:street":"Dolomite St",
    "iso:country":"AU",
    "sg:address":"1 Dolomite St",
    "sg:city":"Runcorn",
    "sg:classifiers":[
        {
            "category":"Wholesale",
            "subcategory":"Metals & Minerals",
            "type":"Manufacturing & Wholesale Goods"
        }
    ],
    "sg:phone":"+61 7 3341 1826",
    "sg:postcode":"4113",
    "sg:province":"QLD",
    "sg:tags":[
        "steel",
        "merchant"
    ],
    "wof:name":"Sanderson Newbould Special Steels Pty Ltd",
    "wof:placetype":"venue"
},
  "geometry": {"coordinates":[153.080810547,-27.5903244019],"type":"Point"}
}