{
  "type": "Feature",
  "properties": {
    "addr:full":"27 Tully Ave Liverpool NSW 2170",
    "addr:housenumber":"27",
    "addr:postcode":"2170",
    "addr:street":"Tully Ave",
    "iso:country":"AU",
    "sg:address":"27 Tully Ave",
    "sg:city":"Liverpool",
    "sg:classifiers":[
        {
            "category":"Health Services",
            "subcategory":"Health Practitioner",
            "type":"Services"
        }
    ],
    "sg:phone":"+61 2 9601 6728",
    "sg:postcode":"2170",
    "sg:province":"NSW",
    "sg:tags":[
        "alternative"
    ],
    "wof:name":"Australian Polarity Therapy College",
    "wof:placetype":"venue"
},
  "geometry": {"coordinates":[150.90834045400001,-33.9362411499],"type":"Point"}
}