{
  "type": "Feature",
  "properties": {
    "addr:full":"176 Macedon Rd Templestowe Lower VIC 3107",
    "addr:housenumber":"176",
    "addr:postcode":"3107",
    "addr:street":"Macedon Rd",
    "iso:country":"AU",
    "sg:address":"176 Macedon Rd",
    "sg:city":"Templestowe Lower",
    "sg:classifiers":[
        {
            "category":"Utilities",
            "subcategory":"Electric",
            "type":"Services"
        }
    ],
    "sg:phone":"+61 3 9850 7524",
    "sg:postcode":"3107",
    "sg:province":"VIC",
    "sg:tags":[
        "electrical",
        "contractor"
    ],
    "wof:name":"GR & SR Electrics",
    "wof:placetype":"venue"
},
  "geometry": {"coordinates":[145.11566162099999,-37.7599220276],"type":"Point"}
}