{
  "type": "Feature",
  "properties": {
    "addr:full":"Lamont St Bermagui South NSW 2546",
    "addr:postcode":"2546",
    "addr:street":"Lamont St",
    "iso:country":"AU",
    "sg:address":"Lamont St",
    "sg:city":"Bermagui South",
    "sg:classifiers":[
        {
            "category":"Travel",
            "subcategory":"Hotels & Motels",
            "type":"Entertainment"
        }
    ],
    "sg:phone":"+61 2 6493 4155",
    "sg:postcode":"2546",
    "sg:province":"NSW",
    "wof:name":"Beachview Motel",
    "wof:placetype":"venue"
},
  "geometry": {"coordinates":[150.076904297,-36.4270820618],"type":"Point"}
}