{
  "type": "Feature",
  "properties": {
    "addr:full":"5 Parkin Crt Eden Hill WA 6054",
    "addr:housenumber":"5",
    "addr:postcode":"6054",
    "addr:street":"Parkin Crt",
    "iso:country":"AU",
    "sg:address":"5 Parkin Crt",
    "sg:city":"Eden Hill",
    "sg:classifiers":[
        {
            "category":"Banks & Credit Unions",
            "subcategory":"Bank",
            "type":"Services"
        }
    ],
    "sg:phone":"+61 8 9379 9009",
    "sg:postcode":"6054",
    "sg:province":"WA",
    "sg:tags":[
        "broker",
        "mortgage"
    ],
    "wof:name":"Ballard Mortgage Services",
    "wof:placetype":"venue"
},
  "geometry": {"coordinates":[115.936073303,-31.8895378113],"type":"Point"}
}