{
  "type": "Feature",
  "properties": {
    "addr:full":"872 Pittwater Rd Dee Why NSW 2099",
    "addr:housenumber":"872",
    "addr:postcode":"2099",
    "addr:street":"Pittwater Rd",
    "iso:country":"AU",
    "sg:address":"872 Pittwater Rd",
    "sg:city":"Dee Why",
    "sg:classifiers":[
        {
            "category":"Banks & Credit Unions",
            "subcategory":"Financial Services",
            "type":"Services"
        }
    ],
    "sg:phone":"+61 2 9932 1333",
    "sg:postcode":"2099",
    "sg:province":"NSW",
    "sg:tags":[
        "loan",
        "finance",
        "mortgage"
    ],
    "wof:name":"Aussie",
    "wof:placetype":"venue"
},
  "geometry": {"coordinates":[151.285614014,-33.7536621094],"type":"Point"}
}