{
  "type": "Feature",
  "properties": {
    "addr:full":"22a Commercial Drv Springfield QLD 4300",
    "addr:housenumber":"22a",
    "addr:postcode":"4300",
    "addr:street":"Commercial Drv",
    "iso:country":"AU",
    "sg:address":"22a Commercial Drv",
    "sg:city":"Springfield",
    "sg:classifiers":[
        {
            "category":"Sports & Exercise",
            "subcategory":"Gym",
            "type":"Entertainment"
        }
    ],
    "sg:phone":"+61 421 601 937",
    "sg:postcode":"4300",
    "sg:province":"QLD",
    "sg:tags":[
        "health",
        "fitness"
    ],
    "wof:name":"Springfield Personal Training Studio",
    "wof:placetype":"venue"
},
  "geometry": {"coordinates":[152.91871643100001,-27.6548423767],"type":"Point"}
}