{
  "type": "Feature",
  "properties": {
    "addr:full":"1 Gumnut Rd Yamba NSW 2464",
    "addr:housenumber":"1",
    "addr:postcode":"2464",
    "addr:street":"Gumnut Rd",
    "iso:country":"AU",
    "sg:address":"1 Gumnut Rd",
    "sg:city":"Yamba",
    "sg:classifiers":[
        {
            "category":"Personal",
            "subcategory":"Beauty Salon",
            "type":"Services"
        }
    ],
    "sg:phone":"+61 2 6646 1024",
    "sg:postcode":"2464",
    "sg:province":"NSW",
    "sg:tags":[
        "hairdresser"
    ],
    "wof:name":"Mobile Hair Fairy",
    "wof:placetype":"venue"
},
  "geometry": {"coordinates":[153.322433472,-29.4239940643],"type":"Point"}
}