{
  "type": "Feature",
  "properties": {
    "iso:country":"AU",
    "sg:address":"Rogers St",
    "sg:city":"Spring Hill",
    "sg:classifiers":[
        {
            "category":"Education",
            "subcategory":"School",
            "type":"Public Place"
        }
    ],
    "sg:phone":"+61 7 3831 5360",
    "sg:postcode":"4000",
    "sg:province":"QLD",
    "sg:tags":[
        "state",
        "except",
        "nsw"
    ],
    "wof:name":"Brisbane Central Primary",
    "wof:placetype":"venue"
},
  "geometry": {"coordinates":[153.02728271500001,-27.4595966339],"type":"Point"}
}