{
  "type": "Feature",
  "properties": {
    "iso:country":"AU",
    "sg:address":"68a Buxton Rd",
    "sg:city":"Wembley Downs",
    "sg:classifiers":[
        {
            "category":"Farming",
            "subcategory":"Fish & Marine Products",
            "type":"Manufacturing & Wholesale Goods"
        }
    ],
    "sg:phone":"+61 8 9245 5554",
    "sg:postcode":"6019",
    "sg:province":"WA",
    "sg:tags":[
        "equipment",
        "salvage"
    ],
    "wof:name":"Joint Technical Services",
    "wof:placetype":"venue"
},
  "geometry": {"coordinates":[115.77004241900001,-31.9213523865],"type":"Point"}
}