{
  "type": "Feature",
  "properties": {
    "iso:country":"AU",
    "sg:address":"98 Talbragar St",
    "sg:city":"Dubbo",
    "sg:classifiers":[
        {
            "category":"Train Station",
            "subcategory":"Light Rail",
            "type":"Transportation"
        }
    ],
    "sg:phone":"+61 2 6885 2295",
    "sg:postcode":"2830",
    "sg:province":"NSW",
    "sg:tags":[
        "equipment",
        "energy",
        "solar"
    ],
    "wof:name":"Orana Energy Systems",
    "wof:placetype":"venue"
},
  "geometry": {"coordinates":[148.604812622,-32.2450790405],"type":"Point"}
}