{
  "type": "Feature",
  "properties": {
    "addr:full":"33a High St Strathalbyn SA 5255",
    "addr:housenumber":"33a",
    "addr:postcode":"5255",
    "addr:street":"High St",
    "iso:country":"AU",
    "sg:address":"33a High St",
    "sg:city":"Strathalbyn",
    "sg:classifiers":[
        {
            "category":"Health Services",
            "subcategory":"Health Practitioner",
            "type":"Services"
        }
    ],
    "sg:phone":"+61 8 8536 3303",
    "sg:postcode":"5255",
    "sg:province":"SA",
    "sg:tags":[
        "physiotherapist"
    ],
    "wof:name":"Steve Argue",
    "wof:placetype":"venue"
},
  "geometry": {"coordinates":[138.89378356899999,-35.2569541931],"type":"Point"}
}