{
  "type": "Feature",
  "properties": {
    "addr:full":"95 Annangrove Rd Kenthurst NSW 2156",
    "addr:housenumber":"95",
    "addr:postcode":"2156",
    "addr:street":"Annangrove Rd",
    "iso:country":"AU",
    "sg:address":"95 Annangrove Rd",
    "sg:city":"Kenthurst",
    "sg:classifiers":[
        {
            "category":"Retail",
            "subcategory":"Repair Shop",
            "type":"Services"
        }
    ],
    "sg:phone":"+61 2 9654 3171",
    "sg:postcode":"2156",
    "sg:province":"NSW",
    "sg:tags":[
        "repairing",
        "piano",
        "tuning"
    ],
    "wof:name":"Coxhead Bruce",
    "wof:placetype":"venue"
},
  "geometry": {"coordinates":[150.97613525400001,-33.6797866821],"type":"Point"}
}