{
  "type": "Feature",
  "properties": {
    "iso:country":"AU",
    "sg:address":"Shop 6, 127 Fryers St",
    "sg:city":"Shepparton",
    "sg:classifiers":[
        {
            "category":"Personal",
            "subcategory":"Skin Care",
            "type":"Services"
        }
    ],
    "sg:phone":"+61 3 5831 1528",
    "sg:postcode":"3630",
    "sg:province":"VIC",
    "sg:tags":[
        "treatment"
    ],
    "wof:name":"Cathy's Beauty Clinic",
    "wof:placetype":"venue"
},
  "geometry": {"coordinates":[145.402999878,-36.3792419434],"type":"Point"}
}