{
  "type": "Feature",
  "properties": {
    "iso:country":"AU",
    "sg:address":"165 Sydney Rd",
    "sg:city":"Coburg",
    "sg:classifiers":[
        {
            "category":"Wholesale",
            "subcategory":"Farm Supplies",
            "type":"Manufacturing & Wholesale Goods"
        }
    ],
    "sg:phone":"+61 3 9386 0326",
    "sg:postcode":"3058",
    "sg:province":"VIC",
    "sg:tags":[
        "feed",
        "supplement",
        "stock"
    ],
    "wof:name":"Andrew's Stock Feed",
    "wof:placetype":"venue"
},
  "geometry": {"coordinates":[144.96479797399999,-37.7507476807],"type":"Point"}
}