{
  "type": "Feature",
  "properties": {
    "addr:full":"111 Haig Rd Auchenflower QLD 4066",
    "addr:housenumber":"111",
    "addr:postcode":"4066",
    "addr:street":"Haig Rd",
    "iso:country":"AU",
    "sg:address":"111 Haig Rd",
    "sg:city":"Auchenflower",
    "sg:classifiers":[
        {
            "category":"Restaurant",
            "type":"Food & Drink"
        }
    ],
    "sg:phone":"+61 7 3870 3030",
    "sg:postcode":"4066",
    "sg:province":"QLD",
    "wof:name":"Sprout Cafe",
    "wof:placetype":"venue"
},
  "geometry": {"coordinates":[152.995895386,-27.4704589844],"type":"Point"}
}