{
  "type": "Feature",
  "properties": {
    "iso:country":"AU",
    "sg:address":"921 Glenhuntly Rd",
    "sg:city":"Caulfield",
    "sg:classifiers":[
        {
            "category":"Professional",
            "type":"Services"
        }
    ],
    "sg:phone":"+61 3 9528 5287",
    "sg:postcode":"3162",
    "sg:province":"VIC",
    "sg:tags":[
        "quality",
        "assurance"
    ],
    "wof:name":"Australian Quality Management Pty Ltd",
    "wof:placetype":"venue"
},
  "geometry": {"coordinates":[145.02865600600001,-37.8875770569],"type":"Point"}
}