{
  "type": "Feature",
  "properties": {
    "addr:full":"95 Alfred St Narraweena NSW 2099",
    "addr:housenumber":"95",
    "addr:postcode":"2099",
    "addr:street":"Alfred St",
    "iso:country":"AU",
    "sg:address":"95 Alfred St",
    "sg:city":"Narraweena",
    "sg:classifiers":[
        {
            "category":"Utilities",
            "subcategory":"Electric",
            "type":"Services"
        }
    ],
    "sg:phone":"+61 414 606 145",
    "sg:postcode":"2099",
    "sg:province":"NSW",
    "sg:tags":[
        "electrical",
        "contractor"
    ],
    "wof:name":"Eire Electrical",
    "wof:placetype":"venue"
},
  "geometry": {"coordinates":[151.27459716800001,-33.7510566711],"type":"Point"}
}