{
  "type": "Feature",
  "properties": {
    "iso:country":"AU",
    "sg:address":"Suite 10, 370-376 Church St",
    "sg:city":"Parramatta",
    "sg:classifiers":[
        {
            "category":"Professional",
            "subcategory":"Lawyer & Legal Services",
            "type":"Services"
        }
    ],
    "sg:phone":"+61 2 8839 5555",
    "sg:postcode":"2150",
    "sg:province":"NSW",
    "sg:tags":[
        "wills",
        "probate",
        "estate"
    ],
    "wof:name":"Watson Stafford",
    "wof:placetype":"venue"
},
  "geometry": {"coordinates":[151.00541687,-33.8090591431],"type":"Point"}
}