{
  "type": "Feature",
  "properties": {
    "iso:country":"AU",
    "sg:address":"6 Westbrook St",
    "sg:city":"Kew East",
    "sg:classifiers":[
        {
            "category":"Professional",
            "subcategory":"Computer Services",
            "type":"Services"
        }
    ],
    "sg:phone":"+61 3 9819 7641",
    "sg:postcode":"3102",
    "sg:province":"VIC",
    "sg:tags":[
        "consultant",
        "system"
    ],
    "wof:name":"Austlink Sterling Pty Ltd",
    "wof:placetype":"venue"
},
  "geometry": {"coordinates":[145.052337647,-37.7985572815],"type":"Point"}
}