{
  "type": "Feature",
  "properties": {
    "addr:full":"Cnr William & North Sts Leichhardt NSW 2040",
    "addr:postcode":"2040",
    "addr:street":"Sts",
    "iso:country":"AU",
    "sg:address":"Cnr William & North Sts",
    "sg:city":"Leichhardt",
    "sg:classifiers":[
        {
            "category":"Retail",
            "subcategory":"Storage",
            "type":"Services"
        }
    ],
    "sg:phone":"+61 2 9518 1788",
    "sg:postcode":"2040",
    "sg:province":"NSW",
    "wof:name":"Glebe Self Storage",
    "wof:placetype":"venue"
},
  "geometry": {"coordinates":[151.160416,-33.883316],"type":"Point"}
}