{
  "type": "Feature",
  "properties": {
    "addr:full":"PO Box 1 Nedlands PLB WA 6909",
    "addr:postcode":"6909",
    "iso:country":"AU",
    "sg:address":"PO Box 1",
    "sg:city":"Nedlands PLB",
    "sg:classifiers":[
        {
            "category":"Professional",
            "subcategory":"Detective & Security Services",
            "type":"Services"
        }
    ],
    "sg:phone":"+61 8 9389 7537",
    "sg:postcode":"6909",
    "sg:province":"WA",
    "sg:tags":[
        "consultant",
        "system"
    ],
    "wof:name":"ISCS WA",
    "wof:placetype":"venue"
},
  "geometry": {"coordinates":[115.810020447,-31.9780101776],"type":"Point"}
}