{
  "type": "Feature",
  "properties": {
    "addr:full":"5 South St Rydalmere NSW 2116",
    "addr:housenumber":"5",
    "addr:postcode":"2116",
    "addr:street":"South St",
    "iso:country":"AU",
    "sg:address":"5 South St",
    "sg:city":"Rydalmere",
    "sg:classifiers":[
        {
            "category":"Autos & Motor Vehicles",
            "subcategory":"Motorcycle Sales",
            "type":"Retail Goods"
        }
    ],
    "sg:phone":"+61 2 9684 1881",
    "sg:postcode":"2116",
    "sg:province":"NSW",
    "sg:tags":[
        "part",
        "recyclers",
        "cycle"
    ],
    "wof:name":"Brisons Motorcycle Wreckers",
    "wof:placetype":"venue"
},
  "geometry": {"coordinates":[151.01138305699999,-33.8328552246],"type":"Point"}
}