{
  "type": "Feature",
  "properties": {
    "addr:full":"35 Grafton St Woollahra NSW 2025",
    "addr:housenumber":"35",
    "addr:postcode":"2025",
    "addr:street":"Grafton St",
    "iso:country":"AU",
    "sg:address":"35 Grafton St",
    "sg:city":"Woollahra",
    "sg:classifiers":[
        {
            "category":"Travel",
            "subcategory":"Travel Agent",
            "type":"Entertainment"
        }
    ],
    "sg:phone":"+61 2 9657 3333",
    "sg:postcode":"2025",
    "sg:province":"NSW",
    "sg:tags":[
        "consultant"
    ],
    "wof:name":"Trafalgar Tours (Aust) Pty Ltd",
    "wof:placetype":"venue"
},
  "geometry": {"coordinates":[151.244903564,-33.8902549744],"type":"Point"}
}