{
  "type": "Feature",
  "properties": {
    "addr:full":"PO Box 718 Caringbah NSW 2229",
    "addr:postcode":"2229",
    "iso:country":"AU",
    "sg:address":"PO Box 718",
    "sg:city":"Caringbah",
    "sg:classifiers":[
        {
            "category":"Shopping",
            "subcategory":"Party Supplies",
            "type":"Retail Goods"
        }
    ],
    "sg:phone":"+61 1300 577 678",
    "sg:postcode":"2229",
    "sg:province":"NSW",
    "sg:tags":[
        "children's"
    ],
    "wof:name":"Kelly Sports Kid's Parties",
    "wof:placetype":"venue"
},
  "geometry": {"coordinates":[151.12121582,-34.0429000854],"type":"Point"}
}