{
  "type": "Feature",
  "properties": {
    "addr:full":"14 Campbell Ave Lane Cove NSW 2066",
    "addr:housenumber":"14",
    "addr:postcode":"2066",
    "addr:street":"Campbell Ave",
    "iso:country":"AU",
    "sg:address":"14 Campbell Ave",
    "sg:city":"Lane Cove",
    "sg:classifiers":[
        {
            "category":"Professional",
            "subcategory":"Detective & Security Services",
            "type":"Services"
        }
    ],
    "sg:phone":"+61 2 9427 3426",
    "sg:postcode":"2066",
    "sg:province":"NSW",
    "sg:tags":[
        "consultant",
        "system"
    ],
    "wof:name":"Alert Tagging",
    "wof:placetype":"venue"
},
  "geometry": {"coordinates":[151.17657470699999,-33.82213974],"type":"Point"}
}