{
  "type": "Feature",
  "properties": {
    "iso:country":"AU",
    "sg:address":"Suite 7 Level 1 117 North Rd",
    "sg:city":"Denistone East",
    "sg:classifiers":[
        {
            "category":"Health Services",
            "subcategory":"Doctor",
            "type":"Services"
        }
    ],
    "sg:phone":"+61 2 9878 6988",
    "sg:postcode":"2112",
    "sg:province":"NSW",
    "sg:tags":[
        "medical",
        "practitioner"
    ],
    "wof:name":"SDS Pathology",
    "wof:placetype":"venue"
},
  "geometry": {"coordinates":[151.10253906200001,-33.7954139709],"type":"Point"}
}