{
  "type": "Feature",
  "properties": {
    "addr:full":"127 Wilson St Horsham VIC 3400",
    "addr:housenumber":"127",
    "addr:postcode":"3400",
    "addr:street":"Wilson St",
    "iso:country":"AU",
    "sg:address":"127 Wilson St",
    "sg:city":"Horsham",
    "sg:classifiers":[
        {
            "category":"Food & Beverages",
            "subcategory":"Groceries & Convenience Stores",
            "type":"Retail Goods"
        }
    ],
    "sg:phone":"+61 3 5382 1363",
    "sg:postcode":"3400",
    "sg:province":"VIC",
    "wof:name":"Natimuk Road Milk Bar",
    "wof:placetype":"venue"
},
  "geometry": {"coordinates":[142.19337463400001,-36.7168045044],"type":"Point"}
}