{
  "type": "Feature",
  "properties": {
    "addr:full":"U1/ 5-7 Boeing Pl Caboolture QLD 4510",
    "addr:housenumber":"5-7",
    "addr:postcode":"4510",
    "addr:street":"U1 /;Pl",
    "iso:country":"AU",
    "sg:address":"U1/ 5-7 Boeing Pl",
    "sg:city":"Caboolture",
    "sg:classifiers":[
        {
            "category":"Retail",
            "subcategory":"Auto Repair",
            "type":"Services"
        }
    ],
    "sg:phone":"+61 7 5495 5658",
    "sg:postcode":"4510",
    "sg:province":"QLD",
    "sg:tags":[
        "repairer",
        "motor",
        "engineer"
    ],
    "wof:name":"Rogers Mechanical Services",
    "wof:placetype":"venue"
},
  "geometry": {"coordinates":[152.979355,-27.084261],"type":"Point"}
}