{
  "type": "Feature",
  "properties": {
    "addr:full":"PO Box 460 Narromine NSW 2821",
    "addr:postcode":"2821",
    "iso:country":"AU",
    "sg:address":"PO Box 460",
    "sg:city":"Narromine",
    "sg:classifiers":[
        {
            "category":"Farming",
            "subcategory":"Farm & Veterinary Services",
            "type":"Manufacturing & Wholesale Goods"
        }
    ],
    "sg:phone":"+61 2 6889 6599",
    "sg:postcode":"2821",
    "sg:province":"NSW",
    "sg:tags":[
        "contracting"
    ],
    "wof:name":"Legion Pastroral",
    "wof:placetype":"venue"
},
  "geometry": {"coordinates":[148.24449157699999,-32.2355308533],"type":"Point"}
}