{
  "type": "Feature",
  "properties": {
    "addr:full":"215 Swan St Richmond VIC 3121",
    "addr:housenumber":"215",
    "addr:postcode":"3121",
    "addr:street":"Swan St",
    "iso:country":"AU",
    "sg:address":"215 Swan St",
    "sg:city":"Richmond",
    "sg:classifiers":[
        {
            "category":"Real Estate",
            "subcategory":"Real Estate Agent",
            "type":"Services"
        }
    ],
    "sg:phone":"+61 3 9429 4522",
    "sg:postcode":"3121",
    "sg:province":"VIC",
    "wof:name":"Wysham Partners",
    "wof:placetype":"venue"
},
  "geometry": {"coordinates":[144.99935913100001,-37.8256835938],"type":"Point"}
}