{
  "type": "Feature",
  "properties": {
    "addr:full":"320 North Boundary Rd Hamilton VIC 3300",
    "addr:housenumber":"320",
    "addr:postcode":"3300",
    "addr:street":"North Boundary Rd",
    "iso:country":"AU",
    "sg:address":"320 North Boundary Rd",
    "sg:city":"Hamilton",
    "sg:classifiers":[
        {
            "category":"Building & Trades",
            "subcategory":"Landscaping Services",
            "type":"Services"
        }
    ],
    "sg:phone":"+61 3 5572 1808",
    "sg:postcode":"3300",
    "sg:province":"VIC",
    "sg:tags":[
        "control",
        "weed"
    ],
    "wof:name":"Hamilton Ag Spraying Pty Ltd",
    "wof:placetype":"venue"
},
  "geometry": {"coordinates":[142.021575928,-37.7422294617],"type":"Point"}
}