{
  "type": "Feature",
  "properties": {
    "iso:country":"AU",
    "sg:address":"1/ 33 Alexandra Pl",
    "sg:city":"Bentley",
    "sg:classifiers":[
        {
            "category":"Mining & Drilling",
            "type":"Manufacturing & Wholesale Goods"
        }
    ],
    "sg:phone":"+61 8 9358 5866",
    "sg:postcode":"6102",
    "sg:province":"WA",
    "sg:tags":[
        "equipment",
        "quarrying",
        "supply"
    ],
    "wof:name":"Metal Mesh Pty Ltd",
    "wof:placetype":"venue"
},
  "geometry": {"coordinates":[115.92616271999999,-32.0043792725],"type":"Point"}
}