{
  "type": "Feature",
  "properties": {
    "addr:full":"46 Elgee Rd Midland WA 6056",
    "addr:housenumber":"46",
    "addr:postcode":"6056",
    "addr:street":"Elgee Rd",
    "iso:country":"AU",
    "sg:address":"46 Elgee Rd",
    "sg:city":"Midland",
    "sg:classifiers":[
        {
            "category":"Retail",
            "subcategory":"Auto Repair",
            "type":"Services"
        }
    ],
    "sg:phone":"+61 8 9250 1616",
    "sg:postcode":"6056",
    "sg:province":"WA",
    "sg:tags":[
        "transmission",
        "automotive",
        "car"
    ],
    "wof:name":"Swan Automotive Airconditioning",
    "wof:placetype":"venue"
},
  "geometry": {"coordinates":[116.018577576,-31.8948612213],"type":"Point"}
}