{
  "type": "Feature",
  "properties": {
    "addr:full":"29 Buchan Pl Kings Langley NSW 2147",
    "addr:housenumber":"29",
    "addr:postcode":"2147",
    "addr:street":"Buchan Pl",
    "iso:country":"AU",
    "sg:address":"29 Buchan Pl",
    "sg:city":"Kings Langley",
    "sg:classifiers":[
        {
            "category":"Professional",
            "subcategory":"Accounting & Tax Preparation",
            "type":"Services"
        }
    ],
    "sg:phone":"+61 2 9674 7987",
    "sg:postcode":"2147",
    "sg:province":"NSW",
    "sg:tags":[
        "bookkeeping"
    ],
    "wof:name":"CDLF Accounting Services",
    "wof:placetype":"venue"
},
  "geometry": {"coordinates":[150.93617248499999,-33.7473640442],"type":"Point"}
}