{
  "type": "Feature",
  "properties": {
    "iso:country":"AU",
    "sg:address":"29 Crosby Rd",
    "sg:city":"Albion",
    "sg:classifiers":[
        {
            "category":"Building & Trades",
            "subcategory":"Construction",
            "type":"Services"
        }
    ],
    "sg:phone":"+61 7 3862 3366",
    "sg:postcode":"4010",
    "sg:province":"QLD",
    "sg:tags":[
        "joiner",
        "carpenter"
    ],
    "wof:name":"Urban Circle Group Pty Ltd",
    "wof:placetype":"venue"
},
  "geometry": {"coordinates":[153.04437255900001,-27.4323730469],"type":"Point"}
}