{
  "type": "Feature",
  "properties": {
    "addr:full":"McPhersons Rd Tallygaroopna VIC 3634",
    "addr:postcode":"3634",
    "addr:street":"Mcphersons Rd",
    "iso:country":"AU",
    "sg:address":"McPhersons Rd",
    "sg:city":"Tallygaroopna",
    "sg:classifiers":[
        {
            "category":"Manufacturing",
            "subcategory":"Retail Goods",
            "type":"Manufacturing & Wholesale Goods"
        }
    ],
    "sg:phone":"+61 3 5826 9690",
    "sg:postcode":"3634",
    "sg:province":"VIC",
    "sg:tags":[
        "merchant",
        "pump",
        "mfrs"
    ],
    "wof:name":"Maggnum Engineering",
    "wof:placetype":"venue"
},
  "geometry": {"coordinates":[145.354736328,-36.1876182556],"type":"Point"}
}