{
  "type": "Feature",
  "properties": {
    "addr:full":"69 Jonson St Byron Bay NSW 2481",
    "addr:housenumber":"69",
    "addr:postcode":"2481",
    "addr:street":"Jonson St",
    "iso:country":"AU",
    "sg:address":"69 Jonson St",
    "sg:city":"Byron Bay",
    "sg:classifiers":[
        {
            "category":"Arts & Performance",
            "subcategory":"Theater",
            "type":"Entertainment"
        }
    ],
    "sg:phone":"+61 2 6685 6807",
    "sg:postcode":"2481",
    "sg:province":"NSW",
    "sg:tags":[
        "theatre"
    ],
    "wof:name":"Byron Community & Cultural Centre",
    "wof:placetype":"venue"
},
  "geometry": {"coordinates":[153.61285400400001,-28.6481990814],"type":"Point"}
}