{
  "type": "Feature",
  "properties": {
    "addr:full":"1 Queen St Mornington VIC 3931",
    "addr:housenumber":"1",
    "addr:postcode":"3931",
    "addr:street":"Queen St",
    "iso:country":"AU",
    "sg:address":"1 Queen St",
    "sg:city":"Mornington",
    "sg:classifiers":[
        {
            "category":"Arts & Performance",
            "subcategory":"Art Gallery",
            "type":"Entertainment"
        }
    ],
    "sg:phone":"+61 3 5976 3830",
    "sg:postcode":"3931",
    "sg:province":"VIC",
    "wof:name":"McGee's Gallery",
    "wof:placetype":"venue"
},
  "geometry": {"coordinates":[145.03706359899999,-38.2177238464],"type":"Point"}
}