{
  "type": "Feature",
  "properties": {
    "iso:country":"AU",
    "sg:address":"3 Bernard Crt",
    "sg:city":"Keilor East",
    "sg:classifiers":[
        {
            "category":"Utilities",
            "subcategory":"Electric",
            "type":"Services"
        }
    ],
    "sg:phone":"+61 3 9336 3204",
    "sg:postcode":"3033",
    "sg:province":"VIC",
    "sg:tags":[
        "electrical",
        "contractor"
    ],
    "wof:name":"Corlette P K",
    "wof:placetype":"venue"
},
  "geometry": {"coordinates":[144.86965900000001,-37.736649],"type":"Point"}
}