{
  "type": "Feature",
  "properties": {
    "iso:country":"AU",
    "sg:address":"10 Nymans Pl",
    "sg:city":"Mandurah",
    "sg:classifiers":[
        {
            "category":"Home & Garden",
            "subcategory":"Building Materials",
            "type":"Retail Goods"
        }
    ],
    "sg:phone":"+61 417 189 171",
    "sg:postcode":"6210",
    "sg:province":"WA",
    "sg:tags":[
        "plaster",
        "plasterboard",
        "supply"
    ],
    "wof:name":"All South West Coast Plasterers",
    "wof:placetype":"venue"
},
  "geometry": {"coordinates":[115.701218,-32.557758],"type":"Point"}
}