{
  "type": "Feature",
  "properties": {
    "addr:full":"137 Blues Point Rd McMahons Point NSW 2060",
    "addr:housenumber":"137",
    "addr:postcode":"2060",
    "addr:street":"Blues Point Rd",
    "iso:country":"AU",
    "sg:address":"137 Blues Point Rd",
    "sg:city":"McMahons Point",
    "sg:classifiers":[
        {
            "category":"Real Estate",
            "subcategory":"Real Estate Agent",
            "type":"Services"
        }
    ],
    "sg:phone":"+61 412 049 610",
    "sg:postcode":"2060",
    "sg:province":"NSW",
    "wof:name":"Kirribilli Real Estate Agent",
    "wof:placetype":"venue"
},
  "geometry": {"coordinates":[151.20452880900001,-33.8442726135],"type":"Point"}
}