{
  "type": "Feature",
  "properties": {
    "addr:full":"Bush Childrens Hostel 408 Williams Broken Hill NSW 2880",
    "addr:housenumber":"408",
    "addr:postcode":"2880",
    "addr:street":"Williams",
    "iso:country":"AU",
    "sg:address":"Bush Childrens Hostel 408",
    "sg:city":"Williams Broken Hill",
    "sg:classifiers":[
        {
            "category":"Travel",
            "subcategory":"Hostel",
            "type":"Entertainment"
        }
    ],
    "sg:phone":"+61 8 8087 5478",
    "sg:postcode":"2880",
    "sg:province":"NSW",
    "sg:tags":[
        "home"
    ],
    "wof:name":"Allison House",
    "wof:placetype":"venue"
},
  "geometry": {"coordinates":[141.46548461899999,-31.9583301544],"type":"Point"}
}