{
  "type": "Feature",
  "properties": {
    "addr:full":"767 Hunter St Newcastle West NSW 2302",
    "addr:housenumber":"767",
    "addr:postcode":"2302",
    "addr:street":"Hunter St",
    "iso:country":"AU",
    "sg:address":"767 Hunter St",
    "sg:city":"Newcastle West",
    "sg:classifiers":[
        {
            "category":"Professional",
            "subcategory":"Business Services",
            "type":"Services"
        }
    ],
    "sg:phone":"+61 2 4969 6011",
    "sg:postcode":"2302",
    "sg:province":"NSW",
    "sg:tags":[
        "broker"
    ],
    "wof:name":"Colin Leonard Pty Ltd",
    "wof:placetype":"venue"
},
  "geometry": {"coordinates":[151.75973500000001,-32.925488],"type":"Point"}
}