{
  "type": "Feature",
  "properties": {
    "addr:full":"Shp 1/ 98 Stirling St Bunbury WA 6230",
    "addr:housenumber":"/ 98",
    "addr:postcode":"6230",
    "addr:street":"Stirling St",
    "iso:country":"AU",
    "sg:address":"Shp 1/ 98 Stirling St",
    "sg:city":"Bunbury",
    "sg:classifiers":[
        {
            "category":"Personal",
            "subcategory":"Beauty Salon",
            "type":"Services"
        }
    ],
    "sg:phone":"+61 8 9721 3772",
    "sg:postcode":"6230",
    "sg:province":"WA",
    "sg:tags":[
        "hairdresser"
    ],
    "wof:name":"Short & Curly",
    "wof:placetype":"venue"
},
  "geometry": {"coordinates":[115.646439,-33.326965],"type":"Point"}
}