{
  "type": "Feature",
  "properties": {
    "addr:full":"458 Panmure St South Albury NSW 2640",
    "addr:housenumber":"458",
    "addr:postcode":"2640",
    "addr:street":"Panmure St",
    "iso:country":"AU",
    "sg:address":"458 Panmure St",
    "sg:city":"South Albury",
    "sg:classifiers":[
        {
            "category":"Commercial Area",
            "type":"Public Place"
        }
    ],
    "sg:phone":"+61 407 835 115",
    "sg:postcode":"2640",
    "sg:province":"NSW",
    "sg:tags":[
        "heavy",
        "carrier"
    ],
    "wof:name":"D & P Haulage Pty Ltd",
    "wof:placetype":"venue"
},
  "geometry": {"coordinates":[146.916870117,-36.0952415466],"type":"Point"}
}