{
  "type": "Feature",
  "properties": {
    "iso:country":"AU",
    "sg:address":"10 Hakea Pl",
    "sg:city":"Sorrento",
    "sg:classifiers":[
        {
            "category":"Utilities",
            "subcategory":"Water",
            "type":"Services"
        }
    ],
    "sg:phone":"+61 8 9448 1655",
    "sg:postcode":"6020",
    "sg:province":"WA",
    "sg:tags":[
        "hot",
        "system"
    ],
    "wof:name":"Northern Suburbs Plumbing",
    "wof:placetype":"venue"
},
  "geometry": {"coordinates":[115.761993408,-31.8308773041],"type":"Point"}
}