{
  "type": "Feature",
  "properties": {
    "addr:full":"27 Main St Pialba QLD 4655",
    "addr:housenumber":"27",
    "addr:postcode":"4655",
    "addr:street":"Main St",
    "iso:country":"AU",
    "sg:address":"27 Main St",
    "sg:city":"Pialba",
    "sg:classifiers":[
        {
            "category":"Retail",
            "subcategory":"Auto Rental",
            "type":"Services"
        }
    ],
    "sg:phone":"+61 7 4124 0844",
    "sg:postcode":"4655",
    "sg:province":"QLD",
    "sg:tags":[
        "car",
        "wedding"
    ],
    "wof:name":"Bow Tie Limousine & Tour Company",
    "wof:placetype":"venue"
},
  "geometry": {"coordinates":[152.837357,-25.291908],"type":"Point"}
}