{
  "type": "Feature",
  "properties": {
    "iso:country":"AU",
    "sg:address":"147 Marrickville Rd",
    "sg:city":"Marrickville",
    "sg:classifiers":[
        {
            "category":"Real Estate",
            "subcategory":"Real Estate Agent",
            "type":"Services"
        }
    ],
    "sg:phone":"+61 2 9550 9711",
    "sg:postcode":"2204",
    "sg:province":"NSW",
    "wof:name":"Ray White Real Estate Pty Ltd",
    "wof:placetype":"venue"
},
  "geometry": {"coordinates":[151.15948499999999,-33.911842],"type":"Point"}
}