{
  "type": "Feature",
  "properties": {
    "addr:full":"PO Box 495 Narooma NSW 2546",
    "addr:postcode":"2546",
    "iso:country":"AU",
    "sg:address":"PO Box 495",
    "sg:city":"Narooma",
    "sg:classifiers":[
        {
            "category":"Home & Garden",
            "subcategory":"Building Materials",
            "type":"Retail Goods"
        }
    ],
    "sg:phone":"+61 407 203 283",
    "sg:postcode":"2546",
    "sg:province":"NSW",
    "sg:tags":[
        "skylight"
    ],
    "wof:name":"Simply Skylights",
    "wof:placetype":"venue"
},
  "geometry": {"coordinates":[150.132324219,-36.2188415527],"type":"Point"}
}