{
  "type": "Feature",
  "properties": {
    "addr:full":"Shop 248-249 West Lakes Mall West Lakes SA 5021",
    "addr:housenumber":"248-249",
    "addr:postcode":"5021",
    "addr:street":"West",
    "iso:country":"AU",
    "sg:address":"Shop 248-249 West Lakes Mall",
    "sg:city":"West Lakes",
    "sg:classifiers":[
        {
            "category":"Fast Food",
            "type":"Food & Drink"
        }
    ],
    "sg:phone":"+61 8 8235 9068",
    "sg:postcode":"5021",
    "sg:province":"SA",
    "sg:tags":[
        "away",
        "take"
    ],
    "wof:name":"Southern Dragon Takeaway Foods",
    "wof:placetype":"venue"
},
  "geometry": {"coordinates":[138.49130249000001,-34.8754615784],"type":"Point"}
}