{
  "type": "Feature",
  "properties": {
    "iso:country":"AU",
    "sg:address":"80 Cartwright St",
    "sg:city":"Ingham",
    "sg:classifiers":[
        {
            "category":"Food & Beverages",
            "subcategory":"Groceries & Convenience Stores",
            "type":"Retail Goods"
        }
    ],
    "sg:phone":"+61 7 4776 2081",
    "sg:postcode":"4850",
    "sg:province":"QLD",
    "wof:name":"Nite-Owl 7 Day Store",
    "wof:placetype":"venue"
},
  "geometry": {"coordinates":[146.16427612300001,-18.6483650208],"type":"Point"}
}