{
  "type": "Feature",
  "properties": {
    "addr:full":"U1/ 5 Ferguson St Underwood QLD 4119",
    "addr:housenumber":"5",
    "addr:postcode":"4119",
    "addr:street":"U1 /;St",
    "iso:country":"AU",
    "sg:address":"U1/ 5 Ferguson St",
    "sg:city":"Underwood",
    "sg:classifiers":[
        {
            "category":"Professional",
            "subcategory":"Printing & Photocopies",
            "type":"Services"
        }
    ],
    "sg:phone":"+61 7 3423 1650",
    "sg:postcode":"4119",
    "sg:province":"QLD",
    "sg:tags":[
        "embroidery"
    ],
    "wof:name":"Top Time Embroidery Pty Ltd",
    "wof:placetype":"venue"
},
  "geometry": {"coordinates":[153.11416625999999,-27.6111736298],"type":"Point"}
}