{
  "type": "Feature",
  "properties": {
    "addr:full":"Forrest St Cunderdin WA 6407",
    "addr:postcode":"6407",
    "addr:street":"Forrest St",
    "iso:country":"AU",
    "sg:address":"Forrest St",
    "sg:city":"Cunderdin",
    "sg:classifiers":[
        {
            "category":"Museum",
            "type":"Entertainment"
        }
    ],
    "sg:phone":"+61 8 9635 1291",
    "sg:postcode":"6407",
    "sg:province":"WA",
    "wof:name":"Cunderdin Municipal Museum",
    "wof:placetype":"venue"
},
  "geometry": {"coordinates":[117.238258362,-31.6517105103],"type":"Point"}
}