{
  "type": "Feature",
  "properties": {
    "addr:full":"82 Biloela St Villawood NSW 2163",
    "addr:housenumber":"82",
    "addr:postcode":"2163",
    "addr:street":"Biloela St",
    "iso:country":"AU",
    "sg:address":"82 Biloela St",
    "sg:city":"Villawood",
    "sg:classifiers":[
        {
            "category":"Shopping",
            "subcategory":"Stationery & Office Supplies",
            "type":"Retail Goods"
        }
    ],
    "sg:phone":"+61 2 9723 9211",
    "sg:postcode":"2163",
    "sg:province":"NSW",
    "sg:tags":[
        "partition"
    ],
    "sg:website":"http://www.toiletpartitions.com.au",
    "wof:name":"Toilet Partition Industries Pty Ltd",
    "wof:placetype":"venue"
},
  "geometry": {"coordinates":[150.984832764,-33.8868408203],"type":"Point"}
}