{
  "type": "Feature",
  "properties": {
    "addr:full":"8 Endurance Ave Queanbeyan NSW 2620",
    "addr:housenumber":"8",
    "addr:postcode":"2620",
    "addr:street":"Endurance Ave",
    "iso:country":"AU",
    "sg:address":"8 Endurance Ave",
    "sg:city":"Queanbeyan",
    "sg:classifiers":[
        {
            "category":"Retail",
            "subcategory":"Auto Repair",
            "type":"Services"
        }
    ],
    "sg:phone":"+61 2 6297 6225",
    "sg:postcode":"2620",
    "sg:province":"NSW",
    "sg:tags":[
        "repairer",
        "motor",
        "engineer"
    ],
    "wof:name":"Seiffert Auto Repairs",
    "wof:placetype":"venue"
},
  "geometry": {"coordinates":[149.24502563499999,-35.3409538269],"type":"Point"}
}