{
  "type": "Feature",
  "properties": {
    "iso:country":"AU",
    "sg:address":"8 Skipton Pl",
    "sg:city":"Endeavour Hills",
    "sg:classifiers":[
        {
            "category":"Building & Trades",
            "subcategory":"Construction",
            "type":"Services"
        }
    ],
    "sg:phone":"+61 418 326 111",
    "sg:postcode":"3802",
    "sg:province":"VIC",
    "sg:tags":[
        "excavation",
        "foundation"
    ],
    "wof:name":"Advance Concrete Co Pty Ltd",
    "wof:placetype":"venue"
},
  "geometry": {"coordinates":[145.27667236299999,-37.9669418335],"type":"Point"}
}