{
  "type": "Feature",
  "properties": {
    "iso:country":"AU",
    "sg:address":"B3/3- 9 Birnie Ave",
    "sg:city":"Lidcombe",
    "sg:classifiers":[
        {
            "category":"Retail",
            "subcategory":"Repair Shop",
            "type":"Services"
        }
    ],
    "sg:phone":"+61 2 9648 4247",
    "sg:postcode":"2141",
    "sg:province":"NSW",
    "sg:tags":[
        "upholsterer"
    ],
    "wof:name":"M.D Style Upholstery Pty. Ltd.",
    "wof:placetype":"venue"
},
  "geometry": {"coordinates":[151.05931091299999,-33.857963562],"type":"Point"}
}