{
  "type": "Feature",
  "properties": {
    "addr:full":"24 Lawson Ave Beresfield NSW 2322",
    "addr:housenumber":"24",
    "addr:postcode":"2322",
    "addr:street":"Lawson Ave",
    "iso:country":"AU",
    "sg:address":"24 Lawson Ave",
    "sg:city":"Beresfield",
    "sg:classifiers":[
        {
            "category":"Autos & Motor Vehicles",
            "subcategory":"Automobile Sales",
            "type":"Retail Goods"
        }
    ],
    "sg:phone":"+61 2 4964 1311",
    "sg:postcode":"2322",
    "sg:province":"NSW",
    "sg:tags":[
        "car",
        "used"
    ],
    "wof:name":"Beresfield Used Cars",
    "wof:placetype":"venue"
},
  "geometry": {"coordinates":[151.65687560999999,-32.8020324707],"type":"Point"}
}