{
  "type": "Feature",
  "properties": {
    "iso:country":"AU",
    "sg:address":"Pine Mountain Rd",
    "sg:city":"Carindale",
    "sg:classifiers":[
        {
            "category":"Building & Trades",
            "subcategory":"Construction",
            "type":"Services"
        }
    ],
    "sg:phone":"+61 7 3216 8391",
    "sg:postcode":"4152",
    "sg:province":"QLD",
    "sg:tags":[
        "contractor"
    ],
    "wof:name":"Confitt Constructions Pty Ltd",
    "wof:placetype":"venue"
},
  "geometry": {"coordinates":[153.101760864,-27.5173435211],"type":"Point"}
}