{
  "type": "Feature",
  "properties": {
    "addr:full":"58 Neumann Rd Capalaba QLD 4157",
    "addr:housenumber":"58",
    "addr:postcode":"4157",
    "addr:street":"Neumann Rd",
    "iso:country":"AU",
    "sg:address":"58 Neumann Rd",
    "sg:city":"Capalaba",
    "sg:classifiers":[
        {
            "category":"Manufacturing",
            "subcategory":"Electronics",
            "type":"Manufacturing & Wholesale Goods"
        }
    ],
    "sg:phone":"+61 7 3823 4271",
    "sg:postcode":"4157",
    "sg:province":"QLD",
    "sg:tags":[
        "wholesaler",
        "equipment",
        "part",
        "mfrs",
        "refrigeration"
    ],
    "wof:name":"Actrol Parts",
    "wof:placetype":"venue"
},
  "geometry": {"coordinates":[153.202270508,-27.5297088623],"type":"Point"}
}