{
  "type": "Feature",
  "properties": {
    "addr:full":"189 Walsh St Albury NSW 2640",
    "addr:housenumber":"189",
    "addr:postcode":"2640",
    "addr:street":"Walsh St",
    "iso:country":"AU",
    "sg:address":"189 Walsh St",
    "sg:city":"Albury",
    "sg:classifiers":[
        {
            "category":"Banks & Credit Unions",
            "subcategory":"Financial Services",
            "type":"Services"
        }
    ],
    "sg:phone":"+61 2 6021 1276",
    "sg:postcode":"2640",
    "sg:province":"NSW",
    "sg:tags":[
        "loan",
        "finance",
        "mortgage"
    ],
    "wof:name":"Driver Business Solutions",
    "wof:placetype":"venue"
},
  "geometry": {"coordinates":[146.936965942,-36.086151123],"type":"Point"}
}