{
  "type": "Feature",
  "properties": {
    "iso:country":"AU",
    "sg:address":"547 Nurigong St",
    "sg:city":"Albury",
    "sg:classifiers":[
        {
            "category":"Autos & Motor Vehicles",
            "subcategory":"Auto Supplies",
            "type":"Retail Goods"
        }
    ],
    "sg:phone":"+61 2 6021 7551",
    "sg:postcode":"2640",
    "sg:province":"NSW",
    "sg:tags":[
        "accessory"
    ],
    "wof:name":"Brooks Motor Cars P/L",
    "wof:placetype":"venue"
},
  "geometry": {"coordinates":[146.91355895999999,-36.0910987854],"type":"Point"}
}