{
  "type": "Feature",
  "properties": {
    "addr:full":"1 Truro St Abbotsford VIC 3067",
    "addr:housenumber":"1",
    "addr:postcode":"3067",
    "addr:street":"Truro St",
    "iso:country":"AU",
    "sg:address":"1 Truro St",
    "sg:city":"Abbotsford",
    "sg:classifiers":[
        {
            "category":"Retail",
            "subcategory":"Auto Repair",
            "type":"Services"
        }
    ],
    "sg:phone":"+61 3 9419 3832",
    "sg:postcode":"3067",
    "sg:province":"VIC",
    "sg:tags":[
        "repairer",
        "motor",
        "engineer"
    ],
    "wof:name":"Scorpion Automotive Pty Ltd",
    "wof:placetype":"venue"
},
  "geometry": {"coordinates":[144.99366760300001,-37.7980957031],"type":"Point"}
}