{
  "type": "Feature",
  "properties": {
    "addr:full":"16 Hadrian Ave Blacktown NSW 2148",
    "addr:housenumber":"16",
    "addr:postcode":"2148",
    "addr:street":"Hadrian Ave",
    "iso:country":"AU",
    "sg:address":"16 Hadrian Ave",
    "sg:city":"Blacktown",
    "sg:classifiers":[
        {
            "category":"Retail",
            "subcategory":"Repair Shop",
            "type":"Services"
        }
    ],
    "sg:phone":"+61 407 881 879",
    "sg:postcode":"2148",
    "sg:province":"NSW",
    "sg:tags":[
        "mending",
        "clothing",
        "alteration"
    ],
    "wof:name":"Janelles Sewing & Alterations",
    "wof:placetype":"venue"
},
  "geometry": {"coordinates":[150.917694092,-33.7880249023],"type":"Point"}
}