{
  "type": "Feature",
  "properties": {
    "iso:country":"AU",
    "sg:address":"105 Wheatley Rd",
    "sg:city":"McKinnon",
    "sg:classifiers":[
        {
            "category":"Building & Trades",
            "subcategory":"Construction",
            "type":"Services"
        }
    ],
    "sg:phone":"+61 3 9578 6402",
    "sg:postcode":"3204",
    "sg:province":"VIC",
    "sg:tags":[
        "mural"
    ],
    "wof:name":"Ringo Art",
    "wof:placetype":"venue"
},
  "geometry": {"coordinates":[145.033905,-37.908504],"type":"Point"}
}