{
  "type": "Feature",
  "properties": {
    "addr:full":"213 Coxs Rd North Ryde NSW 2113",
    "addr:housenumber":"213",
    "addr:postcode":"2113",
    "addr:street":"Coxs Rd",
    "iso:country":"AU",
    "sg:address":"213 Coxs Rd",
    "sg:city":"North Ryde",
    "sg:classifiers":[
        {
            "category":"Fast Food",
            "type":"Food & Drink"
        }
    ],
    "sg:phone":"+61 2 9888 3565",
    "sg:postcode":"2113",
    "sg:province":"NSW",
    "sg:tags":[
        "away",
        "take"
    ],
    "wof:name":"Alpha Chickens",
    "wof:placetype":"venue"
},
  "geometry": {"coordinates":[151.121383667,-33.7942047119],"type":"Point"}
}