{
  "type": "Feature",
  "properties": {
    "iso:country":"AU",
    "sg:address":"135 Victoria Ave (Cnr Penshurst St)",
    "sg:city":"Chatswood",
    "sg:classifiers":[
        {
            "category":"Sports & Exercise",
            "subcategory":"Ski Slope",
            "type":"Entertainment"
        }
    ],
    "sg:phone":"+61 2 9417 4111",
    "sg:postcode":"2067",
    "sg:province":"NSW",
    "sg:tags":[
        "equipment",
        "hire",
        "retail",
        "snow"
    ],
    "wof:name":"Snowbound Sports",
    "wof:placetype":"venue"
},
  "geometry": {"coordinates":[151.19573974599999,-33.7922172546],"type":"Point"}
}