{
  "type": "Feature",
  "properties": {
    "iso:country":"AU",
    "sg:address":"Unit 2, 26 Rudloc Rd",
    "sg:city":"Morley",
    "sg:classifiers":[
        {
            "category":"Education",
            "subcategory":"School",
            "type":"Public Place"
        }
    ],
    "sg:phone":"+61 8 9375 2044",
    "sg:postcode":"6062",
    "sg:province":"WA",
    "sg:tags":[
        "supply"
    ],
    "wof:name":"The Canteen Guys",
    "wof:placetype":"venue"
},
  "geometry": {"coordinates":[115.897338867,-31.9014587402],"type":"Point"}
}