{
  "type": "Feature",
  "properties": {
    "addr:full":"78 Henderson Rd Alexandria NSW 2015",
    "addr:housenumber":"78",
    "addr:postcode":"2015",
    "addr:street":"Henderson Rd",
    "iso:country":"AU",
    "sg:address":"78 Henderson Rd",
    "sg:city":"Alexandria",
    "sg:classifiers":[
        {
            "category":"Home & Garden",
            "subcategory":"Furniture",
            "type":"Retail Goods"
        }
    ],
    "sg:phone":"+61 2 9319 0577",
    "sg:postcode":"2015",
    "sg:province":"NSW",
    "sg:tags":[
        "business"
    ],
    "wof:name":"Workspace Commercial Furniture Pty Ltd",
    "wof:placetype":"venue"
},
  "geometry": {"coordinates":[151.19569397000001,-33.8977088928],"type":"Point"}
}