{
  "type": "Feature",
  "properties": {
    "addr:full":"The Rocks, 56 Marina Blv Cullen Bay NT 0820",
    "addr:housenumber":"56",
    "addr:postcode":"nt 0820",
    "addr:street":"The Rocks;Marina Blv Cullen",
    "iso:country":"AU",
    "sg:address":"The Rocks, 56",
    "sg:city":"Marina Blv Cullen Bay",
    "sg:classifiers":[
        {
            "category":"Banks & Credit Unions",
            "subcategory":"Financial Services",
            "type":"Services"
        }
    ],
    "sg:phone":"+61 8 8942 0111",
    "sg:postcode":"0820",
    "sg:province":"NT",
    "sg:tags":[
        "annuity",
        "rollover",
        "superannuation",
        "consultant"
    ],
    "wof:name":"Wills Financial Planning",
    "wof:placetype":"venue"
},
  "geometry": {"coordinates":[130.82249450699999,-12.4509134293],"type":"Point"}
}