{
  "type": "Feature",
  "properties": {
    "addr:full":"Cnr Gilbert Rd & Edwards St Reservoir VIC 3073",
    "addr:postcode":"3073",
    "addr:street":"Cnr Gilbert Rd & Edwards St",
    "iso:country":"AU",
    "sg:address":"Cnr Gilbert Rd & Edwards St",
    "sg:city":"Reservoir",
    "sg:classifiers":[
        {
            "category":"Arena",
            "subcategory":"Sports Club",
            "type":"Entertainment"
        }
    ],
    "sg:phone":"+61 3 9471 0674",
    "sg:postcode":"3073",
    "sg:province":"VIC",
    "sg:tags":[
        "australian",
        "football",
        "rule"
    ],
    "wof:name":"West Preston Football Club",
    "wof:placetype":"venue"
},
  "geometry": {"coordinates":[144.99234008799999,-37.716468811],"type":"Point"}
}