{
  "type": "Feature",
  "properties": {
    "addr:full":"66 Nicholson St Brunswick East VIC 3057",
    "addr:housenumber":"66",
    "addr:postcode":"3057",
    "addr:street":"Nicholson St",
    "iso:country":"AU",
    "sg:address":"66 Nicholson St",
    "sg:city":"Brunswick East",
    "sg:classifiers":[
        {
            "category":"Health Services",
            "subcategory":"Health Practitioner",
            "type":"Services"
        }
    ],
    "sg:phone":"+61 3 9380 9111",
    "sg:postcode":"3057",
    "sg:province":"VIC",
    "sg:tags":[
        "myotherapy"
    ],
    "wof:name":"Dijana Veljanovska",
    "wof:placetype":"venue"
},
  "geometry": {"coordinates":[144.979705811,-37.7711753845],"type":"Point"}
}