{
  "type": "Feature",
  "properties": {
    "addr:full":"101 Rockhampton Rd Yeppoon QLD 4703",
    "addr:housenumber":"101",
    "addr:postcode":"4703",
    "addr:street":"Rockhampton Rd",
    "iso:country":"AU",
    "sg:address":"101 Rockhampton Rd",
    "sg:city":"Yeppoon",
    "sg:classifiers":[
        {
            "category":"Autos & Motor Vehicles",
            "subcategory":"Fuel & Gas Station",
            "type":"Retail Goods"
        }
    ],
    "sg:phone":"+61 7 4939 4714",
    "sg:postcode":"4703",
    "sg:province":"QLD",
    "wof:name":"United Petroleum Yeppoon",
    "wof:placetype":"venue"
},
  "geometry": {"coordinates":[150.728225708,-23.1328372955],"type":"Point"}
}