{
  "type": "Feature",
  "properties": {
    "addr:full":"11 Produce Rd Humpty Doo NT 0836",
    "addr:housenumber":"11",
    "addr:postcode":"nt 0836",
    "addr:street":"Produce Rd",
    "iso:country":"AU",
    "sg:address":"11 Produce Rd",
    "sg:city":"Humpty Doo",
    "sg:classifiers":[
        {
            "category":"Farming",
            "subcategory":"Livestock Farm",
            "type":"Manufacturing & Wholesale Goods"
        }
    ],
    "sg:phone":"+61 8 8988 2767",
    "sg:postcode":"0836",
    "sg:province":"NT",
    "sg:tags":[
        "breeder",
        "horse",
        "stud"
    ],
    "wof:name":"Oak Haven Miniture Horse & Pony Stud",
    "wof:placetype":"venue"
},
  "geometry": {"coordinates":[131.11859100000001,-12.573622],"type":"Point"}
}