{
  "type": "Feature",
  "properties": {
    "iso:country":"AU",
    "sg:address":"11 Produce Rd",
    "sg:city":"Humpty Doo",
    "sg:classifiers":[
        {
            "category":"Farming",
            "subcategory":"Livestock Farm",
            "type":"Manufacturing & Wholesale Goods"
        }
    ],
    "sg:phone":"+61 8 8988 2767",
    "sg:postcode":"0836",
    "sg:province":"NT",
    "sg:tags":[
        "breeder",
        "horse",
        "stud"
    ],
    "wof:name":"Oak Haven Miniture Horse & Pony Stud",
    "wof:placetype":"venue"
},
  "geometry": {"coordinates":[131.118591,-12.573622],"type":"Point"}
}