{
  "type": "Feature",
  "properties": {
    "iso:country":"AU",
    "sg:address":"33 Anderson St",
    "sg:city":"Templestowe",
    "sg:classifiers":[
        {
            "category":"Banks & Credit Unions",
            "subcategory":"Financial Services",
            "type":"Services"
        }
    ],
    "sg:phone":"+61 3 9846 6542",
    "sg:postcode":"3106",
    "sg:province":"VIC",
    "sg:tags":[
        "planning"
    ],
    "wof:name":"Townshend & Associates P/L",
    "wof:placetype":"venue"
},
  "geometry": {"coordinates":[145.13021850600001,-37.7564353943],"type":"Point"}
}