{
  "type": "Feature",
  "properties": {
    "addr:full":"17 Georgetown Rd Georgetown NSW 2298",
    "addr:housenumber":"17",
    "addr:postcode":"2298",
    "addr:street":"Georgetown Rd",
    "iso:country":"AU",
    "sg:address":"17 Georgetown Rd",
    "sg:city":"Georgetown",
    "sg:classifiers":[
        {
            "category":"Shopping",
            "subcategory":"Baby Store",
            "type":"Retail Goods"
        }
    ],
    "sg:phone":"+61 2 4967 4999",
    "sg:postcode":"2298",
    "sg:province":"NSW",
    "sg:tags":[
        "children's",
        "wear"
    ],
    "wof:name":"Oonka-Poonka Clothing Co",
    "wof:placetype":"venue"
},
  "geometry": {"coordinates":[151.732055664,-32.9105110168],"type":"Point"}
}