{
  "type": "Feature",
  "properties": {
    "addr:full":"Shp21 / 1 Springfield Lakes Blv Springfield Lakes QLD 4300",
    "addr:housenumber":"1",
    "addr:postcode":"4300",
    "addr:street":"Springfield Lakes Blv Springfield",
    "iso:country":"AU",
    "sg:address":"Shp21",
    "sg:city":"/ 1 Springfield Lakes Blv Springfield Lakes",
    "sg:classifiers":[
        {
            "category":"Shopping",
            "subcategory":"Clothing, Apparel, & Fashions",
            "type":"Retail Goods"
        }
    ],
    "sg:phone":"+61 7 3818 9255",
    "sg:postcode":"4300",
    "sg:province":"QLD",
    "sg:tags":[
        "lady",
        "wear"
    ],
    "wof:name":"Georgie Girl Ladies Fashion Pty Ltd",
    "wof:placetype":"venue"
},
  "geometry": {"coordinates":[152.91960144000001,-27.6670856476],"type":"Point"}
}