{
  "type": "Feature",
  "properties": {
    "addr:full":"Lvl 1, 9 Waratah St Mona Vale NSW 2103",
    "addr:housenumber":"9",
    "addr:postcode":"2103",
    "addr:street":"Waratah St",
    "iso:country":"AU",
    "sg:address":"Lvl 1, 9 Waratah St",
    "sg:city":"Mona Vale",
    "sg:classifiers":[
        {
            "category":"Banks & Credit Unions",
            "subcategory":"Financial Services",
            "type":"Services"
        }
    ],
    "sg:phone":"+61 2 9997 4647",
    "sg:postcode":"2103",
    "sg:province":"NSW",
    "sg:tags":[
        "planning"
    ],
    "wof:name":"Genesys Wealth Advisers",
    "wof:placetype":"venue"
},
  "geometry": {"coordinates":[151.30331420900001,-33.6772232056],"type":"Point"}
}