{
  "type": "Feature",
  "properties": {
    "addr:full":"19 Calga St Roseville Chase NSW 2069",
    "addr:housenumber":"19",
    "addr:postcode":"2069",
    "addr:street":"Calga St",
    "iso:country":"AU",
    "sg:address":"19 Calga St",
    "sg:city":"Roseville Chase",
    "sg:classifiers":[
        {
            "category":"Personal",
            "subcategory":"Day Spa",
            "type":"Services"
        }
    ],
    "sg:phone":"+61 2 9417 2011",
    "sg:postcode":"2069",
    "sg:province":"NSW",
    "wof:name":"Time Out Day Spa",
    "wof:placetype":"venue"
},
  "geometry": {"coordinates":[151.20281982399999,-33.7791442871],"type":"Point"}
}