{
  "type": "Feature",
  "properties": {
    "addr:full":"170 Riversdale Rd Cambewarra West NSW 2540",
    "addr:housenumber":"170",
    "addr:postcode":"2540",
    "addr:street":"Riversdale Rd",
    "iso:country":"AU",
    "sg:address":"170 Riversdale Rd",
    "sg:city":"Cambewarra West",
    "sg:classifiers":[
        {
            "category":"Museum",
            "type":"Entertainment"
        }
    ],
    "sg:phone":"+61 2 4422 2100",
    "sg:postcode":"2540",
    "sg:province":"NSW",
    "wof:name":"Bundanon",
    "wof:placetype":"venue"
},
  "geometry": {"coordinates":[150.50140380900001,-34.8575668335],"type":"Point"}
}