{
  "type": "Feature",
  "properties": {
    "iso:country":"AU",
    "sg:address":"3B/ 229 Robinson Rd",
    "sg:city":"East Geebung",
    "sg:classifiers":[
        {
            "category":"Home & Garden",
            "subcategory":"Garden Supply",
            "type":"Retail Goods"
        }
    ],
    "sg:phone":"+61 7 3865 3066",
    "sg:postcode":"4034",
    "sg:province":"QLD",
    "sg:tags":[
        "equipment"
    ],
    "wof:name":"Martin Lattice & Balustrading",
    "wof:placetype":"venue"
},
  "geometry": {"coordinates":[153.048843,-27.368479],"type":"Point"}
}