{
  "type": "Feature",
  "properties": {
    "addr:full":"9 Kangaroo St Raymond Terrace NSW 2324",
    "addr:housenumber":"9",
    "addr:postcode":"2324",
    "addr:street":"Kangaroo St",
    "iso:country":"AU",
    "sg:address":"9 Kangaroo St",
    "sg:city":"Raymond Terrace",
    "sg:classifiers":[
        {
            "category":"Professional",
            "subcategory":"Computer Services",
            "type":"Services"
        }
    ],
    "sg:phone":"+61 2 4987 2677",
    "sg:postcode":"2324",
    "sg:province":"NSW",
    "sg:tags":[
        "repairs",
        "upgrade",
        "equipment"
    ],
    "wof:name":"Saturday Silicon",
    "wof:placetype":"venue"
},
  "geometry": {"coordinates":[151.746917725,-32.7589302063],"type":"Point"}
}