{
  "type": "Feature",
  "properties": {
    "addr:full":"3a Cardigan St Somerset TAS 7322",
    "addr:housenumber":"3a",
    "addr:postcode":"7322",
    "addr:street":"Cardigan St",
    "iso:country":"AU",
    "sg:address":"3a Cardigan St",
    "sg:city":"Somerset",
    "sg:classifiers":[
        {
            "category":"Utilities",
            "subcategory":"Water",
            "type":"Services"
        }
    ],
    "sg:phone":"+61 3 6435 1109",
    "sg:postcode":"7322",
    "sg:province":"TAS",
    "sg:tags":[
        "cartage"
    ],
    "wof:name":"Bob Whiteroad",
    "wof:placetype":"venue"
},
  "geometry": {"coordinates":[145.826584,-41.044674],"type":"Point"}
}