{
  "type": "Feature",
  "properties": {
    "addr:full":"6 Haileybury Crt Keysborough VIC 3173",
    "addr:housenumber":"6",
    "addr:postcode":"3173",
    "addr:street":"Haileybury Crt",
    "iso:country":"AU",
    "sg:address":"6 Haileybury Crt",
    "sg:city":"Keysborough",
    "sg:classifiers":[
        {
            "category":"Home & Garden",
            "subcategory":"Building Materials",
            "type":"Retail Goods"
        }
    ],
    "sg:phone":"+61 419 364 145",
    "sg:postcode":"3173",
    "sg:province":"VIC",
    "sg:tags":[
        "fitting",
        "door"
    ],
    "wof:name":"Builders Maintenance",
    "wof:placetype":"venue"
},
  "geometry": {"coordinates":[145.165725708,-37.9916915894],"type":"Point"}
}