{
  "type": "Feature",
  "properties": {
    "iso:country":"AU",
    "sg:address":"Berkeley Vale, New South Wales, 2261",
    "sg:city":"Berkeley Vale",
    "sg:classifiers":[
        {
            "category":"Personal",
            "subcategory":"Nail Salon",
            "type":"Services"
        }
    ],
    "sg:phone":"+61 2 4389 8882",
    "sg:postcode":"2261",
    "sg:province":"NSW",
    "sg:tags":[
        "artificial"
    ],
    "wof:name":"Kays Claws",
    "wof:placetype":"venue"
},
  "geometry": {"coordinates":[151.42828399999999,-33.341709],"type":"Point"}
}