{
  "type": "Feature",
  "properties": {
    "addr:full":"68 Dampier St Tamworth NSW 2340",
    "addr:housenumber":"68",
    "addr:postcode":"2340",
    "addr:street":"Dampier St",
    "iso:country":"AU",
    "sg:address":"68 Dampier St",
    "sg:city":"Tamworth",
    "sg:classifiers":[
        {
            "category":"Manufacturing",
            "subcategory":"Tools & Machinery",
            "type":"Manufacturing & Wholesale Goods"
        }
    ],
    "sg:phone":"+61 2 6765 5442",
    "sg:postcode":"2340",
    "sg:province":"NSW",
    "sg:tags":[
        "manufactured",
        "specially",
        "designed"
    ],
    "wof:name":"Taminda Hydraulics & Engineering",
    "wof:placetype":"venue"
},
  "geometry": {"coordinates":[150.898605347,-31.0916423798],"type":"Point"}
}