{
  "type": "Feature",
  "properties": {
    "iso:country":"AU",
    "sg:address":"222 Denholms Rd",
    "sg:city":"Cambridge",
    "sg:classifiers":[
        {
            "category":"Utilities",
            "subcategory":"Fuel Oil & Lpg",
            "type":"Services"
        }
    ],
    "sg:phone":"+61 3 6248 5432",
    "sg:postcode":"7170",
    "sg:province":"TAS",
    "sg:tags":[
        "olive"
    ],
    "wof:name":"Island Olive Grove Tasmania",
    "wof:placetype":"venue"
},
  "geometry": {"coordinates":[147.43682861299999,-42.8053436279],"type":"Point"}
}