{
  "type": "Feature",
  "properties": {
    "addr:full":"5 Kingston St Mordialloc VIC 3195",
    "addr:housenumber":"5",
    "addr:postcode":"3195",
    "addr:street":"Kingston St",
    "iso:country":"AU",
    "sg:address":"5 Kingston St",
    "sg:city":"Mordialloc",
    "sg:classifiers":[
        {
            "category":"Arts & Performance",
            "subcategory":"Theater",
            "type":"Entertainment"
        }
    ],
    "sg:phone":"+61 3 9687 4709",
    "sg:postcode":"3195",
    "sg:province":"VIC",
    "sg:tags":[
        "theatre"
    ],
    "wof:name":"Jack Of All Trades Theatre",
    "wof:placetype":"venue"
},
  "geometry": {"coordinates":[145.094207764,-37.9936790466],"type":"Point"}
}