{
  "type": "Feature",
  "properties": {
    "iso:country":"AU",
    "sg:address":"Unit 25/ 20 Fairway Dr",
    "sg:city":"Clear Island Waters",
    "sg:classifiers":[
        {
            "category":"Building & Trades",
            "subcategory":"Construction",
            "type":"Services"
        }
    ],
    "sg:phone":"+61 433 411 776",
    "sg:postcode":"4226",
    "sg:province":"QLD",
    "sg:tags":[
        "industrial",
        "commercial",
        "air conditioning"
    ],
    "wof:name":"Perfect Air Installations",
    "wof:placetype":"venue"
},
  "geometry": {"coordinates":[153.40240478499999,-28.0350551605],"type":"Point"}
}