{
  "type": "Feature",
  "properties": {
    "iso:country":"AU",
    "sg:address":"1246 Hay St",
    "sg:city":"West Perth",
    "sg:classifiers":[
        {
            "category":"Food & Beverages",
            "subcategory":"Bakery",
            "type":"Retail Goods"
        }
    ],
    "sg:phone":"+61 8 9321 6386",
    "sg:postcode":"6005",
    "sg:province":"WA",
    "sg:tags":[
        "cake",
        "shop",
        "pastry"
    ],
    "wof:name":"West End Cake Shop",
    "wof:placetype":"venue"
},
  "geometry": {"coordinates":[115.839988709,-31.9481220245],"type":"Point"}
}