{
  "type": "Feature",
  "properties": {
    "addr:full":"185- 187 Wellington Rd East Brisbane QLD 4169",
    "addr:housenumber":"187",
    "addr:postcode":"4169",
    "addr:street":"Wellington Rd",
    "iso:country":"AU",
    "sg:address":"185- 187 Wellington Rd",
    "sg:city":"East Brisbane",
    "sg:classifiers":[
        {
            "category":"Shopping",
            "subcategory":"Gifts & Souvenirs",
            "type":"Retail Goods"
        }
    ],
    "sg:phone":"+61 7 3891 7300",
    "sg:postcode":"4169",
    "sg:province":"QLD",
    "sg:tags":[
        "shop",
        "supply"
    ],
    "wof:name":"Chameleon House.",
    "wof:placetype":"venue"
},
  "geometry": {"coordinates":[153.04119873100001,-27.4805603027],"type":"Point"}
}