{
  "type": "Feature",
  "properties": {
    "addr:full":"8 Brown Pde Ashgrove QLD 4060",
    "addr:housenumber":"8",
    "addr:postcode":"4060",
    "addr:street":"Brown Pde",
    "iso:country":"AU",
    "sg:address":"8 Brown Pde",
    "sg:city":"Ashgrove",
    "sg:classifiers":[
        {
            "category":"Building & Trades",
            "subcategory":"Landscaping Services",
            "type":"Services"
        }
    ],
    "sg:phone":"+61 7 3366 8181",
    "sg:postcode":"4060",
    "sg:province":"QLD",
    "sg:tags":[
        "designer",
        "landscape",
        "contractor"
    ],
    "wof:name":"Ithaca Landscapes",
    "wof:placetype":"venue"
},
  "geometry": {"coordinates":[152.98965454099999,-27.4354019165],"type":"Point"}
}