{
  "type": "Feature",
  "properties": {
    "addr:full":"44 Broughton St Campbelltown NSW 2560",
    "addr:housenumber":"44",
    "addr:postcode":"2560",
    "addr:street":"Broughton St",
    "iso:country":"AU",
    "sg:address":"44 Broughton St",
    "sg:city":"Campbelltown",
    "sg:classifiers":[
        {
            "category":"Social Services",
            "subcategory":"Child Care",
            "type":"Services"
        }
    ],
    "sg:phone":"+61 2 4645 4000",
    "sg:postcode":"2560",
    "sg:province":"NSW",
    "wof:name":"Child Care Services",
    "wof:placetype":"venue"
},
  "geometry": {"coordinates":[150.81936645499999,-34.0661582947],"type":"Point"}
}