{
  "type": "Feature",
  "properties": {
    "addr:full":"Corner of Oxley Dr & Brisbane Rd Biggera Waters QLD 4216",
    "addr:postcode":"4216",
    "addr:street":"Corner;Rd",
    "iso:country":"AU",
    "sg:address":"Corner of Oxley Dr & Brisbane Rd",
    "sg:city":"Biggera Waters",
    "sg:classifiers":[
        {
            "category":"Retail",
            "subcategory":"Repair Shop",
            "type":"Services"
        }
    ],
    "sg:phone":"+61 7 5537 6455",
    "sg:postcode":"4216",
    "sg:province":"QLD",
    "sg:tags":[
        "mending",
        "clothing",
        "alteration"
    ],
    "wof:name":"Harbour Town Clothing Alterations",
    "wof:placetype":"venue"
},
  "geometry": {"coordinates":[153.39073181099999,-27.9331378937],"type":"Point"}
}