{
  "type": "Feature",
  "properties": {
    "addr:full":"Shp 17/ 39 Queen St Ulverstone TAS 7315",
    "addr:housenumber":"17 / 39",
    "addr:postcode":"7315",
    "addr:street":"Queen St",
    "iso:country":"AU",
    "sg:address":"Shp 17/ 39 Queen St",
    "sg:city":"Ulverstone",
    "sg:classifiers":[
        {
            "category":"Shopping",
            "type":"Retail Goods"
        }
    ],
    "sg:phone":"+61 3 6425 2444",
    "sg:postcode":"7315",
    "sg:province":"TAS",
    "sg:tags":[
        "clearance",
        "factory",
        "outlet"
    ],
    "wof:name":"Small Change Factory Outlet Super Store",
    "wof:placetype":"venue"
},
  "geometry": {"coordinates":[146.16319274899999,-41.1515007019],"type":"Point"}
}