{
  "type": "Feature",
  "properties": {
    "addr:full":"16 Semaphore Rd Semaphore SA 5019",
    "addr:housenumber":"16",
    "addr:postcode":"5019",
    "addr:street":"Semaphore Rd",
    "iso:country":"AU",
    "sg:address":"16 Semaphore Rd",
    "sg:city":"Semaphore",
    "sg:classifiers":[
        {
            "category":"Food & Beverages",
            "subcategory":"Supermarket",
            "type":"Retail Goods"
        }
    ],
    "sg:phone":"+61 8 8241 4000",
    "sg:postcode":"5019",
    "sg:province":"SA",
    "sg:tags":[
        "grocery",
        "store"
    ],
    "wof:name":"Foodland Supermarkets",
    "wof:placetype":"venue"
},
  "geometry": {"coordinates":[138.48472595199999,-34.8392677307],"type":"Point"}
}