{
  "type": "Feature",
  "properties": {
    "addr:full":"145 Gouger St Adelaide SA 5000",
    "addr:housenumber":"145",
    "addr:postcode":"5000",
    "addr:street":"Gouger St",
    "iso:country":"AU",
    "sg:address":"145 Gouger St",
    "sg:city":"Adelaide",
    "sg:classifiers":[
        {
            "category":"Retail",
            "subcategory":"Auto Repair",
            "type":"Services"
        }
    ],
    "sg:phone":"+61 8 8212 0200",
    "sg:postcode":"5000",
    "sg:province":"SA",
    "sg:tags":[
        "muffler",
        "exhaust",
        "system"
    ],
    "wof:name":"Exhaust Techniques",
    "wof:placetype":"venue"
},
  "geometry": {"coordinates":[138.594146728,-34.9302864075],"type":"Point"}
}