{
  "type": "Feature",
  "properties": {
    "addr:full":"601 Sturt St Ballarat VIC 3350",
    "addr:housenumber":"601",
    "addr:postcode":"3350",
    "addr:street":"Sturt St",
    "iso:country":"AU",
    "sg:address":"601 Sturt St",
    "sg:city":"Ballarat",
    "sg:classifiers":[
        {
            "category":"Real Estate",
            "subcategory":"Architect",
            "type":"Services"
        }
    ],
    "sg:phone":"+61 3 5332 1981",
    "sg:postcode":"3350",
    "sg:province":"VIC",
    "sg:tags":[
        "building",
        "designer"
    ],
    "wof:name":"John B Vernon Architect",
    "wof:placetype":"venue"
},
  "geometry": {"coordinates":[143.851685,-37.561539],"type":"Point"}
}