{
  "type": "Feature",
  "properties": {
    "addr:full":"53 March St Richmond NSW 2753",
    "addr:housenumber":"53",
    "addr:postcode":"2753",
    "addr:street":"March St",
    "iso:country":"AU",
    "sg:address":"53 March St",
    "sg:city":"Richmond",
    "sg:classifiers":[
        {
            "category":"Retail",
            "subcategory":"Auto Repair",
            "type":"Services"
        }
    ],
    "sg:phone":"+61 2 4578 3683",
    "sg:postcode":"2753",
    "sg:province":"NSW",
    "sg:tags":[
        "fuel",
        "petrol",
        "injection"
    ],
    "wof:name":"Lennox Automotive Service & Repairs",
    "wof:placetype":"venue"
},
  "geometry": {"coordinates":[150.75352477999999,-33.5997543335],"type":"Point"}
}