{
  "type": "Feature",
  "properties": {
    "addr:full":"108 Mort St Toowoomba QLD 4350",
    "addr:housenumber":"108",
    "addr:postcode":"4350",
    "addr:street":"Mort St",
    "iso:country":"AU",
    "sg:address":"108 Mort St",
    "sg:city":"Toowoomba",
    "sg:classifiers":[
        {
            "category":"Organizations",
            "subcategory":"Non-profit Organization",
            "type":"Services"
        }
    ],
    "sg:phone":"+61 7 4659 5476",
    "sg:postcode":"4350",
    "sg:province":"QLD",
    "sg:tags":[
        "support",
        "disability",
        "organisation"
    ],
    "wof:name":"Quality Lifestyle Support",
    "wof:placetype":"venue"
},
  "geometry": {"coordinates":[151.95031700000001,-27.552198],"type":"Point"}
}