{
  "type": "Feature",
  "properties": {
    "addr:full":"2 Roslyn St West Leederville WA 6007",
    "addr:housenumber":"2",
    "addr:postcode":"6007",
    "addr:street":"Roslyn St West",
    "iso:country":"AU",
    "sg:address":"2 Roslyn St",
    "sg:city":"West Leederville",
    "sg:classifiers":[
        {
            "category":"Professional",
            "subcategory":"Business Services",
            "type":"Services"
        }
    ],
    "sg:phone":"+61 8 9388 2868",
    "sg:postcode":"6007",
    "sg:province":"WA",
    "sg:tags":[
        "fashion",
        "agent"
    ],
    "wof:name":"Donaldson Graeme Agencies Pty Ltd",
    "wof:placetype":"venue"
},
  "geometry": {"coordinates":[115.83341217,-31.9418735504],"type":"Point"}
}