{
  "type": "Feature",
  "properties": {
    "addr:full":"Albert St Brunswick VIC 3056",
    "addr:postcode":"3056",
    "addr:street":"Albert St",
    "iso:country":"AU",
    "sg:address":"Albert St",
    "sg:city":"Brunswick",
    "sg:classifiers":[
        {
            "category":"Arena",
            "subcategory":"Sports Club",
            "type":"Entertainment"
        }
    ],
    "sg:phone":"+61 419 885 023",
    "sg:postcode":"3056",
    "sg:province":"VIC",
    "sg:tags":[
        "defence",
        "supply",
        "self",
        "instruction",
        "martial art"
    ],
    "wof:name":"Goju Kai Karate Do",
    "wof:placetype":"venue"
},
  "geometry": {"coordinates":[144.962280273,-37.7688789368],"type":"Point"}
}