{
  "type": "Feature",
  "properties": {
    "addr:full":"175 Oxford St Leederville WA 6007",
    "addr:housenumber":"175",
    "addr:postcode":"6007",
    "addr:street":"Oxford St",
    "iso:country":"AU",
    "sg:address":"175 Oxford St",
    "sg:city":"Leederville",
    "sg:classifiers":[
        {
            "category":"Restaurant",
            "type":"Food & Drink"
        }
    ],
    "sg:phone":"+61 8 9444 3122",
    "sg:postcode":"6007",
    "sg:province":"WA",
    "wof:name":"Anna Vietnamese Restaurant",
    "wof:placetype":"venue"
},
  "geometry": {"coordinates":[115.841072083,-31.9354190826],"type":"Point"}
}