{
  "type": "Feature",
  "properties": {
    "addr:full":"373 Mann St Gosford NSW 2250",
    "addr:housenumber":"373",
    "addr:postcode":"2250",
    "addr:street":"Mann St",
    "iso:country":"AU",
    "sg:address":"373 Mann St",
    "sg:city":"Gosford",
    "sg:classifiers":[
        {
            "category":"Autos & Motor Vehicles",
            "subcategory":"Automobile Sales",
            "type":"Retail Goods"
        }
    ],
    "sg:phone":"+61 2 4323 1576",
    "sg:postcode":"2250",
    "sg:province":"NSW",
    "sg:tags":[
        "car",
        "new"
    ],
    "wof:name":"Chrysler",
    "wof:placetype":"venue"
},
  "geometry": {"coordinates":[151.344024658,-33.4169502258],"type":"Point"}
}