{
  "type": "Feature",
  "properties": {
    "addr:full":"13 Actinotus Ave Caringbah NSW 2229",
    "addr:housenumber":"13",
    "addr:postcode":"2229",
    "addr:street":"Actinotus Ave",
    "iso:country":"AU",
    "sg:address":"13 Actinotus Ave",
    "sg:city":"Caringbah",
    "sg:classifiers":[
        {
            "category":"Banks & Credit Unions",
            "subcategory":"Bank",
            "type":"Services"
        }
    ],
    "sg:phone":"+61 2 9540 1999",
    "sg:postcode":"2229",
    "sg:province":"NSW",
    "sg:tags":[
        "line",
        "marking",
        "road"
    ],
    "wof:name":"Line-O-Dot",
    "wof:placetype":"venue"
},
  "geometry": {"coordinates":[151.125762939,-34.0542259216],"type":"Point"}
}