{
  "type": "Feature",
  "properties": {
    "addr:full":"23 Daly St Darwin NT 0800",
    "addr:housenumber":"23",
    "addr:postcode":"nt 0800",
    "addr:street":"Daly St",
    "iso:country":"AU",
    "sg:address":"23 Daly St",
    "sg:city":"Darwin",
    "sg:classifiers":[
        {
            "category":"Autos & Motor Vehicles",
            "subcategory":"Automobile Sales",
            "type":"Retail Goods"
        }
    ],
    "sg:phone":"+61 8 8941 4888",
    "sg:postcode":"0800",
    "sg:province":"NT",
    "sg:tags":[
        "car",
        "used"
    ],
    "wof:name":"Darwin Small Car Centre",
    "wof:placetype":"venue"
},
  "geometry": {"coordinates":[130.836761475,-12.4567527771],"type":"Point"}
}