{
  "type": "Feature",
  "properties": {
    "addr:full":"5 Maritime Crt Gillman SA 5013",
    "addr:housenumber":"5",
    "addr:postcode":"5013",
    "addr:street":"Maritime Crt",
    "iso:country":"AU",
    "sg:address":"5 Maritime Crt",
    "sg:city":"Gillman",
    "sg:classifiers":[
        {
            "category":"Retail",
            "subcategory":"Auto Repair",
            "type":"Services"
        }
    ],
    "sg:phone":"+61 8 8447 2844",
    "sg:postcode":"5013",
    "sg:province":"SA",
    "sg:tags":[
        "electrical"
    ],
    "wof:name":"S.A. Auto Electrics",
    "wof:placetype":"venue"
},
  "geometry": {"coordinates":[138.52557373100001,-34.8429794312],"type":"Point"}
}