{
  "type": "Feature",
  "properties": {
    "addr:full":"161 Main St Blacktown NSW 2148",
    "addr:housenumber":"161",
    "addr:postcode":"2148",
    "addr:street":"Main St",
    "iso:country":"AU",
    "sg:address":"161 Main St",
    "sg:city":"Blacktown",
    "sg:classifiers":[
        {
            "category":"Autos & Motor Vehicles",
            "subcategory":"Automobile Sales",
            "type":"Retail Goods"
        }
    ],
    "sg:phone":"+61 2 9622 6333",
    "sg:postcode":"2148",
    "sg:province":"NSW",
    "sg:tags":[
        "car",
        "used"
    ],
    "wof:name":"Blacktown Budget Cars",
    "wof:placetype":"venue"
},
  "geometry": {"coordinates":[150.91395568900001,-33.7729225159],"type":"Point"}
}