{
  "type": "Feature",
  "properties": {
    "addr:full":"10 Mitchell Hwy Nyngan NSW 2825",
    "addr:housenumber":"10",
    "addr:postcode":"2825",
    "addr:street":"Mitchell Hwy",
    "iso:country":"AU",
    "sg:address":"10 Mitchell Hwy",
    "sg:city":"Nyngan",
    "sg:classifiers":[
        {
            "category":"Autos & Motor Vehicles",
            "subcategory":"Automobile Sales",
            "type":"Retail Goods"
        }
    ],
    "sg:phone":"+61 2 6832 1477",
    "sg:postcode":"2825",
    "sg:province":"NSW",
    "sg:tags":[
        "car",
        "used"
    ],
    "wof:name":"Nyngan Toyota",
    "wof:placetype":"venue"
},
  "geometry": {"coordinates":[147.20242309599999,-31.5647945404],"type":"Point"}
}