{
  "type": "Feature",
  "properties": {
    "addr:full":"211 Markeri St Mermaid Waters QLD 4218",
    "addr:housenumber":"211",
    "addr:postcode":"4218",
    "addr:street":"Markeri St",
    "iso:country":"AU",
    "sg:address":"211 Markeri St",
    "sg:city":"Mermaid Waters",
    "sg:classifiers":[
        {
            "category":"Health Services",
            "subcategory":"Medical Lab",
            "type":"Services"
        }
    ],
    "sg:phone":"+61 7 5572 3534",
    "sg:postcode":"4218",
    "sg:province":"QLD",
    "sg:tags":[
        "laboratory",
        "dental"
    ],
    "wof:name":"Denture Direct",
    "wof:placetype":"venue"
},
  "geometry": {"coordinates":[153.42376709000001,-28.0476837158],"type":"Point"}
}