{
  "type": "Feature",
  "properties": {
    "addr:full":"Shop 10 Astra House Cnr Jack Hore Pl & Hovell St Wodonga VIC 3690",
    "addr:housenumber":"shop 10",
    "addr:postcode":"3690",
    "addr:street":"Cnr Jack Hore Pl & Hovell St",
    "iso:country":"AU",
    "sg:address":"Shop 10 Astra House Cnr Jack Hore Pl & Hovell St",
    "sg:city":"Wodonga",
    "sg:classifiers":[
        {
            "category":"Organizations",
            "subcategory":"Community Association",
            "type":"Services"
        }
    ],
    "sg:phone":"+61 2 6056 2802",
    "sg:postcode":"3690",
    "sg:province":"VIC",
    "sg:tags":[
        "organisation",
        "family",
        "welfare"
    ],
    "wof:name":"Resolve Family & Adolescent Counselling",
    "wof:placetype":"venue"
},
  "geometry": {"coordinates":[146.88851928700001,-36.1207122803],"type":"Point"}
}