{
  "type": "Feature",
  "properties": {
    "addr:full":"2B Staley St Brunswick VIC 3056",
    "addr:housenumber":"2b",
    "addr:postcode":"3056",
    "addr:street":"Staley St",
    "iso:country":"AU",
    "sg:address":"2B Staley St",
    "sg:city":"Brunswick",
    "sg:classifiers":[
        {
            "category":"Education",
            "subcategory":"School",
            "type":"Public Place"
        }
    ],
    "sg:phone":"+61 1800 814 787",
    "sg:postcode":"3056",
    "sg:province":"VIC",
    "sg:tags":[
        "supply"
    ],
    "wof:name":"Artistcare School Supplies",
    "wof:placetype":"venue"
},
  "geometry": {"coordinates":[144.962966919,-37.7664794922],"type":"Point"}
}