{
  "type": "Feature",
  "properties": {
    "iso:country":"AU",
    "sg:address":"Unit 2 23 Greenhill Rd",
    "sg:city":"Wayville",
    "sg:classifiers":[
        {
            "category":"Insurance",
            "subcategory":"Insurance Agent",
            "type":"Services"
        }
    ],
    "sg:phone":"+61 8 8272 7100",
    "sg:postcode":"5034",
    "sg:province":"SA",
    "sg:tags":[
        "broker"
    ],
    "wof:name":"SSAA Insurance Brokers Pty Ltd",
    "wof:placetype":"venue"
},
  "geometry": {"coordinates":[138.58747863799999,-34.9421463013],"type":"Point"}
}