{
  "type": "Feature",
  "properties": {
    "addr:full":"54 Docker St Wagga Wagga NSW 2650",
    "addr:housenumber":"54",
    "addr:postcode":"2650",
    "addr:street":"Docker St",
    "iso:country":"AU",
    "sg:address":"54 Docker St",
    "sg:city":"Wagga Wagga",
    "sg:classifiers":[
        {
            "category":"Health Services",
            "subcategory":"Doctor",
            "type":"Services"
        }
    ],
    "sg:phone":"+61 2 6925 5900",
    "sg:postcode":"2650",
    "sg:province":"NSW",
    "sg:tags":[
        "medical",
        "practitioner"
    ],
    "wof:name":"Barnes C J",
    "wof:placetype":"venue"
},
  "geometry": {"coordinates":[147.356033325,-35.1175880432],"type":"Point"}
}