{
  "type": "Feature",
  "properties": {
    "iso:country":"AU",
    "sg:address":"57- 59 Melverton Drv",
    "sg:city":"Hallam",
    "sg:classifiers":[
        {
            "category":"Food & Beverages",
            "subcategory":"Bakery",
            "type":"Retail Goods"
        }
    ],
    "sg:phone":"+61 3 9796 3565",
    "sg:postcode":"3803",
    "sg:province":"VIC",
    "sg:tags":[
        "cake",
        "shop",
        "pastry"
    ],
    "sg:website":"http://www.elegantoccasions.com.au",
    "wof:name":"Elegant Occasions",
    "wof:placetype":"venue"
},
  "geometry": {"coordinates":[145.272537231,-38.0115852356],"type":"Point"}
}