{
  "type": "Feature",
  "properties": {
    "addr:full":"81 Flushcombe Rd Blacktown NSW 2148",
    "addr:housenumber":"81",
    "addr:postcode":"2148",
    "addr:street":"Flushcombe Rd",
    "iso:country":"AU",
    "sg:address":"81 Flushcombe Rd",
    "sg:city":"Blacktown",
    "sg:classifiers":[
        {
            "category":"Health Services",
            "subcategory":"Doctor",
            "type":"Services"
        }
    ],
    "sg:phone":"+61 2 9831 7911",
    "sg:postcode":"2148",
    "sg:province":"NSW",
    "sg:tags":[
        "medical",
        "practitioner"
    ],
    "wof:name":"Norris Gordon G",
    "wof:placetype":"venue"
},
  "geometry": {"coordinates":[150.90802001899999,-33.7725067139],"type":"Point"}
}