{
  "type": "Feature",
  "properties": {
    "iso:country":"AU",
    "sg:address":"120- 124 Learmonth St",
    "sg:city":"Alfredton",
    "sg:classifiers":[
        {
            "category":"Retail",
            "subcategory":"Storage",
            "type":"Services"
        }
    ],
    "sg:phone":"+61 1300 668 468",
    "sg:postcode":"3350",
    "sg:province":"VIC",
    "sg:tags":[
        "shelving",
        "system"
    ],
    "wof:name":"Dynamic Warehouse Supplies",
    "wof:placetype":"venue"
},
  "geometry": {"coordinates":[143.81179800000001,-37.563282],"type":"Point"}
}