{
  "type": "Feature",
  "properties": {
    "addr:full":"27 Titan Drv Carrum Downs VIC 3201",
    "addr:housenumber":"27",
    "addr:postcode":"3201",
    "addr:street":"Titan Drv",
    "iso:country":"AU",
    "sg:address":"27 Titan Drv",
    "sg:city":"Carrum Downs",
    "sg:classifiers":[
        {
            "category":"Utilities",
            "subcategory":"Recycling",
            "type":"Services"
        }
    ],
    "sg:phone":"+61 3 9770 8384",
    "sg:postcode":"3201",
    "sg:province":"VIC",
    "wof:name":"Corporate Recycling",
    "wof:placetype":"venue"
},
  "geometry": {"coordinates":[145.16700700000001,-38.101089],"type":"Point"}
}