{
  "type": "Feature",
  "properties": {
    "iso:country":"AU",
    "sg:address":"497 Whitehorse Rd",
    "sg:city":"Balwyn",
    "sg:classifiers":[
        {
            "category":"Health Services",
            "subcategory":"Doctor",
            "type":"Services"
        }
    ],
    "sg:phone":"+61 3 9836 1088",
    "sg:postcode":"3103",
    "sg:province":"VIC",
    "sg:tags":[
        "medical",
        "practitioner"
    ],
    "wof:name":"Balwyn Medical Clinic",
    "wof:placetype":"venue"
},
  "geometry": {"coordinates":[145.08853149399999,-37.8135490417],"type":"Point"}
}