{
  "type": "Feature",
  "properties": {
    "iso:country":"AU",
    "sg:address":"19 McLean St",
    "sg:city":"Bundaberg",
    "sg:classifiers":[
        {
            "category":"Building & Trades",
            "subcategory":"Plumbing",
            "type":"Services"
        }
    ],
    "sg:phone":"+61 7 4151 3148",
    "sg:postcode":"4670",
    "sg:province":"QLD",
    "sg:tags":[
        "pump",
        "repairer"
    ],
    "wof:name":"Elvery's Electrical Service P/L",
    "wof:placetype":"venue"
},
  "geometry": {"coordinates":[152.346969605,-24.8723297119],"type":"Point"}
}