{
  "type": "Feature",
  "properties": {
    "addr:full":"32 Lambert St Richmond VIC 3121",
    "addr:housenumber":"32",
    "addr:postcode":"3121",
    "addr:street":"Lambert St",
    "iso:country":"AU",
    "sg:address":"32 Lambert St",
    "sg:city":"Richmond",
    "sg:classifiers":[
        {
            "category":"Government",
            "subcategory":"Fire Station",
            "type":"Public Place"
        }
    ],
    "sg:phone":"+61 3 9421 5552",
    "sg:postcode":"3121",
    "sg:province":"VIC",
    "sg:tags":[
        "equipment",
        "protection",
        "consultant"
    ],
    "wof:name":"Notifier Inertia Fire Systems",
    "wof:placetype":"venue"
},
  "geometry": {"coordinates":[145.00254821799999,-37.8121337891],"type":"Point"}
}