{
  "type": "Feature",
  "properties": {
    "iso:country":"AU",
    "sg:address":"45 Victoria Ave",
    "sg:city":"Albert Park",
    "sg:classifiers":[
        {
            "category":"Personal",
            "type":"Services"
        }
    ],
    "sg:phone":"+61 3 9682 2544",
    "sg:postcode":"3206",
    "sg:province":"VIC",
    "sg:tags":[
        "reducing",
        "treatment",
        "weight"
    ],
    "wof:name":"Herbalife Australasia Pty Ltd",
    "wof:placetype":"venue"
},
  "geometry": {"coordinates":[144.952621,-37.842686],"type":"Point"}
}