{
  "type": "Feature",
  "properties": {
    "addr:full":"2 Marnie Rd Bendigo VIC 3550",
    "addr:housenumber":"2",
    "addr:postcode":"3550",
    "addr:street":"Marnie Rd",
    "iso:country":"AU",
    "sg:address":"2 Marnie Rd",
    "sg:city":"Bendigo",
    "sg:classifiers":[
        {
            "category":"Education",
            "subcategory":"School",
            "type":"Public Place"
        }
    ],
    "sg:phone":"+61 3 5441 2277",
    "sg:postcode":"3550",
    "sg:province":"VIC",
    "sg:tags":[
        "co-educational"
    ],
    "wof:name":"Victory Christian College",
    "wof:placetype":"venue"
},
  "geometry": {"coordinates":[144.307937622,-36.7756576538],"type":"Point"}
}