{
  "type": "Feature",
  "properties": {
    "addr:full":"59 Melissa St Donvale VIC 3111",
    "addr:housenumber":"59",
    "addr:postcode":"3111",
    "addr:street":"Melissa St",
    "iso:country":"AU",
    "sg:address":"59 Melissa St",
    "sg:city":"Donvale",
    "sg:classifiers":[
        {
            "category":"Building & Trades",
            "subcategory":"Landscaping Services",
            "type":"Services"
        }
    ],
    "sg:phone":"+61 3 9842 8246",
    "sg:postcode":"3111",
    "sg:province":"VIC",
    "sg:tags":[
        "stump",
        "tree",
        "felling",
        "removal"
    ],
    "wof:name":"Mathews Des & Co",
    "wof:placetype":"venue"
},
  "geometry": {"coordinates":[145.180740356,-37.7829246521],"type":"Point"}
}