{
  "type": "Feature",
  "properties": {
    "addr:full":"Shop 12 Warwick Entertainment Cntr Beach Rd Warwick WA 6024",
    "addr:housenumber":"shop 12",
    "addr:postcode":"6024",
    "addr:street":"Beach Rd",
    "iso:country":"AU",
    "sg:address":"Shop 12 Warwick Entertainment Cntr Beach Rd",
    "sg:city":"Warwick",
    "sg:classifiers":[
        {
            "category":"Health Services",
            "subcategory":"Optometrist",
            "type":"Services"
        }
    ],
    "sg:phone":"+61 8 9243 1331",
    "sg:postcode":"6024",
    "sg:province":"WA",
    "wof:name":"Warwick Optometrists",
    "wof:placetype":"venue"
},
  "geometry": {"coordinates":[115.80818176299999,-31.844959259],"type":"Point"}
}