{
  "type": "Feature",
  "properties": {
    "iso:country":"AU",
    "sg:address":"18 Sarton Rd",
    "sg:city":"Clayton",
    "sg:classifiers":[
        {
            "category":"Fast Food",
            "type":"Food & Drink"
        }
    ],
    "sg:phone":"+61 3 9544 8925",
    "sg:postcode":"3168",
    "sg:province":"VIC",
    "sg:tags":[
        "away",
        "take"
    ],
    "wof:name":"Sarton Sandwich Bar",
    "wof:placetype":"venue"
},
  "geometry": {"coordinates":[145.14410400400001,-37.9207115173],"type":"Point"}
}