{
  "type": "Feature",
  "properties": {
    "addr:full":"24 Brodie St Hughenden QLD 4821",
    "addr:housenumber":"24",
    "addr:postcode":"4821",
    "addr:street":"Brodie St",
    "iso:country":"AU",
    "sg:address":"24 Brodie St",
    "sg:city":"Hughenden",
    "sg:classifiers":[
        {
            "category":"Retail",
            "subcategory":"Auto Repair",
            "type":"Services"
        }
    ],
    "sg:phone":"+61 7 4741 1025",
    "sg:postcode":"4821",
    "sg:province":"QLD",
    "sg:tags":[
        "electrical"
    ],
    "wof:name":"Honnery's All Electrical & Repairs",
    "wof:placetype":"venue"
},
  "geometry": {"coordinates":[144.19552612300001,-20.8416385651],"type":"Point"}
}