{
  "type": "Feature",
  "properties": {
    "addr:full":"Cnr Limestone & Thorn St Ipswich QLD 4305",
    "addr:postcode":"4305",
    "addr:street":"Cnr;St",
    "iso:country":"AU",
    "sg:address":"Cnr Limestone & Thorn St",
    "sg:city":"Ipswich",
    "sg:classifiers":[
        {
            "category":"Retail",
            "subcategory":"Event Space",
            "type":"Services"
        }
    ],
    "sg:phone":"+61 7 3812 0777",
    "sg:postcode":"4305",
    "sg:province":"QLD",
    "sg:tags":[
        "venue",
        "reception",
        "wedding"
    ],
    "wof:name":"Fed Up Deli & Catering Function Centre",
    "wof:placetype":"venue"
},
  "geometry": {"coordinates":[152.754516602,-27.6157894135],"type":"Point"}
}