{
  "type": "Feature",
  "properties": {
    "addr:full":"256b Old Northern Rd Castle Hill NSW 2154",
    "addr:housenumber":"256b",
    "addr:postcode":"2154",
    "addr:street":"Old Northern Rd",
    "iso:country":"AU",
    "sg:address":"256b Old Northern Rd",
    "sg:city":"Castle Hill",
    "sg:classifiers":[
        {
            "category":"Fast Food",
            "type":"Food & Drink"
        }
    ],
    "sg:phone":"+61 2 9659 8880",
    "sg:postcode":"2154",
    "sg:province":"NSW",
    "sg:tags":[
        "away",
        "take"
    ],
    "wof:name":"Original Gourmet Pizza Company",
    "wof:placetype":"venue"
},
  "geometry": {"coordinates":[151.00326538100001,-33.7346763611],"type":"Point"}
}