{
  "type": "Feature",
  "properties": {
    "addr:full":"1st Floor 88 - 96 Bunda St Canberra ACT 2600",
    "addr:housenumber":"88 96",
    "addr:postcode":"2600",
    "addr:street":"Bunda St",
    "iso:country":"AU",
    "sg:address":"1st Floor 88 - 96 Bunda St",
    "sg:city":"Canberra",
    "sg:classifiers":[
        {
            "category":"Health Services",
            "subcategory":"Health Practitioner",
            "type":"Services"
        }
    ],
    "sg:phone":"+61 2 6257 4900",
    "sg:postcode":"2600",
    "sg:province":"ACT",
    "sg:tags":[
        "psychologist"
    ],
    "wof:name":"Corcoran John & Morgan Jo",
    "wof:placetype":"venue"
},
  "geometry": {"coordinates":[149.13267517099999,-35.2782478333],"type":"Point"}
}