{
  "type": "Feature",
  "properties": {
    "addr:full":"59-63 St Hellier St Heidelberg Heights VIC 3081",
    "addr:housenumber":"59-63",
    "addr:postcode":"3081",
    "addr:street":"St Hellier St",
    "iso:country":"AU",
    "sg:address":"59-63 St Hellier St",
    "sg:city":"Heidelberg Heights",
    "sg:classifiers":[
        {
            "category":"Wholesale",
            "subcategory":"Apparel",
            "type":"Manufacturing & Wholesale Goods"
        }
    ],
    "sg:phone":"+61 3 9458 5914",
    "sg:postcode":"3081",
    "sg:province":"VIC",
    "sg:tags":[
        "wholesaler",
        "mfrs",
        "uniform"
    ],
    "wof:name":"Sirc Nominees Pty Ltd",
    "wof:placetype":"venue"
},
  "geometry": {"coordinates":[145.05406189000001,-37.7496337891],"type":"Point"}
}