{
  "type": "Feature",
  "properties": {
    "iso:country":"AU",
    "sg:address":"55a Dinah Pde",
    "sg:city":"Keilor East",
    "sg:classifiers":[
        {
            "category":"Personal",
            "subcategory":"Beauty Salon",
            "type":"Services"
        }
    ],
    "sg:phone":"+61 3 9337 9976",
    "sg:postcode":"3033",
    "sg:province":"VIC",
    "sg:tags":[
        "hairdresser"
    ],
    "wof:name":"Beyond Creation For Hair",
    "wof:placetype":"venue"
},
  "geometry": {"coordinates":[144.866379,-37.743984],"type":"Point"}
}