{
  "type": "Feature",
  "properties": {
    "addr:full":"Unit 1/ 22 Macintosh St Tamworth NSW 2340",
    "addr:housenumber":"22",
    "addr:postcode":"2340",
    "addr:street":"Macintosh St",
    "iso:country":"AU",
    "sg:address":"Unit 1/ 22 Macintosh St",
    "sg:city":"Tamworth",
    "sg:classifiers":[
        {
            "category":"Professional",
            "subcategory":"Testing Lab",
            "type":"Services"
        }
    ],
    "sg:phone":"+61 2 6762 7123",
    "sg:postcode":"2340",
    "sg:province":"NSW",
    "sg:tags":[
        "soil",
        "investigation"
    ],
    "wof:name":"Hunter Geotechnics",
    "wof:placetype":"venue"
},
  "geometry": {"coordinates":[150.90069580100001,-31.097202301],"type":"Point"}
}