{
  "type": "Feature",
  "properties": {
    "addr:full":"51 Hackman St McDowall QLD 4053",
    "addr:housenumber":"51",
    "addr:postcode":"4053",
    "addr:street":"Hackman St",
    "iso:country":"AU",
    "sg:address":"51 Hackman St",
    "sg:city":"McDowall",
    "sg:classifiers":[
        {
            "category":"Professional",
            "subcategory":"Management & Consulting",
            "type":"Services"
        }
    ],
    "sg:phone":"+61 7 3353 1308",
    "sg:postcode":"4053",
    "sg:province":"QLD",
    "sg:tags":[
        "consultant"
    ],
    "wof:name":"Bovey Management Pty Ltd",
    "wof:placetype":"venue"
},
  "geometry": {"coordinates":[152.99064636200001,-27.3820648193],"type":"Point"}
}