{
  "type": "Feature",
  "properties": {
    "addr:full":"7 Townsend St Mortlake VIC 3272",
    "addr:housenumber":"7",
    "addr:postcode":"3272",
    "addr:street":"Townsend St",
    "iso:country":"AU",
    "sg:address":"7 Townsend St",
    "sg:city":"Mortlake",
    "sg:classifiers":[
        {
            "category":"Professional",
            "subcategory":"Business Services",
            "type":"Services"
        }
    ],
    "sg:phone":"+61 3 5599 2186",
    "sg:postcode":"3272",
    "sg:province":"VIC",
    "sg:tags":[
        "livestock",
        "transport"
    ],
    "wof:name":"Wareham J R & S A",
    "wof:placetype":"venue"
},
  "geometry": {"coordinates":[142.798660278,-38.0786247253],"type":"Point"}
}