{
  "type": "Feature",
  "properties": {
    "addr:full":"Shop 1, Eastwood Plaza 102-106 Canterbury Rd Kilsyth VIC 3137",
    "addr:housenumber":"shop 1;102-106",
    "addr:postcode":"3137",
    "addr:street":"Eastwood Plaza;Canterbury Rd",
    "iso:country":"AU",
    "sg:address":"Shop 1, Eastwood Plaza 102-106 Canterbury Rd",
    "sg:city":"Kilsyth",
    "sg:classifiers":[
        {
            "category":"Government",
            "subcategory":"Fire Station",
            "type":"Public Place"
        }
    ],
    "sg:phone":"+61 3 9728 5795",
    "sg:postcode":"3137",
    "sg:province":"VIC",
    "sg:tags":[
        "equipment",
        "protection",
        "consultant"
    ],
    "wof:name":"Centurion Electrical Services P/L",
    "wof:placetype":"venue"
},
  "geometry": {"coordinates":[145.31492614699999,-37.8188476562],"type":"Point"}
}