{
  "type": "Feature",
  "properties": {
    "iso:country":"AU",
    "sg:address":"PO Box 120",
    "sg:city":"Northampton",
    "sg:classifiers":[
        {
            "category":"Farming",
            "subcategory":"Farm",
            "type":"Manufacturing & Wholesale Goods"
        }
    ],
    "sg:phone":"+61 8 9935 1027",
    "sg:postcode":"6535",
    "sg:province":"WA",
    "sg:tags":[
        "farmer"
    ],
    "wof:name":"Suckling A & W",
    "wof:placetype":"venue"
},
  "geometry": {"coordinates":[114.629867554,-28.3565998077],"type":"Point"}
}