{
  "type": "Feature",
  "properties": {
    "iso:country":"AU",
    "sg:address":"143 Clarence Rd",
    "sg:city":"Indooroopilly",
    "sg:classifiers":[
        {
            "category":"Building & Trades",
            "subcategory":"Construction",
            "type":"Services"
        }
    ],
    "sg:phone":"+61 7 3870 0500",
    "sg:postcode":"4068",
    "sg:province":"QLD",
    "sg:tags":[
        "equipment",
        "system",
        "automation"
    ],
    "wof:name":"Acorp Pty Ltd",
    "wof:placetype":"venue"
},
  "geometry": {"coordinates":[152.977127075,-27.5018100739],"type":"Point"}
}