{
  "type": "Feature",
  "properties": {
    "iso:country":"AU",
    "sg:address":"PO Box 679",
    "sg:city":"Newcastle",
    "sg:classifiers":[
        {
            "category":"Banks & Credit Unions",
            "subcategory":"Investment Brokerage",
            "type":"Services"
        }
    ],
    "sg:phone":"+61 2 4969 2040",
    "sg:postcode":"2300",
    "sg:province":"NSW",
    "sg:tags":[
        "debt",
        "collection"
    ],
    "wof:name":"Newcomen Commercial Services",
    "wof:placetype":"venue"
},
  "geometry": {"coordinates":[151.780136,-32.930859],"type":"Point"}
}