{
  "type": "Feature",
  "properties": {
    "addr:full":"13a Cottage St Blackburn VIC 3130",
    "addr:housenumber":"13a",
    "addr:postcode":"3130",
    "addr:street":"Cottage St",
    "iso:country":"AU",
    "sg:address":"13a Cottage St",
    "sg:city":"Blackburn",
    "sg:classifiers":[
        {
            "category":"Home & Garden",
            "subcategory":"Carpets & Floor Coverings",
            "type":"Retail Goods"
        }
    ],
    "sg:phone":"+61 3 9894 2219",
    "sg:postcode":"3130",
    "sg:province":"VIC",
    "sg:tags":[
        "tile",
        "wall"
    ],
    "wof:name":"The Tile Studio Pty Ltd",
    "wof:placetype":"venue"
},
  "geometry": {"coordinates":[145.157714844,-37.8190574646],"type":"Point"}
}