{
  "type": "Feature",
  "properties": {
    "iso:country":"AU",
    "sg:address":"Cnr Ferntree Gully & Springvale Rds",
    "sg:city":"Brandon Park",
    "sg:classifiers":[
        {
            "category":"Retail",
            "subcategory":"Auto Repair",
            "type":"Services"
        }
    ],
    "sg:phone":"+61 3 9562 1022",
    "sg:postcode":"3170",
    "sg:province":"VIC",
    "sg:tags":[
        "repairer",
        "motor",
        "engineer"
    ],
    "wof:name":"UltraTune Systems (Australia) Pty Ltd",
    "wof:placetype":"venue"
},
  "geometry": {"coordinates":[145.161499023,-37.9035377502],"type":"Point"}
}