{
  "type": "Feature",
  "properties": {
    "iso:country":"AU",
    "sg:address":"155 George St",
    "sg:city":"Sydney",
    "sg:classifiers":[
        {
            "category":"Shopping",
            "subcategory":"Clothing, Apparel, & Fashions",
            "type":"Retail Goods"
        }
    ],
    "sg:phone":"+61 2 9252 9373",
    "sg:postcode":"2000",
    "sg:province":"NSW",
    "sg:tags":[
        "menswear"
    ],
    "wof:name":"Rodd Gunn & Logan",
    "wof:placetype":"venue"
},
  "geometry": {"coordinates":[151.20834350600001,-33.860912323],"type":"Point"}
}