{
  "type": "Feature",
  "properties": {
    "iso:country":"AU",
    "sg:address":"45 Bellevue Rd",
    "sg:city":"Figtree",
    "sg:classifiers":[
        {
            "category":"Building & Trades",
            "subcategory":"Construction",
            "type":"Services"
        }
    ],
    "sg:phone":"+61 2 4228 7824",
    "sg:postcode":"2525",
    "sg:province":"NSW",
    "sg:tags":[
        "rendering",
        "cement"
    ],
    "wof:name":"Harb B H",
    "wof:placetype":"venue"
},
  "geometry": {"coordinates":[150.85870361299999,-34.4314155579],"type":"Point"}
}