{
  "type": "Feature",
  "properties": {
    "addr:full":"Emmert St Yarraman QLD 4614",
    "addr:postcode":"4614",
    "addr:street":"Emmert St",
    "iso:country":"AU",
    "sg:address":"Emmert St",
    "sg:city":"Yarraman",
    "sg:classifiers":[
        {
            "category":"Social Services",
            "subcategory":"Adult Care",
            "type":"Services"
        }
    ],
    "sg:phone":"+61 7 4163 8226",
    "sg:postcode":"4614",
    "sg:province":"QLD",
    "sg:tags":[
        "aged"
    ],
    "wof:name":"Meals On Wheels",
    "wof:placetype":"venue"
},
  "geometry": {"coordinates":[151.97940063499999,-26.8424072266],"type":"Point"}
}