{
  "type": "Feature",
  "properties": {
    "addr:full":"405 Tingal Rd Wynnum North QLD 4178",
    "addr:housenumber":"405",
    "addr:postcode":"4178",
    "addr:street":"Tingal Rd",
    "iso:country":"AU",
    "sg:address":"405 Tingal Rd",
    "sg:city":"Wynnum North",
    "sg:classifiers":[
        {
            "category":"Education",
            "subcategory":"School",
            "type":"Public Place"
        }
    ],
    "sg:phone":"+61 7 3396 8007",
    "sg:postcode":"4178",
    "sg:province":"QLD",
    "sg:tags":[
        "state",
        "except",
        "nsw"
    ],
    "wof:name":"Wynnum North Preschool",
    "wof:placetype":"venue"
},
  "geometry": {"coordinates":[153.16604614299999,-27.4334182739],"type":"Point"}
}