{
  "type": "Feature",
  "properties": {
    "addr:full":"Shop 2 178 Henley Beach Rd Torrensville SA 5031",
    "addr:housenumber":"shop 2 178",
    "addr:postcode":"5031",
    "addr:street":"Henley Beach Rd",
    "iso:country":"AU",
    "sg:address":"Shop 2 178 Henley Beach Rd",
    "sg:city":"Torrensville",
    "sg:classifiers":[
        {
            "category":"Personal",
            "subcategory":"Beauty Salon",
            "type":"Services"
        }
    ],
    "sg:phone":"+61 8 8234 2510",
    "sg:postcode":"5031",
    "sg:province":"SA",
    "sg:tags":[
        "hairdresser"
    ],
    "wof:name":"Monsoons For Hair",
    "wof:placetype":"venue"
},
  "geometry": {"coordinates":[138.56141662600001,-34.9239501953],"type":"Point"}
}