{
  "type": "Feature",
  "properties": {
    "iso:country":"AU",
    "sg:address":"26 Brook St",
    "sg:city":"Toowoomba",
    "sg:classifiers":[
        {
            "category":"Shopping",
            "subcategory":"Antiques",
            "type":"Retail Goods"
        }
    ],
    "sg:phone":"+61 7 4639 5411",
    "sg:postcode":"4350",
    "sg:province":"QLD",
    "sg:tags":[
        "restoration",
        "reproduction"
    ],
    "wof:name":"David N Hagan",
    "wof:placetype":"venue"
},
  "geometry": {"coordinates":[151.946167,-27.543911],"type":"Point"}
}