{
  "type": "Feature",
  "properties": {
    "iso:country":"AU",
    "sg:address":"22 Belgrave St",
    "sg:city":"Kempsey",
    "sg:classifiers":[
        {
            "category":"Health Services",
            "subcategory":"Optometrist",
            "type":"Services"
        }
    ],
    "sg:phone":"+61 2 6562 3840",
    "sg:postcode":"2440",
    "sg:province":"NSW",
    "wof:name":"Chapman I D",
    "wof:placetype":"venue"
},
  "geometry": {"coordinates":[152.84144599999999,-31.080723],"type":"Point"}
}