{
  "type": "Feature",
  "properties": {
    "addr:full":"417 Seaview Rd Henley Beach SA 5022",
    "addr:housenumber":"417",
    "addr:postcode":"5022",
    "addr:street":"Seaview Rd",
    "iso:country":"AU",
    "sg:address":"417 Seaview Rd",
    "sg:city":"Henley Beach",
    "sg:classifiers":[
        {
            "category":"Recreation",
            "subcategory":"Sailing Club",
            "type":"Entertainment"
        }
    ],
    "sg:phone":"+61 8 8235 9212",
    "sg:postcode":"5022",
    "sg:province":"SA",
    "sg:tags":[
        "yacht"
    ],
    "wof:name":"Grange Sailing Club Incorporated",
    "wof:placetype":"venue"
},
  "geometry": {"coordinates":[138.49520874000001,-34.9220848083],"type":"Point"}
}