{
  "type": "Feature",
  "properties": {
    "addr:full":"McGregor Rd Smithfield (Cairns) QLD 4878",
    "addr:postcode":"4878",
    "addr:street":"Mcgregor Rd",
    "iso:country":"AU",
    "sg:address":"McGregor Rd",
    "sg:city":"Smithfield (Cairns)",
    "sg:classifiers":[
        {
            "category":"Fast Food",
            "type":"Food & Drink"
        }
    ],
    "sg:phone":"+61 7 4055 6777",
    "sg:postcode":"4878",
    "sg:province":"QLD",
    "sg:tags":[
        "away",
        "take"
    ],
    "wof:name":"Splash's Takeaway",
    "wof:placetype":"venue"
},
  "geometry": {"coordinates":[145.69195556599999,-16.8207645416],"type":"Point"}
}