{
  "type": "Feature",
  "properties": {
    "iso:country":"AU",
    "sg:address":"Level 6/ 39",
    "sg:city":"London Cct Canberra City",
    "sg:classifiers":[
        {
            "category":"Professional",
            "subcategory":"Research",
            "type":"Services"
        }
    ],
    "sg:phone":"+61 2 6263 5982",
    "sg:postcode":"2601",
    "sg:province":"ACT",
    "sg:tags":[
        "market"
    ],
    "wof:name":"ACNielsen",
    "wof:placetype":"venue"
},
  "geometry": {"coordinates":[149.127044678,-35.2794837952],"type":"Point"}
}