{
  "type": "Feature",
  "properties": {
    "iso:country":"AU",
    "sg:address":"PO Box 505",
    "sg:city":"Mudgeeraba",
    "sg:classifiers":[
        {
            "category":"Retail",
            "subcategory":"Repair Shop",
            "type":"Services"
        }
    ],
    "sg:phone":"+61 413 886 709",
    "sg:postcode":"4213",
    "sg:province":"QLD",
    "sg:tags":[
        "maintenance",
        "pool",
        "swimming"
    ],
    "wof:name":"Top Line Pool Maintenance",
    "wof:placetype":"venue"
},
  "geometry": {"coordinates":[153.364578247,-28.0756206512],"type":"Point"}
}