{
  "type": "Feature",
  "properties": {
    "addr:full":"Level 2, 203 - 233 New South Head Rd Edgecliff NSW 2027",
    "addr:housenumber":"203 233",
    "addr:postcode":"2027",
    "addr:street":"New South Head Rd",
    "iso:country":"AU",
    "sg:address":"Level 2, 203 - 233 New South Head Rd",
    "sg:city":"Edgecliff",
    "sg:classifiers":[
        {
            "category":"Shopping",
            "subcategory":"Clothing, Apparel, & Fashions",
            "type":"Retail Goods"
        }
    ],
    "sg:phone":"+61 1300 550 360",
    "sg:postcode":"2027",
    "sg:province":"NSW",
    "sg:tags":[
        "uniform"
    ],
    "wof:name":"David Chrystal Clothing",
    "wof:placetype":"venue"
},
  "geometry": {"coordinates":[151.235961914,-33.8788223267],"type":"Point"}
}