{
  "type": "Feature",
  "properties": {
    "iso:country":"AU",
    "sg:address":"7 Doonside Pl",
    "sg:city":"Morley",
    "sg:classifiers":[
        {
            "category":"Retail",
            "subcategory":"Auto Repair",
            "type":"Services"
        }
    ],
    "sg:phone":"+61 410 311 213",
    "sg:postcode":"6062",
    "sg:province":"WA",
    "sg:tags":[
        "electrical"
    ],
    "wof:name":"Byrne Service & Repair",
    "wof:placetype":"venue"
},
  "geometry": {"coordinates":[115.930740356,-31.8818321228],"type":"Point"}
}