{
  "type": "Feature",
  "properties": {
    "iso:country":"AU",
    "sg:address":"80 Beechboro Rd",
    "sg:city":"Bayswater",
    "sg:classifiers":[
        {
            "category":"Retail",
            "subcategory":"Auto Repair",
            "type":"Services"
        }
    ],
    "sg:phone":"+61 8 9272 8265",
    "sg:postcode":"6053",
    "sg:province":"WA",
    "sg:tags":[
        "beater",
        "painter",
        "panel"
    ],
    "wof:name":"Hi-Lite Automotive Body Repairs",
    "wof:placetype":"venue"
},
  "geometry": {"coordinates":[115.913856506,-31.909330368],"type":"Point"}
}