{
  "type": "Feature",
  "properties": {
    "iso:country":"AU",
    "sg:address":"Meikle St",
    "sg:city":"Bacchus Marsh",
    "sg:classifiers":[
        {
            "category":"Manufacturing",
            "subcategory":"Building Materials",
            "type":"Manufacturing & Wholesale Goods"
        }
    ],
    "sg:phone":"+61 417 678 135",
    "sg:postcode":"3340",
    "sg:province":"VIC",
    "sg:tags":[
        "machinery",
        "secondhand"
    ],
    "sg:website":"http://www.ihub.com.au/allpurpose",
    "wof:name":"All Purpose Machinery Pty Ltd",
    "wof:placetype":"venue"
},
  "geometry": {"coordinates":[144.43112199999999,-37.682224],"type":"Point"}
}