{
  "type": "Feature",
  "properties": {
    "addr:full":"48 Morilla St Lightning Ridge NSW 2834",
    "addr:housenumber":"48",
    "addr:postcode":"2834",
    "addr:street":"Morilla St",
    "iso:country":"AU",
    "sg:address":"48 Morilla St",
    "sg:city":"Lightning Ridge",
    "sg:classifiers":[
        {
            "category":"Social Services",
            "subcategory":"Adult Care",
            "type":"Services"
        }
    ],
    "sg:phone":"+61 2 6829 1393",
    "sg:postcode":"2834",
    "sg:province":"NSW",
    "sg:tags":[
        "disadvantaged",
        "aid",
        "organisation",
        "group"
    ],
    "wof:name":"Meals On Wheels Lightning Ridge",
    "wof:placetype":"venue"
},
  "geometry": {"coordinates":[147.980774,-29.427113],"type":"Point"}
}