{
  "type": "Feature",
  "properties": {
    "iso:country":"AU",
    "sg:address":"PO Box 459",
    "sg:city":"Caringbah",
    "sg:classifiers":[
        {
            "category":"Train Station",
            "subcategory":"Rail",
            "type":"Transportation"
        }
    ],
    "sg:phone":"+61 2 9531 7667",
    "sg:postcode":"2229",
    "sg:province":"NSW",
    "sg:tags":[
        "marine",
        "engineer"
    ],
    "wof:name":"Marine Equipment International",
    "wof:placetype":"venue"
},
  "geometry": {"coordinates":[151.12121582,-34.0429000854],"type":"Point"}
}