{
  "type": "Feature",
  "properties": {
    "iso:country":"AU",
    "sg:address":"34 Swan Street",
    "sg:city":"Longreach",
    "sg:classifiers":[
        {
            "category":"Wholesale",
            "subcategory":"Machinery & Supplies",
            "type":"Manufacturing & Wholesale Goods"
        }
    ],
    "sg:phone":"+61 7 4658 1423",
    "sg:postcode":"4730",
    "sg:province":"QLD",
    "sg:tags":[
        "agricultural"
    ],
    "wof:name":"Johnlee Motors",
    "wof:placetype":"venue"
},
  "geometry": {"coordinates":[144.25074799999999,-23.444658],"type":"Point"}
}