{
  "type": "Feature",
  "properties": {
    "addr:full":"51a Sixth Ave Loftus NSW 2232",
    "addr:housenumber":"51a",
    "addr:postcode":"2232",
    "addr:street":"Sixth Ave",
    "iso:country":"AU",
    "sg:address":"51a Sixth Ave",
    "sg:city":"Loftus",
    "sg:classifiers":[
        {
            "category":"Building & Trades",
            "subcategory":"Construction",
            "type":"Services"
        }
    ],
    "sg:phone":"+61 2 9521 2940",
    "sg:postcode":"2232",
    "sg:province":"NSW",
    "sg:tags":[
        "contractor"
    ],
    "wof:name":"Eldor Pty Ltd",
    "wof:placetype":"venue"
},
  "geometry": {"coordinates":[151.04498290999999,-34.0414543152],"type":"Point"}
}