{
  "type": "Feature",
  "properties": {
    "addr:full":"28 Garrad Crt Charnwood ACT 2615",
    "addr:housenumber":"28",
    "addr:postcode":"2615",
    "addr:street":"Garrad Crt",
    "iso:country":"AU",
    "sg:address":"28 Garrad Crt",
    "sg:city":"Charnwood",
    "sg:classifiers":[
        {
            "category":"Government",
            "subcategory":"Post Office",
            "type":"Public Place"
        }
    ],
    "sg:phone":"+61 412 079 971",
    "sg:postcode":"2615",
    "sg:province":"ACT",
    "sg:tags":[
        "house",
        "doll"
    ],
    "wof:name":"Bambies Babies",
    "wof:placetype":"venue"
},
  "geometry": {"coordinates":[149.04330444300001,-35.1985931396],"type":"Point"}
}