{
  "type": "Feature",
  "properties": {
    "addr:full":"7 Derby Rd Boronia VIC 3155",
    "addr:housenumber":"7",
    "addr:postcode":"3155",
    "addr:street":"Derby Rd",
    "iso:country":"AU",
    "sg:address":"7 Derby Rd",
    "sg:city":"Boronia",
    "sg:classifiers":[
        {
            "category":"Professional",
            "subcategory":"Printing & Photocopies",
            "type":"Services"
        }
    ],
    "sg:phone":"+61 3 9837 5196",
    "sg:postcode":"3155",
    "sg:province":"VIC",
    "sg:tags":[
        "textile",
        "clothing"
    ],
    "sg:website":"http://www.myvision.com.au",
    "wof:name":"My Vision Promotional Products",
    "wof:placetype":"venue"
},
  "geometry": {"coordinates":[145.25807189899999,-37.8605804443],"type":"Point"}
}