{
  "type": "Feature",
  "properties": {
    "iso:country":"AU",
    "sg:address":"89 Argyle St",
    "sg:city":"Picton",
    "sg:classifiers":[
        {
            "category":"Fast Food",
            "type":"Food & Drink"
        }
    ],
    "sg:phone":"+61 2 4677 2006",
    "sg:postcode":"2571",
    "sg:province":"NSW",
    "sg:tags":[
        "away",
        "take"
    ],
    "wof:name":"Garden Pizza Cafe",
    "wof:placetype":"venue"
},
  "geometry": {"coordinates":[150.61207580600001,-34.1676216125],"type":"Point"}
}