{
  "type": "Feature",
  "properties": {
    "iso:country":"AU",
    "sg:address":"Shop 47/ 50a Pembroke St",
    "sg:city":"Minto",
    "sg:classifiers":[
        {
            "category":"Wholesale",
            "subcategory":"Apparel",
            "type":"Manufacturing & Wholesale Goods"
        }
    ],
    "sg:phone":"+61 2 9603 9988",
    "sg:postcode":"2566",
    "sg:province":"NSW",
    "sg:tags":[
        "wholesaler",
        "mfrs",
        "menswear"
    ],
    "wof:name":"The Family Warehouse",
    "wof:placetype":"venue"
},
  "geometry": {"coordinates":[150.85142517099999,-34.0216178894],"type":"Point"}
}