{
  "type": "Feature",
  "properties": {
    "addr:full":"11 Acheson Pl Coburg North VIC 3058",
    "addr:housenumber":"11",
    "addr:postcode":"3058",
    "addr:street":"Acheson Pl",
    "iso:country":"AU",
    "sg:address":"11 Acheson Pl",
    "sg:city":"Coburg North",
    "sg:classifiers":[
        {
            "category":"Government",
            "subcategory":"Police Station",
            "type":"Public Place"
        }
    ],
    "sg:phone":"+61 3 9350 3994",
    "sg:postcode":"3058",
    "sg:province":"VIC",
    "sg:tags":[
        "steering",
        "power"
    ],
    "wof:name":"Metro Power Steering",
    "wof:placetype":"venue"
},
  "geometry": {"coordinates":[144.97207641599999,-37.7272071838],"type":"Point"}
}