{
  "type": "Feature",
  "properties": {
    "addr:full":"Shop 4, 537 Boundary St Spring Hill QLD 4000",
    "addr:housenumber":"shop 4 537",
    "addr:postcode":"4000",
    "addr:street":"Boundary St",
    "iso:country":"AU",
    "sg:address":"Shop 4, 537 Boundary St",
    "sg:city":"Spring Hill",
    "sg:classifiers":[
        {
            "category":"Health Services",
            "subcategory":"Health Practitioner",
            "type":"Services"
        }
    ],
    "sg:phone":"+61 7 3831 8111",
    "sg:postcode":"4000",
    "sg:province":"QLD",
    "sg:tags":[
        "physiotherapist"
    ],
    "wof:name":"Lindsay Trigar",
    "wof:placetype":"venue"
},
  "geometry": {"coordinates":[153.02137756400001,-27.4602508545],"type":"Point"}
}