{
  "type": "Feature",
  "properties": {
    "addr:full":"PO Box 6 Carwarp VIC 3494",
    "addr:postcode":"3494",
    "iso:country":"AU",
    "sg:address":"PO Box 6",
    "sg:city":"Carwarp",
    "sg:classifiers":[
        {
            "category":"Farming",
            "subcategory":"Farm",
            "type":"Manufacturing & Wholesale Goods"
        }
    ],
    "sg:phone":"+61 427 293 275",
    "sg:postcode":"3494",
    "sg:province":"VIC",
    "sg:tags":[
        "farmer"
    ],
    "wof:name":"Gowers T N",
    "wof:placetype":"venue"
},
  "geometry": {"coordinates":[142.199127197,-34.454990387],"type":"Point"}
}