{
  "type": "Feature",
  "properties": {
    "iso:country":"AU",
    "sg:address":"10 Amour St",
    "sg:city":"Milperra",
    "sg:classifiers":[
        {
            "category":"Professional",
            "subcategory":"Business Services",
            "type":"Services"
        }
    ],
    "sg:phone":"+61 2 9774 4981",
    "sg:postcode":"2214",
    "sg:province":"NSW",
    "sg:tags":[
        "exporter"
    ],
    "wof:name":"K S Marketing",
    "wof:placetype":"venue"
},
  "geometry": {"coordinates":[150.99501000000001,-33.934887],"type":"Point"}
}