{
  "type": "Feature",
  "properties": {
    "iso:country":"AU",
    "sg:address":"248 Postle St",
    "sg:city":"Acacia Ridge",
    "sg:classifiers":[
        {
            "category":"Sports & Exercise",
            "subcategory":"Gym",
            "type":"Entertainment"
        }
    ],
    "sg:phone":"+61 7 3275 1962",
    "sg:postcode":"4110",
    "sg:province":"QLD",
    "sg:tags":[
        "health",
        "fitness"
    ],
    "wof:name":"Acacia Ridge Squash & Tennis Centre",
    "wof:placetype":"venue"
},
  "geometry": {"coordinates":[153.02720642099999,-27.5792102814],"type":"Point"}
}