{
  "type": "Feature",
  "properties": {
    "addr:full":"Shp38/ 16 Taylors Rd Keilor Downs VIC 3038",
    "addr:housenumber":"16",
    "addr:postcode":"3038",
    "addr:street":"Taylors Rd",
    "iso:country":"AU",
    "sg:address":"Shp38/ 16 Taylors Rd",
    "sg:city":"Keilor Downs",
    "sg:classifiers":[
        {
            "category":"Fast Food",
            "type":"Food & Drink"
        }
    ],
    "sg:phone":"+61 3 9310 7288",
    "sg:postcode":"3038",
    "sg:province":"VIC",
    "sg:tags":[
        "away",
        "take"
    ],
    "wof:name":"Mazzmoes Charcoal Chicken",
    "wof:placetype":"venue"
},
  "geometry": {"coordinates":[144.81352200000001,-37.729145],"type":"Point"}
}