{
  "type": "Feature",
  "properties": {
    "addr:full":"520 Hunter St Newcastle NSW 2300",
    "addr:housenumber":"520",
    "addr:postcode":"2300",
    "addr:street":"Hunter St",
    "iso:country":"AU",
    "sg:address":"520 Hunter St",
    "sg:city":"Newcastle",
    "sg:classifiers":[
        {
            "category":"Health Services",
            "subcategory":"Health Practitioner",
            "type":"Services"
        }
    ],
    "sg:phone":"+61 2 4925 2555",
    "sg:postcode":"2300",
    "sg:province":"NSW",
    "sg:tags":[
        "alternative"
    ],
    "wof:name":"Newcastle Mind Body Natural Therapies Centre",
    "wof:placetype":"venue"
},
  "geometry": {"coordinates":[151.769104,-32.927143],"type":"Point"}
}