{
  "type": "Feature",
  "properties": {
    "addr:full":"105 Plenty Rd Bundoora VIC 3083",
    "addr:housenumber":"105",
    "addr:postcode":"3083",
    "addr:street":"Plenty Rd",
    "iso:country":"AU",
    "sg:address":"105 Plenty Rd",
    "sg:city":"Bundoora",
    "sg:classifiers":[
        {
            "category":"Health Services",
            "subcategory":"Doctor",
            "type":"Services"
        }
    ],
    "sg:phone":"+61 3 9467 1233",
    "sg:postcode":"3083",
    "sg:province":"VIC",
    "sg:tags":[
        "medical",
        "practitioner"
    ],
    "wof:name":"Culliver J A Dr",
    "wof:placetype":"venue"
},
  "geometry": {"coordinates":[145.06068420400001,-37.693901062],"type":"Point"}
}