{
  "type": "Feature",
  "properties": {
    "iso:country":"AU",
    "sg:address":"Safeway Complex",
    "sg:city":"Rye",
    "sg:classifiers":[
        {
            "category":"Food & Beverages",
            "subcategory":"Liquor & Beverages",
            "type":"Retail Goods"
        }
    ],
    "sg:phone":"+61 3 5985 7633",
    "sg:postcode":"3941",
    "sg:province":"VIC",
    "sg:tags":[
        "store"
    ],
    "wof:name":"Peninsula Cellars",
    "wof:placetype":"venue"
},
  "geometry": {"coordinates":[144.820755005,-38.3701400757],"type":"Point"}
}