{
  "type": "Feature",
  "properties": {
    "addr:full":"Station St Cannington WA 6107",
    "addr:postcode":"6107",
    "addr:street":"Station St",
    "iso:country":"AU",
    "sg:address":"Station St",
    "sg:city":"Cannington",
    "sg:classifiers":[
        {
            "category":"Restaurant",
            "type":"Food & Drink"
        }
    ],
    "sg:phone":"+61 8 9458 9182",
    "sg:postcode":"6107",
    "sg:province":"WA",
    "wof:name":"Checkers at Greyhounds WA",
    "wof:placetype":"venue"
},
  "geometry": {"coordinates":[115.94380188,-32.0225296021],"type":"Point"}
}