{
  "type": "Feature",
  "properties": {
    "addr:full":"65a Kent Ave Croydon VIC 3136",
    "addr:housenumber":"65a",
    "addr:postcode":"3136",
    "addr:street":"Kent Ave",
    "iso:country":"AU",
    "sg:address":"65a Kent Ave",
    "sg:city":"Croydon",
    "sg:classifiers":[
        {
            "category":"Manufacturing",
            "subcategory":"Tools & Machinery",
            "type":"Manufacturing & Wholesale Goods"
        }
    ],
    "sg:phone":"+61 418 385 535",
    "sg:postcode":"3136",
    "sg:province":"VIC",
    "wof:name":"REI Tools Pty Ltd",
    "wof:placetype":"venue"
},
  "geometry": {"coordinates":[145.27653503400001,-37.7896232605],"type":"Point"}
}