{
  "type": "Feature",
  "properties": {
    "iso:country":"AU",
    "sg:address":"4 Reibey St",
    "sg:city":"Ulverstone",
    "sg:classifiers":[
        {
            "category":"Autos & Motor Vehicles",
            "subcategory":"Auto Supplies",
            "type":"Retail Goods"
        }
    ],
    "sg:phone":"+61 3 6425 3337",
    "sg:postcode":"7315",
    "sg:province":"TAS",
    "sg:tags":[
        "part",
        "cycles",
        "accessory"
    ],
    "wof:name":"North West Motorcycles",
    "wof:placetype":"venue"
},
  "geometry": {"coordinates":[146.17608642600001,-41.1582870483],"type":"Point"}
}