{
  "type": "Feature",
  "properties": {
    "addr:full":"Shop 3, 11 Fletcher St Byron Bay NSW 2481",
    "addr:housenumber":"shop;11",
    "addr:postcode":"2481",
    "addr:street":"Fletcher St",
    "iso:country":"AU",
    "sg:address":"Shop 3, 11 Fletcher St",
    "sg:city":"Byron Bay",
    "sg:classifiers":[
        {
            "category":"Insurance",
            "subcategory":"Hazard Insurance",
            "type":"Services"
        }
    ],
    "sg:phone":"+61 2 6680 8590",
    "sg:postcode":"2481",
    "sg:province":"NSW",
    "sg:tags":[
        "fire",
        "accident",
        "marine"
    ],
    "wof:name":"Ausure Insurance & Finance",
    "wof:placetype":"venue"
},
  "geometry": {"coordinates":[153.61378479000001,-28.6435699463],"type":"Point"}
}