{
  "type": "Feature",
  "properties": {
    "iso:country":"AU",
    "sg:address":"Shelly Rd",
    "sg:city":"Walwa",
    "sg:classifiers":[
        {
            "category":"Building & Trades",
            "subcategory":"Plumbing",
            "type":"Services"
        }
    ],
    "sg:phone":"+61 409 371 398",
    "sg:postcode":"3709",
    "sg:province":"VIC",
    "sg:tags":[
        "plumber",
        "gasfitters"
    ],
    "wof:name":"Lee H M & G M Mountain Top Plumbing",
    "wof:placetype":"venue"
},
  "geometry": {"coordinates":[147.73544311500001,-35.9643592834],"type":"Point"}
}