{
  "type": "Feature",
  "properties": {
    "addr:full":"509 King St West Melbourne VIC 3003",
    "addr:housenumber":"509",
    "addr:postcode":"3003",
    "addr:street":"King St",
    "iso:country":"AU",
    "sg:address":"509 King St",
    "sg:city":"West Melbourne",
    "sg:classifiers":[
        {
            "category":"Government",
            "subcategory":"Department Of Motor Vehicles",
            "type":"Public Place"
        }
    ],
    "sg:phone":"+61 3 9328 5494",
    "sg:postcode":"3003",
    "sg:province":"VIC",
    "sg:tags":[
        "wholesaler",
        "mfrs",
        "accessory"
    ],
    "wof:name":"Work Wheels",
    "wof:placetype":"venue"
},
  "geometry": {"coordinates":[144.95149230999999,-37.8081054688],"type":"Point"}
}