{
  "type": "Feature",
  "properties": {
    "iso:country":"AU",
    "sg:address":"6 Blackwattle Pde",
    "sg:city":"Padbury",
    "sg:classifiers":[
        {
            "category":"Fast Food",
            "type":"Food & Drink"
        }
    ],
    "sg:phone":"+61 8 9402 0806",
    "sg:postcode":"6025",
    "sg:province":"WA",
    "sg:tags":[
        "away",
        "take"
    ],
    "wof:name":"Lefteris Quality Seafoods",
    "wof:placetype":"venue"
},
  "geometry": {"coordinates":[115.774261475,-31.818195343],"type":"Point"}
}