{
  "type": "Feature",
  "properties": {
    "addr:full":"117 East St Narrandera NSW 2700",
    "addr:housenumber":"117",
    "addr:postcode":"2700",
    "addr:street":"East St",
    "iso:country":"AU",
    "sg:address":"117 East St",
    "sg:city":"Narrandera",
    "sg:classifiers":[
        {
            "category":"Banks & Credit Unions",
            "subcategory":"Bank",
            "type":"Services"
        }
    ],
    "sg:phone":"+61 2 6959 3237",
    "sg:postcode":"2700",
    "sg:province":"NSW",
    "wof:name":"St.George Bank Limited",
    "wof:placetype":"venue"
},
  "geometry": {"coordinates":[146.553390503,-34.7461471558],"type":"Point"}
}