{
  "type": "Feature",
  "properties": {
    "addr:full":"Navarre Rd Landsborough VIC 3384",
    "addr:postcode":"3384",
    "addr:street":"Navarre Rd",
    "iso:country":"AU",
    "sg:address":"Navarre Rd",
    "sg:city":"Landsborough",
    "sg:classifiers":[
        {
            "category":"Real Estate",
            "subcategory":"Architect",
            "type":"Services"
        }
    ],
    "sg:phone":"+61 3 5356 9336",
    "sg:postcode":"3384",
    "sg:province":"VIC",
    "wof:name":"Dennis P Morris",
    "wof:placetype":"venue"
},
  "geometry": {"coordinates":[143.13075256400001,-37.0062408447],"type":"Point"}
}