{
  "type": "Feature",
  "properties": {
    "iso:country":"AU",
    "sg:address":"32 Kingsway St",
    "sg:city":"Glen Waverley",
    "sg:classifiers":[
        {
            "category":"Professional",
            "subcategory":"Accounting & Tax Preparation",
            "type":"Services"
        }
    ],
    "sg:phone":"+61 3 9887 9277",
    "sg:postcode":"3150",
    "sg:province":"VIC",
    "sg:tags":[
        "accountant",
        "auditor"
    ],
    "wof:name":"Demirci M & Associates",
    "wof:placetype":"venue"
},
  "geometry": {"coordinates":[145.16410827600001,-37.8792915344],"type":"Point"}
}