{
  "type": "Feature",
  "properties": {
    "iso:country":"AU",
    "sg:address":"70 Cabramatta Rd",
    "sg:city":"Mosman",
    "sg:classifiers":[
        {
            "category":"Professional",
            "subcategory":"Management & Consulting",
            "type":"Services"
        }
    ],
    "sg:phone":"+61 2 9953 0185",
    "sg:postcode":"2088",
    "sg:province":"NSW",
    "sg:tags":[
        "consultant",
        "business"
    ],
    "wof:name":"Arona Transition Strategies Pty Ltd",
    "wof:placetype":"venue"
},
  "geometry": {"coordinates":[151.23231506400001,-33.8294448853],"type":"Point"}
}