{
  "type": "Feature",
  "properties": {
    "addr:full":"Queen St Peterborough SA 5422",
    "addr:postcode":"5422",
    "addr:street":"Queen St",
    "iso:country":"AU",
    "sg:address":"Queen St",
    "sg:city":"Peterborough",
    "sg:classifiers":[
        {
            "category":"Education",
            "subcategory":"School",
            "type":"Public Place"
        }
    ],
    "sg:phone":"+61 8 8651 2306",
    "sg:postcode":"5422",
    "sg:province":"SA",
    "sg:tags":[
        "state",
        "except",
        "nsw"
    ],
    "wof:name":"Peterborough High School",
    "wof:placetype":"venue"
},
  "geometry": {"coordinates":[138.84014892600001,-32.9776535034],"type":"Point"}
}