{
  "type": "Feature",
  "properties": {
    "iso:country":"AU",
    "sg:address":"Unit 4, Falcon Grove Shopping Centre, Old Coast Rd",
    "sg:city":"Falcon",
    "sg:classifiers":[
        {
            "category":"Food & Beverages",
            "subcategory":"Liquor & Beverages",
            "type":"Retail Goods"
        }
    ],
    "sg:phone":"+61 8 9534 4500",
    "sg:postcode":"6210",
    "sg:province":"WA",
    "sg:tags":[
        "store"
    ],
    "wof:name":"Liquor Baron Falcon",
    "wof:placetype":"venue"
},
  "geometry": {"coordinates":[115.662201,-32.581303],"type":"Point"}
}