{
  "type": "Feature",
  "properties": {
    "addr:full":"633 Hume Hwy Casula NSW 2170",
    "addr:housenumber":"633",
    "addr:postcode":"2170",
    "addr:street":"Hume Hwy",
    "iso:country":"AU",
    "sg:address":"633 Hume Hwy",
    "sg:city":"Casula",
    "sg:classifiers":[
        {
            "category":"Transit Center",
            "subcategory":"Passenger",
            "type":"Transportation"
        }
    ],
    "sg:phone":"+61 2 9824 2549",
    "sg:postcode":"2170",
    "sg:province":"NSW",
    "sg:tags":[
        "frozen",
        "food",
        "retail"
    ],
    "wof:name":"Sara Lee Australia",
    "wof:placetype":"venue"
},
  "geometry": {"coordinates":[150.90510559099999,-33.9497337341],"type":"Point"}
}