{
  "type": "Feature",
  "properties": {
    "addr:full":"4/ 618 St Kilda Rd Melbourne VIC 3000",
    "addr:housenumber":"/ 618",
    "addr:postcode":"3000",
    "addr:street":"St Kilda Rd",
    "iso:country":"AU",
    "sg:address":"4/ 618 St Kilda Rd",
    "sg:city":"Melbourne",
    "sg:classifiers":[
        {
            "category":"Shopping",
            "subcategory":"Music",
            "type":"Retail Goods"
        }
    ],
    "sg:phone":"+61 3 9867 5058",
    "sg:postcode":"3000",
    "sg:province":"VIC",
    "sg:tags":[
        "store"
    ],
    "wof:name":"Thomas Music",
    "wof:placetype":"venue"
},
  "geometry": {"coordinates":[144.98118591299999,-37.852684021],"type":"Point"}
}