{
  "type": "Feature",
  "properties": {
    "iso:country":"AU",
    "sg:address":"26B Mitchell St",
    "sg:city":"Shepparton",
    "sg:classifiers":[
        {
            "category":"Retail",
            "subcategory":"Auto Repair",
            "type":"Services"
        }
    ],
    "sg:phone":"+61 3 5821 5703",
    "sg:postcode":"3630",
    "sg:province":"VIC",
    "sg:tags":[
        "repairer",
        "motor",
        "engineer"
    ],
    "wof:name":"Hans Stephan",
    "wof:placetype":"venue"
},
  "geometry": {"coordinates":[145.42013549800001,-36.3798828125],"type":"Point"}
}