{
  "type": "Feature",
  "properties": {
    "addr:full":"12 Rivers St South Yarra VIC 3141",
    "addr:housenumber":"12",
    "addr:postcode":"3141",
    "addr:street":"Rivers St",
    "iso:country":"AU",
    "sg:address":"12 Rivers St",
    "sg:city":"South Yarra",
    "sg:classifiers":[
        {
            "category":"Arts & Performance",
            "subcategory":"Art Gallery",
            "type":"Entertainment"
        }
    ],
    "sg:phone":"+61 3 9804 7366",
    "sg:postcode":"3141",
    "sg:province":"VIC",
    "wof:name":"Nellie Castan Gallery",
    "wof:placetype":"venue"
},
  "geometry": {"coordinates":[144.997512817,-37.8386459351],"type":"Point"}
}