{
  "type": "Feature",
  "properties": {
    "addr:full":"Charterhouse St Eaton WA 6232",
    "addr:postcode":"6232",
    "addr:street":"Charterhouse St",
    "iso:country":"AU",
    "sg:address":"Charterhouse St",
    "sg:city":"Eaton",
    "sg:classifiers":[
        {
            "category":"Education",
            "subcategory":"Kindergarten",
            "type":"Public Place"
        }
    ],
    "sg:phone":"+61 8 9725 3576",
    "sg:postcode":"6232",
    "sg:province":"WA",
    "sg:tags":[
        "pre-schools"
    ],
    "wof:name":"Eaton Primary School 4 Yr Olds",
    "wof:placetype":"venue"
},
  "geometry": {"coordinates":[115.69841,-33.318417],"type":"Point"}
}