{
  "type": "Feature",
  "properties": {
    "addr:full":"8 Bay Rd Sandringham VIC 3191",
    "addr:housenumber":"8",
    "addr:postcode":"3191",
    "addr:street":"Bay Rd",
    "iso:country":"AU",
    "sg:address":"8 Bay Rd",
    "sg:city":"Sandringham",
    "sg:classifiers":[
        {
            "category":"Health Services",
            "subcategory":"Dentist",
            "type":"Services"
        }
    ],
    "sg:phone":"+61 3 9598 2097",
    "sg:postcode":"3191",
    "sg:province":"VIC",
    "wof:name":"Williams G",
    "wof:placetype":"venue"
},
  "geometry": {"coordinates":[145.00411987300001,-37.9518280029],"type":"Point"}
}