{
  "type": "Feature",
  "properties": {
    "addr:full":"318 Pinjarra Rd Mandurah WA 6210",
    "addr:housenumber":"318",
    "addr:postcode":"6210",
    "addr:street":"Pinjarra Rd",
    "iso:country":"AU",
    "sg:address":"318 Pinjarra Rd",
    "sg:city":"Mandurah",
    "sg:classifiers":[
        {
            "category":"Professional",
            "subcategory":"Accounting & Tax Preparation",
            "type":"Services"
        }
    ],
    "sg:phone":"+61 8 9586 9880",
    "sg:postcode":"6210",
    "sg:province":"WA",
    "sg:tags":[
        "jukebox"
    ],
    "wof:name":"Party Plus Mandurah",
    "wof:placetype":"venue"
},
  "geometry": {"coordinates":[115.78112,-32.553883],"type":"Point"}
}