{
  "type": "Feature",
  "properties": {
    "iso:country":"AU",
    "sg:address":"539 Sydney Rd",
    "sg:city":"Brunswick",
    "sg:classifiers":[
        {
            "category":"Professional",
            "subcategory":"Art Services",
            "type":"Services"
        }
    ],
    "sg:phone":"+61 3 9388 1077",
    "sg:postcode":"3056",
    "sg:province":"VIC",
    "sg:tags":[
        "picture",
        "frame",
        "framing"
    ],
    "wof:name":"Brunswick Framing Centre",
    "wof:placetype":"venue"
},
  "geometry": {"coordinates":[144.96232605,-37.7645950317],"type":"Point"}
}