{
  "type": "Feature",
  "properties": {
    "addr:full":"165 Emu Bay Rd Deloraine TAS 7304",
    "addr:housenumber":"165",
    "addr:postcode":"7304",
    "addr:street":"Emu Bay Rd",
    "iso:country":"AU",
    "sg:address":"165 Emu Bay Rd",
    "sg:city":"Deloraine",
    "sg:classifiers":[
        {
            "category":"Professional",
            "type":"Services"
        }
    ],
    "sg:phone":"+61 417 561 568",
    "sg:postcode":"7304",
    "sg:province":"TAS",
    "sg:tags":[
        "courier"
    ],
    "wof:name":"Meander Valley Transport",
    "wof:placetype":"venue"
},
  "geometry": {"coordinates":[146.63705400000001,-41.514736],"type":"Point"}
}