{
  "type": "Feature",
  "properties": {
    "addr:full":"42 Rolling Hills Rd Chirnside Park VIC 3116",
    "addr:housenumber":"42",
    "addr:postcode":"3116",
    "addr:street":"Rolling Hills Rd",
    "iso:country":"AU",
    "sg:address":"42 Rolling Hills Rd",
    "sg:city":"Chirnside Park",
    "sg:classifiers":[
        {
            "category":"Education",
            "subcategory":"Music School",
            "type":"Public Place"
        }
    ],
    "sg:phone":"+61 3 9735 4975",
    "sg:postcode":"3116",
    "sg:province":"VIC",
    "sg:tags":[
        "choir",
        "bands",
        "orchestra"
    ],
    "wof:name":"Mozart Down Under",
    "wof:placetype":"venue"
},
  "geometry": {"coordinates":[145.32882690400001,-37.7483558655],"type":"Point"}
}