{
  "type": "Feature",
  "properties": {
    "iso:country":"AU",
    "sg:address":"5 McInnes St",
    "sg:city":"Ridleyton",
    "sg:classifiers":[
        {
            "category":"Wholesale",
            "subcategory":"Painting Supplies",
            "type":"Manufacturing & Wholesale Goods"
        }
    ],
    "sg:phone":"+61 8 8340 0600",
    "sg:postcode":"5008",
    "sg:province":"SA",
    "sg:tags":[
        "equipment",
        "tiling"
    ],
    "wof:name":"P A J Agencies",
    "wof:placetype":"venue"
},
  "geometry": {"coordinates":[138.56749,-34.899223],"type":"Point"}
}