{
  "type": "Feature",
  "properties": {
    "addr:full":"Shop 14 Southside Tce Wodonga VIC 3690",
    "addr:housenumber":"shop 14",
    "addr:postcode":"3690",
    "addr:street":"Southside Tce",
    "iso:country":"AU",
    "sg:address":"Shop 14 Southside Tce",
    "sg:city":"Wodonga",
    "sg:classifiers":[
        {
            "category":"Home & Garden",
            "subcategory":"Household Appliances",
            "type":"Retail Goods"
        }
    ],
    "sg:phone":"+61 2 6024 5345",
    "sg:postcode":"3690",
    "sg:province":"VIC",
    "sg:tags":[
        "heating",
        "system"
    ],
    "wof:name":"Murray River Airconditioning",
    "wof:placetype":"venue"
},
  "geometry": {"coordinates":[146.892501831,-36.1128997803],"type":"Point"}
}