{
  "type": "Feature",
  "properties": {
    "addr:full":"63 Deakin St Bentleigh East VIC 3165",
    "addr:housenumber":"63",
    "addr:postcode":"3165",
    "addr:street":"Deakin St",
    "iso:country":"AU",
    "sg:address":"63 Deakin St",
    "sg:city":"Bentleigh East",
    "sg:classifiers":[
        {
            "category":"Manufacturing",
            "subcategory":"Motor Vehicles & Parts",
            "type":"Manufacturing & Wholesale Goods"
        }
    ],
    "sg:phone":"+61 3 9570 1086",
    "sg:postcode":"3165",
    "sg:province":"VIC",
    "sg:tags":[
        "replacement"
    ],
    "wof:name":"Studebaker Parts",
    "wof:placetype":"venue"
},
  "geometry": {"coordinates":[145.06907653799999,-37.9141693115],"type":"Point"}
}