{
  "type": "Feature",
  "properties": {
    "addr:full":"335A Clayton Rd Clayton VIC 3168",
    "addr:housenumber":"335a",
    "addr:postcode":"3168",
    "addr:street":"Clayton Rd",
    "iso:country":"AU",
    "sg:address":"335A Clayton Rd",
    "sg:city":"Clayton",
    "sg:classifiers":[
        {
            "category":"Professional",
            "subcategory":"Computer Services",
            "type":"Services"
        }
    ],
    "sg:phone":"+61 3 9543 1880",
    "sg:postcode":"3168",
    "sg:province":"VIC",
    "sg:tags":[
        "repairs",
        "upgrade",
        "equipment"
    ],
    "wof:name":"ASP Technology",
    "wof:placetype":"venue"
},
  "geometry": {"coordinates":[145.11955261200001,-37.9251213074],"type":"Point"}
}