{
  "type": "Feature",
  "properties": {
    "iso:country":"AU",
    "sg:address":"65 Auburn St",
    "sg:city":"Wollongong",
    "sg:classifiers":[
        {
            "category":"Health Services",
            "subcategory":"Health Practitioner",
            "type":"Services"
        }
    ],
    "sg:phone":"+61 2 4227 1990",
    "sg:postcode":"2500",
    "sg:province":"NSW",
    "sg:tags":[
        "physiotherapist"
    ],
    "wof:name":"Baimed Physiotherapy & Sports Injury Clinic",
    "wof:placetype":"venue"
},
  "geometry": {"coordinates":[150.888504,-34.432434],"type":"Point"}
}