{
  "type": "Feature",
  "properties": {
    "addr:full":"11 Edithburgh Rd Yorketown SA 5576",
    "addr:housenumber":"11",
    "addr:postcode":"5576",
    "addr:street":"Edithburgh Rd",
    "iso:country":"AU",
    "sg:address":"11 Edithburgh Rd",
    "sg:city":"Yorketown",
    "sg:classifiers":[
        {
            "category":"Home & Garden",
            "subcategory":"Carpets & Floor Coverings",
            "type":"Retail Goods"
        }
    ],
    "sg:phone":"+61 8 8852 1054",
    "sg:postcode":"5576",
    "sg:province":"SA",
    "wof:name":"Launer C P",
    "wof:placetype":"venue"
},
  "geometry": {"coordinates":[137.606155395,-35.0193634033],"type":"Point"}
}