{
  "type": "Feature",
  "properties": {
    "addr:full":"143 Diamond Hill Drv Kurrajong NSW 2758",
    "addr:housenumber":"143",
    "addr:postcode":"2758",
    "addr:street":"Diamond Hill Drv",
    "iso:country":"AU",
    "sg:address":"143 Diamond Hill Drv",
    "sg:city":"Kurrajong",
    "sg:classifiers":[
        {
            "category":"Manufacturing",
            "subcategory":"Apparel",
            "type":"Manufacturing & Wholesale Goods"
        }
    ],
    "sg:phone":"+61 2 4567 7689",
    "sg:postcode":"2758",
    "sg:province":"NSW",
    "sg:tags":[
        "wholesaler",
        "mfrs",
        "footwear"
    ],
    "wof:name":"Barnett Footwear Agency",
    "wof:placetype":"venue"
},
  "geometry": {"coordinates":[150.672775269,-33.5290718079],"type":"Point"}
}