{
  "type": "Feature",
  "properties": {
    "addr:full":"584 Springvale Rd Springvale South VIC 3172",
    "addr:housenumber":"584",
    "addr:postcode":"3172",
    "addr:street":"Springvale Rd",
    "iso:country":"AU",
    "sg:address":"584 Springvale Rd",
    "sg:city":"Springvale South",
    "sg:classifiers":[
        {
            "category":"Home & Garden",
            "subcategory":"Building Materials",
            "type":"Retail Goods"
        }
    ],
    "sg:phone":"+61 3 9546 1155",
    "sg:postcode":"3172",
    "sg:province":"VIC",
    "sg:tags":[
        "supply"
    ],
    "wof:name":"Ideal Garden & Building",
    "wof:placetype":"venue"
},
  "geometry": {"coordinates":[145.14669799800001,-37.9784622192],"type":"Point"}
}