{
  "type": "Feature",
  "properties": {
    "addr:full":"130 Gaffney St Coburg VIC 3058",
    "addr:housenumber":"130",
    "addr:postcode":"3058",
    "addr:street":"Gaffney St",
    "iso:country":"AU",
    "sg:address":"130 Gaffney St",
    "sg:city":"Coburg",
    "sg:classifiers":[
        {
            "category":"Fast Food",
            "type":"Food & Drink"
        }
    ],
    "sg:phone":"+61 3 9354 6690",
    "sg:postcode":"3058",
    "sg:province":"VIC",
    "sg:tags":[
        "away",
        "take"
    ],
    "wof:name":"Home Made Take Away",
    "wof:placetype":"venue"
},
  "geometry": {"coordinates":[144.95555114699999,-37.7329368591],"type":"Point"}
}