{
  "type": "Feature",
  "properties": {
    "addr:full":"30 The Bond 30 Hickson Rd Millers Point NSW 2000",
    "addr:housenumber":"30;30",
    "addr:postcode":"2000",
    "addr:street":"The Bond;Hickson Rd",
    "iso:country":"AU",
    "sg:address":"30 The Bond 30 Hickson Rd",
    "sg:city":"Millers Point",
    "sg:classifiers":[
        {
            "category":"Real Estate",
            "subcategory":"Developer",
            "type":"Services"
        }
    ],
    "sg:phone":"+61 2 9236 6111",
    "sg:postcode":"2000",
    "sg:province":"NSW",
    "sg:tags":[
        "development"
    ],
    "wof:name":"Lend Lease Corporation",
    "wof:placetype":"venue"
},
  "geometry": {"coordinates":[151.20301818900001,-33.857624054],"type":"Point"}
}