{
  "type": "Feature",
  "properties": {
    "iso:country":"AU",
    "sg:address":"Unit 1/ 2 Mozart St St",
    "sg:city":"Kilda",
    "sg:classifiers":[
        {
            "category":"Personal",
            "subcategory":"Massage",
            "type":"Services"
        }
    ],
    "sg:phone":"+61 409 806 733",
    "sg:postcode":"3182",
    "sg:province":"VIC",
    "sg:tags":[
        "therapy"
    ],
    "wof:name":"Peter Jeffrey",
    "wof:placetype":"venue"
},
  "geometry": {"coordinates":[144.987823486,-37.8699455261],"type":"Point"}
}