{
  "type": "Feature",
  "properties": {
    "iso:country":"AU",
    "sg:address":"28 Roslyn St",
    "sg:city":"Ashbury",
    "sg:classifiers":[
        {
            "category":"Wholesale",
            "subcategory":"Home Furnishings",
            "type":"Manufacturing & Wholesale Goods"
        }
    ],
    "sg:phone":"+61 2 9716 6945",
    "sg:postcode":"2193",
    "sg:province":"NSW",
    "sg:tags":[
        "wholesaler",
        "mfrs",
        "manchester"
    ],
    "wof:name":"Jamestex Agents & Consultants",
    "wof:placetype":"venue"
},
  "geometry": {"coordinates":[151.11639400000001,-33.901791],"type":"Point"}
}