{
  "type": "Feature",
  "properties": {
    "iso:country":"AU",
    "sg:address":"12 Kylie Pl",
    "sg:city":"Cheltenham",
    "sg:classifiers":[
        {
            "category":"Communications",
            "subcategory":"Television Station",
            "type":"Services"
        }
    ],
    "sg:phone":"+61 3 9553 3600",
    "sg:postcode":"3192",
    "sg:province":"VIC",
    "sg:tags":[
        "wholesaler",
        "wire",
        "mfrs",
        "electric",
        "cable"
    ],
    "wof:name":"Teclec Australia Pty Ltd",
    "wof:placetype":"venue"
},
  "geometry": {"coordinates":[145.06312560999999,-37.949432373],"type":"Point"}
}