{
  "type": "Feature",
  "properties": {
    "addr:full":"7 Moresby St Trinity Beach QLD 4879",
    "addr:housenumber":"7",
    "addr:postcode":"4879",
    "addr:street":"Moresby St",
    "iso:country":"AU",
    "sg:address":"7 Moresby St",
    "sg:city":"Trinity Beach",
    "sg:classifiers":[
        {
            "category":"Home & Garden",
            "subcategory":"Building Materials",
            "type":"Retail Goods"
        }
    ],
    "sg:phone":"+61 7 4057 9440",
    "sg:postcode":"4879",
    "sg:province":"QLD",
    "sg:tags":[
        "plaster",
        "plasterboard",
        "supply"
    ],
    "wof:name":"The Plaster Mob",
    "wof:placetype":"venue"
},
  "geometry": {"coordinates":[145.69786071799999,-16.7907714844],"type":"Point"}
}