{
  "type": "Feature",
  "properties": {
    "addr:full":"17 Bayview St McMahons Point NSW 2060",
    "addr:housenumber":"17",
    "addr:postcode":"2060",
    "addr:street":"Bayview St",
    "iso:country":"AU",
    "sg:address":"17 Bayview St",
    "sg:city":"McMahons Point",
    "sg:classifiers":[
        {
            "category":"Recreation",
            "subcategory":"Boat Charter",
            "type":"Entertainment"
        }
    ],
    "sg:phone":"+61 2 9929 0728",
    "sg:postcode":"2060",
    "sg:province":"NSW",
    "wof:name":"A1 Bluewater Charters",
    "wof:placetype":"venue"
},
  "geometry": {"coordinates":[151.2059021,-33.8455696106],"type":"Point"}
}