{
  "type": "Feature",
  "properties": {
    "addr:full":"Lot 51 Napier Tce Broome WA 6725",
    "addr:postcode":"6725",
    "addr:street":"Napier Tce",
    "iso:country":"AU",
    "sg:address":"Lot 51 Napier Tce",
    "sg:city":"Broome",
    "sg:classifiers":[
        {
            "category":"Fast Food",
            "type":"Food & Drink"
        }
    ],
    "sg:phone":"+61 8 9193 7565",
    "sg:postcode":"6725",
    "sg:province":"WA",
    "sg:tags":[
        "away",
        "take"
    ],
    "wof:name":"Chicken Treat",
    "wof:placetype":"venue"
},
  "geometry": {"coordinates":[122.24372863799999,-17.9554023743],"type":"Point"}
}