{
  "type": "Feature",
  "properties": {
    "addr:full":"Suite 54 , Commercial Centre, Via Roma Isle Of Capri QLD 4217",
    "addr:postcode":"4217",
    "addr:street":"Via Roma",
    "iso:country":"AU",
    "sg:address":"Suite 54",
    "sg:city":", Commercial Centre, Via Roma Isle Of Capri",
    "sg:classifiers":[
        {
            "category":"Personal",
            "subcategory":"Beauty Salon",
            "type":"Services"
        }
    ],
    "sg:phone":"+61 7 5504 6299",
    "sg:postcode":"4217",
    "sg:province":"QLD",
    "wof:name":"Isle Of Beauty On Capri",
    "wof:placetype":"venue"
},
  "geometry": {"coordinates":[153.42341613799999,-28.0122699738],"type":"Point"}
}