{
  "type": "Feature",
  "properties": {
    "addr:full":"Unit 3, 15- 16 Nicole Cl Bayswater North VIC 3153",
    "addr:housenumber":"15 16",
    "addr:postcode":"3153",
    "addr:street":"Nicole Cl",
    "iso:country":"AU",
    "sg:address":"Unit 3, 15- 16 Nicole Cl",
    "sg:city":"Bayswater North",
    "sg:classifiers":[
        {
            "category":"Military Area",
            "subcategory":"Air Force Base",
            "type":"Public Place"
        }
    ],
    "sg:phone":"+61 3 9761 7600",
    "sg:postcode":"3153",
    "sg:province":"VIC",
    "sg:tags":[
        "fibre",
        "optic"
    ],
    "wof:name":"Anderson Corporation Pty Ltd",
    "wof:placetype":"venue"
},
  "geometry": {"coordinates":[145.29005432100001,-37.8253211975],"type":"Point"}
}