{
  "type": "Feature",
  "properties": {
    "addr:full":"Tambourine Rd Windaroo QLD 4207",
    "addr:postcode":"4207",
    "addr:street":"Tambourine Rd",
    "iso:country":"AU",
    "sg:address":"Tambourine Rd",
    "sg:city":"Windaroo",
    "sg:classifiers":[
        {
            "category":"Arena",
            "subcategory":"Sports Club",
            "type":"Entertainment"
        }
    ],
    "sg:phone":"+61 7 3804 0333",
    "sg:postcode":"4207",
    "sg:province":"QLD",
    "sg:tags":[
        "union",
        "rugby"
    ],
    "wof:name":"Beenleigh & District Rugby Union Club",
    "wof:placetype":"venue"
},
  "geometry": {"coordinates":[153.19134521500001,-27.7409000397],"type":"Point"}
}