{
  "type": "Feature",
  "properties": {
    "addr:full":"11 Egan St Newnham TAS 7248",
    "addr:housenumber":"11",
    "addr:postcode":"7248",
    "addr:street":"Egan St",
    "iso:country":"AU",
    "sg:address":"11 Egan St",
    "sg:city":"Newnham",
    "sg:classifiers":[
        {
            "category":"Manufacturing",
            "subcategory":"Printing",
            "type":"Manufacturing & Wholesale Goods"
        }
    ],
    "sg:phone":"+61 3 6326 9010",
    "sg:postcode":"7248",
    "sg:province":"TAS",
    "sg:tags":[
        "wholesaler",
        "mfrs",
        "greeting",
        "card"
    ],
    "wof:name":"ABC Cards",
    "wof:placetype":"venue"
},
  "geometry": {"coordinates":[147.12948608400001,-41.3921546936],"type":"Point"}
}