{
  "type": "Feature",
  "properties": {
    "iso:country":"AU",
    "sg:address":"353 Enmore Rd",
    "sg:city":"Marrickville",
    "sg:classifiers":[
        {
            "category":"Building & Trades",
            "subcategory":"Plumbing",
            "type":"Services"
        }
    ],
    "sg:phone":"+61 2 9519 3837",
    "sg:postcode":"2204",
    "sg:province":"NSW",
    "sg:tags":[
        "plumber",
        "gasfitters"
    ],
    "wof:name":"Michael Barnby",
    "wof:placetype":"venue"
},
  "geometry": {"coordinates":[151.168533,-33.903419],"type":"Point"}
}