{
  "type": "Feature",
  "properties": {
    "iso:country":"AU",
    "sg:address":"26 High St",
    "sg:city":"Drysdale",
    "sg:classifiers":[
        {
            "category":"Fast Food",
            "type":"Food & Drink"
        }
    ],
    "sg:phone":"+61 3 5251 3937",
    "sg:postcode":"3222",
    "sg:province":"VIC",
    "sg:tags":[
        "away",
        "take"
    ],
    "wof:name":"Drysdale Village Pizza",
    "wof:placetype":"venue"
},
  "geometry": {"coordinates":[144.56933599999999,-38.174057],"type":"Point"}
}