{
  "type": "Feature",
  "properties": {
    "addr:full":"56 Ford St Ganmain NSW 2702",
    "addr:housenumber":"56",
    "addr:postcode":"2702",
    "addr:street":"Ford St",
    "iso:country":"AU",
    "sg:address":"56 Ford St",
    "sg:city":"Ganmain",
    "sg:classifiers":[
        {
            "category":"Autos & Motor Vehicles",
            "subcategory":"Fuel & Gas Station",
            "type":"Retail Goods"
        }
    ],
    "sg:phone":"+61 2 6927 6415",
    "sg:postcode":"2702",
    "sg:province":"NSW",
    "wof:name":"Brills Central Garage",
    "wof:placetype":"venue"
},
  "geometry": {"coordinates":[147.038986206,-34.7929954529],"type":"Point"}
}