{
  "type": "Feature",
  "properties": {
    "addr:full":"24 Catherine St Ayr QLD 4807",
    "addr:housenumber":"24",
    "addr:postcode":"4807",
    "addr:street":"Catherine St",
    "iso:country":"AU",
    "sg:address":"24 Catherine St",
    "sg:city":"Ayr",
    "sg:classifiers":[
        {
            "category":"Building & Trades",
            "subcategory":"Plumbing",
            "type":"Services"
        }
    ],
    "sg:phone":"+61 419 771 480",
    "sg:postcode":"4807",
    "sg:province":"QLD",
    "sg:tags":[
        "plumber",
        "gasfitters"
    ],
    "wof:name":"Roser R E",
    "wof:placetype":"venue"
},
  "geometry": {"coordinates":[147.42079162600001,-19.5776557922],"type":"Point"}
}