{
  "type": "Feature",
  "properties": {
    "addr:full":"20 Main St Kapunda SA 5373",
    "addr:housenumber":"20",
    "addr:postcode":"5373",
    "addr:street":"Main St",
    "iso:country":"AU",
    "sg:address":"20 Main St",
    "sg:city":"Kapunda",
    "sg:classifiers":[
        {
            "category":"Home & Garden",
            "subcategory":"Building Materials",
            "type":"Retail Goods"
        }
    ],
    "sg:phone":"+61 8 8566 2922",
    "sg:postcode":"5373",
    "sg:province":"SA",
    "sg:tags":[
        "shutter",
        "roller",
        "grille"
    ],
    "wof:name":"Home Seal Roller Shutters",
    "wof:placetype":"venue"
},
  "geometry": {"coordinates":[138.91668701200001,-34.3393096924],"type":"Point"}
}