{
  "type": "Feature",
  "properties": {
    "addr:full":"1243 Point Nepean Rd Rosebud VIC 3939",
    "addr:housenumber":"1243",
    "addr:postcode":"3939",
    "addr:street":"Point Nepean Rd",
    "iso:country":"AU",
    "sg:address":"1243 Point Nepean Rd",
    "sg:city":"Rosebud",
    "sg:classifiers":[
        {
            "category":"Banks & Credit Unions",
            "subcategory":"Financial Services",
            "type":"Services"
        }
    ],
    "sg:phone":"+61 3 5982 3700",
    "sg:postcode":"3939",
    "sg:province":"VIC",
    "sg:tags":[
        "loan",
        "finance",
        "mortgage"
    ],
    "wof:name":"Mortgage House Of Australia",
    "wof:placetype":"venue"
},
  "geometry": {"coordinates":[144.895721436,-38.358379364],"type":"Point"}
}