{
  "type": "Feature",
  "properties": {
    "iso:country":"AU",
    "sg:address":"16 Helena La",
    "sg:city":"Cawarral",
    "sg:classifiers":[
        {
            "category":"Park",
            "subcategory":"County",
            "type":"Public Place"
        }
    ],
    "sg:phone":"+61 7 4934 4588",
    "sg:postcode":"4702",
    "sg:province":"QLD",
    "sg:tags":[
        "sanctuary",
        "zoos",
        "animal"
    ],
    "wof:name":"Central Queensland Wildlife Hospital Association",
    "wof:placetype":"venue"
},
  "geometry": {"coordinates":[151.35188293499999,-23.9434871674],"type":"Point"}
}