{
  "type": "Feature",
  "properties": {
    "addr:full":"50 Cleveland St Stones Corner QLD 4120",
    "addr:housenumber":"50",
    "addr:postcode":"4120",
    "addr:street":"Cleveland St",
    "iso:country":"AU",
    "sg:address":"50 Cleveland St",
    "sg:city":"Stones Corner",
    "sg:classifiers":[
        {
            "category":"Banks & Credit Unions",
            "subcategory":"Investment Brokerage",
            "type":"Services"
        }
    ],
    "sg:phone":"+61 1300 367 369",
    "sg:postcode":"4120",
    "sg:province":"QLD",
    "sg:tags":[
        "finance",
        "broker"
    ],
    "wof:name":"Network Finance Pty Ltd",
    "wof:placetype":"venue"
},
  "geometry": {"coordinates":[153.04403686500001,-27.4993877411],"type":"Point"}
}