{
  "type": "Feature",
  "properties": {
    "iso:country":"AU",
    "sg:address":"30 Alfred Rd",
    "sg:city":"Chipping Norton",
    "sg:classifiers":[
        {
            "category":"Banks & Credit Unions",
            "subcategory":"Financial Services",
            "type":"Services"
        }
    ],
    "sg:phone":"+61 1800 000 407",
    "sg:postcode":"2170",
    "sg:province":"NSW",
    "sg:tags":[
        "equipment",
        "chain"
    ],
    "wof:name":"Load Restraint Systems Pty. Ltd.",
    "wof:placetype":"venue"
},
  "geometry": {"coordinates":[150.964767456,-33.9232330322],"type":"Point"}
}