{
  "type": "Feature",
  "properties": {
    "addr:full":"PO Box 137 O'Halloran Hill SA 5158",
    "addr:postcode":"5158",
    "addr:street":"O'Halloran",
    "iso:country":"AU",
    "sg:address":"PO Box 137",
    "sg:city":"O'Halloran Hill",
    "sg:classifiers":[
        {
            "category":"Building & Trades",
            "subcategory":"Construction",
            "type":"Services"
        }
    ],
    "sg:phone":"+61 8 8376 8350",
    "sg:postcode":"5158",
    "sg:province":"SA",
    "sg:tags":[
        "tennis court",
        "repair"
    ],
    "wof:name":"Recreational Surfaces",
    "wof:placetype":"venue"
},
  "geometry": {"coordinates":[138.52659606899999,-35.064868927],"type":"Point"}
}