{
  "type": "Feature",
  "properties": {
    "iso:country":"AU",
    "sg:address":"5 Getting St",
    "sg:city":"Campbell",
    "sg:classifiers":[
        {
            "category":"Building & Trades",
            "subcategory":"Construction",
            "type":"Services"
        }
    ],
    "sg:phone":"+61 2 6262 9286",
    "sg:postcode":"2612",
    "sg:province":"ACT",
    "sg:tags":[
        "contractor"
    ],
    "wof:name":"Euphoria Construction P/L",
    "wof:placetype":"venue"
},
  "geometry": {"coordinates":[149.145385742,-35.2906227112],"type":"Point"}
}