{
  "type": "Feature",
  "properties": {
    "iso:country":"AU",
    "sg:address":"184 Beechboro Rd",
    "sg:city":"Bayswater",
    "sg:classifiers":[
        {
            "category":"Retail",
            "subcategory":"Auto Repair",
            "type":"Services"
        }
    ],
    "sg:phone":"+61 8 9272 1144",
    "sg:postcode":"6053",
    "sg:province":"WA",
    "sg:tags":[
        "repairer",
        "motor",
        "engineer"
    ],
    "wof:name":"Delcon Automotive Engineering",
    "wof:placetype":"venue"
},
  "geometry": {"coordinates":[115.92124176,-31.8987503052],"type":"Point"}
}