{
  "type": "Feature",
  "properties": {
    "addr:full":"2 Kellett St Kings Cross NSW 2011",
    "addr:housenumber":"2",
    "addr:postcode":"2011",
    "addr:street":"Kellett St",
    "iso:country":"AU",
    "sg:address":"2 Kellett St",
    "sg:city":"Kings Cross",
    "sg:classifiers":[
        {
            "category":"Bars & Pubs",
            "subcategory":"Nightclub",
            "type":"Food & Drink"
        }
    ],
    "sg:phone":"+61 2 9331 0058",
    "sg:postcode":"2011",
    "sg:province":"NSW",
    "sg:tags":[
        "discotheque"
    ],
    "wof:name":"Sapphire Suite",
    "wof:placetype":"venue"
},
  "geometry": {"coordinates":[151.22340393100001,-33.8748893738],"type":"Point"}
}