{
  "type": "Feature",
  "properties": {
    "addr:full":"27 Range Rd Sarina QLD 4737",
    "addr:housenumber":"27",
    "addr:postcode":"4737",
    "addr:street":"Range Rd",
    "iso:country":"AU",
    "sg:address":"27 Range Rd",
    "sg:city":"Sarina",
    "sg:classifiers":[
        {
            "category":"Organizations",
            "subcategory":"Professional Association",
            "type":"Services"
        }
    ],
    "sg:phone":"+61 7 4956 1081",
    "sg:postcode":"4737",
    "sg:province":"QLD",
    "sg:tags":[
        "organisation",
        "business"
    ],
    "wof:name":"Queensland Auxiliary Firefighters Association",
    "wof:placetype":"venue"
},
  "geometry": {"coordinates":[149.21196,-21.4251],"type":"Point"}
}