{
  "type": "Feature",
  "properties": {
    "addr:full":"Suite 9, 8 Marathon Rd Darling Point NSW 2027",
    "addr:housenumber":"8",
    "addr:postcode":"2027",
    "addr:street":"Marathon Rd",
    "iso:country":"AU",
    "sg:address":"Suite 9, 8 Marathon Rd",
    "sg:city":"Darling Point",
    "sg:classifiers":[
        {
            "category":"Professional",
            "subcategory":"Art Services",
            "type":"Services"
        }
    ],
    "sg:phone":"+61 2 9328 5548",
    "sg:postcode":"2027",
    "sg:province":"NSW",
    "sg:tags":[
        "interior",
        "designer"
    ],
    "wof:name":"Dreamtime Australia Group",
    "wof:placetype":"venue"
},
  "geometry": {"coordinates":[151.23965454099999,-33.8737983704],"type":"Point"}
}