{
  "type": "Feature",
  "properties": {
    "iso:country":"AU",
    "sg:address":"75 Pynsent St",
    "sg:city":"Horsham",
    "sg:classifiers":[
        {
            "category":"Real Estate",
            "subcategory":"Real Estate Agent",
            "type":"Services"
        }
    ],
    "sg:phone":"+61 3 5381 1616",
    "sg:postcode":"3400",
    "sg:province":"VIC",
    "wof:name":"Rathgebers Real Estate",
    "wof:placetype":"venue"
},
  "geometry": {"coordinates":[142.19801330600001,-36.7155418396],"type":"Point"}
}