{
  "type": "Feature",
  "properties": {
    "addr:full":"Unit 2, 2 Stanbury Pl Quakers Hill NSW 2763",
    "addr:housenumber":"2",
    "addr:postcode":"2763",
    "addr:street":"Stanbury Pl",
    "iso:country":"AU",
    "sg:address":"Unit 2, 2 Stanbury Pl",
    "sg:city":"Quakers Hill",
    "sg:classifiers":[
        {
            "category":"Personal",
            "subcategory":"Sauna",
            "type":"Services"
        }
    ],
    "sg:phone":"+61 425 230 785",
    "sg:postcode":"2763",
    "sg:province":"NSW",
    "sg:tags":[
        "equipment",
        "accessory"
    ],
    "sg:website":"http://www.ukkosaunas.com.au",
    "wof:name":"Ukko Saunas",
    "wof:placetype":"venue"
},
  "geometry": {"coordinates":[150.89146423299999,-33.7269821167],"type":"Point"}
}