{
  "type": "Feature",
  "properties": {
    "addr:full":"Great Western Hwy Wentworth Falls NSW 2782",
    "addr:postcode":"2782",
    "addr:street":"Great Western Hwy",
    "iso:country":"AU",
    "sg:address":"Great Western Hwy",
    "sg:city":"Wentworth Falls",
    "sg:classifiers":[
        {
            "category":"Manufacturing",
            "subcategory":"Pottery",
            "type":"Manufacturing & Wholesale Goods"
        }
    ],
    "sg:phone":"+61 2 4757 4230",
    "sg:postcode":"2782",
    "sg:province":"NSW",
    "wof:name":"Wentworth Falls Pots",
    "wof:placetype":"venue"
},
  "geometry": {"coordinates":[150.38714599599999,-33.7268676758],"type":"Point"}
}