{
  "type": "Feature",
  "properties": {
    "addr:full":"25 Jamieson St Cardwell QLD 4849",
    "addr:housenumber":"25",
    "addr:postcode":"4849",
    "addr:street":"Jamieson St",
    "iso:country":"AU",
    "sg:address":"25 Jamieson St",
    "sg:city":"Cardwell",
    "sg:classifiers":[
        {
            "category":"Building & Trades",
            "subcategory":"Construction",
            "type":"Services"
        }
    ],
    "sg:phone":"+61 7 4066 8694",
    "sg:postcode":"4849",
    "sg:province":"QLD",
    "sg:tags":[
        "contractor"
    ],
    "wof:name":"Gerry Dyer Building Contractor",
    "wof:placetype":"venue"
},
  "geometry": {"coordinates":[146.016571,-18.252264],"type":"Point"}
}