{
  "type": "Feature",
  "properties": {
    "iso:country":"AU",
    "sg:address":"2989 Gold Coast Hwy",
    "sg:city":"Surfers Paradise",
    "sg:classifiers":[
        {
            "category":"Recreation",
            "type":"Entertainment"
        }
    ],
    "sg:phone":"+61 427 640 042",
    "sg:postcode":"4217",
    "sg:province":"QLD",
    "sg:tags":[
        "hire",
        "tour",
        "motor",
        "cycle"
    ],
    "wof:name":"MOPEDS IN PARADISE",
    "wof:placetype":"venue"
},
  "geometry": {"coordinates":[153.42953491200001,-28.0110912323],"type":"Point"}
}