{
  "type": "Feature",
  "properties": {
    "addr:full":"Shop 51, Sorrento Quay, Hillarys Boat Harbour Hillarys WA 6025",
    "addr:housenumber":"shop 51",
    "addr:postcode":"6025",
    "addr:street":"Sorrento Quay",
    "iso:country":"AU",
    "sg:address":"Shop 51, Sorrento Quay, Hillarys Boat Harbour",
    "sg:city":"Hillarys",
    "sg:classifiers":[
        {
            "category":"Cafe",
            "type":"Food & Drink"
        }
    ],
    "sg:phone":"+61 8 9243 1700",
    "sg:postcode":"6025",
    "sg:province":"WA",
    "wof:name":"Sorrento Globe Cafe",
    "wof:placetype":"venue"
},
  "geometry": {"coordinates":[115.744338989,-31.8261623383],"type":"Point"}
}