{
  "type": "Feature",
  "properties": {
    "iso:country":"AU",
    "sg:address":"Locked Bag 26",
    "sg:city":"Mackay",
    "sg:classifiers":[
        {
            "category":"Professional",
            "subcategory":"Accounting & Tax Preparation",
            "type":"Services"
        }
    ],
    "sg:phone":"+61 1800 023 380",
    "sg:postcode":"4740",
    "sg:province":"QLD",
    "sg:tags":[
        "insulation",
        "wholesaler",
        "material",
        "mfrs"
    ],
    "wof:name":"Bradford Insulation",
    "wof:placetype":"venue"
},
  "geometry": {"coordinates":[149.09172100000001,-21.047588],"type":"Point"}
}