{
  "type": "Feature",
  "properties": {
    "addr:full":"36 Wilderness Drv Mandurah WA 6210",
    "addr:housenumber":"36",
    "addr:postcode":"6210",
    "addr:street":"Wilderness Drv",
    "iso:country":"AU",
    "sg:address":"36 Wilderness Drv",
    "sg:city":"Mandurah",
    "sg:classifiers":[
        {
            "category":"Professional",
            "subcategory":"Engineering",
            "type":"Services"
        }
    ],
    "sg:phone":"+61 8 9582 3409",
    "sg:postcode":"6210",
    "sg:province":"WA",
    "sg:tags":[
        "engineer",
        "mechanical"
    ],
    "wof:name":"Evans J H & L R Mechanical Services",
    "wof:placetype":"venue"
},
  "geometry": {"coordinates":[115.639877,-32.640038],"type":"Point"}
}