{
  "type": "Feature",
  "properties": {
    "iso:country":"AU",
    "sg:address":"94 Young St",
    "sg:city":"Frankston",
    "sg:classifiers":[
        {
            "category":"Personal",
            "subcategory":"Massage",
            "type":"Services"
        }
    ],
    "sg:phone":"+61 3 9781 4258",
    "sg:postcode":"3199",
    "sg:province":"VIC",
    "sg:tags":[
        "therapy"
    ],
    "wof:name":"Young Street Therapeutic Clinic",
    "wof:placetype":"venue"
},
  "geometry": {"coordinates":[145.12495422399999,-38.1441230774],"type":"Point"}
}