{
  "type": "Feature",
  "properties": {
    "addr:full":"Lot 1, Mt Buller Rd Mansfield VIC 3722",
    "addr:postcode":"3722",
    "addr:street":"Mt Buller Rd",
    "iso:country":"AU",
    "sg:address":"Lot 1, Mt Buller Rd",
    "sg:city":"Mansfield",
    "sg:classifiers":[
        {
            "category":"Sports & Exercise",
            "subcategory":"Ski Slope",
            "type":"Entertainment"
        }
    ],
    "sg:phone":"+61 3 5775 2380",
    "sg:postcode":"3722",
    "sg:province":"VIC",
    "sg:tags":[
        "equipment",
        "hire",
        "retail",
        "snow"
    ],
    "wof:name":"Mansfield Snow Ski Hire & Sales",
    "wof:placetype":"venue"
},
  "geometry": {"coordinates":[146.14176940900001,-37.0649528503],"type":"Point"}
}