{
  "type": "Feature",
  "properties": {
    "addr:full":"2/ 121 Anzac Ave Engadine NSW 2233",
    "addr:housenumber":"/ 121",
    "addr:postcode":"2233",
    "addr:street":"Anzac Ave",
    "iso:country":"AU",
    "sg:address":"2/ 121 Anzac Ave",
    "sg:city":"Engadine",
    "sg:classifiers":[
        {
            "category":"Building & Trades",
            "subcategory":"Plumbing",
            "type":"Services"
        }
    ],
    "sg:phone":"+61 2 9520 1122",
    "sg:postcode":"2233",
    "sg:province":"NSW",
    "sg:tags":[
        "plumber",
        "gasfitters"
    ],
    "wof:name":"FRONTROW PLUMBING Pty Ltd",
    "wof:placetype":"venue"
},
  "geometry": {"coordinates":[151.00422668499999,-34.0589790344],"type":"Point"}
}