{
  "type": "Feature",
  "properties": {
    "iso:country":"AU",
    "sg:address":"102 Churchill St",
    "sg:city":"Childers",
    "sg:classifiers":[
        {
            "category":"Fast Food",
            "type":"Food & Drink"
        }
    ],
    "sg:phone":"+61 7 4126 1871",
    "sg:postcode":"4660",
    "sg:province":"QLD",
    "sg:tags":[
        "away",
        "take"
    ],
    "wof:name":"Tropicana Cafe & Takeaway",
    "wof:placetype":"venue"
},
  "geometry": {"coordinates":[152.27777099599999,-25.2366027832],"type":"Point"}
}