{
  "type": "Feature",
  "properties": {
    "addr:full":"Cnr Alderley & Ramsay Sts Toowoomba QLD 4350",
    "addr:postcode":"4350",
    "addr:street":"Cnr Alderley & Ramsay Sts",
    "iso:country":"AU",
    "sg:address":"Cnr Alderley & Ramsay Sts",
    "sg:city":"Toowoomba",
    "sg:classifiers":[
        {
            "category":"Retail",
            "subcategory":"Veterinary Services",
            "type":"Services"
        }
    ],
    "sg:phone":"+61 7 4636 2233",
    "sg:postcode":"4350",
    "sg:province":"QLD",
    "sg:tags":[
        "surgeon"
    ],
    "wof:name":"Harboe Julieanne",
    "wof:placetype":"venue"
},
  "geometry": {"coordinates":[151.91340600000001,-27.579803],"type":"Point"}
}