{
  "type": "Feature",
  "properties": {
    "addr:full":"Shop 10a Unistyle Centre, 7172 Bruce Hwy Forest Glen QLD 4556",
    "addr:housenumber":"10a;7172",
    "addr:postcode":"4556",
    "addr:street":"Unistyle Centre;Bruce Hwy",
    "iso:country":"AU",
    "sg:address":"Shop 10a Unistyle Centre, 7172 Bruce Hwy",
    "sg:city":"Forest Glen",
    "sg:classifiers":[
        {
            "category":"Building & Trades",
            "subcategory":"Construction",
            "type":"Services"
        }
    ],
    "sg:phone":"+61 7 5445 6775",
    "sg:postcode":"4556",
    "sg:province":"QLD",
    "sg:tags":[
        "earth",
        "excavating",
        "moving",
        "contractor"
    ],
    "wof:name":"A & K Sebire Earthmoving",
    "wof:placetype":"venue"
},
  "geometry": {"coordinates":[153.00422668499999,-26.6856441498],"type":"Point"}
}