{
  "type": "Feature",
  "properties": {
    "addr:full":"Suite 8 36 Wingecarribee St Bowral NSW 2576",
    "addr:housenumber":"36",
    "addr:postcode":"2576",
    "addr:street":"Wingecarribee St",
    "iso:country":"AU",
    "sg:address":"Suite 8 36 Wingecarribee St",
    "sg:city":"Bowral",
    "sg:classifiers":[
        {
            "category":"Education",
            "subcategory":"Special Training",
            "type":"Public Place"
        }
    ],
    "sg:phone":"+61 2 4862 1020",
    "sg:postcode":"2576",
    "sg:province":"NSW",
    "sg:tags":[
        "tuition-educational"
    ],
    "wof:name":"Kip McGrath Education Centres",
    "wof:placetype":"venue"
},
  "geometry": {"coordinates":[150.41891479500001,-34.4787864685],"type":"Point"}
}