{
  "type": "Feature",
  "properties": {
    "iso:country":"AU",
    "sg:address":"1 Wyndham St",
    "sg:city":"Alexandria",
    "sg:classifiers":[
        {
            "category":"Restaurant",
            "type":"Food & Drink"
        }
    ],
    "sg:phone":"+61 2 9699 9997",
    "sg:postcode":"2015",
    "sg:province":"NSW",
    "wof:name":"Boundary Hotel",
    "wof:placetype":"venue"
},
  "geometry": {"coordinates":[151.19807434099999,-33.8950958252],"type":"Point"}
}