{
  "type": "Feature",
  "properties": {
    "addr:full":"U 17/ 1 Commercial Rd Highett VIC 3190",
    "addr:housenumber":"17 / 1",
    "addr:postcode":"3190",
    "addr:street":"Commercial Rd",
    "iso:country":"AU",
    "sg:address":"U 17/ 1 Commercial Rd",
    "sg:city":"Highett",
    "sg:classifiers":[
        {
            "category":"Wholesale",
            "subcategory":"Medical Equipment & Supplies",
            "type":"Manufacturing & Wholesale Goods"
        }
    ],
    "sg:phone":"+61 3 9893 4277",
    "sg:postcode":"3190",
    "sg:province":"VIC",
    "sg:tags":[
        "dental"
    ],
    "wof:name":"Honour International Trading",
    "wof:placetype":"venue"
},
  "geometry": {"coordinates":[145.055908203,-37.9485702515],"type":"Point"}
}