{
  "type": "Feature",
  "properties": {
    "iso:country":"AU",
    "sg:address":"33b Hastings St",
    "sg:city":"Glenelg",
    "sg:classifiers":[
        {
            "category":"Building & Trades",
            "subcategory":"Equipment Rental",
            "type":"Services"
        }
    ],
    "sg:phone":"+61 8 8294 7936",
    "sg:postcode":"5045",
    "sg:province":"SA",
    "sg:tags":[
        "party",
        "hire"
    ],
    "wof:name":"Carousel Play Equipment Hire Pty Ltd",
    "wof:placetype":"venue"
},
  "geometry": {"coordinates":[138.517014,-34.98867],"type":"Point"}
}