{
  "type": "Feature",
  "properties": {
    "addr:full":"24 Knightsbridge Ave Glenwood NSW 2768",
    "addr:housenumber":"24",
    "addr:postcode":"2768",
    "addr:street":"Knightsbridge Ave",
    "iso:country":"AU",
    "sg:address":"24 Knightsbridge Ave",
    "sg:city":"Glenwood",
    "sg:classifiers":[
        {
            "category":"Professional",
            "subcategory":"Business Services",
            "type":"Services"
        }
    ],
    "sg:phone":"+61 416 257 564",
    "sg:postcode":"2768",
    "sg:province":"NSW",
    "sg:tags":[
        "drafting"
    ],
    "wof:name":"A1 Drafting",
    "wof:placetype":"venue"
},
  "geometry": {"coordinates":[150.93594400000001,-33.742741],"type":"Point"}
}