{
  "type": "Feature",
  "properties": {
    "addr:full":"200 Main St Kangaroo Point QLD 4169",
    "addr:housenumber":"200",
    "addr:postcode":"4169",
    "addr:street":"Main St",
    "iso:country":"AU",
    "sg:address":"200 Main St",
    "sg:city":"Kangaroo Point",
    "sg:classifiers":[
        {
            "category":"Restaurant",
            "type":"Food & Drink"
        }
    ],
    "sg:phone":"+61 7 3391 2266",
    "sg:postcode":"4169",
    "sg:province":"QLD",
    "wof:name":"Deery's Restaurant",
    "wof:placetype":"venue"
},
  "geometry": {"coordinates":[153.035552978,-27.4689712524],"type":"Point"}
}