{
  "type": "Feature",
  "properties": {
    "addr:full":"33 Dickenson Drv Mt Martha VIC 3934",
    "addr:housenumber":"33",
    "addr:postcode":"3934",
    "addr:street":"Dickenson Drv Mt Martha",
    "iso:country":"AU",
    "sg:address":"33 Dickenson Drv",
    "sg:city":"Mt Martha",
    "sg:classifiers":[
        {
            "category":"Building & Trades",
            "subcategory":"Plumbing",
            "type":"Services"
        }
    ],
    "sg:phone":"+61 402 439 186",
    "sg:postcode":"3934",
    "sg:province":"VIC",
    "sg:tags":[
        "plumber",
        "gasfitters"
    ],
    "wof:name":"Clover Gary",
    "wof:placetype":"venue"
},
  "geometry": {"coordinates":[145.01324462900001,-38.2805366516],"type":"Point"}
}