{
  "type": "Feature",
  "properties": {
    "addr:full":"55 Orrong Rd Elsternwick VIC 3185",
    "addr:housenumber":"55",
    "addr:postcode":"3185",
    "addr:street":"Orrong Rd",
    "iso:country":"AU",
    "sg:address":"55 Orrong Rd",
    "sg:city":"Elsternwick",
    "sg:classifiers":[
        {
            "category":"Social Services",
            "subcategory":"Child Care",
            "type":"Services"
        }
    ],
    "sg:phone":"+61 3 9528 1895",
    "sg:postcode":"3185",
    "sg:province":"VIC",
    "sg:tags":[
        "support",
        "health"
    ],
    "wof:name":"Maternal & Child Health Centres",
    "wof:placetype":"venue"
},
  "geometry": {"coordinates":[145.00579834000001,-37.8841896057],"type":"Point"}
}