{
  "type": "Feature",
  "properties": {
    "addr:full":"PO Box 363 Drysdale VIC 3222",
    "addr:postcode":"3222",
    "iso:country":"AU",
    "sg:address":"PO Box 363",
    "sg:city":"Drysdale",
    "sg:classifiers":[
        {
            "category":"Retail",
            "subcategory":"Veterinary Services",
            "type":"Services"
        }
    ],
    "sg:phone":"+61 419 345 919",
    "sg:postcode":"3222",
    "sg:province":"VIC",
    "sg:tags":[
        "surgeon"
    ],
    "wof:name":"Corver Robert Dr",
    "wof:placetype":"venue"
},
  "geometry": {"coordinates":[144.590103,-38.153461],"type":"Point"}
}