{
  "type": "Feature",
  "properties": {
    "addr:full":"U6/ 1a Moorefield Park Drv Wodonga VIC 3690",
    "addr:housenumber":"1a",
    "addr:postcode":"3690",
    "addr:street":"U6 /;Park Drv",
    "iso:country":"AU",
    "sg:address":"U6/ 1a Moorefield Park Drv",
    "sg:city":"Wodonga",
    "sg:classifiers":[
        {
            "category":"Real Estate",
            "subcategory":"Surveying",
            "type":"Services"
        }
    ],
    "sg:phone":"+61 2 6056 8551",
    "sg:postcode":"3690",
    "sg:province":"VIC",
    "sg:tags":[
        "building",
        "surveyor"
    ],
    "wof:name":"Border Certification Group",
    "wof:placetype":"venue"
},
  "geometry": {"coordinates":[146.8618927,-36.112487793],"type":"Point"}
}