{
  "type": "Feature",
  "properties": {
    "addr:full":"6th Floor 505 George St Sydney NSW 2000",
    "addr:housenumber":"505",
    "addr:postcode":"2000",
    "addr:street":"George St",
    "iso:country":"AU",
    "sg:address":"6th Floor 505 George St",
    "sg:city":"Sydney",
    "sg:classifiers":[
        {
            "category":"Cinema",
            "subcategory":"Movie Theater",
            "type":"Entertainment"
        }
    ],
    "sg:phone":"+61 2 9261 7777",
    "sg:postcode":"2000",
    "sg:province":"NSW",
    "wof:name":"Hoyts Corporation Pty Ltd",
    "wof:placetype":"venue"
},
  "geometry": {"coordinates":[151.20652770999999,-33.8750267029],"type":"Point"}
}