{
  "type": "Feature",
  "properties": {
    "iso:country":"AU",
    "sg:address":"25 Pelicam St",
    "sg:city":"Darlinghurst",
    "sg:classifiers":[
        {
            "category":"Shopping",
            "subcategory":"Jewelry",
            "type":"Retail Goods"
        }
    ],
    "sg:phone":"+61 2 9283 3751",
    "sg:postcode":"2010",
    "sg:province":"NSW",
    "sg:tags":[
        "jeweller"
    ],
    "wof:name":"Grimes Charles Pty Ltd",
    "wof:placetype":"venue"
},
  "geometry": {"coordinates":[151.21299743599999,-33.8787460327],"type":"Point"}
}