{
  "type": "Feature",
  "properties": {
    "addr:full":"9 Verdun Rd Murray Bridge SA 5253",
    "addr:housenumber":"9",
    "addr:postcode":"5253",
    "addr:street":"Verdun Rd",
    "iso:country":"AU",
    "sg:address":"9 Verdun Rd",
    "sg:city":"Murray Bridge",
    "sg:classifiers":[
        {
            "category":"Health Services",
            "subcategory":"Health Practitioner",
            "type":"Services"
        }
    ],
    "sg:phone":"+61 8 8532 5925",
    "sg:postcode":"5253",
    "sg:province":"SA",
    "sg:tags":[
        "physiotherapist"
    ],
    "wof:name":"Murray Bridge Physiotherapy Clinic",
    "wof:placetype":"venue"
},
  "geometry": {"coordinates":[139.27268981899999,-35.1229019165],"type":"Point"}
}