{
  "type": "Feature",
  "properties": {
    "addr:full":"144 Piper St Bathurst NSW 2795",
    "addr:housenumber":"144",
    "addr:postcode":"2795",
    "addr:street":"Piper St",
    "iso:country":"AU",
    "sg:address":"144 Piper St",
    "sg:city":"Bathurst",
    "sg:classifiers":[
        {
            "category":"Cinema",
            "subcategory":"Movie Theater",
            "type":"Entertainment"
        }
    ],
    "sg:phone":"+61 2 6331 8000",
    "sg:postcode":"2795",
    "sg:province":"NSW",
    "wof:name":"Metro Cinemas",
    "wof:placetype":"venue"
},
  "geometry": {"coordinates":[149.57432556099999,-33.4199638367],"type":"Point"}
}