{
  "type": "Feature",
  "properties": {
    "iso:country":"AU",
    "sg:address":"Unit 1 27 Bishop St",
    "sg:city":"Woolner",
    "sg:classifiers":[
        {
            "category":"Banks & Credit Unions",
            "subcategory":"Financial Services",
            "type":"Services"
        }
    ],
    "sg:phone":"+61 8 8981 6733",
    "sg:postcode":"0820",
    "sg:province":"NT",
    "sg:tags":[
        "settlement",
        "nt",
        "agent",
        "wa"
    ],
    "wof:name":"Territory Conveyancing Services",
    "wof:placetype":"venue"
},
  "geometry": {"coordinates":[130.85354614299999,-12.4325037003],"type":"Point"}
}