{
  "type": "Feature",
  "properties": {
    "addr:full":"3249 Albany Hwy Armadale WA 6112",
    "addr:housenumber":"3249",
    "addr:postcode":"6112",
    "addr:street":"Albany Hwy",
    "iso:country":"AU",
    "sg:address":"3249 Albany Hwy",
    "sg:city":"Armadale",
    "sg:classifiers":[
        {
            "category":"Autos & Motor Vehicles",
            "subcategory":"Fuel & Gas Station",
            "type":"Retail Goods"
        }
    ],
    "sg:phone":"+61 8 9399 2204",
    "sg:postcode":"6112",
    "sg:province":"WA",
    "wof:name":"BP",
    "wof:placetype":"venue"
},
  "geometry": {"coordinates":[116.026161194,-32.1609306335],"type":"Point"}
}