{
  "type": "Feature",
  "properties": {
    "addr:full":"37 Gibson St Beaconsfield WA 6162",
    "addr:housenumber":"37",
    "addr:postcode":"6162",
    "addr:street":"Gibson St",
    "iso:country":"AU",
    "sg:address":"37 Gibson St",
    "sg:city":"Beaconsfield",
    "sg:classifiers":[
        {
            "category":"Organizations",
            "subcategory":"Professional Association",
            "type":"Services"
        }
    ],
    "sg:phone":"+61 8 9433 6408",
    "sg:postcode":"6162",
    "sg:province":"WA",
    "sg:tags":[
        "web",
        "internet"
    ],
    "wof:name":"A AARDVARK Web Services",
    "wof:placetype":"venue"
},
  "geometry": {"coordinates":[115.77516900000001,-32.066128],"type":"Point"}
}