{
  "type": "Feature",
  "properties": {
    "addr:full":"14 Ayrton St Dalby QLD 4405",
    "addr:housenumber":"14",
    "addr:postcode":"4405",
    "addr:street":"Ayrton St",
    "iso:country":"AU",
    "sg:address":"14 Ayrton St",
    "sg:city":"Dalby",
    "sg:classifiers":[
        {
            "category":"Utilities",
            "subcategory":"Electric",
            "type":"Services"
        }
    ],
    "sg:phone":"+61 7 4662 4390",
    "sg:postcode":"4405",
    "sg:province":"QLD",
    "sg:tags":[
        "electrical",
        "contractor"
    ],
    "wof:name":"Edgar W A & M R",
    "wof:placetype":"venue"
},
  "geometry": {"coordinates":[151.264602661,-27.1964416504],"type":"Point"}
}