{
  "type": "Feature",
  "properties": {
    "addr:full":"227 Waterworks Rd Ashgrove QLD 4060",
    "addr:housenumber":"227",
    "addr:postcode":"4060",
    "addr:street":"Waterworks Rd",
    "iso:country":"AU",
    "sg:address":"227 Waterworks Rd",
    "sg:city":"Ashgrove",
    "sg:classifiers":[
        {
            "category":"Fast Food",
            "type":"Food & Drink"
        }
    ],
    "sg:phone":"+61 7 3366 4442",
    "sg:postcode":"4060",
    "sg:province":"QLD",
    "sg:tags":[
        "away",
        "take"
    ],
    "wof:name":"Let's Eat At Ashgrove",
    "wof:placetype":"venue"
},
  "geometry": {"coordinates":[152.992675781,-27.4453735352],"type":"Point"}
}