{
  "type": "Feature",
  "properties": {
    "addr:full":"230 Malop St Geelong VIC 3220",
    "addr:housenumber":"230",
    "addr:postcode":"3220",
    "addr:street":"Malop St",
    "iso:country":"AU",
    "sg:address":"230 Malop St",
    "sg:city":"Geelong",
    "sg:classifiers":[
        {
            "category":"Government",
            "subcategory":"Post Office",
            "type":"Public Place"
        }
    ],
    "sg:phone":"+61 3 5221 7359",
    "sg:postcode":"3220",
    "sg:province":"VIC",
    "sg:tags":[
        "yoga"
    ],
    "wof:name":"Bayside Yoga",
    "wof:placetype":"venue"
},
  "geometry": {"coordinates":[144.36734000000001,-38.149174],"type":"Point"}
}