{
  "type": "Feature",
  "properties": {
    "addr:full":"55 Slip Rd Paynesville VIC 3880",
    "addr:housenumber":"55",
    "addr:postcode":"3880",
    "addr:street":"Slip Rd",
    "iso:country":"AU",
    "sg:address":"55 Slip Rd",
    "sg:city":"Paynesville",
    "sg:classifiers":[
        {
            "category":"Retail",
            "subcategory":"Auto Repair",
            "type":"Services"
        }
    ],
    "sg:phone":"+61 3 5156 6096",
    "sg:postcode":"3880",
    "sg:province":"VIC",
    "sg:tags":[
        "beater",
        "painter",
        "panel"
    ],
    "wof:name":"Paynesville Smash Repairs",
    "wof:placetype":"venue"
},
  "geometry": {"coordinates":[147.72816467300001,-37.9130516052],"type":"Point"}
}