{
  "type": "Feature",
  "properties": {
    "addr:full":"PO Box 1383 Berrimah NT 0828",
    "addr:postcode":"nt 0828",
    "iso:country":"AU",
    "sg:address":"PO Box 1383",
    "sg:city":"Berrimah",
    "sg:classifiers":[
        {
            "category":"Building & Trades",
            "subcategory":"Construction",
            "type":"Services"
        }
    ],
    "sg:phone":"+61 8 8947 4515",
    "sg:postcode":"0828",
    "sg:province":"NT",
    "sg:tags":[
        "contractor"
    ],
    "wof:name":"Horder Constructions",
    "wof:placetype":"venue"
},
  "geometry": {"coordinates":[130.92344665499999,-12.4338197708],"type":"Point"}
}