{
  "type": "Feature",
  "properties": {
    "addr:full":"69 Rule St North Fremantle WA 6159",
    "addr:housenumber":"69",
    "addr:postcode":"6159",
    "addr:street":"Rule St",
    "iso:country":"AU",
    "sg:address":"69 Rule St",
    "sg:city":"North Fremantle",
    "sg:classifiers":[
        {
            "category":"Farming",
            "subcategory":"Vineyard",
            "type":"Manufacturing & Wholesale Goods"
        }
    ],
    "sg:phone":"+61 8 9321 5355",
    "sg:postcode":"6159",
    "sg:province":"WA",
    "sg:tags":[
        "winery"
    ],
    "wof:name":"Higher Plane Wines",
    "wof:placetype":"venue"
},
  "geometry": {"coordinates":[115.75505800000001,-32.027786],"type":"Point"}
}