{
  "type": "Feature",
  "properties": {
    "addr:full":"35 Birdwood Ave Stanhope VIC 3623",
    "addr:housenumber":"35",
    "addr:postcode":"3623",
    "addr:street":"Birdwood Ave",
    "iso:country":"AU",
    "sg:address":"35 Birdwood Ave",
    "sg:city":"Stanhope",
    "sg:classifiers":[
        {
            "category":"Social Services",
            "subcategory":"Child Care",
            "type":"Services"
        }
    ],
    "sg:phone":"+61 3 5857 2400",
    "sg:postcode":"3623",
    "sg:province":"VIC",
    "sg:tags":[
        "support",
        "health"
    ],
    "wof:name":"Maternal & Child Health Centres",
    "wof:placetype":"venue"
},
  "geometry": {"coordinates":[144.984664917,-36.4460334778],"type":"Point"}
}