{
  "type": "Feature",
  "properties": {
    "addr:full":"Level 5, Bourke Place, 600 Bourke St Melbourne VIC 3000",
    "addr:housenumber":"600",
    "addr:postcode":"3000",
    "addr:street":"Bourke;Bourke St",
    "iso:country":"AU",
    "sg:address":"Level 5, Bourke Place, 600 Bourke St",
    "sg:city":"Melbourne",
    "sg:classifiers":[
        {
            "category":"Banks & Credit Unions",
            "subcategory":"Bank",
            "type":"Services"
        }
    ],
    "sg:phone":"+61 3 9641 2777",
    "sg:postcode":"3000",
    "sg:province":"VIC",
    "wof:name":"Bankwest Corporate Office",
    "wof:placetype":"venue"
},
  "geometry": {"coordinates":[144.956497192,-37.8160324097],"type":"Point"}
}