{
  "type": "Feature",
  "properties": {
    "addr:full":"40 Chasely St Auchenflower QLD 4066",
    "addr:housenumber":"40",
    "addr:postcode":"4066",
    "addr:street":"Chasely St",
    "iso:country":"AU",
    "sg:address":"40 Chasely St",
    "sg:city":"Auchenflower",
    "sg:classifiers":[
        {
            "category":"Health Services",
            "subcategory":"Doctor",
            "type":"Services"
        }
    ],
    "sg:phone":"+61 7 3844 0201",
    "sg:postcode":"4066",
    "sg:province":"QLD",
    "sg:tags":[
        "medical",
        "practitioner"
    ],
    "wof:name":"Steadman Peter",
    "wof:placetype":"venue"
},
  "geometry": {"coordinates":[152.997955322,-27.4771118164],"type":"Point"}
}