{
  "type": "Feature",
  "properties": {
    "addr:full":"268 Turton Rd New Lambton NSW 2305",
    "addr:housenumber":"268",
    "addr:postcode":"2305",
    "addr:street":"Turton Rd",
    "iso:country":"AU",
    "sg:address":"268 Turton Rd",
    "sg:city":"New Lambton",
    "sg:classifiers":[
        {
            "category":"Personal",
            "subcategory":"Beauty Salon",
            "type":"Services"
        }
    ],
    "sg:phone":"+61 1800 424 756",
    "sg:postcode":"2305",
    "sg:province":"NSW",
    "sg:tags":[
        "hair",
        "treatment",
        "replacement"
    ],
    "wof:name":"New Generation Hair Laser Clinics",
    "wof:placetype":"venue"
},
  "geometry": {"coordinates":[151.72554,-32.916138],"type":"Point"}
}