{
  "type": "Feature",
  "properties": {
    "addr:full":"PO Box 341 Ashmore City QLD 4214",
    "addr:postcode":"4214",
    "iso:country":"AU",
    "sg:address":"PO Box 341",
    "sg:city":"Ashmore City",
    "sg:classifiers":[
        {
            "category":"Manufacturing",
            "subcategory":"Rubber & Plastics",
            "type":"Manufacturing & Wholesale Goods"
        }
    ],
    "sg:phone":"+61 7 3801 4044",
    "sg:postcode":"4214",
    "sg:province":"QLD",
    "sg:tags":[
        "wholesaler",
        "product",
        "mfrs"
    ],
    "wof:name":"Molectra Australia Pty Ltd",
    "wof:placetype":"venue"
},
  "geometry": {"coordinates":[153.38270568900001,-27.9863395691],"type":"Point"}
}