{
  "type": "Feature",
  "properties": {
    "iso:country":"AU",
    "sg:address":"Fact 4/ 4 Bedford St",
    "sg:city":"Collingwood",
    "sg:classifiers":[
        {
            "category":"Retail",
            "subcategory":"Storage",
            "type":"Services"
        }
    ],
    "sg:phone":"+61 3 9486 9947",
    "sg:postcode":"3066",
    "sg:province":"VIC",
    "sg:tags":[
        "shelving",
        "system"
    ],
    "wof:name":"Safe Station Locker Solutions",
    "wof:placetype":"venue"
},
  "geometry": {"coordinates":[144.98515319800001,-37.7994003296],"type":"Point"}
}