{
  "type": "Feature",
  "properties": {
    "addr:full":"6 Palermo St South Yarra VIC 3141",
    "addr:housenumber":"6",
    "addr:postcode":"3141",
    "addr:street":"Palermo St",
    "iso:country":"AU",
    "sg:address":"6 Palermo St",
    "sg:city":"South Yarra",
    "sg:classifiers":[
        {
            "category":"Arts & Performance",
            "subcategory":"Music",
            "type":"Entertainment"
        }
    ],
    "sg:phone":"+61 3 9826 6605",
    "sg:postcode":"3141",
    "sg:province":"VIC",
    "sg:tags":[
        "mobile",
        "jockey",
        "disc"
    ],
    "wof:name":"Robert Huggins & Team",
    "wof:placetype":"venue"
},
  "geometry": {"coordinates":[144.99615478499999,-37.8418693542],"type":"Point"}
}