{
  "type": "Feature",
  "properties": {
    "addr:full":"500 Warwick Rd Yamanto QLD 4305",
    "addr:housenumber":"500",
    "addr:postcode":"4305",
    "addr:street":"Warwick Rd",
    "iso:country":"AU",
    "sg:address":"500 Warwick Rd",
    "sg:city":"Yamanto",
    "sg:classifiers":[
        {
            "category":"Communications",
            "subcategory":"Film & Video Production",
            "type":"Services"
        }
    ],
    "sg:phone":"+61 7 3288 6177",
    "sg:postcode":"4305",
    "sg:province":"QLD",
    "sg:tags":[
        "dvd",
        "library"
    ],
    "wof:name":"Network Video Yamanto",
    "wof:placetype":"venue"
},
  "geometry": {"coordinates":[152.74000549300001,-27.6602458954],"type":"Point"}
}