{
  "type": "Feature",
  "properties": {
    "addr:full":"3 O'Hara Crt Greenwood WA 6024",
    "addr:housenumber":"3",
    "addr:postcode":"6024",
    "addr:street":"O'Hara Crt",
    "iso:country":"AU",
    "sg:address":"3 O'Hara Crt",
    "sg:city":"Greenwood",
    "sg:classifiers":[
        {
            "category":"Utilities",
            "subcategory":"Electric",
            "type":"Services"
        }
    ],
    "sg:phone":"+61 8 9342 4436",
    "sg:postcode":"6024",
    "sg:province":"WA",
    "sg:tags":[
        "electrical",
        "contractor"
    ],
    "wof:name":"Cybertronics",
    "wof:placetype":"venue"
},
  "geometry": {"coordinates":[115.81990051299999,-31.8298530579],"type":"Point"}
}