{
  "type": "Feature",
  "properties": {
    "addr:full":"9 Pittwin Rd, North, Capalaba QLD 4157",
    "addr:housenumber":"9",
    "addr:postcode":"4157",
    "addr:street":"Pittwin Rd North",
    "iso:country":"AU",
    "sg:address":"9 Pittwin Rd, North,",
    "sg:city":"Capalaba",
    "sg:classifiers":[
        {
            "category":"Professional",
            "subcategory":"Accounting & Tax Preparation",
            "type":"Services"
        }
    ],
    "sg:phone":"+61 7 3245 4566",
    "sg:postcode":"4157",
    "sg:province":"QLD",
    "sg:tags":[
        "consultant",
        "taxation"
    ],
    "wof:name":"Evans Edwards & Associates",
    "wof:placetype":"venue"
},
  "geometry": {"coordinates":[153.18812560999999,-27.5231952667],"type":"Point"}
}