{
  "type": "Feature",
  "properties": {
    "addr:full":"6 Burns St North Fremantle WA 6159",
    "addr:housenumber":"6",
    "addr:postcode":"6159",
    "addr:street":"Burns St",
    "iso:country":"AU",
    "sg:address":"6 Burns St",
    "sg:city":"North Fremantle",
    "sg:classifiers":[
        {
            "category":"Professional",
            "subcategory":"Accounting & Tax Preparation",
            "type":"Services"
        }
    ],
    "sg:phone":"+61 8 9335 5805",
    "sg:postcode":"6159",
    "sg:province":"WA",
    "sg:tags":[
        "accountant",
        "auditor"
    ],
    "wof:name":"Ward Nick",
    "wof:placetype":"venue"
},
  "geometry": {"coordinates":[115.75380699999999,-32.035412],"type":"Point"}
}