{
  "type": "Feature",
  "properties": {
    "addr:full":"Shop 45 The Centre Forestville NSW 2087",
    "addr:housenumber":"shop 45",
    "addr:postcode":"2087",
    "addr:street":"The Centre",
    "iso:country":"AU",
    "sg:address":"Shop 45",
    "sg:city":"The Centre Forestville",
    "sg:classifiers":[
        {
            "category":"Fast Food",
            "type":"Food & Drink"
        }
    ],
    "sg:phone":"+61 2 9453 4880",
    "sg:postcode":"2087",
    "sg:province":"NSW",
    "sg:tags":[
        "away",
        "take"
    ],
    "wof:name":"Thai Garlic Restaurant",
    "wof:placetype":"venue"
},
  "geometry": {"coordinates":[151.21653747600001,-33.7616004944],"type":"Point"}
}