{
  "type": "Feature",
  "properties": {
    "addr:full":"7 Nerida Crt Keysborough VIC 3173",
    "addr:housenumber":"7",
    "addr:postcode":"3173",
    "addr:street":"Nerida Crt",
    "iso:country":"AU",
    "sg:address":"7 Nerida Crt",
    "sg:city":"Keysborough",
    "sg:classifiers":[
        {
            "category":"Building & Trades",
            "subcategory":"Construction",
            "type":"Services"
        }
    ],
    "sg:phone":"+61 3 9769 0828",
    "sg:postcode":"3173",
    "sg:province":"VIC",
    "sg:tags":[
        "industrial",
        "commercial",
        "air conditioning"
    ],
    "wof:name":"Mac Air",
    "wof:placetype":"venue"
},
  "geometry": {"coordinates":[145.17665100100001,-37.9886207581],"type":"Point"}
}