{
  "type": "Feature",
  "properties": {
    "iso:country":"AU",
    "sg:address":"Unit 3/ 16 Nevilles St",
    "sg:city":"Underwood",
    "sg:classifiers":[
        {
            "category":"Professional",
            "type":"Services"
        }
    ],
    "sg:phone":"+61 7 3290 4533",
    "sg:postcode":"4119",
    "sg:province":"QLD",
    "sg:tags":[
        "shop",
        "fitting"
    ],
    "wof:name":"Melco Shopfitters",
    "wof:placetype":"venue"
},
  "geometry": {"coordinates":[153.11273193400001,-27.6174106598],"type":"Point"}
}