{
  "type": "Feature",
  "properties": {
    "addr:full":"15/ 123 Muriel Ave Moorooka QLD 4105",
    "addr:housenumber":"15 / 123",
    "addr:postcode":"4105",
    "addr:street":"Muriel Ave",
    "iso:country":"AU",
    "sg:address":"15/ 123 Muriel Ave",
    "sg:city":"Moorooka",
    "sg:classifiers":[
        {
            "category":"Wholesale",
            "subcategory":"Drugs",
            "type":"Manufacturing & Wholesale Goods"
        }
    ],
    "sg:phone":"+61 7 3426 9777",
    "sg:postcode":"4105",
    "sg:province":"QLD",
    "sg:tags":[
        "wholesaler",
        "pharmaceutical",
        "product",
        "mfrs"
    ],
    "wof:name":"Pfizer Australia Pty Ltd",
    "wof:placetype":"venue"
},
  "geometry": {"coordinates":[153.014404297,-27.5407371521],"type":"Point"}
}