{
  "type": "Feature",
  "properties": {
    "iso:country":"AU",
    "sg:address":"36 Claredale Rd",
    "sg:city":"Dandenong",
    "sg:classifiers":[
        {
            "category":"Shopping",
            "subcategory":"Crafts & Fabrics",
            "type":"Retail Goods"
        }
    ],
    "sg:phone":"+61 3 9794 0425",
    "sg:postcode":"3175",
    "sg:province":"VIC",
    "sg:tags":[
        "upholstering",
        "supply"
    ],
    "wof:name":"Eliza Furniture & Upholstery Pty Ltd",
    "wof:placetype":"venue"
},
  "geometry": {"coordinates":[145.22779846200001,-37.997428894],"type":"Point"}
}