{
  "type": "Feature",
  "properties": {
    "addr:full":"90 Daffodil Rd Boronia VIC 3155",
    "addr:housenumber":"90",
    "addr:postcode":"3155",
    "addr:street":"Daffodil Rd",
    "iso:country":"AU",
    "sg:address":"90 Daffodil Rd",
    "sg:city":"Boronia",
    "sg:classifiers":[
        {
            "category":"Structure",
            "subcategory":"Office Building",
            "type":"Public Place"
        }
    ],
    "sg:phone":"+61 3 9762 2758",
    "sg:postcode":"3155",
    "sg:province":"VIC",
    "sg:tags":[
        "slater",
        "tiler",
        "roof"
    ],
    "wof:name":"Source Tiling",
    "wof:placetype":"venue"
},
  "geometry": {"coordinates":[145.297164917,-37.8656272888],"type":"Point"}
}