{
  "type": "Feature",
  "properties": {
    "addr:full":"51 Raglan St Daylesford VIC 3460",
    "addr:housenumber":"51",
    "addr:postcode":"3460",
    "addr:street":"Raglan St",
    "iso:country":"AU",
    "sg:address":"51 Raglan St",
    "sg:city":"Daylesford",
    "sg:classifiers":[
        {
            "category":"Health Services",
            "subcategory":"Doctor",
            "type":"Services"
        }
    ],
    "sg:phone":"+61 3 5348 2281",
    "sg:postcode":"3460",
    "sg:province":"VIC",
    "sg:tags":[
        "medical",
        "practitioner"
    ],
    "wof:name":"Malcher G",
    "wof:placetype":"venue"
},
  "geometry": {"coordinates":[144.14752197300001,-37.3401184082],"type":"Point"}
}