{
  "type": "Feature",
  "properties": {
    "addr:full":"66 Fallon St Albury NSW 2640",
    "addr:housenumber":"66",
    "addr:postcode":"2640",
    "addr:street":"Fallon St",
    "iso:country":"AU",
    "sg:address":"66 Fallon St",
    "sg:city":"Albury",
    "sg:classifiers":[
        {
            "category":"Retail",
            "subcategory":"Auto Rental",
            "type":"Services"
        }
    ],
    "sg:phone":"+61 2 6024 1877",
    "sg:postcode":"2640",
    "sg:province":"NSW",
    "sg:tags":[
        "car",
        "hire",
        "minibus"
    ],
    "wof:name":"Mylon Travel Pty Ltd.",
    "wof:placetype":"venue"
},
  "geometry": {"coordinates":[146.928131103,-36.0623512268],"type":"Point"}
}