{
  "type": "Feature",
  "properties": {
    "addr:full":"110 Targo St Bundaberg QLD 4670",
    "addr:housenumber":"110",
    "addr:postcode":"4670",
    "addr:street":"Targo St",
    "iso:country":"AU",
    "sg:address":"110 Targo St",
    "sg:city":"Bundaberg",
    "sg:classifiers":[
        {
            "category":"Professional",
            "subcategory":"Employment Agencies",
            "type":"Services"
        }
    ],
    "sg:phone":"+61 7 4153 5800",
    "sg:postcode":"4670",
    "sg:province":"QLD",
    "wof:name":"Steps Employment",
    "wof:placetype":"venue"
},
  "geometry": {"coordinates":[152.35458374000001,-24.875995636],"type":"Point"}
}