{
  "type": "Feature",
  "properties": {
    "iso:country":"AU",
    "sg:address":"Shop 10, 73 Droughty Point Rd",
    "sg:city":"Rokeby",
    "sg:classifiers":[
        {
            "category":"Home & Garden",
            "subcategory":"Building Materials",
            "type":"Retail Goods"
        }
    ],
    "sg:phone":"+61 3 6247 6199",
    "sg:postcode":"7019",
    "sg:province":"TAS",
    "sg:tags":[
        "merchant",
        "glass",
        "glazier"
    ],
    "wof:name":"Southern Glass",
    "wof:placetype":"venue"
},
  "geometry": {"coordinates":[147.440307617,-42.9047775269],"type":"Point"}
}