{
  "type": "Feature",
  "properties": {
    "addr:full":"Shop 34 Cherrybrook Shopping Village Shepherds Drv Cherrybrook NSW 2126",
    "addr:housenumber":"shop 34",
    "addr:postcode":"2126",
    "addr:street":"Shepherds Drv",
    "iso:country":"AU",
    "sg:address":"Shop 34 Cherrybrook Shopping Village Shepherds Drv",
    "sg:city":"Cherrybrook",
    "sg:classifiers":[
        {
            "category":"Health Services",
            "subcategory":"Optometrist",
            "type":"Services"
        }
    ],
    "sg:phone":"+61 2 9484 7415",
    "sg:postcode":"2126",
    "sg:province":"NSW",
    "wof:name":"Cherrybrook Optometrist",
    "wof:placetype":"venue"
},
  "geometry": {"coordinates":[151.04205322300001,-33.7216720581],"type":"Point"}
}