{
  "type": "Feature",
  "properties": {
    "addr:full":"192 Elizabeth St Coburg North VIC 3058",
    "addr:housenumber":"192",
    "addr:postcode":"3058",
    "addr:street":"Elizabeth St",
    "iso:country":"AU",
    "sg:address":"192 Elizabeth St",
    "sg:city":"Coburg North",
    "sg:classifiers":[
        {
            "category":"Food & Beverages",
            "subcategory":"Groceries & Convenience Stores",
            "type":"Retail Goods"
        }
    ],
    "sg:phone":"+61 3 9350 5949",
    "sg:postcode":"3058",
    "sg:province":"VIC",
    "wof:name":"Dass Milk Bar",
    "wof:placetype":"venue"
},
  "geometry": {"coordinates":[144.98495483400001,-37.724357605],"type":"Point"}
}