{
  "type": "Feature",
  "properties": {
    "addr:full":"42 Raymond St Blackburn North VIC 3130",
    "addr:housenumber":"42",
    "addr:postcode":"3130",
    "addr:street":"Raymond St",
    "iso:country":"AU",
    "sg:address":"42 Raymond St",
    "sg:city":"Blackburn North",
    "sg:classifiers":[
        {
            "category":"Shopping",
            "subcategory":"Gifts & Souvenirs",
            "type":"Retail Goods"
        }
    ],
    "sg:phone":"+61 3 9894 0626",
    "sg:postcode":"3130",
    "sg:province":"VIC",
    "sg:tags":[
        "shop",
        "supply"
    ],
    "wof:name":"Africa Xtreme Distributors",
    "wof:placetype":"venue"
},
  "geometry": {"coordinates":[145.15562439000001,-37.8051490784],"type":"Point"}
}