{
  "type": "Feature",
  "properties": {
    "iso:country":"AU",
    "sg:address":"104 Yanderra St",
    "sg:city":"Condell Park",
    "sg:classifiers":[
        {
            "category":"Building & Trades",
            "subcategory":"Cleaning & Sanitation",
            "type":"Services"
        }
    ],
    "sg:phone":"+61 410 451 229",
    "sg:postcode":"2200",
    "sg:province":"NSW",
    "sg:tags":[
        "cleaner",
        "repairer",
        "roof"
    ],
    "wof:name":"Sams Roof Plumbing",
    "wof:placetype":"venue"
},
  "geometry": {"coordinates":[151.004501,-33.927822],"type":"Point"}
}