{
  "type": "Feature",
  "properties": {
    "iso:country":"AU",
    "sg:address":"3 Norfolk St",
    "sg:city":"Fremantle",
    "sg:classifiers":[
        {
            "category":"Government",
            "subcategory":"Customs House",
            "type":"Public Place"
        }
    ],
    "sg:phone":"+61 8 9335 5877",
    "sg:postcode":"6160",
    "sg:province":"WA",
    "sg:tags":[
        "title",
        "management",
        "stratum"
    ],
    "sg:website":"http://www.jdstrata.com.au",
    "wof:name":"John Dethridge Strata Services",
    "wof:placetype":"venue"
},
  "geometry": {"coordinates":[115.74797100000001,-32.058041],"type":"Point"}
}