{
  "type": "Feature",
  "properties": {
    "addr:full":"183 Bridge St Port Melbourne VIC 3207",
    "addr:housenumber":"183",
    "addr:postcode":"3207",
    "addr:street":"Bridge St",
    "iso:country":"AU",
    "sg:address":"183 Bridge St",
    "sg:city":"Port Melbourne",
    "sg:classifiers":[
        {
            "category":"Health Services",
            "subcategory":"Doctor",
            "type":"Services"
        }
    ],
    "sg:phone":"+61 3 9646 3197",
    "sg:postcode":"3207",
    "sg:province":"VIC",
    "sg:tags":[
        "medical",
        "practitioner"
    ],
    "wof:name":"Goldberg Jack & Associates",
    "wof:placetype":"venue"
},
  "geometry": {"coordinates":[144.941833,-37.835838],"type":"Point"}
}