{
  "type": "Feature",
  "properties": {
    "addr:full":"67 Morpeth Rd East Maitland NSW 2323",
    "addr:housenumber":"67",
    "addr:postcode":"2323",
    "addr:street":"Morpeth Rd",
    "iso:country":"AU",
    "sg:address":"67 Morpeth Rd",
    "sg:city":"East Maitland",
    "sg:classifiers":[
        {
            "category":"Building & Trades",
            "subcategory":"Construction",
            "type":"Services"
        }
    ],
    "sg:phone":"+61 409 318 785",
    "sg:postcode":"2323",
    "sg:province":"NSW",
    "sg:tags":[
        "contractor"
    ],
    "wof:name":"Scott Thorley Building",
    "wof:placetype":"venue"
},
  "geometry": {"coordinates":[151.59518432600001,-32.7403144836],"type":"Point"}
}