{
  "type": "Feature",
  "properties": {
    "addr:full":"Shop 2, 683-703 Hay St Mall Perth WA 6000",
    "addr:housenumber":"shop 2",
    "addr:postcode":"683-703;6000",
    "addr:street":"Hay St Mall",
    "iso:country":"AU",
    "sg:address":"Shop 2, 683-703 Hay St Mall",
    "sg:city":"Perth",
    "sg:classifiers":[
        {
            "category":"Shopping",
            "subcategory":"Clothing, Apparel, & Fashions",
            "type":"Retail Goods"
        }
    ],
    "sg:phone":"+61 8 9481 1123",
    "sg:postcode":"6000",
    "sg:province":"WA",
    "sg:tags":[
        "menswear"
    ],
    "wof:name":"Man To Man Menswear",
    "wof:placetype":"venue"
},
  "geometry": {"coordinates":[115.855102539,-31.9530696869],"type":"Point"}
}