{
  "type": "Feature",
  "properties": {
    "iso:country":"AU",
    "sg:address":"135 Victoria Rd",
    "sg:city":"Marrickville",
    "sg:classifiers":[
        {
            "category":"Structure",
            "subcategory":"Office Building",
            "type":"Public Place"
        }
    ],
    "sg:phone":"+61 2 9564 6422",
    "sg:postcode":"2204",
    "sg:province":"NSW",
    "sg:tags":[
        "wholesaler",
        "tool",
        "mfrs",
        "power"
    ],
    "wof:name":"Feiner Industrial Equipment (Flex Aust) Pty Ltd",
    "wof:placetype":"venue"
},
  "geometry": {"coordinates":[151.164551,-33.906582],"type":"Point"}
}