{
  "type": "Feature",
  "properties": {
    "addr:full":"4 Nambour-Mapleton Rd Nambour QLD 4560",
    "addr:housenumber":"4",
    "addr:postcode":"4560",
    "addr:street":"Nambour-Mapleton Rd",
    "iso:country":"AU",
    "sg:address":"4 Nambour-Mapleton Rd",
    "sg:city":"Nambour",
    "sg:classifiers":[
        {
            "category":"Travel",
            "subcategory":"Hotels & Motels",
            "type":"Entertainment"
        }
    ],
    "sg:phone":"+61 7 5476 1888",
    "sg:postcode":"4560",
    "sg:province":"QLD",
    "wof:name":"Nambour Heights Motel",
    "wof:placetype":"venue"
},
  "geometry": {"coordinates":[152.95228576700001,-26.6207561493],"type":"Point"}
}