{
  "type": "Feature",
  "properties": {
    "iso:country":"AU",
    "sg:address":"2385 Frankston-Flinders Rd",
    "sg:city":"Bittern",
    "sg:classifiers":[
        {
            "category":"Restaurant",
            "type":"Food & Drink"
        }
    ],
    "sg:phone":"+61 3 5983 9506",
    "sg:postcode":"3918",
    "sg:province":"VIC",
    "wof:name":"Bittern Cottage Restaurant",
    "wof:placetype":"venue"
},
  "geometry": {"coordinates":[145.18002319300001,-38.3336677551],"type":"Point"}
}