{
  "type": "Feature",
  "properties": {
    "addr:full":"4 Junction Rd Blackburn North VIC 3130",
    "addr:housenumber":"4",
    "addr:postcode":"3130",
    "addr:street":"Junction Rd",
    "iso:country":"AU",
    "sg:address":"4 Junction Rd",
    "sg:city":"Blackburn North",
    "sg:classifiers":[
        {
            "category":"Professional",
            "subcategory":"Art Services",
            "type":"Services"
        }
    ],
    "sg:phone":"+61 438 769 877",
    "sg:postcode":"3130",
    "sg:province":"VIC",
    "sg:tags":[
        "graphic",
        "designer"
    ],
    "wof:name":"Richard Heath Design",
    "wof:placetype":"venue"
},
  "geometry": {"coordinates":[145.16000366200001,-37.8066558838],"type":"Point"}
}