{
  "type": "Feature",
  "properties": {
    "iso:country":"AU",
    "sg:address":"Studio - 1087 Victoria Rd",
    "sg:city":"West Ryde",
    "sg:classifiers":[
        {
            "category":"Education",
            "subcategory":"Dance Studio",
            "type":"Public Place"
        }
    ],
    "sg:phone":"+61 2 9804 8007",
    "sg:postcode":"2114",
    "sg:province":"NSW",
    "sg:tags":[
        "venue",
        "tuition"
    ],
    "wof:name":"Body Beat Dance Studio",
    "wof:placetype":"venue"
},
  "geometry": {"coordinates":[151.08433532699999,-33.8069610596],"type":"Point"}
}