{
  "type": "Feature",
  "properties": {
    "addr:full":"Shop Fck 1 Fountain Gate Shopp 352 Princes Hwy Narre Warren VIC 3805",
    "addr:housenumber":"1;352",
    "addr:postcode":"3805",
    "addr:street":"Fck;Fountain Gate Shopp;Princes Hwy",
    "iso:country":"AU",
    "sg:address":"Shop Fck 1 Fountain Gate Shopp 352 Princes Hwy",
    "sg:city":"Narre Warren",
    "sg:classifiers":[
        {
            "category":"Fast Food",
            "type":"Food & Drink"
        }
    ],
    "sg:phone":"+61 3 8790 5621",
    "sg:postcode":"3805",
    "sg:province":"VIC",
    "sg:tags":[
        "away",
        "take"
    ],
    "wof:name":"Jesters",
    "wof:placetype":"venue"
},
  "geometry": {"coordinates":[145.30552700000001,-38.0252],"type":"Point"}
}