{
  "type": "Feature",
  "properties": {
    "addr:full":"Shop 14, 185 - 211 Broadway Ultimo NSW 2007",
    "addr:housenumber":"shop 14;211",
    "addr:postcode":"185;2007",
    "addr:street":"Broadway",
    "iso:country":"AU",
    "sg:address":"Shop 14, 185 - 211",
    "sg:city":"Broadway Ultimo",
    "sg:classifiers":[
        {
            "category":"Health Services",
            "subcategory":"Doctor",
            "type":"Services"
        }
    ],
    "sg:phone":"+61 2 9212 2733",
    "sg:postcode":"2007",
    "sg:province":"NSW",
    "sg:tags":[
        "medical",
        "practitioner"
    ],
    "wof:name":"Broadway Medical Centre",
    "wof:placetype":"venue"
},
  "geometry": {"coordinates":[151.19526672399999,-33.8842582703],"type":"Point"}
}