{
  "type": "Feature",
  "properties": {
    "iso:country":"AU",
    "sg:address":"17 David Ave",
    "sg:city":"North Ryde",
    "sg:classifiers":[
        {
            "category":"Shopping",
            "subcategory":"Computers & Home Electronics",
            "type":"Retail Goods"
        }
    ],
    "sg:phone":"+61 2 9870 7777",
    "sg:postcode":"2113",
    "sg:province":"NSW",
    "sg:tags":[
        "small",
        "equipment",
        "business"
    ],
    "wof:name":"Coral Computers Pty Ltd",
    "wof:placetype":"venue"
},
  "geometry": {"coordinates":[151.119995117,-33.7866783142],"type":"Point"}
}