{
  "type": "Feature",
  "properties": {
    "iso:country":"AU",
    "sg:address":"1 Victoria Ave",
    "sg:city":"Albert Park",
    "sg:classifiers":[
        {
            "category":"Health Services",
            "subcategory":"Health Practitioner",
            "type":"Services"
        }
    ],
    "sg:phone":"+61 3 9690 7919",
    "sg:postcode":"3206",
    "sg:province":"VIC",
    "sg:tags":[
        "naturopath"
    ],
    "wof:name":"Veronika Blumenbach",
    "wof:placetype":"venue"
},
  "geometry": {"coordinates":[144.95343,-37.841717],"type":"Point"}
}