{
  "type": "Feature",
  "properties": {
    "iso:country":"AU",
    "sg:address":"PO Box 172",
    "sg:city":"Willaston",
    "sg:classifiers":[
        {
            "category":"Building & Trades",
            "subcategory":"Construction",
            "type":"Services"
        }
    ],
    "sg:phone":"+61 8 8522 6648",
    "sg:postcode":"5118",
    "sg:province":"SA",
    "sg:tags":[
        "earth",
        "excavating",
        "moving",
        "contractor"
    ],
    "wof:name":"Hilton-Nap Earthmovers",
    "wof:placetype":"venue"
},
  "geometry": {"coordinates":[138.73899800000001,-34.583759],"type":"Point"}
}