{
  "type": "Feature",
  "properties": {
    "addr:full":"d'Albora Marinas, The Spit Mosman NSW 2088",
    "addr:postcode":"2088",
    "addr:street":"The",
    "iso:country":"AU",
    "sg:address":"d'Albora Marinas, The Spit",
    "sg:city":"Mosman",
    "sg:classifiers":[
        {
            "category":"Autos & Motor Vehicles",
            "subcategory":"Boat Sales",
            "type":"Retail Goods"
        }
    ],
    "sg:phone":"+61 2 9960 4044",
    "sg:postcode":"2088",
    "sg:province":"NSW",
    "sg:tags":[
        "yacht"
    ],
    "wof:name":"Sports Marine (NSW)",
    "wof:placetype":"venue"
},
  "geometry": {"coordinates":[151.24887085,-33.8284492493],"type":"Point"}
}