{
  "type": "Feature",
  "properties": {
    "addr:full":"Level 20, Tower 2, 201 Sussex St Sydney NSW 2000",
    "addr:housenumber":"20;2 201",
    "addr:postcode":"2000",
    "addr:street":"Tower;Sussex St",
    "iso:country":"AU",
    "sg:address":"Level 20, Tower 2, 201 Sussex St",
    "sg:city":"Sydney",
    "sg:classifiers":[
        {
            "category":"Professional",
            "subcategory":"Computer Services",
            "type":"Services"
        }
    ],
    "sg:phone":"+61 2 9518 6066",
    "sg:postcode":"2000",
    "sg:province":"NSW",
    "sg:tags":[
        "package",
        "software"
    ],
    "wof:name":"Scalable Data Systems",
    "wof:placetype":"venue"
},
  "geometry": {"coordinates":[151.20382690400001,-33.8718338013],"type":"Point"}
}