{
  "type": "Feature",
  "properties": {
    "addr:full":"4 Snowdon St Geraldton WA 6530",
    "addr:housenumber":"4",
    "addr:postcode":"6530",
    "addr:street":"Snowdon St",
    "iso:country":"AU",
    "sg:address":"4 Snowdon St",
    "sg:city":"Geraldton",
    "sg:classifiers":[
        {
            "category":"Professional",
            "subcategory":"Detective & Security Services",
            "type":"Services"
        }
    ],
    "sg:phone":"+61 8 9964 1810",
    "sg:postcode":"6530",
    "sg:province":"WA",
    "sg:tags":[
        "consultant",
        "system"
    ],
    "wof:name":"Vidguard Security Systems",
    "wof:placetype":"venue"
},
  "geometry": {"coordinates":[114.613586426,-28.770488739],"type":"Point"}
}