{
  "type": "Feature",
  "properties": {
    "addr:full":"24 Dalley St Queenscliff NSW 2096",
    "addr:housenumber":"24",
    "addr:postcode":"2096",
    "addr:street":"Dalley St",
    "iso:country":"AU",
    "sg:address":"24 Dalley St",
    "sg:city":"Queenscliff",
    "sg:classifiers":[
        {
            "category":"Health Services",
            "subcategory":"Health Practitioner",
            "type":"Services"
        }
    ],
    "sg:phone":"+61 2 9949 1394",
    "sg:postcode":"2096",
    "sg:province":"NSW",
    "sg:tags":[
        "homoeopath"
    ],
    "wof:name":"Suzanne Lee",
    "wof:placetype":"venue"
},
  "geometry": {"coordinates":[151.28147888199999,-33.7814788818],"type":"Point"}
}