{
  "type": "Feature",
  "properties": {
    "iso:country":"AU",
    "sg:address":"Bruce Hwy",
    "sg:city":"Torbanlea",
    "sg:classifiers":[
        {
            "category":"Farming",
            "subcategory":"Nursery",
            "type":"Manufacturing & Wholesale Goods"
        }
    ],
    "sg:phone":"+61 7 4129 4147",
    "sg:postcode":"4662",
    "sg:province":"QLD",
    "wof:name":"Golden Grove Pty Ltd",
    "wof:placetype":"venue"
},
  "geometry": {"coordinates":[152.587768555,-25.3458461761],"type":"Point"}
}