{
  "type": "Feature",
  "properties": {
    "iso:country":"AU",
    "sg:address":"16 Brampton Ave",
    "sg:city":"Cranbrook",
    "sg:classifiers":[
        {
            "category":"Professional",
            "subcategory":"Accounting & Tax Preparation",
            "type":"Services"
        }
    ],
    "sg:phone":"+61 400 749 708",
    "sg:postcode":"4814",
    "sg:province":"QLD",
    "sg:tags":[
        "bookkeeping"
    ],
    "wof:name":"Aspect Management Pty Ltd",
    "wof:placetype":"venue"
},
  "geometry": {"coordinates":[146.758987,-19.295774],"type":"Point"}
}