{
  "type": "Feature",
  "properties": {
    "iso:country":"AU",
    "sg:address":"96 Neil St",
    "sg:city":"Toowoomba",
    "sg:classifiers":[
        {
            "category":"Health Services",
            "subcategory":"Dentist",
            "type":"Services"
        }
    ],
    "sg:phone":"+61 7 4632 3637",
    "sg:postcode":"4350",
    "sg:province":"QLD",
    "wof:name":"Cameron Tony Dr",
    "wof:placetype":"venue"
},
  "geometry": {"coordinates":[151.954514,-27.567986],"type":"Point"}
}