{
  "type": "Feature",
  "properties": {
    "iso:country":"AU",
    "sg:address":"424 Upper Roma St",
    "sg:city":"Brisbane",
    "sg:classifiers":[
        {
            "category":"Building & Trades",
            "subcategory":"Construction",
            "type":"Services"
        }
    ],
    "sg:phone":"+61 7 3839 0044",
    "sg:postcode":"4000",
    "sg:province":"QLD",
    "sg:tags":[
        "management"
    ],
    "wof:name":"Project Constructions Pty Ltd",
    "wof:placetype":"venue"
},
  "geometry": {"coordinates":[153.01205444300001,-27.4669075012],"type":"Point"}
}