{
  "type": "Feature",
  "properties": {
    "addr:full":"Griffith St Oak Flats NSW 2529",
    "addr:postcode":"2529",
    "addr:street":"Griffith St Oak Flats",
    "iso:country":"AU",
    "sg:address":"Griffith St",
    "sg:city":"Oak Flats",
    "sg:classifiers":[
        {
            "category":"Education",
            "subcategory":"School",
            "type":"Public Place"
        }
    ],
    "sg:phone":"+61 2 4256 1405",
    "sg:postcode":"2529",
    "sg:province":"NSW",
    "sg:tags":[
        "state",
        "-",
        "nsw"
    ],
    "wof:name":"Oak Flats Public School",
    "wof:placetype":"venue"
},
  "geometry": {"coordinates":[150.81936645499999,-34.5629119873],"type":"Point"}
}