{
  "type": "Feature",
  "properties": {
    "addr:full":"138 Balgownie Rd Balgownie NSW 2519",
    "addr:housenumber":"138",
    "addr:postcode":"2519",
    "addr:street":"Balgownie Rd",
    "iso:country":"AU",
    "sg:address":"138 Balgownie Rd",
    "sg:city":"Balgownie",
    "sg:classifiers":[
        {
            "category":"Food & Beverages",
            "subcategory":"Liquor & Beverages",
            "type":"Retail Goods"
        }
    ],
    "sg:phone":"+61 2 4284 2934",
    "sg:postcode":"2519",
    "sg:province":"NSW",
    "sg:tags":[
        "store"
    ],
    "wof:name":"Liquorland",
    "wof:placetype":"venue"
},
  "geometry": {"coordinates":[150.87837200000001,-34.388535],"type":"Point"}
}