{
  "type": "Feature",
  "properties": {
    "iso:country":"AU",
    "sg:address":"443 Horrie Miller Drv",
    "sg:city":"Perth Airport",
    "sg:classifiers":[
        {
            "category":"Home & Garden",
            "subcategory":"Hardware",
            "type":"Retail Goods"
        }
    ],
    "sg:phone":"+61 8 9475 8777",
    "sg:postcode":"6105",
    "sg:province":"WA",
    "sg:tags":[
        "generating",
        "set",
        "generator"
    ],
    "wof:name":"Cummins",
    "wof:placetype":"venue"
},
  "geometry": {"coordinates":[115.96811676,-31.9694309235],"type":"Point"}
}