{
  "type": "Feature",
  "properties": {
    "iso:country":"AU",
    "sg:address":"8 Donnelly St",
    "sg:city":"Toronto",
    "sg:classifiers":[
        {
            "category":"Retail",
            "subcategory":"Repair Shop",
            "type":"Services"
        }
    ],
    "sg:phone":"+61 2 4959 3518",
    "sg:postcode":"2283",
    "sg:province":"NSW",
    "sg:tags":[
        "machine",
        "sewing"
    ],
    "wof:name":"Toronto Sew Easy",
    "wof:placetype":"venue"
},
  "geometry": {"coordinates":[151.559692383,-33.0059890747],"type":"Point"}
}