{
  "type": "Feature",
  "properties": {
    "addr:full":"62 Coomera Gorge Drv Tamborine Mountain QLD 4272",
    "addr:housenumber":"62",
    "addr:postcode":"4272",
    "addr:street":"Coomera Gorge Drv",
    "iso:country":"AU",
    "sg:address":"62 Coomera Gorge Drv",
    "sg:city":"Tamborine Mountain",
    "sg:classifiers":[
        {
            "category":"Professional",
            "subcategory":"Art Services",
            "type":"Services"
        }
    ],
    "sg:phone":"+61 7 5545 1456",
    "sg:postcode":"4272",
    "sg:province":"QLD",
    "sg:tags":[
        "decorator",
        "painter"
    ],
    "wof:name":"Flandorfer K & C",
    "wof:placetype":"venue"
},
  "geometry": {"coordinates":[153.184616089,-27.9589214325],"type":"Point"}
}