{
  "type": "Feature",
  "properties": {
    "iso:country":"AU",
    "sg:address":"1 East St",
    "sg:city":"Loxton",
    "sg:classifiers":[
        {
            "category":"Autos & Motor Vehicles",
            "subcategory":"Automobile Sales",
            "type":"Retail Goods"
        }
    ],
    "sg:phone":"+61 8 8584 7262",
    "sg:postcode":"5333",
    "sg:province":"SA",
    "sg:tags":[
        "car",
        "new"
    ],
    "wof:name":"Riverland Kia",
    "wof:placetype":"venue"
},
  "geometry": {"coordinates":[140.57015991200001,-34.4521827698],"type":"Point"}
}