{
  "type": "Feature",
  "properties": {
    "addr:full":"PO Box 1503 Mt Barker SA 5251",
    "addr:postcode":"5251",
    "iso:country":"AU",
    "sg:address":"PO Box 1503",
    "sg:city":"Mt Barker",
    "sg:classifiers":[
        {
            "category":"Professional",
            "subcategory":"Management & Consulting",
            "type":"Services"
        }
    ],
    "sg:phone":"+61 8 8391 0291",
    "sg:postcode":"5251",
    "sg:province":"SA",
    "sg:tags":[
        "consultant",
        "educational"
    ],
    "wof:name":"Richter Ken & Associates",
    "wof:placetype":"venue"
},
  "geometry": {"coordinates":[138.85289001500001,-35.0617103577],"type":"Point"}
}