{
  "type": "Feature",
  "properties": {
    "iso:country":"AU",
    "sg:address":"56 William St",
    "sg:city":"Rockhampton",
    "sg:classifiers":[
        {
            "category":"Retail",
            "subcategory":"Funeral Services",
            "type":"Services"
        }
    ],
    "sg:phone":"+61 7 4938 1211",
    "sg:postcode":"4700",
    "sg:province":"QLD",
    "sg:tags":[
        "cremation"
    ],
    "wof:name":"Finlayson & McKenzie Funeral Directors",
    "wof:placetype":"venue"
},
  "geometry": {"coordinates":[150.50872802699999,-23.3835277557],"type":"Point"}
}