{
  "type": "Feature",
  "properties": {
    "iso:country":"AU",
    "sg:address":"At The Junctin Of Eltham,Yarra Glen & Glenview Rds",
    "sg:city":"Yarra Glen",
    "sg:classifiers":[
        {
            "category":"Retail",
            "subcategory":"Funeral Services",
            "type":"Services"
        }
    ],
    "sg:phone":"+61 3 9739 6244",
    "sg:postcode":"3775",
    "sg:province":"VIC",
    "sg:tags":[
        "cemetery"
    ],
    "wof:name":"Yarra Glen Cemetery",
    "wof:placetype":"venue"
},
  "geometry": {"coordinates":[145.365997,-37.646511],"type":"Point"}
}