{
  "type": "Feature",
  "properties": {
    "addr:full":"Level 9 66 Hunter St Sydney NSW 2000",
    "addr:housenumber":"66",
    "addr:postcode":"2000",
    "addr:street":"Hunter St",
    "iso:country":"AU",
    "sg:address":"Level 9 66 Hunter St",
    "sg:city":"Sydney",
    "sg:classifiers":[
        {
            "category":"Professional",
            "subcategory":"Detective & Security Services",
            "type":"Services"
        }
    ],
    "sg:phone":"+61 2 9211 5520",
    "sg:postcode":"2000",
    "sg:province":"NSW",
    "sg:tags":[
        "investigator"
    ],
    "wof:name":"Huxley Hill & Associates",
    "wof:placetype":"venue"
},
  "geometry": {"coordinates":[151.210281372,-33.8661270142],"type":"Point"}
}