{
  "type": "Feature",
  "properties": {
    "addr:full":"Cnr Grace & Atherton Sts Mt Isa QLD 4825",
    "addr:postcode":"4825",
    "addr:street":"Cnr;Sts Mt Isa",
    "iso:country":"AU",
    "sg:address":"Cnr Grace & Atherton Sts",
    "sg:city":"Mt Isa",
    "sg:classifiers":[
        {
            "category":"Building & Trades",
            "subcategory":"Construction",
            "type":"Services"
        }
    ],
    "sg:phone":"+61 7 4743 7444",
    "sg:postcode":"4825",
    "sg:province":"QLD",
    "sg:tags":[
        "industrial",
        "commercial",
        "air conditioning"
    ],
    "wof:name":"Schafer & Foord Plumbing Pty Ltd",
    "wof:placetype":"venue"
},
  "geometry": {"coordinates":[139.495834,-20.724945],"type":"Point"}
}