{
  "type": "Feature",
  "properties": {
    "addr:full":"486 South Rd Kurralta Park SA 5037",
    "addr:housenumber":"486",
    "addr:postcode":"5037",
    "addr:street":"South Rd",
    "iso:country":"AU",
    "sg:address":"486 South Rd",
    "sg:city":"Kurralta Park",
    "sg:classifiers":[
        {
            "category":"Shopping",
            "subcategory":"Computers & Home Electronics",
            "type":"Retail Goods"
        }
    ],
    "sg:phone":"+61 8 8375 9100",
    "sg:postcode":"5037",
    "sg:province":"SA",
    "sg:tags":[
        "hardware",
        "equipment"
    ],
    "wof:name":"Compucon Computers (SA) Pty Ltd",
    "wof:placetype":"venue"
},
  "geometry": {"coordinates":[138.571212769,-34.9467163086],"type":"Point"}
}