{
  "type": "Feature",
  "properties": {
    "iso:country":"AU",
    "sg:address":"Suite 2/ 95 Monash Ave",
    "sg:city":"Nedlands",
    "sg:classifiers":[
        {
            "category":"Health Services",
            "subcategory":"Doctor",
            "type":"Services"
        }
    ],
    "sg:phone":"+61 8 6389 0900",
    "sg:postcode":"6009",
    "sg:province":"WA",
    "sg:tags":[
        "medical",
        "practitioner"
    ],
    "wof:name":"Mccormick Clem Mr",
    "wof:placetype":"venue"
},
  "geometry": {"coordinates":[115.806313,-31.970354],"type":"Point"}
}