{
  "type": "Feature",
  "properties": {
    "addr:full":"PO Box 91 Ettalong Beach NSW 2257",
    "addr:postcode":"2257",
    "iso:country":"AU",
    "sg:address":"PO Box 91",
    "sg:city":"Ettalong Beach",
    "sg:classifiers":[
        {
            "category":"Professional",
            "subcategory":"Computer Services",
            "type":"Services"
        }
    ],
    "sg:phone":"+61 2 4342 4148",
    "sg:postcode":"2257",
    "sg:province":"NSW",
    "sg:tags":[
        "consultant",
        "system"
    ],
    "wof:name":"Jaycee Computer Services",
    "wof:placetype":"venue"
},
  "geometry": {"coordinates":[151.334274292,-33.5093383789],"type":"Point"}
}