{
  "type": "Feature",
  "properties": {
    "addr:full":"118 Queen St Woollahra NSW 2025",
    "addr:housenumber":"118",
    "addr:postcode":"2025",
    "addr:street":"Queen St",
    "iso:country":"AU",
    "sg:address":"118 Queen St",
    "sg:city":"Woollahra",
    "sg:classifiers":[
        {
            "category":"Shopping",
            "subcategory":"Clothing, Apparel, & Fashions",
            "type":"Retail Goods"
        }
    ],
    "sg:phone":"+61 2 9363 0654",
    "sg:postcode":"2025",
    "sg:province":"NSW",
    "sg:tags":[
        "lady",
        "wear"
    ],
    "wof:name":"Riada Fashion Boutique",
    "wof:placetype":"venue"
},
  "geometry": {"coordinates":[151.23727417000001,-33.8882713318],"type":"Point"}
}