{
  "type": "Feature",
  "properties": {
    "iso:country":"AU",
    "sg:address":"5 Colton St",
    "sg:city":"Highgate Hill",
    "sg:classifiers":[
        {
            "category":"Real Estate",
            "subcategory":"Real Estate Agent",
            "type":"Services"
        }
    ],
    "sg:phone":"+61 7 3844 3501",
    "sg:postcode":"4101",
    "sg:province":"QLD",
    "sg:tags":[
        "consultant",
        "heritage"
    ],
    "wof:name":"Marquis-Kyle Peter",
    "wof:placetype":"venue"
},
  "geometry": {"coordinates":[153.01402282699999,-27.4860458374],"type":"Point"}
}