{
  "type": "Feature",
  "properties": {
    "addr:full":"42 Shawlands Ave Blackburn South VIC 3130",
    "addr:housenumber":"42",
    "addr:postcode":"3130",
    "addr:street":"Shawlands Ave",
    "iso:country":"AU",
    "sg:address":"42 Shawlands Ave",
    "sg:city":"Blackburn South",
    "sg:classifiers":[
        {
            "category":"Building & Trades",
            "subcategory":"Landscaping Services",
            "type":"Services"
        }
    ],
    "sg:phone":"+61 3 9877 5267",
    "sg:postcode":"3130",
    "sg:province":"VIC",
    "sg:tags":[
        "designer",
        "landscape",
        "contractor"
    ],
    "wof:name":"Eastern Environmental Landscaping",
    "wof:placetype":"venue"
},
  "geometry": {"coordinates":[145.15040588400001,-37.8359947205],"type":"Point"}
}