{
  "type": "Feature",
  "properties": {
    "iso:country":"AU",
    "sg:address":"143 Duckworth St",
    "sg:city":"Garbutt",
    "sg:classifiers":[
        {
            "category":"Cafe",
            "type":"Food & Drink"
        }
    ],
    "sg:phone":"+61 7 4728 4029",
    "sg:postcode":"4814",
    "sg:province":"QLD",
    "wof:name":"The Coffee Domain",
    "wof:placetype":"venue"
},
  "geometry": {"coordinates":[146.75926200000001,-19.278578],"type":"Point"}
}