{
  "type": "Feature",
  "properties": {
    "addr:full":"Unite 1 5 Bessemer St Blacktown NSW 2148",
    "addr:housenumber":"1 5",
    "addr:postcode":"2148",
    "addr:street":"Unite;Bessemer St",
    "iso:country":"AU",
    "sg:address":"Unite 1 5 Bessemer St",
    "sg:city":"Blacktown",
    "sg:classifiers":[
        {
            "category":"Retail",
            "subcategory":"Auto Repair",
            "type":"Services"
        }
    ],
    "sg:phone":"+61 2 9622 4213",
    "sg:postcode":"2148",
    "sg:province":"NSW",
    "sg:tags":[
        "wheel",
        "balancing",
        "alignment"
    ],
    "wof:name":"Newton Automotives",
    "wof:placetype":"venue"
},
  "geometry": {"coordinates":[150.914825439,-33.7544326782],"type":"Point"}
}