{
  "type": "Feature",
  "properties": {
    "addr:full":"Saleyards Rd Deniliquin NSW 2710",
    "addr:postcode":"2710",
    "addr:street":"Saleyards Rd",
    "iso:country":"AU",
    "sg:address":"Saleyards Rd",
    "sg:city":"Deniliquin",
    "sg:classifiers":[
        {
            "category":"Organizations",
            "subcategory":"Community Association",
            "type":"Services"
        }
    ],
    "sg:phone":"+61 3 5881 3777",
    "sg:postcode":"2710",
    "sg:province":"NSW",
    "sg:tags":[
        "cheese",
        "product"
    ],
    "wof:name":"Dairy Farmers",
    "wof:placetype":"venue"
},
  "geometry": {"coordinates":[144.951446533,-35.5481796265],"type":"Point"}
}