{
  "type": "Feature",
  "properties": {
    "iso:country":"AU",
    "sg:address":"Cnr Wills & Watson Sts",
    "sg:city":"Charleville",
    "sg:classifiers":[
        {
            "category":"Education",
            "subcategory":"University",
            "type":"Public Place"
        }
    ],
    "sg:phone":"+61 7 4654 3010",
    "sg:postcode":"4470",
    "sg:province":"QLD",
    "sg:tags":[
        "educational",
        "organisation",
        "cultural"
    ],
    "wof:name":"Education Queensland Roma District Office",
    "wof:placetype":"venue"
},
  "geometry": {"coordinates":[146.24322509800001,-26.4055633545],"type":"Point"}
}