{
  "type": "Feature",
  "properties": {
    "addr:full":"8 Hovey Rd Yatala QLD 4207",
    "addr:housenumber":"8",
    "addr:postcode":"4207",
    "addr:street":"Hovey Rd",
    "iso:country":"AU",
    "sg:address":"8 Hovey Rd",
    "sg:city":"Yatala",
    "sg:classifiers":[
        {
            "category":"Wholesale",
            "subcategory":"Drugs",
            "type":"Manufacturing & Wholesale Goods"
        }
    ],
    "sg:phone":"+61 7 3382 6550",
    "sg:postcode":"4207",
    "sg:province":"QLD",
    "sg:tags":[
        "wholesaler",
        "pharmaceutical",
        "product",
        "mfrs"
    ],
    "wof:name":"Universal Manufacturing & Laboratories Pty Ltd",
    "wof:placetype":"venue"
},
  "geometry": {"coordinates":[153.22921752900001,-27.7401847839],"type":"Point"}
}