{
  "type": "Feature",
  "properties": {
    "addr:full":"PO Box 300 Goulburn NSW 2580",
    "addr:postcode":"2580",
    "iso:country":"AU",
    "sg:address":"PO Box 300",
    "sg:city":"Goulburn",
    "sg:classifiers":[
        {
            "category":"Professional",
            "subcategory":"Detective & Security Services",
            "type":"Services"
        }
    ],
    "sg:phone":"+61 2 4823 5002",
    "sg:postcode":"2580",
    "sg:province":"NSW",
    "sg:tags":[
        "consultant",
        "system"
    ],
    "wof:name":"Falkcom Pty Ltd",
    "wof:placetype":"venue"
},
  "geometry": {"coordinates":[149.716262817,-34.7571792603],"type":"Point"}
}