{
  "type": "Feature",
  "properties": {
    "addr:full":"35 Whiting St Artarmon NSW 2064",
    "addr:housenumber":"35",
    "addr:postcode":"2064",
    "addr:street":"Whiting St",
    "iso:country":"AU",
    "sg:address":"35 Whiting St",
    "sg:city":"Artarmon",
    "sg:classifiers":[
        {
            "category":"Retail",
            "subcategory":"Auto Repair",
            "type":"Services"
        }
    ],
    "sg:phone":"+61 2 9438 2244",
    "sg:postcode":"2064",
    "sg:province":"NSW",
    "sg:tags":[
        "repairer",
        "motor",
        "engineer"
    ],
    "wof:name":"Williams & Wood Auto Repairs Pty Ltd",
    "wof:placetype":"venue"
},
  "geometry": {"coordinates":[151.183319092,-33.8150215149],"type":"Point"}
}