{
  "type": "Feature",
  "properties": {
    "iso:country":"AU",
    "sg:address":"4 Facit Ave",
    "sg:city":"Newton",
    "sg:classifiers":[
        {
            "category":"Building & Trades",
            "subcategory":"Construction",
            "type":"Services"
        }
    ],
    "sg:phone":"+61 8 8337 0325",
    "sg:postcode":"5074",
    "sg:province":"SA",
    "sg:tags":[
        "plasterboard",
        "plasterer",
        "fixer"
    ],
    "wof:name":"Sebastiano R S",
    "wof:placetype":"venue"
},
  "geometry": {"coordinates":[138.68038940400001,-34.8855552673],"type":"Point"}
}