{
  "type": "Feature",
  "properties": {
    "iso:country":"AU",
    "sg:address":"34 Barndioota Rd",
    "sg:city":"Salisbury Plain",
    "sg:classifiers":[
        {
            "category":"Retail",
            "subcategory":"Storage",
            "type":"Services"
        }
    ],
    "sg:phone":"+61 8 8282 5956",
    "sg:postcode":"5109",
    "sg:province":"SA",
    "wof:name":"All Suburbs Self Storage",
    "wof:placetype":"venue"
},
  "geometry": {"coordinates":[138.663894653,-34.7656669617],"type":"Point"}
}