{
  "type": "Feature",
  "properties": {
    "addr:full":"19 Wighton St Margate QLD 4019",
    "addr:housenumber":"19",
    "addr:postcode":"4019",
    "addr:street":"Wighton St",
    "iso:country":"AU",
    "sg:address":"19 Wighton St",
    "sg:city":"Margate",
    "sg:classifiers":[
        {
            "category":"Health Services",
            "subcategory":"Doctor",
            "type":"Services"
        }
    ],
    "sg:phone":"+61 7 3283 4522",
    "sg:postcode":"4019",
    "sg:province":"QLD",
    "sg:tags":[
        "medical",
        "practitioner"
    ],
    "wof:name":"Aitken Malcolm",
    "wof:placetype":"venue"
},
  "geometry": {"coordinates":[153.10879516599999,-27.2432327271],"type":"Point"}
}