{
  "type": "Feature",
  "properties": {
    "addr:full":"9 Melaleuca St Yea VIC 3717",
    "addr:housenumber":"9",
    "addr:postcode":"3717",
    "addr:street":"Melaleuca St",
    "iso:country":"AU",
    "sg:address":"9 Melaleuca St",
    "sg:city":"Yea",
    "sg:classifiers":[
        {
            "category":"Retail",
            "subcategory":"Auto Repair",
            "type":"Services"
        }
    ],
    "sg:phone":"+61 3 5797 2411",
    "sg:postcode":"3717",
    "sg:province":"VIC",
    "sg:tags":[
        "bus",
        "truck"
    ],
    "wof:name":"G C Bedford Automotives",
    "wof:placetype":"venue"
},
  "geometry": {"coordinates":[145.41421508799999,-37.2166404724],"type":"Point"}
}