{
  "type": "Feature",
  "properties": {
    "iso:country":"AU",
    "sg:address":"2/ 92 McCarrs Creek Rd",
    "sg:city":"Church Point",
    "sg:classifiers":[
        {
            "category":"Utilities",
            "subcategory":"Electric",
            "type":"Services"
        }
    ],
    "sg:phone":"+61 2 9962 8397",
    "sg:postcode":"2105",
    "sg:province":"NSW",
    "sg:tags":[
        "electrical",
        "contractor"
    ],
    "wof:name":"Gold Service Electrical",
    "wof:placetype":"venue"
},
  "geometry": {"coordinates":[151.281357,-33.653187],"type":"Point"}
}