{
  "type": "Feature",
  "properties": {
    "iso:country":"AU",
    "sg:address":"6 Kelsey St",
    "sg:city":"Arncliffe",
    "sg:classifiers":[
        {
            "category":"Health Services",
            "subcategory":"Doctor",
            "type":"Services"
        }
    ],
    "sg:phone":"+61 2 9597 4593",
    "sg:postcode":"2205",
    "sg:province":"NSW",
    "sg:tags":[
        "medical",
        "practitioner"
    ],
    "wof:name":"Hourani M",
    "wof:placetype":"venue"
},
  "geometry": {"coordinates":[151.145477,-33.934666],"type":"Point"}
}