{
  "type": "Feature",
  "properties": {
    "iso:country":"AU",
    "sg:address":"1/ 42 Canterbury Rd",
    "sg:city":"Bankstown",
    "sg:classifiers":[
        {
            "category":"Autos & Motor Vehicles",
            "subcategory":"Auto Supplies",
            "type":"Retail Goods"
        }
    ],
    "sg:phone":"+61 2 9791 5556",
    "sg:postcode":"2200",
    "sg:province":"NSW",
    "sg:tags":[
        "accessory"
    ],
    "wof:name":"KSS Moto Cycle Services",
    "wof:placetype":"venue"
},
  "geometry": {"coordinates":[151.035416,-33.934711],"type":"Point"}
}