{
  "type": "Feature",
  "properties": {
    "iso:country":"AU",
    "sg:address":"44a Victoria St",
    "sg:city":"Kerang",
    "sg:classifiers":[
        {
            "category":"Personal",
            "subcategory":"Shoe Repair & Shine",
            "type":"Services"
        }
    ],
    "sg:phone":"+61 3 5452 1559",
    "sg:postcode":"3579",
    "sg:province":"VIC",
    "sg:tags":[
        "footwear"
    ],
    "wof:name":"Nick's Splendid Shoes",
    "wof:placetype":"venue"
},
  "geometry": {"coordinates":[143.92030334500001,-35.7359657288],"type":"Point"}
}