{
  "type": "Feature",
  "properties": {
    "addr:full":"21 Elsworth Mittagong NSW 2575",
    "addr:housenumber":"21",
    "addr:postcode":"2575",
    "addr:street":"Elsworth",
    "iso:country":"AU",
    "sg:address":"21 Elsworth",
    "sg:city":"Mittagong",
    "sg:classifiers":[
        {
            "category":"Education",
            "subcategory":"Kindergarten",
            "type":"Public Place"
        }
    ],
    "sg:phone":"+61 2 4872 4699",
    "sg:postcode":"2575",
    "sg:province":"NSW",
    "sg:tags":[
        "pre-schools"
    ],
    "wof:name":"Birrahlee Childrens Centre",
    "wof:placetype":"venue"
},
  "geometry": {"coordinates":[150.47157287600001,-34.4416694641],"type":"Point"}
}