{
  "type": "Feature",
  "properties": {
    "addr:full":"96 - 98 Douglas Pde Williamstown VIC 3016",
    "addr:housenumber":"98",
    "addr:postcode":"3016",
    "addr:street":"Douglas Pde",
    "iso:country":"AU",
    "sg:address":"96 - 98 Douglas Pde",
    "sg:city":"Williamstown",
    "sg:classifiers":[
        {
            "category":"Health Services",
            "subcategory":"Optometrist",
            "type":"Services"
        }
    ],
    "sg:phone":"+61 3 9397 5895",
    "sg:postcode":"3016",
    "sg:province":"VIC",
    "wof:name":"Brazionis & Associates",
    "wof:placetype":"venue"
},
  "geometry": {"coordinates":[144.897705078,-37.8557472229],"type":"Point"}
}