{
  "type": "Feature",
  "properties": {
    "iso:country":"AU",
    "sg:address":"10 Richardson St",
    "sg:city":"Pacific Paradise",
    "sg:classifiers":[
        {
            "category":"Sports & Exercise",
            "subcategory":"Gym",
            "type":"Entertainment"
        }
    ],
    "sg:phone":"+61 412 475 563",
    "sg:postcode":"4564",
    "sg:province":"QLD",
    "sg:tags":[
        "personal",
        "trainer",
        "fitness"
    ],
    "wof:name":"Kustom Fitness & Health",
    "wof:placetype":"venue"
},
  "geometry": {"coordinates":[153.07986450199999,-26.614988327],"type":"Point"}
}