{
  "type": "Feature",
  "properties": {
    "addr:full":"150 Murphy St Bendigo VIC 3550",
    "addr:housenumber":"150",
    "addr:postcode":"3550",
    "addr:street":"Murphy St",
    "iso:country":"AU",
    "sg:address":"150 Murphy St",
    "sg:city":"Bendigo",
    "sg:classifiers":[
        {
            "category":"Shopping",
            "type":"Retail Goods"
        }
    ],
    "sg:phone":"+61 3 5442 5211",
    "sg:postcode":"3550",
    "sg:province":"VIC",
    "sg:tags":[
        "agent",
        "stock"
    ],
    "wof:name":"Rodwells & Co Pty Ltd",
    "wof:placetype":"venue"
},
  "geometry": {"coordinates":[144.30387878400001,-36.7477111816],"type":"Point"}
}