{
  "type": "Feature",
  "properties": {
    "iso:country":"AU",
    "sg:address":"Cnr Great Eastern Hwy & Helena Tce",
    "sg:city":"Sawyers Valley",
    "sg:classifiers":[
        {
            "category":"Autos & Motor Vehicles",
            "subcategory":"Auto Supplies",
            "type":"Retail Goods"
        }
    ],
    "sg:phone":"+61 8 9295 3399",
    "sg:postcode":"6074",
    "sg:province":"WA",
    "sg:tags":[
        "tyre"
    ],
    "wof:name":"Sawyers Tyre Warehouse",
    "wof:placetype":"venue"
},
  "geometry": {"coordinates":[116.20863342299999,-31.9030723572],"type":"Point"}
}