{
  "type": "Feature",
  "properties": {
    "addr:full":"Cumberland St East Maitland NSW 2323",
    "addr:postcode":"2323",
    "addr:street":"Cumberland St",
    "iso:country":"AU",
    "sg:address":"Cumberland St",
    "sg:city":"East Maitland",
    "sg:classifiers":[
        {
            "category":"Education",
            "subcategory":"School",
            "type":"Public Place"
        }
    ],
    "sg:phone":"+61 2 4934 2066",
    "sg:postcode":"2323",
    "sg:province":"NSW",
    "sg:tags":[
        "state",
        "-",
        "nsw"
    ],
    "wof:name":"Maitland Grossmann High School",
    "wof:placetype":"venue"
},
  "geometry": {"coordinates":[151.58851623499999,-32.7441062927],"type":"Point"}
}