{
  "type": "Feature",
  "properties": {
    "iso:country":"AU",
    "sg:address":"10 Peter St",
    "sg:city":"Eltham",
    "sg:classifiers":[
        {
            "category":"Professional",
            "subcategory":"Business Services",
            "type":"Services"
        }
    ],
    "sg:phone":"+61 3 9439 2721",
    "sg:postcode":"3095",
    "sg:province":"VIC",
    "sg:tags":[
        "drafting"
    ],
    "wof:name":"Scenic Design & Drafting PTY LTD",
    "wof:placetype":"venue"
},
  "geometry": {"coordinates":[145.141525269,-37.7139778137],"type":"Point"}
}