{
  "type": "Feature",
  "properties": {
    "addr:full":"Highlands St Seymour VIC 3660",
    "addr:postcode":"3660",
    "addr:street":"Highlands St",
    "iso:country":"AU",
    "sg:address":"Highlands St",
    "sg:city":"Seymour",
    "sg:classifiers":[
        {
            "category":"Building & Trades",
            "subcategory":"Cleaning & Sanitation",
            "type":"Services"
        }
    ],
    "sg:phone":"+61 409 314 608",
    "sg:postcode":"3660",
    "sg:province":"VIC",
    "sg:tags":[
        "abrasive",
        "blasting"
    ],
    "wof:name":"Goulburn Valley Sandblasting",
    "wof:placetype":"venue"
},
  "geometry": {"coordinates":[145.160644531,-37.0263328552],"type":"Point"}
}