{
  "type": "Feature",
  "properties": {
    "iso:country":"AU",
    "sg:address":"65 Haig St",
    "sg:city":"South Melbourne",
    "sg:classifiers":[
        {
            "category":"Social Services",
            "subcategory":"Job Training",
            "type":"Services"
        }
    ],
    "sg:phone":"+61 3 9690 2888",
    "sg:postcode":"3205",
    "sg:province":"VIC",
    "sg:tags":[
        "hire",
        "computer",
        "leasing"
    ],
    "wof:name":"Durham Audio Visual",
    "wof:placetype":"venue"
},
  "geometry": {"coordinates":[144.956818,-37.827515],"type":"Point"}
}