{
  "type": "Feature",
  "properties": {
    "addr:full":"Shop 2.11, Garden City Shopping Centre, Northcott Adamstown NSW 2289",
    "addr:postcode":"2289",
    "iso:country":"AU",
    "sg:address":"Shop 2.11, Garden City Shopping Centre, Northcott",
    "sg:city":"Adamstown",
    "sg:classifiers":[
        {
            "category":"Shopping",
            "subcategory":"Shoes",
            "type":"Retail Goods"
        }
    ],
    "sg:phone":"+61 2 4952 6286",
    "sg:postcode":"2289",
    "sg:province":"NSW",
    "sg:tags":[
        "footwear"
    ],
    "wof:name":"Mathers Shoes",
    "wof:placetype":"venue"
},
  "geometry": {"coordinates":[151.71209716800001,-32.9381370544],"type":"Point"}
}