{
  "type": "Feature",
  "properties": {
    "addr:full":"5/ 9 Myrtle St Crows Nest NSW 2065",
    "addr:housenumber":"/ 9",
    "addr:postcode":"2065",
    "addr:street":"Myrtle St",
    "iso:country":"AU",
    "sg:address":"5/ 9 Myrtle St",
    "sg:city":"Crows Nest",
    "sg:classifiers":[
        {
            "category":"Sports & Exercise",
            "subcategory":"Ski Resort",
            "type":"Entertainment"
        }
    ],
    "sg:phone":"+61 2 9955 5352",
    "sg:postcode":"2065",
    "sg:province":"NSW",
    "sg:tags":[
        "tour",
        "centres"
    ],
    "wof:name":"Ski & Snowboard Travel Co",
    "wof:placetype":"venue"
},
  "geometry": {"coordinates":[151.20382690400001,-33.831161499],"type":"Point"}
}