{
  "type": "Feature",
  "properties": {
    "addr:full":"Cox Rd Norlane VIC 3214",
    "addr:postcode":"3214",
    "addr:street":"Cox Rd",
    "iso:country":"AU",
    "sg:address":"Cox Rd",
    "sg:city":"Norlane",
    "sg:classifiers":[
        {
            "category":"Education",
            "subcategory":"School",
            "type":"Public Place"
        }
    ],
    "sg:phone":"+61 3 5275 1393",
    "sg:postcode":"3214",
    "sg:province":"VIC",
    "sg:tags":[
        "state",
        "except",
        "nsw"
    ],
    "wof:name":"Norlane Secondary College",
    "wof:placetype":"venue"
},
  "geometry": {"coordinates":[144.349487305,-38.0830383301],"type":"Point"}
}