{
  "type": "Feature",
  "properties": {
    "addr:full":"130 Auburn Rd Hawthorn VIC 3122",
    "addr:housenumber":"130",
    "addr:postcode":"3122",
    "addr:street":"Auburn Rd",
    "iso:country":"AU",
    "sg:address":"130 Auburn Rd",
    "sg:city":"Hawthorn",
    "sg:classifiers":[
        {
            "category":"Shopping",
            "subcategory":"Bridal",
            "type":"Retail Goods"
        }
    ],
    "sg:phone":"+61 3 9819 1488",
    "sg:postcode":"3122",
    "sg:province":"VIC",
    "sg:tags":[
        "hire",
        "wear"
    ],
    "wof:name":"Olwen Bowe-Beale",
    "wof:placetype":"venue"
},
  "geometry": {"coordinates":[145.044845581,-37.8226470947],"type":"Point"}
}