{
  "type": "Feature",
  "properties": {
    "addr:full":"PO Box 6159 Townsville QLD 4810",
    "addr:postcode":"4810",
    "iso:country":"AU",
    "sg:address":"PO Box 6159",
    "sg:city":"Townsville",
    "sg:classifiers":[
        {
            "category":"Shopping",
            "subcategory":"Clothing, Apparel, & Fashions",
            "type":"Retail Goods"
        }
    ],
    "sg:phone":"+61 412 628 204",
    "sg:postcode":"4810",
    "sg:province":"QLD",
    "sg:tags":[
        "millinery"
    ],
    "wof:name":"Rug Ratz Hatz",
    "wof:placetype":"venue"
},
  "geometry": {"coordinates":[146.75546299999999,-19.2351],"type":"Point"}
}