{
  "type": "Feature",
  "properties": {
    "addr:full":"PO Box 973 Dalby QLD 4405",
    "addr:postcode":"4405",
    "iso:country":"AU",
    "sg:address":"PO Box 973",
    "sg:city":"Dalby",
    "sg:classifiers":[
        {
            "category":"Building & Trades",
            "subcategory":"Plumbing",
            "type":"Services"
        }
    ],
    "sg:phone":"+61 419 673 461",
    "sg:postcode":"4405",
    "sg:province":"QLD",
    "sg:tags":[
        "plumber",
        "gasfitters"
    ],
    "wof:name":"Hart Plumbers",
    "wof:placetype":"venue"
},
  "geometry": {"coordinates":[151.257415772,-27.1783504486],"type":"Point"}
}