{
  "type": "Feature",
  "properties": {
    "addr:full":"Kiosk7/ 1 Bligh St Rosny Park TAS 7018",
    "addr:housenumber":"1",
    "addr:postcode":"7018",
    "addr:street":"Bligh St",
    "iso:country":"AU",
    "sg:address":"Kiosk7/ 1 Bligh St",
    "sg:city":"Rosny Park",
    "sg:classifiers":[
        {
            "category":"Manufacturing",
            "subcategory":"Tools & Machinery",
            "type":"Manufacturing & Wholesale Goods"
        }
    ],
    "sg:phone":"+61 3 6244 8809",
    "sg:postcode":"7018",
    "sg:province":"TAS",
    "sg:tags":[
        "wholesaler",
        "mfrs",
        "hosiery"
    ],
    "wof:name":"Jox & Sox",
    "wof:placetype":"venue"
},
  "geometry": {"coordinates":[147.36872863799999,-42.8678207397],"type":"Point"}
}