{
  "type": "Feature",
  "properties": {
    "addr:full":"139 Ormond Rd Elwood VIC 3184",
    "addr:housenumber":"139",
    "addr:postcode":"3184",
    "addr:street":"Ormond Rd",
    "iso:country":"AU",
    "sg:address":"139 Ormond Rd",
    "sg:city":"Elwood",
    "sg:classifiers":[
        {
            "category":"Health Services",
            "subcategory":"Health Practitioner",
            "type":"Services"
        }
    ],
    "sg:phone":"+61 3 9531 0588",
    "sg:postcode":"3184",
    "sg:province":"VIC",
    "sg:tags":[
        "consultant",
        "conservation",
        "hearing"
    ],
    "wof:name":"Industrial Audiometric Services",
    "wof:placetype":"venue"
},
  "geometry": {"coordinates":[144.98870849599999,-37.8858757019],"type":"Point"}
}