{
  "type": "Feature",
  "properties": {
    "iso:country":"AU",
    "sg:address":"63 Railway St",
    "sg:city":"Corrimal",
    "sg:classifiers":[
        {
            "category":"Health Services",
            "subcategory":"Health Practitioner",
            "type":"Services"
        }
    ],
    "sg:phone":"+61 425 234 398",
    "sg:postcode":"2518",
    "sg:province":"NSW",
    "sg:tags":[
        "psychologist"
    ],
    "wof:name":"Orietta Worthington",
    "wof:placetype":"venue"
},
  "geometry": {"coordinates":[150.90240499999999,-34.373554],"type":"Point"}
}