{
  "type": "Feature",
  "properties": {
    "addr:full":"Unit 1/ 1125 Rochedale Rd Rochedale South QLD 4123",
    "addr:housenumber":"/ 1125",
    "addr:postcode":"4123",
    "addr:street":"Rochedale Rd",
    "iso:country":"AU",
    "sg:address":"Unit 1/ 1125 Rochedale Rd",
    "sg:city":"Rochedale South",
    "sg:classifiers":[
        {
            "category":"Health Services",
            "subcategory":"Medical Lab",
            "type":"Services"
        }
    ],
    "sg:phone":"+61 7 3841 5005",
    "sg:postcode":"4123",
    "sg:province":"QLD",
    "sg:tags":[
        "laboratory",
        "dental"
    ],
    "wof:name":"Ancona Dental Laboratory",
    "wof:placetype":"venue"
},
  "geometry": {"coordinates":[153.11982727,-27.6065864563],"type":"Point"}
}