{
  "type": "Feature",
  "properties": {
    "iso:country":"AU",
    "sg:address":"376 Thompsons Rd",
    "sg:city":"Geelong North",
    "sg:classifiers":[
        {
            "category":"Wholesale",
            "subcategory":"Farm Supplies",
            "type":"Manufacturing & Wholesale Goods"
        }
    ],
    "sg:phone":"+61 3 5272 1289",
    "sg:postcode":"3215",
    "sg:province":"VIC",
    "sg:tags":[
        "feed",
        "supplement",
        "stock"
    ],
    "wof:name":"Blyszaks Stockfeeds",
    "wof:placetype":"venue"
},
  "geometry": {"coordinates":[144.345626831,-38.1001472473],"type":"Point"}
}