{
  "type": "Feature",
  "properties": {
    "addr:full":"419 Regency Rd Prospect SA 5082",
    "addr:housenumber":"419",
    "addr:postcode":"5082",
    "addr:street":"Regency Rd",
    "iso:country":"AU",
    "sg:address":"419 Regency Rd",
    "sg:city":"Prospect",
    "sg:classifiers":[
        {
            "category":"Shopping",
            "subcategory":"Beauty & Cosmetics",
            "type":"Retail Goods"
        }
    ],
    "sg:phone":"+61 1300 929 464",
    "sg:postcode":"5082",
    "sg:province":"SA",
    "sg:tags":[
        "equipment",
        "salon",
        "supply"
    ],
    "wof:name":"Essential Distribution",
    "wof:placetype":"venue"
},
  "geometry": {"coordinates":[138.59454345699999,-34.8741340637],"type":"Point"}
}