{
  "type": "Feature",
  "properties": {
    "addr:full":"31 Mary St Blackstone QLD 4304",
    "addr:housenumber":"31",
    "addr:postcode":"4304",
    "addr:street":"Mary St",
    "iso:country":"AU",
    "sg:address":"31 Mary St",
    "sg:city":"Blackstone",
    "sg:classifiers":[
        {
            "category":"Professional",
            "subcategory":"Art Services",
            "type":"Services"
        }
    ],
    "sg:phone":"+61 7 3282 1449",
    "sg:postcode":"4304",
    "sg:province":"QLD",
    "sg:tags":[
        "decorator",
        "painter"
    ],
    "wof:name":"Rush A & L",
    "wof:placetype":"venue"
},
  "geometry": {"coordinates":[152.802566528,-27.6250553131],"type":"Point"}
}