{
  "type": "Feature",
  "properties": {
    "iso:country":"AU",
    "sg:address":"121 Pruden Rd",
    "sg:city":"Mundijong",
    "sg:classifiers":[
        {
            "category":"Wholesale",
            "subcategory":"Seafood",
            "type":"Manufacturing & Wholesale Goods"
        }
    ],
    "sg:phone":"+61 410 652 119",
    "sg:postcode":"6123",
    "sg:province":"WA",
    "sg:tags":[
        "fish"
    ],
    "wof:name":"Yarrabah",
    "wof:placetype":"venue"
},
  "geometry": {"coordinates":[116.011917114,-32.2997703552],"type":"Point"}
}