{
  "type": "Feature",
  "properties": {
    "iso:country":"AU",
    "sg:address":"Boort Rd",
    "sg:city":"Kerang",
    "sg:classifiers":[
        {
            "category":"Home & Garden",
            "subcategory":"Building Materials",
            "type":"Retail Goods"
        }
    ],
    "sg:phone":"+61 3 5452 2188",
    "sg:postcode":"3579",
    "sg:province":"VIC",
    "sg:tags":[
        "fitting",
        "door"
    ],
    "wof:name":"Dahlsens Kerang",
    "wof:placetype":"venue"
},
  "geometry": {"coordinates":[143.91792297399999,-35.7366409302],"type":"Point"}
}