{
  "type": "Feature",
  "properties": {
    "iso:country":"AU",
    "sg:address":"60 Uralba St",
    "sg:city":"Lismore",
    "sg:classifiers":[
        {
            "category":"Health Services",
            "subcategory":"Doctor",
            "type":"Services"
        }
    ],
    "sg:phone":"+61 2 6628 0967",
    "sg:postcode":"2480",
    "sg:province":"NSW",
    "sg:tags":[
        "medical",
        "practitioner"
    ],
    "wof:name":"EEG Service",
    "wof:placetype":"venue"
},
  "geometry": {"coordinates":[153.28993225100001,-28.809841156],"type":"Point"}
}