{
  "type": "Feature",
  "properties": {
    "iso:country":"AU",
    "sg:address":"1615 Point Nepean Hwy",
    "sg:city":"Rosebud",
    "sg:classifiers":[
        {
            "category":"Fast Food",
            "type":"Food & Drink"
        }
    ],
    "sg:phone":"+61 13 12 41",
    "sg:postcode":"3939",
    "sg:province":"VIC",
    "sg:tags":[
        "away",
        "take"
    ],
    "wof:name":"Pizza Haven",
    "wof:placetype":"venue"
},
  "geometry": {"coordinates":[144.87680053700001,-38.3635673523],"type":"Point"}
}