{
  "type": "Feature",
  "properties": {
    "addr:full":"88 Flores Rd Geraldton WA 6530",
    "addr:housenumber":"88",
    "addr:postcode":"6530",
    "addr:street":"Flores Rd",
    "iso:country":"AU",
    "sg:address":"88 Flores Rd",
    "sg:city":"Geraldton",
    "sg:classifiers":[
        {
            "category":"Professional",
            "subcategory":"Engineering",
            "type":"Services"
        }
    ],
    "sg:phone":"+61 8 9921 6193",
    "sg:postcode":"6530",
    "sg:province":"WA",
    "sg:tags":[
        "engineer"
    ],
    "wof:name":"JLW Engineering",
    "wof:placetype":"venue"
},
  "geometry": {"coordinates":[114.63044738799999,-28.7549571991],"type":"Point"}
}