{
  "type": "Feature",
  "properties": {
    "addr:full":"15 Olinda St Glen Waverley VIC 3150",
    "addr:housenumber":"15",
    "addr:postcode":"3150",
    "addr:street":"Olinda St",
    "iso:country":"AU",
    "sg:address":"15 Olinda St",
    "sg:city":"Glen Waverley",
    "sg:classifiers":[
        {
            "category":"Retail",
            "subcategory":"Repair Shop",
            "type":"Services"
        }
    ],
    "sg:phone":"+61 3 9560 8016",
    "sg:postcode":"3150",
    "sg:province":"VIC",
    "sg:tags":[
        "repairing",
        "piano",
        "tuning"
    ],
    "wof:name":"Rick Alabaster",
    "wof:placetype":"venue"
},
  "geometry": {"coordinates":[145.16969299300001,-37.887096405],"type":"Point"}
}