{
  "type": "Feature",
  "properties": {
    "addr:full":"237 William St Devonport TAS 7310",
    "addr:housenumber":"237",
    "addr:postcode":"7310",
    "addr:street":"William St",
    "iso:country":"AU",
    "sg:address":"237 William St",
    "sg:city":"Devonport",
    "sg:classifiers":[
        {
            "category":"Manufacturing",
            "subcategory":"Tools & Machinery",
            "type":"Manufacturing & Wholesale Goods"
        }
    ],
    "sg:phone":"+61 419 325 655",
    "sg:postcode":"7310",
    "sg:province":"TAS",
    "sg:tags":[
        "earth",
        "excavating",
        "moving",
        "equipment"
    ],
    "wof:name":"A.B. & K. Plummer",
    "wof:placetype":"venue"
},
  "geometry": {"coordinates":[146.35310363799999,-41.1669311523],"type":"Point"}
}