{
  "type": "Feature",
  "properties": {
    "addr:full":"Park Rd West Dutton Park QLD 4102",
    "addr:postcode":"4102",
    "addr:street":"Park Rd West",
    "iso:country":"AU",
    "sg:address":"Park Rd West",
    "sg:city":"Dutton Park",
    "sg:classifiers":[
        {
            "category":"Manufacturing",
            "subcategory":"Jewelry",
            "type":"Manufacturing & Wholesale Goods"
        }
    ],
    "sg:phone":"+61 7 3844 9891",
    "sg:postcode":"4102",
    "sg:province":"QLD",
    "sg:tags":[
        "designer",
        "jewellery"
    ],
    "wof:name":"Highgate Jewellery",
    "wof:placetype":"venue"
},
  "geometry": {"coordinates":[153.02444457999999,-27.4914512634],"type":"Point"}
}