{
  "type": "Feature",
  "properties": {
    "iso:country":"AU",
    "sg:address":"1 Evans St",
    "sg:city":"Hobart",
    "sg:classifiers":[
        {
            "category":"Professional",
            "type":"Services"
        }
    ],
    "sg:phone":"+61 3 6231 9600",
    "sg:postcode":"7000",
    "sg:province":"TAS",
    "sg:tags":[
        "forwarding",
        "agent",
        "transport"
    ],
    "wof:name":"GHT Freight Services",
    "wof:placetype":"venue"
},
  "geometry": {"coordinates":[147.33605957,-42.8809318542],"type":"Point"}
}