{
  "type": "Feature",
  "properties": {
    "addr:full":"10 Groome Crt Altona Meadows VIC 3028",
    "addr:housenumber":"10",
    "addr:postcode":"3028",
    "addr:street":"Groome Crt",
    "iso:country":"AU",
    "sg:address":"10 Groome Crt",
    "sg:city":"Altona Meadows",
    "sg:classifiers":[
        {
            "category":"Professional",
            "subcategory":"Detective & Security Services",
            "type":"Services"
        }
    ],
    "sg:phone":"+61 417 785 500",
    "sg:postcode":"3028",
    "sg:province":"VIC",
    "sg:tags":[
        "consultant",
        "system"
    ],
    "wof:name":"Security Innovations",
    "wof:placetype":"venue"
},
  "geometry": {"coordinates":[144.78276099999999,-37.893726],"type":"Point"}
}