{
  "type": "Feature",
  "properties": {
    "addr:full":"2 Tristania St Doncaster East VIC 3109",
    "addr:housenumber":"2",
    "addr:postcode":"3109",
    "addr:street":"Tristania St",
    "iso:country":"AU",
    "sg:address":"2 Tristania St",
    "sg:city":"Doncaster East",
    "sg:classifiers":[
        {
            "category":"Building & Trades",
            "subcategory":"Plumbing",
            "type":"Services"
        }
    ],
    "sg:phone":"+61 414 454 021",
    "sg:postcode":"3109",
    "sg:province":"VIC",
    "sg:tags":[
        "plumber",
        "gasfitters"
    ],
    "wof:name":"Mr Melon Plumbing Services",
    "wof:placetype":"venue"
},
  "geometry": {"coordinates":[145.14337158199999,-37.7931137085],"type":"Point"}
}