{
  "type": "Feature",
  "properties": {
    "addr:full":"612 Darling St Rozelle NSW 2039",
    "addr:housenumber":"612",
    "addr:postcode":"2039",
    "addr:street":"Darling St",
    "iso:country":"AU",
    "sg:address":"612 Darling St",
    "sg:city":"Rozelle",
    "sg:classifiers":[
        {
            "category":"Cafe",
            "type":"Food & Drink"
        }
    ],
    "sg:phone":"+61 2 9818 1607",
    "sg:postcode":"2039",
    "sg:province":"NSW",
    "wof:name":"Coffee Bean Cafe",
    "wof:placetype":"venue"
},
  "geometry": {"coordinates":[151.17137145999999,-33.8618965149],"type":"Point"}
}