{
  "type": "Feature",
  "properties": {
    "addr:full":"14 Telopea Ave Homebush West NSW 2140",
    "addr:housenumber":"14",
    "addr:postcode":"2140",
    "addr:street":"Telopea Ave",
    "iso:country":"AU",
    "sg:address":"14 Telopea Ave",
    "sg:city":"Homebush West",
    "sg:classifiers":[
        {
            "category":"Professional",
            "subcategory":"Computer Services",
            "type":"Services"
        }
    ],
    "sg:phone":"+61 2 9763 7963",
    "sg:postcode":"2140",
    "sg:province":"NSW",
    "sg:tags":[
        "consultant",
        "system"
    ],
    "wof:name":"Acolade Pty Ltd",
    "wof:placetype":"venue"
},
  "geometry": {"coordinates":[151.066574097,-33.8582878113],"type":"Point"}
}