{
  "type": "Feature",
  "properties": {
    "iso:country":"AU",
    "sg:address":"St",
    "sg:city":"George Private Hospital, Kogarah",
    "sg:classifiers":[
        {
            "category":"Health Services",
            "subcategory":"Doctor",
            "type":"Services"
        }
    ],
    "sg:phone":"+61 2 9553 7277",
    "sg:postcode":"2217",
    "sg:province":"NSW",
    "sg:tags":[
        "medical",
        "practitioner"
    ],
    "wof:name":"Katsoulotos Gregory Dr",
    "wof:placetype":"venue"
},
  "geometry": {"coordinates":[151.132675,-33.963169],"type":"Point"}
}