{
  "type": "Feature",
  "properties": {
    "iso:country":"AU",
    "sg:address":"15 Michellan Cres",
    "sg:city":"Bayswater",
    "sg:classifiers":[
        {
            "category":"Retail",
            "subcategory":"Auto Repair",
            "type":"Services"
        }
    ],
    "sg:phone":"+61 3 9720 9848",
    "sg:postcode":"3153",
    "sg:province":"VIC",
    "sg:tags":[
        "repairer",
        "motor",
        "engineer"
    ],
    "wof:name":"Dough Beaton Automotive",
    "wof:placetype":"venue"
},
  "geometry": {"coordinates":[145.241744995,-37.8432540894],"type":"Point"}
}