{
  "type": "Feature",
  "properties": {
    "addr:full":"245 Barker St Castlemaine VIC 3450",
    "addr:housenumber":"245",
    "addr:postcode":"3450",
    "addr:street":"Barker St",
    "iso:country":"AU",
    "sg:address":"245 Barker St",
    "sg:city":"Castlemaine",
    "sg:classifiers":[
        {
            "category":"Fast Food",
            "type":"Food & Drink"
        }
    ],
    "sg:phone":"+61 3 5472 2117",
    "sg:postcode":"3450",
    "sg:province":"VIC",
    "sg:tags":[
        "away",
        "take"
    ],
    "wof:name":"Athens Fish Shop",
    "wof:placetype":"venue"
},
  "geometry": {"coordinates":[144.22198486299999,-37.0486412048],"type":"Point"}
}