{
  "type": "Feature",
  "properties": {
    "addr:full":"287 Byron St Inverell NSW 2360",
    "addr:housenumber":"287",
    "addr:postcode":"2360",
    "addr:street":"Byron St",
    "iso:country":"AU",
    "sg:address":"287 Byron St",
    "sg:city":"Inverell",
    "sg:classifiers":[
        {
            "category":"Wholesale",
            "subcategory":"Machinery & Supplies",
            "type":"Manufacturing & Wholesale Goods"
        }
    ],
    "sg:phone":"+61 2 6722 3388",
    "sg:postcode":"2360",
    "sg:province":"NSW",
    "sg:tags":[
        "agricultural"
    ],
    "wof:name":"Inverell Power Farm Co",
    "wof:placetype":"venue"
},
  "geometry": {"coordinates":[151.121337891,-29.7669487],"type":"Point"}
}