{
  "type": "Feature",
  "properties": {
    "iso:country":"AU",
    "sg:address":"30 Wandoo Ave",
    "sg:city":"Ryde",
    "sg:classifiers":[
        {
            "category":"Farming",
            "subcategory":"Crops",
            "type":"Manufacturing & Wholesale Goods"
        }
    ],
    "sg:phone":"+61 403 062 230",
    "sg:postcode":"2112",
    "sg:province":"NSW",
    "sg:tags":[
        "club",
        "rowing"
    ],
    "wof:name":"Euro Product Sales Pty Ltd",
    "wof:placetype":"venue"
},
  "geometry": {"coordinates":[151.10458374000001,-33.8187332153],"type":"Point"}
}