{
  "type": "Feature",
  "properties": {
    "addr:full":"Kiosk 2900A Macquarie St Liverpool NSW 2170",
    "addr:housenumber":"2900a",
    "addr:postcode":"2170",
    "addr:street":"Macquarie St",
    "iso:country":"AU",
    "sg:address":"Kiosk 2900A Macquarie St",
    "sg:city":"Liverpool",
    "sg:classifiers":[
        {
            "category":"Food & Beverages",
            "subcategory":"Bakery",
            "type":"Retail Goods"
        }
    ],
    "sg:phone":"+61 2 9824 2499",
    "sg:postcode":"2170",
    "sg:province":"NSW",
    "sg:tags":[
        "baker"
    ],
    "wof:name":"Muffin Break",
    "wof:placetype":"venue"
},
  "geometry": {"coordinates":[150.918243408,-33.9284934998],"type":"Point"}
}