{
  "type": "Feature",
  "properties": {
    "iso:country":"AU",
    "sg:address":"Shop 17,20- 28 Kareena Rd",
    "sg:city":"Miranda",
    "sg:classifiers":[
        {
            "category":"Military Area",
            "subcategory":"Air Force Base",
            "type":"Public Place"
        }
    ],
    "sg:phone":"+61 2 9540 2717",
    "sg:postcode":"2228",
    "sg:province":"NSW",
    "sg:tags":[
        "men's",
        "tailor"
    ],
    "wof:name":"V & F Tailoring",
    "wof:placetype":"venue"
},
  "geometry": {"coordinates":[151.114746094,-34.0296325684],"type":"Point"}
}