{
  "type": "Feature",
  "properties": {
    "addr:full":"Shop 3, Calala Green Shopping Village, 10 Campbell Calala NSW 2340",
    "addr:housenumber":"shop 3;10",
    "addr:postcode":"2340",
    "addr:street":"Calala Green;Campbell Calala",
    "iso:country":"AU",
    "sg:address":"Shop 3, Calala Green Shopping Village, 10 Campbell",
    "sg:city":"Calala",
    "sg:classifiers":[
        {
            "category":"Wholesale",
            "subcategory":"Medical Equipment & Supplies",
            "type":"Manufacturing & Wholesale Goods"
        }
    ],
    "sg:phone":"+61 2 6762 2443",
    "sg:postcode":"2340",
    "sg:province":"NSW",
    "sg:tags":[
        "aid",
        "care",
        "health",
        "home"
    ],
    "wof:name":"Mahonys Calala Pharmacy",
    "wof:placetype":"venue"
},
  "geometry": {"coordinates":[150.94122314399999,-31.127155304],"type":"Point"}
}