{
  "type": "Feature",
  "properties": {
    "iso:country":"AU",
    "sg:address":"217 The Entrance Rd",
    "sg:city":"Erina",
    "sg:classifiers":[
        {
            "category":"Retail",
            "subcategory":"Auto Repair",
            "type":"Services"
        }
    ],
    "sg:phone":"+61 2 4367 6955",
    "sg:postcode":"2250",
    "sg:province":"NSW",
    "sg:tags":[
        "muffler",
        "exhaust",
        "system"
    ],
    "wof:name":"The General Muffler Co",
    "wof:placetype":"venue"
},
  "geometry": {"coordinates":[151.389968872,-33.433506012],"type":"Point"}
}