{
  "type": "Feature",
  "properties": {
    "addr:full":"Westfield Woden Shop LG56 Keltie St Phillip ACT 2606",
    "addr:postcode":"2606",
    "addr:street":"Keltie St",
    "iso:country":"AU",
    "sg:address":"Westfield Woden Shop LG56 Keltie St",
    "sg:city":"Phillip",
    "sg:classifiers":[
        {
            "category":"Fast Food",
            "type":"Food & Drink"
        }
    ],
    "sg:phone":"+61 2 6281 2788",
    "sg:postcode":"2606",
    "sg:province":"ACT",
    "sg:tags":[
        "away",
        "take"
    ],
    "wof:name":"Healthy Habits Woden",
    "wof:placetype":"venue"
},
  "geometry": {"coordinates":[149.085861206,-35.3476524353],"type":"Point"}
}