{
  "type": "Feature",
  "properties": {
    "addr:full":"245a Peel St Tamworth NSW 2340",
    "addr:housenumber":"245a",
    "addr:postcode":"2340",
    "addr:street":"Peel St",
    "iso:country":"AU",
    "sg:address":"245a Peel St",
    "sg:city":"Tamworth",
    "sg:classifiers":[
        {
            "category":"Building & Trades",
            "subcategory":"Construction",
            "type":"Services"
        }
    ],
    "sg:phone":"+61 2 6766 8486",
    "sg:postcode":"2340",
    "sg:province":"NSW",
    "sg:tags":[
        "pool",
        "swimming"
    ],
    "wof:name":"Leisure Pools",
    "wof:placetype":"venue"
},
  "geometry": {"coordinates":[150.927932739,-31.0887432098],"type":"Point"}
}