{
  "type": "Feature",
  "properties": {
    "addr:full":"46- 50 Princes Hwy Beaconsfield VIC 3807",
    "addr:housenumber":"50",
    "addr:postcode":"3807",
    "addr:street":"Princes Hwy",
    "iso:country":"AU",
    "sg:address":"46- 50 Princes Hwy",
    "sg:city":"Beaconsfield",
    "sg:classifiers":[
        {
            "category":"Education",
            "subcategory":"Special Training",
            "type":"Public Place"
        }
    ],
    "sg:phone":"+61 3 9707 5699",
    "sg:postcode":"3807",
    "sg:province":"VIC",
    "sg:tags":[
        "tuition-educational"
    ],
    "wof:name":"Master Coaching",
    "wof:placetype":"venue"
},
  "geometry": {"coordinates":[145.36843872099999,-38.0467224121],"type":"Point"}
}