{
  "type": "Feature",
  "properties": {
    "iso:country":"AU",
    "sg:address":"1 Ronston Crt",
    "sg:city":"Wheelers Hill",
    "sg:classifiers":[
        {
            "category":"Building & Trades",
            "subcategory":"Construction",
            "type":"Services"
        }
    ],
    "sg:phone":"+61 3 9574 9122",
    "sg:postcode":"3150",
    "sg:province":"VIC",
    "sg:tags":[
        "contractor"
    ],
    "wof:name":"Lama Industrial Development Pty Ltd",
    "wof:placetype":"venue"
},
  "geometry": {"coordinates":[145.192337036,-37.9134788513],"type":"Point"}
}