{
  "type": "Feature",
  "properties": {
    "iso:country":"AU",
    "sg:address":"1 Apollo Ave",
    "sg:city":"West Pymble",
    "sg:classifiers":[
        {
            "category":"Building & Trades",
            "subcategory":"Cleaning & Sanitation",
            "type":"Services"
        }
    ],
    "sg:phone":"+61 2 9403 1559",
    "sg:postcode":"2073",
    "sg:province":"NSW",
    "sg:tags":[
        "chemical",
        "pressure",
        "steam",
        "contractor"
    ],
    "wof:name":"A Cleana People Pty Ltd",
    "wof:placetype":"venue"
},
  "geometry": {"coordinates":[151.122955322,-33.7646102905],"type":"Point"}
}