{
  "type": "Feature",
  "properties": {
    "addr:full":"15 Dunban Rd Woy Woy NSW 2256",
    "addr:housenumber":"15",
    "addr:postcode":"2256",
    "addr:street":"Dunban Rd",
    "iso:country":"AU",
    "sg:address":"15 Dunban Rd",
    "sg:city":"Woy Woy",
    "sg:classifiers":[
        {
            "category":"Travel",
            "subcategory":"Hotels & Motels",
            "type":"Entertainment"
        }
    ],
    "sg:phone":"+61 2 4341 7374",
    "sg:postcode":"2256",
    "sg:province":"NSW",
    "wof:name":"The Glades Country Club Motor Inn",
    "wof:placetype":"venue"
},
  "geometry": {"coordinates":[151.315063477,-33.4986038208],"type":"Point"}
}