{
  "type": "Feature",
  "properties": {
    "addr:full":"U9/ 14 Hopper Ave Ormeau QLD 4208",
    "addr:housenumber":"14",
    "addr:postcode":"4208",
    "addr:street":"U9 /;Hopper Ave",
    "iso:country":"AU",
    "sg:address":"U9/ 14 Hopper Ave",
    "sg:city":"Ormeau",
    "sg:classifiers":[
        {
            "category":"Transit Center",
            "subcategory":"Passenger",
            "type":"Transportation"
        }
    ],
    "sg:phone":"+61 7 5549 3664",
    "sg:postcode":"4208",
    "sg:province":"QLD",
    "sg:tags":[
        "frozen",
        "food",
        "retail"
    ],
    "wof:name":"Harvestime Queensland",
    "wof:placetype":"venue"
},
  "geometry": {"coordinates":[153.25531005900001,-27.7818183899],"type":"Point"}
}