{
  "type": "Feature",
  "properties": {
    "iso:country":"AU",
    "sg:address":"15 Church St",
    "sg:city":"Moruya",
    "sg:classifiers":[
        {
            "category":"Government",
            "subcategory":"Fire Station",
            "type":"Public Place"
        }
    ],
    "sg:phone":"+61 2 4474 2550",
    "sg:postcode":"2537",
    "sg:province":"NSW",
    "sg:tags":[
        "brigade"
    ],
    "wof:name":"Fire Brigades-NSW",
    "wof:placetype":"venue"
},
  "geometry": {"coordinates":[150.08274841299999,-35.9094543457],"type":"Point"}
}