{
  "type": "Feature",
  "properties": {
    "iso:country":"AU",
    "sg:address":"8 - 140 Baringa St",
    "sg:city":"Morningside",
    "sg:classifiers":[
        {
            "category":"Government",
            "subcategory":"Court House",
            "type":"Public Place"
        }
    ],
    "sg:phone":"+61 7 3899 4924",
    "sg:postcode":"4170",
    "sg:province":"QLD",
    "sg:tags":[
        "personal",
        "marriage",
        "family",
        "counselling"
    ],
    "wof:name":"Change Dynamics",
    "wof:placetype":"venue"
},
  "geometry": {"coordinates":[153.07212829599999,-27.4630489349],"type":"Point"}
}