{
  "type": "Feature",
  "properties": {
    "addr:full":"17 McLean St Bundaberg QLD 4670",
    "addr:housenumber":"17",
    "addr:postcode":"4670",
    "addr:street":"Mclean St",
    "iso:country":"AU",
    "sg:address":"17 McLean St",
    "sg:city":"Bundaberg",
    "sg:classifiers":[
        {
            "category":"Retail",
            "subcategory":"Auto Repair",
            "type":"Services"
        }
    ],
    "sg:phone":"+61 7 4151 5503",
    "sg:postcode":"4670",
    "sg:province":"QLD",
    "sg:tags":[
        "wheel",
        "balancing",
        "alignment"
    ],
    "wof:name":"Dowds Steering Specialists",
    "wof:placetype":"venue"
},
  "geometry": {"coordinates":[152.34687805199999,-24.8720722198],"type":"Point"}
}