{
  "type": "Feature",
  "properties": {
    "addr:full":"4a Mickle St Dandenong VIC 3175",
    "addr:housenumber":"4a",
    "addr:postcode":"3175",
    "addr:street":"Mickle St",
    "iso:country":"AU",
    "sg:address":"4a Mickle St",
    "sg:city":"Dandenong",
    "sg:classifiers":[
        {
            "category":"Manufacturing",
            "subcategory":"Tools & Machinery",
            "type":"Manufacturing & Wholesale Goods"
        }
    ],
    "sg:phone":"+61 3 9768 2887",
    "sg:postcode":"3175",
    "sg:province":"VIC",
    "sg:tags":[
        "toolmaker"
    ],
    "wof:name":"Apex Tooling PTY LTD",
    "wof:placetype":"venue"
},
  "geometry": {"coordinates":[145.202728272,-38.0300102234],"type":"Point"}
}