{
  "type": "Feature",
  "properties": {
    "addr:full":"129 Woodward Rd Bundaberg QLD 4670",
    "addr:housenumber":"129",
    "addr:postcode":"4670",
    "addr:street":"Woodward Rd",
    "iso:country":"AU",
    "sg:address":"129 Woodward Rd",
    "sg:city":"Bundaberg",
    "sg:classifiers":[
        {
            "category":"Manufacturing",
            "subcategory":"Rubber & Plastics",
            "type":"Manufacturing & Wholesale Goods"
        }
    ],
    "sg:phone":"+61 7 4155 1223",
    "sg:postcode":"4670",
    "sg:province":"QLD",
    "sg:tags":[
        "lime"
    ],
    "wof:name":"Nanport Pty Ltd",
    "wof:placetype":"venue"
},
  "geometry": {"coordinates":[152.33824157699999,-24.9308986664],"type":"Point"}
}