{
  "type": "Feature",
  "properties": {
    "iso:country":"AU",
    "sg:address":"Unit 7 37a Tourist Rd",
    "sg:city":"Toowoomba",
    "sg:classifiers":[
        {
            "category":"Personal",
            "subcategory":"Nail Salon",
            "type":"Services"
        }
    ],
    "sg:phone":"+61 7 4639 3772",
    "sg:postcode":"4350",
    "sg:province":"QLD",
    "sg:tags":[
        "artificial"
    ],
    "wof:name":"Busy Fingers",
    "wof:placetype":"venue"
},
  "geometry": {"coordinates":[151.97674599999999,-27.569429],"type":"Point"}
}