{
  "type": "Feature",
  "properties": {
    "iso:country":"AU",
    "sg:address":"1/ 3 Birtwill St",
    "sg:city":"Coolum Beach",
    "sg:classifiers":[
        {
            "category":"Health Services",
            "subcategory":"Doctor",
            "type":"Services"
        }
    ],
    "sg:phone":"+61 13 36 28",
    "sg:postcode":"4573",
    "sg:province":"QLD",
    "sg:tags":[
        "medical",
        "practitioner"
    ],
    "wof:name":"After Hours Medical Care",
    "wof:placetype":"venue"
},
  "geometry": {"coordinates":[153.09019499999999,-26.527267],"type":"Point"}
}