{
  "type": "Feature",
  "properties": {
    "addr:full":"22 Theodore St Curtin ACT 2605",
    "addr:housenumber":"22",
    "addr:postcode":"2605",
    "addr:street":"Theodore St",
    "iso:country":"AU",
    "sg:address":"22 Theodore St",
    "sg:city":"Curtin",
    "sg:classifiers":[
        {
            "category":"Banks & Credit Unions",
            "subcategory":"Bureau De Change",
            "type":"Services"
        }
    ],
    "sg:phone":"+61 2 6285 1843",
    "sg:postcode":"2605",
    "sg:province":"ACT",
    "sg:tags":[
        "planning",
        "family"
    ],
    "wof:name":"Natural Family Planning",
    "wof:placetype":"venue"
},
  "geometry": {"coordinates":[149.08169555699999,-35.3284225464],"type":"Point"}
}