{
  "type": "Feature",
  "properties": {
    "iso:country":"AU",
    "sg:address":"701 / 12 Edward St",
    "sg:city":"Brisbane",
    "sg:classifiers":[
        {
            "category":"Organizations",
            "subcategory":"Professional Association",
            "type":"Services"
        }
    ],
    "sg:phone":"+61 431 788 003",
    "sg:postcode":"4000",
    "sg:province":"QLD",
    "sg:tags":[
        "web",
        "internet"
    ],
    "wof:name":"Insiteful.org",
    "wof:placetype":"venue"
},
  "geometry": {"coordinates":[153.03030395499999,-27.4719657898],"type":"Point"}
}