{
  "type": "Feature",
  "properties": {
    "iso:country":"AU",
    "sg:address":"Suite 3 Grnd Flr 406- 408 King St",
    "sg:city":"Newcastle West",
    "sg:classifiers":[
        {
            "category":"Organizations",
            "subcategory":"Labor Organization",
            "type":"Services"
        }
    ],
    "sg:phone":"+61 2 4929 2988",
    "sg:postcode":"2302",
    "sg:province":"NSW",
    "sg:tags":[
        "union"
    ],
    "wof:name":"Teachers Federation",
    "wof:placetype":"venue"
},
  "geometry": {"coordinates":[151.759644,-32.926857],"type":"Point"}
}