{
  "type": "Feature",
  "properties": {
    "iso:country":"AU",
    "sg:address":"60 Dernancourt Pde",
    "sg:city":"Milperra",
    "sg:classifiers":[
        {
            "category":"Building & Trades",
            "subcategory":"Cleaning & Sanitation",
            "type":"Services"
        }
    ],
    "sg:phone":"+61 2 9771 1770",
    "sg:postcode":"2214",
    "sg:province":"NSW",
    "sg:tags":[
        "cleaner",
        "repairer",
        "roof"
    ],
    "wof:name":"Aussie Metal Roofing",
    "wof:placetype":"venue"
},
  "geometry": {"coordinates":[150.986176,-33.938324],"type":"Point"}
}