{
  "type": "Feature",
  "properties": {
    "iso:country":"AU",
    "sg:address":"38 Kenny St",
    "sg:city":"Wollongong",
    "sg:classifiers":[
        {
            "category":"Education",
            "subcategory":"Kindergarten",
            "type":"Public Place"
        }
    ],
    "sg:phone":"+61 2 4226 6589",
    "sg:postcode":"2500",
    "sg:province":"NSW",
    "sg:tags":[
        "pre-schools"
    ],
    "wof:name":"Grandma Rosie's Quality Long Day Care",
    "wof:placetype":"venue"
},
  "geometry": {"coordinates":[150.891525,-34.428848],"type":"Point"}
}