{
  "type": "Feature",
  "properties": {
    "addr:full":"118 Mcmillans Rd Paddys Green QLD 4880",
    "addr:housenumber":"118",
    "addr:postcode":"4880",
    "addr:street":"Mcmillans Rd",
    "iso:country":"AU",
    "sg:address":"118 Mcmillans Rd",
    "sg:city":"Paddys Green",
    "sg:classifiers":[
        {
            "category":"Farming",
            "subcategory":"Farm & Veterinary Services",
            "type":"Manufacturing & Wholesale Goods"
        }
    ],
    "sg:phone":"+61 408 084 995",
    "sg:postcode":"4880",
    "sg:province":"QLD",
    "sg:tags":[
        "agricultural",
        "advisory"
    ],
    "wof:name":"Zuiden Investments Pty Ltd",
    "wof:placetype":"venue"
},
  "geometry": {"coordinates":[145.3490448,-17.0102291107],"type":"Point"}
}