{
  "type": "Feature",
  "properties": {
    "iso:country":"AU",
    "sg:address":"27 Bondi Rd",
    "sg:city":"Bondi Junction",
    "sg:classifiers":[
        {
            "category":"Health Services",
            "subcategory":"Doctor",
            "type":"Services"
        }
    ],
    "sg:phone":"+61 2 9389 5811",
    "sg:postcode":"2022",
    "sg:province":"NSW",
    "sg:tags":[
        "medical",
        "practitioner"
    ],
    "wof:name":"Rish Adam",
    "wof:placetype":"venue"
},
  "geometry": {"coordinates":[151.25538635300001,-33.8929176331],"type":"Point"}
}