{
  "type": "Feature",
  "properties": {
    "iso:country":"AU",
    "sg:address":"U 3/ 152 Darby St",
    "sg:city":"Cooks Hill",
    "sg:classifiers":[
        {
            "category":"Sports & Exercise",
            "subcategory":"Sports Center",
            "type":"Entertainment"
        }
    ],
    "sg:phone":"+61 408 737 990",
    "sg:postcode":"2300",
    "sg:province":"NSW",
    "sg:tags":[
        "physiologist"
    ],
    "wof:name":"On De Mend",
    "wof:placetype":"venue"
},
  "geometry": {"coordinates":[151.770935,-32.932072],"type":"Point"}
}