{
  "type": "Feature",
  "properties": {
    "iso:country":"AU",
    "sg:address":"10 Pine Ave",
    "sg:city":"Elwood",
    "sg:classifiers":[
        {
            "category":"Real Estate",
            "subcategory":"Architect",
            "type":"Services"
        }
    ],
    "sg:phone":"+61 3 9531 6824",
    "sg:postcode":"3184",
    "sg:province":"VIC",
    "wof:name":"Holden Timms Architect",
    "wof:placetype":"venue"
},
  "geometry": {"coordinates":[144.98861694300001,-37.8867797852],"type":"Point"}
}