{
  "type": "Feature",
  "properties": {
    "addr:full":"62 Crown St Wollongong NSW 2500",
    "addr:housenumber":"62",
    "addr:postcode":"2500",
    "addr:street":"Crown St",
    "iso:country":"AU",
    "sg:address":"62 Crown St",
    "sg:city":"Wollongong",
    "sg:classifiers":[
        {
            "category":"Airline",
            "type":"Transportation"
        }
    ],
    "sg:phone":"+61 2 4254 7000",
    "sg:postcode":"2500",
    "sg:province":"NSW",
    "sg:tags":[
        "agent"
    ],
    "wof:name":"Travelworld",
    "wof:placetype":"venue"
},
  "geometry": {"coordinates":[150.89935299999999,-34.425648],"type":"Point"}
}