{
  "type": "Feature",
  "properties": {
    "addr:full":"Lvl 2 51- 53 Spring St Bondi Junction NSW 2022",
    "addr:housenumber":"51 53",
    "addr:postcode":"2022",
    "addr:street":"Spring St",
    "iso:country":"AU",
    "sg:address":"Lvl 2 51- 53 Spring St",
    "sg:city":"Bondi Junction",
    "sg:classifiers":[
        {
            "category":"Health Services",
            "subcategory":"Clinic",
            "type":"Services"
        }
    ],
    "sg:phone":"+61 2 9369 1248",
    "sg:postcode":"2022",
    "sg:province":"NSW",
    "sg:tags":[
        "aromatherapy"
    ],
    "wof:name":"Aromatherapists, International Federation Of",
    "wof:placetype":"venue"
},
  "geometry": {"coordinates":[151.24789428700001,-33.8924484253],"type":"Point"}
}