{
  "type": "Feature",
  "properties": {
    "addr:full":"283 Hannan St Kalgoorlie WA 6430",
    "addr:housenumber":"283",
    "addr:postcode":"6430",
    "addr:street":"Hannan St",
    "iso:country":"AU",
    "sg:address":"283 Hannan St",
    "sg:city":"Kalgoorlie",
    "sg:classifiers":[
        {
            "category":"Education",
            "subcategory":"School",
            "type":"Public Place"
        }
    ],
    "sg:phone":"+61 8 9021 1979",
    "sg:postcode":"6430",
    "sg:province":"WA",
    "sg:tags":[
        "supply"
    ],
    "wof:name":"Boise Office Solutions",
    "wof:placetype":"venue"
},
  "geometry": {"coordinates":[121.46925354,-30.7502384186],"type":"Point"}
}