{
  "type": "Feature",
  "properties": {
    "addr:full":"Talland Dykes Rd Newdegate WA 6355",
    "addr:postcode":"6355",
    "addr:street":"Dykes Rd",
    "iso:country":"AU",
    "sg:address":"Talland Dykes Rd",
    "sg:city":"Newdegate",
    "sg:classifiers":[
        {
            "category":"Farming",
            "subcategory":"Farm",
            "type":"Manufacturing & Wholesale Goods"
        }
    ],
    "sg:phone":"+61 8 9871 9038",
    "sg:postcode":"6355",
    "sg:province":"WA",
    "sg:tags":[
        "farmer"
    ],
    "wof:name":"Dykes W J & E A",
    "wof:placetype":"venue"
},
  "geometry": {"coordinates":[119.023651,-33.093201],"type":"Point"}
}