{
  "type": "Feature",
  "properties": {
    "addr:full":"Shop 2, 1253-1255 Howitt St Ballarat VIC 3350",
    "addr:housenumber":"shop;1253-1255",
    "addr:postcode":"3350",
    "addr:street":"Howitt St",
    "iso:country":"AU",
    "sg:address":"Shop 2, 1253-1255 Howitt St",
    "sg:city":"Ballarat",
    "sg:classifiers":[
        {
            "category":"Shopping",
            "subcategory":"Shoes",
            "type":"Retail Goods"
        }
    ],
    "sg:phone":"+61 3 5339 4219",
    "sg:postcode":"3350",
    "sg:province":"VIC",
    "sg:tags":[
        "footwear"
    ],
    "wof:name":"Pairs",
    "wof:placetype":"venue"
},
  "geometry": {"coordinates":[143.82540900000001,-37.539684],"type":"Point"}
}