{
  "type": "Feature",
  "properties": {
    "addr:full":"174 Rowan St Wangaratta VIC 3677",
    "addr:housenumber":"174",
    "addr:postcode":"3677",
    "addr:street":"Rowan St",
    "iso:country":"AU",
    "sg:address":"174 Rowan St",
    "sg:city":"Wangaratta",
    "sg:classifiers":[
        {
            "category":"Personal",
            "type":"Services"
        }
    ],
    "sg:phone":"+61 3 5722 1981",
    "sg:postcode":"3677",
    "sg:province":"VIC",
    "sg:tags":[
        "reducing",
        "treatment",
        "weight"
    ],
    "wof:name":"Ashbrook Tony",
    "wof:placetype":"venue"
},
  "geometry": {"coordinates":[146.30621337900001,-36.3496322632],"type":"Point"}
}