{
  "type": "Feature",
  "properties": {
    "addr:full":"Shop 1J, Moore Park Supacenta, 2A Todman Ave Kensington NSW 2033",
    "addr:housenumber":"1j;2a",
    "addr:postcode":"2033",
    "addr:street":"Shop;Supacenta;Todman Ave",
    "iso:country":"AU",
    "sg:address":"Shop 1J, Moore Park Supacenta, 2A Todman Ave",
    "sg:city":"Kensington",
    "sg:classifiers":[
        {
            "category":"Manufacturing",
            "subcategory":"Furniture",
            "type":"Manufacturing & Wholesale Goods"
        }
    ],
    "sg:phone":"+61 2 9313 8958",
    "sg:postcode":"2033",
    "sg:province":"NSW",
    "sg:tags":[
        "builder",
        "designer",
        "custom"
    ],
    "wof:name":"Traders Collections",
    "wof:placetype":"venue"
},
  "geometry": {"coordinates":[151.21476699999999,-33.903908],"type":"Point"}
}