{
  "type": "Feature",
  "properties": {
    "addr:full":"567 Springvale Rd Springvale South VIC 3172",
    "addr:housenumber":"567",
    "addr:postcode":"3172",
    "addr:street":"Springvale Rd",
    "iso:country":"AU",
    "sg:address":"567 Springvale Rd",
    "sg:city":"Springvale South",
    "sg:classifiers":[
        {
            "category":"Personal",
            "subcategory":"Beauty Salon",
            "type":"Services"
        }
    ],
    "sg:phone":"+61 3 9547 8767",
    "sg:postcode":"3172",
    "sg:province":"VIC",
    "sg:tags":[
        "hairdresser"
    ],
    "wof:name":"Paduano D",
    "wof:placetype":"venue"
},
  "geometry": {"coordinates":[145.14865112300001,-37.9715614319],"type":"Point"}
}