{
  "type": "Feature",
  "properties": {
    "addr:full":"Unit 6, 29- 33 Amax Ave Girraween NSW 2145",
    "addr:housenumber":"29 33",
    "addr:postcode":"2145",
    "addr:street":"Amax Ave",
    "iso:country":"AU",
    "sg:address":"Unit 6, 29- 33 Amax Ave",
    "sg:city":"Girraween",
    "sg:classifiers":[
        {
            "category":"Utilities",
            "subcategory":"Fuel Oil & Lpg",
            "type":"Services"
        }
    ],
    "sg:phone":"+61 2 9896 6822",
    "sg:postcode":"2145",
    "sg:province":"NSW",
    "sg:tags":[
        "tungsten",
        "product",
        "carbide"
    ],
    "wof:name":"All-Cut Tools Pty Ltd",
    "wof:placetype":"venue"
},
  "geometry": {"coordinates":[150.937866211,-33.8056335449],"type":"Point"}
}