{
  "type": "Feature",
  "properties": {
    "iso:country":"AU",
    "sg:address":"Lvl 11// 50 Clarence St",
    "sg:city":"Sydney",
    "sg:classifiers":[
        {
            "category":"Professional",
            "subcategory":"Employment Agencies",
            "type":"Services"
        }
    ],
    "sg:phone":"+61 2 9994 8088",
    "sg:postcode":"2000",
    "sg:province":"NSW",
    "wof:name":"Forza",
    "wof:placetype":"venue"
},
  "geometry": {"coordinates":[151.207122803,-33.8651199341],"type":"Point"}
}