{
  "type": "Feature",
  "properties": {
    "addr:full":"Unit 4, 6 Commercial Crt Tullamarine VIC 3043",
    "addr:housenumber":"6",
    "addr:postcode":"3043",
    "addr:street":"Commercial Crt",
    "iso:country":"AU",
    "sg:address":"Unit 4, 6 Commercial Crt",
    "sg:city":"Tullamarine",
    "sg:classifiers":[
        {
            "category":"Building & Trades",
            "subcategory":"Equipment Rental",
            "type":"Services"
        }
    ],
    "sg:phone":"+61 3 8318 5900",
    "sg:postcode":"3043",
    "sg:province":"VIC",
    "sg:tags":[
        "supply",
        "catering"
    ],
    "wof:name":"Hobart Food Equipment",
    "wof:placetype":"venue"
},
  "geometry": {"coordinates":[144.857254028,-37.7083625793],"type":"Point"}
}