{
  "type": "Feature",
  "properties": {
    "addr:full":"33 Pasadena St Ramsgate NSW 2217",
    "addr:housenumber":"33",
    "addr:postcode":"2217",
    "addr:street":"Pasadena St",
    "iso:country":"AU",
    "sg:address":"33 Pasadena St",
    "sg:city":"Ramsgate",
    "sg:classifiers":[
        {
            "category":"Building & Trades",
            "subcategory":"Construction",
            "type":"Services"
        }
    ],
    "sg:phone":"+61 2 9588 2110",
    "sg:postcode":"2217",
    "sg:province":"NSW",
    "sg:tags":[
        "contractor"
    ],
    "wof:name":"Parr K V Pty Ltd",
    "wof:placetype":"venue"
},
  "geometry": {"coordinates":[151.14743000000001,-33.976639],"type":"Point"}
}