{
  "type": "Feature",
  "properties": {
    "addr:full":"289 Torrens Rd West Croydon SA 5008",
    "addr:housenumber":"289",
    "addr:postcode":"5008",
    "addr:street":"Torrens Rd",
    "iso:country":"AU",
    "sg:address":"289 Torrens Rd",
    "sg:city":"West Croydon",
    "sg:classifiers":[
        {
            "category":"Health Services",
            "subcategory":"Dentist",
            "type":"Services"
        }
    ],
    "sg:phone":"+61 8 8346 9660",
    "sg:postcode":"5008",
    "sg:province":"SA",
    "wof:name":"Anh&#039;Thu Nguyen",
    "wof:placetype":"venue"
},
  "geometry": {"coordinates":[138.56298799999999,-34.884167],"type":"Point"}
}