{
  "type": "Feature",
  "properties": {
    "addr:full":"22 Bankhead Crs Stafford Heights QLD 4053",
    "addr:housenumber":"22",
    "addr:postcode":"4053",
    "addr:street":"Bankhead Crs",
    "iso:country":"AU",
    "sg:address":"22 Bankhead Crs",
    "sg:city":"Stafford Heights",
    "sg:classifiers":[
        {
            "category":"Social Services",
            "subcategory":"Adult Care",
            "type":"Services"
        }
    ],
    "sg:phone":"+61 410 511 612",
    "sg:postcode":"4053",
    "sg:province":"QLD",
    "sg:tags":[
        "aged"
    ],
    "wof:name":"Mobile Social Welfare Service The",
    "wof:placetype":"venue"
},
  "geometry": {"coordinates":[153.010696411,-27.3950004578],"type":"Point"}
}