{
  "type": "Feature",
  "properties": {
    "addr:full":"360 New Canterbury Rd Dulwich Hill NSW 2203",
    "addr:housenumber":"360",
    "addr:postcode":"2203",
    "addr:street":"New Canterbury Rd",
    "iso:country":"AU",
    "sg:address":"360 New Canterbury Rd",
    "sg:city":"Dulwich Hill",
    "sg:classifiers":[
        {
            "category":"Health Services",
            "subcategory":"Doctor",
            "type":"Services"
        }
    ],
    "sg:phone":"+61 2 9311 3633",
    "sg:postcode":"2203",
    "sg:province":"NSW",
    "sg:tags":[
        "medical",
        "practitioner"
    ],
    "wof:name":"Inner West Medical Practice",
    "wof:placetype":"venue"
},
  "geometry": {"coordinates":[151.13670300000001,-33.905624],"type":"Point"}
}