{
  "type": "Feature",
  "properties": {
    "iso:country":"AU",
    "sg:address":"360 New Canterbury Rd",
    "sg:city":"Dulwich Hill",
    "sg:classifiers":[
        {
            "category":"Health Services",
            "subcategory":"Doctor",
            "type":"Services"
        }
    ],
    "sg:phone":"+61 2 9311 3633",
    "sg:postcode":"2203",
    "sg:province":"NSW",
    "sg:tags":[
        "medical",
        "practitioner"
    ],
    "wof:name":"Inner West Medical Practice",
    "wof:placetype":"venue"
},
  "geometry": {"coordinates":[151.136703,-33.905624],"type":"Point"}
}