{
  "type": "Feature",
  "properties": {
    "iso:country":"AU",
    "sg:address":"&#034;Calandra&#034; Kiama Digby Rd",
    "sg:city":"Digby",
    "sg:classifiers":[
        {
            "category":"Building & Trades",
            "subcategory":"Plumbing",
            "type":"Services"
        }
    ],
    "sg:phone":"+61 3 5579 3210",
    "sg:postcode":"3309",
    "sg:province":"VIC",
    "sg:tags":[
        "plumber",
        "gasfitters"
    ],
    "wof:name":"Goodman J C T",
    "wof:placetype":"venue"
},
  "geometry": {"coordinates":[141.5990448,-37.7869338989],"type":"Point"}
}