{
  "type": "Feature",
  "properties": {
    "addr:full":"111 Lake St Cairns QLD 4870",
    "addr:housenumber":"111",
    "addr:postcode":"4870",
    "addr:street":"Lake St",
    "iso:country":"AU",
    "sg:address":"111 Lake St",
    "sg:city":"Cairns",
    "sg:classifiers":[
        {
            "category":"Shopping",
            "subcategory":"Clothing, Apparel, & Fashions",
            "type":"Retail Goods"
        }
    ],
    "sg:phone":"+61 7 4051 2780",
    "sg:postcode":"4870",
    "sg:province":"QLD",
    "sg:tags":[
        "menswear"
    ],
    "wof:name":"Tom Hulls MansWorld",
    "wof:placetype":"venue"
},
  "geometry": {"coordinates":[145.775146484,-16.9215297699],"type":"Point"}
}