{
  "type": "Feature",
  "properties": {
    "addr:full":"67 Wright St Devonport East TAS 7310",
    "addr:housenumber":"67",
    "addr:postcode":"7310",
    "addr:street":"Wright St",
    "iso:country":"AU",
    "sg:address":"67 Wright St",
    "sg:city":"Devonport East",
    "sg:classifiers":[
        {
            "category":"Food & Beverages",
            "subcategory":"Bakery",
            "type":"Retail Goods"
        }
    ],
    "sg:phone":"+61 3 6427 8706",
    "sg:postcode":"7310",
    "sg:province":"TAS",
    "sg:tags":[
        "cake",
        "shop",
        "pastry"
    ],
    "wof:name":"Perry Bros Bakery",
    "wof:placetype":"venue"
},
  "geometry": {"coordinates":[146.370529175,-41.1795768738],"type":"Point"}
}