{
  "type": "Feature",
  "properties": {
    "iso:country":"AU",
    "sg:address":"307 Concord Rd",
    "sg:city":"Concord",
    "sg:classifiers":[
        {
            "category":"Fast Food",
            "type":"Food & Drink"
        }
    ],
    "sg:phone":"+61 2 9743 6121",
    "sg:postcode":"2137",
    "sg:province":"NSW",
    "sg:tags":[
        "away",
        "take"
    ],
    "wof:name":"KFC",
    "wof:placetype":"venue"
},
  "geometry": {"coordinates":[151.08987426799999,-33.8487625122],"type":"Point"}
}