{
  "type": "Feature",
  "properties": {
    "iso:country":"AU",
    "sg:address":"6 Maitland St",
    "sg:city":"Salisbury",
    "sg:classifiers":[
        {
            "category":"Building & Trades",
            "subcategory":"Plumbing",
            "type":"Services"
        }
    ],
    "sg:phone":"+61 7 3274 3888",
    "sg:postcode":"4107",
    "sg:province":"QLD",
    "sg:tags":[
        "plumber",
        "gasfitters"
    ],
    "wof:name":"Guaranteed Plumbing",
    "wof:placetype":"venue"
},
  "geometry": {"coordinates":[153.03253173799999,-27.5558605194],"type":"Point"}
}