{
  "type": "Feature",
  "properties": {
    "addr:full":"20 Little St Nundah QLD 4012",
    "addr:housenumber":"20",
    "addr:postcode":"4012",
    "addr:street":"Little St",
    "iso:country":"AU",
    "sg:address":"20 Little St",
    "sg:city":"Nundah",
    "sg:classifiers":[
        {
            "category":"Health Services",
            "subcategory":"Doctor",
            "type":"Services"
        }
    ],
    "sg:phone":"+61 7 3262 3290",
    "sg:postcode":"4012",
    "sg:province":"QLD",
    "sg:tags":[
        "podiatrist"
    ],
    "wof:name":"Bannah George Podiatry",
    "wof:placetype":"venue"
},
  "geometry": {"coordinates":[153.060745239,-27.391828537],"type":"Point"}
}