{
  "type": "Feature",
  "properties": {
    "addr:full":"176 Carp St Bega NSW 2550",
    "addr:housenumber":"176",
    "addr:postcode":"2550",
    "addr:street":"Carp St",
    "iso:country":"AU",
    "sg:address":"176 Carp St",
    "sg:city":"Bega",
    "sg:classifiers":[
        {
            "category":"Banks & Credit Unions",
            "subcategory":"Bank",
            "type":"Services"
        }
    ],
    "sg:phone":"+61 13 13 14",
    "sg:postcode":"2550",
    "sg:province":"NSW",
    "wof:name":"ANZ",
    "wof:placetype":"venue"
},
  "geometry": {"coordinates":[149.84379577600001,-36.6742935181],"type":"Point"}
}