{
  "type": "Feature",
  "properties": {
    "addr:full":"PO Box 308 Wauchope NSW 2446",
    "addr:postcode":"2446",
    "iso:country":"AU",
    "sg:address":"PO Box 308",
    "sg:city":"Wauchope",
    "sg:classifiers":[
        {
            "category":"Professional",
            "subcategory":"Art Services",
            "type":"Services"
        }
    ],
    "sg:phone":"+61 2 6585 1658",
    "sg:postcode":"2446",
    "sg:province":"NSW",
    "sg:tags":[
        "decorator",
        "painter"
    ],
    "wof:name":"Leslie B F",
    "wof:placetype":"venue"
},
  "geometry": {"coordinates":[152.737122,-31.456631],"type":"Point"}
}