{
  "type": "Feature",
  "properties": {
    "addr:full":"Shop ML 93 , Bankstown Square Bankstown NSW 2200",
    "addr:housenumber":"93",
    "addr:postcode":"2200",
    "addr:street":"Bankstown Square",
    "iso:country":"AU",
    "sg:address":"Shop ML 93",
    "sg:city":", Bankstown Square Bankstown",
    "sg:classifiers":[
        {
            "category":"Shopping",
            "subcategory":"Clothing, Apparel, & Fashions",
            "type":"Retail Goods"
        }
    ],
    "sg:phone":"+61 2 9790 8488",
    "sg:postcode":"2200",
    "sg:province":"NSW",
    "sg:tags":[
        "maternity",
        "wear"
    ],
    "wof:name":"Pumpkin Patch",
    "wof:placetype":"venue"
},
  "geometry": {"coordinates":[151.012924,-33.9175],"type":"Point"}
}