{
  "type": "Feature",
  "properties": {
    "addr:full":"114 Dunlop St Mortlake VIC 3272",
    "addr:housenumber":"114",
    "addr:postcode":"3272",
    "addr:street":"Dunlop St",
    "iso:country":"AU",
    "sg:address":"114 Dunlop St",
    "sg:city":"Mortlake",
    "sg:classifiers":[
        {
            "category":"Professional",
            "subcategory":"Art Services",
            "type":"Services"
        }
    ],
    "sg:phone":"+61 3 5599 2700",
    "sg:postcode":"3272",
    "sg:province":"VIC",
    "sg:tags":[
        "interior",
        "decorator"
    ],
    "wof:name":"Jamieson & Co Interior Decoration",
    "wof:placetype":"venue"
},
  "geometry": {"coordinates":[142.807006836,-38.0808868408],"type":"Point"}
}