{
  "type": "Feature",
  "properties": {
    "addr:full":"27 Taronga Rd Taroona TAS 7053",
    "addr:housenumber":"27",
    "addr:postcode":"7053",
    "addr:street":"Taronga Rd",
    "iso:country":"AU",
    "sg:address":"27 Taronga Rd",
    "sg:city":"Taroona",
    "sg:classifiers":[
        {
            "category":"Building & Trades",
            "subcategory":"Construction",
            "type":"Services"
        }
    ],
    "sg:phone":"+61 3 6227 9280",
    "sg:postcode":"7053",
    "sg:province":"TAS",
    "sg:tags":[
        "contractor"
    ],
    "wof:name":"Paradigm Construction",
    "wof:placetype":"venue"
},
  "geometry": {"coordinates":[147.338257,-42.962036],"type":"Point"}
}