{
  "type": "Feature",
  "properties": {
    "addr:full":"81 Archer St Woodford QLD 4514",
    "addr:housenumber":"81",
    "addr:postcode":"4514",
    "addr:street":"Archer St",
    "iso:country":"AU",
    "sg:address":"81 Archer St",
    "sg:city":"Woodford",
    "sg:classifiers":[
        {
            "category":"Travel",
            "subcategory":"Hotels & Motels",
            "type":"Entertainment"
        }
    ],
    "sg:phone":"+61 7 5496 1044",
    "sg:postcode":"4514",
    "sg:province":"QLD",
    "sg:tags":[
        "accommodation"
    ],
    "wof:name":"Woodford Hotel/ Motel",
    "wof:placetype":"venue"
},
  "geometry": {"coordinates":[152.777435,-26.952232],"type":"Point"}
}