{
  "type": "Feature",
  "properties": {
    "addr:full":"Moss Vale Industrial Centre Berrima Rd Moss Vale NSW 2577",
    "addr:postcode":"2577",
    "addr:street":"Berrima Rd",
    "iso:country":"AU",
    "sg:address":"Moss Vale Industrial Centre Berrima Rd",
    "sg:city":"Moss Vale",
    "sg:classifiers":[
        {
            "category":"Wholesale",
            "subcategory":"Farm Supplies",
            "type":"Manufacturing & Wholesale Goods"
        }
    ],
    "sg:phone":"+61 2 4869 1720",
    "sg:postcode":"2577",
    "sg:province":"NSW",
    "sg:tags":[
        "feed",
        "supplement",
        "stock"
    ],
    "wof:name":"Knowles Stock Feed & Trading Co",
    "wof:placetype":"venue"
},
  "geometry": {"coordinates":[150.365310669,-34.5466995239],"type":"Point"}
}