{
  "type": "Feature",
  "properties": {
    "addr:full":"76 George St East Fremantle WA 6158",
    "addr:housenumber":"76",
    "addr:postcode":"6158",
    "addr:street":"George St",
    "iso:country":"AU",
    "sg:address":"76 George St",
    "sg:city":"East Fremantle",
    "sg:classifiers":[
        {
            "category":"Health Services",
            "subcategory":"Doctor",
            "type":"Services"
        }
    ],
    "sg:phone":"+61 8 9321 9133",
    "sg:postcode":"6158",
    "sg:province":"WA",
    "sg:tags":[
        "medical",
        "practitioner"
    ],
    "wof:name":"Dow William A C Dr",
    "wof:placetype":"venue"
},
  "geometry": {"coordinates":[115.761353,-32.044243],"type":"Point"}
}