{
  "type": "Feature",
  "properties": {
    "addr:full":"201 Malabar Rd Maroubra NSW 2035",
    "addr:housenumber":"201",
    "addr:postcode":"2035",
    "addr:street":"Malabar Rd",
    "iso:country":"AU",
    "sg:address":"201 Malabar Rd",
    "sg:city":"Maroubra",
    "sg:classifiers":[
        {
            "category":"Professional",
            "subcategory":"Printing & Photocopies",
            "type":"Services"
        }
    ],
    "sg:phone":"+61 2 9344 7800",
    "sg:postcode":"2035",
    "sg:province":"NSW",
    "sg:tags":[
        "screen",
        "printer"
    ],
    "wof:name":"Alfebet Screen Printing",
    "wof:placetype":"venue"
},
  "geometry": {"coordinates":[151.25823974599999,-33.9341583252],"type":"Point"}
}