{
  "type": "Feature",
  "properties": {
    "addr:full":"Level 5 / 150 Edward St Brisbane QLD 4000",
    "addr:housenumber":"/ 150",
    "addr:postcode":"4000",
    "addr:street":"Edward St",
    "iso:country":"AU",
    "sg:address":"Level 5 / 150 Edward St",
    "sg:city":"Brisbane",
    "sg:classifiers":[
        {
            "category":"Insurance",
            "subcategory":"Insurance Agent",
            "type":"Services"
        }
    ],
    "sg:phone":"+61 7 3316 2400",
    "sg:postcode":"4000",
    "sg:province":"QLD",
    "sg:tags":[
        "broker"
    ],
    "wof:name":"EBM Insurance Brokers",
    "wof:placetype":"venue"
},
  "geometry": {"coordinates":[153.027954102,-27.4695606232],"type":"Point"}
}