{
  "type": "Feature",
  "properties": {
    "addr:full":"106 Aldinga Beach Rd Aldinga SA 5173",
    "addr:housenumber":"106",
    "addr:postcode":"5173",
    "addr:street":"Aldinga Beach Rd",
    "iso:country":"AU",
    "sg:address":"106 Aldinga Beach Rd",
    "sg:city":"Aldinga",
    "sg:classifiers":[
        {
            "category":"Retail",
            "subcategory":"Auto Repair",
            "type":"Services"
        }
    ],
    "sg:phone":"+61 8 8557 7167",
    "sg:postcode":"5173",
    "sg:province":"SA",
    "sg:tags":[
        "muffler",
        "exhaust",
        "system"
    ],
    "wof:name":"Carline Mufflers",
    "wof:placetype":"venue"
},
  "geometry": {"coordinates":[138.47529602,-35.2781028748],"type":"Point"}
}