{
  "type": "Feature",
  "properties": {
    "iso:country":"AU",
    "sg:address":"142 Osbourne Pde",
    "sg:city":"Warilla",
    "sg:classifiers":[
        {
            "category":"Health Services",
            "subcategory":"Health Practitioner",
            "type":"Services"
        }
    ],
    "sg:phone":"+61 2 4296 1437",
    "sg:postcode":"2528",
    "sg:province":"NSW",
    "sg:tags":[
        "osteopath"
    ],
    "wof:name":"Wesley Cuthbert",
    "wof:placetype":"venue"
},
  "geometry": {"coordinates":[150.86639404300001,-34.5578117371],"type":"Point"}
}