{
  "type": "Feature",
  "properties": {
    "addr:full":"Level 6, 11 Queens Rd Melbourne VIC 3004",
    "addr:housenumber":"11",
    "addr:postcode":"3004",
    "addr:street":"Queens Rd",
    "iso:country":"AU",
    "sg:address":"Level 6, 11 Queens Rd",
    "sg:city":"Melbourne",
    "sg:classifiers":[
        {
            "category":"Real Estate",
            "subcategory":"Developer",
            "type":"Services"
        }
    ],
    "sg:phone":"+61 3 9820 3288",
    "sg:postcode":"3004",
    "sg:province":"VIC",
    "sg:tags":[
        "chartering",
        "ship",
        "broker"
    ],
    "wof:name":"Stolt-Nielsen Transportation Group Pty Ltd",
    "wof:placetype":"venue"
},
  "geometry": {"coordinates":[144.97398376500001,-37.8380279541],"type":"Point"}
}