{
  "type": "Feature",
  "properties": {
    "addr:full":"PO Box 551 Casino NSW 2470",
    "addr:postcode":"2470",
    "iso:country":"AU",
    "sg:address":"PO Box 551",
    "sg:city":"Casino",
    "sg:classifiers":[
        {
            "category":"Building & Trades",
            "subcategory":"Cleaning & Sanitation",
            "type":"Services"
        }
    ],
    "sg:phone":"+61 2 6662 3019",
    "sg:postcode":"2470",
    "sg:province":"NSW",
    "sg:tags":[
        "industrial",
        "commercial",
        "contractor"
    ],
    "wof:name":"Neways Cleaning Casino",
    "wof:placetype":"venue"
},
  "geometry": {"coordinates":[153.04786682100001,-28.8585395813],"type":"Point"}
}