{
  "type": "Feature",
  "properties": {
    "iso:country":"AU",
    "sg:address":"32 Morton St",
    "sg:city":"Port Macquarie",
    "sg:classifiers":[
        {
            "category":"Health Services",
            "subcategory":"Doctor",
            "type":"Services"
        }
    ],
    "sg:phone":"+61 2 6583 6422",
    "sg:postcode":"2444",
    "sg:province":"NSW",
    "sg:tags":[
        "medical",
        "practitioner"
    ],
    "wof:name":"Williams G",
    "wof:placetype":"venue"
},
  "geometry": {"coordinates":[152.898026,-31.436432],"type":"Point"}
}