{
  "type": "Feature",
  "properties": {
    "iso:country":"AU",
    "sg:address":"120 Malpas Drv",
    "sg:city":"Wallington",
    "sg:classifiers":[
        {
            "category":"Professional",
            "subcategory":"Art Services",
            "type":"Services"
        }
    ],
    "sg:phone":"+61 3 5250 5789",
    "sg:postcode":"3221",
    "sg:province":"VIC",
    "sg:tags":[
        "decorator",
        "painter"
    ],
    "wof:name":"Wallington Painting Services",
    "wof:placetype":"venue"
},
  "geometry": {"coordinates":[144.52633700000001,-38.223553],"type":"Point"}
}