{
  "type": "Feature",
  "properties": {
    "iso:country":"AU",
    "sg:address":"Industrial Rd",
    "sg:city":"Denmark",
    "sg:classifiers":[
        {
            "category":"Communications",
            "type":"Services"
        }
    ],
    "sg:phone":"+61 8 9848 2001",
    "sg:postcode":"6333",
    "sg:province":"WA",
    "sg:tags":[
        "equipment",
        "radio"
    ],
    "wof:name":"Denmark Technical Services",
    "wof:placetype":"venue"
},
  "geometry": {"coordinates":[117.355636597,-34.9674606323],"type":"Point"}
}