{
  "type": "Feature",
  "properties": {
    "iso:country":"AU",
    "sg:address":"63 Sydney Rd",
    "sg:city":"Kelso",
    "sg:classifiers":[
        {
            "category":"Retail",
            "subcategory":"Auto Repair",
            "type":"Services"
        }
    ],
    "sg:phone":"+61 2 6332 5325",
    "sg:postcode":"2795",
    "sg:province":"NSW",
    "sg:tags":[
        "repairer",
        "motor",
        "engineer"
    ],
    "wof:name":"B.P. Kelso Service Station",
    "wof:placetype":"venue"
},
  "geometry": {"coordinates":[149.608352661,-33.4188652039],"type":"Point"}
}