{
  "type": "Feature",
  "properties": {
    "addr:full":"5 Grevillea Gr Goonellabah NSW 2480",
    "addr:housenumber":"5",
    "addr:postcode":"2480",
    "addr:street":"Grevillea Gr",
    "iso:country":"AU",
    "sg:address":"5 Grevillea Gr",
    "sg:city":"Goonellabah",
    "sg:classifiers":[
        {
            "category":"Building & Trades",
            "subcategory":"Construction",
            "type":"Services"
        }
    ],
    "sg:phone":"+61 418 666 375",
    "sg:postcode":"2480",
    "sg:province":"NSW",
    "sg:tags":[
        "renovation",
        "alterations",
        "extension",
        "contractor"
    ],
    "wof:name":"Brian Rogers Builder",
    "wof:placetype":"venue"
},
  "geometry": {"coordinates":[153.307006836,-28.8309059143],"type":"Point"}
}