{
  "type": "Feature",
  "properties": {
    "addr:full":"40 Taunton Drv Bundoora VIC 3083",
    "addr:housenumber":"40",
    "addr:postcode":"3083",
    "addr:street":"Taunton Drv",
    "iso:country":"AU",
    "sg:address":"40 Taunton Drv",
    "sg:city":"Bundoora",
    "sg:classifiers":[
        {
            "category":"Building & Trades",
            "subcategory":"Cleaning & Sanitation",
            "type":"Services"
        }
    ],
    "sg:phone":"+61 400 633 254",
    "sg:postcode":"3083",
    "sg:province":"VIC",
    "sg:tags":[
        "industrial",
        "commercial",
        "contractor"
    ],
    "wof:name":"Zis Cleaning",
    "wof:placetype":"venue"
},
  "geometry": {"coordinates":[145.061447144,-37.6880722046],"type":"Point"}
}