{
  "type": "Feature",
  "properties": {
    "iso:country":"AU",
    "sg:address":"Cnr Wilson & Wilmot Sts",
    "sg:city":"Burnie",
    "sg:classifiers":[
        {
            "category":"Shopping",
            "subcategory":"Mobile Phones",
            "type":"Retail Goods"
        }
    ],
    "sg:phone":"+61 3 6431 9666",
    "sg:postcode":"7320",
    "sg:province":"TAS",
    "sg:tags":[
        "telephone",
        "accessory"
    ],
    "wof:name":"Contel Communications",
    "wof:placetype":"venue"
},
  "geometry": {"coordinates":[145.903503,-41.050591],"type":"Point"}
}