{
  "type": "Feature",
  "properties": {
    "addr:full":"9 Lauriston Reservoir Rd Kyneton VIC 3444",
    "addr:housenumber":"9",
    "addr:postcode":"3444",
    "addr:street":"Lauriston Reservoir Rd",
    "iso:country":"AU",
    "sg:address":"9 Lauriston Reservoir Rd",
    "sg:city":"Kyneton",
    "sg:classifiers":[
        {
            "category":"Professional",
            "type":"Services"
        }
    ],
    "sg:phone":"+61 3 5422 7547",
    "sg:postcode":"3444",
    "sg:province":"VIC",
    "sg:tags":[
        "buyer",
        "merchant",
        "wool"
    ],
    "wof:name":"AAA Wool Buyers Pty Ltd",
    "wof:placetype":"venue"
},
  "geometry": {"coordinates":[144.449752808,-37.2583808899],"type":"Point"}
}