{
  "type": "Feature",
  "properties": {
    "addr:full":"21n Derby St Walcha NSW 2354",
    "addr:housenumber":"21n",
    "addr:postcode":"2354",
    "addr:street":"Derby St",
    "iso:country":"AU",
    "sg:address":"21n Derby St",
    "sg:city":"Walcha",
    "sg:classifiers":[
        {
            "category":"Cafe",
            "type":"Food & Drink"
        }
    ],
    "sg:phone":"+61 2 6777 2409",
    "sg:postcode":"2354",
    "sg:province":"NSW",
    "wof:name":"Cafe Graze",
    "wof:placetype":"venue"
},
  "geometry": {"coordinates":[151.593383789,-30.9843597412],"type":"Point"}
}