{
  "type": "Feature",
  "properties": {
    "iso:country":"AU",
    "sg:address":"134 Margaret St",
    "sg:city":"Toowoomba",
    "sg:classifiers":[
        {
            "category":"Real Estate",
            "subcategory":"Real Estate Agent",
            "type":"Services"
        }
    ],
    "sg:phone":"+61 7 4638 2877",
    "sg:postcode":"4350",
    "sg:province":"QLD",
    "wof:name":"PRD nationwide",
    "wof:placetype":"venue"
},
  "geometry": {"coordinates":[151.954651,-27.561028],"type":"Point"}
}