{
  "type": "Feature",
  "properties": {
    "addr:full":"21a Pottinger St Toowoomba QLD 4350",
    "addr:housenumber":"21a",
    "addr:postcode":"4350",
    "addr:street":"Pottinger St",
    "iso:country":"AU",
    "sg:address":"21a Pottinger St",
    "sg:city":"Toowoomba",
    "sg:classifiers":[
        {
            "category":"Personal",
            "subcategory":"Beauty Salon",
            "type":"Services"
        }
    ],
    "sg:phone":"+61 7 4634 1442",
    "sg:postcode":"4350",
    "sg:province":"QLD",
    "sg:tags":[
        "hairdresser"
    ],
    "wof:name":"Norma Lee Salon",
    "wof:placetype":"venue"
},
  "geometry": {"coordinates":[151.93077099999999,-27.551121],"type":"Point"}
}