{
  "type": "Feature",
  "properties": {
    "addr:full":"179 Boyce Rd Maroubra NSW 2035",
    "addr:housenumber":"179",
    "addr:postcode":"2035",
    "addr:street":"Boyce Rd",
    "iso:country":"AU",
    "sg:address":"179 Boyce Rd",
    "sg:city":"Maroubra",
    "sg:classifiers":[
        {
            "category":"Utilities",
            "subcategory":"Electric",
            "type":"Services"
        }
    ],
    "sg:phone":"+61 415 772 884",
    "sg:postcode":"2035",
    "sg:province":"NSW",
    "sg:tags":[
        "electrical",
        "contractor"
    ],
    "wof:name":"Peter Voigt Electrical",
    "wof:placetype":"venue"
},
  "geometry": {"coordinates":[151.245635986,-33.9410171509],"type":"Point"}
}