{
  "type": "Feature",
  "properties": {
    "addr:full":"25 Poinsettia Ave Mooloolaba QLD 4557",
    "addr:housenumber":"25",
    "addr:postcode":"4557",
    "addr:street":"Poinsettia Ave",
    "iso:country":"AU",
    "sg:address":"25 Poinsettia Ave",
    "sg:city":"Mooloolaba",
    "sg:classifiers":[
        {
            "category":"Food & Beverages",
            "subcategory":"Groceries & Convenience Stores",
            "type":"Retail Goods"
        }
    ],
    "sg:phone":"+61 7 5444 6922",
    "sg:postcode":"4557",
    "sg:province":"QLD",
    "wof:name":"Emerald Woods Convenience Store",
    "wof:placetype":"venue"
},
  "geometry": {"coordinates":[153.10325622600001,-26.6771850586],"type":"Point"}
}