{
  "type": "Feature",
  "properties": {
    "iso:country":"AU",
    "sg:address":"14 Roberts Rd",
    "sg:city":"Hackham West",
    "sg:classifiers":[
        {
            "category":"Health Services",
            "subcategory":"Dentist",
            "type":"Services"
        }
    ],
    "sg:phone":"+61 8 8384 4872",
    "sg:postcode":"5163",
    "sg:province":"SA",
    "wof:name":"Dunstone Stephen Dr",
    "wof:placetype":"venue"
},
  "geometry": {"coordinates":[138.522827148,-35.1414413452],"type":"Point"}
}