{
  "type": "Feature",
  "properties": {
    "iso:country":"AU",
    "sg:address":"7 Peace St",
    "sg:city":"Glen Iris",
    "sg:classifiers":[
        {
            "category":"Personal",
            "type":"Services"
        }
    ],
    "sg:phone":"+61 438 130 155",
    "sg:postcode":"3146",
    "sg:province":"VIC",
    "sg:tags":[
        "dressmaker"
    ],
    "wof:name":"Sutherland Design",
    "wof:placetype":"venue"
},
  "geometry": {"coordinates":[145.06460571299999,-37.8633460999],"type":"Point"}
}