{
  "type": "Feature",
  "properties": {
    "addr:full":"68 Tulloh St Willoughby NSW 2068",
    "addr:housenumber":"68",
    "addr:postcode":"2068",
    "addr:street":"Tulloh St",
    "iso:country":"AU",
    "sg:address":"68 Tulloh St",
    "sg:city":"Willoughby",
    "sg:classifiers":[
        {
            "category":"Organizations",
            "subcategory":"Professional Association",
            "type":"Services"
        }
    ],
    "sg:phone":"+61 2 9967 3922",
    "sg:postcode":"2068",
    "sg:province":"NSW",
    "sg:tags":[
        "organisation",
        "business"
    ],
    "wof:name":"Australian Institute Of Sales, Marketing & Management",
    "wof:placetype":"venue"
},
  "geometry": {"coordinates":[151.200805664,-33.8075790405],"type":"Point"}
}