{
  "type": "Feature",
  "properties": {
    "iso:country":"AU",
    "sg:address":"455 Victoria Ave",
    "sg:city":"Malaga",
    "sg:classifiers":[
        {
            "category":"Shopping",
            "subcategory":"Baby Store",
            "type":"Retail Goods"
        }
    ],
    "sg:phone":"+61 8 6465 1111",
    "sg:postcode":"6090",
    "sg:province":"WA",
    "sg:tags":[
        "skirt",
        "slack"
    ],
    "wof:name":"Perm-A-Pleat Skirts",
    "wof:placetype":"venue"
},
  "geometry": {"coordinates":[115.91030883800001,-31.8614063263],"type":"Point"}
}