{
  "type": "Feature",
  "properties": {
    "addr:full":"14 Alpinia St Sippy Downs QLD 4556",
    "addr:housenumber":"14",
    "addr:postcode":"4556",
    "addr:street":"Alpinia St",
    "iso:country":"AU",
    "sg:address":"14 Alpinia St",
    "sg:city":"Sippy Downs",
    "sg:classifiers":[
        {
            "category":"Building & Trades",
            "subcategory":"Cleaning & Sanitation",
            "type":"Services"
        }
    ],
    "sg:phone":"+61 7 5445 2895",
    "sg:postcode":"4556",
    "sg:province":"QLD",
    "sg:tags":[
        "industrial",
        "commercial",
        "contractor"
    ],
    "wof:name":"Berry N A & K L",
    "wof:placetype":"venue"
},
  "geometry": {"coordinates":[153.05003356899999,-26.7275791168],"type":"Point"}
}