{
  "type": "Feature",
  "properties": {
    "iso:country":"AU",
    "sg:address":"625 Sturt St",
    "sg:city":"Ballarat",
    "sg:classifiers":[
        {
            "category":"Real Estate",
            "subcategory":"Real Estate Agent",
            "type":"Services"
        }
    ],
    "sg:phone":"+61 3 5333 1444",
    "sg:postcode":"3350",
    "sg:province":"VIC",
    "wof:name":"Barry Plant Real Estate",
    "wof:placetype":"venue"
},
  "geometry": {"coordinates":[143.850739,-37.561443],"type":"Point"}
}