{
  "type": "Feature",
  "properties": {
    "addr:full":"266 Lennox St Richmond VIC 3121",
    "addr:housenumber":"266",
    "addr:postcode":"3121",
    "addr:street":"Lennox St",
    "iso:country":"AU",
    "sg:address":"266 Lennox St",
    "sg:city":"Richmond",
    "sg:classifiers":[
        {
            "category":"Communications",
            "type":"Services"
        }
    ],
    "sg:phone":"+61 417 142 717",
    "sg:postcode":"3121",
    "sg:province":"VIC",
    "sg:tags":[
        "translation"
    ],
    "wof:name":"Chris Sardelis NAATI 3",
    "wof:placetype":"venue"
},
  "geometry": {"coordinates":[144.99357605,-37.823009491],"type":"Point"}
}