{
  "type": "Feature",
  "properties": {
    "addr:full":"147 Robinson St North Rockhampton QLD 4701",
    "addr:housenumber":"147",
    "addr:postcode":"4701",
    "addr:street":"Robinson St North",
    "iso:country":"AU",
    "sg:address":"147 Robinson St",
    "sg:city":"North Rockhampton",
    "sg:classifiers":[
        {
            "category":"Sports & Exercise",
            "subcategory":"Gym",
            "type":"Entertainment"
        }
    ],
    "sg:phone":"+61 7 4928 0333",
    "sg:postcode":"4701",
    "sg:province":"QLD",
    "sg:tags":[
        "personal",
        "trainer",
        "fitness"
    ],
    "wof:name":"Bodyshop Health & Fitness",
    "wof:placetype":"venue"
},
  "geometry": {"coordinates":[150.53709411599999,-23.3524303436],"type":"Point"}
}