{
  "type": "Feature",
  "properties": {
    "addr:full":"152 Churchill Ave Braybrook VIC 3019",
    "addr:housenumber":"152",
    "addr:postcode":"3019",
    "addr:street":"Churchill Ave",
    "iso:country":"AU",
    "sg:address":"152 Churchill Ave",
    "sg:city":"Braybrook",
    "sg:classifiers":[
        {
            "category":"Social Services",
            "subcategory":"Child Care",
            "type":"Services"
        }
    ],
    "sg:phone":"+61 3 9364 9622",
    "sg:postcode":"3019",
    "sg:province":"VIC",
    "sg:tags":[
        "support",
        "health"
    ],
    "wof:name":"Maternal & Child Health Centres",
    "wof:placetype":"venue"
},
  "geometry": {"coordinates":[144.85267639200001,-37.7862930298],"type":"Point"}
}