{
  "type": "Feature",
  "properties": {
    "iso:country":"AU",
    "sg:address":"150 St",
    "sg:city":"Georges Tce Perth",
    "sg:classifiers":[
        {
            "category":"Professional",
            "subcategory":"Engineering",
            "type":"Services"
        }
    ],
    "sg:phone":"+61 8 9480 2922",
    "sg:postcode":"6000",
    "sg:province":"WA",
    "sg:tags":[
        "consulting",
        "engineer"
    ],
    "wof:name":"HBH Consultants",
    "wof:placetype":"venue"
},
  "geometry": {"coordinates":[115.855712891,-31.954284668],"type":"Point"}
}