{
  "type": "Feature",
  "properties": {
    "addr:full":"Smiggin Holes Rd Perisher Valley NSW 2624",
    "addr:postcode":"2624",
    "addr:street":"Smiggin Holes Rd",
    "iso:country":"AU",
    "sg:address":"Smiggin Holes Rd",
    "sg:city":"Perisher Valley",
    "sg:classifiers":[
        {
            "category":"Sports & Exercise",
            "subcategory":"Ski Resort",
            "type":"Entertainment"
        }
    ],
    "sg:phone":"+61 2 6457 5341",
    "sg:postcode":"2624",
    "sg:province":"NSW",
    "sg:tags":[
        "tour",
        "centres"
    ],
    "wof:name":"The Lodge",
    "wof:placetype":"venue"
},
  "geometry": {"coordinates":[148.404296875,-36.4098396301],"type":"Point"}
}