{
  "type": "Feature",
  "properties": {
    "iso:country":"AU",
    "sg:address":"226 Melbourne St",
    "sg:city":"North Adelaide",
    "sg:classifiers":[
        {
            "category":"Shopping",
            "subcategory":"Optical Goods",
            "type":"Retail Goods"
        }
    ],
    "sg:phone":"+61 8 8367 0533",
    "sg:postcode":"5006",
    "sg:province":"SA",
    "sg:tags":[
        "supply"
    ],
    "wof:name":"Adelaide Artificial Eye & Body Protheses Clinic - Peter Knowles",
    "wof:placetype":"venue"
},
  "geometry": {"coordinates":[138.60377502399999,-34.908870697],"type":"Point"}
}