{
  "type": "Feature",
  "properties": {
    "addr:full":"21 George St Devonport TAS 7310",
    "addr:housenumber":"21",
    "addr:postcode":"7310",
    "addr:street":"George St",
    "iso:country":"AU",
    "sg:address":"21 George St",
    "sg:city":"Devonport",
    "sg:classifiers":[
        {
            "category":"Building & Trades",
            "subcategory":"Construction",
            "type":"Services"
        }
    ],
    "sg:phone":"+61 3 6423 1081",
    "sg:postcode":"7310",
    "sg:province":"TAS",
    "sg:tags":[
        "contractor"
    ],
    "wof:name":"French R T & A J",
    "wof:placetype":"venue"
},
  "geometry": {"coordinates":[146.359985352,-41.1699295044],"type":"Point"}
}