{
  "type": "Feature",
  "properties": {
    "iso:country":"AU",
    "sg:address":"75a Moore St",
    "sg:city":"Leichhardt",
    "sg:classifiers":[
        {
            "category":"Building & Trades",
            "subcategory":"Landscaping Services",
            "type":"Services"
        }
    ],
    "sg:phone":"+61 411 768 042",
    "sg:postcode":"2040",
    "sg:province":"NSW",
    "sg:tags":[
        "designer",
        "landscape",
        "contractor"
    ],
    "wof:name":"Excell Landscapes",
    "wof:placetype":"venue"
},
  "geometry": {"coordinates":[151.162827,-33.87883],"type":"Point"}
}