{
  "type": "Feature",
  "properties": {
    "addr:full":"9 Market St Kyneton VIC 3444",
    "addr:housenumber":"9",
    "addr:postcode":"3444",
    "addr:street":"Market St",
    "iso:country":"AU",
    "sg:address":"9 Market St",
    "sg:city":"Kyneton",
    "sg:classifiers":[
        {
            "category":"Health Services",
            "subcategory":"Doctor",
            "type":"Services"
        }
    ],
    "sg:phone":"+61 3 5422 1397",
    "sg:postcode":"3444",
    "sg:province":"VIC",
    "sg:tags":[
        "medical",
        "practitioner"
    ],
    "wof:name":"Kyneton Family Medical Practice",
    "wof:placetype":"venue"
},
  "geometry": {"coordinates":[144.45344543499999,-37.2484512329],"type":"Point"}
}