{
  "type": "Feature",
  "properties": {
    "addr:full":"26 Railway St Chatswood NSW 2067",
    "addr:housenumber":"26",
    "addr:postcode":"2067",
    "addr:street":"Railway St",
    "iso:country":"AU",
    "sg:address":"26 Railway St",
    "sg:city":"Chatswood",
    "sg:classifiers":[
        {
            "category":"Personal",
            "subcategory":"Adult",
            "type":"Services"
        }
    ],
    "sg:phone":"+61 2 9419 5590",
    "sg:postcode":"2067",
    "sg:province":"NSW",
    "sg:tags":[
        "vic",
        "except",
        "state",
        "escort",
        "social",
        "qld"
    ],
    "wof:name":"La Petite Aroma",
    "wof:placetype":"venue"
},
  "geometry": {"coordinates":[151.18016052199999,-33.7949485779],"type":"Point"}
}