{
  "type": "Feature",
  "properties": {
    "addr:full":"23 Blaxland Ave Thomastown VIC 3074",
    "addr:housenumber":"23",
    "addr:postcode":"3074",
    "addr:street":"Blaxland Ave",
    "iso:country":"AU",
    "sg:address":"23 Blaxland Ave",
    "sg:city":"Thomastown",
    "sg:classifiers":[
        {
            "category":"Manufacturing",
            "subcategory":"Rubber & Plastics",
            "type":"Manufacturing & Wholesale Goods"
        }
    ],
    "sg:phone":"+61 3 9462 2243",
    "sg:postcode":"3074",
    "sg:province":"VIC",
    "sg:tags":[
        "consultant"
    ],
    "wof:name":"Wanliss Ron Design Pty Ltd",
    "wof:placetype":"venue"
},
  "geometry": {"coordinates":[144.990722656,-37.6895294189],"type":"Point"}
}