{
  "type": "Feature",
  "properties": {
    "addr:full":"19 Croome La Albion Park NSW 2527",
    "addr:housenumber":"19",
    "addr:postcode":"2527",
    "addr:street":"Croome La Albion Park",
    "iso:country":"AU",
    "sg:address":"19 Croome La",
    "sg:city":"Albion Park",
    "sg:classifiers":[
        {
            "category":"Building & Trades",
            "subcategory":"Construction",
            "type":"Services"
        }
    ],
    "sg:phone":"+61 2 4256 1499",
    "sg:postcode":"2527",
    "sg:province":"NSW",
    "sg:tags":[
        "earth",
        "excavating",
        "moving",
        "contractor"
    ],
    "wof:name":"Coastwide Civil Pty Ltd",
    "wof:placetype":"venue"
},
  "geometry": {"coordinates":[150.78306579599999,-34.5534591675],"type":"Point"}
}