{
  "type": "Feature",
  "properties": {
    "addr:full":"20-28 Duncan St Fortitude Valley QLD 4006",
    "addr:housenumber":"20-28",
    "addr:postcode":"4006",
    "addr:street":"Duncan St",
    "iso:country":"AU",
    "sg:address":"20-28 Duncan St",
    "sg:city":"Fortitude Valley",
    "sg:classifiers":[
        {
            "category":"Shopping",
            "subcategory":"Clothing, Apparel, & Fashions",
            "type":"Retail Goods"
        }
    ],
    "sg:phone":"+61 7 3854 0853",
    "sg:postcode":"4006",
    "sg:province":"QLD",
    "sg:tags":[
        "lady",
        "wear"
    ],
    "wof:name":"Paradiso Pty Ltd",
    "wof:placetype":"venue"
},
  "geometry": {"coordinates":[153.033966064,-27.4585838318],"type":"Point"}
}