{
  "type": "Feature",
  "properties": {
    "iso:country":"AU",
    "sg:address":"44 Milleara Rd",
    "sg:city":"Keilor East",
    "sg:classifiers":[
        {
            "category":"Health Services",
            "subcategory":"Health Practitioner",
            "type":"Services"
        }
    ],
    "sg:phone":"+61 3 9331 5555",
    "sg:postcode":"3033",
    "sg:province":"VIC",
    "sg:tags":[
        "psychotherapist"
    ],
    "wof:name":"Helen Kontogiannis",
    "wof:placetype":"venue"
},
  "geometry": {"coordinates":[144.865356,-37.732471],"type":"Point"}
}