{
  "type": "Feature",
  "properties": {
    "addr:full":"15 Welkin St Windsor Gardens SA 5087",
    "addr:housenumber":"15",
    "addr:postcode":"5087",
    "addr:street":"Welkin St",
    "iso:country":"AU",
    "sg:address":"15 Welkin St",
    "sg:city":"Windsor Gardens",
    "sg:classifiers":[
        {
            "category":"Retail",
            "subcategory":"Auto Repair",
            "type":"Services"
        }
    ],
    "sg:phone":"+61 8 8266 4361",
    "sg:postcode":"5087",
    "sg:province":"SA",
    "sg:tags":[
        "repairer",
        "motor",
        "engineer"
    ],
    "wof:name":"Apaza Mobile Skills",
    "wof:placetype":"venue"
},
  "geometry": {"coordinates":[138.655319214,-34.8584594727],"type":"Point"}
}