{
  "type": "Feature",
  "properties": {
    "addr:full":"82 Stanley St Wyongah NSW 2259",
    "addr:housenumber":"82",
    "addr:postcode":"2259",
    "addr:street":"Stanley St",
    "iso:country":"AU",
    "sg:address":"82 Stanley St",
    "sg:city":"Wyongah",
    "sg:classifiers":[
        {
            "category":"Building & Trades",
            "subcategory":"Construction",
            "type":"Services"
        }
    ],
    "sg:phone":"+61 2 4393 2250",
    "sg:postcode":"2259",
    "sg:province":"NSW",
    "sg:tags":[
        "earth",
        "excavating",
        "moving",
        "contractor"
    ],
    "wof:name":"Sammons P. J. & J. A.",
    "wof:placetype":"venue"
},
  "geometry": {"coordinates":[151.48971557600001,-33.2733306885],"type":"Point"}
}