{
  "type": "Feature",
  "properties": {
    "iso:country":"AU",
    "sg:address":"7 Horscroft Pl",
    "sg:city":"Moorabbin",
    "sg:classifiers":[
        {
            "category":"Building & Trades",
            "subcategory":"Construction",
            "type":"Services"
        }
    ],
    "sg:phone":"+61 3 9532 5755",
    "sg:postcode":"3189",
    "sg:province":"VIC",
    "sg:tags":[
        "window",
        "timber"
    ],
    "wof:name":"Jones Joinery",
    "wof:placetype":"venue"
},
  "geometry": {"coordinates":[145.0418396,-37.9357032776],"type":"Point"}
}