{
  "type": "Feature",
  "properties": {
    "addr:full":"177 Warburton Hwy Lilydale VIC 3140",
    "addr:housenumber":"177",
    "addr:postcode":"3140",
    "addr:street":"Warburton Hwy",
    "iso:country":"AU",
    "sg:address":"177 Warburton Hwy",
    "sg:city":"Lilydale",
    "sg:classifiers":[
        {
            "category":"Building & Trades",
            "subcategory":"Construction",
            "type":"Services"
        }
    ],
    "sg:phone":"+61 427 518 528",
    "sg:postcode":"3140",
    "sg:province":"VIC",
    "sg:tags":[
        "concrete",
        "paving"
    ],
    "wof:name":"Lilydale Constructions Pty Ltd",
    "wof:placetype":"venue"
},
  "geometry": {"coordinates":[145.403533936,-37.7660064697],"type":"Point"}
}