{
  "type": "Feature",
  "properties": {
    "addr:full":"9 Canterbury Ave Sunbury VIC 3429",
    "addr:housenumber":"9",
    "addr:postcode":"3429",
    "addr:street":"Canterbury Ave",
    "iso:country":"AU",
    "sg:address":"9 Canterbury Ave",
    "sg:city":"Sunbury",
    "sg:classifiers":[
        {
            "category":"Real Estate",
            "subcategory":"Developer",
            "type":"Services"
        }
    ],
    "sg:phone":"+61 3 9740 3721",
    "sg:postcode":"3429",
    "sg:province":"VIC",
    "sg:tags":[
        "development"
    ],
    "wof:name":"Canterbury Hills",
    "wof:placetype":"venue"
},
  "geometry": {"coordinates":[144.71078491200001,-37.5587120056],"type":"Point"}
}