{
  "type": "Feature",
  "properties": {
    "addr:full":"Industrial Area 2 Iraci Crs Weipa QLD 4874",
    "addr:housenumber":"2",
    "addr:postcode":"4874",
    "addr:street":"Industrial Area;Iraci Crs",
    "iso:country":"AU",
    "sg:address":"Industrial Area 2 Iraci Crs",
    "sg:city":"Weipa",
    "sg:classifiers":[
        {
            "category":"Home & Garden",
            "subcategory":"Hardware",
            "type":"Retail Goods"
        }
    ],
    "sg:phone":"+61 7 4069 7486",
    "sg:postcode":"4874",
    "sg:province":"QLD",
    "sg:tags":[
        "plumber",
        "supply"
    ],
    "wof:name":"Weipa Hardware",
    "wof:placetype":"venue"
},
  "geometry": {"coordinates":[141.87167358400001,-12.6334495544],"type":"Point"}
}