{
  "type": "Feature",
  "properties": {
    "iso:country":"AU",
    "sg:address":"30 King St",
    "sg:city":"Buderim",
    "sg:classifiers":[
        {
            "category":"Health Services",
            "subcategory":"Health Practitioner",
            "type":"Services"
        }
    ],
    "sg:phone":"+61 7 5445 3055",
    "sg:postcode":"4556",
    "sg:province":"QLD",
    "sg:tags":[
        "naturopath"
    ],
    "wof:name":"Dunmow Josephine",
    "wof:placetype":"venue"
},
  "geometry": {"coordinates":[153.058303833,-26.6832046509],"type":"Point"}
}