{
  "type": "Feature",
  "properties": {
    "iso:country":"AU",
    "sg:address":"25 Phillipson St",
    "sg:city":"Wangaratta",
    "sg:classifiers":[
        {
            "category":"Building & Trades",
            "subcategory":"Construction",
            "type":"Services"
        }
    ],
    "sg:phone":"+61 409 796 610",
    "sg:postcode":"3677",
    "sg:province":"VIC",
    "sg:tags":[
        "home",
        "air conditioning"
    ],
    "wof:name":"Frazer Air Conditioning",
    "wof:placetype":"venue"
},
  "geometry": {"coordinates":[146.30421447800001,-36.3568725586],"type":"Point"}
}