{
  "type": "Feature",
  "properties": {
    "iso:country":"AU",
    "sg:address":"274 Dawson St",
    "sg:city":"Sale",
    "sg:classifiers":[
        {
            "category":"Food & Beverages",
            "subcategory":"Liquor & Beverages",
            "type":"Retail Goods"
        }
    ],
    "sg:phone":"+61 3 5144 4185",
    "sg:postcode":"3850",
    "sg:province":"VIC",
    "sg:tags":[
        "store"
    ],
    "wof:name":"Dawson Street Liquor & Food Mart",
    "wof:placetype":"venue"
},
  "geometry": {"coordinates":[147.08468627900001,-38.0956344604],"type":"Point"}
}