{
  "type": "Feature",
  "properties": {
    "iso:country":"AU",
    "sg:address":"116 Cockman Rd",
    "sg:city":"Kingsley",
    "sg:classifiers":[
        {
            "category":"Health Services",
            "subcategory":"Health Practitioner",
            "type":"Services"
        }
    ],
    "sg:phone":"+61 8 9342 7111",
    "sg:postcode":"6026",
    "sg:province":"WA",
    "sg:tags":[
        "dietitian"
    ],
    "wof:name":"Smith Helen",
    "wof:placetype":"venue"
},
  "geometry": {"coordinates":[115.81549835200001,-31.8217544556],"type":"Point"}
}