{
  "type": "Feature",
  "properties": {
    "iso:country":"AU",
    "sg:address":"1100 Burwood Hwy",
    "sg:city":"Ferntree Gully",
    "sg:classifiers":[
        {
            "category":"Autos & Motor Vehicles",
            "subcategory":"Automobile Sales",
            "type":"Retail Goods"
        }
    ],
    "sg:phone":"+61 3 9752 4188",
    "sg:postcode":"3156",
    "sg:province":"VIC",
    "sg:tags":[
        "car",
        "used"
    ],
    "wof:name":"Spot On Windscreen Bannor Fasting Systems",
    "wof:placetype":"venue"
},
  "geometry": {"coordinates":[145.295974731,-37.8887176514],"type":"Point"}
}