{
  "type": "Feature",
  "properties": {
    "addr:full":"Marine Pde Labrador QLD 4215",
    "addr:postcode":"4215",
    "addr:street":"Marine",
    "iso:country":"AU",
    "sg:address":"Marine Pde",
    "sg:city":"Labrador",
    "sg:classifiers":[
        {
            "category":"Travel",
            "subcategory":"Travel Agent",
            "type":"Entertainment"
        }
    ],
    "sg:phone":"+61 412 940 135",
    "sg:postcode":"4215",
    "sg:province":"QLD",
    "sg:tags":[
        "tour",
        "holiday",
        "adventure"
    ],
    "wof:name":"Australian Kayaking Adventures",
    "wof:placetype":"venue"
},
  "geometry": {"coordinates":[153.40989685100001,-27.9477653503],"type":"Point"}
}