{
  "type": "Feature",
  "properties": {
    "addr:full":"Unit 4/ 6B Baretta Rd Wangara WA 6065",
    "addr:housenumber":"/ 6b",
    "addr:postcode":"6065",
    "addr:street":"Baretta Rd",
    "iso:country":"AU",
    "sg:address":"Unit 4/ 6B Baretta Rd",
    "sg:city":"Wangara",
    "sg:classifiers":[
        {
            "category":"Retail",
            "subcategory":"Auto Repair",
            "type":"Services"
        }
    ],
    "sg:phone":"+61 8 9408 1030",
    "sg:postcode":"6065",
    "sg:province":"WA",
    "sg:tags":[
        "repairer",
        "motor",
        "engineer"
    ],
    "wof:name":"Automotive Addiction",
    "wof:placetype":"venue"
},
  "geometry": {"coordinates":[115.816879273,-31.7922401428],"type":"Point"}
}