{
  "type": "Feature",
  "properties": {
    "addr:full":"Lot 213 Marri Pl Gelorup WA 6230",
    "addr:postcode":"6230",
    "addr:street":"Marri Pl Gelorup",
    "iso:country":"AU",
    "sg:address":"Lot 213 Marri Pl",
    "sg:city":"Gelorup",
    "sg:classifiers":[
        {
            "category":"Building & Trades",
            "subcategory":"Cleaning & Sanitation",
            "type":"Services"
        }
    ],
    "sg:phone":"+61 417 904 337",
    "sg:postcode":"6230",
    "sg:province":"WA",
    "sg:tags":[
        "window"
    ],
    "wof:name":"Winkleen",
    "wof:placetype":"venue"
},
  "geometry": {"coordinates":[115.631439,-33.434338],"type":"Point"}
}