{
  "type": "Feature",
  "properties": {
    "addr:full":"Flinders Hwy Charters Towers QLD 4820",
    "addr:postcode":"4820",
    "addr:street":"Flinders Hwy",
    "iso:country":"AU",
    "sg:address":"Flinders Hwy",
    "sg:city":"Charters Towers",
    "sg:classifiers":[
        {
            "category":"Commercial Area",
            "type":"Public Place"
        }
    ],
    "sg:phone":"+61 417 637 556",
    "sg:postcode":"4820",
    "sg:province":"QLD",
    "sg:tags":[
        "heavy",
        "carrier"
    ],
    "wof:name":"Reiffels Transport",
    "wof:placetype":"venue"
},
  "geometry": {"coordinates":[146.24816899999999,-20.101198],"type":"Point"}
}