{
  "type": "Feature",
  "properties": {
    "addr:full":"12 View St Concord NSW 2137",
    "addr:housenumber":"12",
    "addr:postcode":"2137",
    "addr:street":"View St",
    "iso:country":"AU",
    "sg:address":"12 View St",
    "sg:city":"Concord",
    "sg:classifiers":[
        {
            "category":"Building & Trades",
            "subcategory":"Construction",
            "type":"Services"
        }
    ],
    "sg:phone":"+61 2 9743 6665",
    "sg:postcode":"2137",
    "sg:province":"NSW",
    "sg:tags":[
        "contractor"
    ],
    "wof:name":"Manthon Building Services Pty Ltd",
    "wof:placetype":"venue"
},
  "geometry": {"coordinates":[151.111160278,-33.8556785583],"type":"Point"}
}