{
  "type": "Feature",
  "properties": {
    "addr:full":"24- 28 Morewell St Dandenong VIC 3175",
    "addr:housenumber":"28",
    "addr:postcode":"3175",
    "addr:street":"Morewell St",
    "iso:country":"AU",
    "sg:address":"24- 28 Morewell St",
    "sg:city":"Dandenong",
    "sg:classifiers":[
        {
            "category":"Travel",
            "subcategory":"Hostel",
            "type":"Entertainment"
        }
    ],
    "sg:phone":"+61 3 9791 2304",
    "sg:postcode":"3175",
    "sg:province":"VIC",
    "sg:tags":[
        "home"
    ],
    "wof:name":"Russian Home For The Aged",
    "wof:placetype":"venue"
},
  "geometry": {"coordinates":[145.20375060999999,-37.9969406128],"type":"Point"}
}