{
  "type": "Feature",
  "properties": {
    "addr:full":"1 Dingley Ave Dandenong VIC 3175",
    "addr:housenumber":"1",
    "addr:postcode":"3175",
    "addr:street":"Dingley Ave",
    "iso:country":"AU",
    "sg:address":"1 Dingley Ave",
    "sg:city":"Dandenong",
    "sg:classifiers":[
        {
            "category":"Retail",
            "subcategory":"Auto Repair",
            "type":"Services"
        }
    ],
    "sg:phone":"+61 3 9793 3688",
    "sg:postcode":"3175",
    "sg:province":"VIC",
    "sg:tags":[
        "beater",
        "painter",
        "panel"
    ],
    "wof:name":"Super Star Accident Repair Centre",
    "wof:placetype":"venue"
},
  "geometry": {"coordinates":[145.19631957999999,-37.9921913147],"type":"Point"}
}