{
  "type": "Feature",
  "properties": {
    "iso:country":"AU",
    "sg:address":"405 Tarakan Ave",
    "sg:city":"Albury North",
    "sg:classifiers":[
        {
            "category":"Education",
            "subcategory":"Kindergarten",
            "type":"Public Place"
        }
    ],
    "sg:phone":"+61 2 6025 1282",
    "sg:postcode":"2640",
    "sg:province":"NSW",
    "sg:tags":[
        "pre-schools"
    ],
    "wof:name":"Moresby Park Pre-School",
    "wof:placetype":"venue"
},
  "geometry": {"coordinates":[146.92962646500001,-36.0531082153],"type":"Point"}
}