{
  "type": "Feature",
  "properties": {
    "addr:full":"70- 74 Eastern Rd Traralgon VIC 3844",
    "addr:housenumber":"74",
    "addr:postcode":"3844",
    "addr:street":"Eastern Rd",
    "iso:country":"AU",
    "sg:address":"70- 74 Eastern Rd",
    "sg:city":"Traralgon",
    "sg:classifiers":[
        {
            "category":"Utilities",
            "subcategory":"Refuse",
            "type":"Services"
        }
    ],
    "sg:phone":"+61 3 5175 0144",
    "sg:postcode":"3844",
    "sg:province":"VIC",
    "sg:tags":[
        "disposal",
        "reduction",
        "waste"
    ],
    "wof:name":"Latrobe Valley Recyclers Pty Ltd",
    "wof:placetype":"venue"
},
  "geometry": {"coordinates":[146.56553649899999,-38.1805915833],"type":"Point"}
}