{
  "type": "Feature",
  "properties": {
    "iso:country":"AU",
    "sg:address":"801 Howitt St",
    "sg:city":"Wendouree",
    "sg:classifiers":[
        {
            "category":"Home & Garden",
            "subcategory":"Building Materials",
            "type":"Retail Goods"
        }
    ],
    "sg:phone":"+61 3 5339 5033",
    "sg:postcode":"3355",
    "sg:province":"VIC",
    "sg:tags":[
        "fitting",
        "door"
    ],
    "wof:name":"G. Gay & Co",
    "wof:placetype":"venue"
},
  "geometry": {"coordinates":[143.84848,-37.542423],"type":"Point"}
}