{
  "type": "Feature",
  "properties": {
    "addr:full":"9 Burgan St Doreen VIC 3754",
    "addr:housenumber":"9",
    "addr:postcode":"3754",
    "addr:street":"Burgan St",
    "iso:country":"AU",
    "sg:address":"9 Burgan St",
    "sg:city":"Doreen",
    "sg:classifiers":[
        {
            "category":"Retail",
            "subcategory":"Repair Shop",
            "type":"Services"
        }
    ],
    "sg:phone":"+61 3 9717 3141",
    "sg:postcode":"3754",
    "sg:province":"VIC",
    "sg:tags":[
        "machine",
        "sewing"
    ],
    "wof:name":"Statewide Sewing Centres",
    "wof:placetype":"venue"
},
  "geometry": {"coordinates":[145.13850400000001,-37.589539],"type":"Point"}
}