{
  "type": "Feature",
  "properties": {
    "iso:country":"AU",
    "sg:address":"22 Warilda Ave",
    "sg:city":"Engadine",
    "sg:classifiers":[
        {
            "category":"Wholesale",
            "subcategory":"Electrical",
            "type":"Manufacturing & Wholesale Goods"
        }
    ],
    "sg:phone":"+61 2 9520 9818",
    "sg:postcode":"2233",
    "sg:province":"NSW",
    "sg:tags":[
        "wholesaler",
        "mfrs",
        "accessory"
    ],
    "wof:name":"Sydney Connect Pty Ltd",
    "wof:placetype":"venue"
},
  "geometry": {"coordinates":[151.02337646500001,-34.0484542847],"type":"Point"}
}