{
  "type": "Feature",
  "properties": {
    "addr:full":"Lot 443 Sale Maffra Rd Bundalaguah VIC 3851",
    "addr:postcode":"3851",
    "addr:street":"Maffra Rd",
    "iso:country":"AU",
    "sg:address":"Lot 443 Sale Maffra Rd",
    "sg:city":"Bundalaguah",
    "sg:classifiers":[
        {
            "category":"Wholesale",
            "subcategory":"Machinery & Supplies",
            "type":"Manufacturing & Wholesale Goods"
        }
    ],
    "sg:phone":"+61 3 5147 1857",
    "sg:postcode":"3851",
    "sg:province":"VIC",
    "sg:tags":[
        "agricultural"
    ],
    "wof:name":"Maple Diesel Engineering",
    "wof:placetype":"venue"
},
  "geometry": {"coordinates":[147.216033936,-38.3536987305],"type":"Point"}
}