{
  "type": "Feature",
  "properties": {
    "iso:country":"AU",
    "sg:address":"320 Argent St",
    "sg:city":"Broken Hill",
    "sg:classifiers":[
        {
            "category":"Insurance",
            "subcategory":"Hazard Insurance",
            "type":"Services"
        }
    ],
    "sg:phone":"+61 8 8088 4999",
    "sg:postcode":"2880",
    "sg:province":"NSW",
    "sg:tags":[
        "motor",
        "vehicle"
    ],
    "wof:name":"RAA Insurance Ltd",
    "wof:placetype":"venue"
},
  "geometry": {"coordinates":[141.464553833,-31.9590606689],"type":"Point"}
}