{
  "type": "Feature",
  "properties": {
    "addr:full":"112- 120 Main Rd East St Albans VIC 3021",
    "addr:housenumber":"120",
    "addr:postcode":"3021",
    "addr:street":"Main Rd East",
    "iso:country":"AU",
    "sg:address":"112- 120 Main Rd East St",
    "sg:city":"Albans",
    "sg:classifiers":[
        {
            "category":"Autos & Motor Vehicles",
            "subcategory":"Fuel & Gas Station",
            "type":"Retail Goods"
        }
    ],
    "sg:phone":"+61 3 9364 2809",
    "sg:postcode":"3021",
    "sg:province":"VIC",
    "wof:name":"BP Australia Pty Ltd",
    "wof:placetype":"venue"
},
  "geometry": {"coordinates":[144.820908,-37.746578],"type":"Point"}
}