{
  "type": "Feature",
  "properties": {
    "addr:full":"55 cavendish St Stanmore NSW 2048",
    "addr:housenumber":"55",
    "addr:postcode":"2048",
    "addr:street":"Cavendish St",
    "iso:country":"AU",
    "sg:address":"55 cavendish St",
    "sg:city":"Stanmore",
    "sg:classifiers":[
        {
            "category":"Building & Trades",
            "subcategory":"Construction",
            "type":"Services"
        }
    ],
    "sg:phone":"+61 411 511 661",
    "sg:postcode":"2048",
    "sg:province":"NSW",
    "sg:tags":[
        "rendering",
        "cement"
    ],
    "wof:name":"Able Render Set",
    "wof:placetype":"venue"
},
  "geometry": {"coordinates":[151.168869,-33.897675],"type":"Point"}
}