{
  "type": "Feature",
  "properties": {
    "addr:full":"Cairns Harbour Redbank Rd Gordonvale QLD 4865",
    "addr:postcode":"4865",
    "addr:street":"Redbank Rd",
    "iso:country":"AU",
    "sg:address":"Cairns Harbour Redbank Rd",
    "sg:city":"Gordonvale",
    "sg:classifiers":[
        {
            "category":"Military Area",
            "subcategory":"Air Force Base",
            "type":"Public Place"
        }
    ],
    "sg:phone":"+61 7 4056 5527",
    "sg:postcode":"4865",
    "sg:province":"QLD",
    "sg:tags":[
        "adjuster",
        "compass"
    ],
    "wof:name":"Captain Bob Moss",
    "wof:placetype":"venue"
},
  "geometry": {"coordinates":[145.793136597,-17.0432796478],"type":"Point"}
}