{
  "type": "Feature",
  "properties": {
    "addr:full":"Forrest St Pinjarra WA 6208",
    "addr:postcode":"6208",
    "addr:street":"Forrest St",
    "iso:country":"AU",
    "sg:address":"Forrest St",
    "sg:city":"Pinjarra",
    "sg:classifiers":[
        {
            "category":"Health Services",
            "subcategory":"Doctor",
            "type":"Services"
        }
    ],
    "sg:phone":"+61 8 9531 1866",
    "sg:postcode":"6208",
    "sg:province":"WA",
    "sg:tags":[
        "medical",
        "practitioner"
    ],
    "wof:name":"Handorf M Dr",
    "wof:placetype":"venue"
},
  "geometry": {"coordinates":[115.874031,-32.625031],"type":"Point"}
}