{
  "type": "Feature",
  "properties": {
    "addr:full":"238 Flinders La Melbourne VIC 3000",
    "addr:housenumber":"238",
    "addr:postcode":"3000",
    "addr:street":"Flinders La",
    "iso:country":"AU",
    "sg:address":"238 Flinders La",
    "sg:city":"Melbourne",
    "sg:classifiers":[
        {
            "category":"Shopping",
            "subcategory":"Luggage & Leather Goods",
            "type":"Retail Goods"
        }
    ],
    "sg:phone":"+61 3 9650 7509",
    "sg:postcode":"3000",
    "sg:province":"VIC",
    "sg:tags":[
        "reconditioning"
    ],
    "wof:name":"Stubbs Garry K",
    "wof:placetype":"venue"
},
  "geometry": {"coordinates":[144.96600341800001,-37.8166313171],"type":"Point"}
}