{
  "type": "Feature",
  "properties": {
    "iso:country":"AU",
    "sg:address":"98 Rupert St",
    "sg:city":"Bairnsdale",
    "sg:classifiers":[
        {
            "category":"Retail",
            "subcategory":"Auto Repair",
            "type":"Services"
        }
    ],
    "sg:phone":"+61 3 5152 5347",
    "sg:postcode":"3875",
    "sg:province":"VIC",
    "sg:tags":[
        "beater",
        "painter",
        "panel"
    ],
    "wof:name":"Saxtons Panel Works",
    "wof:placetype":"venue"
},
  "geometry": {"coordinates":[147.62071227999999,-37.8319511414],"type":"Point"}
}