{
  "type": "Feature",
  "properties": {
    "addr:full":"Unit 13, 10 Burnside Rd Yatala QLD 4207",
    "addr:housenumber":"10",
    "addr:postcode":"4207",
    "addr:street":"Burnside Rd",
    "iso:country":"AU",
    "sg:address":"Unit 13, 10 Burnside Rd",
    "sg:city":"Yatala",
    "sg:classifiers":[
        {
            "category":"Home & Garden",
            "subcategory":"Home Furnishings",
            "type":"Retail Goods"
        }
    ],
    "sg:phone":"+61 7 3807 2018",
    "sg:postcode":"4207",
    "sg:province":"QLD",
    "sg:tags":[
        "shower",
        "screen"
    ],
    "wof:name":"Civic Shower Screens & Wardrobes",
    "wof:placetype":"venue"
},
  "geometry": {"coordinates":[153.24009704599999,-27.7555389404],"type":"Point"}
}