{
  "type": "Feature",
  "properties": {
    "addr:full":"Fcty 2/ 12 Norton Drv Melton VIC 3337",
    "addr:housenumber":"/ 12",
    "addr:postcode":"3337",
    "addr:street":"Norton Drv",
    "iso:country":"AU",
    "sg:address":"Fcty 2/ 12 Norton Drv",
    "sg:city":"Melton",
    "sg:classifiers":[
        {
            "category":"Retail",
            "subcategory":"Auto Repair",
            "type":"Services"
        }
    ],
    "sg:phone":"+61 3 9743 1548",
    "sg:postcode":"3337",
    "sg:province":"VIC",
    "sg:tags":[
        "repairer",
        "motor",
        "engineer"
    ],
    "wof:name":"Thoroughbred Automotive",
    "wof:placetype":"venue"
},
  "geometry": {"coordinates":[144.60174599999999,-37.69136],"type":"Point"}
}