{
  "type": "Feature",
  "properties": {
    "iso:country":"AU",
    "sg:address":"41- 45 Albert St",
    "sg:city":"Moe",
    "sg:classifiers":[
        {
            "category":"Health Services",
            "subcategory":"Dentist",
            "type":"Services"
        }
    ],
    "sg:phone":"+61 3 5127 1866",
    "sg:postcode":"3825",
    "sg:province":"VIC",
    "sg:tags":[
        "technician",
        "dental"
    ],
    "wof:name":"White Michael",
    "wof:placetype":"venue"
},
  "geometry": {"coordinates":[146.264114,-38.175007],"type":"Point"}
}