{
  "type": "Feature",
  "properties": {
    "addr:full":"53 Dacre St Mitchell ACT 2911",
    "addr:housenumber":"53",
    "addr:postcode":"2911",
    "addr:street":"Dacre St",
    "iso:country":"AU",
    "sg:address":"53 Dacre St",
    "sg:city":"Mitchell",
    "sg:classifiers":[
        {
            "category":"Retail",
            "subcategory":"Storage",
            "type":"Services"
        }
    ],
    "sg:phone":"+61 2 6242 0092",
    "sg:postcode":"2911",
    "sg:province":"ACT",
    "wof:name":"Capital Self Storage",
    "wof:placetype":"venue"
},
  "geometry": {"coordinates":[149.13705444300001,-35.2121620178],"type":"Point"}
}