{
  "type": "Feature",
  "properties": {
    "iso:country":"AU",
    "sg:address":"Backhouse La",
    "sg:city":"Cambridge",
    "sg:classifiers":[
        {
            "category":"Farming",
            "subcategory":"Fish & Marine Products",
            "type":"Manufacturing & Wholesale Goods"
        }
    ],
    "sg:phone":"+61 3 6248 5378",
    "sg:postcode":"7170",
    "sg:province":"TAS",
    "sg:tags":[
        "supplier",
        "oyster",
        "farmer"
    ],
    "wof:name":"Tasmanian Pitt Water Oysters Pty Ltd",
    "wof:placetype":"venue"
},
  "geometry": {"coordinates":[147.459518433,-42.8298912048],"type":"Point"}
}