{
  "type": "Feature",
  "properties": {
    "addr:full":"325 Clovelly Rd Clovelly NSW 2031",
    "addr:housenumber":"325",
    "addr:postcode":"2031",
    "addr:street":"Clovelly Rd",
    "iso:country":"AU",
    "sg:address":"325 Clovelly Rd",
    "sg:city":"Clovelly",
    "sg:classifiers":[
        {
            "category":"Personal",
            "subcategory":"Beauty Salon",
            "type":"Services"
        }
    ],
    "sg:phone":"+61 2 9664 8084",
    "sg:postcode":"2031",
    "sg:province":"NSW",
    "sg:tags":[
        "hairdresser"
    ],
    "wof:name":"Temple Of Hair",
    "wof:placetype":"venue"
},
  "geometry": {"coordinates":[151.259033203,-33.912109375],"type":"Point"}
}