{
  "type": "Feature",
  "properties": {
    "iso:country":"AU",
    "sg:address":"68 Clarke St",
    "sg:city":"South Melbourne",
    "sg:classifiers":[
        {
            "category":"Building & Trades",
            "subcategory":"Construction",
            "type":"Services"
        }
    ],
    "sg:phone":"+61 3 9696 2522",
    "sg:postcode":"3205",
    "sg:province":"VIC",
    "sg:tags":[
        "contractor"
    ],
    "wof:name":"Stonehenge Group",
    "wof:placetype":"venue"
},
  "geometry": {"coordinates":[144.960022,-37.829094],"type":"Point"}
}