{
  "type": "Feature",
  "properties": {
    "iso:country":"AU",
    "sg:address":"24 Chisholm Cr",
    "sg:city":"Kewdale",
    "sg:classifiers":[
        {
            "category":"Utilities",
            "subcategory":"Recycling",
            "type":"Services"
        }
    ],
    "sg:phone":"+61 8 9352 1900",
    "sg:postcode":"6105",
    "sg:province":"WA",
    "sg:website":"http://www.smorgonsteel.com.au",
    "wof:name":"Smorgon Steel Recycling (Formerly Metalcorp Recyclers)",
    "wof:placetype":"venue"
},
  "geometry": {"coordinates":[115.982383728,-31.9871368408],"type":"Point"}
}