{
  "type": "Feature",
  "properties": {
    "iso:country":"AU",
    "sg:address":"5 Cedar St",
    "sg:city":"Cannon Hill",
    "sg:classifiers":[
        {
            "category":"Professional",
            "type":"Services"
        }
    ],
    "sg:phone":"+61 7 3395 6600",
    "sg:postcode":"4170",
    "sg:province":"QLD",
    "sg:tags":[
        "auctioneer"
    ],
    "wof:name":"Hassall Auctions",
    "wof:placetype":"venue"
},
  "geometry": {"coordinates":[153.090286255,-27.4599647522],"type":"Point"}
}