{
  "type": "Feature",
  "properties": {
    "addr:full":"13 Northumberland Drv East Ballina NSW 2478",
    "addr:housenumber":"13",
    "addr:postcode":"2478",
    "addr:street":"Northumberland Drv",
    "iso:country":"AU",
    "sg:address":"13 Northumberland Drv",
    "sg:city":"East Ballina",
    "sg:classifiers":[
        {
            "category":"Utilities",
            "subcategory":"Electric",
            "type":"Services"
        }
    ],
    "sg:phone":"+61 414 360 274",
    "sg:postcode":"2478",
    "sg:province":"NSW",
    "sg:tags":[
        "electrical",
        "contractor"
    ],
    "wof:name":"B J F Electrical",
    "wof:placetype":"venue"
},
  "geometry": {"coordinates":[153.57911682100001,-28.8609256744],"type":"Point"}
}