{
  "type": "Feature",
  "properties": {
    "addr:full":"12 Cox St Laverton WA 6440",
    "addr:housenumber":"12",
    "addr:postcode":"6440",
    "addr:street":"Cox St",
    "iso:country":"AU",
    "sg:address":"12 Cox St",
    "sg:city":"Laverton",
    "sg:classifiers":[
        {
            "category":"Real Estate",
            "subcategory":"Real Estate Agent",
            "type":"Services"
        }
    ],
    "sg:phone":"+61 8 9031 1126",
    "sg:postcode":"6440",
    "sg:province":"WA",
    "sg:tags":[
        "handyman's",
        "equipment",
        "hire",
        "builders",
        "contractor"
    ],
    "wof:name":"Wreckair",
    "wof:placetype":"venue"
},
  "geometry": {"coordinates":[122.39705658,-28.6237258911],"type":"Point"}
}