{
  "type": "Feature",
  "properties": {
    "addr:full":"PO Box 467 Willaston SA 5118",
    "addr:postcode":"5118",
    "iso:country":"AU",
    "sg:address":"PO Box 467",
    "sg:city":"Willaston",
    "sg:classifiers":[
        {
            "category":"Professional",
            "subcategory":"Accounting & Tax Preparation",
            "type":"Services"
        }
    ],
    "sg:phone":"+61 406 851 255",
    "sg:postcode":"5118",
    "sg:province":"SA",
    "sg:tags":[
        "bookkeeping"
    ],
    "wof:name":"Busy Bookkeeping Northern Suburbs Adelaide",
    "wof:placetype":"venue"
},
  "geometry": {"coordinates":[138.73899800000001,-34.583759],"type":"Point"}
}