{
  "type": "Feature",
  "properties": {
    "addr:full":"45 Bungowla St Bracken Ridge QLD 4017",
    "addr:housenumber":"45",
    "addr:postcode":"4017",
    "addr:street":"Bungowla St",
    "iso:country":"AU",
    "sg:address":"45 Bungowla St",
    "sg:city":"Bracken Ridge",
    "sg:classifiers":[
        {
            "category":"Utilities",
            "subcategory":"Electric",
            "type":"Services"
        }
    ],
    "sg:phone":"+61 408 545 957",
    "sg:postcode":"4017",
    "sg:province":"QLD",
    "sg:tags":[
        "electrical",
        "contractor"
    ],
    "wof:name":"Beam Electrical",
    "wof:placetype":"venue"
},
  "geometry": {"coordinates":[153.02218627900001,-27.3152008057],"type":"Point"}
}