{
  "type": "Feature",
  "properties": {
    "addr:full":"344 San Mateo Ave Mildura VIC 3500",
    "addr:housenumber":"344",
    "addr:postcode":"3500",
    "addr:street":"San Mateo Ave",
    "iso:country":"AU",
    "sg:address":"344 San Mateo Ave",
    "sg:city":"Mildura",
    "sg:classifiers":[
        {
            "category":"Social Services",
            "subcategory":"Retirement Home",
            "type":"Services"
        }
    ],
    "sg:phone":"+61 3 5022 8011",
    "sg:postcode":"3500",
    "sg:province":"VIC",
    "sg:tags":[
        "village"
    ],
    "wof:name":"Village Life",
    "wof:placetype":"venue"
},
  "geometry": {"coordinates":[142.14820861800001,-34.2055397034],"type":"Point"}
}