{
  "type": "Feature",
  "properties": {
    "addr:full":"84 Barry St Reservoir VIC 3073",
    "addr:housenumber":"84",
    "addr:postcode":"3073",
    "addr:street":"Barry St",
    "iso:country":"AU",
    "sg:address":"84 Barry St",
    "sg:city":"Reservoir",
    "sg:classifiers":[
        {
            "category":"Personal",
            "subcategory":"Beauty Salon",
            "type":"Services"
        }
    ],
    "sg:phone":"+61 3 9460 7038",
    "sg:postcode":"3073",
    "sg:province":"VIC",
    "sg:tags":[
        "hairdresser"
    ],
    "wof:name":"Hair Therapy",
    "wof:placetype":"venue"
},
  "geometry": {"coordinates":[145.000366211,-37.7089080811],"type":"Point"}
}