{
  "type": "Feature",
  "properties": {
    "iso:country":"AU",
    "sg:address":"Williams Rd",
    "sg:city":"Wangaratta",
    "sg:classifiers":[
        {
            "category":"Travel",
            "subcategory":"Hostel",
            "type":"Entertainment"
        }
    ],
    "sg:phone":"+61 3 5721 4214",
    "sg:postcode":"3677",
    "sg:province":"VIC",
    "sg:tags":[
        "home"
    ],
    "wof:name":"St John's Retirement Village",
    "wof:placetype":"venue"
},
  "geometry": {"coordinates":[146.30516052199999,-36.3468513489],"type":"Point"}
}