{
  "type": "Feature",
  "properties": {
    "iso:country":"AU",
    "sg:address":"109 High St",
    "sg:city":"Northcote",
    "sg:classifiers":[
        {
            "category":"Professional",
            "subcategory":"Art Services",
            "type":"Services"
        }
    ],
    "sg:phone":"+61 3 9486 8386",
    "sg:postcode":"3070",
    "sg:province":"VIC",
    "sg:tags":[
        "picture",
        "frame",
        "framing"
    ],
    "wof:name":"Mister Pictures",
    "wof:placetype":"venue"
},
  "geometry": {"coordinates":[144.996826,-37.779408],"type":"Point"}
}