{
  "type": "Feature",
  "properties": {
    "iso:country":"AU",
    "sg:address":"Leve 6,l 69 Reservoir St",
    "sg:city":"Surry Hills",
    "sg:classifiers":[
        {
            "category":"Organizations",
            "subcategory":"Professional Association",
            "type":"Services"
        }
    ],
    "sg:phone":"+61 2 8218 2163",
    "sg:postcode":"2010",
    "sg:province":"NSW",
    "sg:tags":[
        "web",
        "internet"
    ],
    "wof:name":"CoCo Creative",
    "wof:placetype":"venue"
},
  "geometry": {"coordinates":[151.210739136,-33.881401062],"type":"Point"}
}