{
  "type": "Feature",
  "properties": {
    "addr:full":"13 Walsh Rd Warrnambool VIC 3280",
    "addr:housenumber":"13",
    "addr:postcode":"3280",
    "addr:street":"Walsh Rd",
    "iso:country":"AU",
    "sg:address":"13 Walsh Rd",
    "sg:city":"Warrnambool",
    "sg:classifiers":[
        {
            "category":"Building & Trades",
            "subcategory":"Equipment Rental",
            "type":"Services"
        }
    ],
    "sg:phone":"+61 3 5561 4533",
    "sg:postcode":"3280",
    "sg:province":"VIC",
    "sg:tags":[
        "crane",
        "hire"
    ],
    "wof:name":"R A Steel Truck & Crane Hire Services",
    "wof:placetype":"venue"
},
  "geometry": {"coordinates":[142.45913696299999,-38.3684005737],"type":"Point"}
}