{
  "type": "Feature",
  "properties": {
    "addr:full":"2 International Crt Scoresby VIC 3179",
    "addr:housenumber":"2",
    "addr:postcode":"3179",
    "addr:street":"International Crt",
    "iso:country":"AU",
    "sg:address":"2 International Crt",
    "sg:city":"Scoresby",
    "sg:classifiers":[
        {
            "category":"Professional",
            "subcategory":"Printing & Photocopies",
            "type":"Services"
        }
    ],
    "sg:phone":"+61 1300 363 440",
    "sg:postcode":"3179",
    "sg:province":"VIC",
    "sg:tags":[
        "equipment",
        "plan"
    ],
    "wof:name":"Oce- Australia Limited",
    "wof:placetype":"venue"
},
  "geometry": {"coordinates":[145.222366333,-37.9017944336],"type":"Point"}
}