{
  "type": "Feature",
  "properties": {
    "addr:full":"Shop T138 Level 1 Bay City Plaza Geelong VIC 3220",
    "addr:postcode":"3220",
    "iso:country":"AU",
    "sg:address":"Shop T138 Level 1 Bay City Plaza",
    "sg:city":"Geelong",
    "sg:classifiers":[
        {
            "category":"Shopping",
            "subcategory":"Clothing, Apparel, & Fashions",
            "type":"Retail Goods"
        }
    ],
    "sg:phone":"+61 3 5221 8404",
    "sg:postcode":"3220",
    "sg:province":"VIC",
    "sg:tags":[
        "lady",
        "wear"
    ],
    "wof:name":"Miller's Fashion Club",
    "wof:placetype":"venue"
},
  "geometry": {"coordinates":[144.35398900000001,-38.121208],"type":"Point"}
}