{
  "type": "Feature",
  "properties": {
    "addr:full":"7180 Great Eastern Hwy Mundaring WA 6073",
    "addr:housenumber":"7180",
    "addr:postcode":"6073",
    "addr:street":"Great Eastern Hwy",
    "iso:country":"AU",
    "sg:address":"7180 Great Eastern Hwy",
    "sg:city":"Mundaring",
    "sg:classifiers":[
        {
            "category":"Health Services",
            "subcategory":"Doctor",
            "type":"Services"
        }
    ],
    "sg:phone":"+61 8 9295 3471",
    "sg:postcode":"6073",
    "sg:province":"WA",
    "sg:tags":[
        "podiatrist"
    ],
    "wof:name":"Eastern Hills Podiatry",
    "wof:placetype":"venue"
},
  "geometry": {"coordinates":[116.168060303,-31.902223587],"type":"Point"}
}