{
  "type": "Feature",
  "properties": {
    "addr:full":"Rear 128 Milperra Rd Revesby NSW 2212",
    "addr:housenumber":"128",
    "addr:postcode":"2212",
    "addr:street":"Milperra Rd",
    "iso:country":"AU",
    "sg:address":"Rear 128 Milperra Rd",
    "sg:city":"Revesby",
    "sg:classifiers":[
        {
            "category":"Retail",
            "subcategory":"Storage",
            "type":"Services"
        }
    ],
    "sg:phone":"+61 2 9792 6667",
    "sg:postcode":"2212",
    "sg:province":"NSW",
    "sg:tags":[
        "removal",
        "furniture"
    ],
    "wof:name":"Jackman Furniture Transport",
    "wof:placetype":"venue"
},
  "geometry": {"coordinates":[151.01205400000001,-33.936577],"type":"Point"}
}