{
  "type": "Feature",
  "properties": {
    "addr:full":"654 Pacific Hwy Kanwal NSW 2259",
    "addr:housenumber":"654",
    "addr:postcode":"2259",
    "addr:street":"Pacific Hwy",
    "iso:country":"AU",
    "sg:address":"654 Pacific Hwy",
    "sg:city":"Kanwal",
    "sg:classifiers":[
        {
            "category":"Education",
            "subcategory":"Kindergarten",
            "type":"Public Place"
        }
    ],
    "sg:phone":"+61 2 4392 8960",
    "sg:postcode":"2259",
    "sg:province":"NSW",
    "sg:tags":[
        "pre-schools"
    ],
    "wof:name":"Strawberry Patch Care & Learning Centre Kanwal",
    "wof:placetype":"venue"
},
  "geometry": {"coordinates":[151.48776245100001,-33.2538909912],"type":"Point"}
}