{
  "type": "Feature",
  "properties": {
    "iso:country":"AU",
    "sg:address":"29 Piccadilly Rd",
    "sg:city":"Salisbury East",
    "sg:classifiers":[
        {
            "category":"Education",
            "subcategory":"Kindergarten",
            "type":"Public Place"
        }
    ],
    "sg:phone":"+61 8 8258 8939",
    "sg:postcode":"5109",
    "sg:province":"SA",
    "sg:tags":[
        "pre-schools"
    ],
    "wof:name":"Madison Park Kindergarten (Salsbry E)",
    "wof:placetype":"venue"
},
  "geometry": {"coordinates":[138.67025756800001,-34.7790107727],"type":"Point"}
}