{
  "type": "Feature",
  "properties": {
    "addr:full":"500 Burwood Hwy Vermont South VIC 3133",
    "addr:housenumber":"500",
    "addr:postcode":"3133",
    "addr:street":"Burwood Hwy",
    "iso:country":"AU",
    "sg:address":"500 Burwood Hwy",
    "sg:city":"Vermont South",
    "sg:classifiers":[
        {
            "category":"Train Station",
            "subcategory":"Rail",
            "type":"Transportation"
        }
    ],
    "sg:phone":"+61 3 9881 1555",
    "sg:postcode":"3133",
    "sg:province":"VIC",
    "sg:tags":[
        "consultant"
    ],
    "wof:name":"ARRB Transport Research Ltd",
    "wof:placetype":"venue"
},
  "geometry": {"coordinates":[145.18440246599999,-37.8569221497],"type":"Point"}
}