{
  "type": "Feature",
  "properties": {
    "addr:full":"12 Drover Crt Walkley Heights SA 5098",
    "addr:housenumber":"12",
    "addr:postcode":"5098",
    "addr:street":"Drover Crt",
    "iso:country":"AU",
    "sg:address":"12 Drover Crt",
    "sg:city":"Walkley Heights",
    "sg:classifiers":[
        {
            "category":"Arts & Performance",
            "subcategory":"Music",
            "type":"Entertainment"
        }
    ],
    "sg:phone":"+61 419 820 134",
    "sg:postcode":"5098",
    "sg:province":"SA",
    "sg:tags":[
        "mobile",
        "jockey",
        "disc"
    ],
    "wof:name":"McMillan Stuart",
    "wof:placetype":"venue"
},
  "geometry": {"coordinates":[138.642852783,-34.8378448486],"type":"Point"}
}