{
  "type": "Feature",
  "properties": {
    "addr:full":"Unit 7, 45- 55 Epsom Rd Rosebery NSW 2018",
    "addr:housenumber":"45 55",
    "addr:postcode":"2018",
    "addr:street":"Epsom Rd",
    "iso:country":"AU",
    "sg:address":"Unit 7, 45- 55 Epsom Rd",
    "sg:city":"Rosebery",
    "sg:classifiers":[
        {
            "category":"Professional",
            "subcategory":"Engineering",
            "type":"Services"
        }
    ],
    "sg:phone":"+61 2 9663 3433",
    "sg:postcode":"2018",
    "sg:province":"NSW",
    "sg:tags":[
        "consulting",
        "engineer"
    ],
    "wof:name":"Structural Design Solutions",
    "wof:placetype":"venue"
},
  "geometry": {"coordinates":[151.20782470699999,-33.9110183716],"type":"Point"}
}