{
  "type": "Feature",
  "properties": {
    "addr:full":"1573 Main Rd Westerway TAS 7140",
    "addr:housenumber":"1573",
    "addr:postcode":"7140",
    "addr:street":"Main Rd",
    "iso:country":"AU",
    "sg:address":"1573 Main Rd",
    "sg:city":"Westerway",
    "sg:classifiers":[
        {
            "category":"Fast Food",
            "type":"Food & Drink"
        }
    ],
    "sg:phone":"+61 3 6288 1115",
    "sg:postcode":"7140",
    "sg:province":"TAS",
    "sg:tags":[
        "away",
        "take"
    ],
    "wof:name":"Westerway Road House",
    "wof:placetype":"venue"
},
  "geometry": {"coordinates":[146.793564,-42.674881],"type":"Point"}
}