{
  "type": "Feature",
  "properties": {
    "iso:country":"AU",
    "sg:address":"2 Marshall St",
    "sg:city":"Mosman Park",
    "sg:classifiers":[
        {
            "category":"Sports & Exercise",
            "subcategory":"Golf",
            "type":"Entertainment"
        }
    ],
    "sg:phone":"+61 8 9384 6312",
    "sg:postcode":"6012",
    "sg:province":"WA",
    "sg:tags":[
        "club"
    ],
    "wof:name":"Mosman Park Golf Club (Inc)",
    "wof:placetype":"venue"
},
  "geometry": {"coordinates":[115.77745819099999,-32.0195465088],"type":"Point"}
}