{
  "type": "Feature",
  "properties": {
    "addr:full":"51/ 26 Goldmind Rd Ormeau QLD 4208",
    "addr:housenumber":"51 / 26",
    "addr:postcode":"4208",
    "addr:street":"Goldmind Rd",
    "iso:country":"AU",
    "sg:address":"51/ 26 Goldmind Rd",
    "sg:city":"Ormeau",
    "sg:classifiers":[
        {
            "category":"Building & Trades",
            "subcategory":"Cleaning & Sanitation",
            "type":"Services"
        }
    ],
    "sg:phone":"+61 412 832 242",
    "sg:postcode":"4208",
    "sg:province":"QLD",
    "sg:tags":[
        "chemical",
        "pressure",
        "steam",
        "contractor"
    ],
    "wof:name":"Mega Blaster",
    "wof:placetype":"venue"
},
  "geometry": {"coordinates":[153.25706481899999,-27.7767601013],"type":"Point"}
}