{
  "type": "Feature",
  "properties": {
    "addr:full":"Suite 4 Level 1, 5-9 Pope St Ryde NSW 2112",
    "addr:housenumber":"5-9",
    "addr:postcode":"2112",
    "addr:street":"Pope St",
    "iso:country":"AU",
    "sg:address":"Suite 4 Level 1, 5-9 Pope St",
    "sg:city":"Ryde",
    "sg:classifiers":[
        {
            "category":"Education",
            "subcategory":"Special Training",
            "type":"Public Place"
        }
    ],
    "sg:phone":"+61 2 9807 2999",
    "sg:postcode":"2112",
    "sg:province":"NSW",
    "sg:tags":[
        "tuition-educational"
    ],
    "wof:name":"Dyslexia Network Australia",
    "wof:placetype":"venue"
},
  "geometry": {"coordinates":[151.10726928700001,-33.8112373352],"type":"Point"}
}