{
  "type": "Feature",
  "properties": {
    "iso:country":"AU",
    "sg:address":"151 Chaffey St",
    "sg:city":"Merbein",
    "sg:classifiers":[
        {
            "category":"Building & Trades",
            "subcategory":"Construction",
            "type":"Services"
        }
    ],
    "sg:phone":"+61 3 5025 2116",
    "sg:postcode":"3505",
    "sg:province":"VIC",
    "sg:tags":[
        "contractor"
    ],
    "wof:name":"Dasey P E",
    "wof:placetype":"venue"
},
  "geometry": {"coordinates":[142.07281494099999,-34.1680641174],"type":"Point"}
}