{
  "type": "Feature",
  "properties": {
    "iso:country":"AU",
    "sg:address":"9 Rayment St",
    "sg:city":"Fairfield",
    "sg:classifiers":[
        {
            "category":"Professional",
            "subcategory":"Computer Services",
            "type":"Services"
        }
    ],
    "sg:phone":"+61 3 9481 2500",
    "sg:postcode":"3078",
    "sg:province":"VIC",
    "sg:tags":[
        "repairs",
        "upgrade",
        "equipment"
    ],
    "wof:name":"Hardware Software Anywhere",
    "wof:placetype":"venue"
},
  "geometry": {"coordinates":[145.025115967,-37.7729492188],"type":"Point"}
}