{
  "type": "Feature",
  "properties": {
    "addr:full":"32 Quarantine Rd Youngtown TAS 7249",
    "addr:housenumber":"32",
    "addr:postcode":"7249",
    "addr:street":"Quarantine Rd",
    "iso:country":"AU",
    "sg:address":"32 Quarantine Rd",
    "sg:city":"Youngtown",
    "sg:classifiers":[
        {
            "category":"Social Services",
            "subcategory":"Adult Care",
            "type":"Services"
        }
    ],
    "sg:phone":"+61 3 6344 8885",
    "sg:postcode":"7249",
    "sg:province":"TAS",
    "sg:tags":[
        "disadvantaged",
        "aid",
        "organisation",
        "group"
    ],
    "wof:name":"NEENA Residential Facility",
    "wof:placetype":"venue"
},
  "geometry": {"coordinates":[147.16868591299999,-41.4733428955],"type":"Point"}
}