{
  "type": "Feature",
  "properties": {
    "addr:full":"Unit 2/ 130 King St Buderim QLD 4556",
    "addr:housenumber":"/ 130",
    "addr:postcode":"4556",
    "addr:street":"King St",
    "iso:country":"AU",
    "sg:address":"Unit 2/ 130 King St",
    "sg:city":"Buderim",
    "sg:classifiers":[
        {
            "category":"Banks & Credit Unions",
            "subcategory":"Investment Brokerage",
            "type":"Services"
        }
    ],
    "sg:phone":"+61 416 263 436",
    "sg:postcode":"4556",
    "sg:province":"QLD",
    "sg:tags":[
        "broker"
    ],
    "wof:name":"Coastal Car Search Vehicle Brokers",
    "wof:placetype":"venue"
},
  "geometry": {"coordinates":[153.06976318400001,-26.6836471558],"type":"Point"}
}