{
  "type": "Feature",
  "properties": {
    "addr:full":"Shop 6/ 130 Coolibah Drv Greenwood WA 6024",
    "addr:housenumber":"shop 6 / 130",
    "addr:postcode":"6024",
    "addr:street":"Coolibah Drv",
    "iso:country":"AU",
    "sg:address":"Shop 6/ 130 Coolibah Drv",
    "sg:city":"Greenwood",
    "sg:classifiers":[
        {
            "category":"Real Estate",
            "subcategory":"Real Estate Agent",
            "type":"Services"
        }
    ],
    "sg:phone":"+61 8 9203 9800",
    "sg:postcode":"6024",
    "sg:province":"WA",
    "wof:name":"LJ Hooker Greenwood",
    "wof:placetype":"venue"
},
  "geometry": {"coordinates":[115.798851013,-31.8318004608],"type":"Point"}
}