{
  "type": "Feature",
  "properties": {
    "iso:country":"AU",
    "sg:address":"49 Gordon Rd (East)",
    "sg:city":"Osborne Park",
    "sg:classifiers":[
        {
            "category":"Manufacturing",
            "subcategory":"Chemicals & Compounds",
            "type":"Manufacturing & Wholesale Goods"
        }
    ],
    "sg:phone":"+61 8 9444 5060",
    "sg:postcode":"6017",
    "sg:province":"WA",
    "sg:tags":[
        "electroplating"
    ],
    "wof:name":"Ultrachrome Pty Ltd",
    "wof:placetype":"venue"
},
  "geometry": {"coordinates":[115.82301330599999,-31.9070262909],"type":"Point"}
}