{
  "type": "Feature",
  "properties": {
    "iso:country":"AU",
    "sg:address":"Cnr Marian & Kookaburra Sts",
    "sg:city":"Mt Isa",
    "sg:classifiers":[
        {
            "category":"Travel",
            "subcategory":"Hotels & Motels",
            "type":"Entertainment"
        }
    ],
    "sg:phone":"+61 7 4743 3328",
    "sg:postcode":"4825",
    "sg:province":"QLD",
    "wof:name":"Townview Motel",
    "wof:placetype":"venue"
},
  "geometry": {"coordinates":[139.49096700000001,-20.72607],"type":"Point"}
}