{
  "type": "Feature",
  "properties": {
    "iso:country":"AU",
    "sg:address":"153 Lyons Rd",
    "sg:city":"Drummoyne",
    "sg:classifiers":[
        {
            "category":"Health Services",
            "subcategory":"Doctor",
            "type":"Services"
        }
    ],
    "sg:phone":"+61 2 9719 1900",
    "sg:postcode":"2047",
    "sg:province":"NSW",
    "sg:tags":[
        "medical",
        "practitioner"
    ],
    "wof:name":"Lyons Rd Medical Centre",
    "wof:placetype":"venue"
},
  "geometry": {"coordinates":[151.147934,-33.855541],"type":"Point"}
}