{
  "type": "Feature",
  "properties": {
    "iso:country":"AU",
    "sg:address":"16 Batar Creek Rd",
    "sg:city":"Kendall",
    "sg:classifiers":[
        {
            "category":"Manufacturing",
            "subcategory":"Tools & Machinery",
            "type":"Manufacturing & Wholesale Goods"
        }
    ],
    "sg:phone":"+61 438 656 786",
    "sg:postcode":"2439",
    "sg:province":"NSW",
    "sg:tags":[
        "earth",
        "excavating",
        "moving",
        "equipment"
    ],
    "wof:name":"Steve Wallis Transport",
    "wof:placetype":"venue"
},
  "geometry": {"coordinates":[152.701965,-31.634203],"type":"Point"}
}