{
  "type": "Feature",
  "properties": {
    "iso:country":"AU",
    "sg:address":"Harris Rd",
    "sg:city":"Picton",
    "sg:classifiers":[
        {
            "category":"Wholesale",
            "subcategory":"Farm Supplies",
            "type":"Manufacturing & Wholesale Goods"
        }
    ],
    "sg:phone":"+61 8 9724 6800",
    "sg:postcode":"6229",
    "sg:province":"WA",
    "sg:tags":[
        "feed",
        "supplement",
        "stock"
    ],
    "wof:name":"Kettridges",
    "wof:placetype":"venue"
},
  "geometry": {"coordinates":[115.709358,-33.35342],"type":"Point"}
}