{
  "type": "Feature",
  "properties": {
    "addr:full":"147 Northern Rd Heidelberg West VIC 3081",
    "addr:housenumber":"147",
    "addr:postcode":"3081",
    "addr:street":"Northern Rd",
    "iso:country":"AU",
    "sg:address":"147 Northern Rd",
    "sg:city":"Heidelberg West",
    "sg:classifiers":[
        {
            "category":"Fast Food",
            "type":"Food & Drink"
        }
    ],
    "sg:phone":"+61 3 9459 0351",
    "sg:postcode":"3081",
    "sg:province":"VIC",
    "sg:tags":[
        "away",
        "take"
    ],
    "wof:name":"Koutsodontis M & Spanos G",
    "wof:placetype":"venue"
},
  "geometry": {"coordinates":[145.057250977,-37.7302131653],"type":"Point"}
}