{
  "type": "Feature",
  "properties": {
    "iso:country":"AU",
    "sg:address":"9 Main Rd",
    "sg:city":"Brighton",
    "sg:classifiers":[
        {
            "category":"Professional",
            "type":"Services"
        }
    ],
    "sg:phone":"+61 3 6268 0033",
    "sg:postcode":"7030",
    "sg:province":"TAS",
    "sg:tags":[
        "buyer",
        "merchant",
        "wool"
    ],
    "wof:name":"G A & A T Wool Buyers",
    "wof:placetype":"venue"
},
  "geometry": {"coordinates":[147.22662353499999,-42.7505455017],"type":"Point"}
}