{
  "type": "Feature",
  "properties": {
    "addr:full":"98 York St Wangaratta VIC 3676",
    "addr:housenumber":"98",
    "addr:postcode":"3676",
    "addr:street":"York St",
    "iso:country":"AU",
    "sg:address":"98 York St",
    "sg:city":"Wangaratta",
    "sg:classifiers":[
        {
            "category":"Health Services",
            "subcategory":"Doctor",
            "type":"Services"
        }
    ],
    "sg:phone":"+61 1300 360 455",
    "sg:postcode":"3676",
    "sg:province":"VIC",
    "sg:tags":[
        "occupational",
        "safety"
    ],
    "wof:name":"St John Ambulance Australia Victoria",
    "wof:placetype":"venue"
},
  "geometry": {"coordinates":[146.32493600000001,-36.35371],"type":"Point"}
}