{
  "type": "Feature",
  "properties": {
    "addr:full":"241 Leitchs Rd Strathpine QLD 4500",
    "addr:housenumber":"241",
    "addr:postcode":"4500",
    "addr:street":"Leitchs Rd",
    "iso:country":"AU",
    "sg:address":"241 Leitchs Rd",
    "sg:city":"Strathpine",
    "sg:classifiers":[
        {
            "category":"Wholesale",
            "subcategory":"Machinery & Supplies",
            "type":"Manufacturing & Wholesale Goods"
        }
    ],
    "sg:phone":"+61 7 3205 4866",
    "sg:postcode":"4500",
    "sg:province":"QLD",
    "wof:name":"Imperial Machinery",
    "wof:placetype":"venue"
},
  "geometry": {"coordinates":[152.98118591299999,-27.3180236816],"type":"Point"}
}