{
  "type": "Feature",
  "properties": {
    "addr:full":"31 Capitol Ave McKinnon VIC 3204",
    "addr:postcode":"3204",
    "addr:street":"Capitol Ave",
    "iso:country":"AU",
    "sg:address":"31 Capitol Ave",
    "sg:city":"McKinnon",
    "sg:classifiers":[
        {
            "category":"Building & Trades",
            "subcategory":"Plumbing",
            "type":"Services"
        }
    ],
    "sg:phone":"+61 3 9578 2152",
    "sg:postcode":"3204",
    "sg:province":"VIC",
    "sg:tags":[
        "plumber",
        "gasfitters"
    ],
    "wof:name":"Paulmatt Pty Ltd",
    "wof:placetype":"venue"
},
  "geometry": {"coordinates":[145.028885,-37.907139],"type":"Point"}
}