{
  "type": "Feature",
  "properties": {
    "addr:full":"140 Hurd St Portland VIC 3305",
    "addr:housenumber":"140",
    "addr:postcode":"3305",
    "addr:street":"Hurd St",
    "iso:country":"AU",
    "sg:address":"140 Hurd St",
    "sg:city":"Portland",
    "sg:classifiers":[
        {
            "category":"Personal",
            "subcategory":"Massage",
            "type":"Services"
        }
    ],
    "sg:phone":"+61 3 5523 4402",
    "sg:postcode":"3305",
    "sg:province":"VIC",
    "sg:tags":[
        "therapy"
    ],
    "wof:name":"Barry Edith",
    "wof:placetype":"venue"
},
  "geometry": {"coordinates":[141.60168457,-38.3374023438],"type":"Point"}
}