{
  "type": "Feature",
  "properties": {
    "addr:full":"26 Newton St Broadmeadow NSW 2292",
    "addr:housenumber":"26",
    "addr:postcode":"2292",
    "addr:street":"Newton St",
    "iso:country":"AU",
    "sg:address":"26 Newton St",
    "sg:city":"Broadmeadow",
    "sg:classifiers":[
        {
            "category":"Industrial Area",
            "type":"Public Place"
        }
    ],
    "sg:phone":"+61 2 4952 9944",
    "sg:postcode":"2292",
    "sg:province":"NSW",
    "sg:tags":[
        "protective",
        "clothing"
    ],
    "wof:name":"Newcastle Workwear Specialists P/L",
    "wof:placetype":"venue"
},
  "geometry": {"coordinates":[151.723342895,-32.924446106],"type":"Point"}
}