{
  "type": "Feature",
  "properties": {
    "addr:full":"79 Tucker St Breakwater VIC 3219",
    "addr:housenumber":"79",
    "addr:postcode":"3219",
    "addr:street":"Tucker St",
    "iso:country":"AU",
    "sg:address":"79 Tucker St",
    "sg:city":"Breakwater",
    "sg:classifiers":[
        {
            "category":"Building & Trades",
            "subcategory":"Construction",
            "type":"Services"
        }
    ],
    "sg:phone":"+61 1800 333 379",
    "sg:postcode":"3219",
    "sg:province":"VIC",
    "sg:tags":[
        "fencing",
        "contractor"
    ],
    "wof:name":"Sfercos Aluminium",
    "wof:placetype":"venue"
},
  "geometry": {"coordinates":[144.366653442,-38.1848526001],"type":"Point"}
}