{
  "type": "Feature",
  "properties": {
    "addr:full":"Tocumwal Rd Cobram VIC 3644",
    "addr:postcode":"3644",
    "addr:street":"Tocumwal Rd",
    "iso:country":"AU",
    "sg:address":"Tocumwal Rd",
    "sg:city":"Cobram",
    "sg:classifiers":[
        {
            "category":"Farming",
            "subcategory":"Orchard",
            "type":"Manufacturing & Wholesale Goods"
        }
    ],
    "sg:phone":"+61 3 5872 2251",
    "sg:postcode":"3644",
    "sg:province":"VIC",
    "sg:tags":[
        "pear",
        "apple",
        "grower"
    ],
    "wof:name":"Perri Toni",
    "wof:placetype":"venue"
},
  "geometry": {"coordinates":[145.663696289,-35.885181427],"type":"Point"}
}