{
  "type": "Feature",
  "properties": {
    "addr:full":"Lvl 3/ 20 Park Rd Brisbane QLD 4000",
    "addr:housenumber":"/ 20",
    "addr:postcode":"4000",
    "addr:street":"Park Rd",
    "iso:country":"AU",
    "sg:address":"Lvl 3/ 20 Park Rd",
    "sg:city":"Brisbane",
    "sg:classifiers":[
        {
            "category":"Building & Trades",
            "subcategory":"Electrical",
            "type":"Services"
        }
    ],
    "sg:phone":"+61 7 3367 0554",
    "sg:postcode":"4000",
    "sg:province":"QLD",
    "sg:tags":[
        "wholesaler",
        "mfrs",
        "appliance"
    ],
    "wof:name":"Electronics Wholesalers Australia",
    "wof:placetype":"venue"
},
  "geometry": {"coordinates":[153.00462341299999,-27.4705600739],"type":"Point"}
}