{
  "type": "Feature",
  "properties": {
    "addr:full":"14 Government Rd Nedlands WA 6009",
    "addr:housenumber":"14",
    "addr:postcode":"6009",
    "addr:street":"Government Rd",
    "iso:country":"AU",
    "sg:address":"14 Government Rd",
    "sg:city":"Nedlands",
    "sg:classifiers":[
        {
            "category":"Professional",
            "subcategory":"Printing & Photocopies",
            "type":"Services"
        }
    ],
    "sg:phone":"+61 8 9389 8950",
    "sg:postcode":"6009",
    "sg:province":"WA",
    "sg:tags":[
        "screen",
        "printer"
    ],
    "wof:name":"Labels Plus",
    "wof:placetype":"venue"
},
  "geometry": {"coordinates":[115.79495199999999,-31.97506],"type":"Point"}
}