{
  "type": "Feature",
  "properties": {
    "addr:full":"Cnr Hawkesbury & Darcy Rds Westmead NSW 2145",
    "addr:postcode":"2145",
    "addr:street":"Cnr",
    "iso:country":"AU",
    "sg:address":"Cnr Hawkesbury & Darcy Rds",
    "sg:city":"Westmead",
    "sg:classifiers":[
        {
            "category":"Health Services",
            "subcategory":"Doctor",
            "type":"Services"
        }
    ],
    "sg:phone":"+61 2 9633 6886",
    "sg:postcode":"2145",
    "sg:province":"NSW",
    "sg:tags":[
        "medical",
        "practitioner"
    ],
    "wof:name":"Dorsch N W C Professor",
    "wof:placetype":"venue"
},
  "geometry": {"coordinates":[150.98712158199999,-33.8080253601],"type":"Point"}
}