{
  "type": "Feature",
  "properties": {
    "iso:country":"AU",
    "sg:address":"3 Birdwod St",
    "sg:city":"Frankston",
    "sg:classifiers":[
        {
            "category":"Building & Trades",
            "subcategory":"Cleaning & Sanitation",
            "type":"Services"
        }
    ],
    "sg:phone":"+61 3 9787 8969",
    "sg:postcode":"3199",
    "sg:province":"VIC",
    "sg:tags":[
        "industrial",
        "commercial",
        "contractor"
    ],
    "wof:name":"John & Mary General Cleaning Services",
    "wof:placetype":"venue"
},
  "geometry": {"coordinates":[145.104049683,-38.0293426514],"type":"Point"}
}