{
  "type": "Feature",
  "properties": {
    "addr:full":"73 winbourne Rd Brookvale NSW 2100",
    "addr:housenumber":"73",
    "addr:postcode":"2100",
    "addr:street":"Winbourne Rd",
    "iso:country":"AU",
    "sg:address":"73 winbourne Rd",
    "sg:city":"Brookvale",
    "sg:classifiers":[
        {
            "category":"Shopping",
            "subcategory":"Pawn Shop",
            "type":"Retail Goods"
        }
    ],
    "sg:phone":"+61 405 925 669",
    "sg:postcode":"2100",
    "sg:province":"NSW",
    "sg:tags":[
        "pawnbroker"
    ],
    "wof:name":"Hock a Car",
    "wof:placetype":"venue"
},
  "geometry": {"coordinates":[151.273895264,-33.7623062134],"type":"Point"}
}