{
  "type": "Feature",
  "properties": {
    "addr:full":"16 Shepherd Rd Swan Hill VIC 3585",
    "addr:housenumber":"16",
    "addr:postcode":"3585",
    "addr:street":"Shepherd Rd",
    "iso:country":"AU",
    "sg:address":"16 Shepherd Rd",
    "sg:city":"Swan Hill",
    "sg:classifiers":[
        {
            "category":"Government",
            "subcategory":"Department Of Motor Vehicles",
            "type":"Public Place"
        }
    ],
    "sg:phone":"+61 3 5032 2106",
    "sg:postcode":"3585",
    "sg:province":"VIC",
    "sg:tags":[
        "wholesaler",
        "mfrs",
        "accessory"
    ],
    "wof:name":"Ultra Auto Australia",
    "wof:placetype":"venue"
},
  "geometry": {"coordinates":[143.539536,-35.32753],"type":"Point"}
}