{
  "type": "Feature",
  "properties": {
    "iso:country":"AU",
    "sg:address":"1/3 Thornycroft St",
    "sg:city":"Campbellfield",
    "sg:classifiers":[
        {
            "category":"Manufacturing",
            "subcategory":"Tools & Machinery",
            "type":"Manufacturing & Wholesale Goods"
        }
    ],
    "sg:phone":"+61 3 9308 6890",
    "sg:postcode":"3061",
    "sg:province":"VIC",
    "sg:tags":[
        "wholesaler",
        "mfrs",
        "hosiery"
    ],
    "wof:name":"Topsocks Manufacturers",
    "wof:placetype":"venue"
},
  "geometry": {"coordinates":[144.94203185999999,-37.6475906372],"type":"Point"}
}