{
  "type": "Feature",
  "properties": {
    "addr:full":"367 Hamilton Rd Fairfield West NSW 2165",
    "addr:housenumber":"367",
    "addr:postcode":"2165",
    "addr:street":"Hamilton Rd",
    "iso:country":"AU",
    "sg:address":"367 Hamilton Rd",
    "sg:city":"Fairfield West",
    "sg:classifiers":[
        {
            "category":"Health Services",
            "subcategory":"Optometrist",
            "type":"Services"
        }
    ],
    "sg:phone":"+61 2 9604 7581",
    "sg:postcode":"2165",
    "sg:province":"NSW",
    "wof:name":"Tan P L",
    "wof:placetype":"venue"
},
  "geometry": {"coordinates":[150.92242431599999,-33.8688468933],"type":"Point"}
}