{
  "type": "Feature",
  "properties": {
    "addr:full":"14 Cullen Pl Smithfield NSW 2164",
    "addr:housenumber":"14",
    "addr:postcode":"2164",
    "addr:street":"Cullen Pl",
    "iso:country":"AU",
    "sg:address":"14 Cullen Pl",
    "sg:city":"Smithfield",
    "sg:classifiers":[
        {
            "category":"Home & Garden",
            "subcategory":"Building Materials",
            "type":"Retail Goods"
        }
    ],
    "sg:phone":"+61 2 9604 2200",
    "sg:postcode":"2164",
    "sg:province":"NSW",
    "sg:tags":[
        "pre-mixed",
        "concrete"
    ],
    "wof:name":"Advanced Readymix",
    "wof:placetype":"venue"
},
  "geometry": {"coordinates":[150.94973754899999,-33.841468811],"type":"Point"}
}