{
  "type": "Feature",
  "properties": {
    "addr:full":"100 Wickham St Brisbane QLD 4000",
    "addr:housenumber":"100",
    "addr:postcode":"4000",
    "addr:street":"Wickham St",
    "iso:country":"AU",
    "sg:address":"100 Wickham St",
    "sg:city":"Brisbane",
    "sg:classifiers":[
        {
            "category":"Cafe",
            "type":"Food & Drink"
        }
    ],
    "sg:phone":"+61 7 3831 6661",
    "sg:postcode":"4000",
    "sg:province":"QLD",
    "wof:name":"Coffee Cellar",
    "wof:placetype":"venue"
},
  "geometry": {"coordinates":[153.02079773,-27.4644050598],"type":"Point"}
}