{
  "type": "Feature",
  "properties": {
    "addr:full":"Level 26, 201 Kent St Sydney NSW 2000",
    "addr:housenumber":"201",
    "addr:postcode":"2000",
    "addr:street":"Kent St",
    "iso:country":"AU",
    "sg:address":"Level 26, 201 Kent St",
    "sg:city":"Sydney",
    "sg:classifiers":[
        {
            "category":"Professional",
            "subcategory":"Management & Consulting",
            "type":"Services"
        }
    ],
    "sg:phone":"+61 2 9247 2111",
    "sg:postcode":"2000",
    "sg:province":"NSW",
    "sg:tags":[
        "information"
    ],
    "wof:name":"ICSGlobal Limited",
    "wof:placetype":"venue"
},
  "geometry": {"coordinates":[151.20382690400001,-33.8636398315],"type":"Point"}
}