{
  "type": "Feature",
  "properties": {
    "iso:country":"AU",
    "sg:address":"Cnr Narre Warren Nth Rd & Prospect Hill Rd",
    "sg:city":"Narre Warren",
    "sg:classifiers":[
        {
            "category":"Health Services",
            "subcategory":"Doctor",
            "type":"Services"
        }
    ],
    "sg:phone":"+61 3 9705 4400",
    "sg:postcode":"3805",
    "sg:province":"VIC",
    "sg:tags":[
        "medical",
        "practitioner"
    ],
    "wof:name":"Narre Warren Clinic",
    "wof:placetype":"venue"
},
  "geometry": {"coordinates":[145.307541,-38.01107],"type":"Point"}
}