{
  "type": "Feature",
  "properties": {
    "addr:full":"6 Lister St Monto QLD 4630",
    "addr:housenumber":"6",
    "addr:postcode":"4630",
    "addr:street":"Lister St",
    "iso:country":"AU",
    "sg:address":"6 Lister St",
    "sg:city":"Monto",
    "sg:classifiers":[
        {
            "category":"Retail",
            "subcategory":"Veterinary Services",
            "type":"Services"
        }
    ],
    "sg:phone":"+61 7 4166 1285",
    "sg:postcode":"4630",
    "sg:province":"QLD",
    "sg:tags":[
        "surgeon"
    ],
    "wof:name":"Monto Veterinary Surgery",
    "wof:placetype":"venue"
},
  "geometry": {"coordinates":[151.120330811,-24.8693332672],"type":"Point"}
}