{
  "type": "Feature",
  "properties": {
    "addr:full":"1 Hall St Alexandra VIC 3714",
    "addr:housenumber":"1",
    "addr:postcode":"3714",
    "addr:street":"Hall St",
    "iso:country":"AU",
    "sg:address":"1 Hall St",
    "sg:city":"Alexandra",
    "sg:classifiers":[
        {
            "category":"Home & Garden",
            "subcategory":"Carpets & Floor Coverings",
            "type":"Retail Goods"
        }
    ],
    "sg:phone":"+61 3 5772 2152",
    "sg:postcode":"3714",
    "sg:province":"VIC",
    "wof:name":"Alexandra Floor Coverings",
    "wof:placetype":"venue"
},
  "geometry": {"coordinates":[145.700927734,-37.1938018799],"type":"Point"}
}