{
  "type": "Feature",
  "properties": {
    "addr:full":"379 Greenhill Rd Toorak Gardens SA 5065",
    "addr:housenumber":"379",
    "addr:postcode":"5065",
    "addr:street":"Greenhill Rd Toorak Gardens",
    "iso:country":"AU",
    "sg:address":"379 Greenhill Rd",
    "sg:city":"Toorak Gardens",
    "sg:classifiers":[
        {
            "category":"Personal",
            "subcategory":"Beauty Salon",
            "type":"Services"
        }
    ],
    "sg:phone":"+61 8 8331 4033",
    "sg:postcode":"5065",
    "sg:province":"SA",
    "sg:tags":[
        "hairdresser"
    ],
    "wof:name":"Kokino Hair Studio",
    "wof:placetype":"venue"
},
  "geometry": {"coordinates":[138.64183044399999,-34.9390602112],"type":"Point"}
}