{
  "type": "Feature",
  "properties": {
    "iso:country":"AU",
    "sg:address":"Suite 9, Level 21, 141 Queen St",
    "sg:city":"Brisbane",
    "sg:classifiers":[
        {
            "category":"Banks & Credit Unions",
            "subcategory":"Financial Services",
            "type":"Services"
        }
    ],
    "sg:phone":"+61 7 3210 1100",
    "sg:postcode":"4000",
    "sg:province":"QLD",
    "sg:tags":[
        "planning"
    ],
    "wof:name":"Winchcombe Carson Financial Planning Pty Ltd",
    "wof:placetype":"venue"
},
  "geometry": {"coordinates":[153.02565002399999,-27.4694957733],"type":"Point"}
}