{
  "type": "Feature",
  "properties": {
    "addr:full":"6 Railway St Gatton QLD 4343",
    "addr:housenumber":"6",
    "addr:postcode":"4343",
    "addr:street":"Railway St",
    "iso:country":"AU",
    "sg:address":"6 Railway St",
    "sg:city":"Gatton",
    "sg:classifiers":[
        {
            "category":"Travel",
            "subcategory":"Hotels & Motels",
            "type":"Entertainment"
        }
    ],
    "sg:phone":"+61 7 5462 1007",
    "sg:postcode":"4343",
    "sg:province":"QLD",
    "sg:tags":[
        "accommodation"
    ],
    "wof:name":"Federal Hotel",
    "wof:placetype":"venue"
},
  "geometry": {"coordinates":[152.277587891,-27.5557155609],"type":"Point"}
}