{
  "type": "Feature",
  "properties": {
    "iso:country":"AU",
    "sg:address":"Unit 4 326 Logan Rd",
    "sg:city":"Underwood",
    "sg:classifiers":[
        {
            "category":"Professional",
            "subcategory":"Computer Services",
            "type":"Services"
        }
    ],
    "sg:phone":"+61 7 3423 2076",
    "sg:postcode":"4119",
    "sg:province":"QLD",
    "sg:tags":[
        "repairs",
        "upgrade",
        "equipment"
    ],
    "wof:name":"All Inkjet & Laser Repairs",
    "wof:placetype":"venue"
},
  "geometry": {"coordinates":[153.11485290499999,-27.6105422974],"type":"Point"}
}