{
  "type": "Feature",
  "properties": {
    "iso:country":"AU",
    "sg:address":"601 Main Rd",
    "sg:city":"Panton Hill",
    "sg:classifiers":[
        {
            "category":"Education",
            "subcategory":"Kindergarten",
            "type":"Public Place"
        }
    ],
    "sg:phone":"+61 3 9719 7396",
    "sg:postcode":"3759",
    "sg:province":"VIC",
    "sg:tags":[
        "pre-schools"
    ],
    "wof:name":"Panton Hill Pre-School",
    "wof:placetype":"venue"
},
  "geometry": {"coordinates":[145.240005,-37.641701],"type":"Point"}
}