{
  "type": "Feature",
  "properties": {
    "addr:full":"50 Newington Rd Stawell VIC 3380",
    "addr:housenumber":"50",
    "addr:postcode":"3380",
    "addr:street":"Newington Rd",
    "iso:country":"AU",
    "sg:address":"50 Newington Rd",
    "sg:city":"Stawell",
    "sg:classifiers":[
        {
            "category":"Building & Trades",
            "subcategory":"Construction",
            "type":"Services"
        }
    ],
    "sg:phone":"+61 3 5358 1629",
    "sg:postcode":"3380",
    "sg:province":"VIC",
    "sg:tags":[
        "contractor"
    ],
    "wof:name":"Blachford G R",
    "wof:placetype":"venue"
},
  "geometry": {"coordinates":[142.77572631800001,-37.0489501953],"type":"Point"}
}