{
  "type": "Feature",
  "properties": {
    "iso:country":"AU",
    "sg:address":"396 Centre Rd",
    "sg:city":"Bentleigh",
    "sg:classifiers":[
        {
            "category":"Real Estate",
            "subcategory":"Real Estate Agent",
            "type":"Services"
        }
    ],
    "sg:phone":"+61 3 9557 5500",
    "sg:postcode":"3204",
    "sg:province":"VIC",
    "wof:name":"Woodards",
    "wof:placetype":"venue"
},
  "geometry": {"coordinates":[145.03645299999999,-37.918274],"type":"Point"}
}