{
  "type": "Feature",
  "properties": {
    "iso:country":"AU",
    "sg:address":"26 Clements Ave",
    "sg:city":"Bundoora",
    "sg:classifiers":[
        {
            "category":"Retail",
            "subcategory":"Storage",
            "type":"Services"
        }
    ],
    "sg:phone":"+61 3 9466 9455",
    "sg:postcode":"3083",
    "sg:province":"VIC",
    "sg:tags":[
        "removal",
        "furniture"
    ],
    "wof:name":"Whittlesea Removals And Storage",
    "wof:placetype":"venue"
},
  "geometry": {"coordinates":[145.073364258,-37.7027015686],"type":"Point"}
}