{
  "type": "Feature",
  "properties": {
    "addr:full":"Suite 2/ 143 Napier St Essendon VIC 3040",
    "addr:housenumber":"/ 143",
    "addr:postcode":"3040",
    "addr:street":"Napier St",
    "iso:country":"AU",
    "sg:address":"Suite 2/ 143 Napier St",
    "sg:city":"Essendon",
    "sg:classifiers":[
        {
            "category":"Health Services",
            "subcategory":"Doctor",
            "type":"Services"
        }
    ],
    "sg:phone":"+61 3 9326 0545",
    "sg:postcode":"3040",
    "sg:province":"VIC",
    "sg:tags":[
        "medical",
        "practitioner"
    ],
    "wof:name":"Foot Roger",
    "wof:placetype":"venue"
},
  "geometry": {"coordinates":[144.91848754899999,-37.7502555847],"type":"Point"}
}