{
  "type": "Feature",
  "properties": {
    "addr:full":"12 Wright St Busselton WA 6280",
    "addr:housenumber":"12",
    "addr:postcode":"6280",
    "addr:street":"Wright St",
    "iso:country":"AU",
    "sg:address":"12 Wright St",
    "sg:city":"Busselton",
    "sg:classifiers":[
        {
            "category":"Retail",
            "subcategory":"Car Wash",
            "type":"Services"
        }
    ],
    "sg:phone":"+61 8 9751 3007",
    "sg:postcode":"6280",
    "sg:province":"WA",
    "sg:tags":[
        "truck",
        "cleaning"
    ],
    "wof:name":"Busselton Car Detailing",
    "wof:placetype":"venue"
},
  "geometry": {"coordinates":[115.347557068,-33.6652259827],"type":"Point"}
}