{
  "type": "Feature",
  "properties": {
    "addr:full":"52 Kings Park Rd West Perth WA 6005",
    "addr:housenumber":"52",
    "addr:postcode":"6005",
    "addr:street":"Kings Park Rd",
    "iso:country":"AU",
    "sg:address":"52 Kings Park Rd",
    "sg:city":"West Perth",
    "sg:classifiers":[
        {
            "category":"Professional",
            "subcategory":"Accounting & Tax Preparation",
            "type":"Services"
        }
    ],
    "sg:phone":"+61 8 9424 5700",
    "sg:postcode":"6005",
    "sg:province":"WA",
    "sg:tags":[
        "accountant",
        "auditor"
    ],
    "wof:name":"Kirk G G",
    "wof:placetype":"venue"
},
  "geometry": {"coordinates":[115.8359375,-31.9510879517],"type":"Point"}
}