{
  "type": "Feature",
  "properties": {
    "iso:country":"AU",
    "sg:address":"Chandler St",
    "sg:city":"Belconnen",
    "sg:classifiers":[
        {
            "category":"Manufacturing",
            "subcategory":"Food",
            "type":"Manufacturing & Wholesale Goods"
        }
    ],
    "sg:phone":"+61 2 6251 7383",
    "sg:postcode":"2617",
    "sg:province":"ACT",
    "sg:tags":[
        "function",
        "catering"
    ],
    "sg:website":"http://www.connoisseur.com.au",
    "wof:name":"Connoisseur Catering",
    "wof:placetype":"venue"
},
  "geometry": {"coordinates":[149.06747436500001,-35.2376403809],"type":"Point"}
}