{
  "type": "Feature",
  "properties": {
    "addr:full":"40 Coleborn Rd Goondiwindi QLD 4390",
    "addr:housenumber":"40",
    "addr:postcode":"4390",
    "addr:street":"Coleborn Rd",
    "iso:country":"AU",
    "sg:address":"40 Coleborn Rd",
    "sg:city":"Goondiwindi",
    "sg:classifiers":[
        {
            "category":"Home & Garden",
            "subcategory":"Building Materials",
            "type":"Retail Goods"
        }
    ],
    "sg:phone":"+61 7 4671 3897",
    "sg:postcode":"4390",
    "sg:province":"QLD",
    "sg:tags":[
        "lawn",
        "cutting",
        "maintenance"
    ],
    "wof:name":"Quality Lawn Mowing",
    "wof:placetype":"venue"
},
  "geometry": {"coordinates":[150.274780273,-28.5379676819],"type":"Point"}
}