{
  "type": "Feature",
  "properties": {
    "addr:full":"Lot 3/ Laharum Rd Horsham VIC 3400",
    "addr:housenumber":"3 / laharum",
    "addr:postcode":"3400",
    "addr:street":"Rd",
    "iso:country":"AU",
    "sg:address":"Lot 3/ Laharum Rd",
    "sg:city":"Horsham",
    "sg:classifiers":[
        {
            "category":"Building & Trades",
            "subcategory":"Landscaping Services",
            "type":"Services"
        }
    ],
    "sg:phone":"+61 3 5382 6364",
    "sg:postcode":"3400",
    "sg:province":"VIC",
    "sg:tags":[
        "control",
        "weed"
    ],
    "wof:name":"Willspray Spraying Service",
    "wof:placetype":"venue"
},
  "geometry": {"coordinates":[142.19619750999999,-36.7172393799],"type":"Point"}
}