{
  "type": "Feature",
  "properties": {
    "iso:country":"AU",
    "sg:address":"20 Roswell St",
    "sg:city":"Glen Waverley",
    "sg:classifiers":[
        {
            "category":"Professional",
            "subcategory":"Engineering",
            "type":"Services"
        }
    ],
    "sg:phone":"+61 3 9561 8205",
    "sg:postcode":"3150",
    "sg:province":"VIC",
    "sg:tags":[
        "consulting",
        "engineer"
    ],
    "wof:name":"C & S Group Pty Ltd",
    "wof:placetype":"venue"
},
  "geometry": {"coordinates":[145.18609619099999,-37.8829879761],"type":"Point"}
}