{
  "type": "Feature",
  "properties": {
    "addr:full":"20 Fogarty St Alice Springs NT 0870",
    "addr:housenumber":"20",
    "addr:postcode":"nt 0870",
    "addr:street":"Fogarty St",
    "iso:country":"AU",
    "sg:address":"20 Fogarty St",
    "sg:city":"Alice Springs",
    "sg:classifiers":[
        {
            "category":"Building & Trades",
            "subcategory":"Equipment Rental",
            "type":"Services"
        }
    ],
    "sg:phone":"+61 8 8952 1712",
    "sg:postcode":"0870",
    "sg:province":"NT",
    "sg:tags":[
        "party",
        "hire"
    ],
    "wof:name":"Country Coolrooms & Hire",
    "wof:placetype":"venue"
},
  "geometry": {"coordinates":[133.87306213400001,-23.6989955902],"type":"Point"}
}