{
  "type": "Feature",
  "properties": {
    "iso:country":"AU",
    "sg:address":"365-367 Allan St",
    "sg:city":"Kyabram",
    "sg:classifiers":[
        {
            "category":"Retail",
            "subcategory":"Auto Repair",
            "type":"Services"
        }
    ],
    "sg:phone":"+61 3 5853 1555",
    "sg:postcode":"3620",
    "sg:province":"VIC",
    "sg:tags":[
        "repairer",
        "motor",
        "engineer"
    ],
    "wof:name":"Morris Motors",
    "wof:placetype":"venue"
},
  "geometry": {"coordinates":[145.05499267600001,-36.3133125305],"type":"Point"}
}