{
  "type": "Feature",
  "properties": {
    "iso:country":"AU",
    "sg:address":"19- 21 Central Rd",
    "sg:city":"Miranda",
    "sg:classifiers":[
        {
            "category":"Banks & Credit Unions",
            "subcategory":"Financial Services",
            "type":"Services"
        }
    ],
    "sg:phone":"+61 2 9540 5425",
    "sg:postcode":"2228",
    "sg:province":"NSW",
    "sg:tags":[
        "planning"
    ],
    "wof:name":"Zoe Csont",
    "wof:placetype":"venue"
},
  "geometry": {"coordinates":[151.10043335,-34.0332489014],"type":"Point"}
}