{
  "type": "Feature",
  "properties": {
    "addr:full":"PO Box 201 Drayton North QLD 4350",
    "addr:postcode":"4350",
    "iso:country":"AU",
    "sg:address":"PO Box 201",
    "sg:city":"Drayton North",
    "sg:classifiers":[
        {
            "category":"Professional",
            "subcategory":"Computer Services",
            "type":"Services"
        }
    ],
    "sg:phone":"+61 7 4638 5022",
    "sg:postcode":"4350",
    "sg:province":"QLD",
    "sg:tags":[
        "equipment",
        "networking",
        "installation"
    ],
    "wof:name":"Computer Terminal The",
    "wof:placetype":"venue"
},
  "geometry": {"coordinates":[151.92846700000001,-27.57962],"type":"Point"}
}