{
  "type": "Feature",
  "properties": {
    "iso:country":"AU",
    "sg:address":"24 Mountfield Rd",
    "sg:city":"Mitcham",
    "sg:classifiers":[
        {
            "category":"Government",
            "subcategory":"Court House",
            "type":"Public Place"
        }
    ],
    "sg:phone":"+61 3 9874 0408",
    "sg:postcode":"3132",
    "sg:province":"VIC",
    "sg:tags":[
        "personal",
        "marriage",
        "family",
        "counselling"
    ],
    "wof:name":"Come Along Kids Counselling",
    "wof:placetype":"venue"
},
  "geometry": {"coordinates":[145.18736267099999,-37.8073043823],"type":"Point"}
}