{
  "type": "Feature",
  "properties": {
    "addr:full":"124 Shoalhaven Heads Rd Shoalhaven Heads NSW 2535",
    "addr:housenumber":"124",
    "addr:postcode":"2535",
    "addr:street":"Shoalhaven Heads Rd",
    "iso:country":"AU",
    "sg:address":"124 Shoalhaven Heads Rd",
    "sg:city":"Shoalhaven Heads",
    "sg:classifiers":[
        {
            "category":"Real Estate",
            "subcategory":"Real Estate Agent",
            "type":"Services"
        }
    ],
    "sg:phone":"+61 2 4448 8344",
    "sg:postcode":"2535",
    "sg:province":"NSW",
    "wof:name":"Shoalhaven Heads First National",
    "wof:placetype":"venue"
},
  "geometry": {"coordinates":[150.74273681599999,-34.8499107361],"type":"Point"}
}