{
  "type": "Feature",
  "properties": {
    "addr:full":"144 Epping Rd North Ryde NSW 2113",
    "addr:housenumber":"144",
    "addr:postcode":"2113",
    "addr:street":"Epping Rd",
    "iso:country":"AU",
    "sg:address":"144 Epping Rd",
    "sg:city":"North Ryde",
    "sg:classifiers":[
        {
            "category":"Professional",
            "subcategory":"Engineering",
            "type":"Services"
        }
    ],
    "sg:phone":"+61 2 9878 0038",
    "sg:postcode":"2113",
    "sg:province":"NSW",
    "sg:tags":[
        "engineer",
        "structural"
    ],
    "wof:name":"Murdocca & Associates Pty Ltd",
    "wof:placetype":"venue"
},
  "geometry": {"coordinates":[151.12486267099999,-33.7870101929],"type":"Point"}
}