{
  "type": "Feature",
  "properties": {
    "addr:full":"PO Box 7 Adamstown NSW 2289",
    "addr:postcode":"2289",
    "iso:country":"AU",
    "sg:address":"PO Box 7",
    "sg:city":"Adamstown",
    "sg:classifiers":[
        {
            "category":"Arts & Performance",
            "subcategory":"Theater",
            "type":"Entertainment"
        }
    ],
    "sg:phone":"+61 500 588 482",
    "sg:postcode":"2289",
    "sg:province":"NSW",
    "sg:tags":[
        "theatre"
    ],
    "wof:name":"Intimate Theatre Company",
    "wof:placetype":"venue"
},
  "geometry": {"coordinates":[151.72576904300001,-32.9347610474],"type":"Point"}
}