{
  "type": "Feature",
  "properties": {
    "addr:full":"2/ 3 Commerce Drv Browns Plains QLD 4118",
    "addr:housenumber":"/ 3",
    "addr:postcode":"4118",
    "addr:street":"Commerce Drv",
    "iso:country":"AU",
    "sg:address":"2/ 3 Commerce Drv",
    "sg:city":"Browns Plains",
    "sg:classifiers":[
        {
            "category":"Health Services",
            "subcategory":"Doctor",
            "type":"Services"
        }
    ],
    "sg:phone":"+61 7 3800 1611",
    "sg:postcode":"4118",
    "sg:province":"QLD",
    "sg:tags":[
        "medical",
        "practitioner"
    ],
    "wof:name":"Medi Prac Browns Plains",
    "wof:placetype":"venue"
},
  "geometry": {"coordinates":[153.04579162600001,-27.6624279022],"type":"Point"}
}