{
  "type": "Feature",
  "properties": {
    "addr:full":"18 Mialli Pl O'Malley ACT 2606",
    "addr:housenumber":"18",
    "addr:postcode":"2606",
    "addr:street":"Mialli Pl",
    "iso:country":"AU",
    "sg:address":"18 Mialli Pl",
    "sg:city":"O'Malley",
    "sg:classifiers":[
        {
            "category":"Building & Trades",
            "subcategory":"Construction",
            "type":"Services"
        }
    ],
    "sg:phone":"+61 2 6286 3175",
    "sg:postcode":"2606",
    "sg:province":"ACT",
    "sg:tags":[
        "contractor"
    ],
    "wof:name":"Rosa & Sons Investments Pty Ltd",
    "wof:placetype":"venue"
},
  "geometry": {"coordinates":[149.10911560100001,-35.3547172546],"type":"Point"}
}