{
  "type": "Feature",
  "properties": {
    "addr:full":"3 Jinatong St Miranda NSW 2228",
    "addr:housenumber":"3",
    "addr:postcode":"2228",
    "addr:street":"Jinatong St Miranda",
    "iso:country":"AU",
    "sg:address":"3 Jinatong St",
    "sg:city":"Miranda",
    "sg:classifiers":[
        {
            "category":"School Buses",
            "type":"Transportation"
        }
    ],
    "sg:phone":"+61 2 9524 3067",
    "sg:postcode":"2228",
    "sg:province":"NSW",
    "sg:tags":[
        "resistor"
    ],
    "wof:name":"Precision Resistors",
    "wof:placetype":"venue"
},
  "geometry": {"coordinates":[151.095794678,-34.0298156738],"type":"Point"}
}