{
  "type": "Feature",
  "properties": {
    "addr:full":"cnr Leach Highway & Stock Road Willagee WA 6156",
    "addr:postcode":"6156",
    "addr:street":"Cnr Leach Highway & Stock Road",
    "iso:country":"AU",
    "sg:address":"cnr Leach Highway & Stock Road",
    "sg:city":"Willagee",
    "sg:classifiers":[
        {
            "category":"Fast Food",
            "type":"Food & Drink"
        }
    ],
    "sg:phone":"+61 8 9331 6155",
    "sg:postcode":"6156",
    "sg:province":"WA",
    "sg:tags":[
        "away",
        "take"
    ],
    "wof:name":"Charcoal Chicken Express Cafe",
    "wof:placetype":"venue"
},
  "geometry": {"coordinates":[115.804573,-32.04771],"type":"Point"}
}