{
  "type": "Feature",
  "properties": {
    "addr:full":"132 Tolley Rd St Agnes SA 5097",
    "addr:housenumber":"132",
    "addr:postcode":"5097",
    "addr:street":"Tolley Rd",
    "iso:country":"AU",
    "sg:address":"132 Tolley Rd St",
    "sg:city":"Agnes",
    "sg:classifiers":[
        {
            "category":"Retail",
            "subcategory":"Auto Repair",
            "type":"Services"
        }
    ],
    "sg:phone":"+61 8 8264 8350",
    "sg:postcode":"5097",
    "sg:province":"SA",
    "sg:tags":[
        "beater",
        "painter",
        "panel"
    ],
    "wof:name":"Tolley Road Crash Repairs",
    "wof:placetype":"venue"
},
  "geometry": {"coordinates":[138.70698547399999,-34.8336029053],"type":"Point"}
}