{
  "type": "Feature",
  "properties": {
    "addr:full":"160 Russell Ave Dolls Point NSW 2219",
    "addr:housenumber":"160",
    "addr:postcode":"2219",
    "addr:street":"Russell Ave",
    "iso:country":"AU",
    "sg:address":"160 Russell Ave",
    "sg:city":"Dolls Point",
    "sg:classifiers":[
        {
            "category":"Home & Garden",
            "subcategory":"Building Materials",
            "type":"Retail Goods"
        }
    ],
    "sg:phone":"+61 412 355 864",
    "sg:postcode":"2219",
    "sg:province":"NSW",
    "sg:tags":[
        "lawn",
        "cutting",
        "maintenance"
    ],
    "wof:name":"Action Lawnmowing & Gardening",
    "wof:placetype":"venue"
},
  "geometry": {"coordinates":[151.144012,-33.994259],"type":"Point"}
}