{
  "type": "Feature",
  "properties": {
    "addr:full":"29 Grey Gum Rd Taree NSW 2430",
    "addr:housenumber":"29",
    "addr:postcode":"2430",
    "addr:street":"Grey Gum Rd",
    "iso:country":"AU",
    "sg:address":"29 Grey Gum Rd",
    "sg:city":"Taree",
    "sg:classifiers":[
        {
            "category":"Professional",
            "subcategory":"Printing & Photocopies",
            "type":"Services"
        }
    ],
    "sg:phone":"+61 1800 461 800",
    "sg:postcode":"2430",
    "sg:province":"NSW",
    "sg:tags":[
        "screen",
        "printer"
    ],
    "wof:name":"Barrier Screenprints",
    "wof:placetype":"venue"
},
  "geometry": {"coordinates":[152.451324,-31.894018],"type":"Point"}
}