{
  "type": "Feature",
  "properties": {
    "addr:full":"175 Richmond Rd Blacktown NSW 2148",
    "addr:housenumber":"175",
    "addr:postcode":"2148",
    "addr:street":"Richmond Rd",
    "iso:country":"AU",
    "sg:address":"175 Richmond Rd",
    "sg:city":"Blacktown",
    "sg:classifiers":[
        {
            "category":"Food & Beverages",
            "subcategory":"Supermarket",
            "type":"Retail Goods"
        }
    ],
    "sg:phone":"+61 2 9831 4200",
    "sg:postcode":"2148",
    "sg:province":"NSW",
    "sg:tags":[
        "grocery",
        "store"
    ],
    "wof:name":"Quix Food Stores",
    "wof:placetype":"venue"
},
  "geometry": {"coordinates":[150.90153503400001,-33.7633247375],"type":"Point"}
}