{
  "type": "Feature",
  "properties": {
    "addr:full":"Shed 2/ 50 Crawford St Katherine NT 0850",
    "addr:housenumber":"2 / 50",
    "addr:postcode":"nt 0850",
    "addr:street":"Crawford St",
    "iso:country":"AU",
    "sg:address":"Shed 2/ 50 Crawford St",
    "sg:city":"Katherine",
    "sg:classifiers":[
        {
            "category":"Utilities",
            "subcategory":"Telephone",
            "type":"Services"
        }
    ],
    "sg:phone":"+61 8 8971 3391",
    "sg:postcode":"0850",
    "sg:province":"NT",
    "sg:tags":[
        "equipment",
        "system"
    ],
    "wof:name":"NBCommunications",
    "wof:placetype":"venue"
},
  "geometry": {"coordinates":[132.288208,-14.477363],"type":"Point"}
}