{
  "type": "Feature",
  "properties": {
    "addr:full":"36 Grahame Colyer Drv Agnes Water QLD 4677",
    "addr:housenumber":"36",
    "addr:postcode":"4677",
    "addr:street":"Grahame Colyer Drv",
    "iso:country":"AU",
    "sg:address":"36 Grahame Colyer Drv",
    "sg:city":"Agnes Water",
    "sg:classifiers":[
        {
            "category":"Building & Trades",
            "subcategory":"Construction",
            "type":"Services"
        }
    ],
    "sg:phone":"+61 7 4974 9555",
    "sg:postcode":"4677",
    "sg:province":"QLD",
    "sg:tags":[
        "contractor"
    ],
    "wof:name":"Ycc 1770 Construction Pty Ltd",
    "wof:placetype":"venue"
},
  "geometry": {"coordinates":[151.90338134800001,-24.2110652924],"type":"Point"}
}