{
  "type": "Feature",
  "properties": {
    "addr:full":"PO Box 161 Karrinyup WA 6921",
    "addr:postcode":"6921",
    "iso:country":"AU",
    "sg:address":"PO Box 161",
    "sg:city":"Karrinyup",
    "sg:classifiers":[
        {
            "category":"Retail",
            "subcategory":"Storage",
            "type":"Services"
        }
    ],
    "sg:phone":"+61 8 9448 2883",
    "sg:postcode":"6921",
    "sg:province":"WA",
    "sg:tags":[
        "removal",
        "furniture"
    ],
    "wof:name":"A AAABADEN TRANSPORT",
    "wof:placetype":"venue"
},
  "geometry": {"coordinates":[115.78073883099999,-31.8783512115],"type":"Point"}
}