{
  "type": "Feature",
  "properties": {
    "iso:country":"AU",
    "sg:address":"Unit 2/ 16 Taylor St",
    "sg:city":"Albion",
    "sg:classifiers":[
        {
            "category":"Autos & Motor Vehicles",
            "subcategory":"Auto Supplies",
            "type":"Retail Goods"
        }
    ],
    "sg:phone":"+61 7 3852 5377",
    "sg:postcode":"4010",
    "sg:province":"QLD",
    "sg:tags":[
        "wheel",
        "automotive",
        "rim"
    ],
    "wof:name":"Albion Wheel Repairs",
    "wof:placetype":"venue"
},
  "geometry": {"coordinates":[153.04107665999999,-27.4342918396],"type":"Point"}
}