{
  "type": "Feature",
  "properties": {
    "iso:country":"AU",
    "sg:address":"14 Goorawahl Ave",
    "sg:city":"La Perouse",
    "sg:classifiers":[
        {
            "category":"Building & Trades",
            "subcategory":"Pest Control",
            "type":"Services"
        }
    ],
    "sg:phone":"+61 2 9661 4515",
    "sg:postcode":"2036",
    "sg:province":"NSW",
    "wof:name":"Hooroo Pest Control",
    "wof:placetype":"venue"
},
  "geometry": {"coordinates":[151.23294067399999,-33.9867019653],"type":"Point"}
}