{
  "type": "Feature",
  "properties": {
    "addr:full":"20 Wharf St Brisbane QLD 4000",
    "addr:housenumber":"20",
    "addr:postcode":"4000",
    "addr:street":"Wharf St",
    "iso:country":"AU",
    "sg:address":"20 Wharf St",
    "sg:city":"Brisbane",
    "sg:classifiers":[
        {
            "category":"Insurance",
            "subcategory":"Life Insurance",
            "type":"Services"
        }
    ],
    "sg:phone":"+61 411 224 194",
    "sg:postcode":"4000",
    "sg:province":"QLD",
    "wof:name":"World Financial Management",
    "wof:placetype":"venue"
},
  "geometry": {"coordinates":[153.029907227,-27.4654884338],"type":"Point"}
}