{
  "type": "Feature",
  "properties": {
    "addr:full":"PO Box 191 Enmore NSW 2042",
    "addr:postcode":"2042",
    "iso:country":"AU",
    "sg:address":"PO Box 191",
    "sg:city":"Enmore",
    "sg:classifiers":[
        {
            "category":"Home & Garden",
            "subcategory":"Building Materials",
            "type":"Retail Goods"
        }
    ],
    "sg:phone":"+61 411 833 448",
    "sg:postcode":"2042",
    "sg:province":"NSW",
    "sg:tags":[
        "gate"
    ],
    "wof:name":"Sydney Automation Services",
    "wof:placetype":"venue"
},
  "geometry": {"coordinates":[151.17117300000001,-33.899288],"type":"Point"}
}