{
  "type": "Feature",
  "properties": {
    "addr:full":"1650 Creek Rd Carina QLD 4152",
    "addr:housenumber":"1650",
    "addr:postcode":"4152",
    "addr:street":"Creek Rd",
    "iso:country":"AU",
    "sg:address":"1650 Creek Rd",
    "sg:city":"Carina",
    "sg:classifiers":[
        {
            "category":"Building & Trades",
            "subcategory":"Construction",
            "type":"Services"
        }
    ],
    "sg:phone":"+61 403 384 775",
    "sg:postcode":"4152",
    "sg:province":"QLD",
    "sg:tags":[
        "plasterboard",
        "plasterer",
        "fixer"
    ],
    "wof:name":"Sharman W",
    "wof:placetype":"venue"
},
  "geometry": {"coordinates":[153.095214844,-27.4804992676],"type":"Point"}
}