{
  "type": "Feature",
  "properties": {
    "addr:full":"187 Newell St Cairns QLD 4870",
    "addr:housenumber":"187",
    "addr:postcode":"4870",
    "addr:street":"Newell St",
    "iso:country":"AU",
    "sg:address":"187 Newell St",
    "sg:city":"Cairns",
    "sg:classifiers":[
        {
            "category":"Communications",
            "subcategory":"Film & Video Production",
            "type":"Services"
        }
    ],
    "sg:phone":"+61 7 4054 5222",
    "sg:postcode":"4870",
    "sg:province":"QLD",
    "sg:tags":[
        "fan",
        "blower"
    ],
    "wof:name":"Cairns Northern Lights",
    "wof:placetype":"venue"
},
  "geometry": {"coordinates":[145.751876831,-16.9395542145],"type":"Point"}
}