{
  "type": "Feature",
  "properties": {
    "iso:country":"AU",
    "sg:address":"12- 24 Basalt St",
    "sg:city":"Geebung",
    "sg:classifiers":[
        {
            "category":"Professional",
            "subcategory":"Printing & Photocopies",
            "type":"Services"
        }
    ],
    "sg:phone":"+61 7 3216 2500",
    "sg:postcode":"4034",
    "sg:province":"QLD",
    "sg:tags":[
        "laminating"
    ],
    "wof:name":"Busy Bee",
    "wof:placetype":"venue"
},
  "geometry": {"coordinates":[153.050873,-27.364969],"type":"Point"}
}