{
  "type": "Feature",
  "properties": {
    "iso:country":"AU",
    "sg:address":"Ground Level/ 47 Sandy bay Rd",
    "sg:city":"Sandy Bay",
    "sg:classifiers":[
        {
            "category":"Professional",
            "subcategory":"Computer Services",
            "type":"Services"
        }
    ],
    "sg:phone":"+61 3 6224 8011",
    "sg:postcode":"7005",
    "sg:province":"TAS",
    "sg:tags":[
        "scanning",
        "document"
    ],
    "wof:name":"Acrodata",
    "wof:placetype":"venue"
},
  "geometry": {"coordinates":[147.32957458499999,-42.8902206421],"type":"Point"}
}