{
  "type": "Feature",
  "properties": {
    "iso:country":"AU",
    "sg:address":"5 Sheffield St",
    "sg:city":"Bentleigh East",
    "sg:classifiers":[
        {
            "category":"Building & Trades",
            "subcategory":"Plumbing",
            "type":"Services"
        }
    ],
    "sg:phone":"+61 3 9579 5526",
    "sg:postcode":"3165",
    "sg:province":"VIC",
    "sg:tags":[
        "plumber",
        "gasfitters"
    ],
    "wof:name":"Stevens Trevor Plumbing",
    "wof:placetype":"venue"
},
  "geometry": {"coordinates":[145.0703125,-37.920085907],"type":"Point"}
}