{
  "type": "Feature",
  "properties": {
    "addr:full":"12 Pine Pl Queanbeyan NSW 2620",
    "addr:housenumber":"12",
    "addr:postcode":"2620",
    "addr:street":"Pine Pl",
    "iso:country":"AU",
    "sg:address":"12 Pine Pl",
    "sg:city":"Queanbeyan",
    "sg:classifiers":[
        {
            "category":"Building & Trades",
            "subcategory":"Plumbing",
            "type":"Services"
        }
    ],
    "sg:phone":"+61 2 6297 6583",
    "sg:postcode":"2620",
    "sg:province":"NSW",
    "sg:tags":[
        "plumber",
        "gasfitters"
    ],
    "wof:name":"Buckley John",
    "wof:placetype":"venue"
},
  "geometry": {"coordinates":[149.22496032699999,-35.3769226074],"type":"Point"}
}