{
  "type": "Feature",
  "properties": {
    "addr:full":"183 Bridge St Oakey QLD 4401",
    "addr:housenumber":"183",
    "addr:postcode":"4401",
    "addr:street":"Bridge St",
    "iso:country":"AU",
    "sg:address":"183 Bridge St",
    "sg:city":"Oakey",
    "sg:classifiers":[
        {
            "category":"Professional",
            "subcategory":"Detective & Security Services",
            "type":"Services"
        }
    ],
    "sg:phone":"+61 7 4691 2587",
    "sg:postcode":"4401",
    "sg:province":"QLD",
    "sg:tags":[
        "equipment",
        "window",
        "doors"
    ],
    "wof:name":"Wolski Glass & Security",
    "wof:placetype":"venue"
},
  "geometry": {"coordinates":[151.71072387699999,-27.4271316528],"type":"Point"}
}