{
  "type": "Feature",
  "properties": {
    "addr:full":"13 Durham Rd Bayswater WA 6053",
    "addr:housenumber":"13",
    "addr:postcode":"6053",
    "addr:street":"Durham Rd",
    "iso:country":"AU",
    "sg:address":"13 Durham Rd",
    "sg:city":"Bayswater",
    "sg:classifiers":[
        {
            "category":"School Buses",
            "type":"Transportation"
        }
    ],
    "sg:phone":"+61 8 9370 1833",
    "sg:postcode":"6053",
    "sg:province":"WA",
    "sg:tags":[
        "brick"
    ],
    "wof:name":"Civil & Demo Pty Ltd",
    "wof:placetype":"venue"
},
  "geometry": {"coordinates":[115.921012878,-31.9178581238],"type":"Point"}
}