{
  "type": "Feature",
  "properties": {
    "iso:country":"AU",
    "sg:address":"29 Goderich St",
    "sg:city":"East Perth",
    "sg:classifiers":[
        {
            "category":"Travel",
            "subcategory":"Hostel",
            "type":"Entertainment"
        }
    ],
    "sg:phone":"+61 8 9325 1063",
    "sg:postcode":"6004",
    "sg:province":"WA",
    "sg:tags":[
        "home"
    ],
    "wof:name":"Archbishop Goody Hostel",
    "wof:placetype":"venue"
},
  "geometry": {"coordinates":[115.875221252,-31.9583320618],"type":"Point"}
}