{
  "type": "Feature",
  "properties": {
    "iso:country":"AU",
    "sg:address":"104 Lugarno Pde",
    "sg:city":"Lugarno",
    "sg:classifiers":[
        {
            "category":"Building & Trades",
            "subcategory":"Landscaping Services",
            "type":"Services"
        }
    ],
    "sg:phone":"+61 2 9533 1656",
    "sg:postcode":"2210",
    "sg:province":"NSW",
    "sg:tags":[
        "designer",
        "landscape",
        "contractor"
    ],
    "wof:name":"Mary Moodie's Consultancy Services",
    "wof:placetype":"venue"
},
  "geometry": {"coordinates":[151.03804,-33.989223],"type":"Point"}
}