{
  "type": "Feature",
  "properties": {
    "addr:full":"12/ 380 Nepean Hwy Frankston VIC 3199",
    "addr:housenumber":"12 / 380",
    "addr:postcode":"3199",
    "addr:street":"Nepean Hwy",
    "iso:country":"AU",
    "sg:address":"12/ 380 Nepean Hwy",
    "sg:city":"Frankston",
    "sg:classifiers":[
        {
            "category":"Professional",
            "subcategory":"Art Services",
            "type":"Services"
        }
    ],
    "sg:phone":"+61 3 9781 3075",
    "sg:postcode":"3199",
    "sg:province":"VIC",
    "sg:tags":[
        "interior",
        "decorator"
    ],
    "wof:name":"Lindsey Glover",
    "wof:placetype":"venue"
},
  "geometry": {"coordinates":[145.081939697,-37.9926261902],"type":"Point"}
}