{
  "type": "Feature",
  "properties": {
    "addr:full":"Shop 16 Charlestown Square Charlestown NSW 2290",
    "addr:housenumber":"shop 16",
    "addr:postcode":"2290",
    "addr:street":"Charlestown Square",
    "iso:country":"AU",
    "sg:address":"Shop 16 Charlestown Square",
    "sg:city":"Charlestown",
    "sg:classifiers":[
        {
            "category":"Health Services",
            "subcategory":"Optometrist",
            "type":"Services"
        }
    ],
    "sg:phone":"+61 2 4943 0744",
    "sg:postcode":"2290",
    "sg:province":"NSW",
    "wof:name":"Eyecare Plus Optometrists",
    "wof:placetype":"venue"
},
  "geometry": {"coordinates":[151.68577575699999,-32.9548149109],"type":"Point"}
}