{
  "type": "Feature",
  "properties": {
    "addr:full":"203 Scenic Crs Eltham North VIC 3095",
    "addr:housenumber":"203",
    "addr:postcode":"3095",
    "addr:street":"Scenic Crs",
    "iso:country":"AU",
    "sg:address":"203 Scenic Crs",
    "sg:city":"Eltham North",
    "sg:classifiers":[
        {
            "category":"Health Services",
            "subcategory":"Health Practitioner",
            "type":"Services"
        }
    ],
    "sg:phone":"+61 414 700 238",
    "sg:postcode":"3095",
    "sg:province":"VIC",
    "sg:tags":[
        "myotherapy"
    ],
    "wof:name":"Christine Domino",
    "wof:placetype":"venue"
},
  "geometry": {"coordinates":[145.144256592,-37.690448761],"type":"Point"}
}