{
  "type": "Feature",
  "properties": {
    "iso:country":"AU",
    "sg:address":"4 Duckenfield Rd",
    "sg:city":"Morpeth",
    "sg:classifiers":[
        {
            "category":"Commercial Area",
            "type":"Public Place"
        }
    ],
    "sg:phone":"+61 2 4933 6295",
    "sg:postcode":"2321",
    "sg:province":"NSW",
    "sg:tags":[
        "heavy",
        "carrier"
    ],
    "wof:name":"Crawley J J & G L & Sons Pty Ltd",
    "wof:placetype":"venue"
},
  "geometry": {"coordinates":[151.637619019,-32.7300453186],"type":"Point"}
}