{
  "type": "Feature",
  "properties": {
    "addr:full":"26 Mirnoo St Currimundi QLD 4551",
    "addr:housenumber":"26",
    "addr:postcode":"4551",
    "addr:street":"Mirnoo St",
    "iso:country":"AU",
    "sg:address":"26 Mirnoo St",
    "sg:city":"Currimundi",
    "sg:classifiers":[
        {
            "category":"Building & Trades",
            "subcategory":"Construction",
            "type":"Services"
        }
    ],
    "sg:phone":"+61 7 5499 7009",
    "sg:postcode":"4551",
    "sg:province":"QLD",
    "sg:tags":[
        "home",
        "air conditioning"
    ],
    "wof:name":"McNicol Air Conditioning Pty Ltd",
    "wof:placetype":"venue"
},
  "geometry": {"coordinates":[153.12577819800001,-26.7695922852],"type":"Point"}
}