{
  "type": "Feature",
  "properties": {
    "addr:full":"319 Parramatta Rd Leichhardt NSW 2040",
    "addr:housenumber":"319",
    "addr:postcode":"2040",
    "addr:street":"Parramatta Rd",
    "iso:country":"AU",
    "sg:address":"319 Parramatta Rd",
    "sg:city":"Leichhardt",
    "sg:classifiers":[
        {
            "category":"Professional",
            "subcategory":"Art Services",
            "type":"Services"
        }
    ],
    "sg:phone":"+61 2 9518 0121",
    "sg:postcode":"2040",
    "sg:province":"NSW",
    "sg:tags":[
        "picture",
        "frame",
        "framing"
    ],
    "wof:name":"Piscean Gallery",
    "wof:placetype":"venue"
},
  "geometry": {"coordinates":[151.16055299999999,-33.88768],"type":"Point"}
}