{
  "type": "Feature",
  "properties": {
    "addr:full":"Shop 3 497 Princes Hwy Noble Park VIC 3174",
    "addr:housenumber":"shop 3 497",
    "addr:postcode":"3174",
    "addr:street":"Princes Hwy",
    "iso:country":"AU",
    "sg:address":"Shop 3 497 Princes Hwy",
    "sg:city":"Noble Park",
    "sg:classifiers":[
        {
            "category":"Food & Beverages",
            "subcategory":"Bakery",
            "type":"Retail Goods"
        }
    ],
    "sg:phone":"+61 3 9546 5987",
    "sg:postcode":"3174",
    "sg:province":"VIC",
    "sg:tags":[
        "baker"
    ],
    "wof:name":"P.J.S Hot Bread & Cakes",
    "wof:placetype":"venue"
},
  "geometry": {"coordinates":[145.179763794,-37.9543952942],"type":"Point"}
}