{
  "type": "Feature",
  "properties": {
    "addr:full":"3/ 36 Victoria St Gosford East NSW 2250",
    "addr:housenumber":"/ 36",
    "addr:postcode":"2250",
    "addr:street":"Victoria St",
    "iso:country":"AU",
    "sg:address":"3/ 36 Victoria St",
    "sg:city":"Gosford East",
    "sg:classifiers":[
        {
            "category":"Banks & Credit Unions",
            "subcategory":"Financial Services",
            "type":"Services"
        }
    ],
    "sg:phone":"+61 2 4324 6311",
    "sg:postcode":"2250",
    "sg:province":"NSW",
    "sg:tags":[
        "planning"
    ],
    "wof:name":"MCS Financial Advisers Pty Ltd",
    "wof:placetype":"venue"
},
  "geometry": {"coordinates":[151.35401916500001,-33.4385375977],"type":"Point"}
}