{
  "type": "Feature",
  "properties": {
    "iso:country":"AU",
    "sg:address":"7 Harbourview St",
    "sg:city":"Lennox Head",
    "sg:classifiers":[
        {
            "category":"Building & Trades",
            "subcategory":"Construction",
            "type":"Services"
        }
    ],
    "sg:phone":"+61 415 664 942",
    "sg:postcode":"2478",
    "sg:province":"NSW",
    "sg:tags":[
        "scaffolding"
    ],
    "wof:name":"Tweed Coast Scaffolding",
    "wof:placetype":"venue"
},
  "geometry": {"coordinates":[153.592193603,-28.8664531708],"type":"Point"}
}