{
  "type": "Feature",
  "properties": {
    "addr:full":"Level 3 99 Creek St Brisbane QLD 4000",
    "addr:housenumber":"99",
    "addr:postcode":"4000",
    "addr:street":"Creek St",
    "iso:country":"AU",
    "sg:address":"Level 3 99 Creek St",
    "sg:city":"Brisbane",
    "sg:classifiers":[
        {
            "category":"Professional",
            "subcategory":"Business Services",
            "type":"Services"
        }
    ],
    "sg:phone":"+61 7 3221 3860",
    "sg:postcode":"4000",
    "sg:province":"QLD",
    "sg:tags":[
        "consultant",
        "leasing"
    ],
    "wof:name":"Financial Solutions Pty Ltd",
    "wof:placetype":"venue"
},
  "geometry": {"coordinates":[153.02828979500001,-27.4664268494],"type":"Point"}
}