{
  "type": "Feature",
  "properties": {
    "iso:country":"AU",
    "sg:address":"359 Odin Drv",
    "sg:city":"Balcatta",
    "sg:classifiers":[
        {
            "category":"Building & Trades",
            "subcategory":"Pest Control",
            "type":"Services"
        }
    ],
    "sg:phone":"+61 412 028 699",
    "sg:postcode":"6021",
    "sg:province":"WA",
    "wof:name":"Carousel Pest Control Pty Ltd",
    "wof:placetype":"venue"
},
  "geometry": {"coordinates":[115.807098389,-31.8674201965],"type":"Point"}
}