{
  "type": "Feature",
  "properties": {
    "addr:full":"201 Sandgate Rd Albion QLD 4010",
    "addr:housenumber":"201",
    "addr:postcode":"4010",
    "addr:street":"Sandgate Rd",
    "iso:country":"AU",
    "sg:address":"201 Sandgate Rd",
    "sg:city":"Albion",
    "sg:classifiers":[
        {
            "category":"Professional",
            "subcategory":"Art Services",
            "type":"Services"
        }
    ],
    "sg:phone":"+61 7 3262 8233",
    "sg:postcode":"4010",
    "sg:province":"QLD",
    "sg:tags":[
        "decorator",
        "painter"
    ],
    "sg:website":"http://www.rochelepainting.com.au",
    "wof:name":"Rochele Painting",
    "wof:placetype":"venue"
},
  "geometry": {"coordinates":[153.04255676299999,-27.4315261841],"type":"Point"}
}