{
  "type": "Feature",
  "properties": {
    "addr:full":"24 Katrina Crs South Kolan QLD 4670",
    "addr:housenumber":"24",
    "addr:postcode":"4670",
    "addr:street":"Katrina Crs",
    "iso:country":"AU",
    "sg:address":"24 Katrina Crs",
    "sg:city":"South Kolan",
    "sg:classifiers":[
        {
            "category":"Manufacturing",
            "subcategory":"Motor Vehicles & Parts",
            "type":"Manufacturing & Wholesale Goods"
        }
    ],
    "sg:phone":"+61 7 4157 7307",
    "sg:postcode":"4670",
    "sg:province":"QLD",
    "sg:tags":[
        "replacement"
    ],
    "wof:name":"Petrol Heads Performance Australia",
    "wof:placetype":"venue"
},
  "geometry": {"coordinates":[152.34210205100001,-24.8605670929],"type":"Point"}
}