{
  "type": "Feature",
  "properties": {
    "iso:country":"AU",
    "sg:address":"Unit 2/ 145 Tolley Rd",
    "sg:city":"St Agnes",
    "sg:classifiers":[
        {
            "category":"Landmark",
            "subcategory":"Scenic View",
            "type":"Public Place"
        }
    ],
    "sg:phone":"+61 8 8395 9411",
    "sg:postcode":"5097",
    "sg:province":"SA",
    "sg:tags":[
        "staircase",
        "handrail"
    ],
    "wof:name":"Absolute Stainless & Aluminium",
    "wof:placetype":"venue"
},
  "geometry": {"coordinates":[138.70680236800001,-34.8275413513],"type":"Point"}
}