{
  "type": "Feature",
  "properties": {
    "addr:full":"Stuart St Helensburgh Helensburgh NSW 2508",
    "addr:postcode":"2508",
    "addr:street":"Stuart St",
    "iso:country":"AU",
    "sg:address":"Stuart St",
    "sg:city":"Helensburgh Helensburgh",
    "sg:classifiers":[
        {
            "category":"Building & Trades",
            "subcategory":"Construction",
            "type":"Services"
        }
    ],
    "sg:phone":"+61 417 941 030",
    "sg:postcode":"2508",
    "sg:province":"NSW",
    "sg:tags":[
        "fencing",
        "contractor"
    ],
    "wof:name":"Helensburg Fencing Services",
    "wof:placetype":"venue"
},
  "geometry": {"coordinates":[150.980423,-34.191723],"type":"Point"}
}