{
  "type": "Feature",
  "properties": {
    "addr:full":"2084 Logan Rd Mt Gravatt QLD 4122",
    "addr:housenumber":"2084",
    "addr:postcode":"4122",
    "addr:street":"Logan Rd",
    "iso:country":"AU",
    "sg:address":"2084 Logan Rd",
    "sg:city":"Mt Gravatt",
    "sg:classifiers":[
        {
            "category":"Health Services",
            "subcategory":"Chiropractor",
            "type":"Services"
        }
    ],
    "sg:phone":"+61 7 3349 0005",
    "sg:postcode":"4122",
    "sg:province":"QLD",
    "wof:name":"Blitz Wellness",
    "wof:placetype":"venue"
},
  "geometry": {"coordinates":[153.08224487300001,-27.5605392456],"type":"Point"}
}