{
  "type": "Feature",
  "properties": {
    "addr:full":"6 Summer St Orange NSW 2800",
    "addr:housenumber":"6",
    "addr:postcode":"2800",
    "addr:street":"Summer St",
    "iso:country":"AU",
    "sg:address":"6 Summer St",
    "sg:city":"Orange",
    "sg:classifiers":[
        {
            "category":"Professional",
            "subcategory":"Computer Services",
            "type":"Services"
        }
    ],
    "sg:phone":"+61 402 213 660",
    "sg:postcode":"2800",
    "sg:province":"NSW",
    "sg:tags":[
        "repairs",
        "upgrade",
        "equipment"
    ],
    "wof:name":"Mobile PC Repairs",
    "wof:placetype":"venue"
},
  "geometry": {"coordinates":[149.090087891,-33.2820968628],"type":"Point"}
}