{
  "type": "Feature",
  "properties": {
    "iso:country":"AU",
    "sg:address":"61 Main St",
    "sg:city":"Woodside",
    "sg:classifiers":[
        {
            "category":"Professional",
            "subcategory":"Accounting & Tax Preparation",
            "type":"Services"
        }
    ],
    "sg:phone":"+61 8 8389 7077",
    "sg:postcode":"5244",
    "sg:province":"SA",
    "sg:tags":[
        "accountant",
        "auditor"
    ],
    "wof:name":"Brauer, Lian, Ho & Chong",
    "wof:placetype":"venue"
},
  "geometry": {"coordinates":[138.87457275400001,-34.9038925171],"type":"Point"}
}