{
  "type": "Feature",
  "properties": {
    "addr:full":"122 Adelaide St Maryborough QLD 4650",
    "addr:housenumber":"122",
    "addr:postcode":"4650",
    "addr:street":"Adelaide St",
    "iso:country":"AU",
    "sg:address":"122 Adelaide St",
    "sg:city":"Maryborough",
    "sg:classifiers":[
        {
            "category":"Real Estate",
            "subcategory":"Real Estate Agent",
            "type":"Services"
        }
    ],
    "sg:phone":"+61 7 4123 3500",
    "sg:postcode":"4650",
    "sg:province":"QLD",
    "wof:name":"Harcourts",
    "wof:placetype":"venue"
},
  "geometry": {"coordinates":[152.69987499999999,-25.540472],"type":"Point"}
}