{
  "type": "Feature",
  "properties": {
    "addr:full":"Wellington Mill Rd Dardanup WA 6236",
    "addr:postcode":"6236",
    "addr:street":"Mill Rd",
    "iso:country":"AU",
    "sg:address":"Wellington Mill Rd",
    "sg:city":"Dardanup",
    "sg:classifiers":[
        {
            "category":"Professional",
            "subcategory":"Art Services",
            "type":"Services"
        }
    ],
    "sg:phone":"+61 8 9728 3003",
    "sg:postcode":"6236",
    "sg:province":"WA",
    "sg:tags":[
        "artist"
    ],
    "wof:name":"Joyce Hatchett",
    "wof:placetype":"venue"
},
  "geometry": {"coordinates":[115.858322,-33.44743],"type":"Point"}
}