{
  "type": "Feature",
  "properties": {
    "addr:full":"328a Invermay Rd Launceston TAS 7250",
    "addr:housenumber":"328a",
    "addr:postcode":"7250",
    "addr:street":"Invermay Rd",
    "iso:country":"AU",
    "sg:address":"328a Invermay Rd",
    "sg:city":"Launceston",
    "sg:classifiers":[
        {
            "category":"Manufacturing",
            "subcategory":"Rubber & Plastics",
            "type":"Manufacturing & Wholesale Goods"
        }
    ],
    "sg:phone":"+61 1800 802 978",
    "sg:postcode":"7250",
    "sg:province":"TAS",
    "sg:tags":[
        "wholesaler",
        "product",
        "mfrs"
    ],
    "wof:name":"Ormiston Industrial Rubber",
    "wof:placetype":"venue"
},
  "geometry": {"coordinates":[147.1302948,-41.4010696411],"type":"Point"}
}