{
  "type": "Feature",
  "properties": {
    "iso:country":"AU",
    "sg:address":"149 Green St",
    "sg:city":"Ivanhoe",
    "sg:classifiers":[
        {
            "category":"Wholesale",
            "subcategory":"Painting Supplies",
            "type":"Manufacturing & Wholesale Goods"
        }
    ],
    "sg:phone":"+61 3 9499 6826",
    "sg:postcode":"3079",
    "sg:province":"VIC",
    "sg:tags":[
        "product",
        "cleaning"
    ],
    "wof:name":"Swipe & Naturcare",
    "wof:placetype":"venue"
},
  "geometry": {"coordinates":[145.02854919399999,-37.7634010315],"type":"Point"}
}