{
  "type": "Feature",
  "properties": {
    "addr:full":"229 High St Ashburton VIC 3147",
    "addr:housenumber":"229",
    "addr:postcode":"3147",
    "addr:street":"High St",
    "iso:country":"AU",
    "sg:address":"229 High St",
    "sg:city":"Ashburton",
    "sg:classifiers":[
        {
            "category":"Deli",
            "type":"Food & Drink"
        }
    ],
    "sg:phone":"+61 3 9885 1808",
    "sg:postcode":"3147",
    "sg:province":"VIC",
    "sg:tags":[
        "delicatessen"
    ],
    "wof:name":"Corner Deli & Gourmet Sandwich Bar",
    "wof:placetype":"venue"
},
  "geometry": {"coordinates":[145.07806396500001,-37.863079071],"type":"Point"}
}