{
  "type": "Feature",
  "properties": {
    "addr:full":"27- 33 Endurance Ave Queanbeyan NSW 2620",
    "addr:housenumber":"33",
    "addr:postcode":"2620",
    "addr:street":"Endurance Ave",
    "iso:country":"AU",
    "sg:address":"27- 33 Endurance Ave",
    "sg:city":"Queanbeyan",
    "sg:classifiers":[
        {
            "category":"Wholesale",
            "subcategory":"Metals & Minerals",
            "type":"Manufacturing & Wholesale Goods"
        }
    ],
    "sg:phone":"+61 2 6297 5533",
    "sg:postcode":"2620",
    "sg:province":"NSW",
    "sg:tags":[
        "steel",
        "merchant"
    ],
    "wof:name":"OneSteel Metaland",
    "wof:placetype":"venue"
},
  "geometry": {"coordinates":[149.24783325199999,-35.3402023315],"type":"Point"}
}