{
  "type": "Feature",
  "properties": {
    "addr:full":"83 McDouall Stuart Ave Whyalla Stuart SA 5608",
    "addr:housenumber":"83",
    "addr:postcode":"5608",
    "addr:street":"Mcdouall Stuart Ave",
    "iso:country":"AU",
    "sg:address":"83 McDouall Stuart Ave",
    "sg:city":"Whyalla Stuart",
    "sg:classifiers":[
        {
            "category":"Health Services",
            "subcategory":"Chiropractor",
            "type":"Services"
        }
    ],
    "sg:phone":"+61 8 8645 3897",
    "sg:postcode":"5608",
    "sg:province":"SA",
    "wof:name":"Whyalla Family Corrective Chiropractic",
    "wof:placetype":"venue"
},
  "geometry": {"coordinates":[137.52972399999999,-33.028519],"type":"Point"}
}