{
  "type": "Feature",
  "properties": {
    "addr:full":"13 Great Alpine Rd Bright VIC 3741",
    "addr:housenumber":"13",
    "addr:postcode":"3741",
    "addr:street":"Great Alpine Rd",
    "iso:country":"AU",
    "sg:address":"13 Great Alpine Rd",
    "sg:city":"Bright",
    "sg:classifiers":[
        {
            "category":"Travel",
            "subcategory":"Hotels & Motels",
            "type":"Entertainment"
        }
    ],
    "sg:phone":"+61 3 5755 1244",
    "sg:postcode":"3741",
    "sg:province":"VIC",
    "wof:name":"High Country Motor Inn",
    "wof:placetype":"venue"
},
  "geometry": {"coordinates":[146.943039,-36.721279],"type":"Point"}
}