{
  "type": "Feature",
  "properties": {
    "iso:country":"AU",
    "sg:address":"2 Hawthorn Crt",
    "sg:city":"Keilor East",
    "sg:classifiers":[
        {
            "category":"Utilities",
            "subcategory":"Electric",
            "type":"Services"
        }
    ],
    "sg:phone":"+61 418 348 729",
    "sg:postcode":"3033",
    "sg:province":"VIC",
    "sg:tags":[
        "electrical",
        "contractor"
    ],
    "wof:name":"Said Electrics",
    "wof:placetype":"venue"
},
  "geometry": {"coordinates":[144.849457,-37.746113],"type":"Point"}
}