{
  "type": "Feature",
  "properties": {
    "iso:country":"AU",
    "sg:address":"Unit 11 & 12 / 27- 29 South Pine Road",
    "sg:city":"Strathpine",
    "sg:classifiers":[
        {
            "category":"Real Estate",
            "subcategory":"Surveying",
            "type":"Services"
        }
    ],
    "sg:phone":"+61 7 3881 1969",
    "sg:postcode":"4500",
    "sg:province":"QLD",
    "sg:tags":[
        "geophysicist"
    ],
    "wof:name":"Precision Energy Services (Australia) Pty Ltd",
    "wof:placetype":"venue"
},
  "geometry": {"coordinates":[152.989700317,-27.3123474121],"type":"Point"}
}