{
  "type": "Feature",
  "properties": {
    "iso:country":"AU",
    "sg:address":"1- 9 Pintu St",
    "sg:city":"Loganholme",
    "sg:classifiers":[
        {
            "category":"Building & Trades",
            "subcategory":"Construction",
            "type":"Services"
        }
    ],
    "sg:phone":"+61 7 3806 4491",
    "sg:postcode":"4129",
    "sg:province":"QLD",
    "sg:tags":[
        "fencing",
        "contractor"
    ],
    "wof:name":"All Fencing & Landscaping",
    "wof:placetype":"venue"
},
  "geometry": {"coordinates":[153.185455322,-27.6672172546],"type":"Point"}
}