{
  "type": "Feature",
  "properties": {
    "addr:full":"96 Goodwood Pde Burswood WA 6100",
    "addr:housenumber":"96",
    "addr:postcode":"6100",
    "addr:street":"Goodwood Pde",
    "iso:country":"AU",
    "sg:address":"96 Goodwood Pde",
    "sg:city":"Burswood",
    "sg:classifiers":[
        {
            "category":"Building & Trades",
            "subcategory":"Equipment Rental",
            "type":"Services"
        }
    ],
    "sg:phone":"+61 8 9361 2442",
    "sg:postcode":"6100",
    "sg:province":"WA",
    "sg:tags":[
        "saw"
    ],
    "wof:name":"Geocam",
    "wof:placetype":"venue"
},
  "geometry": {"coordinates":[115.900680542,-31.9593925476],"type":"Point"}
}