{
  "type": "Feature",
  "properties": {
    "addr:full":"160 Charles St (Cnr Elizabeth St) Launceston TAS 7250",
    "addr:housenumber":"160",
    "addr:postcode":"7250",
    "addr:street":"Charles St Cnr Elizabeth St",
    "iso:country":"AU",
    "sg:address":"160 Charles St (Cnr Elizabeth St)",
    "sg:city":"Launceston",
    "sg:classifiers":[
        {
            "category":"Health Services",
            "subcategory":"Clinic",
            "type":"Services"
        }
    ],
    "sg:phone":"+61 3 6334 4823",
    "sg:postcode":"7250",
    "sg:province":"TAS",
    "sg:tags":[
        "aromatherapy"
    ],
    "wof:name":"Tasmanian Wildflower Essences",
    "wof:placetype":"venue"
},
  "geometry": {"coordinates":[147.13914489699999,-41.4402046204],"type":"Point"}
}