{
  "type": "Feature",
  "properties": {
    "addr:full":"121/ 350 St Kilda Rd Melbourne VIC 3004",
    "addr:housenumber":"121 / 350",
    "addr:postcode":"3004",
    "addr:street":"St Kilda Rd",
    "iso:country":"AU",
    "sg:address":"121/ 350 St Kilda Rd",
    "sg:city":"Melbourne",
    "sg:classifiers":[
        {
            "category":"Professional",
            "subcategory":"Management & Consulting",
            "type":"Services"
        }
    ],
    "sg:phone":"+61 411 103 995",
    "sg:postcode":"3004",
    "sg:province":"VIC",
    "sg:tags":[
        "consultant"
    ],
    "wof:name":"DHA Consulting Group Pty Ltd",
    "wof:placetype":"venue"
},
  "geometry": {"coordinates":[144.97102355999999,-37.8308334351],"type":"Point"}
}