{
  "type": "Feature",
  "properties": {
    "iso:country":"AU",
    "sg:address":"28 Kriesch Rd",
    "sg:city":"Samsonvale",
    "sg:classifiers":[
        {
            "category":"Retail",
            "subcategory":"Repair Shop",
            "type":"Services"
        }
    ],
    "sg:phone":"+61 7 3289 9924",
    "sg:postcode":"4520",
    "sg:province":"QLD",
    "sg:tags":[
        "upholsterer"
    ],
    "wof:name":"Adam Turnell's Upholstery Samsonvale",
    "wof:placetype":"venue"
},
  "geometry": {"coordinates":[152.843719,-27.280249],"type":"Point"}
}