{
  "type": "Feature",
  "properties": {
    "iso:country":"AU",
    "sg:address":"215 Wattle St",
    "sg:city":"Bankstown",
    "sg:classifiers":[
        {
            "category":"Home & Garden",
            "subcategory":"Carpets & Floor Coverings",
            "type":"Retail Goods"
        }
    ],
    "sg:phone":"+61 2 9790 3028",
    "sg:postcode":"2200",
    "sg:province":"NSW",
    "sg:tags":[
        "tile",
        "wall",
        "layer"
    ],
    "wof:name":"Beaven P J",
    "wof:placetype":"venue"
},
  "geometry": {"coordinates":[151.044006,-33.91713],"type":"Point"}
}