{
  "type": "Feature",
  "properties": {
    "iso:country":"AU",
    "sg:address":"14 Wellington Drv",
    "sg:city":"Traralgon",
    "sg:classifiers":[
        {
            "category":"Home & Garden",
            "subcategory":"Carpets & Floor Coverings",
            "type":"Retail Goods"
        }
    ],
    "sg:phone":"+61 3 5174 8196",
    "sg:postcode":"3844",
    "sg:province":"VIC",
    "sg:tags":[
        "layer"
    ],
    "wof:name":"GA & DC Harding Pty Ltd",
    "wof:placetype":"venue"
},
  "geometry": {"coordinates":[146.51423645,-38.179271698],"type":"Point"}
}