{
  "type": "Feature",
  "properties": {
    "addr:full":"23 Bevan St Greenock SA 5360",
    "addr:housenumber":"23",
    "addr:postcode":"5360",
    "addr:street":"Bevan St Greenock",
    "iso:country":"AU",
    "sg:address":"23 Bevan St",
    "sg:city":"Greenock",
    "sg:classifiers":[
        {
            "category":"Wholesale",
            "subcategory":"Apparel",
            "type":"Manufacturing & Wholesale Goods"
        }
    ],
    "sg:phone":"+61 8 8562 8418",
    "sg:postcode":"5360",
    "sg:province":"SA",
    "sg:tags":[
        "wholesaler",
        "mfrs",
        "uniform"
    ],
    "wof:name":"A Cottage Affair",
    "wof:placetype":"venue"
},
  "geometry": {"coordinates":[138.924026489,-34.4581756592],"type":"Point"}
}