{
  "type": "Feature",
  "properties": {
    "addr:full":"102 Forrester Rd St Marys NSW 2760",
    "addr:housenumber":"102",
    "addr:postcode":"2760",
    "addr:street":"Forrester Rd",
    "iso:country":"AU",
    "sg:address":"102 Forrester Rd",
    "sg:city":"St Marys",
    "sg:classifiers":[
        {
            "category":"Building & Trades",
            "subcategory":"Equipment Rental",
            "type":"Services"
        }
    ],
    "sg:phone":"+61 2 9623 8000",
    "sg:postcode":"2760",
    "sg:province":"NSW",
    "sg:tags":[
        "renting",
        "trailer"
    ],
    "wof:name":"Kennards Trailer Hire",
    "wof:placetype":"venue"
},
  "geometry": {"coordinates":[150.775466919,-33.7563323975],"type":"Point"}
}