{
  "type": "Feature",
  "properties": {
    "iso:country":"AU",
    "sg:address":"PO Box 284",
    "sg:city":"Goodna",
    "sg:classifiers":[
        {
            "category":"Professional",
            "subcategory":"Engineering",
            "type":"Services"
        }
    ],
    "sg:phone":"+61 7 3271 3459",
    "sg:postcode":"4300",
    "sg:province":"QLD",
    "sg:tags":[
        "engineer"
    ],
    "sg:website":"http://www.turningandtooling.com.au",
    "wof:name":"J.G. Turning & Tooling Pty Limited",
    "wof:placetype":"venue"
},
  "geometry": {"coordinates":[152.938232422,-27.6217727661],"type":"Point"}
}