{
  "type": "Feature",
  "properties": {
    "iso:country":"AU",
    "sg:address":"Unit D, Harvey Norman Centre, Mulgoa Rd",
    "sg:city":"Penrith",
    "sg:classifiers":[
        {
            "category":"Manufacturing",
            "subcategory":"Textiles",
            "type":"Manufacturing & Wholesale Goods"
        }
    ],
    "sg:phone":"+61 2 4733 2800",
    "sg:postcode":"2740",
    "sg:province":"NSW",
    "sg:tags":[
        "knitted",
        "woven",
        "fabric"
    ],
    "wof:name":"Lincraft",
    "wof:placetype":"venue"
},
  "geometry": {"coordinates":[150.687347,-33.75359],"type":"Point"}
}