{
  "type": "Feature",
  "properties": {
    "addr:full":"14 Searle Crt Dandenong North VIC 3175",
    "addr:housenumber":"14",
    "addr:postcode":"3175",
    "addr:street":"Searle Crt",
    "iso:country":"AU",
    "sg:address":"14 Searle Crt",
    "sg:city":"Dandenong North",
    "sg:classifiers":[
        {
            "category":"Education",
            "subcategory":"Vocational School",
            "type":"Public Place"
        }
    ],
    "sg:phone":"+61 3 9795 7363",
    "sg:postcode":"3175",
    "sg:province":"VIC",
    "sg:tags":[
        "cake",
        "decorating",
        "decorator"
    ],
    "wof:name":"Debbies Cakes",
    "wof:placetype":"venue"
},
  "geometry": {"coordinates":[145.214767456,-37.9533309937],"type":"Point"}
}