{
  "type": "Feature",
  "properties": {
    "addr:full":"92 Sunderland St Derwent Park TAS 7009",
    "addr:housenumber":"92",
    "addr:postcode":"7009",
    "addr:street":"Sunderland St",
    "iso:country":"AU",
    "sg:address":"92 Sunderland St",
    "sg:city":"Derwent Park",
    "sg:classifiers":[
        {
            "category":"Professional",
            "subcategory":"Engineering",
            "type":"Services"
        }
    ],
    "sg:phone":"+61 417 323 474",
    "sg:postcode":"7009",
    "sg:province":"TAS",
    "sg:tags":[
        "engineer"
    ],
    "wof:name":"The Engineering Company Pty Ltd",
    "wof:placetype":"venue"
},
  "geometry": {"coordinates":[147.29296875,-42.8370780945],"type":"Point"}
}