{
  "type": "Feature",
  "properties": {
    "iso:country":"AU",
    "sg:address":"8 Webb Drv",
    "sg:city":"Wonthaggi",
    "sg:classifiers":[
        {
            "category":"Retail",
            "subcategory":"Auto Repair",
            "type":"Services"
        }
    ],
    "sg:phone":"+61 3 5672 3995",
    "sg:postcode":"3995",
    "sg:province":"VIC",
    "sg:tags":[
        "repairer",
        "motor",
        "engineer"
    ],
    "wof:name":"Veeland",
    "wof:placetype":"venue"
},
  "geometry": {"coordinates":[145.603455,-38.604965],"type":"Point"}
}