{
  "type": "Feature",
  "properties": {
    "iso:country":"AU",
    "sg:address":"5 Thor St",
    "sg:city":"Victoria Point",
    "sg:classifiers":[
        {
            "category":"Professional",
            "subcategory":"Business Services",
            "type":"Services"
        }
    ],
    "sg:phone":"+61 7 3207 7769",
    "sg:postcode":"4165",
    "sg:province":"QLD",
    "sg:tags":[
        "drafting"
    ],
    "wof:name":"D.K.L. Drafting",
    "wof:placetype":"venue"
},
  "geometry": {"coordinates":[153.30015564000001,-27.5813694],"type":"Point"}
}