{
  "type": "Feature",
  "properties": {
    "addr:full":"30 Ashbourne Rd Strathalbyn SA 5255",
    "addr:housenumber":"30",
    "addr:postcode":"5255",
    "addr:street":"Ashbourne Rd",
    "iso:country":"AU",
    "sg:address":"30 Ashbourne Rd",
    "sg:city":"Strathalbyn",
    "sg:classifiers":[
        {
            "category":"Building & Trades",
            "subcategory":"Landscaping Services",
            "type":"Services"
        }
    ],
    "sg:phone":"+61 8 8536 2145",
    "sg:postcode":"5255",
    "sg:province":"SA",
    "sg:tags":[
        "grazier"
    ],
    "wof:name":"Formby J H",
    "wof:placetype":"venue"
},
  "geometry": {"coordinates":[138.88284301799999,-35.2605323792],"type":"Point"}
}