{
  "type": "Feature",
  "properties": {
    "iso:country":"AU",
    "sg:address":"14A Cave Hill Industrial Gardens Berresford Rd",
    "sg:city":"Lilydale",
    "sg:classifiers":[
        {
            "category":"Building & Trades",
            "subcategory":"Construction",
            "type":"Services"
        }
    ],
    "sg:phone":"+61 3 9739 5266",
    "sg:postcode":"3140",
    "sg:province":"VIC",
    "sg:tags":[
        "monumental",
        "mason"
    ],
    "wof:name":"Heath Memorials Pty Ltd",
    "wof:placetype":"venue"
},
  "geometry": {"coordinates":[145.35198974599999,-37.7515144348],"type":"Point"}
}