{
  "type": "Feature",
  "properties": {
    "addr:full":"4 Enterprise Crt Mulgrave VIC 3170",
    "addr:housenumber":"4",
    "addr:postcode":"3170",
    "addr:street":"Enterprise Crt",
    "iso:country":"AU",
    "sg:address":"4 Enterprise Crt",
    "sg:city":"Mulgrave",
    "sg:classifiers":[
        {
            "category":"Autos & Motor Vehicles",
            "subcategory":"Auto Supplies",
            "type":"Retail Goods"
        }
    ],
    "sg:phone":"+61 1300 666 608",
    "sg:postcode":"3170",
    "sg:province":"VIC",
    "sg:tags":[
        "garage",
        "equipment"
    ],
    "wof:name":"Gilbert Lodge Australia",
    "wof:placetype":"venue"
},
  "geometry": {"coordinates":[145.162719727,-37.9196281433],"type":"Point"}
}