{
  "type": "Feature",
  "properties": {
    "addr:full":"PO Box 200 Palmwoods QLD 4555",
    "addr:postcode":"4555",
    "iso:country":"AU",
    "sg:address":"PO Box 200",
    "sg:city":"Palmwoods",
    "sg:classifiers":[
        {
            "category":"Shopping",
            "subcategory":"Computers & Home Electronics",
            "type":"Retail Goods"
        }
    ],
    "sg:phone":"+61 413 232 371",
    "sg:postcode":"4555",
    "sg:province":"QLD",
    "sg:tags":[
        "equipment",
        "multimedia"
    ],
    "wof:name":"Vision Maker Studios",
    "wof:placetype":"venue"
},
  "geometry": {"coordinates":[152.956207275,-26.6875400543],"type":"Point"}
}