{
  "type": "Feature",
  "properties": {
    "addr:full":"13 - 15 Babdoyle St Loganholme QLD 4129",
    "addr:housenumber":"15",
    "addr:postcode":"4129",
    "addr:street":"Babdoyle St",
    "iso:country":"AU",
    "sg:address":"13 - 15 Babdoyle St",
    "sg:city":"Loganholme",
    "sg:classifiers":[
        {
            "category":"Manufacturing",
            "subcategory":"Furniture",
            "type":"Manufacturing & Wholesale Goods"
        }
    ],
    "sg:phone":"+61 7 3865 3144",
    "sg:postcode":"4129",
    "sg:province":"QLD",
    "sg:tags":[
        "mfrs",
        "supply"
    ],
    "wof:name":"Nover & Co Pty Ltd",
    "wof:placetype":"venue"
},
  "geometry": {"coordinates":[153.19192504899999,-27.6809139252],"type":"Point"}
}