{
  "type": "Feature",
  "properties": {
    "addr:full":"Private Mail Bag 302 Halls Creek WA 6770",
    "addr:postcode":"6770",
    "iso:country":"AU",
    "sg:address":"Private Mail Bag 302",
    "sg:city":"Halls Creek",
    "sg:classifiers":[
        {
            "category":"Building & Trades",
            "subcategory":"Landscaping Services",
            "type":"Services"
        }
    ],
    "sg:phone":"+61 8 9168 7513",
    "sg:postcode":"6770",
    "sg:province":"WA",
    "sg:tags":[
        "grazier"
    ],
    "wof:name":"Springvale Station",
    "wof:placetype":"venue"
},
  "geometry": {"coordinates":[127.66699218799999,-18.2247505188],"type":"Point"}
}