{
  "type": "Feature",
  "properties": {
    "addr:full":"1 Williams St Nairne SA 5252",
    "addr:housenumber":"1",
    "addr:postcode":"5252",
    "addr:street":"Williams St",
    "iso:country":"AU",
    "sg:address":"1 Williams St",
    "sg:city":"Nairne",
    "sg:classifiers":[
        {
            "category":"Professional",
            "subcategory":"Computer Services",
            "type":"Services"
        }
    ],
    "sg:phone":"+61 403 196 937",
    "sg:postcode":"5252",
    "sg:province":"SA",
    "sg:tags":[
        "equipment",
        "networking",
        "installation"
    ],
    "wof:name":"Ah Ha Complete Computer Solutions",
    "wof:placetype":"venue"
},
  "geometry": {"coordinates":[138.91067504899999,-35.0289077759],"type":"Point"}
}