{
  "type": "Feature",
  "properties": {
    "addr:full":"1 Inverness Ave The Basin VIC 3154",
    "addr:housenumber":"1",
    "addr:postcode":"3154",
    "addr:street":"Inverness Ave",
    "iso:country":"AU",
    "sg:address":"1 Inverness Ave",
    "sg:city":"The Basin",
    "sg:classifiers":[
        {
            "category":"Retail",
            "subcategory":"Auto Repair",
            "type":"Services"
        }
    ],
    "sg:phone":"+61 3 9762 0160",
    "sg:postcode":"3154",
    "sg:province":"VIC",
    "sg:tags":[
        "repairer",
        "motor",
        "engineer"
    ],
    "wof:name":"James Bodourian Automotive Repairs",
    "wof:placetype":"venue"
},
  "geometry": {"coordinates":[145.32463073700001,-37.86170578],"type":"Point"}
}