{
  "type": "Feature",
  "properties": {
    "iso:country":"AU",
    "sg:address":"Lvl 1 Suite 103/ level 1 166 Murray St",
    "sg:city":"Perth",
    "sg:classifiers":[
        {
            "category":"Professional",
            "subcategory":"Management & Consulting",
            "type":"Services"
        }
    ],
    "sg:phone":"+61 8 9221 7745",
    "sg:postcode":"6805",
    "sg:province":"WA",
    "sg:tags":[
        "consultant",
        "migration"
    ],
    "wof:name":"Easymigrate Consultancy Services",
    "wof:placetype":"venue"
},
  "geometry": {"coordinates":[115.85723900000001,-31.95302],"type":"Point"}
}