{
  "type": "Feature",
  "properties": {
    "iso:country":"AU",
    "sg:address":"Shp21/ 417 Sydney Rd",
    "sg:city":"Coburg",
    "sg:classifiers":[
        {
            "category":"Food & Beverages",
            "subcategory":"Meat & Fish",
            "type":"Retail Goods"
        }
    ],
    "sg:phone":"+61 3 9354 1780",
    "sg:postcode":"3058",
    "sg:province":"VIC",
    "sg:tags":[
        "seafood"
    ],
    "wof:name":"Coburg Market Daily Seafood",
    "wof:placetype":"venue"
},
  "geometry": {"coordinates":[144.96600341800001,-37.7436180115],"type":"Point"}
}