{
  "type": "Feature",
  "properties": {
    "iso:country":"AU",
    "sg:address":"2 Tenambit St",
    "sg:city":"East Maitland",
    "sg:classifiers":[
        {
            "category":"Sports & Exercise",
            "subcategory":"Gym",
            "type":"Entertainment"
        }
    ],
    "sg:phone":"+61 2 4933 1232",
    "sg:postcode":"2323",
    "sg:province":"NSW",
    "sg:tags":[
        "health",
        "fitness"
    ],
    "wof:name":"123 Express Pty Ltd",
    "wof:placetype":"venue"
},
  "geometry": {"coordinates":[151.60035705600001,-32.7503852844],"type":"Point"}
}