{
  "type": "Feature",
  "properties": {
    "addr:full":"476 Hampton St Hampton VIC 3188",
    "addr:housenumber":"476",
    "addr:postcode":"3188",
    "addr:street":"Hampton St",
    "iso:country":"AU",
    "sg:address":"476 Hampton St",
    "sg:city":"Hampton",
    "sg:classifiers":[
        {
            "category":"Food & Beverages",
            "subcategory":"Bakery",
            "type":"Retail Goods"
        }
    ],
    "sg:phone":"+61 3 9533 1476",
    "sg:postcode":"3188",
    "sg:province":"VIC",
    "sg:tags":[
        "baker"
    ],
    "wof:name":"Brumby's Bakeries",
    "wof:placetype":"venue"
},
  "geometry": {"coordinates":[145.00294494600001,-37.9359741211],"type":"Point"}
}