{
  "type": "Feature",
  "properties": {
    "addr:full":"8 Lord St Port Campbell VIC 3269",
    "addr:housenumber":"8",
    "addr:postcode":"3269",
    "addr:street":"Lord St Port",
    "iso:country":"AU",
    "sg:address":"8 Lord St",
    "sg:city":"Port Campbell",
    "sg:classifiers":[
        {
            "category":"Fast Food",
            "type":"Food & Drink"
        }
    ],
    "sg:phone":"+61 3 5598 6210",
    "sg:postcode":"3269",
    "sg:province":"VIC",
    "sg:tags":[
        "away",
        "take"
    ],
    "wof:name":"Great Australian Bite The",
    "wof:placetype":"venue"
},
  "geometry": {"coordinates":[142.99298095699999,-38.6210708618],"type":"Point"}
}