{
  "type": "Feature",
  "properties": {
    "addr:full":"85 Glengala Rd Sunshine West VIC 3020",
    "addr:housenumber":"85",
    "addr:postcode":"3020",
    "addr:street":"Glengala Rd",
    "iso:country":"AU",
    "sg:address":"85 Glengala Rd",
    "sg:city":"Sunshine West",
    "sg:classifiers":[
        {
            "category":"Shopping",
            "subcategory":"Baby Store",
            "type":"Retail Goods"
        }
    ],
    "sg:phone":"+61 3 9310 1660",
    "sg:postcode":"3020",
    "sg:province":"VIC",
    "sg:tags":[
        "children's",
        "wear"
    ],
    "wof:name":"Kupid Kidz",
    "wof:placetype":"venue"
},
  "geometry": {"coordinates":[144.81727599999999,-37.790562],"type":"Point"}
}