{
  "type": "Feature",
  "properties": {
    "addr:full":"110 Stephen St Yarraville VIC 3013",
    "addr:housenumber":"110",
    "addr:postcode":"3013",
    "addr:street":"Stephen St",
    "iso:country":"AU",
    "sg:address":"110 Stephen St",
    "sg:city":"Yarraville",
    "sg:classifiers":[
        {
            "category":"Retail",
            "subcategory":"Veterinary Services",
            "type":"Services"
        }
    ],
    "sg:phone":"+61 3 9689 8100",
    "sg:postcode":"3013",
    "sg:province":"VIC",
    "sg:tags":[
        "surgeon"
    ],
    "wof:name":"Yarraville Village Animal Hospital",
    "wof:placetype":"venue"
},
  "geometry": {"coordinates":[144.894088745,-37.8170394897],"type":"Point"}
}