{
  "type": "Feature",
  "properties": {
    "addr:full":"31 Belford St Broadmeadow NSW 2292",
    "addr:housenumber":"31",
    "addr:postcode":"2292",
    "addr:street":"Belford St",
    "iso:country":"AU",
    "sg:address":"31 Belford St",
    "sg:city":"Broadmeadow",
    "sg:classifiers":[
        {
            "category":"Wholesale",
            "subcategory":"Apparel",
            "type":"Manufacturing & Wholesale Goods"
        }
    ],
    "sg:phone":"+61 2 4961 1022",
    "sg:postcode":"2292",
    "sg:province":"NSW",
    "sg:tags":[
        "wholesaler",
        "mfrs",
        "sportswear",
        "women's"
    ],
    "wof:name":"Gazas Embroidery",
    "wof:placetype":"venue"
},
  "geometry": {"coordinates":[151.737884522,-32.9243354797],"type":"Point"}
}