{
  "type": "Feature",
  "properties": {
    "addr:full":"2 Tibouchina Pl Currimundi QLD 4551",
    "addr:housenumber":"2",
    "addr:postcode":"4551",
    "addr:street":"Tibouchina Pl",
    "iso:country":"AU",
    "sg:address":"2 Tibouchina Pl",
    "sg:city":"Currimundi",
    "sg:classifiers":[
        {
            "category":"Professional",
            "subcategory":"Art Services",
            "type":"Services"
        }
    ],
    "sg:phone":"+61 7 5493 3883",
    "sg:postcode":"4551",
    "sg:province":"QLD",
    "sg:tags":[
        "decorator",
        "painter"
    ],
    "wof:name":"Brian Gold",
    "wof:placetype":"venue"
},
  "geometry": {"coordinates":[153.11924743599999,-26.7706851959],"type":"Point"}
}