{
  "type": "Feature",
  "properties": {
    "addr:full":"12 Curry Rd Kilmore VIC 3764",
    "addr:housenumber":"12",
    "addr:postcode":"3764",
    "addr:street":"Curry Rd",
    "iso:country":"AU",
    "sg:address":"12 Curry Rd",
    "sg:city":"Kilmore",
    "sg:classifiers":[
        {
            "category":"Bars & Pubs",
            "subcategory":"Sports Bar",
            "type":"Food & Drink"
        }
    ],
    "sg:phone":"+61 419 518 465",
    "sg:postcode":"3764",
    "sg:province":"VIC",
    "sg:tags":[
        "rolling",
        "forming",
        "metal"
    ],
    "wof:name":"Formroll Technical Engineering Pty Ltd",
    "wof:placetype":"venue"
},
  "geometry": {"coordinates":[144.94493102999999,-37.3172988892],"type":"Point"}
}