{
  "type": "Feature",
  "properties": {
    "iso:country":"AU",
    "sg:address":"198 Coventry St",
    "sg:city":"South Melbourne",
    "sg:classifiers":[
        {
            "category":"Shopping",
            "subcategory":"Clothing, Apparel, & Fashions",
            "type":"Retail Goods"
        }
    ],
    "sg:phone":"+61 3 9690 8776",
    "sg:postcode":"3205",
    "sg:province":"VIC",
    "sg:tags":[
        "menswear"
    ],
    "wof:name":"Propaganda",
    "wof:placetype":"venue"
},
  "geometry": {"coordinates":[144.962738,-37.830994],"type":"Point"}
}