{
  "type": "Feature",
  "properties": {
    "iso:country":"AU",
    "sg:address":"108-112 Wing St",
    "sg:city":"Wingfield",
    "sg:classifiers":[
        {
            "category":"Wholesale",
            "subcategory":"Machinery & Supplies",
            "type":"Manufacturing & Wholesale Goods"
        }
    ],
    "sg:phone":"+61 8 8359 5362",
    "sg:postcode":"5013",
    "sg:province":"SA",
    "sg:tags":[
        "agricultural"
    ],
    "wof:name":"GreenTech Australia",
    "wof:placetype":"venue"
},
  "geometry": {"coordinates":[138.567062378,-34.8365020752],"type":"Point"}
}