{
  "type": "Feature",
  "properties": {
    "iso:country":"AU",
    "sg:address":"38 Eighth Ave",
    "sg:city":"Maylands",
    "sg:classifiers":[
        {
            "category":"Personal",
            "subcategory":"Shoe Repair & Shine",
            "type":"Services"
        }
    ],
    "sg:phone":"+61 8 9271 6313",
    "sg:postcode":"6051",
    "sg:province":"WA",
    "sg:tags":[
        "footwear"
    ],
    "wof:name":"Lammy Shoe Repairs Key Cutting & Alterations",
    "wof:placetype":"venue"
},
  "geometry": {"coordinates":[115.89360000000001,-31.929905],"type":"Point"}
}