{
  "type": "Feature",
  "properties": {
    "addr:full":"7 Chard Rd Brookvale NSW 2100",
    "addr:housenumber":"7",
    "addr:postcode":"2100",
    "addr:street":"Chard Rd",
    "iso:country":"AU",
    "sg:address":"7 Chard Rd",
    "sg:city":"Brookvale",
    "sg:classifiers":[
        {
            "category":"Wholesale",
            "subcategory":"Machinery & Supplies",
            "type":"Manufacturing & Wholesale Goods"
        }
    ],
    "sg:phone":"+61 2 9939 7888",
    "sg:postcode":"2100",
    "sg:province":"NSW",
    "sg:tags":[
        "equipment",
        "welding"
    ],
    "wof:name":"Leko Manufacturing Pty Ltd",
    "wof:placetype":"venue"
},
  "geometry": {"coordinates":[151.27239990199999,-33.7632102966],"type":"Point"}
}