{
  "type": "Feature",
  "properties": {
    "addr:full":"403 Enmore Rd Marrickville NSW 2204",
    "addr:housenumber":"403",
    "addr:postcode":"2204",
    "addr:street":"Enmore Rd",
    "iso:country":"AU",
    "sg:address":"403 Enmore Rd",
    "sg:city":"Marrickville",
    "sg:classifiers":[
        {
            "category":"Building & Trades",
            "subcategory":"Electrical",
            "type":"Services"
        }
    ],
    "sg:phone":"+61 2 9519 6941",
    "sg:postcode":"2204",
    "sg:province":"NSW",
    "sg:tags":[
        "repair",
        "generator",
        "electric",
        "motor"
    ],
    "wof:name":"Industrial Electric Co",
    "wof:placetype":"venue"
},
  "geometry": {"coordinates":[151.167755,-33.904846],"type":"Point"}
}