{
  "type": "Feature",
  "properties": {
    "iso:country":"AU",
    "sg:address":"4 Cardigan St",
    "sg:city":"East Launceston",
    "sg:classifiers":[
        {
            "category":"Freight",
            "type":"Transportation"
        }
    ],
    "sg:phone":"+61 3 6331 6319",
    "sg:postcode":"7250",
    "sg:province":"TAS",
    "sg:tags":[
        "light",
        "carrier"
    ],
    "wof:name":"Hanson J R & M W",
    "wof:placetype":"venue"
},
  "geometry": {"coordinates":[147.15538024899999,-41.4399490356],"type":"Point"}
}