{
  "type": "Feature",
  "properties": {
    "iso:country":"AU",
    "sg:address":"98 Mary St",
    "sg:city":"Grafton",
    "sg:classifiers":[
        {
            "category":"Retail",
            "subcategory":"Car Wash",
            "type":"Services"
        }
    ],
    "sg:phone":"+61 2 6642 3833",
    "sg:postcode":"2460",
    "sg:province":"NSW",
    "sg:tags":[
        "merchant",
        "oil",
        "refiner"
    ],
    "wof:name":"Slick 50",
    "wof:placetype":"venue"
},
  "geometry": {"coordinates":[152.93380737300001,-29.6826248169],"type":"Point"}
}