{
  "type": "Feature",
  "properties": {
    "addr:full":"Shp 1, Westfield Shppng Cntr, 87 Park St Kotara NSW 2289",
    "addr:housenumber":"1;87",
    "addr:postcode":"2289",
    "addr:street":"Westfield Shppng Cntr;Park St",
    "iso:country":"AU",
    "sg:address":"Shp 1, Westfield Shppng Cntr, 87 Park St",
    "sg:city":"Kotara",
    "sg:classifiers":[
        {
            "category":"Food & Beverages",
            "subcategory":"Meat & Fish",
            "type":"Retail Goods"
        }
    ],
    "sg:phone":"+61 2 4957 8688",
    "sg:postcode":"2289",
    "sg:province":"NSW",
    "sg:tags":[
        "seafood"
    ],
    "wof:name":"De Costi's Seafood",
    "wof:placetype":"venue"
},
  "geometry": {"coordinates":[151.71815490700001,-32.9362564087],"type":"Point"}
}