{
  "type": "Feature",
  "properties": {
    "iso:country":"AU",
    "sg:address":"Kater Rd",
    "sg:city":"Sutton Forest",
    "sg:classifiers":[
        {
            "category":"Sports & Exercise",
            "subcategory":"Golf",
            "type":"Entertainment"
        }
    ],
    "sg:phone":"+61 2 4868 3200",
    "sg:postcode":"2577",
    "sg:province":"NSW",
    "sg:tags":[
        "club"
    ],
    "wof:name":"Mount Broughton Golf & Country Club",
    "wof:placetype":"venue"
},
  "geometry": {"coordinates":[150.34243774399999,-34.5652923584],"type":"Point"}
}