{
  "type": "Feature",
  "properties": {
    "addr:full":"2 Williams Rd Narrogin WA 6312",
    "addr:housenumber":"2",
    "addr:postcode":"6312",
    "addr:street":"Williams Rd",
    "iso:country":"AU",
    "sg:address":"2 Williams Rd",
    "sg:city":"Narrogin",
    "sg:classifiers":[
        {
            "category":"Health Services",
            "subcategory":"Doctor",
            "type":"Services"
        }
    ],
    "sg:phone":"+61 8 9881 2999",
    "sg:postcode":"6312",
    "sg:province":"WA",
    "sg:tags":[
        "nurse",
        "nursing"
    ],
    "wof:name":"Silver Chain",
    "wof:placetype":"venue"
},
  "geometry": {"coordinates":[117.175170898,-32.9338798523],"type":"Point"}
}