{
  "type": "Feature",
  "properties": {
    "iso:country":"AU",
    "sg:address":"107/ 54 Park Rd",
    "sg:city":"Cabramatta",
    "sg:classifiers":[
        {
            "category":"Banks & Credit Unions",
            "subcategory":"Investment Brokerage",
            "type":"Services"
        }
    ],
    "sg:phone":"+61 2 9728 1048",
    "sg:postcode":"2166",
    "sg:province":"NSW",
    "sg:tags":[
        "finance",
        "broker"
    ],
    "wof:name":"Financial Solutions Pty Ltd",
    "wof:placetype":"venue"
},
  "geometry": {"coordinates":[150.93707275400001,-33.894657135],"type":"Point"}
}