{
  "type": "Feature",
  "properties": {
    "iso:country":"AU",
    "sg:address":"209 Manly Rd",
    "sg:city":"Manly West",
    "sg:classifiers":[
        {
            "category":"Health Services",
            "subcategory":"Health Practitioner",
            "type":"Services"
        }
    ],
    "sg:phone":"+61 7 3396 9111",
    "sg:postcode":"4179",
    "sg:province":"QLD",
    "sg:tags":[
        "physiotherapist"
    ],
    "wof:name":"Spring Sandra",
    "wof:placetype":"venue"
},
  "geometry": {"coordinates":[153.17294311500001,-27.4670734406],"type":"Point"}
}