{
  "type": "Feature",
  "properties": {
    "iso:country":"AU",
    "sg:address":"Rouchel Rd",
    "sg:city":"Aberdeen",
    "sg:classifiers":[
        {
            "category":"Building & Trades",
            "subcategory":"Construction",
            "type":"Services"
        }
    ],
    "sg:phone":"+61 2 6543 6203",
    "sg:postcode":"2336",
    "sg:province":"NSW",
    "sg:tags":[
        "earth",
        "excavating",
        "moving",
        "contractor"
    ],
    "wof:name":"Walker D M & M P",
    "wof:placetype":"venue"
},
  "geometry": {"coordinates":[150.89613342300001,-32.1543159485],"type":"Point"}
}