{
  "type": "Feature",
  "properties": {
    "addr:full":"133 Combermere St Goulburn NSW 2580",
    "addr:housenumber":"133",
    "addr:postcode":"2580",
    "addr:street":"Combermere St",
    "iso:country":"AU",
    "sg:address":"133 Combermere St",
    "sg:city":"Goulburn",
    "sg:classifiers":[
        {
            "category":"Building & Trades",
            "subcategory":"Landscaping Services",
            "type":"Services"
        }
    ],
    "sg:phone":"+61 427 266 322",
    "sg:postcode":"2580",
    "sg:province":"NSW",
    "sg:tags":[
        "firebreak",
        "clearing",
        "land",
        "contractor"
    ],
    "wof:name":"D.F.B. & M.E. Gardiner",
    "wof:placetype":"venue"
},
  "geometry": {"coordinates":[149.69590759299999,-34.7578048706],"type":"Point"}
}