{
  "type": "Feature",
  "properties": {
    "iso:country":"AU",
    "sg:address":"29 Blackwall Rd",
    "sg:city":"Woy Woy",
    "sg:classifiers":[
        {
            "category":"Travel",
            "subcategory":"Travel Agent",
            "type":"Entertainment"
        }
    ],
    "sg:phone":"+61 2 4344 3233",
    "sg:postcode":"2256",
    "sg:province":"NSW",
    "sg:tags":[
        "consultant"
    ],
    "wof:name":"Dial-A-Holiday Woy Woy",
    "wof:placetype":"venue"
},
  "geometry": {"coordinates":[151.324615478,-33.4857978821],"type":"Point"}
}