{
  "type": "Feature",
  "properties": {
    "addr:full":"605 Grenfell Rd Cowra NSW 2794",
    "addr:housenumber":"605",
    "addr:postcode":"2794",
    "addr:street":"Grenfell Rd",
    "iso:country":"AU",
    "sg:address":"605 Grenfell Rd",
    "sg:city":"Cowra",
    "sg:classifiers":[
        {
            "category":"Farming",
            "subcategory":"Vineyard",
            "type":"Manufacturing & Wholesale Goods"
        }
    ],
    "sg:phone":"+61 2 6342 9270",
    "sg:postcode":"2794",
    "sg:province":"NSW",
    "sg:tags":[
        "winery"
    ],
    "wof:name":"Chiverton",
    "wof:placetype":"venue"
},
  "geometry": {"coordinates":[148.69056701700001,-33.8345909119],"type":"Point"}
}