{
  "type": "Feature",
  "properties": {
    "addr:full":"17 Magill Rd Stepney SA 5069",
    "addr:housenumber":"17",
    "addr:postcode":"5069",
    "addr:street":"Magill Rd",
    "iso:country":"AU",
    "sg:address":"17 Magill Rd",
    "sg:city":"Stepney",
    "sg:classifiers":[
        {
            "category":"Professional",
            "type":"Services"
        }
    ],
    "sg:phone":"+61 8 8362 7395",
    "sg:postcode":"5069",
    "sg:province":"SA",
    "sg:tags":[
        "spray",
        "painting"
    ],
    "wof:name":"Dynamic Paint N Panel",
    "wof:placetype":"venue"
},
  "geometry": {"coordinates":[138.624435425,-34.9154396057],"type":"Point"}
}