{
  "type": "Feature",
  "properties": {
    "addr:full":"31 Corsair St Raby NSW 2566",
    "addr:housenumber":"31",
    "addr:postcode":"2566",
    "addr:street":"Corsair St",
    "iso:country":"AU",
    "sg:address":"31 Corsair St",
    "sg:city":"Raby",
    "sg:classifiers":[
        {
            "category":"Wholesale",
            "subcategory":"Machinery & Supplies",
            "type":"Manufacturing & Wholesale Goods"
        }
    ],
    "sg:phone":"+61 418 471 074",
    "sg:postcode":"2566",
    "sg:province":"NSW",
    "sg:tags":[
        "equipment",
        "hydraulic"
    ],
    "wof:name":"Emergency Hydraulics Pty Ltd",
    "wof:placetype":"venue"
},
  "geometry": {"coordinates":[150.819580078,-34.0211677551],"type":"Point"}
}