{
  "type": "Feature",
  "properties": {
    "iso:country":"AU",
    "sg:address":"41 Chelmsford Drv",
    "sg:city":"Metford",
    "sg:classifiers":[
        {
            "category":"Education",
            "subcategory":"Kindergarten",
            "type":"Public Place"
        }
    ],
    "sg:phone":"+61 2 4933 2397",
    "sg:postcode":"2323",
    "sg:province":"NSW",
    "sg:tags":[
        "pre-schools"
    ],
    "wof:name":"Chelmsford Drive Early Learning",
    "wof:placetype":"venue"
},
  "geometry": {"coordinates":[151.60144043,-32.7635803223],"type":"Point"}
}