{
  "type": "Feature",
  "properties": {
    "iso:country":"AU",
    "sg:address":"164 Toombul Rd",
    "sg:city":"Northgate",
    "sg:classifiers":[
        {
            "category":"Health Services",
            "subcategory":"Doctor",
            "type":"Services"
        }
    ],
    "sg:phone":"+61 7 3256 7896",
    "sg:postcode":"4013",
    "sg:province":"QLD",
    "sg:tags":[
        "medical",
        "practitioner"
    ],
    "wof:name":"North Side Health Clinic",
    "wof:placetype":"venue"
},
  "geometry": {"coordinates":[153.07182312,-27.3916053772],"type":"Point"}
}