{
  "type": "Feature",
  "properties": {
    "iso:country":"AU",
    "sg:address":"190 Birkdale Rd",
    "sg:city":"(beside Birkdale Fair) Birkdale",
    "sg:classifiers":[
        {
            "category":"Social Services",
            "subcategory":"Child Care",
            "type":"Services"
        }
    ],
    "sg:phone":"+61 7 3822 4633",
    "sg:postcode":"4159",
    "sg:province":"QLD",
    "wof:name":"Full of Beans Child Care Kindergarten and Preschool",
    "wof:placetype":"venue"
},
  "geometry": {"coordinates":[153.210861206,-27.5004692078],"type":"Point"}
}