{
  "type": "Feature",
  "properties": {
    "iso:country":"AU",
    "sg:address":"27 Pretty Sally Drv",
    "sg:city":"Wallan",
    "sg:classifiers":[
        {
            "category":"Manufacturing",
            "subcategory":"Wood Products",
            "type":"Manufacturing & Wholesale Goods"
        }
    ],
    "sg:phone":"+61 3 5783 1067",
    "sg:postcode":"3756",
    "sg:province":"VIC",
    "sg:tags":[
        "polisher",
        "french"
    ],
    "wof:name":"R.A. Herman",
    "wof:placetype":"venue"
},
  "geometry": {"coordinates":[144.97410600000001,-37.401485],"type":"Point"}
}