{
  "type": "Feature",
  "properties": {
    "addr:full":"17 Gladstone Rd Rockhampton QLD 4702",
    "addr:housenumber":"17",
    "addr:postcode":"4702",
    "addr:street":"Gladstone Rd",
    "iso:country":"AU",
    "sg:address":"17 Gladstone Rd",
    "sg:city":"Rockhampton",
    "sg:classifiers":[
        {
            "category":"Shopping",
            "subcategory":"Computers & Home Electronics",
            "type":"Retail Goods"
        }
    ],
    "sg:phone":"+61 7 4922 2178",
    "sg:postcode":"4702",
    "sg:province":"QLD",
    "sg:tags":[
        "hardware",
        "equipment"
    ],
    "wof:name":"Access Electronics",
    "wof:placetype":"venue"
},
  "geometry": {"coordinates":[150.50746154800001,-23.3873691559],"type":"Point"}
}