{
  "type": "Feature",
  "properties": {
    "addr:full":"PO Box 292 Palm Cove QLD 4879",
    "addr:postcode":"4879",
    "iso:country":"AU",
    "sg:address":"PO Box 292",
    "sg:city":"Palm Cove",
    "sg:classifiers":[
        {
            "category":"Building & Trades",
            "subcategory":"Cleaning & Sanitation",
            "type":"Services"
        }
    ],
    "sg:phone":"+61 408 805 515",
    "sg:postcode":"4879",
    "sg:province":"QLD",
    "sg:tags":[
        "industrial",
        "commercial",
        "contractor"
    ],
    "wof:name":"Affordable Office Clean",
    "wof:placetype":"venue"
},
  "geometry": {"coordinates":[145.67100524899999,-16.7458992004],"type":"Point"}
}