{
  "type": "Feature",
  "properties": {
    "iso:country":"AU",
    "sg:address":"26 Camion Crt",
    "sg:city":"Petrie",
    "sg:classifiers":[
        {
            "category":"Building & Trades",
            "subcategory":"Pest Control",
            "type":"Services"
        }
    ],
    "sg:phone":"+61 7 3285 2626",
    "sg:postcode":"4502",
    "sg:province":"QLD",
    "wof:name":"Allmax Carpet Cleaning & Pest Management",
    "wof:placetype":"venue"
},
  "geometry": {"coordinates":[152.967895508,-27.2668075562],"type":"Point"}
}