{
  "type": "Feature",
  "properties": {
    "addr:full":"15 Mint St Wodonga VIC 3690",
    "addr:housenumber":"15",
    "addr:postcode":"3690",
    "addr:street":"Mint St",
    "iso:country":"AU",
    "sg:address":"15 Mint St",
    "sg:city":"Wodonga",
    "sg:classifiers":[
        {
            "category":"Shopping",
            "subcategory":"Crafts & Fabrics",
            "type":"Retail Goods"
        }
    ],
    "sg:phone":"+61 2 6056 4599",
    "sg:postcode":"3690",
    "sg:province":"VIC",
    "sg:tags":[
        "synthetic",
        "canvas",
        "product"
    ],
    "wof:name":"Universal Upholstery",
    "wof:placetype":"venue"
},
  "geometry": {"coordinates":[146.89642334000001,-36.1231918335],"type":"Point"}
}