{
  "type": "Feature",
  "properties": {
    "iso:country":"AU",
    "sg:address":"69 Park St",
    "sg:city":"Hyde Park",
    "sg:classifiers":[
        {
            "category":"Education",
            "subcategory":"Special Training",
            "type":"Public Place"
        }
    ],
    "sg:phone":"+61 8 8373 4853",
    "sg:postcode":"5061",
    "sg:province":"SA",
    "sg:tags":[
        "development"
    ],
    "wof:name":"Personnel Development And Training Pty Ltd",
    "wof:placetype":"venue"
},
  "geometry": {"coordinates":[138.60140991200001,-34.9553031921],"type":"Point"}
}