{
  "type": "Feature",
  "properties": {
    "addr:full":"6 Andrew Pl Bundoora VIC 3083",
    "addr:housenumber":"6",
    "addr:postcode":"3083",
    "addr:street":"Andrew Pl",
    "iso:country":"AU",
    "sg:address":"6 Andrew Pl",
    "sg:city":"Bundoora",
    "sg:classifiers":[
        {
            "category":"Manufacturing",
            "subcategory":"Food",
            "type":"Manufacturing & Wholesale Goods"
        }
    ],
    "sg:phone":"+61 3 9467 1332",
    "sg:postcode":"3083",
    "sg:province":"VIC",
    "sg:tags":[
        "function",
        "catering"
    ],
    "wof:name":"It's Divine Specialty Cakes & Pastries",
    "wof:placetype":"venue"
},
  "geometry": {"coordinates":[145.072433472,-37.7009162903],"type":"Point"}
}