{
  "type": "Feature",
  "properties": {
    "addr:full":"539 Dundas Rd Forrestfield WA 6058",
    "addr:housenumber":"539",
    "addr:postcode":"6058",
    "addr:street":"Dundas Rd",
    "iso:country":"AU",
    "sg:address":"539 Dundas Rd",
    "sg:city":"Forrestfield",
    "sg:classifiers":[
        {
            "category":"Building & Trades",
            "subcategory":"Construction",
            "type":"Services"
        }
    ],
    "sg:phone":"+61 8 9454 4088",
    "sg:postcode":"6058",
    "sg:province":"WA",
    "sg:tags":[
        "earth",
        "excavating",
        "moving",
        "contractor"
    ],
    "wof:name":"K T B Contractors (1982) Pty Ltd",
    "wof:placetype":"venue"
},
  "geometry": {"coordinates":[115.988273621,-31.9752597809],"type":"Point"}
}