{
  "type": "Feature",
  "properties": {
    "addr:full":"204 Norton St Leichhardt NSW 2040",
    "addr:housenumber":"204",
    "addr:postcode":"2040",
    "addr:street":"Norton St",
    "iso:country":"AU",
    "sg:address":"204 Norton St",
    "sg:city":"Leichhardt",
    "sg:classifiers":[
        {
            "category":"Home & Garden",
            "subcategory":"Building Materials",
            "type":"Retail Goods"
        }
    ],
    "sg:phone":"+61 2 9564 2877",
    "sg:postcode":"2040",
    "sg:province":"NSW",
    "sg:tags":[
        "fitting",
        "door"
    ],
    "wof:name":"Architectural Door Hardware Pty Ltd",
    "wof:placetype":"venue"
},
  "geometry": {"coordinates":[151.156464,-33.880089],"type":"Point"}
}