{
  "type": "Feature",
  "properties": {
    "iso:country":"AU",
    "sg:address":"14a beaconsfield St",
    "sg:city":"Alexandria",
    "sg:classifiers":[
        {
            "category":"Social Services",
            "subcategory":"Retirement Home",
            "type":"Services"
        }
    ],
    "sg:phone":"+61 416 189 013",
    "sg:postcode":"2015",
    "sg:province":"NSW",
    "sg:tags":[
        "life",
        "coaching"
    ],
    "wof:name":"Lifes a Cupcake",
    "wof:placetype":"venue"
},
  "geometry": {"coordinates":[151.19923400900001,-33.9141044617],"type":"Point"}
}