{
  "type": "Feature",
  "properties": {
    "addr:full":"57 Bendix Drv Clayton VIC 3168",
    "addr:housenumber":"57",
    "addr:postcode":"3168",
    "addr:street":"Bendix Drv",
    "iso:country":"AU",
    "sg:address":"57 Bendix Drv",
    "sg:city":"Clayton",
    "sg:classifiers":[
        {
            "category":"Home & Garden",
            "subcategory":"Home Furnishings",
            "type":"Retail Goods"
        }
    ],
    "sg:phone":"+61 411 799 256",
    "sg:postcode":"3168",
    "sg:province":"VIC",
    "sg:tags":[
        "shower",
        "screen"
    ],
    "wof:name":"Galaxy Screens",
    "wof:placetype":"venue"
},
  "geometry": {"coordinates":[145.12698364299999,-37.9292259216],"type":"Point"}
}