{
  "type": "Feature",
  "properties": {
    "addr:full":"Level 5, 51 Allara St Canberra City ACT 2601",
    "addr:housenumber":"51",
    "addr:postcode":"2601",
    "addr:street":"Allara St",
    "iso:country":"AU",
    "sg:address":"Level 5, 51 Allara St",
    "sg:city":"Canberra City",
    "sg:classifiers":[
        {
            "category":"Professional",
            "subcategory":"Accounting & Tax Preparation",
            "type":"Services"
        }
    ],
    "sg:phone":"+61 2 6230 4663",
    "sg:postcode":"2601",
    "sg:province":"ACT",
    "sg:tags":[
        "accountant",
        "auditor"
    ],
    "wof:name":"Aquila Super",
    "wof:placetype":"venue"
},
  "geometry": {"coordinates":[149.132904053,-35.2837715149],"type":"Point"}
}