{
  "type": "Feature",
  "properties": {
    "addr:full":"14 Bartels St McCrae VIC 3938",
    "addr:housenumber":"14",
    "addr:postcode":"3938",
    "addr:street":"Bartels St",
    "iso:country":"AU",
    "sg:address":"14 Bartels St",
    "sg:city":"McCrae",
    "sg:classifiers":[
        {
            "category":"Home & Garden",
            "subcategory":"Carpets & Floor Coverings",
            "type":"Retail Goods"
        }
    ],
    "sg:phone":"+61 417 336 655",
    "sg:postcode":"3938",
    "sg:province":"VIC",
    "sg:tags":[
        "tile",
        "wall"
    ],
    "wof:name":"Pro Care Carpet Cleaning",
    "wof:placetype":"venue"
},
  "geometry": {"coordinates":[144.92889404300001,-38.3501358032],"type":"Point"}
}