{
  "type": "Feature",
  "properties": {
    "addr:full":"14 Buckingham Drv Wangara WA 6065",
    "addr:housenumber":"14",
    "addr:postcode":"6065",
    "addr:street":"Buckingham Drv",
    "iso:country":"AU",
    "sg:address":"14 Buckingham Drv",
    "sg:city":"Wangara",
    "sg:classifiers":[
        {
            "category":"Autos & Motor Vehicles",
            "subcategory":"Auto Supplies",
            "type":"Retail Goods"
        }
    ],
    "sg:phone":"+61 8 9309 9111",
    "sg:postcode":"6065",
    "sg:province":"WA",
    "sg:tags":[
        "accessory"
    ],
    "wof:name":"Linear Concept Car Company",
    "wof:placetype":"venue"
},
  "geometry": {"coordinates":[115.81503295900001,-31.7872848511],"type":"Point"}
}