{
  "type": "Feature",
  "properties": {
    "addr:full":"88 High St Maryborough VIC 3465",
    "addr:housenumber":"88",
    "addr:postcode":"3465",
    "addr:street":"High St",
    "iso:country":"AU",
    "sg:address":"88 High St",
    "sg:city":"Maryborough",
    "sg:classifiers":[
        {
            "category":"Communications",
            "subcategory":"Film & Video Production",
            "type":"Services"
        }
    ],
    "sg:phone":"+61 3 5461 3923",
    "sg:postcode":"3465",
    "sg:province":"VIC",
    "sg:tags":[
        "dvd",
        "library"
    ],
    "wof:name":"Showtime Entertainment",
    "wof:placetype":"venue"
},
  "geometry": {"coordinates":[143.73611450199999,-37.0480918884],"type":"Point"}
}