{
  "type": "Feature",
  "properties": {
    "addr:full":"Upper Floor, 100 Queen St Busselton WA 6280",
    "addr:housenumber":"100",
    "addr:postcode":"6280",
    "addr:street":"Upper;Queen St",
    "iso:country":"AU",
    "sg:address":"Upper Floor, 100 Queen St",
    "sg:city":"Busselton",
    "sg:classifiers":[
        {
            "category":"Real Estate",
            "subcategory":"Architect",
            "type":"Services"
        }
    ],
    "sg:phone":"+61 8 9752 3146",
    "sg:postcode":"6280",
    "sg:province":"WA",
    "sg:tags":[
        "building",
        "designer"
    ],
    "wof:name":"Joseph D&#039;Agostino & Stuart Luff Architects",
    "wof:placetype":"venue"
},
  "geometry": {"coordinates":[115.344902039,-33.6517295837],"type":"Point"}
}