{
  "type": "Feature",
  "properties": {
    "addr:full":"249 Bondi Rd Bondi NSW 2026",
    "addr:housenumber":"249",
    "addr:postcode":"2026",
    "addr:street":"Bondi Rd",
    "iso:country":"AU",
    "sg:address":"249 Bondi Rd",
    "sg:city":"Bondi",
    "sg:classifiers":[
        {
            "category":"Fast Food",
            "type":"Food & Drink"
        }
    ],
    "sg:phone":"+61 2 9130 4888",
    "sg:postcode":"2026",
    "sg:province":"NSW",
    "sg:tags":[
        "away",
        "take"
    ],
    "wof:name":"Burgerman",
    "wof:placetype":"venue"
},
  "geometry": {"coordinates":[151.267578125,-33.8946304321],"type":"Point"}
}