{
  "type": "Feature",
  "properties": {
    "iso:country":"AU",
    "sg:address":"44 Churchill Ave",
    "sg:city":"Subiaco",
    "sg:classifiers":[
        {
            "category":"Health Services",
            "subcategory":"Doctor",
            "type":"Services"
        }
    ],
    "sg:phone":"+61 8 9388 1108",
    "sg:postcode":"6008",
    "sg:province":"WA",
    "sg:tags":[
        "medical",
        "practitioner"
    ],
    "wof:name":"Crocker Andrew",
    "wof:placetype":"venue"
},
  "geometry": {"coordinates":[115.83476257300001,-31.9478359222],"type":"Point"}
}