{
  "type": "Feature",
  "properties": {
    "addr:full":"2/ 16 St Thomas St Bronte NSW 2024",
    "addr:housenumber":"/ 16",
    "addr:postcode":"2024",
    "addr:street":"St Thomas St",
    "iso:country":"AU",
    "sg:address":"2/ 16 St Thomas St",
    "sg:city":"Bronte",
    "sg:classifiers":[
        {
            "category":"Building & Trades",
            "subcategory":"Landscaping Services",
            "type":"Services"
        }
    ],
    "sg:phone":"+61 412 136 553",
    "sg:postcode":"2024",
    "sg:province":"NSW",
    "sg:tags":[
        "gardener"
    ],
    "wof:name":"Sydney Garden Management",
    "wof:placetype":"venue"
},
  "geometry": {"coordinates":[151.26463317899999,-33.9050521851],"type":"Point"}
}