{
  "type": "Feature",
  "properties": {
    "iso:country":"AU",
    "sg:address":"Cnr Mt Dandenong Tourist Rd & Ridge Rd",
    "sg:city":"Olinda",
    "sg:classifiers":[
        {
            "category":"Real Estate",
            "subcategory":"Real Estate Agent",
            "type":"Services"
        }
    ],
    "sg:phone":"+61 3 9751 2299",
    "sg:postcode":"3788",
    "sg:province":"VIC",
    "wof:name":"Stockdale & Leggo Pty Ltd",
    "wof:placetype":"venue"
},
  "geometry": {"coordinates":[145.358795,-37.841602],"type":"Point"}
}