{
  "type": "Feature",
  "properties": {
    "iso:country":"AU",
    "sg:address":"Wrest Point Casino Sandy Bay Rd",
    "sg:city":"Hobart",
    "sg:classifiers":[
        {
            "category":"Retail",
            "subcategory":"Auto Rental",
            "type":"Services"
        }
    ],
    "sg:phone":"+61 3 6234 1341",
    "sg:postcode":"7000",
    "sg:province":"TAS",
    "sg:tags":[
        "bus",
        "truck"
    ],
    "wof:name":"Thrifty",
    "wof:placetype":"venue"
},
  "geometry": {"coordinates":[147.32765197800001,-42.886341095],"type":"Point"}
}