{
  "type": "Feature",
  "properties": {
    "iso:country":"AU",
    "sg:address":"74 Sandalwood Ave",
    "sg:city":"Dalby",
    "sg:classifiers":[
        {
            "category":"Building & Trades",
            "subcategory":"Construction",
            "type":"Services"
        }
    ],
    "sg:phone":"+61 429 624 469",
    "sg:postcode":"4405",
    "sg:province":"QLD",
    "sg:tags":[
        "earth",
        "excavating",
        "moving",
        "contractor"
    ],
    "wof:name":"Steve Tate",
    "wof:placetype":"venue"
},
  "geometry": {"coordinates":[151.249633789,-27.2107200623],"type":"Point"}
}