{
  "type": "Feature",
  "properties": {
    "addr:full":"Gaulds Estate Walker St Maryborough QLD 4650",
    "addr:postcode":"4650",
    "addr:street":"Walker St",
    "iso:country":"AU",
    "sg:address":"Gaulds Estate Walker St",
    "sg:city":"Maryborough",
    "sg:classifiers":[
        {
            "category":"Professional",
            "type":"Services"
        }
    ],
    "sg:phone":"+61 417 603 273",
    "sg:postcode":"4650",
    "sg:province":"QLD",
    "sg:tags":[
        "courier"
    ],
    "wof:name":"B & L Freight",
    "wof:placetype":"venue"
},
  "geometry": {"coordinates":[152.69729599999999,-25.528755],"type":"Point"}
}