{
  "type": "Feature",
  "properties": {
    "addr:full":"85 (Lower) West Burleigh Rd Burleigh Heads QLD 4220",
    "addr:housenumber":"85",
    "addr:postcode":"4220",
    "addr:street":"Lower West Burleigh Rd",
    "iso:country":"AU",
    "sg:address":"85 (Lower) West Burleigh Rd",
    "sg:city":"Burleigh Heads",
    "sg:classifiers":[
        {
            "category":"Retail",
            "subcategory":"Car Wash",
            "type":"Services"
        }
    ],
    "sg:phone":"+61 7 5576 7646",
    "sg:postcode":"4220",
    "sg:province":"QLD",
    "sg:tags":[
        "truck",
        "cleaning"
    ],
    "wof:name":"Shammys Hand Carwash & Cafe",
    "wof:placetype":"venue"
},
  "geometry": {"coordinates":[153.4425354,-28.1009922028],"type":"Point"}
}