{
  "type": "Feature",
  "properties": {
    "iso:country":"AU",
    "sg:address":"50 Short St",
    "sg:city":"Oyster Bay",
    "sg:classifiers":[
        {
            "category":"Professional",
            "subcategory":"Art Services",
            "type":"Services"
        }
    ],
    "sg:phone":"+61 2 9528 5392",
    "sg:postcode":"2225",
    "sg:province":"NSW",
    "sg:tags":[
        "graphic",
        "designer"
    ],
    "wof:name":"Fresh Approach Designs",
    "wof:placetype":"venue"
},
  "geometry": {"coordinates":[151.077880859,-34.0094223022],"type":"Point"}
}