{
  "type": "Feature",
  "properties": {
    "addr:full":"3/ 19 Lawson Crs Coffs Harbour NSW 2450",
    "addr:housenumber":"/ 19",
    "addr:postcode":"2450",
    "addr:street":"Lawson Crs",
    "iso:country":"AU",
    "sg:address":"3/ 19 Lawson Crs",
    "sg:city":"Coffs Harbour",
    "sg:classifiers":[
        {
            "category":"Home & Garden",
            "subcategory":"Carpets & Floor Coverings",
            "type":"Retail Goods"
        }
    ],
    "sg:phone":"+61 407 256 351",
    "sg:postcode":"2450",
    "sg:province":"NSW",
    "sg:tags":[
        "mat",
        "matting"
    ],
    "wof:name":"Coffs Mat Man",
    "wof:placetype":"venue"
},
  "geometry": {"coordinates":[153.11515800000001,-30.29701],"type":"Point"}
}