{
  "type": "Feature",
  "properties": {
    "iso:country":"AU",
    "sg:address":"3 Playford Mews",
    "sg:city":"Landsdale",
    "sg:classifiers":[
        {
            "category":"Home & Garden",
            "subcategory":"Building Materials",
            "type":"Retail Goods"
        }
    ],
    "sg:phone":"+61 8 9302 3334",
    "sg:postcode":"6065",
    "sg:province":"WA",
    "sg:tags":[
        "wall",
        "frame",
        "truss",
        "roof"
    ],
    "wof:name":"R & J Janter Enterprises",
    "wof:placetype":"venue"
},
  "geometry": {"coordinates":[115.860427856,-31.8054904938],"type":"Point"}
}