{
  "type": "Feature",
  "properties": {
    "addr:full":"19 Duck St Longreach QLD 4730",
    "addr:housenumber":"19",
    "addr:postcode":"4730",
    "addr:street":"Duck St",
    "iso:country":"AU",
    "sg:address":"19 Duck St",
    "sg:city":"Longreach",
    "sg:classifiers":[
        {
            "category":"Organizations",
            "subcategory":"Community Association",
            "type":"Services"
        }
    ],
    "sg:phone":"+61 7 4658 1416",
    "sg:postcode":"4730",
    "sg:province":"QLD",
    "sg:tags":[
        "organisation",
        "family",
        "welfare"
    ],
    "wof:name":"Longreach Home & Community Care Inc.",
    "wof:placetype":"venue"
},
  "geometry": {"coordinates":[144.24955700000001,-23.440796],"type":"Point"}
}