{
  "type": "Feature",
  "properties": {
    "addr:full":"1 Bedford St New Town TAS 7008",
    "addr:housenumber":"1",
    "addr:postcode":"7008",
    "addr:street":"Bedford St",
    "iso:country":"AU",
    "sg:address":"1 Bedford St",
    "sg:city":"New Town",
    "sg:classifiers":[
        {
            "category":"Real Estate",
            "subcategory":"Real Estate Agent",
            "type":"Services"
        }
    ],
    "sg:phone":"+61 3 6228 9119",
    "sg:postcode":"7008",
    "sg:province":"TAS",
    "wof:name":"Hilder Real Estate Services",
    "wof:placetype":"venue"
},
  "geometry": {"coordinates":[147.306884766,-42.8669967651],"type":"Point"}
}