{
  "type": "Feature",
  "properties": {
    "iso:country":"AU",
    "sg:address":"Shop 6/ 55 Kiora Rd",
    "sg:city":"Miranda",
    "sg:classifiers":[
        {
            "category":"Shopping",
            "subcategory":"Mobile Phones",
            "type":"Retail Goods"
        }
    ],
    "sg:phone":"+61 2 9542 7008",
    "sg:postcode":"2228",
    "sg:province":"NSW",
    "sg:tags":[
        "telephone",
        "accessory"
    ],
    "wof:name":"Leading Edge Electronics",
    "wof:placetype":"venue"
},
  "geometry": {"coordinates":[151.101852417,-34.0352706909],"type":"Point"}
}