{
  "type": "Feature",
  "properties": {
    "addr:full":"Shp 3/ 1 Diamond St Cooroy QLD 4563",
    "addr:housenumber":"/ 1",
    "addr:postcode":"4563",
    "addr:street":"Diamond St",
    "iso:country":"AU",
    "sg:address":"Shp 3/ 1 Diamond St",
    "sg:city":"Cooroy",
    "sg:classifiers":[
        {
            "category":"Food & Beverages",
            "subcategory":"Bakery",
            "type":"Retail Goods"
        }
    ],
    "sg:phone":"+61 7 5447 7100",
    "sg:postcode":"4563",
    "sg:province":"QLD",
    "sg:tags":[
        "baker"
    ],
    "wof:name":"Cooroy Hot Bread Kitchen",
    "wof:placetype":"venue"
},
  "geometry": {"coordinates":[152.91166687,-26.416595459],"type":"Point"}
}