{
  "type": "Feature",
  "properties": {
    "addr:full":"1199 Cavendish Rd Mt Gravatt East QLD 4122",
    "addr:housenumber":"1199",
    "addr:postcode":"4122",
    "addr:street":"Cavendish Rd",
    "iso:country":"AU",
    "sg:address":"1199 Cavendish Rd",
    "sg:city":"Mt Gravatt East",
    "sg:classifiers":[
        {
            "category":"Retail",
            "subcategory":"Auto Repair",
            "type":"Services"
        }
    ],
    "sg:phone":"+61 7 3849 3388",
    "sg:postcode":"4122",
    "sg:province":"QLD",
    "sg:tags":[
        "repairer",
        "motor",
        "engineer"
    ],
    "wof:name":"Lyons Mechanical",
    "wof:placetype":"venue"
},
  "geometry": {"coordinates":[153.09332275400001,-27.5311431885],"type":"Point"}
}