{
  "type": "Feature",
  "properties": {
    "addr:full":"769 Fairfield Rd Yeerongpilly QLD 4105",
    "addr:housenumber":"769",
    "addr:postcode":"4105",
    "addr:street":"Fairfield Rd",
    "iso:country":"AU",
    "sg:address":"769 Fairfield Rd",
    "sg:city":"Yeerongpilly",
    "sg:classifiers":[
        {
            "category":"Building & Trades",
            "subcategory":"Construction",
            "type":"Services"
        }
    ],
    "sg:phone":"+61 7 3848 2581",
    "sg:postcode":"4105",
    "sg:province":"QLD",
    "sg:tags":[
        "industrial",
        "commercial",
        "air conditioning"
    ],
    "wof:name":"Siganto & Stacey Pty Ltd",
    "wof:placetype":"venue"
},
  "geometry": {"coordinates":[153.01205444300001,-27.5309352875],"type":"Point"}
}