{
  "type": "Feature",
  "properties": {
    "iso:country":"AU",
    "sg:address":"38 Burton St",
    "sg:city":"Concord",
    "sg:classifiers":[
        {
            "category":"Health Services",
            "subcategory":"Nursing And Care Facility",
            "type":"Services"
        }
    ],
    "sg:phone":"+61 2 9747 5963",
    "sg:postcode":"2137",
    "sg:province":"NSW",
    "sg:tags":[
        "home"
    ],
    "wof:name":"St Marys Villa Hostel & Nursing Home",
    "wof:placetype":"venue"
},
  "geometry": {"coordinates":[151.104782105,-33.8677711487],"type":"Point"}
}