{
  "type": "Feature",
  "properties": {
    "addr:full":"33 Salisbury St Botany NSW 2019",
    "addr:housenumber":"33",
    "addr:postcode":"2019",
    "addr:street":"Salisbury St",
    "iso:country":"AU",
    "sg:address":"33 Salisbury St",
    "sg:city":"Botany",
    "sg:classifiers":[
        {
            "category":"Real Estate",
            "subcategory":"Architect",
            "type":"Services"
        }
    ],
    "sg:phone":"+61 421 630 776",
    "sg:postcode":"2019",
    "sg:province":"NSW",
    "wof:name":"Workshop 1 Pty Ltd Dunn + Hillam Architects",
    "wof:placetype":"venue"
},
  "geometry": {"coordinates":[151.201934814,-33.9498596191],"type":"Point"}
}