{
  "type": "Feature",
  "properties": {
    "iso:country":"AU",
    "sg:address":"145 Walsh St",
    "sg:city":"Mareeba",
    "sg:classifiers":[
        {
            "category":"Retail",
            "subcategory":"Repair Shop",
            "type":"Services"
        }
    ],
    "sg:phone":"+61 7 4092 2166",
    "sg:postcode":"4880",
    "sg:province":"QLD",
    "sg:tags":[
        "windscreen"
    ],
    "wof:name":"Mareeba Radiators & Windscreens",
    "wof:placetype":"venue"
},
  "geometry": {"coordinates":[145.41807556099999,-17.0052204132],"type":"Point"}
}