{
  "type": "Feature",
  "properties": {
    "iso:country":"AU",
    "sg:address":"87 Victoria Rd",
    "sg:city":"Rozelle",
    "sg:classifiers":[
        {
            "category":"Retail",
            "subcategory":"Funeral Services",
            "type":"Services"
        }
    ],
    "sg:phone":"+61 2 9555 7551",
    "sg:postcode":"2039",
    "sg:province":"NSW",
    "sg:tags":[
        "director"
    ],
    "wof:name":"Mannings Funerals",
    "wof:placetype":"venue"
},
  "geometry": {"coordinates":[151.17149352999999,-33.8646125793],"type":"Point"}
}