{
  "type": "Feature",
  "properties": {
    "iso:country":"AU",
    "sg:address":"U49/ 8 dunmore Tce",
    "sg:city":"Auchenflower",
    "sg:classifiers":[
        {
            "category":"Health Services",
            "subcategory":"Doctor",
            "type":"Services"
        }
    ],
    "sg:phone":"+61 1300 731 117",
    "sg:postcode":"4066",
    "sg:province":"QLD",
    "sg:tags":[
        "occupational",
        "safety"
    ],
    "wof:name":"Quality Business Documents",
    "wof:placetype":"venue"
},
  "geometry": {"coordinates":[152.99830627399999,-27.4774570465],"type":"Point"}
}