{
  "type": "Feature",
  "properties": {
    "iso:country":"AU",
    "sg:address":"32 Denison St",
    "sg:city":"Camperdown",
    "sg:classifiers":[
        {
            "category":"Shopping",
            "subcategory":"Stationery & Office Supplies",
            "type":"Retail Goods"
        }
    ],
    "sg:phone":"+61 2 9565 5035",
    "sg:postcode":"2050",
    "sg:province":"NSW",
    "sg:tags":[
        "equipment",
        "display",
        "exhibition"
    ],
    "wof:name":"Cavalier Design & Exhibitions",
    "wof:placetype":"venue"
},
  "geometry": {"coordinates":[151.177734,-33.896568],"type":"Point"}
}