{
  "type": "Feature",
  "properties": {
    "addr:full":"18 Victoria Rd Hawthorn East VIC 3123",
    "addr:housenumber":"18",
    "addr:postcode":"3123",
    "addr:street":"Victoria Rd",
    "iso:country":"AU",
    "sg:address":"18 Victoria Rd",
    "sg:city":"Hawthorn East",
    "sg:classifiers":[
        {
            "category":"Retail",
            "subcategory":"Auto Repair",
            "type":"Services"
        }
    ],
    "sg:phone":"+61 3 9882 5243",
    "sg:postcode":"3123",
    "sg:province":"VIC",
    "sg:tags":[
        "testing",
        "inspection",
        "motor",
        "vehicle"
    ],
    "wof:name":"Dallmore Automotive",
    "wof:placetype":"venue"
},
  "geometry": {"coordinates":[145.047042847,-37.8222465515],"type":"Point"}
}