{
  "type": "Feature",
  "properties": {
    "addr:full":"9 Willow St Churchill VIC 3842",
    "addr:housenumber":"9",
    "addr:postcode":"3842",
    "addr:street":"Willow St",
    "iso:country":"AU",
    "sg:address":"9 Willow St",
    "sg:city":"Churchill",
    "sg:classifiers":[
        {
            "category":"Building & Trades",
            "subcategory":"Plumbing",
            "type":"Services"
        }
    ],
    "sg:phone":"+61 3 5122 1500",
    "sg:postcode":"3842",
    "sg:province":"VIC",
    "sg:tags":[
        "plumber",
        "gasfitters"
    ],
    "wof:name":"Aar Plumbing",
    "wof:placetype":"venue"
},
  "geometry": {"coordinates":[146.41795349099999,-38.3031616211],"type":"Point"}
}