{
  "type": "Feature",
  "properties": {
    "addr:full":"4 McGill St Shepparton VIC 3630",
    "addr:housenumber":"4",
    "addr:postcode":"3630",
    "addr:street":"Mcgill St",
    "iso:country":"AU",
    "sg:address":"4 McGill St",
    "sg:city":"Shepparton",
    "sg:classifiers":[
        {
            "category":"Building & Trades",
            "subcategory":"Construction",
            "type":"Services"
        }
    ],
    "sg:phone":"+61 3 5821 9566",
    "sg:postcode":"3630",
    "sg:province":"VIC",
    "sg:tags":[
        "earth",
        "excavating",
        "moving",
        "contractor"
    ],
    "wof:name":"Williams Graeme Constructions Pty Ltd",
    "wof:placetype":"venue"
},
  "geometry": {"coordinates":[145.42904663100001,-36.3650131226],"type":"Point"}
}