{
  "type": "Feature",
  "properties": {
    "iso:country":"AU",
    "sg:address":"15 Denison St",
    "sg:city":"Newcastle West",
    "sg:classifiers":[
        {
            "category":"Cafe",
            "type":"Food & Drink"
        }
    ],
    "sg:phone":"+61 2 4961 0223",
    "sg:postcode":"2302",
    "sg:province":"NSW",
    "wof:name":"Soapbox Cafe",
    "wof:placetype":"venue"
},
  "geometry": {"coordinates":[151.75735499999999,-32.924774],"type":"Point"}
}