{
  "type": "Feature",
  "properties": {
    "addr:full":"286 North Rd Eastwood NSW 2122",
    "addr:housenumber":"286",
    "addr:postcode":"2122",
    "addr:street":"North Rd",
    "iso:country":"AU",
    "sg:address":"286 North Rd",
    "sg:city":"Eastwood",
    "sg:classifiers":[
        {
            "category":"Health Services",
            "subcategory":"Chiropractor",
            "type":"Services"
        }
    ],
    "sg:phone":"+61 2 9858 4290",
    "sg:postcode":"2122",
    "sg:province":"NSW",
    "wof:name":"Absolute Care Chiropractic & Sports Therapy",
    "wof:placetype":"venue"
},
  "geometry": {"coordinates":[151.09492492699999,-33.7842063904],"type":"Point"}
}