{
  "type": "Feature",
  "properties": {
    "iso:country":"AU",
    "sg:address":"Btwn Cathcart & Malabar St 69 Railway Pde",
    "sg:city":"Fairfield",
    "sg:classifiers":[
        {
            "category":"Retail",
            "subcategory":"Veterinary Services",
            "type":"Services"
        }
    ],
    "sg:phone":"+61 2 9726 1845",
    "sg:postcode":"2165",
    "sg:province":"NSW",
    "sg:tags":[
        "surgeon"
    ],
    "wof:name":"Groat Robert",
    "wof:placetype":"venue"
},
  "geometry": {"coordinates":[150.940185547,-33.8778648376],"type":"Point"}
}