{
  "type": "Feature",
  "properties": {
    "addr:full":"43 Kings Ave Golden Grove SA 5125",
    "addr:housenumber":"43",
    "addr:postcode":"5125",
    "addr:street":"Kings Ave",
    "iso:country":"AU",
    "sg:address":"43 Kings Ave",
    "sg:city":"Golden Grove",
    "sg:classifiers":[
        {
            "category":"Government",
            "subcategory":"Fire Station",
            "type":"Public Place"
        }
    ],
    "sg:phone":"+61 8 8288 1005",
    "sg:postcode":"5125",
    "sg:province":"SA",
    "sg:tags":[
        "equipment",
        "protection",
        "consultant"
    ],
    "wof:name":"Deluge Fire Systems",
    "wof:placetype":"venue"
},
  "geometry": {"coordinates":[138.72302199999999,-34.778332],"type":"Point"}
}