{
  "type": "Feature",
  "properties": {
    "iso:country":"AU",
    "sg:address":"43 Kings Ave",
    "sg:city":"Golden Grove",
    "sg:classifiers":[
        {
            "category":"Government",
            "subcategory":"Fire Station",
            "type":"Public Place"
        }
    ],
    "sg:phone":"+61 8 8288 1005",
    "sg:postcode":"5125",
    "sg:province":"SA",
    "sg:tags":[
        "equipment",
        "protection",
        "consultant"
    ],
    "wof:name":"Deluge Fire Systems",
    "wof:placetype":"venue"
},
  "geometry": {"coordinates":[138.723022,-34.778332],"type":"Point"}
}