{
  "type": "Feature",
  "properties": {
    "iso:country":"AU",
    "sg:address":"Hannaford Rd",
    "sg:city":"Hannaford",
    "sg:classifiers":[
        {
            "category":"Education",
            "subcategory":"School",
            "type":"Public Place"
        }
    ],
    "sg:phone":"+61 7 4665 9239",
    "sg:postcode":"4406",
    "sg:province":"QLD",
    "sg:tags":[
        "state",
        "except",
        "nsw"
    ],
    "wof:name":"Hannaford Primary",
    "wof:placetype":"venue"
},
  "geometry": {"coordinates":[150.059448242,-27.3488006592],"type":"Point"}
}