{
  "type": "Feature",
  "properties": {
    "iso:country":"AU",
    "sg:address":"116 Russell St",
    "sg:city":"Toowoomba",
    "sg:classifiers":[
        {
            "category":"Health Services",
            "subcategory":"Medical Lab",
            "type":"Services"
        }
    ],
    "sg:phone":"+61 7 4616 6550",
    "sg:postcode":"4350",
    "sg:province":"QLD",
    "sg:tags":[
        "laboratory",
        "pathology"
    ],
    "wof:name":"Queensland Health Pathology Service",
    "wof:placetype":"venue"
},
  "geometry": {"coordinates":[151.948288,-27.558418],"type":"Point"}
}