{
  "type": "Feature",
  "properties": {
    "addr:full":"Lvl 3, 448 St Kilda Rd Melbourne VIC 3004",
    "addr:housenumber":"448",
    "addr:postcode":"3004",
    "addr:street":"St Kilda Rd",
    "iso:country":"AU",
    "sg:address":"Lvl 3, 448 St Kilda Rd",
    "sg:city":"Melbourne",
    "sg:classifiers":[
        {
            "category":"Transit Center",
            "subcategory":"Freight",
            "type":"Transportation"
        }
    ],
    "sg:phone":"+61 3 9861 1300",
    "sg:postcode":"3004",
    "sg:province":"VIC",
    "sg:tags":[
        "agent",
        "shipping"
    ],
    "wof:name":"Horizon Shipping Agencies P/L",
    "wof:placetype":"venue"
},
  "geometry": {"coordinates":[144.97604370100001,-37.8386077881],"type":"Point"}
}