{
  "type": "Feature",
  "properties": {
    "iso:country":"AU",
    "sg:address":"1 Bendigo St",
    "sg:city":"Ravenswood",
    "sg:classifiers":[
        {
            "category":"Social Services",
            "subcategory":"Child Care",
            "type":"Services"
        }
    ],
    "sg:phone":"+61 3 6339 2806",
    "sg:postcode":"7250",
    "sg:province":"TAS",
    "sg:tags":[
        "shearer"
    ],
    "wof:name":"Howells Shearing",
    "wof:placetype":"venue"
},
  "geometry": {"coordinates":[147.16856384299999,-41.4106864929],"type":"Point"}
}