{
  "type": "Feature",
  "properties": {
    "addr:full":"2a Mangerton Rd Mangerton NSW 2500",
    "addr:housenumber":"2a",
    "addr:postcode":"2500",
    "addr:street":"Mangerton Rd",
    "iso:country":"AU",
    "sg:address":"2a Mangerton Rd",
    "sg:city":"Mangerton",
    "sg:classifiers":[
        {
            "category":"Fast Food",
            "type":"Food & Drink"
        }
    ],
    "sg:phone":"+61 2 4225 2100",
    "sg:postcode":"2500",
    "sg:province":"NSW",
    "sg:tags":[
        "away",
        "take"
    ],
    "wof:name":"Mangerton Pizza & Trattoria",
    "wof:placetype":"venue"
},
  "geometry": {"coordinates":[150.877579,-34.426285],"type":"Point"}
}