{
  "type": "Feature",
  "properties": {
    "addr:full":"Lv 1, 45 Marrickville Rd Marrickville NSW 2204",
    "addr:housenumber":"45",
    "addr:postcode":"2204",
    "addr:street":"Marrickville Rd",
    "iso:country":"AU",
    "sg:address":"Lv 1, 45 Marrickville Rd",
    "sg:city":"Marrickville",
    "sg:classifiers":[
        {
            "category":"Professional",
            "subcategory":"Art Services",
            "type":"Services"
        }
    ],
    "sg:phone":"+61 2 9557 0917",
    "sg:postcode":"2204",
    "sg:province":"NSW",
    "sg:tags":[
        "graphic",
        "designer"
    ],
    "wof:name":"messy design",
    "wof:placetype":"venue"
},
  "geometry": {"coordinates":[151.16333,-33.914143],"type":"Point"}
}