{
  "type": "Feature",
  "properties": {
    "addr:full":"245 Chalmers St Redfern NSW 2016",
    "addr:housenumber":"245",
    "addr:postcode":"2016",
    "addr:street":"Chalmers St",
    "iso:country":"AU",
    "sg:address":"245 Chalmers St",
    "sg:city":"Redfern",
    "sg:classifiers":[
        {
            "category":"Professional",
            "subcategory":"Employment Agencies",
            "type":"Services"
        }
    ],
    "sg:phone":"+61 2 9319 0066",
    "sg:postcode":"2016",
    "sg:province":"NSW",
    "sg:tags":[
        "theatrical",
        "managers",
        "agent",
        "producer"
    ],
    "wof:name":"Performing Lines Ltd The",
    "wof:placetype":"venue"
},
  "geometry": {"coordinates":[151.205200195,-33.893283844],"type":"Point"}
}