{
  "type": "Feature",
  "properties": {
    "iso:country":"AU",
    "sg:address":"12 Bonnal Rd",
    "sg:city":"Erina",
    "sg:classifiers":[
        {
            "category":"Retail",
            "subcategory":"Auto Repair",
            "type":"Services"
        }
    ],
    "sg:phone":"+61 2 4367 0522",
    "sg:postcode":"2250",
    "sg:province":"NSW",
    "sg:tags":[
        "body",
        "builder",
        "motor"
    ],
    "wof:name":"Splitfire Spark Plugs & Gauges",
    "wof:placetype":"venue"
},
  "geometry": {"coordinates":[151.38372802699999,-33.4351959229],"type":"Point"}
}