{
  "type": "Feature",
  "properties": {
    "addr:full":"Lot8/ Mckenny St Nairne SA 5252",
    "addr:postcode":"5252",
    "addr:street":"St",
    "iso:country":"AU",
    "sg:address":"Lot8/ Mckenny St",
    "sg:city":"Nairne",
    "sg:classifiers":[
        {
            "category":"Building & Trades",
            "subcategory":"Landscaping Services",
            "type":"Services"
        }
    ],
    "sg:phone":"+61 411 854 561",
    "sg:postcode":"5252",
    "sg:province":"SA",
    "sg:tags":[
        "stump",
        "tree",
        "felling",
        "removal"
    ],
    "wof:name":"Black Stump Tree Service",
    "wof:placetype":"venue"
},
  "geometry": {"coordinates":[138.91792297399999,-35.0424957275],"type":"Point"}
}