{
  "type": "Feature",
  "properties": {
    "addr:full":"313 Ballarto Rd Carrum Downs VIC 3201",
    "addr:housenumber":"313",
    "addr:postcode":"3201",
    "addr:street":"Ballarto Rd",
    "iso:country":"AU",
    "sg:address":"313 Ballarto Rd",
    "sg:city":"Carrum Downs",
    "sg:classifiers":[
        {
            "category":"Building & Trades",
            "subcategory":"Construction",
            "type":"Services"
        }
    ],
    "sg:phone":"+61 409 183 542",
    "sg:postcode":"3201",
    "sg:province":"VIC",
    "sg:tags":[
        "concrete",
        "treatment",
        "repair"
    ],
    "wof:name":"John Magro",
    "wof:placetype":"venue"
},
  "geometry": {"coordinates":[145.19132999999999,-38.116535],"type":"Point"}
}