{
  "type": "Feature",
  "properties": {
    "addr:full":"224 Victoria St Taree NSW 2430",
    "addr:housenumber":"224",
    "addr:postcode":"2430",
    "addr:street":"Victoria St",
    "iso:country":"AU",
    "sg:address":"224 Victoria St",
    "sg:city":"Taree",
    "sg:classifiers":[
        {
            "category":"Banks & Credit Unions",
            "subcategory":"Financial Services",
            "type":"Services"
        }
    ],
    "sg:phone":"+61 2 6557 7422",
    "sg:postcode":"2430",
    "sg:province":"NSW",
    "sg:tags":[
        "loan",
        "finance",
        "mortgage"
    ],
    "wof:name":"Mid North Coast Home Loans",
    "wof:placetype":"venue"
},
  "geometry": {"coordinates":[152.460114,-31.914122],"type":"Point"}
}