{
  "type": "Feature",
  "properties": {
    "iso:country":"AU",
    "sg:address":"Queen St",
    "sg:city":"Altona Meadows",
    "sg:classifiers":[
        {
            "category":"Sports & Exercise",
            "subcategory":"Sports Center",
            "type":"Entertainment"
        }
    ],
    "sg:phone":"+61 3 9360 9288",
    "sg:postcode":"3028",
    "sg:province":"VIC",
    "sg:tags":[
        "ground"
    ],
    "wof:name":"Altona Basketball/Netball Stadium",
    "wof:placetype":"venue"
},
  "geometry": {"coordinates":[144.778214,-37.871639],"type":"Point"}
}