{
  "type": "Feature",
  "properties": {
    "iso:country":"AU",
    "sg:address":"Level 6 39 London Cct",
    "sg:city":"Canberra",
    "sg:classifiers":[
        {
            "category":"Banks & Credit Unions",
            "subcategory":"Financial Services",
            "type":"Services"
        }
    ],
    "sg:phone":"+61 1800 688 688",
    "sg:postcode":"2600",
    "sg:province":"ACT",
    "sg:tags":[
        "advisory",
        "planning",
        "retirement"
    ],
    "wof:name":"Beresfords Personal Wealth Management",
    "wof:placetype":"venue"
},
  "geometry": {"coordinates":[149.127044678,-35.2794837952],"type":"Point"}
}