{
  "type": "Feature",
  "properties": {
    "addr:full":"1a Pratt St Wagga Wagga NSW 2650",
    "addr:housenumber":"1a",
    "addr:postcode":"2650",
    "addr:street":"Pratt St",
    "iso:country":"AU",
    "sg:address":"1a Pratt St",
    "sg:city":"Wagga Wagga",
    "sg:classifiers":[
        {
            "category":"Shopping",
            "subcategory":"Computers & Home Electronics",
            "type":"Retail Goods"
        }
    ],
    "sg:phone":"+61 2 6925 4363",
    "sg:postcode":"2650",
    "sg:province":"NSW",
    "sg:tags":[
        "equipment",
        "multimedia"
    ],
    "wof:name":"Historyelectronique",
    "wof:placetype":"venue"
},
  "geometry": {"coordinates":[147.35061645499999,-35.1390571594],"type":"Point"}
}