{
  "type": "Feature",
  "properties": {
    "iso:country":"AU",
    "sg:address":"1 Port Beach Rd",
    "sg:city":"North Fremantle",
    "sg:classifiers":[
        {
            "category":"Transit Center",
            "subcategory":"Freight",
            "type":"Transportation"
        }
    ],
    "sg:phone":"+61 8 9430 0111",
    "sg:postcode":"6159",
    "sg:province":"WA",
    "sg:tags":[
        "stevedore"
    ],
    "wof:name":"P & O Ports",
    "wof:placetype":"venue"
},
  "geometry": {"coordinates":[115.74582700000001,-32.035465],"type":"Point"}
}