{
  "type": "Feature",
  "properties": {
    "iso:country":"AU",
    "sg:address":"25 Nyrang St",
    "sg:city":"Lidcombe",
    "sg:classifiers":[
        {
            "category":"Shopping",
            "type":"Retail Goods"
        }
    ],
    "sg:phone":"+61 2 9649 0161",
    "sg:postcode":"2141",
    "sg:province":"NSW",
    "sg:tags":[
        "equipment",
        "safety",
        "accessory"
    ],
    "wof:name":"Norton Abrasives Pty Ltd",
    "wof:placetype":"venue"
},
  "geometry": {"coordinates":[151.04423523,-33.8533935547],"type":"Point"}
}