{
  "type": "Feature",
  "properties": {
    "addr:full":"412 Marion Rd Plympton SA 5038",
    "addr:housenumber":"412",
    "addr:postcode":"5038",
    "addr:street":"Marion Rd",
    "iso:country":"AU",
    "sg:address":"412 Marion Rd",
    "sg:city":"Plympton",
    "sg:classifiers":[
        {
            "category":"Fast Food",
            "type":"Food & Drink"
        }
    ],
    "sg:phone":"+61 8 8293 8600",
    "sg:postcode":"5038",
    "sg:province":"SA",
    "sg:tags":[
        "away",
        "take"
    ],
    "wof:name":"Plympton Pizza House",
    "wof:placetype":"venue"
},
  "geometry": {"coordinates":[138.55474853499999,-34.9655914307],"type":"Point"}
}