{
  "type": "Feature",
  "properties": {
    "addr:full":"20 Orchard Ave Everard Park SA 5035",
    "addr:housenumber":"20",
    "addr:postcode":"5035",
    "addr:street":"Orchard Ave",
    "iso:country":"AU",
    "sg:address":"20 Orchard Ave",
    "sg:city":"Everard Park",
    "sg:classifiers":[
        {
            "category":"Utilities",
            "subcategory":"Electric",
            "type":"Services"
        }
    ],
    "sg:phone":"+61 8 8297 1940",
    "sg:postcode":"5035",
    "sg:province":"SA",
    "sg:tags":[
        "electrical",
        "contractor"
    ],
    "wof:name":"Thomas Barry",
    "wof:placetype":"venue"
},
  "geometry": {"coordinates":[138.57493591299999,-34.9536476135],"type":"Point"}
}