{
  "type": "Feature",
  "properties": {
    "iso:country":"AU",
    "sg:address":"18 Marks St",
    "sg:city":"Chester Hill",
    "sg:classifiers":[
        {
            "category":"Recreation",
            "subcategory":"Fishing",
            "type":"Entertainment"
        }
    ],
    "sg:phone":"+61 2 9786 4666",
    "sg:postcode":"2162",
    "sg:province":"NSW",
    "sg:tags":[
        "tackle"
    ],
    "wof:name":"Cobalt Custom Rods Pty Ltd",
    "wof:placetype":"venue"
},
  "geometry": {"coordinates":[151.003509522,-33.8922080994],"type":"Point"}
}