{
  "type": "Feature",
  "properties": {
    "iso:country":"AU",
    "sg:address":"20 Hume Rd",
    "sg:city":"Laverton",
    "sg:classifiers":[
        {
            "category":"Home & Garden",
            "subcategory":"Building Materials",
            "type":"Retail Goods"
        }
    ],
    "sg:phone":"+61 3 9398 1242",
    "sg:postcode":"3028",
    "sg:province":"VIC",
    "sg:tags":[
        "pre-mixed",
        "concrete"
    ],
    "wof:name":"Remicon Australia Pty Ltd",
    "wof:placetype":"venue"
},
  "geometry": {"coordinates":[144.796814,-37.826256],"type":"Point"}
}