{
  "type": "Feature",
  "properties": {
    "iso:country":"AU",
    "sg:address":"Suite 9/ 140 Mounts Bay Rd",
    "sg:city":"Perth",
    "sg:classifiers":[
        {
            "category":"Health Services",
            "subcategory":"Doctor",
            "type":"Services"
        }
    ],
    "sg:phone":"+61 8 9226 0133",
    "sg:postcode":"6000",
    "sg:province":"WA",
    "sg:tags":[
        "medical",
        "practitioner"
    ],
    "wof:name":"Mount Nuclear Medicine",
    "wof:placetype":"venue"
},
  "geometry": {"coordinates":[115.84853363000001,-31.9553089142],"type":"Point"}
}