{
  "type": "Feature",
  "properties": {
    "iso:country":"AU",
    "sg:address":"307 Princes Hwy",
    "sg:city":"Werribee",
    "sg:classifiers":[
        {
            "category":"Home & Garden",
            "subcategory":"Hardware",
            "type":"Retail Goods"
        }
    ],
    "sg:phone":"+61 3 9741 8844",
    "sg:postcode":"3030",
    "sg:province":"VIC",
    "sg:tags":[
        "repair",
        "tool",
        "power"
    ],
    "wof:name":"Kango Australia Pty Ltd",
    "wof:placetype":"venue"
},
  "geometry": {"coordinates":[144.697037,-37.885696],"type":"Point"}
}