{
  "type": "Feature",
  "properties": {
    "addr:full":"75 Moorbell St Tarragindi QLD 4121",
    "addr:housenumber":"75",
    "addr:postcode":"4121",
    "addr:street":"Moorbell St",
    "iso:country":"AU",
    "sg:address":"75 Moorbell St",
    "sg:city":"Tarragindi",
    "sg:classifiers":[
        {
            "category":"Professional",
            "subcategory":"Employment Agencies",
            "type":"Services"
        }
    ],
    "sg:phone":"+61 7 3397 4225",
    "sg:postcode":"4121",
    "sg:province":"QLD",
    "wof:name":"Wiser People Pty Ltd",
    "wof:placetype":"venue"
},
  "geometry": {"coordinates":[153.05230712900001,-27.5330085754],"type":"Point"}
}