{
  "type": "Feature",
  "properties": {
    "iso:country":"AU",
    "sg:address":"173 Margaret St",
    "sg:city":"Toowoomba",
    "sg:classifiers":[
        {
            "category":"Personal",
            "subcategory":"Beauty Salon",
            "type":"Services"
        }
    ],
    "sg:phone":"+61 7 4638 0210",
    "sg:postcode":"4350",
    "sg:province":"QLD",
    "sg:tags":[
        "hairdresser"
    ],
    "wof:name":"Baraka",
    "wof:placetype":"venue"
},
  "geometry": {"coordinates":[151.954407,-27.561003],"type":"Point"}
}