{
  "type": "Feature",
  "properties": {
    "addr:full":"15 Tarcoola Rd Wagga Wagga NSW 2650",
    "addr:housenumber":"15",
    "addr:postcode":"2650",
    "addr:street":"Tarcoola Rd",
    "iso:country":"AU",
    "sg:address":"15 Tarcoola Rd",
    "sg:city":"Wagga Wagga",
    "sg:classifiers":[
        {
            "category":"Professional",
            "type":"Services"
        }
    ],
    "sg:phone":"+61 2 6931 0321",
    "sg:postcode":"2650",
    "sg:province":"NSW",
    "sg:tags":[
        "transport"
    ],
    "wof:name":"Simmos Express Freight",
    "wof:placetype":"venue"
},
  "geometry": {"coordinates":[147.39671325699999,-35.1216545105],"type":"Point"}
}