{
  "type": "Feature",
  "properties": {
    "iso:country":"AU",
    "sg:address":"98 Wyndham St",
    "sg:city":"Roma",
    "sg:classifiers":[
        {
            "category":"Commercial Area",
            "type":"Public Place"
        }
    ],
    "sg:phone":"+61 7 4622 7277",
    "sg:postcode":"4455",
    "sg:province":"QLD",
    "sg:tags":[
        "heavy",
        "carrier"
    ],
    "wof:name":"Wards Transport",
    "wof:placetype":"venue"
},
  "geometry": {"coordinates":[148.79043579099999,-26.5756721497],"type":"Point"}
}