{
  "type": "Feature",
  "properties": {
    "iso:country":"AU",
    "sg:address":"82 Redfern St",
    "sg:city":"Wetherill Park",
    "sg:classifiers":[
        {
            "category":"Building & Trades",
            "subcategory":"Construction",
            "type":"Services"
        }
    ],
    "sg:phone":"+61 2 9756 6946",
    "sg:postcode":"2164",
    "sg:province":"NSW",
    "sg:tags":[
        "welding"
    ],
    "wof:name":"ABMS Truck Repairs",
    "wof:placetype":"venue"
},
  "geometry": {"coordinates":[150.91470336899999,-33.8440132141],"type":"Point"}
}