{
  "type": "Feature",
  "properties": {
    "iso:country":"AU",
    "sg:address":"51 Passiflora Drv",
    "sg:city":"Forrestfield",
    "sg:classifiers":[
        {
            "category":"Professional",
            "subcategory":"Computer Services",
            "type":"Services"
        }
    ],
    "sg:phone":"+61 8 9453 2212",
    "sg:postcode":"6058",
    "sg:province":"WA",
    "sg:tags":[
        "equipment",
        "networking",
        "installation"
    ],
    "wof:name":"Home Computing Service & Repair",
    "wof:placetype":"venue"
},
  "geometry": {"coordinates":[116.013008118,-31.9832687378],"type":"Point"}
}