{
  "type": "Feature",
  "properties": {
    "iso:country":"AU",
    "sg:address":"4 Tranberg St",
    "sg:city":"Gladstone",
    "sg:classifiers":[
        {
            "category":"Wholesale",
            "subcategory":"Machinery & Supplies",
            "type":"Manufacturing & Wholesale Goods"
        }
    ],
    "sg:phone":"+61 7 4972 6511",
    "sg:postcode":"4680",
    "sg:province":"QLD",
    "sg:tags":[
        "rigging",
        "equipment",
        "hoisting"
    ],
    "wof:name":"John L. Robertson Pty Ltd",
    "wof:placetype":"venue"
},
  "geometry": {"coordinates":[151.24217224099999,-23.8392982483],"type":"Point"}
}