{
  "type": "Feature",
  "properties": {
    "addr:full":"91 Dick Ward Drv Coconut Grove NT 0810",
    "addr:housenumber":"91",
    "addr:postcode":"0810",
    "addr:street":"Dick Ward Drv",
    "iso:country":"AU",
    "sg:address":"91 Dick Ward Drv",
    "sg:city":"Coconut Grove",
    "sg:classifiers":[
        {
            "category":"Health Services",
            "subcategory":"Chiropractor",
            "type":"Services"
        }
    ],
    "sg:phone":"+61 8 8985 3144",
    "sg:postcode":"0810",
    "sg:province":"NT",
    "wof:name":"Phil Flowers",
    "wof:placetype":"venue"
},
  "geometry": {"coordinates":[130.85244750999999,-12.3998861313],"type":"Point"}
}