{
  "type": "Feature",
  "properties": {
    "addr:full":"Cnr Phoenix & Queen Sts Warragul VIC 3820",
    "addr:postcode":"3820",
    "iso:country":"AU",
    "sg:address":"Cnr Phoenix & Queen Sts",
    "sg:city":"Warragul",
    "sg:classifiers":[
        {
            "category":"Retail",
            "subcategory":"Auto Repair",
            "type":"Services"
        }
    ],
    "sg:phone":"+61 3 5622 3954",
    "sg:postcode":"3820",
    "sg:province":"VIC",
    "sg:tags":[
        "repairer",
        "motor",
        "engineer"
    ],
    "wof:name":"Ross Lyons Motors",
    "wof:placetype":"venue"
},
  "geometry": {"coordinates":[145.94236799999999,-38.162254],"type":"Point"}
}