{
  "type": "Feature",
  "properties": {
    "iso:country":"AU",
    "sg:address":"1 Profita Ave",
    "sg:city":"Sydenham",
    "sg:classifiers":[
        {
            "category":"Health Services",
            "subcategory":"Nursing And Care Facility",
            "type":"Services"
        }
    ],
    "sg:phone":"+61 3 9390 3351",
    "sg:postcode":"3037",
    "sg:province":"VIC",
    "sg:tags":[
        "home"
    ],
    "wof:name":"Belvedere Park Aged Care",
    "wof:placetype":"venue"
},
  "geometry": {"coordinates":[144.76911899999999,-37.704384],"type":"Point"}
}