{
  "type": "Feature",
  "properties": {
    "addr:full":"12 Finlayson Drv Aldgate SA 5154",
    "addr:housenumber":"12",
    "addr:postcode":"5154",
    "addr:street":"Finlayson Drv",
    "iso:country":"AU",
    "sg:address":"12 Finlayson Drv",
    "sg:city":"Aldgate",
    "sg:classifiers":[
        {
            "category":"Real Estate",
            "subcategory":"Real Estate Operator",
            "type":"Services"
        }
    ],
    "sg:phone":"+61 8 8370 8111",
    "sg:postcode":"5154",
    "sg:province":"SA",
    "sg:tags":[
        "concrete",
        "pumping"
    ],
    "wof:name":"Aldgate Concrete Pumping",
    "wof:placetype":"venue"
},
  "geometry": {"coordinates":[138.733642578,-35.0084915161],"type":"Point"}
}