{
  "type": "Feature",
  "properties": {
    "iso:country":"AU",
    "sg:address":"23 Granite St",
    "sg:city":"Port Macquarie",
    "sg:classifiers":[
        {
            "category":"Building & Trades",
            "subcategory":"Plumbing",
            "type":"Services"
        }
    ],
    "sg:phone":"+61 412 676 772",
    "sg:postcode":"2444",
    "sg:province":"NSW",
    "sg:tags":[
        "plumber",
        "gasfitters"
    ],
    "wof:name":"David Thomas Plumbing",
    "wof:placetype":"venue"
},
  "geometry": {"coordinates":[152.914276,-31.439371],"type":"Point"}
}