{
  "type": "Feature",
  "properties": {
    "addr:full":"3 Berwick St Lilydale VIC 3140",
    "addr:housenumber":"3",
    "addr:postcode":"3140",
    "addr:street":"Berwick St",
    "iso:country":"AU",
    "sg:address":"3 Berwick St",
    "sg:city":"Lilydale",
    "sg:classifiers":[
        {
            "category":"Personal",
            "subcategory":"Massage",
            "type":"Services"
        }
    ],
    "sg:phone":"+61 3 9735 5100",
    "sg:postcode":"3140",
    "sg:province":"VIC",
    "sg:tags":[
        "therapy"
    ],
    "wof:name":"Alfio Sorbello Mr",
    "wof:placetype":"venue"
},
  "geometry": {"coordinates":[145.356323242,-37.7566986084],"type":"Point"}
}