{
  "type": "Feature",
  "properties": {
    "addr:full":"Suite 2, 200- 214 sussex St Coburg North VIC 3058",
    "addr:housenumber":"200 214",
    "addr:postcode":"3058",
    "addr:street":"Sussex St",
    "iso:country":"AU",
    "sg:address":"Suite 2, 200- 214 sussex St",
    "sg:city":"Coburg North",
    "sg:classifiers":[
        {
            "category":"Professional",
            "subcategory":"Computer Services",
            "type":"Services"
        }
    ],
    "sg:phone":"+61 1300 667 773",
    "sg:postcode":"3058",
    "sg:province":"VIC",
    "sg:tags":[
        "package",
        "software"
    ],
    "wof:name":"Seekasoft",
    "wof:placetype":"venue"
},
  "geometry": {"coordinates":[144.95074462900001,-37.725402832],"type":"Point"}
}