{
  "type": "Feature",
  "properties": {
    "addr:full":"8 Humphrys St Junee NSW 2663",
    "addr:housenumber":"8",
    "addr:postcode":"2663",
    "addr:street":"Humphrys St",
    "iso:country":"AU",
    "sg:address":"8 Humphrys St",
    "sg:city":"Junee",
    "sg:classifiers":[
        {
            "category":"Fast Food",
            "type":"Food & Drink"
        }
    ],
    "sg:phone":"+61 2 6924 2220",
    "sg:postcode":"2663",
    "sg:province":"NSW",
    "sg:tags":[
        "away",
        "take"
    ],
    "wof:name":"Snack Happy Dine-In & Takeaway",
    "wof:placetype":"venue"
},
  "geometry": {"coordinates":[147.584594727,-34.8697853088],"type":"Point"}
}