{
  "type": "Feature",
  "properties": {
    "addr:full":"4 Richmond Ave Ballina NSW 2478",
    "addr:housenumber":"4",
    "addr:postcode":"2478",
    "addr:street":"Richmond Ave",
    "iso:country":"AU",
    "sg:address":"4 Richmond Ave",
    "sg:city":"Ballina",
    "sg:classifiers":[
        {
            "category":"Real Estate",
            "subcategory":"Real Estate Services",
            "type":"Services"
        }
    ],
    "sg:phone":"+61 2 6686 2880",
    "sg:postcode":"2478",
    "sg:province":"NSW",
    "sg:tags":[
        "valuer"
    ],
    "wof:name":"O&#039;Mara Jim",
    "wof:placetype":"venue"
},
  "geometry": {"coordinates":[153.552001953,-28.8682479858],"type":"Point"}
}