{
  "type": "Feature",
  "properties": {
    "addr:full":"62 Sturt St Mt Gambier SA 5290",
    "addr:housenumber":"62",
    "addr:postcode":"5290",
    "addr:street":"Sturt St",
    "iso:country":"AU",
    "sg:address":"62 Sturt St",
    "sg:city":"Mt Gambier",
    "sg:classifiers":[
        {
            "category":"Freight",
            "type":"Transportation"
        }
    ],
    "sg:phone":"+61 8 8725 5611",
    "sg:postcode":"5290",
    "sg:province":"SA",
    "sg:tags":[
        "light",
        "carrier"
    ],
    "wof:name":"Multigroup Distribution Services Pty Ltd",
    "wof:placetype":"venue"
},
  "geometry": {"coordinates":[140.78810100000001,-37.833233],"type":"Point"}
}