{
  "type": "Feature",
  "properties": {
    "iso:country":"AU",
    "sg:address":"4 Irving Rd",
    "sg:city":"Pakenham",
    "sg:classifiers":[
        {
            "category":"Banks & Credit Unions",
            "subcategory":"Bureau De Change",
            "type":"Services"
        }
    ],
    "sg:phone":"+61 3 5941 1251",
    "sg:postcode":"3810",
    "sg:province":"VIC",
    "sg:tags":[
        "repairs",
        "part",
        "appliance",
        "electrical"
    ],
    "wof:name":"Pakenham Appliance Service",
    "wof:placetype":"venue"
},
  "geometry": {"coordinates":[145.484818,-38.067551],"type":"Point"}
}