{
  "type": "Feature",
  "properties": {
    "addr:full":"PO Box 173 North Tamborine QLD 4272",
    "addr:postcode":"4272",
    "addr:street":"North",
    "iso:country":"AU",
    "sg:address":"PO Box 173",
    "sg:city":"North Tamborine",
    "sg:classifiers":[
        {
            "category":"Utilities",
            "subcategory":"Water",
            "type":"Services"
        }
    ],
    "sg:phone":"+61 7 5545 1993",
    "sg:postcode":"4272",
    "sg:province":"QLD",
    "sg:tags":[
        "cartage"
    ],
    "wof:name":"Ausflo Water Industries",
    "wof:placetype":"venue"
},
  "geometry": {"coordinates":[153.18447875999999,-27.9284591675],"type":"Point"}
}