{
  "type": "Feature",
  "properties": {
    "addr:full":"Shop 6/ 25 Allamanda Drv Daisy Hill QLD 4127",
    "addr:housenumber":"shop 6 / 25",
    "addr:postcode":"4127",
    "addr:street":"Allamanda Drv",
    "iso:country":"AU",
    "sg:address":"Shop 6/ 25 Allamanda Drv",
    "sg:city":"Daisy Hill",
    "sg:classifiers":[
        {
            "category":"Personal",
            "subcategory":"Barber",
            "type":"Services"
        }
    ],
    "sg:phone":"+61 7 3208 1482",
    "sg:postcode":"4127",
    "sg:province":"QLD",
    "wof:name":"Daisy Hill Barber",
    "wof:placetype":"venue"
},
  "geometry": {"coordinates":[153.15635681099999,-27.6443843842],"type":"Point"}
}