{
  "type": "Feature",
  "properties": {
    "addr:full":"PO Box 131 Waramanga ACT 2611",
    "addr:postcode":"2611",
    "iso:country":"AU",
    "sg:address":"PO Box 131",
    "sg:city":"Waramanga",
    "sg:classifiers":[
        {
            "category":"Recreation",
            "type":"Entertainment"
        }
    ],
    "sg:phone":"+61 402 456 981",
    "sg:postcode":"2611",
    "sg:province":"ACT",
    "sg:tags":[
        "children's",
        "play",
        "programme"
    ],
    "wof:name":"Dancekids",
    "wof:placetype":"venue"
},
  "geometry": {"coordinates":[149.06007385300001,-35.3539009094],"type":"Point"}
}