{
  "type": "Feature",
  "properties": {
    "iso:country":"AU",
    "sg:address":"10 Keiley St",
    "sg:city":"Marsfield",
    "sg:classifiers":[
        {
            "category":"Manufacturing",
            "subcategory":"Wood Products",
            "type":"Manufacturing & Wholesale Goods"
        }
    ],
    "sg:phone":"+61 402 114 270",
    "sg:postcode":"2122",
    "sg:province":"NSW",
    "sg:tags":[
        "pallet",
        "platform"
    ],
    "wof:name":"Pallet Logistics Pty Ltd",
    "wof:placetype":"venue"
},
  "geometry": {"coordinates":[151.10356140100001,-33.7840385437],"type":"Point"}
}