{
  "type": "Feature",
  "properties": {
    "iso:country":"AU",
    "sg:address":"1/ 22 Kateena St",
    "sg:city":"Regency Park",
    "sg:classifiers":[
        {
            "category":"Home & Garden",
            "subcategory":"Building Materials",
            "type":"Retail Goods"
        }
    ],
    "sg:phone":"+61 8 8445 9002",
    "sg:postcode":"5010",
    "sg:province":"SA",
    "sg:tags":[
        "shutter",
        "roller",
        "grille"
    ],
    "wof:name":"Ansa Doors Pty Ltd",
    "wof:placetype":"venue"
},
  "geometry": {"coordinates":[138.56959533700001,-34.8558959961],"type":"Point"}
}