{
  "type": "Feature",
  "properties": {
    "iso:country":"AU",
    "sg:address":"118 Nicklin Way",
    "sg:city":"Kawana Waters",
    "sg:classifiers":[
        {
            "category":"Government",
            "subcategory":"Customs House",
            "type":"Public Place"
        }
    ],
    "sg:phone":"+61 7 5437 7751",
    "sg:postcode":"4575",
    "sg:province":"QLD",
    "sg:tags":[
        "title",
        "management",
        "stratum"
    ],
    "wof:name":"AAA Certified Body Corporate Management",
    "wof:placetype":"venue"
},
  "geometry": {"coordinates":[153.122391,-26.727098],"type":"Point"}
}