{
  "type": "Feature",
  "properties": {
    "iso:country":"AU",
    "sg:address":"Shop 6/ 15 Main St",
    "sg:city":"North Tamborine",
    "sg:classifiers":[
        {
            "category":"Food & Beverages",
            "subcategory":"Specialty",
            "type":"Retail Goods"
        }
    ],
    "sg:phone":"+61 7 5545 0499",
    "sg:postcode":"4272",
    "sg:province":"QLD",
    "sg:tags":[
        "product",
        "health"
    ],
    "wof:name":"Olive Branch Health Food Store The",
    "wof:placetype":"venue"
},
  "geometry": {"coordinates":[153.18539428700001,-27.9260234833],"type":"Point"}
}