{
  "type": "Feature",
  "properties": {
    "addr:full":"PO Box 43 Exmouth WA 6707",
    "addr:postcode":"6707",
    "iso:country":"AU",
    "sg:address":"PO Box 43",
    "sg:city":"Exmouth",
    "sg:classifiers":[
        {
            "category":"Recreation",
            "subcategory":"Boat Charter",
            "type":"Entertainment"
        }
    ],
    "sg:phone":"+61 8 9949 1620",
    "sg:postcode":"6707",
    "sg:province":"WA",
    "wof:name":"MaKaira II Pty Ltd",
    "wof:placetype":"venue"
},
  "geometry": {"coordinates":[114.133277893,-21.9462604523],"type":"Point"}
}