{
  "type": "Feature",
  "properties": {
    "addr:full":"83 Mort St Lithgow NSW 2790",
    "addr:housenumber":"83",
    "addr:postcode":"2790",
    "addr:street":"Mort St",
    "iso:country":"AU",
    "sg:address":"83 Mort St",
    "sg:city":"Lithgow",
    "sg:classifiers":[
        {
            "category":"Real Estate",
            "subcategory":"Surveying",
            "type":"Services"
        }
    ],
    "sg:phone":"+61 2 6351 4667",
    "sg:postcode":"2790",
    "sg:province":"NSW",
    "sg:tags":[
        "surveyor",
        "land"
    ],
    "wof:name":"Elliston T",
    "wof:placetype":"venue"
},
  "geometry": {"coordinates":[150.160324097,-33.4814682007],"type":"Point"}
}