{
  "type": "Feature",
  "properties": {
    "iso:country":"AU",
    "sg:address":"7 Rocklea Drv",
    "sg:city":"Torquay",
    "sg:classifiers":[
        {
            "category":"Retail",
            "subcategory":"Repair Shop",
            "type":"Services"
        }
    ],
    "sg:phone":"+61 418 313 381",
    "sg:postcode":"3228",
    "sg:province":"VIC",
    "sg:tags":[
        "leadlights"
    ],
    "wof:name":"Inner Light Stained Glass",
    "wof:placetype":"venue"
},
  "geometry": {"coordinates":[144.31427,-38.332291],"type":"Point"}
}