{
  "type": "Feature",
  "properties": {
    "addr:full":"Cnr Blackburn Rd & Peach Way Templestowe VIC 3106",
    "addr:postcode":"3106",
    "addr:street":"Cnr Blackburn Rd & Peach Way",
    "iso:country":"AU",
    "sg:address":"Cnr Blackburn Rd & Peach Way",
    "sg:city":"Templestowe",
    "sg:classifiers":[
        {
            "category":"Retail",
            "subcategory":"Veterinary Services",
            "type":"Services"
        }
    ],
    "sg:phone":"+61 3 9842 8833",
    "sg:postcode":"3106",
    "sg:province":"VIC",
    "sg:tags":[
        "surgeon"
    ],
    "wof:name":"McDonogh Jedda Dr",
    "wof:placetype":"venue"
},
  "geometry": {"coordinates":[145.16519165,-37.7710533142],"type":"Point"}
}