{
  "type": "Feature",
  "properties": {
    "iso:country":"AU",
    "sg:address":"84 Lipton Drv",
    "sg:city":"Thomastown",
    "sg:classifiers":[
        {
            "category":"Manufacturing",
            "subcategory":"Glass & Minerals",
            "type":"Manufacturing & Wholesale Goods"
        }
    ],
    "sg:phone":"+61 3 9460 3899",
    "sg:postcode":"3074",
    "sg:province":"VIC",
    "sg:tags":[
        "merchant",
        "granite",
        "marble"
    ],
    "sg:website":"http://www.perawaymarble.com.au",
    "wof:name":"Peraway Marble Aust Pty Ltd",
    "wof:placetype":"venue"
},
  "geometry": {"coordinates":[144.992263794,-37.6899032593],"type":"Point"}
}