{
  "type": "Feature",
  "properties": {
    "addr:full":"15 Glismann Rd Beaconsfield VIC 3807",
    "addr:housenumber":"15",
    "addr:postcode":"3807",
    "addr:street":"Glismann Rd",
    "iso:country":"AU",
    "sg:address":"15 Glismann Rd",
    "sg:city":"Beaconsfield",
    "sg:classifiers":[
        {
            "category":"Building & Trades",
            "subcategory":"Plumbing",
            "type":"Services"
        }
    ],
    "sg:phone":"+61 3 9707 2832",
    "sg:postcode":"3807",
    "sg:province":"VIC",
    "sg:tags":[
        "plumber",
        "gasfitters"
    ],
    "wof:name":"Beaconsfield Plumbing Service",
    "wof:placetype":"venue"
},
  "geometry": {"coordinates":[145.37710571299999,-38.0465431213],"type":"Point"}
}