{
  "type": "Feature",
  "properties": {
    "addr:full":"30 Henry St Belmont VIC 3216",
    "addr:housenumber":"30",
    "addr:postcode":"3216",
    "addr:street":"Henry St",
    "iso:country":"AU",
    "sg:address":"30 Henry St",
    "sg:city":"Belmont",
    "sg:classifiers":[
        {
            "category":"Personal",
            "subcategory":"Barber",
            "type":"Services"
        }
    ],
    "sg:phone":"+61 3 5241 9575",
    "sg:postcode":"3216",
    "sg:province":"VIC",
    "wof:name":"Don's Barber Shop",
    "wof:placetype":"venue"
},
  "geometry": {"coordinates":[144.32940673799999,-38.1836204529],"type":"Point"}
}