{
  "type": "Feature",
  "properties": {
    "addr:full":"92- 96 Giles Rd Redland Bay QLD 4165",
    "addr:housenumber":"96",
    "addr:postcode":"4165",
    "addr:street":"Giles Rd",
    "iso:country":"AU",
    "sg:address":"92- 96 Giles Rd",
    "sg:city":"Redland Bay",
    "sg:classifiers":[
        {
            "category":"Building & Trades",
            "subcategory":"Landscaping Services",
            "type":"Services"
        }
    ],
    "sg:phone":"+61 7 3829 0000",
    "sg:postcode":"4165",
    "sg:province":"QLD",
    "sg:tags":[
        "stump",
        "tree",
        "felling",
        "removal"
    ],
    "wof:name":"Redlands Tree Service",
    "wof:placetype":"venue"
},
  "geometry": {"coordinates":[153.26832580600001,-27.6124458313],"type":"Point"}
}