{
  "type": "Feature",
  "properties": {
    "addr:full":"4 Padauk Drv Nerang QLD 4211",
    "addr:housenumber":"4",
    "addr:postcode":"4211",
    "addr:street":"Padauk Drv",
    "iso:country":"AU",
    "sg:address":"4 Padauk Drv",
    "sg:city":"Nerang",
    "sg:classifiers":[
        {
            "category":"Professional",
            "subcategory":"Computer Services",
            "type":"Services"
        }
    ],
    "sg:phone":"+61 7 5596 1810",
    "sg:postcode":"4211",
    "sg:province":"QLD",
    "sg:tags":[
        "repairs",
        "upgrade",
        "equipment"
    ],
    "wof:name":"Asset Computer Services",
    "wof:placetype":"venue"
},
  "geometry": {"coordinates":[153.30581665,-28.0075054169],"type":"Point"}
}