{
  "type": "Feature",
  "properties": {
    "addr:full":"A1/ 632 Princes Hwy Tempe NSW 2044",
    "addr:housenumber":"/ 632",
    "addr:postcode":"2044",
    "addr:street":"Princes Hwy",
    "iso:country":"AU",
    "sg:address":"A1/ 632 Princes Hwy",
    "sg:city":"Tempe",
    "sg:classifiers":[
        {
            "category":"Wholesale",
            "subcategory":"Chemicals & Plastics",
            "type":"Manufacturing & Wholesale Goods"
        }
    ],
    "sg:phone":"+61 2 8347 1939",
    "sg:postcode":"2044",
    "sg:province":"NSW",
    "sg:tags":[
        "bag"
    ],
    "wof:name":"Sunshine Polybag",
    "wof:placetype":"venue"
},
  "geometry": {"coordinates":[151.16549699999999,-33.921368],"type":"Point"}
}