{
  "type": "Feature",
  "properties": {
    "addr:full":"40 Signal Hill Rd Dodges Ferry TAS 7173",
    "addr:housenumber":"40",
    "addr:postcode":"7173",
    "addr:street":"Signal Hill Rd",
    "iso:country":"AU",
    "sg:address":"40 Signal Hill Rd",
    "sg:city":"Dodges Ferry",
    "sg:classifiers":[
        {
            "category":"Building & Trades",
            "subcategory":"Construction",
            "type":"Services"
        }
    ],
    "sg:phone":"+61 419 350 404",
    "sg:postcode":"7173",
    "sg:province":"TAS",
    "sg:tags":[
        "fencing",
        "contractor"
    ],
    "wof:name":"Straight Line Fencing & Maintenance",
    "wof:placetype":"venue"
},
  "geometry": {"coordinates":[147.617431641,-42.8601379395],"type":"Point"}
}