{
  "type": "Feature",
  "properties": {
    "addr:full":"3 Diane Crt Warrandyte VIC 3113",
    "addr:housenumber":"3",
    "addr:postcode":"3113",
    "addr:street":"Diane Crt",
    "iso:country":"AU",
    "sg:address":"3 Diane Crt",
    "sg:city":"Warrandyte",
    "sg:classifiers":[
        {
            "category":"Health Services",
            "subcategory":"Health Practitioner",
            "type":"Services"
        }
    ],
    "sg:phone":"+61 3 9844 1268",
    "sg:postcode":"3113",
    "sg:province":"VIC",
    "sg:tags":[
        "psychologist"
    ],
    "wof:name":"Poon Carolyn",
    "wof:placetype":"venue"
},
  "geometry": {"coordinates":[145.19784545900001,-37.7484474182],"type":"Point"}
}