{
  "type": "Feature",
  "properties": {
    "addr:full":"19 Whiting St Artarmon NSW 2064",
    "addr:housenumber":"19",
    "addr:postcode":"2064",
    "addr:street":"Whiting St",
    "iso:country":"AU",
    "sg:address":"19 Whiting St",
    "sg:city":"Artarmon",
    "sg:classifiers":[
        {
            "category":"Professional",
            "subcategory":"Business Services",
            "type":"Services"
        }
    ],
    "sg:phone":"+61 2 9966 8022",
    "sg:postcode":"2064",
    "sg:province":"NSW",
    "sg:tags":[
        "management",
        "event"
    ],
    "sg:website":"http://www.daylight.com.au",
    "wof:name":"Daylight International",
    "wof:placetype":"venue"
},
  "geometry": {"coordinates":[151.18414306599999,-33.8146057129],"type":"Point"}
}