{
  "type": "Feature",
  "properties": {
    "addr:full":"59 Park Ave Streaky Bay SA 5680",
    "addr:housenumber":"59",
    "addr:postcode":"5680",
    "addr:street":"Park Ave",
    "iso:country":"AU",
    "sg:address":"59 Park Ave",
    "sg:city":"Streaky Bay",
    "sg:classifiers":[
        {
            "category":"Retail",
            "subcategory":"Auto Repair",
            "type":"Services"
        }
    ],
    "sg:phone":"+61 8 8680 2526",
    "sg:postcode":"5680",
    "sg:province":"SA",
    "sg:tags":[
        "repairer",
        "motor",
        "engineer"
    ],
    "wof:name":"Buckley R M & P A",
    "wof:placetype":"venue"
},
  "geometry": {"coordinates":[134.211013794,-32.8004150391],"type":"Point"}
}