{
  "type": "Feature",
  "properties": {
    "iso:country":"AU",
    "sg:address":"Daintree St",
    "sg:city":"Cloncurry",
    "sg:classifiers":[
        {
            "category":"Education",
            "subcategory":"School",
            "type":"Public Place"
        }
    ],
    "sg:phone":"+61 7 4742 8333",
    "sg:postcode":"4824",
    "sg:province":"QLD",
    "sg:tags":[
        "state",
        "except",
        "nsw"
    ],
    "wof:name":"Cloncurry Primary",
    "wof:placetype":"venue"
},
  "geometry": {"coordinates":[140.50932299999999,-20.704445],"type":"Point"}
}