{
  "type": "Feature",
  "properties": {
    "addr:full":"PO Box 7178 Gardenvale VIC 3185",
    "addr:postcode":"3185",
    "iso:country":"AU",
    "sg:address":"PO Box 7178",
    "sg:city":"Gardenvale",
    "sg:classifiers":[
        {
            "category":"Education",
            "subcategory":"Dance Studio",
            "type":"Public Place"
        }
    ],
    "sg:phone":"+61 418 500 729",
    "sg:postcode":"3185",
    "sg:province":"VIC",
    "sg:tags":[
        "venue",
        "tuition"
    ],
    "wof:name":"Banat El Balad Productions",
    "wof:placetype":"venue"
},
  "geometry": {"coordinates":[145.005325317,-37.8965415955],"type":"Point"}
}