{
  "type": "Feature",
  "properties": {
    "addr:full":"Gold Coast Hwy Palm Beach QLD 4221",
    "addr:postcode":"4221",
    "addr:street":"Gold Coast Hwy",
    "iso:country":"AU",
    "sg:address":"Gold Coast Hwy",
    "sg:city":"Palm Beach",
    "sg:classifiers":[
        {
            "category":"Home & Garden",
            "subcategory":"Building Materials",
            "type":"Retail Goods"
        }
    ],
    "sg:phone":"+61 7 5598 2737",
    "sg:postcode":"4221",
    "sg:province":"QLD",
    "sg:tags":[
        "ventilating",
        "equipment",
        "system"
    ],
    "wof:name":"Polycarb Sunshine Skylights",
    "wof:placetype":"venue"
},
  "geometry": {"coordinates":[153.472824097,-28.1213474274],"type":"Point"}
}