{
  "type": "Feature",
  "properties": {
    "iso:country":"AU",
    "sg:address":"34 Hely St",
    "sg:city":"Wyong",
    "sg:classifiers":[
        {
            "category":"Personal",
            "subcategory":"Nail Salon",
            "type":"Services"
        }
    ],
    "sg:phone":"+61 2 4353 0750",
    "sg:postcode":"2259",
    "sg:province":"NSW",
    "sg:tags":[
        "artificial"
    ],
    "wof:name":"Blush Beauty Therapy",
    "wof:placetype":"venue"
},
  "geometry": {"coordinates":[151.42518615700001,-33.2803878784],"type":"Point"}
}