{
  "type": "Feature",
  "properties": {
    "addr:full":"Level 3 / Suite 227, 813 Pacific Hwy Chatswood NSW 1502",
    "addr:housenumber":"/ suite 227 813",
    "addr:postcode":"1502",
    "addr:street":"Pacific Hwy",
    "iso:country":"AU",
    "sg:address":"Level 3 / Suite 227, 813 Pacific Hwy",
    "sg:city":"Chatswood",
    "sg:classifiers":[
        {
            "category":"Professional",
            "subcategory":"Computer Services",
            "type":"Services"
        }
    ],
    "sg:phone":"+61 2 9410 0405",
    "sg:postcode":"1502",
    "sg:province":"NSW",
    "sg:tags":[
        "equipment",
        "networking",
        "installation"
    ],
    "wof:name":"Computer Care IT",
    "wof:placetype":"venue"
},
  "geometry": {"coordinates":[146.45550537099999,-13.1093502045],"type":"Point"}
}