{
  "type": "Feature",
  "properties": {
    "iso:country":"AU",
    "sg:address":"Factory 2/ 1- 3 Bignell Rd",
    "sg:city":"Moorabbin",
    "sg:classifiers":[
        {
            "category":"Retail",
            "subcategory":"Auto Repair",
            "type":"Services"
        }
    ],
    "sg:phone":"+61 3 9555 3020",
    "sg:postcode":"3189",
    "sg:province":"VIC",
    "sg:tags":[
        "repairer",
        "motor",
        "engineer"
    ],
    "wof:name":"Robs Automotive Services Pty Ltd",
    "wof:placetype":"venue"
},
  "geometry": {"coordinates":[145.067337036,-37.9425315857],"type":"Point"}
}