{
  "type": "Feature",
  "properties": {
    "addr:full":"Waroo Rd Yass NSW 2582",
    "addr:postcode":"2582",
    "addr:street":"Waroo Rd",
    "iso:country":"AU",
    "sg:address":"Waroo Rd",
    "sg:city":"Yass",
    "sg:classifiers":[
        {
            "category":"Retail",
            "subcategory":"Storage",
            "type":"Services"
        }
    ],
    "sg:phone":"+61 2 6226 1080",
    "sg:postcode":"2582",
    "sg:province":"NSW",
    "sg:tags":[
        "removal",
        "furniture"
    ],
    "wof:name":"Armidale-Dubbo-Canberra Furniture Movers",
    "wof:placetype":"venue"
},
  "geometry": {"coordinates":[148.916870117,-34.8486747742],"type":"Point"}
}