{
  "type": "Feature",
  "properties": {
    "addr:full":"57 Fifth Ave Barellan Point QLD 4306",
    "addr:housenumber":"57",
    "addr:postcode":"4306",
    "addr:street":"Fifth Ave",
    "iso:country":"AU",
    "sg:address":"57 Fifth Ave",
    "sg:city":"Barellan Point",
    "sg:classifiers":[
        {
            "category":"Home & Garden",
            "subcategory":"Building Materials",
            "type":"Retail Goods"
        }
    ],
    "sg:phone":"+61 7 3294 7620",
    "sg:postcode":"4306",
    "sg:province":"QLD",
    "sg:tags":[
        "lawn",
        "cutting",
        "maintenance"
    ],
    "wof:name":"Western Suburbs Lawn & Garden Service",
    "wof:placetype":"venue"
},
  "geometry": {"coordinates":[152.84417724599999,-27.5766544342],"type":"Point"}
}