{
  "type": "Feature",
  "properties": {
    "iso:country":"AU",
    "sg:address":"4 Homebush Drv",
    "sg:city":"Robina",
    "sg:classifiers":[
        {
            "category":"Taxi",
            "type":"Transportation"
        }
    ],
    "sg:phone":"+61 7 5578 9109",
    "sg:postcode":"4226",
    "sg:province":"QLD",
    "sg:tags":[
        "truck"
    ],
    "wof:name":"Hometown Furniture Removals",
    "wof:placetype":"venue"
},
  "geometry": {"coordinates":[153.40788269000001,-28.0579299927],"type":"Point"}
}