{
  "type": "Feature",
  "properties": {
    "iso:country":"AU",
    "sg:address":"564 Hume Hwy",
    "sg:city":"Yagoona",
    "sg:classifiers":[
        {
            "category":"Food & Beverages",
            "subcategory":"Bakery",
            "type":"Retail Goods"
        }
    ],
    "sg:phone":"+61 2 9708 3885",
    "sg:postcode":"2199",
    "sg:province":"NSW",
    "sg:tags":[
        "cake",
        "shop",
        "pastry"
    ],
    "wof:name":"Helens Pavalova Palace",
    "wof:placetype":"venue"
},
  "geometry": {"coordinates":[151.021255,-33.907059],"type":"Point"}
}