{
  "type": "Feature",
  "properties": {
    "addr:full":"Lot 1530 Lambert Rd Karratha WA 6714",
    "addr:housenumber":"1530",
    "addr:postcode":"6714",
    "addr:street":"Lambert Rd",
    "iso:country":"AU",
    "sg:address":"Lot 1530 Lambert Rd",
    "sg:city":"Karratha",
    "sg:classifiers":[
        {
            "category":"Utilities",
            "subcategory":"Electric",
            "type":"Services"
        }
    ],
    "sg:phone":"+61 8 9185 4601",
    "sg:postcode":"6714",
    "sg:province":"WA",
    "sg:tags":[
        "electrical",
        "contractor"
    ],
    "wof:name":"D K Electrical",
    "wof:placetype":"venue"
},
  "geometry": {"coordinates":[116.86564636200001,-20.773519516],"type":"Point"}
}