{
  "type": "Feature",
  "properties": {
    "addr:full":"103 Scarborough Beach Rd Mt Hawthorn WA 6016",
    "addr:housenumber":"103",
    "addr:postcode":"6016",
    "addr:street":"Scarborough Beach Rd",
    "iso:country":"AU",
    "sg:address":"103 Scarborough Beach Rd",
    "sg:city":"Mt Hawthorn",
    "sg:classifiers":[
        {
            "category":"Shopping",
            "subcategory":"News",
            "type":"Retail Goods"
        }
    ],
    "sg:phone":"+61 8 9443 3400",
    "sg:postcode":"6016",
    "sg:province":"WA",
    "sg:tags":[
        "magazine",
        "periodical"
    ],
    "wof:name":"Energy Publications Pty Ltd",
    "wof:placetype":"venue"
},
  "geometry": {"coordinates":[115.84380340600001,-31.9233551025],"type":"Point"}
}