{
  "type": "Feature",
  "properties": {
    "addr:full":"12 Centre Rd Morwell VIC 3840",
    "addr:housenumber":"12",
    "addr:postcode":"3840",
    "addr:street":"Centre Rd",
    "iso:country":"AU",
    "sg:address":"12 Centre Rd",
    "sg:city":"Morwell",
    "sg:classifiers":[
        {
            "category":"Manufacturing",
            "subcategory":"Metals",
            "type":"Manufacturing & Wholesale Goods"
        }
    ],
    "sg:phone":"+61 3 5135 6277",
    "sg:postcode":"3840",
    "sg:province":"VIC",
    "sg:tags":[
        "sheet",
        "worker"
    ],
    "wof:name":"Latrobe Valley Insulation Pty Ltd",
    "wof:placetype":"venue"
},
  "geometry": {"coordinates":[146.440673828,-38.2276878357],"type":"Point"}
}