{
  "type": "Feature",
  "properties": {
    "addr:full":"Lvl 1/ 87 Brisbane St Launceston TAS 7250",
    "addr:housenumber":"/ 87",
    "addr:postcode":"7250",
    "addr:street":"Brisbane St",
    "iso:country":"AU",
    "sg:address":"Lvl 1/ 87 Brisbane St",
    "sg:city":"Launceston",
    "sg:classifiers":[
        {
            "category":"Professional",
            "subcategory":"Employment Agencies",
            "type":"Services"
        }
    ],
    "sg:phone":"+61 3 6331 6322",
    "sg:postcode":"7250",
    "sg:province":"TAS",
    "wof:name":"Jet Personnel & Recruitment",
    "wof:placetype":"venue"
},
  "geometry": {"coordinates":[147.139892578,-41.436870575],"type":"Point"}
}