{
  "type": "Feature",
  "properties": {
    "addr:full":"5 Nottingham Crs Valley View SA 5093",
    "addr:housenumber":"5",
    "addr:postcode":"5093",
    "addr:street":"Nottingham Crs",
    "iso:country":"AU",
    "sg:address":"5 Nottingham Crs",
    "sg:city":"Valley View",
    "sg:classifiers":[
        {
            "category":"Utilities",
            "subcategory":"Electric",
            "type":"Services"
        }
    ],
    "sg:phone":"+61 402 091 300",
    "sg:postcode":"5093",
    "sg:province":"SA",
    "sg:tags":[
        "electrical",
        "contractor"
    ],
    "wof:name":"Mignone Bill",
    "wof:placetype":"venue"
},
  "geometry": {"coordinates":[138.67445373499999,-34.834148407],"type":"Point"}
}