{
  "type": "Feature",
  "properties": {
    "iso:country":"AU",
    "sg:address":"Suite 3a 574 Whitehorse Rd",
    "sg:city":"Mitcham",
    "sg:classifiers":[
        {
            "category":"Health Services",
            "subcategory":"Health Practitioner",
            "type":"Services"
        }
    ],
    "sg:phone":"+61 3 9873 0567",
    "sg:postcode":"3132",
    "sg:province":"VIC",
    "sg:tags":[
        "naturopath"
    ],
    "wof:name":"Victorian College Of Classical Homoeopathy",
    "wof:placetype":"venue"
},
  "geometry": {"coordinates":[145.194488525,-37.8165588379],"type":"Point"}
}