{
  "type": "Feature",
  "properties": {
    "addr:full":"130 Vineyard Rd Sunbury VIC 3429",
    "addr:housenumber":"130",
    "addr:postcode":"3429",
    "addr:street":"Vineyard Rd",
    "iso:country":"AU",
    "sg:address":"130 Vineyard Rd",
    "sg:city":"Sunbury",
    "sg:classifiers":[
        {
            "category":"Social Services",
            "subcategory":"Child Care",
            "type":"Services"
        }
    ],
    "sg:phone":"+61 3 9744 5533",
    "sg:postcode":"3429",
    "sg:province":"VIC",
    "sg:tags":[
        "equipment",
        "supply"
    ],
    "wof:name":"Joseph De Bono Consultancy",
    "wof:placetype":"venue"
},
  "geometry": {"coordinates":[144.71319580100001,-37.5994033813],"type":"Point"}
}