{
  "type": "Feature",
  "properties": {
    "addr:full":"14 Newman Ave Carnegie VIC 3163",
    "addr:housenumber":"14",
    "addr:postcode":"3163",
    "addr:street":"Newman Ave",
    "iso:country":"AU",
    "sg:address":"14 Newman Ave",
    "sg:city":"Carnegie",
    "sg:classifiers":[
        {
            "category":"Personal",
            "subcategory":"Massage",
            "type":"Services"
        }
    ],
    "sg:phone":"+61 3 9578 1028",
    "sg:postcode":"3163",
    "sg:province":"VIC",
    "sg:tags":[
        "therapy"
    ],
    "wof:name":"Michael Shen",
    "wof:placetype":"venue"
},
  "geometry": {"coordinates":[145.05242919899999,-37.9000778198],"type":"Point"}
}