{
  "type": "Feature",
  "properties": {
    "addr:full":"The Rear 77 Allingham St Condell Park NSW 2200",
    "addr:housenumber":"77",
    "addr:postcode":"2200",
    "addr:street":"Allingham St",
    "iso:country":"AU",
    "sg:address":"The Rear 77 Allingham St",
    "sg:city":"Condell Park",
    "sg:classifiers":[
        {
            "category":"Professional",
            "subcategory":"Employment Agencies",
            "type":"Services"
        }
    ],
    "sg:phone":"+61 2 9790 7878",
    "sg:postcode":"2200",
    "sg:province":"NSW",
    "sg:tags":[
        "broker",
        "custom"
    ],
    "wof:name":"O'Donnell J Customs Agency",
    "wof:placetype":"venue"
},
  "geometry": {"coordinates":[150.999481,-33.919395],"type":"Point"}
}