{
  "type": "Feature",
  "properties": {
    "iso:country":"AU",
    "sg:address":"17 Skene St",
    "sg:city":"Bendigo",
    "sg:classifiers":[
        {
            "category":"Travel",
            "subcategory":"Hotels & Motels",
            "type":"Entertainment"
        }
    ],
    "sg:phone":"+61 3 5443 0453",
    "sg:postcode":"3550",
    "sg:province":"VIC",
    "sg:tags":[
        "accommodation"
    ],
    "wof:name":"Belmont Hotel",
    "wof:placetype":"venue"
},
  "geometry": {"coordinates":[144.29411315900001,-36.7615852356],"type":"Point"}
}