{
  "type": "Feature",
  "properties": {
    "addr:full":"7 Crawford Crt Safety Bay WA 6169",
    "addr:housenumber":"7",
    "addr:postcode":"6169",
    "addr:street":"Crawford Crt",
    "iso:country":"AU",
    "sg:address":"7 Crawford Crt",
    "sg:city":"Safety Bay",
    "sg:classifiers":[
        {
            "category":"Sports & Exercise",
            "subcategory":"Gym",
            "type":"Entertainment"
        }
    ],
    "sg:phone":"+61 8 9591 3497",
    "sg:postcode":"6169",
    "sg:province":"WA",
    "sg:tags":[
        "health",
        "fitness"
    ],
    "wof:name":"Tai Chi Yang Shi",
    "wof:placetype":"venue"
},
  "geometry": {"coordinates":[115.730324,-32.305172],"type":"Point"}
}