{
  "type": "Feature",
  "properties": {
    "addr:full":"22 Siganto Drv Helensvale QLD 4212",
    "addr:housenumber":"22",
    "addr:postcode":"4212",
    "addr:street":"Siganto Drv",
    "iso:country":"AU",
    "sg:address":"22 Siganto Drv",
    "sg:city":"Helensvale",
    "sg:classifiers":[
        {
            "category":"Fast Food",
            "type":"Food & Drink"
        }
    ],
    "sg:phone":"+61 7 5665 8133",
    "sg:postcode":"4212",
    "sg:province":"QLD",
    "sg:tags":[
        "away",
        "take"
    ],
    "wof:name":"Eagle Boys Pizza",
    "wof:placetype":"venue"
},
  "geometry": {"coordinates":[153.31866455100001,-27.9068603516],"type":"Point"}
}