{
  "type": "Feature",
  "properties": {
    "addr:full":"Lvl 3, 1 Katherine St Chatswood NSW 2067",
    "addr:housenumber":"1",
    "addr:postcode":"2067",
    "addr:street":"Katherine St",
    "iso:country":"AU",
    "sg:address":"Lvl 3, 1 Katherine St",
    "sg:city":"Chatswood",
    "sg:classifiers":[
        {
            "category":"Health Services",
            "subcategory":"Doctor",
            "type":"Services"
        }
    ],
    "sg:phone":"+61 2 9904 7436",
    "sg:postcode":"2067",
    "sg:province":"NSW",
    "sg:tags":[
        "medical",
        "practitioner"
    ],
    "wof:name":"Kidson Warren",
    "wof:placetype":"venue"
},
  "geometry": {"coordinates":[151.17962646500001,-33.7977561951],"type":"Point"}
}