{
  "type": "Feature",
  "properties": {
    "iso:country":"AU",
    "sg:address":"PO Box 311",
    "sg:city":"Kelvin Grove",
    "sg:classifiers":[
        {
            "category":"Home & Garden",
            "subcategory":"Building Materials",
            "type":"Retail Goods"
        }
    ],
    "sg:phone":"+61 7 3856 5841",
    "sg:postcode":"4059",
    "sg:province":"QLD",
    "sg:tags":[
        "shutter",
        "roller",
        "grille"
    ],
    "wof:name":"Jennings D R",
    "wof:placetype":"venue"
},
  "geometry": {"coordinates":[153.009307861,-27.4453601837],"type":"Point"}
}