{
  "type": "Feature",
  "properties": {
    "addr:full":"29- 31 Little Boundary Rd Laverton North VIC 3026",
    "addr:housenumber":"31",
    "addr:postcode":"3026",
    "addr:street":"Little Boundary Rd",
    "iso:country":"AU",
    "sg:address":"29- 31 Little Boundary Rd",
    "sg:city":"Laverton North",
    "sg:classifiers":[
        {
            "category":"Retail",
            "subcategory":"Auto Rental",
            "type":"Services"
        }
    ],
    "sg:phone":"+61 3 9315 1396",
    "sg:postcode":"3026",
    "sg:province":"VIC",
    "sg:tags":[
        "bus",
        "truck"
    ],
    "wof:name":"Caltex",
    "wof:placetype":"venue"
},
  "geometry": {"coordinates":[144.81976299999999,-37.819553],"type":"Point"}
}