{
  "type": "Feature",
  "properties": {
    "addr:full":"Shop 13C Norwest Marketown Norwest Blvd Bella Vista NSW 2153",
    "addr:housenumber":"13c",
    "addr:postcode":"2153",
    "addr:street":"Shop;Norwest Blvd",
    "iso:country":"AU",
    "sg:address":"Shop 13C Norwest Marketown Norwest Blvd",
    "sg:city":"Bella Vista",
    "sg:classifiers":[
        {
            "category":"Banks & Credit Unions",
            "subcategory":"Bank",
            "type":"Services"
        }
    ],
    "sg:phone":"+61 2 8850 7766",
    "sg:postcode":"2153",
    "sg:province":"NSW",
    "sg:tags":[
        "broker",
        "mortgage"
    ],
    "wof:name":"Norwest Mortgage View",
    "wof:placetype":"venue"
},
  "geometry": {"coordinates":[150.966720581,-33.7314949036],"type":"Point"}
}