{
  "type": "Feature",
  "properties": {
    "iso:country":"AU",
    "sg:address":"PO Box 53",
    "sg:city":"Revesby North",
    "sg:classifiers":[
        {
            "category":"Wholesale",
            "subcategory":"Machinery & Supplies",
            "type":"Manufacturing & Wholesale Goods"
        }
    ],
    "sg:phone":"+61 2 9772 4499",
    "sg:postcode":"2212",
    "sg:province":"NSW",
    "sg:tags":[
        "equipment",
        "system",
        "elevating",
        "conveying"
    ],
    "wof:name":"Advance Conveyors Pty Ltd",
    "wof:placetype":"venue"
},
  "geometry": {"coordinates":[151.007294,-33.943581],"type":"Point"}
}