{
  "type": "Feature",
  "properties": {
    "iso:country":"AU",
    "sg:address":"Sd 15, Gravel Pit Rd",
    "sg:city":"Geelong",
    "sg:classifiers":[
        {
            "category":"Mining & Drilling",
            "type":"Manufacturing & Wholesale Goods"
        }
    ],
    "sg:phone":"+61 3 5248 0776",
    "sg:postcode":"3220",
    "sg:province":"VIC",
    "sg:tags":[
        "boring",
        "contractor"
    ],
    "wof:name":"Millen Plumbing & Drainage",
    "wof:placetype":"venue"
},
  "geometry": {"coordinates":[144.36322,-38.172874],"type":"Point"}
}