{
  "type": "Feature",
  "properties": {
    "iso:country":"AU",
    "sg:address":"24 Parakeet St",
    "sg:city":"Birkdale",
    "sg:classifiers":[
        {
            "category":"Manufacturing",
            "subcategory":"Metals",
            "type":"Manufacturing & Wholesale Goods"
        }
    ],
    "sg:phone":"+61 412 409 494",
    "sg:postcode":"4159",
    "sg:province":"QLD",
    "sg:tags":[
        "steel",
        "fabricator",
        "mfrs"
    ],
    "wof:name":"ABC Steel Industries",
    "wof:placetype":"venue"
},
  "geometry": {"coordinates":[153.21873474099999,-27.5040340424],"type":"Point"}
}