{
  "type": "Feature",
  "properties": {
    "addr:full":"91a William St Bathurst NSW 2795",
    "addr:housenumber":"91a",
    "addr:postcode":"2795",
    "addr:street":"William St",
    "iso:country":"AU",
    "sg:address":"91a William St",
    "sg:city":"Bathurst",
    "sg:classifiers":[
        {
            "category":"Ice Cream",
            "type":"Food & Drink"
        }
    ],
    "sg:phone":"+61 2 6331 2854",
    "sg:postcode":"2795",
    "sg:province":"NSW",
    "sg:tags":[
        "specialised",
        "fitting",
        "lady",
        "wear"
    ],
    "wof:name":"Sheer Indulgence Lingerie",
    "wof:placetype":"venue"
},
  "geometry": {"coordinates":[149.57911682100001,-33.4192733765],"type":"Point"}
}