{
  "type": "Feature",
  "properties": {
    "iso:country":"AU",
    "sg:address":"Unit 11, 77 Newton Rd",
    "sg:city":"Wetherill Park",
    "sg:classifiers":[
        {
            "category":"Manufacturing",
            "subcategory":"Apparel",
            "type":"Manufacturing & Wholesale Goods"
        }
    ],
    "sg:phone":"+61 2 9756 1970",
    "sg:postcode":"2164",
    "sg:province":"NSW",
    "sg:tags":[
        "wholesaler",
        "mfrs",
        "footwear"
    ],
    "wof:name":"Robment t/as Bluebird Shoes",
    "wof:placetype":"venue"
},
  "geometry": {"coordinates":[150.89321899399999,-33.8456687927],"type":"Point"}
}