{
  "type": "Feature",
  "properties": {
    "iso:country":"AU",
    "sg:address":"162 Brisbane Rd",
    "sg:city":"Mooloolaba",
    "sg:classifiers":[
        {
            "category":"Industrial Area",
            "type":"Public Place"
        }
    ],
    "sg:phone":"+61 7 5444 4801",
    "sg:postcode":"4557",
    "sg:province":"QLD",
    "sg:tags":[
        "protective",
        "clothing"
    ],
    "wof:name":"Tuff Stuff Discount Workwear",
    "wof:placetype":"venue"
},
  "geometry": {"coordinates":[153.11491394000001,-26.6898345947],"type":"Point"}
}