{
  "type": "Feature",
  "properties": {
    "addr:full":"PO Box 115 Bridport TAS 7262",
    "addr:postcode":"7262",
    "iso:country":"AU",
    "sg:address":"PO Box 115",
    "sg:city":"Bridport",
    "sg:classifiers":[
        {
            "category":"Building & Trades",
            "subcategory":"Construction",
            "type":"Services"
        }
    ],
    "sg:phone":"+61 3 6356 0026",
    "sg:postcode":"7262",
    "sg:province":"TAS",
    "sg:tags":[
        "earth",
        "excavating",
        "moving",
        "contractor"
    ],
    "wof:name":"P & H Smythe Excavations Pty Ltd",
    "wof:placetype":"venue"
},
  "geometry": {"coordinates":[147.40353400000001,-41.012718],"type":"Point"}
}