{
  "type": "Feature",
  "properties": {
    "addr:full":"58 Douro St Geelong North VIC 3215",
    "addr:housenumber":"58",
    "addr:postcode":"3215",
    "addr:street":"Douro St",
    "iso:country":"AU",
    "sg:address":"58 Douro St",
    "sg:city":"Geelong North",
    "sg:classifiers":[
        {
            "category":"Wholesale",
            "subcategory":"Scrap",
            "type":"Manufacturing & Wholesale Goods"
        }
    ],
    "sg:phone":"+61 3 5278 7396",
    "sg:postcode":"3215",
    "sg:province":"VIC",
    "sg:tags":[
        "merchant",
        "metal"
    ],
    "wof:name":"Simsmetal Limited",
    "wof:placetype":"venue"
},
  "geometry": {"coordinates":[144.34835815400001,-38.1199913025],"type":"Point"}
}