{
  "type": "Feature",
  "properties": {
    "iso:country":"AU",
    "sg:address":"Shop 3/ 87A Victoria St",
    "sg:city":"Bunbury",
    "sg:classifiers":[
        {
            "category":"Shopping",
            "subcategory":"Luggage & Leather Goods",
            "type":"Retail Goods"
        }
    ],
    "sg:phone":"+61 8 9791 1529",
    "sg:postcode":"6230",
    "sg:province":"WA",
    "wof:name":"The Ratbags At Grand Central",
    "wof:placetype":"venue"
},
  "geometry": {"coordinates":[115.63681,-33.323822],"type":"Point"}
}