{
  "type": "Feature",
  "properties": {
    "addr:full":"5 Guilfoyle St Churchill QLD 4305",
    "addr:housenumber":"5",
    "addr:postcode":"4305",
    "addr:street":"Guilfoyle St",
    "iso:country":"AU",
    "sg:address":"5 Guilfoyle St",
    "sg:city":"Churchill",
    "sg:classifiers":[
        {
            "category":"Personal",
            "subcategory":"Massage",
            "type":"Services"
        }
    ],
    "sg:phone":"+61 7 3202 2534",
    "sg:postcode":"4305",
    "sg:province":"QLD",
    "sg:tags":[
        "therapy"
    ],
    "wof:name":"Muscular Relief Massage Therapy",
    "wof:placetype":"venue"
},
  "geometry": {"coordinates":[152.74902343799999,-27.6425933838],"type":"Point"}
}