{
  "type": "Feature",
  "properties": {
    "addr:full":"RMB 2020a Beechworth Rd Wodonga VIC 3690",
    "addr:postcode":"3690",
    "addr:street":"Beechworth Rd",
    "iso:country":"AU",
    "sg:address":"RMB 2020a Beechworth Rd",
    "sg:city":"Wodonga",
    "sg:classifiers":[
        {
            "category":"Building & Trades",
            "subcategory":"Construction",
            "type":"Services"
        }
    ],
    "sg:phone":"+61 2 6024 6818",
    "sg:postcode":"3690",
    "sg:province":"VIC",
    "sg:tags":[
        "welding"
    ],
    "wof:name":"SAS Welding",
    "wof:placetype":"venue"
},
  "geometry": {"coordinates":[146.88381957999999,-36.1436882019],"type":"Point"}
}