{
  "type": "Feature",
  "properties": {
    "addr:full":"116 Barrow St Coburg VIC 3058",
    "addr:housenumber":"116",
    "addr:postcode":"3058",
    "addr:street":"Barrow St",
    "iso:country":"AU",
    "sg:address":"116 Barrow St",
    "sg:city":"Coburg",
    "sg:classifiers":[
        {
            "category":"Professional",
            "type":"Services"
        }
    ],
    "sg:phone":"+61 3 9386 2219",
    "sg:postcode":"3058",
    "sg:province":"VIC",
    "sg:tags":[
        "shop",
        "fitting"
    ],
    "wof:name":"CDS Shop Fitting",
    "wof:placetype":"venue"
},
  "geometry": {"coordinates":[144.97239685100001,-37.7458572388],"type":"Point"}
}