{
  "type": "Feature",
  "properties": {
    "addr:full":"194 Bong Bong St Bowral NSW 2576",
    "addr:housenumber":"194",
    "addr:postcode":"2576",
    "addr:street":"Bong Bong St",
    "iso:country":"AU",
    "sg:address":"194 Bong Bong St",
    "sg:city":"Bowral",
    "sg:classifiers":[
        {
            "category":"Shopping",
            "subcategory":"Crafts & Fabrics",
            "type":"Retail Goods"
        }
    ],
    "sg:phone":"+61 2 4861 4667",
    "sg:postcode":"2576",
    "sg:province":"NSW",
    "sg:tags":[
        "florist",
        "supply"
    ],
    "wof:name":"Floral Design Centre",
    "wof:placetype":"venue"
},
  "geometry": {"coordinates":[150.41831970199999,-34.4774703979],"type":"Point"}
}