{
  "type": "Feature",
  "properties": {
    "addr:full":"25 Kundle St Dapto NSW 2530",
    "addr:housenumber":"25",
    "addr:postcode":"2530",
    "addr:street":"Kundle St",
    "iso:country":"AU",
    "sg:address":"25 Kundle St",
    "sg:city":"Dapto",
    "sg:classifiers":[
        {
            "category":"Shopping",
            "subcategory":"Gifts & Souvenirs",
            "type":"Retail Goods"
        }
    ],
    "sg:phone":"+61 2 4262 7280",
    "sg:postcode":"2530",
    "sg:province":"NSW",
    "sg:tags":[
        "shop",
        "supply"
    ],
    "wof:name":"J Style Japanese Homewares",
    "wof:placetype":"venue"
},
  "geometry": {"coordinates":[150.80511474599999,-34.4872169495],"type":"Point"}
}