{
  "type": "Feature",
  "properties": {
    "iso:country":"AU",
    "sg:address":"59 McCormack Drv",
    "sg:city":"Murphy&#039;s Creek",
    "sg:classifiers":[
        {
            "category":"Manufacturing",
            "subcategory":"Food",
            "type":"Manufacturing & Wholesale Goods"
        }
    ],
    "sg:phone":"+61 7 4659 0669",
    "sg:postcode":"4352",
    "sg:province":"QLD",
    "sg:tags":[
        "function",
        "catering"
    ],
    "wof:name":"Carys Catering",
    "wof:placetype":"venue"
},
  "geometry": {"coordinates":[151.684128,-27.528872],"type":"Point"}
}