{
  "type": "Feature",
  "properties": {
    "iso:country":"AU",
    "sg:address":"15 Woodrowvale Rd",
    "sg:city":"Colac",
    "sg:classifiers":[
        {
            "category":"Home & Garden",
            "subcategory":"Building Materials",
            "type":"Retail Goods"
        }
    ],
    "sg:phone":"+61 3 5232 1661",
    "sg:postcode":"3250",
    "sg:province":"VIC",
    "sg:tags":[
        "merchant",
        "glass",
        "glazier"
    ],
    "wof:name":"Colac Glass & Screens",
    "wof:placetype":"venue"
},
  "geometry": {"coordinates":[143.595215,-38.360992],"type":"Point"}
}