{
  "type": "Feature",
  "properties": {
    "iso:country":"AU",
    "sg:address":"269 Shute Harbour Rd",
    "sg:city":"Airlie Beach",
    "sg:classifiers":[
        {
            "category":"Retail",
            "subcategory":"Auto Rental",
            "type":"Services"
        }
    ],
    "sg:phone":"+61 7 4946 4133",
    "sg:postcode":"4802",
    "sg:province":"QLD",
    "sg:tags":[
        "car",
        "hire",
        "minibus"
    ],
    "wof:name":"Europcar",
    "wof:placetype":"venue"
},
  "geometry": {"coordinates":[148.717559814,-20.2681522369],"type":"Point"}
}