{
  "type": "Feature",
  "properties": {
    "iso:country":"AU",
    "sg:address":"18 Railway St",
    "sg:city":"Liverpool",
    "sg:classifiers":[
        {
            "category":"Shopping",
            "subcategory":"Pawn Shop",
            "type":"Retail Goods"
        }
    ],
    "sg:phone":"+61 2 9602 4357",
    "sg:postcode":"2170",
    "sg:province":"NSW",
    "sg:tags":[
        "pawnbroker"
    ],
    "wof:name":"Cash Brokers",
    "wof:placetype":"venue"
},
  "geometry": {"coordinates":[150.925689697,-33.9243927002],"type":"Point"}
}