{
  "type": "Feature",
  "properties": {
    "addr:full":"165 Oak Rd Kirrawee NSW 2232",
    "addr:housenumber":"165",
    "addr:postcode":"2232",
    "addr:street":"Oak Rd",
    "iso:country":"AU",
    "sg:address":"165 Oak Rd",
    "sg:city":"Kirrawee",
    "sg:classifiers":[
        {
            "category":"Health Services",
            "subcategory":"Health Practitioner",
            "type":"Services"
        }
    ],
    "sg:phone":"+61 2 9521 7945",
    "sg:postcode":"2232",
    "sg:province":"NSW",
    "sg:tags":[
        "physiotherapist"
    ],
    "wof:name":"My Fizzio",
    "wof:placetype":"venue"
},
  "geometry": {"coordinates":[151.07064819300001,-34.0371894836],"type":"Point"}
}