{
  "type": "Feature",
  "properties": {
    "addr:full":"Ste 213b/Lvl 2/ 250 McCullough St, Times Square Sunnybank QLD 4109",
    "addr:housenumber":"213b;/ 250;square",
    "addr:postcode":"4109",
    "addr:street":"/;Mccullough St",
    "iso:country":"AU",
    "sg:address":"Ste 213b/Lvl 2/ 250 McCullough St, Times Square",
    "sg:city":"Sunnybank",
    "sg:classifiers":[
        {
            "category":"Health Services",
            "subcategory":"Doctor",
            "type":"Services"
        }
    ],
    "sg:phone":"+61 7 3423 7881",
    "sg:postcode":"4109",
    "sg:province":"QLD",
    "sg:tags":[
        "medical",
        "practitioner"
    ],
    "wof:name":"Ng Chin",
    "wof:placetype":"venue"
},
  "geometry": {"coordinates":[153.061767578,-27.5713539124],"type":"Point"}
}