{
  "type": "Feature",
  "properties": {
    "iso:country":"AU",
    "sg:address":"235 Old Maitland Rd",
    "sg:city":"Hexham",
    "sg:classifiers":[
        {
            "category":"Arena",
            "subcategory":"Sports Club",
            "type":"Entertainment"
        }
    ],
    "sg:phone":"+61 2 4964 8922",
    "sg:postcode":"2322",
    "sg:province":"NSW",
    "sg:tags":[
        "organisation",
        "sporting"
    ],
    "wof:name":"Northern NSW Soccer Federation Ltd",
    "wof:placetype":"venue"
},
  "geometry": {"coordinates":[151.686447144,-32.8279037476],"type":"Point"}
}