{
  "type": "Feature",
  "properties": {
    "addr:full":"21 Kawana Crs Ashmore QLD 4214",
    "addr:housenumber":"21",
    "addr:postcode":"4214",
    "addr:street":"Kawana Crs",
    "iso:country":"AU",
    "sg:address":"21 Kawana Crs",
    "sg:city":"Ashmore",
    "sg:classifiers":[
        {
            "category":"Education",
            "subcategory":"Special Training",
            "type":"Public Place"
        }
    ],
    "sg:phone":"+61 7 5539 4068",
    "sg:postcode":"4214",
    "sg:province":"QLD",
    "sg:tags":[
        "development"
    ],
    "wof:name":"Brad Holmes Surf Coaching",
    "wof:placetype":"venue"
},
  "geometry": {"coordinates":[153.38270568900001,-27.9863395691],"type":"Point"}
}