{
  "type": "Feature",
  "properties": {
    "addr:full":"57 Buckingham Drv Wangara WA 6065",
    "addr:housenumber":"57",
    "addr:postcode":"6065",
    "addr:street":"Buckingham Drv",
    "iso:country":"AU",
    "sg:address":"57 Buckingham Drv",
    "sg:city":"Wangara",
    "sg:classifiers":[
        {
            "category":"Social Services",
            "subcategory":"Child Care",
            "type":"Services"
        }
    ],
    "sg:phone":"+61 1300 655 170",
    "sg:postcode":"6065",
    "sg:province":"WA",
    "sg:tags":[
        "fleet",
        "management"
    ],
    "wof:name":"Fleetcare",
    "wof:placetype":"venue"
},
  "geometry": {"coordinates":[115.82343292199999,-31.7870826721],"type":"Point"}
}