{
  "type": "Feature",
  "properties": {
    "iso:country":"AU",
    "sg:address":"Level 4, 228 Pitt St",
    "sg:city":"Sydney",
    "sg:classifiers":[
        {
            "category":"Organizations",
            "subcategory":"Professional Association",
            "type":"Services"
        }
    ],
    "sg:phone":"+61 2 9267 2366",
    "sg:postcode":"2000",
    "sg:province":"NSW",
    "sg:tags":[
        "web",
        "internet"
    ],
    "wof:name":"Multie Software & Services Pty Ltd",
    "wof:placetype":"venue"
},
  "geometry": {"coordinates":[151.20831298799999,-33.872089386],"type":"Point"}
}