{
  "type": "Feature",
  "properties": {
    "addr:full":"127 Glenfern Rd Ferntree Gully Upper VIC 3156",
    "addr:housenumber":"127",
    "addr:postcode":"3156",
    "addr:street":"Glenfern Rd",
    "iso:country":"AU",
    "sg:address":"127 Glenfern Rd",
    "sg:city":"Ferntree Gully Upper",
    "sg:classifiers":[
        {
            "category":"Building & Trades",
            "subcategory":"Construction",
            "type":"Services"
        }
    ],
    "sg:phone":"+61 3 9758 7528",
    "sg:postcode":"3156",
    "sg:province":"VIC",
    "sg:tags":[
        "brick",
        "paving"
    ],
    "wof:name":"Clive Brewer Landscapes & Design",
    "wof:placetype":"venue"
},
  "geometry": {"coordinates":[145.29533386200001,-37.9001159668],"type":"Point"}
}