{
  "type": "Feature",
  "properties": {
    "addr:full":"71 Coronation Rd Hillcrest QLD 4118",
    "addr:housenumber":"71",
    "addr:postcode":"4118",
    "addr:street":"Coronation Rd",
    "iso:country":"AU",
    "sg:address":"71 Coronation Rd",
    "sg:city":"Hillcrest",
    "sg:classifiers":[
        {
            "category":"Health Services",
            "subcategory":"Doctor",
            "type":"Services"
        }
    ],
    "sg:phone":"+61 7 3806 9288",
    "sg:postcode":"4118",
    "sg:province":"QLD",
    "sg:tags":[
        "medical",
        "practitioner"
    ],
    "wof:name":"Middle Road Medical Centre",
    "wof:placetype":"venue"
},
  "geometry": {"coordinates":[153.023803711,-27.6791152954],"type":"Point"}
}