{
  "type": "Feature",
  "properties": {
    "addr:full":"12 Moore St Moe VIC 3825",
    "addr:housenumber":"12",
    "addr:postcode":"3825",
    "addr:street":"Moore St",
    "iso:country":"AU",
    "sg:address":"12 Moore St",
    "sg:city":"Moe",
    "sg:classifiers":[
        {
            "category":"Personal",
            "type":"Services"
        }
    ],
    "sg:phone":"+61 3 5127 8122",
    "sg:postcode":"3825",
    "sg:province":"VIC",
    "sg:tags":[
        "gift"
    ],
    "wof:name":"Lilly Pilly Florist",
    "wof:placetype":"venue"
},
  "geometry": {"coordinates":[146.261078,-38.176189],"type":"Point"}
}