{
  "type": "Feature",
  "properties": {
    "addr:full":"Cnr Acland & Barkley St St Kilda VIC 3182",
    "addr:postcode":"3182",
    "addr:street":"Cnr;St",
    "iso:country":"AU",
    "sg:address":"Cnr Acland & Barkley St",
    "sg:city":"St Kilda",
    "sg:classifiers":[
        {
            "category":"Restaurant",
            "type":"Food & Drink"
        }
    ],
    "sg:phone":"+61 3 9534 4611",
    "sg:postcode":"3182",
    "sg:province":"VIC",
    "wof:name":"Big Mouth",
    "wof:placetype":"venue"
},
  "geometry": {"coordinates":[144.982666016,-37.8592605591],"type":"Point"}
}