{
  "type": "Feature",
  "properties": {
    "iso:country":"AU",
    "sg:address":"50 Tobruk Ave",
    "sg:city":"Cremorne",
    "sg:classifiers":[
        {
            "category":"Farming",
            "subcategory":"Vineyard",
            "type":"Manufacturing & Wholesale Goods"
        }
    ],
    "sg:phone":"+61 2 9953 0000",
    "sg:postcode":"2090",
    "sg:province":"NSW",
    "sg:tags":[
        "winery"
    ],
    "wof:name":"Lindrum Wine Estate",
    "wof:placetype":"venue"
},
  "geometry": {"coordinates":[151.227172852,-33.8208427429],"type":"Point"}
}