{
  "type": "Feature",
  "properties": {
    "addr:full":"1 Collins St Ormond VIC 3163",
    "addr:housenumber":"1",
    "addr:postcode":"3163",
    "addr:street":"Collins St",
    "iso:country":"AU",
    "sg:address":"1 Collins St",
    "sg:city":"Ormond",
    "sg:classifiers":[
        {
            "category":"Professional",
            "subcategory":"Employment Agencies",
            "type":"Services"
        }
    ],
    "sg:phone":"+61 3 9576 7127",
    "sg:postcode":"3163",
    "sg:province":"VIC",
    "wof:name":"Conquest Personnel Pty Ltd",
    "wof:placetype":"venue"
},
  "geometry": {"coordinates":[145.09400939899999,-37.8743591309],"type":"Point"}
}