{
  "type": "Feature",
  "properties": {
    "addr:full":"1290 Grand Junction Rd Hope Valley SA 5090",
    "addr:housenumber":"1290",
    "addr:postcode":"5090",
    "addr:street":"Grand Junction Rd",
    "iso:country":"AU",
    "sg:address":"1290 Grand Junction Rd",
    "sg:city":"Hope Valley",
    "sg:classifiers":[
        {
            "category":"Health Services",
            "subcategory":"Health Practitioner",
            "type":"Services"
        }
    ],
    "sg:phone":"+61 8 8362 0077",
    "sg:postcode":"5090",
    "sg:province":"SA",
    "sg:tags":[
        "physiotherapist"
    ],
    "wof:name":"Dello Rom - SA Physiotherapy & Sports Injury Clinic & Spine Care",
    "wof:placetype":"venue"
},
  "geometry": {"coordinates":[138.70846557600001,-34.8412475586],"type":"Point"}
}