{
  "type": "Feature",
  "properties": {
    "addr:full":"128 Phillip St Thirroul NSW 2515",
    "addr:housenumber":"128",
    "addr:postcode":"2515",
    "addr:street":"Phillip St",
    "iso:country":"AU",
    "sg:address":"128 Phillip St",
    "sg:city":"Thirroul",
    "sg:classifiers":[
        {
            "category":"Building & Trades",
            "subcategory":"Plumbing",
            "type":"Services"
        }
    ],
    "sg:phone":"+61 2 4268 3503",
    "sg:postcode":"2515",
    "sg:province":"NSW",
    "sg:tags":[
        "plumber",
        "gasfitters"
    ],
    "wof:name":"Cadifern Australia",
    "wof:placetype":"venue"
},
  "geometry": {"coordinates":[150.91699199999999,-34.316418],"type":"Point"}
}