{
  "type": "Feature",
  "properties": {
    "iso:country":"AU",
    "sg:address":"Mitchell St",
    "sg:city":"Merredin",
    "sg:classifiers":[
        {
            "category":"Wholesale",
            "subcategory":"Farm Supplies",
            "type":"Manufacturing & Wholesale Goods"
        }
    ],
    "sg:phone":"+61 8 9041 1966",
    "sg:postcode":"6415",
    "sg:province":"WA",
    "sg:tags":[
        "equipment"
    ],
    "wof:name":"Rural Traders Company Ltd",
    "wof:placetype":"venue"
},
  "geometry": {"coordinates":[118.276977539,-31.4808292389],"type":"Point"}
}