{
  "type": "Feature",
  "properties": {
    "iso:country":"AU",
    "sg:address":"7 Executive Drv",
    "sg:city":"Burleigh Waters",
    "sg:classifiers":[
        {
            "category":"Travel",
            "subcategory":"Hotels & Motels",
            "type":"Entertainment"
        }
    ],
    "sg:phone":"+61 7 5593 7811",
    "sg:postcode":"4220",
    "sg:province":"QLD",
    "sg:tags":[
        "pub"
    ],
    "wof:name":"Treetops Tavern",
    "wof:placetype":"venue"
},
  "geometry": {"coordinates":[153.42384338400001,-28.0983295441],"type":"Point"}
}