{
  "type": "Feature",
  "properties": {
    "addr:full":"56 Australia Ave Matraville NSW 2036",
    "addr:housenumber":"56",
    "addr:postcode":"2036",
    "addr:street":"Australia Ave",
    "iso:country":"AU",
    "sg:address":"56 Australia Ave",
    "sg:city":"Matraville",
    "sg:classifiers":[
        {
            "category":"Health Services",
            "subcategory":"Health Practitioner",
            "type":"Services"
        }
    ],
    "sg:phone":"+61 438 752 767",
    "sg:postcode":"2036",
    "sg:province":"NSW",
    "sg:tags":[
        "acupuncture"
    ],
    "wof:name":"Solomon Daniela",
    "wof:placetype":"venue"
},
  "geometry": {"coordinates":[151.22731018100001,-33.9618186951],"type":"Point"}
}