{
  "type": "Feature",
  "properties": {
    "iso:country":"AU",
    "sg:address":"13 Manatoka Pde",
    "sg:city":"Ormeau",
    "sg:classifiers":[
        {
            "category":"Social Services",
            "subcategory":"Child Care",
            "type":"Services"
        }
    ],
    "sg:phone":"+61 7 5546 7383",
    "sg:postcode":"4208",
    "sg:province":"QLD",
    "sg:tags":[
        "childbirth"
    ],
    "wof:name":"Brassard Claire",
    "wof:placetype":"venue"
},
  "geometry": {"coordinates":[153.244537353,-27.7672615051],"type":"Point"}
}