{
  "type": "Feature",
  "properties": {
    "iso:country":"AU",
    "sg:address":"Cnr Pimpala & Panalatinga Rds",
    "sg:city":"Woodcroft",
    "sg:classifiers":[
        {
            "category":"Health Services",
            "subcategory":"Health Practitioner",
            "type":"Services"
        }
    ],
    "sg:phone":"+61 8 8323 8058",
    "sg:postcode":"5162",
    "sg:province":"SA",
    "sg:tags":[
        "physiotherapist"
    ],
    "wof:name":"Muscular Development Fitness Unit",
    "wof:placetype":"venue"
},
  "geometry": {"coordinates":[138.55705261200001,-35.1035385132],"type":"Point"}
}