{
  "type": "Feature",
  "properties": {
    "addr:full":"Unit 2 85 Dixon Rd Rockingham WA 6168",
    "addr:housenumber":"85",
    "addr:postcode":"6168",
    "addr:street":"Dixon Rd",
    "iso:country":"AU",
    "sg:address":"Unit 2 85 Dixon Rd",
    "sg:city":"Rockingham",
    "sg:classifiers":[
        {
            "category":"Autos & Motor Vehicles",
            "subcategory":"Automobile Sales",
            "type":"Retail Goods"
        }
    ],
    "sg:phone":"+61 8 9527 2322",
    "sg:postcode":"6168",
    "sg:province":"WA",
    "sg:tags":[
        "equipment",
        "trailer"
    ],
    "wof:name":"Trailer World",
    "wof:placetype":"venue"
},
  "geometry": {"coordinates":[115.76464799999999,-32.276848],"type":"Point"}
}