{
  "type": "Feature",
  "properties": {
    "addr:full":"329 Wapengo Lake Rd Tanja NSW 2550",
    "addr:housenumber":"329",
    "addr:postcode":"2550",
    "addr:street":"Wapengo Lake Rd",
    "iso:country":"AU",
    "sg:address":"329 Wapengo Lake Rd",
    "sg:city":"Tanja",
    "sg:classifiers":[
        {
            "category":"Farming",
            "subcategory":"Fish & Marine Products",
            "type":"Manufacturing & Wholesale Goods"
        }
    ],
    "sg:phone":"+61 2 6494 0180",
    "sg:postcode":"2550",
    "sg:province":"NSW",
    "sg:tags":[
        "supplier",
        "oyster",
        "farmer"
    ],
    "wof:name":"Simpson R",
    "wof:placetype":"venue"
},
  "geometry": {"coordinates":[150.00958251899999,-36.5824012756],"type":"Point"}
}