{
  "type": "Feature",
  "properties": {
    "iso:country":"AU",
    "sg:address":"32 Mills St",
    "sg:city":"Albert Park",
    "sg:classifiers":[
        {
            "category":"Professional",
            "subcategory":"Art Services",
            "type":"Services"
        }
    ],
    "sg:phone":"+61 3 9686 4944",
    "sg:postcode":"3206",
    "sg:province":"VIC",
    "sg:tags":[
        "graphic",
        "designer"
    ],
    "wof:name":"Terminal Design",
    "wof:placetype":"venue"
},
  "geometry": {"coordinates":[144.959244,-37.845062],"type":"Point"}
}