{
  "type": "Feature",
  "properties": {
    "iso:country":"AU",
    "sg:address":"3 Jordon St",
    "sg:city":"Munno Para West",
    "sg:classifiers":[
        {
            "category":"Professional",
            "subcategory":"Computer Services",
            "type":"Services"
        }
    ],
    "sg:phone":"+61 8 8254 9898",
    "sg:postcode":"5115",
    "sg:province":"SA",
    "sg:tags":[
        "repairs",
        "upgrade",
        "equipment"
    ],
    "wof:name":"Computer Ease",
    "wof:placetype":"venue"
},
  "geometry": {"coordinates":[138.668243408,-34.6662826538],"type":"Point"}
}