{
  "type": "Feature",
  "properties": {
    "iso:country":"AU",
    "sg:address":"Unit 1/ 15 Lavarack Ave",
    "sg:city":"Eagle Farm",
    "sg:classifiers":[
        {
            "category":"Manufacturing",
            "subcategory":"Building Materials",
            "type":"Manufacturing & Wholesale Goods"
        }
    ],
    "sg:phone":"+61 7 3868 4100",
    "sg:postcode":"4009",
    "sg:province":"QLD",
    "sg:tags":[
        "equipment",
        "handling"
    ],
    "wof:name":"National Fleet Network QLD",
    "wof:placetype":"venue"
},
  "geometry": {"coordinates":[153.09263610799999,-27.4334373474],"type":"Point"}
}