{
  "type": "Feature",
  "properties": {
    "addr:full":"39 Breeze St Umina Beach NSW 2257",
    "addr:housenumber":"39",
    "addr:postcode":"2257",
    "addr:street":"Breeze St",
    "iso:country":"AU",
    "sg:address":"39 Breeze St",
    "sg:city":"Umina Beach",
    "sg:phone":"+61 2 4344 3611",
    "sg:postcode":"2257",
    "sg:province":"NSW",
    "wof:name":"Coastal Rainwater Harvesting",
    "wof:placetype":"venue"
},
  "geometry": {"coordinates":[151.31570434599999,-33.507850647],"type":"Point"}
}