{
  "type": "Feature",
  "properties": {
    "addr:full":"Unit 5/ 14 New St North Parramatta NSW 2151",
    "addr:postcode":"2151",
    "addr:street":"New St",
    "iso:country":"AU",
    "sg:address":"Unit 5/ 14 New St",
    "sg:city":"North Parramatta",
    "sg:classifiers":[
        {
            "category":"Professional",
            "subcategory":"Computer Services",
            "type":"Services"
        }
    ],
    "sg:phone":"+61 2 9683 6556",
    "sg:postcode":"2151",
    "sg:province":"NSW",
    "sg:tags":[
        "package",
        "software"
    ],
    "wof:name":"Simitar Software",
    "wof:placetype":"venue"
},
  "geometry": {"coordinates":[151.00193786599999,-33.8009605408],"type":"Point"}
}