{
  "type": "Feature",
  "properties": {
    "addr:full":"118 Burwood Hwy Burwood VIC 3125",
    "addr:housenumber":"118",
    "addr:postcode":"3125",
    "addr:street":"Burwood Hwy",
    "iso:country":"AU",
    "sg:address":"118 Burwood Hwy",
    "sg:city":"Burwood",
    "sg:classifiers":[
        {
            "category":"Home & Garden",
            "subcategory":"Hardware",
            "type":"Retail Goods"
        }
    ],
    "sg:phone":"+61 3 9274 0000",
    "sg:postcode":"3125",
    "sg:province":"VIC",
    "sg:tags":[
        "plumber",
        "supply"
    ],
    "wof:name":"Reece Pty Ltd",
    "wof:placetype":"venue"
},
  "geometry": {"coordinates":[145.09713745100001,-37.8506584167],"type":"Point"}
}