{
  "type": "Feature",
  "properties": {
    "addr:full":"60 Research-Warrandyte Rd Research VIC 3095",
    "addr:housenumber":"60",
    "addr:postcode":"3095",
    "addr:street":"Research-Warrandyte Rd",
    "iso:country":"AU",
    "sg:address":"60 Research-Warrandyte Rd",
    "sg:city":"Research",
    "sg:classifiers":[
        {
            "category":"Building & Trades",
            "subcategory":"Cleaning & Sanitation",
            "type":"Services"
        }
    ],
    "sg:phone":"+61 3 9437 0108",
    "sg:postcode":"3095",
    "sg:province":"VIC",
    "sg:tags":[
        "grease",
        "trap"
    ],
    "wof:name":"Research Septic Tank Cleaning Service",
    "wof:placetype":"venue"
},
  "geometry": {"coordinates":[145.189743042,-37.7110137939],"type":"Point"}
}