{
  "type": "Feature",
  "properties": {
    "addr:full":"16 Papps Rd Brunswick Junction WA 6224",
    "addr:housenumber":"16",
    "addr:postcode":"6224",
    "addr:street":"Papps Rd",
    "iso:country":"AU",
    "sg:address":"16 Papps Rd",
    "sg:city":"Brunswick Junction",
    "sg:classifiers":[
        {
            "category":"Professional",
            "subcategory":"Engineering",
            "type":"Services"
        }
    ],
    "sg:phone":"+61 8 9726 1320",
    "sg:postcode":"6224",
    "sg:province":"WA",
    "sg:tags":[
        "engineer"
    ],
    "wof:name":"B M R Engineering",
    "wof:placetype":"venue"
},
  "geometry": {"coordinates":[115.839691,-33.252102],"type":"Point"}
}