{
  "type": "Feature",
  "properties": {
    "iso:country":"AU",
    "sg:address":"45 Jardine St",
    "sg:city":"Kingston",
    "sg:classifiers":[
        {
            "category":"Banks & Credit Unions",
            "subcategory":"Bank",
            "type":"Services"
        }
    ],
    "sg:phone":"+61 2 6239 4215",
    "sg:postcode":"2604",
    "sg:province":"ACT",
    "sg:tags":[
        "broker",
        "mortgage"
    ],
    "wof:name":"Mortgage Choice",
    "wof:placetype":"venue"
},
  "geometry": {"coordinates":[149.14242553700001,-35.3158950806],"type":"Point"}
}