{
  "type": "Feature",
  "properties": {
    "addr:full":"46 Kenny St Wollongong NSW 2500",
    "addr:housenumber":"46",
    "addr:postcode":"2500",
    "addr:street":"Kenny St",
    "iso:country":"AU",
    "sg:address":"46 Kenny St",
    "sg:city":"Wollongong",
    "sg:classifiers":[
        {
            "category":"Retail",
            "subcategory":"Auto Repair",
            "type":"Services"
        }
    ],
    "sg:phone":"+61 2 4225 3800",
    "sg:postcode":"2500",
    "sg:province":"NSW",
    "sg:tags":[
        "repairer",
        "motor",
        "engineer"
    ],
    "wof:name":"City Centre Automotives",
    "wof:placetype":"venue"
},
  "geometry": {"coordinates":[150.89146400000001,-34.429478],"type":"Point"}
}