{
  "type": "Feature",
  "properties": {
    "iso:country":"AU",
    "sg:address":"Edwards St (cnr Wickham St)",
    "sg:city":"Ayr",
    "sg:classifiers":[
        {
            "category":"Education",
            "subcategory":"School",
            "type":"Public Place"
        }
    ],
    "sg:phone":"+61 7 4790 4333",
    "sg:postcode":"4807",
    "sg:province":"QLD",
    "sg:tags":[
        "state",
        "except",
        "nsw"
    ],
    "wof:name":"Ayr High School",
    "wof:placetype":"venue"
},
  "geometry": {"coordinates":[147.40431213400001,-19.5724773407],"type":"Point"}
}