{
  "type": "Feature",
  "properties": {
    "iso:country":"AU",
    "sg:address":"14 Evans Crs",
    "sg:city":"Laverton",
    "sg:classifiers":[
        {
            "category":"Building & Trades",
            "subcategory":"Plumbing",
            "type":"Services"
        }
    ],
    "sg:phone":"+61 413 259 553",
    "sg:postcode":"3028",
    "sg:province":"VIC",
    "sg:tags":[
        "plumber",
        "gasfitters"
    ],
    "wof:name":"Marshall Plumbing & Roofing",
    "wof:placetype":"venue"
},
  "geometry": {"coordinates":[144.769699,-37.86277],"type":"Point"}
}