{
  "type": "Feature",
  "properties": {
    "iso:country":"AU",
    "sg:address":"13 Moore Rd",
    "sg:city":"Airport West",
    "sg:classifiers":[
        {
            "category":"Autos & Motor Vehicles",
            "subcategory":"Auto Supplies",
            "type":"Retail Goods"
        }
    ],
    "sg:phone":"+61 3 9338 1605",
    "sg:postcode":"3042",
    "sg:province":"VIC",
    "sg:tags":[
        "pipe",
        "bending",
        "tube",
        "machinery"
    ],
    "wof:name":"Westgear Engineering Co",
    "wof:placetype":"venue"
},
  "geometry": {"coordinates":[144.89088439899999,-37.7170372009],"type":"Point"}
}