{
  "type": "Feature",
  "properties": {
    "addr:full":"39 Enterprise St Bundaberg QLD 4670",
    "addr:housenumber":"39",
    "addr:postcode":"4670",
    "addr:street":"Enterprise St",
    "iso:country":"AU",
    "sg:address":"39 Enterprise St",
    "sg:city":"Bundaberg",
    "sg:classifiers":[
        {
            "category":"Home & Garden",
            "subcategory":"Building Materials",
            "type":"Retail Goods"
        }
    ],
    "sg:phone":"+61 7 4151 7709",
    "sg:postcode":"4670",
    "sg:province":"QLD",
    "sg:tags":[
        "pre-mixed",
        "concrete"
    ],
    "wof:name":"Boral",
    "wof:placetype":"venue"
},
  "geometry": {"coordinates":[152.32899475100001,-24.8884658813],"type":"Point"}
}