{
  "type": "Feature",
  "properties": {
    "addr:full":"Level 3/ 104 Bathurst St Sydney NSW 2000",
    "addr:housenumber":"/ 104",
    "addr:postcode":"2000",
    "addr:street":"Bathurst St",
    "iso:country":"AU",
    "sg:address":"Level 3/ 104 Bathurst St",
    "sg:city":"Sydney",
    "sg:classifiers":[
        {
            "category":"Professional",
            "subcategory":"Management & Consulting",
            "type":"Services"
        }
    ],
    "sg:phone":"+61 2 9267 0070",
    "sg:postcode":"2000",
    "sg:province":"NSW",
    "sg:tags":[
        "consultant",
        "migration"
    ],
    "wof:name":"Arain & Associates",
    "wof:placetype":"venue"
},
  "geometry": {"coordinates":[151.20661926299999,-33.8744468689],"type":"Point"}
}