{
  "type": "Feature",
  "properties": {
    "addr:full":"357 Burwood Rd Hawthorn VIC 3122",
    "addr:housenumber":"357",
    "addr:postcode":"3122",
    "addr:street":"Burwood Rd",
    "iso:country":"AU",
    "sg:address":"357 Burwood Rd",
    "sg:city":"Hawthorn",
    "sg:classifiers":[
        {
            "category":"Personal",
            "subcategory":"Beauty Salon",
            "type":"Services"
        }
    ],
    "sg:phone":"+61 3 9818 3355",
    "sg:postcode":"3122",
    "sg:province":"VIC",
    "sg:tags":[
        "hairdresser"
    ],
    "wof:name":"Fran Capelli",
    "wof:placetype":"venue"
},
  "geometry": {"coordinates":[145.03579711899999,-37.8224754333],"type":"Point"}
}