{
  "type": "Feature",
  "properties": {
    "addr:full":"8 Toohey St Kirwan QLD 4817",
    "addr:housenumber":"8",
    "addr:postcode":"4817",
    "addr:street":"Toohey St",
    "iso:country":"AU",
    "sg:address":"8 Toohey St",
    "sg:city":"Kirwan",
    "sg:classifiers":[
        {
            "category":"Professional",
            "subcategory":"Computer Services",
            "type":"Services"
        }
    ],
    "sg:phone":"+61 7 4799 9999",
    "sg:postcode":"4817",
    "sg:province":"QLD",
    "sg:tags":[
        "equipment",
        "networking",
        "installation"
    ],
    "sg:website":"http://www.futuretownsville.com.au",
    "wof:name":"Future Townsville",
    "wof:placetype":"venue"
},
  "geometry": {"coordinates":[146.73335299999999,-19.300898],"type":"Point"}
}