{
  "type": "Feature",
  "properties": {
    "iso:country":"AU",
    "sg:address":"10 Sydney Rd",
    "sg:city":"Bayswater",
    "sg:classifiers":[
        {
            "category":"Banks & Credit Unions",
            "subcategory":"Bank",
            "type":"Services"
        }
    ],
    "sg:phone":"+61 3 9294 7800",
    "sg:postcode":"3153",
    "sg:province":"VIC",
    "sg:tags":[
        "concrete",
        "reinforcement"
    ],
    "wof:name":"Smorgon Steel Reinforcing",
    "wof:placetype":"venue"
},
  "geometry": {"coordinates":[145.25047302199999,-37.8439598083],"type":"Point"}
}