{
  "type": "Feature",
  "properties": {
    "addr:full":"PO Box 37 Hopetoun WA 6348",
    "addr:postcode":"6348",
    "iso:country":"AU",
    "sg:address":"PO Box 37",
    "sg:city":"Hopetoun",
    "sg:classifiers":[
        {
            "category":"Farming",
            "subcategory":"Farm",
            "type":"Manufacturing & Wholesale Goods"
        }
    ],
    "sg:phone":"+61 8 9838 5034",
    "sg:postcode":"6348",
    "sg:province":"WA",
    "sg:tags":[
        "farmer"
    ],
    "wof:name":"Auld Anthony",
    "wof:placetype":"venue"
},
  "geometry": {"coordinates":[120.16433000000001,-33.87133],"type":"Point"}
}