{
  "type": "Feature",
  "properties": {
    "addr:full":"Rear 522 Botany Rd Alexandria NSW 2015",
    "addr:housenumber":"522",
    "addr:postcode":"2015",
    "addr:street":"Botany Rd",
    "iso:country":"AU",
    "sg:address":"Rear 522 Botany Rd",
    "sg:city":"Alexandria",
    "sg:classifiers":[
        {
            "category":"Banks & Credit Unions",
            "subcategory":"Investment Brokerage",
            "type":"Services"
        }
    ],
    "sg:phone":"+61 2 9699 3728",
    "sg:postcode":"2015",
    "sg:province":"NSW",
    "sg:tags":[
        "radiator",
        "motor"
    ],
    "wof:name":"Alexandria Radiator Service",
    "wof:placetype":"venue"
},
  "geometry": {"coordinates":[151.200897217,-33.9140968323],"type":"Point"}
}