{
  "type": "Feature",
  "properties": {
    "iso:country":"AU",
    "sg:address":"( Head Office ) 83",
    "sg:city":"-85 Stirling Highway, Nedlands",
    "sg:classifiers":[
        {
            "category":"Shopping",
            "subcategory":"Computers & Home Electronics",
            "type":"Retail Goods"
        }
    ],
    "sg:phone":"+61 1300 132 203",
    "sg:postcode":"6009",
    "sg:province":"WA",
    "sg:tags":[
        "hi-fi",
        "equipment"
    ],
    "wof:name":"Surround Sounds",
    "wof:placetype":"venue"
},
  "geometry": {"coordinates":[115.804153,-31.978903],"type":"Point"}
}