{
  "type": "Feature",
  "properties": {
    "addr:full":"89 City Rd Southbank VIC 3006",
    "addr:housenumber":"89",
    "addr:postcode":"3006",
    "addr:street":"City Rd",
    "iso:country":"AU",
    "sg:address":"89 City Rd",
    "sg:city":"Southbank",
    "sg:classifiers":[
        {
            "category":"Health Services",
            "subcategory":"Health Practitioner",
            "type":"Services"
        }
    ],
    "sg:phone":"+61 3 9650 1347",
    "sg:postcode":"3006",
    "sg:province":"VIC",
    "sg:tags":[
        "physiotherapist"
    ],
    "wof:name":"Southbank Sports & Spinal Physiotherapy",
    "wof:placetype":"venue"
},
  "geometry": {"coordinates":[144.96461486800001,-37.822517395],"type":"Point"}
}