{
  "type": "Feature",
  "properties": {
    "addr:full":"Suite 208/ 13 Spring St Chatswood NSW 2067",
    "addr:housenumber":"/ 13",
    "addr:postcode":"2067",
    "addr:street":"Spring St",
    "iso:country":"AU",
    "sg:address":"Suite 208/ 13 Spring St",
    "sg:city":"Chatswood",
    "sg:classifiers":[
        {
            "category":"Professional",
            "subcategory":"Accounting & Tax Preparation",
            "type":"Services"
        }
    ],
    "sg:phone":"+61 2 9410 2666",
    "sg:postcode":"2067",
    "sg:province":"NSW",
    "sg:tags":[
        "accountant",
        "auditor"
    ],
    "wof:name":"R A Craig Financial Services",
    "wof:placetype":"venue"
},
  "geometry": {"coordinates":[151.184814453,-33.7964248657],"type":"Point"}
}