{
  "type": "Feature",
  "properties": {
    "addr:full":"Cnr Sunset Drv & Traders Way Mt Isa QLD 4825",
    "addr:postcode":"4825",
    "addr:street":"Cnr Sunset Drv;Way",
    "iso:country":"AU",
    "sg:address":"Cnr Sunset Drv",
    "sg:city":"& Traders Way Mt Isa",
    "sg:classifiers":[
        {
            "category":"Professional",
            "subcategory":"Detective & Security Services",
            "type":"Services"
        }
    ],
    "sg:phone":"+61 7 4743 0203",
    "sg:postcode":"4825",
    "sg:province":"QLD",
    "sg:tags":[
        "equipment",
        "window",
        "doors"
    ],
    "wof:name":"Isa Glass",
    "wof:placetype":"venue"
},
  "geometry": {"coordinates":[139.50224299999999,-20.708803],"type":"Point"}
}