{
  "type": "Feature",
  "properties": {
    "iso:country":"AU",
    "sg:address":"Cnr Sunset Drv",
    "sg:city":"& Traders Way Mt Isa",
    "sg:classifiers":[
        {
            "category":"Professional",
            "subcategory":"Detective & Security Services",
            "type":"Services"
        }
    ],
    "sg:phone":"+61 7 4743 0203",
    "sg:postcode":"4825",
    "sg:province":"QLD",
    "sg:tags":[
        "equipment",
        "window",
        "doors"
    ],
    "wof:name":"Isa Glass",
    "wof:placetype":"venue"
},
  "geometry": {"coordinates":[139.502243,-20.708803],"type":"Point"}
}