{
  "type": "Feature",
  "properties": {
    "iso:country":"AU",
    "sg:address":"Unit 8, 34 Lidco St",
    "sg:city":"Arndell Park",
    "sg:classifiers":[
        {
            "category":"Retail",
            "subcategory":"Auto Repair",
            "type":"Services"
        }
    ],
    "sg:phone":"+61 2 9621 2411",
    "sg:postcode":"2148",
    "sg:province":"NSW",
    "sg:tags":[
        "repairer",
        "motor",
        "engineer"
    ],
    "wof:name":"Insight Motorsports",
    "wof:placetype":"venue"
},
  "geometry": {"coordinates":[150.88351440400001,-33.7915802002],"type":"Point"}
}