{
  "type": "Feature",
  "properties": {
    "addr:full":"509 Burwood Rd Belmore NSW 2192",
    "addr:housenumber":"509",
    "addr:postcode":"2192",
    "addr:street":"Burwood Rd",
    "iso:country":"AU",
    "sg:address":"509 Burwood Rd",
    "sg:city":"Belmore",
    "sg:classifiers":[
        {
            "category":"Health Services",
            "subcategory":"Doctor",
            "type":"Services"
        }
    ],
    "sg:phone":"+61 2 9750 5394",
    "sg:postcode":"2192",
    "sg:province":"NSW",
    "sg:tags":[
        "medical",
        "practitioner"
    ],
    "wof:name":"Salama J B",
    "wof:placetype":"venue"
},
  "geometry": {"coordinates":[151.09019499999999,-33.921597],"type":"Point"}
}