{
  "type": "Feature",
  "properties": {
    "iso:country":"AU",
    "sg:address":"107 Jane St",
    "sg:city":"West End (Brisbane)",
    "sg:classifiers":[
        {
            "category":"Building & Trades",
            "subcategory":"Equipment Rental",
            "type":"Services"
        }
    ],
    "sg:phone":"+61 7 3307 4400",
    "sg:postcode":"4101",
    "sg:province":"QLD",
    "sg:tags":[
        "party",
        "hire"
    ],
    "wof:name":"Express Party Hire",
    "wof:placetype":"venue"
},
  "geometry": {"coordinates":[153.00607299800001,-27.4777984619],"type":"Point"}
}