{
  "type": "Feature",
  "properties": {
    "addr:full":"252 Powell St Grafton NSW 2460",
    "addr:housenumber":"252",
    "addr:postcode":"2460",
    "addr:street":"Powell St",
    "iso:country":"AU",
    "sg:address":"252 Powell St",
    "sg:city":"Grafton",
    "sg:classifiers":[
        {
            "category":"Building & Trades",
            "subcategory":"Construction",
            "type":"Services"
        }
    ],
    "sg:phone":"+61 417 197 532",
    "sg:postcode":"2460",
    "sg:province":"NSW",
    "sg:tags":[
        "contractor"
    ],
    "wof:name":"Gary Powell",
    "wof:placetype":"venue"
},
  "geometry": {"coordinates":[152.93199157699999,-29.674779892],"type":"Point"}
}