{
  "type": "Feature",
  "properties": {
    "addr:full":"60 Adelaide Rd Gawler SA 5118",
    "addr:housenumber":"60",
    "addr:postcode":"5118",
    "addr:street":"Adelaide Rd",
    "iso:country":"AU",
    "sg:address":"60 Adelaide Rd",
    "sg:city":"Gawler",
    "sg:classifiers":[
        {
            "category":"Professional",
            "subcategory":"Printing & Photocopies",
            "type":"Services"
        }
    ],
    "sg:phone":"+61 8 8522 2156",
    "sg:postcode":"5118",
    "sg:province":"SA",
    "sg:tags":[
        "textile",
        "clothing"
    ],
    "wof:name":"Im-Press Promotions Gawler",
    "wof:placetype":"venue"
},
  "geometry": {"coordinates":[138.74487300000001,-34.60648],"type":"Point"}
}