{
  "type": "Feature",
  "properties": {
    "iso:country":"AU",
    "sg:address":"Cnr Southern Cross Drv & Convair Ave",
    "sg:city":"Ballina",
    "sg:classifiers":[
        {
            "category":"Professional",
            "subcategory":"Engineering",
            "type":"Services"
        }
    ],
    "sg:phone":"+61 2 6686 8530",
    "sg:postcode":"2478",
    "sg:province":"NSW",
    "sg:tags":[
        "diesel",
        "engineer"
    ],
    "wof:name":"Ballina Diesel Service",
    "wof:placetype":"venue"
},
  "geometry": {"coordinates":[153.55337524399999,-28.8440418243],"type":"Point"}
}