{
  "type": "Feature",
  "properties": {
    "iso:country":"AU",
    "sg:address":"37 Cowper St",
    "sg:city":"Granville",
    "sg:classifiers":[
        {
            "category":"Retail",
            "subcategory":"Auto Repair",
            "type":"Services"
        }
    ],
    "sg:phone":"+61 2 9637 1077",
    "sg:postcode":"2142",
    "sg:province":"NSW",
    "sg:tags":[
        "repairer",
        "motor",
        "engineer"
    ],
    "wof:name":"Lovely D & P Auto Services",
    "wof:placetype":"venue"
},
  "geometry": {"coordinates":[151.01234435999999,-33.8313827515],"type":"Point"}
}