{
  "type": "Feature",
  "properties": {
    "iso:country":"AU",
    "sg:address":"23 Montalbert Dr",
    "sg:city":"Campbellfield",
    "sg:classifiers":[
        {
            "category":"Professional",
            "subcategory":"Art Services",
            "type":"Services"
        }
    ],
    "sg:phone":"+61 3 9324 1977",
    "sg:postcode":"3061",
    "sg:province":"VIC",
    "sg:tags":[
        "decorator",
        "painter"
    ],
    "wof:name":"Fine Painting",
    "wof:placetype":"venue"
},
  "geometry": {"coordinates":[144.96864318900001,-37.6777801514],"type":"Point"}
}