{
  "type": "Feature",
  "properties": {
    "addr:full":"9 Angorra Rd Terrey Hills NSW 2084",
    "addr:housenumber":"9",
    "addr:postcode":"2084",
    "addr:street":"Angorra Rd",
    "iso:country":"AU",
    "sg:address":"9 Angorra Rd",
    "sg:city":"Terrey Hills",
    "sg:classifiers":[
        {
            "category":"Utilities",
            "subcategory":"Electric",
            "type":"Services"
        }
    ],
    "sg:phone":"+61 2 9450 1493",
    "sg:postcode":"2084",
    "sg:province":"NSW",
    "sg:tags":[
        "electrical",
        "contractor"
    ],
    "wof:name":"B.V. Electrics",
    "wof:placetype":"venue"
},
  "geometry": {"coordinates":[151.22137451200001,-33.6808395386],"type":"Point"}
}