{
  "type": "Feature",
  "properties": {
    "iso:country":"AU",
    "sg:address":"PO Box 97",
    "sg:city":"Penguin",
    "sg:classifiers":[
        {
            "category":"Building & Trades",
            "subcategory":"Construction",
            "type":"Services"
        }
    ],
    "sg:phone":"+61 3 6437 1397",
    "sg:postcode":"7316",
    "sg:province":"TAS",
    "sg:tags":[
        "spouting",
        "guttering"
    ],
    "wof:name":"Good G.C.",
    "wof:placetype":"venue"
},
  "geometry": {"coordinates":[146.06695556599999,-41.1111183167],"type":"Point"}
}