{
  "type": "Feature",
  "properties": {
    "iso:country":"AU",
    "sg:address":"276 Peel St",
    "sg:city":"Tamworth",
    "sg:classifiers":[
        {
            "category":"Fast Food",
            "type":"Food & Drink"
        }
    ],
    "sg:phone":"+61 2 6766 5757",
    "sg:postcode":"2340",
    "sg:province":"NSW",
    "sg:tags":[
        "away",
        "take"
    ],
    "wof:name":"Wing Wah Restaurant",
    "wof:placetype":"venue"
},
  "geometry": {"coordinates":[150.92825317399999,-31.0886745453],"type":"Point"}
}