{
  "type": "Feature",
  "properties": {
    "addr:full":"Shop 2082/ 600 Kingsway Miranda NSW 2228",
    "addr:housenumber":"2082 / 600",
    "addr:postcode":"2228",
    "addr:street":"Kingsway Miranda",
    "iso:country":"AU",
    "sg:address":"Shop 2082/ 600 Kingsway",
    "sg:city":"Miranda",
    "sg:classifiers":[
        {
            "category":"Food & Beverages",
            "subcategory":"Fruits & Vegetables",
            "type":"Retail Goods"
        }
    ],
    "sg:phone":"+61 2 9524 7366",
    "sg:postcode":"2228",
    "sg:province":"NSW",
    "sg:tags":[
        "greengrocer",
        "fruiterer"
    ],
    "wof:name":"Fruities Fruit Market",
    "wof:placetype":"venue"
},
  "geometry": {"coordinates":[151.10191345199999,-34.0343055725],"type":"Point"}
}