{
  "type": "Feature",
  "properties": {
    "iso:country":"AU",
    "sg:address":"53 Main St",
    "sg:city":"Croydon",
    "sg:classifiers":[
        {
            "category":"Real Estate",
            "subcategory":"Real Estate Agent",
            "type":"Services"
        }
    ],
    "sg:phone":"+61 3 9723 0281",
    "sg:postcode":"3136",
    "sg:province":"VIC",
    "wof:name":"Max Brown Real Estate",
    "wof:placetype":"venue"
},
  "geometry": {"coordinates":[145.280883789,-37.7963485718],"type":"Point"}
}