{
  "type": "Feature",
  "properties": {
    "iso:country":"AU",
    "sg:address":"24 Panamena Crs",
    "sg:city":"Eleebana",
    "sg:classifiers":[
        {
            "category":"Home & Garden",
            "subcategory":"Building Materials",
            "type":"Retail Goods"
        }
    ],
    "sg:phone":"+61 421 855 560",
    "sg:postcode":"2282",
    "sg:province":"NSW",
    "sg:tags":[
        "merchant",
        "glass",
        "glazier"
    ],
    "wof:name":"Eastlakes Glass",
    "wof:placetype":"venue"
},
  "geometry": {"coordinates":[151.63616943400001,-32.9896888733],"type":"Point"}
}