{
  "type": "Feature",
  "properties": {
    "iso:country":"AU",
    "sg:address":"6 Waratah Ave",
    "sg:city":"Casula",
    "sg:classifiers":[
        {
            "category":"Professional",
            "subcategory":"Art Services",
            "type":"Services"
        }
    ],
    "sg:phone":"+61 425 278 992",
    "sg:postcode":"2170",
    "sg:province":"NSW",
    "sg:tags":[
        "decorator",
        "painter"
    ],
    "wof:name":"Jacks Painting Works",
    "wof:placetype":"venue"
},
  "geometry": {"coordinates":[150.90779113799999,-33.939125061],"type":"Point"}
}