{
  "type": "Feature",
  "properties": {
    "addr:full":"Lvl 1/ 58 Pitt St Sydney NSW 2000",
    "addr:housenumber":"/ 58",
    "addr:postcode":"2000",
    "addr:street":"Pitt St",
    "iso:country":"AU",
    "sg:address":"Lvl 1/ 58 Pitt St",
    "sg:city":"Sydney",
    "sg:classifiers":[
        {
            "category":"Building & Trades",
            "subcategory":"Construction",
            "type":"Services"
        }
    ],
    "sg:phone":"+61 2 8259 8550",
    "sg:postcode":"2000",
    "sg:province":"NSW",
    "sg:tags":[
        "management"
    ],
    "wof:name":"Calibre Management Pty Ltd",
    "wof:placetype":"venue"
},
  "geometry": {"coordinates":[151.20903015100001,-33.864025116],"type":"Point"}
}