{
  "type": "Feature",
  "properties": {
    "addr:full":"455 Pacific Hwy Belmont NSW 2280",
    "addr:housenumber":"455",
    "addr:postcode":"2280",
    "addr:street":"Pacific Hwy",
    "iso:country":"AU",
    "sg:address":"455 Pacific Hwy",
    "sg:city":"Belmont",
    "sg:classifiers":[
        {
            "category":"Retail",
            "subcategory":"Auto Repair",
            "type":"Services"
        }
    ],
    "sg:phone":"+61 2 4945 9988",
    "sg:postcode":"2280",
    "sg:province":"NSW",
    "sg:tags":[
        "automotive",
        "air conditioning"
    ],
    "wof:name":"Belmont Auto Electrics",
    "wof:placetype":"venue"
},
  "geometry": {"coordinates":[151.661499023,-33.0287780762],"type":"Point"}
}