{
  "type": "Feature",
  "properties": {
    "iso:country":"AU",
    "sg:address":"43 Nancy St",
    "sg:city":"North Bondi",
    "sg:classifiers":[
        {
            "category":"Education",
            "subcategory":"Special Training",
            "type":"Public Place"
        }
    ],
    "sg:phone":"+61 2 9371 7611",
    "sg:postcode":"2026",
    "sg:province":"NSW",
    "sg:tags":[
        "development"
    ],
    "wof:name":"Drum Cafe Australia Pty Ltd",
    "wof:placetype":"venue"
},
  "geometry": {"coordinates":[151.27647399899999,-33.8797531128],"type":"Point"}
}