{
  "type": "Feature",
  "properties": {
    "iso:country":"AU",
    "sg:address":"22 Honeytree Pl",
    "sg:city":"Mandurah",
    "sg:classifiers":[
        {
            "category":"Mining & Drilling",
            "type":"Manufacturing & Wholesale Goods"
        }
    ],
    "sg:phone":"+61 8 9534 4777",
    "sg:postcode":"6210",
    "sg:province":"WA",
    "sg:tags":[
        "geologist"
    ],
    "wof:name":"Peter F Robinson & Associates Pty Ltd",
    "wof:placetype":"venue"
},
  "geometry": {"coordinates":[115.663643,-32.593609],"type":"Point"}
}