{
  "type": "Feature",
  "properties": {
    "addr:full":"22 Honeytree Pl Mandurah WA 6210",
    "addr:housenumber":"22",
    "addr:postcode":"6210",
    "addr:street":"Honeytree Pl",
    "iso:country":"AU",
    "sg:address":"22 Honeytree Pl",
    "sg:city":"Mandurah",
    "sg:classifiers":[
        {
            "category":"Mining & Drilling",
            "type":"Manufacturing & Wholesale Goods"
        }
    ],
    "sg:phone":"+61 8 9534 4777",
    "sg:postcode":"6210",
    "sg:province":"WA",
    "sg:tags":[
        "geologist"
    ],
    "wof:name":"Peter F Robinson & Associates Pty Ltd",
    "wof:placetype":"venue"
},
  "geometry": {"coordinates":[115.66364299999999,-32.593609],"type":"Point"}
}