{
  "type": "Feature",
  "properties": {
    "iso:country":"AU",
    "sg:address":"227 Berwood Rd",
    "sg:city":"Belmore",
    "sg:classifiers":[
        {
            "category":"Utilities",
            "subcategory":"Electric",
            "type":"Services"
        }
    ],
    "sg:phone":"+61 403 944 796",
    "sg:postcode":"2192",
    "sg:province":"NSW",
    "sg:tags":[
        "electrical",
        "contractor"
    ],
    "wof:name":"Michael Fotiadis",
    "wof:placetype":"venue"
},
  "geometry": {"coordinates":[151.085464,-33.912239],"type":"Point"}
}