{
  "type": "Feature",
  "properties": {
    "iso:country":"AU",
    "sg:address":"PO Box 159",
    "sg:city":"Noosa Heads",
    "sg:classifiers":[
        {
            "category":"Health Services",
            "subcategory":"Health Practitioner",
            "type":"Services"
        }
    ],
    "sg:phone":"+61 7 5449 7817",
    "sg:postcode":"4567",
    "sg:province":"QLD",
    "sg:tags":[
        "homoeopath"
    ],
    "wof:name":"Harmony Health",
    "wof:placetype":"venue"
},
  "geometry": {"coordinates":[153.086105347,-26.3990192413],"type":"Point"}
}