{
  "type": "Feature",
  "properties": {
    "addr:full":"29-31 Clarice Rd Box Hill South VIC 3128",
    "addr:housenumber":"29-31",
    "addr:postcode":"3128",
    "addr:street":"Clarice Rd",
    "iso:country":"AU",
    "sg:address":"29-31 Clarice Rd",
    "sg:city":"Box Hill South",
    "sg:classifiers":[
        {
            "category":"Manufacturing",
            "subcategory":"Tools & Machinery",
            "type":"Manufacturing & Wholesale Goods"
        }
    ],
    "sg:phone":"+61 3 9898 9644",
    "sg:postcode":"3128",
    "sg:province":"VIC",
    "sg:tags":[
        "supplier",
        "diamond"
    ],
    "wof:name":"Crozier Diamond Tools Australia (CDTA)",
    "wof:placetype":"venue"
},
  "geometry": {"coordinates":[145.13378906200001,-37.8359642029],"type":"Point"}
}