{
  "type": "Feature",
  "properties": {
    "addr:full":"550 Heatherton Rd Clayton South VIC 3169",
    "addr:housenumber":"550",
    "addr:postcode":"3169",
    "addr:street":"Heatherton Rd",
    "iso:country":"AU",
    "sg:address":"550 Heatherton Rd",
    "sg:city":"Clayton South",
    "sg:classifiers":[
        {
            "category":"Farming",
            "subcategory":"Nursery",
            "type":"Manufacturing & Wholesale Goods"
        }
    ],
    "sg:phone":"+61 3 9551 6929",
    "sg:postcode":"3169",
    "sg:province":"VIC",
    "wof:name":"Greenline Indoor Plants",
    "wof:placetype":"venue"
},
  "geometry": {"coordinates":[145.12150573700001,-37.9586181641],"type":"Point"}
}