{
  "type": "Feature",
  "properties": {
    "addr:full":"Shp7/ 4 Wilmot St Burnie TAS 7320",
    "addr:housenumber":"4",
    "addr:postcode":"7320",
    "addr:street":"Wilmot St",
    "iso:country":"AU",
    "sg:address":"Shp7/ 4 Wilmot St",
    "sg:city":"Burnie",
    "sg:classifiers":[
        {
            "category":"Personal",
            "subcategory":"Beauty Salon",
            "type":"Services"
        }
    ],
    "sg:phone":"+61 3 6431 2233",
    "sg:postcode":"7320",
    "sg:province":"TAS",
    "sg:tags":[
        "hairdresser"
    ],
    "wof:name":"Hair Renaissance",
    "wof:placetype":"venue"
},
  "geometry": {"coordinates":[145.90801999999999,-41.05125],"type":"Point"}
}