{
  "type": "Feature",
  "properties": {
    "addr:full":"17 Church St Wickham NSW 2293",
    "addr:housenumber":"17",
    "addr:postcode":"2293",
    "addr:street":"Church St",
    "iso:country":"AU",
    "sg:address":"17 Church St",
    "sg:city":"Wickham",
    "sg:classifiers":[
        {
            "category":"Sports & Exercise",
            "subcategory":"Gym",
            "type":"Entertainment"
        }
    ],
    "sg:phone":"+61 413 363 958",
    "sg:postcode":"2293",
    "sg:province":"NSW",
    "sg:tags":[
        "personal",
        "trainer",
        "fitness"
    ],
    "wof:name":"Action Boxing & Fitness",
    "wof:placetype":"venue"
},
  "geometry": {"coordinates":[151.75767517099999,-32.9200820923],"type":"Point"}
}