{
  "type": "Feature",
  "properties": {
    "addr:full":"143 Station St Fairfield VIC 3078",
    "addr:housenumber":"143",
    "addr:postcode":"3078",
    "addr:street":"Station St",
    "iso:country":"AU",
    "sg:address":"143 Station St",
    "sg:city":"Fairfield",
    "sg:classifiers":[
        {
            "category":"Food & Beverages",
            "subcategory":"Supermarket",
            "type":"Retail Goods"
        }
    ],
    "sg:phone":"+61 3 9481 0586",
    "sg:postcode":"3078",
    "sg:province":"VIC",
    "sg:tags":[
        "grocery",
        "store"
    ],
    "wof:name":"Cardamone IGA Friendly Grocer",
    "wof:placetype":"venue"
},
  "geometry": {"coordinates":[145.018707275,-37.7765426636],"type":"Point"}
}