{
  "type": "Feature",
  "properties": {
    "addr:full":"81 Granite St Geebung QLD 4034",
    "addr:housenumber":"81",
    "addr:postcode":"4034",
    "addr:street":"Granite St",
    "iso:country":"AU",
    "sg:address":"81 Granite St",
    "sg:city":"Geebung",
    "sg:classifiers":[
        {
            "category":"Government",
            "subcategory":"Court House",
            "type":"Public Place"
        }
    ],
    "sg:phone":"+61 7 3865 8644",
    "sg:postcode":"4034",
    "sg:province":"QLD",
    "sg:tags":[
        "personal",
        "marriage",
        "family",
        "counselling"
    ],
    "wof:name":"Brisbane Grief & Bereavement Support Centre",
    "wof:placetype":"venue"
},
  "geometry": {"coordinates":[153.05114699999999,-27.364342],"type":"Point"}
}