{
  "type": "Feature",
  "properties": {
    "addr:full":"46 Moulamien Rd Barham NSW 2732",
    "addr:housenumber":"46",
    "addr:postcode":"2732",
    "addr:street":"Moulamien Rd",
    "iso:country":"AU",
    "sg:address":"46 Moulamien Rd",
    "sg:city":"Barham",
    "sg:classifiers":[
        {
            "category":"Building & Trades",
            "subcategory":"Plumbing",
            "type":"Services"
        }
    ],
    "sg:phone":"+61 3 5453 2354",
    "sg:postcode":"2732",
    "sg:province":"NSW",
    "sg:tags":[
        "plumber",
        "gasfitters"
    ],
    "wof:name":"Boyd Plumbing&Supplies",
    "wof:placetype":"venue"
},
  "geometry": {"coordinates":[144.13185100000001,-35.62077],"type":"Point"}
}