{
  "type": "Feature",
  "properties": {
    "iso:country":"AU",
    "sg:address":"2/ 22 Marine Tce",
    "sg:city":"Burnie",
    "sg:classifiers":[
        {
            "category":"Shopping",
            "subcategory":"Computers & Home Electronics",
            "type":"Retail Goods"
        }
    ],
    "sg:phone":"+61 3 6432 1206",
    "sg:postcode":"7320",
    "sg:province":"TAS",
    "sg:tags":[
        "hardware",
        "equipment"
    ],
    "wof:name":"SMBT Computing",
    "wof:placetype":"venue"
},
  "geometry": {"coordinates":[145.903992,-41.049217],"type":"Point"}
}