{
  "type": "Feature",
  "properties": {
    "iso:country":"AU",
    "sg:address":"Lot 48 Cutler Rd",
    "sg:city":"Jandakot",
    "sg:classifiers":[
        {
            "category":"Manufacturing",
            "subcategory":"Tools & Machinery",
            "type":"Manufacturing & Wholesale Goods"
        }
    ],
    "sg:phone":"+61 8 9417 7401",
    "sg:postcode":"6164",
    "sg:province":"WA",
    "sg:tags":[
        "earth",
        "excavating",
        "moving",
        "equipment"
    ],
    "wof:name":"Westerfeld Undercarriage Pty Ltd",
    "wof:placetype":"venue"
},
  "geometry": {"coordinates":[115.867958,-32.120567],"type":"Point"}
}