{
  "type": "Feature",
  "properties": {
    "addr:full":"130 Mandurang South Rd Mandurang South VIC 3551",
    "addr:housenumber":"130",
    "addr:postcode":"3551",
    "addr:street":"Mandurang South Rd",
    "iso:country":"AU",
    "sg:address":"130 Mandurang South Rd",
    "sg:city":"Mandurang South",
    "sg:classifiers":[
        {
            "category":"Building & Trades",
            "subcategory":"Landscaping Services",
            "type":"Services"
        }
    ],
    "sg:phone":"+61 3 5439 3778",
    "sg:postcode":"3551",
    "sg:province":"VIC",
    "sg:tags":[
        "firebreak",
        "clearing",
        "land",
        "contractor"
    ],
    "wof:name":"Adrian Todd Earthmoving",
    "wof:placetype":"venue"
},
  "geometry": {"coordinates":[144.28109741200001,-36.8556785583],"type":"Point"}
}