{
  "type": "Feature",
  "properties": {
    "addr:full":"Bowen Rd Townsville QLD 4810",
    "addr:postcode":"4810",
    "addr:street":"Bowen Rd",
    "iso:country":"AU",
    "sg:address":"Bowen Rd",
    "sg:city":"Townsville",
    "sg:classifiers":[
        {
            "category":"Autos & Motor Vehicles",
            "subcategory":"Fuel & Gas Station",
            "type":"Retail Goods"
        }
    ],
    "sg:phone":"+61 7 4779 1029",
    "sg:postcode":"4810",
    "sg:province":"QLD",
    "wof:name":"BP Australia Limited",
    "wof:placetype":"venue"
},
  "geometry": {"coordinates":[146.795975,-19.291185],"type":"Point"}
}