{
  "type": "Feature",
  "properties": {
    "iso:country":"AU",
    "sg:address":"327 High St",
    "sg:city":"Chatswood",
    "sg:phone":"+61 2 9417 3222",
    "sg:postcode":"2067",
    "sg:province":"NSW",
    "wof:name":"Environmental Piping Services",
    "wof:placetype":"venue"
},
  "geometry": {"coordinates":[151.19676208499999,-33.7869987488],"type":"Point"}
}