{
  "type": "Feature",
  "properties": {
    "addr:full":"17 Permarig Pl Rocklea QLD 4106",
    "addr:housenumber":"17",
    "addr:postcode":"4106",
    "addr:street":"Permarig Pl",
    "iso:country":"AU",
    "sg:address":"17 Permarig Pl",
    "sg:city":"Rocklea",
    "sg:classifiers":[
        {
            "category":"Commercial Area",
            "type":"Public Place"
        }
    ],
    "sg:phone":"+61 7 3274 2727",
    "sg:postcode":"4106",
    "sg:province":"QLD",
    "sg:tags":[
        "heavy",
        "carrier"
    ],
    "wof:name":"Marschalls Transport",
    "wof:placetype":"venue"
},
  "geometry": {"coordinates":[153.001495361,-27.5560092926],"type":"Point"}
}