{
  "type": "Feature",
  "properties": {
    "addr:full":"Shop 3, 10 Centenary Drv Maclean NSW 2463",
    "addr:housenumber":"shop;10",
    "addr:postcode":"2463",
    "addr:street":"Centenary Drv",
    "iso:country":"AU",
    "sg:address":"Shop 3, 10 Centenary Drv",
    "sg:city":"Maclean",
    "sg:classifiers":[
        {
            "category":"Health Services",
            "subcategory":"Health Practitioner",
            "type":"Services"
        }
    ],
    "sg:phone":"+61 2 6645 3105",
    "sg:postcode":"2463",
    "sg:province":"NSW",
    "sg:tags":[
        "acupuncture"
    ],
    "wof:name":"Coltman, Sally",
    "wof:placetype":"venue"
},
  "geometry": {"coordinates":[153.19737243599999,-29.4567699432],"type":"Point"}
}