{
  "type": "Feature",
  "properties": {
    "addr:full":"Mamre Rd Erskine Park NSW 2759",
    "addr:postcode":"2759",
    "addr:street":"Mamre Rd",
    "iso:country":"AU",
    "sg:address":"Mamre Rd",
    "sg:city":"Erskine Park",
    "sg:classifiers":[
        {
            "category":"Building & Trades",
            "subcategory":"Electrical",
            "type":"Services"
        }
    ],
    "sg:phone":"+61 2 9834 3113",
    "sg:postcode":"2759",
    "sg:province":"NSW",
    "sg:tags":[
        "electric",
        "fence"
    ],
    "wof:name":"Mamre Produce",
    "wof:placetype":"venue"
},
  "geometry": {"coordinates":[150.775924683,-33.8165740967],"type":"Point"}
}