{
  "type": "Feature",
  "properties": {
    "addr:full":"Shop 3 Lot 8 Mitchell Drv East Maitland NSW 2323",
    "addr:housenumber":"shop 3 lot 8",
    "addr:postcode":"2323",
    "addr:street":"Mitchell Drv",
    "iso:country":"AU",
    "sg:address":"Shop 3 Lot 8 Mitchell Drv",
    "sg:city":"East Maitland",
    "sg:classifiers":[
        {
            "category":"Travel",
            "subcategory":"Travel Agent",
            "type":"Entertainment"
        }
    ],
    "sg:phone":"+61 2 4934 5899",
    "sg:postcode":"2323",
    "sg:province":"NSW",
    "sg:tags":[
        "consultant"
    ],
    "wof:name":"Harvey World Travel",
    "wof:placetype":"venue"
},
  "geometry": {"coordinates":[151.591339111,-32.761013031],"type":"Point"}
}