{
  "type": "Feature",
  "properties": {
    "addr:full":"2 Havelock St West Perth WA 6005",
    "addr:housenumber":"2",
    "addr:postcode":"6005",
    "addr:street":"Havelock St",
    "iso:country":"AU",
    "sg:address":"2 Havelock St",
    "sg:city":"West Perth",
    "sg:classifiers":[
        {
            "category":"Building & Trades",
            "subcategory":"Construction",
            "type":"Services"
        }
    ],
    "sg:phone":"+61 8 9222 5920",
    "sg:postcode":"6005",
    "sg:province":"WA",
    "sg:tags":[
        "management"
    ],
    "wof:name":"Building & Construction Industry Task Force",
    "wof:placetype":"venue"
},
  "geometry": {"coordinates":[115.84291076700001,-31.9529209137],"type":"Point"}
}