{
  "type": "Feature",
  "properties": {
    "addr:full":"Shop 4, 155 Castlereagh St Sydney NSW 2000",
    "addr:housenumber":"shop 4 155",
    "addr:postcode":"2000",
    "addr:street":"Castlereagh St",
    "iso:country":"AU",
    "sg:address":"Shop 4, 155 Castlereagh St",
    "sg:city":"Sydney",
    "sg:classifiers":[
        {
            "category":"Shopping",
            "subcategory":"Hobbies, Toys, & Games",
            "type":"Retail Goods"
        }
    ],
    "sg:phone":"+61 2 9264 6168",
    "sg:postcode":"2000",
    "sg:province":"NSW",
    "sg:tags":[
        "stamp"
    ],
    "sg:website":"http://www.kennedystamps.com.au",
    "wof:name":"Kennedy Stamps Pty Ltd",
    "wof:placetype":"venue"
},
  "geometry": {"coordinates":[151.20916748100001,-33.8720703125],"type":"Point"}
}