{
  "type": "Feature",
  "properties": {
    "iso:country":"AU",
    "sg:address":"U 21/ 81 Briggs St",
    "sg:city":"Carlisle",
    "sg:classifiers":[
        {
            "category":"Shopping",
            "subcategory":"Party Supplies",
            "type":"Retail Goods"
        }
    ],
    "sg:phone":"+61 8 9361 3411",
    "sg:postcode":"6101",
    "sg:province":"WA",
    "sg:tags":[
        "selling",
        "plan"
    ],
    "wof:name":"Wikidz Wear",
    "wof:placetype":"venue"
},
  "geometry": {"coordinates":[115.926208496,-31.9845790863],"type":"Point"}
}