{
  "type": "Feature",
  "properties": {
    "addr:full":"160 Boundary Rd Bardon QLD 4065",
    "addr:housenumber":"160",
    "addr:postcode":"4065",
    "addr:street":"Boundary Rd",
    "iso:country":"AU",
    "sg:address":"160 Boundary Rd",
    "sg:city":"Bardon",
    "sg:classifiers":[
        {
            "category":"Personal",
            "subcategory":"Beauty Salon",
            "type":"Services"
        }
    ],
    "sg:phone":"+61 7 3367 0444",
    "sg:postcode":"4065",
    "sg:province":"QLD",
    "sg:tags":[
        "hairdresser"
    ],
    "wof:name":"Impress Hair Design",
    "wof:placetype":"venue"
},
  "geometry": {"coordinates":[152.98561096200001,-27.4668369293],"type":"Point"}
}