{
  "type": "Feature",
  "properties": {
    "iso:country":"AU",
    "sg:address":"6 May St",
    "sg:city":"Glenbrook",
    "sg:classifiers":[
        {
            "category":"Professional",
            "subcategory":"Business Services",
            "type":"Services"
        }
    ],
    "sg:phone":"+61 2 4739 3740",
    "sg:postcode":"2773",
    "sg:province":"NSW",
    "sg:tags":[
        "drafting"
    ],
    "wof:name":"Glenbrook Drafting",
    "wof:placetype":"venue"
},
  "geometry": {"coordinates":[150.628295898,-33.7658500671],"type":"Point"}
}