{
  "type": "Feature",
  "properties": {
    "iso:country":"AU",
    "sg:address":"22 McEwan Ave",
    "sg:city":"Winston Hills",
    "sg:classifiers":[
        {
            "category":"Building & Trades",
            "subcategory":"Construction",
            "type":"Services"
        }
    ],
    "sg:phone":"+61 2 9686 8890",
    "sg:postcode":"2153",
    "sg:province":"NSW",
    "sg:tags":[
        "contractor"
    ],
    "wof:name":"Totem Constructions",
    "wof:placetype":"venue"
},
  "geometry": {"coordinates":[150.99005126899999,-33.7795906067],"type":"Point"}
}