{
  "type": "Feature",
  "properties": {
    "addr:full":"103 Foveaux St Surry Hills NSW 2010",
    "addr:housenumber":"103",
    "addr:postcode":"2010",
    "addr:street":"Foveaux St",
    "iso:country":"AU",
    "sg:address":"103 Foveaux St",
    "sg:city":"Surry Hills",
    "sg:classifiers":[
        {
            "category":"Wholesale",
            "subcategory":"Apparel",
            "type":"Manufacturing & Wholesale Goods"
        }
    ],
    "sg:phone":"+61 2 9281 6037",
    "sg:postcode":"2010",
    "sg:province":"NSW",
    "sg:tags":[
        "wholesaler",
        "mfrs",
        "sportswear",
        "women's"
    ],
    "wof:name":"Tomato Clothing Company",
    "wof:placetype":"venue"
},
  "geometry": {"coordinates":[151.21168518100001,-33.8848648071],"type":"Point"}
}