{
  "type": "Feature",
  "properties": {
    "addr:full":"313 Mona Vale Rd Terrey Hills NSW 2084",
    "addr:housenumber":"313",
    "addr:postcode":"2084",
    "addr:street":"Mona Vale Rd",
    "iso:country":"AU",
    "sg:address":"313 Mona Vale Rd",
    "sg:city":"Terrey Hills",
    "sg:classifiers":[
        {
            "category":"Landmark",
            "subcategory":"Unesco World Heritage Site",
            "type":"Public Place"
        }
    ],
    "sg:phone":"+61 2 9450 2616",
    "sg:postcode":"2084",
    "sg:province":"NSW",
    "sg:tags":[
        "balloon",
        "hot",
        "air"
    ],
    "wof:name":"Outback Ballooning",
    "wof:placetype":"venue"
},
  "geometry": {"coordinates":[151.220092773,-33.6936912537],"type":"Point"}
}