{
  "type": "Feature",
  "properties": {
    "addr:full":"171 York St Albany WA 6330",
    "addr:housenumber":"171",
    "addr:postcode":"6330",
    "addr:street":"York St",
    "iso:country":"AU",
    "sg:address":"171 York St",
    "sg:city":"Albany",
    "sg:classifiers":[
        {
            "category":"Organizations",
            "subcategory":"Professional Association",
            "type":"Services"
        }
    ],
    "sg:phone":"+61 8 9842 2577",
    "sg:postcode":"6330",
    "sg:province":"WA",
    "sg:tags":[
        "organisation",
        "business"
    ],
    "wof:name":"Albany Chamber Of Commerce & Industry Inc",
    "wof:placetype":"venue"
},
  "geometry": {"coordinates":[117.883407593,-35.0249061584],"type":"Point"}
}