{
  "type": "Feature",
  "properties": {
    "addr:full":"33- 37 Sam St Forbes NSW 2871",
    "addr:housenumber":"37",
    "addr:postcode":"2871",
    "addr:street":"Sam St",
    "iso:country":"AU",
    "sg:address":"33- 37 Sam St",
    "sg:city":"Forbes",
    "sg:classifiers":[
        {
            "category":"Travel",
            "subcategory":"Hotels & Motels",
            "type":"Entertainment"
        }
    ],
    "sg:phone":"+61 2 6852 1957",
    "sg:postcode":"2871",
    "sg:province":"NSW",
    "wof:name":"Country Club Caravan Park",
    "wof:placetype":"venue"
},
  "geometry": {"coordinates":[148.01423600000001,-33.376923],"type":"Point"}
}