{
  "type": "Feature",
  "properties": {
    "addr:full":"153 Penshurst Rd Narwee NSW 2209",
    "addr:housenumber":"153",
    "addr:postcode":"2209",
    "addr:street":"Penshurst Rd",
    "iso:country":"AU",
    "sg:address":"153 Penshurst Rd",
    "sg:city":"Narwee",
    "sg:classifiers":[
        {
            "category":"Food & Beverages",
            "subcategory":"Supermarket",
            "type":"Retail Goods"
        }
    ],
    "sg:phone":"+61 2 9153 8343",
    "sg:postcode":"2209",
    "sg:province":"NSW",
    "sg:tags":[
        "grocery",
        "store"
    ],
    "wof:name":"M.F.C. Food Stores",
    "wof:placetype":"venue"
},
  "geometry": {"coordinates":[151.070618,-33.947048],"type":"Point"}
}