{
  "type": "Feature",
  "properties": {
    "addr:full":"Cnr Of Kingaroy & Alford Sts Kingaroy QLD 4610",
    "addr:postcode":"4610",
    "iso:country":"AU",
    "sg:address":"Cnr Of Kingaroy & Alford Sts",
    "sg:city":"Kingaroy",
    "sg:classifiers":[
        {
            "category":"Shopping",
            "subcategory":"Crafts & Fabrics",
            "type":"Retail Goods"
        }
    ],
    "sg:phone":"+61 7 4162 2974",
    "sg:postcode":"4610",
    "sg:province":"QLD",
    "sg:tags":[
        "supply"
    ],
    "wof:name":"Goldy's Gifts",
    "wof:placetype":"venue"
},
  "geometry": {"coordinates":[151.83926391599999,-26.5410461426],"type":"Point"}
}