{
  "type": "Feature",
  "properties": {
    "addr:full":"Malibu Resort 81 The Esplanade Mooloolaba QLD 4557",
    "addr:housenumber":"81",
    "addr:postcode":"4557",
    "addr:street":"The Esplanade",
    "iso:country":"AU",
    "sg:address":"Malibu Resort 81",
    "sg:city":"The Esplanade Mooloolaba",
    "sg:classifiers":[
        {
            "category":"Arts & Performance",
            "subcategory":"Art Gallery",
            "type":"Entertainment"
        }
    ],
    "sg:phone":"+61 7 5452 5600",
    "sg:postcode":"4557",
    "sg:province":"QLD",
    "wof:name":"Hart Gallery",
    "wof:placetype":"venue"
},
  "geometry": {"coordinates":[153.09645080600001,-26.6928806305],"type":"Point"}
}