{
  "type": "Feature",
  "properties": {
    "iso:country":"AU",
    "sg:address":"696 Pittwater Rd",
    "sg:city":"Brookvale",
    "sg:classifiers":[
        {
            "category":"Real Estate",
            "subcategory":"Architect",
            "type":"Services"
        }
    ],
    "sg:phone":"+61 2 9905 1600",
    "sg:postcode":"2100",
    "sg:province":"NSW",
    "wof:name":"Moline Associates Architects",
    "wof:placetype":"venue"
},
  "geometry": {"coordinates":[151.27191162099999,-33.762134552],"type":"Point"}
}