{
  "type": "Feature",
  "properties": {
    "addr:full":"1/ 12 Traders Way Currumbin QLD 4223",
    "addr:housenumber":"/ 12",
    "addr:postcode":"4223",
    "addr:street":"Traders Way",
    "iso:country":"AU",
    "sg:address":"1/ 12 Traders Way",
    "sg:city":"Currumbin",
    "sg:classifiers":[
        {
            "category":"Home & Garden",
            "subcategory":"Hardware",
            "type":"Retail Goods"
        }
    ],
    "sg:phone":"+61 7 5525 7561",
    "sg:postcode":"4223",
    "sg:province":"QLD",
    "sg:tags":[
        "woodworking",
        "machinery"
    ],
    "wof:name":"Gary Pye Woodturning",
    "wof:placetype":"venue"
},
  "geometry": {"coordinates":[153.47052001899999,-28.1423301697],"type":"Point"}
}