{
  "type": "Feature",
  "properties": {
    "iso:country":"AU",
    "sg:address":"Cnr Melvista Ave & Hackett Rd",
    "sg:city":"Nedlands",
    "sg:classifiers":[
        {
            "category":"Education",
            "subcategory":"School",
            "type":"Public Place"
        }
    ],
    "sg:phone":"+61 8 9386 6151",
    "sg:postcode":"6009",
    "sg:province":"WA",
    "sg:tags":[
        "state",
        "except",
        "nsw"
    ],
    "wof:name":"Melvista Pre-School",
    "wof:placetype":"venue"
},
  "geometry": {"coordinates":[115.803146,-31.9792],"type":"Point"}
}