{
  "type": "Feature",
  "properties": {
    "addr:full":"111 Jonson St Byron Bay NSW 2481",
    "addr:housenumber":"111",
    "addr:postcode":"2481",
    "addr:street":"Jonson St",
    "iso:country":"AU",
    "sg:address":"111 Jonson St",
    "sg:city":"Byron Bay",
    "sg:classifiers":[
        {
            "category":"Cafe",
            "type":"Food & Drink"
        }
    ],
    "sg:phone":"+61 2 6680 9783",
    "sg:postcode":"2481",
    "sg:province":"NSW",
    "wof:name":"Espressohead",
    "wof:placetype":"venue"
},
  "geometry": {"coordinates":[153.613037109,-28.6470527649],"type":"Point"}
}