{
  "type": "Feature",
  "properties": {
    "iso:country":"AU",
    "sg:address":"Unit 1/ 78 Roberts Ave",
    "sg:city":"Mortdale",
    "sg:classifiers":[
        {
            "category":"Retail",
            "subcategory":"Auto Repair",
            "type":"Services"
        }
    ],
    "sg:phone":"+61 2 9580 1333",
    "sg:postcode":"2223",
    "sg:province":"NSW",
    "sg:tags":[
        "repairer",
        "motor",
        "engineer"
    ],
    "wof:name":"P.M. Motors",
    "wof:placetype":"venue"
},
  "geometry": {"coordinates":[151.07054138199999,-33.9701423645],"type":"Point"}
}