{
  "type": "Feature",
  "properties": {
    "addr:full":"274 Rawdon Island Rd Sancrox NSW 2446",
    "addr:housenumber":"274",
    "addr:postcode":"2446",
    "addr:street":"Rawdon Island Rd",
    "iso:country":"AU",
    "sg:address":"274 Rawdon Island Rd",
    "sg:city":"Sancrox",
    "sg:classifiers":[
        {
            "category":"Farming",
            "subcategory":"Nursery",
            "type":"Manufacturing & Wholesale Goods"
        }
    ],
    "sg:phone":"+61 2 6585 1935",
    "sg:postcode":"2446",
    "sg:province":"NSW",
    "wof:name":"Vanderley Nursery",
    "wof:placetype":"venue"
},
  "geometry": {"coordinates":[152.782318,-31.43416],"type":"Point"}
}