{
  "type": "Feature",
  "properties": {
    "addr:full":"Factory 2 52 Bennet St Dandenong VIC 3175",
    "addr:housenumber":"52",
    "addr:postcode":"3175",
    "addr:street":"Bennet St",
    "iso:country":"AU",
    "sg:address":"Factory 2 52 Bennet St",
    "sg:city":"Dandenong",
    "sg:classifiers":[
        {
            "category":"Retail",
            "subcategory":"Auto Repair",
            "type":"Services"
        }
    ],
    "sg:phone":"+61 3 9792 9647",
    "sg:postcode":"3175",
    "sg:province":"VIC",
    "sg:tags":[
        "beater",
        "painter",
        "panel"
    ],
    "wof:name":"Rosebank Panels",
    "wof:placetype":"venue"
},
  "geometry": {"coordinates":[145.19903564399999,-37.9886131287],"type":"Point"}
}