{
  "type": "Feature",
  "properties": {
    "addr:full":"65 Aerodrome Rd Maroochydore QLD 4558",
    "addr:housenumber":"65",
    "addr:postcode":"4558",
    "addr:street":"Aerodrome Rd",
    "iso:country":"AU",
    "sg:address":"65 Aerodrome Rd",
    "sg:city":"Maroochydore",
    "sg:classifiers":[
        {
            "category":"Manufacturing",
            "subcategory":"Furniture",
            "type":"Manufacturing & Wholesale Goods"
        }
    ],
    "sg:phone":"+61 7 5451 1500",
    "sg:postcode":"4558",
    "sg:province":"QLD",
    "sg:tags":[
        "builder",
        "designer",
        "custom"
    ],
    "wof:name":"Coastal Classic Furnishings",
    "wof:placetype":"venue"
},
  "geometry": {"coordinates":[153.09861755399999,-26.6594047546],"type":"Point"}
}