{
  "type": "Feature",
  "properties": {
    "addr:full":"Shop 1133-1134 Westfield Shoppingtown Tuggerah Cobbs Rd Tuggerah NSW 2259",
    "addr:housenumber":"1133-1134",
    "addr:postcode":"2259",
    "addr:street":"Westfield Shoppingtown;Cobbs Rd",
    "iso:country":"AU",
    "sg:address":"Shop 1133-1134 Westfield Shoppingtown Tuggerah Cobbs Rd",
    "sg:city":"Tuggerah",
    "sg:classifiers":[
        {
            "category":"Shopping",
            "subcategory":"Clothing, Apparel, & Fashions",
            "type":"Retail Goods"
        }
    ],
    "sg:phone":"+61 2 4353 4205",
    "sg:postcode":"2259",
    "sg:province":"NSW",
    "sg:tags":[
        "lady",
        "wear"
    ],
    "wof:name":"Portmans",
    "wof:placetype":"venue"
},
  "geometry": {"coordinates":[151.417205811,-33.307674408],"type":"Point"}
}