{
  "type": "Feature",
  "properties": {
    "addr:full":"10 Nawie St Horn Island QLD 4875",
    "addr:housenumber":"10",
    "addr:postcode":"4875",
    "addr:street":"Nawie St",
    "iso:country":"AU",
    "sg:address":"10 Nawie St",
    "sg:city":"Horn Island",
    "sg:classifiers":[
        {
            "category":"Airline",
            "type":"Transportation"
        }
    ],
    "sg:phone":"+61 7 4090 3661",
    "sg:postcode":"4875",
    "sg:province":"QLD",
    "sg:tags":[
        "aircraft",
        "rental",
        "charter"
    ],
    "wof:name":"Cape Air Transport",
    "wof:placetype":"venue"
},
  "geometry": {"coordinates":[142.248214722,-10.5965452194],"type":"Point"}
}