{
  "type": "Feature",
  "properties": {
    "addr:full":"Goolwa Shopping Centre Hutchinson St Goolwa SA 5214",
    "addr:postcode":"5214",
    "addr:street":"Hutchinson St",
    "iso:country":"AU",
    "sg:address":"Goolwa Shopping Centre Hutchinson St",
    "sg:city":"Goolwa",
    "sg:classifiers":[
        {
            "category":"Shopping",
            "subcategory":"Clothing, Apparel, & Fashions",
            "type":"Retail Goods"
        }
    ],
    "sg:phone":"+61 8 8555 1910",
    "sg:postcode":"5214",
    "sg:province":"SA",
    "sg:tags":[
        "recycled",
        "clothing"
    ],
    "wof:name":"Goodwill",
    "wof:placetype":"venue"
},
  "geometry": {"coordinates":[138.77786254899999,-35.5047149658],"type":"Point"}
}