{
  "type": "Feature",
  "properties": {
    "iso:country":"AU",
    "sg:address":"Shop 11 Charthouse Shopng Cntr 78 Charthouse Rd",
    "sg:city":"Waikiki",
    "sg:classifiers":[
        {
            "category":"Personal",
            "subcategory":"Beauty Salon",
            "type":"Services"
        }
    ],
    "sg:phone":"+61 8 9528 3935",
    "sg:postcode":"6169",
    "sg:province":"WA",
    "wof:name":"Beauty By The Beach",
    "wof:placetype":"venue"
},
  "geometry": {"coordinates":[115.74569700000001,-32.313335],"type":"Point"}
}