{
  "type": "Feature",
  "properties": {
    "addr:full":"92 Maling Rd Canterbury VIC 3126",
    "addr:housenumber":"92",
    "addr:postcode":"3126",
    "addr:street":"Maling Rd",
    "iso:country":"AU",
    "sg:address":"92 Maling Rd",
    "sg:city":"Canterbury",
    "sg:classifiers":[
        {
            "category":"Food & Beverages",
            "subcategory":"Supermarket",
            "type":"Retail Goods"
        }
    ],
    "sg:phone":"+61 3 9836 7371",
    "sg:postcode":"3126",
    "sg:province":"VIC",
    "sg:tags":[
        "grocery",
        "store"
    ],
    "wof:name":"IGA Friendly Grocers",
    "wof:placetype":"venue"
},
  "geometry": {"coordinates":[145.081741333,-37.824962616],"type":"Point"}
}