{
  "type": "Feature",
  "properties": {
    "iso:country":"AU",
    "sg:address":"107 Lord St",
    "sg:city":"Cabramatta West",
    "sg:classifiers":[
        {
            "category":"Social Services",
            "subcategory":"Child Care",
            "type":"Services"
        }
    ],
    "sg:phone":"+61 2 9823 8546",
    "sg:postcode":"2166",
    "sg:province":"NSW",
    "wof:name":"Lord Street Long Day Child Care Centre",
    "wof:placetype":"venue"
},
  "geometry": {"coordinates":[150.91282653799999,-33.8912315369],"type":"Point"}
}