{
  "type": "Feature",
  "properties": {
    "addr:full":"38a Walters Drv Osborne Park WA 6017",
    "addr:housenumber":"38a",
    "addr:postcode":"6017",
    "addr:street":"Walters Drv",
    "iso:country":"AU",
    "sg:address":"38a Walters Drv",
    "sg:city":"Osborne Park",
    "sg:classifiers":[
        {
            "category":"Real Estate",
            "subcategory":"Surveying",
            "type":"Services"
        }
    ],
    "sg:phone":"+61 8 9244 2488",
    "sg:postcode":"6017",
    "sg:province":"WA",
    "sg:tags":[
        "map",
        "mapping"
    ],
    "wof:name":"Universal Publishers Pty Ltd",
    "wof:placetype":"venue"
},
  "geometry": {"coordinates":[115.810569763,-31.9104385376],"type":"Point"}
}