{
  "type": "Feature",
  "properties": {
    "addr:full":"103 Nelson St Annandale NSW 2038",
    "addr:housenumber":"103",
    "addr:postcode":"2038",
    "addr:street":"Nelson St",
    "iso:country":"AU",
    "sg:address":"103 Nelson St",
    "sg:city":"Annandale",
    "sg:classifiers":[
        {
            "category":"Building & Trades",
            "subcategory":"Construction",
            "type":"Services"
        }
    ],
    "sg:phone":"+61 2 9571 4575",
    "sg:postcode":"2038",
    "sg:province":"NSW",
    "sg:tags":[
        "window",
        "tinting"
    ],
    "wof:name":"Instant Frost",
    "wof:placetype":"venue"
},
  "geometry": {"coordinates":[151.17433166500001,-33.880317688],"type":"Point"}
}