{
  "type": "Feature",
  "properties": {
    "addr:full":"27 Sturt St Darlinghurst NSW 2010",
    "addr:housenumber":"27",
    "addr:postcode":"2010",
    "addr:street":"Sturt St",
    "iso:country":"AU",
    "sg:address":"27 Sturt St",
    "sg:city":"Darlinghurst",
    "sg:classifiers":[
        {
            "category":"Building & Trades",
            "subcategory":"Construction",
            "type":"Services"
        }
    ],
    "sg:phone":"+61 419 997 996",
    "sg:postcode":"2010",
    "sg:province":"NSW",
    "sg:tags":[
        "contractor"
    ],
    "wof:name":"Glenn Davis Building Contractor",
    "wof:placetype":"venue"
},
  "geometry": {"coordinates":[151.21871948200001,-33.8819198608],"type":"Point"}
}