{
  "type": "Feature",
  "properties": {
    "iso:country":"AU",
    "sg:address":"33 Howson Way",
    "sg:city":"Bibra Lake",
    "sg:classifiers":[
        {
            "category":"Education",
            "subcategory":"Special Training",
            "type":"Public Place"
        }
    ],
    "sg:phone":"+61 8 9434 3774",
    "sg:postcode":"6163",
    "sg:province":"WA",
    "sg:tags":[
        "development"
    ],
    "sg:website":"http://www.xlt.com.au",
    "wof:name":"XLT Industrial Training Pty Ltd",
    "wof:placetype":"venue"
},
  "geometry": {"coordinates":[115.795258,-32.107204],"type":"Point"}
}