{
  "type": "Feature",
  "properties": {
    "iso:country":"AU",
    "sg:address":"Station Rd",
    "sg:city":"Branxholm",
    "sg:classifiers":[
        {
            "category":"Building & Trades",
            "subcategory":"Equipment Rental",
            "type":"Services"
        }
    ],
    "sg:phone":"+61 3 6354 6103",
    "sg:postcode":"7261",
    "sg:province":"TAS",
    "sg:tags":[
        "crane",
        "hire"
    ],
    "wof:name":"Dorset Crane Hire",
    "wof:placetype":"venue"
},
  "geometry": {"coordinates":[147.736237,-41.165466],"type":"Point"}
}