{
  "type": "Feature",
  "properties": {
    "addr:full":"70 Erskine St Sydney NSW 2000",
    "addr:housenumber":"70",
    "addr:postcode":"2000",
    "addr:street":"Erskine St",
    "iso:country":"AU",
    "sg:address":"70 Erskine St",
    "sg:city":"Sydney",
    "sg:classifiers":[
        {
            "category":"Personal",
            "subcategory":"Adult",
            "type":"Services"
        }
    ],
    "sg:phone":"+61 2 9279 2885",
    "sg:postcode":"2000",
    "sg:province":"NSW",
    "sg:tags":[
        "entertainment"
    ],
    "wof:name":"City Touch",
    "wof:placetype":"venue"
},
  "geometry": {"coordinates":[151.20448303200001,-33.866607666],"type":"Point"}
}