{
  "type": "Feature",
  "properties": {
    "addr:full":"227 Berserker St Rockhampton QLD 4700",
    "addr:housenumber":"227",
    "addr:postcode":"4700",
    "addr:street":"Berserker St",
    "iso:country":"AU",
    "sg:address":"227 Berserker St",
    "sg:city":"Rockhampton",
    "sg:classifiers":[
        {
            "category":"Professional",
            "subcategory":"Computer Services",
            "type":"Services"
        }
    ],
    "sg:phone":"+61 7 4928 8811",
    "sg:postcode":"4700",
    "sg:province":"QLD",
    "sg:tags":[
        "repairs",
        "upgrade",
        "equipment"
    ],
    "wof:name":"CQ Video & TV Repairs",
    "wof:placetype":"venue"
},
  "geometry": {"coordinates":[150.53021240199999,-23.3602905273],"type":"Point"}
}