{
  "type": "Feature",
  "properties": {
    "addr:full":"Ste112/ 410 Elizabeth St Surry Hills NSW 2010",
    "addr:housenumber":"410",
    "addr:postcode":"2010",
    "addr:street":"Elizabeth St",
    "iso:country":"AU",
    "sg:address":"Ste112/ 410 Elizabeth St",
    "sg:city":"Surry Hills",
    "sg:classifiers":[
        {
            "category":"Personal",
            "subcategory":"Massage",
            "type":"Services"
        }
    ],
    "sg:phone":"+61 410 353 913",
    "sg:postcode":"2010",
    "sg:province":"NSW",
    "sg:tags":[
        "therapy"
    ],
    "wof:name":"Fresh Therapy",
    "wof:placetype":"venue"
},
  "geometry": {"coordinates":[151.20840454099999,-33.8862571716],"type":"Point"}
}