{
  "type": "Feature",
  "properties": {
    "addr:full":"3 Rosebud Pde Rosebud VIC 3939",
    "addr:housenumber":"3",
    "addr:postcode":"3939",
    "addr:street":"Rosebud Pde",
    "iso:country":"AU",
    "sg:address":"3 Rosebud Pde",
    "sg:city":"Rosebud",
    "sg:classifiers":[
        {
            "category":"Retail",
            "subcategory":"Auto Repair",
            "type":"Services"
        }
    ],
    "sg:phone":"+61 3 5981 1305",
    "sg:postcode":"3939",
    "sg:province":"VIC",
    "sg:tags":[
        "repairer",
        "motor",
        "engineer"
    ],
    "wof:name":"True Automotive",
    "wof:placetype":"venue"
},
  "geometry": {"coordinates":[144.90635681099999,-38.3557357788],"type":"Point"}
}