{
  "type": "Feature",
  "properties": {
    "addr:full":"81 Kable Ave Tamworth NSW 2340",
    "addr:housenumber":"81",
    "addr:postcode":"2340",
    "addr:street":"Kable Ave",
    "iso:country":"AU",
    "sg:address":"81 Kable Ave",
    "sg:city":"Tamworth",
    "sg:classifiers":[
        {
            "category":"Health Services",
            "subcategory":"Doctor",
            "type":"Services"
        }
    ],
    "sg:phone":"+61 2 6761 3033",
    "sg:postcode":"2340",
    "sg:province":"NSW",
    "sg:tags":[
        "medical",
        "practitioner"
    ],
    "wof:name":"Osteoporosis Bone Density Testing Centre",
    "wof:placetype":"venue"
},
  "geometry": {"coordinates":[150.93168640100001,-31.0943584442],"type":"Point"}
}