{
  "type": "Feature",
  "properties": {
    "addr:full":"17 Jarrah St Cooroy QLD 4563",
    "addr:housenumber":"17",
    "addr:postcode":"4563",
    "addr:street":"Jarrah St",
    "iso:country":"AU",
    "sg:address":"17 Jarrah St",
    "sg:city":"Cooroy",
    "sg:classifiers":[
        {
            "category":"Wholesale",
            "subcategory":"Painting Supplies",
            "type":"Manufacturing & Wholesale Goods"
        }
    ],
    "sg:phone":"+61 7 5442 5111",
    "sg:postcode":"4563",
    "sg:province":"QLD",
    "sg:tags":[
        "product",
        "cleaning"
    ],
    "wof:name":"Carpet Cleaners Warehouse",
    "wof:placetype":"venue"
},
  "geometry": {"coordinates":[152.903930664,-26.4115219116],"type":"Point"}
}