{
  "type": "Feature",
  "properties": {
    "iso:country":"AU",
    "sg:address":"231 Victoria Rd",
    "sg:city":"Gladesville",
    "sg:classifiers":[
        {
            "category":"Fast Food",
            "type":"Food & Drink"
        }
    ],
    "sg:phone":"+61 2 9817 2397",
    "sg:postcode":"2111",
    "sg:province":"NSW",
    "sg:tags":[
        "away",
        "take"
    ],
    "wof:name":"Mitchell Pineapple Bar",
    "wof:placetype":"venue"
},
  "geometry": {"coordinates":[151.127044678,-33.8316726685],"type":"Point"}
}