{
  "type": "Feature",
  "properties": {
    "addr:full":"34 Sturt St Ballarat VIC 3350",
    "addr:housenumber":"34",
    "addr:postcode":"3350",
    "addr:street":"Sturt St",
    "iso:country":"AU",
    "sg:address":"34 Sturt St",
    "sg:city":"Ballarat",
    "sg:classifiers":[
        {
            "category":"Restaurant",
            "type":"Food & Drink"
        }
    ],
    "sg:phone":"+61 3 5331 6327",
    "sg:postcode":"3350",
    "sg:province":"VIC",
    "wof:name":"Assuntas",
    "wof:placetype":"venue"
},
  "geometry": {"coordinates":[143.858994,-37.561787],"type":"Point"}
}