{
  "type": "Feature",
  "properties": {
    "addr:full":"31 Geneff St Innaloo WA 6018",
    "addr:housenumber":"31",
    "addr:postcode":"6018",
    "addr:street":"Geneff St",
    "iso:country":"AU",
    "sg:address":"31 Geneff St",
    "sg:city":"Innaloo",
    "sg:classifiers":[
        {
            "category":"Professional",
            "subcategory":"Art Services",
            "type":"Services"
        }
    ],
    "sg:phone":"+61 8 9445 8615",
    "sg:postcode":"6018",
    "sg:province":"WA",
    "sg:tags":[
        "decorator",
        "painter"
    ],
    "wof:name":"Shearwood Painting & Decorating",
    "wof:placetype":"venue"
},
  "geometry": {"coordinates":[115.799583435,-31.8926525116],"type":"Point"}
}