{
  "type": "Feature",
  "properties": {
    "iso:country":"AU",
    "sg:address":"25 Hurley Drv",
    "sg:city":"Coffs Harbour",
    "sg:classifiers":[
        {
            "category":"Shopping",
            "subcategory":"Computers & Home Electronics",
            "type":"Retail Goods"
        }
    ],
    "sg:phone":"+61 2 6651 4677",
    "sg:postcode":"2450",
    "sg:province":"NSW",
    "sg:tags":[
        "hardware",
        "equipment"
    ],
    "wof:name":"Gizmos Affordable Technologies",
    "wof:placetype":"venue"
},
  "geometry": {"coordinates":[153.10110499999999,-30.309151],"type":"Point"}
}