{
  "type": "Feature",
  "properties": {
    "addr:full":"Unit 1/ 12 Bonnal Rd Erina NSW 2250",
    "addr:postcode":"2250",
    "addr:street":"12 Bonnal Rd",
    "iso:country":"AU",
    "sg:address":"Unit 1/ 12 Bonnal Rd",
    "sg:city":"Erina",
    "sg:classifiers":[
        {
            "category":"Retail",
            "subcategory":"Auto Repair",
            "type":"Services"
        }
    ],
    "sg:phone":"+61 2 4367 5095",
    "sg:postcode":"2250",
    "sg:province":"NSW",
    "sg:tags":[
        "repairer",
        "motor",
        "engineer"
    ],
    "wof:name":"Woodport Garage",
    "wof:placetype":"venue"
},
  "geometry": {"coordinates":[151.38372802699999,-33.4351959229],"type":"Point"}
}