{
  "type": "Feature",
  "properties": {
    "addr:full":"1/ 3 Green St Brookvale NSW 2100",
    "addr:housenumber":"/ 3",
    "addr:postcode":"2100",
    "addr:street":"Green St",
    "iso:country":"AU",
    "sg:address":"1/ 3 Green St",
    "sg:city":"Brookvale",
    "sg:classifiers":[
        {
            "category":"Professional",
            "type":"Services"
        }
    ],
    "sg:phone":"+61 2 9939 5100",
    "sg:postcode":"2100",
    "sg:province":"NSW",
    "sg:tags":[
        "packaging",
        "filling",
        "assembling"
    ],
    "wof:name":"Handling Matters Pty Ltd",
    "wof:placetype":"venue"
},
  "geometry": {"coordinates":[151.26690673799999,-33.7650604248],"type":"Point"}
}