{
  "type": "Feature",
  "properties": {
    "iso:country":"AU",
    "sg:address":"7 Helena St",
    "sg:city":"Randwick",
    "sg:classifiers":[
        {
            "category":"Retail",
            "subcategory":"Auto Rental",
            "type":"Services"
        }
    ],
    "sg:phone":"+61 425 277 769",
    "sg:postcode":"2031",
    "sg:province":"NSW",
    "sg:tags":[
        "car",
        "wedding"
    ],
    "wof:name":"Cloud 9 Rolls Royce Wedding Cars",
    "wof:placetype":"venue"
},
  "geometry": {"coordinates":[151.24044799800001,-33.924949646],"type":"Point"}
}