{
  "type": "Feature",
  "properties": {
    "addr:full":"110 Point Leander Drv Port Denison WA 6525",
    "addr:housenumber":"110",
    "addr:postcode":"6525",
    "addr:street":"Point Leander Drv",
    "iso:country":"AU",
    "sg:address":"110 Point Leander Drv",
    "sg:city":"Port Denison",
    "sg:classifiers":[
        {
            "category":"Farming",
            "subcategory":"Fish & Marine Products",
            "type":"Manufacturing & Wholesale Goods"
        }
    ],
    "sg:phone":"+61 8 9927 1170",
    "sg:postcode":"6525",
    "sg:province":"WA",
    "sg:tags":[
        "fisherman"
    ],
    "wof:name":"Money H N",
    "wof:placetype":"venue"
},
  "geometry": {"coordinates":[114.93390655499999,-29.2572898865],"type":"Point"}
}