{
  "type": "Feature",
  "properties": {
    "addr:full":"32 Herald Ave Willetton WA 6155",
    "addr:housenumber":"32",
    "addr:postcode":"6155",
    "addr:street":"Herald Ave",
    "iso:country":"AU",
    "sg:address":"32 Herald Ave",
    "sg:city":"Willetton",
    "sg:classifiers":[
        {
            "category":"Personal",
            "subcategory":"Massage",
            "type":"Services"
        }
    ],
    "sg:phone":"+61 8 9354 8648",
    "sg:postcode":"6155",
    "sg:province":"WA",
    "sg:tags":[
        "therapy"
    ],
    "wof:name":"Qigong Massage & Acpntre",
    "wof:placetype":"venue"
},
  "geometry": {"coordinates":[115.888451,-32.041725],"type":"Point"}
}