{
  "type": "Feature",
  "properties": {
    "iso:country":"AU",
    "sg:address":"232 St. Pauls Tce",
    "sg:city":"Spring Hill",
    "sg:classifiers":[
        {
            "category":"Banks & Credit Unions",
            "subcategory":"Investment Brokerage",
            "type":"Services"
        }
    ],
    "sg:phone":"+61 7 3370 0100",
    "sg:postcode":"4000",
    "sg:province":"QLD",
    "sg:tags":[
        "debt",
        "collection"
    ],
    "wof:name":"National Credit Management Limited",
    "wof:placetype":"venue"
},
  "geometry": {"coordinates":[153.02993774399999,-27.4575233459],"type":"Point"}
}