{
  "type": "Feature",
  "properties": {
    "iso:country":"AU",
    "sg:address":"Tiver Rd",
    "sg:city":"Gawler",
    "sg:classifiers":[
        {
            "category":"Home & Garden",
            "subcategory":"Building Materials",
            "type":"Retail Goods"
        }
    ],
    "sg:phone":"+61 8 8522 3888",
    "sg:postcode":"5118",
    "sg:province":"SA",
    "sg:tags":[
        "pre-mixed",
        "concrete"
    ],
    "wof:name":"Direct Mix Concrete",
    "wof:placetype":"venue"
},
  "geometry": {"coordinates":[138.72477699999999,-34.639618],"type":"Point"}
}