{
  "type": "Feature",
  "properties": {
    "iso:country":"AU",
    "sg:address":"710 New South Head Rd",
    "sg:city":"Rose Bay",
    "sg:classifiers":[
        {
            "category":"Professional",
            "subcategory":"Computer Services",
            "type":"Services"
        }
    ],
    "sg:phone":"+61 2 9371 0300",
    "sg:postcode":"2029",
    "sg:province":"NSW",
    "sg:tags":[
        "information"
    ],
    "wof:name":"Information Edge Pty Ltd",
    "wof:placetype":"venue"
},
  "geometry": {"coordinates":[151.26947021500001,-33.8696861267],"type":"Point"}
}