{
  "type": "Feature",
  "properties": {
    "iso:country":"AU",
    "sg:address":"151 south St",
    "sg:city":"Toowoomba",
    "sg:classifiers":[
        {
            "category":"Personal",
            "subcategory":"Tattoo Parlor",
            "type":"Services"
        }
    ],
    "sg:phone":"+61 409 756 679",
    "sg:postcode":"4350",
    "sg:province":"QLD",
    "sg:tags":[
        "resume"
    ],
    "wof:name":"r?sum?s for results",
    "wof:placetype":"venue"
},
  "geometry": {"coordinates":[151.907623,-27.571999],"type":"Point"}
}