{
  "type": "Feature",
  "properties": {
    "addr:full":"Shp16/ 113 Sheridan St Cairns City QLD 4870",
    "addr:housenumber":"113",
    "addr:postcode":"4870",
    "addr:street":"Sheridan St",
    "iso:country":"AU",
    "sg:address":"Shp16/ 113 Sheridan St",
    "sg:city":"Cairns City",
    "sg:classifiers":[
        {
            "category":"Food & Beverages",
            "subcategory":"Bakery",
            "type":"Retail Goods"
        }
    ],
    "sg:phone":"+61 7 4041 0246",
    "sg:postcode":"4870",
    "sg:province":"QLD",
    "sg:tags":[
        "baker"
    ],
    "wof:name":"Civic Bread Bakery",
    "wof:placetype":"venue"
},
  "geometry": {"coordinates":[145.77235412600001,-16.9217224121],"type":"Point"}
}