{
  "type": "Feature",
  "properties": {
    "addr:full":"9 Memory St Toowoomba QLD 4350",
    "addr:housenumber":"9",
    "addr:postcode":"4350",
    "addr:street":"Memory St",
    "iso:country":"AU",
    "sg:address":"9 Memory St",
    "sg:city":"Toowoomba",
    "sg:classifiers":[
        {
            "category":"Education",
            "subcategory":"School",
            "type":"Public Place"
        }
    ],
    "sg:phone":"+61 7 4635 6200",
    "sg:postcode":"4350",
    "sg:province":"QLD",
    "sg:tags":[
        "co-educational"
    ],
    "wof:name":"St Anthonys Primary & Pre School",
    "wof:placetype":"venue"
},
  "geometry": {"coordinates":[151.93490600000001,-27.573088],"type":"Point"}
}