{
  "type": "Feature",
  "properties": {
    "addr:full":"Lvl 1/ 173 Mounts Bay Rd Perth WA 6000",
    "addr:housenumber":"/ 173",
    "addr:postcode":"6000",
    "addr:street":"Mounts Bay Rd",
    "iso:country":"AU",
    "sg:address":"Lvl 1/ 173 Mounts Bay Rd",
    "sg:city":"Perth",
    "sg:classifiers":[
        {
            "category":"Banks & Credit Unions",
            "subcategory":"Investment Brokerage",
            "type":"Services"
        }
    ],
    "sg:phone":"+61 8 9321 9888",
    "sg:postcode":"6000",
    "sg:province":"WA",
    "wof:name":"Allegra Capital Pty Ltd",
    "wof:placetype":"venue"
},
  "geometry": {"coordinates":[115.848220825,-31.9555015564],"type":"Point"}
}