{
  "type": "Feature",
  "properties": {
    "iso:country":"AU",
    "sg:address":"Orchard St",
    "sg:city":"Carlingford",
    "sg:classifiers":[
        {
            "category":"Education",
            "subcategory":"Special Training",
            "type":"Public Place"
        }
    ],
    "sg:phone":"+61 2 9872 5721",
    "sg:postcode":"2118",
    "sg:province":"NSW",
    "sg:tags":[
        "tuition-educational"
    ],
    "wof:name":"Kumon Institute Of Education",
    "wof:placetype":"venue"
},
  "geometry": {"coordinates":[151.062591553,-33.7781829834],"type":"Point"}
}