{
  "type": "Feature",
  "properties": {
    "addr:full":"8 Torres St Kurnell NSW 2231",
    "addr:housenumber":"8",
    "addr:postcode":"2231",
    "addr:street":"Torres St",
    "iso:country":"AU",
    "sg:address":"8 Torres St",
    "sg:city":"Kurnell",
    "sg:classifiers":[
        {
            "category":"Health Services",
            "subcategory":"Doctor",
            "type":"Services"
        }
    ],
    "sg:phone":"+61 2 9668 9561",
    "sg:postcode":"2231",
    "sg:province":"NSW",
    "sg:tags":[
        "medical",
        "practitioner"
    ],
    "wof:name":"Calverley P",
    "wof:placetype":"venue"
},
  "geometry": {"coordinates":[151.20965576200001,-34.0110321045],"type":"Point"}
}