{
  "type": "Feature",
  "properties": {
    "addr:full":"10 Merinda Ave Epping NSW 2121",
    "addr:housenumber":"10",
    "addr:postcode":"2121",
    "addr:street":"Merinda Ave",
    "iso:country":"AU",
    "sg:address":"10 Merinda Ave",
    "sg:city":"Epping",
    "sg:classifiers":[
        {
            "category":"Professional",
            "subcategory":"Management & Consulting",
            "type":"Services"
        }
    ],
    "sg:phone":"+61 2 9617 2363",
    "sg:postcode":"2121",
    "sg:province":"NSW",
    "sg:tags":[
        "consultant"
    ],
    "wof:name":"Nisbet & Associates Pty Ltd",
    "wof:placetype":"venue"
},
  "geometry": {"coordinates":[151.066574097,-33.7624053955],"type":"Point"}
}