{
  "type": "Feature",
  "properties": {
    "iso:country":"AU",
    "sg:address":"14 Claridge Crt",
    "sg:city":"St Agnes",
    "sg:classifiers":[
        {
            "category":"Personal",
            "type":"Services"
        }
    ],
    "sg:phone":"+61 8 8396 3466",
    "sg:postcode":"5097",
    "sg:province":"SA",
    "sg:tags":[
        "gift"
    ],
    "wof:name":"Send-A-Bear",
    "wof:placetype":"venue"
},
  "geometry": {"coordinates":[138.71800231899999,-34.83644104],"type":"Point"}
}