{
  "type": "Feature",
  "properties": {
    "iso:country":"AU",
    "sg:address":"32 Cox Ave",
    "sg:city":"Kingswood",
    "sg:classifiers":[
        {
            "category":"Health Services",
            "subcategory":"Nursing And Care Facility",
            "type":"Services"
        }
    ],
    "sg:phone":"+61 2 4732 3255",
    "sg:postcode":"2747",
    "sg:province":"NSW",
    "sg:tags":[
        "treatment",
        "preservation",
        "timber"
    ],
    "wof:name":"Treated Pine People",
    "wof:placetype":"venue"
},
  "geometry": {"coordinates":[150.71810913100001,-33.7570037842],"type":"Point"}
}