{
  "type": "Feature",
  "properties": {
    "iso:country":"AU",
    "sg:address":"U2/ 97 Kennedy Drv",
    "sg:city":"Tweed Heads",
    "sg:classifiers":[
        {
            "category":"Health Services",
            "subcategory":"Doctor",
            "type":"Services"
        }
    ],
    "sg:phone":"+61 7 5599 1175",
    "sg:postcode":"2485",
    "sg:province":"NSW",
    "sg:tags":[
        "medical",
        "practitioner"
    ],
    "wof:name":"Dr Devsam Joshua",
    "wof:placetype":"venue"
},
  "geometry": {"coordinates":[153.520355225,-28.1877822876],"type":"Point"}
}