{
  "type": "Feature",
  "properties": {
    "iso:country":"AU",
    "sg:address":"66 Springfield Rd",
    "sg:city":"Blackburn North",
    "sg:classifiers":[
        {
            "category":"Health Services",
            "subcategory":"Optometrist",
            "type":"Services"
        }
    ],
    "sg:phone":"+61 3 9878 9095",
    "sg:postcode":"3130",
    "sg:province":"VIC",
    "wof:name":"Strachan Greg & Strachan Sue",
    "wof:placetype":"venue"
},
  "geometry": {"coordinates":[145.147018433,-37.8096885681],"type":"Point"}
}