{
  "type": "Feature",
  "properties": {
    "addr:full":"Belair Ave Glenroy VIC 3046",
    "addr:postcode":"3046",
    "addr:street":"Belair Ave",
    "iso:country":"AU",
    "sg:address":"Belair Ave",
    "sg:city":"Glenroy",
    "sg:classifiers":[
        {
            "category":"Personal",
            "subcategory":"Massage",
            "type":"Services"
        }
    ],
    "sg:phone":"+61 3 9304 4450",
    "sg:postcode":"3046",
    "sg:province":"VIC",
    "sg:tags":[
        "therapy"
    ],
    "wof:name":"Chamberlain Carol",
    "wof:placetype":"venue"
},
  "geometry": {"coordinates":[144.91542053200001,-37.7044944763],"type":"Point"}
}