{
  "type": "Feature",
  "properties": {
    "addr:full":"9 Station St Currumbin QLD 4223",
    "addr:housenumber":"9",
    "addr:postcode":"4223",
    "addr:street":"Station St",
    "iso:country":"AU",
    "sg:address":"9 Station St",
    "sg:city":"Currumbin",
    "sg:classifiers":[
        {
            "category":"Shopping",
            "subcategory":"Crafts & Fabrics",
            "type":"Retail Goods"
        }
    ],
    "sg:phone":"+61 7 5534 4372",
    "sg:postcode":"4223",
    "sg:province":"QLD",
    "sg:tags":[
        "supply"
    ],
    "wof:name":"Scrapbook Shack The Pty Ltd",
    "wof:placetype":"venue"
},
  "geometry": {"coordinates":[153.47262573200001,-28.1389350891],"type":"Point"}
}