{
  "type": "Feature",
  "properties": {
    "addr:full":"18 Brett Drv Carrum Downs VIC 3201",
    "addr:housenumber":"18",
    "addr:postcode":"3201",
    "addr:street":"Brett Drv",
    "iso:country":"AU",
    "sg:address":"18 Brett Drv",
    "sg:city":"Carrum Downs",
    "sg:classifiers":[
        {
            "category":"Shopping",
            "subcategory":"Computers & Home Electronics",
            "type":"Retail Goods"
        }
    ],
    "sg:phone":"+61 1300 556 044",
    "sg:postcode":"3201",
    "sg:province":"VIC",
    "sg:tags":[
        "equipment",
        "supply"
    ],
    "wof:name":"Global Computer Supplies",
    "wof:placetype":"venue"
},
  "geometry": {"coordinates":[145.163467,-38.09623],"type":"Point"}
}