{
  "type": "Feature",
  "properties": {
    "addr:full":"1407 Anzac Ave Kallangur QLD 4503",
    "addr:housenumber":"1407",
    "addr:postcode":"4503",
    "addr:street":"Anzac Ave",
    "iso:country":"AU",
    "sg:address":"1407 Anzac Ave",
    "sg:city":"Kallangur",
    "sg:classifiers":[
        {
            "category":"Food & Beverages",
            "subcategory":"Supermarket",
            "type":"Retail Goods"
        }
    ],
    "sg:phone":"+61 7 3204 5560",
    "sg:postcode":"4503",
    "sg:province":"QLD",
    "sg:tags":[
        "grocery",
        "store"
    ],
    "wof:name":"Four Square Stores (Qld) Ltd",
    "wof:placetype":"venue"
},
  "geometry": {"coordinates":[152.99400329599999,-27.2506141663],"type":"Point"}
}