{
  "type": "Feature",
  "properties": {
    "addr:full":"Shp5/ 22 George St North Strathfield NSW 2137",
    "addr:housenumber":"22",
    "addr:postcode":"2137",
    "addr:street":"George St",
    "iso:country":"AU",
    "sg:address":"Shp5/ 22 George St",
    "sg:city":"North Strathfield",
    "sg:classifiers":[
        {
            "category":"Personal",
            "subcategory":"Beauty Salon",
            "type":"Services"
        }
    ],
    "sg:phone":"+61 2 9746 6002",
    "sg:postcode":"2137",
    "sg:province":"NSW",
    "wof:name":"Complete Indulgence Beauty",
    "wof:placetype":"venue"
},
  "geometry": {"coordinates":[151.08746337900001,-33.861492157],"type":"Point"}
}