{
  "type": "Feature",
  "properties": {
    "addr:full":"2 Hallam St North Lismore NSW 2480",
    "addr:housenumber":"2",
    "addr:postcode":"2480",
    "addr:street":"Hallam St North",
    "iso:country":"AU",
    "sg:address":"2 Hallam St",
    "sg:city":"North Lismore",
    "sg:classifiers":[
        {
            "category":"Utilities",
            "subcategory":"Natural Gas",
            "type":"Services"
        }
    ],
    "sg:phone":"+61 2 6622 6339",
    "sg:postcode":"2480",
    "sg:province":"NSW",
    "sg:tags":[
        "cylinder",
        "testing"
    ],
    "wof:name":"Town & Country Gas",
    "wof:placetype":"venue"
},
  "geometry": {"coordinates":[153.26551818900001,-28.7988777161],"type":"Point"}
}