{
  "type": "Feature",
  "properties": {
    "addr:full":"Lot 153 \"Industrial Estate\" Miles QLD 4415",
    "addr:postcode":"4415",
    "iso:country":"AU",
    "sg:address":"Lot 153 \"Industrial Estate\"",
    "sg:city":"Miles",
    "sg:classifiers":[
        {
            "category":"Building & Trades",
            "subcategory":"Construction",
            "type":"Services"
        }
    ],
    "sg:phone":"+61 7 4627 1283",
    "sg:postcode":"4415",
    "sg:province":"QLD",
    "sg:tags":[
        "earth",
        "excavating",
        "moving",
        "contractor"
    ],
    "wof:name":"Kerwick's Earthworks",
    "wof:placetype":"venue"
},
  "geometry": {"coordinates":[150.186035156,-26.6594009399],"type":"Point"}
}