{
  "type": "Feature",
  "properties": {
    "addr:full":"13 Hidden Valley Rd Bonogin QLD 4213",
    "addr:housenumber":"13",
    "addr:postcode":"4213",
    "addr:street":"Hidden Valley Rd",
    "iso:country":"AU",
    "sg:address":"13 Hidden Valley Rd",
    "sg:city":"Bonogin",
    "sg:classifiers":[
        {
            "category":"Education",
            "subcategory":"Special Training",
            "type":"Public Place"
        }
    ],
    "sg:phone":"+61 1300 764 339",
    "sg:postcode":"4213",
    "sg:province":"QLD",
    "sg:tags":[
        "development"
    ],
    "wof:name":"TGC Recruitment & Training",
    "wof:placetype":"venue"
},
  "geometry": {"coordinates":[153.328414917,-28.1404037476],"type":"Point"}
}