{
  "type": "Feature",
  "properties": {
    "iso:country":"AU",
    "sg:address":"245 Pitt St",
    "sg:city":"Sydney",
    "sg:classifiers":[
        {
            "category":"Shopping",
            "subcategory":"Clothing, Apparel, & Fashions",
            "type":"Retail Goods"
        }
    ],
    "sg:phone":"+61 2 9264 7485",
    "sg:postcode":"2000",
    "sg:province":"NSW",
    "sg:tags":[
        "menswear"
    ],
    "wof:name":"Ron Bennett",
    "wof:placetype":"venue"
},
  "geometry": {"coordinates":[151.20802307100001,-33.87134552],"type":"Point"}
}