{
  "type": "Feature",
  "properties": {
    "addr:full":"1E Louise Ave Ingleburn NSW 2565",
    "addr:postcode":"2565",
    "addr:street":"1E Louise Ave",
    "iso:country":"AU",
    "sg:address":"1E Louise Ave",
    "sg:city":"Ingleburn",
    "sg:classifiers":[
        {
            "category":"Sports & Exercise",
            "subcategory":"Climbing Gym",
            "type":"Entertainment"
        }
    ],
    "sg:phone":"+61 2 9605 7895",
    "sg:postcode":"2565",
    "sg:province":"NSW",
    "sg:tags":[
        "repetition",
        "engineer"
    ],
    "wof:name":"B.A. Engineering",
    "wof:placetype":"venue"
},
  "geometry": {"coordinates":[150.86619567899999,-33.9951400757],"type":"Point"}
}