{
  "type": "Feature",
  "properties": {
    "addr:full":"23 Fox St Holroyd NSW 2142",
    "addr:housenumber":"23",
    "addr:postcode":"2142",
    "addr:street":"Fox St",
    "iso:country":"AU",
    "sg:address":"23 Fox St",
    "sg:city":"Holroyd",
    "sg:classifiers":[
        {
            "category":"Professional",
            "subcategory":"Engineering",
            "type":"Services"
        }
    ],
    "sg:phone":"+61 2 9897 7887",
    "sg:postcode":"2142",
    "sg:province":"NSW",
    "sg:tags":[
        "engineer"
    ],
    "wof:name":"BNE Engineering",
    "wof:placetype":"venue"
},
  "geometry": {"coordinates":[150.99687194800001,-33.829120636],"type":"Point"}
}