{
  "type": "Feature",
  "properties": {
    "addr:full":"Shop 308 Westfield Shopping Town Hurstville NSW 2220",
    "addr:housenumber":"308",
    "addr:postcode":"2220",
    "addr:street":"Westfield",
    "iso:country":"AU",
    "sg:address":"Shop 308",
    "sg:city":"Westfield Shopping Town Hurstville",
    "sg:classifiers":[
        {
            "category":"Shopping",
            "subcategory":"Clothing, Apparel, & Fashions",
            "type":"Retail Goods"
        }
    ],
    "sg:phone":"+61 2 9580 8672",
    "sg:postcode":"2220",
    "sg:province":"NSW",
    "sg:tags":[
        "lady",
        "wear"
    ],
    "wof:name":"Discovery",
    "wof:placetype":"venue"
},
  "geometry": {"coordinates":[151.10104370100001,-33.9671897888],"type":"Point"}
}