{
  "type": "Feature",
  "properties": {
    "addr:full":"Suite 5, Medical Ctr, Sunshine Coast Priv Hospital Buderim Buderim QLD 4556",
    "addr:postcode":"4556",
    "addr:street":"Sunshine",
    "iso:country":"AU",
    "sg:address":"Suite 5, Medical Ctr, Sunshine Coast Priv Hospital",
    "sg:city":"Buderim Buderim",
    "sg:classifiers":[
        {
            "category":"Health Services",
            "subcategory":"Doctor",
            "type":"Services"
        }
    ],
    "sg:phone":"+61 7 5444 8066",
    "sg:postcode":"4556",
    "sg:province":"QLD",
    "sg:tags":[
        "medical",
        "practitioner"
    ],
    "wof:name":"Sunder Shyam Dr",
    "wof:placetype":"venue"
},
  "geometry": {"coordinates":[153.094802856,-26.6795597076],"type":"Point"}
}