{
  "type": "Feature",
  "properties": {
    "addr:full":"6 Drushi Crt Clayton South VIC 3169",
    "addr:housenumber":"6",
    "addr:postcode":"3169",
    "addr:street":"Drushi Crt",
    "iso:country":"AU",
    "sg:address":"6 Drushi Crt",
    "sg:city":"Clayton South",
    "sg:classifiers":[
        {
            "category":"Shopping",
            "subcategory":"Computers & Home Electronics",
            "type":"Retail Goods"
        }
    ],
    "sg:phone":"+61 3 9551 4476",
    "sg:postcode":"3169",
    "sg:province":"VIC",
    "sg:tags":[
        "small",
        "equipment",
        "business"
    ],
    "wof:name":"Castle Security",
    "wof:placetype":"venue"
},
  "geometry": {"coordinates":[145.112747192,-37.9462356567],"type":"Point"}
}