{
  "type": "Feature",
  "properties": {
    "addr:full":"Shop 2, 35 Mends St South Perth WA 6151",
    "addr:housenumber":"shop;35",
    "addr:postcode":"6151",
    "addr:street":"Mends St South",
    "iso:country":"AU",
    "sg:address":"Shop 2, 35 Mends St",
    "sg:city":"South Perth",
    "sg:classifiers":[
        {
            "category":"Cafe",
            "type":"Food & Drink"
        }
    ],
    "sg:phone":"+61 8 9367 7332",
    "sg:postcode":"6151",
    "sg:province":"WA",
    "wof:name":"Mends Street Cafe",
    "wof:placetype":"venue"
},
  "geometry": {"coordinates":[115.852959,-31.971708],"type":"Point"}
}