{
  "type": "Feature",
  "properties": {
    "addr:full":"49 Industrial Park Drv Lilydale VIC 3140",
    "addr:housenumber":"49",
    "addr:postcode":"3140",
    "addr:street":"Industrial Park Drv",
    "iso:country":"AU",
    "sg:address":"49 Industrial Park Drv",
    "sg:city":"Lilydale",
    "sg:classifiers":[
        {
            "category":"Shopping",
            "subcategory":"Crafts & Fabrics",
            "type":"Retail Goods"
        }
    ],
    "sg:phone":"+61 3 9735 8400",
    "sg:postcode":"3140",
    "sg:province":"VIC",
    "sg:tags":[
        "adhesive"
    ],
    "wof:name":"ACM Pty Ltd",
    "wof:placetype":"venue"
},
  "geometry": {"coordinates":[145.351654053,-37.748336792],"type":"Point"}
}