{
  "type": "Feature",
  "properties": {
    "addr:full":"28 Hallstrom Pl Wetherill Park NSW 2164",
    "addr:housenumber":"28",
    "addr:postcode":"2164",
    "addr:street":"Hallstrom Pl",
    "iso:country":"AU",
    "sg:address":"28 Hallstrom Pl",
    "sg:city":"Wetherill Park",
    "sg:classifiers":[
        {
            "category":"Utilities",
            "subcategory":"Refuse",
            "type":"Services"
        }
    ],
    "sg:phone":"+61 2 9756 2636",
    "sg:postcode":"2164",
    "sg:province":"NSW",
    "sg:tags":[
        "remover",
        "rubbish"
    ],
    "wof:name":"W & K Scrap Metal Pty Ltd",
    "wof:placetype":"venue"
},
  "geometry": {"coordinates":[150.88536071799999,-33.8449287415],"type":"Point"}
}