{
  "type": "Feature",
  "properties": {
    "addr:full":"52 Wecker Rd Mansfield QLD 4122",
    "addr:housenumber":"52",
    "addr:postcode":"4122",
    "addr:street":"Wecker Rd",
    "iso:country":"AU",
    "sg:address":"52 Wecker Rd",
    "sg:city":"Mansfield",
    "sg:classifiers":[
        {
            "category":"Manufacturing",
            "subcategory":"Motor Vehicles & Parts",
            "type":"Manufacturing & Wholesale Goods"
        }
    ],
    "sg:phone":"+61 7 3343 9449",
    "sg:postcode":"4122",
    "sg:province":"QLD",
    "sg:tags":[
        "replacement"
    ],
    "wof:name":"F Trucks Australia",
    "wof:placetype":"venue"
},
  "geometry": {"coordinates":[153.095581055,-27.5325737],"type":"Point"}
}