{
  "type": "Feature",
  "properties": {
    "iso:country":"AU",
    "sg:address":"28 Waterview St",
    "sg:city":"Forster",
    "sg:classifiers":[
        {
            "category":"Professional",
            "subcategory":"Research",
            "type":"Services"
        }
    ],
    "sg:phone":"+61 2 6555 3318",
    "sg:postcode":"2428",
    "sg:province":"NSW",
    "sg:tags":[
        "market"
    ],
    "wof:name":"Greg Ellis Market Resarch",
    "wof:placetype":"venue"
},
  "geometry": {"coordinates":[152.52624499999999,-32.191746],"type":"Point"}
}