{
  "type": "Feature",
  "properties": {
    "addr:full":"119 Logan Rd Woolloongabba QLD 4102",
    "addr:housenumber":"119",
    "addr:postcode":"4102",
    "addr:street":"Logan Rd",
    "iso:country":"AU",
    "sg:address":"119 Logan Rd",
    "sg:city":"Woolloongabba",
    "sg:classifiers":[
        {
            "category":"Banks & Credit Unions",
            "subcategory":"Bank",
            "type":"Services"
        }
    ],
    "sg:phone":"+61 7 3456 0104",
    "sg:postcode":"4102",
    "sg:province":"QLD",
    "sg:tags":[
        "broker",
        "mortgage"
    ],
    "wof:name":"Mortgage Choice",
    "wof:placetype":"venue"
},
  "geometry": {"coordinates":[153.039993286,-27.490858078],"type":"Point"}
}