{
  "type": "Feature",
  "properties": {
    "addr:full":"17- 23 Station St Malvern VIC 3144",
    "addr:housenumber":"23",
    "addr:postcode":"3144",
    "addr:street":"Station St",
    "iso:country":"AU",
    "sg:address":"17- 23 Station St",
    "sg:city":"Malvern",
    "sg:classifiers":[
        {
            "category":"Professional",
            "subcategory":"Computer Services",
            "type":"Services"
        }
    ],
    "sg:phone":"+61 3 9576 0077",
    "sg:postcode":"3144",
    "sg:province":"VIC",
    "sg:tags":[
        "package",
        "software"
    ],
    "wof:name":"Australian Payroll & Personnel Systems Pty Ltd",
    "wof:placetype":"venue"
},
  "geometry": {"coordinates":[145.02865600600001,-37.8650360107],"type":"Point"}
}