{
  "type": "Feature",
  "properties": {
    "addr:full":"1st Floor, 610 South Rd Moorabbin VIC 3189",
    "addr:housenumber":"610",
    "addr:postcode":"3189",
    "addr:street":"South Rd",
    "iso:country":"AU",
    "sg:address":"1st Floor, 610 South Rd",
    "sg:city":"Moorabbin",
    "sg:classifiers":[
        {
            "category":"Professional",
            "subcategory":"Accounting & Tax Preparation",
            "type":"Services"
        }
    ],
    "sg:phone":"+61 3 9555 9544",
    "sg:postcode":"3189",
    "sg:province":"VIC",
    "sg:tags":[
        "consultant",
        "taxation"
    ],
    "wof:name":"Act Now Taxation Consultants",
    "wof:placetype":"venue"
},
  "geometry": {"coordinates":[145.06466674800001,-37.9370651245],"type":"Point"}
}