{
  "type": "Feature",
  "properties": {
    "iso:country":"AU",
    "sg:address":"87 Flinders St",
    "sg:city":"Port Kembla",
    "sg:classifiers":[
        {
            "category":"Autos & Motor Vehicles",
            "subcategory":"Fuel & Gas Station",
            "type":"Retail Goods"
        }
    ],
    "sg:phone":"+61 2 4275 2899",
    "sg:postcode":"2505",
    "sg:province":"NSW",
    "wof:name":"Shell Australia Limited",
    "wof:placetype":"venue"
},
  "geometry": {"coordinates":[150.886841,-34.473068],"type":"Point"}
}