{
  "type": "Feature",
  "properties": {
    "iso:country":"AU",
    "sg:address":"22- 24 Bell St",
    "sg:city":"Preston",
    "sg:classifiers":[
        {
            "category":"Home & Garden",
            "subcategory":"Furniture",
            "type":"Retail Goods"
        }
    ],
    "sg:phone":"+61 3 9416 9970",
    "sg:postcode":"3072",
    "sg:province":"VIC",
    "sg:tags":[
        "outdoor"
    ],
    "wof:name":"Aaron's Outdoor Creations",
    "wof:placetype":"venue"
},
  "geometry": {"coordinates":[145.03225707999999,-37.748336792],"type":"Point"}
}