{
  "type": "Feature",
  "properties": {
    "addr:full":"24 Orchard Ave Eltham North VIC 3095",
    "addr:housenumber":"24",
    "addr:postcode":"3095",
    "addr:street":"Orchard Ave",
    "iso:country":"AU",
    "sg:address":"24 Orchard Ave",
    "sg:city":"Eltham North",
    "sg:classifiers":[
        {
            "category":"Travel",
            "subcategory":"Travel Agent",
            "type":"Entertainment"
        }
    ],
    "sg:phone":"+61 3 9439 6917",
    "sg:postcode":"3095",
    "sg:province":"VIC",
    "sg:tags":[
        "consultant"
    ],
    "wof:name":"Canada CMI",
    "wof:placetype":"venue"
},
  "geometry": {"coordinates":[145.143630981,-37.6999816895],"type":"Point"}
}