{
  "type": "Feature",
  "properties": {
    "iso:country":"AU",
    "sg:address":"69 Kent St",
    "sg:city":"Deakin",
    "sg:classifiers":[
        {
            "category":"Retail",
            "subcategory":"Veterinary Services",
            "type":"Services"
        }
    ],
    "sg:phone":"+61 2 6281 5199",
    "sg:postcode":"2600",
    "sg:province":"ACT",
    "sg:tags":[
        "surgeon"
    ],
    "wof:name":"Bradley Bob Dr",
    "wof:placetype":"venue"
},
  "geometry": {"coordinates":[149.09776306099999,-35.3228378296],"type":"Point"}
}