{
  "type": "Feature",
  "properties": {
    "addr:full":"Unit 6/ 6-8 Enterprise St Ashmore QLD 4214",
    "addr:housenumber":"6-8",
    "addr:postcode":"4214",
    "addr:street":"Enterprise St",
    "iso:country":"AU",
    "sg:address":"Unit 6/ 6-8 Enterprise St",
    "sg:city":"Ashmore",
    "sg:classifiers":[
        {
            "category":"Shopping",
            "subcategory":"Beauty & Cosmetics",
            "type":"Retail Goods"
        }
    ],
    "sg:phone":"+61 1300 766 121",
    "sg:postcode":"4214",
    "sg:province":"QLD",
    "sg:tags":[
        "equipment",
        "salon",
        "supply"
    ],
    "wof:name":"Young Nails",
    "wof:placetype":"venue"
},
  "geometry": {"coordinates":[153.375900269,-27.9799861908],"type":"Point"}
}