{
  "type": "Feature",
  "properties": {
    "addr:full":"Honeypot Rd Noarlunga Downs SA 5168",
    "addr:postcode":"5168",
    "addr:street":"Honeypot Rd",
    "iso:country":"AU",
    "sg:address":"Honeypot Rd",
    "sg:city":"Noarlunga Downs",
    "sg:classifiers":[
        {
            "category":"Education",
            "subcategory":"School",
            "type":"Public Place"
        }
    ],
    "sg:phone":"+61 8 8392 9500",
    "sg:postcode":"5168",
    "sg:province":"SA",
    "sg:tags":[
        "co-educational"
    ],
    "wof:name":"Cardijn College",
    "wof:placetype":"venue"
},
  "geometry": {"coordinates":[138.501342773,-35.1473388672],"type":"Point"}
}