{
  "type": "Feature",
  "properties": {
    "addr:full":"1/ 16 Spine St Sumner Park QLD 4074",
    "addr:housenumber":"/ 16",
    "addr:postcode":"4074",
    "addr:street":"Spine St",
    "iso:country":"AU",
    "sg:address":"1/ 16 Spine St",
    "sg:city":"Sumner Park",
    "sg:classifiers":[
        {
            "category":"Retail",
            "subcategory":"Auto Repair",
            "type":"Services"
        }
    ],
    "sg:phone":"+61 7 3715 8755",
    "sg:postcode":"4074",
    "sg:province":"QLD",
    "sg:tags":[
        "electrical"
    ],
    "wof:name":"Sumner Auto Electrics",
    "wof:placetype":"venue"
},
  "geometry": {"coordinates":[152.93707275400001,-27.5654983521],"type":"Point"}
}