{
  "type": "Feature",
  "properties": {
    "iso:country":"AU",
    "sg:address":"86 Blackburn Rd",
    "sg:city":"Doncaster East",
    "sg:classifiers":[
        {
            "category":"Building & Trades",
            "subcategory":"Plumbing",
            "type":"Services"
        }
    ],
    "sg:phone":"+61 418 355 210",
    "sg:postcode":"3109",
    "sg:province":"VIC",
    "sg:tags":[
        "plumber",
        "gasfitters"
    ],
    "wof:name":"Poseidon Plumbing & Gasfitting",
    "wof:placetype":"venue"
},
  "geometry": {"coordinates":[145.16114807100001,-37.7942848206],"type":"Point"}
}