{
  "type": "Feature",
  "properties": {
    "iso:country":"AU",
    "sg:address":"Level 1, 9 Trickett St",
    "sg:city":"Surfers Paradise",
    "sg:classifiers":[
        {
            "category":"Real Estate",
            "subcategory":"Architect",
            "type":"Services"
        }
    ],
    "sg:phone":"+61 7 5539 9788",
    "sg:postcode":"4217",
    "sg:province":"QLD",
    "wof:name":"DBI Architecture",
    "wof:placetype":"venue"
},
  "geometry": {"coordinates":[153.429199219,-28.0038318634],"type":"Point"}
}