{
  "type": "Feature",
  "properties": {
    "addr:full":"43 Reordan Drv Greenwith SA 5125",
    "addr:housenumber":"43",
    "addr:postcode":"5125",
    "addr:street":"Reordan Drv",
    "iso:country":"AU",
    "sg:address":"43 Reordan Drv",
    "sg:city":"Greenwith",
    "sg:classifiers":[
        {
            "category":"Health Services",
            "subcategory":"Health Practitioner",
            "type":"Services"
        }
    ],
    "sg:phone":"+61 8 8289 7766",
    "sg:postcode":"5125",
    "sg:province":"SA",
    "sg:tags":[
        "psychologist"
    ],
    "wof:name":"Access Psychology",
    "wof:placetype":"venue"
},
  "geometry": {"coordinates":[138.70086699999999,-34.773521],"type":"Point"}
}