{
  "type": "Feature",
  "properties": {
    "addr:full":"8b Cumberland Drv Seaford VIC 3198",
    "addr:housenumber":"8b",
    "addr:postcode":"3198",
    "addr:street":"Cumberland Drv",
    "iso:country":"AU",
    "sg:address":"8b Cumberland Drv",
    "sg:city":"Seaford",
    "sg:classifiers":[
        {
            "category":"Building & Trades",
            "subcategory":"Equipment Rental",
            "type":"Services"
        }
    ],
    "sg:phone":"+61 3 9785 2100",
    "sg:postcode":"3198",
    "sg:province":"VIC",
    "sg:tags":[
        "saw"
    ],
    "wof:name":"Peninsula Saw Service",
    "wof:placetype":"venue"
},
  "geometry": {"coordinates":[145.14120483400001,-38.1133117676],"type":"Point"}
}