{
  "type": "Feature",
  "properties": {
    "iso:country":"AU",
    "sg:address":"28 Thomas St",
    "sg:city":"Croydon",
    "sg:classifiers":[
        {
            "category":"Retail",
            "subcategory":"Repair Shop",
            "type":"Services"
        }
    ],
    "sg:phone":"+61 417 822 972",
    "sg:postcode":"5008",
    "sg:province":"SA",
    "sg:tags":[
        "maintenance",
        "pool",
        "swimming"
    ],
    "wof:name":"Model Brick Paving",
    "wof:placetype":"venue"
},
  "geometry": {"coordinates":[138.565765,-34.894611],"type":"Point"}
}