{
  "type": "Feature",
  "properties": {
    "addr:full":"Shop 2/ 50 Main St Normanville SA 5204",
    "addr:housenumber":"shop 2 / 50",
    "addr:postcode":"5204",
    "addr:street":"Main St",
    "iso:country":"AU",
    "sg:address":"Shop 2/ 50 Main St",
    "sg:city":"Normanville",
    "sg:classifiers":[
        {
            "category":"Personal",
            "subcategory":"Beauty Salon",
            "type":"Services"
        }
    ],
    "sg:phone":"+61 8 8558 3388",
    "sg:postcode":"5204",
    "sg:province":"SA",
    "sg:tags":[
        "hairdresser"
    ],
    "wof:name":"Tonya's Hair Design",
    "wof:placetype":"venue"
},
  "geometry": {"coordinates":[138.317626953,-35.4467086792],"type":"Point"}
}