{
  "type": "Feature",
  "properties": {
    "iso:country":"AU",
    "sg:address":"1 Kings Cross Rd",
    "sg:city":"Kings Cross",
    "sg:classifiers":[
        {
            "category":"Professional",
            "subcategory":"Research",
            "type":"Services"
        }
    ],
    "sg:phone":"+61 2 9955 6559",
    "sg:postcode":"2011",
    "sg:province":"NSW",
    "sg:tags":[
        "market"
    ],
    "wof:name":"Tebbutt Research",
    "wof:placetype":"venue"
},
  "geometry": {"coordinates":[151.22267150900001,-33.8755760193],"type":"Point"}
}