{
  "type": "Feature",
  "properties": {
    "addr:full":"1 Miles St Mt Isa QLD 4825",
    "addr:housenumber":"1",
    "addr:postcode":"4825",
    "addr:street":"Miles St",
    "iso:country":"AU",
    "sg:address":"1 Miles St",
    "sg:city":"Mt Isa",
    "sg:classifiers":[
        {
            "category":"Real Estate",
            "subcategory":"Real Estate Agent",
            "type":"Services"
        }
    ],
    "sg:phone":"+61 7 4743 9499",
    "sg:postcode":"4825",
    "sg:province":"QLD",
    "wof:name":"Ray White Real Estate Mount Isa",
    "wof:placetype":"venue"
},
  "geometry": {"coordinates":[139.49113500000001,-20.7278],"type":"Point"}
}