{
  "type": "Feature",
  "properties": {
    "addr:full":"Unit 11 41-49 Norcal Rd Nunawading VIC 3131",
    "addr:housenumber":"41-49",
    "addr:postcode":"3131",
    "addr:street":"Norcal Rd",
    "iso:country":"AU",
    "sg:address":"Unit 11 41-49 Norcal Rd",
    "sg:city":"Nunawading",
    "sg:classifiers":[
        {
            "category":"Shopping",
            "subcategory":"Discount & Variety Stores",
            "type":"Retail Goods"
        }
    ],
    "sg:phone":"+61 3 9874 7222",
    "sg:postcode":"3131",
    "sg:province":"VIC",
    "sg:tags":[
        "recording",
        "equipment",
        "supply"
    ],
    "wof:name":"Studio Connections Australia Pty Ltd",
    "wof:placetype":"venue"
},
  "geometry": {"coordinates":[145.18138122600001,-37.8227958679],"type":"Point"}
}