{
  "type": "Feature",
  "properties": {
    "addr:full":"8 Hutton St Kyneton VIC 3444",
    "addr:housenumber":"8",
    "addr:postcode":"3444",
    "addr:street":"Hutton St",
    "iso:country":"AU",
    "sg:address":"8 Hutton St",
    "sg:city":"Kyneton",
    "sg:classifiers":[
        {
            "category":"Banks & Credit Unions",
            "subcategory":"Financial Services",
            "type":"Services"
        }
    ],
    "sg:phone":"+61 3 5422 2622",
    "sg:postcode":"3444",
    "sg:province":"VIC",
    "sg:tags":[
        "planning"
    ],
    "wof:name":"Adrian Plowman & Associates Pty Ltd",
    "wof:placetype":"venue"
},
  "geometry": {"coordinates":[144.45158386200001,-37.2464981079],"type":"Point"}
}