{
  "type": "Feature",
  "properties": {
    "addr:full":"Shop 1/220 The Entrance Rd Erina Mall Erina NSW 2250",
    "addr:housenumber":"shop 1 / 220",
    "addr:postcode":"2250",
    "addr:street":"The Entrance Rd;Mall",
    "iso:country":"AU",
    "sg:address":"Shop 1/220 The Entrance Rd",
    "sg:city":"Erina Mall Erina",
    "sg:classifiers":[
        {
            "category":"Shopping",
            "subcategory":"Music",
            "type":"Retail Goods"
        }
    ],
    "sg:phone":"+61 2 4365 5231",
    "sg:postcode":"2250",
    "sg:province":"NSW",
    "sg:tags":[
        "instrument",
        "musical"
    ],
    "sg:website":"http://www.makinmusic.com.au",
    "wof:name":"Makin Music",
    "wof:placetype":"venue"
},
  "geometry": {"coordinates":[151.390899658,-33.4332122803],"type":"Point"}
}