{
  "type": "Feature",
  "properties": {
    "iso:country":"AU",
    "sg:address":"240 Sydney Rd",
    "sg:city":"Coburg",
    "sg:classifiers":[
        {
            "category":"Home & Garden",
            "subcategory":"Hardware",
            "type":"Retail Goods"
        }
    ],
    "sg:phone":"+61 3 9383 5144",
    "sg:postcode":"3058",
    "sg:province":"VIC",
    "sg:tags":[
        "tarpaulin"
    ],
    "wof:name":"Grangers Camping World",
    "wof:placetype":"venue"
},
  "geometry": {"coordinates":[144.96543884299999,-37.7488174438],"type":"Point"}
}