{
  "type": "Feature",
  "properties": {
    "iso:country":"AU",
    "sg:address":"4 Sotherby Ave",
    "sg:city":"Terrigal",
    "sg:classifiers":[
        {
            "category":"Organizations",
            "subcategory":"Professional Association",
            "type":"Services"
        }
    ],
    "sg:phone":"+61 2 4365 0386",
    "sg:postcode":"2260",
    "sg:province":"NSW",
    "sg:tags":[
        "web",
        "internet"
    ],
    "wof:name":"ramJammas Interactive",
    "wof:placetype":"venue"
},
  "geometry": {"coordinates":[151.408997,-33.442863],"type":"Point"}
}