{
  "type": "Feature",
  "properties": {
    "addr:full":"2 Chetwynd Rd Erina NSW 2250",
    "addr:housenumber":"2",
    "addr:postcode":"2250",
    "addr:street":"Chetwynd Rd",
    "iso:country":"AU",
    "sg:address":"2 Chetwynd Rd",
    "sg:city":"Erina",
    "sg:classifiers":[
        {
            "category":"Health Services",
            "subcategory":"Doctor",
            "type":"Services"
        }
    ],
    "sg:phone":"+61 2 4365 2477",
    "sg:postcode":"2250",
    "sg:province":"NSW",
    "sg:tags":[
        "podiatrist"
    ],
    "wof:name":"Brewin, G.M",
    "wof:placetype":"venue"
},
  "geometry": {"coordinates":[151.39578247099999,-33.434463501],"type":"Point"}
}