{
  "type": "Feature",
  "properties": {
    "iso:country":"AU",
    "sg:address":"Dubbo City Centre Macquarie St",
    "sg:city":"Dubbo",
    "sg:classifiers":[
        {
            "category":"Personal",
            "subcategory":"Beauty Salon",
            "type":"Services"
        }
    ],
    "sg:phone":"+61 2 6882 4853",
    "sg:postcode":"2830",
    "sg:province":"NSW",
    "wof:name":"Body Boutique",
    "wof:placetype":"venue"
},
  "geometry": {"coordinates":[148.60118102999999,-32.2478790283],"type":"Point"}
}