{
  "type": "Feature",
  "properties": {
    "iso:country":"AU",
    "sg:address":"115 Emu Bay Rd",
    "sg:city":"Deloraine",
    "sg:classifiers":[
        {
            "category":"Shopping",
            "subcategory":"Party Supplies",
            "type":"Retail Goods"
        }
    ],
    "sg:phone":"+61 3 6362 3289",
    "sg:postcode":"7304",
    "sg:province":"TAS",
    "sg:tags":[
        "selling",
        "plan"
    ],
    "wof:name":"Lindum Country Crafts",
    "wof:placetype":"venue"
},
  "geometry": {"coordinates":[146.646103,-41.521893],"type":"Point"}
}