{
  "type": "Feature",
  "properties": {
    "addr:full":"637 A Glen Huntly Rd Caulfield VIC 3162",
    "addr:housenumber":"637 a",
    "addr:postcode":"3162",
    "addr:street":"Glen Huntly Rd",
    "iso:country":"AU",
    "sg:address":"637 A Glen Huntly Rd",
    "sg:city":"Caulfield",
    "sg:classifiers":[
        {
            "category":"Health Services",
            "subcategory":"Health Practitioner",
            "type":"Services"
        }
    ],
    "sg:phone":"+61 3 9532 9117",
    "sg:postcode":"3162",
    "sg:province":"VIC",
    "sg:tags":[
        "homoeopath"
    ],
    "wof:name":"The Homoeopathic Dispensary",
    "wof:placetype":"venue"
},
  "geometry": {"coordinates":[145.02137756400001,-37.8868026733],"type":"Point"}
}