{
  "type": "Feature",
  "properties": {
    "addr:full":"14 Spa Ave Hepburn Springs VIC 3461",
    "addr:housenumber":"14",
    "addr:postcode":"3461",
    "addr:street":"Spa Ave Hepburn Springs",
    "iso:country":"AU",
    "sg:address":"14 Spa Ave",
    "sg:city":"Hepburn Springs",
    "sg:classifiers":[
        {
            "category":"Building & Trades",
            "subcategory":"Construction",
            "type":"Services"
        }
    ],
    "sg:phone":"+61 3 5348 2595",
    "sg:postcode":"3461",
    "sg:province":"VIC",
    "sg:tags":[
        "concrete",
        "contractor"
    ],
    "wof:name":"Torrance G W",
    "wof:placetype":"venue"
},
  "geometry": {"coordinates":[144.13592529300001,-37.3086509705],"type":"Point"}
}