{
  "type": "Feature",
  "properties": {
    "addr:full":"Unit 5/ 280 New Line Rd Dural NSW 2158",
    "addr:housenumber":"/ 280",
    "addr:postcode":"2158",
    "addr:street":"New Line Rd",
    "iso:country":"AU",
    "sg:address":"Unit 5/ 280 New Line Rd",
    "sg:city":"Dural",
    "sg:classifiers":[
        {
            "category":"Professional",
            "subcategory":"Detective & Security Services",
            "type":"Services"
        }
    ],
    "sg:phone":"+61 1300 761 686",
    "sg:postcode":"2158",
    "sg:province":"NSW",
    "sg:tags":[
        "consultant",
        "system"
    ],
    "wof:name":"Class Security Services Pty Ltd",
    "wof:placetype":"venue"
},
  "geometry": {"coordinates":[151.03053283700001,-33.6961593628],"type":"Point"}
}