{
  "type": "Feature",
  "properties": {
    "addr:full":"4 Volunteer Pl Ocean Reef WA 6027",
    "addr:housenumber":"4",
    "addr:postcode":"6027",
    "addr:street":"Volunteer Pl",
    "iso:country":"AU",
    "sg:address":"4 Volunteer Pl",
    "sg:city":"Ocean Reef",
    "sg:classifiers":[
        {
            "category":"Building & Trades",
            "subcategory":"Construction",
            "type":"Services"
        }
    ],
    "sg:phone":"+61 1300 652 075",
    "sg:postcode":"6027",
    "sg:province":"WA",
    "sg:tags":[
        "scaffolding"
    ],
    "wof:name":"Scaf-West Pty Ltd",
    "wof:placetype":"venue"
},
  "geometry": {"coordinates":[115.731140137,-31.7532482147],"type":"Point"}
}