{
  "type": "Feature",
  "properties": {
    "iso:country":"AU",
    "sg:address":"Woolshed Creek Rd",
    "sg:city":"Hatton Vale",
    "sg:classifiers":[
        {
            "category":"Home & Garden",
            "subcategory":"Hardware",
            "type":"Retail Goods"
        }
    ],
    "sg:phone":"+61 417 006 057",
    "sg:postcode":"4341",
    "sg:province":"QLD",
    "sg:tags":[
        "tarpaulin"
    ],
    "wof:name":"Country Road Canvas",
    "wof:placetype":"venue"
},
  "geometry": {"coordinates":[152.464355469,-27.5750312805],"type":"Point"}
}