{
  "type": "Feature",
  "properties": {
    "iso:country":"AU",
    "sg:address":"148 Barker St",
    "sg:city":"Randwick",
    "sg:classifiers":[
        {
            "category":"Retail",
            "subcategory":"Veterinary Services",
            "type":"Services"
        }
    ],
    "sg:phone":"+61 425 312 001",
    "sg:postcode":"2031",
    "sg:province":"NSW",
    "sg:tags":[
        "surgeon"
    ],
    "wof:name":"City & Easy Suburbs Mobile Vet",
    "wof:placetype":"venue"
},
  "geometry": {"coordinates":[151.236602783,-33.9209518433],"type":"Point"}
}