{
  "type": "Feature",
  "properties": {
    "addr:full":"33b William St Raymond Terrace NSW 2324",
    "addr:housenumber":"33b",
    "addr:postcode":"2324",
    "addr:street":"William St",
    "iso:country":"AU",
    "sg:address":"33b William St",
    "sg:city":"Raymond Terrace",
    "sg:classifiers":[
        {
            "category":"Shopping",
            "subcategory":"Mobile Phones",
            "type":"Retail Goods"
        }
    ],
    "sg:phone":"+61 2 4987 7730",
    "sg:postcode":"2324",
    "sg:province":"NSW",
    "sg:tags":[
        "telephone",
        "accessory"
    ],
    "wof:name":"Lets Communicate",
    "wof:placetype":"venue"
},
  "geometry": {"coordinates":[151.74322509800001,-32.7617378235],"type":"Point"}
}