{
  "type": "Feature",
  "properties": {
    "iso:country":"AU",
    "sg:address":"PO Box 166",
    "sg:city":"Bankstown",
    "sg:classifiers":[
        {
            "category":"Health Services",
            "subcategory":"Health Practitioner",
            "type":"Services"
        }
    ],
    "sg:phone":"+61 2 9707 3303",
    "sg:postcode":"2200",
    "sg:province":"NSW",
    "sg:tags":[
        "psychologist"
    ],
    "wof:name":"Dunn Sandra",
    "wof:placetype":"venue"
},
  "geometry": {"coordinates":[151.034164,-33.914791],"type":"Point"}
}