{
  "type": "Feature",
  "properties": {
    "iso:country":"AU",
    "sg:address":"17 Urunga Pde",
    "sg:city":"Miranda",
    "sg:classifiers":[
        {
            "category":"Health Services",
            "subcategory":"Doctor",
            "type":"Services"
        }
    ],
    "sg:phone":"+61 2 9525 7158",
    "sg:postcode":"2228",
    "sg:province":"NSW",
    "sg:tags":[
        "medical",
        "practitioner"
    ],
    "wof:name":"Ghougassian Dr D",
    "wof:placetype":"venue"
},
  "geometry": {"coordinates":[151.10569763199999,-34.035987854],"type":"Point"}
}