{
  "type": "Feature",
  "properties": {
    "addr:full":"Wehl St North Mt Gambier SA 5290",
    "addr:postcode":"5290",
    "addr:street":"Wehl St North Mt",
    "iso:country":"AU",
    "sg:address":"Wehl St North",
    "sg:city":"Mt Gambier",
    "sg:classifiers":[
        {
            "category":"Health Services",
            "subcategory":"Medical Lab",
            "type":"Services"
        }
    ],
    "sg:phone":"+61 8 8721 1666",
    "sg:postcode":"5290",
    "sg:province":"SA",
    "sg:tags":[
        "laboratory",
        "pathology"
    ],
    "wof:name":"Institute of Medical & Veterinary Science",
    "wof:placetype":"venue"
},
  "geometry": {"coordinates":[140.77543600000001,-37.824486],"type":"Point"}
}