{
  "type": "Feature",
  "properties": {
    "addr:full":"Cnr Sandy Bay Rd & St Georges Terrace Sandy Bay TAS 7005",
    "addr:postcode":"7005",
    "addr:street":"Cnr Sandy Bay Rd & St Georges Terrace",
    "iso:country":"AU",
    "sg:address":"Cnr Sandy Bay Rd & St",
    "sg:city":"Georges Terrace Sandy Bay",
    "sg:classifiers":[
        {
            "category":"Travel",
            "subcategory":"Hotels & Motels",
            "type":"Entertainment"
        }
    ],
    "sg:phone":"+61 3 6224 1044",
    "sg:postcode":"7005",
    "sg:province":"TAS",
    "sg:tags":[
        "pub"
    ],
    "wof:name":"St Ives",
    "wof:placetype":"venue"
},
  "geometry": {"coordinates":[147.332794189,-42.9012336731],"type":"Point"}
}