{
  "type": "Feature",
  "properties": {
    "iso:country":"AU",
    "sg:address":"29 Strong Ave",
    "sg:city":"Thomastown",
    "sg:classifiers":[
        {
            "category":"Sports & Exercise",
            "subcategory":"Sports Center",
            "type":"Entertainment"
        }
    ],
    "sg:phone":"+61 3 9460 1377",
    "sg:postcode":"3074",
    "sg:province":"VIC",
    "sg:tags":[
        "ground"
    ],
    "wof:name":"Action Indoor Sports Stadiums",
    "wof:placetype":"venue"
},
  "geometry": {"coordinates":[145.004348755,-37.6887016296],"type":"Point"}
}