{
  "type": "Feature",
  "properties": {
    "iso:country":"AU",
    "sg:address":"Unit 4, 23 Essington Street",
    "sg:city":"Mitchell",
    "sg:classifiers":[
        {
            "category":"Professional",
            "subcategory":"Computer Services",
            "type":"Services"
        }
    ],
    "sg:phone":"+61 2 6241 9910",
    "sg:postcode":"2911",
    "sg:province":"ACT",
    "sg:tags":[
        "equipment",
        "networking",
        "installation"
    ],
    "wof:name":"Chloride Power Protection",
    "wof:placetype":"venue"
},
  "geometry": {"coordinates":[149.141387939,-35.2126235962],"type":"Point"}
}