{
  "type": "Feature",
  "properties": {
    "addr:full":"45 Park Rd Carlton NSW 2218",
    "addr:housenumber":"45",
    "addr:postcode":"2218",
    "addr:street":"Park Rd",
    "iso:country":"AU",
    "sg:address":"45 Park Rd",
    "sg:city":"Carlton",
    "sg:classifiers":[
        {
            "category":"Retail",
            "subcategory":"Repair Shop",
            "type":"Services"
        }
    ],
    "sg:phone":"+61 2 9547 3232",
    "sg:postcode":"2218",
    "sg:province":"NSW",
    "sg:tags":[
        "upholsterer"
    ],
    "wof:name":"B&H Upholstery",
    "wof:placetype":"venue"
},
  "geometry": {"coordinates":[151.12179599999999,-33.977955],"type":"Point"}
}