{
  "type": "Feature",
  "properties": {
    "iso:country":"AU",
    "sg:address":"Moffats Rd",
    "sg:city":"Swan Bay",
    "sg:classifiers":[
        {
            "category":"Communications",
            "subcategory":"News Services",
            "type":"Services"
        }
    ],
    "sg:phone":"+61 2 4997 5433",
    "sg:postcode":"2324",
    "sg:province":"NSW",
    "sg:tags":[
        "information",
        "tourist",
        "attractions"
    ],
    "wof:name":"Moffats Oyster Barn Restaurant",
    "wof:placetype":"venue"
},
  "geometry": {"coordinates":[151.94322204599999,-32.7076034546],"type":"Point"}
}