{
  "type": "Feature",
  "properties": {
    "iso:country":"AU",
    "sg:address":"Merilba St",
    "sg:city":"Tottenham",
    "sg:classifiers":[
        {
            "category":"Education",
            "subcategory":"Kindergarten",
            "type":"Public Place"
        }
    ],
    "sg:phone":"+61 2 6892 4230",
    "sg:postcode":"2873",
    "sg:province":"NSW",
    "sg:tags":[
        "pre-schools"
    ],
    "wof:name":"Tottenham Pre-School",
    "wof:placetype":"venue"
},
  "geometry": {"coordinates":[147.349777,-32.244587],"type":"Point"}
}