{
  "type": "Feature",
  "properties": {
    "iso:country":"AU",
    "sg:address":"Unit 7/ 27 Warraba Rd",
    "sg:city":"Narrabeen",
    "sg:classifiers":[
        {
            "category":"Parking",
            "subcategory":"Lot",
            "type":"Transportation"
        }
    ],
    "sg:phone":"+61 2 9970 5905",
    "sg:postcode":"2101",
    "sg:province":"NSW",
    "sg:tags":[
        "finishing",
        "flock",
        "suede"
    ],
    "wof:name":"Ace Flockcraft Pty Ltd",
    "wof:placetype":"venue"
},
  "geometry": {"coordinates":[151.293915,-33.7006],"type":"Point"}
}