{
  "type": "Feature",
  "properties": {
    "addr:full":"78 William St Paddington NSW 2021",
    "addr:housenumber":"78",
    "addr:postcode":"2021",
    "addr:street":"William St",
    "iso:country":"AU",
    "sg:address":"78 William St",
    "sg:city":"Paddington",
    "sg:classifiers":[
        {
            "category":"Shopping",
            "subcategory":"Jewelry",
            "type":"Retail Goods"
        }
    ],
    "sg:phone":"+61 2 8021 9612",
    "sg:postcode":"2021",
    "sg:province":"NSW",
    "sg:tags":[
        "jeweller"
    ],
    "wof:name":"Grebe Berenice",
    "wof:placetype":"venue"
},
  "geometry": {"coordinates":[151.23020935100001,-33.8845863342],"type":"Point"}
}