{
  "type": "Feature",
  "properties": {
    "addr:full":"River Glen Marina Jervois Rd Murray Bridge SA 5253",
    "addr:postcode":"5253",
    "addr:street":"Jervois Rd",
    "iso:country":"AU",
    "sg:address":"River Glen Marina Jervois Rd",
    "sg:city":"Murray Bridge",
    "sg:classifiers":[
        {
            "category":"Real Estate",
            "subcategory":"Real Estate Services",
            "type":"Services"
        }
    ],
    "sg:phone":"+61 8 8333 0454",
    "sg:postcode":"5253",
    "sg:province":"SA",
    "sg:tags":[
        "house",
        "hire",
        "boat"
    ],
    "wof:name":"Rivabella Houseboat",
    "wof:placetype":"venue"
},
  "geometry": {"coordinates":[139.29299926799999,-35.1571884155],"type":"Point"}
}