{
  "type": "Feature",
  "properties": {
    "iso:country":"AU",
    "sg:address":"8/ 107 Walker St",
    "sg:city":"Casino",
    "sg:classifiers":[
        {
            "category":"Professional",
            "subcategory":"Accounting & Tax Preparation",
            "type":"Services"
        }
    ],
    "sg:phone":"+61 2 6662 8677",
    "sg:postcode":"2470",
    "sg:province":"NSW",
    "sg:tags":[
        "accountant",
        "auditor"
    ],
    "wof:name":"Helen Ramsey Accounting",
    "wof:placetype":"venue"
},
  "geometry": {"coordinates":[153.04856872600001,-28.8627948761],"type":"Point"}
}