{
  "type": "Feature",
  "properties": {
    "addr:full":"152 Bourke St Melbourne VIC 3000",
    "addr:housenumber":"152",
    "addr:postcode":"3000",
    "addr:street":"Bourke St",
    "iso:country":"AU",
    "sg:address":"152 Bourke St",
    "sg:city":"Melbourne",
    "sg:classifiers":[
        {
            "category":"Shopping",
            "subcategory":"Music",
            "type":"Retail Goods"
        }
    ],
    "sg:phone":"+61 3 9654 8444",
    "sg:postcode":"3000",
    "sg:province":"VIC",
    "sg:tags":[
        "instrument",
        "musical"
    ],
    "wof:name":"Allans Melbourne",
    "wof:placetype":"venue"
},
  "geometry": {"coordinates":[144.968658447,-37.8124961853],"type":"Point"}
}