{
  "type": "Feature",
  "properties": {
    "iso:country":"AU",
    "sg:address":"39 Dunn Rd",
    "sg:city":"Rocklea",
    "sg:classifiers":[
        {
            "category":"Retail",
            "subcategory":"Auto Repair",
            "type":"Services"
        }
    ],
    "sg:phone":"+61 7 3255 5757",
    "sg:postcode":"4106",
    "sg:province":"QLD",
    "sg:tags":[
        "electrical"
    ],
    "wof:name":"Lawty Auto Electrics & Air",
    "wof:placetype":"venue"
},
  "geometry": {"coordinates":[152.99513244600001,-27.5554924011],"type":"Point"}
}