{
  "type": "Feature",
  "properties": {
    "addr:full":"Graham Rd Tongala VIC 3621",
    "addr:postcode":"3621",
    "addr:street":"Graham Rd",
    "iso:country":"AU",
    "sg:address":"Graham Rd",
    "sg:city":"Tongala",
    "sg:classifiers":[
        {
            "category":"Farming",
            "subcategory":"Dairy Farm",
            "type":"Manufacturing & Wholesale Goods"
        }
    ],
    "sg:phone":"+61 3 5859 0435",
    "sg:postcode":"3621",
    "sg:province":"VIC",
    "wof:name":"Mangan D J & A M",
    "wof:placetype":"venue"
},
  "geometry": {"coordinates":[144.958450317,-36.2988166809],"type":"Point"}
}