{
  "type": "Feature",
  "properties": {
    "iso:country":"AU",
    "sg:address":"8/ 207 Bank St",
    "sg:city":"East Victoria Park",
    "sg:classifiers":[
        {
            "category":"Banks & Credit Unions",
            "subcategory":"Bank",
            "type":"Services"
        }
    ],
    "sg:phone":"+61 8 9362 5008",
    "sg:postcode":"6101",
    "sg:province":"WA",
    "sg:tags":[
        "sealing",
        "compound"
    ],
    "wof:name":"Steinwerk Solutions",
    "wof:placetype":"venue"
},
  "geometry": {"coordinates":[115.917762756,-31.9910964966],"type":"Point"}
}