{
  "type": "Feature",
  "properties": {
    "addr:full":"1581 Monkey Gully Rd Mansfield VIC 3724",
    "addr:housenumber":"1581",
    "addr:postcode":"3724",
    "addr:street":"Monkey Gully Rd",
    "iso:country":"AU",
    "sg:address":"1581 Monkey Gully Rd",
    "sg:city":"Mansfield",
    "sg:classifiers":[
        {
            "category":"Industrial Area",
            "type":"Public Place"
        }
    ],
    "sg:phone":"+61 1300 650 264",
    "sg:postcode":"3724",
    "sg:province":"VIC",
    "sg:tags":[
        "rural",
        "shed"
    ],
    "wof:name":"P.I.G Shed Erections",
    "wof:placetype":"venue"
},
  "geometry": {"coordinates":[146.08876037600001,-37.0791091919],"type":"Point"}
}