{
  "type": "Feature",
  "properties": {
    "iso:country":"AU",
    "sg:address":"PO Box 144",
    "sg:city":"Whittlesea",
    "sg:classifiers":[
        {
            "category":"Shopping",
            "subcategory":"Event Tickets",
            "type":"Retail Goods"
        }
    ],
    "sg:phone":"+61 3 9696 0310",
    "sg:postcode":"3757",
    "sg:province":"VIC",
    "sg:tags":[
        "machine",
        "issuing"
    ],
    "wof:name":"Video Ticket Machines Australia Pty Ltd",
    "wof:placetype":"venue"
},
  "geometry": {"coordinates":[145.11811800000001,-37.511532],"type":"Point"}
}