{
  "type": "Feature",
  "properties": {
    "iso:country":"AU",
    "sg:address":"32 Robert St",
    "sg:city":"Rozelle",
    "sg:classifiers":[
        {
            "category":"Cafe",
            "type":"Food & Drink"
        }
    ],
    "sg:phone":"+61 2 9555 5222",
    "sg:postcode":"2039",
    "sg:province":"NSW",
    "wof:name":"Overdrive Cafe",
    "wof:placetype":"venue"
},
  "geometry": {"coordinates":[151.17665100100001,-33.8658027649],"type":"Point"}
}