{
  "type": "Feature",
  "properties": {
    "iso:country":"AU",
    "sg:address":"Gosnells Railway Markets Albany Hwy",
    "sg:city":"Gosnells",
    "sg:classifiers":[
        {
            "category":"Food & Beverages",
            "subcategory":"Bakery",
            "type":"Retail Goods"
        }
    ],
    "sg:phone":"+61 8 9490 2456",
    "sg:postcode":"6110",
    "sg:province":"WA",
    "sg:tags":[
        "baker"
    ],
    "wof:name":"Gosnells Market Bakery",
    "wof:placetype":"venue"
},
  "geometry": {"coordinates":[116.012382507,-32.0894584656],"type":"Point"}
}