{
  "type": "Feature",
  "properties": {
    "addr:full":"Level 3/ 128 Rothschild Ave Rosebery NSW 2018",
    "addr:housenumber":"/ 128",
    "addr:postcode":"2018",
    "addr:street":"Rothschild Ave",
    "iso:country":"AU",
    "sg:address":"Level 3/ 128 Rothschild Ave",
    "sg:city":"Rosebery",
    "sg:classifiers":[
        {
            "category":"Autos & Motor Vehicles",
            "subcategory":"Boat Sales",
            "type":"Retail Goods"
        }
    ],
    "sg:phone":"+61 2 9700 9788",
    "sg:postcode":"2018",
    "sg:province":"NSW",
    "sg:tags":[
        "dictating",
        "machine"
    ],
    "wof:name":"Nationwide Dictating Pty Ltd",
    "wof:placetype":"venue"
},
  "geometry": {"coordinates":[151.20307922399999,-33.9199943542],"type":"Point"}
}