{
  "type": "Feature",
  "properties": {
    "iso:country":"AU",
    "sg:address":"Suite 2 183 Fernberg Rd",
    "sg:city":"Paddington",
    "sg:classifiers":[
        {
            "category":"Health Services",
            "subcategory":"Health Practitioner",
            "type":"Services"
        }
    ],
    "sg:phone":"+61 7 3369 0465",
    "sg:postcode":"4064",
    "sg:province":"QLD",
    "sg:tags":[
        "physiotherapist"
    ],
    "wof:name":"Beverley Bishop",
    "wof:placetype":"venue"
},
  "geometry": {"coordinates":[152.99085998499999,-27.4621334076],"type":"Point"}
}