{
  "type": "Feature",
  "properties": {
    "iso:country":"AU",
    "sg:address":"9 Silas St",
    "sg:city":"East Fremantle",
    "sg:classifiers":[
        {
            "category":"Personal",
            "subcategory":"Beauty Salon",
            "type":"Services"
        }
    ],
    "sg:phone":"+61 8 9438 1813",
    "sg:postcode":"6158",
    "sg:province":"WA",
    "wof:name":"Leonhardi",
    "wof:placetype":"venue"
},
  "geometry": {"coordinates":[115.764191,-32.041904],"type":"Point"}
}