{
  "type": "Feature",
  "properties": {
    "addr:full":"2 Cool Store Rd Huonville TAS 7109",
    "addr:housenumber":"2",
    "addr:postcode":"7109",
    "addr:street":"Cool Store Rd",
    "iso:country":"AU",
    "sg:address":"2 Cool Store Rd",
    "sg:city":"Huonville",
    "sg:classifiers":[
        {
            "category":"Shopping",
            "subcategory":"Stationery & Office Supplies",
            "type":"Retail Goods"
        }
    ],
    "sg:phone":"+61 3 6264 1377",
    "sg:postcode":"7109",
    "sg:province":"TAS",
    "sg:tags":[
        "packaging",
        "material"
    ],
    "wof:name":"Amcor Fibre Packaging Australasia",
    "wof:placetype":"venue"
},
  "geometry": {"coordinates":[147.04838562,-43.0358848572],"type":"Point"}
}