{
  "type": "Feature",
  "properties": {
    "iso:country":"AU",
    "sg:address":"370 Nepean Hwy",
    "sg:city":"Mt Martha",
    "sg:classifiers":[
        {
            "category":"Building & Trades",
            "subcategory":"Construction",
            "type":"Services"
        }
    ],
    "sg:phone":"+61 3 5974 4222",
    "sg:postcode":"3934",
    "sg:province":"VIC",
    "sg:tags":[
        "contractor"
    ],
    "wof:name":"Barrand Enterprises Pty Ltd",
    "wof:placetype":"venue"
},
  "geometry": {"coordinates":[145.030960083,-38.2859916687],"type":"Point"}
}