{
  "type": "Feature",
  "properties": {
    "addr:full":"Level 1 / 749a Nicholson St Carlton North VIC 3054",
    "addr:housenumber":"/ 749a",
    "addr:postcode":"3054",
    "addr:street":"Nicholson St",
    "iso:country":"AU",
    "sg:address":"Level 1 / 749a Nicholson St",
    "sg:city":"Carlton North",
    "sg:classifiers":[
        {
            "category":"Home & Garden",
            "subcategory":"Furniture",
            "type":"Retail Goods"
        }
    ],
    "sg:phone":"+61 3 9381 0311",
    "sg:postcode":"3054",
    "sg:province":"VIC",
    "sg:tags":[
        "business"
    ],
    "wof:name":"Pascal Commercial Interiors",
    "wof:placetype":"venue"
},
  "geometry": {"coordinates":[144.977584839,-37.7818145752],"type":"Point"}
}