{
  "type": "Feature",
  "properties": {
    "addr:full":"Level 12/ 390 St Kilda Rd Melbourne VIC 3000",
    "addr:housenumber":"/ 390",
    "addr:postcode":"3000",
    "addr:street":"St Kilda Rd",
    "iso:country":"AU",
    "sg:address":"Level 12/ 390 St Kilda Rd",
    "sg:city":"Melbourne",
    "sg:classifiers":[
        {
            "category":"Taxi",
            "type":"Transportation"
        }
    ],
    "sg:phone":"+61 1800 812 768",
    "sg:postcode":"3000",
    "sg:province":"VIC",
    "sg:tags":[
        "cab"
    ],
    "wof:name":"Save Time",
    "wof:placetype":"venue"
},
  "geometry": {"coordinates":[144.97352600100001,-37.8341751099],"type":"Point"}
}