{
  "type": "Feature",
  "properties": {
    "addr:full":"16 Grendon St North Mackay QLD 4740",
    "addr:housenumber":"16",
    "addr:postcode":"4740",
    "addr:street":"Grendon St",
    "iso:country":"AU",
    "sg:address":"16 Grendon St",
    "sg:city":"North Mackay",
    "sg:classifiers":[
        {
            "category":"Professional",
            "subcategory":"Art Services",
            "type":"Services"
        }
    ],
    "sg:phone":"+61 410 597 403",
    "sg:postcode":"4740",
    "sg:province":"QLD",
    "sg:tags":[
        "decorator",
        "painter"
    ],
    "wof:name":"RJ & Son Roof Painting",
    "wof:placetype":"venue"
},
  "geometry": {"coordinates":[149.18902600000001,-21.124231],"type":"Point"}
}