{
  "type": "Feature",
  "properties": {
    "addr:full":"140 East St Rockhampton QLD 4702",
    "addr:housenumber":"140",
    "addr:postcode":"4702",
    "addr:street":"East St",
    "iso:country":"AU",
    "sg:address":"140 East St",
    "sg:city":"Rockhampton",
    "sg:classifiers":[
        {
            "category":"Health Services",
            "subcategory":"Health Practitioner",
            "type":"Services"
        }
    ],
    "sg:phone":"+61 7 4925 0171",
    "sg:postcode":"4702",
    "sg:province":"QLD",
    "sg:tags":[
        "osteopath"
    ],
    "wof:name":"Afshean Asaadi",
    "wof:placetype":"venue"
},
  "geometry": {"coordinates":[149.070556641,-23.5815944672],"type":"Point"}
}