{
  "type": "Feature",
  "properties": {
    "iso:country":"AU",
    "sg:address":"21 Yarroma Ave",
    "sg:city":"Swan Haven",
    "sg:classifiers":[
        {
            "category":"Building & Trades",
            "subcategory":"Construction",
            "type":"Services"
        }
    ],
    "sg:phone":"+61 421 044 635",
    "sg:postcode":"2540",
    "sg:province":"NSW",
    "sg:tags":[
        "joiner",
        "carpenter"
    ],
    "wof:name":"Inlet Contractors",
    "wof:placetype":"venue"
},
  "geometry": {"coordinates":[150.583709717,-35.1729660034],"type":"Point"}
}