{
  "type": "Feature",
  "properties": {
    "addr:full":"14 Shepherd St Darwin NT 0800",
    "addr:housenumber":"14",
    "addr:postcode":"nt 0800",
    "addr:street":"Shepherd St",
    "iso:country":"AU",
    "sg:address":"14 Shepherd St",
    "sg:city":"Darwin",
    "sg:classifiers":[
        {
            "category":"Professional",
            "subcategory":"Engineering",
            "type":"Services"
        }
    ],
    "sg:phone":"+61 1800 800 528",
    "sg:postcode":"0800",
    "sg:province":"NT",
    "sg:tags":[
        "consulting",
        "engineer"
    ],
    "wof:name":"The Association Of Consulting Engineers Australia",
    "wof:placetype":"venue"
},
  "geometry": {"coordinates":[130.84063720699999,-12.4577980042],"type":"Point"}
}