{
  "type": "Feature",
  "properties": {
    "iso:country":"AU",
    "sg:address":"Suite 18, Level 1, 8-24 Kippax St",
    "sg:city":"Surry Hills",
    "sg:classifiers":[
        {
            "category":"Shopping",
            "subcategory":"Jewelry",
            "type":"Retail Goods"
        }
    ],
    "sg:phone":"+61 2 9212 2888",
    "sg:postcode":"2010",
    "sg:province":"NSW",
    "sg:tags":[
        "fashion",
        "jewellery"
    ],
    "wof:name":"Vianne",
    "wof:placetype":"venue"
},
  "geometry": {"coordinates":[151.208984375,-33.8844032288],"type":"Point"}
}