{
  "type": "Feature",
  "properties": {
    "addr:full":"2267 Point Nepean Rd Rye VIC 3941",
    "addr:housenumber":"2267",
    "addr:postcode":"3941",
    "addr:street":"Point Nepean Rd",
    "iso:country":"AU",
    "sg:address":"2267 Point Nepean Rd",
    "sg:city":"Rye",
    "sg:classifiers":[
        {
            "category":"Personal",
            "subcategory":"Beauty Salon",
            "type":"Services"
        }
    ],
    "sg:phone":"+61 3 5985 3517",
    "sg:postcode":"3941",
    "sg:province":"VIC",
    "sg:tags":[
        "hairdresser"
    ],
    "wof:name":"Beach Hedz Beach Bodz",
    "wof:placetype":"venue"
},
  "geometry": {"coordinates":[144.82658386200001,-38.370967865],"type":"Point"}
}