{
  "type": "Feature",
  "properties": {
    "addr:full":"Range Industrial Park 4/ 3275 Logan Rd Underwood QLD 4119",
    "addr:housenumber":"/ 3275",
    "addr:postcode":"4119",
    "addr:street":"Park;Logan Rd",
    "iso:country":"AU",
    "sg:address":"Range Industrial Park 4/ 3275 Logan Rd",
    "sg:city":"Underwood",
    "sg:classifiers":[
        {
            "category":"Building & Trades",
            "subcategory":"Construction",
            "type":"Services"
        }
    ],
    "sg:phone":"+61 7 3219 0330",
    "sg:postcode":"4119",
    "sg:province":"QLD",
    "sg:tags":[
        "home",
        "air conditioning"
    ],
    "wof:name":"South Qld Electrical Pty Ltd",
    "wof:placetype":"venue"
},
  "geometry": {"coordinates":[153.115890503,-27.6112346649],"type":"Point"}
}