{
  "type": "Feature",
  "properties": {
    "iso:country":"AU",
    "sg:address":"Un 48, 8 Avenue Of Americas",
    "sg:city":"Newington",
    "sg:classifiers":[
        {
            "category":"Shopping",
            "subcategory":"Beauty & Cosmetics",
            "type":"Retail Goods"
        }
    ],
    "sg:phone":"+61 2 9748 8877",
    "sg:postcode":"2127",
    "sg:province":"NSW",
    "wof:name":"For Solutions Pty Ltd",
    "wof:placetype":"venue"
},
  "geometry": {"coordinates":[151.05632019000001,-33.8324699402],"type":"Point"}
}