{
  "type": "Feature",
  "properties": {
    "addr:full":"Factory 18, 200 Canterbury Rd Bayswater North VIC 3153",
    "addr:housenumber":"200",
    "addr:postcode":"3153",
    "addr:street":"Canterbury Rd",
    "iso:country":"AU",
    "sg:address":"Factory 18, 200 Canterbury Rd",
    "sg:city":"Bayswater North",
    "sg:classifiers":[
        {
            "category":"Manufacturing",
            "subcategory":"Tools & Machinery",
            "type":"Manufacturing & Wholesale Goods"
        }
    ],
    "sg:phone":"+61 3 9720 9400",
    "sg:postcode":"3153",
    "sg:province":"VIC",
    "sg:tags":[
        "toolmaker"
    ],
    "wof:name":"Digital Sports Systems",
    "wof:placetype":"venue"
},
  "geometry": {"coordinates":[145.28724670400001,-37.8258934021],"type":"Point"}
}