{
  "type": "Feature",
  "properties": {
    "addr:full":"10 Watson St Turner ACT 2612",
    "addr:housenumber":"10",
    "addr:postcode":"2612",
    "addr:street":"Watson St",
    "iso:country":"AU",
    "sg:address":"10 Watson St",
    "sg:city":"Turner",
    "sg:classifiers":[
        {
            "category":"Education",
            "subcategory":"Dance Studio",
            "type":"Public Place"
        }
    ],
    "sg:phone":"+61 428 798 490",
    "sg:postcode":"2612",
    "sg:province":"ACT",
    "sg:tags":[
        "venue",
        "tuition"
    ],
    "wof:name":"Kokoloco Latino Dancing",
    "wof:placetype":"venue"
},
  "geometry": {"coordinates":[149.126052856,-35.2739944458],"type":"Point"}
}