{
  "type": "Feature",
  "properties": {
    "iso:country":"AU",
    "sg:address":"Shop 4 Shearwater Resort Esp",
    "sg:city":"Kings Beach",
    "sg:classifiers":[
        {
            "category":"Fast Food",
            "type":"Food & Drink"
        }
    ],
    "sg:phone":"+61 7 5492 8889",
    "sg:postcode":"4551",
    "sg:province":"QLD",
    "sg:tags":[
        "away",
        "take"
    ],
    "wof:name":"Thai Sea Breeze",
    "wof:placetype":"venue"
},
  "geometry": {"coordinates":[153.11830139200001,-26.7848968506],"type":"Point"}
}