{
  "type": "Feature",
  "properties": {
    "addr:full":"Shop 2, 34 Seaford Rd Seaford SA 5169",
    "addr:housenumber":"shop;34",
    "addr:postcode":"5169",
    "addr:street":"Seaford Rd",
    "iso:country":"AU",
    "sg:address":"Shop 2, 34 Seaford Rd",
    "sg:city":"Seaford",
    "sg:classifiers":[
        {
            "category":"Personal",
            "subcategory":"Beauty Salon",
            "type":"Services"
        }
    ],
    "sg:phone":"+61 8 8386 2615",
    "sg:postcode":"5169",
    "sg:province":"SA",
    "sg:tags":[
        "hairdresser"
    ],
    "wof:name":"Fringes Hair Design",
    "wof:placetype":"venue"
},
  "geometry": {"coordinates":[138.47776794399999,-35.1807556152],"type":"Point"}
}