{
  "type": "Feature",
  "properties": {
    "addr:full":"Unit 2 261- 265 Dunmore St Pendle Hill NSW 2145",
    "addr:housenumber":"261 265",
    "addr:postcode":"2145",
    "addr:street":"Dunmore St",
    "iso:country":"AU",
    "sg:address":"Unit 2 261- 265 Dunmore St",
    "sg:city":"Pendle Hill",
    "sg:classifiers":[
        {
            "category":"Professional",
            "type":"Services"
        }
    ],
    "sg:phone":"+61 412 448 984",
    "sg:postcode":"2145",
    "sg:province":"NSW",
    "sg:tags":[
        "courier"
    ],
    "wof:name":"Swanhold Pty Ltd",
    "wof:placetype":"venue"
},
  "geometry": {"coordinates":[150.95735168499999,-33.8042488098],"type":"Point"}
}