{
  "type": "Feature",
  "properties": {
    "addr:full":"Level 12, 227 Collins St Melbourne VIC 3000",
    "addr:housenumber":"227",
    "addr:postcode":"3000",
    "addr:street":"Collins St",
    "iso:country":"AU",
    "sg:address":"Level 12, 227 Collins St",
    "sg:city":"Melbourne",
    "sg:classifiers":[
        {
            "category":"Shopping",
            "subcategory":"Jewelry",
            "type":"Retail Goods"
        }
    ],
    "sg:phone":"+61 3 9654 1477",
    "sg:postcode":"3000",
    "sg:province":"VIC",
    "sg:tags":[
        "jeweller",
        "supply"
    ],
    "wof:name":"Twin Plaza Metals Pty Ltd",
    "wof:placetype":"venue"
},
  "geometry": {"coordinates":[144.96644592300001,-37.8156509399],"type":"Point"}
}