{
  "type": "Feature",
  "properties": {
    "addr:full":"10 Windsor Rd Croydon VIC 3136",
    "addr:housenumber":"10",
    "addr:postcode":"3136",
    "addr:street":"Windsor Rd",
    "iso:country":"AU",
    "sg:address":"10 Windsor Rd",
    "sg:city":"Croydon",
    "sg:classifiers":[
        {
            "category":"Manufacturing",
            "subcategory":"Motor Vehicles & Parts",
            "type":"Manufacturing & Wholesale Goods"
        }
    ],
    "sg:phone":"+61 3 9725 5344",
    "sg:postcode":"3136",
    "sg:province":"VIC",
    "sg:tags":[
        "replacement"
    ],
    "wof:name":"Croydon Auto Parts & Accessories",
    "wof:placetype":"venue"
},
  "geometry": {"coordinates":[145.28558349599999,-37.7953033447],"type":"Point"}
}