{
  "type": "Feature",
  "properties": {
    "addr:full":"5 General Bridges Crs Kingsford NSW 2032",
    "addr:postcode":"2032",
    "addr:street":"Bridges Crs",
    "iso:country":"AU",
    "sg:address":"5 General Bridges Crs",
    "sg:city":"Kingsford",
    "sg:classifiers":[
        {
            "category":"Retail",
            "subcategory":"Repair Shop",
            "type":"Services"
        }
    ],
    "sg:phone":"+61 2 9663 2258",
    "sg:postcode":"2032",
    "sg:province":"NSW",
    "sg:tags":[
        "machine",
        "sewing"
    ],
    "wof:name":"Eastern Suburbs Sewing Machine Centre",
    "wof:placetype":"venue"
},
  "geometry": {"coordinates":[151.227493286,-33.9234886169],"type":"Point"}
}