{
  "type": "Feature",
  "properties": {
    "iso:country":"AU",
    "sg:address":"Old Ballarat Rd",
    "sg:city":"Batesford",
    "sg:classifiers":[
        {
            "category":"Education",
            "subcategory":"School",
            "type":"Public Place"
        }
    ],
    "sg:phone":"+61 3 5276 1290",
    "sg:postcode":"3221",
    "sg:province":"VIC",
    "sg:tags":[
        "state",
        "except",
        "nsw"
    ],
    "wof:name":"Rollins Primary School",
    "wof:placetype":"venue"
},
  "geometry": {"coordinates":[144.28939800000001,-38.092552],"type":"Point"}
}