{
  "type": "Feature",
  "properties": {
    "iso:country":"AU",
    "sg:address":"14 Johnstone Rd",
    "sg:city":"Brendale",
    "sg:classifiers":[
        {
            "category":"Utilities",
            "type":"Services"
        }
    ],
    "sg:phone":"+61 7 3205 2512",
    "sg:postcode":"4500",
    "sg:province":"QLD",
    "sg:tags":[
        "refrigeration",
        "industrial",
        "commercial",
        "retail"
    ],
    "wof:name":"Northside Refrigeration Sales & Service",
    "wof:placetype":"venue"
},
  "geometry": {"coordinates":[152.990722656,-27.3217868805],"type":"Point"}
}