{
  "type": "Feature",
  "properties": {
    "addr:full":"6/ 43 Kirwan St Floreat WA 6014",
    "addr:housenumber":"/ 43",
    "addr:postcode":"6014",
    "addr:street":"Kirwan St",
    "iso:country":"AU",
    "sg:address":"6/ 43 Kirwan St",
    "sg:city":"Floreat",
    "sg:classifiers":[
        {
            "category":"Building & Trades",
            "subcategory":"Construction",
            "type":"Services"
        }
    ],
    "sg:phone":"+61 8 9387 5888",
    "sg:postcode":"6014",
    "sg:province":"WA",
    "sg:tags":[
        "contractor"
    ],
    "wof:name":"Glenway Homes",
    "wof:placetype":"venue"
},
  "geometry": {"coordinates":[115.798851013,-31.9451618195],"type":"Point"}
}