{
  "type": "Feature",
  "properties": {
    "addr:full":"Shop 4-5 Orange Grove Mall 296 Windsor St Richmond NSW 2753",
    "addr:housenumber":"shop 4-5;296",
    "addr:postcode":"2753",
    "addr:street":"Orange Grove;Windsor St",
    "iso:country":"AU",
    "sg:address":"Shop 4-5 Orange Grove Mall 296 Windsor St",
    "sg:city":"Richmond",
    "sg:classifiers":[
        {
            "category":"Fast Food",
            "type":"Food & Drink"
        }
    ],
    "sg:phone":"+61 2 4578 1525",
    "sg:postcode":"2753",
    "sg:province":"NSW",
    "sg:tags":[
        "away",
        "take"
    ],
    "wof:name":"Aldos Pizza",
    "wof:placetype":"venue"
},
  "geometry": {"coordinates":[150.750091553,-33.5965270996],"type":"Point"}
}