{
  "type": "Feature",
  "properties": {
    "addr:full":"266 Sydney Rd Coburg VIC 3058",
    "addr:housenumber":"266",
    "addr:postcode":"3058",
    "addr:street":"Sydney Rd",
    "iso:country":"AU",
    "sg:address":"266 Sydney Rd",
    "sg:city":"Coburg",
    "sg:classifiers":[
        {
            "category":"Professional",
            "subcategory":"Detective & Security Services",
            "type":"Services"
        }
    ],
    "sg:phone":"+61 3 9384 1811",
    "sg:postcode":"3058",
    "sg:province":"VIC",
    "sg:tags":[
        "domestic",
        "alarm",
        "commercial",
        "burglar"
    ],
    "wof:name":"Jaycar Electronics Pty Ltd",
    "wof:placetype":"venue"
},
  "geometry": {"coordinates":[144.96554565400001,-37.7482070923],"type":"Point"}
}