{
  "type": "Feature",
  "properties": {
    "iso:country":"AU",
    "sg:address":"Cnr Talavera & Culloden Rds",
    "sg:city":"Marsfield",
    "sg:classifiers":[
        {
            "category":"Sports & Exercise",
            "subcategory":"Sports Center",
            "type":"Entertainment"
        }
    ],
    "sg:phone":"+61 2 9878 6668",
    "sg:postcode":"2122",
    "sg:province":"NSW",
    "sg:tags":[
        "coach",
        "tennis"
    ],
    "wof:name":"Vince Barclay Tennis",
    "wof:placetype":"venue"
},
  "geometry": {"coordinates":[151.11268615700001,-33.7672157288],"type":"Point"}
}