{
  "type": "Feature",
  "properties": {
    "iso:country":"AU",
    "sg:address":"276 Pease St",
    "sg:city":"Edge Hill",
    "sg:classifiers":[
        {
            "category":"Social Services",
            "subcategory":"Retirement Home",
            "type":"Services"
        }
    ],
    "sg:phone":"+61 7 4053 2033",
    "sg:postcode":"4870",
    "sg:province":"QLD",
    "sg:tags":[
        "environmental",
        "consultant",
        "pollution"
    ],
    "wof:name":"Ecosure Pty Ltd",
    "wof:placetype":"venue"
},
  "geometry": {"coordinates":[145.74200439399999,-16.9048614502],"type":"Point"}
}