{
  "type": "Feature",
  "properties": {
    "addr:full":"PO Box 3 Higgins ACT 2615",
    "addr:postcode":"2615",
    "iso:country":"AU",
    "sg:address":"PO Box 3",
    "sg:city":"Higgins",
    "sg:classifiers":[
        {
            "category":"Shopping",
            "subcategory":"Party Supplies",
            "type":"Retail Goods"
        }
    ],
    "sg:phone":"+61 2 6254 8047",
    "sg:postcode":"2615",
    "sg:province":"ACT",
    "sg:tags":[
        "children's"
    ],
    "wof:name":"The Gecko Gang",
    "wof:placetype":"venue"
},
  "geometry": {"coordinates":[149.027511597,-35.2332687378],"type":"Point"}
}