{
  "type": "Feature",
  "properties": {
    "addr:full":"PO Box 371 Waterford QLD 4133",
    "addr:postcode":"4133",
    "iso:country":"AU",
    "sg:address":"PO Box 371",
    "sg:city":"Waterford",
    "sg:classifiers":[
        {
            "category":"Building & Trades",
            "subcategory":"Construction",
            "type":"Services"
        }
    ],
    "sg:phone":"+61 418 797 956",
    "sg:postcode":"4133",
    "sg:province":"QLD",
    "sg:tags":[
        "earth",
        "excavating",
        "moving",
        "contractor"
    ],
    "wof:name":"Grader Hire Mike Stevens",
    "wof:placetype":"venue"
},
  "geometry": {"coordinates":[153.136795044,-27.7082004547],"type":"Point"}
}