{
  "type": "Feature",
  "properties": {
    "addr:full":"Avonside Rd Dunedoo NSW 2844",
    "addr:postcode":"2844",
    "addr:street":"Avonside Rd",
    "iso:country":"AU",
    "sg:address":"Avonside Rd",
    "sg:city":"Dunedoo",
    "sg:classifiers":[
        {
            "category":"Building & Trades",
            "subcategory":"Landscaping Services",
            "type":"Services"
        }
    ],
    "sg:phone":"+61 2 6375 1257",
    "sg:postcode":"2844",
    "sg:province":"NSW",
    "sg:tags":[
        "grazier"
    ],
    "wof:name":"Taylor R H J & W J",
    "wof:placetype":"venue"
},
  "geometry": {"coordinates":[149.37953200000001,-32.023342],"type":"Point"}
}