{
  "type": "Feature",
  "properties": {
    "iso:country":"AU",
    "sg:address":"2 Shannon St",
    "sg:city":"Redbank Plains",
    "sg:classifiers":[
        {
            "category":"Communications",
            "subcategory":"Film & Video Production",
            "type":"Services"
        }
    ],
    "sg:phone":"+61 7 3814 3133",
    "sg:postcode":"4301",
    "sg:province":"QLD",
    "sg:tags":[
        "dvd",
        "library"
    ],
    "wof:name":"Video Ezy",
    "wof:placetype":"venue"
},
  "geometry": {"coordinates":[152.873443603,-27.6344985962],"type":"Point"}
}