{
  "type": "Feature",
  "properties": {
    "iso:country":"AU",
    "sg:address":"Unit 1/ 944 Nudgee Rd",
    "sg:city":"Northgate",
    "sg:classifiers":[
        {
            "category":"Manufacturing",
            "subcategory":"Tools & Machinery",
            "type":"Manufacturing & Wholesale Goods"
        }
    ],
    "sg:phone":"+61 7 3267 1187",
    "sg:postcode":"4013",
    "sg:province":"QLD",
    "sg:tags":[
        "equipment",
        "scale",
        "weighing"
    ],
    "wof:name":"A'Asia Scales Service Pty Ltd",
    "wof:placetype":"venue"
},
  "geometry": {"coordinates":[153.08663940400001,-27.3873023987],"type":"Point"}
}