{
  "type": "Feature",
  "properties": {
    "addr:full":"Cnr Buln Buln & Jabiru Sts Quilpie QLD 4480",
    "addr:postcode":"4480",
    "addr:street":"Cnr",
    "iso:country":"AU",
    "sg:address":"Cnr Buln Buln & Jabiru Sts",
    "sg:city":"Quilpie",
    "sg:classifiers":[
        {
            "category":"Food & Beverages",
            "subcategory":"Supermarket",
            "type":"Retail Goods"
        }
    ],
    "sg:phone":"+61 7 4656 1377",
    "sg:postcode":"4480",
    "sg:province":"QLD",
    "sg:tags":[
        "grocery",
        "store"
    ],
    "wof:name":"Paulsen Bros Supermarket",
    "wof:placetype":"venue"
},
  "geometry": {"coordinates":[144.2681427,-26.6172580719],"type":"Point"}
}