{
  "type": "Feature",
  "properties": {
    "addr:full":"Cnr Moore & Broughton Sts Campbelltown NSW 2560",
    "addr:postcode":"2560",
    "addr:street":"Cnr",
    "iso:country":"AU",
    "sg:address":"Cnr Moore & Broughton Sts",
    "sg:city":"Campbelltown",
    "sg:classifiers":[
        {
            "category":"Retail",
            "subcategory":"Funeral Services",
            "type":"Services"
        }
    ],
    "sg:phone":"+61 2 4625 1854",
    "sg:postcode":"2560",
    "sg:province":"NSW",
    "sg:tags":[
        "director"
    ],
    "wof:name":"P.E. Butler Funerals",
    "wof:placetype":"venue"
},
  "geometry": {"coordinates":[150.82972717300001,-34.078086853],"type":"Point"}
}