{
  "type": "Feature",
  "properties": {
    "addr:full":"2 Gooyong St Kingaroy QLD 4610",
    "addr:housenumber":"2",
    "addr:postcode":"4610",
    "addr:street":"Gooyong St",
    "iso:country":"AU",
    "sg:address":"2 Gooyong St",
    "sg:city":"Kingaroy",
    "sg:classifiers":[
        {
            "category":"Social Services",
            "subcategory":"Child Care",
            "type":"Services"
        }
    ],
    "sg:phone":"+61 7 4162 3196",
    "sg:postcode":"4610",
    "sg:province":"QLD",
    "wof:name":"Jennys Day Care Centre.",
    "wof:placetype":"venue"
},
  "geometry": {"coordinates":[151.844238281,-26.5410728455],"type":"Point"}
}