{
  "type": "Feature",
  "properties": {
    "addr:full":"Lot 989 Industrial Rd Light Industrial Area Denmark WA 6333",
    "addr:postcode":"6333",
    "addr:street":"Industrial Rd",
    "iso:country":"AU",
    "sg:address":"Lot 989 Industrial Rd Light Industrial Area",
    "sg:city":"Denmark",
    "sg:classifiers":[
        {
            "category":"Autos & Motor Vehicles",
            "subcategory":"Auto Supplies",
            "type":"Retail Goods"
        }
    ],
    "sg:phone":"+61 8 9848 2728",
    "sg:postcode":"6333",
    "sg:province":"WA",
    "sg:tags":[
        "tyre"
    ],
    "wof:name":"Denmark Tyrepower",
    "wof:placetype":"venue"
},
  "geometry": {"coordinates":[117.355636597,-34.9674606323],"type":"Point"}
}