{
  "type": "Feature",
  "properties": {
    "iso:country":"AU",
    "sg:address":"Marathon Stadium Turton Rd",
    "sg:city":"New Lambton",
    "sg:classifiers":[
        {
            "category":"Food & Beverages",
            "subcategory":"Fruits & Vegetables",
            "type":"Retail Goods"
        }
    ],
    "sg:phone":"+61 2 4957 7099",
    "sg:postcode":"2305",
    "sg:province":"NSW",
    "sg:tags":[
        "consultant",
        "catering"
    ],
    "wof:name":"Newcastle Knight Captains Club",
    "wof:placetype":"venue"
},
  "geometry": {"coordinates":[151.722855,-32.922935],"type":"Point"}
}