{
  "type": "Feature",
  "properties": {
    "addr:full":"15 Illouera Ave Grovedale VIC 3216",
    "addr:housenumber":"15",
    "addr:postcode":"3216",
    "addr:street":"Illouera Ave",
    "iso:country":"AU",
    "sg:address":"15 Illouera Ave",
    "sg:city":"Grovedale",
    "sg:classifiers":[
        {
            "category":"Building & Trades",
            "subcategory":"Plumbing",
            "type":"Services"
        }
    ],
    "sg:phone":"+61 418 522 653",
    "sg:postcode":"3216",
    "sg:province":"VIC",
    "sg:tags":[
        "plumber",
        "gasfitters"
    ],
    "wof:name":"Grovedale Plumbing Services Pty Ltd",
    "wof:placetype":"venue"
},
  "geometry": {"coordinates":[144.324417114,-38.2070350647],"type":"Point"}
}