{
  "type": "Feature",
  "properties": {
    "addr:full":"344 Henley Beach Rd Lockleys SA 5032",
    "addr:housenumber":"344",
    "addr:postcode":"5032",
    "addr:street":"Henley Beach Rd",
    "iso:country":"AU",
    "sg:address":"344 Henley Beach Rd",
    "sg:city":"Lockleys",
    "sg:classifiers":[
        {
            "category":"Retail",
            "subcategory":"Funeral Services",
            "type":"Services"
        }
    ],
    "sg:phone":"+61 8 8354 3055",
    "sg:postcode":"5032",
    "sg:province":"SA",
    "sg:tags":[
        "director"
    ],
    "wof:name":"Alfred James & Sons Pty Ltd",
    "wof:placetype":"venue"
},
  "geometry": {"coordinates":[138.538894653,-34.9267692566],"type":"Point"}
}