{
  "type": "Feature",
  "properties": {
    "addr:full":"Old Backwater Rd Narromine NSW 2821",
    "addr:postcode":"2821",
    "addr:street":"Backwater Rd",
    "iso:country":"AU",
    "sg:address":"Old Backwater Rd",
    "sg:city":"Narromine",
    "sg:classifiers":[
        {
            "category":"Professional",
            "type":"Services"
        }
    ],
    "sg:phone":"+61 2 6889 2068",
    "sg:postcode":"2821",
    "sg:province":"NSW",
    "sg:tags":[
        "transport"
    ],
    "wof:name":"Hitchcock G & A M",
    "wof:placetype":"venue"
},
  "geometry": {"coordinates":[148.237915039,-32.2394065857],"type":"Point"}
}