{
  "type": "Feature",
  "properties": {
    "addr:full":"1000 Point Nepean Rd Rosebud VIC 3939",
    "addr:housenumber":"1000",
    "addr:postcode":"3939",
    "addr:street":"Point Nepean Rd",
    "iso:country":"AU",
    "sg:address":"1000 Point Nepean Rd",
    "sg:city":"Rosebud",
    "sg:classifiers":[
        {
            "category":"Education",
            "subcategory":"Kindergarten",
            "type":"Public Place"
        }
    ],
    "sg:phone":"+61 3 5986 8970",
    "sg:postcode":"3939",
    "sg:province":"VIC",
    "sg:tags":[
        "pre-schools"
    ],
    "wof:name":"Rosebud Kindergarten Inc",
    "wof:placetype":"venue"
},
  "geometry": {"coordinates":[144.90005493199999,-38.3565864563],"type":"Point"}
}