{
  "type": "Feature",
  "properties": {
    "addr:full":"2 Elizabeth St Tanunda SA 5352",
    "addr:housenumber":"2",
    "addr:postcode":"5352",
    "addr:street":"Elizabeth St",
    "iso:country":"AU",
    "sg:address":"2 Elizabeth St",
    "sg:city":"Tanunda",
    "sg:classifiers":[
        {
            "category":"Health Services",
            "subcategory":"Health Practitioner",
            "type":"Services"
        }
    ],
    "sg:phone":"+61 8 8564 3399",
    "sg:postcode":"5352",
    "sg:province":"SA",
    "sg:tags":[
        "physiotherapist"
    ],
    "wof:name":"Schilling Natalie",
    "wof:placetype":"venue"
},
  "geometry": {"coordinates":[138.96018981899999,-34.5235061646],"type":"Point"}
}