{
  "type": "Feature",
  "properties": {
    "addr:full":"5 Dudley St Cessnock NSW 2325",
    "addr:housenumber":"5",
    "addr:postcode":"2325",
    "addr:street":"Dudley St",
    "iso:country":"AU",
    "sg:address":"5 Dudley St",
    "sg:city":"Cessnock",
    "sg:classifiers":[
        {
            "category":"Education",
            "subcategory":"Kindergarten",
            "type":"Public Place"
        }
    ],
    "sg:phone":"+61 2 4990 2687",
    "sg:postcode":"2325",
    "sg:province":"NSW",
    "sg:tags":[
        "pre-schools"
    ],
    "wof:name":"Cessnock Multipurpose Children's Centre Ltd",
    "wof:placetype":"venue"
},
  "geometry": {"coordinates":[151.35243225100001,-32.8323326111],"type":"Point"}
}