{
  "type": "Feature",
  "properties": {
    "addr:full":"7-9 Warren St Ingham QLD 4850",
    "addr:housenumber":"7-9",
    "addr:postcode":"4850",
    "addr:street":"Warren St",
    "iso:country":"AU",
    "sg:address":"7-9 Warren St",
    "sg:city":"Ingham",
    "sg:classifiers":[
        {
            "category":"Travel",
            "subcategory":"Hotels & Motels",
            "type":"Entertainment"
        }
    ],
    "sg:phone":"+61 1800 238 077",
    "sg:postcode":"4850",
    "sg:province":"QLD",
    "wof:name":"Noorla Hotel",
    "wof:placetype":"venue"
},
  "geometry": {"coordinates":[146.157440186,-18.6466903687],"type":"Point"}
}