{
  "type": "Feature",
  "properties": {
    "iso:country":"AU",
    "sg:address":"33b Alan Rd",
    "sg:city":"Berowra Heights",
    "sg:classifiers":[
        {
            "category":"Building & Trades",
            "subcategory":"Construction",
            "type":"Services"
        }
    ],
    "sg:phone":"+61 413 237 181",
    "sg:postcode":"2082",
    "sg:province":"NSW",
    "sg:tags":[
        "contractor"
    ],
    "wof:name":"Donelan Construction",
    "wof:placetype":"venue"
},
  "geometry": {"coordinates":[151.142303467,-33.6115455627],"type":"Point"}
}