{
  "type": "Feature",
  "properties": {
    "addr:full":"Unit 9/ 29 Robertson St Kogarah NSW 2217",
    "addr:housenumber":"29",
    "addr:postcode":"2217",
    "addr:street":"Robertson St",
    "iso:country":"AU",
    "sg:address":"Unit 9/ 29 Robertson St",
    "sg:city":"Kogarah",
    "sg:classifiers":[
        {
            "category":"Utilities",
            "subcategory":"Telephone",
            "type":"Services"
        }
    ],
    "sg:phone":"+61 411 601 358",
    "sg:postcode":"2217",
    "sg:province":"NSW",
    "sg:tags":[
        "installation",
        "system",
        "maintenance"
    ],
    "wof:name":"Domtek Pty Ltd",
    "wof:placetype":"venue"
},
  "geometry": {"coordinates":[151.130157,-33.962196],"type":"Point"}
}