{
  "type": "Feature",
  "properties": {
    "addr:full":"Style At Home Centre, Shop T1, 8, 49-59 O'Riordan Alexandria NSW 2015",
    "addr:housenumber":"8",
    "addr:postcode":"49-59;2015",
    "addr:street":"T1",
    "iso:country":"AU",
    "sg:address":"Style At Home Centre, Shop T1, 8, 49-59 O'Riordan",
    "sg:city":"Alexandria",
    "sg:classifiers":[
        {
            "category":"Building & Trades",
            "subcategory":"Construction",
            "type":"Services"
        }
    ],
    "sg:phone":"+61 2 9317 2677",
    "sg:postcode":"2015",
    "sg:province":"NSW",
    "sg:tags":[
        "home",
        "air conditioning"
    ],
    "wof:name":"Bing Lee",
    "wof:placetype":"venue"
},
  "geometry": {"coordinates":[151.197097778,-33.9120788574],"type":"Point"}
}