{
  "type": "Feature",
  "properties": {
    "addr:full":"Victoria Parade Eye Consulatants, Level 1 , Fitzroy VIC 3065",
    "addr:housenumber":"1",
    "addr:postcode":"3065",
    "addr:street":"Victoria",
    "iso:country":"AU",
    "sg:address":"Victoria Parade Eye Consulatants, Level 1",
    "sg:city":", Fitzroy",
    "sg:classifiers":[
        {
            "category":"Health Services",
            "subcategory":"Doctor",
            "type":"Services"
        }
    ],
    "sg:phone":"+61 3 9417 1079",
    "sg:postcode":"3065",
    "sg:province":"VIC",
    "sg:tags":[
        "medical",
        "practitioner"
    ],
    "wof:name":"Ferguson, Malcolm Dr. Eye Specialist & Surgeon",
    "wof:placetype":"venue"
},
  "geometry": {"coordinates":[144.977386475,-37.808216095],"type":"Point"}
}