{
  "type": "Feature",
  "properties": {
    "addr:full":"9 Roosevelt Crt Brighton East VIC 3187",
    "addr:housenumber":"9",
    "addr:postcode":"3187",
    "addr:street":"Roosevelt Crt",
    "iso:country":"AU",
    "sg:address":"9 Roosevelt Crt",
    "sg:city":"Brighton East",
    "sg:classifiers":[
        {
            "category":"Professional",
            "subcategory":"Business Services",
            "type":"Services"
        }
    ],
    "sg:phone":"+61 413 007 493",
    "sg:postcode":"3187",
    "sg:province":"VIC",
    "sg:tags":[
        "salesperson"
    ],
    "wof:name":"Mason Marketing",
    "wof:placetype":"venue"
},
  "geometry": {"coordinates":[145.01492309599999,-37.9280052185],"type":"Point"}
}