{
  "type": "Feature",
  "properties": {
    "addr:full":"1 Darlington Drv Cherrybrook NSW 2126",
    "addr:housenumber":"1",
    "addr:postcode":"2126",
    "addr:street":"Darlington Drv",
    "iso:country":"AU",
    "sg:address":"1 Darlington Drv",
    "sg:city":"Cherrybrook",
    "sg:classifiers":[
        {
            "category":"Professional",
            "subcategory":"Computer Services",
            "type":"Services"
        }
    ],
    "sg:phone":"+61 418 162 553",
    "sg:postcode":"2126",
    "sg:province":"NSW",
    "sg:tags":[
        "consultant",
        "system"
    ],
    "wof:name":"Rimpaq R.T.S. Pty Ltd",
    "wof:placetype":"venue"
},
  "geometry": {"coordinates":[151.03527832,-33.7258224487],"type":"Point"}
}