{
  "type": "Feature",
  "properties": {
    "iso:country":"AU",
    "sg:address":"33 Holbeche Rd",
    "sg:city":"Arndell Park",
    "sg:classifiers":[
        {
            "category":"Building & Trades",
            "subcategory":"Construction",
            "type":"Services"
        }
    ],
    "sg:phone":"+61 2 9676 3516",
    "sg:postcode":"2148",
    "sg:province":"NSW",
    "sg:tags":[
        "contractor"
    ],
    "wof:name":"Tailored Construction Group",
    "wof:placetype":"venue"
},
  "geometry": {"coordinates":[150.882736206,-33.7885322571],"type":"Point"}
}