{
  "type": "Feature",
  "properties": {
    "addr:full":"87 Jervois St Torrensville SA 5031",
    "addr:housenumber":"87",
    "addr:postcode":"5031",
    "addr:street":"Jervois St",
    "iso:country":"AU",
    "sg:address":"87 Jervois St",
    "sg:city":"Torrensville",
    "sg:classifiers":[
        {
            "category":"Food & Beverages",
            "subcategory":"Liquor & Beverages",
            "type":"Retail Goods"
        }
    ],
    "sg:phone":"+61 8 8416 7500",
    "sg:postcode":"5031",
    "sg:province":"SA",
    "sg:tags":[
        "merchant",
        "spirit",
        "wine"
    ],
    "wof:name":"S.A. Liquor Distributors Ltd",
    "wof:placetype":"venue"
},
  "geometry": {"coordinates":[138.56076049800001,-34.9146842957],"type":"Point"}
}