{
  "type": "Feature",
  "properties": {
    "addr:full":"42 Neasham Drv Dandenong North VIC 3175",
    "addr:housenumber":"42",
    "addr:postcode":"3175",
    "addr:street":"Neasham Drv",
    "iso:country":"AU",
    "sg:address":"42 Neasham Drv",
    "sg:city":"Dandenong North",
    "sg:classifiers":[
        {
            "category":"Banks & Credit Unions",
            "subcategory":"Financial Services",
            "type":"Services"
        }
    ],
    "sg:phone":"+61 3 9795 0602",
    "sg:postcode":"3175",
    "sg:province":"VIC",
    "sg:tags":[
        "loan",
        "finance",
        "mortgage"
    ],
    "wof:name":"R.S. Financial Services",
    "wof:placetype":"venue"
},
  "geometry": {"coordinates":[145.19920349099999,-37.9447555542],"type":"Point"}
}