{
  "type": "Feature",
  "properties": {
    "addr:full":"Cnr Canberra Ave & Stephens Rd Queanbeyan ACT 2620",
    "addr:postcode":"2620",
    "addr:street":"Canberra Ave & Stephens Rd",
    "iso:country":"AU",
    "sg:address":"Cnr Canberra Ave & Stephens Rd",
    "sg:city":"Queanbeyan",
    "sg:classifiers":[
        {
            "category":"Retail",
            "subcategory":"Auto Repair",
            "type":"Services"
        }
    ],
    "sg:phone":"+61 2 6297 6006",
    "sg:postcode":"2620",
    "sg:province":"ACT",
    "sg:tags":[
        "repairer",
        "motor",
        "engineer"
    ],
    "wof:name":"Monaro Off Road Centre",
    "wof:placetype":"venue"
},
  "geometry": {"coordinates":[149.20787048299999,-35.3484725952],"type":"Point"}
}