{
  "type": "Feature",
  "properties": {
    "addr:full":"81 Antoine St Rydalmere NSW 2116",
    "addr:housenumber":"81",
    "addr:postcode":"2116",
    "addr:street":"Antoine St",
    "iso:country":"AU",
    "sg:address":"81 Antoine St",
    "sg:city":"Rydalmere",
    "sg:classifiers":[
        {
            "category":"Building & Trades",
            "subcategory":"Construction",
            "type":"Services"
        }
    ],
    "sg:phone":"+61 2 9638 2692",
    "sg:postcode":"2116",
    "sg:province":"NSW",
    "sg:tags":[
        "polishing",
        "sanding",
        "floor"
    ],
    "wof:name":"Barber G E",
    "wof:placetype":"venue"
},
  "geometry": {"coordinates":[151.047805786,-33.8176383972],"type":"Point"}
}