{
  "type": "Feature",
  "properties": {
    "iso:country":"AU",
    "sg:address":"Level 2, 1 Taylor St",
    "sg:city":"Moorabbin",
    "sg:classifiers":[
        {
            "category":"Education",
            "subcategory":"Special Training",
            "type":"Public Place"
        }
    ],
    "sg:phone":"+61 3 9532 1086",
    "sg:postcode":"3189",
    "sg:province":"VIC",
    "sg:tags":[
        "development"
    ],
    "wof:name":"Skillsplus",
    "wof:placetype":"venue"
},
  "geometry": {"coordinates":[145.03805542000001,-37.9348640442],"type":"Point"}
}