{
  "type": "Feature",
  "properties": {
    "iso:country":"AU",
    "sg:address":"Village Shopping Centre 601 Robinson Rd",
    "sg:city":"Aspley",
    "sg:classifiers":[
        {
            "category":"Health Services",
            "subcategory":"Doctor",
            "type":"Services"
        }
    ],
    "sg:phone":"+61 7 3832 4160",
    "sg:postcode":"4034",
    "sg:province":"QLD",
    "sg:tags":[
        "medical",
        "practitioner"
    ],
    "wof:name":"Foster W J",
    "wof:placetype":"venue"
},
  "geometry": {"coordinates":[153.019913,-27.356684],"type":"Point"}
}