{
  "type": "Feature",
  "properties": {
    "addr:full":"Shop P16, NorthPoint Plaza, 100 Miller Street North Sydney NSW 2060",
    "addr:housenumber":"p16;100",
    "addr:postcode":"2060",
    "addr:street":"Miller Street",
    "iso:country":"AU",
    "sg:address":"Shop P16, NorthPoint Plaza, 100 Miller Street",
    "sg:city":"North Sydney",
    "sg:classifiers":[
        {
            "category":"Health Services",
            "subcategory":"Health Practitioner",
            "type":"Services"
        }
    ],
    "sg:phone":"+61 2 9922 2212",
    "sg:postcode":"2060",
    "sg:province":"NSW",
    "sg:tags":[
        "physiotherapist"
    ],
    "sg:website":"http://www.physio4all.com.au",
    "wof:name":"PHYSIO4All",
    "wof:placetype":"venue"
},
  "geometry": {"coordinates":[151.206954956,-33.8375396729],"type":"Point"}
}