{
  "type": "Feature",
  "properties": {
    "addr:full":"Shop 42/ 42 Williams St Bowen QLD 4805",
    "addr:housenumber":"shop 42 / 42",
    "addr:postcode":"4805",
    "addr:street":"Williams St",
    "iso:country":"AU",
    "sg:address":"Shop 42/ 42 Williams St",
    "sg:city":"Bowen",
    "sg:classifiers":[
        {
            "category":"Cafe",
            "type":"Food & Drink"
        }
    ],
    "sg:phone":"+61 7 4786 6841",
    "sg:postcode":"4805",
    "sg:province":"QLD",
    "wof:name":"Jeaneys Magic Menu",
    "wof:placetype":"venue"
},
  "geometry": {"coordinates":[148.24511718799999,-20.014169693],"type":"Point"}
}