{
  "type": "Feature",
  "properties": {
    "addr:full":"Lot 2 Watson St Bendigo VIC 3550",
    "addr:housenumber":"2",
    "addr:postcode":"3550",
    "addr:street":"Watson St",
    "iso:country":"AU",
    "sg:address":"Lot 2 Watson St",
    "sg:city":"Bendigo",
    "sg:classifiers":[
        {
            "category":"Communications",
            "subcategory":"News Services",
            "type":"Services"
        }
    ],
    "sg:phone":"+61 3 5436 1565",
    "sg:postcode":"3550",
    "sg:province":"VIC",
    "sg:tags":[
        "information",
        "tourist",
        "attractions"
    ],
    "wof:name":"Ironbark Riding Centre",
    "wof:placetype":"venue"
},
  "geometry": {"coordinates":[144.25767517099999,-36.7244377136],"type":"Point"}
}