{
  "type": "Feature",
  "properties": {
    "addr:full":"11 Smart St Mall Mandurah WA 6210",
    "addr:housenumber":"11",
    "addr:postcode":"6210",
    "addr:street":"Smart St Mall",
    "iso:country":"AU",
    "sg:address":"11 Smart St",
    "sg:city":"Mall Mandurah",
    "sg:classifiers":[
        {
            "category":"Manufacturing",
            "subcategory":"Textiles",
            "type":"Manufacturing & Wholesale Goods"
        }
    ],
    "sg:phone":"+61 8 9535 7323",
    "sg:postcode":"6210",
    "sg:province":"WA",
    "sg:tags":[
        "knitted",
        "woven",
        "fabric"
    ],
    "wof:name":"Mandurah Fabrics Wool & Craft",
    "wof:placetype":"venue"
},
  "geometry": {"coordinates":[115.720528,-32.533474],"type":"Point"}
}