{
  "type": "Feature",
  "properties": {
    "addr:full":"115 Nepean Hwy Aspendale VIC 3195",
    "addr:housenumber":"115",
    "addr:postcode":"3195",
    "addr:street":"Nepean Hwy",
    "iso:country":"AU",
    "sg:address":"115 Nepean Hwy",
    "sg:city":"Aspendale",
    "sg:classifiers":[
        {
            "category":"Shopping",
            "subcategory":"Antiques",
            "type":"Retail Goods"
        }
    ],
    "sg:phone":"+61 3 9587 5362",
    "sg:postcode":"3195",
    "sg:province":"VIC",
    "wof:name":"Seaspray Rose",
    "wof:placetype":"venue"
},
  "geometry": {"coordinates":[145.10011291500001,-38.0246047974],"type":"Point"}
}