{
  "type": "Feature",
  "properties": {
    "iso:country":"AU",
    "sg:address":"183 Lord St",
    "sg:city":"Perth",
    "sg:classifiers":[
        {
            "category":"Professional",
            "subcategory":"Employment Agencies",
            "type":"Services"
        }
    ],
    "sg:phone":"+61 8 9227 1676",
    "sg:postcode":"6000",
    "sg:province":"WA",
    "sg:tags":[
        "provider",
        "internet"
    ],
    "wof:name":"ICENet",
    "wof:placetype":"venue"
},
  "geometry": {"coordinates":[115.87046814,-31.9480285645],"type":"Point"}
}