{
  "type": "Feature",
  "properties": {
    "addr:full":"Unit 30, 589 Stirling Hwy Cottesloe WA 6011",
    "addr:housenumber":"589",
    "addr:postcode":"6011",
    "addr:street":"Stirling Hwy",
    "iso:country":"AU",
    "sg:address":"Unit 30, 589 Stirling Hwy",
    "sg:city":"Cottesloe",
    "sg:classifiers":[
        {
            "category":"Real Estate",
            "subcategory":"Architect",
            "type":"Services"
        }
    ],
    "sg:phone":"+61 500 555 436",
    "sg:postcode":"6011",
    "sg:province":"WA",
    "wof:name":"Ariane Prevost Architect",
    "wof:placetype":"venue"
},
  "geometry": {"coordinates":[115.761260986,-31.9998416901],"type":"Point"}
}