{
  "type": "Feature",
  "properties": {
    "addr:full":"34 Lincoln St Lindisfarne TAS 7015",
    "addr:housenumber":"34",
    "addr:postcode":"7015",
    "addr:street":"Lincoln St",
    "iso:country":"AU",
    "sg:address":"34 Lincoln St",
    "sg:city":"Lindisfarne",
    "sg:classifiers":[
        {
            "category":"Government",
            "subcategory":"Post Office",
            "type":"Public Place"
        }
    ],
    "sg:phone":"+61 3 6243 4330",
    "sg:postcode":"7015",
    "sg:province":"TAS",
    "sg:tags":[
        "postal"
    ],
    "wof:name":"Australia Post Offices",
    "wof:placetype":"venue"
},
  "geometry": {"coordinates":[147.35269165,-42.8477020264],"type":"Point"}
}