{
  "type": "Feature",
  "properties": {
    "addr:full":"283 Cleveland St Surry Hills NSW 2010",
    "addr:housenumber":"283",
    "addr:postcode":"2010",
    "addr:street":"Cleveland St",
    "iso:country":"AU",
    "sg:address":"283 Cleveland St",
    "sg:city":"Surry Hills",
    "sg:classifiers":[
        {
            "category":"Shopping",
            "subcategory":"Gifts & Souvenirs",
            "type":"Retail Goods"
        }
    ],
    "sg:phone":"+61 2 9310 5500",
    "sg:postcode":"2010",
    "sg:province":"NSW",
    "sg:tags":[
        "shop",
        "supply"
    ],
    "wof:name":"Crystals Of The World",
    "wof:placetype":"venue"
},
  "geometry": {"coordinates":[151.20835876500001,-33.8902397156],"type":"Point"}
}