{
  "type": "Feature",
  "properties": {
    "addr:full":"80 East St Springsure QLD 4722",
    "addr:housenumber":"80",
    "addr:postcode":"4722",
    "addr:street":"East St",
    "iso:country":"AU",
    "sg:address":"80 East St",
    "sg:city":"Springsure",
    "sg:classifiers":[
        {
            "category":"Building & Trades",
            "subcategory":"Construction",
            "type":"Services"
        }
    ],
    "sg:phone":"+61 7 4984 1388",
    "sg:postcode":"4722",
    "sg:province":"QLD",
    "sg:tags":[
        "earth",
        "excavating",
        "moving",
        "contractor"
    ],
    "wof:name":"Mahady & Sons",
    "wof:placetype":"venue"
},
  "geometry": {"coordinates":[148.094864,-24.119244],"type":"Point"}
}