{
  "type": "Feature",
  "properties": {
    "addr:full":"78 Mont Albert Rd Canterbury VIC 3126",
    "addr:housenumber":"78",
    "addr:postcode":"3126",
    "addr:street":"Mont Albert Rd",
    "iso:country":"AU",
    "sg:address":"78 Mont Albert Rd",
    "sg:city":"Canterbury",
    "sg:classifiers":[
        {
            "category":"Health Services",
            "subcategory":"Health Practitioner",
            "type":"Services"
        }
    ],
    "sg:phone":"+61 3 9836 0229",
    "sg:postcode":"3126",
    "sg:province":"VIC",
    "sg:tags":[
        "psychotherapist"
    ],
    "wof:name":"Rotmiler de Zentner Maria-Ines",
    "wof:placetype":"venue"
},
  "geometry": {"coordinates":[145.06687927199999,-37.8168563843],"type":"Point"}
}