{
  "type": "Feature",
  "properties": {
    "addr:full":"62e Fitzroy St Walcha NSW 2354",
    "addr:housenumber":"62e",
    "addr:postcode":"2354",
    "addr:street":"Fitzroy St",
    "iso:country":"AU",
    "sg:address":"62e Fitzroy St",
    "sg:city":"Walcha",
    "sg:classifiers":[
        {
            "category":"Retail",
            "subcategory":"Veterinary Services",
            "type":"Services"
        }
    ],
    "sg:phone":"+61 2 6777 2302",
    "sg:postcode":"2354",
    "sg:province":"NSW",
    "sg:tags":[
        "surgeon"
    ],
    "wof:name":"Walcha Vet Clinic",
    "wof:placetype":"venue"
},
  "geometry": {"coordinates":[151.58522033700001,-30.9838180542],"type":"Point"}
}