{
  "type": "Feature",
  "properties": {
    "addr:full":"8 Kooyong Crt Grahamvale VIC 3631",
    "addr:housenumber":"8",
    "addr:postcode":"3631",
    "addr:street":"Kooyong Crt",
    "iso:country":"AU",
    "sg:address":"8 Kooyong Crt",
    "sg:city":"Grahamvale",
    "sg:classifiers":[
        {
            "category":"Professional",
            "subcategory":"Art Services",
            "type":"Services"
        }
    ],
    "sg:phone":"+61 3 5822 2631",
    "sg:postcode":"3631",
    "sg:province":"VIC",
    "sg:tags":[
        "decorator",
        "painter"
    ],
    "wof:name":"Halsall's Roof Tiling Pty Ltd",
    "wof:placetype":"venue"
},
  "geometry": {"coordinates":[145.44171142600001,-36.3734741211],"type":"Point"}
}