{
  "type": "Feature",
  "properties": {
    "iso:country":"AU",
    "sg:address":"PO Box 735",
    "sg:city":"Moonah",
    "sg:classifiers":[
        {
            "category":"Shopping",
            "subcategory":"Crafts & Fabrics",
            "type":"Retail Goods"
        }
    ],
    "sg:phone":"+61 3 6272 2919",
    "sg:postcode":"7009",
    "sg:province":"TAS",
    "sg:tags":[
        "adhesive"
    ],
    "wof:name":"Pak Supplies",
    "wof:placetype":"venue"
},
  "geometry": {"coordinates":[147.295455933,-42.8458518982],"type":"Point"}
}