{
  "type": "Feature",
  "properties": {
    "addr:full":"PO Box 121 Belfield NSW 2191",
    "addr:postcode":"2191",
    "iso:country":"AU",
    "sg:address":"PO Box 121",
    "sg:city":"Belfield",
    "sg:classifiers":[
        {
            "category":"Professional",
            "subcategory":"Detective & Security Services",
            "type":"Services"
        }
    ],
    "sg:phone":"+61 1300 306 090",
    "sg:postcode":"2191",
    "sg:province":"NSW",
    "sg:tags":[
        "consultant",
        "system"
    ],
    "wof:name":"Ad-Tech Security Pty Ltd.",
    "wof:placetype":"venue"
},
  "geometry": {"coordinates":[151.08616599999999,-33.90453],"type":"Point"}
}