{
  "type": "Feature",
  "properties": {
    "addr:full":"77 East St Narrandera NSW 2700",
    "addr:housenumber":"77",
    "addr:postcode":"2700",
    "addr:street":"East St",
    "iso:country":"AU",
    "sg:address":"77 East St",
    "sg:city":"Narrandera",
    "sg:classifiers":[
        {
            "category":"Travel",
            "subcategory":"Hotels & Motels",
            "type":"Entertainment"
        }
    ],
    "sg:phone":"+61 2 6959 2042",
    "sg:postcode":"2700",
    "sg:province":"NSW",
    "sg:tags":[
        "accommodation"
    ],
    "wof:name":"Charles Sturt Hotel",
    "wof:placetype":"venue"
},
  "geometry": {"coordinates":[146.55364990199999,-34.7446403503],"type":"Point"}
}