{
  "type": "Feature",
  "properties": {
    "iso:country":"AU",
    "sg:address":"1373 Logan Rd",
    "sg:city":"Mt Gravatt",
    "sg:classifiers":[
        {
            "category":"Cafe",
            "type":"Food & Drink"
        }
    ],
    "sg:phone":"+61 7 3343 8344",
    "sg:postcode":"4122",
    "sg:province":"QLD",
    "wof:name":"MJ&#039;S Cafe",
    "wof:placetype":"venue"
},
  "geometry": {"coordinates":[153.07420349099999,-27.5328178406],"type":"Point"}
}