{
  "type": "Feature",
  "properties": {
    "iso:country":"AU",
    "sg:address":"20 McGowan St",
    "sg:city":"Pooraka",
    "sg:classifiers":[
        {
            "category":"Wholesale",
            "subcategory":"Furniture",
            "type":"Manufacturing & Wholesale Goods"
        }
    ],
    "sg:phone":"+61 8 8262 1277",
    "sg:postcode":"5095",
    "sg:province":"SA",
    "sg:tags":[
        "wholesaler",
        "mfrs"
    ],
    "wof:name":"Lanfranco Furniture Int.",
    "wof:placetype":"venue"
},
  "geometry": {"coordinates":[138.63490295400001,-34.8183898926],"type":"Point"}
}