{
  "type": "Feature",
  "properties": {
    "iso:country":"AU",
    "sg:address":"Corio Village Shopng Centre",
    "sg:city":"Corio",
    "sg:classifiers":[
        {
            "category":"Banks & Credit Unions",
            "subcategory":"Bank",
            "type":"Services"
        }
    ],
    "sg:phone":"+61 13 20 32",
    "sg:postcode":"3214",
    "sg:province":"VIC",
    "wof:name":"Westpac",
    "wof:placetype":"venue"
},
  "geometry": {"coordinates":[144.35798645,-38.0738639832],"type":"Point"}
}