{
  "type": "Feature",
  "properties": {
    "iso:country":"AU",
    "sg:address":"Old Bull Creek Rd",
    "sg:city":"Strathalbyn",
    "sg:classifiers":[
        {
            "category":"Building & Trades",
            "subcategory":"Landscaping Services",
            "type":"Services"
        }
    ],
    "sg:phone":"+61 8 8536 6062",
    "sg:postcode":"5255",
    "sg:province":"SA",
    "sg:tags":[
        "grazier"
    ],
    "wof:name":"Montello Pty Ltd",
    "wof:placetype":"venue"
},
  "geometry": {"coordinates":[138.885696411,-35.2553100586],"type":"Point"}
}