{
  "type": "Feature",
  "properties": {
    "addr:full":"Shop 3 78 Pacific Hwy Swansea NSW 2281",
    "addr:housenumber":"shop;78",
    "addr:postcode":"2281",
    "addr:street":"Pacific Hwy",
    "iso:country":"AU",
    "sg:address":"Shop 3 78 Pacific Hwy",
    "sg:city":"Swansea",
    "sg:classifiers":[
        {
            "category":"Professional",
            "subcategory":"Testing Lab",
            "type":"Services"
        }
    ],
    "sg:phone":"+61 2 4972 1534",
    "sg:postcode":"2281",
    "sg:province":"NSW",
    "sg:tags":[
        "inspection"
    ],
    "wof:name":"Lake Macquarie Test&#039;n&#039;Tag",
    "wof:placetype":"venue"
},
  "geometry": {"coordinates":[151.63783264200001,-33.0905990601],"type":"Point"}
}