{
  "type": "Feature",
  "properties": {
    "addr:full":"Cnr Arthur Hwy & Bay St Dunalley TAS 7177",
    "addr:postcode":"7177",
    "addr:street":"Cnr Arthur Hwy & Bay St",
    "iso:country":"AU",
    "sg:address":"Cnr Arthur Hwy & Bay St",
    "sg:city":"Dunalley",
    "sg:classifiers":[
        {
            "category":"Shopping",
            "subcategory":"Bicycles & Sporting Goods",
            "type":"Retail Goods"
        }
    ],
    "sg:phone":"+61 1800 736 088",
    "sg:postcode":"7177",
    "sg:province":"TAS",
    "sg:tags":[
        "trampoline"
    ],
    "wof:name":"Davis Canvas",
    "wof:placetype":"venue"
},
  "geometry": {"coordinates":[147.80749499999999,-42.889317],"type":"Point"}
}