{
  "type": "Feature",
  "properties": {
    "addr:full":"Cnr Alice & Bazaar Sts Maryborough QLD 4650",
    "addr:postcode":"4650",
    "addr:street":"Sts",
    "iso:country":"AU",
    "sg:address":"Cnr Alice & Bazaar Sts",
    "sg:city":"Maryborough",
    "sg:classifiers":[
        {
            "category":"Government",
            "subcategory":"Court House",
            "type":"Public Place"
        }
    ],
    "sg:phone":"+61 7 4122 2144",
    "sg:postcode":"4650",
    "sg:province":"QLD",
    "sg:tags":[
        "personal",
        "marriage",
        "family",
        "counselling"
    ],
    "wof:name":"Lifeline Fraser District",
    "wof:placetype":"venue"
},
  "geometry": {"coordinates":[152.70062300000001,-25.541597],"type":"Point"}
}