{
  "type": "Feature",
  "properties": {
    "addr:full":"1007 Stanley St East East Brisbane QLD 4169",
    "addr:housenumber":"1007",
    "addr:postcode":"4169",
    "addr:street":"Stanley St East",
    "iso:country":"AU",
    "sg:address":"1007 Stanley St",
    "sg:city":"East East Brisbane",
    "sg:classifiers":[
        {
            "category":"Wholesale",
            "subcategory":"Machinery & Supplies",
            "type":"Manufacturing & Wholesale Goods"
        }
    ],
    "sg:phone":"+61 7 3286 1040",
    "sg:postcode":"4169",
    "sg:province":"QLD",
    "sg:tags":[
        "instrument",
        "scientific"
    ],
    "wof:name":"Radtronics Pty Ltd",
    "wof:placetype":"venue"
},
  "geometry": {"coordinates":[153.048660278,-27.4883213043],"type":"Point"}
}