{
  "type": "Feature",
  "properties": {
    "addr:full":"275 Burwood Hwy Burwood VIC 3125",
    "addr:housenumber":"275",
    "addr:postcode":"3125",
    "addr:street":"Burwood Hwy",
    "iso:country":"AU",
    "sg:address":"275 Burwood Hwy",
    "sg:city":"Burwood",
    "sg:classifiers":[
        {
            "category":"Personal",
            "type":"Services"
        }
    ],
    "sg:phone":"+61 3 9887 7777",
    "sg:postcode":"3125",
    "sg:province":"VIC",
    "sg:tags":[
        "reducing",
        "treatment",
        "weight"
    ],
    "wof:name":"Medical Weight Control",
    "wof:placetype":"venue"
},
  "geometry": {"coordinates":[145.158004761,-37.8532295227],"type":"Point"}
}