{
  "type": "Feature",
  "properties": {
    "iso:country":"AU",
    "sg:address":"12 Honeysuckle Drv",
    "sg:city":"Suffolk Park",
    "sg:classifiers":[
        {
            "category":"Building & Trades",
            "subcategory":"Construction",
            "type":"Services"
        }
    ],
    "sg:phone":"+61 2 6685 4626",
    "sg:postcode":"2481",
    "sg:province":"NSW",
    "sg:tags":[
        "earth",
        "excavating",
        "moving",
        "contractor"
    ],
    "wof:name":"Byron Bay Bobcat",
    "wof:placetype":"venue"
},
  "geometry": {"coordinates":[153.60786438,-28.6888008118],"type":"Point"}
}