{
  "type": "Feature",
  "properties": {
    "iso:country":"AU",
    "sg:address":"Wards Rd",
    "sg:city":"Dumbleyung",
    "sg:classifiers":[
        {
            "category":"Farming",
            "subcategory":"Farm",
            "type":"Manufacturing & Wholesale Goods"
        }
    ],
    "sg:phone":"+61 8 9863 4210",
    "sg:postcode":"6350",
    "sg:province":"WA",
    "sg:tags":[
        "farmer"
    ],
    "wof:name":"Bairstow P & C",
    "wof:placetype":"venue"
},
  "geometry": {"coordinates":[117.72197,-33.270573],"type":"Point"}
}