{
  "type": "Feature",
  "properties": {
    "addr:full":"103 Murray St Gawler SA 5118",
    "addr:housenumber":"103",
    "addr:postcode":"5118",
    "addr:street":"Murray St",
    "iso:country":"AU",
    "sg:address":"103 Murray St",
    "sg:city":"Gawler",
    "sg:classifiers":[
        {
            "category":"Insurance",
            "subcategory":"Health Insurance",
            "type":"Services"
        }
    ],
    "sg:phone":"+61 8 8523 1333",
    "sg:postcode":"5118",
    "sg:province":"SA",
    "wof:name":"Medibank Private",
    "wof:placetype":"venue"
},
  "geometry": {"coordinates":[138.74923699999999,-34.596664],"type":"Point"}
}