{
  "type": "Feature",
  "properties": {
    "addr:full":"277 - 289 Woodpark Rd Smithfield NSW 2164",
    "addr:housenumber":"289",
    "addr:postcode":"2164",
    "addr:street":"Woodpark Rd",
    "iso:country":"AU",
    "sg:address":"277 - 289 Woodpark Rd",
    "sg:city":"Smithfield",
    "sg:classifiers":[
        {
            "category":"Social Services",
            "subcategory":"Retirement Home",
            "type":"Services"
        }
    ],
    "sg:phone":"+61 2 8784 8555",
    "sg:postcode":"2164",
    "sg:province":"NSW",
    "sg:tags":[
        "environmental",
        "consultant",
        "pollution"
    ],
    "wof:name":"ALS Laboratory Group",
    "wof:placetype":"venue"
},
  "geometry": {"coordinates":[150.935302734,-33.8371582031],"type":"Point"}
}