{
  "type": "Feature",
  "properties": {
    "addr:full":"7/ 18-22 First Ave Maroochydore QLD 4558",
    "addr:housenumber":"/ 18-22",
    "addr:postcode":"4558",
    "addr:street":"First Ave",
    "iso:country":"AU",
    "sg:address":"7/ 18-22 First Ave",
    "sg:city":"Maroochydore",
    "sg:classifiers":[
        {
            "category":"Professional",
            "subcategory":"Employment Agencies",
            "type":"Services"
        }
    ],
    "sg:phone":"+61 7 5430 0700",
    "sg:postcode":"4558",
    "sg:province":"QLD",
    "wof:name":"Centacare Employment Group",
    "wof:placetype":"venue"
},
  "geometry": {"coordinates":[153.09312439000001,-26.6555900574],"type":"Point"}
}