{
  "type": "Feature",
  "properties": {
    "iso:country":"AU",
    "sg:address":"1071 Mcmillans Rd",
    "sg:city":"Knuckeys Lagoon",
    "sg:classifiers":[
        {
            "category":"Building & Trades",
            "subcategory":"Construction",
            "type":"Services"
        }
    ],
    "sg:phone":"+61 8 8947 3203",
    "sg:postcode":"0852",
    "sg:province":"NT",
    "sg:tags":[
        "contractor"
    ],
    "wof:name":"Ironbark Contracting Pty Ltd",
    "wof:placetype":"venue"
},
  "geometry": {"coordinates":[130.94683800000001,-12.425249],"type":"Point"}
}