{
  "type": "Feature",
  "properties": {
    "addr:full":"234 Torrens Rd Croydon Park SA 5008",
    "addr:housenumber":"234",
    "addr:postcode":"5008",
    "addr:street":"Torrens Rd",
    "iso:country":"AU",
    "sg:address":"234 Torrens Rd",
    "sg:city":"Croydon Park",
    "sg:classifiers":[
        {
            "category":"Retail",
            "subcategory":"Veterinary Services",
            "type":"Services"
        }
    ],
    "sg:phone":"+61 8 8346 9666",
    "sg:postcode":"5008",
    "sg:province":"SA",
    "sg:tags":[
        "surgeon"
    ],
    "wof:name":"Torrens Road Veterinary Clinic",
    "wof:placetype":"venue"
},
  "geometry": {"coordinates":[138.56300400000001,-34.883858],"type":"Point"}
}