{
  "type": "Feature",
  "properties": {
    "addr:full":"South St Miriam Vale QLD 4677",
    "addr:postcode":"4677",
    "addr:street":"South St",
    "iso:country":"AU",
    "sg:address":"South St",
    "sg:city":"Miriam Vale",
    "sg:classifiers":[
        {
            "category":"Autos & Motor Vehicles",
            "subcategory":"Fuel & Gas Station",
            "type":"Retail Goods"
        }
    ],
    "sg:phone":"+61 7 4974 5206",
    "sg:postcode":"4677",
    "sg:province":"QLD",
    "wof:name":"Miriam Vale Garage",
    "wof:placetype":"venue"
},
  "geometry": {"coordinates":[151.563095,-24.330128],"type":"Point"}
}