{
  "type": "Feature",
  "properties": {
    "iso:country":"AU",
    "sg:address":"3-5 Attunga Drv",
    "sg:city":"Torquay",
    "sg:classifiers":[
        {
            "category":"Social Services",
            "subcategory":"Child Care",
            "type":"Services"
        }
    ],
    "sg:phone":"+61 3 5261 9822",
    "sg:postcode":"3228",
    "sg:province":"VIC",
    "wof:name":"Kids Clubs Torquay Pty Ltd",
    "wof:placetype":"venue"
},
  "geometry": {"coordinates":[144.313889,-38.325436],"type":"Point"}
}