{
  "type": "Feature",
  "properties": {
    "iso:country":"AU",
    "sg:address":"Unit B/ 34 Barnett Ave",
    "sg:city":"Glynde",
    "sg:classifiers":[
        {
            "category":"Farming",
            "subcategory":"Fish & Marine Products",
            "type":"Manufacturing & Wholesale Goods"
        }
    ],
    "sg:phone":"+61 8 8337 7702",
    "sg:postcode":"5070",
    "sg:province":"SA",
    "sg:tags":[
        "chemical",
        "supplier"
    ],
    "wof:name":"Dacini Agencies",
    "wof:placetype":"venue"
},
  "geometry": {"coordinates":[138.65434265100001,-34.8939781189],"type":"Point"}
}