{
  "type": "Feature",
  "properties": {
    "addr:full":"134 Marshall St Goondiwindi QLD 4390",
    "addr:housenumber":"134",
    "addr:postcode":"4390",
    "addr:street":"Marshall St",
    "iso:country":"AU",
    "sg:address":"134 Marshall St",
    "sg:city":"Goondiwindi",
    "sg:classifiers":[
        {
            "category":"Travel",
            "subcategory":"Hotels & Motels",
            "type":"Entertainment"
        }
    ],
    "sg:phone":"+61 7 4671 2011",
    "sg:postcode":"4390",
    "sg:province":"QLD",
    "wof:name":"Queensland Hotel",
    "wof:placetype":"venue"
},
  "geometry": {"coordinates":[150.310012817,-28.5474853516],"type":"Point"}
}