{
  "type": "Feature",
  "properties": {
    "addr:full":"9 Partridge Ave Hoxton Park NSW 2171",
    "addr:housenumber":"9",
    "addr:postcode":"2171",
    "addr:street":"Partridge Ave",
    "iso:country":"AU",
    "sg:address":"9 Partridge Ave",
    "sg:city":"Hoxton Park",
    "sg:classifiers":[
        {
            "category":"Home & Garden",
            "subcategory":"Building Materials",
            "type":"Retail Goods"
        }
    ],
    "sg:phone":"+61 2 9607 5528",
    "sg:postcode":"2171",
    "sg:province":"NSW",
    "sg:tags":[
        "lawn",
        "cutting",
        "maintenance"
    ],
    "wof:name":"Industrial Lawn Service",
    "wof:placetype":"venue"
},
  "geometry": {"coordinates":[150.866165161,-33.9166488647],"type":"Point"}
}