{
  "type": "Feature",
  "properties": {
    "addr:full":"Shop 2/ 18 Tallarook St Seymour VIC 3660",
    "addr:housenumber":"shop 2 / 18",
    "addr:postcode":"3660",
    "addr:street":"Tallarook St",
    "iso:country":"AU",
    "sg:address":"Shop 2/ 18 Tallarook St",
    "sg:city":"Seymour",
    "sg:classifiers":[
        {
            "category":"Fast Food",
            "type":"Food & Drink"
        }
    ],
    "sg:phone":"+61 3 5799 0322",
    "sg:postcode":"3660",
    "sg:province":"VIC",
    "sg:tags":[
        "away",
        "take"
    ],
    "wof:name":"King Asian Fast Food",
    "wof:placetype":"venue"
},
  "geometry": {"coordinates":[145.13378906200001,-37.0247077942],"type":"Point"}
}