{
  "type": "Feature",
  "properties": {
    "iso:country":"AU",
    "sg:address":"11 Waterview St",
    "sg:city":"Oyster Bay",
    "sg:classifiers":[
        {
            "category":"Utilities",
            "subcategory":"Electric",
            "type":"Services"
        }
    ],
    "sg:phone":"+61 418 211 245",
    "sg:postcode":"2225",
    "sg:province":"NSW",
    "sg:tags":[
        "electrical",
        "contractor"
    ],
    "wof:name":"Michael Grant Pty Ltd",
    "wof:placetype":"venue"
},
  "geometry": {"coordinates":[151.07986450199999,-34.0065689087],"type":"Point"}
}