{
  "type": "Feature",
  "properties": {
    "iso:country":"AU",
    "sg:address":"161 Stony Rise Rd",
    "sg:city":"Devonport",
    "sg:classifiers":[
        {
            "category":"Retail",
            "subcategory":"Auto Rental",
            "type":"Services"
        }
    ],
    "sg:phone":"+61 3 6424 9112",
    "sg:postcode":"7310",
    "sg:province":"TAS",
    "sg:tags":[
        "car",
        "hire",
        "minibus"
    ],
    "wof:name":"Phoenix Minibus Rentals",
    "wof:placetype":"venue"
},
  "geometry": {"coordinates":[146.32943725600001,-41.1916770935],"type":"Point"}
}