{
  "type": "Feature",
  "properties": {
    "iso:country":"AU",
    "sg:address":"13 Maxim Pl",
    "sg:city":"St Marys",
    "sg:classifiers":[
        {
            "category":"Home & Garden",
            "subcategory":"Building Materials",
            "type":"Retail Goods"
        }
    ],
    "sg:phone":"+61 2 9673 2044",
    "sg:postcode":"2760",
    "sg:province":"NSW",
    "sg:tags":[
        "balustrading"
    ],
    "wof:name":"Wor Engineering",
    "wof:placetype":"venue"
},
  "geometry": {"coordinates":[150.77226257300001,-33.7538146973],"type":"Point"}
}