{
  "type": "Feature",
  "properties": {
    "addr:full":"319 Galston Rd Galston NSW 2159",
    "addr:housenumber":"319",
    "addr:postcode":"2159",
    "addr:street":"Galston Rd",
    "iso:country":"AU",
    "sg:address":"319 Galston Rd",
    "sg:city":"Galston",
    "sg:classifiers":[
        {
            "category":"Professional",
            "subcategory":"Engineering",
            "type":"Services"
        }
    ],
    "sg:phone":"+61 2 9653 1373",
    "sg:postcode":"2159",
    "sg:province":"NSW",
    "sg:tags":[
        "engineer"
    ],
    "wof:name":"Morton Engineering",
    "wof:placetype":"venue"
},
  "geometry": {"coordinates":[151.052642822,-33.6541137695],"type":"Point"}
}