{
  "type": "Feature",
  "properties": {
    "addr:full":"94 Bottlebrush Drv Glenning Valley NSW 2261",
    "addr:housenumber":"94",
    "addr:postcode":"2261",
    "addr:street":"Bottlebrush Drv",
    "iso:country":"AU",
    "sg:address":"94 Bottlebrush Drv",
    "sg:city":"Glenning Valley",
    "sg:classifiers":[
        {
            "category":"Arts & Performance",
            "subcategory":"Dance",
            "type":"Entertainment"
        }
    ],
    "sg:phone":"+61 419 436 024",
    "sg:postcode":"2261",
    "sg:province":"NSW",
    "sg:tags":[
        "theatrical",
        "ballet",
        "tuition"
    ],
    "wof:name":"CoastQuest Championships",
    "wof:placetype":"venue"
},
  "geometry": {"coordinates":[151.43014500000001,-33.334145],"type":"Point"}
}