{
  "type": "Feature",
  "properties": {
    "addr:full":"76 Hemmings St Dandenong VIC 3175",
    "addr:housenumber":"76",
    "addr:postcode":"3175",
    "addr:street":"Hemmings St",
    "iso:country":"AU",
    "sg:address":"76 Hemmings St",
    "sg:city":"Dandenong",
    "sg:classifiers":[
        {
            "category":"Food & Beverages",
            "subcategory":"Bakery",
            "type":"Retail Goods"
        }
    ],
    "sg:phone":"+61 3 9791 6383",
    "sg:postcode":"3175",
    "sg:province":"VIC",
    "sg:tags":[
        "baker"
    ],
    "wof:name":"LM Fresh Bread",
    "wof:placetype":"venue"
},
  "geometry": {"coordinates":[145.20274352999999,-37.9826431274],"type":"Point"}
}