{
  "type": "Feature",
  "properties": {
    "addr:full":"31 Stringybark Pl Alfords Point NSW 2234",
    "addr:housenumber":"31",
    "addr:postcode":"2234",
    "addr:street":"Stringybark Pl",
    "iso:country":"AU",
    "sg:address":"31 Stringybark Pl",
    "sg:city":"Alfords Point",
    "sg:classifiers":[
        {
            "category":"Building & Trades",
            "subcategory":"Construction",
            "type":"Services"
        }
    ],
    "sg:phone":"+61 418 605 884",
    "sg:postcode":"2234",
    "sg:province":"NSW",
    "sg:tags":[
        "home",
        "air conditioning"
    ],
    "wof:name":"Lion Airconditioning Pty Ltd",
    "wof:placetype":"venue"
},
  "geometry": {"coordinates":[151.029022217,-33.9804992676],"type":"Point"}
}