{
  "type": "Feature",
  "properties": {
    "iso:country":"AU",
    "sg:address":"24 Surfers Ave",
    "sg:city":"Mermaid Waters",
    "sg:classifiers":[
        {
            "category":"Personal",
            "type":"Services"
        }
    ],
    "sg:phone":"+61 7 5572 5203",
    "sg:postcode":"4218",
    "sg:province":"QLD",
    "sg:tags":[
        "gift"
    ],
    "wof:name":"Gold Coast Florist.com.au",
    "wof:placetype":"venue"
},
  "geometry": {"coordinates":[153.43121337900001,-28.0394954681],"type":"Point"}
}