{
  "type": "Feature",
  "properties": {
    "addr:full":"Factory 1/ 28 Peninsula Blv Seaford VIC 3198",
    "addr:housenumber":"/ 28",
    "addr:postcode":"3198",
    "addr:street":"Peninsula Blv",
    "iso:country":"AU",
    "sg:address":"Factory 1/ 28",
    "sg:city":"Peninsula Blv Seaford",
    "sg:classifiers":[
        {
            "category":"Utilities",
            "subcategory":"Electric",
            "type":"Services"
        }
    ],
    "sg:phone":"+61 3 9785 3825",
    "sg:postcode":"3198",
    "sg:province":"VIC",
    "sg:tags":[
        "electrical",
        "contractor"
    ],
    "wof:name":"Dinnage Electrical",
    "wof:placetype":"venue"
},
  "geometry": {"coordinates":[145.13816833499999,-38.1150588989],"type":"Point"}
}