{
  "type": "Feature",
  "properties": {
    "addr:full":"192 Anzac Pde Kensington NSW 2033",
    "addr:housenumber":"192",
    "addr:postcode":"2033",
    "addr:street":"Anzac Pde",
    "iso:country":"AU",
    "sg:address":"192 Anzac Pde",
    "sg:city":"Kensington",
    "sg:classifiers":[
        {
            "category":"Health Services",
            "subcategory":"Dentist",
            "type":"Services"
        }
    ],
    "sg:phone":"+61 2 9663 2062",
    "sg:postcode":"2033",
    "sg:province":"NSW",
    "wof:name":"Kipriotis George Dr",
    "wof:placetype":"venue"
},
  "geometry": {"coordinates":[151.223511,-33.910477],"type":"Point"}
}