{
  "type": "Feature",
  "properties": {
    "addr:full":"6 Standen St Murray Bridge SA 5253",
    "addr:housenumber":"6",
    "addr:postcode":"5253",
    "addr:street":"Standen St",
    "iso:country":"AU",
    "sg:address":"6 Standen St",
    "sg:city":"Murray Bridge",
    "sg:classifiers":[
        {
            "category":"Health Services",
            "subcategory":"Dentist",
            "type":"Services"
        }
    ],
    "sg:phone":"+61 8 8532 5700",
    "sg:postcode":"5253",
    "sg:province":"SA",
    "sg:tags":[
        "state",
        "orthodontist",
        "qld",
        "exc"
    ],
    "wof:name":"Barber Tony F, Burnett Guy J, Tindall Andrew, Farrer Steven & Parlange L. Mauree",
    "wof:placetype":"venue"
},
  "geometry": {"coordinates":[139.273193359,-35.1208152771],"type":"Point"}
}