{
  "type": "Feature",
  "properties": {
    "iso:country":"AU",
    "sg:address":"259 Darby St",
    "sg:city":"Cooks Hill",
    "sg:classifiers":[
        {
            "category":"Deli",
            "type":"Food & Drink"
        }
    ],
    "sg:phone":"+61 2 4929 4630",
    "sg:postcode":"2300",
    "sg:province":"NSW",
    "sg:tags":[
        "delicatessen"
    ],
    "wof:name":"Darby St Sandwich & Deli",
    "wof:placetype":"venue"
},
  "geometry": {"coordinates":[151.767578,-32.935707],"type":"Point"}
}