{
  "type": "Feature",
  "properties": {
    "addr:full":"Unit 4/ 31 Ern Harley Drv Burleigh Heads QLD 4220",
    "addr:postcode":"4220",
    "addr:street":"31 Ern Harley Drv",
    "iso:country":"AU",
    "sg:address":"Unit 4/ 31 Ern Harley Drv",
    "sg:city":"Burleigh Heads",
    "sg:classifiers":[
        {
            "category":"Home & Garden",
            "subcategory":"Building Materials",
            "type":"Retail Goods"
        }
    ],
    "sg:phone":"+61 7 5593 6111",
    "sg:postcode":"4220",
    "sg:province":"QLD",
    "sg:tags":[
        "balustrading"
    ],
    "wof:name":"Designa Iron",
    "wof:placetype":"venue"
},
  "geometry": {"coordinates":[153.414886475,-28.1025447845],"type":"Point"}
}