{
  "type": "Feature",
  "properties": {
    "iso:country":"AU",
    "sg:address":"378 New Canterbury Rd",
    "sg:city":"Dulwich Hill",
    "sg:classifiers":[
        {
            "category":"Food & Beverages",
            "subcategory":"Bakery",
            "type":"Retail Goods"
        }
    ],
    "sg:phone":"+61 2 9572 8444",
    "sg:postcode":"2203",
    "sg:province":"NSW",
    "sg:tags":[
        "cake",
        "shop",
        "pastry"
    ],
    "wof:name":"Cake Bazaar",
    "wof:placetype":"venue"
},
  "geometry": {"coordinates":[151.136642,-33.905651],"type":"Point"}
}