{
  "type": "Feature",
  "properties": {
    "iso:country":"AU",
    "sg:address":"24 Production Ave",
    "sg:city":"Kogarah",
    "sg:classifiers":[
        {
            "category":"Building & Trades",
            "subcategory":"Construction",
            "type":"Services"
        }
    ],
    "sg:phone":"+61 2 9553 8042",
    "sg:postcode":"2217",
    "sg:province":"NSW",
    "sg:tags":[
        "joinery"
    ],
    "wof:name":"A Force Constructions",
    "wof:placetype":"venue"
},
  "geometry": {"coordinates":[151.13885500000001,-33.978413],"type":"Point"}
}