{
  "type": "Feature",
  "properties": {
    "addr:full":"11 Maria St Thebarton SA 5031",
    "addr:housenumber":"11",
    "addr:postcode":"5031",
    "addr:street":"Maria St",
    "iso:country":"AU",
    "sg:address":"11 Maria St",
    "sg:city":"Thebarton",
    "sg:classifiers":[
        {
            "category":"Utilities",
            "subcategory":"Water",
            "type":"Services"
        }
    ],
    "sg:phone":"+61 1800 153 351",
    "sg:postcode":"5031",
    "sg:province":"SA",
    "sg:tags":[
        "hot",
        "system"
    ],
    "wof:name":"Stiebel Eltron (Aust) Pty Ltd",
    "wof:placetype":"venue"
},
  "geometry": {"coordinates":[138.578201294,-34.9194068909],"type":"Point"}
}