{
  "type": "Feature",
  "properties": {
    "addr:full":"4 Mortimer St Kalbarri WA 6536",
    "addr:housenumber":"4",
    "addr:postcode":"6536",
    "addr:street":"Mortimer St",
    "iso:country":"AU",
    "sg:address":"4 Mortimer St",
    "sg:city":"Kalbarri",
    "sg:classifiers":[
        {
            "category":"Utilities",
            "subcategory":"Electric",
            "type":"Services"
        }
    ],
    "sg:phone":"+61 417 966 369",
    "sg:postcode":"6536",
    "sg:province":"WA",
    "sg:tags":[
        "electrical",
        "contractor"
    ],
    "wof:name":"Mark Armstrong Electrical",
    "wof:placetype":"venue"
},
  "geometry": {"coordinates":[114.169090271,-27.7024688721],"type":"Point"}
}