{
  "type": "Feature",
  "properties": {
    "iso:country":"AU",
    "sg:address":"8/ 85 Pound Ave",
    "sg:city":"Davidson",
    "sg:classifiers":[
        {
            "category":"Personal",
            "subcategory":"Beauty Salon",
            "type":"Services"
        }
    ],
    "sg:phone":"+61 2 9451 6026",
    "sg:postcode":"2085",
    "sg:province":"NSW",
    "sg:tags":[
        "hairdresser"
    ],
    "wof:name":"Hair Clip",
    "wof:placetype":"venue"
},
  "geometry": {"coordinates":[151.201705933,-33.7441101074],"type":"Point"}
}