{
  "type": "Feature",
  "properties": {
    "iso:country":"AU",
    "sg:address":"200d Beechworth Rd",
    "sg:city":"Wodonga",
    "sg:classifiers":[
        {
            "category":"Personal",
            "subcategory":"Beauty Salon",
            "type":"Services"
        }
    ],
    "sg:phone":"+61 2 6024 7700",
    "sg:postcode":"3690",
    "sg:province":"VIC",
    "sg:tags":[
        "hairdresser"
    ],
    "wof:name":"La Coupe Hair Studio",
    "wof:placetype":"venue"
},
  "geometry": {"coordinates":[146.888183594,-36.1257514954],"type":"Point"}
}