{
  "type": "Feature",
  "properties": {
    "addr:full":"2 Cressall Rd Balcatta WA 6021",
    "addr:housenumber":"2",
    "addr:postcode":"6021",
    "addr:street":"Cressall Rd",
    "iso:country":"AU",
    "sg:address":"2 Cressall Rd",
    "sg:city":"Balcatta",
    "sg:classifiers":[
        {
            "category":"Building & Trades",
            "subcategory":"Construction",
            "type":"Services"
        }
    ],
    "sg:phone":"+61 8 9240 1999",
    "sg:postcode":"6021",
    "sg:province":"WA",
    "sg:tags":[
        "contractor"
    ],
    "wof:name":"West-Ville Homes Pty Ltd",
    "wof:placetype":"venue"
},
  "geometry": {"coordinates":[115.810722351,-31.8643302917],"type":"Point"}
}