{
  "type": "Feature",
  "properties": {
    "addr:full":"3 Effex Crt Strathdale VIC 3550",
    "addr:housenumber":"3",
    "addr:postcode":"3550",
    "addr:street":"Effex Crt",
    "iso:country":"AU",
    "sg:address":"3 Effex Crt",
    "sg:city":"Strathdale",
    "sg:classifiers":[
        {
            "category":"Professional",
            "subcategory":"Computer Services",
            "type":"Services"
        }
    ],
    "sg:phone":"+61 418 389 200",
    "sg:postcode":"3550",
    "sg:province":"VIC",
    "sg:tags":[
        "package",
        "software"
    ],
    "wof:name":"Carpac",
    "wof:placetype":"venue"
},
  "geometry": {"coordinates":[144.31741332999999,-36.7604293823],"type":"Point"}
}