{
  "type": "Feature",
  "properties": {
    "addr:full":"Shop 2/ 362a Pakington St Newtown VIC 3220",
    "addr:housenumber":"shop 2 / 362a",
    "addr:postcode":"3220",
    "addr:street":"Pakington St",
    "iso:country":"AU",
    "sg:address":"Shop 2/ 362a Pakington St",
    "sg:city":"Newtown",
    "sg:classifiers":[
        {
            "category":"Personal",
            "subcategory":"Beauty Salon",
            "type":"Services"
        }
    ],
    "sg:phone":"+61 3 5222 6080",
    "sg:postcode":"3220",
    "sg:province":"VIC",
    "sg:tags":[
        "hairdresser"
    ],
    "wof:name":"Strand On Pako Hair & Beauty",
    "wof:placetype":"venue"
},
  "geometry": {"coordinates":[144.34509299999999,-38.158497],"type":"Point"}
}