{
  "type": "Feature",
  "properties": {
    "addr:full":"46 Ramsey St Rochester VIC 3561",
    "addr:housenumber":"46",
    "addr:postcode":"3561",
    "addr:street":"Ramsey St",
    "iso:country":"AU",
    "sg:address":"46 Ramsey St",
    "sg:city":"Rochester",
    "sg:classifiers":[
        {
            "category":"Retail",
            "subcategory":"Auto Repair",
            "type":"Services"
        }
    ],
    "sg:phone":"+61 3 5484 2484",
    "sg:postcode":"3561",
    "sg:province":"VIC",
    "sg:tags":[
        "muffler",
        "exhaust",
        "system"
    ],
    "wof:name":"Williams Exhaust & Spare Parts",
    "wof:placetype":"venue"
},
  "geometry": {"coordinates":[144.69915771500001,-36.3596496582],"type":"Point"}
}