{
  "type": "Feature",
  "properties": {
    "addr:full":"Lot 5 Robson St null QLD 4019",
    "addr:housenumber":"5",
    "addr:postcode":"4019",
    "addr:street":"Robson St",
    "iso:country":"AU",
    "sg:address":"Lot 5 Robson St",
    "sg:city":"null",
    "sg:phone":"+61 7 3889 5300",
    "sg:postcode":"4019",
    "sg:province":"QLD",
    "wof:name":"Polyworld",
    "wof:placetype":"venue"
},
  "geometry": {"coordinates":[153.076904297,-27.2389183044],"type":"Point"}
}