{
  "type": "Feature",
  "properties": {
    "iso:country":"AU",
    "sg:address":"415 High St",
    "sg:city":"Lalor",
    "sg:classifiers":[
        {
            "category":"Social Services",
            "subcategory":"Child Care",
            "type":"Services"
        }
    ],
    "sg:phone":"+61 3 9464 0323",
    "sg:postcode":"3075",
    "sg:province":"VIC",
    "wof:name":"Lalor Childcare Centre",
    "wof:placetype":"venue"
},
  "geometry": {"coordinates":[145.002243042,-37.8529205322],"type":"Point"}
}