{
  "type": "Feature",
  "properties": {
    "addr:full":"12 Oakern St Mt Waverley VIC 3149",
    "addr:housenumber":"12",
    "addr:postcode":"3149",
    "addr:street":"Oakern St Mt",
    "iso:country":"AU",
    "sg:address":"12 Oakern St",
    "sg:city":"Mt Waverley",
    "sg:classifiers":[
        {
            "category":"Professional",
            "subcategory":"Business Services",
            "type":"Services"
        }
    ],
    "sg:phone":"+61 3 9806 0622",
    "sg:postcode":"3149",
    "sg:province":"VIC",
    "sg:tags":[
        "drafting"
    ],
    "wof:name":"Eastcoast Drafting Service",
    "wof:placetype":"venue"
},
  "geometry": {"coordinates":[145.116729736,-37.8854904175],"type":"Point"}
}