{
  "type": "Feature",
  "properties": {
    "addr:full":"10 Karragarra Pl Thornlands QLD 4164",
    "addr:housenumber":"10",
    "addr:postcode":"4164",
    "addr:street":"Karragarra Pl",
    "iso:country":"AU",
    "sg:address":"10 Karragarra Pl",
    "sg:city":"Thornlands",
    "sg:classifiers":[
        {
            "category":"Building & Trades",
            "subcategory":"Construction",
            "type":"Services"
        }
    ],
    "sg:phone":"+61 402 017 072",
    "sg:postcode":"4164",
    "sg:province":"QLD",
    "sg:tags":[
        "fencing",
        "contractor"
    ],
    "wof:name":"S.F. Fencing",
    "wof:placetype":"venue"
},
  "geometry": {"coordinates":[153.280349731,-27.5594730377],"type":"Point"}
}