{
  "type": "Feature",
  "properties": {
    "iso:country":"AU",
    "sg:address":"Stall 19 Fish Market",
    "sg:city":"Footscray",
    "sg:classifiers":[
        {
            "category":"Wholesale",
            "subcategory":"Seafood",
            "type":"Manufacturing & Wholesale Goods"
        }
    ],
    "sg:phone":"+61 3 9689 5099",
    "sg:postcode":"3011",
    "sg:province":"VIC",
    "sg:tags":[
        "fish"
    ],
    "wof:name":"Fish Traders (Melbourne) Pty Ltd",
    "wof:placetype":"venue"
},
  "geometry": {"coordinates":[144.88934326200001,-37.8070487976],"type":"Point"}
}