{
  "type": "Feature",
  "properties": {
    "iso:country":"AU",
    "sg:address":"5 Main St",
    "sg:city":"Crafers",
    "sg:classifiers":[
        {
            "category":"Professional",
            "subcategory":"Employment Agencies",
            "type":"Services"
        }
    ],
    "sg:phone":"+61 8 8339 0030",
    "sg:postcode":"5152",
    "sg:province":"SA",
    "sg:tags":[
        "provider",
        "internet"
    ],
    "wof:name":"Adelaide Hills Infonet",
    "wof:placetype":"venue"
},
  "geometry": {"coordinates":[138.704345703,-34.9973564148],"type":"Point"}
}