{
  "type": "Feature",
  "properties": {
    "iso:country":"AU",
    "sg:address":"24 High St",
    "sg:city":"Yea",
    "sg:classifiers":[
        {
            "category":"Fast Food",
            "type":"Food & Drink"
        }
    ],
    "sg:phone":"+61 3 5797 2680",
    "sg:postcode":"3717",
    "sg:province":"VIC",
    "sg:tags":[
        "away",
        "take"
    ],
    "wof:name":"Ambleinn Cafe",
    "wof:placetype":"venue"
},
  "geometry": {"coordinates":[145.42596435600001,-37.210647583],"type":"Point"}
}