{
  "type": "Feature",
  "properties": {
    "addr:full":"Maroondah Hwy Buxton VIC 3711",
    "addr:postcode":"3711",
    "addr:street":"Maroondah Hwy",
    "iso:country":"AU",
    "sg:address":"Maroondah Hwy",
    "sg:city":"Buxton",
    "sg:classifiers":[
        {
            "category":"Restaurant",
            "type":"Food & Drink"
        }
    ],
    "sg:phone":"+61 3 5774 7322",
    "sg:postcode":"3711",
    "sg:province":"VIC",
    "wof:name":"Buxton Roadhouse Pty Ltd",
    "wof:placetype":"venue"
},
  "geometry": {"coordinates":[145.70895385700001,-37.4228668213],"type":"Point"}
}