{
  "type": "Feature",
  "properties": {
    "iso:country":"AU",
    "sg:address":"104 Monaco St",
    "sg:city":"Broadbeach",
    "sg:classifiers":[
        {
            "category":"Utilities",
            "subcategory":"Electric",
            "type":"Services"
        }
    ],
    "sg:phone":"+61 7 5531 6580",
    "sg:postcode":"4218",
    "sg:province":"QLD",
    "sg:tags":[
        "electrical",
        "contractor"
    ],
    "wof:name":"Broadbeach Electrical",
    "wof:placetype":"venue"
},
  "geometry": {"coordinates":[153.42027282699999,-28.0179920197],"type":"Point"}
}