{
  "type": "Feature",
  "properties": {
    "addr:full":"4 Hall St Cessnock NSW 2325",
    "addr:housenumber":"4",
    "addr:postcode":"2325",
    "addr:street":"Hall St",
    "iso:country":"AU",
    "sg:address":"4 Hall St",
    "sg:city":"Cessnock",
    "sg:classifiers":[
        {
            "category":"Professional",
            "subcategory":"Art Services",
            "type":"Services"
        }
    ],
    "sg:phone":"+61 2 4998 1883",
    "sg:postcode":"2325",
    "sg:province":"NSW",
    "sg:tags":[
        "decorator",
        "painter"
    ],
    "wof:name":"Duncan Coote Master Painter",
    "wof:placetype":"venue"
},
  "geometry": {"coordinates":[151.35450744600001,-32.8373832703],"type":"Point"}
}