{
  "type": "Feature",
  "properties": {
    "addr:full":"39 Beverage Drv Tullamarine VIC 3043",
    "addr:postcode":"3043",
    "addr:street":"Beverage Drv",
    "iso:country":"AU",
    "sg:address":"39 Beverage Drv",
    "sg:city":"Tullamarine",
    "sg:classifiers":[
        {
            "category":"Military Area",
            "subcategory":"Bunker",
            "type":"Public Place"
        }
    ],
    "sg:phone":"+61 3 9338 8644",
    "sg:postcode":"3043",
    "sg:province":"VIC",
    "sg:tags":[
        "tub",
        "planter"
    ],
    "sg:website":"http://www.allaria.com.au",
    "wof:name":"Allaria Pty Ltd",
    "wof:placetype":"venue"
},
  "geometry": {"coordinates":[144.86518859899999,-37.7191429138],"type":"Point"}
}