{
  "type": "Feature",
  "properties": {
    "iso:country":"AU",
    "sg:address":"221 Canning Hwy",
    "sg:city":"South Perth",
    "sg:classifiers":[
        {
            "category":"Real Estate",
            "subcategory":"Real Estate Agent",
            "type":"Services"
        }
    ],
    "sg:phone":"+61 8 9368 7555",
    "sg:postcode":"6151",
    "sg:province":"WA",
    "wof:name":"Elders City South",
    "wof:placetype":"venue"
},
  "geometry": {"coordinates":[115.871727,-31.987318],"type":"Point"}
}