{
  "type": "Feature",
  "properties": {
    "iso:country":"AU",
    "sg:address":"6 Carween Ave",
    "sg:city":"Brighton East",
    "sg:classifiers":[
        {
            "category":"Banks & Credit Unions",
            "subcategory":"Financial Services",
            "type":"Services"
        }
    ],
    "sg:phone":"+61 3 9576 7831",
    "sg:postcode":"3187",
    "sg:province":"VIC",
    "sg:tags":[
        "financier"
    ],
    "wof:name":"Cobrum Capital Trading Pty Ltd",
    "wof:placetype":"venue"
},
  "geometry": {"coordinates":[145.02406310999999,-37.9034080505],"type":"Point"}
}