{
  "type": "Feature",
  "properties": {
    "iso:country":"AU",
    "sg:address":"20 Stretham Ave",
    "sg:city":"Picnic Point",
    "sg:classifiers":[
        {
            "category":"Health Services",
            "subcategory":"Health Practitioner",
            "type":"Services"
        }
    ],
    "sg:phone":"+61 2 9774 4825",
    "sg:postcode":"2213",
    "sg:province":"NSW",
    "sg:tags":[
        "physiotherapist"
    ],
    "wof:name":"Brown Gemma",
    "wof:placetype":"venue"
},
  "geometry": {"coordinates":[151.010727,-33.965832],"type":"Point"}
}