{
  "type": "Feature",
  "properties": {
    "addr:full":"Shp 376 Kawana Shopping World Kawana QLD 4701",
    "addr:housenumber":"376",
    "addr:postcode":"4701",
    "addr:street":"Kawana",
    "iso:country":"AU",
    "sg:address":"Shp 376 Kawana Shopping World",
    "sg:city":"Kawana",
    "sg:classifiers":[
        {
            "category":"Shopping",
            "subcategory":"Clothing, Apparel, & Fashions",
            "type":"Retail Goods"
        }
    ],
    "sg:phone":"+61 7 5478 1291",
    "sg:postcode":"4701",
    "sg:province":"QLD",
    "sg:tags":[
        "jean"
    ],
    "wof:name":"Just Jeans",
    "wof:placetype":"venue"
},
  "geometry": {"coordinates":[150.51556396500001,-23.3370304108],"type":"Point"}
}