{
  "type": "Feature",
  "properties": {
    "addr:full":"38 Buckingham Ave Springvale VIC 3171",
    "addr:housenumber":"38",
    "addr:postcode":"3171",
    "addr:street":"Buckingham Ave",
    "iso:country":"AU",
    "sg:address":"38 Buckingham Ave",
    "sg:city":"Springvale",
    "sg:classifiers":[
        {
            "category":"Fast Food",
            "type":"Food & Drink"
        }
    ],
    "sg:phone":"+61 3 9548 3205",
    "sg:postcode":"3171",
    "sg:province":"VIC",
    "sg:tags":[
        "away",
        "take"
    ],
    "wof:name":"Tan Dinh",
    "wof:placetype":"venue"
},
  "geometry": {"coordinates":[145.15130615199999,-37.9492454529],"type":"Point"}
}