{
  "type": "Feature",
  "properties": {
    "addr:full":"193 Yarra St Warrandyte VIC 3113",
    "addr:housenumber":"193",
    "addr:postcode":"3113",
    "addr:street":"Yarra St",
    "iso:country":"AU",
    "sg:address":"193 Yarra St",
    "sg:city":"Warrandyte",
    "sg:classifiers":[
        {
            "category":"Food & Beverages",
            "subcategory":"Bakery",
            "type":"Retail Goods"
        }
    ],
    "sg:phone":"+61 3 9844 1809",
    "sg:postcode":"3113",
    "sg:province":"VIC",
    "sg:tags":[
        "baker"
    ],
    "wof:name":"The Bakery -Warrandyte",
    "wof:placetype":"venue"
},
  "geometry": {"coordinates":[145.220413208,-37.7367897034],"type":"Point"}
}