{
  "type": "Feature",
  "properties": {
    "addr:full":"Unit C3, 26 Oakdale Rd Gateshead NSW 2290",
    "addr:housenumber":"26",
    "addr:postcode":"2290",
    "addr:street":"Oakdale Rd",
    "iso:country":"AU",
    "sg:address":"Unit C3, 26 Oakdale Rd",
    "sg:city":"Gateshead",
    "sg:classifiers":[
        {
            "category":"Organizations",
            "subcategory":"Professional Association",
            "type":"Services"
        }
    ],
    "sg:phone":"+61 1300 769 986",
    "sg:postcode":"2290",
    "sg:province":"NSW",
    "sg:tags":[
        "web",
        "internet"
    ],
    "wof:name":"Design Reaction",
    "wof:placetype":"venue"
},
  "geometry": {"coordinates":[151.69664001500001,-32.9895248413],"type":"Point"}
}