{
  "type": "Feature",
  "properties": {
    "addr:full":"Anzac Square Arcade, Edward St Brisbane QLD 4000",
    "addr:postcode":"4000",
    "addr:street":"Edward St",
    "iso:country":"AU",
    "sg:address":"Anzac Square Arcade, Edward St",
    "sg:city":"Brisbane",
    "sg:classifiers":[
        {
            "category":"Personal",
            "type":"Services"
        }
    ],
    "sg:phone":"+61 7 3221 1604",
    "sg:postcode":"4000",
    "sg:province":"QLD",
    "sg:tags":[
        "gift"
    ],
    "wof:name":"Iris Florist",
    "wof:placetype":"venue"
},
  "geometry": {"coordinates":[153.02470398,-27.4657669067],"type":"Point"}
}