{
  "type": "Feature",
  "properties": {
    "addr:full":"14 Lucas St Lutwyche QLD 4030",
    "addr:housenumber":"14",
    "addr:postcode":"4030",
    "addr:street":"Lucas St",
    "iso:country":"AU",
    "sg:address":"14 Lucas St",
    "sg:city":"Lutwyche",
    "sg:classifiers":[
        {
            "category":"Education",
            "subcategory":"Kindergarten",
            "type":"Public Place"
        }
    ],
    "sg:phone":"+61 7 3857 2430",
    "sg:postcode":"4030",
    "sg:province":"QLD",
    "sg:tags":[
        "pre-schools"
    ],
    "wof:name":"Lutwyche-Windsor Kindergarten & Pre-School Association Inc",
    "wof:placetype":"venue"
},
  "geometry": {"coordinates":[153.03280599999999,-27.421412],"type":"Point"}
}