{
  "type": "Feature",
  "properties": {
    "iso:country":"AU",
    "sg:address":"58 Anderson Ave",
    "sg:city":"Panania",
    "sg:classifiers":[
        {
            "category":"Food & Beverages",
            "subcategory":"Liquor & Beverages",
            "type":"Retail Goods"
        }
    ],
    "sg:phone":"+61 2 9773 9171",
    "sg:postcode":"2213",
    "sg:province":"NSW",
    "sg:tags":[
        "store"
    ],
    "wof:name":"Cellarbrations",
    "wof:placetype":"venue"
},
  "geometry": {"coordinates":[150.998764,-33.953838],"type":"Point"}
}