{
  "type": "Feature",
  "properties": {
    "addr:full":"125 Hanckel Rd Oakville NSW 2765",
    "addr:housenumber":"125",
    "addr:postcode":"2765",
    "addr:street":"Hanckel Rd",
    "iso:country":"AU",
    "sg:address":"125 Hanckel Rd",
    "sg:city":"Oakville",
    "sg:classifiers":[
        {
            "category":"Utilities",
            "subcategory":"Electric",
            "type":"Services"
        }
    ],
    "sg:phone":"+61 2 9627 2233",
    "sg:postcode":"2765",
    "sg:province":"NSW",
    "sg:tags":[
        "electrical",
        "contractor"
    ],
    "wof:name":"Andrew Scott Electrical Pty Ltd",
    "wof:placetype":"venue"
},
  "geometry": {"coordinates":[150.8802948,-33.6293525696],"type":"Point"}
}