{
  "type": "Feature",
  "properties": {
    "addr:full":"1 Abley Crt Brahma Lodge SA 5109",
    "addr:housenumber":"1",
    "addr:postcode":"5109",
    "addr:street":"Abley Crt",
    "iso:country":"AU",
    "sg:address":"1 Abley Crt",
    "sg:city":"Brahma Lodge",
    "sg:classifiers":[
        {
            "category":"Wholesale",
            "subcategory":"Auto Parts",
            "type":"Manufacturing & Wholesale Goods"
        }
    ],
    "sg:phone":"+61 413 456 309",
    "sg:postcode":"5109",
    "sg:province":"SA",
    "sg:tags":[
        "tyre"
    ],
    "wof:name":"Premier Tyre Service",
    "wof:placetype":"venue"
},
  "geometry": {"coordinates":[138.656692505,-34.7786521912],"type":"Point"}
}