{
  "type": "Feature",
  "properties": {
    "addr:full":"19 Pellew St Sandringham VIC 3191",
    "addr:housenumber":"19",
    "addr:postcode":"3191",
    "addr:street":"Pellew St",
    "iso:country":"AU",
    "sg:address":"19 Pellew St",
    "sg:city":"Sandringham",
    "sg:classifiers":[
        {
            "category":"Building & Trades",
            "subcategory":"Construction",
            "type":"Services"
        }
    ],
    "sg:phone":"+61 3 9598 0363",
    "sg:postcode":"3191",
    "sg:province":"VIC",
    "sg:tags":[
        "contractor"
    ],
    "wof:name":"Gulliver K.J. Constructions pty ltd",
    "wof:placetype":"venue"
},
  "geometry": {"coordinates":[145.01475524899999,-37.9524345398],"type":"Point"}
}