{
  "type": "Feature",
  "properties": {
    "addr:full":"Unit1/ 449 Brunswick Rd Brunswick West VIC 3055",
    "addr:housenumber":"449",
    "addr:postcode":"3055",
    "addr:street":"Brunswick Rd",
    "iso:country":"AU",
    "sg:address":"Unit1/ 449 Brunswick Rd",
    "sg:city":"Brunswick West",
    "sg:classifiers":[
        {
            "category":"Professional",
            "subcategory":"Accounting & Tax Preparation",
            "type":"Services"
        }
    ],
    "sg:phone":"+61 3 9381 2977",
    "sg:postcode":"3055",
    "sg:province":"VIC",
    "sg:tags":[
        "bookkeeping"
    ],
    "wof:name":"Accurate Figures Accounting & Taxation Services",
    "wof:placetype":"venue"
},
  "geometry": {"coordinates":[144.94841003400001,-37.7754478455],"type":"Point"}
}