{
  "type": "Feature",
  "properties": {
    "addr:full":"Shop 60a, Endeavour Hills Shopping Centre, Cnr Heatherton Rd & Mathew Flinders Drv Endeavour Hills VIC 3802",
    "addr:housenumber":"60a",
    "addr:postcode":"3802",
    "addr:street":"Endeavour;Cnr Heatherton Rd &;Flinders Drv",
    "iso:country":"AU",
    "sg:address":"Shop 60a, Endeavour Hills Shopping Centre, Cnr Heatherton Rd & Mathew Flinders Drv",
    "sg:city":"Endeavour Hills",
    "sg:classifiers":[
        {
            "category":"Food & Beverages",
            "subcategory":"Bakery",
            "type":"Retail Goods"
        }
    ],
    "sg:phone":"+61 3 9700 6035",
    "sg:postcode":"3802",
    "sg:province":"VIC",
    "sg:tags":[
        "baker"
    ],
    "wof:name":"Bakers Delight Ltd",
    "wof:placetype":"venue"
},
  "geometry": {"coordinates":[145.26531982399999,-37.9758796692],"type":"Point"}
}