{
  "type": "Feature",
  "properties": {
    "addr:full":"Fyshwick Fresh Food Markets Dalby St Fyshwick ACT 2609",
    "addr:postcode":"2609",
    "addr:street":"Dalby St",
    "iso:country":"AU",
    "sg:address":"Fyshwick Fresh Food Markets Dalby St",
    "sg:city":"Fyshwick",
    "sg:classifiers":[
        {
            "category":"Deli",
            "type":"Food & Drink"
        }
    ],
    "sg:phone":"+61 2 6295 8067",
    "sg:postcode":"2609",
    "sg:province":"ACT",
    "sg:tags":[
        "delicatessen"
    ],
    "wof:name":"Deli Planet",
    "wof:placetype":"venue"
},
  "geometry": {"coordinates":[149.153930664,-35.3238372803],"type":"Point"}
}