{
  "type": "Feature",
  "properties": {
    "addr:full":"104b Grant St Alexandra VIC 3714",
    "addr:housenumber":"104b",
    "addr:postcode":"3714",
    "addr:street":"Grant St",
    "iso:country":"AU",
    "sg:address":"104b Grant St",
    "sg:city":"Alexandra",
    "sg:classifiers":[
        {
            "category":"Shopping",
            "subcategory":"Clothing, Apparel, & Fashions",
            "type":"Retail Goods"
        }
    ],
    "sg:phone":"+61 3 5772 2311",
    "sg:postcode":"3714",
    "sg:province":"VIC",
    "sg:tags":[
        "lady",
        "wear"
    ],
    "wof:name":"Mikany Fashions Pty Ltd",
    "wof:placetype":"venue"
},
  "geometry": {"coordinates":[145.709594727,-37.1917800903],"type":"Point"}
}