{
  "type": "Feature",
  "properties": {
    "addr:full":"66 Grants Gully Rd Clarendon SA 5157",
    "addr:housenumber":"66",
    "addr:postcode":"5157",
    "addr:street":"Grants Gully Rd",
    "iso:country":"AU",
    "sg:address":"66 Grants Gully Rd",
    "sg:city":"Clarendon",
    "sg:classifiers":[
        {
            "category":"Government",
            "subcategory":"Post Office",
            "type":"Public Place"
        }
    ],
    "sg:phone":"+61 8 8383 6020",
    "sg:postcode":"5157",
    "sg:province":"SA",
    "sg:tags":[
        "postal"
    ],
    "wof:name":"Australia Post",
    "wof:placetype":"venue"
},
  "geometry": {"coordinates":[138.62901306099999,-35.1089096069],"type":"Point"}
}