{
  "type": "Feature",
  "properties": {
    "addr:full":"41- 47 Lahey Rd North Tamborine QLD 4272",
    "addr:housenumber":"47",
    "addr:postcode":"4272",
    "addr:street":"Lahey Rd",
    "iso:country":"AU",
    "sg:address":"41- 47 Lahey Rd",
    "sg:city":"North Tamborine",
    "sg:classifiers":[
        {
            "category":"Shopping",
            "subcategory":"Antiques",
            "type":"Retail Goods"
        }
    ],
    "sg:phone":"+61 438 750 448",
    "sg:postcode":"4272",
    "sg:province":"QLD",
    "wof:name":"Country Chattels",
    "wof:placetype":"venue"
},
  "geometry": {"coordinates":[153.18324279800001,-27.992937088],"type":"Point"}
}