{
  "type": "Feature",
  "properties": {
    "addr:full":"33 Barringer St Conder ACT 2906",
    "addr:housenumber":"33",
    "addr:postcode":"2906",
    "addr:street":"Barringer St",
    "iso:country":"AU",
    "sg:address":"33 Barringer St",
    "sg:city":"Conder",
    "sg:classifiers":[
        {
            "category":"Professional",
            "subcategory":"Business Services",
            "type":"Services"
        }
    ],
    "sg:phone":"+61 416 278 125",
    "sg:postcode":"2906",
    "sg:province":"ACT",
    "sg:tags":[
        "drafting"
    ],
    "wof:name":"ACT Design & Drafting",
    "wof:placetype":"venue"
},
  "geometry": {"coordinates":[149.109283447,-35.4621162415],"type":"Point"}
}