{
  "type": "Feature",
  "properties": {
    "iso:country":"AU",
    "sg:address":"99 Daping St",
    "sg:city":"Katanning",
    "sg:classifiers":[
        {
            "category":"Manufacturing",
            "subcategory":"Metals",
            "type":"Manufacturing & Wholesale Goods"
        }
    ],
    "sg:phone":"+61 8 9821 5211",
    "sg:postcode":"6317",
    "sg:province":"WA",
    "sg:tags":[
        "steel",
        "fabricator",
        "mfrs"
    ],
    "wof:name":"Katanning Fabrication",
    "wof:placetype":"venue"
},
  "geometry": {"coordinates":[117.563781738,-33.6951141357],"type":"Point"}
}