{
  "type": "Feature",
  "properties": {
    "iso:country":"AU",
    "sg:address":"154a- 160 Station St",
    "sg:city":"Norlane",
    "sg:classifiers":[
        {
            "category":"Professional",
            "type":"Services"
        }
    ],
    "sg:phone":"+61 3 5274 1944",
    "sg:postcode":"3214",
    "sg:province":"VIC",
    "sg:tags":[
        "packaging",
        "filling",
        "assembling"
    ],
    "wof:name":"Shannon Park Industries",
    "wof:placetype":"venue"
},
  "geometry": {"coordinates":[144.36697387699999,-38.0883979797],"type":"Point"}
}