{
  "type": "Feature",
  "properties": {
    "addr:full":"Shop 26 K-Mart Plaza Cnr Blackburn & Burwood Hwy Burwood East VIC 3151",
    "addr:housenumber":"shop 26",
    "addr:postcode":"3151",
    "addr:street":"Plaza Cnr Blackburn;Hwy",
    "iso:country":"AU",
    "sg:address":"Shop 26 K-Mart Plaza Cnr Blackburn & Burwood Hwy",
    "sg:city":"Burwood East",
    "sg:classifiers":[
        {
            "category":"Personal",
            "subcategory":"Beauty Salon",
            "type":"Services"
        }
    ],
    "sg:phone":"+61 3 9886 8841",
    "sg:postcode":"3151",
    "sg:province":"VIC",
    "sg:tags":[
        "hairdresser"
    ],
    "wof:name":"Cutters His & Hers",
    "wof:placetype":"venue"
},
  "geometry": {"coordinates":[145.151687622,-37.85364151],"type":"Point"}
}