{
  "type": "Feature",
  "properties": {
    "addr:full":"272 - 290 Fryar Rd Eagleby QLD 4207",
    "addr:housenumber":"290",
    "addr:postcode":"4207",
    "addr:street":"Fryar Rd",
    "iso:country":"AU",
    "sg:address":"272 - 290 Fryar Rd",
    "sg:city":"Eagleby",
    "sg:classifiers":[
        {
            "category":"Social Services",
            "subcategory":"Retirement Home",
            "type":"Services"
        }
    ],
    "sg:phone":"+61 7 3804 7044",
    "sg:postcode":"4207",
    "sg:province":"QLD",
    "sg:tags":[
        "village"
    ],
    "wof:name":"The Jacarandas Eagleby",
    "wof:placetype":"venue"
},
  "geometry": {"coordinates":[153.215408325,-27.688457489],"type":"Point"}
}