{
  "type": "Feature",
  "properties": {
    "addr:full":"132 Tanti Ave Mornington VIC 3931",
    "addr:housenumber":"132",
    "addr:postcode":"3931",
    "addr:street":"Tanti Ave",
    "iso:country":"AU",
    "sg:address":"132 Tanti Ave",
    "sg:city":"Mornington",
    "sg:classifiers":[
        {
            "category":"Health Services",
            "subcategory":"Doctor",
            "type":"Services"
        }
    ],
    "sg:phone":"+61 3 5975 8877",
    "sg:postcode":"3931",
    "sg:province":"VIC",
    "sg:tags":[
        "medical",
        "practitioner"
    ],
    "wof:name":"Tanti Medical Rooms",
    "wof:placetype":"venue"
},
  "geometry": {"coordinates":[145.04771423299999,-38.2249946594],"type":"Point"}
}