{
  "type": "Feature",
  "properties": {
    "addr:full":"Unit 2, 14 Timms Crt Woodridge QLD 4114",
    "addr:housenumber":"14",
    "addr:postcode":"4114",
    "addr:street":"Timms Crt",
    "iso:country":"AU",
    "sg:address":"Unit 2, 14 Timms Crt",
    "sg:city":"Woodridge",
    "sg:classifiers":[
        {
            "category":"Manufacturing",
            "subcategory":"Tools & Machinery",
            "type":"Manufacturing & Wholesale Goods"
        }
    ],
    "sg:phone":"+61 7 3808 6220",
    "sg:postcode":"4114",
    "sg:province":"QLD",
    "sg:tags":[
        "machine",
        "industrial",
        "sewing"
    ],
    "wof:name":"K.M.A. Sewing Machines",
    "wof:placetype":"venue"
},
  "geometry": {"coordinates":[153.10700988799999,-27.620349884],"type":"Point"}
}