{
  "type": "Feature",
  "properties": {
    "iso:country":"AU",
    "sg:address":"4/ 446 Enogerra Rd",
    "sg:city":"Alderley",
    "sg:classifiers":[
        {
            "category":"Professional",
            "subcategory":"Business Services",
            "type":"Services"
        }
    ],
    "sg:phone":"+61 7 3856 6949",
    "sg:postcode":"4051",
    "sg:province":"QLD",
    "sg:tags":[
        "drafting"
    ],
    "wof:name":"Concepts Unlimited",
    "wof:placetype":"venue"
},
  "geometry": {"coordinates":[153.001831055,-27.4267253876],"type":"Point"}
}