{
  "type": "Feature",
  "properties": {
    "addr:full":"3 Massinger St Salisbury QLD 4107",
    "addr:housenumber":"3",
    "addr:postcode":"4107",
    "addr:street":"Massinger St",
    "iso:country":"AU",
    "sg:address":"3 Massinger St",
    "sg:city":"Salisbury",
    "sg:classifiers":[
        {
            "category":"Utilities",
            "subcategory":"Electric",
            "type":"Services"
        }
    ],
    "sg:phone":"+61 7 3275 2467",
    "sg:postcode":"4107",
    "sg:province":"QLD",
    "sg:tags":[
        "electrical",
        "contractor"
    ],
    "wof:name":"Greg Scholz Electrician",
    "wof:placetype":"venue"
},
  "geometry": {"coordinates":[153.03358459500001,-27.5521755219],"type":"Point"}
}