{
  "type": "Feature",
  "properties": {
    "iso:country":"AU",
    "sg:address":"275 Turton Rd",
    "sg:city":"New Lambton",
    "sg:classifiers":[
        {
            "category":"Shopping",
            "subcategory":"Musical Instruments",
            "type":"Retail Goods"
        }
    ],
    "sg:phone":"+61 2 4957 4966",
    "sg:postcode":"2305",
    "sg:province":"NSW",
    "sg:tags":[
        "musician",
        "agent"
    ],
    "wof:name":"Hill Barry",
    "wof:placetype":"venue"
},
  "geometry": {"coordinates":[151.724869,-32.917053],"type":"Point"}
}