{
  "type": "Feature",
  "properties": {
    "addr:full":"120 Fowler Rd Illawong NSW 2234",
    "addr:housenumber":"120",
    "addr:postcode":"2234",
    "addr:street":"Fowler Rd",
    "iso:country":"AU",
    "sg:address":"120 Fowler Rd",
    "sg:city":"Illawong",
    "sg:classifiers":[
        {
            "category":"Communications",
            "subcategory":"Film & Video Production",
            "type":"Services"
        }
    ],
    "sg:phone":"+61 2 9541 0271",
    "sg:postcode":"2234",
    "sg:province":"NSW",
    "sg:tags":[
        "dvd",
        "library"
    ],
    "wof:name":"Motelvideo",
    "wof:placetype":"venue"
},
  "geometry": {"coordinates":[151.05645751899999,-33.9950370789],"type":"Point"}
}