{
  "type": "Feature",
  "properties": {
    "addr:full":"130 Lang St Kurri Kurri NSW 2327",
    "addr:housenumber":"130",
    "addr:postcode":"2327",
    "addr:street":"Lang St",
    "iso:country":"AU",
    "sg:address":"130 Lang St",
    "sg:city":"Kurri Kurri",
    "sg:classifiers":[
        {
            "category":"Personal",
            "type":"Services"
        }
    ],
    "sg:phone":"+61 2 4937 3055",
    "sg:postcode":"2327",
    "sg:province":"NSW",
    "sg:tags":[
        "gift"
    ],
    "wof:name":"Bubbles & Bows",
    "wof:placetype":"venue"
},
  "geometry": {"coordinates":[151.47984314000001,-32.8192062378],"type":"Point"}
}