{
  "type": "Feature",
  "properties": {
    "addr:full":"1/ 402-410 Chapel Rd Bankstown NSW 2200",
    "addr:housenumber":"/ 402-410",
    "addr:postcode":"2200",
    "addr:street":"Chapel Rd",
    "iso:country":"AU",
    "sg:address":"1/ 402-410 Chapel Rd",
    "sg:city":"Bankstown",
    "sg:classifiers":[
        {
            "category":"Health Services",
            "subcategory":"Doctor",
            "type":"Services"
        }
    ],
    "sg:phone":"+61 2 9709 6499",
    "sg:postcode":"2200",
    "sg:province":"NSW",
    "sg:tags":[
        "medical",
        "practitioner"
    ],
    "wof:name":"Maniam Vijay Dr",
    "wof:placetype":"venue"
},
  "geometry": {"coordinates":[151.033142,-33.913567],"type":"Point"}
}