{
  "type": "Feature",
  "properties": {
    "iso:country":"AU",
    "sg:address":"6 Schurmann St",
    "sg:city":"Natimuk",
    "sg:classifiers":[
        {
            "category":"Health Services",
            "subcategory":"Doctor",
            "type":"Services"
        }
    ],
    "sg:phone":"+61 3 5363 4480",
    "sg:postcode":"3409",
    "sg:province":"VIC",
    "sg:tags":[
        "medical",
        "practitioner"
    ],
    "wof:name":"Natimuk Surgery",
    "wof:placetype":"venue"
},
  "geometry": {"coordinates":[141.93780517600001,-36.7449378967],"type":"Point"}
}