{
  "type": "Feature",
  "properties": {
    "addr:full":"27 Redman Rd Dee Why NSW 2099",
    "addr:housenumber":"27",
    "addr:postcode":"2099",
    "addr:street":"Redman Rd",
    "iso:country":"AU",
    "sg:address":"27 Redman Rd",
    "sg:city":"Dee Why",
    "sg:classifiers":[
        {
            "category":"Personal",
            "subcategory":"Beauty Salon",
            "type":"Services"
        }
    ],
    "sg:phone":"+61 2 9982 6303",
    "sg:postcode":"2099",
    "sg:province":"NSW",
    "sg:tags":[
        "hairdresser"
    ],
    "wof:name":"Lu's Vanity",
    "wof:placetype":"venue"
},
  "geometry": {"coordinates":[151.28225707999999,-33.7533454895],"type":"Point"}
}