{
  "type": "Feature",
  "properties": {
    "iso:country":"AU",
    "sg:address":"1 Bridge St",
    "sg:city":"Richmond",
    "sg:classifiers":[
        {
            "category":"Shopping",
            "subcategory":"Antiques",
            "type":"Retail Goods"
        }
    ],
    "sg:phone":"+61 3 6260 1099",
    "sg:postcode":"7025",
    "sg:province":"TAS",
    "sg:tags":[
        "collectable",
        "memorabilia"
    ],
    "wof:name":"Teddies On The Green",
    "wof:placetype":"venue"
},
  "geometry": {"coordinates":[147.43133544899999,-42.7381248474],"type":"Point"}
}