{
  "type": "Feature",
  "properties": {
    "addr:full":"Shelley Bay Resort 465 The Esplanade Hervey Bay QLD 4655",
    "addr:housenumber":"465",
    "addr:postcode":"4655",
    "addr:street":"The Esplanade",
    "iso:country":"AU",
    "sg:address":"Shelley Bay Resort 465",
    "sg:city":"The Esplanade Hervey Bay",
    "sg:classifiers":[
        {
            "category":"Fast Food",
            "type":"Food & Drink"
        }
    ],
    "sg:phone":"+61 7 4125 5338",
    "sg:postcode":"4655",
    "sg:province":"QLD",
    "sg:tags":[
        "away",
        "take"
    ],
    "wof:name":"Thai Diamond Restaurant",
    "wof:placetype":"venue"
},
  "geometry": {"coordinates":[152.87983700000001,-25.28282],"type":"Point"}
}