{
  "type": "Feature",
  "properties": {
    "addr:full":"384 Hargreaves St Bendigo VIC 3550",
    "addr:housenumber":"384",
    "addr:postcode":"3550",
    "addr:street":"Hargreaves St",
    "iso:country":"AU",
    "sg:address":"384 Hargreaves St",
    "sg:city":"Bendigo",
    "sg:classifiers":[
        {
            "category":"Professional",
            "subcategory":"Employment Agencies",
            "type":"Services"
        }
    ],
    "sg:phone":"+61 3 5441 9100",
    "sg:postcode":"3550",
    "sg:province":"VIC",
    "wof:name":"MAETS (JOBfutures)-BENDIGO",
    "wof:placetype":"venue"
},
  "geometry": {"coordinates":[144.27828979500001,-36.7612686157],"type":"Point"}
}