{
  "type": "Feature",
  "properties": {
    "addr:full":"Level 1, 39 Market St South Melbourne VIC 3205",
    "addr:housenumber":"39",
    "addr:postcode":"3205",
    "addr:street":"Market St",
    "iso:country":"AU",
    "sg:address":"Level 1, 39 Market St",
    "sg:city":"South Melbourne",
    "sg:classifiers":[
        {
            "category":"Education",
            "subcategory":"Special Training",
            "type":"Public Place"
        }
    ],
    "sg:phone":"+61 3 9682 5444",
    "sg:postcode":"3205",
    "sg:province":"VIC",
    "sg:tags":[
        "development",
        "sale"
    ],
    "wof:name":"Esource Pty Ltd",
    "wof:placetype":"venue"
},
  "geometry": {"coordinates":[144.96000699999999,-37.829521],"type":"Point"}
}