{
  "type": "Feature",
  "properties": {
    "iso:country":"AU",
    "sg:address":"2 - 10 Mayne St",
    "sg:city":"Murrurundi",
    "sg:classifiers":[
        {
            "category":"Manufacturing",
            "subcategory":"Tools & Machinery",
            "type":"Manufacturing & Wholesale Goods"
        }
    ],
    "sg:phone":"+61 2 6546 6568",
    "sg:postcode":"2338",
    "sg:province":"NSW",
    "sg:tags":[
        "earth",
        "excavating",
        "moving",
        "equipment"
    ],
    "wof:name":"Murrurundi Sand & Gravel Pty Ltd",
    "wof:placetype":"venue"
},
  "geometry": {"coordinates":[150.83375549300001,-31.7631912231],"type":"Point"}
}