{
  "type": "Feature",
  "properties": {
    "iso:country":"AU",
    "sg:address":"PO Box 417",
    "sg:city":"New Norfolk",
    "sg:classifiers":[
        {
            "category":"Building & Trades",
            "subcategory":"Construction",
            "type":"Services"
        }
    ],
    "sg:phone":"+61 3 6261 1294",
    "sg:postcode":"7140",
    "sg:province":"TAS",
    "sg:tags":[
        "contractor"
    ],
    "wof:name":"Cross Fencing",
    "wof:placetype":"venue"
},
  "geometry": {"coordinates":[147.05613700000001,-42.772594],"type":"Point"}
}