{
  "type": "Feature",
  "properties": {
    "addr:full":"111 Susan St Scone NSW 2337",
    "addr:housenumber":"111",
    "addr:postcode":"2337",
    "addr:street":"Susan St",
    "iso:country":"AU",
    "sg:address":"111 Susan St",
    "sg:city":"Scone",
    "sg:classifiers":[
        {
            "category":"Professional",
            "subcategory":"Engineering",
            "type":"Services"
        }
    ],
    "sg:phone":"+61 2 6545 2732",
    "sg:postcode":"2337",
    "sg:province":"NSW",
    "sg:tags":[
        "consulting",
        "engineer"
    ],
    "wof:name":"Berthon John F & Associates - Consulting Engineers",
    "wof:placetype":"venue"
},
  "geometry": {"coordinates":[150.87753295900001,-32.0455245972],"type":"Point"}
}