{
  "type": "Feature",
  "properties": {
    "addr:full":"18 Loddon Ave Keilor VIC 3036",
    "addr:housenumber":"18",
    "addr:postcode":"3036",
    "addr:street":"Loddon Ave",
    "iso:country":"AU",
    "sg:address":"18 Loddon Ave",
    "sg:city":"Keilor",
    "sg:classifiers":[
        {
            "category":"Mining & Drilling",
            "type":"Manufacturing & Wholesale Goods"
        }
    ],
    "sg:phone":"+61 3 9336 2787",
    "sg:postcode":"3036",
    "sg:province":"VIC",
    "sg:tags":[
        "geologist"
    ],
    "wof:name":"Carl Layden",
    "wof:placetype":"venue"
},
  "geometry": {"coordinates":[144.82484400000001,-37.719776],"type":"Point"}
}