{
  "type": "Feature",
  "properties": {
    "iso:country":"AU",
    "sg:address":"Shop 3, Cnr Otranto & Bulcock Sts",
    "sg:city":"Caloundra",
    "sg:classifiers":[
        {
            "category":"Banks & Credit Unions",
            "subcategory":"Bank",
            "type":"Services"
        }
    ],
    "sg:phone":"+61 7 5437 0717",
    "sg:postcode":"4551",
    "sg:province":"QLD",
    "sg:tags":[
        "broker",
        "mortgage"
    ],
    "wof:name":"City Pacific Finance",
    "wof:placetype":"venue"
},
  "geometry": {"coordinates":[153.13038635300001,-26.8047161102],"type":"Point"}
}