{
  "type": "Feature",
  "properties": {
    "addr:full":"158 Victoria Rd Gladesville NSW 2111",
    "addr:housenumber":"158",
    "addr:postcode":"2111",
    "addr:street":"Victoria Rd",
    "iso:country":"AU",
    "sg:address":"158 Victoria Rd",
    "sg:city":"Gladesville",
    "sg:classifiers":[
        {
            "category":"Health Services",
            "subcategory":"Doctor",
            "type":"Services"
        }
    ],
    "sg:phone":"+61 2 9817 1693",
    "sg:postcode":"2111",
    "sg:province":"NSW",
    "sg:tags":[
        "medical",
        "practitioner"
    ],
    "wof:name":"Neville-Towle Andrew Dr",
    "wof:placetype":"venue"
},
  "geometry": {"coordinates":[151.126876831,-33.833114624],"type":"Point"}
}