{
  "type": "Feature",
  "properties": {
    "addr:full":"59 Clermont St Emerald QLD 4720",
    "addr:housenumber":"59",
    "addr:postcode":"4720",
    "addr:street":"Clermont St",
    "iso:country":"AU",
    "sg:address":"59 Clermont St",
    "sg:city":"Emerald",
    "sg:classifiers":[
        {
            "category":"Industrial Area",
            "type":"Public Place"
        }
    ],
    "sg:phone":"+61 7 4982 1104",
    "sg:postcode":"4720",
    "sg:province":"QLD",
    "sg:tags":[
        "protective",
        "clothing"
    ],
    "wof:name":"Eagleshams Menswear",
    "wof:placetype":"venue"
},
  "geometry": {"coordinates":[148.157883,-23.525541],"type":"Point"}
}