{
  "type": "Feature",
  "properties": {
    "addr:full":"313 Liverpool Rd Ashfield NSW 2131",
    "addr:housenumber":"313",
    "addr:postcode":"2131",
    "addr:street":"Liverpool Rd",
    "iso:country":"AU",
    "sg:address":"313 Liverpool Rd",
    "sg:city":"Ashfield",
    "sg:classifiers":[
        {
            "category":"Restaurant",
            "type":"Food & Drink"
        }
    ],
    "sg:phone":"+61 2 9798 7135",
    "sg:postcode":"2131",
    "sg:province":"NSW",
    "wof:name":"Chinese Kitchen Restaurant",
    "wof:placetype":"venue"
},
  "geometry": {"coordinates":[151.12298584000001,-33.8876724243],"type":"Point"}
}