{
  "type": "Feature",
  "properties": {
    "addr:full":"95 Ford St Ivanhoe VIC 3079",
    "addr:housenumber":"95",
    "addr:postcode":"3079",
    "addr:street":"Ford St",
    "iso:country":"AU",
    "sg:address":"95 Ford St",
    "sg:city":"Ivanhoe",
    "sg:classifiers":[
        {
            "category":"Professional",
            "subcategory":"Detective & Security Services",
            "type":"Services"
        }
    ],
    "sg:phone":"+61 3 9499 9332",
    "sg:postcode":"3079",
    "sg:province":"VIC",
    "sg:tags":[
        "consultant",
        "system"
    ],
    "wof:name":"Watchouse Security Systems",
    "wof:placetype":"venue"
},
  "geometry": {"coordinates":[145.03533935600001,-37.7635574341],"type":"Point"}
}