{
  "type": "Feature",
  "properties": {
    "iso:country":"AU",
    "sg:address":"Shop 9, 450 High St",
    "sg:city":"Penrith",
    "sg:classifiers":[
        {
            "category":"Government",
            "subcategory":"Court House",
            "type":"Public Place"
        }
    ],
    "sg:phone":"+61 2 4722 8261",
    "sg:postcode":"2750",
    "sg:province":"NSW",
    "sg:tags":[
        "personal",
        "marriage",
        "family",
        "counselling"
    ],
    "wof:name":"Cait Wotherspoon",
    "wof:placetype":"venue"
},
  "geometry": {"coordinates":[150.915557861,-33.8949356079],"type":"Point"}
}