{
  "type": "Feature",
  "properties": {
    "addr:full":"21 Sobraon Rd Marsfield NSW 2122",
    "addr:housenumber":"21",
    "addr:postcode":"2122",
    "addr:street":"Sobraon Rd",
    "iso:country":"AU",
    "sg:address":"21 Sobraon Rd",
    "sg:city":"Marsfield",
    "sg:classifiers":[
        {
            "category":"Health Services",
            "subcategory":"Health Practitioner",
            "type":"Services"
        }
    ],
    "sg:phone":"+61 2 9801 5499",
    "sg:postcode":"2122",
    "sg:province":"NSW",
    "sg:tags":[
        "acupuncture"
    ],
    "wof:name":"Fang Margaret",
    "wof:placetype":"venue"
},
  "geometry": {"coordinates":[151.102325439,-33.7803497314],"type":"Point"}
}