{
  "type": "Feature",
  "properties": {
    "addr:full":"282 Merri Crs Warrnambool VIC 3280",
    "addr:housenumber":"282",
    "addr:postcode":"3280",
    "addr:street":"Merri Crs",
    "iso:country":"AU",
    "sg:address":"282 Merri Crs",
    "sg:city":"Warrnambool",
    "sg:classifiers":[
        {
            "category":"Building & Trades",
            "subcategory":"Cleaning & Sanitation",
            "type":"Services"
        }
    ],
    "sg:phone":"+61 3 5562 0895",
    "sg:postcode":"3280",
    "sg:province":"VIC",
    "sg:tags":[
        "cleaner",
        "repairer",
        "roof"
    ],
    "wof:name":"Blair J R & D M",
    "wof:placetype":"venue"
},
  "geometry": {"coordinates":[142.47935485799999,-38.386428833],"type":"Point"}
}