{
  "type": "Feature",
  "properties": {
    "iso:country":"AU",
    "sg:address":"1538 Uralla Rd",
    "sg:city":"Katherine",
    "sg:classifiers":[
        {
            "category":"Utilities",
            "subcategory":"Electric",
            "type":"Services"
        }
    ],
    "sg:phone":"+61 8 8972 3153",
    "sg:postcode":"0850",
    "sg:province":"NT",
    "sg:tags":[
        "electrical",
        "contractor"
    ],
    "wof:name":"Uralla Electrical Services",
    "wof:placetype":"venue"
},
  "geometry": {"coordinates":[132.29603599999999,-14.489296],"type":"Point"}
}