{
  "type": "Feature",
  "properties": {
    "addr:full":"Shp 67 Garden City Shopng Cntr 125 Riseley St Booragoon WA 6154",
    "addr:housenumber":"67;125",
    "addr:postcode":"6154",
    "addr:street":"Riseley St",
    "iso:country":"AU",
    "sg:address":"Shp 67 Garden City Shopng Cntr 125 Riseley St",
    "sg:city":"Booragoon",
    "sg:classifiers":[
        {
            "category":"Health Services",
            "subcategory":"Optometrist",
            "type":"Services"
        }
    ],
    "sg:phone":"+61 8 9364 9577",
    "sg:postcode":"6154",
    "sg:province":"WA",
    "wof:name":"OPSM Optometry",
    "wof:placetype":"venue"
},
  "geometry": {"coordinates":[115.83802,-32.032337],"type":"Point"}
}