{
  "type": "Feature",
  "properties": {
    "addr:full":"Brisbane Arc Queen St Mall Brisbane QLD 4000",
    "addr:postcode":"4000",
    "addr:street":"Queen St Mall",
    "iso:country":"AU",
    "sg:address":"Brisbane Arc Queen St",
    "sg:city":"Mall Brisbane",
    "sg:classifiers":[
        {
            "category":"Shopping",
            "subcategory":"Jewelry",
            "type":"Retail Goods"
        }
    ],
    "sg:phone":"+61 7 3211 9110",
    "sg:postcode":"4000",
    "sg:province":"QLD",
    "sg:tags":[
        "jeweller"
    ],
    "wof:name":"Kosta Gold & Diamonds",
    "wof:placetype":"venue"
},
  "geometry": {"coordinates":[153.02276611299999,-27.4651203156],"type":"Point"}
}