{
  "type": "Feature",
  "properties": {
    "addr:full":"336 Cambridge St Wembley WA 6014",
    "addr:housenumber":"336",
    "addr:postcode":"6014",
    "addr:street":"Cambridge St",
    "iso:country":"AU",
    "sg:address":"336 Cambridge St",
    "sg:city":"Wembley",
    "sg:classifiers":[
        {
            "category":"Building & Trades",
            "subcategory":"Construction",
            "type":"Services"
        }
    ],
    "sg:phone":"+61 431 935 992",
    "sg:postcode":"6014",
    "sg:province":"WA",
    "sg:tags":[
        "window",
        "tinting"
    ],
    "wof:name":"Assured Window Tinting",
    "wof:placetype":"venue"
},
  "geometry": {"coordinates":[115.811080933,-31.9406147003],"type":"Point"}
}