{
  "type": "Feature",
  "properties": {
    "iso:country":"AU",
    "sg:address":"670 Port Rd",
    "sg:city":"Beverley",
    "sg:classifiers":[
        {
            "category":"Retail",
            "subcategory":"Auto Rental",
            "type":"Services"
        }
    ],
    "sg:phone":"+61 8 8345 0162",
    "sg:postcode":"5009",
    "sg:province":"SA",
    "sg:tags":[
        "chauffeur",
        "car",
        "hire",
        "driven",
        "limousine"
    ],
    "wof:name":"Drive My Limo",
    "wof:placetype":"venue"
},
  "geometry": {"coordinates":[138.548065186,-34.8897514343],"type":"Point"}
}