{
  "type": "Feature",
  "properties": {
    "addr:full":"1007 Glenhuntly Rd Caulfield South VIC 3162",
    "addr:housenumber":"1007",
    "addr:postcode":"3162",
    "addr:street":"Glenhuntly Rd",
    "iso:country":"AU",
    "sg:address":"1007 Glenhuntly Rd",
    "sg:city":"Caulfield South",
    "sg:classifiers":[
        {
            "category":"Health Services",
            "subcategory":"Health Practitioner",
            "type":"Services"
        }
    ],
    "sg:phone":"+61 3 9563 5513",
    "sg:postcode":"3162",
    "sg:province":"VIC",
    "sg:tags":[
        "psychologist"
    ],
    "wof:name":"Barabash Syndon",
    "wof:placetype":"venue"
},
  "geometry": {"coordinates":[145.03314209000001,-37.8881568909],"type":"Point"}
}