{
  "type": "Feature",
  "properties": {
    "iso:country":"AU",
    "sg:address":"10- 13 Hammond Pl",
    "sg:city":"Warrnambool",
    "sg:classifiers":[
        {
            "category":"Commercial Area",
            "type":"Public Place"
        }
    ],
    "sg:phone":"+61 409 529 332",
    "sg:postcode":"3280",
    "sg:province":"VIC",
    "sg:tags":[
        "heavy",
        "carrier"
    ],
    "wof:name":"Westvic Container Handling Pty Ltd",
    "wof:placetype":"venue"
},
  "geometry": {"coordinates":[142.45614624000001,-38.3666305542],"type":"Point"}
}