{
  "type": "Feature",
  "properties": {
    "iso:country":"AU",
    "sg:address":"307 Prospect Rd",
    "sg:city":"Blair Athol",
    "sg:classifiers":[
        {
            "category":"Shopping",
            "subcategory":"Clothing, Apparel, & Fashions",
            "type":"Retail Goods"
        }
    ],
    "sg:phone":"+61 8 8269 5788",
    "sg:postcode":"5084",
    "sg:province":"SA",
    "sg:tags":[
        "recycled",
        "clothing"
    ],
    "wof:name":"Lutheran Community Care and Clothing Shop",
    "wof:placetype":"venue"
},
  "geometry": {"coordinates":[138.59280395499999,-34.8663291931],"type":"Point"}
}