{
  "type": "Feature",
  "properties": {
    "addr:full":"1 Hutt St Adelaide SA 5000",
    "addr:housenumber":"1",
    "addr:postcode":"5000",
    "addr:street":"Hutt St",
    "iso:country":"AU",
    "sg:address":"1 Hutt St",
    "sg:city":"Adelaide",
    "sg:classifiers":[
        {
            "category":"Health Services",
            "subcategory":"Doctor",
            "type":"Services"
        }
    ],
    "sg:phone":"+61 8 8232 3525",
    "sg:postcode":"5000",
    "sg:province":"SA",
    "sg:tags":[
        "medical",
        "practitioner"
    ],
    "wof:name":"Doddridge M E",
    "wof:placetype":"venue"
},
  "geometry": {"coordinates":[138.61155700699999,-34.9257278442],"type":"Point"}
}