{
  "type": "Feature",
  "properties": {
    "iso:country":"AU",
    "sg:address":"30 Patrick St",
    "sg:city":"North Hobart",
    "sg:classifiers":[
        {
            "category":"Professional",
            "subcategory":"Art Services",
            "type":"Services"
        }
    ],
    "sg:phone":"+61 3 6231 1138",
    "sg:postcode":"7000",
    "sg:province":"TAS",
    "sg:tags":[
        "graphic",
        "designer"
    ],
    "wof:name":"Heath Pickett Design",
    "wof:placetype":"venue"
},
  "geometry": {"coordinates":[147.323287964,-42.8773918152],"type":"Point"}
}