{
  "type": "Feature",
  "properties": {
    "iso:country":"AU",
    "sg:address":"54- 56 Halsey Rd",
    "sg:city":"Airport West",
    "sg:classifiers":[
        {
            "category":"Building & Trades",
            "subcategory":"Construction",
            "type":"Services"
        }
    ],
    "sg:phone":"+61 3 9335 5479",
    "sg:postcode":"3042",
    "sg:province":"VIC",
    "sg:tags":[
        "window",
        "aluminium"
    ],
    "wof:name":"Calder Windows & Glass",
    "wof:placetype":"venue"
},
  "geometry": {"coordinates":[144.88677978499999,-37.7189598083],"type":"Point"}
}