{
  "type": "Feature",
  "properties": {
    "addr:full":"12 Donald St Guildford NSW 2161",
    "addr:housenumber":"12",
    "addr:postcode":"2161",
    "addr:street":"Donald St",
    "iso:country":"AU",
    "sg:address":"12 Donald St",
    "sg:city":"Guildford",
    "sg:classifiers":[
        {
            "category":"Home & Garden",
            "subcategory":"Building Materials",
            "type":"Retail Goods"
        }
    ],
    "sg:phone":"+61 1800 020 002",
    "sg:postcode":"2161",
    "sg:province":"NSW",
    "sg:tags":[
        "laminate",
        "laminated",
        "panel"
    ],
    "wof:name":"Arketique Solid Surface",
    "wof:placetype":"venue"
},
  "geometry": {"coordinates":[150.980834961,-33.8674354553],"type":"Point"}
}