{
  "type": "Feature",
  "properties": {
    "iso:country":"AU",
    "sg:address":"52 Seymour St",
    "sg:city":"Busselton",
    "sg:classifiers":[
        {
            "category":"Building & Trades",
            "subcategory":"Cleaning & Sanitation",
            "type":"Services"
        }
    ],
    "sg:phone":"+61 418 952 327",
    "sg:postcode":"6280",
    "sg:province":"WA",
    "sg:tags":[
        "commercial",
        "maintenance"
    ],
    "wof:name":"Barretts Handyman Services",
    "wof:placetype":"venue"
},
  "geometry": {"coordinates":[115.332969666,-33.6557540894],"type":"Point"}
}