{
  "type": "Feature",
  "properties": {
    "addr:full":"59 Hickory St Dorrigo NSW 2453",
    "addr:housenumber":"59",
    "addr:postcode":"2453",
    "addr:street":"Hickory St",
    "iso:country":"AU",
    "sg:address":"59 Hickory St",
    "sg:city":"Dorrigo",
    "sg:classifiers":[
        {
            "category":"Professional",
            "subcategory":"Computer Services",
            "type":"Services"
        }
    ],
    "sg:phone":"+61 2 6657 2982",
    "sg:postcode":"2453",
    "sg:province":"NSW",
    "sg:tags":[
        "repairs",
        "upgrade",
        "equipment"
    ],
    "wof:name":"Dorrigo Computer Services",
    "wof:placetype":"venue"
},
  "geometry": {"coordinates":[152.71206699999999,-30.339483],"type":"Point"}
}