{
  "type": "Feature",
  "properties": {
    "addr:full":"16 Forster Rd Mt Waverley VIC 3149",
    "addr:housenumber":"16",
    "addr:postcode":"3149",
    "addr:street":"Forster Rd",
    "iso:country":"AU",
    "sg:address":"16 Forster Rd",
    "sg:city":"Mt Waverley",
    "sg:classifiers":[
        {
            "category":"Communications",
            "type":"Services"
        }
    ],
    "sg:phone":"+61 418 508 201",
    "sg:postcode":"3149",
    "sg:province":"VIC",
    "sg:tags":[
        "public",
        "system",
        "address"
    ],
    "wof:name":"Glen Rumble",
    "wof:placetype":"venue"
},
  "geometry": {"coordinates":[145.13174438499999,-37.8868980408],"type":"Point"}
}