{
  "type": "Feature",
  "properties": {
    "addr:full":"34 Beluga St Mt Eliza VIC 3930",
    "addr:housenumber":"34",
    "addr:postcode":"3930",
    "addr:street":"Beluga St",
    "iso:country":"AU",
    "sg:address":"34 Beluga St",
    "sg:city":"Mt Eliza",
    "sg:classifiers":[
        {
            "category":"Home & Garden",
            "subcategory":"Building Materials",
            "type":"Retail Goods"
        }
    ],
    "sg:phone":"+61 3 9787 9931",
    "sg:postcode":"3930",
    "sg:province":"VIC",
    "sg:tags":[
        "lawn",
        "cutting",
        "maintenance"
    ],
    "wof:name":"Greenpeace Lawns",
    "wof:placetype":"venue"
},
  "geometry": {"coordinates":[145.07603454599999,-38.1977386475],"type":"Point"}
}