{
  "type": "Feature",
  "properties": {
    "iso:country":"AU",
    "sg:address":"44 Darley Rd",
    "sg:city":"Paradise",
    "sg:classifiers":[
        {
            "category":"Retail",
            "subcategory":"Repair Shop",
            "type":"Services"
        }
    ],
    "sg:phone":"+61 8 8365 1546",
    "sg:postcode":"5075",
    "sg:province":"SA",
    "sg:tags":[
        "recorder",
        "tape"
    ],
    "wof:name":"Techpro Engineering",
    "wof:placetype":"venue"
},
  "geometry": {"coordinates":[138.667205811,-34.8720207214],"type":"Point"}
}