{
  "type": "Feature",
  "properties": {
    "addr:full":"Shp 2/ 87 Mount Eliza Way Mt Eliza VIC 3930",
    "addr:housenumber":"/ 87",
    "addr:postcode":"3930",
    "addr:street":"Mount Eliza Way",
    "iso:country":"AU",
    "sg:address":"Shp 2/ 87",
    "sg:city":"Mount Eliza Way Mt Eliza",
    "sg:classifiers":[
        {
            "category":"Cafe",
            "type":"Food & Drink"
        }
    ],
    "sg:phone":"+61 3 9787 3738",
    "sg:postcode":"3930",
    "sg:province":"VIC",
    "wof:name":"In The Kitchen",
    "wof:placetype":"venue"
},
  "geometry": {"coordinates":[145.089309692,-38.1843070984],"type":"Point"}
}