{
  "type": "Feature",
  "properties": {
    "iso:country":"AU",
    "sg:address":"22 Mander Rd",
    "sg:city":"Holtze",
    "sg:classifiers":[
        {
            "category":"Shopping",
            "subcategory":"Computers & Home Electronics",
            "type":"Retail Goods"
        }
    ],
    "sg:phone":"+61 8 8939 0585",
    "sg:postcode":"0830",
    "sg:province":"NT",
    "sg:tags":[
        "hardware",
        "equipment"
    ],
    "wof:name":"iShop",
    "wof:placetype":"venue"
},
  "geometry": {"coordinates":[130.966629,-12.453044],"type":"Point"}
}