{
  "type": "Feature",
  "properties": {
    "addr:full":"19 Waverley Rd Malvern East VIC 3145",
    "addr:housenumber":"19",
    "addr:postcode":"3145",
    "addr:street":"Waverley Rd",
    "iso:country":"AU",
    "sg:address":"19 Waverley Rd",
    "sg:city":"Malvern East",
    "sg:classifiers":[
        {
            "category":"Health Services",
            "subcategory":"Medical Lab",
            "type":"Services"
        }
    ],
    "sg:phone":"+61 3 9572 1376",
    "sg:postcode":"3145",
    "sg:province":"VIC",
    "sg:tags":[
        "laboratory",
        "dental"
    ],
    "wof:name":"Prosthetic Dental Laboratories",
    "wof:placetype":"venue"
},
  "geometry": {"coordinates":[145.04319763199999,-37.8752288818],"type":"Point"}
}