{
  "type": "Feature",
  "properties": {
    "addr:full":"6/ 36 Kortum Drv Burleigh QLD 4220",
    "addr:housenumber":"/ 36",
    "addr:postcode":"4220",
    "addr:street":"Kortum Drv",
    "iso:country":"AU",
    "sg:address":"6/ 36 Kortum Drv",
    "sg:city":"Burleigh",
    "sg:classifiers":[
        {
            "category":"Building & Trades",
            "subcategory":"Equipment Rental",
            "type":"Services"
        }
    ],
    "sg:phone":"+61 1300 883 809",
    "sg:postcode":"4220",
    "sg:province":"QLD",
    "sg:tags":[
        "party",
        "hire"
    ],
    "wof:name":"Dreamweavers Hire",
    "wof:placetype":"venue"
},
  "geometry": {"coordinates":[153.427200317,-28.1033096313],"type":"Point"}
}