{
  "type": "Feature",
  "properties": {
    "iso:country":"AU",
    "sg:address":"Shop 40",
    "sg:city":"Stockland Super Centre Glendale",
    "sg:classifiers":[
        {
            "category":"Banks & Credit Unions",
            "subcategory":"Bank",
            "type":"Services"
        }
    ],
    "sg:phone":"+61 2 4956 7301",
    "sg:postcode":"2285",
    "sg:province":"NSW",
    "wof:name":"St George Bank Ltd",
    "wof:placetype":"venue"
},
  "geometry": {"coordinates":[151.64448547399999,-32.933506012],"type":"Point"}
}