{
  "type": "Feature",
  "properties": {
    "iso:country":"AU",
    "sg:address":"17 Elms Rd",
    "sg:city":"Mooroolbark",
    "sg:classifiers":[
        {
            "category":"Building & Trades",
            "subcategory":"Construction",
            "type":"Services"
        }
    ],
    "sg:phone":"+61 3 9726 8074",
    "sg:postcode":"3138",
    "sg:province":"VIC",
    "sg:tags":[
        "contractor"
    ],
    "wof:name":"Mazar L",
    "wof:placetype":"venue"
},
  "geometry": {"coordinates":[145.32640075699999,-37.7851715088],"type":"Point"}
}