{
  "type": "Feature",
  "properties": {
    "addr:full":"Unit 2 71A Rhodes St Hillsdale NSW 2036",
    "addr:housenumber":"71a",
    "addr:postcode":"2036",
    "addr:street":"Rhodes St",
    "iso:country":"AU",
    "sg:address":"Unit 2 71A Rhodes St",
    "sg:city":"Hillsdale",
    "sg:classifiers":[
        {
            "category":"Retail",
            "subcategory":"Auto Repair",
            "type":"Services"
        }
    ],
    "sg:phone":"+61 2 9661 3507",
    "sg:postcode":"2036",
    "sg:province":"NSW",
    "sg:tags":[
        "repairer",
        "motor",
        "engineer"
    ],
    "wof:name":"S & A Auto Repairs",
    "wof:placetype":"venue"
},
  "geometry": {"coordinates":[151.226287842,-33.950378418],"type":"Point"}
}