{
  "type": "Feature",
  "properties": {
    "addr:full":"1st Floor 940 Glenhuntly Rd Caulfield South VIC 3162",
    "addr:housenumber":"940",
    "addr:postcode":"3162",
    "addr:street":"Glenhuntly Rd",
    "iso:country":"AU",
    "sg:address":"1st Floor 940 Glenhuntly Rd",
    "sg:city":"Caulfield South",
    "sg:classifiers":[
        {
            "category":"Insurance",
            "subcategory":"Insurance Agent",
            "type":"Services"
        }
    ],
    "sg:phone":"+61 3 9572 0155",
    "sg:postcode":"3162",
    "sg:province":"VIC",
    "sg:tags":[
        "broker"
    ],
    "wof:name":"Armbro Insurance Brokers Pty Ltd",
    "wof:placetype":"venue"
},
  "geometry": {"coordinates":[145.02972412099999,-37.887966156],"type":"Point"}
}