{
  "type": "Feature",
  "properties": {
    "iso:country":"AU",
    "sg:address":"197 Ross River Rd",
    "sg:city":"Aitkenvale",
    "sg:classifiers":[
        {
            "category":"Organizations",
            "subcategory":"Labor Organization",
            "type":"Services"
        }
    ],
    "sg:phone":"+61 7 4725 5644",
    "sg:postcode":"4814",
    "sg:province":"QLD",
    "sg:tags":[
        "union"
    ],
    "wof:name":"Australasian Meat Industry Employees' Union",
    "wof:placetype":"venue"
},
  "geometry": {"coordinates":[146.776611,-19.296089],"type":"Point"}
}