{
  "type": "Feature",
  "properties": {
    "iso:country":"AU",
    "sg:address":"PO Box 8041",
    "sg:city":"Griffith East",
    "sg:classifiers":[
        {
            "category":"Building & Trades",
            "subcategory":"Landscaping Services",
            "type":"Services"
        }
    ],
    "sg:phone":"+61 418 267 140",
    "sg:postcode":"2680",
    "sg:province":"NSW",
    "sg:tags":[
        "designer",
        "landscape",
        "contractor"
    ],
    "wof:name":"Star Landscapes",
    "wof:placetype":"venue"
},
  "geometry": {"coordinates":[146.05879200000001,-34.283588],"type":"Point"}
}