{
  "type": "Feature",
  "properties": {
    "addr:full":"Shop 25 Bracken Ridge Plaza, Telegraph Rd Bracken Ridge QLD 4017",
    "addr:housenumber":"shop 25",
    "addr:postcode":"4017",
    "addr:street":"Telegraph Rd",
    "iso:country":"AU",
    "sg:address":"Shop 25 Bracken Ridge Plaza, Telegraph Rd",
    "sg:city":"Bracken Ridge",
    "sg:classifiers":[
        {
            "category":"Communications",
            "subcategory":"Film & Video Production",
            "type":"Services"
        }
    ],
    "sg:phone":"+61 7 3261 5900",
    "sg:postcode":"4017",
    "sg:province":"QLD",
    "sg:tags":[
        "dvd",
        "library"
    ],
    "wof:name":"Blockbuster",
    "wof:placetype":"venue"
},
  "geometry": {"coordinates":[153.026245117,-27.3311252594],"type":"Point"}
}