{
  "type": "Feature",
  "properties": {
    "addr:full":"4/ 68 Lexton Rd Box Hill VIC 3128",
    "addr:housenumber":"/ 68",
    "addr:postcode":"3128",
    "addr:street":"Lexton Rd",
    "iso:country":"AU",
    "sg:address":"4/ 68 Lexton Rd",
    "sg:city":"Box Hill",
    "sg:classifiers":[
        {
            "category":"Manufacturing",
            "subcategory":"Tools & Machinery",
            "type":"Manufacturing & Wholesale Goods"
        }
    ],
    "sg:phone":"+61 3 9897 1911",
    "sg:postcode":"3128",
    "sg:province":"VIC",
    "wof:name":"Baileys Toolbank",
    "wof:placetype":"venue"
},
  "geometry": {"coordinates":[145.139160156,-37.8125114441],"type":"Point"}
}