{
  "type": "Feature",
  "properties": {
    "addr:full":"Cnr Piggott St & Bellmere Rd Caboolture QLD 4510",
    "addr:postcode":"4510",
    "addr:street":"Cnr Piggott St & Bellmere Rd",
    "iso:country":"AU",
    "sg:address":"Cnr Piggott St & Bellmere Rd",
    "sg:city":"Caboolture",
    "sg:classifiers":[
        {
            "category":"Food & Beverages",
            "subcategory":"Bakery",
            "type":"Retail Goods"
        }
    ],
    "sg:phone":"+61 7 5495 5136",
    "sg:postcode":"4510",
    "sg:province":"QLD",
    "sg:tags":[
        "baker"
    ],
    "wof:name":"Bellmere Bakery",
    "wof:placetype":"venue"
},
  "geometry": {"coordinates":[152.93540999999999,-27.081141],"type":"Point"}
}