{
  "type": "Feature",
  "properties": {
    "addr:full":"22 Meriton St Gladesville NSW 2111",
    "addr:housenumber":"22",
    "addr:postcode":"2111",
    "addr:street":"Meriton St",
    "iso:country":"AU",
    "sg:address":"22 Meriton St",
    "sg:city":"Gladesville",
    "sg:classifiers":[
        {
            "category":"Building & Trades",
            "subcategory":"Construction",
            "type":"Services"
        }
    ],
    "sg:phone":"+61 2 9816 1936",
    "sg:postcode":"2111",
    "sg:province":"NSW",
    "sg:tags":[
        "brick",
        "paving"
    ],
    "wof:name":"Ben Hall Enterprises",
    "wof:placetype":"venue"
},
  "geometry": {"coordinates":[151.12347412099999,-33.8359832764],"type":"Point"}
}