{
  "type": "Feature",
  "properties": {
    "addr:full":"321-323 Sheridan St Cairns North QLD 4870",
    "addr:housenumber":"321-323",
    "addr:postcode":"4870",
    "addr:street":"Sheridan St",
    "iso:country":"AU",
    "sg:address":"321-323 Sheridan St",
    "sg:city":"Cairns North",
    "sg:classifiers":[
        {
            "category":"Health Services",
            "subcategory":"Doctor",
            "type":"Services"
        }
    ],
    "sg:phone":"+61 7 4041 4736",
    "sg:postcode":"4870",
    "sg:province":"QLD",
    "sg:tags":[
        "medical",
        "practitioner"
    ],
    "wof:name":"North Queensland Eye Clinic",
    "wof:placetype":"venue"
},
  "geometry": {"coordinates":[145.75941467300001,-16.9064464569],"type":"Point"}
}