{
  "type": "Feature",
  "properties": {
    "addr:full":"61 Collier Rd Morley WA 6062",
    "addr:housenumber":"61",
    "addr:postcode":"6062",
    "addr:street":"Collier Rd",
    "iso:country":"AU",
    "sg:address":"61 Collier Rd",
    "sg:city":"Morley",
    "sg:classifiers":[
        {
            "category":"Health Services",
            "subcategory":"Health Practitioner",
            "type":"Services"
        }
    ],
    "sg:phone":"+61 8 9276 7974",
    "sg:postcode":"6062",
    "sg:province":"WA",
    "sg:tags":[
        "naturopath"
    ],
    "wof:name":"Natural Health & Myotherapy Centre",
    "wof:placetype":"venue"
},
  "geometry": {"coordinates":[115.902481079,-31.8988246918],"type":"Point"}
}