{
  "type": "Feature",
  "properties": {
    "addr:full":"9 Thompson Crt Altona Meadows VIC 3028",
    "addr:housenumber":"9",
    "addr:postcode":"3028",
    "addr:street":"Thompson Crt",
    "iso:country":"AU",
    "sg:address":"9 Thompson Crt",
    "sg:city":"Altona Meadows",
    "sg:classifiers":[
        {
            "category":"Building & Trades",
            "subcategory":"Plumbing",
            "type":"Services"
        }
    ],
    "sg:phone":"+61 3 9315 6546",
    "sg:postcode":"3028",
    "sg:province":"VIC",
    "sg:tags":[
        "plumber",
        "gasfitters"
    ],
    "wof:name":"Mark Whiffin Plumbing Services",
    "wof:placetype":"venue"
},
  "geometry": {"coordinates":[144.78523300000001,-37.891171],"type":"Point"}
}