{
  "type": "Feature",
  "properties": {
    "iso:country":"AU",
    "sg:address":"98 Scarborough Beach Rd",
    "sg:city":"Mt Hawthorn",
    "sg:classifiers":[
        {
            "category":"Utilities",
            "subcategory":"Telephone",
            "type":"Services"
        }
    ],
    "sg:phone":"+61 8 9444 1288",
    "sg:postcode":"6016",
    "sg:province":"WA",
    "sg:tags":[
        "equipment",
        "system"
    ],
    "wof:name":"Icon Communications",
    "wof:placetype":"venue"
},
  "geometry": {"coordinates":[115.84342956499999,-31.9229488373],"type":"Point"}
}