{
  "type": "Feature",
  "properties": {
    "iso:country":"AU",
    "sg:address":"Old Sturt Hwy",
    "sg:city":"Berri",
    "sg:classifiers":[
        {
            "category":"Autos & Motor Vehicles",
            "subcategory":"Automobile Sales",
            "type":"Retail Goods"
        }
    ],
    "sg:phone":"+61 8 8582 2933",
    "sg:postcode":"5343",
    "sg:province":"SA",
    "sg:tags":[
        "car",
        "new"
    ],
    "wof:name":"Taylor Ford",
    "wof:placetype":"venue"
},
  "geometry": {"coordinates":[140.595214844,-34.2835884094],"type":"Point"}
}