{
  "type": "Feature",
  "properties": {
    "iso:country":"AU",
    "sg:address":"PO Box 839",
    "sg:city":"Ashmore City",
    "sg:classifiers":[
        {
            "category":"Building & Trades",
            "subcategory":"Construction",
            "type":"Services"
        }
    ],
    "sg:phone":"+61 411 027 013",
    "sg:postcode":"4214",
    "sg:province":"QLD",
    "sg:tags":[
        "brick",
        "paving"
    ],
    "wof:name":"D G M Paving",
    "wof:placetype":"venue"
},
  "geometry": {"coordinates":[153.38270568900001,-27.9863395691],"type":"Point"}
}