{
  "type": "Feature",
  "properties": {
    "addr:full":"67 Drummond St Carlton VIC 3053",
    "addr:housenumber":"67",
    "addr:postcode":"3053",
    "addr:street":"Drummond St",
    "iso:country":"AU",
    "sg:address":"67 Drummond St",
    "sg:city":"Carlton",
    "sg:classifiers":[
        {
            "category":"Building & Trades",
            "subcategory":"Cleaning & Sanitation",
            "type":"Services"
        }
    ],
    "sg:phone":"+61 3 9663 2111",
    "sg:postcode":"3053",
    "sg:province":"VIC",
    "sg:tags":[
        "window"
    ],
    "wof:name":"ACL Cleaning Services",
    "wof:placetype":"venue"
},
  "geometry": {"coordinates":[144.96746826200001,-37.8052978516],"type":"Point"}
}