{
  "type": "Feature",
  "properties": {
    "addr:full":"9 Old Lilydale Rd Ringwood East VIC 3135",
    "addr:housenumber":"9",
    "addr:postcode":"3135",
    "addr:street":"Old Lilydale Rd",
    "iso:country":"AU",
    "sg:address":"9 Old Lilydale Rd",
    "sg:city":"Ringwood East",
    "sg:classifiers":[
        {
            "category":"Insurance",
            "subcategory":"Hazard Insurance",
            "type":"Services"
        }
    ],
    "sg:phone":"+61 3 9879 5454",
    "sg:postcode":"3135",
    "sg:province":"VIC",
    "sg:tags":[
        "loss",
        "adjuster",
        "assessor"
    ],
    "wof:name":"Thomas D P & Associates Pty Ltd",
    "wof:placetype":"venue"
},
  "geometry": {"coordinates":[145.254074097,-37.803981781],"type":"Point"}
}