{
  "type": "Feature",
  "properties": {
    "addr:full":"79b Wright St Sunshine VIC 3020",
    "addr:housenumber":"79b",
    "addr:postcode":"3020",
    "addr:street":"Wright St",
    "iso:country":"AU",
    "sg:address":"79b Wright St",
    "sg:city":"Sunshine",
    "sg:classifiers":[
        {
            "category":"Professional",
            "type":"Services"
        }
    ],
    "sg:phone":"+61 3 9312 4445",
    "sg:postcode":"3020",
    "sg:province":"VIC",
    "sg:tags":[
        "transport"
    ],
    "wof:name":"Australian Transport Logistics",
    "wof:placetype":"venue"
},
  "geometry": {"coordinates":[144.82835399999999,-37.795776],"type":"Point"}
}