{
  "type": "Feature",
  "properties": {
    "addr:full":"325 Gosport St Moree NSW 2400",
    "addr:housenumber":"325",
    "addr:postcode":"2400",
    "addr:street":"Gosport St",
    "iso:country":"AU",
    "sg:address":"325 Gosport St",
    "sg:city":"Moree",
    "sg:classifiers":[
        {
            "category":"Restaurant",
            "type":"Food & Drink"
        }
    ],
    "sg:phone":"+61 2 6752 5233",
    "sg:postcode":"2400",
    "sg:province":"NSW",
    "wof:name":"Cascades Theatre & Chargrill Pty Ltd",
    "wof:placetype":"venue"
},
  "geometry": {"coordinates":[149.847122192,-29.4726161957],"type":"Point"}
}