{
  "type": "Feature",
  "properties": {
    "addr:full":"6 Pegus St Thornlie WA 6108",
    "addr:housenumber":"6",
    "addr:postcode":"6108",
    "addr:street":"Pegus St",
    "iso:country":"AU",
    "sg:address":"6 Pegus St",
    "sg:city":"Thornlie",
    "sg:classifiers":[
        {
            "category":"Professional",
            "subcategory":"Accounting & Tax Preparation",
            "type":"Services"
        }
    ],
    "sg:phone":"+61 413 296 771",
    "sg:postcode":"6108",
    "sg:province":"WA",
    "sg:tags":[
        "consultant",
        "taxation"
    ],
    "wof:name":"BTS Bookeeping & Tax Services",
    "wof:placetype":"venue"
},
  "geometry": {"coordinates":[115.962333679,-32.0479698181],"type":"Point"}
}