{
  "type": "Feature",
  "properties": {
    "addr:full":"Heidelberg Crt Healesville VIC 3777",
    "addr:postcode":"3777",
    "addr:street":"Heidelberg Crt",
    "iso:country":"AU",
    "sg:address":"Heidelberg Crt",
    "sg:city":"Healesville",
    "sg:classifiers":[
        {
            "category":"Building & Trades",
            "subcategory":"Landscaping Services",
            "type":"Services"
        }
    ],
    "sg:phone":"+61 3 5962 2324",
    "sg:postcode":"3777",
    "sg:province":"VIC",
    "sg:tags":[
        "designer",
        "landscape",
        "contractor"
    ],
    "wof:name":"Clarke Y V",
    "wof:placetype":"venue"
},
  "geometry": {"coordinates":[145.53822299999999,-37.673679],"type":"Point"}
}