{
  "type": "Feature",
  "properties": {
    "addr:full":"8 Mernda Rd Olinda VIC 3788",
    "addr:housenumber":"8",
    "addr:postcode":"3788",
    "addr:street":"Mernda Rd",
    "iso:country":"AU",
    "sg:address":"8 Mernda Rd",
    "sg:city":"Olinda",
    "sg:classifiers":[
        {
            "category":"Building & Trades",
            "subcategory":"Landscaping Services",
            "type":"Services"
        }
    ],
    "sg:phone":"+61 3 9751 2714",
    "sg:postcode":"3788",
    "sg:province":"VIC",
    "sg:tags":[
        "designer",
        "landscape",
        "contractor"
    ],
    "wof:name":"Gardens",
    "wof:placetype":"venue"
},
  "geometry": {"coordinates":[145.382767,-37.87421],"type":"Point"}
}