{
  "type": "Feature",
  "properties": {
    "addr:full":"Ballajura City Shopping Centre 225 Illawarra Crs Ballajura WA 6066",
    "addr:housenumber":"225",
    "addr:postcode":"6066",
    "addr:street":"Illawarra Crs",
    "iso:country":"AU",
    "sg:address":"Ballajura City Shopping Centre 225 Illawarra Crs",
    "sg:city":"Ballajura",
    "sg:classifiers":[
        {
            "category":"Personal",
            "subcategory":"Beauty Salon",
            "type":"Services"
        }
    ],
    "sg:phone":"+61 8 9249 5533",
    "sg:postcode":"6066",
    "sg:province":"WA",
    "sg:tags":[
        "hairdresser"
    ],
    "wof:name":"Hair Exclusive Unisex",
    "wof:placetype":"venue"
},
  "geometry": {"coordinates":[116.133247376,-32.0911560059],"type":"Point"}
}