{
  "type": "Feature",
  "properties": {
    "addr:full":"120 Swallow St Mooroobool QLD 4870",
    "addr:housenumber":"120",
    "addr:postcode":"4870",
    "addr:street":"Swallow St",
    "iso:country":"AU",
    "sg:address":"120 Swallow St",
    "sg:city":"Mooroobool",
    "sg:classifiers":[
        {
            "category":"Social Services",
            "subcategory":"Child Care",
            "type":"Services"
        }
    ],
    "sg:phone":"+61 7 4032 3588",
    "sg:postcode":"4870",
    "sg:province":"QLD",
    "wof:name":"Mooroobool's Children's Centre",
    "wof:placetype":"venue"
},
  "geometry": {"coordinates":[145.737594605,-16.9301834106],"type":"Point"}
}