{
  "type": "Feature",
  "properties": {
    "iso:country":"AU",
    "sg:address":"Aerodrome Rd",
    "sg:city":"Caboolture",
    "sg:classifiers":[
        {
            "category":"Recreation",
            "subcategory":"Sailing Club",
            "type":"Entertainment"
        }
    ],
    "sg:phone":"+61 7 5495 3882",
    "sg:postcode":"4510",
    "sg:province":"QLD",
    "sg:tags":[
        "gliding",
        "flying"
    ],
    "wof:name":"Caboolture Aero Club",
    "wof:placetype":"venue"
},
  "geometry": {"coordinates":[152.981583,-27.079426],"type":"Point"}
}