{
  "type": "Feature",
  "properties": {
    "addr:full":"82 Franmaree Rd Newnham TAS 7248",
    "addr:housenumber":"82",
    "addr:postcode":"7248",
    "addr:street":"Franmaree Rd",
    "iso:country":"AU",
    "sg:address":"82 Franmaree Rd",
    "sg:city":"Newnham",
    "sg:classifiers":[
        {
            "category":"Home & Garden",
            "subcategory":"Building Materials",
            "type":"Retail Goods"
        }
    ],
    "sg:phone":"+61 408 128 467",
    "sg:postcode":"7248",
    "sg:province":"TAS",
    "sg:tags":[
        "concrete",
        "gutter",
        "kerb"
    ],
    "wof:name":"Northern Concrete Constructions",
    "wof:placetype":"venue"
},
  "geometry": {"coordinates":[147.11631774899999,-41.3825721741],"type":"Point"}
}