{
  "type": "Feature",
  "properties": {
    "addr:full":"U3/ 10 Ereton Drv Labrador QLD 4215",
    "addr:postcode":"4215",
    "addr:street":"U3 / 10 Ereton Drv",
    "iso:country":"AU",
    "sg:address":"U3/ 10 Ereton Drv",
    "sg:city":"Labrador",
    "sg:classifiers":[
        {
            "category":"Retail",
            "subcategory":"Auto Repair",
            "type":"Services"
        }
    ],
    "sg:phone":"+61 7 5563 7022",
    "sg:postcode":"4215",
    "sg:province":"QLD",
    "sg:tags":[
        "beater",
        "painter",
        "panel"
    ],
    "wof:name":"Mr-Car-Aligner Australia Pty Ltd",
    "wof:placetype":"venue"
},
  "geometry": {"coordinates":[153.38619995100001,-27.9348106384],"type":"Point"}
}