{
  "type": "Feature",
  "properties": {
    "iso:country":"AU",
    "sg:address":"Suite 1, 199 Union St",
    "sg:city":"The Junction",
    "sg:classifiers":[
        {
            "category":"Health Services",
            "subcategory":"Health Practitioner",
            "type":"Services"
        }
    ],
    "sg:phone":"+61 2 4961 4612",
    "sg:postcode":"2291",
    "sg:province":"NSW",
    "sg:tags":[
        "naturopath"
    ],
    "wof:name":"Standen Kylie",
    "wof:placetype":"venue"
},
  "geometry": {"coordinates":[151.75901794399999,-32.9384002686],"type":"Point"}
}