{
  "type": "Feature",
  "properties": {
    "iso:country":"AU",
    "sg:address":"Shop 3/ 273 Sibley Rd",
    "sg:city":"Wynnum West",
    "sg:classifiers":[
        {
            "category":"Personal",
            "subcategory":"Beauty Salon",
            "type":"Services"
        }
    ],
    "sg:phone":"+61 7 3396 7559",
    "sg:postcode":"4178",
    "sg:province":"QLD",
    "sg:tags":[
        "hairdresser"
    ],
    "wof:name":"Euro Hair Design",
    "wof:placetype":"venue"
},
  "geometry": {"coordinates":[153.144256592,-27.4425868988],"type":"Point"}
}