{
  "type": "Feature",
  "properties": {
    "addr:full":"12 Langer Pl Arundel QLD 4214",
    "addr:postcode":"4214",
    "addr:street":"Langer Pl",
    "iso:country":"AU",
    "sg:address":"12 Langer Pl",
    "sg:city":"Arundel",
    "sg:classifiers":[
        {
            "category":"Health Services",
            "subcategory":"Health Practitioner",
            "type":"Services"
        }
    ],
    "sg:phone":"+61 7 5574 5323",
    "sg:postcode":"4214",
    "sg:province":"QLD",
    "sg:tags":[
        "alternative"
    ],
    "wof:name":"Mind Body Medicine Clinic",
    "wof:placetype":"venue"
},
  "geometry": {"coordinates":[153.376831055,-27.9456386566],"type":"Point"}
}