{
  "type": "Feature",
  "properties": {
    "addr:full":"43- 47 Lyn Pde Prestons NSW 2170",
    "addr:housenumber":"47",
    "addr:postcode":"2170",
    "addr:street":"Lyn Pde",
    "iso:country":"AU",
    "sg:address":"43- 47 Lyn Pde",
    "sg:city":"Prestons",
    "sg:classifiers":[
        {
            "category":"Manufacturing",
            "subcategory":"Metals",
            "type":"Manufacturing & Wholesale Goods"
        }
    ],
    "sg:phone":"+61 2 9607 1555",
    "sg:postcode":"2170",
    "sg:province":"NSW",
    "sg:tags":[
        "steel",
        "fabricator",
        "mfrs"
    ],
    "wof:name":"Natsteel Australia Pty Ltd",
    "wof:placetype":"venue"
},
  "geometry": {"coordinates":[150.88760375999999,-33.931098938],"type":"Point"}
}