{
  "type": "Feature",
  "properties": {
    "addr:full":"487 High St Prahran VIC 3181",
    "addr:housenumber":"487",
    "addr:postcode":"3181",
    "addr:street":"High St",
    "iso:country":"AU",
    "sg:address":"487 High St",
    "sg:city":"Prahran",
    "sg:classifiers":[
        {
            "category":"Shopping",
            "subcategory":"Jewelry",
            "type":"Retail Goods"
        }
    ],
    "sg:phone":"+61 3 9529 3244",
    "sg:postcode":"3181",
    "sg:province":"VIC",
    "sg:tags":[
        "jeweller"
    ],
    "wof:name":"Celtic Origins",
    "wof:placetype":"venue"
},
  "geometry": {"coordinates":[145.004302978,-37.8531723022],"type":"Point"}
}