{
  "type": "Feature",
  "properties": {
    "iso:country":"AU",
    "sg:address":"Bridge St (Cnr Abel St)",
    "sg:city":"Boyup Brook",
    "sg:classifiers":[
        {
            "category":"Landmark",
            "subcategory":"Tourist Information",
            "type":"Public Place"
        }
    ],
    "sg:phone":"+61 8 9765 1444",
    "sg:postcode":"6244",
    "sg:province":"WA",
    "sg:tags":[
        "bureau"
    ],
    "wof:name":"Boyup Brook Tourist Information Centre",
    "wof:placetype":"venue"
},
  "geometry": {"coordinates":[116.388328552,-33.8355484009],"type":"Point"}
}