{
  "type": "Feature",
  "properties": {
    "addr:full":"8 Lefroy Ave Midland WA 6056",
    "addr:housenumber":"8",
    "addr:postcode":"6056",
    "addr:street":"Lefroy Ave",
    "iso:country":"AU",
    "sg:address":"8 Lefroy Ave",
    "sg:city":"Midland",
    "sg:classifiers":[
        {
            "category":"Retail",
            "subcategory":"Auto Repair",
            "type":"Services"
        }
    ],
    "sg:phone":"+61 8 9274 1101",
    "sg:postcode":"6056",
    "sg:province":"WA",
    "sg:tags":[
        "beater",
        "painter",
        "panel"
    ],
    "wof:name":"A-Lign Panel & Paint",
    "wof:placetype":"venue"
},
  "geometry": {"coordinates":[116.016983032,-31.8939495087],"type":"Point"}
}