{
  "type": "Feature",
  "properties": {
    "addr:full":"38 Parkwood Ave Woodvale WA 6026",
    "addr:housenumber":"38",
    "addr:postcode":"6026",
    "addr:street":"Parkwood Ave",
    "iso:country":"AU",
    "sg:address":"38 Parkwood Ave",
    "sg:city":"Woodvale",
    "sg:classifiers":[
        {
            "category":"Mining & Drilling",
            "type":"Manufacturing & Wholesale Goods"
        }
    ],
    "sg:phone":"+61 8 9390 9652",
    "sg:postcode":"6026",
    "sg:province":"WA",
    "sg:tags":[
        "boring",
        "contractor"
    ],
    "wof:name":"Fluidstar",
    "wof:placetype":"venue"
},
  "geometry": {"coordinates":[115.784973145,-31.7818489075],"type":"Point"}
}