{
  "type": "Feature",
  "properties": {
    "addr:full":"5 Dunlop Pl Ashmont NSW 2650",
    "addr:housenumber":"5",
    "addr:postcode":"2650",
    "addr:street":"Dunlop Pl",
    "iso:country":"AU",
    "sg:address":"5 Dunlop Pl",
    "sg:city":"Ashmont",
    "sg:classifiers":[
        {
            "category":"Organizations",
            "subcategory":"Non-profit Organization",
            "type":"Services"
        }
    ],
    "sg:phone":"+61 2 6971 3038",
    "sg:postcode":"2650",
    "sg:province":"NSW",
    "sg:tags":[
        "support",
        "disability",
        "organisation"
    ],
    "wof:name":"Northcott Society",
    "wof:placetype":"venue"
},
  "geometry": {"coordinates":[147.339309692,-35.1173782349],"type":"Point"}
}