{
  "type": "Feature",
  "properties": {
    "addr:full":"Aspley Homemaker Centre, Cnr Zillmere & Gympies Ro Aspley QLD 4034",
    "addr:postcode":"4034",
    "addr:street":"Cnr",
    "iso:country":"AU",
    "sg:address":"Aspley Homemaker Centre, Cnr Zillmere & Gympies Ro",
    "sg:city":"Aspley",
    "sg:classifiers":[
        {
            "category":"Building & Trades",
            "subcategory":"Equipment Rental",
            "type":"Services"
        }
    ],
    "sg:phone":"+61 7 3263 8266",
    "sg:postcode":"4034",
    "sg:province":"QLD",
    "sg:tags":[
        "fitness"
    ],
    "wof:name":"Workout World",
    "wof:placetype":"venue"
},
  "geometry": {"coordinates":[153.019913,-27.356684],"type":"Point"}
}