{
  "type": "Feature",
  "properties": {
    "addr:full":"Unit 2/ 34 Tradelink Rd Hillcrest QLD 4118",
    "addr:postcode":"4118",
    "addr:street":"34 Tradelink Rd",
    "iso:country":"AU",
    "sg:address":"Unit 2/ 34 Tradelink Rd",
    "sg:city":"Hillcrest",
    "sg:classifiers":[
        {
            "category":"Arena",
            "subcategory":"Indoor Arena",
            "type":"Entertainment"
        }
    ],
    "sg:phone":"+61 7 3802 8663",
    "sg:postcode":"4118",
    "sg:province":"QLD",
    "sg:tags":[
        "modelmakers"
    ],
    "wof:name":"Amalgamated Engineering Pattern Makers",
    "wof:placetype":"venue"
},
  "geometry": {"coordinates":[153.03404235799999,-27.6648178101],"type":"Point"}
}