{
  "type": "Feature",
  "properties": {
    "addr:full":"Shop AF 16, Canberra Centre Canberra ACT 2600",
    "addr:postcode":"2600",
    "addr:street":"Af 16",
    "iso:country":"AU",
    "sg:address":"Shop AF 16, Canberra Centre",
    "sg:city":"Canberra",
    "sg:classifiers":[
        {
            "category":"Shopping",
            "subcategory":"Shoes",
            "type":"Retail Goods"
        }
    ],
    "sg:phone":"+61 2 6257 5398",
    "sg:postcode":"2600",
    "sg:province":"ACT",
    "sg:tags":[
        "footwear"
    ],
    "wof:name":"Aquila Shoes",
    "wof:placetype":"venue"
},
  "geometry": {"coordinates":[149.13059997600001,-35.3158035278],"type":"Point"}
}