{
  "type": "Feature",
  "properties": {
    "addr:full":"5 Wadell Rd Gympie QLD 4570",
    "addr:housenumber":"5",
    "addr:postcode":"4570",
    "addr:street":"Wadell Rd",
    "iso:country":"AU",
    "sg:address":"5 Wadell Rd",
    "sg:city":"Gympie",
    "sg:classifiers":[
        {
            "category":"Wholesale",
            "subcategory":"Construction Materials",
            "type":"Manufacturing & Wholesale Goods"
        }
    ],
    "sg:phone":"+61 7 5482 1757",
    "sg:postcode":"4570",
    "sg:province":"QLD",
    "sg:tags":[
        "protective",
        "coating"
    ],
    "wof:name":"Cooloola Sandblasting & Industrial Painting",
    "wof:placetype":"venue"
},
  "geometry": {"coordinates":[152.646682739,-26.1707019806],"type":"Point"}
}