{
  "type": "Feature",
  "properties": {
    "addr:full":"683 George St Sydney NSW 2000",
    "addr:housenumber":"683",
    "addr:postcode":"2000",
    "addr:street":"George St",
    "iso:country":"AU",
    "sg:address":"683 George St",
    "sg:city":"Sydney",
    "sg:classifiers":[
        {
            "category":"Shopping",
            "subcategory":"Music",
            "type":"Retail Goods"
        }
    ],
    "sg:phone":"+61 2 9281 8811",
    "sg:postcode":"2000",
    "sg:province":"NSW",
    "sg:tags":[
        "store"
    ],
    "wof:name":"Golden Winner Network Pty Ltd",
    "wof:placetype":"venue"
},
  "geometry": {"coordinates":[151.205154419,-33.8797874451],"type":"Point"}
}