{
  "type": "Feature",
  "properties": {
    "iso:country":"AU",
    "sg:address":"172 Barrington St",
    "sg:city":"Spearwood",
    "sg:classifiers":[
        {
            "category":"Fast Food",
            "type":"Food & Drink"
        }
    ],
    "sg:phone":"+61 8 9418 1094",
    "sg:postcode":"6163",
    "sg:province":"WA",
    "sg:tags":[
        "away",
        "take"
    ],
    "wof:name":"Cheffy's Food Bar",
    "wof:placetype":"venue"
},
  "geometry": {"coordinates":[115.78868900000001,-32.116508],"type":"Point"}
}