{
  "type": "Feature",
  "properties": {
    "addr:full":"Lot 15A Minesite LIA Tom Price WA 6751",
    "addr:postcode":"6751",
    "addr:street":"Minesite Lia",
    "iso:country":"AU",
    "sg:address":"Lot 15A Minesite LIA",
    "sg:city":"Tom Price",
    "sg:classifiers":[
        {
            "category":"Building & Trades",
            "subcategory":"Construction",
            "type":"Services"
        }
    ],
    "sg:phone":"+61 8 9188 1600",
    "sg:postcode":"6751",
    "sg:province":"WA",
    "sg:tags":[
        "excavation",
        "foundation"
    ],
    "wof:name":"Gumala Contracting",
    "wof:placetype":"venue"
},
  "geometry": {"coordinates":[117.784286499,-22.6861400604],"type":"Point"}
}