{
  "type": "Feature",
  "properties": {
    "addr:full":"39 Kendal St Cowra NSW 2794",
    "addr:housenumber":"39",
    "addr:postcode":"2794",
    "addr:street":"Kendal St",
    "iso:country":"AU",
    "sg:address":"39 Kendal St",
    "sg:city":"Cowra",
    "sg:classifiers":[
        {
            "category":"Professional",
            "subcategory":"Employment Agencies",
            "type":"Services"
        }
    ],
    "sg:phone":"+61 2 6341 1640",
    "sg:postcode":"2794",
    "sg:province":"NSW",
    "wof:name":"Central West Community College Ltd",
    "wof:placetype":"venue"
},
  "geometry": {"coordinates":[148.69776916500001,-33.8355636597],"type":"Point"}
}