{
  "type": "Feature",
  "properties": {
    "iso:country":"AU",
    "sg:address":"295 Campbell St",
    "sg:city":"Swan Hill",
    "sg:classifiers":[
        {
            "category":"Cinema",
            "subcategory":"Movie Theater",
            "type":"Entertainment"
        }
    ],
    "sg:phone":"+61 3 5032 3344",
    "sg:postcode":"3585",
    "sg:province":"NSW",
    "wof:name":"Oasis Twin Cinemas",
    "wof:placetype":"venue"
},
  "geometry": {"coordinates":[143.560867,-35.342686],"type":"Point"}
}