{
  "type": "Feature",
  "properties": {
    "addr:full":"Shop 2/ 46 Broad St Sarina QLD 4737",
    "addr:housenumber":"shop 2 / 46",
    "addr:postcode":"4737",
    "addr:street":"Broad St",
    "iso:country":"AU",
    "sg:address":"Shop 2/ 46 Broad St",
    "sg:city":"Sarina",
    "sg:classifiers":[
        {
            "category":"Fast Food",
            "type":"Food & Drink"
        }
    ],
    "sg:phone":"+61 7 4956 1439",
    "sg:postcode":"4737",
    "sg:province":"QLD",
    "sg:tags":[
        "away",
        "take"
    ],
    "wof:name":"Sarina Seafoods",
    "wof:placetype":"venue"
},
  "geometry": {"coordinates":[149.217468,-21.422176],"type":"Point"}
}