{
  "type": "Feature",
  "properties": {
    "addr:full":"1st Floor, 30 Ledgar Rd Balcatta WA 6021",
    "addr:housenumber":"30",
    "addr:postcode":"6021",
    "addr:street":"Ledgar Rd",
    "iso:country":"AU",
    "sg:address":"1st Floor, 30 Ledgar Rd",
    "sg:city":"Balcatta",
    "sg:classifiers":[
        {
            "category":"Professional",
            "subcategory":"Accounting & Tax Preparation",
            "type":"Services"
        }
    ],
    "sg:phone":"+61 8 9240 2665",
    "sg:postcode":"6021",
    "sg:province":"WA",
    "sg:tags":[
        "consultant",
        "taxation"
    ],
    "wof:name":"PTR Business Services",
    "wof:placetype":"venue"
},
  "geometry": {"coordinates":[115.803367615,-31.8626556396],"type":"Point"}
}