{
  "type": "Feature",
  "properties": {
    "addr:full":"Shop 8/ 19 O'Brien St Bondi Beach NSW 2026",
    "addr:housenumber":"shop 8 / 19",
    "addr:postcode":"2026",
    "addr:street":"O'Brien St",
    "iso:country":"AU",
    "sg:address":"Shop 8/ 19 O'Brien St",
    "sg:city":"Bondi Beach",
    "sg:classifiers":[
        {
            "category":"Food & Beverages",
            "subcategory":"Groceries & Convenience Stores",
            "type":"Retail Goods"
        }
    ],
    "sg:phone":"+61 2 9130 8578",
    "sg:postcode":"2026",
    "sg:province":"NSW",
    "wof:name":"Oz 5 Convenience Store The",
    "wof:placetype":"venue"
},
  "geometry": {"coordinates":[151.26873779300001,-33.8888702393],"type":"Point"}
}