{
  "type": "Feature",
  "properties": {
    "addr:full":"17 Judith Drv Athelstone SA 5076",
    "addr:housenumber":"17",
    "addr:postcode":"5076",
    "addr:street":"Judith Drv",
    "iso:country":"AU",
    "sg:address":"17 Judith Drv",
    "sg:city":"Athelstone",
    "sg:classifiers":[
        {
            "category":"Building & Trades",
            "subcategory":"Pest Control",
            "type":"Services"
        }
    ],
    "sg:phone":"+61 8 8337 8263",
    "sg:postcode":"5076",
    "sg:province":"SA",
    "sg:tags":[
        "wholesaler",
        "mfrs",
        "walking",
        "umbrella",
        "stick"
    ],
    "wof:name":"Clifton Umbrellas",
    "wof:placetype":"venue"
},
  "geometry": {"coordinates":[138.69920349099999,-34.8795661926],"type":"Point"}
}