{
  "type": "Feature",
  "properties": {
    "iso:country":"AU",
    "sg:address":"8-10 Cottage La",
    "sg:city":"Hackham",
    "sg:classifiers":[
        {
            "category":"Retail",
            "subcategory":"Auto Repair",
            "type":"Services"
        }
    ],
    "sg:phone":"+61 8 8384 3591",
    "sg:postcode":"5163",
    "sg:province":"SA",
    "sg:tags":[
        "beater",
        "painter",
        "panel"
    ],
    "wof:name":"Steve's Body Shop",
    "wof:placetype":"venue"
},
  "geometry": {"coordinates":[138.52670288100001,-35.1505622864],"type":"Point"}
}