{
  "type": "Feature",
  "properties": {
    "iso:country":"AU",
    "sg:address":"Ground Floor, 283 Elizabeth St",
    "sg:city":"Brisbane",
    "sg:classifiers":[
        {
            "category":"Travel",
            "subcategory":"Travel Agent",
            "type":"Entertainment"
        }
    ],
    "sg:phone":"+61 1300 302 623",
    "sg:postcode":"4000",
    "sg:province":"QLD",
    "sg:tags":[
        "consultant"
    ],
    "wof:name":"Renault Eurodrive Leasing",
    "wof:placetype":"venue"
},
  "geometry": {"coordinates":[153.029006958,-27.4682121277],"type":"Point"}
}