{
  "type": "Feature",
  "properties": {
    "addr:full":"Level 3 69 Phillip St Parramatta NSW 2151",
    "addr:housenumber":"69",
    "addr:postcode":"2151",
    "addr:street":"Phillip St",
    "iso:country":"AU",
    "sg:address":"Level 3 69 Phillip St",
    "sg:city":"Parramatta",
    "sg:classifiers":[
        {
            "category":"Professional",
            "subcategory":"Accounting & Tax Preparation",
            "type":"Services"
        }
    ],
    "sg:phone":"+61 2 9893 8600",
    "sg:postcode":"2151",
    "sg:province":"NSW",
    "sg:tags":[
        "accountant",
        "auditor"
    ],
    "wof:name":"Marcos Accountants Pty Ltd",
    "wof:placetype":"venue"
},
  "geometry": {"coordinates":[151.005615234,-33.8128395081],"type":"Point"}
}