{
  "type": "Feature",
  "properties": {
    "addr:full":"215 Learmonth Rd Wendouree VIC 3355",
    "addr:housenumber":"215",
    "addr:postcode":"3355",
    "addr:street":"Learmonth Rd",
    "iso:country":"AU",
    "sg:address":"215 Learmonth Rd",
    "sg:city":"Wendouree",
    "sg:classifiers":[
        {
            "category":"Wholesale",
            "subcategory":"Machinery & Supplies",
            "type":"Manufacturing & Wholesale Goods"
        }
    ],
    "sg:phone":"+61 3 5339 3062",
    "sg:postcode":"3355",
    "sg:province":"VIC",
    "sg:tags":[
        "agricultural"
    ],
    "wof:name":"Farm Masters & Irish Machinery",
    "wof:placetype":"venue"
},
  "geometry": {"coordinates":[143.81376599999999,-37.530243],"type":"Point"}
}