{
  "type": "Feature",
  "properties": {
    "addr:full":"386 Albert St Balcatta WA 6021",
    "addr:housenumber":"386",
    "addr:postcode":"6021",
    "addr:street":"Albert St",
    "iso:country":"AU",
    "sg:address":"386 Albert St",
    "sg:city":"Balcatta",
    "sg:classifiers":[
        {
            "category":"Education",
            "subcategory":"Kindergarten",
            "type":"Public Place"
        }
    ],
    "sg:phone":"+61 8 9344 4944",
    "sg:postcode":"6021",
    "sg:province":"WA",
    "sg:tags":[
        "pre-schools"
    ],
    "wof:name":"Catholic Church",
    "wof:placetype":"venue"
},
  "geometry": {"coordinates":[115.827331543,-31.878578186],"type":"Point"}
}