{
  "type": "Feature",
  "properties": {
    "addr:full":"Brisbane Technology Park, 30b McKechnie Drv Eight Mile Plains QLD 4113",
    "addr:housenumber":"30b",
    "addr:postcode":"4113",
    "addr:street":"Mckechnie Drv",
    "iso:country":"AU",
    "sg:address":"Brisbane Technology Park, 30b McKechnie Drv",
    "sg:city":"Eight Mile Plains",
    "sg:classifiers":[
        {
            "category":"Education",
            "subcategory":"University",
            "type":"Public Place"
        }
    ],
    "sg:phone":"+61 7 3841 5500",
    "sg:postcode":"4113",
    "sg:province":"QLD",
    "sg:tags":[
        "college",
        "tertiary"
    ],
    "wof:name":"CEED Program (Qld)",
    "wof:placetype":"venue"
},
  "geometry": {"coordinates":[153.097366333,-27.5783882141],"type":"Point"}
}