{
  "type": "Feature",
  "properties": {
    "addr:full":"Shop 4/ 8 North St Batemans Bay NSW 2536",
    "addr:housenumber":"shop 4 / 8",
    "addr:postcode":"2536",
    "addr:street":"North St",
    "iso:country":"AU",
    "sg:address":"Shop 4/ 8 North St",
    "sg:city":"Batemans Bay",
    "sg:classifiers":[
        {
            "category":"Shopping",
            "subcategory":"Computers & Home Electronics",
            "type":"Retail Goods"
        }
    ],
    "sg:phone":"+61 2 4472 7170",
    "sg:postcode":"2536",
    "sg:province":"NSW",
    "sg:tags":[
        "hardware",
        "equipment"
    ],
    "wof:name":"Active Computer Technologies",
    "wof:placetype":"venue"
},
  "geometry": {"coordinates":[150.17762756400001,-35.7090759277],"type":"Point"}
}