{
  "type": "Feature",
  "properties": {
    "addr:full":"36 Regent St Chippendale NSW 2008",
    "addr:housenumber":"36",
    "addr:postcode":"2008",
    "addr:street":"Regent St",
    "iso:country":"AU",
    "sg:address":"36 Regent St",
    "sg:city":"Chippendale",
    "sg:classifiers":[
        {
            "category":"Health Services",
            "subcategory":"Doctor",
            "type":"Services"
        }
    ],
    "sg:phone":"+61 2 9211 2311",
    "sg:postcode":"2008",
    "sg:province":"NSW",
    "sg:tags":[
        "medical",
        "practitioner"
    ],
    "wof:name":"Clinic 36",
    "wof:placetype":"venue"
},
  "geometry": {"coordinates":[151.20184326200001,-33.8868942261],"type":"Point"}
}