{
  "type": "Feature",
  "properties": {
    "iso:country":"AU",
    "sg:address":"12 George St",
    "sg:city":"Southport",
    "sg:classifiers":[
        {
            "category":"Building & Trades",
            "subcategory":"Construction",
            "type":"Services"
        }
    ],
    "sg:phone":"+61 418 759 211",
    "sg:postcode":"4215",
    "sg:province":"QLD",
    "sg:tags":[
        "rendering",
        "cement"
    ],
    "wof:name":"QSP Pty Ltd",
    "wof:placetype":"venue"
},
  "geometry": {"coordinates":[153.405349731,-27.9668807983],"type":"Point"}
}