{
  "type": "Feature",
  "properties": {
    "iso:country":"AU",
    "sg:address":"82 Baillie St",
    "sg:city":"Horsham",
    "sg:classifiers":[
        {
            "category":"Health Services",
            "subcategory":"Chiropractor",
            "type":"Services"
        }
    ],
    "sg:phone":"+61 3 5382 2528",
    "sg:postcode":"3400",
    "sg:province":"VIC",
    "wof:name":"Wimmera Chiropractic Centres",
    "wof:placetype":"venue"
},
  "geometry": {"coordinates":[142.209259033,-36.711566925],"type":"Point"}
}