{
  "type": "Feature",
  "properties": {
    "addr:full":"Level 2, 135 Wickham Tce Brisbane QLD 4000",
    "addr:housenumber":"135",
    "addr:postcode":"4000",
    "addr:street":"Wickham Tce",
    "iso:country":"AU",
    "sg:address":"Level 2, 135",
    "sg:city":"Wickham Tce Brisbane",
    "sg:classifiers":[
        {
            "category":"Banks & Credit Unions",
            "subcategory":"Financial Services",
            "type":"Services"
        }
    ],
    "sg:phone":"+61 7 3832 5554",
    "sg:postcode":"4000",
    "sg:province":"QLD",
    "sg:tags":[
        "annuity",
        "rollover",
        "superannuation",
        "consultant"
    ],
    "wof:name":"BUSS (Q)",
    "wof:placetype":"venue"
},
  "geometry": {"coordinates":[153.02549743599999,-27.4646282196],"type":"Point"}
}