{
  "type": "Feature",
  "properties": {
    "addr:full":"Flat 3 206 Arthur St Fairfield VIC 3078",
    "addr:housenumber":"206",
    "addr:postcode":"3078",
    "addr:street":"Arthur St",
    "iso:country":"AU",
    "sg:address":"Flat 3 206 Arthur St",
    "sg:city":"Fairfield",
    "sg:classifiers":[
        {
            "category":"Home & Garden",
            "subcategory":"Building Materials",
            "type":"Retail Goods"
        }
    ],
    "sg:phone":"+61 412 180 911",
    "sg:postcode":"3078",
    "sg:province":"VIC",
    "sg:tags":[
        "lawn",
        "cutting",
        "maintenance"
    ],
    "wof:name":"Dads Lawns &#039;N&#039; More",
    "wof:placetype":"venue"
},
  "geometry": {"coordinates":[145.020355225,-37.77161026],"type":"Point"}
}