{
  "type": "Feature",
  "properties": {
    "addr:full":"686 Main Rd Edgeworth NSW 2285",
    "addr:housenumber":"686",
    "addr:postcode":"2285",
    "addr:street":"Main Rd",
    "iso:country":"AU",
    "sg:address":"686 Main Rd",
    "sg:city":"Edgeworth",
    "sg:classifiers":[
        {
            "category":"Retail",
            "subcategory":"Auto Repair",
            "type":"Services"
        }
    ],
    "sg:phone":"+61 2 4958 3111",
    "sg:postcode":"2285",
    "sg:province":"NSW",
    "sg:tags":[
        "bus",
        "truck"
    ],
    "wof:name":"Merv Barlow Radiators",
    "wof:placetype":"venue"
},
  "geometry": {"coordinates":[151.62091064399999,-32.9241333008],"type":"Point"}
}