{
  "type": "Feature",
  "properties": {
    "addr:full":"4 Wilson St Terang VIC 3264",
    "addr:housenumber":"4",
    "addr:postcode":"3264",
    "addr:street":"Wilson St",
    "iso:country":"AU",
    "sg:address":"4 Wilson St",
    "sg:city":"Terang",
    "sg:classifiers":[
        {
            "category":"Food & Beverages",
            "subcategory":"Farmers Market",
            "type":"Retail Goods"
        }
    ],
    "sg:phone":"+61 3 5592 1302",
    "sg:postcode":"3264",
    "sg:province":"VIC",
    "sg:tags":[
        "beekeeper"
    ],
    "wof:name":"Gardiner Neil",
    "wof:placetype":"venue"
},
  "geometry": {"coordinates":[142.922485352,-38.2392845154],"type":"Point"}
}