{
  "type": "Feature",
  "properties": {
    "iso:country":"AU",
    "sg:address":"492 Jones St",
    "sg:city":"Ultimo",
    "sg:classifiers":[
        {
            "category":"Retail",
            "subcategory":"Storage",
            "type":"Services"
        }
    ],
    "sg:phone":"+61 2 9211 1133",
    "sg:postcode":"2007",
    "sg:province":"NSW",
    "wof:name":"Kennards Self Storage",
    "wof:placetype":"venue"
},
  "geometry": {"coordinates":[151.197540283,-33.8795509338],"type":"Point"}
}