{
  "type": "Feature",
  "properties": {
    "addr:full":"PO Box 681 Bowral NSW 2576",
    "addr:postcode":"2576",
    "iso:country":"AU",
    "sg:address":"PO Box 681",
    "sg:city":"Bowral",
    "sg:classifiers":[
        {
            "category":"Building & Trades",
            "subcategory":"Construction",
            "type":"Services"
        }
    ],
    "sg:phone":"+61 2 4885 2488",
    "sg:postcode":"2576",
    "sg:province":"NSW",
    "sg:tags":[
        "contractor"
    ],
    "wof:name":"Robert Richard Leso",
    "wof:placetype":"venue"
},
  "geometry": {"coordinates":[150.385894775,-34.4550590515],"type":"Point"}
}