{
  "type": "Feature",
  "properties": {
    "iso:country":"AU",
    "sg:address":"16 Jason Pl",
    "sg:city":"North Rocks",
    "sg:classifiers":[
        {
            "category":"Professional",
            "subcategory":"Computer Services",
            "type":"Services"
        }
    ],
    "sg:phone":"+61 2 9872 1300",
    "sg:postcode":"2151",
    "sg:province":"NSW",
    "sg:tags":[
        "repairs",
        "upgrade",
        "equipment"
    ],
    "wof:name":"Home Computer Services",
    "wof:placetype":"venue"
},
  "geometry": {"coordinates":[151.02174377399999,-33.772693634],"type":"Point"}
}