{
  "type": "Feature",
  "properties": {
    "addr:full":"70 Fulcrum Rd Richlands QLD 4077",
    "addr:housenumber":"70",
    "addr:postcode":"4077",
    "addr:street":"Fulcrum Rd",
    "iso:country":"AU",
    "sg:address":"70 Fulcrum Rd",
    "sg:city":"Richlands",
    "sg:classifiers":[
        {
            "category":"Communications",
            "type":"Services"
        }
    ],
    "sg:phone":"+61 7 3212 9588",
    "sg:postcode":"4077",
    "sg:province":"QLD",
    "sg:tags":[
        "equipment",
        "satellite"
    ],
    "wof:name":"Hills Industries Limited",
    "wof:placetype":"venue"
},
  "geometry": {"coordinates":[152.94563293499999,-27.5881214142],"type":"Point"}
}