{
  "type": "Feature",
  "properties": {
    "iso:country":"AU",
    "sg:address":"RMB 1530/ Warrenbayne Rd",
    "sg:city":"Baddaginnie",
    "sg:classifiers":[
        {
            "category":"Building & Trades",
            "subcategory":"Landscaping Services",
            "type":"Services"
        }
    ],
    "sg:phone":"+61 3 5763 2240",
    "sg:postcode":"3670",
    "sg:province":"VIC",
    "sg:tags":[
        "control",
        "weed"
    ],
    "wof:name":"Industrial Weed Control",
    "wof:placetype":"venue"
},
  "geometry": {"coordinates":[145.86731,-36.600132],"type":"Point"}
}