{
  "type": "Feature",
  "properties": {
    "addr:full":"PO Box 3 Aldgate SA 5154",
    "addr:postcode":"5154",
    "iso:country":"AU",
    "sg:address":"PO Box 3",
    "sg:city":"Aldgate",
    "sg:classifiers":[
        {
            "category":"Health Services",
            "subcategory":"Health Practitioner",
            "type":"Services"
        }
    ],
    "sg:phone":"+61 8 8339 1120",
    "sg:postcode":"5154",
    "sg:province":"SA",
    "sg:tags":[
        "alternative"
    ],
    "wof:name":"Connected Self",
    "wof:placetype":"venue"
},
  "geometry": {"coordinates":[138.73538207999999,-35.016040802],"type":"Point"}
}