{
  "type": "Feature",
  "properties": {
    "addr:full":"41 Prince William Drv Seven Hills NSW 2147",
    "addr:housenumber":"41",
    "addr:postcode":"2147",
    "addr:street":"Prince William Drv",
    "iso:country":"AU",
    "sg:address":"41 Prince William Drv",
    "sg:city":"Seven Hills",
    "sg:classifiers":[
        {
            "category":"Mining & Drilling",
            "type":"Manufacturing & Wholesale Goods"
        }
    ],
    "sg:phone":"+61 2 9674 6733",
    "sg:postcode":"2147",
    "sg:province":"NSW",
    "sg:tags":[
        "equipment",
        "quarrying",
        "supply"
    ],
    "wof:name":"Eickhoff Aust Pty Ltd",
    "wof:placetype":"venue"
},
  "geometry": {"coordinates":[150.96080017099999,-33.7773475647],"type":"Point"}
}