{
  "type": "Feature",
  "properties": {
    "addr:full":"28A Mary St Auburn NSW 2144",
    "addr:housenumber":"28a",
    "addr:postcode":"2144",
    "addr:street":"Mary St",
    "iso:country":"AU",
    "sg:address":"28A Mary St",
    "sg:city":"Auburn",
    "sg:classifiers":[
        {
            "category":"Health Services",
            "subcategory":"Doctor",
            "type":"Services"
        }
    ],
    "sg:phone":"+61 2 9649 8123",
    "sg:postcode":"2144",
    "sg:province":"NSW",
    "sg:tags":[
        "medical",
        "practitioner"
    ],
    "wof:name":"Lvoff Gregory",
    "wof:placetype":"venue"
},
  "geometry": {"coordinates":[151.030883789,-33.8518295288],"type":"Point"}
}