{
  "type": "Feature",
  "properties": {
    "iso:country":"AU",
    "sg:address":"71 Wilson St",
    "sg:city":"Moonee Ponds",
    "sg:classifiers":[
        {
            "category":"Personal",
            "subcategory":"Beauty Salon",
            "type":"Services"
        }
    ],
    "sg:phone":"+61 3 9370 2251",
    "sg:postcode":"3039",
    "sg:province":"VIC",
    "sg:tags":[
        "supply",
        "artist",
        "make-up"
    ],
    "wof:name":"Rachel Braden",
    "wof:placetype":"venue"
},
  "geometry": {"coordinates":[144.93121300000001,-37.76302],"type":"Point"}
}