{
  "type": "Feature",
  "properties": {
    "iso:country":"AU",
    "sg:address":"5 Kooluna Crt",
    "sg:city":"Frankston",
    "sg:classifiers":[
        {
            "category":"Banks & Credit Unions",
            "subcategory":"Investment Brokerage",
            "type":"Services"
        }
    ],
    "sg:phone":"+61 419 392 575",
    "sg:postcode":"3199",
    "sg:province":"VIC",
    "sg:tags":[
        "paint",
        "supply",
        "removal"
    ],
    "wof:name":"H 2 0 Pressure Cleaning Services",
    "wof:placetype":"venue"
},
  "geometry": {"coordinates":[145.164306641,-38.1353874207],"type":"Point"}
}