{
  "type": "Feature",
  "properties": {
    "addr:full":"14- 18 Borthistle Rd Gunnedah NSW 2380",
    "addr:housenumber":"18",
    "addr:postcode":"2380",
    "addr:street":"Borthistle Rd",
    "iso:country":"AU",
    "sg:address":"14- 18 Borthistle Rd",
    "sg:city":"Gunnedah",
    "sg:classifiers":[
        {
            "category":"Professional",
            "subcategory":"Engineering",
            "type":"Services"
        }
    ],
    "sg:phone":"+61 2 6742 0500",
    "sg:postcode":"2380",
    "sg:province":"NSW",
    "sg:tags":[
        "engineer"
    ],
    "wof:name":"Gibson J M Engineering",
    "wof:placetype":"venue"
},
  "geometry": {"coordinates":[150.23541259800001,-30.9772663116],"type":"Point"}
}