{
  "type": "Feature",
  "properties": {
    "addr:full":"18 Heales St Inglewood VIC 3517",
    "addr:housenumber":"18",
    "addr:postcode":"3517",
    "addr:street":"Heales St",
    "iso:country":"AU",
    "sg:address":"18 Heales St",
    "sg:city":"Inglewood",
    "sg:classifiers":[
        {
            "category":"Shopping",
            "type":"Retail Goods"
        }
    ],
    "sg:phone":"+61 3 5438 3515",
    "sg:postcode":"3517",
    "sg:province":"VIC",
    "sg:tags":[
        "agent",
        "stock"
    ],
    "wof:name":"Nevins J F",
    "wof:placetype":"venue"
},
  "geometry": {"coordinates":[143.869034,-36.578056],"type":"Point"}
}