{
  "type": "Feature",
  "properties": {
    "addr:full":"Shop 13a Leeming Forum Leeming WA 6149",
    "addr:housenumber":"13a",
    "addr:postcode":"6149",
    "iso:country":"AU",
    "sg:address":"Shop 13a Leeming Forum",
    "sg:city":"Leeming",
    "sg:classifiers":[
        {
            "category":"Health Services",
            "subcategory":"Optometrist",
            "type":"Services"
        }
    ],
    "sg:phone":"+61 8 9310 1006",
    "sg:postcode":"6149",
    "sg:province":"WA",
    "wof:name":"Abernethy Owens Optometrists",
    "wof:placetype":"venue"
},
  "geometry": {"coordinates":[115.858841,-32.078442],"type":"Point"}
}