{
  "type": "Feature",
  "properties": {
    "addr:full":"61 Glen Eira Rd Ripponlea VIC 3185",
    "addr:housenumber":"61",
    "addr:postcode":"3185",
    "addr:street":"Glen Eira Rd",
    "iso:country":"AU",
    "sg:address":"61 Glen Eira Rd",
    "sg:city":"Ripponlea",
    "sg:classifiers":[
        {
            "category":"Cafe",
            "type":"Food & Drink"
        }
    ],
    "sg:phone":"+61 3 9532 7574",
    "sg:postcode":"3185",
    "sg:province":"VIC",
    "wof:name":"Beat Bar & Lounge",
    "wof:placetype":"venue"
},
  "geometry": {"coordinates":[144.99717712399999,-37.876663208],"type":"Point"}
}