{
  "type": "Feature",
  "properties": {
    "iso:country":"AU",
    "sg:address":"PO Box 777",
    "sg:city":"Gisborne",
    "sg:classifiers":[
        {
            "category":"Manufacturing",
            "subcategory":"Rubber & Plastics",
            "type":"Manufacturing & Wholesale Goods"
        }
    ],
    "sg:phone":"+61 1800 456 232",
    "sg:postcode":"3437",
    "sg:province":"VIC",
    "sg:tags":[
        "equipment",
        "card"
    ],
    "wof:name":"Globe Cards",
    "wof:placetype":"venue"
},
  "geometry": {"coordinates":[144.59135437,-37.4869995117],"type":"Point"}
}