{
  "type": "Feature",
  "properties": {
    "iso:country":"AU",
    "sg:address":"U9G/ 160 Bourke Rd",
    "sg:city":"Alexandria",
    "sg:classifiers":[
        {
            "category":"Shopping",
            "subcategory":"Clothing, Apparel, & Fashions",
            "type":"Retail Goods"
        }
    ],
    "sg:phone":"+61 2 9669 6834",
    "sg:postcode":"2015",
    "sg:province":"NSW",
    "sg:tags":[
        "textile",
        "designer"
    ],
    "wof:name":"Sumakhi",
    "wof:placetype":"venue"
},
  "geometry": {"coordinates":[151.190185547,-33.9164276123],"type":"Point"}
}