{
  "type": "Feature",
  "properties": {
    "addr:full":"860A King Georges Rd South Hurstville NSW 2221",
    "addr:housenumber":"860a",
    "addr:postcode":"2221",
    "addr:street":"King Georges Rd",
    "iso:country":"AU",
    "sg:address":"860A King Georges Rd",
    "sg:city":"South Hurstville",
    "sg:classifiers":[
        {
            "category":"Real Estate",
            "subcategory":"Real Estate Agent",
            "type":"Services"
        }
    ],
    "sg:phone":"+61 2 8558 7288",
    "sg:postcode":"2221",
    "sg:province":"NSW",
    "wof:name":"McGrath Estate Agents",
    "wof:placetype":"venue"
},
  "geometry": {"coordinates":[151.105957031,-33.9783592224],"type":"Point"}
}