{
  "type": "Feature",
  "properties": {
    "addr:full":"122 Guildford Rd Guildford NSW 2161",
    "addr:housenumber":"122",
    "addr:postcode":"2161",
    "addr:street":"Guildford Rd",
    "iso:country":"AU",
    "sg:address":"122 Guildford Rd",
    "sg:city":"Guildford",
    "sg:classifiers":[
        {
            "category":"Government",
            "subcategory":"Post Office",
            "type":"Public Place"
        }
    ],
    "sg:phone":"+61 410 726 111",
    "sg:postcode":"2161",
    "sg:province":"NSW",
    "sg:tags":[
        "box",
        "mail"
    ],
    "wof:name":"Letterboxes Of Australia",
    "wof:placetype":"venue"
},
  "geometry": {"coordinates":[150.986694336,-33.8542251587],"type":"Point"}
}