{
  "type": "Feature",
  "properties": {
    "iso:country":"AU",
    "sg:address":"13 Hatchman St",
    "sg:city":"Victoria Point",
    "sg:classifiers":[
        {
            "category":"Building & Trades",
            "subcategory":"Plumbing",
            "type":"Services"
        }
    ],
    "sg:phone":"+61 413 073 367",
    "sg:postcode":"4165",
    "sg:province":"QLD",
    "sg:tags":[
        "plumber",
        "gasfitters"
    ],
    "wof:name":"Col Kingston",
    "wof:placetype":"venue"
},
  "geometry": {"coordinates":[153.309783936,-27.5828781128],"type":"Point"}
}