{
  "type": "Feature",
  "properties": {
    "iso:country":"AU",
    "sg:address":"139 Buchan St",
    "sg:city":"Bungalow",
    "sg:classifiers":[
        {
            "category":"Professional",
            "subcategory":"Art Services",
            "type":"Services"
        }
    ],
    "sg:phone":"+61 408 774 140",
    "sg:postcode":"4870",
    "sg:province":"QLD",
    "sg:tags":[
        "decorator",
        "painter"
    ],
    "wof:name":"McKinley Des",
    "wof:placetype":"venue"
},
  "geometry": {"coordinates":[145.763839722,-16.9329395294],"type":"Point"}
}