{
  "type": "Feature",
  "properties": {
    "addr:full":"433 Magill Rd St Morris SA 5068",
    "addr:housenumber":"433",
    "addr:postcode":"5068",
    "addr:street":"Magill Rd",
    "iso:country":"AU",
    "sg:address":"433 Magill Rd",
    "sg:city":"St Morris",
    "sg:classifiers":[
        {
            "category":"Health Services",
            "subcategory":"Health Practitioner",
            "type":"Services"
        }
    ],
    "sg:phone":"+61 8 8331 0552",
    "sg:postcode":"5068",
    "sg:province":"SA",
    "sg:tags":[
        "physiotherapist"
    ],
    "wof:name":"Sabine Rebecca",
    "wof:placetype":"venue"
},
  "geometry": {"coordinates":[138.65606689399999,-34.9138908386],"type":"Point"}
}