{
  "type": "Feature",
  "properties": {
    "addr:full":"53- 55 Military Rd Port Kembla NSW 2505",
    "addr:housenumber":"55",
    "addr:postcode":"2505",
    "addr:street":"Military Rd",
    "iso:country":"AU",
    "sg:address":"53- 55 Military Rd",
    "sg:city":"Port Kembla",
    "sg:classifiers":[
        {
            "category":"Wholesale",
            "subcategory":"Farm Supplies",
            "type":"Manufacturing & Wholesale Goods"
        }
    ],
    "sg:phone":"+61 2 4275 1112",
    "sg:postcode":"2505",
    "sg:province":"NSW",
    "sg:tags":[
        "feed",
        "supplement",
        "stock"
    ],
    "wof:name":"Petstock Animal Supplies",
    "wof:placetype":"venue"
},
  "geometry": {"coordinates":[150.902817,-34.480801],"type":"Point"}
}