{
  "type": "Feature",
  "properties": {
    "addr:full":"48b Browns Rd Kingston TAS 7050",
    "addr:housenumber":"48b",
    "addr:postcode":"7050",
    "addr:street":"Browns Rd",
    "iso:country":"AU",
    "sg:address":"48b Browns Rd",
    "sg:city":"Kingston",
    "sg:classifiers":[
        {
            "category":"Farming",
            "subcategory":"Berry Farm",
            "type":"Manufacturing & Wholesale Goods"
        }
    ],
    "sg:phone":"+61 3 6229 7090",
    "sg:postcode":"7050",
    "sg:province":"TAS",
    "sg:tags":[
        "fruit",
        "grower"
    ],
    "wof:name":"Pegusas Sprouts",
    "wof:placetype":"venue"
},
  "geometry": {"coordinates":[147.31321700000001,-42.96965],"type":"Point"}
}