{
  "type": "Feature",
  "properties": {
    "iso:country":"AU",
    "sg:address":"4-6 McGrath St",
    "sg:city":"Fairy Meadow",
    "sg:classifiers":[
        {
            "category":"Manufacturing",
            "subcategory":"Glass & Minerals",
            "type":"Manufacturing & Wholesale Goods"
        }
    ],
    "sg:phone":"+61 2 4226 1866",
    "sg:postcode":"2519",
    "sg:province":"NSW",
    "sg:tags":[
        "merchant",
        "granite",
        "marble"
    ],
    "wof:name":"Italianastone",
    "wof:placetype":"venue"
},
  "geometry": {"coordinates":[150.89106799999999,-34.400356],"type":"Point"}
}