{
  "type": "Feature",
  "properties": {
    "addr:full":"72 Keon Pde Thomastown VIC 3074",
    "addr:housenumber":"72",
    "addr:postcode":"3074",
    "addr:street":"Keon Pde",
    "iso:country":"AU",
    "sg:address":"72 Keon Pde",
    "sg:city":"Thomastown",
    "sg:classifiers":[
        {
            "category":"Autos & Motor Vehicles",
            "subcategory":"Fuel & Gas Station",
            "type":"Retail Goods"
        }
    ],
    "sg:phone":"+61 3 9460 7962",
    "sg:postcode":"3074",
    "sg:province":"VIC",
    "wof:name":"BP Australia Pty Ltd",
    "wof:placetype":"venue"
},
  "geometry": {"coordinates":[145.021682739,-37.6958198547],"type":"Point"}
}