{
  "type": "Feature",
  "properties": {
    "iso:country":"AU",
    "sg:address":"81 Old South Head Rd",
    "sg:city":"Bondi Junction",
    "sg:classifiers":[
        {
            "category":"Health Services",
            "subcategory":"Health Practitioner",
            "type":"Services"
        }
    ],
    "sg:phone":"+61 2 9389 6163",
    "sg:postcode":"2022",
    "sg:province":"NSW",
    "sg:tags":[
        "acupuncture"
    ],
    "wof:name":"Ivanoff Acupuncture Centre",
    "wof:placetype":"venue"
},
  "geometry": {"coordinates":[151.25425720199999,-33.8906974792],"type":"Point"}
}