{
  "type": "Feature",
  "properties": {
    "iso:country":"AU",
    "sg:address":"39- 49 Longview Crt",
    "sg:city":"Thomastown",
    "sg:classifiers":[
        {
            "category":"Bus Charters",
            "type":"Transportation"
        }
    ],
    "sg:phone":"+61 3 9465 4511",
    "sg:postcode":"3074",
    "sg:province":"VIC",
    "sg:tags":[
        "builder"
    ],
    "wof:name":"Custom Coaches (Sales) Pty Ltd",
    "wof:placetype":"venue"
},
  "geometry": {"coordinates":[145.04612731899999,-37.6887779236],"type":"Point"}
}