{
  "type": "Feature",
  "properties": {
    "addr:full":"6 Little St Toowoomba QLD 4350",
    "addr:housenumber":"6",
    "addr:postcode":"4350",
    "addr:street":"Little St",
    "iso:country":"AU",
    "sg:address":"6 Little St",
    "sg:city":"Toowoomba",
    "sg:classifiers":[
        {
            "category":"Social Services",
            "subcategory":"Child Care",
            "type":"Services"
        }
    ],
    "sg:phone":"+61 7 4632 4728",
    "sg:postcode":"4350",
    "sg:province":"QLD",
    "wof:name":"Mothercraft Childcare Centre",
    "wof:placetype":"venue"
},
  "geometry": {"coordinates":[151.95172099999999,-27.563274],"type":"Point"}
}