{
  "type": "Feature",
  "properties": {
    "iso:country":"AU",
    "sg:address":"6 Little St",
    "sg:city":"Toowoomba",
    "sg:classifiers":[
        {
            "category":"Social Services",
            "subcategory":"Child Care",
            "type":"Services"
        }
    ],
    "sg:phone":"+61 7 4632 4728",
    "sg:postcode":"4350",
    "sg:province":"QLD",
    "wof:name":"Mothercraft Childcare Centre",
    "wof:placetype":"venue"
},
  "geometry": {"coordinates":[151.951721,-27.563274],"type":"Point"}
}