{
  "type": "Feature",
  "properties": {
    "iso:country":"AU",
    "sg:address":"800 Gympie Rd",
    "sg:city":"Chermside",
    "sg:classifiers":[
        {
            "category":"Health Services",
            "subcategory":"Dentist",
            "type":"Services"
        }
    ],
    "sg:phone":"+61 7 3350 4344",
    "sg:postcode":"4032",
    "sg:province":"QLD",
    "sg:tags":[
        "periodontist"
    ],
    "wof:name":"Clark Ryan Peter",
    "wof:placetype":"venue"
},
  "geometry": {"coordinates":[153.030807495,-27.3865661621],"type":"Point"}
}