{
  "type": "Feature",
  "properties": {
    "addr:full":"326 Montague Rd West End (Brisbane) QLD 4101",
    "addr:housenumber":"326",
    "addr:postcode":"4101",
    "addr:street":"Montague Rd",
    "iso:country":"AU",
    "sg:address":"326 Montague Rd",
    "sg:city":"West End (Brisbane)",
    "sg:classifiers":[
        {
            "category":"Health Services",
            "subcategory":"Health Practitioner",
            "type":"Services"
        }
    ],
    "sg:phone":"+61 7 3846 6214",
    "sg:postcode":"4101",
    "sg:province":"QLD",
    "sg:tags":[
        "dietitian"
    ],
    "wof:name":"Barr Diane",
    "wof:placetype":"venue"
},
  "geometry": {"coordinates":[153.00425720199999,-27.4819965363],"type":"Point"}
}