{
  "type": "Feature",
  "properties": {
    "addr:full":"10 Good St Granville NSW 2142",
    "addr:housenumber":"10",
    "addr:postcode":"2142",
    "addr:street":"Good St",
    "iso:country":"AU",
    "sg:address":"10 Good St",
    "sg:city":"Granville",
    "sg:classifiers":[
        {
            "category":"Travel",
            "subcategory":"Hotels & Motels",
            "type":"Entertainment"
        }
    ],
    "sg:phone":"+61 2 9637 1424",
    "sg:postcode":"2142",
    "sg:province":"NSW",
    "sg:tags":[
        "accommodation"
    ],
    "wof:name":"Granville Hotel",
    "wof:placetype":"venue"
},
  "geometry": {"coordinates":[151.01136779800001,-33.8317947388],"type":"Point"}
}