{
  "type": "Feature",
  "properties": {
    "addr:full":"6 Fern St Portland VIC 3305",
    "addr:housenumber":"6",
    "addr:postcode":"3305",
    "addr:street":"Fern St",
    "iso:country":"AU",
    "sg:address":"6 Fern St",
    "sg:city":"Portland",
    "sg:classifiers":[
        {
            "category":"Health Services",
            "subcategory":"Doctor",
            "type":"Services"
        }
    ],
    "sg:phone":"+61 3 5523 2322",
    "sg:postcode":"3305",
    "sg:province":"VIC",
    "sg:tags":[
        "medical",
        "practitioner"
    ],
    "wof:name":"Das Jesse F.R.C.S.",
    "wof:placetype":"venue"
},
  "geometry": {"coordinates":[141.60610961899999,-38.3399658203],"type":"Point"}
}