{
  "type": "Feature",
  "properties": {
    "addr:full":"14 Ruskin St Orbost VIC 3888",
    "addr:housenumber":"14",
    "addr:postcode":"3888",
    "addr:street":"Ruskin St",
    "iso:country":"AU",
    "sg:address":"14 Ruskin St",
    "sg:city":"Orbost",
    "sg:classifiers":[
        {
            "category":"Professional",
            "subcategory":"Accounting & Tax Preparation",
            "type":"Services"
        }
    ],
    "sg:phone":"+61 3 5154 1599",
    "sg:postcode":"3888",
    "sg:province":"VIC",
    "sg:tags":[
        "accountant",
        "auditor"
    ],
    "wof:name":"Martin Taylor Associates Pty Ltd",
    "wof:placetype":"venue"
},
  "geometry": {"coordinates":[148.45596313499999,-37.7076187134],"type":"Point"}
}