{
  "type": "Feature",
  "properties": {
    "iso:country":"AU",
    "sg:address":"61 Herberton Rd",
    "sg:city":"Atherton",
    "sg:classifiers":[
        {
            "category":"Communications",
            "subcategory":"News Services",
            "type":"Services"
        }
    ],
    "sg:phone":"+61 7 4091 7052",
    "sg:postcode":"4883",
    "sg:province":"QLD",
    "sg:tags":[
        "information",
        "tourist",
        "attractions"
    ],
    "wof:name":"Platypus Information Services",
    "wof:placetype":"venue"
},
  "geometry": {"coordinates":[145.470458984,-17.2859516144],"type":"Point"}
}