{
  "type": "Feature",
  "properties": {
    "addr:full":"159 Denman Ave Caringbah NSW 2229",
    "addr:housenumber":"159",
    "addr:postcode":"2229",
    "addr:street":"Denman Ave",
    "iso:country":"AU",
    "sg:address":"159 Denman Ave",
    "sg:city":"Caringbah",
    "sg:classifiers":[
        {
            "category":"Shopping",
            "subcategory":"Clothing, Apparel, & Fashions",
            "type":"Retail Goods"
        }
    ],
    "sg:phone":"+61 2 9525 1058",
    "sg:postcode":"2229",
    "sg:province":"NSW",
    "sg:tags":[
        "lady",
        "wear"
    ],
    "wof:name":"Daisies",
    "wof:placetype":"venue"
},
  "geometry": {"coordinates":[151.122650147,-34.0411567688],"type":"Point"}
}