{
  "type": "Feature",
  "properties": {
    "addr:full":"Clearys La Wildes Meadow NSW 2577",
    "addr:postcode":"2577",
    "iso:country":"AU",
    "sg:address":"Clearys La",
    "sg:city":"Wildes Meadow",
    "sg:classifiers":[
        {
            "category":"Retail",
            "subcategory":"Animal Services",
            "type":"Services"
        }
    ],
    "sg:phone":"+61 2 4887 7336",
    "sg:postcode":"2577",
    "sg:province":"NSW",
    "sg:tags":[
        "breeder",
        "sheep",
        "stud",
        "cattle"
    ],
    "wof:name":"Eureka Park Gelbvieh Stud",
    "wof:placetype":"venue"
},
  "geometry": {"coordinates":[150.499267578,-34.609172821],"type":"Point"}
}