{
  "type": "Feature",
  "properties": {
    "addr:full":"24 Fennell St North Parramatta NSW 2151",
    "addr:housenumber":"24",
    "addr:postcode":"2151",
    "addr:street":"Fennell St",
    "iso:country":"AU",
    "sg:address":"24 Fennell St",
    "sg:city":"North Parramatta",
    "sg:classifiers":[
        {
            "category":"Professional",
            "type":"Services"
        }
    ],
    "sg:phone":"+61 2 8838 2300",
    "sg:postcode":"2151",
    "sg:province":"NSW",
    "sg:tags":[
        "message",
        "answering",
        "telephone"
    ],
    "sg:website":"http://www.ossgroup.com.au",
    "wof:name":"Office Support Services",
    "wof:placetype":"venue"
},
  "geometry": {"coordinates":[151.008743286,-33.8058624268],"type":"Point"}
}