{
  "type": "Feature",
  "properties": {
    "iso:country":"AU",
    "sg:address":"44 McEachern Crs",
    "sg:city":"Melba",
    "sg:classifiers":[
        {
            "category":"Professional",
            "subcategory":"Employment Agencies",
            "type":"Services"
        }
    ],
    "sg:phone":"+61 412 703 198",
    "sg:postcode":"2615",
    "sg:province":"ACT",
    "sg:tags":[
        "entertainer",
        "agent"
    ],
    "wof:name":"Elvis Tribute Artist",
    "wof:placetype":"venue"
},
  "geometry": {"coordinates":[149.05996704099999,-35.2097015381],"type":"Point"}
}