{
  "type": "Feature",
  "properties": {
    "addr:full":"Unit 4/ 44 Hutton St Osborne Park WA 6017",
    "addr:housenumber":"44",
    "addr:postcode":"6017",
    "addr:street":"Hutton St",
    "iso:country":"AU",
    "sg:address":"Unit 4/ 44 Hutton St",
    "sg:city":"Osborne Park",
    "sg:classifiers":[
        {
            "category":"Home & Garden",
            "subcategory":"Carpets & Floor Coverings",
            "type":"Retail Goods"
        }
    ],
    "sg:phone":"+61 8 9444 9331",
    "sg:postcode":"6017",
    "sg:province":"WA",
    "wof:name":"Rug Junction",
    "wof:placetype":"venue"
},
  "geometry": {"coordinates":[115.819297791,-31.9029083252],"type":"Point"}
}