{
  "type": "Feature",
  "properties": {
    "addr:full":"Sturt Hwy Gol Gol NSW 2738",
    "addr:postcode":"2738",
    "addr:street":"Sturt Hwy",
    "iso:country":"AU",
    "sg:address":"Sturt Hwy",
    "sg:city":"Gol Gol",
    "sg:classifiers":[
        {
            "category":"Food & Beverages",
            "subcategory":"Meat & Fish",
            "type":"Retail Goods"
        }
    ],
    "sg:phone":"+61 3 5024 8613",
    "sg:postcode":"2738",
    "sg:province":"NSW",
    "sg:tags":[
        "aquaculture"
    ],
    "wof:name":"Gol Gol Fisheries",
    "wof:placetype":"venue"
},
  "geometry": {"coordinates":[142.24807699999999,-34.223221],"type":"Point"}
}