{
  "type": "Feature",
  "properties": {
    "iso:country":"AU",
    "sg:address":"Fifth St",
    "sg:city":"Wonthella",
    "sg:classifiers":[
        {
            "category":"Food & Beverages",
            "subcategory":"Supermarket",
            "type":"Retail Goods"
        }
    ],
    "sg:phone":"+61 8 9921 4798",
    "sg:postcode":"6530",
    "sg:province":"WA",
    "sg:tags":[
        "grocery",
        "store"
    ],
    "wof:name":"Dewsons",
    "wof:placetype":"venue"
},
  "geometry": {"coordinates":[114.626289368,-28.7649402618],"type":"Point"}
}