{
  "type": "Feature",
  "properties": {
    "addr:full":"3 Rosenthal Ave Lane Cove NSW 2066",
    "addr:housenumber":"3",
    "addr:postcode":"2066",
    "addr:street":"Rosenthal Ave",
    "iso:country":"AU",
    "sg:address":"3 Rosenthal Ave",
    "sg:city":"Lane Cove",
    "sg:classifiers":[
        {
            "category":"Health Services",
            "subcategory":"Doctor",
            "type":"Services"
        }
    ],
    "sg:phone":"+61 2 9428 5545",
    "sg:postcode":"2066",
    "sg:province":"NSW",
    "sg:tags":[
        "medical",
        "practitioner"
    ],
    "wof:name":"Norris John",
    "wof:placetype":"venue"
},
  "geometry": {"coordinates":[151.168869019,-33.813835144],"type":"Point"}
}