{
  "type": "Feature",
  "properties": {
    "addr:full":"Shop 22/23 Sanderson Rd Shopng Cntr Lesmurdie WA 6076",
    "addr:housenumber":"shop 22 / 23",
    "addr:postcode":"6076",
    "addr:street":"Sanderson Rd Shopng Cntr",
    "iso:country":"AU",
    "sg:address":"Shop 22/23 Sanderson Rd",
    "sg:city":"Shopng Cntr Lesmurdie",
    "sg:classifiers":[
        {
            "category":"Communications",
            "subcategory":"Film & Video Production",
            "type":"Services"
        }
    ],
    "sg:phone":"+61 8 9291 9919",
    "sg:postcode":"6076",
    "sg:province":"WA",
    "sg:tags":[
        "dvd",
        "library"
    ],
    "wof:name":"Sanderson Road Super Deli & Video",
    "wof:placetype":"venue"
},
  "geometry": {"coordinates":[116.045959473,-32.0070037842],"type":"Point"}
}