{
  "type": "Feature",
  "properties": {
    "iso:country":"AU",
    "sg:address":"2/90 Pritchard Rd",
    "sg:city":"Virginia",
    "sg:classifiers":[
        {
            "category":"Manufacturing",
            "subcategory":"Motor Vehicles & Parts",
            "type":"Manufacturing & Wholesale Goods"
        }
    ],
    "sg:phone":"+61 7 3865 5600",
    "sg:postcode":"4014",
    "sg:province":"QLD",
    "sg:tags":[
        "body",
        "builder",
        "supply"
    ],
    "wof:name":"Universal Engineers Supplies (Aust) Pty Ltd",
    "wof:placetype":"venue"
},
  "geometry": {"coordinates":[153.05625915499999,-27.3737354279],"type":"Point"}
}