{
  "type": "Feature",
  "properties": {
    "iso:country":"AU",
    "sg:address":"36 Kildare Rd",
    "sg:city":"Blacktown",
    "sg:classifiers":[
        {
            "category":"Health Services",
            "subcategory":"Optometrist",
            "type":"Services"
        }
    ],
    "sg:phone":"+61 2 9622 2832",
    "sg:postcode":"2148",
    "sg:province":"NSW",
    "wof:name":"Joseph Nazarian",
    "wof:placetype":"venue"
},
  "geometry": {"coordinates":[150.90472412099999,-33.7689971924],"type":"Point"}
}