{
  "type": "Feature",
  "properties": {
    "addr:full":"454 City Rd South Melbourne VIC 3205",
    "addr:housenumber":"454",
    "addr:postcode":"3205",
    "addr:street":"City Rd",
    "iso:country":"AU",
    "sg:address":"454 City Rd",
    "sg:city":"South Melbourne",
    "sg:classifiers":[
        {
            "category":"Banks & Credit Unions",
            "subcategory":"Investment Brokerage",
            "type":"Services"
        }
    ],
    "sg:phone":"+61 3 9682 7580",
    "sg:postcode":"3205",
    "sg:province":"VIC",
    "sg:tags":[
        "finance",
        "broker"
    ],
    "wof:name":"Corporate Financial Services Australia Pty Ltd",
    "wof:placetype":"venue"
},
  "geometry": {"coordinates":[144.95368999999999,-37.831184],"type":"Point"}
}