{
  "type": "Feature",
  "properties": {
    "iso:country":"AU",
    "sg:address":"Cnr Bains & Panalatinga Rd",
    "sg:city":"Woodcroft",
    "sg:classifiers":[
        {
            "category":"Food & Beverages",
            "subcategory":"Supermarket",
            "type":"Retail Goods"
        }
    ],
    "sg:phone":"+61 8 8325 1143",
    "sg:postcode":"5162",
    "sg:province":"SA",
    "sg:tags":[
        "grocery",
        "store"
    ],
    "wof:name":"Woodcroft Foodland",
    "wof:placetype":"venue"
},
  "geometry": {"coordinates":[138.55723571799999,-35.1140708923],"type":"Point"}
}