{
  "type": "Feature",
  "properties": {
    "addr:full":"54 Frederick St Launceston TAS 7250",
    "addr:housenumber":"54",
    "addr:postcode":"7250",
    "addr:street":"Frederick St",
    "iso:country":"AU",
    "sg:address":"54 Frederick St",
    "sg:city":"Launceston",
    "sg:classifiers":[
        {
            "category":"Food & Beverages",
            "subcategory":"Specialty",
            "type":"Retail Goods"
        }
    ],
    "sg:phone":"+61 3 6331 7682",
    "sg:postcode":"7250",
    "sg:province":"TAS",
    "sg:tags":[
        "product",
        "health"
    ],
    "wof:name":"Wholefoods Launceston",
    "wof:placetype":"venue"
},
  "geometry": {"coordinates":[147.137405395,-41.4426078796],"type":"Point"}
}