{
  "type": "Feature",
  "properties": {
    "iso:country":"AU",
    "sg:address":"Shop 225 Stockland",
    "sg:city":"Shellharbour City Centre",
    "sg:classifiers":[
        {
            "category":"Shopping",
            "subcategory":"Jewelry",
            "type":"Retail Goods"
        }
    ],
    "sg:phone":"+61 2 4297 2264",
    "sg:postcode":"2529",
    "sg:province":"NSW",
    "sg:tags":[
        "jeweller"
    ],
    "wof:name":"Bellino Jewellers",
    "wof:placetype":"venue"
},
  "geometry": {"coordinates":[150.83636474599999,-34.5661811829],"type":"Point"}
}