{
  "type": "Feature",
  "properties": {
    "addr:full":"Shop 1031A, Carindale Shopng Cntr, Creek Rd Carindale QLD 4152",
    "addr:housenumber":"1031a",
    "addr:postcode":"4152",
    "addr:street":"Creek Rd",
    "iso:country":"AU",
    "sg:address":"Shop 1031A, Carindale Shopng Cntr, Creek Rd",
    "sg:city":"Carindale",
    "sg:classifiers":[
        {
            "category":"Travel",
            "subcategory":"Travel Agent",
            "type":"Entertainment"
        }
    ],
    "sg:phone":"+61 13 18 66",
    "sg:postcode":"4152",
    "sg:province":"QLD",
    "sg:tags":[
        "consultant"
    ],
    "wof:name":"Flight Centre",
    "wof:placetype":"venue"
},
  "geometry": {"coordinates":[153.10345459000001,-27.5023994446],"type":"Point"}
}