{
  "type": "Feature",
  "properties": {
    "addr:full":"1/ 200 Sturt St Ballarat Central VIC 3350",
    "addr:housenumber":"/ 200",
    "addr:postcode":"3350",
    "addr:street":"Sturt St",
    "iso:country":"AU",
    "sg:address":"1/ 200 Sturt St",
    "sg:city":"Ballarat Central",
    "sg:classifiers":[
        {
            "category":"Professional",
            "subcategory":"Art Services",
            "type":"Services"
        }
    ],
    "sg:phone":"+61 1300 133 326",
    "sg:postcode":"3350",
    "sg:province":"VIC",
    "sg:tags":[
        "interior",
        "designer"
    ],
    "wof:name":"TTG Timeless Interior Ballarat Central",
    "wof:placetype":"venue"
},
  "geometry": {"coordinates":[143.831985,-37.558529],"type":"Point"}
}