{
  "type": "Feature",
  "properties": {
    "iso:country":"AU",
    "sg:address":"14 Yates St",
    "sg:city":"Branxton",
    "sg:classifiers":[
        {
            "category":"Professional",
            "subcategory":"Employment Agencies",
            "type":"Services"
        }
    ],
    "sg:phone":"+61 2 4938 3577",
    "sg:postcode":"2335",
    "sg:province":"NSW",
    "sg:tags":[
        "entertainer",
        "agent"
    ],
    "wof:name":"2,s a crowd",
    "wof:placetype":"venue"
},
  "geometry": {"coordinates":[151.364700317,-32.6571006775],"type":"Point"}
}