{
  "type": "Feature",
  "properties": {
    "addr:full":"534- 542 Mt Dandenong Rd Kilsyth VIC 3137",
    "addr:housenumber":"542",
    "addr:postcode":"3137",
    "addr:street":"Mt Dandenong Rd",
    "iso:country":"AU",
    "sg:address":"534- 542 Mt Dandenong Rd",
    "sg:city":"Kilsyth",
    "sg:classifiers":[
        {
            "category":"Health Services",
            "subcategory":"Health Practitioner",
            "type":"Services"
        }
    ],
    "sg:phone":"+61 431 848 703",
    "sg:postcode":"3137",
    "sg:province":"VIC",
    "sg:tags":[
        "psychologist"
    ],
    "wof:name":"Brown James",
    "wof:placetype":"venue"
},
  "geometry": {"coordinates":[145.311004639,-37.8023109436],"type":"Point"}
}