{
  "type": "Feature",
  "properties": {
    "addr:full":"200 Castle Hill Rd Cherrybrook NSW 2126",
    "addr:housenumber":"200",
    "addr:postcode":"2126",
    "addr:street":"Castle Hill Rd",
    "iso:country":"AU",
    "sg:address":"200 Castle Hill Rd",
    "sg:city":"Cherrybrook",
    "sg:classifiers":[
        {
            "category":"Building & Trades",
            "subcategory":"Cleaning & Sanitation",
            "type":"Services"
        }
    ],
    "sg:phone":"+61 2 9899 2371",
    "sg:postcode":"2126",
    "sg:province":"NSW",
    "sg:tags":[
        "cleaner",
        "repairer",
        "roof"
    ],
    "wof:name":"Webb R T",
    "wof:placetype":"venue"
},
  "geometry": {"coordinates":[151.03123474099999,-33.7364845276],"type":"Point"}
}