{
  "type": "Feature",
  "properties": {
    "addr:full":"PO Box 210 Endeavour Hills VIC 3802",
    "addr:postcode":"3802",
    "iso:country":"AU",
    "sg:address":"PO Box 210",
    "sg:city":"Endeavour Hills",
    "sg:classifiers":[
        {
            "category":"Professional",
            "subcategory":"Accounting & Tax Preparation",
            "type":"Services"
        }
    ],
    "sg:phone":"+61 438 457 697",
    "sg:postcode":"3802",
    "sg:province":"VIC",
    "sg:tags":[
        "jukebox"
    ],
    "wof:name":"Megajuke",
    "wof:placetype":"venue"
},
  "geometry": {"coordinates":[145.25584411599999,-37.96900177],"type":"Point"}
}