{
  "type": "Feature",
  "properties": {
    "addr:full":"20 Edward St Wagga Wagga NSW 2650",
    "addr:housenumber":"20",
    "addr:postcode":"2650",
    "addr:street":"Edward St",
    "iso:country":"AU",
    "sg:address":"20 Edward St",
    "sg:city":"Wagga Wagga",
    "sg:classifiers":[
        {
            "category":"Manufacturing",
            "subcategory":"Motor Vehicles & Parts",
            "type":"Manufacturing & Wholesale Goods"
        }
    ],
    "sg:phone":"+61 2 6921 6555",
    "sg:postcode":"2650",
    "sg:province":"NSW",
    "sg:tags":[
        "replacement"
    ],
    "wof:name":"Jupiter Motors",
    "wof:placetype":"venue"
},
  "geometry": {"coordinates":[147.37672424300001,-35.1200027466],"type":"Point"}
}