{
  "type": "Feature",
  "properties": {
    "addr:full":"Unit 1/ 207 Banks St Welshpool WA 6106",
    "addr:housenumber":"/ 207",
    "addr:postcode":"6106",
    "addr:street":"Banks St",
    "iso:country":"AU",
    "sg:address":"Unit 1/ 207 Banks St",
    "sg:city":"Welshpool",
    "sg:classifiers":[
        {
            "category":"Wholesale",
            "subcategory":"Electrical",
            "type":"Manufacturing & Wholesale Goods"
        }
    ],
    "sg:phone":"+61 8 9229 8990",
    "sg:postcode":"6106",
    "sg:province":"WA",
    "sg:tags":[
        "equipment",
        "testing",
        "electronic",
        "electric"
    ],
    "wof:name":"Nesco Electrical Products",
    "wof:placetype":"venue"
},
  "geometry": {"coordinates":[115.946907044,-31.9927997589],"type":"Point"}
}