{
  "type": "Feature",
  "properties": {
    "iso:country":"AU",
    "sg:address":"10 Lockett St",
    "sg:city":"Coolbellup",
    "sg:classifiers":[
        {
            "category":"Building & Trades",
            "subcategory":"Pest Control",
            "type":"Services"
        }
    ],
    "sg:phone":"+61 8 9337 2589",
    "sg:postcode":"6163",
    "sg:province":"WA",
    "wof:name":"United Pest Control & Agencies",
    "wof:placetype":"venue"
},
  "geometry": {"coordinates":[115.79347199999999,-32.075279],"type":"Point"}
}