{
  "type": "Feature",
  "properties": {
    "addr:full":"Unit 6/ 2 Forge St Blacktown NSW 2148",
    "addr:housenumber":"2",
    "addr:postcode":"2148",
    "addr:street":"Forge St",
    "iso:country":"AU",
    "sg:address":"Unit 6/ 2 Forge St",
    "sg:city":"Blacktown",
    "sg:classifiers":[
        {
            "category":"Retail",
            "subcategory":"Auto Repair",
            "type":"Services"
        }
    ],
    "sg:phone":"+61 2 9621 2488",
    "sg:postcode":"2148",
    "sg:province":"NSW",
    "sg:tags":[
        "beater",
        "painter",
        "panel"
    ],
    "wof:name":"Pat & Mick Smash Repairs Pty Ltd",
    "wof:placetype":"venue"
},
  "geometry": {"coordinates":[150.90934753400001,-33.7570533752],"type":"Point"}
}