{
  "type": "Feature",
  "properties": {
    "addr:full":"39 Victoria St Grafton NSW 2460",
    "addr:housenumber":"39",
    "addr:postcode":"2460",
    "addr:street":"Victoria St",
    "iso:country":"AU",
    "sg:address":"39 Victoria St",
    "sg:city":"Grafton",
    "sg:classifiers":[
        {
            "category":"Education",
            "subcategory":"School",
            "type":"Public Place"
        }
    ],
    "sg:phone":"+61 2 6642 2011",
    "sg:postcode":"2460",
    "sg:province":"NSW",
    "wof:name":"Cathedral School The",
    "wof:placetype":"venue"
},
  "geometry": {"coordinates":[152.934204102,-29.6933479309],"type":"Point"}
}