{
  "type": "Feature",
  "properties": {
    "addr:full":"5 Standing Drv Traralgon VIC 3844",
    "addr:housenumber":"5",
    "addr:postcode":"3844",
    "addr:street":"Standing Drv",
    "iso:country":"AU",
    "sg:address":"5 Standing Drv",
    "sg:city":"Traralgon",
    "sg:classifiers":[
        {
            "category":"Manufacturing",
            "subcategory":"Tools & Machinery",
            "type":"Manufacturing & Wholesale Goods"
        }
    ],
    "sg:phone":"+61 3 5174 1012",
    "sg:postcode":"3844",
    "sg:province":"VIC",
    "sg:tags":[
        "earth",
        "excavating",
        "moving",
        "equipment"
    ],
    "wof:name":"Latrobe EQuipment",
    "wof:placetype":"venue"
},
  "geometry": {"coordinates":[146.56304931599999,-38.1915435791],"type":"Point"}
}