{
  "type": "Feature",
  "properties": {
    "addr:full":"Sturt St Echuca VIC 3564",
    "addr:postcode":"3564",
    "addr:street":"Sturt St",
    "iso:country":"AU",
    "sg:address":"Sturt St",
    "sg:city":"Echuca",
    "sg:classifiers":[
        {
            "category":"Autos & Motor Vehicles",
            "subcategory":"Fuel & Gas Station",
            "type":"Retail Goods"
        }
    ],
    "sg:phone":"+61 3 5482 1455",
    "sg:postcode":"3564",
    "sg:province":"VIC",
    "wof:name":"BP Australia Limited",
    "wof:placetype":"venue"
},
  "geometry": {"coordinates":[144.75393676799999,-36.1288833618],"type":"Point"}
}