{
  "type": "Feature",
  "properties": {
    "iso:country":"AU",
    "sg:address":"268a Oxford St",
    "sg:city":"Bondi Junction",
    "sg:classifiers":[
        {
            "category":"Health Services",
            "subcategory":"Health Practitioner",
            "type":"Services"
        }
    ],
    "sg:phone":"+61 2 9386 9377",
    "sg:postcode":"2022",
    "sg:province":"NSW",
    "sg:tags":[
        "alternative"
    ],
    "wof:name":"Biological Medicine Institute Integrative Medical Centre",
    "wof:placetype":"venue"
},
  "geometry": {"coordinates":[151.24446105999999,-33.8907928467],"type":"Point"}
}