{
  "type": "Feature",
  "properties": {
    "iso:country":"AU",
    "sg:address":"14 Pickering Rd",
    "sg:city":"Mulgrave",
    "sg:classifiers":[
        {
            "category":"Manufacturing",
            "subcategory":"Metals",
            "type":"Manufacturing & Wholesale Goods"
        }
    ],
    "sg:phone":"+61 3 9561 4233",
    "sg:postcode":"3170",
    "sg:province":"VIC",
    "sg:tags":[
        "steel",
        "fabricator",
        "mfrs"
    ],
    "wof:name":"Melness Fabrications Pty Ltd",
    "wof:placetype":"venue"
},
  "geometry": {"coordinates":[145.154571533,-37.9073638916],"type":"Point"}
}