{
  "type": "Feature",
  "properties": {
    "iso:country":"AU",
    "sg:address":"2 Palomar Pde",
    "sg:city":"Harbord",
    "sg:classifiers":[
        {
            "category":"Professional",
            "subcategory":"Art Services",
            "type":"Services"
        }
    ],
    "sg:phone":"+61 2 9938 1053",
    "sg:postcode":"2096",
    "sg:province":"NSW",
    "sg:tags":[
        "caricaturist",
        "cartoonist"
    ],
    "wof:name":"Richard Jones",
    "wof:placetype":"venue"
},
  "geometry": {"coordinates":[151.27903747600001,-33.7790298462],"type":"Point"}
}