{
  "type": "Feature",
  "properties": {
    "addr:full":"Suite 106, 43- 47 Townshend St Phillip ACT 2606",
    "addr:housenumber":"47",
    "addr:postcode":"2606",
    "addr:street":"Townshend St",
    "iso:country":"AU",
    "sg:address":"Suite 106, 43- 47 Townshend St",
    "sg:city":"Phillip",
    "sg:classifiers":[
        {
            "category":"Building & Trades",
            "subcategory":"Construction",
            "type":"Services"
        }
    ],
    "sg:phone":"+61 2 6285 3900",
    "sg:postcode":"2606",
    "sg:province":"ACT",
    "sg:tags":[
        "contractor"
    ],
    "wof:name":"Pavilion Developments",
    "wof:placetype":"venue"
},
  "geometry": {"coordinates":[149.08866882300001,-35.3535118103],"type":"Point"}
}