{
  "type": "Feature",
  "properties": {
    "addr:full":"171 Bay Rd Moonta Bay SA 5558",
    "addr:housenumber":"171",
    "addr:postcode":"5558",
    "addr:street":"Bay Rd",
    "iso:country":"AU",
    "sg:address":"171 Bay Rd",
    "sg:city":"Moonta Bay",
    "sg:classifiers":[
        {
            "category":"Retail",
            "subcategory":"Event Space",
            "type":"Services"
        }
    ],
    "sg:phone":"+61 8 8825 3270",
    "sg:postcode":"5558",
    "sg:province":"SA",
    "sg:tags":[
        "venue",
        "reception",
        "wedding"
    ],
    "wof:name":"Seagate Motel",
    "wof:placetype":"venue"
},
  "geometry": {"coordinates":[137.573455811,-34.0610961914],"type":"Point"}
}