{
  "type": "Feature",
  "properties": {
    "iso:country":"AU",
    "sg:address":"385 Gympie Rd",
    "sg:city":"Kedron",
    "sg:classifiers":[
        {
            "category":"Restaurant",
            "type":"Food & Drink"
        }
    ],
    "sg:phone":"+61 7 3359 0681",
    "sg:postcode":"4031",
    "sg:province":"QLD",
    "wof:name":"Chillies Mexican Restaurant",
    "wof:placetype":"venue"
},
  "geometry": {"coordinates":[153.03185999999999,-27.4028],"type":"Point"}
}