{
  "type": "Feature",
  "properties": {
    "addr:full":"393 Townsend St Albury NSW 2640",
    "addr:housenumber":"393",
    "addr:postcode":"2640",
    "addr:street":"Townsend St",
    "iso:country":"AU",
    "sg:address":"393 Townsend St",
    "sg:city":"Albury",
    "sg:classifiers":[
        {
            "category":"Building & Trades",
            "subcategory":"Construction",
            "type":"Services"
        }
    ],
    "sg:phone":"+61 2 6021 5944",
    "sg:postcode":"2640",
    "sg:province":"NSW",
    "sg:tags":[
        "window",
        "aluminium"
    ],
    "wof:name":"Rylock Windows & Doors",
    "wof:placetype":"venue"
},
  "geometry": {"coordinates":[146.91285705600001,-36.0807418823],"type":"Point"}
}