{
  "type": "Feature",
  "properties": {
    "addr:full":"99- 111 Military Rd Neutral Bay NSW 2089",
    "addr:housenumber":"111",
    "addr:postcode":"2089",
    "addr:street":"99;Military Rd",
    "iso:country":"AU",
    "sg:address":"99- 111 Military Rd",
    "sg:city":"Neutral Bay",
    "sg:classifiers":[
        {
            "category":"Restaurant",
            "type":"Food & Drink"
        }
    ],
    "sg:phone":"+61 2 9908 1161",
    "sg:postcode":"2089",
    "sg:province":"NSW",
    "wof:name":"CJ's French Fondu Restaurant",
    "wof:placetype":"venue"
},
  "geometry": {"coordinates":[151.22019958499999,-33.8308601379],"type":"Point"}
}