{
  "type": "Feature",
  "properties": {
    "iso:country":"AU",
    "sg:address":"76 George St",
    "sg:city":"Singleton",
    "sg:classifiers":[
        {
            "category":"Fast Food",
            "type":"Food & Drink"
        }
    ],
    "sg:phone":"+61 2 6572 3555",
    "sg:postcode":"2330",
    "sg:province":"NSW",
    "sg:tags":[
        "away",
        "take"
    ],
    "wof:name":"Downtown Cafe & Takeaway",
    "wof:placetype":"venue"
},
  "geometry": {"coordinates":[151.175705,-32.562424],"type":"Point"}
}