{
  "type": "Feature",
  "properties": {
    "iso:country":"AU",
    "sg:address":"201 Banksia St",
    "sg:city":"Ivanhoe",
    "sg:classifiers":[
        {
            "category":"Health Services",
            "subcategory":"Health Practitioner",
            "type":"Services"
        }
    ],
    "sg:phone":"+61 3 9441 0088",
    "sg:postcode":"3079",
    "sg:province":"VIC",
    "sg:tags":[
        "physiotherapist"
    ],
    "wof:name":"Radford M",
    "wof:placetype":"venue"
},
  "geometry": {"coordinates":[145.04301452600001,-37.757068634],"type":"Point"}
}