{
  "type": "Feature",
  "properties": {
    "addr:full":"11 Power Ave Alexandria NSW 2015",
    "addr:housenumber":"11",
    "addr:postcode":"2015",
    "addr:street":"Power Ave",
    "iso:country":"AU",
    "sg:address":"11 Power Ave",
    "sg:city":"Alexandria",
    "sg:classifiers":[
        {
            "category":"Cafe",
            "type":"Food & Drink"
        }
    ],
    "sg:phone":"+61 2 9690 0393",
    "sg:postcode":"2015",
    "sg:province":"NSW",
    "wof:name":"Park Cafe",
    "wof:placetype":"venue"
},
  "geometry": {"coordinates":[151.19793701200001,-33.9009628296],"type":"Point"}
}