{
  "type": "Feature",
  "properties": {
    "addr:full":"6 Donald St Highett VIC 3190",
    "addr:housenumber":"6",
    "addr:postcode":"3190",
    "addr:street":"Donald St",
    "iso:country":"AU",
    "sg:address":"6 Donald St",
    "sg:city":"Highett",
    "sg:classifiers":[
        {
            "category":"Building & Trades",
            "subcategory":"Construction",
            "type":"Services"
        }
    ],
    "sg:phone":"+61 417 147 050",
    "sg:postcode":"3190",
    "sg:province":"VIC",
    "sg:tags":[
        "ceiling"
    ],
    "wof:name":"All Right Ceilings & Partitions Pty Ltd",
    "wof:placetype":"venue"
},
  "geometry": {"coordinates":[145.03808593799999,-37.951915741],"type":"Point"}
}