{
  "type": "Feature",
  "properties": {
    "addr:full":"Shop 14 Freeman St Lalor Park NSW 2147",
    "addr:housenumber":"shop 14",
    "addr:postcode":"2147",
    "addr:street":"Freeman St",
    "iso:country":"AU",
    "sg:address":"Shop 14 Freeman St",
    "sg:city":"Lalor Park",
    "sg:classifiers":[
        {
            "category":"Shopping",
            "subcategory":"Optical Goods",
            "type":"Retail Goods"
        }
    ],
    "sg:phone":"+61 2 9620 5160",
    "sg:postcode":"2147",
    "sg:province":"NSW",
    "sg:tags":[
        "dispenser",
        "prescription"
    ],
    "wof:name":"Seven Hills Optical",
    "wof:placetype":"venue"
},
  "geometry": {"coordinates":[150.93072509800001,-33.7614593506],"type":"Point"}
}