{
  "type": "Feature",
  "properties": {
    "addr:full":"158 Stirling Hwy Nedlands WA 6009",
    "addr:housenumber":"158",
    "addr:postcode":"6009",
    "addr:street":"Stirling Hwy",
    "iso:country":"AU",
    "sg:address":"158 Stirling Hwy",
    "sg:city":"Nedlands",
    "sg:classifiers":[
        {
            "category":"Sports & Exercise",
            "subcategory":"Playing Field",
            "type":"Entertainment"
        }
    ],
    "sg:phone":"+61 8 9389 8363",
    "sg:postcode":"6009",
    "sg:province":"WA",
    "sg:tags":[
        "repair",
        "walking",
        "retail",
        "umbrella",
        "stick"
    ],
    "wof:name":"Oasis Umbrella World",
    "wof:placetype":"venue"
},
  "geometry": {"coordinates":[115.794296,-31.980885],"type":"Point"}
}