{
  "type": "Feature",
  "properties": {
    "iso:country":"AU",
    "sg:address":"Shed 2 27-29 Main St",
    "sg:city":"Palmwoods",
    "sg:classifiers":[
        {
            "category":"Professional",
            "type":"Services"
        }
    ],
    "sg:phone":"+61 7 5478 8922",
    "sg:postcode":"4555",
    "sg:province":"QLD",
    "sg:tags":[
        "spray",
        "painting"
    ],
    "wof:name":"Palmwoods Smash Repairs",
    "wof:placetype":"venue"
},
  "geometry": {"coordinates":[152.96070861800001,-26.6901035309],"type":"Point"}
}