{
  "type": "Feature",
  "properties": {
    "addr:full":"PO Box 1298 Victor Harbor SA 5211",
    "addr:postcode":"5211",
    "iso:country":"AU",
    "sg:address":"PO Box 1298",
    "sg:city":"Victor Harbor",
    "sg:classifiers":[
        {
            "category":"Retail",
            "subcategory":"Veterinary Services",
            "type":"Services"
        }
    ],
    "sg:phone":"+61 414 855 923",
    "sg:postcode":"5211",
    "sg:province":"SA",
    "sg:tags":[
        "surgeon"
    ],
    "wof:name":"Fleurieu Country Vet",
    "wof:placetype":"venue"
},
  "geometry": {"coordinates":[138.624435425,-35.5497398376],"type":"Point"}
}