{
  "type": "Feature",
  "properties": {
    "addr:full":"161 Boddington Crs Kambah ACT 2902",
    "addr:housenumber":"161",
    "addr:postcode":"2902",
    "addr:street":"Boddington Crs",
    "iso:country":"AU",
    "sg:address":"161 Boddington Crs",
    "sg:city":"Kambah",
    "sg:classifiers":[
        {
            "category":"Home & Garden",
            "subcategory":"Building Materials",
            "type":"Retail Goods"
        }
    ],
    "sg:phone":"+61 412 483 846",
    "sg:postcode":"2902",
    "sg:province":"ACT",
    "sg:tags":[
        "lawn",
        "cutting",
        "maintenance"
    ],
    "wof:name":"Capital Coring",
    "wof:placetype":"venue"
},
  "geometry": {"coordinates":[149.06053161599999,-35.3863983154],"type":"Point"}
}