{
  "type": "Feature",
  "properties": {
    "addr:full":"239 Burwood Hwy Burwood East VIC 3151",
    "addr:housenumber":"239",
    "addr:postcode":"3151",
    "addr:street":"Burwood Hwy",
    "iso:country":"AU",
    "sg:address":"239 Burwood Hwy",
    "sg:city":"Burwood East",
    "sg:classifiers":[
        {
            "category":"Health Services",
            "subcategory":"Dentist",
            "type":"Services"
        }
    ],
    "sg:phone":"+61 3 9802 4679",
    "sg:postcode":"3151",
    "sg:province":"VIC",
    "wof:name":"Bergman John D Dr",
    "wof:placetype":"venue"
},
  "geometry": {"coordinates":[145.15434265100001,-37.8526115417],"type":"Point"}
}