{
  "type": "Feature",
  "properties": {
    "addr:full":"502 Murray St Perth WA 6000",
    "addr:housenumber":"502",
    "addr:postcode":"6000",
    "addr:street":"Murray St",
    "iso:country":"AU",
    "sg:address":"502 Murray St",
    "sg:city":"Perth",
    "sg:classifiers":[
        {
            "category":"Personal",
            "subcategory":"Beauty Salon",
            "type":"Services"
        }
    ],
    "sg:phone":"+61 8 9322 5996",
    "sg:postcode":"6000",
    "sg:province":"WA",
    "sg:tags":[
        "hairdresser"
    ],
    "wof:name":"Hair Plus",
    "wof:placetype":"venue"
},
  "geometry": {"coordinates":[115.85949707,-31.9532203674],"type":"Point"}
}