{
  "type": "Feature",
  "properties": {
    "addr:full":"Suite 108, 149 Castlereagh St Sydney NSW 2000",
    "addr:housenumber":"149",
    "addr:postcode":"2000",
    "addr:street":"Castlereagh St",
    "iso:country":"AU",
    "sg:address":"Suite 108, 149 Castlereagh St",
    "sg:city":"Sydney",
    "sg:classifiers":[
        {
            "category":"Health Services",
            "subcategory":"Dentist",
            "type":"Services"
        }
    ],
    "sg:phone":"+61 2 9264 8920",
    "sg:postcode":"2000",
    "sg:province":"NSW",
    "wof:name":"Cheah Madeleine Dr & Associates",
    "wof:placetype":"venue"
},
  "geometry": {"coordinates":[151.209182739,-33.8718948364],"type":"Point"}
}