{
  "type": "Feature",
  "properties": {
    "addr:full":"Shop 3, Bi-Lo Complex 104 Dangar St Armidale NSW 2350",
    "addr:housenumber":"shop 3;104",
    "addr:postcode":"2350",
    "addr:street":"Complex;Dangar St",
    "iso:country":"AU",
    "sg:address":"Shop 3, Bi-Lo Complex 104 Dangar St",
    "sg:city":"Armidale",
    "sg:classifiers":[
        {
            "category":"Personal",
            "subcategory":"Beauty Salon",
            "type":"Services"
        }
    ],
    "sg:phone":"+61 2 6772 7089",
    "sg:postcode":"2350",
    "sg:province":"NSW",
    "wof:name":"Anna Louise Skin & Beauty",
    "wof:placetype":"venue"
},
  "geometry": {"coordinates":[151.66545105,-30.5133991241],"type":"Point"}
}