{
  "type": "Feature",
  "properties": {
    "addr:full":"Lot 111 Bidgee Rd Cooma NSW 2630",
    "addr:postcode":"2630",
    "addr:street":"Bidgee Rd",
    "iso:country":"AU",
    "sg:address":"Lot 111 Bidgee Rd",
    "sg:city":"Cooma",
    "sg:classifiers":[
        {
            "category":"Building & Trades",
            "subcategory":"Construction",
            "type":"Services"
        }
    ],
    "sg:phone":"+61 412 274 778",
    "sg:postcode":"2630",
    "sg:province":"NSW",
    "sg:tags":[
        "plasterboard",
        "plasterer",
        "fixer"
    ],
    "wof:name":"Brett Osborne Plastering",
    "wof:placetype":"venue"
},
  "geometry": {"coordinates":[149.10784912099999,-36.1710128784],"type":"Point"}
}