{
  "type": "Feature",
  "properties": {
    "addr:full":"8 Kingscote St Kewdale WA 6105",
    "addr:housenumber":"8",
    "addr:postcode":"6105",
    "addr:street":"Kingscote St",
    "iso:country":"AU",
    "sg:address":"8 Kingscote St",
    "sg:city":"Kewdale",
    "sg:classifiers":[
        {
            "category":"Food & Beverages",
            "subcategory":"Specialty",
            "type":"Retail Goods"
        }
    ],
    "sg:phone":"+61 8 9353 3380",
    "sg:postcode":"6105",
    "sg:province":"WA",
    "sg:tags":[
        "delicacy"
    ],
    "wof:name":"Kongs Trading Pty Ltd",
    "wof:placetype":"venue"
},
  "geometry": {"coordinates":[115.96945953399999,-31.9776935577],"type":"Point"}
}