{
  "type": "Feature",
  "properties": {
    "addr:full":"226 Lillian Ave Salisbury QLD 4107",
    "addr:housenumber":"226",
    "addr:postcode":"4107",
    "addr:street":"Lillian Ave",
    "iso:country":"AU",
    "sg:address":"226 Lillian Ave",
    "sg:city":"Salisbury",
    "sg:classifiers":[
        {
            "category":"Food & Beverages",
            "subcategory":"Supermarket",
            "type":"Retail Goods"
        }
    ],
    "sg:phone":"+61 7 3277 4350",
    "sg:postcode":"4107",
    "sg:province":"QLD",
    "sg:tags":[
        "grocery",
        "store"
    ],
    "wof:name":"Four Square Stores (Qld) Ltd",
    "wof:placetype":"venue"
},
  "geometry": {"coordinates":[153.033966064,-27.5547027588],"type":"Point"}
}