{
  "type": "Feature",
  "properties": {
    "iso:country":"AU",
    "sg:address":"921 Albany Hwy",
    "sg:city":"East Victoria Park",
    "sg:classifiers":[
        {
            "category":"Professional",
            "subcategory":"Printing & Photocopies",
            "type":"Services"
        }
    ],
    "sg:phone":"+61 8 9362 3633",
    "sg:postcode":"6101",
    "sg:province":"WA",
    "sg:tags":[
        "photocopying"
    ],
    "wof:name":"Snap Printing",
    "wof:placetype":"venue"
},
  "geometry": {"coordinates":[115.91596984900001,-31.9984264374],"type":"Point"}
}