{
  "type": "Feature",
  "properties": {
    "addr:full":"1 The Crescent Annandale NSW 2038",
    "addr:housenumber":"1",
    "addr:postcode":"2038",
    "addr:street":"The Crescent",
    "iso:country":"AU",
    "sg:address":"1 The Crescent",
    "sg:city":"Annandale",
    "sg:classifiers":[
        {
            "category":"Home & Garden",
            "subcategory":"Carpets & Floor Coverings",
            "type":"Retail Goods"
        }
    ],
    "sg:phone":"+61 2 9660 2933",
    "sg:postcode":"2038",
    "sg:province":"NSW",
    "sg:website":"http://www.webbercarpets.com.au",
    "wof:name":"Webber's Carpet Warehouse",
    "wof:placetype":"venue"
},
  "geometry": {"coordinates":[151.17527770999999,-33.8759918213],"type":"Point"}
}