{
  "type": "Feature",
  "properties": {
    "addr:full":"Upstairs 445a Centre Rd Bentleigh VIC 3204",
    "addr:housenumber":"445a",
    "addr:postcode":"3204",
    "addr:street":"Centre Rd",
    "iso:country":"AU",
    "sg:address":"Upstairs 445a Centre Rd",
    "sg:city":"Bentleigh",
    "sg:classifiers":[
        {
            "category":"Personal",
            "subcategory":"Beauty Salon",
            "type":"Services"
        }
    ],
    "sg:phone":"+61 3 9557 3666",
    "sg:postcode":"3204",
    "sg:province":"VIC",
    "sg:tags":[
        "hairdresser"
    ],
    "wof:name":"Head Hunters Hair Body Beauty",
    "wof:placetype":"venue"
},
  "geometry": {"coordinates":[145.04028299999999,-37.918507],"type":"Point"}
}