{
  "type": "Feature",
  "properties": {
    "addr:full":"38 Wellington St Burnie South TAS 7320",
    "addr:housenumber":"38",
    "addr:postcode":"7320",
    "addr:street":"Wellington St",
    "iso:country":"AU",
    "sg:address":"38 Wellington St",
    "sg:city":"Burnie South",
    "sg:classifiers":[
        {
            "category":"Professional",
            "subcategory":"Detective & Security Services",
            "type":"Services"
        }
    ],
    "sg:phone":"+61 3 6431 1340",
    "sg:postcode":"7320",
    "sg:province":"TAS",
    "sg:tags":[
        "equipment",
        "window",
        "doors"
    ],
    "wof:name":"Walters Glass",
    "wof:placetype":"venue"
},
  "geometry": {"coordinates":[145.91040000000001,-41.062996],"type":"Point"}
}