{
  "type": "Feature",
  "properties": {
    "addr:full":"6 Upway St Prospect NSW 2148",
    "addr:housenumber":"6",
    "addr:postcode":"2148",
    "addr:street":"Upway St",
    "iso:country":"AU",
    "sg:address":"6 Upway St",
    "sg:city":"Prospect",
    "sg:classifiers":[
        {
            "category":"Manufacturing",
            "subcategory":"Food",
            "type":"Manufacturing & Wholesale Goods"
        }
    ],
    "sg:phone":"+61 2 9671 7843",
    "sg:postcode":"2148",
    "sg:province":"NSW",
    "sg:tags":[
        "function",
        "catering"
    ],
    "wof:name":"Australian Sports Catering Service Pty Ltd",
    "wof:placetype":"venue"
},
  "geometry": {"coordinates":[150.907012939,-33.7920074463],"type":"Point"}
}