{
  "type": "Feature",
  "properties": {
    "addr:full":"43 Charles St Woolloomooloo NSW 2011",
    "addr:housenumber":"43",
    "addr:postcode":"2011",
    "addr:street":"Charles St",
    "iso:country":"AU",
    "sg:address":"43 Charles St",
    "sg:city":"Woolloomooloo",
    "sg:classifiers":[
        {
            "category":"Food & Beverages",
            "subcategory":"Supermarket",
            "type":"Retail Goods"
        }
    ],
    "sg:phone":"+61 2 9358 2772",
    "sg:postcode":"2011",
    "sg:province":"NSW",
    "sg:tags":[
        "grocery",
        "store"
    ],
    "wof:name":"Nick's Till Midnight",
    "wof:placetype":"venue"
},
  "geometry": {"coordinates":[151.219116211,-33.8720626831],"type":"Point"}
}