{
  "type": "Feature",
  "properties": {
    "addr:full":"17 Russell St Branxton NSW 2335",
    "addr:housenumber":"17",
    "addr:postcode":"2335",
    "addr:street":"Russell St",
    "iso:country":"AU",
    "sg:address":"17 Russell St",
    "sg:city":"Branxton",
    "sg:classifiers":[
        {
            "category":"Building & Trades",
            "subcategory":"Construction",
            "type":"Services"
        }
    ],
    "sg:phone":"+61 2 4930 9111",
    "sg:postcode":"2335",
    "sg:province":"NSW",
    "sg:tags":[
        "earth",
        "excavating",
        "moving",
        "contractor"
    ],
    "wof:name":"CZL Group Pty Ltd",
    "wof:placetype":"venue"
},
  "geometry": {"coordinates":[151.35369873100001,-32.6622619629],"type":"Point"}
}