{
  "type": "Feature",
  "properties": {
    "addr:full":"22 Starkey St Forestville NSW 2087",
    "addr:housenumber":"22",
    "addr:postcode":"2087",
    "addr:street":"Starkey St",
    "iso:country":"AU",
    "sg:address":"22 Starkey St",
    "sg:city":"Forestville",
    "sg:classifiers":[
        {
            "category":"Health Services",
            "subcategory":"Dentist",
            "type":"Services"
        }
    ],
    "sg:phone":"+61 2 9452 1213",
    "sg:postcode":"2087",
    "sg:province":"NSW",
    "wof:name":"Dentists On Starkey",
    "wof:placetype":"venue"
},
  "geometry": {"coordinates":[151.216064453,-33.7633094788],"type":"Point"}
}