{
  "type": "Feature",
  "properties": {
    "iso:country":"AU",
    "sg:address":"PO Box 541",
    "sg:city":"Mawson",
    "sg:classifiers":[
        {
            "category":"Utilities",
            "subcategory":"Sewage",
            "type":"Services"
        }
    ],
    "sg:phone":"+61 1300 135 835",
    "sg:postcode":"2607",
    "sg:province":"ACT",
    "sg:tags":[
        "arboriculturist"
    ],
    "wof:name":"Skyline Tree Surgery",
    "wof:placetype":"venue"
},
  "geometry": {"coordinates":[149.09529113799999,-35.3641891479],"type":"Point"}
}