{
  "type": "Feature",
  "properties": {
    "iso:country":"AU",
    "sg:address":"Dntst 17 Knox St",
    "sg:city":"Double Bay",
    "sg:classifiers":[
        {
            "category":"Health Services",
            "subcategory":"Dentist",
            "type":"Services"
        }
    ],
    "sg:phone":"+61 2 9363 3351",
    "sg:postcode":"2028",
    "sg:province":"NSW",
    "wof:name":"Burns P A & Carr K A",
    "wof:placetype":"venue"
},
  "geometry": {"coordinates":[151.24273681599999,-33.8769111633],"type":"Point"}
}