{
  "type": "Feature",
  "properties": {
    "addr:full":"5 Frances Crt Sale VIC 3850",
    "addr:housenumber":"5",
    "addr:postcode":"3850",
    "addr:street":"Frances Crt",
    "iso:country":"AU",
    "sg:address":"5 Frances Crt",
    "sg:city":"Sale",
    "sg:classifiers":[
        {
            "category":"Building & Trades",
            "subcategory":"Landscaping Services",
            "type":"Services"
        }
    ],
    "sg:phone":"+61 412 001 561",
    "sg:postcode":"3850",
    "sg:province":"VIC",
    "sg:tags":[
        "gardener"
    ],
    "wof:name":"Micks Mowing & Gardening",
    "wof:placetype":"venue"
},
  "geometry": {"coordinates":[147.08236694300001,-38.1142654419],"type":"Point"}
}