{
  "type": "Feature",
  "properties": {
    "addr:full":"249a Belmore Rd Balwyn North VIC 3104",
    "addr:housenumber":"249a",
    "addr:postcode":"3104",
    "addr:street":"Belmore Rd",
    "iso:country":"AU",
    "sg:address":"249a Belmore Rd",
    "sg:city":"Balwyn North",
    "sg:classifiers":[
        {
            "category":"Education",
            "subcategory":"Special Training",
            "type":"Public Place"
        }
    ],
    "sg:phone":"+61 3 9576 0135",
    "sg:postcode":"3104",
    "sg:province":"VIC",
    "sg:tags":[
        "school",
        "art"
    ],
    "wof:name":"Art Factory The",
    "wof:placetype":"venue"
},
  "geometry": {"coordinates":[145.08334350600001,-37.8033447266],"type":"Point"}
}