{
  "type": "Feature",
  "properties": {
    "addr:full":"146- 148 High St Melton VIC 3337",
    "addr:housenumber":"148",
    "addr:postcode":"3337",
    "addr:street":"High St",
    "iso:country":"AU",
    "sg:address":"146- 148 High St",
    "sg:city":"Melton",
    "sg:classifiers":[
        {
            "category":"Autos & Motor Vehicles",
            "subcategory":"Auto Supplies",
            "type":"Retail Goods"
        }
    ],
    "sg:phone":"+61 3 9743 5592",
    "sg:postcode":"3337",
    "sg:province":"VIC",
    "sg:tags":[
        "tyre"
    ],
    "wof:name":"Tyrepower",
    "wof:placetype":"venue"
},
  "geometry": {"coordinates":[144.58682300000001,-37.682812],"type":"Point"}
}