{
  "type": "Feature",
  "properties": {
    "iso:country":"AU",
    "sg:address":"146- 148 High St",
    "sg:city":"Melton",
    "sg:classifiers":[
        {
            "category":"Autos & Motor Vehicles",
            "subcategory":"Auto Supplies",
            "type":"Retail Goods"
        }
    ],
    "sg:phone":"+61 3 9743 5592",
    "sg:postcode":"3337",
    "sg:province":"VIC",
    "sg:tags":[
        "tyre"
    ],
    "wof:name":"Tyrepower",
    "wof:placetype":"venue"
},
  "geometry": {"coordinates":[144.586823,-37.682812],"type":"Point"}
}