{
  "type": "Feature",
  "properties": {
    "iso:country":"AU",
    "sg:address":"3 Railway St",
    "sg:city":"Toowoomba",
    "sg:classifiers":[
        {
            "category":"Shopping",
            "subcategory":"Antiques",
            "type":"Retail Goods"
        }
    ],
    "sg:phone":"+61 7 4632 1830",
    "sg:postcode":"4350",
    "sg:province":"QLD",
    "wof:name":"Lancaster's Toowoomba Antique Centre",
    "wof:placetype":"venue"
},
  "geometry": {"coordinates":[151.951096,-27.557175],"type":"Point"}
}