{
  "type": "Feature",
  "properties": {
    "addr:full":"16 Belmore St Penrith NSW 2751",
    "addr:housenumber":"16",
    "addr:postcode":"2751",
    "addr:street":"Belmore St",
    "iso:country":"AU",
    "sg:address":"16 Belmore St",
    "sg:city":"Penrith",
    "sg:classifiers":[
        {
            "category":"Autos & Motor Vehicles",
            "subcategory":"Auto Supplies",
            "type":"Retail Goods"
        }
    ],
    "sg:phone":"+61 2 4731 1200",
    "sg:postcode":"2751",
    "sg:province":"NSW",
    "sg:tags":[
        "tyre"
    ],
    "wof:name":"Bob Jane T-Mart",
    "wof:placetype":"venue"
},
  "geometry": {"coordinates":[151.01057434099999,-33.8004455566],"type":"Point"}
}