{
  "type": "Feature",
  "properties": {
    "iso:country":"AU",
    "sg:address":"10 Marion St",
    "sg:city":"Bankstown",
    "sg:classifiers":[
        {
            "category":"Food & Beverages",
            "subcategory":"Liquor & Beverages",
            "type":"Retail Goods"
        }
    ],
    "sg:phone":"+61 2 9796 8921",
    "sg:postcode":"2200",
    "sg:province":"NSW",
    "sg:tags":[
        "store"
    ],
    "wof:name":"Liquorstop",
    "wof:placetype":"venue"
},
  "geometry": {"coordinates":[151.032898,-33.917366],"type":"Point"}
}