{
  "type": "Feature",
  "properties": {
    "iso:country":"AU",
    "sg:address":"7- 9 Sturt Bay Rd",
    "sg:city":"Warooka",
    "sg:classifiers":[
        {
            "category":"Utilities",
            "type":"Services"
        }
    ],
    "sg:phone":"+61 8 8854 5333",
    "sg:postcode":"5577",
    "sg:province":"SA",
    "sg:tags":[
        "refrigeration",
        "industrial",
        "commercial",
        "retail"
    ],
    "wof:name":"Chilltech",
    "wof:placetype":"venue"
},
  "geometry": {"coordinates":[137.40119934099999,-34.9921417236],"type":"Point"}
}