{
  "type": "Feature",
  "properties": {
    "addr:full":"10 Hattam St Golden Square VIC 3555",
    "addr:housenumber":"10",
    "addr:postcode":"3555",
    "addr:street":"Hattam St",
    "iso:country":"AU",
    "sg:address":"10 Hattam St",
    "sg:city":"Golden Square",
    "sg:classifiers":[
        {
            "category":"Shopping",
            "subcategory":"Pets & Pet Supplies",
            "type":"Retail Goods"
        }
    ],
    "sg:phone":"+61 3 5442 9200",
    "sg:postcode":"3555",
    "sg:province":"VIC",
    "sg:tags":[
        "food"
    ],
    "wof:name":"Petstock Bendigo",
    "wof:placetype":"venue"
},
  "geometry": {"coordinates":[144.26791381800001,-36.7822647095],"type":"Point"}
}