{
  "type": "Feature",
  "properties": {
    "iso:country":"AU",
    "sg:address":"15 High Rd",
    "sg:city":"Bethania",
    "sg:classifiers":[
        {
            "category":"Home & Garden",
            "subcategory":"Building Materials",
            "type":"Retail Goods"
        }
    ],
    "sg:phone":"+61 7 3805 5883",
    "sg:postcode":"4205",
    "sg:province":"QLD",
    "sg:tags":[
        "laminate",
        "laminated",
        "panel"
    ],
    "wof:name":"South East Benchtops",
    "wof:placetype":"venue"
},
  "geometry": {"coordinates":[153.155487061,-27.6972408295],"type":"Point"}
}