{
  "type": "Feature",
  "properties": {
    "addr:full":"15 Wentworth Pl Banyo QLD 4014",
    "addr:housenumber":"15",
    "addr:postcode":"4014",
    "addr:street":"Wentworth Pl",
    "iso:country":"AU",
    "sg:address":"15 Wentworth Pl",
    "sg:city":"Banyo",
    "sg:classifiers":[
        {
            "category":"Home & Garden",
            "subcategory":"Building Materials",
            "type":"Retail Goods"
        }
    ],
    "sg:phone":"+61 7 3260 6455",
    "sg:postcode":"4014",
    "sg:province":"QLD",
    "sg:tags":[
        "roofing"
    ],
    "wof:name":"Brisbane Sheet Metal",
    "wof:placetype":"venue"
},
  "geometry": {"coordinates":[153.079681397,-27.3882751465],"type":"Point"}
}