{
  "type": "Feature",
  "properties": {
    "addr:full":"13 Willi St Warwick QLD 4370",
    "addr:housenumber":"13",
    "addr:postcode":"4370",
    "addr:street":"Willi St",
    "iso:country":"AU",
    "sg:address":"13 Willi St",
    "sg:city":"Warwick",
    "sg:classifiers":[
        {
            "category":"Building & Trades",
            "subcategory":"Plumbing",
            "type":"Services"
        }
    ],
    "sg:phone":"+61 7 4661 1826",
    "sg:postcode":"4370",
    "sg:province":"QLD",
    "sg:tags":[
        "plumber",
        "gasfitters"
    ],
    "wof:name":"Watts Cec & Co",
    "wof:placetype":"venue"
},
  "geometry": {"coordinates":[152.00819397000001,-28.2242717743],"type":"Point"}
}