{
  "type": "Feature",
  "properties": {
    "addr:full":"50- 54 Grange Rd Carnegie VIC 3163",
    "addr:housenumber":"54",
    "addr:postcode":"3163",
    "addr:street":"Grange Rd",
    "iso:country":"AU",
    "sg:address":"50- 54 Grange Rd",
    "sg:city":"Carnegie",
    "sg:classifiers":[
        {
            "category":"Professional",
            "subcategory":"Computer Services",
            "type":"Services"
        }
    ],
    "sg:phone":"+61 3 9571 3111",
    "sg:postcode":"3163",
    "sg:province":"VIC",
    "sg:tags":[
        "consultant",
        "system"
    ],
    "wof:name":"MBS (Meier Business Systems)",
    "wof:placetype":"venue"
},
  "geometry": {"coordinates":[145.047607422,-37.8849372864],"type":"Point"}
}