{
  "type": "Feature",
  "properties": {
    "iso:country":"AU",
    "sg:address":"Shops 2-3, 775 Canning Hwy",
    "sg:city":"Applecross",
    "sg:classifiers":[
        {
            "category":"Arena",
            "subcategory":"Horse Racetrack",
            "type":"Entertainment"
        }
    ],
    "sg:phone":"+61 8 9315 9972",
    "sg:postcode":"6153",
    "sg:province":"WA",
    "sg:tags":[
        "retail",
        "swimwear"
    ],
    "wof:name":"Centre Break Surf Gallery",
    "wof:placetype":"venue"
},
  "geometry": {"coordinates":[115.84446,-32.014687],"type":"Point"}
}