{
  "type": "Feature",
  "properties": {
    "addr:full":"Suite 7/ 29-30 Grattan St Prahran VIC 3181",
    "addr:housenumber":"/ 29-30",
    "addr:postcode":"3181",
    "addr:street":"Grattan St",
    "iso:country":"AU",
    "sg:address":"Suite 7/ 29-30 Grattan St",
    "sg:city":"Prahran",
    "sg:classifiers":[
        {
            "category":"Real Estate",
            "subcategory":"Architect",
            "type":"Services"
        }
    ],
    "sg:phone":"+61 3 9521 4498",
    "sg:postcode":"3181",
    "sg:province":"VIC",
    "sg:website":"http://www.tribecagroup.com.au",
    "wof:name":"Tribeca Group Australia Pty Ltd",
    "wof:placetype":"venue"
},
  "geometry": {"coordinates":[144.99130249000001,-37.846660614],"type":"Point"}
}