{
  "type": "Feature",
  "properties": {
    "iso:country":"AU",
    "sg:address":"227 Kelly St",
    "sg:city":"Scone",
    "sg:classifiers":[
        {
            "category":"Professional",
            "subcategory":"Computer Services",
            "type":"Services"
        }
    ],
    "sg:phone":"+61 2 6545 9900",
    "sg:postcode":"2337",
    "sg:province":"NSW",
    "sg:tags":[
        "equipment",
        "networking",
        "installation"
    ],
    "wof:name":"Bhee Services Pty Ltd",
    "wof:placetype":"venue"
},
  "geometry": {"coordinates":[150.866912842,-32.0531234741],"type":"Point"}
}