{
  "type": "Feature",
  "properties": {
    "iso:country":"AU",
    "sg:address":"Becks Rd",
    "sg:city":"Drysdale",
    "sg:classifiers":[
        {
            "category":"Utilities",
            "subcategory":"Refuse",
            "type":"Services"
        }
    ],
    "sg:phone":"+61 3 5251 2935",
    "sg:postcode":"3222",
    "sg:province":"VIC",
    "sg:tags":[
        "disposal",
        "reduction",
        "waste"
    ],
    "wof:name":"Drysdale Resource Recovery Centre",
    "wof:placetype":"venue"
},
  "geometry": {"coordinates":[144.626602,-38.172321],"type":"Point"}
}