{
  "type": "Feature",
  "properties": {
    "iso:country":"AU",
    "sg:address":"PO Box 2293",
    "sg:city":"St Kilda West",
    "sg:classifiers":[
        {
            "category":"Professional",
            "subcategory":"Management & Consulting",
            "type":"Services"
        }
    ],
    "sg:phone":"+61 3 9534 1600",
    "sg:postcode":"3182",
    "sg:province":"VIC",
    "sg:tags":[
        "consultant",
        "educational"
    ],
    "wof:name":"World Challenge Expeditions",
    "wof:placetype":"venue"
},
  "geometry": {"coordinates":[144.97416687,-37.856918335],"type":"Point"}
}