{
  "type": "Feature",
  "properties": {
    "addr:full":"3 King St Nanango QLD 4615",
    "addr:housenumber":"3",
    "addr:postcode":"4615",
    "addr:street":"King St",
    "iso:country":"AU",
    "sg:address":"3 King St",
    "sg:city":"Nanango",
    "sg:classifiers":[
        {
            "category":"Professional",
            "subcategory":"Engineering",
            "type":"Services"
        }
    ],
    "sg:phone":"+61 7 4163 2999",
    "sg:postcode":"4615",
    "sg:province":"QLD",
    "sg:tags":[
        "engineer",
        "mechanical"
    ],
    "wof:name":"Uncle Arthur's Work Shop",
    "wof:placetype":"venue"
},
  "geometry": {"coordinates":[151.99745178200001,-26.6792430878],"type":"Point"}
}