{
  "type": "Feature",
  "properties": {
    "addr:full":"4 Naiooka St South Kempsey NSW 2440",
    "addr:housenumber":"4",
    "addr:postcode":"2440",
    "addr:street":"Naiooka St South",
    "iso:country":"AU",
    "sg:address":"4 Naiooka St",
    "sg:city":"South Kempsey",
    "sg:classifiers":[
        {
            "category":"Professional",
            "subcategory":"Computer Services",
            "type":"Services"
        }
    ],
    "sg:phone":"+61 2 6562 4448",
    "sg:postcode":"2440",
    "sg:province":"NSW",
    "sg:tags":[
        "repairs",
        "upgrade",
        "equipment"
    ],
    "wof:name":"Macleay Computer Services",
    "wof:placetype":"venue"
},
  "geometry": {"coordinates":[152.839279,-31.089495],"type":"Point"}
}