{
  "type": "Feature",
  "properties": {
    "addr:full":"Woolworths Complex Sandy Bay TAS 7005",
    "addr:postcode":"7005",
    "iso:country":"AU",
    "sg:address":"Woolworths Complex",
    "sg:city":"Sandy Bay",
    "sg:classifiers":[
        {
            "category":"Food & Beverages",
            "subcategory":"Specialty",
            "type":"Retail Goods"
        }
    ],
    "sg:phone":"+61 3 6224 2412",
    "sg:postcode":"7005",
    "sg:province":"TAS",
    "sg:tags":[
        "product",
        "health"
    ],
    "wof:name":"My Goodness Health Foods & Go Vita",
    "wof:placetype":"venue"
},
  "geometry": {"coordinates":[147.33280944800001,-42.9012489319],"type":"Point"}
}