{
  "type": "Feature",
  "properties": {
    "addr:full":"44 Villiers St North Melbourne VIC 3051",
    "addr:housenumber":"44",
    "addr:postcode":"3051",
    "addr:street":"Villiers St",
    "iso:country":"AU",
    "sg:address":"44 Villiers St",
    "sg:city":"North Melbourne",
    "sg:classifiers":[
        {
            "category":"Professional",
            "subcategory":"Employment Agencies",
            "type":"Services"
        }
    ],
    "sg:phone":"+61 413 135 600",
    "sg:postcode":"3051",
    "sg:province":"VIC",
    "sg:tags":[
        "occupational",
        "therapist"
    ],
    "wof:name":"NW Home Occupational Therapy",
    "wof:placetype":"venue"
},
  "geometry": {"coordinates":[144.95335388199999,-37.7994842529],"type":"Point"}
}