{
  "type": "Feature",
  "properties": {
    "addr:full":"Cnr. Mitchell & Clarinda Sts Parkes NSW 2870",
    "addr:postcode":"2870",
    "addr:street":"Sts",
    "iso:country":"AU",
    "sg:address":"Cnr. Mitchell & Clarinda Sts",
    "sg:city":"Parkes",
    "sg:classifiers":[
        {
            "category":"Retail",
            "subcategory":"Auto Repair",
            "type":"Services"
        }
    ],
    "sg:phone":"+61 2 6862 2266",
    "sg:postcode":"2870",
    "sg:province":"NSW",
    "sg:tags":[
        "repairer",
        "motor",
        "engineer"
    ],
    "wof:name":"Holden",
    "wof:placetype":"venue"
},
  "geometry": {"coordinates":[148.17349200000001,-33.129341],"type":"Point"}
}