{
  "type": "Feature",
  "properties": {
    "addr:full":"144 Toongabbie Rd Toongabbie NSW 2146",
    "addr:housenumber":"144",
    "addr:postcode":"2146",
    "addr:street":"Toongabbie Rd",
    "iso:country":"AU",
    "sg:address":"144 Toongabbie Rd",
    "sg:city":"Toongabbie",
    "sg:classifiers":[
        {
            "category":"Building & Trades",
            "subcategory":"Construction",
            "type":"Services"
        }
    ],
    "sg:phone":"+61 2 9688 3414",
    "sg:postcode":"2146",
    "sg:province":"NSW",
    "sg:tags":[
        "contractor"
    ],
    "wof:name":"Timbermass Constructions Pty Ltd",
    "wof:placetype":"venue"
},
  "geometry": {"coordinates":[150.93955993599999,-33.7941436768],"type":"Point"}
}