{
  "type": "Feature",
  "properties": {
    "addr:full":"11 Queen St Northam WA 6401",
    "addr:housenumber":"11",
    "addr:postcode":"6401",
    "addr:street":"Queen St",
    "iso:country":"AU",
    "sg:address":"11 Queen St",
    "sg:city":"Northam",
    "sg:classifiers":[
        {
            "category":"Retail",
            "subcategory":"Repair Shop",
            "type":"Services"
        }
    ],
    "sg:phone":"+61 8 9622 2690",
    "sg:postcode":"6401",
    "sg:province":"WA",
    "sg:tags":[
        "machine",
        "repairs",
        "part",
        "dryer",
        "washing"
    ],
    "wof:name":"Inland Washer Services",
    "wof:placetype":"venue"
},
  "geometry": {"coordinates":[116.661506653,-31.6475086212],"type":"Point"}
}