{
  "type": "Feature",
  "properties": {
    "addr:full":"Level 10, 333 George St Sydney NSW 2000",
    "addr:housenumber":"333",
    "addr:postcode":"2000",
    "addr:street":"George St",
    "iso:country":"AU",
    "sg:address":"Level 10, 333 George St",
    "sg:city":"Sydney",
    "sg:classifiers":[
        {
            "category":"Health Services",
            "subcategory":"Dentist",
            "type":"Services"
        }
    ],
    "sg:phone":"+61 2 8231 7400",
    "sg:postcode":"2000",
    "sg:province":"NSW",
    "wof:name":"Dean Giang",
    "wof:placetype":"venue"
},
  "geometry": {"coordinates":[151.20698547399999,-33.8669166565],"type":"Point"}
}