{
  "type": "Feature",
  "properties": {
    "addr:full":"67 Leumeah Rd Leumeah NSW 2560",
    "addr:housenumber":"67",
    "addr:postcode":"2560",
    "addr:street":"Leumeah Rd",
    "iso:country":"AU",
    "sg:address":"67 Leumeah Rd",
    "sg:city":"Leumeah",
    "sg:classifiers":[
        {
            "category":"Autos & Motor Vehicles",
            "subcategory":"Motorcycle Sales",
            "type":"Retail Goods"
        }
    ],
    "sg:phone":"+61 2 4626 2504",
    "sg:postcode":"2560",
    "sg:province":"NSW",
    "sg:tags":[
        "outboard"
    ],
    "wof:name":"Eather Mobile Marine Services",
    "wof:placetype":"venue"
},
  "geometry": {"coordinates":[150.84062194800001,-34.0522956848],"type":"Point"}
}