{
  "type": "Feature",
  "properties": {
    "addr:full":"5 Alexander St Boyne Island QLD 4680",
    "addr:housenumber":"5",
    "addr:postcode":"4680",
    "addr:street":"Alexander St",
    "iso:country":"AU",
    "sg:address":"5 Alexander St",
    "sg:city":"Boyne Island",
    "sg:classifiers":[
        {
            "category":"Health Services",
            "subcategory":"Doctor",
            "type":"Services"
        }
    ],
    "sg:phone":"+61 7 4973 3400",
    "sg:postcode":"4680",
    "sg:province":"QLD",
    "sg:tags":[
        "occupational",
        "safety"
    ],
    "wof:name":"Gateway O H & S Pty Ltd",
    "wof:placetype":"venue"
},
  "geometry": {"coordinates":[151.35812377900001,-23.9553852081],"type":"Point"}
}