{
  "type": "Feature",
  "properties": {
    "addr:full":"Ground Floor, Building A, 12 Julius Ave North Ryde NSW 2113",
    "addr:housenumber":"12",
    "addr:postcode":"2113",
    "addr:street":"Julius Ave",
    "iso:country":"AU",
    "sg:address":"Ground Floor, Building A, 12 Julius Ave",
    "sg:city":"North Ryde",
    "sg:classifiers":[
        {
            "category":"Professional",
            "subcategory":"Computer Services",
            "type":"Services"
        }
    ],
    "sg:phone":"+61 2 9805 9000",
    "sg:postcode":"2113",
    "sg:province":"NSW",
    "sg:tags":[
        "tele-communications",
        "consultant"
    ],
    "wof:name":"Comverse Network Systems",
    "wof:placetype":"venue"
},
  "geometry": {"coordinates":[151.140792847,-33.797580719],"type":"Point"}
}