{
  "type": "Feature",
  "properties": {
    "addr:full":"2/177 Glenayr Ave Bondi Beach NSW 2026",
    "addr:housenumber":"/ 177",
    "addr:postcode":"2026",
    "addr:street":"Glenayr Ave",
    "iso:country":"AU",
    "sg:address":"2/177 Glenayr Ave",
    "sg:city":"Bondi Beach",
    "sg:classifiers":[
        {
            "category":"Health Services",
            "subcategory":"Dentist",
            "type":"Services"
        }
    ],
    "sg:phone":"+61 2 9130 4827",
    "sg:postcode":"2026",
    "sg:province":"NSW",
    "wof:name":"Kanikevich Helen",
    "wof:placetype":"venue"
},
  "geometry": {"coordinates":[151.27076721200001,-33.8884239197],"type":"Point"}
}