{
  "type": "Feature",
  "properties": {
    "addr:full":"Unit 1, 33 McCoy St Myaree WA 6154",
    "addr:housenumber":"33",
    "addr:postcode":"6154",
    "addr:street":"Mccoy St",
    "iso:country":"AU",
    "sg:address":"Unit 1, 33 McCoy St",
    "sg:city":"Myaree",
    "sg:classifiers":[
        {
            "category":"Utilities",
            "subcategory":"Water",
            "type":"Services"
        }
    ],
    "sg:phone":"+61 8 9317 4893",
    "sg:postcode":"6154",
    "sg:province":"WA",
    "sg:tags":[
        "equipment",
        "treatment"
    ],
    "wof:name":"Advanced Watertek Pty Ltd",
    "wof:placetype":"venue"
},
  "geometry": {"coordinates":[115.80959300000001,-32.043724],"type":"Point"}
}