{
  "type": "Feature",
  "properties": {
    "addr:full":"Shop B39 Chadstone Shopping Centre Chadstone VIC 3148",
    "addr:housenumber":"b39",
    "addr:postcode":"3148",
    "iso:country":"AU",
    "sg:address":"Shop B39 Chadstone Shopping Centre",
    "sg:city":"Chadstone",
    "sg:classifiers":[
        {
            "category":"Professional",
            "subcategory":"Printing & Photocopies",
            "type":"Services"
        }
    ],
    "sg:phone":"+61 421 351 351",
    "sg:postcode":"3148",
    "sg:province":"VIC",
    "sg:tags":[
        "trophy"
    ],
    "sg:website":"http://www.philsengraving.com.au",
    "wof:name":"Phils Trophies",
    "wof:placetype":"venue"
},
  "geometry": {"coordinates":[145.096893311,-37.881111145],"type":"Point"}
}