{
  "type": "Feature",
  "properties": {
    "addr:full":"10 Princetown Rd Simpson VIC 3266",
    "addr:housenumber":"10",
    "addr:postcode":"3266",
    "addr:street":"Princetown Rd",
    "iso:country":"AU",
    "sg:address":"10 Princetown Rd",
    "sg:city":"Simpson",
    "sg:classifiers":[
        {
            "category":"Home & Garden",
            "subcategory":"Garden Supply",
            "type":"Retail Goods"
        }
    ],
    "sg:phone":"+61 3 5594 3250",
    "sg:postcode":"3266",
    "sg:province":"VIC",
    "sg:tags":[
        "fertilizer"
    ],
    "wof:name":"Heytesbury Fertilizers",
    "wof:placetype":"venue"
},
  "geometry": {"coordinates":[143.20021057100001,-38.5086364746],"type":"Point"}
}