{
  "type": "Feature",
  "properties": {
    "iso:country":"AU",
    "sg:address":"Unit 3/ 11 Angove Drv",
    "sg:city":"Hillarys",
    "sg:classifiers":[
        {
            "category":"Building & Trades",
            "subcategory":"Landscaping Services",
            "type":"Services"
        }
    ],
    "sg:phone":"+61 8 9227 3727",
    "sg:postcode":"6025",
    "sg:province":"WA",
    "sg:tags":[
        "designer",
        "landscape",
        "contractor"
    ],
    "wof:name":"Combined Landscaping Services",
    "wof:placetype":"venue"
},
  "geometry": {"coordinates":[115.742919922,-31.813293457],"type":"Point"}
}