{
  "type": "Feature",
  "properties": {
    "iso:country":"AU",
    "sg:address":"Rocky Rd",
    "sg:city":"Forest Grove",
    "sg:classifiers":[
        {
            "category":"Farming",
            "subcategory":"Vineyard",
            "type":"Manufacturing & Wholesale Goods"
        }
    ],
    "sg:phone":"+61 8 9757 7573",
    "sg:postcode":"6286",
    "sg:province":"WA",
    "sg:tags":[
        "winery"
    ],
    "wof:name":"Devil's Lair Vineyard",
    "wof:placetype":"venue"
},
  "geometry": {"coordinates":[115.10816955599999,-34.063495636],"type":"Point"}
}