{
  "type": "Feature",
  "properties": {
    "addr:full":"20 Millrose Drv Malaga WA 6090",
    "addr:housenumber":"20",
    "addr:postcode":"6090",
    "addr:street":"Millrose Drv",
    "iso:country":"AU",
    "sg:address":"20 Millrose Drv",
    "sg:city":"Malaga",
    "sg:classifiers":[
        {
            "category":"Shopping",
            "subcategory":"Mobile Phones",
            "type":"Retail Goods"
        }
    ],
    "sg:phone":"+61 8 9248 9744",
    "sg:postcode":"6090",
    "sg:province":"WA",
    "sg:tags":[
        "wholesaler",
        "mfrs",
        "electrical",
        "switchboard"
    ],
    "wof:name":"B & R Enclosures Pty Ltd",
    "wof:placetype":"venue"
},
  "geometry": {"coordinates":[115.897422791,-31.8650531769],"type":"Point"}
}