{
  "type": "Feature",
  "properties": {
    "addr:full":"25 Eagle Drv Jandakot WA 6164",
    "addr:housenumber":"25",
    "addr:postcode":"6164",
    "addr:street":"Eagle Drv",
    "iso:country":"AU",
    "sg:address":"25 Eagle Drv",
    "sg:city":"Jandakot",
    "sg:classifiers":[
        {
            "category":"Utilities",
            "subcategory":"Fuel Oil & Lpg",
            "type":"Services"
        }
    ],
    "sg:phone":"+61 8 9414 1515",
    "sg:postcode":"6164",
    "sg:province":"WA",
    "sg:tags":[
        "merchant"
    ],
    "wof:name":"Jandakot Refuelling Services",
    "wof:placetype":"venue"
},
  "geometry": {"coordinates":[115.87545,-32.095959],"type":"Point"}
}