{
  "type": "Feature",
  "properties": {
    "addr:full":"18b Chapman St Proserpine QLD 4800",
    "addr:housenumber":"18b",
    "addr:postcode":"4800",
    "addr:street":"Chapman St",
    "iso:country":"AU",
    "sg:address":"18b Chapman St",
    "sg:city":"Proserpine",
    "sg:classifiers":[
        {
            "category":"Social Services",
            "subcategory":"Child Care",
            "type":"Services"
        }
    ],
    "sg:phone":"+61 7 4945 2422",
    "sg:postcode":"4800",
    "sg:province":"QLD",
    "wof:name":"Whitsunday Shire Family Day Care",
    "wof:placetype":"venue"
},
  "geometry": {"coordinates":[148.58320617699999,-20.4007797241],"type":"Point"}
}