{
  "type": "Feature",
  "properties": {
    "addr:full":"52 Old Kent Rd Greenacre NSW 2190",
    "addr:housenumber":"52",
    "addr:postcode":"2190",
    "addr:street":"Old Kent Rd",
    "iso:country":"AU",
    "sg:address":"52 Old Kent Rd",
    "sg:city":"Greenacre",
    "sg:classifiers":[
        {
            "category":"Real Estate",
            "subcategory":"Real Estate Operator",
            "type":"Services"
        }
    ],
    "sg:phone":"+61 2 9750 3172",
    "sg:postcode":"2190",
    "sg:province":"NSW",
    "sg:tags":[
        "concrete",
        "pumping"
    ],
    "wof:name":"Master Concrete Pumping",
    "wof:placetype":"venue"
},
  "geometry": {"coordinates":[151.057816,-33.915401],"type":"Point"}
}