{
  "type": "Feature",
  "properties": {
    "addr:full":"4 Robert St Smithfield NSW 2164",
    "addr:housenumber":"4",
    "addr:postcode":"2164",
    "addr:street":"Robert St",
    "iso:country":"AU",
    "sg:address":"4 Robert St",
    "sg:city":"Smithfield",
    "sg:classifiers":[
        {
            "category":"Bars & Pubs",
            "subcategory":"Sports Bar",
            "type":"Food & Drink"
        }
    ],
    "sg:phone":"+61 2 9609 5890",
    "sg:postcode":"2164",
    "sg:province":"NSW",
    "sg:tags":[
        "rolling",
        "forming",
        "metal"
    ],
    "wof:name":"Mark Griffiths Engineering Services Pty Ltd",
    "wof:placetype":"venue"
},
  "geometry": {"coordinates":[150.94374084500001,-33.8506736755],"type":"Point"}
}