{
  "type": "Feature",
  "properties": {
    "addr:full":"152 Mary St Gympie QLD 4570",
    "addr:housenumber":"152",
    "addr:postcode":"4570",
    "addr:street":"Mary St",
    "iso:country":"AU",
    "sg:address":"152 Mary St",
    "sg:city":"Gympie",
    "sg:classifiers":[
        {
            "category":"Shopping",
            "subcategory":"Jewelry",
            "type":"Retail Goods"
        }
    ],
    "sg:phone":"+61 7 5482 2239",
    "sg:postcode":"4570",
    "sg:province":"QLD",
    "sg:tags":[
        "jeweller"
    ],
    "wof:name":"Goodyear Jewellers",
    "wof:placetype":"venue"
},
  "geometry": {"coordinates":[152.66122436500001,-26.1898078918],"type":"Point"}
}