{
  "type": "Feature",
  "properties": {
    "addr:full":"22a Regent St Preston VIC 3072",
    "addr:housenumber":"22a",
    "addr:postcode":"3072",
    "addr:street":"Regent St",
    "iso:country":"AU",
    "sg:address":"22a Regent St",
    "sg:city":"Preston",
    "sg:classifiers":[
        {
            "category":"Social Services",
            "subcategory":"Child Care",
            "type":"Services"
        }
    ],
    "sg:phone":"+61 3 9471 4688",
    "sg:postcode":"3072",
    "sg:province":"VIC",
    "wof:name":"Regent Child Care Centre",
    "wof:placetype":"venue"
},
  "geometry": {"coordinates":[145.0027771,-37.7303733826],"type":"Point"}
}