{
  "type": "Feature",
  "properties": {
    "addr:full":"18 Bank Pl Melbourne VIC 3000",
    "addr:housenumber":"18",
    "addr:postcode":"3000",
    "addr:street":"Bank Pl",
    "iso:country":"AU",
    "sg:address":"18 Bank Pl",
    "sg:city":"Melbourne",
    "sg:classifiers":[
        {
            "category":"Travel",
            "subcategory":"Hotels & Motels",
            "type":"Entertainment"
        }
    ],
    "sg:phone":"+61 3 9604 4321",
    "sg:postcode":"3000",
    "sg:province":"VIC",
    "sg:tags":[
        "accommodation"
    ],
    "wof:name":"Metro Apartments Melbourne",
    "wof:placetype":"venue"
},
  "geometry": {"coordinates":[144.96052551299999,-37.8164863586],"type":"Point"}
}