{
  "type": "Feature",
  "properties": {
    "addr:full":"17 Church St Traralgon VIC 3844",
    "addr:housenumber":"17",
    "addr:postcode":"3844",
    "addr:street":"Church St",
    "iso:country":"AU",
    "sg:address":"17 Church St",
    "sg:city":"Traralgon",
    "sg:classifiers":[
        {
            "category":"Professional",
            "subcategory":"Art Services",
            "type":"Services"
        }
    ],
    "sg:phone":"+61 3 5174 7172",
    "sg:postcode":"3844",
    "sg:province":"VIC",
    "sg:tags":[
        "graphic",
        "designer"
    ],
    "wof:name":"Phil Smith Design",
    "wof:placetype":"venue"
},
  "geometry": {"coordinates":[146.534988403,-38.1974372864],"type":"Point"}
}