{
  "type": "Feature",
  "properties": {
    "addr:full":"569 Olive St Albury NSW 2640",
    "addr:housenumber":"569",
    "addr:postcode":"2640",
    "addr:street":"Olive St",
    "iso:country":"AU",
    "sg:address":"569 Olive St",
    "sg:city":"Albury",
    "sg:classifiers":[
        {
            "category":"Personal",
            "subcategory":"Beauty Salon",
            "type":"Services"
        }
    ],
    "sg:phone":"+61 2 6041 2171",
    "sg:postcode":"2640",
    "sg:province":"NSW",
    "sg:tags":[
        "hairdresser"
    ],
    "wof:name":"The ParLour On Olive",
    "wof:placetype":"venue"
},
  "geometry": {"coordinates":[146.918457031,-36.0786628723],"type":"Point"}
}