{
  "type": "Feature",
  "properties": {
    "addr:full":"Unit 6, 49 Qualtrough St Woolloongabba QLD 4102",
    "addr:housenumber":"49",
    "addr:postcode":"4102",
    "addr:street":"Qualtrough St",
    "iso:country":"AU",
    "sg:address":"Unit 6, 49 Qualtrough St",
    "sg:city":"Woolloongabba",
    "sg:classifiers":[
        {
            "category":"Arts & Performance",
            "subcategory":"Art Gallery",
            "type":"Entertainment"
        }
    ],
    "sg:phone":"+61 7 3391 7997",
    "sg:postcode":"4102",
    "sg:province":"QLD",
    "wof:name":"Rental Art Australia",
    "wof:placetype":"venue"
},
  "geometry": {"coordinates":[153.035842895,-27.4891109467],"type":"Point"}
}