{
  "type": "Feature",
  "properties": {
    "addr:full":"187 Bridge St Oakey QLD 4401",
    "addr:housenumber":"187",
    "addr:postcode":"4401",
    "addr:street":"Bridge St",
    "iso:country":"AU",
    "sg:address":"187 Bridge St",
    "sg:city":"Oakey",
    "sg:classifiers":[
        {
            "category":"Wholesale",
            "subcategory":"Farm Supplies",
            "type":"Manufacturing & Wholesale Goods"
        }
    ],
    "sg:phone":"+61 7 4691 4691",
    "sg:postcode":"4401",
    "sg:province":"QLD",
    "sg:tags":[
        "feed",
        "supplement",
        "stock"
    ],
    "wof:name":"Better Blend Stockfeeds",
    "wof:placetype":"venue"
},
  "geometry": {"coordinates":[151.71078491200001,-27.4271469116],"type":"Point"}
}