{
  "type": "Feature",
  "properties": {
    "iso:country":"AU",
    "sg:address":"27 Elizabeth St",
    "sg:city":"George Town",
    "sg:classifiers":[
        {
            "category":"Retail",
            "subcategory":"Auto Repair",
            "type":"Services"
        }
    ],
    "sg:phone":"+61 3 6382 1951",
    "sg:postcode":"7253",
    "sg:province":"TAS",
    "sg:tags":[
        "beater",
        "painter",
        "panel"
    ],
    "wof:name":"George Town Panel & Paint",
    "wof:placetype":"venue"
},
  "geometry": {"coordinates":[146.81988525400001,-41.1063079834],"type":"Point"}
}