{
  "type": "Feature",
  "properties": {
    "iso:country":"AU",
    "sg:address":"357 Gardeners Rd",
    "sg:city":"Rosebery",
    "sg:classifiers":[
        {
            "category":"Food & Beverages",
            "subcategory":"Fruits & Vegetables",
            "type":"Retail Goods"
        }
    ],
    "sg:phone":"+61 2 9667 2035",
    "sg:postcode":"2018",
    "sg:province":"NSW",
    "sg:tags":[
        "greengrocer",
        "fruiterer"
    ],
    "wof:name":"Arida International Fruit Market",
    "wof:placetype":"venue"
},
  "geometry": {"coordinates":[151.20428466800001,-33.922668457],"type":"Point"}
}