{
  "type": "Feature",
  "properties": {
    "addr:full":"PO Box 423 Currumbin QLD 4223",
    "addr:postcode":"4223",
    "iso:country":"AU",
    "sg:address":"PO Box 423",
    "sg:city":"Currumbin",
    "sg:classifiers":[
        {
            "category":"Building & Trades",
            "subcategory":"Construction",
            "type":"Services"
        }
    ],
    "sg:phone":"+61 402 474 977",
    "sg:postcode":"4223",
    "sg:province":"QLD",
    "sg:tags":[
        "polishing",
        "sanding",
        "floor"
    ],
    "wof:name":"Master Tint Floor Sanding",
    "wof:placetype":"venue"
},
  "geometry": {"coordinates":[153.47454834000001,-28.1377792358],"type":"Point"}
}