{
  "type": "Feature",
  "properties": {
    "addr:full":"87 Wickham Tce Brisbane QLD 4000",
    "addr:housenumber":"87",
    "addr:postcode":"4000",
    "addr:street":"Wickham Tce",
    "iso:country":"AU",
    "sg:address":"87 Wickham Tce",
    "sg:city":"Brisbane",
    "sg:classifiers":[
        {
            "category":"Health Services",
            "subcategory":"Doctor",
            "type":"Services"
        }
    ],
    "sg:phone":"+61 1300 360 456",
    "sg:postcode":"4000",
    "sg:province":"QLD",
    "sg:tags":[
        "nurse",
        "nursing"
    ],
    "sg:website":"http://www.oxleynursing.com.au",
    "wof:name":"Oxley Nursing Service Pty Ltd",
    "wof:placetype":"venue"
},
  "geometry": {"coordinates":[153.02684020999999,-27.4644565582],"type":"Point"}
}