{
  "type": "Feature",
  "properties": {
    "iso:country":"AU",
    "sg:address":"Rm 614/ 37 Swanston St",
    "sg:city":"Melbourne",
    "sg:classifiers":[
        {
            "category":"Real Estate",
            "subcategory":"Architect",
            "type":"Services"
        }
    ],
    "sg:phone":"+61 3 9650 3270",
    "sg:postcode":"3000",
    "sg:province":"VIC",
    "wof:name":"Butcher Mardi Architect",
    "wof:placetype":"venue"
},
  "geometry": {"coordinates":[144.96693420400001,-37.8166503906],"type":"Point"}
}