{
  "type": "Feature",
  "properties": {
    "addr:full":"Bourbon St Gulargambone NSW 2828",
    "addr:postcode":"2828",
    "iso:country":"AU",
    "sg:address":"Bourbon St",
    "sg:city":"Gulargambone",
    "sg:classifiers":[
        {
            "category":"Banks & Credit Unions",
            "subcategory":"Bank",
            "type":"Services"
        }
    ],
    "sg:phone":"+61 13 24 40",
    "sg:postcode":"2828",
    "sg:province":"NSW",
    "sg:tags":[
        "society"
    ],
    "wof:name":"Reliance Credit Union",
    "wof:placetype":"venue"
},
  "geometry": {"coordinates":[148.473190308,-31.3318004608],"type":"Point"}
}