{
  "type": "Feature",
  "properties": {
    "addr:full":"Suite 10, Medical Centre Sunshine Coast Private Hospital Buderim QLD 4556",
    "addr:postcode":"4556",
    "addr:street":"Sunshine Coast",
    "iso:country":"AU",
    "sg:address":"Suite 10, Medical Centre Sunshine Coast Private Hospital",
    "sg:city":"Buderim",
    "sg:classifiers":[
        {
            "category":"Health Services",
            "subcategory":"Doctor",
            "type":"Services"
        }
    ],
    "sg:phone":"+61 7 5477 6412",
    "sg:postcode":"4556",
    "sg:province":"QLD",
    "sg:tags":[
        "medical",
        "practitioner"
    ],
    "wof:name":"Alana Harris Dr",
    "wof:placetype":"venue"
},
  "geometry": {"coordinates":[153.08071899399999,-26.6554775238],"type":"Point"}
}