{
  "type": "Feature",
  "properties": {
    "iso:country":"AU",
    "sg:address":"59 Ellen St",
    "sg:city":"Fremantle",
    "sg:classifiers":[
        {
            "category":"Health Services",
            "subcategory":"Doctor",
            "type":"Services"
        }
    ],
    "sg:phone":"+61 8 9430 5001",
    "sg:postcode":"6160",
    "sg:province":"WA",
    "sg:tags":[
        "medical",
        "practitioner"
    ],
    "wof:name":"Ellen Street Family Practice",
    "wof:placetype":"venue"
},
  "geometry": {"coordinates":[115.749901,-32.052181],"type":"Point"}
}