{
  "type": "Feature",
  "properties": {
    "addr:full":"37 Percy St Ingleburn NSW 2565",
    "addr:housenumber":"37",
    "addr:postcode":"2565",
    "addr:street":"Percy St",
    "iso:country":"AU",
    "sg:address":"37 Percy St",
    "sg:city":"Ingleburn",
    "sg:classifiers":[
        {
            "category":"Professional",
            "subcategory":"Accounting & Tax Preparation",
            "type":"Services"
        }
    ],
    "sg:phone":"+61 2 9618 3928",
    "sg:postcode":"2565",
    "sg:province":"NSW",
    "sg:tags":[
        "accountant",
        "auditor"
    ],
    "wof:name":"Laws R W & Associates Pty Ltd",
    "wof:placetype":"venue"
},
  "geometry": {"coordinates":[150.865631103,-34.0099372864],"type":"Point"}
}