{
  "type": "Feature",
  "properties": {
    "addr:full":"37 Edinburgh Crs Goodwood TAS 7010",
    "addr:housenumber":"37",
    "addr:postcode":"7010",
    "addr:street":"Edinburgh Crs",
    "iso:country":"AU",
    "sg:address":"37 Edinburgh Crs",
    "sg:city":"Goodwood",
    "sg:classifiers":[
        {
            "category":"Autos & Motor Vehicles",
            "subcategory":"Recreational Vehicle Sales",
            "type":"Retail Goods"
        }
    ],
    "sg:phone":"+61 409 827 845",
    "sg:postcode":"7010",
    "sg:province":"TAS",
    "sg:tags":[
        "industrial",
        "sewing",
        "contractor"
    ],
    "wof:name":"Stephen Marskell",
    "wof:placetype":"venue"
},
  "geometry": {"coordinates":[147.289505005,-42.8290596008],"type":"Point"}
}