{
  "type": "Feature",
  "properties": {
    "addr:full":"808 Bellarine Hwy Leopold VIC 3224",
    "addr:housenumber":"808",
    "addr:postcode":"3224",
    "addr:street":"Bellarine Hwy Leopold",
    "iso:country":"AU",
    "sg:address":"808 Bellarine Hwy",
    "sg:city":"Leopold",
    "sg:classifiers":[
        {
            "category":"Food & Beverages",
            "subcategory":"Groceries & Convenience Stores",
            "type":"Retail Goods"
        }
    ],
    "sg:phone":"+61 3 5250 3085",
    "sg:postcode":"3224",
    "sg:province":"VIC",
    "wof:name":"Caltex Q 7 Convenience Store",
    "wof:placetype":"venue"
},
  "geometry": {"coordinates":[144.47051999999999,-38.19083],"type":"Point"}
}