{
  "type": "Feature",
  "properties": {
    "iso:country":"AU",
    "sg:address":"579 Grand Junction Rd",
    "sg:city":"Gepps Cross",
    "sg:classifiers":[
        {
            "category":"Wholesale",
            "subcategory":"Auto Parts",
            "type":"Manufacturing & Wholesale Goods"
        }
    ],
    "sg:phone":"+61 8 8262 3700",
    "sg:postcode":"5094",
    "sg:province":"SA",
    "sg:tags":[
        "recyclers"
    ],
    "wof:name":"Parts Of Distinction",
    "wof:placetype":"venue"
},
  "geometry": {"coordinates":[138.59016418499999,-34.8483924866],"type":"Point"}
}