{
  "type": "Feature",
  "properties": {
    "addr:full":"Shp 2, 78-86 Harbour St Haymarket NSW 2000",
    "addr:housenumber":"2 78-86",
    "addr:postcode":"2000",
    "addr:street":"Harbour St",
    "iso:country":"AU",
    "sg:address":"Shp 2, 78-86 Harbour St",
    "sg:city":"Haymarket",
    "sg:classifiers":[
        {
            "category":"Restaurant",
            "type":"Food & Drink"
        }
    ],
    "sg:phone":"+61 2 9211 8637",
    "sg:postcode":"2000",
    "sg:province":"NSW",
    "wof:name":"Burger King Australia Pty Ltd",
    "wof:placetype":"venue"
},
  "geometry": {"coordinates":[151.20353698700001,-33.8790779114],"type":"Point"}
}