{
  "type": "Feature",
  "properties": {
    "addr:full":"36 Wellington Rd Box Hill VIC 3128",
    "addr:housenumber":"36",
    "addr:postcode":"3128",
    "addr:street":"Wellington Rd",
    "iso:country":"AU",
    "sg:address":"36 Wellington Rd",
    "sg:city":"Box Hill",
    "sg:classifiers":[
        {
            "category":"Health Services",
            "subcategory":"Doctor",
            "type":"Services"
        }
    ],
    "sg:phone":"+61 3 9890 5799",
    "sg:postcode":"3128",
    "sg:province":"VIC",
    "sg:tags":[
        "medical",
        "practitioner"
    ],
    "wof:name":"Skin Cancer Institute Australian",
    "wof:placetype":"venue"
},
  "geometry": {"coordinates":[145.117874145,-37.8143806458],"type":"Point"}
}