{
  "type": "Feature",
  "properties": {
    "addr:full":"22A Blaxland Rd Campbelltown NSW 2560",
    "addr:housenumber":"22a",
    "addr:postcode":"2560",
    "addr:street":"Blaxland Rd",
    "iso:country":"AU",
    "sg:address":"22A Blaxland Rd",
    "sg:city":"Campbelltown",
    "sg:classifiers":[
        {
            "category":"Home & Garden",
            "subcategory":"Carpets & Floor Coverings",
            "type":"Retail Goods"
        }
    ],
    "sg:phone":"+61 2 4621 5285",
    "sg:postcode":"2560",
    "sg:province":"NSW",
    "sg:tags":[
        "wood"
    ],
    "wof:name":"Harvey Norman Flooring",
    "wof:placetype":"venue"
},
  "geometry": {"coordinates":[150.815383911,-34.0586395264],"type":"Point"}
}