{
  "type": "Feature",
  "properties": {
    "addr:full":"Unit 2/ 92a Mona Vale Rd Mona Vale NSW 2103",
    "addr:housenumber":"/ 92a",
    "addr:postcode":"2103",
    "addr:street":"Mona Vale Rd",
    "iso:country":"AU",
    "sg:address":"Unit 2/ 92a Mona Vale Rd",
    "sg:city":"Mona Vale",
    "sg:classifiers":[
        {
            "category":"Insurance",
            "subcategory":"Life Insurance",
            "type":"Services"
        }
    ],
    "sg:phone":"+61 2 9999 4111",
    "sg:postcode":"2103",
    "sg:province":"NSW",
    "wof:name":"Specialist Consulting Group Pty Ltd",
    "wof:placetype":"venue"
},
  "geometry": {"coordinates":[151.28919982900001,-33.676109314],"type":"Point"}
}