{
  "type": "Feature",
  "properties": {
    "addr:full":"43 Park Ave Streaky Bay SA 5680",
    "addr:housenumber":"43",
    "addr:postcode":"5680",
    "addr:street":"Park Ave",
    "iso:country":"AU",
    "sg:address":"43 Park Ave",
    "sg:city":"Streaky Bay",
    "sg:classifiers":[
        {
            "category":"Building & Trades",
            "subcategory":"Pest Control",
            "type":"Services"
        }
    ],
    "sg:phone":"+61 427 722 236",
    "sg:postcode":"5680",
    "sg:province":"SA",
    "wof:name":"Streaky Bay Pest Control",
    "wof:placetype":"venue"
},
  "geometry": {"coordinates":[134.21307373100001,-32.8002128601],"type":"Point"}
}