{
  "type": "Feature",
  "properties": {
    "addr:full":"Unit 3, 160 Gilba Rd Girraween NSW 2145",
    "addr:housenumber":"160",
    "addr:postcode":"2145",
    "addr:street":"Gilba Rd",
    "iso:country":"AU",
    "sg:address":"Unit 3, 160 Gilba Rd",
    "sg:city":"Girraween",
    "sg:classifiers":[
        {
            "category":"Retail",
            "subcategory":"Auto Repair",
            "type":"Services"
        }
    ],
    "sg:phone":"+61 2 9688 3686",
    "sg:postcode":"2145",
    "sg:province":"NSW",
    "sg:tags":[
        "muffler",
        "exhaust",
        "system"
    ],
    "wof:name":"Berklee Australia Exhaust Centre",
    "wof:placetype":"venue"
},
  "geometry": {"coordinates":[150.94046020499999,-33.7967147827],"type":"Point"}
}