{
  "type": "Feature",
  "properties": {
    "addr:full":"Hastings St Noosa Heads QLD 4567",
    "addr:postcode":"4567",
    "addr:street":"Hastings St",
    "iso:country":"AU",
    "sg:address":"Hastings St",
    "sg:city":"Noosa Heads",
    "sg:classifiers":[
        {
            "category":"Communications",
            "subcategory":"News Services",
            "type":"Services"
        }
    ],
    "sg:phone":"+61 7 5447 2411",
    "sg:postcode":"4567",
    "sg:province":"QLD",
    "sg:tags":[
        "information",
        "tourist",
        "attractions"
    ],
    "wof:name":"Fraser Island Day Tours",
    "wof:placetype":"venue"
},
  "geometry": {"coordinates":[153.08932495100001,-26.3864173889],"type":"Point"}
}