{
  "type": "Feature",
  "properties": {
    "addr:full":"266 Bolton St Eltham VIC 3095",
    "addr:housenumber":"266",
    "addr:postcode":"3095",
    "addr:street":"Bolton St",
    "iso:country":"AU",
    "sg:address":"266 Bolton St",
    "sg:city":"Eltham",
    "sg:classifiers":[
        {
            "category":"Shopping",
            "subcategory":"Music",
            "type":"Retail Goods"
        }
    ],
    "sg:phone":"+61 3 9439 4800",
    "sg:postcode":"3095",
    "sg:province":"VIC",
    "sg:tags":[
        "instrument",
        "musical"
    ],
    "wof:name":"Manhattan School of Music",
    "wof:placetype":"venue"
},
  "geometry": {"coordinates":[145.13746643100001,-37.7206115723],"type":"Point"}
}