{
  "type": "Feature",
  "properties": {
    "iso:country":"AU",
    "sg:address":"67 Hoskins Ave",
    "sg:city":"Bankstown",
    "sg:classifiers":[
        {
            "category":"Building & Trades",
            "subcategory":"Construction",
            "type":"Services"
        }
    ],
    "sg:phone":"+61 2 9793 7714",
    "sg:postcode":"2200",
    "sg:province":"NSW",
    "sg:tags":[
        "window",
        "aluminium"
    ],
    "wof:name":"Prestige Commercial Windows Pty Ltd",
    "wof:placetype":"venue"
},
  "geometry": {"coordinates":[151.03501900000001,-33.931606],"type":"Point"}
}