{
  "type": "Feature",
  "properties": {
    "addr:full":"216 Glebe Point Rd Glebe NSW 2037",
    "addr:housenumber":"216",
    "addr:postcode":"2037",
    "addr:street":"Glebe Point Rd",
    "iso:country":"AU",
    "sg:address":"216 Glebe Point Rd",
    "sg:city":"Glebe",
    "sg:classifiers":[
        {
            "category":"Health Services",
            "subcategory":"Doctor",
            "type":"Services"
        }
    ],
    "sg:phone":"+61 2 9660 1177",
    "sg:postcode":"2037",
    "sg:province":"NSW",
    "sg:tags":[
        "medical",
        "practitioner"
    ],
    "wof:name":"Salgo Anthony Dr",
    "wof:placetype":"venue"
},
  "geometry": {"coordinates":[151.18431091299999,-33.8766021729],"type":"Point"}
}