{
  "type": "Feature",
  "properties": {
    "addr:full":"Shop 10/ 2 Sunnybrooke Drv Wynn Vale SA 5127",
    "addr:housenumber":"shop 10 / 2",
    "addr:postcode":"5127",
    "addr:street":"Sunnybrooke Drv",
    "iso:country":"AU",
    "sg:address":"Shop 10/ 2 Sunnybrooke Drv",
    "sg:city":"Wynn Vale",
    "sg:classifiers":[
        {
            "category":"Communications",
            "subcategory":"Film & Video Production",
            "type":"Services"
        }
    ],
    "sg:phone":"+61 8 8251 5733",
    "sg:postcode":"5127",
    "sg:province":"SA",
    "sg:tags":[
        "dvd",
        "library"
    ],
    "wof:name":"Video Ezy",
    "wof:placetype":"venue"
},
  "geometry": {"coordinates":[138.68898010300001,-34.8008766174],"type":"Point"}
}