{
  "type": "Feature",
  "properties": {
    "addr:full":"36 Eileen Rd Clayton VIC 3168",
    "addr:housenumber":"36",
    "addr:postcode":"3168",
    "addr:street":"Eileen Rd",
    "iso:country":"AU",
    "sg:address":"36 Eileen Rd",
    "sg:city":"Clayton",
    "sg:classifiers":[
        {
            "category":"Retail",
            "subcategory":"Auto Repair",
            "type":"Services"
        }
    ],
    "sg:phone":"+61 3 9547 6686",
    "sg:postcode":"3168",
    "sg:province":"VIC",
    "sg:tags":[
        "electrical"
    ],
    "wof:name":"Buzza Auto Electrical",
    "wof:placetype":"venue"
},
  "geometry": {"coordinates":[145.124755859,-37.899181366],"type":"Point"}
}