{
  "type": "Feature",
  "properties": {
    "addr:full":"PO Box 111 Subiaco Private Boxes WA 6904",
    "addr:postcode":"6904",
    "iso:country":"AU",
    "sg:address":"PO Box 111",
    "sg:city":"Subiaco Private Boxes",
    "sg:classifiers":[
        {
            "category":"Professional",
            "subcategory":"Management & Consulting",
            "type":"Services"
        }
    ],
    "sg:phone":"+61 8 9382 3595",
    "sg:postcode":"6904",
    "sg:province":"WA",
    "sg:tags":[
        "consultant"
    ],
    "wof:name":"Peters Management Services",
    "wof:placetype":"venue"
},
  "geometry": {"coordinates":[115.829773,-31.943567],"type":"Point"}
}