{
  "type": "Feature",
  "properties": {
    "iso:country":"AU",
    "sg:address":"Cnr Rose & Nihil Sts",
    "sg:city":"Alexandra",
    "sg:classifiers":[
        {
            "category":"Travel",
            "subcategory":"Hotels & Motels",
            "type":"Entertainment"
        }
    ],
    "sg:phone":"+61 3 5772 1777",
    "sg:postcode":"3714",
    "sg:province":"VIC",
    "wof:name":"Alexandra Redgate Motel",
    "wof:placetype":"venue"
},
  "geometry": {"coordinates":[145.71107482900001,-37.1933822632],"type":"Point"}
}