{
  "type": "Feature",
  "properties": {
    "addr:full":"36 Scotland St Bundaberg QLD 4670",
    "addr:housenumber":"36",
    "addr:postcode":"4670",
    "addr:street":"Scotland St",
    "iso:country":"AU",
    "sg:address":"36 Scotland St",
    "sg:city":"Bundaberg",
    "sg:classifiers":[
        {
            "category":"Building & Trades",
            "subcategory":"Plumbing",
            "type":"Services"
        }
    ],
    "sg:phone":"+61 7 4152 4757",
    "sg:postcode":"4670",
    "sg:province":"QLD",
    "sg:tags":[
        "pump",
        "repairer"
    ],
    "wof:name":"Archies Pool Centre",
    "wof:placetype":"venue"
},
  "geometry": {"coordinates":[152.36651611299999,-24.8617458344],"type":"Point"}
}