{
  "type": "Feature",
  "properties": {
    "addr:full":"62 John St Camden NSW 2570",
    "addr:housenumber":"62",
    "addr:postcode":"2570",
    "addr:street":"John St",
    "iso:country":"AU",
    "sg:address":"62 John St",
    "sg:city":"Camden",
    "sg:classifiers":[
        {
            "category":"Retail",
            "subcategory":"Funeral Services",
            "type":"Services"
        }
    ],
    "sg:phone":"+61 2 4655 4871",
    "sg:postcode":"2570",
    "sg:province":"NSW",
    "sg:tags":[
        "director"
    ],
    "wof:name":"Southern Cross Funeral Directors",
    "wof:placetype":"venue"
},
  "geometry": {"coordinates":[150.696075439,-34.0548210144],"type":"Point"}
}