{
  "type": "Feature",
  "properties": {
    "iso:country":"AU",
    "sg:address":"4 Exceller Ave",
    "sg:city":"Bankstown",
    "sg:classifiers":[
        {
            "category":"Banks & Credit Unions",
            "subcategory":"Investment Brokerage",
            "type":"Services"
        }
    ],
    "sg:phone":"+61 2 9798 1888",
    "sg:postcode":"2200",
    "sg:province":"NSW",
    "sg:tags":[
        "radiator",
        "motor"
    ],
    "wof:name":"A.A.A. Radiator Specialists",
    "wof:placetype":"venue"
},
  "geometry": {"coordinates":[151.03483600000001,-33.933971],"type":"Point"}
}