{
  "type": "Feature",
  "properties": {
    "addr:full":"PO Box 283 West Burleigh QLD 4219",
    "addr:postcode":"4219",
    "iso:country":"AU",
    "sg:address":"PO Box 283",
    "sg:city":"West Burleigh",
    "sg:classifiers":[
        {
            "category":"Building & Trades",
            "subcategory":"Construction",
            "type":"Services"
        }
    ],
    "sg:phone":"+61 7 5522 5255",
    "sg:postcode":"4219",
    "sg:province":"QLD",
    "sg:tags":[
        "tennis court",
        "repair"
    ],
    "wof:name":"Deuce Tennis Court Constructions",
    "wof:placetype":"venue"
},
  "geometry": {"coordinates":[153.44146728499999,-28.112159729],"type":"Point"}
}