{
  "type": "Feature",
  "properties": {
    "iso:country":"AU",
    "sg:address":"65 Concord Drv",
    "sg:city":"Reynella",
    "sg:classifiers":[
        {
            "category":"Social Services",
            "subcategory":"Child Care",
            "type":"Services"
        }
    ],
    "sg:phone":"+61 8 8381 3699",
    "sg:postcode":"5161",
    "sg:province":"SA",
    "wof:name":"Reynella Community Children's Centre Inc.",
    "wof:placetype":"venue"
},
  "geometry": {"coordinates":[138.53463745100001,-35.1003646851],"type":"Point"}
}