{
  "type": "Feature",
  "properties": {
    "iso:country":"AU",
    "sg:address":"PO Box 395",
    "sg:city":"East Maitland",
    "sg:classifiers":[
        {
            "category":"Shopping",
            "subcategory":"Musical Instruments",
            "type":"Retail Goods"
        }
    ],
    "sg:phone":"+61 2 4933 8799",
    "sg:postcode":"2323",
    "sg:province":"NSW",
    "sg:tags":[
        "musician",
        "agent"
    ],
    "wof:name":"Whirlwind Entertainment",
    "wof:placetype":"venue"
},
  "geometry": {"coordinates":[151.58555602999999,-32.753780365],"type":"Point"}
}