{
  "type": "Feature",
  "properties": {
    "addr:full":"25 Fleet St Somerton VIC 3062",
    "addr:housenumber":"25",
    "addr:postcode":"3062",
    "addr:street":"Fleet St",
    "iso:country":"AU",
    "sg:address":"25 Fleet St",
    "sg:city":"Somerton",
    "sg:classifiers":[
        {
            "category":"Professional",
            "type":"Services"
        }
    ],
    "sg:phone":"+61 3 9305 3681",
    "sg:postcode":"3062",
    "sg:province":"VIC",
    "sg:tags":[
        "shop",
        "fitting"
    ],
    "wof:name":"Newsome Ron L",
    "wof:placetype":"venue"
},
  "geometry": {"coordinates":[144.96116638199999,-37.6431694031],"type":"Point"}
}