{
  "type": "Feature",
  "properties": {
    "addr:full":"105 Kyogle St Lismore NSW 2480",
    "addr:housenumber":"105",
    "addr:postcode":"2480",
    "addr:street":"Kyogle St",
    "iso:country":"AU",
    "sg:address":"105 Kyogle St",
    "sg:city":"Lismore",
    "sg:classifiers":[
        {
            "category":"Professional",
            "subcategory":"Art Services",
            "type":"Services"
        }
    ],
    "sg:phone":"+61 2 6622 2363",
    "sg:postcode":"2480",
    "sg:province":"NSW",
    "sg:tags":[
        "decorator",
        "painter"
    ],
    "wof:name":"Jim Whipps Painting",
    "wof:placetype":"venue"
},
  "geometry": {"coordinates":[153.259765625,-28.8096046448],"type":"Point"}
}