{
  "type": "Feature",
  "properties": {
    "iso:country":"AU",
    "sg:address":"245 Albert St",
    "sg:city":"Brisbane",
    "sg:classifiers":[
        {
            "category":"Health Services",
            "subcategory":"Doctor",
            "type":"Services"
        }
    ],
    "sg:phone":"+61 7 3211 2992",
    "sg:postcode":"4000",
    "sg:province":"QLD",
    "sg:tags":[
        "medical",
        "practitioner"
    ],
    "wof:name":"Adelaide & Albert St CBD 7 Day Medical Centre",
    "wof:placetype":"venue"
},
  "geometry": {"coordinates":[153.0259552,-27.4701690674],"type":"Point"}
}