{
  "type": "Feature",
  "properties": {
    "addr:full":"42 Ayr St Doncaster VIC 3108",
    "addr:housenumber":"42",
    "addr:postcode":"3108",
    "addr:street":"Ayr St",
    "iso:country":"AU",
    "sg:address":"42 Ayr St",
    "sg:city":"Doncaster",
    "sg:classifiers":[
        {
            "category":"Food & Beverages",
            "subcategory":"Groceries & Convenience Stores",
            "type":"Retail Goods"
        }
    ],
    "sg:phone":"+61 3 9857 7606",
    "sg:postcode":"3108",
    "sg:province":"VIC",
    "wof:name":"Shen W K",
    "wof:placetype":"venue"
},
  "geometry": {"coordinates":[145.103149414,-37.7836875916],"type":"Point"}
}