{
  "type": "Feature",
  "properties": {
    "iso:country":"AU",
    "sg:address":"5 Arnold St",
    "sg:city":"Blackwater",
    "sg:classifiers":[
        {
            "category":"Fast Food",
            "type":"Food & Drink"
        }
    ],
    "sg:phone":"+61 7 4982 5400",
    "sg:postcode":"4717",
    "sg:province":"QLD",
    "sg:tags":[
        "away",
        "take"
    ],
    "wof:name":"Sail-In Takeaway",
    "wof:placetype":"venue"
},
  "geometry": {"coordinates":[148.879364,-23.582615],"type":"Point"}
}