{
  "type": "Feature",
  "properties": {
    "addr:full":"Unit 2 5 Mallard Way Cannington WA 6107",
    "addr:housenumber":"5",
    "addr:postcode":"6107",
    "addr:street":"Mallard Way",
    "iso:country":"AU",
    "sg:address":"Unit 2 5 Mallard Way",
    "sg:city":"Cannington",
    "sg:classifiers":[
        {
            "category":"Building & Trades",
            "subcategory":"Construction",
            "type":"Services"
        }
    ],
    "sg:phone":"+61 8 9358 0651",
    "sg:postcode":"6107",
    "sg:province":"WA",
    "sg:tags":[
        "home",
        "air conditioning"
    ],
    "wof:name":"Quality Air Conditioning & Heating",
    "wof:placetype":"venue"
},
  "geometry": {"coordinates":[115.928833008,-32.0128860474],"type":"Point"}
}