{
  "type": "Feature",
  "properties": {
    "iso:country":"AU",
    "sg:address":"Cnr Bourke & Erskine Sts",
    "sg:city":"Dubbo",
    "sg:classifiers":[
        {
            "category":"Autos & Motor Vehicles",
            "subcategory":"Automobile Sales",
            "type":"Retail Goods"
        }
    ],
    "sg:phone":"+61 2 6882 3422",
    "sg:postcode":"2830",
    "sg:province":"NSW",
    "sg:tags":[
        "equipment",
        "trailer"
    ],
    "wof:name":"Mathews Motorcycles & Marine",
    "wof:placetype":"venue"
},
  "geometry": {"coordinates":[148.60171508799999,-32.2427177429],"type":"Point"}
}