{
  "type": "Feature",
  "properties": {
    "addr:full":"19 Watergardens Town Cntr, 339 Melton Hwy Taylors Lakes VIC 3038",
    "addr:housenumber":"19;339",
    "addr:postcode":"3038",
    "addr:street":"Watergardens Town Cntr;Melton Hwy",
    "iso:country":"AU",
    "sg:address":"19 Watergardens Town Cntr, 339 Melton Hwy",
    "sg:city":"Taylors Lakes",
    "sg:classifiers":[
        {
            "category":"Shopping",
            "subcategory":"Jewelry",
            "type":"Retail Goods"
        }
    ],
    "sg:phone":"+61 3 9449 0151",
    "sg:postcode":"3038",
    "sg:province":"VIC",
    "sg:tags":[
        "jeweller"
    ],
    "wof:name":"Prouds The Jewellers",
    "wof:placetype":"venue"
},
  "geometry": {"coordinates":[144.78483600000001,-37.698368],"type":"Point"}
}