{
  "type": "Feature",
  "properties": {
    "addr:full":"Shop 4, 169- 179 Meadows Rd Mt Pritchard NSW 2170",
    "addr:housenumber":"shop 4",
    "addr:postcode":"169;2170",
    "addr:street":"179 Meadows Rd;Pritchard",
    "iso:country":"AU",
    "sg:address":"Shop 4, 169- 179 Meadows Rd",
    "sg:city":"Mt Pritchard",
    "sg:classifiers":[
        {
            "category":"Restaurant",
            "type":"Food & Drink"
        }
    ],
    "sg:phone":"+61 2 9826 0488",
    "sg:postcode":"2170",
    "sg:province":"NSW",
    "sg:tags":[
        "pizza"
    ],
    "wof:name":"Domino's Pizza",
    "wof:placetype":"venue"
},
  "geometry": {"coordinates":[150.89907836899999,-33.9000244141],"type":"Point"}
}