{
  "type": "Feature",
  "properties": {
    "addr:full":"682 Malvern Rd Prahran East VIC 3181",
    "addr:housenumber":"682",
    "addr:postcode":"3181",
    "addr:street":"Malvern Rd",
    "iso:country":"AU",
    "sg:address":"682 Malvern Rd",
    "sg:city":"Prahran East",
    "sg:classifiers":[
        {
            "category":"Retail",
            "subcategory":"Veterinary Services",
            "type":"Services"
        }
    ],
    "sg:phone":"+61 3 9510 1335",
    "sg:postcode":"3181",
    "sg:province":"VIC",
    "sg:tags":[
        "surgeon"
    ],
    "wof:name":"Heslop Jennie",
    "wof:placetype":"venue"
},
  "geometry": {"coordinates":[145.00946044899999,-37.8489952087],"type":"Point"}
}