{
  "type": "Feature",
  "properties": {
    "iso:country":"AU",
    "sg:address":"2/34- 36 Wingecarribee St",
    "sg:city":"Bowral",
    "sg:classifiers":[
        {
            "category":"Professional",
            "subcategory":"Business Services",
            "type":"Services"
        }
    ],
    "sg:phone":"+61 2 4862 2199",
    "sg:postcode":"2576",
    "sg:province":"NSW",
    "sg:tags":[
        "drafting"
    ],
    "wof:name":"Bloor Plans",
    "wof:placetype":"venue"
},
  "geometry": {"coordinates":[150.41891479500001,-34.4787864685],"type":"Point"}
}