{
  "type": "Feature",
  "properties": {
    "addr:full":"Gateway Clinic 12 Mellar Crt Midland WA 6056",
    "addr:housenumber":"12",
    "addr:postcode":"6056",
    "addr:street":"Mellar Crt",
    "iso:country":"AU",
    "sg:address":"Gateway Clinic 12 Mellar Crt",
    "sg:city":"Midland",
    "sg:classifiers":[
        {
            "category":"Health Services",
            "subcategory":"Health Practitioner",
            "type":"Services"
        }
    ],
    "sg:phone":"+61 8 9274 3375",
    "sg:postcode":"6056",
    "sg:province":"WA",
    "sg:tags":[
        "psychologist"
    ],
    "wof:name":"Christman Bill",
    "wof:placetype":"venue"
},
  "geometry": {"coordinates":[116.01374054,-31.8876113892],"type":"Point"}
}