{
  "type": "Feature",
  "properties": {
    "addr:full":"108 Minnie St Southport QLD 4215",
    "addr:housenumber":"108",
    "addr:postcode":"4215",
    "addr:street":"Minnie St",
    "iso:country":"AU",
    "sg:address":"108 Minnie St",
    "sg:city":"Southport",
    "sg:classifiers":[
        {
            "category":"Retail",
            "subcategory":"Auto Repair",
            "type":"Services"
        }
    ],
    "sg:phone":"+61 7 5527 1811",
    "sg:postcode":"4215",
    "sg:province":"QLD",
    "sg:tags":[
        "beater",
        "painter",
        "panel"
    ],
    "wof:name":"Bodyworks The",
    "wof:placetype":"venue"
},
  "geometry": {"coordinates":[153.40069580100001,-27.974981308],"type":"Point"}
}