{
  "type": "Feature",
  "properties": {
    "addr:full":"441 Raymond St Sale VIC 3850",
    "addr:housenumber":"441",
    "addr:postcode":"3850",
    "addr:street":"Raymond St",
    "iso:country":"AU",
    "sg:address":"441 Raymond St",
    "sg:city":"Sale",
    "sg:classifiers":[
        {
            "category":"Professional",
            "subcategory":"Accounting & Tax Preparation",
            "type":"Services"
        }
    ],
    "sg:phone":"+61 3 5143 0041",
    "sg:postcode":"3850",
    "sg:province":"VIC",
    "sg:tags":[
        "consultant",
        "taxation"
    ],
    "wof:name":"Booth Cartledge",
    "wof:placetype":"venue"
},
  "geometry": {"coordinates":[147.0652771,-38.1039848328],"type":"Point"}
}