{
  "type": "Feature",
  "properties": {
    "iso:country":"AU",
    "sg:address":"3 Molloy St",
    "sg:city":"Toowoomba",
    "sg:classifiers":[
        {
            "category":"Wholesale",
            "subcategory":"Machinery & Supplies",
            "type":"Manufacturing & Wholesale Goods"
        }
    ],
    "sg:phone":"+61 7 4634 8177",
    "sg:postcode":"4350",
    "sg:province":"QLD",
    "sg:tags":[
        "agricultural"
    ],
    "wof:name":"C J & G N Strickland",
    "wof:placetype":"venue"
},
  "geometry": {"coordinates":[151.898132,-27.555988],"type":"Point"}
}