{
  "type": "Feature",
  "properties": {
    "addr:full":"17 Fred La Lilyfield NSW 2040",
    "addr:housenumber":"17",
    "addr:postcode":"2040",
    "addr:street":"Fred La",
    "iso:country":"AU",
    "sg:address":"17 Fred La",
    "sg:city":"Lilyfield",
    "sg:classifiers":[
        {
            "category":"Professional",
            "subcategory":"Art Services",
            "type":"Services"
        }
    ],
    "sg:phone":"+61 2 9810 0600",
    "sg:postcode":"2040",
    "sg:province":"NSW",
    "sg:tags":[
        "artist"
    ],
    "wof:name":"Burrows T",
    "wof:placetype":"venue"
},
  "geometry": {"coordinates":[151.16662600000001,-33.866913],"type":"Point"}
}