{
  "type": "Feature",
  "properties": {
    "addr:full":"35a Ararat St Altona North VIC 3025",
    "addr:housenumber":"35a",
    "addr:postcode":"3025",
    "addr:street":"Ararat St",
    "iso:country":"AU",
    "sg:address":"35a Ararat St",
    "sg:city":"Altona North",
    "sg:classifiers":[
        {
            "category":"Building & Trades",
            "subcategory":"Construction",
            "type":"Services"
        }
    ],
    "sg:phone":"+61 3 9399 5800",
    "sg:postcode":"3025",
    "sg:province":"VIC",
    "sg:tags":[
        "contractor"
    ],
    "wof:name":"Circle Constructons",
    "wof:placetype":"venue"
},
  "geometry": {"coordinates":[144.860962,-37.839561],"type":"Point"}
}