{
  "type": "Feature",
  "properties": {
    "addr:full":"13 Sassafras Ave Windang NSW 2528",
    "addr:housenumber":"13",
    "addr:postcode":"2528",
    "addr:street":"Sassafras Ave",
    "iso:country":"AU",
    "sg:address":"13 Sassafras Ave",
    "sg:city":"Windang",
    "sg:classifiers":[
        {
            "category":"Building & Trades",
            "subcategory":"Cleaning & Sanitation",
            "type":"Services"
        }
    ],
    "sg:phone":"+61 2 4296 2927",
    "sg:postcode":"2528",
    "sg:province":"NSW",
    "sg:tags":[
        "industrial",
        "commercial",
        "contractor"
    ],
    "wof:name":"Wollongong Cleaning Service",
    "wof:placetype":"venue"
},
  "geometry": {"coordinates":[150.86854553200001,-34.5285263062],"type":"Point"}
}