{
  "type": "Feature",
  "properties": {
    "addr:full":"4 Watson Ave Rose Park SA 5067",
    "addr:housenumber":"4",
    "addr:postcode":"5067",
    "addr:street":"Watson Ave Rose",
    "iso:country":"AU",
    "sg:address":"4 Watson Ave",
    "sg:city":"Rose Park",
    "sg:classifiers":[
        {
            "category":"Banks & Credit Unions",
            "subcategory":"Financial Services",
            "type":"Services"
        }
    ],
    "sg:phone":"+61 8 8364 1555",
    "sg:postcode":"5067",
    "sg:province":"SA",
    "sg:tags":[
        "planning"
    ],
    "wof:name":"Wealth Logic Pty Ltd",
    "wof:placetype":"venue"
},
  "geometry": {"coordinates":[138.62411499000001,-34.9301185608],"type":"Point"}
}