{
  "type": "Feature",
  "properties": {
    "addr:full":"64 Gowrie St Bentleigh East VIC 3165",
    "addr:housenumber":"64",
    "addr:postcode":"3165",
    "addr:street":"Gowrie St",
    "iso:country":"AU",
    "sg:address":"64 Gowrie St",
    "sg:city":"Bentleigh East",
    "sg:classifiers":[
        {
            "category":"Manufacturing",
            "subcategory":"Aerospace",
            "type":"Manufacturing & Wholesale Goods"
        }
    ],
    "sg:phone":"+61 402 028 635",
    "sg:postcode":"3165",
    "sg:province":"VIC",
    "sg:tags":[
        "equipment",
        "aircraft",
        "maintenance"
    ],
    "wof:name":"Leading Edge Enterprises",
    "wof:placetype":"venue"
},
  "geometry": {"coordinates":[145.082519531,-37.9161453247],"type":"Point"}
}