{
  "type": "Feature",
  "properties": {
    "addr:full":"Shop T5 Essendon Homemaker Hub (Essendon Airport) Dandenong VIC 3175",
    "addr:postcode":"3175",
    "iso:country":"AU",
    "sg:address":"Shop T5 Essendon Homemaker Hub (Essendon Airport)",
    "sg:city":"Dandenong",
    "sg:classifiers":[
        {
            "category":"Retail",
            "subcategory":"Repair Shop",
            "type":"Services"
        }
    ],
    "sg:phone":"+61 3 9937 7555",
    "sg:postcode":"3175",
    "sg:province":"VIC",
    "sg:tags":[
        "cleaner",
        "part",
        "vacuum"
    ],
    "wof:name":"Godfreys",
    "wof:placetype":"venue"
},
  "geometry": {"coordinates":[145.218215942,-37.9853210449],"type":"Point"}
}