{
  "type": "Feature",
  "properties": {
    "addr:full":"Shop T5 Westpac Plaza 60 Margaret St Sydney NSW 2000",
    "addr:housenumber":"60",
    "addr:postcode":"2000",
    "addr:street":"Margaret St",
    "iso:country":"AU",
    "sg:address":"Shop T5 Westpac Plaza 60 Margaret St",
    "sg:city":"Sydney",
    "sg:classifiers":[
        {
            "category":"Cafe",
            "type":"Food & Drink"
        }
    ],
    "sg:phone":"+61 2 9252 9815",
    "sg:postcode":"2000",
    "sg:province":"NSW",
    "wof:name":"Bread Spread",
    "wof:placetype":"venue"
},
  "geometry": {"coordinates":[151.207122803,-33.8651199341],"type":"Point"}
}