{
  "type": "Feature",
  "properties": {
    "iso:country":"AU",
    "sg:address":"70 Muscio Rd",
    "sg:city":"Sancrox",
    "sg:classifiers":[
        {
            "category":"Retail",
            "subcategory":"Driving School",
            "type":"Services"
        }
    ],
    "sg:phone":"+61 2 6585 1760",
    "sg:postcode":"2446",
    "sg:province":"NSW",
    "wof:name":"Safety First Driver Training",
    "wof:placetype":"venue"
},
  "geometry": {"coordinates":[152.77813699999999,-31.454454],"type":"Point"}
}