{
  "type": "Feature",
  "properties": {
    "iso:country":"AU",
    "sg:address":"191- 193 Old Geelong Rd",
    "sg:city":"Hoppers Crossing",
    "sg:classifiers":[
        {
            "category":"Retail",
            "subcategory":"Car Wash",
            "type":"Services"
        }
    ],
    "sg:phone":"+61 3 9974 3011",
    "sg:postcode":"3029",
    "sg:province":"VIC",
    "sg:tags":[
        "truck",
        "cleaning"
    ],
    "wof:name":"Grand Car Wash",
    "wof:placetype":"venue"
},
  "geometry": {"coordinates":[144.712097,-37.877117],"type":"Point"}
}