{
  "type": "Feature",
  "properties": {
    "iso:country":"AU",
    "sg:address":"11 Barnes St",
    "sg:city":"Tamworth",
    "sg:classifiers":[
        {
            "category":"Real Estate",
            "subcategory":"Real Estate Agent",
            "type":"Services"
        }
    ],
    "sg:phone":"+61 2 6762 6600",
    "sg:postcode":"2340",
    "sg:province":"NSW",
    "wof:name":"Haynes Pest Management Pty Ltd",
    "wof:placetype":"venue"
},
  "geometry": {"coordinates":[150.91627502399999,-31.0891456604],"type":"Point"}
}