{
  "type": "Feature",
  "properties": {
    "iso:country":"AU",
    "sg:address":"Level 1/ 12 Brookes St",
    "sg:city":"Bowen Hills",
    "sg:classifiers":[
        {
            "category":"Wholesale",
            "subcategory":"Apparel",
            "type":"Manufacturing & Wholesale Goods"
        }
    ],
    "sg:phone":"+61 7 3216 1771",
    "sg:postcode":"4006",
    "sg:province":"QLD",
    "sg:tags":[
        "wholesaler",
        "mfrs",
        "cap",
        "hat"
    ],
    "sg:website":"http://www.capcit.com.au",
    "wof:name":"Capital City Connections",
    "wof:placetype":"venue"
},
  "geometry": {"coordinates":[153.03521728499999,-27.4488945007],"type":"Point"}
}