{
  "type": "Feature",
  "properties": {
    "addr:full":"Pender Rd Bass VIC 3991",
    "addr:postcode":"3991",
    "addr:street":"Pender Rd",
    "iso:country":"AU",
    "sg:address":"Pender Rd",
    "sg:city":"Bass",
    "sg:classifiers":[
        {
            "category":"Communications",
            "subcategory":"News Services",
            "type":"Services"
        }
    ],
    "sg:phone":"+61 3 5678 2389",
    "sg:postcode":"3991",
    "sg:province":"VIC",
    "sg:tags":[
        "information",
        "tourist",
        "attractions"
    ],
    "wof:name":"Bass Valley Knitting Mill",
    "wof:placetype":"venue"
},
  "geometry": {"coordinates":[145.46809400000001,-38.477722],"type":"Point"}
}