{
  "type": "Feature",
  "properties": {
    "addr:full":"520 Canning Hwy Attadale WA 6156",
    "addr:housenumber":"520",
    "addr:postcode":"6156",
    "addr:street":"Canning Hwy",
    "iso:country":"AU",
    "sg:address":"520 Canning Hwy",
    "sg:city":"Attadale",
    "sg:classifiers":[
        {
            "category":"Health Services",
            "subcategory":"Health Practitioner",
            "type":"Services"
        }
    ],
    "sg:phone":"+61 8 9330 4976",
    "sg:postcode":"6156",
    "sg:province":"WA",
    "sg:tags":[
        "pathologist",
        "speech"
    ],
    "wof:name":"Britten Jennifer",
    "wof:placetype":"venue"
},
  "geometry": {"coordinates":[115.800613,-32.032238],"type":"Point"}
}