{
  "type": "Feature",
  "properties": {
    "iso:country":"AU",
    "sg:address":"31 Lawson St",
    "sg:city":"Penrith",
    "sg:classifiers":[
        {
            "category":"Health Services",
            "subcategory":"Doctor",
            "type":"Services"
        }
    ],
    "sg:phone":"+61 2 4734 6500",
    "sg:postcode":"2740",
    "sg:province":"NSW",
    "sg:tags":[
        "medical",
        "practitioner"
    ],
    "wof:name":"Barratt & Smith Pathology",
    "wof:placetype":"venue"
},
  "geometry": {"coordinates":[150.70004299999999,-33.753262],"type":"Point"}
}