{
  "type": "Feature",
  "properties": {
    "addr:full":"Unit 1, 45 Stanley St Peakhurst NSW 2210",
    "addr:housenumber":"45",
    "addr:postcode":"2210",
    "addr:street":"Stanley St",
    "iso:country":"AU",
    "sg:address":"Unit 1, 45 Stanley St",
    "sg:city":"Peakhurst",
    "sg:classifiers":[
        {
            "category":"Home & Garden",
            "subcategory":"Building Materials",
            "type":"Retail Goods"
        }
    ],
    "sg:phone":"+61 2 9153 5200",
    "sg:postcode":"2210",
    "sg:province":"NSW",
    "sg:tags":[
        "merchant",
        "glass",
        "glazier"
    ],
    "wof:name":"BBS Glass Splashbacks",
    "wof:placetype":"venue"
},
  "geometry": {"coordinates":[151.062241,-33.962986],"type":"Point"}
}