{
  "type": "Feature",
  "properties": {
    "iso:country":"AU",
    "sg:address":"Virginia Park Level 1 / 2 -236 262 North Drive Eas",
    "sg:city":"Bentleigh",
    "sg:classifiers":[
        {
            "category":"Professional",
            "subcategory":"Employment Agencies",
            "type":"Services"
        }
    ],
    "sg:phone":"+61 3 9575 9000",
    "sg:postcode":"3204",
    "sg:province":"VIC",
    "sg:tags":[
        "provider",
        "internet"
    ],
    "wof:name":"Redrock Communications",
    "wof:placetype":"venue"
},
  "geometry": {"coordinates":[145.059555,-37.918236],"type":"Point"}
}