{
  "type": "Feature",
  "properties": {
    "addr:full":"Shp 77-78 Westfield Shoppingtown Strathpine QLD 4500",
    "addr:housenumber":"77-78",
    "addr:postcode":"4500",
    "addr:street":"Westfield Shoppingtown",
    "iso:country":"AU",
    "sg:address":"Shp 77-78 Westfield Shoppingtown",
    "sg:city":"Strathpine",
    "sg:classifiers":[
        {
            "category":"Shopping",
            "subcategory":"Clothing, Apparel, & Fashions",
            "type":"Retail Goods"
        }
    ],
    "sg:phone":"+61 7 3205 6134",
    "sg:postcode":"4500",
    "sg:province":"QLD",
    "sg:tags":[
        "jean"
    ],
    "wof:name":"Just Jeans",
    "wof:placetype":"venue"
},
  "geometry": {"coordinates":[153.00437927199999,-27.316368103],"type":"Point"}
}