{
  "type": "Feature",
  "properties": {
    "addr:full":"28 Olympic Ave Cheltenham VIC 3192",
    "addr:housenumber":"28",
    "addr:postcode":"3192",
    "addr:street":"Olympic Ave",
    "iso:country":"AU",
    "sg:address":"28 Olympic Ave",
    "sg:city":"Cheltenham",
    "sg:classifiers":[
        {
            "category":"Education",
            "subcategory":"Kindergarten",
            "type":"Public Place"
        }
    ],
    "sg:phone":"+61 3 9583 6166",
    "sg:postcode":"3192",
    "sg:province":"VIC",
    "sg:tags":[
        "pre-schools"
    ],
    "wof:name":"Olympic Avenue Kindergarten",
    "wof:placetype":"venue"
},
  "geometry": {"coordinates":[145.04649352999999,-37.9619598389],"type":"Point"}
}