{
  "type": "Feature",
  "properties": {
    "addr:full":"16 Pigdon St Carlton North VIC 3054",
    "addr:housenumber":"16",
    "addr:postcode":"3054",
    "addr:street":"Pigdon St",
    "iso:country":"AU",
    "sg:address":"16 Pigdon St",
    "sg:city":"Carlton North",
    "sg:classifiers":[
        {
            "category":"Manufacturing",
            "subcategory":"Food",
            "type":"Manufacturing & Wholesale Goods"
        }
    ],
    "sg:phone":"+61 3 9482 1055",
    "sg:postcode":"3054",
    "sg:province":"VIC",
    "sg:tags":[
        "function",
        "catering"
    ],
    "wof:name":"Something Wicked Cocktails",
    "wof:placetype":"venue"
},
  "geometry": {"coordinates":[144.97731018100001,-37.782459259],"type":"Point"}
}