{
  "type": "Feature",
  "properties": {
    "iso:country":"AU",
    "sg:address":"6 Martin St",
    "sg:city":"Wynyard East",
    "sg:classifiers":[
        {
            "category":"Commercial Area",
            "type":"Public Place"
        }
    ],
    "sg:phone":"+61 3 6442 2422",
    "sg:postcode":"7325",
    "sg:province":"TAS",
    "sg:tags":[
        "heavy",
        "carrier"
    ],
    "wof:name":"Brown L V Carrier",
    "wof:placetype":"venue"
},
  "geometry": {"coordinates":[145.739746,-40.990803],"type":"Point"}
}