{
  "type": "Feature",
  "properties": {
    "iso:country":"AU",
    "sg:address":"Uni Plaza Shopng Cntr 462-472 West St",
    "sg:city":"Toowoomba",
    "sg:classifiers":[
        {
            "category":"Personal",
            "subcategory":"Beauty Salon",
            "type":"Services"
        }
    ],
    "sg:phone":"+61 7 4630 2758",
    "sg:postcode":"4350",
    "sg:province":"QLD",
    "sg:tags":[
        "hairdresser"
    ],
    "wof:name":"Uni Plaza Hair & Beauty Studio",
    "wof:placetype":"venue"
},
  "geometry": {"coordinates":[151.935196,-27.607407],"type":"Point"}
}