{
  "type": "Feature",
  "properties": {
    "addr:full":"Suite 20, Coulter Crt Launceston TAS 7250",
    "addr:postcode":"7250",
    "addr:street":"Coulter Crt",
    "iso:country":"AU",
    "sg:address":"Suite 20, Coulter Crt",
    "sg:city":"Launceston",
    "sg:classifiers":[
        {
            "category":"Professional",
            "subcategory":"Employment Agencies",
            "type":"Services"
        }
    ],
    "sg:phone":"+61 3 6334 4988",
    "sg:postcode":"7250",
    "sg:province":"TAS",
    "wof:name":"Equity Intowork",
    "wof:placetype":"venue"
},
  "geometry": {"coordinates":[147.13995361299999,-41.4370956421],"type":"Point"}
}