{
  "type": "Feature",
  "properties": {
    "iso:country":"AU",
    "sg:address":"U1/ 14 Holland St",
    "sg:city":"Northgate",
    "sg:classifiers":[
        {
            "category":"Retail",
            "subcategory":"Auto Repair",
            "type":"Services"
        }
    ],
    "sg:phone":"+61 7 3260 7500",
    "sg:postcode":"4013",
    "sg:province":"QLD",
    "sg:tags":[
        "repairer",
        "motor",
        "engineer"
    ],
    "wof:name":"Peugeotech",
    "wof:placetype":"venue"
},
  "geometry": {"coordinates":[153.07095336899999,-27.3938293457],"type":"Point"}
}