{
  "type": "Feature",
  "properties": {
    "addr:full":"27 Campbell Rd St Peters NSW 2044",
    "addr:housenumber":"27",
    "addr:postcode":"2044",
    "addr:street":"Campbell Rd",
    "iso:country":"AU",
    "sg:address":"27 Campbell Rd",
    "sg:city":"St Peters",
    "sg:classifiers":[
        {
            "category":"Manufacturing",
            "subcategory":"Building Materials",
            "type":"Manufacturing & Wholesale Goods"
        }
    ],
    "sg:phone":"+61 2 9666 8333",
    "sg:postcode":"2044",
    "sg:province":"NSW",
    "sg:tags":[
        "stone",
        "product",
        "supply"
    ],
    "wof:name":"Antique Stone",
    "wof:placetype":"venue"
},
  "geometry": {"coordinates":[151.180847,-33.912956],"type":"Point"}
}