{
  "type": "Feature",
  "properties": {
    "addr:full":"173 Miles St Winston QLD 4825",
    "addr:housenumber":"173",
    "addr:postcode":"4825",
    "addr:street":"Miles St",
    "iso:country":"AU",
    "sg:address":"173 Miles St",
    "sg:city":"Winston",
    "sg:classifiers":[
        {
            "category":"Professional",
            "subcategory":"Accounting & Tax Preparation",
            "type":"Services"
        }
    ],
    "sg:phone":"+61 7 4749 4659",
    "sg:postcode":"4825",
    "sg:province":"QLD",
    "sg:tags":[
        "bookkeeping"
    ],
    "wof:name":"Kwikbooks Book Keeping Services",
    "wof:placetype":"venue"
},
  "geometry": {"coordinates":[139.49603300000001,-20.70997],"type":"Point"}
}