{
  "type": "Feature",
  "properties": {
    "addr:full":"57 Hall St Bondi Beach NSW 2026",
    "addr:housenumber":"57",
    "addr:postcode":"2026",
    "addr:street":"Hall St",
    "iso:country":"AU",
    "sg:address":"57 Hall St",
    "sg:city":"Bondi Beach",
    "sg:classifiers":[
        {
            "category":"Banks & Credit Unions",
            "subcategory":"Investment Brokerage",
            "type":"Services"
        }
    ],
    "sg:phone":"+61 2 9130 2720",
    "sg:postcode":"2026",
    "sg:province":"NSW",
    "sg:tags":[
        "finance",
        "broker"
    ],
    "wof:name":"A G P Finance",
    "wof:placetype":"venue"
},
  "geometry": {"coordinates":[151.272506714,-33.8901367188],"type":"Point"}
}