{
  "type": "Feature",
  "properties": {
    "iso:country":"AU",
    "sg:address":"Rowney Rd",
    "sg:city":"Mundulla West",
    "sg:classifiers":[
        {
            "category":"Food & Beverages",
            "subcategory":"Fruits & Vegetables",
            "type":"Retail Goods"
        }
    ],
    "sg:phone":"+61 8 8758 6223",
    "sg:postcode":"5270",
    "sg:province":"SA",
    "sg:tags":[
        "grower"
    ],
    "wof:name":"Ciampa Produce Pty Ltd",
    "wof:placetype":"venue"
},
  "geometry": {"coordinates":[140.615326,-36.362896],"type":"Point"}
}