{
  "type": "Feature",
  "properties": {
    "addr:full":"6 Victor Drv Valley View SA 5093",
    "addr:housenumber":"6",
    "addr:postcode":"5093",
    "addr:street":"Victor Drv",
    "iso:country":"AU",
    "sg:address":"6 Victor Drv",
    "sg:city":"Valley View",
    "sg:classifiers":[
        {
            "category":"Building & Trades",
            "subcategory":"Landscaping Services",
            "type":"Services"
        }
    ],
    "sg:phone":"+61 8 8396 0881",
    "sg:postcode":"5093",
    "sg:province":"SA",
    "sg:tags":[
        "designer",
        "landscape",
        "contractor"
    ],
    "wof:name":"Down Under Diggers",
    "wof:placetype":"venue"
},
  "geometry": {"coordinates":[138.647384644,-34.8399467468],"type":"Point"}
}