{
  "type": "Feature",
  "properties": {
    "addr:full":"Suite 19/71- 77 Penshurst St Willoughby NSW 2068",
    "addr:housenumber":"19 / 71 77",
    "addr:postcode":"2068",
    "addr:street":"Penshurst St",
    "iso:country":"AU",
    "sg:address":"Suite 19/71- 77 Penshurst St",
    "sg:city":"Willoughby",
    "sg:classifiers":[
        {
            "category":"Professional",
            "subcategory":"Accounting & Tax Preparation",
            "type":"Services"
        }
    ],
    "sg:phone":"+61 2 9967 5044",
    "sg:postcode":"2068",
    "sg:province":"NSW",
    "sg:tags":[
        "accountant",
        "auditor"
    ],
    "wof:name":"Currie Partners Pty Ltd",
    "wof:placetype":"venue"
},
  "geometry": {"coordinates":[151.198852539,-33.8008270264],"type":"Point"}
}