{
  "type": "Feature",
  "properties": {
    "iso:country":"AU",
    "sg:address":"10 Heswall Crt",
    "sg:city":"Wantirna",
    "sg:classifiers":[
        {
            "category":"Professional",
            "subcategory":"Art Services",
            "type":"Services"
        }
    ],
    "sg:phone":"+61 3 9801 3290",
    "sg:postcode":"3152",
    "sg:province":"VIC",
    "sg:tags":[
        "decorator",
        "painter"
    ],
    "wof:name":"Battista Giovanni",
    "wof:placetype":"venue"
},
  "geometry": {"coordinates":[145.228027344,-37.8516731262],"type":"Point"}
}