{
  "type": "Feature",
  "properties": {
    "iso:country":"AU",
    "sg:address":"208 Pinnacle Drv",
    "sg:city":"Rasmussen",
    "sg:classifiers":[
        {
            "category":"Professional",
            "subcategory":"Employment Agencies",
            "type":"Services"
        }
    ],
    "sg:phone":"+61 7 4773 4270",
    "sg:postcode":"4815",
    "sg:province":"QLD",
    "sg:tags":[
        "occupational",
        "therapist"
    ],
    "wof:name":"Kathryn Purse",
    "wof:placetype":"venue"
},
  "geometry": {"coordinates":[146.726471,-19.343979],"type":"Point"}
}