{
  "type": "Feature",
  "properties": {
    "iso:country":"AU",
    "sg:address":"17 Lampton Ave",
    "sg:city":"Derwent Park",
    "sg:classifiers":[
        {
            "category":"Home & Garden",
            "subcategory":"Carpets & Floor Coverings",
            "type":"Retail Goods"
        }
    ],
    "sg:phone":"+61 3 6272 0088",
    "sg:postcode":"7009",
    "sg:province":"TAS",
    "sg:tags":[
        "double",
        "window",
        "glazed"
    ],
    "wof:name":"Architectural Windows",
    "wof:placetype":"venue"
},
  "geometry": {"coordinates":[147.290771484,-42.835483551],"type":"Point"}
}