{
  "type": "Feature",
  "properties": {
    "addr:full":"78 Charles St Roma QLD 4455",
    "addr:housenumber":"78",
    "addr:postcode":"4455",
    "addr:street":"Charles St",
    "iso:country":"AU",
    "sg:address":"78 Charles St",
    "sg:city":"Roma",
    "sg:classifiers":[
        {
            "category":"Retail",
            "subcategory":"Auto Repair",
            "type":"Services"
        }
    ],
    "sg:phone":"+61 7 4622 5445",
    "sg:postcode":"4455",
    "sg:province":"QLD",
    "sg:tags":[
        "recapping",
        "repairing",
        "retreading",
        "tyre"
    ],
    "wof:name":"Roma Tyre & Battery Service Pty. Ltd.",
    "wof:placetype":"venue"
},
  "geometry": {"coordinates":[148.79208374000001,-26.5737380981],"type":"Point"}
}