{
  "type": "Feature",
  "properties": {
    "iso:country":"AU",
    "sg:address":"46 Bokissa Drv",
    "sg:city":"Frankston",
    "sg:classifiers":[
        {
            "category":"Building & Trades",
            "subcategory":"Construction",
            "type":"Services"
        }
    ],
    "sg:phone":"+61 3 9783 2217",
    "sg:postcode":"3199",
    "sg:province":"VIC",
    "sg:tags":[
        "welding"
    ],
    "wof:name":"KA Welding",
    "wof:placetype":"venue"
},
  "geometry": {"coordinates":[145.14991760300001,-38.1360092163],"type":"Point"}
}