{
  "type": "Feature",
  "properties": {
    "iso:country":"AU",
    "sg:address":"Bourbah St",
    "sg:city":"Gulargambone",
    "sg:classifiers":[
        {
            "category":"Autos & Motor Vehicles",
            "subcategory":"Fuel & Gas Station",
            "type":"Retail Goods"
        }
    ],
    "sg:phone":"+61 2 6825 1104",
    "sg:postcode":"2828",
    "sg:province":"NSW",
    "wof:name":"Gular Motors",
    "wof:placetype":"venue"
},
  "geometry": {"coordinates":[148.47352600100001,-31.3302230835],"type":"Point"}
}