{
  "type": "Feature",
  "properties": {
    "iso:country":"AU",
    "sg:address":"162 Sheridan St",
    "sg:city":"Gundagai",
    "sg:classifiers":[
        {
            "category":"Personal",
            "subcategory":"Beauty Salon",
            "type":"Services"
        }
    ],
    "sg:phone":"+61 2 6944 1656",
    "sg:postcode":"2722",
    "sg:province":"NSW",
    "sg:tags":[
        "hairdresser"
    ],
    "wof:name":"Gundagai Hair Design",
    "wof:placetype":"venue"
},
  "geometry": {"coordinates":[148.10438500000001,-35.064095],"type":"Point"}
}