{
  "type": "Feature",
  "properties": {
    "addr:full":"Shop 6 & 7, 361 Wanneroo Rd Balcatta WA 6021",
    "addr:housenumber":"shop 6 & 7 361",
    "addr:postcode":"6021",
    "addr:street":"Wanneroo Rd",
    "iso:country":"AU",
    "sg:address":"Shop 6 & 7, 361 Wanneroo Rd",
    "sg:city":"Balcatta",
    "sg:classifiers":[
        {
            "category":"Restaurant",
            "type":"Food & Drink"
        }
    ],
    "sg:phone":"+61 8 9461 7377",
    "sg:postcode":"6021",
    "sg:province":"WA",
    "sg:tags":[
        "pizza"
    ],
    "wof:name":"Domino's Pizza",
    "wof:placetype":"venue"
},
  "geometry": {"coordinates":[115.832107544,-31.8750705719],"type":"Point"}
}