{
  "type": "Feature",
  "properties": {
    "iso:country":"AU",
    "sg:address":"Ste304/ 4 Buckingham St",
    "sg:city":"Surry Hills",
    "sg:classifiers":[
        {
            "category":"Organizations",
            "subcategory":"Professional Association",
            "type":"Services"
        }
    ],
    "sg:phone":"+61 2 9690 1414",
    "sg:postcode":"2010",
    "sg:province":"NSW",
    "sg:tags":[
        "web",
        "internet"
    ],
    "wof:name":"Boom Interactive Pty Ltd",
    "wof:placetype":"venue"
},
  "geometry": {"coordinates":[151.20777893100001,-33.8866348267],"type":"Point"}
}