{
  "type": "Feature",
  "properties": {
    "addr:full":"6/ 35 John St Elwood VIC 3184",
    "addr:housenumber":"/ 35",
    "addr:postcode":"3184",
    "addr:street":"John St",
    "iso:country":"AU",
    "sg:address":"6/ 35 John St",
    "sg:city":"Elwood",
    "sg:classifiers":[
        {
            "category":"Organizations",
            "subcategory":"Professional Association",
            "type":"Services"
        }
    ],
    "sg:phone":"+61 403 194 303",
    "sg:postcode":"3184",
    "sg:province":"VIC",
    "sg:tags":[
        "web",
        "internet"
    ],
    "wof:name":"The Rigney Group",
    "wof:placetype":"venue"
},
  "geometry": {"coordinates":[144.98733520499999,-37.8792648315],"type":"Point"}
}