{
  "type": "Feature",
  "properties": {
    "addr:full":"4 Powell St Osborne Park WA 6017",
    "addr:housenumber":"4",
    "addr:postcode":"6017",
    "addr:street":"Powell St",
    "iso:country":"AU",
    "sg:address":"4 Powell St",
    "sg:city":"Osborne Park",
    "sg:phone":"+61 8 9443 8311",
    "sg:postcode":"6017",
    "sg:province":"WA",
    "wof:name":"Glass Workx (WA)",
    "wof:placetype":"venue"
},
  "geometry": {"coordinates":[115.82704925500001,-31.9104957581],"type":"Point"}
}