{
  "type": "Feature",
  "properties": {
    "addr:full":"47 Ballartyre St Thornbury VIC 3071",
    "addr:housenumber":"47",
    "addr:postcode":"3071",
    "addr:street":"Ballartyre St",
    "iso:country":"AU",
    "sg:address":"47 Ballartyre St",
    "sg:city":"Thornbury",
    "sg:classifiers":[
        {
            "category":"Arts & Performance",
            "subcategory":"Music",
            "type":"Entertainment"
        }
    ],
    "sg:phone":"+61 3 9416 7733",
    "sg:postcode":"3071",
    "sg:province":"VIC",
    "sg:tags":[
        "mobile",
        "jockey",
        "disc"
    ],
    "wof:name":"Peppers Parties",
    "wof:placetype":"venue"
},
  "geometry": {"coordinates":[144.996994019,-37.7583580017],"type":"Point"}
}