{
  "type": "Feature",
  "properties": {
    "addr:full":"83 Smart Rd Modbury SA 5092",
    "addr:housenumber":"83",
    "addr:postcode":"5092",
    "addr:street":"Smart Rd",
    "iso:country":"AU",
    "sg:address":"83 Smart Rd",
    "sg:city":"Modbury",
    "sg:classifiers":[
        {
            "category":"Health Services",
            "subcategory":"Doctor",
            "type":"Services"
        }
    ],
    "sg:phone":"+61 8 8265 5355",
    "sg:postcode":"5092",
    "sg:province":"SA",
    "sg:tags":[
        "medical",
        "practitioner"
    ],
    "wof:name":"Herzberg Zenon",
    "wof:placetype":"venue"
},
  "geometry": {"coordinates":[138.69265747099999,-34.8332862854],"type":"Point"}
}