{
  "type": "Feature",
  "properties": {
    "iso:country":"AU",
    "sg:address":"88 Cunningham St",
    "sg:city":"Northcote",
    "sg:classifiers":[
        {
            "category":"Health Services",
            "subcategory":"Nursing And Care Facility",
            "type":"Services"
        }
    ],
    "sg:phone":"+61 3 9489 3022",
    "sg:postcode":"3070",
    "sg:province":"VIC",
    "sg:tags":[
        "home"
    ],
    "wof:name":"Lonsdale House Private Nursing Home",
    "wof:placetype":"venue"
},
  "geometry": {"coordinates":[145.000687,-37.782719],"type":"Point"}
}