{
  "type": "Feature",
  "properties": {
    "iso:country":"AU",
    "sg:address":"250 Beatty Rd",
    "sg:city":"Archerfield",
    "sg:classifiers":[
        {
            "category":"Industrial Area",
            "type":"Public Place"
        }
    ],
    "sg:phone":"+61 1300 656 636",
    "sg:postcode":"4108",
    "sg:province":"QLD",
    "sg:tags":[
        "protective",
        "clothing"
    ],
    "wof:name":"RS Components Pty Limited",
    "wof:placetype":"venue"
},
  "geometry": {"coordinates":[153.01527404800001,-27.5671310425],"type":"Point"}
}