{
  "type": "Feature",
  "properties": {
    "addr:full":"Shop 11 43 Maple St Maleny QLD 4552",
    "addr:housenumber":"shop 11 43",
    "addr:postcode":"4552",
    "addr:street":"Maple St",
    "iso:country":"AU",
    "sg:address":"Shop 11 43 Maple St",
    "sg:city":"Maleny",
    "sg:classifiers":[
        {
            "category":"Deli",
            "type":"Food & Drink"
        }
    ],
    "sg:phone":"+61 7 5494 2670",
    "sg:postcode":"4552",
    "sg:province":"QLD",
    "sg:tags":[
        "delicatessen"
    ],
    "wof:name":"Monicaz",
    "wof:placetype":"venue"
},
  "geometry": {"coordinates":[152.849975586,-26.7583713531],"type":"Point"}
}