{
  "type": "Feature",
  "properties": {
    "iso:country":"AU",
    "sg:address":"PO Box 75",
    "sg:city":"Drayton North",
    "sg:classifiers":[
        {
            "category":"Professional",
            "subcategory":"Detective & Security Services",
            "type":"Services"
        }
    ],
    "sg:phone":"+61 7 4633 5476",
    "sg:postcode":"4350",
    "sg:province":"QLD",
    "sg:tags":[
        "guard",
        "patrol"
    ],
    "wof:name":"Garden City Security Service",
    "wof:placetype":"venue"
},
  "geometry": {"coordinates":[151.915955,-27.589491],"type":"Point"}
}