{
  "type": "Feature",
  "properties": {
    "addr:full":"5 Bass Hwy Wynyard East TAS 7325",
    "addr:housenumber":"5",
    "addr:postcode":"7325",
    "addr:street":"Bass Hwy Wynyard East",
    "iso:country":"AU",
    "sg:address":"5 Bass Hwy",
    "sg:city":"Wynyard East",
    "sg:classifiers":[
        {
            "category":"Freight",
            "type":"Transportation"
        }
    ],
    "sg:phone":"+61 3 6442 2738",
    "sg:postcode":"7325",
    "sg:province":"TAS",
    "sg:tags":[
        "light",
        "carrier"
    ],
    "wof:name":"Brown C W",
    "wof:placetype":"venue"
},
  "geometry": {"coordinates":[145.71293600000001,-41.002995],"type":"Point"}
}