{
  "type": "Feature",
  "properties": {
    "addr:full":"Unit 5/ 377 Scarborough Beach Rd Innaloo WA 6018",
    "addr:housenumber":"/ 377",
    "addr:postcode":"6018",
    "addr:street":"Scarborough Beach Rd",
    "iso:country":"AU",
    "sg:address":"Unit 5/ 377 Scarborough Beach Rd",
    "sg:city":"Innaloo",
    "sg:classifiers":[
        {
            "category":"Shopping",
            "subcategory":"Bicycles & Sporting Goods",
            "type":"Retail Goods"
        }
    ],
    "sg:phone":"+61 8 9445 9255",
    "sg:postcode":"6018",
    "sg:province":"WA",
    "sg:tags":[
        "chemical",
        "equipment",
        "pool",
        "swimming"
    ],
    "wof:name":"Oceanside Pools & Spas",
    "wof:placetype":"venue"
},
  "geometry": {"coordinates":[115.796897888,-31.9024868011],"type":"Point"}
}