{
  "type": "Feature",
  "properties": {
    "iso:country":"AU",
    "sg:address":"PO Box 2437",
    "sg:city":"Richmond",
    "sg:classifiers":[
        {
            "category":"Professional",
            "subcategory":"Accounting & Tax Preparation",
            "type":"Services"
        }
    ],
    "sg:phone":"+61 421 792 171",
    "sg:postcode":"3121",
    "sg:province":"VIC",
    "sg:tags":[
        "bookkeeping"
    ],
    "wof:name":"Counting the Pennies Bookkeeping Services",
    "wof:placetype":"venue"
},
  "geometry": {"coordinates":[144.99945068400001,-37.8170204163],"type":"Point"}
}