{
  "type": "Feature",
  "properties": {
    "addr:full":"109 Gladstone Rd Highgate Hill QLD 4101",
    "addr:housenumber":"109",
    "addr:postcode":"4101",
    "addr:street":"Gladstone Rd",
    "iso:country":"AU",
    "sg:address":"109 Gladstone Rd",
    "sg:city":"Highgate Hill",
    "sg:classifiers":[
        {
            "category":"Health Services",
            "subcategory":"Health Practitioner",
            "type":"Services"
        }
    ],
    "sg:phone":"+61 7 3846 2598",
    "sg:postcode":"4101",
    "sg:province":"QLD",
    "sg:tags":[
        "physiotherapist"
    ],
    "wof:name":"Hewett Scott",
    "wof:placetype":"venue"
},
  "geometry": {"coordinates":[153.01846313499999,-27.4893054962],"type":"Point"}
}