{
  "type": "Feature",
  "properties": {
    "iso:country":"AU",
    "sg:address":"9 Champion Drv",
    "sg:city":"Armadale",
    "sg:classifiers":[
        {
            "category":"Retail",
            "subcategory":"Auto Repair",
            "type":"Services"
        }
    ],
    "sg:phone":"+61 8 9497 1768",
    "sg:postcode":"6112",
    "sg:province":"WA",
    "sg:tags":[
        "repairer",
        "motor",
        "engineer"
    ],
    "wof:name":"Kelmscott Engine Reconditioner",
    "wof:placetype":"venue"
},
  "geometry": {"coordinates":[115.994369507,-32.1245803833],"type":"Point"}
}