{
  "type": "Feature",
  "properties": {
    "iso:country":"AU",
    "sg:address":"Lot 2 Kemp Rd",
    "sg:city":"Pemberton",
    "sg:classifiers":[
        {
            "category":"Farming",
            "subcategory":"Vineyard",
            "type":"Manufacturing & Wholesale Goods"
        }
    ],
    "sg:phone":"+61 8 9776 0225",
    "sg:postcode":"6260",
    "sg:province":"WA",
    "sg:tags":[
        "winery"
    ],
    "wof:name":"Woodsmoke Wines & Cafe",
    "wof:placetype":"venue"
},
  "geometry": {"coordinates":[116.032592773,-34.4310531616],"type":"Point"}
}