{
  "type": "Feature",
  "properties": {
    "addr:full":"26 Reserve Rd Slacks Creek QLD 4127",
    "addr:housenumber":"26",
    "addr:postcode":"4127",
    "addr:street":"Reserve Rd",
    "iso:country":"AU",
    "sg:address":"26 Reserve Rd",
    "sg:city":"Slacks Creek",
    "sg:classifiers":[
        {
            "category":"Professional",
            "type":"Services"
        }
    ],
    "sg:phone":"+61 418 199 375",
    "sg:postcode":"4127",
    "sg:province":"QLD",
    "sg:tags":[
        "transport"
    ],
    "wof:name":"A J & D Crane Trucks Pty Ltd",
    "wof:placetype":"venue"
},
  "geometry": {"coordinates":[153.12130737300001,-27.6320858002],"type":"Point"}
}