{
  "type": "Feature",
  "properties": {
    "iso:country":"AU",
    "sg:address":"59 River St",
    "sg:city":"Maclean",
    "sg:classifiers":[
        {
            "category":"Retail",
            "subcategory":"Funeral Services",
            "type":"Services"
        }
    ],
    "sg:phone":"+61 2 6645 2699",
    "sg:postcode":"2463",
    "sg:province":"NSW",
    "sg:tags":[
        "director"
    ],
    "wof:name":"John Baker Funerals",
    "wof:placetype":"venue"
},
  "geometry": {"coordinates":[153.203216553,-29.4475345612],"type":"Point"}
}