{
  "type": "Feature",
  "properties": {
    "addr:full":"315 Punt Rd Richmond VIC 3121",
    "addr:housenumber":"315",
    "addr:postcode":"3121",
    "addr:street":"Punt Rd",
    "iso:country":"AU",
    "sg:address":"315 Punt Rd",
    "sg:city":"Richmond",
    "sg:classifiers":[
        {
            "category":"Professional",
            "subcategory":"Employment Agencies",
            "type":"Services"
        }
    ],
    "sg:phone":"+61 3 9428 5530",
    "sg:postcode":"3121",
    "sg:province":"VIC",
    "sg:tags":[
        "provider",
        "internet"
    ],
    "wof:name":"Moniker",
    "wof:placetype":"venue"
},
  "geometry": {"coordinates":[144.989379883,-37.82239151],"type":"Point"}
}