{
  "type": "Feature",
  "properties": {
    "iso:country":"AU",
    "sg:address":"4/ 6 Vesper Dr",
    "sg:city":"Narre Warren",
    "sg:classifiers":[
        {
            "category":"Building & Trades",
            "subcategory":"Construction",
            "type":"Services"
        }
    ],
    "sg:phone":"+61 3 8790 6999",
    "sg:postcode":"3805",
    "sg:province":"VIC",
    "sg:tags":[
        "industrial",
        "commercial",
        "air conditioning"
    ],
    "wof:name":"Brenair Mechanical Services",
    "wof:placetype":"venue"
},
  "geometry": {"coordinates":[145.296494,-38.020283],"type":"Point"}
}