{
  "type": "Feature",
  "properties": {
    "addr:full":"7 Towradgi Rd Towradgi NSW 2518",
    "addr:housenumber":"7",
    "addr:postcode":"2518",
    "addr:street":"Towradgi Rd",
    "iso:country":"AU",
    "sg:address":"7 Towradgi Rd",
    "sg:city":"Towradgi",
    "sg:classifiers":[
        {
            "category":"Building & Trades",
            "subcategory":"Construction",
            "type":"Services"
        }
    ],
    "sg:phone":"+61 2 4283 6783",
    "sg:postcode":"2518",
    "sg:province":"NSW",
    "sg:tags":[
        "ceiling"
    ],
    "wof:name":"Stevens Plastering",
    "wof:placetype":"venue"
},
  "geometry": {"coordinates":[150.887878,-34.373028],"type":"Point"}
}