{
  "type": "Feature",
  "properties": {
    "iso:country":"AU",
    "sg:address":"60 North Alice St",
    "sg:city":"Wiley Park",
    "sg:classifiers":[
        {
            "category":"Social Services",
            "subcategory":"Child Care",
            "type":"Services"
        }
    ],
    "sg:phone":"+61 2 9758 1122",
    "sg:postcode":"2195",
    "sg:province":"NSW",
    "wof:name":"Alice St Childcare",
    "wof:placetype":"venue"
},
  "geometry": {"coordinates":[151.072647,-33.925632],"type":"Point"}
}