{
  "type": "Feature",
  "properties": {
    "iso:country":"AU",
    "sg:address":"Shop 8/ 128 Wyong Rd",
    "sg:city":"Killarney Vale",
    "sg:classifiers":[
        {
            "category":"Personal",
            "subcategory":"Beauty Salon",
            "type":"Services"
        }
    ],
    "sg:phone":"+61 2 4333 1100",
    "sg:postcode":"2261",
    "sg:province":"NSW",
    "sg:tags":[
        "hairdresser"
    ],
    "wof:name":"Louise's Hair Studio",
    "wof:placetype":"venue"
},
  "geometry": {"coordinates":[151.462906,-33.366196],"type":"Point"}
}