{
  "type": "Feature",
  "properties": {
    "addr:full":"95 Southern View Drv Albury West NSW 2640",
    "addr:housenumber":"95",
    "addr:postcode":"2640",
    "addr:street":"Southern View Drv",
    "iso:country":"AU",
    "sg:address":"95 Southern View Drv",
    "sg:city":"Albury West",
    "sg:classifiers":[
        {
            "category":"Health Services",
            "subcategory":"Doctor",
            "type":"Services"
        }
    ],
    "sg:phone":"+61 2 6021 3047",
    "sg:postcode":"2640",
    "sg:province":"NSW",
    "sg:tags":[
        "medical",
        "practitioner"
    ],
    "wof:name":"J. Stuchbery",
    "wof:placetype":"venue"
},
  "geometry": {"coordinates":[146.884689331,-36.0751342773],"type":"Point"}
}