{
  "type": "Feature",
  "properties": {
    "addr:full":"21- 23 Broadwood St Kalgoorlie WA 6430",
    "addr:housenumber":"23",
    "addr:postcode":"6430",
    "addr:street":"Broadwood St",
    "iso:country":"AU",
    "sg:address":"21- 23 Broadwood St",
    "sg:city":"Kalgoorlie",
    "sg:classifiers":[
        {
            "category":"Home & Garden",
            "subcategory":"Hardware",
            "type":"Retail Goods"
        }
    ],
    "sg:phone":"+61 13 34 20",
    "sg:postcode":"6430",
    "sg:province":"WA",
    "sg:tags":[
        "generating",
        "set",
        "generator"
    ],
    "wof:name":"Prime Industrial Rental",
    "wof:placetype":"venue"
},
  "geometry": {"coordinates":[121.438438416,-30.7841053009],"type":"Point"}
}