{
  "type": "Feature",
  "properties": {
    "addr:full":"Pinnacles St Wedgefield WA 6724",
    "addr:postcode":"6724",
    "addr:street":"Pinnacles St",
    "iso:country":"AU",
    "sg:address":"Pinnacles St",
    "sg:city":"Wedgefield",
    "sg:classifiers":[
        {
            "category":"Food & Beverages",
            "subcategory":"Bakery",
            "type":"Retail Goods"
        }
    ],
    "sg:phone":"+61 8 9172 1044",
    "sg:postcode":"6724",
    "sg:province":"WA",
    "sg:tags":[
        "baker"
    ],
    "wof:name":"Pilbara Bakeries",
    "wof:placetype":"venue"
},
  "geometry": {"coordinates":[118.592330933,-20.3749542236],"type":"Point"}
}