{
  "type": "Feature",
  "properties": {
    "addr:full":"47 Seventh St (East) Mildura VIC 3500",
    "addr:housenumber":"47",
    "addr:postcode":"3500",
    "addr:street":"Seventh St East",
    "iso:country":"AU",
    "sg:address":"47 Seventh St (East)",
    "sg:city":"Mildura",
    "sg:classifiers":[
        {
            "category":"Home & Garden",
            "subcategory":"Garden Supply",
            "type":"Retail Goods"
        }
    ],
    "sg:phone":"+61 3 5022 7500",
    "sg:postcode":"3500",
    "sg:province":"VIC",
    "sg:tags":[
        "fertilizer"
    ],
    "wof:name":"Muir E E & Sons Pty Ltd",
    "wof:placetype":"venue"
},
  "geometry": {"coordinates":[142.173706055,-34.2033538818],"type":"Point"}
}