{
  "type": "Feature",
  "properties": {
    "iso:country":"AU",
    "sg:address":"41 Bareena Drv",
    "sg:city":"Mt Eliza",
    "sg:classifiers":[
        {
            "category":"Sports & Exercise",
            "subcategory":"Gym",
            "type":"Entertainment"
        }
    ],
    "sg:phone":"+61 419 512 469",
    "sg:postcode":"3930",
    "sg:province":"VIC",
    "sg:tags":[
        "health",
        "fitness"
    ],
    "wof:name":"Pace-Personal Training",
    "wof:placetype":"venue"
},
  "geometry": {"coordinates":[145.10641479500001,-38.1841087341],"type":"Point"}
}