{
  "type": "Feature",
  "properties": {
    "addr:full":"PO Box 147 Annerley DC Annerley QLD 4103",
    "addr:postcode":"4103",
    "iso:country":"AU",
    "sg:address":"PO Box 147 Annerley DC",
    "sg:city":"Annerley",
    "sg:classifiers":[
        {
            "category":"Health Services",
            "subcategory":"Health Practitioner",
            "type":"Services"
        }
    ],
    "sg:phone":"+61 7 3201 2125",
    "sg:postcode":"4103",
    "sg:province":"QLD",
    "sg:tags":[
        "alternative"
    ],
    "wof:name":"Rei-ki Usui Rei-ki Network",
    "wof:placetype":"venue"
},
  "geometry": {"coordinates":[153.032546997,-27.5099563599],"type":"Point"}
}