{
  "type": "Feature",
  "properties": {
    "iso:country":"AU",
    "sg:address":"Durkins Rd",
    "sg:city":"Spreyton",
    "sg:classifiers":[
        {
            "category":"Retail",
            "subcategory":"Veterinary Services",
            "type":"Services"
        }
    ],
    "sg:phone":"+61 3 6424 2495",
    "sg:postcode":"7310",
    "sg:province":"TAS",
    "sg:tags":[
        "surgeon"
    ],
    "wof:name":"Adam S Richardson",
    "wof:placetype":"venue"
},
  "geometry": {"coordinates":[146.34611511200001,-41.206829071],"type":"Point"}
}