{
  "type": "Feature",
  "properties": {
    "iso:country":"AU",
    "sg:address":"9 James Congdon Dr",
    "sg:city":"Mile End",
    "sg:classifiers":[
        {
            "category":"Manufacturing",
            "subcategory":"Buildings",
            "type":"Manufacturing & Wholesale Goods"
        }
    ],
    "sg:phone":"+61 8 8301 8333",
    "sg:postcode":"5031",
    "sg:province":"SA",
    "sg:tags":[
        "transportable",
        "domestic",
        "relocatable"
    ],
    "sg:website":"http://www.sarahhomes.com.au",
    "wof:name":"Sarah Homes",
    "wof:placetype":"venue"
},
  "geometry": {"coordinates":[138.57057189899999,-34.9242782593],"type":"Point"}
}