{
  "type": "Feature",
  "properties": {
    "addr:full":"322 Peel St Tamworth NSW 2340",
    "addr:housenumber":"322",
    "addr:postcode":"2340",
    "addr:street":"Peel St",
    "iso:country":"AU",
    "sg:address":"322 Peel St",
    "sg:city":"Tamworth",
    "sg:classifiers":[
        {
            "category":"Professional",
            "subcategory":"Computer Services",
            "type":"Services"
        }
    ],
    "sg:phone":"+61 2 6761 2324",
    "sg:postcode":"2340",
    "sg:province":"NSW",
    "sg:tags":[
        "consultant",
        "system"
    ],
    "wof:name":"Case Computers",
    "wof:placetype":"venue"
},
  "geometry": {"coordinates":[150.929153442,-31.0896263123],"type":"Point"}
}