{
  "type": "Feature",
  "properties": {
    "addr:full":"Suite 5 97 Lewis Rd Wantirna South VIC 3152",
    "addr:housenumber":"97",
    "addr:postcode":"3152",
    "addr:street":"Lewis Rd",
    "iso:country":"AU",
    "sg:address":"Suite 5 97 Lewis Rd",
    "sg:city":"Wantirna South",
    "sg:classifiers":[
        {
            "category":"Building & Trades",
            "subcategory":"Cleaning & Sanitation",
            "type":"Services"
        }
    ],
    "sg:phone":"+61 3 9887 2488",
    "sg:postcode":"3152",
    "sg:province":"VIC",
    "sg:tags":[
        "tank",
        "septic"
    ],
    "wof:name":"Central Waste Services",
    "wof:placetype":"venue"
},
  "geometry": {"coordinates":[145.25079345699999,-37.8677635193],"type":"Point"}
}