{
  "type": "Feature",
  "properties": {
    "iso:country":"AU",
    "sg:address":"31 Thomas St",
    "sg:city":"Barnsley",
    "sg:classifiers":[
        {
            "category":"Arts & Performance",
            "subcategory":"Music",
            "type":"Entertainment"
        }
    ],
    "sg:phone":"+61 2 4955 2900",
    "sg:postcode":"2278",
    "sg:province":"NSW",
    "sg:tags":[
        "mobile",
        "jockey",
        "disc"
    ],
    "wof:name":"Extreme Mobile Entertainment",
    "wof:placetype":"venue"
},
  "geometry": {"coordinates":[151.593231,-32.929321],"type":"Point"}
}