{
  "type": "Feature",
  "properties": {
    "iso:country":"AU",
    "sg:address":"33 New St",
    "sg:city":"Falmouth",
    "sg:classifiers":[
        {
            "category":"Shopping",
            "subcategory":"Computers & Home Electronics",
            "type":"Retail Goods"
        }
    ],
    "sg:phone":"+61 3 6372 5510",
    "sg:postcode":"7215",
    "sg:province":"TAS",
    "sg:tags":[
        "hi-fi",
        "equipment"
    ],
    "wof:name":"Muse Audio",
    "wof:placetype":"venue"
},
  "geometry": {"coordinates":[148.27282700000001,-41.508423],"type":"Point"}
}