{
  "type": "Feature",
  "properties": {
    "iso:country":"AU",
    "sg:address":"Lot 5/ Pittsburg St",
    "sg:city":"White Rock",
    "sg:classifiers":[
        {
            "category":"Manufacturing",
            "subcategory":"Food",
            "type":"Manufacturing & Wholesale Goods"
        }
    ],
    "sg:phone":"+61 7 4036 3666",
    "sg:postcode":"4868",
    "sg:province":"QLD",
    "sg:tags":[
        "function",
        "catering"
    ],
    "wof:name":"Nice Bite Catering",
    "wof:placetype":"venue"
},
  "geometry": {"coordinates":[145.75213623100001,-16.9900474548],"type":"Point"}
}