{
  "type": "Feature",
  "properties": {
    "iso:country":"AU",
    "sg:address":"Unit 5 23 Regans Rd",
    "sg:city":"Hampton Park",
    "sg:classifiers":[
        {
            "category":"Education",
            "subcategory":"University",
            "type":"Public Place"
        }
    ],
    "sg:phone":"+61 3 9799 3430",
    "sg:postcode":"3976",
    "sg:province":"VIC",
    "sg:tags":[
        "educational",
        "organisation",
        "cultural"
    ],
    "wof:name":"Muslim Women Of Australia",
    "wof:placetype":"venue"
},
  "geometry": {"coordinates":[145.25112915,-38.0335502625],"type":"Point"}
}