{
  "type": "Feature",
  "properties": {
    "addr:full":"PO Box 1402 Wangara WA 6065",
    "addr:postcode":"6065",
    "iso:country":"AU",
    "sg:address":"PO Box 1402",
    "sg:city":"Wangara",
    "sg:classifiers":[
        {
            "category":"Utilities",
            "subcategory":"Refuse",
            "type":"Services"
        }
    ],
    "sg:phone":"+61 407 959 782",
    "sg:postcode":"6065",
    "sg:province":"WA",
    "sg:tags":[
        "remover",
        "rubbish"
    ],
    "wof:name":"Stargate Rubbish Removals",
    "wof:placetype":"venue"
},
  "geometry": {"coordinates":[115.82280731199999,-31.788772583],"type":"Point"}
}