{
  "type": "Feature",
  "properties": {
    "iso:country":"AU",
    "sg:address":"Cnr Laidlaw & Orien Sts",
    "sg:city":"Yass",
    "sg:classifiers":[
        {
            "category":"Utilities",
            "subcategory":"Electric",
            "type":"Services"
        }
    ],
    "sg:phone":"+61 2 6227 6151",
    "sg:postcode":"2582",
    "sg:province":"NSW",
    "sg:tags":[
        "electrical",
        "contractor"
    ],
    "wof:name":"Buzz Electrics Yass Pty Ltd",
    "wof:placetype":"venue"
},
  "geometry": {"coordinates":[148.907012939,-34.8374252319],"type":"Point"}
}