{
  "type": "Feature",
  "properties": {
    "addr:full":"U 1/ 5 Forge Pl Narellan NSW 2567",
    "addr:housenumber":"5",
    "addr:postcode":"2567",
    "addr:street":"Forge Pl",
    "iso:country":"AU",
    "sg:address":"U 1/ 5 Forge Pl",
    "sg:city":"Narellan",
    "sg:classifiers":[
        {
            "category":"Shopping",
            "subcategory":"Crafts & Fabrics",
            "type":"Retail Goods"
        }
    ],
    "sg:phone":"+61 2 4647 0866",
    "sg:postcode":"2567",
    "sg:province":"NSW",
    "sg:tags":[
        "synthetic",
        "canvas",
        "product"
    ],
    "wof:name":"All Trim Macarthur",
    "wof:placetype":"venue"
},
  "geometry": {"coordinates":[150.73178100600001,-34.0376358032],"type":"Point"}
}