{
  "type": "Feature",
  "properties": {
    "iso:country":"AU",
    "sg:address":"12A Racecourse Rd",
    "sg:city":"Rutherford",
    "sg:classifiers":[
        {
            "category":"Retail",
            "subcategory":"Auto Repair",
            "type":"Services"
        }
    ],
    "sg:phone":"+61 2 4932 0063",
    "sg:postcode":"2320",
    "sg:province":"NSW",
    "sg:tags":[
        "body",
        "builder",
        "motor"
    ],
    "wof:name":"Allbars & Traybacks",
    "wof:placetype":"venue"
},
  "geometry": {"coordinates":[151.51564025900001,-32.7126541138],"type":"Point"}
}