{
  "type": "Feature",
  "properties": {
    "iso:country":"AU",
    "sg:address":"Braidwood St",
    "sg:city":"Enfield",
    "sg:classifiers":[
        {
            "category":"Wholesale",
            "subcategory":"Farm Supplies",
            "type":"Manufacturing & Wholesale Goods"
        }
    ],
    "sg:phone":"+61 2 9764 8222",
    "sg:postcode":"2136",
    "sg:province":"NSW",
    "sg:tags":[
        "feed",
        "supplement",
        "stock"
    ],
    "wof:name":"Millmaster Feeds",
    "wof:placetype":"venue"
},
  "geometry": {"coordinates":[151.07078552199999,-33.8863868713],"type":"Point"}
}