{
  "type": "Feature",
  "properties": {
    "addr:full":"4 Arlott St Gracemere QLD 4702",
    "addr:housenumber":"4",
    "addr:postcode":"4702",
    "addr:street":"Arlott St",
    "iso:country":"AU",
    "sg:address":"4 Arlott St",
    "sg:city":"Gracemere",
    "sg:classifiers":[
        {
            "category":"Building & Trades",
            "subcategory":"Cleaning & Sanitation",
            "type":"Services"
        }
    ],
    "sg:phone":"+61 417 515 372",
    "sg:postcode":"4702",
    "sg:province":"QLD",
    "sg:tags":[
        "window"
    ],
    "wof:name":"Clean As Window Cleaning",
    "wof:placetype":"venue"
},
  "geometry": {"coordinates":[150.45770263700001,-23.440738678],"type":"Point"}
}