{
  "type": "Feature",
  "properties": {
    "iso:country":"AU",
    "sg:address":"13 Wattle Crt",
    "sg:city":"Jan Juc",
    "sg:classifiers":[
        {
            "category":"Real Estate",
            "subcategory":"Architect",
            "type":"Services"
        }
    ],
    "sg:phone":"+61 3 5261 6561",
    "sg:postcode":"3228",
    "sg:province":"VIC",
    "wof:name":"Jeremy J Ham",
    "wof:placetype":"venue"
},
  "geometry": {"coordinates":[144.292435,-38.349396],"type":"Point"}
}