{
  "type": "Feature",
  "properties": {
    "iso:country":"AU",
    "sg:address":"536 New South Head Rd",
    "sg:city":"Double Bay",
    "sg:classifiers":[
        {
            "category":"Government",
            "subcategory":"Department Of Motor Vehicles",
            "type":"Public Place"
        }
    ],
    "sg:phone":"+61 2 9391 7000",
    "sg:postcode":"2028",
    "sg:province":"NSW",
    "sg:tags":[
        "organisation",
        "local"
    ],
    "wof:name":"Woollahra Municipal Council",
    "wof:placetype":"venue"
},
  "geometry": {"coordinates":[151.24736023,-33.873008728],"type":"Point"}
}