{
  "type": "Feature",
  "properties": {
    "iso:country":"AU",
    "sg:address":"44 Lakeside Drv",
    "sg:city":"Jabiru",
    "sg:classifiers":[
        {
            "category":"Autos & Motor Vehicles",
            "subcategory":"Fuel & Gas Station",
            "type":"Retail Goods"
        }
    ],
    "sg:phone":"+61 8 8979 2001",
    "sg:postcode":"0886",
    "sg:province":"NT",
    "wof:name":"Mobil Oil Aust Pty Ltd",
    "wof:placetype":"venue"
},
  "geometry": {"coordinates":[132.839264,-12.664223],"type":"Point"}
}