{
  "type": "Feature",
  "properties": {
    "iso:country":"AU",
    "sg:address":"Lot3407 Export Drv",
    "sg:city":"Berrimah",
    "sg:classifiers":[
        {
            "category":"Manufacturing",
            "subcategory":"Glass & Minerals",
            "type":"Manufacturing & Wholesale Goods"
        }
    ],
    "sg:phone":"+61 8 8947 3677",
    "sg:postcode":"0828",
    "sg:province":"NT",
    "sg:tags":[
        "exploration"
    ],
    "wof:name":"Arafura Resources Ni",
    "wof:placetype":"venue"
},
  "geometry": {"coordinates":[130.92274475100001,-12.4695053101],"type":"Point"}
}