{
  "type": "Feature",
  "properties": {
    "iso:country":"AU",
    "sg:address":"Shop 159",
    "sg:city":"Sunshine Plz Maroochydore",
    "sg:classifiers":[
        {
            "category":"Wholesale",
            "subcategory":"Non-durable Goods",
            "type":"Manufacturing & Wholesale Goods"
        }
    ],
    "sg:phone":"+61 7 5452 7993",
    "sg:postcode":"4558",
    "sg:province":"QLD",
    "sg:tags":[
        "wholesaler",
        "craft",
        "mfrs"
    ],
    "wof:name":"Bead Shack The",
    "wof:placetype":"venue"
},
  "geometry": {"coordinates":[153.08071899399999,-26.6554775238],"type":"Point"}
}