{
  "type": "Feature",
  "properties": {
    "addr:full":"Shop 3, Cnr Wilberforce Rd & King St Wilberforce NSW 2756",
    "addr:housenumber":"shop 3",
    "addr:postcode":"2756",
    "addr:street":"Cnr Wilberforce Rd & King St",
    "iso:country":"AU",
    "sg:address":"Shop 3, Cnr Wilberforce Rd & King St",
    "sg:city":"Wilberforce",
    "sg:classifiers":[
        {
            "category":"Structure",
            "subcategory":"Bridge",
            "type":"Public Place"
        }
    ],
    "sg:phone":"+61 2 4575 1533",
    "sg:postcode":"2756",
    "sg:province":"NSW",
    "sg:tags":[
        "chainsaw",
        "brushcutters"
    ],
    "wof:name":"Wilberforce Mowers",
    "wof:placetype":"venue"
},
  "geometry": {"coordinates":[150.838790894,-33.5621528625],"type":"Point"}
}