{
  "type": "Feature",
  "properties": {
    "addr:full":"Level 12 344 Queen St Brisbane QLD 4000",
    "addr:housenumber":"344",
    "addr:postcode":"4000",
    "addr:street":"Queen St",
    "iso:country":"AU",
    "sg:address":"Level 12 344 Queen St",
    "sg:city":"Brisbane",
    "sg:classifiers":[
        {
            "category":"Real Estate",
            "subcategory":"Developer",
            "type":"Services"
        }
    ],
    "sg:phone":"+61 7 3229 8350",
    "sg:postcode":"4000",
    "sg:province":"QLD",
    "sg:tags":[
        "development"
    ],
    "wof:name":"Consolidated Properties Ltd",
    "wof:placetype":"venue"
},
  "geometry": {"coordinates":[153.029006958,-27.4665374756],"type":"Point"}
}