{
  "type": "Feature",
  "properties": {
    "addr:full":"36 Peachey Rd Ormeau QLD 4208",
    "addr:housenumber":"36",
    "addr:postcode":"4208",
    "addr:street":"Peachey Rd",
    "iso:country":"AU",
    "sg:address":"36 Peachey Rd",
    "sg:city":"Ormeau",
    "sg:classifiers":[
        {
            "category":"Mining & Drilling",
            "type":"Manufacturing & Wholesale Goods"
        }
    ],
    "sg:phone":"+61 7 5546 6000",
    "sg:postcode":"4208",
    "sg:province":"QLD",
    "sg:tags":[
        "concrete",
        "breaking",
        "grinding",
        "sawing"
    ],
    "wof:name":"Smith & Osborne (Qld) Pty Ltd",
    "wof:placetype":"venue"
},
  "geometry": {"coordinates":[153.24913024899999,-27.7859249115],"type":"Point"}
}