{
  "type": "Feature",
  "properties": {
    "addr:full":"450 Frome St Moree NSW 2400",
    "addr:housenumber":"450",
    "addr:postcode":"2400",
    "addr:street":"Frome St",
    "iso:country":"AU",
    "sg:address":"450 Frome St",
    "sg:city":"Moree",
    "sg:classifiers":[
        {
            "category":"Autos & Motor Vehicles",
            "subcategory":"Auto Supplies",
            "type":"Retail Goods"
        }
    ],
    "sg:phone":"+61 2 6752 5777",
    "sg:postcode":"2400",
    "sg:province":"NSW",
    "sg:tags":[
        "tyre"
    ],
    "wof:name":"Moree Tyrepower",
    "wof:placetype":"venue"
},
  "geometry": {"coordinates":[149.84161376899999,-29.466211319],"type":"Point"}
}