{
  "type": "Feature",
  "properties": {
    "iso:country":"AU",
    "sg:address":"20 Enterprise Ave",
    "sg:city":"Berwick",
    "sg:classifiers":[
        {
            "category":"Building & Trades",
            "subcategory":"Plumbing",
            "type":"Services"
        }
    ],
    "sg:phone":"+61 3 9707 0341",
    "sg:postcode":"3806",
    "sg:province":"VIC",
    "sg:tags":[
        "tool",
        "air",
        "accessory",
        "supply"
    ],
    "wof:name":"K & R Power Tools Sales & Service",
    "wof:placetype":"venue"
},
  "geometry": {"coordinates":[145.34124755900001,-38.0373954773],"type":"Point"}
}