{
  "type": "Feature",
  "properties": {
    "addr:full":"6 Raphael St Caulfield North VIC 3161",
    "addr:housenumber":"6",
    "addr:postcode":"3161",
    "addr:street":"Raphael St",
    "iso:country":"AU",
    "sg:address":"6 Raphael St",
    "sg:city":"Caulfield North",
    "sg:classifiers":[
        {
            "category":"Manufacturing",
            "subcategory":"Retail Goods",
            "type":"Manufacturing & Wholesale Goods"
        }
    ],
    "sg:phone":"+61 3 9525 9355",
    "sg:postcode":"3161",
    "sg:province":"VIC",
    "sg:tags":[
        "merchant",
        "pump",
        "mfrs"
    ],
    "wof:name":"Metropolitan Pump Shop",
    "wof:placetype":"venue"
},
  "geometry": {"coordinates":[145.01742553700001,-37.8700447083],"type":"Point"}
}