{
  "type": "Feature",
  "properties": {
    "addr:full":"Shop 2 121a Brisbane Rd Mooloolaba QLD 4557",
    "addr:housenumber":"shop 2 121a",
    "addr:postcode":"4557",
    "addr:street":"Brisbane Rd",
    "iso:country":"AU",
    "sg:address":"Shop 2 121a Brisbane Rd",
    "sg:city":"Mooloolaba",
    "sg:classifiers":[
        {
            "category":"Recreation",
            "subcategory":"Fishing",
            "type":"Entertainment"
        }
    ],
    "sg:phone":"+61 408 182 087",
    "sg:postcode":"4557",
    "sg:province":"QLD",
    "sg:tags":[
        "tackle"
    ],
    "wof:name":"Tacklebusters",
    "wof:placetype":"venue"
},
  "geometry": {"coordinates":[153.115356445,-26.6891899109],"type":"Point"}
}