{
  "type": "Feature",
  "properties": {
    "addr:full":"195 Pirie St Adelaide SA 5000",
    "addr:housenumber":"195",
    "addr:postcode":"5000",
    "addr:street":"Pirie St",
    "iso:country":"AU",
    "sg:address":"195 Pirie St",
    "sg:city":"Adelaide",
    "sg:classifiers":[
        {
            "category":"Banks & Credit Unions",
            "subcategory":"Investment Brokerage",
            "type":"Services"
        }
    ],
    "sg:phone":"+61 8 8223 1212",
    "sg:postcode":"5000",
    "sg:province":"SA",
    "sg:tags":[
        "finance",
        "broker"
    ],
    "wof:name":"Delta Finance Pty Ltd",
    "wof:placetype":"venue"
},
  "geometry": {"coordinates":[138.60618591299999,-34.9255752563],"type":"Point"}
}