{
  "type": "Feature",
  "properties": {
    "iso:country":"AU",
    "sg:address":"PO Box 385",
    "sg:city":"Robina",
    "sg:classifiers":[
        {
            "category":"Professional",
            "subcategory":"Detective & Security Services",
            "type":"Services"
        }
    ],
    "sg:phone":"+61 7 5593 2332",
    "sg:postcode":"4226",
    "sg:province":"QLD",
    "sg:tags":[
        "consultant",
        "system"
    ],
    "wof:name":"S.S.S. Security Services",
    "wof:placetype":"venue"
},
  "geometry": {"coordinates":[153.390380859,-28.0680007935],"type":"Point"}
}