{
  "type": "Feature",
  "properties": {
    "addr:full":"106 Pacific Hwy Tuggerah NSW 2259",
    "addr:housenumber":"106",
    "addr:postcode":"2259",
    "addr:street":"Pacific Hwy",
    "iso:country":"AU",
    "sg:address":"106 Pacific Hwy",
    "sg:city":"Tuggerah",
    "sg:classifiers":[
        {
            "category":"Home & Garden",
            "subcategory":"Hardware",
            "type":"Retail Goods"
        }
    ],
    "sg:phone":"+61 2 4352 2136",
    "sg:postcode":"2259",
    "sg:province":"NSW",
    "sg:tags":[
        "generating",
        "set",
        "generator"
    ],
    "wof:name":"Dunlite",
    "wof:placetype":"venue"
},
  "geometry": {"coordinates":[151.42022705100001,-33.3051605225],"type":"Point"}
}