{
  "type": "Feature",
  "properties": {
    "addr:full":"The Parks Community Centre Cowan St Angle Park SA 5010",
    "addr:postcode":"5010",
    "addr:street":"Cowan St",
    "iso:country":"AU",
    "sg:address":"The Parks Community Centre Cowan St",
    "sg:city":"Angle Park",
    "sg:classifiers":[
        {
            "category":"Organizations",
            "subcategory":"Non-profit Organization",
            "type":"Services"
        }
    ],
    "sg:phone":"+61 8 8445 9900",
    "sg:postcode":"5010",
    "sg:province":"SA",
    "sg:tags":[
        "support",
        "disability",
        "organisation"
    ],
    "wof:name":"Individual Supported Accommodation Service Incorporated",
    "wof:placetype":"venue"
},
  "geometry": {"coordinates":[138.56195068400001,-34.8590660095],"type":"Point"}
}