{
  "type": "Feature",
  "properties": {
    "addr:full":"Shop 1, 66 Maple St Maleny QLD 4552",
    "addr:housenumber":"shop;66",
    "addr:postcode":"4552",
    "addr:street":"Maple St",
    "iso:country":"AU",
    "sg:address":"Shop 1, 66 Maple St",
    "sg:city":"Maleny",
    "sg:classifiers":[
        {
            "category":"Shopping",
            "subcategory":"Mobile Phones",
            "type":"Retail Goods"
        }
    ],
    "sg:phone":"+61 7 5429 6311",
    "sg:postcode":"4552",
    "sg:province":"QLD",
    "sg:tags":[
        "telephone",
        "accessory"
    ],
    "wof:name":"One Zero - Maleny",
    "wof:placetype":"venue"
},
  "geometry": {"coordinates":[152.84872436500001,-26.7579441071],"type":"Point"}
}