{
  "type": "Feature",
  "properties": {
    "addr:full":"Princess Hwy Bairnsdale VIC 3875",
    "addr:postcode":"3875",
    "addr:street":"Princess Hwy",
    "iso:country":"AU",
    "sg:address":"Princess Hwy",
    "sg:city":"Bairnsdale",
    "sg:classifiers":[
        {
            "category":"Autos & Motor Vehicles",
            "subcategory":"Fuel & Gas Station",
            "type":"Retail Goods"
        }
    ],
    "sg:phone":"+61 3 5152 3124",
    "sg:postcode":"3875",
    "sg:province":"VIC",
    "wof:name":"BP Australia Limited",
    "wof:placetype":"venue"
},
  "geometry": {"coordinates":[147.61001586899999,-37.8316841125],"type":"Point"}
}