{
  "type": "Feature",
  "properties": {
    "addr:full":"1, 27 Township Drv West Burleigh QLD 4219",
    "addr:housenumber":"27",
    "addr:postcode":"4219",
    "addr:street":"1;Township Drv West",
    "iso:country":"AU",
    "sg:address":"1, 27 Township Drv",
    "sg:city":"West Burleigh",
    "sg:phone":"+61 7 5535 8989",
    "sg:postcode":"4219",
    "sg:province":"QLD",
    "wof:name":"Ezy Tanks",
    "wof:placetype":"venue"
},
  "geometry": {"coordinates":[153.43728637699999,-28.1122989655],"type":"Point"}
}