{
  "type": "Feature",
  "properties": {
    "iso:country":"AU",
    "sg:address":"123-130 Kite St",
    "sg:city":"Orange",
    "sg:classifiers":[
        {
            "category":"Health Services",
            "subcategory":"Health Practitioner",
            "type":"Services"
        }
    ],
    "sg:phone":"+61 2 6366 8498",
    "sg:postcode":"2800",
    "sg:province":"NSW",
    "sg:tags":[
        "pathologist",
        "speech"
    ],
    "wof:name":"Bowler J J",
    "wof:placetype":"venue"
},
  "geometry": {"coordinates":[149.10133361800001,-33.2857971191],"type":"Point"}
}