{
  "type": "Feature",
  "properties": {
    "addr:full":"251 Glenferrie Rd Malvern VIC 3144",
    "addr:housenumber":"251",
    "addr:postcode":"3144",
    "addr:street":"Glenferrie Rd",
    "iso:country":"AU",
    "sg:address":"251 Glenferrie Rd",
    "sg:city":"Malvern",
    "sg:classifiers":[
        {
            "category":"Personal",
            "subcategory":"Beauty Salon",
            "type":"Services"
        }
    ],
    "sg:phone":"+61 3 9500 9859",
    "sg:postcode":"3144",
    "sg:province":"VIC",
    "wof:name":"Allure Skin & Body",
    "wof:placetype":"venue"
},
  "geometry": {"coordinates":[145.02894592300001,-37.8576011658],"type":"Point"}
}