{
  "type": "Feature",
  "properties": {
    "addr:full":"6 Henley Crt Craigieburn VIC 3064",
    "addr:housenumber":"6",
    "addr:postcode":"3064",
    "addr:street":"Henley Crt",
    "iso:country":"AU",
    "sg:address":"6 Henley Crt",
    "sg:city":"Craigieburn",
    "sg:classifiers":[
        {
            "category":"Professional",
            "type":"Services"
        }
    ],
    "sg:phone":"+61 411 117 201",
    "sg:postcode":"3064",
    "sg:province":"VIC",
    "sg:tags":[
        "transport"
    ],
    "wof:name":"Mainframe Transport Pty Ltd",
    "wof:placetype":"venue"
},
  "geometry": {"coordinates":[144.92860412600001,-37.6116981506],"type":"Point"}
}