{
  "type": "Feature",
  "properties": {
    "iso:country":"AU",
    "sg:address":"7 Princess St",
    "sg:city":"Taringa",
    "sg:classifiers":[
        {
            "category":"Shopping",
            "subcategory":"Gifts & Souvenirs",
            "type":"Retail Goods"
        }
    ],
    "sg:phone":"+61 7 3720 8533",
    "sg:postcode":"4068",
    "sg:province":"QLD",
    "sg:tags":[
        "print",
        "poster",
        "pictures"
    ],
    "wof:name":"Townsends Place",
    "wof:placetype":"venue"
},
  "geometry": {"coordinates":[152.98173523,-27.4934692383],"type":"Point"}
}