{
  "type": "Feature",
  "properties": {
    "iso:country":"AU",
    "sg:address":"White Sands Drv",
    "sg:city":"Seaton",
    "sg:classifiers":[
        {
            "category":"Retail",
            "subcategory":"Event Space",
            "type":"Services"
        }
    ],
    "sg:phone":"+61 8 8355 7100",
    "sg:postcode":"5023",
    "sg:province":"SA",
    "sg:tags":[
        "venue",
        "reception",
        "wedding"
    ],
    "wof:name":"Grange Golf Club",
    "wof:placetype":"venue"
},
  "geometry": {"coordinates":[138.50198364299999,-34.8920211792],"type":"Point"}
}