{
  "type": "Feature",
  "properties": {
    "addr:full":"Hunter St Muswellbrook NSW 2333",
    "addr:postcode":"2333",
    "addr:street":"Hunter St",
    "iso:country":"AU",
    "sg:address":"Hunter St",
    "sg:city":"Muswellbrook",
    "sg:classifiers":[
        {
            "category":"Wholesale",
            "subcategory":"Farm Supplies",
            "type":"Manufacturing & Wholesale Goods"
        }
    ],
    "sg:phone":"+61 2 6543 1999",
    "sg:postcode":"2333",
    "sg:province":"NSW",
    "sg:tags":[
        "equipment"
    ],
    "wof:name":"Dairy Farmers Country Stores",
    "wof:placetype":"venue"
},
  "geometry": {"coordinates":[150.89114379899999,-32.2544288635],"type":"Point"}
}