{
  "type": "Feature",
  "properties": {
    "iso:country":"AU",
    "sg:address":"7 Symes Rd",
    "sg:city":"Woori Yallock",
    "sg:classifiers":[
        {
            "category":"Social Services",
            "subcategory":"Child Care",
            "type":"Services"
        }
    ],
    "sg:phone":"+61 3 5961 5955",
    "sg:postcode":"3139",
    "sg:province":"VIC",
    "wof:name":"Woori Yallock Care For Kids",
    "wof:placetype":"venue"
},
  "geometry": {"coordinates":[145.529953003,-37.7775230408],"type":"Point"}
}