{
  "type": "Feature",
  "properties": {
    "iso:country":"AU",
    "sg:address":"11- 15 Waverley Rd",
    "sg:city":"Malvern East",
    "sg:classifiers":[
        {
            "category":"Professional",
            "subcategory":"Business Services",
            "type":"Services"
        }
    ],
    "sg:phone":"+61 3 9571 7566",
    "sg:postcode":"3145",
    "sg:province":"VIC",
    "sg:tags":[
        "broker"
    ],
    "wof:name":"Valentines Licensed Estate & Business Agents",
    "wof:placetype":"venue"
},
  "geometry": {"coordinates":[145.04310607900001,-37.8752212524],"type":"Point"}
}