{
  "type": "Feature",
  "properties": {
    "addr:full":"239 Separation St Northcote VIC 3070",
    "addr:housenumber":"239",
    "addr:postcode":"3070",
    "addr:street":"Separation St",
    "iso:country":"AU",
    "sg:address":"239 Separation St",
    "sg:city":"Northcote",
    "sg:classifiers":[
        {
            "category":"Shopping",
            "subcategory":"Stationery & Office Supplies",
            "type":"Retail Goods"
        }
    ],
    "sg:phone":"+61 3 9489 1000",
    "sg:postcode":"3070",
    "sg:province":"VIC",
    "sg:tags":[
        "equipment",
        "display",
        "exhibition"
    ],
    "wof:name":"Altvisual",
    "wof:placetype":"venue"
},
  "geometry": {"coordinates":[145.01632699999999,-37.77121],"type":"Point"}
}