{
  "type": "Feature",
  "properties": {
    "iso:country":"AU",
    "sg:address":"8b 39 Lawrence Drv",
    "sg:city":"Nerang",
    "sg:classifiers":[
        {
            "category":"Organizations",
            "subcategory":"Professional Association",
            "type":"Services"
        }
    ],
    "sg:phone":"+61 7 5500 4566",
    "sg:postcode":"4211",
    "sg:province":"QLD",
    "sg:tags":[
        "web",
        "internet"
    ],
    "sg:website":"http://www.mantistech.com.au",
    "wof:name":"Mantis Technologies Pty Ltd",
    "wof:placetype":"venue"
},
  "geometry": {"coordinates":[153.34681701700001,-27.997177124],"type":"Point"}
}