{
  "type": "Feature",
  "properties": {
    "iso:country":"AU",
    "sg:address":"509 The Entrance Rd",
    "sg:city":"Shelly Beach",
    "sg:classifiers":[
        {
            "category":"Personal",
            "subcategory":"Beauty Salon",
            "type":"Services"
        }
    ],
    "sg:phone":"+61 2 4333 7166",
    "sg:postcode":"2261",
    "sg:province":"NSW",
    "wof:name":"Krickets Beauty Therapy",
    "wof:placetype":"venue"
},
  "geometry": {"coordinates":[151.47569300000001,-33.367451],"type":"Point"}
}