{
  "type": "Feature",
  "properties": {
    "addr:full":"RMB 1462 Gough's Bay Rd Mansfield VIC 3722",
    "addr:postcode":"3722",
    "addr:street":"Bay Rd",
    "iso:country":"AU",
    "sg:address":"RMB 1462 Gough's Bay Rd",
    "sg:city":"Mansfield",
    "sg:classifiers":[
        {
            "category":"Building & Trades",
            "subcategory":"Plumbing",
            "type":"Services"
        }
    ],
    "sg:phone":"+61 3 5777 3848",
    "sg:postcode":"3722",
    "sg:province":"VIC",
    "sg:tags":[
        "drainers"
    ],
    "wof:name":"Delatite Digger",
    "wof:placetype":"venue"
},
  "geometry": {"coordinates":[146.15074157699999,-37.0491905212],"type":"Point"}
}