{
  "type": "Feature",
  "properties": {
    "iso:country":"AU",
    "sg:address":"Nicholson Rd",
    "sg:city":"(Cnr Armadale Rd) Forrestdale",
    "sg:classifiers":[
        {
            "category":"Deli",
            "type":"Food & Drink"
        }
    ],
    "sg:phone":"+61 8 9397 0060",
    "sg:postcode":"6112",
    "sg:province":"WA",
    "sg:tags":[
        "delicatessen"
    ],
    "wof:name":"Forrestdale Deli & News",
    "wof:placetype":"venue"
},
  "geometry": {"coordinates":[115.925231934,-32.131023407],"type":"Point"}
}