{
  "type": "Feature",
  "properties": {
    "addr:full":"91 Ashmore Rd Bundall QLD 4217",
    "addr:housenumber":"91",
    "addr:postcode":"4217",
    "addr:street":"Ashmore Rd",
    "iso:country":"AU",
    "sg:address":"91 Ashmore Rd",
    "sg:city":"Bundall",
    "sg:classifiers":[
        {
            "category":"Home & Garden",
            "subcategory":"Furniture",
            "type":"Retail Goods"
        }
    ],
    "sg:phone":"+61 7 5539 9001",
    "sg:postcode":"4217",
    "sg:province":"QLD",
    "sg:tags":[
        "outdoor"
    ],
    "wof:name":"Leisure Living Company",
    "wof:placetype":"venue"
},
  "geometry": {"coordinates":[153.40359497099999,-28.0099334717],"type":"Point"}
}