{
  "type": "Feature",
  "properties": {
    "iso:country":"AU",
    "sg:address":"92 Prince St",
    "sg:city":"Annerley",
    "sg:classifiers":[
        {
            "category":"Government",
            "subcategory":"Court House",
            "type":"Public Place"
        }
    ],
    "sg:phone":"+61 7 3392 2706",
    "sg:postcode":"4103",
    "sg:province":"QLD",
    "sg:tags":[
        "personal",
        "marriage",
        "family",
        "counselling"
    ],
    "wof:name":"Anthony Coyne Counselling Services",
    "wof:placetype":"venue"
},
  "geometry": {"coordinates":[153.037384033,-27.5063800812],"type":"Point"}
}