{
  "type": "Feature",
  "properties": {
    "addr:full":"Level 1 103 Miller St North Sydney NSW 2060",
    "addr:housenumber":"103",
    "addr:postcode":"2060",
    "addr:street":"Miller St",
    "iso:country":"AU",
    "sg:address":"Level 1 103 Miller St",
    "sg:city":"North Sydney",
    "sg:classifiers":[
        {
            "category":"Professional",
            "subcategory":"Computer Services",
            "type":"Services"
        }
    ],
    "sg:phone":"+61 2 8273 3201",
    "sg:postcode":"2060",
    "sg:province":"NSW",
    "sg:tags":[
        "tele-communications",
        "consultant"
    ],
    "wof:name":"Cable & Wireless Global Card Services Pty Ltd",
    "wof:placetype":"venue"
},
  "geometry": {"coordinates":[151.206954956,-33.8392028809],"type":"Point"}
}