{
  "type": "Feature",
  "properties": {
    "addr:full":"U5/ 171 Kingsgrove Rd Kingsgrove NSW 2208",
    "addr:housenumber":"171",
    "addr:postcode":"2208",
    "addr:street":"U5 /;Kingsgrove Rd",
    "iso:country":"AU",
    "sg:address":"U5/ 171 Kingsgrove Rd",
    "sg:city":"Kingsgrove",
    "sg:classifiers":[
        {
            "category":"Building & Trades",
            "subcategory":"Plumbing",
            "type":"Services"
        }
    ],
    "sg:phone":"+61 2 9150 0611",
    "sg:postcode":"2208",
    "sg:province":"NSW",
    "sg:tags":[
        "plumber",
        "gasfitters"
    ],
    "wof:name":"Jims Plumbing Services Pty Ltd",
    "wof:placetype":"venue"
},
  "geometry": {"coordinates":[151.09985399999999,-33.93568],"type":"Point"}
}