{
  "type": "Feature",
  "properties": {
    "addr:full":"8 Forest Rd (North) Lara VIC 3212",
    "addr:housenumber":"8",
    "addr:postcode":"3212",
    "addr:street":"Forest Rd North",
    "iso:country":"AU",
    "sg:address":"8 Forest Rd",
    "sg:city":"(North) Lara",
    "sg:classifiers":[
        {
            "category":"Retail",
            "subcategory":"Funeral Services",
            "type":"Services"
        }
    ],
    "sg:phone":"+61 3 5282 1212",
    "sg:postcode":"3212",
    "sg:province":"VIC",
    "sg:tags":[
        "director"
    ],
    "wof:name":"Lara Funeral Services",
    "wof:placetype":"venue"
},
  "geometry": {"coordinates":[144.39614868199999,-38.0231742859],"type":"Point"}
}