{
  "type": "Feature",
  "properties": {
    "iso:country":"AU",
    "sg:address":"11 Dobney Ave",
    "sg:city":"Wagga Wagga",
    "sg:classifiers":[
        {
            "category":"Home & Garden",
            "subcategory":"Building Materials",
            "type":"Retail Goods"
        }
    ],
    "sg:phone":"+61 2 6925 2576",
    "sg:postcode":"2650",
    "sg:province":"NSW",
    "sg:tags":[
        "merchant",
        "glass",
        "glazier"
    ],
    "sg:website":"http://www.waggaglass.com.au",
    "wof:name":"Wagga Glass & Aluminium",
    "wof:placetype":"venue"
},
  "geometry": {"coordinates":[147.348587036,-35.1168823242],"type":"Point"}
}