{
  "type": "Feature",
  "properties": {
    "iso:country":"AU",
    "sg:address":"PO Box 414",
    "sg:city":"Mt Ommaney",
    "sg:classifiers":[
        {
            "category":"Home & Garden",
            "subcategory":"Building Materials",
            "type":"Retail Goods"
        }
    ],
    "sg:phone":"+61 418 740 471",
    "sg:postcode":"4074",
    "sg:province":"QLD",
    "sg:tags":[
        "retaining",
        "wall"
    ],
    "wof:name":"The Retaining Wall Specialists",
    "wof:placetype":"venue"
},
  "geometry": {"coordinates":[152.93179321299999,-27.5443897247],"type":"Point"}
}