{
  "type": "Feature",
  "properties": {
    "iso:country":"AU",
    "sg:address":"13 Rickey St",
    "sg:city":"Capalaba",
    "sg:classifiers":[
        {
            "category":"Real Estate",
            "subcategory":"Real Estate Agent",
            "type":"Services"
        }
    ],
    "sg:phone":"+61 7 3245 5244",
    "sg:postcode":"4157",
    "sg:province":"QLD",
    "wof:name":"Capalaba Agencies Real Estate",
    "wof:placetype":"venue"
},
  "geometry": {"coordinates":[153.19325256400001,-27.5228118896],"type":"Point"}
}