{
  "type": "Feature",
  "properties": {
    "addr:full":"34 Swanton St Chisholm ACT 2905",
    "addr:housenumber":"34",
    "addr:postcode":"2905",
    "addr:street":"Swanton St",
    "iso:country":"AU",
    "sg:address":"34 Swanton St",
    "sg:city":"Chisholm",
    "sg:classifiers":[
        {
            "category":"Building & Trades",
            "subcategory":"Cleaning & Sanitation",
            "type":"Services"
        }
    ],
    "sg:phone":"+61 2 6292 3670",
    "sg:postcode":"2905",
    "sg:province":"ACT",
    "sg:tags":[
        "cleaner",
        "repairer",
        "roof"
    ],
    "wof:name":"Chris Kuglar Roofing",
    "wof:placetype":"venue"
},
  "geometry": {"coordinates":[149.114868164,-35.4234199524],"type":"Point"}
}