{
  "type": "Feature",
  "properties": {
    "iso:country":"AU",
    "sg:address":"PO Box 1665",
    "sg:city":"Aitkenvale",
    "sg:classifiers":[
        {
            "category":"Building & Trades",
            "subcategory":"Construction",
            "type":"Services"
        }
    ],
    "sg:phone":"+61 7 4775 7400",
    "sg:postcode":"4814",
    "sg:province":"QLD",
    "sg:tags":[
        "contractor"
    ],
    "wof:name":"Mybelle Homes Pty Ltd",
    "wof:placetype":"venue"
},
  "geometry": {"coordinates":[146.755417,-19.273424],"type":"Point"}
}