{
  "type": "Feature",
  "properties": {
    "iso:country":"AU",
    "sg:address":"31 Watkins St",
    "sg:city":"Merewether",
    "sg:classifiers":[
        {
            "category":"Professional",
            "subcategory":"Art Services",
            "type":"Services"
        }
    ],
    "sg:phone":"+61 2 4963 6939",
    "sg:postcode":"2291",
    "sg:province":"NSW",
    "sg:tags":[
        "graphic",
        "designer"
    ],
    "wof:name":"Kau Designs",
    "wof:placetype":"venue"
},
  "geometry": {"coordinates":[151.75845336899999,-32.942527771],"type":"Point"}
}