{
  "type": "Feature",
  "properties": {
    "addr:full":"Ste105/ 155 Avoca St Randwick NSW 2031",
    "addr:housenumber":"155",
    "addr:postcode":"2031",
    "addr:street":"Avoca St",
    "iso:country":"AU",
    "sg:address":"Ste105/ 155 Avoca St",
    "sg:city":"Randwick",
    "sg:classifiers":[
        {
            "category":"Building & Trades",
            "subcategory":"Landscaping Services",
            "type":"Services"
        }
    ],
    "sg:phone":"+61 2 9398 9122",
    "sg:postcode":"2031",
    "sg:province":"NSW",
    "sg:tags":[
        "forestry",
        "consultant"
    ],
    "wof:name":"S F M Australasia Pty Ltd",
    "wof:placetype":"venue"
},
  "geometry": {"coordinates":[151.24206543,-33.9136314392],"type":"Point"}
}