{
  "type": "Feature",
  "properties": {
    "addr:full":"U11/ 202 Harbord Rd Brookvale NSW 2100",
    "addr:housenumber":"202",
    "addr:postcode":"2100",
    "addr:street":"/;Harbord Rd",
    "iso:country":"AU",
    "sg:address":"U11/ 202 Harbord Rd",
    "sg:city":"Brookvale",
    "sg:classifiers":[
        {
            "category":"Government",
            "subcategory":"Fire Station",
            "type":"Public Place"
        }
    ],
    "sg:phone":"+61 2 9939 1711",
    "sg:postcode":"2100",
    "sg:province":"NSW",
    "sg:tags":[
        "equipment",
        "protection",
        "consultant"
    ],
    "wof:name":"Austral Fire Protection",
    "wof:placetype":"venue"
},
  "geometry": {"coordinates":[151.27981567399999,-33.7626457214],"type":"Point"}
}