{
  "type": "Feature",
  "properties": {
    "addr:full":"520 George St Granville NSW 2142",
    "addr:housenumber":"520",
    "addr:postcode":"2142",
    "addr:street":"George St",
    "iso:country":"AU",
    "sg:address":"520 George St",
    "sg:city":"Granville",
    "sg:classifiers":[
        {
            "category":"Landmark",
            "subcategory":"Scenic View",
            "type":"Public Place"
        }
    ],
    "sg:phone":"+61 2 9637 7542",
    "sg:postcode":"2142",
    "sg:province":"NSW",
    "sg:tags":[
        "staircase",
        "handrail"
    ],
    "wof:name":"Stairlock International Pty Ltd",
    "wof:placetype":"venue"
},
  "geometry": {"coordinates":[151.01719665499999,-33.833896637],"type":"Point"}
}