{
  "type": "Feature",
  "properties": {
    "addr:full":"6 Susan Crt Seaford VIC 3198",
    "addr:housenumber":"6",
    "addr:postcode":"3198",
    "addr:street":"Susan Crt",
    "iso:country":"AU",
    "sg:address":"6 Susan Crt",
    "sg:city":"Seaford",
    "sg:classifiers":[
        {
            "category":"Professional",
            "subcategory":"Art Services",
            "type":"Services"
        }
    ],
    "sg:phone":"+61 3 8682 8632",
    "sg:postcode":"3198",
    "sg:province":"VIC",
    "wof:name":"Artistart",
    "wof:placetype":"venue"
},
  "geometry": {"coordinates":[145.150634766,-38.1088676453],"type":"Point"}
}