{
  "type": "Feature",
  "properties": {
    "addr:full":"34 Leather St Breakwater VIC 3219",
    "addr:housenumber":"34",
    "addr:postcode":"3219",
    "addr:street":"Leather St",
    "iso:country":"AU",
    "sg:address":"34 Leather St",
    "sg:city":"Breakwater",
    "sg:classifiers":[
        {
            "category":"Building & Trades",
            "subcategory":"Construction",
            "type":"Services"
        }
    ],
    "sg:phone":"+61 3 5221 0493",
    "sg:postcode":"3219",
    "sg:province":"VIC",
    "sg:tags":[
        "scaffolding"
    ],
    "wof:name":"Geelong West Scaffolding",
    "wof:placetype":"venue"
},
  "geometry": {"coordinates":[144.37236023,-38.1859436035],"type":"Point"}
}