{
  "type": "Feature",
  "properties": {
    "addr:full":"7 Elmwood Ave Woodlands WA 6018",
    "addr:housenumber":"7",
    "addr:postcode":"6018",
    "addr:street":"Elmwood Ave",
    "iso:country":"AU",
    "sg:address":"7 Elmwood Ave",
    "sg:city":"Woodlands",
    "sg:classifiers":[
        {
            "category":"Building & Trades",
            "subcategory":"Landscaping Services",
            "type":"Services"
        }
    ],
    "sg:phone":"+61 8 9446 5826",
    "sg:postcode":"6018",
    "sg:province":"WA",
    "sg:tags":[
        "stump",
        "tree",
        "felling",
        "removal"
    ],
    "wof:name":"R & M Franklyn Pty Ltd",
    "wof:placetype":"venue"
},
  "geometry": {"coordinates":[115.78990936300001,-31.9140758514],"type":"Point"}
}