{
  "type": "Feature",
  "properties": {
    "addr:full":"85 Smith Rd Bonogin QLD 4213",
    "addr:housenumber":"85",
    "addr:postcode":"4213",
    "addr:street":"Smith Rd",
    "iso:country":"AU",
    "sg:address":"85 Smith Rd",
    "sg:city":"Bonogin",
    "sg:classifiers":[
        {
            "category":"Government",
            "subcategory":"Department Of Motor Vehicles",
            "type":"Public Place"
        }
    ],
    "sg:phone":"+61 7 5530 5218",
    "sg:postcode":"4213",
    "sg:province":"QLD",
    "sg:tags":[
        "machine",
        "knitting"
    ],
    "wof:name":"Trudy Sehmish",
    "wof:placetype":"venue"
},
  "geometry": {"coordinates":[153.363006592,-28.131319046],"type":"Point"}
}