{
  "type": "Feature",
  "properties": {
    "iso:country":"AU",
    "sg:address":"PO Box 2223",
    "sg:city":"Crestmead",
    "sg:classifiers":[
        {
            "category":"Building & Trades",
            "subcategory":"Construction",
            "type":"Services"
        }
    ],
    "sg:phone":"+61 1800 137 233",
    "sg:postcode":"4132",
    "sg:province":"QLD",
    "sg:tags":[
        "fencing",
        "contractor"
    ],
    "wof:name":"Rent A Fence",
    "wof:placetype":"venue"
},
  "geometry": {"coordinates":[153.10435485799999,-27.6893997192],"type":"Point"}
}