{
  "type": "Feature",
  "properties": {
    "addr:full":"24 Burns St Byron Bay NSW 2481",
    "addr:housenumber":"24",
    "addr:postcode":"2481",
    "addr:street":"Burns St",
    "iso:country":"AU",
    "sg:address":"24 Burns St",
    "sg:city":"Byron Bay",
    "sg:classifiers":[
        {
            "category":"Real Estate",
            "subcategory":"Real Estate Agent",
            "type":"Services"
        }
    ],
    "sg:phone":"+61 2 6685 6051",
    "sg:postcode":"2481",
    "sg:province":"NSW",
    "wof:name":"McCarthy Paul Real Estate",
    "wof:placetype":"venue"
},
  "geometry": {"coordinates":[153.608154297,-28.6450843811],"type":"Point"}
}