{
  "type": "Feature",
  "properties": {
    "addr:full":"76 Catalina Ave Parafield Gardens SA 5107",
    "addr:housenumber":"76",
    "addr:postcode":"5107",
    "addr:street":"Catalina Ave",
    "iso:country":"AU",
    "sg:address":"76 Catalina Ave",
    "sg:city":"Parafield Gardens",
    "sg:classifiers":[
        {
            "category":"Professional",
            "subcategory":"Computer Services",
            "type":"Services"
        }
    ],
    "sg:phone":"+61 8 8250 0509",
    "sg:postcode":"5107",
    "sg:province":"SA",
    "sg:tags":[
        "equipment",
        "networking",
        "installation"
    ],
    "wof:name":"LJF Communications",
    "wof:placetype":"venue"
},
  "geometry": {"coordinates":[138.61009216299999,-34.7861862183],"type":"Point"}
}