{
  "type": "Feature",
  "properties": {
    "addr:full":"18 Alma Rd Hampton Park VIC 3976",
    "addr:housenumber":"18",
    "addr:postcode":"3976",
    "addr:street":"Alma Rd",
    "iso:country":"AU",
    "sg:address":"18 Alma Rd",
    "sg:city":"Hampton Park",
    "sg:classifiers":[
        {
            "category":"Professional",
            "subcategory":"Accounting & Tax Preparation",
            "type":"Services"
        }
    ],
    "sg:phone":"+61 3 9799 1589",
    "sg:postcode":"3976",
    "sg:province":"VIC",
    "sg:tags":[
        "bookkeeping"
    ],
    "wof:name":"Minou Accounting",
    "wof:placetype":"venue"
},
  "geometry": {"coordinates":[145.25471496599999,-38.0288314819],"type":"Point"}
}