{
  "type": "Feature",
  "properties": {
    "iso:country":"AU",
    "sg:address":"527 Station St",
    "sg:city":"Box Hill",
    "sg:classifiers":[
        {
            "category":"Personal",
            "subcategory":"Beauty Salon",
            "type":"Services"
        }
    ],
    "sg:phone":"+61 3 9890 9478",
    "sg:postcode":"3128",
    "sg:province":"VIC",
    "sg:tags":[
        "hairdresser"
    ],
    "wof:name":"Hair Place",
    "wof:placetype":"venue"
},
  "geometry": {"coordinates":[145.123168945,-37.8207168579],"type":"Point"}
}