{
  "type": "Feature",
  "properties": {
    "addr:full":"62 Landsdowne Rd Orchard Hills NSW 2748",
    "addr:housenumber":"62",
    "addr:postcode":"2748",
    "addr:street":"Landsdowne Rd",
    "iso:country":"AU",
    "sg:address":"62 Landsdowne Rd",
    "sg:city":"Orchard Hills",
    "sg:classifiers":[
        {
            "category":"Building & Trades",
            "subcategory":"Cleaning & Sanitation",
            "type":"Services"
        }
    ],
    "sg:phone":"+61 411 198 949",
    "sg:postcode":"2748",
    "sg:province":"NSW",
    "sg:tags":[
        "industrial",
        "commercial",
        "contractor"
    ],
    "wof:name":"ARF Caretaking Building Management",
    "wof:placetype":"venue"
},
  "geometry": {"coordinates":[150.74871826200001,-33.7898826599],"type":"Point"}
}