{
  "type": "Feature",
  "properties": {
    "addr:full":"108 Gradens Rd Tyabb VIC 3913",
    "addr:housenumber":"108",
    "addr:postcode":"3913",
    "addr:street":"Gradens Rd",
    "iso:country":"AU",
    "sg:address":"108 Gradens Rd",
    "sg:city":"Tyabb",
    "sg:classifiers":[
        {
            "category":"Building & Trades",
            "subcategory":"Landscaping Services",
            "type":"Services"
        }
    ],
    "sg:phone":"+61 3 5979 3922",
    "sg:postcode":"3913",
    "sg:province":"VIC",
    "sg:tags":[
        "stump",
        "tree",
        "felling",
        "removal"
    ],
    "wof:name":"Charlie Wright Tree Felling Pty Ltd",
    "wof:placetype":"venue"
},
  "geometry": {"coordinates":[145.14649963400001,-38.2847328186],"type":"Point"}
}