{
  "type": "Feature",
  "properties": {
    "addr:full":"56 Ballina St Lismore NSW 2480",
    "addr:housenumber":"56",
    "addr:postcode":"2480",
    "addr:street":"Ballina St",
    "iso:country":"AU",
    "sg:address":"56 Ballina St",
    "sg:city":"Lismore",
    "sg:classifiers":[
        {
            "category":"Retail",
            "subcategory":"Event Space",
            "type":"Services"
        }
    ],
    "sg:phone":"+61 2 6621 6135",
    "sg:postcode":"2480",
    "sg:province":"NSW",
    "sg:tags":[
        "function",
        "organiser"
    ],
    "wof:name":"Paupiettes",
    "wof:placetype":"venue"
},
  "geometry": {"coordinates":[153.27914428700001,-28.8142547607],"type":"Point"}
}