{
  "type": "Feature",
  "properties": {
    "addr:full":"10 Heath Ave Hepburn Springs VIC 3461",
    "addr:housenumber":"10",
    "addr:postcode":"3461",
    "addr:street":"Heath Ave Hepburn Springs",
    "iso:country":"AU",
    "sg:address":"10 Heath Ave",
    "sg:city":"Hepburn Springs",
    "sg:classifiers":[
        {
            "category":"Building & Trades",
            "subcategory":"Construction",
            "type":"Services"
        }
    ],
    "sg:phone":"+61 408 510 446",
    "sg:postcode":"3461",
    "sg:province":"VIC",
    "sg:tags":[
        "joinery"
    ],
    "wof:name":"Gerard Bugden Joiner",
    "wof:placetype":"venue"
},
  "geometry": {"coordinates":[144.13574218799999,-37.3074874878],"type":"Point"}
}