{
  "type": "Feature",
  "properties": {
    "addr:full":"11 Stanley St Chirnside Park VIC 3116",
    "addr:housenumber":"11",
    "addr:postcode":"3116",
    "addr:street":"Stanley St",
    "iso:country":"AU",
    "sg:address":"11 Stanley St",
    "sg:city":"Chirnside Park",
    "sg:classifiers":[
        {
            "category":"Shopping",
            "subcategory":"Stationery & Office Supplies",
            "type":"Retail Goods"
        }
    ],
    "sg:phone":"+61 3 9727 4759",
    "sg:postcode":"3116",
    "sg:province":"VIC",
    "sg:tags":[
        "packaging",
        "material"
    ],
    "wof:name":"Abreeze Packaging",
    "wof:placetype":"venue"
},
  "geometry": {"coordinates":[145.30189514200001,-37.75157547],"type":"Point"}
}