{
  "type": "Feature",
  "properties": {
    "addr:full":"11 Miller St Essendon VIC 3040",
    "addr:housenumber":"11",
    "addr:postcode":"3040",
    "addr:street":"Miller St",
    "iso:country":"AU",
    "sg:address":"11 Miller St",
    "sg:city":"Essendon",
    "sg:classifiers":[
        {
            "category":"Utilities",
            "subcategory":"Electric",
            "type":"Services"
        }
    ],
    "sg:phone":"+61 3 9337 5903",
    "sg:postcode":"3040",
    "sg:province":"VIC",
    "sg:tags":[
        "electrical",
        "contractor"
    ],
    "wof:name":"Johnstone L A",
    "wof:placetype":"venue"
},
  "geometry": {"coordinates":[144.91273498499999,-37.7541999817],"type":"Point"}
}