{
  "type": "Feature",
  "properties": {
    "addr:full":"Cnr Neale & Hammer Sts Flora Hill VIC 3550",
    "addr:postcode":"3550",
    "addr:street":"Cnr Neale & Hammer Sts Flora Hill",
    "iso:country":"AU",
    "sg:address":"Cnr Neale & Hammer Sts",
    "sg:city":"Flora Hill",
    "sg:classifiers":[
        {
            "category":"Wholesale",
            "subcategory":"Medical Equipment & Supplies",
            "type":"Manufacturing & Wholesale Goods"
        }
    ],
    "sg:phone":"+61 3 5443 3238",
    "sg:postcode":"3550",
    "sg:province":"VIC",
    "sg:tags":[
        "aid",
        "care",
        "health",
        "home"
    ],
    "wof:name":"Vanstan Pharmacy",
    "wof:placetype":"venue"
},
  "geometry": {"coordinates":[144.292114258,-36.7764930725],"type":"Point"}
}