{
  "type": "Feature",
  "properties": {
    "addr:full":"Shop 220 Airport West Shopngtwn, 29 Louis Airport West VIC 3042",
    "addr:housenumber":"220;29",
    "addr:postcode":"3042",
    "addr:street":"Shopngtwn;Louis Airport West",
    "iso:country":"AU",
    "sg:address":"Shop 220 Airport West Shopngtwn, 29",
    "sg:city":"Louis Airport West",
    "sg:classifiers":[
        {
            "category":"Food & Beverages",
            "subcategory":"Bakery",
            "type":"Retail Goods"
        }
    ],
    "sg:phone":"+61 3 9335 6515",
    "sg:postcode":"3042",
    "sg:province":"VIC",
    "sg:tags":[
        "baker"
    ],
    "wof:name":"Muffin Break",
    "wof:placetype":"venue"
},
  "geometry": {"coordinates":[144.887619019,-37.7126998901],"type":"Point"}
}