{
  "type": "Feature",
  "properties": {
    "addr:full":"117 Evans Lookout Rd Blackheath NSW 2785",
    "addr:housenumber":"117",
    "addr:postcode":"2785",
    "addr:street":"Evans Lookout Rd",
    "iso:country":"AU",
    "sg:address":"117 Evans Lookout Rd",
    "sg:city":"Blackheath",
    "sg:classifiers":[
        {
            "category":"Health Services",
            "subcategory":"Doctor",
            "type":"Services"
        }
    ],
    "sg:phone":"+61 2 4782 2385",
    "sg:postcode":"2785",
    "sg:province":"NSW",
    "sg:tags":[
        "holiday",
        "retreat"
    ],
    "wof:name":"Lavender Cottage & Manor",
    "wof:placetype":"venue"
},
  "geometry": {"coordinates":[150.29745483400001,-33.6495819092],"type":"Point"}
}