{
  "type": "Feature",
  "properties": {
    "addr:full":"93 Loralyn Ave St Georges Basin NSW 2540",
    "addr:housenumber":"93",
    "addr:postcode":"2540",
    "addr:street":"Loralyn Ave",
    "iso:country":"AU",
    "sg:address":"93 Loralyn Ave St",
    "sg:city":"Georges Basin",
    "sg:classifiers":[
        {
            "category":"Social Services",
            "subcategory":"Child Care",
            "type":"Services"
        }
    ],
    "sg:phone":"+61 2 4443 8882",
    "sg:postcode":"2540",
    "sg:province":"NSW",
    "wof:name":"Paradise Waters Childcare Centre",
    "wof:placetype":"venue"
},
  "geometry": {"coordinates":[150.60667419399999,-35.0983848572],"type":"Point"}
}