{
  "type": "Feature",
  "properties": {
    "addr:full":"61 Main St Croydon VIC 3136",
    "addr:housenumber":"61",
    "addr:postcode":"3136",
    "addr:street":"Main St",
    "iso:country":"AU",
    "sg:address":"61 Main St",
    "sg:city":"Croydon",
    "sg:classifiers":[
        {
            "category":"Food & Beverages",
            "subcategory":"Bakery",
            "type":"Retail Goods"
        }
    ],
    "sg:phone":"+61 3 9723 1853",
    "sg:postcode":"3136",
    "sg:province":"VIC",
    "sg:tags":[
        "cake",
        "shop",
        "pastry"
    ],
    "wof:name":"Blue Rabbit Cakes",
    "wof:placetype":"venue"
},
  "geometry": {"coordinates":[145.28086852999999,-37.7964172363],"type":"Point"}
}