{
  "type": "Feature",
  "properties": {
    "addr:full":"49 Secomb Ave Parafield Gardens SA 5107",
    "addr:housenumber":"49",
    "addr:postcode":"5107",
    "addr:street":"Secomb Ave",
    "iso:country":"AU",
    "sg:address":"49 Secomb Ave",
    "sg:city":"Parafield Gardens",
    "sg:classifiers":[
        {
            "category":"Retail",
            "subcategory":"Car Wash",
            "type":"Services"
        }
    ],
    "sg:phone":"+61 8 8281 9953",
    "sg:postcode":"5107",
    "sg:province":"SA",
    "sg:tags":[
        "truck",
        "cleaning"
    ],
    "wof:name":"Auto Car Clean",
    "wof:placetype":"venue"
},
  "geometry": {"coordinates":[138.62530517600001,-34.779045105],"type":"Point"}
}