{
  "type": "Feature",
  "properties": {
    "addr:full":"2/ 1968 Hume Hwy Campbellfield VIC 3061",
    "addr:housenumber":"/ 1968",
    "addr:postcode":"3061",
    "addr:street":"Hume Hwy",
    "iso:country":"AU",
    "sg:address":"2/ 1968 Hume Hwy",
    "sg:city":"Campbellfield",
    "sg:classifiers":[
        {
            "category":"Shopping",
            "subcategory":"Discount & Variety Stores",
            "type":"Retail Goods"
        }
    ],
    "sg:phone":"+61 3 9357 8801",
    "sg:postcode":"3061",
    "sg:province":"VIC",
    "sg:tags":[
        "shop",
        "adult"
    ],
    "wof:name":"Sexyland Adult Department Store",
    "wof:placetype":"venue"
},
  "geometry": {"coordinates":[144.95335388199999,-37.6529045105],"type":"Point"}
}