{
  "type": "Feature",
  "properties": {
    "iso:country":"AU",
    "sg:address":"19 Middleton Rd",
    "sg:city":"Cromer",
    "sg:classifiers":[
        {
            "category":"Home & Garden",
            "subcategory":"Building Materials",
            "type":"Retail Goods"
        }
    ],
    "sg:phone":"+61 2 9972 1006",
    "sg:postcode":"2099",
    "sg:province":"NSW",
    "sg:tags":[
        "fencing"
    ],
    "wof:name":"Beyond Balconies",
    "wof:placetype":"venue"
},
  "geometry": {"coordinates":[151.282272339,-33.7347755432],"type":"Point"}
}