{
  "type": "Feature",
  "properties": {
    "addr:full":"11 Frosts Rd Margate TAS 7054",
    "addr:housenumber":"11",
    "addr:postcode":"7054",
    "addr:street":"Frosts Rd",
    "iso:country":"AU",
    "sg:address":"11 Frosts Rd",
    "sg:city":"Margate",
    "sg:classifiers":[
        {
            "category":"Professional",
            "subcategory":"Computer Services",
            "type":"Services"
        }
    ],
    "sg:phone":"+61 3 6267 1444",
    "sg:postcode":"7054",
    "sg:province":"TAS",
    "sg:tags":[
        "repairs",
        "upgrade",
        "equipment"
    ],
    "wof:name":"Taslan Computer Services",
    "wof:placetype":"venue"
},
  "geometry": {"coordinates":[147.26165800000001,-43.027023],"type":"Point"}
}