{
  "type": "Feature",
  "properties": {
    "iso:country":"AU",
    "sg:address":"11 Frosts Rd",
    "sg:city":"Margate",
    "sg:classifiers":[
        {
            "category":"Professional",
            "subcategory":"Computer Services",
            "type":"Services"
        }
    ],
    "sg:phone":"+61 3 6267 1444",
    "sg:postcode":"7054",
    "sg:province":"TAS",
    "sg:tags":[
        "repairs",
        "upgrade",
        "equipment"
    ],
    "wof:name":"Taslan Computer Services",
    "wof:placetype":"venue"
},
  "geometry": {"coordinates":[147.261658,-43.027023],"type":"Point"}
}