{
  "type": "Feature",
  "properties": {
    "iso:country":"AU",
    "sg:address":"361 Goodwood Rd",
    "sg:city":"Westbourne Park",
    "sg:classifiers":[
        {
            "category":"Health Services",
            "subcategory":"Health Practitioner",
            "type":"Services"
        }
    ],
    "sg:phone":"+61 8 8271 3803",
    "sg:postcode":"5041",
    "sg:province":"SA",
    "sg:tags":[
        "physiotherapist"
    ],
    "wof:name":"Pontifex Ned",
    "wof:placetype":"venue"
},
  "geometry": {"coordinates":[138.59108000000001,-34.967896],"type":"Point"}
}