{
  "type": "Feature",
  "properties": {
    "addr:full":"119 Walkerville Tce Walkerville SA 5081",
    "addr:housenumber":"119",
    "addr:postcode":"5081",
    "addr:street":"Walkerville Tce",
    "iso:country":"AU",
    "sg:address":"119 Walkerville Tce",
    "sg:city":"Walkerville",
    "sg:classifiers":[
        {
            "category":"Retail",
            "subcategory":"Event Space",
            "type":"Services"
        }
    ],
    "sg:phone":"+61 8 8344 8311",
    "sg:postcode":"5081",
    "sg:province":"SA",
    "sg:tags":[
        "venue",
        "reception",
        "wedding"
    ],
    "sg:website":"http://www.classicsrestaurant.com.au",
    "wof:name":"Classics Restaurant",
    "wof:placetype":"venue"
},
  "geometry": {"coordinates":[138.617553711,-34.8948974609],"type":"Point"}
}