{
  "type": "Feature",
  "properties": {
    "addr:full":"105 Tusmore Ave Tusmore SA 5065",
    "addr:housenumber":"105",
    "addr:postcode":"5065",
    "addr:street":"Tusmore Ave",
    "iso:country":"AU",
    "sg:address":"105 Tusmore Ave",
    "sg:city":"Tusmore",
    "sg:classifiers":[
        {
            "category":"Manufacturing",
            "subcategory":"Glass & Minerals",
            "type":"Manufacturing & Wholesale Goods"
        }
    ],
    "sg:phone":"+61 8 8304 8201",
    "sg:postcode":"5065",
    "sg:province":"SA",
    "sg:tags":[
        "exploration"
    ],
    "wof:name":"Petratherm Ltd",
    "wof:placetype":"venue"
},
  "geometry": {"coordinates":[138.65191650400001,-34.9385070801],"type":"Point"}
}