{
  "type": "Feature",
  "properties": {
    "iso:country":"AU",
    "sg:address":"1 Frinton St",
    "sg:city":"Southport",
    "sg:classifiers":[
        {
            "category":"Home & Garden",
            "subcategory":"Household Appliances",
            "type":"Retail Goods"
        }
    ],
    "sg:phone":"+61 7 5532 8500",
    "sg:postcode":"4215",
    "sg:province":"QLD",
    "sg:tags":[
        "chemical",
        "equipment",
        "steam",
        "cleaning",
        "pressure"
    ],
    "wof:name":"Rightway Plant Equipment & Truck Hire",
    "wof:placetype":"venue"
},
  "geometry": {"coordinates":[153.388671875,-27.9741954803],"type":"Point"}
}