{
  "type": "Feature",
  "properties": {
    "iso:country":"AU",
    "sg:address":"100 Terminus St",
    "sg:city":"Liverpool",
    "sg:classifiers":[
        {
            "category":"Home & Garden",
            "subcategory":"Carpets & Floor Coverings",
            "type":"Retail Goods"
        }
    ],
    "sg:phone":"+61 2 9602 2244",
    "sg:postcode":"2170",
    "sg:province":"NSW",
    "sg:tags":[
        "tile",
        "wall",
        "layer"
    ],
    "wof:name":"Buildzone",
    "wof:placetype":"venue"
},
  "geometry": {"coordinates":[150.922363281,-33.9265022278],"type":"Point"}
}