{
  "type": "Feature",
  "properties": {
    "addr:full":"6 Warby St Campbelltown NSW 2560",
    "addr:housenumber":"6",
    "addr:postcode":"2560",
    "addr:street":"Warby St",
    "iso:country":"AU",
    "sg:address":"6 Warby St",
    "sg:city":"Campbelltown",
    "sg:classifiers":[
        {
            "category":"Bars & Pubs",
            "subcategory":"Lounge",
            "type":"Food & Drink"
        }
    ],
    "sg:phone":"+61 2 4625 1422",
    "sg:postcode":"2560",
    "sg:province":"NSW",
    "sg:tags":[
        "water",
        "filter",
        "drinking"
    ],
    "wof:name":"Breathe Easy Purification",
    "wof:placetype":"venue"
},
  "geometry": {"coordinates":[150.81976318400001,-34.0612220764],"type":"Point"}
}