{
  "type": "Feature",
  "properties": {
    "addr:full":"PO Box 124 Batchelor NT 0845",
    "addr:postcode":"nt 0845",
    "iso:country":"AU",
    "sg:address":"PO Box 124",
    "sg:city":"Batchelor",
    "sg:classifiers":[
        {
            "category":"Food & Beverages",
            "subcategory":"Groceries & Convenience Stores",
            "type":"Retail Goods"
        }
    ],
    "sg:phone":"+61 8 8978 2861",
    "sg:postcode":"0845",
    "sg:province":"NT",
    "wof:name":"Wangi Kiosk Wangi Falls",
    "wof:placetype":"venue"
},
  "geometry": {"coordinates":[131.10508727999999,-13.0708398819],"type":"Point"}
}