{
  "type": "Feature",
  "properties": {
    "addr:full":"15 Roopena St Ingle Farm SA 5098",
    "addr:housenumber":"15",
    "addr:postcode":"5098",
    "addr:street":"Roopena St",
    "iso:country":"AU",
    "sg:address":"15 Roopena St",
    "sg:city":"Ingle Farm",
    "sg:classifiers":[
        {
            "category":"Health Services",
            "subcategory":"Doctor",
            "type":"Services"
        }
    ],
    "sg:phone":"+61 8 8263 1133",
    "sg:postcode":"5098",
    "sg:province":"SA",
    "sg:tags":[
        "medical",
        "practitioner"
    ],
    "wof:name":"Burrough Tim",
    "wof:placetype":"venue"
},
  "geometry": {"coordinates":[138.65074157699999,-34.8301200867],"type":"Point"}
}