{
  "type": "Feature",
  "properties": {
    "addr:full":"47 Johnston St Dalwallinu WA 6609",
    "addr:housenumber":"47",
    "addr:postcode":"6609",
    "addr:street":"Johnston St",
    "iso:country":"AU",
    "sg:address":"47 Johnston St",
    "sg:city":"Dalwallinu",
    "sg:classifiers":[
        {
            "category":"Food & Beverages",
            "subcategory":"Groceries & Convenience Stores",
            "type":"Retail Goods"
        }
    ],
    "sg:phone":"+61 8 9661 1110",
    "sg:postcode":"6609",
    "sg:province":"WA",
    "wof:name":"R & E General Store",
    "wof:placetype":"venue"
},
  "geometry": {"coordinates":[116.662330627,-30.2765712738],"type":"Point"}
}