{
  "type": "Feature",
  "properties": {
    "addr:full":"223 Rookwood Rd Yagoona NSW 2199",
    "addr:housenumber":"223",
    "addr:postcode":"2199",
    "addr:street":"Rookwood Rd",
    "iso:country":"AU",
    "sg:address":"223 Rookwood Rd",
    "sg:city":"Yagoona",
    "sg:classifiers":[
        {
            "category":"Autos & Motor Vehicles",
            "subcategory":"Auto Supplies",
            "type":"Retail Goods"
        }
    ],
    "sg:phone":"+61 2 9722 6100",
    "sg:postcode":"2199",
    "sg:province":"NSW",
    "sg:tags":[
        "tyre"
    ],
    "wof:name":"Bridgestone Australia Ltd",
    "wof:placetype":"venue"
},
  "geometry": {"coordinates":[151.03767400000001,-33.898327],"type":"Point"}
}