{
  "type": "Feature",
  "properties": {
    "addr:full":"24 Edward St Wagga Wagga NSW 2650",
    "addr:housenumber":"24",
    "addr:postcode":"2650",
    "addr:street":"Edward St",
    "iso:country":"AU",
    "sg:address":"24 Edward St",
    "sg:city":"Wagga Wagga",
    "sg:classifiers":[
        {
            "category":"Retail",
            "subcategory":"Auto Repair",
            "type":"Services"
        }
    ],
    "sg:phone":"+61 2 6921 4865",
    "sg:postcode":"2650",
    "sg:province":"NSW",
    "sg:tags":[
        "muffler",
        "exhaust",
        "system"
    ],
    "wof:name":"The Exhaust Specialists",
    "wof:placetype":"venue"
},
  "geometry": {"coordinates":[147.37635803200001,-35.1199569702],"type":"Point"}
}