{
  "type": "Feature",
  "properties": {
    "iso:country":"AU",
    "sg:address":"12 Queens Ave",
    "sg:city":"Hawthorn",
    "sg:classifiers":[
        {
            "category":"Professional",
            "subcategory":"Computer Services",
            "type":"Services"
        }
    ],
    "sg:phone":"+61 3 9815 0400",
    "sg:postcode":"3122",
    "sg:province":"VIC",
    "sg:tags":[
        "package",
        "software"
    ],
    "wof:name":"Dataccount Computer Pty Ltd",
    "wof:placetype":"venue"
},
  "geometry": {"coordinates":[145.043167114,-37.8229675293],"type":"Point"}
}