{
  "type": "Feature",
  "properties": {
    "addr:full":"568 Oxford St Bondi Junction NSW 2022",
    "addr:housenumber":"568",
    "addr:postcode":"2022",
    "addr:street":"Oxford St",
    "iso:country":"AU",
    "sg:address":"568 Oxford St",
    "sg:city":"Bondi Junction",
    "sg:classifiers":[
        {
            "category":"Shopping",
            "subcategory":"Computers & Home Electronics",
            "type":"Retail Goods"
        }
    ],
    "sg:phone":"+61 2 9386 0422",
    "sg:postcode":"2022",
    "sg:province":"NSW",
    "sg:tags":[
        "hi-fi",
        "equipment"
    ],
    "wof:name":"DME Hi-Fi Sales",
    "wof:placetype":"venue"
},
  "geometry": {"coordinates":[151.25239563,-33.8911857605],"type":"Point"}
}