{
  "type": "Feature",
  "properties": {
    "iso:country":"AU",
    "sg:address":"68 Eulinga Crt",
    "sg:city":"Ninderry",
    "sg:classifiers":[
        {
            "category":"Education",
            "subcategory":"Special Training",
            "type":"Public Place"
        }
    ],
    "sg:phone":"+61 7 5446 7686",
    "sg:postcode":"4561",
    "sg:province":"QLD",
    "sg:tags":[
        "drama",
        "speech",
        "speaking",
        "tuition"
    ],
    "wof:name":"Mary McLaren",
    "wof:placetype":"venue"
},
  "geometry": {"coordinates":[152.97796630900001,-26.53855896],"type":"Point"}
}