{
  "type": "Feature",
  "properties": {
    "addr:full":"Shop 128-129, Brandon Park Shopping Centre, Cnr Fe Mulgrave VIC 3170",
    "addr:housenumber":"128-129",
    "addr:postcode":"3170",
    "addr:street":"Brandon Park;Cnr Fe",
    "iso:country":"AU",
    "sg:address":"Shop 128-129, Brandon Park Shopping Centre, Cnr Fe",
    "sg:city":"Mulgrave",
    "sg:classifiers":[
        {
            "category":"Shopping",
            "subcategory":"Computers & Home Electronics",
            "type":"Retail Goods"
        }
    ],
    "sg:phone":"+61 3 9562 5850",
    "sg:postcode":"3170",
    "sg:province":"VIC",
    "sg:tags":[
        "equipment",
        "part",
        "electronic"
    ],
    "wof:name":"Tandy",
    "wof:placetype":"venue"
},
  "geometry": {"coordinates":[145.169189453,-37.9045143127],"type":"Point"}
}