{
  "type": "Feature",
  "properties": {
    "addr:full":"Unit 3 Mainsport Place Cnr Main Drive and Sportsma Bokarina QLD 4575",
    "addr:postcode":"4575",
    "addr:street":"Place Cnr Main Drive",
    "iso:country":"AU",
    "sg:address":"Unit 3 Mainsport Place Cnr Main Drive and Sportsma",
    "sg:city":"Bokarina",
    "sg:classifiers":[
        {
            "category":"Shopping",
            "subcategory":"Computers & Home Electronics",
            "type":"Retail Goods"
        }
    ],
    "sg:phone":"+61 7 5493 8277",
    "sg:postcode":"4575",
    "sg:province":"QLD",
    "sg:tags":[
        "hardware",
        "equipment"
    ],
    "wof:name":"CCS",
    "wof:placetype":"venue"
},
  "geometry": {"coordinates":[153.128525,-26.730846],"type":"Point"}
}