{
  "type": "Feature",
  "properties": {
    "addr:full":"27 Knox St Double Bay NSW 2028",
    "addr:housenumber":"27",
    "addr:postcode":"2028",
    "addr:street":"Knox St",
    "iso:country":"AU",
    "sg:address":"27 Knox St",
    "sg:city":"Double Bay",
    "sg:classifiers":[
        {
            "category":"Restaurant",
            "type":"Food & Drink"
        }
    ],
    "sg:phone":"+61 2 9327 6696",
    "sg:postcode":"2028",
    "sg:province":"NSW",
    "wof:name":"Dee Bee's Cafe",
    "wof:placetype":"venue"
},
  "geometry": {"coordinates":[151.24250793499999,-33.8767547607],"type":"Point"}
}