{
  "type": "Feature",
  "properties": {
    "addr:full":"Shop C & D 113 Greville St Chatswood NSW 2067",
    "addr:housenumber":"113",
    "addr:postcode":"2067",
    "addr:street":"Greville St",
    "iso:country":"AU",
    "sg:address":"Shop C & D 113 Greville St",
    "sg:city":"Chatswood",
    "sg:classifiers":[
        {
            "category":"Professional",
            "subcategory":"Accounting & Tax Preparation",
            "type":"Services"
        }
    ],
    "sg:phone":"+61 2 9412 4566",
    "sg:postcode":"2067",
    "sg:province":"NSW",
    "sg:tags":[
        "consultant",
        "taxation"
    ],
    "wof:name":"Yeldham Taxation & Business Services Pty Ltd",
    "wof:placetype":"venue"
},
  "geometry": {"coordinates":[151.16921997099999,-33.7934379578],"type":"Point"}
}