{
  "type": "Feature",
  "properties": {
    "iso:country":"AU",
    "sg:address":"210 Pakenham Rd",
    "sg:city":"Pakenham",
    "sg:classifiers":[
        {
            "category":"Home & Garden",
            "subcategory":"Garden Supply",
            "type":"Retail Goods"
        }
    ],
    "sg:phone":"+61 3 5941 3550",
    "sg:postcode":"3810",
    "sg:province":"VIC",
    "sg:tags":[
        "equipment"
    ],
    "wof:name":"Cardinia Sand & Soil",
    "wof:placetype":"venue"
},
  "geometry": {"coordinates":[145.47934000000001,-38.052509],"type":"Point"}
}