{
  "type": "Feature",
  "properties": {
    "addr:full":"Summer St Orange NSW 2800",
    "addr:postcode":"2800",
    "addr:street":"Summer St",
    "iso:country":"AU",
    "sg:address":"Summer St",
    "sg:city":"Orange",
    "sg:classifiers":[
        {
            "category":"Travel",
            "subcategory":"Hotels & Motels",
            "type":"Entertainment"
        }
    ],
    "sg:phone":"+61 2 6362 1855",
    "sg:postcode":"2800",
    "sg:province":"NSW",
    "sg:tags":[
        "accommodation"
    ],
    "wof:name":"Royal Hotel",
    "wof:placetype":"venue"
},
  "geometry": {"coordinates":[149.09507751500001,-33.282875061],"type":"Point"}
}