{
  "type": "Feature",
  "properties": {
    "addr:full":"St James WA 6102",
    "addr:postcode":"6102",
    "iso:country":"AU",
    "sg:address":"St",
    "sg:city":"James",
    "sg:classifiers":[
        {
            "category":"Professional",
            "subcategory":"Engineering",
            "type":"Services"
        }
    ],
    "sg:phone":"+61 429 451 699",
    "sg:postcode":"6102",
    "sg:province":"WA",
    "sg:tags":[
        "engineer",
        "designing"
    ],
    "wof:name":"Trent Engineering",
    "wof:placetype":"venue"
},
  "geometry": {"coordinates":[115.91004180900001,-31.9991893768],"type":"Point"}
}