{
  "type": "Feature",
  "properties": {
    "iso:country":"AU",
    "sg:address":"PO Box 554",
    "sg:city":"Edgecliff",
    "sg:classifiers":[
        {
            "category":"Food & Beverages",
            "subcategory":"Fruits & Vegetables",
            "type":"Retail Goods"
        }
    ],
    "sg:phone":"+61 2 9745 5660",
    "sg:postcode":"2027",
    "sg:province":"NSW",
    "sg:tags":[
        "consultant",
        "catering"
    ],
    "wof:name":"Corporate Caterer",
    "wof:placetype":"venue"
},
  "geometry": {"coordinates":[151.237792969,-33.8803787231],"type":"Point"}
}