{
  "type": "Feature",
  "properties": {
    "addr:full":"6 Loraine Ave Box Hill North VIC 3129",
    "addr:housenumber":"6",
    "addr:postcode":"3129",
    "addr:street":"Loraine Ave",
    "iso:country":"AU",
    "sg:address":"6 Loraine Ave",
    "sg:city":"Box Hill North",
    "sg:classifiers":[
        {
            "category":"Professional",
            "subcategory":"Accounting & Tax Preparation",
            "type":"Services"
        }
    ],
    "sg:phone":"+61 3 9890 7954",
    "sg:postcode":"3129",
    "sg:province":"VIC",
    "sg:tags":[
        "accountant",
        "auditor"
    ],
    "wof:name":"Allen T & J",
    "wof:placetype":"venue"
},
  "geometry": {"coordinates":[145.118484497,-37.8028144836],"type":"Point"}
}