{
  "type": "Feature",
  "properties": {
    "iso:country":"AU",
    "sg:address":"100 Dight St",
    "sg:city":"Collingwood",
    "sg:classifiers":[
        {
            "category":"Bars & Pubs",
            "subcategory":"Biergarten",
            "type":"Food & Drink"
        }
    ],
    "sg:phone":"+61 3 9419 0860",
    "sg:postcode":"3066",
    "sg:province":"VIC",
    "sg:tags":[
        "eucalyptus",
        "oil",
        "tree",
        "essential",
        "tea"
    ],
    "wof:name":"Essential Therapeutics Pty Ltd",
    "wof:placetype":"venue"
},
  "geometry": {"coordinates":[144.98907470699999,-37.7997283936],"type":"Point"}
}