{
  "type": "Feature",
  "properties": {
    "addr:full":"Merri St Warrnambool VIC 3280",
    "addr:postcode":"3280",
    "addr:street":"Merri St",
    "iso:country":"AU",
    "sg:address":"Merri St",
    "sg:city":"Warrnambool",
    "sg:classifiers":[
        {
            "category":"Organizations",
            "subcategory":"Membership Organization",
            "type":"Services"
        }
    ],
    "sg:phone":"+61 3 5561 4277",
    "sg:postcode":"3280",
    "sg:province":"VIC",
    "sg:tags":[
        "railway"
    ],
    "wof:name":"West Coast Railway",
    "wof:placetype":"venue"
},
  "geometry": {"coordinates":[142.48052978499999,-38.3867835999],"type":"Point"}
}