{
  "type": "Feature",
  "properties": {
    "addr:full":"Level 8, St Martin&#039;s Tower, 31 Market St Sydney NSW 2000",
    "addr:housenumber":"31",
    "addr:postcode":"2000",
    "addr:street":"S;Market St",
    "iso:country":"AU",
    "sg:address":"Level 8, St Martin&#039;s Tower, 31 Market St",
    "sg:city":"Sydney",
    "sg:classifiers":[
        {
            "category":"Banks & Credit Unions",
            "subcategory":"Financial Services",
            "type":"Services"
        }
    ],
    "sg:phone":"+61 2 8268 5200",
    "sg:postcode":"2000",
    "sg:province":"NSW",
    "sg:tags":[
        "planning"
    ],
    "wof:name":"Winchcombe Carson Financial Planning Pty Ltd",
    "wof:placetype":"venue"
},
  "geometry": {"coordinates":[151.20591735799999,-33.8709983826],"type":"Point"}
}