{
  "type": "Feature",
  "properties": {
    "iso:country":"AU",
    "sg:address":"249 Joseph St",
    "sg:city":"Ballarat",
    "sg:classifiers":[
        {
            "category":"Shopping",
            "subcategory":"Antiques",
            "type":"Retail Goods"
        }
    ],
    "sg:phone":"+61 3 5333 3604",
    "sg:postcode":"3350",
    "sg:province":"VIC",
    "wof:name":"Superior Secondhand",
    "wof:placetype":"venue"
},
  "geometry": {"coordinates":[143.877914,-37.575027],"type":"Point"}
}