{
  "type": "Feature",
  "properties": {
    "addr:full":"35b Glen Rd Silvan VIC 3795",
    "addr:housenumber":"35b",
    "addr:postcode":"3795",
    "addr:street":"Glen Rd",
    "iso:country":"AU",
    "sg:address":"35b Glen Rd",
    "sg:city":"Silvan",
    "sg:classifiers":[
        {
            "category":"Wholesale",
            "subcategory":"Plants",
            "type":"Manufacturing & Wholesale Goods"
        }
    ],
    "sg:phone":"+61 3 9737 9502",
    "sg:postcode":"3795",
    "sg:province":"VIC",
    "sg:tags":[
        "florist"
    ],
    "wof:name":"Monvale Flowers",
    "wof:placetype":"venue"
},
  "geometry": {"coordinates":[145.43353271500001,-37.829044342],"type":"Point"}
}