{
  "type": "Feature",
  "properties": {
    "addr:full":"Rockdale Plaza, Rockdale Plaza Drv Rockdale NSW 2216",
    "addr:postcode":"2216",
    "addr:street":"Plaza Drv",
    "iso:country":"AU",
    "sg:address":"Rockdale Plaza, Rockdale Plaza Drv",
    "sg:city":"Rockdale",
    "sg:classifiers":[
        {
            "category":"Social Services",
            "subcategory":"Child Care",
            "type":"Services"
        }
    ],
    "sg:phone":"+61 2 9588 9822",
    "sg:postcode":"2216",
    "sg:province":"NSW",
    "wof:name":"Rockdale Occasional Child Care Centre",
    "wof:placetype":"venue"
},
  "geometry": {"coordinates":[151.14561499999999,-33.958714],"type":"Point"}
}