{
  "type": "Feature",
  "properties": {
    "addr:full":"Cnr Leeson Rd & Princes Hwy Traralgon East VIC 3844",
    "addr:postcode":"3844",
    "addr:street":"Leeson Rd & Princes Hwy",
    "iso:country":"AU",
    "sg:address":"Cnr Leeson Rd & Princes Hwy",
    "sg:city":"Traralgon East",
    "sg:classifiers":[
        {
            "category":"School Buses",
            "type":"Transportation"
        }
    ],
    "sg:phone":"+61 3 5174 7800",
    "sg:postcode":"3844",
    "sg:province":"VIC",
    "sg:tags":[
        "brick"
    ],
    "wof:name":"Deerings Buildpro",
    "wof:placetype":"venue"
},
  "geometry": {"coordinates":[146.56132507300001,-38.1906890869],"type":"Point"}
}