{
  "type": "Feature",
  "properties": {
    "addr:full":"23 Hopewell St Paddington NSW 2021",
    "addr:housenumber":"23",
    "addr:postcode":"2021",
    "addr:street":"Hopewell St",
    "iso:country":"AU",
    "sg:address":"23 Hopewell St",
    "sg:city":"Paddington",
    "sg:classifiers":[
        {
            "category":"Health Services",
            "subcategory":"Dentist",
            "type":"Services"
        }
    ],
    "sg:phone":"+61 2 9361 3389",
    "sg:postcode":"2021",
    "sg:province":"NSW",
    "wof:name":"Chan Frank",
    "wof:placetype":"venue"
},
  "geometry": {"coordinates":[151.22232055699999,-33.8824539185],"type":"Point"}
}