{
  "type": "Feature",
  "properties": {
    "addr:full":"Shop LG 82 The Mall Campbelltown NSW 2560",
    "addr:housenumber":"82",
    "addr:postcode":"2560",
    "addr:street":"The Mall",
    "iso:country":"AU",
    "sg:address":"Shop LG 82",
    "sg:city":"The Mall Campbelltown",
    "sg:classifiers":[
        {
            "category":"Food & Beverages",
            "subcategory":"Specialty",
            "type":"Retail Goods"
        }
    ],
    "sg:phone":"+61 2 4628 4699",
    "sg:postcode":"2560",
    "sg:province":"NSW",
    "sg:tags":[
        "product",
        "health"
    ],
    "wof:name":"Go Vita Campbelltown",
    "wof:placetype":"venue"
},
  "geometry": {"coordinates":[150.82493591299999,-34.063167572],"type":"Point"}
}