{
  "type": "Feature",
  "properties": {
    "iso:country":"AU",
    "sg:address":"Copperfield Drv",
    "sg:city":"Ambarvale",
    "sg:classifiers":[
        {
            "category":"Education",
            "subcategory":"School",
            "type":"Public Place"
        }
    ],
    "sg:phone":"+61 2 4626 1485",
    "sg:postcode":"2560",
    "sg:province":"NSW",
    "sg:tags":[
        "state",
        "-",
        "nsw"
    ],
    "wof:name":"Ambarvale Primary",
    "wof:placetype":"venue"
},
  "geometry": {"coordinates":[150.79757690400001,-34.0865364075],"type":"Point"}
}