{
  "type": "Feature",
  "properties": {
    "iso:country":"AU",
    "sg:address":"Pinga St",
    "sg:city":"South Hedland",
    "sg:classifiers":[
        {
            "category":"Manufacturing",
            "subcategory":"Motor Vehicles & Parts",
            "type":"Manufacturing & Wholesale Goods"
        }
    ],
    "sg:phone":"+61 8 9172 1066",
    "sg:postcode":"6722",
    "sg:province":"WA",
    "sg:tags":[
        "replacement"
    ],
    "wof:name":"Coventrys",
    "wof:placetype":"venue"
},
  "geometry": {"coordinates":[118.597427368,-20.3797054291],"type":"Point"}
}