{
  "type": "Feature",
  "properties": {
    "addr:full":"Level 1/ 2 Manning St Kiama NSW 2533",
    "addr:housenumber":"/ 2",
    "addr:postcode":"2533",
    "addr:street":"Manning St",
    "iso:country":"AU",
    "sg:address":"Level 1/ 2 Manning St",
    "sg:city":"Kiama",
    "sg:classifiers":[
        {
            "category":"Insurance",
            "subcategory":"Insurance Agent",
            "type":"Services"
        }
    ],
    "sg:phone":"+61 2 4232 3692",
    "sg:postcode":"2533",
    "sg:province":"NSW",
    "sg:tags":[
        "broker"
    ],
    "wof:name":"Greg Walsh & Associates+Insurance Consultants",
    "wof:placetype":"venue"
},
  "geometry": {"coordinates":[150.85194397000001,-34.6767997742],"type":"Point"}
}