{
  "type": "Feature",
  "properties": {
    "iso:country":"AU",
    "sg:address":"3 Rafferty St",
    "sg:city":"Wingfield",
    "sg:classifiers":[
        {
            "category":"Utilities",
            "subcategory":"Refuse",
            "type":"Services"
        }
    ],
    "sg:phone":"+61 8 8260 3016",
    "sg:postcode":"5013",
    "sg:province":"SA",
    "sg:tags":[
        "disposal",
        "reduction",
        "waste"
    ],
    "sg:website":"http://www.allstaterecycling.com.au",
    "wof:name":"All State Group Pty Ltd",
    "wof:placetype":"venue"
},
  "geometry": {"coordinates":[138.568115234,-34.8383140564],"type":"Point"}
}