{
  "type": "Feature",
  "properties": {
    "addr:full":"Dowell St Cowra NSW 2794",
    "addr:postcode":"2794",
    "addr:street":"Dowell St",
    "iso:country":"AU",
    "sg:address":"Dowell St",
    "sg:city":"Cowra",
    "sg:classifiers":[
        {
            "category":"Education",
            "subcategory":"School",
            "type":"Public Place"
        }
    ],
    "sg:phone":"+61 2 6342 1766",
    "sg:postcode":"2794",
    "sg:province":"NSW",
    "sg:tags":[
        "state",
        "-",
        "nsw"
    ],
    "wof:name":"Cowra High School",
    "wof:placetype":"venue"
},
  "geometry": {"coordinates":[148.693527222,-33.8164176941],"type":"Point"}
}