{
  "type": "Feature",
  "properties": {
    "iso:country":"AU",
    "sg:address":"11 Boys Ave",
    "sg:city":"Maryborough",
    "sg:classifiers":[
        {
            "category":"Personal",
            "subcategory":"Beauty Salon",
            "type":"Services"
        }
    ],
    "sg:phone":"+61 7 4121 4588",
    "sg:postcode":"4650",
    "sg:province":"QLD",
    "sg:tags":[
        "hairdresser"
    ],
    "wof:name":"Miss MaGees Hair Studio",
    "wof:placetype":"venue"
},
  "geometry": {"coordinates":[152.682724,-25.515697],"type":"Point"}
}