{
  "type": "Feature",
  "properties": {
    "addr:full":"Nepean Hwy Parkdale VIC 3195",
    "addr:postcode":"3195",
    "addr:street":"Nepean Hwy",
    "iso:country":"AU",
    "sg:address":"Nepean Hwy",
    "sg:city":"Parkdale",
    "sg:classifiers":[
        {
            "category":"Education",
            "subcategory":"School",
            "type":"Public Place"
        }
    ],
    "sg:phone":"+61 3 9580 1451",
    "sg:postcode":"3195",
    "sg:province":"VIC",
    "sg:tags":[
        "state",
        "except",
        "nsw"
    ],
    "wof:name":"Parkdale Primary",
    "wof:placetype":"venue"
},
  "geometry": {"coordinates":[145.081375122,-37.9913291931],"type":"Point"}
}