{
  "type": "Feature",
  "properties": {
    "addr:full":"30 Rocklands Rd Crows Nest NSW 2065",
    "addr:housenumber":"30",
    "addr:postcode":"2065",
    "addr:street":"Rocklands Rd",
    "iso:country":"AU",
    "sg:address":"30 Rocklands Rd",
    "sg:city":"Crows Nest",
    "sg:classifiers":[
        {
            "category":"Travel",
            "subcategory":"Hostel",
            "type":"Entertainment"
        }
    ],
    "sg:phone":"+61 2 8907 7100",
    "sg:postcode":"2065",
    "sg:province":"NSW",
    "sg:tags":[
        "home"
    ],
    "wof:name":"Catholic Health Care Services Limited",
    "wof:placetype":"venue"
},
  "geometry": {"coordinates":[151.201446533,-33.8310012817],"type":"Point"}
}