{
  "type": "Feature",
  "properties": {
    "iso:country":"AU",
    "sg:address":"PO Box 88",
    "sg:city":"Yarragon",
    "sg:classifiers":[
        {
            "category":"Health Services",
            "subcategory":"Health Practitioner",
            "type":"Services"
        }
    ],
    "sg:phone":"+61 419 563 648",
    "sg:postcode":"3823",
    "sg:province":"VIC",
    "sg:tags":[
        "psychotherapist"
    ],
    "wof:name":"Hillier Jenny",
    "wof:placetype":"venue"
},
  "geometry": {"coordinates":[146.084976,-38.184219],"type":"Point"}
}