{
  "type": "Feature",
  "properties": {
    "addr:full":"Cnr Dalrymple & Bayswater Rds Garbutt QLD 4814",
    "addr:postcode":"4814",
    "addr:street":"Cnr",
    "iso:country":"AU",
    "sg:address":"Cnr Dalrymple & Bayswater Rds",
    "sg:city":"Garbutt",
    "sg:classifiers":[
        {
            "category":"Autos & Motor Vehicles",
            "subcategory":"Auto Supplies",
            "type":"Retail Goods"
        }
    ],
    "sg:phone":"+61 7 4779 6544",
    "sg:postcode":"4814",
    "sg:province":"QLD",
    "sg:tags":[
        "tyre"
    ],
    "sg:website":"http://www.johnbarrtyres.com.au",
    "wof:name":"John Barr Tyres Pty Ltd",
    "wof:placetype":"venue"
},
  "geometry": {"coordinates":[146.78088399999999,-19.266947],"type":"Point"}
}