{
  "type": "Feature",
  "properties": {
    "addr:full":"222 Serpells Rd Templestowe VIC 3106",
    "addr:housenumber":"222",
    "addr:postcode":"3106",
    "addr:street":"Serpells Rd",
    "iso:country":"AU",
    "sg:address":"222 Serpells Rd",
    "sg:city":"Templestowe",
    "sg:classifiers":[
        {
            "category":"Education",
            "subcategory":"School",
            "type":"Public Place"
        }
    ],
    "sg:phone":"+61 3 9842 7634",
    "sg:postcode":"3106",
    "sg:province":"VIC",
    "sg:tags":[
        "co-educational"
    ],
    "wof:name":"St Charles Borromeo Primary",
    "wof:placetype":"venue"
},
  "geometry": {"coordinates":[145.15328979500001,-37.7671127319],"type":"Point"}
}