{
  "type": "Feature",
  "properties": {
    "addr:full":"17 Preston St Geelong West VIC 3218",
    "addr:housenumber":"17",
    "addr:postcode":"3218",
    "addr:street":"Preston St",
    "iso:country":"AU",
    "sg:address":"17 Preston St",
    "sg:city":"Geelong West",
    "sg:classifiers":[
        {
            "category":"Building & Trades",
            "subcategory":"Construction",
            "type":"Services"
        }
    ],
    "sg:phone":"+61 3 5229 8825",
    "sg:postcode":"3218",
    "sg:province":"VIC",
    "sg:tags":[
        "polishing",
        "sanding",
        "floor"
    ],
    "wof:name":"Kelly Floor Co.",
    "wof:placetype":"venue"
},
  "geometry": {"coordinates":[144.35260009800001,-38.1404876709],"type":"Point"}
}