{
  "type": "Feature",
  "properties": {
    "addr:full":"206 Barkly St St Kilda VIC 3182",
    "addr:housenumber":"206",
    "addr:postcode":"3182",
    "addr:street":"Barkly St",
    "iso:country":"AU",
    "sg:address":"206 Barkly St St",
    "sg:city":"Kilda",
    "sg:classifiers":[
        {
            "category":"Retail",
            "subcategory":"Storage",
            "type":"Services"
        }
    ],
    "sg:phone":"+61 1800 555 577",
    "sg:postcode":"3182",
    "sg:province":"VIC",
    "sg:tags":[
        "removal",
        "furniture"
    ],
    "wof:name":"Finishing Touch Home Unpacking Services",
    "wof:placetype":"venue"
},
  "geometry": {"coordinates":[144.980834961,-37.8700523376],"type":"Point"}
}