{
  "type": "Feature",
  "properties": {
    "iso:country":"AU",
    "sg:address":"Shops 16 Northside Plaza 222 Musgrave St",
    "sg:city":"North Rockhampton",
    "sg:classifiers":[
        {
            "category":"Food & Beverages",
            "subcategory":"Liquor & Beverages",
            "type":"Retail Goods"
        }
    ],
    "sg:phone":"+61 7 4921 2462",
    "sg:postcode":"4701",
    "sg:province":"QLD",
    "sg:tags":[
        "store"
    ],
    "wof:name":"BWS Liquor Stores",
    "wof:placetype":"venue"
},
  "geometry": {"coordinates":[150.523513794,-23.35978508],"type":"Point"}
}