{
  "type": "Feature",
  "properties": {
    "addr:full":"Shop 32, Crown Central Shopping Centre, 200 Crown St Wollongong NSW 2500",
    "addr:housenumber":"shop 32;200",
    "addr:postcode":"2500",
    "addr:street":"Crown Central;Crown St",
    "iso:country":"AU",
    "sg:address":"Shop 32, Crown Central Shopping Centre, 200 Crown St",
    "sg:city":"Wollongong",
    "sg:classifiers":[
        {
            "category":"Shopping",
            "subcategory":"Clothing, Apparel, & Fashions",
            "type":"Retail Goods"
        }
    ],
    "sg:phone":"+61 2 4229 2311",
    "sg:postcode":"2500",
    "sg:province":"NSW",
    "sg:tags":[
        "lady",
        "wear"
    ],
    "wof:name":"Noni- B-Fashions",
    "wof:placetype":"venue"
},
  "geometry": {"coordinates":[150.871735,-34.425396],"type":"Point"}
}