{
  "type": "Feature",
  "properties": {
    "iso:country":"AU",
    "sg:address":"2/ 184 Gladstone St",
    "sg:city":"Fyshwick",
    "sg:classifiers":[
        {
            "category":"Building & Trades",
            "subcategory":"Construction",
            "type":"Services"
        }
    ],
    "sg:phone":"+61 1800 885 881",
    "sg:postcode":"2609",
    "sg:province":"ACT",
    "sg:tags":[
        "home",
        "air conditioning"
    ],
    "wof:name":"Thermal Active",
    "wof:placetype":"venue"
},
  "geometry": {"coordinates":[149.18490600600001,-35.3296737671],"type":"Point"}
}