{
  "type": "Feature",
  "properties": {
    "iso:country":"AU",
    "sg:address":"640 Stanley St",
    "sg:city":"Woolloongabba",
    "sg:classifiers":[
        {
            "category":"Travel",
            "subcategory":"Hotels & Motels",
            "type":"Entertainment"
        }
    ],
    "sg:phone":"+61 7 3435 1700",
    "sg:postcode":"4102",
    "sg:province":"QLD",
    "sg:tags":[
        "accommodation"
    ],
    "wof:name":"MGW Hotels Pty Ltd",
    "wof:placetype":"venue"
},
  "geometry": {"coordinates":[153.03060913100001,-27.4856376648],"type":"Point"}
}