{
  "type": "Feature",
  "properties": {
    "addr:full":"Shop 2, 11-17 Burleigh St Burwood NSW 2134",
    "addr:housenumber":"shop 2",
    "addr:postcode":"11-17;2134",
    "addr:street":"Burleigh St",
    "iso:country":"AU",
    "sg:address":"Shop 2, 11-17 Burleigh St",
    "sg:city":"Burwood",
    "sg:classifiers":[
        {
            "category":"Health Services",
            "subcategory":"Dentist",
            "type":"Services"
        }
    ],
    "sg:phone":"+61 2 9747 8699",
    "sg:postcode":"2134",
    "sg:province":"NSW",
    "wof:name":"Ho Dr Gareth Orthodontist",
    "wof:placetype":"venue"
},
  "geometry": {"coordinates":[151.10443115199999,-33.8784255981],"type":"Point"}
}