{
  "type": "Feature",
  "properties": {
    "addr:full":"124 Mcdowall St Roma QLD 4455",
    "addr:housenumber":"124",
    "addr:postcode":"4455",
    "addr:street":"Mcdowall St",
    "iso:country":"AU",
    "sg:address":"124 Mcdowall St",
    "sg:city":"Roma",
    "sg:classifiers":[
        {
            "category":"Health Services",
            "subcategory":"Doctor",
            "type":"Services"
        }
    ],
    "sg:phone":"+61 7 4622 5681",
    "sg:postcode":"4455",
    "sg:province":"QLD",
    "sg:tags":[
        "medical",
        "practitioner"
    ],
    "wof:name":"Alpenglow Australia Pty Ltd",
    "wof:placetype":"venue"
},
  "geometry": {"coordinates":[148.787353516,-26.5714511871],"type":"Point"}
}