{
  "type": "Feature",
  "properties": {
    "addr:full":"PO Box 725 Lilydale VIC 3140",
    "addr:postcode":"3140",
    "iso:country":"AU",
    "sg:address":"PO Box 725",
    "sg:city":"Lilydale",
    "sg:classifiers":[
        {
            "category":"Professional",
            "subcategory":"Management & Consulting",
            "type":"Services"
        }
    ],
    "sg:phone":"+61 3 9777 0352",
    "sg:postcode":"3140",
    "sg:province":"VIC",
    "sg:tags":[
        "consultant",
        "energy"
    ],
    "wof:name":"Eltec Energy Service",
    "wof:placetype":"venue"
},
  "geometry": {"coordinates":[145.37161254899999,-37.7617797852],"type":"Point"}
}