{
  "type": "Feature",
  "properties": {
    "addr:full":"PO Box 52 Mt Helena WA 6082",
    "addr:postcode":"6082",
    "iso:country":"AU",
    "sg:address":"PO Box 52",
    "sg:city":"Mt Helena",
    "sg:classifiers":[
        {
            "category":"Banks & Credit Unions",
            "subcategory":"Financial Services",
            "type":"Services"
        }
    ],
    "sg:phone":"+61 8 9572 2200",
    "sg:postcode":"6082",
    "sg:province":"WA",
    "sg:tags":[
        "settlement",
        "nt",
        "agent",
        "wa"
    ],
    "wof:name":"Anne Lynch Conveyancing",
    "wof:placetype":"venue"
},
  "geometry": {"coordinates":[116.21082305900001,-31.8779201508],"type":"Point"}
}