{
  "type": "Feature",
  "properties": {
    "iso:country":"AU",
    "sg:address":"388 Springvale Rd",
    "sg:city":"Forest Hill",
    "sg:classifiers":[
        {
            "category":"Home & Garden",
            "subcategory":"Garden Supply",
            "type":"Retail Goods"
        }
    ],
    "sg:phone":"+61 3 9877 1430",
    "sg:postcode":"3131",
    "sg:province":"VIC",
    "sg:tags":[
        "landscape"
    ],
    "wof:name":"Whitehouse Gardens",
    "wof:placetype":"venue"
},
  "geometry": {"coordinates":[145.17129516599999,-37.8396072388],"type":"Point"}
}