{
  "type": "Feature",
  "properties": {
    "iso:country":"AU",
    "sg:address":"24 Ross Ave",
    "sg:city":"Sorrento",
    "sg:classifiers":[
        {
            "category":"Recreation",
            "subcategory":"Boat Charter",
            "type":"Entertainment"
        }
    ],
    "sg:phone":"+61 8 9447 6956",
    "sg:postcode":"6020",
    "sg:province":"WA",
    "wof:name":"Hillarys Fishing & Whale Watch Excursions",
    "wof:placetype":"venue"
},
  "geometry": {"coordinates":[115.751502991,-31.8345756531],"type":"Point"}
}