{
  "type": "Feature",
  "properties": {
    "addr:full":"75a Astor Tce Spring Hill QLD 4000",
    "addr:housenumber":"75a",
    "addr:postcode":"4000",
    "addr:street":"Astor Tce",
    "iso:country":"AU",
    "sg:address":"75a Astor Tce",
    "sg:city":"Spring Hill",
    "sg:classifiers":[
        {
            "category":"Health Services",
            "subcategory":"Doctor",
            "type":"Services"
        }
    ],
    "sg:phone":"+61 7 3815 6900",
    "sg:postcode":"4000",
    "sg:province":"QLD",
    "sg:tags":[
        "medical",
        "practitioner"
    ],
    "sg:website":"http://www.traveldoctor.com.au",
    "wof:name":"Travel Doctor - TMVC",
    "wof:placetype":"venue"
},
  "geometry": {"coordinates":[153.02676391599999,-27.4633846283],"type":"Point"}
}