{
  "type": "Feature",
  "properties": {
    "iso:country":"AU",
    "sg:address":"24 South St",
    "sg:city":"Gunnedah",
    "sg:classifiers":[
        {
            "category":"Building & Trades",
            "subcategory":"Pest Control",
            "type":"Services"
        }
    ],
    "sg:phone":"+61 2 6742 1511",
    "sg:postcode":"2380",
    "sg:province":"NSW",
    "wof:name":"Gunnedah Pest Control Renton's",
    "wof:placetype":"venue"
},
  "geometry": {"coordinates":[150.253143311,-30.9820232391],"type":"Point"}
}