{
  "type": "Feature",
  "properties": {
    "addr:full":"Unit G, 84 Stanbel Rd Salisbury Plain SA 5109",
    "addr:housenumber":"84",
    "addr:postcode":"5109",
    "addr:street":"Stanbel Rd",
    "iso:country":"AU",
    "sg:address":"Unit G, 84 Stanbel Rd",
    "sg:city":"Salisbury Plain",
    "sg:classifiers":[
        {
            "category":"Landmark",
            "subcategory":"Scenic View",
            "type":"Public Place"
        }
    ],
    "sg:phone":"+61 8 8258 6006",
    "sg:postcode":"5109",
    "sg:province":"SA",
    "sg:tags":[
        "staircase",
        "handrail"
    ],
    "wof:name":"Stairs By Design",
    "wof:placetype":"venue"
},
  "geometry": {"coordinates":[138.66156005900001,-34.7706108093],"type":"Point"}
}