{
  "type": "Feature",
  "properties": {
    "iso:country":"AU",
    "sg:address":"5 Astor St",
    "sg:city":"Adamstown Heights",
    "sg:classifiers":[
        {
            "category":"Professional",
            "subcategory":"Art Services",
            "type":"Services"
        }
    ],
    "sg:phone":"+61 419 985 203",
    "sg:postcode":"2289",
    "sg:province":"NSW",
    "sg:tags":[
        "decorator",
        "painter"
    ],
    "wof:name":"Johnson Guy",
    "wof:placetype":"venue"
},
  "geometry": {"coordinates":[151.70619201700001,-32.9524497986],"type":"Point"}
}