{
  "type": "Feature",
  "properties": {
    "addr:full":"6 Prospect Rd Fitzroy SA 5082",
    "addr:housenumber":"6",
    "addr:postcode":"5082",
    "addr:street":"Prospect Rd",
    "iso:country":"AU",
    "sg:address":"6 Prospect Rd",
    "sg:city":"Fitzroy",
    "sg:classifiers":[
        {
            "category":"Personal",
            "subcategory":"Beauty Salon",
            "type":"Services"
        }
    ],
    "sg:phone":"+61 8 8342 1066",
    "sg:postcode":"5082",
    "sg:province":"SA",
    "sg:tags":[
        "hairdresser"
    ],
    "wof:name":"Brigittes Salon",
    "wof:placetype":"venue"
},
  "geometry": {"coordinates":[138.59461975100001,-34.8977775574],"type":"Point"}
}