{
  "type": "Feature",
  "properties": {
    "addr:full":"75 Thomson Rd North Fremantle WA 6159",
    "addr:housenumber":"75",
    "addr:postcode":"6159",
    "addr:street":"Thomson Rd",
    "iso:country":"AU",
    "sg:address":"75 Thomson Rd",
    "sg:city":"North Fremantle",
    "sg:classifiers":[
        {
            "category":"Farming",
            "subcategory":"Farm & Veterinary Services",
            "type":"Manufacturing & Wholesale Goods"
        }
    ],
    "sg:phone":"+61 8 9433 2444",
    "sg:postcode":"6159",
    "sg:province":"WA",
    "sg:tags":[
        "agricultural",
        "advisory"
    ],
    "wof:name":"Sheep Management & Production Consultants",
    "wof:placetype":"venue"
},
  "geometry": {"coordinates":[115.753838,-32.028137],"type":"Point"}
}