{
  "type": "Feature",
  "properties": {
    "addr:full":"29 Lord St Port Macquarie NSW 2444",
    "addr:housenumber":"29",
    "addr:postcode":"2444",
    "addr:street":"Lord St",
    "iso:country":"AU",
    "sg:address":"29 Lord St",
    "sg:city":"Port Macquarie",
    "sg:classifiers":[
        {
            "category":"Autos & Motor Vehicles",
            "subcategory":"Fuel & Gas Station",
            "type":"Retail Goods"
        }
    ],
    "sg:phone":"+61 2 6583 1663",
    "sg:postcode":"2444",
    "sg:province":"NSW",
    "wof:name":"Ampol",
    "wof:placetype":"venue"
},
  "geometry": {"coordinates":[152.91720599999999,-31.433146],"type":"Point"}
}