{
  "type": "Feature",
  "properties": {
    "addr:full":"16 Stoddart Rd Prospect NSW 2148",
    "addr:housenumber":"16",
    "addr:postcode":"2148",
    "addr:street":"Stoddart Rd",
    "iso:country":"AU",
    "sg:address":"16 Stoddart Rd",
    "sg:city":"Prospect",
    "sg:classifiers":[
        {
            "category":"Building & Trades",
            "subcategory":"Construction",
            "type":"Services"
        }
    ],
    "sg:phone":"+61 2 9896 7232",
    "sg:postcode":"2148",
    "sg:province":"NSW",
    "sg:tags":[
        "scaffolding"
    ],
    "wof:name":"Roof Safe T Systems",
    "wof:placetype":"venue"
},
  "geometry": {"coordinates":[150.92164611800001,-33.7998733521],"type":"Point"}
}