{
  "type": "Feature",
  "properties": {
    "iso:country":"AU",
    "sg:address":"U1/ 9",
    "sg:city":"Drury Tce Clovelly Park",
    "sg:classifiers":[
        {
            "category":"Manufacturing",
            "subcategory":"Rubber & Plastics",
            "type":"Manufacturing & Wholesale Goods"
        }
    ],
    "sg:phone":"+61 8 8357 5611",
    "sg:postcode":"5042",
    "sg:province":"SA",
    "sg:tags":[
        "moulders"
    ],
    "wof:name":"Copeland Industries Pty Ltd",
    "wof:placetype":"venue"
},
  "geometry": {"coordinates":[138.57264699999999,-35.004688],"type":"Point"}
}