{
  "type": "Feature",
  "properties": {
    "addr:full":"20 Lochiel Ave Mt Martha VIC 3934",
    "addr:housenumber":"20",
    "addr:postcode":"3934",
    "addr:street":"Lochiel Ave Mt Martha",
    "iso:country":"AU",
    "sg:address":"20 Lochiel Ave",
    "sg:city":"Mt Martha",
    "sg:classifiers":[
        {
            "category":"Farming",
            "subcategory":"Farm & Veterinary Services",
            "type":"Manufacturing & Wholesale Goods"
        }
    ],
    "sg:phone":"+61 3 5974 8668",
    "sg:postcode":"3934",
    "sg:province":"VIC",
    "sg:tags":[
        "irrigation",
        "reticulation",
        "system"
    ],
    "wof:name":"Jones Paul & Associates Pty Ltd",
    "wof:placetype":"venue"
},
  "geometry": {"coordinates":[145.012939453,-38.2677116394],"type":"Point"}
}