{
  "type": "Feature",
  "properties": {
    "addr:full":"112 Main St Greensborough VIC 3088",
    "addr:housenumber":"112",
    "addr:postcode":"3088",
    "addr:street":"Main St",
    "iso:country":"AU",
    "sg:address":"112 Main St",
    "sg:city":"Greensborough",
    "sg:classifiers":[
        {
            "category":"Health Services",
            "subcategory":"Doctor",
            "type":"Services"
        }
    ],
    "sg:phone":"+61 3 9432 0000",
    "sg:postcode":"3088",
    "sg:province":"VIC",
    "sg:tags":[
        "medical",
        "practitioner"
    ],
    "wof:name":"Betta Health Medical Centres",
    "wof:placetype":"venue"
},
  "geometry": {"coordinates":[145.10597229000001,-37.7020797729],"type":"Point"}
}