{
  "type": "Feature",
  "properties": {
    "iso:country":"AU",
    "sg:address":"226 McIntyre Rd",
    "sg:city":"Sunshine",
    "sg:classifiers":[
        {
            "category":"Home & Garden",
            "subcategory":"Hardware",
            "type":"Retail Goods"
        }
    ],
    "sg:phone":"+61 3 9364 6606",
    "sg:postcode":"3020",
    "sg:province":"VIC",
    "sg:tags":[
        "plumber",
        "supply"
    ],
    "wof:name":"McCanns Plumbing Plus",
    "wof:placetype":"venue"
},
  "geometry": {"coordinates":[144.833023,-37.754318],"type":"Point"}
}