{
  "type": "Feature",
  "properties": {
    "iso:country":"AU",
    "sg:address":"16- 22 Playne St",
    "sg:city":"Frankston",
    "sg:classifiers":[
        {
            "category":"Shopping",
            "subcategory":"Clothing, Apparel, & Fashions",
            "type":"Retail Goods"
        }
    ],
    "sg:phone":"+61 3 9783 1711",
    "sg:postcode":"3199",
    "sg:province":"VIC",
    "sg:tags":[
        "recycled",
        "clothing"
    ],
    "wof:name":"Savers Australia Inc.",
    "wof:placetype":"venue"
},
  "geometry": {"coordinates":[145.121536255,-38.1446914673],"type":"Point"}
}