{
  "type": "Feature",
  "properties": {
    "addr:full":"31 Chesterman St Moonah TAS 7009",
    "addr:housenumber":"31",
    "addr:postcode":"7009",
    "addr:street":"Chesterman St",
    "iso:country":"AU",
    "sg:address":"31 Chesterman St",
    "sg:city":"Moonah",
    "sg:classifiers":[
        {
            "category":"Building & Trades",
            "subcategory":"Construction",
            "type":"Services"
        }
    ],
    "sg:phone":"+61 3 6278 8688",
    "sg:postcode":"7009",
    "sg:province":"TAS",
    "sg:tags":[
        "industrial",
        "commercial",
        "air conditioning"
    ],
    "wof:name":"Klimate Solutions",
    "wof:placetype":"venue"
},
  "geometry": {"coordinates":[147.295852661,-42.8409919739],"type":"Point"}
}