{
  "type": "Feature",
  "properties": {
    "iso:country":"AU",
    "sg:address":"Suite 14, 39 Market St",
    "sg:city":"Wollongong",
    "sg:classifiers":[
        {
            "category":"Health Services",
            "subcategory":"Health Practitioner",
            "type":"Services"
        }
    ],
    "sg:phone":"+61 416 209 219",
    "sg:postcode":"2500",
    "sg:province":"NSW",
    "sg:tags":[
        "psychologist"
    ],
    "wof:name":"Lisa Densley",
    "wof:placetype":"venue"
},
  "geometry": {"coordinates":[150.881149,-34.425949],"type":"Point"}
}