{
  "type": "Feature",
  "properties": {
    "iso:country":"AU",
    "sg:address":"523 Pacific Hwy",
    "sg:city":"Mt Colah",
    "sg:classifiers":[
        {
            "category":"Farming",
            "subcategory":"Fish & Marine Products",
            "type":"Manufacturing & Wholesale Goods"
        }
    ],
    "sg:phone":"+61 2 9477 1655",
    "sg:postcode":"2079",
    "sg:province":"NSW",
    "sg:tags":[
        "supplier",
        "oyster",
        "farmer"
    ],
    "wof:name":"Windybank's Seafood",
    "wof:placetype":"venue"
},
  "geometry": {"coordinates":[151.11183166500001,-33.6777763367],"type":"Point"}
}