{
  "type": "Feature",
  "properties": {
    "iso:country":"AU",
    "sg:address":"6562 Maroondah Hwy",
    "sg:city":"Yarck",
    "sg:classifiers":[
        {
            "category":"Building & Trades",
            "subcategory":"Construction",
            "type":"Services"
        }
    ],
    "sg:phone":"+61 3 5773 4242",
    "sg:postcode":"3719",
    "sg:province":"VIC",
    "sg:tags":[
        "road",
        "contractor"
    ],
    "wof:name":"Keaths Excavations Pty Ltd",
    "wof:placetype":"venue"
},
  "geometry": {"coordinates":[145.615432739,-37.1037483215],"type":"Point"}
}