{
  "type": "Feature",
  "properties": {
    "addr:full":"65 Salisbury St Inglewood WA 6052",
    "addr:housenumber":"65",
    "addr:postcode":"6052",
    "addr:street":"Salisbury St",
    "iso:country":"AU",
    "sg:address":"65 Salisbury St",
    "sg:city":"Inglewood",
    "sg:classifiers":[
        {
            "category":"Education",
            "subcategory":"Special Training",
            "type":"Public Place"
        }
    ],
    "sg:phone":"+61 8 9324 9836",
    "sg:postcode":"6052",
    "sg:province":"WA",
    "sg:tags":[
        "development"
    ],
    "wof:name":"Nylund Lindsay & Associates",
    "wof:placetype":"venue"
},
  "geometry": {"coordinates":[115.89041137700001,-31.915851593],"type":"Point"}
}