{
  "type": "Feature",
  "properties": {
    "addr:full":"Cnr Sunraysia Hwy & Waringa Drv Wendouree VIC 3355",
    "addr:postcode":"3355",
    "addr:street":"Cnr Sunraysia Hwy & Waringa Drv",
    "iso:country":"AU",
    "sg:address":"Cnr Sunraysia Hwy & Waringa Drv",
    "sg:city":"Wendouree",
    "sg:classifiers":[
        {
            "category":"Autos & Motor Vehicles",
            "subcategory":"Automobile Sales",
            "type":"Retail Goods"
        }
    ],
    "sg:phone":"+61 3 5339 9339",
    "sg:postcode":"3355",
    "sg:province":"VIC",
    "sg:tags":[
        "car",
        "new"
    ],
    "wof:name":"BMW",
    "wof:placetype":"venue"
},
  "geometry": {"coordinates":[143.78703300000001,-37.485661],"type":"Point"}
}