{
  "type": "Feature",
  "properties": {
    "iso:country":"AU",
    "sg:address":"28 Lionel St",
    "sg:city":"Naval Base",
    "sg:classifiers":[
        {
            "category":"Building & Trades",
            "subcategory":"Construction",
            "type":"Services"
        }
    ],
    "sg:phone":"+61 8 9410 0095",
    "sg:postcode":"6165",
    "sg:province":"WA",
    "sg:tags":[
        "concrete",
        "paving"
    ],
    "wof:name":"Prime Stone Architectural Paving",
    "wof:placetype":"venue"
},
  "geometry": {"coordinates":[115.78537799999999,-32.195972],"type":"Point"}
}