{
  "type": "Feature",
  "properties": {
    "addr:full":"2 Athena Ave St Ives NSW 2075",
    "addr:housenumber":"2",
    "addr:postcode":"2075",
    "addr:street":"Athena Ave",
    "iso:country":"AU",
    "sg:address":"2 Athena Ave St",
    "sg:city":"Ives",
    "sg:classifiers":[
        {
            "category":"Professional",
            "subcategory":"Accounting & Tax Preparation",
            "type":"Services"
        }
    ],
    "sg:phone":"+61 2 9144 1292",
    "sg:postcode":"2075",
    "sg:province":"NSW",
    "sg:tags":[
        "accountant",
        "auditor"
    ],
    "wof:name":"Davar A R",
    "wof:placetype":"venue"
},
  "geometry": {"coordinates":[151.17965698200001,-33.7258033752],"type":"Point"}
}