{
  "type": "Feature",
  "properties": {
    "addr:full":"52 Mulheron Ave Baulkham Hills NSW 2153",
    "addr:housenumber":"52",
    "addr:postcode":"2153",
    "addr:street":"Mulheron Ave",
    "iso:country":"AU",
    "sg:address":"52 Mulheron Ave",
    "sg:city":"Baulkham Hills",
    "sg:classifiers":[
        {
            "category":"Banks & Credit Unions",
            "subcategory":"Bureau De Change",
            "type":"Services"
        }
    ],
    "sg:phone":"+61 2 9838 9594",
    "sg:postcode":"2153",
    "sg:province":"NSW",
    "sg:tags":[
        "repairs",
        "part",
        "appliance",
        "electrical"
    ],
    "wof:name":"Oakedge Pty Ltd",
    "wof:placetype":"venue"
},
  "geometry": {"coordinates":[150.96870422399999,-33.76222229],"type":"Point"}
}