{
  "type": "Feature",
  "properties": {
    "addr:full":"4 Albion St Wingfield SA 5013",
    "addr:housenumber":"4",
    "addr:postcode":"5013",
    "addr:street":"Albion St",
    "iso:country":"AU",
    "sg:address":"4 Albion St",
    "sg:city":"Wingfield",
    "sg:classifiers":[
        {
            "category":"Shopping",
            "subcategory":"Party Supplies",
            "type":"Retail Goods"
        }
    ],
    "sg:phone":"+61 8 8347 2992",
    "sg:postcode":"5013",
    "sg:province":"SA",
    "wof:name":"Wingfield Ice Supplies",
    "wof:placetype":"venue"
},
  "geometry": {"coordinates":[138.55732727,-34.8453292847],"type":"Point"}
}