{
  "type": "Feature",
  "properties": {
    "addr:full":"1, 9 Myrtle St Crows Nest NSW 2065",
    "addr:housenumber":"9",
    "addr:postcode":"2065",
    "addr:street":"Myrtle St",
    "iso:country":"AU",
    "sg:address":"1, 9 Myrtle St",
    "sg:city":"Crows Nest",
    "sg:classifiers":[
        {
            "category":"Wholesale",
            "subcategory":"Drugs",
            "type":"Manufacturing & Wholesale Goods"
        }
    ],
    "sg:phone":"+61 2 9955 8688",
    "sg:postcode":"2065",
    "sg:province":"NSW",
    "sg:tags":[
        "wholesaler",
        "pharmaceutical",
        "product",
        "mfrs"
    ],
    "wof:name":"Ego Pharmaceuticals Pty Ltd",
    "wof:placetype":"venue"
},
  "geometry": {"coordinates":[151.20382690400001,-33.831161499],"type":"Point"}
}