{
  "type": "Feature",
  "properties": {
    "iso:country":"AU",
    "sg:address":"23 Hewson St",
    "sg:city":"Nyora",
    "sg:classifiers":[
        {
            "category":"Home & Garden",
            "subcategory":"Building Materials",
            "type":"Retail Goods"
        }
    ],
    "sg:phone":"+61 3 5659 0297",
    "sg:postcode":"3987",
    "sg:province":"VIC",
    "sg:tags":[
        "lawn",
        "cutting",
        "maintenance"
    ],
    "wof:name":"Pottsies Garden Maintenance",
    "wof:placetype":"venue"
},
  "geometry": {"coordinates":[145.66923523,-38.3356933594],"type":"Point"}
}