{
  "type": "Feature",
  "properties": {
    "addr:full":"Ste 6/ 14 Narabang Way Belrose NSW 2085",
    "addr:postcode":"2085",
    "addr:street":"14 Narabang Way",
    "iso:country":"AU",
    "sg:address":"Ste 6/ 14",
    "sg:city":"Narabang Way Belrose",
    "sg:classifiers":[
        {
            "category":"Professional",
            "subcategory":"Computer Services",
            "type":"Services"
        }
    ],
    "sg:phone":"+61 2 8205 7585",
    "sg:postcode":"2085",
    "sg:province":"NSW",
    "sg:tags":[
        "package",
        "software"
    ],
    "wof:name":"SMO Technology",
    "wof:placetype":"venue"
},
  "geometry": {"coordinates":[151.21241760300001,-33.7053260803],"type":"Point"}
}