{
  "type": "Feature",
  "properties": {
    "iso:country":"AU",
    "sg:address":"328 Leichhardt St",
    "sg:city":"North Rockhampton",
    "sg:classifiers":[
        {
            "category":"Banks & Credit Unions",
            "subcategory":"Financial Services",
            "type":"Services"
        }
    ],
    "sg:phone":"+61 7 4936 2076",
    "sg:postcode":"4701",
    "sg:province":"QLD",
    "sg:tags":[
        "wholesaler",
        "mfrs",
        "gear"
    ],
    "wof:name":"Dharma Engineering Pty Ltd",
    "wof:placetype":"venue"
},
  "geometry": {"coordinates":[150.50067138700001,-23.3264770508],"type":"Point"}
}