{
  "type": "Feature",
  "properties": {
    "iso:country":"AU",
    "sg:address":"81- 83 Victoria St",
    "sg:city":"Taree",
    "sg:classifiers":[
        {
            "category":"Manufacturing",
            "subcategory":"Food",
            "type":"Manufacturing & Wholesale Goods"
        }
    ],
    "sg:phone":"+61 2 6552 4199",
    "sg:postcode":"2430",
    "sg:province":"NSW",
    "sg:tags":[
        "function",
        "catering"
    ],
    "wof:name":"Island Trader Restaurant",
    "wof:placetype":"venue"
},
  "geometry": {"coordinates":[152.46400499999999,-31.91148],"type":"Point"}
}