{
  "type": "Feature",
  "properties": {
    "addr:full":"111 Main St Blacktown NSW 2148",
    "addr:housenumber":"111",
    "addr:postcode":"2148",
    "addr:street":"Main St",
    "iso:country":"AU",
    "sg:address":"111 Main St",
    "sg:city":"Blacktown",
    "sg:classifiers":[
        {
            "category":"Education",
            "subcategory":"Special Training",
            "type":"Public Place"
        }
    ],
    "sg:phone":"+61 2 9671 3300",
    "sg:postcode":"2148",
    "sg:province":"NSW",
    "sg:tags":[
        "tuition-educational"
    ],
    "wof:name":"Master Coaching",
    "wof:placetype":"venue"
},
  "geometry": {"coordinates":[150.910766602,-33.7711029053],"type":"Point"}
}