{
  "type": "Feature",
  "properties": {
    "iso:country":"AU",
    "sg:address":"Lot 2243 Elsherana Rd Light Industrial Area (LIA)",
    "sg:city":"Jabiru",
    "sg:classifiers":[
        {
            "category":"Utilities",
            "subcategory":"Electric",
            "type":"Services"
        }
    ],
    "sg:phone":"+61 8 8979 2229",
    "sg:postcode":"0886",
    "sg:province":"NT",
    "sg:tags":[
        "electrical",
        "contractor"
    ],
    "wof:name":"Kakadu Contracting Pty. Ltd.",
    "wof:placetype":"venue"
},
  "geometry": {"coordinates":[132.84916699999999,-12.659088],"type":"Point"}
}