{
  "type": "Feature",
  "properties": {
    "iso:country":"AU",
    "sg:address":"420 Burke Rd",
    "sg:city":"Camberwell",
    "sg:classifiers":[
        {
            "category":"Home & Garden",
            "subcategory":"Furniture",
            "type":"Retail Goods"
        }
    ],
    "sg:phone":"+61 3 9889 4984",
    "sg:postcode":"3124",
    "sg:province":"VIC",
    "sg:tags":[
        "repair",
        "restoration"
    ],
    "wof:name":"Sheridan Brown Antiques",
    "wof:placetype":"venue"
},
  "geometry": {"coordinates":[145.054321289,-37.8447532654],"type":"Point"}
}