{
  "type": "Feature",
  "properties": {
    "iso:country":"AU",
    "sg:address":"Marine Pde",
    "sg:city":"Southport",
    "sg:classifiers":[
        {
            "category":"Food & Beverages",
            "subcategory":"Liquor & Beverages",
            "type":"Retail Goods"
        }
    ],
    "sg:phone":"+61 7 5591 5611",
    "sg:postcode":"4215",
    "sg:province":"QLD",
    "sg:tags":[
        "store"
    ],
    "wof:name":"Champion Liquor Stores",
    "wof:placetype":"venue"
},
  "geometry": {"coordinates":[153.41558837900001,-27.9655361176],"type":"Point"}
}