{
  "type": "Feature",
  "properties": {
    "addr:full":"Timbury St Roma QLD 4455",
    "addr:postcode":"4455",
    "addr:street":"Timbury St",
    "iso:country":"AU",
    "sg:address":"Timbury St",
    "sg:city":"Roma",
    "sg:classifiers":[
        {
            "category":"Education",
            "subcategory":"School",
            "type":"Public Place"
        }
    ],
    "sg:phone":"+61 7 4622 2717",
    "sg:postcode":"4455",
    "sg:province":"QLD",
    "sg:tags":[
        "state",
        "except",
        "nsw"
    ],
    "wof:name":"Roma West Preschool",
    "wof:placetype":"venue"
},
  "geometry": {"coordinates":[148.78189086899999,-26.5672206879],"type":"Point"}
}