{
  "type": "Feature",
  "properties": {
    "addr:full":"178 Richmond Rd Marleston SA 5033",
    "addr:housenumber":"178",
    "addr:postcode":"5033",
    "addr:street":"Richmond Rd",
    "iso:country":"AU",
    "sg:address":"178 Richmond Rd",
    "sg:city":"Marleston",
    "sg:classifiers":[
        {
            "category":"Fast Food",
            "type":"Food & Drink"
        }
    ],
    "sg:phone":"+61 8 8352 1759",
    "sg:postcode":"5033",
    "sg:province":"SA",
    "sg:tags":[
        "away",
        "take"
    ],
    "wof:name":"Rex Food Bar The",
    "wof:placetype":"venue"
},
  "geometry": {"coordinates":[138.56394958499999,-34.9425888062],"type":"Point"}
}