{
  "type": "Feature",
  "properties": {
    "addr:full":"39 Freeman St Yarraville VIC 3013",
    "addr:housenumber":"39",
    "addr:postcode":"3013",
    "addr:street":"Freeman St",
    "iso:country":"AU",
    "sg:address":"39 Freeman St",
    "sg:city":"Yarraville",
    "sg:classifiers":[
        {
            "category":"Utilities",
            "subcategory":"Electric",
            "type":"Services"
        }
    ],
    "sg:phone":"+61 3 9315 1200",
    "sg:postcode":"3013",
    "sg:province":"VIC",
    "sg:tags":[
        "electrical",
        "contractor"
    ],
    "wof:name":"Molec Electrical Contractors",
    "wof:placetype":"venue"
},
  "geometry": {"coordinates":[144.87391662600001,-37.8188743591],"type":"Point"}
}