{
  "type": "Feature",
  "properties": {
    "iso:country":"AU",
    "sg:address":"Lot1121/ Boomerang Rd",
    "sg:city":"Oldbury",
    "sg:classifiers":[
        {
            "category":"Professional",
            "subcategory":"Engineering",
            "type":"Services"
        }
    ],
    "sg:phone":"+61 8 9523 1066",
    "sg:postcode":"6121",
    "sg:province":"WA",
    "sg:tags":[
        "engineer"
    ],
    "wof:name":"Triangle Engineering Consultants Pty Ltd",
    "wof:placetype":"venue"
},
  "geometry": {"coordinates":[115.901428223,-32.2676506042],"type":"Point"}
}