{
  "type": "Feature",
  "properties": {
    "addr:full":"3 Second St Quandialla NSW 2721",
    "addr:housenumber":"3",
    "addr:postcode":"2721",
    "addr:street":"Second St",
    "iso:country":"AU",
    "sg:address":"3 Second St",
    "sg:city":"Quandialla",
    "sg:classifiers":[
        {
            "category":"Wholesale",
            "subcategory":"Farm Supplies",
            "type":"Manufacturing & Wholesale Goods"
        }
    ],
    "sg:phone":"+61 2 6347 1153",
    "sg:postcode":"2721",
    "sg:province":"NSW",
    "sg:tags":[
        "equipment"
    ],
    "wof:name":"PFC Ag Quandialla",
    "wof:placetype":"venue"
},
  "geometry": {"coordinates":[147.793091,-34.011536],"type":"Point"}
}