{
  "type": "Feature",
  "properties": {
    "iso:country":"AU",
    "sg:address":"970 South Rd",
    "sg:city":"Edwardstown",
    "sg:classifiers":[
        {
            "category":"Building & Trades",
            "subcategory":"Construction",
            "type":"Services"
        }
    ],
    "sg:phone":"+61 8 8297 0199",
    "sg:postcode":"5039",
    "sg:province":"SA",
    "sg:tags":[
        "window",
        "tinting"
    ],
    "wof:name":"United Windscreens",
    "wof:placetype":"venue"
},
  "geometry": {"coordinates":[138.573608398,-34.9787864685],"type":"Point"}
}