{
  "type": "Feature",
  "properties": {
    "addr:full":"Ste11/ 895 Pacific Hwy Pymble NSW 2073",
    "addr:housenumber":"895",
    "addr:postcode":"2073",
    "addr:street":"Pacific Hwy",
    "iso:country":"AU",
    "sg:address":"Ste11/ 895 Pacific Hwy",
    "sg:city":"Pymble",
    "sg:classifiers":[
        {
            "category":"Professional",
            "subcategory":"Engineering",
            "type":"Services"
        }
    ],
    "sg:phone":"+61 2 9440 3844",
    "sg:postcode":"2073",
    "sg:province":"NSW",
    "sg:tags":[
        "electrical",
        "engineer"
    ],
    "wof:name":"Scomac Automation Pty Ltd",
    "wof:placetype":"venue"
},
  "geometry": {"coordinates":[151.14540100100001,-33.7471466064],"type":"Point"}
}