{
  "type": "Feature",
  "properties": {
    "addr:full":"Suite 2, Level 6, 88- 90 Foveaux St Surry Hills NSW 2010",
    "addr:housenumber":"88 90",
    "addr:postcode":"2010",
    "addr:street":"Foveaux St",
    "iso:country":"AU",
    "sg:address":"Suite 2, Level 6, 88- 90 Foveaux St",
    "sg:city":"Surry Hills",
    "sg:classifiers":[
        {
            "category":"Banks & Credit Unions",
            "subcategory":"Bank",
            "type":"Services"
        }
    ],
    "sg:phone":"+61 2 9211 7018",
    "sg:postcode":"2010",
    "sg:province":"NSW",
    "sg:tags":[
        "broker",
        "mortgage"
    ],
    "wof:name":"Gay Finanz Management",
    "wof:placetype":"venue"
},
  "geometry": {"coordinates":[151.21214294399999,-33.884677887],"type":"Point"}
}