{
  "type": "Feature",
  "properties": {
    "addr:full":"19 Bulli St Moorabbin VIC 3189",
    "addr:housenumber":"19",
    "addr:postcode":"3189",
    "addr:street":"Bulli St",
    "iso:country":"AU",
    "sg:address":"19 Bulli St",
    "sg:city":"Moorabbin",
    "sg:classifiers":[
        {
            "category":"Professional",
            "subcategory":"Engineering",
            "type":"Services"
        }
    ],
    "sg:phone":"+61 3 9555 9258",
    "sg:postcode":"3189",
    "sg:province":"VIC",
    "sg:tags":[
        "engineer"
    ],
    "wof:name":"Ebli Engineering",
    "wof:placetype":"venue"
},
  "geometry": {"coordinates":[145.05384826700001,-37.943901062],"type":"Point"}
}