{
  "type": "Feature",
  "properties": {
    "addr:full":"4 Seaview Rd Port Elliot SA 5212",
    "addr:housenumber":"4",
    "addr:postcode":"5212",
    "addr:street":"Seaview Rd",
    "iso:country":"AU",
    "sg:address":"4 Seaview Rd",
    "sg:city":"Port Elliot",
    "sg:classifiers":[
        {
            "category":"Organizations",
            "subcategory":"Non-profit Organization",
            "type":"Services"
        }
    ],
    "sg:phone":"+61 8 8554 2340",
    "sg:postcode":"5212",
    "sg:province":"SA",
    "sg:tags":[
        "support",
        "disability",
        "organisation"
    ],
    "wof:name":"Minda Incorporated",
    "wof:placetype":"venue"
},
  "geometry": {"coordinates":[138.676315308,-35.5344314575],"type":"Point"}
}