{
  "type": "Feature",
  "properties": {
    "addr:full":"7-21 Saber St Woollahra NSW 2025",
    "addr:housenumber":"7-21",
    "addr:postcode":"2025",
    "addr:street":"Saber St",
    "iso:country":"AU",
    "sg:address":"7-21 Saber St",
    "sg:city":"Woollahra",
    "sg:classifiers":[
        {
            "category":"Organizations",
            "subcategory":"Community Association",
            "type":"Services"
        }
    ],
    "sg:phone":"+61 2 9369 3444",
    "sg:postcode":"2025",
    "sg:province":"NSW",
    "sg:tags":[
        "organisation",
        "family",
        "welfare"
    ],
    "wof:name":"Jewish Care",
    "wof:placetype":"venue"
},
  "geometry": {"coordinates":[151.24790954599999,-33.8903465271],"type":"Point"}
}