{
  "type": "Feature",
  "properties": {
    "addr:full":"69 Portrush Rd Payneham SA 5070",
    "addr:housenumber":"69",
    "addr:postcode":"5070",
    "addr:street":"Portrush Rd",
    "iso:country":"AU",
    "sg:address":"69 Portrush Rd",
    "sg:city":"Payneham",
    "sg:classifiers":[
        {
            "category":"Health Services",
            "subcategory":"Doctor",
            "type":"Services"
        }
    ],
    "sg:phone":"+61 8 8363 5022",
    "sg:postcode":"5070",
    "sg:province":"SA",
    "sg:tags":[
        "medical",
        "practitioner"
    ],
    "wof:name":"Jadhav R M",
    "wof:placetype":"venue"
},
  "geometry": {"coordinates":[138.63937377900001,-34.9022293091],"type":"Point"}
}