{
  "type": "Feature",
  "properties": {
    "iso:country":"AU",
    "sg:address":"Ste4/ 872 Albany Hwy",
    "sg:city":"East Victoria Park",
    "sg:classifiers":[
        {
            "category":"Autos & Motor Vehicles",
            "subcategory":"Auto Supplies",
            "type":"Retail Goods"
        }
    ],
    "sg:phone":"+61 8 9355 0484",
    "sg:postcode":"6101",
    "sg:province":"WA",
    "sg:tags":[
        "accessory"
    ],
    "wof:name":"Styled 2 Race Motor Sports",
    "wof:placetype":"venue"
},
  "geometry": {"coordinates":[115.903808594,-31.9853954315],"type":"Point"}
}