{
  "type": "Feature",
  "properties": {
    "addr:full":"97- 99 Melrose Drv Wodonga VIC 3690",
    "addr:housenumber":"99",
    "addr:postcode":"3690",
    "addr:street":"Melrose Drv",
    "iso:country":"AU",
    "sg:address":"97- 99 Melrose Drv",
    "sg:city":"Wodonga",
    "sg:classifiers":[
        {
            "category":"Restaurant",
            "type":"Food & Drink"
        }
    ],
    "sg:phone":"+61 2 6059 4666",
    "sg:postcode":"3690",
    "sg:province":"VIC",
    "wof:name":"Birallee Tavern",
    "wof:placetype":"venue"
},
  "geometry": {"coordinates":[146.86595153799999,-36.1273498535],"type":"Point"}
}