{
  "type": "Feature",
  "properties": {
    "addr:full":"2- 11 Lindaway Pl Tullamarine VIC 3043",
    "addr:housenumber":"11",
    "addr:postcode":"3043",
    "addr:street":"2;Pl",
    "iso:country":"AU",
    "sg:address":"2- 11 Lindaway Pl",
    "sg:city":"Tullamarine",
    "sg:classifiers":[
        {
            "category":"Farming",
            "subcategory":"Farm & Veterinary Services",
            "type":"Manufacturing & Wholesale Goods"
        }
    ],
    "sg:phone":"+61 3 9338 9935",
    "sg:postcode":"3043",
    "sg:province":"VIC",
    "sg:tags":[
        "poultry",
        "processing",
        "supply"
    ],
    "wof:name":"Topline Farm Fresh Chicken",
    "wof:placetype":"venue"
},
  "geometry": {"coordinates":[144.88475036599999,-37.7037811279],"type":"Point"}
}