{
  "type": "Feature",
  "properties": {
    "iso:country":"AU",
    "sg:address":"Abbey Beach Resort 595 Bussell Hwy",
    "sg:city":"Busselton",
    "sg:classifiers":[
        {
            "category":"Arts & Performance",
            "subcategory":"Art Gallery",
            "type":"Entertainment"
        }
    ],
    "sg:phone":"+61 412 423 986",
    "sg:postcode":"6280",
    "sg:province":"WA",
    "wof:name":"Jenny Taylor's Hang Ups Gallery",
    "wof:placetype":"venue"
},
  "geometry": {"coordinates":[115.27451324499999,-33.6601257324],"type":"Point"}
}