{
  "type": "Feature",
  "properties": {
    "addr:full":"13 Main St Osborne Park WA 6017",
    "addr:housenumber":"13",
    "addr:postcode":"6017",
    "addr:street":"Main St",
    "iso:country":"AU",
    "sg:address":"13 Main St",
    "sg:city":"Osborne Park",
    "sg:classifiers":[
        {
            "category":"Retail",
            "subcategory":"Driving School",
            "type":"Services"
        }
    ],
    "sg:phone":"+61 8 9443 3555",
    "sg:postcode":"6017",
    "sg:province":"WA",
    "sg:tags":[
        "defensive",
        "advanced"
    ],
    "wof:name":"Motor Cycle Academy The",
    "wof:placetype":"venue"
},
  "geometry": {"coordinates":[115.82801055900001,-31.9128913879],"type":"Point"}
}