{
  "type": "Feature",
  "properties": {
    "iso:country":"AU",
    "sg:address":"77 Morgan Rd",
    "sg:city":"Seville Grove",
    "sg:classifiers":[
        {
            "category":"Social Services",
            "subcategory":"Child Care",
            "type":"Services"
        }
    ],
    "sg:phone":"+61 8 9497 3030",
    "sg:postcode":"6112",
    "sg:province":"WA",
    "wof:name":"Tiny Town Day Care",
    "wof:placetype":"venue"
},
  "geometry": {"coordinates":[115.99299621599999,-32.1343574524],"type":"Point"}
}