{
  "type": "Feature",
  "properties": {
    "addr:full":"17 Victor St Mt Gambier SA 5290",
    "addr:housenumber":"17",
    "addr:postcode":"5290",
    "addr:street":"Victor St",
    "iso:country":"AU",
    "sg:address":"17 Victor St",
    "sg:city":"Mt Gambier",
    "sg:classifiers":[
        {
            "category":"Farming",
            "subcategory":"Livestock Farm",
            "type":"Manufacturing & Wholesale Goods"
        }
    ],
    "sg:phone":"+61 8 8725 6481",
    "sg:postcode":"5290",
    "sg:province":"SA",
    "sg:tags":[
        "buyer"
    ],
    "wof:name":"King J R & G R",
    "wof:placetype":"venue"
},
  "geometry": {"coordinates":[140.78280599999999,-37.836952],"type":"Point"}
}