{
  "type": "Feature",
  "properties": {
    "addr:full":"993 Stumpy Gully Rd Moorooduc VIC 3933",
    "addr:housenumber":"993",
    "addr:postcode":"3933",
    "addr:street":"Stumpy Gully Rd",
    "iso:country":"AU",
    "sg:address":"993 Stumpy Gully Rd",
    "sg:city":"Moorooduc",
    "sg:classifiers":[
        {
            "category":"Retail",
            "subcategory":"Storage",
            "type":"Services"
        }
    ],
    "sg:phone":"+61 3 5978 8390",
    "sg:postcode":"3933",
    "sg:province":"VIC",
    "sg:tags":[
        "cold"
    ],
    "wof:name":"Karrawingi Park",
    "wof:placetype":"venue"
},
  "geometry": {"coordinates":[145.127029419,-38.2844276428],"type":"Point"}
}