{
  "type": "Feature",
  "properties": {
    "addr:full":"110 Napier St St Arnaud VIC 3478",
    "addr:housenumber":"110",
    "addr:postcode":"3478",
    "addr:street":"Napier St",
    "iso:country":"AU",
    "sg:address":"110 Napier St",
    "sg:city":"St Arnaud",
    "sg:classifiers":[
        {
            "category":"Personal",
            "subcategory":"Beauty Salon",
            "type":"Services"
        }
    ],
    "sg:phone":"+61 3 5495 1306",
    "sg:postcode":"3478",
    "sg:province":"VIC",
    "sg:tags":[
        "hairdresser"
    ],
    "wof:name":"Top Of The Town Beauty Salon",
    "wof:placetype":"venue"
},
  "geometry": {"coordinates":[142.98953247099999,-36.3740768433],"type":"Point"}
}