{
  "type": "Feature",
  "properties": {
    "addr:full":"10 Bradwardine Rd Bathurst NSW 2795",
    "addr:housenumber":"10",
    "addr:postcode":"2795",
    "addr:street":"Bradwardine Rd",
    "iso:country":"AU",
    "sg:address":"10 Bradwardine Rd",
    "sg:city":"Bathurst",
    "sg:classifiers":[
        {
            "category":"Industrial Area",
            "type":"Public Place"
        }
    ],
    "sg:phone":"+61 2 6332 5077",
    "sg:postcode":"2795",
    "sg:province":"NSW",
    "sg:tags":[
        "rural",
        "shed"
    ],
    "wof:name":"Art-Tec National",
    "wof:placetype":"venue"
},
  "geometry": {"coordinates":[149.54380798299999,-33.4153022766],"type":"Point"}
}