{
  "type": "Feature",
  "properties": {
    "addr:full":"21 Gumeracha Rd Lobethal SA 5241",
    "addr:housenumber":"21",
    "addr:postcode":"5241",
    "addr:street":"Gumeracha Rd",
    "iso:country":"AU",
    "sg:address":"21 Gumeracha Rd",
    "sg:city":"Lobethal",
    "sg:classifiers":[
        {
            "category":"Manufacturing",
            "subcategory":"Metals",
            "type":"Manufacturing & Wholesale Goods"
        }
    ],
    "sg:phone":"+61 8 8389 6678",
    "sg:postcode":"5241",
    "sg:province":"SA",
    "sg:tags":[
        "sheet",
        "worker"
    ],
    "wof:name":"Lobethal Sheet Metal",
    "wof:placetype":"venue"
},
  "geometry": {"coordinates":[138.87628173799999,-34.9008102417],"type":"Point"}
}