{
  "type": "Feature",
  "properties": {
    "addr:full":"99 Anderson St Geraldton WA 6530",
    "addr:housenumber":"99",
    "addr:postcode":"6530",
    "addr:street":"Anderson St",
    "iso:country":"AU",
    "sg:address":"99 Anderson St",
    "sg:city":"Geraldton",
    "sg:classifiers":[
        {
            "category":"Industrial Area",
            "type":"Public Place"
        }
    ],
    "sg:phone":"+61 8 9964 3344",
    "sg:postcode":"6530",
    "sg:province":"WA",
    "sg:tags":[
        "rural",
        "shed"
    ],
    "wof:name":"Carimor Sheds",
    "wof:placetype":"venue"
},
  "geometry": {"coordinates":[114.63398742699999,-28.7515258789],"type":"Point"}
}