{
  "type": "Feature",
  "properties": {
    "addr:full":"5 Nundah St Nundah QLD 4012",
    "addr:housenumber":"5",
    "addr:postcode":"4012",
    "addr:street":"Nundah St",
    "iso:country":"AU",
    "sg:address":"5 Nundah St",
    "sg:city":"Nundah",
    "sg:classifiers":[
        {
            "category":"Organizations",
            "subcategory":"Community Association",
            "type":"Services"
        }
    ],
    "sg:phone":"+61 7 3266 5633",
    "sg:postcode":"4012",
    "sg:province":"QLD",
    "sg:tags":[
        "organisation",
        "family",
        "welfare"
    ],
    "wof:name":"Community Living Program",
    "wof:placetype":"venue"
},
  "geometry": {"coordinates":[153.06155395499999,-27.4007911682],"type":"Point"}
}