{
  "type": "Feature",
  "properties": {
    "addr:full":"59 Hector St West Osborne Park WA 6017",
    "addr:housenumber":"59",
    "addr:postcode":"6017",
    "addr:street":"Hector St West",
    "iso:country":"AU",
    "sg:address":"59 Hector St",
    "sg:city":"West Osborne Park",
    "sg:classifiers":[
        {
            "category":"Wholesale",
            "subcategory":"Home Furnishings",
            "type":"Manufacturing & Wholesale Goods"
        }
    ],
    "sg:phone":"+61 1800 142 737",
    "sg:postcode":"6017",
    "sg:province":"WA",
    "sg:tags":[
        "tile",
        "wholesaler",
        "mfrs",
        "carpet"
    ],
    "wof:name":"Redbook Carpets",
    "wof:placetype":"venue"
},
  "geometry": {"coordinates":[115.816429138,-31.9013385773],"type":"Point"}
}