{
  "type": "Feature",
  "properties": {
    "addr:full":"U5/ 3 Nuetron Pl Rowville VIC 3178",
    "addr:postcode":"3178",
    "addr:street":"U5 / 3 Nuetron Pl",
    "iso:country":"AU",
    "sg:address":"U5/ 3 Nuetron Pl",
    "sg:city":"Rowville",
    "sg:classifiers":[
        {
            "category":"Military Area",
            "subcategory":"Air Force Base",
            "type":"Public Place"
        }
    ],
    "sg:phone":"+61 3 9095 6353",
    "sg:postcode":"3178",
    "sg:province":"VIC",
    "sg:tags":[
        "fibre",
        "optic"
    ],
    "wof:name":"Linktech Telecom",
    "wof:placetype":"venue"
},
  "geometry": {"coordinates":[145.24703979500001,-37.9059867859],"type":"Point"}
}