{
  "type": "Feature",
  "properties": {
    "addr:full":"301 Eaglehawk Rd California Gully VIC 3556",
    "addr:housenumber":"301",
    "addr:postcode":"3556",
    "addr:street":"Eaglehawk Rd",
    "iso:country":"AU",
    "sg:address":"301 Eaglehawk Rd",
    "sg:city":"California Gully",
    "sg:classifiers":[
        {
            "category":"Building & Trades",
            "subcategory":"Equipment Rental",
            "type":"Services"
        }
    ],
    "sg:phone":"+61 3 5446 2944",
    "sg:postcode":"3556",
    "sg:province":"VIC",
    "sg:tags":[
        "party",
        "hire"
    ],
    "wof:name":"Eaglehawk Party Hire",
    "wof:placetype":"venue"
},
  "geometry": {"coordinates":[144.25848388700001,-36.7360076904],"type":"Point"}
}