{
  "type": "Feature",
  "properties": {
    "iso:country":"AU",
    "sg:address":"40 Wakaden St",
    "sg:city":"Griffith",
    "sg:classifiers":[
        {
            "category":"Retail",
            "subcategory":"Auto Repair",
            "type":"Services"
        }
    ],
    "sg:phone":"+61 2 6964 6166",
    "sg:postcode":"2680",
    "sg:province":"NSW",
    "sg:tags":[
        "repairer",
        "motor",
        "engineer"
    ],
    "wof:name":"Repco Authorised Service",
    "wof:placetype":"venue"
},
  "geometry": {"coordinates":[146.053589,-34.286213],"type":"Point"}
}