{
  "type": "Feature",
  "properties": {
    "iso:country":"AU",
    "sg:address":"9 Turley St",
    "sg:city":"Raceview",
    "sg:classifiers":[
        {
            "category":"Social Services",
            "subcategory":"Adult Care",
            "type":"Services"
        }
    ],
    "sg:phone":"+61 7 3294 1800",
    "sg:postcode":"4305",
    "sg:province":"QLD",
    "sg:tags":[
        "towing"
    ],
    "wof:name":"S & D Body Works Towing",
    "wof:placetype":"venue"
},
  "geometry": {"coordinates":[152.758712769,-27.6342487335],"type":"Point"}
}