{
  "type": "Feature",
  "properties": {
    "iso:country":"AU",
    "sg:address":"126 Radium St",
    "sg:city":"Welshpool",
    "sg:classifiers":[
        {
            "category":"Retail",
            "subcategory":"Auto Repair",
            "type":"Services"
        }
    ],
    "sg:phone":"+61 8 9451 4236",
    "sg:postcode":"6106",
    "sg:province":"WA",
    "sg:tags":[
        "repairer",
        "motor",
        "engineer"
    ],
    "wof:name":"Langham Auto Engineers",
    "wof:placetype":"venue"
},
  "geometry": {"coordinates":[115.933822632,-31.997543335],"type":"Point"}
}