{
  "type": "Feature",
  "properties": {
    "iso:country":"AU",
    "sg:address":"Tablet House Level 1, 60 Bowman St",
    "sg:city":"Pyrmont",
    "sg:classifiers":[
        {
            "category":"Professional",
            "subcategory":"Art Services",
            "type":"Services"
        }
    ],
    "sg:phone":"+61 2 8514 5100",
    "sg:postcode":"2009",
    "sg:province":"NSW",
    "sg:tags":[
        "graphic",
        "designer"
    ],
    "wof:name":"How Graphic Design Pty Ltd",
    "wof:placetype":"venue"
},
  "geometry": {"coordinates":[151.19056701700001,-33.8669395447],"type":"Point"}
}