{
  "type": "Feature",
  "properties": {
    "addr:full":"105 High St Woodend VIC 3442",
    "addr:housenumber":"105",
    "addr:postcode":"3442",
    "addr:street":"High St",
    "iso:country":"AU",
    "sg:address":"105 High St",
    "sg:city":"Woodend",
    "sg:classifiers":[
        {
            "category":"Personal",
            "subcategory":"Beauty Salon",
            "type":"Services"
        }
    ],
    "sg:phone":"+61 3 5427 3030",
    "sg:postcode":"3442",
    "sg:province":"VIC",
    "sg:tags":[
        "hairdresser"
    ],
    "wof:name":"Bella The Cut & Colour Salon",
    "wof:placetype":"venue"
},
  "geometry": {"coordinates":[144.52859497099999,-37.3550338745],"type":"Point"}
}