{
  "type": "Feature",
  "properties": {
    "addr:full":"4 South Australia One Drv North Haven SA 5018",
    "addr:housenumber":"4",
    "addr:postcode":"5018",
    "addr:street":"One Drv",
    "iso:country":"AU",
    "sg:address":"4 South Australia One Drv",
    "sg:city":"North Haven",
    "sg:classifiers":[
        {
            "category":"Building & Trades",
            "subcategory":"Plumbing",
            "type":"Services"
        }
    ],
    "sg:phone":"+61 413 137 690",
    "sg:postcode":"5018",
    "sg:province":"SA",
    "sg:tags":[
        "plumber",
        "gasfitters"
    ],
    "wof:name":"Tansell R L & J",
    "wof:placetype":"venue"
},
  "geometry": {"coordinates":[138.48434448200001,-34.78150177],"type":"Point"}
}