{
  "type": "Feature",
  "properties": {
    "iso:country":"AU",
    "sg:address":"247 Bay Rd",
    "sg:city":"Sandringham",
    "sg:classifiers":[
        {
            "category":"Personal",
            "subcategory":"Beauty Salon",
            "type":"Services"
        }
    ],
    "sg:phone":"+61 3 9532 3450",
    "sg:postcode":"3191",
    "sg:province":"VIC",
    "wof:name":"Body Deck Tanning & Waxing",
    "wof:placetype":"venue"
},
  "geometry": {"coordinates":[145.03140258799999,-37.9548797607],"type":"Point"}
}