{
  "type": "Feature",
  "properties": {
    "addr:full":"Unit 3 / 20 Fargo Way Welshpool WA 6106",
    "addr:housenumber":"20",
    "addr:postcode":"6106",
    "addr:street":"Fargo Way",
    "iso:country":"AU",
    "sg:address":"Unit 3 / 20",
    "sg:city":"Fargo Way Welshpool",
    "sg:classifiers":[
        {
            "category":"Juice Bar",
            "subcategory":"None",
            "type":"Food & Drink"
        }
    ],
    "sg:phone":"+61 8 9258 6611",
    "sg:postcode":"6106",
    "sg:province":"WA",
    "sg:tags":[
        "merchant",
        "fruit",
        "processor"
    ],
    "wof:name":"Crusta Fruit Juices Pty Ltd",
    "wof:placetype":"venue"
},
  "geometry": {"coordinates":[115.971832275,-31.9975070953],"type":"Point"}
}