{
  "type": "Feature",
  "properties": {
    "addr:full":"Cnr Forest & Stoney Creek Rds Peakhurst NSW 2210",
    "addr:postcode":"2210",
    "addr:street":"Cnr",
    "iso:country":"AU",
    "sg:address":"Cnr Forest & Stoney Creek Rds",
    "sg:city":"Peakhurst",
    "sg:classifiers":[
        {
            "category":"Building & Trades",
            "subcategory":"Construction",
            "type":"Services"
        }
    ],
    "sg:phone":"+61 1300 887 200",
    "sg:postcode":"2210",
    "sg:province":"NSW",
    "sg:tags":[
        "home",
        "air conditioning"
    ],
    "wof:name":"Coral Air Pty Ltd",
    "wof:placetype":"venue"
},
  "geometry": {"coordinates":[151.06845100000001,-33.957676],"type":"Point"}
}