{
  "type": "Feature",
  "properties": {
    "iso:country":"AU",
    "sg:address":"Suite 4, 473 Mulgrave Rd",
    "sg:city":"Earlville",
    "sg:classifiers":[
        {
            "category":"Insurance",
            "subcategory":"Insurance Agent",
            "type":"Services"
        }
    ],
    "sg:phone":"+61 7 4047 8555",
    "sg:postcode":"4870",
    "sg:province":"QLD",
    "sg:tags":[
        "broker"
    ],
    "wof:name":"OAMPS Insurance Brokers Ltd",
    "wof:placetype":"venue"
},
  "geometry": {"coordinates":[145.74104309099999,-16.9415683746],"type":"Point"}
}