{
  "type": "Feature",
  "properties": {
    "iso:country":"AU",
    "sg:address":"1 Elizabeth Ave",
    "sg:city":"Mascot",
    "sg:classifiers":[
        {
            "category":"Military Area",
            "subcategory":"Air Force Base",
            "type":"Public Place"
        }
    ],
    "sg:phone":"+61 2 9666 1099",
    "sg:postcode":"2020",
    "sg:province":"NSW",
    "sg:tags":[
        "box",
        "case",
        "wood"
    ],
    "wof:name":"Handy Case Co Pty Ltd",
    "wof:placetype":"venue"
},
  "geometry": {"coordinates":[151.19380188,-33.9312057495],"type":"Point"}
}