{
  "type": "Feature",
  "properties": {
    "iso:country":"AU",
    "sg:address":"Joalah Ave",
    "sg:city":"Blaxland",
    "sg:classifiers":[
        {
            "category":"Building & Trades",
            "subcategory":"Equipment Rental",
            "type":"Services"
        }
    ],
    "sg:phone":"+61 2 4739 4244",
    "sg:postcode":"2774",
    "sg:province":"NSW",
    "sg:tags":[
        "fitness"
    ],
    "wof:name":"Strathdee Electrical",
    "wof:placetype":"venue"
},
  "geometry": {"coordinates":[150.631393433,-33.7482337952],"type":"Point"}
}