{
  "type": "Feature",
  "properties": {
    "addr:full":"Maggea Rd Waikerie SA 5330",
    "addr:postcode":"5330",
    "addr:street":"Maggea Rd",
    "iso:country":"AU",
    "sg:address":"Maggea Rd",
    "sg:city":"Waikerie",
    "sg:classifiers":[
        {
            "category":"Retail",
            "subcategory":"Animal Services",
            "type":"Services"
        }
    ],
    "sg:phone":"+61 8 8541 2742",
    "sg:postcode":"5330",
    "sg:province":"SA",
    "sg:tags":[
        "breeder",
        "sheep",
        "stud",
        "cattle"
    ],
    "wof:name":"Kroehn P R & K L",
    "wof:placetype":"venue"
},
  "geometry": {"coordinates":[140.00276184099999,-34.189201355],"type":"Point"}
}