{
  "type": "Feature",
  "properties": {
    "addr:full":"3 Millicent St Burwood VIC 3125",
    "addr:housenumber":"3",
    "addr:postcode":"3125",
    "addr:street":"Millicent St",
    "iso:country":"AU",
    "sg:address":"3 Millicent St",
    "sg:city":"Burwood",
    "sg:classifiers":[
        {
            "category":"Professional",
            "subcategory":"Detective & Security Services",
            "type":"Services"
        }
    ],
    "sg:phone":"+61 3 9888 8211",
    "sg:postcode":"3125",
    "sg:province":"VIC",
    "sg:tags":[
        "equipment",
        "window",
        "doors"
    ],
    "wof:name":"Security Doors Bulleen",
    "wof:placetype":"venue"
},
  "geometry": {"coordinates":[145.10231018100001,-37.8509750366],"type":"Point"}
}