{
  "type": "Feature",
  "properties": {
    "addr:full":"Harris Rd Lenswood SA 5240",
    "addr:postcode":"5240",
    "addr:street":"Harris Rd",
    "iso:country":"AU",
    "sg:address":"Harris Rd",
    "sg:city":"Lenswood",
    "sg:classifiers":[
        {
            "category":"Farming",
            "subcategory":"Vineyard",
            "type":"Manufacturing & Wholesale Goods"
        }
    ],
    "sg:phone":"+61 8 8389 8339",
    "sg:postcode":"5240",
    "sg:province":"SA",
    "sg:tags":[
        "winery"
    ],
    "wof:name":"Mt Lofty Ranges Vineyard",
    "wof:placetype":"venue"
},
  "geometry": {"coordinates":[138.81724548299999,-34.9174919128],"type":"Point"}
}