{
  "type": "Feature",
  "properties": {
    "iso:country":"AU",
    "sg:address":"18 Bagotville Rd",
    "sg:city":"Meerschaum Vale",
    "sg:classifiers":[
        {
            "category":"Building & Trades",
            "subcategory":"Landscaping Services",
            "type":"Services"
        }
    ],
    "sg:phone":"+61 2 6683 4601",
    "sg:postcode":"2477",
    "sg:province":"NSW",
    "sg:tags":[
        "designer",
        "landscape",
        "contractor"
    ],
    "wof:name":"Rising Fast Landscapes & Nursery",
    "wof:placetype":"venue"
},
  "geometry": {"coordinates":[153.43214416500001,-28.923412323],"type":"Point"}
}