{
  "type": "Feature",
  "properties": {
    "addr:full":"98 Warrigal Rd Runcorn QLD 4113",
    "addr:housenumber":"98",
    "addr:postcode":"4113",
    "addr:street":"Warrigal Rd",
    "iso:country":"AU",
    "sg:address":"98 Warrigal Rd",
    "sg:city":"Runcorn",
    "sg:classifiers":[
        {
            "category":"Home & Garden",
            "subcategory":"Building Materials",
            "type":"Retail Goods"
        }
    ],
    "sg:phone":"+61 7 3841 4489",
    "sg:postcode":"4113",
    "sg:province":"QLD",
    "sg:tags":[
        "retaining",
        "wall"
    ],
    "wof:name":"Abetta Quality Fencing",
    "wof:placetype":"venue"
},
  "geometry": {"coordinates":[153.08377075199999,-27.5955181122],"type":"Point"}
}