{
  "type": "Feature",
  "properties": {
    "addr:full":"171A Richmond Rd Blacktown NSW 2148",
    "addr:housenumber":"171a",
    "addr:postcode":"2148",
    "addr:street":"Richmond Rd",
    "iso:country":"AU",
    "sg:address":"171A Richmond Rd",
    "sg:city":"Blacktown",
    "sg:classifiers":[
        {
            "category":"Home & Garden",
            "subcategory":"Building Materials",
            "type":"Retail Goods"
        }
    ],
    "sg:phone":"+61 414 392 022",
    "sg:postcode":"2148",
    "sg:province":"NSW",
    "sg:tags":[
        "lawn",
        "cutting",
        "maintenance"
    ],
    "wof:name":"Blacktown City Lawns",
    "wof:placetype":"venue"
},
  "geometry": {"coordinates":[150.90155029300001,-33.7633323669],"type":"Point"}
}