{
  "type": "Feature",
  "properties": {
    "addr:full":"3/31 Victoria Pde Manly NSW 2095",
    "addr:housenumber":"/ 31",
    "addr:postcode":"2095",
    "addr:street":"Victoria Pde",
    "iso:country":"AU",
    "sg:address":"3/31 Victoria Pde",
    "sg:city":"Manly",
    "sg:classifiers":[
        {
            "category":"Personal",
            "type":"Services"
        }
    ],
    "sg:phone":"+61 406 485 495",
    "sg:postcode":"2095",
    "sg:province":"NSW",
    "sg:tags":[
        "reducing",
        "treatment",
        "weight"
    ],
    "wof:name":"Herbalife Manly",
    "wof:placetype":"venue"
},
  "geometry": {"coordinates":[151.288772583,-33.7991600037],"type":"Point"}
}