{
  "type": "Feature",
  "properties": {
    "addr:full":"3 Barrier Reef Drv Robina QLD 4226",
    "addr:housenumber":"3",
    "addr:postcode":"4226",
    "addr:street":"Barrier Reef Drv",
    "iso:country":"AU",
    "sg:address":"3 Barrier Reef Drv",
    "sg:city":"Robina",
    "sg:classifiers":[
        {
            "category":"Home & Garden",
            "subcategory":"Hardware",
            "type":"Retail Goods"
        }
    ],
    "sg:phone":"+61 419 887 886",
    "sg:postcode":"4226",
    "sg:province":"QLD",
    "sg:tags":[
        "battery",
        "dry",
        "rechargeable",
        "cell"
    ],
    "wof:name":"Hayhurst Distributors",
    "wof:placetype":"venue"
},
  "geometry": {"coordinates":[153.419555664,-28.0521621704],"type":"Point"}
}