{
  "type": "Feature",
  "properties": {
    "iso:country":"AU",
    "sg:address":"116 Miller St",
    "sg:city":"North Sydney",
    "sg:classifiers":[
        {
            "category":"Cafe",
            "type":"Food & Drink"
        }
    ],
    "sg:phone":"+61 2 9954 3368",
    "sg:postcode":"2060",
    "sg:province":"NSW",
    "wof:name":"Cafe Yianni",
    "wof:placetype":"venue"
},
  "geometry": {"coordinates":[151.20704650900001,-33.8370513916],"type":"Point"}
}