{
  "type": "Feature",
  "properties": {
    "addr:full":"27 Belford St Broadmeadow NSW 2292",
    "addr:housenumber":"27",
    "addr:postcode":"2292",
    "addr:street":"Belford St",
    "iso:country":"AU",
    "sg:address":"27 Belford St",
    "sg:city":"Broadmeadow",
    "sg:classifiers":[
        {
            "category":"Retail",
            "subcategory":"Funeral Services",
            "type":"Services"
        }
    ],
    "sg:phone":"+61 2 4961 1435",
    "sg:postcode":"2292",
    "sg:province":"NSW",
    "sg:tags":[
        "director"
    ],
    "wof:name":"James Murray Funeral Directors P/L",
    "wof:placetype":"venue"
},
  "geometry": {"coordinates":[151.73797607399999,-32.9243431091],"type":"Point"}
}