{
  "type": "Feature",
  "properties": {
    "addr:full":"River Rd Kingaroy QLD 4610",
    "addr:postcode":"4610",
    "addr:street":"River Rd",
    "iso:country":"AU",
    "sg:address":"River Rd",
    "sg:city":"Kingaroy",
    "sg:classifiers":[
        {
            "category":"Wholesale",
            "subcategory":"Electrical",
            "type":"Manufacturing & Wholesale Goods"
        }
    ],
    "sg:phone":"+61 7 4162 5585",
    "sg:postcode":"4610",
    "sg:province":"QLD",
    "sg:tags":[
        "wholesaler"
    ],
    "wof:name":"Haymans Electrical",
    "wof:placetype":"venue"
},
  "geometry": {"coordinates":[151.83273315400001,-26.5515365601],"type":"Point"}
}