{
  "type": "Feature",
  "properties": {
    "addr:full":"9 Stanmore Rd Stanmore NSW 2048",
    "addr:housenumber":"9",
    "addr:postcode":"2048",
    "addr:street":"Stanmore Rd",
    "iso:country":"AU",
    "sg:address":"9 Stanmore Rd",
    "sg:city":"Stanmore",
    "sg:classifiers":[
        {
            "category":"Real Estate",
            "subcategory":"Real Estate Agent",
            "type":"Services"
        }
    ],
    "sg:phone":"+61 2 9516 1800",
    "sg:postcode":"2048",
    "sg:province":"NSW",
    "wof:name":"Ray White Enmore",
    "wof:placetype":"venue"
},
  "geometry": {"coordinates":[151.16920500000001,-33.898949],"type":"Point"}
}