{
  "type": "Feature",
  "properties": {
    "addr:full":"4/ 3 La Fayette Blv Bibra Lake WA 6163",
    "addr:housenumber":"/ 3",
    "addr:postcode":"6163",
    "addr:street":"La Fayette Blv",
    "iso:country":"AU",
    "sg:address":"4/ 3 La Fayette Blv",
    "sg:city":"Bibra Lake",
    "sg:classifiers":[
        {
            "category":"Education",
            "subcategory":"Vocational School",
            "type":"Public Place"
        }
    ],
    "sg:phone":"+61 8 9418 5929",
    "sg:postcode":"6163",
    "sg:province":"WA",
    "sg:tags":[
        "cake",
        "decorating",
        "decorator"
    ],
    "wof:name":"My Delicious Cake Decorators & Supplies",
    "wof:placetype":"venue"
},
  "geometry": {"coordinates":[115.813782,-32.090302],"type":"Point"}
}