{
  "type": "Feature",
  "properties": {
    "addr:full":"537 Elizabeth St Surry Hills NSW 2010",
    "addr:housenumber":"537",
    "addr:postcode":"2010",
    "addr:street":"Elizabeth St",
    "iso:country":"AU",
    "sg:address":"537 Elizabeth St",
    "sg:city":"Surry Hills",
    "sg:classifiers":[
        {
            "category":"Home & Garden",
            "subcategory":"Hardware",
            "type":"Retail Goods"
        }
    ],
    "sg:phone":"+61 2 9698 2361",
    "sg:postcode":"2010",
    "sg:province":"NSW",
    "sg:tags":[
        "plumber",
        "supply"
    ],
    "wof:name":"Australian & Imported Bathroom Supplies",
    "wof:placetype":"venue"
},
  "geometry": {"coordinates":[151.20791625999999,-33.888633728],"type":"Point"}
}