{
  "type": "Feature",
  "properties": {
    "addr:full":"481 Boundary Rd Richlands QLD 4077",
    "addr:housenumber":"481",
    "addr:postcode":"4077",
    "addr:street":"Boundary Rd",
    "iso:country":"AU",
    "sg:address":"481 Boundary Rd",
    "sg:city":"Richlands",
    "sg:classifiers":[
        {
            "category":"Taxi",
            "type":"Transportation"
        }
    ],
    "sg:phone":"+61 7 3710 4444",
    "sg:postcode":"4077",
    "sg:province":"QLD",
    "sg:tags":[
        "truck"
    ],
    "wof:name":"Amalgamated Taxi Trucks & Logistics Pty Ltd",
    "wof:placetype":"venue"
},
  "geometry": {"coordinates":[152.96366882300001,-27.5749778748],"type":"Point"}
}