{
  "type": "Feature",
  "properties": {
    "addr:full":"Unit 7 571 Old South Head Rd Rose Bay NSW 2029",
    "addr:housenumber":"571",
    "addr:postcode":"2029",
    "addr:street":"Old South Head Rd",
    "iso:country":"AU",
    "sg:address":"Unit 7 571 Old South Head Rd",
    "sg:city":"Rose Bay",
    "sg:classifiers":[
        {
            "category":"Utilities",
            "subcategory":"Electric",
            "type":"Services"
        }
    ],
    "sg:phone":"+61 439 962 673",
    "sg:postcode":"2029",
    "sg:province":"NSW",
    "sg:tags":[
        "electrical",
        "contractor"
    ],
    "wof:name":"Captain Electric",
    "wof:placetype":"venue"
},
  "geometry": {"coordinates":[151.27583313,-33.8707504272],"type":"Point"}
}