{
  "type": "Feature",
  "properties": {
    "addr:full":"Unit 13/ 2 King St Bayswater WA 6053",
    "addr:housenumber":"/ 2",
    "addr:postcode":"6053",
    "addr:street":"King St",
    "iso:country":"AU",
    "sg:address":"Unit 13/ 2 King St",
    "sg:city":"Bayswater",
    "sg:classifiers":[
        {
            "category":"Retail",
            "subcategory":"Auto Repair",
            "type":"Services"
        }
    ],
    "sg:phone":"+61 8 9272 7790",
    "sg:postcode":"6053",
    "sg:province":"WA",
    "sg:tags":[
        "beater",
        "painter",
        "panel"
    ],
    "wof:name":"Car Convert Panel & Paint",
    "wof:placetype":"venue"
},
  "geometry": {"coordinates":[115.915847778,-31.9054069519],"type":"Point"}
}