{
  "type": "Feature",
  "properties": {
    "addr:full":"5958 Maroondah Hwy Alexandra VIC 3714",
    "addr:housenumber":"5958",
    "addr:postcode":"3714",
    "addr:street":"Maroondah Hwy",
    "iso:country":"AU",
    "sg:address":"5958 Maroondah Hwy",
    "sg:city":"Alexandra",
    "sg:classifiers":[
        {
            "category":"Professional",
            "subcategory":"Art Services",
            "type":"Services"
        }
    ],
    "sg:phone":"+61 3 5773 4236",
    "sg:postcode":"3714",
    "sg:province":"VIC",
    "sg:tags":[
        "graphic",
        "designer"
    ],
    "wof:name":"Graph Attack",
    "wof:placetype":"venue"
},
  "geometry": {"coordinates":[145.69192504899999,-37.1957359314],"type":"Point"}
}