{
  "type": "Feature",
  "properties": {
    "addr:full":"PO Box 5679 Brendale QLD 4500",
    "addr:postcode":"4500",
    "iso:country":"AU",
    "sg:address":"PO Box 5679",
    "sg:city":"Brendale",
    "sg:classifiers":[
        {
            "category":"Health Services",
            "subcategory":"Dentist",
            "type":"Services"
        }
    ],
    "sg:phone":"+61 414 694 846",
    "sg:postcode":"4500",
    "sg:province":"QLD",
    "sg:tags":[
        "technician",
        "dental"
    ],
    "wof:name":"Smith's Dental Ceramics",
    "wof:placetype":"venue"
},
  "geometry": {"coordinates":[152.982345581,-27.32695961],"type":"Point"}
}