{
  "type": "Feature",
  "properties": {
    "addr:full":"7 Daniel St Wetherill Park NSW 2164",
    "addr:housenumber":"7",
    "addr:postcode":"2164",
    "addr:street":"Daniel St",
    "iso:country":"AU",
    "sg:address":"7 Daniel St",
    "sg:city":"Wetherill Park",
    "sg:classifiers":[
        {
            "category":"Manufacturing",
            "subcategory":"Wood Products",
            "type":"Manufacturing & Wholesale Goods"
        }
    ],
    "sg:phone":"+61 2 9609 6443",
    "sg:postcode":"2164",
    "sg:province":"NSW",
    "sg:tags":[
        "pallet",
        "platform"
    ],
    "wof:name":"Dupond Industries Pty Ltd",
    "wof:placetype":"venue"
},
  "geometry": {"coordinates":[150.90557861299999,-33.8479347229],"type":"Point"}
}