{
  "type": "Feature",
  "properties": {
    "iso:country":"AU",
    "sg:address":"918 Willandra Ave",
    "sg:city":"Griffith",
    "sg:classifiers":[
        {
            "category":"Manufacturing",
            "subcategory":"Metals",
            "type":"Manufacturing & Wholesale Goods"
        }
    ],
    "sg:phone":"+61 429 444 905",
    "sg:postcode":"2680",
    "sg:province":"NSW",
    "sg:tags":[
        "steel",
        "fabricator",
        "mfrs"
    ],
    "wof:name":"Hall's Mobile Fabrication & Welding",
    "wof:placetype":"venue"
},
  "geometry": {"coordinates":[146.046921,-34.299099],"type":"Point"}
}