{
  "type": "Feature",
  "properties": {
    "iso:country":"AU",
    "sg:address":"175 Hall St",
    "sg:city":"Ardeer",
    "sg:classifiers":[
        {
            "category":"Building & Trades",
            "subcategory":"Plumbing",
            "type":"Services"
        }
    ],
    "sg:phone":"+61 425 809 933",
    "sg:postcode":"3022",
    "sg:province":"VIC",
    "sg:tags":[
        "plumber",
        "gasfitters"
    ],
    "wof:name":"John Paul Plumbing",
    "wof:placetype":"venue"
},
  "geometry": {"coordinates":[144.794144,-37.78968],"type":"Point"}
}