{
  "type": "Feature",
  "properties": {
    "iso:country":"AU",
    "sg:address":"Unit 3, 6- 8 Ralph Black Drv",
    "sg:city":"North Wollongong",
    "sg:classifiers":[
        {
            "category":"Professional",
            "subcategory":"Accounting & Tax Preparation",
            "type":"Services"
        }
    ],
    "sg:phone":"+61 2 4227 2833",
    "sg:postcode":"2500",
    "sg:province":"NSW",
    "sg:tags":[
        "broom",
        "brush"
    ],
    "wof:name":"RapidClean Illawarra",
    "wof:placetype":"venue"
},
  "geometry": {"coordinates":[150.89352400000001,-34.40654],"type":"Point"}
}