{
  "type": "Feature",
  "properties": {
    "iso:country":"AU",
    "sg:address":"8 Dudley Gr",
    "sg:city":"Edithvale",
    "sg:classifiers":[
        {
            "category":"Health Services",
            "subcategory":"Health Practitioner",
            "type":"Services"
        }
    ],
    "sg:phone":"+61 3 9776 2366",
    "sg:postcode":"3196",
    "sg:province":"VIC",
    "sg:tags":[
        "psychologist"
    ],
    "wof:name":"Andrew Remenyi Dr MAPS",
    "wof:placetype":"venue"
},
  "geometry": {"coordinates":[145.10867309599999,-38.0390586853],"type":"Point"}
}