{
  "type": "Feature",
  "properties": {
    "addr:full":"7 Hood St Miranda NSW 2228",
    "addr:housenumber":"7",
    "addr:postcode":"2228",
    "addr:street":"Hood St Miranda",
    "iso:country":"AU",
    "sg:address":"7 Hood St",
    "sg:city":"Miranda",
    "sg:classifiers":[
        {
            "category":"Personal",
            "subcategory":"Beauty Salon",
            "type":"Services"
        }
    ],
    "sg:phone":"+61 2 9524 3003",
    "sg:postcode":"2228",
    "sg:province":"NSW",
    "sg:tags":[
        "hairdresser"
    ],
    "wof:name":"Jo On The Go",
    "wof:placetype":"venue"
},
  "geometry": {"coordinates":[151.099121094,-34.0422058105],"type":"Point"}
}