{
  "type": "Feature",
  "properties": {
    "addr:full":"194 Scarborough Beach Rd Mt Hawthorn WA 6016",
    "addr:housenumber":"194",
    "addr:postcode":"6016",
    "addr:street":"Scarborough Beach Rd",
    "iso:country":"AU",
    "sg:address":"194 Scarborough Beach Rd",
    "sg:city":"Mt Hawthorn",
    "sg:classifiers":[
        {
            "category":"Shopping",
            "subcategory":"Baby Store",
            "type":"Retail Goods"
        }
    ],
    "sg:phone":"+61 8 9355 5965",
    "sg:postcode":"6016",
    "sg:province":"WA",
    "sg:tags":[
        "children's",
        "wear"
    ],
    "wof:name":"Cheeky Kids Wear",
    "wof:placetype":"venue"
},
  "geometry": {"coordinates":[115.83602142300001,-31.9198112488],"type":"Point"}
}