{
  "type": "Feature",
  "properties": {
    "addr:full":"16 Reid St Bayswater VIC 3153",
    "addr:housenumber":"16",
    "addr:postcode":"3153",
    "addr:street":"Reid St",
    "iso:country":"AU",
    "sg:address":"16 Reid St",
    "sg:city":"Bayswater",
    "sg:classifiers":[
        {
            "category":"Manufacturing",
            "subcategory":"Tools & Machinery",
            "type":"Manufacturing & Wholesale Goods"
        }
    ],
    "sg:phone":"+61 3 9762 7044",
    "sg:postcode":"3153",
    "sg:province":"VIC",
    "sg:tags":[
        "toolmaker"
    ],
    "wof:name":"Dalin Tooling Pty Ltd",
    "wof:placetype":"venue"
},
  "geometry": {"coordinates":[145.28126525900001,-37.8498954773],"type":"Point"}
}