{
  "type": "Feature",
  "properties": {
    "iso:country":"AU",
    "sg:address":"10 Nelson Ave",
    "sg:city":"Padstow",
    "sg:classifiers":[
        {
            "category":"Building & Trades",
            "subcategory":"Plumbing",
            "type":"Services"
        }
    ],
    "sg:phone":"+61 2 9708 5666",
    "sg:postcode":"2211",
    "sg:province":"NSW",
    "sg:tags":[
        "plumber",
        "gasfitters"
    ],
    "wof:name":"Axis Plumbing Pty Ltd",
    "wof:placetype":"venue"
},
  "geometry": {"coordinates":[151.028336,-33.936798],"type":"Point"}
}