{
  "type": "Feature",
  "properties": {
    "iso:country":"AU",
    "sg:address":"7 Tointon St",
    "sg:city":"Toowoomba",
    "sg:classifiers":[
        {
            "category":"Government",
            "subcategory":"Fire Station",
            "type":"Public Place"
        }
    ],
    "sg:phone":"+61 7 4632 6747",
    "sg:postcode":"4350",
    "sg:province":"QLD",
    "sg:tags":[
        "equipment",
        "protection",
        "consultant"
    ],
    "wof:name":"Sunstate Fire Protection",
    "wof:placetype":"venue"
},
  "geometry": {"coordinates":[151.94560200000001,-27.565195],"type":"Point"}
}