{
  "type": "Feature",
  "properties": {
    "iso:country":"AU",
    "sg:address":"744 Darling St",
    "sg:city":"Rozelle",
    "sg:classifiers":[
        {
            "category":"Fast Food",
            "type":"Food & Drink"
        }
    ],
    "sg:phone":"+61 2 9810 5711",
    "sg:postcode":"2039",
    "sg:province":"NSW",
    "sg:tags":[
        "away",
        "take"
    ],
    "wof:name":"Pizza Haven Delivery",
    "wof:placetype":"venue"
},
  "geometry": {"coordinates":[151.16807556099999,-33.865272522],"type":"Point"}
}