{
  "type": "Feature",
  "properties": {
    "addr:full":"6 Braddock Pl Baulkham Hills NSW 2153",
    "addr:housenumber":"6",
    "addr:postcode":"2153",
    "addr:street":"Braddock Pl",
    "iso:country":"AU",
    "sg:address":"6 Braddock Pl",
    "sg:city":"Baulkham Hills",
    "sg:classifiers":[
        {
            "category":"Organizations",
            "subcategory":"Professional Association",
            "type":"Services"
        }
    ],
    "sg:phone":"+61 2 9686 8256",
    "sg:postcode":"2153",
    "sg:province":"NSW",
    "sg:tags":[
        "web",
        "internet"
    ],
    "wof:name":"Damn Dog Web Solutions",
    "wof:placetype":"venue"
},
  "geometry": {"coordinates":[150.99656677199999,-33.7695808411],"type":"Point"}
}