{
  "type": "Feature",
  "properties": {
    "addr:full":"Rd Gymea Bay NSW 2227",
    "addr:postcode":"2227",
    "addr:street":"Rd",
    "iso:country":"AU",
    "sg:address":"Rd",
    "sg:city":"Gymea Bay",
    "sg:classifiers":[
        {
            "category":"Restaurant",
            "type":"Food & Drink"
        }
    ],
    "sg:phone":"+61 2 9524 9004",
    "sg:postcode":"2227",
    "sg:province":"NSW",
    "wof:name":"Caruso's Gourmet Pizza & Italian Restaurant",
    "wof:placetype":"venue"
},
  "geometry": {"coordinates":[151.087692261,-34.0421791077],"type":"Point"}
}