{
  "type": "Feature",
  "properties": {
    "addr:full":"Cnr Samford Rd & Arbor St Ferny Grove QLD 4055",
    "addr:postcode":"4055",
    "addr:street":"Cnr Samford Rd & Arbor St",
    "iso:country":"AU",
    "sg:address":"Cnr Samford Rd & Arbor St",
    "sg:city":"Ferny Grove",
    "sg:classifiers":[
        {
            "category":"Autos & Motor Vehicles",
            "subcategory":"Fuel & Gas Station",
            "type":"Retail Goods"
        }
    ],
    "sg:phone":"+61 7 3351 4460",
    "sg:postcode":"4055",
    "sg:province":"QLD",
    "wof:name":"BP",
    "wof:placetype":"venue"
},
  "geometry": {"coordinates":[152.936737061,-27.401512146],"type":"Point"}
}