{
  "type": "Feature",
  "properties": {
    "addr:full":"37 Hargreaves St Edmonton QLD 4869",
    "addr:housenumber":"37",
    "addr:postcode":"4869",
    "addr:street":"Hargreaves St",
    "iso:country":"AU",
    "sg:address":"37 Hargreaves St",
    "sg:city":"Edmonton",
    "sg:classifiers":[
        {
            "category":"Wholesale",
            "subcategory":"Farm Supplies",
            "type":"Manufacturing & Wholesale Goods"
        }
    ],
    "sg:phone":"+61 7 4045 1140",
    "sg:postcode":"4869",
    "sg:province":"QLD",
    "sg:tags":[
        "feed",
        "supplement",
        "stock"
    ],
    "wof:name":"NQ Stockfeeds & Farm Supplies",
    "wof:placetype":"venue"
},
  "geometry": {"coordinates":[145.7447052,-17.0006217957],"type":"Point"}
}