{
  "type": "Feature",
  "properties": {
    "iso:country":"AU",
    "sg:address":"18 Beveridge St",
    "sg:city":"Swan Hill",
    "sg:classifiers":[
        {
            "category":"Social Services",
            "subcategory":"Adult Care",
            "type":"Services"
        }
    ],
    "sg:phone":"+61 3 5033 1740",
    "sg:postcode":"3585",
    "sg:province":"VIC",
    "sg:tags":[
        "aged"
    ],
    "wof:name":"Aged Care Assessment Service",
    "wof:placetype":"venue"
},
  "geometry": {"coordinates":[143.55699200000001,-35.335777],"type":"Point"}
}