{
  "type": "Feature",
  "properties": {
    "iso:country":"AU",
    "sg:address":"1731 Albany Hwy",
    "sg:city":"Kenwick",
    "sg:classifiers":[
        {
            "category":"Building & Trades",
            "subcategory":"Locksmith",
            "type":"Services"
        }
    ],
    "sg:phone":"+61 8 9493 2204",
    "sg:postcode":"6107",
    "sg:province":"WA",
    "sg:tags":[
        "lock"
    ],
    "wof:name":"Western Lockservice",
    "wof:placetype":"venue"
},
  "geometry": {"coordinates":[115.972183227,-32.0416069031],"type":"Point"}
}