{
  "type": "Feature",
  "properties": {
    "addr:full":"2690 Albany Hwy Kelmscott WA 6111",
    "addr:housenumber":"2690",
    "addr:postcode":"6111",
    "addr:street":"Albany Hwy",
    "iso:country":"AU",
    "sg:address":"2690 Albany Hwy",
    "sg:city":"Kelmscott",
    "sg:classifiers":[
        {
            "category":"Manufacturing",
            "subcategory":"Signs",
            "type":"Manufacturing & Wholesale Goods"
        }
    ],
    "sg:phone":"+61 8 9390 9609",
    "sg:postcode":"6111",
    "sg:province":"WA",
    "sg:tags":[
        "traffic",
        "safety"
    ],
    "wof:name":"Signs Of Safety",
    "wof:placetype":"venue"
},
  "geometry": {"coordinates":[116.018226623,-32.1242485046],"type":"Point"}
}