{
  "type": "Feature",
  "properties": {
    "addr:full":"8 Hakea St Kambalda WA 6442",
    "addr:housenumber":"8",
    "addr:postcode":"6442",
    "addr:street":"Hakea St",
    "iso:country":"AU",
    "sg:address":"8 Hakea St",
    "sg:city":"Kambalda",
    "sg:classifiers":[
        {
            "category":"Professional",
            "subcategory":"Art Services",
            "type":"Services"
        }
    ],
    "sg:phone":"+61 8 9027 0801",
    "sg:postcode":"6442",
    "sg:province":"WA",
    "sg:tags":[
        "graphic",
        "designer"
    ],
    "wof:name":"Digital Effects",
    "wof:placetype":"venue"
},
  "geometry": {"coordinates":[121.619537353,-31.2116241455],"type":"Point"}
}