{
  "type": "Feature",
  "properties": {
    "addr:full":"70 Pink Lake Rd Esperance WA 6450",
    "addr:housenumber":"70",
    "addr:postcode":"6450",
    "addr:street":"Pink Lake Rd",
    "iso:country":"AU",
    "sg:address":"70 Pink Lake Rd",
    "sg:city":"Esperance",
    "sg:classifiers":[
        {
            "category":"Autos & Motor Vehicles",
            "subcategory":"Fuel & Gas Station",
            "type":"Retail Goods"
        }
    ],
    "sg:phone":"+61 8 9071 1805",
    "sg:postcode":"6450",
    "sg:province":"WA",
    "wof:name":"Caltex",
    "wof:placetype":"venue"
},
  "geometry": {"coordinates":[121.88053893999999,-33.8596305847],"type":"Point"}
}