{
  "type": "Feature",
  "properties": {
    "iso:country":"AU",
    "sg:address":"49 McCallum St",
    "sg:city":"Swan Hill",
    "sg:classifiers":[
        {
            "category":"Organizations",
            "subcategory":"Non-profit Organization",
            "type":"Services"
        }
    ],
    "sg:phone":"+61 417 350 585",
    "sg:postcode":"3585",
    "sg:province":"NSW",
    "sg:tags":[
        "support",
        "disability",
        "organisation"
    ],
    "wof:name":"R.V.I.B (Royal Victorian Institute For The Blind)",
    "wof:placetype":"venue"
},
  "geometry": {"coordinates":[143.558975,-35.338943],"type":"Point"}
}