{
  "type": "Feature",
  "properties": {
    "addr:full":"5 Black Crt Toowoomba QLD 4352",
    "addr:housenumber":"5",
    "addr:postcode":"4352",
    "addr:street":"Black Crt",
    "iso:country":"AU",
    "sg:address":"5 Black Crt",
    "sg:city":"Toowoomba",
    "sg:classifiers":[
        {
            "category":"Professional",
            "subcategory":"Art Services",
            "type":"Services"
        }
    ],
    "sg:phone":"+61 7 4633 2839",
    "sg:postcode":"4352",
    "sg:province":"QLD",
    "sg:tags":[
        "decorator",
        "painter"
    ],
    "wof:name":"Dowling K",
    "wof:placetype":"venue"
},
  "geometry": {"coordinates":[151.90785199999999,-27.53562],"type":"Point"}
}