{
  "type": "Feature",
  "properties": {
    "iso:country":"AU",
    "sg:address":"117 Loftus Ave",
    "sg:city":"Loftus",
    "sg:classifiers":[
        {
            "category":"Autos & Motor Vehicles",
            "subcategory":"Fuel & Gas Station",
            "type":"Retail Goods"
        }
    ],
    "sg:phone":"+61 2 9521 5017",
    "sg:postcode":"2232",
    "sg:province":"NSW",
    "wof:name":"Freedom Fuel Loftus",
    "wof:placetype":"venue"
},
  "geometry": {"coordinates":[151.05091857900001,-34.045589447],"type":"Point"}
}