{
  "type": "Feature",
  "properties": {
    "addr:full":"Shop 75 Cnr. Whitford & Marmion Ave Hillarys WA 6025",
    "addr:housenumber":"shop 75",
    "addr:postcode":"6025",
    "addr:street":"Cnr. Whitford & Marmion Ave",
    "iso:country":"AU",
    "sg:address":"Shop 75 Cnr. Whitford & Marmion Ave",
    "sg:city":"Hillarys",
    "sg:classifiers":[
        {
            "category":"Retail",
            "subcategory":"Repair Shop",
            "type":"Services"
        }
    ],
    "sg:phone":"+61 8 9402 5047",
    "sg:postcode":"6025",
    "sg:province":"WA",
    "sg:tags":[
        "handbag"
    ],
    "wof:name":"Kays Bag Store",
    "wof:placetype":"venue"
},
  "geometry": {"coordinates":[115.755699158,-31.8075447083],"type":"Point"}
}