{
  "type": "Feature",
  "properties": {
    "addr:full":"137 Gillies St South Ballarat VIC 3350",
    "addr:housenumber":"137",
    "addr:postcode":"3350",
    "addr:street":"Gillies St South",
    "iso:country":"AU",
    "sg:address":"137 Gillies St South",
    "sg:city":"Ballarat",
    "sg:classifiers":[
        {
            "category":"Shopping",
            "type":"Retail Goods"
        }
    ],
    "sg:phone":"+61 3 5334 1030",
    "sg:postcode":"3350",
    "sg:province":"VIC",
    "sg:tags":[
        "agent",
        "stock"
    ],
    "wof:name":"Landmark Operations Limited",
    "wof:placetype":"venue"
},
  "geometry": {"coordinates":[143.81625399999999,-37.568382],"type":"Point"}
}