{
  "type": "Feature",
  "properties": {
    "iso:country":"AU",
    "sg:address":"Unit 4 35 Qantas Drv",
    "sg:city":"Brisbane Airport",
    "sg:classifiers":[
        {
            "category":"Airline",
            "type":"Transportation"
        }
    ],
    "sg:phone":"+61 7 3860 5855",
    "sg:postcode":"4007",
    "sg:province":"QLD",
    "sg:tags":[
        "agent"
    ],
    "wof:name":"Pel-Air Express",
    "wof:placetype":"venue"
},
  "geometry": {"coordinates":[153.096313,-27.410807],"type":"Point"}
}