{
  "type": "Feature",
  "properties": {
    "addr:full":"18 Adrian Pl Balgowlah Heights NSW 2093",
    "addr:housenumber":"18",
    "addr:postcode":"2093",
    "addr:street":"Adrian Pl",
    "iso:country":"AU",
    "sg:address":"18 Adrian Pl",
    "sg:city":"Balgowlah Heights",
    "sg:classifiers":[
        {
            "category":"Building & Trades",
            "subcategory":"Cleaning & Sanitation",
            "type":"Services"
        }
    ],
    "sg:phone":"+61 2 9948 6800",
    "sg:postcode":"2093",
    "sg:province":"NSW",
    "sg:tags":[
        "industrial",
        "commercial",
        "contractor"
    ],
    "wof:name":"ProCoustic Australia Pty Ltd",
    "wof:placetype":"venue"
},
  "geometry": {"coordinates":[151.260787964,-33.8076210022],"type":"Point"}
}