{
  "type": "Feature",
  "properties": {
    "addr:full":"PO Box 54 Glenroy VIC 3046",
    "addr:postcode":"3046",
    "iso:country":"AU",
    "sg:address":"PO Box 54",
    "sg:city":"Glenroy",
    "sg:classifiers":[
        {
            "category":"Manufacturing",
            "subcategory":"Building Materials",
            "type":"Manufacturing & Wholesale Goods"
        }
    ],
    "sg:phone":"+61 409 213 142",
    "sg:postcode":"3046",
    "sg:province":"VIC",
    "sg:tags":[
        "stone",
        "product",
        "supply"
    ],
    "wof:name":"New Zealand Rock & Stone",
    "wof:placetype":"venue"
},
  "geometry": {"coordinates":[144.920288086,-37.7054786682],"type":"Point"}
}