{
  "type": "Feature",
  "properties": {
    "addr:full":"Shop 46 Richmond Marketplace Medical Centre 78 March St Richmond NSW 2753",
    "addr:housenumber":"shop 46;78",
    "addr:postcode":"2753",
    "addr:street":"Richmond;March St",
    "iso:country":"AU",
    "sg:address":"Shop 46 Richmond Marketplace Medical Centre 78 March St",
    "sg:city":"Richmond",
    "sg:classifiers":[
        {
            "category":"Health Services",
            "subcategory":"Chiropractor",
            "type":"Services"
        }
    ],
    "sg:phone":"+61 2 4578 4800",
    "sg:postcode":"2753",
    "sg:province":"NSW",
    "wof:name":"Spinal & Sports Injury Specialists",
    "wof:placetype":"venue"
},
  "geometry": {"coordinates":[150.752853394,-33.5997428894],"type":"Point"}
}