{
  "type": "Feature",
  "properties": {
    "addr:full":"101 Beenleigh Rd Acacia Ridge QLD 4110",
    "addr:housenumber":"101",
    "addr:postcode":"4110",
    "addr:street":"Beenleigh Rd",
    "iso:country":"AU",
    "sg:address":"101 Beenleigh Rd",
    "sg:city":"Acacia Ridge",
    "sg:classifiers":[
        {
            "category":"Commercial Area",
            "type":"Public Place"
        }
    ],
    "sg:phone":"+61 7 3344 7400",
    "sg:postcode":"4110",
    "sg:province":"QLD",
    "sg:tags":[
        "heavy",
        "carrier"
    ],
    "wof:name":"Blue Star Logistics",
    "wof:placetype":"venue"
},
  "geometry": {"coordinates":[153.037963867,-27.5745582581],"type":"Point"}
}