{
  "type": "Feature",
  "properties": {
    "addr:full":"9 Banksia St Dee Why NSW 2099",
    "addr:housenumber":"9",
    "addr:postcode":"2099",
    "addr:street":"Banksia St",
    "iso:country":"AU",
    "sg:address":"9 Banksia St",
    "sg:city":"Dee Why",
    "sg:classifiers":[
        {
            "category":"Building & Trades",
            "subcategory":"Construction",
            "type":"Services"
        }
    ],
    "sg:phone":"+61 2 9972 0985",
    "sg:postcode":"2099",
    "sg:province":"NSW",
    "sg:tags":[
        "contractor"
    ],
    "wof:name":"Billabong Constructions & Developments Pty Ltd",
    "wof:placetype":"venue"
},
  "geometry": {"coordinates":[151.29493713400001,-33.758102417],"type":"Point"}
}