{
  "type": "Feature",
  "properties": {
    "addr:full":"648 Toorak Rd Toorak VIC 3142",
    "addr:housenumber":"648",
    "addr:postcode":"3142",
    "addr:street":"Toorak Rd",
    "iso:country":"AU",
    "sg:address":"648 Toorak Rd",
    "sg:city":"Toorak",
    "sg:classifiers":[
        {
            "category":"Personal",
            "type":"Services"
        }
    ],
    "sg:phone":"+61 3 9824 7699",
    "sg:postcode":"3142",
    "sg:province":"VIC",
    "sg:tags":[
        "dressmaker"
    ],
    "wof:name":"Denise Luk Designer Dressmaker",
    "wof:placetype":"venue"
},
  "geometry": {"coordinates":[145.02879333499999,-37.8435630798],"type":"Point"}
}