{
  "type": "Feature",
  "properties": {
    "addr:full":"Shop 4, Cnr Green Wattle St & Glenvale Rd Toowoomba QLD 4350",
    "addr:housenumber":"shop 4",
    "addr:postcode":"4350",
    "addr:street":"Cnr Green Wattle St & Glenvale Rd",
    "iso:country":"AU",
    "sg:address":"Shop 4, Cnr Green Wattle St & Glenvale Rd",
    "sg:city":"Toowoomba",
    "sg:classifiers":[
        {
            "category":"Food & Beverages",
            "subcategory":"Liquor & Beverages",
            "type":"Retail Goods"
        }
    ],
    "sg:phone":"+61 7 4633 4103",
    "sg:postcode":"4350",
    "sg:province":"QLD",
    "sg:tags":[
        "store"
    ],
    "wof:name":"Wilsonton Hotel",
    "wof:placetype":"venue"
},
  "geometry": {"coordinates":[151.88623000000001,-27.560198],"type":"Point"}
}