{
  "type": "Feature",
  "properties": {
    "iso:country":"AU",
    "sg:address":"10 Powys Drv",
    "sg:city":"Beaumaris",
    "sg:classifiers":[
        {
            "category":"Wholesale",
            "subcategory":"Music Publishers",
            "type":"Manufacturing & Wholesale Goods"
        }
    ],
    "sg:phone":"+61 3 9583 0881",
    "sg:postcode":"3193",
    "sg:province":"VIC",
    "sg:tags":[
        "wholesaler",
        "dvd",
        "mfrs",
        "cd"
    ],
    "wof:name":"Strictly Country Records Australia",
    "wof:placetype":"venue"
},
  "geometry": {"coordinates":[145.046707153,-37.9858055115],"type":"Point"}
}