{
  "type": "Feature",
  "properties": {
    "addr:full":"Gurwood St Wagga Wagga NSW 2650",
    "addr:postcode":"2650",
    "addr:street":"St",
    "iso:country":"AU",
    "sg:address":"Gurwood St",
    "sg:city":"Wagga Wagga",
    "sg:classifiers":[
        {
            "category":"Food & Beverages",
            "subcategory":"Liquor & Beverages",
            "type":"Retail Goods"
        }
    ],
    "sg:phone":"+61 2 6921 6200",
    "sg:postcode":"2650",
    "sg:province":"NSW",
    "sg:tags":[
        "store"
    ],
    "wof:name":"Macs Liquor",
    "wof:placetype":"venue"
},
  "geometry": {"coordinates":[147.352249145,-35.1113319397],"type":"Point"}
}