{
  "type": "Feature",
  "properties": {
    "addr:full":"Nelson Crs East Perth WA 6004",
    "addr:postcode":"6004",
    "addr:street":"Nelson Crs East",
    "iso:country":"AU",
    "sg:address":"Nelson Crs",
    "sg:city":"East Perth",
    "sg:classifiers":[
        {
            "category":"Conference Center",
            "type":"Public Place"
        }
    ],
    "sg:phone":"+61 8 9265 7288",
    "sg:postcode":"6004",
    "sg:province":"WA",
    "sg:tags":[
        "venue",
        "convention"
    ],
    "wof:name":"W.A.C.A",
    "wof:placetype":"venue"
},
  "geometry": {"coordinates":[115.877098084,-31.9540901184],"type":"Point"}
}