{
  "type": "Feature",
  "properties": {
    "addr:full":"U1/ 16 Metroplex Ave Murarrie QLD 4172",
    "addr:postcode":"4172",
    "addr:street":"U1 / 16 Metroplex Ave",
    "iso:country":"AU",
    "sg:address":"U1/ 16 Metroplex Ave",
    "sg:city":"Murarrie",
    "sg:classifiers":[
        {
            "category":"Building & Trades",
            "subcategory":"Construction",
            "type":"Services"
        }
    ],
    "sg:phone":"+61 7 3899 8511",
    "sg:postcode":"4172",
    "sg:province":"QLD",
    "sg:tags":[
        "contractor"
    ],
    "wof:name":"Franciswhite Constructions",
    "wof:placetype":"venue"
},
  "geometry": {"coordinates":[153.09918212900001,-27.4549160004],"type":"Point"}
}