{
  "type": "Feature",
  "properties": {
    "addr:full":"130 Moreland Rd Footscray VIC 3011",
    "addr:housenumber":"130",
    "addr:postcode":"3011",
    "addr:street":"Moreland Rd",
    "iso:country":"AU",
    "sg:address":"130 Moreland Rd",
    "sg:city":"Footscray",
    "sg:classifiers":[
        {
            "category":"Autos & Motor Vehicles",
            "subcategory":"Automobile Sales",
            "type":"Retail Goods"
        }
    ],
    "sg:phone":"+61 3 9687 9933",
    "sg:postcode":"3011",
    "sg:province":"VIC",
    "sg:tags":[
        "car",
        "used"
    ],
    "wof:name":"Tony's Car Sales",
    "wof:placetype":"venue"
},
  "geometry": {"coordinates":[144.90809631400001,-37.7995872498],"type":"Point"}
}