{
  "type": "Feature",
  "properties": {
    "addr:full":"Beardmore Pl St George QLD 4487",
    "addr:postcode":"4487",
    "addr:street":"Beardmore Pl",
    "iso:country":"AU",
    "sg:address":"Beardmore Pl St",
    "sg:city":"George",
    "sg:classifiers":[
        {
            "category":"Building & Trades",
            "subcategory":"Construction",
            "type":"Services"
        }
    ],
    "sg:phone":"+61 7 4625 5535",
    "sg:postcode":"4487",
    "sg:province":"QLD",
    "sg:tags":[
        "welding"
    ],
    "wof:name":"Cruse Fab",
    "wof:placetype":"venue"
},
  "geometry": {"coordinates":[148.58003234899999,-28.0352191925],"type":"Point"}
}