{
  "type": "Feature",
  "properties": {
    "iso:country":"AU",
    "sg:address":"126 Alexandra Pde",
    "sg:city":"Alexandra Headland",
    "sg:classifiers":[
        {
            "category":"Building & Trades",
            "subcategory":"Landscaping Services",
            "type":"Services"
        }
    ],
    "sg:phone":"+61 7 5443 3200",
    "sg:postcode":"4572",
    "sg:province":"QLD",
    "sg:tags":[
        "architect",
        "landscape"
    ],
    "wof:name":"Blackburne Jackson Design",
    "wof:placetype":"venue"
},
  "geometry": {"coordinates":[153.105774,-26.665854],"type":"Point"}
}