{
  "type": "Feature",
  "properties": {
    "addr:full":"148 Warrigal Rd Mentone VIC 3194",
    "addr:housenumber":"148",
    "addr:postcode":"3194",
    "addr:street":"Warrigal Rd",
    "iso:country":"AU",
    "sg:address":"148 Warrigal Rd",
    "sg:city":"Mentone",
    "sg:classifiers":[
        {
            "category":"Utilities",
            "subcategory":"Electric",
            "type":"Services"
        }
    ],
    "sg:phone":"+61 409 197 342",
    "sg:postcode":"3194",
    "sg:province":"VIC",
    "sg:tags":[
        "electrical",
        "contractor"
    ],
    "wof:name":"Peter Nowak",
    "wof:placetype":"venue"
},
  "geometry": {"coordinates":[145.072067261,-37.9793586731],"type":"Point"}
}