{
  "type": "Feature",
  "properties": {
    "addr:full":"12 Bunora Ave Ferny Hills QLD 4055",
    "addr:housenumber":"12",
    "addr:postcode":"4055",
    "addr:street":"Bunora Ave",
    "iso:country":"AU",
    "sg:address":"12 Bunora Ave",
    "sg:city":"Ferny Hills",
    "sg:classifiers":[
        {
            "category":"Education",
            "subcategory":"Music School",
            "type":"Public Place"
        }
    ],
    "sg:phone":"+61 7 3351 6928",
    "sg:postcode":"4055",
    "sg:province":"QLD",
    "sg:tags":[
        "teacher"
    ],
    "wof:name":"Busteed Ruth",
    "wof:placetype":"venue"
},
  "geometry": {"coordinates":[152.942871094,-27.3959674835],"type":"Point"}
}