{
  "type": "Feature",
  "properties": {
    "iso:country":"AU",
    "sg:address":"17 Flinders St",
    "sg:city":"Taree",
    "sg:classifiers":[
        {
            "category":"Real Estate",
            "subcategory":"Real Estate Operator",
            "type":"Services"
        }
    ],
    "sg:phone":"+61 417 662 685",
    "sg:postcode":"2430",
    "sg:province":"NSW",
    "sg:tags":[
        "concrete",
        "pumping"
    ],
    "wof:name":"Australian Holiday Coast Concrete Pumping",
    "wof:placetype":"venue"
},
  "geometry": {"coordinates":[152.477875,-31.893715],"type":"Point"}
}