{
  "type": "Feature",
  "properties": {
    "iso:country":"AU",
    "sg:address":"80 Wilton Park Rd",
    "sg:city":"Wilton",
    "sg:classifiers":[
        {
            "category":"Building & Trades",
            "subcategory":"Construction",
            "type":"Services"
        }
    ],
    "sg:phone":"+61 2 4630 9375",
    "sg:postcode":"2571",
    "sg:province":"NSW",
    "sg:tags":[
        "fencing",
        "contractor"
    ],
    "wof:name":"Douglas Park Town & Country Fencing",
    "wof:placetype":"venue"
},
  "geometry": {"coordinates":[150.65496826200001,-34.226020813],"type":"Point"}
}