{
  "type": "Feature",
  "properties": {
    "addr:full":"10 Outlook Drv Edgewater WA 6027",
    "addr:housenumber":"10",
    "addr:postcode":"6027",
    "addr:street":"Outlook Drv",
    "iso:country":"AU",
    "sg:address":"10 Outlook Drv",
    "sg:city":"Edgewater",
    "sg:classifiers":[
        {
            "category":"Professional",
            "subcategory":"Detective & Security Services",
            "type":"Services"
        }
    ],
    "sg:phone":"+61 411 223 171",
    "sg:postcode":"6027",
    "sg:province":"WA",
    "sg:tags":[
        "investigator"
    ],
    "wof:name":"Domestic Detective",
    "wof:placetype":"venue"
},
  "geometry": {"coordinates":[115.782203674,-31.7638683319],"type":"Point"}
}