{
  "type": "Feature",
  "properties": {
    "addr:full":"13 Ellard Ave Belmont WA 6104",
    "addr:housenumber":"13",
    "addr:postcode":"6104",
    "addr:street":"Ellard Ave",
    "iso:country":"AU",
    "sg:address":"13 Ellard Ave",
    "sg:city":"Belmont",
    "sg:classifiers":[
        {
            "category":"Personal",
            "type":"Services"
        }
    ],
    "sg:phone":"+61 8 9478 2837",
    "sg:postcode":"6104",
    "sg:province":"WA",
    "sg:tags":[
        "dressmaker"
    ],
    "wof:name":"Cullen J",
    "wof:placetype":"venue"
},
  "geometry": {"coordinates":[115.93982696499999,-31.9491291046],"type":"Point"}
}