{
  "type": "Feature",
  "properties": {
    "addr:full":"548 Frankston-Dandenong Rd Carrum Downs VIC 3201",
    "addr:housenumber":"548",
    "addr:postcode":"3201",
    "addr:street":"Frankston-Dandenong Rd",
    "iso:country":"AU",
    "sg:address":"548 Frankston-Dandenong Rd",
    "sg:city":"Carrum Downs",
    "sg:classifiers":[
        {
            "category":"Home & Garden",
            "subcategory":"Hardware",
            "type":"Retail Goods"
        }
    ],
    "sg:phone":"+61 3 9775 1177",
    "sg:postcode":"3201",
    "sg:province":"VIC",
    "sg:tags":[
        "trolley",
        "truck",
        "hand"
    ],
    "wof:name":"M.P.A. Shopping Jeeps P/L",
    "wof:placetype":"venue"
},
  "geometry": {"coordinates":[145.16952499999999,-38.102451],"type":"Point"}
}