{
  "type": "Feature",
  "properties": {
    "addr:full":"295 Walter Rd Morley WA 6062",
    "addr:housenumber":"295",
    "addr:postcode":"6062",
    "addr:street":"Walter Rd",
    "iso:country":"AU",
    "sg:address":"295 Walter Rd",
    "sg:city":"Morley",
    "sg:classifiers":[
        {
            "category":"Health Services",
            "subcategory":"Doctor",
            "type":"Services"
        }
    ],
    "sg:phone":"+61 8 9275 9006",
    "sg:postcode":"6062",
    "sg:province":"WA",
    "sg:tags":[
        "podiatrist"
    ],
    "sg:website":"http://www.galleriapodiatry.com.au",
    "wof:name":"Galleria Podiatry",
    "wof:placetype":"venue"
},
  "geometry": {"coordinates":[115.90097045900001,-31.8945140839],"type":"Point"}
}