{
  "type": "Feature",
  "properties": {
    "addr:full":"6 Main St Proserpine QLD 4800",
    "addr:housenumber":"6",
    "addr:postcode":"4800",
    "addr:street":"Main St",
    "iso:country":"AU",
    "sg:address":"6 Main St",
    "sg:city":"Proserpine",
    "sg:classifiers":[
        {
            "category":"Building & Trades",
            "subcategory":"Equipment Rental",
            "type":"Services"
        }
    ],
    "sg:phone":"+61 7 4945 3533",
    "sg:postcode":"4800",
    "sg:province":"QLD",
    "sg:tags":[
        "supply",
        "catering"
    ],
    "wof:name":"Caterquip (Qld) Pty Ltd",
    "wof:placetype":"venue"
},
  "geometry": {"coordinates":[148.58409118599999,-20.4019794464],"type":"Point"}
}