{
  "type": "Feature",
  "properties": {
    "addr:full":"Shop 2/ 216 Shaw Rd Wavell Heights QLD 4012",
    "addr:housenumber":"shop 2 / 216",
    "addr:postcode":"4012",
    "addr:street":"Shaw Rd",
    "iso:country":"AU",
    "sg:address":"Shop 2/ 216 Shaw Rd",
    "sg:city":"Wavell Heights",
    "sg:classifiers":[
        {
            "category":"Food & Beverages",
            "subcategory":"Fruits & Vegetables",
            "type":"Retail Goods"
        }
    ],
    "sg:phone":"+61 7 3256 9018",
    "sg:postcode":"4012",
    "sg:province":"QLD",
    "sg:tags":[
        "greengrocer",
        "fruiterer"
    ],
    "wof:name":"Fresh Selections",
    "wof:placetype":"venue"
},
  "geometry": {"coordinates":[153.04827880900001,-27.3993625641],"type":"Point"}
}