{
  "type": "Feature",
  "properties": {
    "addr:full":"12 Market St Box Hill VIC 3128",
    "addr:housenumber":"12",
    "addr:postcode":"3128",
    "addr:street":"Market St",
    "iso:country":"AU",
    "sg:address":"12 Market St",
    "sg:city":"Box Hill",
    "sg:classifiers":[
        {
            "category":"Shopping",
            "subcategory":"Optical Goods",
            "type":"Retail Goods"
        }
    ],
    "sg:phone":"+61 3 9899 0399",
    "sg:postcode":"3128",
    "sg:province":"VIC",
    "sg:tags":[
        "dispenser",
        "prescription"
    ],
    "wof:name":"Optical City",
    "wof:placetype":"venue"
},
  "geometry": {"coordinates":[145.12237548799999,-37.8185501099],"type":"Point"}
}