{
  "type": "Feature",
  "properties": {
    "addr:full":"141 Victoria St North Geelong VIC 3215",
    "addr:housenumber":"141",
    "addr:postcode":"3215",
    "addr:street":"Victoria St",
    "iso:country":"AU",
    "sg:address":"141 Victoria St",
    "sg:city":"North Geelong",
    "sg:classifiers":[
        {
            "category":"Retail",
            "subcategory":"Repair Shop",
            "type":"Services"
        }
    ],
    "sg:phone":"+61 3 5278 5489",
    "sg:postcode":"3215",
    "sg:province":"VIC",
    "sg:tags":[
        "upholsterer"
    ],
    "wof:name":"Relaxa Furniture",
    "wof:placetype":"venue"
},
  "geometry": {"coordinates":[144.346359253,-38.1222229004],"type":"Point"}
}