{
  "type": "Feature",
  "properties": {
    "addr:full":"319- 331 Boundary Rd Braeside VIC 3195",
    "addr:housenumber":"331",
    "addr:postcode":"3195",
    "addr:street":"Boundary Rd",
    "iso:country":"AU",
    "sg:address":"319- 331 Boundary Rd",
    "sg:city":"Braeside",
    "sg:classifiers":[
        {
            "category":"Retail",
            "subcategory":"Car Wash",
            "type":"Services"
        }
    ],
    "sg:phone":"+61 3 9587 0203",
    "sg:postcode":"3195",
    "sg:province":"VIC",
    "sg:tags":[
        "truck",
        "cleaning"
    ],
    "wof:name":"Carlovers The Ultimate Car Wash",
    "wof:placetype":"venue"
},
  "geometry": {"coordinates":[145.108810425,-37.9872703552],"type":"Point"}
}