{
  "type": "Feature",
  "properties": {
    "addr:full":"Upper Level Cnr Affleck & Grogan Rds Perth Airport WA 6105",
    "addr:postcode":"6105",
    "addr:street":"Cnr",
    "iso:country":"AU",
    "sg:address":"Upper Level Cnr Affleck & Grogan Rds",
    "sg:city":"Perth Airport",
    "sg:classifiers":[
        {
            "category":"Farming",
            "subcategory":"Crops",
            "type":"Manufacturing & Wholesale Goods"
        }
    ],
    "sg:phone":"+61 8 9270 1200",
    "sg:postcode":"6105",
    "sg:province":"WA",
    "sg:tags":[
        "warehousing"
    ],
    "wof:name":"Exel (Australia) Logistics Pty Ltd",
    "wof:placetype":"venue"
},
  "geometry": {"coordinates":[115.975212097,-31.9499397278],"type":"Point"}
}