{
  "type": "Feature",
  "properties": {
    "iso:country":"AU",
    "sg:address":"Shp4/ 61 Esplanade",
    "sg:city":"Coffin Bay",
    "sg:classifiers":[
        {
            "category":"Fast Food",
            "type":"Food & Drink"
        }
    ],
    "sg:phone":"+61 8 8685 5042",
    "sg:postcode":"5607",
    "sg:province":"SA",
    "sg:tags":[
        "away",
        "take"
    ],
    "wof:name":"Coffin Bay Gourmet Catering",
    "wof:placetype":"venue"
},
  "geometry": {"coordinates":[135.462906,-34.62001],"type":"Point"}
}