{
  "type": "Feature",
  "properties": {
    "addr:full":"Newell Hwy Gilgandra NSW 2827",
    "addr:postcode":"2827",
    "addr:street":"Newell Hwy",
    "iso:country":"AU",
    "sg:address":"Newell Hwy",
    "sg:city":"Gilgandra",
    "sg:classifiers":[
        {
            "category":"Cafe",
            "type":"Food & Drink"
        }
    ],
    "sg:phone":"+61 2 6847 2707",
    "sg:postcode":"2827",
    "sg:province":"NSW",
    "wof:name":"The Next Grind Coffee & Gallery",
    "wof:placetype":"venue"
},
  "geometry": {"coordinates":[148.67123413100001,-31.7023849487],"type":"Point"}
}