{
  "type": "Feature",
  "properties": {
    "addr:full":"8-10 Sharon Rd Batemans Bay NSW 2536",
    "addr:housenumber":"8-10",
    "addr:postcode":"2536",
    "addr:street":"Sharon Rd",
    "iso:country":"AU",
    "sg:address":"8-10 Sharon Rd",
    "sg:city":"Batemans Bay",
    "sg:classifiers":[
        {
            "category":"Home & Garden",
            "subcategory":"Building Materials",
            "type":"Retail Goods"
        }
    ],
    "sg:phone":"+61 2 4472 9504",
    "sg:postcode":"2536",
    "sg:province":"NSW",
    "sg:tags":[
        "wall",
        "frame",
        "truss",
        "roof"
    ],
    "wof:name":"Batemans Bay Frames & Trusses",
    "wof:placetype":"venue"
},
  "geometry": {"coordinates":[150.173736572,-35.7185249329],"type":"Point"}
}