{
  "type": "Feature",
  "properties": {
    "iso:country":"AU",
    "sg:address":"175 Hamilton Hwy",
    "sg:city":"Fyansford",
    "sg:classifiers":[
        {
            "category":"Wholesale",
            "subcategory":"Farm Supplies",
            "type":"Manufacturing & Wholesale Goods"
        }
    ],
    "sg:phone":"+61 3 5229 9566",
    "sg:postcode":"3221",
    "sg:province":"VIC",
    "sg:tags":[
        "feed",
        "supplement",
        "stock"
    ],
    "wof:name":"Gugger N A & Sons",
    "wof:placetype":"venue"
},
  "geometry": {"coordinates":[144.308975,-38.142136],"type":"Point"}
}