{
  "type": "Feature",
  "properties": {
    "iso:country":"AU",
    "sg:address":"1/ 86 Avenue Rd",
    "sg:city":"Highgate",
    "sg:classifiers":[
        {
            "category":"Wholesale",
            "subcategory":"Apparel",
            "type":"Manufacturing & Wholesale Goods"
        }
    ],
    "sg:phone":"+61 8 8357 9330",
    "sg:postcode":"5063",
    "sg:province":"SA",
    "sg:tags":[
        "wholesaler",
        "mfrs",
        "cap",
        "hat"
    ],
    "wof:name":"A-Tag",
    "wof:placetype":"venue"
},
  "geometry": {"coordinates":[138.617645264,-34.9624977112],"type":"Point"}
}