{
  "type": "Feature",
  "properties": {
    "addr:full":"3A CB Fisher Drv Cavan SA 5094",
    "addr:postcode":"5094",
    "addr:street":"Fisher Drv",
    "iso:country":"AU",
    "sg:address":"3A CB Fisher Drv",
    "sg:city":"Cavan",
    "sg:classifiers":[
        {
            "category":"Wholesale",
            "subcategory":"Machinery & Supplies",
            "type":"Manufacturing & Wholesale Goods"
        }
    ],
    "sg:phone":"+61 8 8359 8920",
    "sg:postcode":"5094",
    "sg:province":"SA",
    "sg:tags":[
        "equipment",
        "hydraulic"
    ],
    "wof:name":"Eaton Fluid Power",
    "wof:placetype":"venue"
},
  "geometry": {"coordinates":[138.60386657699999,-34.8218421936],"type":"Point"}
}