{
  "type": "Feature",
  "properties": {
    "iso:country":"AU",
    "sg:address":"140c Tolley Rd",
    "sg:city":"St Agnes",
    "sg:classifiers":[
        {
            "category":"Retail",
            "subcategory":"Auto Repair",
            "type":"Services"
        }
    ],
    "sg:phone":"+61 8 8264 1161",
    "sg:postcode":"5097",
    "sg:province":"SA",
    "sg:tags":[
        "body",
        "builder",
        "motor"
    ],
    "wof:name":"Auscar Conversions",
    "wof:placetype":"venue"
},
  "geometry": {"coordinates":[138.70698547399999,-34.8335266113],"type":"Point"}
}