{
  "type": "Feature",
  "properties": {
    "addr:full":"Room 1315 Holiday Inn 334 Flinders Mall Townsville QLD 4810",
    "addr:housenumber":"1315;334",
    "addr:postcode":"4810",
    "addr:street":"Holiday;Flinders Mall",
    "iso:country":"AU",
    "sg:address":"Room 1315 Holiday Inn 334",
    "sg:city":"Flinders Mall Townsville",
    "sg:classifiers":[
        {
            "category":"Personal",
            "subcategory":"Massage",
            "type":"Services"
        }
    ],
    "sg:phone":"+61 7 4721 5338",
    "sg:postcode":"4810",
    "sg:province":"QLD",
    "sg:tags":[
        "therapy"
    ],
    "wof:name":"Jade Health Centre",
    "wof:placetype":"venue"
},
  "geometry": {"coordinates":[146.81712300000001,-19.259705],"type":"Point"}
}