{
  "type": "Feature",
  "properties": {
    "addr:full":"432- 434 Scarborough Bch Rd Osborne Park WA 6017",
    "addr:housenumber":"434",
    "addr:postcode":"6017",
    "addr:street":"Scarborough Bch Rd",
    "iso:country":"AU",
    "sg:address":"432- 434 Scarborough Bch Rd",
    "sg:city":"Osborne Park",
    "sg:classifiers":[
        {
            "category":"Autos & Motor Vehicles",
            "subcategory":"Automobile Sales",
            "type":"Retail Goods"
        }
    ],
    "sg:phone":"+61 8 9449 9000",
    "sg:postcode":"6017",
    "sg:province":"WA",
    "sg:tags":[
        "car",
        "new"
    ],
    "wof:name":"Honda North",
    "wof:placetype":"venue"
},
  "geometry": {"coordinates":[115.811508179,-31.9077129364],"type":"Point"}
}