{
  "type": "Feature",
  "properties": {
    "addr:full":"717 Forest Rd Bexley NSW 2207",
    "addr:housenumber":"717",
    "addr:postcode":"2207",
    "addr:street":"Forest Rd",
    "iso:country":"AU",
    "sg:address":"717 Forest Rd",
    "sg:city":"Bexley",
    "sg:classifiers":[
        {
            "category":"Autos & Motor Vehicles",
            "subcategory":"Auto Supplies",
            "type":"Retail Goods"
        }
    ],
    "sg:phone":"+61 2 9587 2469",
    "sg:postcode":"2207",
    "sg:province":"NSW",
    "sg:tags":[
        "battery",
        "automotive"
    ],
    "wof:name":"St George Eagle Batteries",
    "wof:placetype":"venue"
},
  "geometry": {"coordinates":[151.11601300000001,-33.960865],"type":"Point"}
}