{
  "type": "Feature",
  "properties": {
    "addr:full":"7 Dallas Pde Keperra QLD 4054",
    "addr:housenumber":"7",
    "addr:postcode":"4054",
    "addr:street":"Dallas Pde",
    "iso:country":"AU",
    "sg:address":"7 Dallas Pde",
    "sg:city":"Keperra",
    "sg:classifiers":[
        {
            "category":"Sports & Exercise",
            "subcategory":"Ski Resort",
            "type":"Entertainment"
        }
    ],
    "sg:phone":"+61 7 3855 1264",
    "sg:postcode":"4054",
    "sg:province":"QLD",
    "sg:tags":[
        "tour",
        "centres"
    ],
    "wof:name":"Ski Tours World Wide",
    "wof:placetype":"venue"
},
  "geometry": {"coordinates":[152.958618164,-27.4090671539],"type":"Point"}
}