{
  "type": "Feature",
  "properties": {
    "addr:full":"55- 63 Dalrymple Rd Garbutt QLD 4814",
    "addr:housenumber":"63",
    "addr:postcode":"4814",
    "addr:street":"Dalrymple Rd",
    "iso:country":"AU",
    "sg:address":"55- 63 Dalrymple Rd",
    "sg:city":"Garbutt",
    "sg:classifiers":[
        {
            "category":"Autos & Motor Vehicles",
            "subcategory":"Automobile Sales",
            "type":"Retail Goods"
        }
    ],
    "sg:phone":"+61 7 4775 3033",
    "sg:postcode":"4814",
    "sg:province":"QLD",
    "sg:tags":[
        "car",
        "new"
    ],
    "wof:name":"TJM 4X4 Megastore",
    "wof:placetype":"venue"
},
  "geometry": {"coordinates":[146.776917,-19.268518],"type":"Point"}
}