{
  "type": "Feature",
  "properties": {
    "iso:country":"AU",
    "sg:address":"62 York St",
    "sg:city":"Gosford East",
    "sg:classifiers":[
        {
            "category":"Health Services",
            "subcategory":"Chiropractor",
            "type":"Services"
        }
    ],
    "sg:phone":"+61 2 4321 0511",
    "sg:postcode":"2250",
    "sg:province":"NSW",
    "wof:name":"Tweedie Jane",
    "wof:placetype":"venue"
},
  "geometry": {"coordinates":[151.35101318400001,-33.4367332458],"type":"Point"}
}