{
  "type": "Feature",
  "properties": {
    "addr:full":"941 Wynnum Rd Cannon Hill QLD 4170",
    "addr:housenumber":"941",
    "addr:postcode":"4170",
    "addr:street":"Wynnum Rd",
    "iso:country":"AU",
    "sg:address":"941 Wynnum Rd",
    "sg:city":"Cannon Hill",
    "sg:classifiers":[
        {
            "category":"Fast Food",
            "type":"Food & Drink"
        }
    ],
    "sg:phone":"+61 7 3399 9861",
    "sg:postcode":"4170",
    "sg:province":"QLD",
    "sg:tags":[
        "away",
        "take"
    ],
    "wof:name":"Furama Chinese Kitchen",
    "wof:placetype":"venue"
},
  "geometry": {"coordinates":[153.087280273,-27.4683418274],"type":"Point"}
}