{
  "type": "Feature",
  "properties": {
    "addr:full":"33 Bulcock St Caloundra QLD 4551",
    "addr:housenumber":"33",
    "addr:postcode":"4551",
    "addr:street":"Bulcock St",
    "iso:country":"AU",
    "sg:address":"33 Bulcock St",
    "sg:city":"Caloundra",
    "sg:classifiers":[
        {
            "category":"Health Services",
            "subcategory":"Optometrist",
            "type":"Services"
        }
    ],
    "sg:phone":"+61 7 5491 1222",
    "sg:postcode":"4551",
    "sg:province":"QLD",
    "wof:name":"Advanced Eyecare",
    "wof:placetype":"venue"
},
  "geometry": {"coordinates":[153.12962341299999,-26.8046684265],"type":"Point"}
}