{
  "type": "Feature",
  "properties": {
    "addr:full":"unit 9-209 23 Robinson Rd Geebung QLD 4034",
    "addr:housenumber":"23",
    "addr:postcode":"4034",
    "addr:street":"Robinson Rd",
    "iso:country":"AU",
    "sg:address":"unit 9-209 23 Robinson Rd",
    "sg:city":"Geebung",
    "sg:classifiers":[
        {
            "category":"Building & Trades",
            "subcategory":"Equipment Rental",
            "type":"Services"
        }
    ],
    "sg:phone":"+61 1300 135 596",
    "sg:postcode":"4034",
    "sg:province":"QLD",
    "sg:tags":[
        "fitness"
    ],
    "wof:name":"T-Zone Pro",
    "wof:placetype":"venue"
},
  "geometry": {"coordinates":[153.06059300000001,-27.370226],"type":"Point"}
}