{
  "type": "Feature",
  "properties": {
    "iso:country":"AU",
    "sg:address":"8 Malabar Rd",
    "sg:city":"Coogee",
    "sg:classifiers":[
        {
            "category":"Fast Food",
            "type":"Food & Drink"
        }
    ],
    "sg:phone":"+61 2 9665 0038",
    "sg:postcode":"2034",
    "sg:province":"NSW",
    "sg:tags":[
        "away",
        "take"
    ],
    "wof:name":"South Coogee Chinese Cafe",
    "wof:placetype":"venue"
},
  "geometry": {"coordinates":[151.25074768100001,-33.9276237488],"type":"Point"}
}