{
  "type": "Feature",
  "properties": {
    "addr:full":"Level 1/ 46 Ventnor Ave West Perth WA 6005",
    "addr:housenumber":"/ 46",
    "addr:postcode":"6005",
    "addr:street":"Ventnor Ave",
    "iso:country":"AU",
    "sg:address":"Level 1/ 46 Ventnor Ave",
    "sg:city":"West Perth",
    "sg:classifiers":[
        {
            "category":"Personal",
            "subcategory":"Skin Care",
            "type":"Services"
        }
    ],
    "sg:phone":"+61 8 9212 4300",
    "sg:postcode":"6005",
    "sg:province":"WA",
    "sg:tags":[
        "information",
        "treatment",
        "smoker"
    ],
    "wof:name":"Australian Council On Smoking & Health (ACOSH)",
    "wof:placetype":"venue"
},
  "geometry": {"coordinates":[115.838752747,-31.9485301971],"type":"Point"}
}