{
  "type": "Feature",
  "properties": {
    "addr:full":"94 Brisbane St Cowra NSW 2794",
    "addr:housenumber":"94",
    "addr:postcode":"2794",
    "addr:street":"Brisbane St",
    "iso:country":"AU",
    "sg:address":"94 Brisbane St",
    "sg:city":"Cowra",
    "sg:classifiers":[
        {
            "category":"Health Services",
            "subcategory":"Dentist",
            "type":"Services"
        }
    ],
    "sg:phone":"+61 2 6342 2433",
    "sg:postcode":"2794",
    "sg:province":"NSW",
    "wof:name":"Quirk F",
    "wof:placetype":"venue"
},
  "geometry": {"coordinates":[148.69128418,-33.8335113525],"type":"Point"}
}