{
  "type": "Feature",
  "properties": {
    "iso:country":"AU",
    "sg:address":"99 Mulgrave Rd",
    "sg:city":"Parramatta Park",
    "sg:classifiers":[
        {
            "category":"Fast Food",
            "type":"Food & Drink"
        }
    ],
    "sg:phone":"+61 7 4041 3115",
    "sg:postcode":"4870",
    "sg:province":"QLD",
    "sg:tags":[
        "away",
        "take"
    ],
    "wof:name":"Natralicious",
    "wof:placetype":"venue"
},
  "geometry": {"coordinates":[145.76498413100001,-16.9249954224],"type":"Point"}
}