{
  "type": "Feature",
  "properties": {
    "addr:full":"Yandina Rd Coolum Beach QLD 4573",
    "addr:postcode":"4573",
    "addr:street":"Yandina Rd",
    "iso:country":"AU",
    "sg:address":"Yandina Rd",
    "sg:city":"Coolum Beach",
    "sg:classifiers":[
        {
            "category":"Home & Garden",
            "subcategory":"Building Materials",
            "type":"Retail Goods"
        }
    ],
    "sg:phone":"+61 7 5446 1585",
    "sg:postcode":"4573",
    "sg:province":"QLD",
    "sg:tags":[
        "pre-mixed",
        "concrete"
    ],
    "wof:name":"Readymix",
    "wof:placetype":"venue"
},
  "geometry": {"coordinates":[153.07545500000001,-26.53541],"type":"Point"}
}