{
  "type": "Feature",
  "properties": {
    "iso:country":"AU",
    "sg:address":"11 Factory St",
    "sg:city":"Kallangur",
    "sg:classifiers":[
        {
            "category":"Utilities",
            "subcategory":"Electric",
            "type":"Services"
        }
    ],
    "sg:phone":"+61 418 767 110",
    "sg:postcode":"4503",
    "sg:province":"QLD",
    "sg:tags":[
        "electrical",
        "contractor"
    ],
    "wof:name":"Python Electrical",
    "wof:placetype":"venue"
},
  "geometry": {"coordinates":[152.97825622600001,-27.2558860779],"type":"Point"}
}