{
  "type": "Feature",
  "properties": {
    "addr:full":"29 Catherine St Subiaco WA 6008",
    "addr:housenumber":"29",
    "addr:postcode":"6008",
    "addr:street":"Catherine St",
    "iso:country":"AU",
    "sg:address":"29 Catherine St",
    "sg:city":"Subiaco",
    "sg:classifiers":[
        {
            "category":"Social Services",
            "subcategory":"Retirement Home",
            "type":"Services"
        }
    ],
    "sg:phone":"+61 8 9489 4300",
    "sg:postcode":"6008",
    "sg:province":"WA",
    "sg:tags":[
        "environmental",
        "consultant",
        "pollution"
    ],
    "wof:name":"WSP Enviromental",
    "wof:placetype":"venue"
},
  "geometry": {"coordinates":[115.825843811,-31.9460544586],"type":"Point"}
}