{
  "type": "Feature",
  "properties": {
    "addr:full":"9 Columbia Ave Gladstone QLD 4680",
    "addr:housenumber":"9",
    "addr:postcode":"4680",
    "addr:street":"Columbia Ave",
    "iso:country":"AU",
    "sg:address":"9 Columbia Ave",
    "sg:city":"Gladstone",
    "sg:classifiers":[
        {
            "category":"Real Estate",
            "subcategory":"Developer",
            "type":"Services"
        }
    ],
    "sg:phone":"+61 7 4978 2061",
    "sg:postcode":"4680",
    "sg:province":"QLD",
    "sg:tags":[
        "development"
    ],
    "wof:name":"Beaumont Investments Pty Ltd",
    "wof:placetype":"venue"
},
  "geometry": {"coordinates":[151.21304321299999,-23.8750457764],"type":"Point"}
}