{
  "type": "Feature",
  "properties": {
    "iso:country":"AU",
    "sg:address":"Suite 3 69 King St",
    "sg:city":"Caboolture",
    "sg:classifiers":[
        {
            "category":"Health Services",
            "subcategory":"Optometrist",
            "type":"Services"
        }
    ],
    "sg:phone":"+61 7 5495 2316",
    "sg:postcode":"4510",
    "sg:province":"QLD",
    "wof:name":"Roberts Bev",
    "wof:placetype":"venue"
},
  "geometry": {"coordinates":[152.949356,-27.084467],"type":"Point"}
}