{
  "type": "Feature",
  "properties": {
    "iso:country":"AU",
    "sg:address":"PO Box 1482",
    "sg:city":"Carindale",
    "sg:classifiers":[
        {
            "category":"Manufacturing",
            "subcategory":"Jewelry",
            "type":"Manufacturing & Wholesale Goods"
        }
    ],
    "sg:phone":"+61 414 487 845",
    "sg:postcode":"4152",
    "sg:province":"QLD",
    "sg:tags":[
        "mfrg",
        "jeweller"
    ],
    "wof:name":"G T Diamond",
    "wof:placetype":"venue"
},
  "geometry": {"coordinates":[153.102005005,-27.5056304932],"type":"Point"}
}