{
  "type": "Feature",
  "properties": {
    "addr:full":"Shop 10 Karalee Shopng Vlge Junction Rd Karalee QLD 4306",
    "addr:housenumber":"shop 10",
    "addr:postcode":"4306",
    "addr:street":"Karalee Shopng Vlge Junction Rd",
    "iso:country":"AU",
    "sg:address":"Shop 10 Karalee Shopng Vlge Junction Rd",
    "sg:city":"Karalee",
    "sg:classifiers":[
        {
            "category":"Fast Food",
            "type":"Food & Drink"
        }
    ],
    "sg:phone":"+61 7 3812 2464",
    "sg:postcode":"4306",
    "sg:province":"QLD",
    "sg:tags":[
        "away",
        "take"
    ],
    "wof:name":"Karalee Snack Bar",
    "wof:placetype":"venue"
},
  "geometry": {"coordinates":[152.821243286,-27.5673065186],"type":"Point"}
}