{
  "type": "Feature",
  "properties": {
    "addr:full":"Level 1, Toowong Terraces Bldg 31 Sherwood Rd Toowong QLD 4066",
    "addr:housenumber":"31",
    "addr:postcode":"4066",
    "addr:street":"Sherwood Rd",
    "iso:country":"AU",
    "sg:address":"Level 1, Toowong Terraces Bldg 31 Sherwood Rd",
    "sg:city":"Toowong",
    "sg:classifiers":[
        {
            "category":"Health Services",
            "subcategory":"Dentist",
            "type":"Services"
        }
    ],
    "sg:phone":"+61 7 3870 3344",
    "sg:postcode":"4066",
    "sg:province":"QLD",
    "wof:name":"Pokarier Meredith",
    "wof:placetype":"venue"
},
  "geometry": {"coordinates":[152.991287231,-27.4852657318],"type":"Point"}
}