{
  "type": "Feature",
  "properties": {
    "iso:country":"AU",
    "sg:address":"Unit 1, 6 Rob Pl",
    "sg:city":"Vineyard",
    "sg:classifiers":[
        {
            "category":"Shopping",
            "subcategory":"Bicycles & Sporting Goods",
            "type":"Retail Goods"
        }
    ],
    "sg:phone":"+61 2 4577 9114",
    "sg:postcode":"2765",
    "sg:province":"NSW",
    "sg:tags":[
        "water",
        "equipment",
        "skiing"
    ],
    "wof:name":"Wake 2 Wake",
    "wof:placetype":"venue"
},
  "geometry": {"coordinates":[150.84176635700001,-33.6310958862],"type":"Point"}
}