{
  "type": "Feature",
  "properties": {
    "iso:country":"AU",
    "sg:address":"47 Gordon Rd East",
    "sg:city":"Osborne Park",
    "sg:classifiers":[
        {
            "category":"Retail",
            "subcategory":"Auto Repair",
            "type":"Services"
        }
    ],
    "sg:phone":"+61 8 9444 1777",
    "sg:postcode":"6017",
    "sg:province":"WA",
    "sg:tags":[
        "body",
        "motor",
        "trimmer"
    ],
    "wof:name":"Newlan's Coachbuilders",
    "wof:placetype":"venue"
},
  "geometry": {"coordinates":[115.823188782,-31.9067554474],"type":"Point"}
}