{
  "type": "Feature",
  "properties": {
    "addr:full":"Cressy Rd Beeac VIC 3251",
    "addr:postcode":"3251",
    "addr:street":"Cressy Rd",
    "iso:country":"AU",
    "sg:address":"Cressy Rd",
    "sg:city":"Beeac",
    "sg:classifiers":[
        {
            "category":"Commercial Area",
            "type":"Public Place"
        }
    ],
    "sg:phone":"+61 3 5234 6471",
    "sg:postcode":"3251",
    "sg:province":"VIC",
    "sg:tags":[
        "heavy",
        "carrier"
    ],
    "wof:name":"Vagg W",
    "wof:placetype":"venue"
},
  "geometry": {"coordinates":[143.74595600000001,-38.128788],"type":"Point"}
}