{
  "type": "Feature",
  "properties": {
    "addr:full":"46 Colebard St Acacia Ridge QLD 4110",
    "addr:housenumber":"46",
    "addr:postcode":"4110",
    "addr:street":"Colebard St",
    "iso:country":"AU",
    "sg:address":"46 Colebard St",
    "sg:city":"Acacia Ridge",
    "sg:classifiers":[
        {
            "category":"Manufacturing",
            "subcategory":"Motor Vehicles & Parts",
            "type":"Manufacturing & Wholesale Goods"
        }
    ],
    "sg:phone":"+61 7 3276 8441",
    "sg:postcode":"4110",
    "sg:province":"QLD",
    "sg:tags":[
        "engine",
        "equipment",
        "diesel"
    ],
    "wof:name":"Energy Power Systems",
    "wof:placetype":"venue"
},
  "geometry": {"coordinates":[153.00607299800001,-27.5818691254],"type":"Point"}
}