{
  "type": "Feature",
  "properties": {
    "addr:full":"9 Wimbledon Crt Doncaster East VIC 3109",
    "addr:housenumber":"9",
    "addr:postcode":"3109",
    "addr:street":"Wimbledon Crt",
    "iso:country":"AU",
    "sg:address":"9 Wimbledon Crt",
    "sg:city":"Doncaster East",
    "sg:classifiers":[
        {
            "category":"Utilities",
            "subcategory":"Electric",
            "type":"Services"
        }
    ],
    "sg:phone":"+61 3 9842 0733",
    "sg:postcode":"3109",
    "sg:province":"VIC",
    "sg:tags":[
        "electrical",
        "contractor"
    ],
    "wof:name":"Bell Wiggins Electrical",
    "wof:placetype":"venue"
},
  "geometry": {"coordinates":[145.16716003400001,-37.764667511],"type":"Point"}
}