{
  "type": "Feature",
  "properties": {
    "iso:country":"AU",
    "sg:address":"Melbourne Rd",
    "sg:city":"Shepparton South",
    "sg:classifiers":[
        {
            "category":"Autos & Motor Vehicles",
            "subcategory":"Automobile Sales",
            "type":"Retail Goods"
        }
    ],
    "sg:phone":"+61 3 5823 2100",
    "sg:postcode":"3630",
    "sg:province":"VIC",
    "sg:tags":[
        "car",
        "new"
    ],
    "wof:name":"McPherson Motors",
    "wof:placetype":"venue"
},
  "geometry": {"coordinates":[145.390136719,-36.4269676208],"type":"Point"}
}