{
  "type": "Feature",
  "properties": {
    "addr:full":"90b Northgate Drv Thomastown VIC 3074",
    "addr:housenumber":"90b",
    "addr:postcode":"3074",
    "addr:street":"Northgate Drv",
    "iso:country":"AU",
    "sg:address":"90b Northgate Drv",
    "sg:city":"Thomastown",
    "sg:classifiers":[
        {
            "category":"Wholesale",
            "subcategory":"Medical Equipment & Supplies",
            "type":"Manufacturing & Wholesale Goods"
        }
    ],
    "sg:phone":"+61 3 9466 3211",
    "sg:postcode":"3074",
    "sg:province":"VIC",
    "sg:tags":[
        "aid",
        "care",
        "health",
        "home"
    ],
    "wof:name":"Hand Rail Industries",
    "wof:placetype":"venue"
},
  "geometry": {"coordinates":[145.03361511200001,-37.6883506775],"type":"Point"}
}