{
  "type": "Feature",
  "properties": {
    "addr:full":"1899 Princess Hwy Clayton North VIC 3168",
    "addr:housenumber":"1899",
    "addr:postcode":"3168",
    "addr:street":"Princess Hwy",
    "iso:country":"AU",
    "sg:address":"1899 Princess Hwy",
    "sg:city":"Clayton North",
    "sg:classifiers":[
        {
            "category":"Professional",
            "subcategory":"Computer Services",
            "type":"Services"
        }
    ],
    "sg:phone":"+61 3 9562 9999",
    "sg:postcode":"3168",
    "sg:province":"VIC",
    "sg:tags":[
        "consultant",
        "system"
    ],
    "wof:name":"Digital Peripherals Pty Ltd",
    "wof:placetype":"venue"
},
  "geometry": {"coordinates":[145.12176513700001,-37.914516449],"type":"Point"}
}