{
  "type": "Feature",
  "properties": {
    "addr:full":"31 Perwell St Keperra QLD 4054",
    "addr:housenumber":"31",
    "addr:postcode":"4054",
    "addr:street":"Perwell St",
    "iso:country":"AU",
    "sg:address":"31 Perwell St",
    "sg:city":"Keperra",
    "sg:classifiers":[
        {
            "category":"Professional",
            "subcategory":"Management & Consulting",
            "type":"Services"
        }
    ],
    "sg:phone":"+61 7 3351 5222",
    "sg:postcode":"4054",
    "sg:province":"QLD",
    "sg:tags":[
        "consultant",
        "educational"
    ],
    "wof:name":"IndiAust Consultants",
    "wof:placetype":"venue"
},
  "geometry": {"coordinates":[152.94543457,-27.410572052],"type":"Point"}
}