{
  "type": "Feature",
  "properties": {
    "addr:full":"PO Box 18 Chirnside Park VIC 3116",
    "addr:postcode":"3116",
    "iso:country":"AU",
    "sg:address":"PO Box 18",
    "sg:city":"Chirnside Park",
    "sg:classifiers":[
        {
            "category":"Professional",
            "subcategory":"Business Services",
            "type":"Services"
        }
    ],
    "sg:phone":"+61 3 9727 5262",
    "sg:postcode":"3116",
    "sg:province":"VIC",
    "sg:tags":[
        "drafting"
    ],
    "wof:name":"Sure Haven Design",
    "wof:placetype":"venue"
},
  "geometry": {"coordinates":[145.31483459500001,-37.7397918701],"type":"Point"}
}