{
  "type": "Feature",
  "properties": {
    "addr:full":"554 Pacific Hwy Killara NSW 2071",
    "addr:housenumber":"554",
    "addr:postcode":"2071",
    "addr:street":"Pacific Hwy",
    "iso:country":"AU",
    "sg:address":"554 Pacific Hwy",
    "sg:city":"Killara",
    "sg:classifiers":[
        {
            "category":"Shopping",
            "subcategory":"Bicycles & Sporting Goods",
            "type":"Retail Goods"
        }
    ],
    "sg:phone":"+61 2 9498 3633",
    "sg:postcode":"2071",
    "sg:province":"NSW",
    "sg:tags":[
        "chemical",
        "equipment",
        "pool",
        "swimming"
    ],
    "wof:name":"Killara Services",
    "wof:placetype":"venue"
},
  "geometry": {"coordinates":[151.159591675,-33.7691497803],"type":"Point"}
}