{
  "type": "Feature",
  "properties": {
    "addr:full":"PO Box 608 Mundaring WA 6073",
    "addr:postcode":"6073",
    "iso:country":"AU",
    "sg:address":"PO Box 608",
    "sg:city":"Mundaring",
    "sg:classifiers":[
        {
            "category":"Communications",
            "subcategory":"Film & Video Production",
            "type":"Services"
        }
    ],
    "sg:phone":"+61 413 561 790",
    "sg:postcode":"6073",
    "sg:province":"WA",
    "sg:tags":[
        "linen",
        "good"
    ],
    "wof:name":"Linenshop",
    "wof:placetype":"venue"
},
  "geometry": {"coordinates":[116.167037964,-31.921880722],"type":"Point"}
}