{
  "type": "Feature",
  "properties": {
    "addr:full":"28 Meeks Rd Marrickville NSW 2204",
    "addr:housenumber":"28",
    "addr:postcode":"2204",
    "addr:street":"Meeks Rd",
    "iso:country":"AU",
    "sg:address":"28 Meeks Rd",
    "sg:city":"Marrickville",
    "sg:classifiers":[
        {
            "category":"Manufacturing",
            "subcategory":"Textiles",
            "type":"Manufacturing & Wholesale Goods"
        }
    ],
    "sg:phone":"+61 2 9550 1272",
    "sg:postcode":"2204",
    "sg:province":"NSW",
    "sg:tags":[
        "fibre"
    ],
    "wof:name":"Aussie Enterprises Pty Ltd",
    "wof:placetype":"venue"
},
  "geometry": {"coordinates":[151.16210899999999,-33.911072],"type":"Point"}
}