{
  "type": "Feature",
  "properties": {
    "iso:country":"AU",
    "sg:address":"28 Meeks Rd",
    "sg:city":"Marrickville",
    "sg:classifiers":[
        {
            "category":"Manufacturing",
            "subcategory":"Textiles",
            "type":"Manufacturing & Wholesale Goods"
        }
    ],
    "sg:phone":"+61 2 9550 1272",
    "sg:postcode":"2204",
    "sg:province":"NSW",
    "sg:tags":[
        "fibre"
    ],
    "wof:name":"Aussie Enterprises Pty Ltd",
    "wof:placetype":"venue"
},
  "geometry": {"coordinates":[151.162109,-33.911072],"type":"Point"}
}