{
  "type": "Feature",
  "properties": {
    "iso:country":"AU",
    "sg:address":"1/ 77 Camooweal St",
    "sg:city":"Mt Isa",
    "sg:classifiers":[
        {
            "category":"Personal",
            "subcategory":"Beauty Salon",
            "type":"Services"
        }
    ],
    "sg:phone":"+61 7 4743 7303",
    "sg:postcode":"4825",
    "sg:province":"QLD",
    "sg:tags":[
        "hairdresser"
    ],
    "wof:name":"Room Seventy Seven Hairdressing",
    "wof:placetype":"venue"
},
  "geometry": {"coordinates":[139.492737,-20.727215],"type":"Point"}
}