{
  "type": "Feature",
  "properties": {
    "iso:country":"AU",
    "sg:address":"1370 Main Rd",
    "sg:city":"Eltham",
    "sg:classifiers":[
        {
            "category":"Professional",
            "subcategory":"Art Services",
            "type":"Services"
        }
    ],
    "sg:phone":"+61 3 9439 8562",
    "sg:postcode":"3095",
    "sg:province":"VIC",
    "sg:tags":[
        "decorator",
        "painter"
    ],
    "wof:name":"M & M Richardson",
    "wof:placetype":"venue"
},
  "geometry": {"coordinates":[145.168869019,-37.7024879456],"type":"Point"}
}