{
  "type": "Feature",
  "properties": {
    "addr:full":"33 Main Rd Wivenhoe TAS 7320",
    "addr:housenumber":"33",
    "addr:postcode":"7320",
    "addr:street":"Main Rd",
    "iso:country":"AU",
    "sg:address":"33 Main Rd",
    "sg:city":"Wivenhoe",
    "sg:classifiers":[
        {
            "category":"Building & Trades",
            "subcategory":"Construction",
            "type":"Services"
        }
    ],
    "sg:phone":"+61 419 531 146",
    "sg:postcode":"7320",
    "sg:province":"TAS",
    "sg:tags":[
        "earth",
        "excavating",
        "moving",
        "contractor"
    ],
    "wof:name":"David Jessup",
    "wof:placetype":"venue"
},
  "geometry": {"coordinates":[145.93438699999999,-41.06797],"type":"Point"}
}