{
  "type": "Feature",
  "properties": {
    "addr:full":"PO Box 7138 McMahons Point NSW 2060",
    "addr:postcode":"2060",
    "iso:country":"AU",
    "sg:address":"PO Box 7138",
    "sg:city":"McMahons Point",
    "sg:classifiers":[
        {
            "category":"Professional",
            "subcategory":"Management & Consulting",
            "type":"Services"
        }
    ],
    "sg:phone":"+61 2 9956 5309",
    "sg:postcode":"2060",
    "sg:province":"NSW",
    "sg:tags":[
        "consultant"
    ],
    "wof:name":"Syntropy Pty Ltd",
    "wof:placetype":"venue"
},
  "geometry": {"coordinates":[151.20399475100001,-33.8462905884],"type":"Point"}
}