{
  "type": "Feature",
  "properties": {
    "addr:full":"24 Wilga Rd Pampoolah NSW 2430",
    "addr:housenumber":"24",
    "addr:postcode":"2430",
    "addr:street":"Wilga Rd",
    "iso:country":"AU",
    "sg:address":"24 Wilga Rd",
    "sg:city":"Pampoolah",
    "sg:classifiers":[
        {
            "category":"Building & Trades",
            "subcategory":"Construction",
            "type":"Services"
        }
    ],
    "sg:phone":"+61 418 656 678",
    "sg:postcode":"2430",
    "sg:province":"NSW",
    "sg:tags":[
        "earth",
        "excavating",
        "moving",
        "contractor"
    ],
    "wof:name":"Peter Dale Excavations",
    "wof:placetype":"venue"
},
  "geometry": {"coordinates":[152.52006499999999,-31.943989],"type":"Point"}
}