{
  "type": "Feature",
  "properties": {
    "iso:country":"AU",
    "sg:address":"Shop 3, 57 Smart St",
    "sg:city":"Fairfield",
    "sg:classifiers":[
        {
            "category":"Banks & Credit Unions",
            "subcategory":"Investment Brokerage",
            "type":"Services"
        }
    ],
    "sg:phone":"+61 2 9724 0444",
    "sg:postcode":"2165",
    "sg:province":"NSW",
    "sg:tags":[
        "management",
        "property"
    ],
    "wof:name":"Acclaim Real Estate",
    "wof:placetype":"venue"
},
  "geometry": {"coordinates":[150.95309448200001,-33.8655853271],"type":"Point"}
}