{
  "type": "Feature",
  "properties": {
    "addr:full":"122 Dawson St Ballarat South VIC 3350",
    "addr:housenumber":"122",
    "addr:postcode":"3350",
    "addr:street":"Dawson St",
    "iso:country":"AU",
    "sg:address":"122 Dawson St",
    "sg:city":"Ballarat South",
    "sg:classifiers":[
        {
            "category":"Wholesale",
            "subcategory":"Machinery & Supplies",
            "type":"Manufacturing & Wholesale Goods"
        }
    ],
    "sg:phone":"+61 419 355 497",
    "sg:postcode":"3350",
    "sg:province":"VIC",
    "sg:tags":[
        "instrument"
    ],
    "wof:name":"Tom Taranto Instruments",
    "wof:placetype":"venue"
},
  "geometry": {"coordinates":[143.85243199999999,-37.565556],"type":"Point"}
}