{
  "type": "Feature",
  "properties": {
    "addr:full":"8 Jordan Ave Lammermoor QLD 4703",
    "addr:housenumber":"8",
    "addr:postcode":"4703",
    "addr:street":"Jordan Ave",
    "iso:country":"AU",
    "sg:address":"8 Jordan Ave",
    "sg:city":"Lammermoor",
    "sg:classifiers":[
        {
            "category":"Building & Trades",
            "subcategory":"Construction",
            "type":"Services"
        }
    ],
    "sg:phone":"+61 7 4933 7767",
    "sg:postcode":"4703",
    "sg:province":"QLD",
    "sg:tags":[
        "contractor"
    ],
    "wof:name":"Radana Pty Ltd",
    "wof:placetype":"venue"
},
  "geometry": {"coordinates":[150.757446289,-23.1581764221],"type":"Point"}
}