{
  "type": "Feature",
  "properties": {
    "addr:full":"120 Perouse Rd Randwick NSW 2031",
    "addr:housenumber":"120",
    "addr:postcode":"2031",
    "addr:street":"Perouse Rd",
    "iso:country":"AU",
    "sg:address":"120 Perouse Rd",
    "sg:city":"Randwick",
    "sg:classifiers":[
        {
            "category":"Manufacturing",
            "subcategory":"Furniture",
            "type":"Manufacturing & Wholesale Goods"
        }
    ],
    "sg:phone":"+61 439 731 889",
    "sg:postcode":"2031",
    "sg:province":"NSW",
    "sg:tags":[
        "builder",
        "designer",
        "custom"
    ],
    "wof:name":"Harry Howard Fine Furniture",
    "wof:placetype":"venue"
},
  "geometry": {"coordinates":[151.243743897,-33.9231109619],"type":"Point"}
}