{
  "type": "Feature",
  "properties": {
    "addr:full":"Level 30, 400 George St Sydney NSW 2000",
    "addr:housenumber":"400",
    "addr:postcode":"2000",
    "addr:street":"George St",
    "iso:country":"AU",
    "sg:address":"Level 30, 400 George St",
    "sg:city":"Sydney",
    "sg:classifiers":[
        {
            "category":"Shopping Center",
            "type":"Public Place"
        }
    ],
    "sg:phone":"+61 2 8233 6224",
    "sg:postcode":"2000",
    "sg:province":"NSW",
    "sg:tags":[
        "trade"
    ],
    "wof:name":"IDA Ireland",
    "wof:placetype":"venue"
},
  "geometry": {"coordinates":[151.207122803,-33.8691177368],"type":"Point"}
}