{
  "type": "Feature",
  "properties": {
    "addr:full":"67 Grey St South Brisbane QLD 4101",
    "addr:housenumber":"67",
    "addr:postcode":"4101",
    "addr:street":"Grey St",
    "iso:country":"AU",
    "sg:address":"67 Grey St",
    "sg:city":"South Brisbane",
    "sg:classifiers":[
        {
            "category":"Banks & Credit Unions",
            "subcategory":"Financial Services",
            "type":"Services"
        }
    ],
    "sg:phone":"+61 7 3011 8600",
    "sg:postcode":"4101",
    "sg:province":"QLD",
    "sg:tags":[
        "annuity",
        "rollover",
        "superannuation",
        "consultant"
    ],
    "wof:name":"Asteron Limited",
    "wof:placetype":"venue"
},
  "geometry": {"coordinates":[153.016845703,-27.4719791412],"type":"Point"}
}