{
  "type": "Feature",
  "properties": {
    "iso:country":"AU",
    "sg:address":"1032a North Rd",
    "sg:city":"Bentleigh East",
    "sg:classifiers":[
        {
            "category":"Building & Trades",
            "subcategory":"Cleaning & Sanitation",
            "type":"Services"
        }
    ],
    "sg:phone":"+61 500 880 056",
    "sg:postcode":"3165",
    "sg:province":"VIC",
    "sg:tags":[
        "cleaner",
        "repairer",
        "roof"
    ],
    "wof:name":"Flexi Shield",
    "wof:placetype":"venue"
},
  "geometry": {"coordinates":[145.07432556099999,-37.9082565308],"type":"Point"}
}