{
  "type": "Feature",
  "properties": {
    "addr:full":"72 Dayboro Rd Petrie QLD 4502",
    "addr:housenumber":"72",
    "addr:postcode":"4502",
    "addr:street":"Dayboro Rd",
    "iso:country":"AU",
    "sg:address":"72 Dayboro Rd",
    "sg:city":"Petrie",
    "sg:classifiers":[
        {
            "category":"Building & Trades",
            "subcategory":"Construction",
            "type":"Services"
        }
    ],
    "sg:phone":"+61 7 3285 1039",
    "sg:postcode":"4502",
    "sg:province":"QLD",
    "sg:tags":[
        "concrete",
        "contractor"
    ],
    "wof:name":"Payne Roadmarkers",
    "wof:placetype":"venue"
},
  "geometry": {"coordinates":[152.977172852,-27.2694034576],"type":"Point"}
}