{
  "type": "Feature",
  "properties": {
    "iso:country":"AU",
    "sg:address":"Lot 5, Kyte Pl",
    "sg:city":"Tumbi Umbi",
    "sg:classifiers":[
        {
            "category":"Social Services",
            "type":"Services"
        }
    ],
    "sg:phone":"+61 2 4385 1299",
    "sg:postcode":"2261",
    "sg:province":"NSW",
    "sg:tags":[
        "domestic",
        "help"
    ],
    "wof:name":"Dial&#039;N&#039;Ironer",
    "wof:placetype":"venue"
},
  "geometry": {"coordinates":[151.46090699999999,-33.396873],"type":"Point"}
}