{
  "type": "Feature",
  "properties": {
    "iso:country":"AU",
    "sg:address":"Unit 4/ 158 Princes Hwy",
    "sg:city":"Nowra South",
    "sg:classifiers":[
        {
            "category":"Building & Trades",
            "subcategory":"Equipment Rental",
            "type":"Services"
        }
    ],
    "sg:phone":"+61 2 4423 1574",
    "sg:postcode":"2541",
    "sg:province":"NSW",
    "sg:tags":[
        "supply",
        "catering"
    ],
    "wof:name":"Shoalhaven Commercial Catering Equipment",
    "wof:placetype":"venue"
},
  "geometry": {"coordinates":[150.603683472,-34.9137878418],"type":"Point"}
}