{
  "type": "Feature",
  "properties": {
    "addr:full":"2 Waters St Rapid Creek NT 0810",
    "addr:housenumber":"2",
    "addr:postcode":"nt 0810",
    "addr:street":"Waters St",
    "iso:country":"AU",
    "sg:address":"2 Waters St",
    "sg:city":"Rapid Creek",
    "sg:classifiers":[
        {
            "category":"Education",
            "subcategory":"Special Training",
            "type":"Public Place"
        }
    ],
    "sg:phone":"+61 8 8948 4933",
    "sg:postcode":"0810",
    "sg:province":"NT",
    "sg:tags":[
        "tuition-educational"
    ],
    "wof:name":"Kip McGrath Education Centres",
    "wof:placetype":"venue"
},
  "geometry": {"coordinates":[130.85911560100001,-12.386472702],"type":"Point"}
}