{
  "type": "Feature",
  "properties": {
    "addr:full":"260 Leach Hwy (Cnr Norma Rd) Booragoon WA 6154",
    "addr:housenumber":"260",
    "addr:postcode":"6154",
    "addr:street":"Leach Hwy Cnr Norma Rd",
    "iso:country":"AU",
    "sg:address":"260 Leach Hwy (Cnr Norma Rd)",
    "sg:city":"Booragoon",
    "sg:classifiers":[
        {
            "category":"Health Services",
            "subcategory":"Doctor",
            "type":"Services"
        }
    ],
    "sg:phone":"+61 8 9317 8488",
    "sg:postcode":"6154",
    "sg:province":"WA",
    "sg:tags":[
        "medical",
        "practitioner"
    ],
    "wof:name":"Perth Radiological Clinic",
    "wof:placetype":"venue"
},
  "geometry": {"coordinates":[115.81935900000001,-32.045918],"type":"Point"}
}