{
  "type": "Feature",
  "properties": {
    "addr:full":"First Ave Woorim QLD 4507",
    "addr:postcode":"4507",
    "addr:street":"First Ave",
    "iso:country":"AU",
    "sg:address":"First Ave",
    "sg:city":"Woorim",
    "sg:classifiers":[
        {
            "category":"Arena",
            "subcategory":"Sports Club",
            "type":"Entertainment"
        }
    ],
    "sg:phone":"+61 7 3408 1188",
    "sg:postcode":"4507",
    "sg:province":"QLD",
    "sg:tags":[
        "life",
        "surfing",
        "saving"
    ],
    "wof:name":"Bribie Island Surf Life Saving Club",
    "wof:placetype":"venue"
},
  "geometry": {"coordinates":[153.199615478,-27.0712661743],"type":"Point"}
}