{
  "type": "Feature",
  "properties": {
    "addr:full":"60 South Park Drv Dandenong South VIC 3175",
    "addr:housenumber":"60",
    "addr:postcode":"3175",
    "addr:street":"South Park Drv",
    "iso:country":"AU",
    "sg:address":"60 South Park Drv",
    "sg:city":"Dandenong South",
    "sg:classifiers":[
        {
            "category":"Wholesale",
            "subcategory":"Drugs",
            "type":"Manufacturing & Wholesale Goods"
        }
    ],
    "sg:phone":"+61 3 9554 0500",
    "sg:postcode":"3175",
    "sg:province":"VIC",
    "sg:tags":[
        "wholesaler",
        "pharmaceutical",
        "product",
        "mfrs"
    ],
    "wof:name":"CH2 Clifford Hallam Healthcare",
    "wof:placetype":"venue"
},
  "geometry": {"coordinates":[145.20185852,-38.0133209229],"type":"Point"}
}