{
  "type": "Feature",
  "properties": {
    "addr:full":"439 Whitehorse Rd Balwyn VIC 3103",
    "addr:housenumber":"439",
    "addr:postcode":"3103",
    "addr:street":"Whitehorse Rd",
    "iso:country":"AU",
    "sg:address":"439 Whitehorse Rd",
    "sg:city":"Balwyn",
    "sg:classifiers":[
        {
            "category":"Food & Beverages",
            "subcategory":"Bakery",
            "type":"Retail Goods"
        }
    ],
    "sg:phone":"+61 3 9888 4940",
    "sg:postcode":"3103",
    "sg:province":"VIC",
    "sg:tags":[
        "baker"
    ],
    "wof:name":"Brumby's Bakeries",
    "wof:placetype":"venue"
},
  "geometry": {"coordinates":[145.085174561,-37.813167572],"type":"Point"}
}