{
  "type": "Feature",
  "properties": {
    "addr:full":"55 Maroonda Hwy Alexandra VIC 3714",
    "addr:housenumber":"55",
    "addr:postcode":"3714",
    "addr:street":"Maroonda Hwy",
    "iso:country":"AU",
    "sg:address":"55 Maroonda Hwy",
    "sg:city":"Alexandra",
    "sg:classifiers":[
        {
            "category":"Retail",
            "subcategory":"Repair Shop",
            "type":"Services"
        }
    ],
    "sg:phone":"+61 3 5772 0400",
    "sg:postcode":"3714",
    "sg:province":"VIC",
    "sg:tags":[
        "maintenance",
        "pool",
        "swimming"
    ],
    "wof:name":"Alexander Pools",
    "wof:placetype":"venue"
},
  "geometry": {"coordinates":[145.69844055199999,-37.1854629517],"type":"Point"}
}