{
  "type": "Feature",
  "properties": {
    "addr:full":"67 Enterprise Ave Berwick VIC 3806",
    "addr:housenumber":"67",
    "addr:postcode":"3806",
    "addr:street":"Enterprise Ave",
    "iso:country":"AU",
    "sg:address":"67 Enterprise Ave",
    "sg:city":"Berwick",
    "sg:classifiers":[
        {
            "category":"Autos & Motor Vehicles",
            "subcategory":"Auto Supplies",
            "type":"Retail Goods"
        }
    ],
    "sg:phone":"+61 1800 676 317",
    "sg:postcode":"3806",
    "sg:province":"VIC",
    "sg:tags":[
        "garage",
        "equipment"
    ],
    "sg:website":"http://www.alljacks.com.au",
    "wof:name":"Alljacks & Hoists Pty Ltd",
    "wof:placetype":"venue"
},
  "geometry": {"coordinates":[145.33555602999999,-38.0361595154],"type":"Point"}
}