{
  "type": "Feature",
  "properties": {
    "iso:country":"AU",
    "sg:address":"116 Dandaloo St",
    "sg:city":"Narromine",
    "sg:classifiers":[
        {
            "category":"Travel",
            "subcategory":"Hotels & Motels",
            "type":"Entertainment"
        }
    ],
    "sg:phone":"+61 2 6889 1017",
    "sg:postcode":"2821",
    "sg:province":"NSW",
    "wof:name":"Narromine Hotel-Motel",
    "wof:placetype":"venue"
},
  "geometry": {"coordinates":[148.23928832999999,-32.2344703674],"type":"Point"}
}