{
  "type": "Feature",
  "properties": {
    "addr:full":"Orkney St Wangaratta VIC 3677",
    "addr:postcode":"3677",
    "addr:street":"Orkney St",
    "iso:country":"AU",
    "sg:address":"Orkney St",
    "sg:city":"Wangaratta",
    "sg:classifiers":[
        {
            "category":"Education",
            "subcategory":"Kindergarten",
            "type":"Public Place"
        }
    ],
    "sg:phone":"+61 3 5721 6017",
    "sg:postcode":"3677",
    "sg:province":"VIC",
    "sg:tags":[
        "pre-schools"
    ],
    "wof:name":"Wangaratta West",
    "wof:placetype":"venue"
},
  "geometry": {"coordinates":[146.29881286599999,-36.3534049988],"type":"Point"}
}