{
  "type": "Feature",
  "properties": {
    "addr:full":"PO Box 8317 Rockhampton QLD 4702",
    "addr:postcode":"4702",
    "iso:country":"AU",
    "sg:address":"PO Box 8317",
    "sg:city":"Rockhampton",
    "sg:classifiers":[
        {
            "category":"Utilities",
            "subcategory":"Cable",
            "type":"Services"
        }
    ],
    "sg:phone":"+61 427 473 176",
    "sg:postcode":"4702",
    "sg:province":"QLD",
    "sg:tags":[
        "agricultural",
        "aerial"
    ],
    "wof:name":"Frederickson Air Service Pty Ltd",
    "wof:placetype":"venue"
},
  "geometry": {"coordinates":[150.43182373100001,-25.0342769623],"type":"Point"}
}