{
  "type": "Feature",
  "properties": {
    "addr:full":"18 Fearn Ave Margaret River WA 6285",
    "addr:housenumber":"18",
    "addr:postcode":"6285",
    "addr:street":"Fearn Ave",
    "iso:country":"AU",
    "sg:address":"18 Fearn Ave",
    "sg:city":"Margaret River",
    "sg:classifiers":[
        {
            "category":"Real Estate",
            "subcategory":"Real Estate Agent",
            "type":"Services"
        }
    ],
    "sg:phone":"+61 8 9757 9847",
    "sg:postcode":"6285",
    "sg:province":"WA",
    "wof:name":"Prater Real Estate Pty Ltd",
    "wof:placetype":"venue"
},
  "geometry": {"coordinates":[115.072410584,-33.9513015747],"type":"Point"}
}