{
  "type": "Feature",
  "properties": {
    "addr:full":"Factory 2/ 5 Macro Crt Rowville VIC 3178",
    "addr:housenumber":"/ 5",
    "addr:postcode":"3178",
    "addr:street":"Macro Crt",
    "iso:country":"AU",
    "sg:address":"Factory 2/ 5 Macro Crt",
    "sg:city":"Rowville",
    "sg:classifiers":[
        {
            "category":"Professional",
            "type":"Services"
        }
    ],
    "sg:phone":"+61 3 9764 8155",
    "sg:postcode":"3178",
    "sg:province":"VIC",
    "sg:tags":[
        "coating",
        "powder"
    ],
    "wof:name":"Galaxy Sheet Metal Pty Ltd",
    "wof:placetype":"venue"
},
  "geometry": {"coordinates":[145.24612426799999,-37.9090499878],"type":"Point"}
}