{
  "type": "Feature",
  "properties": {
    "addr:full":"3 Baldwin St Golden Beach QLD 4551",
    "addr:housenumber":"3",
    "addr:postcode":"4551",
    "addr:street":"Baldwin St",
    "iso:country":"AU",
    "sg:address":"3 Baldwin St",
    "sg:city":"Golden Beach",
    "sg:classifiers":[
        {
            "category":"Travel",
            "subcategory":"Hotels & Motels",
            "type":"Entertainment"
        }
    ],
    "sg:phone":"+61 7 5491 2344",
    "sg:postcode":"4551",
    "sg:province":"QLD",
    "wof:name":"Golden Beach Motor Inn",
    "wof:placetype":"venue"
},
  "geometry": {"coordinates":[153.120040894,-26.8049697876],"type":"Point"}
}