{
  "type": "Feature",
  "properties": {
    "iso:country":"AU",
    "sg:address":"7095 Great Eastern Hwy",
    "sg:city":"Mundaring",
    "sg:classifiers":[
        {
            "category":"Banks & Credit Unions",
            "subcategory":"Bank",
            "type":"Services"
        }
    ],
    "sg:phone":"+61 8 9295 3474",
    "sg:postcode":"6073",
    "sg:province":"WA",
    "sg:tags":[
        "broker",
        "mortgage"
    ],
    "wof:name":"Mortgage Magnet.",
    "wof:placetype":"venue"
},
  "geometry": {"coordinates":[116.16526794400001,-31.9015922546],"type":"Point"}
}