{
  "type": "Feature",
  "properties": {
    "iso:country":"AU",
    "sg:address":"9 St Georges Pde",
    "sg:city":"Hurstville",
    "sg:classifiers":[
        {
            "category":"Professional",
            "subcategory":"Computer Services",
            "type":"Services"
        }
    ],
    "sg:phone":"+61 402 848 202",
    "sg:postcode":"2220",
    "sg:province":"NSW",
    "sg:tags":[
        "consultant",
        "system"
    ],
    "wof:name":"Krishnan Raja",
    "wof:placetype":"venue"
},
  "geometry": {"coordinates":[151.106887817,-33.9692687988],"type":"Point"}
}