{
  "type": "Feature",
  "properties": {
    "addr:full":"Shp11/Wharf2/ Circular Qy Sydney NSW 2000",
    "addr:postcode":"2000",
    "iso:country":"AU",
    "sg:address":"Shp11/Wharf2/ Circular Qy",
    "sg:city":"Sydney",
    "sg:classifiers":[
        {
            "category":"Cafe",
            "type":"Food & Drink"
        }
    ],
    "sg:phone":"+61 2 9247 3648",
    "sg:postcode":"2000",
    "sg:province":"NSW",
    "wof:name":"Quay Express",
    "wof:placetype":"venue"
},
  "geometry": {"coordinates":[151.20893859899999,-33.8588409424],"type":"Point"}
}