{
  "type": "Feature",
  "properties": {
    "iso:country":"AU",
    "sg:address":"101 Princes Hwy",
    "sg:city":"Yarragon",
    "sg:classifiers":[
        {
            "category":"Personal",
            "subcategory":"Beauty Salon",
            "type":"Services"
        }
    ],
    "sg:phone":"+61 3 5634 2248",
    "sg:postcode":"3823",
    "sg:province":"VIC",
    "wof:name":"Studio Y",
    "wof:placetype":"venue"
},
  "geometry": {"coordinates":[146.078842,-38.20462],"type":"Point"}
}