{
  "type": "Feature",
  "properties": {
    "addr:full":"123 South Rd Thebarton SA 5031",
    "addr:housenumber":"123",
    "addr:postcode":"5031",
    "addr:street":"South Rd",
    "iso:country":"AU",
    "sg:address":"123 South Rd",
    "sg:city":"Thebarton",
    "sg:classifiers":[
        {
            "category":"Professional",
            "subcategory":"Computer Services",
            "type":"Services"
        }
    ],
    "sg:phone":"+61 1800 307 595",
    "sg:postcode":"5031",
    "sg:province":"SA",
    "sg:tags":[
        "package",
        "software"
    ],
    "wof:name":"John Temple Group",
    "wof:placetype":"venue"
},
  "geometry": {"coordinates":[138.568634033,-34.9201927185],"type":"Point"}
}