{
  "type": "Feature",
  "properties": {
    "iso:country":"AU",
    "sg:address":"113 Melba Drv",
    "sg:city":"East Ryde",
    "sg:classifiers":[
        {
            "category":"Personal",
            "subcategory":"Beauty Salon",
            "type":"Services"
        }
    ],
    "sg:phone":"+61 2 9888 7367",
    "sg:postcode":"2113",
    "sg:province":"NSW",
    "sg:tags":[
        "hairdresser"
    ],
    "wof:name":"Lidias Hairdressing",
    "wof:placetype":"venue"
},
  "geometry": {"coordinates":[151.13870239299999,-33.8118400574],"type":"Point"}
}