{
  "type": "Feature",
  "properties": {
    "iso:country":"AU",
    "sg:address":"Unit 11, 3 King Edward Rd",
    "sg:city":"Osborne Park",
    "sg:classifiers":[
        {
            "category":"Shopping",
            "subcategory":"Stationery & Office Supplies",
            "type":"Retail Goods"
        }
    ],
    "sg:phone":"+61 8 9204 1555",
    "sg:postcode":"6017",
    "sg:province":"WA",
    "sg:tags":[
        "equipment",
        "facsimile"
    ],
    "wof:name":"Sharp Facsimiles Can Also Be Repaired By The Fax Clinics Specialist Repairers Pt",
    "wof:placetype":"venue"
},
  "geometry": {"coordinates":[115.804450989,-31.9037075043],"type":"Point"}
}