{
  "type": "Feature",
  "properties": {
    "addr:full":"Shop 4/ 196 Main St Osborne Park WA 6017",
    "addr:housenumber":"shop 4 / 196",
    "addr:postcode":"6017",
    "addr:street":"Main St",
    "iso:country":"AU",
    "sg:address":"Shop 4/ 196 Main St",
    "sg:city":"Osborne Park",
    "sg:classifiers":[
        {
            "category":"Travel",
            "subcategory":"Travel Agent",
            "type":"Entertainment"
        }
    ],
    "sg:phone":"+61 8 9345 5455",
    "sg:postcode":"6017",
    "sg:province":"WA",
    "sg:tags":[
        "consultant"
    ],
    "wof:name":"Jetset Travel-Osborne Park",
    "wof:placetype":"venue"
},
  "geometry": {"coordinates":[115.828422546,-31.8982028961],"type":"Point"}
}