{
  "type": "Feature",
  "properties": {
    "iso:country":"AU",
    "sg:address":"326 Peel St",
    "sg:city":"Tamworth",
    "sg:classifiers":[
        {
            "category":"Shopping",
            "subcategory":"Pawn Shop",
            "type":"Retail Goods"
        }
    ],
    "sg:phone":"+61 2 6766 9994",
    "sg:postcode":"2340",
    "sg:province":"NSW",
    "sg:tags":[
        "pawnbroker"
    ],
    "wof:name":"Cash Exchange",
    "wof:placetype":"venue"
},
  "geometry": {"coordinates":[150.929244995,-31.0897102356],"type":"Point"}
}