{
  "type": "Feature",
  "properties": {
    "addr:full":"858 Nudgee Rd Northgate QLD 4013",
    "addr:housenumber":"858",
    "addr:postcode":"4013",
    "addr:street":"Nudgee Rd",
    "iso:country":"AU",
    "sg:address":"858 Nudgee Rd",
    "sg:city":"Northgate",
    "sg:classifiers":[
        {
            "category":"Commercial Area",
            "type":"Public Place"
        }
    ],
    "sg:phone":"+61 7 3266 6533",
    "sg:postcode":"4013",
    "sg:province":"QLD",
    "sg:tags":[
        "heavy",
        "carrier"
    ],
    "wof:name":"H F Palmer & Sons Transport",
    "wof:placetype":"venue"
},
  "geometry": {"coordinates":[153.08172607399999,-27.3909568787],"type":"Point"}
}