{
  "type": "Feature",
  "properties": {
    "addr:full":"43 Clifton St Euroa VIC 3666",
    "addr:housenumber":"43",
    "addr:postcode":"3666",
    "addr:street":"Clifton St",
    "iso:country":"AU",
    "sg:address":"43 Clifton St",
    "sg:city":"Euroa",
    "sg:classifiers":[
        {
            "category":"Wholesale",
            "subcategory":"Farm Supplies",
            "type":"Manufacturing & Wholesale Goods"
        }
    ],
    "sg:phone":"+61 3 5795 3033",
    "sg:postcode":"3666",
    "sg:province":"VIC",
    "sg:tags":[
        "equipment"
    ],
    "wof:name":"Ausrural",
    "wof:placetype":"venue"
},
  "geometry": {"coordinates":[145.56681823700001,-36.7581748962],"type":"Point"}
}