{
  "type": "Feature",
  "properties": {
    "addr:full":"34 Donegal Rd Lonsdale SA 5160",
    "addr:housenumber":"34",
    "addr:postcode":"5160",
    "addr:street":"Donegal Rd",
    "iso:country":"AU",
    "sg:address":"34 Donegal Rd",
    "sg:city":"Lonsdale",
    "sg:classifiers":[
        {
            "category":"Manufacturing",
            "subcategory":"Tools & Machinery",
            "type":"Manufacturing & Wholesale Goods"
        }
    ],
    "sg:phone":"+61 8 8382 2456",
    "sg:postcode":"5160",
    "sg:province":"SA",
    "sg:tags":[
        "manufactured",
        "specially",
        "designed"
    ],
    "wof:name":"Quadmech Engineering Pty Ltd",
    "wof:placetype":"venue"
},
  "geometry": {"coordinates":[138.494216919,-35.1192626953],"type":"Point"}
}