{
  "type": "Feature",
  "properties": {
    "addr:full":"Main St Timboon VIC 3268",
    "addr:postcode":"3268",
    "addr:street":"Main St",
    "iso:country":"AU",
    "sg:address":"Main St",
    "sg:city":"Timboon",
    "sg:classifiers":[
        {
            "category":"Professional",
            "subcategory":"Accounting & Tax Preparation",
            "type":"Services"
        }
    ],
    "sg:phone":"+61 3 5598 3019",
    "sg:postcode":"3268",
    "sg:province":"VIC",
    "sg:tags":[
        "accountant",
        "auditor"
    ],
    "wof:name":"Noonan Ron A",
    "wof:placetype":"venue"
},
  "geometry": {"coordinates":[142.968353272,-38.4829101562],"type":"Point"}
}