{
  "type": "Feature",
  "properties": {
    "addr:full":"Hoopers Rd Chewton VIC 3451",
    "addr:postcode":"3451",
    "addr:street":"Hoopers Rd",
    "iso:country":"AU",
    "sg:address":"Hoopers Rd",
    "sg:city":"Chewton",
    "sg:classifiers":[
        {
            "category":"Manufacturing",
            "subcategory":"Pottery",
            "type":"Manufacturing & Wholesale Goods"
        }
    ],
    "sg:phone":"+61 3 5470 5544",
    "sg:postcode":"3451",
    "sg:province":"VIC",
    "wof:name":"Yerangle Pottery",
    "wof:placetype":"venue"
},
  "geometry": {"coordinates":[144.26490783700001,-37.0960464478],"type":"Point"}
}