{
  "type": "Feature",
  "properties": {
    "addr:full":"Forest Lake Blv Forest Lake QLD 4078",
    "addr:postcode":"4078",
    "addr:street":"Forest Lake Blv",
    "iso:country":"AU",
    "sg:address":"Forest Lake Blv",
    "sg:city":"Forest Lake",
    "sg:classifiers":[
        {
            "category":"Fast Food",
            "type":"Food & Drink"
        }
    ],
    "sg:phone":"+61 7 3278 8566",
    "sg:postcode":"4078",
    "sg:province":"QLD",
    "sg:tags":[
        "away",
        "take"
    ],
    "wof:name":"Star Doner Kebabs",
    "wof:placetype":"venue"
},
  "geometry": {"coordinates":[153.02505493199999,-27.6665706635],"type":"Point"}
}