{
  "type": "Feature",
  "properties": {
    "addr:full":"24 Lightfoot St Shepparton VIC 3630",
    "addr:housenumber":"24",
    "addr:postcode":"3630",
    "addr:street":"Lightfoot St",
    "iso:country":"AU",
    "sg:address":"24 Lightfoot St",
    "sg:city":"Shepparton",
    "sg:classifiers":[
        {
            "category":"Real Estate",
            "subcategory":"Surveying",
            "type":"Services"
        }
    ],
    "sg:phone":"+61 3 5821 4776",
    "sg:postcode":"3630",
    "sg:province":"VIC",
    "sg:tags":[
        "surveyor",
        "land"
    ],
    "wof:name":"Onley Consulting",
    "wof:placetype":"venue"
},
  "geometry": {"coordinates":[145.40008544899999,-36.3721313477],"type":"Point"}
}