{
  "type": "Feature",
  "properties": {
    "addr:full":"211 March St Orange NSW 2800",
    "addr:housenumber":"211",
    "addr:postcode":"2800",
    "addr:street":"March St",
    "iso:country":"AU",
    "sg:address":"211 March St",
    "sg:city":"Orange",
    "sg:classifiers":[
        {
            "category":"Organizations",
            "subcategory":"Community Association",
            "type":"Services"
        }
    ],
    "sg:phone":"+61 2 6361 4883",
    "sg:postcode":"2800",
    "sg:province":"NSW",
    "sg:tags":[
        "organisation",
        "family",
        "welfare"
    ],
    "wof:name":"Orange Family Support Service",
    "wof:placetype":"venue"
},
  "geometry": {"coordinates":[149.113769531,-33.2814331055],"type":"Point"}
}