{
  "type": "Feature",
  "properties": {
    "iso:country":"AU",
    "sg:address":"399 Gympie Rd",
    "sg:city":"Strathpine",
    "sg:classifiers":[
        {
            "category":"Autos & Motor Vehicles",
            "subcategory":"Automobile Sales",
            "type":"Retail Goods"
        }
    ],
    "sg:phone":"+61 7 3205 2057",
    "sg:postcode":"4500",
    "sg:province":"QLD",
    "sg:tags":[
        "car",
        "used"
    ],
    "wof:name":"J B C Cars",
    "wof:placetype":"venue"
},
  "geometry": {"coordinates":[152.988845825,-27.302406311],"type":"Point"}
}