{
  "type": "Feature",
  "properties": {
    "iso:country":"AU",
    "sg:address":"41 Montpellier Drv",
    "sg:city":"Avondale Heights",
    "sg:classifiers":[
        {
            "category":"Personal",
            "subcategory":"Massage",
            "type":"Services"
        }
    ],
    "sg:phone":"+61 401 007 140",
    "sg:postcode":"3034",
    "sg:province":"VIC",
    "sg:tags":[
        "therapy"
    ],
    "wof:name":"Justin Oosterhof",
    "wof:placetype":"venue"
},
  "geometry": {"coordinates":[144.86586,-37.754833],"type":"Point"}
}