{
  "type": "Feature",
  "properties": {
    "addr:full":"Cnr Queen & Therry Sts Melbourne VIC 3000",
    "addr:postcode":"3000",
    "addr:street":"Cnr",
    "iso:country":"AU",
    "sg:address":"Cnr Queen & Therry Sts",
    "sg:city":"Melbourne",
    "sg:classifiers":[
        {
            "category":"Social Services",
            "subcategory":"Adult Care",
            "type":"Services"
        }
    ],
    "sg:phone":"+61 419 002 235",
    "sg:postcode":"3000",
    "sg:province":"VIC",
    "sg:tags":[
        "towing"
    ],
    "wof:name":"Boys Towing Service",
    "wof:placetype":"venue"
},
  "geometry": {"coordinates":[144.96061706500001,-37.8068847656],"type":"Point"}
}