{
  "type": "Feature",
  "properties": {
    "iso:country":"AU",
    "sg:address":"Level 4 1945 Varsity Pde",
    "sg:city":"Varsity Lakes",
    "sg:classifiers":[
        {
            "category":"Insurance",
            "subcategory":"Insurance Agent",
            "type":"Services"
        }
    ],
    "sg:phone":"+61 7 5553 8900",
    "sg:postcode":"4227",
    "sg:province":"QLD",
    "sg:tags":[
        "broker"
    ],
    "wof:name":"Aon Risk Services",
    "wof:placetype":"venue"
},
  "geometry": {"coordinates":[153.41111755399999,-28.0794372559],"type":"Point"}
}