{
  "type": "Feature",
  "properties": {
    "addr:full":"62 Hardware La Melbourne VIC 3000",
    "addr:postcode":"3000",
    "addr:street":"La",
    "iso:country":"AU",
    "sg:address":"62 Hardware La",
    "sg:city":"Melbourne",
    "sg:classifiers":[
        {
            "category":"Shopping",
            "subcategory":"Jewelry",
            "type":"Retail Goods"
        }
    ],
    "sg:phone":"+61 3 9602 2153",
    "sg:postcode":"3000",
    "sg:province":"VIC",
    "sg:tags":[
        "jeweller"
    ],
    "wof:name":"Diamond Affaire",
    "wof:placetype":"venue"
},
  "geometry": {"coordinates":[144.961227417,-37.813243866],"type":"Point"}
}