{
  "type": "Feature",
  "properties": {
    "iso:country":"AU",
    "sg:address":"38 Maitland Rd",
    "sg:city":"Islington",
    "sg:classifiers":[
        {
            "category":"Autos & Motor Vehicles",
            "subcategory":"Automobile Sales",
            "type":"Retail Goods"
        }
    ],
    "sg:phone":"+61 2 4940 0200",
    "sg:postcode":"2296",
    "sg:province":"NSW",
    "sg:tags":[
        "car",
        "used"
    ],
    "wof:name":"National Auto Wholesale",
    "wof:placetype":"venue"
},
  "geometry": {"coordinates":[151.75050354000001,-32.9187088013],"type":"Point"}
}