{
  "type": "Feature",
  "properties": {
    "addr:full":"22 Bellevue Rd Bellevue Hill NSW 2023",
    "addr:housenumber":"22",
    "addr:postcode":"2023",
    "addr:street":"Bellevue Rd",
    "iso:country":"AU",
    "sg:address":"22 Bellevue Rd",
    "sg:city":"Bellevue Hill",
    "sg:classifiers":[
        {
            "category":"Deli",
            "type":"Food & Drink"
        }
    ],
    "sg:phone":"+61 2 9327 5446",
    "sg:postcode":"2023",
    "sg:province":"NSW",
    "sg:tags":[
        "delicatessen"
    ],
    "wof:name":"Zabars Delicatessen",
    "wof:placetype":"venue"
},
  "geometry": {"coordinates":[151.256713867,-33.8860626221],"type":"Point"}
}