{
  "type": "Feature",
  "properties": {
    "addr:full":"92 Canterbury Rd Bayswater North VIC 3153",
    "addr:housenumber":"92",
    "addr:postcode":"3153",
    "addr:street":"Canterbury Rd",
    "iso:country":"AU",
    "sg:address":"92 Canterbury Rd",
    "sg:city":"Bayswater North",
    "sg:classifiers":[
        {
            "category":"Building & Trades",
            "subcategory":"Construction",
            "type":"Services"
        }
    ],
    "sg:phone":"+61 3 9751 7000",
    "sg:postcode":"3153",
    "sg:province":"VIC",
    "sg:tags":[
        "window",
        "timber"
    ],
    "wof:name":"Quantum Windows",
    "wof:placetype":"venue"
},
  "geometry": {"coordinates":[145.29487609899999,-37.8239135742],"type":"Point"}
}