{
  "type": "Feature",
  "properties": {
    "addr:full":"PO Box 106 Morgan SA 5320",
    "addr:postcode":"5320",
    "iso:country":"AU",
    "sg:address":"PO Box 106",
    "sg:city":"Morgan",
    "sg:classifiers":[
        {
            "category":"Recreation",
            "subcategory":"Marina",
            "type":"Entertainment"
        }
    ],
    "sg:phone":"+61 8 8540 2257",
    "sg:postcode":"5320",
    "sg:province":"SA",
    "wof:name":"Koala Houseboats Marina",
    "wof:placetype":"venue"
},
  "geometry": {"coordinates":[139.668136597,-34.0263290405],"type":"Point"}
}