{
  "type": "Feature",
  "properties": {
    "addr:full":"715 Albany Creek Rd (Cnr Ferguson St) Albany Creek QLD 4035",
    "addr:housenumber":"715",
    "addr:postcode":"4035",
    "addr:street":"Albany Creek Rd Cnr Ferguson St",
    "iso:country":"AU",
    "sg:address":"715 Albany Creek Rd (Cnr Ferguson St)",
    "sg:city":"Albany Creek",
    "sg:classifiers":[
        {
            "category":"Real Estate",
            "subcategory":"Real Estate Agent",
            "type":"Services"
        }
    ],
    "sg:phone":"+61 7 3264 5511",
    "sg:postcode":"4035",
    "sg:province":"QLD",
    "wof:name":"Raine & Horne",
    "wof:placetype":"venue"
},
  "geometry": {"coordinates":[152.965744,-27.345331],"type":"Point"}
}