{
  "type": "Feature",
  "properties": {
    "iso:country":"AU",
    "sg:address":"862 Mt Alexander Rd",
    "sg:city":"Moonee Ponds",
    "sg:classifiers":[
        {
            "category":"Professional",
            "subcategory":"Business Services",
            "type":"Services"
        }
    ],
    "sg:phone":"+61 3 9370 4528",
    "sg:postcode":"3039",
    "sg:province":"VIC",
    "sg:tags":[
        "drafting"
    ],
    "wof:name":"Yvonne George",
    "wof:placetype":"venue"
},
  "geometry": {"coordinates":[144.919891,-37.75795],"type":"Point"}
}