{
  "type": "Feature",
  "properties": {
    "addr:full":"Rear 46 Adderley St East Silverwater NSW 2128",
    "addr:housenumber":"46",
    "addr:postcode":"2128",
    "addr:street":"Adderley St East",
    "iso:country":"AU",
    "sg:address":"Rear 46 Adderley St East",
    "sg:city":"Silverwater",
    "sg:classifiers":[
        {
            "category":"Retail",
            "subcategory":"Auto Repair",
            "type":"Services"
        }
    ],
    "sg:phone":"+61 2 9748 4944",
    "sg:postcode":"2128",
    "sg:province":"NSW",
    "sg:tags":[
        "clutch",
        "brake"
    ],
    "wof:name":"Automotive Brake Reconditioning",
    "wof:placetype":"venue"
},
  "geometry": {"coordinates":[151.04478454599999,-33.8440666199],"type":"Point"}
}