{
  "type": "Feature",
  "properties": {
    "iso:country":"AU",
    "sg:address":"9 Townsend Rd",
    "sg:city":"Malaga",
    "sg:classifiers":[
        {
            "category":"Retail",
            "subcategory":"Auto Repair",
            "type":"Services"
        }
    ],
    "sg:phone":"+61 419 959 025",
    "sg:postcode":"6090",
    "sg:province":"WA",
    "sg:tags":[
        "body",
        "builder",
        "motor"
    ],
    "wof:name":"Hoylake Transport Equipment",
    "wof:placetype":"venue"
},
  "geometry": {"coordinates":[115.88899231000001,-31.8463802338],"type":"Point"}
}