{
  "type": "Feature",
  "properties": {
    "addr:full":"PO Box 3184 Yokine WA 6060",
    "addr:postcode":"6060",
    "iso:country":"AU",
    "sg:address":"PO Box 3184",
    "sg:city":"Yokine",
    "sg:classifiers":[
        {
            "category":"Shopping",
            "subcategory":"Baby Store",
            "type":"Retail Goods"
        }
    ],
    "sg:phone":"+61 8 9349 7393",
    "sg:postcode":"6060",
    "sg:province":"WA",
    "sg:tags":[
        "wear"
    ],
    "wof:name":"Babe's Design",
    "wof:placetype":"venue"
},
  "geometry": {"coordinates":[115.850013733,-31.9015102386],"type":"Point"}
}