{
  "type": "Feature",
  "properties": {
    "addr:full":"Factory 14 40 Frankston-Dandenong Rd Dandenong VIC 3175",
    "addr:housenumber":"40",
    "addr:postcode":"3175",
    "addr:street":"Frankston-Dandenong Rd",
    "iso:country":"AU",
    "sg:address":"Factory 14 40 Frankston-Dandenong Rd",
    "sg:city":"Dandenong",
    "sg:classifiers":[
        {
            "category":"Retail",
            "subcategory":"Repair Shop",
            "type":"Services"
        }
    ],
    "sg:phone":"+61 3 9794 0944",
    "sg:postcode":"3175",
    "sg:province":"VIC",
    "sg:tags":[
        "upholsterer"
    ],
    "wof:name":"Graylene Furniture Pty Ltd",
    "wof:placetype":"venue"
},
  "geometry": {"coordinates":[145.217697144,-38.0011634827],"type":"Point"}
}