{
  "type": "Feature",
  "properties": {
    "addr:full":"23 Dixon Rd Rockingham WA 6168",
    "addr:housenumber":"23",
    "addr:postcode":"6168",
    "addr:street":"Dixon Rd",
    "iso:country":"AU",
    "sg:address":"23 Dixon Rd",
    "sg:city":"Rockingham",
    "sg:classifiers":[
        {
            "category":"Autos & Motor Vehicles",
            "subcategory":"Automobile Sales",
            "type":"Retail Goods"
        }
    ],
    "sg:phone":"+61 8 9529 3666",
    "sg:postcode":"6168",
    "sg:province":"WA",
    "sg:tags":[
        "car",
        "used"
    ],
    "wof:name":"Kwinana Auto Wholesale",
    "wof:placetype":"venue"
},
  "geometry": {"coordinates":[115.748306,-32.277081],"type":"Point"}
}