{
  "type": "Feature",
  "properties": {
    "iso:country":"AU",
    "sg:address":"20 Carmell Drv",
    "sg:city":"Warrnambool",
    "sg:classifiers":[
        {
            "category":"Building & Trades",
            "subcategory":"Cleaning & Sanitation",
            "type":"Services"
        }
    ],
    "sg:phone":"+61 3 5562 9430",
    "sg:postcode":"3280",
    "sg:province":"VIC",
    "sg:tags":[
        "industrial",
        "commercial",
        "contractor"
    ],
    "wof:name":"Colin Davey",
    "wof:placetype":"venue"
},
  "geometry": {"coordinates":[142.49012756400001,-38.3707275391],"type":"Point"}
}