{
  "type": "Feature",
  "properties": {
    "addr:full":"4 Kuhlmann St Ceduna SA 5690",
    "addr:housenumber":"4",
    "addr:postcode":"5690",
    "addr:street":"Kuhlmann St",
    "iso:country":"AU",
    "sg:address":"4 Kuhlmann St",
    "sg:city":"Ceduna",
    "sg:classifiers":[
        {
            "category":"Food & Beverages",
            "subcategory":"Bakery",
            "type":"Retail Goods"
        }
    ],
    "sg:phone":"+61 8 8625 2359",
    "sg:postcode":"5690",
    "sg:province":"SA",
    "sg:tags":[
        "cake",
        "shop",
        "pastry"
    ],
    "wof:name":"Ceduna Bakery",
    "wof:placetype":"venue"
},
  "geometry": {"coordinates":[133.68019104000001,-32.1219749451],"type":"Point"}
}