{
  "type": "Feature",
  "properties": {
    "addr:full":"424 Sturt St Ballarat VIC 3350",
    "addr:housenumber":"424",
    "addr:postcode":"3350",
    "addr:street":"Sturt St",
    "iso:country":"AU",
    "sg:address":"424 Sturt St",
    "sg:city":"Ballarat",
    "sg:classifiers":[
        {
            "category":"Real Estate",
            "subcategory":"Architect",
            "type":"Services"
        }
    ],
    "sg:phone":"+61 3 5331 5977",
    "sg:postcode":"3350",
    "sg:province":"VIC",
    "sg:tags":[
        "building",
        "designer"
    ],
    "wof:name":"Morton Dunn Architects",
    "wof:placetype":"venue"
},
  "geometry": {"coordinates":[143.85394299999999,-37.561199],"type":"Point"}
}