{
  "type": "Feature",
  "properties": {
    "addr:full":"442 Swan St Richmond VIC 3121",
    "addr:housenumber":"442",
    "addr:postcode":"3121",
    "addr:street":"Swan St",
    "iso:country":"AU",
    "sg:address":"442 Swan St",
    "sg:city":"Richmond",
    "sg:classifiers":[
        {
            "category":"Manufacturing",
            "subcategory":"Furniture",
            "type":"Manufacturing & Wholesale Goods"
        }
    ],
    "sg:phone":"+61 3 9427 8452",
    "sg:postcode":"3121",
    "sg:province":"VIC",
    "sg:tags":[
        "builder",
        "designer",
        "custom"
    ],
    "wof:name":"Jati",
    "wof:placetype":"venue"
},
  "geometry": {"coordinates":[145.006515503,-37.8267021179],"type":"Point"}
}