{
  "type": "Feature",
  "properties": {
    "addr:full":"1 Knox St Pendle Hill NSW 2145",
    "addr:housenumber":"1",
    "addr:postcode":"2145",
    "addr:street":"Knox St",
    "iso:country":"AU",
    "sg:address":"1 Knox St",
    "sg:city":"Pendle Hill",
    "sg:classifiers":[
        {
            "category":"Building & Trades",
            "subcategory":"Landscaping Services",
            "type":"Services"
        }
    ],
    "sg:phone":"+61 2 9688 1151",
    "sg:postcode":"2145",
    "sg:province":"NSW",
    "sg:tags":[
        "designer",
        "landscape",
        "contractor"
    ],
    "wof:name":"First Wraight Landscapes",
    "wof:placetype":"venue"
},
  "geometry": {"coordinates":[150.96194457999999,-33.7966270447],"type":"Point"}
}