{
  "type": "Feature",
  "properties": {
    "addr:full":"4/ 55 Ourimbah Rd Tweed Heads NSW 2485",
    "addr:housenumber":"/ 55",
    "addr:postcode":"2485",
    "addr:street":"Ourimbah Rd",
    "iso:country":"AU",
    "sg:address":"4/ 55 Ourimbah Rd",
    "sg:city":"Tweed Heads",
    "sg:classifiers":[
        {
            "category":"Professional",
            "subcategory":"Printing & Photocopies",
            "type":"Services"
        }
    ],
    "sg:phone":"+61 7 5536 4400",
    "sg:postcode":"2485",
    "sg:province":"NSW",
    "sg:tags":[
        "textile",
        "clothing"
    ],
    "wof:name":"Hand Printz Gold Coast",
    "wof:placetype":"venue"
},
  "geometry": {"coordinates":[153.522949219,-28.1754932404],"type":"Point"}
}