{
  "type": "Feature",
  "properties": {
    "addr:full":"171 Concord Rd North Strathfield NSW 2137",
    "addr:housenumber":"171",
    "addr:postcode":"2137",
    "addr:street":"Concord Rd",
    "iso:country":"AU",
    "sg:address":"171 Concord Rd",
    "sg:city":"North Strathfield",
    "sg:classifiers":[
        {
            "category":"Retail",
            "subcategory":"Repair Shop",
            "type":"Services"
        }
    ],
    "sg:phone":"+61 2 9739 6068",
    "sg:postcode":"2137",
    "sg:province":"NSW",
    "sg:tags":[
        "mending",
        "clothing",
        "alteration"
    ],
    "wof:name":"Antoun Mikhael",
    "wof:placetype":"venue"
},
  "geometry": {"coordinates":[151.092285156,-33.8579177856],"type":"Point"}
}