{
  "type": "Feature",
  "properties": {
    "addr:full":"79 New Canterbury Rd Petersham NSW 2049",
    "addr:housenumber":"79",
    "addr:postcode":"2049",
    "addr:street":"New Canterbury Rd",
    "iso:country":"AU",
    "sg:address":"79 New Canterbury Rd",
    "sg:city":"Petersham",
    "sg:classifiers":[
        {
            "category":"Real Estate",
            "subcategory":"Real Estate Agent",
            "type":"Services"
        }
    ],
    "sg:phone":"+61 2 9560 5000",
    "sg:postcode":"2049",
    "sg:province":"NSW",
    "wof:name":"Greer & Greer",
    "wof:placetype":"venue"
},
  "geometry": {"coordinates":[151.152344,-33.896786],"type":"Point"}
}