{
  "type": "Feature",
  "properties": {
    "iso:country":"AU",
    "sg:address":"1389 Murradoc Rd",
    "sg:city":"St Leonards",
    "sg:classifiers":[
        {
            "category":"Real Estate",
            "subcategory":"Real Estate Agent",
            "type":"Services"
        }
    ],
    "sg:phone":"+61 3 5257 1744",
    "sg:postcode":"3223",
    "sg:province":"VIC",
    "wof:name":"C.J. Keane & Co.",
    "wof:placetype":"venue"
},
  "geometry": {"coordinates":[144.71809400000001,-38.170856],"type":"Point"}
}