{
  "type": "Feature",
  "properties": {
    "addr:full":"9 Nilsson Crt Bucasia QLD 4750",
    "addr:housenumber":"9",
    "addr:postcode":"4750",
    "addr:street":"Nilsson Crt",
    "iso:country":"AU",
    "sg:address":"9 Nilsson Crt",
    "sg:city":"Bucasia",
    "sg:classifiers":[
        {
            "category":"Building & Trades",
            "subcategory":"Construction",
            "type":"Services"
        }
    ],
    "sg:phone":"+61 7 4954 8541",
    "sg:postcode":"4750",
    "sg:province":"QLD",
    "sg:tags":[
        "contractor"
    ],
    "wof:name":"Bucasia Property Maintenance",
    "wof:placetype":"venue"
},
  "geometry": {"coordinates":[149.155304,-21.027332],"type":"Point"}
}