{
  "type": "Feature",
  "properties": {
    "addr:full":"95a Ann St Mitchell QLD 4465",
    "addr:housenumber":"95a",
    "addr:postcode":"4465",
    "addr:street":"Ann St",
    "iso:country":"AU",
    "sg:address":"95a Ann St",
    "sg:city":"Mitchell",
    "sg:classifiers":[
        {
            "category":"Health Services",
            "subcategory":"Doctor",
            "type":"Services"
        }
    ],
    "sg:phone":"+61 7 4623 1138",
    "sg:postcode":"4465",
    "sg:province":"QLD",
    "sg:tags":[
        "medical",
        "practitioner"
    ],
    "wof:name":"Mitchell Medical Practice",
    "wof:placetype":"venue"
},
  "geometry": {"coordinates":[147.97279357900001,-26.4883403778],"type":"Point"}
}