{
  "type": "Feature",
  "properties": {
    "addr:full":"39 Barkly St Brunswick East VIC 3057",
    "addr:housenumber":"39",
    "addr:postcode":"3057",
    "addr:street":"Barkly St",
    "iso:country":"AU",
    "sg:address":"39 Barkly St",
    "sg:city":"Brunswick East",
    "sg:classifiers":[
        {
            "category":"Professional",
            "subcategory":"Management & Consulting",
            "type":"Services"
        }
    ],
    "sg:phone":"+61 418 556 912",
    "sg:postcode":"3057",
    "sg:province":"VIC",
    "sg:tags":[
        "consultant",
        "business"
    ],
    "wof:name":"Pryor Knowledge",
    "wof:placetype":"venue"
},
  "geometry": {"coordinates":[144.97789001500001,-37.7778205872],"type":"Point"}
}