{
  "type": "Feature",
  "properties": {
    "addr:full":"20 Caroline St Ringwood VIC 3134",
    "addr:housenumber":"20",
    "addr:postcode":"3134",
    "addr:street":"Caroline St",
    "iso:country":"AU",
    "sg:address":"20 Caroline St",
    "sg:city":"Ringwood",
    "sg:classifiers":[
        {
            "category":"Education",
            "subcategory":"Music School",
            "type":"Public Place"
        }
    ],
    "sg:phone":"+61 437 757 380",
    "sg:postcode":"3134",
    "sg:province":"VIC",
    "sg:tags":[
        "teacher"
    ],
    "wof:name":"Paul Carter Saxaphone Tuition",
    "wof:placetype":"venue"
},
  "geometry": {"coordinates":[145.23298645,-37.8196411133],"type":"Point"}
}