{
  "type": "Feature",
  "properties": {
    "addr:full":"Lomers Rd Euroa VIC 3666",
    "addr:postcode":"3666",
    "addr:street":"Lomers Rd",
    "iso:country":"AU",
    "sg:address":"Lomers Rd",
    "sg:city":"Euroa",
    "sg:classifiers":[
        {
            "category":"Building & Trades",
            "subcategory":"Plumbing",
            "type":"Services"
        }
    ],
    "sg:phone":"+61 418 531 255",
    "sg:postcode":"3666",
    "sg:province":"VIC",
    "sg:tags":[
        "plumber",
        "gasfitters"
    ],
    "wof:name":"Smith PJ & LH Plumbing",
    "wof:placetype":"venue"
},
  "geometry": {"coordinates":[145.58010864299999,-36.7353820801],"type":"Point"}
}