{
  "type": "Feature",
  "properties": {
    "iso:country":"AU",
    "sg:address":"121 Regency Rd",
    "sg:city":"Croydon Park",
    "sg:classifiers":[
        {
            "category":"Professional",
            "subcategory":"Engineering",
            "type":"Services"
        }
    ],
    "sg:phone":"+61 439 886 667",
    "sg:postcode":"5008",
    "sg:province":"SA",
    "sg:tags":[
        "engineer"
    ],
    "wof:name":"Stramech Engineering",
    "wof:placetype":"venue"
},
  "geometry": {"coordinates":[138.56838999999999,-34.875351],"type":"Point"}
}