{
  "type": "Feature",
  "properties": {
    "addr:full":"90 Greengate St Tewantin QLD 4565",
    "addr:housenumber":"90",
    "addr:postcode":"4565",
    "addr:street":"Greengate St",
    "iso:country":"AU",
    "sg:address":"90 Greengate St",
    "sg:city":"Tewantin",
    "sg:classifiers":[
        {
            "category":"Home & Garden",
            "subcategory":"Building Materials",
            "type":"Retail Goods"
        }
    ],
    "sg:phone":"+61 423 402 023",
    "sg:postcode":"4565",
    "sg:province":"QLD",
    "sg:tags":[
        "lawn",
        "cutting",
        "maintenance"
    ],
    "wof:name":"Red hot Mowing & Maintenance",
    "wof:placetype":"venue"
},
  "geometry": {"coordinates":[152.988647461,-26.3507442474],"type":"Point"}
}