{
  "type": "Feature",
  "properties": {
    "addr:full":"Bonney Place, 318 Junction Rd Clayfield QLD 4011",
    "addr:housenumber":"318",
    "addr:postcode":"4011",
    "addr:street":"Junction Rd",
    "iso:country":"AU",
    "sg:address":"Bonney Place, 318 Junction Rd",
    "sg:city":"Clayfield",
    "sg:classifiers":[
        {
            "category":"Health Services",
            "subcategory":"Doctor",
            "type":"Services"
        }
    ],
    "sg:phone":"+61 7 3857 2799",
    "sg:postcode":"4011",
    "sg:province":"QLD",
    "sg:tags":[
        "medical",
        "practitioner"
    ],
    "wof:name":"Bampton Antoinette",
    "wof:placetype":"venue"
},
  "geometry": {"coordinates":[153.048508,-27.414764],"type":"Point"}
}