{
  "type": "Feature",
  "properties": {
    "addr:full":"Shop 1133, Westfield Shoppingtown Diagonal Rd Oaklands Park SA 5046",
    "addr:housenumber":"1133",
    "addr:postcode":"5046",
    "addr:street":"Westfield Shoppingtown Diagonal Rd",
    "iso:country":"AU",
    "sg:address":"Shop 1133, Westfield Shoppingtown Diagonal Rd",
    "sg:city":"Oaklands Park",
    "sg:classifiers":[
        {
            "category":"Personal",
            "subcategory":"Beauty Salon",
            "type":"Services"
        }
    ],
    "sg:phone":"+61 8 8296 7363",
    "sg:postcode":"5046",
    "sg:province":"SA",
    "sg:tags":[
        "hairdresser"
    ],
    "wof:name":"Price Attack",
    "wof:placetype":"venue"
},
  "geometry": {"coordinates":[138.53732299999999,-35.002277],"type":"Point"}
}