{
  "type": "Feature",
  "properties": {
    "iso:country":"AU",
    "sg:address":"Lot 28 Boeing Way",
    "sg:city":"Jandakot",
    "sg:classifiers":[
        {
            "category":"Farming",
            "subcategory":"Farm & Veterinary Services",
            "type":"Manufacturing & Wholesale Goods"
        }
    ],
    "sg:phone":"+61 8 9417 5438",
    "sg:postcode":"6164",
    "sg:province":"WA",
    "sg:tags":[
        "irrigation",
        "reticulation",
        "system"
    ],
    "wof:name":"Delta Consultancy & Drilling Services Pty Ltd",
    "wof:placetype":"venue"
},
  "geometry": {"coordinates":[115.870789,-32.111462],"type":"Point"}
}