{
  "type": "Feature",
  "properties": {
    "addr:full":"179- 181 Liebig St Warrnambool VIC 3280",
    "addr:housenumber":"181",
    "addr:postcode":"3280",
    "addr:street":"Liebig St",
    "iso:country":"AU",
    "sg:address":"179- 181 Liebig St",
    "sg:city":"Warrnambool",
    "sg:classifiers":[
        {
            "category":"Shopping",
            "subcategory":"Bridal",
            "type":"Retail Goods"
        }
    ],
    "sg:phone":"+61 3 5562 7333",
    "sg:postcode":"3280",
    "sg:province":"VIC",
    "sg:tags":[
        "hire",
        "wear"
    ],
    "wof:name":"Whoopies Bridal & Debutante Boutique",
    "wof:placetype":"venue"
},
  "geometry": {"coordinates":[142.485305786,-38.3811683655],"type":"Point"}
}