{
  "type": "Feature",
  "properties": {
    "iso:country":"AU",
    "sg:address":"15 Harold Rd",
    "sg:city":"Springvale South",
    "sg:classifiers":[
        {
            "category":"Arts & Performance",
            "subcategory":"Dance",
            "type":"Entertainment"
        }
    ],
    "sg:phone":"+61 3 9546 4679",
    "sg:postcode":"3172",
    "sg:province":"VIC",
    "sg:tags":[
        "theatrical",
        "ballet",
        "tuition"
    ],
    "wof:name":"Gwenrose Australian Academy Of Dance & Ballet Theatre Of Australia The",
    "wof:placetype":"venue"
},
  "geometry": {"coordinates":[145.15086364699999,-37.9751205444],"type":"Point"}
}