{
  "type": "Feature",
  "properties": {
    "iso:country":"AU",
    "sg:address":"344 Clarinda St",
    "sg:city":"Parkes",
    "sg:classifiers":[
        {
            "category":"Health Services",
            "subcategory":"Doctor",
            "type":"Services"
        }
    ],
    "sg:phone":"+61 2 6862 6622",
    "sg:postcode":"2870",
    "sg:province":"NSW",
    "sg:tags":[
        "medical",
        "practitioner"
    ],
    "wof:name":"Central West Radiology",
    "wof:placetype":"venue"
},
  "geometry": {"coordinates":[148.17378199999999,-33.132412],"type":"Point"}
}