{
  "type": "Feature",
  "properties": {
    "addr:full":"Unit 1/ 4 Harvton St Stafford QLD 4053",
    "addr:housenumber":"4",
    "addr:postcode":"4053",
    "addr:street":"Harvton St",
    "iso:country":"AU",
    "sg:address":"Unit 1/ 4 Harvton St",
    "sg:city":"Stafford",
    "sg:classifiers":[
        {
            "category":"Professional",
            "subcategory":"Detective & Security Services",
            "type":"Services"
        }
    ],
    "sg:phone":"+61 7 3856 1229",
    "sg:postcode":"4053",
    "sg:province":"QLD",
    "sg:tags":[
        "equipment",
        "window",
        "doors"
    ],
    "wof:name":"Morris Screens Manufacturing Company",
    "wof:placetype":"venue"
},
  "geometry": {"coordinates":[153.013793945,-27.4173488617],"type":"Point"}
}