{
  "type": "Feature",
  "properties": {
    "addr:full":"Lot 13 Rouchel Rd Aberdeen NSW 2336",
    "addr:postcode":"2336",
    "addr:street":"Rouchel Rd",
    "iso:country":"AU",
    "sg:address":"Lot 13 Rouchel Rd",
    "sg:city":"Aberdeen",
    "sg:classifiers":[
        {
            "category":"Farming",
            "subcategory":"Livestock Farm",
            "type":"Manufacturing & Wholesale Goods"
        }
    ],
    "sg:phone":"+61 2 6543 7711",
    "sg:postcode":"2336",
    "sg:province":"NSW",
    "sg:tags":[
        "breeder",
        "horse",
        "stud"
    ],
    "wof:name":"Brooklyn Lodge",
    "wof:placetype":"venue"
},
  "geometry": {"coordinates":[150.93687439000001,-32.1386451721],"type":"Point"}
}