{
  "type": "Feature",
  "properties": {
    "addr:full":"2 Catania St Mentone VIC 3194",
    "addr:housenumber":"2",
    "addr:postcode":"3194",
    "addr:street":"Catania St",
    "iso:country":"AU",
    "sg:address":"2 Catania St",
    "sg:city":"Mentone",
    "sg:classifiers":[
        {
            "category":"Home & Garden",
            "subcategory":"Home Furnishings",
            "type":"Retail Goods"
        }
    ],
    "sg:phone":"+61 3 9585 5710",
    "sg:postcode":"3194",
    "sg:province":"VIC",
    "sg:tags":[
        "candle"
    ],
    "wof:name":"Aromatrail",
    "wof:placetype":"venue"
},
  "geometry": {"coordinates":[145.058349609,-37.9834976196],"type":"Point"}
}