{
  "type": "Feature",
  "properties": {
    "addr:full":"37 Wermol St Kurri Kurri NSW 2327",
    "addr:housenumber":"37",
    "addr:postcode":"2327",
    "addr:street":"Wermol St",
    "iso:country":"AU",
    "sg:address":"37 Wermol St",
    "sg:city":"Kurri Kurri",
    "sg:classifiers":[
        {
            "category":"Structure",
            "subcategory":"Bridge",
            "type":"Public Place"
        }
    ],
    "sg:phone":"+61 2 4937 5122",
    "sg:postcode":"2327",
    "sg:province":"NSW",
    "sg:tags":[
        "chainsaw",
        "brushcutters"
    ],
    "wof:name":"Kurri Mowers & Maintenance",
    "wof:placetype":"venue"
},
  "geometry": {"coordinates":[151.476486206,-32.8117408752],"type":"Point"}
}