{
  "type": "Feature",
  "properties": {
    "addr:full":"85 Commercial St Walla Walla NSW 2659",
    "addr:housenumber":"85",
    "addr:postcode":"2659",
    "addr:street":"Commercial St",
    "iso:country":"AU",
    "sg:address":"85 Commercial St",
    "sg:city":"Walla Walla",
    "sg:classifiers":[
        {
            "category":"Government",
            "subcategory":"Post Office",
            "type":"Public Place"
        }
    ],
    "sg:phone":"+61 2 6029 2300",
    "sg:postcode":"2659",
    "sg:province":"NSW",
    "sg:tags":[
        "postal"
    ],
    "wof:name":"Walla Walla Post Office",
    "wof:placetype":"venue"
},
  "geometry": {"coordinates":[146.90061950699999,-35.7679786682],"type":"Point"}
}