{
  "type": "Feature",
  "properties": {
    "addr:full":"5 Carneys Rd Wonthaggi VIC 3995",
    "addr:housenumber":"5",
    "addr:postcode":"3995",
    "addr:street":"Carneys Rd",
    "iso:country":"AU",
    "sg:address":"5 Carneys Rd",
    "sg:city":"Wonthaggi",
    "sg:classifiers":[
        {
            "category":"Retail",
            "subcategory":"Storage",
            "type":"Services"
        }
    ],
    "sg:phone":"+61 3 5672 3010",
    "sg:postcode":"3995",
    "sg:province":"VIC",
    "sg:tags":[
        "removal",
        "furniture"
    ],
    "wof:name":"South Gippsland Removals",
    "wof:placetype":"venue"
},
  "geometry": {"coordinates":[145.607056,-38.607738],"type":"Point"}
}