{
  "type": "Feature",
  "properties": {
    "iso:country":"AU",
    "sg:address":"Shop 9/ 10 Stuart Hwy",
    "sg:city":"Coolalinga",
    "sg:classifiers":[
        {
            "category":"Manufacturing",
            "subcategory":"Motor Vehicles & Parts",
            "type":"Manufacturing & Wholesale Goods"
        }
    ],
    "sg:phone":"+61 8 8983 3322",
    "sg:postcode":"0835",
    "sg:province":"NT",
    "sg:tags":[
        "wholesaler",
        "cycle",
        "mfrs",
        "accessory"
    ],
    "wof:name":"ATVS NT",
    "wof:placetype":"venue"
},
  "geometry": {"coordinates":[131.04148900000001,-12.523006],"type":"Point"}
}