{
  "type": "Feature",
  "properties": {
    "iso:country":"AU",
    "sg:address":"51 Maitland Rd",
    "sg:city":"Mayfield East",
    "sg:classifiers":[
        {
            "category":"Health Services",
            "subcategory":"Health Practitioner",
            "type":"Services"
        }
    ],
    "sg:phone":"+61 2 4967 7575",
    "sg:postcode":"2304",
    "sg:province":"NSW",
    "sg:tags":[
        "herbalist"
    ],
    "wof:name":"Newcastle Traditional Chinese Medicine & Acupuncture",
    "wof:placetype":"venue"
},
  "geometry": {"coordinates":[151.74505615199999,-32.9038505554],"type":"Point"}
}