{
  "type": "Feature",
  "properties": {
    "addr:full":"493a Swift St Albury NSW 2640",
    "addr:housenumber":"493a",
    "addr:postcode":"2640",
    "addr:street":"Swift St",
    "iso:country":"AU",
    "sg:address":"493a Swift St",
    "sg:city":"Albury",
    "sg:classifiers":[
        {
            "category":"Personal",
            "subcategory":"Beauty Salon",
            "type":"Services"
        }
    ],
    "sg:phone":"+61 2 6021 0345",
    "sg:postcode":"2640",
    "sg:province":"NSW",
    "sg:tags":[
        "hairdresser"
    ],
    "wof:name":"Boss Hair Studio",
    "wof:placetype":"venue"
},
  "geometry": {"coordinates":[146.916213989,-36.0787773132],"type":"Point"}
}