{
  "type": "Feature",
  "properties": {
    "iso:country":"AU",
    "sg:address":"49 Adina Ave",
    "sg:city":"Phillip Bay",
    "sg:classifiers":[
        {
            "category":"Communications",
            "type":"Services"
        }
    ],
    "sg:phone":"+61 2 9311 2228",
    "sg:postcode":"2036",
    "sg:province":"NSW",
    "sg:tags":[
        "translation"
    ],
    "wof:name":"Thai Communication Services",
    "wof:placetype":"venue"
},
  "geometry": {"coordinates":[151.233642578,-33.9840698242],"type":"Point"}
}