{
  "type": "Feature",
  "properties": {
    "iso:country":"AU",
    "sg:address":"331 Fullarton Rd",
    "sg:city":"Parkside",
    "sg:classifiers":[
        {
            "category":"Personal",
            "subcategory":"Beauty Salon",
            "type":"Services"
        }
    ],
    "sg:phone":"+61 8 8373 4920",
    "sg:postcode":"5063",
    "sg:province":"SA",
    "sg:tags":[
        "hairdresser"
    ],
    "wof:name":"Shear Identity (Hair Concepts By Marsali)",
    "wof:placetype":"venue"
},
  "geometry": {"coordinates":[138.62532043499999,-34.9515991211],"type":"Point"}
}