{
  "type": "Feature",
  "properties": {
    "addr:full":"96 Balo St Moree NSW 2400",
    "addr:housenumber":"96",
    "addr:postcode":"2400",
    "addr:street":"Balo St",
    "iso:country":"AU",
    "sg:address":"96 Balo St",
    "sg:city":"Moree",
    "sg:classifiers":[
        {
            "category":"Personal",
            "subcategory":"Beauty Salon",
            "type":"Services"
        }
    ],
    "sg:phone":"+61 2 6752 1061",
    "sg:postcode":"2400",
    "sg:province":"NSW",
    "sg:tags":[
        "hairdresser"
    ],
    "wof:name":"Trendsetter Salon",
    "wof:placetype":"venue"
},
  "geometry": {"coordinates":[149.84175109899999,-29.4649372101],"type":"Point"}
}