{
  "type": "Feature",
  "properties": {
    "addr:full":"Shop 9m, Forrestfield Market Place, Hale Rd Forrestfield WA 6058",
    "addr:housenumber":"9m",
    "addr:postcode":"6058",
    "addr:street":"Market Place Hale Rd",
    "iso:country":"AU",
    "sg:address":"Shop 9m, Forrestfield Market Place, Hale Rd",
    "sg:city":"Forrestfield",
    "sg:classifiers":[
        {
            "category":"Professional",
            "subcategory":"Art Services",
            "type":"Services"
        }
    ],
    "sg:phone":"+61 8 9359 0319",
    "sg:postcode":"6058",
    "sg:province":"WA",
    "sg:tags":[
        "picture",
        "frame",
        "framing"
    ],
    "wof:name":"Forrestfield Fast Fotos & Framing",
    "wof:placetype":"venue"
},
  "geometry": {"coordinates":[116.01738739,-31.984369278],"type":"Point"}
}