{
  "type": "Feature",
  "properties": {
    "iso:country":"AU",
    "sg:address":"6 Maud St",
    "sg:city":"Newstead",
    "sg:classifiers":[
        {
            "category":"Government",
            "subcategory":"Post Office",
            "type":"Public Place"
        }
    ],
    "sg:phone":"+61 7 3252 1036",
    "sg:postcode":"4006",
    "sg:province":"QLD",
    "sg:tags":[
        "chair",
        "manufacturer"
    ],
    "wof:name":"The Table & Chair Co.",
    "wof:placetype":"venue"
},
  "geometry": {"coordinates":[153.04368591299999,-27.4447174072],"type":"Point"}
}