{
  "type": "Feature",
  "properties": {
    "addr:full":"Shop 215, GO 5 Bent St Moore Park NSW 2021",
    "addr:housenumber":"5",
    "addr:postcode":"2021",
    "addr:street":"Bent St",
    "iso:country":"AU",
    "sg:address":"Shop 215, GO 5 Bent St",
    "sg:city":"Moore Park",
    "sg:classifiers":[
        {
            "category":"Restaurant",
            "type":"Food & Drink"
        }
    ],
    "sg:phone":"+61 2 9331 4166",
    "sg:postcode":"2021",
    "sg:province":"NSW",
    "wof:name":"Arthouse Blue",
    "wof:placetype":"venue"
},
  "geometry": {"coordinates":[151.228790283,-33.8873710632],"type":"Point"}
}