{
  "type": "Feature",
  "properties": {
    "iso:country":"AU",
    "sg:address":"185 Scott St",
    "sg:city":"Bungalow",
    "sg:classifiers":[
        {
            "category":"Arts & Performance",
            "subcategory":"Dance",
            "type":"Entertainment"
        }
    ],
    "sg:phone":"+61 7 4031 3390",
    "sg:postcode":"4870",
    "sg:province":"QLD",
    "sg:tags":[
        "theatrical",
        "ballet",
        "tuition"
    ],
    "sg:website":"http://www.turningpointe.com.au",
    "wof:name":"Turning Pointe Dance Studios",
    "wof:placetype":"venue"
},
  "geometry": {"coordinates":[145.75424194300001,-16.9388027191],"type":"Point"}
}