{
  "type": "Feature",
  "properties": {
    "addr:full":"Tempe St Greenacre NSW 2190",
    "addr:postcode":"2190",
    "addr:street":"Tempe St",
    "iso:country":"AU",
    "sg:address":"Tempe St",
    "sg:city":"Greenacre",
    "sg:classifiers":[
        {
            "category":"Education",
            "subcategory":"School",
            "type":"Public Place"
        }
    ],
    "sg:phone":"+61 2 9759 9153",
    "sg:postcode":"2190",
    "sg:province":"NSW",
    "wof:name":"St John Vianney's Primary School",
    "wof:placetype":"venue"
},
  "geometry": {"coordinates":[151.06016500000001,-33.901493],"type":"Point"}
}