{
  "type": "Feature",
  "properties": {
    "addr:full":"877 Princes Hwy Springvale VIC 3171",
    "addr:housenumber":"877",
    "addr:postcode":"3171",
    "addr:street":"Princes Hwy",
    "iso:country":"AU",
    "sg:address":"877 Princes Hwy",
    "sg:city":"Springvale",
    "sg:classifiers":[
        {
            "category":"Social Services",
            "subcategory":"Adult Care",
            "type":"Services"
        }
    ],
    "sg:phone":"+61 3 9545 7070",
    "sg:postcode":"3171",
    "sg:province":"VIC",
    "sg:tags":[
        "towing"
    ],
    "wof:name":"ACE Towing Service",
    "wof:placetype":"venue"
},
  "geometry": {"coordinates":[145.151779175,-37.9302368164],"type":"Point"}
}