{
  "type": "Feature",
  "properties": {
    "addr:full":"15 Gibraltar St Bungendore ACT 2621",
    "addr:housenumber":"15",
    "addr:postcode":"2621",
    "addr:street":"Gibraltar St",
    "iso:country":"AU",
    "sg:address":"15 Gibraltar St",
    "sg:city":"Bungendore",
    "sg:classifiers":[
        {
            "category":"Cafe",
            "type":"Food & Drink"
        }
    ],
    "sg:phone":"+61 2 6238 1088",
    "sg:postcode":"2621",
    "sg:province":"ACT",
    "wof:name":"Gib Street Cafe",
    "wof:placetype":"venue"
},
  "geometry": {"coordinates":[149.44036865199999,-35.2541847229],"type":"Point"}
}