{
  "type": "Feature",
  "properties": {
    "iso:country":"AU",
    "sg:address":"Level 4, Kirin Centre 15 Ogilvie Rd",
    "sg:city":"Mt Pleasant",
    "sg:classifiers":[
        {
            "category":"Personal",
            "subcategory":"Day Spa",
            "type":"Services"
        }
    ],
    "sg:phone":"+61 8 6310 5200",
    "sg:postcode":"6153",
    "sg:province":"WA",
    "wof:name":"Eight Degrees Day Spa",
    "wof:placetype":"venue"
},
  "geometry": {"coordinates":[115.848572,-32.013355],"type":"Point"}
}