{
  "type": "Feature",
  "properties": {
    "iso:country":"AU",
    "sg:address":"Great Eastern Hwy",
    "sg:city":"Merredin",
    "sg:classifiers":[
        {
            "category":"Travel",
            "subcategory":"Hotels & Motels",
            "type":"Entertainment"
        }
    ],
    "sg:phone":"+61 8 9041 1588",
    "sg:postcode":"6415",
    "sg:province":"WA",
    "wof:name":"Merredin Olympic Motel",
    "wof:placetype":"venue"
},
  "geometry": {"coordinates":[118.29292297400001,-31.4842586517],"type":"Point"}
}