{
  "type": "Feature",
  "properties": {
    "addr:full":"PO Box 8769 Kooringal NSW 2650",
    "addr:postcode":"2650",
    "iso:country":"AU",
    "sg:address":"PO Box 8769",
    "sg:city":"Kooringal",
    "sg:classifiers":[
        {
            "category":"Professional",
            "subcategory":"Business Services",
            "type":"Services"
        }
    ],
    "sg:phone":"+61 412 639 934",
    "sg:postcode":"2650",
    "sg:province":"NSW",
    "sg:tags":[
        "drafting"
    ],
    "wof:name":"Rivplan Design Services",
    "wof:placetype":"venue"
},
  "geometry": {"coordinates":[147.37730407699999,-35.1417884827],"type":"Point"}
}