{
  "type": "Feature",
  "properties": {
    "iso:country":"AU",
    "sg:address":"9- 15 Redwood Drv",
    "sg:city":"Dingley",
    "sg:classifiers":[
        {
            "category":"Shopping",
            "subcategory":"Stationery & Office Supplies",
            "type":"Retail Goods"
        }
    ],
    "sg:phone":"+61 1800 335 751",
    "sg:postcode":"3172",
    "sg:province":"VIC",
    "sg:tags":[
        "packaging",
        "material"
    ],
    "wof:name":"Andrew Kohn Pty Ltd",
    "wof:placetype":"venue"
},
  "geometry": {"coordinates":[145.11227417000001,-37.9837760925],"type":"Point"}
}