{
  "type": "Feature",
  "properties": {
    "addr:full":"PO Box 8281 Armadale VIC 3143",
    "addr:postcode":"3143",
    "iso:country":"AU",
    "sg:address":"PO Box 8281",
    "sg:city":"Armadale",
    "sg:classifiers":[
        {
            "category":"Arts & Performance",
            "subcategory":"Theater",
            "type":"Entertainment"
        }
    ],
    "sg:phone":"+61 3 9576 9598",
    "sg:postcode":"3143",
    "sg:province":"VIC",
    "sg:tags":[
        "theatrical",
        "supply"
    ],
    "wof:name":"Entertainment Production Personnel",
    "wof:placetype":"venue"
},
  "geometry": {"coordinates":[145.01930236800001,-37.8576812744],"type":"Point"}
}