{
  "type": "Feature",
  "properties": {
    "iso:country":"AU",
    "sg:address":"8 Grandview Drv",
    "sg:city":"Campbelltown",
    "sg:classifiers":[
        {
            "category":"Government",
            "subcategory":"Court House",
            "type":"Public Place"
        }
    ],
    "sg:phone":"+61 448 800 572",
    "sg:postcode":"2560",
    "sg:province":"NSW",
    "sg:tags":[
        "personal",
        "marriage",
        "family",
        "counselling"
    ],
    "wof:name":"Chris Roodenrys",
    "wof:placetype":"venue"
},
  "geometry": {"coordinates":[150.81629943900001,-34.0764808655],"type":"Point"}
}