{
  "type": "Feature",
  "properties": {
    "addr:full":"31 Michellan Crt Bayswater VIC 3153",
    "addr:housenumber":"31",
    "addr:postcode":"3153",
    "addr:street":"Michellan Crt",
    "iso:country":"AU",
    "sg:address":"31 Michellan Crt",
    "sg:city":"Bayswater",
    "sg:classifiers":[
        {
            "category":"Wholesale",
            "subcategory":"Metals & Minerals",
            "type":"Manufacturing & Wholesale Goods"
        }
    ],
    "sg:phone":"+61 3 9720 5042",
    "sg:postcode":"3153",
    "sg:province":"VIC",
    "sg:tags":[
        "steel",
        "stainless",
        "product",
        "equipment"
    ],
    "wof:name":"Brita Stainless Steel",
    "wof:placetype":"venue"
},
  "geometry": {"coordinates":[145.24171447800001,-37.8418998718],"type":"Point"}
}