{
  "type": "Feature",
  "properties": {
    "addr:full":"24- 26 Hollywood Drv Lansvale NSW 2166",
    "addr:housenumber":"26",
    "addr:postcode":"2166",
    "addr:street":"Hollywood Drv",
    "iso:country":"AU",
    "sg:address":"24- 26 Hollywood Drv",
    "sg:city":"Lansvale",
    "sg:classifiers":[
        {
            "category":"Retail",
            "subcategory":"Auto Repair",
            "type":"Services"
        }
    ],
    "sg:phone":"+61 2 9727 6788",
    "sg:postcode":"2166",
    "sg:province":"NSW",
    "sg:tags":[
        "beater",
        "painter",
        "panel"
    ],
    "wof:name":"Hume Smash Repairs",
    "wof:placetype":"venue"
},
  "geometry": {"coordinates":[150.959075928,-33.8964157104],"type":"Point"}
}