{
  "type": "Feature",
  "properties": {
    "addr:full":"16- 20 Clairmont Ave Bentleigh VIC 3204",
    "addr:housenumber":"20",
    "addr:postcode":"3204",
    "addr:street":"Clairmont Ave",
    "iso:country":"AU",
    "sg:address":"16- 20 Clairmont Ave",
    "sg:city":"Bentleigh",
    "sg:classifiers":[
        {
            "category":"Professional",
            "subcategory":"Employment Agencies",
            "type":"Services"
        }
    ],
    "sg:phone":"+61 3 8530 6600",
    "sg:postcode":"3204",
    "sg:province":"VIC",
    "sg:tags":[
        "hire",
        "labour",
        "contractor"
    ],
    "wof:name":"Apprenticeships Victoria",
    "wof:placetype":"venue"
},
  "geometry": {"coordinates":[145.02526900000001,-37.921654],"type":"Point"}
}