{
  "type": "Feature",
  "properties": {
    "addr:full":"31 Mason St Newport VIC 3015",
    "addr:housenumber":"31",
    "addr:postcode":"3015",
    "addr:street":"Mason St",
    "iso:country":"AU",
    "sg:address":"31 Mason St",
    "sg:city":"Newport",
    "sg:classifiers":[
        {
            "category":"Food & Beverages",
            "subcategory":"Fruits & Vegetables",
            "type":"Retail Goods"
        }
    ],
    "sg:phone":"+61 3 9391 3826",
    "sg:postcode":"3015",
    "sg:province":"VIC",
    "sg:tags":[
        "greengrocer",
        "fruiterer"
    ],
    "wof:name":"Merlino J & N",
    "wof:placetype":"venue"
},
  "geometry": {"coordinates":[144.88116455100001,-37.8424758911],"type":"Point"}
}