{
  "type": "Feature",
  "properties": {
    "iso:country":"AU",
    "sg:address":"Shop 4 'Focal Point' 42 Torquay Rd",
    "sg:city":"Pialba",
    "sg:classifiers":[
        {
            "category":"Personal",
            "subcategory":"Tattoo Parlor",
            "type":"Services"
        }
    ],
    "sg:phone":"+61 7 4128 2522",
    "sg:postcode":"4655",
    "sg:province":"QLD",
    "sg:tags":[
        "tattooing"
    ],
    "wof:name":"Fraser Coast Tattoo & Body Piercing",
    "wof:placetype":"venue"
},
  "geometry": {"coordinates":[152.84326200000001,-25.282887],"type":"Point"}
}