{
  "type": "Feature",
  "properties": {
    "addr:full":"94 Edward St Molong NSW 2866",
    "addr:housenumber":"94",
    "addr:postcode":"2866",
    "addr:street":"Edward St",
    "iso:country":"AU",
    "sg:address":"94 Edward St",
    "sg:city":"Molong",
    "sg:classifiers":[
        {
            "category":"Fast Food",
            "type":"Food & Drink"
        }
    ],
    "sg:phone":"+61 2 6366 8326",
    "sg:postcode":"2866",
    "sg:province":"NSW",
    "sg:tags":[
        "away",
        "take"
    ],
    "wof:name":"Molong Korner",
    "wof:placetype":"venue"
},
  "geometry": {"coordinates":[148.86502100000001,-33.096813],"type":"Point"}
}