{
  "type": "Feature",
  "properties": {
    "iso:country":"AU",
    "sg:address":"68 South St",
    "sg:city":"Rydalmere",
    "sg:classifiers":[
        {
            "category":"Retail",
            "subcategory":"Car Wash",
            "type":"Services"
        }
    ],
    "sg:phone":"+61 2 9684 6022",
    "sg:postcode":"2116",
    "sg:province":"NSW",
    "sg:tags":[
        "truck",
        "cleaning"
    ],
    "wof:name":"Profile Detailing",
    "wof:placetype":"venue"
},
  "geometry": {"coordinates":[151.010696411,-33.8348312378],"type":"Point"}
}