{
  "type": "Feature",
  "properties": {
    "addr:full":"Lvl 40 140 William St Melbourne VIC 3000",
    "addr:housenumber":"140",
    "addr:postcode":"3000",
    "addr:street":"William St",
    "iso:country":"AU",
    "sg:address":"Lvl 40 140 William St",
    "sg:city":"Melbourne",
    "sg:classifiers":[
        {
            "category":"Wholesale",
            "subcategory":"Metals & Minerals",
            "type":"Manufacturing & Wholesale Goods"
        }
    ],
    "sg:phone":"+61 3 9607 8361",
    "sg:postcode":"3000",
    "sg:province":"VIC",
    "sg:tags":[
        "steel",
        "merchant"
    ],
    "wof:name":"Australian Business Merchants",
    "wof:placetype":"venue"
},
  "geometry": {"coordinates":[144.95840454099999,-37.8157501221],"type":"Point"}
}