{
  "type": "Feature",
  "properties": {
    "iso:country":"AU",
    "sg:address":"508 Marmion St",
    "sg:city":"Booragoon",
    "sg:classifiers":[
        {
            "category":"Retail",
            "subcategory":"Veterinary Services",
            "type":"Services"
        }
    ],
    "sg:phone":"+61 8 9330 1665",
    "sg:postcode":"6154",
    "sg:province":"WA",
    "sg:tags":[
        "surgeon"
    ],
    "wof:name":"Booragoon Vet",
    "wof:placetype":"venue"
},
  "geometry": {"coordinates":[115.827072,-32.039307],"type":"Point"}
}