{
  "type": "Feature",
  "properties": {
    "addr:full":"17- 25 Patrick St Hobart TAS 7000",
    "addr:housenumber":"25",
    "addr:postcode":"7000",
    "addr:street":"Patrick St",
    "iso:country":"AU",
    "sg:address":"17- 25 Patrick St",
    "sg:city":"Hobart",
    "sg:classifiers":[
        {
            "category":"Autos & Motor Vehicles",
            "subcategory":"Auto Supplies",
            "type":"Retail Goods"
        }
    ],
    "sg:phone":"+61 13 15 09",
    "sg:postcode":"7000",
    "sg:province":"TAS",
    "sg:tags":[
        "tyre"
    ],
    "wof:name":"Yokohama",
    "wof:placetype":"venue"
},
  "geometry": {"coordinates":[147.32351684599999,-42.8768386841],"type":"Point"}
}