{
  "type": "Feature",
  "properties": {
    "iso:country":"AU",
    "sg:address":"442 Oceanic Drv",
    "sg:city":"Wurtulla",
    "sg:classifiers":[
        {
            "category":"Building & Trades",
            "subcategory":"Construction",
            "type":"Services"
        }
    ],
    "sg:phone":"+61 408 800 659",
    "sg:postcode":"4575",
    "sg:province":"QLD",
    "sg:tags":[
        "concrete",
        "contractor"
    ],
    "wof:name":"All Types Concrete",
    "wof:placetype":"venue"
},
  "geometry": {"coordinates":[153.13429300000001,-26.750843],"type":"Point"}
}