{
  "type": "Feature",
  "properties": {
    "addr:full":"Lot 1, Old Springhill Rd Coniston NSW 2500",
    "addr:postcode":"2500",
    "addr:street":"Old Springhill Rd",
    "iso:country":"AU",
    "sg:address":"Lot 1, Old Springhill Rd",
    "sg:city":"Coniston",
    "sg:classifiers":[
        {
            "category":"Utilities",
            "subcategory":"Refuse",
            "type":"Services"
        }
    ],
    "sg:phone":"+61 13 13 35",
    "sg:postcode":"2500",
    "sg:province":"NSW",
    "sg:tags":[
        "remover",
        "rubbish"
    ],
    "wof:name":"Sita Environmental Solutions",
    "wof:placetype":"venue"
},
  "geometry": {"coordinates":[150.886887,-34.43969],"type":"Point"}
}