{
  "type": "Feature",
  "properties": {
    "iso:country":"AU",
    "sg:address":"4 Miners Crt",
    "sg:city":"Mulgrave",
    "sg:classifiers":[
        {
            "category":"Professional",
            "subcategory":"Business Services",
            "type":"Services"
        }
    ],
    "sg:phone":"+61 412 229 713",
    "sg:postcode":"3170",
    "sg:province":"VIC",
    "sg:tags":[
        "drafting"
    ],
    "wof:name":"N V Drafting Services",
    "wof:placetype":"venue"
},
  "geometry": {"coordinates":[145.199783325,-37.9280052185],"type":"Point"}
}