{
  "type": "Feature",
  "properties": {
    "addr:full":"12 Poinciana St Cranbrook QLD 4814",
    "addr:housenumber":"12",
    "addr:postcode":"4814",
    "addr:street":"Poinciana St",
    "iso:country":"AU",
    "sg:address":"12 Poinciana St",
    "sg:city":"Cranbrook",
    "sg:classifiers":[
        {
            "category":"Home & Garden",
            "subcategory":"Carpets & Floor Coverings",
            "type":"Retail Goods"
        }
    ],
    "sg:phone":"+61 411 699 428",
    "sg:postcode":"4814",
    "sg:province":"QLD",
    "sg:tags":[
        "tile",
        "wall",
        "layer"
    ],
    "wof:name":"Abel John & Sue",
    "wof:placetype":"venue"
},
  "geometry": {"coordinates":[146.75810200000001,-19.294399],"type":"Point"}
}