{
  "type": "Feature",
  "properties": {
    "addr:full":"5 Mc Connan St Benalla VIC 3672",
    "addr:housenumber":"5",
    "addr:postcode":"3672",
    "addr:street":"Mc Connan St",
    "iso:country":"AU",
    "sg:address":"5 Mc Connan St",
    "sg:city":"Benalla",
    "sg:classifiers":[
        {
            "category":"Building & Trades",
            "subcategory":"Plumbing",
            "type":"Services"
        }
    ],
    "sg:phone":"+61 3 5762 2760",
    "sg:postcode":"3672",
    "sg:province":"VIC",
    "sg:tags":[
        "plumber",
        "gasfitters"
    ],
    "wof:name":"Briggs PP & PE Plumbing",
    "wof:placetype":"venue"
},
  "geometry": {"coordinates":[145.97920199999999,-36.562778],"type":"Point"}
}