{
  "type": "Feature",
  "properties": {
    "addr:full":"46 John St Rosewood QLD 4340",
    "addr:housenumber":"46",
    "addr:postcode":"4340",
    "addr:street":"John St",
    "iso:country":"AU",
    "sg:address":"46 John St",
    "sg:city":"Rosewood",
    "sg:classifiers":[
        {
            "category":"Personal",
            "subcategory":"Beauty Salon",
            "type":"Services"
        }
    ],
    "sg:phone":"+61 7 5464 1362",
    "sg:postcode":"4340",
    "sg:province":"QLD",
    "sg:tags":[
        "hairdresser"
    ],
    "wof:name":"Busy Snips",
    "wof:placetype":"venue"
},
  "geometry": {"coordinates":[152.59068298299999,-27.6357135773],"type":"Point"}
}