{
  "type": "Feature",
  "properties": {
    "addr:full":"1 Oatberry Crs Shailer Park QLD 4128",
    "addr:housenumber":"1",
    "addr:postcode":"4128",
    "addr:street":"Oatberry Crs",
    "iso:country":"AU",
    "sg:address":"1 Oatberry Crs",
    "sg:city":"Shailer Park",
    "sg:classifiers":[
        {
            "category":"Retail",
            "subcategory":"Auto Repair",
            "type":"Services"
        }
    ],
    "sg:phone":"+61 7 3801 4152",
    "sg:postcode":"4128",
    "sg:province":"QLD",
    "sg:tags":[
        "electrical"
    ],
    "wof:name":"Auto Electrical Mobile Service",
    "wof:placetype":"venue"
},
  "geometry": {"coordinates":[153.17202758799999,-27.6515808105],"type":"Point"}
}