{
  "type": "Feature",
  "properties": {
    "iso:country":"AU",
    "sg:address":"31 Blenheim St",
    "sg:city":"Croydon Park",
    "sg:classifiers":[
        {
            "category":"Utilities",
            "subcategory":"Electric",
            "type":"Services"
        }
    ],
    "sg:phone":"+61 418 947 942",
    "sg:postcode":"2133",
    "sg:province":"NSW",
    "sg:tags":[
        "electrical",
        "contractor"
    ],
    "wof:name":"George Electrical",
    "wof:placetype":"venue"
},
  "geometry": {"coordinates":[151.09201049800001,-33.8965797424],"type":"Point"}
}