{
  "type": "Feature",
  "properties": {
    "addr:full":"162 Kendal St Cowra NSW 2794",
    "addr:housenumber":"162",
    "addr:postcode":"2794",
    "addr:street":"Kendal St",
    "iso:country":"AU",
    "sg:address":"162 Kendal St",
    "sg:city":"Cowra",
    "sg:classifiers":[
        {
            "category":"Travel",
            "subcategory":"Hotels & Motels",
            "type":"Entertainment"
        }
    ],
    "sg:phone":"+61 2 6342 2900",
    "sg:postcode":"2794",
    "sg:province":"NSW",
    "sg:tags":[
        "accommodation"
    ],
    "wof:name":"Lachlan Valley Hotel Motel",
    "wof:placetype":"venue"
},
  "geometry": {"coordinates":[148.69776916500001,-33.8355636597],"type":"Point"}
}