{
  "type": "Feature",
  "properties": {
    "iso:country":"AU",
    "sg:address":"47 Moresby Ave",
    "sg:city":"Seaford",
    "sg:classifiers":[
        {
            "category":"Banks & Credit Unions",
            "subcategory":"Bank",
            "type":"Services"
        }
    ],
    "sg:phone":"+61 3 9775 7668",
    "sg:postcode":"3198",
    "sg:province":"VIC",
    "sg:tags":[
        "concrete",
        "reinforcement"
    ],
    "wof:name":"Sutherland R & J Reinforcements Pty Ltd",
    "wof:placetype":"venue"
},
  "geometry": {"coordinates":[145.134597778,-38.1163711548],"type":"Point"}
}