{
  "type": "Feature",
  "properties": {
    "iso:country":"AU",
    "sg:address":"Suite 4 Kenmore Medical Centre 2081 Moggill Rd",
    "sg:city":"Kenmore",
    "sg:classifiers":[
        {
            "category":"Health Services",
            "subcategory":"Health Practitioner",
            "type":"Services"
        }
    ],
    "sg:phone":"+61 7 3378 5712",
    "sg:postcode":"4069",
    "sg:province":"QLD",
    "sg:tags":[
        "physiotherapist"
    ],
    "wof:name":"Griffin Damian",
    "wof:placetype":"venue"
},
  "geometry": {"coordinates":[152.93812560999999,-27.5089797974],"type":"Point"}
}