{
  "type": "Feature",
  "properties": {
    "iso:country":"AU",
    "sg:address":"198 High St",
    "sg:city":"Maitland",
    "sg:classifiers":[
        {
            "category":"Retail",
            "subcategory":"Laundry & Dry Cleaning",
            "type":"Services"
        }
    ],
    "sg:phone":"+61 2 4933 5147",
    "sg:postcode":"2320",
    "sg:province":"NSW",
    "wof:name":"Maitland City Dry Cleaners",
    "wof:placetype":"venue"
},
  "geometry": {"coordinates":[151.55352783199999,-32.7311859131],"type":"Point"}
}