{
  "type": "Feature",
  "properties": {
    "iso:country":"AU",
    "sg:address":"15 Rosedale Ave",
    "sg:city":"Blair Athol",
    "sg:classifiers":[
        {
            "category":"Building & Trades",
            "subcategory":"Construction",
            "type":"Services"
        }
    ],
    "sg:phone":"+61 8 8260 5112",
    "sg:postcode":"5084",
    "sg:province":"SA",
    "sg:tags":[
        "earth",
        "excavating",
        "moving",
        "contractor"
    ],
    "wof:name":"White R H & L M Cartage Contractors",
    "wof:placetype":"venue"
},
  "geometry": {"coordinates":[138.597747803,-34.8499565125],"type":"Point"}
}