{
  "type": "Feature",
  "properties": {
    "addr:full":"Shop 2A, 25 South Western Hwy Donnybrook WA 6239",
    "addr:housenumber":"shop 2a 25",
    "addr:postcode":"6239",
    "addr:street":"South Western Hwy",
    "iso:country":"AU",
    "sg:address":"Shop 2A, 25 South Western Hwy",
    "sg:city":"Donnybrook",
    "sg:classifiers":[
        {
            "category":"Personal",
            "subcategory":"Beauty Salon",
            "type":"Services"
        }
    ],
    "sg:phone":"+61 8 9731 0171",
    "sg:postcode":"6239",
    "sg:province":"WA",
    "sg:tags":[
        "hairdresser"
    ],
    "wof:name":"The Cutting Shed",
    "wof:placetype":"venue"
},
  "geometry": {"coordinates":[115.82261699999999,-33.569969],"type":"Point"}
}