{
  "type": "Feature",
  "properties": {
    "iso:country":"AU",
    "sg:address":"3 Wavell Ave",
    "sg:city":"Carlingford",
    "sg:classifiers":[
        {
            "category":"Retail",
            "subcategory":"Auto Rental",
            "type":"Services"
        }
    ],
    "sg:phone":"+61 411 211 400",
    "sg:postcode":"2118",
    "sg:province":"NSW",
    "sg:tags":[
        "chauffeur",
        "car",
        "hire",
        "driven",
        "limousine"
    ],
    "wof:name":"The Limousine Line",
    "wof:placetype":"venue"
},
  "geometry": {"coordinates":[151.05340576200001,-33.7699737549],"type":"Point"}
}