{
  "type": "Feature",
  "properties": {
    "addr:full":"297 Margaret St Toowoomba QLD 4350",
    "addr:housenumber":"297",
    "addr:postcode":"4350",
    "addr:street":"Margaret St",
    "iso:country":"AU",
    "sg:address":"297 Margaret St",
    "sg:city":"Toowoomba",
    "sg:classifiers":[
        {
            "category":"Banks & Credit Unions",
            "subcategory":"Investment Brokerage",
            "type":"Services"
        }
    ],
    "sg:phone":"+61 7 4639 1399",
    "sg:postcode":"4350",
    "sg:province":"QLD",
    "wof:name":"Charter Financial Planning",
    "wof:placetype":"venue"
},
  "geometry": {"coordinates":[151.94882200000001,-27.56019],"type":"Point"}
}