{
  "type": "Feature",
  "properties": {
    "iso:country":"AU",
    "sg:address":"45 Incana Drv",
    "sg:city":"Mill Park",
    "sg:classifiers":[
        {
            "category":"Personal",
            "subcategory":"Massage",
            "type":"Services"
        }
    ],
    "sg:phone":"+61 409 105 811",
    "sg:postcode":"3082",
    "sg:province":"VIC",
    "sg:tags":[
        "therapy"
    ],
    "wof:name":"Avagliano Joann Booth",
    "wof:placetype":"venue"
},
  "geometry": {"coordinates":[145.08160400400001,-37.6679458618],"type":"Point"}
}