{
  "type": "Feature",
  "properties": {
    "addr:full":"24- 26 Cambridge St Box Hill VIC 3128",
    "addr:housenumber":"26",
    "addr:postcode":"3128",
    "addr:street":"Cambridge St",
    "iso:country":"AU",
    "sg:address":"24- 26 Cambridge St",
    "sg:city":"Box Hill",
    "sg:classifiers":[
        {
            "category":"Retail",
            "subcategory":"Event Space",
            "type":"Services"
        }
    ],
    "sg:phone":"+61 3 9898 1220",
    "sg:postcode":"3128",
    "sg:province":"VIC",
    "sg:tags":[
        "function",
        "organiser"
    ],
    "wof:name":"Cambridge International",
    "wof:placetype":"venue"
},
  "geometry": {"coordinates":[145.119873047,-37.8203964233],"type":"Point"}
}