{
  "type": "Feature",
  "properties": {
    "addr:full":"3 Sweet Wattle Pl Somerville VIC 3912",
    "addr:housenumber":"3",
    "addr:postcode":"3912",
    "addr:street":"Sweet Wattle Pl",
    "iso:country":"AU",
    "sg:address":"3 Sweet Wattle Pl",
    "sg:city":"Somerville",
    "sg:classifiers":[
        {
            "category":"Professional",
            "subcategory":"Art Services",
            "type":"Services"
        }
    ],
    "sg:phone":"+61 410 692 952",
    "sg:postcode":"3912",
    "sg:province":"VIC",
    "sg:tags":[
        "interior",
        "decorator"
    ],
    "wof:name":"Always Busy Colours & Design",
    "wof:placetype":"venue"
},
  "geometry": {"coordinates":[145.185546875,-38.2318305969],"type":"Point"}
}