{
  "type": "Feature",
  "properties": {
    "iso:country":"AU",
    "sg:address":"32 Smith St",
    "sg:city":"Warragul",
    "sg:classifiers":[
        {
            "category":"Manufacturing",
            "subcategory":"Jewelry",
            "type":"Manufacturing & Wholesale Goods"
        }
    ],
    "sg:phone":"+61 3 5623 1773",
    "sg:postcode":"3820",
    "sg:province":"VIC",
    "sg:tags":[
        "designer",
        "jewellery"
    ],
    "wof:name":"Pettits Jewellers",
    "wof:placetype":"venue"
},
  "geometry": {"coordinates":[145.931458,-38.162422],"type":"Point"}
}