{
  "type": "Feature",
  "properties": {
    "addr:full":"Kenwick Rd Kenwick WA 6107",
    "addr:postcode":"6107",
    "addr:street":"Kenwick Rd",
    "iso:country":"AU",
    "sg:address":"Kenwick Rd",
    "sg:city":"Kenwick",
    "sg:classifiers":[
        {
            "category":"Education",
            "subcategory":"School",
            "type":"Public Place"
        }
    ],
    "sg:phone":"+61 8 9459 1251",
    "sg:postcode":"6107",
    "sg:province":"WA",
    "sg:tags":[
        "state",
        "except",
        "nsw"
    ],
    "wof:name":"East Kenwick Primary",
    "wof:placetype":"venue"
},
  "geometry": {"coordinates":[115.973243713,-32.0352058411],"type":"Point"}
}