{
  "type": "Feature",
  "properties": {
    "addr:full":"13 Western Ave Hepburn Springs VIC 3461",
    "addr:housenumber":"13",
    "addr:postcode":"3461",
    "addr:street":"Western Ave Hepburn Springs",
    "iso:country":"AU",
    "sg:address":"13 Western Ave",
    "sg:city":"Hepburn Springs",
    "sg:classifiers":[
        {
            "category":"Donuts",
            "subcategory":"None",
            "type":"Food & Drink"
        }
    ],
    "sg:phone":"+61 3 5348 1815",
    "sg:postcode":"3461",
    "sg:province":"VIC",
    "sg:tags":[
        "die",
        "engraver",
        "sinker"
    ],
    "wof:name":"Tag Safe",
    "wof:placetype":"venue"
},
  "geometry": {"coordinates":[144.13502502399999,-37.3215103149],"type":"Point"}
}