{
  "type": "Feature",
  "properties": {
    "addr:full":"East Side Village, New Cleveland Rd Gumdale QLD 4154",
    "addr:postcode":"4154",
    "addr:street":"Cleveland Rd",
    "iso:country":"AU",
    "sg:address":"East Side Village, New Cleveland Rd",
    "sg:city":"Gumdale",
    "sg:classifiers":[
        {
            "category":"Personal",
            "subcategory":"Beauty Salon",
            "type":"Services"
        }
    ],
    "sg:phone":"+61 7 3907 0834",
    "sg:postcode":"4154",
    "sg:province":"QLD",
    "sg:tags":[
        "hairdresser"
    ],
    "wof:name":"Charlie's Place",
    "wof:placetype":"venue"
},
  "geometry": {"coordinates":[153.15237426799999,-27.4907112122],"type":"Point"}
}