{
  "type": "Feature",
  "properties": {
    "iso:country":"AU",
    "sg:address":"78 Toowoon Bay Rd",
    "sg:city":"Toowoon Bay",
    "sg:classifiers":[
        {
            "category":"Shopping",
            "subcategory":"Antiques",
            "type":"Retail Goods"
        }
    ],
    "sg:phone":"+61 2 4334 1775",
    "sg:postcode":"2261",
    "sg:province":"NSW",
    "wof:name":"Toowoon Bay Antiques",
    "wof:placetype":"venue"
},
  "geometry": {"coordinates":[151.495804,-33.357735],"type":"Point"}
}