{
  "type": "Feature",
  "properties": {
    "iso:country":"AU",
    "sg:address":"36 Palm St",
    "sg:city":"Rowes Bay",
    "sg:classifiers":[
        {
            "category":"Professional",
            "subcategory":"Business Services",
            "type":"Services"
        }
    ],
    "sg:phone":"+61 7 4724 3244",
    "sg:postcode":"4810",
    "sg:province":"QLD",
    "sg:tags":[
        "drafting"
    ],
    "wof:name":"Viv-E Design",
    "wof:placetype":"venue"
},
  "geometry": {"coordinates":[146.78732299999999,-19.238016],"type":"Point"}
}