{
  "type": "Feature",
  "properties": {
    "iso:country":"AU",
    "sg:address":"5 Dursley Rd",
    "sg:city":"Fairfield",
    "sg:classifiers":[
        {
            "category":"Transit Center",
            "subcategory":"Passenger",
            "type":"Transportation"
        }
    ],
    "sg:phone":"+61 2 9892 2186",
    "sg:postcode":"2165",
    "sg:province":"NSW",
    "sg:tags":[
        "packing",
        "gasket"
    ],
    "wof:name":"Sealrite Gaskets Pty Ltd",
    "wof:placetype":"venue"
},
  "geometry": {"coordinates":[150.95884704599999,-33.8577804565],"type":"Point"}
}