{
  "type": "Feature",
  "properties": {
    "iso:country":"AU",
    "sg:address":"27 Meek Rd",
    "sg:city":"Marrickville",
    "sg:classifiers":[
        {
            "category":"Manufacturing",
            "subcategory":"Furniture",
            "type":"Manufacturing & Wholesale Goods"
        }
    ],
    "sg:phone":"+61 408 602 455",
    "sg:postcode":"2204",
    "sg:province":"NSW",
    "sg:tags":[
        "builder",
        "designer",
        "custom"
    ],
    "wof:name":"Nicholas Pike Furniture",
    "wof:placetype":"venue"
},
  "geometry": {"coordinates":[151.162277,-33.911331],"type":"Point"}
}