{
  "type": "Feature",
  "properties": {
    "addr:full":"57 Ronald St Robinvale VIC 3549",
    "addr:housenumber":"57",
    "addr:postcode":"3549",
    "addr:street":"Ronald St",
    "iso:country":"AU",
    "sg:address":"57 Ronald St",
    "sg:city":"Robinvale",
    "sg:classifiers":[
        {
            "category":"Retail",
            "subcategory":"Veterinary Services",
            "type":"Services"
        }
    ],
    "sg:phone":"+61 3 5026 1984",
    "sg:postcode":"3549",
    "sg:province":"VIC",
    "sg:tags":[
        "surgeon"
    ],
    "wof:name":"Robinvale Veterinary Clinic",
    "wof:placetype":"venue"
},
  "geometry": {"coordinates":[142.77711486800001,-34.5881156921],"type":"Point"}
}