{
  "type": "Feature",
  "properties": {
    "addr:full":"6 Sark Crt Hoppers Crossing VIC 3029",
    "addr:housenumber":"6",
    "addr:postcode":"3029",
    "addr:street":"Sark Crt",
    "iso:country":"AU",
    "sg:address":"6 Sark Crt",
    "sg:city":"Hoppers Crossing",
    "sg:classifiers":[
        {
            "category":"Professional",
            "subcategory":"Detective & Security Services",
            "type":"Services"
        }
    ],
    "sg:phone":"+61 3 9974 3663",
    "sg:postcode":"3029",
    "sg:province":"VIC",
    "sg:tags":[
        "consultant",
        "system"
    ],
    "wof:name":"RedB Enterprises",
    "wof:placetype":"venue"
},
  "geometry": {"coordinates":[144.67465200000001,-37.852795],"type":"Point"}
}