{
  "type": "Feature",
  "properties": {
    "addr:full":"Ken Howard Drv Nambucca Heads NSW 2448",
    "addr:postcode":"2448",
    "addr:street":"Howard Drv",
    "iso:country":"AU",
    "sg:address":"Ken Howard Drv",
    "sg:city":"Nambucca Heads",
    "sg:classifiers":[
        {
            "category":"Commercial Area",
            "type":"Public Place"
        }
    ],
    "sg:phone":"+61 2 6568 6322",
    "sg:postcode":"2448",
    "sg:province":"NSW",
    "sg:tags":[
        "heavy",
        "carrier"
    ],
    "wof:name":"Midcoast Freight - Tyretrans",
    "wof:placetype":"venue"
},
  "geometry": {"coordinates":[152.980682,-30.635605],"type":"Point"}
}