{
  "type": "Feature",
  "properties": {
    "addr:full":"8 Queen St Nambour QLD 4560",
    "addr:housenumber":"8",
    "addr:postcode":"4560",
    "addr:street":"Queen St",
    "iso:country":"AU",
    "sg:address":"8 Queen St",
    "sg:city":"Nambour",
    "sg:classifiers":[
        {
            "category":"Health Services",
            "subcategory":"Health Practitioner",
            "type":"Services"
        }
    ],
    "sg:phone":"+61 7 5441 1953",
    "sg:postcode":"4560",
    "sg:province":"QLD",
    "sg:tags":[
        "psychologist"
    ],
    "wof:name":"Dique Leah Psychologist",
    "wof:placetype":"venue"
},
  "geometry": {"coordinates":[152.95994567899999,-26.6267204285],"type":"Point"}
}