{
  "type": "Feature",
  "properties": {
    "iso:country":"AU",
    "sg:address":"53 Winnellie Rd",
    "sg:city":"Winnellie",
    "sg:classifiers":[
        {
            "category":"Home & Garden",
            "subcategory":"Building Materials",
            "type":"Retail Goods"
        }
    ],
    "sg:phone":"+61 8 8947 0077",
    "sg:postcode":"0820",
    "sg:province":"NT",
    "sg:tags":[
        "decorative",
        "coating"
    ],
    "wof:name":"Granosite",
    "wof:placetype":"venue"
},
  "geometry": {"coordinates":[130.87796020499999,-12.4264888763],"type":"Point"}
}