{
  "type": "Feature",
  "properties": {
    "addr:full":"1/ 54 Shannon Ave Geelong West VIC 3218",
    "addr:housenumber":"/ 54",
    "addr:postcode":"3218",
    "addr:street":"Shannon Ave",
    "iso:country":"AU",
    "sg:address":"1/ 54 Shannon Ave",
    "sg:city":"Geelong West",
    "sg:classifiers":[
        {
            "category":"Organizations",
            "subcategory":"Professional Association",
            "type":"Services"
        }
    ],
    "sg:phone":"+61 3 5229 7662",
    "sg:postcode":"3218",
    "sg:province":"VIC",
    "sg:tags":[
        "web",
        "internet"
    ],
    "wof:name":"Bri-Ter Design",
    "wof:placetype":"venue"
},
  "geometry": {"coordinates":[144.33793640100001,-38.133354187],"type":"Point"}
}