{
  "type": "Feature",
  "properties": {
    "addr:full":"3 McIlwraith St South Townsville QLD 4810",
    "addr:housenumber":"3",
    "addr:postcode":"4810",
    "addr:street":"Mcilwraith St",
    "iso:country":"AU",
    "sg:address":"3 McIlwraith St",
    "sg:city":"South Townsville",
    "sg:classifiers":[
        {
            "category":"Building & Trades",
            "subcategory":"Landscaping Services",
            "type":"Services"
        }
    ],
    "sg:phone":"+61 7 4724 5566",
    "sg:postcode":"4810",
    "sg:province":"QLD",
    "sg:tags":[
        "designer",
        "landscape",
        "contractor"
    ],
    "wof:name":"Naturform Pty Ltd",
    "wof:placetype":"venue"
},
  "geometry": {"coordinates":[146.82002299999999,-19.261831],"type":"Point"}
}