{
  "type": "Feature",
  "properties": {
    "addr:full":"Cliffords Rd Somerton VIC 3062",
    "addr:postcode":"3062",
    "addr:street":"Cliffords Rd",
    "iso:country":"AU",
    "sg:address":"Cliffords Rd",
    "sg:city":"Somerton",
    "sg:classifiers":[
        {
            "category":"Manufacturing",
            "subcategory":"Metals",
            "type":"Manufacturing & Wholesale Goods"
        }
    ],
    "sg:phone":"+61 3 9305 4144",
    "sg:postcode":"3062",
    "sg:province":"VIC",
    "sg:tags":[
        "steel",
        "fabricator",
        "mfrs"
    ],
    "wof:name":"Onesteel Martin Bright Pty Ltd",
    "wof:placetype":"venue"
},
  "geometry": {"coordinates":[144.94009399399999,-37.6347198486],"type":"Point"}
}