{
  "type": "Feature",
  "properties": {
    "addr:full":"Flaxley Rd Echunga SA 5153",
    "addr:postcode":"5153",
    "addr:street":"Flaxley Rd",
    "iso:country":"AU",
    "sg:address":"Flaxley Rd",
    "sg:city":"Echunga",
    "sg:classifiers":[
        {
            "category":"Real Estate",
            "subcategory":"Architect",
            "type":"Services"
        }
    ],
    "sg:phone":"+61 8 8388 8271",
    "sg:postcode":"5153",
    "sg:province":"SA",
    "sg:tags":[
        "building",
        "designer"
    ],
    "wof:name":"Detail Homes & Designs",
    "wof:placetype":"venue"
},
  "geometry": {"coordinates":[138.831344605,-35.1069107056],"type":"Point"}
}