{
  "type": "Feature",
  "properties": {
    "addr:full":"4 Alexander St Narrabri NSW 2390",
    "addr:housenumber":"4",
    "addr:postcode":"2390",
    "addr:street":"Alexander St",
    "iso:country":"AU",
    "sg:address":"4 Alexander St",
    "sg:city":"Narrabri",
    "sg:classifiers":[
        {
            "category":"Building & Trades",
            "subcategory":"Landscaping Services",
            "type":"Services"
        }
    ],
    "sg:phone":"+61 407 468 768",
    "sg:postcode":"2390",
    "sg:province":"NSW",
    "sg:tags":[
        "grazier"
    ],
    "wof:name":"Douglas M J F",
    "wof:placetype":"venue"
},
  "geometry": {"coordinates":[149.76792907699999,-30.3327865601],"type":"Point"}
}