{
  "type": "Feature",
  "properties": {
    "addr:full":"571 Great Western Hwy Huntingwood NSW 2148",
    "addr:housenumber":"571",
    "addr:postcode":"2148",
    "addr:street":"Great Western Hwy",
    "iso:country":"AU",
    "sg:address":"571 Great Western Hwy",
    "sg:city":"Huntingwood",
    "sg:classifiers":[
        {
            "category":"Farming",
            "subcategory":"Poultry Farm",
            "type":"Manufacturing & Wholesale Goods"
        }
    ],
    "sg:phone":"+61 2 9672 1399",
    "sg:postcode":"2148",
    "sg:province":"NSW",
    "sg:tags":[
        "farmer"
    ],
    "wof:name":"Barter S F & Sons",
    "wof:placetype":"venue"
},
  "geometry": {"coordinates":[150.872924805,-33.792175293],"type":"Point"}
}