{
  "type": "Feature",
  "properties": {
    "addr:full":"49 Station St Malvern VIC 3144",
    "addr:housenumber":"49",
    "addr:postcode":"3144",
    "addr:street":"Station St",
    "iso:country":"AU",
    "sg:address":"49 Station St",
    "sg:city":"Malvern",
    "sg:classifiers":[
        {
            "category":"Insurance",
            "subcategory":"Insurance Agent",
            "type":"Services"
        }
    ],
    "sg:phone":"+61 3 9509 0999",
    "sg:postcode":"3144",
    "sg:province":"VIC",
    "sg:tags":[
        "broker"
    ],
    "wof:name":"Roberts Joyce Insurance Brokers (Aust) Pty Ltd",
    "wof:placetype":"venue"
},
  "geometry": {"coordinates":[145.02923584000001,-37.8654975891],"type":"Point"}
}