{
  "type": "Feature",
  "properties": {
    "addr:full":"31- 33 Victoria St Ballarat VIC 3350",
    "addr:housenumber":"33",
    "addr:postcode":"3350",
    "addr:street":"Victoria St",
    "iso:country":"AU",
    "sg:address":"31- 33 Victoria St",
    "sg:city":"Ballarat",
    "sg:classifiers":[
        {
            "category":"Fast Food",
            "type":"Food & Drink"
        }
    ],
    "sg:phone":"+61 13 11 66",
    "sg:postcode":"3350",
    "sg:province":"VIC",
    "sg:tags":[
        "away",
        "take"
    ],
    "wof:name":"Pizza Hut",
    "wof:placetype":"venue"
},
  "geometry": {"coordinates":[143.86878999999999,-37.57589],"type":"Point"}
}