{
  "type": "Feature",
  "properties": {
    "addr:full":"199 Hawke St West Melbourne VIC 3003",
    "addr:housenumber":"199",
    "addr:postcode":"3003",
    "addr:street":"Hawke St",
    "iso:country":"AU",
    "sg:address":"199 Hawke St",
    "sg:city":"West Melbourne",
    "sg:classifiers":[
        {
            "category":"Retail",
            "subcategory":"Storage",
            "type":"Services"
        }
    ],
    "sg:phone":"+61 3 9328 3701",
    "sg:postcode":"3003",
    "sg:province":"VIC",
    "wof:name":"Moorside Document Storage",
    "wof:placetype":"venue"
},
  "geometry": {"coordinates":[144.944778442,-37.8093070984],"type":"Point"}
}