{
  "type": "Feature",
  "properties": {
    "iso:country":"AU",
    "sg:address":"108 Pickering St",
    "sg:city":"Enoggera",
    "sg:classifiers":[
        {
            "category":"Recreation",
            "subcategory":"Boat Charter",
            "type":"Entertainment"
        }
    ],
    "sg:phone":"+61 7 3855 4444",
    "sg:postcode":"4051",
    "sg:province":"QLD",
    "sg:tags":[
        "canopy",
        "motor"
    ],
    "wof:name":"TJM 4WD Megastores",
    "wof:placetype":"venue"
},
  "geometry": {"coordinates":[152.991821289,-27.4192485809],"type":"Point"}
}