{
  "type": "Feature",
  "properties": {
    "iso:country":"AU",
    "sg:address":"1403 Logan Rd",
    "sg:city":"Mt Gravatt",
    "sg:classifiers":[
        {
            "category":"Health Services",
            "subcategory":"Dentist",
            "type":"Services"
        }
    ],
    "sg:phone":"+61 7 3343 2100",
    "sg:postcode":"4122",
    "sg:province":"QLD",
    "wof:name":"Kham Le",
    "wof:placetype":"venue"
},
  "geometry": {"coordinates":[153.07928466800001,-27.5385322571],"type":"Point"}
}