{
  "type": "Feature",
  "properties": {
    "iso:country":"AU",
    "sg:address":"16 Bull St",
    "sg:city":"Cooks Hill",
    "sg:classifiers":[
        {
            "category":"Education",
            "subcategory":"University",
            "type":"Public Place"
        }
    ],
    "sg:phone":"+61 2 4927 0156",
    "sg:postcode":"2300",
    "sg:province":"NSW",
    "sg:tags":[
        "educational",
        "organisation",
        "cultural"
    ],
    "wof:name":"WEA NSW",
    "wof:placetype":"venue"
},
  "geometry": {"coordinates":[151.771332,-32.93264],"type":"Point"}
}