{
  "type": "Feature",
  "properties": {
    "iso:country":"AU",
    "sg:address":"80 Glenala Rd",
    "sg:city":"Durack",
    "sg:classifiers":[
        {
            "category":"Health Services",
            "subcategory":"Doctor",
            "type":"Services"
        }
    ],
    "sg:phone":"+61 7 3372 4577",
    "sg:postcode":"4077",
    "sg:province":"QLD",
    "sg:tags":[
        "medical",
        "practitioner"
    ],
    "wof:name":"Durack Medical Centre",
    "wof:placetype":"venue"
},
  "geometry": {"coordinates":[152.98452758799999,-27.5854511261],"type":"Point"}
}