{
  "type": "Feature",
  "properties": {
    "addr:full":"3/ 1236 Boundary Rd Wacol QLD 4076",
    "addr:housenumber":"/ 1236",
    "addr:postcode":"4076",
    "addr:street":"Boundary Rd",
    "iso:country":"AU",
    "sg:address":"3/ 1236 Boundary Rd",
    "sg:city":"Wacol",
    "sg:classifiers":[
        {
            "category":"Professional",
            "subcategory":"Employment Agencies",
            "type":"Services"
        }
    ],
    "sg:phone":"+61 7 3271 4166",
    "sg:postcode":"4076",
    "sg:province":"QLD",
    "sg:tags":[
        "hire",
        "labour",
        "contractor"
    ],
    "wof:name":"Macquarie People Labour Hire",
    "wof:placetype":"venue"
},
  "geometry": {"coordinates":[152.93429565400001,-27.5938911438],"type":"Point"}
}