{
  "type": "Feature",
  "properties": {
    "addr:full":"5/ 3 Richard Cl North Rocks NSW 2151",
    "addr:housenumber":"/ 3",
    "addr:postcode":"2151",
    "addr:street":"Richard Cl",
    "iso:country":"AU",
    "sg:address":"5/ 3 Richard Cl",
    "sg:city":"North Rocks",
    "sg:classifiers":[
        {
            "category":"Retail",
            "subcategory":"Auto Repair",
            "type":"Services"
        }
    ],
    "sg:phone":"+61 2 9890 3434",
    "sg:postcode":"2151",
    "sg:province":"NSW",
    "sg:tags":[
        "repairer",
        "motor",
        "engineer"
    ],
    "wof:name":"Stewart Follows Automotive Pty Ltd",
    "wof:placetype":"venue"
},
  "geometry": {"coordinates":[151.021286011,-33.7750396729],"type":"Point"}
}