{
  "type": "Feature",
  "properties": {
    "iso:country":"AU",
    "sg:address":"15 Helios St",
    "sg:city":"Shailer Park",
    "sg:classifiers":[
        {
            "category":"Building & Trades",
            "subcategory":"Construction",
            "type":"Services"
        }
    ],
    "sg:phone":"+61 7 3209 6141",
    "sg:postcode":"4128",
    "sg:province":"QLD",
    "sg:tags":[
        "brick",
        "paving"
    ],
    "wof:name":"Robinson David",
    "wof:placetype":"venue"
},
  "geometry": {"coordinates":[153.17486572300001,-27.6556797028],"type":"Point"}
}