{
  "type": "Feature",
  "properties": {
    "addr:full":"410 Huntingdale Rd Chadstone VIC 3148",
    "addr:housenumber":"410",
    "addr:postcode":"3148",
    "addr:street":"Huntingdale Rd",
    "iso:country":"AU",
    "sg:address":"410 Huntingdale Rd",
    "sg:city":"Chadstone",
    "sg:classifiers":[
        {
            "category":"Health Services",
            "subcategory":"Health Practitioner",
            "type":"Services"
        }
    ],
    "sg:phone":"+61 3 9888 2522",
    "sg:postcode":"3148",
    "sg:province":"VIC",
    "sg:tags":[
        "physiotherapist"
    ],
    "wof:name":"Clough Jan",
    "wof:placetype":"venue"
},
  "geometry": {"coordinates":[145.10934448200001,-37.8814849854],"type":"Point"}
}