{
  "type": "Feature",
  "properties": {
    "addr:full":"64 Bultje St Dubbo NSW 2830",
    "addr:housenumber":"64",
    "addr:postcode":"2830",
    "addr:street":"Bultje St",
    "iso:country":"AU",
    "sg:address":"64 Bultje St",
    "sg:city":"Dubbo",
    "sg:classifiers":[
        {
            "category":"Health Services",
            "subcategory":"Health Practitioner",
            "type":"Services"
        }
    ],
    "sg:phone":"+61 428 840 833",
    "sg:postcode":"2830",
    "sg:province":"NSW",
    "sg:tags":[
        "naturopath"
    ],
    "wof:name":"Liza Twohill",
    "wof:placetype":"venue"
},
  "geometry": {"coordinates":[148.604980469,-32.2514762878],"type":"Point"}
}