{
  "type": "Feature",
  "properties": {
    "addr:full":"28 Kidman St Alice Springs NT 0870",
    "addr:housenumber":"28",
    "addr:postcode":"nt 0870",
    "addr:street":"Kidman St",
    "iso:country":"AU",
    "sg:address":"28 Kidman St",
    "sg:city":"Alice Springs",
    "sg:classifiers":[
        {
            "category":"Utilities",
            "subcategory":"Electric",
            "type":"Services"
        }
    ],
    "sg:phone":"+61 8 8952 3344",
    "sg:postcode":"0870",
    "sg:province":"NT",
    "sg:tags":[
        "electrical",
        "contractor"
    ],
    "wof:name":"C.K.S. Electrical Mechanical Services Pty Ltd",
    "wof:placetype":"venue"
},
  "geometry": {"coordinates":[133.86964416500001,-23.696100235],"type":"Point"}
}