{
  "type": "Feature",
  "properties": {
    "iso:country":"AU",
    "sg:address":"Suite C15 Level 1, Dalgety Square 376-428 Wattle S",
    "sg:city":"Ultimo",
    "sg:classifiers":[
        {
            "category":"Arena",
            "subcategory":"Sports Club",
            "type":"Entertainment"
        }
    ],
    "sg:phone":"+61 13 19 69",
    "sg:postcode":"2007",
    "sg:province":"NSW",
    "sg:tags":[
        "tour",
        "holiday"
    ],
    "wof:name":"Asia Specialist Holidays",
    "wof:placetype":"venue"
},
  "geometry": {"coordinates":[151.196777344,-33.880531311],"type":"Point"}
}