{
  "type": "Feature",
  "properties": {
    "addr:full":"Cnr Bains & Panatalinga Rds, Woodcroft SA 5162",
    "addr:postcode":"5162",
    "iso:country":"AU",
    "sg:address":"Cnr Bains & Panatalinga Rds,",
    "sg:city":"Woodcroft",
    "sg:classifiers":[
        {
            "category":"Communications",
            "subcategory":"Film & Video Production",
            "type":"Services"
        }
    ],
    "sg:phone":"+61 8 8325 0155",
    "sg:postcode":"5162",
    "sg:province":"SA",
    "sg:tags":[
        "mirror"
    ],
    "wof:name":"Woodcroft Picture Framing",
    "wof:placetype":"venue"
},
  "geometry": {"coordinates":[138.55723571799999,-35.1140708923],"type":"Point"}
}