{
  "type": "Feature",
  "properties": {
    "addr:full":"3 Florence Ave Gosford NSW 2250",
    "addr:housenumber":"3",
    "addr:postcode":"2250",
    "addr:street":"Florence Ave",
    "iso:country":"AU",
    "sg:address":"3 Florence Ave",
    "sg:city":"Gosford",
    "sg:classifiers":[
        {
            "category":"Professional",
            "subcategory":"Business Services",
            "type":"Services"
        }
    ],
    "sg:phone":"+61 2 4325 7505",
    "sg:postcode":"2250",
    "sg:province":"NSW",
    "sg:tags":[
        "drafting"
    ],
    "wof:name":"Cherry NSW",
    "wof:placetype":"venue"
},
  "geometry": {"coordinates":[151.34231567399999,-33.4387359619],"type":"Point"}
}