{
  "type": "Feature",
  "properties": {
    "iso:country":"AU",
    "sg:address":"1 Carson St",
    "sg:city":"Dundas",
    "sg:classifiers":[
        {
            "category":"Real Estate",
            "subcategory":"Architect",
            "type":"Services"
        }
    ],
    "sg:phone":"+61 2 9874 0113",
    "sg:postcode":"2117",
    "sg:province":"NSW",
    "sg:tags":[
        "building",
        "designer"
    ],
    "wof:name":"Warner Peter",
    "wof:placetype":"venue"
},
  "geometry": {"coordinates":[151.06347656200001,-33.7962608337],"type":"Point"}
}