{
  "type": "Feature",
  "properties": {
    "iso:country":"AU",
    "sg:address":"Unit 9U, 175 Gibbes St",
    "sg:city":"Chatswood",
    "sg:classifiers":[
        {
            "category":"Building & Trades",
            "subcategory":"Construction",
            "type":"Services"
        }
    ],
    "sg:phone":"+61 2 9406 8400",
    "sg:postcode":"2067",
    "sg:province":"NSW",
    "sg:tags":[
        "contractor"
    ],
    "wof:name":"Crestway Construction Pty Ltd",
    "wof:placetype":"venue"
},
  "geometry": {"coordinates":[151.198165894,-33.7848129272],"type":"Point"}
}