{
  "type": "Feature",
  "properties": {
    "addr:full":"Noosa-Cooroy Rd Tewantin QLD 4565",
    "addr:postcode":"4565",
    "addr:street":"Noosa-Cooroy Rd",
    "iso:country":"AU",
    "sg:address":"Noosa-Cooroy Rd",
    "sg:city":"Tewantin",
    "sg:classifiers":[
        {
            "category":"Retail",
            "subcategory":"Funeral Services",
            "type":"Services"
        }
    ],
    "sg:phone":"+61 7 5449 9383",
    "sg:postcode":"4565",
    "sg:province":"QLD",
    "sg:tags":[
        "director"
    ],
    "wof:name":"Drysdale Funerals",
    "wof:placetype":"venue"
},
  "geometry": {"coordinates":[153.08274841299999,-26.4040546417],"type":"Point"}
}