{
  "type": "Feature",
  "properties": {
    "addr:full":"Suite 11/ 480 Military Rd Mosman NSW 2088",
    "addr:housenumber":"11 / 480",
    "addr:postcode":"2088",
    "addr:street":"Military Rd",
    "iso:country":"AU",
    "sg:address":"Suite 11/ 480 Military Rd",
    "sg:city":"Mosman",
    "sg:classifiers":[
        {
            "category":"Professional",
            "subcategory":"Computer Services",
            "type":"Services"
        }
    ],
    "sg:phone":"+61 409 376 683",
    "sg:postcode":"2088",
    "sg:province":"NSW",
    "sg:tags":[
        "consultant",
        "system"
    ],
    "wof:name":"Productivity Plus",
    "wof:placetype":"venue"
},
  "geometry": {"coordinates":[151.23298645,-33.8256378174],"type":"Point"}
}