{
  "type": "Feature",
  "properties": {
    "addr:full":"Gerrale St Cronulla NSW 2230",
    "addr:postcode":"2230",
    "addr:street":"St",
    "iso:country":"AU",
    "sg:address":"Gerrale St",
    "sg:city":"Cronulla",
    "sg:classifiers":[
        {
            "category":"Building & Trades",
            "subcategory":"Construction",
            "type":"Services"
        }
    ],
    "sg:phone":"+61 410 486 765",
    "sg:postcode":"2230",
    "sg:province":"NSW",
    "sg:tags":[
        "concrete",
        "contractor"
    ],
    "wof:name":"DMC Concrete",
    "wof:placetype":"venue"
},
  "geometry": {"coordinates":[151.153366089,-34.0552368164],"type":"Point"}
}