{
  "type": "Feature",
  "properties": {
    "addr:full":"93 Sternberg St Bendigo VIC 3550",
    "addr:housenumber":"93",
    "addr:postcode":"3550",
    "addr:street":"Sternberg St",
    "iso:country":"AU",
    "sg:address":"93 Sternberg St",
    "sg:city":"Bendigo",
    "sg:classifiers":[
        {
            "category":"Personal",
            "subcategory":"Massage",
            "type":"Services"
        }
    ],
    "sg:phone":"+61 3 5441 3275",
    "sg:postcode":"3550",
    "sg:province":"VIC",
    "sg:tags":[
        "therapy"
    ],
    "wof:name":"Peter Ietto",
    "wof:placetype":"venue"
},
  "geometry": {"coordinates":[144.29241943400001,-36.7670288086],"type":"Point"}
}