{
  "type": "Feature",
  "properties": {
    "addr:full":"Shop 2 10 Heidke St Bundaberg QLD 4670",
    "addr:housenumber":"shop;10",
    "addr:postcode":"4670",
    "addr:street":"Heidke St",
    "iso:country":"AU",
    "sg:address":"Shop 2 10 Heidke St",
    "sg:city":"Bundaberg",
    "sg:classifiers":[
        {
            "category":"Personal",
            "type":"Services"
        }
    ],
    "sg:phone":"+61 1800 630 722",
    "sg:postcode":"4670",
    "sg:province":"QLD",
    "sg:tags":[
        "gift"
    ],
    "wof:name":"Westside Florist & Gifts",
    "wof:placetype":"venue"
},
  "geometry": {"coordinates":[152.32041931099999,-24.8870239258],"type":"Point"}
}