{
  "type": "Feature",
  "properties": {
    "addr:full":"1094 Botany Rd Botany NSW 2019",
    "addr:housenumber":"1094",
    "addr:postcode":"2019",
    "addr:street":"Botany Rd",
    "iso:country":"AU",
    "sg:address":"1094 Botany Rd",
    "sg:city":"Botany",
    "sg:classifiers":[
        {
            "category":"Shopping",
            "subcategory":"Computers & Home Electronics",
            "type":"Retail Goods"
        }
    ],
    "sg:phone":"+61 2 9695 1393",
    "sg:postcode":"2019",
    "sg:province":"NSW",
    "sg:tags":[
        "small",
        "equipment",
        "business"
    ],
    "wof:name":"AJS Computers 4 U",
    "wof:placetype":"venue"
},
  "geometry": {"coordinates":[151.195678711,-33.9435081482],"type":"Point"}
}