{
  "type": "Feature",
  "properties": {
    "iso:country":"AU",
    "sg:address":"Unit 8 14 Hensman St",
    "sg:city":"South Perth",
    "sg:classifiers":[
        {
            "category":"Shopping",
            "subcategory":"Baby Store",
            "type":"Retail Goods"
        }
    ],
    "sg:phone":"+61 8 9368 6849",
    "sg:postcode":"6151",
    "sg:province":"WA",
    "sg:tags":[
        "wear"
    ],
    "wof:name":"Heavenly Christening Outfits",
    "wof:placetype":"venue"
},
  "geometry": {"coordinates":[115.856697,-31.983503],"type":"Point"}
}