{
  "type": "Feature",
  "properties": {
    "addr:full":"14 Creswick St Glen Waverley VIC 3150",
    "addr:housenumber":"14",
    "addr:postcode":"3150",
    "addr:street":"Creswick St",
    "iso:country":"AU",
    "sg:address":"14 Creswick St",
    "sg:city":"Glen Waverley",
    "sg:classifiers":[
        {
            "category":"Utilities",
            "subcategory":"Electric",
            "type":"Services"
        }
    ],
    "sg:phone":"+61 3 9560 4685",
    "sg:postcode":"3150",
    "sg:province":"VIC",
    "sg:tags":[
        "electrical",
        "contractor"
    ],
    "wof:name":"O&#039;Shea T H & Associates",
    "wof:placetype":"venue"
},
  "geometry": {"coordinates":[145.1849823,-37.8812065125],"type":"Point"}
}