{
  "type": "Feature",
  "properties": {
    "addr:full":"19 Carlo St Pialba QLD 4655",
    "addr:housenumber":"19",
    "addr:postcode":"4655",
    "addr:street":"Carlo St",
    "iso:country":"AU",
    "sg:address":"19 Carlo St",
    "sg:city":"Pialba",
    "sg:classifiers":[
        {
            "category":"Bars & Pubs",
            "subcategory":"Nightclub",
            "type":"Food & Drink"
        }
    ],
    "sg:phone":"+61 7 4124 8300",
    "sg:postcode":"4655",
    "sg:province":"QLD",
    "sg:tags":[
        "discotheque"
    ],
    "wof:name":"Seven",
    "wof:placetype":"venue"
},
  "geometry": {"coordinates":[152.83320599999999,-25.286037],"type":"Point"}
}