{
  "type": "Feature",
  "properties": {
    "iso:country":"AU",
    "sg:address":"PO Box 1325",
    "sg:city":"Belconnen",
    "sg:classifiers":[
        {
            "category":"Utilities",
            "subcategory":"Telephone",
            "type":"Services"
        }
    ],
    "sg:phone":"+61 408 770 767",
    "sg:postcode":"2616",
    "sg:province":"ACT",
    "sg:tags":[
        "installation",
        "system",
        "maintenance"
    ],
    "wof:name":"Netchange",
    "wof:placetype":"venue"
},
  "geometry": {"coordinates":[149.06735229500001,-35.2362289429],"type":"Point"}
}