{
  "type": "Feature",
  "properties": {
    "addr:full":"Shop 14 42 Harp St Belmont NSW 2280",
    "addr:housenumber":"shop 14 42",
    "addr:postcode":"2280",
    "addr:street":"Harp St",
    "iso:country":"AU",
    "sg:address":"Shop 14 42 Harp St",
    "sg:city":"Belmont",
    "sg:classifiers":[
        {
            "category":"Professional",
            "subcategory":"Printing & Photocopies",
            "type":"Services"
        }
    ],
    "sg:phone":"+61 2 9718 9570",
    "sg:postcode":"2280",
    "sg:province":"NSW",
    "sg:tags":[
        "embroidery"
    ],
    "wof:name":"New Line Embroidery Company",
    "wof:placetype":"venue"
},
  "geometry": {"coordinates":[151.657913208,-33.0347557068],"type":"Point"}
}