{
  "type": "Feature",
  "properties": {
    "addr:full":"197 High St Kew VIC 3101",
    "addr:housenumber":"197",
    "addr:postcode":"3101",
    "addr:street":"High St",
    "iso:country":"AU",
    "sg:address":"197 High St",
    "sg:city":"Kew",
    "sg:classifiers":[
        {
            "category":"Shopping",
            "subcategory":"Clothing, Apparel, & Fashions",
            "type":"Retail Goods"
        }
    ],
    "sg:phone":"+61 3 9853 8472",
    "sg:postcode":"3101",
    "sg:province":"VIC",
    "sg:tags":[
        "lady",
        "wear"
    ],
    "wof:name":"Langknitt",
    "wof:placetype":"venue"
},
  "geometry": {"coordinates":[145.031936645,-37.8062362671],"type":"Point"}
}