{
  "type": "Feature",
  "properties": {
    "iso:country":"AU",
    "sg:address":"13 Barrowby St",
    "sg:city":"Portland",
    "sg:classifiers":[
        {
            "category":"Building & Trades",
            "subcategory":"Construction",
            "type":"Services"
        }
    ],
    "sg:phone":"+61 438 357 180",
    "sg:postcode":"3305",
    "sg:province":"VIC",
    "sg:tags":[
        "fencing",
        "contractor"
    ],
    "wof:name":"Tigerweld",
    "wof:placetype":"venue"
},
  "geometry": {"coordinates":[141.594284058,-38.3306236267],"type":"Point"}
}