{
  "type": "Feature",
  "properties": {
    "addr:full":"69 Spencer St Fairfield NSW 2165",
    "addr:housenumber":"69",
    "addr:postcode":"2165",
    "addr:street":"Spencer St",
    "iso:country":"AU",
    "sg:address":"69 Spencer St",
    "sg:city":"Fairfield",
    "sg:classifiers":[
        {
            "category":"Health Services",
            "subcategory":"Optometrist",
            "type":"Services"
        }
    ],
    "sg:phone":"+61 2 9724 2210",
    "sg:postcode":"2165",
    "sg:province":"NSW",
    "wof:name":"Donoghue John",
    "wof:placetype":"venue"
},
  "geometry": {"coordinates":[150.95521545400001,-33.8710136414],"type":"Point"}
}