{
  "type": "Feature",
  "properties": {
    "addr:full":"Suite 1 Southlands Medical Clinic Southlands Shopng C NSW 2750",
    "addr:postcode":"2750",
    "addr:street":"C",
    "iso:country":"AU",
    "sg:address":"Suite 1",
    "sg:city":"Southlands Medical Clinic Southlands Shopng C",
    "sg:classifiers":[
        {
            "category":"Health Services",
            "subcategory":"Doctor",
            "type":"Services"
        }
    ],
    "sg:phone":"+61 2 4732 1166",
    "sg:postcode":"2750",
    "sg:province":"NSW",
    "sg:tags":[
        "medical",
        "practitioner"
    ],
    "wof:name":"Tan Helen",
    "wof:placetype":"venue"
},
  "geometry": {"coordinates":[150.69708251899999,-33.7735290527],"type":"Point"}
}