{
  "type": "Feature",
  "properties": {
    "addr:full":"96 Fairfax Rd Warners Bay NSW 2282",
    "addr:housenumber":"96",
    "addr:postcode":"2282",
    "addr:street":"Fairfax Rd",
    "iso:country":"AU",
    "sg:address":"96 Fairfax Rd",
    "sg:city":"Warners Bay",
    "sg:classifiers":[
        {
            "category":"Wholesale",
            "subcategory":"Construction Materials",
            "type":"Manufacturing & Wholesale Goods"
        }
    ],
    "sg:phone":"+61 2 4950 6600",
    "sg:postcode":"2282",
    "sg:province":"NSW",
    "sg:tags":[
        "protective",
        "coating"
    ],
    "wof:name":"Advanced Pigments & Protective Coatings",
    "wof:placetype":"venue"
},
  "geometry": {"coordinates":[151.64085388199999,-32.9619140625],"type":"Point"}
}