{
  "type": "Feature",
  "properties": {
    "addr:full":"3/ 14 Boag St Morley PLB WA 6943",
    "addr:housenumber":"/ 14",
    "addr:postcode":"6943",
    "addr:street":"Boag St",
    "iso:country":"AU",
    "sg:address":"3/ 14 Boag St",
    "sg:city":"Morley PLB",
    "sg:classifiers":[
        {
            "category":"Autos & Motor Vehicles",
            "subcategory":"Auto Supplies",
            "type":"Retail Goods"
        }
    ],
    "sg:phone":"+61 8 6363 5351",
    "sg:postcode":"6943",
    "sg:province":"WA",
    "sg:tags":[
        "accessory"
    ],
    "wof:name":"Crusin On",
    "wof:placetype":"venue"
},
  "geometry": {"coordinates":[115.89531707800001,-31.8971443176],"type":"Point"}
}