{
  "type": "Feature",
  "properties": {
    "addr:full":"17 Barina Rd Glen Iris VIC 3146",
    "addr:housenumber":"17",
    "addr:postcode":"3146",
    "addr:street":"Barina Rd",
    "iso:country":"AU",
    "sg:address":"17 Barina Rd",
    "sg:city":"Glen Iris",
    "sg:classifiers":[
        {
            "category":"Organizations",
            "subcategory":"Membership Organization",
            "type":"Services"
        }
    ],
    "sg:phone":"+61 3 9885 1303",
    "sg:postcode":"3146",
    "sg:province":"VIC",
    "sg:tags":[
        "club",
        "bridge"
    ],
    "wof:name":"Ravens Bridge Club",
    "wof:placetype":"venue"
},
  "geometry": {"coordinates":[145.06712341299999,-37.8604049683],"type":"Point"}
}