{
  "type": "Feature",
  "properties": {
    "addr:full":"PO Box 88 Floreat Forum WA 6014",
    "addr:postcode":"6014",
    "iso:country":"AU",
    "sg:address":"PO Box 88",
    "sg:city":"Floreat Forum",
    "sg:classifiers":[
        {
            "category":"Organizations",
            "subcategory":"Professional Association",
            "type":"Services"
        }
    ],
    "sg:phone":"+61 8 9367 9088",
    "sg:postcode":"6014",
    "sg:province":"WA",
    "sg:tags":[
        "web",
        "internet"
    ],
    "wof:name":"Apiix",
    "wof:placetype":"venue"
},
  "geometry": {"coordinates":[115.792800903,-31.9380493164],"type":"Point"}
}