{
  "type": "Feature",
  "properties": {
    "addr:full":"277 Elizabeth St Hobart TAS 7000",
    "addr:housenumber":"277",
    "addr:postcode":"7000",
    "addr:street":"Elizabeth St",
    "iso:country":"AU",
    "sg:address":"277 Elizabeth St",
    "sg:city":"Hobart",
    "sg:classifiers":[
        {
            "category":"Utilities",
            "subcategory":"Electric",
            "type":"Services"
        }
    ],
    "sg:phone":"+61 3 6231 4055",
    "sg:postcode":"7000",
    "sg:province":"TAS",
    "sg:tags":[
        "electrical",
        "contractor"
    ],
    "wof:name":"Electrical Testing & Compliance Service",
    "wof:placetype":"venue"
},
  "geometry": {"coordinates":[147.318115234,-42.8756103516],"type":"Point"}
}