{
  "type": "Feature",
  "properties": {
    "addr:full":"65 Margaret St Toowoomba QLD 4350",
    "addr:housenumber":"65",
    "addr:postcode":"4350",
    "addr:street":"Margaret St",
    "iso:country":"AU",
    "sg:address":"65 Margaret St",
    "sg:city":"Toowoomba",
    "sg:classifiers":[
        {
            "category":"Education",
            "subcategory":"School",
            "type":"Public Place"
        }
    ],
    "sg:phone":"+61 7 4637 5252",
    "sg:postcode":"4350",
    "sg:province":"QLD",
    "sg:tags":[
        "state",
        "except",
        "nsw"
    ],
    "wof:name":"Toowoomba East Preschool",
    "wof:placetype":"venue"
},
  "geometry": {"coordinates":[151.955063,-27.561069],"type":"Point"}
}