{
  "type": "Feature",
  "properties": {
    "addr:full":"12 Newcastle Drv Coffs Harbour NSW 2450",
    "addr:housenumber":"12",
    "addr:postcode":"2450",
    "addr:street":"Newcastle Drv",
    "iso:country":"AU",
    "sg:address":"12 Newcastle Drv",
    "sg:city":"Coffs Harbour",
    "sg:classifiers":[
        {
            "category":"Home & Garden",
            "subcategory":"Building Materials",
            "type":"Retail Goods"
        }
    ],
    "sg:phone":"+61 2 6658 9315",
    "sg:postcode":"2450",
    "sg:province":"NSW",
    "sg:tags":[
        "pre-mixed",
        "concrete"
    ],
    "wof:name":"Boral Country-Concrete & Quarries",
    "wof:placetype":"venue"
},
  "geometry": {"coordinates":[153.09150700000001,-30.361971],"type":"Point"}
}