{
  "type": "Feature",
  "properties": {
    "addr:full":"19 Philippine Pde Palm Beach QLD 4221",
    "addr:housenumber":"19",
    "addr:postcode":"4221",
    "addr:street":"Philippine Pde",
    "iso:country":"AU",
    "sg:address":"19 Philippine Pde",
    "sg:city":"Palm Beach",
    "sg:classifiers":[
        {
            "category":"Cafe",
            "type":"Food & Drink"
        }
    ],
    "sg:phone":"+61 7 5598 4783",
    "sg:postcode":"4221",
    "sg:province":"QLD",
    "wof:name":"Casabean",
    "wof:placetype":"venue"
},
  "geometry": {"coordinates":[153.47085571299999,-28.1254673004],"type":"Point"}
}