{
  "type": "Feature",
  "properties": {
    "iso:country":"AU",
    "sg:address":"2/ 29 Wilmot St",
    "sg:city":"Burnie",
    "sg:classifiers":[
        {
            "category":"Shopping",
            "subcategory":"Optical Goods",
            "type":"Retail Goods"
        }
    ],
    "sg:phone":"+61 3 6431 3422",
    "sg:postcode":"7320",
    "sg:province":"TAS",
    "sg:tags":[
        "dispenser",
        "prescription"
    ],
    "wof:name":"Chris Dobson Optometrist",
    "wof:placetype":"venue"
},
  "geometry": {"coordinates":[145.906372,-41.051056],"type":"Point"}
}