{
  "type": "Feature",
  "properties": {
    "iso:country":"AU",
    "sg:address":"9 Huntington St",
    "sg:city":"Clontarf",
    "sg:classifiers":[
        {
            "category":"Industrial Area",
            "type":"Public Place"
        }
    ],
    "sg:phone":"+61 7 3284 6333",
    "sg:postcode":"4019",
    "sg:province":"QLD",
    "sg:tags":[
        "rural",
        "shed"
    ],
    "wof:name":"Tuff Built Garages",
    "wof:placetype":"venue"
},
  "geometry": {"coordinates":[153.081863403,-27.237865448],"type":"Point"}
}