{
  "type": "Feature",
  "properties": {
    "addr:full":"162 Hindmarsh Rd Victor Harbor SA 5211",
    "addr:housenumber":"162",
    "addr:postcode":"5211",
    "addr:street":"Hindmarsh Rd",
    "iso:country":"AU",
    "sg:address":"162 Hindmarsh Rd",
    "sg:city":"Victor Harbor",
    "sg:classifiers":[
        {
            "category":"Building & Trades",
            "subcategory":"Construction",
            "type":"Services"
        }
    ],
    "sg:phone":"+61 8 8552 7277",
    "sg:postcode":"5211",
    "sg:province":"SA",
    "sg:tags":[
        "contractor"
    ],
    "wof:name":"G.J. Gardner. Homes",
    "wof:placetype":"venue"
},
  "geometry": {"coordinates":[138.623214722,-35.5516014099],"type":"Point"}
}