{
  "type": "Feature",
  "properties": {
    "iso:country":"AU",
    "sg:address":"59 Virginius St",
    "sg:city":"Padstow",
    "sg:classifiers":[
        {
            "category":"Building & Trades",
            "subcategory":"Plumbing",
            "type":"Services"
        }
    ],
    "sg:phone":"+61 414 445 781",
    "sg:postcode":"2211",
    "sg:province":"NSW",
    "sg:tags":[
        "plumber",
        "gasfitters"
    ],
    "wof:name":"Slick Plumbing Pty Ltd",
    "wof:placetype":"venue"
},
  "geometry": {"coordinates":[151.02383399999999,-33.960293],"type":"Point"}
}