{
  "type": "Feature",
  "properties": {
    "iso:country":"AU",
    "sg:address":"Blackrock Creek Rd",
    "sg:city":"Pindi Pindi",
    "sg:classifiers":[
        {
            "category":"Farming",
            "subcategory":"Farm",
            "type":"Manufacturing & Wholesale Goods"
        }
    ],
    "sg:phone":"+61 427 889 979",
    "sg:postcode":"4798",
    "sg:province":"QLD",
    "sg:tags":[
        "farmer"
    ],
    "wof:name":"Reedman R K",
    "wof:placetype":"venue"
},
  "geometry": {"coordinates":[148.704223633,-20.8500099182],"type":"Point"}
}