{
  "type": "Feature",
  "properties": {
    "iso:country":"AU",
    "sg:address":"20 Manning Rd",
    "sg:city":"Double Bay",
    "sg:classifiers":[
        {
            "category":"Health Services",
            "subcategory":"Doctor",
            "type":"Services"
        }
    ],
    "sg:phone":"+61 2 9362 7400",
    "sg:postcode":"2028",
    "sg:province":"NSW",
    "sg:tags":[
        "medical",
        "practitioner"
    ],
    "wof:name":"Darryl J Hodgkinson Dr",
    "wof:placetype":"venue"
},
  "geometry": {"coordinates":[151.24316406200001,-33.8794555664],"type":"Point"}
}