{
  "type": "Feature",
  "properties": {
    "addr:full":"11 Elaroo Ave Salisbury North SA 5108",
    "addr:housenumber":"11",
    "addr:postcode":"5108",
    "addr:street":"Elaroo Ave",
    "iso:country":"AU",
    "sg:address":"11 Elaroo Ave",
    "sg:city":"Salisbury North",
    "sg:classifiers":[
        {
            "category":"Building & Trades",
            "subcategory":"Construction",
            "type":"Services"
        }
    ],
    "sg:phone":"+61 8 8281 2326",
    "sg:postcode":"5108",
    "sg:province":"SA",
    "sg:tags":[
        "pool",
        "swimming"
    ],
    "wof:name":"Welson Enterprises",
    "wof:placetype":"venue"
},
  "geometry": {"coordinates":[138.62179565400001,-34.7349586487],"type":"Point"}
}