{
  "type": "Feature",
  "properties": {
    "addr:full":"72- 86 Nathan Rd Dandenong South VIC 3175",
    "addr:housenumber":"86",
    "addr:postcode":"3175",
    "addr:street":"Nathan Rd",
    "iso:country":"AU",
    "sg:address":"72- 86 Nathan Rd",
    "sg:city":"Dandenong South",
    "sg:classifiers":[
        {
            "category":"Wholesale",
            "subcategory":"Metals & Minerals",
            "type":"Manufacturing & Wholesale Goods"
        }
    ],
    "sg:phone":"+61 3 8792 9600",
    "sg:postcode":"3175",
    "sg:province":"VIC",
    "sg:tags":[
        "steel",
        "merchant"
    ],
    "wof:name":"Vulcan Steel",
    "wof:placetype":"venue"
},
  "geometry": {"coordinates":[145.243286133,-38.0116462708],"type":"Point"}
}