{
  "type": "Feature",
  "properties": {
    "addr:full":"9a Hitech Pl Seaford VIC 3198",
    "addr:housenumber":"9a",
    "addr:postcode":"3198",
    "addr:street":"Hitech Pl",
    "iso:country":"AU",
    "sg:address":"9a Hitech Pl",
    "sg:city":"Seaford",
    "sg:classifiers":[
        {
            "category":"Manufacturing",
            "subcategory":"Glass & Minerals",
            "type":"Manufacturing & Wholesale Goods"
        }
    ],
    "sg:phone":"+61 3 9773 6433",
    "sg:postcode":"3198",
    "sg:province":"VIC",
    "sg:tags":[
        "repair",
        "fibreglass",
        "product"
    ],
    "wof:name":"K & E Fibreglass Industries",
    "wof:placetype":"venue"
},
  "geometry": {"coordinates":[145.13812255900001,-38.1166038513],"type":"Point"}
}