{
  "type": "Feature",
  "properties": {
    "addr:full":"90 The Avenue St Alexander Heights WA 6064",
    "addr:housenumber":"90",
    "addr:postcode":"6064",
    "addr:street":"The Avenue St",
    "iso:country":"AU",
    "sg:address":"90 The Avenue St",
    "sg:city":"Alexander Heights",
    "sg:classifiers":[
        {
            "category":"Building & Trades",
            "subcategory":"Construction",
            "type":"Services"
        }
    ],
    "sg:phone":"+61 8 9247 2238",
    "sg:postcode":"6064",
    "sg:province":"WA",
    "sg:tags":[
        "plasterboard",
        "plasterer",
        "fixer"
    ],
    "wof:name":"Marcello F & N",
    "wof:placetype":"venue"
},
  "geometry": {"coordinates":[115.867462158,-31.8235149384],"type":"Point"}
}