{
  "type": "Feature",
  "properties": {
    "iso:country":"AU",
    "sg:address":"7 Barnesdale Drv",
    "sg:city":"Vermont",
    "sg:classifiers":[
        {
            "category":"Professional",
            "subcategory":"Management & Consulting",
            "type":"Services"
        }
    ],
    "sg:phone":"+61 3 9872 5865",
    "sg:postcode":"3133",
    "sg:province":"VIC",
    "sg:tags":[
        "consultant"
    ],
    "wof:name":"Ian Mann & Associates",
    "wof:placetype":"venue"
},
  "geometry": {"coordinates":[145.19546508799999,-37.8406333923],"type":"Point"}
}