{
  "type": "Feature",
  "properties": {
    "addr:full":"Shp2a/ 57 Windsor Rd Rouse Hill NSW 2155",
    "addr:housenumber":"57",
    "addr:postcode":"2155",
    "addr:street":"Windsor Rd",
    "iso:country":"AU",
    "sg:address":"Shp2a/ 57 Windsor Rd",
    "sg:city":"Rouse Hill",
    "sg:classifiers":[
        {
            "category":"Shopping",
            "subcategory":"Clothing, Apparel, & Fashions",
            "type":"Retail Goods"
        }
    ],
    "sg:phone":"+61 2 9836 2775",
    "sg:postcode":"2155",
    "sg:province":"NSW",
    "sg:tags":[
        "boutique"
    ],
    "wof:name":"Sassee Pty Ltd",
    "wof:placetype":"venue"
},
  "geometry": {"coordinates":[150.91523742699999,-33.6814041138],"type":"Point"}
}