{
  "type": "Feature",
  "properties": {
    "iso:country":"AU",
    "sg:address":"U 3/ 33",
    "sg:city":"Ascog Tce Toowong",
    "sg:classifiers":[
        {
            "category":"Real Estate",
            "subcategory":"Architect",
            "type":"Services"
        }
    ],
    "sg:phone":"+61 7 3371 2200",
    "sg:postcode":"4066",
    "sg:province":"QLD",
    "wof:name":"Eric Hebron Architect Pty Ltd",
    "wof:placetype":"venue"
},
  "geometry": {"coordinates":[152.988723755,-27.4823131561],"type":"Point"}
}