{
  "type": "Feature",
  "properties": {
    "iso:country":"AU",
    "sg:address":"PO Box 169",
    "sg:city":"Stirling",
    "sg:classifiers":[
        {
            "category":"Wholesale",
            "subcategory":"Machinery & Supplies",
            "type":"Manufacturing & Wholesale Goods"
        }
    ],
    "sg:phone":"+61 8 8339 5111",
    "sg:postcode":"5152",
    "sg:province":"SA",
    "sg:tags":[
        "equipment",
        "hydraulic"
    ],
    "wof:name":"Fluid Clean (SA) Pty Ltd",
    "wof:placetype":"venue"
},
  "geometry": {"coordinates":[138.72253418,-35.0080490112],"type":"Point"}
}