{
  "type": "Feature",
  "properties": {
    "iso:country":"AU",
    "sg:address":"69 Memorial Ave St",
    "sg:city":"Ives",
    "sg:classifiers":[
        {
            "category":"Health Services",
            "subcategory":"Health Practitioner",
            "type":"Services"
        }
    ],
    "sg:phone":"+61 2 9144 1118",
    "sg:postcode":"2075",
    "sg:province":"NSW",
    "sg:tags":[
        "physiotherapist"
    ],
    "wof:name":"St Ives Physiotherapy & Sports Therapy Centre",
    "wof:placetype":"venue"
},
  "geometry": {"coordinates":[151.162353516,-33.7208976746],"type":"Point"}
}