{
  "type": "Feature",
  "properties": {
    "addr:full":"4/ 8 Lorraine St Dandenong VIC 3175",
    "addr:housenumber":"/ 8",
    "addr:postcode":"3175",
    "addr:street":"Lorraine St",
    "iso:country":"AU",
    "sg:address":"4/ 8 Lorraine St",
    "sg:city":"Dandenong",
    "sg:classifiers":[
        {
            "category":"Social Services",
            "subcategory":"Adult Care",
            "type":"Services"
        }
    ],
    "sg:phone":"+61 3 9706 8554",
    "sg:postcode":"3175",
    "sg:province":"VIC",
    "sg:tags":[
        "towing"
    ],
    "wof:name":"Local Trade Towing",
    "wof:placetype":"venue"
},
  "geometry": {"coordinates":[145.197921753,-37.9791297913],"type":"Point"}
}