{
  "type": "Feature",
  "properties": {
    "iso:country":"AU",
    "sg:address":"106 Mort St",
    "sg:city":"Toowoomba",
    "sg:classifiers":[
        {
            "category":"Professional",
            "subcategory":"Printing & Photocopies",
            "type":"Services"
        }
    ],
    "sg:phone":"+61 7 4659 9473",
    "sg:postcode":"4350",
    "sg:province":"QLD",
    "sg:tags":[
        "trophy"
    ],
    "wof:name":"Sandstream Etching",
    "wof:placetype":"venue"
},
  "geometry": {"coordinates":[151.950333,-27.552052],"type":"Point"}
}