{
  "type": "Feature",
  "properties": {
    "addr:full":"228 High St Cranbourne VIC 3977",
    "addr:housenumber":"228",
    "addr:postcode":"3977",
    "addr:street":"High St",
    "iso:country":"AU",
    "sg:address":"228 High St",
    "sg:city":"Cranbourne",
    "sg:classifiers":[
        {
            "category":"Retail",
            "subcategory":"Auto Repair",
            "type":"Services"
        }
    ],
    "sg:phone":"+61 3 5995 1844",
    "sg:postcode":"3977",
    "sg:province":"VIC",
    "sg:tags":[
        "repairer",
        "motor",
        "engineer"
    ],
    "wof:name":"UltraTune",
    "wof:placetype":"venue"
},
  "geometry": {"coordinates":[145.28334045400001,-38.0994682312],"type":"Point"}
}