{
  "type": "Feature",
  "properties": {
    "iso:country":"AU",
    "sg:address":"332 Crown St",
    "sg:city":"Wollongong",
    "sg:classifiers":[
        {
            "category":"Health Services",
            "subcategory":"Doctor",
            "type":"Services"
        }
    ],
    "sg:phone":"+61 1300 651 149",
    "sg:postcode":"2500",
    "sg:province":"NSW",
    "sg:tags":[
        "medical",
        "practitioner"
    ],
    "wof:name":"Ada Laser Cosmetic",
    "wof:placetype":"venue"
},
  "geometry": {"coordinates":[150.881149,-34.425949],"type":"Point"}
}