{
  "type": "Feature",
  "properties": {
    "iso:country":"AU",
    "sg:address":"First Floor 474 Centre Rd",
    "sg:city":"Bentleigh",
    "sg:classifiers":[
        {
            "category":"Professional",
            "subcategory":"Lawyer & Legal Services",
            "type":"Services"
        }
    ],
    "sg:phone":"+61 3 9563 9897",
    "sg:postcode":"3204",
    "sg:province":"VIC",
    "sg:tags":[
        "wills",
        "probate",
        "estate"
    ],
    "wof:name":"Anthony Naughton",
    "wof:placetype":"venue"
},
  "geometry": {"coordinates":[145.039719,-37.91869],"type":"Point"}
}