{
  "type": "Feature",
  "properties": {
    "addr:full":"Shop 2, 102 Moorabool St Geelong VIC 3220",
    "addr:housenumber":"shop 2",
    "addr:postcode":"102;3220",
    "addr:street":"Moorabool St",
    "iso:country":"AU",
    "sg:address":"Shop 2, 102 Moorabool St",
    "sg:city":"Geelong",
    "sg:classifiers":[
        {
            "category":"Travel",
            "subcategory":"Travel Agent",
            "type":"Entertainment"
        }
    ],
    "sg:phone":"+61 3 5222 5525",
    "sg:postcode":"3220",
    "sg:province":"VIC",
    "sg:tags":[
        "consultant"
    ],
    "wof:name":"Jetset",
    "wof:placetype":"venue"
},
  "geometry": {"coordinates":[144.36041299999999,-38.147606],"type":"Point"}
}