{
  "type": "Feature",
  "properties": {
    "addr:full":"8 Derby Rd Caulfield East VIC 3145",
    "addr:housenumber":"8",
    "addr:postcode":"3145",
    "addr:street":"Derby Rd",
    "iso:country":"AU",
    "sg:address":"8 Derby Rd",
    "sg:city":"Caulfield East",
    "sg:classifiers":[
        {
            "category":"Fast Food",
            "type":"Food & Drink"
        }
    ],
    "sg:phone":"+61 3 9571 2344",
    "sg:postcode":"3145",
    "sg:province":"VIC",
    "sg:tags":[
        "away",
        "take"
    ],
    "wof:name":"Pinky's Pizza",
    "wof:placetype":"venue"
},
  "geometry": {"coordinates":[145.041946411,-37.8762435913],"type":"Point"}
}