{
  "type": "Feature",
  "properties": {
    "iso:country":"AU",
    "sg:address":"RMB 311",
    "sg:city":"Stirling",
    "sg:classifiers":[
        {
            "category":"Arts & Performance",
            "subcategory":"Dance",
            "type":"Entertainment"
        }
    ],
    "sg:phone":"+61 439 896 986",
    "sg:postcode":"5152",
    "sg:province":"SA",
    "sg:tags":[
        "theatrical",
        "ballet",
        "tuition"
    ],
    "wof:name":"Glow Entertainment",
    "wof:placetype":"venue"
},
  "geometry": {"coordinates":[138.72253418,-35.0080490112],"type":"Point"}
}