{
  "type": "Feature",
  "properties": {
    "addr:full":"1147 Friday Hut Rd Binna Burra NSW 2479",
    "addr:housenumber":"1147",
    "addr:postcode":"2479",
    "addr:street":"Friday Hut Rd",
    "iso:country":"AU",
    "sg:address":"1147 Friday Hut Rd",
    "sg:city":"Binna Burra",
    "sg:classifiers":[
        {
            "category":"School Buses",
            "type":"Transportation"
        }
    ],
    "sg:phone":"+61 2 6687 1218",
    "sg:postcode":"2479",
    "sg:province":"NSW",
    "sg:tags":[
        "brick"
    ],
    "wof:name":"Parmenter R V & B M",
    "wof:placetype":"venue"
},
  "geometry": {"coordinates":[153.50575256400001,-28.7201461792],"type":"Point"}
}