{
  "type": "Feature",
  "properties": {
    "addr:full":"3 Airdrie Mews Greenvale VIC 3059",
    "addr:housenumber":"3",
    "addr:postcode":"3059",
    "addr:street":"Airdrie Mews",
    "iso:country":"AU",
    "sg:address":"3 Airdrie Mews",
    "sg:city":"Greenvale",
    "sg:classifiers":[
        {
            "category":"Building & Trades",
            "subcategory":"Construction",
            "type":"Services"
        }
    ],
    "sg:phone":"+61 3 9333 1290",
    "sg:postcode":"3059",
    "sg:province":"VIC",
    "sg:tags":[
        "installation",
        "air conditioning"
    ],
    "wof:name":"A AB Airconditioning & Heating",
    "wof:placetype":"venue"
},
  "geometry": {"coordinates":[144.88255310100001,-37.6451950073],"type":"Point"}
}