{
  "type": "Feature",
  "properties": {
    "addr:full":"230 Old Maitland Rd Hexham NSW 2322",
    "addr:housenumber":"230",
    "addr:postcode":"2322",
    "addr:street":"Old Maitland Rd",
    "iso:country":"AU",
    "sg:address":"230 Old Maitland Rd",
    "sg:city":"Hexham",
    "sg:classifiers":[
        {
            "category":"Wholesale",
            "subcategory":"Machinery & Supplies",
            "type":"Manufacturing & Wholesale Goods"
        }
    ],
    "sg:phone":"+61 2 4964 9605",
    "sg:postcode":"2322",
    "sg:province":"NSW",
    "sg:tags":[
        "equipment",
        "hydraulic"
    ],
    "wof:name":"Cone-Ring",
    "wof:placetype":"venue"
},
  "geometry": {"coordinates":[151.68870544399999,-32.8282012939],"type":"Point"}
}