{
  "type": "Feature",
  "properties": {
    "iso:country":"AU",
    "sg:address":"159 Nerang St",
    "sg:city":"Southport",
    "sg:classifiers":[
        {
            "category":"Health Services",
            "subcategory":"Doctor",
            "type":"Services"
        }
    ],
    "sg:phone":"+61 7 5531 1277",
    "sg:postcode":"4215",
    "sg:province":"QLD",
    "sg:tags":[
        "medical",
        "practitioner"
    ],
    "wof:name":"Sleep Disorders Clinic",
    "wof:placetype":"venue"
},
  "geometry": {"coordinates":[153.40452575699999,-27.9727478027],"type":"Point"}
}