{
  "type": "Feature",
  "properties": {
    "addr:full":"Suite 603 / Level 6, 6 Help St Chatswood NSW 2067",
    "addr:housenumber":"603 / level;6",
    "addr:postcode":"2067",
    "addr:street":"Help St",
    "iso:country":"AU",
    "sg:address":"Suite 603 / Level 6, 6 Help St",
    "sg:city":"Chatswood",
    "sg:classifiers":[
        {
            "category":"Shopping",
            "subcategory":"Computers & Home Electronics",
            "type":"Retail Goods"
        }
    ],
    "sg:phone":"+61 1800 008 525",
    "sg:postcode":"2067",
    "sg:province":"NSW",
    "sg:tags":[
        "small",
        "equipment",
        "business"
    ],
    "wof:name":"GAMEHEAD.COM.AU PTY LTD",
    "wof:placetype":"venue"
},
  "geometry": {"coordinates":[151.18167114299999,-33.7952804565],"type":"Point"}
}