{
  "type": "Feature",
  "properties": {
    "iso:country":"AU",
    "sg:address":"1 River Rd",
    "sg:city":"Ermington",
    "sg:classifiers":[
        {
            "category":"Restaurant",
            "type":"Food & Drink"
        }
    ],
    "sg:phone":"+61 1300 528 447",
    "sg:postcode":"2115",
    "sg:province":"NSW",
    "sg:tags":[
        "theatre"
    ],
    "wof:name":"Frightnight Comedy Theatre Restaurant",
    "wof:placetype":"venue"
},
  "geometry": {"coordinates":[151.05337524399999,-33.8144111633],"type":"Point"}
}