{
  "type": "Feature",
  "properties": {
    "addr:full":"Shop 189 , Bayside Shopping Centre, Frankston VIC 3199",
    "addr:housenumber":"189",
    "addr:postcode":"3199",
    "addr:street":"Bayside Shopping",
    "iso:country":"AU",
    "sg:address":"Shop 189",
    "sg:city":", Bayside Shopping Centre, Frankston",
    "sg:classifiers":[
        {
            "category":"Retail",
            "subcategory":"Repair Shop",
            "type":"Services"
        }
    ],
    "sg:phone":"+61 3 9783 5570",
    "sg:postcode":"3199",
    "sg:province":"VIC",
    "sg:tags":[
        "mending",
        "clothing",
        "alteration"
    ],
    "wof:name":"Looksmart Alterations",
    "wof:placetype":"venue"
},
  "geometry": {"coordinates":[145.135665894,-38.1624717712],"type":"Point"}
}