{
  "type": "Feature",
  "properties": {
    "iso:country":"AU",
    "sg:address":"Cairns Plastic Surgery 163 Lake St",
    "sg:city":"Cairns",
    "sg:classifiers":[
        {
            "category":"Health Services",
            "subcategory":"Doctor",
            "type":"Services"
        }
    ],
    "sg:phone":"+61 7 4031 5755",
    "sg:postcode":"4870",
    "sg:province":"QLD",
    "sg:tags":[
        "medical",
        "practitioner"
    ],
    "wof:name":"Hertess Isolde",
    "wof:placetype":"venue"
},
  "geometry": {"coordinates":[145.771560669,-16.9172420502],"type":"Point"}
}