{
  "type": "Feature",
  "properties": {
    "addr:full":"107 Shannon Ave Manifold Heights VIC 3218",
    "addr:housenumber":"107",
    "addr:postcode":"3218",
    "addr:street":"Shannon Ave",
    "iso:country":"AU",
    "sg:address":"107 Shannon Ave",
    "sg:city":"Manifold Heights",
    "sg:classifiers":[
        {
            "category":"Health Services",
            "subcategory":"Dentist",
            "type":"Services"
        }
    ],
    "sg:phone":"+61 3 5229 1802",
    "sg:postcode":"3218",
    "sg:province":"VIC",
    "sg:tags":[
        "dental",
        "prosthetist"
    ],
    "wof:name":"Dental Prosthetists Denture Clinic",
    "wof:placetype":"venue"
},
  "geometry": {"coordinates":[144.337036133,-38.1363563538],"type":"Point"}
}