{
  "type": "Feature",
  "properties": {
    "iso:country":"AU",
    "sg:address":"438 The Entrance Rd",
    "sg:city":"Erina Heights",
    "sg:classifiers":[
        {
            "category":"Health Services",
            "subcategory":"Chiropractor",
            "type":"Services"
        }
    ],
    "sg:phone":"+61 2 4367 6335",
    "sg:postcode":"2260",
    "sg:province":"NSW",
    "wof:name":"Bell John",
    "wof:placetype":"venue"
},
  "geometry": {"coordinates":[151.40690599999999,-33.425259],"type":"Point"}
}