{
  "type": "Feature",
  "properties": {
    "addr:full":"341 Fison Ave East Eagle Farm QLD 4009",
    "addr:housenumber":"341",
    "addr:postcode":"4009",
    "addr:street":"Fison Ave East",
    "iso:country":"AU",
    "sg:address":"341 Fison Ave East",
    "sg:city":"Eagle Farm",
    "sg:classifiers":[
        {
            "category":"Real Estate",
            "subcategory":"Real Estate Agent",
            "type":"Services"
        }
    ],
    "sg:phone":"+61 7 3630 1244",
    "sg:postcode":"4009",
    "sg:province":"QLD",
    "sg:tags":[
        "export"
    ],
    "wof:name":"Cargoclear International",
    "wof:placetype":"venue"
},
  "geometry": {"coordinates":[153.10064697300001,-27.434337616],"type":"Point"}
}