{
  "type": "Feature",
  "properties": {
    "iso:country":"AU",
    "sg:address":"1 Shore St",
    "sg:city":"Cleveland",
    "sg:classifiers":[
        {
            "category":"Health Services",
            "subcategory":"Doctor",
            "type":"Services"
        }
    ],
    "sg:phone":"+61 7 3286 1122",
    "sg:postcode":"4163",
    "sg:province":"QLD",
    "sg:tags":[
        "medical",
        "practitioner"
    ],
    "wof:name":"Hunter Russell",
    "wof:placetype":"venue"
},
  "geometry": {"coordinates":[153.269454956,-27.5265884399],"type":"Point"}
}