{
  "type": "Feature",
  "properties": {
    "addr:full":"37 Eddie Rd Minchinbury NSW 2770",
    "addr:housenumber":"37",
    "addr:postcode":"2770",
    "addr:street":"Eddie Rd",
    "iso:country":"AU",
    "sg:address":"37 Eddie Rd",
    "sg:city":"Minchinbury",
    "sg:classifiers":[
        {
            "category":"Manufacturing",
            "subcategory":"Motor Vehicles & Parts",
            "type":"Manufacturing & Wholesale Goods"
        }
    ],
    "sg:phone":"+61 2 9675 3444",
    "sg:postcode":"2770",
    "sg:province":"NSW",
    "sg:tags":[
        "engine",
        "equipment",
        "diesel"
    ],
    "sg:website":"http://www.eipdiesel.com.au",
    "wof:name":"EIP Diesel Pty Ltd",
    "wof:placetype":"venue"
},
  "geometry": {"coordinates":[150.81695556599999,-33.7846565247],"type":"Point"}
}