{
  "type": "Feature",
  "properties": {
    "iso:country":"AU",
    "sg:address":"66 Roberts Rd",
    "sg:city":"Osborne Park",
    "sg:classifiers":[
        {
            "category":"Shopping",
            "subcategory":"Computers & Home Electronics",
            "type":"Retail Goods"
        }
    ],
    "sg:phone":"+61 8 9201 0363",
    "sg:postcode":"6017",
    "sg:province":"WA",
    "sg:tags":[
        "equipment",
        "part",
        "electronic"
    ],
    "wof:name":"MechTronics R & D",
    "wof:placetype":"venue"
},
  "geometry": {"coordinates":[115.823928833,-31.9079647064],"type":"Point"}
}