{
  "type": "Feature",
  "properties": {
    "addr:full":"79 Stevenson St Kew VIC 3101",
    "addr:housenumber":"79",
    "addr:postcode":"3101",
    "addr:street":"Stevenson St",
    "iso:country":"AU",
    "sg:address":"79 Stevenson St",
    "sg:city":"Kew",
    "sg:classifiers":[
        {
            "category":"Travel",
            "subcategory":"Hostel",
            "type":"Entertainment"
        }
    ],
    "sg:phone":"+61 3 9853 3570",
    "sg:postcode":"3101",
    "sg:province":"VIC",
    "sg:tags":[
        "home"
    ],
    "wof:name":"Highgrove Studley Park",
    "wof:placetype":"venue"
},
  "geometry": {"coordinates":[145.017456055,-37.8092041016],"type":"Point"}
}