{
  "type": "Feature",
  "properties": {
    "addr:full":"246 Robert Rd Centenary Park QLD 4869",
    "addr:housenumber":"246",
    "addr:postcode":"4869",
    "addr:street":"Robert Rd Centenary",
    "iso:country":"AU",
    "sg:address":"246 Robert Rd",
    "sg:city":"Centenary Park",
    "sg:classifiers":[
        {
            "category":"Personal",
            "subcategory":"Beauty Salon",
            "type":"Services"
        }
    ],
    "sg:phone":"+61 7 4045 5194",
    "sg:postcode":"4869",
    "sg:province":"QLD",
    "wof:name":"Skin Deep Therapy",
    "wof:placetype":"venue"
},
  "geometry": {"coordinates":[145.729125977,-17.0122394562],"type":"Point"}
}