{
  "type": "Feature",
  "properties": {
    "addr:full":"906 Main St Eltham VIC 3095",
    "addr:housenumber":"906",
    "addr:postcode":"3095",
    "addr:street":"Main St",
    "iso:country":"AU",
    "sg:address":"906 Main St",
    "sg:city":"Eltham",
    "sg:classifiers":[
        {
            "category":"Shopping",
            "subcategory":"Clothing, Apparel, & Fashions",
            "type":"Retail Goods"
        }
    ],
    "sg:phone":"+61 3 9431 1132",
    "sg:postcode":"3095",
    "sg:province":"VIC",
    "sg:tags":[
        "accessory"
    ],
    "wof:name":"Calypso Fashion",
    "wof:placetype":"venue"
},
  "geometry": {"coordinates":[145.14848327600001,-37.7146530151],"type":"Point"}
}