{
  "type": "Feature",
  "properties": {
    "addr:full":"32 Browning St Wangaratta VIC 3677",
    "addr:housenumber":"32",
    "addr:postcode":"3677",
    "addr:street":"Browning St",
    "iso:country":"AU",
    "sg:address":"32 Browning St",
    "sg:city":"Wangaratta",
    "sg:classifiers":[
        {
            "category":"Utilities",
            "subcategory":"Refuse",
            "type":"Services"
        }
    ],
    "sg:phone":"+61 3 5722 4545",
    "sg:postcode":"3677",
    "sg:province":"VIC",
    "sg:tags":[
        "boiler"
    ],
    "wof:name":"R.B.C.S.",
    "wof:placetype":"venue"
},
  "geometry": {"coordinates":[146.288406372,-36.3709373474],"type":"Point"}
}