{
  "type": "Feature",
  "properties": {
    "addr:full":"2 Birru Rd Gosford North NSW 2250",
    "addr:housenumber":"2",
    "addr:postcode":"2250",
    "addr:street":"Birru Rd",
    "iso:country":"AU",
    "sg:address":"2 Birru Rd",
    "sg:city":"Gosford North",
    "sg:classifiers":[
        {
            "category":"Retail",
            "subcategory":"Auto Repair",
            "type":"Services"
        }
    ],
    "sg:phone":"+61 2 4324 3053",
    "sg:postcode":"2250",
    "sg:province":"NSW",
    "sg:tags":[
        "engine",
        "reconditioning"
    ],
    "wof:name":"Coast Headmaster",
    "wof:placetype":"venue"
},
  "geometry": {"coordinates":[151.34359741200001,-33.4115180969],"type":"Point"}
}