{
  "type": "Feature",
  "properties": {
    "addr:full":"14- 16 Settlement Rd Belmont VIC 3216",
    "addr:housenumber":"16",
    "addr:postcode":"3216",
    "addr:street":"Settlement Rd",
    "iso:country":"AU",
    "sg:address":"14- 16 Settlement Rd",
    "sg:city":"Belmont",
    "sg:classifiers":[
        {
            "category":"Travel",
            "subcategory":"Hotels & Motels",
            "type":"Entertainment"
        }
    ],
    "sg:phone":"+61 3 5241 9441",
    "sg:postcode":"3216",
    "sg:province":"VIC",
    "wof:name":"Rose Garden Motel",
    "wof:placetype":"venue"
},
  "geometry": {"coordinates":[144.35125732399999,-38.176990509],"type":"Point"}
}