{
  "type": "Feature",
  "properties": {
    "addr:full":"83 Cahills Rd Mandurang VIC 3551",
    "addr:housenumber":"83",
    "addr:postcode":"3551",
    "addr:street":"Cahills Rd",
    "iso:country":"AU",
    "sg:address":"83 Cahills Rd",
    "sg:city":"Mandurang",
    "sg:classifiers":[
        {
            "category":"Farming",
            "subcategory":"Vineyard",
            "type":"Manufacturing & Wholesale Goods"
        }
    ],
    "sg:phone":"+61 3 5439 3635",
    "sg:postcode":"3551",
    "sg:province":"VIC",
    "sg:tags":[
        "winery"
    ],
    "wof:name":"Lynnevale Estate",
    "wof:placetype":"venue"
},
  "geometry": {"coordinates":[144.29408264200001,-36.829624176],"type":"Point"}
}