{
  "type": "Feature",
  "properties": {
    "iso:country":"AU",
    "sg:address":"44 Porter St",
    "sg:city":"Prahran",
    "sg:classifiers":[
        {
            "category":"Shopping",
            "subcategory":"Stationery & Office Supplies",
            "type":"Retail Goods"
        }
    ],
    "sg:phone":"+61 3 9510 5155",
    "sg:postcode":"3181",
    "sg:province":"VIC",
    "sg:tags":[
        "packaging",
        "material"
    ],
    "wof:name":"Magnet Packaging",
    "wof:placetype":"venue"
},
  "geometry": {"coordinates":[144.99046325699999,-37.8479766846],"type":"Point"}
}