{
  "type": "Feature",
  "properties": {
    "addr:full":"3 Oakwood St Parafield Gardens SA 5107",
    "addr:housenumber":"3",
    "addr:postcode":"5107",
    "addr:street":"Oakwood St",
    "iso:country":"AU",
    "sg:address":"3 Oakwood St",
    "sg:city":"Parafield Gardens",
    "sg:classifiers":[
        {
            "category":"Mining & Drilling",
            "type":"Manufacturing & Wholesale Goods"
        }
    ],
    "sg:phone":"+61 414 612 199",
    "sg:postcode":"5107",
    "sg:province":"SA",
    "sg:tags":[
        "concrete",
        "breaking",
        "grinding",
        "sawing"
    ],
    "wof:name":"Supercore",
    "wof:placetype":"venue"
},
  "geometry": {"coordinates":[138.627120972,-34.7841911316],"type":"Point"}
}