{
  "type": "Feature",
  "properties": {
    "addr:full":"151 Kingaroy St Kingaroy QLD 4610",
    "addr:housenumber":"151",
    "addr:postcode":"4610",
    "addr:street":"Kingaroy St",
    "iso:country":"AU",
    "sg:address":"151 Kingaroy St",
    "sg:city":"Kingaroy",
    "sg:classifiers":[
        {
            "category":"Shopping",
            "subcategory":"Discount & Variety Stores",
            "type":"Retail Goods"
        }
    ],
    "sg:phone":"+61 7 4162 2344",
    "sg:postcode":"4610",
    "sg:province":"QLD",
    "sg:tags":[
        "shop",
        "adult"
    ],
    "wof:name":"Don&#039;t Be Shy Adult Shop",
    "wof:placetype":"venue"
},
  "geometry": {"coordinates":[151.83903503400001,-26.541595459],"type":"Point"}
}