{
  "type": "Feature",
  "properties": {
    "addr:full":"116a Carlton Rd Dandenong VIC 3175",
    "addr:housenumber":"116a",
    "addr:postcode":"3175",
    "addr:street":"Carlton Rd",
    "iso:country":"AU",
    "sg:address":"116a Carlton Rd",
    "sg:city":"Dandenong",
    "sg:classifiers":[
        {
            "category":"Food & Beverages",
            "subcategory":"Groceries & Convenience Stores",
            "type":"Retail Goods"
        }
    ],
    "sg:phone":"+61 3 9791 2640",
    "sg:postcode":"3175",
    "sg:province":"VIC",
    "wof:name":"Abouchaka M",
    "wof:placetype":"venue"
},
  "geometry": {"coordinates":[145.22213745100001,-37.9611549377],"type":"Point"}
}