{
  "type": "Feature",
  "properties": {
    "iso:country":"AU",
    "sg:address":"56 Moira St",
    "sg:city":"Adamstown",
    "sg:classifiers":[
        {
            "category":"Building & Trades",
            "subcategory":"Landscaping Services",
            "type":"Services"
        }
    ],
    "sg:phone":"+61 2 4965 5595",
    "sg:postcode":"2289",
    "sg:province":"NSW",
    "sg:tags":[
        "designer",
        "landscape",
        "contractor"
    ],
    "wof:name":"Temple Stone Landscaping",
    "wof:placetype":"venue"
},
  "geometry": {"coordinates":[151.71946716299999,-32.9399986267],"type":"Point"}
}