{
  "type": "Feature",
  "properties": {
    "addr:full":"79 Invermay Rd Invermay TAS 7248",
    "addr:housenumber":"79",
    "addr:postcode":"7248",
    "addr:street":"Invermay Rd",
    "iso:country":"AU",
    "sg:address":"79 Invermay Rd",
    "sg:city":"Invermay",
    "sg:classifiers":[
        {
            "category":"Banks & Credit Unions",
            "subcategory":"Investment Brokerage",
            "type":"Services"
        }
    ],
    "sg:phone":"+61 1300 551 322",
    "sg:postcode":"7248",
    "sg:province":"TAS",
    "sg:tags":[
        "bedspread",
        "quilt"
    ],
    "wof:name":"The Quilt & Pillow Factory",
    "wof:placetype":"venue"
},
  "geometry": {"coordinates":[147.13499450699999,-41.4191436768],"type":"Point"}
}