{
  "type": "Feature",
  "properties": {
    "iso:country":"AU",
    "sg:address":"105 Hastings River Drv",
    "sg:city":"Port Macquarie",
    "sg:classifiers":[
        {
            "category":"Travel",
            "subcategory":"Hotels & Motels",
            "type":"Entertainment"
        }
    ],
    "sg:phone":"+61 2 6583 5222",
    "sg:postcode":"2444",
    "sg:province":"NSW",
    "wof:name":"Golden Chain Port O'Call Motel",
    "wof:placetype":"venue"
},
  "geometry": {"coordinates":[152.888077,-31.431108],"type":"Point"}
}