{
  "type": "Feature",
  "properties": {
    "addr:full":"3/43- 51 College St Gladesville NSW 2111",
    "addr:housenumber":"/;51",
    "addr:postcode":"2111",
    "addr:street":"43;College St",
    "iso:country":"AU",
    "sg:address":"3/43- 51 College St",
    "sg:city":"Gladesville",
    "sg:classifiers":[
        {
            "category":"Parking",
            "type":"Transportation"
        }
    ],
    "sg:phone":"+61 1800 628 730",
    "sg:postcode":"2111",
    "sg:province":"NSW",
    "sg:tags":[
        "equipment",
        "system"
    ],
    "wof:name":"Leda Security Products",
    "wof:placetype":"venue"
},
  "geometry": {"coordinates":[151.12124633799999,-33.8198814392],"type":"Point"}
}