{
  "type": "Feature",
  "properties": {
    "addr:full":"6 Charles St South Perth WA 6151",
    "addr:housenumber":"6",
    "addr:postcode":"6151",
    "addr:street":"Charles St South",
    "iso:country":"AU",
    "sg:address":"6 Charles St",
    "sg:city":"South Perth",
    "sg:classifiers":[
        {
            "category":"Banks & Credit Unions",
            "subcategory":"Financial Services",
            "type":"Services"
        }
    ],
    "sg:phone":"+61 8 9367 2088",
    "sg:postcode":"6151",
    "sg:province":"WA",
    "sg:tags":[
        "planning"
    ],
    "wof:name":"Phil Clements",
    "wof:placetype":"venue"
},
  "geometry": {"coordinates":[115.84925800000001,-31.977194],"type":"Point"}
}