{
  "type": "Feature",
  "properties": {
    "addr:full":"Taragala St Cowra NSW 2794",
    "addr:postcode":"2794",
    "addr:street":"St",
    "iso:country":"AU",
    "sg:address":"Taragala St",
    "sg:city":"Cowra",
    "sg:classifiers":[
        {
            "category":"Food & Beverages",
            "subcategory":"Fruits & Vegetables",
            "type":"Retail Goods"
        }
    ],
    "sg:phone":"+61 2 6342 1531",
    "sg:postcode":"2794",
    "sg:province":"NSW",
    "sg:tags":[
        "greengrocer",
        "fruiterer"
    ],
    "wof:name":"Riverside Markets",
    "wof:placetype":"venue"
},
  "geometry": {"coordinates":[148.688323975,-33.8364181519],"type":"Point"}
}