{
  "type": "Feature",
  "properties": {
    "addr:full":"Unit 2, 4 Beaumont Rd Mt Kuring-gai NSW 2080",
    "addr:housenumber":"4",
    "addr:postcode":"2080",
    "addr:street":"Beaumont Rd",
    "iso:country":"AU",
    "sg:address":"Unit 2, 4 Beaumont Rd",
    "sg:city":"Mt Kuring-gai",
    "sg:classifiers":[
        {
            "category":"Organizations",
            "subcategory":"Community Association",
            "type":"Services"
        }
    ],
    "sg:phone":"+61 2 9457 8059",
    "sg:postcode":"2080",
    "sg:province":"NSW",
    "sg:tags":[
        "soldering"
    ],
    "wof:name":"Mektronics (NSW) Pty Ltd",
    "wof:placetype":"venue"
},
  "geometry": {"coordinates":[151.133178711,-33.6436386108],"type":"Point"}
}