{
  "type": "Feature",
  "properties": {
    "addr:full":"3 Spit Rd Mosman NSW 2088",
    "addr:housenumber":"3",
    "addr:postcode":"2088",
    "addr:street":"Spit Rd",
    "iso:country":"AU",
    "sg:address":"3 Spit Rd",
    "sg:city":"Mosman",
    "sg:classifiers":[
        {
            "category":"Social Services",
            "subcategory":"Retirement Home",
            "type":"Services"
        }
    ],
    "sg:phone":"+61 2 9960 5666",
    "sg:postcode":"2088",
    "sg:province":"NSW",
    "sg:tags":[
        "decoration",
        "supplier",
        "contractor"
    ],
    "wof:name":"Born To Party",
    "wof:placetype":"venue"
},
  "geometry": {"coordinates":[151.24124145499999,-33.8244361877],"type":"Point"}
}