{
  "type": "Feature",
  "properties": {
    "addr:full":"120 Erindale Rd Balcatta WA 6021",
    "addr:housenumber":"120",
    "addr:postcode":"6021",
    "addr:street":"Erindale Rd",
    "iso:country":"AU",
    "sg:address":"120 Erindale Rd",
    "sg:city":"Balcatta",
    "sg:classifiers":[
        {
            "category":"Retail",
            "subcategory":"Auto Repair",
            "type":"Services"
        }
    ],
    "sg:phone":"+61 8 9344 2666",
    "sg:postcode":"6021",
    "sg:province":"WA",
    "sg:tags":[
        "repairer",
        "motor",
        "engineer"
    ],
    "wof:name":"Midas",
    "wof:placetype":"venue"
},
  "geometry": {"coordinates":[115.80648803699999,-31.8663597107],"type":"Point"}
}