{
  "type": "Feature",
  "properties": {
    "addr:full":"6 Marty Ave Salamander Bay NSW 2317",
    "addr:housenumber":"6",
    "addr:postcode":"2317",
    "addr:street":"Marty Ave",
    "iso:country":"AU",
    "sg:address":"6 Marty Ave",
    "sg:city":"Salamander Bay",
    "sg:classifiers":[
        {
            "category":"Banks & Credit Unions",
            "subcategory":"Financial Services",
            "type":"Services"
        }
    ],
    "sg:phone":"+61 2 4984 6477",
    "sg:postcode":"2317",
    "sg:province":"NSW",
    "sg:tags":[
        "planning"
    ],
    "wof:name":"Tristen Cosgrove",
    "wof:placetype":"venue"
},
  "geometry": {"coordinates":[152.070526,-32.714531],"type":"Point"}
}