{
  "type": "Feature",
  "properties": {
    "addr:full":"24 Stennett Rd Ingleburn NSW 2565",
    "addr:housenumber":"24",
    "addr:postcode":"2565",
    "addr:street":"Stennett Rd",
    "iso:country":"AU",
    "sg:address":"24 Stennett Rd",
    "sg:city":"Ingleburn",
    "sg:classifiers":[
        {
            "category":"Building & Trades",
            "subcategory":"Construction",
            "type":"Services"
        }
    ],
    "sg:phone":"+61 2 9618 1392",
    "sg:postcode":"2565",
    "sg:province":"NSW",
    "sg:tags":[
        "joiner",
        "carpenter"
    ],
    "wof:name":"Brian Cummins Carpentry & Maintenance Service Pty Ltd",
    "wof:placetype":"venue"
},
  "geometry": {"coordinates":[150.852493286,-34.0033035278],"type":"Point"}
}