{
  "type": "Feature",
  "properties": {
    "iso:country":"AU",
    "sg:address":"6C / 31 -37 Pacific Pde",
    "sg:city":"Dee Why",
    "sg:classifiers":[
        {
            "category":"Communications",
            "type":"Services"
        }
    ],
    "sg:phone":"+61 2 9981 2607",
    "sg:postcode":"2099",
    "sg:province":"NSW",
    "sg:tags":[
        "translation"
    ],
    "wof:name":"Anne Franco",
    "wof:placetype":"venue"
},
  "geometry": {"coordinates":[151.286712647,-33.754825592],"type":"Point"}
}