{
  "type": "Feature",
  "properties": {
    "iso:country":"AU",
    "sg:address":"182 Mt Dandenong Rd",
    "sg:city":"Ringwood",
    "sg:classifiers":[
        {
            "category":"Shopping",
            "subcategory":"Antiques",
            "type":"Retail Goods"
        }
    ],
    "sg:phone":"+61 3 9879 1686",
    "sg:postcode":"3134",
    "sg:province":"VIC",
    "wof:name":"Ringwood Antique Market",
    "wof:placetype":"venue"
},
  "geometry": {"coordinates":[145.25932312,-37.8016471863],"type":"Point"}
}