{
  "type": "Feature",
  "properties": {
    "iso:country":"AU",
    "sg:address":"37 Truman Ave",
    "sg:city":"Cromer Heights",
    "sg:classifiers":[
        {
            "category":"Education",
            "subcategory":"Special Training",
            "type":"Public Place"
        }
    ],
    "sg:phone":"+61 2 9981 7794",
    "sg:postcode":"2099",
    "sg:province":"NSW",
    "sg:tags":[
        "school",
        "art"
    ],
    "wof:name":"Emma Jane Hutchings Studio & Gallery",
    "wof:placetype":"venue"
},
  "geometry": {"coordinates":[151.26445007300001,-33.734703064],"type":"Point"}
}