{
  "type": "Feature",
  "properties": {
    "iso:country":"AU",
    "sg:address":"Unit 8, 103 Campbell St",
    "sg:city":"Belmont",
    "sg:classifiers":[
        {
            "category":"Wholesale",
            "subcategory":"Durable Goods & Equipment",
            "type":"Manufacturing & Wholesale Goods"
        }
    ],
    "sg:phone":"+61 8 9277 4355",
    "sg:postcode":"6104",
    "sg:province":"WA",
    "sg:tags":[
        "wholesaler",
        "mfrs",
        "lubrication"
    ],
    "wof:name":"National Lubrication & Hydraulic Systems",
    "wof:placetype":"venue"
},
  "geometry": {"coordinates":[115.92497253400001,-31.9564094543],"type":"Point"}
}