{
  "type": "Feature",
  "properties": {
    "addr:full":"2 264 Main Rd Toukley NSW 2263",
    "addr:housenumber":"2 264",
    "addr:postcode":"2263",
    "addr:street":"Main Rd",
    "iso:country":"AU",
    "sg:address":"2 264 Main Rd",
    "sg:city":"Toukley",
    "sg:classifiers":[
        {
            "category":"Shopping",
            "subcategory":"Party Supplies",
            "type":"Retail Goods"
        }
    ],
    "sg:phone":"+61 2 4396 1122",
    "sg:postcode":"2263",
    "sg:province":"NSW",
    "sg:tags":[
        "selling",
        "plan"
    ],
    "wof:name":"Aileen May's Party Service",
    "wof:placetype":"venue"
},
  "geometry": {"coordinates":[151.543442,-33.264256],"type":"Point"}
}