{
  "type": "Feature",
  "properties": {
    "addr:full":"20 Benetook Ave Koorlong VIC 3501",
    "addr:housenumber":"20",
    "addr:postcode":"3501",
    "addr:street":"Benetook Ave",
    "iso:country":"AU",
    "sg:address":"20 Benetook Ave",
    "sg:city":"Koorlong",
    "sg:classifiers":[
        {
            "category":"Professional",
            "type":"Services"
        }
    ],
    "sg:phone":"+61 3 5025 7171",
    "sg:postcode":"3501",
    "sg:province":"VIC",
    "sg:tags":[
        "transport"
    ],
    "wof:name":"Gregg B L & K J",
    "wof:placetype":"venue"
},
  "geometry": {"coordinates":[142.10418701200001,-34.2578887939],"type":"Point"}
}