{
  "type": "Feature",
  "properties": {
    "iso:country":"AU",
    "sg:address":"313 Gilles St",
    "sg:city":"Adelaide",
    "sg:classifiers":[
        {
            "category":"Home & Garden",
            "subcategory":"Building Materials",
            "type":"Retail Goods"
        }
    ],
    "sg:phone":"+61 419 867 415",
    "sg:postcode":"5000",
    "sg:province":"SA",
    "sg:tags":[
        "lawn",
        "cutting",
        "maintenance"
    ],
    "wof:name":"Swann Phil",
    "wof:placetype":"venue"
},
  "geometry": {"coordinates":[138.61210632300001,-34.9338607788],"type":"Point"}
}