{
  "type": "Feature",
  "properties": {
    "addr:full":"47 Amherst St Ulverstone TAS 7315",
    "addr:housenumber":"47",
    "addr:postcode":"7315",
    "addr:street":"Amherst St",
    "iso:country":"AU",
    "sg:address":"47 Amherst St",
    "sg:city":"Ulverstone",
    "sg:classifiers":[
        {
            "category":"Building & Trades",
            "subcategory":"Plumbing",
            "type":"Services"
        }
    ],
    "sg:phone":"+61 3 6425 7528",
    "sg:postcode":"7315",
    "sg:province":"TAS",
    "sg:tags":[
        "plumber",
        "gasfitters"
    ],
    "wof:name":"Rowlands Lynton Plumbing",
    "wof:placetype":"venue"
},
  "geometry": {"coordinates":[146.16163635300001,-41.1535797119],"type":"Point"}
}