{
  "type": "Feature",
  "properties": {
    "iso:country":"AU",
    "sg:address":"725 Albany Creek Rd",
    "sg:city":"Albany Creek",
    "sg:classifiers":[
        {
            "category":"Health Services",
            "subcategory":"Dentist",
            "type":"Services"
        }
    ],
    "sg:phone":"+61 7 3264 5698",
    "sg:postcode":"4035",
    "sg:province":"QLD",
    "wof:name":"David Stephenson Dr",
    "wof:placetype":"venue"
},
  "geometry": {"coordinates":[152.965836,-27.344938],"type":"Point"}
}