{
  "type": "Feature",
  "properties": {
    "addr:full":"Market Street Community Centre 5 Market Street Lismore NSW 2480",
    "addr:housenumber":"5",
    "addr:postcode":"2480",
    "addr:street":"Market;Market Street",
    "iso:country":"AU",
    "sg:address":"Market Street Community Centre 5",
    "sg:city":"Market Street Lismore",
    "sg:classifiers":[
        {
            "category":"Social Services",
            "subcategory":"Child Care",
            "type":"Services"
        }
    ],
    "sg:phone":"+61 2 6622 8810",
    "sg:postcode":"2480",
    "sg:province":"NSW",
    "wof:name":"Market Street After School Care",
    "wof:placetype":"venue"
},
  "geometry": {"coordinates":[153.27377319300001,-28.8111629486],"type":"Point"}
}