{
  "type": "Feature",
  "properties": {
    "iso:country":"AU",
    "sg:address":"Centenary Rd",
    "sg:city":"Slacks Creek",
    "sg:classifiers":[
        {
            "category":"Manufacturing",
            "subcategory":"Building Materials",
            "type":"Manufacturing & Wholesale Goods"
        }
    ],
    "sg:phone":"+61 7 3808 1818",
    "sg:postcode":"4127",
    "sg:province":"QLD",
    "sg:tags":[
        "concrete",
        "product"
    ],
    "wof:name":"Icon Industries Pty Ltd",
    "wof:placetype":"venue"
},
  "geometry": {"coordinates":[153.15252685600001,-27.6490821838],"type":"Point"}
}