{
  "type": "Feature",
  "properties": {
    "addr:full":"208 Anzac Ave Redcliffe QLD 4020",
    "addr:housenumber":"208",
    "addr:postcode":"4020",
    "addr:street":"Anzac Ave",
    "iso:country":"AU",
    "sg:address":"208 Anzac Ave",
    "sg:city":"Redcliffe",
    "sg:classifiers":[
        {
            "category":"Autos & Motor Vehicles",
            "subcategory":"Automobile Sales",
            "type":"Retail Goods"
        }
    ],
    "sg:phone":"+61 7 3283 1000",
    "sg:postcode":"4020",
    "sg:province":"QLD",
    "sg:tags":[
        "car",
        "used"
    ],
    "wof:name":"JB Cars",
    "wof:placetype":"venue"
},
  "geometry": {"coordinates":[153.093445,-27.227526],"type":"Point"}
}