{
  "type": "Feature",
  "properties": {
    "addr:full":"43 North Valley Rd Highton VIC 3216",
    "addr:housenumber":"43",
    "addr:postcode":"3216",
    "addr:street":"North Valley Rd",
    "iso:country":"AU",
    "sg:address":"43 North Valley Rd",
    "sg:city":"Highton",
    "sg:classifiers":[
        {
            "category":"Personal",
            "subcategory":"Beauty Salon",
            "type":"Services"
        }
    ],
    "sg:phone":"+61 3 5244 2144",
    "sg:postcode":"3216",
    "sg:province":"VIC",
    "sg:tags":[
        "hairdresser"
    ],
    "wof:name":"Rapport Hairdressing",
    "wof:placetype":"venue"
},
  "geometry": {"coordinates":[144.31877136200001,-38.1721725464],"type":"Point"}
}