{
  "type": "Feature",
  "properties": {
    "addr:full":"Cnr Clifton Drv & Gisborne Rd Bacchus Marsh VIC 3340",
    "addr:postcode":"3340",
    "addr:street":"Cnr Clifton Drv & Gisborne Rd",
    "iso:country":"AU",
    "sg:address":"Cnr Clifton Drv & Gisborne Rd",
    "sg:city":"Bacchus Marsh",
    "sg:classifiers":[
        {
            "category":"Health Services",
            "subcategory":"Health Practitioner",
            "type":"Services"
        }
    ],
    "sg:phone":"+61 3 5367 4130",
    "sg:postcode":"3340",
    "sg:province":"VIC",
    "sg:tags":[
        "physiotherapist"
    ],
    "wof:name":"Bacchus Marsh Physiotherapy & Hydrotherapy Clinic",
    "wof:placetype":"venue"
},
  "geometry": {"coordinates":[144.43554700000001,-37.674751],"type":"Point"}
}