{
  "type": "Feature",
  "properties": {
    "addr:full":"1 Golding St Port Pirie SA 5540",
    "addr:housenumber":"1",
    "addr:postcode":"5540",
    "addr:street":"Golding St",
    "iso:country":"AU",
    "sg:address":"1 Golding St",
    "sg:city":"Port Pirie",
    "sg:classifiers":[
        {
            "category":"Wholesale",
            "subcategory":"Painting Supplies",
            "type":"Manufacturing & Wholesale Goods"
        }
    ],
    "sg:phone":"+61 8 8633 2266",
    "sg:postcode":"5540",
    "sg:province":"SA",
    "sg:tags":[
        "product",
        "cleaning"
    ],
    "wof:name":"Keller Agencies",
    "wof:placetype":"venue"
},
  "geometry": {"coordinates":[137.993942261,-33.2015991211],"type":"Point"}
}