{
  "type": "Feature",
  "properties": {
    "iso:country":"AU",
    "sg:address":"60 Milner Rd",
    "sg:city":"High Wycombe",
    "sg:classifiers":[
        {
            "category":"Farming",
            "subcategory":"Nursery",
            "type":"Manufacturing & Wholesale Goods"
        }
    ],
    "sg:phone":"+61 8 9454 6933",
    "sg:postcode":"6057",
    "sg:province":"WA",
    "wof:name":"Tony & Sons Nurseries & Orchid Farm",
    "wof:placetype":"venue"
},
  "geometry": {"coordinates":[115.99961853000001,-31.9544143677],"type":"Point"}
}