{
  "type": "Feature",
  "properties": {
    "addr:full":"Shp2/ 29 Station St Subiaco WA 6008",
    "addr:housenumber":"29",
    "addr:postcode":"6008",
    "addr:street":"Station St",
    "iso:country":"AU",
    "sg:address":"Shp2/ 29 Station St",
    "sg:city":"Subiaco",
    "sg:classifiers":[
        {
            "category":"Fast Food",
            "type":"Food & Drink"
        }
    ],
    "sg:phone":"+61 8 9380 6040",
    "sg:postcode":"6008",
    "sg:province":"WA",
    "sg:tags":[
        "away",
        "take"
    ],
    "wof:name":"Mediterranean Pizzas & Kebabs",
    "wof:placetype":"venue"
},
  "geometry": {"coordinates":[115.82357788100001,-31.94389534],"type":"Point"}
}