{
  "type": "Feature",
  "properties": {
    "addr:full":"18 Dudley St Coogee NSW 2034",
    "addr:housenumber":"18",
    "addr:postcode":"2034",
    "addr:street":"Dudley St",
    "iso:country":"AU",
    "sg:address":"18 Dudley St",
    "sg:city":"Coogee",
    "sg:classifiers":[
        {
            "category":"Food & Beverages",
            "subcategory":"Specialty",
            "type":"Retail Goods"
        }
    ],
    "sg:phone":"+61 2 9665 5560",
    "sg:postcode":"2034",
    "sg:province":"NSW",
    "sg:tags":[
        "product",
        "health"
    ],
    "wof:name":"Bill Redmond",
    "wof:placetype":"venue"
},
  "geometry": {"coordinates":[151.24778747600001,-33.9219741821],"type":"Point"}
}