{
  "type": "Feature",
  "properties": {
    "addr:full":"2/5 Knox St (Entrance Goldman Lane) Double Bay NSW 2028",
    "addr:housenumber":"/ 5",
    "addr:postcode":"2028",
    "addr:street":"Knox St;Goldman Lane",
    "iso:country":"AU",
    "sg:address":"2/5 Knox St (Entrance Goldman Lane)",
    "sg:city":"Double Bay",
    "sg:classifiers":[
        {
            "category":"Health Services",
            "subcategory":"Health Practitioner",
            "type":"Services"
        }
    ],
    "sg:phone":"+61 2 9326 1061",
    "sg:postcode":"2028",
    "sg:province":"NSW",
    "sg:tags":[
        "physiotherapist"
    ],
    "wof:name":"Double Bay Physiotherapy Centre",
    "wof:placetype":"venue"
},
  "geometry": {"coordinates":[151.24296569800001,-33.8770294189],"type":"Point"}
}