{
  "type": "Feature",
  "properties": {
    "iso:country":"AU",
    "sg:address":"215 Mount Dandenong Tourist Rd",
    "sg:city":"Ferny Creek",
    "sg:classifiers":[
        {
            "category":"Building & Trades",
            "subcategory":"Plumbing",
            "type":"Services"
        }
    ],
    "sg:phone":"+61 3 9755 1569",
    "sg:postcode":"3786",
    "sg:province":"VIC",
    "sg:tags":[
        "plumber",
        "gasfitters"
    ],
    "wof:name":"Paco's Plumbing",
    "wof:placetype":"venue"
},
  "geometry": {"coordinates":[145.34045399999999,-37.880127],"type":"Point"}
}