{
  "type": "Feature",
  "properties": {
    "addr:full":"213 Pomeroy Rd Lesmurdie WA 6076",
    "addr:housenumber":"213",
    "addr:postcode":"6076",
    "addr:street":"Pomeroy Rd",
    "iso:country":"AU",
    "sg:address":"213 Pomeroy Rd",
    "sg:city":"Lesmurdie",
    "sg:classifiers":[
        {
            "category":"Manufacturing",
            "subcategory":"Pottery",
            "type":"Manufacturing & Wholesale Goods"
        }
    ],
    "sg:phone":"+61 8 9291 6244",
    "sg:postcode":"6076",
    "sg:province":"WA",
    "wof:name":"Kim Lyons Pottery",
    "wof:placetype":"venue"
},
  "geometry": {"coordinates":[116.062202454,-32.0091743469],"type":"Point"}
}