{
  "type": "Feature",
  "properties": {
    "addr:full":"26 Gordon St Coffs Harbour NSW 2450",
    "addr:housenumber":"26",
    "addr:postcode":"2450",
    "addr:street":"Gordon St",
    "iso:country":"AU",
    "sg:address":"26 Gordon St",
    "sg:city":"Coffs Harbour",
    "sg:classifiers":[
        {
            "category":"Professional",
            "subcategory":"Accounting & Tax Preparation",
            "type":"Services"
        }
    ],
    "sg:phone":"+61 2 6652 2999",
    "sg:postcode":"2450",
    "sg:province":"NSW",
    "sg:tags":[
        "accountant",
        "auditor"
    ],
    "wof:name":"Caldwell T",
    "wof:placetype":"venue"
},
  "geometry": {"coordinates":[153.117355,-30.297131],"type":"Point"}
}