{
  "type": "Feature",
  "properties": {
    "addr:full":"5 De Feu St North Melbourne VIC 3051",
    "addr:housenumber":"5",
    "addr:postcode":"3051",
    "addr:street":"De Feu St",
    "iso:country":"AU",
    "sg:address":"5 De Feu St",
    "sg:city":"North Melbourne",
    "sg:classifiers":[
        {
            "category":"Personal",
            "subcategory":"Massage",
            "type":"Services"
        }
    ],
    "sg:phone":"+61 403 777 075",
    "sg:postcode":"3051",
    "sg:province":"VIC",
    "sg:tags":[
        "therapy"
    ],
    "wof:name":"Body Logic",
    "wof:placetype":"venue"
},
  "geometry": {"coordinates":[144.94302368199999,-37.8017578125],"type":"Point"}
}