{
  "type": "Feature",
  "properties": {
    "addr:full":"ShpT20/ 8 Galbraith Park Drv Cannonvale QLD 4802",
    "addr:housenumber":"8",
    "addr:postcode":"4802",
    "addr:street":"Galbraith Park Drv",
    "iso:country":"AU",
    "sg:address":"ShpT20/ 8 Galbraith Park Drv",
    "sg:city":"Cannonvale",
    "sg:classifiers":[
        {
            "category":"Shopping",
            "subcategory":"Jewelry",
            "type":"Retail Goods"
        }
    ],
    "sg:phone":"+61 7 4946 1911",
    "sg:postcode":"4802",
    "sg:province":"QLD",
    "sg:tags":[
        "jeweller"
    ],
    "wof:name":"Kleins Whitsundays",
    "wof:placetype":"venue"
},
  "geometry": {"coordinates":[148.674072266,-20.2913703918],"type":"Point"}
}