{
  "type": "Feature",
  "properties": {
    "iso:country":"AU",
    "sg:address":"10 Pindari St",
    "sg:city":"Keiraville",
    "sg:classifiers":[
        {
            "category":"Professional",
            "subcategory":"Computer Services",
            "type":"Services"
        }
    ],
    "sg:phone":"+61 2 4226 9557",
    "sg:postcode":"2500",
    "sg:province":"NSW",
    "sg:tags":[
        "consultant",
        "system"
    ],
    "wof:name":"Robert Green",
    "wof:placetype":"venue"
},
  "geometry": {"coordinates":[150.866409,-34.414688],"type":"Point"}
}