{
  "type": "Feature",
  "properties": {
    "addr:full":"PO Box 81 Dongara WA 6525",
    "addr:postcode":"6525",
    "iso:country":"AU",
    "sg:address":"PO Box 81",
    "sg:city":"Dongara",
    "sg:classifiers":[
        {
            "category":"Home & Garden",
            "subcategory":"Building Materials",
            "type":"Retail Goods"
        }
    ],
    "sg:phone":"+61 8 9927 1577",
    "sg:postcode":"6525",
    "sg:province":"WA",
    "sg:tags":[
        "retaining",
        "wall"
    ],
    "wof:name":"Keboda Stone Construction",
    "wof:placetype":"venue"
},
  "geometry": {"coordinates":[114.937973023,-29.2507896423],"type":"Point"}
}