{
  "type": "Feature",
  "properties": {
    "addr:full":"12-14 Glen Osmond Rd Parkside SA 5063",
    "addr:housenumber":"12-14",
    "addr:postcode":"5063",
    "addr:street":"Glen Osmond Rd",
    "iso:country":"AU",
    "sg:address":"12-14 Glen Osmond Rd",
    "sg:city":"Parkside",
    "sg:classifiers":[
        {
            "category":"Health Services",
            "subcategory":"Health Practitioner",
            "type":"Services"
        }
    ],
    "sg:phone":"+61 8 8357 7663",
    "sg:postcode":"5063",
    "sg:province":"SA",
    "sg:tags":[
        "naturopath"
    ],
    "wof:name":"Naturally Health & Body Care",
    "wof:placetype":"venue"
},
  "geometry": {"coordinates":[138.616577148,-34.9412307739],"type":"Point"}
}