{
  "type": "Feature",
  "properties": {
    "addr:full":"110 Upper Level, Gay&#039;s Arcade, Twin St Adelaide SA 5000",
    "addr:housenumber":"110",
    "addr:postcode":"5000",
    "addr:street":"Upper Level Gay &;039 S Arcade Twin St",
    "iso:country":"AU",
    "sg:address":"110 Upper Level, Gay&#039;s Arcade, Twin St",
    "sg:city":"Adelaide",
    "sg:classifiers":[
        {
            "category":"Professional",
            "subcategory":"Computer Services",
            "type":"Services"
        }
    ],
    "sg:phone":"+61 8 8359 3110",
    "sg:postcode":"5000",
    "sg:province":"SA",
    "sg:tags":[
        "package",
        "software"
    ],
    "wof:name":"Innovation Science Pty Ltd",
    "wof:placetype":"venue"
},
  "geometry": {"coordinates":[138.60446167000001,-34.9235572815],"type":"Point"}
}