{
  "type": "Feature",
  "properties": {
    "addr:full":"19 Marsh St Mackay QLD 4740",
    "addr:housenumber":"19",
    "addr:postcode":"4740",
    "addr:street":"Marsh St",
    "iso:country":"AU",
    "sg:address":"19 Marsh St",
    "sg:city":"Mackay",
    "sg:classifiers":[
        {
            "category":"Social Services",
            "subcategory":"Child Care",
            "type":"Services"
        }
    ],
    "sg:phone":"+61 7 4957 3040",
    "sg:postcode":"4740",
    "sg:province":"QLD",
    "sg:tags":[
        "baby",
        "sitter"
    ],
    "wof:name":"Dial-A-Maid Babysitting Service",
    "wof:placetype":"venue"
},
  "geometry": {"coordinates":[149.19726600000001,-21.152328],"type":"Point"}
}