{
  "type": "Feature",
  "properties": {
    "iso:country":"AU",
    "sg:address":"12 Church Rd",
    "sg:city":"Ingleburn",
    "sg:classifiers":[
        {
            "category":"Home & Garden",
            "subcategory":"Building Materials",
            "type":"Retail Goods"
        }
    ],
    "sg:phone":"+61 2 9605 8332",
    "sg:postcode":"2565",
    "sg:province":"NSW",
    "sg:tags":[
        "retaining",
        "wall"
    ],
    "wof:name":"Crawford A & G",
    "wof:placetype":"venue"
},
  "geometry": {"coordinates":[150.84341430699999,-33.9824638367],"type":"Point"}
}