{
  "type": "Feature",
  "properties": {
    "iso:country":"AU",
    "sg:address":"55 Bank St",
    "sg:city":"Port Fairy",
    "sg:classifiers":[
        {
            "category":"Cafe",
            "type":"Food & Drink"
        }
    ],
    "sg:phone":"+61 3 5568 3000",
    "sg:postcode":"3284",
    "sg:province":"VIC",
    "wof:name":"Jules On Bank",
    "wof:placetype":"venue"
},
  "geometry": {"coordinates":[142.23277282699999,-38.3831634521],"type":"Point"}
}