{
  "type": "Feature",
  "properties": {
    "iso:country":"AU",
    "sg:address":"31 Forbes St",
    "sg:city":"Devonport",
    "sg:classifiers":[
        {
            "category":"Autos & Motor Vehicles",
            "subcategory":"Auto Supplies",
            "type":"Retail Goods"
        }
    ],
    "sg:phone":"+61 3 6424 8574",
    "sg:postcode":"7310",
    "sg:province":"TAS",
    "sg:tags":[
        "electric"
    ],
    "wof:name":"Transmission Australia",
    "wof:placetype":"venue"
},
  "geometry": {"coordinates":[146.35552978499999,-41.1840858459],"type":"Point"}
}