{
  "type": "Feature",
  "properties": {
    "addr:full":"23 Wollong St Gosford NSW 2250",
    "addr:housenumber":"23",
    "addr:postcode":"2250",
    "addr:street":"Wollong St",
    "iso:country":"AU",
    "sg:address":"23 Wollong St",
    "sg:city":"Gosford",
    "sg:classifiers":[
        {
            "category":"Building & Trades",
            "subcategory":"Landscaping Services",
            "type":"Services"
        }
    ],
    "sg:phone":"+61 2 4328 4077",
    "sg:postcode":"2250",
    "sg:province":"NSW",
    "sg:tags":[
        "stump",
        "tree",
        "felling",
        "removal"
    ],
    "wof:name":"Coastline Tree Services",
    "wof:placetype":"venue"
},
  "geometry": {"coordinates":[151.34230041500001,-33.4105453491],"type":"Point"}
}