{
  "type": "Feature",
  "properties": {
    "iso:country":"AU",
    "sg:address":"1b Gannawarra St",
    "sg:city":"Currimundi",
    "sg:classifiers":[
        {
            "category":"Professional",
            "subcategory":"Engineering",
            "type":"Services"
        }
    ],
    "sg:phone":"+61 7 5437 7522",
    "sg:postcode":"4551",
    "sg:province":"QLD",
    "sg:tags":[
        "consulting",
        "engineer"
    ],
    "wof:name":"Gilbert & Sutherland Pty Ltd",
    "wof:placetype":"venue"
},
  "geometry": {"coordinates":[153.12663269000001,-26.766740799],"type":"Point"}
}