{
  "type": "Feature",
  "properties": {
    "iso:country":"AU",
    "sg:address":"31 Queen Elizabeth Drv",
    "sg:city":"Eatons Hill",
    "sg:classifiers":[
        {
            "category":"Professional",
            "subcategory":"Accounting & Tax Preparation",
            "type":"Services"
        }
    ],
    "sg:phone":"+61 7 3882 3840",
    "sg:postcode":"4037",
    "sg:province":"QLD",
    "sg:tags":[
        "jukebox"
    ],
    "wof:name":"PartyJuke",
    "wof:placetype":"venue"
},
  "geometry": {"coordinates":[152.952026,-27.335981],"type":"Point"}
}