{
  "type": "Feature",
  "properties": {
    "addr:full":"49 Cook St Flinders VIC 3929",
    "addr:housenumber":"49",
    "addr:postcode":"3929",
    "addr:street":"Cook St",
    "iso:country":"AU",
    "sg:address":"49 Cook St",
    "sg:city":"Flinders",
    "sg:classifiers":[
        {
            "category":"Cafe",
            "type":"Food & Drink"
        }
    ],
    "sg:phone":"+61 3 5989 0700",
    "sg:postcode":"3929",
    "sg:province":"VIC",
    "wof:name":"Flinders Village Cafe",
    "wof:placetype":"venue"
},
  "geometry": {"coordinates":[145.016723633,-38.4738922119],"type":"Point"}
}