{
  "type": "Feature",
  "properties": {
    "addr:full":"Cnr Leeton & Mildura Sts Kingston ACT 2604",
    "addr:postcode":"2604",
    "addr:street":"Cnr;Sts",
    "iso:country":"AU",
    "sg:address":"Cnr Leeton & Mildura Sts",
    "sg:city":"Kingston",
    "sg:classifiers":[
        {
            "category":"Health Services",
            "subcategory":"Doctor",
            "type":"Services"
        }
    ],
    "sg:phone":"+61 2 6271 6331",
    "sg:postcode":"2604",
    "sg:province":"ACT",
    "sg:tags":[
        "occupational",
        "safety"
    ],
    "wof:name":"Hydatid Control Campaign (South East N.S.W. & A.C.T.)",
    "wof:placetype":"venue"
},
  "geometry": {"coordinates":[149.151947022,-35.3211517334],"type":"Point"}
}