{
  "type": "Feature",
  "properties": {
    "addr:full":"Lot 26 Millstream Rd Jimboomba QLD 4280",
    "addr:postcode":"4280",
    "addr:street":"Millstream Rd",
    "iso:country":"AU",
    "sg:address":"Lot 26 Millstream Rd",
    "sg:city":"Jimboomba",
    "sg:classifiers":[
        {
            "category":"Home & Garden",
            "subcategory":"Building Materials",
            "type":"Retail Goods"
        }
    ],
    "sg:phone":"+61 7 5547 7699",
    "sg:postcode":"4280",
    "sg:province":"QLD",
    "sg:tags":[
        "fencing"
    ],
    "wof:name":"Cobble Patch",
    "wof:placetype":"venue"
},
  "geometry": {"coordinates":[153.01942399999999,-27.85844],"type":"Point"}
}