{
  "type": "Feature",
  "properties": {
    "addr:full":"5th Floor 251- 257 Hay St East Perth WA 6004",
    "addr:housenumber":"251 257",
    "addr:postcode":"6004",
    "addr:street":"Hay St East",
    "iso:country":"AU",
    "sg:address":"5th Floor 251- 257 Hay St",
    "sg:city":"East Perth",
    "sg:classifiers":[
        {
            "category":"Banks & Credit Unions",
            "subcategory":"Investment Brokerage",
            "type":"Services"
        }
    ],
    "sg:phone":"+61 8 9221 4166",
    "sg:postcode":"6004",
    "sg:province":"WA",
    "sg:tags":[
        "debt",
        "collection"
    ],
    "wof:name":"Recievables Management Limited",
    "wof:placetype":"venue"
},
  "geometry": {"coordinates":[115.870910645,-31.9582252502],"type":"Point"}
}