{
  "type": "Feature",
  "properties": {
    "iso:country":"AU",
    "sg:address":"56 Newcombe St",
    "sg:city":"Portarlington",
    "sg:classifiers":[
        {
            "category":"Fast Food",
            "type":"Food & Drink"
        }
    ],
    "sg:phone":"+61 3 5259 2986",
    "sg:postcode":"3223",
    "sg:province":"VIC",
    "sg:tags":[
        "away",
        "take"
    ],
    "wof:name":"Boatman's Fish & Chips",
    "wof:placetype":"venue"
},
  "geometry": {"coordinates":[144.651962,-38.114986],"type":"Point"}
}