{
  "type": "Feature",
  "properties": {
    "addr:full":"218 Urana St Wagga Wagga NSW 2650",
    "addr:housenumber":"218",
    "addr:postcode":"2650",
    "addr:street":"Urana St",
    "iso:country":"AU",
    "sg:address":"218 Urana St",
    "sg:city":"Wagga Wagga",
    "sg:classifiers":[
        {
            "category":"Food & Beverages",
            "subcategory":"Bakery",
            "type":"Retail Goods"
        }
    ],
    "sg:phone":"+61 2 6925 6322",
    "sg:postcode":"2650",
    "sg:province":"NSW",
    "sg:tags":[
        "baker"
    ],
    "wof:name":"Tip Top Bakery",
    "wof:placetype":"venue"
},
  "geometry": {"coordinates":[147.341873169,-35.1249542236],"type":"Point"}
}