{
  "type": "Feature",
  "properties": {
    "iso:country":"AU",
    "sg:address":"45 Murrumbidgee Crs",
    "sg:city":"Bateau Bay",
    "sg:classifiers":[
        {
            "category":"Retail",
            "subcategory":"Repair Shop",
            "type":"Services"
        }
    ],
    "sg:phone":"+61 2 4333 3827",
    "sg:postcode":"2261",
    "sg:province":"NSW",
    "sg:tags":[
        "upholsterer"
    ],
    "wof:name":"Cascade Upholstery",
    "wof:placetype":"venue"
},
  "geometry": {"coordinates":[151.478317,-33.38269],"type":"Point"}
}