{
  "type": "Feature",
  "properties": {
    "iso:country":"AU",
    "sg:address":"Suite 702 Lvl 7 The Trust Bldng 155 King",
    "sg:city":"Sydney",
    "sg:classifiers":[
        {
            "category":"Real Estate",
            "subcategory":"Developer",
            "type":"Services"
        }
    ],
    "sg:phone":"+61 2 9235 0461",
    "sg:postcode":"2000",
    "sg:province":"NSW",
    "sg:tags":[
        "development"
    ],
    "wof:name":"Uxbridge Property Group Pty Ltd",
    "wof:placetype":"venue"
},
  "geometry": {"coordinates":[151.20982360799999,-33.8691902161],"type":"Point"}
}