{
  "type": "Feature",
  "properties": {
    "iso:country":"AU",
    "sg:address":"17 Neutron Pl",
    "sg:city":"Rowville",
    "sg:classifiers":[
        {
            "category":"Building & Trades",
            "subcategory":"Construction",
            "type":"Services"
        }
    ],
    "sg:phone":"+61 3 9764 1977",
    "sg:postcode":"3178",
    "sg:province":"VIC",
    "sg:tags":[
        "spouting",
        "guttering"
    ],
    "wof:name":"Dura-tex Roofing Services",
    "wof:placetype":"venue"
},
  "geometry": {"coordinates":[145.24673461899999,-37.9058380127],"type":"Point"}
}