{
  "type": "Feature",
  "properties": {
    "iso:country":"AU",
    "sg:address":"64 Hungerford Drv",
    "sg:city":"Glenwood",
    "sg:classifiers":[
        {
            "category":"Wholesale",
            "subcategory":"Home Furnishings",
            "type":"Manufacturing & Wholesale Goods"
        }
    ],
    "sg:phone":"+61 2 9629 8298",
    "sg:postcode":"2768",
    "sg:province":"NSW",
    "sg:tags":[
        "wholesaler",
        "mfrs",
        "manchester"
    ],
    "wof:name":"Beddingtown",
    "wof:placetype":"venue"
},
  "geometry": {"coordinates":[150.93714900000001,-33.737514],"type":"Point"}
}