{
  "type": "Feature",
  "properties": {
    "addr:full":"3/ 32 Bay St Tweed Heads NSW 2485",
    "addr:housenumber":"/ 32",
    "addr:postcode":"2485",
    "addr:street":"Bay St",
    "iso:country":"AU",
    "sg:address":"3/ 32 Bay St",
    "sg:city":"Tweed Heads",
    "sg:classifiers":[
        {
            "category":"Health Services",
            "subcategory":"Health Practitioner",
            "type":"Services"
        }
    ],
    "sg:phone":"+61 7 5536 2343",
    "sg:postcode":"2485",
    "sg:province":"NSW",
    "sg:tags":[
        "osteopath"
    ],
    "wof:name":"Terence C. Vardy Dr",
    "wof:placetype":"venue"
},
  "geometry": {"coordinates":[153.54290771500001,-28.1711616516],"type":"Point"}
}