{
  "type": "Feature",
  "properties": {
    "addr:full":"Factory 4 6 Woodbine Crt Wantirna South VIC 3152",
    "addr:housenumber":"6",
    "addr:postcode":"3152",
    "addr:street":"Woodbine Crt",
    "iso:country":"AU",
    "sg:address":"Factory 4 6 Woodbine Crt",
    "sg:city":"Wantirna South",
    "sg:classifiers":[
        {
            "category":"Manufacturing",
            "subcategory":"Motor Vehicles & Parts",
            "type":"Manufacturing & Wholesale Goods"
        }
    ],
    "sg:phone":"+61 3 9801 7067",
    "sg:postcode":"3152",
    "sg:province":"VIC",
    "sg:tags":[
        "wholesaler",
        "cycle",
        "mfrs",
        "accessory"
    ],
    "wof:name":"Planet Disc Pty Ltd",
    "wof:placetype":"venue"
},
  "geometry": {"coordinates":[145.25097656200001,-37.8703460693],"type":"Point"}
}