{
  "type": "Feature",
  "properties": {
    "addr:full":"6 Charles St Richmond VIC 3121",
    "addr:housenumber":"6",
    "addr:postcode":"3121",
    "addr:street":"Charles St",
    "iso:country":"AU",
    "sg:address":"6 Charles St",
    "sg:city":"Richmond",
    "sg:classifiers":[
        {
            "category":"Manufacturing",
            "subcategory":"Tools & Machinery",
            "type":"Manufacturing & Wholesale Goods"
        }
    ],
    "sg:phone":"+61 3 9421 0040",
    "sg:postcode":"3121",
    "sg:province":"VIC",
    "sg:tags":[
        "earth",
        "excavating",
        "moving",
        "equipment"
    ],
    "wof:name":"Muck-truck",
    "wof:placetype":"venue"
},
  "geometry": {"coordinates":[145.00062560999999,-37.8232078552],"type":"Point"}
}