{
  "type": "Feature",
  "properties": {
    "addr:full":"4 Ponto Crt Endeavour Hills VIC 3802",
    "addr:housenumber":"4",
    "addr:postcode":"3802",
    "addr:street":"Ponto Crt",
    "iso:country":"AU",
    "sg:address":"4 Ponto Crt",
    "sg:city":"Endeavour Hills",
    "sg:classifiers":[
        {
            "category":"Home & Garden",
            "subcategory":"Building Materials",
            "type":"Retail Goods"
        }
    ],
    "sg:phone":"+61 419 135 190",
    "sg:postcode":"3802",
    "sg:province":"VIC",
    "sg:tags":[
        "merchant",
        "glass",
        "glazier"
    ],
    "wof:name":"M & D Glass",
    "wof:placetype":"venue"
},
  "geometry": {"coordinates":[145.26272582999999,-37.9865531921],"type":"Point"}
}