{
  "type": "Feature",
  "properties": {
    "addr:full":"Unit J, 61 Waratah St Kirrawee NSW 2232",
    "addr:housenumber":"61",
    "addr:postcode":"2232",
    "addr:street":"Waratah St",
    "iso:country":"AU",
    "sg:address":"Unit J, 61 Waratah St",
    "sg:city":"Kirrawee",
    "sg:classifiers":[
        {
            "category":"Professional",
            "type":"Services"
        }
    ],
    "sg:phone":"+61 2 9542 3996",
    "sg:postcode":"2232",
    "sg:province":"NSW",
    "sg:tags":[
        "shop",
        "fitting"
    ],
    "wof:name":"Fourway Projects",
    "wof:placetype":"venue"
},
  "geometry": {"coordinates":[151.07427978499999,-34.0284385681],"type":"Point"}
}