{
  "type": "Feature",
  "properties": {
    "addr:full":"3/173 Arden St Coogee NSW 2034",
    "addr:housenumber":"/ 173",
    "addr:postcode":"2034",
    "addr:street":"Arden St",
    "iso:country":"AU",
    "sg:address":"3/173 Arden St",
    "sg:city":"Coogee",
    "sg:classifiers":[
        {
            "category":"Personal",
            "subcategory":"Beauty Salon",
            "type":"Services"
        }
    ],
    "sg:phone":"+61 2 9664 9044",
    "sg:postcode":"2034",
    "sg:province":"NSW",
    "sg:tags":[
        "hairdresser"
    ],
    "wof:name":"Tide Hairdressing",
    "wof:placetype":"venue"
},
  "geometry": {"coordinates":[151.25738525400001,-33.9186401367],"type":"Point"}
}