{
  "type": "Feature",
  "properties": {
    "addr:full":"82 Helen St North Sefton NSW 2162",
    "addr:housenumber":"82",
    "addr:postcode":"2162",
    "addr:street":"Helen St North",
    "iso:country":"AU",
    "sg:address":"82 Helen St",
    "sg:city":"North Sefton",
    "sg:classifiers":[
        {
            "category":"Building & Trades",
            "subcategory":"Construction",
            "type":"Services"
        }
    ],
    "sg:phone":"+61 2 9644 9599",
    "sg:postcode":"2162",
    "sg:province":"NSW",
    "sg:tags":[
        "management"
    ],
    "wof:name":"Mullaly Constructions",
    "wof:placetype":"venue"
},
  "geometry": {"coordinates":[151.01258850100001,-33.8802108765],"type":"Point"}
}