{
  "type": "Feature",
  "properties": {
    "addr:full":"91a Willoughby Rd Crows Nest NSW 2065",
    "addr:housenumber":"91a",
    "addr:postcode":"2065",
    "addr:street":"Willoughby Rd",
    "iso:country":"AU",
    "sg:address":"91a Willoughby Rd",
    "sg:city":"Crows Nest",
    "sg:classifiers":[
        {
            "category":"Professional",
            "subcategory":"Printing & Photocopies",
            "type":"Services"
        }
    ],
    "sg:phone":"+61 2 9966 9744",
    "sg:postcode":"2065",
    "sg:province":"NSW",
    "sg:tags":[
        "publishing",
        "desktop"
    ],
    "wof:name":"Big Colour Imaging",
    "wof:placetype":"venue"
},
  "geometry": {"coordinates":[151.20106506400001,-33.8241729736],"type":"Point"}
}