{
  "type": "Feature",
  "properties": {
    "addr:full":"27 Clyde St Box Hill VIC 3128",
    "addr:housenumber":"27",
    "addr:postcode":"3128",
    "addr:street":"Clyde St",
    "iso:country":"AU",
    "sg:address":"27 Clyde St",
    "sg:city":"Box Hill",
    "sg:classifiers":[
        {
            "category":"Shopping",
            "subcategory":"Antiques",
            "type":"Retail Goods"
        }
    ],
    "sg:phone":"+61 409 986 021",
    "sg:postcode":"3128",
    "sg:province":"VIC",
    "sg:tags":[
        "restoration",
        "reproduction"
    ],
    "wof:name":"Independent Valuations & Antique Restoration Services",
    "wof:placetype":"venue"
},
  "geometry": {"coordinates":[145.08985900900001,-37.8161506653],"type":"Point"}
}