{
  "type": "Feature",
  "properties": {
    "iso:country":"AU",
    "sg:address":"72 Darby St",
    "sg:city":"Cooks Hill",
    "sg:classifiers":[
        {
            "category":"Shopping",
            "subcategory":"Music",
            "type":"Retail Goods"
        }
    ],
    "sg:phone":"+61 2 4929 5079",
    "sg:postcode":"2300",
    "sg:province":"NSW",
    "sg:tags":[
        "store"
    ],
    "wof:name":"Cooks Hill Books & Records",
    "wof:placetype":"venue"
},
  "geometry": {"coordinates":[151.768661,-32.93457],"type":"Point"}
}