{
  "type": "Feature",
  "properties": {
    "addr:full":"238 Rouse St Tenterfield NSW 2372",
    "addr:housenumber":"238",
    "addr:postcode":"2372",
    "addr:street":"Rouse St",
    "iso:country":"AU",
    "sg:address":"238 Rouse St",
    "sg:city":"Tenterfield",
    "sg:classifiers":[
        {
            "category":"Health Services",
            "subcategory":"Optometrist",
            "type":"Services"
        }
    ],
    "sg:phone":"+61 2 6736 2536",
    "sg:postcode":"2372",
    "sg:province":"NSW",
    "wof:name":"Lamas & Brown Optometrists",
    "wof:placetype":"venue"
},
  "geometry": {"coordinates":[152.01875305199999,-29.0547065735],"type":"Point"}
}