{
  "type": "Feature",
  "properties": {
    "addr:full":"23 George St Warilla NSW 2528",
    "addr:housenumber":"23",
    "addr:postcode":"2528",
    "addr:street":"George St",
    "iso:country":"AU",
    "sg:address":"23 George St",
    "sg:city":"Warilla",
    "sg:classifiers":[
        {
            "category":"Health Services",
            "subcategory":"Dentist",
            "type":"Services"
        }
    ],
    "sg:phone":"+61 2 4296 7230",
    "sg:postcode":"2528",
    "sg:province":"NSW",
    "wof:name":"Saeed Dr Hana",
    "wof:placetype":"venue"
},
  "geometry": {"coordinates":[150.86227417000001,-34.5525245667],"type":"Point"}
}