{
  "type": "Feature",
  "properties": {
    "addr:full":"Carillon City Arcade Shop 64, Hay St Perth WA 6000",
    "addr:housenumber":"64",
    "addr:postcode":"6000",
    "addr:street":"Hay St",
    "iso:country":"AU",
    "sg:address":"Carillon City Arcade Shop 64, Hay St",
    "sg:city":"Perth",
    "sg:classifiers":[
        {
            "category":"Personal",
            "subcategory":"Skin Care",
            "type":"Services"
        }
    ],
    "sg:phone":"+61 8 9481 8085",
    "sg:postcode":"6000",
    "sg:province":"WA",
    "sg:tags":[
        "treatment"
    ],
    "wof:name":"Skin Revision Anti-Aging & Body Clinic",
    "wof:placetype":"venue"
},
  "geometry": {"coordinates":[115.853050232,-31.9523906708],"type":"Point"}
}