{
  "type": "Feature",
  "properties": {
    "addr:full":"12 Eskay Rd Oakleigh South VIC 3167",
    "addr:housenumber":"12",
    "addr:postcode":"3167",
    "addr:street":"Eskay Rd",
    "iso:country":"AU",
    "sg:address":"12 Eskay Rd",
    "sg:city":"Oakleigh South",
    "sg:classifiers":[
        {
            "category":"Professional",
            "subcategory":"Printing & Photocopies",
            "type":"Services"
        }
    ],
    "sg:phone":"+61 3 9570 8052",
    "sg:postcode":"3167",
    "sg:province":"VIC",
    "sg:tags":[
        "embroidery"
    ],
    "wof:name":"J S Embroidery",
    "wof:placetype":"venue"
},
  "geometry": {"coordinates":[145.09254455600001,-37.9270935059],"type":"Point"}
}