{
  "type": "Feature",
  "properties": {
    "addr:full":"77 Main St Atherton QLD 4883",
    "addr:housenumber":"77",
    "addr:postcode":"4883",
    "addr:street":"Main St",
    "iso:country":"AU",
    "sg:address":"77 Main St",
    "sg:city":"Atherton",
    "sg:classifiers":[
        {
            "category":"Travel",
            "subcategory":"Hotels & Motels",
            "type":"Entertainment"
        }
    ],
    "sg:phone":"+61 7 4091 1139",
    "sg:postcode":"4883",
    "sg:province":"QLD",
    "sg:tags":[
        "accommodation"
    ],
    "wof:name":"Carrington Hotel",
    "wof:placetype":"venue"
},
  "geometry": {"coordinates":[145.475631714,-17.2659835815],"type":"Point"}
}