{
  "type": "Feature",
  "properties": {
    "addr:full":"16 Glencoe Ave Riverside TAS 7250",
    "addr:housenumber":"16",
    "addr:postcode":"7250",
    "addr:street":"Glencoe Ave",
    "iso:country":"AU",
    "sg:address":"16 Glencoe Ave",
    "sg:city":"Riverside",
    "sg:classifiers":[
        {
            "category":"Personal",
            "subcategory":"Massage",
            "type":"Services"
        }
    ],
    "sg:phone":"+61 418 373 403",
    "sg:postcode":"7250",
    "sg:province":"TAS",
    "sg:tags":[
        "therapy"
    ],
    "wof:name":"Keith Lucas",
    "wof:placetype":"venue"
},
  "geometry": {"coordinates":[147.10958862300001,-41.4296112061],"type":"Point"}
}