{
  "type": "Feature",
  "properties": {
    "addr:full":"67 Murtho Rd Paringa SA 5340",
    "addr:housenumber":"67",
    "addr:postcode":"5340",
    "addr:street":"Murtho Rd",
    "iso:country":"AU",
    "sg:address":"67 Murtho Rd",
    "sg:city":"Paringa",
    "sg:classifiers":[
        {
            "category":"Farming",
            "subcategory":"Orchard",
            "type":"Manufacturing & Wholesale Goods"
        }
    ],
    "sg:phone":"+61 8 8595 5072",
    "sg:postcode":"5340",
    "sg:province":"SA",
    "sg:tags":[
        "citrus",
        "fruit",
        "grower"
    ],
    "wof:name":"Broomell J A & S T",
    "wof:placetype":"venue"
},
  "geometry": {"coordinates":[140.78216552699999,-34.1775588989],"type":"Point"}
}