{
  "type": "Feature",
  "properties": {
    "addr:full":"1 / 69 Bedford Rd Ringwood East VIC 3135",
    "addr:housenumber":"/ 69",
    "addr:postcode":"3135",
    "addr:street":"Bedford Rd",
    "iso:country":"AU",
    "sg:address":"1 / 69 Bedford Rd",
    "sg:city":"Ringwood East",
    "sg:classifiers":[
        {
            "category":"Health Services",
            "subcategory":"Health Practitioner",
            "type":"Services"
        }
    ],
    "sg:phone":"+61 3 9870 5169",
    "sg:postcode":"3135",
    "sg:province":"VIC",
    "sg:tags":[
        "dietitian"
    ],
    "wof:name":"Margaret Klemick",
    "wof:placetype":"venue"
},
  "geometry": {"coordinates":[145.24253845199999,-37.8181991577],"type":"Point"}
}