{
  "type": "Feature",
  "properties": {
    "addr:full":"Shop 5 / 116 Main St Pakenham VIC 3810",
    "addr:housenumber":"shop 5 / 116",
    "addr:postcode":"3810",
    "addr:street":"Main St",
    "iso:country":"AU",
    "sg:address":"Shop 5 / 116 Main St",
    "sg:city":"Pakenham",
    "sg:classifiers":[
        {
            "category":"Shopping",
            "subcategory":"Mobile Phones",
            "type":"Retail Goods"
        }
    ],
    "sg:phone":"+61 3 5941 5155",
    "sg:postcode":"3810",
    "sg:province":"VIC",
    "sg:tags":[
        "telephone",
        "accessory"
    ],
    "wof:name":"Cell To Cell",
    "wof:placetype":"venue"
},
  "geometry": {"coordinates":[145.482193,-38.077759],"type":"Point"}
}