{
  "type": "Feature",
  "properties": {
    "iso:country":"AU",
    "sg:address":"47 Pakington St",
    "sg:city":"Geelong",
    "sg:classifiers":[
        {
            "category":"Government",
            "subcategory":"Court House",
            "type":"Public Place"
        }
    ],
    "sg:phone":"+61 407 502 794",
    "sg:postcode":"3220",
    "sg:province":"VIC",
    "sg:tags":[
        "personal",
        "marriage",
        "family",
        "counselling"
    ],
    "wof:name":"McFarlane Fay",
    "wof:placetype":"venue"
},
  "geometry": {"coordinates":[144.349289,-38.134663],"type":"Point"}
}