{
  "type": "Feature",
  "properties": {
    "iso:country":"AU",
    "sg:address":"12 Birdie Ave",
    "sg:city":"Anglesea",
    "sg:classifiers":[
        {
            "category":"Shopping",
            "subcategory":"Jewelry",
            "type":"Retail Goods"
        }
    ],
    "sg:phone":"+61 3 5263 3372",
    "sg:postcode":"3230",
    "sg:province":"VIC",
    "sg:tags":[
        "jeweller"
    ],
    "wof:name":"Dreamscape IXL",
    "wof:placetype":"venue"
},
  "geometry": {"coordinates":[144.168076,-38.410187],"type":"Point"}
}