{
  "type": "Feature",
  "properties": {
    "addr:full":"46 Stradbroke St Anglers Paradise QLD 4216",
    "addr:housenumber":"46",
    "addr:postcode":"4216",
    "addr:street":"Stradbroke St",
    "iso:country":"AU",
    "sg:address":"46 Stradbroke St",
    "sg:city":"Anglers Paradise",
    "sg:classifiers":[
        {
            "category":"Professional",
            "subcategory":"Business Services",
            "type":"Services"
        }
    ],
    "sg:phone":"+61 7 5537 3757",
    "sg:postcode":"4216",
    "sg:province":"QLD",
    "sg:tags":[
        "broker"
    ],
    "wof:name":"Biggera Pacific Investments",
    "wof:placetype":"venue"
},
  "geometry": {"coordinates":[153.40049743599999,-27.9280834198],"type":"Point"}
}