{
  "type": "Feature",
  "properties": {
    "iso:country":"AU",
    "sg:address":"64 Greenleaf Rd",
    "sg:city":"Kooragang Island",
    "sg:classifiers":[
        {
            "category":"Real Estate",
            "subcategory":"Real Estate Agent",
            "type":"Services"
        }
    ],
    "sg:phone":"+61 2 4928 2211",
    "sg:postcode":"2304",
    "sg:province":"NSW",
    "sg:tags":[
        "handyman's",
        "equipment",
        "hire",
        "builders",
        "contractor"
    ],
    "wof:name":"Custom Transportable Buildings",
    "wof:placetype":"venue"
},
  "geometry": {"coordinates":[151.78318786599999,-32.8860015869],"type":"Point"}
}