{
  "type": "Feature",
  "properties": {
    "iso:country":"AU",
    "sg:address":"Suite 2 19 Palmer St",
    "sg:city":"North Mackay",
    "sg:classifiers":[
        {
            "category":"Personal",
            "subcategory":"Beauty Salon",
            "type":"Services"
        }
    ],
    "sg:phone":"+61 7 4953 1166",
    "sg:postcode":"4740",
    "sg:province":"QLD",
    "wof:name":"Lynne's Natural Body & Beauty",
    "wof:placetype":"venue"
},
  "geometry": {"coordinates":[149.18902600000001,-21.124676],"type":"Point"}
}