{
  "type": "Feature",
  "properties": {
    "addr:full":"11 Cabernet Crt Buderim QLD 4556",
    "addr:housenumber":"11",
    "addr:postcode":"4556",
    "addr:street":"Cabernet Crt",
    "iso:country":"AU",
    "sg:address":"11 Cabernet Crt",
    "sg:city":"Buderim",
    "sg:classifiers":[
        {
            "category":"Organizations",
            "subcategory":"Professional Association",
            "type":"Services"
        }
    ],
    "sg:phone":"+61 7 5478 2215",
    "sg:postcode":"4556",
    "sg:province":"QLD",
    "sg:tags":[
        "web",
        "internet"
    ],
    "wof:name":"12 Website",
    "wof:placetype":"venue"
},
  "geometry": {"coordinates":[153.0753479,-26.6977386475],"type":"Point"}
}