{
  "type": "Feature",
  "properties": {
    "addr:full":"1675 Burwood Hwy Belgrave VIC 3160",
    "addr:housenumber":"1675",
    "addr:postcode":"3160",
    "addr:street":"Burwood Hwy",
    "iso:country":"AU",
    "sg:address":"1675 Burwood Hwy",
    "sg:city":"Belgrave",
    "sg:classifiers":[
        {
            "category":"Farming",
            "subcategory":"Fish & Marine Products",
            "type":"Manufacturing & Wholesale Goods"
        }
    ],
    "sg:phone":"+61 3 9754 8800",
    "sg:postcode":"3160",
    "sg:province":"VIC",
    "sg:tags":[
        "organic"
    ],
    "wof:name":"Belgrave Organics",
    "wof:placetype":"venue"
},
  "geometry": {"coordinates":[145.35432434099999,-37.9090461731],"type":"Point"}
}