{
  "type": "Feature",
  "properties": {
    "iso:country":"AU",
    "sg:address":"380 Johnston St",
    "sg:city":"Abbotsford",
    "sg:classifiers":[
        {
            "category":"Professional",
            "subcategory":"Printing & Photocopies",
            "type":"Services"
        }
    ],
    "sg:phone":"+61 3 9415 1111",
    "sg:postcode":"3067",
    "sg:province":"VIC",
    "sg:tags":[
        "embroidery"
    ],
    "wof:name":"Access Embroidery Australia Pty Ltd",
    "wof:placetype":"venue"
},
  "geometry": {"coordinates":[144.998245239,-37.8002090454],"type":"Point"}
}