{
  "type": "Feature",
  "properties": {
    "iso:country":"AU",
    "sg:address":"Shp15/ 51 Rockingham Rd",
    "sg:city":"Hamilton Hill",
    "sg:classifiers":[
        {
            "category":"Personal",
            "subcategory":"Beauty Salon",
            "type":"Services"
        }
    ],
    "sg:phone":"+61 8 9335 5087",
    "sg:postcode":"6163",
    "sg:province":"WA",
    "sg:tags":[
        "hairdresser"
    ],
    "wof:name":"Snippers Mens Hair Design",
    "wof:placetype":"venue"
},
  "geometry": {"coordinates":[115.769676,-32.082283],"type":"Point"}
}