{
  "type": "Feature",
  "properties": {
    "iso:country":"AU",
    "sg:address":"178A Old Kent Rd",
    "sg:city":"Greenacre",
    "sg:classifiers":[
        {
            "category":"Real Estate",
            "subcategory":"Surveying",
            "type":"Services"
        }
    ],
    "sg:phone":"+61 409 121 535",
    "sg:postcode":"2190",
    "sg:province":"NSW",
    "sg:tags":[
        "surveyor",
        "land"
    ],
    "wof:name":"S.C.Surveyors",
    "wof:placetype":"venue"
},
  "geometry": {"coordinates":[151.04727199999999,-33.913551],"type":"Point"}
}