{
  "type": "Feature",
  "properties": {
    "addr:full":"14 Victor St Birkdale QLD 4159",
    "addr:housenumber":"14",
    "addr:postcode":"4159",
    "addr:street":"Victor St",
    "iso:country":"AU",
    "sg:address":"14 Victor St",
    "sg:city":"Birkdale",
    "sg:classifiers":[
        {
            "category":"Professional",
            "subcategory":"Employment Agencies",
            "type":"Services"
        }
    ],
    "sg:phone":"+61 1300 663 977",
    "sg:postcode":"4159",
    "sg:province":"QLD",
    "sg:tags":[
        "provider",
        "internet"
    ],
    "wof:name":"Hotkey Brisbane Southside",
    "wof:placetype":"venue"
},
  "geometry": {"coordinates":[153.21282959000001,-27.4910163879],"type":"Point"}
}