{
  "type": "Feature",
  "properties": {
    "addr:full":"66 Gungah Bay Rd Oatley NSW 2223",
    "addr:housenumber":"66",
    "addr:postcode":"2223",
    "addr:street":"Gungah Bay Rd",
    "iso:country":"AU",
    "sg:address":"66 Gungah Bay Rd",
    "sg:city":"Oatley",
    "sg:classifiers":[
        {
            "category":"Building & Trades",
            "subcategory":"Plumbing",
            "type":"Services"
        }
    ],
    "sg:phone":"+61 2 9580 3313",
    "sg:postcode":"2223",
    "sg:province":"NSW",
    "sg:tags":[
        "plumber",
        "gasfitters"
    ],
    "wof:name":"Brian's Plumbing Service",
    "wof:placetype":"venue"
},
  "geometry": {"coordinates":[151.07223510700001,-33.9748382568],"type":"Point"}
}