{
  "type": "Feature",
  "properties": {
    "addr:full":"Rear 451 Fitzgerald St North Perth WA 6006",
    "addr:housenumber":"451",
    "addr:postcode":"6006",
    "addr:street":"Fitzgerald St",
    "iso:country":"AU",
    "sg:address":"Rear 451 Fitzgerald St",
    "sg:city":"North Perth",
    "sg:classifiers":[
        {
            "category":"Shopping",
            "subcategory":"Discount & Variety Stores",
            "type":"Retail Goods"
        }
    ],
    "sg:phone":"+61 8 9228 3522",
    "sg:postcode":"6006",
    "sg:province":"WA",
    "sg:tags":[
        "register",
        "cash"
    ],
    "wof:name":"Western Business Machines",
    "wof:placetype":"venue"
},
  "geometry": {"coordinates":[115.859016419,-31.9309234619],"type":"Point"}
}