{
  "type": "Feature",
  "properties": {
    "iso:country":"AU",
    "sg:address":"71 MacLeod St",
    "sg:city":"Bairnsdale",
    "sg:classifiers":[
        {
            "category":"Shopping",
            "subcategory":"Stationery & Office Supplies",
            "type":"Retail Goods"
        }
    ],
    "sg:phone":"+61 3 5152 4499",
    "sg:postcode":"3875",
    "sg:province":"VIC",
    "wof:name":"Office National Bairnsdale",
    "wof:placetype":"venue"
},
  "geometry": {"coordinates":[147.63168335,-37.8273735046],"type":"Point"}
}