{
  "type": "Feature",
  "properties": {
    "addr:full":"16 Fulford St Trevallyn TAS 7250",
    "addr:housenumber":"16",
    "addr:postcode":"7250",
    "addr:street":"Fulford St",
    "iso:country":"AU",
    "sg:address":"16 Fulford St",
    "sg:city":"Trevallyn",
    "sg:classifiers":[
        {
            "category":"Education",
            "subcategory":"Music School",
            "type":"Public Place"
        }
    ],
    "sg:phone":"+61 438 293 886",
    "sg:postcode":"7250",
    "sg:province":"TAS",
    "sg:tags":[
        "teacher"
    ],
    "wof:name":"Andrew Collins",
    "wof:placetype":"venue"
},
  "geometry": {"coordinates":[147.11256408700001,-41.4382591248],"type":"Point"}
}