{
  "type": "Feature",
  "properties": {
    "iso:country":"AU",
    "sg:address":"Unit 7/ 25 Green Street",
    "sg:city":"Kogarah",
    "sg:classifiers":[
        {
            "category":"Professional",
            "subcategory":"Computer Services",
            "type":"Services"
        }
    ],
    "sg:phone":"+61 1300 851 866",
    "sg:postcode":"2217",
    "sg:province":"NSW",
    "sg:tags":[
        "package",
        "software"
    ],
    "wof:name":"Seratec Pty Ltd",
    "wof:placetype":"venue"
},
  "geometry": {"coordinates":[151.139816,-33.963448],"type":"Point"}
}