{
  "type": "Feature",
  "properties": {
    "iso:country":"AU",
    "sg:address":"80 Waratah Drv",
    "sg:city":"Crestmead",
    "sg:classifiers":[
        {
            "category":"Professional",
            "subcategory":"Computer Services",
            "type":"Services"
        }
    ],
    "sg:phone":"+61 402 986 863",
    "sg:postcode":"4132",
    "sg:province":"QLD",
    "sg:tags":[
        "repairs",
        "upgrade",
        "equipment"
    ],
    "wof:name":"Inspect-a-gadget Computer Services",
    "wof:placetype":"venue"
},
  "geometry": {"coordinates":[153.097946167,-27.6873130798],"type":"Point"}
}