{
  "type": "Feature",
  "properties": {
    "iso:country":"AU",
    "sg:address":"107A Eighth St",
    "sg:city":"Mildura",
    "sg:classifiers":[
        {
            "category":"Shopping",
            "subcategory":"Computers & Home Electronics",
            "type":"Retail Goods"
        }
    ],
    "sg:phone":"+61 3 5022 1070",
    "sg:postcode":"3500",
    "sg:province":"VIC",
    "sg:tags":[
        "equipment",
        "part",
        "electronic"
    ],
    "wof:name":"A & R Electronics",
    "wof:placetype":"venue"
},
  "geometry": {"coordinates":[142.16557312,-34.1872901917],"type":"Point"}
}