{
  "type": "Feature",
  "properties": {
    "addr:full":"121 Stephen Rd Botany NSW 2019",
    "addr:housenumber":"121",
    "addr:postcode":"2019",
    "addr:street":"Stephen Rd",
    "iso:country":"AU",
    "sg:address":"121 Stephen Rd",
    "sg:city":"Botany",
    "sg:classifiers":[
        {
            "category":"Autos & Motor Vehicles",
            "subcategory":"Boat Sales",
            "type":"Retail Goods"
        }
    ],
    "sg:phone":"+61 2 9666 8066",
    "sg:postcode":"2019",
    "sg:province":"NSW",
    "sg:tags":[
        "equipment",
        "yacht"
    ],
    "wof:name":"Liferaft Servicing Group Pty. Ltd.",
    "wof:placetype":"venue"
},
  "geometry": {"coordinates":[151.206207275,-33.9566497803],"type":"Point"}
}