{
  "type": "Feature",
  "properties": {
    "iso:country":"AU",
    "sg:address":"27 Dandenong St",
    "sg:city":"Dandenong",
    "sg:classifiers":[
        {
            "category":"Manufacturing",
            "subcategory":"Metals",
            "type":"Manufacturing & Wholesale Goods"
        }
    ],
    "sg:phone":"+61 3 9794 9288",
    "sg:postcode":"3175",
    "sg:province":"VIC",
    "sg:tags":[
        "sheet",
        "worker"
    ],
    "wof:name":"B J Sheet Metal",
    "wof:placetype":"venue"
},
  "geometry": {"coordinates":[145.19993591299999,-37.9928283691],"type":"Point"}
}