{
  "type": "Feature",
  "properties": {
    "iso:country":"AU",
    "sg:address":"Unit 7 / 28 Salpietro St",
    "sg:city":"Spearwood",
    "sg:classifiers":[
        {
            "category":"Arts & Performance",
            "subcategory":"Dance",
            "type":"Entertainment"
        }
    ],
    "sg:phone":"+61 8 9434 4691",
    "sg:postcode":"6163",
    "sg:province":"WA",
    "sg:tags":[
        "theatrical",
        "ballet",
        "tuition"
    ],
    "wof:name":"Kerry Gough Gotta Dance School",
    "wof:placetype":"venue"
},
  "geometry": {"coordinates":[115.795242,-32.113895],"type":"Point"}
}