{
  "type": "Feature",
  "properties": {
    "addr:full":"6 Irvine St Bayswater WA 6053",
    "addr:housenumber":"6",
    "addr:postcode":"6053",
    "addr:street":"Irvine St",
    "iso:country":"AU",
    "sg:address":"6 Irvine St",
    "sg:city":"Bayswater",
    "sg:classifiers":[
        {
            "category":"Wholesale",
            "subcategory":"Auto Parts",
            "type":"Manufacturing & Wholesale Goods"
        }
    ],
    "sg:phone":"+61 8 9271 0538",
    "sg:postcode":"6053",
    "sg:province":"WA",
    "sg:tags":[
        "recyclers"
    ],
    "wof:name":"A All Commodore Parts",
    "wof:placetype":"venue"
},
  "geometry": {"coordinates":[115.917991638,-31.9124240875],"type":"Point"}
}