{
  "type": "Feature",
  "properties": {
    "addr:full":"5 Aid St Emerald QLD 4720",
    "addr:housenumber":"5",
    "addr:postcode":"4720",
    "addr:street":"Aid St",
    "iso:country":"AU",
    "sg:address":"5 Aid St",
    "sg:city":"Emerald",
    "sg:classifiers":[
        {
            "category":"Professional",
            "subcategory":"Employment Agencies",
            "type":"Services"
        }
    ],
    "sg:phone":"+61 7 4987 7184",
    "sg:postcode":"4720",
    "sg:province":"QLD",
    "wof:name":"Golden West Employment Solutions",
    "wof:placetype":"venue"
},
  "geometry": {"coordinates":[148.15533400000001,-23.511122],"type":"Point"}
}