{
  "type": "Feature",
  "properties": {
    "iso:country":"AU",
    "sg:address":"5 Aid St",
    "sg:city":"Emerald",
    "sg:classifiers":[
        {
            "category":"Professional",
            "subcategory":"Employment Agencies",
            "type":"Services"
        }
    ],
    "sg:phone":"+61 7 4987 7184",
    "sg:postcode":"4720",
    "sg:province":"QLD",
    "wof:name":"Golden West Employment Solutions",
    "wof:placetype":"venue"
},
  "geometry": {"coordinates":[148.155334,-23.511122],"type":"Point"}
}