{
  "type": "Feature",
  "properties": {
    "iso:country":"AU",
    "sg:address":"1/ 14 Jennings Crt",
    "sg:city":"Rosebud",
    "sg:classifiers":[
        {
            "category":"Building & Trades",
            "subcategory":"Construction",
            "type":"Services"
        }
    ],
    "sg:phone":"+61 3 5986 7621",
    "sg:postcode":"3939",
    "sg:province":"VIC",
    "sg:tags":[
        "fencing",
        "contractor"
    ],
    "wof:name":"Woodville",
    "wof:placetype":"venue"
},
  "geometry": {"coordinates":[144.883102417,-38.3803405762],"type":"Point"}
}