{
  "type": "Feature",
  "properties": {
    "addr:full":"Old Sturt Hwy Berri SA 5343",
    "addr:postcode":"5343",
    "addr:street":"Sturt Hwy",
    "iso:country":"AU",
    "sg:address":"Old Sturt Hwy",
    "sg:city":"Berri",
    "sg:classifiers":[
        {
            "category":"Autos & Motor Vehicles",
            "subcategory":"Fuel & Gas Station",
            "type":"Retail Goods"
        }
    ],
    "sg:phone":"+61 8 8582 1025",
    "sg:postcode":"5343",
    "sg:province":"SA",
    "wof:name":"Caltex Service Station",
    "wof:placetype":"venue"
},
  "geometry": {"coordinates":[140.595214844,-34.2835884094],"type":"Point"}
}