{
  "type": "Feature",
  "properties": {
    "iso:country":"AU",
    "sg:address":"54 Walmsley St",
    "sg:city":"Kangaroo Point",
    "sg:classifiers":[
        {
            "category":"Real Estate",
            "subcategory":"Architect",
            "type":"Services"
        }
    ],
    "sg:phone":"+61 7 3891 5667",
    "sg:postcode":"4169",
    "sg:province":"QLD",
    "sg:tags":[
        "building",
        "designer"
    ],
    "wof:name":"David Murray & Associates",
    "wof:placetype":"venue"
},
  "geometry": {"coordinates":[153.03431701700001,-27.4816017151],"type":"Point"}
}