{
  "type": "Feature",
  "properties": {
    "addr:full":"83 Cimitiere St Launceston TAS 7900",
    "addr:housenumber":"83",
    "addr:postcode":"7900",
    "addr:street":"Cimitiere St",
    "iso:country":"AU",
    "sg:address":"83 Cimitiere St",
    "sg:city":"Launceston",
    "sg:classifiers":[
        {
            "category":"Personal",
            "type":"Services"
        }
    ],
    "sg:phone":"+61 1800 850 851",
    "sg:postcode":"7900",
    "sg:province":"TAS",
    "sg:tags":[
        "gift"
    ],
    "wof:name":"Gifts Direct",
    "wof:placetype":"venue"
},
  "geometry": {"coordinates":[147.139694214,-41.4334487915],"type":"Point"}
}