{
  "type": "Feature",
  "properties": {
    "addr:full":"Boiling Down Rd Warrnambool VIC 3280",
    "addr:postcode":"3280",
    "addr:street":"Down Rd",
    "iso:country":"AU",
    "sg:address":"Boiling Down Rd",
    "sg:city":"Warrnambool",
    "sg:classifiers":[
        {
            "category":"Professional",
            "subcategory":"Engineering",
            "type":"Services"
        }
    ],
    "sg:phone":"+61 3 5561 3721",
    "sg:postcode":"3280",
    "sg:province":"VIC",
    "sg:tags":[
        "manufacturing",
        "engineer"
    ],
    "wof:name":"SWI Engineering Pty Ltd",
    "wof:placetype":"venue"
},
  "geometry": {"coordinates":[142.525756836,-38.3718223572],"type":"Point"}
}