{
  "type": "Feature",
  "properties": {
    "addr:full":"2- 4 Park St Wendouree VIC 3355",
    "addr:housenumber":"4",
    "addr:postcode":"3355",
    "addr:street":"Park St",
    "iso:country":"AU",
    "sg:address":"2- 4 Park St",
    "sg:city":"Wendouree",
    "sg:classifiers":[
        {
            "category":"Health Services",
            "subcategory":"Nursing And Care Facility",
            "type":"Services"
        }
    ],
    "sg:phone":"+61 3 5339 4211",
    "sg:postcode":"3355",
    "sg:province":"VIC",
    "sg:tags":[
        "home"
    ],
    "wof:name":"Kelaston Nursing Home",
    "wof:placetype":"venue"
},
  "geometry": {"coordinates":[143.82502700000001,-37.538918],"type":"Point"}
}