{
  "type": "Feature",
  "properties": {
    "addr:full":"PO Box 83 Fulham Gardens SA 5024",
    "addr:postcode":"5024",
    "iso:country":"AU",
    "sg:address":"PO Box 83",
    "sg:city":"Fulham Gardens",
    "sg:classifiers":[
        {
            "category":"Professional",
            "subcategory":"Employment Agencies",
            "type":"Services"
        }
    ],
    "sg:phone":"+61 417 890 549",
    "sg:postcode":"5024",
    "sg:province":"SA",
    "sg:tags":[
        "entertainer",
        "agent"
    ],
    "wof:name":"KTC Entertainment",
    "wof:placetype":"venue"
},
  "geometry": {"coordinates":[138.509643555,-34.9196548462],"type":"Point"}
}