{
  "type": "Feature",
  "properties": {
    "addr:full":"18 Sylvester St North Lakes QLD 4509",
    "addr:housenumber":"18",
    "addr:postcode":"4509",
    "addr:street":"Sylvester St",
    "iso:country":"AU",
    "sg:address":"18 Sylvester St",
    "sg:city":"North Lakes",
    "sg:classifiers":[
        {
            "category":"Professional",
            "subcategory":"Art Services",
            "type":"Services"
        }
    ],
    "sg:phone":"+61 7 3886 1012",
    "sg:postcode":"4509",
    "sg:province":"QLD",
    "sg:tags":[
        "graphic",
        "designer"
    ],
    "wof:name":"Genesis Art Pty Ltd",
    "wof:placetype":"venue"
},
  "geometry": {"coordinates":[153.02127075199999,-27.2303638458],"type":"Point"}
}