{
  "type": "Feature",
  "properties": {
    "addr:full":"34 James St Fortitude Valley QLD 4006",
    "addr:housenumber":"34",
    "addr:postcode":"4006",
    "addr:street":"James St",
    "iso:country":"AU",
    "sg:address":"34 James St",
    "sg:city":"Fortitude Valley",
    "sg:classifiers":[
        {
            "category":"Shopping",
            "subcategory":"Computers & Home Electronics",
            "type":"Retail Goods"
        }
    ],
    "sg:phone":"+61 7 3852 1666",
    "sg:postcode":"4006",
    "sg:province":"QLD",
    "sg:tags":[
        "hardware",
        "equipment"
    ],
    "wof:name":"Mac1 Newfarm",
    "wof:placetype":"venue"
},
  "geometry": {"coordinates":[153.03976440400001,-27.4564304352],"type":"Point"}
}