{
  "type": "Feature",
  "properties": {
    "addr:full":"123 Maritana St Kalgoorlie WA 6430",
    "addr:housenumber":"123",
    "addr:postcode":"6430",
    "addr:street":"Maritana St",
    "iso:country":"AU",
    "sg:address":"123 Maritana St",
    "sg:city":"Kalgoorlie",
    "sg:classifiers":[
        {
            "category":"Professional",
            "subcategory":"Accounting & Tax Preparation",
            "type":"Services"
        }
    ],
    "sg:phone":"+61 8 9022 9162",
    "sg:postcode":"6430",
    "sg:province":"WA",
    "sg:tags":[
        "bookkeeping"
    ],
    "wof:name":"bookkeepers@work",
    "wof:placetype":"venue"
},
  "geometry": {"coordinates":[121.47528839100001,-30.746553421],"type":"Point"}
}