{
  "type": "Feature",
  "properties": {
    "addr:full":"Factory 10/10- 14 Simms Rd Greensborough VIC 3088",
    "addr:housenumber":"10 / 10 14",
    "addr:postcode":"3088",
    "addr:street":"Simms Rd",
    "iso:country":"AU",
    "sg:address":"Factory 10/10- 14 Simms Rd",
    "sg:city":"Greensborough",
    "sg:classifiers":[
        {
            "category":"Home & Garden",
            "subcategory":"Carpets & Floor Coverings",
            "type":"Retail Goods"
        }
    ],
    "sg:phone":"+61 3 9435 8030",
    "sg:postcode":"3088",
    "sg:province":"VIC",
    "sg:tags":[
        "wood"
    ],
    "wof:name":"Rainbow Timber Floors",
    "wof:placetype":"venue"
},
  "geometry": {"coordinates":[145.11317443900001,-37.7117118835],"type":"Point"}
}