{
  "type": "Feature",
  "properties": {
    "addr:full":"90 Channon St Gympie QLD 4570",
    "addr:housenumber":"90",
    "addr:postcode":"4570",
    "addr:street":"Channon St",
    "iso:country":"AU",
    "sg:address":"90 Channon St",
    "sg:city":"Gympie",
    "sg:classifiers":[
        {
            "category":"Health Services",
            "subcategory":"Dentist",
            "type":"Services"
        }
    ],
    "sg:phone":"+61 7 5482 7688",
    "sg:postcode":"4570",
    "sg:province":"QLD",
    "wof:name":"Starcevic, Branka Dr",
    "wof:placetype":"venue"
},
  "geometry": {"coordinates":[152.665161133,-26.1846485138],"type":"Point"}
}