{
  "type": "Feature",
  "properties": {
    "addr:full":"28- 32 Brisbane St Hobart TAS 7000",
    "addr:housenumber":"32",
    "addr:postcode":"7000",
    "addr:street":"Brisbane St",
    "iso:country":"AU",
    "sg:address":"28- 32 Brisbane St",
    "sg:city":"Hobart",
    "sg:classifiers":[
        {
            "category":"Autos & Motor Vehicles",
            "subcategory":"Automobile Sales",
            "type":"Retail Goods"
        }
    ],
    "sg:phone":"+61 3 6231 2833",
    "sg:postcode":"7000",
    "sg:province":"TAS",
    "sg:tags":[
        "car",
        "new"
    ],
    "wof:name":"Audi - Stevenson Prestige",
    "wof:placetype":"venue"
},
  "geometry": {"coordinates":[147.324752808,-42.8782920837],"type":"Point"}
}