{
  "type": "Feature",
  "properties": {
    "addr:full":"75 Churchill St Childers QLD 4660",
    "addr:housenumber":"75",
    "addr:postcode":"4660",
    "addr:street":"Churchill St",
    "iso:country":"AU",
    "sg:address":"75 Churchill St",
    "sg:city":"Childers",
    "sg:classifiers":[
        {
            "category":"Shopping",
            "subcategory":"Crafts & Fabrics",
            "type":"Retail Goods"
        }
    ],
    "sg:phone":"+61 7 4126 2708",
    "sg:postcode":"4660",
    "sg:province":"QLD",
    "sg:tags":[
        "supply"
    ],
    "wof:name":"Bead Creative",
    "wof:placetype":"venue"
},
  "geometry": {"coordinates":[152.27653503400001,-25.2363910675],"type":"Point"}
}