{
  "type": "Feature",
  "properties": {
    "addr:full":"14 Wilkins Rd Elizabeth Downs SA 5113",
    "addr:housenumber":"14",
    "addr:postcode":"5113",
    "addr:street":"Wilkins Rd",
    "iso:country":"AU",
    "sg:address":"14 Wilkins Rd",
    "sg:city":"Elizabeth Downs",
    "sg:classifiers":[
        {
            "category":"Home & Garden",
            "subcategory":"Building Materials",
            "type":"Retail Goods"
        }
    ],
    "sg:phone":"+61 415 766 751",
    "sg:postcode":"5113",
    "sg:province":"SA",
    "sg:tags":[
        "lawn",
        "cutting",
        "maintenance"
    ],
    "wof:name":"SA Budget Services",
    "wof:placetype":"venue"
},
  "geometry": {"coordinates":[138.68882751500001,-34.696975708],"type":"Point"}
}