{
  "type": "Feature",
  "properties": {
    "addr:full":"Shop 2 16- 18 Church St Morwell VIC 3840",
    "addr:housenumber":"shop;16 18",
    "addr:postcode":"3840",
    "addr:street":"Church St",
    "iso:country":"AU",
    "sg:address":"Shop 2 16- 18 Church St",
    "sg:city":"Morwell",
    "sg:classifiers":[
        {
            "category":"Health Services",
            "subcategory":"Health Practitioner",
            "type":"Services"
        }
    ],
    "sg:phone":"+61 3 5195 5092",
    "sg:postcode":"3840",
    "sg:province":"VIC",
    "sg:tags":[
        "bowen",
        "therapy"
    ],
    "wof:name":"Blue Wren Therapy",
    "wof:placetype":"venue"
},
  "geometry": {"coordinates":[146.39921569800001,-38.2360115051],"type":"Point"}
}