{
  "type": "Feature",
  "properties": {
    "iso:country":"AU",
    "sg:address":"5 Brunsdon St",
    "sg:city":"Bayswater",
    "sg:classifiers":[
        {
            "category":"Wholesale",
            "subcategory":"Medical Equipment & Supplies",
            "type":"Manufacturing & Wholesale Goods"
        }
    ],
    "sg:phone":"+61 3 8727 7111",
    "sg:postcode":"3153",
    "sg:province":"VIC",
    "sg:tags":[
        "dental"
    ],
    "wof:name":"SDI Ltd",
    "wof:placetype":"venue"
},
  "geometry": {"coordinates":[145.277145386,-37.8478736877],"type":"Point"}
}