{
  "type": "Feature",
  "properties": {
    "addr:full":"37 Queen St Busselton WA 6280",
    "addr:housenumber":"37",
    "addr:postcode":"6280",
    "addr:street":"Queen St",
    "iso:country":"AU",
    "sg:address":"37 Queen St",
    "sg:city":"Busselton",
    "sg:classifiers":[
        {
            "category":"Cafe",
            "type":"Food & Drink"
        }
    ],
    "sg:phone":"+61 8 9752 2501",
    "sg:postcode":"6280",
    "sg:province":"WA",
    "wof:name":"Geographe Pizza & Take Away Foods",
    "wof:placetype":"venue"
},
  "geometry": {"coordinates":[115.344413757,-33.6489257812],"type":"Point"}
}