{
  "type": "Feature",
  "properties": {
    "iso:country":"AU",
    "sg:address":"U1/ 22 Stirling Tce",
    "sg:city":"Toodyay",
    "sg:classifiers":[
        {
            "category":"Sports & Exercise",
            "subcategory":"Gym",
            "type":"Entertainment"
        }
    ],
    "sg:phone":"+61 8 9574 5687",
    "sg:postcode":"6566",
    "sg:province":"WA",
    "sg:tags":[
        "health",
        "fitness"
    ],
    "wof:name":"Full Circle Gym & Fitness",
    "wof:placetype":"venue"
},
  "geometry": {"coordinates":[116.475891,-31.556355],"type":"Point"}
}