{
  "type": "Feature",
  "properties": {
    "addr:full":"44- 46 Stuart Hwy Darwin NT 0800",
    "addr:housenumber":"46",
    "addr:postcode":"nt 0800",
    "addr:street":"Stuart Hwy",
    "iso:country":"AU",
    "sg:address":"44- 46 Stuart Hwy",
    "sg:city":"Darwin",
    "sg:classifiers":[
        {
            "category":"Retail",
            "subcategory":"Auto Rental",
            "type":"Services"
        }
    ],
    "sg:phone":"+61 8 8981 2081",
    "sg:postcode":"0800",
    "sg:province":"NT",
    "sg:tags":[
        "car",
        "hire",
        "minibus"
    ],
    "wof:name":"Britz Campervan Rentals",
    "wof:placetype":"venue"
},
  "geometry": {"coordinates":[130.84124755900001,-12.4470186234],"type":"Point"}
}