{
  "type": "Feature",
  "properties": {
    "iso:country":"AU",
    "sg:address":"3/ 66 Sunderland St",
    "sg:city":"Derwent Park",
    "sg:classifiers":[
        {
            "category":"Communications",
            "subcategory":"Television Station",
            "type":"Services"
        }
    ],
    "sg:phone":"+61 3 6273 6736",
    "sg:postcode":"7009",
    "sg:province":"TAS",
    "sg:tags":[
        "screening",
        "machinery",
        "grading"
    ],
    "wof:name":"Johnson Screens (Australia) Pty Ltd",
    "wof:placetype":"venue"
},
  "geometry": {"coordinates":[147.29434204099999,-42.8399353027],"type":"Point"}
}