{
  "type": "Feature",
  "properties": {
    "addr:full":"698 Old Cleveland Rd Camp Hill QLD 4152",
    "addr:housenumber":"698",
    "addr:postcode":"4152",
    "addr:street":"Old Cleveland Rd",
    "iso:country":"AU",
    "sg:address":"698 Old Cleveland Rd",
    "sg:city":"Camp Hill",
    "sg:classifiers":[
        {
            "category":"Shopping",
            "subcategory":"Bridal",
            "type":"Retail Goods"
        }
    ],
    "sg:phone":"+61 7 3843 1359",
    "sg:postcode":"4152",
    "sg:province":"QLD",
    "sg:tags":[
        "hire",
        "wear"
    ],
    "wof:name":"Beautiful Brides",
    "wof:placetype":"venue"
},
  "geometry": {"coordinates":[153.080474853,-27.4928741455],"type":"Point"}
}