{
  "type": "Feature",
  "properties": {
    "iso:country":"AU",
    "sg:address":"23 Abor St",
    "sg:city":"Capella",
    "sg:classifiers":[
        {
            "category":"Professional",
            "subcategory":"Business Services",
            "type":"Services"
        }
    ],
    "sg:phone":"+61 7 4984 9187",
    "sg:postcode":"4702",
    "sg:province":"QLD",
    "sg:tags":[
        "livestock",
        "transport"
    ],
    "wof:name":"Matschoss N B & J E",
    "wof:placetype":"venue"
},
  "geometry": {"coordinates":[147.698364258,-23.417673111],"type":"Point"}
}