{
  "type": "Feature",
  "properties": {
    "iso:country":"AU",
    "sg:address":"542 Glenhuntly Rd",
    "sg:city":"Elsternwick",
    "sg:classifiers":[
        {
            "category":"Professional",
            "subcategory":"Art Services",
            "type":"Services"
        }
    ],
    "sg:phone":"+61 3 9528 2769",
    "sg:postcode":"3185",
    "sg:province":"VIC",
    "wof:name":"Caldwells",
    "wof:placetype":"venue"
},
  "geometry": {"coordinates":[144.99261474599999,-37.8833045959],"type":"Point"}
}