{
  "type": "Feature",
  "properties": {
    "addr:full":"23 Kilpa Rd Moorabbin VIC 3189",
    "addr:housenumber":"23",
    "addr:postcode":"3189",
    "addr:street":"Kilpa Rd",
    "iso:country":"AU",
    "sg:address":"23 Kilpa Rd",
    "sg:city":"Moorabbin",
    "sg:classifiers":[
        {
            "category":"Train Station",
            "subcategory":"Light Rail",
            "type":"Transportation"
        }
    ],
    "sg:phone":"+61 3 9553 3000",
    "sg:postcode":"3189",
    "sg:province":"VIC",
    "sg:tags":[
        "searchlight"
    ],
    "wof:name":"Trakka Corp Pty Ltd",
    "wof:placetype":"venue"
},
  "geometry": {"coordinates":[145.07325744600001,-37.9463043213],"type":"Point"}
}