{
  "type": "Feature",
  "properties": {
    "addr:full":"519 Burke Rd Camberwell VIC 3124",
    "addr:housenumber":"519",
    "addr:postcode":"3124",
    "addr:street":"Burke Rd",
    "iso:country":"AU",
    "sg:address":"519 Burke Rd",
    "sg:city":"Camberwell",
    "sg:classifiers":[
        {
            "category":"Shopping",
            "subcategory":"Computers & Home Electronics",
            "type":"Retail Goods"
        }
    ],
    "sg:phone":"+61 3 9822 7895",
    "sg:postcode":"3124",
    "sg:province":"VIC",
    "sg:tags":[
        "hardware",
        "equipment"
    ],
    "wof:name":"Data Parts Pty Ltd",
    "wof:placetype":"venue"
},
  "geometry": {"coordinates":[145.05409240700001,-37.8442001343],"type":"Point"}
}