{
  "type": "Feature",
  "properties": {
    "addr:full":"10 Cooraminta St Brunswick VIC 3056",
    "addr:housenumber":"10",
    "addr:postcode":"3056",
    "addr:street":"Cooraminta St",
    "iso:country":"AU",
    "sg:address":"10 Cooraminta St",
    "sg:city":"Brunswick",
    "sg:classifiers":[
        {
            "category":"Building & Trades",
            "subcategory":"Plumbing",
            "type":"Services"
        }
    ],
    "sg:phone":"+61 3 9380 5741",
    "sg:postcode":"3056",
    "sg:province":"VIC",
    "sg:tags":[
        "plumber",
        "gasfitters"
    ],
    "wof:name":"Pierce K J",
    "wof:placetype":"venue"
},
  "geometry": {"coordinates":[144.96783447300001,-37.7654342651],"type":"Point"}
}