{
  "type": "Feature",
  "properties": {
    "iso:country":"AU",
    "sg:address":"37 Warren Ave",
    "sg:city":"Bankstown",
    "sg:classifiers":[
        {
            "category":"Sports & Exercise",
            "subcategory":"Gym",
            "type":"Entertainment"
        }
    ],
    "sg:phone":"+61 1300 553 813",
    "sg:postcode":"2200",
    "sg:province":"NSW",
    "sg:tags":[
        "health",
        "fitness"
    ],
    "wof:name":"Yang Mian System",
    "wof:placetype":"venue"
},
  "geometry": {"coordinates":[151.03619399999999,-33.93264],"type":"Point"}
}