{
  "type": "Feature",
  "properties": {
    "addr:full":"446 Maroondah Hwy Lilydale VIC 3140",
    "addr:housenumber":"446",
    "addr:postcode":"3140",
    "addr:street":"Maroondah Hwy",
    "iso:country":"AU",
    "sg:address":"446 Maroondah Hwy",
    "sg:city":"Lilydale",
    "sg:classifiers":[
        {
            "category":"Health Services",
            "subcategory":"Health Practitioner",
            "type":"Services"
        }
    ],
    "sg:phone":"+61 3 9739 5868",
    "sg:postcode":"3140",
    "sg:province":"VIC",
    "sg:tags":[
        "physiotherapist"
    ],
    "wof:name":"De Soysa Ravi",
    "wof:placetype":"venue"
},
  "geometry": {"coordinates":[145.257522583,-37.7957725525],"type":"Point"}
}