{
  "type": "Feature",
  "properties": {
    "addr:full":"2 Villiers St Parramatta NSW 2150",
    "addr:housenumber":"2",
    "addr:postcode":"2150",
    "addr:street":"Villiers St",
    "iso:country":"AU",
    "sg:address":"2 Villiers St",
    "sg:city":"Parramatta",
    "sg:classifiers":[
        {
            "category":"Social Services",
            "subcategory":"Child Care",
            "type":"Services"
        }
    ],
    "sg:phone":"+61 2 9630 0665",
    "sg:postcode":"2150",
    "sg:province":"NSW",
    "wof:name":"Childhood Friends Parramatta",
    "wof:placetype":"venue"
},
  "geometry": {"coordinates":[150.97708129899999,-33.8416519165],"type":"Point"}
}