{
  "type": "Feature",
  "properties": {
    "iso:country":"AU",
    "sg:address":"7 Carween Ave",
    "sg:city":"Brighton East",
    "sg:classifiers":[
        {
            "category":"Building & Trades",
            "subcategory":"Construction",
            "type":"Services"
        }
    ],
    "sg:phone":"+61 3 9576 7008",
    "sg:postcode":"3187",
    "sg:province":"VIC",
    "sg:tags":[
        "joiner",
        "carpenter"
    ],
    "wof:name":"No Knots Carpentry",
    "wof:placetype":"venue"
},
  "geometry": {"coordinates":[145.02505493199999,-37.9037666321],"type":"Point"}
}