{
  "type": "Feature",
  "properties": {
    "addr:full":"40 Wentworth St Randwick NSW 2031",
    "addr:housenumber":"40",
    "addr:postcode":"2031",
    "addr:street":"Wentworth St",
    "iso:country":"AU",
    "sg:address":"40 Wentworth St",
    "sg:city":"Randwick",
    "sg:classifiers":[
        {
            "category":"Health Services",
            "subcategory":"Medical Lab",
            "type":"Services"
        }
    ],
    "sg:phone":"+61 2 9399 9796",
    "sg:postcode":"2031",
    "sg:province":"NSW",
    "sg:tags":[
        "laboratory",
        "dental"
    ],
    "wof:name":"Swift Dental Labortary",
    "wof:placetype":"venue"
},
  "geometry": {"coordinates":[151.24082946799999,-33.9068641663],"type":"Point"}
}