{
  "type": "Feature",
  "properties": {
    "addr:full":"29 Blanck St Ormeau QLD 4208",
    "addr:housenumber":"29",
    "addr:postcode":"4208",
    "addr:street":"Blanck St",
    "iso:country":"AU",
    "sg:address":"29 Blanck St",
    "sg:city":"Ormeau",
    "sg:classifiers":[
        {
            "category":"Structure",
            "subcategory":"Building",
            "type":"Public Place"
        }
    ],
    "sg:phone":"+61 401 545 434",
    "sg:postcode":"4208",
    "sg:province":"QLD",
    "sg:tags":[
        "sail",
        "shade"
    ],
    "wof:name":"Shadesails4U",
    "wof:placetype":"venue"
},
  "geometry": {"coordinates":[153.25717163100001,-27.7823543549],"type":"Point"}
}