{
  "type": "Feature",
  "properties": {
    "iso:country":"AU",
    "sg:address":"PO Box 46",
    "sg:city":"Duffy",
    "sg:classifiers":[
        {
            "category":"Professional",
            "subcategory":"Employment Agencies",
            "type":"Services"
        }
    ],
    "sg:phone":"+61 2 6287 2582",
    "sg:postcode":"2611",
    "sg:province":"ACT",
    "sg:tags":[
        "theatrical",
        "managers",
        "agent",
        "producer"
    ],
    "wof:name":"BITS Theatre Company",
    "wof:placetype":"venue"
},
  "geometry": {"coordinates":[149.031692505,-35.3368415833],"type":"Point"}
}