{
  "type": "Feature",
  "properties": {
    "iso:country":"AU",
    "sg:address":"Westridge Shopping Centre 300 West St",
    "sg:city":"Toowoomba",
    "sg:classifiers":[
        {
            "category":"Professional",
            "subcategory":"Printing & Photocopies",
            "type":"Services"
        }
    ],
    "sg:phone":"+61 7 4636 0100",
    "sg:postcode":"4350",
    "sg:province":"QLD",
    "sg:tags":[
        "laminating"
    ],
    "wof:name":"Westridge Photos",
    "wof:placetype":"venue"
},
  "geometry": {"coordinates":[151.937164,-27.596003],"type":"Point"}
}