{
  "type": "Feature",
  "properties": {
    "addr:full":"Suite 4 / 101 Scarborough Beach Rd Mt Hawthorn WA 6016",
    "addr:housenumber":"/ 101",
    "addr:postcode":"6016",
    "addr:street":"Scarborough Beach Rd",
    "iso:country":"AU",
    "sg:address":"Suite 4 / 101 Scarborough Beach Rd",
    "sg:city":"Mt Hawthorn",
    "sg:classifiers":[
        {
            "category":"Professional",
            "subcategory":"Employment Agencies",
            "type":"Services"
        }
    ],
    "sg:phone":"+61 8 9201 2222",
    "sg:postcode":"6016",
    "sg:province":"WA",
    "wof:name":"Personnel Access",
    "wof:placetype":"venue"
},
  "geometry": {"coordinates":[115.843971252,-31.9234104156],"type":"Point"}
}