{
  "type": "Feature",
  "properties": {
    "addr:full":"U2/ 61 Derham St Port Melbourne VIC 3207",
    "addr:postcode":"3207",
    "addr:street":"U2 / 61 Derham St",
    "iso:country":"AU",
    "sg:address":"U2/ 61 Derham St",
    "sg:city":"Port Melbourne",
    "sg:classifiers":[
        {
            "category":"Professional",
            "subcategory":"Printing & Photocopies",
            "type":"Services"
        }
    ],
    "sg:phone":"+61 3 9645 1599",
    "sg:postcode":"3207",
    "sg:province":"VIC",
    "sg:tags":[
        "publishing",
        "desktop"
    ],
    "wof:name":"MacWorld Media Pty Ltd",
    "wof:placetype":"venue"
},
  "geometry": {"coordinates":[144.940979,-37.832001],"type":"Point"}
}