{
  "type": "Feature",
  "properties": {
    "addr:full":"19 Shirlow St Marrickville NSW 2204",
    "addr:housenumber":"19",
    "addr:postcode":"2204",
    "addr:street":"Shirlow St",
    "iso:country":"AU",
    "sg:address":"19 Shirlow St",
    "sg:city":"Marrickville",
    "sg:classifiers":[
        {
            "category":"Utilities",
            "type":"Services"
        }
    ],
    "sg:phone":"+61 2 9565 1570",
    "sg:postcode":"2204",
    "sg:province":"NSW",
    "sg:tags":[
        "refrigeration",
        "industrial",
        "commercial",
        "retail"
    ],
    "wof:name":"Air Cond Refrigeration Pty Ltd",
    "wof:placetype":"venue"
},
  "geometry": {"coordinates":[151.16691599999999,-33.91172],"type":"Point"}
}