{
  "type": "Feature",
  "properties": {
    "addr:full":"189 Old Cleveland Rd Capalaba QLD 4157",
    "addr:housenumber":"189",
    "addr:postcode":"4157",
    "addr:street":"Old Cleveland Rd",
    "iso:country":"AU",
    "sg:address":"189 Old Cleveland Rd",
    "sg:city":"Capalaba",
    "sg:classifiers":[
        {
            "category":"Health Services",
            "subcategory":"Doctor",
            "type":"Services"
        }
    ],
    "sg:phone":"+61 7 3245 9600",
    "sg:postcode":"4157",
    "sg:province":"QLD",
    "sg:tags":[
        "medical",
        "practitioner"
    ],
    "wof:name":"Lai Kim",
    "wof:placetype":"venue"
},
  "geometry": {"coordinates":[153.19926452600001,-27.5216598511],"type":"Point"}
}