{
  "type": "Feature",
  "properties": {
    "addr:full":"Flynn Creek Rd Rosedale VIC 3847",
    "addr:postcode":"3847",
    "addr:street":"Creek Rd",
    "iso:country":"AU",
    "sg:address":"Flynn Creek Rd",
    "sg:city":"Rosedale",
    "sg:classifiers":[
        {
            "category":"Shopping",
            "subcategory":"Musical Instruments",
            "type":"Retail Goods"
        }
    ],
    "sg:phone":"+61 3 5199 2888",
    "sg:postcode":"3847",
    "sg:province":"VIC",
    "sg:tags":[
        "musician",
        "agent"
    ],
    "wof:name":"Astral Entertainment Agency",
    "wof:placetype":"venue"
},
  "geometry": {"coordinates":[146.78872680699999,-38.1552581787],"type":"Point"}
}