{
  "type": "Feature",
  "properties": {
    "addr:full":"53 Wood St Warwick QLD 4370",
    "addr:housenumber":"53",
    "addr:postcode":"4370",
    "addr:street":"Wood St",
    "iso:country":"AU",
    "sg:address":"53 Wood St",
    "sg:city":"Warwick",
    "sg:classifiers":[
        {
            "category":"Health Services",
            "subcategory":"Doctor",
            "type":"Services"
        }
    ],
    "sg:phone":"+61 7 4666 9666",
    "sg:postcode":"4370",
    "sg:province":"QLD",
    "sg:tags":[
        "medical",
        "practitioner"
    ],
    "wof:name":"Geisel Leith Dr",
    "wof:placetype":"venue"
},
  "geometry": {"coordinates":[152.035324097,-28.2209663391],"type":"Point"}
}