{
  "type": "Feature",
  "properties": {
    "iso:country":"AU",
    "sg:address":"Brownsville Ave",
    "sg:city":"Brownsville",
    "sg:classifiers":[
        {
            "category":"Government",
            "subcategory":"Post Office",
            "type":"Public Place"
        }
    ],
    "sg:phone":"+61 2 4261 1390",
    "sg:postcode":"2530",
    "sg:province":"NSW",
    "sg:tags":[
        "postal"
    ],
    "wof:name":"Australia Post",
    "wof:placetype":"venue"
},
  "geometry": {"coordinates":[150.80595398,-34.4819984436],"type":"Point"}
}