{
  "type": "Feature",
  "properties": {
    "iso:country":"AU",
    "sg:address":"5 Millers Rd",
    "sg:city":"Wingfield",
    "sg:classifiers":[
        {
            "category":"Wholesale",
            "subcategory":"Auto Parts",
            "type":"Manufacturing & Wholesale Goods"
        }
    ],
    "sg:phone":"+61 8 8243 0098",
    "sg:postcode":"5013",
    "sg:province":"SA",
    "sg:tags":[
        "recyclers"
    ],
    "wof:name":"Cheap Motor Wreckers",
    "wof:placetype":"venue"
},
  "geometry": {"coordinates":[138.55909729000001,-34.8384170532],"type":"Point"}
}