{
  "type": "Feature",
  "properties": {
    "addr:full":"GPO Box 1345 Sydney NSW 2001",
    "addr:postcode":"2001",
    "iso:country":"AU",
    "sg:address":"GPO Box 1345",
    "sg:city":"Sydney",
    "sg:classifiers":[
        {
            "category":"Professional",
            "subcategory":"Computer Services",
            "type":"Services"
        }
    ],
    "sg:phone":"+61 419 290 524",
    "sg:postcode":"2001",
    "sg:province":"NSW",
    "sg:tags":[
        "consultant",
        "system"
    ],
    "wof:name":"AIT Consultancy Pty Ltd",
    "wof:placetype":"venue"
},
  "geometry": {"coordinates":[151.207107544,-33.8671417236],"type":"Point"}
}