{
  "type": "Feature",
  "properties": {
    "addr:full":"75 Junction St Nowra NSW 2541",
    "addr:housenumber":"75",
    "addr:postcode":"2541",
    "addr:street":"Junction St",
    "iso:country":"AU",
    "sg:address":"75 Junction St",
    "sg:city":"Nowra",
    "sg:classifiers":[
        {
            "category":"Shopping",
            "subcategory":"Discount & Variety Stores",
            "type":"Retail Goods"
        }
    ],
    "sg:phone":"+61 2 4422 3522",
    "sg:postcode":"2541",
    "sg:province":"NSW",
    "sg:tags":[
        "shop",
        "adult"
    ],
    "wof:name":"The Condomerie",
    "wof:placetype":"venue"
},
  "geometry": {"coordinates":[150.600875855,-34.8741645813],"type":"Point"}
}