{
  "type": "Feature",
  "properties": {
    "addr:full":"Factory 7- 63 Bayfield Rd Bayswater North VIC 3153",
    "addr:housenumber":"63",
    "addr:postcode":"3153",
    "addr:street":"Bayfield Rd",
    "iso:country":"AU",
    "sg:address":"Factory 7- 63 Bayfield Rd",
    "sg:city":"Bayswater North",
    "sg:classifiers":[
        {
            "category":"Utilities",
            "subcategory":"Electric",
            "type":"Services"
        }
    ],
    "sg:phone":"+61 3 9729 1554",
    "sg:postcode":"3153",
    "sg:province":"VIC",
    "sg:tags":[
        "electrical",
        "contractor"
    ],
    "wof:name":"Master Electrics",
    "wof:placetype":"venue"
},
  "geometry": {"coordinates":[145.275665283,-37.8238525391],"type":"Point"}
}