{
  "type": "Feature",
  "properties": {
    "iso:country":"AU",
    "sg:address":"PO Box 4898",
    "sg:city":"Sunshine Coast Mail Centre",
    "sg:classifiers":[
        {
            "category":"Food & Beverages",
            "subcategory":"Specialty",
            "type":"Retail Goods"
        }
    ],
    "sg:phone":"+61 7 5442 3343",
    "sg:postcode":"4560",
    "sg:province":"QLD",
    "sg:tags":[
        "product",
        "health"
    ],
    "wof:name":"Herbalife Ind. Distributer",
    "wof:placetype":"venue"
},
  "geometry": {"coordinates":[152.949752808,-26.621389389],"type":"Point"}
}