{
  "type": "Feature",
  "properties": {
    "addr:full":"2 Chidley Pl Rockingham WA 6168",
    "addr:housenumber":"2",
    "addr:postcode":"6168",
    "addr:street":"Chidley Pl",
    "iso:country":"AU",
    "sg:address":"2 Chidley Pl",
    "sg:city":"Rockingham",
    "sg:classifiers":[
        {
            "category":"Autos & Motor Vehicles",
            "subcategory":"Auto Supplies",
            "type":"Retail Goods"
        }
    ],
    "sg:phone":"+61 8 9528 1145",
    "sg:postcode":"6168",
    "sg:province":"WA",
    "sg:tags":[
        "wheel",
        "four",
        "equipment",
        "drive",
        "accessory"
    ],
    "wof:name":"Autokwip Industries",
    "wof:placetype":"venue"
},
  "geometry": {"coordinates":[115.730766,-32.290085],"type":"Point"}
}