{
  "type": "Feature",
  "properties": {
    "iso:country":"AU",
    "sg:address":"PO Box 162",
    "sg:city":"Galston",
    "sg:classifiers":[
        {
            "category":"Building & Trades",
            "subcategory":"Construction",
            "type":"Services"
        }
    ],
    "sg:phone":"+61 2 9653 2092",
    "sg:postcode":"2159",
    "sg:province":"NSW",
    "sg:tags":[
        "contractor"
    ],
    "wof:name":"Livingstone Murray & Associates",
    "wof:placetype":"venue"
},
  "geometry": {"coordinates":[151.045013428,-33.6529197693],"type":"Point"}
}