{
  "type": "Feature",
  "properties": {
    "iso:country":"AU",
    "sg:address":"7 Hunter St",
    "sg:city":"Stuart",
    "sg:classifiers":[
        {
            "category":"Building & Trades",
            "subcategory":"Landscaping Services",
            "type":"Services"
        }
    ],
    "sg:phone":"+61 7 4778 2331",
    "sg:postcode":"4811",
    "sg:province":"QLD",
    "sg:tags":[
        "firebreak",
        "clearing",
        "land",
        "contractor"
    ],
    "wof:name":"Civilquip Earthmovers",
    "wof:placetype":"venue"
},
  "geometry": {"coordinates":[146.85249300000001,-19.338791],"type":"Point"}
}