{
  "type": "Feature",
  "properties": {
    "iso:country":"AU",
    "sg:address":"67 Canning Rd",
    "sg:city":"Kalamunda",
    "sg:classifiers":[
        {
            "category":"Professional",
            "subcategory":"Accounting & Tax Preparation",
            "type":"Services"
        }
    ],
    "sg:phone":"+61 8 9293 3044",
    "sg:postcode":"6076",
    "sg:province":"WA",
    "sg:tags":[
        "accountant",
        "auditor"
    ],
    "wof:name":"Thornburys Accountants & Advisors",
    "wof:placetype":"venue"
},
  "geometry": {"coordinates":[116.09796905499999,-32.0293426514],"type":"Point"}
}