{
  "type": "Feature",
  "properties": {
    "addr:full":"19 Taylor St Albion QLD 4010",
    "addr:housenumber":"19",
    "addr:postcode":"4010",
    "addr:street":"Taylor St",
    "iso:country":"AU",
    "sg:address":"19 Taylor St",
    "sg:city":"Albion",
    "sg:classifiers":[
        {
            "category":"Retail",
            "subcategory":"Auto Repair",
            "type":"Services"
        }
    ],
    "sg:phone":"+61 7 3852 2700",
    "sg:postcode":"4010",
    "sg:province":"QLD",
    "sg:tags":[
        "recapping",
        "repairing",
        "retreading",
        "tyre"
    ],
    "wof:name":"Tyrepower",
    "wof:placetype":"venue"
},
  "geometry": {"coordinates":[153.041671753,-27.4345436096],"type":"Point"}
}