{
  "type": "Feature",
  "properties": {
    "addr:full":"Scotts Rd Bororen QLD 4678",
    "addr:postcode":"4678",
    "addr:street":"Scotts Rd",
    "iso:country":"AU",
    "sg:address":"Scotts Rd",
    "sg:city":"Bororen",
    "sg:classifiers":[
        {
            "category":"Communications",
            "subcategory":"News Services",
            "type":"Services"
        }
    ],
    "sg:phone":"+61 7 4974 4190",
    "sg:postcode":"4678",
    "sg:province":"QLD",
    "sg:tags":[
        "information",
        "tourist",
        "attractions"
    ],
    "wof:name":"Dragonhall",
    "wof:placetype":"venue"
},
  "geometry": {"coordinates":[151.50636299999999,-24.264189],"type":"Point"}
}