{
  "type": "Feature",
  "properties": {
    "addr:full":"Factory 8, 10- 14 Simms Rd Greensborough VIC 3088",
    "addr:housenumber":"10 14",
    "addr:postcode":"3088",
    "addr:street":"Simms Rd",
    "iso:country":"AU",
    "sg:address":"Factory 8, 10- 14 Simms Rd",
    "sg:city":"Greensborough",
    "sg:classifiers":[
        {
            "category":"Utilities",
            "subcategory":"Electric",
            "type":"Services"
        }
    ],
    "sg:phone":"+61 3 9434 6422",
    "sg:postcode":"3088",
    "sg:province":"VIC",
    "sg:tags":[
        "electrical",
        "contractor"
    ],
    "wof:name":"Hilite Electrics Pty Ltd",
    "wof:placetype":"venue"
},
  "geometry": {"coordinates":[145.11317443900001,-37.7117118835],"type":"Point"}
}