{
  "type": "Feature",
  "properties": {
    "iso:country":"AU",
    "sg:address":"37 Kinglock Pde",
    "sg:city":"Wantirna",
    "sg:classifiers":[
        {
            "category":"Professional",
            "subcategory":"Art Services",
            "type":"Services"
        }
    ],
    "sg:phone":"+61 3 9729 1120",
    "sg:postcode":"3152",
    "sg:province":"VIC",
    "sg:tags":[
        "graphic",
        "designer"
    ],
    "wof:name":"Moses Tan Photography",
    "wof:placetype":"venue"
},
  "geometry": {"coordinates":[145.23809814399999,-37.8480606079],"type":"Point"}
}