{
  "type": "Feature",
  "properties": {
    "addr:full":"91 Carrington Rd Waverley NSW 2024",
    "addr:housenumber":"91",
    "addr:postcode":"2024",
    "addr:street":"Carrington Rd",
    "iso:country":"AU",
    "sg:address":"91 Carrington Rd",
    "sg:city":"Waverley",
    "sg:classifiers":[
        {
            "category":"Home & Garden",
            "subcategory":"Carpets & Floor Coverings",
            "type":"Retail Goods"
        }
    ],
    "sg:phone":"+61 2 9388 0842",
    "sg:postcode":"2024",
    "sg:province":"NSW",
    "wof:name":"Carpet Image",
    "wof:placetype":"venue"
},
  "geometry": {"coordinates":[151.25340270999999,-33.9006652832],"type":"Point"}
}