{
  "type": "Feature",
  "properties": {
    "iso:country":"AU",
    "sg:address":"Clare Medical Centre 41 Old North Road",
    "sg:city":"Clare",
    "sg:classifiers":[
        {
            "category":"Health Services",
            "subcategory":"Health Practitioner",
            "type":"Services"
        }
    ],
    "sg:phone":"+61 1300 734 866",
    "sg:postcode":"5453",
    "sg:province":"SA",
    "sg:tags":[
        "audiologists"
    ],
    "wof:name":"Ron Kendall",
    "wof:placetype":"venue"
},
  "geometry": {"coordinates":[138.61149599999999,-33.83197],"type":"Point"}
}