{
  "type": "Feature",
  "properties": {
    "addr:full":"Shop 1018, Australia Fair, Marine Parade Southport QLD 4215",
    "addr:postcode":"1018;4215",
    "addr:street":"Marine Parade",
    "iso:country":"AU",
    "sg:address":"Shop 1018, Australia Fair, Marine Parade",
    "sg:city":"Southport",
    "sg:classifiers":[
        {
            "category":"Wholesale",
            "subcategory":"Medical Equipment & Supplies",
            "type":"Manufacturing & Wholesale Goods"
        }
    ],
    "sg:phone":"+61 7 5532 5760",
    "sg:postcode":"4215",
    "sg:province":"QLD",
    "sg:tags":[
        "aids",
        "hearing"
    ],
    "wof:name":"National Hearing Care",
    "wof:placetype":"venue"
},
  "geometry": {"coordinates":[153.41558837900001,-27.9655361176],"type":"Point"}
}