{
  "type": "Feature",
  "properties": {
    "addr:full":"71 Wright St East Devonport TAS 7310",
    "addr:housenumber":"71",
    "addr:postcode":"7310",
    "addr:street":"Wright St East",
    "iso:country":"AU",
    "sg:address":"71 Wright St",
    "sg:city":"East Devonport",
    "sg:classifiers":[
        {
            "category":"Farming",
            "subcategory":"Vineyard",
            "type":"Manufacturing & Wholesale Goods"
        }
    ],
    "sg:phone":"+61 3 6427 0477",
    "sg:postcode":"7310",
    "sg:province":"TAS",
    "sg:tags":[
        "winery"
    ],
    "wof:name":"Gingerbread House Cafe",
    "wof:placetype":"venue"
},
  "geometry": {"coordinates":[146.370437622,-41.1799850464],"type":"Point"}
}