{
  "type": "Feature",
  "properties": {
    "addr:full":"69 Holbeche Rd Arndell Park NSW 2148",
    "addr:housenumber":"69",
    "addr:postcode":"2148",
    "addr:street":"Holbeche Rd",
    "iso:country":"AU",
    "sg:address":"69 Holbeche Rd",
    "sg:city":"Arndell Park",
    "sg:classifiers":[
        {
            "category":"Health Services",
            "subcategory":"Health Practitioner",
            "type":"Services"
        }
    ],
    "sg:phone":"+61 2 9622 0106",
    "sg:postcode":"2148",
    "sg:province":"NSW",
    "sg:tags":[
        "physiotherapist"
    ],
    "wof:name":"Precision Physio",
    "wof:placetype":"venue"
},
  "geometry": {"coordinates":[150.88182067899999,-33.7884178162],"type":"Point"}
}