{
  "type": "Feature",
  "properties": {
    "addr:full":"126 Gladstone St Mudgee NSW 2850",
    "addr:housenumber":"126",
    "addr:postcode":"2850",
    "addr:street":"Gladstone St",
    "iso:country":"AU",
    "sg:address":"126 Gladstone St",
    "sg:city":"Mudgee",
    "sg:classifiers":[
        {
            "category":"Retail",
            "subcategory":"Auto Repair",
            "type":"Services"
        }
    ],
    "sg:phone":"+61 2 6372 2542",
    "sg:postcode":"2850",
    "sg:province":"NSW",
    "sg:tags":[
        "repairer",
        "motor",
        "engineer"
    ],
    "wof:name":"Gladstone Street Mechanical Repairs",
    "wof:placetype":"venue"
},
  "geometry": {"coordinates":[149.578247,-32.593742],"type":"Point"}
}