{
  "type": "Feature",
  "properties": {
    "iso:country":"AU",
    "sg:address":"14 Elizabeth St",
    "sg:city":"Coffs Harbour",
    "sg:classifiers":[
        {
            "category":"Travel",
            "subcategory":"Hotels & Motels",
            "type":"Entertainment"
        }
    ],
    "sg:phone":"+61 2 6652 4655",
    "sg:postcode":"2450",
    "sg:province":"NSW",
    "wof:name":"Best Western Parkside Motor Inn",
    "wof:placetype":"venue"
},
  "geometry": {"coordinates":[153.11103800000001,-30.299295],"type":"Point"}
}