{
  "type": "Feature",
  "properties": {
    "addr:full":"128 Eleventh St Mildura VIC 3500",
    "addr:housenumber":"128",
    "addr:postcode":"3500",
    "addr:street":"Eleventh St",
    "iso:country":"AU",
    "sg:address":"128 Eleventh St",
    "sg:city":"Mildura",
    "sg:classifiers":[
        {
            "category":"Home & Garden",
            "subcategory":"Carpets & Floor Coverings",
            "type":"Retail Goods"
        }
    ],
    "sg:phone":"+61 3 5023 6366",
    "sg:postcode":"3500",
    "sg:province":"VIC",
    "sg:tags":[
        "tile",
        "wall"
    ],
    "wof:name":"David Berry Tiling",
    "wof:placetype":"venue"
},
  "geometry": {"coordinates":[142.16682434099999,-34.1971588135],"type":"Point"}
}