{
  "type": "Feature",
  "properties": {
    "iso:country":"AU",
    "sg:address":"3 Greenslade St",
    "sg:city":"Hamilton Hill",
    "sg:classifiers":[
        {
            "category":"Food & Beverages",
            "subcategory":"Fruits & Vegetables",
            "type":"Retail Goods"
        }
    ],
    "sg:phone":"+61 8 9337 6467",
    "sg:postcode":"6163",
    "sg:province":"WA",
    "sg:tags":[
        "wholesale"
    ],
    "wof:name":"Sunripe Fruit And Vegetables Delivery",
    "wof:placetype":"venue"
},
  "geometry": {"coordinates":[115.788063,-32.075043],"type":"Point"}
}