{
  "type": "Feature",
  "properties": {
    "addr:full":"8 Birch Ave Dandenong North VIC 3175",
    "addr:housenumber":"8",
    "addr:postcode":"3175",
    "addr:street":"Birch Ave",
    "iso:country":"AU",
    "sg:address":"8 Birch Ave",
    "sg:city":"Dandenong North",
    "sg:classifiers":[
        {
            "category":"Professional",
            "subcategory":"Engineering",
            "type":"Services"
        }
    ],
    "sg:phone":"+61 3 9701 0075",
    "sg:postcode":"3175",
    "sg:province":"VIC",
    "sg:tags":[
        "electrical",
        "engineer"
    ],
    "wof:name":"Integrated Automation Pty Ltd",
    "wof:placetype":"venue"
},
  "geometry": {"coordinates":[145.20469665499999,-37.9638404846],"type":"Point"}
}