{
  "type": "Feature",
  "properties": {
    "iso:country":"AU",
    "sg:address":"Frankston Executive Centre, Suite 1, 40 Young St",
    "sg:city":"Frankston",
    "sg:classifiers":[
        {
            "category":"Organizations",
            "subcategory":"Professional Association",
            "type":"Services"
        }
    ],
    "sg:phone":"+61 408 344 125",
    "sg:postcode":"3199",
    "sg:province":"VIC",
    "sg:tags":[
        "web",
        "internet"
    ],
    "wof:name":"Basil Creative",
    "wof:placetype":"venue"
},
  "geometry": {"coordinates":[144.99468994099999,-37.8655471802],"type":"Point"}
}