{
  "type": "Feature",
  "properties": {
    "addr:full":"58 John St Salisbury SA 5108",
    "addr:housenumber":"58",
    "addr:postcode":"5108",
    "addr:street":"John St",
    "iso:country":"AU",
    "sg:address":"58 John St",
    "sg:city":"Salisbury",
    "sg:classifiers":[
        {
            "category":"Real Estate",
            "subcategory":"Real Estate Agent",
            "type":"Services"
        }
    ],
    "sg:phone":"+61 8 8285 4777",
    "sg:postcode":"5108",
    "sg:province":"SA",
    "wof:name":"Brock Harcourts",
    "wof:placetype":"venue"
},
  "geometry": {"coordinates":[138.64508056599999,-34.762298584],"type":"Point"}
}