{
  "type": "Feature",
  "properties": {
    "addr:full":"26 Ferrier Rd Narangba QLD 4504",
    "addr:housenumber":"26",
    "addr:postcode":"4504",
    "addr:street":"Ferrier Rd",
    "iso:country":"AU",
    "sg:address":"26 Ferrier Rd",
    "sg:city":"Narangba",
    "sg:classifiers":[
        {
            "category":"Retail",
            "subcategory":"Auto Repair",
            "type":"Services"
        }
    ],
    "sg:phone":"+61 7 3888 0119",
    "sg:postcode":"4504",
    "sg:province":"QLD",
    "sg:tags":[
        "repairer",
        "motor",
        "engineer"
    ],
    "wof:name":"John Briggs Automotives",
    "wof:placetype":"venue"
},
  "geometry": {"coordinates":[152.97723388700001,-27.2050628662],"type":"Point"}
}