{
  "type": "Feature",
  "properties": {
    "iso:country":"AU",
    "sg:address":"7 Faull St",
    "sg:city":"Parkes",
    "sg:classifiers":[
        {
            "category":"Building & Trades",
            "subcategory":"Construction",
            "type":"Services"
        }
    ],
    "sg:phone":"+61 2 6862 5021",
    "sg:postcode":"2870",
    "sg:province":"NSW",
    "sg:tags":[
        "repair",
        "maintenance",
        "contractor"
    ],
    "wof:name":"Need A Man Handy Service",
    "wof:placetype":"venue"
},
  "geometry": {"coordinates":[148.178146,-33.146549],"type":"Point"}
}