{
  "type": "Feature",
  "properties": {
    "iso:country":"AU",
    "sg:address":"Shop 7, Boulevard Shopping Centre, 31 Gayton Rd",
    "sg:city":"City Beach",
    "sg:classifiers":[
        {
            "category":"Personal",
            "subcategory":"Beauty Salon",
            "type":"Services"
        }
    ],
    "sg:phone":"+61 8 9385 7371",
    "sg:postcode":"6015",
    "sg:province":"WA",
    "wof:name":"Boulevard Skin & Beauty Centre",
    "wof:placetype":"venue"
},
  "geometry": {"coordinates":[115.761711121,-31.9337806702],"type":"Point"}
}