{
  "type": "Feature",
  "properties": {
    "iso:country":"AU",
    "sg:address":"Shop 4 519 Portrush Rd",
    "sg:city":"Glenunga",
    "sg:classifiers":[
        {
            "category":"Personal",
            "subcategory":"Beauty Salon",
            "type":"Services"
        }
    ],
    "sg:phone":"+61 8 8338 3626",
    "sg:postcode":"5064",
    "sg:province":"SA",
    "wof:name":"Irresistible Nails And Beauty",
    "wof:placetype":"venue"
},
  "geometry": {"coordinates":[138.64295959500001,-34.9480781555],"type":"Point"}
}