{
  "type": "Feature",
  "properties": {
    "addr:full":"28 Pottery Rd Lenah Valley TAS 7008",
    "addr:housenumber":"28",
    "addr:postcode":"7008",
    "addr:street":"Pottery Rd",
    "iso:country":"AU",
    "sg:address":"28 Pottery Rd",
    "sg:city":"Lenah Valley",
    "sg:classifiers":[
        {
            "category":"Health Services",
            "subcategory":"Health Practitioner",
            "type":"Services"
        }
    ],
    "sg:phone":"+61 411 389 811",
    "sg:postcode":"7008",
    "sg:province":"TAS",
    "sg:tags":[
        "naturopath"
    ],
    "wof:name":"Mariangela Parodi",
    "wof:placetype":"venue"
},
  "geometry": {"coordinates":[147.28895568900001,-42.8655700684],"type":"Point"}
}