{
  "type": "Feature",
  "properties": {
    "addr:full":"Shop 2 Big W Development Ford St Wangaratta VIC 3676",
    "addr:housenumber":"shop 2",
    "addr:postcode":"3676",
    "addr:street":"Big W Development Ford St",
    "iso:country":"AU",
    "sg:address":"Shop 2 Big W Development Ford St",
    "sg:city":"Wangaratta",
    "sg:classifiers":[
        {
            "category":"Shopping",
            "subcategory":"Mobile Phones",
            "type":"Retail Goods"
        }
    ],
    "sg:phone":"+61 3 5722 3822",
    "sg:postcode":"3676",
    "sg:province":"VIC",
    "sg:tags":[
        "telephone",
        "accessory"
    ],
    "wof:name":"Into Mobiles Pty Ltd",
    "wof:placetype":"venue"
},
  "geometry": {"coordinates":[146.32371499999999,-36.355743],"type":"Point"}
}