{
  "type": "Feature",
  "properties": {
    "iso:country":"AU",
    "sg:address":"8 Redhead St",
    "sg:city":"Doolandella",
    "sg:classifiers":[
        {
            "category":"Farming",
            "subcategory":"Livestock Farm",
            "type":"Manufacturing & Wholesale Goods"
        }
    ],
    "sg:phone":"+61 7 3372 2316",
    "sg:postcode":"4077",
    "sg:province":"QLD",
    "sg:tags":[
        "breeder",
        "horse",
        "stud"
    ],
    "wof:name":"M.G.S. Equine Investments",
    "wof:placetype":"venue"
},
  "geometry": {"coordinates":[152.985305786,-27.6160182953],"type":"Point"}
}