{
  "type": "Feature",
  "properties": {
    "addr:full":"15a Bailey Ave Keilor East VIC 3033",
    "addr:housenumber":"15a",
    "addr:postcode":"3033",
    "addr:street":"Bailey Ave",
    "iso:country":"AU",
    "sg:address":"15a Bailey Ave",
    "sg:city":"Keilor East",
    "sg:classifiers":[
        {
            "category":"Professional",
            "subcategory":"Accounting & Tax Preparation",
            "type":"Services"
        }
    ],
    "sg:phone":"+61 3 9331 7694",
    "sg:postcode":"3033",
    "sg:province":"VIC",
    "sg:tags":[
        "bookkeeping"
    ],
    "wof:name":"K B Bookkeeping Enterprises",
    "wof:placetype":"venue"
},
  "geometry": {"coordinates":[144.85888700000001,-37.730671],"type":"Point"}
}