{
  "type": "Feature",
  "properties": {
    "addr:full":"Cnr Princess Highway & Orange Grove Ave Unanderra NSW 2526",
    "addr:postcode":"2526",
    "addr:street":"Princess Highway & Orange Grove Ave",
    "iso:country":"AU",
    "sg:address":"Cnr Princess Highway & Orange Grove Ave",
    "sg:city":"Unanderra",
    "sg:classifiers":[
        {
            "category":"Autos & Motor Vehicles",
            "subcategory":"Auto Supplies",
            "type":"Retail Goods"
        }
    ],
    "sg:phone":"+61 2 4271 1811",
    "sg:postcode":"2526",
    "sg:province":"NSW",
    "sg:tags":[
        "equipment",
        "part",
        "truck"
    ],
    "wof:name":"South Coast Truck Sales & Spares Pty Ltd",
    "wof:placetype":"venue"
},
  "geometry": {"coordinates":[150.84356689399999,-34.4509315491],"type":"Point"}
}