{
  "type": "Feature",
  "properties": {
    "addr:full":"93 Konkerberry Drv Kununurra WA 6743",
    "addr:housenumber":"93",
    "addr:postcode":"6743",
    "addr:street":"Konkerberry Drv",
    "iso:country":"AU",
    "sg:address":"93 Konkerberry Drv",
    "sg:city":"Kununurra",
    "sg:classifiers":[
        {
            "category":"Arts & Performance",
            "subcategory":"Art Gallery",
            "type":"Entertainment"
        }
    ],
    "sg:phone":"+61 8 9169 1133",
    "sg:postcode":"6743",
    "sg:province":"WA",
    "wof:name":"Kimberley Fine Diamonds",
    "wof:placetype":"venue"
},
  "geometry": {"coordinates":[128.739746094,-15.7747869492],"type":"Point"}
}