{
  "type": "Feature",
  "properties": {
    "iso:country":"AU",
    "sg:address":"221 Church St",
    "sg:city":"Cowes",
    "sg:classifiers":[
        {
            "category":"Building & Trades",
            "subcategory":"Equipment Rental",
            "type":"Services"
        }
    ],
    "sg:phone":"+61 3 5952 2131",
    "sg:postcode":"3922",
    "sg:province":"VIC",
    "sg:tags":[
        "party",
        "hire"
    ],
    "wof:name":"Martins Party Hire",
    "wof:placetype":"venue"
},
  "geometry": {"coordinates":[145.22291564899999,-38.4524459839],"type":"Point"}
}