{
  "type": "Feature",
  "properties": {
    "addr:full":"Shop 4/ 18 Main Rd Huonville TAS 7109",
    "addr:housenumber":"shop 4 / 18",
    "addr:postcode":"7109",
    "addr:street":"Main Rd",
    "iso:country":"AU",
    "sg:address":"Shop 4/ 18 Main Rd",
    "sg:city":"Huonville",
    "sg:classifiers":[
        {
            "category":"Personal",
            "subcategory":"Beauty Salon",
            "type":"Services"
        }
    ],
    "sg:phone":"+61 3 6264 2285",
    "sg:postcode":"7109",
    "sg:province":"TAS",
    "wof:name":"Star Anise Beauty Therapy",
    "wof:placetype":"venue"
},
  "geometry": {"coordinates":[147.04818725600001,-43.0315513611],"type":"Point"}
}