{
  "type": "Feature",
  "properties": {
    "addr:full":"5 / 31 Thompson St Victoria Point QLD 4165",
    "addr:housenumber":"/ 31",
    "addr:postcode":"4165",
    "addr:street":"Thompson St",
    "iso:country":"AU",
    "sg:address":"5 / 31 Thompson St",
    "sg:city":"Victoria Point",
    "sg:classifiers":[
        {
            "category":"Education",
            "subcategory":"Music School",
            "type":"Public Place"
        }
    ],
    "sg:phone":"+61 7 3207 7222",
    "sg:postcode":"4165",
    "sg:province":"QLD",
    "sg:tags":[
        "choir",
        "bands",
        "orchestra"
    ],
    "wof:name":"Swing Fever Big Band",
    "wof:placetype":"venue"
},
  "geometry": {"coordinates":[153.30950927699999,-27.588640213],"type":"Point"}
}