{
  "type": "Feature",
  "properties": {
    "addr:full":"Derrimut Rd Werribee VIC 3030",
    "addr:postcode":"3030",
    "addr:street":"Derrimut Rd",
    "iso:country":"AU",
    "sg:address":"Derrimut Rd",
    "sg:city":"Werribee",
    "sg:classifiers":[
        {
            "category":"Food & Beverages",
            "subcategory":"Supermarket",
            "type":"Retail Goods"
        }
    ],
    "sg:phone":"+61 3 9748 4631",
    "sg:postcode":"3030",
    "sg:province":"VIC",
    "sg:tags":[
        "grocery",
        "store"
    ],
    "wof:name":"Safeway",
    "wof:placetype":"venue"
},
  "geometry": {"coordinates":[144.68042,-37.893932],"type":"Point"}
}