{
  "type": "Feature",
  "properties": {
    "iso:country":"AU",
    "sg:address":"401 Little Bourke St",
    "sg:city":"Melbourne",
    "sg:classifiers":[
        {
            "category":"Bars & Pubs",
            "subcategory":"Nightclub",
            "type":"Food & Drink"
        }
    ],
    "sg:phone":"+61 3 9670 4020",
    "sg:postcode":"3000",
    "sg:province":"VIC",
    "sg:tags":[
        "discotheque"
    ],
    "wof:name":"The Apartment Restaurant Club Lounge",
    "wof:placetype":"venue"
},
  "geometry": {"coordinates":[144.961013794,-37.8138885498],"type":"Point"}
}