{
  "type": "Feature",
  "properties": {
    "addr:full":"53 Anderson Rd Mortdale NSW 2223",
    "addr:housenumber":"53",
    "addr:postcode":"2223",
    "addr:street":"Anderson Rd",
    "iso:country":"AU",
    "sg:address":"53 Anderson Rd",
    "sg:city":"Mortdale",
    "sg:classifiers":[
        {
            "category":"Fast Food",
            "type":"Food & Drink"
        }
    ],
    "sg:phone":"+61 2 9533 9100",
    "sg:postcode":"2223",
    "sg:province":"NSW",
    "sg:tags":[
        "away",
        "take"
    ],
    "wof:name":"Mortdale Sandwich Shack",
    "wof:placetype":"venue"
},
  "geometry": {"coordinates":[151.066314697,-33.967590332],"type":"Point"}
}