{
  "type": "Feature",
  "properties": {
    "addr:full":"PO Box 1763 Wangara WA 6947",
    "addr:postcode":"6947",
    "iso:country":"AU",
    "sg:address":"PO Box 1763",
    "sg:city":"Wangara",
    "sg:classifiers":[
        {
            "category":"Banks & Credit Unions",
            "subcategory":"Financial Services",
            "type":"Services"
        }
    ],
    "sg:phone":"+61 8 9408 1373",
    "sg:postcode":"6947",
    "sg:province":"WA",
    "sg:tags":[
        "surge",
        "protection",
        "lightning"
    ],
    "wof:name":"A & P Power Distributors",
    "wof:placetype":"venue"
},
  "geometry": {"coordinates":[115.83036041299999,-31.7966709137],"type":"Point"}
}