{
  "type": "Feature",
  "properties": {
    "addr:full":"PO Box 42 Cairns North QLD 4870",
    "addr:postcode":"4870",
    "iso:country":"AU",
    "sg:address":"PO Box 42",
    "sg:city":"Cairns North",
    "sg:classifiers":[
        {
            "category":"Airline",
            "type":"Transportation"
        }
    ],
    "sg:phone":"+61 427 504 340",
    "sg:postcode":"4870",
    "sg:province":"QLD",
    "sg:tags":[
        "aircraft",
        "rental",
        "charter"
    ],
    "wof:name":"Queensland Aviation Services",
    "wof:placetype":"venue"
},
  "geometry": {"coordinates":[145.759002686,-16.9041805267],"type":"Point"}
}