{
  "type": "Feature",
  "properties": {
    "addr:full":"6 Watson Crt Toorington Toowoomba QLD 4350",
    "addr:housenumber":"6",
    "addr:postcode":"4350",
    "addr:street":"Watson Crt Toorington",
    "iso:country":"AU",
    "sg:address":"6 Watson Crt Toorington",
    "sg:city":"Toowoomba",
    "sg:classifiers":[
        {
            "category":"Manufacturing",
            "subcategory":"Tools & Machinery",
            "type":"Manufacturing & Wholesale Goods"
        }
    ],
    "sg:phone":"+61 7 4634 2000",
    "sg:postcode":"4350",
    "sg:province":"QLD",
    "sg:tags":[
        "earth",
        "excavating",
        "moving",
        "equipment"
    ],
    "wof:name":"Deaf Jeff's Cat Bits",
    "wof:placetype":"venue"
},
  "geometry": {"coordinates":[151.90020799999999,-27.547588],"type":"Point"}
}