{
  "type": "Feature",
  "properties": {
    "addr:full":"586 Main St Mordialloc VIC 3195",
    "addr:housenumber":"586",
    "addr:postcode":"3195",
    "addr:street":"Main St",
    "iso:country":"AU",
    "sg:address":"586 Main St",
    "sg:city":"Mordialloc",
    "sg:classifiers":[
        {
            "category":"Real Estate",
            "subcategory":"Real Estate Agent",
            "type":"Services"
        }
    ],
    "sg:phone":"+61 3 9580 1033",
    "sg:postcode":"3195",
    "sg:province":"VIC",
    "wof:name":"Stockdale & Leggo Pty Ltd",
    "wof:placetype":"venue"
},
  "geometry": {"coordinates":[145.086425781,-38.0072059631],"type":"Point"}
}