{
  "type": "Feature",
  "properties": {
    "addr:full":"Ross St Port Melbourne VIC 3207",
    "addr:postcode":"3207",
    "addr:street":"Ross St",
    "iso:country":"AU",
    "sg:address":"Ross St",
    "sg:city":"Port Melbourne",
    "sg:classifiers":[
        {
            "category":"Building & Trades",
            "subcategory":"Construction",
            "type":"Services"
        }
    ],
    "sg:phone":"+61 417 141 970",
    "sg:postcode":"3207",
    "sg:province":"VIC",
    "sg:tags":[
        "fencing",
        "contractor"
    ],
    "wof:name":"Port Melbourne Fencing",
    "wof:placetype":"venue"
},
  "geometry": {"coordinates":[144.935226,-37.836693],"type":"Point"}
}