{
  "type": "Feature",
  "properties": {
    "addr:full":"Acacia Market Place 1150 Beaudesert Rd Acacia Ridge QLD 4110",
    "addr:postcode":"1150;4110",
    "addr:street":"Market;Beaudesert Rd",
    "iso:country":"AU",
    "sg:address":"Acacia Market Place 1150 Beaudesert Rd",
    "sg:city":"Acacia Ridge",
    "sg:classifiers":[
        {
            "category":"Manufacturing",
            "subcategory":"Motor Vehicles & Parts",
            "type":"Manufacturing & Wholesale Goods"
        }
    ],
    "sg:phone":"+61 7 3274 6311",
    "sg:postcode":"4110",
    "sg:province":"QLD",
    "sg:tags":[
        "replacement"
    ],
    "wof:name":"Super Cheap Auto",
    "wof:placetype":"venue"
},
  "geometry": {"coordinates":[153.02926635700001,-27.5915794373],"type":"Point"}
}