{
  "type": "Feature",
  "properties": {
    "addr:full":"206 Paine St Maroubra NSW 2035",
    "addr:housenumber":"206",
    "addr:postcode":"2035",
    "addr:street":"Paine St",
    "iso:country":"AU",
    "sg:address":"206 Paine St",
    "sg:city":"Maroubra",
    "sg:classifiers":[
        {
            "category":"Building & Trades",
            "subcategory":"Cleaning & Sanitation",
            "type":"Services"
        }
    ],
    "sg:phone":"+61 403 190 598",
    "sg:postcode":"2035",
    "sg:province":"NSW",
    "sg:tags":[
        "industrial",
        "commercial",
        "contractor"
    ],
    "wof:name":"Dirty Deeds Cleaning Services",
    "wof:placetype":"venue"
},
  "geometry": {"coordinates":[151.23658752399999,-33.9464035034],"type":"Point"}
}