{
  "type": "Feature",
  "properties": {
    "iso:country":"AU",
    "sg:address":"Holbury St",
    "sg:city":"Forest Hill",
    "sg:classifiers":[
        {
            "category":"Building & Trades",
            "subcategory":"Construction",
            "type":"Services"
        }
    ],
    "sg:phone":"+61 401 866 480",
    "sg:postcode":"3131",
    "sg:province":"VIC",
    "sg:tags":[
        "concrete",
        "contractor"
    ],
    "wof:name":"Mark V Concreting",
    "wof:placetype":"venue"
},
  "geometry": {"coordinates":[145.173828125,-37.8295288086],"type":"Point"}
}