{
  "type": "Feature",
  "properties": {
    "addr:full":"200 Upper Main St Stawell VIC 3380",
    "addr:housenumber":"200",
    "addr:postcode":"3380",
    "addr:street":"Upper Main St",
    "iso:country":"AU",
    "sg:address":"200 Upper Main St",
    "sg:city":"Stawell",
    "sg:classifiers":[
        {
            "category":"Wholesale",
            "subcategory":"Electrical",
            "type":"Manufacturing & Wholesale Goods"
        }
    ],
    "sg:phone":"+61 3 5358 3088",
    "sg:postcode":"3380",
    "sg:province":"VIC",
    "sg:tags":[
        "wholesaler"
    ],
    "wof:name":"Middendorp Electric Co Pty Ltd",
    "wof:placetype":"venue"
},
  "geometry": {"coordinates":[142.765625,-37.0643806458],"type":"Point"}
}