{
  "type": "Feature",
  "properties": {
    "addr:full":"8 Tabratong St Nyngan NSW 2825",
    "addr:housenumber":"8",
    "addr:postcode":"2825",
    "addr:street":"Tabratong St",
    "iso:country":"AU",
    "sg:address":"8 Tabratong St",
    "sg:city":"Nyngan",
    "sg:classifiers":[
        {
            "category":"Arts & Performance",
            "subcategory":"Dance",
            "type":"Entertainment"
        }
    ],
    "sg:phone":"+61 2 6832 2952",
    "sg:postcode":"2825",
    "sg:province":"NSW",
    "sg:tags":[
        "theatrical",
        "ballet",
        "tuition"
    ],
    "wof:name":"Western Studio of Performing Arts",
    "wof:placetype":"venue"
},
  "geometry": {"coordinates":[147.19476318400001,-31.5633735657],"type":"Point"}
}