{
  "type": "Feature",
  "properties": {
    "iso:country":"AU",
    "sg:address":"49 Railway Rd",
    "sg:city":"Collinsville",
    "sg:classifiers":[
        {
            "category":"Real Estate",
            "subcategory":"Real Estate Agent",
            "type":"Services"
        }
    ],
    "sg:phone":"+61 7 4785 5198",
    "sg:postcode":"4804",
    "sg:province":"QLD",
    "wof:name":"Collinsville Real Estate",
    "wof:placetype":"venue"
},
  "geometry": {"coordinates":[147.844284058,-20.5565471649],"type":"Point"}
}