{
  "type": "Feature",
  "properties": {
    "addr:full":"45 Dean St Toowong QLD 4066",
    "addr:housenumber":"45",
    "addr:postcode":"4066",
    "addr:street":"Dean St",
    "iso:country":"AU",
    "sg:address":"45 Dean St",
    "sg:city":"Toowong",
    "sg:classifiers":[
        {
            "category":"Real Estate",
            "subcategory":"Real Estate Services",
            "type":"Services"
        }
    ],
    "sg:phone":"+61 7 3870 4111",
    "sg:postcode":"4066",
    "sg:province":"QLD",
    "sg:tags":[
        "consultant",
        "property"
    ],
    "wof:name":"Advance Group Property Consultants",
    "wof:placetype":"venue"
},
  "geometry": {"coordinates":[152.98231506400001,-27.4821662903],"type":"Point"}
}