{
  "type": "Feature",
  "properties": {
    "addr:full":"5 Fairway Ave Hoppers Crossing VIC 3029",
    "addr:housenumber":"5",
    "addr:postcode":"3029",
    "addr:street":"Fairway Ave",
    "iso:country":"AU",
    "sg:address":"5 Fairway Ave",
    "sg:city":"Hoppers Crossing",
    "sg:classifiers":[
        {
            "category":"Retail",
            "subcategory":"Auto Repair",
            "type":"Services"
        }
    ],
    "sg:phone":"+61 3 9749 5886",
    "sg:postcode":"3029",
    "sg:province":"VIC",
    "sg:tags":[
        "repairer",
        "motor",
        "engineer"
    ],
    "wof:name":"Costless Automotive",
    "wof:placetype":"venue"
},
  "geometry": {"coordinates":[144.69459499999999,-37.882751],"type":"Point"}
}