{
  "type": "Feature",
  "properties": {
    "addr:full":"31 Keen St Lismore NSW 2480",
    "addr:housenumber":"31",
    "addr:postcode":"2480",
    "addr:street":"Keen St",
    "iso:country":"AU",
    "sg:address":"31 Keen St",
    "sg:city":"Lismore",
    "sg:classifiers":[
        {
            "category":"Banks & Credit Unions",
            "subcategory":"Financial Services",
            "type":"Services"
        }
    ],
    "sg:phone":"+61 2 6621 9033",
    "sg:postcode":"2480",
    "sg:province":"NSW",
    "sg:tags":[
        "annuity",
        "rollover",
        "superannuation",
        "consultant"
    ],
    "wof:name":"Professional Investment Services",
    "wof:placetype":"venue"
},
  "geometry": {"coordinates":[153.278930664,-28.8086013794],"type":"Point"}
}