{
  "type": "Feature",
  "properties": {
    "addr:full":"PO Box 313 Avalon Beach NSW 2107",
    "addr:postcode":"2107",
    "iso:country":"AU",
    "sg:address":"PO Box 313",
    "sg:city":"Avalon Beach",
    "sg:classifiers":[
        {
            "category":"Professional",
            "subcategory":"Accounting & Tax Preparation",
            "type":"Services"
        }
    ],
    "sg:phone":"+61 419 185 977",
    "sg:postcode":"2107",
    "sg:province":"NSW",
    "sg:tags":[
        "accountant",
        "auditor"
    ],
    "wof:name":"Account4all Pty Ltd",
    "wof:placetype":"venue"
},
  "geometry": {"coordinates":[151.33059692399999,-33.6363182068],"type":"Point"}
}