{
  "type": "Feature",
  "properties": {
    "iso:country":"AU",
    "sg:address":"140 Toner Rd",
    "sg:city":"Cora Lynn",
    "sg:classifiers":[
        {
            "category":"Farming",
            "subcategory":"Farm",
            "type":"Manufacturing & Wholesale Goods"
        }
    ],
    "sg:phone":"+61 3 5997 7384",
    "sg:postcode":"3814",
    "sg:province":"VIC",
    "sg:tags":[
        "farmer"
    ],
    "wof:name":"Ianello C & S",
    "wof:placetype":"venue"
},
  "geometry": {"coordinates":[145.61282299999999,-38.153851],"type":"Point"}
}