{
  "type": "Feature",
  "properties": {
    "addr:full":"8 Meaney Pl Lennox Head NSW 2478",
    "addr:housenumber":"8",
    "addr:postcode":"2478",
    "addr:street":"Meaney Pl Lennox",
    "iso:country":"AU",
    "sg:address":"8 Meaney Pl",
    "sg:city":"Lennox Head",
    "sg:classifiers":[
        {
            "category":"Personal",
            "subcategory":"Massage",
            "type":"Services"
        }
    ],
    "sg:phone":"+61 2 6687 5848",
    "sg:postcode":"2478",
    "sg:province":"NSW",
    "sg:tags":[
        "therapy"
    ],
    "wof:name":"Milinda Rodziewicz-Pure Touch Massage",
    "wof:placetype":"venue"
},
  "geometry": {"coordinates":[153.58314514200001,-28.8128585815],"type":"Point"}
}