{
  "type": "Feature",
  "properties": {
    "addr:full":"Main Street Medical Centre 140 Main St Murwillumbah NSW 2484",
    "addr:housenumber":"140",
    "addr:postcode":"2484",
    "addr:street":"Main St",
    "iso:country":"AU",
    "sg:address":"Main Street Medical Centre 140 Main St",
    "sg:city":"Murwillumbah",
    "sg:classifiers":[
        {
            "category":"Government",
            "subcategory":"Court House",
            "type":"Public Place"
        }
    ],
    "sg:phone":"+61 414 370 259",
    "sg:postcode":"2484",
    "sg:province":"NSW",
    "sg:tags":[
        "personal",
        "marriage",
        "family",
        "counselling"
    ],
    "wof:name":"Judith Magee",
    "wof:placetype":"venue"
},
  "geometry": {"coordinates":[153.40342712399999,-28.3228321075],"type":"Point"}
}