{
  "type": "Feature",
  "properties": {
    "addr:full":"Lvl3/ 13 Lawson St Southport QLD 4215",
    "addr:housenumber":"13",
    "addr:postcode":"4215",
    "addr:street":"Lawson St",
    "iso:country":"AU",
    "sg:address":"Lvl3/ 13 Lawson St",
    "sg:city":"Southport",
    "sg:classifiers":[
        {
            "category":"Banks & Credit Unions",
            "subcategory":"Financial Services",
            "type":"Services"
        }
    ],
    "sg:phone":"+61 7 5557 8444",
    "sg:postcode":"4215",
    "sg:province":"QLD",
    "sg:tags":[
        "loan",
        "finance",
        "mortgage"
    ],
    "wof:name":"Dezign Home Loans",
    "wof:placetype":"venue"
},
  "geometry": {"coordinates":[153.41244506800001,-27.9710540771],"type":"Point"}
}