{
  "type": "Feature",
  "properties": {
    "addr:full":"70 Patten St Sale VIC 3850",
    "addr:housenumber":"70",
    "addr:postcode":"3850",
    "addr:street":"Patten St",
    "iso:country":"AU",
    "sg:address":"70 Patten St",
    "sg:city":"Sale",
    "sg:classifiers":[
        {
            "category":"Food & Beverages",
            "subcategory":"Supermarket",
            "type":"Retail Goods"
        }
    ],
    "sg:phone":"+61 3 5144 2531",
    "sg:postcode":"3850",
    "sg:province":"VIC",
    "sg:tags":[
        "grocery",
        "store"
    ],
    "wof:name":"Foodworks Sale",
    "wof:placetype":"venue"
},
  "geometry": {"coordinates":[147.088546753,-38.1122894287],"type":"Point"}
}