{
  "type": "Feature",
  "properties": {
    "iso:country":"AU",
    "sg:address":"55 Charles St",
    "sg:city":"Norwood",
    "sg:classifiers":[
        {
            "category":"Farming",
            "subcategory":"Vineyard",
            "type":"Manufacturing & Wholesale Goods"
        }
    ],
    "sg:phone":"+61 8 8332 2761",
    "sg:postcode":"5067",
    "sg:province":"SA",
    "sg:tags":[
        "winery"
    ],
    "wof:name":"Rumball Sparkling Wines",
    "wof:placetype":"venue"
},
  "geometry": {"coordinates":[138.62564086899999,-34.9269638062],"type":"Point"}
}