{
  "type": "Feature",
  "properties": {
    "iso:country":"AU",
    "sg:address":"35 Queen St",
    "sg:city":"Campbelltown",
    "sg:classifiers":[
        {
            "category":"Real Estate",
            "subcategory":"Real Estate Agent",
            "type":"Services"
        }
    ],
    "sg:phone":"+61 2 4628 8800",
    "sg:postcode":"2560",
    "sg:province":"NSW",
    "wof:name":"Century 21 Campbell Real Estate",
    "wof:placetype":"venue"
},
  "geometry": {"coordinates":[150.81915283199999,-34.0610771179],"type":"Point"}
}