{
  "type": "Feature",
  "properties": {
    "addr:full":"Level 1, 192 Rundle St Adelaide SA 5000",
    "addr:housenumber":"192",
    "addr:postcode":"5000",
    "addr:street":"Rundle St",
    "iso:country":"AU",
    "sg:address":"Level 1, 192 Rundle St",
    "sg:city":"Adelaide",
    "sg:classifiers":[
        {
            "category":"Travel",
            "subcategory":"Travel Agent",
            "type":"Entertainment"
        }
    ],
    "sg:phone":"+61 8 8223 5920",
    "sg:postcode":"5000",
    "sg:province":"SA",
    "sg:tags":[
        "tour",
        "holiday",
        "adventure"
    ],
    "sg:website":"http://www.walkingholidays.com.au",
    "wof:name":"Walking Holidays",
    "wof:placetype":"venue"
},
  "geometry": {"coordinates":[138.60691833499999,-34.9224815369],"type":"Point"}
}