{
  "type": "Feature",
  "properties": {
    "addr:full":"Shop 1, 212 Preston Rd Manly West QLD 4179",
    "addr:housenumber":"shop 1 212",
    "addr:postcode":"4179",
    "addr:street":"Preston Rd",
    "iso:country":"AU",
    "sg:address":"Shop 1, 212 Preston Rd",
    "sg:city":"Manly West",
    "sg:classifiers":[
        {
            "category":"Personal",
            "subcategory":"Beauty Salon",
            "type":"Services"
        }
    ],
    "sg:phone":"+61 7 3396 3126",
    "sg:postcode":"4179",
    "sg:province":"QLD",
    "sg:tags":[
        "hairdresser"
    ],
    "wof:name":"The Lock Tamer",
    "wof:placetype":"venue"
},
  "geometry": {"coordinates":[153.16746520999999,-27.4546031952],"type":"Point"}
}