{
  "type": "Feature",
  "properties": {
    "iso:country":"AU",
    "sg:address":"6 Carbine Pl",
    "sg:city":"Bundoora",
    "sg:classifiers":[
        {
            "category":"Professional",
            "subcategory":"Business Services",
            "type":"Services"
        }
    ],
    "sg:phone":"+61 3 9466 9910",
    "sg:postcode":"3083",
    "sg:province":"VIC",
    "sg:tags":[
        "drafting"
    ],
    "wof:name":"M. Di Cesare & Co. Building Design & Drafting",
    "wof:placetype":"venue"
},
  "geometry": {"coordinates":[145.05055236800001,-37.7029495239],"type":"Point"}
}