{
  "type": "Feature",
  "properties": {
    "addr:full":"32A Croydon Rd Keswick SA 5035",
    "addr:housenumber":"32a",
    "addr:postcode":"5035",
    "addr:street":"Croydon Rd",
    "iso:country":"AU",
    "sg:address":"32A Croydon Rd",
    "sg:city":"Keswick",
    "sg:classifiers":[
        {
            "category":"Wholesale",
            "subcategory":"Construction Materials",
            "type":"Manufacturing & Wholesale Goods"
        }
    ],
    "sg:phone":"+61 8 8297 5155",
    "sg:postcode":"5035",
    "sg:province":"SA",
    "sg:tags":[
        "wholesaler",
        "lighting",
        "mfrs",
        "accessory"
    ],
    "wof:name":"Eye Lighting Australia Pty Ltd",
    "wof:placetype":"venue"
},
  "geometry": {"coordinates":[138.578292847,-34.9451599121],"type":"Point"}
}