{
  "type": "Feature",
  "properties": {
    "addr:full":"15 Millennium Crt Silverwater NSW 2128",
    "addr:housenumber":"15",
    "addr:postcode":"2128",
    "addr:street":"Millennium Crt",
    "iso:country":"AU",
    "sg:address":"15 Millennium Crt",
    "sg:city":"Silverwater",
    "sg:classifiers":[
        {
            "category":"Farming",
            "subcategory":"Dairy Farm",
            "type":"Manufacturing & Wholesale Goods"
        }
    ],
    "sg:phone":"+61 2 9714 2400",
    "sg:postcode":"2128",
    "sg:province":"NSW",
    "sg:tags":[
        "wholesaler",
        "product",
        "mfrs"
    ],
    "wof:name":"Plateau Food Distributors",
    "wof:placetype":"venue"
},
  "geometry": {"coordinates":[151.039230347,-33.8328132629],"type":"Point"}
}