{
  "type": "Feature",
  "properties": {
    "addr:full":"3 Leo Alley Rd Noosaville QLD 4566",
    "addr:housenumber":"3",
    "addr:postcode":"4566",
    "addr:street":"Leo Alley Rd",
    "iso:country":"AU",
    "sg:address":"3 Leo Alley Rd",
    "sg:city":"Noosaville",
    "sg:classifiers":[
        {
            "category":"Professional",
            "subcategory":"Art Services",
            "type":"Services"
        }
    ],
    "sg:phone":"+61 7 5449 7933",
    "sg:postcode":"4566",
    "sg:province":"QLD",
    "sg:tags":[
        "graphic",
        "designer"
    ],
    "wof:name":"Noosa Graphica",
    "wof:placetype":"venue"
},
  "geometry": {"coordinates":[153.04307556099999,-26.4136333466],"type":"Point"}
}