{
  "type": "Feature",
  "properties": {
    "addr:full":"Shop 5052 Westfield Shopping Centre Parramatta NSW 2150",
    "addr:housenumber":"5052",
    "addr:postcode":"2150",
    "addr:street":"Westfield Shopping",
    "iso:country":"AU",
    "sg:address":"Shop 5052 Westfield Shopping Centre",
    "sg:city":"Parramatta",
    "sg:classifiers":[
        {
            "category":"Fast Food",
            "type":"Food & Drink"
        }
    ],
    "sg:phone":"+61 2 9635 5083",
    "sg:postcode":"2150",
    "sg:province":"NSW",
    "sg:tags":[
        "away",
        "take"
    ],
    "wof:name":"Hong Kong Seafood",
    "wof:placetype":"venue"
},
  "geometry": {"coordinates":[151.00668335,-33.81483078],"type":"Point"}
}