{
  "type": "Feature",
  "properties": {
    "addr:full":"46 Bentley St Wetherill Park NSW 2164",
    "addr:housenumber":"46",
    "addr:postcode":"2164",
    "addr:street":"Bentley St",
    "iso:country":"AU",
    "sg:address":"46 Bentley St",
    "sg:city":"Wetherill Park",
    "sg:classifiers":[
        {
            "category":"Building & Trades",
            "subcategory":"Construction",
            "type":"Services"
        }
    ],
    "sg:phone":"+61 403 370 033",
    "sg:postcode":"2164",
    "sg:province":"NSW",
    "sg:tags":[
        "scaffolding"
    ],
    "wof:name":"Turbo International",
    "wof:placetype":"venue"
},
  "geometry": {"coordinates":[150.88398742699999,-33.8438911438],"type":"Point"}
}