{
  "type": "Feature",
  "properties": {
    "iso:country":"AU",
    "sg:address":"9 Lennon Lodge La",
    "sg:city":"Coromandel Valley",
    "sg:classifiers":[
        {
            "category":"Professional",
            "subcategory":"Art Services",
            "type":"Services"
        }
    ],
    "sg:phone":"+61 417 822 482",
    "sg:postcode":"5051",
    "sg:province":"SA",
    "sg:tags":[
        "decorator",
        "painter"
    ],
    "wof:name":"Thomas Painting & Repairs",
    "wof:placetype":"venue"
},
  "geometry": {"coordinates":[138.62698399999999,-35.042042],"type":"Point"}
}