{
  "type": "Feature",
  "properties": {
    "iso:country":"AU",
    "sg:address":"17 Margaret St",
    "sg:city":"Southport",
    "sg:classifiers":[
        {
            "category":"Health Services",
            "subcategory":"Health Practitioner",
            "type":"Services"
        }
    ],
    "sg:phone":"+61 7 5591 4798",
    "sg:postcode":"4215",
    "sg:province":"QLD",
    "sg:tags":[
        "acupuncture"
    ],
    "wof:name":"Thompson Elisabeth B.App.Sc.,T.C.M.",
    "wof:placetype":"venue"
},
  "geometry": {"coordinates":[153.403839111,-27.9767150879],"type":"Point"}
}