{
  "type": "Feature",
  "properties": {
    "addr:full":"M.S 541 Mt Perry Rd Kolan South QLD 4670",
    "addr:housenumber":"541",
    "addr:postcode":"4670",
    "addr:street":"M.S;Mt Perry Rd",
    "iso:country":"AU",
    "sg:address":"M.S 541 Mt Perry Rd",
    "sg:city":"Kolan South",
    "sg:classifiers":[
        {
            "category":"Farming",
            "subcategory":"Farm",
            "type":"Manufacturing & Wholesale Goods"
        }
    ],
    "sg:phone":"+61 7 4157 7256",
    "sg:postcode":"4670",
    "sg:province":"QLD",
    "sg:tags":[
        "farmer"
    ],
    "wof:name":"Algeo D R & S A",
    "wof:placetype":"venue"
},
  "geometry": {"coordinates":[152.32713317899999,-24.8505649567],"type":"Point"}
}