{
  "type": "Feature",
  "properties": {
    "iso:country":"AU",
    "sg:address":"17 Paraburdoo Crs",
    "sg:city":"Shailer Park",
    "sg:classifiers":[
        {
            "category":"Utilities",
            "subcategory":"Electric",
            "type":"Services"
        }
    ],
    "sg:phone":"+61 7 3801 3654",
    "sg:postcode":"4128",
    "sg:province":"QLD",
    "sg:tags":[
        "electrical",
        "contractor"
    ],
    "wof:name":"Crossley Connections",
    "wof:placetype":"venue"
},
  "geometry": {"coordinates":[153.17202758799999,-27.6515808105],"type":"Point"}
}