{
  "type": "Feature",
  "properties": {
    "addr:full":"2 Bransdon St Wauchope NSW 2446",
    "addr:housenumber":"2",
    "addr:postcode":"2446",
    "addr:street":"Bransdon St",
    "iso:country":"AU",
    "sg:address":"2 Bransdon St",
    "sg:city":"Wauchope",
    "sg:classifiers":[
        {
            "category":"Shopping",
            "subcategory":"Clothing, Apparel, & Fashions",
            "type":"Retail Goods"
        }
    ],
    "sg:phone":"+61 2 6585 1898",
    "sg:postcode":"2446",
    "sg:province":"NSW",
    "sg:tags":[
        "lady",
        "wear"
    ],
    "wof:name":"Carnaby",
    "wof:placetype":"venue"
},
  "geometry": {"coordinates":[152.73350500000001,-31.457251],"type":"Point"}
}