{
  "type": "Feature",
  "properties": {
    "iso:country":"AU",
    "sg:address":"\"Genpalea\" M/S 848",
    "sg:city":"Warwick",
    "sg:classifiers":[
        {
            "category":"Farming",
            "subcategory":"Farm",
            "type":"Manufacturing & Wholesale Goods"
        }
    ],
    "sg:phone":"+61 7 4667 3755",
    "sg:postcode":"4370",
    "sg:province":"QLD",
    "sg:tags":[
        "farmer"
    ],
    "wof:name":"Marsden E",
    "wof:placetype":"venue"
},
  "geometry": {"coordinates":[152.03463745100001,-28.2441101074],"type":"Point"}
}