{
  "type": "Feature",
  "properties": {
    "addr:full":"5 Commercial Rd Sheidow Park SA 5158",
    "addr:housenumber":"5",
    "addr:postcode":"5158",
    "addr:street":"Commercial Rd",
    "iso:country":"AU",
    "sg:address":"5 Commercial Rd",
    "sg:city":"Sheidow Park",
    "sg:classifiers":[
        {
            "category":"Health Services",
            "subcategory":"Health Practitioner",
            "type":"Services"
        }
    ],
    "sg:phone":"+61 8 8322 2455",
    "sg:postcode":"5158",
    "sg:province":"SA",
    "sg:tags":[
        "physiotherapist"
    ],
    "wof:name":"Olympic Sports Clinic",
    "wof:placetype":"venue"
},
  "geometry": {"coordinates":[138.522872925,-35.0759506226],"type":"Point"}
}