{
  "type": "Feature",
  "properties": {
    "addr:full":"26 Nixon Rd Wingfield SA 5013",
    "addr:housenumber":"26",
    "addr:postcode":"5013",
    "addr:street":"Nixon Rd",
    "iso:country":"AU",
    "sg:address":"26 Nixon Rd",
    "sg:city":"Wingfield",
    "sg:classifiers":[
        {
            "category":"Retail",
            "subcategory":"Auto Repair",
            "type":"Services"
        }
    ],
    "sg:phone":"+61 8 8244 5822",
    "sg:postcode":"5013",
    "sg:province":"SA",
    "sg:tags":[
        "bus",
        "truck"
    ],
    "wof:name":"DS Truck Repairs",
    "wof:placetype":"venue"
},
  "geometry": {"coordinates":[138.55781555199999,-34.8351249695],"type":"Point"}
}