{
  "type": "Feature",
  "properties": {
    "addr:full":"381 Lord St Highgate WA 6003",
    "addr:housenumber":"381",
    "addr:postcode":"6003",
    "addr:street":"Lord St",
    "iso:country":"AU",
    "sg:address":"381 Lord St",
    "sg:city":"Highgate",
    "sg:classifiers":[
        {
            "category":"Health Services",
            "subcategory":"Doctor",
            "type":"Services"
        }
    ],
    "sg:phone":"+61 8 9328 8960",
    "sg:postcode":"6003",
    "sg:province":"WA",
    "sg:tags":[
        "podiatrist"
    ],
    "wof:name":"Frank Pigliardo",
    "wof:placetype":"venue"
},
  "geometry": {"coordinates":[115.87551116900001,-31.9409637451],"type":"Point"}
}