{
  "type": "Feature",
  "properties": {
    "addr:full":"Ste 15, L3, St George Private Hospital South St Kogarah NSW 2217",
    "addr:housenumber":"l3",
    "addr:postcode":"2217",
    "addr:street":"St;St",
    "iso:country":"AU",
    "sg:address":"Ste 15, L3, St George Private Hospital South St",
    "sg:city":"Kogarah",
    "sg:classifiers":[
        {
            "category":"Health Services",
            "subcategory":"Doctor",
            "type":"Services"
        }
    ],
    "sg:phone":"+61 2 9553 7555",
    "sg:postcode":"2217",
    "sg:province":"NSW",
    "sg:tags":[
        "medical",
        "practitioner"
    ],
    "wof:name":"Chapman Michael Prof",
    "wof:placetype":"venue"
},
  "geometry": {"coordinates":[151.13627600000001,-33.966221],"type":"Point"}
}