{
  "type": "Feature",
  "properties": {
    "addr:full":"Shop 1, 2 Osborne Rd Mitchelton QLD 4053",
    "addr:housenumber":"shop;2",
    "addr:postcode":"4053",
    "addr:street":"Osborne Rd",
    "iso:country":"AU",
    "sg:address":"Shop 1, 2 Osborne Rd",
    "sg:city":"Mitchelton",
    "sg:classifiers":[
        {
            "category":"Real Estate",
            "subcategory":"Real Estate Agent",
            "type":"Services"
        }
    ],
    "sg:phone":"+61 7 3354 7777",
    "sg:postcode":"4053",
    "sg:province":"QLD",
    "sg:website":"http://www.ljhooker.com.au/mitchelton",
    "wof:name":"L.J. Hooker Mitchelton",
    "wof:placetype":"venue"
},
  "geometry": {"coordinates":[152.97659301799999,-27.414604187],"type":"Point"}
}