{
  "type": "Feature",
  "properties": {
    "addr:full":"39 Cuthero Tce Kensington Gardens SA 5068",
    "addr:housenumber":"39",
    "addr:postcode":"5068",
    "addr:street":"Cuthero Tce Kensington Gardens",
    "iso:country":"AU",
    "sg:address":"39 Cuthero Tce",
    "sg:city":"Kensington Gardens",
    "sg:classifiers":[
        {
            "category":"Professional",
            "subcategory":"Art Services",
            "type":"Services"
        }
    ],
    "sg:phone":"+61 8 8331 0746",
    "sg:postcode":"5068",
    "sg:province":"SA",
    "sg:tags":[
        "decorator",
        "painter"
    ],
    "wof:name":"Lasting Looks",
    "wof:placetype":"venue"
},
  "geometry": {"coordinates":[138.66348266599999,-34.9172019958],"type":"Point"}
}