{
  "type": "Feature",
  "properties": {
    "addr:full":"PO Box 38 BK Black Hill VIC 3350",
    "addr:postcode":"3350",
    "iso:country":"AU",
    "sg:address":"PO Box 38",
    "sg:city":"BK Black Hill",
    "sg:classifiers":[
        {
            "category":"Professional",
            "subcategory":"Art Services",
            "type":"Services"
        }
    ],
    "sg:phone":"+61 3 5332 7661",
    "sg:postcode":"3350",
    "sg:province":"VIC",
    "sg:tags":[
        "decorator",
        "painter"
    ],
    "wof:name":"Henry Manzl & Son Pty Ltd",
    "wof:placetype":"venue"
},
  "geometry": {"coordinates":[143.869675,-37.549999],"type":"Point"}
}