{
  "type": "Feature",
  "properties": {
    "iso:country":"AU",
    "sg:address":"180 Pacific Hwy",
    "sg:city":"Hornsby",
    "sg:classifiers":[
        {
            "category":"Retail",
            "subcategory":"Funeral Services",
            "type":"Services"
        }
    ],
    "sg:phone":"+61 2 9477 3272",
    "sg:postcode":"2077",
    "sg:province":"NSW",
    "sg:tags":[
        "director"
    ],
    "wof:name":"T J Andrews Funeral Services",
    "wof:placetype":"venue"
},
  "geometry": {"coordinates":[151.09901428200001,-33.7068252563],"type":"Point"}
}