{
  "type": "Feature",
  "properties": {
    "addr:full":"99 Newell St Cairns QLD 4870",
    "addr:housenumber":"99",
    "addr:postcode":"4870",
    "addr:street":"Newell St",
    "iso:country":"AU",
    "sg:address":"99 Newell St",
    "sg:city":"Cairns",
    "sg:classifiers":[
        {
            "category":"Professional",
            "subcategory":"Computer Services",
            "type":"Services"
        }
    ],
    "sg:phone":"+61 7 4050 9199",
    "sg:postcode":"4870",
    "sg:province":"QLD",
    "sg:tags":[
        "equipment",
        "networking",
        "installation"
    ],
    "wof:name":"S.E.M.S Pty Ltd",
    "wof:placetype":"venue"
},
  "geometry": {"coordinates":[145.75559997600001,-16.9438877106],"type":"Point"}
}