{
  "type": "Feature",
  "properties": {
    "addr:full":"58 Vincent St Sandringham VIC 3191",
    "addr:housenumber":"58",
    "addr:postcode":"3191",
    "addr:street":"Vincent St",
    "iso:country":"AU",
    "sg:address":"58 Vincent St",
    "sg:city":"Sandringham",
    "sg:classifiers":[
        {
            "category":"Building & Trades",
            "subcategory":"Cleaning & Sanitation",
            "type":"Services"
        }
    ],
    "sg:phone":"+61 3 9598 0799",
    "sg:postcode":"3191",
    "sg:province":"VIC",
    "sg:tags":[
        "industrial",
        "commercial",
        "contractor"
    ],
    "wof:name":"Bayside Cleaning Group",
    "wof:placetype":"venue"
},
  "geometry": {"coordinates":[145.01901245100001,-37.9498519897],"type":"Point"}
}