{
  "type": "Feature",
  "properties": {
    "addr:full":"28 Struenmarie St Kareela NSW 2232",
    "addr:housenumber":"28",
    "addr:postcode":"2232",
    "addr:street":"Struenmarie St",
    "iso:country":"AU",
    "sg:address":"28 Struenmarie St",
    "sg:city":"Kareela",
    "sg:classifiers":[
        {
            "category":"Professional",
            "subcategory":"Accounting & Tax Preparation",
            "type":"Services"
        }
    ],
    "sg:phone":"+61 2 9528 2996",
    "sg:postcode":"2232",
    "sg:province":"NSW",
    "sg:tags":[
        "bookkeeping"
    ],
    "wof:name":"Dibden Peter",
    "wof:placetype":"venue"
},
  "geometry": {"coordinates":[151.08169555699999,-34.0113067627],"type":"Point"}
}