{
  "type": "Feature",
  "properties": {
    "iso:country":"AU",
    "sg:address":"43- 45 Cochrane St",
    "sg:city":"Brighton",
    "sg:classifiers":[
        {
            "category":"Social Services",
            "subcategory":"Child Care",
            "type":"Services"
        }
    ],
    "sg:phone":"+61 3 9596 3999",
    "sg:postcode":"3186",
    "sg:province":"VIC",
    "sg:website":"http://www.childcare.com.au",
    "wof:name":"ABC Brighton Junction",
    "wof:placetype":"venue"
},
  "geometry": {"coordinates":[144.998321533,-37.9020843506],"type":"Point"}
}