{
  "type": "Feature",
  "properties": {
    "iso:country":"AU",
    "sg:address":"953 Maleny-Montville Rd",
    "sg:city":"Maleny",
    "sg:classifiers":[
        {
            "category":"Retail",
            "subcategory":"Event Space",
            "type":"Services"
        }
    ],
    "sg:phone":"+61 7 5494 3422",
    "sg:postcode":"4552",
    "sg:province":"QLD",
    "sg:tags":[
        "venue",
        "reception",
        "wedding"
    ],
    "wof:name":"Laurels",
    "wof:placetype":"venue"
},
  "geometry": {"coordinates":[152.88519287099999,-26.7679843903],"type":"Point"}
}