{
  "type": "Feature",
  "properties": {
    "iso:country":"AU",
    "sg:address":"4/ 71 King St",
    "sg:city":"Newcastle",
    "sg:classifiers":[
        {
            "category":"Insurance",
            "subcategory":"Life Insurance",
            "type":"Services"
        }
    ],
    "sg:phone":"+61 2 4929 5566",
    "sg:postcode":"2300",
    "sg:province":"NSW",
    "wof:name":"Joy Paul Of Total Financial Planning Pty Ltd",
    "wof:placetype":"venue"
},
  "geometry": {"coordinates":[151.782623,-32.928581],"type":"Point"}
}