{
  "type": "Feature",
  "properties": {
    "iso:country":"AU",
    "sg:address":"Dorsen St",
    "sg:city":"Hawkesdale",
    "sg:classifiers":[
        {
            "category":"Home & Garden",
            "subcategory":"Garden Supply",
            "type":"Retail Goods"
        }
    ],
    "sg:phone":"+61 428 172 119",
    "sg:postcode":"3287",
    "sg:province":"VIC",
    "sg:tags":[
        "fertilizer"
    ],
    "wof:name":"Southwest Ag Services",
    "wof:placetype":"venue"
},
  "geometry": {"coordinates":[142.322174072,-38.105430603],"type":"Point"}
}