{
  "type": "Feature",
  "properties": {
    "iso:country":"AU",
    "sg:address":"1 Bice St",
    "sg:city":"Barmera",
    "sg:classifiers":[
        {
            "category":"Personal",
            "subcategory":"Beauty Salon",
            "type":"Services"
        }
    ],
    "sg:phone":"+61 8 8588 2885",
    "sg:postcode":"5345",
    "sg:province":"SA",
    "sg:tags":[
        "hairdresser"
    ],
    "wof:name":"The Snip Shoppe Hiz & Herz Hairdressers",
    "wof:placetype":"venue"
},
  "geometry": {"coordinates":[140.46517944300001,-34.2498435974],"type":"Point"}
}