{
  "type": "Feature",
  "properties": {
    "iso:country":"AU",
    "sg:address":"8 Joel Crt",
    "sg:city":"Moorabbin",
    "sg:classifiers":[
        {
            "category":"Building & Trades",
            "subcategory":"Construction",
            "type":"Services"
        }
    ],
    "sg:phone":"+61 3 9532 3155",
    "sg:postcode":"3189",
    "sg:province":"VIC",
    "sg:tags":[
        "concrete",
        "contractor"
    ],
    "wof:name":"KPA Concrete Construction",
    "wof:placetype":"venue"
},
  "geometry": {"coordinates":[145.071136475,-37.9400634766],"type":"Point"}
}