{
  "type": "Feature",
  "properties": {
    "addr:full":"40 South St Ipswich QLD 4305",
    "addr:housenumber":"40",
    "addr:postcode":"4305",
    "addr:street":"South St",
    "iso:country":"AU",
    "sg:address":"40 South St",
    "sg:city":"Ipswich",
    "sg:classifiers":[
        {
            "category":"Education",
            "subcategory":"University",
            "type":"Public Place"
        }
    ],
    "sg:phone":"+61 7 3282 8163",
    "sg:postcode":"4305",
    "sg:province":"QLD",
    "sg:tags":[
        "college",
        "tertiary"
    ],
    "wof:name":"University Of Southern Queensland (Ipswich Centre)",
    "wof:placetype":"venue"
},
  "geometry": {"coordinates":[152.760162353,-27.6165885925],"type":"Point"}
}