{
  "type": "Feature",
  "properties": {
    "addr:full":"Taylors Rd Walloon QLD 4306",
    "addr:postcode":"4306",
    "addr:street":"Taylors Rd",
    "iso:country":"AU",
    "sg:address":"Taylors Rd",
    "sg:city":"Walloon",
    "sg:classifiers":[
        {
            "category":"Professional",
            "subcategory":"Business Services",
            "type":"Services"
        }
    ],
    "sg:phone":"+61 7 5464 5542",
    "sg:postcode":"4306",
    "sg:province":"QLD",
    "sg:tags":[
        "livestock",
        "transport"
    ],
    "wof:name":"Warrego Livestock Transport",
    "wof:placetype":"venue"
},
  "geometry": {"coordinates":[152.663162231,-27.5951900482],"type":"Point"}
}