{
  "type": "Feature",
  "properties": {
    "iso:country":"AU",
    "sg:address":"57 Main Rd",
    "sg:city":"Huonville",
    "sg:classifiers":[
        {
            "category":"Banks & Credit Unions",
            "subcategory":"Bank",
            "type":"Services"
        }
    ],
    "sg:phone":"+61 13 20 32",
    "sg:postcode":"7109",
    "sg:province":"TAS",
    "wof:name":"Westpac",
    "wof:placetype":"venue"
},
  "geometry": {"coordinates":[147.04908752399999,-43.029384613],"type":"Point"}
}