{
  "type": "Feature",
  "properties": {
    "iso:country":"AU",
    "sg:address":"Crown St",
    "sg:city":"Stockton",
    "sg:classifiers":[
        {
            "category":"Food & Beverages",
            "subcategory":"Supermarket",
            "type":"Retail Goods"
        }
    ],
    "sg:phone":"+61 2 4928 1599",
    "sg:postcode":"2295",
    "sg:province":"NSW",
    "sg:tags":[
        "grocery",
        "store"
    ],
    "wof:name":"I G A Supermarket",
    "wof:placetype":"venue"
},
  "geometry": {"coordinates":[151.7840271,-32.9159126282],"type":"Point"}
}