{
  "type": "Feature",
  "properties": {
    "iso:country":"AU",
    "sg:address":"Level 15, 44 St",
    "sg:city":"Georges Tce Perth",
    "sg:classifiers":[
        {
            "category":"Professional",
            "subcategory":"Engineering",
            "type":"Services"
        }
    ],
    "sg:phone":"+61 8 9225 5550",
    "sg:postcode":"6000",
    "sg:province":"WA",
    "sg:tags":[
        "consulting",
        "engineer"
    ],
    "wof:name":"OSD Energy Services",
    "wof:placetype":"venue"
},
  "geometry": {"coordinates":[115.859298706,-31.9554786682],"type":"Point"}
}