{
  "type": "Feature",
  "properties": {
    "addr:full":"Mermaid Waters Shopping Centre Cnr Markeri St & Sunshine Blv Mermaid Waters QLD 4218",
    "addr:postcode":"4218",
    "addr:street":"Cnr Markeri St & Sunshine Blv",
    "iso:country":"AU",
    "sg:address":"Mermaid Waters Shopping Centre Cnr Markeri St & Sunshine Blv",
    "sg:city":"Mermaid Waters",
    "sg:classifiers":[
        {
            "category":"Fast Food",
            "type":"Food & Drink"
        }
    ],
    "sg:phone":"+61 7 5572 6200",
    "sg:postcode":"4218",
    "sg:province":"QLD",
    "sg:tags":[
        "away",
        "take"
    ],
    "wof:name":"Milano's Pizza Pasta & Ribs",
    "wof:placetype":"venue"
},
  "geometry": {"coordinates":[153.41465759299999,-28.0459346771],"type":"Point"}
}