{
  "type": "Feature",
  "properties": {
    "iso:country":"AU",
    "sg:address":"229 Stirling Hwy",
    "sg:city":"Claremont",
    "sg:classifiers":[
        {
            "category":"Wholesale",
            "subcategory":"Apparel",
            "type":"Manufacturing & Wholesale Goods"
        }
    ],
    "sg:phone":"+61 8 9284 7212",
    "sg:postcode":"6010",
    "sg:province":"WA",
    "sg:tags":[
        "wholesaler",
        "mfrs",
        "cap",
        "hat"
    ],
    "wof:name":"Katz Agencies",
    "wof:placetype":"venue"
},
  "geometry": {"coordinates":[115.78822326700001,-31.9817523956],"type":"Point"}
}