{
  "type": "Feature",
  "properties": {
    "iso:country":"AU",
    "sg:address":"130 Newmans Rd",
    "sg:city":"Woolgoolga",
    "sg:classifiers":[
        {
            "category":"Autos & Motor Vehicles",
            "subcategory":"Auto Supplies",
            "type":"Retail Goods"
        }
    ],
    "sg:phone":"+61 2 6654 7014",
    "sg:postcode":"2456",
    "sg:province":"NSW",
    "sg:tags":[
        "camper-trailers",
        "caravan",
        "equipment"
    ],
    "wof:name":"Camp-Let Qld",
    "wof:placetype":"venue"
},
  "geometry": {"coordinates":[153.180709839,-30.1076107025],"type":"Point"}
}