{
  "type": "Feature",
  "properties": {
    "addr:full":"155 Mole Creek Rd Deloraine TAS 7304",
    "addr:housenumber":"155",
    "addr:postcode":"7304",
    "addr:street":"Mole Creek Rd",
    "iso:country":"AU",
    "sg:address":"155 Mole Creek Rd",
    "sg:city":"Deloraine",
    "sg:classifiers":[
        {
            "category":"Bars & Pubs",
            "subcategory":"Lounge",
            "type":"Food & Drink"
        }
    ],
    "sg:phone":"+61 3 6266 6464",
    "sg:postcode":"7304",
    "sg:province":"TAS",
    "sg:tags":[
        "water",
        "filter",
        "drinking"
    ],
    "wof:name":"Tasmanian Mountain Waters",
    "wof:placetype":"venue"
},
  "geometry": {"coordinates":[146.629547,-41.522369],"type":"Point"}
}