{
  "type": "Feature",
  "properties": {
    "addr:full":"32a Balfour Ave Heathmont VIC 3135",
    "addr:housenumber":"32a",
    "addr:postcode":"3135",
    "addr:street":"Balfour Ave",
    "iso:country":"AU",
    "sg:address":"32a Balfour Ave",
    "sg:city":"Heathmont",
    "sg:classifiers":[
        {
            "category":"Professional",
            "subcategory":"Employment Agencies",
            "type":"Services"
        }
    ],
    "sg:phone":"+61 3 9870 6725",
    "sg:postcode":"3135",
    "sg:province":"VIC",
    "sg:tags":[
        "provider",
        "internet"
    ],
    "wof:name":"Hotkey Outer SE Melbourne",
    "wof:placetype":"venue"
},
  "geometry": {"coordinates":[145.241424561,-37.8274345398],"type":"Point"}
}