{
  "type": "Feature",
  "properties": {
    "addr:full":"16 Armada Pl Banyo QLD 4014",
    "addr:housenumber":"16",
    "addr:postcode":"4014",
    "addr:street":"Armada Pl",
    "iso:country":"AU",
    "sg:address":"16 Armada Pl",
    "sg:city":"Banyo",
    "sg:classifiers":[
        {
            "category":"Wholesale",
            "subcategory":"Machinery & Supplies",
            "type":"Manufacturing & Wholesale Goods"
        }
    ],
    "sg:phone":"+61 7 3267 0065",
    "sg:postcode":"4014",
    "sg:province":"QLD",
    "sg:tags":[
        "equipment",
        "hydraulic"
    ],
    "wof:name":"Flaretite",
    "wof:placetype":"venue"
},
  "geometry": {"coordinates":[153.08982849099999,-27.3846244812],"type":"Point"}
}