{
  "type": "Feature",
  "properties": {
    "addr:full":"42 Lawsons Rd Toora VIC 3962",
    "addr:housenumber":"42",
    "addr:postcode":"3962",
    "addr:street":"Lawsons Rd",
    "iso:country":"AU",
    "sg:address":"42 Lawsons Rd",
    "sg:city":"Toora",
    "sg:classifiers":[
        {
            "category":"Professional",
            "subcategory":"Accounting & Tax Preparation",
            "type":"Services"
        }
    ],
    "sg:phone":"+61 3 5686 2411",
    "sg:postcode":"3962",
    "sg:province":"VIC",
    "sg:tags":[
        "bookkeeping"
    ],
    "wof:name":"Do-It Consultancy Pty Ltd",
    "wof:placetype":"venue"
},
  "geometry": {"coordinates":[146.314697266,-38.6865997314],"type":"Point"}
}