{
  "type": "Feature",
  "properties": {
    "addr:full":"Shop 1 46 Outlook Drv Dandenong North VIC 3175",
    "addr:housenumber":"shop;46",
    "addr:postcode":"3175",
    "addr:street":"Outlook Drv",
    "iso:country":"AU",
    "sg:address":"Shop 1 46 Outlook Drv",
    "sg:city":"Dandenong North",
    "sg:classifiers":[
        {
            "category":"Communications",
            "subcategory":"Film & Video Production",
            "type":"Services"
        }
    ],
    "sg:phone":"+61 3 9795 6338",
    "sg:postcode":"3175",
    "sg:province":"VIC",
    "sg:tags":[
        "dvd",
        "library"
    ],
    "wof:name":"Top Video & DVDs Dandenong North",
    "wof:placetype":"venue"
},
  "geometry": {"coordinates":[145.22111511200001,-37.9503250122],"type":"Point"}
}