{
  "type": "Feature",
  "properties": {
    "addr:full":"U7/ 20 Swallow Rd Grafton NSW 2460",
    "addr:housenumber":"20",
    "addr:postcode":"2460",
    "addr:street":"U7 /;Swallow Rd",
    "iso:country":"AU",
    "sg:address":"U7/ 20 Swallow Rd",
    "sg:city":"Grafton",
    "sg:classifiers":[
        {
            "category":"Structure",
            "subcategory":"Building",
            "type":"Public Place"
        }
    ],
    "sg:phone":"+61 423 345 757",
    "sg:postcode":"2460",
    "sg:province":"NSW",
    "sg:tags":[
        "sail",
        "shade"
    ],
    "wof:name":"Clarence Coast Constructions",
    "wof:placetype":"venue"
},
  "geometry": {"coordinates":[152.94691467300001,-29.7215080261],"type":"Point"}
}