{
  "type": "Feature",
  "properties": {
    "addr:full":"29 Clarence St Lake Munmorah NSW 2259",
    "addr:housenumber":"29",
    "addr:postcode":"2259",
    "addr:street":"Clarence St",
    "iso:country":"AU",
    "sg:address":"29 Clarence St",
    "sg:city":"Lake Munmorah",
    "sg:classifiers":[
        {
            "category":"Real Estate",
            "subcategory":"Real Estate Operator",
            "type":"Services"
        }
    ],
    "sg:phone":"+61 416 011 579",
    "sg:postcode":"2259",
    "sg:province":"NSW",
    "sg:tags":[
        "concrete",
        "pumping"
    ],
    "wof:name":"All Areas Concrete Pumping",
    "wof:placetype":"venue"
},
  "geometry": {"coordinates":[151.58274841299999,-33.1998214722],"type":"Point"}
}