{
  "type": "Feature",
  "properties": {
    "addr:full":"Middleton St Parkes NSW 2870",
    "addr:postcode":"2870",
    "addr:street":"Middleton St",
    "iso:country":"AU",
    "sg:address":"Middleton St",
    "sg:city":"Parkes",
    "sg:classifiers":[
        {
            "category":"Social Services",
            "subcategory":"Retirement Home",
            "type":"Services"
        }
    ],
    "sg:phone":"+61 2 6862 5800",
    "sg:postcode":"2870",
    "sg:province":"NSW",
    "sg:tags":[
        "village"
    ],
    "wof:name":"Southern Cross Village",
    "wof:placetype":"venue"
},
  "geometry": {"coordinates":[148.16525300000001,-33.134808],"type":"Point"}
}