{
  "type": "Feature",
  "properties": {
    "iso:country":"AU",
    "sg:address":"PO Box 583",
    "sg:city":"North Sydney",
    "sg:classifiers":[
        {
            "category":"Professional",
            "subcategory":"Engineering",
            "type":"Services"
        }
    ],
    "sg:phone":"+61 2 9411 1333",
    "sg:postcode":"2060",
    "sg:province":"NSW",
    "sg:tags":[
        "consulting",
        "engineer"
    ],
    "wof:name":"Association Of Hydraulic Services Consultants Australia (NSW) Inc",
    "wof:placetype":"venue"
},
  "geometry": {"coordinates":[151.207717895,-33.8398590088],"type":"Point"}
}