{
  "type": "Feature",
  "properties": {
    "iso:country":"AU",
    "sg:address":"8 Egerton St",
    "sg:city":"Silverwater",
    "sg:classifiers":[
        {
            "category":"Manufacturing",
            "subcategory":"Leather Goods",
            "type":"Manufacturing & Wholesale Goods"
        }
    ],
    "sg:phone":"+61 2 8748 9999",
    "sg:postcode":"2128",
    "sg:province":"NSW",
    "sg:tags":[
        "wholesaler",
        "mfrs"
    ],
    "wof:name":"Solar Leathergoods International Pty Ltd",
    "wof:placetype":"venue"
},
  "geometry": {"coordinates":[151.05296325699999,-33.8370742798],"type":"Point"}
}