{
  "type": "Feature",
  "properties": {
    "addr:full":"Suite 4, 7 John St Kingston TAS 7050",
    "addr:housenumber":"7",
    "addr:postcode":"7050",
    "addr:street":"John St",
    "iso:country":"AU",
    "sg:address":"Suite 4, 7 John St",
    "sg:city":"Kingston",
    "sg:classifiers":[
        {
            "category":"Health Services",
            "subcategory":"Health Practitioner",
            "type":"Services"
        }
    ],
    "sg:phone":"+61 3 6229 2111",
    "sg:postcode":"7050",
    "sg:province":"TAS",
    "sg:tags":[
        "psychologist"
    ],
    "wof:name":"Peter Hamer",
    "wof:placetype":"venue"
},
  "geometry": {"coordinates":[147.310104,-42.9841],"type":"Point"}
}