{
  "type": "Feature",
  "properties": {
    "addr:full":"26 Wright St Busselton WA 6280",
    "addr:housenumber":"26",
    "addr:postcode":"6280",
    "addr:street":"Wright St",
    "iso:country":"AU",
    "sg:address":"26 Wright St",
    "sg:city":"Busselton",
    "sg:classifiers":[
        {
            "category":"Building & Trades",
            "subcategory":"Cleaning & Sanitation",
            "type":"Services"
        }
    ],
    "sg:phone":"+61 8 9754 2911",
    "sg:postcode":"6280",
    "sg:province":"WA",
    "sg:tags":[
        "industrial",
        "commercial",
        "contractor"
    ],
    "wof:name":"Delron Cleaning",
    "wof:placetype":"venue"
},
  "geometry": {"coordinates":[115.347923279,-33.6676445007],"type":"Point"}
}