{
  "type": "Feature",
  "properties": {
    "addr:full":"84 Galah St Longreach QLD 4730",
    "addr:housenumber":"84",
    "addr:postcode":"4730",
    "addr:street":"Galah St",
    "iso:country":"AU",
    "sg:address":"84 Galah St",
    "sg:city":"Longreach",
    "sg:classifiers":[
        {
            "category":"Travel",
            "subcategory":"Hotels & Motels",
            "type":"Entertainment"
        }
    ],
    "sg:phone":"+61 7 4658 2322",
    "sg:postcode":"4730",
    "sg:province":"QLD",
    "wof:name":"Longreach Motor Inn",
    "wof:placetype":"venue"
},
  "geometry": {"coordinates":[144.252197,-23.441013],"type":"Point"}
}