{
  "type": "Feature",
  "properties": {
    "iso:country":"AU",
    "sg:address":"110 Landa St",
    "sg:city":"Lithgow",
    "sg:classifiers":[
        {
            "category":"Education",
            "subcategory":"Dance Studio",
            "type":"Public Place"
        }
    ],
    "sg:phone":"+61 2 6353 1964",
    "sg:postcode":"2790",
    "sg:province":"NSW",
    "sg:tags":[
        "venue",
        "tuition"
    ],
    "wof:name":"Lithgow Bootscooters",
    "wof:placetype":"venue"
},
  "geometry": {"coordinates":[150.13027954099999,-33.4900741577],"type":"Point"}
}