{
  "type": "Feature",
  "properties": {
    "addr:full":"156 Lance St Albany WA 6330",
    "addr:housenumber":"156",
    "addr:postcode":"6330",
    "addr:street":"Lance St",
    "iso:country":"AU",
    "sg:address":"156 Lance St",
    "sg:city":"Albany",
    "sg:classifiers":[
        {
            "category":"Building & Trades",
            "subcategory":"Plumbing",
            "type":"Services"
        }
    ],
    "sg:phone":"+61 8 9841 8594",
    "sg:postcode":"6330",
    "sg:province":"WA",
    "sg:tags":[
        "plumber",
        "gasfitters"
    ],
    "wof:name":"Marshall Smith Plumbing",
    "wof:placetype":"venue"
},
  "geometry": {"coordinates":[117.87220764200001,-34.9938964844],"type":"Point"}
}