{
  "type": "Feature",
  "properties": {
    "addr:full":"41 Forest Drv Jerrabomberra NSW 2619",
    "addr:housenumber":"41",
    "addr:postcode":"2619",
    "addr:street":"Forest Drv",
    "iso:country":"AU",
    "sg:address":"41 Forest Drv",
    "sg:city":"Jerrabomberra",
    "sg:classifiers":[
        {
            "category":"Personal",
            "type":"Services"
        }
    ],
    "sg:phone":"+61 2 6299 9487",
    "sg:postcode":"2619",
    "sg:province":"NSW",
    "sg:tags":[
        "gift"
    ],
    "wof:name":"Sweet Treat Bouquets",
    "wof:placetype":"venue"
},
  "geometry": {"coordinates":[149.19822692899999,-35.3925743103],"type":"Point"}
}