{
  "type": "Feature",
  "properties": {
    "iso:country":"AU",
    "sg:address":"The Mall 3/ 115 Brisbane St",
    "sg:city":"Launceston",
    "sg:classifiers":[
        {
            "category":"Personal",
            "subcategory":"Beauty Salon",
            "type":"Services"
        }
    ],
    "sg:phone":"+61 3 6334 3222",
    "sg:postcode":"7250",
    "sg:province":"TAS",
    "sg:tags":[
        "hairdresser"
    ],
    "wof:name":"Price Cutters",
    "wof:placetype":"venue"
},
  "geometry": {"coordinates":[147.13908386200001,-41.4373512268],"type":"Point"}
}