{
  "type": "Feature",
  "properties": {
    "addr:full":"42 Douglas St Milton QLD 4064",
    "addr:housenumber":"42",
    "addr:postcode":"4064",
    "addr:street":"Douglas St",
    "iso:country":"AU",
    "sg:address":"42 Douglas St",
    "sg:city":"Milton",
    "sg:classifiers":[
        {
            "category":"Wholesale",
            "subcategory":"Medical Equipment & Supplies",
            "type":"Manufacturing & Wholesale Goods"
        }
    ],
    "sg:phone":"+61 7 3369 0965",
    "sg:postcode":"4064",
    "sg:province":"QLD",
    "sg:tags":[
        "aid",
        "care",
        "health",
        "home"
    ],
    "wof:name":"Aitchison Ian & Co",
    "wof:placetype":"venue"
},
  "geometry": {"coordinates":[153.003616333,-27.4718284607],"type":"Point"}
}