{
  "type": "Feature",
  "properties": {
    "iso:country":"AU",
    "sg:address":"Ste 25/ 42-26 Wattle Rd",
    "sg:city":"Brookvale",
    "sg:classifiers":[
        {
            "category":"Shopping",
            "subcategory":"Gifts & Souvenirs",
            "type":"Retail Goods"
        }
    ],
    "sg:phone":"+61 2 9907 3388",
    "sg:postcode":"2100",
    "sg:province":"NSW",
    "sg:tags":[
        "shop",
        "supply"
    ],
    "wof:name":"Britt Design Pty Ltd",
    "wof:placetype":"venue"
},
  "geometry": {"coordinates":[151.262161255,-33.7668914795],"type":"Point"}
}