{
  "type": "Feature",
  "properties": {
    "addr:full":"38 Roswell St Glen Waverley VIC 3150",
    "addr:housenumber":"38",
    "addr:postcode":"3150",
    "addr:street":"Roswell St",
    "iso:country":"AU",
    "sg:address":"38 Roswell St",
    "sg:city":"Glen Waverley",
    "sg:classifiers":[
        {
            "category":"Building & Trades",
            "subcategory":"Cleaning & Sanitation",
            "type":"Services"
        }
    ],
    "sg:phone":"+61 418 956 177",
    "sg:postcode":"3150",
    "sg:province":"VIC",
    "sg:tags":[
        "industrial",
        "commercial",
        "contractor"
    ],
    "wof:name":"Glen Cleaning",
    "wof:placetype":"venue"
},
  "geometry": {"coordinates":[145.18504333499999,-37.883266449],"type":"Point"}
}