{
  "type": "Feature",
  "properties": {
    "iso:country":"AU",
    "sg:address":"Spacelands Shopping Centre Shop 11-12,73 John St",
    "sg:city":"Salisbury",
    "sg:classifiers":[
        {
            "category":"Food & Beverages",
            "subcategory":"Bakery",
            "type":"Retail Goods"
        }
    ],
    "sg:phone":"+61 8 8285 5166",
    "sg:postcode":"5108",
    "sg:province":"SA",
    "sg:tags":[
        "cake",
        "shop",
        "pastry"
    ],
    "wof:name":"Cheesecake Shop The",
    "wof:placetype":"venue"
},
  "geometry": {"coordinates":[138.64637756400001,-34.7621307373],"type":"Point"}
}