{
  "type": "Feature",
  "properties": {
    "addr:full":"42 Poole St Cootamundra NSW 2590",
    "addr:housenumber":"42",
    "addr:postcode":"2590",
    "addr:street":"Poole St",
    "iso:country":"AU",
    "sg:address":"42 Poole St",
    "sg:city":"Cootamundra",
    "sg:classifiers":[
        {
            "category":"Mining & Drilling",
            "type":"Manufacturing & Wholesale Goods"
        }
    ],
    "sg:phone":"+61 2 6942 3934",
    "sg:postcode":"2590",
    "sg:province":"NSW",
    "sg:tags":[
        "boring",
        "contractor"
    ],
    "wof:name":"Skillin P A & E A",
    "wof:placetype":"venue"
},
  "geometry": {"coordinates":[148.01716613799999,-34.638092041],"type":"Point"}
}