{
  "type": "Feature",
  "properties": {
    "addr:full":"1173 Botany Rd Mascot NSW 2020",
    "addr:housenumber":"1173",
    "addr:postcode":"2020",
    "addr:street":"Botany Rd",
    "iso:country":"AU",
    "sg:address":"1173 Botany Rd",
    "sg:city":"Mascot",
    "sg:classifiers":[
        {
            "category":"Fast Food",
            "type":"Food & Drink"
        }
    ],
    "sg:phone":"+61 2 9667 1982",
    "sg:postcode":"2020",
    "sg:province":"NSW",
    "sg:tags":[
        "away",
        "take"
    ],
    "wof:name":"Mascot Charcoal Chickens",
    "wof:placetype":"venue"
},
  "geometry": {"coordinates":[151.19450378400001,-33.930896759],"type":"Point"}
}