{
  "type": "Feature",
  "properties": {
    "addr:full":"20 Smalls Rd Ryde NSW 2112",
    "addr:housenumber":"20",
    "addr:postcode":"2112",
    "addr:street":"Smalls Rd",
    "iso:country":"AU",
    "sg:address":"20 Smalls Rd",
    "sg:city":"Ryde",
    "sg:classifiers":[
        {
            "category":"Education",
            "subcategory":"Vocational School",
            "type":"Public Place"
        }
    ],
    "sg:phone":"+61 2 9878 5656",
    "sg:postcode":"2112",
    "sg:province":"NSW",
    "sg:tags":[
        "cake",
        "decorating",
        "decorator"
    ],
    "wof:name":"Armstrong A A & M",
    "wof:placetype":"venue"
},
  "geometry": {"coordinates":[151.110198975,-33.7983856201],"type":"Point"}
}