{
  "type": "Feature",
  "properties": {
    "iso:country":"AU",
    "sg:address":"2/ 7 Banfield St",
    "sg:city":"Rosny",
    "sg:classifiers":[
        {
            "category":"Travel",
            "subcategory":"Travel Agent",
            "type":"Entertainment"
        }
    ],
    "sg:phone":"+61 13 18 66",
    "sg:postcode":"7018",
    "sg:province":"TAS",
    "sg:tags":[
        "consultant"
    ],
    "wof:name":"Flight Centre",
    "wof:placetype":"venue"
},
  "geometry": {"coordinates":[147.37005615199999,-42.866558075],"type":"Point"}
}