{
  "type": "Feature",
  "properties": {
    "addr:full":"120 Paris Rd Australind WA 6233",
    "addr:housenumber":"120",
    "addr:postcode":"6233",
    "addr:street":"Paris Rd",
    "iso:country":"AU",
    "sg:address":"120 Paris Rd",
    "sg:city":"Australind",
    "sg:classifiers":[
        {
            "category":"Health Services",
            "subcategory":"Doctor",
            "type":"Services"
        }
    ],
    "sg:phone":"+61 8 9725 8471",
    "sg:postcode":"6233",
    "sg:province":"WA",
    "sg:tags":[
        "medical",
        "practitioner"
    ],
    "wof:name":"Leschenault Medical Centre",
    "wof:placetype":"venue"
},
  "geometry": {"coordinates":[115.728722,-33.275249],"type":"Point"}
}