{
  "type": "Feature",
  "properties": {
    "iso:country":"AU",
    "sg:address":"Lot 1 South Gloucester St",
    "sg:city":"Forbes",
    "sg:classifiers":[
        {
            "category":"Building & Trades",
            "subcategory":"Pest Control",
            "type":"Services"
        }
    ],
    "sg:phone":"+61 2 6852 4390",
    "sg:postcode":"2871",
    "sg:province":"NSW",
    "sg:tags":[
        "equipment",
        "construction",
        "green",
        "bowling"
    ],
    "wof:name":"Mayo Trevor & Sharon",
    "wof:placetype":"venue"
},
  "geometry": {"coordinates":[148.001526,-33.376652],"type":"Point"}
}