{
  "type": "Feature",
  "properties": {
    "addr:full":"Shop 28, Northgate Plaza Chapman Rd Geraldton WA 6530",
    "addr:housenumber":"shop 28",
    "addr:postcode":"6530",
    "addr:street":"Northgate Plaza Chapman Rd",
    "iso:country":"AU",
    "sg:address":"Shop 28, Northgate Plaza Chapman Rd",
    "sg:city":"Geraldton",
    "sg:classifiers":[
        {
            "category":"Shopping",
            "subcategory":"Mobile Phones",
            "type":"Retail Goods"
        }
    ],
    "sg:phone":"+61 8 9964 8422",
    "sg:postcode":"6530",
    "sg:province":"WA",
    "sg:tags":[
        "telephone",
        "accessory"
    ],
    "wof:name":"Pocketphone",
    "wof:placetype":"venue"
},
  "geometry": {"coordinates":[114.62223815900001,-28.7424926758],"type":"Point"}
}