{
  "type": "Feature",
  "properties": {
    "iso:country":"AU",
    "sg:address":"2 Bowen Rd",
    "sg:city":"Moonah",
    "sg:classifiers":[
        {
            "category":"Retail",
            "subcategory":"Storage",
            "type":"Services"
        }
    ],
    "sg:phone":"+61 3 6278 8138",
    "sg:postcode":"7009",
    "sg:province":"TAS",
    "wof:name":"Scobies Storage And Business Centres",
    "wof:placetype":"venue"
},
  "geometry": {"coordinates":[147.30596923799999,-42.8500556946],"type":"Point"}
}