{
  "type": "Feature",
  "properties": {
    "addr:full":"Royal Pde Parkville VIC 3052",
    "addr:postcode":"3052",
    "addr:street":"Royal Pde",
    "iso:country":"AU",
    "sg:address":"Royal Pde",
    "sg:city":"Parkville",
    "sg:classifiers":[
        {
            "category":"Health Services",
            "subcategory":"Doctor",
            "type":"Services"
        }
    ],
    "sg:phone":"+61 3 9347 1550",
    "sg:postcode":"3052",
    "sg:province":"VIC",
    "sg:tags":[
        "medical",
        "practitioner"
    ],
    "wof:name":"Ebeling Peter R Dr",
    "wof:placetype":"venue"
},
  "geometry": {"coordinates":[144.95880126899999,-37.788356781],"type":"Point"}
}