{
  "type": "Feature",
  "properties": {
    "addr:full":"Unit 3/ 140 Millaroo Drv Gaven QLD 4211",
    "addr:housenumber":"/ 140",
    "addr:postcode":"4211",
    "addr:street":"Millaroo Drv",
    "iso:country":"AU",
    "sg:address":"Unit 3/ 140 Millaroo Drv",
    "sg:city":"Gaven",
    "sg:classifiers":[
        {
            "category":"Professional",
            "subcategory":"Testing Lab",
            "type":"Services"
        }
    ],
    "sg:phone":"+61 7 5580 1133",
    "sg:postcode":"4211",
    "sg:province":"QLD",
    "sg:tags":[
        "soil",
        "investigation"
    ],
    "wof:name":"Maiden Geotechnics",
    "wof:placetype":"venue"
},
  "geometry": {"coordinates":[153.337646484,-27.9389095306],"type":"Point"}
}