{
  "type": "Feature",
  "properties": {
    "addr:full":"42 Station St Fairfield VIC 3078",
    "addr:housenumber":"42",
    "addr:postcode":"3078",
    "addr:street":"Station St",
    "iso:country":"AU",
    "sg:address":"42 Station St",
    "sg:city":"Fairfield",
    "sg:classifiers":[
        {
            "category":"Health Services",
            "subcategory":"Doctor",
            "type":"Services"
        }
    ],
    "sg:phone":"+61 3 9486 6398",
    "sg:postcode":"3078",
    "sg:province":"VIC",
    "sg:tags":[
        "medical",
        "practitioner"
    ],
    "wof:name":"Darebin Endoscopy Services",
    "wof:placetype":"venue"
},
  "geometry": {"coordinates":[145.017578125,-37.7813491821],"type":"Point"}
}