{
  "type": "Feature",
  "properties": {
    "addr:full":"404 Newcastle St West Perth WA 6005",
    "addr:housenumber":"404",
    "addr:postcode":"6005",
    "addr:street":"Newcastle St",
    "iso:country":"AU",
    "sg:address":"404 Newcastle St",
    "sg:city":"West Perth",
    "sg:classifiers":[
        {
            "category":"Retail",
            "subcategory":"Auto Repair",
            "type":"Services"
        }
    ],
    "sg:phone":"+61 8 9228 3244",
    "sg:postcode":"6005",
    "sg:province":"WA",
    "sg:tags":[
        "clutch",
        "brake"
    ],
    "wof:name":"Exhaust World",
    "wof:placetype":"venue"
},
  "geometry": {"coordinates":[115.850059509,-31.9413166046],"type":"Point"}
}