{
  "type": "Feature",
  "properties": {
    "iso:country":"AU",
    "sg:address":"144 Edgecliff Rd",
    "sg:city":"Woollahra",
    "sg:classifiers":[
        {
            "category":"Personal",
            "subcategory":"Beauty Salon",
            "type":"Services"
        }
    ],
    "sg:phone":"+61 2 9369 4322",
    "sg:postcode":"2025",
    "sg:province":"NSW",
    "wof:name":"SALUS Face & Body",
    "wof:placetype":"venue"
},
  "geometry": {"coordinates":[151.24203491200001,-33.8848266602],"type":"Point"}
}