{
  "type": "Feature",
  "properties": {
    "iso:country":"AU",
    "sg:address":"81 Campbell St",
    "sg:city":"Oakey",
    "sg:classifiers":[
        {
            "category":"Fast Food",
            "type":"Food & Drink"
        }
    ],
    "sg:phone":"+61 7 4691 2749",
    "sg:postcode":"4401",
    "sg:province":"QLD",
    "sg:tags":[
        "away",
        "take"
    ],
    "wof:name":"Tuckerbox",
    "wof:placetype":"venue"
},
  "geometry": {"coordinates":[151.720794678,-27.4331550598],"type":"Point"}
}