{
  "type": "Feature",
  "properties": {
    "iso:country":"AU",
    "sg:address":"57 Station Rd",
    "sg:city":"Woodridge",
    "sg:classifiers":[
        {
            "category":"Health Services",
            "subcategory":"Optometrist",
            "type":"Services"
        }
    ],
    "sg:phone":"+61 7 3208 3644",
    "sg:postcode":"4114",
    "sg:province":"QLD",
    "wof:name":"Risdon Janet H",
    "wof:placetype":"venue"
},
  "geometry": {"coordinates":[153.10289001500001,-27.6372146606],"type":"Point"}
}