{
  "type": "Feature",
  "properties": {
    "addr:full":"39 Federal Rd Kalgoorlie WA 6430",
    "addr:housenumber":"39",
    "addr:postcode":"6430",
    "addr:street":"Federal Rd",
    "iso:country":"AU",
    "sg:address":"39 Federal Rd",
    "sg:city":"Kalgoorlie",
    "sg:classifiers":[
        {
            "category":"Health Services",
            "subcategory":"Chiropractor",
            "type":"Services"
        }
    ],
    "sg:phone":"+61 8 9021 4275",
    "sg:postcode":"6430",
    "sg:province":"WA",
    "wof:name":"Kalgoorlie Chiropractic Clinic",
    "wof:placetype":"venue"
},
  "geometry": {"coordinates":[121.487342834,-30.7624073029],"type":"Point"}
}