{
  "type": "Feature",
  "properties": {
    "addr:full":"Shop 153 Myer Centre, Queen St Mall Brisbane QLD 4000",
    "addr:housenumber":"153",
    "addr:postcode":"4000",
    "addr:street":"Myer Centre Queen St Mall",
    "iso:country":"AU",
    "sg:address":"Shop 153 Myer Centre, Queen St Mall",
    "sg:city":"Brisbane",
    "sg:classifiers":[
        {
            "category":"Retail",
            "subcategory":"Repair Shop",
            "type":"Services"
        }
    ],
    "sg:phone":"+61 7 3229 7032",
    "sg:postcode":"4000",
    "sg:province":"QLD",
    "sg:tags":[
        "handbag"
    ],
    "wof:name":"Strandbags",
    "wof:placetype":"venue"
},
  "geometry": {"coordinates":[153.02607727,-27.4689922333],"type":"Point"}
}