{
  "type": "Feature",
  "properties": {
    "addr:full":"2/ 77 Bulwer St Perth WA 6000",
    "addr:housenumber":"/ 77",
    "addr:postcode":"6000",
    "addr:street":"Bulwer St",
    "iso:country":"AU",
    "sg:address":"2/ 77 Bulwer St",
    "sg:city":"Perth",
    "sg:classifiers":[
        {
            "category":"Shopping",
            "subcategory":"Clothing, Apparel, & Fashions",
            "type":"Retail Goods"
        }
    ],
    "sg:phone":"+61 402 435 060",
    "sg:postcode":"6000",
    "sg:province":"WA",
    "sg:tags":[
        "recycled",
        "clothing"
    ],
    "wof:name":"Ragtrade",
    "wof:placetype":"venue"
},
  "geometry": {"coordinates":[115.859832764,-31.9393863678],"type":"Point"}
}