{
  "type": "Feature",
  "properties": {
    "addr:full":"U1/ 16 Newing Way Caloundra West QLD 4551",
    "addr:postcode":"4551",
    "addr:street":"U1 / 16 Newing Way",
    "iso:country":"AU",
    "sg:address":"U1/ 16 Newing Way",
    "sg:city":"Caloundra West",
    "sg:classifiers":[
        {
            "category":"Retail",
            "subcategory":"Auto Repair",
            "type":"Services"
        }
    ],
    "sg:phone":"+61 7 5438 0422",
    "sg:postcode":"4551",
    "sg:province":"QLD",
    "sg:tags":[
        "repairer",
        "motor",
        "engineer"
    ],
    "wof:name":"Boztech Automotive",
    "wof:placetype":"venue"
},
  "geometry": {"coordinates":[153.111236572,-26.7916107178],"type":"Point"}
}