{
  "type": "Feature",
  "properties": {
    "addr:full":"1 Glenwood Ave Glen Waverley VIC 3150",
    "addr:housenumber":"1",
    "addr:postcode":"3150",
    "addr:street":"Glenwood Ave",
    "iso:country":"AU",
    "sg:address":"1 Glenwood Ave",
    "sg:city":"Glen Waverley",
    "sg:classifiers":[
        {
            "category":"Professional",
            "subcategory":"Printing & Photocopies",
            "type":"Services"
        }
    ],
    "sg:phone":"+61 3 9560 5614",
    "sg:postcode":"3150",
    "sg:province":"VIC",
    "sg:tags":[
        "trophy"
    ],
    "wof:name":"Ted's Trophies",
    "wof:placetype":"venue"
},
  "geometry": {"coordinates":[145.157546997,-37.8883323669],"type":"Point"}
}