{
  "type": "Feature",
  "properties": {
    "addr:full":"131 Loftus Ave Loftus NSW 2232",
    "addr:housenumber":"131",
    "addr:postcode":"2232",
    "addr:street":"Loftus Ave",
    "iso:country":"AU",
    "sg:address":"131 Loftus Ave",
    "sg:city":"Loftus",
    "sg:classifiers":[
        {
            "category":"Education",
            "subcategory":"Dance Studio",
            "type":"Public Place"
        }
    ],
    "sg:phone":"+61 2 9521 1800",
    "sg:postcode":"2232",
    "sg:province":"NSW",
    "sg:tags":[
        "venue",
        "tuition"
    ],
    "wof:name":"Danceology",
    "wof:placetype":"venue"
},
  "geometry": {"coordinates":[151.051055908,-34.0463638306],"type":"Point"}
}