{
  "type": "Feature",
  "properties": {
    "iso:country":"AU",
    "sg:address":"49A Freshwater Rd",
    "sg:city":"Jingili",
    "sg:classifiers":[
        {
            "category":"Building & Trades",
            "subcategory":"Construction",
            "type":"Services"
        }
    ],
    "sg:phone":"+61 418 895 512",
    "sg:postcode":"0810",
    "sg:province":"NT",
    "sg:tags":[
        "earth",
        "excavating",
        "moving",
        "contractor"
    ],
    "wof:name":"Budget Plumbing",
    "wof:placetype":"venue"
},
  "geometry": {"coordinates":[130.87188720699999,-12.3904752731],"type":"Point"}
}