{
  "type": "Feature",
  "properties": {
    "addr:full":"935 Plenty Rd Bundoora VIC 3083",
    "addr:housenumber":"935",
    "addr:postcode":"3083",
    "addr:street":"Plenty Rd",
    "iso:country":"AU",
    "sg:address":"935 Plenty Rd",
    "sg:city":"Bundoora",
    "sg:classifiers":[
        {
            "category":"Shopping",
            "subcategory":"Clothing, Apparel, & Fashions",
            "type":"Retail Goods"
        }
    ],
    "sg:phone":"+61 3 9470 4105",
    "sg:postcode":"3083",
    "sg:province":"VIC",
    "sg:tags":[
        "menswear"
    ],
    "wof:name":"The Knitwear Gallery",
    "wof:placetype":"venue"
},
  "geometry": {"coordinates":[145.058425903,-37.6998710632],"type":"Point"}
}