{
  "type": "Feature",
  "properties": {
    "iso:country":"AU",
    "sg:address":"14/ 35-39 Fontenoy Rd",
    "sg:city":"Macquarie Park",
    "sg:classifiers":[
        {
            "category":"Utilities",
            "subcategory":"Mobile Phone",
            "type":"Services"
        }
    ],
    "sg:phone":"+61 2 9889 2977",
    "sg:postcode":"2113",
    "sg:province":"NSW",
    "sg:tags":[
        "assembly",
        "part",
        "electronic"
    ],
    "wof:name":"Entech Electronic Manufacturing",
    "wof:placetype":"venue"
},
  "geometry": {"coordinates":[151.12957763700001,-33.7766723633],"type":"Point"}
}