{
  "type": "Feature",
  "properties": {
    "addr:full":"39 Barton St Surrey Hills VIC 3127",
    "addr:housenumber":"39",
    "addr:postcode":"3127",
    "addr:street":"Barton St",
    "iso:country":"AU",
    "sg:address":"39 Barton St",
    "sg:city":"Surrey Hills",
    "sg:classifiers":[
        {
            "category":"Building & Trades",
            "subcategory":"Landscaping Services",
            "type":"Services"
        }
    ],
    "sg:phone":"+61 417 309 528",
    "sg:postcode":"3127",
    "sg:province":"VIC",
    "sg:tags":[
        "designer",
        "landscape",
        "contractor"
    ],
    "wof:name":"robb tidd landscape construction",
    "wof:placetype":"venue"
},
  "geometry": {"coordinates":[145.09991455100001,-37.8175315857],"type":"Point"}
}