{
  "type": "Feature",
  "properties": {
    "addr:full":"48 Quorn Rd Stirling North SA 5710",
    "addr:housenumber":"48",
    "addr:postcode":"5710",
    "addr:street":"Quorn Rd",
    "iso:country":"AU",
    "sg:address":"48 Quorn Rd",
    "sg:city":"Stirling North",
    "sg:classifiers":[
        {
            "category":"Government",
            "subcategory":"Post Office",
            "type":"Public Place"
        }
    ],
    "sg:phone":"+61 8 8643 6234",
    "sg:postcode":"5710",
    "sg:province":"SA",
    "sg:tags":[
        "postal"
    ],
    "wof:name":"Australia Post",
    "wof:placetype":"venue"
},
  "geometry": {"coordinates":[137.84027099599999,-32.5179367065],"type":"Point"}
}