{
  "type": "Feature",
  "properties": {
    "addr:full":"605 Elizabeth St Surry Hills NSW 2010",
    "addr:housenumber":"605",
    "addr:postcode":"2010",
    "addr:street":"Elizabeth St",
    "iso:country":"AU",
    "sg:address":"605 Elizabeth St",
    "sg:city":"Surry Hills",
    "sg:classifiers":[
        {
            "category":"Manufacturing",
            "subcategory":"Food",
            "type":"Manufacturing & Wholesale Goods"
        }
    ],
    "sg:phone":"+61 2 9319 2700",
    "sg:postcode":"2010",
    "sg:province":"NSW",
    "sg:tags":[
        "function",
        "catering"
    ],
    "wof:name":"Katering Pty Ltd",
    "wof:placetype":"venue"
},
  "geometry": {"coordinates":[151.207489014,-33.8914108276],"type":"Point"}
}