{
  "type": "Feature",
  "properties": {
    "addr:full":"3 Newbridge Rd Chipping Norton NSW 2170",
    "addr:housenumber":"3",
    "addr:postcode":"2170",
    "addr:street":"Newbridge Rd",
    "iso:country":"AU",
    "sg:address":"3 Newbridge Rd",
    "sg:city":"Chipping Norton",
    "sg:classifiers":[
        {
            "category":"Recreation",
            "subcategory":"Fishing",
            "type":"Entertainment"
        }
    ],
    "sg:phone":"+61 2 9821 4109",
    "sg:postcode":"2170",
    "sg:province":"NSW",
    "sg:tags":[
        "tackle"
    ],
    "wof:name":"Ace Fishing Tackle & Bait",
    "wof:placetype":"venue"
},
  "geometry": {"coordinates":[150.940948486,-33.9293861389],"type":"Point"}
}