{
  "type": "Feature",
  "properties": {
    "addr:full":"2 Hill St Burnside SA 5066",
    "addr:housenumber":"2",
    "addr:postcode":"5066",
    "addr:street":"Hill St",
    "iso:country":"AU",
    "sg:address":"2 Hill St",
    "sg:city":"Burnside",
    "sg:classifiers":[
        {
            "category":"Banks & Credit Unions",
            "subcategory":"Financial Services",
            "type":"Services"
        }
    ],
    "sg:phone":"+61 8 8431 8815",
    "sg:postcode":"5066",
    "sg:province":"SA",
    "sg:tags":[
        "planning"
    ],
    "wof:name":"Count Wealth Accountants",
    "wof:placetype":"venue"
},
  "geometry": {"coordinates":[138.66166687,-34.9393081665],"type":"Point"}
}