{
  "type": "Feature",
  "properties": {
    "addr:full":"427 Darling St Balmain NSW 2041",
    "addr:housenumber":"427",
    "addr:postcode":"2041",
    "addr:street":"Darling St",
    "iso:country":"AU",
    "sg:address":"427 Darling St",
    "sg:city":"Balmain",
    "sg:classifiers":[
        {
            "category":"Farming",
            "subcategory":"Nursery",
            "type":"Manufacturing & Wholesale Goods"
        }
    ],
    "sg:phone":"+61 2 9810 3517",
    "sg:postcode":"2041",
    "sg:province":"NSW",
    "wof:name":"Bonsai & Beyond Garden Centre Pty Ltd",
    "wof:placetype":"venue"
},
  "geometry": {"coordinates":[151.17507900000001,-33.855797],"type":"Point"}
}