{
  "type": "Feature",
  "properties": {
    "iso:country":"AU",
    "sg:address":"29 Williewa St",
    "sg:city":"Portland",
    "sg:classifiers":[
        {
            "category":"Personal",
            "subcategory":"Beauty Salon",
            "type":"Services"
        }
    ],
    "sg:phone":"+61 2 6355 5411",
    "sg:postcode":"2847",
    "sg:province":"NSW",
    "sg:tags":[
        "hairdresser"
    ],
    "wof:name":"Hair Perfection",
    "wof:placetype":"venue"
},
  "geometry": {"coordinates":[149.980469,-33.352989],"type":"Point"}
}