{
  "type": "Feature",
  "properties": {
    "addr:full":"Cnr Lake & Aplin Sts Cairns QLD 4870",
    "addr:postcode":"4870",
    "addr:street":"Cnr",
    "iso:country":"AU",
    "sg:address":"Cnr Lake & Aplin Sts",
    "sg:city":"Cairns",
    "sg:classifiers":[
        {
            "category":"Recreation",
            "type":"Entertainment"
        }
    ],
    "sg:phone":"+61 7 4051 8722",
    "sg:postcode":"4870",
    "sg:province":"QLD",
    "sg:tags":[
        "recreational",
        "diver"
    ],
    "wof:name":"Taka Dive Adventures",
    "wof:placetype":"venue"
},
  "geometry": {"coordinates":[145.779205322,-16.9260311127],"type":"Point"}
}