{
  "type": "Feature",
  "properties": {
    "iso:country":"AU",
    "sg:address":"PO Box 239",
    "sg:city":"Epping",
    "sg:classifiers":[
        {
            "category":"Building & Trades",
            "subcategory":"Plumbing",
            "type":"Services"
        }
    ],
    "sg:phone":"+61 1800 641 449",
    "sg:postcode":"3076",
    "sg:province":"VIC",
    "sg:tags":[
        "plumber",
        "gasfitters"
    ],
    "wof:name":"Adirondack Plumbing & Gas",
    "wof:placetype":"venue"
},
  "geometry": {"coordinates":[145.009490967,-37.6383590698],"type":"Point"}
}