{
  "type": "Feature",
  "properties": {
    "addr:full":"Shp 4/ 41 Willarong Rd Caringbah NSW 2229",
    "addr:housenumber":"/ 41",
    "addr:postcode":"2229",
    "addr:street":"Willarong Rd",
    "iso:country":"AU",
    "sg:address":"Shp 4/ 41 Willarong Rd",
    "sg:city":"Caringbah",
    "sg:classifiers":[
        {
            "category":"Social Services",
            "subcategory":"Retirement Home",
            "type":"Services"
        }
    ],
    "sg:phone":"+61 2 9542 7177",
    "sg:postcode":"2229",
    "sg:province":"NSW",
    "sg:tags":[
        "furrier"
    ],
    "wof:name":"Custom Designs",
    "wof:placetype":"venue"
},
  "geometry": {"coordinates":[151.12240600600001,-34.0294418335],"type":"Point"}
}