{
  "type": "Feature",
  "properties": {
    "iso:country":"AU",
    "sg:address":"5 Wirriga St",
    "sg:city":"Regency Park",
    "sg:classifiers":[
        {
            "category":"Autos & Motor Vehicles",
            "subcategory":"Auto Supplies",
            "type":"Retail Goods"
        }
    ],
    "sg:phone":"+61 8 8347 1622",
    "sg:postcode":"5010",
    "sg:province":"SA",
    "sg:tags":[
        "equipment",
        "part",
        "truck"
    ],
    "wof:name":"Barry Stoodley Pty Ltd",
    "wof:placetype":"venue"
},
  "geometry": {"coordinates":[138.56617736800001,-34.8533821106],"type":"Point"}
}