{
  "type": "Feature",
  "properties": {
    "iso:country":"AU",
    "sg:address":"37 Benwerrin Drv",
    "sg:city":"Burwood East",
    "sg:classifiers":[
        {
            "category":"Building & Trades",
            "subcategory":"Construction",
            "type":"Services"
        }
    ],
    "sg:phone":"+61 3 9803 5444",
    "sg:postcode":"3151",
    "sg:province":"VIC",
    "sg:tags":[
        "industrial",
        "commercial",
        "air conditioning"
    ],
    "wof:name":"EN-MET Pty Ltd",
    "wof:placetype":"venue"
},
  "geometry": {"coordinates":[145.1431427,-37.8553123474],"type":"Point"}
}