{
  "type": "Feature",
  "properties": {
    "addr:full":"15 Farrell Pl Boondall QLD 4034",
    "addr:housenumber":"15",
    "addr:postcode":"4034",
    "addr:street":"Farrell Pl",
    "iso:country":"AU",
    "sg:address":"15 Farrell Pl",
    "sg:city":"Boondall",
    "sg:classifiers":[
        {
            "category":"Building & Trades",
            "subcategory":"Cleaning & Sanitation",
            "type":"Services"
        }
    ],
    "sg:phone":"+61 7 3265 7572",
    "sg:postcode":"4034",
    "sg:province":"QLD",
    "sg:tags":[
        "industrial",
        "commercial",
        "contractor"
    ],
    "wof:name":"A.aaabacus Carpet & Curtain Cleaning Service",
    "wof:placetype":"venue"
},
  "geometry": {"coordinates":[153.05751000000001,-27.350689],"type":"Point"}
}