{
  "type": "Feature",
  "properties": {
    "addr:full":"22 Wey St Blackwater QLD 4717",
    "addr:housenumber":"22",
    "addr:postcode":"4717",
    "addr:street":"Wey St",
    "iso:country":"AU",
    "sg:address":"22 Wey St",
    "sg:city":"Blackwater",
    "sg:classifiers":[
        {
            "category":"Professional",
            "subcategory":"Art Services",
            "type":"Services"
        }
    ],
    "sg:phone":"+61 7 4982 5187",
    "sg:postcode":"4717",
    "sg:province":"QLD",
    "sg:tags":[
        "decorator",
        "painter"
    ],
    "wof:name":"North West Painters",
    "wof:placetype":"venue"
},
  "geometry": {"coordinates":[148.87730400000001,-23.583204],"type":"Point"}
}