{
  "type": "Feature",
  "properties": {
    "addr:full":"62 West St Casino NSW 2470",
    "addr:housenumber":"62",
    "addr:postcode":"2470",
    "addr:street":"West St",
    "iso:country":"AU",
    "sg:address":"62 West St",
    "sg:city":"Casino",
    "sg:classifiers":[
        {
            "category":"Building & Trades",
            "subcategory":"Construction",
            "type":"Services"
        }
    ],
    "sg:phone":"+61 1300 761 816",
    "sg:postcode":"2470",
    "sg:province":"NSW",
    "sg:tags":[
        "monumental",
        "mason"
    ],
    "wof:name":"Casino Monuments",
    "wof:placetype":"venue"
},
  "geometry": {"coordinates":[153.04302978499999,-28.8646831512],"type":"Point"}
}