{
  "type": "Feature",
  "properties": {
    "addr:full":"65 Downey St Alexandra VIC 3714",
    "addr:housenumber":"65",
    "addr:postcode":"3714",
    "addr:street":"Downey St",
    "iso:country":"AU",
    "sg:address":"65 Downey St",
    "sg:city":"Alexandra",
    "sg:classifiers":[
        {
            "category":"Home & Garden",
            "subcategory":"Household Appliances",
            "type":"Retail Goods"
        }
    ],
    "sg:phone":"+61 3 5772 3380",
    "sg:postcode":"3714",
    "sg:province":"VIC",
    "sg:tags":[
        "heating",
        "system"
    ],
    "wof:name":"Bowd Heating",
    "wof:placetype":"venue"
},
  "geometry": {"coordinates":[145.70504760700001,-37.1925544739],"type":"Point"}
}