{
  "type": "Feature",
  "properties": {
    "iso:country":"AU",
    "sg:address":"130 Princess Rd",
    "sg:city":"Nedlands",
    "sg:classifiers":[
        {
            "category":"Professional",
            "subcategory":"Art Services",
            "type":"Services"
        }
    ],
    "sg:phone":"+61 8 9304 7229",
    "sg:postcode":"6009",
    "sg:province":"WA",
    "sg:tags":[
        "interior",
        "decorator"
    ],
    "wof:name":"Morriosn Interiors",
    "wof:placetype":"venue"
},
  "geometry": {"coordinates":[115.81723,-31.986267],"type":"Point"}
}