{
  "type": "Feature",
  "properties": {
    "addr:full":"32 Burrows Rd Alexandria NSW 2015",
    "addr:housenumber":"32",
    "addr:postcode":"2015",
    "addr:street":"Burrows Rd",
    "iso:country":"AU",
    "sg:address":"32 Burrows Rd",
    "sg:city":"Alexandria",
    "sg:classifiers":[
        {
            "category":"Utilities",
            "subcategory":"Refuse",
            "type":"Services"
        }
    ],
    "sg:phone":"+61 2 9519 9999",
    "sg:postcode":"2015",
    "sg:province":"NSW",
    "sg:tags":[
        "disposal",
        "reduction",
        "waste"
    ],
    "sg:website":"http://www.dialadump.com.au",
    "wof:name":"Dial A Dump",
    "wof:placetype":"venue"
},
  "geometry": {"coordinates":[151.18470764200001,-33.9166107178],"type":"Point"}
}