{
  "type": "Feature",
  "properties": {
    "addr:full":"10 May Holman Drv Bassendean WA 6054",
    "addr:housenumber":"10",
    "addr:postcode":"6054",
    "addr:street":"May Holman Drv",
    "iso:country":"AU",
    "sg:address":"10 May Holman Drv",
    "sg:city":"Bassendean",
    "sg:classifiers":[
        {
            "category":"Building & Trades",
            "subcategory":"Landscaping Services",
            "type":"Services"
        }
    ],
    "sg:phone":"+61 8 6278 2688",
    "sg:postcode":"6054",
    "sg:province":"WA",
    "sg:tags":[
        "designer",
        "landscape",
        "contractor"
    ],
    "wof:name":"Elegant Landscapes",
    "wof:placetype":"venue"
},
  "geometry": {"coordinates":[115.939857483,-31.9072685242],"type":"Point"}
}