{
  "type": "Feature",
  "properties": {
    "iso:country":"AU",
    "sg:address":"Shop 25/ 53",
    "sg:city":"Cecil Av Cannington",
    "sg:classifiers":[
        {
            "category":"Health Services",
            "subcategory":"Medical Lab",
            "type":"Services"
        }
    ],
    "sg:phone":"+61 8 9451 1477",
    "sg:postcode":"6107",
    "sg:province":"WA",
    "sg:tags":[
        "laboratory",
        "dental"
    ],
    "wof:name":"Denture Professionals",
    "wof:placetype":"venue"
},
  "geometry": {"coordinates":[115.93724822999999,-32.0164375305],"type":"Point"}
}