{
  "type": "Feature",
  "properties": {
    "addr:full":"18 Highview St Blacktown NSW 2148",
    "addr:housenumber":"18",
    "addr:postcode":"2148",
    "addr:street":"Highview St",
    "iso:country":"AU",
    "sg:address":"18 Highview St",
    "sg:city":"Blacktown",
    "sg:classifiers":[
        {
            "category":"Home & Garden",
            "subcategory":"Home Furnishings",
            "type":"Retail Goods"
        }
    ],
    "sg:phone":"+61 2 9920 5625",
    "sg:postcode":"2148",
    "sg:province":"NSW",
    "sg:tags":[
        "candle"
    ],
    "wof:name":"Pitta Patta Designs",
    "wof:placetype":"venue"
},
  "geometry": {"coordinates":[150.89729309099999,-33.78565979],"type":"Point"}
}