{
  "type": "Feature",
  "properties": {
    "iso:country":"AU",
    "sg:address":"10 Len Shield St",
    "sg:city":"Mackay",
    "sg:classifiers":[
        {
            "category":"Real Estate",
            "subcategory":"Real Estate Agent",
            "type":"Services"
        }
    ],
    "sg:phone":"+61 7 4952 6233",
    "sg:postcode":"4740",
    "sg:province":"QLD",
    "sg:tags":[
        "handyman's",
        "equipment",
        "hire",
        "builders",
        "contractor"
    ],
    "sg:website":"http://www.flexihire.com.au",
    "wof:name":"Flexihire",
    "wof:placetype":"venue"
},
  "geometry": {"coordinates":[149.166016,-21.177898],"type":"Point"}
}