{
  "type": "Feature",
  "properties": {
    "addr:full":"493 Main Rd Glenorchy TAS 7010",
    "addr:housenumber":"493",
    "addr:postcode":"7010",
    "addr:street":"Main Rd",
    "iso:country":"AU",
    "sg:address":"493 Main Rd",
    "sg:city":"Glenorchy",
    "sg:classifiers":[
        {
            "category":"Landmark",
            "subcategory":"Scenic View",
            "type":"Public Place"
        }
    ],
    "sg:phone":"+61 3 6273 3579",
    "sg:postcode":"7010",
    "sg:province":"TAS",
    "sg:tags":[
        "staircase",
        "handrail"
    ],
    "wof:name":"Complete Stairs",
    "wof:placetype":"venue"
},
  "geometry": {"coordinates":[147.26771545400001,-42.8274536133],"type":"Point"}
}