{
  "type": "Feature",
  "properties": {
    "addr:full":"6 Perrett Ave St Albans VIC 3021",
    "addr:housenumber":"6",
    "addr:postcode":"3021",
    "addr:street":"Perrett Ave",
    "iso:country":"AU",
    "sg:address":"6 Perrett Ave",
    "sg:city":"St Albans",
    "sg:classifiers":[
        {
            "category":"Professional",
            "subcategory":"Detective & Security Services",
            "type":"Services"
        }
    ],
    "sg:phone":"+61 3 9356 0173",
    "sg:postcode":"3021",
    "sg:province":"VIC",
    "sg:tags":[
        "domestic",
        "alarm",
        "commercial",
        "burglar"
    ],
    "wof:name":"All Safe Security Services",
    "wof:placetype":"venue"
},
  "geometry": {"coordinates":[144.82038900000001,-37.737556],"type":"Point"}
}