{
  "type": "Feature",
  "properties": {
    "addr:full":"33 Melbourne Rd Yea VIC 3717",
    "addr:housenumber":"33",
    "addr:postcode":"3717",
    "addr:street":"Melbourne Rd",
    "iso:country":"AU",
    "sg:address":"33 Melbourne Rd",
    "sg:city":"Yea",
    "sg:classifiers":[
        {
            "category":"Personal",
            "subcategory":"Beauty Salon",
            "type":"Services"
        }
    ],
    "sg:phone":"+61 3 5797 2965",
    "sg:postcode":"3717",
    "sg:province":"VIC",
    "sg:tags":[
        "hairdresser"
    ],
    "wof:name":"Yea Hair Design",
    "wof:placetype":"venue"
},
  "geometry": {"coordinates":[145.41864013700001,-37.2170600891],"type":"Point"}
}