{
  "type": "Feature",
  "properties": {
    "addr:full":"145D Musgrave St North Rockhampton QLD 4701",
    "addr:housenumber":"145d",
    "addr:postcode":"4701",
    "addr:street":"Musgrave St North",
    "iso:country":"AU",
    "sg:address":"145D Musgrave St",
    "sg:city":"North Rockhampton",
    "sg:classifiers":[
        {
            "category":"Retail",
            "subcategory":"Laundry & Dry Cleaning",
            "type":"Services"
        }
    ],
    "sg:phone":"+61 417 736 346",
    "sg:postcode":"4701",
    "sg:province":"QLD",
    "wof:name":"Rockhampton Speed Queen Laundrette",
    "wof:placetype":"venue"
},
  "geometry": {"coordinates":[150.52215576200001,-23.3644256592],"type":"Point"}
}