{
  "type": "Feature",
  "properties": {
    "addr:full":"5 Durham Ave St Ives NSW 2075",
    "addr:housenumber":"5",
    "addr:postcode":"2075",
    "addr:street":"Durham Ave",
    "iso:country":"AU",
    "sg:address":"5 Durham Ave",
    "sg:city":"St Ives",
    "sg:classifiers":[
        {
            "category":"Health Services",
            "subcategory":"Medical Lab",
            "type":"Services"
        }
    ],
    "sg:phone":"+61 2 9449 6462",
    "sg:postcode":"2075",
    "sg:province":"NSW",
    "sg:tags":[
        "laboratory",
        "dental"
    ],
    "wof:name":"Kulbert Z Paul",
    "wof:placetype":"venue"
},
  "geometry": {"coordinates":[151.160522461,-33.730014801],"type":"Point"}
}