{
  "type": "Feature",
  "properties": {
    "addr:full":"Gate 1, Subiaco Oval, Subiaco Rd Subiaco WA 6008",
    "addr:housenumber":"1",
    "addr:postcode":"6008",
    "addr:street":"Gate;Subiaco Rd",
    "iso:country":"AU",
    "sg:address":"Gate 1, Subiaco Oval, Subiaco Rd",
    "sg:city":"Subiaco",
    "sg:classifiers":[
        {
            "category":"Arena",
            "subcategory":"Sports Club",
            "type":"Entertainment"
        }
    ],
    "sg:phone":"+61 8 6380 1311",
    "sg:postcode":"6008",
    "sg:province":"WA",
    "sg:tags":[
        "australian",
        "football",
        "rule"
    ],
    "wof:name":"W.A. Amateur Football League Inc",
    "wof:placetype":"venue"
},
  "geometry": {"coordinates":[115.841171265,-31.9437599182],"type":"Point"}
}