{
  "type": "Feature",
  "properties": {
    "addr:full":"Prahan Market 195 Commercial Rd South Yarra VIC 3141",
    "addr:housenumber":"195",
    "addr:postcode":"3141",
    "addr:street":"Commercial Rd",
    "iso:country":"AU",
    "sg:address":"Prahan Market 195 Commercial Rd",
    "sg:city":"South Yarra",
    "sg:classifiers":[
        {
            "category":"Banks & Credit Unions",
            "subcategory":"Investment Brokerage",
            "type":"Services"
        }
    ],
    "sg:phone":"+61 1800 653 061",
    "sg:postcode":"3141",
    "sg:province":"VIC",
    "wof:name":"Commonwealth Financial Planning",
    "wof:placetype":"venue"
},
  "geometry": {"coordinates":[144.99281310999999,-37.8465385437],"type":"Point"}
}