{
  "type": "Feature",
  "properties": {
    "iso:country":"AU",
    "sg:address":"18 Princes Hwy",
    "sg:city":"Arncliffe",
    "sg:classifiers":[
        {
            "category":"Taxi",
            "type":"Transportation"
        }
    ],
    "sg:phone":"+61 2 9567 3800",
    "sg:postcode":"2205",
    "sg:province":"NSW",
    "sg:tags":[
        "cab"
    ],
    "wof:name":"Go Cabs",
    "wof:placetype":"venue"
},
  "geometry": {"coordinates":[151.153336,-33.933125],"type":"Point"}
}