{
  "type": "Feature",
  "properties": {
    "iso:country":"AU",
    "sg:address":"Level 4/ 252 Swanston St",
    "sg:city":"Melbourne",
    "sg:classifiers":[
        {
            "category":"Arena",
            "subcategory":"Sports Club",
            "type":"Entertainment"
        }
    ],
    "sg:phone":"+61 3 9650 8280",
    "sg:postcode":"3000",
    "sg:province":"VIC",
    "sg:tags":[
        "defence",
        "supply",
        "self",
        "instruction",
        "martial art"
    ],
    "sg:website":"http://www.wingchunbingfakungfu.com.au",
    "wof:name":"Wing Chun Bing Fa Kung Fu",
    "wof:placetype":"venue"
},
  "geometry": {"coordinates":[144.965118408,-37.8120384216],"type":"Point"}
}