{
  "type": "Feature",
  "properties": {
    "addr:full":"Lot 3 Geebung St Polo Flat Cooma NSW 2630",
    "addr:postcode":"2630",
    "addr:street":"Geebung St Polo",
    "iso:country":"AU",
    "sg:address":"Lot 3 Geebung St Polo Flat",
    "sg:city":"Cooma",
    "sg:classifiers":[
        {
            "category":"Building & Trades",
            "subcategory":"Construction",
            "type":"Services"
        }
    ],
    "sg:phone":"+61 2 6452 5125",
    "sg:postcode":"2630",
    "sg:province":"NSW",
    "sg:tags":[
        "welding"
    ],
    "wof:name":"Allenspach Steel",
    "wof:placetype":"venue"
},
  "geometry": {"coordinates":[149.14857482900001,-36.2242393494],"type":"Point"}
}