{
  "type": "Feature",
  "properties": {
    "addr:full":"137 King George St Cohuna VIC 3568",
    "addr:housenumber":"137",
    "addr:postcode":"3568",
    "addr:street":"King George St",
    "iso:country":"AU",
    "sg:address":"137 King George St",
    "sg:city":"Cohuna",
    "sg:classifiers":[
        {
            "category":"Banks & Credit Unions",
            "subcategory":"Financial Services",
            "type":"Services"
        }
    ],
    "sg:phone":"+61 3 5456 2183",
    "sg:postcode":"3568",
    "sg:province":"VIC",
    "sg:tags":[
        "advisory",
        "planning",
        "retirement"
    ],
    "wof:name":"AMP Cohuna",
    "wof:placetype":"venue"
},
  "geometry": {"coordinates":[144.221099853,-35.8085784912],"type":"Point"}
}