{
  "type": "Feature",
  "properties": {
    "iso:country":"AU",
    "sg:address":"35 Jack St",
    "sg:city":"Toowoomba",
    "sg:classifiers":[
        {
            "category":"Arena",
            "subcategory":"Indoor Arena",
            "type":"Entertainment"
        }
    ],
    "sg:phone":"+61 7 4636 3613",
    "sg:postcode":"4350",
    "sg:province":"QLD",
    "sg:tags":[
        "modelmakers"
    ],
    "wof:name":"Rime Chan Design",
    "wof:placetype":"venue"
},
  "geometry": {"coordinates":[151.935867,-27.59713],"type":"Point"}
}