{
  "type": "Feature",
  "properties": {
    "addr:full":"10 Parkes St Kirribilli NSW 2061",
    "addr:housenumber":"10",
    "addr:postcode":"2061",
    "addr:street":"Parkes St",
    "iso:country":"AU",
    "sg:address":"10 Parkes St",
    "sg:city":"Kirribilli",
    "sg:classifiers":[
        {
            "category":"Travel",
            "subcategory":"Hotels & Motels",
            "type":"Entertainment"
        }
    ],
    "sg:phone":"+61 2 9925 0517",
    "sg:postcode":"2061",
    "sg:province":"NSW",
    "sg:tags":[
        "accommodation"
    ],
    "wof:name":"Carnarvon Private Hotel Kirribilli",
    "wof:placetype":"venue"
},
  "geometry": {"coordinates":[151.21583557100001,-33.8479309082],"type":"Point"}
}