{
  "type": "Feature",
  "properties": {
    "addr:full":"242 Merrylands Rd Merrylands NSW 2160",
    "addr:housenumber":"242",
    "addr:postcode":"2160",
    "addr:street":"Merrylands Rd",
    "iso:country":"AU",
    "sg:address":"242 Merrylands Rd",
    "sg:city":"Merrylands",
    "sg:classifiers":[
        {
            "category":"Health Services",
            "subcategory":"Podiatrist",
            "type":"Services"
        }
    ],
    "sg:phone":"+61 2 9637 5620",
    "sg:postcode":"2160",
    "sg:province":"NSW",
    "sg:tags":[
        "cap",
        "hat",
        "renovation",
        "retail"
    ],
    "wof:name":"Hat Hospital The",
    "wof:placetype":"venue"
},
  "geometry": {"coordinates":[150.98794555699999,-33.8362121582],"type":"Point"}
}