{
  "type": "Feature",
  "properties": {
    "iso:country":"AU",
    "sg:address":"39 Withers St",
    "sg:city":"North Rockhampton",
    "sg:classifiers":[
        {
            "category":"Real Estate",
            "subcategory":"Surveying",
            "type":"Services"
        }
    ],
    "sg:phone":"+61 7 4922 3834",
    "sg:postcode":"4701",
    "sg:province":"QLD",
    "sg:tags":[
        "surveyor",
        "land"
    ],
    "wof:name":"Hoffmann A.J. & M.K. Pty Ltd",
    "wof:placetype":"venue"
},
  "geometry": {"coordinates":[150.502975464,-23.3388957977],"type":"Point"}
}