{
  "type": "Feature",
  "properties": {
    "addr:full":"Shop 5 Waurn Ponds Shopping Centre Opposite Safeway Waurn Ponds VIC 3216",
    "addr:housenumber":"shop 5;opposite",
    "addr:postcode":"3216",
    "addr:street":"Waurn Ponds Shopping",
    "iso:country":"AU",
    "sg:address":"Shop 5 Waurn Ponds Shopping Centre Opposite Safeway",
    "sg:city":"Waurn Ponds",
    "sg:classifiers":[
        {
            "category":"Food & Beverages",
            "subcategory":"Meat & Fish",
            "type":"Retail Goods"
        }
    ],
    "sg:phone":"+61 3 5243 7119",
    "sg:postcode":"3216",
    "sg:province":"VIC",
    "sg:tags":[
        "seafood"
    ],
    "wof:name":"Fish Day",
    "wof:placetype":"venue"
},
  "geometry": {"coordinates":[144.30209350600001,-38.2035293579],"type":"Point"}
}