{
  "type": "Feature",
  "properties": {
    "addr:full":"355 Bong Bong Rd Bowral NSW 2576",
    "addr:housenumber":"355",
    "addr:postcode":"2576",
    "addr:street":"Bong Bong Rd",
    "iso:country":"AU",
    "sg:address":"355 Bong Bong Rd",
    "sg:city":"Bowral",
    "sg:classifiers":[
        {
            "category":"Shopping",
            "subcategory":"Clothing, Apparel, & Fashions",
            "type":"Retail Goods"
        }
    ],
    "sg:phone":"+61 2 4861 7092",
    "sg:postcode":"2576",
    "sg:province":"NSW",
    "sg:tags":[
        "lady",
        "wear"
    ],
    "wof:name":"Miller's Fashion Club",
    "wof:placetype":"venue"
},
  "geometry": {"coordinates":[150.417694092,-34.4804115295],"type":"Point"}
}