{
  "type": "Feature",
  "properties": {
    "addr:full":"Level 1/ 601 Botany Rd Rosebery NSW 2018",
    "addr:housenumber":"/ 601",
    "addr:postcode":"2018",
    "addr:street":"Botany Rd",
    "iso:country":"AU",
    "sg:address":"Level 1/ 601 Botany Rd",
    "sg:city":"Rosebery",
    "sg:classifiers":[
        {
            "category":"Professional",
            "type":"Services"
        }
    ],
    "sg:phone":"+61 1300 306 830",
    "sg:postcode":"2018",
    "sg:province":"NSW",
    "sg:tags":[
        "control",
        "equipment",
        "traffic"
    ],
    "wof:name":"Workforce International",
    "wof:placetype":"venue"
},
  "geometry": {"coordinates":[151.20214843799999,-33.9113006592],"type":"Point"}
}