{
  "type": "Feature",
  "properties": {
    "addr:full":"Shop 3/ 1015 Lower North East Road Highbury SA 5089",
    "addr:housenumber":"shop 3 / 1015",
    "addr:postcode":"5089",
    "addr:street":"Lower North East Road",
    "iso:country":"AU",
    "sg:address":"Shop 3/ 1015 Lower North East Road",
    "sg:city":"Highbury",
    "sg:classifiers":[
        {
            "category":"Health Services",
            "subcategory":"Dentist",
            "type":"Services"
        }
    ],
    "sg:phone":"+61 8 8265 6082",
    "sg:postcode":"5089",
    "sg:province":"SA",
    "wof:name":"Sokolowski Chris",
    "wof:placetype":"venue"
},
  "geometry": {"coordinates":[138.70033264200001,-34.8527069092],"type":"Point"}
}