{
  "type": "Feature",
  "properties": {
    "addr:full":"110- 114 Almond Ave Mildura VIC 3500",
    "addr:housenumber":"114",
    "addr:postcode":"3500",
    "addr:street":"Almond Ave",
    "iso:country":"AU",
    "sg:address":"110- 114 Almond Ave",
    "sg:city":"Mildura",
    "sg:classifiers":[
        {
            "category":"Professional",
            "type":"Services"
        }
    ],
    "sg:phone":"+61 3 5023 2841",
    "sg:postcode":"3500",
    "sg:province":"VIC",
    "sg:tags":[
        "spray",
        "painting"
    ],
    "wof:name":"Boseley's Crash Repairs",
    "wof:placetype":"venue"
},
  "geometry": {"coordinates":[142.16668701200001,-34.1936912537],"type":"Point"}
}