{
  "type": "Feature",
  "properties": {
    "iso:country":"AU",
    "sg:address":"66 Leather St",
    "sg:city":"Breakwater",
    "sg:classifiers":[
        {
            "category":"Building & Trades",
            "subcategory":"Construction",
            "type":"Services"
        }
    ],
    "sg:phone":"+61 3 5248 8822",
    "sg:postcode":"3219",
    "sg:province":"VIC",
    "sg:tags":[
        "window",
        "timber"
    ],
    "wof:name":"Window Warehouse",
    "wof:placetype":"venue"
},
  "geometry": {"coordinates":[144.37991332999999,-38.1861839294],"type":"Point"}
}