{
  "type": "Feature",
  "properties": {
    "addr:full":"36 Addison Rd Manly NSW 2095",
    "addr:housenumber":"36",
    "addr:postcode":"2095",
    "addr:street":"Addison Rd",
    "iso:country":"AU",
    "sg:address":"36 Addison Rd",
    "sg:city":"Manly",
    "sg:classifiers":[
        {
            "category":"Professional",
            "subcategory":"Computer Services",
            "type":"Services"
        }
    ],
    "sg:phone":"+61 2 9976 4500",
    "sg:postcode":"2095",
    "sg:province":"NSW",
    "sg:tags":[
        "on-line",
        "provider"
    ],
    "wof:name":"Avoka Technologies",
    "wof:placetype":"venue"
},
  "geometry": {"coordinates":[151.28453064000001,-33.8064613342],"type":"Point"}
}