{
  "type": "Feature",
  "properties": {
    "iso:country":"AU",
    "sg:address":"Shp3/ 133 Watton St",
    "sg:city":"Werribee",
    "sg:classifiers":[
        {
            "category":"Real Estate",
            "subcategory":"Real Estate Agent",
            "type":"Services"
        }
    ],
    "sg:phone":"+61 3 9741 5533",
    "sg:postcode":"3030",
    "sg:province":"VIC",
    "wof:name":"Werribee Reality",
    "wof:placetype":"venue"
},
  "geometry": {"coordinates":[144.659225,-37.902618],"type":"Point"}
}