{
  "type": "Feature",
  "properties": {
    "addr:full":"Shop 16, 520 Mt Dandenong Rd Kilsyth VIC 3137",
    "addr:housenumber":"shop 16 520",
    "addr:postcode":"3137",
    "addr:street":"Mt Dandenong Rd",
    "iso:country":"AU",
    "sg:address":"Shop 16, 520 Mt Dandenong Rd",
    "sg:city":"Kilsyth",
    "sg:classifiers":[
        {
            "category":"Fast Food",
            "type":"Food & Drink"
        }
    ],
    "sg:phone":"+61 3 9723 3811",
    "sg:postcode":"3137",
    "sg:province":"VIC",
    "sg:tags":[
        "away",
        "take"
    ],
    "wof:name":"Gourmet Connection",
    "wof:placetype":"venue"
},
  "geometry": {"coordinates":[145.31781005900001,-37.8065986633],"type":"Point"}
}