{
  "type": "Feature",
  "properties": {
    "iso:country":"AU",
    "sg:address":"Corinda Professional Centre 667 Oxley Rd",
    "sg:city":"Corinda",
    "sg:classifiers":[
        {
            "category":"Health Services",
            "subcategory":"Optometrist",
            "type":"Services"
        }
    ],
    "sg:phone":"+61 7 3379 5688",
    "sg:postcode":"4075",
    "sg:province":"QLD",
    "wof:name":"Gibson Mark",
    "wof:placetype":"venue"
},
  "geometry": {"coordinates":[152.98144531200001,-27.5398826599],"type":"Point"}
}