{
  "type": "Feature",
  "properties": {
    "addr:full":"135 Scott St Bungalow QLD 4870",
    "addr:housenumber":"135",
    "addr:postcode":"4870",
    "addr:street":"Scott St",
    "iso:country":"AU",
    "sg:address":"135 Scott St",
    "sg:city":"Bungalow",
    "sg:classifiers":[
        {
            "category":"Banks & Credit Unions",
            "subcategory":"Financial Services",
            "type":"Services"
        }
    ],
    "sg:phone":"+61 7 4051 5338",
    "sg:postcode":"4870",
    "sg:province":"QLD",
    "sg:tags":[
        "equipment",
        "chain"
    ],
    "wof:name":"NQ Fasteners & Lifting",
    "wof:placetype":"venue"
},
  "geometry": {"coordinates":[145.7578125,-16.9359798431],"type":"Point"}
}