{
  "type": "Feature",
  "properties": {
    "addr:full":"100 George St The Rocks NSW 2000",
    "addr:housenumber":"100",
    "addr:postcode":"2000",
    "addr:street":"George St",
    "iso:country":"AU",
    "sg:address":"100 George St",
    "sg:city":"The Rocks",
    "sg:classifiers":[
        {
            "category":"Arts & Performance",
            "subcategory":"Art Gallery",
            "type":"Entertainment"
        }
    ],
    "sg:phone":"+61 2 9252 1481",
    "sg:postcode":"2000",
    "sg:province":"NSW",
    "wof:name":"Billich Gallery",
    "wof:placetype":"venue"
},
  "geometry": {"coordinates":[151.20921325699999,-33.8580627441],"type":"Point"}
}