{
  "type": "Feature",
  "properties": {
    "addr:full":"217 Kent St Rockhampton QLD 4700",
    "addr:housenumber":"217",
    "addr:postcode":"4700",
    "addr:street":"Kent St",
    "iso:country":"AU",
    "sg:address":"217 Kent St",
    "sg:city":"Rockhampton",
    "sg:classifiers":[
        {
            "category":"Transit Center",
            "subcategory":"Freight",
            "type":"Transportation"
        }
    ],
    "sg:phone":"+61 7 4927 4366",
    "sg:postcode":"4700",
    "sg:province":"QLD",
    "sg:tags":[
        "forklift",
        "truck"
    ],
    "wof:name":"Red Australia",
    "wof:placetype":"venue"
},
  "geometry": {"coordinates":[150.519897461,-23.3960208893],"type":"Point"}
}