{
  "type": "Feature",
  "properties": {
    "addr:full":"220 New South Head Rd Double Bay NSW 2028",
    "addr:housenumber":"220",
    "addr:postcode":"2028",
    "addr:street":"New South Head Rd",
    "iso:country":"AU",
    "sg:address":"220 New South Head Rd",
    "sg:city":"Double Bay",
    "sg:classifiers":[
        {
            "category":"Shopping",
            "subcategory":"Bridal",
            "type":"Retail Goods"
        }
    ],
    "sg:phone":"+61 2 9363 8844",
    "sg:postcode":"2028",
    "sg:province":"NSW",
    "sg:tags":[
        "hire",
        "wear"
    ],
    "wof:name":"Mira Mandic",
    "wof:placetype":"venue"
},
  "geometry": {"coordinates":[151.237792969,-33.8788948059],"type":"Point"}
}