{
  "type": "Feature",
  "properties": {
    "addr:full":"Suite 7, 37- 39 Albert Rd Melbourne VIC 3004",
    "addr:housenumber":"37 39",
    "addr:postcode":"3004",
    "addr:street":"Albert Rd",
    "iso:country":"AU",
    "sg:address":"Suite 7, 37- 39 Albert Rd",
    "sg:city":"Melbourne",
    "sg:classifiers":[
        {
            "category":"Health Services",
            "subcategory":"Dentist",
            "type":"Services"
        }
    ],
    "sg:phone":"+61 3 9867 5555",
    "sg:postcode":"3004",
    "sg:province":"VIC",
    "sg:website":"http://www.albertsquaredental.com.au",
    "wof:name":"Albert Square Dental",
    "wof:placetype":"venue"
},
  "geometry": {"coordinates":[144.97128295900001,-37.8351707458],"type":"Point"}
}