{
  "type": "Feature",
  "properties": {
    "iso:country":"AU",
    "sg:address":"Unit 4, 9- 11 Slade St",
    "sg:city":"Mandurah",
    "sg:classifiers":[
        {
            "category":"Home & Garden",
            "subcategory":"Building Materials",
            "type":"Retail Goods"
        }
    ],
    "sg:phone":"+61 8 9581 8192",
    "sg:postcode":"6210",
    "sg:province":"WA",
    "sg:tags":[
        "shutter",
        "roller",
        "grille"
    ],
    "wof:name":"West Coast Roller Shutters",
    "wof:placetype":"venue"
},
  "geometry": {"coordinates":[115.74861900000001,-32.511185],"type":"Point"}
}