{
  "type": "Feature",
  "properties": {
    "iso:country":"AU",
    "sg:address":"248 Cheltenham Rd",
    "sg:city":"Keysborough",
    "sg:classifiers":[
        {
            "category":"Retail",
            "subcategory":"Auto Repair",
            "type":"Services"
        }
    ],
    "sg:phone":"+61 3 9798 2776",
    "sg:postcode":"3173",
    "sg:province":"VIC",
    "sg:tags":[
        "repairer",
        "motor",
        "engineer"
    ],
    "wof:name":"Jack Jennings Garage Service Station",
    "wof:placetype":"venue"
},
  "geometry": {"coordinates":[145.18205261200001,-37.9952430725],"type":"Point"}
}