{
  "type": "Feature",
  "properties": {
    "addr:full":"Berth 2 North Quay Port Beach Rd North Fremantle WA 6159",
    "addr:housenumber":"2",
    "addr:postcode":"6159",
    "addr:street":"North Quay Port Beach Rd",
    "iso:country":"AU",
    "sg:address":"Berth 2 North Quay Port Beach Rd",
    "sg:city":"North Fremantle",
    "sg:classifiers":[
        {
            "category":"Transit Center",
            "subcategory":"Freight",
            "type":"Transportation"
        }
    ],
    "sg:phone":"+61 8 9335 4329",
    "sg:postcode":"6159",
    "sg:province":"WA",
    "sg:tags":[
        "agent",
        "shipping"
    ],
    "wof:name":"Quay West Agencies",
    "wof:placetype":"venue"
},
  "geometry": {"coordinates":[115.745819,-32.035393],"type":"Point"}
}