{
  "type": "Feature",
  "properties": {
    "iso:country":"AU",
    "sg:address":"Unit 2 / 39 Casey St",
    "sg:city":"Bendigo",
    "sg:classifiers":[
        {
            "category":"Manufacturing",
            "subcategory":"Tools & Machinery",
            "type":"Manufacturing & Wholesale Goods"
        }
    ],
    "sg:phone":"+61 418 506 959",
    "sg:postcode":"3550",
    "sg:province":"VIC",
    "sg:tags":[
        "earth",
        "excavating",
        "moving",
        "equipment"
    ],
    "wof:name":"A Houlihan Earthmoving",
    "wof:placetype":"venue"
},
  "geometry": {"coordinates":[144.296630859,-36.7564735413],"type":"Point"}
}