{
  "type": "Feature",
  "properties": {
    "addr:full":"John St Manoora SA 5414",
    "addr:postcode":"5414",
    "addr:street":"John St",
    "iso:country":"AU",
    "sg:address":"John St",
    "sg:city":"Manoora",
    "sg:classifiers":[
        {
            "category":"Farming",
            "subcategory":"Farm & Veterinary Services",
            "type":"Manufacturing & Wholesale Goods"
        }
    ],
    "sg:phone":"+61 8 8848 4335",
    "sg:postcode":"5414",
    "sg:province":"SA",
    "sg:tags":[
        "seedsman"
    ],
    "wof:name":"Manoora Seeds Pty Ltd",
    "wof:placetype":"venue"
},
  "geometry": {"coordinates":[138.81703185999999,-34.001663208],"type":"Point"}
}