{
  "type": "Feature",
  "properties": {
    "iso:country":"AU",
    "sg:address":"7 Bant St",
    "sg:city":"Bathurst",
    "sg:classifiers":[
        {
            "category":"Retail",
            "subcategory":"Auto Repair",
            "type":"Services"
        }
    ],
    "sg:phone":"+61 2 6331 6614",
    "sg:postcode":"2795",
    "sg:province":"NSW",
    "sg:tags":[
        "repairer",
        "motor",
        "engineer"
    ],
    "wof:name":"Jones Rod & Shane Automotive",
    "wof:placetype":"venue"
},
  "geometry": {"coordinates":[149.57893371599999,-33.4294319153],"type":"Point"}
}