{
  "type": "Feature",
  "properties": {
    "iso:country":"AU",
    "sg:address":"Unit 1 / 103 Campbell St",
    "sg:city":"Belmont",
    "sg:classifiers":[
        {
            "category":"Professional",
            "subcategory":"Employment Agencies",
            "type":"Services"
        }
    ],
    "sg:phone":"+61 8 9478 0700",
    "sg:postcode":"6104",
    "sg:province":"WA",
    "sg:tags":[
        "provider",
        "internet"
    ],
    "wof:name":"TPG",
    "wof:placetype":"venue"
},
  "geometry": {"coordinates":[115.92497253400001,-31.9564094543],"type":"Point"}
}