{
  "type": "Feature",
  "properties": {
    "iso:country":"AU",
    "sg:address":"Shop 160, 49 North Pde",
    "sg:city":"Mt Druitt",
    "sg:classifiers":[
        {
            "category":"Shopping",
            "subcategory":"Clothing, Apparel, & Fashions",
            "type":"Retail Goods"
        }
    ],
    "sg:phone":"+61 2 9675 7928",
    "sg:postcode":"2770",
    "sg:province":"NSW",
    "sg:tags":[
        "lady",
        "wear"
    ],
    "wof:name":"Bezerk /Mennyx",
    "wof:placetype":"venue"
},
  "geometry": {"coordinates":[150.820480347,-33.7691497803],"type":"Point"}
}