{
  "type": "Feature",
  "properties": {
    "iso:country":"AU",
    "sg:address":"1 Frideswide St",
    "sg:city":"Goondiwindi",
    "sg:classifiers":[
        {
            "category":"Health Services",
            "subcategory":"Health Practitioner",
            "type":"Services"
        }
    ],
    "sg:phone":"+61 7 4671 4455",
    "sg:postcode":"4390",
    "sg:province":"QLD",
    "sg:tags":[
        "bowen",
        "therapy"
    ],
    "wof:name":"In Touch Bowen & Natural Therapies Clinic",
    "wof:placetype":"venue"
},
  "geometry": {"coordinates":[150.30418395999999,-28.5388641357],"type":"Point"}
}