{
  "type": "Feature",
  "properties": {
    "addr:full":"67 Albert Ave Chatswood NSW 2067",
    "addr:housenumber":"67",
    "addr:postcode":"2067",
    "addr:street":"Albert Ave",
    "iso:country":"AU",
    "sg:address":"67 Albert Ave",
    "sg:city":"Chatswood",
    "sg:classifiers":[
        {
            "category":"Professional",
            "subcategory":"Management & Consulting",
            "type":"Services"
        }
    ],
    "sg:phone":"+61 2 9413 4155",
    "sg:postcode":"2067",
    "sg:province":"NSW",
    "sg:tags":[
        "consultant"
    ],
    "wof:name":"Wareham Associates",
    "wof:placetype":"venue"
},
  "geometry": {"coordinates":[151.182006836,-33.7979621887],"type":"Point"}
}