{
  "type": "Feature",
  "properties": {
    "addr:full":"11 Pitcairn Crs Evatt ACT 2617",
    "addr:housenumber":"11",
    "addr:postcode":"2617",
    "addr:street":"Pitcairn Crs",
    "iso:country":"AU",
    "sg:address":"11 Pitcairn Crs",
    "sg:city":"Evatt",
    "sg:classifiers":[
        {
            "category":"Wholesale",
            "subcategory":"Medical Equipment & Supplies",
            "type":"Manufacturing & Wholesale Goods"
        }
    ],
    "sg:phone":"+61 2 6258 1111",
    "sg:postcode":"2617",
    "sg:province":"ACT",
    "sg:tags":[
        "aid",
        "care",
        "health",
        "home"
    ],
    "wof:name":"Southern Electric Scooters Pty Ltd",
    "wof:placetype":"venue"
},
  "geometry": {"coordinates":[149.06854248100001,-35.2099571228],"type":"Point"}
}