{
  "type": "Feature",
  "properties": {
    "addr:full":"12 Pace Rd Medina WA 6167",
    "addr:housenumber":"12",
    "addr:postcode":"6167",
    "addr:street":"Pace Rd",
    "iso:country":"AU",
    "sg:address":"12 Pace Rd",
    "sg:city":"Medina",
    "sg:classifiers":[
        {
            "category":"Wholesale",
            "subcategory":"Medical Equipment & Supplies",
            "type":"Manufacturing & Wholesale Goods"
        }
    ],
    "sg:phone":"+61 8 9419 2949",
    "sg:postcode":"6167",
    "sg:province":"WA",
    "sg:tags":[
        "aid",
        "care",
        "health",
        "home"
    ],
    "wof:name":"Medina Pharmacy",
    "wof:placetype":"venue"
},
  "geometry": {"coordinates":[115.80645,-32.235954],"type":"Point"}
}