{
  "type": "Feature",
  "properties": {
    "iso:country":"AU",
    "sg:address":"25 Jetty Rd",
    "sg:city":"Largs Bay",
    "sg:classifiers":[
        {
            "category":"Banks & Credit Unions",
            "subcategory":"Investment Brokerage",
            "type":"Services"
        }
    ],
    "sg:phone":"+61 8 8341 6885",
    "sg:postcode":"5016",
    "sg:province":"SA",
    "sg:tags":[
        "paint",
        "supply",
        "removal"
    ],
    "wof:name":"PaintSA Pty Ltd",
    "wof:placetype":"venue"
},
  "geometry": {"coordinates":[138.500854492,-34.8252487183],"type":"Point"}
}