{
  "type": "Feature",
  "properties": {
    "iso:country":"AU",
    "sg:address":"Main Rd",
    "sg:city":"Burringbar",
    "sg:classifiers":[
        {
            "category":"Farming",
            "subcategory":"Nursery",
            "type":"Manufacturing & Wholesale Goods"
        }
    ],
    "sg:phone":"+61 2 6677 1173",
    "sg:postcode":"2483",
    "sg:province":"NSW",
    "wof:name":"Burringbah Flowers Nursery",
    "wof:placetype":"venue"
},
  "geometry": {"coordinates":[153.432693481,-28.5036067963],"type":"Point"}
}