{
  "type": "Feature",
  "properties": {
    "addr:full":"199 River St Maclean NSW 2463",
    "addr:housenumber":"199",
    "addr:postcode":"2463",
    "addr:street":"River St",
    "iso:country":"AU",
    "sg:address":"199 River St",
    "sg:city":"Maclean",
    "sg:classifiers":[
        {
            "category":"Food & Beverages",
            "subcategory":"Liquor & Beverages",
            "type":"Retail Goods"
        }
    ],
    "sg:phone":"+61 2 6645 2525",
    "sg:postcode":"2463",
    "sg:province":"NSW",
    "sg:tags":[
        "store"
    ],
    "wof:name":"Maclean Cellars",
    "wof:placetype":"venue"
},
  "geometry": {"coordinates":[153.19688415499999,-29.4550590515],"type":"Point"}
}