{
  "type": "Feature",
  "properties": {
    "addr:full":"19a Queen St Mitcham VIC 3132",
    "addr:housenumber":"19a",
    "addr:postcode":"3132",
    "addr:street":"Queen St",
    "iso:country":"AU",
    "sg:address":"19a Queen St",
    "sg:city":"Mitcham",
    "sg:classifiers":[
        {
            "category":"Retail",
            "subcategory":"Auto Repair",
            "type":"Services"
        }
    ],
    "sg:phone":"+61 3 9873 5800",
    "sg:postcode":"3132",
    "sg:province":"VIC",
    "sg:tags":[
        "repairer",
        "motor",
        "engineer"
    ],
    "wof:name":"Fuel Line Automotive",
    "wof:placetype":"venue"
},
  "geometry": {"coordinates":[145.18621826200001,-37.8182601929],"type":"Point"}
}