{
  "type": "Feature",
  "properties": {
    "iso:country":"AU",
    "sg:address":"75 Burdekin Drv",
    "sg:city":"Albion Park",
    "sg:classifiers":[
        {
            "category":"Wholesale",
            "subcategory":"Home Furnishings",
            "type":"Manufacturing & Wholesale Goods"
        }
    ],
    "sg:phone":"+61 2 4256 9193",
    "sg:postcode":"2527",
    "sg:province":"NSW",
    "sg:tags":[
        "wholesaler",
        "curtain",
        "mfrs"
    ],
    "wof:name":"Curtain Call By Sue-Anne",
    "wof:placetype":"venue"
},
  "geometry": {"coordinates":[150.78157043499999,-34.5833930969],"type":"Point"}
}