{
  "type": "Feature",
  "properties": {
    "addr:full":"7 Degillern Pl Richmond TAS 7025",
    "addr:housenumber":"7",
    "addr:postcode":"7025",
    "addr:street":"Degillern Pl",
    "iso:country":"AU",
    "sg:address":"7 Degillern Pl",
    "sg:city":"Richmond",
    "sg:classifiers":[
        {
            "category":"Professional",
            "subcategory":"Art Services",
            "type":"Services"
        }
    ],
    "sg:phone":"+61 407 994 667",
    "sg:postcode":"7025",
    "sg:province":"TAS",
    "sg:tags":[
        "graphic",
        "designer"
    ],
    "wof:name":"Dixie Makrogamvrakis",
    "wof:placetype":"venue"
},
  "geometry": {"coordinates":[147.381958008,-42.7659378052],"type":"Point"}
}