{
  "type": "Feature",
  "properties": {
    "addr:full":"National Bank Building 299 Brunswick St Fortitude Valley QLD 4006",
    "addr:housenumber":"299",
    "addr:postcode":"4006",
    "addr:street":"Brunswick St",
    "iso:country":"AU",
    "sg:address":"National Bank Building 299 Brunswick St",
    "sg:city":"Fortitude Valley",
    "sg:classifiers":[
        {
            "category":"Health Services",
            "subcategory":"Dentist",
            "type":"Services"
        }
    ],
    "sg:phone":"+61 7 3852 1366",
    "sg:postcode":"4006",
    "sg:province":"QLD",
    "wof:name":"Lane Ben",
    "wof:placetype":"venue"
},
  "geometry": {"coordinates":[153.03408813499999,-27.4578952789],"type":"Point"}
}