{
  "type": "Feature",
  "properties": {
    "iso:country":"AU",
    "sg:address":"38 Hannah St",
    "sg:city":"Mt Ommaney",
    "sg:classifiers":[
        {
            "category":"Professional",
            "subcategory":"Computer Services",
            "type":"Services"
        }
    ],
    "sg:phone":"+61 7 3376 3453",
    "sg:postcode":"4074",
    "sg:province":"QLD",
    "sg:tags":[
        "repairs",
        "upgrade",
        "equipment"
    ],
    "wof:name":"Activ IT",
    "wof:placetype":"venue"
},
  "geometry": {"coordinates":[152.92918395999999,-27.5476665497],"type":"Point"}
}