{
  "type": "Feature",
  "properties": {
    "iso:country":"AU",
    "sg:address":"37 Elanora Drv",
    "sg:city":"Rockingham",
    "sg:classifiers":[
        {
            "category":"Health Services",
            "subcategory":"Doctor",
            "type":"Services"
        }
    ],
    "sg:phone":"+61 8 9592 4411",
    "sg:postcode":"6168",
    "sg:province":"WA",
    "sg:tags":[
        "medical",
        "practitioner"
    ],
    "wof:name":"Moore P Dr",
    "wof:placetype":"venue"
},
  "geometry": {"coordinates":[115.765022,-32.293007],"type":"Point"}
}