{
  "type": "Feature",
  "properties": {
    "iso:country":"AU",
    "sg:address":"32- 34 Claremont Ave",
    "sg:city":"Greenacre",
    "sg:classifiers":[
        {
            "category":"Manufacturing",
            "subcategory":"Motor Vehicles & Parts",
            "type":"Manufacturing & Wholesale Goods"
        }
    ],
    "sg:phone":"+61 2 9708 1033",
    "sg:postcode":"2190",
    "sg:province":"NSW",
    "sg:tags":[
        "replacement"
    ],
    "wof:name":"Platinum Parts",
    "wof:placetype":"venue"
},
  "geometry": {"coordinates":[151.038605,-33.90078],"type":"Point"}
}