{
  "type": "Feature",
  "properties": {
    "addr:full":"38 Monastir Rd Phegans Bay NSW 2256",
    "addr:housenumber":"38",
    "addr:postcode":"2256",
    "addr:street":"Monastir Rd",
    "iso:country":"AU",
    "sg:address":"38 Monastir Rd",
    "sg:city":"Phegans Bay",
    "sg:classifiers":[
        {
            "category":"Home & Garden",
            "subcategory":"Building Materials",
            "type":"Retail Goods"
        }
    ],
    "sg:phone":"+61 2 4324 9100",
    "sg:postcode":"2256",
    "sg:province":"NSW",
    "sg:tags":[
        "merchant",
        "glass",
        "glazier"
    ],
    "wof:name":"Harrison Glass Services Pty Ltd",
    "wof:placetype":"venue"
},
  "geometry": {"coordinates":[151.309082031,-33.4907951355],"type":"Point"}
}