{
  "type": "Feature",
  "properties": {
    "addr:full":"Shop 451 Castle Towers Shopping Centre Castle Hill NSW 2154",
    "addr:housenumber":"451",
    "addr:postcode":"2154",
    "addr:street":"Castle",
    "iso:country":"AU",
    "sg:address":"Shop 451 Castle Towers Shopping Centre",
    "sg:city":"Castle Hill",
    "sg:classifiers":[
        {
            "category":"Shopping",
            "subcategory":"Clothing, Apparel, & Fashions",
            "type":"Retail Goods"
        }
    ],
    "sg:phone":"+61 2 9680 4515",
    "sg:postcode":"2154",
    "sg:province":"NSW",
    "sg:tags":[
        "lady",
        "wear"
    ],
    "wof:name":"Hound Dog Clothing",
    "wof:placetype":"venue"
},
  "geometry": {"coordinates":[151.003814697,-33.7317695618],"type":"Point"}
}