{
  "type": "Feature",
  "properties": {
    "addr:full":"Sir Thomas Mitchell Drv Chester Hill NSW 2162",
    "addr:postcode":"2162",
    "addr:street":"Mitchell Drv",
    "iso:country":"AU",
    "sg:address":"Sir Thomas Mitchell Drv",
    "sg:city":"Chester Hill",
    "sg:classifiers":[
        {
            "category":"Building & Trades",
            "subcategory":"Cleaning & Sanitation",
            "type":"Services"
        }
    ],
    "sg:phone":"+61 2 9644 5413",
    "sg:postcode":"2162",
    "sg:province":"NSW",
    "sg:tags":[
        "chemical",
        "pressure",
        "steam",
        "contractor"
    ],
    "wof:name":"Austwide Building Services Pty Ltd",
    "wof:placetype":"venue"
},
  "geometry": {"coordinates":[150.99528503400001,-33.8877563477],"type":"Point"}
}