{
  "type": "Feature",
  "properties": {
    "addr:full":"233 Macquarie St Liverpool NSW 2170",
    "addr:housenumber":"233",
    "addr:postcode":"2170",
    "addr:street":"Macquarie St",
    "iso:country":"AU",
    "sg:address":"233 Macquarie St",
    "sg:city":"Liverpool",
    "sg:classifiers":[
        {
            "category":"Health Services",
            "subcategory":"Dentist",
            "type":"Services"
        }
    ],
    "sg:phone":"+61 2 9602 3339",
    "sg:postcode":"2170",
    "sg:province":"NSW",
    "wof:name":"Denture Design Clinic",
    "wof:placetype":"venue"
},
  "geometry": {"coordinates":[150.923431397,-33.9233131409],"type":"Point"}
}