{
  "type": "Feature",
  "properties": {
    "addr:full":"28 Marcia St Coffs Harbour NSW 2450",
    "addr:housenumber":"28",
    "addr:postcode":"2450",
    "addr:street":"Marcia St",
    "iso:country":"AU",
    "sg:address":"28 Marcia St",
    "sg:city":"Coffs Harbour",
    "sg:classifiers":[
        {
            "category":"Home & Garden",
            "subcategory":"Hardware",
            "type":"Retail Goods"
        }
    ],
    "sg:phone":"+61 2 6652 5177",
    "sg:postcode":"2450",
    "sg:province":"NSW",
    "sg:tags":[
        "plumber",
        "supply"
    ],
    "wof:name":"Tradelink Plumbing Centres",
    "wof:placetype":"venue"
},
  "geometry": {"coordinates":[153.11755400000001,-30.289534],"type":"Point"}
}