{
  "type": "Feature",
  "properties": {
    "iso:country":"AU",
    "sg:address":"Coolum Park Shopping Centre South Coolum Rd",
    "sg:city":"Coolum Beach",
    "sg:classifiers":[
        {
            "category":"Health Services",
            "subcategory":"Doctor",
            "type":"Services"
        }
    ],
    "sg:phone":"+61 7 5446 5999",
    "sg:postcode":"4573",
    "sg:province":"QLD",
    "sg:tags":[
        "medical",
        "practitioner"
    ],
    "wof:name":"De Jager Joe",
    "wof:placetype":"venue"
},
  "geometry": {"coordinates":[153.078217,-26.536676],"type":"Point"}
}