{
  "type": "Feature",
  "properties": {
    "addr:full":"PO Box 1177 Spring Hill QLD 4004",
    "addr:postcode":"4004",
    "iso:country":"AU",
    "sg:address":"PO Box 1177",
    "sg:city":"Spring Hill",
    "sg:classifiers":[
        {
            "category":"Real Estate",
            "subcategory":"Architect",
            "type":"Services"
        }
    ],
    "sg:phone":"+61 7 3715 7811",
    "sg:postcode":"4004",
    "sg:province":"QLD",
    "sg:tags":[
        "building",
        "designer"
    ],
    "wof:name":"Grey Design",
    "wof:placetype":"venue"
},
  "geometry": {"coordinates":[153.02444457999999,-27.4608707428],"type":"Point"}
}