{
  "type": "Feature",
  "properties": {
    "addr:full":"7 Brinawa St Mona Vale NSW 2103",
    "addr:housenumber":"7",
    "addr:postcode":"2103",
    "addr:street":"Brinawa St",
    "iso:country":"AU",
    "sg:address":"7 Brinawa St",
    "sg:city":"Mona Vale",
    "sg:classifiers":[
        {
            "category":"Building & Trades",
            "subcategory":"Construction",
            "type":"Services"
        }
    ],
    "sg:phone":"+61 2 9979 4599",
    "sg:postcode":"2103",
    "sg:province":"NSW",
    "sg:tags":[
        "contractor"
    ],
    "wof:name":"Upstairs Design & Building Co.",
    "wof:placetype":"venue"
},
  "geometry": {"coordinates":[151.29457092300001,-33.6787147522],"type":"Point"}
}