{
  "type": "Feature",
  "properties": {
    "addr:full":"56 Spencer St Bunbury WA 6230",
    "addr:housenumber":"56",
    "addr:postcode":"6230",
    "addr:street":"Spencer St",
    "iso:country":"AU",
    "sg:address":"56 Spencer St",
    "sg:city":"Bunbury",
    "sg:classifiers":[
        {
            "category":"Retail",
            "subcategory":"Event Space",
            "type":"Services"
        }
    ],
    "sg:phone":"+61 8 9721 7322",
    "sg:postcode":"6230",
    "sg:province":"WA",
    "sg:tags":[
        "venue",
        "reception",
        "wedding"
    ],
    "wof:name":"Admiral Function Centre",
    "wof:placetype":"venue"
},
  "geometry": {"coordinates":[115.641563,-33.346828],"type":"Point"}
}