{
  "type": "Feature",
  "properties": {
    "iso:country":"AU",
    "sg:address":"Lower Ground, 363 Pitt St",
    "sg:city":"Sydney",
    "sg:classifiers":[
        {
            "category":"Communications",
            "subcategory":"Film & Video Production",
            "type":"Services"
        }
    ],
    "sg:phone":"+61 2 9267 2915",
    "sg:postcode":"2000",
    "sg:province":"NSW",
    "sg:tags":[
        "equipment",
        "amplification",
        "music"
    ],
    "wof:name":"Velvet Sound Recording Studio",
    "wof:placetype":"venue"
},
  "geometry": {"coordinates":[151.20773315400001,-33.8758850098],"type":"Point"}
}