{
  "type": "Feature",
  "properties": {
    "addr:full":"33 Bacon St Hindmarsh SA 5007",
    "addr:housenumber":"33",
    "addr:postcode":"5007",
    "addr:street":"Bacon St",
    "iso:country":"AU",
    "sg:address":"33 Bacon St",
    "sg:city":"Hindmarsh",
    "sg:classifiers":[
        {
            "category":"Professional",
            "subcategory":"Accounting & Tax Preparation",
            "type":"Services"
        }
    ],
    "sg:phone":"+61 8 8340 7771",
    "sg:postcode":"5007",
    "sg:province":"SA",
    "sg:tags":[
        "jukebox"
    ],
    "wof:name":"Jukebox",
    "wof:placetype":"venue"
},
  "geometry": {"coordinates":[138.566574097,-34.9069328308],"type":"Point"}
}