{
  "type": "Feature",
  "properties": {
    "addr:full":"142 Timor St Warrnambool VIC 3280",
    "addr:housenumber":"142",
    "addr:postcode":"3280",
    "addr:street":"Timor St",
    "iso:country":"AU",
    "sg:address":"142 Timor St",
    "sg:city":"Warrnambool",
    "sg:classifiers":[
        {
            "category":"Real Estate",
            "subcategory":"Architect",
            "type":"Services"
        }
    ],
    "sg:phone":"+61 3 5562 6372",
    "sg:postcode":"3280",
    "sg:province":"VIC",
    "sg:tags":[
        "building",
        "designer"
    ],
    "wof:name":"Merri Designs Pty Ltd",
    "wof:placetype":"venue"
},
  "geometry": {"coordinates":[142.48292541500001,-38.3855056763],"type":"Point"}
}