{
  "type": "Feature",
  "properties": {
    "addr:full":"71 Ridge Rd Kilaben Bay NSW 2283",
    "addr:housenumber":"71",
    "addr:postcode":"2283",
    "addr:street":"Ridge Rd",
    "iso:country":"AU",
    "sg:address":"71 Ridge Rd",
    "sg:city":"Kilaben Bay",
    "sg:classifiers":[
        {
            "category":"Real Estate",
            "subcategory":"Real Estate Agent",
            "type":"Services"
        }
    ],
    "sg:phone":"+61 2 4959 6458",
    "sg:postcode":"2283",
    "sg:province":"NSW",
    "wof:name":"Magin David",
    "wof:placetype":"venue"
},
  "geometry": {"coordinates":[151.587234497,-33.0255432129],"type":"Point"}
}