{
  "type": "Feature",
  "properties": {
    "iso:country":"AU",
    "sg:address":"32 Albany Hwy",
    "sg:city":"Albany",
    "sg:classifiers":[
        {
            "category":"Health Services",
            "subcategory":"Doctor",
            "type":"Services"
        }
    ],
    "sg:phone":"+61 8 9841 2733",
    "sg:postcode":"6330",
    "sg:province":"WA",
    "sg:tags":[
        "medical",
        "practitioner"
    ],
    "wof:name":"Mildenhall David Dr",
    "wof:placetype":"venue"
},
  "geometry": {"coordinates":[117.88276672400001,-35.0204925537],"type":"Point"}
}