{
  "type": "Feature",
  "properties": {
    "addr:full":"45 Parklands Ave Leonay NSW 2750",
    "addr:housenumber":"45",
    "addr:postcode":"2750",
    "addr:street":"Parklands Ave",
    "iso:country":"AU",
    "sg:address":"45 Parklands Ave",
    "sg:city":"Leonay",
    "sg:classifiers":[
        {
            "category":"Home & Garden",
            "subcategory":"Carpets & Floor Coverings",
            "type":"Retail Goods"
        }
    ],
    "sg:phone":"+61 2 4735 8637",
    "sg:postcode":"2750",
    "sg:province":"NSW",
    "sg:tags":[
        "tile",
        "wall",
        "layer"
    ],
    "wof:name":"A & P Kennedy Wall & Floor Tiling",
    "wof:placetype":"venue"
},
  "geometry": {"coordinates":[150.64921569800001,-33.7696037292],"type":"Point"}
}