{
  "type": "Feature",
  "properties": {
    "addr:full":"78 Aberdeen Rd Macleod VIC 3085",
    "addr:housenumber":"78",
    "addr:postcode":"3085",
    "addr:street":"Aberdeen Rd",
    "iso:country":"AU",
    "sg:address":"78 Aberdeen Rd",
    "sg:city":"Macleod",
    "sg:classifiers":[
        {
            "category":"Health Services",
            "subcategory":"Doctor",
            "type":"Services"
        }
    ],
    "sg:phone":"+61 3 9459 8329",
    "sg:postcode":"3085",
    "sg:province":"VIC",
    "sg:tags":[
        "medical",
        "practitioner"
    ],
    "wof:name":"Rose Dr Laurie",
    "wof:placetype":"venue"
},
  "geometry": {"coordinates":[145.07078552199999,-37.7261657715],"type":"Point"}
}