{
  "type": "Feature",
  "properties": {
    "iso:country":"AU",
    "sg:address":"9 Taronga Pl",
    "sg:city":"Mona Vale",
    "sg:classifiers":[
        {
            "category":"Building & Trades",
            "subcategory":"Construction",
            "type":"Services"
        }
    ],
    "sg:phone":"+61 2 9979 7350",
    "sg:postcode":"2103",
    "sg:province":"NSW",
    "sg:tags":[
        "joinery"
    ],
    "wof:name":"Pittwater Joinery Pty Ltd",
    "wof:placetype":"venue"
},
  "geometry": {"coordinates":[151.30668640100001,-33.6741218567],"type":"Point"}
}