{
  "type": "Feature",
  "properties": {
    "addr:full":"38 Scott St Cranbourne South VIC 3977",
    "addr:housenumber":"38",
    "addr:postcode":"3977",
    "addr:street":"Scott St",
    "iso:country":"AU",
    "sg:address":"38 Scott St",
    "sg:city":"Cranbourne South",
    "sg:classifiers":[
        {
            "category":"Building & Trades",
            "subcategory":"Construction",
            "type":"Services"
        }
    ],
    "sg:phone":"+61 3 9785 3457",
    "sg:postcode":"3977",
    "sg:province":"VIC",
    "sg:tags":[
        "concrete",
        "paving"
    ],
    "wof:name":"Carrum Downs Bobcat & Paving",
    "wof:placetype":"venue"
},
  "geometry": {"coordinates":[145.28047180199999,-38.1090812683],"type":"Point"}
}