{
  "type": "Feature",
  "properties": {
    "addr:full":"13 Jubilee St Parkes NSW 2870",
    "addr:housenumber":"13",
    "addr:postcode":"2870",
    "addr:street":"Jubilee St",
    "iso:country":"AU",
    "sg:address":"13 Jubilee St",
    "sg:city":"Parkes",
    "sg:classifiers":[
        {
            "category":"Real Estate",
            "subcategory":"Real Estate Services",
            "type":"Services"
        }
    ],
    "sg:phone":"+61 2 6862 1555",
    "sg:postcode":"2870",
    "sg:province":"NSW",
    "sg:tags":[
        "valuer"
    ],
    "wof:name":"Clarke E W & Associates",
    "wof:placetype":"venue"
},
  "geometry": {"coordinates":[148.16836499999999,-33.12458],"type":"Point"}
}