{
  "type": "Feature",
  "properties": {
    "iso:country":"AU",
    "sg:address":"131 Myers St",
    "sg:city":"Geelong",
    "sg:classifiers":[
        {
            "category":"Building & Trades",
            "subcategory":"Landscaping Services",
            "type":"Services"
        }
    ],
    "sg:phone":"+61 3 5272 4450",
    "sg:postcode":"3220",
    "sg:province":"VIC",
    "sg:tags":[
        "consultant"
    ],
    "wof:name":"City Of Greater Geelong",
    "wof:placetype":"venue"
},
  "geometry": {"coordinates":[144.36094700000001,-38.151802],"type":"Point"}
}