{
  "type": "Feature",
  "properties": {
    "addr:full":"121 Sackville St Collingwood VIC 3066",
    "addr:housenumber":"121",
    "addr:postcode":"3066",
    "addr:street":"Sackville St",
    "iso:country":"AU",
    "sg:address":"121 Sackville St",
    "sg:city":"Collingwood",
    "sg:classifiers":[
        {
            "category":"Manufacturing",
            "subcategory":"Tools & Machinery",
            "type":"Manufacturing & Wholesale Goods"
        }
    ],
    "sg:phone":"+61 3 9419 2269",
    "sg:postcode":"3066",
    "sg:province":"VIC",
    "sg:tags":[
        "fastener",
        "industrial"
    ],
    "wof:name":"Ezifix Victoria",
    "wof:placetype":"venue"
},
  "geometry": {"coordinates":[144.98643493599999,-37.7990226746],"type":"Point"}
}