{
  "type": "Feature",
  "properties": {
    "addr:full":"20-22 Churchill Rd North Dry Creek SA 5094",
    "addr:housenumber":"20-22",
    "addr:postcode":"5094",
    "addr:street":"Churchill Rd North Dry",
    "iso:country":"AU",
    "sg:address":"20-22 Churchill Rd North",
    "sg:city":"Dry Creek",
    "sg:classifiers":[
        {
            "category":"Farming",
            "subcategory":"Fish & Marine Products",
            "type":"Manufacturing & Wholesale Goods"
        }
    ],
    "sg:phone":"+61 8 8262 1221",
    "sg:postcode":"5094",
    "sg:province":"SA",
    "sg:tags":[
        "wire"
    ],
    "wof:name":"Whites Wires Australia Pty Ltd",
    "wof:placetype":"venue"
},
  "geometry": {"coordinates":[138.588256836,-34.8364295959],"type":"Point"}
}