{
  "type": "Feature",
  "properties": {
    "addr:full":"42 Gertz Ave Reservoir VIC 3073",
    "addr:housenumber":"42",
    "addr:postcode":"3073",
    "addr:street":"Gertz Ave",
    "iso:country":"AU",
    "sg:address":"42 Gertz Ave",
    "sg:city":"Reservoir",
    "sg:classifiers":[
        {
            "category":"Building & Trades",
            "subcategory":"Construction",
            "type":"Services"
        }
    ],
    "sg:phone":"+61 3 9460 6590",
    "sg:postcode":"3073",
    "sg:province":"VIC",
    "sg:tags":[
        "contractor"
    ],
    "wof:name":"Infantino Constructions Pty Ltd",
    "wof:placetype":"venue"
},
  "geometry": {"coordinates":[145.03222656200001,-37.6997184753],"type":"Point"}
}