{
  "type": "Feature",
  "properties": {
    "addr:full":"620 Seventeen Mile Rocks Rd Sinnamon Park QLD 4073",
    "addr:housenumber":"620",
    "addr:postcode":"4073",
    "addr:street":"Seventeen Mile Rocks Rd",
    "iso:country":"AU",
    "sg:address":"620 Seventeen Mile Rocks Rd",
    "sg:city":"Sinnamon Park",
    "sg:classifiers":[
        {
            "category":"Travel",
            "subcategory":"Hostel",
            "type":"Entertainment"
        }
    ],
    "sg:phone":"+61 7 3714 5100",
    "sg:postcode":"4073",
    "sg:province":"QLD",
    "sg:tags":[
        "home"
    ],
    "wof:name":"Wesley Mission Brisbane",
    "wof:placetype":"venue"
},
  "geometry": {"coordinates":[152.949661255,-27.5374336243],"type":"Point"}
}