{
  "type": "Feature",
  "properties": {
    "addr:full":"Factory 2/ 4 Quarantine Rd Kings Meadows TAS 7249",
    "addr:housenumber":"/ 4",
    "addr:postcode":"7249",
    "addr:street":"Quarantine Rd",
    "iso:country":"AU",
    "sg:address":"Factory 2/ 4 Quarantine Rd",
    "sg:city":"Kings Meadows",
    "sg:classifiers":[
        {
            "category":"Professional",
            "type":"Services"
        }
    ],
    "sg:phone":"+61 3 6343 3661",
    "sg:postcode":"7249",
    "sg:province":"TAS",
    "sg:tags":[
        "coating",
        "powder"
    ],
    "wof:name":"Metal Coat",
    "wof:placetype":"venue"
},
  "geometry": {"coordinates":[147.16549682600001,-41.4747314453],"type":"Point"}
}