{
  "type": "Feature",
  "properties": {
    "addr:full":"3 Bligh St Kirrawee NSW 2232",
    "addr:housenumber":"3",
    "addr:postcode":"2232",
    "addr:street":"Bligh St",
    "iso:country":"AU",
    "sg:address":"3 Bligh St",
    "sg:city":"Kirrawee",
    "sg:classifiers":[
        {
            "category":"Retail",
            "subcategory":"Repair Shop",
            "type":"Services"
        }
    ],
    "sg:phone":"+61 411 330 005",
    "sg:postcode":"2232",
    "sg:province":"NSW",
    "sg:tags":[
        "windscreen"
    ],
    "wof:name":"Astrobond Windscreen Repair System",
    "wof:placetype":"venue"
},
  "geometry": {"coordinates":[151.07400512699999,-34.0452384949],"type":"Point"}
}