{
  "type": "Feature",
  "properties": {
    "addr:full":"34- 38 Kent Rd North Ryde NSW 2113",
    "addr:housenumber":"38",
    "addr:postcode":"2113",
    "addr:street":"Kent Rd",
    "iso:country":"AU",
    "sg:address":"34- 38 Kent Rd",
    "sg:city":"North Ryde",
    "sg:classifiers":[
        {
            "category":"Autos & Motor Vehicles",
            "subcategory":"Fuel & Gas Station",
            "type":"Retail Goods"
        }
    ],
    "sg:phone":"+61 2 9870 7989",
    "sg:postcode":"2113",
    "sg:province":"NSW",
    "wof:name":"G & F Petroleum Pty Ltd",
    "wof:placetype":"venue"
},
  "geometry": {"coordinates":[151.115844727,-33.7913551331],"type":"Point"}
}