{
  "type": "Feature",
  "properties": {
    "addr:full":"26-28 Glenbarry Rd Campbellfield VIC 3061",
    "addr:housenumber":"26-28",
    "addr:postcode":"3061",
    "addr:street":"Glenbarry Rd",
    "iso:country":"AU",
    "sg:address":"26-28 Glenbarry Rd",
    "sg:city":"Campbellfield",
    "sg:classifiers":[
        {
            "category":"Manufacturing",
            "subcategory":"Chemicals & Compounds",
            "type":"Manufacturing & Wholesale Goods"
        }
    ],
    "sg:phone":"+61 3 9357 0386",
    "sg:postcode":"3061",
    "sg:province":"VIC",
    "sg:tags":[
        "industrial"
    ],
    "sg:website":"http://www.mcmchem.com.au",
    "wof:name":"MCM Chemical Handling Pty Ltd",
    "wof:placetype":"venue"
},
  "geometry": {"coordinates":[144.96116638199999,-37.6634368896],"type":"Point"}
}