{
  "type": "Feature",
  "properties": {
    "iso:country":"AU",
    "sg:address":"24a Ozone St",
    "sg:city":"Chinderah",
    "sg:classifiers":[
        {
            "category":"Building & Trades",
            "subcategory":"Construction",
            "type":"Services"
        }
    ],
    "sg:phone":"+61 2 6674 0300",
    "sg:postcode":"2487",
    "sg:province":"NSW",
    "sg:tags":[
        "earth",
        "excavating",
        "moving",
        "contractor"
    ],
    "wof:name":"South East Excavations Pty. Ltd.",
    "wof:placetype":"venue"
},
  "geometry": {"coordinates":[153.55844116200001,-28.2445907593],"type":"Point"}
}