{
  "type": "Feature",
  "properties": {
    "iso:country":"AU",
    "sg:address":"6 Strome Rd",
    "sg:city":"Applecross",
    "sg:classifiers":[
        {
            "category":"Building & Trades",
            "subcategory":"Construction",
            "type":"Services"
        }
    ],
    "sg:phone":"+61 8 9330 1212",
    "sg:postcode":"6153",
    "sg:province":"WA",
    "sg:tags":[
        "home",
        "air conditioning"
    ],
    "wof:name":"Target Air Conditioning",
    "wof:placetype":"venue"
},
  "geometry": {"coordinates":[115.844078,-32.005493],"type":"Point"}
}