{
  "type": "Feature",
  "properties": {
    "addr:full":"Cook St Parndana SA 5220",
    "addr:postcode":"5220",
    "addr:street":"Cook St",
    "iso:country":"AU",
    "sg:address":"Cook St",
    "sg:city":"Parndana",
    "sg:classifiers":[
        {
            "category":"Home & Garden",
            "subcategory":"Garden Supply",
            "type":"Retail Goods"
        }
    ],
    "sg:phone":"+61 8 8559 6075",
    "sg:postcode":"5220",
    "sg:province":"SA",
    "sg:tags":[
        "fertilizer"
    ],
    "wof:name":"Keilem Pty Ltd",
    "wof:placetype":"venue"
},
  "geometry": {"coordinates":[137.26130676299999,-35.7900123596],"type":"Point"}
}