{
  "type": "Feature",
  "properties": {
    "iso:country":"AU",
    "sg:address":"32 Warren Ave",
    "sg:city":"Avoca Beach",
    "sg:classifiers":[
        {
            "category":"Building & Trades",
            "subcategory":"Construction",
            "type":"Services"
        }
    ],
    "sg:phone":"+61 2 4382 2190",
    "sg:postcode":"2251",
    "sg:province":"NSW",
    "sg:tags":[
        "decking",
        "contractor"
    ],
    "wof:name":"Oasis Decks & Pergolas",
    "wof:placetype":"venue"
},
  "geometry": {"coordinates":[151.43252563499999,-33.4672813416],"type":"Point"}
}