{
  "type": "Feature",
  "properties": {
    "addr:full":"11 Columbia Drv Wheelers Hill VIC 3150",
    "addr:housenumber":"11",
    "addr:postcode":"3150",
    "addr:street":"Columbia Drv",
    "iso:country":"AU",
    "sg:address":"11 Columbia Drv",
    "sg:city":"Wheelers Hill",
    "sg:classifiers":[
        {
            "category":"Education",
            "subcategory":"School",
            "type":"Public Place"
        }
    ],
    "sg:phone":"+61 3 9561 2879",
    "sg:postcode":"3150",
    "sg:province":"VIC",
    "sg:tags":[
        "state",
        "except",
        "nsw"
    ],
    "wof:name":"Waverley Meadows Primary",
    "wof:placetype":"venue"
},
  "geometry": {"coordinates":[145.18421935999999,-37.9151687622],"type":"Point"}
}