{
  "type": "Feature",
  "properties": {
    "iso:country":"AU",
    "sg:address":"8 Meleri Pl",
    "sg:city":"Margaret River",
    "sg:classifiers":[
        {
            "category":"Building & Trades",
            "subcategory":"Construction",
            "type":"Services"
        }
    ],
    "sg:phone":"+61 8 9757 2954",
    "sg:postcode":"6285",
    "sg:province":"WA",
    "sg:tags":[
        "concrete",
        "contractor"
    ],
    "wof:name":"Jamkel Contractors",
    "wof:placetype":"venue"
},
  "geometry": {"coordinates":[115.06347656200001,-33.9495277405],"type":"Point"}
}