{
  "type": "Feature",
  "properties": {
    "addr:full":"46 Hill St Port Elliot SA 5212",
    "addr:housenumber":"46",
    "addr:postcode":"5212",
    "addr:street":"Hill St",
    "iso:country":"AU",
    "sg:address":"46 Hill St",
    "sg:city":"Port Elliot",
    "sg:classifiers":[
        {
            "category":"Retail",
            "subcategory":"Auto Repair",
            "type":"Services"
        }
    ],
    "sg:phone":"+61 8 8554 3227",
    "sg:postcode":"5212",
    "sg:province":"SA",
    "sg:tags":[
        "repairer",
        "motor",
        "engineer"
    ],
    "wof:name":"Mark Smith's Autos",
    "wof:placetype":"venue"
},
  "geometry": {"coordinates":[138.67268371599999,-35.5234222412],"type":"Point"}
}