{
  "type": "Feature",
  "properties": {
    "iso:country":"AU",
    "sg:address":"79b Forbes St",
    "sg:city":"Devonport",
    "sg:classifiers":[
        {
            "category":"Professional",
            "subcategory":"Accounting & Tax Preparation",
            "type":"Services"
        }
    ],
    "sg:phone":"+61 3 6423 3888",
    "sg:postcode":"7310",
    "sg:province":"TAS",
    "sg:tags":[
        "consultant",
        "taxation"
    ],
    "wof:name":"Phoenix Accounting Services Tasmania",
    "wof:placetype":"venue"
},
  "geometry": {"coordinates":[146.355392456,-41.1865081787],"type":"Point"}
}