{
  "type": "Feature",
  "properties": {
    "addr:full":"106 Glasson St Chinchilla QLD 4413",
    "addr:housenumber":"106",
    "addr:postcode":"4413",
    "addr:street":"Glasson St",
    "iso:country":"AU",
    "sg:address":"106 Glasson St",
    "sg:city":"Chinchilla",
    "sg:classifiers":[
        {
            "category":"Autos & Motor Vehicles",
            "subcategory":"Auto Supplies",
            "type":"Retail Goods"
        }
    ],
    "sg:phone":"+61 7 4662 8102",
    "sg:postcode":"4413",
    "sg:province":"QLD",
    "sg:tags":[
        "wheel",
        "four",
        "equipment",
        "drive",
        "accessory"
    ],
    "wof:name":"Midstate Spares",
    "wof:placetype":"venue"
},
  "geometry": {"coordinates":[150.63543701200001,-26.7444839478],"type":"Point"}
}