{
  "type": "Feature",
  "properties": {
    "addr:full":"3/ 2 Garling Rd Kings Park NSW 2148",
    "addr:housenumber":"/ 2",
    "addr:postcode":"2148",
    "addr:street":"Garling Rd",
    "iso:country":"AU",
    "sg:address":"3/ 2 Garling Rd",
    "sg:city":"Kings Park",
    "sg:classifiers":[
        {
            "category":"Communications",
            "subcategory":"Film & Video Production",
            "type":"Services"
        }
    ],
    "sg:phone":"+61 2 9622 9600",
    "sg:postcode":"2148",
    "sg:province":"NSW",
    "sg:tags":[
        "dvd",
        "library"
    ],
    "wof:name":"Video Ezy",
    "wof:placetype":"venue"
},
  "geometry": {"coordinates":[150.91604614299999,-33.745475769],"type":"Point"}
}