{
  "type": "Feature",
  "properties": {
    "addr:full":"205 Main St Osborne Park WA 6017",
    "addr:housenumber":"205",
    "addr:postcode":"6017",
    "addr:street":"Main St",
    "iso:country":"AU",
    "sg:address":"205 Main St",
    "sg:city":"Osborne Park",
    "sg:classifiers":[
        {
            "category":"Food & Beverages",
            "subcategory":"Bakery",
            "type":"Retail Goods"
        }
    ],
    "sg:phone":"+61 8 9344 3283",
    "sg:postcode":"6017",
    "sg:province":"WA",
    "sg:tags":[
        "baker"
    ],
    "wof:name":"Osborne Bakery",
    "wof:placetype":"venue"
},
  "geometry": {"coordinates":[115.828102112,-31.8977985382],"type":"Point"}
}