{
  "type": "Feature",
  "properties": {
    "iso:country":"AU",
    "sg:address":"164 Belmore Rd",
    "sg:city":"Riverwood",
    "sg:classifiers":[
        {
            "category":"Real Estate",
            "subcategory":"Real Estate Agent",
            "type":"Services"
        }
    ],
    "sg:phone":"+61 2 9533 1111",
    "sg:postcode":"2210",
    "sg:province":"NSW",
    "wof:name":"L J Hooker",
    "wof:placetype":"venue"
},
  "geometry": {"coordinates":[151.05178799999999,-33.953808],"type":"Point"}
}