{
  "type": "Feature",
  "properties": {
    "addr:full":"5 Gardiner St Brunswick VIC 3056",
    "addr:housenumber":"5",
    "addr:postcode":"3056",
    "addr:street":"Gardiner St",
    "iso:country":"AU",
    "sg:address":"5 Gardiner St",
    "sg:city":"Brunswick",
    "sg:classifiers":[
        {
            "category":"Retail",
            "subcategory":"Auto Repair",
            "type":"Services"
        }
    ],
    "sg:phone":"+61 3 9380 8823",
    "sg:postcode":"3056",
    "sg:province":"VIC",
    "sg:tags":[
        "beater",
        "painter",
        "panel"
    ],
    "wof:name":"Brandi & Son Body Repairs",
    "wof:placetype":"venue"
},
  "geometry": {"coordinates":[144.95582580600001,-37.7680206299],"type":"Point"}
}