{
  "type": "Feature",
  "properties": {
    "addr:full":"105- 107 City Rd Beenleigh QLD 4207",
    "addr:housenumber":"105 107",
    "addr:postcode":"4207",
    "addr:street":"City Rd",
    "iso:country":"AU",
    "sg:address":"105- 107 City Rd",
    "sg:city":"Beenleigh",
    "sg:classifiers":[
        {
            "category":"Health Services",
            "subcategory":"Doctor",
            "type":"Services"
        }
    ],
    "sg:phone":"+61 7 5545 3677",
    "sg:postcode":"4207",
    "sg:province":"QLD",
    "sg:tags":[
        "medical",
        "practitioner"
    ],
    "wof:name":"Centre For Rheumatic Diseases",
    "wof:placetype":"venue"
},
  "geometry": {"coordinates":[153.202224731,-27.7143192291],"type":"Point"}
}