{
  "type": "Feature",
  "properties": {
    "iso:country":"AU",
    "sg:address":"Shop 8, Rivergum Village Crn Plenty Rd",
    "sg:city":"& Development Blv South Morang",
    "sg:classifiers":[
        {
            "category":"Health Services",
            "subcategory":"Optometrist",
            "type":"Services"
        }
    ],
    "sg:phone":"+61 3 9436 9644",
    "sg:postcode":"3752",
    "sg:province":"VIC",
    "wof:name":"Mill Park Eye Care",
    "wof:placetype":"venue"
},
  "geometry": {"coordinates":[145.095596,-37.637253],"type":"Point"}
}