{
  "type": "Feature",
  "properties": {
    "addr:full":"Fcty 10/ 8 Bray St Hastings VIC 3915",
    "addr:housenumber":"10 / 8",
    "addr:postcode":"3915",
    "addr:street":"Bray St",
    "iso:country":"AU",
    "sg:address":"Fcty 10/ 8 Bray St",
    "sg:city":"Hastings",
    "sg:classifiers":[
        {
            "category":"Recreation",
            "subcategory":"Amusement Park",
            "type":"Entertainment"
        }
    ],
    "sg:phone":"+61 3 5979 3200",
    "sg:postcode":"3915",
    "sg:province":"VIC",
    "wof:name":"Kidz World Indoor Play Centre",
    "wof:placetype":"venue"
},
  "geometry": {"coordinates":[145.18101501500001,-38.3139572144],"type":"Point"}
}