{
  "type": "Feature",
  "properties": {
    "addr:full":"98 Flinders Hwy Port Lincoln SA 5606",
    "addr:housenumber":"98",
    "addr:postcode":"5606",
    "addr:street":"Flinders Hwy",
    "iso:country":"AU",
    "sg:address":"98 Flinders Hwy",
    "sg:city":"Port Lincoln",
    "sg:classifiers":[
        {
            "category":"Freight",
            "type":"Transportation"
        }
    ],
    "sg:phone":"+61 8 8682 5045",
    "sg:postcode":"5606",
    "sg:province":"SA",
    "sg:tags":[
        "light",
        "carrier"
    ],
    "wof:name":"Happy Valley Transport",
    "wof:placetype":"venue"
},
  "geometry": {"coordinates":[135.837006,-34.714478],"type":"Point"}
}