{
  "type": "Feature",
  "properties": {
    "addr:full":"2/ 351 Mt Nelson Rd Mt Nelson TAS 7007",
    "addr:housenumber":"/ 351",
    "addr:postcode":"7007",
    "addr:street":"Mt Nelson Rd",
    "iso:country":"AU",
    "sg:address":"2/ 351 Mt Nelson Rd",
    "sg:city":"Mt Nelson",
    "sg:classifiers":[
        {
            "category":"Education",
            "subcategory":"Music School",
            "type":"Public Place"
        }
    ],
    "sg:phone":"+61 3 6223 7131",
    "sg:postcode":"7007",
    "sg:province":"TAS",
    "sg:tags":[
        "teacher"
    ],
    "wof:name":"Yasmin Shoobridge",
    "wof:placetype":"venue"
},
  "geometry": {"coordinates":[147.323822022,-42.9139976501],"type":"Point"}
}