{
  "type": "Feature",
  "properties": {
    "addr:full":"Balgowlah Rd Manly NSW 2095",
    "addr:postcode":"2095",
    "addr:street":"Balgowlah Rd",
    "iso:country":"AU",
    "sg:address":"Balgowlah Rd",
    "sg:city":"Manly",
    "sg:classifiers":[
        {
            "category":"Manufacturing",
            "subcategory":"Food",
            "type":"Manufacturing & Wholesale Goods"
        }
    ],
    "sg:phone":"+61 2 9977 5497",
    "sg:postcode":"2095",
    "sg:province":"NSW",
    "sg:tags":[
        "function",
        "catering"
    ],
    "wof:name":"Aquatic Caterers",
    "wof:placetype":"venue"
},
  "geometry": {"coordinates":[151.28007507300001,-33.7896232605],"type":"Point"}
}