{
  "type": "Feature",
  "properties": {
    "iso:country":"AU",
    "sg:address":"17 Shipton St",
    "sg:city":"Elizabeth",
    "sg:classifiers":[
        {
            "category":"Health Services",
            "subcategory":"Health Practitioner",
            "type":"Services"
        }
    ],
    "sg:phone":"+61 8 8255 2314",
    "sg:postcode":"5112",
    "sg:province":"SA",
    "sg:tags":[
        "bowen",
        "therapy"
    ],
    "wof:name":"Brian Cabrera",
    "wof:placetype":"venue"
},
  "geometry": {"coordinates":[138.67033386200001,-34.7225608826],"type":"Point"}
}