{
  "type": "Feature",
  "properties": {
    "iso:country":"AU",
    "sg:address":"Shop T191, Werribee Plaza Shopping Centre, Cnr of Heath & Derrimut Rds",
    "sg:city":"Hoppers Crossing",
    "sg:classifiers":[
        {
            "category":"Wholesale",
            "subcategory":"Medical Equipment & Supplies",
            "type":"Manufacturing & Wholesale Goods"
        }
    ],
    "sg:phone":"+61 3 9748 3166",
    "sg:postcode":"3029",
    "sg:province":"VIC",
    "sg:tags":[
        "scooter",
        "mobility"
    ],
    "sg:website":"http://www.wyndhammobility.com.au",
    "wof:name":"Wyndham Mobility",
    "wof:placetype":"venue"
},
  "geometry": {"coordinates":[144.685394,-37.864441],"type":"Point"}
}