{
  "type": "Feature",
  "properties": {
    "addr:full":"11/52- 54 Banks St Monterey NSW 2217",
    "addr:housenumber":"11 / 52 54",
    "addr:postcode":"2217",
    "addr:street":"Banks St",
    "iso:country":"AU",
    "sg:address":"11/52- 54 Banks St",
    "sg:city":"Monterey",
    "sg:classifiers":[
        {
            "category":"Home & Garden",
            "subcategory":"Building Materials",
            "type":"Retail Goods"
        }
    ],
    "sg:phone":"+61 410 695 396",
    "sg:postcode":"2217",
    "sg:province":"NSW",
    "sg:tags":[
        "supply"
    ],
    "wof:name":"Touch of Glass",
    "wof:placetype":"venue"
},
  "geometry": {"coordinates":[151.152557,-33.967884],"type":"Point"}
}