{
  "type": "Feature",
  "properties": {
    "addr:full":"718 Malvern Rd Toorak VIC 3142",
    "addr:housenumber":"718",
    "addr:postcode":"3142",
    "addr:street":"Malvern Rd",
    "iso:country":"AU",
    "sg:address":"718 Malvern Rd",
    "sg:city":"Toorak",
    "sg:classifiers":[
        {
            "category":"Retail",
            "subcategory":"Auto Repair",
            "type":"Services"
        }
    ],
    "sg:phone":"+61 3 9529 7347",
    "sg:postcode":"3142",
    "sg:province":"VIC",
    "sg:tags":[
        "beater",
        "painter",
        "panel"
    ],
    "wof:name":"Toorak Accident Repair Centre Pty Ltd",
    "wof:placetype":"venue"
},
  "geometry": {"coordinates":[145.01158142099999,-37.8492774963],"type":"Point"}
}