{
  "type": "Feature",
  "properties": {
    "iso:country":"AU",
    "sg:address":"175 Great Eastern Hwy",
    "sg:city":"Bakers Hill",
    "sg:classifiers":[
        {
            "category":"Autos & Motor Vehicles",
            "subcategory":"Fuel & Gas Station",
            "type":"Retail Goods"
        }
    ],
    "sg:phone":"+61 8 9574 1530",
    "sg:postcode":"6562",
    "sg:province":"WA",
    "wof:name":"Shell Co Of Australia Ltd The",
    "wof:placetype":"venue"
},
  "geometry": {"coordinates":[116.457832,-31.748598],"type":"Point"}
}