{
  "type": "Feature",
  "properties": {
    "iso:country":"AU",
    "sg:address":"12 Catherine St",
    "sg:city":"Rockhampton",
    "sg:classifiers":[
        {
            "category":"Manufacturing",
            "subcategory":"Rubber & Plastics",
            "type":"Manufacturing & Wholesale Goods"
        }
    ],
    "sg:phone":"+61 409 877 741",
    "sg:postcode":"4700",
    "sg:province":"QLD",
    "sg:tags":[
        "fabricator"
    ],
    "wof:name":"Plastweld",
    "wof:placetype":"venue"
},
  "geometry": {"coordinates":[150.49717712399999,-23.3705234528],"type":"Point"}
}