{
  "type": "Feature",
  "properties": {
    "addr:full":"Shop 20/ 161- 169 The Parade Norwood SA 5067",
    "addr:housenumber":"shop 20 / 161 169",
    "addr:postcode":"5067",
    "addr:street":"The Parade",
    "iso:country":"AU",
    "sg:address":"Shop 20/ 161- 169",
    "sg:city":"The Parade Norwood",
    "sg:classifiers":[
        {
            "category":"Government",
            "subcategory":"Post Office",
            "type":"Public Place"
        }
    ],
    "sg:phone":"+61 13 13 18",
    "sg:postcode":"5067",
    "sg:province":"SA",
    "sg:tags":[
        "postal"
    ],
    "wof:name":"Australia Post",
    "wof:placetype":"venue"
},
  "geometry": {"coordinates":[138.63276672399999,-34.92137146],"type":"Point"}
}