{
  "type": "Feature",
  "properties": {
    "addr:full":"138 Annangrove Rd Annangrove NSW 2156",
    "addr:housenumber":"138",
    "addr:postcode":"2156",
    "addr:street":"Annangrove Rd",
    "iso:country":"AU",
    "sg:address":"138 Annangrove Rd",
    "sg:city":"Annangrove",
    "sg:classifiers":[
        {
            "category":"Professional",
            "subcategory":"Engineering",
            "type":"Services"
        }
    ],
    "sg:phone":"+61 2 9654 2282",
    "sg:postcode":"2156",
    "sg:province":"NSW",
    "sg:tags":[
        "engineer"
    ],
    "wof:name":"Segeng Pty Ltd",
    "wof:placetype":"venue"
},
  "geometry": {"coordinates":[150.96771240199999,-33.67710495],"type":"Point"}
}