{
  "type": "Feature",
  "properties": {
    "addr:full":"325 Pier St Perth WA 6000",
    "addr:housenumber":"325",
    "addr:postcode":"6000",
    "addr:street":"Pier St",
    "iso:country":"AU",
    "sg:address":"325 Pier St",
    "sg:city":"Perth",
    "sg:classifiers":[
        {
            "category":"Real Estate",
            "subcategory":"Architect",
            "type":"Services"
        }
    ],
    "sg:phone":"+61 8 9227 1692",
    "sg:postcode":"6000",
    "sg:province":"WA",
    "wof:name":"Calvin Koh Architects (Aust) Pty Ltd",
    "wof:placetype":"venue"
},
  "geometry": {"coordinates":[115.868911743,-31.9448242188],"type":"Point"}
}