{
  "type": "Feature",
  "properties": {
    "addr:full":"395 Sevenoak St Beckenham WA 6107",
    "addr:housenumber":"395",
    "addr:postcode":"6107",
    "addr:street":"Sevenoak St",
    "iso:country":"AU",
    "sg:address":"395 Sevenoak St",
    "sg:city":"Beckenham",
    "sg:classifiers":[
        {
            "category":"Retail",
            "subcategory":"Auto Repair",
            "type":"Services"
        }
    ],
    "sg:phone":"+61 8 9356 1192",
    "sg:postcode":"6107",
    "sg:province":"WA",
    "sg:tags":[
        "repairer",
        "motor",
        "engineer"
    ],
    "wof:name":"Giorgiante Automotive Engineering Pty Ltd",
    "wof:placetype":"venue"
},
  "geometry": {"coordinates":[115.95375061,-32.0225372314],"type":"Point"}
}