{
  "type": "Feature",
  "properties": {
    "addr:full":"14 Elgata Rd Sheidow Park SA 5158",
    "addr:housenumber":"14",
    "addr:postcode":"5158",
    "addr:street":"Elgata Rd",
    "iso:country":"AU",
    "sg:address":"14 Elgata Rd",
    "sg:city":"Sheidow Park",
    "sg:classifiers":[
        {
            "category":"Personal",
            "subcategory":"Massage",
            "type":"Services"
        }
    ],
    "sg:phone":"+61 8 8381 7643",
    "sg:postcode":"5158",
    "sg:province":"SA",
    "sg:tags":[
        "therapy"
    ],
    "wof:name":"Grant P Guerin",
    "wof:placetype":"venue"
},
  "geometry": {"coordinates":[138.53222656200001,-35.0687446594],"type":"Point"}
}