{
  "type": "Feature",
  "properties": {
    "iso:country":"AU",
    "sg:address":"Shop 2032 Westfield Marion",
    "sg:city":"Oaklands Park",
    "sg:classifiers":[
        {
            "category":"Shopping",
            "subcategory":"Jewelry",
            "type":"Retail Goods"
        }
    ],
    "sg:phone":"+61 8 8377 0544",
    "sg:postcode":"5046",
    "sg:province":"SA",
    "sg:tags":[
        "jeweller"
    ],
    "wof:name":"Shiels",
    "wof:placetype":"venue"
},
  "geometry": {"coordinates":[138.537323,-35.002277],"type":"Point"}
}