{
  "type": "Feature",
  "properties": {
    "addr:full":"44 John Tebbutt Pl Richmond NSW 2753",
    "addr:housenumber":"44",
    "addr:postcode":"2753",
    "addr:street":"John Tebbutt Pl",
    "iso:country":"AU",
    "sg:address":"44 John Tebbutt Pl",
    "sg:city":"Richmond",
    "sg:classifiers":[
        {
            "category":"Organizations",
            "subcategory":"Professional Association",
            "type":"Services"
        }
    ],
    "sg:phone":"+61 404 458 946",
    "sg:postcode":"2753",
    "sg:province":"NSW",
    "sg:tags":[
        "web",
        "internet"
    ],
    "wof:name":"SiteFX",
    "wof:placetype":"venue"
},
  "geometry": {"coordinates":[150.74334716800001,-33.5974578857],"type":"Point"}
}