{
  "type": "Feature",
  "properties": {
    "addr:full":"PO Box 750 Muswellbrook NSW 2333",
    "addr:postcode":"2333",
    "iso:country":"AU",
    "sg:address":"PO Box 750",
    "sg:city":"Muswellbrook",
    "sg:classifiers":[
        {
            "category":"Shopping",
            "subcategory":"Party Supplies",
            "type":"Retail Goods"
        }
    ],
    "sg:phone":"+61 2 6543 8233",
    "sg:postcode":"2333",
    "sg:province":"NSW",
    "wof:name":"Function Hire",
    "wof:placetype":"venue"
},
  "geometry": {"coordinates":[150.88752746599999,-32.2689208984],"type":"Point"}
}