{
  "type": "Feature",
  "properties": {
    "addr:full":"PO Box 1091 Goolwa SA 5214",
    "addr:postcode":"5214",
    "iso:country":"AU",
    "sg:address":"PO Box 1091",
    "sg:city":"Goolwa",
    "sg:classifiers":[
        {
            "category":"Home & Garden",
            "subcategory":"Building Materials",
            "type":"Retail Goods"
        }
    ],
    "sg:phone":"+61 400 090 081",
    "sg:postcode":"5214",
    "sg:province":"SA",
    "sg:tags":[
        "pre-mixed",
        "concrete"
    ],
    "wof:name":"South Coast Concrete Supplies Pty Ltd",
    "wof:placetype":"venue"
},
  "geometry": {"coordinates":[138.77671814000001,-35.5021095276],"type":"Point"}
}