{
  "type": "Feature",
  "properties": {
    "iso:country":"AU",
    "sg:address":"51 Whyte St",
    "sg:city":"Coleraine",
    "sg:classifiers":[
        {
            "category":"Home & Garden",
            "subcategory":"Building Materials",
            "type":"Retail Goods"
        }
    ],
    "sg:phone":"+61 3 5575 2382",
    "sg:postcode":"3315",
    "sg:province":"VIC",
    "sg:tags":[
        "supply"
    ],
    "wof:name":"Coleraine Joinery & Building Supplies Pty Ltd",
    "wof:placetype":"venue"
},
  "geometry": {"coordinates":[141.69236755399999,-37.5983810425],"type":"Point"}
}