{
  "type": "Feature",
  "properties": {
    "addr:full":"14 Axel Pl Sinnamon Park QLD 4073",
    "addr:housenumber":"14",
    "addr:postcode":"4073",
    "addr:street":"Axel Pl",
    "iso:country":"AU",
    "sg:address":"14 Axel Pl",
    "sg:city":"Sinnamon Park",
    "sg:classifiers":[
        {
            "category":"Shopping",
            "subcategory":"Musical Instruments",
            "type":"Retail Goods"
        }
    ],
    "sg:phone":"+61 7 3279 6035",
    "sg:postcode":"4073",
    "sg:province":"QLD",
    "sg:tags":[
        "musician",
        "agent"
    ],
    "wof:name":"Mixed Up",
    "wof:placetype":"venue"
},
  "geometry": {"coordinates":[152.94490051299999,-27.5513153076],"type":"Point"}
}