{
  "type": "Feature",
  "properties": {
    "addr:full":"Bridge Rd Para Hills SA 5096",
    "addr:postcode":"5096",
    "addr:street":"Bridge Rd",
    "iso:country":"AU",
    "sg:address":"Bridge Rd",
    "sg:city":"Para Hills",
    "sg:classifiers":[
        {
            "category":"Arena",
            "subcategory":"Sports Club",
            "type":"Entertainment"
        }
    ],
    "sg:phone":"+61 8 8258 8863",
    "sg:postcode":"5096",
    "sg:province":"SA",
    "sg:tags":[
        "australian",
        "football",
        "rule"
    ],
    "wof:name":"Para Hills Football Club Incorporated",
    "wof:placetype":"venue"
},
  "geometry": {"coordinates":[138.649337769,-34.8067779541],"type":"Point"}
}