{
  "type": "Feature",
  "properties": {
    "iso:country":"AU",
    "sg:address":"29 Morrison Crt",
    "sg:city":"North Wangaratta",
    "sg:classifiers":[
        {
            "category":"Mining & Drilling",
            "type":"Manufacturing & Wholesale Goods"
        }
    ],
    "sg:phone":"+61 429 120 900",
    "sg:postcode":"3678",
    "sg:province":"VIC",
    "sg:tags":[
        "boring",
        "contractor"
    ],
    "wof:name":"Les Adams Industrial Pty Ltd",
    "wof:placetype":"venue"
},
  "geometry": {"coordinates":[146.34413147000001,-36.3223838806],"type":"Point"}
}