{
  "type": "Feature",
  "properties": {
    "iso:country":"AU",
    "sg:address":"Cnr Compton & Kingston Rds",
    "sg:city":"Underwood",
    "sg:classifiers":[
        {
            "category":"Personal",
            "type":"Services"
        }
    ],
    "sg:phone":"+61 7 3290 2633",
    "sg:postcode":"4119",
    "sg:province":"QLD",
    "sg:tags":[
        "reducing",
        "treatment",
        "weight"
    ],
    "wof:name":"Fernwood Slimplicity",
    "wof:placetype":"venue"
},
  "geometry": {"coordinates":[153.11184692399999,-27.6087932587],"type":"Point"}
}