{
  "type": "Feature",
  "properties": {
    "addr:full":"Cut Hill Rd Kangarilla SA 5157",
    "addr:postcode":"5157",
    "addr:street":"Hill Rd",
    "iso:country":"AU",
    "sg:address":"Cut Hill Rd",
    "sg:city":"Kangarilla",
    "sg:classifiers":[
        {
            "category":"Arena",
            "subcategory":"Horse Racetrack",
            "type":"Entertainment"
        }
    ],
    "sg:phone":"+61 8 8383 7238",
    "sg:postcode":"5157",
    "sg:province":"SA",
    "sg:tags":[
        "rotary",
        "hoeing"
    ],
    "wof:name":"Dowling N B & J G",
    "wof:placetype":"venue"
},
  "geometry": {"coordinates":[138.665893555,-35.1470794678],"type":"Point"}
}