{
  "type": "Feature",
  "properties": {
    "iso:country":"AU",
    "sg:address":"Lot 12/ 70 Sermelfi Drv",
    "sg:city":"Glenorie",
    "sg:classifiers":[
        {
            "category":"Banks & Credit Unions",
            "subcategory":"Investment Brokerage",
            "type":"Services"
        }
    ],
    "sg:phone":"+61 2 9659 6166",
    "sg:postcode":"2157",
    "sg:province":"NSW",
    "sg:tags":[
        "finance",
        "broker"
    ],
    "wof:name":"Scope Financial Services",
    "wof:placetype":"venue"
},
  "geometry": {"coordinates":[151.00227355999999,-33.594543457],"type":"Point"}
}