{
  "type": "Feature",
  "properties": {
    "addr:full":"Shop 1 112-118 Campbell Pde Bondi Beach NSW 2026",
    "addr:housenumber":"shop 1",
    "addr:postcode":"112-118;2026",
    "addr:street":"Campbell Pde",
    "iso:country":"AU",
    "sg:address":"Shop 1 112-118 Campbell Pde",
    "sg:city":"Bondi Beach",
    "sg:classifiers":[
        {
            "category":"Shopping",
            "subcategory":"Clothing, Apparel, & Fashions",
            "type":"Retail Goods"
        }
    ],
    "sg:phone":"+61 2 9130 6122",
    "sg:postcode":"2026",
    "sg:province":"NSW",
    "sg:tags":[
        "jean"
    ],
    "wof:name":"General Pants Co Pty Ltd",
    "wof:placetype":"venue"
},
  "geometry": {"coordinates":[151.27378845199999,-33.8912658691],"type":"Point"}
}