{
  "type": "Feature",
  "properties": {
    "addr:full":"40 Station Rd Indooroopilly QLD 4068",
    "addr:housenumber":"40",
    "addr:postcode":"4068",
    "addr:street":"Station Rd",
    "iso:country":"AU",
    "sg:address":"40 Station Rd",
    "sg:city":"Indooroopilly",
    "sg:classifiers":[
        {
            "category":"Health Services",
            "subcategory":"Dentist",
            "type":"Services"
        }
    ],
    "sg:phone":"+61 7 3378 9882",
    "sg:postcode":"4068",
    "sg:province":"QLD",
    "wof:name":"Floria Farhadi",
    "wof:placetype":"venue"
},
  "geometry": {"coordinates":[152.97383117699999,-27.5020561218],"type":"Point"}
}