{
  "type": "Feature",
  "properties": {
    "addr:full":"Woodvale Park Commercial Centre, Unit 6/923 Whitfo Woodvale WA 6026",
    "addr:housenumber":"6 / 923",
    "addr:postcode":"6026",
    "addr:street":"Whitfo",
    "iso:country":"AU",
    "sg:address":"Woodvale Park Commercial Centre, Unit 6/923 Whitfo",
    "sg:city":"Woodvale",
    "sg:classifiers":[
        {
            "category":"Personal",
            "subcategory":"Hair Removal",
            "type":"Services"
        }
    ],
    "sg:phone":"+61 8 9309 5677",
    "sg:postcode":"6026",
    "sg:province":"WA",
    "wof:name":"Beauty Gallery The",
    "wof:placetype":"venue"
},
  "geometry": {"coordinates":[115.79387664799999,-31.8001995087],"type":"Point"}
}