{
  "type": "Feature",
  "properties": {
    "addr:full":"PO Box 435 Yandina QLD 4561",
    "addr:postcode":"4561",
    "iso:country":"AU",
    "sg:address":"PO Box 435",
    "sg:city":"Yandina",
    "sg:classifiers":[
        {
            "category":"Building & Trades",
            "subcategory":"Construction",
            "type":"Services"
        }
    ],
    "sg:phone":"+61 405 234 145",
    "sg:postcode":"4561",
    "sg:province":"QLD",
    "sg:tags":[
        "contractor"
    ],
    "wof:name":"G.W. Back Brick & Block Layer",
    "wof:placetype":"venue"
},
  "geometry": {"coordinates":[152.956344605,-26.5604496002],"type":"Point"}
}