{
  "type": "Feature",
  "properties": {
    "iso:country":"AU",
    "sg:address":"60 Whiting St",
    "sg:city":"Artarmon",
    "sg:classifiers":[
        {
            "category":"Personal",
            "subcategory":"Adult",
            "type":"Services"
        }
    ],
    "sg:phone":"+61 2 9460 7456",
    "sg:postcode":"2064",
    "sg:province":"NSW",
    "sg:tags":[
        "entertainment"
    ],
    "wof:name":"Amanda Heavens",
    "wof:placetype":"venue"
},
  "geometry": {"coordinates":[151.181564331,-33.816204071],"type":"Point"}
}