{
  "type": "Feature",
  "properties": {
    "iso:country":"AU",
    "sg:address":"Springbank Rd",
    "sg:city":"Panorama",
    "sg:classifiers":[
        {
            "category":"Government",
            "subcategory":"Court House",
            "type":"Public Place"
        }
    ],
    "sg:phone":"+61 8 8277 2357",
    "sg:postcode":"5041",
    "sg:province":"SA",
    "sg:tags":[
        "personal",
        "marriage",
        "family",
        "counselling"
    ],
    "wof:name":"Pamela Brear",
    "wof:placetype":"venue"
},
  "geometry": {"coordinates":[138.597946,-34.99054],"type":"Point"}
}