{
  "type": "Feature",
  "properties": {
    "addr:full":"15 Cedar St Maleny QLD 4552",
    "addr:housenumber":"15",
    "addr:postcode":"4552",
    "addr:street":"Cedar St",
    "iso:country":"AU",
    "sg:address":"15 Cedar St",
    "sg:city":"Maleny",
    "sg:classifiers":[
        {
            "category":"Education",
            "subcategory":"Kindergarten",
            "type":"Public Place"
        }
    ],
    "sg:phone":"+61 7 5494 2330",
    "sg:postcode":"4552",
    "sg:province":"QLD",
    "sg:tags":[
        "pre-schools"
    ],
    "wof:name":"C&K Maleny Community Kindergarten",
    "wof:placetype":"venue"
},
  "geometry": {"coordinates":[152.84698486299999,-26.7580833435],"type":"Point"}
}