{
  "type": "Feature",
  "properties": {
    "addr:full":"382- 384 Princes Hwy Noble Park VIC 3174",
    "addr:housenumber":"384",
    "addr:postcode":"3174",
    "addr:street":"Princes Hwy",
    "iso:country":"AU",
    "sg:address":"382- 384 Princes Hwy",
    "sg:city":"Noble Park",
    "sg:classifiers":[
        {
            "category":"Social Services",
            "subcategory":"Retirement Home",
            "type":"Services"
        }
    ],
    "sg:phone":"+61 3 9794 8584",
    "sg:postcode":"3174",
    "sg:province":"VIC",
    "sg:tags":[
        "accommodation",
        "special"
    ],
    "wof:name":"Galilee",
    "wof:placetype":"venue"
},
  "geometry": {"coordinates":[145.18919372600001,-37.9617271423],"type":"Point"}
}