{
  "type": "Feature",
  "properties": {
    "addr:full":"28 Foote St Albert Park VIC 3206",
    "addr:housenumber":"28",
    "addr:postcode":"3206",
    "addr:street":"Foote St",
    "iso:country":"AU",
    "sg:address":"28 Foote St",
    "sg:city":"Albert Park",
    "sg:classifiers":[
        {
            "category":"Home & Garden",
            "subcategory":"Building Materials",
            "type":"Retail Goods"
        }
    ],
    "sg:phone":"+61 3 9699 1159",
    "sg:postcode":"3206",
    "sg:province":"VIC",
    "sg:tags":[
        "restoration",
        "supply"
    ],
    "wof:name":"Australian Damp Proofing",
    "wof:placetype":"venue"
},
  "geometry": {"coordinates":[144.94610599999999,-37.844749],"type":"Point"}
}