{
  "type": "Feature",
  "properties": {
    "addr:full":"Wirrabirra Primary School 71 Corfield St Gosnells WA 6110",
    "addr:housenumber":"71",
    "addr:postcode":"6110",
    "addr:street":"Corfield St",
    "iso:country":"AU",
    "sg:address":"Wirrabirra Primary School 71 Corfield St",
    "sg:city":"Gosnells",
    "sg:classifiers":[
        {
            "category":"Education",
            "subcategory":"School",
            "type":"Public Place"
        }
    ],
    "sg:phone":"+61 8 9398 7233",
    "sg:postcode":"6110",
    "sg:province":"WA",
    "sg:tags":[
        "state",
        "except",
        "nsw"
    ],
    "wof:name":"Schools Government (Public)",
    "wof:placetype":"venue"
},
  "geometry": {"coordinates":[115.999389648,-32.0901298523],"type":"Point"}
}