{
  "type": "Feature",
  "properties": {
    "addr:full":"26 High St Glen Iris VIC 3146",
    "addr:housenumber":"26",
    "addr:postcode":"3146",
    "addr:street":"High St",
    "iso:country":"AU",
    "sg:address":"26 High St",
    "sg:city":"Glen Iris",
    "sg:classifiers":[
        {
            "category":"Fast Food",
            "type":"Food & Drink"
        }
    ],
    "sg:phone":"+61 3 9885 5390",
    "sg:postcode":"3146",
    "sg:province":"VIC",
    "sg:tags":[
        "away",
        "take"
    ],
    "wof:name":"Hello Sharky's Seafood",
    "wof:placetype":"venue"
},
  "geometry": {"coordinates":[145.06532287600001,-37.8618545532],"type":"Point"}
}