{
  "type": "Feature",
  "properties": {
    "addr:full":"42 Union St Wickham NSW 2293",
    "addr:housenumber":"42",
    "addr:postcode":"2293",
    "addr:street":"Union St",
    "iso:country":"AU",
    "sg:address":"42 Union St",
    "sg:city":"Wickham",
    "sg:classifiers":[
        {
            "category":"Wholesale",
            "subcategory":"Drugs",
            "type":"Manufacturing & Wholesale Goods"
        }
    ],
    "sg:phone":"+61 2 4965 3263",
    "sg:postcode":"2293",
    "sg:province":"NSW",
    "sg:tags":[
        "wholesaler",
        "pharmaceutical",
        "product",
        "mfrs"
    ],
    "wof:name":"Scott Dibben Pty Ltd",
    "wof:placetype":"venue"
},
  "geometry": {"coordinates":[151.75799560600001,-32.9217453003],"type":"Point"}
}