{
  "type": "Feature",
  "properties": {
    "iso:country":"AU",
    "sg:address":"52 First Ave",
    "sg:city":"Five Dock",
    "sg:classifiers":[
        {
            "category":"Food & Beverages",
            "subcategory":"Groceries & Convenience Stores",
            "type":"Retail Goods"
        }
    ],
    "sg:phone":"+61 2 9713 9013",
    "sg:postcode":"2046",
    "sg:province":"NSW",
    "wof:name":"Rodd Point Convenience Store",
    "wof:placetype":"venue"
},
  "geometry": {"coordinates":[151.141357,-33.866112],"type":"Point"}
}