{
  "type": "Feature",
  "properties": {
    "addr:full":"34 Cliff St Sandgate QLD 4017",
    "addr:housenumber":"34",
    "addr:postcode":"4017",
    "addr:street":"Cliff St",
    "iso:country":"AU",
    "sg:address":"34 Cliff St",
    "sg:city":"Sandgate",
    "sg:classifiers":[
        {
            "category":"Professional",
            "subcategory":"Art Services",
            "type":"Services"
        }
    ],
    "sg:phone":"+61 421 511 788",
    "sg:postcode":"4017",
    "sg:province":"QLD",
    "sg:tags":[
        "graphic",
        "designer"
    ],
    "wof:name":"Designa Brisbane",
    "wof:placetype":"venue"
},
  "geometry": {"coordinates":[153.07145690900001,-27.3201847076],"type":"Point"}
}