{
  "type": "Feature",
  "properties": {
    "iso:country":"AU",
    "sg:address":"53 Richmond Rd",
    "sg:city":"Blacktown",
    "sg:classifiers":[
        {
            "category":"Autos & Motor Vehicles",
            "subcategory":"Auto Supplies",
            "type":"Retail Goods"
        }
    ],
    "sg:phone":"+61 2 9622 1091",
    "sg:postcode":"2148",
    "sg:province":"NSW",
    "sg:tags":[
        "part",
        "cycles",
        "accessory"
    ],
    "wof:name":"B.W. Northcott Motor Cycles",
    "wof:placetype":"venue"
},
  "geometry": {"coordinates":[150.902740478,-33.7643547058],"type":"Point"}
}