{
  "type": "Feature",
  "properties": {
    "addr:full":"Queen St Barraba NSW 2347",
    "addr:postcode":"2347",
    "addr:street":"Queen St",
    "iso:country":"AU",
    "sg:address":"Queen St",
    "sg:city":"Barraba",
    "sg:classifiers":[
        {
            "category":"Restaurant",
            "type":"Food & Drink"
        }
    ],
    "sg:phone":"+61 2 6782 1402",
    "sg:postcode":"2347",
    "sg:province":"NSW",
    "wof:name":"Barraba Bowling Club Chinese Restaurant",
    "wof:placetype":"venue"
},
  "geometry": {"coordinates":[150.610031128,-30.3815441132],"type":"Point"}
}