{
  "type": "Feature",
  "properties": {
    "iso:country":"AU",
    "sg:address":"115 Pacific Hwy",
    "sg:city":"Taree",
    "sg:classifiers":[
        {
            "category":"Building & Trades",
            "subcategory":"Construction",
            "type":"Services"
        }
    ],
    "sg:phone":"+61 2 6553 6885",
    "sg:postcode":"2430",
    "sg:province":"NSW",
    "sg:tags":[
        "contractor"
    ],
    "wof:name":"Cross Tim",
    "wof:placetype":"venue"
},
  "geometry": {"coordinates":[152.55006399999999,-31.887613],"type":"Point"}
}