{
  "type": "Feature",
  "properties": {
    "iso:country":"AU",
    "sg:address":"18 Christina St",
    "sg:city":"Wellington Point",
    "sg:classifiers":[
        {
            "category":"Retail",
            "subcategory":"Photofinishing",
            "type":"Services"
        }
    ],
    "sg:phone":"+61 7 3822 5812",
    "sg:postcode":"4160",
    "sg:province":"QLD",
    "sg:tags":[
        "refractory"
    ],
    "wof:name":"Cookson Plibrico Pty Ltd",
    "wof:placetype":"venue"
},
  "geometry": {"coordinates":[153.23611450199999,-27.485458374],"type":"Point"}
}