{
  "type": "Feature",
  "properties": {
    "addr:full":"Babbage Rd East Roseville NSW 2069",
    "addr:postcode":"2069",
    "addr:street":"Babbage Rd",
    "iso:country":"AU",
    "sg:address":"Babbage Rd",
    "sg:city":"East Roseville",
    "sg:classifiers":[
        {
            "category":"Education",
            "subcategory":"Kindergarten",
            "type":"Public Place"
        }
    ],
    "sg:phone":"+61 2 9417 3041",
    "sg:postcode":"2069",
    "sg:province":"NSW",
    "sg:tags":[
        "pre-schools"
    ],
    "wof:name":"Chase Kindergarten Community Hall The",
    "wof:placetype":"venue"
},
  "geometry": {"coordinates":[151.194854736,-33.7823982239],"type":"Point"}
}