{
  "type": "Feature",
  "properties": {
    "addr:full":"Suite 6, 262- 264 Springvale Rd Glen Waverley VIC 3150",
    "addr:housenumber":"262 264",
    "addr:postcode":"3150",
    "addr:street":"Springvale Rd",
    "iso:country":"AU",
    "sg:address":"Suite 6, 262- 264 Springvale Rd",
    "sg:city":"Glen Waverley",
    "sg:classifiers":[
        {
            "category":"Health Services",
            "subcategory":"Doctor",
            "type":"Services"
        }
    ],
    "sg:phone":"+61 3 9426 6693",
    "sg:postcode":"3150",
    "sg:province":"VIC",
    "sg:tags":[
        "medical",
        "practitioner"
    ],
    "wof:name":"Walton Tony",
    "wof:placetype":"venue"
},
  "geometry": {"coordinates":[145.165847778,-37.8809242249],"type":"Point"}
}