{
  "type": "Feature",
  "properties": {
    "iso:country":"AU",
    "sg:address":"Needle St",
    "sg:city":"Cockatoo Valley",
    "sg:classifiers":[
        {
            "category":"Retail",
            "subcategory":"Repair Shop",
            "type":"Services"
        }
    ],
    "sg:phone":"+61 8 8523 0277",
    "sg:postcode":"5351",
    "sg:province":"SA",
    "sg:tags":[
        "windscreen"
    ],
    "wof:name":"Gawler Autoglass",
    "wof:placetype":"venue"
},
  "geometry": {"coordinates":[138.86360168499999,-34.6535263062],"type":"Point"}
}