{
  "type": "Feature",
  "properties": {
    "iso:country":"AU",
    "sg:address":"55 Nightingale Rd",
    "sg:city":"Pheasants Nest",
    "sg:classifiers":[
        {
            "category":"Building & Trades",
            "subcategory":"Construction",
            "type":"Services"
        }
    ],
    "sg:phone":"+61 2 4684 1129",
    "sg:postcode":"2574",
    "sg:province":"NSW",
    "sg:tags":[
        "contractor"
    ],
    "wof:name":"Chalker Constructions",
    "wof:placetype":"venue"
},
  "geometry": {"coordinates":[150.63081359899999,-34.2701301575],"type":"Point"}
}