{
  "type": "Feature",
  "properties": {
    "addr:full":"54A Bromfield St Colac VIC 3250",
    "addr:housenumber":"54a",
    "addr:postcode":"3250",
    "addr:street":"Bromfield St",
    "iso:country":"AU",
    "sg:address":"54A Bromfield St",
    "sg:city":"Colac",
    "sg:classifiers":[
        {
            "category":"Professional",
            "subcategory":"Employment Agencies",
            "type":"Services"
        }
    ],
    "sg:phone":"+61 3 5231 5590",
    "sg:postcode":"3250",
    "sg:province":"VIC",
    "wof:name":"St. Laurence",
    "wof:placetype":"venue"
},
  "geometry": {"coordinates":[143.58554100000001,-38.341061],"type":"Point"}
}