{
  "type": "Feature",
  "properties": {
    "iso:country":"AU",
    "sg:address":"159 Enmore Rd",
    "sg:city":"Enmore",
    "sg:classifiers":[
        {
            "category":"Communications",
            "subcategory":"Film & Video Production",
            "type":"Services"
        }
    ],
    "sg:phone":"+61 2 9516 4444",
    "sg:postcode":"2042",
    "sg:province":"NSW",
    "sg:tags":[
        "dvd",
        "library"
    ],
    "wof:name":"Civic Video Pty Ltd",
    "wof:placetype":"venue"
},
  "geometry": {"coordinates":[151.172714,-33.898804],"type":"Point"}
}