{
  "type": "Feature",
  "properties": {
    "iso:country":"AU",
    "sg:address":"1 Innisfallen Ave",
    "sg:city":"Templestowe",
    "sg:classifiers":[
        {
            "category":"Health Services",
            "subcategory":"Nursing And Care Facility",
            "type":"Services"
        }
    ],
    "sg:phone":"+61 3 9846 6077",
    "sg:postcode":"3106",
    "sg:province":"VIC",
    "sg:tags":[
        "home"
    ],
    "wof:name":"Huon Healthcare",
    "wof:placetype":"venue"
},
  "geometry": {"coordinates":[145.15162658700001,-37.7542648315],"type":"Point"}
}