{
  "type": "Feature",
  "properties": {
    "addr:full":"2175 Sheffield Rd Sheffield TAS 7306",
    "addr:housenumber":"2175",
    "addr:postcode":"7306",
    "addr:street":"Sheffield Rd",
    "iso:country":"AU",
    "sg:address":"2175 Sheffield Rd",
    "sg:city":"Sheffield",
    "sg:classifiers":[
        {
            "category":"Real Estate",
            "subcategory":"Surveying",
            "type":"Services"
        }
    ],
    "sg:phone":"+61 3 6491 1442",
    "sg:postcode":"7306",
    "sg:province":"TAS",
    "sg:tags":[
        "surveyor",
        "land"
    ],
    "wof:name":"Sands Richard",
    "wof:placetype":"venue"
},
  "geometry": {"coordinates":[146.31114199999999,-41.375729],"type":"Point"}
}