{
  "type": "Feature",
  "properties": {
    "iso:country":"AU",
    "sg:address":"25B Jackson St",
    "sg:city":"Bassendean",
    "sg:classifiers":[
        {
            "category":"Professional",
            "subcategory":"Engineering",
            "type":"Services"
        }
    ],
    "sg:phone":"+61 8 9279 5622",
    "sg:postcode":"6054",
    "sg:province":"WA",
    "sg:tags":[
        "diesel",
        "engineer"
    ],
    "wof:name":"All States Mechanical Engineering & Tyres",
    "wof:placetype":"venue"
},
  "geometry": {"coordinates":[115.928466797,-31.9087219238],"type":"Point"}
}