{
  "type": "Feature",
  "properties": {
    "iso:country":"AU",
    "sg:address":"220 Oxford St",
    "sg:city":"Paddington",
    "sg:classifiers":[
        {
            "category":"Government",
            "subcategory":"Post Office",
            "type":"Public Place"
        }
    ],
    "sg:phone":"+61 413 088 792",
    "sg:postcode":"2021",
    "sg:province":"NSW",
    "sg:tags":[
        "yoga"
    ],
    "wof:name":"Yoga Sam",
    "wof:placetype":"venue"
},
  "geometry": {"coordinates":[151.22564697300001,-33.884803772],"type":"Point"}
}