{
  "type": "Feature",
  "properties": {
    "addr:full":"Nabiac Showground, Nabiac St Nabiac NSW 2312",
    "addr:postcode":"2312",
    "addr:street":"Nabiac St",
    "iso:country":"AU",
    "sg:address":"Nabiac Showground, Nabiac St",
    "sg:city":"Nabiac",
    "sg:classifiers":[
        {
            "category":"Building & Trades",
            "subcategory":"Landscaping Services",
            "type":"Services"
        }
    ],
    "sg:phone":"+61 2 6554 1906",
    "sg:postcode":"2312",
    "sg:province":"NSW",
    "sg:tags":[
        "market"
    ],
    "wof:name":"Nabiac Farmers Market",
    "wof:placetype":"venue"
},
  "geometry": {"coordinates":[152.37629699999999,-32.09848],"type":"Point"}
}