{
  "type": "Feature",
  "properties": {
    "addr:full":"30 Brickwood St Brighton VIC 3186",
    "addr:housenumber":"30",
    "addr:postcode":"3186",
    "addr:street":"Brickwood St",
    "iso:country":"AU",
    "sg:address":"30 Brickwood St",
    "sg:city":"Brighton",
    "sg:classifiers":[
        {
            "category":"Building & Trades",
            "subcategory":"Plumbing",
            "type":"Services"
        }
    ],
    "sg:phone":"+61 419 192 925",
    "sg:postcode":"3186",
    "sg:province":"VIC",
    "sg:tags":[
        "plumber",
        "gasfitters"
    ],
    "wof:name":"Bright Sands Plumbing",
    "wof:placetype":"venue"
},
  "geometry": {"coordinates":[144.99815368599999,-37.8935775757],"type":"Point"}
}