{
  "type": "Feature",
  "properties": {
    "addr:full":"9 Taylor St Woy Woy Bay NSW 2256",
    "addr:housenumber":"9",
    "addr:postcode":"2256",
    "addr:street":"Taylor St",
    "iso:country":"AU",
    "sg:address":"9 Taylor St",
    "sg:city":"Woy Woy Bay",
    "sg:classifiers":[
        {
            "category":"Building & Trades",
            "subcategory":"Construction",
            "type":"Services"
        }
    ],
    "sg:phone":"+61 2 4342 9157",
    "sg:postcode":"2256",
    "sg:province":"NSW",
    "sg:tags":[
        "contractor"
    ],
    "wof:name":"Mark Lynch",
    "wof:placetype":"venue"
},
  "geometry": {"coordinates":[151.31500244099999,-33.4836654663],"type":"Point"}
}