{
  "type": "Feature",
  "properties": {
    "iso:country":"AU",
    "sg:address":"102 Ingrid Rd",
    "sg:city":"Kareela",
    "sg:classifiers":[
        {
            "category":"Professional",
            "subcategory":"Art Services",
            "type":"Services"
        }
    ],
    "sg:phone":"+61 2 9589 3803",
    "sg:postcode":"2232",
    "sg:province":"NSW",
    "sg:tags":[
        "decorator",
        "painter"
    ],
    "wof:name":"A & S Fawns",
    "wof:placetype":"venue"
},
  "geometry": {"coordinates":[151.08546447800001,-34.013885498],"type":"Point"}
}