{
  "type": "Feature",
  "properties": {
    "addr:full":"30 Redhill Rd Young NSW 2594",
    "addr:housenumber":"30",
    "addr:postcode":"2594",
    "addr:street":"Redhill Rd",
    "iso:country":"AU",
    "sg:address":"30 Redhill Rd",
    "sg:city":"Young",
    "sg:classifiers":[
        {
            "category":"Farming",
            "subcategory":"Nursery",
            "type":"Manufacturing & Wholesale Goods"
        }
    ],
    "sg:phone":"+61 2 6382 3181",
    "sg:postcode":"2594",
    "sg:province":"NSW",
    "wof:name":"Olive Tree Nursery",
    "wof:placetype":"venue"
},
  "geometry": {"coordinates":[148.29080200199999,-34.2963485718],"type":"Point"}
}