{
  "type": "Feature",
  "properties": {
    "addr:full":"110 Doveton St South Ballarat VIC 3350",
    "addr:housenumber":"110",
    "addr:postcode":"3350",
    "addr:street":"Doveton St South",
    "iso:country":"AU",
    "sg:address":"110 Doveton St",
    "sg:city":"South Ballarat",
    "sg:classifiers":[
        {
            "category":"Health Services",
            "subcategory":"Dentist",
            "type":"Services"
        }
    ],
    "sg:phone":"+61 3 5331 1802",
    "sg:postcode":"3350",
    "sg:province":"VIC",
    "sg:tags":[
        "technician",
        "dental"
    ],
    "wof:name":"Davies W T",
    "wof:placetype":"venue"
},
  "geometry": {"coordinates":[143.85415599999999,-37.564358],"type":"Point"}
}