{
  "type": "Feature",
  "properties": {
    "addr:full":"3/ 124 Main St Proserpine QLD 4800",
    "addr:housenumber":"/ 124",
    "addr:postcode":"4800",
    "addr:street":"Main St",
    "iso:country":"AU",
    "sg:address":"3/ 124 Main St",
    "sg:city":"Proserpine",
    "sg:classifiers":[
        {
            "category":"Communications",
            "subcategory":"Film & Video Production",
            "type":"Services"
        }
    ],
    "sg:phone":"+61 7 4945 2864",
    "sg:postcode":"4800",
    "sg:province":"QLD",
    "sg:tags":[
        "dvd",
        "library"
    ],
    "wof:name":"Video Main Street",
    "wof:placetype":"venue"
},
  "geometry": {"coordinates":[148.58546447800001,-20.4021224976],"type":"Point"}
}