{
  "type": "Feature",
  "properties": {
    "iso:country":"AU",
    "sg:address":"PO Box 1058",
    "sg:city":"Altona Meadows",
    "sg:classifiers":[
        {
            "category":"Professional",
            "type":"Services"
        }
    ],
    "sg:phone":"+61 402 473 203",
    "sg:postcode":"3028",
    "sg:province":"VIC",
    "sg:tags":[
        "transport"
    ],
    "wof:name":"Exquisite Transport Operations Pty Ltd",
    "wof:placetype":"venue"
},
  "geometry": {"coordinates":[144.777481,-37.872028],"type":"Point"}
}