{
  "type": "Feature",
  "properties": {
    "addr:full":"Sunshine Coast Private Hospital Suite 14, The Medical Centre 12 Elsa Wilson Drv Buderim QLD 4556",
    "addr:housenumber":"12",
    "addr:postcode":"4556",
    "addr:street":"Sunshine;Elsa Wilson Drv",
    "iso:country":"AU",
    "sg:address":"Sunshine Coast Private Hospital Suite 14, The Medical Centre 12 Elsa Wilson Drv",
    "sg:city":"Buderim",
    "sg:classifiers":[
        {
            "category":"Health Services",
            "subcategory":"Doctor",
            "type":"Services"
        }
    ],
    "sg:phone":"+61 7 5452 6511",
    "sg:postcode":"4556",
    "sg:province":"QLD",
    "sg:tags":[
        "medical",
        "practitioner"
    ],
    "wof:name":"Hoyle Kirsten Dr",
    "wof:placetype":"venue"
},
  "geometry": {"coordinates":[153.09608459500001,-26.6818027496],"type":"Point"}
}