{
  "type": "Feature",
  "properties": {
    "addr:full":"26 Graffin Crs Winnellie NT 0820",
    "addr:housenumber":"26",
    "addr:postcode":"nt 0820",
    "addr:street":"Graffin Crs",
    "iso:country":"AU",
    "sg:address":"26 Graffin Crs",
    "sg:city":"Winnellie",
    "sg:classifiers":[
        {
            "category":"Transit Center",
            "subcategory":"Freight",
            "type":"Transportation"
        }
    ],
    "sg:phone":"+61 8 8947 1102",
    "sg:postcode":"0820",
    "sg:province":"NT",
    "sg:tags":[
        "forklift",
        "truck"
    ],
    "wof:name":"Red Australia Equipment Pty Ltd",
    "wof:placetype":"venue"
},
  "geometry": {"coordinates":[130.89439392099999,-12.4263296127],"type":"Point"}
}