{
  "type": "Feature",
  "properties": {
    "addr:full":"90b Newlands Rd Reservoir VIC 3073",
    "addr:housenumber":"90b",
    "addr:postcode":"3073",
    "addr:street":"Newlands Rd",
    "iso:country":"AU",
    "sg:address":"90b Newlands Rd",
    "sg:city":"Reservoir",
    "sg:classifiers":[
        {
            "category":"Fast Food",
            "type":"Food & Drink"
        }
    ],
    "sg:phone":"+61 3 9462 1582",
    "sg:postcode":"3073",
    "sg:province":"VIC",
    "sg:tags":[
        "away",
        "take"
    ],
    "wof:name":"The Corner Take-A-Way",
    "wof:placetype":"venue"
},
  "geometry": {"coordinates":[144.983154297,-37.7163391113],"type":"Point"}
}