{
  "type": "Feature",
  "properties": {
    "addr:full":"Shp 4/ 19 Cribb St Milton QLD 4064",
    "addr:housenumber":"/ 19",
    "addr:postcode":"4064",
    "addr:street":"Cribb St",
    "iso:country":"AU",
    "sg:address":"Shp 4/ 19 Cribb St",
    "sg:city":"Milton",
    "sg:classifiers":[
        {
            "category":"Personal",
            "subcategory":"Beauty Salon",
            "type":"Services"
        }
    ],
    "sg:phone":"+61 7 3876 2055",
    "sg:postcode":"4064",
    "sg:province":"QLD",
    "sg:tags":[
        "hairdresser"
    ],
    "wof:name":"Imagine Hair & Body",
    "wof:placetype":"venue"
},
  "geometry": {"coordinates":[153.00813293499999,-27.4695148468],"type":"Point"}
}