{
  "type": "Feature",
  "properties": {
    "iso:country":"AU",
    "sg:address":"2 64 Annerley Rd",
    "sg:city":"Woolloongabba",
    "sg:classifiers":[
        {
            "category":"Health Services",
            "subcategory":"Health Practitioner",
            "type":"Services"
        }
    ],
    "sg:phone":"+61 7 3004 3450",
    "sg:postcode":"4102",
    "sg:province":"QLD",
    "sg:tags":[
        "psychologist"
    ],
    "wof:name":"Lamberton Anna",
    "wof:placetype":"venue"
},
  "geometry": {"coordinates":[153.027877808,-27.4892158508],"type":"Point"}
}