{
  "type": "Feature",
  "properties": {
    "iso:country":"AU",
    "sg:address":"118 High St",
    "sg:city":"Kew",
    "sg:classifiers":[
        {
            "category":"Autos & Motor Vehicles",
            "subcategory":"Automobile Sales",
            "type":"Retail Goods"
        }
    ],
    "sg:phone":"+61 3 9853 5471",
    "sg:postcode":"3101",
    "sg:province":"VIC",
    "sg:tags":[
        "car",
        "used"
    ],
    "wof:name":"Q Cars",
    "wof:placetype":"venue"
},
  "geometry": {"coordinates":[145.02911376899999,-37.8075256348],"type":"Point"}
}