{
  "type": "Feature",
  "properties": {
    "addr:full":"393 Mt Alexander Rd Ascot Vale VIC 3032",
    "addr:housenumber":"393",
    "addr:postcode":"3032",
    "addr:street":"Mt Alexander Rd",
    "iso:country":"AU",
    "sg:address":"393 Mt Alexander Rd",
    "sg:city":"Ascot Vale",
    "sg:classifiers":[
        {
            "category":"Shopping",
            "subcategory":"Crafts & Fabrics",
            "type":"Retail Goods"
        }
    ],
    "sg:phone":"+61 3 9326 2235",
    "sg:postcode":"3032",
    "sg:province":"VIC",
    "sg:tags":[
        "supply"
    ],
    "wof:name":"Teddys Bits Pty Ltd",
    "wof:placetype":"venue"
},
  "geometry": {"coordinates":[144.92778000000001,-37.774761],"type":"Point"}
}