{
  "type": "Feature",
  "properties": {
    "iso:country":"AU",
    "sg:address":"101 Lynfield Drv",
    "sg:city":"Caboolture",
    "sg:classifiers":[
        {
            "category":"Social Services",
            "subcategory":"Child Care",
            "type":"Services"
        }
    ],
    "sg:phone":"+61 7 5495 6133",
    "sg:postcode":"4510",
    "sg:province":"QLD",
    "wof:name":"Caboolture West Children's Centre",
    "wof:placetype":"venue"
},
  "geometry": {"coordinates":[152.934647,-27.077307],"type":"Point"}
}