{
  "type": "Feature",
  "properties": {
    "addr:full":"101 Lynfield Drv Caboolture QLD 4510",
    "addr:housenumber":"101",
    "addr:postcode":"4510",
    "addr:street":"Lynfield Drv",
    "iso:country":"AU",
    "sg:address":"101 Lynfield Drv",
    "sg:city":"Caboolture",
    "sg:classifiers":[
        {
            "category":"Social Services",
            "subcategory":"Child Care",
            "type":"Services"
        }
    ],
    "sg:phone":"+61 7 5495 6133",
    "sg:postcode":"4510",
    "sg:province":"QLD",
    "wof:name":"Caboolture West Children's Centre",
    "wof:placetype":"venue"
},
  "geometry": {"coordinates":[152.93464700000001,-27.077307],"type":"Point"}
}