{
  "type": "Feature",
  "properties": {
    "addr:full":"11b Yallourn St Fyshwick ACT 2609",
    "addr:housenumber":"11b",
    "addr:postcode":"2609",
    "addr:street":"Yallourn St",
    "iso:country":"AU",
    "sg:address":"11b Yallourn St",
    "sg:city":"Fyshwick",
    "sg:classifiers":[
        {
            "category":"Shopping",
            "subcategory":"Stationery & Office Supplies",
            "type":"Retail Goods"
        }
    ],
    "sg:phone":"+61 2 6280 5805",
    "sg:postcode":"2609",
    "sg:province":"ACT",
    "sg:tags":[
        "equipment",
        "display",
        "exhibition"
    ],
    "wof:name":"Neoplex Pty Ltd",
    "wof:placetype":"venue"
},
  "geometry": {"coordinates":[149.17054748499999,-35.3328552246],"type":"Point"}
}