{
  "type": "Feature",
  "properties": {
    "iso:country":"AU",
    "sg:address":"145 Scott Pde",
    "sg:city":"Ballarat East",
    "sg:classifiers":[
        {
            "category":"Personal",
            "subcategory":"Massage",
            "type":"Services"
        }
    ],
    "sg:phone":"+61 3 5331 7228",
    "sg:postcode":"3350",
    "sg:province":"VIC",
    "sg:tags":[
        "therapy"
    ],
    "wof:name":"Tonie Swinkels-Johnson",
    "wof:placetype":"venue"
},
  "geometry": {"coordinates":[143.876434,-37.558064],"type":"Point"}
}