{
  "type": "Feature",
  "properties": {
    "addr:full":"3 Everton Rd Strathfield NSW 2135",
    "addr:housenumber":"3",
    "addr:postcode":"2135",
    "addr:street":"Everton Rd",
    "iso:country":"AU",
    "sg:address":"3 Everton Rd",
    "sg:city":"Strathfield",
    "sg:classifiers":[
        {
            "category":"Health Services",
            "subcategory":"Doctor",
            "type":"Services"
        }
    ],
    "sg:phone":"+61 2 9745 7431",
    "sg:postcode":"2135",
    "sg:province":"NSW",
    "sg:tags":[
        "medical",
        "practitioner"
    ],
    "wof:name":"Gillett David",
    "wof:placetype":"venue"
},
  "geometry": {"coordinates":[151.09799194300001,-33.8721923828],"type":"Point"}
}