{
  "type": "Feature",
  "properties": {
    "addr:full":"115 Eagleby Rd Eagleby QLD 4207",
    "addr:housenumber":"115",
    "addr:postcode":"4207",
    "addr:street":"Eagleby Rd",
    "iso:country":"AU",
    "sg:address":"115 Eagleby Rd",
    "sg:city":"Eagleby",
    "sg:classifiers":[
        {
            "category":"Farming",
            "subcategory":"Farm",
            "type":"Manufacturing & Wholesale Goods"
        }
    ],
    "sg:phone":"+61 7 3287 2620",
    "sg:postcode":"4207",
    "sg:province":"QLD",
    "sg:tags":[
        "farmer"
    ],
    "wof:name":"Ludcke D G",
    "wof:placetype":"venue"
},
  "geometry": {"coordinates":[153.21604919399999,-27.6870040894],"type":"Point"}
}