{
  "type": "Feature",
  "properties": {
    "addr:full":"23 Bittern Ave Burleigh Heads QLD 4220",
    "addr:housenumber":"23",
    "addr:postcode":"4220",
    "addr:street":"Bittern Ave",
    "iso:country":"AU",
    "sg:address":"23 Bittern Ave",
    "sg:city":"Burleigh Heads",
    "sg:classifiers":[
        {
            "category":"Shopping",
            "subcategory":"Computers & Home Electronics",
            "type":"Retail Goods"
        }
    ],
    "sg:phone":"+61 7 5535 9316",
    "sg:postcode":"4220",
    "sg:province":"QLD",
    "sg:tags":[
        "hardware",
        "equipment"
    ],
    "wof:name":"Networx I.T. Support",
    "wof:placetype":"venue"
},
  "geometry": {"coordinates":[153.43853759800001,-28.0828113556],"type":"Point"}
}