{
  "type": "Feature",
  "properties": {
    "addr:full":"177 Jells Rd Wheelers Hill VIC 3150",
    "addr:housenumber":"177",
    "addr:postcode":"3150",
    "addr:street":"Jells Rd",
    "iso:country":"AU",
    "sg:address":"177 Jells Rd",
    "sg:city":"Wheelers Hill",
    "sg:classifiers":[
        {
            "category":"Health Services",
            "subcategory":"Health Practitioner",
            "type":"Services"
        }
    ],
    "sg:phone":"+61 3 9561 2201",
    "sg:postcode":"3150",
    "sg:province":"VIC",
    "sg:tags":[
        "acupuncture"
    ],
    "wof:name":"Holistic Body Health Care Clinic",
    "wof:placetype":"venue"
},
  "geometry": {"coordinates":[145.18864440900001,-37.9080657959],"type":"Point"}
}