{
  "type": "Feature",
  "properties": {
    "addr:full":"2/ 777 South Dowling St Redfern NSW 2016",
    "addr:housenumber":"/ 777",
    "addr:postcode":"2016",
    "addr:street":"South Dowling St",
    "iso:country":"AU",
    "sg:address":"2/ 777 South Dowling St",
    "sg:city":"Redfern",
    "sg:classifiers":[
        {
            "category":"Banks & Credit Unions",
            "subcategory":"Financial Services",
            "type":"Services"
        }
    ],
    "sg:phone":"+61 2 9319 3213",
    "sg:postcode":"2016",
    "sg:province":"NSW",
    "sg:tags":[
        "franchising"
    ],
    "wof:name":"Franchise & Business Promoters",
    "wof:placetype":"venue"
},
  "geometry": {"coordinates":[151.21595764200001,-33.8952407837],"type":"Point"}
}