{
  "type": "Feature",
  "properties": {
    "iso:country":"AU",
    "sg:address":"21 Wimmera St",
    "sg:city":"Mt Gambier",
    "sg:classifiers":[
        {
            "category":"Education",
            "subcategory":"Kindergarten",
            "type":"Public Place"
        }
    ],
    "sg:phone":"+61 8 8725 7373",
    "sg:postcode":"5290",
    "sg:province":"SA",
    "sg:tags":[
        "pre-schools"
    ],
    "wof:name":"Acacia Kindergarten",
    "wof:placetype":"venue"
},
  "geometry": {"coordinates":[140.77694700000001,-37.817619],"type":"Point"}
}