{
  "type": "Feature",
  "properties": {
    "iso:country":"AU",
    "sg:address":"36 baker St",
    "sg:city":"Toowoomba",
    "sg:classifiers":[
        {
            "category":"Social Services",
            "subcategory":"Child Care",
            "type":"Services"
        }
    ],
    "sg:phone":"+61 7 4630 1359",
    "sg:postcode":"4350",
    "sg:province":"QLD",
    "wof:name":"Garndoo Jarowair Child Care Training & Resource Unit",
    "wof:placetype":"venue"
},
  "geometry": {"coordinates":[151.92489599999999,-27.598755],"type":"Point"}
}