{
  "type": "Feature",
  "properties": {
    "iso:country":"AU",
    "sg:address":"4 / 410 Stuart Hwy",
    "sg:city":"Winnellie",
    "sg:classifiers":[
        {
            "category":"Utilities",
            "subcategory":"Electric",
            "type":"Services"
        }
    ],
    "sg:phone":"+61 8 8947 7022",
    "sg:postcode":"0820",
    "sg:province":"NT",
    "sg:tags":[
        "electrical",
        "contractor"
    ],
    "wof:name":"A.E.Solutions",
    "wof:placetype":"venue"
},
  "geometry": {"coordinates":[130.875686645,-12.4254217148],"type":"Point"}
}