{
  "type": "Feature",
  "properties": {
    "addr:full":"175 Shepherdson Rd Parafield Gardens SA 5107",
    "addr:housenumber":"175",
    "addr:postcode":"5107",
    "addr:street":"Shepherdson Rd",
    "iso:country":"AU",
    "sg:address":"175 Shepherdson Rd",
    "sg:city":"Parafield Gardens",
    "sg:classifiers":[
        {
            "category":"Personal",
            "subcategory":"Massage",
            "type":"Services"
        }
    ],
    "sg:phone":"+61 8 8281 1042",
    "sg:postcode":"5107",
    "sg:province":"SA",
    "sg:tags":[
        "therapy"
    ],
    "wof:name":"Prime Health Massage",
    "wof:placetype":"venue"
},
  "geometry": {"coordinates":[138.602386475,-34.7780723572],"type":"Point"}
}