{
  "type": "Feature",
  "properties": {
    "iso:country":"AU",
    "sg:address":"1 Borella Rd",
    "sg:city":"Sunnybank Hills",
    "sg:classifiers":[
        {
            "category":"Government",
            "subcategory":"Customs House",
            "type":"Public Place"
        }
    ],
    "sg:phone":"+61 7 3273 6345",
    "sg:postcode":"4109",
    "sg:province":"QLD",
    "sg:tags":[
        "title",
        "management",
        "stratum"
    ],
    "wof:name":"Brisdon Body Corporate Service",
    "wof:placetype":"venue"
},
  "geometry": {"coordinates":[153.05343627900001,-27.5986442566],"type":"Point"}
}