{
  "type": "Feature",
  "properties": {
    "iso:country":"AU",
    "sg:address":"14 Norfolk Ave",
    "sg:city":"Grovedale",
    "sg:classifiers":[
        {
            "category":"Education",
            "subcategory":"Music School",
            "type":"Public Place"
        }
    ],
    "sg:phone":"+61 3 5243 5590",
    "sg:postcode":"3216",
    "sg:province":"VIC",
    "sg:tags":[
        "choir",
        "bands",
        "orchestra"
    ],
    "wof:name":"Amabile String Quartet",
    "wof:placetype":"venue"
},
  "geometry": {"coordinates":[144.32771301299999,-38.2030181885],"type":"Point"}
}