{
  "type": "Feature",
  "properties": {
    "addr:full":"26 Chelford St Alderley QLD 4051",
    "addr:housenumber":"26",
    "addr:postcode":"4051",
    "addr:street":"Chelford St",
    "iso:country":"AU",
    "sg:address":"26 Chelford St",
    "sg:city":"Alderley",
    "sg:classifiers":[
        {
            "category":"Education",
            "subcategory":"Dance Studio",
            "type":"Public Place"
        }
    ],
    "sg:phone":"+61 7 3356 5182",
    "sg:postcode":"4051",
    "sg:province":"QLD",
    "sg:tags":[
        "venue",
        "tuition"
    ],
    "wof:name":"Vaughan Williams-Horn School Of Dance",
    "wof:placetype":"venue"
},
  "geometry": {"coordinates":[153.00627136200001,-27.4198074341],"type":"Point"}
}