{
  "type": "Feature",
  "properties": {
    "addr:full":"Unit 3, 1 Blaxland Rd Campbelltown NSW 2560",
    "addr:housenumber":"1",
    "addr:postcode":"2560",
    "addr:street":"Blaxland Rd",
    "iso:country":"AU",
    "sg:address":"Unit 3, 1 Blaxland Rd",
    "sg:city":"Campbelltown",
    "sg:classifiers":[
        {
            "category":"Retail",
            "subcategory":"Auto Repair",
            "type":"Services"
        }
    ],
    "sg:phone":"+61 2 4625 9081",
    "sg:postcode":"2560",
    "sg:province":"NSW",
    "sg:tags":[
        "beater",
        "painter",
        "panel"
    ],
    "wof:name":"Re-Nu Smash Repairs",
    "wof:placetype":"venue"
},
  "geometry": {"coordinates":[150.81820678700001,-34.056312561],"type":"Point"}
}