{
  "type": "Feature",
  "properties": {
    "addr:full":"Unit 1/ 34 Garner Pl Ingleburn NSW 2565",
    "addr:housenumber":"34",
    "addr:postcode":"nsw 2565",
    "addr:street":"Pl",
    "iso:country":"AU",
    "sg:address":"Unit 1/ 34 Garner Pl",
    "sg:city":"Ingleburn",
    "sg:classifiers":[
        {
            "category":"Retail",
            "subcategory":"Auto Repair",
            "type":"Services"
        }
    ],
    "sg:phone":"+61 2 9618 7779",
    "sg:postcode":"2565",
    "sg:province":"NSW",
    "sg:tags":[
        "bus",
        "truck"
    ],
    "wof:name":"Regents Park Truck Align",
    "wof:placetype":"venue"
},
  "geometry": {"coordinates":[150.86781310999999,-33.9865493774],"type":"Point"}
}