{
  "type": "Feature",
  "properties": {
    "addr:full":"15 Tyrrell St Mont Albert North VIC 3129",
    "addr:housenumber":"15",
    "addr:postcode":"3129",
    "addr:street":"Tyrrell St",
    "iso:country":"AU",
    "sg:address":"15 Tyrrell St",
    "sg:city":"Mont Albert North",
    "sg:classifiers":[
        {
            "category":"Health Services",
            "subcategory":"Health Practitioner",
            "type":"Services"
        }
    ],
    "sg:phone":"+61 3 9898 4907",
    "sg:postcode":"3129",
    "sg:province":"VIC",
    "sg:tags":[
        "hypnotherapy"
    ],
    "wof:name":"Russell Neill",
    "wof:placetype":"venue"
},
  "geometry": {"coordinates":[145.11227417000001,-37.8048324585],"type":"Point"}
}