{
  "type": "Feature",
  "properties": {
    "addr:full":"Suite 4 1757 Pittwater Rd Mona Vale NSW 2103",
    "addr:housenumber":"1757",
    "addr:postcode":"2103",
    "addr:street":"Pittwater Rd",
    "iso:country":"AU",
    "sg:address":"Suite 4 1757 Pittwater Rd",
    "sg:city":"Mona Vale",
    "sg:classifiers":[
        {
            "category":"Communications",
            "subcategory":"Television Station",
            "type":"Services"
        }
    ],
    "sg:phone":"+61 500 800 303",
    "sg:postcode":"2103",
    "sg:province":"NSW",
    "sg:tags":[
        "equipment",
        "laser"
    ],
    "wof:name":"Beamshot Australia",
    "wof:placetype":"venue"
},
  "geometry": {"coordinates":[151.30364990199999,-33.6776046753],"type":"Point"}
}