{
  "type": "Feature",
  "properties": {
    "addr:full":"Lvl 3/ 333 King William St Adelaide SA 5000",
    "addr:housenumber":"/ 333",
    "addr:postcode":"5000",
    "addr:street":"King William St",
    "iso:country":"AU",
    "sg:address":"Lvl 3/ 333 King William St",
    "sg:city":"Adelaide",
    "sg:classifiers":[
        {
            "category":"Banks & Credit Unions",
            "subcategory":"Financial Services",
            "type":"Services"
        }
    ],
    "sg:phone":"+61 8 8216 4141",
    "sg:postcode":"5000",
    "sg:province":"SA",
    "sg:tags":[
        "loan",
        "finance",
        "mortgage"
    ],
    "wof:name":"Golden Gate Funding",
    "wof:placetype":"venue"
},
  "geometry": {"coordinates":[138.59996032699999,-34.9320755005],"type":"Point"}
}