{
  "type": "Feature",
  "properties": {
    "addr:full":"17 Torquay Rd Pialba QLD 4655",
    "addr:housenumber":"17",
    "addr:postcode":"4655",
    "addr:street":"Torquay Rd",
    "iso:country":"AU",
    "sg:address":"17 Torquay Rd",
    "sg:city":"Pialba",
    "sg:classifiers":[
        {
            "category":"Health Services",
            "subcategory":"Dentist",
            "type":"Services"
        }
    ],
    "sg:phone":"+61 7 4124 1671",
    "sg:postcode":"4655",
    "sg:province":"QLD",
    "wof:name":"Pearly Whites Dental Services",
    "wof:placetype":"venue"
},
  "geometry": {"coordinates":[152.841599,-25.2822],"type":"Point"}
}