{
  "type": "Feature",
  "properties": {
    "addr:full":"39 Smeeton Rd Londonderry NSW 2753",
    "addr:housenumber":"39",
    "addr:postcode":"2753",
    "addr:street":"Smeeton Rd",
    "iso:country":"AU",
    "sg:address":"39 Smeeton Rd",
    "sg:city":"Londonderry",
    "sg:classifiers":[
        {
            "category":"Transit Center",
            "subcategory":"Freight",
            "type":"Transportation"
        }
    ],
    "sg:phone":"+61 2 4777 5330",
    "sg:postcode":"2753",
    "sg:province":"NSW",
    "sg:tags":[
        "forklift",
        "truck"
    ],
    "wof:name":"Arrow Forklift Services Pty Ltd",
    "wof:placetype":"venue"
},
  "geometry": {"coordinates":[150.726364136,-33.6826553345],"type":"Point"}
}