{
  "type": "Feature",
  "properties": {
    "addr:full":"91 Howick St South Launceston TAS 7249",
    "addr:housenumber":"91",
    "addr:postcode":"7249",
    "addr:street":"Howick St",
    "iso:country":"AU",
    "sg:address":"91 Howick St",
    "sg:city":"South Launceston",
    "sg:classifiers":[
        {
            "category":"Government",
            "subcategory":"Department Of Motor Vehicles",
            "type":"Public Place"
        }
    ],
    "sg:phone":"+61 3 6344 8222",
    "sg:postcode":"7249",
    "sg:province":"TAS",
    "sg:tags":[
        "wholesaler",
        "mfrs",
        "accessory"
    ],
    "wof:name":"Ingram Corporation Pty Ltd",
    "wof:placetype":"venue"
},
  "geometry": {"coordinates":[147.140914917,-41.449180603],"type":"Point"}
}