{
  "type": "Feature",
  "properties": {
    "addr:full":"27 Healey Rd Dandenong VIC 3175",
    "addr:housenumber":"27",
    "addr:postcode":"3175",
    "addr:street":"Healey Rd",
    "iso:country":"AU",
    "sg:address":"27 Healey Rd",
    "sg:city":"Dandenong",
    "sg:classifiers":[
        {
            "category":"Industrial Area",
            "type":"Public Place"
        }
    ],
    "sg:phone":"+61 3 9706 4913",
    "sg:postcode":"3175",
    "sg:province":"VIC",
    "sg:tags":[
        "consulting",
        "chemist"
    ],
    "wof:name":"Sypharma Pty Ltd",
    "wof:placetype":"venue"
},
  "geometry": {"coordinates":[145.22598266599999,-38.0294418335],"type":"Point"}
}