{
  "type": "Feature",
  "properties": {
    "addr:full":"64 Buckingham St Richmond VIC 3121",
    "addr:housenumber":"64",
    "addr:postcode":"3121",
    "addr:street":"Buckingham St",
    "iso:country":"AU",
    "sg:address":"64 Buckingham St",
    "sg:city":"Richmond",
    "sg:classifiers":[
        {
            "category":"Building & Trades",
            "subcategory":"Construction",
            "type":"Services"
        }
    ],
    "sg:phone":"+61 419 444 033",
    "sg:postcode":"3121",
    "sg:province":"VIC",
    "sg:tags":[
        "joiner",
        "carpenter"
    ],
    "wof:name":"Ability Carpenters",
    "wof:placetype":"venue"
},
  "geometry": {"coordinates":[145.00318908700001,-37.8140258789],"type":"Point"}
}