{
  "type": "Feature",
  "properties": {
    "iso:country":"AU",
    "sg:address":"7 Grose St",
    "sg:city":"Leura",
    "sg:classifiers":[
        {
            "category":"Health Services",
            "subcategory":"Health Practitioner",
            "type":"Services"
        }
    ],
    "sg:phone":"+61 2 4784 3993",
    "sg:postcode":"2780",
    "sg:province":"NSW",
    "sg:tags":[
        "physiotherapist"
    ],
    "wof:name":"Blue Mountains Physiotherapy Centre",
    "wof:placetype":"venue"
},
  "geometry": {"coordinates":[150.33299255399999,-33.7127876282],"type":"Point"}
}