{
  "type": "Feature",
  "properties": {
    "iso:country":"AU",
    "sg:address":"Factory 4, 50 Export Drv",
    "sg:city":"Ernest",
    "sg:classifiers":[
        {
            "category":"Landmark",
            "subcategory":"Scenic View",
            "type":"Public Place"
        }
    ],
    "sg:phone":"+61 416 939 979",
    "sg:postcode":"4214",
    "sg:province":"QLD",
    "sg:tags":[
        "staircase",
        "handrail"
    ],
    "wof:name":"All Coast Stairs & Balustrading Pty Ltd",
    "wof:placetype":"venue"
},
  "geometry": {"coordinates":[153.36021423299999,-27.9665241241],"type":"Point"}
}