{
  "type": "Feature",
  "properties": {
    "addr:full":"73 Orrong Crs Caulfield North VIC 3161",
    "addr:housenumber":"73",
    "addr:postcode":"3161",
    "addr:street":"Orrong Crs",
    "iso:country":"AU",
    "sg:address":"73 Orrong Crs",
    "sg:city":"Caulfield North",
    "sg:classifiers":[
        {
            "category":"Home & Garden",
            "subcategory":"Building Materials",
            "type":"Retail Goods"
        }
    ],
    "sg:phone":"+61 3 9527 7615",
    "sg:postcode":"3161",
    "sg:province":"VIC",
    "sg:tags":[
        "merchant",
        "glass",
        "glazier"
    ],
    "wof:name":"Prahran Glass",
    "wof:placetype":"venue"
},
  "geometry": {"coordinates":[145.00932312,-37.8667602539],"type":"Point"}
}