{
  "type": "Feature",
  "properties": {
    "addr:full":"29 Daisy Ave Pioneer Bay VIC 3984",
    "addr:housenumber":"29",
    "addr:postcode":"3984",
    "addr:street":"Daisy Ave Pioneer",
    "iso:country":"AU",
    "sg:address":"29 Daisy Ave",
    "sg:city":"Pioneer Bay",
    "sg:classifiers":[
        {
            "category":"Education",
            "subcategory":"Music School",
            "type":"Public Place"
        }
    ],
    "sg:phone":"+61 3 5997 6265",
    "sg:postcode":"3984",
    "sg:province":"VIC",
    "sg:tags":[
        "teacher"
    ],
    "wof:name":"Island View Music School",
    "wof:placetype":"venue"
},
  "geometry": {"coordinates":[145.549072266,-38.3804397583],"type":"Point"}
}