{
  "type": "Feature",
  "properties": {
    "addr:full":"PO Box 56 Doncaster East VIC 3109",
    "addr:postcode":"3109",
    "iso:country":"AU",
    "sg:address":"PO Box 56",
    "sg:city":"Doncaster East",
    "sg:classifiers":[
        {
            "category":"Building & Trades",
            "subcategory":"Construction",
            "type":"Services"
        }
    ],
    "sg:phone":"+61 430 116 600",
    "sg:postcode":"3109",
    "sg:province":"VIC",
    "sg:tags":[
        "renovation",
        "alterations",
        "extension",
        "contractor"
    ],
    "wof:name":"Apple Professional Services",
    "wof:placetype":"venue"
},
  "geometry": {"coordinates":[145.16328430199999,-37.7757987976],"type":"Point"}
}