{
  "type": "Feature",
  "properties": {
    "addr:full":"155 Hale Rd Forrestfield WA 6058",
    "addr:housenumber":"155",
    "addr:postcode":"6058",
    "addr:street":"Hale Rd",
    "iso:country":"AU",
    "sg:address":"155 Hale Rd",
    "sg:city":"Forrestfield",
    "sg:classifiers":[
        {
            "category":"Autos & Motor Vehicles",
            "subcategory":"Fuel & Gas Station",
            "type":"Retail Goods"
        }
    ],
    "sg:phone":"+61 8 9359 4503",
    "sg:postcode":"6058",
    "sg:province":"WA",
    "wof:name":"BP",
    "wof:placetype":"venue"
},
  "geometry": {"coordinates":[115.993423462,-31.9953956604],"type":"Point"}
}