{
  "type": "Feature",
  "properties": {
    "addr:full":"Door 5, Conquest Drv Hallam VIC 3803",
    "addr:postcode":"3803",
    "addr:street":"Conquest Drv",
    "iso:country":"AU",
    "sg:address":"Door 5, Conquest Drv",
    "sg:city":"Hallam",
    "sg:classifiers":[
        {
            "category":"Home & Garden",
            "subcategory":"Hardware",
            "type":"Retail Goods"
        }
    ],
    "sg:phone":"+61 3 9350 4495",
    "sg:postcode":"3803",
    "sg:province":"VIC",
    "sg:tags":[
        "plumber",
        "supply"
    ],
    "wof:name":"Reece Onsite Hallam",
    "wof:placetype":"venue"
},
  "geometry": {"coordinates":[145.254394531,-38.0109405518],"type":"Point"}
}