{
  "type": "Feature",
  "properties": {
    "addr:full":"56G Patrick St Dalby QLD 4405",
    "addr:housenumber":"56g",
    "addr:postcode":"4405",
    "addr:street":"Patrick St",
    "iso:country":"AU",
    "sg:address":"56G Patrick St",
    "sg:city":"Dalby",
    "sg:classifiers":[
        {
            "category":"Personal",
            "subcategory":"Shoe Repair & Shine",
            "type":"Services"
        }
    ],
    "sg:phone":"+61 7 4662 5501",
    "sg:postcode":"4405",
    "sg:province":"QLD",
    "sg:tags":[
        "footwear"
    ],
    "wof:name":"Bazs Quality Shoe Repair",
    "wof:placetype":"venue"
},
  "geometry": {"coordinates":[151.26177978499999,-27.1766452789],"type":"Point"}
}