{
  "type": "Feature",
  "properties": {
    "addr:full":"36 Assembly Drv Tullamarine VIC 3043",
    "addr:housenumber":"36",
    "addr:postcode":"3043",
    "addr:street":"Assembly Drv",
    "iso:country":"AU",
    "sg:address":"36 Assembly Drv",
    "sg:city":"Tullamarine",
    "sg:classifiers":[
        {
            "category":"Transit Center",
            "subcategory":"Freight",
            "type":"Transportation"
        }
    ],
    "sg:phone":"+61 3 9335 1027",
    "sg:postcode":"3043",
    "sg:province":"VIC",
    "sg:tags":[
        "agent",
        "shipping"
    ],
    "wof:name":"Export Consolidation Services",
    "wof:placetype":"venue"
},
  "geometry": {"coordinates":[144.863723755,-37.7082290649],"type":"Point"}
}