{
  "type": "Feature",
  "properties": {
    "iso:country":"AU",
    "sg:address":"Level 5",
    "sg:city":", Bellerive Qy Bellerive",
    "sg:classifiers":[
        {
            "category":"Education",
            "subcategory":"Special Training",
            "type":"Public Place"
        }
    ],
    "sg:phone":"+61 1300 796 244",
    "sg:postcode":"7018",
    "sg:province":"TAS",
    "sg:tags":[
        "development"
    ],
    "wof:name":"Productivity Plus Tasmania",
    "wof:placetype":"venue"
},
  "geometry": {"coordinates":[147.4090271,-42.8923530579],"type":"Point"}
}