{
  "type": "Feature",
  "properties": {
    "addr:full":"PO Box 167 Banora Point NSW 2486",
    "addr:postcode":"2486",
    "iso:country":"AU",
    "sg:address":"PO Box 167",
    "sg:city":"Banora Point",
    "sg:classifiers":[
        {
            "category":"Building & Trades",
            "subcategory":"Construction",
            "type":"Services"
        }
    ],
    "sg:phone":"+61 417 646 538",
    "sg:postcode":"2486",
    "sg:province":"NSW",
    "sg:tags":[
        "contractor"
    ],
    "wof:name":"Bonnor Errol",
    "wof:placetype":"venue"
},
  "geometry": {"coordinates":[153.54563903799999,-28.2131099701],"type":"Point"}
}