{
  "type": "Feature",
  "properties": {
    "iso:country":"AU",
    "sg:address":"3 Cross St",
    "sg:city":"Footscray",
    "sg:classifiers":[
        {
            "category":"Home & Garden",
            "subcategory":"Household Appliances",
            "type":"Retail Goods"
        }
    ],
    "sg:phone":"+61 3 9687 8933",
    "sg:postcode":"3011",
    "sg:province":"VIC",
    "sg:tags":[
        "heating",
        "system"
    ],
    "wof:name":"Australian Induction Heating Co. Pty Ltd.",
    "wof:placetype":"venue"
},
  "geometry": {"coordinates":[144.88829040499999,-37.801776886],"type":"Point"}
}