{
  "type": "Feature",
  "properties": {
    "addr:full":"Cnr Bath St & Gregory Tce Alice Springs NT 0870",
    "addr:postcode":"nt 0870",
    "addr:street":"Cnr Bath St & Gregory Tce",
    "iso:country":"AU",
    "sg:address":"Cnr Bath St",
    "sg:city":"& Gregory Tce Alice Springs",
    "sg:classifiers":[
        {
            "category":"Wholesale",
            "subcategory":"Medical Equipment & Supplies",
            "type":"Manufacturing & Wholesale Goods"
        }
    ],
    "sg:phone":"+61 8 8953 3282",
    "sg:postcode":"0870",
    "sg:province":"NT",
    "sg:tags":[
        "aids",
        "hearing"
    ],
    "wof:name":"Australian Hearing",
    "wof:placetype":"venue"
},
  "geometry": {"coordinates":[133.87852477999999,-23.7023410797],"type":"Point"}
}