{
  "type": "Feature",
  "properties": {
    "iso:country":"AU",
    "sg:address":"Shop 15",
    "sg:city":"Diamond Creek Plz Diamond Creek",
    "sg:classifiers":[
        {
            "category":"Health Services",
            "subcategory":"Optometrist",
            "type":"Services"
        }
    ],
    "sg:phone":"+61 3 9438 3286",
    "sg:postcode":"3089",
    "sg:province":"VIC",
    "wof:name":"Diamond Valley Optical",
    "wof:placetype":"venue"
},
  "geometry": {"coordinates":[145.146072,-37.675117],"type":"Point"}
}