{
  "type": "Feature",
  "properties": {
    "addr:full":"57 Maloga Rd Heidelberg West VIC 3081",
    "addr:housenumber":"57",
    "addr:postcode":"3081",
    "addr:street":"Maloga Rd",
    "iso:country":"AU",
    "sg:address":"57 Maloga Rd",
    "sg:city":"Heidelberg West",
    "sg:classifiers":[
        {
            "category":"Retail",
            "subcategory":"Storage",
            "type":"Services"
        }
    ],
    "sg:phone":"+61 1800 819 948",
    "sg:postcode":"3081",
    "sg:province":"VIC",
    "sg:tags":[
        "removal",
        "furniture"
    ],
    "wof:name":"Alcatraz Storage & Removals",
    "wof:placetype":"venue"
},
  "geometry": {"coordinates":[145.045944214,-37.7330551147],"type":"Point"}
}