{
  "type": "Feature",
  "properties": {
    "iso:country":"AU",
    "sg:address":"U18/ 90 The Grand Pde",
    "sg:city":"Brighton-le-Sands",
    "sg:classifiers":[
        {
            "category":"Professional",
            "subcategory":"Business Services",
            "type":"Services"
        }
    ],
    "sg:phone":"+61 2 9567 7373",
    "sg:postcode":"2216",
    "sg:province":"NSW",
    "sg:tags":[
        "exporter"
    ],
    "wof:name":"Gallipoli Trade Gateway",
    "wof:placetype":"venue"
},
  "geometry": {"coordinates":[151.155655,-33.961926],"type":"Point"}
}