{
  "type": "Feature",
  "properties": {
    "iso:country":"AU",
    "sg:address":"24 Church St",
    "sg:city":"Beerburrum",
    "sg:classifiers":[
        {
            "category":"Autos & Motor Vehicles",
            "subcategory":"Boat Sales",
            "type":"Retail Goods"
        }
    ],
    "sg:phone":"+61 7 5496 0504",
    "sg:postcode":"4517",
    "sg:province":"QLD",
    "sg:tags":[
        "equipment",
        "yacht"
    ],
    "wof:name":"Sunshine Coast Boat Lifts Pty Ltd",
    "wof:placetype":"venue"
},
  "geometry": {"coordinates":[152.958054,-26.960064],"type":"Point"}
}