{
  "type": "Feature",
  "properties": {
    "addr:full":"625 Marsh Rd Bobs Farm NSW 2316",
    "addr:housenumber":"625",
    "addr:postcode":"2316",
    "addr:street":"Marsh Rd",
    "iso:country":"AU",
    "sg:address":"625 Marsh Rd",
    "sg:city":"Bobs Farm",
    "sg:classifiers":[
        {
            "category":"Home & Garden",
            "subcategory":"Building Materials",
            "type":"Retail Goods"
        }
    ],
    "sg:phone":"+61 2 4982 6690",
    "sg:postcode":"2316",
    "sg:province":"NSW",
    "sg:tags":[
        "merchant",
        "glass",
        "glazier"
    ],
    "wof:name":"Deco Glaze",
    "wof:placetype":"venue"
},
  "geometry": {"coordinates":[151.99693300000001,-32.768341],"type":"Point"}
}