{
  "type": "Feature",
  "properties": {
    "addr:full":"Chinner St Melba ACT 2615",
    "addr:postcode":"2615",
    "addr:street":"St",
    "iso:country":"AU",
    "sg:address":"Chinner St",
    "sg:city":"Melba",
    "sg:classifiers":[
        {
            "category":"Food & Beverages",
            "subcategory":"Liquor & Beverages",
            "type":"Retail Goods"
        }
    ],
    "sg:phone":"+61 2 6258 1336",
    "sg:postcode":"2615",
    "sg:province":"ACT",
    "sg:tags":[
        "store"
    ],
    "wof:name":"Local Liquor",
    "wof:placetype":"venue"
},
  "geometry": {"coordinates":[149.04930114699999,-35.2100372314],"type":"Point"}
}