{
  "type": "Feature",
  "properties": {
    "addr:full":"Stoney Creek Rd Kimbriki NSW 2429",
    "addr:postcode":"2429",
    "addr:street":"Stoney Creek Rd",
    "iso:country":"AU",
    "sg:address":"Stoney Creek Rd",
    "sg:city":"Kimbriki",
    "sg:classifiers":[
        {
            "category":"Farming",
            "subcategory":"Livestock Farm",
            "type":"Manufacturing & Wholesale Goods"
        }
    ],
    "sg:phone":"+61 2 6550 6341",
    "sg:postcode":"2429",
    "sg:province":"NSW",
    "sg:tags":[
        "breeder",
        "horse",
        "stud"
    ],
    "wof:name":"Dale G Training Stables",
    "wof:placetype":"venue"
},
  "geometry": {"coordinates":[152.261078,-31.919889],"type":"Point"}
}