{
  "type": "Feature",
  "properties": {
    "addr:full":"Mortdale Heritage Medical Centre 23 a Morts Rd Mortdale NSW 2223",
    "addr:housenumber":"23",
    "addr:postcode":"2223",
    "addr:street":"Morts Rd",
    "iso:country":"AU",
    "sg:address":"Mortdale Heritage Medical Centre 23 a Morts Rd",
    "sg:city":"Mortdale",
    "sg:classifiers":[
        {
            "category":"Health Services",
            "subcategory":"Doctor",
            "type":"Services"
        }
    ],
    "sg:phone":"+61 2 9579 5733",
    "sg:postcode":"2223",
    "sg:province":"NSW",
    "sg:tags":[
        "medical",
        "practitioner"
    ],
    "wof:name":"Ong T",
    "wof:placetype":"venue"
},
  "geometry": {"coordinates":[151.07974243199999,-33.9700927734],"type":"Point"}
}