{
  "type": "Feature",
  "properties": {
    "addr:full":"Range Shopping Centre James St Toowoomba QLD 4350",
    "addr:postcode":"4350",
    "addr:street":"James St",
    "iso:country":"AU",
    "sg:address":"Range Shopping Centre James St",
    "sg:city":"Toowoomba",
    "sg:classifiers":[
        {
            "category":"Food & Beverages",
            "subcategory":"Bakery",
            "type":"Retail Goods"
        }
    ],
    "sg:phone":"+61 7 4638 9100",
    "sg:postcode":"4350",
    "sg:province":"QLD",
    "sg:tags":[
        "cake",
        "shop",
        "pastry"
    ],
    "wof:name":"Windmill Bakery",
    "wof:placetype":"venue"
},
  "geometry": {"coordinates":[151.92970299999999,-27.565884],"type":"Point"}
}