{
  "type": "Feature",
  "properties": {
    "addr:full":"1470 Loves La Dumbalk VIC 3956",
    "addr:postcode":"1470;3956",
    "addr:street":"Loves La Dumbalk",
    "iso:country":"AU",
    "sg:address":"1470 Loves La",
    "sg:city":"Dumbalk",
    "sg:classifiers":[
        {
            "category":"Utilities",
            "subcategory":"Electric",
            "type":"Services"
        }
    ],
    "sg:phone":"+61 427 343 851",
    "sg:postcode":"3956",
    "sg:province":"VIC",
    "sg:tags":[
        "electrical",
        "contractor"
    ],
    "wof:name":"Strzelectrics",
    "wof:placetype":"venue"
},
  "geometry": {"coordinates":[146.09501648,-38.5316314697],"type":"Point"}
}