{
  "type": "Feature",
  "properties": {
    "iso:country":"AU",
    "sg:address":"14 Robinson St",
    "sg:city":"Subiaco",
    "sg:classifiers":[
        {
            "category":"Professional",
            "subcategory":"Art Services",
            "type":"Services"
        }
    ],
    "sg:phone":"+61 412 852 334",
    "sg:postcode":"6008",
    "sg:province":"WA",
    "sg:tags":[
        "graphic",
        "designer"
    ],
    "wof:name":"Softspace",
    "wof:placetype":"venue"
},
  "geometry": {"coordinates":[115.826889038,-31.9510746002],"type":"Point"}
}