{
  "type": "Feature",
  "properties": {
    "addr:full":"5 Phillips Ave West Wollongong NSW 2500",
    "addr:housenumber":"5",
    "addr:postcode":"2500",
    "addr:street":"Phillips Ave West",
    "iso:country":"AU",
    "sg:address":"5 Phillips Ave",
    "sg:city":"West Wollongong",
    "sg:classifiers":[
        {
            "category":"Health Services",
            "subcategory":"Health Practitioner",
            "type":"Services"
        }
    ],
    "sg:phone":"+61 2 4228 7769",
    "sg:postcode":"2500",
    "sg:province":"NSW",
    "sg:tags":[
        "dietitian"
    ],
    "wof:name":"Complete Care Consultancy Centre",
    "wof:placetype":"venue"
},
  "geometry": {"coordinates":[150.88124099999999,-34.425922],"type":"Point"}
}