{
  "type": "Feature",
  "properties": {
    "addr:full":"4 Lawnhill Rd Malvern VIC 3144",
    "addr:housenumber":"4",
    "addr:postcode":"3144",
    "addr:street":"Lawnhill Rd",
    "iso:country":"AU",
    "sg:address":"4 Lawnhill Rd",
    "sg:city":"Malvern",
    "sg:classifiers":[
        {
            "category":"Real Estate",
            "subcategory":"Real Estate Agent",
            "type":"Services"
        }
    ],
    "sg:phone":"+61 418 336 234",
    "sg:postcode":"3144",
    "sg:province":"VIC",
    "wof:name":"Tomlinson Rae",
    "wof:placetype":"venue"
},
  "geometry": {"coordinates":[145.03623962399999,-37.847114563],"type":"Point"}
}