{
  "type": "Feature",
  "properties": {
    "addr:full":"2 Kenneth St Thomastown VIC 3074",
    "addr:housenumber":"2",
    "addr:postcode":"3074",
    "addr:street":"Kenneth St",
    "iso:country":"AU",
    "sg:address":"2 Kenneth St",
    "sg:city":"Thomastown",
    "sg:classifiers":[
        {
            "category":"Wholesale",
            "subcategory":"Furniture",
            "type":"Manufacturing & Wholesale Goods"
        }
    ],
    "sg:phone":"+61 3 9462 2933",
    "sg:postcode":"3074",
    "sg:province":"VIC",
    "sg:tags":[
        "wholesaler",
        "mfrs"
    ],
    "wof:name":"Divans Fine Furniture",
    "wof:placetype":"venue"
},
  "geometry": {"coordinates":[145.004837036,-37.6883010864],"type":"Point"}
}