{
  "type": "Feature",
  "properties": {
    "addr:full":"3/ 6 Bergen Way Mindarie WA 6030",
    "addr:housenumber":"/ 6",
    "addr:postcode":"6030",
    "addr:street":"Bergen Way",
    "iso:country":"AU",
    "sg:address":"3/ 6 Bergen Way",
    "sg:city":"Mindarie",
    "sg:classifiers":[
        {
            "category":"Personal",
            "subcategory":"Beauty Salon",
            "type":"Services"
        }
    ],
    "sg:phone":"+61 8 9305 8077",
    "sg:postcode":"6030",
    "sg:province":"WA",
    "sg:tags":[
        "hairdresser"
    ],
    "wof:name":"Boo Hairdressing",
    "wof:placetype":"venue"
},
  "geometry": {"coordinates":[115.710838318,-31.6775588989],"type":"Point"}
}