{
  "type": "Feature",
  "properties": {
    "addr:full":"PO Box 223 Round Corner NSW 2158",
    "addr:postcode":"2158",
    "iso:country":"AU",
    "sg:address":"PO Box 223",
    "sg:city":"Round Corner",
    "sg:classifiers":[
        {
            "category":"Building & Trades",
            "subcategory":"Pest Control",
            "type":"Services"
        }
    ],
    "sg:phone":"+61 418 407 317",
    "sg:postcode":"2158",
    "sg:province":"NSW",
    "wof:name":"True Blue Yard N Garden Care",
    "wof:placetype":"venue"
},
  "geometry": {"coordinates":[151.01791381800001,-33.695098877],"type":"Point"}
}