{
  "type": "Feature",
  "properties": {
    "addr:full":"Suite 3 23 Louis St Airport West VIC 3042",
    "addr:housenumber":"23",
    "addr:postcode":"3042",
    "addr:street":"Louis St",
    "iso:country":"AU",
    "sg:address":"Suite 3 23 Louis St",
    "sg:city":"Airport West",
    "sg:classifiers":[
        {
            "category":"Health Services",
            "subcategory":"Dentist",
            "type":"Services"
        }
    ],
    "sg:phone":"+61 3 9330 2455",
    "sg:postcode":"3042",
    "sg:province":"VIC",
    "wof:name":"Hand Philip",
    "wof:placetype":"venue"
},
  "geometry": {"coordinates":[144.888305664,-37.7149581909],"type":"Point"}
}