{
  "type": "Feature",
  "properties": {
    "iso:country":"AU",
    "sg:address":"139 Claremont Crs",
    "sg:city":"Swanbourne",
    "sg:classifiers":[
        {
            "category":"Health Services",
            "subcategory":"Health Practitioner",
            "type":"Services"
        }
    ],
    "sg:phone":"+61 402 688 297",
    "sg:postcode":"6010",
    "sg:province":"WA",
    "sg:tags":[
        "psychologist"
    ],
    "wof:name":"Susan Hutchinson",
    "wof:placetype":"venue"
},
  "geometry": {"coordinates":[115.767486572,-31.9709300995],"type":"Point"}
}