{
  "type": "Feature",
  "properties": {
    "addr:full":"61 Taloombi St Cronulla NSW 2230",
    "addr:housenumber":"61",
    "addr:postcode":"2230",
    "addr:street":"Taloombi St",
    "iso:country":"AU",
    "sg:address":"61 Taloombi St",
    "sg:city":"Cronulla",
    "sg:classifiers":[
        {
            "category":"Utilities",
            "subcategory":"Water",
            "type":"Services"
        }
    ],
    "sg:phone":"+61 407 181 161",
    "sg:postcode":"2230",
    "sg:province":"NSW",
    "sg:tags":[
        "equipment",
        "treatment"
    ],
    "wof:name":"Waste Heat Energy Systems Technology",
    "wof:placetype":"venue"
},
  "geometry": {"coordinates":[151.14729309099999,-34.0637359619],"type":"Point"}
}