{
  "type": "Feature",
  "properties": {
    "iso:country":"AU",
    "sg:address":"157 Grenfell St",
    "sg:city":"Adelaide",
    "sg:classifiers":[
        {
            "category":"Professional",
            "subcategory":"Accounting & Tax Preparation",
            "type":"Services"
        }
    ],
    "sg:phone":"+61 8 8223 1468",
    "sg:postcode":"5000",
    "sg:province":"SA",
    "sg:tags":[
        "accountant",
        "auditor"
    ],
    "wof:name":"Graetz S P",
    "wof:placetype":"venue"
},
  "geometry": {"coordinates":[138.60699462900001,-34.9241333008],"type":"Point"}
}