{
  "type": "Feature",
  "properties": {
    "iso:country":"AU",
    "sg:address":"12 David St",
    "sg:city":"Lalor",
    "sg:classifiers":[
        {
            "category":"Health Services",
            "subcategory":"Chiropractor",
            "type":"Services"
        }
    ],
    "sg:phone":"+61 3 9464 3822",
    "sg:postcode":"3075",
    "sg:province":"VIC",
    "wof:name":"David Street Chiropractic",
    "wof:placetype":"venue"
},
  "geometry": {"coordinates":[144.945755005,-37.7088050842],"type":"Point"}
}