{
  "type": "Feature",
  "properties": {
    "addr:full":"107 - 109 Clarence St Sydney NSW 2001",
    "addr:housenumber":"109",
    "addr:postcode":"2001",
    "addr:street":"Clarence St",
    "iso:country":"AU",
    "sg:address":"107 - 109 Clarence St",
    "sg:city":"Sydney",
    "sg:classifiers":[
        {
            "category":"Travel",
            "subcategory":"Hotels & Motels",
            "type":"Entertainment"
        }
    ],
    "sg:phone":"+61 2 9299 1330",
    "sg:postcode":"2001",
    "sg:province":"NSW",
    "sg:tags":[
        "accommodation"
    ],
    "wof:name":"WYNYARD HOTEL",
    "wof:placetype":"venue"
},
  "geometry": {"coordinates":[151.20492553700001,-33.8668670654],"type":"Point"}
}