{
  "type": "Feature",
  "properties": {
    "addr:full":"46 Watt Rd Mornington VIC 3931",
    "addr:housenumber":"46",
    "addr:postcode":"3931",
    "addr:street":"Watt Rd",
    "iso:country":"AU",
    "sg:address":"46 Watt Rd",
    "sg:city":"Mornington",
    "sg:classifiers":[
        {
            "category":"Professional",
            "type":"Services"
        }
    ],
    "sg:phone":"+61 3 5975 4630",
    "sg:postcode":"3931",
    "sg:province":"VIC",
    "sg:tags":[
        "spray",
        "painting"
    ],
    "wof:name":"Johnny's Auto Repairs",
    "wof:placetype":"venue"
},
  "geometry": {"coordinates":[145.05348205600001,-38.2312660217],"type":"Point"}
}