{
  "type": "Feature",
  "properties": {
    "iso:country":"AU",
    "sg:address":"Shp 6/ 2 Parkridge Ave",
    "sg:city":"Upper Caboolture",
    "sg:classifiers":[
        {
            "category":"Personal",
            "subcategory":"Beauty Salon",
            "type":"Services"
        }
    ],
    "sg:phone":"+61 7 5428 3385",
    "sg:postcode":"4510",
    "sg:province":"QLD",
    "sg:tags":[
        "hairdresser"
    ],
    "wof:name":"Lee Lees Hair Salon",
    "wof:placetype":"venue"
},
  "geometry": {"coordinates":[152.91751099999999,-27.107172],"type":"Point"}
}