{
  "type": "Feature",
  "properties": {
    "addr:full":"115 Canterbury Rd Canterbury NSW 2193",
    "addr:housenumber":"115",
    "addr:postcode":"2193",
    "addr:street":"Canterbury Rd",
    "iso:country":"AU",
    "sg:address":"115 Canterbury Rd",
    "sg:city":"Canterbury",
    "sg:classifiers":[
        {
            "category":"Government",
            "subcategory":"Court House",
            "type":"Public Place"
        }
    ],
    "sg:phone":"+61 2 9789 6668",
    "sg:postcode":"2193",
    "sg:province":"NSW",
    "sg:tags":[
        "personal",
        "marriage",
        "family",
        "counselling"
    ],
    "wof:name":"SoulCare",
    "wof:placetype":"venue"
},
  "geometry": {"coordinates":[151.121307,-33.910568],"type":"Point"}
}