{
  "type": "Feature",
  "properties": {
    "addr:full":"1375, Main North Road Para Hills West SA 5096",
    "addr:housenumber":"1375",
    "addr:postcode":"5096",
    "addr:street":"Main North Road",
    "iso:country":"AU",
    "sg:address":"1375, Main North Road",
    "sg:city":"Para Hills West",
    "sg:classifiers":[
        {
            "category":"Manufacturing",
            "subcategory":"Motor Vehicles & Parts",
            "type":"Manufacturing & Wholesale Goods"
        }
    ],
    "sg:phone":"+61 1300 869 632",
    "sg:postcode":"5096",
    "sg:province":"SA",
    "sg:tags":[
        "replacement"
    ],
    "wof:name":"Paradise Auto Parts",
    "wof:placetype":"venue"
},
  "geometry": {"coordinates":[138.64129638700001,-34.7987365723],"type":"Point"}
}