{
  "type": "Feature",
  "properties": {
    "addr:full":"36 Baronia Crs Holloways Beach QLD 4878",
    "addr:housenumber":"36",
    "addr:postcode":"4878",
    "addr:street":"Baronia Crs",
    "iso:country":"AU",
    "sg:address":"36 Baronia Crs",
    "sg:city":"Holloways Beach",
    "sg:classifiers":[
        {
            "category":"Professional",
            "subcategory":"Business Services",
            "type":"Services"
        }
    ],
    "sg:phone":"+61 7 4055 0078",
    "sg:postcode":"4878",
    "sg:province":"QLD",
    "sg:tags":[
        "processing",
        "word"
    ],
    "wof:name":"Weston J A",
    "wof:placetype":"venue"
},
  "geometry": {"coordinates":[145.73991394000001,-16.8386592865],"type":"Point"}
}