{
  "type": "Feature",
  "properties": {
    "addr:full":"15 Kentucky Crt Kirwan QLD 4817",
    "addr:housenumber":"15",
    "addr:postcode":"4817",
    "addr:street":"Kentucky Crt",
    "iso:country":"AU",
    "sg:address":"15 Kentucky Crt",
    "sg:city":"Kirwan",
    "sg:classifiers":[
        {
            "category":"Travel",
            "subcategory":"Travel Agent",
            "type":"Entertainment"
        }
    ],
    "sg:phone":"+61 429 654 732",
    "sg:postcode":"4817",
    "sg:province":"QLD",
    "sg:tags":[
        "tour",
        "holiday",
        "adventure"
    ],
    "wof:name":"Authentic Bush Tours",
    "wof:placetype":"venue"
},
  "geometry": {"coordinates":[146.73980700000001,-19.302675],"type":"Point"}
}