{
  "type": "Feature",
  "properties": {
    "addr:full":"Lot 5 Mills Rd Axedale VIC 3551",
    "addr:housenumber":"5",
    "addr:postcode":"3551",
    "addr:street":"Mills Rd",
    "iso:country":"AU",
    "sg:address":"Lot 5 Mills Rd",
    "sg:city":"Axedale",
    "sg:classifiers":[
        {
            "category":"Farming",
            "subcategory":"Livestock Farm",
            "type":"Manufacturing & Wholesale Goods"
        }
    ],
    "sg:phone":"+61 3 5439 7251",
    "sg:postcode":"3551",
    "sg:province":"VIC",
    "sg:tags":[
        "breeder",
        "horse",
        "stud"
    ],
    "wof:name":"International Horse Breeders",
    "wof:placetype":"venue"
},
  "geometry": {"coordinates":[144.48478698700001,-36.810710907],"type":"Point"}
}