{
  "type": "Feature",
  "properties": {
    "iso:country":"AU",
    "sg:address":"PO Box 39",
    "sg:city":"Rundle Mall P O",
    "sg:classifiers":[
        {
            "category":"Organizations",
            "subcategory":"Community Association",
            "type":"Services"
        }
    ],
    "sg:phone":"+61 13 14 78",
    "sg:postcode":"5000",
    "sg:province":"SA",
    "sg:tags":[
        "organisation",
        "family",
        "welfare"
    ],
    "wof:name":"Child Abuse Report Line",
    "wof:placetype":"venue"
},
  "geometry": {"coordinates":[138.600097656,-34.9229545593],"type":"Point"}
}