{
  "type": "Feature",
  "properties": {
    "addr:full":"Suite 15 Level 3 / 38-40 , Urunga Parade Miranda NSW 2228",
    "addr:housenumber":"/ 38-40",
    "addr:postcode":"2228",
    "addr:street":"Urunga Parade Miranda",
    "iso:country":"AU",
    "sg:address":"Suite 15 Level 3 / 38-40 , Urunga Parade",
    "sg:city":"Miranda",
    "sg:classifiers":[
        {
            "category":"Health Services",
            "subcategory":"Doctor",
            "type":"Services"
        }
    ],
    "sg:phone":"+61 2 9526 8600",
    "sg:postcode":"2228",
    "sg:province":"NSW",
    "sg:tags":[
        "medical",
        "practitioner"
    ],
    "wof:name":"Shire Cosmetic Medicine",
    "wof:placetype":"venue"
},
  "geometry": {"coordinates":[151.10699462900001,-34.0361480713],"type":"Point"}
}