{
  "type": "Feature",
  "properties": {
    "addr:full":"132 Ellen St Port Pirie SA 5540",
    "addr:housenumber":"132",
    "addr:postcode":"5540",
    "addr:street":"Ellen St",
    "iso:country":"AU",
    "sg:address":"132 Ellen St",
    "sg:city":"Port Pirie",
    "sg:classifiers":[
        {
            "category":"Shopping",
            "subcategory":"Crafts & Fabrics",
            "type":"Retail Goods"
        }
    ],
    "sg:phone":"+61 8 8632 1721",
    "sg:postcode":"5540",
    "sg:province":"SA",
    "sg:tags":[
        "supply"
    ],
    "wof:name":"Jo-Cee's Craft Shop",
    "wof:placetype":"venue"
},
  "geometry": {"coordinates":[138.01014709500001,-33.1773681641],"type":"Point"}
}