{
  "type": "Feature",
  "properties": {
    "iso:country":"AU",
    "sg:address":"5a Douglas St",
    "sg:city":"Merrylands",
    "sg:classifiers":[
        {
            "category":"Building & Trades",
            "subcategory":"Construction",
            "type":"Services"
        }
    ],
    "sg:phone":"+61 2 9635 1935",
    "sg:postcode":"2160",
    "sg:province":"NSW",
    "sg:tags":[
        "contractor"
    ],
    "wof:name":"Farrugia Julian L",
    "wof:placetype":"venue"
},
  "geometry": {"coordinates":[150.97036743199999,-33.8277854919],"type":"Point"}
}