{
  "type": "Feature",
  "properties": {
    "addr:full":"PO Box 470 Tamworth NSW 2340",
    "addr:postcode":"2340",
    "iso:country":"AU",
    "sg:address":"PO Box 470",
    "sg:city":"Tamworth",
    "sg:classifiers":[
        {
            "category":"Professional",
            "subcategory":"Business Services",
            "type":"Services"
        }
    ],
    "sg:phone":"+61 2 6766 4971",
    "sg:postcode":"2340",
    "sg:province":"NSW",
    "sg:tags":[
        "drafting"
    ],
    "wof:name":"S.A.E Building Design & Drafting",
    "wof:placetype":"venue"
},
  "geometry": {"coordinates":[150.92852783199999,-31.0906391144],"type":"Point"}
}