{
  "type": "Feature",
  "properties": {
    "iso:country":"AU",
    "sg:address":"64 Penshurst Rd",
    "sg:city":"Narwee",
    "sg:classifiers":[
        {
            "category":"Social Services",
            "subcategory":"Child Care",
            "type":"Services"
        }
    ],
    "sg:phone":"+61 2 9153 8284",
    "sg:postcode":"2209",
    "sg:province":"NSW",
    "wof:name":"Active Kids",
    "wof:placetype":"venue"
},
  "geometry": {"coordinates":[151.07191499999999,-33.942459],"type":"Point"}
}