{
  "type": "Feature",
  "properties": {
    "iso:country":"AU",
    "sg:address":"PO Box 78",
    "sg:city":"Highgate",
    "sg:classifiers":[
        {
            "category":"Retail",
            "subcategory":"Car Wash",
            "type":"Services"
        }
    ],
    "sg:phone":"+61 1300 657 515",
    "sg:postcode":"5063",
    "sg:province":"SA",
    "sg:tags":[
        "truck",
        "cleaning"
    ],
    "wof:name":"Cargroomers- Mobile Car Grooming",
    "wof:placetype":"venue"
},
  "geometry": {"coordinates":[138.62623596200001,-34.9617004395],"type":"Point"}
}