{
  "type": "Feature",
  "properties": {
    "addr:full":"16 Industrial Ave Molendinar QLD 4214",
    "addr:housenumber":"16",
    "addr:postcode":"4214",
    "addr:street":"Industrial Ave",
    "iso:country":"AU",
    "sg:address":"16 Industrial Ave",
    "sg:city":"Molendinar",
    "sg:classifiers":[
        {
            "category":"Autos & Motor Vehicles",
            "subcategory":"Boat Sales",
            "type":"Retail Goods"
        }
    ],
    "sg:phone":"+61 7 5564 9565",
    "sg:postcode":"4214",
    "sg:province":"QLD",
    "sg:tags":[
        "equipment",
        "yacht"
    ],
    "sg:website":"http://www.rae-line.com.au",
    "wof:name":"Rae-Line",
    "wof:placetype":"venue"
},
  "geometry": {"coordinates":[153.37518310600001,-27.9776439667],"type":"Point"}
}