{
  "type": "Feature",
  "properties": {
    "addr:full":"16 Turriell Bay Rd Lilli Pilli NSW 2229",
    "addr:housenumber":"16",
    "addr:postcode":"2229",
    "addr:street":"Turriell Bay Rd",
    "iso:country":"AU",
    "sg:address":"16 Turriell Bay Rd",
    "sg:city":"Lilli Pilli",
    "sg:classifiers":[
        {
            "category":"Building & Trades",
            "subcategory":"Construction",
            "type":"Services"
        }
    ],
    "sg:phone":"+61 2 9524 5581",
    "sg:postcode":"2229",
    "sg:province":"NSW",
    "sg:tags":[
        "contractor"
    ],
    "wof:name":"Neate Gregory J Building Pty Limited",
    "wof:placetype":"venue"
},
  "geometry": {"coordinates":[151.11585998499999,-34.0630722046],"type":"Point"}
}