{
  "type": "Feature",
  "properties": {
    "addr:full":"4 Malvern St Bayswater VIC 3153",
    "addr:housenumber":"4",
    "addr:postcode":"3153",
    "addr:street":"Malvern St",
    "iso:country":"AU",
    "sg:address":"4 Malvern St",
    "sg:city":"Bayswater",
    "sg:classifiers":[
        {
            "category":"Manufacturing",
            "subcategory":"Motor Vehicles & Parts",
            "type":"Manufacturing & Wholesale Goods"
        }
    ],
    "sg:phone":"+61 3 9720 4442",
    "sg:postcode":"3153",
    "sg:province":"VIC",
    "sg:tags":[
        "replacement"
    ],
    "wof:name":"Alfa Monza Motors",
    "wof:placetype":"venue"
},
  "geometry": {"coordinates":[145.27070617699999,-37.8427238464],"type":"Point"}
}