{
  "type": "Feature",
  "properties": {
    "addr:full":"17 Pindari Drv Greensborough VIC 3088",
    "addr:housenumber":"17",
    "addr:postcode":"3088",
    "addr:street":"Pindari Drv",
    "iso:country":"AU",
    "sg:address":"17 Pindari Drv",
    "sg:city":"Greensborough",
    "sg:classifiers":[
        {
            "category":"Professional",
            "subcategory":"Art Services",
            "type":"Services"
        }
    ],
    "sg:phone":"+61 3 9435 0699",
    "sg:postcode":"3088",
    "sg:province":"VIC",
    "sg:tags":[
        "decorator",
        "painter"
    ],
    "wof:name":"Awesome Painting Services",
    "wof:placetype":"venue"
},
  "geometry": {"coordinates":[145.119338989,-37.6893119812],"type":"Point"}
}