{
  "type": "Feature",
  "properties": {
    "addr:full":"107 Illawarra Rd Marrickville NSW 2204",
    "addr:housenumber":"107",
    "addr:postcode":"2204",
    "addr:street":"Illawarra Rd",
    "iso:country":"AU",
    "sg:address":"107 Illawarra Rd",
    "sg:city":"Marrickville",
    "sg:classifiers":[
        {
            "category":"Retail",
            "subcategory":"Auto Repair",
            "type":"Services"
        }
    ],
    "sg:phone":"+61 2 9569 5792",
    "sg:postcode":"2204",
    "sg:province":"NSW",
    "sg:tags":[
        "repairer",
        "motor",
        "engineer"
    ],
    "wof:name":"Jimmy's Brake Service",
    "wof:placetype":"venue"
},
  "geometry": {"coordinates":[151.160583,-33.906082],"type":"Point"}
}