{
  "type": "Feature",
  "properties": {
    "iso:country":"AU",
    "sg:address":"18 Wickham St",
    "sg:city":"East Perth",
    "sg:classifiers":[
        {
            "category":"Banks & Credit Unions",
            "subcategory":"Financial Services",
            "type":"Services"
        }
    ],
    "sg:phone":"+61 8 9261 6000",
    "sg:postcode":"6004",
    "sg:province":"WA",
    "sg:tags":[
        "planning"
    ],
    "wof:name":"Leed Financial Services",
    "wof:placetype":"venue"
},
  "geometry": {"coordinates":[115.87667083700001,-31.9548301697],"type":"Point"}
}