{
  "type": "Feature",
  "properties": {
    "addr:full":"64 Charles St Launceston TAS 7250",
    "addr:housenumber":"64",
    "addr:postcode":"7250",
    "addr:street":"Charles St",
    "iso:country":"AU",
    "sg:address":"64 Charles St",
    "sg:city":"Launceston",
    "sg:classifiers":[
        {
            "category":"Fast Food",
            "type":"Food & Drink"
        }
    ],
    "sg:phone":"+61 3 6331 6984",
    "sg:postcode":"7250",
    "sg:province":"TAS",
    "sg:tags":[
        "away",
        "take"
    ],
    "wof:name":"The Pantry",
    "wof:placetype":"venue"
},
  "geometry": {"coordinates":[147.13658142099999,-41.4374465942],"type":"Point"}
}