{
  "type": "Feature",
  "properties": {
    "iso:country":"AU",
    "sg:address":"Cnr Soldier & Butcher Rds",
    "sg:city":"Shenton Park",
    "sg:classifiers":[
        {
            "category":"Organizations",
            "subcategory":"Non-profit Organization",
            "type":"Services"
        }
    ],
    "sg:phone":"+61 8 9381 9661",
    "sg:postcode":"6008",
    "sg:province":"WA",
    "sg:tags":[
        "support",
        "disability",
        "organisation"
    ],
    "wof:name":"ISADD",
    "wof:placetype":"venue"
},
  "geometry": {"coordinates":[115.814331055,-31.9608802795],"type":"Point"}
}