{
  "type": "Feature",
  "properties": {
    "addr:full":"100 Glencoe Drv Diggers Rest VIC 3427",
    "addr:housenumber":"100",
    "addr:postcode":"3427",
    "addr:street":"Glencoe Drv",
    "iso:country":"AU",
    "sg:address":"100 Glencoe Drv",
    "sg:city":"Diggers Rest",
    "sg:classifiers":[
        {
            "category":"Building & Trades",
            "subcategory":"Construction",
            "type":"Services"
        }
    ],
    "sg:phone":"+61 419 305 425",
    "sg:postcode":"3427",
    "sg:province":"VIC",
    "sg:tags":[
        "earth",
        "excavating",
        "moving",
        "contractor"
    ],
    "wof:name":"Absolute Excavation",
    "wof:placetype":"venue"
},
  "geometry": {"coordinates":[144.74598693900001,-37.6265602112],"type":"Point"}
}