{
  "type": "Feature",
  "properties": {
    "iso:country":"AU",
    "sg:address":"29 Crawford St",
    "sg:city":"Berala",
    "sg:classifiers":[
        {
            "category":"Real Estate",
            "subcategory":"Real Estate Agent",
            "type":"Services"
        }
    ],
    "sg:phone":"+61 2 9649 8699",
    "sg:postcode":"2141",
    "sg:province":"NSW",
    "wof:name":"Berala Real Estate",
    "wof:placetype":"venue"
},
  "geometry": {"coordinates":[151.03099060100001,-33.87134552],"type":"Point"}
}