{
  "type": "Feature",
  "properties": {
    "addr:full":"18 Sandy Creek Rd Camira QLD 4300",
    "addr:housenumber":"18",
    "addr:postcode":"4300",
    "addr:street":"Sandy Creek Rd",
    "iso:country":"AU",
    "sg:address":"18 Sandy Creek Rd",
    "sg:city":"Camira",
    "sg:classifiers":[
        {
            "category":"Health Services",
            "subcategory":"Medical Lab",
            "type":"Services"
        }
    ],
    "sg:phone":"+61 402 862 562",
    "sg:postcode":"4300",
    "sg:province":"QLD",
    "sg:tags":[
        "laboratory",
        "dental"
    ],
    "wof:name":"D & M Dental Laboratory",
    "wof:placetype":"venue"
},
  "geometry": {"coordinates":[152.926177978,-27.6329307556],"type":"Point"}
}