{
  "type": "Feature",
  "properties": {
    "iso:country":"AU",
    "sg:address":"11 Turnbury Park Drv",
    "sg:city":"Jandakot",
    "sg:classifiers":[
        {
            "category":"Professional",
            "subcategory":"Detective & Security Services",
            "type":"Services"
        }
    ],
    "sg:phone":"+61 414 441 348",
    "sg:postcode":"6164",
    "sg:province":"WA",
    "sg:tags":[
        "consultant",
        "system"
    ],
    "wof:name":"Discount Security",
    "wof:placetype":"venue"
},
  "geometry": {"coordinates":[115.85449199999999,-32.108299],"type":"Point"}
}