{
  "type": "Feature",
  "properties": {
    "addr:full":"Shp5/ 90 Terrigal Esp Terrigal NSW 2260",
    "addr:postcode":"2260",
    "iso:country":"AU",
    "sg:address":"Shp5/ 90",
    "sg:city":"Terrigal Esp Terrigal",
    "sg:classifiers":[
        {
            "category":"Fast Food",
            "type":"Food & Drink"
        }
    ],
    "sg:phone":"+61 2 4385 8522",
    "sg:postcode":"2260",
    "sg:province":"NSW",
    "sg:tags":[
        "away",
        "take"
    ],
    "wof:name":"Asian Chef Terrigal",
    "wof:placetype":"venue"
},
  "geometry": {"coordinates":[151.433426,-33.439682],"type":"Point"}
}