{
  "type": "Feature",
  "properties": {
    "addr:full":"21 Balmain St Richmond VIC 3121",
    "addr:housenumber":"21",
    "addr:postcode":"3121",
    "addr:street":"Balmain St",
    "iso:country":"AU",
    "sg:address":"21 Balmain St",
    "sg:city":"Richmond",
    "sg:classifiers":[
        {
            "category":"Real Estate",
            "subcategory":"Architect",
            "type":"Services"
        }
    ],
    "sg:phone":"+61 3 9428 5600",
    "sg:postcode":"3121",
    "sg:province":"VIC",
    "wof:name":"Neil & Idle Architects",
    "wof:placetype":"venue"
},
  "geometry": {"coordinates":[144.99159240700001,-37.8297042847],"type":"Point"}
}