{
  "type": "Feature",
  "properties": {
    "addr:full":"Unit 1, 5 Delmont Pl Mandurah WA 6210",
    "addr:housenumber":"5",
    "addr:postcode":"6210",
    "addr:street":"Delmont Pl",
    "iso:country":"AU",
    "sg:address":"Unit 1, 5 Delmont Pl",
    "sg:city":"Mandurah",
    "sg:classifiers":[
        {
            "category":"Home & Garden",
            "subcategory":"Building Materials",
            "type":"Retail Goods"
        }
    ],
    "sg:phone":"+61 1800 066 494",
    "sg:postcode":"6210",
    "sg:province":"WA",
    "sg:tags":[
        "merchant",
        "glass",
        "glazier"
    ],
    "wof:name":"Glass4 Mandurah",
    "wof:placetype":"venue"
},
  "geometry": {"coordinates":[115.751244,-32.513031],"type":"Point"}
}