{
  "type": "Feature",
  "properties": {
    "addr:full":"78 McEvoy St Alexandria NSW 2015",
    "addr:housenumber":"78",
    "addr:postcode":"2015",
    "addr:street":"Mcevoy St",
    "iso:country":"AU",
    "sg:address":"78 McEvoy St",
    "sg:city":"Alexandria",
    "sg:classifiers":[
        {
            "category":"Retail",
            "subcategory":"Auto Repair",
            "type":"Services"
        }
    ],
    "sg:phone":"+61 2 9550 2569",
    "sg:postcode":"2015",
    "sg:province":"NSW",
    "sg:tags":[
        "muffler",
        "exhaust",
        "system"
    ],
    "wof:name":"Camperdown Mufflers",
    "wof:placetype":"venue"
},
  "geometry": {"coordinates":[151.19944763199999,-33.9020385742],"type":"Point"}
}