{
  "type": "Feature",
  "properties": {
    "iso:country":"AU",
    "sg:address":"Shop 1 350 The Kingsway",
    "sg:city":"Caringbah",
    "sg:classifiers":[
        {
            "category":"Utilities",
            "subcategory":"Mobile Phone",
            "type":"Services"
        }
    ],
    "sg:phone":"+61 2 9524 4412",
    "sg:postcode":"2229",
    "sg:province":"NSW",
    "sg:tags":[
        "repair",
        "telephone"
    ],
    "wof:name":"Fone Doc Mobile Phone Repair Centre",
    "wof:placetype":"venue"
},
  "geometry": {"coordinates":[151.12420654300001,-34.0129547119],"type":"Point"}
}