{
  "type": "Feature",
  "properties": {
    "iso:country":"AU",
    "sg:address":"2 Fryer Pl",
    "sg:city":"Fadden",
    "sg:classifiers":[
        {
            "category":"Manufacturing",
            "subcategory":"Tools & Machinery",
            "type":"Manufacturing & Wholesale Goods"
        }
    ],
    "sg:phone":"+61 418 211 532",
    "sg:postcode":"2904",
    "sg:province":"ACT",
    "sg:tags":[
        "earth",
        "excavating",
        "moving",
        "equipment"
    ],
    "wof:name":"Bob Webber Building Products",
    "wof:placetype":"venue"
},
  "geometry": {"coordinates":[149.12098693900001,-35.403427124],"type":"Point"}
}