{
  "type": "Feature",
  "properties": {
    "addr:full":"11/ 39 Market St Wollongong NSW 2500",
    "addr:housenumber":"11 / 39",
    "addr:postcode":"2500",
    "addr:street":"Market St",
    "iso:country":"AU",
    "sg:address":"11/ 39 Market St",
    "sg:city":"Wollongong",
    "sg:classifiers":[
        {
            "category":"Banks & Credit Unions",
            "subcategory":"Bank",
            "type":"Services"
        }
    ],
    "sg:phone":"+61 2 4226 6633",
    "sg:postcode":"2500",
    "sg:province":"NSW",
    "sg:tags":[
        "broker",
        "mortgage"
    ],
    "wof:name":"Mortgage Choice",
    "wof:placetype":"venue"
},
  "geometry": {"coordinates":[150.898056,-34.424149],"type":"Point"}
}