{
  "type": "Feature",
  "properties": {
    "addr:full":"PO Box 451 Mowbray TAS 7248",
    "addr:postcode":"7248",
    "iso:country":"AU",
    "sg:address":"PO Box 451",
    "sg:city":"Mowbray",
    "sg:classifiers":[
        {
            "category":"Banks & Credit Unions",
            "subcategory":"Financial Services",
            "type":"Services"
        }
    ],
    "sg:phone":"+61 3 6326 1498",
    "sg:postcode":"7248",
    "sg:province":"TAS",
    "sg:tags":[
        "coin"
    ],
    "wof:name":"Tamar Valley Coins",
    "wof:placetype":"venue"
},
  "geometry": {"coordinates":[147.13265991200001,-41.4055099487],"type":"Point"}
}