{
  "type": "Feature",
  "properties": {
    "addr:full":"9 High St Bute SA 5560",
    "addr:housenumber":"9",
    "addr:postcode":"5560",
    "addr:street":"High St",
    "iso:country":"AU",
    "sg:address":"9 High St",
    "sg:city":"Bute",
    "sg:classifiers":[
        {
            "category":"Food & Beverages",
            "subcategory":"Supermarket",
            "type":"Retail Goods"
        }
    ],
    "sg:phone":"+61 8 8826 2010",
    "sg:postcode":"5560",
    "sg:province":"SA",
    "sg:tags":[
        "grocery",
        "store"
    ],
    "wof:name":"IGA Friendly Grocer",
    "wof:placetype":"venue"
},
  "geometry": {"coordinates":[138.00587463400001,-33.863658905],"type":"Point"}
}