{
  "type": "Feature",
  "properties": {
    "addr:full":"Unit 2 /National Bank Building Mandurah WA 6210",
    "addr:postcode":"6210",
    "iso:country":"AU",
    "sg:address":"Unit 2",
    "sg:city":"/National Bank Building Mandurah",
    "sg:classifiers":[
        {
            "category":"Banks & Credit Unions",
            "subcategory":"Financial Services",
            "type":"Services"
        }
    ],
    "sg:phone":"+61 8 9535 7399",
    "sg:postcode":"6210",
    "sg:province":"WA",
    "sg:tags":[
        "settlement",
        "nt",
        "agent",
        "wa"
    ],
    "wof:name":"Bouvard Settlements",
    "wof:placetype":"venue"
},
  "geometry": {"coordinates":[115.78473700000001,-32.509258],"type":"Point"}
}