{
  "type": "Feature",
  "properties": {
    "iso:country":"AU",
    "sg:address":"37 Arthur St",
    "sg:city":"Toowoomba",
    "sg:classifiers":[
        {
            "category":"Professional",
            "subcategory":"Computer Services",
            "type":"Services"
        }
    ],
    "sg:phone":"+61 7 4639 2294",
    "sg:postcode":"4350",
    "sg:province":"QLD",
    "sg:tags":[
        "consultant",
        "system"
    ],
    "wof:name":"Tod John H",
    "wof:placetype":"venue"
},
  "geometry": {"coordinates":[151.967697,-27.559917],"type":"Point"}
}