{
  "type": "Feature",
  "properties": {
    "addr:full":"36 Hugh Ryan Drv Garbutt QLD 4814",
    "addr:housenumber":"36",
    "addr:postcode":"4814",
    "addr:street":"Hugh Ryan Drv",
    "iso:country":"AU",
    "sg:address":"36 Hugh Ryan Drv",
    "sg:city":"Garbutt",
    "sg:classifiers":[
        {
            "category":"Manufacturing",
            "subcategory":"Retail Goods",
            "type":"Manufacturing & Wholesale Goods"
        }
    ],
    "sg:phone":"+61 7 4779 4880",
    "sg:postcode":"4814",
    "sg:province":"QLD",
    "sg:tags":[
        "merchant",
        "pump",
        "mfrs"
    ],
    "wof:name":"Poolrite Equipment Pty Ltd (Nth Qld)",
    "wof:placetype":"venue"
},
  "geometry": {"coordinates":[146.762573,-19.271362],"type":"Point"}
}