{
  "type": "Feature",
  "properties": {
    "iso:country":"AU",
    "sg:address":"2/ 14 Depot St",
    "sg:city":"Maroochydore",
    "sg:classifiers":[
        {
            "category":"Sports & Exercise",
            "subcategory":"Gym",
            "type":"Entertainment"
        }
    ],
    "sg:phone":"+61 7 5408 0156",
    "sg:postcode":"4558",
    "sg:province":"QLD",
    "sg:tags":[
        "health",
        "fitness"
    ],
    "wof:name":"Sunshine Coast Karate",
    "wof:placetype":"venue"
},
  "geometry": {"coordinates":[153.062957764,-26.6521778107],"type":"Point"}
}