{
  "type": "Feature",
  "properties": {
    "addr:full":"21 Garner Pl Ingleburn NSW 2565",
    "addr:housenumber":"21",
    "addr:postcode":"2565",
    "addr:street":"Pl",
    "iso:country":"AU",
    "sg:address":"21 Garner Pl",
    "sg:city":"Ingleburn",
    "sg:classifiers":[
        {
            "category":"Utilities",
            "subcategory":"Sewage",
            "type":"Services"
        }
    ],
    "sg:phone":"+61 2 9618 4600",
    "sg:postcode":"2565",
    "sg:province":"NSW",
    "sg:tags":[
        "water",
        "waste",
        "treatment"
    ],
    "wof:name":"Dominator Compressors",
    "wof:placetype":"venue"
},
  "geometry": {"coordinates":[150.86744689899999,-33.9864044189],"type":"Point"}
}