{
  "type": "Feature",
  "properties": {
    "iso:country":"AU",
    "sg:address":"Shop 5, Metropol, Cnr Pine Mtn & Creek Rds",
    "sg:city":"Carindale",
    "sg:classifiers":[
        {
            "category":"Health Services",
            "subcategory":"Health Practitioner",
            "type":"Services"
        }
    ],
    "sg:phone":"+61 7 3219 3700",
    "sg:postcode":"4152",
    "sg:province":"QLD",
    "sg:tags":[
        "physiotherapist"
    ],
    "wof:name":"Blackmur Meredith",
    "wof:placetype":"venue"
},
  "geometry": {"coordinates":[153.101760864,-27.5173435211],"type":"Point"}
}