{
  "type": "Feature",
  "properties": {
    "iso:country":"AU",
    "sg:address":"425 Miller St",
    "sg:city":"Cammeray",
    "sg:classifiers":[
        {
            "category":"Bars & Pubs",
            "subcategory":"Lounge",
            "type":"Food & Drink"
        }
    ],
    "sg:phone":"+61 2 9956 5677",
    "sg:postcode":"2062",
    "sg:province":"NSW",
    "sg:tags":[
        "water",
        "filter",
        "drinking"
    ],
    "wof:name":"A.A.A. Hills District Water Filters",
    "wof:placetype":"venue"
},
  "geometry": {"coordinates":[151.21052551299999,-33.822303772],"type":"Point"}
}