{
  "type": "Feature",
  "properties": {
    "addr:full":"Terrica Place Cnr Creek & Adelaide Sts Brisbane QLD 4000",
    "addr:postcode":"4000",
    "addr:street":"Place Cnr Creek & Adelaide Sts",
    "iso:country":"AU",
    "sg:address":"Terrica Place Cnr Creek & Adelaide Sts",
    "sg:city":"Brisbane",
    "sg:classifiers":[
        {
            "category":"Banks & Credit Unions",
            "subcategory":"Bank",
            "type":"Services"
        }
    ],
    "sg:phone":"+61 7 3229 9799",
    "sg:postcode":"4000",
    "sg:province":"QLD",
    "sg:tags":[
        "society"
    ],
    "wof:name":"Discovery Credit Union Ltd",
    "wof:placetype":"venue"
},
  "geometry": {"coordinates":[153.02536010700001,-27.4681777954],"type":"Point"}
}