{
  "type": "Feature",
  "properties": {
    "iso:country":"AU",
    "sg:address":"Shop 1a, Professional Centre 12 Werner Drv",
    "sg:city":"Hallett Cove",
    "sg:classifiers":[
        {
            "category":"Real Estate",
            "subcategory":"Real Estate Agent",
            "type":"Services"
        }
    ],
    "sg:phone":"+61 8 8322 7322",
    "sg:postcode":"5158",
    "sg:province":"SA",
    "wof:name":"Hooker L.J. Hallett Cove",
    "wof:placetype":"venue"
},
  "geometry": {"coordinates":[138.51617431599999,-35.0761985779],"type":"Point"}
}