{
  "type": "Feature",
  "properties": {
    "addr:full":"64 Mt Stuart Rd Mt Stuart TAS 7000",
    "addr:housenumber":"64",
    "addr:postcode":"7000",
    "addr:street":"Mt Stuart Rd",
    "iso:country":"AU",
    "sg:address":"64 Mt Stuart Rd",
    "sg:city":"Mt Stuart",
    "sg:classifiers":[
        {
            "category":"Health Services",
            "subcategory":"Doctor",
            "type":"Services"
        }
    ],
    "sg:phone":"+61 3 6234 1676",
    "sg:postcode":"7000",
    "sg:province":"TAS",
    "sg:tags":[
        "occupational",
        "safety"
    ],
    "wof:name":"Ian Macdonald Consulting",
    "wof:placetype":"venue"
},
  "geometry": {"coordinates":[147.30484008799999,-42.8740272522],"type":"Point"}
}