{
  "type": "Feature",
  "properties": {
    "addr:full":"29 Mary St Mirani QLD 4754",
    "addr:housenumber":"29",
    "addr:postcode":"4754",
    "addr:street":"Mary St",
    "iso:country":"AU",
    "sg:address":"29 Mary St",
    "sg:city":"Mirani",
    "sg:classifiers":[
        {
            "category":"Building & Trades",
            "subcategory":"Cleaning & Sanitation",
            "type":"Services"
        }
    ],
    "sg:phone":"+61 7 4959 1158",
    "sg:postcode":"4754",
    "sg:province":"QLD",
    "sg:tags":[
        "industrial",
        "commercial",
        "contractor"
    ],
    "wof:name":"Pioneer Valley Exteriors",
    "wof:placetype":"venue"
},
  "geometry": {"coordinates":[148.86582899999999,-21.162521],"type":"Point"}
}