{
  "type": "Feature",
  "properties": {
    "addr:full":"63 Barossa Rd Glenorchy TAS 7010",
    "addr:housenumber":"63",
    "addr:postcode":"7010",
    "addr:street":"Barossa Rd",
    "iso:country":"AU",
    "sg:address":"63 Barossa Rd",
    "sg:city":"Glenorchy",
    "sg:classifiers":[
        {
            "category":"Building & Trades",
            "subcategory":"Construction",
            "type":"Services"
        }
    ],
    "sg:phone":"+61 402 280 732",
    "sg:postcode":"7010",
    "sg:province":"TAS",
    "sg:tags":[
        "plasterboard",
        "plasterer",
        "fixer"
    ],
    "wof:name":"Carroll Ray",
    "wof:placetype":"venue"
},
  "geometry": {"coordinates":[147.26773071299999,-42.8485527039],"type":"Point"}
}