{
  "type": "Feature",
  "properties": {
    "iso:country":"AU",
    "sg:address":"67 - 69 Victoria St",
    "sg:city":"Smithfield",
    "sg:classifiers":[
        {
            "category":"Shopping",
            "subcategory":"Pets & Pet Supplies",
            "type":"Retail Goods"
        }
    ],
    "sg:phone":"+61 2 9604 1208",
    "sg:postcode":"2164",
    "sg:province":"NSW",
    "sg:tags":[
        "shop",
        "supplier"
    ],
    "wof:name":"Australian Pet Supplies Pty Ltd",
    "wof:placetype":"venue"
},
  "geometry": {"coordinates":[150.936035156,-33.8508377075],"type":"Point"}
}