{
  "type": "Feature",
  "properties": {
    "addr:full":"9 Krone Ave Shepparton VIC 3630",
    "addr:housenumber":"9",
    "addr:postcode":"3630",
    "addr:street":"Krone Ave",
    "iso:country":"AU",
    "sg:address":"9 Krone Ave",
    "sg:city":"Shepparton",
    "sg:classifiers":[
        {
            "category":"Building & Trades",
            "subcategory":"Plumbing",
            "type":"Services"
        }
    ],
    "sg:phone":"+61 409 314 578",
    "sg:postcode":"3630",
    "sg:province":"VIC",
    "sg:tags":[
        "plumber",
        "gasfitters"
    ],
    "wof:name":"Travis Frost Plumbing & Gasfitting",
    "wof:placetype":"venue"
},
  "geometry": {"coordinates":[145.402999878,-36.3944740295],"type":"Point"}
}