{
  "type": "Feature",
  "properties": {
    "iso:country":"AU",
    "sg:address":"14 Groundberry St",
    "sg:city":"South Morang",
    "sg:classifiers":[
        {
            "category":"Building & Trades",
            "subcategory":"Construction",
            "type":"Services"
        }
    ],
    "sg:phone":"+61 417 361 692",
    "sg:postcode":"3752",
    "sg:province":"VIC",
    "sg:tags":[
        "contractor"
    ],
    "wof:name":"Libreri Homes",
    "wof:placetype":"venue"
},
  "geometry": {"coordinates":[145.09404000000001,-37.624252],"type":"Point"}
}