{
  "type": "Feature",
  "properties": {
    "addr:full":"Mt Lawley Private Hospital 14 Alvan Street Mt Lawley WA 6050",
    "addr:housenumber":"14",
    "addr:postcode":"6050",
    "addr:street":"Alvan Street",
    "iso:country":"AU",
    "sg:address":"Mt Lawley Private Hospital 14 Alvan Street",
    "sg:city":"Mt Lawley",
    "sg:classifiers":[
        {
            "category":"Health Services",
            "subcategory":"Dentist",
            "type":"Services"
        }
    ],
    "sg:phone":"+61 8 9371 8585",
    "sg:postcode":"6050",
    "sg:province":"WA",
    "wof:name":"Greenberg HC Dr Oral Surgeon",
    "wof:placetype":"venue"
},
  "geometry": {"coordinates":[115.874198914,-31.9342041016],"type":"Point"}
}