{
  "type": "Feature",
  "properties": {
    "addr:full":"PO Box 5397 Alexandra Hills QLD 4161",
    "addr:postcode":"4161",
    "iso:country":"AU",
    "sg:address":"PO Box 5397",
    "sg:city":"Alexandra Hills",
    "sg:classifiers":[
        {
            "category":"Home & Garden",
            "subcategory":"Carpets & Floor Coverings",
            "type":"Retail Goods"
        }
    ],
    "sg:phone":"+61 7 3822 1242",
    "sg:postcode":"4161",
    "sg:province":"QLD",
    "sg:tags":[
        "tile",
        "wall",
        "layer"
    ],
    "wof:name":"JP & KL Price",
    "wof:placetype":"venue"
},
  "geometry": {"coordinates":[153.22071838400001,-27.5468406677],"type":"Point"}
}