{
  "type": "Feature",
  "properties": {
    "addr:full":"21B Whistler St Manly NSW 2095",
    "addr:housenumber":"21b",
    "addr:postcode":"2095",
    "addr:street":"Whistler St",
    "iso:country":"AU",
    "sg:address":"21B Whistler St",
    "sg:city":"Manly",
    "sg:classifiers":[
        {
            "category":"Farming",
            "subcategory":"Fish & Marine Products",
            "type":"Manufacturing & Wholesale Goods"
        }
    ],
    "sg:phone":"+61 2 9977 0177",
    "sg:postcode":"2095",
    "sg:province":"NSW",
    "sg:tags":[
        "organic"
    ],
    "wof:name":"Manly Food Co-Operative",
    "wof:placetype":"venue"
},
  "geometry": {"coordinates":[151.28573608400001,-33.7954788208],"type":"Point"}
}