{
  "type": "Feature",
  "properties": {
    "addr:full":"Cnr Mains Rd & McCullough St Sunnybank QLD 4109",
    "addr:postcode":"4109",
    "addr:street":"Cnr Mains Rd & Mccullough St",
    "iso:country":"AU",
    "sg:address":"Cnr Mains Rd & McCullough St",
    "sg:city":"Sunnybank",
    "sg:classifiers":[
        {
            "category":"Health Services",
            "subcategory":"Dentist",
            "type":"Services"
        }
    ],
    "sg:phone":"+61 7 3345 3144",
    "sg:postcode":"4109",
    "sg:province":"QLD",
    "wof:name":"Market Square Dental Group",
    "wof:placetype":"venue"
},
  "geometry": {"coordinates":[153.06275939899999,-27.5783214569],"type":"Point"}
}