{
  "type": "Feature",
  "properties": {
    "iso:country":"AU",
    "sg:address":"Ste6/ 138 Old Town Plz",
    "sg:city":"Bankstown",
    "sg:classifiers":[
        {
            "category":"Banks & Credit Unions",
            "subcategory":"Financial Services",
            "type":"Services"
        }
    ],
    "sg:phone":"+61 2 9793 1237",
    "sg:postcode":"2200",
    "sg:province":"NSW",
    "sg:tags":[
        "financier"
    ],
    "wof:name":"Easy Way Finance",
    "wof:placetype":"venue"
},
  "geometry": {"coordinates":[151.03497300000001,-33.91814],"type":"Point"}
}