{
  "type": "Feature",
  "properties": {
    "iso:country":"AU",
    "sg:address":"100 Vincent St",
    "sg:city":"Beverley",
    "sg:classifiers":[
        {
            "category":"Personal",
            "subcategory":"Beauty Salon",
            "type":"Services"
        }
    ],
    "sg:phone":"+61 8 9646 1122",
    "sg:postcode":"6304",
    "sg:province":"WA",
    "sg:tags":[
        "hairdresser"
    ],
    "wof:name":"T M Hair Design",
    "wof:placetype":"venue"
},
  "geometry": {"coordinates":[116.92111206,-32.1105651855],"type":"Point"}
}