{
  "type": "Feature",
  "properties": {
    "addr:full":"Shop 6 Belmont Forum Fulham St Belmont WA 6104",
    "addr:housenumber":"shop 6;forum",
    "addr:postcode":"6104",
    "addr:street":"Belmont;Fulham St",
    "iso:country":"AU",
    "sg:address":"Shop 6 Belmont Forum Fulham St",
    "sg:city":"Belmont",
    "sg:classifiers":[
        {
            "category":"Retail",
            "subcategory":"Repair Shop",
            "type":"Services"
        }
    ],
    "sg:phone":"+61 8 9478 3644",
    "sg:postcode":"6104",
    "sg:province":"WA",
    "sg:tags":[
        "handbag"
    ],
    "wof:name":"Kays Handbags & Luggage",
    "wof:placetype":"venue"
},
  "geometry": {"coordinates":[115.91742706300001,-31.9522838593],"type":"Point"}
}