{
  "type": "Feature",
  "properties": {
    "addr:full":"88 Oxford St Woollahra NSW 2025",
    "addr:housenumber":"88",
    "addr:postcode":"2025",
    "addr:street":"Oxford St",
    "iso:country":"AU",
    "sg:address":"88 Oxford St",
    "sg:city":"Woollahra",
    "sg:classifiers":[
        {
            "category":"Travel",
            "subcategory":"Hotels & Motels",
            "type":"Entertainment"
        }
    ],
    "sg:phone":"+61 2 9362 3838",
    "sg:postcode":"2025",
    "sg:province":"NSW",
    "sg:tags":[
        "accommodation"
    ],
    "wof:name":"Centennial Hotel Restaurant",
    "wof:placetype":"venue"
},
  "geometry": {"coordinates":[151.23526000999999,-33.8898887634],"type":"Point"}
}