{
  "type": "Feature",
  "properties": {
    "addr:full":"23 Kestrel Ave Hinchinbrook NSW 2168",
    "addr:housenumber":"23",
    "addr:postcode":"2168",
    "addr:street":"Kestrel Ave",
    "iso:country":"AU",
    "sg:address":"23 Kestrel Ave",
    "sg:city":"Hinchinbrook",
    "sg:classifiers":[
        {
            "category":"Professional",
            "subcategory":"Computer Services",
            "type":"Services"
        }
    ],
    "sg:phone":"+61 419 426 826",
    "sg:postcode":"2168",
    "sg:province":"NSW",
    "sg:tags":[
        "repairs",
        "upgrade",
        "equipment"
    ],
    "wof:name":"PC Horizon",
    "wof:placetype":"venue"
},
  "geometry": {"coordinates":[150.864334106,-33.9185409546],"type":"Point"}
}