{
  "type": "Feature",
  "properties": {
    "addr:full":"Factory 3, 25 Graham Crt Hoppers Crossing VIC 3029",
    "addr:housenumber":"25",
    "addr:postcode":"3029",
    "addr:street":"Graham Crt",
    "iso:country":"AU",
    "sg:address":"Factory 3, 25 Graham Crt",
    "sg:city":"Hoppers Crossing",
    "sg:classifiers":[
        {
            "category":"Professional",
            "type":"Services"
        }
    ],
    "sg:phone":"+61 3 9931 1391",
    "sg:postcode":"3029",
    "sg:province":"VIC",
    "sg:tags":[
        "control",
        "equipment",
        "traffic"
    ],
    "wof:name":"Metropolitan Traffic Management",
    "wof:placetype":"venue"
},
  "geometry": {"coordinates":[144.729614,-37.873222],"type":"Point"}
}