{
  "type": "Feature",
  "properties": {
    "iso:country":"AU",
    "sg:address":"Factory 3 - 3 Elma Rd",
    "sg:city":"Cheltenham",
    "sg:classifiers":[
        {
            "category":"Home & Garden",
            "subcategory":"Building Materials",
            "type":"Retail Goods"
        }
    ],
    "sg:phone":"+61 3 9555 0088",
    "sg:postcode":"3192",
    "sg:province":"VIC",
    "sg:tags":[
        "gate"
    ],
    "wof:name":"Absolute Steel Security P/L",
    "wof:placetype":"venue"
},
  "geometry": {"coordinates":[145.073287964,-37.9518089294],"type":"Point"}
}