{
  "type": "Feature",
  "properties": {
    "iso:country":"AU",
    "sg:address":"1 Regiment Crt",
    "sg:city":"Kirwan",
    "sg:classifiers":[
        {
            "category":"Retail",
            "subcategory":"Storage",
            "type":"Services"
        }
    ],
    "sg:phone":"+61 7 4723 6066",
    "sg:postcode":"4817",
    "sg:province":"QLD",
    "wof:name":"Willows Self Storage",
    "wof:placetype":"venue"
},
  "geometry": {"coordinates":[146.724396,-19.320877],"type":"Point"}
}