{
  "type": "Feature",
  "properties": {
    "addr:full":"90 Passage St Cleveland QLD 4163",
    "addr:housenumber":"90",
    "addr:postcode":"4163",
    "addr:street":"Passage St",
    "iso:country":"AU",
    "sg:address":"90 Passage St",
    "sg:city":"Cleveland",
    "sg:classifiers":[
        {
            "category":"Building & Trades",
            "subcategory":"Construction",
            "type":"Services"
        }
    ],
    "sg:phone":"+61 7 3821 3232",
    "sg:postcode":"4163",
    "sg:province":"QLD",
    "sg:tags":[
        "home",
        "air conditioning"
    ],
    "wof:name":"Q-Tech Airconditioning & Essential Services Pty Ltd",
    "wof:placetype":"venue"
},
  "geometry": {"coordinates":[153.27865600600001,-27.5324325562],"type":"Point"}
}