{
  "type": "Feature",
  "properties": {
    "addr:full":"53 Alawa Crs Alawa NT 0810",
    "addr:housenumber":"53",
    "addr:postcode":"nt 0810",
    "addr:street":"Alawa Crs",
    "iso:country":"AU",
    "sg:address":"53 Alawa Crs",
    "sg:city":"Alawa",
    "sg:classifiers":[
        {
            "category":"Food & Beverages",
            "subcategory":"Supermarket",
            "type":"Retail Goods"
        }
    ],
    "sg:phone":"+61 8 8985 1529",
    "sg:postcode":"0810",
    "sg:province":"NT",
    "sg:tags":[
        "grocery",
        "store"
    ],
    "wof:name":"Alawa Food Store",
    "wof:placetype":"venue"
},
  "geometry": {"coordinates":[130.87542724599999,-12.3819999695],"type":"Point"}
}