{
  "type": "Feature",
  "properties": {
    "addr:full":"2/190 Sharp St Cooma NSW 2630",
    "addr:housenumber":"/ 190",
    "addr:postcode":"2630",
    "addr:street":"Sharp St",
    "iso:country":"AU",
    "sg:address":"2/190 Sharp St",
    "sg:city":"Cooma",
    "sg:classifiers":[
        {
            "category":"Health Services",
            "subcategory":"Medical Lab",
            "type":"Services"
        }
    ],
    "sg:phone":"+61 2 6452 3150",
    "sg:postcode":"2630",
    "sg:province":"NSW",
    "sg:tags":[
        "laboratory",
        "pathology"
    ],
    "wof:name":"Capital Pathology",
    "wof:placetype":"venue"
},
  "geometry": {"coordinates":[149.13409423799999,-36.2312316895],"type":"Point"}
}