{
  "type": "Feature",
  "properties": {
    "addr:full":"Shop 17 Somerville Blvd Winthrop Village Winthrop WA 6150",
    "addr:housenumber":"shop 17",
    "addr:postcode":"6150",
    "addr:street":"Somerville Blvd",
    "iso:country":"AU",
    "sg:address":"Shop 17 Somerville Blvd Winthrop Village",
    "sg:city":"Winthrop",
    "sg:classifiers":[
        {
            "category":"Personal",
            "subcategory":"Beauty Salon",
            "type":"Services"
        }
    ],
    "sg:phone":"+61 8 9310 5516",
    "sg:postcode":"6150",
    "sg:province":"WA",
    "sg:tags":[
        "hairdresser"
    ],
    "wof:name":"Naducci For Hair",
    "wof:placetype":"venue"
},
  "geometry": {"coordinates":[115.83419000000001,-32.059471],"type":"Point"}
}