{
  "type": "Feature",
  "properties": {
    "iso:country":"AU",
    "sg:address":"38 Ross Smith Ave",
    "sg:city":"Frankston",
    "sg:classifiers":[
        {
            "category":"Retail",
            "subcategory":"Auto Repair",
            "type":"Services"
        }
    ],
    "sg:phone":"+61 3 9770 0844",
    "sg:postcode":"3199",
    "sg:province":"VIC",
    "sg:tags":[
        "repairer",
        "motor",
        "engineer"
    ],
    "wof:name":"Prime Express Auto Service",
    "wof:placetype":"venue"
},
  "geometry": {"coordinates":[145.125244141,-38.1420898438],"type":"Point"}
}