{
  "type": "Feature",
  "properties": {
    "addr:full":"23 Crows La Glen Waverley VIC 3150",
    "addr:housenumber":"23",
    "addr:postcode":"3150",
    "addr:street":"Crows La",
    "iso:country":"AU",
    "sg:address":"23 Crows La",
    "sg:city":"Glen Waverley",
    "sg:classifiers":[
        {
            "category":"Real Estate",
            "subcategory":"Developer",
            "type":"Services"
        }
    ],
    "sg:phone":"+61 3 9802 5358",
    "sg:postcode":"3150",
    "sg:province":"VIC",
    "sg:tags":[
        "development"
    ],
    "wof:name":"Jessco Investments Pty Ltd",
    "wof:placetype":"venue"
},
  "geometry": {"coordinates":[145.16484069800001,-37.8637733459],"type":"Point"}
}