{
  "type": "Feature",
  "properties": {
    "iso:country":"AU",
    "sg:address":"Artfox Sculpture Gallery 7 Barrani Pl",
    "sg:city":"Lilli Pilli",
    "sg:classifiers":[
        {
            "category":"Professional",
            "subcategory":"Art Services",
            "type":"Services"
        }
    ],
    "sg:phone":"+61 404 086 513",
    "sg:postcode":"2536",
    "sg:province":"NSW",
    "sg:tags":[
        "sculptor"
    ],
    "wof:name":"Fox, David Sculptor",
    "wof:placetype":"venue"
},
  "geometry": {"coordinates":[150.227218628,-35.7774887085],"type":"Point"}
}