{
  "type": "Feature",
  "properties": {
    "addr:full":"3 / 14 Reliance Drv Tuggerah NSW 2259",
    "addr:housenumber":"/ 14",
    "addr:postcode":"2259",
    "addr:street":"Reliance Drv",
    "iso:country":"AU",
    "sg:address":"3 / 14 Reliance Drv",
    "sg:city":"Tuggerah",
    "sg:classifiers":[
        {
            "category":"Professional",
            "subcategory":"Testing Lab",
            "type":"Services"
        }
    ],
    "sg:phone":"+61 2 4351 0210",
    "sg:postcode":"2259",
    "sg:province":"NSW",
    "sg:tags":[
        "inspection"
    ],
    "wof:name":"Survival Solutions (Aust) Pty Ltd",
    "wof:placetype":"venue"
},
  "geometry": {"coordinates":[151.42100524899999,-33.3188209534],"type":"Point"}
}