{
  "type": "Feature",
  "properties": {
    "addr:full":"Cnr Melton Hwy & Village Ave Taylors Lakes VIC 3038",
    "addr:postcode":"3038",
    "addr:street":"Cnr Melton Hwy & Village Ave",
    "iso:country":"AU",
    "sg:address":"Cnr Melton Hwy & Village Ave",
    "sg:city":"Taylors Lakes",
    "sg:classifiers":[
        {
            "category":"Retail",
            "subcategory":"Auto Repair",
            "type":"Services"
        }
    ],
    "sg:phone":"+61 3 9390 9600",
    "sg:postcode":"3038",
    "sg:province":"VIC",
    "sg:tags":[
        "repairer",
        "motor",
        "engineer"
    ],
    "wof:name":"Comprehensive Automotive Repair Engineering",
    "wof:placetype":"venue"
},
  "geometry": {"coordinates":[144.781036,-37.697227],"type":"Point"}
}