{
  "type": "Feature",
  "properties": {
    "iso:country":"AU",
    "sg:address":"61 Manor Crt",
    "sg:city":"Canungra",
    "sg:classifiers":[
        {
            "category":"Building & Trades",
            "subcategory":"Equipment Rental",
            "type":"Services"
        }
    ],
    "sg:phone":"+61 7 5543 4411",
    "sg:postcode":"4275",
    "sg:province":"QLD",
    "sg:tags":[
        "party",
        "hire"
    ],
    "wof:name":"Alfa Whiskey Equipment Services",
    "wof:placetype":"venue"
},
  "geometry": {"coordinates":[153.15625,-28.0141887665],"type":"Point"}
}