{
  "type": "Feature",
  "properties": {
    "addr:full":"Wendouree Pde Ballarat VIC 3350",
    "addr:postcode":"3350",
    "addr:street":"Wendouree Pde",
    "iso:country":"AU",
    "sg:address":"Wendouree Pde",
    "sg:city":"Ballarat",
    "sg:classifiers":[
        {
            "category":"Retail",
            "subcategory":"Event Space",
            "type":"Services"
        }
    ],
    "sg:phone":"+61 3 5331 5869",
    "sg:postcode":"3350",
    "sg:province":"VIC",
    "sg:tags":[
        "venue",
        "reception",
        "wedding"
    ],
    "wof:name":"Sails on the Lake",
    "wof:placetype":"venue"
},
  "geometry": {"coordinates":[143.84184300000001,-37.555893],"type":"Point"}
}