{
  "type": "Feature",
  "properties": {
    "addr:full":"Cnr Empire Bay Drv & Cochrane St Kincumber NSW 2251",
    "addr:postcode":"2251",
    "addr:street":"Bay Drv & Cochrane St",
    "iso:country":"AU",
    "sg:address":"Cnr Empire Bay Drv & Cochrane St",
    "sg:city":"Kincumber",
    "sg:classifiers":[
        {
            "category":"Retail",
            "subcategory":"Storage",
            "type":"Services"
        }
    ],
    "sg:phone":"+61 2 4322 0927",
    "sg:postcode":"2251",
    "sg:province":"NSW",
    "wof:name":"Kincumber Mini Stores",
    "wof:placetype":"venue"
},
  "geometry": {"coordinates":[151.388793945,-33.4768447876],"type":"Point"}
}