{
  "type": "Feature",
  "properties": {
    "addr:full":"1 Tripovich St Cnr Ballarat St Brunswick VIC 3056",
    "addr:housenumber":"1",
    "addr:postcode":"3056",
    "addr:street":"Tripovich St Cnr;St",
    "iso:country":"AU",
    "sg:address":"1 Tripovich St Cnr Ballarat St",
    "sg:city":"Brunswick",
    "sg:classifiers":[
        {
            "category":"Arts & Performance",
            "subcategory":"Theater",
            "type":"Entertainment"
        }
    ],
    "sg:phone":"+61 3 9381 4188",
    "sg:postcode":"3056",
    "sg:province":"VIC",
    "sg:tags":[
        "theatre"
    ],
    "wof:name":"Italian Drama Company",
    "wof:placetype":"venue"
},
  "geometry": {"coordinates":[144.96194457999999,-37.7660293579],"type":"Point"}
}