{
  "type": "Feature",
  "properties": {
    "addr:full":"1 Burnside Ave Tamworth NSW 2340",
    "addr:housenumber":"1",
    "addr:postcode":"2340",
    "addr:street":"Burnside Ave",
    "iso:country":"AU",
    "sg:address":"1 Burnside Ave",
    "sg:city":"Tamworth",
    "sg:classifiers":[
        {
            "category":"Health Services",
            "subcategory":"Dentist",
            "type":"Services"
        }
    ],
    "sg:phone":"+61 2 6766 3718",
    "sg:postcode":"2340",
    "sg:province":"NSW",
    "sg:tags":[
        "technician",
        "dental"
    ],
    "wof:name":"Both R. G. & E. M.",
    "wof:placetype":"venue"
},
  "geometry": {"coordinates":[150.94117736800001,-31.0822563171],"type":"Point"}
}