{
  "type": "Feature",
  "properties": {
    "addr:full":"514 Canterbury Rd Vermont VIC 3133",
    "addr:housenumber":"514",
    "addr:postcode":"3133",
    "addr:street":"Canterbury Rd",
    "iso:country":"AU",
    "sg:address":"514 Canterbury Rd",
    "sg:city":"Vermont",
    "sg:classifiers":[
        {
            "category":"Autos & Motor Vehicles",
            "subcategory":"Boat Sales",
            "type":"Retail Goods"
        }
    ],
    "sg:phone":"+61 3 9874 4624",
    "sg:postcode":"3133",
    "sg:province":"VIC",
    "sg:tags":[
        "yacht"
    ],
    "wof:name":"Regal Marine",
    "wof:placetype":"venue"
},
  "geometry": {"coordinates":[145.18666076700001,-37.8366241455],"type":"Point"}
}