{
  "type": "Feature",
  "properties": {
    "iso:country":"AU",
    "sg:address":"The Atrium 76 Ainsworth St",
    "sg:city":"Mawson",
    "sg:classifiers":[
        {
            "category":"Organizations",
            "subcategory":"Labor Organization",
            "type":"Services"
        }
    ],
    "sg:phone":"+61 2 6290 2599",
    "sg:postcode":"2607",
    "sg:province":"ACT",
    "sg:tags":[
        "organisation",
        "retiree"
    ],
    "wof:name":"Association Of Independent Retirees (AIR) Ltd",
    "wof:placetype":"venue"
},
  "geometry": {"coordinates":[149.09753418,-35.355796814],"type":"Point"}
}