{
  "type": "Feature",
  "properties": {
    "iso:country":"AU",
    "sg:address":"Sugar Bag Rd",
    "sg:city":"Caloundra",
    "sg:classifiers":[
        {
            "category":"Building & Trades",
            "subcategory":"Cleaning & Sanitation",
            "type":"Services"
        }
    ],
    "sg:phone":"+61 7 5491 5717",
    "sg:postcode":"4551",
    "sg:province":"QLD",
    "sg:tags":[
        "window"
    ],
    "wof:name":"Window King",
    "wof:placetype":"venue"
},
  "geometry": {"coordinates":[153.12083435100001,-26.7912254333],"type":"Point"}
}