{
  "type": "Feature",
  "properties": {
    "addr:full":"18 Carnelian St Hope Valley SA 5090",
    "addr:housenumber":"18",
    "addr:postcode":"5090",
    "addr:street":"Carnelian St",
    "iso:country":"AU",
    "sg:address":"18 Carnelian St",
    "sg:city":"Hope Valley",
    "sg:classifiers":[
        {
            "category":"Sports & Exercise",
            "subcategory":"Sports Center",
            "type":"Entertainment"
        }
    ],
    "sg:phone":"+61 8 8263 7068",
    "sg:postcode":"5090",
    "sg:province":"SA",
    "sg:tags":[
        "coach",
        "tennis"
    ],
    "wof:name":"Crowe Janine",
    "wof:placetype":"venue"
},
  "geometry": {"coordinates":[138.71116638199999,-34.8442993164],"type":"Point"}
}