{
  "type": "Feature",
  "properties": {
    "addr:full":"5 / 86 Township Drv West Burleigh QLD 4219",
    "addr:housenumber":"/ 86",
    "addr:postcode":"4219",
    "addr:street":"Township Drv West",
    "iso:country":"AU",
    "sg:address":"5 / 86 Township Drv",
    "sg:city":"West Burleigh",
    "sg:classifiers":[
        {
            "category":"Wholesale",
            "subcategory":"Painting Supplies",
            "type":"Manufacturing & Wholesale Goods"
        }
    ],
    "sg:phone":"+61 7 5569 5655",
    "sg:postcode":"4219",
    "sg:province":"QLD",
    "sg:tags":[
        "wholesaler",
        "paint",
        "mfrs"
    ],
    "wof:name":"Motorama Paint & Refinish",
    "wof:placetype":"venue"
},
  "geometry": {"coordinates":[153.43655395499999,-28.1113128662],"type":"Point"}
}