{
  "type": "Feature",
  "properties": {
    "addr:full":"2- 10 Chetwynd St Loganholme QLD 4129",
    "addr:housenumber":"10",
    "addr:postcode":"4129",
    "addr:street":"2;Chetwynd St",
    "iso:country":"AU",
    "sg:address":"2- 10 Chetwynd St",
    "sg:city":"Loganholme",
    "sg:classifiers":[
        {
            "category":"Manufacturing",
            "subcategory":"Chemicals & Compounds",
            "type":"Manufacturing & Wholesale Goods"
        }
    ],
    "sg:phone":"+61 1800 654 758",
    "sg:postcode":"4129",
    "sg:province":"QLD",
    "sg:tags":[
        "agricultural"
    ],
    "wof:name":"Agrichem",
    "wof:placetype":"venue"
},
  "geometry": {"coordinates":[153.18629455600001,-27.67852211],"type":"Point"}
}