{
  "type": "Feature",
  "properties": {
    "addr:full":"Unit 3, Southlands Mawson ACT 2607",
    "addr:housenumber":"southlands",
    "addr:postcode":"2607",
    "iso:country":"AU",
    "sg:address":"Unit 3, Southlands",
    "sg:city":"Mawson",
    "sg:classifiers":[
        {
            "category":"Building & Trades",
            "subcategory":"Construction",
            "type":"Services"
        }
    ],
    "sg:phone":"+61 2 6286 6100",
    "sg:postcode":"2607",
    "sg:province":"ACT",
    "sg:tags":[
        "management"
    ],
    "wof:name":"FGC Developments Pty Ltd",
    "wof:placetype":"venue"
},
  "geometry": {"coordinates":[149.09529113799999,-35.3641891479],"type":"Point"}
}