{
  "type": "Feature",
  "properties": {
    "iso:country":"AU",
    "sg:address":"Lot3/ Corfield Drv",
    "sg:city":"Agnes Water",
    "sg:classifiers":[
        {
            "category":"Utilities",
            "subcategory":"Electric",
            "type":"Services"
        }
    ],
    "sg:phone":"+61 7 4974 7686",
    "sg:postcode":"4677",
    "sg:province":"QLD",
    "sg:tags":[
        "electrical",
        "contractor"
    ],
    "wof:name":"COD Electrical",
    "wof:placetype":"venue"
},
  "geometry": {"coordinates":[151.876099,-24.224787],"type":"Point"}
}