{
  "type": "Feature",
  "properties": {
    "addr:full":"1183 Pittwater Rd Collaroy NSW 2097",
    "addr:housenumber":"1183",
    "addr:postcode":"2097",
    "addr:street":"Pittwater Rd",
    "iso:country":"AU",
    "sg:address":"1183 Pittwater Rd",
    "sg:city":"Collaroy",
    "sg:classifiers":[
        {
            "category":"Government",
            "subcategory":"City Hall",
            "type":"Public Place"
        }
    ],
    "sg:phone":"+61 2 9971 2913",
    "sg:postcode":"2097",
    "sg:province":"NSW",
    "wof:name":"Masonic Halls & Centres",
    "wof:placetype":"venue"
},
  "geometry": {"coordinates":[151.29937744099999,-33.7280273438],"type":"Point"}
}