{
  "type": "Feature",
  "properties": {
    "addr:full":"280 Doncaster Rd Balwyn North VIC 3104",
    "addr:housenumber":"280",
    "addr:postcode":"3104",
    "addr:street":"Doncaster Rd",
    "iso:country":"AU",
    "sg:address":"280 Doncaster Rd",
    "sg:city":"Balwyn North",
    "sg:classifiers":[
        {
            "category":"Shopping",
            "subcategory":"Clothing, Apparel, & Fashions",
            "type":"Retail Goods"
        }
    ],
    "sg:phone":"+61 3 9816 4411",
    "sg:postcode":"3104",
    "sg:province":"VIC",
    "sg:tags":[
        "lady",
        "wear"
    ],
    "wof:name":"Roxanne Fashions",
    "wof:placetype":"venue"
},
  "geometry": {"coordinates":[145.09370422399999,-37.7919502258],"type":"Point"}
}