{
  "type": "Feature",
  "properties": {
    "iso:country":"AU",
    "sg:address":"15 James St",
    "sg:city":"Lowood",
    "sg:classifiers":[
        {
            "category":"Education",
            "subcategory":"Music School",
            "type":"Public Place"
        }
    ],
    "sg:phone":"+61 7 5426 1178",
    "sg:postcode":"4311",
    "sg:province":"QLD",
    "sg:tags":[
        "teacher"
    ],
    "wof:name":"Dave Teis",
    "wof:placetype":"venue"
},
  "geometry": {"coordinates":[152.57664489699999,-27.4614524841],"type":"Point"}
}