{
  "type": "Feature",
  "properties": {
    "iso:country":"AU",
    "sg:address":"15 Elizabeth St",
    "sg:city":"Adelaide",
    "sg:classifiers":[
        {
            "category":"Home & Garden",
            "subcategory":"Hardware",
            "type":"Retail Goods"
        }
    ],
    "sg:phone":"+61 8 8212 5619",
    "sg:postcode":"5000",
    "sg:province":"SA",
    "sg:tags":[
        "plumber",
        "supply"
    ],
    "wof:name":"Reeceprojects Adelaide",
    "wof:placetype":"venue"
},
  "geometry": {"coordinates":[138.591506958,-34.9249839783],"type":"Point"}
}