{
  "type": "Feature",
  "properties": {
    "addr:full":"Capalaba Park Shopping Cntr Capalaba QLD 4157",
    "addr:postcode":"4157",
    "iso:country":"AU",
    "sg:address":"Capalaba Park Shopping Cntr",
    "sg:city":"Capalaba",
    "sg:classifiers":[
        {
            "category":"Shopping",
            "subcategory":"Gifts & Souvenirs",
            "type":"Retail Goods"
        }
    ],
    "sg:phone":"+61 7 3823 3422",
    "sg:postcode":"4157",
    "sg:province":"QLD",
    "sg:tags":[
        "print",
        "poster",
        "pictures"
    ],
    "wof:name":"Framing Corner",
    "wof:placetype":"venue"
},
  "geometry": {"coordinates":[153.19229125999999,-27.5437927246],"type":"Point"}
}