{
  "type": "Feature",
  "properties": {
    "iso:country":"AU",
    "sg:address":"8- 10 Copernicus Way",
    "sg:city":"Keilor Downs",
    "sg:classifiers":[
        {
            "category":"Health Services",
            "subcategory":"Dentist",
            "type":"Services"
        }
    ],
    "sg:phone":"+61 3 9366 8130",
    "sg:postcode":"3038",
    "sg:province":"VIC",
    "wof:name":"Snell Chris Dr",
    "wof:placetype":"venue"
},
  "geometry": {"coordinates":[144.80604600000001,-37.723736],"type":"Point"}
}