{
  "type": "Feature",
  "properties": {
    "addr:full":"Gordon St Footscray VIC 3011",
    "addr:postcode":"3011",
    "addr:street":"Gordon St",
    "iso:country":"AU",
    "sg:address":"Gordon St",
    "sg:city":"Footscray",
    "sg:classifiers":[
        {
            "category":"Health Services",
            "subcategory":"Doctor",
            "type":"Services"
        }
    ],
    "sg:phone":"+61 3 9318 3588",
    "sg:postcode":"3011",
    "sg:province":"VIC",
    "sg:tags":[
        "medical",
        "practitioner"
    ],
    "wof:name":"Thompson Graeme A",
    "wof:placetype":"venue"
},
  "geometry": {"coordinates":[144.889434814,-37.7915725708],"type":"Point"}
}