{
  "type": "Feature",
  "properties": {
    "iso:country":"AU",
    "sg:address":"Moodemere St",
    "sg:city":"Noble Park",
    "sg:classifiers":[
        {
            "category":"Arena",
            "subcategory":"Sports Club",
            "type":"Entertainment"
        }
    ],
    "sg:phone":"+61 3 9546 0653",
    "sg:postcode":"3174",
    "sg:province":"VIC",
    "sg:tags":[
        "australian",
        "football",
        "rule"
    ],
    "wof:name":"Noble Park Football Club",
    "wof:placetype":"venue"
},
  "geometry": {"coordinates":[145.17703247099999,-37.9774284363],"type":"Point"}
}