{
  "type": "Feature",
  "properties": {
    "addr:full":"325 Barker St (cnr Hunter St) Castlemaine VIC 3450",
    "addr:housenumber":"325",
    "addr:postcode":"3450",
    "addr:street":"Barker St Cnr Hunter St",
    "iso:country":"AU",
    "sg:address":"325 Barker St (cnr Hunter St)",
    "sg:city":"Castlemaine",
    "sg:classifiers":[
        {
            "category":"Retail",
            "subcategory":"Veterinary Services",
            "type":"Services"
        }
    ],
    "sg:phone":"+61 3 5472 5477",
    "sg:postcode":"3450",
    "sg:province":"VIC",
    "sg:tags":[
        "surgeon"
    ],
    "wof:name":"Vets All Natural Animal Health Centre",
    "wof:placetype":"venue"
},
  "geometry": {"coordinates":[144.22198486299999,-37.0486412048],"type":"Point"}
}