{
  "type": "Feature",
  "properties": {
    "iso:country":"AU",
    "sg:address":"9 Titus Drv St",
    "sg:city":"Andrews Beach",
    "sg:classifiers":[
        {
            "category":"Building & Trades",
            "subcategory":"Construction",
            "type":"Services"
        }
    ],
    "sg:phone":"+61 403 252 206",
    "sg:postcode":"3941",
    "sg:province":"VIC",
    "sg:tags":[
        "home",
        "air conditioning"
    ],
    "wof:name":"Estate Plumbing & Air Conditioning",
    "wof:placetype":"venue"
},
  "geometry": {"coordinates":[144.831268311,-38.4162940979],"type":"Point"}
}