{
  "type": "Feature",
  "properties": {
    "iso:country":"AU",
    "sg:address":"824 East Kurrajong Rd",
    "sg:city":"Kurrajong East",
    "sg:classifiers":[
        {
            "category":"Health Services",
            "subcategory":"Health Practitioner",
            "type":"Services"
        }
    ],
    "sg:phone":"+61 2 4576 6786",
    "sg:postcode":"2758",
    "sg:province":"NSW",
    "sg:tags":[
        "naturopath"
    ],
    "wof:name":"Knot Cottage Natural Health Therapy",
    "wof:placetype":"venue"
},
  "geometry": {"coordinates":[150.77273559599999,-33.5145683289],"type":"Point"}
}