{
  "type": "Feature",
  "properties": {
    "addr:full":"25 Warraba Rd North Narrabeen NSW 2101",
    "addr:housenumber":"25",
    "addr:postcode":"2101",
    "addr:street":"Warraba Rd",
    "iso:country":"AU",
    "sg:address":"25 Warraba Rd",
    "sg:city":"North Narrabeen",
    "sg:classifiers":[
        {
            "category":"Retail",
            "subcategory":"Auto Repair",
            "type":"Services"
        }
    ],
    "sg:phone":"+61 2 9913 1893",
    "sg:postcode":"2101",
    "sg:province":"NSW",
    "sg:tags":[
        "beater",
        "painter",
        "panel"
    ],
    "wof:name":"David Gregory Body Repairs",
    "wof:placetype":"venue"
},
  "geometry": {"coordinates":[151.293961,-33.70071],"type":"Point"}
}