{
  "type": "Feature",
  "properties": {
    "addr:full":"52 Connells Point Rd Hurstville South NSW 2221",
    "addr:housenumber":"52",
    "addr:postcode":"2221",
    "addr:street":"Connells Point Rd",
    "iso:country":"AU",
    "sg:address":"52 Connells Point Rd",
    "sg:city":"Hurstville South",
    "sg:classifiers":[
        {
            "category":"Professional",
            "subcategory":"Management & Consulting",
            "type":"Services"
        }
    ],
    "sg:phone":"+61 2 9546 6774",
    "sg:postcode":"2221",
    "sg:province":"NSW",
    "sg:tags":[
        "consultant",
        "business"
    ],
    "wof:name":"Critical Insights Australasia Pty Ltd",
    "wof:placetype":"venue"
},
  "geometry": {"coordinates":[151.09388732900001,-33.9866409302],"type":"Point"}
}