{
  "type": "Feature",
  "properties": {
    "addr:full":"14 Pacific St Caves Beach NSW 2281",
    "addr:housenumber":"14",
    "addr:postcode":"2281",
    "addr:street":"Pacific St",
    "iso:country":"AU",
    "sg:address":"14 Pacific St",
    "sg:city":"Caves Beach",
    "sg:classifiers":[
        {
            "category":"Utilities",
            "subcategory":"Electric",
            "type":"Services"
        }
    ],
    "sg:phone":"+61 411 800 038",
    "sg:postcode":"2281",
    "sg:province":"NSW",
    "sg:tags":[
        "electrical",
        "contractor"
    ],
    "wof:name":"Construction & Maintenance Services Pty Ltd",
    "wof:placetype":"venue"
},
  "geometry": {"coordinates":[151.64329528799999,-33.1080055237],"type":"Point"}
}