{
  "type": "Feature",
  "properties": {
    "addr:full":"31 Carol St Scoresby VIC 3179",
    "addr:housenumber":"31",
    "addr:postcode":"3179",
    "addr:street":"Carol St",
    "iso:country":"AU",
    "sg:address":"31 Carol St",
    "sg:city":"Scoresby",
    "sg:classifiers":[
        {
            "category":"Retail",
            "subcategory":"Repair Shop",
            "type":"Services"
        }
    ],
    "sg:phone":"+61 3 9763 6681",
    "sg:postcode":"3179",
    "sg:province":"VIC",
    "sg:tags":[
        "machine",
        "sewing"
    ],
    "wof:name":"Roger Edwards",
    "wof:placetype":"venue"
},
  "geometry": {"coordinates":[145.225067139,-37.8967704773],"type":"Point"}
}