{
  "type": "Feature",
  "properties": {
    "addr:full":"7 Johnstone Rd Warrnambool VIC 3280",
    "addr:housenumber":"7",
    "addr:postcode":"3280",
    "addr:street":"Johnstone Rd",
    "iso:country":"AU",
    "sg:address":"7 Johnstone Rd",
    "sg:city":"Warrnambool",
    "sg:classifiers":[
        {
            "category":"Professional",
            "subcategory":"Accounting & Tax Preparation",
            "type":"Services"
        }
    ],
    "sg:phone":"+61 3 5561 5888",
    "sg:postcode":"3280",
    "sg:province":"VIC",
    "sg:tags":[
        "accountant",
        "auditor"
    ],
    "wof:name":"Cho Perry",
    "wof:placetype":"venue"
},
  "geometry": {"coordinates":[142.48675537099999,-38.3593673706],"type":"Point"}
}