{
  "type": "Feature",
  "properties": {
    "addr:full":"130 Seventh Ave Altona North VIC 3025",
    "addr:housenumber":"130",
    "addr:postcode":"3025",
    "addr:street":"Seventh Ave",
    "iso:country":"AU",
    "sg:address":"130 Seventh Ave",
    "sg:city":"Altona North",
    "sg:classifiers":[
        {
            "category":"Building & Trades",
            "subcategory":"Construction",
            "type":"Services"
        }
    ],
    "sg:phone":"+61 417 512 286",
    "sg:postcode":"3025",
    "sg:province":"VIC",
    "sg:tags":[
        "rendering",
        "cement"
    ],
    "wof:name":"ABC Rendering & Tiling",
    "wof:placetype":"venue"
},
  "geometry": {"coordinates":[144.84922800000001,-37.832943],"type":"Point"}
}