{
  "type": "Feature",
  "properties": {
    "addr:full":"19 Salisbury Ave Valley View SA 5093",
    "addr:housenumber":"19",
    "addr:postcode":"5093",
    "addr:street":"Salisbury Ave",
    "iso:country":"AU",
    "sg:address":"19 Salisbury Ave",
    "sg:city":"Valley View",
    "sg:classifiers":[
        {
            "category":"Building & Trades",
            "subcategory":"Cleaning & Sanitation",
            "type":"Services"
        }
    ],
    "sg:phone":"+61 400 006 674",
    "sg:postcode":"5093",
    "sg:province":"SA",
    "sg:tags":[
        "window"
    ],
    "wof:name":"Cosmic Image Cleaning",
    "wof:placetype":"venue"
},
  "geometry": {"coordinates":[138.67202758799999,-34.8389129639],"type":"Point"}
}