{
  "type": "Feature",
  "properties": {
    "iso:country":"AU",
    "sg:address":"Dawson Hwy",
    "sg:city":"Biloela",
    "sg:classifiers":[
        {
            "category":"Retail",
            "subcategory":"Auto Repair",
            "type":"Services"
        }
    ],
    "sg:phone":"+61 7 4992 4193",
    "sg:postcode":"4715",
    "sg:province":"QLD",
    "sg:tags":[
        "repairer",
        "motor",
        "engineer"
    ],
    "wof:name":"Callide Dawson Automatics",
    "wof:placetype":"venue"
},
  "geometry": {"coordinates":[150.512207031,-24.4028396606],"type":"Point"}
}