{
  "type": "Feature",
  "properties": {
    "iso:country":"AU",
    "sg:address":"524 Elgar Rd",
    "sg:city":"Box Hill North",
    "sg:classifiers":[
        {
            "category":"Education",
            "subcategory":"Kindergarten",
            "type":"Public Place"
        }
    ],
    "sg:phone":"+61 3 9890 8979",
    "sg:postcode":"3129",
    "sg:province":"VIC",
    "sg:tags":[
        "pre-schools"
    ],
    "wof:name":"Parkside Pre-School Centre",
    "wof:placetype":"venue"
},
  "geometry": {"coordinates":[145.11654663100001,-37.8094024658],"type":"Point"}
}