{
  "type": "Feature",
  "properties": {
    "iso:country":"AU",
    "sg:address":"5- 9 Finlay Rd",
    "sg:city":"Goulburn",
    "sg:classifiers":[
        {
            "category":"Retail",
            "subcategory":"Storage",
            "type":"Services"
        }
    ],
    "sg:phone":"+61 2 4821 3788",
    "sg:postcode":"2580",
    "sg:province":"NSW",
    "wof:name":"Moffatt's Security Storage",
    "wof:placetype":"venue"
},
  "geometry": {"coordinates":[149.708694458,-34.7707061768],"type":"Point"}
}