{
  "type": "Feature",
  "properties": {
    "addr:full":"126 Majors Bay Rd Concord NSW 2137",
    "addr:housenumber":"126",
    "addr:postcode":"2137",
    "addr:street":"Majors Bay Rd",
    "iso:country":"AU",
    "sg:address":"126 Majors Bay Rd",
    "sg:city":"Concord",
    "sg:classifiers":[
        {
            "category":"Health Services",
            "subcategory":"Dentist",
            "type":"Services"
        }
    ],
    "sg:phone":"+61 2 9743 2054",
    "sg:postcode":"2137",
    "sg:province":"NSW",
    "wof:name":"Concord Dental Care",
    "wof:placetype":"venue"
},
  "geometry": {"coordinates":[151.10292053200001,-33.8549423218],"type":"Point"}
}