{
  "type": "Feature",
  "properties": {
    "addr:full":"245 Cotham Rd Kew VIC 3101",
    "addr:housenumber":"245",
    "addr:postcode":"3101",
    "addr:street":"Cotham Rd",
    "iso:country":"AU",
    "sg:address":"245 Cotham Rd",
    "sg:city":"Kew",
    "sg:classifiers":[
        {
            "category":"Retail",
            "subcategory":"Auto Repair",
            "type":"Services"
        }
    ],
    "sg:phone":"+61 3 9817 1111",
    "sg:postcode":"3101",
    "sg:province":"VIC",
    "sg:tags":[
        "repairer",
        "motor",
        "engineer"
    ],
    "wof:name":"Kmart Tyre & Auto Service",
    "wof:placetype":"venue"
},
  "geometry": {"coordinates":[145.05111694300001,-37.8090667725],"type":"Point"}
}