{
  "type": "Feature",
  "properties": {
    "addr:full":"Charles St Mooroopna VIC 3629",
    "addr:postcode":"3629",
    "addr:street":"Charles St",
    "iso:country":"AU",
    "sg:address":"Charles St",
    "sg:city":"Mooroopna",
    "sg:classifiers":[
        {
            "category":"Personal",
            "subcategory":"Beauty Salon",
            "type":"Services"
        }
    ],
    "sg:phone":"+61 3 5825 4811",
    "sg:postcode":"3629",
    "sg:province":"VIC",
    "wof:name":"Dominique Rachelle's World Of Beauty",
    "wof:placetype":"venue"
},
  "geometry": {"coordinates":[145.34036254899999,-36.3993339539],"type":"Point"}
}