{
  "type": "Feature",
  "properties": {
    "addr:full":"46 Cyril St Bassendean WA 6054",
    "addr:housenumber":"46",
    "addr:postcode":"6054",
    "addr:street":"Cyril St",
    "iso:country":"AU",
    "sg:address":"46 Cyril St",
    "sg:city":"Bassendean",
    "sg:classifiers":[
        {
            "category":"Banks & Credit Unions",
            "subcategory":"Financial Services",
            "type":"Services"
        }
    ],
    "sg:phone":"+61 8 9379 1080",
    "sg:postcode":"6054",
    "sg:province":"WA",
    "sg:tags":[
        "franchising"
    ],
    "wof:name":"Rosies Chicken",
    "wof:placetype":"venue"
},
  "geometry": {"coordinates":[115.940223694,-31.9109134674],"type":"Point"}
}