{
  "type": "Feature",
  "properties": {
    "iso:country":"AU",
    "sg:address":"920 Kilmore-Glenaroua Rd",
    "sg:city":"Broadford",
    "sg:classifiers":[
        {
            "category":"Professional",
            "subcategory":"Business Services",
            "type":"Services"
        }
    ],
    "sg:phone":"+61 1300 362 502",
    "sg:postcode":"3658",
    "sg:province":"VIC",
    "sg:tags":[
        "broker"
    ],
    "wof:name":"Australian Business Listing Exchange",
    "wof:placetype":"venue"
},
  "geometry": {"coordinates":[144.98350524899999,-37.288684845],"type":"Point"}
}