{
  "type": "Feature",
  "properties": {
    "addr:full":"Mosman Park Shopping Centre Shop 2/ 50 Harvey St Mosman Park WA 6012",
    "addr:housenumber":"shop 2 / 50",
    "addr:postcode":"6012",
    "addr:street":"Harvey St",
    "iso:country":"AU",
    "sg:address":"Mosman Park Shopping Centre Shop 2/ 50 Harvey St",
    "sg:city":"Mosman Park",
    "sg:classifiers":[
        {
            "category":"Personal",
            "subcategory":"Hair Removal",
            "type":"Services"
        }
    ],
    "sg:phone":"+61 8 9384 0011",
    "sg:postcode":"6012",
    "sg:province":"WA",
    "wof:name":"Advance Beauty Concepts Medi Spa",
    "wof:placetype":"venue"
},
  "geometry": {"coordinates":[115.76210021999999,-32.0085334778],"type":"Point"}
}