{
  "type": "Feature",
  "properties": {
    "addr:full":"Shop 17/ 1007 North East Rd Modbury SA 5092",
    "addr:housenumber":"shop 17 / 1007",
    "addr:postcode":"5092",
    "addr:street":"North East Rd",
    "iso:country":"AU",
    "sg:address":"Shop 17/ 1007 North East Rd",
    "sg:city":"Modbury",
    "sg:classifiers":[
        {
            "category":"Food & Beverages",
            "subcategory":"Specialty",
            "type":"Retail Goods"
        }
    ],
    "sg:phone":"+61 8 8396 1145",
    "sg:postcode":"5092",
    "sg:province":"SA",
    "sg:tags":[
        "product",
        "health"
    ],
    "wof:name":"Cohens Lifestyle Clinic",
    "wof:placetype":"venue"
},
  "geometry": {"coordinates":[138.69456481899999,-34.827671051],"type":"Point"}
}