{
  "type": "Feature",
  "properties": {
    "iso:country":"AU",
    "sg:address":"175 Bains Rd",
    "sg:city":"Woodcroft",
    "sg:classifiers":[
        {
            "category":"Organizations",
            "subcategory":"Non-profit Organization",
            "type":"Services"
        }
    ],
    "sg:phone":"+61 8 8325 3522",
    "sg:postcode":"5162",
    "sg:province":"SA",
    "sg:tags":[
        "support",
        "disability",
        "organisation"
    ],
    "wof:name":"Family Advocacy Incorporated",
    "wof:placetype":"venue"
},
  "geometry": {"coordinates":[138.55157470699999,-35.1141738892],"type":"Point"}
}