{
  "type": "Feature",
  "properties": {
    "addr:full":"Main St Beenleigh QLD 4207",
    "addr:postcode":"4207",
    "addr:street":"Main St",
    "iso:country":"AU",
    "sg:address":"Main St",
    "sg:city":"Beenleigh",
    "sg:classifiers":[
        {
            "category":"Government",
            "subcategory":"Post Office",
            "type":"Public Place"
        }
    ],
    "sg:phone":"+61 13 11 18",
    "sg:postcode":"4207",
    "sg:province":"QLD",
    "sg:tags":[
        "postal"
    ],
    "wof:name":"Beenleigh Post Office",
    "wof:placetype":"venue"
},
  "geometry": {"coordinates":[153.20216369600001,-27.7162704468],"type":"Point"}
}