{
  "type": "Feature",
  "properties": {
    "addr:full":"88d Moreing Rd Attadale WA 6156",
    "addr:housenumber":"88d",
    "addr:postcode":"6156",
    "addr:street":"Moreing Rd",
    "iso:country":"AU",
    "sg:address":"88d Moreing Rd",
    "sg:city":"Attadale",
    "sg:classifiers":[
        {
            "category":"Banks & Credit Unions",
            "subcategory":"Investment Brokerage",
            "type":"Services"
        }
    ],
    "sg:phone":"+61 8 9330 2555",
    "sg:postcode":"6156",
    "sg:province":"WA",
    "sg:tags":[
        "finance",
        "broker"
    ],
    "wof:name":"Leeuwin Finance",
    "wof:placetype":"venue"
},
  "geometry": {"coordinates":[115.794991,-32.031277],"type":"Point"}
}