{
  "type": "Feature",
  "properties": {
    "addr:full":"35 Barlee St Busselton WA 6280",
    "addr:housenumber":"35",
    "addr:postcode":"6280",
    "addr:street":"Barlee St",
    "iso:country":"AU",
    "sg:address":"35 Barlee St",
    "sg:city":"Busselton",
    "sg:classifiers":[
        {
            "category":"Manufacturing",
            "subcategory":"Motor Vehicles & Parts",
            "type":"Manufacturing & Wholesale Goods"
        }
    ],
    "sg:phone":"+61 8 9751 5990",
    "sg:postcode":"6280",
    "sg:province":"WA",
    "sg:tags":[
        "replacement"
    ],
    "wof:name":"Busselton Bearing Services",
    "wof:placetype":"venue"
},
  "geometry": {"coordinates":[115.34654998800001,-33.6608428955],"type":"Point"}
}