{
  "type": "Feature",
  "properties": {
    "addr:full":"Unit 233/ 1 Serisier Ave Main Beach QLD 4217",
    "addr:housenumber":"/ 1",
    "addr:postcode":"4217",
    "addr:street":"Serisier Ave",
    "iso:country":"AU",
    "sg:address":"Unit 233/ 1 Serisier Ave",
    "sg:city":"Main Beach",
    "sg:classifiers":[
        {
            "category":"Professional",
            "subcategory":"Computer Services",
            "type":"Services"
        }
    ],
    "sg:phone":"+61 1300 662 084",
    "sg:postcode":"4217",
    "sg:province":"QLD",
    "sg:tags":[
        "consultant",
        "system"
    ],
    "wof:name":"Verve Suppliers",
    "wof:placetype":"venue"
},
  "geometry": {"coordinates":[153.42689514200001,-27.982011795],"type":"Point"}
}