{
  "type": "Feature",
  "properties": {
    "addr:full":"Unit 4, Downtown Estate Cawdor Rd Camden NSW 2570",
    "addr:postcode":"2570",
    "addr:street":"Cawdor Rd",
    "iso:country":"AU",
    "sg:address":"Unit 4, Downtown Estate Cawdor Rd",
    "sg:city":"Camden",
    "sg:classifiers":[
        {
            "category":"Professional",
            "subcategory":"Printing & Photocopies",
            "type":"Services"
        }
    ],
    "sg:phone":"+61 2 4655 2281",
    "sg:postcode":"2570",
    "sg:province":"NSW",
    "sg:tags":[
        "rubber",
        "stamp",
        "metal"
    ],
    "wof:name":"Camden Printing Pty Ltd",
    "wof:placetype":"venue"
},
  "geometry": {"coordinates":[150.69302368199999,-34.0558624268],"type":"Point"}
}