{
  "type": "Feature",
  "properties": {
    "addr:full":"180 Stoney Rise Rd Devonport TAS 7310",
    "addr:housenumber":"180",
    "addr:postcode":"7310",
    "addr:street":"Stoney Rise Rd",
    "iso:country":"AU",
    "sg:address":"180 Stoney Rise Rd",
    "sg:city":"Devonport",
    "sg:classifiers":[
        {
            "category":"Building & Trades",
            "subcategory":"Construction",
            "type":"Services"
        }
    ],
    "sg:phone":"+61 3 6423 5474",
    "sg:postcode":"7310",
    "sg:province":"TAS",
    "sg:tags":[
        "joinery"
    ],
    "wof:name":"Prestige Joinery",
    "wof:placetype":"venue"
},
  "geometry": {"coordinates":[146.32244873100001,-41.1851234436],"type":"Point"}
}