{
  "type": "Feature",
  "properties": {
    "iso:country":"AU",
    "sg:address":"25 Challis Ave",
    "sg:city":"Potts Point",
    "sg:classifiers":[
        {
            "category":"Professional",
            "subcategory":"Employment Agencies",
            "type":"Services"
        }
    ],
    "sg:phone":"+61 2 9332 2422",
    "sg:postcode":"2011",
    "sg:province":"NSW",
    "sg:tags":[
        "model"
    ],
    "wof:name":"Priscilla's Model Management Pty Ltd",
    "wof:placetype":"venue"
},
  "geometry": {"coordinates":[151.22401428200001,-33.8688926697],"type":"Point"}
}