{
  "type": "Feature",
  "properties": {
    "addr:full":"120 McKenzie St Melton VIC 3337",
    "addr:housenumber":"120",
    "addr:postcode":"3337",
    "addr:street":"Mckenzie St",
    "iso:country":"AU",
    "sg:address":"120 McKenzie St",
    "sg:city":"Melton",
    "sg:classifiers":[
        {
            "category":"Professional",
            "subcategory":"Accounting & Tax Preparation",
            "type":"Services"
        }
    ],
    "sg:phone":"+61 3 9746 9311",
    "sg:postcode":"3337",
    "sg:province":"VIC",
    "sg:tags":[
        "consultant",
        "taxation"
    ],
    "wof:name":"Morbak Accounting & Taxation Services",
    "wof:placetype":"venue"
},
  "geometry": {"coordinates":[144.58079499999999,-37.684578],"type":"Point"}
}