{
  "type": "Feature",
  "properties": {
    "addr:full":"16 Dowsett St South Geelong VIC 3220",
    "addr:housenumber":"16",
    "addr:postcode":"3220",
    "addr:street":"Dowsett St",
    "iso:country":"AU",
    "sg:address":"16 Dowsett St",
    "sg:city":"South Geelong",
    "sg:classifiers":[
        {
            "category":"Home & Garden",
            "subcategory":"Hardware",
            "type":"Retail Goods"
        }
    ],
    "sg:phone":"+61 3 5222 7244",
    "sg:postcode":"3220",
    "sg:province":"VIC",
    "sg:tags":[
        "plumber",
        "supply"
    ],
    "wof:name":"Green Taps Geelong",
    "wof:placetype":"venue"
},
  "geometry": {"coordinates":[144.368301,-38.167713],"type":"Point"}
}