{
  "type": "Feature",
  "properties": {
    "iso:country":"AU",
    "sg:address":"50 Oxford Rd",
    "sg:city":"Ingleburn",
    "sg:classifiers":[
        {
            "category":"Manufacturing",
            "subcategory":"Motor Vehicles & Parts",
            "type":"Manufacturing & Wholesale Goods"
        }
    ],
    "sg:phone":"+61 2 9829 2846",
    "sg:postcode":"2565",
    "sg:province":"NSW",
    "sg:tags":[
        "replacement"
    ],
    "wof:name":"Viking Car Spares & Accessories",
    "wof:placetype":"venue"
},
  "geometry": {"coordinates":[150.86724853499999,-33.999206543],"type":"Point"}
}