{
  "type": "Feature",
  "properties": {
    "addr:full":"4 289 Brunker Yd Adamstown NSW 2289",
    "addr:housenumber":"4 289",
    "addr:postcode":"2289",
    "addr:street":"Brunker Yd",
    "iso:country":"AU",
    "sg:address":"4 289 Brunker Yd",
    "sg:city":"Adamstown",
    "sg:classifiers":[
        {
            "category":"Shopping",
            "subcategory":"Computers & Home Electronics",
            "type":"Retail Goods"
        }
    ],
    "sg:phone":"+61 2 4952 4988",
    "sg:postcode":"2289",
    "sg:province":"NSW",
    "sg:tags":[
        "hardware",
        "equipment"
    ],
    "wof:name":"Winner Computers",
    "wof:placetype":"venue"
},
  "geometry": {"coordinates":[151.72625732399999,-32.9332733154],"type":"Point"}
}