{
  "type": "Feature",
  "properties": {
    "iso:country":"AU",
    "sg:address":"169- 171 Northbourne Rd",
    "sg:city":"Campbellfield",
    "sg:classifiers":[
        {
            "category":"Wholesale",
            "subcategory":"Machinery & Supplies",
            "type":"Manufacturing & Wholesale Goods"
        }
    ],
    "sg:phone":"+61 3 9305 4600",
    "sg:postcode":"3061",
    "sg:province":"VIC",
    "sg:tags":[
        "equipment",
        "hydraulic"
    ],
    "wof:name":"H.I.S. Hose Pty Ltd",
    "wof:placetype":"venue"
},
  "geometry": {"coordinates":[144.96275329599999,-37.6486778259],"type":"Point"}
}