{
  "type": "Feature",
  "properties": {
    "addr:full":"Boothby St Drayton QLD 4350",
    "addr:postcode":"4350",
    "addr:street":"Boothby St",
    "iso:country":"AU",
    "sg:address":"Boothby St",
    "sg:city":"Drayton",
    "sg:classifiers":[
        {
            "category":"Manufacturing",
            "subcategory":"Motor Vehicles & Parts",
            "type":"Manufacturing & Wholesale Goods"
        }
    ],
    "sg:phone":"+61 7 4630 1699",
    "sg:postcode":"4350",
    "sg:province":"QLD",
    "sg:tags":[
        "replacement"
    ],
    "wof:name":"Renault-Peugeot Parts",
    "wof:placetype":"venue"
},
  "geometry": {"coordinates":[151.91395600000001,-27.590815],"type":"Point"}
}