{
  "type": "Feature",
  "properties": {
    "iso:country":"AU",
    "sg:address":"16 Wahroonga St",
    "sg:city":"Cowra",
    "sg:classifiers":[
        {
            "category":"Building & Trades",
            "subcategory":"Construction",
            "type":"Services"
        }
    ],
    "sg:phone":"+61 427 406 044",
    "sg:postcode":"2794",
    "sg:province":"NSW",
    "sg:tags":[
        "earth",
        "excavating",
        "moving",
        "contractor"
    ],
    "wof:name":"Les Gee Excavations",
    "wof:placetype":"venue"
},
  "geometry": {"coordinates":[148.69056701700001,-33.8345909119],"type":"Point"}
}