{
  "type": "Feature",
  "properties": {
    "addr:full":"35A Herbert St Bowen QLD 4805",
    "addr:housenumber":"35a",
    "addr:postcode":"4805",
    "addr:street":"Herbert St",
    "iso:country":"AU",
    "sg:address":"35A Herbert St",
    "sg:city":"Bowen",
    "sg:classifiers":[
        {
            "category":"Insurance",
            "subcategory":"Insurance Agent",
            "type":"Services"
        }
    ],
    "sg:phone":"+61 7 4786 2766",
    "sg:postcode":"4805",
    "sg:province":"QLD",
    "wof:name":"Karen Clarke CFP",
    "wof:placetype":"venue"
},
  "geometry": {"coordinates":[148.24093627900001,-20.0033893585],"type":"Point"}
}