{
  "type": "Feature",
  "properties": {
    "addr:full":"Unit 6 / 21A Macpherson St Warriewood NSW 2102",
    "addr:housenumber":"/ 21a",
    "addr:postcode":"2102",
    "addr:street":"Macpherson St",
    "iso:country":"AU",
    "sg:address":"Unit 6 / 21A Macpherson St",
    "sg:city":"Warriewood",
    "sg:classifiers":[
        {
            "category":"Retail",
            "subcategory":"Veterinary Services",
            "type":"Services"
        }
    ],
    "sg:phone":"+61 405 661 186",
    "sg:postcode":"2102",
    "sg:province":"NSW",
    "sg:tags":[
        "surgeon"
    ],
    "wof:name":"Horse Drenching",
    "wof:placetype":"venue"
},
  "geometry": {"coordinates":[151.29780600000001,-33.689911],"type":"Point"}
}