{
  "type": "Feature",
  "properties": {
    "iso:country":"AU",
    "sg:address":"Unit 6 / 21A Macpherson St",
    "sg:city":"Warriewood",
    "sg:classifiers":[
        {
            "category":"Retail",
            "subcategory":"Veterinary Services",
            "type":"Services"
        }
    ],
    "sg:phone":"+61 405 661 186",
    "sg:postcode":"2102",
    "sg:province":"NSW",
    "sg:tags":[
        "surgeon"
    ],
    "wof:name":"Horse Drenching",
    "wof:placetype":"venue"
},
  "geometry": {"coordinates":[151.297806,-33.689911],"type":"Point"}
}