{
  "type": "Feature",
  "properties": {
    "addr:full":"158 Ardross St Mt Pleasant WA 6153",
    "addr:housenumber":"158",
    "addr:postcode":"6153",
    "addr:street":"Ardross St",
    "iso:country":"AU",
    "sg:address":"158 Ardross St",
    "sg:city":"Mt Pleasant",
    "sg:classifiers":[
        {
            "category":"Professional",
            "type":"Services"
        }
    ],
    "sg:phone":"+61 8 9316 8078",
    "sg:postcode":"6153",
    "sg:province":"WA",
    "sg:tags":[
        "quality",
        "assurance"
    ],
    "wof:name":"Keystone Q.A. Services",
    "wof:placetype":"venue"
},
  "geometry": {"coordinates":[115.843971,-32.023048],"type":"Point"}
}