{
  "type": "Feature",
  "properties": {
    "iso:country":"AU",
    "sg:address":"Unit 1, 47 Prince William Drv",
    "sg:city":"Seven Hills",
    "sg:classifiers":[
        {
            "category":"Autos & Motor Vehicles",
            "subcategory":"Auto Supplies",
            "type":"Retail Goods"
        }
    ],
    "sg:phone":"+61 2 9674 3833",
    "sg:postcode":"2147",
    "sg:province":"NSW",
    "sg:tags":[
        "part",
        "cycles",
        "accessory"
    ],
    "wof:name":"Motor Cycle Disposals",
    "wof:placetype":"venue"
},
  "geometry": {"coordinates":[150.960494995,-33.7775993347],"type":"Point"}
}