{
  "type": "Feature",
  "properties": {
    "iso:country":"AU",
    "sg:address":"Unit 4/ 23 Stennett Rd",
    "sg:city":"Ingleburn",
    "sg:classifiers":[
        {
            "category":"Manufacturing",
            "subcategory":"Paper Products",
            "type":"Manufacturing & Wholesale Goods"
        }
    ],
    "sg:phone":"+61 2 9892 2598",
    "sg:postcode":"2565",
    "sg:province":"NSW",
    "sg:tags":[
        "wholesaler",
        "mfrs"
    ],
    "wof:name":"Benny Paper Supplies",
    "wof:placetype":"venue"
},
  "geometry": {"coordinates":[150.852493286,-34.0034141541],"type":"Point"}
}