{
  "type": "Feature",
  "properties": {
    "iso:country":"AU",
    "sg:address":"171 Riding Rd",
    "sg:city":"Hawthorne",
    "sg:classifiers":[
        {
            "category":"Health Services",
            "subcategory":"Doctor",
            "type":"Services"
        }
    ],
    "sg:phone":"+61 7 3399 5444",
    "sg:postcode":"4171",
    "sg:province":"QLD",
    "sg:tags":[
        "medical",
        "practitioner"
    ],
    "wof:name":"Hawthorne Clinic",
    "wof:placetype":"venue"
},
  "geometry": {"coordinates":[153.06367492699999,-27.4619884491],"type":"Point"}
}