{
  "type": "Feature",
  "properties": {
    "iso:country":"AU",
    "sg:address":"1 Warraba Rd",
    "sg:city":"Narrabeen",
    "sg:classifiers":[
        {
            "category":"Home & Garden",
            "subcategory":"Building Materials",
            "type":"Retail Goods"
        }
    ],
    "sg:phone":"+61 2 9970 8359",
    "sg:postcode":"2101",
    "sg:province":"NSW",
    "sg:tags":[
        "insulation"
    ],
    "wof:name":"No 1 Roofing & Building Supplies",
    "wof:placetype":"venue"
},
  "geometry": {"coordinates":[151.29466199999999,-33.702351],"type":"Point"}
}