{
  "type": "Feature",
  "properties": {
    "addr:full":"Unit 2, 49 Gavenlock Rd Tuggerah NSW 2259",
    "addr:housenumber":"49",
    "addr:postcode":"2259",
    "addr:street":"Gavenlock Rd",
    "iso:country":"AU",
    "sg:address":"Unit 2, 49 Gavenlock Rd",
    "sg:city":"Tuggerah",
    "sg:classifiers":[
        {
            "category":"Communications",
            "type":"Services"
        }
    ],
    "sg:phone":"+61 2 4355 1599",
    "sg:postcode":"2259",
    "sg:province":"NSW",
    "sg:tags":[
        "equipment",
        "radio"
    ],
    "wof:name":"Karera Communications",
    "wof:placetype":"venue"
},
  "geometry": {"coordinates":[151.41679382300001,-33.3014450073],"type":"Point"}
}