{
  "type": "Feature",
  "properties": {
    "addr:full":"149 Forrest St Boulder WA 6432",
    "addr:housenumber":"149",
    "addr:postcode":"6432",
    "addr:street":"Forrest St",
    "iso:country":"AU",
    "sg:address":"149 Forrest St",
    "sg:city":"Boulder",
    "sg:classifiers":[
        {
            "category":"Mining & Drilling",
            "type":"Manufacturing & Wholesale Goods"
        }
    ],
    "sg:phone":"+61 8 9080 9100",
    "sg:postcode":"6432",
    "sg:province":"WA",
    "sg:tags":[
        "equipment",
        "quarrying",
        "supply"
    ],
    "wof:name":"Ausdrill Ltd",
    "wof:placetype":"venue"
},
  "geometry": {"coordinates":[121.481369019,-30.7853546143],"type":"Point"}
}