{
  "type": "Feature",
  "properties": {
    "addr:full":"11 School Rd Geeveston TAS 7116",
    "addr:housenumber":"11",
    "addr:postcode":"7116",
    "addr:street":"School Rd",
    "iso:country":"AU",
    "sg:address":"11 School Rd",
    "sg:city":"Geeveston",
    "sg:classifiers":[
        {
            "category":"Communications",
            "subcategory":"News Services",
            "type":"Services"
        }
    ],
    "sg:phone":"+61 3 6297 0039",
    "sg:postcode":"7116",
    "sg:province":"TAS",
    "sg:tags":[
        "information",
        "tourist",
        "attractions"
    ],
    "wof:name":"Southern Design Centre",
    "wof:placetype":"venue"
},
  "geometry": {"coordinates":[146.92413330100001,-43.1663818359],"type":"Point"}
}