{
  "type": "Feature",
  "properties": {
    "iso:country":"AU",
    "sg:address":"2282 Warragul-Korumburra Rd",
    "sg:city":"Seaview",
    "sg:classifiers":[
        {
            "category":"Professional",
            "subcategory":"Management & Consulting",
            "type":"Services"
        }
    ],
    "sg:phone":"+61 3 5659 5272",
    "sg:postcode":"3821",
    "sg:province":"VIC",
    "sg:tags":[
        "consultant",
        "migration"
    ],
    "wof:name":"Dennis R Heslin",
    "wof:placetype":"venue"
},
  "geometry": {"coordinates":[145.93309,-38.27972],"type":"Point"}
}