{
  "type": "Feature",
  "properties": {
    "iso:country":"AU",
    "sg:address":"Shop 88 Sunnybank Plaza Shopping Centre",
    "sg:city":"Sunnybank",
    "sg:classifiers":[
        {
            "category":"Food & Beverages",
            "subcategory":"Supermarket",
            "type":"Retail Goods"
        }
    ],
    "sg:phone":"+61 7 3344 5886",
    "sg:postcode":"4109",
    "sg:province":"QLD",
    "sg:tags":[
        "grocery",
        "store"
    ],
    "wof:name":"Formosa Asian Markets",
    "wof:placetype":"venue"
},
  "geometry": {"coordinates":[153.06663513199999,-27.5967483521],"type":"Point"}
}