{
  "type": "Feature",
  "properties": {
    "iso:country":"AU",
    "sg:address":"47 Anakie St",
    "sg:city":"Emerald",
    "sg:classifiers":[
        {
            "category":"Health Services",
            "subcategory":"Doctor",
            "type":"Services"
        }
    ],
    "sg:phone":"+61 7 4987 4100",
    "sg:postcode":"4720",
    "sg:province":"QLD",
    "sg:tags":[
        "medical",
        "practitioner"
    ],
    "wof:name":"Belonogoff Michael",
    "wof:placetype":"venue"
},
  "geometry": {"coordinates":[148.16026299999999,-23.523762],"type":"Point"}
}