{
  "type": "Feature",
  "properties": {
    "addr:full":"130 Horseshoe Bend Rd Belmont VIC 3216",
    "addr:housenumber":"130",
    "addr:postcode":"3216",
    "addr:street":"Horseshoe Bend Rd",
    "iso:country":"AU",
    "sg:address":"130 Horseshoe Bend Rd",
    "sg:city":"Belmont",
    "sg:classifiers":[
        {
            "category":"Home & Garden",
            "subcategory":"Building Materials",
            "type":"Retail Goods"
        }
    ],
    "sg:phone":"+61 3 5241 3964",
    "sg:postcode":"3216",
    "sg:province":"VIC",
    "sg:tags":[
        "balustrading"
    ],
    "wof:name":"The Ultimate Handrail Company",
    "wof:placetype":"venue"
},
  "geometry": {"coordinates":[144.36405944800001,-38.1899452209],"type":"Point"}
}