{
  "type": "Feature",
  "properties": {
    "iso:country":"AU",
    "sg:address":"146 Charters Towers Rd",
    "sg:city":"Hermit Park",
    "sg:classifiers":[
        {
            "category":"Real Estate",
            "subcategory":"Real Estate Agent",
            "type":"Services"
        }
    ],
    "sg:phone":"+61 7 4771 6477",
    "sg:postcode":"4812",
    "sg:province":"QLD",
    "wof:name":"Professionals Walducks Real Estate",
    "wof:placetype":"venue"
},
  "geometry": {"coordinates":[146.799622,-19.279495],"type":"Point"}
}