{
  "type": "Feature",
  "properties": {
    "iso:country":"AU",
    "sg:address":"245 Hartley St",
    "sg:city":"Portsmith",
    "sg:classifiers":[
        {
            "category":"Retail",
            "subcategory":"Auto Repair",
            "type":"Services"
        }
    ],
    "sg:phone":"+61 7 4035 6789",
    "sg:postcode":"4870",
    "sg:province":"QLD",
    "sg:tags":[
        "repairer",
        "motor",
        "engineer"
    ],
    "wof:name":"B & B Automotive",
    "wof:placetype":"venue"
},
  "geometry": {"coordinates":[145.76203918499999,-16.9392471313],"type":"Point"}
}