{
  "type": "Feature",
  "properties": {
    "addr:full":"8 Anthony St Yagoona NSW 2199",
    "addr:housenumber":"8",
    "addr:postcode":"2199",
    "addr:street":"Anthony St",
    "iso:country":"AU",
    "sg:address":"8 Anthony St",
    "sg:city":"Yagoona",
    "sg:classifiers":[
        {
            "category":"Building & Trades",
            "subcategory":"Construction",
            "type":"Services"
        }
    ],
    "sg:phone":"+61 414 300 050",
    "sg:postcode":"2199",
    "sg:province":"NSW",
    "sg:tags":[
        "contractor"
    ],
    "wof:name":"Telese Construction Company",
    "wof:placetype":"venue"
},
  "geometry": {"coordinates":[151.03196700000001,-33.898567],"type":"Point"}
}