{
  "type": "Feature",
  "properties": {
    "addr:full":"5 Pirie St Fyshwick ACT 2609",
    "addr:housenumber":"5",
    "addr:postcode":"2609",
    "addr:street":"Pirie St",
    "iso:country":"AU",
    "sg:address":"5 Pirie St",
    "sg:city":"Fyshwick",
    "sg:classifiers":[
        {
            "category":"Professional",
            "subcategory":"Detective & Security Services",
            "type":"Services"
        }
    ],
    "sg:phone":"+61 2 6280 4443",
    "sg:postcode":"2609",
    "sg:province":"ACT",
    "sg:tags":[
        "equipment",
        "window",
        "doors"
    ],
    "wof:name":"Watson Blinds And Awnings",
    "wof:placetype":"venue"
},
  "geometry": {"coordinates":[149.169998169,-35.3256645203],"type":"Point"}
}