{
  "type": "Feature",
  "properties": {
    "addr:full":"42 Beverly Hills Drv Templestowe VIC 3106",
    "addr:housenumber":"42",
    "addr:postcode":"3106",
    "addr:street":"Beverly Hills Drv",
    "iso:country":"AU",
    "sg:address":"42 Beverly Hills Drv",
    "sg:city":"Templestowe",
    "sg:classifiers":[
        {
            "category":"Health Services",
            "subcategory":"Doctor",
            "type":"Services"
        }
    ],
    "sg:phone":"+61 3 9846 2333",
    "sg:postcode":"3106",
    "sg:province":"VIC",
    "sg:tags":[
        "medical",
        "practitioner"
    ],
    "wof:name":"King Peter",
    "wof:placetype":"venue"
},
  "geometry": {"coordinates":[145.16705322300001,-37.7586174011],"type":"Point"}
}