{
  "type": "Feature",
  "properties": {
    "iso:country":"AU",
    "sg:address":"11 Carrathool Ave",
    "sg:city":"Rosebud South",
    "sg:classifiers":[
        {
            "category":"Retail",
            "subcategory":"Car Wash",
            "type":"Services"
        }
    ],
    "sg:phone":"+61 402 023 681",
    "sg:postcode":"3939",
    "sg:province":"VIC",
    "sg:tags":[
        "truck",
        "cleaning"
    ],
    "wof:name":"Steve's Complete Car Care",
    "wof:placetype":"venue"
},
  "geometry": {"coordinates":[144.93161010700001,-38.3816604614],"type":"Point"}
}