{
  "type": "Feature",
  "properties": {
    "iso:country":"AU",
    "sg:address":"34 Pickering St",
    "sg:city":"Ouyen",
    "sg:classifiers":[
        {
            "category":"Building & Trades",
            "subcategory":"Plumbing",
            "type":"Services"
        }
    ],
    "sg:phone":"+61 3 5092 1537",
    "sg:postcode":"3490",
    "sg:province":"VIC",
    "sg:tags":[
        "plumber",
        "gasfitters"
    ],
    "wof:name":"Ouyen & District Plumbing Services",
    "wof:placetype":"venue"
},
  "geometry": {"coordinates":[142.31599426299999,-35.070148468],"type":"Point"}
}