{
  "type": "Feature",
  "properties": {
    "addr:full":"31a Greenacre Rd Greenacre NSW 2190",
    "addr:housenumber":"31a",
    "addr:postcode":"2190",
    "addr:street":"Greenacre Rd",
    "iso:country":"AU",
    "sg:address":"31a Greenacre Rd",
    "sg:city":"Greenacre",
    "sg:classifiers":[
        {
            "category":"Education",
            "subcategory":"Kindergarten",
            "type":"Public Place"
        }
    ],
    "sg:phone":"+61 2 9709 5378",
    "sg:postcode":"2190",
    "sg:province":"NSW",
    "sg:tags":[
        "pre-schools"
    ],
    "wof:name":"Mickey's World Child Care Centre",
    "wof:placetype":"venue"
},
  "geometry": {"coordinates":[151.05380199999999,-33.912125],"type":"Point"}
}