{
  "type": "Feature",
  "properties": {
    "iso:country":"AU",
    "sg:address":"51 Horace St St",
    "sg:city":"Ives",
    "sg:classifiers":[
        {
            "category":"Professional",
            "subcategory":"Art Services",
            "type":"Services"
        }
    ],
    "sg:phone":"+61 2 9402 5505",
    "sg:postcode":"2075",
    "sg:province":"NSW",
    "sg:tags":[
        "picture",
        "frame",
        "framing"
    ],
    "wof:name":"The Frame Maker",
    "wof:placetype":"venue"
},
  "geometry": {"coordinates":[151.165161133,-33.7396240234],"type":"Point"}
}