{
  "type": "Feature",
  "properties": {
    "iso:country":"AU",
    "sg:address":"5/ 47 Anderson St",
    "sg:city":"Fortitude Valley",
    "sg:classifiers":[
        {
            "category":"Shopping",
            "subcategory":"Clothing, Apparel, & Fashions",
            "type":"Retail Goods"
        }
    ],
    "sg:phone":"+61 7 3257 7644",
    "sg:postcode":"4006",
    "sg:province":"QLD",
    "sg:tags":[
        "uniform"
    ],
    "wof:name":"Five Star Uniforms",
    "wof:placetype":"venue"
},
  "geometry": {"coordinates":[153.03140258799999,-27.4525413513],"type":"Point"}
}