{
  "type": "Feature",
  "properties": {
    "addr:full":"49 Ballard St Yarraville VIC 3013",
    "addr:housenumber":"49",
    "addr:postcode":"3013",
    "addr:street":"Ballard St",
    "iso:country":"AU",
    "sg:address":"49 Ballard St",
    "sg:city":"Yarraville",
    "sg:classifiers":[
        {
            "category":"Building & Trades",
            "subcategory":"Cleaning & Sanitation",
            "type":"Services"
        }
    ],
    "sg:phone":"+61 3 9325 1482",
    "sg:postcode":"3013",
    "sg:province":"VIC",
    "sg:tags":[
        "cleaner",
        "repairer",
        "roof"
    ],
    "wof:name":"Barkshire Roofing Services",
    "wof:placetype":"venue"
},
  "geometry": {"coordinates":[144.86781310999999,-37.8156776428],"type":"Point"}
}