{
  "type": "Feature",
  "properties": {
    "addr:full":"53 Boothby St Panorama SA 5041",
    "addr:housenumber":"53",
    "addr:postcode":"5041",
    "addr:street":"Boothby St",
    "iso:country":"AU",
    "sg:address":"53 Boothby St",
    "sg:city":"Panorama",
    "sg:classifiers":[
        {
            "category":"Professional",
            "type":"Services"
        }
    ],
    "sg:phone":"+61 8 8277 4833",
    "sg:postcode":"5041",
    "sg:province":"SA",
    "sg:tags":[
        "spray",
        "painting"
    ],
    "wof:name":"Clifford Brian Motor Body Repairs",
    "wof:placetype":"venue"
},
  "geometry": {"coordinates":[138.59669500000001,-34.992641],"type":"Point"}
}