{
  "type": "Feature",
  "properties": {
    "addr:full":"71 Longueville Rd Lane Cove NSW 2066",
    "addr:housenumber":"71",
    "addr:postcode":"2066",
    "addr:street":"Longueville Rd",
    "iso:country":"AU",
    "sg:address":"71 Longueville Rd",
    "sg:city":"Lane Cove",
    "sg:classifiers":[
        {
            "category":"Professional",
            "subcategory":"Computer Services",
            "type":"Services"
        }
    ],
    "sg:phone":"+61 2 9844 8222",
    "sg:postcode":"2066",
    "sg:province":"NSW",
    "sg:tags":[
        "consultant",
        "system"
    ],
    "wof:name":"CV Services International Pty Ltd",
    "wof:placetype":"venue"
},
  "geometry": {"coordinates":[151.170120239,-33.8139648438],"type":"Point"}
}