{
  "type": "Feature",
  "properties": {
    "iso:country":"AU",
    "sg:address":"41-45 Grove Ave",
    "sg:city":"Marleston",
    "sg:classifiers":[
        {
            "category":"Manufacturing",
            "subcategory":"Printing",
            "type":"Manufacturing & Wholesale Goods"
        }
    ],
    "sg:phone":"+61 8 8351 4422",
    "sg:postcode":"5033",
    "sg:province":"SA",
    "sg:tags":[
        "encoding",
        "cheque"
    ],
    "wof:name":"Star Printing",
    "wof:placetype":"venue"
},
  "geometry": {"coordinates":[138.562774658,-34.9466094971],"type":"Point"}
}