{
  "type": "Feature",
  "properties": {
    "addr:full":"72 Cooper Rd Birrong NSW 2143",
    "addr:housenumber":"72",
    "addr:postcode":"2143",
    "addr:street":"Cooper Rd",
    "iso:country":"AU",
    "sg:address":"72 Cooper Rd",
    "sg:city":"Birrong",
    "sg:classifiers":[
        {
            "category":"Professional",
            "subcategory":"Engineering",
            "type":"Services"
        }
    ],
    "sg:phone":"+61 2 9644 4968",
    "sg:postcode":"2143",
    "sg:province":"NSW",
    "sg:tags":[
        "consulting",
        "engineer"
    ],
    "wof:name":"Ozsher Pty Ltd",
    "wof:placetype":"venue"
},
  "geometry": {"coordinates":[151.026412964,-33.8940582275],"type":"Point"}
}