{
  "type": "Feature",
  "properties": {
    "addr:full":"7 Vicar St Coogee NSW 2034",
    "addr:housenumber":"7",
    "addr:postcode":"2034",
    "addr:street":"Vicar St",
    "iso:country":"AU",
    "sg:address":"7 Vicar St",
    "sg:city":"Coogee",
    "sg:classifiers":[
        {
            "category":"Health Services",
            "subcategory":"Doctor",
            "type":"Services"
        }
    ],
    "sg:phone":"+61 2 9665 5665",
    "sg:postcode":"2034",
    "sg:province":"NSW",
    "sg:tags":[
        "medical",
        "practitioner"
    ],
    "wof:name":"Casamento J B Shiner P R & O'Hearn C A",
    "wof:placetype":"venue"
},
  "geometry": {"coordinates":[151.25526428200001,-33.9210395813],"type":"Point"}
}