{
  "type": "Feature",
  "properties": {
    "addr:full":"12 Hilton St Beaumaris VIC 3193",
    "addr:housenumber":"12",
    "addr:postcode":"3193",
    "addr:street":"Hilton St",
    "iso:country":"AU",
    "sg:address":"12 Hilton St",
    "sg:city":"Beaumaris",
    "sg:classifiers":[
        {
            "category":"Organizations",
            "subcategory":"Community Association",
            "type":"Services"
        }
    ],
    "sg:phone":"+61 3 9589 4763",
    "sg:postcode":"3193",
    "sg:province":"VIC",
    "sg:tags":[
        "shiatsu",
        "therapy"
    ],
    "wof:name":"Andrea Gault",
    "wof:placetype":"venue"
},
  "geometry": {"coordinates":[145.026412964,-37.9788780212],"type":"Point"}
}