{
  "type": "Feature",
  "properties": {
    "addr:full":"PO Box 697 Kensington NSW 2033",
    "addr:postcode":"2033",
    "iso:country":"AU",
    "sg:address":"PO Box 697",
    "sg:city":"Kensington",
    "sg:classifiers":[
        {
            "category":"Building & Trades",
            "subcategory":"Equipment Rental",
            "type":"Services"
        }
    ],
    "sg:phone":"+61 2 9666 9777",
    "sg:postcode":"2033",
    "sg:province":"NSW",
    "sg:tags":[
        "crane",
        "hire"
    ],
    "wof:name":"Construction Rescue Services",
    "wof:placetype":"venue"
},
  "geometry": {"coordinates":[151.21902499999999,-33.912998],"type":"Point"}
}