{
  "type": "Feature",
  "properties": {
    "addr:full":"Railway St Boonah QLD 4310",
    "addr:postcode":"4310",
    "addr:street":"Railway St",
    "iso:country":"AU",
    "sg:address":"Railway St",
    "sg:city":"Boonah",
    "sg:classifiers":[
        {
            "category":"Shopping",
            "subcategory":"Antiques",
            "type":"Retail Goods"
        }
    ],
    "sg:phone":"+61 412 720 403",
    "sg:postcode":"4310",
    "sg:province":"QLD",
    "sg:tags":[
        "restoration",
        "reproduction"
    ],
    "wof:name":"Then & Now Woodcraft",
    "wof:placetype":"venue"
},
  "geometry": {"coordinates":[152.68211364699999,-27.9958190918],"type":"Point"}
}