{
  "type": "Feature",
  "properties": {
    "addr:full":"Shop 2 70 Watton St Werribee VIC 3030",
    "addr:housenumber":"shop;70",
    "addr:postcode":"3030",
    "addr:street":"Watton St",
    "iso:country":"AU",
    "sg:address":"Shop 2 70 Watton St",
    "sg:city":"Werribee",
    "sg:classifiers":[
        {
            "category":"Shopping",
            "subcategory":"Mobile Phones",
            "type":"Retail Goods"
        }
    ],
    "sg:phone":"+61 3 9974 1277",
    "sg:postcode":"3030",
    "sg:province":"VIC",
    "sg:tags":[
        "telephone",
        "accessory"
    ],
    "wof:name":"Delta Phones",
    "wof:placetype":"venue"
},
  "geometry": {"coordinates":[144.658691,-37.902596],"type":"Point"}
}