{
  "type": "Feature",
  "properties": {
    "addr:full":"Suite 5 Ground Floor Hogg Lawson Building 50 McDougall St Milton QLD 4064",
    "addr:housenumber":"50",
    "addr:postcode":"4064",
    "addr:street":"Mcdougall St",
    "iso:country":"AU",
    "sg:address":"Suite 5 Ground Floor Hogg Lawson Building 50 McDougall St",
    "sg:city":"Milton",
    "sg:classifiers":[
        {
            "category":"Education",
            "subcategory":"Special Training",
            "type":"Public Place"
        }
    ],
    "sg:phone":"+61 7 3217 5447",
    "sg:postcode":"4064",
    "sg:province":"QLD",
    "sg:tags":[
        "development"
    ],
    "wof:name":"ACTS Associate Consultancy & Training Services",
    "wof:placetype":"venue"
},
  "geometry": {"coordinates":[153.00607299800001,-27.4713726044],"type":"Point"}
}