{
  "type": "Feature",
  "properties": {
    "addr:full":"Congewai Rd Congewai Via Cessnock NSW 2325",
    "addr:postcode":"2325",
    "addr:street":"Congewai Rd Congewai Via Cessnock",
    "iso:country":"AU",
    "sg:address":"Congewai Rd",
    "sg:city":"Congewai Via Cessnock",
    "sg:classifiers":[
        {
            "category":"Manufacturing",
            "subcategory":"Rubber & Plastics",
            "type":"Manufacturing & Wholesale Goods"
        }
    ],
    "sg:phone":"+61 2 4998 1245",
    "sg:postcode":"2325",
    "sg:province":"NSW",
    "sg:tags":[
        "lime"
    ],
    "wof:name":"Swift Fertilizers Pty Ltd",
    "wof:placetype":"venue"
},
  "geometry": {"coordinates":[151.28477477999999,-32.9078102112],"type":"Point"}
}