{
  "type": "Feature",
  "properties": {
    "addr:full":"Cnr Robertson & Grange Rds Eastern Heights QLD 4305",
    "addr:postcode":"4305",
    "addr:street":"Cnr",
    "iso:country":"AU",
    "sg:address":"Cnr Robertson & Grange Rds",
    "sg:city":"Eastern Heights",
    "sg:classifiers":[
        {
            "category":"Autos & Motor Vehicles",
            "subcategory":"Fuel & Gas Station",
            "type":"Retail Goods"
        }
    ],
    "sg:phone":"+61 7 3281 3044",
    "sg:postcode":"4305",
    "sg:province":"QLD",
    "wof:name":"BP",
    "wof:placetype":"venue"
},
  "geometry": {"coordinates":[152.778106689,-27.6279659271],"type":"Point"}
}