{
  "type": "Feature",
  "properties": {
    "addr:full":"26 Hands Ave Eaton WA 6232",
    "addr:housenumber":"26",
    "addr:postcode":"6232",
    "addr:street":"Hands Ave",
    "iso:country":"AU",
    "sg:address":"26 Hands Ave",
    "sg:city":"Eaton",
    "sg:classifiers":[
        {
            "category":"Education",
            "subcategory":"Dance Studio",
            "type":"Public Place"
        }
    ],
    "sg:phone":"+61 407 422 399",
    "sg:postcode":"6232",
    "sg:province":"WA",
    "sg:tags":[
        "training",
        "video",
        "film"
    ],
    "wof:name":"Supernova Sound & Vision",
    "wof:placetype":"venue"
},
  "geometry": {"coordinates":[115.715378,-33.316513],"type":"Point"}
}