{
  "type": "Feature",
  "properties": {
    "iso:country":"AU",
    "sg:address":"16 Hampton St",
    "sg:city":"Alexandra Hills",
    "sg:classifiers":[
        {
            "category":"Utilities",
            "subcategory":"Electric",
            "type":"Services"
        }
    ],
    "sg:phone":"+61 7 3824 0214",
    "sg:postcode":"4161",
    "sg:province":"QLD",
    "sg:tags":[
        "electrical",
        "contractor"
    ],
    "wof:name":"Bill Croft Electrical",
    "wof:placetype":"venue"
},
  "geometry": {"coordinates":[153.227005005,-27.5214138031],"type":"Point"}
}