{
  "type": "Feature",
  "properties": {
    "addr:full":"224 Main St Osborne Park WA 6017",
    "addr:housenumber":"224",
    "addr:postcode":"6017",
    "addr:street":"Main St",
    "iso:country":"AU",
    "sg:address":"224 Main St",
    "sg:city":"Osborne Park",
    "sg:classifiers":[
        {
            "category":"Retail",
            "subcategory":"Event Space",
            "type":"Services"
        }
    ],
    "sg:phone":"+61 8 9440 6001",
    "sg:postcode":"6017",
    "sg:province":"WA",
    "sg:tags":[
        "function",
        "organiser"
    ],
    "wof:name":"La Scala Caffe & Ristorant",
    "wof:placetype":"venue"
},
  "geometry": {"coordinates":[115.82840728799999,-31.8957481384],"type":"Point"}
}