{
  "type": "Feature",
  "properties": {
    "iso:country":"AU",
    "sg:address":"1/ 49 Holland St",
    "sg:city":"Thebarton",
    "sg:classifiers":[
        {
            "category":"Health Services",
            "subcategory":"Doctor",
            "type":"Services"
        }
    ],
    "sg:phone":"+61 1300 650 182",
    "sg:postcode":"5031",
    "sg:province":"SA",
    "sg:tags":[
        "occupational",
        "safety"
    ],
    "wof:name":"Chubb Training Group",
    "wof:placetype":"venue"
},
  "geometry": {"coordinates":[138.573562622,-34.9110641479],"type":"Point"}
}