{
  "type": "Feature",
  "properties": {
    "addr:full":"70 Summerhill Rd Yarra Junction VIC 3797",
    "addr:housenumber":"70",
    "addr:postcode":"3797",
    "addr:street":"Summerhill Rd",
    "iso:country":"AU",
    "sg:address":"70 Summerhill Rd",
    "sg:city":"Yarra Junction",
    "sg:classifiers":[
        {
            "category":"Farming",
            "subcategory":"Vineyard",
            "type":"Manufacturing & Wholesale Goods"
        }
    ],
    "sg:phone":"+61 3 5967 2773",
    "sg:postcode":"3797",
    "sg:province":"VIC",
    "sg:tags":[
        "winery"
    ],
    "wof:name":"Bulong Estate",
    "wof:placetype":"venue"
},
  "geometry": {"coordinates":[145.62382507300001,-37.8019485474],"type":"Point"}
}