{
  "type": "Feature",
  "properties": {
    "addr:full":"7 Gretel Drv Mermaid Waters QLD 4218",
    "addr:housenumber":"7",
    "addr:postcode":"4218",
    "addr:street":"Gretel Drv",
    "iso:country":"AU",
    "sg:address":"7 Gretel Drv",
    "sg:city":"Mermaid Waters",
    "sg:classifiers":[
        {
            "category":"Home & Garden",
            "subcategory":"Carpets & Floor Coverings",
            "type":"Retail Goods"
        }
    ],
    "sg:phone":"+61 7 5578 6469",
    "sg:postcode":"4218",
    "sg:province":"QLD",
    "sg:tags":[
        "tile",
        "wall",
        "layer"
    ],
    "wof:name":"Sullivan Tiling Services",
    "wof:placetype":"venue"
},
  "geometry": {"coordinates":[153.42755126899999,-28.0454101562],"type":"Point"}
}