{
  "type": "Feature",
  "properties": {
    "addr:full":"259 Tapleys Hill Rd Seaton SA 5023",
    "addr:housenumber":"259",
    "addr:postcode":"5023",
    "addr:street":"Tapleys Hill Rd",
    "iso:country":"AU",
    "sg:address":"259 Tapleys Hill Rd",
    "sg:city":"Seaton",
    "sg:classifiers":[
        {
            "category":"Health Services",
            "subcategory":"Dentist",
            "type":"Services"
        }
    ],
    "sg:phone":"+61 8 8244 0655",
    "sg:postcode":"5023",
    "sg:province":"SA",
    "wof:name":"Tapleys Hill Denture Clinic",
    "wof:placetype":"venue"
},
  "geometry": {"coordinates":[138.51385498100001,-34.8921394348],"type":"Point"}
}