{
  "type": "Feature",
  "properties": {
    "iso:country":"AU",
    "sg:address":"1004 Albany Hwy",
    "sg:city":"East Victoria Park",
    "sg:classifiers":[
        {
            "category":"Retail",
            "subcategory":"Auto Rental",
            "type":"Services"
        }
    ],
    "sg:phone":"+61 8 9360 3366",
    "sg:postcode":"6101",
    "sg:province":"WA",
    "sg:tags":[
        "car",
        "hire",
        "minibus"
    ],
    "wof:name":"Houghton Motors",
    "wof:placetype":"venue"
},
  "geometry": {"coordinates":[115.910728455,-31.9920959473],"type":"Point"}
}