{
  "type": "Feature",
  "properties": {
    "iso:country":"AU",
    "sg:address":"542 Bunnerong Rd",
    "sg:city":"Matraville",
    "sg:classifiers":[
        {
            "category":"Food & Beverages",
            "subcategory":"Bakery",
            "type":"Retail Goods"
        }
    ],
    "sg:phone":"+61 2 9661 3234",
    "sg:postcode":"2036",
    "sg:province":"NSW",
    "sg:tags":[
        "cake",
        "shop",
        "pastry"
    ],
    "wof:name":"House Of Pie The",
    "wof:placetype":"venue"
},
  "geometry": {"coordinates":[151.23110961899999,-33.959777832],"type":"Point"}
}