{
  "type": "Feature",
  "properties": {
    "addr:full":"152 Millers Rd Altona North VIC 3025",
    "addr:housenumber":"152",
    "addr:postcode":"3025",
    "addr:street":"Millers Rd",
    "iso:country":"AU",
    "sg:address":"152 Millers Rd",
    "sg:city":"Altona North",
    "sg:classifiers":[
        {
            "category":"Wholesale",
            "subcategory":"Medical Equipment & Supplies",
            "type":"Manufacturing & Wholesale Goods"
        }
    ],
    "sg:phone":"+61 3 9325 1200",
    "sg:postcode":"3025",
    "sg:province":"VIC",
    "sg:tags":[
        "aids",
        "hearing"
    ],
    "wof:name":"Victorian Hearing & Advisory Service",
    "wof:placetype":"venue"
},
  "geometry": {"coordinates":[144.84818999999999,-37.830437],"type":"Point"}
}