{
  "type": "Feature",
  "properties": {
    "iso:country":"AU",
    "sg:address":"11 Glendale Ave",
    "sg:city":"Hastings",
    "sg:classifiers":[
        {
            "category":"Wholesale",
            "subcategory":"Scrap",
            "type":"Manufacturing & Wholesale Goods"
        }
    ],
    "sg:phone":"+61 3 5979 3928",
    "sg:postcode":"3915",
    "sg:province":"VIC",
    "sg:tags":[
        "merchant",
        "metal"
    ],
    "wof:name":"Mr Scrap Metal Pty Ltd",
    "wof:placetype":"venue"
},
  "geometry": {"coordinates":[145.18377685600001,-38.2946586609],"type":"Point"}
}