{
  "type": "Feature",
  "properties": {
    "addr:full":"5/ 38 Computer Rd Yatala QLD 4207",
    "addr:housenumber":"/ 38",
    "addr:postcode":"4207",
    "addr:street":"Computer Rd",
    "iso:country":"AU",
    "sg:address":"5/ 38 Computer Rd",
    "sg:city":"Yatala",
    "sg:classifiers":[
        {
            "category":"Shopping",
            "subcategory":"Stationery & Office Supplies",
            "type":"Retail Goods"
        }
    ],
    "sg:phone":"+61 7 3382 0855",
    "sg:postcode":"4207",
    "sg:province":"QLD",
    "sg:tags":[
        "packaging",
        "material"
    ],
    "wof:name":"Quantum Trading",
    "wof:placetype":"venue"
},
  "geometry": {"coordinates":[153.24107360799999,-27.7594871521],"type":"Point"}
}