{
  "type": "Feature",
  "properties": {
    "addr:full":"613 Mair St Ballarat VIC 3350",
    "addr:housenumber":"613",
    "addr:postcode":"3350",
    "addr:street":"Mair St",
    "iso:country":"AU",
    "sg:address":"613 Mair St",
    "sg:city":"Ballarat",
    "sg:classifiers":[
        {
            "category":"Organizations",
            "subcategory":"Non-profit Organization",
            "type":"Services"
        }
    ],
    "sg:phone":"+61 3 5331 5667",
    "sg:postcode":"3350",
    "sg:province":"VIC",
    "sg:tags":[
        "support",
        "disability",
        "organisation"
    ],
    "wof:name":"EW Tipping Foundation",
    "wof:placetype":"venue"
},
  "geometry": {"coordinates":[143.85107400000001,-37.559052],"type":"Point"}
}