{
  "type": "Feature",
  "properties": {
    "addr:full":"21 Crescent St Penguin TAS 7316",
    "addr:housenumber":"21",
    "addr:postcode":"7316",
    "addr:street":"Crescent St",
    "iso:country":"AU",
    "sg:address":"21 Crescent St",
    "sg:city":"Penguin",
    "sg:classifiers":[
        {
            "category":"Organizations",
            "subcategory":"Professional Association",
            "type":"Services"
        }
    ],
    "sg:phone":"+61 3 6437 0838",
    "sg:postcode":"7316",
    "sg:province":"TAS",
    "sg:tags":[
        "web",
        "internet"
    ],
    "wof:name":"JETblack Internet Development",
    "wof:placetype":"venue"
},
  "geometry": {"coordinates":[146.070709228,-41.1130714417],"type":"Point"}
}