{
  "type": "Feature",
  "properties": {
    "addr:full":"147 Pennant Pde Epping NSW 2121",
    "addr:housenumber":"147",
    "addr:postcode":"2121",
    "addr:street":"Pennant Pde",
    "iso:country":"AU",
    "sg:address":"147 Pennant Pde",
    "sg:city":"Epping",
    "sg:classifiers":[
        {
            "category":"Arts & Performance",
            "subcategory":"Music",
            "type":"Entertainment"
        }
    ],
    "sg:phone":"+61 2 9869 1634",
    "sg:postcode":"2121",
    "sg:province":"NSW",
    "sg:tags":[
        "mobile",
        "jockey",
        "disc"
    ],
    "wof:name":"D.L. Discos",
    "wof:placetype":"venue"
},
  "geometry": {"coordinates":[151.060455322,-33.7766685486],"type":"Point"}
}