{
  "type": "Feature",
  "properties": {
    "addr:full":"11a Kurrajong Pde Mildura VIC 3500",
    "addr:housenumber":"11a",
    "addr:postcode":"3500",
    "addr:street":"Kurrajong Pde",
    "iso:country":"AU",
    "sg:address":"11a Kurrajong Pde",
    "sg:city":"Mildura",
    "sg:classifiers":[
        {
            "category":"Home & Garden",
            "subcategory":"Carpets & Floor Coverings",
            "type":"Retail Goods"
        }
    ],
    "sg:phone":"+61 400 103 082",
    "sg:postcode":"3500",
    "sg:province":"VIC",
    "sg:tags":[
        "tile",
        "wall"
    ],
    "wof:name":"Jason Modica Tiling",
    "wof:placetype":"venue"
},
  "geometry": {"coordinates":[142.15136718799999,-34.1892623901],"type":"Point"}
}