{
  "type": "Feature",
  "properties": {
    "iso:country":"AU",
    "sg:address":"Level 7 179 Queen St",
    "sg:city":"Melbourne",
    "sg:classifiers":[
        {
            "category":"Professional",
            "subcategory":"Art Services",
            "type":"Services"
        }
    ],
    "sg:phone":"+61 3 9670 4447",
    "sg:postcode":"3000",
    "sg:province":"VIC",
    "sg:tags":[
        "interior",
        "designer"
    ],
    "wof:name":"Graham Nicholas Pty Ltd",
    "wof:placetype":"venue"
},
  "geometry": {"coordinates":[144.96026611299999,-37.8143386841],"type":"Point"}
}