{
  "type": "Feature",
  "properties": {
    "addr:full":"593 Ruthven St Toowoomba QLD 4350",
    "addr:housenumber":"593",
    "addr:postcode":"4350",
    "addr:street":"Ruthven St",
    "iso:country":"AU",
    "sg:address":"593 Ruthven St",
    "sg:city":"Toowoomba",
    "sg:classifiers":[
        {
            "category":"Shopping",
            "subcategory":"Bridal",
            "type":"Retail Goods"
        }
    ],
    "sg:phone":"+61 7 4632 0777",
    "sg:postcode":"4350",
    "sg:province":"QLD",
    "sg:tags":[
        "hire",
        "wear"
    ],
    "wof:name":"The Princess Bride & Formal",
    "wof:placetype":"venue"
},
  "geometry": {"coordinates":[151.952316,-27.568052],"type":"Point"}
}