{
  "type": "Feature",
  "properties": {
    "iso:country":"AU",
    "sg:address":"3 Maughan Rd",
    "sg:city":"Mt Eliza",
    "sg:classifiers":[
        {
            "category":"Building & Trades",
            "subcategory":"Plumbing",
            "type":"Services"
        }
    ],
    "sg:phone":"+61 3 9787 9000",
    "sg:postcode":"3930",
    "sg:province":"VIC",
    "sg:tags":[
        "plumber",
        "gasfitters"
    ],
    "wof:name":"Griffith Trevor J",
    "wof:placetype":"venue"
},
  "geometry": {"coordinates":[145.091430664,-38.2112236023],"type":"Point"}
}