{
  "type": "Feature",
  "properties": {
    "addr:full":"3 Cananga Crt Mill Park VIC 3082",
    "addr:housenumber":"3",
    "addr:postcode":"3082",
    "addr:street":"Cananga Crt",
    "iso:country":"AU",
    "sg:address":"3 Cananga Crt",
    "sg:city":"Mill Park",
    "sg:classifiers":[
        {
            "category":"Social Services",
            "subcategory":"Adult Care",
            "type":"Services"
        }
    ],
    "sg:phone":"+61 414 566 233",
    "sg:postcode":"3082",
    "sg:province":"VIC",
    "sg:tags":[
        "towing"
    ],
    "wof:name":"Banyule Towing",
    "wof:placetype":"venue"
},
  "geometry": {"coordinates":[145.07681274399999,-37.674041748],"type":"Point"}
}