{
  "type": "Feature",
  "properties": {
    "addr:full":"125 Old Pitt Town Rd Box Hill NSW 2765",
    "addr:housenumber":"125",
    "addr:postcode":"2765",
    "addr:street":"Old Pitt Town Rd",
    "iso:country":"AU",
    "sg:address":"125 Old Pitt Town Rd",
    "sg:city":"Box Hill",
    "sg:classifiers":[
        {
            "category":"Organizations",
            "subcategory":"Non-profit Organization",
            "type":"Services"
        }
    ],
    "sg:phone":"+61 2 9679 1246",
    "sg:postcode":"2765",
    "sg:province":"NSW",
    "sg:tags":[
        "support",
        "disability",
        "organisation"
    ],
    "wof:name":"Riding For The Disabled Association (NSW)",
    "wof:placetype":"venue"
},
  "geometry": {"coordinates":[150.90934753400001,-33.6413917542],"type":"Point"}
}