{
  "type": "Feature",
  "properties": {
    "iso:country":"AU",
    "sg:address":"8 Wiarando Crs",
    "sg:city":"Doncaster East",
    "sg:classifiers":[
        {
            "category":"Building & Trades",
            "subcategory":"Construction",
            "type":"Services"
        }
    ],
    "sg:phone":"+61 3 9842 1211",
    "sg:postcode":"3109",
    "sg:province":"VIC",
    "sg:tags":[
        "contractor"
    ],
    "wof:name":"Walton Construction Pty Ltd",
    "wof:placetype":"venue"
},
  "geometry": {"coordinates":[145.17059326200001,-37.7737998962],"type":"Point"}
}