{
  "type": "Feature",
  "properties": {
    "iso:country":"AU",
    "sg:address":"1st Floor, 9 Denison St",
    "sg:city":"Newcastle",
    "sg:classifiers":[
        {
            "category":"Professional",
            "subcategory":"Employment Agencies",
            "type":"Services"
        }
    ],
    "sg:phone":"+61 2 4969 0122",
    "sg:postcode":"2300",
    "sg:province":"NSW",
    "sg:tags":[
        "provider",
        "internet"
    ],
    "wof:name":"Hunterlink Pty Ltd",
    "wof:placetype":"venue"
},
  "geometry": {"coordinates":[151.73942600000001,-32.925163],"type":"Point"}
}