{
  "type": "Feature",
  "properties": {
    "iso:country":"AU",
    "sg:address":"Shp 152b/ Pendle Way",
    "sg:city":"Pendle Hill",
    "sg:classifiers":[
        {
            "category":"Shopping",
            "subcategory":"Clothing, Apparel, & Fashions",
            "type":"Retail Goods"
        }
    ],
    "sg:phone":"+61 2 9636 6187",
    "sg:postcode":"2145",
    "sg:province":"NSW",
    "sg:tags":[
        "lady",
        "wear"
    ],
    "wof:name":"Gudia's Collection",
    "wof:placetype":"venue"
},
  "geometry": {"coordinates":[150.956298828,-33.8020019531],"type":"Point"}
}