{
  "type": "Feature",
  "properties": {
    "addr:full":"6 Production Pl Penrith NSW 2750",
    "addr:housenumber":"6",
    "addr:postcode":"2750",
    "addr:street":"Production Pl",
    "iso:country":"AU",
    "sg:address":"6 Production Pl",
    "sg:city":"Penrith",
    "sg:classifiers":[
        {
            "category":"Communications",
            "type":"Services"
        }
    ],
    "sg:phone":"+61 2 4731 2085",
    "sg:postcode":"2750",
    "sg:province":"NSW",
    "sg:tags":[
        "equipment",
        "radio"
    ],
    "wof:name":"BTW Communications Pty. Ltd.",
    "wof:placetype":"venue"
},
  "geometry": {"coordinates":[150.68487548799999,-33.7687263489],"type":"Point"}
}