{
  "type": "Feature",
  "properties": {
    "iso:country":"AU",
    "sg:address":"119 Main St",
    "sg:city":"Pakenham",
    "sg:classifiers":[
        {
            "category":"Real Estate",
            "subcategory":"Real Estate Agent",
            "type":"Services"
        }
    ],
    "sg:phone":"+61 3 5941 1255",
    "sg:postcode":"3810",
    "sg:province":"VIC",
    "wof:name":"Gerard Collins",
    "wof:placetype":"venue"
},
  "geometry": {"coordinates":[145.48234600000001,-38.078335],"type":"Point"}
}