{
  "type": "Feature",
  "properties": {
    "iso:country":"AU",
    "sg:address":"55 Berriman Drv",
    "sg:city":"Wangara",
    "sg:classifiers":[
        {
            "category":"Building & Trades",
            "subcategory":"Cleaning & Sanitation",
            "type":"Services"
        }
    ],
    "sg:phone":"+61 8 9409 8567",
    "sg:postcode":"6065",
    "sg:province":"WA",
    "sg:tags":[
        "abrasive",
        "blasting"
    ],
    "wof:name":"Powderline Coatings",
    "wof:placetype":"venue"
},
  "geometry": {"coordinates":[115.82711792000001,-31.7915744781],"type":"Point"}
}