{
  "type": "Feature",
  "properties": {
    "iso:country":"AU",
    "sg:address":"22 Church St",
    "sg:city":"Collector",
    "sg:classifiers":[
        {
            "category":"Arts & Performance",
            "subcategory":"Art Gallery",
            "type":"Entertainment"
        }
    ],
    "sg:phone":"+61 2 4848 0073",
    "sg:postcode":"2581",
    "sg:province":"NSW",
    "wof:name":"Collector Gallery",
    "wof:placetype":"venue"
},
  "geometry": {"coordinates":[149.43197631800001,-34.91223526],"type":"Point"}
}