{
  "type": "Feature",
  "properties": {
    "iso:country":"AU",
    "sg:address":"134 Stawell St",
    "sg:city":"Burnley",
    "sg:classifiers":[
        {
            "category":"Manufacturing",
            "subcategory":"Metals",
            "type":"Manufacturing & Wholesale Goods"
        }
    ],
    "sg:phone":"+61 3 9428 6569",
    "sg:postcode":"3121",
    "sg:province":"VIC",
    "sg:tags":[
        "polisher"
    ],
    "wof:name":"G & S Metal Polishers",
    "wof:placetype":"venue"
},
  "geometry": {"coordinates":[145.00921630900001,-37.8273735046],"type":"Point"}
}