{
  "type": "Feature",
  "properties": {
    "iso:country":"AU",
    "sg:address":"3 Tathra St",
    "sg:city":"Stafford",
    "sg:classifiers":[
        {
            "category":"Landmark",
            "subcategory":"Square",
            "type":"Public Place"
        }
    ],
    "sg:phone":"+61 7 3356 9693",
    "sg:postcode":"4053",
    "sg:province":"QLD",
    "sg:tags":[
        "lampshade"
    ],
    "wof:name":"Cluttered Closets",
    "wof:placetype":"venue"
},
  "geometry": {"coordinates":[153.021392822,-27.4109268188],"type":"Point"}
}