{
  "type": "Feature",
  "properties": {
    "iso:country":"AU",
    "sg:address":"26 Park Ave",
    "sg:city":"Coffs Harbour",
    "sg:classifiers":[
        {
            "category":"Banks & Credit Unions",
            "subcategory":"Financial Services",
            "type":"Services"
        }
    ],
    "sg:phone":"+61 2 6651 2000",
    "sg:postcode":"2450",
    "sg:province":"NSW",
    "sg:tags":[
        "advisory",
        "planning",
        "retirement"
    ],
    "wof:name":"Bridges Personal Investment Services",
    "wof:placetype":"venue"
},
  "geometry": {"coordinates":[153.11497499999999,-30.298632],"type":"Point"}
}