{
  "type": "Feature",
  "properties": {
    "iso:country":"AU",
    "sg:address":"12 Mercer La",
    "sg:city":"Joondalup",
    "sg:classifiers":[
        {
            "category":"Building & Trades",
            "subcategory":"Construction",
            "type":"Services"
        }
    ],
    "sg:phone":"+61 8 9301 5000",
    "sg:postcode":"6027",
    "sg:province":"WA",
    "sg:tags":[
        "home",
        "air conditioning"
    ],
    "wof:name":"Aclimatize Airconditioning",
    "wof:placetype":"venue"
},
  "geometry": {"coordinates":[115.761558533,-31.7430858612],"type":"Point"}
}