{
  "type": "Feature",
  "properties": {
    "iso:country":"AU",
    "sg:address":"PO Box 101",
    "sg:city":"Brunswick East",
    "sg:classifiers":[
        {
            "category":"Shopping",
            "subcategory":"Antiques",
            "type":"Retail Goods"
        }
    ],
    "sg:phone":"+61 3 9378 8475",
    "sg:postcode":"3057",
    "sg:province":"VIC",
    "wof:name":"Web-Antiques",
    "wof:placetype":"venue"
},
  "geometry": {"coordinates":[144.97850036599999,-37.7685012817],"type":"Point"}
}