{
  "type": "Feature",
  "properties": {
    "addr:full":"PO Box 852 Hamilton QLD 4007",
    "addr:postcode":"4007",
    "iso:country":"AU",
    "sg:address":"PO Box 852",
    "sg:city":"Hamilton",
    "sg:classifiers":[
        {
            "category":"Professional",
            "subcategory":"Testing Lab",
            "type":"Services"
        }
    ],
    "sg:phone":"+61 7 3860 5305",
    "sg:postcode":"4007",
    "sg:province":"QLD",
    "sg:tags":[
        "soil",
        "investigation"
    ],
    "wof:name":"Road Material Stabilizers Australia",
    "wof:placetype":"venue"
},
  "geometry": {"coordinates":[153.064606,-27.4375],"type":"Point"}
}