{
  "type": "Feature",
  "properties": {
    "addr:full":"13 Russell Rd Mt Thorley NSW 2330",
    "addr:housenumber":"13",
    "addr:postcode":"2330",
    "addr:street":"Russell Rd",
    "iso:country":"AU",
    "sg:address":"13 Russell Rd",
    "sg:city":"Mt Thorley",
    "sg:classifiers":[
        {
            "category":"Building & Trades",
            "subcategory":"Construction",
            "type":"Services"
        }
    ],
    "sg:phone":"+61 2 6574 0000",
    "sg:postcode":"2330",
    "sg:province":"NSW",
    "sg:tags":[
        "welding"
    ],
    "wof:name":"Hedweld Engineering Pty Ltd",
    "wof:placetype":"venue"
},
  "geometry": {"coordinates":[151.10169999999999,-32.625355],"type":"Point"}
}