{
  "type": "Feature",
  "properties": {
    "addr:full":"9 Worley St North Hobart TAS 7000",
    "addr:housenumber":"9",
    "addr:postcode":"7000",
    "addr:street":"Worley St",
    "iso:country":"AU",
    "sg:address":"9 Worley St",
    "sg:city":"North Hobart",
    "sg:classifiers":[
        {
            "category":"Professional",
            "type":"Services"
        }
    ],
    "sg:phone":"+61 418 535 077",
    "sg:postcode":"7000",
    "sg:province":"TAS",
    "sg:tags":[
        "mail",
        "contractor"
    ],
    "wof:name":"Mail Direct",
    "wof:placetype":"venue"
},
  "geometry": {"coordinates":[147.31933593799999,-42.8701629639],"type":"Point"}
}