{
  "type": "Feature",
  "properties": {
    "addr:full":"57 Blaxland Drv Illawong NSW 2234",
    "addr:housenumber":"57",
    "addr:postcode":"2234",
    "addr:street":"Blaxland Drv",
    "iso:country":"AU",
    "sg:address":"57 Blaxland Drv",
    "sg:city":"Illawong",
    "sg:classifiers":[
        {
            "category":"Real Estate",
            "subcategory":"Real Estate Services",
            "type":"Services"
        }
    ],
    "sg:phone":"+61 2 9532 0618",
    "sg:postcode":"2234",
    "sg:province":"NSW",
    "sg:tags":[
        "valuer"
    ],
    "wof:name":"ACIB Valuations Pty Ltd",
    "wof:placetype":"venue"
},
  "geometry": {"coordinates":[151.031539917,-34.0043869019],"type":"Point"}
}