{
  "type": "Feature",
  "properties": {
    "iso:country":"AU",
    "sg:address":"Depot Rd",
    "sg:city":"Shearwater",
    "sg:classifiers":[
        {
            "category":"Building & Trades",
            "subcategory":"Construction",
            "type":"Services"
        }
    ],
    "sg:phone":"+61 428 286 600",
    "sg:postcode":"7307",
    "sg:province":"TAS",
    "sg:tags":[
        "contractor"
    ],
    "wof:name":"McCoy J.T",
    "wof:placetype":"venue"
},
  "geometry": {"coordinates":[146.53440900000001,-41.157669],"type":"Point"}
}