{
  "type": "Feature",
  "properties": {
    "addr:full":"33 Shaddock Ave Villawood NSW 2163",
    "addr:housenumber":"33",
    "addr:postcode":"2163",
    "addr:street":"Shaddock Ave",
    "iso:country":"AU",
    "sg:address":"33 Shaddock Ave",
    "sg:city":"Villawood",
    "sg:classifiers":[
        {
            "category":"Banks & Credit Unions",
            "subcategory":"Bank",
            "type":"Services"
        }
    ],
    "sg:phone":"+61 2 9794 1000",
    "sg:postcode":"2163",
    "sg:province":"NSW",
    "sg:tags":[
        "concrete",
        "reinforcement"
    ],
    "wof:name":"OneSteel Reinforcing",
    "wof:placetype":"venue"
},
  "geometry": {"coordinates":[150.98312377900001,-33.884677887],"type":"Point"}
}