{
  "type": "Feature",
  "properties": {
    "addr:full":"12 Ada St Parramatta NSW 2150",
    "addr:housenumber":"12",
    "addr:postcode":"2150",
    "addr:street":"Ada St",
    "iso:country":"AU",
    "sg:address":"12 Ada St",
    "sg:city":"Parramatta",
    "sg:classifiers":[
        {
            "category":"Professional",
            "subcategory":"Employment Agencies",
            "type":"Services"
        }
    ],
    "sg:phone":"+61 2 9687 3666",
    "sg:postcode":"2150",
    "sg:province":"NSW",
    "sg:tags":[
        "model"
    ],
    "wof:name":"Maple Model Management",
    "wof:placetype":"venue"
},
  "geometry": {"coordinates":[151.00909423799999,-33.8202018738],"type":"Point"}
}