{
  "type": "Feature",
  "properties": {
    "addr:full":"Suite 4/ 2 Classic Way Burleigh Waters QLD 4220",
    "addr:housenumber":"2",
    "addr:postcode":"4220",
    "addr:street":"Classic Way",
    "iso:country":"AU",
    "sg:address":"Suite 4/ 2",
    "sg:city":"Classic Way Burleigh Waters",
    "sg:classifiers":[
        {
            "category":"Health Services",
            "subcategory":"Doctor",
            "type":"Services"
        }
    ],
    "sg:phone":"+61 7 5593 7059",
    "sg:postcode":"4220",
    "sg:province":"QLD",
    "sg:tags":[
        "medical",
        "practitioner"
    ],
    "wof:name":"Cosson John Dr",
    "wof:placetype":"venue"
},
  "geometry": {"coordinates":[153.423751831,-28.1004199982],"type":"Point"}
}