{
  "type": "Feature",
  "properties": {
    "addr:full":"7 Petal St Toowoomba QLD 4350",
    "addr:housenumber":"7",
    "addr:postcode":"4350",
    "addr:street":"Petal St",
    "iso:country":"AU",
    "sg:address":"7 Petal St",
    "sg:city":"Toowoomba",
    "sg:classifiers":[
        {
            "category":"Health Services",
            "subcategory":"Health Practitioner",
            "type":"Services"
        }
    ],
    "sg:phone":"+61 7 4636 6389",
    "sg:postcode":"4350",
    "sg:province":"QLD",
    "sg:tags":[
        "naturopath"
    ],
    "wof:name":"Fertility Matters",
    "wof:placetype":"venue"
},
  "geometry": {"coordinates":[151.97886700000001,-27.584776],"type":"Point"}
}