{
  "type": "Feature",
  "properties": {
    "iso:country":"AU",
    "sg:address":"10 Little Valley Rd",
    "sg:city":"Templestowe",
    "sg:classifiers":[
        {
            "category":"Professional",
            "subcategory":"Accounting & Tax Preparation",
            "type":"Services"
        }
    ],
    "sg:phone":"+61 3 9846 2578",
    "sg:postcode":"3106",
    "sg:province":"VIC",
    "sg:tags":[
        "accountant",
        "auditor"
    ],
    "wof:name":"Thomas J O",
    "wof:placetype":"venue"
},
  "geometry": {"coordinates":[145.13769531200001,-37.761631012],"type":"Point"}
}