{
  "type": "Feature",
  "properties": {
    "addr:full":"Lvl 2/ 20 Collins St Melbourne VIC 3000",
    "addr:housenumber":"/ 20",
    "addr:postcode":"3000",
    "addr:street":"Collins St",
    "iso:country":"AU",
    "sg:address":"Lvl 2/ 20 Collins St",
    "sg:city":"Melbourne",
    "sg:classifiers":[
        {
            "category":"Manufacturing",
            "subcategory":"Jewelry",
            "type":"Manufacturing & Wholesale Goods"
        }
    ],
    "sg:phone":"+61 3 9654 5006",
    "sg:postcode":"3000",
    "sg:province":"VIC",
    "sg:tags":[
        "mfrg",
        "jeweller"
    ],
    "wof:name":"Douglas William R",
    "wof:placetype":"venue"
},
  "geometry": {"coordinates":[144.97080993599999,-37.8141098022],"type":"Point"}
}