{
  "type": "Feature",
  "properties": {
    "iso:country":"AU",
    "sg:address":"58 Donlan Rd",
    "sg:city":"Mollymook",
    "sg:classifiers":[
        {
            "category":"Building & Trades",
            "subcategory":"Construction",
            "type":"Services"
        }
    ],
    "sg:phone":"+61 2 4455 1024",
    "sg:postcode":"2539",
    "sg:province":"NSW",
    "sg:tags":[
        "contractor"
    ],
    "wof:name":"A-Board Constructions Pty Ltd",
    "wof:placetype":"venue"
},
  "geometry": {"coordinates":[150.47410583499999,-35.3321266174],"type":"Point"}
}