{
  "type": "Feature",
  "properties": {
    "addr:full":"1 Baldwin St Kewdale WA 6105",
    "addr:housenumber":"1",
    "addr:postcode":"6105",
    "addr:street":"Baldwin St",
    "iso:country":"AU",
    "sg:address":"1 Baldwin St",
    "sg:city":"Kewdale",
    "sg:classifiers":[
        {
            "category":"Manufacturing",
            "subcategory":"Metals",
            "type":"Manufacturing & Wholesale Goods"
        }
    ],
    "sg:phone":"+61 8 9353 4044",
    "sg:postcode":"6105",
    "sg:province":"WA",
    "sg:tags":[
        "wholesaler",
        "aluminium",
        "mfrs"
    ],
    "wof:name":"Austral Wright Metals",
    "wof:placetype":"venue"
},
  "geometry": {"coordinates":[115.972099304,-31.9798069],"type":"Point"}
}