{
  "type": "Feature",
  "properties": {
    "addr:full":"395 Chapel St South Yarra VIC 3141",
    "addr:housenumber":"395",
    "addr:postcode":"3141",
    "addr:street":"Chapel St",
    "iso:country":"AU",
    "sg:address":"395 Chapel St",
    "sg:city":"South Yarra",
    "sg:classifiers":[
        {
            "category":"Shopping",
            "subcategory":"Clothing, Apparel, & Fashions",
            "type":"Retail Goods"
        }
    ],
    "sg:phone":"+61 3 9826 1888",
    "sg:postcode":"3141",
    "sg:province":"VIC",
    "sg:tags":[
        "wholesaler",
        "mfrs",
        "maternity",
        "wear"
    ],
    "wof:name":"Groove Mama Pty Ltd",
    "wof:placetype":"venue"
},
  "geometry": {"coordinates":[144.99424743599999,-37.8454284668],"type":"Point"}
}