{
  "type": "Feature",
  "properties": {
    "addr:full":"41 Currajong St Parkes NSW 2870",
    "addr:housenumber":"41",
    "addr:postcode":"2870",
    "addr:street":"Currajong St",
    "iso:country":"AU",
    "sg:address":"41 Currajong St",
    "sg:city":"Parkes",
    "sg:classifiers":[
        {
            "category":"Health Services",
            "subcategory":"Doctor",
            "type":"Services"
        }
    ],
    "sg:phone":"+61 2 6863 5888",
    "sg:postcode":"2870",
    "sg:province":"NSW",
    "sg:tags":[
        "occupational",
        "safety"
    ],
    "wof:name":"Country Safe",
    "wof:placetype":"venue"
},
  "geometry": {"coordinates":[148.17628500000001,-33.135956],"type":"Point"}
}