{
  "type": "Feature",
  "properties": {
    "addr:full":"77 Main St West Wyalong NSW 2671",
    "addr:housenumber":"77",
    "addr:postcode":"2671",
    "addr:street":"Main St West",
    "iso:country":"AU",
    "sg:address":"77 Main St",
    "sg:city":"West Wyalong",
    "sg:classifiers":[
        {
            "category":"Organizations",
            "subcategory":"Community Association",
            "type":"Services"
        }
    ],
    "sg:phone":"+61 2 6972 3515",
    "sg:postcode":"2671",
    "sg:province":"NSW",
    "sg:tags":[
        "organisation",
        "family",
        "welfare"
    ],
    "wof:name":"St Vincent De Paul Socy",
    "wof:placetype":"venue"
},
  "geometry": {"coordinates":[147.201416016,-33.9222717285],"type":"Point"}
}