{
  "type": "Feature",
  "properties": {
    "iso:country":"AU",
    "sg:address":"235 Annetts Pde",
    "sg:city":"Mossy Point",
    "sg:classifiers":[
        {
            "category":"Real Estate",
            "subcategory":"Surveying",
            "type":"Services"
        }
    ],
    "sg:phone":"+61 2 4471 5350",
    "sg:postcode":"2537",
    "sg:province":"NSW",
    "sg:tags":[
        "surveyor",
        "land"
    ],
    "wof:name":"Roger Farrington",
    "wof:placetype":"venue"
},
  "geometry": {"coordinates":[150.17958068900001,-35.8343009949],"type":"Point"}
}