{
  "type": "Feature",
  "properties": {
    "addr:full":"Parkside Ave Miranda NSW 2228",
    "addr:postcode":"2228",
    "addr:street":"Parkside Ave Miranda",
    "iso:country":"AU",
    "sg:address":"Parkside Ave",
    "sg:city":"Miranda",
    "sg:classifiers":[
        {
            "category":"Sports & Exercise",
            "subcategory":"Sports Center",
            "type":"Entertainment"
        }
    ],
    "sg:phone":"+61 2 9526 1004",
    "sg:postcode":"2228",
    "sg:province":"NSW",
    "sg:tags":[
        "coach",
        "tennis"
    ],
    "wof:name":"Gilmour Tennis",
    "wof:placetype":"venue"
},
  "geometry": {"coordinates":[151.09999084500001,-34.0317344666],"type":"Point"}
}