{
  "type": "Feature",
  "properties": {
    "iso:country":"AU",
    "sg:address":"OPSM Shp 11 Nepean Sq Shopng Cntr Cnr Station & Woodriff Sts",
    "sg:city":"Penrith",
    "sg:classifiers":[
        {
            "category":"Health Services",
            "subcategory":"Optometrist",
            "type":"Services"
        }
    ],
    "sg:phone":"+61 2 4722 8645",
    "sg:postcode":"2750",
    "sg:province":"NSW",
    "wof:name":"Adam Kelly & Belinda Snashel Optometrists",
    "wof:placetype":"venue"
},
  "geometry": {"coordinates":[150.66299438499999,-33.7561378479],"type":"Point"}
}