{
  "type": "Feature",
  "properties": {
    "addr:full":"Lvl 1/ 810 George St Sydney NSW 2000",
    "addr:housenumber":"/ 810",
    "addr:postcode":"2000",
    "addr:street":"George St",
    "iso:country":"AU",
    "sg:address":"Lvl 1/ 810 George St",
    "sg:city":"Sydney",
    "sg:classifiers":[
        {
            "category":"Shopping",
            "subcategory":"Clothing, Apparel, & Fashions",
            "type":"Retail Goods"
        }
    ],
    "sg:phone":"+61 2 9280 2390",
    "sg:postcode":"2000",
    "sg:province":"NSW",
    "sg:tags":[
        "accessory"
    ],
    "wof:name":"Baku",
    "wof:placetype":"venue"
},
  "geometry": {"coordinates":[151.204681397,-33.8818626404],"type":"Point"}
}