{
  "type": "Feature",
  "properties": {
    "addr:full":"Tasman Hwy St Helens TAS 7216",
    "addr:postcode":"7216",
    "addr:street":"Tasman Hwy",
    "iso:country":"AU",
    "sg:address":"Tasman Hwy",
    "sg:city":"St Helens",
    "sg:classifiers":[
        {
            "category":"Shopping",
            "subcategory":"Antiques",
            "type":"Retail Goods"
        }
    ],
    "sg:phone":"+61 3 6376 1735",
    "sg:postcode":"7216",
    "sg:province":"TAS",
    "wof:name":"Shop In The Bush",
    "wof:placetype":"venue"
},
  "geometry": {"coordinates":[148.23608400000001,-41.315479],"type":"Point"}
}