{
  "type": "Feature",
  "properties": {
    "iso:country":"AU",
    "sg:address":"5 Paperbark Pl",
    "sg:city":"Booral",
    "sg:classifiers":[
        {
            "category":"Personal",
            "subcategory":"Massage",
            "type":"Services"
        }
    ],
    "sg:phone":"+61 2 4994 9301",
    "sg:postcode":"2425",
    "sg:province":"NSW",
    "sg:tags":[
        "therapy"
    ],
    "wof:name":"McNaughton G W",
    "wof:placetype":"venue"
},
  "geometry": {"coordinates":[151.98663330100001,-32.4723625183],"type":"Point"}
}