{
  "type": "Feature",
  "properties": {
    "iso:country":"AU",
    "sg:address":"Shop 1/ 94 Boundary St",
    "sg:city":"West End",
    "sg:classifiers":[
        {
            "category":"Ice Cream",
            "type":"Food & Drink"
        }
    ],
    "sg:phone":"+61 7 3255 1661",
    "sg:postcode":"4101",
    "sg:province":"QLD",
    "sg:tags":[
        "retail"
    ],
    "wof:name":"Baskin Robbins West End",
    "wof:placetype":"venue"
},
  "geometry": {"coordinates":[153.01266479500001,-27.4783935547],"type":"Point"}
}