{
  "type": "Feature",
  "properties": {
    "addr:full":"7 Northcote Ave Balwyn VIC 3103",
    "addr:housenumber":"7",
    "addr:postcode":"3103",
    "addr:street":"Northcote Ave",
    "iso:country":"AU",
    "sg:address":"7 Northcote Ave",
    "sg:city":"Balwyn",
    "sg:classifiers":[
        {
            "category":"Professional",
            "subcategory":"Accounting & Tax Preparation",
            "type":"Services"
        }
    ],
    "sg:phone":"+61 3 9888 6797",
    "sg:postcode":"3103",
    "sg:province":"VIC",
    "sg:tags":[
        "accountant",
        "auditor"
    ],
    "wof:name":"Molan M",
    "wof:placetype":"venue"
},
  "geometry": {"coordinates":[145.08636474599999,-37.817943573],"type":"Point"}
}