{
  "type": "Feature",
  "properties": {
    "iso:country":"AU",
    "sg:address":"Main Rd",
    "sg:city":"Brukunga",
    "sg:classifiers":[
        {
            "category":"Manufacturing",
            "subcategory":"Tools & Machinery",
            "type":"Manufacturing & Wholesale Goods"
        }
    ],
    "sg:phone":"+61 8 8388 6244",
    "sg:postcode":"5252",
    "sg:province":"SA",
    "sg:tags":[
        "earth",
        "excavating",
        "moving",
        "equipment"
    ],
    "wof:name":"Somerled Services",
    "wof:placetype":"venue"
},
  "geometry": {"coordinates":[138.910644531,-35.0345726013],"type":"Point"}
}