{
  "type": "Feature",
  "properties": {
    "iso:country":"AU",
    "sg:address":"230 Bank St",
    "sg:city":"South Melbourne",
    "sg:classifiers":[
        {
            "category":"Communications",
            "subcategory":"Film & Video Production",
            "type":"Services"
        }
    ],
    "sg:phone":"+61 3 9690 6800",
    "sg:postcode":"3205",
    "sg:province":"VIC",
    "sg:tags":[
        "services",
        "equipment",
        "microfilming",
        "supply"
    ],
    "wof:name":"Australian Microfilm Services",
    "wof:placetype":"venue"
},
  "geometry": {"coordinates":[144.95898399999999,-37.834568],"type":"Point"}
}