{
  "type": "Feature",
  "properties": {
    "addr:full":"29 Indooroopilly St Taringa QLD 4068",
    "addr:housenumber":"29",
    "addr:postcode":"4068",
    "addr:street":"Indooroopilly St",
    "iso:country":"AU",
    "sg:address":"29 Indooroopilly St",
    "sg:city":"Taringa",
    "sg:classifiers":[
        {
            "category":"Education",
            "subcategory":"Music School",
            "type":"Public Place"
        }
    ],
    "sg:phone":"+61 7 3870 8012",
    "sg:postcode":"4068",
    "sg:province":"QLD",
    "sg:tags":[
        "teacher"
    ],
    "wof:name":"The Piano Studio",
    "wof:placetype":"venue"
},
  "geometry": {"coordinates":[152.99012756400001,-27.4924812317],"type":"Point"}
}