{
  "type": "Feature",
  "properties": {
    "addr:full":"Shop 6/ 2012 Logan Rd Upper Mt Gravatt QLD 4122",
    "addr:housenumber":"shop 6 / 2012",
    "addr:postcode":"4122",
    "addr:street":"Logan Rd Upper",
    "iso:country":"AU",
    "sg:address":"Shop 6/ 2012 Logan Rd",
    "sg:city":"Upper Mt Gravatt",
    "sg:classifiers":[
        {
            "category":"Retail",
            "subcategory":"Repair Shop",
            "type":"Services"
        }
    ],
    "sg:phone":"+61 7 3343 9134",
    "sg:postcode":"4122",
    "sg:province":"QLD",
    "sg:tags":[
        "mending",
        "clothing",
        "alteration"
    ],
    "wof:name":"Kim Yang Fashion",
    "wof:placetype":"venue"
},
  "geometry": {"coordinates":[153.08085632300001,-27.5587615967],"type":"Point"}
}