{
  "type": "Feature",
  "properties": {
    "iso:country":"AU",
    "sg:address":"Suite 13 241 Diagonal Rd",
    "sg:city":"Warradale",
    "sg:classifiers":[
        {
            "category":"Building & Trades",
            "subcategory":"Construction",
            "type":"Services"
        }
    ],
    "sg:phone":"+61 8 8358 4500",
    "sg:postcode":"5046",
    "sg:province":"SA",
    "sg:tags":[
        "fitting",
        "line",
        "electric",
        "power"
    ],
    "wof:name":"Distribution Power Design",
    "wof:placetype":"venue"
},
  "geometry": {"coordinates":[138.539017,-35.008911],"type":"Point"}
}