{
  "type": "Feature",
  "properties": {
    "iso:country":"AU",
    "sg:address":"83 Pine Ave",
    "sg:city":"Leeton",
    "sg:classifiers":[
        {
            "category":"Communications",
            "subcategory":"Film & Video Production",
            "type":"Services"
        }
    ],
    "sg:phone":"+61 2 6953 4065",
    "sg:postcode":"2705",
    "sg:province":"NSW",
    "sg:tags":[
        "dvd",
        "library"
    ],
    "wof:name":"Leeton Video Rentals",
    "wof:placetype":"venue"
},
  "geometry": {"coordinates":[146.405151367,-34.5515174866],"type":"Point"}
}