{
  "type": "Feature",
  "properties": {
    "addr:full":"PO Box 125 Collaroy NSW 2097",
    "addr:postcode":"2097",
    "iso:country":"AU",
    "sg:address":"PO Box 125",
    "sg:city":"Collaroy",
    "sg:classifiers":[
        {
            "category":"Building & Trades",
            "subcategory":"Construction",
            "type":"Services"
        }
    ],
    "sg:phone":"+61 409 654 161",
    "sg:postcode":"2097",
    "sg:province":"NSW",
    "sg:tags":[
        "earth",
        "excavating",
        "moving",
        "contractor"
    ],
    "wof:name":"Bayview Mini Excavations",
    "wof:placetype":"venue"
},
  "geometry": {"coordinates":[151.296051025,-33.7346115112],"type":"Point"}
}