{
  "type": "Feature",
  "properties": {
    "addr:full":"Factory 8, 11 Mary St Blackburn VIC 3130",
    "addr:housenumber":"11",
    "addr:postcode":"3130",
    "addr:street":"Mary St",
    "iso:country":"AU",
    "sg:address":"Factory 8, 11 Mary St",
    "sg:city":"Blackburn",
    "sg:classifiers":[
        {
            "category":"Retail",
            "subcategory":"Auto Repair",
            "type":"Services"
        }
    ],
    "sg:phone":"+61 3 9877 1344",
    "sg:postcode":"3130",
    "sg:province":"VIC",
    "sg:tags":[
        "repairer",
        "motor",
        "engineer"
    ],
    "wof:name":"Enterprize Automotive Engineering",
    "wof:placetype":"venue"
},
  "geometry": {"coordinates":[145.15525817899999,-37.8199081421],"type":"Point"}
}