{
  "type": "Feature",
  "properties": {
    "addr:full":"25 Albert St Harbord NSW 2096",
    "addr:housenumber":"25",
    "addr:postcode":"2096",
    "addr:street":"Albert St",
    "iso:country":"AU",
    "sg:address":"25 Albert St",
    "sg:city":"Harbord",
    "sg:classifiers":[
        {
            "category":"Personal",
            "subcategory":"Beauty Salon",
            "type":"Services"
        }
    ],
    "sg:phone":"+61 2 9905 1220",
    "sg:postcode":"2096",
    "sg:province":"NSW",
    "sg:tags":[
        "hairdresser"
    ],
    "wof:name":"Cassidy's Of Harbord Hairdressing",
    "wof:placetype":"venue"
},
  "geometry": {"coordinates":[151.28024292000001,-33.7780914307],"type":"Point"}
}