{
  "type": "Feature",
  "properties": {
    "addr:full":"34 Wyatt St Adelaide SA 5000",
    "addr:housenumber":"34",
    "addr:postcode":"5000",
    "addr:street":"Wyatt St",
    "iso:country":"AU",
    "sg:address":"34 Wyatt St",
    "sg:city":"Adelaide",
    "sg:classifiers":[
        {
            "category":"Shopping",
            "subcategory":"Music",
            "type":"Retail Goods"
        }
    ],
    "sg:phone":"+61 8 8232 8696",
    "sg:postcode":"5000",
    "sg:province":"SA",
    "sg:tags":[
        "store"
    ],
    "wof:name":"Inbound Drum & Bass",
    "wof:placetype":"venue"
},
  "geometry": {"coordinates":[138.603805542,-34.9249191284],"type":"Point"}
}