{
  "type": "Feature",
  "properties": {
    "addr:full":"191 Bronte Rd Waverley NSW 2024",
    "addr:housenumber":"191",
    "addr:postcode":"2024",
    "addr:street":"Bronte Rd",
    "iso:country":"AU",
    "sg:address":"191 Bronte Rd",
    "sg:city":"Waverley",
    "sg:classifiers":[
        {
            "category":"Real Estate",
            "subcategory":"Architect",
            "type":"Services"
        }
    ],
    "sg:phone":"+61 2 9369 2059",
    "sg:postcode":"2024",
    "sg:province":"NSW",
    "wof:name":"Archimatrics Pty Ltd",
    "wof:placetype":"venue"
},
  "geometry": {"coordinates":[151.25311279300001,-33.8999328613],"type":"Point"}
}