{
  "type": "Feature",
  "properties": {
    "iso:country":"AU",
    "sg:address":"Rose Bay Marina, Suite 1, 594 New South Head Rd,",
    "sg:city":"Rose Bay",
    "sg:classifiers":[
        {
            "category":"Autos & Motor Vehicles",
            "subcategory":"Boat Sales",
            "type":"Retail Goods"
        }
    ],
    "sg:phone":"+61 2 9326 2867",
    "sg:postcode":"2029",
    "sg:province":"NSW",
    "sg:tags":[
        "yacht"
    ],
    "wof:name":"Chapman Marine Sales Pty Ltd",
    "wof:placetype":"venue"
},
  "geometry": {"coordinates":[151.261917114,-33.8724899292],"type":"Point"}
}