{
  "type": "Feature",
  "properties": {
    "addr:full":"25 Enterprise Way Browns Plains QLD 4118",
    "addr:housenumber":"25",
    "addr:postcode":"4118",
    "addr:street":"Enterprise Way",
    "iso:country":"AU",
    "sg:address":"25 Enterprise Way",
    "sg:city":"Browns Plains",
    "sg:classifiers":[
        {
            "category":"Retail",
            "subcategory":"Auto Repair",
            "type":"Services"
        }
    ],
    "sg:phone":"+61 7 3809 0504",
    "sg:postcode":"4118",
    "sg:province":"QLD",
    "sg:tags":[
        "repairer",
        "motor",
        "engineer"
    ],
    "wof:name":"Q Ford",
    "wof:placetype":"venue"
},
  "geometry": {"coordinates":[153.052078247,-27.6625995636],"type":"Point"}
}