{
  "type": "Feature",
  "properties": {
    "addr:full":"84 Cemetery Rd Ipswich QLD 4305",
    "addr:housenumber":"84",
    "addr:postcode":"4305",
    "addr:street":"Cemetery Rd",
    "iso:country":"AU",
    "sg:address":"84 Cemetery Rd",
    "sg:city":"Ipswich",
    "sg:classifiers":[
        {
            "category":"Home & Garden",
            "subcategory":"Building Materials",
            "type":"Retail Goods"
        }
    ],
    "sg:phone":"+61 7 3281 3327",
    "sg:postcode":"4305",
    "sg:province":"QLD",
    "sg:tags":[
        "fencing"
    ],
    "wof:name":"Eastern Suburbs Hardware",
    "wof:placetype":"venue"
},
  "geometry": {"coordinates":[152.772537231,-27.632686615],"type":"Point"}
}