{
  "type": "Feature",
  "properties": {
    "addr:full":"118 Brisbane Rd Labrador QLD 4215",
    "addr:housenumber":"118",
    "addr:postcode":"4215",
    "addr:street":"Brisbane Rd",
    "iso:country":"AU",
    "sg:address":"118 Brisbane Rd",
    "sg:city":"Labrador",
    "sg:classifiers":[
        {
            "category":"Sports & Exercise",
            "subcategory":"Ski Resort",
            "type":"Entertainment"
        }
    ],
    "sg:phone":"+61 7 5529 0322",
    "sg:postcode":"4215",
    "sg:province":"QLD",
    "sg:tags":[
        "propelled",
        "jet"
    ],
    "wof:name":"Gold Coast Sea.Doo",
    "wof:placetype":"venue"
},
  "geometry": {"coordinates":[153.395217895,-27.9357051849],"type":"Point"}
}