{
  "type": "Feature",
  "properties": {
    "addr:full":"2 Elura St Modbury North SA 5092",
    "addr:housenumber":"2",
    "addr:postcode":"5092",
    "addr:street":"Elura St",
    "iso:country":"AU",
    "sg:address":"2 Elura St",
    "sg:city":"Modbury North",
    "sg:classifiers":[
        {
            "category":"Home & Garden",
            "subcategory":"Building Materials",
            "type":"Retail Goods"
        }
    ],
    "sg:phone":"+61 432 284 529",
    "sg:postcode":"5092",
    "sg:province":"SA",
    "sg:tags":[
        "lawn",
        "cutting",
        "maintenance"
    ],
    "wof:name":"Oasis Maintenance Service",
    "wof:placetype":"venue"
},
  "geometry": {"coordinates":[138.686676025,-34.8232154846],"type":"Point"}
}