{
  "type": "Feature",
  "properties": {
    "addr:full":"Milton St Mackay QLD 4740",
    "addr:postcode":"4740",
    "addr:street":"Milton St",
    "iso:country":"AU",
    "sg:address":"Milton St",
    "sg:city":"Mackay",
    "sg:classifiers":[
        {
            "category":"Arena",
            "subcategory":"Sports Club",
            "type":"Entertainment"
        }
    ],
    "sg:phone":"+61 7 4951 1680",
    "sg:postcode":"4740",
    "sg:province":"QLD",
    "sg:tags":[
        "hunt",
        "racing"
    ],
    "wof:name":"Mackay & District Greyhound Racing Club",
    "wof:placetype":"venue"
},
  "geometry": {"coordinates":[149.17506399999999,-21.161919],"type":"Point"}
}