{
  "type": "Feature",
  "properties": {
    "iso:country":"AU",
    "sg:address":"Pacific Hwy",
    "sg:city":"Nambucca Heads",
    "sg:classifiers":[
        {
            "category":"Home & Garden",
            "subcategory":"Carpets & Floor Coverings",
            "type":"Retail Goods"
        }
    ],
    "sg:phone":"+61 2 6568 6588",
    "sg:postcode":"2448",
    "sg:province":"NSW",
    "wof:name":"Your Local Paint Place",
    "wof:placetype":"venue"
},
  "geometry": {"coordinates":[152.99011200000001,-30.652456],"type":"Point"}
}