{
  "type": "Feature",
  "properties": {
    "addr:full":"131 Princes Hwy St Peters NSW 2044",
    "addr:housenumber":"131",
    "addr:postcode":"2044",
    "addr:street":"Princes Hwy",
    "iso:country":"AU",
    "sg:address":"131 Princes Hwy",
    "sg:city":"St Peters",
    "sg:classifiers":[
        {
            "category":"Manufacturing",
            "subcategory":"Buildings",
            "type":"Manufacturing & Wholesale Goods"
        }
    ],
    "sg:phone":"+61 2 9516 1556",
    "sg:postcode":"2044",
    "sg:province":"NSW",
    "sg:tags":[
        "transportable",
        "domestic",
        "relocatable"
    ],
    "wof:name":"Ark Space Pty Ltd",
    "wof:placetype":"venue"
},
  "geometry": {"coordinates":[151.17918399999999,-33.912392],"type":"Point"}
}