{
  "type": "Feature",
  "properties": {
    "addr:full":"24 Brougham Pl North Adelaide SA 5006",
    "addr:housenumber":"24",
    "addr:postcode":"5006",
    "addr:street":"Brougham Pl",
    "iso:country":"AU",
    "sg:address":"24 Brougham Pl",
    "sg:city":"North Adelaide",
    "sg:classifiers":[
        {
            "category":"Health Services",
            "subcategory":"Doctor",
            "type":"Services"
        }
    ],
    "sg:phone":"+61 8 8239 2400",
    "sg:postcode":"5006",
    "sg:province":"SA",
    "sg:tags":[
        "medical",
        "practitioner"
    ],
    "wof:name":"Gauvin P J & D M",
    "wof:placetype":"venue"
},
  "geometry": {"coordinates":[138.599685669,-34.9087295532],"type":"Point"}
}