{
  "type": "Feature",
  "properties": {
    "addr:full":"Town Square Medical Centre,Lady Cutler Ave Bankstown NSW 2200",
    "addr:postcode":"2200",
    "addr:street":"Cutler Ave",
    "iso:country":"AU",
    "sg:address":"Town Square Medical Centre,Lady Cutler Ave",
    "sg:city":"Bankstown",
    "sg:classifiers":[
        {
            "category":"Health Services",
            "subcategory":"Doctor",
            "type":"Services"
        }
    ],
    "sg:phone":"+61 2 9545 4378",
    "sg:postcode":"2200",
    "sg:province":"NSW",
    "sg:tags":[
        "podiatrist"
    ],
    "wof:name":"I C B Gait & Posture Clinic",
    "wof:placetype":"venue"
},
  "geometry": {"coordinates":[151.040176,-33.916813],"type":"Point"}
}