{
  "type": "Feature",
  "properties": {
    "iso:country":"AU",
    "sg:address":"120 Sexton St",
    "sg:city":"Tarragindi",
    "sg:classifiers":[
        {
            "category":"Real Estate",
            "subcategory":"Architect",
            "type":"Services"
        }
    ],
    "sg:phone":"+61 7 3255 8855",
    "sg:postcode":"4121",
    "sg:province":"QLD",
    "sg:tags":[
        "building",
        "designer"
    ],
    "wof:name":"Sovereign Homes Qld Pty Ltd",
    "wof:placetype":"venue"
},
  "geometry": {"coordinates":[153.045013428,-27.5176849365],"type":"Point"}
}