{
  "type": "Feature",
  "properties": {
    "addr:full":"135 Hayes St Shepparton VIC 3630",
    "addr:housenumber":"135",
    "addr:postcode":"3630",
    "addr:street":"Hayes St",
    "iso:country":"AU",
    "sg:address":"135 Hayes St",
    "sg:city":"Shepparton",
    "sg:classifiers":[
        {
            "category":"Building & Trades",
            "subcategory":"Construction",
            "type":"Services"
        }
    ],
    "sg:phone":"+61 3 5821 7451",
    "sg:postcode":"3630",
    "sg:province":"VIC",
    "sg:tags":[
        "renovation",
        "alterations",
        "extension",
        "contractor"
    ],
    "wof:name":"Crighton Strudwick",
    "wof:placetype":"venue"
},
  "geometry": {"coordinates":[145.404953003,-36.3885307312],"type":"Point"}
}