{
  "type": "Feature",
  "properties": {
    "iso:country":"AU",
    "sg:address":"PO Box 2798",
    "sg:city":"Burleigh BC",
    "sg:classifiers":[
        {
            "category":"Building & Trades",
            "subcategory":"Plumbing",
            "type":"Services"
        }
    ],
    "sg:phone":"+61 403 450 904",
    "sg:postcode":"4220",
    "sg:province":"QLD",
    "sg:tags":[
        "plumber",
        "gasfitters"
    ],
    "wof:name":"Watertite Plumbing Services",
    "wof:placetype":"venue"
},
  "geometry": {"coordinates":[153.42413330100001,-28.1080608368],"type":"Point"}
}