{
  "type": "Feature",
  "properties": {
    "iso:country":"AU",
    "sg:address":"71 Duke St",
    "sg:city":"Annerley",
    "sg:classifiers":[
        {
            "category":"Structure",
            "subcategory":"Office Building",
            "type":"Public Place"
        }
    ],
    "sg:phone":"+61 1300 798 688",
    "sg:postcode":"4103",
    "sg:province":"QLD",
    "sg:tags":[
        "wholesaler",
        "tool",
        "mfrs",
        "power"
    ],
    "wof:name":"Fein Australasia Pty Ltd",
    "wof:placetype":"venue"
},
  "geometry": {"coordinates":[153.03828430199999,-27.5054092407],"type":"Point"}
}