{
  "type": "Feature",
  "properties": {
    "addr:full":"49 Turnbull St Bairnsdale VIC 3875",
    "addr:housenumber":"49",
    "addr:postcode":"3875",
    "addr:street":"Turnbull St",
    "iso:country":"AU",
    "sg:address":"49 Turnbull St",
    "sg:city":"Bairnsdale",
    "sg:classifiers":[
        {
            "category":"Sports & Exercise",
            "subcategory":"Gym",
            "type":"Entertainment"
        }
    ],
    "sg:phone":"+61 3 5152 4909",
    "sg:postcode":"3875",
    "sg:province":"VIC",
    "sg:tags":[
        "health",
        "fitness"
    ],
    "wof:name":"Bairnsdale Outdoor Pool",
    "wof:placetype":"venue"
},
  "geometry": {"coordinates":[147.614700317,-37.8233108521],"type":"Point"}
}