{
  "type": "Feature",
  "properties": {
    "iso:country":"AU",
    "sg:address":"28 Dale St",
    "sg:city":"Brookvale",
    "sg:classifiers":[
        {
            "category":"Home & Garden",
            "subcategory":"Carpets & Floor Coverings",
            "type":"Retail Goods"
        }
    ],
    "sg:phone":"+61 417 679 681",
    "sg:postcode":"2100",
    "sg:province":"NSW",
    "sg:tags":[
        "tile",
        "wall",
        "layer"
    ],
    "wof:name":"Metrotech Ceramic Tile & Stone",
    "wof:placetype":"venue"
},
  "geometry": {"coordinates":[151.26828002900001,-33.7649879456],"type":"Point"}
}