{
  "type": "Feature",
  "properties": {
    "addr:full":"1/ 6 Kirkcaldy St Bathurst NSW 2795",
    "addr:housenumber":"/ 6",
    "addr:postcode":"2795",
    "addr:street":"Kirkcaldy St",
    "iso:country":"AU",
    "sg:address":"1/ 6 Kirkcaldy St",
    "sg:city":"Bathurst",
    "sg:classifiers":[
        {
            "category":"Autos & Motor Vehicles",
            "subcategory":"Auto Supplies",
            "type":"Retail Goods"
        }
    ],
    "sg:phone":"+61 2 6332 1628",
    "sg:postcode":"2795",
    "sg:province":"NSW",
    "sg:tags":[
        "tyre"
    ],
    "wof:name":"Archie's Breakdown & Recovery Service",
    "wof:placetype":"venue"
},
  "geometry": {"coordinates":[149.57957458499999,-33.4387016296],"type":"Point"}
}