{
  "type": "Feature",
  "properties": {
    "iso:country":"AU",
    "sg:address":"12 Evelyn St",
    "sg:city":"Toowoomba",
    "sg:classifiers":[
        {
            "category":"Food & Beverages",
            "subcategory":"Fruits & Vegetables",
            "type":"Retail Goods"
        }
    ],
    "sg:phone":"+61 7 4632 7566",
    "sg:postcode":"4350",
    "sg:province":"QLD",
    "sg:tags":[
        "wholesale"
    ],
    "wof:name":"Downs Banana Ripeners",
    "wof:placetype":"venue"
},
  "geometry": {"coordinates":[151.955399,-27.553328],"type":"Point"}
}