{
  "type": "Feature",
  "properties": {
    "addr:full":"Level 6, 36 Carrington St Sydney NSW 2000",
    "addr:housenumber":"36",
    "addr:postcode":"2000",
    "addr:street":"Carrington St",
    "iso:country":"AU",
    "sg:address":"Level 6, 36 Carrington St",
    "sg:city":"Sydney",
    "sg:classifiers":[
        {
            "category":"Banks & Credit Unions",
            "subcategory":"Financial Services",
            "type":"Services"
        }
    ],
    "sg:phone":"+61 2 8297 3300",
    "sg:postcode":"2000",
    "sg:province":"NSW",
    "sg:tags":[
        "financier"
    ],
    "wof:name":"Venture Capital Partners Pty Limited",
    "wof:placetype":"venue"
},
  "geometry": {"coordinates":[151.206466675,-33.8664360046],"type":"Point"}
}