{
  "type": "Feature",
  "properties": {
    "iso:country":"AU",
    "sg:address":"22 Carrier St",
    "sg:city":"Benalla",
    "sg:classifiers":[
        {
            "category":"Internet Cafe",
            "subcategory":"None",
            "type":"Food & Drink"
        }
    ],
    "sg:phone":"+61 3 5762 7507",
    "sg:postcode":"3672",
    "sg:province":"VIC",
    "wof:name":"Benallas Bits And Bytes",
    "wof:placetype":"venue"
},
  "geometry": {"coordinates":[145.98436000000001,-36.54739],"type":"Point"}
}