{
  "type": "Feature",
  "properties": {
    "addr:full":"16 Herbert St Montrose TAS 7010",
    "addr:housenumber":"16",
    "addr:postcode":"7010",
    "addr:street":"Herbert St",
    "iso:country":"AU",
    "sg:address":"16 Herbert St",
    "sg:city":"Montrose",
    "sg:classifiers":[
        {
            "category":"Farming",
            "subcategory":"Nursery",
            "type":"Manufacturing & Wholesale Goods"
        }
    ],
    "sg:phone":"+61 3 6272 1666",
    "sg:postcode":"7010",
    "sg:province":"TAS",
    "wof:name":"M C Tibballs & Son Pty Ltd",
    "wof:placetype":"venue"
},
  "geometry": {"coordinates":[147.269973755,-42.8262672424],"type":"Point"}
}