{
  "type": "Feature",
  "properties": {
    "addr:full":"11 - 15 Lundberg Drv Murwillumbah NSW 2484",
    "addr:housenumber":"15",
    "addr:postcode":"2484",
    "addr:street":"Lundberg Drv",
    "iso:country":"AU",
    "sg:address":"11 - 15 Lundberg Drv",
    "sg:city":"Murwillumbah",
    "sg:classifiers":[
        {
            "category":"Manufacturing",
            "subcategory":"Motor Vehicles & Parts",
            "type":"Manufacturing & Wholesale Goods"
        }
    ],
    "sg:phone":"+61 2 6672 2869",
    "sg:postcode":"2484",
    "sg:province":"NSW",
    "sg:tags":[
        "replacement"
    ],
    "wof:name":"Murwillumbah Wreckers",
    "wof:placetype":"venue"
},
  "geometry": {"coordinates":[153.417205811,-28.3309497833],"type":"Point"}
}