{
  "type": "Feature",
  "properties": {
    "iso:country":"AU",
    "sg:address":"3 Halliburton Ave",
    "sg:city":"Warnbro",
    "sg:classifiers":[
        {
            "category":"Health Services",
            "subcategory":"Doctor",
            "type":"Services"
        }
    ],
    "sg:phone":"+61 8 9593 2033",
    "sg:postcode":"6169",
    "sg:province":"WA",
    "sg:tags":[
        "medical",
        "practitioner"
    ],
    "wof:name":"Miller Kaye Dr",
    "wof:placetype":"venue"
},
  "geometry": {"coordinates":[115.761971,-32.348389],"type":"Point"}
}