{
  "type": "Feature",
  "properties": {
    "addr:full":"252 Toorak Rd South Yarra VIC 3141",
    "addr:housenumber":"252",
    "addr:postcode":"3141",
    "addr:street":"Toorak Rd",
    "iso:country":"AU",
    "sg:address":"252 Toorak Rd",
    "sg:city":"South Yarra",
    "sg:classifiers":[
        {
            "category":"Shopping",
            "subcategory":"Clothing, Apparel, & Fashions",
            "type":"Retail Goods"
        }
    ],
    "sg:phone":"+61 3 9824 0133",
    "sg:postcode":"3141",
    "sg:province":"VIC",
    "sg:tags":[
        "lady",
        "wear"
    ],
    "wof:name":"Country Road Clothing Pty Ltd",
    "wof:placetype":"venue"
},
  "geometry": {"coordinates":[144.995437622,-37.8395690918],"type":"Point"}
}