{
  "type": "Feature",
  "properties": {
    "addr:full":"648 Wyndham St Shepparton VIC 3630",
    "addr:housenumber":"648",
    "addr:postcode":"3630",
    "addr:street":"Wyndham St",
    "iso:country":"AU",
    "sg:address":"648 Wyndham St",
    "sg:city":"Shepparton",
    "sg:classifiers":[
        {
            "category":"Food & Beverages",
            "subcategory":"Bakery",
            "type":"Retail Goods"
        }
    ],
    "sg:phone":"+61 3 5821 1008",
    "sg:postcode":"3630",
    "sg:province":"VIC",
    "sg:tags":[
        "cake",
        "shop",
        "pastry"
    ],
    "wof:name":"Vita Pellegrinos Bakery",
    "wof:placetype":"venue"
},
  "geometry": {"coordinates":[145.39485168499999,-36.4009513855],"type":"Point"}
}