{
  "type": "Feature",
  "properties": {
    "addr:full":"Rear Of 148 Scarborough Beach Rd Mt Hawthorn WA 6016",
    "addr:housenumber":"rear;148",
    "addr:postcode":"6016",
    "addr:street":"Scarborough Beach Rd",
    "iso:country":"AU",
    "sg:address":"Rear Of 148 Scarborough Beach Rd",
    "sg:city":"Mt Hawthorn",
    "sg:classifiers":[
        {
            "category":"Fast Food",
            "type":"Food & Drink"
        }
    ],
    "sg:phone":"+61 8 9444 7333",
    "sg:postcode":"6016",
    "sg:province":"WA",
    "sg:tags":[
        "away",
        "take"
    ],
    "wof:name":"Mt Hawthorn Fish & Chips",
    "wof:placetype":"venue"
},
  "geometry": {"coordinates":[115.83934021,-31.9215068817],"type":"Point"}
}