{
  "type": "Feature",
  "properties": {
    "addr:full":"3 / 15 Mangrove Pl Taren Point NSW 2229",
    "addr:housenumber":"/ 15",
    "addr:postcode":"2229",
    "addr:street":"Pl",
    "iso:country":"AU",
    "sg:address":"3 / 15 Mangrove Pl",
    "sg:city":"Taren Point",
    "sg:classifiers":[
        {
            "category":"Train Station",
            "subcategory":"Rail",
            "type":"Transportation"
        }
    ],
    "sg:phone":"+61 2 9524 4701",
    "sg:postcode":"2229",
    "sg:province":"NSW",
    "sg:tags":[
        "marine",
        "engineer"
    ],
    "wof:name":"Mobile Marine Repairs Pty Ltd",
    "wof:placetype":"venue"
},
  "geometry": {"coordinates":[151.13088989299999,-34.0236053467],"type":"Point"}
}