{
  "type": "Feature",
  "properties": {
    "addr:full":"11 Lee St Deer Park VIC 3023",
    "addr:housenumber":"11",
    "addr:postcode":"3023",
    "addr:street":"Lee St",
    "iso:country":"AU",
    "sg:address":"11 Lee St",
    "sg:city":"Deer Park",
    "sg:classifiers":[
        {
            "category":"Building & Trades",
            "subcategory":"Cleaning & Sanitation",
            "type":"Services"
        }
    ],
    "sg:phone":"+61 3 9266 0682",
    "sg:postcode":"3023",
    "sg:province":"VIC",
    "sg:tags":[
        "cleaner",
        "repairer",
        "roof"
    ],
    "wof:name":"Roof Restore",
    "wof:placetype":"venue"
},
  "geometry": {"coordinates":[144.75799599999999,-37.771114],"type":"Point"}
}