{
  "type": "Feature",
  "properties": {
    "addr:full":"21 Forsyth St Wagga Wagga NSW 2650",
    "addr:housenumber":"21",
    "addr:postcode":"2650",
    "addr:street":"Forsyth St",
    "iso:country":"AU",
    "sg:address":"21 Forsyth St",
    "sg:city":"Wagga Wagga",
    "sg:classifiers":[
        {
            "category":"Communications",
            "subcategory":"Film & Video Production",
            "type":"Services"
        }
    ],
    "sg:phone":"+61 2 6921 8866",
    "sg:postcode":"2650",
    "sg:province":"NSW",
    "sg:tags":[
        "dvd",
        "library"
    ],
    "wof:name":"Civic Video",
    "wof:placetype":"venue"
},
  "geometry": {"coordinates":[147.37384033199999,-35.1143493652],"type":"Point"}
}