{
  "type": "Feature",
  "properties": {
    "addr:full":"81 Cabramatta Rd Cabramatta NSW 2166",
    "addr:housenumber":"81",
    "addr:postcode":"2166",
    "addr:street":"Cabramatta Rd",
    "iso:country":"AU",
    "sg:address":"81 Cabramatta Rd",
    "sg:city":"Cabramatta",
    "sg:classifiers":[
        {
            "category":"Personal",
            "type":"Services"
        }
    ],
    "sg:phone":"+61 2 9726 4006",
    "sg:postcode":"2166",
    "sg:province":"NSW",
    "sg:tags":[
        "counselling",
        "alcohol",
        "drug"
    ],
    "wof:name":"South West Alternative Drug & Alcohol Programme",
    "wof:placetype":"venue"
},
  "geometry": {"coordinates":[150.903366089,-33.894695282],"type":"Point"}
}