{
  "type": "Feature",
  "properties": {
    "addr:full":"27 Podmore St Dandenong VIC 3175",
    "addr:housenumber":"27",
    "addr:postcode":"3175",
    "addr:street":"Podmore St",
    "iso:country":"AU",
    "sg:address":"27 Podmore St",
    "sg:city":"Dandenong",
    "sg:classifiers":[
        {
            "category":"Retail",
            "subcategory":"Auto Repair",
            "type":"Services"
        }
    ],
    "sg:phone":"+61 3 9794 9009",
    "sg:postcode":"3175",
    "sg:province":"VIC",
    "sg:tags":[
        "repairer",
        "motor",
        "engineer"
    ],
    "wof:name":"Ian's Motor Wreckers",
    "wof:placetype":"venue"
},
  "geometry": {"coordinates":[145.21675109899999,-37.9973487854],"type":"Point"}
}