{
  "type": "Feature",
  "properties": {
    "addr:full":"33 Mensa Crt Roxburgh Park VIC 3064",
    "addr:postcode":"3064",
    "iso:country":"AU",
    "sg:address":"33 Mensa Crt",
    "sg:city":"Roxburgh Park",
    "sg:classifiers":[
        {
            "category":"Personal",
            "subcategory":"Beauty Salon",
            "type":"Services"
        }
    ],
    "sg:phone":"+61 431 072 185",
    "sg:postcode":"3064",
    "sg:province":"VIC",
    "sg:tags":[
        "hairdresser"
    ],
    "wof:name":"24 Hrs For Hair",
    "wof:placetype":"venue"
},
  "geometry": {"coordinates":[144.936965942,-37.6263122559],"type":"Point"}
}