{
  "type": "Feature",
  "properties": {
    "addr:full":"1 San Remo Pl Dural NSW 2158",
    "addr:housenumber":"1",
    "addr:postcode":"2158",
    "addr:street":"Pl",
    "iso:country":"AU",
    "sg:address":"1 San Remo Pl",
    "sg:city":"Dural",
    "sg:classifiers":[
        {
            "category":"Building & Trades",
            "subcategory":"Construction",
            "type":"Services"
        }
    ],
    "sg:phone":"+61 2 9651 2043",
    "sg:postcode":"2158",
    "sg:province":"NSW",
    "sg:tags":[
        "contractor"
    ],
    "wof:name":"Taylor J F Constructions Pty Ltd",
    "wof:placetype":"venue"
},
  "geometry": {"coordinates":[151.03358459500001,-33.675239563],"type":"Point"}
}