{
  "type": "Feature",
  "properties": {
    "addr:full":"755 Hampton St Brighton VIC 3186",
    "addr:housenumber":"755",
    "addr:postcode":"3186",
    "addr:street":"Hampton St",
    "iso:country":"AU",
    "sg:address":"755 Hampton St",
    "sg:city":"Brighton",
    "sg:classifiers":[
        {
            "category":"Health Services",
            "subcategory":"Doctor",
            "type":"Services"
        }
    ],
    "sg:phone":"+61 3 9592 3965",
    "sg:postcode":"3186",
    "sg:province":"VIC",
    "sg:tags":[
        "medical",
        "practitioner"
    ],
    "wof:name":"Owies J J",
    "wof:placetype":"venue"
},
  "geometry": {"coordinates":[145.005737305,-37.9197158813],"type":"Point"}
}