{
  "type": "Feature",
  "properties": {
    "addr:full":"3 Cossart St Boonah QLD 4310",
    "addr:housenumber":"3",
    "addr:postcode":"4310",
    "addr:street":"Cossart St",
    "iso:country":"AU",
    "sg:address":"3 Cossart St",
    "sg:city":"Boonah",
    "sg:classifiers":[
        {
            "category":"Home & Garden",
            "subcategory":"Hardware",
            "type":"Retail Goods"
        }
    ],
    "sg:phone":"+61 7 5463 2888",
    "sg:postcode":"4310",
    "sg:province":"QLD",
    "sg:tags":[
        "plumber",
        "supply"
    ],
    "wof:name":"Fassifern Plumbing Supplies & Pumps",
    "wof:placetype":"venue"
},
  "geometry": {"coordinates":[152.68380737300001,-27.9978485107],"type":"Point"}
}