{
  "type": "Feature",
  "properties": {
    "iso:country":"AU",
    "sg:address":"49 High St",
    "sg:city":"Redcliffe",
    "sg:classifiers":[
        {
            "category":"Retail",
            "subcategory":"Auto Repair",
            "type":"Services"
        }
    ],
    "sg:phone":"+61 7 3284 5900",
    "sg:postcode":"4020",
    "sg:province":"QLD",
    "sg:tags":[
        "beater",
        "painter",
        "panel"
    ],
    "wof:name":"Milner's Smash Repairs",
    "wof:placetype":"venue"
},
  "geometry": {"coordinates":[153.092224,-27.226475],"type":"Point"}
}