{
  "type": "Feature",
  "properties": {
    "iso:country":"AU",
    "sg:address":"4 Norton St",
    "sg:city":"Leichhardt",
    "sg:classifiers":[
        {
            "category":"Health Services",
            "subcategory":"Doctor",
            "type":"Services"
        }
    ],
    "sg:phone":"+61 2 9560 5844",
    "sg:postcode":"2040",
    "sg:province":"NSW",
    "sg:tags":[
        "medical",
        "practitioner"
    ],
    "wof:name":"Bennelong X-Ray",
    "wof:placetype":"venue"
},
  "geometry": {"coordinates":[151.15744000000001,-33.887726],"type":"Point"}
}