{
  "type": "Feature",
  "properties": {
    "addr:full":"61 North East Rd Collinswood SA 5081",
    "addr:housenumber":"61",
    "addr:postcode":"5081",
    "addr:street":"North East Rd",
    "iso:country":"AU",
    "sg:address":"61 North East Rd",
    "sg:city":"Collinswood",
    "sg:classifiers":[
        {
            "category":"Fast Food",
            "type":"Food & Drink"
        }
    ],
    "sg:phone":"+61 8 8269 5220",
    "sg:postcode":"5081",
    "sg:province":"SA",
    "sg:tags":[
        "away",
        "take"
    ],
    "wof:name":"McDonald's Family Restaurants",
    "wof:placetype":"venue"
},
  "geometry": {"coordinates":[138.613449097,-34.8890075684],"type":"Point"}
}