{
  "type": "Feature",
  "properties": {
    "iso:country":"AU",
    "sg:address":"220 Ingles St",
    "sg:city":"Port Melbourne",
    "sg:classifiers":[
        {
            "category":"Education",
            "subcategory":"University",
            "type":"Public Place"
        }
    ],
    "sg:phone":"+61 3 9676 9000",
    "sg:postcode":"3207",
    "sg:province":"VIC",
    "sg:tags":[
        "college",
        "tertiary"
    ],
    "wof:name":"The Australian Academy Of Design",
    "wof:placetype":"venue"
},
  "geometry": {"coordinates":[144.941452,-37.828979],"type":"Point"}
}