{
  "type": "Feature",
  "properties": {
    "iso:country":"AU",
    "sg:address":"6 Palma Pl",
    "sg:city":"Coogee",
    "sg:classifiers":[
        {
            "category":"Banks & Credit Unions",
            "subcategory":"Investment Brokerage",
            "type":"Services"
        }
    ],
    "sg:phone":"+61 8 9434 6453",
    "sg:postcode":"6166",
    "sg:province":"WA",
    "wof:name":"BKS Financial Services",
    "wof:placetype":"venue"
},
  "geometry": {"coordinates":[115.774544,-32.122799],"type":"Point"}
}