{
  "type": "Feature",
  "properties": {
    "addr:full":"10 Scarborough St Southport QLD 4215",
    "addr:housenumber":"10",
    "addr:postcode":"4215",
    "addr:street":"Scarborough St",
    "iso:country":"AU",
    "sg:address":"10 Scarborough St",
    "sg:city":"Southport",
    "sg:classifiers":[
        {
            "category":"Health Services",
            "subcategory":"Dentist",
            "type":"Services"
        }
    ],
    "sg:phone":"+61 7 5571 0866",
    "sg:postcode":"4215",
    "sg:province":"QLD",
    "wof:name":"Mendoza Tony Dr",
    "wof:placetype":"venue"
},
  "geometry": {"coordinates":[153.415283203,-27.9723339081],"type":"Point"}
}