{
  "type": "Feature",
  "properties": {
    "addr:full":"2 Baker St Uranquinty NSW 2652",
    "addr:housenumber":"2",
    "addr:postcode":"2652",
    "addr:street":"Baker St",
    "iso:country":"AU",
    "sg:address":"2 Baker St",
    "sg:city":"Uranquinty",
    "sg:classifiers":[
        {
            "category":"Building & Trades",
            "subcategory":"Pest Control",
            "type":"Services"
        }
    ],
    "sg:phone":"+61 2 6922 9743",
    "sg:postcode":"2652",
    "sg:province":"NSW",
    "wof:name":"Prince's Pest Control",
    "wof:placetype":"venue"
},
  "geometry": {"coordinates":[147.24259948700001,-35.1890830994],"type":"Point"}
}