{
  "type": "Feature",
  "properties": {
    "addr:full":"2/ 11 Carol Ave Springwood QLD 4127",
    "addr:housenumber":"/ 11",
    "addr:postcode":"4127",
    "addr:street":"Carol Ave",
    "iso:country":"AU",
    "sg:address":"2/ 11 Carol Ave",
    "sg:city":"Springwood",
    "sg:classifiers":[
        {
            "category":"Professional",
            "subcategory":"Printing & Photocopies",
            "type":"Services"
        }
    ],
    "sg:phone":"+61 7 3208 2871",
    "sg:postcode":"4127",
    "sg:province":"QLD",
    "sg:tags":[
        "laminating"
    ],
    "wof:name":"Image Techniques Pty Ltd",
    "wof:placetype":"venue"
},
  "geometry": {"coordinates":[153.127227783,-27.6167316437],"type":"Point"}
}