{
  "type": "Feature",
  "properties": {
    "addr:full":"8 Weatherall Rd Beaumaris VIC 3193",
    "addr:housenumber":"8",
    "addr:postcode":"3193",
    "addr:street":"Weatherall Rd",
    "iso:country":"AU",
    "sg:address":"8 Weatherall Rd",
    "sg:city":"Beaumaris",
    "sg:classifiers":[
        {
            "category":"Building & Trades",
            "subcategory":"Construction",
            "type":"Services"
        }
    ],
    "sg:phone":"+61 3 9589 1889",
    "sg:postcode":"3193",
    "sg:province":"VIC",
    "sg:tags":[
        "contractor"
    ],
    "wof:name":"G.C.R. Treadwell & Co",
    "wof:placetype":"venue"
},
  "geometry": {"coordinates":[145.03669738799999,-37.9704055786],"type":"Point"}
}