{
  "type": "Feature",
  "properties": {
    "addr:full":"597 Kalamunda Rd High Wycombe WA 6057",
    "addr:housenumber":"597",
    "addr:postcode":"6057",
    "addr:street":"Kalamunda Rd",
    "iso:country":"AU",
    "sg:address":"597 Kalamunda Rd",
    "sg:city":"High Wycombe",
    "sg:classifiers":[
        {
            "category":"Autos & Motor Vehicles",
            "subcategory":"Auto Supplies",
            "type":"Retail Goods"
        }
    ],
    "sg:phone":"+61 8 9352 8808",
    "sg:postcode":"6057",
    "sg:province":"WA",
    "sg:tags":[
        "equipment",
        "part",
        "truck"
    ],
    "wof:name":"National Trucking Supplies",
    "wof:placetype":"venue"
},
  "geometry": {"coordinates":[116.012550354,-31.9391765594],"type":"Point"}
}