{
  "type": "Feature",
  "properties": {
    "addr:full":"16 Tooke St Bar Beach NSW 2300",
    "addr:housenumber":"16",
    "addr:postcode":"2300",
    "addr:street":"Tooke St",
    "iso:country":"AU",
    "sg:address":"16 Tooke St",
    "sg:city":"Bar Beach",
    "sg:classifiers":[
        {
            "category":"Shopping",
            "subcategory":"Musical Instruments",
            "type":"Retail Goods"
        }
    ],
    "sg:phone":"+61 2 4929 7149",
    "sg:postcode":"2300",
    "sg:province":"NSW",
    "sg:tags":[
        "musician",
        "agent"
    ],
    "wof:name":"The Cremona String Ensemble",
    "wof:placetype":"venue"
},
  "geometry": {"coordinates":[151.76913500000001,-32.936878],"type":"Point"}
}