{
  "type": "Feature",
  "properties": {
    "iso:country":"AU",
    "sg:address":"16 Tooke St",
    "sg:city":"Bar Beach",
    "sg:classifiers":[
        {
            "category":"Shopping",
            "subcategory":"Musical Instruments",
            "type":"Retail Goods"
        }
    ],
    "sg:phone":"+61 2 4929 7149",
    "sg:postcode":"2300",
    "sg:province":"NSW",
    "sg:tags":[
        "musician",
        "agent"
    ],
    "wof:name":"The Cremona String Ensemble",
    "wof:placetype":"venue"
},
  "geometry": {"coordinates":[151.769135,-32.936878],"type":"Point"}
}