{
  "type": "Feature",
  "properties": {
    "iso:country":"AU",
    "sg:address":"245 Chasemore Rd",
    "sg:city":"Cardinia",
    "sg:classifiers":[
        {
            "category":"Retail",
            "subcategory":"Auto Repair",
            "type":"Services"
        }
    ],
    "sg:phone":"+61 3 5998 8376",
    "sg:postcode":"3978",
    "sg:province":"VIC",
    "sg:tags":[
        "bus",
        "truck"
    ],
    "wof:name":"Sherratts Auto",
    "wof:placetype":"venue"
},
  "geometry": {"coordinates":[145.411819458,-38.1250572205],"type":"Point"}
}