{
  "type": "Feature",
  "properties": {
    "addr:full":"61 Dalgety St East Fremantle WA 6158",
    "addr:housenumber":"61",
    "addr:postcode":"6158",
    "addr:street":"Dalgety St",
    "iso:country":"AU",
    "sg:address":"61 Dalgety St",
    "sg:city":"East Fremantle",
    "sg:classifiers":[
        {
            "category":"Real Estate",
            "subcategory":"Architect",
            "type":"Services"
        }
    ],
    "sg:phone":"+61 8 9339 7607",
    "sg:postcode":"6158",
    "sg:province":"WA",
    "wof:name":"Connor M E",
    "wof:placetype":"venue"
},
  "geometry": {"coordinates":[115.771019,-32.044395],"type":"Point"}
}