{
  "type": "Feature",
  "properties": {
    "iso:country":"AU",
    "sg:address":"5th Floor 401 Sussex St",
    "sg:city":"Sydney",
    "sg:classifiers":[
        {
            "category":"Health Services",
            "subcategory":"Health Practitioner",
            "type":"Services"
        }
    ],
    "sg:phone":"+61 402 209 026",
    "sg:postcode":"2000",
    "sg:province":"NSW",
    "sg:tags":[
        "hypnotherapy"
    ],
    "wof:name":"Tommy Haung",
    "wof:placetype":"venue"
},
  "geometry": {"coordinates":[151.20463562,-33.8782501221],"type":"Point"}
}