{
  "type": "Feature",
  "properties": {
    "addr:full":"17 Droughty Point Rd Rokeby TAS 7019",
    "addr:housenumber":"17",
    "addr:postcode":"7019",
    "addr:street":"Droughty Point Rd",
    "iso:country":"AU",
    "sg:address":"17 Droughty Point Rd",
    "sg:city":"Rokeby",
    "sg:classifiers":[
        {
            "category":"Retail",
            "subcategory":"Auto Repair",
            "type":"Services"
        }
    ],
    "sg:phone":"+61 3 6247 7013",
    "sg:postcode":"7019",
    "sg:province":"TAS",
    "sg:tags":[
        "body",
        "builder",
        "motor"
    ],
    "wof:name":"Archer's Bodyworks Pty Ltd",
    "wof:placetype":"venue"
},
  "geometry": {"coordinates":[147.44192504899999,-42.9018516541],"type":"Point"}
}