{
  "type": "Feature",
  "properties": {
    "iso:country":"AU",
    "sg:address":"22 Cupania St",
    "sg:city":"Victoria Point",
    "sg:classifiers":[
        {
            "category":"Utilities",
            "subcategory":"Water",
            "type":"Services"
        }
    ],
    "sg:phone":"+61 419 164 024",
    "sg:postcode":"4165",
    "sg:province":"QLD",
    "sg:tags":[
        "hot",
        "system"
    ],
    "wof:name":"Bay Coast Electrical",
    "wof:placetype":"venue"
},
  "geometry": {"coordinates":[153.30427551299999,-27.5749473572],"type":"Point"}
}