{
  "type": "Feature",
  "properties": {
    "iso:country":"AU",
    "sg:address":"65 Buvelot St",
    "sg:city":"Weston",
    "sg:classifiers":[
        {
            "category":"Building & Trades",
            "subcategory":"Construction",
            "type":"Services"
        }
    ],
    "sg:phone":"+61 418 632 223",
    "sg:postcode":"2611",
    "sg:province":"ACT",
    "sg:tags":[
        "joiner",
        "carpenter"
    ],
    "wof:name":"Bedford Carpentry Pty Ltd",
    "wof:placetype":"venue"
},
  "geometry": {"coordinates":[149.065551758,-35.3431625366],"type":"Point"}
}