{
  "type": "Feature",
  "properties": {
    "addr:full":"410 Lonsdale St Melbourne VIC 3000",
    "addr:housenumber":"410",
    "addr:postcode":"3000",
    "addr:street":"Lonsdale St",
    "iso:country":"AU",
    "sg:address":"410 Lonsdale St",
    "sg:city":"Melbourne",
    "sg:classifiers":[
        {
            "category":"Sports & Exercise",
            "subcategory":"Gym",
            "type":"Entertainment"
        }
    ],
    "sg:phone":"+61 3 9670 6702",
    "sg:postcode":"3000",
    "sg:province":"VIC",
    "sg:tags":[
        "meditation"
    ],
    "wof:name":"KI Health International",
    "wof:placetype":"venue"
},
  "geometry": {"coordinates":[144.96022033700001,-37.8127288818],"type":"Point"}
}