{
  "type": "Feature",
  "properties": {
    "iso:country":"AU",
    "sg:address":"Junction Rd",
    "sg:city":"Maitland",
    "sg:classifiers":[
        {
            "category":"Education",
            "subcategory":"School",
            "type":"Public Place"
        }
    ],
    "sg:phone":"+61 8 8832 2613",
    "sg:postcode":"5573",
    "sg:province":"SA",
    "sg:tags":[
        "state",
        "except",
        "nsw"
    ],
    "wof:name":"Maitland Area School",
    "wof:placetype":"venue"
},
  "geometry": {"coordinates":[137.675018311,-34.3697891235],"type":"Point"}
}