{
  "type": "Feature",
  "properties": {
    "iso:country":"AU",
    "sg:address":"29 Churchill St",
    "sg:city":"Jamberoo",
    "sg:classifiers":[
        {
            "category":"Education",
            "subcategory":"School",
            "type":"Public Place"
        }
    ],
    "sg:phone":"+61 2 4236 0173",
    "sg:postcode":"2533",
    "sg:province":"NSW",
    "sg:tags":[
        "state",
        "-",
        "nsw"
    ],
    "wof:name":"Jamberoo Public School",
    "wof:placetype":"venue"
},
  "geometry": {"coordinates":[150.773895264,-34.644908905],"type":"Point"}
}