{
  "type": "Feature",
  "properties": {
    "iso:country":"AU",
    "sg:address":"87 Chester Rd",
    "sg:city":"Annerley",
    "sg:classifiers":[
        {
            "category":"Retail",
            "subcategory":"Repair Shop",
            "type":"Services"
        }
    ],
    "sg:phone":"+61 7 3892 7653",
    "sg:postcode":"4103",
    "sg:province":"QLD",
    "sg:tags":[
        "machine",
        "repairs",
        "part",
        "dryer",
        "washing"
    ],
    "wof:name":"Five Star Appliance Service",
    "wof:placetype":"venue"
},
  "geometry": {"coordinates":[153.03503418,-27.5160255432],"type":"Point"}
}