{
  "type": "Feature",
  "properties": {
    "iso:country":"AU",
    "sg:address":"83 Wilmot St",
    "sg:city":"Burnie",
    "sg:classifiers":[
        {
            "category":"Health Services",
            "subcategory":"Doctor",
            "type":"Services"
        }
    ],
    "sg:phone":"+61 3 6431 3244",
    "sg:postcode":"7320",
    "sg:province":"TAS",
    "sg:tags":[
        "medical",
        "practitioner"
    ],
    "wof:name":"Wild I",
    "wof:placetype":"venue"
},
  "geometry": {"coordinates":[145.901428,-41.050495],"type":"Point"}
}