{
  "type": "Feature",
  "properties": {
    "iso:country":"AU",
    "sg:address":"83 Hiller St",
    "sg:city":"Devonport",
    "sg:classifiers":[
        {
            "category":"Building & Trades",
            "subcategory":"Construction",
            "type":"Services"
        }
    ],
    "sg:phone":"+61 3 6424 2723",
    "sg:postcode":"7310",
    "sg:province":"TAS",
    "sg:tags":[
        "joinery"
    ],
    "wof:name":"Joinery Dotcom",
    "wof:placetype":"venue"
},
  "geometry": {"coordinates":[146.357055664,-41.1901893616],"type":"Point"}
}