{
  "type": "Feature",
  "properties": {
    "iso:country":"AU",
    "sg:address":"91b Arthur St",
    "sg:city":"Magill",
    "sg:classifiers":[
        {
            "category":"Personal",
            "subcategory":"Massage",
            "type":"Services"
        }
    ],
    "sg:phone":"+61 414 838 637",
    "sg:postcode":"5072",
    "sg:province":"SA",
    "sg:tags":[
        "therapy"
    ],
    "wof:name":"Healing Spirit Massage & Natural Therapies",
    "wof:placetype":"venue"
},
  "geometry": {"coordinates":[138.668792725,-34.9034843445],"type":"Point"}
}