{
  "type": "Feature",
  "properties": {
    "iso:country":"AU",
    "sg:address":"8 Arcadia Crt",
    "sg:city":"Highfields",
    "sg:classifiers":[
        {
            "category":"Building & Trades",
            "subcategory":"Construction",
            "type":"Services"
        }
    ],
    "sg:phone":"+61 418 770 488",
    "sg:postcode":"4352",
    "sg:province":"QLD",
    "sg:tags":[
        "ceiling"
    ],
    "wof:name":"Commplast",
    "wof:placetype":"venue"
},
  "geometry": {"coordinates":[151.94657900000001,-27.457783],"type":"Point"}
}