{
  "type": "Feature",
  "properties": {
    "iso:country":"AU",
    "sg:address":"1223 High St",
    "sg:city":"Armadale",
    "sg:classifiers":[
        {
            "category":"Professional",
            "subcategory":"Art Services",
            "type":"Services"
        }
    ],
    "sg:phone":"+61 3 9824 6914",
    "sg:postcode":"3143",
    "sg:province":"VIC",
    "sg:tags":[
        "interior",
        "decorator"
    ],
    "wof:name":"A Day On Earth",
    "wof:placetype":"venue"
},
  "geometry": {"coordinates":[145.02835082999999,-37.856338501],"type":"Point"}
}