{
  "type": "Feature",
  "properties": {
    "addr:full":"19 Ely St Wangaratta VIC 3677",
    "addr:housenumber":"19",
    "addr:postcode":"3677",
    "addr:street":"Ely St",
    "iso:country":"AU",
    "sg:address":"19 Ely St",
    "sg:city":"Wangaratta",
    "sg:classifiers":[
        {
            "category":"Health Services",
            "subcategory":"Doctor",
            "type":"Services"
        }
    ],
    "sg:phone":"+61 3 5721 2141",
    "sg:postcode":"3677",
    "sg:province":"VIC",
    "sg:tags":[
        "medical",
        "practitioner"
    ],
    "wof:name":"Keenan P J",
    "wof:placetype":"venue"
},
  "geometry": {"coordinates":[146.326095581,-36.3567886353],"type":"Point"}
}