{
  "type": "Feature",
  "properties": {
    "addr:full":"Unit 3/ 2 Mint St East Victoria Park WA 6101",
    "addr:housenumber":"2",
    "addr:postcode":"6101",
    "addr:street":"Mint St",
    "iso:country":"AU",
    "sg:address":"Unit 3/ 2 Mint St",
    "sg:city":"East Victoria Park",
    "sg:classifiers":[
        {
            "category":"Professional",
            "subcategory":"Research",
            "type":"Services"
        }
    ],
    "sg:phone":"+61 8 9355 2199",
    "sg:postcode":"6101",
    "sg:province":"WA",
    "sg:tags":[
        "market"
    ],
    "wof:name":"ASK AUSTRALIA Fieldwork Services",
    "wof:placetype":"venue"
},
  "geometry": {"coordinates":[115.903160095,-31.9842338562],"type":"Point"}
}