{
  "type": "Feature",
  "properties": {
    "addr:full":"1 Tallai Rd Mudgeeraba QLD 4213",
    "addr:housenumber":"1",
    "addr:postcode":"4213",
    "addr:street":"Tallai Rd",
    "iso:country":"AU",
    "sg:address":"1 Tallai Rd",
    "sg:city":"Mudgeeraba",
    "sg:classifiers":[
        {
            "category":"Food & Beverages",
            "subcategory":"Supermarket",
            "type":"Retail Goods"
        }
    ],
    "sg:phone":"+61 7 5530 5235",
    "sg:postcode":"4213",
    "sg:province":"QLD",
    "sg:tags":[
        "grocery",
        "store"
    ],
    "wof:name":"Tallai General Store",
    "wof:placetype":"venue"
},
  "geometry": {"coordinates":[153.353057861,-28.0703868866],"type":"Point"}
}