{
  "type": "Feature",
  "properties": {
    "addr:full":"18 Patterson Ave West Pymble NSW 2073",
    "addr:housenumber":"18",
    "addr:postcode":"2073",
    "addr:street":"Patterson Ave",
    "iso:country":"AU",
    "sg:address":"18 Patterson Ave",
    "sg:city":"West Pymble",
    "sg:classifiers":[
        {
            "category":"Building & Trades",
            "subcategory":"Landscaping Services",
            "type":"Services"
        }
    ],
    "sg:phone":"+61 2 9499 9156",
    "sg:postcode":"2073",
    "sg:province":"NSW",
    "sg:tags":[
        "gardener"
    ],
    "wof:name":"Pymble Wizard Handyman & Gardening Service",
    "wof:placetype":"venue"
},
  "geometry": {"coordinates":[151.12547302199999,-33.7636985779],"type":"Point"}
}