{
  "type": "Feature",
  "properties": {
    "addr:full":"7 Chambers Rd Woodford QLD 4514",
    "addr:housenumber":"7",
    "addr:postcode":"4514",
    "addr:street":"Chambers Rd",
    "iso:country":"AU",
    "sg:address":"7 Chambers Rd",
    "sg:city":"Woodford",
    "sg:classifiers":[
        {
            "category":"Shopping",
            "type":"Retail Goods"
        }
    ],
    "sg:phone":"+61 7 5496 3420",
    "sg:postcode":"4514",
    "sg:province":"QLD",
    "sg:tags":[
        "produce",
        "grain"
    ],
    "wof:name":"Woodford Landscape Supplies Pty Ltd",
    "wof:placetype":"venue"
},
  "geometry": {"coordinates":[152.78973400000001,-26.972141],"type":"Point"}
}