{
  "type": "Feature",
  "properties": {
    "addr:full":"1 Cosmos Crt Doncaster East VIC 3109",
    "addr:housenumber":"1",
    "addr:postcode":"3109",
    "addr:street":"Cosmos Crt",
    "iso:country":"AU",
    "sg:address":"1 Cosmos Crt",
    "sg:city":"Doncaster East",
    "sg:classifiers":[
        {
            "category":"Professional",
            "subcategory":"Computer Services",
            "type":"Services"
        }
    ],
    "sg:phone":"+61 3 9894 5371",
    "sg:postcode":"3109",
    "sg:province":"VIC",
    "sg:tags":[
        "repairs",
        "upgrade",
        "equipment"
    ],
    "wof:name":"Technet Solutions Pty. Ltd.",
    "wof:placetype":"venue"
},
  "geometry": {"coordinates":[145.175537109,-37.7705841064],"type":"Point"}
}