{
  "type": "Feature",
  "properties": {
    "addr:full":"13a Wingate Ave Ascot Vale VIC 3032",
    "addr:housenumber":"13a",
    "addr:postcode":"3032",
    "addr:street":"Wingate Ave",
    "iso:country":"AU",
    "sg:address":"13a Wingate Ave",
    "sg:city":"Ascot Vale",
    "sg:classifiers":[
        {
            "category":"Social Services",
            "subcategory":"Child Care",
            "type":"Services"
        }
    ],
    "sg:phone":"+61 3 9376 5244",
    "sg:postcode":"3032",
    "sg:province":"VIC",
    "sg:tags":[
        "support",
        "health"
    ],
    "wof:name":"Maternal & Child Health Centres",
    "wof:placetype":"venue"
},
  "geometry": {"coordinates":[144.91952499999999,-37.779224],"type":"Point"}
}