{
  "type": "Feature",
  "properties": {
    "addr:full":"Ste 4/6- 8 Old Castle Hill Rd Castle Hill NSW 2154",
    "addr:housenumber":"8",
    "addr:postcode":"2154",
    "addr:street":"Old Castle Hill Rd",
    "iso:country":"AU",
    "sg:address":"Ste 4/6- 8 Old Castle Hill Rd",
    "sg:city":"Castle Hill",
    "sg:classifiers":[
        {
            "category":"Professional",
            "subcategory":"Accounting & Tax Preparation",
            "type":"Services"
        }
    ],
    "sg:phone":"+61 2 9899 1530",
    "sg:postcode":"2154",
    "sg:province":"NSW",
    "sg:tags":[
        "accountant",
        "auditor"
    ],
    "wof:name":"William Groves & Associates",
    "wof:placetype":"venue"
},
  "geometry": {"coordinates":[151.00833129899999,-33.7307128906],"type":"Point"}
}