{
  "type": "Feature",
  "properties": {
    "addr:full":"26 Bluegrass St Little Mountain QLD 4551",
    "addr:housenumber":"26",
    "addr:postcode":"4551",
    "addr:street":"Bluegrass St",
    "iso:country":"AU",
    "sg:address":"26 Bluegrass St",
    "sg:city":"Little Mountain",
    "sg:classifiers":[
        {
            "category":"Building & Trades",
            "subcategory":"Construction",
            "type":"Services"
        }
    ],
    "sg:phone":"+61 7 5491 1391",
    "sg:postcode":"4551",
    "sg:province":"QLD",
    "sg:tags":[
        "ceiling"
    ],
    "wof:name":"R G & D A Tolhurst Plasterers",
    "wof:placetype":"venue"
},
  "geometry": {"coordinates":[153.081375122,-26.7998905182],"type":"Point"}
}