{
  "type": "Feature",
  "properties": {
    "addr:full":"25 Lamerough Pde Golden Beach QLD 4551",
    "addr:housenumber":"25",
    "addr:postcode":"4551",
    "addr:street":"Lamerough Pde",
    "iso:country":"AU",
    "sg:address":"25 Lamerough Pde",
    "sg:city":"Golden Beach",
    "sg:classifiers":[
        {
            "category":"Building & Trades",
            "subcategory":"Pest Control",
            "type":"Services"
        }
    ],
    "sg:phone":"+61 7 5492 1500",
    "sg:postcode":"4551",
    "sg:province":"QLD",
    "wof:name":"Expect The Best",
    "wof:placetype":"venue"
},
  "geometry": {"coordinates":[153.118286133,-26.8307952881],"type":"Point"}
}