{
  "type": "Feature",
  "properties": {
    "addr:full":"110 Park Ave Ashfield NSW 2131",
    "addr:housenumber":"110",
    "addr:postcode":"2131",
    "addr:street":"Park Ave",
    "iso:country":"AU",
    "sg:address":"110 Park Ave",
    "sg:city":"Ashfield",
    "sg:classifiers":[
        {
            "category":"Social Services",
            "subcategory":"Child Care",
            "type":"Services"
        }
    ],
    "sg:phone":"+61 2 8701 4742",
    "sg:postcode":"2131",
    "sg:province":"NSW",
    "sg:tags":[
        "equipment",
        "identification"
    ],
    "wof:name":"Omega ID & Access Supplies",
    "wof:placetype":"venue"
},
  "geometry": {"coordinates":[151.12405395499999,-33.8940353394],"type":"Point"}
}