{
  "type": "Feature",
  "properties": {
    "addr:full":"13 Littlefield St Blackwater QLD 4717",
    "addr:housenumber":"13",
    "addr:postcode":"4717",
    "addr:street":"Littlefield St",
    "iso:country":"AU",
    "sg:address":"13 Littlefield St",
    "sg:city":"Blackwater",
    "sg:classifiers":[
        {
            "category":"Retail",
            "subcategory":"Veterinary Services",
            "type":"Services"
        }
    ],
    "sg:phone":"+61 7 4982 5222",
    "sg:postcode":"4717",
    "sg:province":"QLD",
    "sg:tags":[
        "surgeon"
    ],
    "wof:name":"Blackwater Veterinary Clinic",
    "wof:placetype":"venue"
},
  "geometry": {"coordinates":[148.87524400000001,-23.577208],"type":"Point"}
}