{
  "type": "Feature",
  "properties": {
    "addr:full":"10 Beatty St Rochedale QLD 4123",
    "addr:housenumber":"10",
    "addr:postcode":"4123",
    "addr:street":"Beatty St",
    "iso:country":"AU",
    "sg:address":"10 Beatty St",
    "sg:city":"Rochedale",
    "sg:classifiers":[
        {
            "category":"Health Services",
            "subcategory":"Doctor",
            "type":"Services"
        }
    ],
    "sg:phone":"+61 7 3341 7157",
    "sg:postcode":"4123",
    "sg:province":"QLD",
    "sg:tags":[
        "occupational",
        "safety"
    ],
    "wof:name":"Safety Inductions Pty Ltd",
    "wof:placetype":"venue"
},
  "geometry": {"coordinates":[153.124755859,-27.5941085815],"type":"Point"}
}