{
  "type": "Feature",
  "properties": {
    "addr:full":"Elizabeth St Kenilworth QLD 4574",
    "addr:postcode":"4574",
    "addr:street":"Elizabeth St",
    "iso:country":"AU",
    "sg:address":"Elizabeth St",
    "sg:city":"Kenilworth",
    "sg:classifiers":[
        {
            "category":"Food & Beverages",
            "subcategory":"Supermarket",
            "type":"Retail Goods"
        }
    ],
    "sg:phone":"+61 7 5446 0195",
    "sg:postcode":"4574",
    "sg:province":"QLD",
    "sg:tags":[
        "grocery",
        "store"
    ],
    "wof:name":"Four Square Stores (Qld) Ltd",
    "wof:placetype":"venue"
},
  "geometry": {"coordinates":[152.727463,-26.595497],"type":"Point"}
}