{
  "type": "Feature",
  "properties": {
    "addr:full":"19 Careel Bay Crs Avalon NSW 2107",
    "addr:housenumber":"19",
    "addr:postcode":"2107",
    "addr:street":"Careel Bay Crs",
    "iso:country":"AU",
    "sg:address":"19 Careel Bay Crs",
    "sg:city":"Avalon",
    "sg:classifiers":[
        {
            "category":"Building & Trades",
            "subcategory":"Construction",
            "type":"Services"
        }
    ],
    "sg:phone":"+61 2 9973 2775",
    "sg:postcode":"2107",
    "sg:province":"NSW",
    "sg:tags":[
        "joiner",
        "carpenter"
    ],
    "wof:name":"Paul Meehan",
    "wof:placetype":"venue"
},
  "geometry": {"coordinates":[151.32705688499999,-33.6231307983],"type":"Point"}
}