{
  "type": "Feature",
  "properties": {
    "iso:country":"AU",
    "sg:address":"116 Lyons St North",
    "sg:city":"Ballarat",
    "sg:classifiers":[
        {
            "category":"Personal",
            "subcategory":"Massage",
            "type":"Services"
        }
    ],
    "sg:phone":"+61 3 5333 4083",
    "sg:postcode":"3350",
    "sg:province":"VIC",
    "sg:tags":[
        "therapy"
    ],
    "wof:name":"Trevor Close",
    "wof:placetype":"venue"
},
  "geometry": {"coordinates":[143.852554,-37.557823],"type":"Point"}
}