{
  "type": "Feature",
  "properties": {
    "addr:full":"8 May Rd Dee Why NSW 2099",
    "addr:housenumber":"8",
    "addr:postcode":"2099",
    "addr:street":"May Rd",
    "iso:country":"AU",
    "sg:address":"8 May Rd",
    "sg:city":"Dee Why",
    "sg:classifiers":[
        {
            "category":"Professional",
            "subcategory":"Computer Services",
            "type":"Services"
        }
    ],
    "sg:phone":"+61 2 9982 3550",
    "sg:postcode":"2099",
    "sg:province":"NSW",
    "sg:tags":[
        "consultant",
        "system"
    ],
    "wof:name":"Data Stream Pty Ltd",
    "wof:placetype":"venue"
},
  "geometry": {"coordinates":[151.28126525900001,-33.7559967041],"type":"Point"}
}