{
  "type": "Feature",
  "properties": {
    "addr:full":"16- 20 Military Rd Bellevue WA 6056",
    "addr:housenumber":"20",
    "addr:postcode":"6056",
    "addr:street":"Military Rd",
    "iso:country":"AU",
    "sg:address":"16- 20 Military Rd",
    "sg:city":"Bellevue",
    "sg:classifiers":[
        {
            "category":"Building & Trades",
            "subcategory":"Construction",
            "type":"Services"
        }
    ],
    "sg:phone":"+61 8 9274 7820",
    "sg:postcode":"6056",
    "sg:province":"WA",
    "sg:tags":[
        "earth",
        "excavating",
        "moving",
        "contractor"
    ],
    "wof:name":"Plantman Equipment",
    "wof:placetype":"venue"
},
  "geometry": {"coordinates":[116.017303467,-31.9020271301],"type":"Point"}
}