{
  "type": "Feature",
  "properties": {
    "addr:full":"10 Asheville Pde Landsdale WA 6065",
    "addr:housenumber":"10",
    "addr:postcode":"6065",
    "addr:street":"Asheville Pde",
    "iso:country":"AU",
    "sg:address":"10 Asheville Pde",
    "sg:city":"Landsdale",
    "sg:classifiers":[
        {
            "category":"Professional",
            "subcategory":"Detective & Security Services",
            "type":"Services"
        }
    ],
    "sg:phone":"+61 411 030 715",
    "sg:postcode":"6065",
    "sg:province":"WA",
    "sg:tags":[
        "consultant",
        "system"
    ],
    "wof:name":"Quality Guards",
    "wof:placetype":"venue"
},
  "geometry": {"coordinates":[115.85932159399999,-31.8027572632],"type":"Point"}
}