{
  "type": "Feature",
  "properties": {
    "iso:country":"AU",
    "sg:address":"Fcty4/ 64 Rebecca Drv",
    "sg:city":"Ravenhall",
    "sg:classifiers":[
        {
            "category":"Retail",
            "subcategory":"Auto Repair",
            "type":"Services"
        }
    ],
    "sg:phone":"+61 3 9360 5770",
    "sg:postcode":"3023",
    "sg:province":"VIC",
    "sg:tags":[
        "repairer",
        "motor",
        "engineer"
    ],
    "wof:name":"Western Pro",
    "wof:placetype":"venue"
},
  "geometry": {"coordinates":[144.749298,-37.763729],"type":"Point"}
}