{
  "type": "Feature",
  "properties": {
    "addr:full":"Fcty4/ 64 Rebecca Drv Ravenhall VIC 3023",
    "addr:housenumber":"64",
    "addr:postcode":"3023",
    "addr:street":"Rebecca Drv",
    "iso:country":"AU",
    "sg:address":"Fcty4/ 64 Rebecca Drv",
    "sg:city":"Ravenhall",
    "sg:classifiers":[
        {
            "category":"Retail",
            "subcategory":"Auto Repair",
            "type":"Services"
        }
    ],
    "sg:phone":"+61 3 9360 5770",
    "sg:postcode":"3023",
    "sg:province":"VIC",
    "sg:tags":[
        "repairer",
        "motor",
        "engineer"
    ],
    "wof:name":"Western Pro",
    "wof:placetype":"venue"
},
  "geometry": {"coordinates":[144.74929800000001,-37.763729],"type":"Point"}
}