{
  "type": "Feature",
  "properties": {
    "iso:country":"AU",
    "sg:address":"Lot 343 Harries Way",
    "sg:city":"Pinjarra",
    "sg:classifiers":[
        {
            "category":"Retail",
            "subcategory":"Storage",
            "type":"Services"
        }
    ],
    "sg:phone":"+61 438 179 828",
    "sg:postcode":"6208",
    "sg:province":"WA",
    "sg:tags":[
        "removal",
        "furniture"
    ],
    "wof:name":"DJ's Removals & Storage",
    "wof:placetype":"venue"
},
  "geometry": {"coordinates":[115.849251,-32.615208],"type":"Point"}
}