{
  "type": "Feature",
  "properties": {
    "addr:full":"PO Box 5107 Kahibah NSW 2290",
    "addr:postcode":"2290",
    "iso:country":"AU",
    "sg:address":"PO Box 5107",
    "sg:city":"Kahibah",
    "sg:classifiers":[
        {
            "category":"Professional",
            "subcategory":"Printing & Photocopies",
            "type":"Services"
        }
    ],
    "sg:phone":"+61 2 4943 0366",
    "sg:postcode":"2290",
    "sg:province":"NSW",
    "sg:tags":[
        "embroidery"
    ],
    "wof:name":"AGHA Promotional Products",
    "wof:placetype":"venue"
},
  "geometry": {"coordinates":[151.71333313,-32.9619102478],"type":"Point"}
}