{
  "type": "Feature",
  "properties": {
    "addr:full":"Level 1/ 100 Dorcas St South Melbourne VIC 3205",
    "addr:housenumber":"/ 100",
    "addr:postcode":"3205",
    "addr:street":"Dorcas St",
    "iso:country":"AU",
    "sg:address":"Level 1/ 100 Dorcas St",
    "sg:city":"South Melbourne",
    "sg:classifiers":[
        {
            "category":"Banks & Credit Unions",
            "subcategory":"Financial Services",
            "type":"Services"
        }
    ],
    "sg:phone":"+61 1300 842 346",
    "sg:postcode":"3205",
    "sg:province":"VIC",
    "sg:tags":[
        "loan",
        "finance",
        "mortgage"
    ],
    "sg:website":"http://www.victoriafinance.com.au",
    "wof:name":"Victoria Finance",
    "wof:placetype":"venue"
},
  "geometry": {"coordinates":[144.95167499999999,-37.836037],"type":"Point"}
}