{
  "type": "Feature",
  "properties": {
    "iso:country":"AU",
    "sg:address":"12 Baker St",
    "sg:city":"Geraldton",
    "sg:classifiers":[
        {
            "category":"Building & Trades",
            "subcategory":"Pest Control",
            "type":"Services"
        }
    ],
    "sg:phone":"+61 8 9965 3330",
    "sg:postcode":"6530",
    "sg:province":"WA",
    "wof:name":"Pest-A-Kill WA",
    "wof:placetype":"venue"
},
  "geometry": {"coordinates":[114.597251892,-28.7848434448],"type":"Point"}
}