{
  "type": "Feature",
  "properties": {
    "addr:full":"1 Eve Crt Bendigo VIC 3550",
    "addr:housenumber":"1",
    "addr:postcode":"3550",
    "addr:street":"Eve Crt",
    "iso:country":"AU",
    "sg:address":"1 Eve Crt",
    "sg:city":"Bendigo",
    "sg:classifiers":[
        {
            "category":"Building & Trades",
            "subcategory":"Construction",
            "type":"Services"
        }
    ],
    "sg:phone":"+61 3 5443 7800",
    "sg:postcode":"3550",
    "sg:province":"VIC",
    "sg:tags":[
        "welding"
    ],
    "wof:name":"Bellys Engineering",
    "wof:placetype":"venue"
},
  "geometry": {"coordinates":[144.27346801799999,-36.7707252502],"type":"Point"}
}