{
  "type": "Feature",
  "properties": {
    "addr:full":"799 Fairfield Rd Yeerongpilly QLD 4105",
    "addr:housenumber":"799",
    "addr:postcode":"4105",
    "addr:street":"Fairfield Rd",
    "iso:country":"AU",
    "sg:address":"799 Fairfield Rd",
    "sg:city":"Yeerongpilly",
    "sg:classifiers":[
        {
            "category":"Building & Trades",
            "subcategory":"Construction",
            "type":"Services"
        }
    ],
    "sg:phone":"+61 1800 336 237",
    "sg:postcode":"4105",
    "sg:province":"QLD",
    "sg:tags":[
        "fencing",
        "contractor"
    ],
    "wof:name":"Cyclone Security",
    "wof:placetype":"venue"
},
  "geometry": {"coordinates":[153.01205444300001,-27.5303897858],"type":"Point"}
}