{
  "type": "Feature",
  "properties": {
    "iso:country":"AU",
    "sg:address":"58 Mather St",
    "sg:city":"Garbutt",
    "sg:classifiers":[
        {
            "category":"Retail",
            "subcategory":"Auto Repair",
            "type":"Services"
        }
    ],
    "sg:phone":"+61 7 4774 8133",
    "sg:postcode":"4814",
    "sg:province":"QLD",
    "sg:tags":[
        "hire",
        "go-kart"
    ],
    "wof:name":"Kart Mania",
    "wof:placetype":"venue"
},
  "geometry": {"coordinates":[146.74873400000001,-19.267641],"type":"Point"}
}