{
  "type": "Feature",
  "properties": {
    "addr:full":"15 Arundell Ave Nambour QLD 4560",
    "addr:housenumber":"15",
    "addr:postcode":"4560",
    "addr:street":"Arundell Ave",
    "iso:country":"AU",
    "sg:address":"15 Arundell Ave",
    "sg:city":"Nambour",
    "sg:classifiers":[
        {
            "category":"Personal",
            "subcategory":"Beauty Salon",
            "type":"Services"
        }
    ],
    "sg:phone":"+61 7 5476 1999",
    "sg:postcode":"4560",
    "sg:province":"QLD",
    "sg:tags":[
        "hairdresser"
    ],
    "wof:name":"Slice Hair Design",
    "wof:placetype":"venue"
},
  "geometry": {"coordinates":[152.95866394000001,-26.631149292],"type":"Point"}
}