{
  "type": "Feature",
  "properties": {
    "addr:full":"28 Wallace Drv Greenvale VIC 3059",
    "addr:housenumber":"28",
    "addr:postcode":"3059",
    "addr:street":"Wallace Drv",
    "iso:country":"AU",
    "sg:address":"28 Wallace Drv",
    "sg:city":"Greenvale",
    "sg:classifiers":[
        {
            "category":"Professional",
            "subcategory":"Accounting & Tax Preparation",
            "type":"Services"
        }
    ],
    "sg:phone":"+61 422 341 445",
    "sg:postcode":"3059",
    "sg:province":"VIC",
    "sg:tags":[
        "bookkeeping"
    ],
    "wof:name":"Hayel Bookkeeping & Accounting",
    "wof:placetype":"venue"
},
  "geometry": {"coordinates":[144.89982605,-37.6511535645],"type":"Point"}
}