{
  "type": "Feature",
  "properties": {
    "addr:full":"21 Kanangra Rd Dernancourt SA 5075",
    "addr:housenumber":"21",
    "addr:postcode":"5075",
    "addr:street":"Kanangra Rd",
    "iso:country":"AU",
    "sg:address":"21 Kanangra Rd",
    "sg:city":"Dernancourt",
    "sg:classifiers":[
        {
            "category":"Education",
            "subcategory":"Music School",
            "type":"Public Place"
        }
    ],
    "sg:phone":"+61 8 8261 8107",
    "sg:postcode":"5075",
    "sg:province":"SA",
    "sg:tags":[
        "choir",
        "bands",
        "orchestra"
    ],
    "wof:name":"Sweet Adelines, International (Adelaide Sound Connection)",
    "wof:placetype":"venue"
},
  "geometry": {"coordinates":[138.674682617,-34.8637428284],"type":"Point"}
}