{
  "type": "Feature",
  "properties": {
    "iso:country":"AU",
    "sg:address":"Cnr Furlong Rd & Dawes St",
    "sg:city":"Queanbeyan",
    "sg:classifiers":[
        {
            "category":"Social Services",
            "subcategory":"Child Care",
            "type":"Services"
        }
    ],
    "sg:phone":"+61 2 6284 2022",
    "sg:postcode":"2620",
    "sg:province":"NSW",
    "wof:name":"Furlong Rd Early Learning Centre",
    "wof:placetype":"venue"
},
  "geometry": {"coordinates":[149.19979858400001,-35.3619194031],"type":"Point"}
}