{
  "type": "Feature",
  "properties": {
    "addr:full":"Suite 409, 10 Century Cct Baulkham Hills NSW 2153",
    "addr:postcode":"2153",
    "addr:street":"Century",
    "iso:country":"AU",
    "sg:address":"Suite 409, 10",
    "sg:city":"Century Cct Baulkham Hills",
    "sg:classifiers":[
        {
            "category":"Insurance",
            "subcategory":"Life Insurance",
            "type":"Services"
        }
    ],
    "sg:phone":"+61 2 9680 1588",
    "sg:postcode":"2153",
    "sg:province":"NSW",
    "wof:name":"Central Financial Planning Pty Ltd",
    "wof:placetype":"venue"
},
  "geometry": {"coordinates":[150.989624023,-33.7578811646],"type":"Point"}
}