{
  "type": "Feature",
  "properties": {
    "addr:full":"4/ 57 Buckingham Drv Wangara WA 6065",
    "addr:housenumber":"/ 57",
    "addr:postcode":"6065",
    "addr:street":"Buckingham Drv",
    "iso:country":"AU",
    "sg:address":"4/ 57 Buckingham Drv",
    "sg:city":"Wangara",
    "sg:classifiers":[
        {
            "category":"Manufacturing",
            "subcategory":"Wood Products",
            "type":"Manufacturing & Wholesale Goods"
        }
    ],
    "sg:phone":"+61 8 9309 9552",
    "sg:postcode":"6065",
    "sg:province":"WA",
    "sg:tags":[
        "polisher",
        "french"
    ],
    "wof:name":"Wangara French Polishers",
    "wof:placetype":"venue"
},
  "geometry": {"coordinates":[115.82343292199999,-31.7870826721],"type":"Point"}
}