{
  "type": "Feature",
  "properties": {
    "iso:country":"AU",
    "sg:address":"Rear 113 High Rd",
    "sg:city":"Willetton",
    "sg:classifiers":[
        {
            "category":"Utilities",
            "subcategory":"Water",
            "type":"Services"
        }
    ],
    "sg:phone":"+61 1300 369 039",
    "sg:postcode":"6155",
    "sg:province":"WA",
    "sg:tags":[
        "hot",
        "system"
    ],
    "wof:name":"Hot Water Ambulance",
    "wof:placetype":"venue"
},
  "geometry": {"coordinates":[115.890411,-32.038761],"type":"Point"}
}