{
  "type": "Feature",
  "properties": {
    "iso:country":"AU",
    "sg:address":"1 Belmore Drv",
    "sg:city":"Rochedale South",
    "sg:classifiers":[
        {
            "category":"Food & Beverages",
            "subcategory":"Bakery",
            "type":"Retail Goods"
        }
    ],
    "sg:phone":"+61 7 3341 7098",
    "sg:postcode":"4123",
    "sg:province":"QLD",
    "sg:tags":[
        "cake",
        "shop",
        "pastry"
    ],
    "wof:name":"Rochedale Cakes & Pastries",
    "wof:placetype":"venue"
},
  "geometry": {"coordinates":[153.14140319800001,-27.5991210938],"type":"Point"}
}