{
  "type": "Feature",
  "properties": {
    "addr:full":"298a Stapylton-Jacobs Well Rd Stapylton QLD 4207",
    "addr:housenumber":"298a",
    "addr:postcode":"4207",
    "addr:street":"Stapylton-Jacobs Well Rd",
    "iso:country":"AU",
    "sg:address":"298a Stapylton-Jacobs Well Rd",
    "sg:city":"Stapylton",
    "sg:classifiers":[
        {
            "category":"Home & Garden",
            "subcategory":"Hardware",
            "type":"Retail Goods"
        }
    ],
    "sg:phone":"+61 7 3807 1922",
    "sg:postcode":"4207",
    "sg:province":"QLD",
    "sg:tags":[
        "plumber",
        "supply"
    ],
    "wof:name":"Fabfit",
    "wof:placetype":"venue"
},
  "geometry": {"coordinates":[153.19267273,-27.7140846252],"type":"Point"}
}