{
  "type": "Feature",
  "properties": {
    "addr:full":"1/ 43 Gateway Blv Morisset NSW 2264",
    "addr:housenumber":"/ 43",
    "addr:postcode":"2264",
    "addr:street":"Gateway Blv",
    "iso:country":"AU",
    "sg:address":"1/ 43 Gateway Blv",
    "sg:city":"Morisset",
    "sg:classifiers":[
        {
            "category":"Shopping",
            "subcategory":"Bicycles & Sporting Goods",
            "type":"Retail Goods"
        }
    ],
    "sg:phone":"+61 2 4973 3133",
    "sg:postcode":"2264",
    "sg:province":"NSW",
    "sg:tags":[
        "dance",
        "accessory",
        "wear",
        "supply"
    ],
    "wof:name":"Fiona's Studio Of Dance",
    "wof:placetype":"venue"
},
  "geometry": {"coordinates":[151.47373999999999,-33.117626],"type":"Point"}
}