{
  "type": "Feature",
  "properties": {
    "addr:full":"Cnr Livingston & Ranford Sts Canning Vale WA 6155",
    "addr:postcode":"6155",
    "addr:street":"Cnr",
    "iso:country":"AU",
    "sg:address":"Cnr Livingston & Ranford Sts",
    "sg:city":"Canning Vale",
    "sg:classifiers":[
        {
            "category":"Communications",
            "subcategory":"Film & Video Production",
            "type":"Services"
        }
    ],
    "sg:phone":"+61 8 9456 0600",
    "sg:postcode":"6155",
    "sg:province":"WA",
    "sg:tags":[
        "dvd",
        "library"
    ],
    "wof:name":"Video Ezy",
    "wof:placetype":"venue"
},
  "geometry": {"coordinates":[115.9226,-32.091831],"type":"Point"}
}