{
  "type": "Feature",
  "properties": {
    "addr:full":"10A Burgay Crt Osborne Park WA 6017",
    "addr:housenumber":"10a",
    "addr:postcode":"6017",
    "addr:street":"Burgay Crt",
    "iso:country":"AU",
    "sg:address":"10A Burgay Crt",
    "sg:city":"Osborne Park",
    "sg:classifiers":[
        {
            "category":"Retail",
            "subcategory":"Auto Repair",
            "type":"Services"
        }
    ],
    "sg:phone":"+61 8 9244 3877",
    "sg:postcode":"6017",
    "sg:province":"WA",
    "sg:tags":[
        "gas",
        "conversion",
        "natural",
        "lp",
        "vehicle"
    ],
    "wof:name":"Adamson Keith Auto Repairs",
    "wof:placetype":"venue"
},
  "geometry": {"coordinates":[115.803131103,-31.9067840576],"type":"Point"}
}