{
  "type": "Feature",
  "properties": {
    "addr:full":"5 Lewis Rd Warrandyte North VIC 3113",
    "addr:housenumber":"5",
    "addr:postcode":"3113",
    "addr:street":"Lewis Rd",
    "iso:country":"AU",
    "sg:address":"5 Lewis Rd",
    "sg:city":"Warrandyte North",
    "sg:classifiers":[
        {
            "category":"Personal",
            "subcategory":"Massage",
            "type":"Services"
        }
    ],
    "sg:phone":"+61 3 9844 5676",
    "sg:postcode":"3113",
    "sg:province":"VIC",
    "sg:tags":[
        "therapy"
    ],
    "wof:name":"Rejuvenating Hands A.A.M.T.",
    "wof:placetype":"venue"
},
  "geometry": {"coordinates":[145.224975586,-37.7342948914],"type":"Point"}
}