{
  "type": "Feature",
  "properties": {
    "addr:full":"411 Melbourne Rd Newport VIC 3015",
    "addr:housenumber":"411",
    "addr:postcode":"3015",
    "addr:street":"Melbourne Rd",
    "iso:country":"AU",
    "sg:address":"411 Melbourne Rd",
    "sg:city":"Newport",
    "sg:classifiers":[
        {
            "category":"Shopping",
            "subcategory":"Crafts & Fabrics",
            "type":"Retail Goods"
        }
    ],
    "sg:phone":"+61 3 9399 4177",
    "sg:postcode":"3015",
    "sg:province":"VIC",
    "sg:tags":[
        "supply"
    ],
    "wof:name":"In Stitches of Williamstown",
    "wof:placetype":"venue"
},
  "geometry": {"coordinates":[144.88279724099999,-37.8407363892],"type":"Point"}
}