{
  "type": "Feature",
  "properties": {
    "addr:full":"Charles St Cobram NSW 3644",
    "addr:postcode":"3644",
    "addr:street":"Charles St",
    "iso:country":"AU",
    "sg:address":"Charles St",
    "sg:city":"Cobram",
    "sg:classifiers":[
        {
            "category":"Health Services",
            "subcategory":"Doctor",
            "type":"Services"
        }
    ],
    "sg:phone":"+61 3 5871 1433",
    "sg:postcode":"3644",
    "sg:province":"NSW",
    "sg:tags":[
        "medical",
        "practitioner"
    ],
    "wof:name":"Moncrieff Sonya Dr",
    "wof:placetype":"venue"
},
  "geometry": {"coordinates":[145.64831543,-35.9149513245],"type":"Point"}
}