{
  "type": "Feature",
  "properties": {
    "iso:country":"AU",
    "sg:address":"89 Stirling St",
    "sg:city":"Perth",
    "sg:classifiers":[
        {
            "category":"Banks & Credit Unions",
            "subcategory":"Bureau De Change",
            "type":"Services"
        }
    ],
    "sg:phone":"+61 8 9328 8233",
    "sg:postcode":"6000",
    "sg:province":"WA",
    "sg:tags":[
        "repairs",
        "part",
        "appliance",
        "electrical"
    ],
    "wof:name":"Swift Appliance Service",
    "wof:placetype":"venue"
},
  "geometry": {"coordinates":[115.863998413,-31.9494075775],"type":"Point"}
}