{
  "type": "Feature",
  "properties": {
    "addr:full":"Shop 19 , Centro Galleria, Morley WA 6062",
    "addr:housenumber":"shop 19",
    "addr:postcode":"6062",
    "addr:street":"Galleria",
    "iso:country":"AU",
    "sg:address":"Shop 19",
    "sg:city":", Centro Galleria, Morley",
    "sg:classifiers":[
        {
            "category":"Shopping",
            "subcategory":"Jewelry",
            "type":"Retail Goods"
        }
    ],
    "sg:phone":"+61 8 9375 2772",
    "sg:postcode":"6062",
    "sg:province":"WA",
    "sg:tags":[
        "jeweller"
    ],
    "wof:name":"Zamels",
    "wof:placetype":"venue"
},
  "geometry": {"coordinates":[115.896888733,-31.8942699432],"type":"Point"}
}