{
  "type": "Feature",
  "properties": {
    "addr:full":"22 Rynoela Rd Gympie QLD 4570",
    "addr:housenumber":"22",
    "addr:postcode":"4570",
    "addr:street":"Rynoela Rd",
    "iso:country":"AU",
    "sg:address":"22 Rynoela Rd",
    "sg:city":"Gympie",
    "sg:classifiers":[
        {
            "category":"Professional",
            "subcategory":"Business Services",
            "type":"Services"
        }
    ],
    "sg:phone":"+61 7 5483 7000",
    "sg:postcode":"4570",
    "sg:province":"QLD",
    "sg:tags":[
        "consultant",
        "promoter",
        "entertainment"
    ],
    "wof:name":"Heart Of Gold Film Festival",
    "wof:placetype":"venue"
},
  "geometry": {"coordinates":[152.65098571799999,-26.1535758972],"type":"Point"}
}