{
  "type": "Feature",
  "properties": {
    "addr:full":"1 Melaleuca St Yarrawonga VIC 3730",
    "addr:housenumber":"1",
    "addr:postcode":"3730",
    "addr:street":"Melaleuca St",
    "iso:country":"AU",
    "sg:address":"1 Melaleuca St",
    "sg:city":"Yarrawonga",
    "sg:classifiers":[
        {
            "category":"Building & Trades",
            "subcategory":"Construction",
            "type":"Services"
        }
    ],
    "sg:phone":"+61 3 5744 1288",
    "sg:postcode":"3730",
    "sg:province":"VIC",
    "sg:tags":[
        "contractor"
    ],
    "wof:name":"River Country Homes",
    "wof:placetype":"venue"
},
  "geometry": {"coordinates":[145.99577331500001,-36.0308036804],"type":"Point"}
}