{
  "type": "Feature",
  "properties": {
    "addr:full":"Ryde Hospital+ Denistone Rd Eastwood NSW 2122",
    "addr:postcode":"2122",
    "addr:street":"Denistone Rd",
    "iso:country":"AU",
    "sg:address":"Ryde Hospital+ Denistone Rd",
    "sg:city":"Eastwood",
    "sg:classifiers":[
        {
            "category":"Health Services",
            "subcategory":"Doctor",
            "type":"Services"
        }
    ],
    "sg:phone":"+61 2 9858 7542",
    "sg:postcode":"2122",
    "sg:province":"NSW",
    "sg:tags":[
        "medical",
        "practitioner"
    ],
    "wof:name":"PaLMS# Pathology",
    "wof:placetype":"venue"
},
  "geometry": {"coordinates":[151.08810424800001,-33.7926750183],"type":"Point"}
}