{
  "type": "Feature",
  "properties": {
    "addr:full":"218 Wollombi Rd Cessnock NSW 2325",
    "addr:housenumber":"218",
    "addr:postcode":"2325",
    "addr:street":"Wollombi Rd",
    "iso:country":"AU",
    "sg:address":"218 Wollombi Rd",
    "sg:city":"Cessnock",
    "sg:classifiers":[
        {
            "category":"Shopping",
            "subcategory":"Bicycles & Sporting Goods",
            "type":"Retail Goods"
        }
    ],
    "sg:phone":"+61 2 4990 6211",
    "sg:postcode":"2325",
    "sg:province":"NSW",
    "sg:tags":[
        "chemical",
        "equipment",
        "pool",
        "swimming"
    ],
    "wof:name":"Cessnock Pool & Spa Supplies",
    "wof:placetype":"venue"
},
  "geometry": {"coordinates":[151.35435485799999,-32.8326721191],"type":"Point"}
}