{
  "type": "Feature",
  "properties": {
    "addr:full":"24 Somersby Falls Rd Somersby NSW 2250",
    "addr:housenumber":"24",
    "addr:postcode":"2250",
    "addr:street":"Somersby Falls Rd",
    "iso:country":"AU",
    "sg:address":"24 Somersby Falls Rd",
    "sg:city":"Somersby",
    "sg:classifiers":[
        {
            "category":"Professional",
            "subcategory":"Art Services",
            "type":"Services"
        }
    ],
    "sg:phone":"+61 2 4340 1699",
    "sg:postcode":"2250",
    "sg:province":"NSW",
    "sg:tags":[
        "picture",
        "frame",
        "framing"
    ],
    "wof:name":"Star Framing Gallery Pty Ltd",
    "wof:placetype":"venue"
},
  "geometry": {"coordinates":[151.27723693900001,-33.4020843506],"type":"Point"}
}