{
  "type": "Feature",
  "properties": {
    "addr:full":"27 Iverney Rd Hamilton Hill WA 6163",
    "addr:housenumber":"27",
    "addr:postcode":"6163",
    "addr:street":"Iverney Rd",
    "iso:country":"AU",
    "sg:address":"27 Iverney Rd",
    "sg:city":"Hamilton Hill",
    "sg:classifiers":[
        {
            "category":"Health Services",
            "subcategory":"Nursing And Care Facility",
            "type":"Services"
        }
    ],
    "sg:phone":"+61 8 9337 2238",
    "sg:postcode":"6163",
    "sg:province":"WA",
    "sg:tags":[
        "home"
    ],
    "wof:name":"Carrington Aged Care Facility",
    "wof:placetype":"venue"
},
  "geometry": {"coordinates":[115.77948000000001,-32.080853],"type":"Point"}
}