{
  "type": "Feature",
  "properties": {
    "iso:country":"AU",
    "sg:address":"31 Palamountain Ave",
    "sg:city":"Greenwith",
    "sg:classifiers":[
        {
            "category":"Banks & Credit Unions",
            "subcategory":"Financial Services",
            "type":"Services"
        }
    ],
    "sg:phone":"+61 8 8288 0518",
    "sg:postcode":"5125",
    "sg:province":"SA",
    "sg:tags":[
        "finance",
        "motor",
        "vehicle"
    ],
    "wof:name":"Allan Herbert Financial Services",
    "wof:placetype":"venue"
},
  "geometry": {"coordinates":[138.716766,-34.767937],"type":"Point"}
}