{
  "type": "Feature",
  "properties": {
    "addr:full":"112 Railway Pde Kogarah NSW 2217",
    "addr:housenumber":"112",
    "addr:postcode":"2217",
    "addr:street":"Railway Pde",
    "iso:country":"AU",
    "sg:address":"112 Railway Pde",
    "sg:city":"Kogarah",
    "sg:classifiers":[
        {
            "category":"Food & Beverages",
            "subcategory":"Bakery",
            "type":"Retail Goods"
        }
    ],
    "sg:phone":"+61 2 9588 6144",
    "sg:postcode":"2217",
    "sg:province":"NSW",
    "sg:tags":[
        "baker"
    ],
    "wof:name":"Georges Bakery Kogarah",
    "wof:placetype":"venue"
},
  "geometry": {"coordinates":[151.13249200000001,-33.964218],"type":"Point"}
}