{
  "type": "Feature",
  "properties": {
    "iso:country":"AU",
    "sg:address":"724 Springvale Rd",
    "sg:city":"Mulgrave",
    "sg:classifiers":[
        {
            "category":"Manufacturing",
            "subcategory":"Motor Vehicles & Parts",
            "type":"Manufacturing & Wholesale Goods"
        }
    ],
    "sg:phone":"+61 3 9561 5033",
    "sg:postcode":"3170",
    "sg:province":"VIC",
    "sg:tags":[
        "replacement"
    ],
    "wof:name":"Nsk Bearings",
    "wof:placetype":"venue"
},
  "geometry": {"coordinates":[145.158477783,-37.9218559265],"type":"Point"}
}