{
  "type": "Feature",
  "properties": {
    "iso:country":"AU",
    "sg:address":"30- 32 Brighton Ave",
    "sg:city":"Croydon Park",
    "sg:classifiers":[
        {
            "category":"Ice Cream",
            "type":"Food & Drink"
        }
    ],
    "sg:phone":"+61 2 9716 4488",
    "sg:postcode":"2133",
    "sg:province":"NSW",
    "sg:tags":[
        "retail"
    ],
    "wof:name":"Pure Gelato",
    "wof:placetype":"venue"
},
  "geometry": {"coordinates":[151.10824585,-33.8969841003],"type":"Point"}
}