{
  "type": "Feature",
  "properties": {
    "addr:full":"165 Main St Hahndorf SA 5245",
    "addr:housenumber":"165",
    "addr:postcode":"5245",
    "addr:street":"Main St",
    "iso:country":"AU",
    "sg:address":"165 Main St",
    "sg:city":"Hahndorf",
    "sg:classifiers":[
        {
            "category":"Retail",
            "subcategory":"Veterinary Services",
            "type":"Services"
        }
    ],
    "sg:phone":"+61 8 8388 7489",
    "sg:postcode":"5245",
    "sg:province":"SA",
    "sg:tags":[
        "surgeon"
    ],
    "wof:name":"Frauenfelder Harry",
    "wof:placetype":"venue"
},
  "geometry": {"coordinates":[138.80992126500001,-35.029296875],"type":"Point"}
}