{
  "type": "Feature",
  "properties": {
    "addr:full":"175 Plenty Rd Bundoora VIC 3083",
    "addr:housenumber":"175",
    "addr:postcode":"3083",
    "addr:street":"Plenty Rd",
    "iso:country":"AU",
    "sg:address":"175 Plenty Rd",
    "sg:city":"Bundoora",
    "sg:classifiers":[
        {
            "category":"Wholesale",
            "subcategory":"Medical Equipment & Supplies",
            "type":"Manufacturing & Wholesale Goods"
        }
    ],
    "sg:phone":"+61 3 9470 8300",
    "sg:postcode":"3083",
    "sg:province":"VIC",
    "sg:tags":[
        "aids",
        "hearing"
    ],
    "wof:name":"Complete Hearing Solutions",
    "wof:placetype":"venue"
},
  "geometry": {"coordinates":[145.065917969,-37.6884536743],"type":"Point"}
}