{
  "type": "Feature",
  "properties": {
    "addr:full":"1717 Ipswich Rd Rocklea QLD 4106",
    "addr:housenumber":"1717",
    "addr:postcode":"4106",
    "addr:street":"Ipswich Rd",
    "iso:country":"AU",
    "sg:address":"1717 Ipswich Rd",
    "sg:city":"Rocklea",
    "sg:classifiers":[
        {
            "category":"Professional",
            "subcategory":"Employment Agencies",
            "type":"Services"
        }
    ],
    "sg:phone":"+61 1300 022 277",
    "sg:postcode":"4106",
    "sg:province":"QLD",
    "sg:tags":[
        "broker",
        "custom"
    ],
    "wof:name":"Total Care Logistics",
    "wof:placetype":"venue"
},
  "geometry": {"coordinates":[152.99307250999999,-27.5642814636],"type":"Point"}
}