{
  "type": "Feature",
  "properties": {
    "addr:full":"336 Penshurst St Willoughby NSW 2068",
    "addr:housenumber":"336",
    "addr:postcode":"2068",
    "addr:street":"Penshurst St",
    "iso:country":"AU",
    "sg:address":"336 Penshurst St",
    "sg:city":"Willoughby",
    "sg:classifiers":[
        {
            "category":"Fast Food",
            "type":"Food & Drink"
        }
    ],
    "sg:phone":"+61 2 9417 2603",
    "sg:postcode":"2068",
    "sg:province":"NSW",
    "sg:tags":[
        "away",
        "take"
    ],
    "wof:name":"Botany Chinese Take Away",
    "wof:placetype":"venue"
},
  "geometry": {"coordinates":[151.19595336899999,-33.7938079834],"type":"Point"}
}