{
  "type": "Feature",
  "properties": {
    "iso:country":"AU",
    "sg:address":"1885 Point Nepean Rd",
    "sg:city":"Tootgarook",
    "sg:classifiers":[
        {
            "category":"Autos & Motor Vehicles",
            "subcategory":"Motorcycle Sales",
            "type":"Retail Goods"
        }
    ],
    "sg:phone":"+61 3 5985 1011",
    "sg:postcode":"3941",
    "sg:province":"VIC",
    "sg:tags":[
        "outboard"
    ],
    "wof:name":"Seaside Marine",
    "wof:placetype":"venue"
},
  "geometry": {"coordinates":[144.85694885300001,-38.368347168],"type":"Point"}
}