{
  "type": "Feature",
  "properties": {
    "addr:full":"83a Whyte St Coleraine VIC 3315",
    "addr:housenumber":"83a",
    "addr:postcode":"3315",
    "addr:street":"Whyte St",
    "iso:country":"AU",
    "sg:address":"83a Whyte St",
    "sg:city":"Coleraine",
    "sg:classifiers":[
        {
            "category":"Personal",
            "subcategory":"Beauty Salon",
            "type":"Services"
        }
    ],
    "sg:phone":"+61 3 5575 2246",
    "sg:postcode":"3315",
    "sg:province":"VIC",
    "sg:tags":[
        "hairdresser"
    ],
    "wof:name":"Roots To Tips Hair Design",
    "wof:placetype":"venue"
},
  "geometry": {"coordinates":[141.69236755399999,-37.5983810425],"type":"Point"}
}