{
  "type": "Feature",
  "properties": {
    "addr:full":"PO Box 401 Heathcote VIC 3523",
    "addr:postcode":"3523",
    "iso:country":"AU",
    "sg:address":"PO Box 401",
    "sg:city":"Heathcote",
    "sg:classifiers":[
        {
            "category":"Professional",
            "subcategory":"Printing & Photocopies",
            "type":"Services"
        }
    ],
    "sg:phone":"+61 417 532 856",
    "sg:postcode":"3523",
    "sg:province":"VIC",
    "sg:tags":[
        "embroidery"
    ],
    "wof:name":"Rinnie B Embroidery",
    "wof:placetype":"venue"
},
  "geometry": {"coordinates":[144.70033264200001,-36.9143600464],"type":"Point"}
}