{
  "type": "Feature",
  "properties": {
    "iso:country":"AU",
    "sg:address":"21 Kerrs Rd",
    "sg:city":"Lidcombe",
    "sg:classifiers":[
        {
            "category":"Personal",
            "subcategory":"Adult",
            "type":"Services"
        }
    ],
    "sg:phone":"+61 2 9649 8814",
    "sg:postcode":"2141",
    "sg:province":"NSW",
    "sg:tags":[
        "vic",
        "except",
        "state",
        "escort",
        "social",
        "qld"
    ],
    "wof:name":"AA Service",
    "wof:placetype":"venue"
},
  "geometry": {"coordinates":[151.040924072,-33.8664245605],"type":"Point"}
}