{
  "type": "Feature",
  "properties": {
    "addr:full":"U26/ 61 Frankston Gardens Drv Carrum Downs VIC 3201",
    "addr:postcode":"3201",
    "addr:street":"/ 61;Gardens Drv",
    "iso:country":"AU",
    "sg:address":"U26/ 61 Frankston Gardens Drv",
    "sg:city":"Carrum Downs",
    "sg:classifiers":[
        {
            "category":"Professional",
            "subcategory":"Engineering",
            "type":"Services"
        }
    ],
    "sg:phone":"+61 3 9775 1735",
    "sg:postcode":"3201",
    "sg:province":"VIC",
    "sg:tags":[
        "engineer"
    ],
    "wof:name":"Eastlink Engineering",
    "wof:placetype":"venue"
},
  "geometry": {"coordinates":[145.15954600000001,-38.101322],"type":"Point"}
}