{
  "type": "Feature",
  "properties": {
    "addr:full":"12 Manly Rd Manly QLD 4179",
    "addr:housenumber":"12",
    "addr:postcode":"4179",
    "addr:street":"Manly Rd",
    "iso:country":"AU",
    "sg:address":"12 Manly Rd",
    "sg:city":"Manly",
    "sg:classifiers":[
        {
            "category":"Health Services",
            "subcategory":"Doctor",
            "type":"Services"
        }
    ],
    "sg:phone":"+61 7 3348 6111",
    "sg:postcode":"4179",
    "sg:province":"QLD",
    "sg:tags":[
        "medical",
        "practitioner"
    ],
    "wof:name":"Novic Robert",
    "wof:placetype":"venue"
},
  "geometry": {"coordinates":[153.177856445,-27.4581871033],"type":"Point"}
}