{
  "type": "Feature",
  "properties": {
    "iso:country":"AU",
    "sg:address":"67 Townshend St",
    "sg:city":"Phillip",
    "sg:classifiers":[
        {
            "category":"Education",
            "subcategory":"Dance Studio",
            "type":"Public Place"
        }
    ],
    "sg:phone":"+61 1300 856 756",
    "sg:postcode":"2606",
    "sg:province":"ACT",
    "sg:tags":[
        "venue",
        "tuition"
    ],
    "wof:name":"Just Dance",
    "wof:placetype":"venue"
},
  "geometry": {"coordinates":[149.088745117,-35.3545875549],"type":"Point"}
}