{
  "type": "Feature",
  "properties": {
    "addr:full":"85 O'Shanassy St Sunbury VIC 3429",
    "addr:housenumber":"85",
    "addr:postcode":"3429",
    "addr:street":"O'Shanassy St",
    "iso:country":"AU",
    "sg:address":"85 O'Shanassy St",
    "sg:city":"Sunbury",
    "sg:classifiers":[
        {
            "category":"Recreation",
            "type":"Entertainment"
        }
    ],
    "sg:phone":"+61 3 9744 7908",
    "sg:postcode":"3429",
    "sg:province":"VIC",
    "sg:tags":[
        "supply",
        "outdoor",
        "adventure",
        "activity"
    ],
    "wof:name":"Aussie Disposals Pty Ltd",
    "wof:placetype":"venue"
},
  "geometry": {"coordinates":[144.73062133799999,-37.5805664062],"type":"Point"}
}