{
  "type": "Feature",
  "properties": {
    "addr:full":"54 The Entrance Rd The Entrance NSW 2261",
    "addr:housenumber":"54",
    "addr:postcode":"2261",
    "addr:street":"The Entrance Rd",
    "iso:country":"AU",
    "sg:address":"54 The Entrance Rd",
    "sg:city":"The Entrance",
    "sg:classifiers":[
        {
            "category":"Cinema",
            "subcategory":"Movie Theater",
            "type":"Entertainment"
        }
    ],
    "sg:phone":"+61 2 4332 6566",
    "sg:postcode":"2261",
    "sg:province":"NSW",
    "wof:name":"The Entrance Cinema",
    "wof:placetype":"venue"
},
  "geometry": {"coordinates":[151.49705499999999,-33.344013],"type":"Point"}
}