{
  "type": "Feature",
  "properties": {
    "addr:full":"42 St Andrews Ave Isle Of Capri QLD 4217",
    "addr:housenumber":"42",
    "addr:postcode":"4217",
    "addr:street":"St Andrews Ave",
    "iso:country":"AU",
    "sg:address":"42 St Andrews Ave",
    "sg:city":"Isle Of Capri",
    "sg:classifiers":[
        {
            "category":"Education",
            "subcategory":"School",
            "type":"Public Place"
        }
    ],
    "sg:phone":"+61 7 5582 0333",
    "sg:postcode":"4217",
    "sg:province":"QLD",
    "sg:tags":[
        "state",
        "except",
        "nsw"
    ],
    "wof:name":"Surfers Paradise Primary School",
    "wof:placetype":"venue"
},
  "geometry": {"coordinates":[153.42137145999999,-28.0118236542],"type":"Point"}
}