{
  "type": "Feature",
  "properties": {
    "addr:full":"15 Tate St Albion QLD 4010",
    "addr:housenumber":"15",
    "addr:postcode":"4010",
    "addr:street":"Tate St",
    "iso:country":"AU",
    "sg:address":"15 Tate St",
    "sg:city":"Albion",
    "sg:classifiers":[
        {
            "category":"Building & Trades",
            "subcategory":"Construction",
            "type":"Services"
        }
    ],
    "sg:phone":"+61 7 3262 9819",
    "sg:postcode":"4010",
    "sg:province":"QLD",
    "sg:tags":[
        "contractor"
    ],
    "wof:name":"East Coast Constructions",
    "wof:placetype":"venue"
},
  "geometry": {"coordinates":[153.04441833499999,-27.4334621429],"type":"Point"}
}