{
  "type": "Feature",
  "properties": {
    "addr:full":"1031 Wellington St West Perth WA 6005",
    "addr:housenumber":"1031",
    "addr:postcode":"6005",
    "addr:street":"Wellington St",
    "iso:country":"AU",
    "sg:address":"1031 Wellington St",
    "sg:city":"West Perth",
    "sg:classifiers":[
        {
            "category":"Education",
            "subcategory":"Special Training",
            "type":"Public Place"
        }
    ],
    "sg:phone":"+61 8 9321 1702",
    "sg:postcode":"6005",
    "sg:province":"WA",
    "sg:tags":[
        "development"
    ],
    "wof:name":"IDC Technologies",
    "wof:placetype":"venue"
},
  "geometry": {"coordinates":[115.84499359100001,-31.9467735291],"type":"Point"}
}