{
  "type": "Feature",
  "properties": {
    "addr:full":"95 Brisbane St Hobart TAS 7000",
    "addr:housenumber":"95",
    "addr:postcode":"7000",
    "addr:street":"Brisbane St",
    "iso:country":"AU",
    "sg:address":"95 Brisbane St",
    "sg:city":"Hobart",
    "sg:classifiers":[
        {
            "category":"Autos & Motor Vehicles",
            "subcategory":"Auto Supplies",
            "type":"Retail Goods"
        }
    ],
    "sg:phone":"+61 3 6234 8099",
    "sg:postcode":"7000",
    "sg:province":"TAS",
    "sg:tags":[
        "tyre"
    ],
    "wof:name":"Sparco",
    "wof:placetype":"venue"
},
  "geometry": {"coordinates":[147.32142639200001,-42.8807830811],"type":"Point"}
}