{
  "type": "Feature",
  "properties": {
    "iso:country":"AU",
    "sg:address":"4 999 Lower North East Rd",
    "sg:city":"Highbury",
    "sg:classifiers":[
        {
            "category":"Professional",
            "subcategory":"Accounting & Tax Preparation",
            "type":"Services"
        }
    ],
    "sg:phone":"+61 8 8395 9500",
    "sg:postcode":"5089",
    "sg:province":"SA",
    "sg:tags":[
        "consultant",
        "taxation"
    ],
    "wof:name":"Chandler Janet",
    "wof:placetype":"venue"
},
  "geometry": {"coordinates":[138.71498107900001,-34.8497009277],"type":"Point"}
}