{
  "type": "Feature",
  "properties": {
    "addr:full":"40 Don Rd Devonport TAS 7310",
    "addr:housenumber":"40",
    "addr:postcode":"7310",
    "addr:street":"Don Rd",
    "iso:country":"AU",
    "sg:address":"40 Don Rd",
    "sg:city":"Devonport",
    "sg:classifiers":[
        {
            "category":"Shopping",
            "subcategory":"Computers & Home Electronics",
            "type":"Retail Goods"
        }
    ],
    "sg:phone":"+61 3 6424 7012",
    "sg:postcode":"7310",
    "sg:province":"TAS",
    "sg:tags":[
        "hardware",
        "equipment"
    ],
    "wof:name":"Computer Troubleshooters",
    "wof:placetype":"venue"
},
  "geometry": {"coordinates":[146.33590698200001,-41.1800765991],"type":"Point"}
}