{
  "type": "Feature",
  "properties": {
    "addr:full":"3 Julienne Crt Doncaster East VIC 3109",
    "addr:housenumber":"3",
    "addr:postcode":"3109",
    "addr:street":"Julienne Crt",
    "iso:country":"AU",
    "sg:address":"3 Julienne Crt",
    "sg:city":"Doncaster East",
    "sg:classifiers":[
        {
            "category":"Professional",
            "subcategory":"Computer Services",
            "type":"Services"
        }
    ],
    "sg:phone":"+61 3 9842 0225",
    "sg:postcode":"3109",
    "sg:province":"VIC",
    "sg:tags":[
        "package",
        "software"
    ],
    "wof:name":"Consist Australia",
    "wof:placetype":"venue"
},
  "geometry": {"coordinates":[145.17494201700001,-37.7583198547],"type":"Point"}
}