{
  "type": "Feature",
  "properties": {
    "iso:country":"AU",
    "sg:address":"2073 Castlereagh Rd",
    "sg:city":"Penrith",
    "sg:classifiers":[
        {
            "category":"Autos & Motor Vehicles",
            "subcategory":"Automobile Sales",
            "type":"Retail Goods"
        }
    ],
    "sg:phone":"+61 2 4729 4444",
    "sg:postcode":"2751",
    "sg:province":"NSW",
    "sg:tags":[
        "car",
        "used"
    ],
    "wof:name":"Penrith City Used Cars Pty Ltd",
    "wof:placetype":"venue"
},
  "geometry": {"coordinates":[150.691162109,-33.7455177307],"type":"Point"}
}