{
  "type": "Feature",
  "properties": {
    "addr:full":"11 Lewis St Silverdale NSW 2752",
    "addr:housenumber":"11",
    "addr:postcode":"2752",
    "addr:street":"Lewis St",
    "iso:country":"AU",
    "sg:address":"11 Lewis St",
    "sg:city":"Silverdale",
    "sg:classifiers":[
        {
            "category":"Personal",
            "subcategory":"Nail Salon",
            "type":"Services"
        }
    ],
    "sg:phone":"+61 2 4774 2130",
    "sg:postcode":"2752",
    "sg:province":"NSW",
    "sg:tags":[
        "artificial"
    ],
    "wof:name":"Simply Beauty And Nails",
    "wof:placetype":"venue"
},
  "geometry": {"coordinates":[150.60833740199999,-33.9014091492],"type":"Point"}
}