{
  "type": "Feature",
  "properties": {
    "addr:full":"72 Hawkesbury Rd Westmead NSW 2145",
    "addr:housenumber":"72",
    "addr:postcode":"2145",
    "addr:street":"Hawkesbury Rd",
    "iso:country":"AU",
    "sg:address":"72 Hawkesbury Rd",
    "sg:city":"Westmead",
    "sg:classifiers":[
        {
            "category":"Health Services",
            "subcategory":"Doctor",
            "type":"Services"
        }
    ],
    "sg:phone":"+61 2 9635 1064",
    "sg:postcode":"2145",
    "sg:province":"NSW",
    "sg:tags":[
        "medical",
        "practitioner"
    ],
    "wof:name":"Baptist E D",
    "wof:placetype":"venue"
},
  "geometry": {"coordinates":[150.98710632300001,-33.8099975586],"type":"Point"}
}