{
  "type": "Feature",
  "properties": {
    "iso:country":"AU",
    "sg:address":"400 Blackall Range Rd",
    "sg:city":"Woombye",
    "sg:classifiers":[
        {
            "category":"Building & Trades",
            "subcategory":"Construction",
            "type":"Services"
        }
    ],
    "sg:phone":"+61 7 5442 3476",
    "sg:postcode":"4559",
    "sg:province":"QLD",
    "sg:tags":[
        "contractor"
    ],
    "wof:name":"Hendrik Kroon",
    "wof:placetype":"venue"
},
  "geometry": {"coordinates":[152.92759704599999,-26.6657123566],"type":"Point"}
}