{
  "type": "Feature",
  "properties": {
    "addr:full":"Cnr Russell St & Pullman Pl Emu Plains NSW 2750",
    "addr:postcode":"2750",
    "addr:street":"Cnr Russell St &;Pl",
    "iso:country":"AU",
    "sg:address":"Cnr Russell St & Pullman Pl",
    "sg:city":"Emu Plains",
    "sg:classifiers":[
        {
            "category":"Autos & Motor Vehicles",
            "subcategory":"Auto Supplies",
            "type":"Retail Goods"
        }
    ],
    "sg:phone":"+61 2 4735 4610",
    "sg:postcode":"2750",
    "sg:province":"NSW",
    "sg:tags":[
        "part",
        "cycles",
        "accessory"
    ],
    "wof:name":"Motorex Australia",
    "wof:placetype":"venue"
},
  "geometry": {"coordinates":[150.65354919399999,-33.7524490356],"type":"Point"}
}