{
  "type": "Feature",
  "properties": {
    "iso:country":"AU",
    "sg:address":"2 Victoria Knox Ave",
    "sg:city":"Rowville",
    "sg:classifiers":[
        {
            "category":"Building & Trades",
            "subcategory":"Cleaning & Sanitation",
            "type":"Services"
        }
    ],
    "sg:phone":"+61 3 9752 7276",
    "sg:postcode":"3178",
    "sg:province":"VIC",
    "sg:tags":[
        "industrial",
        "commercial",
        "contractor"
    ],
    "wof:name":"AA Cleaning Services",
    "wof:placetype":"venue"
},
  "geometry": {"coordinates":[145.270584106,-37.9063987732],"type":"Point"}
}