{
  "type": "Feature",
  "properties": {
    "iso:country":"AU",
    "sg:address":"3 Supply Crt",
    "sg:city":"Albion Park",
    "sg:classifiers":[
        {
            "category":"Shopping",
            "subcategory":"Pets & Pet Supplies",
            "type":"Retail Goods"
        }
    ],
    "sg:phone":"+61 2 4256 6569",
    "sg:postcode":"2527",
    "sg:province":"NSW",
    "sg:tags":[
        "boring",
        "drilling",
        "equipment"
    ],
    "wof:name":"Chemdrex Chemicals",
    "wof:placetype":"venue"
},
  "geometry": {"coordinates":[150.77101135300001,-34.5742797852],"type":"Point"}
}