{
  "type": "Feature",
  "properties": {
    "addr:full":"199 Golden Four Drv Bilinga QLD 4225",
    "addr:housenumber":"199",
    "addr:postcode":"4225",
    "addr:street":"Golden Four Drv",
    "iso:country":"AU",
    "sg:address":"199 Golden Four Drv",
    "sg:city":"Bilinga",
    "sg:classifiers":[
        {
            "category":"Shopping",
            "subcategory":"Crafts & Fabrics",
            "type":"Retail Goods"
        }
    ],
    "sg:phone":"+61 7 5536 1999",
    "sg:postcode":"4225",
    "sg:province":"QLD",
    "sg:tags":[
        "supply"
    ],
    "wof:name":"Dreen -ni Manda World Crafts Cafe",
    "wof:placetype":"venue"
},
  "geometry": {"coordinates":[153.509857178,-28.1586856842],"type":"Point"}
}