{
  "type": "Feature",
  "properties": {
    "iso:country":"AU",
    "sg:address":"4/ 33 Advantage Ave",
    "sg:city":"Morisset",
    "sg:classifiers":[
        {
            "category":"Retail",
            "subcategory":"Auto Repair",
            "type":"Services"
        }
    ],
    "sg:phone":"+61 2 4970 5599",
    "sg:postcode":"2264",
    "sg:province":"NSW",
    "sg:tags":[
        "repairer",
        "motor",
        "engineer"
    ],
    "wof:name":"Hi-Perform Exhaust & Auto",
    "wof:placetype":"venue"
},
  "geometry": {"coordinates":[151.471115,-33.119568],"type":"Point"}
}