{
  "type": "Feature",
  "properties": {
    "addr:full":"Signal Flat Rd Ashbourne SA 5157",
    "addr:postcode":"5157",
    "addr:street":"Flat Rd",
    "iso:country":"AU",
    "sg:address":"Signal Flat Rd",
    "sg:city":"Ashbourne",
    "sg:classifiers":[
        {
            "category":"Sports & Exercise",
            "subcategory":"Golf",
            "type":"Entertainment"
        }
    ],
    "sg:phone":"+61 8 8536 6120",
    "sg:postcode":"5157",
    "sg:province":"SA",
    "sg:tags":[
        "club"
    ],
    "wof:name":"Ashbourne Private Golf Course",
    "wof:placetype":"venue"
},
  "geometry": {"coordinates":[138.77293395999999,-35.3000907898],"type":"Point"}
}