{
  "type": "Feature",
  "properties": {
    "addr:full":"Main South Rd O'Halloran Hill SA 5158",
    "addr:postcode":"5158",
    "addr:street":"South Rd O'Halloran",
    "iso:country":"AU",
    "sg:address":"Main South Rd",
    "sg:city":"O'Halloran Hill",
    "sg:classifiers":[
        {
            "category":"Food & Beverages",
            "subcategory":"Liquor & Beverages",
            "type":"Retail Goods"
        }
    ],
    "sg:phone":"+61 8 8298 6633",
    "sg:postcode":"5158",
    "sg:province":"SA",
    "sg:tags":[
        "store"
    ],
    "wof:name":"Booze Brothers",
    "wof:placetype":"venue"
},
  "geometry": {"coordinates":[138.555374145,-35.0646247864],"type":"Point"}
}