{
  "type": "Feature",
  "properties": {
    "iso:country":"AU",
    "sg:address":"PO Box 29",
    "sg:city":"Willow Tree",
    "sg:classifiers":[
        {
            "category":"Shopping",
            "subcategory":"Clothing, Apparel, & Fashions",
            "type":"Retail Goods"
        }
    ],
    "sg:phone":"+61 2 6747 1316",
    "sg:postcode":"2339",
    "sg:province":"NSW",
    "sg:tags":[
        "uniform"
    ],
    "wof:name":"Trishs Embroidery Service",
    "wof:placetype":"venue"
},
  "geometry": {"coordinates":[150.72622680699999,-31.6481399536],"type":"Point"}
}