{
  "type": "Feature",
  "properties": {
    "iso:country":"AU",
    "sg:address":"Suite-4/15-21 Collier Rd",
    "sg:city":"Morley",
    "sg:classifiers":[
        {
            "category":"Health Services",
            "subcategory":"Dentist",
            "type":"Services"
        }
    ],
    "sg:phone":"+61 8 9275 8322",
    "sg:postcode":"6062",
    "sg:province":"WA",
    "wof:name":"Cooper Richard N H",
    "wof:placetype":"venue"
},
  "geometry": {"coordinates":[115.902450562,-31.896068573],"type":"Point"}
}