{
  "type": "Feature",
  "properties": {
    "iso:country":"AU",
    "sg:address":"Taylors Lakes Shopping Centre 3 Melton Hwy",
    "sg:city":"Taylors Lakes",
    "sg:classifiers":[
        {
            "category":"Shopping",
            "subcategory":"Bicycles & Sporting Goods",
            "type":"Retail Goods"
        }
    ],
    "sg:phone":"+61 3 9390 9555",
    "sg:postcode":"3038",
    "sg:province":"VIC",
    "sg:tags":[
        "dance",
        "accessory",
        "wear",
        "supply"
    ],
    "wof:name":"Dance Spirit",
    "wof:placetype":"venue"
},
  "geometry": {"coordinates":[144.80032299999999,-37.701912],"type":"Point"}
}