{
  "type": "Feature",
  "properties": {
    "addr:full":"PO Box 142 Legana TAS 7277",
    "addr:postcode":"7277",
    "iso:country":"AU",
    "sg:address":"PO Box 142",
    "sg:city":"Legana",
    "sg:classifiers":[
        {
            "category":"Utilities",
            "subcategory":"Electric",
            "type":"Services"
        }
    ],
    "sg:phone":"+61 3 6330 2991",
    "sg:postcode":"7277",
    "sg:province":"TAS",
    "sg:tags":[
        "electrical",
        "contractor"
    ],
    "wof:name":"Harvey M.R. & N.T.",
    "wof:placetype":"venue"
},
  "geometry": {"coordinates":[147.045089722,-41.3669891357],"type":"Point"}
}