{
  "type": "Feature",
  "properties": {
    "iso:country":"AU",
    "sg:address":"84 Forsyth St",
    "sg:city":"Wagga Wagga",
    "sg:classifiers":[
        {
            "category":"Food & Beverages",
            "subcategory":"Bakery",
            "type":"Retail Goods"
        }
    ],
    "sg:phone":"+61 2 6921 4238",
    "sg:postcode":"2650",
    "sg:province":"NSW",
    "sg:tags":[
        "cake",
        "shop",
        "pastry"
    ],
    "wof:name":"Bread Crock The",
    "wof:placetype":"venue"
},
  "geometry": {"coordinates":[147.35940551799999,-35.1127586365],"type":"Point"}
}