{
  "type": "Feature",
  "properties": {
    "addr:full":"Mt Buller Rd Merrijig VIC 3723",
    "addr:postcode":"3723",
    "addr:street":"Mt Buller Rd",
    "iso:country":"AU",
    "sg:address":"Mt Buller Rd",
    "sg:city":"Merrijig",
    "sg:classifiers":[
        {
            "category":"Sports & Exercise",
            "subcategory":"Ski Resort",
            "type":"Entertainment"
        }
    ],
    "sg:phone":"+61 1800 033 214",
    "sg:postcode":"3723",
    "sg:province":"VIC",
    "sg:tags":[
        "tour",
        "centres"
    ],
    "wof:name":"Pinnacle Valley Resort",
    "wof:placetype":"venue"
},
  "geometry": {"coordinates":[146.26617431599999,-37.1101074219],"type":"Point"}
}