{
  "type": "Feature",
  "properties": {
    "addr:full":"Graet Eastern Hwy Tammin WA 6409",
    "addr:postcode":"6409",
    "addr:street":"Eastern Hwy",
    "iso:country":"AU",
    "sg:address":"Graet Eastern Hwy",
    "sg:city":"Tammin",
    "sg:classifiers":[
        {
            "category":"Autos & Motor Vehicles",
            "subcategory":"Fuel & Gas Station",
            "type":"Retail Goods"
        }
    ],
    "sg:phone":"+61 8 9637 1200",
    "sg:postcode":"6409",
    "sg:province":"WA",
    "wof:name":"Mobil Tammin Roadhouse",
    "wof:placetype":"venue"
},
  "geometry": {"coordinates":[117.48194122300001,-31.6419658661],"type":"Point"}
}