{
  "type": "Feature",
  "properties": {
    "iso:country":"AU",
    "sg:address":"48 Church St",
    "sg:city":"Penola",
    "sg:classifiers":[
        {
            "category":"Cafe",
            "type":"Food & Drink"
        }
    ],
    "sg:phone":"+61 8 8737 2967",
    "sg:postcode":"5277",
    "sg:province":"SA",
    "wof:name":"Irises Cafe",
    "wof:placetype":"venue"
},
  "geometry": {"coordinates":[140.836853,-37.378494],"type":"Point"}
}