{
  "type": "Feature",
  "properties": {
    "addr:full":"Gay St Benalla VIC 3672",
    "addr:postcode":"3672",
    "addr:street":"Gay St",
    "iso:country":"AU",
    "sg:address":"Gay St",
    "sg:city":"Benalla",
    "sg:classifiers":[
        {
            "category":"Professional",
            "subcategory":"Detective & Security Services",
            "type":"Services"
        }
    ],
    "sg:phone":"+61 3 5762 2944",
    "sg:postcode":"3672",
    "sg:province":"VIC",
    "sg:tags":[
        "equipment",
        "window",
        "doors"
    ],
    "wof:name":"Benalla Glass",
    "wof:placetype":"venue"
},
  "geometry": {"coordinates":[145.99818400000001,-36.542038],"type":"Point"}
}