{
  "type": "Feature",
  "properties": {
    "addr:full":"Lvl1/ 132 Albert St Brisbane QLD 4000",
    "addr:housenumber":"132",
    "addr:postcode":"4000",
    "addr:street":"Albert St",
    "iso:country":"AU",
    "sg:address":"Lvl1/ 132 Albert St",
    "sg:city":"Brisbane",
    "sg:classifiers":[
        {
            "category":"Personal",
            "subcategory":"Beauty Salon",
            "type":"Services"
        }
    ],
    "sg:phone":"+61 7 3229 0002",
    "sg:postcode":"4000",
    "sg:province":"QLD",
    "sg:tags":[
        "hairdresser"
    ],
    "wof:name":"Koogi Hair Dressing",
    "wof:placetype":"venue"
},
  "geometry": {"coordinates":[153.02708435100001,-27.4716835022],"type":"Point"}
}