{
  "type": "Feature",
  "properties": {
    "iso:country":"AU",
    "sg:address":"Shop 6/ 10 Ringwood St",
    "sg:city":"Ringwood",
    "sg:classifiers":[
        {
            "category":"Personal",
            "subcategory":"Beauty Salon",
            "type":"Services"
        }
    ],
    "sg:phone":"+61 3 9870 6182",
    "sg:postcode":"3134",
    "sg:province":"VIC",
    "sg:tags":[
        "hairdresser"
    ],
    "wof:name":"Tinas Hair & Nail Design",
    "wof:placetype":"venue"
},
  "geometry": {"coordinates":[145.22718810999999,-37.8145179749],"type":"Point"}
}