{
  "type": "Feature",
  "properties": {
    "iso:country":"AU",
    "sg:address":"RMB 502",
    "sg:city":"Rheola",
    "sg:classifiers":[
        {
            "category":"Professional",
            "type":"Services"
        }
    ],
    "sg:phone":"+61 418 571 529",
    "sg:postcode":"3517",
    "sg:province":"VIC",
    "sg:tags":[
        "transport"
    ],
    "wof:name":"Poynton James",
    "wof:placetype":"venue"
},
  "geometry": {"coordinates":[143.701981,-36.649448],"type":"Point"}
}