{
  "type": "Feature",
  "properties": {
    "addr:full":"8 Riddell Pde Elsternwick VIC 3185",
    "addr:housenumber":"8",
    "addr:postcode":"3185",
    "addr:street":"Riddell Pde",
    "iso:country":"AU",
    "sg:address":"8 Riddell Pde",
    "sg:city":"Elsternwick",
    "sg:classifiers":[
        {
            "category":"Manufacturing",
            "subcategory":"Jewelry",
            "type":"Manufacturing & Wholesale Goods"
        }
    ],
    "sg:phone":"+61 3 9523 6603",
    "sg:postcode":"3185",
    "sg:province":"VIC",
    "sg:tags":[
        "mfrg",
        "jeweller"
    ],
    "wof:name":"All Gem Jewellers Aust Pty Ltd",
    "wof:placetype":"venue"
},
  "geometry": {"coordinates":[145.00205993599999,-37.8845748901],"type":"Point"}
}