{
  "type": "Feature",
  "properties": {
    "iso:country":"AU",
    "sg:address":"Ste 1/ 4 Charles St",
    "sg:city":"South Perth",
    "sg:classifiers":[
        {
            "category":"Building & Trades",
            "subcategory":"Construction",
            "type":"Services"
        }
    ],
    "sg:phone":"+61 8 9367 1252",
    "sg:postcode":"6151",
    "sg:province":"WA",
    "sg:tags":[
        "contractor"
    ],
    "wof:name":"Amano Homes",
    "wof:placetype":"venue"
},
  "geometry": {"coordinates":[115.84908299999999,-31.977251],"type":"Point"}
}