{
  "type": "Feature",
  "properties": {
    "addr:full":"Factory 4, 24 Orthla Ave Heidelberg West VIC 3081",
    "addr:housenumber":"24",
    "addr:postcode":"3081",
    "addr:street":"Orthla Ave",
    "iso:country":"AU",
    "sg:address":"Factory 4, 24 Orthla Ave",
    "sg:city":"Heidelberg West",
    "sg:classifiers":[
        {
            "category":"Retail",
            "subcategory":"Repair Shop",
            "type":"Services"
        }
    ],
    "sg:phone":"+61 3 9459 1804",
    "sg:postcode":"3081",
    "sg:province":"VIC",
    "sg:tags":[
        "windscreen"
    ],
    "wof:name":"Windscreen Deals",
    "wof:placetype":"venue"
},
  "geometry": {"coordinates":[145.04876709000001,-37.7328109741],"type":"Point"}
}