{
  "type": "Feature",
  "properties": {
    "iso:country":"AU",
    "sg:address":"198 South Valley Rd",
    "sg:city":"Highton",
    "sg:classifiers":[
        {
            "category":"Personal",
            "subcategory":"Massage",
            "type":"Services"
        }
    ],
    "sg:phone":"+61 3 5241 1137",
    "sg:postcode":"3216",
    "sg:province":"VIC",
    "sg:tags":[
        "therapy"
    ],
    "wof:name":"Tracey Langham",
    "wof:placetype":"venue"
},
  "geometry": {"coordinates":[144.31825256400001,-38.1732978821],"type":"Point"}
}