{
  "type": "Feature",
  "properties": {
    "addr:full":"10a Woodburn Rd Berala NSW 2141",
    "addr:housenumber":"10a",
    "addr:postcode":"2141",
    "addr:street":"Woodburn Rd",
    "iso:country":"AU",
    "sg:address":"10a Woodburn Rd",
    "sg:city":"Berala",
    "sg:classifiers":[
        {
            "category":"Food & Beverages",
            "subcategory":"Fruits & Vegetables",
            "type":"Retail Goods"
        }
    ],
    "sg:phone":"+61 2 9646 3565",
    "sg:postcode":"2141",
    "sg:province":"NSW",
    "sg:tags":[
        "greengrocer",
        "fruiterer"
    ],
    "wof:name":"Roy Fruit Market",
    "wof:placetype":"venue"
},
  "geometry": {"coordinates":[151.03619384800001,-33.8627357483],"type":"Point"}
}