{
  "type": "Feature",
  "properties": {
    "addr:full":"11 Marine Ave Tannum Sands QLD 4680",
    "addr:housenumber":"11",
    "addr:postcode":"4680",
    "addr:street":"Marine Ave",
    "iso:country":"AU",
    "sg:address":"11 Marine Ave",
    "sg:city":"Tannum Sands",
    "sg:classifiers":[
        {
            "category":"Professional",
            "subcategory":"Art Services",
            "type":"Services"
        }
    ],
    "sg:phone":"+61 7 4973 8958",
    "sg:postcode":"4680",
    "sg:province":"QLD",
    "sg:tags":[
        "decorator",
        "painter"
    ],
    "wof:name":"Allan Giles",
    "wof:placetype":"venue"
},
  "geometry": {"coordinates":[151.37603759800001,-23.9523601532],"type":"Point"}
}