{
  "type": "Feature",
  "properties": {
    "addr:full":"625 Glenhuntly Rd Caulfield VIC 3162",
    "addr:housenumber":"625",
    "addr:postcode":"3162",
    "addr:street":"Glenhuntly Rd",
    "iso:country":"AU",
    "sg:address":"625 Glenhuntly Rd",
    "sg:city":"Caulfield",
    "sg:classifiers":[
        {
            "category":"Retail",
            "subcategory":"Storage",
            "type":"Services"
        }
    ],
    "sg:phone":"+61 3 9527 8868",
    "sg:postcode":"3162",
    "sg:province":"VIC",
    "sg:tags":[
        "removal",
        "furniture"
    ],
    "wof:name":"Caulfield Auction Centre",
    "wof:placetype":"venue"
},
  "geometry": {"coordinates":[145.01539611800001,-37.8859367371],"type":"Point"}
}