{
  "type": "Feature",
  "properties": {
    "addr:full":"Victoria Rd Rydalmere NSW 2116",
    "addr:postcode":"2116",
    "addr:street":"Victoria Rd",
    "iso:country":"AU",
    "sg:address":"Victoria Rd",
    "sg:city":"Rydalmere",
    "sg:classifiers":[
        {
            "category":"Travel",
            "subcategory":"Hotels & Motels",
            "type":"Entertainment"
        }
    ],
    "sg:phone":"+61 2 9638 1778",
    "sg:postcode":"2116",
    "sg:province":"NSW",
    "sg:tags":[
        "accommodation"
    ],
    "wof:name":"Family Inn The",
    "wof:placetype":"venue"
},
  "geometry": {"coordinates":[151.210037231,-33.9042472839],"type":"Point"}
}