{
  "type": "Feature",
  "properties": {
    "iso:country":"AU",
    "sg:address":"101 Junction Rd",
    "sg:city":"Wahroonga",
    "sg:classifiers":[
        {
            "category":"Professional",
            "subcategory":"Employment Agencies",
            "type":"Services"
        }
    ],
    "sg:phone":"+61 2 4340 4266",
    "sg:postcode":"2076",
    "sg:province":"NSW",
    "sg:tags":[
        "provider",
        "internet"
    ],
    "wof:name":"Hotkey Nobbys",
    "wof:placetype":"venue"
},
  "geometry": {"coordinates":[151.13165283199999,-33.7104187012],"type":"Point"}
}