{
  "type": "Feature",
  "properties": {
    "addr:full":"Unit 2 45- 47 King St Doncaster East VIC 3109",
    "addr:housenumber":"45 47",
    "addr:postcode":"3109",
    "addr:street":"King St",
    "iso:country":"AU",
    "sg:address":"Unit 2 45- 47 King St",
    "sg:city":"Doncaster East",
    "sg:classifiers":[
        {
            "category":"Building & Trades",
            "subcategory":"Plumbing",
            "type":"Services"
        }
    ],
    "sg:phone":"+61 418 153 959",
    "sg:postcode":"3109",
    "sg:province":"VIC",
    "sg:tags":[
        "plumber",
        "gasfitters"
    ],
    "wof:name":"Agosta D J",
    "wof:placetype":"venue"
},
  "geometry": {"coordinates":[145.15133667000001,-37.7734298706],"type":"Point"}
}