{
  "type": "Feature",
  "properties": {
    "iso:country":"AU",
    "sg:address":"168 Norton St",
    "sg:city":"Leichhardt",
    "sg:classifiers":[
        {
            "category":"Travel",
            "subcategory":"Hostel",
            "type":"Entertainment"
        }
    ],
    "sg:phone":"+61 2 9569 2615",
    "sg:postcode":"2040",
    "sg:province":"NSW",
    "sg:tags":[
        "home"
    ],
    "wof:name":"Harold Hawkins Court Hostel",
    "wof:placetype":"venue"
},
  "geometry": {"coordinates":[151.156601,-33.881248],"type":"Point"}
}