{
  "type": "Feature",
  "properties": {
    "addr:full":"144 Elder St Clarinda VIC 3169",
    "addr:housenumber":"144",
    "addr:postcode":"3169",
    "addr:street":"Elder St",
    "iso:country":"AU",
    "sg:address":"144 Elder St",
    "sg:city":"Clarinda",
    "sg:classifiers":[
        {
            "category":"Building & Trades",
            "subcategory":"Construction",
            "type":"Services"
        }
    ],
    "sg:phone":"+61 414 661 884",
    "sg:postcode":"3169",
    "sg:province":"VIC",
    "sg:tags":[
        "concrete",
        "contractor"
    ],
    "wof:name":"General Concrete",
    "wof:placetype":"venue"
},
  "geometry": {"coordinates":[145.101654053,-37.9459228516],"type":"Point"}
}