{
  "type": "Feature",
  "properties": {
    "addr:full":"38 Bradford St Wonthella WA 6530",
    "addr:housenumber":"38",
    "addr:postcode":"6530",
    "addr:street":"Bradford St",
    "iso:country":"AU",
    "sg:address":"38 Bradford St",
    "sg:city":"Wonthella",
    "sg:classifiers":[
        {
            "category":"Building & Trades",
            "subcategory":"Plumbing",
            "type":"Services"
        }
    ],
    "sg:phone":"+61 8 9965 3044",
    "sg:postcode":"6530",
    "sg:province":"WA",
    "sg:tags":[
        "plumber",
        "gasfitters"
    ],
    "wof:name":"Active Plumbing Pty Ltd",
    "wof:placetype":"venue"
},
  "geometry": {"coordinates":[114.633460998,-28.7604198456],"type":"Point"}
}