{
  "type": "Feature",
  "properties": {
    "addr:full":"22 Cadell St Tooleybuc VIC 2736",
    "addr:housenumber":"22",
    "addr:postcode":"2736",
    "addr:street":"Cadell St",
    "iso:country":"AU",
    "sg:address":"22 Cadell St",
    "sg:city":"Tooleybuc",
    "sg:classifiers":[
        {
            "category":"Utilities",
            "subcategory":"Water",
            "type":"Services"
        }
    ],
    "sg:phone":"+61 419 175 305",
    "sg:postcode":"2736",
    "sg:province":"VIC",
    "sg:tags":[
        "hot",
        "system"
    ],
    "wof:name":"Mark Norton Plumbing Pty Ltd",
    "wof:placetype":"venue"
},
  "geometry": {"coordinates":[143.33812,-35.028908],"type":"Point"}
}