{
  "type": "Feature",
  "properties": {
    "addr:full":"185 Racecourse Rd Mt Martha VIC 3934",
    "addr:housenumber":"185",
    "addr:postcode":"3934",
    "addr:street":"Racecourse Rd",
    "iso:country":"AU",
    "sg:address":"185 Racecourse Rd",
    "sg:city":"Mt Martha",
    "sg:classifiers":[
        {
            "category":"Social Services",
            "subcategory":"Retirement Home",
            "type":"Services"
        }
    ],
    "sg:phone":"+61 3 5976 5700",
    "sg:postcode":"3934",
    "sg:province":"VIC",
    "sg:tags":[
        "village"
    ],
    "wof:name":"Sir James By The Bay",
    "wof:placetype":"venue"
},
  "geometry": {"coordinates":[145.059036255,-38.2501792908],"type":"Point"}
}