{
  "type": "Feature",
  "properties": {
    "iso:country":"AU",
    "sg:address":"265 George St",
    "sg:city":"Liverpool",
    "sg:classifiers":[
        {
            "category":"Shopping",
            "subcategory":"Clothing, Apparel, & Fashions",
            "type":"Retail Goods"
        }
    ],
    "sg:phone":"+61 2 9600 6853",
    "sg:postcode":"2170",
    "sg:province":"NSW",
    "sg:tags":[
        "recycled",
        "clothing"
    ],
    "wof:name":"White Elephant The",
    "wof:placetype":"venue"
},
  "geometry": {"coordinates":[150.9243927,-33.9245185852],"type":"Point"}
}