{
  "type": "Feature",
  "properties": {
    "iso:country":"AU",
    "sg:address":"110- 120 Addison Rd",
    "sg:city":"Marrickville",
    "sg:classifiers":[
        {
            "category":"Retail",
            "subcategory":"Car Wash",
            "type":"Services"
        }
    ],
    "sg:phone":"+61 2 9564 6841",
    "sg:postcode":"2204",
    "sg:province":"NSW",
    "sg:tags":[
        "truck",
        "cleaning"
    ],
    "wof:name":"Carlovers Carwash Limited",
    "wof:placetype":"venue"
},
  "geometry": {"coordinates":[151.163391,-33.902061],"type":"Point"}
}