{
  "type": "Feature",
  "properties": {
    "iso:country":"AU",
    "sg:address":"134 Sheffield Rd",
    "sg:city":"Welshpool",
    "sg:classifiers":[
        {
            "category":"Manufacturing",
            "subcategory":"Metals",
            "type":"Manufacturing & Wholesale Goods"
        }
    ],
    "sg:phone":"+61 8 9451 0500",
    "sg:postcode":"6106",
    "sg:province":"WA",
    "sg:tags":[
        "steel",
        "fabricator",
        "mfrs"
    ],
    "wof:name":"Abesque Engineering and Construction Ltd",
    "wof:placetype":"venue"
},
  "geometry": {"coordinates":[115.976829529,-31.9971370697],"type":"Point"}
}