{
  "type": "Feature",
  "properties": {
    "addr:full":"Bridge Inn Rd Mernda VIC 3754",
    "addr:postcode":"3754",
    "addr:street":"Bridge;Rd",
    "iso:country":"AU",
    "sg:address":"Bridge Inn Rd",
    "sg:city":"Mernda",
    "sg:classifiers":[
        {
            "category":"Building & Trades",
            "subcategory":"Construction",
            "type":"Services"
        }
    ],
    "sg:phone":"+61 3 9717 3923",
    "sg:postcode":"3754",
    "sg:province":"VIC",
    "sg:tags":[
        "contractor"
    ],
    "wof:name":"Feature Homes",
    "wof:placetype":"venue"
},
  "geometry": {"coordinates":[145.09831199999999,-37.600838],"type":"Point"}
}