{
  "type": "Feature",
  "properties": {
    "addr:full":"55 Cavan St Annerley QLD 4103",
    "addr:housenumber":"55",
    "addr:postcode":"4103",
    "addr:street":"Cavan St",
    "iso:country":"AU",
    "sg:address":"55 Cavan St",
    "sg:city":"Annerley",
    "sg:classifiers":[
        {
            "category":"Professional",
            "subcategory":"Accounting & Tax Preparation",
            "type":"Services"
        }
    ],
    "sg:phone":"+61 7 3848 2762",
    "sg:postcode":"4103",
    "sg:province":"QLD",
    "sg:tags":[
        "accountant",
        "auditor"
    ],
    "wof:name":"Ruddle Peter J",
    "wof:placetype":"venue"
},
  "geometry": {"coordinates":[153.03372192399999,-27.5216217041],"type":"Point"}
}