{
  "type": "Feature",
  "properties": {
    "iso:country":"AU",
    "sg:address":"RMB 5800",
    "sg:city":"Myrtleford",
    "sg:classifiers":[
        {
            "category":"Farming",
            "subcategory":"Vineyard",
            "type":"Manufacturing & Wholesale Goods"
        }
    ],
    "sg:phone":"+61 3 5756 2993",
    "sg:postcode":"3736",
    "sg:province":"VIC",
    "sg:tags":[
        "winery"
    ],
    "wof:name":"Cavedon Estate",
    "wof:placetype":"venue"
},
  "geometry": {"coordinates":[146.72390747099999,-36.5608596802],"type":"Point"}
}