{
  "type": "Feature",
  "properties": {
    "addr:full":"Rear Building 646 North East Rd Holden Hill SA 5088",
    "addr:housenumber":"646",
    "addr:postcode":"5088",
    "addr:street":"North East Rd",
    "iso:country":"AU",
    "sg:address":"Rear Building 646 North East Rd",
    "sg:city":"Holden Hill",
    "sg:classifiers":[
        {
            "category":"Health Services",
            "subcategory":"Medical Lab",
            "type":"Services"
        }
    ],
    "sg:phone":"+61 8 8261 4911",
    "sg:postcode":"5088",
    "sg:province":"SA",
    "sg:tags":[
        "laboratory",
        "dental"
    ],
    "wof:name":"Progressive Dental Laboratories",
    "wof:placetype":"venue"
},
  "geometry": {"coordinates":[138.664825439,-34.8531799316],"type":"Point"}
}