{
  "type": "Feature",
  "properties": {
    "iso:country":"AU",
    "sg:address":"Unit 3, 90 Wecker Rd",
    "sg:city":"Mansfield",
    "sg:classifiers":[
        {
            "category":"Wholesale",
            "subcategory":"Music Publishers",
            "type":"Manufacturing & Wholesale Goods"
        }
    ],
    "sg:phone":"+61 7 3349 7111",
    "sg:postcode":"4122",
    "sg:province":"QLD",
    "sg:tags":[
        "wholesaler",
        "dvd",
        "mfrs",
        "cd"
    ],
    "sg:website":"http://www.actionav.com.au",
    "wof:name":"Action AV",
    "wof:placetype":"venue"
},
  "geometry": {"coordinates":[153.098144531,-27.5329875946],"type":"Point"}
}