{
  "type": "Feature",
  "properties": {
    "addr:full":"307 Campbell St Rockhampton QLD 4700",
    "addr:housenumber":"307",
    "addr:postcode":"4700",
    "addr:street":"Campbell St",
    "iso:country":"AU",
    "sg:address":"307 Campbell St",
    "sg:city":"Rockhampton",
    "sg:classifiers":[
        {
            "category":"Retail",
            "subcategory":"Auto Repair",
            "type":"Services"
        }
    ],
    "sg:phone":"+61 7 4927 5962",
    "sg:postcode":"4700",
    "sg:province":"QLD",
    "sg:tags":[
        "testing",
        "inspection",
        "motor",
        "vehicle"
    ],
    "wof:name":"Kehl's Auto Electrical & Mechanical Repairs",
    "wof:placetype":"venue"
},
  "geometry": {"coordinates":[150.51141357399999,-23.3866710663],"type":"Point"}
}