{
  "type": "Feature",
  "properties": {
    "addr:full":"307 Ruthven St Toowoomba QLD 4350",
    "addr:housenumber":"307",
    "addr:postcode":"4350",
    "addr:street":"Ruthven St",
    "iso:country":"AU",
    "sg:address":"307 Ruthven St",
    "sg:city":"Toowoomba",
    "sg:classifiers":[
        {
            "category":"Autos & Motor Vehicles",
            "subcategory":"Auto Supplies",
            "type":"Retail Goods"
        }
    ],
    "sg:phone":"+61 7 4638 2811",
    "sg:postcode":"4350",
    "sg:province":"QLD",
    "sg:tags":[
        "part",
        "cycles",
        "accessory"
    ],
    "wof:name":"Boyd Yung Motorcycles",
    "wof:placetype":"venue"
},
  "geometry": {"coordinates":[151.952271,-27.568356],"type":"Point"}
}