{
  "type": "Feature",
  "properties": {
    "iso:country":"AU",
    "sg:address":"1 Lakeshore Ave",
    "sg:city":"North Buderim",
    "sg:classifiers":[
        {
            "category":"Professional",
            "subcategory":"Accounting & Tax Preparation",
            "type":"Services"
        }
    ],
    "sg:phone":"+61 7 5453 4872",
    "sg:postcode":"4556",
    "sg:province":"QLD",
    "sg:tags":[
        "consultant",
        "taxation"
    ],
    "wof:name":"McMaster & Associates",
    "wof:placetype":"venue"
},
  "geometry": {"coordinates":[153.063598633,-26.6666564941],"type":"Point"}
}