{
  "type": "Feature",
  "properties": {
    "iso:country":"AU",
    "sg:address":"352 Fison Ave",
    "sg:city":"Eagle Farm",
    "sg:classifiers":[
        {
            "category":"Wholesale",
            "subcategory":"Furniture",
            "type":"Manufacturing & Wholesale Goods"
        }
    ],
    "sg:phone":"+61 7 3268 2471",
    "sg:postcode":"4009",
    "sg:province":"QLD",
    "sg:tags":[
        "metal"
    ],
    "wof:name":"Minnis & Samson",
    "wof:placetype":"venue"
},
  "geometry": {"coordinates":[153.10017395,-27.4342689514],"type":"Point"}
}