{
  "type": "Feature",
  "properties": {
    "iso:country":"AU",
    "sg:address":"Devon St",
    "sg:city":"Wallsend",
    "sg:classifiers":[
        {
            "category":"Government",
            "subcategory":"Fire Station",
            "type":"Public Place"
        }
    ],
    "sg:phone":"+61 2 4955 9539",
    "sg:postcode":"2287",
    "sg:province":"NSW",
    "sg:tags":[
        "brigade"
    ],
    "wof:name":"Fire Brigades-NSW",
    "wof:placetype":"venue"
},
  "geometry": {"coordinates":[151.66569519000001,-32.9007301331],"type":"Point"}
}