{
  "type": "Feature",
  "properties": {
    "addr:full":"303 Stirling Hwy Claremont WA 6010",
    "addr:housenumber":"303",
    "addr:postcode":"6010",
    "addr:street":"Stirling Hwy",
    "iso:country":"AU",
    "sg:address":"303 Stirling Hwy",
    "sg:city":"Claremont",
    "sg:classifiers":[
        {
            "category":"Shopping",
            "subcategory":"Clothing, Apparel, & Fashions",
            "type":"Retail Goods"
        }
    ],
    "sg:phone":"+61 8 9384 4930",
    "sg:postcode":"6010",
    "sg:province":"WA",
    "sg:tags":[
        "lady",
        "wear"
    ],
    "wof:name":"Carla Zampatti",
    "wof:placetype":"venue"
},
  "geometry": {"coordinates":[115.782592773,-31.9826660156],"type":"Point"}
}