{
  "type": "Feature",
  "properties": {
    "addr:full":"245 Junction Rd Cootharaba QLD 4565",
    "addr:housenumber":"245",
    "addr:postcode":"4565",
    "addr:street":"Junction Rd",
    "iso:country":"AU",
    "sg:address":"245 Junction Rd",
    "sg:city":"Cootharaba",
    "sg:classifiers":[
        {
            "category":"Home & Garden",
            "subcategory":"Building Materials",
            "type":"Retail Goods"
        }
    ],
    "sg:phone":"+61 7 5485 3941",
    "sg:postcode":"4565",
    "sg:province":"QLD",
    "sg:tags":[
        "lawn",
        "cutting",
        "maintenance"
    ],
    "wof:name":"Ride & Whip Mowing",
    "wof:placetype":"venue"
},
  "geometry": {"coordinates":[152.94889831500001,-26.2957572937],"type":"Point"}
}