{
  "type": "Feature",
  "properties": {
    "addr:full":"285 Main St Katoomba NSW 2780",
    "addr:housenumber":"285",
    "addr:postcode":"2780",
    "addr:street":"Main St",
    "iso:country":"AU",
    "sg:address":"285 Main St",
    "sg:city":"Katoomba",
    "sg:classifiers":[
        {
            "category":"Travel",
            "subcategory":"Travel Agent",
            "type":"Entertainment"
        }
    ],
    "sg:phone":"+61 2 4782 7999",
    "sg:postcode":"2780",
    "sg:province":"NSW",
    "sg:tags":[
        "tour",
        "holiday",
        "adventure"
    ],
    "wof:name":"Trolley Tours",
    "wof:placetype":"venue"
},
  "geometry": {"coordinates":[150.311035156,-33.7122764587],"type":"Point"}
}