{
  "type": "Feature",
  "properties": {
    "iso:country":"AU",
    "sg:address":"4 Peace Ave",
    "sg:city":"Warragul",
    "sg:classifiers":[
        {
            "category":"Autos & Motor Vehicles",
            "subcategory":"Auto Supplies",
            "type":"Retail Goods"
        }
    ],
    "sg:phone":"+61 3 5623 4664",
    "sg:postcode":"3820",
    "sg:province":"VIC",
    "sg:tags":[
        "part",
        "cycles",
        "accessory"
    ],
    "wof:name":"Kings Warragul Pty Ltd",
    "wof:placetype":"venue"
},
  "geometry": {"coordinates":[145.937027,-38.164764],"type":"Point"}
}