{
  "type": "Feature",
  "properties": {
    "iso:country":"AU",
    "sg:address":"49 Taylors Rd",
    "sg:city":"Keilor Downs",
    "sg:classifiers":[
        {
            "category":"Health Services",
            "subcategory":"Dentist",
            "type":"Services"
        }
    ],
    "sg:phone":"+61 3 9375 1600",
    "sg:postcode":"3038",
    "sg:province":"VIC",
    "wof:name":"Riley McGlade D'Adamo Orthodontics",
    "wof:placetype":"venue"
},
  "geometry": {"coordinates":[144.809525,-37.729164],"type":"Point"}
}