{
  "type": "Feature",
  "properties": {
    "addr:full":"Shop 1, 18 Karalta Rd Erina NSW 2250",
    "addr:housenumber":"shop;18",
    "addr:postcode":"2250",
    "addr:street":"Karalta Rd",
    "iso:country":"AU",
    "sg:address":"Shop 1, 18 Karalta Rd",
    "sg:city":"Erina",
    "sg:classifiers":[
        {
            "category":"Shopping",
            "subcategory":"Musical Instruments",
            "type":"Retail Goods"
        }
    ],
    "sg:phone":"+61 2 4367 0877",
    "sg:postcode":"2250",
    "sg:province":"NSW",
    "sg:tags":[
        "piano",
        "organ"
    ],
    "wof:name":"Premiere Pianos & Organs",
    "wof:placetype":"venue"
},
  "geometry": {"coordinates":[151.395217895,-33.4346389771],"type":"Point"}
}