{
  "type": "Feature",
  "properties": {
    "addr:full":"Level 20 1 Macquarie Pl Sydney NSW 2000",
    "addr:housenumber":"1",
    "addr:postcode":"2000",
    "addr:street":"Macquarie Pl",
    "iso:country":"AU",
    "sg:address":"Level 20 1 Macquarie Pl",
    "sg:city":"Sydney",
    "sg:classifiers":[
        {
            "category":"Banks & Credit Unions",
            "subcategory":"Investment Brokerage",
            "type":"Services"
        }
    ],
    "sg:phone":"+61 2 8336 7100",
    "sg:postcode":"2000",
    "sg:province":"NSW",
    "wof:name":"DFA Australia Limited",
    "wof:placetype":"venue"
},
  "geometry": {"coordinates":[151.21043395999999,-33.8626480103],"type":"Point"}
}