{
  "type": "Feature",
  "properties": {
    "addr:full":"4 Henry St Seymour VIC 3660",
    "addr:housenumber":"4",
    "addr:postcode":"3660",
    "addr:street":"Henry St",
    "iso:country":"AU",
    "sg:address":"4 Henry St",
    "sg:city":"Seymour",
    "sg:classifiers":[
        {
            "category":"Retail",
            "subcategory":"Repair Shop",
            "type":"Services"
        }
    ],
    "sg:phone":"+61 3 5792 3844",
    "sg:postcode":"3660",
    "sg:province":"VIC",
    "sg:tags":[
        "machine",
        "repairs",
        "part",
        "dryer",
        "washing"
    ],
    "wof:name":"Seymour Electronics",
    "wof:placetype":"venue"
},
  "geometry": {"coordinates":[145.13771057100001,-37.0237846375],"type":"Point"}
}