{
  "type": "Feature",
  "properties": {
    "addr:full":"Shop 1 388 Moggill Rd Indooroopilly QLD 4068",
    "addr:housenumber":"shop 1",
    "addr:postcode":"388;4068",
    "addr:street":"Moggill Rd",
    "iso:country":"AU",
    "sg:address":"Shop 1 388 Moggill Rd",
    "sg:city":"Indooroopilly",
    "sg:classifiers":[
        {
            "category":"Travel",
            "subcategory":"Travel Agent",
            "type":"Entertainment"
        }
    ],
    "sg:phone":"+61 13 18 66",
    "sg:postcode":"4068",
    "sg:province":"QLD",
    "sg:tags":[
        "consultant"
    ],
    "wof:name":"Flight Centre",
    "wof:placetype":"venue"
},
  "geometry": {"coordinates":[152.97085571299999,-27.4980888367],"type":"Point"}
}