{
  "type": "Feature",
  "properties": {
    "addr:full":"8 Clarkson St Pearce ACT 2607",
    "addr:housenumber":"8",
    "addr:postcode":"2607",
    "addr:street":"Clarkson St",
    "iso:country":"AU",
    "sg:address":"8 Clarkson St",
    "sg:city":"Pearce",
    "sg:classifiers":[
        {
            "category":"Communications",
            "type":"Services"
        }
    ],
    "sg:phone":"+61 2 6286 6223",
    "sg:postcode":"2607",
    "sg:province":"ACT",
    "sg:tags":[
        "translation"
    ],
    "wof:name":"Croatian Translations",
    "wof:placetype":"venue"
},
  "geometry": {"coordinates":[149.080535889,-35.3574981689],"type":"Point"}
}