{
  "type": "Feature",
  "properties": {
    "addr:full":"\"Inveresk Railyards\" 4 Invermay Rd Invermay TAS 7248",
    "addr:housenumber":"4",
    "addr:postcode":"7248",
    "addr:street":"Invermay Rd",
    "iso:country":"AU",
    "sg:address":"\"Inveresk Railyards\" 4 Invermay Rd",
    "sg:city":"Invermay",
    "sg:classifiers":[
        {
            "category":"Organizations",
            "subcategory":"Professional Association",
            "type":"Services"
        }
    ],
    "sg:phone":"+61 3 6331 6044",
    "sg:postcode":"7248",
    "sg:province":"TAS",
    "sg:tags":[
        "rural",
        "organisation",
        "production",
        "primary"
    ],
    "wof:name":"The Royal National Agricultural & Pastoral Society Of Tasmania",
    "wof:placetype":"venue"
},
  "geometry": {"coordinates":[147.13461303700001,-41.418548584],"type":"Point"}
}