{
  "type": "Feature",
  "properties": {
    "addr:full":"Burgoyne St Kerang VIC 3579",
    "addr:postcode":"3579",
    "addr:street":"St",
    "iso:country":"AU",
    "sg:address":"Burgoyne St",
    "sg:city":"Kerang",
    "sg:classifiers":[
        {
            "category":"Health Services",
            "subcategory":"Nursing And Care Facility",
            "type":"Services"
        }
    ],
    "sg:phone":"+61 3 5450 9278",
    "sg:postcode":"3579",
    "sg:province":"VIC",
    "sg:tags":[
        "home"
    ],
    "wof:name":"Glenarm Nursing Home",
    "wof:placetype":"venue"
},
  "geometry": {"coordinates":[143.91812133799999,-35.7246398926],"type":"Point"}
}