{
  "type": "Feature",
  "properties": {
    "iso:country":"AU",
    "sg:address":"51 John St",
    "sg:city":"Singleton",
    "sg:classifiers":[
        {
            "category":"Travel",
            "subcategory":"Hotels & Motels",
            "type":"Entertainment"
        }
    ],
    "sg:phone":"+61 2 6572 1141",
    "sg:postcode":"2330",
    "sg:province":"NSW",
    "sg:tags":[
        "accommodation"
    ],
    "wof:name":"Central Hotel",
    "wof:placetype":"venue"
},
  "geometry": {"coordinates":[151.164871,-32.567863],"type":"Point"}
}