{
  "type": "Feature",
  "properties": {
    "addr:full":"Fitzroy St Carrington NSW 2294",
    "addr:postcode":"2294",
    "addr:street":"Fitzroy St",
    "iso:country":"AU",
    "sg:address":"Fitzroy St",
    "sg:city":"Carrington",
    "sg:classifiers":[
        {
            "category":"Transit Center",
            "subcategory":"Passenger",
            "type":"Transportation"
        }
    ],
    "sg:phone":"+61 2 4961 0561",
    "sg:postcode":"2294",
    "sg:province":"NSW",
    "sg:tags":[
        "cargo",
        "superintendent"
    ],
    "wof:name":"SGS Australia Pty Ltd",
    "wof:placetype":"venue"
},
  "geometry": {"coordinates":[151.762374878,-32.9147377014],"type":"Point"}
}