{
  "type": "Feature",
  "properties": {
    "addr:full":"11 Rangeview St Rochedale South QLD 4123",
    "addr:housenumber":"11",
    "addr:postcode":"4123",
    "addr:street":"Rangeview St",
    "iso:country":"AU",
    "sg:address":"11 Rangeview St",
    "sg:city":"Rochedale South",
    "sg:classifiers":[
        {
            "category":"Military Area",
            "subcategory":"Coast Guard Base",
            "type":"Public Place"
        }
    ],
    "sg:phone":"+61 419 731 030",
    "sg:postcode":"4123",
    "sg:province":"QLD",
    "sg:tags":[
        "sound",
        "engineer"
    ],
    "wof:name":"T & J Audio/Electronic Services Pty Ltd",
    "wof:placetype":"venue"
},
  "geometry": {"coordinates":[153.12168884299999,-27.6021003723],"type":"Point"}
}