{
  "type": "Feature",
  "properties": {
    "addr:full":"30 Guginya Crs Ngunnawal ACT 2913",
    "addr:housenumber":"30",
    "addr:postcode":"2913",
    "addr:street":"Guginya Crs",
    "iso:country":"AU",
    "sg:address":"30 Guginya Crs",
    "sg:city":"Ngunnawal",
    "sg:classifiers":[
        {
            "category":"Utilities",
            "subcategory":"Natural Gas",
            "type":"Services"
        }
    ],
    "sg:phone":"+61 400 803 917",
    "sg:postcode":"2913",
    "sg:province":"ACT",
    "sg:tags":[
        "solid",
        "plasterer"
    ],
    "wof:name":"Alex Rose",
    "wof:placetype":"venue"
},
  "geometry": {"coordinates":[149.108032227,-35.173160553],"type":"Point"}
}