{
  "type": "Feature",
  "properties": {
    "iso:country":"AU",
    "sg:address":"2 Avenal Rd",
    "sg:city":"Gymea Bay",
    "sg:classifiers":[
        {
            "category":"Utilities",
            "subcategory":"Electric",
            "type":"Services"
        }
    ],
    "sg:phone":"+61 2 9526 6690",
    "sg:postcode":"2227",
    "sg:province":"NSW",
    "sg:tags":[
        "electrical",
        "contractor"
    ],
    "wof:name":"Bulls Electrical Pty Ltd",
    "wof:placetype":"venue"
},
  "geometry": {"coordinates":[151.08253479000001,-34.0450363159],"type":"Point"}
}