{
  "type": "Feature",
  "properties": {
    "iso:country":"AU",
    "sg:address":"Lvl 10, 229 Macquarie St",
    "sg:city":"Sydney",
    "sg:classifiers":[
        {
            "category":"Health Services",
            "subcategory":"Health Practitioner",
            "type":"Services"
        }
    ],
    "sg:phone":"+61 2 9221 1115",
    "sg:postcode":"2000",
    "sg:province":"NSW",
    "sg:tags":[
        "naturopath"
    ],
    "wof:name":"Spicer Margaret",
    "wof:placetype":"venue"
},
  "geometry": {"coordinates":[151.21191406200001,-33.8690109253],"type":"Point"}
}