{
  "type": "Feature",
  "properties": {
    "addr:full":"Rose St Murrumbateman NSW 2582",
    "addr:postcode":"2582",
    "addr:street":"Rose St",
    "iso:country":"AU",
    "sg:address":"Rose St",
    "sg:city":"Murrumbateman",
    "sg:classifiers":[
        {
            "category":"Retail",
            "subcategory":"Auto Repair",
            "type":"Services"
        }
    ],
    "sg:phone":"+61 2 6227 5782",
    "sg:postcode":"2582",
    "sg:province":"NSW",
    "sg:tags":[
        "repairer",
        "motor",
        "engineer"
    ],
    "wof:name":"Wheatley Bill Motors",
    "wof:placetype":"venue"
},
  "geometry": {"coordinates":[149.02850341800001,-34.970500946],"type":"Point"}
}