{
  "type": "Feature",
  "properties": {
    "addr:full":"Himalaya Crs Seven Hills NSW 2147",
    "addr:postcode":"2147",
    "addr:street":"Himalaya Crs",
    "iso:country":"AU",
    "sg:address":"Himalaya Crs",
    "sg:city":"Seven Hills",
    "sg:classifiers":[
        {
            "category":"Professional",
            "subcategory":"Accounting & Tax Preparation",
            "type":"Services"
        }
    ],
    "sg:phone":"+61 401 182 060",
    "sg:postcode":"2147",
    "sg:province":"NSW",
    "sg:tags":[
        "bookkeeping"
    ],
    "wof:name":"Antonio Ferrari & Associates",
    "wof:placetype":"venue"
},
  "geometry": {"coordinates":[150.933883667,-33.775970459],"type":"Point"}
}