{
  "type": "Feature",
  "properties": {
    "iso:country":"AU",
    "sg:address":"11 Braedene Drv",
    "sg:city":"Bendigo",
    "sg:classifiers":[
        {
            "category":"Retail",
            "subcategory":"Laundry & Dry Cleaning",
            "type":"Services"
        }
    ],
    "sg:phone":"+61 438 093 026",
    "sg:postcode":"3550",
    "sg:province":"VIC",
    "sg:tags":[
        "manicurist"
    ],
    "wof:name":"Beauty With Simone",
    "wof:placetype":"venue"
},
  "geometry": {"coordinates":[144.22181701700001,-36.7516288757],"type":"Point"}
}