{
  "type": "Feature",
  "properties": {
    "iso:country":"AU",
    "sg:address":"30 Miguel Rd",
    "sg:city":"Bibra Lake",
    "sg:classifiers":[
        {
            "category":"Wholesale",
            "subcategory":"Construction Materials",
            "type":"Manufacturing & Wholesale Goods"
        }
    ],
    "sg:phone":"+61 8 9418 7900",
    "sg:postcode":"6163",
    "sg:province":"WA",
    "sg:tags":[
        "protective",
        "coating"
    ],
    "wof:name":"Lothway TBS",
    "wof:placetype":"venue"
},
  "geometry": {"coordinates":[115.810799,-32.114986],"type":"Point"}
}