{
  "type": "Feature",
  "properties": {
    "addr:full":"2 Midwood St New Town TAS 7008",
    "addr:housenumber":"2",
    "addr:postcode":"7008",
    "addr:street":"Midwood St",
    "iso:country":"AU",
    "sg:address":"2 Midwood St",
    "sg:city":"New Town",
    "sg:classifiers":[
        {
            "category":"Professional",
            "subcategory":"Accounting & Tax Preparation",
            "type":"Services"
        }
    ],
    "sg:phone":"+61 3 6228 5244",
    "sg:postcode":"7008",
    "sg:province":"TAS",
    "sg:tags":[
        "pregnancy",
        "related",
        "counselling"
    ],
    "wof:name":"Pregnancy Advice & Testing",
    "wof:placetype":"venue"
},
  "geometry": {"coordinates":[147.30426025400001,-42.8522186279],"type":"Point"}
}