{
  "type": "Feature",
  "properties": {
    "addr:full":"1/ 41 Mclaren St North Sydney NSW 2060",
    "addr:housenumber":"/ 41",
    "addr:postcode":"2060",
    "addr:street":"Mclaren St",
    "iso:country":"AU",
    "sg:address":"1/ 41 Mclaren St",
    "sg:city":"North Sydney",
    "sg:classifiers":[
        {
            "category":"Professional",
            "subcategory":"Engineering",
            "type":"Services"
        }
    ],
    "sg:phone":"+61 2 8907 0900",
    "sg:postcode":"2060",
    "sg:province":"NSW",
    "sg:tags":[
        "consulting",
        "engineer"
    ],
    "wof:name":"Lincolne Scott Consulting Engineers",
    "wof:placetype":"venue"
},
  "geometry": {"coordinates":[151.208450317,-33.8350563049],"type":"Point"}
}