{
  "type": "Feature",
  "properties": {
    "iso:country":"AU",
    "sg:address":"Lvl 2, Suite 3/ 9 Bowman St",
    "sg:city":"South Perth",
    "sg:classifiers":[
        {
            "category":"Building & Trades",
            "subcategory":"Construction",
            "type":"Services"
        }
    ],
    "sg:phone":"+61 8 9368 6808",
    "sg:postcode":"6151",
    "sg:province":"WA",
    "sg:tags":[
        "renovation",
        "alterations",
        "extension",
        "contractor"
    ],
    "wof:name":"Complete Property Renovations",
    "wof:placetype":"venue"
},
  "geometry": {"coordinates":[115.849113,-31.973969],"type":"Point"}
}