{
  "type": "Feature",
  "properties": {
    "addr:full":"6- 10 Talavara Rd North Ryde NSW 2113",
    "addr:housenumber":"10",
    "addr:postcode":"2113",
    "addr:street":"6;Talavara Rd",
    "iso:country":"AU",
    "sg:address":"6- 10 Talavara Rd",
    "sg:city":"North Ryde",
    "sg:classifiers":[
        {
            "category":"Professional",
            "subcategory":"Printing & Photocopies",
            "type":"Services"
        }
    ],
    "sg:phone":"+61 2 9888 9999",
    "sg:postcode":"2113",
    "sg:province":"NSW",
    "sg:tags":[
        "photocopier"
    ],
    "wof:name":"Kyocera Mita Australia Pty Ltd",
    "wof:placetype":"venue"
},
  "geometry": {"coordinates":[151.13035583499999,-33.7813529968],"type":"Point"}
}