{
  "type": "Feature",
  "properties": {
    "addr:full":"Shop 252 Dandenong Plaza, Cnr McCrae & Walker Street D VIC 3175",
    "addr:housenumber":"252",
    "addr:postcode":"3175",
    "addr:street":"Dandenong Plaza Cnr Mccrae & Walker Street",
    "iso:country":"AU",
    "sg:address":"Shop 252",
    "sg:city":"Dandenong Plaza, Cnr McCrae & Walker Street D",
    "sg:classifiers":[
        {
            "category":"Shopping",
            "subcategory":"Mobile Phones",
            "type":"Retail Goods"
        }
    ],
    "sg:phone":"+61 3 9793 3255",
    "sg:postcode":"3175",
    "sg:province":"VIC",
    "sg:tags":[
        "telephone",
        "accessory"
    ],
    "wof:name":"Allphones",
    "wof:placetype":"venue"
},
  "geometry": {"coordinates":[145.216995239,-37.9874916077],"type":"Point"}
}