{
  "type": "Feature",
  "properties": {
    "addr:full":"26 Horne St Sunbury VIC 3429",
    "addr:housenumber":"26",
    "addr:postcode":"3429",
    "addr:street":"Horne St",
    "iso:country":"AU",
    "sg:address":"26 Horne St",
    "sg:city":"Sunbury",
    "sg:classifiers":[
        {
            "category":"Health Services",
            "subcategory":"Doctor",
            "type":"Services"
        }
    ],
    "sg:phone":"+61 3 9740 7554",
    "sg:postcode":"3429",
    "sg:province":"VIC",
    "sg:tags":[
        "medical",
        "practitioner"
    ],
    "wof:name":"Anderson Stuart",
    "wof:placetype":"venue"
},
  "geometry": {"coordinates":[144.72677612300001,-37.5781021118],"type":"Point"}
}