{
  "type": "Feature",
  "properties": {
    "addr:full":"167 St James Rd New Lambton NSW 2305",
    "addr:housenumber":"167",
    "addr:postcode":"2305",
    "addr:street":"St James Rd",
    "iso:country":"AU",
    "sg:address":"167 St James Rd",
    "sg:city":"New Lambton",
    "sg:classifiers":[
        {
            "category":"Building & Trades",
            "subcategory":"Construction",
            "type":"Services"
        }
    ],
    "sg:phone":"+61 2 4952 4615",
    "sg:postcode":"2305",
    "sg:province":"NSW",
    "sg:tags":[
        "concrete",
        "contractor"
    ],
    "wof:name":"Macleod A D & E C",
    "wof:placetype":"venue"
},
  "geometry": {"coordinates":[151.71185299999999,-32.92712],"type":"Point"}
}