{
  "type": "Feature",
  "properties": {
    "addr:full":"139 Brunker Rd Adamstown NSW 2289",
    "addr:housenumber":"139",
    "addr:postcode":"2289",
    "addr:street":"Brunker Rd",
    "iso:country":"AU",
    "sg:address":"139 Brunker Rd",
    "sg:city":"Adamstown",
    "sg:classifiers":[
        {
            "category":"Retail",
            "subcategory":"Auto Repair",
            "type":"Services"
        }
    ],
    "sg:phone":"+61 2 4940 8388",
    "sg:postcode":"2289",
    "sg:province":"NSW",
    "sg:tags":[
        "repairer",
        "motor",
        "engineer"
    ],
    "wof:name":"Adbsolute Auto Excellence",
    "wof:placetype":"venue"
},
  "geometry": {"coordinates":[151.72593689000001,-32.9347915649],"type":"Point"}
}