{
  "type": "Feature",
  "properties": {
    "addr:full":"Level 2 88 Pitt St Sydney NSW 2000",
    "addr:housenumber":"88",
    "addr:postcode":"2000",
    "addr:street":"Pitt St",
    "iso:country":"AU",
    "sg:address":"Level 2 88 Pitt St",
    "sg:city":"Sydney",
    "sg:classifiers":[
        {
            "category":"Professional",
            "subcategory":"Employment Agencies",
            "type":"Services"
        }
    ],
    "sg:phone":"+61 2 9223 2001",
    "sg:postcode":"2000",
    "sg:province":"NSW",
    "wof:name":"Banking Career Solutions",
    "wof:placetype":"venue"
},
  "geometry": {"coordinates":[151.208694458,-33.8668785095],"type":"Point"}
}