{
  "type": "Feature",
  "properties": {
    "addr:full":"142 Susan St Scone NSW 2337",
    "addr:housenumber":"142",
    "addr:postcode":"2337",
    "addr:street":"Susan St",
    "iso:country":"AU",
    "sg:address":"142 Susan St",
    "sg:city":"Scone",
    "sg:classifiers":[
        {
            "category":"Manufacturing",
            "subcategory":"Food",
            "type":"Manufacturing & Wholesale Goods"
        }
    ],
    "sg:phone":"+61 2 6545 1986",
    "sg:postcode":"2337",
    "sg:province":"NSW",
    "sg:tags":[
        "function",
        "catering"
    ],
    "wof:name":"Janes Home Cuisine",
    "wof:placetype":"venue"
},
  "geometry": {"coordinates":[150.87115478499999,-32.0465431213],"type":"Point"}
}