{
  "type": "Feature",
  "properties": {
    "addr:full":"43 Tom St Yarrawonga VIC 3730",
    "addr:housenumber":"43",
    "addr:postcode":"3730",
    "addr:street":"Tom St",
    "iso:country":"AU",
    "sg:address":"43 Tom St",
    "sg:city":"Yarrawonga",
    "sg:classifiers":[
        {
            "category":"Utilities",
            "subcategory":"Electric",
            "type":"Services"
        }
    ],
    "sg:phone":"+61 418 378 795",
    "sg:postcode":"3730",
    "sg:province":"VIC",
    "sg:tags":[
        "electrical",
        "contractor"
    ],
    "wof:name":"Thompson Ian",
    "wof:placetype":"venue"
},
  "geometry": {"coordinates":[146.001495361,-36.0155181885],"type":"Point"}
}