{
  "type": "Feature",
  "properties": {
    "addr:full":"2 Nar Nar Goon Rd Nar Nar Goon VIC 3812",
    "addr:housenumber":"2",
    "addr:postcode":"3812",
    "addr:street":"Nar Nar Goon Rd",
    "iso:country":"AU",
    "sg:address":"2 Nar Nar Goon Rd",
    "sg:city":"Nar Nar Goon",
    "sg:classifiers":[
        {
            "category":"Travel",
            "subcategory":"Hotels & Motels",
            "type":"Entertainment"
        }
    ],
    "sg:phone":"+61 3 5942 5221",
    "sg:postcode":"3812",
    "sg:province":"VIC",
    "sg:tags":[
        "pub"
    ],
    "wof:name":"Nar Nar Goon Hotel",
    "wof:placetype":"venue"
},
  "geometry": {"coordinates":[145.570145,-38.081631],"type":"Point"}
}