{
  "type": "Feature",
  "properties": {
    "iso:country":"AU",
    "sg:address":"43 Eclipse Drv",
    "sg:city":"Atherton",
    "sg:classifiers":[
        {
            "category":"Professional",
            "subcategory":"Detective & Security Services",
            "type":"Services"
        }
    ],
    "sg:phone":"+61 7 4091 3077",
    "sg:postcode":"4883",
    "sg:province":"QLD",
    "sg:tags":[
        "equipment",
        "window",
        "doors"
    ],
    "wof:name":"P & E Glass & Aluminium Windows",
    "wof:placetype":"venue"
},
  "geometry": {"coordinates":[145.47428894000001,-17.2557506561],"type":"Point"}
}