{
  "type": "Feature",
  "properties": {
    "addr:full":"35 Fairy St Bell Post Hill VIC 3215",
    "addr:housenumber":"35",
    "addr:postcode":"3215",
    "addr:street":"Fairy St",
    "iso:country":"AU",
    "sg:address":"35 Fairy St",
    "sg:city":"Bell Post Hill",
    "sg:classifiers":[
        {
            "category":"Utilities",
            "subcategory":"Water",
            "type":"Services"
        }
    ],
    "sg:phone":"+61 419 138 944",
    "sg:postcode":"3215",
    "sg:province":"VIC",
    "sg:tags":[
        "hot",
        "system"
    ],
    "wof:name":"Hey M G & C E",
    "wof:placetype":"venue"
},
  "geometry": {"coordinates":[144.328857422,-38.1040802002],"type":"Point"}
}