{
  "type": "Feature",
  "properties": {
    "iso:country":"AU",
    "sg:address":"54 Bligh Ave",
    "sg:city":"Camden South",
    "sg:classifiers":[
        {
            "category":"Sports & Exercise",
            "subcategory":"Sports Center",
            "type":"Entertainment"
        }
    ],
    "sg:phone":"+61 2 4655 3928",
    "sg:postcode":"2570",
    "sg:province":"NSW",
    "sg:tags":[
        "coach",
        "tennis"
    ],
    "wof:name":"Hit-Up Tennis",
    "wof:placetype":"venue"
},
  "geometry": {"coordinates":[150.69000244099999,-34.0774459839],"type":"Point"}
}