{
  "type": "Feature",
  "properties": {
    "addr:full":"3/32 Kularoo Drv Forster NSW 2428",
    "addr:housenumber":"/ 32",
    "addr:postcode":"2428",
    "addr:street":"Kularoo Drv",
    "iso:country":"AU",
    "sg:address":"3/32 Kularoo Drv",
    "sg:city":"Forster",
    "sg:classifiers":[
        {
            "category":"Home & Garden",
            "subcategory":"Furniture",
            "type":"Retail Goods"
        }
    ],
    "sg:phone":"+61 2 6555 3525",
    "sg:postcode":"2428",
    "sg:province":"NSW",
    "sg:tags":[
        "business"
    ],
    "wof:name":"Dale's Variety Warehouse",
    "wof:placetype":"venue"
},
  "geometry": {"coordinates":[152.51754800000001,-32.196323],"type":"Point"}
}