{
  "type": "Feature",
  "properties": {
    "addr:full":"38- 40 Glen Eira Rd Ripponlea VIC 3185",
    "addr:housenumber":"40",
    "addr:postcode":"3185",
    "addr:street":"Glen Eira Rd",
    "iso:country":"AU",
    "sg:address":"38- 40 Glen Eira Rd",
    "sg:city":"Ripponlea",
    "sg:classifiers":[
        {
            "category":"Sports & Exercise",
            "subcategory":"Gym",
            "type":"Entertainment"
        }
    ],
    "sg:phone":"+61 3 9533 0333",
    "sg:postcode":"3185",
    "sg:province":"VIC",
    "sg:tags":[
        "personal",
        "trainer",
        "fitness"
    ],
    "wof:name":"Fitness Fever Personal Training",
    "wof:placetype":"venue"
},
  "geometry": {"coordinates":[144.99598693900001,-37.8767967224],"type":"Point"}
}