{
  "type": "Feature",
  "properties": {
    "addr:full":"Shop B 105 Bateau Bay Rd Bateau Bay NSW 2261",
    "addr:housenumber":"105",
    "addr:postcode":"2261",
    "addr:street":"Bateau Bay Rd",
    "iso:country":"AU",
    "sg:address":"Shop B 105 Bateau Bay Rd",
    "sg:city":"Bateau Bay",
    "sg:classifiers":[
        {
            "category":"Personal",
            "subcategory":"Beauty Salon",
            "type":"Services"
        }
    ],
    "sg:phone":"+61 2 4333 4200",
    "sg:postcode":"2261",
    "sg:province":"NSW",
    "wof:name":"Essential Tanning Beauty & Nail Studio",
    "wof:placetype":"venue"
},
  "geometry": {"coordinates":[151.48114000000001,-33.381344],"type":"Point"}
}