{
  "type": "Feature",
  "properties": {
    "addr:full":"32 Vermont Crt Berriedale TAS 7011",
    "addr:housenumber":"32",
    "addr:postcode":"7011",
    "addr:street":"Vermont Crt",
    "iso:country":"AU",
    "sg:address":"32 Vermont Crt",
    "sg:city":"Berriedale",
    "sg:classifiers":[
        {
            "category":"Professional",
            "subcategory":"Art Services",
            "type":"Services"
        }
    ],
    "sg:phone":"+61 3 6249 2041",
    "sg:postcode":"7011",
    "sg:province":"TAS",
    "sg:tags":[
        "decorator",
        "painter"
    ],
    "wof:name":"Cameron Bennette Painting Decorating",
    "wof:placetype":"venue"
},
  "geometry": {"coordinates":[147.251663208,-42.8116455078],"type":"Point"}
}