{
  "type": "Feature",
  "properties": {
    "addr:full":"609 Whitehorse Rd Balwyn VIC 3103",
    "addr:housenumber":"609",
    "addr:postcode":"3103",
    "addr:street":"Whitehorse Rd",
    "iso:country":"AU",
    "sg:address":"609 Whitehorse Rd",
    "sg:city":"Balwyn",
    "sg:classifiers":[
        {
            "category":"Shopping",
            "subcategory":"Clothing, Apparel, & Fashions",
            "type":"Retail Goods"
        }
    ],
    "sg:phone":"+61 3 9880 7848",
    "sg:postcode":"3103",
    "sg:province":"VIC",
    "sg:tags":[
        "recycled",
        "clothing"
    ],
    "wof:name":"Brotherhood Of St Laurence",
    "wof:placetype":"venue"
},
  "geometry": {"coordinates":[145.09901428200001,-37.8148155212],"type":"Point"}
}