{
  "type": "Feature",
  "properties": {
    "addr:full":"18 Pavitt Crs Wyong NSW 2259",
    "addr:housenumber":"18",
    "addr:postcode":"2259",
    "addr:street":"Pavitt Crs",
    "iso:country":"AU",
    "sg:address":"18 Pavitt Crs",
    "sg:city":"Wyong",
    "sg:classifiers":[
        {
            "category":"Home & Garden",
            "subcategory":"Building Materials",
            "type":"Retail Goods"
        }
    ],
    "sg:phone":"+61 2 4353 1624",
    "sg:postcode":"2259",
    "sg:province":"NSW",
    "sg:tags":[
        "pre-mixed",
        "concrete"
    ],
    "wof:name":"Readymix",
    "wof:placetype":"venue"
},
  "geometry": {"coordinates":[151.42552185100001,-33.2829093933],"type":"Point"}
}