{
  "type": "Feature",
  "properties": {
    "iso:country":"AU",
    "sg:address":"211 Waterworks Rd",
    "sg:city":"Ashgrove",
    "sg:classifiers":[
        {
            "category":"Restaurant",
            "type":"Food & Drink"
        }
    ],
    "sg:phone":"+61 7 3366 0580",
    "sg:postcode":"4060",
    "sg:province":"QLD",
    "wof:name":"Ashgrove Chinese Kitchen",
    "wof:placetype":"venue"
},
  "geometry": {"coordinates":[152.99420165999999,-27.4453678131],"type":"Point"}
}