{
  "type": "Feature",
  "properties": {
    "iso:country":"AU",
    "sg:address":"Cnr Breese Pde & Enterprise Crt",
    "sg:city":"Forster",
    "sg:classifiers":[
        {
            "category":"Utilities",
            "subcategory":"Water",
            "type":"Services"
        }
    ],
    "sg:phone":"+61 2 6591 7917",
    "sg:postcode":"2428",
    "sg:province":"NSW",
    "sg:tags":[
        "hot",
        "system"
    ],
    "wof:name":"Town Plumbing Supplies",
    "wof:placetype":"venue"
},
  "geometry": {"coordinates":[152.52041600000001,-32.200291],"type":"Point"}
}