{
  "type": "Feature",
  "properties": {
    "addr:full":"445 Queensberry St North Melbourne VIC 3051",
    "addr:housenumber":"445",
    "addr:postcode":"3051",
    "addr:street":"Queensberry St",
    "iso:country":"AU",
    "sg:address":"445 Queensberry St",
    "sg:city":"North Melbourne",
    "sg:classifiers":[
        {
            "category":"Fast Food",
            "type":"Food & Drink"
        }
    ],
    "sg:phone":"+61 3 9329 9522",
    "sg:postcode":"3051",
    "sg:province":"VIC",
    "sg:tags":[
        "away",
        "take"
    ],
    "wof:name":"BK Jam",
    "wof:placetype":"venue"
},
  "geometry": {"coordinates":[144.950439453,-37.8033370972],"type":"Point"}
}