{
  "type": "Feature",
  "properties": {
    "addr:full":"7b Audsley St Clayton South VIC 3169",
    "addr:housenumber":"7b",
    "addr:postcode":"3169",
    "addr:street":"Audsley St",
    "iso:country":"AU",
    "sg:address":"7b Audsley St",
    "sg:city":"Clayton South",
    "sg:classifiers":[
        {
            "category":"Building & Trades",
            "subcategory":"Construction",
            "type":"Services"
        }
    ],
    "sg:phone":"+61 3 9562 8150",
    "sg:postcode":"3169",
    "sg:province":"VIC",
    "sg:tags":[
        "stonework",
        "stone",
        "mason"
    ],
    "sg:website":"http://www.classiquestone.com.au",
    "wof:name":"Classique Stone",
    "wof:placetype":"venue"
},
  "geometry": {"coordinates":[145.12193298299999,-37.9309005737],"type":"Point"}
}