{
  "type": "Feature",
  "properties": {
    "iso:country":"AU",
    "sg:address":"163 Argyle St",
    "sg:city":"Camden",
    "sg:classifiers":[
        {
            "category":"Fast Food",
            "type":"Food & Drink"
        }
    ],
    "sg:phone":"+61 2 4655 6247",
    "sg:postcode":"2570",
    "sg:province":"NSW",
    "sg:tags":[
        "away",
        "take"
    ],
    "wof:name":"Queen's Charcoal Chicken",
    "wof:placetype":"venue"
},
  "geometry": {"coordinates":[150.69424438499999,-34.0549888611],"type":"Point"}
}