{
  "type": "Feature",
  "properties": {
    "iso:country":"AU",
    "sg:address":"Ring Rd",
    "sg:city":"Wendouree",
    "sg:classifiers":[
        {
            "category":"Building & Trades",
            "subcategory":"Construction",
            "type":"Services"
        }
    ],
    "sg:phone":"+61 3 5339 4659",
    "sg:postcode":"3355",
    "sg:province":"VIC",
    "sg:tags":[
        "concrete",
        "paving"
    ],
    "wof:name":"Sovereign Concrete Products",
    "wof:placetype":"venue"
},
  "geometry": {"coordinates":[143.811615,-37.524189],"type":"Point"}
}