{
  "type": "Feature",
  "properties": {
    "iso:country":"AU",
    "sg:address":"56 Chandos St",
    "sg:city":"St Leonards",
    "sg:classifiers":[
        {
            "category":"Insurance",
            "subcategory":"Insurance Agent",
            "type":"Services"
        }
    ],
    "sg:phone":"+61 2 9438 3411",
    "sg:postcode":"2065",
    "sg:province":"NSW",
    "wof:name":"M Q Carbone Pty Ltd",
    "wof:placetype":"venue"
},
  "geometry": {"coordinates":[151.19760131800001,-33.8218841553],"type":"Point"}
}