{
  "type": "Feature",
  "properties": {
    "addr:full":"3 Belgrave Crt Parkside SA 5063",
    "addr:housenumber":"3",
    "addr:postcode":"5063",
    "addr:street":"Belgrave Crt",
    "iso:country":"AU",
    "sg:address":"3 Belgrave Crt",
    "sg:city":"Parkside",
    "sg:classifiers":[
        {
            "category":"Real Estate",
            "subcategory":"Real Estate Agent",
            "type":"Services"
        }
    ],
    "sg:phone":"+61 8 8272 0666",
    "sg:postcode":"5063",
    "sg:province":"SA",
    "wof:name":"Stanley Samuels Pty Ltd",
    "wof:placetype":"venue"
},
  "geometry": {"coordinates":[138.60746765100001,-34.9462661743],"type":"Point"}
}