{
  "type": "Feature",
  "properties": {
    "addr:full":"Station St Nyah West VIC 3595",
    "addr:postcode":"3595",
    "addr:street":"Station St",
    "iso:country":"AU",
    "sg:address":"Station St",
    "sg:city":"Nyah West",
    "sg:classifiers":[
        {
            "category":"Travel",
            "subcategory":"Hotels & Motels",
            "type":"Entertainment"
        }
    ],
    "sg:phone":"+61 3 5030 2403",
    "sg:postcode":"3595",
    "sg:province":"VIC",
    "sg:tags":[
        "accommodation"
    ],
    "wof:name":"The Grand Hotel Nyah West",
    "wof:placetype":"venue"
},
  "geometry": {"coordinates":[143.345626831,-35.1855201721],"type":"Point"}
}