{
  "type": "Feature",
  "properties": {
    "addr:full":"PO Box 5044 Chisholm ACT 2905",
    "addr:postcode":"2905",
    "iso:country":"AU",
    "sg:address":"PO Box 5044",
    "sg:city":"Chisholm",
    "sg:classifiers":[
        {
            "category":"Building & Trades",
            "subcategory":"Cleaning & Sanitation",
            "type":"Services"
        }
    ],
    "sg:phone":"+61 418 697 507",
    "sg:postcode":"2905",
    "sg:province":"ACT",
    "sg:tags":[
        "window"
    ],
    "wof:name":"A-O-K Window Cleaning A.C.T.",
    "wof:placetype":"venue"
},
  "geometry": {"coordinates":[149.124176025,-35.4190483093],"type":"Point"}
}