{
  "type": "Feature",
  "properties": {
    "addr:full":"1/ 9 Doggett St Fortitude Valley QLD 4006",
    "addr:housenumber":"/ 9",
    "addr:postcode":"4006",
    "addr:street":"Doggett St",
    "iso:country":"AU",
    "sg:address":"1/ 9 Doggett St",
    "sg:city":"Fortitude Valley",
    "sg:classifiers":[
        {
            "category":"Home & Garden",
            "subcategory":"Carpets & Floor Coverings",
            "type":"Retail Goods"
        }
    ],
    "sg:phone":"+61 7 3254 1344",
    "sg:postcode":"4006",
    "sg:province":"QLD",
    "sg:tags":[
        "tile",
        "wall"
    ],
    "wof:name":"Project Stone & Tile P/L",
    "wof:placetype":"venue"
},
  "geometry": {"coordinates":[153.04083251899999,-27.456785202],"type":"Point"}
}