{
  "type": "Feature",
  "properties": {
    "addr:full":"Shop 7, Petrie Village 15 Dayboro Rd Petrie QLD 4502",
    "addr:housenumber":"shop 7;15",
    "addr:postcode":"4502",
    "addr:street":"Village;Dayboro Rd",
    "iso:country":"AU",
    "sg:address":"Shop 7, Petrie Village 15 Dayboro Rd",
    "sg:city":"Petrie",
    "sg:classifiers":[
        {
            "category":"Real Estate",
            "subcategory":"Real Estate Agent",
            "type":"Services"
        }
    ],
    "sg:phone":"+61 7 3285 2111",
    "sg:postcode":"4502",
    "sg:province":"QLD",
    "wof:name":"L J Hooker",
    "wof:placetype":"venue"
},
  "geometry": {"coordinates":[152.973999023,-27.268371582],"type":"Point"}
}