{
  "type": "Feature",
  "properties": {
    "iso:country":"AU",
    "sg:address":"PO Box 16",
    "sg:city":"Port Neill",
    "sg:classifiers":[
        {
            "category":"Communications",
            "subcategory":"Film & Video Production",
            "type":"Services"
        }
    ],
    "sg:phone":"+61 8 8688 9002",
    "sg:postcode":"5604",
    "sg:province":"SA",
    "sg:tags":[
        "made",
        "clothing",
        "custom"
    ],
    "wof:name":"Carrow Fabrics & Clothing",
    "wof:placetype":"venue"
},
  "geometry": {"coordinates":[136.298294,-34.082729],"type":"Point"}
}