{
  "type": "Feature",
  "properties": {
    "addr:full":"27 Sale St Orange NSW 2800",
    "addr:housenumber":"27",
    "addr:postcode":"2800",
    "addr:street":"Sale St",
    "iso:country":"AU",
    "sg:address":"27 Sale St",
    "sg:city":"Orange",
    "sg:classifiers":[
        {
            "category":"Professional",
            "subcategory":"Accounting & Tax Preparation",
            "type":"Services"
        }
    ],
    "sg:phone":"+61 2 6362 1533",
    "sg:postcode":"2800",
    "sg:province":"NSW",
    "sg:tags":[
        "consultant",
        "taxation"
    ],
    "wof:name":"Yates Baker McLean",
    "wof:placetype":"venue"
},
  "geometry": {"coordinates":[149.09580993599999,-33.2844772339],"type":"Point"}
}