{
  "type": "Feature",
  "properties": {
    "addr:full":"398 Burnley St Richmond VIC 3121",
    "addr:housenumber":"398",
    "addr:postcode":"3121",
    "addr:street":"Burnley St",
    "iso:country":"AU",
    "sg:address":"398 Burnley St",
    "sg:city":"Richmond",
    "sg:classifiers":[
        {
            "category":"Health Services",
            "subcategory":"Health Practitioner",
            "type":"Services"
        }
    ],
    "sg:phone":"+61 3 9591 0440",
    "sg:postcode":"3121",
    "sg:province":"VIC",
    "sg:tags":[
        "psychologist"
    ],
    "wof:name":"Magnusson Ruth",
    "wof:placetype":"venue"
},
  "geometry": {"coordinates":[145.00694274899999,-37.8261260986],"type":"Point"}
}