{
  "type": "Feature",
  "properties": {
    "addr:full":"Shakespeare St Carinda NSW 2831",
    "addr:postcode":"2831",
    "addr:street":"Shakespeare St",
    "iso:country":"AU",
    "sg:address":"Shakespeare St",
    "sg:city":"Carinda",
    "sg:classifiers":[
        {
            "category":"Sports & Exercise",
            "subcategory":"Golf",
            "type":"Entertainment"
        }
    ],
    "sg:phone":"+61 2 6823 2257",
    "sg:postcode":"2831",
    "sg:province":"NSW",
    "sg:tags":[
        "club"
    ],
    "wof:name":"Carinda Golf Club",
    "wof:placetype":"venue"
},
  "geometry": {"coordinates":[147.69046020499999,-30.4611091614],"type":"Point"}
}