{
  "type": "Feature",
  "properties": {
    "addr:full":"15 Spark St Mascot NSW 2020",
    "addr:housenumber":"15",
    "addr:postcode":"2020",
    "addr:street":"Spark St",
    "iso:country":"AU",
    "sg:address":"15 Spark St",
    "sg:city":"Mascot",
    "sg:classifiers":[
        {
            "category":"Professional",
            "type":"Services"
        }
    ],
    "sg:phone":"+61 2 9669 3553",
    "sg:postcode":"2020",
    "sg:province":"NSW",
    "sg:tags":[
        "transport"
    ],
    "wof:name":"ADB Transportation Pty Ltd",
    "wof:placetype":"venue"
},
  "geometry": {"coordinates":[151.20045471200001,-33.9335479736],"type":"Point"}
}