{
  "type": "Feature",
  "properties": {
    "iso:country":"AU",
    "sg:address":"Main Rd",
    "sg:city":"Frances",
    "sg:classifiers":[
        {
            "category":"Farming",
            "subcategory":"Farm & Veterinary Services",
            "type":"Manufacturing & Wholesale Goods"
        }
    ],
    "sg:phone":"+61 8 8765 1011",
    "sg:postcode":"5262",
    "sg:province":"SA",
    "sg:tags":[
        "drying",
        "seed",
        "cleaning",
        "grading"
    ],
    "wof:name":"Frances Seeds",
    "wof:placetype":"venue"
},
  "geometry": {"coordinates":[140.953995,-36.70504],"type":"Point"}
}