{
  "type": "Feature",
  "properties": {
    "addr:full":"Level 1/ 20 Tompson St Wagga Wagga NSW 2650",
    "addr:housenumber":"/ 20",
    "addr:postcode":"2650",
    "addr:street":"Tompson St",
    "iso:country":"AU",
    "sg:address":"Level 1/ 20 Tompson St",
    "sg:city":"Wagga Wagga",
    "sg:classifiers":[
        {
            "category":"Education",
            "subcategory":"Special Training",
            "type":"Public Place"
        }
    ],
    "sg:phone":"+61 2 6931 8666",
    "sg:postcode":"2650",
    "sg:province":"NSW",
    "sg:tags":[
        "development"
    ],
    "wof:name":"Summit Business Coaching",
    "wof:placetype":"venue"
},
  "geometry": {"coordinates":[147.372756958,-35.1123466492],"type":"Point"}
}