{
  "type": "Feature",
  "properties": {
    "iso:country":"AU",
    "sg:address":"8 Isaacs St",
    "sg:city":"Busselton",
    "sg:classifiers":[
        {
            "category":"Professional",
            "type":"Services"
        }
    ],
    "sg:phone":"+61 8 9752 3945",
    "sg:postcode":"6280",
    "sg:province":"WA",
    "sg:tags":[
        "courier"
    ],
    "wof:name":"Gbay Couriers",
    "wof:placetype":"venue"
},
  "geometry": {"coordinates":[115.351387024,-33.6603164673],"type":"Point"}
}