{
  "type": "Feature",
  "properties": {
    "iso:country":"AU",
    "sg:address":"37- 41 Canton Beach Rd",
    "sg:city":"Toukley",
    "sg:classifiers":[
        {
            "category":"Health Services",
            "subcategory":"Doctor",
            "type":"Services"
        }
    ],
    "sg:phone":"+61 2 4396 8877",
    "sg:postcode":"2263",
    "sg:province":"NSW",
    "sg:tags":[
        "medical",
        "practitioner"
    ],
    "wof:name":"Palan.D Dr",
    "wof:placetype":"venue"
},
  "geometry": {"coordinates":[151.54093900000001,-33.264996],"type":"Point"}
}