{
  "type": "Feature",
  "properties": {
    "iso:country":"AU",
    "sg:address":"259 Forrest St",
    "sg:city":"Kalgoorlie",
    "sg:classifiers":[
        {
            "category":"Manufacturing",
            "subcategory":"Metals",
            "type":"Manufacturing & Wholesale Goods"
        }
    ],
    "sg:phone":"+61 8 9021 1549",
    "sg:postcode":"6430",
    "sg:province":"WA",
    "sg:tags":[
        "steel",
        "fabricator",
        "mfrs"
    ],
    "wof:name":"J & R Miller Mining & Engineering Services",
    "wof:placetype":"venue"
},
  "geometry": {"coordinates":[121.46410369900001,-30.7496242523],"type":"Point"}
}