{
  "type": "Feature",
  "properties": {
    "addr:full":"10 Sleep Rd Para Hills SA 5096",
    "addr:postcode":"5096",
    "addr:street":"Sleep Rd Para",
    "iso:country":"AU",
    "sg:address":"10 Sleep Rd",
    "sg:city":"Para Hills",
    "sg:classifiers":[
        {
            "category":"Building & Trades",
            "subcategory":"Cleaning & Sanitation",
            "type":"Services"
        }
    ],
    "sg:phone":"+61 8 8264 6446",
    "sg:postcode":"5096",
    "sg:province":"SA",
    "sg:tags":[
        "cleaner",
        "repairer",
        "roof"
    ],
    "wof:name":"D R Roofing",
    "wof:placetype":"venue"
},
  "geometry": {"coordinates":[138.65861511200001,-34.8140945435],"type":"Point"}
}