{
  "type": "Feature",
  "properties": {
    "addr:full":"124 Northgate Rd Northgate QLD 4013",
    "addr:housenumber":"124",
    "addr:postcode":"4013",
    "addr:street":"Northgate Rd",
    "iso:country":"AU",
    "sg:address":"124 Northgate Rd",
    "sg:city":"Northgate",
    "sg:classifiers":[
        {
            "category":"Social Services",
            "subcategory":"Child Care",
            "type":"Services"
        }
    ],
    "sg:phone":"+61 7 3266 1052",
    "sg:postcode":"4013",
    "sg:province":"QLD",
    "wof:name":"Northgate Early Childhood Centre",
    "wof:placetype":"venue"
},
  "geometry": {"coordinates":[153.06524658199999,-27.3903007507],"type":"Point"}
}