{
  "type": "Feature",
  "properties": {
    "addr:full":"Nepondi Crt Fairview Park SA 5126",
    "addr:postcode":"5126",
    "addr:street":"Nepondi Crt",
    "iso:country":"AU",
    "sg:address":"Nepondi Crt",
    "sg:city":"Fairview Park",
    "sg:classifiers":[
        {
            "category":"Education",
            "subcategory":"School",
            "type":"Public Place"
        }
    ],
    "sg:phone":"+61 8 8251 2717",
    "sg:postcode":"5126",
    "sg:province":"SA",
    "sg:tags":[
        "state",
        "except",
        "nsw"
    ],
    "wof:name":"Fairview Park Primary",
    "wof:placetype":"venue"
},
  "geometry": {"coordinates":[138.73057556099999,-34.7987747192],"type":"Point"}
}