{
  "type": "Feature",
  "properties": {
    "addr:full":"Cnr Collet & Corio St Shepparton VIC 3630",
    "addr:postcode":"3630",
    "addr:street":"Cnr;St",
    "iso:country":"AU",
    "sg:address":"Cnr Collet & Corio St",
    "sg:city":"Shepparton",
    "sg:classifiers":[
        {
            "category":"Health Services",
            "subcategory":"Health Practitioner",
            "type":"Services"
        }
    ],
    "sg:phone":"+61 3 5831 2712",
    "sg:postcode":"3630",
    "sg:province":"VIC",
    "sg:tags":[
        "naturopath"
    ],
    "wof:name":"Collie Kevin",
    "wof:placetype":"venue"
},
  "geometry": {"coordinates":[145.402618408,-36.3852005005],"type":"Point"}
}