{
  "type": "Feature",
  "properties": {
    "addr:full":"197 Sherbourne Rd Eltham VIC 3095",
    "addr:housenumber":"197",
    "addr:postcode":"3095",
    "addr:street":"Sherbourne Rd",
    "iso:country":"AU",
    "sg:address":"197 Sherbourne Rd",
    "sg:city":"Eltham",
    "sg:classifiers":[
        {
            "category":"Shopping",
            "subcategory":"Bicycles & Sporting Goods",
            "type":"Retail Goods"
        }
    ],
    "sg:phone":"+61 3 9439 8218",
    "sg:postcode":"3095",
    "sg:province":"VIC",
    "sg:tags":[
        "chemical",
        "equipment",
        "pool",
        "swimming"
    ],
    "wof:name":"Kreepy Krauly",
    "wof:placetype":"venue"
},
  "geometry": {"coordinates":[145.136062622,-37.7155151367],"type":"Point"}
}