{
  "type": "Feature",
  "properties": {
    "addr:full":"1003 Latrobe St Ballarat VIC 3350",
    "addr:housenumber":"1003",
    "addr:postcode":"3350",
    "addr:street":"Latrobe St",
    "iso:country":"AU",
    "sg:address":"1003 Latrobe St",
    "sg:city":"Ballarat",
    "sg:classifiers":[
        {
            "category":"Wholesale",
            "subcategory":"Chemicals & Plastics",
            "type":"Manufacturing & Wholesale Goods"
        }
    ],
    "sg:phone":"+61 3 5335 9349",
    "sg:postcode":"3350",
    "sg:province":"VIC",
    "sg:tags":[
        "repair"
    ],
    "wof:name":"Ballarat Bumpers",
    "wof:placetype":"venue"
},
  "geometry": {"coordinates":[143.82072400000001,-37.571083],"type":"Point"}
}