{
  "type": "Feature",
  "properties": {
    "addr:full":"2 Bennett Pl Worrigee NSW 2540",
    "addr:housenumber":"2",
    "addr:postcode":"2540",
    "addr:street":"Bennett Pl Worrigee",
    "iso:country":"AU",
    "sg:address":"2 Bennett Pl",
    "sg:city":"Worrigee",
    "sg:classifiers":[
        {
            "category":"Utilities",
            "subcategory":"Water",
            "type":"Services"
        }
    ],
    "sg:phone":"+61 2 4421 8082",
    "sg:postcode":"2540",
    "sg:province":"NSW",
    "sg:tags":[
        "hot",
        "system"
    ],
    "wof:name":"Finney Electrical",
    "wof:placetype":"venue"
},
  "geometry": {"coordinates":[150.63424682600001,-34.908039093],"type":"Point"}
}