{
  "type": "Feature",
  "properties": {
    "addr:full":"Mt Rascal Rd Toowoomba QLD 4350",
    "addr:postcode":"4350",
    "addr:street":"Rascal Rd",
    "iso:country":"AU",
    "sg:address":"Mt Rascal Rd",
    "sg:city":"Toowoomba",
    "sg:classifiers":[
        {
            "category":"Utilities",
            "subcategory":"Electric",
            "type":"Services"
        }
    ],
    "sg:phone":"+61 7 4637 2224",
    "sg:postcode":"4350",
    "sg:province":"QLD",
    "sg:tags":[
        "electrical",
        "contractor"
    ],
    "wof:name":"Brett Ebneter Electrical",
    "wof:placetype":"venue"
},
  "geometry": {"coordinates":[151.91377299999999,-27.628035],"type":"Point"}
}