{
  "type": "Feature",
  "properties": {
    "iso:country":"AU",
    "sg:address":"Unit 2, 7 Taree St",
    "sg:city":"West Burleigh",
    "sg:classifiers":[
        {
            "category":"Building & Trades",
            "subcategory":"Construction",
            "type":"Services"
        }
    ],
    "sg:phone":"+61 7 5593 8444",
    "sg:postcode":"4219",
    "sg:province":"QLD",
    "sg:tags":[
        "renovation",
        "alterations",
        "extension",
        "contractor"
    ],
    "wof:name":"Timbertone & Garage Doors",
    "wof:placetype":"venue"
},
  "geometry": {"coordinates":[153.422317505,-28.1026172638],"type":"Point"}
}