{
  "type": "Feature",
  "properties": {
    "iso:country":"AU",
    "sg:address":"119 Greens Rd",
    "sg:city":"Dandenong",
    "sg:classifiers":[
        {
            "category":"Manufacturing",
            "subcategory":"Chemicals & Compounds",
            "type":"Manufacturing & Wholesale Goods"
        }
    ],
    "sg:phone":"+61 3 9706 0042",
    "sg:postcode":"3175",
    "sg:province":"VIC",
    "sg:tags":[
        "electroplating"
    ],
    "wof:name":"Advanced Electroplating",
    "wof:placetype":"venue"
},
  "geometry": {"coordinates":[145.212432861,-38.0141029358],"type":"Point"}
}