{
  "type": "Feature",
  "properties": {
    "iso:country":"AU",
    "sg:address":"23 Gordon St",
    "sg:city":"Coffs Harbour",
    "sg:classifiers":[
        {
            "category":"Organizations",
            "subcategory":"Non-profit Organization",
            "type":"Services"
        }
    ],
    "sg:phone":"+61 2 6651 1863",
    "sg:postcode":"2450",
    "sg:province":"NSW",
    "sg:tags":[
        "support",
        "disability",
        "organisation"
    ],
    "wof:name":"Royal Blind Society Of NSW - Coffs Harbour",
    "wof:placetype":"venue"
},
  "geometry": {"coordinates":[153.11731,-30.296764],"type":"Point"}
}