{
  "type": "Feature",
  "properties": {
    "iso:country":"AU",
    "sg:address":"6/ 29 Casey St",
    "sg:city":"Aitkenvale",
    "sg:classifiers":[
        {
            "category":"Autos & Motor Vehicles",
            "subcategory":"Auto Supplies",
            "type":"Retail Goods"
        }
    ],
    "sg:phone":"+61 7 4779 1340",
    "sg:postcode":"4814",
    "sg:province":"QLD",
    "sg:tags":[
        "part",
        "cycles",
        "accessory"
    ],
    "wof:name":"RHD Classic Supplies & Services",
    "wof:placetype":"venue"
},
  "geometry": {"coordinates":[146.76980599999999,-19.294333],"type":"Point"}
}