{
  "type": "Feature",
  "properties": {
    "addr:full":"Hamilton Rd Horsham VIC 3400",
    "addr:postcode":"3400",
    "addr:street":"Hamilton Rd",
    "iso:country":"AU",
    "sg:address":"Hamilton Rd",
    "sg:city":"Horsham",
    "sg:classifiers":[
        {
            "category":"Manufacturing",
            "subcategory":"Motor Vehicles & Parts",
            "type":"Manufacturing & Wholesale Goods"
        }
    ],
    "sg:phone":"+61 3 5381 1724",
    "sg:postcode":"3400",
    "sg:province":"VIC",
    "sg:tags":[
        "replacement"
    ],
    "wof:name":"Membrey Auto Wreckers & Repairs",
    "wof:placetype":"venue"
},
  "geometry": {"coordinates":[142.19769287099999,-36.7178382874],"type":"Point"}
}