{
  "type": "Feature",
  "properties": {
    "iso:country":"AU",
    "sg:address":"Shop 1 / 243 Anzac Pde,",
    "sg:city":"Kingsford",
    "sg:classifiers":[
        {
            "category":"Health Services",
            "subcategory":"Health Practitioner",
            "type":"Services"
        }
    ],
    "sg:phone":"+61 2 9313 8474",
    "sg:postcode":"2032",
    "sg:province":"NSW",
    "sg:tags":[
        "physiotherapist"
    ],
    "wof:name":"Anzac Parade Physiotherapy",
    "wof:placetype":"venue"
},
  "geometry": {"coordinates":[151.22633361800001,-33.9195976257],"type":"Point"}
}