{
  "type": "Feature",
  "properties": {
    "addr:full":"8155 Bass Hwy Leongatha VIC 3953",
    "addr:housenumber":"8155",
    "addr:postcode":"3953",
    "addr:street":"Bass Hwy",
    "iso:country":"AU",
    "sg:address":"8155 Bass Hwy",
    "sg:city":"Leongatha",
    "sg:classifiers":[
        {
            "category":"Professional",
            "subcategory":"Accounting & Tax Preparation",
            "type":"Services"
        }
    ],
    "sg:phone":"+61 409 622 820",
    "sg:postcode":"3953",
    "sg:province":"VIC",
    "sg:tags":[
        "bookkeeping"
    ],
    "wof:name":"Lorade Bookkeeping",
    "wof:placetype":"venue"
},
  "geometry": {"coordinates":[145.936843872,-38.4787368774],"type":"Point"}
}