{
  "type": "Feature",
  "properties": {
    "addr:full":"PO Box 50 Tumby Bay SA 5605",
    "addr:postcode":"5605",
    "iso:country":"AU",
    "sg:address":"PO Box 50",
    "sg:city":"Tumby Bay",
    "sg:classifiers":[
        {
            "category":"Farming",
            "subcategory":"Farm",
            "type":"Manufacturing & Wholesale Goods"
        }
    ],
    "sg:phone":"+61 8 8688 2182",
    "sg:postcode":"5605",
    "sg:province":"SA",
    "sg:tags":[
        "farmer"
    ],
    "wof:name":"Richardson A G & S J",
    "wof:placetype":"venue"
},
  "geometry": {"coordinates":[136.10131799999999,-34.37513],"type":"Point"}
}