{
  "type": "Feature",
  "properties": {
    "addr:full":"Cnr Young Rd & Waratah St Cowra NSW 2794",
    "addr:postcode":"2794",
    "addr:street":"Cnr Young Rd & Waratah St",
    "iso:country":"AU",
    "sg:address":"Cnr Young Rd & Waratah St",
    "sg:city":"Cowra",
    "sg:classifiers":[
        {
            "category":"Autos & Motor Vehicles",
            "subcategory":"Auto Supplies",
            "type":"Retail Goods"
        }
    ],
    "sg:phone":"+61 2 6342 4533",
    "sg:postcode":"2794",
    "sg:province":"NSW",
    "sg:tags":[
        "equipment",
        "part",
        "truck"
    ],
    "wof:name":"Cowra Truck Wreckers",
    "wof:placetype":"venue"
},
  "geometry": {"coordinates":[148.67721557600001,-33.8435707092],"type":"Point"}
}