{
  "type": "Feature",
  "properties": {
    "addr:full":"Unit 20/ 33 Scrivener St Warwick Farm NSW 2170",
    "addr:housenumber":"/ 33",
    "addr:postcode":"2170",
    "addr:street":"Scrivener St",
    "iso:country":"AU",
    "sg:address":"Unit 20/ 33 Scrivener St",
    "sg:city":"Warwick Farm",
    "sg:classifiers":[
        {
            "category":"Shopping",
            "subcategory":"Stationery & Office Supplies",
            "type":"Retail Goods"
        }
    ],
    "sg:phone":"+61 2 9600 8330",
    "sg:postcode":"2170",
    "sg:province":"NSW",
    "sg:tags":[
        "packaging",
        "material"
    ],
    "wof:name":"W F Plastic Pty Ltd",
    "wof:placetype":"venue"
},
  "geometry": {"coordinates":[150.93753051799999,-33.9193458557],"type":"Point"}
}