{
  "type": "Feature",
  "properties": {
    "addr:full":"Cnr Esplanade & Second Ave Maroochydore QLD 4558",
    "addr:postcode":"4558",
    "addr:street":"Cnr Esplanade;Second Ave",
    "iso:country":"AU",
    "sg:address":"Cnr Esplanade & Second Ave",
    "sg:city":"Maroochydore",
    "sg:classifiers":[
        {
            "category":"Health Services",
            "subcategory":"Doctor",
            "type":"Services"
        }
    ],
    "sg:phone":"+61 7 5443 4301",
    "sg:postcode":"4558",
    "sg:province":"QLD",
    "sg:tags":[
        "medical",
        "practitioner"
    ],
    "wof:name":"Stokes Paul Dr",
    "wof:placetype":"venue"
},
  "geometry": {"coordinates":[153.09390258799999,-26.6590766907],"type":"Point"}
}