{
  "type": "Feature",
  "properties": {
    "iso:country":"AU",
    "sg:address":"St Aloysius College 73 Boundary Rd",
    "sg:city":"North Melbourne",
    "sg:classifiers":[
        {
            "category":"Sports & Exercise",
            "subcategory":"Gym",
            "type":"Entertainment"
        }
    ],
    "sg:phone":"+61 401 025 866",
    "sg:postcode":"3051",
    "sg:province":"VIC",
    "sg:tags":[
        "health",
        "fitness"
    ],
    "wof:name":"EFM Nth Melbourne",
    "wof:placetype":"venue"
},
  "geometry": {"coordinates":[144.93919372600001,-37.7928619385],"type":"Point"}
}