{
  "type": "Feature",
  "properties": {
    "iso:country":"AU",
    "sg:address":"286 White Rd",
    "sg:city":"Wonthaggi",
    "sg:classifiers":[
        {
            "category":"Home & Garden",
            "subcategory":"Garden Supply",
            "type":"Retail Goods"
        }
    ],
    "sg:phone":"+61 3 5672 3884",
    "sg:postcode":"3995",
    "sg:province":"VIC",
    "sg:tags":[
        "statuary",
        "fountains",
        "sundial"
    ],
    "wof:name":"White Road Garden Centre",
    "wof:placetype":"venue"
},
  "geometry": {"coordinates":[145.581406,-38.588902],"type":"Point"}
}