{
  "type": "Feature",
  "properties": {
    "addr:full":"Church St Brighton VIC 3186",
    "addr:postcode":"3186",
    "addr:street":"Church St",
    "iso:country":"AU",
    "sg:address":"Church St",
    "sg:city":"Brighton",
    "sg:classifiers":[
        {
            "category":"Health Services",
            "subcategory":"Health Practitioner",
            "type":"Services"
        }
    ],
    "sg:phone":"+61 3 9592 9232",
    "sg:postcode":"3186",
    "sg:province":"VIC",
    "sg:tags":[
        "psychologist"
    ],
    "wof:name":"Shaw Mary",
    "wof:placetype":"venue"
},
  "geometry": {"coordinates":[144.99372863799999,-37.9132766724],"type":"Point"}
}