{
  "type": "Feature",
  "properties": {
    "iso:country":"AU",
    "sg:address":"93 Railway Pde",
    "sg:city":"Marrickville",
    "sg:classifiers":[
        {
            "category":"Wholesale",
            "subcategory":"Apparel",
            "type":"Manufacturing & Wholesale Goods"
        }
    ],
    "sg:phone":"+61 2 9519 1346",
    "sg:postcode":"2204",
    "sg:province":"NSW",
    "sg:tags":[
        "wholesaler",
        "mfrs",
        "dress"
    ],
    "wof:name":"Jenny Australia Pty Ltd",
    "wof:placetype":"venue"
},
  "geometry": {"coordinates":[151.1651,-33.914516],"type":"Point"}
}