{
  "type": "Feature",
  "properties": {
    "addr:full":"Shop 2104 Westfield Shoppingtown Parramatta NSW 2150",
    "addr:housenumber":"2104;shoppingtown",
    "addr:postcode":"2150",
    "addr:street":"Westfield",
    "iso:country":"AU",
    "sg:address":"Shop 2104 Westfield Shoppingtown",
    "sg:city":"Parramatta",
    "sg:classifiers":[
        {
            "category":"Banks & Credit Unions",
            "subcategory":"Bank",
            "type":"Services"
        }
    ],
    "sg:phone":"+61 2 9893 8833",
    "sg:postcode":"2150",
    "sg:province":"NSW",
    "wof:name":"Bank Of China",
    "wof:placetype":"venue"
},
  "geometry": {"coordinates":[151.00227355999999,-33.8176116943],"type":"Point"}
}