{
  "type": "Feature",
  "properties": {
    "addr:full":"Lot 2, 5 Teran Cl Gateshead NSW 2290",
    "addr:housenumber":"5",
    "addr:postcode":"2290",
    "addr:street":"Teran Cl",
    "iso:country":"AU",
    "sg:address":"Lot 2, 5 Teran Cl",
    "sg:city":"Gateshead",
    "sg:classifiers":[
        {
            "category":"Retail",
            "subcategory":"Auto Repair",
            "type":"Services"
        }
    ],
    "sg:phone":"+61 2 4942 1402",
    "sg:postcode":"2290",
    "sg:province":"NSW",
    "sg:tags":[
        "repairer",
        "motor",
        "engineer"
    ],
    "wof:name":"Griff Smith Mechanical",
    "wof:placetype":"venue"
},
  "geometry": {"coordinates":[151.75765991200001,-32.912311554],"type":"Point"}
}