{
  "type": "Feature",
  "properties": {
    "addr:full":"PO Box 110 Kingston TAS 7050",
    "addr:postcode":"7050",
    "iso:country":"AU",
    "sg:address":"PO Box 110",
    "sg:city":"Kingston",
    "sg:classifiers":[
        {
            "category":"Professional",
            "subcategory":"Art Services",
            "type":"Services"
        }
    ],
    "sg:phone":"+61 405 086 522",
    "sg:postcode":"7050",
    "sg:province":"TAS",
    "sg:tags":[
        "product",
        "industrial",
        "designer"
    ],
    "wof:name":"Innovatas",
    "wof:placetype":"venue"
},
  "geometry": {"coordinates":[147.289917,-42.964359],"type":"Point"}
}