{
  "type": "Feature",
  "properties": {
    "addr:full":"Factory 1 413 Dorset Rd Bayswater VIC 3153",
    "addr:housenumber":"413",
    "addr:postcode":"3153",
    "addr:street":"Dorset Rd",
    "iso:country":"AU",
    "sg:address":"Factory 1 413 Dorset Rd",
    "sg:city":"Bayswater",
    "sg:classifiers":[
        {
            "category":"Manufacturing",
            "subcategory":"Metals",
            "type":"Manufacturing & Wholesale Goods"
        }
    ],
    "sg:phone":"+61 3 9720 1519",
    "sg:postcode":"3153",
    "sg:province":"VIC",
    "sg:tags":[
        "sheet",
        "worker"
    ],
    "wof:name":"A I J Services Pty Ltd",
    "wof:placetype":"venue"
},
  "geometry": {"coordinates":[145.2865448,-37.8422470093],"type":"Point"}
}