{
  "type": "Feature",
  "properties": {
    "addr:full":"16B Wanneroo Rd (Cnr Hepburn Ave) Madeley WA 6065",
    "addr:housenumber":"16b",
    "addr:postcode":"6065",
    "addr:street":"Wanneroo Rd Cnr Hepburn Ave",
    "iso:country":"AU",
    "sg:address":"16B Wanneroo Rd (Cnr Hepburn Ave)",
    "sg:city":"Madeley",
    "sg:classifiers":[
        {
            "category":"Health Services",
            "subcategory":"Dentist",
            "type":"Services"
        }
    ],
    "sg:phone":"+61 8 9409 3619",
    "sg:postcode":"6065",
    "sg:province":"WA",
    "sg:tags":[
        "dental",
        "emergency"
    ],
    "sg:website":"http://www.dentistsinperth.com.au",
    "wof:name":"Lifecare Dental",
    "wof:placetype":"venue"
},
  "geometry": {"coordinates":[115.821006775,-31.8193531036],"type":"Point"}
}