{
  "type": "Feature",
  "properties": {
    "addr:full":"6 Ontario Ave Panorama SA 5041",
    "addr:housenumber":"6",
    "addr:postcode":"5041",
    "addr:street":"Ontario Ave",
    "iso:country":"AU",
    "sg:address":"6 Ontario Ave",
    "sg:city":"Panorama",
    "sg:classifiers":[
        {
            "category":"Shopping",
            "subcategory":"Bicycles & Sporting Goods",
            "type":"Retail Goods"
        }
    ],
    "sg:phone":"+61 8 8271 1147",
    "sg:postcode":"5041",
    "sg:province":"SA",
    "sg:tags":[
        "dance",
        "accessory",
        "wear",
        "supply"
    ],
    "wof:name":"A. Strobel Custom Made Footwear",
    "wof:placetype":"venue"
},
  "geometry": {"coordinates":[138.59605400000001,-34.993233],"type":"Point"}
}