{
  "type": "Feature",
  "properties": {
    "addr:full":"1081 Waugh Rd Albury North NSW 2640",
    "addr:housenumber":"1081",
    "addr:postcode":"2640",
    "addr:street":"Waugh Rd",
    "iso:country":"AU",
    "sg:address":"1081 Waugh Rd",
    "sg:city":"Albury North",
    "sg:classifiers":[
        {
            "category":"Health Services",
            "subcategory":"Chiropractor",
            "type":"Services"
        }
    ],
    "sg:phone":"+61 2 6025 2447",
    "sg:postcode":"2640",
    "sg:province":"NSW",
    "wof:name":"North Albury Chiropractic Centre",
    "wof:placetype":"venue"
},
  "geometry": {"coordinates":[146.93095398,-36.0537757874],"type":"Point"}
}