{
  "type": "Feature",
  "properties": {
    "addr:full":"43b Appletree Rd Holmesville NSW 2286",
    "addr:housenumber":"43b",
    "addr:postcode":"2286",
    "addr:street":"Appletree Rd",
    "iso:country":"AU",
    "sg:address":"43b Appletree Rd",
    "sg:city":"Holmesville",
    "sg:classifiers":[
        {
            "category":"Personal",
            "subcategory":"Beauty Salon",
            "type":"Services"
        }
    ],
    "sg:phone":"+61 2 4955 2155",
    "sg:postcode":"2286",
    "sg:province":"NSW",
    "sg:tags":[
        "hairdresser"
    ],
    "wof:name":"Hair On Appletree",
    "wof:placetype":"venue"
},
  "geometry": {"coordinates":[151.581939697,-32.9155654907],"type":"Point"}
}