{
  "type": "Feature",
  "properties": {
    "iso:country":"AU",
    "sg:address":"1/ 44 Watson St",
    "sg:city":"Werribee",
    "sg:classifiers":[
        {
            "category":"Banks & Credit Unions",
            "subcategory":"Bank",
            "type":"Services"
        }
    ],
    "sg:phone":"+61 3 9974 0799",
    "sg:postcode":"3030",
    "sg:province":"VIC",
    "sg:tags":[
        "broker",
        "mortgage"
    ],
    "wof:name":"Smartline Home Loans",
    "wof:placetype":"venue"
},
  "geometry": {"coordinates":[144.706863,-37.864384],"type":"Point"}
}