{
  "type": "Feature",
  "properties": {
    "addr:full":"The Mews Suite 7, 11-13 Bundaroo St Bowral NSW 2576",
    "addr:housenumber":"11-13",
    "addr:postcode":"2576",
    "addr:street":"Bundaroo St",
    "iso:country":"AU",
    "sg:address":"The Mews Suite 7, 11-13 Bundaroo St",
    "sg:city":"Bowral",
    "sg:classifiers":[
        {
            "category":"Health Services",
            "subcategory":"Dentist",
            "type":"Services"
        }
    ],
    "sg:phone":"+61 2 4861 6265",
    "sg:postcode":"2576",
    "sg:province":"NSW",
    "wof:name":"Duncan Stephen L Orthodontist",
    "wof:placetype":"venue"
},
  "geometry": {"coordinates":[150.39749145499999,-34.4953613281],"type":"Point"}
}