{
  "type": "Feature",
  "properties": {
    "iso:country":"AU",
    "sg:address":"Shop 5",
    "sg:city":", Bibra Lake Shopping Centre, Parkway Bibra L",
    "sg:classifiers":[
        {
            "category":"Real Estate",
            "subcategory":"Real Estate Agent",
            "type":"Services"
        }
    ],
    "sg:phone":"+61 8 9321 7000",
    "sg:postcode":"6163",
    "sg:province":"WA",
    "wof:name":"Property Masters",
    "wof:placetype":"venue"
},
  "geometry": {"coordinates":[115.835747,-32.086563],"type":"Point"}
}