{
  "type": "Feature",
  "properties": {
    "iso:country":"AU",
    "sg:address":"227 South Beach Rd",
    "sg:city":"Ballina",
    "sg:classifiers":[
        {
            "category":"Building & Trades",
            "subcategory":"Landscaping Services",
            "type":"Services"
        }
    ],
    "sg:phone":"+61 2 6686 6978",
    "sg:postcode":"2478",
    "sg:province":"NSW",
    "sg:tags":[
        "designer",
        "landscape",
        "contractor"
    ],
    "wof:name":"Earthworks Landscaping",
    "wof:placetype":"venue"
},
  "geometry": {"coordinates":[153.59144592300001,-28.8672790527],"type":"Point"}
}