{
  "type": "Feature",
  "properties": {
    "addr:full":"Shop 429 Kawana Shopping Centre Nicklin Way Kawana Waters QLD 4575",
    "addr:housenumber":"429",
    "addr:postcode":"4575",
    "addr:street":"Kawana Shopping;Nicklin Way",
    "iso:country":"AU",
    "sg:address":"Shop 429 Kawana Shopping Centre Nicklin Way",
    "sg:city":"Kawana Waters",
    "sg:classifiers":[
        {
            "category":"Autos & Motor Vehicles",
            "subcategory":"Auto Supplies",
            "type":"Retail Goods"
        }
    ],
    "sg:phone":"+61 7 5444 6961",
    "sg:postcode":"4575",
    "sg:province":"QLD",
    "sg:tags":[
        "copper",
        "brass",
        "product"
    ],
    "wof:name":"Copperart",
    "wof:placetype":"venue"
},
  "geometry": {"coordinates":[153.12896699999999,-26.738571],"type":"Point"}
}