{
  "type": "Feature",
  "properties": {
    "iso:country":"AU",
    "sg:address":"79 Gt Ocean Rd",
    "sg:city":"Anglesea",
    "sg:classifiers":[
        {
            "category":"Real Estate",
            "subcategory":"Real Estate Agent",
            "type":"Services"
        }
    ],
    "sg:phone":"+61 3 5263 2477",
    "sg:postcode":"3230",
    "sg:province":"VIC",
    "wof:name":"Smyth Real Estate",
    "wof:placetype":"venue"
},
  "geometry": {"coordinates":[144.190308,-38.404747],"type":"Point"}
}