{
  "type": "Feature",
  "properties": {
    "addr:full":"277 Gounyan Rd Murrumbateman NSW 2582",
    "addr:housenumber":"277",
    "addr:postcode":"2582",
    "addr:street":"Gounyan Rd",
    "iso:country":"AU",
    "sg:address":"277 Gounyan Rd",
    "sg:city":"Murrumbateman",
    "sg:classifiers":[
        {
            "category":"Farming",
            "subcategory":"Livestock Farm",
            "type":"Manufacturing & Wholesale Goods"
        }
    ],
    "sg:phone":"+61 2 6227 0236",
    "sg:postcode":"2582",
    "sg:province":"NSW",
    "sg:tags":[
        "breeder",
        "horse",
        "stud"
    ],
    "wof:name":"Kyang Arabian Stud",
    "wof:placetype":"venue"
},
  "geometry": {"coordinates":[149.00097656200001,-34.9280128479],"type":"Point"}
}