{
  "type": "Feature",
  "properties": {
    "iso:country":"AU",
    "sg:address":"91 Great Alpine Rd",
    "sg:city":"Bright",
    "sg:classifiers":[
        {
            "category":"Travel",
            "subcategory":"Hotels & Motels",
            "type":"Entertainment"
        }
    ],
    "sg:phone":"+61 3 5755 1277",
    "sg:postcode":"3741",
    "sg:province":"VIC",
    "sg:tags":[
        "accommodation"
    ],
    "wof:name":"Star Hotel",
    "wof:placetype":"venue"
},
  "geometry": {"coordinates":[147.063583,-36.882011],"type":"Point"}
}