{
  "type": "Feature",
  "properties": {
    "addr:full":"120 Crozier Ave Newton SA 5074",
    "addr:housenumber":"120",
    "addr:postcode":"5074",
    "addr:street":"Crozier Ave",
    "iso:country":"AU",
    "sg:address":"120 Crozier Ave",
    "sg:city":"Newton",
    "sg:classifiers":[
        {
            "category":"Arena",
            "subcategory":"Sports Club",
            "type":"Entertainment"
        }
    ],
    "sg:phone":"+61 413 192 554",
    "sg:postcode":"5074",
    "sg:province":"SA",
    "sg:tags":[
        "defence",
        "supply",
        "self",
        "instruction",
        "martial art"
    ],
    "wof:name":"The Australian Karate Academy",
    "wof:placetype":"venue"
},
  "geometry": {"coordinates":[138.68708801299999,-34.884349823],"type":"Point"}
}