{
  "type": "Feature",
  "properties": {
    "iso:country":"AU",
    "sg:address":"7 Fortril Ave",
    "sg:city":"Bankstown",
    "sg:classifiers":[
        {
            "category":"Transit Center",
            "subcategory":"Freight",
            "type":"Transportation"
        }
    ],
    "sg:phone":"+61 2 9709 3500",
    "sg:postcode":"2200",
    "sg:province":"NSW",
    "sg:tags":[
        "forklift",
        "truck"
    ],
    "sg:website":"http://www.rentcorp.com.au",
    "wof:name":"Rentcorp Forklifts",
    "wof:placetype":"venue"
},
  "geometry": {"coordinates":[151.036575,-33.93346],"type":"Point"}
}