{
  "type": "Feature",
  "properties": {
    "addr:full":"182 Prairievale Rd Bossley Park NSW 2176",
    "addr:housenumber":"182",
    "addr:postcode":"2176",
    "addr:street":"Prairievale Rd",
    "iso:country":"AU",
    "sg:address":"182 Prairievale Rd",
    "sg:city":"Bossley Park",
    "sg:classifiers":[
        {
            "category":"Food & Beverages",
            "subcategory":"Fruits & Vegetables",
            "type":"Retail Goods"
        }
    ],
    "sg:phone":"+61 2 9823 3173",
    "sg:postcode":"2176",
    "sg:province":"NSW",
    "sg:tags":[
        "wholesale"
    ],
    "wof:name":"Wayne's Fresh Produce",
    "wof:placetype":"venue"
},
  "geometry": {"coordinates":[150.88284301799999,-33.8661651611],"type":"Point"}
}