{
  "type": "Feature",
  "properties": {
    "addr:full":"26 Oakdale Rd Gateshead NSW 2290",
    "addr:housenumber":"26",
    "addr:postcode":"2290",
    "addr:street":"Oakdale Rd",
    "iso:country":"AU",
    "sg:address":"26 Oakdale Rd",
    "sg:city":"Gateshead",
    "sg:classifiers":[
        {
            "category":"Sports & Exercise",
            "subcategory":"Gym",
            "type":"Entertainment"
        }
    ],
    "sg:phone":"+61 2 4943 5855",
    "sg:postcode":"2290",
    "sg:province":"NSW",
    "sg:tags":[
        "pilate",
        "method"
    ],
    "wof:name":"Fitness Revolution",
    "wof:placetype":"venue"
},
  "geometry": {"coordinates":[151.69664001500001,-32.9895248413],"type":"Point"}
}