{
  "type": "Feature",
  "properties": {
    "iso:country":"AU",
    "sg:address":"Suite 3 Level 1 Lot 4 Villawood Pl",
    "sg:city":"Villawood",
    "sg:classifiers":[
        {
            "category":"Health Services",
            "subcategory":"Dentist",
            "type":"Services"
        }
    ],
    "sg:phone":"+61 2 9723 0955",
    "sg:postcode":"2163",
    "sg:province":"NSW",
    "wof:name":"Tran Victor",
    "wof:placetype":"venue"
},
  "geometry": {"coordinates":[150.97608947800001,-33.8828468323],"type":"Point"}
}