{
  "type": "Feature",
  "properties": {
    "addr:full":"Unit 12 88 Briggs St Carlisle WA 6101",
    "addr:housenumber":"88",
    "addr:postcode":"6101",
    "addr:street":"Briggs St",
    "iso:country":"AU",
    "sg:address":"Unit 12 88 Briggs St",
    "sg:city":"Carlisle",
    "sg:classifiers":[
        {
            "category":"Education",
            "subcategory":"Music School",
            "type":"Public Place"
        }
    ],
    "sg:phone":"+61 8 9362 2271",
    "sg:postcode":"6101",
    "sg:province":"WA",
    "sg:tags":[
        "choir",
        "bands",
        "orchestra"
    ],
    "wof:name":"Town of Vic Park Brass",
    "wof:placetype":"venue"
},
  "geometry": {"coordinates":[115.926696777,-31.9841537476],"type":"Point"}
}