{
  "type": "Feature",
  "properties": {
    "addr:full":"Fulton Maffra Rd Myrtlebank VIC 3851",
    "addr:postcode":"3851",
    "addr:street":"Maffra Rd",
    "iso:country":"AU",
    "sg:address":"Fulton Maffra Rd",
    "sg:city":"Myrtlebank",
    "sg:classifiers":[
        {
            "category":"Farming",
            "subcategory":"Farm & Veterinary Services",
            "type":"Manufacturing & Wholesale Goods"
        }
    ],
    "sg:phone":"+61 428 514 906",
    "sg:postcode":"3851",
    "sg:province":"VIC",
    "sg:tags":[
        "contracting"
    ],
    "wof:name":"Morrison T J & L",
    "wof:placetype":"venue"
},
  "geometry": {"coordinates":[147.216033936,-38.3536987305],"type":"Point"}
}