{
  "type": "Feature",
  "properties": {
    "addr:full":"175 Peel St Tamworth NSW 2340",
    "addr:housenumber":"175",
    "addr:postcode":"2340",
    "addr:street":"Peel St",
    "iso:country":"AU",
    "sg:address":"175 Peel St",
    "sg:city":"Tamworth",
    "sg:classifiers":[
        {
            "category":"Shopping",
            "subcategory":"Antiques",
            "type":"Retail Goods"
        }
    ],
    "sg:phone":"+61 2 6766 7707",
    "sg:postcode":"2340",
    "sg:province":"NSW",
    "wof:name":"Munros Mill Antique Centre",
    "wof:placetype":"venue"
},
  "geometry": {"coordinates":[150.927490234,-31.0878791809],"type":"Point"}
}