{
  "type": "Feature",
  "properties": {
    "iso:country":"AU",
    "sg:address":"16 Grosvenor St",
    "sg:city":"Abbotsford",
    "sg:classifiers":[
        {
            "category":"Autos & Motor Vehicles",
            "subcategory":"Auto Supplies",
            "type":"Retail Goods"
        }
    ],
    "sg:phone":"+61 3 9427 0611",
    "sg:postcode":"3067",
    "sg:province":"VIC",
    "sg:tags":[
        "wheel",
        "automotive",
        "rim"
    ],
    "wof:name":"Designer Wheels & Accessories",
    "wof:placetype":"venue"
},
  "geometry": {"coordinates":[145.00663757300001,-37.8100547791],"type":"Point"}
}