{
  "type": "Feature",
  "properties": {
    "iso:country":"AU",
    "sg:address":"21 Macmillan St",
    "sg:city":"Ayr",
    "sg:classifiers":[
        {
            "category":"Real Estate",
            "subcategory":"Real Estate Agent",
            "type":"Services"
        }
    ],
    "sg:phone":"+61 7 4783 1944",
    "sg:postcode":"4807",
    "sg:province":"QLD",
    "wof:name":"Burdekin Real Estate",
    "wof:placetype":"venue"
},
  "geometry": {"coordinates":[147.40591430699999,-19.5772151947],"type":"Point"}
}