{
  "type": "Feature",
  "properties": {
    "addr:full":"9 River St Kendall NSW 2439",
    "addr:housenumber":"9",
    "addr:postcode":"2439",
    "addr:street":"River St",
    "iso:country":"AU",
    "sg:address":"9 River St",
    "sg:city":"Kendall",
    "sg:classifiers":[
        {
            "category":"Home & Garden",
            "subcategory":"Carpets & Floor Coverings",
            "type":"Retail Goods"
        }
    ],
    "sg:phone":"+61 2 6559 4420",
    "sg:postcode":"2439",
    "sg:province":"NSW",
    "sg:tags":[
        "tile",
        "wall",
        "layer"
    ],
    "wof:name":"Mostyn D L",
    "wof:placetype":"venue"
},
  "geometry": {"coordinates":[152.707932,-31.633114],"type":"Point"}
}