{
  "type": "Feature",
  "properties": {
    "addr:full":"57/ 30 MacPherson St Warriewood NSW 2102",
    "addr:housenumber":"57 / 30",
    "addr:postcode":"2102",
    "addr:street":"Macpherson St",
    "iso:country":"AU",
    "sg:address":"57/ 30 MacPherson St",
    "sg:city":"Warriewood",
    "sg:classifiers":[
        {
            "category":"Shopping",
            "subcategory":"Beauty & Cosmetics",
            "type":"Retail Goods"
        }
    ],
    "sg:phone":"+61 2 9999 1752",
    "sg:postcode":"2102",
    "sg:province":"NSW",
    "wof:name":"Grace Cosmetics",
    "wof:placetype":"venue"
},
  "geometry": {"coordinates":[151.298248,-33.689705],"type":"Point"}
}