{
  "type": "Feature",
  "properties": {
    "addr:full":"436 Springvale Rd Glen Waverley VIC 3150",
    "addr:housenumber":"436",
    "addr:postcode":"3150",
    "addr:street":"Springvale Rd",
    "iso:country":"AU",
    "sg:address":"436 Springvale Rd",
    "sg:city":"Glen Waverley",
    "sg:classifiers":[
        {
            "category":"Health Services",
            "subcategory":"Dentist",
            "type":"Services"
        }
    ],
    "sg:phone":"+61 3 9562 0323",
    "sg:postcode":"3150",
    "sg:province":"VIC",
    "wof:name":"Shi Lilian Dr",
    "wof:placetype":"venue"
},
  "geometry": {"coordinates":[145.163665772,-37.8935012817],"type":"Point"}
}