{
  "type": "Feature",
  "properties": {
    "iso:country":"AU",
    "sg:address":"1/ 17 Woids Ave",
    "sg:city":"Hurstville",
    "sg:classifiers":[
        {
            "category":"Travel",
            "subcategory":"Travel Agent",
            "type":"Entertainment"
        }
    ],
    "sg:phone":"+61 2 9580 7139",
    "sg:postcode":"2220",
    "sg:province":"NSW",
    "sg:tags":[
        "consultant"
    ],
    "wof:name":"New Millennium Travel",
    "wof:placetype":"venue"
},
  "geometry": {"coordinates":[151.109832764,-33.9696121216],"type":"Point"}
}