{
  "type": "Feature",
  "properties": {
    "iso:country":"AU",
    "sg:address":"721 Albany Creek Rd",
    "sg:city":"Albany Creek",
    "sg:classifiers":[
        {
            "category":"Health Services",
            "subcategory":"Doctor",
            "type":"Services"
        }
    ],
    "sg:phone":"+61 7 3264 2211",
    "sg:postcode":"4035",
    "sg:province":"QLD",
    "sg:tags":[
        "medical",
        "practitioner"
    ],
    "wof:name":"Prasad Krishna",
    "wof:placetype":"venue"
},
  "geometry": {"coordinates":[152.965836,-27.34494],"type":"Point"}
}