{
  "type": "Feature",
  "properties": {
    "addr:full":"32 Albert St Warrnambool VIC 3280",
    "addr:housenumber":"32",
    "addr:postcode":"3280",
    "addr:street":"Albert St",
    "iso:country":"AU",
    "sg:address":"32 Albert St",
    "sg:city":"Warrnambool",
    "sg:classifiers":[
        {
            "category":"Retail",
            "subcategory":"Auto Repair",
            "type":"Services"
        }
    ],
    "sg:phone":"+61 3 5561 2577",
    "sg:postcode":"3280",
    "sg:province":"VIC",
    "sg:tags":[
        "beater",
        "painter",
        "panel"
    ],
    "wof:name":"Baudinette's Max Body Repairs",
    "wof:placetype":"venue"
},
  "geometry": {"coordinates":[142.45976257300001,-38.3709907532],"type":"Point"}
}