{
  "type": "Feature",
  "properties": {
    "addr:full":"939 Port Rd Cheltenham SA 5014",
    "addr:housenumber":"939",
    "addr:postcode":"5014",
    "addr:street":"Port Rd",
    "iso:country":"AU",
    "sg:address":"939 Port Rd",
    "sg:city":"Cheltenham",
    "sg:classifiers":[
        {
            "category":"Building & Trades",
            "subcategory":"Equipment Rental",
            "type":"Services"
        }
    ],
    "sg:phone":"+61 8 8445 8726",
    "sg:postcode":"5014",
    "sg:province":"SA",
    "sg:tags":[
        "saw"
    ],
    "wof:name":"A.A. Saw Works",
    "wof:placetype":"venue"
},
  "geometry": {"coordinates":[138.522979736,-34.8722076416],"type":"Point"}
}