{
  "type": "Feature",
  "properties": {
    "addr:full":"Unit 1/ 11 Lydiard St Ballarat Central VIC 3350",
    "addr:housenumber":"11",
    "addr:postcode":"3350",
    "addr:street":"Lydiard St",
    "iso:country":"AU",
    "sg:address":"Unit 1/ 11 Lydiard St",
    "sg:city":"Ballarat Central",
    "sg:classifiers":[
        {
            "category":"Banks & Credit Unions",
            "subcategory":"Investment Brokerage",
            "type":"Services"
        }
    ],
    "sg:phone":"+61 1300 852 669",
    "sg:postcode":"3350",
    "sg:province":"VIC",
    "sg:tags":[
        "finance",
        "broker"
    ],
    "wof:name":"Refer Now Pty Ltd",
    "wof:placetype":"venue"
},
  "geometry": {"coordinates":[143.85781900000001,-37.5625],"type":"Point"}
}