{
  "type": "Feature",
  "properties": {
    "addr:full":"PO Box 4 Newport VIC 3015",
    "addr:postcode":"3015",
    "iso:country":"AU",
    "sg:address":"PO Box 4",
    "sg:city":"Newport",
    "sg:classifiers":[
        {
            "category":"Communications",
            "subcategory":"News Services",
            "type":"Services"
        }
    ],
    "sg:phone":"+61 3 9391 2949",
    "sg:postcode":"3015",
    "sg:province":"VIC",
    "sg:tags":[
        "information",
        "tourist",
        "attractions"
    ],
    "wof:name":"Around And About Travel & Planning",
    "wof:placetype":"venue"
},
  "geometry": {"coordinates":[144.882247925,-37.8427085876],"type":"Point"}
}