{
  "type": "Feature",
  "properties": {
    "addr:full":"23 Parkhurst Drv Knoxfield VIC 3180",
    "addr:housenumber":"23",
    "addr:postcode":"3180",
    "addr:street":"Parkhurst Drv",
    "iso:country":"AU",
    "sg:address":"23 Parkhurst Drv",
    "sg:city":"Knoxfield",
    "sg:classifiers":[
        {
            "category":"Professional",
            "subcategory":"Business Services",
            "type":"Services"
        }
    ],
    "sg:phone":"+61 3 9887 1255",
    "sg:postcode":"3180",
    "sg:province":"VIC",
    "sg:tags":[
        "exporter"
    ],
    "wof:name":"Australian Export Consortia Pty Ltd",
    "wof:placetype":"venue"
},
  "geometry": {"coordinates":[145.25299072300001,-37.8722229004],"type":"Point"}
}