{
  "type": "Feature",
  "properties": {
    "addr:full":"93 Renwick St Alexandria NSW 2015",
    "addr:housenumber":"93",
    "addr:postcode":"2015",
    "addr:street":"Renwick St",
    "iso:country":"AU",
    "sg:address":"93 Renwick St",
    "sg:city":"Alexandria",
    "sg:classifiers":[
        {
            "category":"Building & Trades",
            "subcategory":"Plumbing",
            "type":"Services"
        }
    ],
    "sg:phone":"+61 2 9519 3440",
    "sg:postcode":"2015",
    "sg:province":"NSW",
    "sg:tags":[
        "plumber",
        "gasfitters"
    ],
    "wof:name":"Alexandria Plumbing",
    "wof:placetype":"venue"
},
  "geometry": {"coordinates":[151.19085693400001,-33.899559021],"type":"Point"}
}