{
  "type": "Feature",
  "properties": {
    "addr:full":"47 Harman St St Albans VIC 3021",
    "addr:housenumber":"47",
    "addr:postcode":"3021",
    "addr:street":"Harman St",
    "iso:country":"AU",
    "sg:address":"47 Harman St",
    "sg:city":"St Albans",
    "sg:classifiers":[
        {
            "category":"Wholesale",
            "subcategory":"Apparel",
            "type":"Manufacturing & Wholesale Goods"
        }
    ],
    "sg:phone":"+61 3 8307 3927",
    "sg:postcode":"3021",
    "sg:province":"VIC",
    "sg:tags":[
        "wholesaler",
        "mfrs",
        "dress"
    ],
    "wof:name":"Jamey Wholesale",
    "wof:placetype":"venue"
},
  "geometry": {"coordinates":[144.800217,-37.744259],"type":"Point"}
}