{
  "type": "Feature",
  "properties": {
    "addr:full":"Unit 3, 10 Warton Rd Thornlie WA 6108",
    "addr:housenumber":"10",
    "addr:postcode":"6108",
    "addr:street":"Warton Rd",
    "iso:country":"AU",
    "sg:address":"Unit 3, 10 Warton Rd",
    "sg:city":"Thornlie",
    "sg:classifiers":[
        {
            "category":"Restaurant",
            "type":"Food & Drink"
        }
    ],
    "sg:phone":"+61 8 9493 2565",
    "sg:postcode":"6108",
    "sg:province":"WA",
    "sg:tags":[
        "pizza"
    ],
    "wof:name":"Domino's Pizza",
    "wof:placetype":"venue"
},
  "geometry": {"coordinates":[115.970153809,-32.0676345825],"type":"Point"}
}