{
  "type": "Feature",
  "properties": {
    "iso:country":"AU",
    "sg:address":"21 West Fyans St",
    "sg:city":"Newtown",
    "sg:classifiers":[
        {
            "category":"Home & Garden",
            "subcategory":"Garden Supply",
            "type":"Retail Goods"
        }
    ],
    "sg:phone":"+61 3 5221 1180",
    "sg:postcode":"3220",
    "sg:province":"VIC",
    "sg:tags":[
        "statuary",
        "fountains",
        "sundial"
    ],
    "wof:name":"The Complete Garden Geelong",
    "wof:placetype":"venue"
},
  "geometry": {"coordinates":[144.348175,-38.160095],"type":"Point"}
}