{
  "type": "Feature",
  "properties": {
    "addr:full":"New England Hwy Willow Tree NSW 2339",
    "addr:postcode":"2339",
    "addr:street":"England Hwy",
    "iso:country":"AU",
    "sg:address":"New England Hwy",
    "sg:city":"Willow Tree",
    "sg:classifiers":[
        {
            "category":"Autos & Motor Vehicles",
            "subcategory":"Fuel & Gas Station",
            "type":"Retail Goods"
        }
    ],
    "sg:phone":"+61 2 6747 1239",
    "sg:postcode":"2339",
    "sg:province":"NSW",
    "wof:name":"BP Australia Limited",
    "wof:placetype":"venue"
},
  "geometry": {"coordinates":[150.72624206500001,-31.648141861],"type":"Point"}
}