{
  "type": "Feature",
  "properties": {
    "iso:country":"AU",
    "sg:address":"Shop 3/ 13 Cadell St",
    "sg:city":"Goolwa",
    "sg:classifiers":[
        {
            "category":"Banks & Credit Unions",
            "subcategory":"Bank",
            "type":"Services"
        }
    ],
    "sg:phone":"+61 8 8555 3838",
    "sg:postcode":"5214",
    "sg:province":"SA",
    "sg:tags":[
        "society"
    ],
    "wof:name":"Encounter Coast Agency",
    "wof:placetype":"venue"
},
  "geometry": {"coordinates":[138.780792236,-35.4996452332],"type":"Point"}
}