{
  "type": "Feature",
  "properties": {
    "addr:full":"38 Alexandra St Bundaberg QLD 4670",
    "addr:housenumber":"38",
    "addr:postcode":"4670",
    "addr:street":"Alexandra St",
    "iso:country":"AU",
    "sg:address":"38 Alexandra St",
    "sg:city":"Bundaberg",
    "sg:classifiers":[
        {
            "category":"Professional",
            "type":"Services"
        }
    ],
    "sg:phone":"+61 7 4152 2355",
    "sg:postcode":"4670",
    "sg:province":"QLD",
    "sg:tags":[
        "transport"
    ],
    "wof:name":"Degunst Transport",
    "wof:placetype":"venue"
},
  "geometry": {"coordinates":[152.37017822300001,-24.8537635803],"type":"Point"}
}