{
  "type": "Feature",
  "properties": {
    "iso:country":"AU",
    "sg:address":"432 Waverley Rd",
    "sg:city":"Malvern East",
    "sg:classifiers":[
        {
            "category":"Sports & Exercise",
            "subcategory":"Gym",
            "type":"Entertainment"
        }
    ],
    "sg:phone":"+61 3 9571 6977",
    "sg:postcode":"3145",
    "sg:province":"VIC",
    "sg:tags":[
        "pilate",
        "method"
    ],
    "wof:name":"Pilates Based Physicalmind Studio",
    "wof:placetype":"venue"
},
  "geometry": {"coordinates":[145.066574097,-37.8782691956],"type":"Point"}
}