{
  "type": "Feature",
  "properties": {
    "iso:country":"AU",
    "sg:address":"Shop 3, 104 Meadow St",
    "sg:city":"Tarrawanna",
    "sg:classifiers":[
        {
            "category":"Deli",
            "type":"Food & Drink"
        }
    ],
    "sg:phone":"+61 2 4284 9832",
    "sg:postcode":"2518",
    "sg:province":"NSW",
    "sg:tags":[
        "delicatessen"
    ],
    "wof:name":"Tarrawanna Village Deli",
    "wof:placetype":"venue"
},
  "geometry": {"coordinates":[150.887543,-34.382324],"type":"Point"}
}