{
  "type": "Feature",
  "properties": {
    "addr:full":"638 Sandy Bay Rd Sandy Bay TAS 7005",
    "addr:housenumber":"638",
    "addr:postcode":"7005",
    "addr:street":"Sandy Bay Rd",
    "iso:country":"AU",
    "sg:address":"638 Sandy Bay Rd",
    "sg:city":"Sandy Bay",
    "sg:classifiers":[
        {
            "category":"Health Services",
            "subcategory":"Health Practitioner",
            "type":"Services"
        }
    ],
    "sg:phone":"+61 3 6225 1306",
    "sg:postcode":"7005",
    "sg:province":"TAS",
    "sg:tags":[
        "naturopath"
    ],
    "sg:website":"http://www.baysidepharmacy.com.au",
    "wof:name":"Bayside Amcal Pharmacy",
    "wof:placetype":"venue"
},
  "geometry": {"coordinates":[147.35508727999999,-42.9129867554],"type":"Point"}
}