{
  "type": "Feature",
  "properties": {
    "iso:country":"AU",
    "sg:address":"1 Snowy River Ave",
    "sg:city":"Jindabyne",
    "sg:classifiers":[
        {
            "category":"Health Services",
            "subcategory":"Dentist",
            "type":"Services"
        }
    ],
    "sg:phone":"+61 2 6456 2096",
    "sg:postcode":"2627",
    "sg:province":"NSW",
    "wof:name":"Slater A W & Associates",
    "wof:placetype":"venue"
},
  "geometry": {"coordinates":[148.619750977,-36.4160079956],"type":"Point"}
}