{
  "type": "Feature",
  "properties": {
    "addr:full":"6/ 585 Wyndham St Shepparton VIC 3630",
    "addr:housenumber":"/ 585",
    "addr:postcode":"3630",
    "addr:street":"Wyndham St",
    "iso:country":"AU",
    "sg:address":"6/ 585 Wyndham St",
    "sg:city":"Shepparton",
    "sg:classifiers":[
        {
            "category":"Professional",
            "subcategory":"Accounting & Tax Preparation",
            "type":"Services"
        }
    ],
    "sg:phone":"+61 3 5822 4226",
    "sg:postcode":"3630",
    "sg:province":"VIC",
    "sg:tags":[
        "consultant",
        "taxation"
    ],
    "wof:name":"Sherbourne Accounting Partners",
    "wof:placetype":"venue"
},
  "geometry": {"coordinates":[145.39643859899999,-36.3962173462],"type":"Point"}
}