{
  "type": "Feature",
  "properties": {
    "addr:full":"12 Tierney Pl Tweed Heads South NSW 2486",
    "addr:housenumber":"12",
    "addr:postcode":"2486",
    "addr:street":"Tierney Pl",
    "iso:country":"AU",
    "sg:address":"12 Tierney Pl",
    "sg:city":"Tweed Heads South",
    "sg:classifiers":[
        {
            "category":"Health Services",
            "subcategory":"Doctor",
            "type":"Services"
        }
    ],
    "sg:phone":"+61 7 5524 3708",
    "sg:postcode":"2486",
    "sg:province":"NSW",
    "sg:tags":[
        "occupational",
        "safety"
    ],
    "wof:name":"Job Safety Australia",
    "wof:placetype":"venue"
},
  "geometry": {"coordinates":[153.53831481899999,-28.202665329],"type":"Point"}
}