{
  "type": "Feature",
  "properties": {
    "addr:full":"22 Embleton Ave Embleton WA 6062",
    "addr:housenumber":"22",
    "addr:postcode":"6062",
    "addr:street":"Embleton Ave",
    "iso:country":"AU",
    "sg:address":"22 Embleton Ave",
    "sg:city":"Embleton",
    "sg:classifiers":[
        {
            "category":"Autos & Motor Vehicles",
            "subcategory":"Auto Supplies",
            "type":"Retail Goods"
        }
    ],
    "sg:phone":"+61 8 9371 9988",
    "sg:postcode":"6062",
    "sg:province":"WA",
    "sg:tags":[
        "tyre"
    ],
    "sg:website":"http://www.bayswatertyres.com.au",
    "wof:name":"Bayswater Tyres & Brakes",
    "wof:placetype":"venue"
},
  "geometry": {"coordinates":[115.916786194,-31.90275383],"type":"Point"}
}