{
  "type": "Feature",
  "properties": {
    "addr:full":"Shop 2/ 3 Oaka La Gladstone QLD 4680",
    "addr:housenumber":"shop 2 / 3",
    "addr:postcode":"4680",
    "addr:street":"Oaka La",
    "iso:country":"AU",
    "sg:address":"Shop 2/ 3 Oaka La",
    "sg:city":"Gladstone",
    "sg:classifiers":[
        {
            "category":"Personal",
            "subcategory":"Beauty Salon",
            "type":"Services"
        }
    ],
    "sg:phone":"+61 7 4972 0733",
    "sg:postcode":"4680",
    "sg:province":"QLD",
    "sg:tags":[
        "hairdresser"
    ],
    "wof:name":"Hair Culture By Raylene",
    "wof:placetype":"venue"
},
  "geometry": {"coordinates":[151.263137817,-23.8526744843],"type":"Point"}
}