{
  "type": "Feature",
  "properties": {
    "iso:country":"AU",
    "sg:address":"32 Victor Ave",
    "sg:city":"Forster",
    "sg:classifiers":[
        {
            "category":"Building & Trades",
            "subcategory":"Construction",
            "type":"Services"
        }
    ],
    "sg:phone":"+61 2 6554 5058",
    "sg:postcode":"2428",
    "sg:province":"NSW",
    "sg:tags":[
        "earth",
        "excavating",
        "moving",
        "contractor"
    ],
    "wof:name":"Bestwick R C & M",
    "wof:placetype":"venue"
},
  "geometry": {"coordinates":[152.522751,-32.215099],"type":"Point"}
}