{
  "type": "Feature",
  "properties": {
    "addr:full":"14 Tandem Ave Warana QLD 4575",
    "addr:housenumber":"14",
    "addr:postcode":"4575",
    "addr:street":"Tandem Ave",
    "iso:country":"AU",
    "sg:address":"14 Tandem Ave",
    "sg:city":"Warana",
    "sg:classifiers":[
        {
            "category":"Building & Trades",
            "subcategory":"Construction",
            "type":"Services"
        }
    ],
    "sg:phone":"+61 7 5493 2277",
    "sg:postcode":"4575",
    "sg:province":"QLD",
    "sg:tags":[
        "fencing",
        "contractor"
    ],
    "wof:name":"Premier Fencing",
    "wof:placetype":"venue"
},
  "geometry": {"coordinates":[153.12548799999999,-26.728252],"type":"Point"}
}