{
  "type": "Feature",
  "properties": {
    "iso:country":"AU",
    "sg:address":"14 Tandem Ave",
    "sg:city":"Warana",
    "sg:classifiers":[
        {
            "category":"Building & Trades",
            "subcategory":"Construction",
            "type":"Services"
        }
    ],
    "sg:phone":"+61 7 5493 2277",
    "sg:postcode":"4575",
    "sg:province":"QLD",
    "sg:tags":[
        "fencing",
        "contractor"
    ],
    "wof:name":"Premier Fencing",
    "wof:placetype":"venue"
},
  "geometry": {"coordinates":[153.125488,-26.728252],"type":"Point"}
}