{
  "type": "Feature",
  "properties": {
    "addr:full":"195 Albany Hwy Mt Barker WA 6324",
    "addr:housenumber":"195",
    "addr:postcode":"6324",
    "addr:street":"Albany Hwy Mt",
    "iso:country":"AU",
    "sg:address":"195 Albany Hwy",
    "sg:city":"Mt Barker",
    "sg:classifiers":[
        {
            "category":"Farming",
            "subcategory":"Vineyard",
            "type":"Manufacturing & Wholesale Goods"
        }
    ],
    "sg:phone":"+61 8 9851 2464",
    "sg:postcode":"6324",
    "sg:province":"WA",
    "sg:tags":[
        "winery"
    ],
    "wof:name":"Fox River Wines Company",
    "wof:placetype":"venue"
},
  "geometry": {"coordinates":[117.663337708,-34.6254119873],"type":"Point"}
}