{
  "type": "Feature",
  "properties": {
    "iso:country":"AU",
    "sg:address":"Margaret St",
    "sg:city":"Mt Gambier",
    "sg:classifiers":[
        {
            "category":"Wholesale",
            "subcategory":"Farm Supplies",
            "type":"Manufacturing & Wholesale Goods"
        }
    ],
    "sg:phone":"+61 8 8725 4028",
    "sg:postcode":"5290",
    "sg:province":"SA",
    "sg:tags":[
        "feed",
        "supplement",
        "stock"
    ],
    "wof:name":"Ridley Agriproducts Pty Ltd",
    "wof:placetype":"venue"
},
  "geometry": {"coordinates":[140.776382,-37.832058],"type":"Point"}
}