{
  "type": "Feature",
  "properties": {
    "addr:full":"35 Keoghs Rd Kangaroo Valley NSW 2577",
    "addr:housenumber":"35",
    "addr:postcode":"2577",
    "addr:street":"Keoghs Rd",
    "iso:country":"AU",
    "sg:address":"35 Keoghs Rd",
    "sg:city":"Kangaroo Valley",
    "sg:classifiers":[
        {
            "category":"Professional",
            "subcategory":"Detective & Security Services",
            "type":"Services"
        }
    ],
    "sg:phone":"+61 428 651 659",
    "sg:postcode":"2577",
    "sg:province":"NSW",
    "sg:tags":[
        "consultant",
        "system"
    ],
    "wof:name":"Kangaroo Valley Security",
    "wof:placetype":"venue"
},
  "geometry": {"coordinates":[150.57432556099999,-34.7565574646],"type":"Point"}
}