{
  "type": "Feature",
  "properties": {
    "addr:full":"4 Sliedell Crt Yinnar VIC 3869",
    "addr:housenumber":"4",
    "addr:postcode":"3869",
    "addr:street":"Sliedell Crt",
    "iso:country":"AU",
    "sg:address":"4 Sliedell Crt",
    "sg:city":"Yinnar",
    "sg:classifiers":[
        {
            "category":"Building & Trades",
            "subcategory":"Plumbing",
            "type":"Services"
        }
    ],
    "sg:phone":"+61 408 631 582",
    "sg:postcode":"3869",
    "sg:province":"VIC",
    "sg:tags":[
        "plumber",
        "gasfitters"
    ],
    "wof:name":"Darrell Martin Plumbing",
    "wof:placetype":"venue"
},
  "geometry": {"coordinates":[146.330535889,-38.3180580139],"type":"Point"}
}