{
  "type": "Feature",
  "properties": {
    "iso:country":"AU",
    "sg:address":"80 Hamilton Ave",
    "sg:city":"Earlwood",
    "sg:classifiers":[
        {
            "category":"Building & Trades",
            "subcategory":"Plumbing",
            "type":"Services"
        }
    ],
    "sg:phone":"+61 417 433 417",
    "sg:postcode":"2206",
    "sg:province":"NSW",
    "sg:tags":[
        "plumber",
        "gasfitters"
    ],
    "wof:name":"Dynamite Plumbing",
    "wof:placetype":"venue"
},
  "geometry": {"coordinates":[151.122864,-33.923824],"type":"Point"}
}