{
  "type": "Feature",
  "properties": {
    "iso:country":"AU",
    "sg:address":"245 Plenty River Drv",
    "sg:city":"Greensborough",
    "sg:classifiers":[
        {
            "category":"Health Services",
            "subcategory":"Health Practitioner",
            "type":"Services"
        }
    ],
    "sg:phone":"+61 3 9432 0710",
    "sg:postcode":"3088",
    "sg:province":"VIC",
    "sg:tags":[
        "naturopath"
    ],
    "wof:name":"Wholistic Healing Clinic",
    "wof:placetype":"venue"
},
  "geometry": {"coordinates":[145.11309814399999,-37.6826820374],"type":"Point"}
}