{
  "type": "Feature",
  "properties": {
    "addr:full":"Murray Rd Dandenong North VIC 3175",
    "addr:postcode":"3175",
    "addr:street":"Murray Rd",
    "iso:country":"AU",
    "sg:address":"Murray Rd",
    "sg:city":"Dandenong North",
    "sg:classifiers":[
        {
            "category":"Education",
            "subcategory":"School",
            "type":"Public Place"
        }
    ],
    "sg:phone":"+61 3 9795 3744",
    "sg:postcode":"3175",
    "sg:province":"VIC",
    "sg:tags":[
        "state",
        "except",
        "nsw"
    ],
    "wof:name":"Rosewood Downs Primary",
    "wof:placetype":"venue"
},
  "geometry": {"coordinates":[145.21612548799999,-37.9445343018],"type":"Point"}
}