{
  "type": "Feature",
  "properties": {
    "addr:full":"742 Parramatta Rd Leichhardt NSW 2040",
    "addr:housenumber":"742",
    "addr:postcode":"2040",
    "addr:street":"Parramatta Rd",
    "iso:country":"AU",
    "sg:address":"742 Parramatta Rd",
    "sg:city":"Leichhardt",
    "sg:classifiers":[
        {
            "category":"Autos & Motor Vehicles",
            "subcategory":"Auto Supplies",
            "type":"Retail Goods"
        }
    ],
    "sg:phone":"+61 2 9550 9777",
    "sg:postcode":"2040",
    "sg:province":"NSW",
    "sg:tags":[
        "tyre"
    ],
    "sg:website":"http://www.ontracktyreauto.com.au",
    "wof:name":"On Track Tyre & Auto",
    "wof:placetype":"venue"
},
  "geometry": {"coordinates":[151.14927700000001,-33.889893],"type":"Point"}
}