{
  "type": "Feature",
  "properties": {
    "addr:full":"Shop 10/ 30-32 Charles St Parramatta NSW 2150",
    "addr:housenumber":"shop 10 / 30-32",
    "addr:postcode":"2150",
    "addr:street":"Charles St",
    "iso:country":"AU",
    "sg:address":"Shop 10/ 30-32 Charles St",
    "sg:city":"Parramatta",
    "sg:classifiers":[
        {
            "category":"Cafe",
            "type":"Food & Drink"
        }
    ],
    "sg:phone":"+61 2 9635 0677",
    "sg:postcode":"2150",
    "sg:province":"NSW",
    "wof:name":"Rouge Coffee Bar",
    "wof:placetype":"venue"
},
  "geometry": {"coordinates":[151.01150512699999,-33.842338562],"type":"Point"}
}