{
  "type": "Feature",
  "properties": {
    "iso:country":"AU",
    "sg:address":"7 Laconia Crt",
    "sg:city":"Riverton",
    "sg:classifiers":[
        {
            "category":"Personal",
            "subcategory":"Skin Care",
            "type":"Services"
        }
    ],
    "sg:phone":"+61 412 389 119",
    "sg:postcode":"6148",
    "sg:province":"WA",
    "sg:tags":[
        "hair",
        "product"
    ],
    "wof:name":"Hebbards Fine Products",
    "wof:placetype":"venue"
},
  "geometry": {"coordinates":[115.891586,-32.031815],"type":"Point"}
}