{
  "type": "Feature",
  "properties": {
    "addr:full":"4 Lucania St Currumbin Waters QLD 4223",
    "addr:housenumber":"4",
    "addr:postcode":"4223",
    "addr:street":"Lucania St",
    "iso:country":"AU",
    "sg:address":"4 Lucania St",
    "sg:city":"Currumbin Waters",
    "sg:classifiers":[
        {
            "category":"Real Estate",
            "subcategory":"Architect",
            "type":"Services"
        }
    ],
    "sg:phone":"+61 7 5598 7057",
    "sg:postcode":"4223",
    "sg:province":"QLD",
    "sg:tags":[
        "house",
        "damp",
        "waterproofing",
        "repair"
    ],
    "wof:name":"Aquaseal",
    "wof:placetype":"venue"
},
  "geometry": {"coordinates":[153.457519531,-28.1398887634],"type":"Point"}
}