{
  "type": "Feature",
  "properties": {
    "addr:full":"403 Bay St Port Melbourne VIC 3207",
    "addr:housenumber":"403",
    "addr:postcode":"3207",
    "addr:street":"Bay St",
    "iso:country":"AU",
    "sg:address":"403 Bay St",
    "sg:city":"Port Melbourne",
    "sg:classifiers":[
        {
            "category":"Personal",
            "subcategory":"Day Spa",
            "type":"Services"
        }
    ],
    "sg:phone":"+61 3 9646 3422",
    "sg:postcode":"3207",
    "sg:province":"VIC",
    "wof:name":"Endota Spa",
    "wof:placetype":"venue"
},
  "geometry": {"coordinates":[144.945908,-37.834431],"type":"Point"}
}