{
  "type": "Feature",
  "properties": {
    "addr:full":"15B Stanley St Wodonga VIC 3690",
    "addr:housenumber":"15b",
    "addr:postcode":"3690",
    "addr:street":"Stanley St",
    "iso:country":"AU",
    "sg:address":"15B Stanley St",
    "sg:city":"Wodonga",
    "sg:classifiers":[
        {
            "category":"Professional",
            "subcategory":"Printing & Photocopies",
            "type":"Services"
        }
    ],
    "sg:phone":"+61 2 6056 3938",
    "sg:postcode":"3690",
    "sg:province":"VIC",
    "sg:tags":[
        "photocopying"
    ],
    "wof:name":"Snap Printing",
    "wof:placetype":"venue"
},
  "geometry": {"coordinates":[146.88630676299999,-36.1223564148],"type":"Point"}
}