{
  "type": "Feature",
  "properties": {
    "addr:full":"18 Elimatta St Warneet VIC 3980",
    "addr:housenumber":"18",
    "addr:postcode":"3980",
    "addr:street":"Elimatta St",
    "iso:country":"AU",
    "sg:address":"18 Elimatta St",
    "sg:city":"Warneet",
    "sg:classifiers":[
        {
            "category":"Transit Center",
            "subcategory":"Freight",
            "type":"Transportation"
        }
    ],
    "sg:phone":"+61 448 488 258",
    "sg:postcode":"3980",
    "sg:province":"VIC",
    "sg:tags":[
        "forklift",
        "truck"
    ],
    "wof:name":"Seabrook Forklifts",
    "wof:placetype":"venue"
},
  "geometry": {"coordinates":[145.312301636,-38.2236022949],"type":"Point"}
}