{
  "type": "Feature",
  "properties": {
    "addr:full":"39 Redgum Drv Dandenong South VIC 3175",
    "addr:housenumber":"39",
    "addr:postcode":"3175",
    "addr:street":"Redgum Drv",
    "iso:country":"AU",
    "sg:address":"39 Redgum Drv",
    "sg:city":"Dandenong South",
    "sg:classifiers":[
        {
            "category":"Building & Trades",
            "subcategory":"Construction",
            "type":"Services"
        }
    ],
    "sg:phone":"+61 3 9706 4378",
    "sg:postcode":"3175",
    "sg:province":"VIC",
    "sg:tags":[
        "distributor",
        "platform",
        "work",
        "mfrs",
        "elevating"
    ],
    "wof:name":"LG Travel Tower Service",
    "wof:placetype":"venue"
},
  "geometry": {"coordinates":[145.19737243599999,-38.0248336792],"type":"Point"}
}