{
  "type": "Feature",
  "properties": {
    "addr:full":"1140 McMillans Rd Berrimah NT 0828",
    "addr:housenumber":"1140",
    "addr:postcode":"nt 0828",
    "addr:street":"Mcmillans Rd",
    "iso:country":"AU",
    "sg:address":"1140 McMillans Rd",
    "sg:city":"Berrimah",
    "sg:classifiers":[
        {
            "category":"Building & Trades",
            "subcategory":"Cleaning & Sanitation",
            "type":"Services"
        }
    ],
    "sg:phone":"+61 8 8984 3137",
    "sg:postcode":"0828",
    "sg:province":"NT",
    "sg:tags":[
        "abrasive",
        "blasting"
    ],
    "wof:name":"Boscato V. & Co Pty Ltd",
    "wof:placetype":"venue"
},
  "geometry": {"coordinates":[130.952835083,-12.4308681488],"type":"Point"}
}