{
  "type": "Feature",
  "properties": {
    "iso:country":"AU",
    "sg:address":"3 Ness St",
    "sg:city":"Clare",
    "sg:classifiers":[
        {
            "category":"Insurance",
            "subcategory":"Hazard Insurance",
            "type":"Services"
        }
    ],
    "sg:phone":"+61 8 8842 2575",
    "sg:postcode":"5453",
    "sg:province":"SA",
    "sg:tags":[
        "motor",
        "vehicle"
    ],
    "wof:name":"RAA Insurance Ltd",
    "wof:placetype":"venue"
},
  "geometry": {"coordinates":[138.612274,-33.83345],"type":"Point"}
}