{
  "type": "Feature",
  "properties": {
    "iso:country":"AU",
    "sg:address":"26 Malbon Rd",
    "sg:city":"Kirwan",
    "sg:classifiers":[
        {
            "category":"Retail",
            "subcategory":"Driving School",
            "type":"Services"
        }
    ],
    "sg:phone":"+61 7 4723 7399",
    "sg:postcode":"4817",
    "sg:province":"QLD",
    "wof:name":"Kingfisher Driving School",
    "wof:placetype":"venue"
},
  "geometry": {"coordinates":[146.736877,-19.307961],"type":"Point"}
}