{
  "type": "Feature",
  "properties": {
    "addr:full":"57 Scott St Warracknabeal VIC 3393",
    "addr:housenumber":"57",
    "addr:postcode":"3393",
    "addr:street":"Scott St",
    "iso:country":"AU",
    "sg:address":"57 Scott St",
    "sg:city":"Warracknabeal",
    "sg:classifiers":[
        {
            "category":"Banks & Credit Unions",
            "subcategory":"Bureau De Change",
            "type":"Services"
        }
    ],
    "sg:phone":"+61 3 5394 1122",
    "sg:postcode":"3393",
    "sg:province":"VIC",
    "sg:tags":[
        "repairs",
        "part",
        "appliance",
        "electrical"
    ],
    "wof:name":"De Vries Electrics",
    "wof:placetype":"venue"
},
  "geometry": {"coordinates":[142.39517211899999,-36.2492446899],"type":"Point"}
}