{
  "type": "Feature",
  "properties": {
    "addr:full":"PO Box 1626 St Kilda VIC 3182",
    "addr:postcode":"3182",
    "iso:country":"AU",
    "sg:address":"PO Box 1626",
    "sg:city":"St Kilda",
    "sg:classifiers":[
        {
            "category":"Banks & Credit Unions",
            "subcategory":"Financial Services",
            "type":"Services"
        }
    ],
    "sg:phone":"+61 1300 302 798",
    "sg:postcode":"3182",
    "sg:province":"VIC",
    "sg:tags":[
        "financier"
    ],
    "wof:name":"Davis Clarke",
    "wof:placetype":"venue"
},
  "geometry": {"coordinates":[144.96989440900001,-37.8590087891],"type":"Point"}
}