{
  "type": "Feature",
  "properties": {
    "addr:full":"Box Flat Estate, Swanbank Rd Swanbank QLD 4306",
    "addr:postcode":"4306",
    "addr:street":"Swanbank Rd",
    "iso:country":"AU",
    "sg:address":"Box Flat Estate, Swanbank Rd",
    "sg:city":"Swanbank",
    "sg:classifiers":[
        {
            "category":"Building & Trades",
            "subcategory":"Pest Control",
            "type":"Services"
        }
    ],
    "sg:phone":"+61 7 3280 3000",
    "sg:postcode":"4306",
    "sg:province":"QLD",
    "sg:tags":[
        "herbicide",
        "insecticides",
        "fungicide"
    ],
    "wof:name":"Barmac Industries Pty Ltd",
    "wof:placetype":"venue"
},
  "geometry": {"coordinates":[152.81158447300001,-27.6576957703],"type":"Point"}
}