{
  "type": "Feature",
  "properties": {
    "addr:full":"Level 1/ 157 The Parade Norwood SA 5067",
    "addr:housenumber":"/ 157",
    "addr:postcode":"5067",
    "addr:street":"The Parade",
    "iso:country":"AU",
    "sg:address":"Level 1/ 157",
    "sg:city":"The Parade Norwood",
    "sg:classifiers":[
        {
            "category":"Professional",
            "subcategory":"Accounting & Tax Preparation",
            "type":"Services"
        }
    ],
    "sg:phone":"+61 8 8333 3266",
    "sg:postcode":"5067",
    "sg:province":"SA",
    "sg:tags":[
        "accountant",
        "auditor"
    ],
    "wof:name":"MLCS Corporate Pty Ltd",
    "wof:placetype":"venue"
},
  "geometry": {"coordinates":[138.63276672399999,-34.92137146],"type":"Point"}
}