{
  "type": "Feature",
  "properties": {
    "addr:full":"Melaleuca Drv Boondall QLD 4034",
    "addr:postcode":"4034",
    "addr:street":"Melaleuca Drv",
    "iso:country":"AU",
    "sg:address":"Melaleuca Drv",
    "sg:city":"Boondall",
    "sg:classifiers":[
        {
            "category":"Retail",
            "subcategory":"Event Space",
            "type":"Services"
        }
    ],
    "sg:phone":"+61 7 3265 8111",
    "sg:postcode":"4034",
    "sg:province":"QLD",
    "sg:tags":[
        "venue",
        "reception",
        "wedding"
    ],
    "wof:name":"Brisbane Entertainment Centre",
    "wof:placetype":"venue"
},
  "geometry": {"coordinates":[153.06781000000001,-27.344688],"type":"Point"}
}