{
  "type": "Feature",
  "properties": {
    "addr:full":"5 Delta St Geebung QLD 4034",
    "addr:housenumber":"5",
    "addr:postcode":"4034",
    "addr:street":"Delta St",
    "iso:country":"AU",
    "sg:address":"5 Delta St",
    "sg:city":"Geebung",
    "sg:classifiers":[
        {
            "category":"Shopping",
            "subcategory":"Hobbies, Toys, & Games",
            "type":"Retail Goods"
        }
    ],
    "sg:phone":"+61 7 3265 3738",
    "sg:postcode":"4034",
    "sg:province":"QLD",
    "sg:tags":[
        "bag",
        "sack"
    ],
    "wof:name":"Colquhoun&#039;Brisbane Bag Company",
    "wof:placetype":"venue"
},
  "geometry": {"coordinates":[153.04887400000001,-27.365788],"type":"Point"}
}