{
  "type": "Feature",
  "properties": {
    "iso:country":"AU",
    "sg:address":"1170 Minimbah Rd",
    "sg:city":"Nabiac",
    "sg:classifiers":[
        {
            "category":"Utilities",
            "subcategory":"Electric",
            "type":"Services"
        }
    ],
    "sg:phone":"+61 2 6554 1556",
    "sg:postcode":"2312",
    "sg:province":"NSW",
    "sg:tags":[
        "electrical",
        "contractor"
    ],
    "wof:name":"Nabiac Electrical Services - Col Menser",
    "wof:placetype":"venue"
},
  "geometry": {"coordinates":[152.36854600000001,-32.119301],"type":"Point"}
}