{
  "type": "Feature",
  "properties": {
    "addr:full":"50 New England Drv Hillarys WA 6025",
    "addr:housenumber":"50",
    "addr:postcode":"6025",
    "addr:street":"New England Drv",
    "iso:country":"AU",
    "sg:address":"50 New England Drv",
    "sg:city":"Hillarys",
    "sg:classifiers":[
        {
            "category":"Building & Trades",
            "subcategory":"Construction",
            "type":"Services"
        }
    ],
    "sg:phone":"+61 8 9401 3783",
    "sg:postcode":"6025",
    "sg:province":"WA",
    "sg:tags":[
        "polishing",
        "sanding",
        "floor"
    ],
    "wof:name":"Kings Floor Sanding",
    "wof:placetype":"venue"
},
  "geometry": {"coordinates":[115.742408752,-31.8046379089],"type":"Point"}
}