{
  "type": "Feature",
  "properties": {
    "addr:full":"16 Brookland Valley Drv Woodcroft SA 5162",
    "addr:housenumber":"16",
    "addr:postcode":"5162",
    "addr:street":"Brookland Valley Drv",
    "iso:country":"AU",
    "sg:address":"16 Brookland Valley Drv",
    "sg:city":"Woodcroft",
    "sg:classifiers":[
        {
            "category":"Retail",
            "subcategory":"Auto Repair",
            "type":"Services"
        }
    ],
    "sg:phone":"+61 421 469 272",
    "sg:postcode":"5162",
    "sg:province":"SA",
    "sg:tags":[
        "sport",
        "motor"
    ],
    "wof:name":"PME Racewear",
    "wof:placetype":"venue"
},
  "geometry": {"coordinates":[138.55355835,-35.1173667908],"type":"Point"}
}