{
  "type": "Feature",
  "properties": {
    "iso:country":"AU",
    "sg:address":"68-70 Cranford Ave",
    "sg:city":"Brentwood",
    "sg:classifiers":[
        {
            "category":"Deli",
            "type":"Food & Drink"
        }
    ],
    "sg:phone":"+61 8 9364 6038",
    "sg:postcode":"6153",
    "sg:province":"WA",
    "sg:tags":[
        "delicatessen"
    ],
    "wof:name":"Brentwood Delicatessen",
    "wof:placetype":"venue"
},
  "geometry": {"coordinates":[115.849411,-32.040928],"type":"Point"}
}