{
  "type": "Feature",
  "properties": {
    "addr:full":"231 Holt St Eagle Farm QLD 4009",
    "addr:housenumber":"231",
    "addr:postcode":"4009",
    "addr:street":"Holt St",
    "iso:country":"AU",
    "sg:address":"231 Holt St",
    "sg:city":"Eagle Farm",
    "sg:classifiers":[
        {
            "category":"Building & Trades",
            "subcategory":"Pest Control",
            "type":"Services"
        }
    ],
    "sg:phone":"+61 7 3868 4777",
    "sg:postcode":"4009",
    "sg:province":"QLD",
    "sg:tags":[
        "controller",
        "automatic"
    ],
    "wof:name":"Dawson Technology Pty Ltd",
    "wof:placetype":"venue"
},
  "geometry": {"coordinates":[153.10394287099999,-27.4381542206],"type":"Point"}
}