{
  "type": "Feature",
  "properties": {
    "addr:full":"52 Restwell St Bankstown NSW 2200",
    "addr:housenumber":"52",
    "addr:postcode":"2200",
    "addr:street":"Restwell St",
    "iso:country":"AU",
    "sg:address":"52 Restwell St",
    "sg:city":"Bankstown",
    "sg:classifiers":[
        {
            "category":"Health Services",
            "subcategory":"Health Practitioner",
            "type":"Services"
        }
    ],
    "sg:phone":"+61 409 606 824",
    "sg:postcode":"2200",
    "sg:province":"NSW",
    "sg:tags":[
        "hypnotherapy"
    ],
    "wof:name":"Wilks Frankh",
    "wof:placetype":"venue"
},
  "geometry": {"coordinates":[151.03486599999999,-33.920502],"type":"Point"}
}