{
  "type": "Feature",
  "properties": {
    "addr:full":"8 Butcher St Kwinana WA 6167",
    "addr:housenumber":"8",
    "addr:postcode":"6167",
    "addr:street":"Butcher St",
    "iso:country":"AU",
    "sg:address":"8 Butcher St",
    "sg:city":"Kwinana",
    "sg:classifiers":[
        {
            "category":"Autos & Motor Vehicles",
            "subcategory":"Boat Sales",
            "type":"Retail Goods"
        }
    ],
    "sg:phone":"+61 8 9419 2663",
    "sg:postcode":"6167",
    "sg:province":"WA",
    "sg:tags":[
        "equipment",
        "yacht"
    ],
    "wof:name":"Spar Shed",
    "wof:placetype":"venue"
},
  "geometry": {"coordinates":[115.78265399999999,-32.235516],"type":"Point"}
}