{
  "type": "Feature",
  "properties": {
    "iso:country":"AU",
    "sg:address":"1st Floor 25 Sturt St",
    "sg:city":"Townsville",
    "sg:classifiers":[
        {
            "category":"Professional",
            "subcategory":"Accounting & Tax Preparation",
            "type":"Services"
        }
    ],
    "sg:phone":"+61 7 4722 2777",
    "sg:postcode":"4810",
    "sg:province":"QLD",
    "sg:tags":[
        "bookkeeping"
    ],
    "wof:name":"Sturt Business Centre",
    "wof:placetype":"venue"
},
  "geometry": {"coordinates":[146.814682,-19.26083],"type":"Point"}
}