{
  "type": "Feature",
  "properties": {
    "addr:full":"Cnr Neale & Station Sts Deer Park VIC 3023",
    "addr:postcode":"3023",
    "addr:street":"Cnr Neale",
    "iso:country":"AU",
    "sg:address":"Cnr Neale & Station Sts",
    "sg:city":"Deer Park",
    "sg:classifiers":[
        {
            "category":"Food & Beverages",
            "subcategory":"Supermarket",
            "type":"Retail Goods"
        }
    ],
    "sg:phone":"+61 3 9361 1247",
    "sg:postcode":"3023",
    "sg:province":"VIC",
    "sg:tags":[
        "grocery",
        "store"
    ],
    "wof:name":"Bi-Lo Pty Ltd",
    "wof:placetype":"venue"
},
  "geometry": {"coordinates":[144.776657,-37.752533],"type":"Point"}
}