{
  "type": "Feature",
  "properties": {
    "addr:full":"44 Augusta St Maylands SA 5069",
    "addr:postcode":"5069",
    "addr:street":"44 Augusta St",
    "iso:country":"AU",
    "sg:address":"44 Augusta St",
    "sg:city":"Maylands",
    "sg:classifiers":[
        {
            "category":"Building & Trades",
            "subcategory":"Construction",
            "type":"Services"
        }
    ],
    "sg:phone":"+61 8 8362 3613",
    "sg:postcode":"5069",
    "sg:province":"SA",
    "sg:tags":[
        "renovation",
        "alterations",
        "extension",
        "contractor"
    ],
    "wof:name":"B.N.Q. Building Co",
    "wof:placetype":"venue"
},
  "geometry": {"coordinates":[138.63543701200001,-34.9106788635],"type":"Point"}
}