{
  "type": "Feature",
  "properties": {
    "addr:full":"Unit 9/ 36 New St Ringwood VIC 3134",
    "addr:postcode":"3134",
    "addr:street":"New St",
    "iso:country":"AU",
    "sg:address":"Unit 9/ 36 New St",
    "sg:city":"Ringwood",
    "sg:classifiers":[
        {
            "category":"Utilities",
            "subcategory":"Mobile Phone",
            "type":"Services"
        }
    ],
    "sg:phone":"+61 3 9876 9011",
    "sg:postcode":"3134",
    "sg:province":"VIC",
    "sg:tags":[
        "assembly",
        "part",
        "electronic"
    ],
    "wof:name":"Alfatron Pty Ltd",
    "wof:placetype":"venue"
},
  "geometry": {"coordinates":[145.220306397,-37.8143196106],"type":"Point"}
}