{
  "type": "Feature",
  "properties": {
    "iso:country":"AU",
    "sg:address":"14 Thompson St",
    "sg:city":"Kensington",
    "sg:classifiers":[
        {
            "category":"Professional",
            "type":"Services"
        }
    ],
    "sg:phone":"+61 3 9326 2555",
    "sg:postcode":"3031",
    "sg:province":"VIC",
    "sg:tags":[
        "courier"
    ],
    "wof:name":"Jet Worldwide (Aust) Pty Ltd",
    "wof:placetype":"venue"
},
  "geometry": {"coordinates":[144.93441799999999,-37.792561],"type":"Point"}
}