{
  "type": "Feature",
  "properties": {
    "addr:full":"Unit 1/ 38a Walder Rd Hammondville NSW 2170",
    "addr:housenumber":"/ 38a",
    "addr:postcode":"2170",
    "addr:street":"Walder Rd",
    "iso:country":"AU",
    "sg:address":"Unit 1/ 38a Walder Rd",
    "sg:city":"Hammondville",
    "sg:classifiers":[
        {
            "category":"Fast Food",
            "type":"Food & Drink"
        }
    ],
    "sg:phone":"+61 2 9825 3263",
    "sg:postcode":"2170",
    "sg:province":"NSW",
    "sg:tags":[
        "away",
        "take"
    ],
    "wof:name":"Charlies Charcoal Chicken",
    "wof:placetype":"venue"
},
  "geometry": {"coordinates":[150.95399475100001,-33.9482192993],"type":"Point"}
}