{
  "type": "Feature",
  "properties": {
    "addr:full":"21 Queen St Nunawading VIC 3131",
    "addr:housenumber":"21",
    "addr:postcode":"3131",
    "addr:street":"Queen St",
    "iso:country":"AU",
    "sg:address":"21 Queen St",
    "sg:city":"Nunawading",
    "sg:classifiers":[
        {
            "category":"Wholesale",
            "subcategory":"Machinery & Supplies",
            "type":"Manufacturing & Wholesale Goods"
        }
    ],
    "sg:phone":"+61 3 9872 6222",
    "sg:postcode":"3131",
    "sg:province":"VIC",
    "sg:tags":[
        "equipment",
        "welding"
    ],
    "wof:name":"Tanjant Tool Co Pty Ltd",
    "wof:placetype":"venue"
},
  "geometry": {"coordinates":[145.18669128400001,-37.8181877136],"type":"Point"}
}