{
  "type": "Feature",
  "properties": {
    "addr:full":"318 Sandgate Rd Shortland NSW 2307",
    "addr:housenumber":"318",
    "addr:postcode":"2307",
    "addr:street":"Sandgate Rd",
    "iso:country":"AU",
    "sg:address":"318 Sandgate Rd",
    "sg:city":"Shortland",
    "sg:classifiers":[
        {
            "category":"Professional",
            "subcategory":"Printing & Photocopies",
            "type":"Services"
        }
    ],
    "sg:phone":"+61 2 4955 0550",
    "sg:postcode":"2307",
    "sg:province":"NSW",
    "sg:tags":[
        "textile",
        "clothing"
    ],
    "wof:name":"Zulu Graphics",
    "wof:placetype":"venue"
},
  "geometry": {"coordinates":[151.695831,-32.885082],"type":"Point"}
}