{
  "type": "Feature",
  "properties": {
    "addr:full":"334 Ruthven St Toowoomba QLD 4350",
    "addr:housenumber":"334",
    "addr:postcode":"4350",
    "addr:street":"Ruthven St",
    "iso:country":"AU",
    "sg:address":"334 Ruthven St",
    "sg:city":"Toowoomba",
    "sg:classifiers":[
        {
            "category":"Fast Food",
            "type":"Food & Drink"
        }
    ],
    "sg:phone":"+61 7 4639 2807",
    "sg:postcode":"4350",
    "sg:province":"QLD",
    "sg:tags":[
        "away",
        "take"
    ],
    "wof:name":"Pizza Hut",
    "wof:placetype":"venue"
},
  "geometry": {"coordinates":[151.952271,-27.568327],"type":"Point"}
}