{
  "type": "Feature",
  "properties": {
    "iso:country":"AU",
    "sg:address":"94 Pacific Hwy",
    "sg:city":"Tuggerah",
    "sg:classifiers":[
        {
            "category":"Home & Garden",
            "subcategory":"Furniture",
            "type":"Retail Goods"
        }
    ],
    "sg:phone":"+61 2 4351 1299",
    "sg:postcode":"2259",
    "sg:province":"NSW",
    "sg:tags":[
        "business"
    ],
    "wof:name":"Lakes Office Choice",
    "wof:placetype":"venue"
},
  "geometry": {"coordinates":[151.41995239299999,-33.3062782288],"type":"Point"}
}