{
  "type": "Feature",
  "properties": {
    "addr:full":"126 Haldon St Lakemba NSW 2195",
    "addr:housenumber":"126",
    "addr:postcode":"2195",
    "addr:street":"Haldon St",
    "iso:country":"AU",
    "sg:address":"126 Haldon St",
    "sg:city":"Lakemba",
    "sg:classifiers":[
        {
            "category":"Food & Beverages",
            "subcategory":"Supermarket",
            "type":"Retail Goods"
        }
    ],
    "sg:phone":"+61 2 9759 3399",
    "sg:postcode":"2195",
    "sg:province":"NSW",
    "sg:tags":[
        "grocery",
        "store"
    ],
    "wof:name":"Best Price Supermarket",
    "wof:placetype":"venue"
},
  "geometry": {"coordinates":[151.07818599999999,-33.922001],"type":"Point"}
}