{
  "type": "Feature",
  "properties": {
    "addr:full":"626 Brunswick St New Farm QLD 4005",
    "addr:housenumber":"626",
    "addr:postcode":"4005",
    "addr:street":"Brunswick St",
    "iso:country":"AU",
    "sg:address":"626 Brunswick St",
    "sg:city":"New Farm",
    "sg:classifiers":[
        {
            "category":"Professional",
            "type":"Services"
        }
    ],
    "sg:phone":"+61 7 3358 4891",
    "sg:postcode":"4005",
    "sg:province":"QLD",
    "sg:tags":[
        "auctioneer"
    ],
    "wof:name":"Liddy Paul",
    "wof:placetype":"venue"
},
  "geometry": {"coordinates":[153.040740967,-27.4631328583],"type":"Point"}
}