{
  "type": "Feature",
  "properties": {
    "addr:full":"PO Box 589 Beecroft NSW 2119",
    "addr:postcode":"2119",
    "iso:country":"AU",
    "sg:address":"PO Box 589",
    "sg:city":"Beecroft",
    "sg:classifiers":[
        {
            "category":"Banks & Credit Unions",
            "subcategory":"Investment Brokerage",
            "type":"Services"
        }
    ],
    "sg:phone":"+61 2 9871 7772",
    "sg:postcode":"2119",
    "sg:province":"NSW",
    "sg:tags":[
        "shutter",
        "louvre"
    ],
    "wof:name":"Boomerang Blinds & Shutters",
    "wof:placetype":"venue"
},
  "geometry": {"coordinates":[151.06483459500001,-33.7503204346],"type":"Point"}
}