{
  "type": "Feature",
  "properties": {
    "addr:full":"4/ 4 Kelly Crt Maroochydore QLD 4558",
    "addr:housenumber":"/ 4",
    "addr:postcode":"4558",
    "addr:street":"Kelly Crt",
    "iso:country":"AU",
    "sg:address":"4/ 4 Kelly Crt",
    "sg:city":"Maroochydore",
    "sg:classifiers":[
        {
            "category":"Home & Garden",
            "subcategory":"Hardware",
            "type":"Retail Goods"
        }
    ],
    "sg:phone":"+61 7 5443 6122",
    "sg:postcode":"4558",
    "sg:province":"QLD",
    "sg:tags":[
        "repair",
        "tool",
        "power"
    ],
    "wof:name":"Mac's Power Tools & Rewinds",
    "wof:placetype":"venue"
},
  "geometry": {"coordinates":[153.08872985799999,-26.6704845428],"type":"Point"}
}