{
  "type": "Feature",
  "properties": {
    "addr:full":"Flt1/ 2 Phillip St Stanmore NSW 2048",
    "addr:housenumber":"2",
    "addr:postcode":"2048",
    "addr:street":"Phillip St",
    "iso:country":"AU",
    "sg:address":"Flt1/ 2 Phillip St",
    "sg:city":"Stanmore",
    "sg:classifiers":[
        {
            "category":"Professional",
            "subcategory":"Engineering",
            "type":"Services"
        }
    ],
    "sg:phone":"+61 2 9564 6658",
    "sg:postcode":"2048",
    "sg:province":"NSW",
    "sg:tags":[
        "engineer"
    ],
    "wof:name":"Face Engineering Pty Ltd",
    "wof:placetype":"venue"
},
  "geometry": {"coordinates":[151.16151400000001,-33.888138],"type":"Point"}
}