{
  "type": "Feature",
  "properties": {
    "addr:full":"30 Gordon St Paddington NSW 2021",
    "addr:housenumber":"30",
    "addr:postcode":"2021",
    "addr:street":"Gordon St",
    "iso:country":"AU",
    "sg:address":"30 Gordon St",
    "sg:city":"Paddington",
    "sg:classifiers":[
        {
            "category":"Social Services",
            "subcategory":"Child Care",
            "type":"Services"
        }
    ],
    "sg:phone":"+61 2 9360 4485",
    "sg:postcode":"2021",
    "sg:province":"NSW",
    "wof:name":"Paddington Children's Centre (UnitingCare)",
    "wof:placetype":"venue"
},
  "geometry": {"coordinates":[151.228607178,-33.8867454529],"type":"Point"}
}