{
  "type": "Feature",
  "properties": {
    "iso:country":"AU",
    "sg:address":"257 Gympie Rd",
    "sg:city":"Kedron",
    "sg:classifiers":[
        {
            "category":"Shopping",
            "subcategory":"Clothing, Apparel, & Fashions",
            "type":"Retail Goods"
        }
    ],
    "sg:phone":"+61 7 3350 4677",
    "sg:postcode":"4031",
    "sg:province":"QLD",
    "sg:tags":[
        "hire",
        "men's",
        "wear",
        "formal"
    ],
    "wof:name":"Spurling Bridal & Formalwear",
    "wof:placetype":"venue"
},
  "geometry": {"coordinates":[153.032623,-27.408127],"type":"Point"}
}