{
  "type": "Feature",
  "properties": {
    "iso:country":"AU",
    "sg:address":"Suite 5, 110 Woodlark St",
    "sg:city":"Lismore",
    "sg:classifiers":[
        {
            "category":"Professional",
            "subcategory":"Employment Agencies",
            "type":"Services"
        }
    ],
    "sg:phone":"+61 2 6622 1363",
    "sg:postcode":"2480",
    "sg:province":"NSW",
    "wof:name":"Northern Rivers Group Training",
    "wof:placetype":"venue"
},
  "geometry": {"coordinates":[153.27914428700001,-28.8074474335],"type":"Point"}
}