{
  "type": "Feature",
  "properties": {
    "iso:country":"AU",
    "sg:address":"Unit 3/ 39 Susan St",
    "sg:city":"Eltham",
    "sg:classifiers":[
        {
            "category":"Building & Trades",
            "subcategory":"Plumbing",
            "type":"Services"
        }
    ],
    "sg:phone":"+61 418 545 848",
    "sg:postcode":"3095",
    "sg:province":"VIC",
    "sg:tags":[
        "pump",
        "repairer"
    ],
    "wof:name":"Pumpworks Victoria Pty Ltd",
    "wof:placetype":"venue"
},
  "geometry": {"coordinates":[145.14125060999999,-37.7200660706],"type":"Point"}
}