{
  "type": "Feature",
  "properties": {
    "addr:full":"Shop 1 - 121/ 123 Military Rd Neutral Bay NSW 2089",
    "addr:housenumber":"shop 1 121 / 123",
    "addr:postcode":"2089",
    "addr:street":"Military Rd",
    "iso:country":"AU",
    "sg:address":"Shop 1 - 121/ 123 Military Rd",
    "sg:city":"Neutral Bay",
    "sg:classifiers":[
        {
            "category":"Food & Beverages",
            "subcategory":"Bakery",
            "type":"Retail Goods"
        }
    ],
    "sg:phone":"+61 2 9953 8550",
    "sg:postcode":"2089",
    "sg:province":"NSW",
    "sg:tags":[
        "cake",
        "shop",
        "pastry"
    ],
    "wof:name":"Le Patissier Chocolatier",
    "wof:placetype":"venue"
},
  "geometry": {"coordinates":[151.220825195,-33.8310813904],"type":"Point"}
}