{
  "type": "Feature",
  "properties": {
    "addr:full":"U 1/ 154 Mt Vernon Drv Kambah ACT 2902",
    "addr:housenumber":"/ 154",
    "addr:postcode":"2902",
    "addr:street":"Mt Vernon Drv",
    "iso:country":"AU",
    "sg:address":"U 1/ 154 Mt Vernon Drv",
    "sg:city":"Kambah",
    "sg:classifiers":[
        {
            "category":"Autos & Motor Vehicles",
            "subcategory":"Automobile Sales",
            "type":"Retail Goods"
        }
    ],
    "sg:phone":"+61 418 633 494",
    "sg:postcode":"2902",
    "sg:province":"ACT",
    "sg:tags":[
        "car",
        "used"
    ],
    "wof:name":"Wytoo Holdings Pty Ltd",
    "wof:placetype":"venue"
},
  "geometry": {"coordinates":[149.03192138700001,-35.3905792236],"type":"Point"}
}