{
  "type": "Feature",
  "properties": {
    "addr:full":"544 Boundary Rd Dingley VIC 3172",
    "addr:housenumber":"544",
    "addr:postcode":"3172",
    "addr:street":"Boundary Rd",
    "iso:country":"AU",
    "sg:address":"544 Boundary Rd",
    "sg:city":"Dingley",
    "sg:classifiers":[
        {
            "category":"Building & Trades",
            "subcategory":"Cleaning & Sanitation",
            "type":"Services"
        }
    ],
    "sg:phone":"+61 1300 723 988",
    "sg:postcode":"3172",
    "sg:province":"VIC",
    "sg:tags":[
        "grease",
        "trap"
    ],
    "wof:name":"Eastern Liquid Services",
    "wof:placetype":"venue"
},
  "geometry": {"coordinates":[145.11114501899999,-37.9775733948],"type":"Point"}
}