{
  "type": "Feature",
  "properties": {
    "addr:full":"Shop 1 Bailey Centre 150 Pacific Hwy Coffs Harbour NSW 2450",
    "addr:housenumber":"shop 1;150",
    "addr:postcode":"2450",
    "addr:street":"Bailey;Pacific Hwy",
    "iso:country":"AU",
    "sg:address":"Shop 1 Bailey Centre 150 Pacific Hwy",
    "sg:city":"Coffs Harbour",
    "sg:classifiers":[
        {
            "category":"Building & Trades",
            "subcategory":"Equipment Rental",
            "type":"Services"
        }
    ],
    "sg:phone":"+61 2 6652 7500",
    "sg:postcode":"2450",
    "sg:province":"NSW",
    "sg:tags":[
        "fitness"
    ],
    "wof:name":"Amart All Sports",
    "wof:placetype":"venue"
},
  "geometry": {"coordinates":[153.09053,-30.318281],"type":"Point"}
}