{
  "type": "Feature",
  "properties": {
    "addr:full":"55 Bingley Crt Bell Post Hill VIC 3215",
    "addr:housenumber":"55",
    "addr:postcode":"3215",
    "addr:street":"Bingley Crt",
    "iso:country":"AU",
    "sg:address":"55 Bingley Crt",
    "sg:city":"Bell Post Hill",
    "sg:classifiers":[
        {
            "category":"Building & Trades",
            "subcategory":"Construction",
            "type":"Services"
        }
    ],
    "sg:phone":"+61 3 5277 0415",
    "sg:postcode":"3215",
    "sg:province":"VIC",
    "sg:tags":[
        "earth",
        "excavating",
        "moving",
        "contractor"
    ],
    "wof:name":"George Dimitrovski Excavations & Plumbing",
    "wof:placetype":"venue"
},
  "geometry": {"coordinates":[144.322555542,-38.0989494324],"type":"Point"}
}