{
  "type": "Feature",
  "properties": {
    "addr:full":"203 River St Maclean NSW 2463",
    "addr:housenumber":"203",
    "addr:postcode":"2463",
    "addr:street":"River St",
    "iso:country":"AU",
    "sg:address":"203 River St",
    "sg:city":"Maclean",
    "sg:classifiers":[
        {
            "category":"Personal",
            "subcategory":"Beauty Salon",
            "type":"Services"
        }
    ],
    "sg:phone":"+61 2 6645 4411",
    "sg:postcode":"2463",
    "sg:province":"NSW",
    "wof:name":"Endessa's Beauty Spot",
    "wof:placetype":"venue"
},
  "geometry": {"coordinates":[153.19676208499999,-29.4551811218],"type":"Point"}
}