{
  "type": "Feature",
  "properties": {
    "iso:country":"AU",
    "sg:address":"Gardeners Rd",
    "sg:city":"Eastlakes",
    "sg:classifiers":[
        {
            "category":"Food & Beverages",
            "subcategory":"Liquor & Beverages",
            "type":"Retail Goods"
        }
    ],
    "sg:phone":"+61 2 9667 0697",
    "sg:postcode":"2018",
    "sg:province":"NSW",
    "sg:tags":[
        "store"
    ],
    "wof:name":"Macs Liquor",
    "wof:placetype":"venue"
},
  "geometry": {"coordinates":[151.212646484,-33.9241104126],"type":"Point"}
}