{
  "type": "Feature",
  "properties": {
    "addr:full":"17 Tarnard Drv Braeside VIC 3195",
    "addr:housenumber":"17",
    "addr:postcode":"3195",
    "addr:street":"Tarnard Drv",
    "iso:country":"AU",
    "sg:address":"17 Tarnard Drv",
    "sg:city":"Braeside",
    "sg:classifiers":[
        {
            "category":"Building & Trades",
            "subcategory":"Construction",
            "type":"Services"
        }
    ],
    "sg:phone":"+61 3 9587 3154",
    "sg:postcode":"3195",
    "sg:province":"VIC",
    "sg:tags":[
        "insulation",
        "contractor"
    ],
    "wof:name":"Insulation Wholesalers Pty Ltd",
    "wof:placetype":"venue"
},
  "geometry": {"coordinates":[145.110397339,-37.9889068604],"type":"Point"}
}