{
  "type": "Feature",
  "properties": {
    "addr:full":"2462 Albany Hwy Gosnells WA 6110",
    "addr:housenumber":"2462",
    "addr:postcode":"6110",
    "addr:street":"Albany Hwy",
    "iso:country":"AU",
    "sg:address":"2462 Albany Hwy",
    "sg:city":"Gosnells",
    "sg:classifiers":[
        {
            "category":"Social Services",
            "subcategory":"Retirement Home",
            "type":"Services"
        }
    ],
    "sg:phone":"+61 8 9398 8008",
    "sg:postcode":"6110",
    "sg:province":"WA",
    "sg:tags":[
        "village"
    ],
    "wof:name":"Riverside Gardens Lifestyle Estate",
    "wof:placetype":"venue"
},
  "geometry": {"coordinates":[116.012107849,-32.0865402222],"type":"Point"}
}