{
  "type": "Feature",
  "properties": {
    "addr:full":"28 Chickerell St Morwell VIC 3840",
    "addr:housenumber":"28",
    "addr:postcode":"3840",
    "addr:street":"Chickerell St",
    "iso:country":"AU",
    "sg:address":"28 Chickerell St",
    "sg:city":"Morwell",
    "sg:classifiers":[
        {
            "category":"Retail",
            "subcategory":"Auto Repair",
            "type":"Services"
        }
    ],
    "sg:phone":"+61 3 5134 4023",
    "sg:postcode":"3840",
    "sg:province":"VIC",
    "sg:tags":[
        "repairer",
        "motor",
        "engineer"
    ],
    "wof:name":"Bobs Tuning & Repairs",
    "wof:placetype":"venue"
},
  "geometry": {"coordinates":[146.43551635700001,-38.2322540283],"type":"Point"}
}