{
  "type": "Feature",
  "properties": {
    "iso:country":"AU",
    "sg:address":"44 Chapel St",
    "sg:city":"Bendigo",
    "sg:classifiers":[
        {
            "category":"Retail",
            "subcategory":"Auto Repair",
            "type":"Services"
        }
    ],
    "sg:phone":"+61 3 5443 5709",
    "sg:postcode":"3550",
    "sg:province":"VIC",
    "sg:tags":[
        "wheel",
        "balancing",
        "alignment"
    ],
    "wof:name":"Tyrepower",
    "wof:placetype":"venue"
},
  "geometry": {"coordinates":[144.28594970699999,-36.7567939758],"type":"Point"}
}