{
  "type": "Feature",
  "properties": {
    "addr:full":"197 Lygon St Carlton VIC 3053",
    "addr:housenumber":"197",
    "addr:postcode":"3053",
    "addr:street":"Lygon St",
    "iso:country":"AU",
    "sg:address":"197 Lygon St",
    "sg:city":"Carlton",
    "sg:classifiers":[
        {
            "category":"Ice Cream",
            "type":"Food & Drink"
        }
    ],
    "sg:phone":"+61 3 9349 3888",
    "sg:postcode":"3053",
    "sg:province":"VIC",
    "sg:tags":[
        "retail"
    ],
    "wof:name":"Baskin 31 Robbins Ice Cream & Yogurt",
    "wof:placetype":"venue"
},
  "geometry": {"coordinates":[144.966720581,-37.800983429],"type":"Point"}
}