{
  "type": "Feature",
  "properties": {
    "addr:full":"Richmond Rd Morningside QLD 4170",
    "addr:postcode":"4170",
    "addr:street":"Richmond Rd",
    "iso:country":"AU",
    "sg:address":"Richmond Rd",
    "sg:city":"Morningside",
    "sg:classifiers":[
        {
            "category":"Professional",
            "subcategory":"Accounting & Tax Preparation",
            "type":"Services"
        }
    ],
    "sg:phone":"+61 412 496 901",
    "sg:postcode":"4170",
    "sg:province":"QLD",
    "sg:tags":[
        "bookkeeping"
    ],
    "wof:name":"Paragon Bookkeeping",
    "wof:placetype":"venue"
},
  "geometry": {"coordinates":[153.070602417,-27.4705295563],"type":"Point"}
}