{
  "type": "Feature",
  "properties": {
    "iso:country":"AU",
    "sg:address":"18 Raglan St",
    "sg:city":"Manly",
    "sg:classifiers":[
        {
            "category":"Retail",
            "subcategory":"Funeral Services",
            "type":"Services"
        }
    ],
    "sg:phone":"+61 2 9976 0854",
    "sg:postcode":"2095",
    "sg:province":"NSW",
    "sg:tags":[
        "director"
    ],
    "wof:name":"White Lady Funerals",
    "wof:placetype":"venue"
},
  "geometry": {"coordinates":[151.28610229500001,-33.795539856],"type":"Point"}
}