{
  "type": "Feature",
  "properties": {
    "addr:full":"3 Haymer Crt Braeside VIC 3195",
    "addr:housenumber":"3",
    "addr:postcode":"3195",
    "addr:street":"Haymer Crt",
    "iso:country":"AU",
    "sg:address":"3 Haymer Crt",
    "sg:city":"Braeside",
    "sg:classifiers":[
        {
            "category":"Professional",
            "subcategory":"Detective & Security Services",
            "type":"Services"
        }
    ],
    "sg:phone":"+61 3 9580 1066",
    "sg:postcode":"3195",
    "sg:province":"VIC",
    "sg:tags":[
        "consultant",
        "laser"
    ],
    "wof:name":"National Laser Group",
    "wof:placetype":"venue"
},
  "geometry": {"coordinates":[145.104934692,-38.0099830627],"type":"Point"}
}