{
  "type": "Feature",
  "properties": {
    "iso:country":"AU",
    "sg:address":"209 Pallas St",
    "sg:city":"Maryborough",
    "sg:classifiers":[
        {
            "category":"Arts & Performance",
            "subcategory":"Music",
            "type":"Entertainment"
        }
    ],
    "sg:phone":"+61 438 739 800",
    "sg:postcode":"4650",
    "sg:province":"QLD",
    "sg:tags":[
        "hi-fi",
        "equipment"
    ],
    "wof:name":"R & W Electronics",
    "wof:placetype":"venue"
},
  "geometry": {"coordinates":[152.69996599999999,-25.524479],"type":"Point"}
}