{
  "type": "Feature",
  "properties": {
    "iso:country":"AU",
    "sg:address":"8 William Dowle Pl",
    "sg:city":"Camden",
    "sg:classifiers":[
        {
            "category":"Professional",
            "subcategory":"Business Services",
            "type":"Services"
        }
    ],
    "sg:phone":"+61 2 4655 3444",
    "sg:postcode":"2570",
    "sg:province":"NSW",
    "sg:tags":[
        "drafting"
    ],
    "wof:name":"Accurate Plans",
    "wof:placetype":"venue"
},
  "geometry": {"coordinates":[150.66543579099999,-34.0484771729],"type":"Point"}
}