{
  "type": "Feature",
  "properties": {
    "addr:full":"1511F World Tower 87-89 Liverpool St Sydney NSW 2000",
    "addr:housenumber":"1511f;87-89",
    "addr:postcode":"2000",
    "addr:street":"Liverpool St",
    "iso:country":"AU",
    "sg:address":"1511F World Tower 87-89 Liverpool St",
    "sg:city":"Sydney",
    "sg:classifiers":[
        {
            "category":"Professional",
            "subcategory":"Management & Consulting",
            "type":"Services"
        }
    ],
    "sg:phone":"+61 2 9267 2926",
    "sg:postcode":"2000",
    "sg:province":"NSW",
    "sg:tags":[
        "consultant",
        "migration"
    ],
    "wof:name":"Phoenix Group Australia Pty Ltd",
    "wof:placetype":"venue"
},
  "geometry": {"coordinates":[151.20652770999999,-33.8765411377],"type":"Point"}
}