{
  "type": "Feature",
  "properties": {
    "iso:country":"AU",
    "sg:address":"Ferry St",
    "sg:city":"Nerang",
    "sg:classifiers":[
        {
            "category":"Organizations",
            "subcategory":"Community Association",
            "type":"Services"
        }
    ],
    "sg:phone":"+61 7 5596 1026",
    "sg:postcode":"4211",
    "sg:province":"QLD",
    "sg:tags":[
        "organisation",
        "family",
        "welfare"
    ],
    "wof:name":"Meals On Wheels",
    "wof:placetype":"venue"
},
  "geometry": {"coordinates":[153.33619689899999,-27.9890956879],"type":"Point"}
}