{
  "type": "Feature",
  "properties": {
    "addr:full":"42a Langtree Ave Mildura VIC 3500",
    "addr:housenumber":"42a",
    "addr:postcode":"3500",
    "addr:street":"Langtree Ave",
    "iso:country":"AU",
    "sg:address":"42a Langtree Ave",
    "sg:city":"Mildura",
    "sg:classifiers":[
        {
            "category":"Shopping",
            "subcategory":"Discount & Variety Stores",
            "type":"Retail Goods"
        }
    ],
    "sg:phone":"+61 3 5022 8869",
    "sg:postcode":"3500",
    "sg:province":"VIC",
    "sg:tags":[
        "shop",
        "adult"
    ],
    "wof:name":"Erotic Nights Adult Centre",
    "wof:placetype":"venue"
},
  "geometry": {"coordinates":[142.161865234,-34.1840629578],"type":"Point"}
}