{
  "type": "Feature",
  "properties": {
    "iso:country":"AU",
    "sg:address":"110 Main St",
    "sg:city":"Rutherglen",
    "sg:classifiers":[
        {
            "category":"Professional",
            "subcategory":"Secretarial Services",
            "type":"Services"
        }
    ],
    "sg:phone":"+61 2 6033 2611",
    "sg:postcode":"3685",
    "sg:province":"VIC",
    "sg:tags":[
        "typing"
    ],
    "wof:name":"Corowa Rutherglen Secretarial Service",
    "wof:placetype":"venue"
},
  "geometry": {"coordinates":[146.459884644,-36.0542144775],"type":"Point"}
}