{
  "type": "Feature",
  "properties": {
    "iso:country":"AU",
    "sg:address":"Grant-Williams Rd",
    "sg:city":"Pingrup East",
    "sg:classifiers":[
        {
            "category":"Farming",
            "subcategory":"Farm",
            "type":"Manufacturing & Wholesale Goods"
        }
    ],
    "sg:phone":"+61 8 9820 6025",
    "sg:postcode":"6343",
    "sg:province":"WA",
    "sg:tags":[
        "farmer"
    ],
    "wof:name":"Grant-Williams N",
    "wof:placetype":"venue"
},
  "geometry": {"coordinates":[118.932007,-33.377045],"type":"Point"}
}