{
  "type": "Feature",
  "properties": {
    "addr:full":"\"Hillcrest\" Moobi Rd Scone NSW 2337",
    "addr:postcode":"2337",
    "addr:street":"Moobi Rd",
    "iso:country":"AU",
    "sg:address":"\"Hillcrest\" Moobi Rd",
    "sg:city":"Scone",
    "sg:classifiers":[
        {
            "category":"Building & Trades",
            "subcategory":"Construction",
            "type":"Services"
        }
    ],
    "sg:phone":"+61 2 6545 3521",
    "sg:postcode":"2337",
    "sg:province":"NSW",
    "sg:tags":[
        "earth",
        "excavating",
        "moving",
        "contractor"
    ],
    "wof:name":"Campbells Excavations",
    "wof:placetype":"venue"
},
  "geometry": {"coordinates":[150.84376525900001,-32.0483589172],"type":"Point"}
}