{
  "type": "Feature",
  "properties": {
    "addr:full":"493-495 Keilor Rd Niddrie VIC 3042",
    "addr:postcode":"493-495;3042",
    "addr:street":"Keilor Rd",
    "iso:country":"AU",
    "sg:address":"493-495 Keilor Rd",
    "sg:city":"Niddrie",
    "sg:classifiers":[
        {
            "category":"Food & Beverages",
            "subcategory":"Supermarket",
            "type":"Retail Goods"
        }
    ],
    "sg:phone":"+61 3 9351 0097",
    "sg:postcode":"3042",
    "sg:province":"VIC",
    "sg:tags":[
        "grocery",
        "store"
    ],
    "wof:name":"NQR Supermarket Clearance Outlets",
    "wof:placetype":"venue"
},
  "geometry": {"coordinates":[144.8881073,-37.7357521057],"type":"Point"}
}