{
  "type": "Feature",
  "properties": {
    "addr:full":"12 Naperian Rd Salisbury North SA 5108",
    "addr:housenumber":"12",
    "addr:postcode":"5108",
    "addr:street":"Naperian Rd",
    "iso:country":"AU",
    "sg:address":"12 Naperian Rd",
    "sg:city":"Salisbury North",
    "sg:classifiers":[
        {
            "category":"Building & Trades",
            "subcategory":"Construction",
            "type":"Services"
        }
    ],
    "sg:phone":"+61 8 8258 4402",
    "sg:postcode":"5108",
    "sg:province":"SA",
    "sg:tags":[
        "earth",
        "excavating",
        "moving",
        "contractor"
    ],
    "wof:name":"Ietto D",
    "wof:placetype":"venue"
},
  "geometry": {"coordinates":[138.62767028799999,-34.7442016602],"type":"Point"}
}