{
  "type": "Feature",
  "properties": {
    "iso:country":"AU",
    "sg:address":"Level 1, 103 Oxford St",
    "sg:city":"Darlinghurst",
    "sg:classifiers":[
        {
            "category":"Shopping",
            "subcategory":"Clothing, Apparel, & Fashions",
            "type":"Retail Goods"
        }
    ],
    "sg:phone":"+61 2 9360 1519",
    "sg:postcode":"2010",
    "sg:province":"NSW",
    "sg:tags":[
        "textile",
        "designer"
    ],
    "wof:name":"Jacques Tchong",
    "wof:placetype":"venue"
},
  "geometry": {"coordinates":[151.21487426799999,-33.8790969849],"type":"Point"}
}