{
  "type": "Feature",
  "properties": {
    "addr:full":"Spitfire St Toowoomba QLD 4350",
    "addr:postcode":"4350",
    "addr:street":"Spitfire St",
    "iso:country":"AU",
    "sg:address":"Spitfire St",
    "sg:city":"Toowoomba",
    "sg:classifiers":[
        {
            "category":"Professional",
            "subcategory":"Detective & Security Services",
            "type":"Services"
        }
    ],
    "sg:phone":"+61 7 4633 1315",
    "sg:postcode":"4350",
    "sg:province":"QLD",
    "sg:tags":[
        "distributor",
        "aircraft",
        "mfrs"
    ],
    "wof:name":"Aerotec Queensland Pty Ltd",
    "wof:placetype":"venue"
},
  "geometry": {"coordinates":[151.875641,-27.55761],"type":"Point"}
}