{
  "type": "Feature",
  "properties": {
    "addr:full":"20 Carr Ave Leongatha VIC 3953",
    "addr:housenumber":"20",
    "addr:postcode":"3953",
    "addr:street":"Carr Ave",
    "iso:country":"AU",
    "sg:address":"20 Carr Ave",
    "sg:city":"Leongatha",
    "sg:classifiers":[
        {
            "category":"Building & Trades",
            "subcategory":"Cleaning & Sanitation",
            "type":"Services"
        }
    ],
    "sg:phone":"+61 407 622 937",
    "sg:postcode":"3953",
    "sg:province":"VIC",
    "sg:tags":[
        "chemical",
        "pressure",
        "steam",
        "contractor"
    ],
    "wof:name":"Mick Adkins Pressure Cleaning",
    "wof:placetype":"venue"
},
  "geometry": {"coordinates":[145.957565308,-38.4887886047],"type":"Point"}
}