{
  "type": "Feature",
  "properties": {
    "addr:full":"28 Shannon St Birdwood SA 5234",
    "addr:housenumber":"28",
    "addr:postcode":"5234",
    "addr:street":"Shannon St",
    "iso:country":"AU",
    "sg:address":"28 Shannon St",
    "sg:city":"Birdwood",
    "sg:classifiers":[
        {
            "category":"Shopping",
            "subcategory":"Antiques",
            "type":"Retail Goods"
        }
    ],
    "sg:phone":"+61 8 8568 5467",
    "sg:postcode":"5234",
    "sg:province":"SA",
    "wof:name":"Rose Cottage Antiques",
    "wof:placetype":"venue"
},
  "geometry": {"coordinates":[138.955688477,-34.8202934265],"type":"Point"}
}