{
  "type": "Feature",
  "properties": {
    "addr:full":"PO Box 301 Monarto South SA 5254",
    "addr:postcode":"5254",
    "iso:country":"AU",
    "sg:address":"PO Box 301",
    "sg:city":"Monarto South",
    "sg:classifiers":[
        {
            "category":"Shopping",
            "subcategory":"Pets & Pet Supplies",
            "type":"Retail Goods"
        }
    ],
    "sg:phone":"+61 8 8534 4129",
    "sg:postcode":"5254",
    "sg:province":"SA",
    "sg:tags":[
        "dog"
    ],
    "wof:name":"EZYCOAT",
    "wof:placetype":"venue"
},
  "geometry": {"coordinates":[139.13343810999999,-35.1181716919],"type":"Point"}
}