{
  "type": "Feature",
  "properties": {
    "iso:country":"AU",
    "sg:address":"77 Main St",
    "sg:city":"Gembrook",
    "sg:classifiers":[
        {
            "category":"Shopping",
            "subcategory":"Antiques",
            "type":"Retail Goods"
        }
    ],
    "sg:phone":"+61 3 5967 7050",
    "sg:postcode":"3783",
    "sg:province":"VIC",
    "wof:name":"Pandoras Box Antiques & Collectables",
    "wof:placetype":"venue"
},
  "geometry": {"coordinates":[145.55023199999999,-37.952576],"type":"Point"}
}