{
  "type": "Feature",
  "properties": {
    "addr:full":"46 Hickman St Winnellie NT 0820",
    "addr:housenumber":"46",
    "addr:postcode":"nt 0820",
    "addr:street":"Hickman St",
    "iso:country":"AU",
    "sg:address":"46 Hickman St",
    "sg:city":"Winnellie",
    "sg:classifiers":[
        {
            "category":"Building & Trades",
            "subcategory":"Construction",
            "type":"Services"
        }
    ],
    "sg:phone":"+61 8 8984 3582",
    "sg:postcode":"0820",
    "sg:province":"NT",
    "sg:tags":[
        "welding"
    ],
    "wof:name":"Fingers Aluminium",
    "wof:placetype":"venue"
},
  "geometry": {"coordinates":[130.87045288100001,-12.4289073944],"type":"Point"}
}