{
  "type": "Feature",
  "properties": {
    "addr:full":"55 Creswell St Campbell ACT 2612",
    "addr:housenumber":"55",
    "addr:postcode":"2612",
    "addr:street":"Creswell St",
    "iso:country":"AU",
    "sg:address":"55 Creswell St",
    "sg:city":"Campbell",
    "sg:classifiers":[
        {
            "category":"Education",
            "subcategory":"Special Training",
            "type":"Public Place"
        }
    ],
    "sg:phone":"+61 2 6247 7979",
    "sg:postcode":"2612",
    "sg:province":"ACT",
    "sg:tags":[
        "drama",
        "speech",
        "speaking",
        "tuition"
    ],
    "wof:name":"Lois Bogg",
    "wof:placetype":"venue"
},
  "geometry": {"coordinates":[149.147415161,-35.2867431641],"type":"Point"}
}