{
  "type": "Feature",
  "properties": {
    "iso:country":"AU",
    "sg:address":"Lakehaven Cntr Lakehaven Drv",
    "sg:city":"Gorokan",
    "sg:classifiers":[
        {
            "category":"Food & Beverages",
            "subcategory":"Supermarket",
            "type":"Retail Goods"
        }
    ],
    "sg:phone":"+61 2 4393 3051",
    "sg:postcode":"2263",
    "sg:province":"NSW",
    "sg:tags":[
        "grocery",
        "store"
    ],
    "wof:name":"Franklins Limited",
    "wof:placetype":"venue"
},
  "geometry": {"coordinates":[151.503555,-33.254799],"type":"Point"}
}