{
  "type": "Feature",
  "properties": {
    "addr:full":"180 High St Northcote VIC 3070",
    "addr:housenumber":"180",
    "addr:postcode":"3070",
    "addr:street":"High St",
    "iso:country":"AU",
    "sg:address":"180 High St",
    "sg:city":"Northcote",
    "sg:classifiers":[
        {
            "category":"Health Services",
            "subcategory":"Dentist",
            "type":"Services"
        }
    ],
    "sg:phone":"+61 3 9486 4455",
    "sg:postcode":"3070",
    "sg:province":"VIC",
    "wof:name":"Celebic Vukoslav Dr",
    "wof:placetype":"venue"
},
  "geometry": {"coordinates":[144.99801600000001,-37.775009],"type":"Point"}
}