{
  "type": "Feature",
  "properties": {
    "iso:country":"AU",
    "sg:address":"180 High St",
    "sg:city":"Northcote",
    "sg:classifiers":[
        {
            "category":"Health Services",
            "subcategory":"Dentist",
            "type":"Services"
        }
    ],
    "sg:phone":"+61 3 9486 4455",
    "sg:postcode":"3070",
    "sg:province":"VIC",
    "wof:name":"Celebic Vukoslav Dr",
    "wof:placetype":"venue"
},
  "geometry": {"coordinates":[144.998016,-37.775009],"type":"Point"}
}