{
  "type": "Feature",
  "properties": {
    "addr:full":"2975 Midland Hwy Newlyn VIC 3364",
    "addr:housenumber":"2975",
    "addr:postcode":"3364",
    "addr:street":"Midland Hwy",
    "iso:country":"AU",
    "sg:address":"2975 Midland Hwy",
    "sg:city":"Newlyn",
    "sg:classifiers":[
        {
            "category":"Farming",
            "subcategory":"Farm",
            "type":"Manufacturing & Wholesale Goods"
        }
    ],
    "sg:phone":"+61 3 5345 7375",
    "sg:postcode":"3364",
    "sg:province":"VIC",
    "sg:tags":[
        "farmer"
    ],
    "wof:name":"Miller L R",
    "wof:placetype":"venue"
},
  "geometry": {"coordinates":[143.97558593799999,-37.410369873],"type":"Point"}
}