{
  "type": "Feature",
  "properties": {
    "iso:country":"AU",
    "sg:address":"248 Hannan St",
    "sg:city":"Kalgoorlie",
    "sg:classifiers":[
        {
            "category":"Cafe",
            "type":"Food & Drink"
        }
    ],
    "sg:phone":"+61 8 9091 1095",
    "sg:postcode":"6430",
    "sg:province":"WA",
    "wof:name":"Hugo's Cafe Espresso",
    "wof:placetype":"venue"
},
  "geometry": {"coordinates":[121.469421387,-30.7500839233],"type":"Point"}
}