{
  "type": "Feature",
  "properties": {
    "iso:country":"AU",
    "sg:address":"20 Bambra St",
    "sg:city":"Lauderdale",
    "sg:classifiers":[
        {
            "category":"Building & Trades",
            "subcategory":"Construction",
            "type":"Services"
        }
    ],
    "sg:phone":"+61 3 6248 6249",
    "sg:postcode":"7021",
    "sg:province":"TAS",
    "sg:tags":[
        "plasterboard",
        "plasterer",
        "fixer"
    ],
    "wof:name":"Reading D G",
    "wof:placetype":"venue"
},
  "geometry": {"coordinates":[147.49786376899999,-42.8943710327],"type":"Point"}
}