{
  "type": "Feature",
  "properties": {
    "addr:full":"Lot 16 Albert St Junee NSW 2663",
    "addr:housenumber":"16",
    "addr:postcode":"2663",
    "addr:street":"Albert St",
    "iso:country":"AU",
    "sg:address":"Lot 16 Albert St",
    "sg:city":"Junee",
    "sg:classifiers":[
        {
            "category":"Building & Trades",
            "subcategory":"Construction",
            "type":"Services"
        }
    ],
    "sg:phone":"+61 413 158 358",
    "sg:postcode":"2663",
    "sg:province":"NSW",
    "sg:tags":[
        "brick",
        "paving"
    ],
    "wof:name":"Wholesale Sleeper Co.",
    "wof:placetype":"venue"
},
  "geometry": {"coordinates":[147.56813049300001,-34.8866386414],"type":"Point"}
}