{
  "type": "Feature",
  "properties": {
    "iso:country":"AU",
    "sg:address":"435 Stuart Drv",
    "sg:city":"Stuart",
    "sg:classifiers":[
        {
            "category":"Building & Trades",
            "subcategory":"Construction",
            "type":"Services"
        }
    ],
    "sg:phone":"+61 7 4778 2723",
    "sg:postcode":"4811",
    "sg:province":"QLD",
    "sg:tags":[
        "earth",
        "excavating",
        "moving",
        "contractor"
    ],
    "wof:name":"David Knight Skid Marks",
    "wof:placetype":"venue"
},
  "geometry": {"coordinates":[146.83215300000001,-19.339933],"type":"Point"}
}