{
  "type": "Feature",
  "properties": {
    "addr:full":"U3/ 9 Amherst St Cammeray NSW 2062",
    "addr:housenumber":"9",
    "addr:postcode":"2062",
    "addr:street":"U3 /;Amherst St",
    "iso:country":"AU",
    "sg:address":"U3/ 9 Amherst St",
    "sg:city":"Cammeray",
    "sg:classifiers":[
        {
            "category":"Organizations",
            "subcategory":"Professional Association",
            "type":"Services"
        }
    ],
    "sg:phone":"+61 425 297 432",
    "sg:postcode":"2062",
    "sg:province":"NSW",
    "sg:tags":[
        "web",
        "internet"
    ],
    "wof:name":"System Central Solutions",
    "wof:placetype":"venue"
},
  "geometry": {"coordinates":[151.21087646500001,-33.8229370117],"type":"Point"}
}