{
  "type": "Feature",
  "properties": {
    "iso:country":"AU",
    "sg:address":"Golf Club",
    "sg:city":"Surat",
    "sg:classifiers":[
        {
            "category":"Sports & Exercise",
            "subcategory":"Golf",
            "type":"Entertainment"
        }
    ],
    "sg:phone":"+61 7 4626 5258",
    "sg:postcode":"4417",
    "sg:province":"QLD",
    "sg:tags":[
        "club"
    ],
    "wof:name":"Surat Golf Club Inc",
    "wof:placetype":"venue"
},
  "geometry": {"coordinates":[149.064086914,-27.155166626],"type":"Point"}
}