{
  "type": "Feature",
  "properties": {
    "addr:full":"4 Wishart St Gwelup WA 6018",
    "addr:housenumber":"4",
    "addr:postcode":"6018",
    "addr:street":"Wishart St",
    "iso:country":"AU",
    "sg:address":"4 Wishart St",
    "sg:city":"Gwelup",
    "sg:classifiers":[
        {
            "category":"Building & Trades",
            "subcategory":"Construction",
            "type":"Services"
        }
    ],
    "sg:phone":"+61 408 926 494",
    "sg:postcode":"6018",
    "sg:province":"WA",
    "sg:tags":[
        "concrete",
        "treatment",
        "repair"
    ],
    "wof:name":"A1 Hitech Concrete Repair",
    "wof:placetype":"venue"
},
  "geometry": {"coordinates":[115.796913147,-31.8766155243],"type":"Point"}
}