{
  "type": "Feature",
  "properties": {
    "iso:country":"AU",
    "sg:address":"5- 7 Lorraine St",
    "sg:city":"Peakhurst",
    "sg:classifiers":[
        {
            "category":"Building & Trades",
            "subcategory":"Equipment Rental",
            "type":"Services"
        }
    ],
    "sg:phone":"+61 2 9533 5411",
    "sg:postcode":"2210",
    "sg:province":"NSW",
    "sg:tags":[
        "crane",
        "hire"
    ],
    "wof:name":"Robway Crane Safety Systems",
    "wof:placetype":"venue"
},
  "geometry": {"coordinates":[151.060913,-33.964035],"type":"Point"}
}