{
  "type": "Feature",
  "properties": {
    "iso:country":"AU",
    "sg:address":"23 Lawson Crs",
    "sg:city":"Thomastown",
    "sg:classifiers":[
        {
            "category":"Manufacturing",
            "subcategory":"Tobacco Products",
            "type":"Manufacturing & Wholesale Goods"
        }
    ],
    "sg:phone":"+61 3 9460 8394",
    "sg:postcode":"3074",
    "sg:province":"VIC",
    "sg:tags":[
        "polyethylene"
    ],
    "wof:name":"Jemseal Packaging Co Pty Ltd",
    "wof:placetype":"venue"
},
  "geometry": {"coordinates":[145.01148986800001,-37.6832199097],"type":"Point"}
}