{
  "type": "Feature",
  "properties": {
    "addr:full":"31 Railway Tce South St Lameroo SA 5302",
    "addr:housenumber":"31",
    "addr:postcode":"5302",
    "addr:street":"Railway Tce South St",
    "iso:country":"AU",
    "sg:address":"31 Railway Tce South St",
    "sg:city":"Lameroo",
    "sg:classifiers":[
        {
            "category":"Fast Food",
            "type":"Food & Drink"
        }
    ],
    "sg:phone":"+61 8 8576 3046",
    "sg:postcode":"5302",
    "sg:province":"SA",
    "sg:tags":[
        "away",
        "take"
    ],
    "wof:name":"Maynard L F",
    "wof:placetype":"venue"
},
  "geometry": {"coordinates":[140.396606445,-35.1552391052],"type":"Point"}
}