{
  "type": "Feature",
  "properties": {
    "addr:full":"220 Collins St Melbourne VIC 3000",
    "addr:housenumber":"220",
    "addr:postcode":"3000",
    "addr:street":"Collins St",
    "iso:country":"AU",
    "sg:address":"220 Collins St",
    "sg:city":"Melbourne",
    "sg:classifiers":[
        {
            "category":"Professional",
            "subcategory":"Business Services",
            "type":"Services"
        }
    ],
    "sg:phone":"+61 3 9650 4747",
    "sg:postcode":"3000",
    "sg:province":"VIC",
    "sg:tags":[
        "exporter"
    ],
    "wof:name":"Moregate Exports Pty Ltd",
    "wof:placetype":"venue"
},
  "geometry": {"coordinates":[144.96635437,-37.815410614],"type":"Point"}
}