{
  "type": "Feature",
  "properties": {
    "addr:full":"5 Hunter St Keilor VIC 3036",
    "addr:housenumber":"5",
    "addr:postcode":"3036",
    "addr:street":"Hunter St",
    "iso:country":"AU",
    "sg:address":"5 Hunter St",
    "sg:city":"Keilor",
    "sg:classifiers":[
        {
            "category":"Mining & Drilling",
            "type":"Manufacturing & Wholesale Goods"
        }
    ],
    "sg:phone":"+61 418 353 995",
    "sg:postcode":"3036",
    "sg:province":"VIC",
    "sg:tags":[
        "concrete",
        "breaking",
        "grinding",
        "sawing"
    ],
    "wof:name":"Able Concrete Sawing Pty Ltd",
    "wof:placetype":"venue"
},
  "geometry": {"coordinates":[144.835297,-37.721481],"type":"Point"}
}