{
  "type": "Feature",
  "properties": {
    "iso:country":"AU",
    "sg:address":"144 Jukes Rd",
    "sg:city":"Fawkner",
    "sg:classifiers":[
        {
            "category":"Health Services",
            "subcategory":"Health Practitioner",
            "type":"Services"
        }
    ],
    "sg:phone":"+61 3 9359 5260",
    "sg:postcode":"3060",
    "sg:province":"VIC",
    "sg:tags":[
        "psychologist"
    ],
    "wof:name":"Riaz Shagufta",
    "wof:placetype":"venue"
},
  "geometry": {"coordinates":[144.96403503400001,-37.7013282776],"type":"Point"}
}