{
  "type": "Feature",
  "properties": {
    "iso:country":"AU",
    "sg:address":"1/ 14 Lancaster St",
    "sg:city":"Ingleburn",
    "sg:classifiers":[
        {
            "category":"Personal",
            "subcategory":"Adult",
            "type":"Services"
        }
    ],
    "sg:phone":"+61 2 9829 3234",
    "sg:postcode":"2565",
    "sg:province":"NSW",
    "sg:tags":[
        "vic",
        "except",
        "state",
        "escort",
        "social",
        "qld"
    ],
    "wof:name":"Ingleburn Angels",
    "wof:placetype":"venue"
},
  "geometry": {"coordinates":[150.86480712900001,-33.9914245605],"type":"Point"}
}