{
  "type": "Feature",
  "properties": {
    "addr:full":"68 Hoskins St Mitchell ACT 2911",
    "addr:housenumber":"68",
    "addr:postcode":"2911",
    "addr:street":"Hoskins St",
    "iso:country":"AU",
    "sg:address":"68 Hoskins St",
    "sg:city":"Mitchell",
    "sg:classifiers":[
        {
            "category":"Home & Garden",
            "subcategory":"Garden Supply",
            "type":"Retail Goods"
        }
    ],
    "sg:phone":"+61 2 6241 7474",
    "sg:postcode":"2911",
    "sg:province":"ACT",
    "sg:tags":[
        "landscape"
    ],
    "wof:name":"Gungahlin Landscape Centre",
    "wof:placetype":"venue"
},
  "geometry": {"coordinates":[149.13815307600001,-35.2131347656],"type":"Point"}
}