{
  "type": "Feature",
  "properties": {
    "addr:full":"86 Poath Rd Hughesdale VIC 3166",
    "addr:housenumber":"86",
    "addr:postcode":"3166",
    "addr:street":"Poath Rd",
    "iso:country":"AU",
    "sg:address":"86 Poath Rd",
    "sg:city":"Hughesdale",
    "sg:classifiers":[
        {
            "category":"Personal",
            "subcategory":"Beauty Salon",
            "type":"Services"
        }
    ],
    "sg:phone":"+61 3 9568 2912",
    "sg:postcode":"3166",
    "sg:province":"VIC",
    "sg:tags":[
        "hairdresser"
    ],
    "wof:name":"Solutions For Hair",
    "wof:placetype":"venue"
},
  "geometry": {"coordinates":[145.077026367,-37.8940353394],"type":"Point"}
}