{
  "type": "Feature",
  "properties": {
    "addr:full":"Bells Reef Rd Maldon VIC 3463",
    "addr:postcode":"3463",
    "addr:street":"Reef Rd",
    "iso:country":"AU",
    "sg:address":"Bells Reef Rd",
    "sg:city":"Maldon",
    "sg:classifiers":[
        {
            "category":"Professional",
            "subcategory":"Business Services",
            "type":"Services"
        }
    ],
    "sg:phone":"+61 3 5475 2762",
    "sg:postcode":"3463",
    "sg:province":"VIC",
    "sg:tags":[
        "drafting"
    ],
    "wof:name":"Peter Laurie",
    "wof:placetype":"venue"
},
  "geometry": {"coordinates":[144.076416016,-36.9816322327],"type":"Point"}
}