{
  "type": "Feature",
  "properties": {
    "addr:full":"82 Ray Rd Mareeba QLD 4880",
    "addr:housenumber":"82",
    "addr:postcode":"4880",
    "addr:street":"Ray Rd",
    "iso:country":"AU",
    "sg:address":"82 Ray Rd",
    "sg:city":"Mareeba",
    "sg:classifiers":[
        {
            "category":"Commercial Area",
            "type":"Public Place"
        }
    ],
    "sg:phone":"+61 7 4092 2531",
    "sg:postcode":"4880",
    "sg:province":"QLD",
    "sg:tags":[
        "heavy",
        "carrier"
    ],
    "wof:name":"Harris Transport",
    "wof:placetype":"venue"
},
  "geometry": {"coordinates":[145.41912841800001,-17.03008461],"type":"Point"}
}