{
  "type": "Feature",
  "properties": {
    "iso:country":"AU",
    "sg:address":"14 Warattah Crt",
    "sg:city":"Wurtulla",
    "sg:classifiers":[
        {
            "category":"Utilities",
            "subcategory":"Electric",
            "type":"Services"
        }
    ],
    "sg:phone":"+61 7 5493 9585",
    "sg:postcode":"4575",
    "sg:province":"QLD",
    "sg:tags":[
        "electrical",
        "contractor"
    ],
    "wof:name":"Geoff Catto Electrical",
    "wof:placetype":"venue"
},
  "geometry": {"coordinates":[153.132736,-26.750923],"type":"Point"}
}