{
  "type": "Feature",
  "properties": {
    "addr:full":"123 Barkly St Ararat VIC 3377",
    "addr:housenumber":"123",
    "addr:postcode":"3377",
    "addr:street":"Barkly St",
    "iso:country":"AU",
    "sg:address":"123 Barkly St",
    "sg:city":"Ararat",
    "sg:classifiers":[
        {
            "category":"Shopping",
            "subcategory":"Music",
            "type":"Retail Goods"
        }
    ],
    "sg:phone":"+61 3 5352 1244",
    "sg:postcode":"3377",
    "sg:province":"VIC",
    "sg:tags":[
        "store"
    ],
    "wof:name":"Ararat Records & Tapes",
    "wof:placetype":"venue"
},
  "geometry": {"coordinates":[142.929321289,-37.2839355469],"type":"Point"}
}