{
  "type": "Feature",
  "properties": {
    "addr:full":"152 Otho St Inverell NSW 2360",
    "addr:housenumber":"152",
    "addr:postcode":"2360",
    "addr:street":"Otho St",
    "iso:country":"AU",
    "sg:address":"152 Otho St",
    "sg:city":"Inverell",
    "sg:classifiers":[
        {
            "category":"Health Services",
            "subcategory":"Doctor",
            "type":"Services"
        }
    ],
    "sg:phone":"+61 2 6721 9777",
    "sg:postcode":"2360",
    "sg:province":"NSW",
    "sg:tags":[
        "medical",
        "practitioner"
    ],
    "wof:name":"Armajun Aboriginal Health Services",
    "wof:placetype":"venue"
},
  "geometry": {"coordinates":[151.11581420900001,-29.7781677246],"type":"Point"}
}