{
  "type": "Feature",
  "properties": {
    "iso:country":"AU",
    "sg:address":"Norwood Centre 1 Andrea St St",
    "sg:city":"Albans",
    "sg:classifiers":[
        {
            "category":"Organizations",
            "subcategory":"Non-profit Organization",
            "type":"Services"
        }
    ],
    "sg:phone":"+61 3 9310 7166",
    "sg:postcode":"3021",
    "sg:province":"VIC",
    "sg:tags":[
        "support",
        "disability",
        "organisation"
    ],
    "wof:name":"Norwood Association Incorporated",
    "wof:placetype":"venue"
},
  "geometry": {"coordinates":[144.798447,-37.747967],"type":"Point"}
}