{
  "type": "Feature",
  "properties": {
    "addr:full":"100 Hammond Ave Wagga Wagga NSW 2650",
    "addr:housenumber":"100",
    "addr:postcode":"2650",
    "addr:street":"Hammond Ave",
    "iso:country":"AU",
    "sg:address":"100 Hammond Ave",
    "sg:city":"Wagga Wagga",
    "sg:classifiers":[
        {
            "category":"Building & Trades",
            "subcategory":"Construction",
            "type":"Services"
        }
    ],
    "sg:phone":"+61 2 6971 8200",
    "sg:postcode":"2650",
    "sg:province":"NSW",
    "sg:tags":[
        "installation",
        "air conditioning"
    ],
    "wof:name":"Craig Stewart Electrical Pty Ltd",
    "wof:placetype":"venue"
},
  "geometry": {"coordinates":[147.395385742,-35.1226806641],"type":"Point"}
}