{
  "type": "Feature",
  "properties": {
    "iso:country":"AU",
    "sg:address":"13 Letitia Rd",
    "sg:city":"Fingal Head",
    "sg:classifiers":[
        {
            "category":"Health Services",
            "subcategory":"Health Practitioner",
            "type":"Services"
        }
    ],
    "sg:phone":"+61 7 5523 4236",
    "sg:postcode":"2487",
    "sg:province":"NSW",
    "sg:tags":[
        "naturopath"
    ],
    "wof:name":"Webster Robyn",
    "wof:placetype":"venue"
},
  "geometry": {"coordinates":[153.55856323200001,-28.189622879],"type":"Point"}
}