{
  "type": "Feature",
  "properties": {
    "addr:full":"Barlee St Busselton WA 6280",
    "addr:postcode":"6280",
    "addr:street":"Barlee St",
    "iso:country":"AU",
    "sg:address":"Barlee St",
    "sg:city":"Busselton",
    "sg:classifiers":[
        {
            "category":"Retail",
            "subcategory":"Auto Repair",
            "type":"Services"
        }
    ],
    "sg:phone":"+61 8 9752 4800",
    "sg:postcode":"6280",
    "sg:province":"WA",
    "sg:tags":[
        "beater",
        "painter",
        "panel"
    ],
    "wof:name":"James Smash Repairs",
    "wof:placetype":"venue"
},
  "geometry": {"coordinates":[115.345497131,-33.6607627869],"type":"Point"}
}