{
  "type": "Feature",
  "properties": {
    "iso:country":"AU",
    "sg:address":"Shp 1/ 31 Roscoe St",
    "sg:city":"Holland Park",
    "sg:classifiers":[
        {
            "category":"Building & Trades",
            "subcategory":"Construction",
            "type":"Services"
        }
    ],
    "sg:phone":"+61 7 3219 1140",
    "sg:postcode":"4121",
    "sg:province":"QLD",
    "sg:tags":[
        "contractor"
    ],
    "wof:name":"Roslin Builders Pty Ltd",
    "wof:placetype":"venue"
},
  "geometry": {"coordinates":[153.07054138199999,-27.5234661102],"type":"Point"}
}