{
  "type": "Feature",
  "properties": {
    "iso:country":"AU",
    "sg:address":"25- 27 Hay St",
    "sg:city":"Port Macquarie",
    "sg:classifiers":[
        {
            "category":"Real Estate",
            "subcategory":"Surveying",
            "type":"Services"
        }
    ],
    "sg:phone":"+61 2 6586 2555",
    "sg:postcode":"2444",
    "sg:province":"NSW",
    "sg:tags":[
        "surveyor",
        "land"
    ],
    "wof:name":"King & Campbell Pty. Ltd.",
    "wof:placetype":"venue"
},
  "geometry": {"coordinates":[152.90939299999999,-31.430124],"type":"Point"}
}