{
  "type": "Feature",
  "properties": {
    "addr:full":"41 High St Boonah QLD 4310",
    "addr:housenumber":"41",
    "addr:postcode":"4310",
    "addr:street":"High St",
    "iso:country":"AU",
    "sg:address":"41 High St",
    "sg:city":"Boonah",
    "sg:classifiers":[
        {
            "category":"Professional",
            "subcategory":"Employment Agencies",
            "type":"Services"
        }
    ],
    "sg:phone":"+61 7 5463 1168",
    "sg:postcode":"4310",
    "sg:province":"QLD",
    "sg:tags":[
        "provider",
        "internet"
    ],
    "wof:name":"Ozsell.com",
    "wof:placetype":"venue"
},
  "geometry": {"coordinates":[152.682174683,-27.9969367981],"type":"Point"}
}