{
  "type": "Feature",
  "properties": {
    "iso:country":"AU",
    "sg:address":"Unit 6/ 17 Rob Pl",
    "sg:city":"Vineyard",
    "sg:classifiers":[
        {
            "category":"Manufacturing",
            "subcategory":"Printing",
            "type":"Manufacturing & Wholesale Goods"
        }
    ],
    "sg:phone":"+61 2 4577 7077",
    "sg:postcode":"2765",
    "sg:province":"NSW",
    "sg:tags":[
        "wholesaler",
        "mfrs",
        "greeting",
        "card"
    ],
    "wof:name":"Dewcard Australia",
    "wof:placetype":"venue"
},
  "geometry": {"coordinates":[150.84136962900001,-33.6315879822],"type":"Point"}
}