{
  "type": "Feature",
  "properties": {
    "addr:full":"92 Daws Rd Edwardstown SA 5039",
    "addr:housenumber":"92",
    "addr:postcode":"5039",
    "addr:street":"Daws Rd",
    "iso:country":"AU",
    "sg:address":"92 Daws Rd",
    "sg:city":"Edwardstown",
    "sg:classifiers":[
        {
            "category":"Retail",
            "subcategory":"Auto Repair",
            "type":"Services"
        }
    ],
    "sg:phone":"+61 8 8277 0999",
    "sg:postcode":"5039",
    "sg:province":"SA",
    "sg:tags":[
        "electrical"
    ],
    "wof:name":"Warren Wilson Auto Electrics",
    "wof:placetype":"venue"
},
  "geometry": {"coordinates":[138.573486328,-34.9926643372],"type":"Point"}
}