{
  "type": "Feature",
  "properties": {
    "addr:full":"153 Pendennis Rd Tamborine QLD 4270",
    "addr:housenumber":"153",
    "addr:postcode":"4270",
    "addr:street":"Pendennis Rd",
    "iso:country":"AU",
    "sg:address":"153 Pendennis Rd",
    "sg:city":"Tamborine",
    "sg:classifiers":[
        {
            "category":"Banks & Credit Unions",
            "subcategory":"Investment Brokerage",
            "type":"Services"
        }
    ],
    "sg:phone":"+61 7 5543 8167",
    "sg:postcode":"4270",
    "sg:province":"QLD",
    "sg:tags":[
        "care",
        "day",
        "family",
        "child"
    ],
    "wof:name":"In Home Childcare Services",
    "wof:placetype":"venue"
},
  "geometry": {"coordinates":[153.09085082999999,-27.8559913635],"type":"Point"}
}