{
  "type": "Feature",
  "properties": {
    "addr:full":"Shop 1a, Ormiston Village Mkt Wellington St Ormiston QLD 4160",
    "addr:housenumber":"shop 1a",
    "addr:postcode":"4160",
    "addr:street":"Wellington St",
    "iso:country":"AU",
    "sg:address":"Shop 1a, Ormiston Village Mkt Wellington St",
    "sg:city":"Ormiston",
    "sg:classifiers":[
        {
            "category":"Food & Beverages",
            "subcategory":"Liquor & Beverages",
            "type":"Retail Goods"
        }
    ],
    "sg:phone":"+61 7 3286 7532",
    "sg:postcode":"4160",
    "sg:province":"QLD",
    "sg:tags":[
        "store"
    ],
    "wof:name":"Ormiston Cellars",
    "wof:placetype":"venue"
},
  "geometry": {"coordinates":[153.25660705600001,-27.5124950409],"type":"Point"}
}