{
  "type": "Feature",
  "properties": {
    "iso:country":"AU",
    "sg:address":"47 Mountford Ave",
    "sg:city":"Guildford",
    "sg:classifiers":[
        {
            "category":"Building & Trades",
            "subcategory":"Cleaning & Sanitation",
            "type":"Services"
        }
    ],
    "sg:phone":"+61 2 9632 7993",
    "sg:postcode":"2161",
    "sg:province":"NSW",
    "sg:tags":[
        "industrial",
        "commercial",
        "contractor"
    ],
    "wof:name":"Longreach Cleaning Services",
    "wof:placetype":"venue"
},
  "geometry": {"coordinates":[150.99053955100001,-33.8524665833],"type":"Point"}
}