{
  "type": "Feature",
  "properties": {
    "addr:full":"6 Doyle St Goodooga NSW 2831",
    "addr:housenumber":"6",
    "addr:postcode":"2831",
    "addr:street":"Doyle St",
    "iso:country":"AU",
    "sg:address":"6 Doyle St",
    "sg:city":"Goodooga",
    "sg:classifiers":[
        {
            "category":"Social Services",
            "subcategory":"Child Care",
            "type":"Services"
        }
    ],
    "sg:phone":"+61 2 6829 6260",
    "sg:postcode":"2831",
    "sg:province":"NSW",
    "wof:name":"Goodooga Pre-School Inc",
    "wof:placetype":"venue"
},
  "geometry": {"coordinates":[147.45469665499999,-29.1138153076],"type":"Point"}
}