{
  "type": "Feature",
  "properties": {
    "addr:full":"41 Plateau Rd Avalon NSW 2107",
    "addr:housenumber":"41",
    "addr:postcode":"2107",
    "addr:street":"Plateau Rd",
    "iso:country":"AU",
    "sg:address":"41 Plateau Rd",
    "sg:city":"Avalon",
    "sg:classifiers":[
        {
            "category":"Communications",
            "subcategory":"News Services",
            "type":"Services"
        }
    ],
    "sg:phone":"+61 2 9918 9340",
    "sg:postcode":"2107",
    "sg:province":"NSW",
    "sg:tags":[
        "information",
        "tourist",
        "attractions"
    ],
    "wof:name":"HOME AND AWAY TOURS",
    "wof:placetype":"venue"
},
  "geometry": {"coordinates":[151.32386779800001,-33.6420097351],"type":"Point"}
}