{
  "type": "Feature",
  "properties": {
    "addr:full":"Suite 13, 51 Spring St Bondi Junction NSW 2022",
    "addr:housenumber":"51",
    "addr:postcode":"2022",
    "addr:street":"Spring St",
    "iso:country":"AU",
    "sg:address":"Suite 13, 51 Spring St",
    "sg:city":"Bondi Junction",
    "sg:classifiers":[
        {
            "category":"Professional",
            "subcategory":"Business Services",
            "type":"Services"
        }
    ],
    "sg:phone":"+61 2 9386 9494",
    "sg:postcode":"2022",
    "sg:province":"NSW",
    "sg:tags":[
        "management",
        "event"
    ],
    "wof:name":"Tp Events",
    "wof:placetype":"venue"
},
  "geometry": {"coordinates":[151.24781799300001,-33.8924369812],"type":"Point"}
}