{
  "type": "Feature",
  "properties": {
    "addr:full":"475 Kingston Rd Kingston QLD 4114",
    "addr:housenumber":"475",
    "addr:postcode":"4114",
    "addr:street":"Kingston Rd",
    "iso:country":"AU",
    "sg:address":"475 Kingston Rd",
    "sg:city":"Kingston",
    "sg:classifiers":[
        {
            "category":"Retail",
            "subcategory":"Storage",
            "type":"Services"
        }
    ],
    "sg:phone":"+61 7 3386 0777",
    "sg:postcode":"4114",
    "sg:province":"QLD",
    "wof:name":"Storage King",
    "wof:placetype":"venue"
},
  "geometry": {"coordinates":[153.11805725100001,-27.6616973877],"type":"Point"}
}