{
  "type": "Feature",
  "properties": {
    "iso:country":"AU",
    "sg:address":"1175 South Rd",
    "sg:city":"St Marys",
    "sg:classifiers":[
        {
            "category":"Food & Beverages",
            "subcategory":"Bakery",
            "type":"Retail Goods"
        }
    ],
    "sg:phone":"+61 8 8357 5911",
    "sg:postcode":"5042",
    "sg:province":"SA",
    "sg:tags":[
        "baker"
    ],
    "wof:name":"Brumby's Bakeries",
    "wof:placetype":"venue"
},
  "geometry": {"coordinates":[138.57548499999999,-34.998066],"type":"Point"}
}