{
  "type": "Feature",
  "properties": {
    "addr:full":"39 Fulham Rd Pimlico QLD 4812",
    "addr:housenumber":"39",
    "addr:postcode":"4812",
    "addr:street":"Fulham Rd",
    "iso:country":"AU",
    "sg:address":"39 Fulham Rd",
    "sg:city":"Pimlico",
    "sg:classifiers":[
        {
            "category":"Health Services",
            "subcategory":"Doctor",
            "type":"Services"
        }
    ],
    "sg:phone":"+61 7 4725 7003",
    "sg:postcode":"4812",
    "sg:province":"QLD",
    "sg:tags":[
        "medical",
        "practitioner"
    ],
    "wof:name":"Rogers Dr John(Psychiatrist)",
    "wof:placetype":"venue"
},
  "geometry": {"coordinates":[146.78619399999999,-19.289068],"type":"Point"}
}