{
  "type": "Feature",
  "properties": {
    "addr:full":"5 Mineral Rd Oak Flats NSW 2529",
    "addr:housenumber":"5",
    "addr:postcode":"2529",
    "addr:street":"Mineral Rd",
    "iso:country":"AU",
    "sg:address":"5 Mineral Rd",
    "sg:city":"Oak Flats",
    "sg:classifiers":[
        {
            "category":"Shopping",
            "subcategory":"Crafts & Fabrics",
            "type":"Retail Goods"
        }
    ],
    "sg:phone":"+61 2 4257 1888",
    "sg:postcode":"2529",
    "sg:province":"NSW",
    "sg:tags":[
        "synthetic",
        "canvas",
        "product"
    ],
    "wof:name":"Enviro-Tarps Australia Pty Ltd",
    "wof:placetype":"venue"
},
  "geometry": {"coordinates":[150.81022644000001,-34.566116333],"type":"Point"}
}