{
  "type": "Feature",
  "properties": {
    "addr:full":"8 Lukas Ave Kenthurst NSW 2156",
    "addr:housenumber":"8",
    "addr:postcode":"2156",
    "addr:street":"Lukas Ave",
    "iso:country":"AU",
    "sg:address":"8 Lukas Ave",
    "sg:city":"Kenthurst",
    "sg:classifiers":[
        {
            "category":"Shopping",
            "subcategory":"Antiques",
            "type":"Retail Goods"
        }
    ],
    "sg:phone":"+61 414 654 104",
    "sg:postcode":"2156",
    "sg:province":"NSW",
    "wof:name":"Enchantment Antiques",
    "wof:placetype":"venue"
},
  "geometry": {"coordinates":[151.00514221200001,-33.6641082764],"type":"Point"}
}