{
  "type": "Feature",
  "properties": {
    "addr:full":"71 Fitzwilliam Drv Sippy Downs QLD 4556",
    "addr:housenumber":"71",
    "addr:postcode":"4556",
    "addr:street":"Fitzwilliam Drv",
    "iso:country":"AU",
    "sg:address":"71 Fitzwilliam Drv",
    "sg:city":"Sippy Downs",
    "sg:classifiers":[
        {
            "category":"Industrial Area",
            "type":"Public Place"
        }
    ],
    "sg:phone":"+61 7 5476 1717",
    "sg:postcode":"4556",
    "sg:province":"QLD",
    "sg:tags":[
        "rural",
        "shed"
    ],
    "sg:website":"http://www.aus-steel.com.au",
    "wof:name":"Sunshine Steel Building Systems",
    "wof:placetype":"venue"
},
  "geometry": {"coordinates":[153.07232665999999,-26.7268390656],"type":"Point"}
}