{
  "type": "Feature",
  "properties": {
    "addr:full":"36 Castlereagh St Coonamble NSW 2829",
    "addr:housenumber":"36",
    "addr:postcode":"2829",
    "addr:street":"Castlereagh St",
    "iso:country":"AU",
    "sg:address":"36 Castlereagh St",
    "sg:city":"Coonamble",
    "sg:classifiers":[
        {
            "category":"Cafe",
            "type":"Food & Drink"
        }
    ],
    "sg:phone":"+61 2 6822 2013",
    "sg:postcode":"2829",
    "sg:province":"NSW",
    "wof:name":"Gumnut Cafe The",
    "wof:placetype":"venue"
},
  "geometry": {"coordinates":[148.388473511,-30.9528884888],"type":"Point"}
}