{
  "type": "Feature",
  "properties": {
    "addr:full":"6a / 46 Mt Gravatt-Capalaba Rd Upper Mt Gravatt QLD 4122",
    "addr:housenumber":"6a / 46",
    "addr:postcode":"4122",
    "addr:street":"Mt Gravatt-Capalaba Rd Upper",
    "iso:country":"AU",
    "sg:address":"6a / 46 Mt Gravatt-Capalaba Rd",
    "sg:city":"Upper Mt Gravatt",
    "sg:classifiers":[
        {
            "category":"Real Estate",
            "subcategory":"Real Estate Agent",
            "type":"Services"
        }
    ],
    "sg:phone":"+61 7 3349 3370",
    "sg:postcode":"4122",
    "sg:province":"QLD",
    "wof:name":"Ray White Mt Gravatt / Garden City",
    "wof:placetype":"venue"
},
  "geometry": {"coordinates":[153.08065795900001,-27.5593204498],"type":"Point"}
}