{
  "type": "Feature",
  "properties": {
    "addr:full":"130 Main South Rd Morphett Vale SA 5162",
    "addr:housenumber":"130",
    "addr:postcode":"5162",
    "addr:street":"Main South Rd",
    "iso:country":"AU",
    "sg:address":"130 Main South Rd",
    "sg:city":"Morphett Vale",
    "sg:classifiers":[
        {
            "category":"Retail",
            "subcategory":"Veterinary Services",
            "type":"Services"
        }
    ],
    "sg:phone":"+61 8 8382 3666",
    "sg:postcode":"5162",
    "sg:province":"SA",
    "sg:tags":[
        "surgeon"
    ],
    "wof:name":"Jackson Rachael",
    "wof:placetype":"venue"
},
  "geometry": {"coordinates":[138.523895264,-35.1271781921],"type":"Point"}
}