{
  "type": "Feature",
  "properties": {
    "iso:country":"AU",
    "sg:address":"59 Harris Rd",
    "sg:city":"Elliminyt",
    "sg:classifiers":[
        {
            "category":"Professional",
            "subcategory":"Computer Services",
            "type":"Services"
        }
    ],
    "sg:phone":"+61 3 5231 5125",
    "sg:postcode":"3249",
    "sg:province":"VIC",
    "sg:tags":[
        "equipment",
        "networking",
        "installation"
    ],
    "wof:name":"Burrell Computer Systems",
    "wof:placetype":"venue"
},
  "geometry": {"coordinates":[143.58480835,-38.3677711487],"type":"Point"}
}