{
  "type": "Feature",
  "properties": {
    "addr:full":"Hardys Rd Tallangatta VIC 3700",
    "addr:postcode":"3700",
    "addr:street":"Hardys Rd",
    "iso:country":"AU",
    "sg:address":"Hardys Rd",
    "sg:city":"Tallangatta",
    "sg:classifiers":[
        {
            "category":"Building & Trades",
            "subcategory":"Landscaping Services",
            "type":"Services"
        }
    ],
    "sg:phone":"+61 2 6071 2691",
    "sg:postcode":"3700",
    "sg:province":"VIC",
    "sg:tags":[
        "grazier"
    ],
    "wof:name":"Maddock K O",
    "wof:placetype":"venue"
},
  "geometry": {"coordinates":[147.16000366200001,-36.2362594604],"type":"Point"}
}