{
  "type": "Feature",
  "properties": {
    "iso:country":"AU",
    "sg:address":"3 Gallipoli Rd",
    "sg:city":"Coffs Harbour",
    "sg:classifiers":[
        {
            "category":"Personal",
            "subcategory":"Beauty Salon",
            "type":"Services"
        }
    ],
    "sg:phone":"+61 2 6651 1650",
    "sg:postcode":"2450",
    "sg:province":"NSW",
    "wof:name":"Ann Hobsons Beauty Therapy",
    "wof:placetype":"venue"
},
  "geometry": {"coordinates":[153.113693,-30.297731],"type":"Point"}
}