{
  "type": "Feature",
  "properties": {
    "addr:full":"264 Manningham Rd Templestowe Lower VIC 3107",
    "addr:housenumber":"264",
    "addr:postcode":"3107",
    "addr:street":"Manningham Rd",
    "iso:country":"AU",
    "sg:address":"264 Manningham Rd",
    "sg:city":"Templestowe Lower",
    "sg:classifiers":[
        {
            "category":"Health Services",
            "subcategory":"Health Practitioner",
            "type":"Services"
        }
    ],
    "sg:phone":"+61 3 9852 3811",
    "sg:postcode":"3107",
    "sg:province":"VIC",
    "sg:tags":[
        "naturopath"
    ],
    "wof:name":"Ding Steven",
    "wof:placetype":"venue"
},
  "geometry": {"coordinates":[145.10949707,-37.7732391357],"type":"Point"}
}