{
  "type": "Feature",
  "properties": {
    "addr:full":"Shp8/ 470 High St Maitland NSW 2320",
    "addr:housenumber":"470",
    "addr:postcode":"2320",
    "addr:street":"High St",
    "iso:country":"AU",
    "sg:address":"Shp8/ 470 High St",
    "sg:city":"Maitland",
    "sg:classifiers":[
        {
            "category":"Professional",
            "subcategory":"Computer Services",
            "type":"Services"
        }
    ],
    "sg:phone":"+61 2 4934 5955",
    "sg:postcode":"2320",
    "sg:province":"NSW",
    "sg:tags":[
        "equipment",
        "networking",
        "installation"
    ],
    "wof:name":"About Time Computer Solutions",
    "wof:placetype":"venue"
},
  "geometry": {"coordinates":[151.55325317399999,-32.730796814],"type":"Point"}
}