{
  "type": "Feature",
  "properties": {
    "iso:country":"AU",
    "sg:address":"76 Regal Drv",
    "sg:city":"Thornlie",
    "sg:classifiers":[
        {
            "category":"Retail",
            "subcategory":"Auto Rental",
            "type":"Services"
        }
    ],
    "sg:phone":"+61 437 700 111",
    "sg:postcode":"6108",
    "sg:province":"WA",
    "sg:tags":[
        "chauffeur",
        "car",
        "hire",
        "driven",
        "limousine"
    ],
    "wof:name":"Allegiance Limousines",
    "wof:placetype":"venue"
},
  "geometry": {"coordinates":[115.962997437,-32.0674667358],"type":"Point"}
}