{
  "type": "Feature",
  "properties": {
    "addr:full":"66-72 Mercedes Drv Thomastown VIC 3074",
    "addr:housenumber":"66-72",
    "addr:postcode":"3074",
    "addr:street":"Mercedes Drv",
    "iso:country":"AU",
    "sg:address":"66-72 Mercedes Drv",
    "sg:city":"Thomastown",
    "sg:classifiers":[
        {
            "category":"Wholesale",
            "subcategory":"Drugs",
            "type":"Manufacturing & Wholesale Goods"
        }
    ],
    "sg:phone":"+61 3 9465 5033",
    "sg:postcode":"3074",
    "sg:province":"VIC",
    "sg:tags":[
        "wholesaler",
        "pharmaceutical",
        "product",
        "mfrs"
    ],
    "wof:name":"Cottons Pty Ltd",
    "wof:placetype":"venue"
},
  "geometry": {"coordinates":[145.04470825199999,-37.6891136169],"type":"Point"}
}