{
  "type": "Feature",
  "properties": {
    "addr:full":"85 King William Rd Unley SA 5061",
    "addr:housenumber":"85",
    "addr:postcode":"5061",
    "addr:street":"King William Rd",
    "iso:country":"AU",
    "sg:address":"85 King William Rd",
    "sg:city":"Unley",
    "sg:classifiers":[
        {
            "category":"Banks & Credit Unions",
            "subcategory":"Financial Services",
            "type":"Services"
        }
    ],
    "sg:phone":"+61 8 8272 0959",
    "sg:postcode":"5061",
    "sg:province":"SA",
    "sg:tags":[
        "annuity",
        "rollover",
        "superannuation",
        "consultant"
    ],
    "wof:name":"Superannuation Consulting & Advisory Service Pty Ltd",
    "wof:placetype":"venue"
},
  "geometry": {"coordinates":[138.60661315900001,-34.9411354065],"type":"Point"}
}