{
  "type": "Feature",
  "properties": {
    "addr:full":"100 Furlong Rd Cairnlea VIC 3023",
    "addr:housenumber":"100",
    "addr:postcode":"3023",
    "addr:street":"Furlong Rd",
    "iso:country":"AU",
    "sg:address":"100 Furlong Rd",
    "sg:city":"Cairnlea",
    "sg:classifiers":[
        {
            "category":"Personal",
            "subcategory":"Beauty Salon",
            "type":"Services"
        }
    ],
    "sg:phone":"+61 3 9361 2300",
    "sg:postcode":"3023",
    "sg:province":"VIC",
    "wof:name":"L'Ambyounce Beauty & Spa",
    "wof:placetype":"venue"
},
  "geometry": {"coordinates":[144.78851299999999,-37.758389],"type":"Point"}
}