{
  "type": "Feature",
  "properties": {
    "addr:full":"8/ 13-25 Sedhurst St Coopers Plains QLD 4108",
    "addr:housenumber":"/ 13-25",
    "addr:postcode":"4108",
    "addr:street":"Sedhurst St",
    "iso:country":"AU",
    "sg:address":"8/ 13-25 Sedhurst St",
    "sg:city":"Coopers Plains",
    "sg:classifiers":[
        {
            "category":"Building & Trades",
            "subcategory":"Plumbing",
            "type":"Services"
        }
    ],
    "sg:phone":"+61 7 3345 7395",
    "sg:postcode":"4108",
    "sg:province":"QLD",
    "sg:tags":[
        "equipment",
        "valves"
    ],
    "wof:name":"C M W-B V A Valves",
    "wof:placetype":"venue"
},
  "geometry": {"coordinates":[153.03585815400001,-27.5712509155],"type":"Point"}
}