{
  "type": "Feature",
  "properties": {
    "addr:full":"Cuthill St Randwick NSW 2031",
    "addr:postcode":"2031",
    "addr:street":"Cuthill St",
    "iso:country":"AU",
    "sg:address":"Cuthill St",
    "sg:city":"Randwick",
    "sg:classifiers":[
        {
            "category":"Travel",
            "subcategory":"Hotels & Motels",
            "type":"Entertainment"
        }
    ],
    "sg:phone":"+61 2 9399 3006",
    "sg:postcode":"2031",
    "sg:province":"NSW",
    "sg:tags":[
        "accommodation"
    ],
    "wof:name":"Royal Hotel Randwick",
    "wof:placetype":"venue"
},
  "geometry": {"coordinates":[151.24154663100001,-33.9181289673],"type":"Point"}
}