{
  "type": "Feature",
  "properties": {
    "addr:full":"96 South Pde Auburn NSW 2144",
    "addr:housenumber":"96",
    "addr:postcode":"2144",
    "addr:street":"South Pde",
    "iso:country":"AU",
    "sg:address":"96 South Pde",
    "sg:city":"Auburn",
    "sg:classifiers":[
        {
            "category":"Professional",
            "subcategory":"Accounting & Tax Preparation",
            "type":"Services"
        }
    ],
    "sg:phone":"+61 2 9646 4344",
    "sg:postcode":"2144",
    "sg:province":"NSW",
    "sg:tags":[
        "accountant",
        "auditor"
    ],
    "wof:name":"McGuren & Associates",
    "wof:placetype":"venue"
},
  "geometry": {"coordinates":[151.03187560999999,-33.8489341736],"type":"Point"}
}