{
  "type": "Feature",
  "properties": {
    "addr:full":"Western Hwy Dadswells Bridge VIC 3385",
    "addr:postcode":"3385",
    "addr:street":"Western Hwy",
    "iso:country":"AU",
    "sg:address":"Western Hwy",
    "sg:city":"Dadswells Bridge",
    "sg:classifiers":[
        {
            "category":"Farming",
            "subcategory":"Poultry Farm",
            "type":"Manufacturing & Wholesale Goods"
        }
    ],
    "sg:phone":"+61 3 5359 5220",
    "sg:postcode":"3385",
    "sg:province":"VIC",
    "sg:tags":[
        "farmer"
    ],
    "wof:name":"Deutscher's Turkey Farm",
    "wof:placetype":"venue"
},
  "geometry": {"coordinates":[142.51414489699999,-36.9177284241],"type":"Point"}
}