{
  "type": "Feature",
  "properties": {
    "iso:country":"AU",
    "sg:address":"Masterhead Drv",
    "sg:city":"Cleveland",
    "sg:classifiers":[
        {
            "category":"Autos & Motor Vehicles",
            "subcategory":"Boat Sales",
            "type":"Retail Goods"
        }
    ],
    "sg:phone":"+61 7 3821 4144",
    "sg:postcode":"4163",
    "sg:province":"QLD",
    "sg:tags":[
        "yacht"
    ],
    "wof:name":"Peter Hansen Yacht Brokers",
    "wof:placetype":"venue"
},
  "geometry": {"coordinates":[153.26957702600001,-27.5245246887],"type":"Point"}
}