{
  "type": "Feature",
  "properties": {
    "addr:full":"Shp 4/ 39 East Esp Manly NSW 2095",
    "addr:housenumber":"/ 39",
    "addr:postcode":"2095",
    "addr:street":"East Esp",
    "iso:country":"AU",
    "sg:address":"Shp 4/ 39",
    "sg:city":"East Esp Manly",
    "sg:classifiers":[
        {
            "category":"Retail",
            "subcategory":"Self-service Laundry",
            "type":"Services"
        }
    ],
    "sg:phone":"+61 2 9977 0989",
    "sg:postcode":"2095",
    "sg:province":"NSW",
    "wof:name":"Come Clean & Chat Pty Ltd",
    "wof:placetype":"venue"
},
  "geometry": {"coordinates":[151.28582763700001,-33.799911499],"type":"Point"}
}