{
  "type": "Feature",
  "properties": {
    "addr:full":"25 Russell St Cleveland QLD 4163",
    "addr:housenumber":"25",
    "addr:postcode":"4163",
    "addr:street":"Russell St",
    "iso:country":"AU",
    "sg:address":"25 Russell St",
    "sg:city":"Cleveland",
    "sg:classifiers":[
        {
            "category":"Retail",
            "subcategory":"Auto Repair",
            "type":"Services"
        }
    ],
    "sg:phone":"+61 7 3286 1996",
    "sg:postcode":"4163",
    "sg:province":"QLD",
    "sg:tags":[
        "beater",
        "painter",
        "panel"
    ],
    "wof:name":"Cleveland Auto Accident Centre",
    "wof:placetype":"venue"
},
  "geometry": {"coordinates":[153.278640747,-27.5304889679],"type":"Point"}
}