{
  "type": "Feature",
  "properties": {
    "addr:full":"Unit 3/ 21- 23 Daniel St Wetherill Park NSW 2164",
    "addr:housenumber":"23",
    "addr:postcode":"2164",
    "addr:street":"Daniel St",
    "iso:country":"AU",
    "sg:address":"Unit 3/ 21- 23 Daniel St",
    "sg:city":"Wetherill Park",
    "sg:classifiers":[
        {
            "category":"Professional",
            "subcategory":"Engineering",
            "type":"Services"
        }
    ],
    "sg:phone":"+61 2 9756 1771",
    "sg:postcode":"2164",
    "sg:province":"NSW",
    "sg:tags":[
        "engineer"
    ],
    "wof:name":"Phil Bruce Engineering Pty Ltd",
    "wof:placetype":"venue"
},
  "geometry": {"coordinates":[150.904785156,-33.8486595154],"type":"Point"}
}