{
  "type": "Feature",
  "properties": {
    "iso:country":"AU",
    "sg:address":"102 Ocean Parade",
    "sg:city":"The Entrance",
    "sg:classifiers":[
        {
            "category":"Retail",
            "subcategory":"Event Space",
            "type":"Services"
        }
    ],
    "sg:phone":"+61 2 4332 5911",
    "sg:postcode":"2261",
    "sg:province":"NSW",
    "sg:tags":[
        "venue",
        "reception",
        "wedding"
    ],
    "wof:name":"Ocean Front At The Entrance",
    "wof:placetype":"venue"
},
  "geometry": {"coordinates":[151.50315900000001,-33.350918],"type":"Point"}
}