{
  "type": "Feature",
  "properties": {
    "addr:full":"Suite 1, 1st Floor 19 Kenrick St The Junction NSW 2291",
    "addr:housenumber":"19",
    "addr:postcode":"2291",
    "addr:street":"Kenrick St",
    "iso:country":"AU",
    "sg:address":"Suite 1, 1st Floor 19 Kenrick St",
    "sg:city":"The Junction",
    "sg:classifiers":[
        {
            "category":"Professional",
            "subcategory":"Accounting & Tax Preparation",
            "type":"Services"
        }
    ],
    "sg:phone":"+61 2 4962 2088",
    "sg:postcode":"2291",
    "sg:province":"NSW",
    "sg:tags":[
        "consultant",
        "taxation"
    ],
    "wof:name":"Hancock & Jesson Pty Limited",
    "wof:placetype":"venue"
},
  "geometry": {"coordinates":[151.76031494099999,-32.9382209778],"type":"Point"}
}