{
  "type": "Feature",
  "properties": {
    "iso:country":"AU",
    "sg:address":"285 Whitehorse Rd",
    "sg:city":"Balwyn",
    "sg:classifiers":[
        {
            "category":"Insurance",
            "subcategory":"Insurance Agent",
            "type":"Services"
        }
    ],
    "sg:phone":"+61 3 9836 3122",
    "sg:postcode":"3103",
    "sg:province":"VIC",
    "sg:tags":[
        "broker"
    ],
    "wof:name":"Catterall Stephen & Associates",
    "wof:placetype":"venue"
},
  "geometry": {"coordinates":[145.07864379899999,-37.8123626709],"type":"Point"}
}