{
  "type": "Feature",
  "properties": {
    "addr:full":"Calrose Ave Coleambally NSW 2707",
    "addr:postcode":"2707",
    "addr:street":"Calrose Ave",
    "iso:country":"AU",
    "sg:address":"Calrose Ave",
    "sg:city":"Coleambally",
    "sg:classifiers":[
        {
            "category":"Retail",
            "subcategory":"Auto Repair",
            "type":"Services"
        }
    ],
    "sg:phone":"+61 2 6954 4171",
    "sg:postcode":"2707",
    "sg:province":"NSW",
    "sg:tags":[
        "repairer",
        "motor",
        "engineer"
    ],
    "wof:name":"Hi-Trac Equipment",
    "wof:placetype":"venue"
},
  "geometry": {"coordinates":[145.89584350600001,-34.7950363159],"type":"Point"}
}