{
  "type": "Feature",
  "properties": {
    "addr:full":"PO Box 215 Sunbury VIC 3429",
    "addr:postcode":"3429",
    "iso:country":"AU",
    "sg:address":"PO Box 215",
    "sg:city":"Sunbury",
    "sg:classifiers":[
        {
            "category":"Food & Beverages",
            "subcategory":"Specialty",
            "type":"Retail Goods"
        }
    ],
    "sg:phone":"+61 3 9445 9682",
    "sg:postcode":"3429",
    "sg:province":"VIC",
    "sg:tags":[
        "product",
        "health"
    ],
    "wof:name":"Herbalife Independent Distributor",
    "wof:placetype":"venue"
},
  "geometry": {"coordinates":[144.7290802,-37.5800704956],"type":"Point"}
}