{
  "type": "Feature",
  "properties": {
    "iso:country":"AU",
    "sg:address":"33 Murray St",
    "sg:city":"Wonthaggi",
    "sg:classifiers":[
        {
            "category":"Real Estate",
            "subcategory":"Surveying",
            "type":"Services"
        }
    ],
    "sg:phone":"+61 3 5672 4655",
    "sg:postcode":"3995",
    "sg:province":"VIC",
    "sg:tags":[
        "building",
        "surveyor"
    ],
    "wof:name":"Anthony G. Zoanetti & Assoc. Pty Ltd.",
    "wof:placetype":"venue"
},
  "geometry": {"coordinates":[145.589127,-38.605198],"type":"Point"}
}