{
  "type": "Feature",
  "properties": {
    "addr:full":"118 Dumaresq St Armidale NSW 2350",
    "addr:housenumber":"118",
    "addr:postcode":"2350",
    "addr:street":"Dumaresq St",
    "iso:country":"AU",
    "sg:address":"118 Dumaresq St",
    "sg:city":"Armidale",
    "sg:classifiers":[
        {
            "category":"Shopping",
            "subcategory":"Luggage & Leather Goods",
            "type":"Retail Goods"
        }
    ],
    "sg:phone":"+61 2 6772 4786",
    "sg:postcode":"2350",
    "sg:province":"NSW",
    "wof:name":"Burton's Saddlery",
    "wof:placetype":"venue"
},
  "geometry": {"coordinates":[151.668655395,-30.512386322],"type":"Point"}
}