{
  "type": "Feature",
  "properties": {
    "addr:full":"1 Calidore St Bankstown NSW 2200",
    "addr:housenumber":"1",
    "addr:postcode":"2200",
    "addr:street":"Calidore St",
    "iso:country":"AU",
    "sg:address":"1 Calidore St",
    "sg:city":"Bankstown",
    "sg:classifiers":[
        {
            "category":"Health Services",
            "subcategory":"Doctor",
            "type":"Services"
        }
    ],
    "sg:phone":"+61 2 9708 5694",
    "sg:postcode":"2200",
    "sg:province":"NSW",
    "sg:tags":[
        "medical",
        "practitioner"
    ],
    "wof:name":"V Dutoit",
    "wof:placetype":"venue"
},
  "geometry": {"coordinates":[151.02557400000001,-33.933674],"type":"Point"}
}