{
  "type": "Feature",
  "properties": {
    "addr:full":"Level 1 2 Hassall St Parramatta NSW 2150",
    "addr:housenumber":"2",
    "addr:postcode":"2150",
    "addr:street":"Hassall St",
    "iso:country":"AU",
    "sg:address":"Level 1 2 Hassall St",
    "sg:city":"Parramatta",
    "sg:classifiers":[
        {
            "category":"Professional",
            "subcategory":"Computer Services",
            "type":"Services"
        }
    ],
    "sg:phone":"+61 2 9204 6851",
    "sg:postcode":"2150",
    "sg:province":"NSW",
    "sg:tags":[
        "information"
    ],
    "wof:name":"Serco Transport Services",
    "wof:placetype":"venue"
},
  "geometry": {"coordinates":[151.015258789,-33.8185882568],"type":"Point"}
}