{
  "type": "Feature",
  "properties": {
    "iso:country":"AU",
    "sg:address":"47 Blackwood Ave",
    "sg:city":"Mentone",
    "sg:classifiers":[
        {
            "category":"Utilities",
            "subcategory":"Refuse",
            "type":"Services"
        }
    ],
    "sg:phone":"+61 1800 707 778",
    "sg:postcode":"3194",
    "sg:province":"VIC",
    "sg:tags":[
        "remover",
        "rubbish"
    ],
    "wof:name":"Cost Less Bin Hire",
    "wof:placetype":"venue"
},
  "geometry": {"coordinates":[145.08140564000001,-37.9794616699],"type":"Point"}
}