{
  "type": "Feature",
  "properties": {
    "iso:country":"AU",
    "sg:address":"5/ 471 Tufnell Rd",
    "sg:city":"Banyo",
    "sg:classifiers":[
        {
            "category":"Manufacturing",
            "subcategory":"Tools & Machinery",
            "type":"Manufacturing & Wholesale Goods"
        }
    ],
    "sg:phone":"+61 7 3267 1811",
    "sg:postcode":"4014",
    "sg:province":"QLD",
    "sg:tags":[
        "abrasive"
    ],
    "wof:name":"Abrasiflex Pty Ltd",
    "wof:placetype":"venue"
},
  "geometry": {"coordinates":[153.086395264,-27.3859348297],"type":"Point"}
}