{
  "type": "Feature",
  "properties": {
    "addr:full":"22-38 Rundle Mall, Kiosk 106, Myer Centre Adelaide Adelaide SA 5000",
    "addr:housenumber":"22-38;106;centre",
    "addr:postcode":"5000",
    "addr:street":"Rundle Mall Kiosk;Adelaide Adelaide",
    "iso:country":"AU",
    "sg:address":"22-38 Rundle Mall, Kiosk 106, Myer Centre Adelaide",
    "sg:city":"Adelaide",
    "sg:classifiers":[
        {
            "category":"Professional",
            "subcategory":"Printing & Photocopies",
            "type":"Services"
        }
    ],
    "sg:phone":"+61 8 8410 2200",
    "sg:postcode":"5000",
    "sg:province":"SA",
    "sg:tags":[
        "embroidery"
    ],
    "wof:name":"Looksmart Alterations",
    "wof:placetype":"venue"
},
  "geometry": {"coordinates":[138.601028442,-34.9227790833],"type":"Point"}
}