{
  "type": "Feature",
  "properties": {
    "addr:full":"846 Kingston Rd Waterford QLD 4133",
    "addr:housenumber":"846",
    "addr:postcode":"4133",
    "addr:street":"Kingston Rd",
    "iso:country":"AU",
    "sg:address":"846 Kingston Rd",
    "sg:city":"Waterford",
    "sg:classifiers":[
        {
            "category":"Retail",
            "subcategory":"Auto Rental",
            "type":"Services"
        }
    ],
    "sg:phone":"+61 7 3200 6309",
    "sg:postcode":"4133",
    "sg:province":"QLD",
    "sg:tags":[
        "camper-trailers",
        "caravan",
        "hire"
    ],
    "wof:name":"Rj & K Lee Caravan Hire",
    "wof:placetype":"venue"
},
  "geometry": {"coordinates":[153.13267517099999,-27.6913318634],"type":"Point"}
}