{
  "type": "Feature",
  "properties": {
    "addr:full":"156a Rosebank Ave Clayton South VIC 3169",
    "addr:housenumber":"156a",
    "addr:postcode":"3169",
    "addr:street":"Rosebank Ave",
    "iso:country":"AU",
    "sg:address":"156a Rosebank Ave",
    "sg:city":"Clayton South",
    "sg:classifiers":[
        {
            "category":"Personal",
            "subcategory":"Beauty Salon",
            "type":"Services"
        }
    ],
    "sg:phone":"+61 3 9548 3882",
    "sg:postcode":"3169",
    "sg:province":"VIC",
    "sg:tags":[
        "hairdresser"
    ],
    "wof:name":"Cattiva Hair",
    "wof:placetype":"venue"
},
  "geometry": {"coordinates":[145.13908386200001,-37.9404525757],"type":"Point"}
}