{
  "type": "Feature",
  "properties": {
    "iso:country":"AU",
    "sg:address":"120 Elder St",
    "sg:city":"Lambton",
    "sg:classifiers":[
        {
            "category":"Organizations",
            "subcategory":"Non-profit Organization",
            "type":"Services"
        }
    ],
    "sg:phone":"+61 2 4965 3533",
    "sg:postcode":"2299",
    "sg:province":"NSW",
    "sg:tags":[
        "support",
        "disability",
        "organisation"
    ],
    "wof:name":"Response Services",
    "wof:placetype":"venue"
},
  "geometry": {"coordinates":[151.70721435600001,-32.9112472534],"type":"Point"}
}