{
  "type": "Feature",
  "properties": {
    "addr:full":"1st Floor 20 Chapman St Proserpine QLD 4800",
    "addr:housenumber":"20",
    "addr:postcode":"4800",
    "addr:street":"Chapman St",
    "iso:country":"AU",
    "sg:address":"1st Floor 20 Chapman St",
    "sg:city":"Proserpine",
    "sg:classifiers":[
        {
            "category":"Insurance",
            "subcategory":"Insurance Agent",
            "type":"Services"
        }
    ],
    "sg:phone":"+61 7 4945 3666",
    "sg:postcode":"4800",
    "sg:province":"QLD",
    "wof:name":"Wagemakers Conrad Insurance",
    "wof:placetype":"venue"
},
  "geometry": {"coordinates":[148.58319091800001,-20.4008922577],"type":"Point"}
}