{
  "type": "Feature",
  "properties": {
    "iso:country":"AU",
    "sg:address":"12 Morrison Pl",
    "sg:city":"East Melbourne",
    "sg:classifiers":[
        {
            "category":"Communications",
            "subcategory":"Television Station",
            "type":"Services"
        }
    ],
    "sg:phone":"+61 1300 887 344",
    "sg:postcode":"3002",
    "sg:province":"VIC",
    "sg:tags":[
        "equipment",
        "laser"
    ],
    "wof:name":"Australian Institute Of Laser Therapy",
    "wof:placetype":"venue"
},
  "geometry": {"coordinates":[144.97679138199999,-37.8093070984],"type":"Point"}
}