{
  "type": "Feature",
  "properties": {
    "iso:country":"AU",
    "sg:address":"261 Belmore Rd",
    "sg:city":"Riverwood",
    "sg:classifiers":[
        {
            "category":"Food & Beverages",
            "subcategory":"Supermarket",
            "type":"Retail Goods"
        }
    ],
    "sg:phone":"+61 2 9534 2167",
    "sg:postcode":"2210",
    "sg:province":"NSW",
    "sg:tags":[
        "grocery",
        "store"
    ],
    "wof:name":"Franklins Stores",
    "wof:placetype":"venue"
},
  "geometry": {"coordinates":[151.052597,-33.950001],"type":"Point"}
}