{
  "type": "Feature",
  "properties": {
    "addr:full":"402 Stuart Hwy Winnellie NT 0820",
    "addr:housenumber":"402",
    "addr:postcode":"nt 0820",
    "addr:street":"Stuart Hwy",
    "iso:country":"AU",
    "sg:address":"402 Stuart Hwy",
    "sg:city":"Winnellie",
    "sg:classifiers":[
        {
            "category":"Manufacturing",
            "subcategory":"Tools & Machinery",
            "type":"Manufacturing & Wholesale Goods"
        }
    ],
    "sg:phone":"+61 8 8984 3166",
    "sg:postcode":"0820",
    "sg:province":"NT",
    "sg:tags":[
        "earth",
        "excavating",
        "moving",
        "equipment"
    ],
    "wof:name":"Hitachi Construction Machinery Australia",
    "wof:placetype":"venue"
},
  "geometry": {"coordinates":[130.87452697800001,-12.4254512787],"type":"Point"}
}