{
  "type": "Feature",
  "properties": {
    "addr:full":"46 Winfield St Morawa WA 6623",
    "addr:housenumber":"46",
    "addr:postcode":"6623",
    "addr:street":"Winfield St",
    "iso:country":"AU",
    "sg:address":"46 Winfield St",
    "sg:city":"Morawa",
    "sg:classifiers":[
        {
            "category":"Banks & Credit Unions",
            "subcategory":"Bank",
            "type":"Services"
        }
    ],
    "sg:phone":"+61 13 20 32",
    "sg:postcode":"6623",
    "sg:province":"WA",
    "wof:name":"Westpac",
    "wof:placetype":"venue"
},
  "geometry": {"coordinates":[116.00907898,-29.2112789154],"type":"Point"}
}