{
  "type": "Feature",
  "properties": {
    "addr:full":"63 St Andrew Drv Tewantin QLD 4565",
    "addr:housenumber":"63",
    "addr:postcode":"4565",
    "addr:street":"St Andrew Drv",
    "iso:country":"AU",
    "sg:address":"63 St Andrew Drv",
    "sg:city":"Tewantin",
    "sg:classifiers":[
        {
            "category":"Food & Beverages",
            "subcategory":"Bakery",
            "type":"Retail Goods"
        }
    ],
    "sg:phone":"+61 7 5442 4100",
    "sg:postcode":"4565",
    "sg:province":"QLD",
    "sg:tags":[
        "baker"
    ],
    "wof:name":"Outlook Hot Bread & Patisserie",
    "wof:placetype":"venue"
},
  "geometry": {"coordinates":[153.02206420900001,-26.4033126831],"type":"Point"}
}