{
  "type": "Feature",
  "properties": {
    "addr:full":"14 Dee St Heidelberg VIC 3084",
    "addr:housenumber":"14",
    "addr:postcode":"3084",
    "addr:street":"Dee St",
    "iso:country":"AU",
    "sg:address":"14 Dee St",
    "sg:city":"Heidelberg",
    "sg:classifiers":[
        {
            "category":"Building & Trades",
            "subcategory":"Landscaping Services",
            "type":"Services"
        }
    ],
    "sg:phone":"+61 418 562 115",
    "sg:postcode":"3084",
    "sg:province":"VIC",
    "sg:tags":[
        "stump",
        "tree",
        "felling",
        "removal"
    ],
    "wof:name":"GVP Arbor Service",
    "wof:placetype":"venue"
},
  "geometry": {"coordinates":[145.06460571299999,-37.7500991821],"type":"Point"}
}