{
  "type": "Feature",
  "properties": {
    "addr:full":"Duffys Rd Terrigal NSW 2260",
    "addr:postcode":"2260",
    "addr:street":"Duffys Rd",
    "iso:country":"AU",
    "sg:address":"Duffys Rd",
    "sg:city":"Terrigal",
    "sg:classifiers":[
        {
            "category":"Sports & Exercise",
            "subcategory":"Sports Center",
            "type":"Entertainment"
        }
    ],
    "sg:phone":"+61 2 4385 5564",
    "sg:postcode":"2260",
    "sg:province":"NSW",
    "sg:tags":[
        "coach",
        "tennis"
    ],
    "wof:name":"Tennis Learning Company",
    "wof:placetype":"venue"
},
  "geometry": {"coordinates":[151.427933,-33.445255],"type":"Point"}
}