{
  "type": "Feature",
  "properties": {
    "iso:country":"AU",
    "sg:address":"1A Ascot St",
    "sg:city":"Preston",
    "sg:classifiers":[
        {
            "category":"Education",
            "subcategory":"Special Training",
            "type":"Public Place"
        }
    ],
    "sg:phone":"+61 3 9443 7222",
    "sg:postcode":"3072",
    "sg:province":"VIC",
    "sg:tags":[
        "development"
    ],
    "wof:name":"Trainers' Trainers The",
    "wof:placetype":"venue"
},
  "geometry": {"coordinates":[145.00990295400001,-37.7519226074],"type":"Point"}
}