{
  "type": "Feature",
  "properties": {
    "addr:full":"34 Cawthorne St Thebarton SA 5031",
    "addr:housenumber":"34",
    "addr:postcode":"5031",
    "addr:street":"Cawthorne St",
    "iso:country":"AU",
    "sg:address":"34 Cawthorne St",
    "sg:city":"Thebarton",
    "sg:classifiers":[
        {
            "category":"Home & Garden",
            "subcategory":"Carpets & Floor Coverings",
            "type":"Retail Goods"
        }
    ],
    "sg:phone":"+61 8 8443 8666",
    "sg:postcode":"5031",
    "sg:province":"SA",
    "sg:tags":[
        "mattress"
    ],
    "sg:website":"http://www.latexbeds.com.au",
    "wof:name":"Futon Dawn",
    "wof:placetype":"venue"
},
  "geometry": {"coordinates":[138.575073242,-34.9129295349],"type":"Point"}
}