{
  "type": "Feature",
  "properties": {
    "iso:country":"AU",
    "sg:address":"85 Guthrie St",
    "sg:city":"Osborne Park",
    "sg:classifiers":[
        {
            "category":"Retail",
            "subcategory":"Auto Repair",
            "type":"Services"
        }
    ],
    "sg:phone":"+61 8 9244 2484",
    "sg:postcode":"6017",
    "sg:province":"WA",
    "sg:tags":[
        "muffler",
        "exhaust",
        "system"
    ],
    "wof:name":"Supercat Convertors",
    "wof:placetype":"venue"
},
  "geometry": {"coordinates":[115.816650391,-31.9066371918],"type":"Point"}
}