{
  "type": "Feature",
  "properties": {
    "addr:full":"8 Cowie Pl Hoppers Crossing VIC 3029",
    "addr:housenumber":"8",
    "addr:postcode":"3029",
    "addr:street":"Cowie Pl",
    "iso:country":"AU",
    "sg:address":"8 Cowie Pl",
    "sg:city":"Hoppers Crossing",
    "sg:classifiers":[
        {
            "category":"Banks & Credit Unions",
            "subcategory":"Atm",
            "type":"Services"
        }
    ],
    "sg:phone":"+61 3 9749 2240",
    "sg:postcode":"3029",
    "sg:province":"VIC",
    "sg:tags":[
        "reconditioners",
        "drum",
        "manufacturers"
    ],
    "wof:name":"Page Drums",
    "wof:placetype":"venue"
},
  "geometry": {"coordinates":[144.67549099999999,-37.872852],"type":"Point"}
}