{
  "type": "Feature",
  "properties": {
    "iso:country":"AU",
    "sg:address":"Shop 15 Cherrybrook Vlge Shepherds Drv",
    "sg:city":"Cherrybrook",
    "sg:classifiers":[
        {
            "category":"Travel",
            "subcategory":"Travel Agent",
            "type":"Entertainment"
        }
    ],
    "sg:phone":"+61 2 9438 2711",
    "sg:postcode":"2126",
    "sg:province":"NSW",
    "sg:tags":[
        "consultant"
    ],
    "wof:name":"Tip Top Travel Service Pty Ltd",
    "wof:placetype":"venue"
},
  "geometry": {"coordinates":[151.051544189,-33.7330551147],"type":"Point"}
}