{
  "type": "Feature",
  "properties": {
    "iso:country":"AU",
    "sg:address":"840 Ashmore Rd",
    "sg:city":"Nerang",
    "sg:classifiers":[
        {
            "category":"Building & Trades",
            "subcategory":"Pest Control",
            "type":"Services"
        }
    ],
    "sg:phone":"+61 7 5539 6671",
    "sg:postcode":"4211",
    "sg:province":"QLD",
    "wof:name":"Ashmore Pest Control",
    "wof:placetype":"venue"
},
  "geometry": {"coordinates":[153.35606384299999,-27.9672870636],"type":"Point"}
}