{
  "type": "Feature",
  "properties": {
    "iso:country":"AU",
    "sg:address":"Memorial Ave",
    "sg:city":"Keith",
    "sg:classifiers":[
        {
            "category":"Arena",
            "subcategory":"Sports Club",
            "type":"Entertainment"
        }
    ],
    "sg:phone":"+61 8 8755 1237",
    "sg:postcode":"5267",
    "sg:province":"SA",
    "sg:tags":[
        "australian",
        "football",
        "rule"
    ],
    "wof:name":"Keith Football Club Incorporated",
    "wof:placetype":"venue"
},
  "geometry": {"coordinates":[140.34982299999999,-36.098888],"type":"Point"}
}