{
  "type": "Feature",
  "properties": {
    "iso:country":"AU",
    "sg:address":"29 Reynton St",
    "sg:city":"Currumbin Waters",
    "sg:classifiers":[
        {
            "category":"Retail",
            "subcategory":"Auto Repair",
            "type":"Services"
        }
    ],
    "sg:phone":"+61 408 758 254",
    "sg:postcode":"4223",
    "sg:province":"QLD",
    "sg:tags":[
        "beater",
        "painter",
        "panel"
    ],
    "wof:name":"Color Match Gold Coast",
    "wof:placetype":"venue"
},
  "geometry": {"coordinates":[153.476364136,-28.1446666718],"type":"Point"}
}