{
  "type": "Feature",
  "properties": {
    "addr:full":"110 Elizabeth St Hobart TAS 7000",
    "addr:housenumber":"110",
    "addr:postcode":"7000",
    "addr:street":"Elizabeth St",
    "iso:country":"AU",
    "sg:address":"110 Elizabeth St",
    "sg:city":"Hobart",
    "sg:classifiers":[
        {
            "category":"Structure",
            "subcategory":"Office Building",
            "type":"Public Place"
        }
    ],
    "sg:phone":"+61 3 6234 5848",
    "sg:postcode":"7000",
    "sg:province":"TAS",
    "sg:tags":[
        "serviced"
    ],
    "wof:name":"Studio 110 Serviced Offices",
    "wof:placetype":"venue"
},
  "geometry": {"coordinates":[147.325042725,-42.8803596497],"type":"Point"}
}