{
  "type": "Feature",
  "properties": {
    "iso:country":"AU",
    "sg:address":"80 Merivale St",
    "sg:city":"South Brisbane",
    "sg:classifiers":[
        {
            "category":"Retail",
            "subcategory":"Auto Repair",
            "type":"Services"
        }
    ],
    "sg:phone":"+61 7 3844 6273",
    "sg:postcode":"4101",
    "sg:province":"QLD",
    "sg:tags":[
        "wheel",
        "balancing",
        "alignment"
    ],
    "wof:name":"Bridgestone Tyre Centres",
    "wof:placetype":"venue"
},
  "geometry": {"coordinates":[153.01846313499999,-27.478061676],"type":"Point"}
}