{
  "type": "Feature",
  "properties": {
    "iso:country":"AU",
    "sg:address":"Rosedale Rd",
    "sg:city":"Rosedale",
    "sg:classifiers":[
        {
            "category":"Education",
            "subcategory":"School",
            "type":"Public Place"
        }
    ],
    "sg:phone":"+61 8 8524 9032",
    "sg:postcode":"5350",
    "sg:province":"SA",
    "sg:tags":[
        "state",
        "except",
        "nsw"
    ],
    "wof:name":"Rosedale Primary School",
    "wof:placetype":"venue"
},
  "geometry": {"coordinates":[138.84617614699999,-34.5612182617],"type":"Point"}
}