{
  "type": "Feature",
  "properties": {
    "iso:country":"AU",
    "sg:address":"25 Albert St",
    "sg:city":"Cooma",
    "sg:classifiers":[
        {
            "category":"Building & Trades",
            "subcategory":"Construction",
            "type":"Services"
        }
    ],
    "sg:phone":"+61 2 6452 2661",
    "sg:postcode":"2630",
    "sg:province":"NSW",
    "sg:tags":[
        "polishing",
        "sanding",
        "floor"
    ],
    "wof:name":"Brown T G",
    "wof:placetype":"venue"
},
  "geometry": {"coordinates":[149.13259887699999,-36.2404899597],"type":"Point"}
}