{
  "type": "Feature",
  "properties": {
    "iso:country":"AU",
    "sg:address":"Unit 1/34 Quinns La",
    "sg:city":"Nowra",
    "sg:classifiers":[
        {
            "category":"Home & Garden",
            "subcategory":"Building Materials",
            "type":"Retail Goods"
        }
    ],
    "sg:phone":"+61 2 4423 7000",
    "sg:postcode":"2540",
    "sg:province":"NSW",
    "sg:tags":[
        "wall",
        "frame",
        "truss",
        "roof"
    ],
    "wof:name":"Truss Steel",
    "wof:placetype":"venue"
},
  "geometry": {"coordinates":[150.606689453,-34.9089698792],"type":"Point"}
}