{
  "type": "Feature",
  "properties": {
    "addr:full":"70 Pine Camp Rd Beerwah QLD 4519",
    "addr:housenumber":"70",
    "addr:postcode":"4519",
    "addr:street":"Pine Camp Rd",
    "iso:country":"AU",
    "sg:address":"70 Pine Camp Rd",
    "sg:city":"Beerwah",
    "sg:classifiers":[
        {
            "category":"Professional",
            "subcategory":"Art Services",
            "type":"Services"
        }
    ],
    "sg:phone":"+61 7 5494 0947",
    "sg:postcode":"4519",
    "sg:province":"QLD",
    "sg:tags":[
        "conservation",
        "restoration"
    ],
    "wof:name":"Frame D&#039;Art",
    "wof:placetype":"venue"
},
  "geometry": {"coordinates":[152.95130900000001,-26.853146],"type":"Point"}
}