{
  "type": "Feature",
  "properties": {
    "addr:full":"93 Bank St Molong NSW 2866",
    "addr:housenumber":"93",
    "addr:postcode":"2866",
    "addr:street":"Bank St",
    "iso:country":"AU",
    "sg:address":"93 Bank St",
    "sg:city":"Molong",
    "sg:classifiers":[
        {
            "category":"Health Services",
            "subcategory":"Dentist",
            "type":"Services"
        }
    ],
    "sg:phone":"+61 2 6366 8033",
    "sg:postcode":"2866",
    "sg:province":"NSW",
    "wof:name":"Green A D",
    "wof:placetype":"venue"
},
  "geometry": {"coordinates":[148.869247,-33.092121],"type":"Point"}
}