{
  "type": "Feature",
  "properties": {
    "iso:country":"AU",
    "sg:address":"Alice St",
    "sg:city":"Pialba",
    "sg:classifiers":[
        {
            "category":"Education",
            "subcategory":"School",
            "type":"Public Place"
        }
    ],
    "sg:phone":"+61 7 4197 7777",
    "sg:postcode":"4655",
    "sg:province":"QLD",
    "sg:tags":[
        "state",
        "except",
        "nsw"
    ],
    "wof:name":"Pialba Primary",
    "wof:placetype":"venue"
},
  "geometry": {"coordinates":[152.83592200000001,-25.280806],"type":"Point"}
}