{
  "type": "Feature",
  "properties": {
    "iso:country":"AU",
    "sg:address":"47 Park Rd",
    "sg:city":"Milton",
    "sg:classifiers":[
        {
            "category":"Health Services",
            "subcategory":"Health Practitioner",
            "type":"Services"
        }
    ],
    "sg:phone":"+61 7 3369 6788",
    "sg:postcode":"4064",
    "sg:province":"QLD",
    "sg:tags":[
        "psychologist"
    ],
    "wof:name":"Greenhalgh Diana",
    "wof:placetype":"venue"
},
  "geometry": {"coordinates":[153.00486755399999,-27.4717788696],"type":"Point"}
}