{
  "type": "Feature",
  "properties": {
    "addr:full":"15 Collins St Drysdale VIC 3222",
    "addr:housenumber":"15",
    "addr:postcode":"3222",
    "addr:street":"Collins St",
    "iso:country":"AU",
    "sg:address":"15 Collins St",
    "sg:city":"Drysdale",
    "sg:classifiers":[
        {
            "category":"Health Services",
            "subcategory":"Doctor",
            "type":"Services"
        }
    ],
    "sg:phone":"+61 3 5251 2865",
    "sg:postcode":"3222",
    "sg:province":"VIC",
    "sg:tags":[
        "medical",
        "practitioner"
    ],
    "wof:name":"Pilgrim Dr Carmel",
    "wof:placetype":"venue"
},
  "geometry": {"coordinates":[144.57167100000001,-38.172119],"type":"Point"}
}