{
  "type": "Feature",
  "properties": {
    "iso:country":"AU",
    "sg:address":"Suite 7, The Heights Medical Centre, Lookout Rd",
    "sg:city":"New Lambton",
    "sg:classifiers":[
        {
            "category":"Health Services",
            "subcategory":"Doctor",
            "type":"Services"
        }
    ],
    "sg:phone":"+61 2 4952 3900",
    "sg:postcode":"2305",
    "sg:province":"NSW",
    "sg:tags":[
        "medical",
        "practitioner"
    ],
    "wof:name":"Leitch Dr James W",
    "wof:placetype":"venue"
},
  "geometry": {"coordinates":[151.701370239,-32.9221611023],"type":"Point"}
}