{
  "type": "Feature",
  "properties": {
    "addr:full":"Ste2/ 374 Pacific Hwy Lindfield NSW 2070",
    "addr:housenumber":"374",
    "addr:postcode":"2070",
    "addr:street":"Pacific Hwy",
    "iso:country":"AU",
    "sg:address":"Ste2/ 374 Pacific Hwy",
    "sg:city":"Lindfield",
    "sg:classifiers":[
        {
            "category":"Health Services",
            "subcategory":"Optometrist",
            "type":"Services"
        }
    ],
    "sg:phone":"+61 2 9416 7699",
    "sg:postcode":"2070",
    "sg:province":"NSW",
    "sg:website":"http://www.oaansw.com.au",
    "wof:name":"J.A. Nicol Optometrist",
    "wof:placetype":"venue"
},
  "geometry": {"coordinates":[151.16781616200001,-33.774307251],"type":"Point"}
}