{
  "type": "Feature",
  "properties": {
    "addr:full":"Shop 13 44 Woodbine St North Balgowlah NSW 2093",
    "addr:housenumber":"shop 13 44",
    "addr:postcode":"2093",
    "addr:street":"Woodbine St",
    "iso:country":"AU",
    "sg:address":"Shop 13 44 Woodbine St",
    "sg:city":"North Balgowlah",
    "sg:classifiers":[
        {
            "category":"Personal",
            "subcategory":"Beauty Salon",
            "type":"Services"
        }
    ],
    "sg:phone":"+61 2 9907 9656",
    "sg:postcode":"2093",
    "sg:province":"NSW",
    "wof:name":"Serenity Skin & Body",
    "wof:placetype":"venue"
},
  "geometry": {"coordinates":[151.25126648,-33.7866706848],"type":"Point"}
}