{
  "type": "Feature",
  "properties": {
    "addr:full":"397 Banna Ave Griffith NSW 2680",
    "addr:housenumber":"397",
    "addr:postcode":"2680",
    "addr:street":"Banna Ave",
    "iso:country":"AU",
    "sg:address":"397 Banna Ave",
    "sg:city":"Griffith",
    "sg:classifiers":[
        {
            "category":"Shopping",
            "subcategory":"Clothing, Apparel, & Fashions",
            "type":"Retail Goods"
        }
    ],
    "sg:phone":"+61 2 6964 6155",
    "sg:postcode":"2680",
    "sg:province":"NSW",
    "sg:tags":[
        "lady",
        "wear"
    ],
    "wof:name":"Sassi",
    "wof:placetype":"venue"
},
  "geometry": {"coordinates":[146.04281599999999,-34.287304],"type":"Point"}
}