{
  "type": "Feature",
  "properties": {
    "iso:country":"AU",
    "sg:address":"290 Schubach St",
    "sg:city":"Albury",
    "sg:classifiers":[
        {
            "category":"Wholesale",
            "subcategory":"Home Furnishings",
            "type":"Manufacturing & Wholesale Goods"
        }
    ],
    "sg:phone":"+61 409 462 834",
    "sg:postcode":"2640",
    "sg:province":"NSW",
    "sg:tags":[
        "terrazzo"
    ],
    "wof:name":"Spec Floors",
    "wof:placetype":"venue"
},
  "geometry": {"coordinates":[146.929489136,-36.0801734924],"type":"Point"}
}