{
  "type": "Feature",
  "properties": {
    "iso:country":"AU",
    "sg:address":"10 Davies St",
    "sg:city":"Chatswood",
    "sg:classifiers":[
        {
            "category":"Government",
            "subcategory":"Court House",
            "type":"Public Place"
        }
    ],
    "sg:phone":"+61 2 9904 7778",
    "sg:postcode":"2067",
    "sg:province":"NSW",
    "sg:tags":[
        "personal",
        "marriage",
        "family",
        "counselling"
    ],
    "wof:name":"Jan Gracie Mulcahy",
    "wof:placetype":"venue"
},
  "geometry": {"coordinates":[151.171432495,-33.7950553894],"type":"Point"}
}