{
  "type": "Feature",
  "properties": {
    "addr:full":"5 Spicer St Laidley QLD 4341",
    "addr:housenumber":"5",
    "addr:postcode":"4341",
    "addr:street":"Spicer St",
    "iso:country":"AU",
    "sg:address":"5 Spicer St",
    "sg:city":"Laidley",
    "sg:classifiers":[
        {
            "category":"Retail",
            "subcategory":"Auto Repair",
            "type":"Services"
        }
    ],
    "sg:phone":"+61 7 5465 1406",
    "sg:postcode":"4341",
    "sg:province":"QLD",
    "sg:tags":[
        "repairer",
        "motor",
        "engineer"
    ],
    "wof:name":"Holden",
    "wof:placetype":"venue"
},
  "geometry": {"coordinates":[152.39434814399999,-27.6297893524],"type":"Point"}
}