{
  "type": "Feature",
  "properties": {
    "addr:full":"PO Box 3282 Batehaven NSW 2536",
    "addr:postcode":"2536",
    "iso:country":"AU",
    "sg:address":"PO Box 3282",
    "sg:city":"Batehaven",
    "sg:classifiers":[
        {
            "category":"Building & Trades",
            "subcategory":"Construction",
            "type":"Services"
        }
    ],
    "sg:phone":"+61 2 4472 9551",
    "sg:postcode":"2536",
    "sg:province":"NSW",
    "sg:tags":[
        "contractor"
    ],
    "wof:name":"Sealine Homes",
    "wof:placetype":"venue"
},
  "geometry": {"coordinates":[150.19996643100001,-35.7324409485],"type":"Point"}
}