{
  "type": "Feature",
  "properties": {
    "iso:country":"AU",
    "sg:address":"8 McHenry St",
    "sg:city":"Amaroo",
    "sg:classifiers":[
        {
            "category":"Professional",
            "subcategory":"Art Services",
            "type":"Services"
        }
    ],
    "sg:phone":"+61 413 588 186",
    "sg:postcode":"2914",
    "sg:province":"ACT",
    "sg:tags":[
        "decorator",
        "painter"
    ],
    "wof:name":"Artform Painting Services",
    "wof:placetype":"venue"
},
  "geometry": {"coordinates":[149.133743286,-35.1703453064],"type":"Point"}
}