{
  "type": "Feature",
  "properties": {
    "addr:full":"1 Maitland Pl Baulkham Hills NSW 2153",
    "addr:housenumber":"1",
    "addr:postcode":"2153",
    "addr:street":"Pl",
    "iso:country":"AU",
    "sg:address":"1 Maitland Pl",
    "sg:city":"Baulkham Hills",
    "sg:classifiers":[
        {
            "category":"Banks & Credit Unions",
            "subcategory":"Investment Brokerage",
            "type":"Services"
        }
    ],
    "sg:phone":"+61 2 8850 2766",
    "sg:postcode":"2153",
    "sg:province":"NSW",
    "sg:tags":[
        "finance",
        "broker"
    ],
    "wof:name":"Bus & Machinery Finance",
    "wof:placetype":"venue"
},
  "geometry": {"coordinates":[150.966064453,-33.7307014465],"type":"Point"}
}