{
  "type": "Feature",
  "properties": {
    "addr:full":"72 Hanson Rd Craigieburn VIC 3064",
    "addr:housenumber":"72",
    "addr:postcode":"3064",
    "addr:street":"Hanson Rd",
    "iso:country":"AU",
    "sg:address":"72 Hanson Rd",
    "sg:city":"Craigieburn",
    "sg:classifiers":[
        {
            "category":"Autos & Motor Vehicles",
            "subcategory":"Fuel & Gas Station",
            "type":"Retail Goods"
        }
    ],
    "sg:phone":"+61 3 9308 1817",
    "sg:postcode":"3064",
    "sg:province":"VIC",
    "wof:name":"BP Australia Pty Ltd",
    "wof:placetype":"venue"
},
  "geometry": {"coordinates":[144.93739318900001,-37.5924034119],"type":"Point"}
}