{
  "type": "Feature",
  "properties": {
    "iso:country":"AU",
    "sg:address":"8A Ascot St",
    "sg:city":"Toowoomba",
    "sg:classifiers":[
        {
            "category":"Social Services",
            "subcategory":"Adult Care",
            "type":"Services"
        }
    ],
    "sg:phone":"+61 419 761 735",
    "sg:postcode":"4350",
    "sg:province":"QLD",
    "sg:tags":[
        "towing"
    ],
    "wof:name":"Russell Day Towing",
    "wof:placetype":"venue"
},
  "geometry": {"coordinates":[151.931824,-27.556894],"type":"Point"}
}