{
  "type": "Feature",
  "properties": {
    "iso:country":"AU",
    "sg:address":"Shop1/ 26 Knight St",
    "sg:city":"North Rockhampton",
    "sg:classifiers":[
        {
            "category":"Manufacturing",
            "subcategory":"Metals",
            "type":"Manufacturing & Wholesale Goods"
        }
    ],
    "sg:phone":"+61 7 4926 6695",
    "sg:postcode":"4701",
    "sg:province":"QLD",
    "sg:tags":[
        "casting"
    ],
    "wof:name":"M D Plastic Welding Service",
    "wof:placetype":"venue"
},
  "geometry": {"coordinates":[150.51426696799999,-23.3631229401],"type":"Point"}
}