{
  "type": "Feature",
  "properties": {
    "iso:country":"AU",
    "sg:address":"79 High St",
    "sg:city":"Shepparton",
    "sg:classifiers":[
        {
            "category":"Shopping",
            "subcategory":"Mobile Phones",
            "type":"Retail Goods"
        }
    ],
    "sg:phone":"+61 3 5831 4499",
    "sg:postcode":"3630",
    "sg:province":"VIC",
    "sg:tags":[
        "telephone",
        "accessory"
    ],
    "wof:name":"Amber Communications",
    "wof:placetype":"venue"
},
  "geometry": {"coordinates":[145.4012146,-36.3811569214],"type":"Point"}
}