{
  "type": "Feature",
  "properties": {
    "iso:country":"AU",
    "sg:address":"1179 Botany Rd",
    "sg:city":"Mascot",
    "sg:classifiers":[
        {
            "category":"Shopping",
            "type":"Retail Goods"
        }
    ],
    "sg:phone":"+61 2 9669 1644",
    "sg:postcode":"2020",
    "sg:province":"NSW",
    "sg:tags":[
        "repair",
        "travel"
    ],
    "wof:name":"Antler Service Centre",
    "wof:placetype":"venue"
},
  "geometry": {"coordinates":[151.194488525,-33.9309654236],"type":"Point"}
}