{
  "type": "Feature",
  "properties": {
    "addr:full":"74 Normanby Rd Greenvale VIC 3059",
    "addr:housenumber":"74",
    "addr:postcode":"3059",
    "addr:street":"Normanby Rd",
    "iso:country":"AU",
    "sg:address":"74 Normanby Rd",
    "sg:city":"Greenvale",
    "sg:classifiers":[
        {
            "category":"Home & Garden",
            "subcategory":"Building Materials",
            "type":"Retail Goods"
        }
    ],
    "sg:phone":"+61 418 562 027",
    "sg:postcode":"3059",
    "sg:province":"VIC",
    "sg:tags":[
        "merchant",
        "glass",
        "glazier"
    ],
    "wof:name":"M R Glass Pty Ltd",
    "wof:placetype":"venue"
},
  "geometry": {"coordinates":[144.89924621599999,-37.6595687866],"type":"Point"}
}