{
  "type": "Feature",
  "properties": {
    "addr:full":"Handley Drv Boyne Island QLD 4680",
    "addr:postcode":"4680",
    "addr:street":"Handley Drv",
    "iso:country":"AU",
    "sg:address":"Handley Drv",
    "sg:city":"Boyne Island",
    "sg:classifiers":[
        {
            "category":"Manufacturing",
            "subcategory":"Metals",
            "type":"Manufacturing & Wholesale Goods"
        }
    ],
    "sg:phone":"+61 7 4973 0211",
    "sg:postcode":"4680",
    "sg:province":"QLD",
    "sg:tags":[
        "wholesaler",
        "aluminium",
        "mfrs"
    ],
    "wof:name":"Boyne Smelters Limited",
    "wof:placetype":"venue"
},
  "geometry": {"coordinates":[151.34129333499999,-23.9602146149],"type":"Point"}
}