{
  "type": "Feature",
  "properties": {
    "iso:country":"AU",
    "sg:address":"12 Ballantyne Rd",
    "sg:city":"Kewdale",
    "sg:classifiers":[
        {
            "category":"Home & Garden",
            "subcategory":"Building Materials",
            "type":"Retail Goods"
        }
    ],
    "sg:phone":"+61 8 9353 1400",
    "sg:postcode":"6105",
    "sg:province":"WA",
    "sg:tags":[
        "wall",
        "frame",
        "truss",
        "roof"
    ],
    "wof:name":"The Truss Factory",
    "wof:placetype":"venue"
},
  "geometry": {"coordinates":[115.938087463,-31.9845066071],"type":"Point"}
}