{
  "type": "Feature",
  "properties": {
    "addr:full":"1 Kay St Granville NSW 2142",
    "addr:housenumber":"1",
    "addr:postcode":"2142",
    "addr:street":"Kay St",
    "iso:country":"AU",
    "sg:address":"1 Kay St",
    "sg:city":"Granville",
    "sg:classifiers":[
        {
            "category":"Wholesale",
            "subcategory":"Machinery & Supplies",
            "type":"Manufacturing & Wholesale Goods"
        }
    ],
    "sg:phone":"+61 2 9897 1410",
    "sg:postcode":"2142",
    "sg:province":"NSW",
    "sg:tags":[
        "distributor",
        "crane",
        "mfrs"
    ],
    "sg:website":"http://www.palfinger.com.au",
    "wof:name":"Palfinger Australia Pty Ltd",
    "wof:placetype":"venue"
},
  "geometry": {"coordinates":[151.02255249000001,-33.8308792114],"type":"Point"}
}