{
  "type": "Feature",
  "properties": {
    "iso:country":"AU",
    "sg:address":"110 Queen St",
    "sg:city":"Woollahra",
    "sg:classifiers":[
        {
            "category":"Shopping",
            "subcategory":"Beauty & Cosmetics",
            "type":"Retail Goods"
        }
    ],
    "sg:phone":"+61 2 9362 5555",
    "sg:postcode":"2025",
    "sg:province":"NSW",
    "wof:name":"Jo Malone",
    "wof:placetype":"venue"
},
  "geometry": {"coordinates":[151.236572266,-33.8884048462],"type":"Point"}
}