{
  "type": "Feature",
  "properties": {
    "addr:full":"18 Wolseley Rd Lindfield NSW 2070",
    "addr:housenumber":"18",
    "addr:postcode":"2070",
    "addr:street":"Wolseley Rd",
    "iso:country":"AU",
    "sg:address":"18 Wolseley Rd",
    "sg:city":"Lindfield",
    "sg:classifiers":[
        {
            "category":"Health Services",
            "subcategory":"Doctor",
            "type":"Services"
        }
    ],
    "sg:phone":"+61 2 9415 8379",
    "sg:postcode":"2070",
    "sg:province":"NSW",
    "sg:tags":[
        "nurse",
        "nursing"
    ],
    "wof:name":"Williamson Janet",
    "wof:placetype":"venue"
},
  "geometry": {"coordinates":[151.16558837900001,-33.7723197937],"type":"Point"}
}