{
  "type": "Feature",
  "properties": {
    "iso:country":"AU",
    "sg:address":"14 George St",
    "sg:city":"Green Fields",
    "sg:classifiers":[
        {
            "category":"Manufacturing",
            "subcategory":"Wood Products",
            "type":"Manufacturing & Wholesale Goods"
        }
    ],
    "sg:phone":"+61 8 8182 0411",
    "sg:postcode":"5107",
    "sg:province":"SA",
    "sg:tags":[
        "resin"
    ],
    "wof:name":"Nuplex Industries (Aust) Pty Ltd",
    "wof:placetype":"venue"
},
  "geometry": {"coordinates":[138.602249145,-34.7937469482],"type":"Point"}
}