{
  "type": "Feature",
  "properties": {
    "iso:country":"AU",
    "sg:address":"Cnr Tank & Goondoon St",
    "sg:city":"Gladstone",
    "sg:classifiers":[
        {
            "category":"Organizations",
            "subcategory":"Professional Association",
            "type":"Services"
        }
    ],
    "sg:phone":"+61 1300 306 126",
    "sg:postcode":"4680",
    "sg:province":"QLD",
    "sg:tags":[
        "web",
        "internet"
    ],
    "wof:name":"Dreamtilt",
    "wof:placetype":"venue"
},
  "geometry": {"coordinates":[151.257568359,-23.8499412537],"type":"Point"}
}