{
  "type": "Feature",
  "properties": {
    "addr:full":"Lot 1, Main Rd North Rothbury NSW 2335",
    "addr:housenumber":"1",
    "addr:postcode":"2335",
    "addr:street":"Main Rd North",
    "iso:country":"AU",
    "sg:address":"Lot 1, Main Rd",
    "sg:city":"North Rothbury",
    "sg:classifiers":[
        {
            "category":"Landmark",
            "subcategory":"Unesco World Heritage Site",
            "type":"Public Place"
        }
    ],
    "sg:phone":"+61 1800 028 568",
    "sg:postcode":"2335",
    "sg:province":"NSW",
    "sg:tags":[
        "balloon",
        "hot",
        "air"
    ],
    "wof:name":"Balloon Aloft Australia",
    "wof:placetype":"venue"
},
  "geometry": {"coordinates":[151.35171508799999,-32.6742172241],"type":"Point"}
}