{
  "type": "Feature",
  "properties": {
    "addr:full":"256 Molesworth St Lismore NSW 2480",
    "addr:housenumber":"256",
    "addr:postcode":"2480",
    "addr:street":"Molesworth St",
    "iso:country":"AU",
    "sg:address":"256 Molesworth St",
    "sg:city":"Lismore",
    "sg:classifiers":[
        {
            "category":"Banks & Credit Unions",
            "subcategory":"Financial Services",
            "type":"Services"
        }
    ],
    "sg:phone":"+61 1300 364 799",
    "sg:postcode":"2480",
    "sg:province":"NSW",
    "sg:tags":[
        "loan",
        "finance",
        "mortgage"
    ],
    "wof:name":"First Pacific Credit Union Ltd",
    "wof:placetype":"venue"
},
  "geometry": {"coordinates":[153.27418518100001,-28.8115367889],"type":"Point"}
}