{
  "type": "Feature",
  "properties": {
    "addr:full":"18 Virginia St Mornington VIC 3931",
    "addr:housenumber":"18",
    "addr:postcode":"3931",
    "addr:street":"Virginia St",
    "iso:country":"AU",
    "sg:address":"18 Virginia St",
    "sg:city":"Mornington",
    "sg:classifiers":[
        {
            "category":"Shopping",
            "subcategory":"Clothing, Apparel, & Fashions",
            "type":"Retail Goods"
        }
    ],
    "sg:phone":"+61 3 5975 0411",
    "sg:postcode":"3931",
    "sg:province":"VIC",
    "sg:tags":[
        "recycled",
        "clothing"
    ],
    "wof:name":"Bayside Recycling",
    "wof:placetype":"venue"
},
  "geometry": {"coordinates":[145.048919678,-38.2320671082],"type":"Point"}
}