{
  "type": "Feature",
  "properties": {
    "addr:full":"5 Ashford St Templestowe Lower VIC 3107",
    "addr:housenumber":"5",
    "addr:postcode":"3107",
    "addr:street":"Ashford St",
    "iso:country":"AU",
    "sg:address":"5 Ashford St",
    "sg:city":"Templestowe Lower",
    "sg:classifiers":[
        {
            "category":"Building & Trades",
            "subcategory":"Landscaping Services",
            "type":"Services"
        }
    ],
    "sg:phone":"+61 419 598 013",
    "sg:postcode":"3107",
    "sg:province":"VIC",
    "sg:tags":[
        "designer",
        "landscape",
        "contractor"
    ],
    "wof:name":"R & N Landscaping",
    "wof:placetype":"venue"
},
  "geometry": {"coordinates":[145.12031555199999,-37.7589645386],"type":"Point"}
}