{
  "type": "Feature",
  "properties": {
    "addr:full":"3/ 111 Industrial Rd Oak Flats NSW 2529",
    "addr:housenumber":"/ 111",
    "addr:postcode":"2529",
    "addr:street":"Industrial Rd",
    "iso:country":"AU",
    "sg:address":"3/ 111 Industrial Rd",
    "sg:city":"Oak Flats",
    "sg:classifiers":[
        {
            "category":"Wholesale",
            "subcategory":"Machinery & Supplies",
            "type":"Manufacturing & Wholesale Goods"
        }
    ],
    "sg:phone":"+61 2 4257 9700",
    "sg:postcode":"2529",
    "sg:province":"NSW",
    "sg:tags":[
        "equipment",
        "welding"
    ],
    "wof:name":"Shellharbour Industrial Distributors",
    "wof:placetype":"venue"
},
  "geometry": {"coordinates":[150.80984497099999,-34.5668373108],"type":"Point"}
}