{
  "type": "Feature",
  "properties": {
    "addr:full":"28 Harry St Doncaster East VIC 3109",
    "addr:housenumber":"28",
    "addr:postcode":"3109",
    "addr:street":"Harry St",
    "iso:country":"AU",
    "sg:address":"28 Harry St",
    "sg:city":"Doncaster East",
    "sg:classifiers":[
        {
            "category":"Banks & Credit Unions",
            "subcategory":"Bank",
            "type":"Services"
        }
    ],
    "sg:phone":"+61 3 9842 3611",
    "sg:postcode":"3109",
    "sg:province":"VIC",
    "sg:tags":[
        "concrete",
        "reinforcement"
    ],
    "wof:name":"P P Steel Fixers",
    "wof:placetype":"venue"
},
  "geometry": {"coordinates":[145.164718628,-37.7964363098],"type":"Point"}
}