{
  "type": "Feature",
  "properties": {
    "iso:country":"AU",
    "sg:address":"129 Hilma St",
    "sg:city":"Sunshine West",
    "sg:classifiers":[
        {
            "category":"Shopping",
            "subcategory":"Mobile Phones",
            "type":"Retail Goods"
        }
    ],
    "sg:phone":"+61 411 758 073",
    "sg:postcode":"3020",
    "sg:province":"VIC",
    "sg:tags":[
        "telephone",
        "accessory"
    ],
    "wof:name":"High Sierra Communications",
    "wof:placetype":"venue"
},
  "geometry": {"coordinates":[144.794373,-37.790665],"type":"Point"}
}