{
  "type": "Feature",
  "properties": {
    "iso:country":"AU",
    "sg:address":"113 Blackshaws Rd",
    "sg:city":"Newport",
    "sg:classifiers":[
        {
            "category":"Building & Trades",
            "subcategory":"Plumbing",
            "type":"Services"
        }
    ],
    "sg:phone":"+61 3 9399 1211",
    "sg:postcode":"3015",
    "sg:province":"VIC",
    "sg:tags":[
        "fitting",
        "hose",
        "supply"
    ],
    "wof:name":"Dodge Industrial Supplies Pty Ltd",
    "wof:placetype":"venue"
},
  "geometry": {"coordinates":[144.87396240199999,-37.834072113],"type":"Point"}
}