{
  "type": "Feature",
  "properties": {
    "addr:full":"50 Molesworth St Tenterfield NSW 2372",
    "addr:housenumber":"50",
    "addr:postcode":"2372",
    "addr:street":"Molesworth St",
    "iso:country":"AU",
    "sg:address":"50 Molesworth St",
    "sg:city":"Tenterfield",
    "sg:classifiers":[
        {
            "category":"Building & Trades",
            "subcategory":"Construction",
            "type":"Services"
        }
    ],
    "sg:phone":"+61 2 6736 1708",
    "sg:postcode":"2372",
    "sg:province":"NSW",
    "sg:tags":[
        "contractor"
    ],
    "wof:name":"Graham F J",
    "wof:placetype":"venue"
},
  "geometry": {"coordinates":[152.01832580600001,-29.0511226654],"type":"Point"}
}