{
  "type": "Feature",
  "properties": {
    "addr:full":"\"Kurrajong\" Kareela Rd Wingello NSW 2579",
    "addr:postcode":"2579",
    "addr:street":"Kareela Rd",
    "iso:country":"AU",
    "sg:address":"\"Kurrajong\" Kareela Rd",
    "sg:city":"Wingello",
    "sg:classifiers":[
        {
            "category":"Building & Trades",
            "subcategory":"Construction",
            "type":"Services"
        }
    ],
    "sg:phone":"+61 2 4884 4411",
    "sg:postcode":"2579",
    "sg:province":"NSW",
    "sg:tags":[
        "contractor"
    ],
    "wof:name":"Christie Trevor Builder",
    "wof:placetype":"venue"
},
  "geometry": {"coordinates":[150.15298461899999,-34.6951141357],"type":"Point"}
}