{
  "type": "Feature",
  "properties": {
    "addr:full":"2 Bay View St Bayswater WA 6053",
    "addr:housenumber":"2",
    "addr:postcode":"6053",
    "addr:street":"Bay View St",
    "iso:country":"AU",
    "sg:address":"2 Bay View St",
    "sg:city":"Bayswater",
    "sg:classifiers":[
        {
            "category":"Education",
            "subcategory":"School",
            "type":"Public Place"
        }
    ],
    "sg:phone":"+61 8 9271 5694",
    "sg:postcode":"6053",
    "sg:province":"WA",
    "sg:tags":[
        "state",
        "except",
        "nsw"
    ],
    "wof:name":"Hillcrest Pre-Primary",
    "wof:placetype":"venue"
},
  "geometry": {"coordinates":[115.90235900899999,-31.9093093872],"type":"Point"}
}