{
  "type": "Feature",
  "properties": {
    "addr:full":"Warrenheip St Buninyong VIC 3357",
    "addr:postcode":"3357",
    "addr:street":"Warrenheip St",
    "iso:country":"AU",
    "sg:address":"Warrenheip St",
    "sg:city":"Buninyong",
    "sg:classifiers":[
        {
            "category":"Travel",
            "subcategory":"Hotels & Motels",
            "type":"Entertainment"
        }
    ],
    "sg:phone":"+61 3 5341 3402",
    "sg:postcode":"3357",
    "sg:province":"VIC",
    "sg:tags":[
        "accommodation"
    ],
    "wof:name":"Crown Hotel",
    "wof:placetype":"venue"
},
  "geometry": {"coordinates":[143.884018,-37.650097],"type":"Point"}
}