{
  "type": "Feature",
  "properties": {
    "addr:full":"Wattle St Tullibigeal NSW 2669",
    "addr:postcode":"2669",
    "addr:street":"Wattle St",
    "iso:country":"AU",
    "sg:address":"Wattle St",
    "sg:city":"Tullibigeal",
    "sg:classifiers":[
        {
            "category":"Shopping",
            "type":"Retail Goods"
        }
    ],
    "sg:phone":"+61 2 6972 9176",
    "sg:postcode":"2669",
    "sg:province":"NSW",
    "sg:tags":[
        "agent",
        "stock"
    ],
    "wof:name":"Frankel M J & Son",
    "wof:placetype":"venue"
},
  "geometry": {"coordinates":[146.72787475600001,-33.4212875366],"type":"Point"}
}