{
  "type": "Feature",
  "properties": {
    "addr:full":"Level 11/ 234 Georges St Sydney NSW 2000",
    "addr:housenumber":"/ 234",
    "addr:postcode":"2000",
    "addr:street":"Georges St",
    "iso:country":"AU",
    "sg:address":"Level 11/ 234 Georges St",
    "sg:city":"Sydney",
    "sg:classifiers":[
        {
            "category":"Communications",
            "subcategory":"News Services",
            "type":"Services"
        }
    ],
    "sg:phone":"+61 2 9252 9838",
    "sg:postcode":"2000",
    "sg:province":"NSW",
    "sg:tags":[
        "information",
        "tourist",
        "attractions"
    ],
    "wof:name":"China National Tourist Office",
    "wof:placetype":"venue"
},
  "geometry": {"coordinates":[151.20765685999999,-33.8633384705],"type":"Point"}
}