{
  "type": "Feature",
  "properties": {
    "addr:full":"145 Pacific Hwy Hornsby NSW 2077",
    "addr:housenumber":"145",
    "addr:postcode":"2077",
    "addr:street":"Pacific Hwy",
    "iso:country":"AU",
    "sg:address":"145 Pacific Hwy",
    "sg:city":"Hornsby",
    "sg:classifiers":[
        {
            "category":"Home & Garden",
            "subcategory":"Household Appliances",
            "type":"Retail Goods"
        }
    ],
    "sg:phone":"+61 2 9482 7411",
    "sg:postcode":"2077",
    "sg:province":"NSW",
    "sg:tags":[
        "heating",
        "system"
    ],
    "wof:name":"AGL Energy Shop Hornsby",
    "wof:placetype":"venue"
},
  "geometry": {"coordinates":[151.097381592,-33.7040634155],"type":"Point"}
}