{
  "type": "Feature",
  "properties": {
    "addr:full":"209A Edward St Wagga Wagga NSW 2650",
    "addr:housenumber":"209a",
    "addr:postcode":"2650",
    "addr:street":"Edward St",
    "iso:country":"AU",
    "sg:address":"209A Edward St",
    "sg:city":"Wagga Wagga",
    "sg:classifiers":[
        {
            "category":"Professional",
            "subcategory":"Art Services",
            "type":"Services"
        }
    ],
    "sg:phone":"+61 2 6931 9100",
    "sg:postcode":"2650",
    "sg:province":"NSW",
    "sg:tags":[
        "picture",
        "frame",
        "framing"
    ],
    "wof:name":"Willy Sheather Gallery",
    "wof:placetype":"venue"
},
  "geometry": {"coordinates":[147.34783935600001,-35.1159858704],"type":"Point"}
}