{
  "type": "Feature",
  "properties": {
    "iso:country":"AU",
    "sg:address":"Factory 6, 18 Sloane St",
    "sg:city":"Maribyrnong",
    "sg:classifiers":[
        {
            "category":"Building & Trades",
            "subcategory":"Construction",
            "type":"Services"
        }
    ],
    "sg:phone":"+61 417 367 507",
    "sg:postcode":"3032",
    "sg:province":"VIC",
    "sg:tags":[
        "fencing",
        "contractor"
    ],
    "wof:name":"Essendon Pickets",
    "wof:placetype":"venue"
},
  "geometry": {"coordinates":[144.883423,-37.774475],"type":"Point"}
}