{
  "type": "Feature",
  "properties": {
    "addr:full":"Suite 2, 79 Tamar St Ballina NSW 2478",
    "addr:housenumber":"79",
    "addr:postcode":"2478",
    "addr:street":"Tamar St",
    "iso:country":"AU",
    "sg:address":"Suite 2, 79 Tamar St",
    "sg:city":"Ballina",
    "sg:classifiers":[
        {
            "category":"Insurance",
            "subcategory":"Insurance Agent",
            "type":"Services"
        }
    ],
    "sg:phone":"+61 2 6686 4488",
    "sg:postcode":"2478",
    "sg:province":"NSW",
    "sg:tags":[
        "broker"
    ],
    "wof:name":"Corporate Insurance Brokers Ballina Pty Ltd",
    "wof:placetype":"venue"
},
  "geometry": {"coordinates":[153.56048584000001,-28.8689136505],"type":"Point"}
}