{
  "type": "Feature",
  "properties": {
    "addr:full":"27 Burgundy St Waurn Ponds VIC 3216",
    "addr:housenumber":"27",
    "addr:postcode":"3216",
    "addr:street":"Burgundy St",
    "iso:country":"AU",
    "sg:address":"27 Burgundy St",
    "sg:city":"Waurn Ponds",
    "sg:classifiers":[
        {
            "category":"Utilities",
            "subcategory":"Electric",
            "type":"Services"
        }
    ],
    "sg:phone":"+61 418 177 342",
    "sg:postcode":"3216",
    "sg:province":"VIC",
    "sg:tags":[
        "electrical",
        "contractor"
    ],
    "wof:name":"Stephen Johnson Electrics",
    "wof:placetype":"venue"
},
  "geometry": {"coordinates":[144.30563354500001,-38.2058410645],"type":"Point"}
}