{
  "type": "Feature",
  "properties": {
    "addr:full":"Unit 5/ 27 Truganina Rd Malaga WA 6090",
    "addr:postcode":"6090",
    "addr:street":"Truganina Rd",
    "iso:country":"AU",
    "sg:address":"Unit 5/ 27 Truganina Rd",
    "sg:city":"Malaga",
    "sg:classifiers":[
        {
            "category":"Professional",
            "subcategory":"Art Services",
            "type":"Services"
        }
    ],
    "sg:phone":"+61 8 9248 2086",
    "sg:postcode":"6090",
    "sg:province":"WA",
    "sg:tags":[
        "conservation",
        "restoration"
    ],
    "wof:name":"Impact Panel & Paint",
    "wof:placetype":"venue"
},
  "geometry": {"coordinates":[115.885536194,-31.8639278412],"type":"Point"}
}