{
  "type": "Feature",
  "properties": {
    "addr:full":"GPO Box 4116 Darwin NT 0800",
    "addr:postcode":"nt 0800",
    "iso:country":"AU",
    "sg:address":"GPO Box 4116",
    "sg:city":"Darwin",
    "sg:classifiers":[
        {
            "category":"Personal",
            "type":"Services"
        }
    ],
    "sg:phone":"+61 8 8941 7000",
    "sg:postcode":"0800",
    "sg:province":"NT",
    "sg:tags":[
        "introduction",
        "social"
    ],
    "wof:name":"Dinner For Six (N.T.)",
    "wof:placetype":"venue"
},
  "geometry": {"coordinates":[130.84231567399999,-12.4620399475],"type":"Point"}
}