{
  "type": "Feature",
  "properties": {
    "addr:full":"110 Taylor St Armidale NSW 2350",
    "addr:housenumber":"110",
    "addr:postcode":"2350",
    "addr:street":"Taylor St",
    "iso:country":"AU",
    "sg:address":"110 Taylor St",
    "sg:city":"Armidale",
    "sg:classifiers":[
        {
            "category":"Train Station",
            "subcategory":"Light Rail",
            "type":"Transportation"
        }
    ],
    "sg:phone":"+61 2 6772 6233",
    "sg:postcode":"2350",
    "sg:province":"NSW",
    "sg:tags":[
        "equipment",
        "energy",
        "solar"
    ],
    "wof:name":"New England Solar Power",
    "wof:placetype":"venue"
},
  "geometry": {"coordinates":[151.67132568400001,-30.5151901245],"type":"Point"}
}