{
  "type": "Feature",
  "properties": {
    "addr:full":"532 Old Northern Rd Dural NSW 2158",
    "addr:housenumber":"532",
    "addr:postcode":"2158",
    "addr:street":"Old Northern Rd",
    "iso:country":"AU",
    "sg:address":"532 Old Northern Rd",
    "sg:city":"Dural",
    "sg:classifiers":[
        {
            "category":"Retail",
            "subcategory":"Auto Rental",
            "type":"Services"
        }
    ],
    "sg:phone":"+61 2 9651 2306",
    "sg:postcode":"2158",
    "sg:province":"NSW",
    "sg:tags":[
        "car",
        "hire",
        "minibus"
    ],
    "wof:name":"A AAAscot Car Rentals",
    "wof:placetype":"venue"
},
  "geometry": {"coordinates":[151.022613525,-33.6948280334],"type":"Point"}
}