{
  "type": "Feature",
  "properties": {
    "iso:country":"AU",
    "sg:address":"Suite 6a, 27 Dale St",
    "sg:city":"Brookvale",
    "sg:classifiers":[
        {
            "category":"Shopping",
            "subcategory":"Computers & Home Electronics",
            "type":"Retail Goods"
        }
    ],
    "sg:phone":"+61 2 9905 3373",
    "sg:postcode":"2100",
    "sg:province":"NSW",
    "sg:tags":[
        "global",
        "positioning",
        "system"
    ],
    "wof:name":"Trackonline",
    "wof:placetype":"venue"
},
  "geometry": {"coordinates":[151.26858520499999,-33.765045166],"type":"Point"}
}