{
  "type": "Feature",
  "properties": {
    "iso:country":"AU",
    "sg:address":"8 Stirling St",
    "sg:city":"Fremantle",
    "sg:classifiers":[
        {
            "category":"Real Estate",
            "subcategory":"Surveying",
            "type":"Services"
        }
    ],
    "sg:phone":"+61 8 9335 6222",
    "sg:postcode":"6160",
    "sg:province":"WA",
    "sg:tags":[
        "surveyor",
        "land"
    ],
    "wof:name":"Giudice Surveys",
    "wof:placetype":"venue"
},
  "geometry": {"coordinates":[115.754158,-32.052231],"type":"Point"}
}