{
  "type": "Feature",
  "properties": {
    "iso:country":"AU",
    "sg:address":"PO Box 1161 CP",
    "sg:city":"Mildura",
    "sg:classifiers":[
        {
            "category":"Building & Trades",
            "subcategory":"Construction",
            "type":"Services"
        }
    ],
    "sg:phone":"+61 408 210 304",
    "sg:postcode":"3501",
    "sg:province":"VIC",
    "sg:tags":[
        "concrete",
        "contractor"
    ],
    "wof:name":"Roger Bath Concreting",
    "wof:placetype":"venue"
},
  "geometry": {"coordinates":[142.161712647,-34.186050415],"type":"Point"}
}