{
  "type": "Feature",
  "properties": {
    "iso:country":"AU",
    "sg:address":"6- 10 Wellington St",
    "sg:city":"Longford",
    "sg:classifiers":[
        {
            "category":"Wholesale",
            "subcategory":"Farm Supplies",
            "type":"Manufacturing & Wholesale Goods"
        }
    ],
    "sg:phone":"+61 3 6391 2411",
    "sg:postcode":"7301",
    "sg:province":"TAS",
    "sg:tags":[
        "equipment"
    ],
    "wof:name":"Farm Machinery Tasmania",
    "wof:placetype":"venue"
},
  "geometry": {"coordinates":[147.11909499999999,-41.588074],"type":"Point"}
}