{
  "type": "Feature",
  "properties": {
    "iso:country":"AU",
    "sg:address":"Kaoota Rd",
    "sg:city":"Lindisfarne",
    "sg:classifiers":[
        {
            "category":"Education",
            "subcategory":"School",
            "type":"Public Place"
        }
    ],
    "sg:phone":"+61 3 6233 7786",
    "sg:postcode":"7015",
    "sg:province":"TAS",
    "sg:tags":[
        "correspondence"
    ],
    "wof:name":"Distance Education Tasmania",
    "wof:placetype":"venue"
},
  "geometry": {"coordinates":[147.35899352999999,-42.8537788391],"type":"Point"}
}