{
  "type": "Feature",
  "properties": {
    "iso:country":"AU",
    "sg:address":"5/ 21a Victoria Ave",
    "sg:city":"Castle Hill",
    "sg:classifiers":[
        {
            "category":"Home & Garden",
            "subcategory":"Household Appliances",
            "type":"Retail Goods"
        }
    ],
    "sg:phone":"+61 2 9894 7950",
    "sg:postcode":"2154",
    "sg:province":"NSW",
    "sg:tags":[
        "heating",
        "system"
    ],
    "wof:name":"Lopi",
    "wof:placetype":"venue"
},
  "geometry": {"coordinates":[150.97947692899999,-33.7297973633],"type":"Point"}
}