{
  "type": "Feature",
  "properties": {
    "addr:full":"1/ 144 Tyler St Tuart Hill WA 6060",
    "addr:housenumber":"/ 144",
    "addr:postcode":"6060",
    "addr:street":"Tyler St",
    "iso:country":"AU",
    "sg:address":"1/ 144 Tyler St",
    "sg:city":"Tuart Hill",
    "sg:classifiers":[
        {
            "category":"Personal",
            "subcategory":"Massage",
            "type":"Services"
        }
    ],
    "sg:phone":"+61 8 9345 5477",
    "sg:postcode":"6060",
    "sg:province":"WA",
    "sg:tags":[
        "therapy"
    ],
    "wof:name":"Dee Ms Sue",
    "wof:placetype":"venue"
},
  "geometry": {"coordinates":[115.831047058,-31.8998508453],"type":"Point"}
}