{
  "type": "Feature",
  "properties": {
    "addr:full":"8 Tannery Rd Dubbo NSW 2830",
    "addr:housenumber":"8",
    "addr:postcode":"2830",
    "addr:street":"Tannery Rd",
    "iso:country":"AU",
    "sg:address":"8 Tannery Rd",
    "sg:city":"Dubbo",
    "sg:classifiers":[
        {
            "category":"Building & Trades",
            "subcategory":"Construction",
            "type":"Services"
        }
    ],
    "sg:phone":"+61 419 221 446",
    "sg:postcode":"2830",
    "sg:province":"NSW",
    "sg:tags":[
        "welding"
    ],
    "wof:name":"Smyth's Structural Steel Fabrication",
    "wof:placetype":"venue"
},
  "geometry": {"coordinates":[148.62139892600001,-32.2197608948],"type":"Point"}
}