{
  "type": "Feature",
  "properties": {
    "addr:full":"4 Engineering St Salisbury QLD 4107",
    "addr:housenumber":"4",
    "addr:postcode":"4107",
    "addr:street":"Engineering St",
    "iso:country":"AU",
    "sg:address":"4 Engineering St",
    "sg:city":"Salisbury",
    "sg:classifiers":[
        {
            "category":"Building & Trades",
            "subcategory":"Construction",
            "type":"Services"
        }
    ],
    "sg:phone":"+61 7 3277 2011",
    "sg:postcode":"4107",
    "sg:province":"QLD",
    "sg:tags":[
        "road",
        "contractor"
    ],
    "wof:name":"FRH Fulton Hogan-Astec",
    "wof:placetype":"venue"
},
  "geometry": {"coordinates":[153.029205322,-27.5455322266],"type":"Point"}
}