{
  "type": "Feature",
  "properties": {
    "addr:full":"395 Princes Hwy Rockdale NSW 2216",
    "addr:housenumber":"395",
    "addr:postcode":"2216",
    "addr:street":"Princes Hwy",
    "iso:country":"AU",
    "sg:address":"395 Princes Hwy",
    "sg:city":"Rockdale",
    "sg:classifiers":[
        {
            "category":"Autos & Motor Vehicles",
            "subcategory":"Automobile Sales",
            "type":"Retail Goods"
        }
    ],
    "sg:phone":"+61 2 9567 7888",
    "sg:postcode":"2216",
    "sg:province":"NSW",
    "sg:tags":[
        "car",
        "used"
    ],
    "wof:name":"Greggarys",
    "wof:placetype":"venue"
},
  "geometry": {"coordinates":[151.137787,-33.958656],"type":"Point"}
}