{
  "type": "Feature",
  "properties": {
    "addr:full":"U3/ 5 Salvado Ave East Fremantle WA 6158",
    "addr:housenumber":"5",
    "addr:postcode":"6158",
    "addr:street":"U3 /;Salvado Ave",
    "iso:country":"AU",
    "sg:address":"U3/ 5 Salvado Ave",
    "sg:city":"East Fremantle",
    "sg:classifiers":[
        {
            "category":"Building & Trades",
            "subcategory":"Construction",
            "type":"Services"
        }
    ],
    "sg:phone":"+61 8 9438 1165",
    "sg:postcode":"6158",
    "sg:province":"WA",
    "sg:tags":[
        "rigging",
        "erection",
        "contractor"
    ],
    "wof:name":"Artistic Steel Pty Ltd",
    "wof:placetype":"venue"
},
  "geometry": {"coordinates":[115.766869,-32.037727],"type":"Point"}
}