{
  "type": "Feature",
  "properties": {
    "addr:full":"4 Ann St Salisbury SA 5108",
    "addr:housenumber":"4",
    "addr:postcode":"5108",
    "addr:street":"Ann St",
    "iso:country":"AU",
    "sg:address":"4 Ann St",
    "sg:city":"Salisbury",
    "sg:classifiers":[
        {
            "category":"Health Services",
            "subcategory":"Doctor",
            "type":"Services"
        }
    ],
    "sg:phone":"+61 8 8267 3976",
    "sg:postcode":"5108",
    "sg:province":"SA",
    "sg:tags":[
        "medical",
        "practitioner"
    ],
    "wof:name":"Harries Richard F.R.A.C.S.",
    "wof:placetype":"venue"
},
  "geometry": {"coordinates":[138.64857482900001,-34.7628364563],"type":"Point"}
}