{
  "type": "Feature",
  "properties": {
    "addr:full":"Depot Godwin Island Forster NSW 2428",
    "addr:postcode":"2428",
    "iso:country":"AU",
    "sg:address":"Depot Godwin Island",
    "sg:city":"Forster",
    "sg:classifiers":[
        {
            "category":"Farming",
            "subcategory":"Fish & Marine Products",
            "type":"Manufacturing & Wholesale Goods"
        }
    ],
    "sg:phone":"+61 2 6555 6085",
    "sg:postcode":"2428",
    "sg:province":"NSW",
    "sg:tags":[
        "supplier",
        "oyster",
        "farmer"
    ],
    "wof:name":"Ravell J & J Oysters",
    "wof:placetype":"venue"
},
  "geometry": {"coordinates":[152.48315400000001,-32.179646],"type":"Point"}
}