{
  "type": "Feature",
  "properties": {
    "addr:full":"51 Wattlepark Ave Moolap VIC 3221",
    "addr:housenumber":"51",
    "addr:postcode":"3221",
    "addr:street":"Wattlepark Ave",
    "iso:country":"AU",
    "sg:address":"51 Wattlepark Ave",
    "sg:city":"Moolap",
    "sg:classifiers":[
        {
            "category":"Manufacturing",
            "subcategory":"Tools & Machinery",
            "type":"Manufacturing & Wholesale Goods"
        }
    ],
    "sg:phone":"+61 3 5248 1944",
    "sg:postcode":"3221",
    "sg:province":"VIC",
    "sg:tags":[
        "earth",
        "excavating",
        "moving",
        "equipment"
    ],
    "wof:name":"Geelong Hardchrome Services",
    "wof:placetype":"venue"
},
  "geometry": {"coordinates":[144.40898100000001,-38.167095],"type":"Point"}
}