{
  "type": "Feature",
  "properties": {
    "addr:full":"Cnr Stock Rd & Barrington St Spearwood WA 6163",
    "addr:postcode":"6163",
    "addr:street":"Stock Rd & Barrington St",
    "iso:country":"AU",
    "sg:address":"Cnr Stock Rd & Barrington St",
    "sg:city":"Spearwood",
    "sg:classifiers":[
        {
            "category":"Retail",
            "subcategory":"Auto Repair",
            "type":"Services"
        }
    ],
    "sg:phone":"+61 412 915 516",
    "sg:postcode":"6163",
    "sg:province":"WA",
    "sg:tags":[
        "electrical"
    ],
    "wof:name":"Micks Auto Electrics",
    "wof:placetype":"venue"
},
  "geometry": {"coordinates":[115.79454800000001,-32.112591],"type":"Point"}
}