{
  "type": "Feature",
  "properties": {
    "addr:full":"8 /9 60 Dellamarta Rd Wangara WA 6065",
    "addr:housenumber":"/;60",
    "addr:postcode":"6065",
    "addr:street":"9;Dellamarta Rd",
    "iso:country":"AU",
    "sg:address":"8 /9 60 Dellamarta Rd",
    "sg:city":"Wangara",
    "sg:classifiers":[
        {
            "category":"Autos & Motor Vehicles",
            "subcategory":"Auto Supplies",
            "type":"Retail Goods"
        }
    ],
    "sg:phone":"+61 8 9409 7433",
    "sg:postcode":"6065",
    "sg:province":"WA",
    "sg:tags":[
        "camper-trailers",
        "caravan",
        "equipment"
    ],
    "sg:website":"http://www.outbackcampers.net",
    "wof:name":"Outback Campers",
    "wof:placetype":"venue"
},
  "geometry": {"coordinates":[115.826202393,-31.7909870148],"type":"Point"}
}