{
  "type": "Feature",
  "properties": {
    "addr:full":"Cnr Beach Rd & Bavarde Ave Batemans Bay NSW 2536",
    "addr:postcode":"2536",
    "addr:street":"Cnr Beach Rd & Bavarde Ave",
    "iso:country":"AU",
    "sg:address":"Cnr Beach Rd & Bavarde Ave",
    "sg:city":"Batemans Bay",
    "sg:classifiers":[
        {
            "category":"Health Services",
            "subcategory":"Dentist",
            "type":"Services"
        }
    ],
    "sg:phone":"+61 2 4472 4113",
    "sg:postcode":"2536",
    "sg:province":"NSW",
    "wof:name":"Gifford R",
    "wof:placetype":"venue"
},
  "geometry": {"coordinates":[150.17732238799999,-35.7083892822],"type":"Point"}
}