{
  "type": "Feature",
  "properties": {
    "iso:country":"AU",
    "sg:address":"1/ 5 Glen Ebor Ave",
    "sg:city":"Blackburn",
    "sg:classifiers":[
        {
            "category":"Health Services",
            "subcategory":"Health Practitioner",
            "type":"Services"
        }
    ],
    "sg:phone":"+61 3 9584 8094",
    "sg:postcode":"3130",
    "sg:province":"VIC",
    "sg:tags":[
        "naturopath"
    ],
    "wof:name":"Alison Blundy",
    "wof:placetype":"venue"
},
  "geometry": {"coordinates":[145.15798950199999,-37.8214683533],"type":"Point"}
}