{
  "type": "Feature",
  "properties": {
    "iso:country":"AU",
    "sg:address":"Shop 73, Stocklands Centre 90 Middle St",
    "sg:city":"Cleveland",
    "sg:classifiers":[
        {
            "category":"Fast Food",
            "type":"Food & Drink"
        }
    ],
    "sg:phone":"+61 7 3286 2277",
    "sg:postcode":"4163",
    "sg:province":"QLD",
    "sg:tags":[
        "away",
        "take"
    ],
    "wof:name":"Kiss My Fish",
    "wof:placetype":"venue"
},
  "geometry": {"coordinates":[153.26873779300001,-27.5257987976],"type":"Point"}
}