{
  "type": "Feature",
  "properties": {
    "addr:full":"31 Minnamurra Ave Pymble NSW 2073",
    "addr:housenumber":"31",
    "addr:postcode":"2073",
    "addr:street":"Minnamurra Ave",
    "iso:country":"AU",
    "sg:address":"31 Minnamurra Ave",
    "sg:city":"Pymble",
    "sg:classifiers":[
        {
            "category":"Building & Trades",
            "subcategory":"Construction",
            "type":"Services"
        }
    ],
    "sg:phone":"+61 2 9498 2562",
    "sg:postcode":"2073",
    "sg:province":"NSW",
    "sg:tags":[
        "window",
        "timber"
    ],
    "wof:name":"Sydney Window Installations Pty Ltd",
    "wof:placetype":"venue"
},
  "geometry": {"coordinates":[151.14019775400001,-33.7577590942],"type":"Point"}
}