{
  "type": "Feature",
  "properties": {
    "iso:country":"AU",
    "sg:address":"55` Smyth St",
    "sg:city":"Benalla",
    "sg:classifiers":[
        {
            "category":"Food & Beverages",
            "subcategory":"Liquor & Beverages",
            "type":"Retail Goods"
        }
    ],
    "sg:phone":"+61 3 5762 7500",
    "sg:postcode":"3672",
    "sg:province":"VIC",
    "sg:tags":[
        "store"
    ],
    "wof:name":"Liquor Legends",
    "wof:placetype":"venue"
},
  "geometry": {"coordinates":[145.988327,-36.549969],"type":"Point"}
}