{
  "type": "Feature",
  "properties": {
    "addr:full":"263 Appleby Rd Stafford Heights QLD 4053",
    "addr:housenumber":"263",
    "addr:postcode":"4053",
    "addr:street":"Appleby Rd",
    "iso:country":"AU",
    "sg:address":"263 Appleby Rd",
    "sg:city":"Stafford Heights",
    "sg:classifiers":[
        {
            "category":"Retail",
            "subcategory":"Veterinary Services",
            "type":"Services"
        }
    ],
    "sg:phone":"+61 7 3359 0777",
    "sg:postcode":"4053",
    "sg:province":"QLD",
    "sg:tags":[
        "surgeon"
    ],
    "wof:name":"Straw Rod",
    "wof:placetype":"venue"
},
  "geometry": {"coordinates":[153.011154175,-27.3934192657],"type":"Point"}
}