{
  "type": "Feature",
  "properties": {
    "addr:full":"Centro Shopping Centre, Boat Harbour Drv Hervey Bay QLD 4655",
    "addr:postcode":"4655",
    "addr:street":"Boat Harbour Drv",
    "iso:country":"AU",
    "sg:address":"Centro Shopping Centre, Boat Harbour Drv",
    "sg:city":"Hervey Bay",
    "sg:classifiers":[
        {
            "category":"Travel",
            "subcategory":"Travel Agent",
            "type":"Entertainment"
        }
    ],
    "sg:phone":"+61 7 4128 3355",
    "sg:postcode":"4655",
    "sg:province":"QLD",
    "sg:tags":[
        "consultant"
    ],
    "wof:name":"Jetset Hervey Bay",
    "wof:placetype":"venue"
},
  "geometry": {"coordinates":[152.836288,-25.287842],"type":"Point"}
}