{
  "type": "Feature",
  "properties": {
    "iso:country":"AU",
    "sg:address":"PO Box 354",
    "sg:city":"Cessnock",
    "sg:classifiers":[
        {
            "category":"Personal",
            "type":"Services"
        }
    ],
    "sg:phone":"+61 2 4990 7771",
    "sg:postcode":"2325",
    "sg:province":"NSW",
    "sg:tags":[
        "gift"
    ],
    "wof:name":"Hobby Hampers",
    "wof:placetype":"venue"
},
  "geometry": {"coordinates":[151.354934692,-32.8325691223],"type":"Point"}
}