{
  "type": "Feature",
  "properties": {
    "iso:country":"AU",
    "sg:address":"246 St Mary's Rd",
    "sg:city":"Berkshire Park",
    "sg:classifiers":[
        {
            "category":"Building & Trades",
            "subcategory":"Plumbing",
            "type":"Services"
        }
    ],
    "sg:phone":"+61 2 4572 0974",
    "sg:postcode":"2765",
    "sg:province":"NSW",
    "sg:tags":[
        "equipment",
        "valves"
    ],
    "wof:name":"Flotech Solutions Pty Ltd",
    "wof:placetype":"venue"
},
  "geometry": {"coordinates":[150.77061462399999,-33.7093772888],"type":"Point"}
}