{
  "type": "Feature",
  "properties": {
    "addr:full":"80b Charles St Putney NSW 2112",
    "addr:housenumber":"80b",
    "addr:postcode":"2112",
    "addr:street":"Charles St",
    "iso:country":"AU",
    "sg:address":"80b Charles St",
    "sg:city":"Putney",
    "sg:classifiers":[
        {
            "category":"Health Services",
            "subcategory":"Dentist",
            "type":"Services"
        }
    ],
    "sg:phone":"+61 2 9809 7110",
    "sg:postcode":"2112",
    "sg:province":"NSW",
    "wof:name":"Patel Sushma Dr",
    "wof:placetype":"venue"
},
  "geometry": {"coordinates":[151.10911560100001,-33.8230514526],"type":"Point"}
}