{
  "type": "Feature",
  "properties": {
    "addr:full":"Ground Floor, 10 Valentine St Parramatta NSW 2150",
    "addr:housenumber":"10",
    "addr:postcode":"2150",
    "addr:street":"Valentine St",
    "iso:country":"AU",
    "sg:address":"Ground Floor, 10 Valentine St",
    "sg:city":"Parramatta",
    "sg:classifiers":[
        {
            "category":"Banks & Credit Unions",
            "subcategory":"Bank",
            "type":"Services"
        }
    ],
    "sg:phone":"+61 2 9891 4828",
    "sg:postcode":"2150",
    "sg:province":"NSW",
    "sg:tags":[
        "society"
    ],
    "wof:name":"Resources Credit Union Ltd",
    "wof:placetype":"venue"
},
  "geometry": {"coordinates":[150.905197144,-33.7842330933],"type":"Point"}
}