{
  "type": "Feature",
  "properties": {
    "addr:full":"14C Jijaws St Sumner Park QLD 4074",
    "addr:housenumber":"14c",
    "addr:postcode":"4074",
    "addr:street":"Jijaws St",
    "iso:country":"AU",
    "sg:address":"14C Jijaws St",
    "sg:city":"Sumner Park",
    "sg:classifiers":[
        {
            "category":"Wholesale",
            "subcategory":"Painting Supplies",
            "type":"Manufacturing & Wholesale Goods"
        }
    ],
    "sg:phone":"+61 7 3712 0038",
    "sg:postcode":"4074",
    "sg:province":"QLD",
    "sg:tags":[
        "product",
        "polyurethane"
    ],
    "wof:name":"Equis Industries Pty Ltd",
    "wof:placetype":"venue"
},
  "geometry": {"coordinates":[152.94012451200001,-27.5648975372],"type":"Point"}
}