{
  "type": "Feature",
  "properties": {
    "addr:full":"71 Lillicur Rd Montmorency VIC 3094",
    "addr:housenumber":"71",
    "addr:postcode":"3094",
    "addr:street":"Lillicur Rd",
    "iso:country":"AU",
    "sg:address":"71 Lillicur Rd",
    "sg:city":"Montmorency",
    "sg:classifiers":[
        {
            "category":"Shopping",
            "subcategory":"Gifts & Souvenirs",
            "type":"Retail Goods"
        }
    ],
    "sg:phone":"+61 3 9431 2676",
    "sg:postcode":"3094",
    "sg:province":"VIC",
    "sg:tags":[
        "shop",
        "supply"
    ],
    "wof:name":"Tradecorp Pty Ltd",
    "wof:placetype":"venue"
},
  "geometry": {"coordinates":[145.13070678700001,-37.7147521973],"type":"Point"}
}