{
  "type": "Feature",
  "properties": {
    "addr:full":"PO Box 25 Greenslopes QLD 4120",
    "addr:postcode":"4120",
    "iso:country":"AU",
    "sg:address":"PO Box 25",
    "sg:city":"Greenslopes",
    "sg:classifiers":[
        {
            "category":"Organizations",
            "subcategory":"Community Association",
            "type":"Services"
        }
    ],
    "sg:phone":"+61 417 632 844",
    "sg:postcode":"4120",
    "sg:province":"QLD",
    "sg:tags":[
        "organisation",
        "family",
        "welfare"
    ],
    "wof:name":"Post Natal Disorders Support Group Assn Inc",
    "wof:placetype":"venue"
},
  "geometry": {"coordinates":[153.05221557600001,-27.5098495483],"type":"Point"}
}