{
  "type": "Feature",
  "properties": {
    "iso:country":"AU",
    "sg:address":"31 Wentworth St",
    "sg:city":"Wallsend",
    "sg:classifiers":[
        {
            "category":"Professional",
            "subcategory":"Art Services",
            "type":"Services"
        }
    ],
    "sg:phone":"+61 411 743 828",
    "sg:postcode":"2287",
    "sg:province":"NSW",
    "sg:tags":[
        "decorator",
        "painter"
    ],
    "wof:name":"Burrows Mark",
    "wof:placetype":"venue"
},
  "geometry": {"coordinates":[151.664672852,-32.8968887329],"type":"Point"}
}