{
  "type": "Feature",
  "properties": {
    "iso:country":"AU",
    "sg:address":"10 Parker Farm Pl",
    "sg:city":"Casula",
    "sg:classifiers":[
        {
            "category":"Building & Trades",
            "subcategory":"Construction",
            "type":"Services"
        }
    ],
    "sg:phone":"+61 2 9602 1999",
    "sg:postcode":"2170",
    "sg:province":"NSW",
    "sg:tags":[
        "brick",
        "paving"
    ],
    "wof:name":"Flower Power Garden Centres",
    "wof:placetype":"venue"
},
  "geometry": {"coordinates":[150.88278198200001,-33.9599723816],"type":"Point"}
}