{
  "type": "Feature",
  "properties": {
    "addr:full":"Cnr Cranstons & Old Northern Road Dural NSW 2158",
    "addr:postcode":"2158",
    "addr:street":"Cnr Cranstons & Old Northern Road",
    "iso:country":"AU",
    "sg:address":"Cnr Cranstons & Old Northern Road",
    "sg:city":"Dural",
    "sg:classifiers":[
        {
            "category":"Shopping",
            "subcategory":"Party Supplies",
            "type":"Retail Goods"
        }
    ],
    "sg:phone":"+61 2 9651 1334",
    "sg:postcode":"2158",
    "sg:province":"NSW",
    "sg:tags":[
        "children's"
    ],
    "wof:name":"Dural Putt Putt",
    "wof:placetype":"venue"
},
  "geometry": {"coordinates":[151.01594543499999,-33.6500091553],"type":"Point"}
}