{
  "type": "Feature",
  "properties": {
    "iso:country":"AU",
    "sg:address":"18 Ascot Ave",
    "sg:city":"Westcourt",
    "sg:classifiers":[
        {
            "category":"Shopping",
            "subcategory":"Optical Goods",
            "type":"Retail Goods"
        }
    ],
    "sg:phone":"+61 7 4051 4546",
    "sg:postcode":"4870",
    "sg:province":"QLD",
    "sg:tags":[
        "supply"
    ],
    "wof:name":"Frame Care Australia",
    "wof:placetype":"venue"
},
  "geometry": {"coordinates":[145.75584411599999,-16.9325218201],"type":"Point"}
}