{
  "type": "Feature",
  "properties": {
    "iso:country":"AU",
    "sg:address":"Shop 2/ 2 Orient St",
    "sg:city":"Batemans Bay",
    "sg:classifiers":[
        {
            "category":"Banks & Credit Unions",
            "subcategory":"Bank",
            "type":"Services"
        }
    ],
    "sg:phone":"+61 1300 660 666",
    "sg:postcode":"2536",
    "sg:province":"NSW",
    "sg:tags":[
        "society"
    ],
    "wof:name":"CPS Credit Union Cooperative (ACT) Limited",
    "wof:placetype":"venue"
},
  "geometry": {"coordinates":[150.17794799800001,-35.7060966492],"type":"Point"}
}