{
  "type": "Feature",
  "properties": {
    "addr:full":"23b Edinburgh St Oakleigh South VIC 3167",
    "addr:housenumber":"23b",
    "addr:postcode":"3167",
    "addr:street":"Edinburgh St",
    "iso:country":"AU",
    "sg:address":"23b Edinburgh St",
    "sg:city":"Oakleigh South",
    "sg:classifiers":[
        {
            "category":"Professional",
            "subcategory":"Engineering",
            "type":"Services"
        }
    ],
    "sg:phone":"+61 3 9540 0440",
    "sg:postcode":"3167",
    "sg:province":"VIC",
    "sg:tags":[
        "engineer"
    ],
    "wof:name":"Shaw R L & A M Pty Ltd",
    "wof:placetype":"venue"
},
  "geometry": {"coordinates":[145.112426758,-37.9152908325],"type":"Point"}
}