{
  "type": "Feature",
  "properties": {
    "addr:full":"25 Clovelly Pl Sandstone Point QLD 4511",
    "addr:housenumber":"25",
    "addr:postcode":"4511",
    "addr:street":"Clovelly Pl",
    "iso:country":"AU",
    "sg:address":"25 Clovelly Pl",
    "sg:city":"Sandstone Point",
    "sg:classifiers":[
        {
            "category":"Building & Trades",
            "subcategory":"Construction",
            "type":"Services"
        }
    ],
    "sg:phone":"+61 1800 683 811",
    "sg:postcode":"4511",
    "sg:province":"QLD",
    "sg:tags":[
        "concrete",
        "paving"
    ],
    "wof:name":"Spraycrete",
    "wof:placetype":"venue"
},
  "geometry": {"coordinates":[153.124313,-27.080425],"type":"Point"}
}