{
  "type": "Feature",
  "properties": {
    "iso:country":"AU",
    "sg:address":"42A Batts St",
    "sg:city":"Emerald",
    "sg:classifiers":[
        {
            "category":"Freight",
            "type":"Transportation"
        }
    ],
    "sg:phone":"+61 7 4982 2061",
    "sg:postcode":"4720",
    "sg:province":"QLD",
    "sg:tags":[
        "light",
        "carrier"
    ],
    "wof:name":"McKenzies Tilt Trays & Transport Services",
    "wof:placetype":"venue"
},
  "geometry": {"coordinates":[148.147476,-23.523159],"type":"Point"}
}