{
  "type": "Feature",
  "properties": {
    "addr:full":"PO Box 244 Red Hill QLD 4059",
    "addr:postcode":"4059",
    "iso:country":"AU",
    "sg:address":"PO Box 244",
    "sg:city":"Red Hill",
    "sg:classifiers":[
        {
            "category":"Real Estate",
            "subcategory":"Real Estate Services",
            "type":"Services"
        }
    ],
    "sg:phone":"+61 1300 888 789",
    "sg:postcode":"4059",
    "sg:province":"QLD",
    "sg:tags":[
        "consultant",
        "property"
    ],
    "wof:name":"Property 1",
    "wof:placetype":"venue"
},
  "geometry": {"coordinates":[153.003814697,-27.4533290863],"type":"Point"}
}