{
  "type": "Feature",
  "properties": {
    "addr:full":"269 Oakland Rd Marion SA 5043",
    "addr:housenumber":"269",
    "addr:postcode":"5043",
    "addr:street":"Oakland Rd",
    "iso:country":"AU",
    "sg:address":"269 Oakland Rd",
    "sg:city":"Marion",
    "sg:classifiers":[
        {
            "category":"Building & Trades",
            "subcategory":"Construction",
            "type":"Services"
        }
    ],
    "sg:phone":"+61 400 448 433",
    "sg:postcode":"5043",
    "sg:province":"SA",
    "sg:tags":[
        "ceiling"
    ],
    "wof:name":"ABACAD Ceilings Pty Ltd",
    "wof:placetype":"venue"
},
  "geometry": {"coordinates":[138.548553,-34.995537],"type":"Point"}
}