{
  "type": "Feature",
  "properties": {
    "iso:country":"AU",
    "sg:address":"46 Hayes Rd",
    "sg:city":"Seven Hills",
    "sg:classifiers":[
        {
            "category":"Professional",
            "subcategory":"Printing & Photocopies",
            "type":"Services"
        }
    ],
    "sg:phone":"+61 2 9621 7305",
    "sg:postcode":"2147",
    "sg:province":"NSW",
    "sg:tags":[
        "embroidery"
    ],
    "wof:name":"A Excell Embroidery Services",
    "wof:placetype":"venue"
},
  "geometry": {"coordinates":[150.92681884800001,-33.7798690796],"type":"Point"}
}