{
  "type": "Feature",
  "properties": {
    "addr:full":"Bordertown Rd Pinnaroo SA 5304",
    "addr:postcode":"5304",
    "addr:street":"Bordertown Rd",
    "iso:country":"AU",
    "sg:address":"Bordertown Rd",
    "sg:city":"Pinnaroo",
    "sg:classifiers":[
        {
            "category":"Farming",
            "subcategory":"Farm",
            "type":"Manufacturing & Wholesale Goods"
        }
    ],
    "sg:phone":"+61 8 8576 6171",
    "sg:postcode":"5304",
    "sg:province":"SA",
    "sg:tags":[
        "farmer"
    ],
    "wof:name":"Wurfel T",
    "wof:placetype":"venue"
},
  "geometry": {"coordinates":[140.872512817,-35.304599762],"type":"Point"}
}