{
  "type": "Feature",
  "properties": {
    "addr:full":"PO Box 440 Lutwyche QLD 4030",
    "addr:postcode":"4030",
    "iso:country":"AU",
    "sg:address":"PO Box 440",
    "sg:city":"Lutwyche",
    "sg:classifiers":[
        {
            "category":"Building & Trades",
            "subcategory":"Cleaning & Sanitation",
            "type":"Services"
        }
    ],
    "sg:phone":"+61 7 3221 0088",
    "sg:postcode":"4030",
    "sg:province":"QLD",
    "sg:tags":[
        "commercial",
        "maintenance"
    ],
    "wof:name":"ACRO Maintenance Pty Ltd",
    "wof:placetype":"venue"
},
  "geometry": {"coordinates":[153.033905,-27.42214],"type":"Point"}
}