{
  "type": "Feature",
  "properties": {
    "addr:full":"Shop 51 A, Centro Cranbourne, Cranbourne VIC 3977",
    "addr:housenumber":"shop 51 a",
    "addr:postcode":"3977",
    "iso:country":"AU",
    "sg:address":"Shop 51",
    "sg:city":"A, Centro Cranbourne, Cranbourne",
    "sg:classifiers":[
        {
            "category":"Shopping",
            "subcategory":"Jewelry",
            "type":"Retail Goods"
        }
    ],
    "sg:phone":"+61 3 5996 4233",
    "sg:postcode":"3977",
    "sg:province":"VIC",
    "sg:tags":[
        "jeweller"
    ],
    "wof:name":"Zamels",
    "wof:placetype":"venue"
},
  "geometry": {"coordinates":[145.26637268100001,-38.0809516907],"type":"Point"}
}