{
  "type": "Feature",
  "properties": {
    "iso:country":"AU",
    "sg:address":"Level 4, 31 Flinders La",
    "sg:city":"Melbourne",
    "sg:classifiers":[
        {
            "category":"Building & Trades",
            "subcategory":"Construction",
            "type":"Services"
        }
    ],
    "sg:phone":"+61 3 9663 9110",
    "sg:postcode":"3000",
    "sg:province":"VIC",
    "sg:tags":[
        "contractor"
    ],
    "wof:name":"Lokal",
    "wof:placetype":"venue"
},
  "geometry": {"coordinates":[144.97325134299999,-37.8147888184],"type":"Point"}
}