{
  "type": "Feature",
  "properties": {
    "iso:country":"AU",
    "sg:address":"1/ 31 Berriman Drv",
    "sg:city":"Wangara",
    "sg:classifiers":[
        {
            "category":"Home & Garden",
            "subcategory":"Building Materials",
            "type":"Retail Goods"
        }
    ],
    "sg:phone":"+61 8 9309 2600",
    "sg:postcode":"6065",
    "sg:province":"WA",
    "sg:tags":[
        "roofing"
    ],
    "wof:name":"Roof Restoration Supplies",
    "wof:placetype":"venue"
},
  "geometry": {"coordinates":[115.82219696,-31.7934322357],"type":"Point"}
}