{
  "type": "Feature",
  "properties": {
    "iso:country":"AU",
    "sg:address":"Shop 5/ 2713 Main Pl",
    "sg:city":"Broadbeach",
    "sg:classifiers":[
        {
            "category":"Personal",
            "subcategory":"Shoe Repair & Shine",
            "type":"Services"
        }
    ],
    "sg:phone":"+61 7 5570 1091",
    "sg:postcode":"4218",
    "sg:province":"QLD",
    "sg:tags":[
        "footwear"
    ],
    "wof:name":"A Load Of Old Cobblers",
    "wof:placetype":"venue"
},
  "geometry": {"coordinates":[153.43060302699999,-28.0284976959],"type":"Point"}
}