{
  "type": "Feature",
  "properties": {
    "addr:full":"14 Seldon St Quakers Hill NSW 2763",
    "addr:housenumber":"14",
    "addr:postcode":"2763",
    "addr:street":"Seldon St",
    "iso:country":"AU",
    "sg:address":"14 Seldon St",
    "sg:city":"Quakers Hill",
    "sg:classifiers":[
        {
            "category":"Shopping",
            "subcategory":"Bicycles & Sporting Goods",
            "type":"Retail Goods"
        }
    ],
    "sg:phone":"+61 2 9837 7594",
    "sg:postcode":"2763",
    "sg:province":"NSW",
    "sg:tags":[
        "chemical",
        "equipment",
        "pool",
        "swimming"
    ],
    "wof:name":"Norwest Total Pool Services",
    "wof:placetype":"venue"
},
  "geometry": {"coordinates":[150.88107299800001,-33.7125587463],"type":"Point"}
}