{
  "type": "Feature",
  "properties": {
    "addr:full":"Moulamein Rd Barham NSW 2732",
    "addr:postcode":"2732",
    "addr:street":"Moulamein Rd",
    "iso:country":"AU",
    "sg:address":"Moulamein Rd",
    "sg:city":"Barham",
    "sg:classifiers":[
        {
            "category":"Sports & Exercise",
            "subcategory":"Golf",
            "type":"Entertainment"
        }
    ],
    "sg:phone":"+61 3 5453 2772",
    "sg:postcode":"2732",
    "sg:province":"NSW",
    "sg:tags":[
        "club"
    ],
    "wof:name":"Barham Golf & Country Club",
    "wof:placetype":"venue"
},
  "geometry": {"coordinates":[144.130707,-35.622829],"type":"Point"}
}