{
  "type": "Feature",
  "properties": {
    "iso:country":"AU",
    "sg:address":"34 Diminions Rd",
    "sg:city":"Ashmore",
    "sg:classifiers":[
        {
            "category":"Education",
            "subcategory":"University",
            "type":"Public Place"
        }
    ],
    "sg:phone":"+61 7 5597 0744",
    "sg:postcode":"4214",
    "sg:province":"QLD",
    "sg:tags":[
        "sewing",
        "dressmaking",
        "tuition"
    ],
    "wof:name":"Complete Sewing & Alterations",
    "wof:placetype":"venue"
},
  "geometry": {"coordinates":[153.38392639200001,-27.9806404114],"type":"Point"}
}