{
  "type": "Feature",
  "properties": {
    "addr:full":"203 Anzac Ave Toowoomba QLD 4350",
    "addr:housenumber":"203",
    "addr:postcode":"4350",
    "addr:street":"Anzac Ave",
    "iso:country":"AU",
    "sg:address":"203 Anzac Ave",
    "sg:city":"Toowoomba",
    "sg:classifiers":[
        {
            "category":"Home & Garden",
            "subcategory":"Hardware",
            "type":"Retail Goods"
        }
    ],
    "sg:phone":"+61 7 4634 4577",
    "sg:postcode":"4350",
    "sg:province":"QLD",
    "sg:tags":[
        "generating",
        "set",
        "generator"
    ],
    "wof:name":"Motor Mecca",
    "wof:placetype":"venue"
},
  "geometry": {"coordinates":[151.92454499999999,-27.572216],"type":"Point"}
}