{
  "type": "Feature",
  "properties": {
    "addr:full":"158 Welsford St Shepparton VIC 3630",
    "addr:housenumber":"158",
    "addr:postcode":"3630",
    "addr:street":"Welsford St",
    "iso:country":"AU",
    "sg:address":"158 Welsford St",
    "sg:city":"Shepparton",
    "sg:classifiers":[
        {
            "category":"Home & Garden",
            "subcategory":"Kitchen Supply",
            "type":"Retail Goods"
        }
    ],
    "sg:phone":"+61 3 5821 9600",
    "sg:postcode":"3630",
    "sg:province":"VIC",
    "sg:tags":[
        "equipment",
        "surveyor"
    ],
    "wof:name":"Land Management Services",
    "wof:placetype":"venue"
},
  "geometry": {"coordinates":[145.397613525,-36.3812179565],"type":"Point"}
}