{
  "type": "Feature",
  "properties": {
    "addr:full":"297- 301 Argent St Broken Hill NSW 2880",
    "addr:housenumber":"301",
    "addr:postcode":"2880",
    "addr:street":"Argent St",
    "iso:country":"AU",
    "sg:address":"297- 301 Argent St",
    "sg:city":"Broken Hill",
    "sg:classifiers":[
        {
            "category":"Banks & Credit Unions",
            "subcategory":"Bank",
            "type":"Services"
        }
    ],
    "sg:phone":"+61 13 20 32",
    "sg:postcode":"2880",
    "sg:province":"NSW",
    "wof:name":"Westpac Banking Corporation",
    "wof:placetype":"venue"
},
  "geometry": {"coordinates":[141.46548461899999,-31.9585018158],"type":"Point"}
}