{
  "type": "Feature",
  "properties": {
    "iso:country":"AU",
    "sg:address":"2 City Rd",
    "sg:city":"Ringwood",
    "sg:classifiers":[
        {
            "category":"Social Services",
            "subcategory":"Retirement Home",
            "type":"Services"
        }
    ],
    "sg:phone":"+61 3 9870 4459",
    "sg:postcode":"3134",
    "sg:province":"VIC",
    "sg:tags":[
        "village"
    ],
    "wof:name":"Good Shepherd Retirement Village",
    "wof:placetype":"venue"
},
  "geometry": {"coordinates":[145.227615356,-37.8220443726],"type":"Point"}
}