{
  "type": "Feature",
  "properties": {
    "iso:country":"AU",
    "sg:address":"Goulburn Valley Hwy",
    "sg:city":"Shepparton",
    "sg:classifiers":[
        {
            "category":"Travel",
            "subcategory":"Hotels & Motels",
            "type":"Entertainment"
        }
    ],
    "sg:phone":"+61 3 5821 4472",
    "sg:postcode":"3630",
    "sg:province":"VIC",
    "wof:name":"Apex Motel",
    "wof:placetype":"venue"
},
  "geometry": {"coordinates":[145.409500122,-36.3885993958],"type":"Point"}
}