{
  "type": "Feature",
  "properties": {
    "addr:full":"8 St Georges St Greensborough VIC 3088",
    "addr:housenumber":"8",
    "addr:postcode":"3088",
    "addr:street":"St Georges St",
    "iso:country":"AU",
    "sg:address":"8 St Georges St",
    "sg:city":"Greensborough",
    "sg:classifiers":[
        {
            "category":"Building & Trades",
            "subcategory":"Plumbing",
            "type":"Services"
        }
    ],
    "sg:phone":"+61 418 346 219",
    "sg:postcode":"3088",
    "sg:province":"VIC",
    "sg:tags":[
        "plumber",
        "gasfitters"
    ],
    "wof:name":"P & L Plumbing",
    "wof:placetype":"venue"
},
  "geometry": {"coordinates":[145.11843872099999,-37.6863365173],"type":"Point"}
}