{
  "type": "Feature",
  "properties": {
    "addr:full":"90 Mangan St Tongala VIC 3621",
    "addr:housenumber":"90",
    "addr:postcode":"3621",
    "addr:street":"Mangan St",
    "iso:country":"AU",
    "sg:address":"90 Mangan St",
    "sg:city":"Tongala",
    "sg:classifiers":[
        {
            "category":"Fast Food",
            "type":"Food & Drink"
        }
    ],
    "sg:phone":"+61 3 5859 0836",
    "sg:postcode":"3621",
    "sg:province":"VIC",
    "sg:tags":[
        "away",
        "take"
    ],
    "wof:name":"Tongala Hot Bread",
    "wof:placetype":"venue"
},
  "geometry": {"coordinates":[144.95021057100001,-36.2503013611],"type":"Point"}
}