{
  "type": "Feature",
  "properties": {
    "addr:full":"206 Dana St Ballarat VIC 3350",
    "addr:housenumber":"206",
    "addr:postcode":"3350",
    "addr:street":"Dana St",
    "iso:country":"AU",
    "sg:address":"206 Dana St",
    "sg:city":"Ballarat",
    "sg:classifiers":[
        {
            "category":"Shopping",
            "subcategory":"Stationery & Office Supplies",
            "type":"Retail Goods"
        }
    ],
    "sg:phone":"+61 3 5332 1968",
    "sg:postcode":"3350",
    "sg:province":"VIC",
    "wof:name":"Berry, Anderson Office Supplies",
    "wof:placetype":"venue"
},
  "geometry": {"coordinates":[143.85694899999999,-37.56398],"type":"Point"}
}