{
  "type": "Feature",
  "properties": {
    "iso:country":"AU",
    "sg:address":"243 Lawrence Hargrave Drv",
    "sg:city":"Coalcliff",
    "sg:classifiers":[
        {
            "category":"Professional",
            "subcategory":"Art Services",
            "type":"Services"
        }
    ],
    "sg:phone":"+61 2 4294 9466",
    "sg:postcode":"2508",
    "sg:province":"NSW",
    "sg:tags":[
        "interior",
        "designer"
    ],
    "wof:name":"The Inside Story Design Concepts Pty Ltd",
    "wof:placetype":"venue"
},
  "geometry": {"coordinates":[150.975632,-34.243805],"type":"Point"}
}