{
  "type": "Feature",
  "properties": {
    "addr:full":"4 Brandwood St Royal Park SA 5014",
    "addr:housenumber":"4",
    "addr:postcode":"5014",
    "addr:street":"Brandwood St",
    "iso:country":"AU",
    "sg:address":"4 Brandwood St",
    "sg:city":"Royal Park",
    "sg:classifiers":[
        {
            "category":"Government",
            "subcategory":"Department Of Motor Vehicles",
            "type":"Public Place"
        }
    ],
    "sg:phone":"+61 8 8447 8585",
    "sg:postcode":"5014",
    "sg:province":"SA",
    "sg:tags":[
        "wholesaler",
        "mfrs",
        "accessory"
    ],
    "wof:name":"United Lubricants Pty Ltd",
    "wof:placetype":"venue"
},
  "geometry": {"coordinates":[138.50636291500001,-34.8657112122],"type":"Point"}
}