{
  "type": "Feature",
  "properties": {
    "addr:full":"1 William St Wickham NSW 2293",
    "addr:housenumber":"1",
    "addr:postcode":"2293",
    "addr:street":"William St",
    "iso:country":"AU",
    "sg:address":"1 William St",
    "sg:city":"Wickham",
    "sg:classifiers":[
        {
            "category":"Military Area",
            "subcategory":"Air Force Base",
            "type":"Public Place"
        }
    ],
    "sg:phone":"+61 2 4969 6788",
    "sg:postcode":"2293",
    "sg:province":"NSW",
    "sg:tags":[
        "equipment",
        "speed",
        "variation"
    ],
    "wof:name":"Zener Electric (Newcastle) Pty Ltd",
    "wof:placetype":"venue"
},
  "geometry": {"coordinates":[151.75608825699999,-32.9120521545],"type":"Point"}
}