{
  "type": "Feature",
  "properties": {
    "addr:full":"14 Shepherd St Darwin NT 0801",
    "addr:housenumber":"14",
    "addr:postcode":"nt 0801",
    "addr:street":"Shepherd St",
    "iso:country":"AU",
    "sg:address":"14 Shepherd St",
    "sg:city":"Darwin",
    "sg:classifiers":[
        {
            "category":"Organizations",
            "subcategory":"Community Association",
            "type":"Services"
        }
    ],
    "sg:phone":"+61 8 8941 9743",
    "sg:postcode":"0801",
    "sg:province":"NT",
    "sg:tags":[
        "international",
        "organisation",
        "relation",
        "aid"
    ],
    "wof:name":"Australian Volunteers International (Remote Recruiting)",
    "wof:placetype":"venue"
},
  "geometry": {"coordinates":[130.84063720699999,-12.4577980042],"type":"Point"}
}