{
  "type": "Feature",
  "properties": {
    "iso:country":"AU",
    "sg:address":"110 Albany Hwy",
    "sg:city":"Albany",
    "sg:classifiers":[
        {
            "category":"Travel",
            "subcategory":"Travel Agent",
            "type":"Entertainment"
        }
    ],
    "sg:phone":"+61 8 9842 1210",
    "sg:postcode":"6330",
    "sg:province":"WA",
    "sg:tags":[
        "consultant"
    ],
    "wof:name":"RAC Travel Services",
    "wof:placetype":"venue"
},
  "geometry": {"coordinates":[117.88031768800001,-35.0185966492],"type":"Point"}
}