{
  "type": "Feature",
  "properties": {
    "addr:full":"418 Canterbury Rd Surrey Hills VIC 3127",
    "addr:housenumber":"418",
    "addr:postcode":"3127",
    "addr:street":"Canterbury Rd",
    "iso:country":"AU",
    "sg:address":"418 Canterbury Rd",
    "sg:city":"Surrey Hills",
    "sg:classifiers":[
        {
            "category":"Building & Trades",
            "subcategory":"Plumbing",
            "type":"Services"
        }
    ],
    "sg:phone":"+61 3 9830 5666",
    "sg:postcode":"3127",
    "sg:province":"VIC",
    "sg:tags":[
        "plumber",
        "gasfitters"
    ],
    "wof:name":"V.I.P Plumbing Services",
    "wof:placetype":"venue"
},
  "geometry": {"coordinates":[145.09927368199999,-37.826335907],"type":"Point"}
}