{
  "type": "Feature",
  "properties": {
    "addr:full":"6/ 78 Union Rd Penrith NSW 2750",
    "addr:housenumber":"/ 78",
    "addr:postcode":"2750",
    "addr:street":"Union Rd",
    "iso:country":"AU",
    "sg:address":"6/ 78 Union Rd",
    "sg:city":"Penrith",
    "sg:classifiers":[
        {
            "category":"Professional",
            "subcategory":"Testing Lab",
            "type":"Services"
        }
    ],
    "sg:phone":"+61 2 4722 6512",
    "sg:postcode":"2750",
    "sg:province":"NSW",
    "sg:tags":[
        "inspection"
    ],
    "wof:name":"ERG Consulting",
    "wof:placetype":"venue"
},
  "geometry": {"coordinates":[150.69161987300001,-33.753704071],"type":"Point"}
}