{
  "type": "Feature",
  "properties": {
    "addr:full":"100 Harburgh Drv Beenleigh QLD 4207",
    "addr:housenumber":"100",
    "addr:postcode":"4207",
    "addr:street":"Harburgh Drv",
    "iso:country":"AU",
    "sg:address":"100 Harburgh Drv",
    "sg:city":"Beenleigh",
    "sg:classifiers":[
        {
            "category":"Retail",
            "subcategory":"Auto Repair",
            "type":"Services"
        }
    ],
    "sg:phone":"+61 7 3807 4747",
    "sg:postcode":"4207",
    "sg:province":"QLD",
    "sg:tags":[
        "repairer",
        "motor",
        "engineer"
    ],
    "wof:name":"One Stop Truck Doctor The",
    "wof:placetype":"venue"
},
  "geometry": {"coordinates":[153.18197631800001,-27.7155132294],"type":"Point"}
}