{
  "type": "Feature",
  "properties": {
    "addr:full":"50 Williams Rd Shepparton VIC 3630",
    "addr:housenumber":"50",
    "addr:postcode":"3630",
    "addr:street":"Williams Rd",
    "iso:country":"AU",
    "sg:address":"50 Williams Rd",
    "sg:city":"Shepparton",
    "sg:classifiers":[
        {
            "category":"Manufacturing",
            "subcategory":"Tools & Machinery",
            "type":"Manufacturing & Wholesale Goods"
        }
    ],
    "sg:phone":"+61 3 5831 2680",
    "sg:postcode":"3630",
    "sg:province":"VIC",
    "sg:tags":[
        "abrasive"
    ],
    "wof:name":"Apricot Kernels Australia Pty Ltd",
    "wof:placetype":"venue"
},
  "geometry": {"coordinates":[145.418792725,-36.38098526],"type":"Point"}
}