{
  "type": "Feature",
  "properties": {
    "iso:country":"AU",
    "sg:address":"10 Marine Crt",
    "sg:city":"Berwick",
    "sg:classifiers":[
        {
            "category":"Building & Trades",
            "subcategory":"Construction",
            "type":"Services"
        }
    ],
    "sg:phone":"+61 1300 726 188",
    "sg:postcode":"3806",
    "sg:province":"VIC",
    "sg:tags":[
        "polishing",
        "sanding",
        "floor"
    ],
    "wof:name":"Circa Flooring",
    "wof:placetype":"venue"
},
  "geometry": {"coordinates":[145.34828185999999,-38.0561828613],"type":"Point"}
}