{
  "type": "Feature",
  "properties": {
    "addr:full":"46 Williamson Rd Maribyrnong VIC 3032",
    "addr:housenumber":"46",
    "addr:postcode":"3032",
    "addr:street":"Williamson Rd",
    "iso:country":"AU",
    "sg:address":"46 Williamson Rd",
    "sg:city":"Maribyrnong",
    "sg:classifiers":[
        {
            "category":"Banks & Credit Unions",
            "subcategory":"Financial Services",
            "type":"Services"
        }
    ],
    "sg:phone":"+61 3 9318 6211",
    "sg:postcode":"3032",
    "sg:province":"VIC",
    "sg:tags":[
        "financier"
    ],
    "wof:name":"City Finance",
    "wof:placetype":"venue"
},
  "geometry": {"coordinates":[144.87927199999999,-37.774605],"type":"Point"}
}