{
  "type": "Feature",
  "properties": {
    "iso:country":"AU",
    "sg:address":"216 Homer St",
    "sg:city":"Earlwood",
    "sg:classifiers":[
        {
            "category":"Industrial Area",
            "type":"Public Place"
        }
    ],
    "sg:phone":"+61 2 9559 1366",
    "sg:postcode":"2206",
    "sg:province":"NSW",
    "sg:tags":[
        "protective",
        "clothing"
    ],
    "wof:name":"Blackjack Merchandising Pty Ltd",
    "wof:placetype":"venue"
},
  "geometry": {"coordinates":[151.12339800000001,-33.928028],"type":"Point"}
}