{
  "type": "Feature",
  "properties": {
    "addr:full":"86 Wyndham St Alexandria NSW 2015",
    "addr:housenumber":"86",
    "addr:postcode":"2015",
    "addr:street":"Wyndham St",
    "iso:country":"AU",
    "sg:address":"86 Wyndham St",
    "sg:city":"Alexandria",
    "sg:classifiers":[
        {
            "category":"Building & Trades",
            "subcategory":"Equipment Rental",
            "type":"Services"
        }
    ],
    "sg:phone":"+61 2 9699 8600",
    "sg:postcode":"2015",
    "sg:province":"NSW",
    "sg:tags":[
        "party",
        "hire"
    ],
    "wof:name":"A. Aace Chair Covers",
    "wof:placetype":"venue"
},
  "geometry": {"coordinates":[151.198852539,-33.8979644775],"type":"Point"}
}