{
  "type": "Feature",
  "properties": {
    "addr:full":"Unit 4/ 72 Chifley Drv Preston VIC 3072",
    "addr:housenumber":"72",
    "addr:postcode":"3072",
    "addr:street":"Chifley Drv",
    "iso:country":"AU",
    "sg:address":"Unit 4/ 72 Chifley Drv",
    "sg:city":"Preston",
    "sg:classifiers":[
        {
            "category":"Wholesale",
            "subcategory":"Machinery & Supplies",
            "type":"Manufacturing & Wholesale Goods"
        }
    ],
    "sg:phone":"+61 3 9480 4999",
    "sg:postcode":"3072",
    "sg:province":"VIC",
    "sg:tags":[
        "instrument",
        "scientific"
    ],
    "wof:name":"Scitech Pty Ltd",
    "wof:placetype":"venue"
},
  "geometry": {"coordinates":[145.02973938,-37.7491950989],"type":"Point"}
}