{
  "type": "Feature",
  "properties": {
    "iso:country":"AU",
    "sg:address":"269-271 Old Northern Rd",
    "sg:city":"(opposite Showground Rd) Castle Hill",
    "sg:classifiers":[
        {
            "category":"Health Services",
            "subcategory":"Doctor",
            "type":"Services"
        }
    ],
    "sg:phone":"+61 2 9634 5000",
    "sg:postcode":"2154",
    "sg:province":"NSW",
    "sg:tags":[
        "podiatrist"
    ],
    "wof:name":"Castle Hill Medical Centre Podiatry",
    "wof:placetype":"venue"
},
  "geometry": {"coordinates":[151.00431823700001,-33.7337875366],"type":"Point"}
}