{
  "type": "Feature",
  "properties": {
    "addr:full":"108 Herries St Toowoomba QLD 4350",
    "addr:housenumber":"108",
    "addr:postcode":"4350",
    "addr:street":"Herries St",
    "iso:country":"AU",
    "sg:address":"108 Herries St",
    "sg:city":"Toowoomba",
    "sg:classifiers":[
        {
            "category":"Health Services",
            "subcategory":"Doctor",
            "type":"Services"
        }
    ],
    "sg:phone":"+61 7 4688 2000",
    "sg:postcode":"4350",
    "sg:province":"QLD",
    "sg:tags":[
        "medical",
        "practitioner"
    ],
    "wof:name":"Toowoomba & District Division of General Practice",
    "wof:placetype":"venue"
},
  "geometry": {"coordinates":[151.93751499999999,-27.562201],"type":"Point"}
}