{
  "type": "Feature",
  "properties": {
    "addr:full":"PO Box 22 Yarralumla ACT 2600",
    "addr:postcode":"2600",
    "iso:country":"AU",
    "sg:address":"PO Box 22",
    "sg:city":"Yarralumla",
    "sg:classifiers":[
        {
            "category":"Professional",
            "subcategory":"Employment Agencies",
            "type":"Services"
        }
    ],
    "sg:phone":"+61 427 539 615",
    "sg:postcode":"2600",
    "sg:province":"ACT",
    "sg:tags":[
        "entertainer",
        "agent"
    ],
    "wof:name":"Funky Fedoras",
    "wof:placetype":"venue"
},
  "geometry": {"coordinates":[149.10671997099999,-35.3059005737],"type":"Point"}
}