{
  "type": "Feature",
  "properties": {
    "addr:full":"12 Days Rd Grange QLD 4051",
    "addr:housenumber":"12",
    "addr:postcode":"4051",
    "addr:street":"Days Rd",
    "iso:country":"AU",
    "sg:address":"12 Days Rd",
    "sg:city":"Grange",
    "sg:classifiers":[
        {
            "category":"Retail",
            "subcategory":"Veterinary Services",
            "type":"Services"
        }
    ],
    "sg:phone":"+61 7 3856 4882",
    "sg:postcode":"4051",
    "sg:province":"QLD",
    "sg:tags":[
        "surgeon"
    ],
    "wof:name":"Grange Vet Surgery",
    "wof:placetype":"venue"
},
  "geometry": {"coordinates":[153.02284240700001,-27.427236557],"type":"Point"}
}