{
  "type": "Feature",
  "properties": {
    "iso:country":"AU",
    "sg:address":"Lot 15 Edelsten Rd",
    "sg:city":"Howard Springs",
    "sg:classifiers":[
        {
            "category":"Farming",
            "subcategory":"Nursery",
            "type":"Manufacturing & Wholesale Goods"
        }
    ],
    "sg:phone":"+61 8 8983 2001",
    "sg:postcode":"0835",
    "sg:province":"NT",
    "wof:name":"Girraween Nursery",
    "wof:placetype":"venue"
},
  "geometry": {"coordinates":[131.049683,-12.527509],"type":"Point"}
}