{
  "type": "Feature",
  "properties": {
    "addr:full":"Shop 3 Bassendean Sq Shopng Cntr Bassendean WA 6054",
    "addr:housenumber":"shop 3",
    "addr:postcode":"6054",
    "addr:street":"Bassendean Sq Shopng Cntr",
    "iso:country":"AU",
    "sg:address":"Shop 3 Bassendean Sq Shopng Cntr",
    "sg:city":"Bassendean",
    "sg:classifiers":[
        {
            "category":"Food & Beverages",
            "subcategory":"Bakery",
            "type":"Retail Goods"
        }
    ],
    "sg:phone":"+61 8 9279 6674",
    "sg:postcode":"6054",
    "sg:province":"WA",
    "sg:tags":[
        "baker"
    ],
    "wof:name":"LTD Bakery",
    "wof:placetype":"venue"
},
  "geometry": {"coordinates":[115.942138672,-31.9080696106],"type":"Point"}
}