{
  "type": "Feature",
  "properties": {
    "addr:full":"Factory 3/26- 30 Burgess Rd Bayswater North VIC 3153",
    "addr:housenumber":"/;30",
    "addr:postcode":"3153",
    "addr:street":"26;Burgess Rd",
    "iso:country":"AU",
    "sg:address":"Factory 3/26- 30 Burgess Rd",
    "sg:city":"Bayswater North",
    "sg:classifiers":[
        {
            "category":"Home & Garden",
            "subcategory":"Kitchen Supply",
            "type":"Retail Goods"
        }
    ],
    "sg:phone":"+61 3 9761 4544",
    "sg:postcode":"3153",
    "sg:province":"VIC",
    "sg:tags":[
        "sharpening"
    ],
    "wof:name":"Sharpening Solutions",
    "wof:placetype":"venue"
},
  "geometry": {"coordinates":[145.28904724099999,-37.8218345642],"type":"Point"}
}