{
  "type": "Feature",
  "properties": {
    "iso:country":"AU",
    "sg:address":"42 Borec Rd",
    "sg:city":"Penrith",
    "sg:classifiers":[
        {
            "category":"Home & Garden",
            "subcategory":"Hardware",
            "type":"Retail Goods"
        }
    ],
    "sg:phone":"+61 2 4722 3034",
    "sg:postcode":"2750",
    "sg:province":"NSW",
    "sg:tags":[
        "repair",
        "tool",
        "power"
    ],
    "wof:name":"Nepean Boltmaster Pty Ltd",
    "wof:placetype":"venue"
},
  "geometry": {"coordinates":[150.69102477999999,-33.7361106873],"type":"Point"}
}