{
  "type": "Feature",
  "properties": {
    "addr:full":"27 Alexandra St Emu Park QLD 4702",
    "addr:housenumber":"27",
    "addr:postcode":"4702",
    "addr:street":"Alexandra St",
    "iso:country":"AU",
    "sg:address":"27 Alexandra St",
    "sg:city":"Emu Park",
    "sg:classifiers":[
        {
            "category":"Arena",
            "subcategory":"Sports Club",
            "type":"Entertainment"
        }
    ],
    "sg:phone":"+61 7 4926 3590",
    "sg:postcode":"4702",
    "sg:province":"QLD",
    "sg:tags":[
        "life",
        "surfing",
        "saving"
    ],
    "wof:name":"Emu Park Surf Life Saving Club",
    "wof:placetype":"venue"
},
  "geometry": {"coordinates":[150.50868225100001,-23.3440494537],"type":"Point"}
}