{
  "type": "Feature",
  "properties": {
    "addr:full":"128 Francis St Richmond NSW 2753",
    "addr:housenumber":"128",
    "addr:postcode":"2753",
    "addr:street":"Francis St",
    "iso:country":"AU",
    "sg:address":"128 Francis St",
    "sg:city":"Richmond",
    "sg:classifiers":[
        {
            "category":"Health Services",
            "subcategory":"Doctor",
            "type":"Services"
        }
    ],
    "sg:phone":"+61 2 4578 4788",
    "sg:postcode":"2753",
    "sg:province":"NSW",
    "sg:tags":[
        "podiatrist"
    ],
    "wof:name":"Hawkesbury Podiatry",
    "wof:placetype":"venue"
},
  "geometry": {"coordinates":[150.74908447300001,-33.5941505432],"type":"Point"}
}