{
  "type": "Feature",
  "properties": {
    "addr:full":"Alexander Ave Evanston South SA 5116",
    "addr:postcode":"5116",
    "addr:street":"Alexander Ave",
    "iso:country":"AU",
    "sg:address":"Alexander Ave",
    "sg:city":"Evanston South",
    "sg:classifiers":[
        {
            "category":"Education",
            "subcategory":"School",
            "type":"Public Place"
        }
    ],
    "sg:phone":"+61 8 8522 0666",
    "sg:postcode":"5116",
    "sg:province":"SA",
    "wof:name":"Trinity College Gawler Incorporated",
    "wof:placetype":"venue"
},
  "geometry": {"coordinates":[138.73832702600001,-34.6345596313],"type":"Point"}
}