{
  "type": "Feature",
  "properties": {
    "addr:full":"12 Intrepid Drv Mermaid Waters QLD 4218",
    "addr:housenumber":"12",
    "addr:postcode":"4218",
    "addr:street":"Intrepid Drv",
    "iso:country":"AU",
    "sg:address":"12 Intrepid Drv",
    "sg:city":"Mermaid Waters",
    "sg:classifiers":[
        {
            "category":"Building & Trades",
            "subcategory":"Plumbing",
            "type":"Services"
        }
    ],
    "sg:phone":"+61 7 5575 4114",
    "sg:postcode":"4218",
    "sg:province":"QLD",
    "sg:tags":[
        "pump",
        "repairer"
    ],
    "wof:name":"Kenz Pool Kare",
    "wof:placetype":"venue"
},
  "geometry": {"coordinates":[153.42190551799999,-28.0463485718],"type":"Point"}
}