{
  "type": "Feature",
  "properties": {
    "iso:country":"AU",
    "sg:address":"77 Beerburrum Rd",
    "sg:city":"Caboolture",
    "sg:classifiers":[
        {
            "category":"Fast Food",
            "type":"Food & Drink"
        }
    ],
    "sg:phone":"+61 7 5495 1283",
    "sg:postcode":"4510",
    "sg:province":"QLD",
    "sg:tags":[
        "away",
        "take"
    ],
    "wof:name":"Caboolture Munchies",
    "wof:placetype":"venue"
},
  "geometry": {"coordinates":[152.95031700000001,-27.0763],"type":"Point"}
}