{
  "type": "Feature",
  "properties": {
    "addr:full":"25a Lysterfield Rd Orange NSW 2800",
    "addr:housenumber":"25a",
    "addr:postcode":"2800",
    "addr:street":"Lysterfield Rd",
    "iso:country":"AU",
    "sg:address":"25a Lysterfield Rd",
    "sg:city":"Orange",
    "sg:classifiers":[
        {
            "category":"Mining & Drilling",
            "type":"Manufacturing & Wholesale Goods"
        }
    ],
    "sg:phone":"+61 2 6365 3567",
    "sg:postcode":"2800",
    "sg:province":"NSW",
    "sg:tags":[
        "equipment",
        "quarrying",
        "supply"
    ],
    "wof:name":"McDonell Earthmoving Civil & Mining Services",
    "wof:placetype":"venue"
},
  "geometry": {"coordinates":[149.075317383,-33.3152999878],"type":"Point"}
}