{
  "type": "Feature",
  "properties": {
    "addr:full":"Shop 2, 7 Lonsdale St Braddon ACT 2612",
    "addr:housenumber":"shop;7",
    "addr:postcode":"2612",
    "addr:street":"Lonsdale St",
    "iso:country":"AU",
    "sg:address":"Shop 2, 7 Lonsdale St",
    "sg:city":"Braddon",
    "sg:classifiers":[
        {
            "category":"Transit Center",
            "subcategory":"Freight",
            "type":"Transportation"
        }
    ],
    "sg:phone":"+61 2 6162 1989",
    "sg:postcode":"2612",
    "sg:province":"ACT",
    "sg:tags":[
        "agent",
        "shipping"
    ],
    "wof:name":"Pack & Send",
    "wof:placetype":"venue"
},
  "geometry": {"coordinates":[149.132324219,-35.2751502991],"type":"Point"}
}