{
  "type": "Feature",
  "properties": {
    "addr:full":"First St Ardrossan SA 5571",
    "addr:postcode":"5571",
    "addr:street":"First St",
    "iso:country":"AU",
    "sg:address":"First St",
    "sg:city":"Ardrossan",
    "sg:classifiers":[
        {
            "category":"Government",
            "subcategory":"Post Office",
            "type":"Public Place"
        }
    ],
    "sg:phone":"+61 8 8837 3020",
    "sg:postcode":"5571",
    "sg:province":"SA",
    "sg:tags":[
        "postal"
    ],
    "wof:name":"Australia Post",
    "wof:placetype":"venue"
},
  "geometry": {"coordinates":[137.91468810999999,-34.4221534729],"type":"Point"}
}