{
  "type": "Feature",
  "properties": {
    "addr:full":"30 Lawrence Drv Nerang QLD 4211",
    "addr:housenumber":"30",
    "addr:postcode":"4211",
    "addr:street":"Lawrence Drv",
    "iso:country":"AU",
    "sg:address":"30 Lawrence Drv",
    "sg:city":"Nerang",
    "sg:classifiers":[
        {
            "category":"Organizations",
            "subcategory":"Community Association",
            "type":"Services"
        }
    ],
    "sg:phone":"+61 7 5578 3434",
    "sg:postcode":"4211",
    "sg:province":"QLD",
    "sg:tags":[
        "organisation",
        "family",
        "welfare"
    ],
    "wof:name":"Kalwun Development Corporation",
    "wof:placetype":"venue"
},
  "geometry": {"coordinates":[153.346923828,-27.9969787598],"type":"Point"}
}