{
  "type": "Feature",
  "properties": {
    "iso:country":"AU",
    "sg:address":"180- 210 Williamstown Rd",
    "sg:city":"Port Melbourne",
    "sg:classifiers":[
        {
            "category":"Freight",
            "type":"Transportation"
        }
    ],
    "sg:phone":"+61 3 9644 5270",
    "sg:postcode":"3207",
    "sg:province":"VIC",
    "sg:tags":[
        "transport",
        "refrigerated"
    ],
    "wof:name":"Edwards Transport",
    "wof:placetype":"venue"
},
  "geometry": {"coordinates":[144.911835,-37.837643],"type":"Point"}
}