{
  "type": "Feature",
  "properties": {
    "iso:country":"AU",
    "sg:address":"PO Box 386",
    "sg:city":"Werribee",
    "sg:classifiers":[
        {
            "category":"Health Services",
            "subcategory":"Health Practitioner",
            "type":"Services"
        }
    ],
    "sg:phone":"+61 404 096 801",
    "sg:postcode":"3030",
    "sg:province":"VIC",
    "sg:tags":[
        "naturopath"
    ],
    "wof:name":"Rebecca Screen",
    "wof:placetype":"venue"
},
  "geometry": {"coordinates":[144.659637,-37.903702],"type":"Point"}
}