{
  "type": "Feature",
  "properties": {
    "addr:full":"185 Spring St Doveton VIC 3177",
    "addr:housenumber":"185",
    "addr:postcode":"3177",
    "addr:street":"Spring St",
    "iso:country":"AU",
    "sg:address":"185 Spring St",
    "sg:city":"Doveton",
    "sg:classifiers":[
        {
            "category":"Utilities",
            "subcategory":"Electric",
            "type":"Services"
        }
    ],
    "sg:phone":"+61 3 9794 9047",
    "sg:postcode":"3177",
    "sg:province":"VIC",
    "sg:tags":[
        "electrical",
        "contractor"
    ],
    "wof:name":"A.AAABA Home Phone Cabeling",
    "wof:placetype":"venue"
},
  "geometry": {"coordinates":[145.23721313499999,-37.9829826355],"type":"Point"}
}