{
  "type": "Feature",
  "properties": {
    "iso:country":"AU",
    "sg:address":"Beek St",
    "sg:city":"Katamatite",
    "sg:classifiers":[
        {
            "category":"Travel",
            "subcategory":"Hotels & Motels",
            "type":"Entertainment"
        }
    ],
    "sg:phone":"+61 3 5865 1356",
    "sg:postcode":"3649",
    "sg:province":"VIC",
    "sg:tags":[
        "accommodation"
    ],
    "wof:name":"Katamatite Hotel",
    "wof:placetype":"venue"
},
  "geometry": {"coordinates":[145.68904113799999,-36.0789146423],"type":"Point"}
}