{
  "type": "Feature",
  "properties": {
    "addr:full":"Floor 5, 122 Castlereagh St Sydney NSW 2000",
    "addr:housenumber":"122",
    "addr:postcode":"2000",
    "addr:street":"Castlereagh St",
    "iso:country":"AU",
    "sg:address":"Floor 5, 122 Castlereagh St",
    "sg:city":"Sydney",
    "sg:classifiers":[
        {
            "category":"Health Services",
            "subcategory":"Health Practitioner",
            "type":"Services"
        }
    ],
    "sg:phone":"+61 2 9261 5007",
    "sg:postcode":"2000",
    "sg:province":"NSW",
    "sg:tags":[
        "naturopath"
    ],
    "wof:name":"Hankins C C",
    "wof:placetype":"venue"
},
  "geometry": {"coordinates":[151.209594727,-33.8711471558],"type":"Point"}
}