{
  "type": "Feature",
  "properties": {
    "iso:country":"AU",
    "sg:address":"61 High St",
    "sg:city":"Waratah",
    "sg:classifiers":[
        {
            "category":"Shopping",
            "subcategory":"Musical Instruments",
            "type":"Retail Goods"
        }
    ],
    "sg:phone":"+61 2 4967 1829",
    "sg:postcode":"2298",
    "sg:province":"NSW",
    "sg:tags":[
        "musician",
        "agent"
    ],
    "wof:name":"Waratah Girls Choir",
    "wof:placetype":"venue"
},
  "geometry": {"coordinates":[151.722579956,-32.9040145874],"type":"Point"}
}