{
  "type": "Feature",
  "properties": {
    "addr:full":"Cnr Warrego Hwy & Black St Dalby QLD 4405",
    "addr:postcode":"4405",
    "addr:street":"Cnr Warrego Hwy & Black St",
    "iso:country":"AU",
    "sg:address":"Cnr Warrego Hwy & Black St",
    "sg:city":"Dalby",
    "sg:classifiers":[
        {
            "category":"Shopping",
            "type":"Retail Goods"
        }
    ],
    "sg:phone":"+61 7 4662 4866",
    "sg:postcode":"4405",
    "sg:province":"QLD",
    "sg:tags":[
        "produce",
        "grain"
    ],
    "wof:name":"Keating's Produce",
    "wof:placetype":"venue"
},
  "geometry": {"coordinates":[151.255325317,-27.1777229309],"type":"Point"}
}