{
  "type": "Feature",
  "properties": {
    "iso:country":"AU",
    "sg:address":"80 Restwell St",
    "sg:city":"Bankstown",
    "sg:classifiers":[
        {
            "category":"Organizations",
            "subcategory":"Non-profit Organization",
            "type":"Services"
        }
    ],
    "sg:phone":"+61 2 9790 0600",
    "sg:postcode":"2200",
    "sg:province":"NSW",
    "sg:tags":[
        "support",
        "disability",
        "organisation"
    ],
    "wof:name":"Bankstown Handicapped Children's Centre",
    "wof:placetype":"venue"
},
  "geometry": {"coordinates":[151.03504899999999,-33.9216],"type":"Point"}
}