{
  "type": "Feature",
  "properties": {
    "iso:country":"AU",
    "sg:address":"203 Brisbane St",
    "sg:city":"Ipswich",
    "sg:classifiers":[
        {
            "category":"Shopping",
            "subcategory":"Crafts & Fabrics",
            "type":"Retail Goods"
        }
    ],
    "sg:phone":"+61 7 3812 1188",
    "sg:postcode":"4305",
    "sg:province":"QLD",
    "sg:tags":[
        "supply"
    ],
    "wof:name":"Art-Time Supplies",
    "wof:placetype":"venue"
},
  "geometry": {"coordinates":[152.75703430199999,-27.6139583588],"type":"Point"}
}