{
  "type": "Feature",
  "properties": {
    "addr:full":"12 Goldsworthy Rd Corio VIC 3214",
    "addr:housenumber":"12",
    "addr:postcode":"3214",
    "addr:street":"Goldsworthy Rd",
    "iso:country":"AU",
    "sg:address":"12 Goldsworthy Rd",
    "sg:city":"Corio",
    "sg:classifiers":[
        {
            "category":"Building & Trades",
            "subcategory":"Construction",
            "type":"Services"
        }
    ],
    "sg:phone":"+61 411 419 877",
    "sg:postcode":"3214",
    "sg:province":"VIC",
    "sg:tags":[
        "concrete",
        "contractor"
    ],
    "wof:name":"Stevies Concreting",
    "wof:placetype":"venue"
},
  "geometry": {"coordinates":[144.35658264200001,-38.0780410767],"type":"Point"}
}