{
  "type": "Feature",
  "properties": {
    "iso:country":"AU",
    "sg:address":"164 South Pde",
    "sg:city":"Auburn",
    "sg:classifiers":[
        {
            "category":"Personal",
            "type":"Services"
        }
    ],
    "sg:phone":"+61 2 9749 1712",
    "sg:postcode":"2144",
    "sg:province":"NSW",
    "sg:tags":[
        "reducing",
        "treatment",
        "weight"
    ],
    "wof:name":"Herbalife Auburn",
    "wof:placetype":"venue"
},
  "geometry": {"coordinates":[151.03082275400001,-33.8478965759],"type":"Point"}
}