{
  "type": "Feature",
  "properties": {
    "addr:full":"235 Victoria Ave Margate QLD 4019",
    "addr:housenumber":"235",
    "addr:postcode":"4019",
    "addr:street":"Victoria Ave",
    "iso:country":"AU",
    "sg:address":"235 Victoria Ave",
    "sg:city":"Margate",
    "sg:classifiers":[
        {
            "category":"Building & Trades",
            "subcategory":"Landscaping Services",
            "type":"Services"
        }
    ],
    "sg:phone":"+61 417 228 676",
    "sg:postcode":"4019",
    "sg:province":"QLD",
    "sg:tags":[
        "designer",
        "landscape",
        "contractor"
    ],
    "wof:name":"Express Landscapes & Paving",
    "wof:placetype":"venue"
},
  "geometry": {"coordinates":[153.10011291500001,-27.2380008698],"type":"Point"}
}