{
  "type": "Feature",
  "properties": {
    "addr:full":"5 York St Sydney NSW 2000",
    "addr:housenumber":"5",
    "addr:postcode":"2000",
    "addr:street":"York St",
    "iso:country":"AU",
    "sg:address":"5 York St",
    "sg:city":"Sydney",
    "sg:classifiers":[
        {
            "category":"Restaurant",
            "type":"Food & Drink"
        }
    ],
    "sg:phone":"+61 2 9299 8686",
    "sg:postcode":"2000",
    "sg:province":"NSW",
    "wof:name":"Condor Japanese Noodle Restaurant",
    "wof:placetype":"venue"
},
  "geometry": {"coordinates":[151.205444336,-33.8647079468],"type":"Point"}
}