{
  "type": "Feature",
  "properties": {
    "addr:full":"901 Beaudesert Rd Coopers Plains QLD 4108",
    "addr:housenumber":"901",
    "addr:postcode":"4108",
    "addr:street":"Beaudesert Rd",
    "iso:country":"AU",
    "sg:address":"901 Beaudesert Rd",
    "sg:city":"Coopers Plains",
    "sg:classifiers":[
        {
            "category":"Home & Garden",
            "subcategory":"Hardware",
            "type":"Retail Goods"
        }
    ],
    "sg:phone":"+61 7 3277 2044",
    "sg:postcode":"4108",
    "sg:province":"QLD",
    "sg:tags":[
        "tarpaulin"
    ],
    "wof:name":"Great Escape Camping Co. The",
    "wof:placetype":"venue"
},
  "geometry": {"coordinates":[153.02296447800001,-27.5644302368],"type":"Point"}
}