{
  "type": "Feature",
  "properties": {
    "iso:country":"AU",
    "sg:address":"Factory 18 10 Norton Drv",
    "sg:city":"Melton",
    "sg:classifiers":[
        {
            "category":"Home & Garden",
            "subcategory":"Garden Supply",
            "type":"Retail Goods"
        }
    ],
    "sg:phone":"+61 3 9746 9256",
    "sg:postcode":"3337",
    "sg:province":"VIC",
    "sg:tags":[
        "equipment",
        "hydroponics"
    ],
    "wof:name":"Melton Hydroponic Supplies",
    "wof:placetype":"venue"
},
  "geometry": {"coordinates":[144.60179099999999,-37.691059],"type":"Point"}
}