{
  "type": "Feature",
  "properties": {
    "iso:country":"AU",
    "sg:address":"PO Box 570",
    "sg:city":"Moe",
    "sg:classifiers":[
        {
            "category":"Farming",
            "subcategory":"Nursery",
            "type":"Manufacturing & Wholesale Goods"
        }
    ],
    "sg:phone":"+61 3 5126 2384",
    "sg:postcode":"3825",
    "sg:province":"VIC",
    "wof:name":"GEST Nurseries",
    "wof:placetype":"venue"
},
  "geometry": {"coordinates":[146.26391599999999,-38.174858],"type":"Point"}
}