{
  "type": "Feature",
  "properties": {
    "addr:full":"12 Killara Rd Campbellfield VIC 3061",
    "addr:housenumber":"12",
    "addr:postcode":"3061",
    "addr:street":"Killara Rd",
    "iso:country":"AU",
    "sg:address":"12 Killara Rd",
    "sg:city":"Campbellfield",
    "sg:classifiers":[
        {
            "category":"Wholesale",
            "subcategory":"Auto Parts",
            "type":"Manufacturing & Wholesale Goods"
        }
    ],
    "sg:phone":"+61 3 9357 7335",
    "sg:postcode":"3061",
    "sg:province":"VIC",
    "sg:tags":[
        "recyclers"
    ],
    "wof:name":"Hyon",
    "wof:placetype":"venue"
},
  "geometry": {"coordinates":[144.964187622,-37.667301178],"type":"Point"}
}