{
  "type": "Feature",
  "properties": {
    "iso:country":"AU",
    "sg:address":"Mayfield Rd",
    "sg:city":"Waroona",
    "sg:classifiers":[
        {
            "category":"Building & Trades",
            "subcategory":"Construction",
            "type":"Services"
        }
    ],
    "sg:phone":"+61 8 9733 2690",
    "sg:postcode":"6215",
    "sg:province":"WA",
    "sg:tags":[
        "fencing",
        "contractor"
    ],
    "wof:name":"Warback Contracting",
    "wof:placetype":"venue"
},
  "geometry": {"coordinates":[115.907692,-32.817314],"type":"Point"}
}