{
  "type": "Feature",
  "properties": {
    "addr:full":"PO Box 2054 Tarrawanna NSW 2518",
    "addr:postcode":"2518",
    "iso:country":"AU",
    "sg:address":"PO Box 2054",
    "sg:city":"Tarrawanna",
    "sg:classifiers":[
        {
            "category":"Professional",
            "subcategory":"Employment Agencies",
            "type":"Services"
        }
    ],
    "sg:phone":"+61 402 802 321",
    "sg:postcode":"2518",
    "sg:province":"NSW",
    "sg:tags":[
        "model"
    ],
    "wof:name":"Jason Cole Photography Modelling Careers Wollongong",
    "wof:placetype":"venue"
},
  "geometry": {"coordinates":[150.88807700000001,-34.380859],"type":"Point"}
}