{
  "type": "Feature",
  "properties": {
    "addr:full":"600 Lemnos Rd North Congupna VIC 3633",
    "addr:housenumber":"600",
    "addr:postcode":"3633",
    "addr:street":"Lemnos Rd North",
    "iso:country":"AU",
    "sg:address":"600 Lemnos Rd North",
    "sg:city":"Congupna",
    "sg:classifiers":[
        {
            "category":"Shopping",
            "type":"Retail Goods"
        }
    ],
    "sg:phone":"+61 3 5829 9245",
    "sg:postcode":"3633",
    "sg:province":"VIC",
    "sg:tags":[
        "agent",
        "stock"
    ],
    "wof:name":"Rodwells & Co Pty Ltd",
    "wof:placetype":"venue"
},
  "geometry": {"coordinates":[145.46211242699999,-36.3113327026],"type":"Point"}
}