{
  "type": "Feature",
  "properties": {
    "addr:full":"PO Box 6132 Shepparton VIC 3632",
    "addr:postcode":"3632",
    "iso:country":"AU",
    "sg:address":"PO Box 6132",
    "sg:city":"Shepparton",
    "sg:classifiers":[
        {
            "category":"Utilities",
            "subcategory":"Natural Gas",
            "type":"Services"
        }
    ],
    "sg:phone":"+61 3 5821 2999",
    "sg:postcode":"3632",
    "sg:province":"VIC",
    "sg:tags":[
        "cylinder",
        "testing"
    ],
    "wof:name":"Blazes Cylinder Testing Station",
    "wof:placetype":"venue"
},
  "geometry": {"coordinates":[145.399291992,-36.3811683655],"type":"Point"}
}