{
  "type": "Feature",
  "properties": {
    "addr:full":"Galloway Road Rd O'Sullivan Beach SA 5166",
    "addr:postcode":"5166",
    "addr:street":"Galloway Road Rd",
    "iso:country":"AU",
    "sg:address":"Galloway Road Rd",
    "sg:city":"O'Sullivan Beach",
    "sg:classifiers":[
        {
            "category":"Education",
            "subcategory":"Dance Studio",
            "type":"Public Place"
        }
    ],
    "sg:phone":"+61 8 8382 9494",
    "sg:postcode":"5166",
    "sg:province":"SA",
    "sg:tags":[
        "venue",
        "tuition"
    ],
    "wof:name":"Bits & Pieces Line Dancers",
    "wof:placetype":"venue"
},
  "geometry": {"coordinates":[138.476119995,-35.1221542358],"type":"Point"}
}