{
  "type": "Feature",
  "properties": {
    "iso:country":"AU",
    "sg:address":"30 Main St Mall",
    "sg:city":"Box Hill",
    "sg:classifiers":[
        {
            "category":"Shopping",
            "subcategory":"Clothing, Apparel, & Fashions",
            "type":"Retail Goods"
        }
    ],
    "sg:phone":"+61 3 9890 8689",
    "sg:postcode":"3128",
    "sg:province":"VIC",
    "sg:tags":[
        "menswear"
    ],
    "wof:name":"Louis Economy Shop Pty Ltd",
    "wof:placetype":"venue"
},
  "geometry": {"coordinates":[145.122650147,-37.8189201355],"type":"Point"}
}