{
  "type": "Feature",
  "properties": {
    "iso:country":"AU",
    "sg:address":"2 Corhampton Rd",
    "sg:city":"Balwyn North",
    "sg:classifiers":[
        {
            "category":"Health Services",
            "subcategory":"Doctor",
            "type":"Services"
        }
    ],
    "sg:phone":"+61 3 9859 3561",
    "sg:postcode":"3104",
    "sg:province":"VIC",
    "sg:tags":[
        "medical",
        "practitioner"
    ],
    "wof:name":"Parikh R",
    "wof:placetype":"venue"
},
  "geometry": {"coordinates":[145.067626953,-37.7931251526],"type":"Point"}
}