{
  "type": "Feature",
  "properties": {
    "addr:full":"317 Middleton Rd Albany WA 6330",
    "addr:housenumber":"317",
    "addr:postcode":"6330",
    "addr:street":"Middleton Rd",
    "iso:country":"AU",
    "sg:address":"317 Middleton Rd",
    "sg:city":"Albany",
    "sg:classifiers":[
        {
            "category":"Health Services",
            "subcategory":"Dentist",
            "type":"Services"
        }
    ],
    "sg:phone":"+61 8 9842 3252",
    "sg:postcode":"6330",
    "sg:province":"WA",
    "wof:name":"Singer Steven L",
    "wof:placetype":"venue"
},
  "geometry": {"coordinates":[117.88935852,-35.0174598694],"type":"Point"}
}