{
  "type": "Feature",
  "properties": {
    "addr:full":"117 Penshurst St Penshurst NSW 2222",
    "addr:housenumber":"117",
    "addr:postcode":"2222",
    "addr:street":"Penshurst St",
    "iso:country":"AU",
    "sg:address":"117 Penshurst St",
    "sg:city":"Penshurst",
    "sg:classifiers":[
        {
            "category":"Building & Trades",
            "subcategory":"Construction",
            "type":"Services"
        }
    ],
    "sg:phone":"+61 2 9570 1189",
    "sg:postcode":"2222",
    "sg:province":"NSW",
    "sg:tags":[
        "contractor"
    ],
    "wof:name":"Chris Wurst Builders",
    "wof:placetype":"venue"
},
  "geometry": {"coordinates":[151.08201599099999,-33.958278656],"type":"Point"}
}