{
  "type": "Feature",
  "properties": {
    "addr:full":"Shop 9 218 Dorset Rd Boronia VIC 3155",
    "addr:housenumber":"shop 9 218",
    "addr:postcode":"3155",
    "addr:street":"Dorset Rd",
    "iso:country":"AU",
    "sg:address":"Shop 9 218 Dorset Rd",
    "sg:city":"Boronia",
    "sg:classifiers":[
        {
            "category":"Cafe",
            "type":"Food & Drink"
        }
    ],
    "sg:phone":"+61 3 9761 1481",
    "sg:postcode":"3155",
    "sg:province":"VIC",
    "wof:name":"Before & After Coffee Shop",
    "wof:placetype":"venue"
},
  "geometry": {"coordinates":[145.28579711899999,-37.861869812],"type":"Point"}
}