{
  "type": "Feature",
  "properties": {
    "addr:full":"44 French St Netherby SA 5062",
    "addr:housenumber":"44",
    "addr:postcode":"5062",
    "addr:street":"French St",
    "iso:country":"AU",
    "sg:address":"44 French St",
    "sg:city":"Netherby",
    "sg:classifiers":[
        {
            "category":"Professional",
            "subcategory":"Business Services",
            "type":"Services"
        }
    ],
    "sg:phone":"+61 8 8227 0130",
    "sg:postcode":"5062",
    "sg:province":"SA",
    "sg:tags":[
        "broker"
    ],
    "wof:name":"Grant Kevin",
    "wof:placetype":"venue"
},
  "geometry": {"coordinates":[138.62164306599999,-34.972114563],"type":"Point"}
}