{
  "type": "Feature",
  "properties": {
    "addr:full":"5/ 72 Cecil Ave Castle Hill NSW 2154",
    "addr:housenumber":"/ 72",
    "addr:postcode":"2154",
    "addr:street":"Cecil Ave",
    "iso:country":"AU",
    "sg:address":"5/ 72 Cecil Ave",
    "sg:city":"Castle Hill",
    "sg:classifiers":[
        {
            "category":"Health Services",
            "subcategory":"Doctor",
            "type":"Services"
        }
    ],
    "sg:phone":"+61 2 9899 7322",
    "sg:postcode":"2154",
    "sg:province":"NSW",
    "sg:tags":[
        "medical",
        "practitioner"
    ],
    "wof:name":"Hollands Michael Dr",
    "wof:placetype":"venue"
},
  "geometry": {"coordinates":[151.00401306099999,-33.7352638245],"type":"Point"}
}