{
  "type": "Feature",
  "properties": {
    "iso:country":"AU",
    "sg:address":"37 Brunel Rd",
    "sg:city":"Seaford",
    "sg:classifiers":[
        {
            "category":"Fast Food",
            "type":"Food & Drink"
        }
    ],
    "sg:phone":"+61 3 9786 5866",
    "sg:postcode":"3198",
    "sg:province":"VIC",
    "sg:tags":[
        "away",
        "take"
    ],
    "wof:name":"Seaford Gourmet Foods",
    "wof:placetype":"venue"
},
  "geometry": {"coordinates":[145.14346313499999,-38.1007347107],"type":"Point"}
}