{
  "type": "Feature",
  "properties": {
    "addr:full":"10 Victoria St Alexandria NSW 2015",
    "addr:housenumber":"10",
    "addr:postcode":"2015",
    "addr:street":"Victoria St",
    "iso:country":"AU",
    "sg:address":"10 Victoria St",
    "sg:city":"Alexandria",
    "sg:classifiers":[
        {
            "category":"Retail",
            "subcategory":"Auto Repair",
            "type":"Services"
        }
    ],
    "sg:phone":"+61 2 9310 5555",
    "sg:postcode":"2015",
    "sg:province":"NSW",
    "sg:tags":[
        "repairer",
        "motor",
        "engineer"
    ],
    "wof:name":"V & A Car Repairs",
    "wof:placetype":"venue"
},
  "geometry": {"coordinates":[151.20164489699999,-33.9087295532],"type":"Point"}
}