{
  "type": "Feature",
  "properties": {
    "iso:country":"AU",
    "sg:address":"15 Salisbury Rd",
    "sg:city":"Albany",
    "sg:classifiers":[
        {
            "category":"Wholesale",
            "subcategory":"Plants",
            "type":"Manufacturing & Wholesale Goods"
        }
    ],
    "sg:phone":"+61 8 9841 6663",
    "sg:postcode":"6330",
    "sg:province":"WA",
    "sg:tags":[
        "florist"
    ],
    "wof:name":"Albany Alstroemerias",
    "wof:placetype":"venue"
},
  "geometry": {"coordinates":[117.847633362,-34.9834022522],"type":"Point"}
}