{
  "type": "Feature",
  "properties": {
    "iso:country":"AU",
    "sg:address":"176 River St",
    "sg:city":"Ballina",
    "sg:classifiers":[
        {
            "category":"Real Estate",
            "subcategory":"Real Estate Agent",
            "type":"Services"
        }
    ],
    "sg:phone":"+61 2 6686 8000",
    "sg:postcode":"2478",
    "sg:province":"NSW",
    "wof:name":"Elders Real Estate Ballina",
    "wof:placetype":"venue"
},
  "geometry": {"coordinates":[153.55967712399999,-28.8702793121],"type":"Point"}
}