{
  "type": "Feature",
  "properties": {
    "iso:country":"AU",
    "sg:address":"Koonwarra Rd",
    "sg:city":"Leongatha",
    "sg:classifiers":[
        {
            "category":"Health Services",
            "subcategory":"Doctor",
            "type":"Services"
        }
    ],
    "sg:phone":"+61 3 5667 5579",
    "sg:postcode":"3953",
    "sg:province":"VIC",
    "sg:tags":[
        "medical",
        "practitioner"
    ],
    "wof:name":"MIA Victoria",
    "wof:placetype":"venue"
},
  "geometry": {"coordinates":[145.94935607900001,-38.480091095],"type":"Point"}
}