{
  "type": "Feature",
  "properties": {
    "addr:full":"91 Brebner Drv West Lakes SA 5021",
    "addr:housenumber":"91",
    "addr:postcode":"5021",
    "addr:street":"Brebner Drv",
    "iso:country":"AU",
    "sg:address":"91 Brebner Drv",
    "sg:city":"West Lakes",
    "sg:classifiers":[
        {
            "category":"Commercial Area",
            "type":"Public Place"
        }
    ],
    "sg:phone":"+61 8 8235 9136",
    "sg:postcode":"5021",
    "sg:province":"SA",
    "sg:tags":[
        "heavy",
        "carrier"
    ],
    "wof:name":"Glen Karron",
    "wof:placetype":"venue"
},
  "geometry": {"coordinates":[138.48954773,-34.8816108704],"type":"Point"}
}