{
  "type": "Feature",
  "properties": {
    "iso:country":"AU",
    "sg:address":"68 Avondale Ave",
    "sg:city":"Lismore East",
    "sg:classifiers":[
        {
            "category":"Health Services",
            "subcategory":"Doctor",
            "type":"Services"
        }
    ],
    "sg:phone":"+61 2 6622 8155",
    "sg:postcode":"2480",
    "sg:province":"NSW",
    "sg:tags":[
        "medical",
        "practitioner"
    ],
    "wof:name":"Mcculloch John Dr",
    "wof:placetype":"venue"
},
  "geometry": {"coordinates":[153.28985595699999,-28.8188266754],"type":"Point"}
}