{
  "type": "Feature",
  "properties": {
    "iso:country":"AU",
    "sg:address":"44 Spencer St",
    "sg:city":"Melbourne",
    "sg:classifiers":[
        {
            "category":"Travel",
            "subcategory":"Hotels & Motels",
            "type":"Entertainment"
        }
    ],
    "sg:phone":"+61 3 9629 6991",
    "sg:postcode":"3000",
    "sg:province":"VIC",
    "sg:tags":[
        "accommodation"
    ],
    "wof:name":"Hotel Enterprize",
    "wof:placetype":"venue"
},
  "geometry": {"coordinates":[144.954681397,-37.819770813],"type":"Point"}
}