{
  "type": "Feature",
  "properties": {
    "addr:full":"Head Office (Australasia) 11 Averill St Rhodes NSW 2138",
    "addr:housenumber":"11",
    "addr:postcode":"2138",
    "addr:street":"Australasia;Averill St",
    "iso:country":"AU",
    "sg:address":"Head Office (Australasia) 11 Averill St",
    "sg:city":"Rhodes",
    "sg:classifiers":[
        {
            "category":"Education",
            "subcategory":"Special Training",
            "type":"Public Place"
        }
    ],
    "sg:phone":"+61 2 9736 0000",
    "sg:postcode":"2138",
    "sg:province":"NSW",
    "sg:tags":[
        "development",
        "sale"
    ],
    "wof:name":"Priority Management",
    "wof:placetype":"venue"
},
  "geometry": {"coordinates":[151.08999633799999,-33.8253135681],"type":"Point"}
}