{
  "type": "Feature",
  "properties": {
    "addr:full":"192 Lonsdale St Melbourne VIC 3000",
    "addr:housenumber":"192",
    "addr:postcode":"3000",
    "addr:street":"Lonsdale St",
    "iso:country":"AU",
    "sg:address":"192 Lonsdale St",
    "sg:city":"Melbourne",
    "sg:classifiers":[
        {
            "category":"Restaurant",
            "type":"Food & Drink"
        }
    ],
    "sg:phone":"+61 3 9663 3375",
    "sg:postcode":"3000",
    "sg:province":"VIC",
    "wof:name":"Elements On Lonsdale",
    "wof:placetype":"venue"
},
  "geometry": {"coordinates":[144.96621704099999,-37.8109931946],"type":"Point"}
}