{
  "type": "Feature",
  "properties": {
    "iso:country":"AU",
    "sg:address":"Forsyth St",
    "sg:city":"Whyalla",
    "sg:classifiers":[
        {
            "category":"Travel",
            "subcategory":"Hotels & Motels",
            "type":"Entertainment"
        }
    ],
    "sg:phone":"+61 8 8645 8411",
    "sg:postcode":"5600",
    "sg:province":"SA",
    "sg:tags":[
        "accommodation"
    ],
    "wof:name":"Hotel Spencer",
    "wof:placetype":"venue"
},
  "geometry": {"coordinates":[137.580093,-33.030159],"type":"Point"}
}