{
  "type": "Feature",
  "properties": {
    "addr:full":"45 Ninth St Mildura VIC 3500",
    "addr:housenumber":"45",
    "addr:postcode":"3500",
    "addr:street":"Ninth St",
    "iso:country":"AU",
    "sg:address":"45 Ninth St",
    "sg:city":"Mildura",
    "sg:classifiers":[
        {
            "category":"Building & Trades",
            "subcategory":"Construction",
            "type":"Services"
        }
    ],
    "sg:phone":"+61 3 5023 4700",
    "sg:postcode":"3500",
    "sg:province":"VIC",
    "sg:tags":[
        "joinery"
    ],
    "wof:name":"Fuda Larry",
    "wof:placetype":"venue"
},
  "geometry": {"coordinates":[142.16807556099999,-34.1927604675],"type":"Point"}
}