{
  "type": "Feature",
  "properties": {
    "addr:full":"142 Dynon Rd West Melbourne VIC 3003",
    "addr:housenumber":"142",
    "addr:postcode":"3003",
    "addr:street":"Dynon Rd",
    "iso:country":"AU",
    "sg:address":"142 Dynon Rd",
    "sg:city":"West Melbourne",
    "sg:classifiers":[
        {
            "category":"Social Services",
            "subcategory":"Retirement Home",
            "type":"Services"
        }
    ],
    "sg:phone":"+61 3 9372 5688",
    "sg:postcode":"3003",
    "sg:province":"VIC",
    "sg:tags":[
        "environmental",
        "consultant",
        "pollution"
    ],
    "sg:website":"http://www.connolly.com.au",
    "wof:name":"Connolly Environmental",
    "wof:placetype":"venue"
},
  "geometry": {"coordinates":[144.92942810100001,-37.8029594421],"type":"Point"}
}