{
  "type": "Feature",
  "properties": {
    "addr:full":"92 Queen St Bendigo VIC 3550",
    "addr:housenumber":"92",
    "addr:postcode":"3550",
    "addr:street":"Queen St",
    "iso:country":"AU",
    "sg:address":"92 Queen St",
    "sg:city":"Bendigo",
    "sg:classifiers":[
        {
            "category":"Real Estate",
            "subcategory":"Real Estate Agent",
            "type":"Services"
        }
    ],
    "sg:phone":"+61 3 5442 9000",
    "sg:postcode":"3550",
    "sg:province":"VIC",
    "wof:name":"Bendigo Property Management Pty. Ltd.",
    "wof:placetype":"venue"
},
  "geometry": {"coordinates":[144.27755737300001,-36.763168335],"type":"Point"}
}