{
  "type": "Feature",
  "properties": {
    "iso:country":"AU",
    "sg:address":"28a Wells St",
    "sg:city":"Frankston",
    "sg:classifiers":[
        {
            "category":"Restaurant",
            "type":"Food & Drink"
        }
    ],
    "sg:phone":"+61 3 9781 5642",
    "sg:postcode":"3199",
    "sg:province":"VIC",
    "wof:name":"Cha-Chi's Mexican Place Frankston",
    "wof:placetype":"venue"
},
  "geometry": {"coordinates":[144.968826294,-37.8266410828],"type":"Point"}
}