{
  "type": "Feature",
  "properties": {
    "addr:full":"14/ 100 McLeod St Cairns QLD 4870",
    "addr:housenumber":"14 / 100",
    "addr:postcode":"4870",
    "addr:street":"Mcleod St",
    "iso:country":"AU",
    "sg:address":"14/ 100 McLeod St",
    "sg:city":"Cairns",
    "sg:classifiers":[
        {
            "category":"Building & Trades",
            "subcategory":"Landscaping Services",
            "type":"Services"
        }
    ],
    "sg:phone":"+61 7 4041 1616",
    "sg:postcode":"4870",
    "sg:province":"QLD",
    "sg:tags":[
        "inspection"
    ],
    "wof:name":"TKO Pest Management",
    "wof:placetype":"venue"
},
  "geometry": {"coordinates":[145.768844605,-16.9196987152],"type":"Point"}
}