{
  "type": "Feature",
  "properties": {
    "iso:country":"AU",
    "sg:address":"3 Moresby Crt",
    "sg:city":"Heidelberg West",
    "sg:classifiers":[
        {
            "category":"Food & Beverages",
            "subcategory":"Liquor & Beverages",
            "type":"Retail Goods"
        }
    ],
    "sg:phone":"+61 3 9455 0813",
    "sg:postcode":"3081",
    "sg:province":"VIC",
    "sg:tags":[
        "store"
    ],
    "wof:name":"Bottle Mart At Norman's Olympic Cellars",
    "wof:placetype":"venue"
},
  "geometry": {"coordinates":[145.039993286,-37.7410736084],"type":"Point"}
}