{
  "type": "Feature",
  "properties": {
    "iso:country":"AU",
    "sg:address":"145 Browns Plains Rd",
    "sg:city":"Browns Plains",
    "sg:classifiers":[
        {
            "category":"Utilities",
            "subcategory":"Electric",
            "type":"Services"
        }
    ],
    "sg:phone":"+61 7 3802 4500",
    "sg:postcode":"4118",
    "sg:province":"QLD",
    "sg:tags":[
        "tube",
        "lamps",
        "globe"
    ],
    "wof:name":"Ideal Electrical Suppliers",
    "wof:placetype":"venue"
},
  "geometry": {"coordinates":[153.05267334000001,-27.6625957489],"type":"Point"}
}