{
  "type": "Feature",
  "properties": {
    "addr:full":"145 Boronia Rd Boronia VIC 3155",
    "addr:housenumber":"145",
    "addr:postcode":"3155",
    "addr:street":"Boronia Rd",
    "iso:country":"AU",
    "sg:address":"145 Boronia Rd",
    "sg:city":"Boronia",
    "sg:classifiers":[
        {
            "category":"Communications",
            "subcategory":"Film & Video Production",
            "type":"Services"
        }
    ],
    "sg:phone":"+61 3 9762 3600",
    "sg:postcode":"3155",
    "sg:province":"VIC",
    "sg:tags":[
        "dvd",
        "library"
    ],
    "wof:name":"Video Busters",
    "wof:placetype":"venue"
},
  "geometry": {"coordinates":[145.28346252399999,-37.8622093201],"type":"Point"}
}