{
  "type": "Feature",
  "properties": {
    "iso:country":"AU",
    "sg:address":"7- 11 Hovell St",
    "sg:city":"Wodonga",
    "sg:phone":"+61 2 6055 3333",
    "sg:postcode":"3689",
    "sg:province":"NSW",
    "wof:name":"Kellys Wodonga",
    "wof:placetype":"venue"
},
  "geometry": {"coordinates":[146.89434800000001,-36.115417],"type":"Point"}
}