{
  "type": "Feature",
  "properties": {
    "addr:full":"West Mooreville Rd Burnie TAS 7320",
    "addr:postcode":"7320",
    "addr:street":"West Mooreville Rd",
    "iso:country":"AU",
    "sg:address":"West Mooreville Rd",
    "sg:city":"Burnie",
    "sg:classifiers":[
        {
            "category":"Organizations",
            "subcategory":"Non-profit Organization",
            "type":"Services"
        }
    ],
    "sg:phone":"+61 3 6433 3922",
    "sg:postcode":"7320",
    "sg:province":"TAS",
    "sg:tags":[
        "support",
        "disability",
        "organisation"
    ],
    "wof:name":"Panorama Supported Accommodation",
    "wof:placetype":"venue"
},
  "geometry": {"coordinates":[145.88121000000001,-41.059193],"type":"Point"}
}