{
  "type": "Feature",
  "properties": {
    "iso:country":"AU",
    "sg:address":"22 Seventh St",
    "sg:city":"Lambton North",
    "sg:classifiers":[
        {
            "category":"Building & Trades",
            "subcategory":"Construction",
            "type":"Services"
        }
    ],
    "sg:phone":"+61 414 844 880",
    "sg:postcode":"2299",
    "sg:province":"NSW",
    "sg:tags":[
        "concrete",
        "contractor"
    ],
    "wof:name":"Ben Cowling Concreting",
    "wof:placetype":"venue"
},
  "geometry": {"coordinates":[151.70399475100001,-32.9027137756],"type":"Point"}
}