{
  "type": "Feature",
  "properties": {
    "iso:country":"AU",
    "sg:address":"2/ 13 Douglas Mawson Rd",
    "sg:city":"Dubbo",
    "sg:classifiers":[
        {
            "category":"Food & Beverages",
            "subcategory":"Groceries & Convenience Stores",
            "type":"Retail Goods"
        }
    ],
    "sg:phone":"+61 2 6884 1166",
    "sg:postcode":"2830",
    "sg:province":"NSW",
    "wof:name":"GARIAN FOOD WHOLESALERS",
    "wof:placetype":"venue"
},
  "geometry": {"coordinates":[148.63336181599999,-32.2473297119],"type":"Point"}
}