{
  "type": "Feature",
  "properties": {
    "iso:country":"AU",
    "sg:address":"4/ 59 Bowen Rd",
    "sg:city":"Rosslea",
    "sg:classifiers":[
        {
            "category":"Education",
            "subcategory":"School",
            "type":"Public Place"
        }
    ],
    "sg:phone":"+61 7 4725 4418",
    "sg:postcode":"4812",
    "sg:province":"QLD",
    "sg:tags":[
        "supply"
    ],
    "wof:name":"Headstart",
    "wof:placetype":"venue"
},
  "geometry": {"coordinates":[146.797699,-19.2969],"type":"Point"}
}