{
  "type": "Feature",
  "properties": {
    "addr:full":"7 Barlee Pl Aspley QLD 4034",
    "addr:housenumber":"7",
    "addr:postcode":"4034",
    "addr:street":"Barlee Pl",
    "iso:country":"AU",
    "sg:address":"7 Barlee Pl",
    "sg:city":"Aspley",
    "sg:classifiers":[
        {
            "category":"Education",
            "subcategory":"Music School",
            "type":"Public Place"
        }
    ],
    "sg:phone":"+61 417 603 852",
    "sg:postcode":"4034",
    "sg:province":"QLD",
    "sg:tags":[
        "choir",
        "bands",
        "orchestra"
    ],
    "wof:name":"Aisle Be There",
    "wof:placetype":"venue"
},
  "geometry": {"coordinates":[153.00994900000001,-27.368685],"type":"Point"}
}