{
  "type": "Feature",
  "properties": {
    "addr:full":"U3/ 2a Burrows Rd St Peters NSW 2044",
    "addr:housenumber":"2a",
    "addr:postcode":"2044",
    "addr:street":"U3 /;Burrows Rd",
    "iso:country":"AU",
    "sg:address":"U3/ 2a Burrows Rd",
    "sg:city":"St Peters",
    "sg:classifiers":[
        {
            "category":"Fast Food",
            "type":"Food & Drink"
        }
    ],
    "sg:phone":"+61 2 9519 5504",
    "sg:postcode":"2044",
    "sg:province":"NSW",
    "sg:tags":[
        "away",
        "take"
    ],
    "wof:name":"Garlo's Pies St Peters",
    "wof:placetype":"venue"
},
  "geometry": {"coordinates":[151.17871099999999,-33.919483],"type":"Point"}
}