{
  "type": "Feature",
  "properties": {
    "addr:full":"24 Croydon Rd Croydon VIC 3136",
    "addr:housenumber":"24",
    "addr:postcode":"3136",
    "addr:street":"Croydon Rd",
    "iso:country":"AU",
    "sg:address":"24 Croydon Rd",
    "sg:city":"Croydon",
    "sg:classifiers":[
        {
            "category":"Arena",
            "subcategory":"Sports Club",
            "type":"Entertainment"
        }
    ],
    "sg:phone":"+61 3 9725 5677",
    "sg:postcode":"3136",
    "sg:province":"VIC",
    "sg:tags":[
        "defence",
        "supply",
        "self",
        "instruction",
        "martial art"
    ],
    "wof:name":"Norton Karate Do",
    "wof:placetype":"venue"
},
  "geometry": {"coordinates":[145.28216552699999,-37.7919960022],"type":"Point"}
}