{
  "type": "Feature",
  "properties": {
    "addr:full":"42 Killara Ave Panania NSW 2213",
    "addr:housenumber":"42",
    "addr:postcode":"2213",
    "addr:street":"Killara Ave",
    "iso:country":"AU",
    "sg:address":"42 Killara Ave",
    "sg:city":"Panania",
    "sg:classifiers":[
        {
            "category":"Professional",
            "subcategory":"Art Services",
            "type":"Services"
        }
    ],
    "sg:phone":"+61 2 9772 4572",
    "sg:postcode":"2213",
    "sg:province":"NSW",
    "sg:tags":[
        "decorator",
        "painter"
    ],
    "wof:name":"M.G. & N. Childs",
    "wof:placetype":"venue"
},
  "geometry": {"coordinates":[150.995499,-33.94952],"type":"Point"}
}