{
  "type": "Feature",
  "properties": {
    "addr:full":"PO Box 185 Punchbowl NSW 2196",
    "addr:postcode":"2196",
    "iso:country":"AU",
    "sg:address":"PO Box 185",
    "sg:city":"Punchbowl",
    "sg:classifiers":[
        {
            "category":"Building & Trades",
            "subcategory":"Construction",
            "type":"Services"
        }
    ],
    "sg:phone":"+61 410 543 443",
    "sg:postcode":"2196",
    "sg:province":"NSW",
    "sg:tags":[
        "waterproofing",
        "contractor"
    ],
    "wof:name":"No Limit Waterproofing & Painting",
    "wof:placetype":"venue"
},
  "geometry": {"coordinates":[151.053391,-33.9286],"type":"Point"}
}