{
  "type": "Feature",
  "properties": {
    "iso:country":"AU",
    "sg:address":"291 Homer St",
    "sg:city":"Earlwood",
    "sg:classifiers":[
        {
            "category":"Health Services",
            "subcategory":"Optometrist",
            "type":"Services"
        }
    ],
    "sg:phone":"+61 2 9558 7233",
    "sg:postcode":"2206",
    "sg:province":"NSW",
    "sg:website":"http://www.oaansw.com.au",
    "wof:name":"Peter T Coroneo",
    "wof:placetype":"venue"
},
  "geometry": {"coordinates":[151.123734,-33.92791],"type":"Point"}
}