{
  "type": "Feature",
  "properties": {
    "addr:full":"16- 20 Good St Granville NSW 2142",
    "addr:housenumber":"20",
    "addr:postcode":"2142",
    "addr:street":"Good St",
    "iso:country":"AU",
    "sg:address":"16- 20 Good St",
    "sg:city":"Granville",
    "sg:classifiers":[
        {
            "category":"Organizations",
            "subcategory":"Labor Organization",
            "type":"Services"
        }
    ],
    "sg:phone":"+61 2 9897 3644",
    "sg:postcode":"2142",
    "sg:province":"NSW",
    "sg:tags":[
        "union"
    ],
    "wof:name":"Australian Workers Union (NSW Branch)",
    "wof:placetype":"venue"
},
  "geometry": {"coordinates":[151.01150512699999,-33.831577301],"type":"Point"}
}