{
  "type": "Feature",
  "properties": {
    "iso:country":"AU",
    "sg:address":"McCulloch Drv",
    "sg:city":"Hadspen",
    "sg:classifiers":[
        {
            "category":"Social Services",
            "subcategory":"Retirement Home",
            "type":"Services"
        }
    ],
    "sg:phone":"+61 3 6393 6461",
    "sg:postcode":"7290",
    "sg:province":"TAS",
    "sg:tags":[
        "village"
    ],
    "wof:name":"Rutherglen Residential Club",
    "wof:placetype":"venue"
},
  "geometry": {"coordinates":[147.06124877900001,-41.5166931152],"type":"Point"}
}