{
  "type": "Feature",
  "properties": {
    "addr:full":"Prinsep St Norseman WA 6443",
    "addr:postcode":"6443",
    "addr:street":"St",
    "iso:country":"AU",
    "sg:address":"Prinsep St",
    "sg:city":"Norseman",
    "sg:classifiers":[
        {
            "category":"Travel",
            "subcategory":"Hotels & Motels",
            "type":"Entertainment"
        }
    ],
    "sg:phone":"+61 8 9039 1633",
    "sg:postcode":"6443",
    "sg:province":"WA",
    "wof:name":"Norseman Great Western Travel Village",
    "wof:placetype":"venue"
},
  "geometry": {"coordinates":[121.778839111,-32.1954193115],"type":"Point"}
}