{
  "type": "Feature",
  "properties": {
    "iso:country":"AU",
    "sg:address":"Shop 3, 6 Thomas Brew La",
    "sg:city":"Croydon",
    "sg:classifiers":[
        {
            "category":"Professional",
            "subcategory":"Computer Services",
            "type":"Services"
        }
    ],
    "sg:phone":"+61 3 9725 9826",
    "sg:postcode":"3136",
    "sg:province":"VIC",
    "sg:tags":[
        "repairs",
        "upgrade",
        "equipment"
    ],
    "wof:name":"PC City",
    "wof:placetype":"venue"
},
  "geometry": {"coordinates":[145.281982422,-37.7957077026],"type":"Point"}
}