{
  "type": "Feature",
  "properties": {
    "iso:country":"AU",
    "sg:address":"16 Stewart Ave",
    "sg:city":"Inverloch",
    "sg:classifiers":[
        {
            "category":"Home & Garden",
            "subcategory":"Building Materials",
            "type":"Retail Goods"
        }
    ],
    "sg:phone":"+61 3 5674 3990",
    "sg:postcode":"3996",
    "sg:province":"VIC",
    "sg:tags":[
        "concrete",
        "gutter",
        "kerb"
    ],
    "wof:name":"Sean & Dayle Hubbard",
    "wof:placetype":"venue"
},
  "geometry": {"coordinates":[145.728424,-38.627239],"type":"Point"}
}