{
  "type": "Feature",
  "properties": {
    "addr:full":"360 Bourke St Melbourne VIC 3000",
    "addr:housenumber":"360",
    "addr:postcode":"3000",
    "addr:street":"Bourke St",
    "iso:country":"AU",
    "sg:address":"360 Bourke St",
    "sg:city":"Melbourne",
    "sg:classifiers":[
        {
            "category":"Shopping",
            "type":"Retail Goods"
        }
    ],
    "sg:phone":"+61 3 9642 1942",
    "sg:postcode":"3000",
    "sg:province":"VIC",
    "sg:tags":[
        "repair",
        "travel"
    ],
    "wof:name":"Kathmandu",
    "wof:placetype":"venue"
},
  "geometry": {"coordinates":[144.963012695,-37.8141555786],"type":"Point"}
}