{
  "type": "Feature",
  "properties": {
    "iso:country":"AU",
    "sg:address":"1348 Gregory St",
    "sg:city":"Wendouree",
    "sg:classifiers":[
        {
            "category":"Building & Trades",
            "subcategory":"Construction",
            "type":"Services"
        }
    ],
    "sg:phone":"+61 3 5339 6445",
    "sg:postcode":"3355",
    "sg:province":"VIC",
    "sg:tags":[
        "fencing",
        "contractor"
    ],
    "wof:name":"Rick Sutherland Fencing & Construction",
    "wof:placetype":"venue"
},
  "geometry": {"coordinates":[143.824631,-37.54108],"type":"Point"}
}