{
  "type": "Feature",
  "properties": {
    "iso:country":"AU",
    "sg:address":"15 Lindus St",
    "sg:city":"Wickham",
    "sg:classifiers":[
        {
            "category":"Taxi",
            "type":"Transportation"
        }
    ],
    "sg:phone":"+61 2 4969 6779",
    "sg:postcode":"2293",
    "sg:province":"NSW",
    "sg:tags":[
        "truck"
    ],
    "wof:name":"Security & Integrated Services Pty Ltd",
    "wof:placetype":"venue"
},
  "geometry": {"coordinates":[151.75750732399999,-32.921836853],"type":"Point"}
}