{
  "type": "Feature",
  "properties": {
    "iso:country":"AU",
    "sg:address":"44 Yeneda St",
    "sg:city":"Balwyn North",
    "sg:classifiers":[
        {
            "category":"Utilities",
            "subcategory":"Refuse",
            "type":"Services"
        }
    ],
    "sg:phone":"+61 3 9816 4132",
    "sg:postcode":"3104",
    "sg:province":"VIC",
    "sg:tags":[
        "boiler"
    ],
    "wof:name":"D & S Boiler Services",
    "wof:placetype":"venue"
},
  "geometry": {"coordinates":[145.103424072,-37.8017311096],"type":"Point"}
}