{
  "type": "Feature",
  "properties": {
    "addr:full":"42- 50 Dobney Ave Wagga Wagga NSW 2650",
    "addr:housenumber":"50",
    "addr:postcode":"2650",
    "addr:street":"Dobney Ave",
    "iso:country":"AU",
    "sg:address":"42- 50 Dobney Ave",
    "sg:city":"Wagga Wagga",
    "sg:classifiers":[
        {
            "category":"Autos & Motor Vehicles",
            "subcategory":"Automobile Sales",
            "type":"Retail Goods"
        }
    ],
    "sg:phone":"+61 2 6937 3288",
    "sg:postcode":"2650",
    "sg:province":"NSW",
    "sg:tags":[
        "car",
        "new"
    ],
    "wof:name":"Wagga Prestige",
    "wof:placetype":"venue"
},
  "geometry": {"coordinates":[147.34259033199999,-35.1231536865],"type":"Point"}
}