{
  "type": "Feature",
  "properties": {
    "iso:country":"AU",
    "sg:address":"36 Kennedy's Drv",
    "sg:city":"Delacombe",
    "sg:classifiers":[
        {
            "category":"Building & Trades",
            "subcategory":"Plumbing",
            "type":"Services"
        }
    ],
    "sg:phone":"+61 3 5335 5890",
    "sg:postcode":"3356",
    "sg:province":"VIC",
    "sg:tags":[
        "equipment",
        "valves"
    ],
    "wof:name":"Pipeline Controls Pty Ltd",
    "wof:placetype":"venue"
},
  "geometry": {"coordinates":[143.83866900000001,-37.568298],"type":"Point"}
}