{
  "type": "Feature",
  "properties": {
    "addr:full":"508a Punchbowl Rd Lakemba NSW 2195",
    "addr:housenumber":"508a",
    "addr:postcode":"2195",
    "addr:street":"Punchbowl Rd",
    "iso:country":"AU",
    "sg:address":"508a Punchbowl Rd",
    "sg:city":"Lakemba",
    "sg:classifiers":[
        {
            "category":"Retail",
            "subcategory":"Auto Repair",
            "type":"Services"
        }
    ],
    "sg:phone":"+61 2 9759 6666",
    "sg:postcode":"2195",
    "sg:province":"NSW",
    "sg:tags":[
        "beater",
        "painter",
        "panel"
    ],
    "wof:name":"AAA Body & Paint",
    "wof:placetype":"venue"
},
  "geometry": {"coordinates":[151.07456999999999,-33.910477],"type":"Point"}
}