{
  "type": "Feature",
  "properties": {
    "iso:country":"AU",
    "sg:address":"Factory 2 4 England St",
    "sg:city":"Dandenong South",
    "sg:classifiers":[
        {
            "category":"Manufacturing",
            "subcategory":"Furniture",
            "type":"Manufacturing & Wholesale Goods"
        }
    ],
    "sg:phone":"+61 3 9706 6588",
    "sg:postcode":"3175",
    "sg:province":"VIC",
    "sg:tags":[
        "builder",
        "designer",
        "custom"
    ],
    "wof:name":"Makfurn Furniture",
    "wof:placetype":"venue"
},
  "geometry": {"coordinates":[145.21890258799999,-38.0318222046],"type":"Point"}
}