{
  "type": "Feature",
  "properties": {
    "addr:full":"25 Carbine Way Mornington VIC 3931",
    "addr:housenumber":"25",
    "addr:postcode":"3931",
    "addr:street":"Carbine Way",
    "iso:country":"AU",
    "sg:address":"25 Carbine Way",
    "sg:city":"Mornington",
    "sg:classifiers":[
        {
            "category":"Home & Garden",
            "subcategory":"Carpets & Floor Coverings",
            "type":"Retail Goods"
        }
    ],
    "sg:phone":"+61 3 5975 6323",
    "sg:postcode":"3931",
    "sg:province":"VIC",
    "sg:tags":[
        "tile",
        "wall"
    ],
    "sg:website":"http://www.stoneandtile.com.au",
    "wof:name":"Stone & Tile Centre",
    "wof:placetype":"venue"
},
  "geometry": {"coordinates":[145.065872192,-38.22996521],"type":"Point"}
}