{
  "type": "Feature",
  "properties": {
    "iso:country":"AU",
    "sg:address":"Northland Shopping Centre, 2 Murray Rd",
    "sg:city":"Preston East",
    "sg:classifiers":[
        {
            "category":"Banks & Credit Unions",
            "subcategory":"Investment Brokerage",
            "type":"Services"
        }
    ],
    "sg:phone":"+61 1800 630 705",
    "sg:postcode":"3072",
    "sg:province":"VIC",
    "wof:name":"St Andrew's Financial Services Ltd",
    "wof:placetype":"venue"
},
  "geometry": {"coordinates":[145.03074645999999,-37.7408294678],"type":"Point"}
}