{
  "type": "Feature",
  "properties": {
    "iso:country":"AU",
    "sg:address":"164 Rifle Range Rd",
    "sg:city":"Gympie",
    "sg:classifiers":[
        {
            "category":"Retail",
            "subcategory":"Auto Repair",
            "type":"Services"
        }
    ],
    "sg:phone":"+61 7 5482 8418",
    "sg:postcode":"4570",
    "sg:province":"QLD",
    "sg:tags":[
        "recapping",
        "repairing",
        "retreading",
        "tyre"
    ],
    "wof:name":"Petes Mobile Tyre Service",
    "wof:placetype":"venue"
},
  "geometry": {"coordinates":[152.684051514,-26.189868927],"type":"Point"}
}