{
  "type": "Feature",
  "properties": {
    "iso:country":"AU",
    "sg:address":"17 Gunya St",
    "sg:city":"Regents Park",
    "sg:classifiers":[
        {
            "category":"Professional",
            "subcategory":"Engineering",
            "type":"Services"
        }
    ],
    "sg:phone":"+61 2 9738 5508",
    "sg:postcode":"2143",
    "sg:province":"NSW",
    "sg:tags":[
        "manufacturing",
        "engineer"
    ],
    "wof:name":"Severs Technical Systems",
    "wof:placetype":"venue"
},
  "geometry": {"coordinates":[151.022903442,-33.8863372803],"type":"Point"}
}