{
  "type": "Feature",
  "properties": {
    "addr:full":"Level 1/ 141 Osborne St South Yarra VIC 3141",
    "addr:housenumber":"/ 141",
    "addr:postcode":"3141",
    "addr:street":"Osborne St",
    "iso:country":"AU",
    "sg:address":"Level 1/ 141 Osborne St",
    "sg:city":"South Yarra",
    "sg:classifiers":[
        {
            "category":"Professional",
            "subcategory":"Employment Agencies",
            "type":"Services"
        }
    ],
    "sg:phone":"+61 3 9279 3910",
    "sg:postcode":"3141",
    "sg:province":"VIC",
    "wof:name":"Whats Vanilla Pty Ltd",
    "wof:placetype":"venue"
},
  "geometry": {"coordinates":[144.99137878400001,-37.8395042419],"type":"Point"}
}