{
  "type": "Feature",
  "properties": {
    "iso:country":"AU",
    "sg:address":"Factory 3 49 Randall St",
    "sg:city":"Slacks Creek",
    "sg:classifiers":[
        {
            "category":"Manufacturing",
            "subcategory":"Building Materials",
            "type":"Manufacturing & Wholesale Goods"
        }
    ],
    "sg:phone":"+61 7 3209 3566",
    "sg:postcode":"4127",
    "sg:province":"QLD",
    "sg:tags":[
        "concrete",
        "product"
    ],
    "wof:name":"Qld Concrete Sealants Pty Ltd",
    "wof:placetype":"venue"
},
  "geometry": {"coordinates":[153.12254333499999,-27.6248703003],"type":"Point"}
}