{
  "type": "Feature",
  "properties": {
    "addr:full":"PO Box 115 Aldgate SA 5154",
    "addr:postcode":"5154",
    "iso:country":"AU",
    "sg:address":"PO Box 115",
    "sg:city":"Aldgate",
    "sg:classifiers":[
        {
            "category":"Shopping",
            "subcategory":"Jewelry",
            "type":"Retail Goods"
        }
    ],
    "sg:phone":"+61 8 8388 5413",
    "sg:postcode":"5154",
    "sg:province":"SA",
    "sg:tags":[
        "fashion",
        "jewellery"
    ],
    "wof:name":"Libertine Streetlook",
    "wof:placetype":"venue"
},
  "geometry": {"coordinates":[138.73538207999999,-35.016040802],"type":"Point"}
}