{
  "type": "Feature",
  "properties": {
    "addr:full":"Specialist Centre 2166 Logan Rd Mt Gravatt QLD 4122",
    "addr:housenumber":"2166",
    "addr:postcode":"4122",
    "addr:street":"Logan Rd",
    "iso:country":"AU",
    "sg:address":"Specialist Centre 2166 Logan Rd",
    "sg:city":"Mt Gravatt",
    "sg:classifiers":[
        {
            "category":"Health Services",
            "subcategory":"Doctor",
            "type":"Services"
        }
    ],
    "sg:phone":"+61 7 3847 8848",
    "sg:postcode":"4122",
    "sg:province":"QLD",
    "sg:tags":[
        "medical",
        "practitioner"
    ],
    "wof:name":"Hockings Gregory I",
    "wof:placetype":"venue"
},
  "geometry": {"coordinates":[153.085494995,-27.5625171661],"type":"Point"}
}