{
  "type": "Feature",
  "properties": {
    "addr:full":"74 Fitzgerald St Portland VIC 3305",
    "addr:housenumber":"74",
    "addr:postcode":"3305",
    "addr:street":"Fitzgerald St",
    "iso:country":"AU",
    "sg:address":"74 Fitzgerald St",
    "sg:city":"Portland",
    "sg:classifiers":[
        {
            "category":"Building & Trades",
            "subcategory":"Construction",
            "type":"Services"
        }
    ],
    "sg:phone":"+61 3 5521 8055",
    "sg:postcode":"3305",
    "sg:province":"VIC",
    "sg:tags":[
        "welding"
    ],
    "wof:name":"Robertson G F & B J Plumbing Contractors Pty Ltd",
    "wof:placetype":"venue"
},
  "geometry": {"coordinates":[141.590133667,-38.3330688477],"type":"Point"}
}