{
  "type": "Feature",
  "properties": {
    "iso:country":"AU",
    "sg:address":"78 Hope St",
    "sg:city":"Seaforth",
    "sg:classifiers":[
        {
            "category":"Shopping",
            "subcategory":"Computers & Home Electronics",
            "type":"Retail Goods"
        }
    ],
    "sg:phone":"+61 2 9907 6289",
    "sg:postcode":"2092",
    "sg:province":"NSW",
    "sg:tags":[
        "hardware",
        "equipment"
    ],
    "wof:name":"Magtron Monitors (Australia) Pty Ltd",
    "wof:placetype":"venue"
},
  "geometry": {"coordinates":[151.25289917000001,-33.7934150696],"type":"Point"}
}