{
  "type": "Feature",
  "properties": {
    "iso:country":"AU",
    "sg:address":"32 High St",
    "sg:city":"Boonah",
    "sg:classifiers":[
        {
            "category":"Travel",
            "subcategory":"Hotels & Motels",
            "type":"Entertainment"
        }
    ],
    "sg:phone":"+61 7 5463 1444",
    "sg:postcode":"4310",
    "sg:province":"QLD",
    "sg:tags":[
        "accommodation"
    ],
    "wof:name":"Australian Hotel",
    "wof:placetype":"venue"
},
  "geometry": {"coordinates":[152.68228149399999,-27.9979801178],"type":"Point"}
}