{
  "type": "Feature",
  "properties": {
    "addr:full":"16 Redfern St Wetherill Park NSW 2164",
    "addr:housenumber":"16",
    "addr:postcode":"2164",
    "addr:street":"Redfern St",
    "iso:country":"AU",
    "sg:address":"16 Redfern St",
    "sg:city":"Wetherill Park",
    "sg:classifiers":[
        {
            "category":"Retail",
            "subcategory":"Car Wash",
            "type":"Services"
        }
    ],
    "sg:phone":"+61 2 9604 9133",
    "sg:postcode":"2164",
    "sg:province":"NSW",
    "sg:tags":[
        "merchant",
        "oil",
        "refiner"
    ],
    "wof:name":"Global Oil",
    "wof:placetype":"venue"
},
  "geometry": {"coordinates":[150.91140747099999,-33.8436851501],"type":"Point"}
}