{
  "type": "Feature",
  "properties": {
    "addr:full":"L 2 Melbourne VIC 3000",
    "addr:postcode":"3000",
    "iso:country":"AU",
    "sg:address":"L 2",
    "sg:city":"Melbourne",
    "sg:classifiers":[
        {
            "category":"Cafe",
            "type":"Food & Drink"
        }
    ],
    "sg:phone":"+61 3 9620 3222",
    "sg:postcode":"3000",
    "sg:province":"VIC",
    "wof:name":"Cafe Bocadillo On King Street",
    "wof:placetype":"venue"
},
  "geometry": {"coordinates":[144.96862793,-37.8136253357],"type":"Point"}
}