{
  "type": "Feature",
  "properties": {
    "iso:country":"AU",
    "sg:address":"1 Lilian St",
    "sg:city":"Upwey",
    "sg:classifiers":[
        {
            "category":"Building & Trades",
            "subcategory":"Construction",
            "type":"Services"
        }
    ],
    "sg:phone":"+61 3 9761 4412",
    "sg:postcode":"3158",
    "sg:province":"VIC",
    "sg:tags":[
        "industrial",
        "commercial",
        "air conditioning"
    ],
    "wof:name":"Mainline Mechanical Services",
    "wof:placetype":"venue"
},
  "geometry": {"coordinates":[145.33192443900001,-37.9124031067],"type":"Point"}
}