{
  "type": "Feature",
  "properties": {
    "iso:country":"AU",
    "sg:address":"2 Avoca St",
    "sg:city":"Brunswick East",
    "sg:classifiers":[
        {
            "category":"Manufacturing",
            "subcategory":"Textiles",
            "type":"Manufacturing & Wholesale Goods"
        }
    ],
    "sg:phone":"+61 3 9383 2268",
    "sg:postcode":"3057",
    "sg:province":"VIC",
    "sg:tags":[
        "wholesaler",
        "knitwear",
        "mfrs"
    ],
    "wof:name":"Evergreen Knitwear Pty Ltd",
    "wof:placetype":"venue"
},
  "geometry": {"coordinates":[144.974121094,-37.7571144104],"type":"Point"}
}