{
  "type": "Feature",
  "properties": {
    "iso:country":"AU",
    "sg:address":"Unit 6 126 Bannister Rd",
    "sg:city":"Canning Vale",
    "sg:classifiers":[
        {
            "category":"Retail",
            "subcategory":"Storage",
            "type":"Services"
        }
    ],
    "sg:phone":"+61 8 9456 1778",
    "sg:postcode":"6155",
    "sg:province":"WA",
    "sg:tags":[
        "removal",
        "furniture"
    ],
    "wof:name":"One Stop Moving Shop",
    "wof:placetype":"venue"
},
  "geometry": {"coordinates":[115.91690800000001,-32.057964],"type":"Point"}
}