{
  "type": "Feature",
  "properties": {
    "addr:full":"Cardiolab 91 Flemington Rd North Melbourne VIC 3051",
    "addr:housenumber":"91",
    "addr:postcode":"3051",
    "addr:street":"Cardiolab;Flemington Rd",
    "iso:country":"AU",
    "sg:address":"Cardiolab 91 Flemington Rd",
    "sg:city":"North Melbourne",
    "sg:classifiers":[
        {
            "category":"Health Services",
            "subcategory":"Doctor",
            "type":"Services"
        }
    ],
    "sg:phone":"+61 3 9328 2588",
    "sg:postcode":"3051",
    "sg:province":"VIC",
    "sg:tags":[
        "medical",
        "practitioner"
    ],
    "wof:name":"Goh T H Dr",
    "wof:placetype":"venue"
},
  "geometry": {"coordinates":[144.953033447,-37.7984695435],"type":"Point"}
}