{
  "type": "Feature",
  "properties": {
    "iso:country":"AU",
    "sg:address":"Level 8, Westfield Tower Marion, 297 Diagonal Rd",
    "sg:city":"Oaklands Park",
    "sg:classifiers":[
        {
            "category":"Health Services",
            "subcategory":"Doctor",
            "type":"Services"
        }
    ],
    "sg:phone":"+61 8 8298 1133",
    "sg:postcode":"5046",
    "sg:province":"SA",
    "sg:tags":[
        "podiatrist"
    ],
    "wof:name":"Dobie Valerie C",
    "wof:placetype":"venue"
},
  "geometry": {"coordinates":[138.547745,-35.015984],"type":"Point"}
}