{
  "type": "Feature",
  "properties": {
    "iso:country":"AU",
    "sg:address":"17 Broadmoor St",
    "sg:city":"Kenmore Hills",
    "sg:classifiers":[
        {
            "category":"Wholesale",
            "subcategory":"Construction Materials",
            "type":"Manufacturing & Wholesale Goods"
        }
    ],
    "sg:phone":"+61 7 3374 4944",
    "sg:postcode":"4069",
    "sg:province":"QLD",
    "sg:tags":[
        "lift"
    ],
    "wof:name":"GPA Facility Management",
    "wof:placetype":"venue"
},
  "geometry": {"coordinates":[152.91737365700001,-27.5020866394],"type":"Point"}
}