{
  "type": "Feature",
  "properties": {
    "iso:country":"AU",
    "sg:address":"189 Princes Hwy",
    "sg:city":"Albion Park Rail",
    "sg:classifiers":[
        {
            "category":"Personal",
            "subcategory":"Beauty Salon",
            "type":"Services"
        }
    ],
    "sg:phone":"+61 2 4256 1480",
    "sg:postcode":"2527",
    "sg:province":"NSW",
    "sg:tags":[
        "hairdresser"
    ],
    "wof:name":"Cuts &#039;N&#039; Curls At Leasas &#039;N&#039; Kylies",
    "wof:placetype":"venue"
},
  "geometry": {"coordinates":[150.800216675,-34.5655021667],"type":"Point"}
}