{
  "type": "Feature",
  "properties": {
    "addr:full":"186 Lambton Rd New Lambton NSW 2305",
    "addr:housenumber":"186",
    "addr:postcode":"2305",
    "addr:street":"Lambton Rd",
    "iso:country":"AU",
    "sg:address":"186 Lambton Rd",
    "sg:city":"New Lambton",
    "sg:classifiers":[
        {
            "category":"Health Services",
            "subcategory":"Health Practitioner",
            "type":"Services"
        }
    ],
    "sg:phone":"+61 2 4957 0207",
    "sg:postcode":"2305",
    "sg:province":"NSW",
    "sg:tags":[
        "physiotherapist"
    ],
    "wof:name":"Chiropractic Plus",
    "wof:placetype":"venue"
},
  "geometry": {"coordinates":[151.72015400000001,-32.922649],"type":"Point"}
}