{
  "type": "Feature",
  "properties": {
    "iso:country":"AU",
    "sg:address":"1 Nalya Rd",
    "sg:city":"Berowra Heights",
    "sg:classifiers":[
        {
            "category":"Professional",
            "subcategory":"Computer Services",
            "type":"Services"
        }
    ],
    "sg:phone":"+61 2 9456 1245",
    "sg:postcode":"2082",
    "sg:province":"NSW",
    "sg:tags":[
        "consultant",
        "system"
    ],
    "wof:name":"Emvale Pty Ltd",
    "wof:placetype":"venue"
},
  "geometry": {"coordinates":[151.135498047,-33.6075286865],"type":"Point"}
}