{
  "type": "Feature",
  "properties": {
    "iso:country":"AU",
    "sg:address":"1/ 316 Sturt St",
    "sg:city":"Townsville",
    "sg:classifiers":[
        {
            "category":"Banks & Credit Unions",
            "subcategory":"Bank",
            "type":"Services"
        }
    ],
    "sg:phone":"+61 7 4721 5266",
    "sg:postcode":"4810",
    "sg:province":"QLD",
    "sg:tags":[
        "broker",
        "mortgage"
    ],
    "wof:name":"Packer Ryder Home Loan Services",
    "wof:placetype":"venue"
},
  "geometry": {"coordinates":[146.81304900000001,-19.262735],"type":"Point"}
}