{
  "type": "Feature",
  "properties": {
    "addr:full":"56c Patrick St Dalby QLD 4405",
    "addr:housenumber":"56c",
    "addr:postcode":"4405",
    "addr:street":"Patrick St",
    "iso:country":"AU",
    "sg:address":"56c Patrick St",
    "sg:city":"Dalby",
    "sg:classifiers":[
        {
            "category":"Shopping",
            "subcategory":"Jewelry",
            "type":"Retail Goods"
        }
    ],
    "sg:phone":"+61 7 4669 6888",
    "sg:postcode":"4405",
    "sg:province":"QLD",
    "sg:tags":[
        "jeweller"
    ],
    "wof:name":"Bead Studio",
    "wof:placetype":"venue"
},
  "geometry": {"coordinates":[151.262374878,-27.1774349213],"type":"Point"}
}