{
  "type": "Feature",
  "properties": {
    "addr:full":"9 Edward St Bendigo VIC 3550",
    "addr:housenumber":"9",
    "addr:postcode":"3550",
    "addr:street":"Edward St",
    "iso:country":"AU",
    "sg:address":"9 Edward St",
    "sg:city":"Bendigo",
    "sg:classifiers":[
        {
            "category":"Shopping",
            "subcategory":"Stationery & Office Supplies",
            "type":"Retail Goods"
        }
    ],
    "sg:phone":"+61 3 5443 9366",
    "sg:postcode":"3550",
    "sg:province":"VIC",
    "sg:tags":[
        "equipment",
        "display",
        "exhibition"
    ],
    "wof:name":"Sign A Rama",
    "wof:placetype":"venue"
},
  "geometry": {"coordinates":[144.27999877900001,-36.7639808655],"type":"Point"}
}