{
  "type": "Feature",
  "properties": {
    "addr:full":"3r Tinks La Dubbo NSW 2830",
    "addr:postcode":"2830",
    "addr:street":"Tinks La",
    "iso:country":"AU",
    "sg:address":"3r Tinks La",
    "sg:city":"Dubbo",
    "sg:classifiers":[
        {
            "category":"Food & Beverages",
            "subcategory":"Farmers Market",
            "type":"Retail Goods"
        }
    ],
    "sg:phone":"+61 2 6884 9778",
    "sg:postcode":"2830",
    "sg:province":"NSW",
    "sg:tags":[
        "beekeeper"
    ],
    "wof:name":"Ashfield W",
    "wof:placetype":"venue"
},
  "geometry": {"coordinates":[148.61256408700001,-32.2663536072],"type":"Point"}
}