{
  "type": "Feature",
  "properties": {
    "iso:country":"AU",
    "sg:address":"Shp 8/ 28 Lamont St",
    "sg:city":"Bermagui",
    "sg:classifiers":[
        {
            "category":"Professional",
            "subcategory":"Accounting & Tax Preparation",
            "type":"Services"
        }
    ],
    "sg:phone":"+61 2 6493 3900",
    "sg:postcode":"2546",
    "sg:province":"NSW",
    "sg:tags":[
        "accountant",
        "auditor"
    ],
    "wof:name":"Gilchrist & Assoc. Pty Ltd",
    "wof:placetype":"venue"
},
  "geometry": {"coordinates":[150.077590942,-36.4268531799],"type":"Point"}
}