{
  "type": "Feature",
  "properties": {
    "addr:full":"PO Box 241 Zillmere QLD 4034",
    "addr:postcode":"4034",
    "iso:country":"AU",
    "sg:address":"PO Box 241",
    "sg:city":"Zillmere",
    "sg:classifiers":[
        {
            "category":"Retail",
            "subcategory":"Driving School",
            "type":"Services"
        }
    ],
    "sg:phone":"+61 7 3865 2044",
    "sg:postcode":"4034",
    "sg:province":"QLD",
    "sg:tags":[
        "defensive",
        "advanced"
    ],
    "wof:name":"Advanced Defensive And 4WD Centre Australia",
    "wof:placetype":"venue"
},
  "geometry": {"coordinates":[153.03808599999999,-27.360001],"type":"Point"}
}