{
  "type": "Feature",
  "properties": {
    "addr:full":"73 Latrobe Rd Morwell VIC 3840",
    "addr:housenumber":"73",
    "addr:postcode":"3840",
    "addr:street":"Latrobe Rd",
    "iso:country":"AU",
    "sg:address":"73 Latrobe Rd",
    "sg:city":"Morwell",
    "sg:classifiers":[
        {
            "category":"Retail",
            "subcategory":"Auto Repair",
            "type":"Services"
        }
    ],
    "sg:phone":"+61 3 5134 2244",
    "sg:postcode":"3840",
    "sg:province":"VIC",
    "sg:tags":[
        "beater",
        "painter",
        "panel"
    ],
    "wof:name":"Morwell Panel Works",
    "wof:placetype":"venue"
},
  "geometry": {"coordinates":[146.39569091800001,-38.2291145325],"type":"Point"}
}