{
  "type": "Feature",
  "properties": {
    "addr:full":"Bulmans Rd Melton VIC 3337",
    "addr:postcode":"3337",
    "addr:street":"Bulmans Rd",
    "iso:country":"AU",
    "sg:address":"Bulmans Rd",
    "sg:city":"Melton",
    "sg:classifiers":[
        {
            "category":"Education",
            "subcategory":"School",
            "type":"Public Place"
        }
    ],
    "sg:phone":"+61 3 9743 6522",
    "sg:postcode":"3337",
    "sg:province":"VIC",
    "sg:tags":[
        "co-educational"
    ],
    "wof:name":"Catholic Regional College Melton",
    "wof:placetype":"venue"
},
  "geometry": {"coordinates":[144.55072000000001,-37.679279],"type":"Point"}
}