{
  "type": "Feature",
  "properties": {
    "iso:country":"AU",
    "sg:address":"139 Gregory St",
    "sg:city":"Auchenflower",
    "sg:classifiers":[
        {
            "category":"Real Estate",
            "subcategory":"Architect",
            "type":"Services"
        }
    ],
    "sg:phone":"+61 7 3371 9965",
    "sg:postcode":"4066",
    "sg:province":"QLD",
    "wof:name":"Curtis G W",
    "wof:placetype":"venue"
},
  "geometry": {"coordinates":[152.98916625999999,-27.4712696075],"type":"Point"}
}