{
  "type": "Feature",
  "properties": {
    "addr:full":"11 Beaulieu Crs Carindale QLD 4152",
    "addr:housenumber":"11",
    "addr:postcode":"4152",
    "addr:street":"Beaulieu Crs",
    "iso:country":"AU",
    "sg:address":"11 Beaulieu Crs",
    "sg:city":"Carindale",
    "sg:classifiers":[
        {
            "category":"Building & Trades",
            "subcategory":"Construction",
            "type":"Services"
        }
    ],
    "sg:phone":"+61 412 031 465",
    "sg:postcode":"4152",
    "sg:province":"QLD",
    "sg:tags":[
        "stonework",
        "stone",
        "mason"
    ],
    "wof:name":"Marmaro Art",
    "wof:placetype":"venue"
},
  "geometry": {"coordinates":[153.102005005,-27.5056304932],"type":"Point"}
}