{
  "type": "Feature",
  "properties": {
    "addr:full":"6 Abbott Rd Hallam VIC 3803",
    "addr:housenumber":"6",
    "addr:postcode":"3803",
    "addr:street":"Abbott Rd",
    "iso:country":"AU",
    "sg:address":"6 Abbott Rd",
    "sg:city":"Hallam",
    "sg:classifiers":[
        {
            "category":"Utilities",
            "type":"Services"
        }
    ],
    "sg:phone":"+61 3 9796 3222",
    "sg:postcode":"3803",
    "sg:province":"VIC",
    "sg:tags":[
        "equipment",
        "towing"
    ],
    "wof:name":"Bartlett",
    "wof:placetype":"venue"
},
  "geometry": {"coordinates":[145.27180480999999,-38.0101966858],"type":"Point"}
}