{
  "type": "Feature",
  "properties": {
    "addr:full":"215 George St Liverpool NSW 2170",
    "addr:housenumber":"215",
    "addr:postcode":"2170",
    "addr:street":"George St",
    "iso:country":"AU",
    "sg:address":"215 George St",
    "sg:city":"Liverpool",
    "sg:classifiers":[
        {
            "category":"Banks & Credit Unions",
            "subcategory":"Financial Services",
            "type":"Services"
        }
    ],
    "sg:phone":"+61 2 9824 1977",
    "sg:postcode":"2170",
    "sg:province":"NSW",
    "sg:tags":[
        "loan",
        "finance",
        "mortgage"
    ],
    "wof:name":"Mortgage House Liverpool",
    "wof:placetype":"venue"
},
  "geometry": {"coordinates":[150.92451477,-33.9239006042],"type":"Point"}
}