{
  "type": "Feature",
  "properties": {
    "iso:country":"AU",
    "sg:address":"445 Brighton Rd",
    "sg:city":"Brighton",
    "sg:classifiers":[
        {
            "category":"Food & Beverages",
            "subcategory":"Specialty",
            "type":"Retail Goods"
        }
    ],
    "sg:phone":"+61 8 8377 0919",
    "sg:postcode":"5048",
    "sg:province":"SA",
    "sg:tags":[
        "product",
        "health"
    ],
    "wof:name":"Happy Health",
    "wof:placetype":"venue"
},
  "geometry": {"coordinates":[138.52323899999999,-35.021801],"type":"Point"}
}