{
  "type": "Feature",
  "properties": {
    "addr:full":"233 Pitt St Merrylands NSW 2160",
    "addr:housenumber":"233",
    "addr:postcode":"2160",
    "addr:street":"Pitt St",
    "iso:country":"AU",
    "sg:address":"233 Pitt St",
    "sg:city":"Merrylands",
    "sg:classifiers":[
        {
            "category":"Shopping",
            "subcategory":"Pawn Shop",
            "type":"Retail Goods"
        }
    ],
    "sg:phone":"+61 2 9637 7253",
    "sg:postcode":"2160",
    "sg:province":"NSW",
    "sg:tags":[
        "pawnbroker"
    ],
    "wof:name":"Merrylands Loan Office",
    "wof:placetype":"venue"
},
  "geometry": {"coordinates":[150.991363525,-33.8359947205],"type":"Point"}
}