{
  "type": "Feature",
  "properties": {
    "iso:country":"AU",
    "sg:address":"35 Elizabeth Cook Drv",
    "sg:city":"Rankin Park",
    "sg:classifiers":[
        {
            "category":"Personal",
            "subcategory":"Massage",
            "type":"Services"
        }
    ],
    "sg:phone":"+61 2 4951 2443",
    "sg:postcode":"2287",
    "sg:province":"NSW",
    "sg:tags":[
        "therapy"
    ],
    "wof:name":"Bodyworks Massage Clinic",
    "wof:placetype":"venue"
},
  "geometry": {"coordinates":[151.675292969,-32.9247360229],"type":"Point"}
}