{
  "type": "Feature",
  "properties": {
    "iso:country":"AU",
    "sg:address":"PO Box 544",
    "sg:city":"Wamberal",
    "sg:classifiers":[
        {
            "category":"Education",
            "subcategory":"Special Training",
            "type":"Public Place"
        }
    ],
    "sg:phone":"+61 2 4385 5930",
    "sg:postcode":"2260",
    "sg:province":"NSW",
    "sg:tags":[
        "development"
    ],
    "wof:name":"The Games Arena",
    "wof:placetype":"venue"
},
  "geometry": {"coordinates":[151.443146,-33.418209],"type":"Point"}
}