{
  "type": "Feature",
  "properties": {
    "addr:full":"17 Ramsden St Carina QLD 4152",
    "addr:housenumber":"17",
    "addr:postcode":"4152",
    "addr:street":"Ramsden St",
    "iso:country":"AU",
    "sg:address":"17 Ramsden St",
    "sg:city":"Carina",
    "sg:classifiers":[
        {
            "category":"Wholesale",
            "subcategory":"Medical Equipment & Supplies",
            "type":"Manufacturing & Wholesale Goods"
        }
    ],
    "sg:phone":"+61 7 3398 1188",
    "sg:postcode":"4152",
    "sg:province":"QLD",
    "sg:tags":[
        "dental"
    ],
    "wof:name":"Avant-Garde Dental Interiors",
    "wof:placetype":"venue"
},
  "geometry": {"coordinates":[153.09640502900001,-27.4865550995],"type":"Point"}
}