{
  "type": "Feature",
  "properties": {
    "addr:full":"3 Nullum St Murwillumbah NSW 2484",
    "addr:housenumber":"3",
    "addr:postcode":"2484",
    "addr:street":"Nullum St",
    "iso:country":"AU",
    "sg:address":"3 Nullum St",
    "sg:city":"Murwillumbah",
    "sg:classifiers":[
        {
            "category":"Education",
            "subcategory":"Special Training",
            "type":"Public Place"
        }
    ],
    "sg:phone":"+61 2 6672 5549",
    "sg:postcode":"2484",
    "sg:province":"NSW",
    "sg:tags":[
        "development"
    ],
    "wof:name":"Tweed Training & Enterprise Co Ltd",
    "wof:placetype":"venue"
},
  "geometry": {"coordinates":[153.393432617,-28.3268566132],"type":"Point"}
}