{
  "type": "Feature",
  "properties": {
    "addr:full":"Cnr Flemington & Racecourse Rds North Melbourne VIC 3051",
    "addr:postcode":"3051",
    "addr:street":"Cnr",
    "iso:country":"AU",
    "sg:address":"Cnr Flemington & Racecourse Rds",
    "sg:city":"North Melbourne",
    "sg:classifiers":[
        {
            "category":"Utilities",
            "subcategory":"Telephone",
            "type":"Services"
        }
    ],
    "sg:phone":"+61 3 9326 9499",
    "sg:postcode":"3051",
    "sg:province":"VIC",
    "sg:tags":[
        "equipment",
        "system"
    ],
    "wof:name":"Polaris Communications Pty Ltd",
    "wof:placetype":"venue"
},
  "geometry": {"coordinates":[144.94920349099999,-37.7951087952],"type":"Point"}
}