{
  "type": "Feature",
  "properties": {
    "iso:country":"AU",
    "sg:address":"117 Gipps St",
    "sg:city":"Fortitude Valley",
    "sg:classifiers":[
        {
            "category":"Government",
            "subcategory":"Court House",
            "type":"Public Place"
        }
    ],
    "sg:phone":"+61 7 3250 1900",
    "sg:postcode":"4006",
    "sg:province":"QLD",
    "sg:tags":[
        "personal",
        "marriage",
        "family",
        "counselling"
    ],
    "wof:name":"Lifeline Brisbane",
    "wof:placetype":"venue"
},
  "geometry": {"coordinates":[153.031524658,-27.4581890106],"type":"Point"}
}