{
  "type": "Feature",
  "properties": {
    "addr:full":"29 Phillip St Parramatta NSW 2150",
    "addr:housenumber":"29",
    "addr:postcode":"2150",
    "addr:street":"Phillip St",
    "iso:country":"AU",
    "sg:address":"29 Phillip St",
    "sg:city":"Parramatta",
    "sg:classifiers":[
        {
            "category":"Personal",
            "subcategory":"Beauty Salon",
            "type":"Services"
        }
    ],
    "sg:phone":"+61 2 9635 5698",
    "sg:postcode":"2150",
    "sg:province":"NSW",
    "sg:tags":[
        "hairdresser"
    ],
    "wof:name":"Sheik Snip",
    "wof:placetype":"venue"
},
  "geometry": {"coordinates":[151.023071289,-33.7949562073],"type":"Point"}
}