{
  "type": "Feature",
  "properties": {
    "addr:full":"Level 1/ 1 Cecil Pl Prahran VIC 3181",
    "addr:housenumber":"/ 1",
    "addr:postcode":"3181",
    "addr:street":"Cecil Pl",
    "iso:country":"AU",
    "sg:address":"Level 1/ 1 Cecil Pl",
    "sg:city":"Prahran",
    "sg:classifiers":[
        {
            "category":"Professional",
            "subcategory":"Art Services",
            "type":"Services"
        }
    ],
    "sg:phone":"+61 3 9529 3888",
    "sg:postcode":"3181",
    "sg:province":"VIC",
    "sg:tags":[
        "graphic",
        "designer"
    ],
    "wof:name":"Grid Creative",
    "wof:placetype":"venue"
},
  "geometry": {"coordinates":[144.99395751899999,-37.8502998352],"type":"Point"}
}