{
  "type": "Feature",
  "properties": {
    "iso:country":"AU",
    "sg:address":"Kime Rd",
    "sg:city":"Mt Thorley",
    "sg:classifiers":[
        {
            "category":"Professional",
            "type":"Services"
        }
    ],
    "sg:phone":"+61 2 6574 6644",
    "sg:postcode":"2330",
    "sg:province":"NSW",
    "sg:tags":[
        "transport"
    ],
    "wof:name":"Boral Transport Limited",
    "wof:placetype":"venue"
},
  "geometry": {"coordinates":[151.12591599999999,-32.62429],"type":"Point"}
}