{
  "type": "Feature",
  "properties": {
    "addr:full":"73A Spofforth St Cremorne NSW 2090",
    "addr:housenumber":"73a",
    "addr:postcode":"2090",
    "addr:street":"Spofforth St",
    "iso:country":"AU",
    "sg:address":"73A Spofforth St",
    "sg:city":"Cremorne",
    "sg:classifiers":[
        {
            "category":"Retail",
            "subcategory":"Veterinary Services",
            "type":"Services"
        }
    ],
    "sg:phone":"+61 2 9953 1090",
    "sg:postcode":"2090",
    "sg:province":"NSW",
    "sg:tags":[
        "surgeon"
    ],
    "wof:name":"Waugh Tony",
    "wof:placetype":"venue"
},
  "geometry": {"coordinates":[151.23025512699999,-33.8293991089],"type":"Point"}
}