{
  "type": "Feature",
  "properties": {
    "addr:full":"1 Morley Ave Kingswood NSW 2747",
    "addr:housenumber":"1",
    "addr:postcode":"2747",
    "addr:street":"Morley Ave",
    "iso:country":"AU",
    "sg:address":"1 Morley Ave",
    "sg:city":"Kingswood",
    "sg:classifiers":[
        {
            "category":"Autos & Motor Vehicles",
            "subcategory":"Automobile Sales",
            "type":"Retail Goods"
        }
    ],
    "sg:phone":"+61 2 4736 6805",
    "sg:postcode":"2747",
    "sg:province":"NSW",
    "sg:tags":[
        "car",
        "used"
    ],
    "wof:name":"Nepean Wholesale Cars",
    "wof:placetype":"venue"
},
  "geometry": {"coordinates":[150.72651672399999,-33.7592468262],"type":"Point"}
}