{
  "type": "Feature",
  "properties": {
    "addr:full":"Pialba Place Shopping Centre Main St Pialba QLD 4655",
    "addr:postcode":"4655",
    "addr:street":"Pialba;Main St",
    "iso:country":"AU",
    "sg:address":"Pialba Place Shopping Centre Main St",
    "sg:city":"Pialba",
    "sg:classifiers":[
        {
            "category":"Shopping",
            "subcategory":"Clothing, Apparel, & Fashions",
            "type":"Retail Goods"
        }
    ],
    "sg:phone":"+61 7 4124 1123",
    "sg:postcode":"4655",
    "sg:province":"QLD",
    "sg:tags":[
        "hire",
        "men's",
        "wear",
        "formal"
    ],
    "wof:name":"K-Cees Menswear",
    "wof:placetype":"venue"
},
  "geometry": {"coordinates":[152.83824200000001,-25.287683],"type":"Point"}
}