{
  "type": "Feature",
  "properties": {
    "addr:full":"Cnr Ocean St & Duporth Ave Maroochydore QLD 4558",
    "addr:postcode":"4558",
    "addr:street":"Cnr Ocean St & Duporth Ave",
    "iso:country":"AU",
    "sg:address":"Cnr Ocean St & Duporth Ave",
    "sg:city":"Maroochydore",
    "sg:classifiers":[
        {
            "category":"Real Estate",
            "subcategory":"Real Estate Agent",
            "type":"Services"
        }
    ],
    "sg:phone":"+61 7 5443 5899",
    "sg:postcode":"4558",
    "sg:province":"QLD",
    "wof:name":"Ray White Commercial",
    "wof:placetype":"venue"
},
  "geometry": {"coordinates":[153.09083557100001,-26.6521549225],"type":"Point"}
}