{
  "type": "Feature",
  "properties": {
    "addr:full":"16 Larwood St Upper Mt Gravatt QLD 4122",
    "addr:housenumber":"16",
    "addr:postcode":"4122",
    "addr:street":"Larwood St",
    "iso:country":"AU",
    "sg:address":"16 Larwood St",
    "sg:city":"Upper Mt Gravatt",
    "sg:classifiers":[
        {
            "category":"Education",
            "subcategory":"Special Training",
            "type":"Public Place"
        }
    ],
    "sg:phone":"+61 7 3349 2855",
    "sg:postcode":"4122",
    "sg:province":"QLD",
    "sg:tags":[
        "development"
    ],
    "wof:name":"Holland P A & Associates",
    "wof:placetype":"venue"
},
  "geometry": {"coordinates":[153.074310303,-27.5561141968],"type":"Point"}
}