{
  "type": "Feature",
  "properties": {
    "addr:full":"Wentworth Rd Denmark WA 6333",
    "addr:postcode":"6333",
    "addr:street":"Wentworth Rd",
    "iso:country":"AU",
    "sg:address":"Wentworth Rd",
    "sg:city":"Denmark",
    "sg:classifiers":[
        {
            "category":"Farming",
            "subcategory":"Vineyard",
            "type":"Manufacturing & Wholesale Goods"
        }
    ],
    "sg:phone":"+61 8 9840 9353",
    "sg:postcode":"6333",
    "sg:province":"WA",
    "sg:tags":[
        "winery"
    ],
    "wof:name":"Monkey Rock Winery",
    "wof:placetype":"venue"
},
  "geometry": {"coordinates":[117.25765991199999,-34.9856491089],"type":"Point"}
}