{
  "type": "Feature",
  "properties": {
    "iso:country":"AU",
    "sg:address":"7 Maryborough St",
    "sg:city":"Bundaberg",
    "sg:classifiers":[
        {
            "category":"Organizations",
            "subcategory":"Professional Association",
            "type":"Services"
        }
    ],
    "sg:phone":"+61 7 4151 7755",
    "sg:postcode":"4670",
    "sg:province":"QLD",
    "sg:tags":[
        "organisation",
        "business"
    ],
    "wof:name":"Bundaberg Mediation Services",
    "wof:placetype":"venue"
},
  "geometry": {"coordinates":[152.34657287600001,-24.8670825958],"type":"Point"}
}