{
  "type": "Feature",
  "properties": {
    "iso:country":"AU",
    "sg:address":"4 Glenfield Pl",
    "sg:city":"Mt Nasura",
    "sg:classifiers":[
        {
            "category":"Home & Garden",
            "subcategory":"Building Materials",
            "type":"Retail Goods"
        }
    ],
    "sg:phone":"+61 8 9390 8988",
    "sg:postcode":"6112",
    "sg:province":"WA",
    "sg:tags":[
        "lawn",
        "cutting",
        "maintenance"
    ],
    "wof:name":"Glenfield Turf Maintenance",
    "wof:placetype":"venue"
},
  "geometry": {"coordinates":[116.02146911600001,-32.1272239685],"type":"Point"}
}