{
  "type": "Feature",
  "properties": {
    "addr:full":"113 Leopold St South Yarra VIC 3141",
    "addr:housenumber":"113",
    "addr:postcode":"3141",
    "addr:street":"Leopold St",
    "iso:country":"AU",
    "sg:address":"113 Leopold St",
    "sg:city":"South Yarra",
    "sg:classifiers":[
        {
            "category":"Health Services",
            "subcategory":"Doctor",
            "type":"Services"
        }
    ],
    "sg:phone":"+61 3 9867 5369",
    "sg:postcode":"3141",
    "sg:province":"VIC",
    "sg:tags":[
        "medical",
        "practitioner"
    ],
    "wof:name":"Jeuniewic N",
    "wof:placetype":"venue"
},
  "geometry": {"coordinates":[144.98298645,-37.8351554871],"type":"Point"}
}