{
  "type": "Feature",
  "properties": {
    "addr:full":"Suite 7, 72-74 Church St Brighton Brighton VIC 3186",
    "addr:housenumber":"72-74",
    "addr:postcode":"3186",
    "addr:street":"Church St",
    "iso:country":"AU",
    "sg:address":"Suite 7, 72-74 Church St",
    "sg:city":"Brighton Brighton",
    "sg:classifiers":[
        {
            "category":"Health Services",
            "subcategory":"Health Practitioner",
            "type":"Services"
        }
    ],
    "sg:phone":"+61 3 9593 1239",
    "sg:postcode":"3186",
    "sg:province":"VIC",
    "sg:tags":[
        "pathologist",
        "speech"
    ],
    "wof:name":"Sharon Vaughan",
    "wof:placetype":"venue"
},
  "geometry": {"coordinates":[144.99502563499999,-37.9146156311],"type":"Point"}
}