{
  "type": "Feature",
  "properties": {
    "addr:full":"1/11 Wrights Pl Labrador QLD 4215",
    "addr:housenumber":"/ 11",
    "addr:postcode":"4215",
    "addr:street":"Wrights Pl",
    "iso:country":"AU",
    "sg:address":"1/11 Wrights Pl",
    "sg:city":"Labrador",
    "sg:classifiers":[
        {
            "category":"Manufacturing",
            "subcategory":"Glass & Minerals",
            "type":"Manufacturing & Wholesale Goods"
        }
    ],
    "sg:phone":"+61 7 5563 8122",
    "sg:postcode":"4215",
    "sg:province":"QLD",
    "sg:tags":[
        "fabricator",
        "fibreglass"
    ],
    "wof:name":"Horizon Multihulls Pty Ltd",
    "wof:placetype":"venue"
},
  "geometry": {"coordinates":[153.381713867,-27.934627533],"type":"Point"}
}