{
  "type": "Feature",
  "properties": {
    "addr:full":"Walcha Rd Nowendoc NSW 2354",
    "addr:postcode":"2354",
    "addr:street":"Walcha Rd",
    "iso:country":"AU",
    "sg:address":"Walcha Rd",
    "sg:city":"Nowendoc",
    "sg:classifiers":[
        {
            "category":"Education",
            "subcategory":"School",
            "type":"Public Place"
        }
    ],
    "sg:phone":"+61 2 6777 0905",
    "sg:postcode":"2354",
    "sg:province":"NSW",
    "sg:tags":[
        "state",
        "-",
        "nsw"
    ],
    "wof:name":"Nowendoc Public School",
    "wof:placetype":"venue"
},
  "geometry": {"coordinates":[151.611938477,-31.439239502],"type":"Point"}
}