{
  "type": "Feature",
  "properties": {
    "addr:full":"160 Gilmore Rd Queanbeyan NSW 2620",
    "addr:housenumber":"160",
    "addr:postcode":"2620",
    "addr:street":"Gilmore Rd",
    "iso:country":"AU",
    "sg:address":"160 Gilmore Rd",
    "sg:city":"Queanbeyan",
    "sg:classifiers":[
        {
            "category":"Building & Trades",
            "subcategory":"Construction",
            "type":"Services"
        }
    ],
    "sg:phone":"+61 2 6297 2862",
    "sg:postcode":"2620",
    "sg:province":"NSW",
    "sg:tags":[
        "fencing",
        "contractor"
    ],
    "wof:name":"Gilmore Engineering",
    "wof:placetype":"venue"
},
  "geometry": {"coordinates":[149.207763672,-35.3521995544],"type":"Point"}
}