{
  "type": "Feature",
  "properties": {
    "addr:full":"28 Singleton Rd Point Clare NSW 2250",
    "addr:housenumber":"28",
    "addr:postcode":"2250",
    "addr:street":"Singleton Rd",
    "iso:country":"AU",
    "sg:address":"28 Singleton Rd",
    "sg:city":"Point Clare",
    "sg:classifiers":[
        {
            "category":"Personal",
            "subcategory":"Beauty Salon",
            "type":"Services"
        }
    ],
    "sg:phone":"+61 2 4322 0001",
    "sg:postcode":"2250",
    "sg:province":"NSW",
    "wof:name":"Melrose Nails",
    "wof:placetype":"venue"
},
  "geometry": {"coordinates":[151.30891418499999,-33.4303245544],"type":"Point"}
}