{
  "type": "Feature",
  "properties": {
    "addr:full":"211 Fleming Rd Hemmant QLD 4174",
    "addr:housenumber":"211",
    "addr:postcode":"4174",
    "addr:street":"Fleming Rd",
    "iso:country":"AU",
    "sg:address":"211 Fleming Rd",
    "sg:city":"Hemmant",
    "sg:classifiers":[
        {
            "category":"Retail",
            "subcategory":"Storage",
            "type":"Services"
        }
    ],
    "sg:phone":"+61 7 3890 5799",
    "sg:postcode":"4174",
    "sg:province":"QLD",
    "sg:tags":[
        "removal",
        "furniture"
    ],
    "wof:name":"Across Australia One-Way Trailer Rentals",
    "wof:placetype":"venue"
},
  "geometry": {"coordinates":[153.128250122,-27.4620742798],"type":"Point"}
}