{
  "type": "Feature",
  "properties": {
    "addr:full":"U6/ 6 Raymond Ave Bayswater WA 6053",
    "addr:housenumber":"6",
    "addr:postcode":"6053",
    "addr:street":"U6 /;Raymond Ave",
    "iso:country":"AU",
    "sg:address":"U6/ 6 Raymond Ave",
    "sg:city":"Bayswater",
    "sg:classifiers":[
        {
            "category":"Retail",
            "subcategory":"Auto Repair",
            "type":"Services"
        }
    ],
    "sg:phone":"+61 8 9272 4889",
    "sg:postcode":"6053",
    "sg:province":"WA",
    "sg:tags":[
        "repairer",
        "motor",
        "engineer"
    ],
    "wof:name":"Autoforce Mechanical Repairs",
    "wof:placetype":"venue"
},
  "geometry": {"coordinates":[115.91686248800001,-31.9094791412],"type":"Point"}
}