{
  "type": "Feature",
  "properties": {
    "addr:full":"28 Grandview Ave Glen Iris VIC 3146",
    "addr:housenumber":"28",
    "addr:postcode":"3146",
    "addr:street":"Grandview Ave",
    "iso:country":"AU",
    "sg:address":"28 Grandview Ave",
    "sg:city":"Glen Iris",
    "sg:classifiers":[
        {
            "category":"Banks & Credit Unions",
            "subcategory":"Financial Services",
            "type":"Services"
        }
    ],
    "sg:phone":"+61 3 9809 1288",
    "sg:postcode":"3146",
    "sg:province":"VIC",
    "sg:tags":[
        "annuity",
        "rollover",
        "superannuation",
        "consultant"
    ],
    "wof:name":"SuperAssist",
    "wof:placetype":"venue"
},
  "geometry": {"coordinates":[145.08355712900001,-37.8514556885],"type":"Point"}
}