{
  "type": "Feature",
  "properties": {
    "addr:full":"210 Bannister Rd Canning Vale WA 6155",
    "addr:housenumber":"210",
    "addr:postcode":"6155",
    "addr:street":"Bannister Rd",
    "iso:country":"AU",
    "sg:address":"210 Bannister Rd",
    "sg:city":"Canning Vale",
    "sg:classifiers":[
        {
            "category":"Food & Beverages",
            "subcategory":"Liquor & Beverages",
            "type":"Retail Goods"
        }
    ],
    "sg:phone":"+61 8 9455 9000",
    "sg:postcode":"6155",
    "sg:province":"WA",
    "sg:tags":[
        "merchant",
        "spirit",
        "wine"
    ],
    "wof:name":"Australian Liquor Marketers",
    "wof:placetype":"venue"
},
  "geometry": {"coordinates":[115.90406,-32.062347],"type":"Point"}
}