{
  "type": "Feature",
  "properties": {
    "addr:full":"15 Manning St Newtown VIC 3220",
    "addr:housenumber":"15",
    "addr:postcode":"3220",
    "addr:street":"Manning St",
    "iso:country":"AU",
    "sg:address":"15 Manning St",
    "sg:city":"Newtown",
    "sg:classifiers":[
        {
            "category":"Building & Trades",
            "subcategory":"Construction",
            "type":"Services"
        }
    ],
    "sg:phone":"+61 3 5221 3349",
    "sg:postcode":"3220",
    "sg:province":"VIC",
    "sg:tags":[
        "contractor"
    ],
    "wof:name":"Stow B J & M M",
    "wof:placetype":"venue"
},
  "geometry": {"coordinates":[144.343887,-38.148964],"type":"Point"}
}