{
  "type": "Feature",
  "properties": {
    "addr:full":"PO Box 69 Kurnell NSW 2231",
    "addr:postcode":"2231",
    "iso:country":"AU",
    "sg:address":"PO Box 69",
    "sg:city":"Kurnell",
    "sg:classifiers":[
        {
            "category":"Autos & Motor Vehicles",
            "subcategory":"Motorcycle Sales",
            "type":"Retail Goods"
        }
    ],
    "sg:phone":"+61 2 9668 9630",
    "sg:postcode":"2231",
    "sg:province":"NSW",
    "sg:tags":[
        "outboard"
    ],
    "wof:name":"Sportsfisherman Marine",
    "wof:placetype":"venue"
},
  "geometry": {"coordinates":[151.21469116200001,-34.0098495483],"type":"Point"}
}