{
  "type": "Feature",
  "properties": {
    "addr:full":"Goldfields Hwy Kalgoorlie WA 6430",
    "addr:postcode":"6430",
    "addr:street":"Goldfields Hwy",
    "iso:country":"AU",
    "sg:address":"Goldfields Hwy",
    "sg:city":"Kalgoorlie",
    "sg:classifiers":[
        {
            "category":"Retail",
            "subcategory":"Event Space",
            "type":"Services"
        }
    ],
    "sg:phone":"+61 8 9026 2700",
    "sg:postcode":"6430",
    "sg:province":"WA",
    "sg:tags":[
        "venue",
        "reception",
        "wedding"
    ],
    "wof:name":"Mining Hall Of Fame",
    "wof:placetype":"venue"
},
  "geometry": {"coordinates":[121.479118347,-30.745054245],"type":"Point"}
}