{
  "type": "Feature",
  "properties": {
    "addr:full":"79 King St Caboolture QLD 4510",
    "addr:housenumber":"79",
    "addr:postcode":"4510",
    "addr:street":"King St",
    "iso:country":"AU",
    "sg:address":"79 King St",
    "sg:city":"Caboolture",
    "sg:classifiers":[
        {
            "category":"Professional",
            "subcategory":"Employment Agencies",
            "type":"Services"
        }
    ],
    "sg:phone":"+61 7 5428 3590",
    "sg:postcode":"4510",
    "sg:province":"QLD",
    "wof:name":"Mission Australia",
    "wof:placetype":"venue"
},
  "geometry": {"coordinates":[152.948746,-27.084408],"type":"Point"}
}