{
  "type": "Feature",
  "properties": {
    "iso:country":"AU",
    "sg:address":"53 Ervin Rd",
    "sg:city":"Croydon",
    "sg:classifiers":[
        {
            "category":"Building & Trades",
            "subcategory":"Construction",
            "type":"Services"
        }
    ],
    "sg:phone":"+61 418 548 999",
    "sg:postcode":"3136",
    "sg:province":"VIC",
    "sg:tags":[
        "contractor"
    ],
    "wof:name":"Sajaf Trading",
    "wof:placetype":"venue"
},
  "geometry": {"coordinates":[145.30862426799999,-37.7959861755],"type":"Point"}
}