{
  "type": "Feature",
  "properties": {
    "addr:full":"Level 12, 40 St Georges Tce Perth WA 6000",
    "addr:housenumber":"40",
    "addr:postcode":"6000",
    "addr:street":"St Georges Tce",
    "iso:country":"AU",
    "sg:address":"Level 12, 40 St",
    "sg:city":"Georges Tce Perth",
    "sg:classifiers":[
        {
            "category":"Organizations",
            "subcategory":"Community Association",
            "type":"Services"
        }
    ],
    "sg:phone":"+61 8 9463 3000",
    "sg:postcode":"6000",
    "sg:province":"WA",
    "sg:tags":[
        "registered",
        "trustee",
        "bankruptcy"
    ],
    "wof:name":"SimsPartners",
    "wof:placetype":"venue"
},
  "geometry": {"coordinates":[115.859642029,-31.9555892944],"type":"Point"}
}