{
  "type": "Feature",
  "properties": {
    "addr:full":"Small Boat Habour Rd Carnarvon WA 6701",
    "addr:postcode":"6701",
    "addr:street":"Habour Rd",
    "iso:country":"AU",
    "sg:address":"Small Boat Habour Rd",
    "sg:city":"Carnarvon",
    "sg:classifiers":[
        {
            "category":"Utilities",
            "subcategory":"Fuel Oil & Lpg",
            "type":"Services"
        }
    ],
    "sg:phone":"+61 8 9941 1569",
    "sg:postcode":"6701",
    "sg:province":"WA",
    "sg:tags":[
        "merchant"
    ],
    "wof:name":"Sovereign Petroleum",
    "wof:placetype":"venue"
},
  "geometry": {"coordinates":[113.65937805199999,-24.8811206818],"type":"Point"}
}