{
  "type": "Feature",
  "properties": {
    "addr:full":"268 Hotham Creek Rd Willowvale QLD 4209",
    "addr:housenumber":"268",
    "addr:postcode":"4209",
    "addr:street":"Hotham Creek Rd",
    "iso:country":"AU",
    "sg:address":"268 Hotham Creek Rd",
    "sg:city":"Willowvale",
    "sg:classifiers":[
        {
            "category":"Professional",
            "subcategory":"Detective & Security Services",
            "type":"Services"
        }
    ],
    "sg:phone":"+61 7 5546 6700",
    "sg:postcode":"4209",
    "sg:province":"QLD",
    "sg:tags":[
        "distributor",
        "aircraft",
        "mfrs"
    ],
    "wof:name":"Conroy's Aviation Pty Ltd",
    "wof:placetype":"venue"
},
  "geometry": {"coordinates":[153.260375977,-27.8388824463],"type":"Point"}
}