{
  "type": "Feature",
  "properties": {
    "addr:full":"3 Claremont Ave Malvern VIC 3144",
    "addr:housenumber":"3",
    "addr:postcode":"3144",
    "addr:street":"Claremont Ave",
    "iso:country":"AU",
    "sg:address":"3 Claremont Ave",
    "sg:city":"Malvern",
    "sg:classifiers":[
        {
            "category":"Professional",
            "subcategory":"Detective & Security Services",
            "type":"Services"
        }
    ],
    "sg:phone":"+61 3 9576 2977",
    "sg:postcode":"3144",
    "sg:province":"VIC",
    "sg:tags":[
        "investigator"
    ],
    "wof:name":"Trace Detective Agency",
    "wof:placetype":"venue"
},
  "geometry": {"coordinates":[145.029571533,-37.8656845093],"type":"Point"}
}