{
  "type": "Feature",
  "properties": {
    "iso:country":"AU",
    "sg:address":"24 Kilvington Drv",
    "sg:city":"Emerald",
    "sg:classifiers":[
        {
            "category":"Building & Trades",
            "subcategory":"Landscaping Services",
            "type":"Services"
        }
    ],
    "sg:phone":"+61 3 5968 5668",
    "sg:postcode":"3782",
    "sg:province":"VIC",
    "sg:tags":[
        "designer",
        "landscape",
        "contractor"
    ],
    "wof:name":"Natural Impressions",
    "wof:placetype":"venue"
},
  "geometry": {"coordinates":[145.44001800000001,-37.936287],"type":"Point"}
}