{
  "type": "Feature",
  "properties": {
    "addr:full":"10 Seaforth Ave Somerton Park SA 5044",
    "addr:housenumber":"10",
    "addr:postcode":"5044",
    "addr:street":"Seaforth Ave Somerton",
    "iso:country":"AU",
    "sg:address":"10 Seaforth Ave",
    "sg:city":"Somerton Park",
    "sg:classifiers":[
        {
            "category":"Professional",
            "type":"Services"
        }
    ],
    "sg:phone":"+61 8 8377 1949",
    "sg:postcode":"5044",
    "sg:province":"SA",
    "sg:tags":[
        "coating",
        "powder"
    ],
    "wof:name":"Seaforth Powdercoaters",
    "wof:placetype":"venue"
},
  "geometry": {"coordinates":[138.52299500000001,-35.000984],"type":"Point"}
}