{
  "type": "Feature",
  "properties": {
    "iso:country":"AU",
    "sg:address":"37 Main St",
    "sg:city":"Pakenham",
    "sg:classifiers":[
        {
            "category":"Health Services",
            "subcategory":"Chiropractor",
            "type":"Services"
        }
    ],
    "sg:phone":"+61 3 5941 2055",
    "sg:postcode":"3810",
    "sg:province":"VIC",
    "wof:name":"Pakenham Main St Chiropractic",
    "wof:placetype":"venue"
},
  "geometry": {"coordinates":[145.479263,-38.075256],"type":"Point"}
}