{
  "type": "Feature",
  "properties": {
    "addr:full":"25335 New England Hwy The Summit QLD 4377",
    "addr:postcode":"25335;4377",
    "addr:street":"New England Hwy The Summit",
    "iso:country":"AU",
    "sg:address":"25335 New England Hwy",
    "sg:city":"The Summit",
    "sg:classifiers":[
        {
            "category":"Home & Garden",
            "subcategory":"Garden Supply",
            "type":"Retail Goods"
        }
    ],
    "sg:phone":"+61 429 919 914",
    "sg:postcode":"4377",
    "sg:province":"QLD",
    "sg:tags":[
        "fertilizer"
    ],
    "wof:name":"South East Queensland Spreading",
    "wof:placetype":"venue"
},
  "geometry": {"coordinates":[151.95407104500001,-28.5910167694],"type":"Point"}
}