{
  "type": "Feature",
  "properties": {
    "iso:country":"AU",
    "sg:address":"25 Charlotte St",
    "sg:city":"Smithfield",
    "sg:classifiers":[
        {
            "category":"Retail",
            "subcategory":"Auto Repair",
            "type":"Services"
        }
    ],
    "sg:phone":"+61 8 8254 1077",
    "sg:postcode":"5114",
    "sg:province":"SA",
    "sg:tags":[
        "repairer",
        "motor",
        "engineer"
    ],
    "wof:name":"Selway's Auto Repairs",
    "wof:placetype":"venue"
},
  "geometry": {"coordinates":[138.688995361,-34.6818733215],"type":"Point"}
}