{
  "type": "Feature",
  "properties": {
    "addr:full":"68 McEwen Rd Kyabram VIC 3620",
    "addr:housenumber":"68",
    "addr:postcode":"3620",
    "addr:street":"Mcewen Rd",
    "iso:country":"AU",
    "sg:address":"68 McEwen Rd",
    "sg:city":"Kyabram",
    "sg:classifiers":[
        {
            "category":"Manufacturing",
            "subcategory":"Retail Goods",
            "type":"Manufacturing & Wholesale Goods"
        }
    ],
    "sg:phone":"+61 3 5853 2653",
    "sg:postcode":"3620",
    "sg:province":"VIC",
    "sg:tags":[
        "merchant",
        "pump",
        "mfrs"
    ],
    "wof:name":"W & P Pumps",
    "wof:placetype":"venue"
},
  "geometry": {"coordinates":[145.03225707999999,-36.3062286377],"type":"Point"}
}