{
  "type": "Feature",
  "properties": {
    "iso:country":"AU",
    "sg:address":"2 Walker St",
    "sg:city":"Bowral",
    "sg:classifiers":[
        {
            "category":"Professional",
            "subcategory":"Accounting & Tax Preparation",
            "type":"Services"
        }
    ],
    "sg:phone":"+61 2 4861 8318",
    "sg:postcode":"2576",
    "sg:province":"NSW",
    "sg:tags":[
        "consultant",
        "taxation"
    ],
    "wof:name":"Actax Services",
    "wof:placetype":"venue"
},
  "geometry": {"coordinates":[150.41566467300001,-34.483089447],"type":"Point"}
}