{
  "type": "Feature",
  "properties": {
    "addr:full":"27- 31 Linton St Roma QLD 4455",
    "addr:housenumber":"31",
    "addr:postcode":"4455",
    "addr:street":"Linton St",
    "iso:country":"AU",
    "sg:address":"27- 31 Linton St",
    "sg:city":"Roma",
    "sg:classifiers":[
        {
            "category":"Building & Trades",
            "subcategory":"Construction",
            "type":"Services"
        }
    ],
    "sg:phone":"+61 7 4622 4291",
    "sg:postcode":"4455",
    "sg:province":"QLD",
    "sg:tags":[
        "earth",
        "excavating",
        "moving",
        "contractor"
    ],
    "wof:name":"Lawrie Jones Earthmoving",
    "wof:placetype":"venue"
},
  "geometry": {"coordinates":[148.77796935999999,-26.5816688538],"type":"Point"}
}