{
  "type": "Feature",
  "properties": {
    "addr:full":"Unit 8, 1-3 Coller Rd Kings Point NSW 2539",
    "addr:housenumber":"1-3",
    "addr:postcode":"2539",
    "addr:street":"Coller Rd",
    "iso:country":"AU",
    "sg:address":"Unit 8, 1-3 Coller Rd",
    "sg:city":"Kings Point",
    "sg:classifiers":[
        {
            "category":"Professional",
            "type":"Services"
        }
    ],
    "sg:phone":"+61 2 4454 5451",
    "sg:postcode":"2539",
    "sg:province":"NSW",
    "sg:tags":[
        "spray",
        "painting"
    ],
    "wof:name":"Ulladulla Creative Images",
    "wof:placetype":"venue"
},
  "geometry": {"coordinates":[150.47224426299999,-35.3623275757],"type":"Point"}
}