{
  "type": "Feature",
  "properties": {
    "iso:country":"AU",
    "sg:address":"Shp4b/ 3063",
    "sg:city":"Surfers Paradise Blv Surfers Paradise",
    "sg:classifiers":[
        {
            "category":"Shopping",
            "subcategory":"Clothing, Apparel, & Fashions",
            "type":"Retail Goods"
        }
    ],
    "sg:phone":"+61 7 5526 7473",
    "sg:postcode":"4217",
    "sg:province":"QLD",
    "sg:tags":[
        "boutique"
    ],
    "wof:name":"Love Kavalier",
    "wof:placetype":"venue"
},
  "geometry": {"coordinates":[153.42880249000001,-28.0029582977],"type":"Point"}
}