{
  "type": "Feature",
  "properties": {
    "addr:full":"45 Barwon Park Rd St Peters NSW 2044",
    "addr:housenumber":"45",
    "addr:postcode":"2044",
    "addr:street":"Barwon Park Rd",
    "iso:country":"AU",
    "sg:address":"45 Barwon Park Rd",
    "sg:city":"St Peters",
    "sg:classifiers":[
        {
            "category":"Shopping",
            "subcategory":"Antiques",
            "type":"Retail Goods"
        }
    ],
    "sg:phone":"+61 2 9557 8380",
    "sg:postcode":"2044",
    "sg:province":"NSW",
    "sg:tags":[
        "restoration",
        "reproduction"
    ],
    "wof:name":"Major & Tom Restoration",
    "wof:placetype":"venue"
},
  "geometry": {"coordinates":[151.18107599999999,-33.913078],"type":"Point"}
}