{
  "type": "Feature",
  "properties": {
    "addr:full":"6 Lindisfarne Crt Thurgoona NSW 2640",
    "addr:housenumber":"6",
    "addr:postcode":"2640",
    "addr:street":"Lindisfarne Crt",
    "iso:country":"AU",
    "sg:address":"6 Lindisfarne Crt",
    "sg:city":"Thurgoona",
    "sg:classifiers":[
        {
            "category":"Building & Trades",
            "subcategory":"Construction",
            "type":"Services"
        }
    ],
    "sg:phone":"+61 2 6043 1266",
    "sg:postcode":"2640",
    "sg:province":"NSW",
    "sg:tags":[
        "concrete",
        "paving"
    ],
    "wof:name":"Eves Phil Concreting",
    "wof:placetype":"venue"
},
  "geometry": {"coordinates":[146.996780395,-36.0539054871],"type":"Point"}
}