{
  "type": "Feature",
  "properties": {
    "addr:full":"56 Porter St North Wollongong NSW 2500",
    "addr:housenumber":"56",
    "addr:postcode":"2500",
    "addr:street":"Porter St North",
    "iso:country":"AU",
    "sg:address":"56 Porter St",
    "sg:city":"North Wollongong",
    "sg:classifiers":[
        {
            "category":"Education",
            "subcategory":"School",
            "type":"Public Place"
        }
    ],
    "sg:phone":"+61 2 4229 1922",
    "sg:postcode":"2500",
    "sg:province":"NSW",
    "sg:tags":[
        "co-educational"
    ],
    "wof:name":"Para Meadows Public School",
    "wof:placetype":"venue"
},
  "geometry": {"coordinates":[150.887787,-34.412247],"type":"Point"}
}