{
  "type": "Feature",
  "properties": {
    "addr:full":"77 Verdon St Williamstown VIC 3016",
    "addr:housenumber":"77",
    "addr:postcode":"3016",
    "addr:street":"Verdon St",
    "iso:country":"AU",
    "sg:address":"77 Verdon St",
    "sg:city":"Williamstown",
    "sg:classifiers":[
        {
            "category":"Real Estate",
            "subcategory":"Architect",
            "type":"Services"
        }
    ],
    "sg:phone":"+61 3 9399 9480",
    "sg:postcode":"3016",
    "sg:province":"VIC",
    "wof:name":"Frank Marioli",
    "wof:placetype":"venue"
},
  "geometry": {"coordinates":[144.89326477,-37.8599128723],"type":"Point"}
}