{
  "type": "Feature",
  "properties": {
    "addr:full":"21 Albert St Goondiwindi QLD 4390",
    "addr:housenumber":"21",
    "addr:postcode":"4390",
    "addr:street":"Albert St",
    "iso:country":"AU",
    "sg:address":"21 Albert St",
    "sg:city":"Goondiwindi",
    "sg:classifiers":[
        {
            "category":"Travel",
            "subcategory":"Travel Agent",
            "type":"Entertainment"
        }
    ],
    "sg:phone":"+61 7 4671 1677",
    "sg:postcode":"4390",
    "sg:province":"QLD",
    "sg:tags":[
        "consultant"
    ],
    "wof:name":"Goondiwindi Travel Centre",
    "wof:placetype":"venue"
},
  "geometry": {"coordinates":[150.31788635300001,-28.5484085083],"type":"Point"}
}