{
  "type": "Feature",
  "properties": {
    "iso:country":"AU",
    "sg:address":"4/ 9 Oakdale Rd",
    "sg:city":"Gateshead",
    "sg:classifiers":[
        {
            "category":"Arts & Performance",
            "subcategory":"Dance",
            "type":"Entertainment"
        }
    ],
    "sg:phone":"+61 2 4948 2953",
    "sg:postcode":"2290",
    "sg:province":"NSW",
    "sg:tags":[
        "theatrical",
        "ballet",
        "tuition"
    ],
    "wof:name":"Central School of Dance",
    "wof:placetype":"venue"
},
  "geometry": {"coordinates":[151.698394775,-32.9661941528],"type":"Point"}
}