{
  "type": "Feature",
  "properties": {
    "addr:full":"231 Morphett St Adelaide SA 5000",
    "addr:housenumber":"231",
    "addr:postcode":"5000",
    "addr:street":"Morphett St",
    "iso:country":"AU",
    "sg:address":"231 Morphett St",
    "sg:city":"Adelaide",
    "sg:classifiers":[
        {
            "category":"Social Services",
            "subcategory":"Adult Care",
            "type":"Services"
        }
    ],
    "sg:phone":"+61 8 8218 0700",
    "sg:postcode":"5000",
    "sg:province":"SA",
    "sg:tags":[
        "disadvantaged",
        "aid",
        "organisation",
        "group"
    ],
    "wof:name":"OARS SA",
    "wof:placetype":"venue"
},
  "geometry": {"coordinates":[138.59371948200001,-34.9283828735],"type":"Point"}
}