{
  "type": "Feature",
  "properties": {
    "iso:country":"AU",
    "sg:address":"Robina Town Cntr, 1 Bazaar St",
    "sg:city":"Robina",
    "sg:classifiers":[
        {
            "category":"Shopping",
            "subcategory":"Mobile Phones",
            "type":"Retail Goods"
        }
    ],
    "sg:phone":"+61 7 5593 2205",
    "sg:postcode":"4226",
    "sg:province":"QLD",
    "sg:tags":[
        "telephone",
        "accessory"
    ],
    "wof:name":"Digicall",
    "wof:placetype":"venue"
},
  "geometry": {"coordinates":[153.387374878,-28.0709590912],"type":"Point"}
}