{
  "type": "Feature",
  "properties": {
    "iso:country":"AU",
    "sg:address":"49 Norman St",
    "sg:city":"Peakhurst",
    "sg:classifiers":[
        {
            "category":"Donuts",
            "subcategory":"None",
            "type":"Food & Drink"
        }
    ],
    "sg:phone":"+61 2 9584 2433",
    "sg:postcode":"2210",
    "sg:province":"NSW",
    "sg:tags":[
        "die",
        "engraver",
        "sinker"
    ],
    "wof:name":"Ryan Signage Pty Ltd",
    "wof:placetype":"venue"
},
  "geometry": {"coordinates":[151.063187,-33.964706],"type":"Point"}
}