{
  "type": "Feature",
  "properties": {
    "iso:country":"AU",
    "sg:address":"13 Bell St",
    "sg:city":"Ipswich",
    "sg:classifiers":[
        {
            "category":"Health Services",
            "subcategory":"Doctor",
            "type":"Services"
        }
    ],
    "sg:phone":"+61 7 3281 4933",
    "sg:postcode":"4305",
    "sg:province":"QLD",
    "sg:tags":[
        "medical",
        "practitioner"
    ],
    "wof:name":"Van Hecke A Dr",
    "wof:placetype":"venue"
},
  "geometry": {"coordinates":[152.760375977,-27.6133155823],"type":"Point"}
}