{
  "type": "Feature",
  "properties": {
    "addr:full":"PO Box 12396 A'Beckett Street VIC 8006",
    "addr:postcode":"8006",
    "addr:street":"A'Beckett Street",
    "iso:country":"AU",
    "sg:address":"PO Box 12396",
    "sg:city":"A'Beckett Street",
    "sg:classifiers":[
        {
            "category":"Communications",
            "type":"Services"
        }
    ],
    "sg:phone":"+61 404 944 546",
    "sg:postcode":"8006",
    "sg:province":"VIC",
    "sg:tags":[
        "translation"
    ],
    "wof:name":"Marcia Pinheiro",
    "wof:placetype":"venue"
},
  "geometry": {"coordinates":[145.09234619099999,-37.8060150146],"type":"Point"}
}