{
  "type": "Feature",
  "properties": {
    "addr:full":"38 Grey St St Kilda VIC 3182",
    "addr:housenumber":"38",
    "addr:postcode":"3182",
    "addr:street":"Grey St",
    "iso:country":"AU",
    "sg:address":"38 Grey St",
    "sg:city":"St Kilda",
    "sg:classifiers":[
        {
            "category":"Travel",
            "subcategory":"Hotels & Motels",
            "type":"Entertainment"
        }
    ],
    "sg:phone":"+61 1800 501 752",
    "sg:postcode":"3182",
    "sg:province":"VIC",
    "sg:tags":[
        "accommodation"
    ],
    "wof:name":"Oslo Hotel For Budget Travellers",
    "wof:placetype":"venue"
},
  "geometry": {"coordinates":[144.97903442399999,-37.8611869812],"type":"Point"}
}