{
  "type": "Feature",
  "properties": {
    "iso:country":"AU",
    "sg:address":"477 Darling St",
    "sg:city":"Balmain",
    "sg:classifiers":[
        {
            "category":"Utilities",
            "subcategory":"Electric",
            "type":"Services"
        }
    ],
    "sg:phone":"+61 2 9810 0351",
    "sg:postcode":"2041",
    "sg:province":"NSW",
    "sg:tags":[
        "electrical",
        "contractor"
    ],
    "wof:name":"Atilight Dev Pty Ltd",
    "wof:placetype":"venue"
},
  "geometry": {"coordinates":[151.17295799999999,-33.8563],"type":"Point"}
}