{
  "type": "Feature",
  "properties": {
    "iso:country":"AU",
    "sg:address":"Fisher St",
    "sg:city":"Magill",
    "sg:classifiers":[
        {
            "category":"Education",
            "subcategory":"School",
            "type":"Public Place"
        }
    ],
    "sg:phone":"+61 8 8337 2988",
    "sg:postcode":"5072",
    "sg:province":"SA",
    "sg:tags":[
        "state",
        "except",
        "nsw"
    ],
    "wof:name":"Hectorville Primary",
    "wof:placetype":"venue"
},
  "geometry": {"coordinates":[138.66894531200001,-34.9028701782],"type":"Point"}
}