{
  "type": "Feature",
  "properties": {
    "addr:full":"1 Crown St Geelong South VIC 3220",
    "addr:housenumber":"1",
    "addr:postcode":"3220",
    "addr:street":"Crown St",
    "iso:country":"AU",
    "sg:address":"1 Crown St",
    "sg:city":"Geelong South",
    "sg:classifiers":[
        {
            "category":"Sports & Exercise",
            "subcategory":"Sports Center",
            "type":"Entertainment"
        }
    ],
    "sg:phone":"+61 3 5223 1992",
    "sg:postcode":"3220",
    "sg:province":"VIC",
    "sg:tags":[
        "ground"
    ],
    "wof:name":"Life Be In It Sport For All",
    "wof:placetype":"venue"
},
  "geometry": {"coordinates":[144.36717200000001,-38.165791],"type":"Point"}
}