{
  "type": "Feature",
  "properties": {
    "iso:country":"AU",
    "sg:address":"Unit A5, 303 The Horsley Drv",
    "sg:city":"Fairfield",
    "sg:classifiers":[
        {
            "category":"Retail",
            "subcategory":"Auto Repair",
            "type":"Services"
        }
    ],
    "sg:phone":"+61 2 9726 5178",
    "sg:postcode":"2165",
    "sg:province":"NSW",
    "sg:tags":[
        "repairer",
        "motor",
        "engineer"
    ],
    "wof:name":"Ultra Tune",
    "wof:placetype":"venue"
},
  "geometry": {"coordinates":[150.96107482900001,-33.8708686829],"type":"Point"}
}