{
  "type": "Feature",
  "properties": {
    "addr:full":"74 Roberts Rd Greenacre NSW 2190",
    "addr:housenumber":"74",
    "addr:postcode":"2190",
    "addr:street":"Roberts Rd",
    "iso:country":"AU",
    "sg:address":"74 Roberts Rd",
    "sg:city":"Greenacre",
    "sg:classifiers":[
        {
            "category":"Autos & Motor Vehicles",
            "subcategory":"Fuel & Gas Station",
            "type":"Retail Goods"
        }
    ],
    "sg:phone":"+61 2 9742 1002",
    "sg:postcode":"2190",
    "sg:province":"NSW",
    "wof:name":"Shell Select",
    "wof:placetype":"venue"
},
  "geometry": {"coordinates":[151.06559799999999,-33.897179],"type":"Point"}
}