{
  "type": "Feature",
  "properties": {
    "addr:full":"150 Kent St Rockhampton QLD 4700",
    "addr:housenumber":"150",
    "addr:postcode":"4700",
    "addr:street":"Kent St",
    "iso:country":"AU",
    "sg:address":"150 Kent St",
    "sg:city":"Rockhampton",
    "sg:classifiers":[
        {
            "category":"Shopping",
            "type":"Retail Goods"
        }
    ],
    "sg:phone":"+61 7 4936 0420",
    "sg:postcode":"4700",
    "sg:province":"QLD",
    "sg:tags":[
        "agent",
        "stock"
    ],
    "wof:name":"Bluegum Cooperative Association Ltd",
    "wof:placetype":"venue"
},
  "geometry": {"coordinates":[150.51965332,-23.395690918],"type":"Point"}
}