{
  "type": "Feature",
  "properties": {
    "iso:country":"AU",
    "sg:address":"Fullerton St",
    "sg:city":"Stockton",
    "sg:classifiers":[
        {
            "category":"Health Services",
            "subcategory":"Nursing And Care Facility",
            "type":"Services"
        }
    ],
    "sg:phone":"+61 2 4928 1822",
    "sg:postcode":"2295",
    "sg:province":"NSW",
    "sg:tags":[
        "home"
    ],
    "wof:name":"Wescott Nursing Home & Hostel",
    "wof:placetype":"venue"
},
  "geometry": {"coordinates":[151.78147888199999,-32.9164543152],"type":"Point"}
}