{
  "type": "Feature",
  "properties": {
    "iso:country":"AU",
    "sg:address":"3 Prestige Drv",
    "sg:city":"Clayton South",
    "sg:classifiers":[
        {
            "category":"Autos & Motor Vehicles",
            "subcategory":"Auto Supplies",
            "type":"Retail Goods"
        }
    ],
    "sg:phone":"+61 3 9558 1656",
    "sg:postcode":"3169",
    "sg:province":"VIC",
    "sg:tags":[
        "accessory"
    ],
    "wof:name":"Motorware Australia",
    "wof:placetype":"venue"
},
  "geometry": {"coordinates":[145.12159729000001,-37.9431533813],"type":"Point"}
}