{
  "type": "Feature",
  "properties": {
    "addr:full":"68 Forsyth St O'Connor WA 6163",
    "addr:housenumber":"68",
    "addr:postcode":"6163",
    "addr:street":"Forsyth St",
    "iso:country":"AU",
    "sg:address":"68 Forsyth St",
    "sg:city":"O'Connor",
    "sg:classifiers":[
        {
            "category":"Manufacturing",
            "subcategory":"Furniture",
            "type":"Manufacturing & Wholesale Goods"
        }
    ],
    "sg:phone":"+61 8 9314 4720",
    "sg:postcode":"6163",
    "sg:province":"WA",
    "sg:tags":[
        "mfrs",
        "supply"
    ],
    "wof:name":"Joyce Foam Products",
    "wof:placetype":"venue"
},
  "geometry": {"coordinates":[115.79274700000001,-32.055389],"type":"Point"}
}