{
  "type": "Feature",
  "properties": {
    "addr:full":"222 Castle Rd Orchard Hills NSW 2748",
    "addr:housenumber":"222",
    "addr:postcode":"2748",
    "addr:street":"Castle Rd",
    "iso:country":"AU",
    "sg:address":"222 Castle Rd",
    "sg:city":"Orchard Hills",
    "sg:classifiers":[
        {
            "category":"Building & Trades",
            "subcategory":"Cleaning & Sanitation",
            "type":"Services"
        }
    ],
    "sg:phone":"+61 1800 723 632",
    "sg:postcode":"2748",
    "sg:province":"NSW",
    "sg:tags":[
        "industrial",
        "commercial",
        "contractor"
    ],
    "wof:name":"Scene Clean NSW",
    "wof:placetype":"venue"
},
  "geometry": {"coordinates":[150.71591186500001,-33.7788391113],"type":"Point"}
}