{
  "type": "Feature",
  "properties": {
    "addr:full":"112 Finley St Finley NSW 2713",
    "addr:housenumber":"112",
    "addr:postcode":"2713",
    "addr:street":"Finley St",
    "iso:country":"AU",
    "sg:address":"112 Finley St",
    "sg:city":"Finley",
    "sg:classifiers":[
        {
            "category":"Professional",
            "subcategory":"Testing Lab",
            "type":"Services"
        }
    ],
    "sg:phone":"+61 3 5883 1013",
    "sg:postcode":"2713",
    "sg:province":"NSW",
    "sg:tags":[
        "soil",
        "investigation"
    ],
    "wof:name":"Angove Lloyd",
    "wof:placetype":"venue"
},
  "geometry": {"coordinates":[145.57984924300001,-35.6440887451],"type":"Point"}
}