{
  "type": "Feature",
  "properties": {
    "addr:full":"88 McKinnon Rd McKinnon VIC 3204",
    "addr:housenumber":"88",
    "addr:postcode":"3204",
    "addr:street":"Mckinnon Rd",
    "iso:country":"AU",
    "sg:address":"88 McKinnon Rd",
    "sg:city":"McKinnon",
    "sg:classifiers":[
        {
            "category":"Retail",
            "subcategory":"Auto Repair",
            "type":"Services"
        }
    ],
    "sg:phone":"+61 3 9578 5031",
    "sg:postcode":"3204",
    "sg:province":"VIC",
    "sg:tags":[
        "electrical"
    ],
    "wof:name":"Gils Auto Electrical",
    "wof:placetype":"venue"
},
  "geometry": {"coordinates":[145.033783,-37.910622],"type":"Point"}
}