{
  "type": "Feature",
  "properties": {
    "addr:full":"254 Somerville Rd Kingsville VIC 3012",
    "addr:housenumber":"254",
    "addr:postcode":"3012",
    "addr:street":"Somerville Rd",
    "iso:country":"AU",
    "sg:address":"254 Somerville Rd",
    "sg:city":"Kingsville",
    "sg:classifiers":[
        {
            "category":"Communications",
            "type":"Services"
        }
    ],
    "sg:phone":"+61 3 9325 1655",
    "sg:postcode":"3012",
    "sg:province":"VIC",
    "sg:tags":[
        "antenna"
    ],
    "wof:name":"Satelvision Antenna & Digital Services",
    "wof:placetype":"venue"
},
  "geometry": {"coordinates":[144.876785278,-37.8118896484],"type":"Point"}
}