{
  "type": "Feature",
  "properties": {
    "iso:country":"AU",
    "sg:address":"56 Marlene St",
    "sg:city":"Mt Gravatt East",
    "sg:classifiers":[
        {
            "category":"Personal",
            "type":"Services"
        }
    ],
    "sg:phone":"+61 433 746 463",
    "sg:postcode":"4122",
    "sg:province":"QLD",
    "sg:tags":[
        "introduction",
        "social"
    ],
    "wof:name":"Conxus",
    "wof:placetype":"venue"
},
  "geometry": {"coordinates":[153.08607482900001,-27.5390148163],"type":"Point"}
}