{
  "type": "Feature",
  "properties": {
    "iso:country":"AU",
    "sg:address":"212 Military Rd",
    "sg:city":"Henley Beach",
    "sg:classifiers":[
        {
            "category":"Shopping",
            "subcategory":"Bicycles & Sporting Goods",
            "type":"Retail Goods"
        }
    ],
    "sg:phone":"+61 8 8221 6099",
    "sg:postcode":"5022",
    "sg:province":"SA",
    "sg:tags":[
        "chemical",
        "equipment",
        "pool",
        "swimming"
    ],
    "wof:name":"Spa Cover Specialists",
    "wof:placetype":"venue"
},
  "geometry": {"coordinates":[138.495162964,-34.91822052],"type":"Point"}
}