{
  "type": "Feature",
  "properties": {
    "addr:full":"Muirfield Drv Sunbury VIC 3429",
    "addr:postcode":"3429",
    "addr:street":"Muirfield Drv",
    "iso:country":"AU",
    "sg:address":"Muirfield Drv",
    "sg:city":"Sunbury",
    "sg:classifiers":[
        {
            "category":"Real Estate",
            "subcategory":"Real Estate Agent",
            "type":"Services"
        }
    ],
    "sg:phone":"+61 3 9740 8265",
    "sg:postcode":"3429",
    "sg:province":"VIC",
    "sg:tags":[
        "handyman's",
        "equipment",
        "hire",
        "builders",
        "contractor"
    ],
    "wof:name":"Langton Blasting Compressor Equipment Hire",
    "wof:placetype":"venue"
},
  "geometry": {"coordinates":[144.755004883,-37.5826187134],"type":"Point"}
}