{
  "type": "Feature",
  "properties": {
    "iso:country":"AU",
    "sg:address":"897 Brooker Hwy",
    "sg:city":"Berriedale",
    "sg:classifiers":[
        {
            "category":"Travel",
            "subcategory":"Hotels & Motels",
            "type":"Entertainment"
        }
    ],
    "sg:phone":"+61 3 6272 6721",
    "sg:postcode":"7011",
    "sg:province":"TAS",
    "wof:name":"Comfort Inn Riverfront",
    "wof:placetype":"venue"
},
  "geometry": {"coordinates":[147.25918579099999,-42.8171539307],"type":"Point"}
}