{
  "type": "Feature",
  "properties": {
    "iso:country":"AU",
    "sg:address":"Shed 2, 40 Clifford St",
    "sg:city":"Toowoomba",
    "sg:classifiers":[
        {
            "category":"Manufacturing",
            "subcategory":"Paper Products",
            "type":"Manufacturing & Wholesale Goods"
        }
    ],
    "sg:phone":"+61 7 4632 0290",
    "sg:postcode":"4352",
    "sg:province":"QLD",
    "sg:tags":[
        "disposable"
    ],
    "wof:name":"Emital Distributors",
    "wof:placetype":"venue"
},
  "geometry": {"coordinates":[151.946899,-27.564402],"type":"Point"}
}