{
  "type": "Feature",
  "properties": {
    "iso:country":"AU",
    "sg:address":"50 Greenvalley Crs",
    "sg:city":"Hampton Park",
    "sg:classifiers":[
        {
            "category":"Professional",
            "subcategory":"Computer Services",
            "type":"Services"
        }
    ],
    "sg:phone":"+61 418 553 039",
    "sg:postcode":"3976",
    "sg:province":"VIC",
    "sg:tags":[
        "tele-communications",
        "consultant"
    ],
    "wof:name":"Compaq Communications",
    "wof:placetype":"venue"
},
  "geometry": {"coordinates":[145.26762390100001,-38.0422897339],"type":"Point"}
}