{
  "type": "Feature",
  "properties": {
    "iso:country":"AU",
    "sg:address":"Level 4, 20 Hunter St",
    "sg:city":"Sydney",
    "sg:classifiers":[
        {
            "category":"Professional",
            "subcategory":"Employment Agencies",
            "type":"Services"
        }
    ],
    "sg:phone":"+61 2 9346 9555",
    "sg:postcode":"2000",
    "sg:province":"NSW",
    "wof:name":"Jarrah Psychology",
    "wof:placetype":"venue"
},
  "geometry": {"coordinates":[151.20802307100001,-33.8654441833],"type":"Point"}
}