{
  "type": "Feature",
  "properties": {
    "addr:full":"531 Ruthven St Toowoomba QLD 4350",
    "addr:housenumber":"531",
    "addr:postcode":"4350",
    "addr:street":"Ruthven St",
    "iso:country":"AU",
    "sg:address":"531 Ruthven St",
    "sg:city":"Toowoomba",
    "sg:classifiers":[
        {
            "category":"Museum",
            "type":"Entertainment"
        }
    ],
    "sg:phone":"+61 7 4688 6652",
    "sg:postcode":"4350",
    "sg:province":"QLD",
    "wof:name":"Toowoomba Regional Art Gallery",
    "wof:placetype":"venue"
},
  "geometry": {"coordinates":[151.952316,-27.568119],"type":"Point"}
}