{
  "type": "Feature",
  "properties": {
    "iso:country":"AU",
    "sg:address":"Hervey Bay Marina Complex",
    "sg:city":"Hervey Bay",
    "sg:classifiers":[
        {
            "category":"Travel",
            "subcategory":"Travel Agent",
            "type":"Entertainment"
        }
    ],
    "sg:phone":"+61 7 4128 9800",
    "sg:postcode":"4655",
    "sg:province":"QLD",
    "sg:tags":[
        "tour",
        "holiday",
        "adventure"
    ],
    "wof:name":"Fraser Coast Tour Booking Office",
    "wof:placetype":"venue"
},
  "geometry": {"coordinates":[152.838257,-25.287661],"type":"Point"}
}