{
  "type": "Feature",
  "properties": {
    "addr:full":"113 Ross St Tatura VIC 3616",
    "addr:housenumber":"113",
    "addr:postcode":"3616",
    "addr:street":"Ross St",
    "iso:country":"AU",
    "sg:address":"113 Ross St",
    "sg:city":"Tatura",
    "sg:classifiers":[
        {
            "category":"Farming",
            "subcategory":"Farm & Veterinary Services",
            "type":"Manufacturing & Wholesale Goods"
        }
    ],
    "sg:phone":"+61 3 5824 3400",
    "sg:postcode":"3616",
    "sg:province":"VIC",
    "sg:tags":[
        "irrigation",
        "reticulation",
        "system"
    ],
    "wof:name":"Dairy Technology Services",
    "wof:placetype":"venue"
},
  "geometry": {"coordinates":[145.22247314399999,-36.4463157654],"type":"Point"}
}