{
  "type": "Feature",
  "properties": {
    "addr:full":"10 Main St Mermaid Beach QLD 4218",
    "addr:housenumber":"10",
    "addr:postcode":"4218",
    "addr:street":"Main St",
    "iso:country":"AU",
    "sg:address":"10 Main St",
    "sg:city":"Mermaid Beach",
    "sg:classifiers":[
        {
            "category":"Professional",
            "subcategory":"Computer Services",
            "type":"Services"
        }
    ],
    "sg:phone":"+61 7 5554 5476",
    "sg:postcode":"4218",
    "sg:province":"QLD",
    "sg:tags":[
        "technical",
        "support"
    ],
    "wof:name":"Bluejet Computers",
    "wof:placetype":"venue"
},
  "geometry": {"coordinates":[153.43060302699999,-28.0284976959],"type":"Point"}
}