{
  "type": "Feature",
  "properties": {
    "addr:full":"Nerrena Rd Dumbalk VIC 3956",
    "addr:postcode":"3956",
    "addr:street":"Nerrena Rd",
    "iso:country":"AU",
    "sg:address":"Nerrena Rd",
    "sg:city":"Dumbalk",
    "sg:classifiers":[
        {
            "category":"Farming",
            "subcategory":"Farm",
            "type":"Manufacturing & Wholesale Goods"
        }
    ],
    "sg:phone":"+61 3 5664 4213",
    "sg:postcode":"3956",
    "sg:province":"VIC",
    "sg:tags":[
        "farmer"
    ],
    "wof:name":"Fitzgerald S",
    "wof:placetype":"venue"
},
  "geometry": {"coordinates":[146.09390258799999,-38.5337181091],"type":"Point"}
}