{
  "type": "Feature",
  "properties": {
    "addr:full":"162 Edward St Brisbane QLD 4000",
    "addr:housenumber":"162",
    "addr:postcode":"4000",
    "addr:street":"Edward St",
    "iso:country":"AU",
    "sg:address":"162 Edward St",
    "sg:city":"Brisbane",
    "sg:classifiers":[
        {
            "category":"Banks & Credit Unions",
            "subcategory":"Financial Services",
            "type":"Services"
        }
    ],
    "sg:phone":"+61 7 3229 0500",
    "sg:postcode":"4000",
    "sg:province":"QLD",
    "sg:tags":[
        "building",
        "society"
    ],
    "wof:name":"First Australian Building Society Limited",
    "wof:placetype":"venue"
},
  "geometry": {"coordinates":[153.027786255,-27.4694042206],"type":"Point"}
}