{
  "type": "Feature",
  "properties": {
    "iso:country":"AU",
    "sg:address":"127 City Rd",
    "sg:city":"Beenleigh",
    "sg:classifiers":[
        {
            "category":"Banks & Credit Unions",
            "subcategory":"Financial Services",
            "type":"Services"
        }
    ],
    "sg:phone":"+61 7 3807 0331",
    "sg:postcode":"4207",
    "sg:province":"QLD",
    "sg:tags":[
        "planning"
    ],
    "wof:name":"Michael Crandon",
    "wof:placetype":"venue"
},
  "geometry": {"coordinates":[153.202026367,-27.7154636383],"type":"Point"}
}