{
  "type": "Feature",
  "properties": {
    "iso:country":"AU",
    "sg:address":"45 Adelong Rd",
    "sg:city":"Shailer Park",
    "sg:classifiers":[
        {
            "category":"Utilities",
            "subcategory":"Electric",
            "type":"Services"
        }
    ],
    "sg:phone":"+61 7 3801 3115",
    "sg:postcode":"4128",
    "sg:province":"QLD",
    "sg:tags":[
        "electrical",
        "contractor"
    ],
    "wof:name":"D.E.W. Electrical",
    "wof:placetype":"venue"
},
  "geometry": {"coordinates":[153.18272399899999,-27.6539459229],"type":"Point"}
}