{
  "type": "Feature",
  "properties": {
    "addr:full":"Unit 1/ 49 Boyland Ave Coopers Plains QLD 4108",
    "addr:postcode":"4108",
    "addr:street":"49 Boyland Ave",
    "iso:country":"AU",
    "sg:address":"Unit 1/ 49 Boyland Ave",
    "sg:city":"Coopers Plains",
    "sg:classifiers":[
        {
            "category":"Manufacturing",
            "subcategory":"Rubber & Plastics",
            "type":"Manufacturing & Wholesale Goods"
        }
    ],
    "sg:phone":"+61 7 3275 1611",
    "sg:postcode":"4108",
    "sg:province":"QLD",
    "sg:tags":[
        "wholesaler",
        "product",
        "mfrs"
    ],
    "sg:website":"http://www.magnaplas.com",
    "wof:name":"Magna Plas Pty Ltd",
    "wof:placetype":"venue"
},
  "geometry": {"coordinates":[153.02554321299999,-27.564081192],"type":"Point"}
}