{
  "type": "Feature",
  "properties": {
    "addr:full":"26 Preston St Penrith NSW 2750",
    "addr:housenumber":"26",
    "addr:postcode":"2750",
    "addr:street":"Preston St",
    "iso:country":"AU",
    "sg:address":"26 Preston St",
    "sg:city":"Penrith",
    "sg:classifiers":[
        {
            "category":"Retail",
            "subcategory":"Auto Repair",
            "type":"Services"
        }
    ],
    "sg:phone":"+61 2 4732 1716",
    "sg:postcode":"2750",
    "sg:province":"NSW",
    "sg:tags":[
        "clutch",
        "brake"
    ],
    "wof:name":"Holland Don Automotive",
    "wof:placetype":"venue"
},
  "geometry": {"coordinates":[150.686645508,-33.7632675171],"type":"Point"}
}