{
  "type": "Feature",
  "properties": {
    "addr:full":"2 El Paso St Bardon QLD 4065",
    "addr:housenumber":"2",
    "addr:postcode":"4065",
    "addr:street":"El Paso St",
    "iso:country":"AU",
    "sg:address":"2 El Paso St",
    "sg:city":"Bardon",
    "sg:classifiers":[
        {
            "category":"Building & Trades",
            "subcategory":"Landscaping Services",
            "type":"Services"
        }
    ],
    "sg:phone":"+61 7 3369 4579",
    "sg:postcode":"4065",
    "sg:province":"QLD",
    "sg:tags":[
        "architect",
        "landscape"
    ],
    "wof:name":"Chenoweth A R F",
    "wof:placetype":"venue"
},
  "geometry": {"coordinates":[152.971832275,-27.4565181732],"type":"Point"}
}