{
  "type": "Feature",
  "properties": {
    "iso:country":"AU",
    "sg:address":"16 Clements Ave",
    "sg:city":"Bundoora",
    "sg:classifiers":[
        {
            "category":"Retail",
            "subcategory":"Auto Repair",
            "type":"Services"
        }
    ],
    "sg:phone":"+61 3 9467 3433",
    "sg:postcode":"3083",
    "sg:province":"VIC",
    "sg:tags":[
        "beater",
        "painter",
        "panel"
    ],
    "wof:name":"Paul J Panels",
    "wof:placetype":"venue"
},
  "geometry": {"coordinates":[145.07325744600001,-37.7016067505],"type":"Point"}
}