{
  "type": "Feature",
  "properties": {
    "iso:country":"AU",
    "sg:address":"Level 4, 100 Eagle St",
    "sg:city":"Brisbane",
    "sg:classifiers":[
        {
            "category":"Social Services",
            "subcategory":"Adult Care",
            "type":"Services"
        }
    ],
    "sg:phone":"+61 7 3100 1303",
    "sg:postcode":"4000",
    "sg:province":"QLD",
    "sg:tags":[
        "aged"
    ],
    "wof:name":"Clinical One",
    "wof:placetype":"venue"
},
  "geometry": {"coordinates":[153.030059814,-27.4675216675],"type":"Point"}
}