{
  "type": "Feature",
  "properties": {
    "addr:full":"350 Clovelly Rd Clovelly NSW 2031",
    "addr:housenumber":"350",
    "addr:postcode":"2031",
    "addr:street":"Clovelly Rd",
    "iso:country":"AU",
    "sg:address":"350 Clovelly Rd",
    "sg:city":"Clovelly",
    "sg:classifiers":[
        {
            "category":"Fast Food",
            "type":"Food & Drink"
        }
    ],
    "sg:phone":"+61 2 9665 6558",
    "sg:postcode":"2031",
    "sg:province":"NSW",
    "sg:tags":[
        "away",
        "take"
    ],
    "wof:name":"Jilted Anchovy, The",
    "wof:placetype":"venue"
},
  "geometry": {"coordinates":[151.26507568400001,-33.9137191772],"type":"Point"}
}