{
  "type": "Feature",
  "properties": {
    "iso:country":"AU",
    "sg:address":"105 Peruse Rd",
    "sg:city":"Randwick",
    "sg:classifiers":[
        {
            "category":"Government",
            "subcategory":"Court House",
            "type":"Public Place"
        }
    ],
    "sg:phone":"+61 418 466 049",
    "sg:postcode":"2031",
    "sg:province":"NSW",
    "sg:tags":[
        "personal",
        "marriage",
        "family",
        "counselling"
    ],
    "wof:name":"Divorce Recovery Centre",
    "wof:placetype":"venue"
},
  "geometry": {"coordinates":[151.24336242699999,-33.9216842651],"type":"Point"}
}