{
  "type": "Feature",
  "properties": {
    "addr:full":"Playford Ave Whyalla SA 5600",
    "addr:postcode":"5600",
    "addr:street":"Playford Ave",
    "iso:country":"AU",
    "sg:address":"Playford Ave",
    "sg:city":"Whyalla",
    "sg:classifiers":[
        {
            "category":"Travel",
            "subcategory":"Hotels & Motels",
            "type":"Entertainment"
        }
    ],
    "sg:phone":"+61 8 8645 7188",
    "sg:postcode":"5600",
    "sg:province":"SA",
    "sg:tags":[
        "accommodation"
    ],
    "wof:name":"Hotel Eyre",
    "wof:placetype":"venue"
},
  "geometry": {"coordinates":[137.56300400000001,-33.035633],"type":"Point"}
}