{
  "type": "Feature",
  "properties": {
    "addr:full":"34 First Ave Sawtell NSW 2452",
    "addr:housenumber":"34",
    "addr:postcode":"2452",
    "addr:street":"First Ave",
    "iso:country":"AU",
    "sg:address":"34 First Ave",
    "sg:city":"Sawtell",
    "sg:classifiers":[
        {
            "category":"Health Services",
            "subcategory":"Dentist",
            "type":"Services"
        }
    ],
    "sg:phone":"+61 2 6653 3457",
    "sg:postcode":"2452",
    "sg:province":"NSW",
    "wof:name":"Sawtell Dental Surgery",
    "wof:placetype":"venue"
},
  "geometry": {"coordinates":[153.10067699999999,-30.368593],"type":"Point"}
}