{
  "type": "Feature",
  "properties": {
    "iso:country":"AU",
    "sg:address":"19 Symes St",
    "sg:city":"Kangaroo Flat",
    "sg:classifiers":[
        {
            "category":"Personal",
            "subcategory":"Massage",
            "type":"Services"
        }
    ],
    "sg:phone":"+61 3 5447 9954",
    "sg:postcode":"3555",
    "sg:province":"VIC",
    "sg:tags":[
        "therapy"
    ],
    "wof:name":"Corazon Gyger",
    "wof:placetype":"venue"
},
  "geometry": {"coordinates":[144.23710632300001,-36.810459137],"type":"Point"}
}