{
  "type": "Feature",
  "properties": {
    "addr:full":"Corringal Rd Newmerella VIC 3886",
    "addr:postcode":"3886",
    "addr:street":"Corringal Rd",
    "iso:country":"AU",
    "sg:address":"Corringal Rd",
    "sg:city":"Newmerella",
    "sg:classifiers":[
        {
            "category":"Food & Beverages",
            "subcategory":"Specialty",
            "type":"Retail Goods"
        }
    ],
    "sg:phone":"+61 3 5154 2317",
    "sg:postcode":"3886",
    "sg:province":"VIC",
    "sg:tags":[
        "product",
        "health"
    ],
    "wof:name":"Judy Dench",
    "wof:placetype":"venue"
},
  "geometry": {"coordinates":[148.423904419,-37.7514457703],"type":"Point"}
}