{
  "type": "Feature",
  "properties": {
    "iso:country":"AU",
    "sg:address":"Cnr Newcastle & Stirling Sts",
    "sg:city":"Perth",
    "sg:classifiers":[
        {
            "category":"Professional",
            "type":"Services"
        }
    ],
    "sg:phone":"+61 8 9428 2000",
    "sg:postcode":"6000",
    "sg:province":"WA",
    "sg:tags":[
        "mail",
        "contractor"
    ],
    "wof:name":"HPA (Hermes Precisa Pty Ltd)",
    "wof:placetype":"venue"
},
  "geometry": {"coordinates":[115.858291626,-31.9449977875],"type":"Point"}
}