{
  "type": "Feature",
  "properties": {
    "addr:full":"262 Grange Rd Flinders Park SA 5025",
    "addr:housenumber":"262",
    "addr:postcode":"5025",
    "addr:street":"Grange Rd",
    "iso:country":"AU",
    "sg:address":"262 Grange Rd",
    "sg:city":"Flinders Park",
    "sg:classifiers":[
        {
            "category":"Manufacturing",
            "subcategory":"Building Materials",
            "type":"Manufacturing & Wholesale Goods"
        }
    ],
    "sg:phone":"+61 8 8352 4466",
    "sg:postcode":"5025",
    "sg:province":"SA",
    "sg:tags":[
        "equipment",
        "handling"
    ],
    "wof:name":"Demag Cranes & Components Pty Ltd",
    "wof:placetype":"venue"
},
  "geometry": {"coordinates":[138.53793335,-34.9053344727],"type":"Point"}
}