{
  "type": "Feature",
  "properties": {
    "addr:full":"19 Hulett St Sunshine VIC 3020",
    "addr:housenumber":"19",
    "addr:postcode":"3020",
    "addr:street":"Hulett St",
    "iso:country":"AU",
    "sg:address":"19 Hulett St",
    "sg:city":"Sunshine",
    "sg:classifiers":[
        {
            "category":"Manufacturing",
            "subcategory":"Furniture",
            "type":"Manufacturing & Wholesale Goods"
        }
    ],
    "sg:phone":"+61 3 9312 7050",
    "sg:postcode":"3020",
    "sg:province":"VIC",
    "sg:tags":[
        "builder",
        "designer",
        "custom"
    ],
    "wof:name":"Ace Craft",
    "wof:placetype":"venue"
},
  "geometry": {"coordinates":[144.811035,-37.772755],"type":"Point"}
}