{
  "type": "Feature",
  "properties": {
    "addr:full":"123 Alfred St Parramatta NSW 2150",
    "addr:housenumber":"123",
    "addr:postcode":"2150",
    "addr:street":"Alfred St",
    "iso:country":"AU",
    "sg:address":"123 Alfred St",
    "sg:city":"Parramatta",
    "sg:classifiers":[
        {
            "category":"Fast Food",
            "type":"Food & Drink"
        }
    ],
    "sg:phone":"+61 2 9893 9693",
    "sg:postcode":"2150",
    "sg:province":"NSW",
    "sg:tags":[
        "away",
        "take"
    ],
    "wof:name":"Eatery 33",
    "wof:placetype":"venue"
},
  "geometry": {"coordinates":[151.016555786,-33.8199119568],"type":"Point"}
}