{
  "type": "Feature",
  "properties": {
    "addr:full":"Cnr Playhouse Lane & Gilles St Adelaide SA 5001",
    "addr:postcode":"5001",
    "addr:street":"St",
    "iso:country":"AU",
    "sg:address":"Cnr Playhouse Lane & Gilles St",
    "sg:city":"Adelaide",
    "sg:classifiers":[
        {
            "category":"Retail",
            "subcategory":"Event Space",
            "type":"Services"
        }
    ],
    "sg:phone":"+61 8 8203 9888",
    "sg:postcode":"5001",
    "sg:province":"SA",
    "sg:tags":[
        "function",
        "organiser"
    ],
    "wof:name":"Queen's Theatre",
    "wof:placetype":"venue"
},
  "geometry": {"coordinates":[138.60040283199999,-34.9342918396],"type":"Point"}
}