{
  "type": "Feature",
  "properties": {
    "iso:country":"AU",
    "sg:address":"4 Doyle Pl",
    "sg:city":"Baulkham Hills",
    "sg:classifiers":[
        {
            "category":"Building & Trades",
            "subcategory":"Construction",
            "type":"Services"
        }
    ],
    "sg:phone":"+61 412 352 250",
    "sg:postcode":"2153",
    "sg:province":"NSW",
    "sg:tags":[
        "plasterboard",
        "plasterer",
        "fixer"
    ],
    "wof:name":"Hyclass Ceiling Services Pty Ltd",
    "wof:placetype":"venue"
},
  "geometry": {"coordinates":[150.89862060600001,-33.7403945923],"type":"Point"}
}