{
  "type": "Feature",
  "properties": {
    "iso:country":"AU",
    "sg:address":"14 Seeger St",
    "sg:city":"Morphett Vale",
    "sg:classifiers":[
        {
            "category":"Building & Trades",
            "subcategory":"Cleaning & Sanitation",
            "type":"Services"
        }
    ],
    "sg:phone":"+61 411 119 619",
    "sg:postcode":"5162",
    "sg:province":"SA",
    "sg:tags":[
        "industrial",
        "commercial",
        "contractor"
    ],
    "wof:name":"Alan Jones Cleaning",
    "wof:placetype":"venue"
},
  "geometry": {"coordinates":[138.51141357399999,-35.109954834],"type":"Point"}
}