{
  "type": "Feature",
  "properties": {
    "iso:country":"AU",
    "sg:address":"Cnr Sage & Sunshine Ave",
    "sg:city":"Kealba",
    "sg:classifiers":[
        {
            "category":"Health Services",
            "subcategory":"Health Practitioner",
            "type":"Services"
        }
    ],
    "sg:phone":"+61 3 9366 8000",
    "sg:postcode":"3021",
    "sg:province":"VIC",
    "sg:tags":[
        "physiotherapist"
    ],
    "wof:name":"Gioskos Steve",
    "wof:placetype":"venue"
},
  "geometry": {"coordinates":[144.829193,-37.745979],"type":"Point"}
}