{
  "type": "Feature",
  "properties": {
    "addr:full":"Windang Rd Windang NSW 2528",
    "addr:postcode":"2528",
    "addr:street":"Windang Rd",
    "iso:country":"AU",
    "sg:address":"Windang Rd",
    "sg:city":"Windang",
    "sg:classifiers":[
        {
            "category":"Building & Trades",
            "subcategory":"Construction",
            "type":"Services"
        }
    ],
    "sg:phone":"+61 415 145 324",
    "sg:postcode":"2528",
    "sg:province":"NSW",
    "sg:tags":[
        "waterproofing",
        "contractor"
    ],
    "wof:name":"Overflow Proofing",
    "wof:placetype":"venue"
},
  "geometry": {"coordinates":[150.868942261,-34.5309143066],"type":"Point"}
}