{
  "type": "Feature",
  "properties": {
    "addr:full":"1A Pacific Hwy Wyong NSW 2259",
    "addr:housenumber":"1a",
    "addr:postcode":"2259",
    "addr:street":"Pacific Hwy",
    "iso:country":"AU",
    "sg:address":"1A Pacific Hwy",
    "sg:city":"Wyong",
    "sg:classifiers":[
        {
            "category":"Government",
            "subcategory":"Court House",
            "type":"Public Place"
        }
    ],
    "sg:phone":"+61 2 4351 0116",
    "sg:postcode":"2259",
    "sg:province":"NSW",
    "sg:tags":[
        "personal",
        "marriage",
        "family",
        "counselling"
    ],
    "wof:name":"Wesley Counselling Services Central Coast",
    "wof:placetype":"venue"
},
  "geometry": {"coordinates":[151.424285889,-33.2883453369],"type":"Point"}
}