{
  "type": "Feature",
  "properties": {
    "iso:country":"AU",
    "sg:address":"64 Poinciana Ave",
    "sg:city":"Tewantin",
    "sg:classifiers":[
        {
            "category":"Banks & Credit Unions",
            "subcategory":"Financial Services",
            "type":"Services"
        }
    ],
    "sg:phone":"+61 7 5474 1455",
    "sg:postcode":"4565",
    "sg:province":"QLD",
    "sg:tags":[
        "planning"
    ],
    "wof:name":"Holman McGregor Financial Services",
    "wof:placetype":"venue"
},
  "geometry": {"coordinates":[153.03521728499999,-26.3910999298],"type":"Point"}
}