{
  "type": "Feature",
  "properties": {
    "addr:full":"22 Clifton St Nedlands WA 6009",
    "addr:housenumber":"22",
    "addr:postcode":"6009",
    "addr:street":"Clifton St",
    "iso:country":"AU",
    "sg:address":"22 Clifton St",
    "sg:city":"Nedlands",
    "sg:classifiers":[
        {
            "category":"Shopping",
            "subcategory":"Computers & Home Electronics",
            "type":"Retail Goods"
        }
    ],
    "sg:phone":"+61 8 9386 3371",
    "sg:postcode":"6009",
    "sg:province":"WA",
    "sg:tags":[
        "equipment",
        "multimedia"
    ],
    "wof:name":"Mariposa New Media Concepts",
    "wof:placetype":"venue"
},
  "geometry": {"coordinates":[115.811531,-31.972279],"type":"Point"}
}