{
  "type": "Feature",
  "properties": {
    "iso:country":"AU",
    "sg:address":"43- 45 Kylta Rd",
    "sg:city":"Heidelberg West",
    "sg:classifiers":[
        {
            "category":"Manufacturing",
            "subcategory":"Tools & Machinery",
            "type":"Manufacturing & Wholesale Goods"
        }
    ],
    "sg:phone":"+61 3 9458 2814",
    "sg:postcode":"3081",
    "sg:province":"VIC",
    "sg:tags":[
        "toolmaker"
    ],
    "wof:name":"Melville Tooling",
    "wof:placetype":"venue"
},
  "geometry": {"coordinates":[145.04466247600001,-37.7317695618],"type":"Point"}
}