{
  "type": "Feature",
  "properties": {
    "addr:full":"49 Wulagi Crs Wulagi NT 0812",
    "addr:housenumber":"49",
    "addr:postcode":"nt 0812",
    "addr:street":"Wulagi Crs",
    "iso:country":"AU",
    "sg:address":"49 Wulagi Crs",
    "sg:city":"Wulagi",
    "sg:classifiers":[
        {
            "category":"Professional",
            "type":"Services"
        }
    ],
    "sg:phone":"+61 408 892 200",
    "sg:postcode":"0812",
    "sg:province":"NT",
    "sg:tags":[
        "courier"
    ],
    "wof:name":"Speedy Bee Couriers",
    "wof:placetype":"venue"
},
  "geometry": {"coordinates":[130.89434800000001,-12.384549],"type":"Point"}
}