{
  "type": "Feature",
  "properties": {
    "addr:full":"88 Wardell Rd Dulwich Hill NSW 2203",
    "addr:housenumber":"88",
    "addr:postcode":"2203",
    "addr:street":"Wardell Rd",
    "iso:country":"AU",
    "sg:address":"88 Wardell Rd",
    "sg:city":"Dulwich Hill",
    "sg:classifiers":[
        {
            "category":"Professional",
            "subcategory":"Computer Services",
            "type":"Services"
        }
    ],
    "sg:phone":"+61 500 550 075",
    "sg:postcode":"2203",
    "sg:province":"NSW",
    "sg:tags":[
        "consultant",
        "system"
    ],
    "wof:name":"Kraus Christian",
    "wof:placetype":"venue"
},
  "geometry": {"coordinates":[151.13829000000001,-33.913258],"type":"Point"}
}