{
  "type": "Feature",
  "properties": {
    "addr:full":"149 Centre Dandenong Rd Cheltenham VIC 3192",
    "addr:housenumber":"149",
    "addr:postcode":"3192",
    "addr:street":"Centre Dandenong Rd",
    "iso:country":"AU",
    "sg:address":"149 Centre Dandenong Rd",
    "sg:city":"Cheltenham",
    "sg:classifiers":[
        {
            "category":"Health Services",
            "subcategory":"Optometrist",
            "type":"Services"
        }
    ],
    "sg:phone":"+61 3 9583 3596",
    "sg:postcode":"3192",
    "sg:province":"VIC",
    "wof:name":"Lamont & Walters Optometrists",
    "wof:placetype":"venue"
},
  "geometry": {"coordinates":[145.074020386,-37.967502594],"type":"Point"}
}