{
  "type": "Feature",
  "properties": {
    "addr:full":"Un C24 / 148 Old Pittwater Rd Brookvale NSW 2100",
    "addr:housenumber":"/ 148",
    "addr:postcode":"2100",
    "addr:street":"Old Pittwater Rd",
    "iso:country":"AU",
    "sg:address":"Un C24 / 148 Old Pittwater Rd",
    "sg:city":"Brookvale",
    "sg:classifiers":[
        {
            "category":"Shopping",
            "subcategory":"Beauty & Cosmetics",
            "type":"Retail Goods"
        }
    ],
    "sg:phone":"+61 2 9939 5622",
    "sg:postcode":"2100",
    "sg:province":"NSW",
    "wof:name":"Fresh Face Skin Care",
    "wof:placetype":"venue"
},
  "geometry": {"coordinates":[151.26280212399999,-33.7680854797],"type":"Point"}
}