{
  "type": "Feature",
  "properties": {
    "iso:country":"AU",
    "sg:address":"1 Baker St",
    "sg:city":"Banksmeadow",
    "sg:classifiers":[
        {
            "category":"Professional",
            "type":"Services"
        }
    ],
    "sg:phone":"+61 2 9666 3933",
    "sg:postcode":"2019",
    "sg:province":"NSW",
    "sg:tags":[
        "coating",
        "powder"
    ],
    "wof:name":"A Australian Powder Coaters",
    "wof:placetype":"venue"
},
  "geometry": {"coordinates":[151.216674805,-33.943157196],"type":"Point"}
}