{
  "type": "Feature",
  "properties": {
    "addr:full":"Ste 37, 2nd Floor, Trinity Arcade, 671 Hay St Mall Perth City WA 6000",
    "addr:housenumber":"671",
    "addr:postcode":"6000",
    "addr:street":"Hay St Mall",
    "iso:country":"AU",
    "sg:address":"Ste 37, 2nd Floor, Trinity Arcade, 671 Hay St Mall",
    "sg:city":"Perth City",
    "sg:classifiers":[
        {
            "category":"Manufacturing",
            "subcategory":"Jewelry",
            "type":"Manufacturing & Wholesale Goods"
        }
    ],
    "sg:phone":"+61 8 9481 4338",
    "sg:postcode":"6000",
    "sg:province":"WA",
    "sg:tags":[
        "mfrg",
        "jeweller"
    ],
    "wof:name":"Werner's Manufacturing Jewellers",
    "wof:placetype":"venue"
},
  "geometry": {"coordinates":[115.848747253,-31.9717483521],"type":"Point"}
}