{
  "type": "Feature",
  "properties": {
    "iso:country":"AU",
    "sg:address":"4/ 18 Minter St",
    "sg:city":"Canterbury",
    "sg:classifiers":[
        {
            "category":"Building & Trades",
            "subcategory":"Plumbing",
            "type":"Services"
        }
    ],
    "sg:phone":"+61 2 9718 2254",
    "sg:postcode":"2193",
    "sg:province":"NSW",
    "sg:tags":[
        "plumber",
        "gasfitters"
    ],
    "wof:name":"Freestyle Plumbing",
    "wof:placetype":"venue"
},
  "geometry": {"coordinates":[151.12171900000001,-33.90704],"type":"Point"}
}