{
  "type": "Feature",
  "properties": {
    "addr:full":"48 Curran Rd Blacktown NSW 2148",
    "addr:housenumber":"48",
    "addr:postcode":"2148",
    "addr:street":"Curran Rd",
    "iso:country":"AU",
    "sg:address":"48 Curran Rd",
    "sg:city":"Blacktown",
    "sg:classifiers":[
        {
            "category":"Building & Trades",
            "subcategory":"Construction",
            "type":"Services"
        }
    ],
    "sg:phone":"+61 2 9831 5482",
    "sg:postcode":"2148",
    "sg:province":"NSW",
    "sg:tags":[
        "brick",
        "paving"
    ],
    "wof:name":"Dave Michies Paving",
    "wof:placetype":"venue"
},
  "geometry": {"coordinates":[150.893188477,-33.7543449402],"type":"Point"}
}