{
  "type": "Feature",
  "properties": {
    "iso:country":"AU",
    "sg:address":"Shop 34",
    "sg:city":"Forrestfield Forum Shppng Cntr Forrestfield",
    "sg:classifiers":[
        {
            "category":"Travel",
            "subcategory":"Travel Agent",
            "type":"Entertainment"
        }
    ],
    "sg:phone":"+61 8 9453 1088",
    "sg:postcode":"6058",
    "sg:province":"WA",
    "sg:tags":[
        "consultant"
    ],
    "wof:name":"Golden Sands Travel",
    "wof:placetype":"venue"
},
  "geometry": {"coordinates":[116.00077819800001,-31.9696292877],"type":"Point"}
}