{
  "type": "Feature",
  "properties": {
    "iso:country":"AU",
    "sg:address":"Level 1/ 74 Clarence St",
    "sg:city":"Port Macquarie",
    "sg:classifiers":[
        {
            "category":"Restaurant",
            "type":"Food & Drink"
        }
    ],
    "sg:phone":"+61 2 6584 1422",
    "sg:postcode":"2444",
    "sg:province":"NSW",
    "wof:name":"Bliss Restaurant",
    "wof:placetype":"venue"
},
  "geometry": {"coordinates":[152.906128,-31.429422],"type":"Point"}
}