{
  "type": "Feature",
  "properties": {
    "addr:full":"83- 85 Main Rd Lower Plenty VIC 3093",
    "addr:housenumber":"85",
    "addr:postcode":"3093",
    "addr:street":"Main Rd",
    "iso:country":"AU",
    "sg:address":"83- 85 Main Rd",
    "sg:city":"Lower Plenty",
    "sg:classifiers":[
        {
            "category":"Personal",
            "subcategory":"Beauty Salon",
            "type":"Services"
        }
    ],
    "sg:phone":"+61 3 9434 5262",
    "sg:postcode":"3093",
    "sg:province":"VIC",
    "sg:tags":[
        "hairdresser"
    ],
    "wof:name":"Scaffidi Hair Design",
    "wof:placetype":"venue"
},
  "geometry": {"coordinates":[145.11257934599999,-37.7273254395],"type":"Point"}
}