{
  "type": "Feature",
  "properties": {
    "iso:country":"AU",
    "sg:address":"2 Strangman Rd",
    "sg:city":"Waikerie",
    "sg:classifiers":[
        {
            "category":"Health Services",
            "subcategory":"Doctor",
            "type":"Services"
        }
    ],
    "sg:phone":"+61 8 8541 3500",
    "sg:postcode":"5330",
    "sg:province":"SA",
    "sg:tags":[
        "medical",
        "practitioner"
    ],
    "wof:name":"Miller A S",
    "wof:placetype":"venue"
},
  "geometry": {"coordinates":[139.98606872600001,-34.1828689575],"type":"Point"}
}