{
  "type": "Feature",
  "properties": {
    "addr:full":"21 Kimberley Pl Gymea Bay NSW 2227",
    "addr:housenumber":"21",
    "addr:postcode":"2227",
    "addr:street":"Kimberley Pl",
    "iso:country":"AU",
    "sg:address":"21 Kimberley Pl",
    "sg:city":"Gymea Bay",
    "sg:classifiers":[
        {
            "category":"Education",
            "subcategory":"Special Training",
            "type":"Public Place"
        }
    ],
    "sg:phone":"+61 400 606 596",
    "sg:postcode":"2227",
    "sg:province":"NSW",
    "sg:tags":[
        "development"
    ],
    "wof:name":"Beattie Ltd",
    "wof:placetype":"venue"
},
  "geometry": {"coordinates":[151.09463500999999,-34.0474777222],"type":"Point"}
}