{
  "type": "Feature",
  "properties": {
    "addr:full":"26 Alex Ave Schofields NSW 2762",
    "addr:housenumber":"26",
    "addr:postcode":"2762",
    "addr:street":"Alex Ave",
    "iso:country":"AU",
    "sg:address":"26 Alex Ave",
    "sg:city":"Schofields",
    "sg:classifiers":[
        {
            "category":"Wholesale",
            "subcategory":"Toys & Hobbies",
            "type":"Manufacturing & Wholesale Goods"
        }
    ],
    "sg:phone":"+61 418 123 777",
    "sg:postcode":"2762",
    "sg:province":"NSW",
    "wof:name":"Rainbow D",
    "wof:placetype":"venue"
},
  "geometry": {"coordinates":[150.88616943400001,-33.7088356018],"type":"Point"}
}