{
  "type": "Feature",
  "properties": {
    "addr:full":"Parkes St Woodstock NSW 2793",
    "addr:postcode":"2793",
    "addr:street":"Parkes St",
    "iso:country":"AU",
    "sg:address":"Parkes St",
    "sg:city":"Woodstock",
    "sg:classifiers":[
        {
            "category":"Shopping",
            "type":"Retail Goods"
        }
    ],
    "sg:phone":"+61 2 6345 0354",
    "sg:postcode":"2793",
    "sg:province":"NSW",
    "sg:tags":[
        "agent",
        "stock"
    ],
    "wof:name":"Dresser & Co",
    "wof:placetype":"venue"
},
  "geometry": {"coordinates":[148.84800720199999,-33.7448616028],"type":"Point"}
}