{
  "type": "Feature",
  "properties": {
    "addr:full":"PO Box 1169 Hartwell VIC 3124",
    "addr:postcode":"3124",
    "iso:country":"AU",
    "sg:address":"PO Box 1169",
    "sg:city":"Hartwell",
    "sg:classifiers":[
        {
            "category":"Building & Trades",
            "subcategory":"Construction",
            "type":"Services"
        }
    ],
    "sg:phone":"+61 3 9889 9710",
    "sg:postcode":"3124",
    "sg:province":"VIC",
    "sg:tags":[
        "contractor"
    ],
    "wof:name":"Sienna Trading Master Builders",
    "wof:placetype":"venue"
},
  "geometry": {"coordinates":[145.067596436,-37.8465805054],"type":"Point"}
}