{
  "type": "Feature",
  "properties": {
    "addr:full":"3 Whitfield St Darwin NT 0800",
    "addr:housenumber":"3",
    "addr:postcode":"nt 0800",
    "addr:street":"Whitfield St",
    "iso:country":"AU",
    "sg:address":"3 Whitfield St",
    "sg:city":"Darwin",
    "sg:classifiers":[
        {
            "category":"Banks & Credit Unions",
            "subcategory":"Bank",
            "type":"Services"
        }
    ],
    "sg:phone":"+61 8 8981 3955",
    "sg:postcode":"0800",
    "sg:province":"NT",
    "sg:tags":[
        "broker",
        "mortgage"
    ],
    "wof:name":"Darwin Home Loans",
    "wof:placetype":"venue"
},
  "geometry": {"coordinates":[130.83966064399999,-12.4588680267],"type":"Point"}
}