{
  "type": "Feature",
  "properties": {
    "iso:country":"AU",
    "sg:address":"20 Divett St",
    "sg:city":"Port Adelaide",
    "sg:classifiers":[
        {
            "category":"Communications",
            "subcategory":"News Services",
            "type":"Services"
        }
    ],
    "sg:phone":"+61 8 8447 7824",
    "sg:postcode":"5015",
    "sg:province":"SA",
    "sg:tags":[
        "information",
        "tourist",
        "attractions"
    ],
    "wof:name":"The Seahorse Farm",
    "wof:placetype":"venue"
},
  "geometry": {"coordinates":[138.506256103,-34.8429107666],"type":"Point"}
}