{
  "type": "Feature",
  "properties": {
    "addr:full":"48-52 Majorie Crt Jimboomba QLD 4280",
    "addr:housenumber":"48-52",
    "addr:postcode":"4280",
    "addr:street":"Majorie Crt",
    "iso:country":"AU",
    "sg:address":"48-52 Majorie Crt",
    "sg:city":"Jimboomba",
    "sg:classifiers":[
        {
            "category":"Food & Beverages",
            "subcategory":"Bakery",
            "type":"Retail Goods"
        }
    ],
    "sg:phone":"+61 411 897 818",
    "sg:postcode":"4280",
    "sg:province":"QLD",
    "sg:tags":[
        "cake",
        "shop",
        "pastry"
    ],
    "wof:name":"Nicole Brady",
    "wof:placetype":"venue"
},
  "geometry": {"coordinates":[152.98460399999999,-27.806179],"type":"Point"}
}