{
  "type": "Feature",
  "properties": {
    "addr:full":"181 Bay St Port Melbourne VIC 3207",
    "addr:housenumber":"181",
    "addr:postcode":"3207",
    "addr:street":"Bay St",
    "iso:country":"AU",
    "sg:address":"181 Bay St",
    "sg:city":"Port Melbourne",
    "sg:classifiers":[
        {
            "category":"Fast Food",
            "type":"Food & Drink"
        }
    ],
    "sg:phone":"+61 3 9646 5050",
    "sg:postcode":"3207",
    "sg:province":"VIC",
    "sg:tags":[
        "away",
        "take"
    ],
    "wof:name":"Noodle Box The",
    "wof:placetype":"venue"
},
  "geometry": {"coordinates":[144.941498,-37.83926],"type":"Point"}
}