{
  "type": "Feature",
  "properties": {
    "addr:full":"42 Reilly La St Peters NSW 2044",
    "addr:housenumber":"42",
    "addr:postcode":"2044",
    "addr:street":"Reilly La",
    "iso:country":"AU",
    "sg:address":"42 Reilly La",
    "sg:city":"St Peters",
    "sg:classifiers":[
        {
            "category":"Home & Garden",
            "subcategory":"Furniture",
            "type":"Retail Goods"
        }
    ],
    "sg:phone":"+61 2 9519 3844",
    "sg:postcode":"2044",
    "sg:province":"NSW",
    "sg:tags":[
        "business"
    ],
    "wof:name":"Rosebery Furniture Pty Ltd",
    "wof:placetype":"venue"
},
  "geometry": {"coordinates":[151.16949500000001,-33.91782],"type":"Point"}
}