{
  "type": "Feature",
  "properties": {
    "addr:full":"Level 8/ 1 Collins St Melbourne VIC 3000",
    "addr:housenumber":"/ 1",
    "addr:postcode":"3000",
    "addr:street":"Collins St",
    "iso:country":"AU",
    "sg:address":"Level 8/ 1 Collins St",
    "sg:city":"Melbourne",
    "sg:classifiers":[
        {
            "category":"Professional",
            "subcategory":"Management & Consulting",
            "type":"Services"
        }
    ],
    "sg:phone":"+61 3 9660 8600",
    "sg:postcode":"3000",
    "sg:province":"VIC",
    "sg:tags":[
        "consultant"
    ],
    "wof:name":"P.G.A. Management",
    "wof:placetype":"venue"
},
  "geometry": {"coordinates":[144.97392273,-37.8134498596],"type":"Point"}
}