{
  "type": "Feature",
  "properties": {
    "addr:full":"21473 Tasman Hwy Four Mile Creek TAS 7215",
    "addr:housenumber":"21473",
    "addr:postcode":"7215",
    "addr:street":"Tasman Hwy",
    "iso:country":"AU",
    "sg:address":"21473 Tasman Hwy",
    "sg:city":"Four Mile Creek",
    "sg:classifiers":[
        {
            "category":"Building & Trades",
            "subcategory":"Construction",
            "type":"Services"
        }
    ],
    "sg:phone":"+61 3 6372 2669",
    "sg:postcode":"7215",
    "sg:province":"TAS",
    "sg:tags":[
        "contractor"
    ],
    "wof:name":"C G W Building",
    "wof:placetype":"venue"
},
  "geometry": {"coordinates":[148.31024199999999,-41.583782],"type":"Point"}
}