{
  "type": "Feature",
  "properties": {
    "addr:full":"226 Alexandra St North Rockhampton QLD 4701",
    "addr:housenumber":"226",
    "addr:postcode":"4701",
    "addr:street":"Alexandra St North",
    "iso:country":"AU",
    "sg:address":"226 Alexandra St",
    "sg:city":"North Rockhampton",
    "sg:classifiers":[
        {
            "category":"Professional",
            "type":"Services"
        }
    ],
    "sg:phone":"+61 7 4931 4066",
    "sg:postcode":"4701",
    "sg:province":"QLD",
    "sg:tags":[
        "shop",
        "fitting"
    ],
    "wof:name":"Kawana Joinery",
    "wof:placetype":"venue"
},
  "geometry": {"coordinates":[150.50498962399999,-23.3382263184],"type":"Point"}
}