{
  "type": "Feature",
  "properties": {
    "iso:country":"AU",
    "sg:address":"9 Warralong Ave",
    "sg:city":"Greensborough",
    "sg:classifiers":[
        {
            "category":"Professional",
            "subcategory":"Employment Agencies",
            "type":"Services"
        }
    ],
    "sg:phone":"+61 3 9444 6427",
    "sg:postcode":"3088",
    "sg:province":"VIC",
    "sg:tags":[
        "provider",
        "internet"
    ],
    "wof:name":"Bluesky Web Solutions",
    "wof:placetype":"venue"
},
  "geometry": {"coordinates":[145.09327697800001,-37.7169494629],"type":"Point"}
}