{
  "type": "Feature",
  "properties": {
    "iso:country":"AU",
    "sg:address":"Inner Vision Health Centre, 53 Grand Blv",
    "sg:city":"Joondalup",
    "sg:classifiers":[
        {
            "category":"Personal",
            "subcategory":"Beauty Salon",
            "type":"Services"
        }
    ],
    "sg:phone":"+61 8 9301 2269",
    "sg:postcode":"6027",
    "sg:province":"WA",
    "wof:name":"Rhona's Electrolysis & Beauty",
    "wof:placetype":"venue"
},
  "geometry": {"coordinates":[115.769828796,-31.7364578247],"type":"Point"}
}