{
  "type": "Feature",
  "properties": {
    "iso:country":"AU",
    "sg:address":"31 First Ave",
    "sg:city":"Cape Woolamai",
    "sg:classifiers":[
        {
            "category":"Building & Trades",
            "subcategory":"Construction",
            "type":"Services"
        }
    ],
    "sg:phone":"+61 421 423 738",
    "sg:postcode":"3925",
    "sg:province":"VIC",
    "sg:tags":[
        "plasterboard",
        "plasterer",
        "fixer"
    ],
    "wof:name":"Colonnades Plaster Bass Coast",
    "wof:placetype":"venue"
},
  "geometry": {"coordinates":[145.33282470699999,-38.5260772705],"type":"Point"}
}