{
  "type": "Feature",
  "properties": {
    "addr:full":"40 Gillies St Maryborough VIC 3465",
    "addr:housenumber":"40",
    "addr:postcode":"3465",
    "addr:street":"Gillies St",
    "iso:country":"AU",
    "sg:address":"40 Gillies St",
    "sg:city":"Maryborough",
    "sg:classifiers":[
        {
            "category":"Sports & Exercise",
            "subcategory":"Gym",
            "type":"Entertainment"
        }
    ],
    "sg:phone":"+61 3 5461 4300",
    "sg:postcode":"3465",
    "sg:province":"VIC",
    "sg:tags":[
        "health",
        "fitness"
    ],
    "wof:name":"Maryborough Sports And Fitness Centre",
    "wof:placetype":"venue"
},
  "geometry": {"coordinates":[143.742874145,-37.0555648804],"type":"Point"}
}