{
  "type": "Feature",
  "properties": {
    "addr:full":"1A McCauley St Thirroul NSW 2515",
    "addr:housenumber":"1a",
    "addr:postcode":"2515",
    "addr:street":"Mccauley St",
    "iso:country":"AU",
    "sg:address":"1A McCauley St",
    "sg:city":"Thirroul",
    "sg:classifiers":[
        {
            "category":"Food & Beverages",
            "subcategory":"Meat & Fish",
            "type":"Retail Goods"
        }
    ],
    "sg:phone":"+61 2 4268 2421",
    "sg:postcode":"2515",
    "sg:province":"NSW",
    "sg:tags":[
        "seafood"
    ],
    "wof:name":"Jolly Roger Seafoods",
    "wof:placetype":"venue"
},
  "geometry": {"coordinates":[150.92280600000001,-34.315674],"type":"Point"}
}