{
  "type": "Feature",
  "properties": {
    "addr:full":"6 Tucker St Ulverstone TAS 7315",
    "addr:housenumber":"6",
    "addr:postcode":"7315",
    "addr:street":"Tucker St",
    "iso:country":"AU",
    "sg:address":"6 Tucker St",
    "sg:city":"Ulverstone",
    "sg:classifiers":[
        {
            "category":"Education",
            "subcategory":"Music School",
            "type":"Public Place"
        }
    ],
    "sg:phone":"+61 419 371 787",
    "sg:postcode":"7315",
    "sg:province":"TAS",
    "sg:tags":[
        "teacher"
    ],
    "wof:name":"Robert Tucker Piano Service",
    "wof:placetype":"venue"
},
  "geometry": {"coordinates":[146.18096923799999,-41.1590881348],"type":"Point"}
}