{
  "type": "Feature",
  "properties": {
    "iso:country":"AU",
    "sg:address":"Cnr Russell Rd (West) & Rockingham Rd",
    "sg:city":"Henderson",
    "sg:classifiers":[
        {
            "category":"Commercial Area",
            "type":"Public Place"
        }
    ],
    "sg:phone":"+61 8 9437 3300",
    "sg:postcode":"6166",
    "sg:province":"WA",
    "sg:tags":[
        "heavy",
        "carrier"
    ],
    "wof:name":"Bulkwest Pty Ltd",
    "wof:placetype":"venue"
},
  "geometry": {"coordinates":[115.80069,-32.153152],"type":"Point"}
}