{
  "type": "Feature",
  "properties": {
    "addr:full":"Cnr Tapleys Rd & Valetta Rd Fulham Gardens SA 5024",
    "addr:postcode":"5024",
    "addr:street":"Cnr Tapleys Rd & Valetta Rd",
    "iso:country":"AU",
    "sg:address":"Cnr Tapleys Rd & Valetta Rd",
    "sg:city":"Fulham Gardens",
    "sg:classifiers":[
        {
            "category":"Food & Beverages",
            "subcategory":"Supermarket",
            "type":"Retail Goods"
        }
    ],
    "sg:phone":"+61 8 8353 3422",
    "sg:postcode":"5024",
    "sg:province":"SA",
    "sg:tags":[
        "grocery",
        "store"
    ],
    "wof:name":"Bi-Lo",
    "wof:placetype":"venue"
},
  "geometry": {"coordinates":[138.51687622099999,-34.9129142761],"type":"Point"}
}