{
  "type": "Feature",
  "properties": {
    "addr:full":"188 Chalmers St Surry Hills NSW 2010",
    "addr:housenumber":"188",
    "addr:postcode":"2010",
    "addr:street":"Chalmers St",
    "iso:country":"AU",
    "sg:address":"188 Chalmers St",
    "sg:city":"Surry Hills",
    "sg:classifiers":[
        {
            "category":"Home & Garden",
            "subcategory":"Carpets & Floor Coverings",
            "type":"Retail Goods"
        }
    ],
    "sg:phone":"+61 2 9690 0991",
    "sg:postcode":"2010",
    "sg:province":"NSW",
    "sg:tags":[
        "wood"
    ],
    "sg:website":"http://www.precisionflooring.com.au",
    "wof:name":"Precision Flooring",
    "wof:placetype":"venue"
},
  "geometry": {"coordinates":[151.20640564000001,-33.8888702393],"type":"Point"}
}