{
  "type": "Feature",
  "properties": {
    "iso:country":"AU",
    "sg:address":"Dukes Hwy",
    "sg:city":"Keith",
    "sg:classifiers":[
        {
            "category":"Autos & Motor Vehicles",
            "subcategory":"Fuel & Gas Station",
            "type":"Retail Goods"
        }
    ],
    "sg:phone":"+61 8 8755 3155",
    "sg:postcode":"5267",
    "sg:province":"SA",
    "wof:name":"BP Australia Limited",
    "wof:placetype":"venue"
},
  "geometry": {"coordinates":[140.355896,-36.098904],"type":"Point"}
}