{
  "type": "Feature",
  "properties": {
    "iso:country":"AU",
    "sg:address":"Factory 1, 19 Olive Gr",
    "sg:city":"Keysborough",
    "sg:classifiers":[
        {
            "category":"Building & Trades",
            "subcategory":"Construction",
            "type":"Services"
        }
    ],
    "sg:phone":"+61 3 9798 8255",
    "sg:postcode":"3173",
    "sg:province":"VIC",
    "sg:tags":[
        "contractor"
    ],
    "wof:name":"Ross Godden Pty Ltd",
    "wof:placetype":"venue"
},
  "geometry": {"coordinates":[145.184326172,-37.9992904663],"type":"Point"}
}