{
  "type": "Feature",
  "properties": {
    "addr:full":"60a Central Ave Oak Flats NSW 2529",
    "addr:housenumber":"60a",
    "addr:postcode":"2529",
    "addr:street":"Central Ave Oak Flats",
    "iso:country":"AU",
    "sg:address":"60a Central Ave",
    "sg:city":"Oak Flats",
    "sg:classifiers":[
        {
            "category":"Professional",
            "subcategory":"Accounting & Tax Preparation",
            "type":"Services"
        }
    ],
    "sg:phone":"+61 2 4256 6777",
    "sg:postcode":"2529",
    "sg:province":"NSW",
    "sg:tags":[
        "accountant",
        "auditor"
    ],
    "wof:name":"G M Egan & Co",
    "wof:placetype":"venue"
},
  "geometry": {"coordinates":[150.81944274899999,-34.5644569397],"type":"Point"}
}