{
  "type": "Feature",
  "properties": {
    "addr:full":"Suite A 15 Railway Ave Wahroonga NSW 2076",
    "addr:housenumber":"15",
    "addr:postcode":"2076",
    "addr:street":"Railway Ave",
    "iso:country":"AU",
    "sg:address":"Suite A 15 Railway Ave",
    "sg:city":"Wahroonga",
    "sg:classifiers":[
        {
            "category":"Professional",
            "subcategory":"Accounting & Tax Preparation",
            "type":"Services"
        }
    ],
    "sg:phone":"+61 2 9489 9998",
    "sg:postcode":"2076",
    "sg:province":"NSW",
    "sg:tags":[
        "accountant",
        "auditor"
    ],
    "wof:name":"Kate Fernie And Co",
    "wof:placetype":"venue"
},
  "geometry": {"coordinates":[151.116455078,-33.7181129456],"type":"Point"}
}