{
  "type": "Feature",
  "properties": {
    "iso:country":"AU",
    "sg:address":"Shp 2/ 419 Fairfield Rd",
    "sg:city":"Yeronga",
    "sg:classifiers":[
        {
            "category":"Food & Beverages",
            "subcategory":"Fruits & Vegetables",
            "type":"Retail Goods"
        }
    ],
    "sg:phone":"+61 7 3848 4950",
    "sg:postcode":"4104",
    "sg:province":"QLD",
    "sg:tags":[
        "greengrocer",
        "fruiterer"
    ],
    "wof:name":"Harvest Fruit & Veg",
    "wof:placetype":"venue"
},
  "geometry": {"coordinates":[153.017852783,-27.5156917572],"type":"Point"}
}