{
  "type": "Feature",
  "properties": {
    "addr:full":"158 Carp St Bega NSW 2550",
    "addr:housenumber":"158",
    "addr:postcode":"2550",
    "addr:street":"Carp St",
    "iso:country":"AU",
    "sg:address":"158 Carp St",
    "sg:city":"Bega",
    "sg:classifiers":[
        {
            "category":"Organizations",
            "subcategory":"Community Association",
            "type":"Services"
        }
    ],
    "sg:phone":"+61 2 6492 1966",
    "sg:postcode":"2550",
    "sg:province":"NSW",
    "sg:tags":[
        "organisation",
        "family",
        "welfare"
    ],
    "wof:name":"Home Care Service of NSW",
    "wof:placetype":"venue"
},
  "geometry": {"coordinates":[149.84379577600001,-36.6742935181],"type":"Point"}
}