{
  "type": "Feature",
  "properties": {
    "addr:full":"192 King St Newtown NSW 2042",
    "addr:housenumber":"192",
    "addr:postcode":"2042",
    "addr:street":"King St",
    "iso:country":"AU",
    "sg:address":"192 King St",
    "sg:city":"Newtown",
    "sg:classifiers":[
        {
            "category":"Real Estate",
            "subcategory":"Real Estate Agent",
            "type":"Services"
        }
    ],
    "sg:phone":"+61 2 9262 3700",
    "sg:postcode":"2042",
    "sg:province":"NSW",
    "wof:name":"Ray White Real Estate Pty Ltd",
    "wof:placetype":"venue"
},
  "geometry": {"coordinates":[151.182526,-33.894581],"type":"Point"}
}