{
  "type": "Feature",
  "properties": {
    "addr:full":"3 Maffra-Sale Rd Maffra VIC 3860",
    "addr:housenumber":"3",
    "addr:postcode":"3860",
    "addr:street":"Maffra-Sale Rd",
    "iso:country":"AU",
    "sg:address":"3 Maffra-Sale Rd",
    "sg:city":"Maffra",
    "sg:classifiers":[
        {
            "category":"Health Services",
            "subcategory":"Health Practitioner",
            "type":"Services"
        }
    ],
    "sg:phone":"+61 3 5147 1212",
    "sg:postcode":"3860",
    "sg:province":"VIC",
    "sg:tags":[
        "physiotherapist"
    ],
    "wof:name":"Hilda Mcleod Physiotherapist",
    "wof:placetype":"venue"
},
  "geometry": {"coordinates":[146.98670959500001,-37.9760017395],"type":"Point"}
}