{
  "type": "Feature",
  "properties": {
    "iso:country":"AU",
    "sg:address":"56 Marloo Rd",
    "sg:city":"Westminster",
    "sg:classifiers":[
        {
            "category":"Health Services",
            "subcategory":"Doctor",
            "type":"Services"
        }
    ],
    "sg:phone":"+61 8 9349 3948",
    "sg:postcode":"6061",
    "sg:province":"WA",
    "sg:tags":[
        "medical",
        "practitioner"
    ],
    "wof:name":"Wong N S",
    "wof:placetype":"venue"
},
  "geometry": {"coordinates":[115.837661743,-31.86835289],"type":"Point"}
}