{
  "type": "Feature",
  "properties": {
    "iso:country":"AU",
    "sg:address":"39 Pimelea St",
    "sg:city":"Everton Hills",
    "sg:classifiers":[
        {
            "category":"Building & Trades",
            "subcategory":"Plumbing",
            "type":"Services"
        }
    ],
    "sg:phone":"+61 438 642 384",
    "sg:postcode":"4053",
    "sg:province":"QLD",
    "sg:tags":[
        "plumber",
        "gasfitters"
    ],
    "wof:name":"Tonys Affordable Plumbing Service",
    "wof:placetype":"venue"
},
  "geometry": {"coordinates":[152.96551513700001,-27.3950538635],"type":"Point"}
}