{
  "type": "Feature",
  "properties": {
    "addr:full":"50 Hannah St Wallsend NSW 2287",
    "addr:housenumber":"50",
    "addr:postcode":"2287",
    "addr:street":"Hannah St",
    "iso:country":"AU",
    "sg:address":"50 Hannah St",
    "sg:city":"Wallsend",
    "sg:classifiers":[
        {
            "category":"Sports & Exercise",
            "subcategory":"Gym",
            "type":"Entertainment"
        }
    ],
    "sg:phone":"+61 402 122 096",
    "sg:postcode":"2287",
    "sg:province":"NSW",
    "sg:tags":[
        "personal",
        "trainer",
        "fitness"
    ],
    "wof:name":"Inspire Personal Training",
    "wof:placetype":"venue"
},
  "geometry": {"coordinates":[151.66110229500001,-32.8954277039],"type":"Point"}
}