{
  "type": "Feature",
  "properties": {
    "addr:full":"8 Damosh Ave Carrum Downs VIC 3201",
    "addr:housenumber":"8",
    "addr:postcode":"3201",
    "addr:street":"Damosh Ave",
    "iso:country":"AU",
    "sg:address":"8 Damosh Ave",
    "sg:city":"Carrum Downs",
    "sg:classifiers":[
        {
            "category":"Professional",
            "subcategory":"Engineering",
            "type":"Services"
        }
    ],
    "sg:phone":"+61 3 9775 0133",
    "sg:postcode":"3201",
    "sg:province":"VIC",
    "sg:tags":[
        "engineer",
        "mechanical"
    ],
    "wof:name":"Protech Developments Pty Ltd",
    "wof:placetype":"venue"
},
  "geometry": {"coordinates":[145.162476,-38.099297],"type":"Point"}
}