{
  "type": "Feature",
  "properties": {
    "iso:country":"AU",
    "sg:address":"6 Braybrook Pl",
    "sg:city":"Craigie",
    "sg:classifiers":[
        {
            "category":"Health Services",
            "subcategory":"Health Practitioner",
            "type":"Services"
        }
    ],
    "sg:phone":"+61 8 9307 2785",
    "sg:postcode":"6025",
    "sg:province":"WA",
    "sg:tags":[
        "psychologist"
    ],
    "wof:name":"Barr Georgina",
    "wof:placetype":"venue"
},
  "geometry": {"coordinates":[115.77243042000001,-31.7824993134],"type":"Point"}
}