{
  "type": "Feature",
  "properties": {
    "addr:full":"U2/ 1 Howard St Fremantle WA 6160",
    "addr:housenumber":"1",
    "addr:postcode":"6160",
    "addr:street":"U2 /;Howard St",
    "iso:country":"AU",
    "sg:address":"U2/ 1 Howard St",
    "sg:city":"Fremantle",
    "sg:classifiers":[
        {
            "category":"Recreation",
            "subcategory":"Fishing",
            "type":"Entertainment"
        }
    ],
    "sg:phone":"+61 8 9335 9653",
    "sg:postcode":"6160",
    "sg:province":"WA",
    "sg:tags":[
        "bait"
    ],
    "wof:name":"Cicerello & Backhouse",
    "wof:placetype":"venue"
},
  "geometry": {"coordinates":[115.749092,-32.060448],"type":"Point"}
}