{
  "type": "Feature",
  "properties": {
    "iso:country":"AU",
    "sg:address":"76- 82 Botany Rd",
    "sg:city":"Alexandria",
    "sg:classifiers":[
        {
            "category":"Shopping",
            "subcategory":"Clothing, Apparel, & Fashions",
            "type":"Retail Goods"
        }
    ],
    "sg:phone":"+61 2 9310 7000",
    "sg:postcode":"2015",
    "sg:province":"NSW",
    "sg:tags":[
        "uniform"
    ],
    "wof:name":"S F Corporate Clothing Pty Ltd",
    "wof:placetype":"venue"
},
  "geometry": {"coordinates":[151.19934082,-33.8973503113],"type":"Point"}
}