{
  "type": "Feature",
  "properties": {
    "iso:country":"AU",
    "sg:address":"37 Andrews St",
    "sg:city":"Eltham",
    "sg:classifiers":[
        {
            "category":"Professional",
            "subcategory":"Employment Agencies",
            "type":"Services"
        }
    ],
    "sg:phone":"+61 3 9439 3753",
    "sg:postcode":"3095",
    "sg:province":"VIC",
    "sg:tags":[
        "entertainer",
        "agent"
    ],
    "wof:name":"The Leftovers",
    "wof:placetype":"venue"
},
  "geometry": {"coordinates":[145.16267395,-37.705997467],"type":"Point"}
}