{
  "type": "Feature",
  "properties": {
    "addr:full":"Shed 10 /90 Dick Ward Drive Industrial Village Coconu NT 0810",
    "addr:postcode":"nt 0810",
    "addr:street":"Ward Drive Industrial Village",
    "iso:country":"AU",
    "sg:address":"Shed 10",
    "sg:city":"/90 Dick Ward Drive Industrial Village Coconu",
    "sg:classifiers":[
        {
            "category":"Manufacturing",
            "subcategory":"Metals",
            "type":"Manufacturing & Wholesale Goods"
        }
    ],
    "sg:phone":"+61 8 8985 4145",
    "sg:postcode":"0810",
    "sg:province":"NT",
    "sg:tags":[
        "fabricator",
        "aluminium"
    ],
    "wof:name":"Black Arrow",
    "wof:placetype":"venue"
},
  "geometry": {"coordinates":[130.85244750999999,-12.3998861313],"type":"Point"}
}