{
  "type": "Feature",
  "properties": {
    "addr:full":"138- 140 Lily St Bendigo VIC 3550",
    "addr:housenumber":"140",
    "addr:postcode":"3550",
    "addr:street":"Lily St",
    "iso:country":"AU",
    "sg:address":"138- 140 Lily St",
    "sg:city":"Bendigo",
    "sg:classifiers":[
        {
            "category":"Health Services",
            "subcategory":"Doctor",
            "type":"Services"
        }
    ],
    "sg:phone":"+61 3 5434 3390",
    "sg:postcode":"3550",
    "sg:province":"VIC",
    "sg:tags":[
        "medical",
        "practitioner"
    ],
    "wof:name":"Lindsay, Stephen Mr",
    "wof:placetype":"venue"
},
  "geometry": {"coordinates":[144.263748169,-36.761341095],"type":"Point"}
}