{
  "type": "Feature",
  "properties": {
    "iso:country":"AU",
    "sg:address":"1234 Glenhuntly Rd",
    "sg:city":"Glen Huntly",
    "sg:classifiers":[
        {
            "category":"Autos & Motor Vehicles",
            "subcategory":"Automobile Sales",
            "type":"Retail Goods"
        }
    ],
    "sg:phone":"+61 3 9584 3333",
    "sg:postcode":"3163",
    "sg:province":"VIC",
    "sg:tags":[
        "car",
        "new"
    ],
    "wof:name":"Booran Service",
    "wof:placetype":"venue"
},
  "geometry": {"coordinates":[145.04544067399999,-37.889919281],"type":"Point"}
}