{
  "type": "Feature",
  "properties": {
    "addr:full":"7/ 23 Mitchell Rd Mosman NSW 2088",
    "addr:housenumber":"/ 23",
    "addr:postcode":"2088",
    "addr:street":"Mitchell Rd",
    "iso:country":"AU",
    "sg:address":"7/ 23 Mitchell Rd",
    "sg:city":"Mosman",
    "sg:classifiers":[
        {
            "category":"Professional",
            "subcategory":"Printing & Photocopies",
            "type":"Services"
        }
    ],
    "sg:phone":"+61 2 9960 7290",
    "sg:postcode":"2088",
    "sg:province":"NSW",
    "sg:tags":[
        "publishing",
        "desktop"
    ],
    "wof:name":"Barclay Graphics",
    "wof:placetype":"venue"
},
  "geometry": {"coordinates":[151.24322509800001,-33.8179321289],"type":"Point"}
}