{
  "type": "Feature",
  "properties": {
    "iso:country":"AU",
    "sg:address":"Unit 4, 6 Barcelona Way",
    "sg:city":"Maddington",
    "sg:classifiers":[
        {
            "category":"Utilities",
            "subcategory":"Electric",
            "type":"Services"
        }
    ],
    "sg:phone":"+61 8 9459 1538",
    "sg:postcode":"6109",
    "sg:province":"WA",
    "sg:tags":[
        "electrical",
        "contractor"
    ],
    "wof:name":"Holdens Electrical Contracting",
    "wof:placetype":"venue"
},
  "geometry": {"coordinates":[115.994163513,-32.0377197266],"type":"Point"}
}