{
  "type": "Feature",
  "properties": {
    "addr:full":"6-8 Rennick St Preston VIC 3072",
    "addr:housenumber":"6-8",
    "addr:postcode":"3072",
    "addr:street":"Rennick St",
    "iso:country":"AU",
    "sg:address":"6-8 Rennick St",
    "sg:city":"Preston",
    "sg:classifiers":[
        {
            "category":"Wholesale",
            "subcategory":"Seafood",
            "type":"Manufacturing & Wholesale Goods"
        }
    ],
    "sg:phone":"+61 3 9484 2955",
    "sg:postcode":"3072",
    "sg:province":"VIC",
    "sg:tags":[
        "fish"
    ],
    "wof:name":"Southern Ocean Seafoods Pty Ltd",
    "wof:placetype":"venue"
},
  "geometry": {"coordinates":[145.02815246599999,-37.7499961853],"type":"Point"}
}