{
  "type": "Feature",
  "properties": {
    "addr:full":"Connors Rd Mackay QLD 4740",
    "addr:postcode":"4740",
    "addr:street":"Connors Rd",
    "iso:country":"AU",
    "sg:address":"Connors Rd",
    "sg:city":"Mackay",
    "sg:classifiers":[
        {
            "category":"Manufacturing",
            "subcategory":"Tools & Machinery",
            "type":"Manufacturing & Wholesale Goods"
        }
    ],
    "sg:phone":"+61 7 4952 2455",
    "sg:postcode":"4740",
    "sg:province":"QLD",
    "sg:tags":[
        "earth",
        "excavating",
        "moving",
        "equipment"
    ],
    "wof:name":"CJD Equipment Pty Ltd",
    "wof:placetype":"venue"
},
  "geometry": {"coordinates":[149.16082800000001,-21.180748],"type":"Point"}
}