{
  "type": "Feature",
  "properties": {
    "addr:full":"216 Newcastle St Perth WA 6000",
    "addr:housenumber":"216",
    "addr:postcode":"6000",
    "addr:street":"Newcastle St",
    "iso:country":"AU",
    "sg:address":"216 Newcastle St",
    "sg:city":"Perth",
    "sg:classifiers":[
        {
            "category":"Autos & Motor Vehicles",
            "subcategory":"Automobile Sales",
            "type":"Retail Goods"
        }
    ],
    "sg:phone":"+61 8 9227 8888",
    "sg:postcode":"6000",
    "sg:province":"WA",
    "sg:tags":[
        "car",
        "new"
    ],
    "wof:name":"Ford Centre",
    "wof:placetype":"venue"
},
  "geometry": {"coordinates":[115.85842895499999,-31.9449214935],"type":"Point"}
}