{
  "type": "Feature",
  "properties": {
    "addr:full":"Unit 4 29 Helles Ave Moorebank NSW 2170",
    "addr:housenumber":"29",
    "addr:postcode":"2170",
    "addr:street":"Helles Ave",
    "iso:country":"AU",
    "sg:address":"Unit 4 29 Helles Ave",
    "sg:city":"Moorebank",
    "sg:classifiers":[
        {
            "category":"Shopping",
            "subcategory":"Optical Goods",
            "type":"Retail Goods"
        }
    ],
    "sg:phone":"+61 2 9821 4111",
    "sg:postcode":"2170",
    "sg:province":"NSW",
    "sg:tags":[
        "supply"
    ],
    "wof:name":"Apollo Optical Pty Ltd",
    "wof:placetype":"venue"
},
  "geometry": {"coordinates":[150.922042847,-33.938457489],"type":"Point"}
}