{
  "type": "Feature",
  "properties": {
    "addr:full":"22L Yarrandale Rd Dubbo NSW 2830",
    "addr:housenumber":"22l",
    "addr:postcode":"2830",
    "addr:street":"Yarrandale Rd",
    "iso:country":"AU",
    "sg:address":"22L Yarrandale Rd",
    "sg:city":"Dubbo",
    "sg:classifiers":[
        {
            "category":"Wholesale",
            "subcategory":"Painting Supplies",
            "type":"Manufacturing & Wholesale Goods"
        }
    ],
    "sg:phone":"+61 2 6884 8444",
    "sg:postcode":"2830",
    "sg:province":"NSW",
    "sg:tags":[
        "product",
        "cleaning"
    ],
    "wof:name":"B & J Chemicals",
    "wof:placetype":"venue"
},
  "geometry": {"coordinates":[148.63192749000001,-32.2226219177],"type":"Point"}
}