{
  "type": "Feature",
  "properties": {
    "iso:country":"AU",
    "sg:address":"19 Alicia St",
    "sg:city":"Southport",
    "sg:classifiers":[
        {
            "category":"Fast Food",
            "type":"Food & Drink"
        }
    ],
    "sg:phone":"+61 7 5532 7271",
    "sg:postcode":"4215",
    "sg:province":"QLD",
    "sg:tags":[
        "away",
        "take"
    ],
    "wof:name":"Golden Deer Chinese Restaurant",
    "wof:placetype":"venue"
},
  "geometry": {"coordinates":[153.403533936,-27.9781074524],"type":"Point"}
}