{
  "type": "Feature",
  "properties": {
    "addr:full":"19 Bourke St Maitland NSW 2320",
    "addr:housenumber":"19",
    "addr:postcode":"2320",
    "addr:street":"Bourke St",
    "iso:country":"AU",
    "sg:address":"19 Bourke St",
    "sg:city":"Maitland",
    "sg:classifiers":[
        {
            "category":"Professional",
            "subcategory":"Employment Agencies",
            "type":"Services"
        }
    ],
    "sg:phone":"+61 2 4934 8200",
    "sg:postcode":"2320",
    "sg:province":"NSW",
    "wof:name":"Wallsend Employment & Training Services",
    "wof:placetype":"venue"
},
  "geometry": {"coordinates":[151.556732178,-32.7341003418],"type":"Point"}
}