{
  "type": "Feature",
  "properties": {
    "iso:country":"AU",
    "sg:address":"560 Hume Hwy",
    "sg:city":"Yagoona",
    "sg:classifiers":[
        {
            "category":"Autos & Motor Vehicles",
            "subcategory":"Auto Supplies",
            "type":"Retail Goods"
        }
    ],
    "sg:phone":"+61 2 9709 4499",
    "sg:postcode":"2199",
    "sg:province":"NSW",
    "sg:tags":[
        "accessory"
    ],
    "wof:name":"Autopro",
    "wof:placetype":"venue"
},
  "geometry": {"coordinates":[151.021347,-33.907051],"type":"Point"}
}