{
  "type": "Feature",
  "properties": {
    "addr:full":"60 Elder St Alice Springs NT 0870",
    "addr:housenumber":"60",
    "addr:postcode":"nt 0870",
    "addr:street":"Elder St",
    "iso:country":"AU",
    "sg:address":"60 Elder St",
    "sg:city":"Alice Springs",
    "sg:classifiers":[
        {
            "category":"Building & Trades",
            "subcategory":"Construction",
            "type":"Services"
        }
    ],
    "sg:phone":"+61 8 8953 1488",
    "sg:postcode":"0870",
    "sg:province":"NT",
    "sg:tags":[
        "home",
        "air conditioning"
    ],
    "wof:name":"Condition Air",
    "wof:placetype":"venue"
},
  "geometry": {"coordinates":[133.864990234,-23.6947841644],"type":"Point"}
}