{
  "type": "Feature",
  "properties": {
    "addr:full":"Seaton Medical & Specialist Centre 175 Trimmer Pde Seaton SA 5023",
    "addr:housenumber":"175",
    "addr:postcode":"5023",
    "addr:street":"Trimmer Pde",
    "iso:country":"AU",
    "sg:address":"Seaton Medical & Specialist Centre 175 Trimmer Pde",
    "sg:city":"Seaton",
    "sg:classifiers":[
        {
            "category":"Health Services",
            "subcategory":"Health Practitioner",
            "type":"Services"
        }
    ],
    "sg:phone":"+61 8 8345 4959",
    "sg:postcode":"5023",
    "sg:province":"SA",
    "sg:tags":[
        "pathologist",
        "speech"
    ],
    "wof:name":"Sulley Catherine",
    "wof:placetype":"venue"
},
  "geometry": {"coordinates":[138.51507568400001,-34.8919334412],"type":"Point"}
}