{
  "type": "Feature",
  "properties": {
    "addr:full":"13 Verrell St Wetherill Park NSW 2164",
    "addr:housenumber":"13",
    "addr:postcode":"2164",
    "addr:street":"Verrell St",
    "iso:country":"AU",
    "sg:address":"13 Verrell St",
    "sg:city":"Wetherill Park",
    "sg:classifiers":[
        {
            "category":"Building & Trades",
            "subcategory":"Construction",
            "type":"Services"
        }
    ],
    "sg:phone":"+61 2 9757 1944",
    "sg:postcode":"2164",
    "sg:province":"NSW",
    "sg:tags":[
        "road",
        "contractor"
    ],
    "wof:name":"Power Civil",
    "wof:placetype":"venue"
},
  "geometry": {"coordinates":[150.92176818900001,-33.8438339233],"type":"Point"}
}