{
  "type": "Feature",
  "properties": {
    "addr:full":"Main St Carrieton SA 5432",
    "addr:postcode":"5432",
    "addr:street":"Main St",
    "iso:country":"AU",
    "sg:address":"Main St",
    "sg:city":"Carrieton",
    "sg:classifiers":[
        {
            "category":"Travel",
            "subcategory":"Hotels & Motels",
            "type":"Entertainment"
        }
    ],
    "sg:phone":"+61 8 8658 9007",
    "sg:postcode":"5432",
    "sg:province":"SA",
    "sg:tags":[
        "accommodation"
    ],
    "wof:name":"Carrieton Hotel",
    "wof:placetype":"venue"
},
  "geometry": {"coordinates":[138.530059814,-32.4218063354],"type":"Point"}
}