{
  "type": "Feature",
  "properties": {
    "addr:full":"1 Genty St Campbelltown NSW 2560",
    "addr:housenumber":"1",
    "addr:postcode":"2560",
    "addr:street":"Genty St",
    "iso:country":"AU",
    "sg:address":"1 Genty St",
    "sg:city":"Campbelltown",
    "sg:classifiers":[
        {
            "category":"Travel",
            "subcategory":"Hostel",
            "type":"Entertainment"
        }
    ],
    "sg:phone":"+61 2 4625 1828",
    "sg:postcode":"2560",
    "sg:province":"NSW",
    "sg:tags":[
        "home"
    ],
    "wof:name":"Vince's Place (Men's Hostel)",
    "wof:placetype":"venue"
},
  "geometry": {"coordinates":[150.82049560600001,-34.0663490295],"type":"Point"}
}