{
  "type": "Feature",
  "properties": {
    "addr:full":"207 Thorneside Rd Thorneside QLD 4158",
    "addr:housenumber":"207",
    "addr:postcode":"4158",
    "addr:street":"Thorneside Rd",
    "iso:country":"AU",
    "sg:address":"207 Thorneside Rd",
    "sg:city":"Thorneside",
    "sg:classifiers":[
        {
            "category":"Food & Beverages",
            "subcategory":"Specialty",
            "type":"Retail Goods"
        }
    ],
    "sg:phone":"+61 7 3822 3799",
    "sg:postcode":"4158",
    "sg:province":"QLD",
    "sg:tags":[
        "product",
        "health"
    ],
    "wof:name":"Thorneside Day & Night",
    "wof:placetype":"venue"
},
  "geometry": {"coordinates":[153.198318481,-27.4861221313],"type":"Point"}
}