{
  "type": "Feature",
  "properties": {
    "addr:full":"Lot 22-23 Bourke St Dubbo NSW 2830",
    "addr:housenumber":"22-23",
    "addr:postcode":"2830",
    "addr:street":"Bourke St",
    "iso:country":"AU",
    "sg:address":"Lot 22-23 Bourke St",
    "sg:city":"Dubbo",
    "sg:classifiers":[
        {
            "category":"Industrial Area",
            "type":"Public Place"
        }
    ],
    "sg:phone":"+61 2 6884 4044",
    "sg:postcode":"2830",
    "sg:province":"NSW",
    "sg:tags":[
        "rural",
        "shed"
    ],
    "wof:name":"Ranbuild Western Plains",
    "wof:placetype":"venue"
},
  "geometry": {"coordinates":[148.61111450199999,-32.2355957031],"type":"Point"}
}