{
  "type": "Feature",
  "properties": {
    "iso:country":"AU",
    "sg:address":"37 Walpole St",
    "sg:city":"Millmerran",
    "sg:classifiers":[
        {
            "category":"Utilities",
            "subcategory":"Natural Gas",
            "type":"Services"
        }
    ],
    "sg:phone":"+61 7 4695 1443",
    "sg:postcode":"4357",
    "sg:province":"QLD",
    "sg:tags":[
        "supplier"
    ],
    "wof:name":"Millmerran Plumbing & Hardware Co",
    "wof:placetype":"venue"
},
  "geometry": {"coordinates":[151.27076700000001,-27.873579],"type":"Point"}
}