{
  "type": "Feature",
  "properties": {
    "iso:country":"AU",
    "sg:address":"94 Cartwright St",
    "sg:city":"Ingham",
    "sg:classifiers":[
        {
            "category":"Professional",
            "subcategory":"Art Services",
            "type":"Services"
        }
    ],
    "sg:phone":"+61 7 4776 6620",
    "sg:postcode":"4850",
    "sg:province":"QLD",
    "sg:tags":[
        "picture",
        "frame",
        "framing"
    ],
    "wof:name":"Picture This Framed",
    "wof:placetype":"venue"
},
  "geometry": {"coordinates":[146.16270446799999,-18.6469116211],"type":"Point"}
}