{
  "type": "Feature",
  "properties": {
    "addr:full":"17 Uralla Rd Port Macquarie NSW 2444",
    "addr:housenumber":"17",
    "addr:postcode":"2444",
    "addr:street":"Uralla Rd",
    "iso:country":"AU",
    "sg:address":"17 Uralla Rd",
    "sg:city":"Port Macquarie",
    "sg:classifiers":[
        {
            "category":"Professional",
            "type":"Services"
        }
    ],
    "sg:phone":"+61 2 6581 0599",
    "sg:postcode":"2444",
    "sg:province":"NSW",
    "sg:tags":[
        "spray",
        "painting"
    ],
    "wof:name":"Port Panel Works",
    "wof:placetype":"venue"
},
  "geometry": {"coordinates":[152.883545,-31.450838],"type":"Point"}
}