{
  "type": "Feature",
  "properties": {
    "addr:full":"Greenhalghs Rd Ballarat VIC 3350",
    "addr:postcode":"3350",
    "addr:street":"Greenhalghs Rd",
    "iso:country":"AU",
    "sg:address":"Greenhalghs Rd",
    "sg:city":"Ballarat",
    "sg:classifiers":[
        {
            "category":"Education",
            "subcategory":"School",
            "type":"Public Place"
        }
    ],
    "sg:phone":"+61 3 5335 6103",
    "sg:postcode":"3350",
    "sg:province":"VIC",
    "sg:tags":[
        "state",
        "except",
        "nsw"
    ],
    "wof:name":"Delacombe Primary School",
    "wof:placetype":"venue"
},
  "geometry": {"coordinates":[143.82517999999999,-37.586548],"type":"Point"}
}