{
  "type": "Feature",
  "properties": {
    "iso:country":"AU",
    "sg:address":"2/78- 82 Trinity Beach Rd",
    "sg:city":"Trinity Beach",
    "sg:classifiers":[
        {
            "category":"Real Estate",
            "subcategory":"Real Estate Agent",
            "type":"Services"
        }
    ],
    "sg:phone":"+61 7 4057 8417",
    "sg:postcode":"4879",
    "sg:province":"QLD",
    "wof:name":"Richert Lesley",
    "wof:placetype":"venue"
},
  "geometry": {"coordinates":[145.69204711899999,-16.7898902893],"type":"Point"}
}