{
  "type": "Feature",
  "properties": {
    "addr:full":"Old Forts Rd Albany WA 6330",
    "addr:postcode":"6330",
    "addr:street":"Forts Rd",
    "iso:country":"AU",
    "sg:address":"Old Forts Rd",
    "sg:city":"Albany",
    "sg:classifiers":[
        {
            "category":"Retail",
            "subcategory":"Event Space",
            "type":"Services"
        }
    ],
    "sg:phone":"+61 8 9842 6630",
    "sg:postcode":"6330",
    "sg:province":"WA",
    "sg:tags":[
        "venue",
        "reception",
        "wedding"
    ],
    "wof:name":"Carlyles Function Centre",
    "wof:placetype":"venue"
},
  "geometry": {"coordinates":[117.91522979699999,-35.0294036865],"type":"Point"}
}