{
  "type": "Feature",
  "properties": {
    "iso:country":"AU",
    "sg:address":"4 Hartree Pl",
    "sg:city":"Cherrybrook",
    "sg:classifiers":[
        {
            "category":"Retail",
            "subcategory":"Auto Repair",
            "type":"Services"
        }
    ],
    "sg:phone":"+61 417 088 869",
    "sg:postcode":"2126",
    "sg:province":"NSW",
    "sg:tags":[
        "bus",
        "truck"
    ],
    "wof:name":"Truck Doctor The",
    "wof:placetype":"venue"
},
  "geometry": {"coordinates":[151.05371093799999,-33.7240104675],"type":"Point"}
}