{
  "type": "Feature",
  "properties": {
    "iso:country":"AU",
    "sg:address":"7 Hawthorn Pl",
    "sg:city":"Orange",
    "sg:classifiers":[
        {
            "category":"Wholesale",
            "subcategory":"Machinery & Supplies",
            "type":"Manufacturing & Wholesale Goods"
        }
    ],
    "sg:phone":"+61 2 6362 5690",
    "sg:postcode":"2800",
    "sg:province":"NSW",
    "sg:tags":[
        "equipment",
        "hydraulic"
    ],
    "wof:name":"Country Hydraulics Pty Ltd",
    "wof:placetype":"venue"
},
  "geometry": {"coordinates":[149.11199951200001,-33.3095855713],"type":"Point"}
}