{
  "type": "Feature",
  "properties": {
    "addr:full":"46 Marion St Harris Park NSW 2150",
    "addr:housenumber":"46",
    "addr:postcode":"2150",
    "addr:street":"Marion St",
    "iso:country":"AU",
    "sg:address":"46 Marion St",
    "sg:city":"Harris Park",
    "sg:classifiers":[
        {
            "category":"Shopping",
            "subcategory":"Clothing, Apparel, & Fashions",
            "type":"Retail Goods"
        }
    ],
    "sg:phone":"+61 2 9891 2266",
    "sg:postcode":"2150",
    "sg:province":"NSW",
    "sg:tags":[
        "menswear"
    ],
    "sg:website":"http://www.bigguys.com.au",
    "wof:name":"Big Guys Australia Fashion House Pty Ltd",
    "wof:placetype":"venue"
},
  "geometry": {"coordinates":[151.00733947800001,-33.8221817017],"type":"Point"}
}