{
  "type": "Feature",
  "properties": {
    "addr:full":"3 Crittenden Rd Glass House Mountains QLD 4518",
    "addr:housenumber":"3",
    "addr:postcode":"4518",
    "addr:street":"Crittenden Rd",
    "iso:country":"AU",
    "sg:address":"3 Crittenden Rd",
    "sg:city":"Glass House Mountains",
    "sg:classifiers":[
        {
            "category":"Farming",
            "subcategory":"Nursery",
            "type":"Manufacturing & Wholesale Goods"
        }
    ],
    "sg:phone":"+61 7 5496 9684",
    "sg:postcode":"4518",
    "sg:province":"QLD",
    "wof:name":"Rumbalara Nursery",
    "wof:placetype":"venue"
},
  "geometry": {"coordinates":[152.97430419899999,-26.9158401489],"type":"Point"}
}