{
  "type": "Feature",
  "properties": {
    "addr:full":"234 Collins St Melbourne VIC 3000",
    "addr:housenumber":"234",
    "addr:postcode":"3000",
    "addr:street":"Collins St",
    "iso:country":"AU",
    "sg:address":"234 Collins St",
    "sg:city":"Melbourne",
    "sg:classifiers":[
        {
            "category":"Shopping",
            "subcategory":"Clothing, Apparel, & Fashions",
            "type":"Retail Goods"
        }
    ],
    "sg:phone":"+61 3 9654 3524",
    "sg:postcode":"3000",
    "sg:province":"VIC",
    "sg:tags":[
        "lady",
        "wear"
    ],
    "wof:name":"Saba- Women",
    "wof:placetype":"venue"
},
  "geometry": {"coordinates":[144.965942383,-37.8155288696],"type":"Point"}
}