{
  "type": "Feature",
  "properties": {
    "iso:country":"AU",
    "sg:address":"RMB 417",
    "sg:city":"Pingelly",
    "sg:classifiers":[
        {
            "category":"Farming",
            "subcategory":"Farm",
            "type":"Manufacturing & Wholesale Goods"
        }
    ],
    "sg:phone":"+61 8 9887 1236",
    "sg:postcode":"6308",
    "sg:province":"WA",
    "sg:tags":[
        "farmer"
    ],
    "wof:name":"O&#039;Brien R G & M J",
    "wof:placetype":"venue"
},
  "geometry": {"coordinates":[117.084129334,-32.5337715149],"type":"Point"}
}