{
  "type": "Feature",
  "properties": {
    "iso:country":"AU",
    "sg:address":"25 Turner Rd",
    "sg:city":"Stanthorpe",
    "sg:classifiers":[
        {
            "category":"Farming",
            "subcategory":"Vineyard",
            "type":"Manufacturing & Wholesale Goods"
        }
    ],
    "sg:phone":"+61 7 4683 5100",
    "sg:postcode":"4380",
    "sg:province":"QLD",
    "sg:tags":[
        "winery"
    ],
    "wof:name":"Whiskey Gully Wines",
    "wof:placetype":"venue"
},
  "geometry": {"coordinates":[151.908127,-28.702232],"type":"Point"}
}