{
  "type": "Feature",
  "properties": {
    "addr:full":"Unit 3 26 Mornington Rd Mornington TAS 7018",
    "addr:housenumber":"26",
    "addr:postcode":"7018",
    "addr:street":"Mornington Rd",
    "iso:country":"AU",
    "sg:address":"Unit 3 26 Mornington Rd",
    "sg:city":"Mornington",
    "sg:classifiers":[
        {
            "category":"Building & Trades",
            "subcategory":"Construction",
            "type":"Services"
        }
    ],
    "sg:phone":"+61 3 6245 1175",
    "sg:postcode":"7018",
    "sg:province":"TAS",
    "sg:tags":[
        "roof"
    ],
    "wof:name":"Raymark Roofing Pty Ltd",
    "wof:placetype":"venue"
},
  "geometry": {"coordinates":[147.39663696299999,-42.8594398499],"type":"Point"}
}