{
  "type": "Feature",
  "properties": {
    "addr:full":"60 Everard Ave Adelaide SA 5000",
    "addr:housenumber":"60",
    "addr:postcode":"5000",
    "addr:street":"Everard Ave",
    "iso:country":"AU",
    "sg:address":"60 Everard Ave",
    "sg:city":"Adelaide",
    "sg:classifiers":[
        {
            "category":"Professional",
            "type":"Services"
        }
    ],
    "sg:phone":"+61 1300 656 532",
    "sg:postcode":"5000",
    "sg:province":"SA",
    "sg:tags":[
        "courier"
    ],
    "wof:name":"Greyhound Freight",
    "wof:placetype":"venue"
},
  "geometry": {"coordinates":[138.57705688499999,-34.9459152222],"type":"Point"}
}