{
  "type": "Feature",
  "properties": {
    "iso:country":"AU",
    "sg:address":"2- 14 Cliff Rd",
    "sg:city":"North Wollongong",
    "sg:classifiers":[
        {
            "category":"Retail",
            "subcategory":"Event Space",
            "type":"Services"
        }
    ],
    "sg:phone":"+61 2 4224 3111",
    "sg:postcode":"2500",
    "sg:province":"NSW",
    "sg:tags":[
        "venue",
        "reception",
        "wedding"
    ],
    "wof:name":"Novotel Northbeach",
    "wof:placetype":"venue"
},
  "geometry": {"coordinates":[150.900742,-34.414219],"type":"Point"}
}