{
  "type": "Feature",
  "properties": {
    "iso:country":"AU",
    "sg:address":"133 Hurd St",
    "sg:city":"Portland",
    "sg:classifiers":[
        {
            "category":"Retail",
            "subcategory":"Auto Repair",
            "type":"Services"
        }
    ],
    "sg:phone":"+61 3 5523 3895",
    "sg:postcode":"3305",
    "sg:province":"VIC",
    "sg:tags":[
        "electrical"
    ],
    "wof:name":"Jack Graham Auto Electrics",
    "wof:placetype":"venue"
},
  "geometry": {"coordinates":[141.60418701200001,-38.3402290344],"type":"Point"}
}