{
  "type": "Feature",
  "properties": {
    "iso:country":"AU",
    "sg:address":"7 McGowan St",
    "sg:city":"Pooraka",
    "sg:classifiers":[
        {
            "category":"Utilities",
            "subcategory":"Electric",
            "type":"Services"
        }
    ],
    "sg:phone":"+61 8 8349 7617",
    "sg:postcode":"5095",
    "sg:province":"SA",
    "sg:tags":[
        "element"
    ],
    "wof:name":"Gra-Mall Hot Water Systems Pty Ltd",
    "wof:placetype":"venue"
},
  "geometry": {"coordinates":[138.637115478,-34.8193473816],"type":"Point"}
}