{
  "type": "Feature",
  "properties": {
    "addr:full":"721 Daniel St Albury NSW 2640",
    "addr:housenumber":"721",
    "addr:postcode":"2640",
    "addr:street":"Daniel St",
    "iso:country":"AU",
    "sg:address":"721 Daniel St",
    "sg:city":"Albury",
    "sg:classifiers":[
        {
            "category":"Wholesale",
            "subcategory":"Electrical",
            "type":"Manufacturing & Wholesale Goods"
        }
    ],
    "sg:phone":"+61 2 6040 6987",
    "sg:postcode":"2640",
    "sg:province":"NSW",
    "sg:tags":[
        "control",
        "equipment",
        "switch"
    ],
    "wof:name":"Bremark Controls Pty Ltd",
    "wof:placetype":"venue"
},
  "geometry": {"coordinates":[146.90928649899999,-36.0583686829],"type":"Point"}
}