{
  "type": "Feature",
  "properties": {
    "addr:full":"48 Myoora Rd Terrey Hills NSW 2084",
    "addr:housenumber":"48",
    "addr:postcode":"2084",
    "addr:street":"Myoora Rd",
    "iso:country":"AU",
    "sg:address":"48 Myoora Rd",
    "sg:city":"Terrey Hills",
    "sg:classifiers":[
        {
            "category":"Manufacturing",
            "subcategory":"Food",
            "type":"Manufacturing & Wholesale Goods"
        }
    ],
    "sg:phone":"+61 2 9450 2000",
    "sg:postcode":"2084",
    "sg:province":"NSW",
    "sg:tags":[
        "function",
        "catering"
    ],
    "wof:name":"Miramare Gardens",
    "wof:placetype":"venue"
},
  "geometry": {"coordinates":[151.21949768100001,-33.6907081604],"type":"Point"}
}