{
  "type": "Feature",
  "properties": {
    "addr:full":"St Andrews Beach VIC 3941",
    "addr:postcode":"3941",
    "iso:country":"AU",
    "sg:address":"St",
    "sg:city":"Andrews Beach",
    "sg:classifiers":[
        {
            "category":"Building & Trades",
            "subcategory":"Landscaping Services",
            "type":"Services"
        }
    ],
    "sg:phone":"+61 401 298 778",
    "sg:postcode":"3941",
    "sg:province":"VIC",
    "sg:tags":[
        "control",
        "weed"
    ],
    "wof:name":"Coast and Bush Weed Management",
    "wof:placetype":"venue"
},
  "geometry": {"coordinates":[144.835861206,-38.4160995483],"type":"Point"}
}