{
  "type": "Feature",
  "properties": {
    "addr:full":"80 Brewster Rd North Ararat VIC 3377",
    "addr:housenumber":"80",
    "addr:postcode":"3377",
    "addr:street":"Brewster Rd North",
    "iso:country":"AU",
    "sg:address":"80 Brewster Rd North",
    "sg:city":"Ararat",
    "sg:classifiers":[
        {
            "category":"Building & Trades",
            "subcategory":"Plumbing",
            "type":"Services"
        }
    ],
    "sg:phone":"+61 3 5352 5335",
    "sg:postcode":"3377",
    "sg:province":"VIC",
    "sg:tags":[
        "plumber",
        "gasfitters"
    ],
    "wof:name":"Fleming Gas & Plumbing",
    "wof:placetype":"venue"
},
  "geometry": {"coordinates":[142.91484069800001,-37.2788391113],"type":"Point"}
}