{
  "type": "Feature",
  "properties": {
    "iso:country":"AU",
    "sg:address":"PO Box 493",
    "sg:city":"Launceston",
    "sg:classifiers":[
        {
            "category":"Education",
            "subcategory":"Special Training",
            "type":"Public Place"
        }
    ],
    "sg:phone":"+61 402 634 820",
    "sg:postcode":"7250",
    "sg:province":"TAS",
    "sg:tags":[
        "drama",
        "tuition"
    ],
    "wof:name":"Second Storey Youth Theatre",
    "wof:placetype":"venue"
},
  "geometry": {"coordinates":[147.138504028,-41.4452018738],"type":"Point"}
}