{
  "type": "Feature",
  "properties": {
    "addr:full":"86 Burns Pde Chapel Hill QLD 4069",
    "addr:housenumber":"86",
    "addr:postcode":"4069",
    "addr:street":"Burns Pde",
    "iso:country":"AU",
    "sg:address":"86 Burns Pde",
    "sg:city":"Chapel Hill",
    "sg:classifiers":[
        {
            "category":"Professional",
            "subcategory":"Business Services",
            "type":"Services"
        }
    ],
    "sg:phone":"+61 7 3701 5488",
    "sg:postcode":"4069",
    "sg:province":"QLD",
    "sg:tags":[
        "small",
        "advisory"
    ],
    "wof:name":"Prophet Strategies",
    "wof:placetype":"venue"
},
  "geometry": {"coordinates":[152.951660156,-27.5133419037],"type":"Point"}
}