{
  "type": "Feature",
  "properties": {
    "iso:country":"AU",
    "sg:address":"2 Monet Crs",
    "sg:city":"Mackenzie",
    "sg:classifiers":[
        {
            "category":"Arts & Performance",
            "subcategory":"Dance",
            "type":"Entertainment"
        }
    ],
    "sg:phone":"+61 7 3849 3015",
    "sg:postcode":"4156",
    "sg:province":"QLD",
    "sg:tags":[
        "theatrical",
        "ballet",
        "tuition"
    ],
    "wof:name":"Entertainment Unlimited",
    "wof:placetype":"venue"
},
  "geometry": {"coordinates":[153.122116089,-27.5388393402],"type":"Point"}
}