{
  "type": "Feature",
  "properties": {
    "iso:country":"AU",
    "sg:address":"145 Gladstone St",
    "sg:city":"South Melbourne",
    "sg:classifiers":[
        {
            "category":"Retail",
            "subcategory":"Auto Repair",
            "type":"Services"
        }
    ],
    "sg:phone":"+61 3 9690 7776",
    "sg:postcode":"3205",
    "sg:province":"VIC",
    "sg:tags":[
        "beater",
        "painter",
        "panel"
    ],
    "wof:name":"Spencer Panels Pty Ltd",
    "wof:placetype":"venue"
},
  "geometry": {"coordinates":[144.949234,-37.830578],"type":"Point"}
}