{
  "type": "Feature",
  "properties": {
    "addr:full":"4 Centennial Plz 300 Elizabeth Surry Hills NSW 2010",
    "addr:housenumber":"4;300",
    "addr:postcode":"2010",
    "addr:street":"Centennial Plz",
    "iso:country":"AU",
    "sg:address":"4 Centennial Plz 300",
    "sg:city":"Elizabeth Surry Hills",
    "sg:classifiers":[
        {
            "category":"Fast Food",
            "type":"Food & Drink"
        }
    ],
    "sg:phone":"+61 2 9281 2886",
    "sg:postcode":"2010",
    "sg:province":"NSW",
    "sg:tags":[
        "away",
        "take"
    ],
    "wof:name":"Angelos Seafood",
    "wof:placetype":"venue"
},
  "geometry": {"coordinates":[151.20854187,-33.8831214905],"type":"Point"}
}