{
  "type": "Feature",
  "properties": {
    "addr:full":"Shop 100 Mandurah Forum Mandurah WA 6210",
    "addr:housenumber":"100",
    "addr:postcode":"6210",
    "addr:street":"Mandurah",
    "iso:country":"AU",
    "sg:address":"Shop 100 Mandurah Forum",
    "sg:city":"Mandurah",
    "sg:classifiers":[
        {
            "category":"Fast Food",
            "type":"Food & Drink"
        }
    ],
    "sg:phone":"+61 8 9586 1315",
    "sg:postcode":"6210",
    "sg:province":"WA",
    "sg:tags":[
        "away",
        "take"
    ],
    "wof:name":"Coffee Break",
    "wof:placetype":"venue"
},
  "geometry": {"coordinates":[115.72232099999999,-32.525631],"type":"Point"}
}