{
  "type": "Feature",
  "properties": {
    "addr:full":"Roma St Morven QLD 4468",
    "addr:postcode":"4468",
    "addr:street":"Roma St",
    "iso:country":"AU",
    "sg:address":"Roma St",
    "sg:city":"Morven",
    "sg:classifiers":[
        {
            "category":"Social Services",
            "subcategory":"Job Training",
            "type":"Services"
        }
    ],
    "sg:phone":"+61 7 4654 8137",
    "sg:postcode":"4468",
    "sg:province":"QLD",
    "sg:tags":[
        "tannery"
    ],
    "wof:name":"Bonsella Holdings Pty Ltd",
    "wof:placetype":"venue"
},
  "geometry": {"coordinates":[147.119049072,-26.4162807465],"type":"Point"}
}