{
  "type": "Feature",
  "properties": {
    "addr:full":"28 Burke Rd Malvern East VIC 3145",
    "addr:housenumber":"28",
    "addr:postcode":"3145",
    "addr:street":"Burke Rd",
    "iso:country":"AU",
    "sg:address":"28 Burke Rd",
    "sg:city":"Malvern East",
    "sg:classifiers":[
        {
            "category":"Building & Trades",
            "subcategory":"Construction",
            "type":"Services"
        }
    ],
    "sg:phone":"+61 3 9571 8231",
    "sg:postcode":"3145",
    "sg:province":"VIC",
    "sg:tags":[
        "stonework",
        "stone",
        "mason"
    ],
    "wof:name":"Exclusive Ceramics (Vic) Pty Ltd",
    "wof:placetype":"venue"
},
  "geometry": {"coordinates":[145.04830932600001,-37.8760910034],"type":"Point"}
}