{
  "type": "Feature",
  "properties": {
    "addr:full":"32 Gifford Rd Dunsborough WA 6281",
    "addr:housenumber":"32",
    "addr:postcode":"6281",
    "addr:street":"Gifford Rd",
    "iso:country":"AU",
    "sg:address":"32 Gifford Rd",
    "sg:city":"Dunsborough",
    "sg:classifiers":[
        {
            "category":"Health Services",
            "subcategory":"Doctor",
            "type":"Services"
        }
    ],
    "sg:phone":"+61 8 9756 8999",
    "sg:postcode":"6281",
    "sg:province":"WA",
    "sg:tags":[
        "medical",
        "practitioner"
    ],
    "wof:name":"Buckeridge Paul",
    "wof:placetype":"venue"
},
  "geometry": {"coordinates":[115.102111816,-33.6014823914],"type":"Point"}
}