{
  "type": "Feature",
  "properties": {
    "iso:country":"AU",
    "sg:address":"Level 1, 300 George St",
    "sg:city":"Sydney",
    "sg:classifiers":[
        {
            "category":"Health Services",
            "subcategory":"Dentist",
            "type":"Services"
        }
    ],
    "sg:phone":"+61 2 9232 3900",
    "sg:postcode":"2000",
    "sg:province":"NSW",
    "sg:website":"http://www.sydneycitydental.com.au",
    "wof:name":"Tooth Whitening Information Line",
    "wof:placetype":"venue"
},
  "geometry": {"coordinates":[151.207427978,-33.8656806946],"type":"Point"}
}