{
  "type": "Feature",
  "properties": {
    "addr:full":"Cnr of Station & Oxford St Box Hill VIC 3128",
    "addr:postcode":"3128",
    "addr:street":"St",
    "iso:country":"AU",
    "sg:address":"Cnr of Station & Oxford St",
    "sg:city":"Box Hill",
    "sg:classifiers":[
        {
            "category":"Education",
            "subcategory":"Dance Studio",
            "type":"Public Place"
        }
    ],
    "sg:phone":"+61 3 9878 8830",
    "sg:postcode":"3128",
    "sg:province":"VIC",
    "sg:tags":[
        "venue",
        "tuition"
    ],
    "wof:name":"Sway Dance Studio",
    "wof:placetype":"venue"
},
  "geometry": {"coordinates":[145.121383667,-37.8217124939],"type":"Point"}
}