{
  "type": "Feature",
  "properties": {
    "addr:full":"Torrens Vale Rd Yankalilla SA 5203",
    "addr:postcode":"5203",
    "addr:street":"Torrens Vale Rd",
    "iso:country":"AU",
    "sg:address":"Torrens Vale Rd",
    "sg:city":"Yankalilla",
    "sg:classifiers":[
        {
            "category":"Building & Trades",
            "subcategory":"Landscaping Services",
            "type":"Services"
        }
    ],
    "sg:phone":"+61 8 8558 2655",
    "sg:postcode":"5203",
    "sg:province":"SA",
    "sg:tags":[
        "grazier"
    ],
    "wof:name":"Stone R G & M J",
    "wof:placetype":"venue"
},
  "geometry": {"coordinates":[138.381515503,-35.4935264587],"type":"Point"}
}