{
  "type": "Feature",
  "properties": {
    "addr:full":"51 Sugar Rd Maroochydore QLD 4558",
    "addr:housenumber":"51",
    "addr:postcode":"4558",
    "addr:street":"Sugar Rd",
    "iso:country":"AU",
    "sg:address":"51 Sugar Rd",
    "sg:city":"Maroochydore",
    "sg:classifiers":[
        {
            "category":"Autos & Motor Vehicles",
            "subcategory":"Auto Supplies",
            "type":"Retail Goods"
        }
    ],
    "sg:phone":"+61 7 5479 3294",
    "sg:postcode":"4558",
    "sg:province":"QLD",
    "sg:tags":[
        "camper-trailers",
        "caravan",
        "equipment"
    ],
    "wof:name":"The Great Outdoors",
    "wof:placetype":"venue"
},
  "geometry": {"coordinates":[153.09275817899999,-26.666601181],"type":"Point"}
}