{
  "type": "Feature",
  "properties": {
    "addr:full":"551- 553 Barkly St Footscray West VIC 3012",
    "addr:housenumber":"551 553",
    "addr:postcode":"3012",
    "addr:street":"Barkly St",
    "iso:country":"AU",
    "sg:address":"551- 553 Barkly St",
    "sg:city":"Footscray West",
    "sg:classifiers":[
        {
            "category":"Communications",
            "subcategory":"Film & Video Production",
            "type":"Services"
        }
    ],
    "sg:phone":"+61 3 9689 8836",
    "sg:postcode":"3012",
    "sg:province":"VIC",
    "sg:tags":[
        "dvd",
        "library"
    ],
    "wof:name":"Network Video",
    "wof:placetype":"venue"
},
  "geometry": {"coordinates":[144.87718200699999,-37.7974357605],"type":"Point"}
}