{
  "type": "Feature",
  "properties": {
    "addr:full":"50 Brisbane St Murwillumbah NSW 2484",
    "addr:housenumber":"50",
    "addr:postcode":"2484",
    "addr:street":"Brisbane St",
    "iso:country":"AU",
    "sg:address":"50 Brisbane St",
    "sg:city":"Murwillumbah",
    "sg:classifiers":[
        {
            "category":"Building & Trades",
            "subcategory":"Construction",
            "type":"Services"
        }
    ],
    "sg:phone":"+61 412 576 860",
    "sg:postcode":"2484",
    "sg:province":"NSW",
    "sg:tags":[
        "plasterboard",
        "plasterer",
        "fixer"
    ],
    "wof:name":"Kennaugh R M",
    "wof:placetype":"venue"
},
  "geometry": {"coordinates":[153.395141602,-28.3321418762],"type":"Point"}
}