{
  "type": "Feature",
  "properties": {
    "iso:country":"AU",
    "sg:address":"York Rd",
    "sg:city":"Quairading",
    "sg:classifiers":[
        {
            "category":"Autos & Motor Vehicles",
            "subcategory":"Fuel & Gas Station",
            "type":"Retail Goods"
        }
    ],
    "sg:phone":"+61 8 9645 1230",
    "sg:postcode":"6383",
    "sg:province":"WA",
    "wof:name":"BP Australia Limited",
    "wof:placetype":"venue"
},
  "geometry": {"coordinates":[117.40125999999999,-32.010132],"type":"Point"}
}