{
  "type": "Feature",
  "properties": {
    "addr:full":"Cnr Jersey Rd & Bunting St Emerton NSW 2770",
    "addr:postcode":"2770",
    "addr:street":"Jersey Rd & Bunting St",
    "iso:country":"AU",
    "sg:address":"Cnr Jersey Rd & Bunting St",
    "sg:city":"Emerton",
    "sg:classifiers":[
        {
            "category":"Food & Beverages",
            "subcategory":"Supermarket",
            "type":"Retail Goods"
        }
    ],
    "sg:phone":"+61 2 9835 6288",
    "sg:postcode":"2770",
    "sg:province":"NSW",
    "sg:tags":[
        "grocery",
        "store"
    ],
    "wof:name":"Woolworths Limited",
    "wof:placetype":"venue"
},
  "geometry": {"coordinates":[150.80612182600001,-33.7428092957],"type":"Point"}
}