{
  "type": "Feature",
  "properties": {
    "addr:full":"96 Showground Rd Gosford North NSW 2250",
    "addr:housenumber":"96",
    "addr:postcode":"2250",
    "addr:street":"Showground Rd",
    "iso:country":"AU",
    "sg:address":"96 Showground Rd",
    "sg:city":"Gosford North",
    "sg:classifiers":[
        {
            "category":"Retail",
            "subcategory":"Auto Repair",
            "type":"Services"
        }
    ],
    "sg:phone":"+61 2 4324 3996",
    "sg:postcode":"2250",
    "sg:province":"NSW",
    "sg:tags":[
        "repairer",
        "motor",
        "engineer"
    ],
    "wof:name":"North Gosford Automotive Repairs",
    "wof:placetype":"venue"
},
  "geometry": {"coordinates":[151.34437560999999,-33.411693573],"type":"Point"}
}