{
  "type": "Feature",
  "properties": {
    "addr:full":"623 Plenty Rd Preston VIC 3072",
    "addr:housenumber":"623",
    "addr:postcode":"3072",
    "addr:street":"Plenty Rd",
    "iso:country":"AU",
    "sg:address":"623 Plenty Rd",
    "sg:city":"Preston",
    "sg:classifiers":[
        {
            "category":"Education",
            "subcategory":"Vocational School",
            "type":"Public Place"
        }
    ],
    "sg:phone":"+61 3 9478 5235",
    "sg:postcode":"3072",
    "sg:province":"VIC",
    "sg:tags":[
        "beauty"
    ],
    "wof:name":"All Star Professional Beauty Training",
    "wof:placetype":"venue"
},
  "geometry": {"coordinates":[145.100067139,-37.7292747498],"type":"Point"}
}