{
  "type": "Feature",
  "properties": {
    "addr:full":"47 Bay Rd Taren Point NSW 2229",
    "addr:housenumber":"47",
    "addr:postcode":"2229",
    "addr:street":"Bay Rd",
    "iso:country":"AU",
    "sg:address":"47 Bay Rd",
    "sg:city":"Taren Point",
    "sg:classifiers":[
        {
            "category":"Professional",
            "subcategory":"Art Services",
            "type":"Services"
        }
    ],
    "sg:phone":"+61 2 9525 0355",
    "sg:postcode":"2229",
    "sg:province":"NSW",
    "sg:tags":[
        "graphic",
        "designer"
    ],
    "wof:name":"Presrose Pty Ltd",
    "wof:placetype":"venue"
},
  "geometry": {"coordinates":[151.122955322,-34.0229759216],"type":"Point"}
}