{
  "type": "Feature",
  "properties": {
    "iso:country":"AU",
    "sg:address":"Cnr Hughes St & Railway Pde",
    "sg:city":"Cabramatta",
    "sg:classifiers":[
        {
            "category":"Professional",
            "subcategory":"Accounting & Tax Preparation",
            "type":"Services"
        }
    ],
    "sg:phone":"+61 2 9724 1668",
    "sg:postcode":"2166",
    "sg:province":"NSW",
    "sg:tags":[
        "consultant",
        "taxation"
    ],
    "wof:name":"MB Tax",
    "wof:placetype":"venue"
},
  "geometry": {"coordinates":[150.93797302199999,-33.8936462402],"type":"Point"}
}