{
  "type": "Feature",
  "properties": {
    "iso:country":"AU",
    "sg:address":"369 New South Head Rd",
    "sg:city":"Double Bay",
    "sg:classifiers":[
        {
            "category":"Personal",
            "subcategory":"Beauty Salon",
            "type":"Services"
        }
    ],
    "sg:phone":"+61 2 9328 2090",
    "sg:postcode":"2028",
    "sg:province":"NSW",
    "sg:tags":[
        "hairdresser"
    ],
    "wof:name":"Platino Salon",
    "wof:placetype":"venue"
},
  "geometry": {"coordinates":[151.24252319300001,-33.878276825],"type":"Point"}
}