{
  "type": "Feature",
  "properties": {
    "iso:country":"AU",
    "sg:address":"38 Jetty Rd",
    "sg:city":"Glenelg",
    "sg:classifiers":[
        {
            "category":"Fast Food",
            "type":"Food & Drink"
        }
    ],
    "sg:phone":"+61 8 8295 8177",
    "sg:postcode":"5045",
    "sg:province":"SA",
    "sg:tags":[
        "away",
        "take"
    ],
    "wof:name":"Makis BBQ Eating & Takeaway",
    "wof:placetype":"venue"
},
  "geometry": {"coordinates":[138.512726,-34.980492],"type":"Point"}
}