{
  "type": "Feature",
  "properties": {
    "addr:full":"3 Bostock Crt Thomastown VIC 3074",
    "addr:housenumber":"3",
    "addr:postcode":"3074",
    "addr:street":"Bostock Crt",
    "iso:country":"AU",
    "sg:address":"3 Bostock Crt",
    "sg:city":"Thomastown",
    "sg:classifiers":[
        {
            "category":"Retail",
            "subcategory":"Auto Repair",
            "type":"Services"
        }
    ],
    "sg:phone":"+61 3 9464 0494",
    "sg:postcode":"3074",
    "sg:province":"VIC",
    "sg:tags":[
        "testing",
        "inspection",
        "motor",
        "vehicle"
    ],
    "wof:name":"Mitsu Serv",
    "wof:placetype":"venue"
},
  "geometry": {"coordinates":[145.02589416500001,-37.6944007874],"type":"Point"}
}