{
  "type": "Feature",
  "properties": {
    "addr:full":"32 Margaret St Mt Gambier SA 5290",
    "addr:housenumber":"32",
    "addr:postcode":"5290",
    "addr:street":"Margaret St",
    "iso:country":"AU",
    "sg:address":"32 Margaret St",
    "sg:city":"Mt Gambier",
    "sg:classifiers":[
        {
            "category":"Wholesale",
            "subcategory":"Machinery & Supplies",
            "type":"Manufacturing & Wholesale Goods"
        }
    ],
    "sg:phone":"+61 8 8724 4500",
    "sg:postcode":"5290",
    "sg:province":"SA",
    "sg:tags":[
        "equipment",
        "welding"
    ],
    "wof:name":"GT Industrial Sales",
    "wof:placetype":"venue"
},
  "geometry": {"coordinates":[140.77479600000001,-37.83144],"type":"Point"}
}