{
  "type": "Feature",
  "properties": {
    "addr:full":"12 McNicol Rd Tecoma VIC 3160",
    "addr:housenumber":"12",
    "addr:postcode":"3160",
    "addr:street":"Mcnicol Rd",
    "iso:country":"AU",
    "sg:address":"12 McNicol Rd",
    "sg:city":"Tecoma",
    "sg:classifiers":[
        {
            "category":"Professional",
            "subcategory":"Art Services",
            "type":"Services"
        }
    ],
    "sg:phone":"+61 3 9754 2920",
    "sg:postcode":"3160",
    "sg:province":"VIC",
    "sg:tags":[
        "decorator",
        "painter"
    ],
    "wof:name":"Depace Sam",
    "wof:placetype":"venue"
},
  "geometry": {"coordinates":[145.34565734899999,-37.9096031189],"type":"Point"}
}