{
  "type": "Feature",
  "properties": {
    "iso:country":"AU",
    "sg:address":"5 Louttit Crt",
    "sg:city":"Toowoomba",
    "sg:classifiers":[
        {
            "category":"Professional",
            "type":"Services"
        }
    ],
    "sg:phone":"+61 407 860 852",
    "sg:postcode":"4350",
    "sg:province":"QLD",
    "sg:tags":[
        "courier"
    ],
    "wof:name":"Jams Express",
    "wof:placetype":"venue"
},
  "geometry": {"coordinates":[151.820358,-27.518396],"type":"Point"}
}