{
  "type": "Feature",
  "properties": {
    "iso:country":"AU",
    "sg:address":"6/ 11- 13 Maynard Drv",
    "sg:city":"Epsom",
    "sg:classifiers":[
        {
            "category":"Retail",
            "subcategory":"Auto Repair",
            "type":"Services"
        }
    ],
    "sg:phone":"+61 3 5448 5100",
    "sg:postcode":"3551",
    "sg:province":"VIC",
    "sg:tags":[
        "automotive",
        "air conditioning"
    ],
    "wof:name":"Kool Ideas",
    "wof:placetype":"venue"
},
  "geometry": {"coordinates":[144.317428589,-36.7069396973],"type":"Point"}
}