{
  "type": "Feature",
  "properties": {
    "addr:full":"1386 Port Drv Broome WA 6725",
    "addr:housenumber":"1386",
    "addr:postcode":"6725",
    "addr:street":"Port Drv",
    "iso:country":"AU",
    "sg:address":"1386 Port Drv",
    "sg:city":"Broome",
    "sg:classifiers":[
        {
            "category":"Transit Center",
            "subcategory":"Passenger",
            "type":"Transportation"
        }
    ],
    "sg:phone":"+61 8 9193 5108",
    "sg:postcode":"6725",
    "sg:province":"WA",
    "sg:tags":[
        "wood",
        "moulding",
        "plastic"
    ],
    "wof:name":"Broome Moulded Timber Products",
    "wof:placetype":"venue"
},
  "geometry": {"coordinates":[122.677589416,-18.2141704559],"type":"Point"}
}