{
  "type": "Feature",
  "properties": {
    "addr:full":"High St Nagambie VIC 3608",
    "addr:postcode":"3608",
    "addr:street":"High St",
    "iso:country":"AU",
    "sg:address":"High St",
    "sg:city":"Nagambie",
    "sg:classifiers":[
        {
            "category":"Government",
            "subcategory":"Post Office",
            "type":"Public Place"
        }
    ],
    "sg:phone":"+61 3 5794 2603",
    "sg:postcode":"3608",
    "sg:province":"VIC",
    "sg:tags":[
        "postal"
    ],
    "wof:name":"Australia Post",
    "wof:placetype":"venue"
},
  "geometry": {"coordinates":[145.15234375,-36.789981842],"type":"Point"}
}