{
  "type": "Feature",
  "properties": {
    "addr:full":"Unit 3,2-4 Corner Keppel Drive and Hallam Road, Hallam Hallam VIC 3803",
    "addr:housenumber":"3,2 -4",
    "addr:postcode":"3803",
    "addr:street":"Corner Keppel Drive;Hallam Road",
    "iso:country":"AU",
    "sg:address":"Unit 3,2-4 Corner Keppel Drive and Hallam Road, Hallam",
    "sg:city":"Hallam",
    "sg:classifiers":[
        {
            "category":"Farming",
            "subcategory":"Fish & Marine Products",
            "type":"Manufacturing & Wholesale Goods"
        }
    ],
    "sg:phone":"+61 3 9796 5000",
    "sg:postcode":"3803",
    "sg:province":"VIC",
    "sg:tags":[
        "wholesaler",
        "mfrs",
        "swimwear"
    ],
    "wof:name":"Pro-Am Australia",
    "wof:placetype":"venue"
},
  "geometry": {"coordinates":[145.27284240700001,-38.0156059265],"type":"Point"}
}