{
  "type": "Feature",
  "properties": {
    "iso:country":"AU",
    "sg:address":"12 Grice St",
    "sg:city":"Clontarf",
    "sg:classifiers":[
        {
            "category":"Manufacturing",
            "subcategory":"Tools & Machinery",
            "type":"Manufacturing & Wholesale Goods"
        }
    ],
    "sg:phone":"+61 7 3284 4020",
    "sg:postcode":"4019",
    "sg:province":"QLD",
    "sg:tags":[
        "toolmaker"
    ],
    "wof:name":"Margate Precision Engineering",
    "wof:placetype":"venue"
},
  "geometry": {"coordinates":[153.08004760700001,-27.2397785187],"type":"Point"}
}