{
  "type": "Feature",
  "properties": {
    "iso:country":"AU",
    "sg:address":"182 Bennett St",
    "sg:city":"East Perth",
    "sg:classifiers":[
        {
            "category":"Professional",
            "subcategory":"Engineering",
            "type":"Services"
        }
    ],
    "sg:phone":"+61 8 9325 4774",
    "sg:postcode":"6004",
    "sg:province":"WA",
    "sg:tags":[
        "consultant",
        "geotechnical",
        "engineer"
    ],
    "wof:name":"Douglas Partners Pty Ltd",
    "wof:placetype":"venue"
},
  "geometry": {"coordinates":[115.87299346899999,-31.9562778473],"type":"Point"}
}