{
  "type": "Feature",
  "properties": {
    "addr:full":"16 Fiveash Drv Pasadena SA 5042",
    "addr:housenumber":"16",
    "addr:postcode":"5042",
    "addr:street":"Fiveash Drv",
    "iso:country":"AU",
    "sg:address":"16 Fiveash Drv",
    "sg:city":"Pasadena",
    "sg:classifiers":[
        {
            "category":"Food & Beverages",
            "subcategory":"Fruits & Vegetables",
            "type":"Retail Goods"
        }
    ],
    "sg:phone":"+61 8 8276 6821",
    "sg:postcode":"5042",
    "sg:province":"SA",
    "sg:tags":[
        "greengrocer",
        "fruiterer"
    ],
    "wof:name":"Pasadena Fruit Mart",
    "wof:placetype":"venue"
},
  "geometry": {"coordinates":[138.59103400000001,-35.00106],"type":"Point"}
}