{
  "type": "Feature",
  "properties": {
    "iso:country":"AU",
    "sg:address":"UWS Hawkesbury Campus Cnr Vines Drv & Smithy Pl",
    "sg:city":"Richmond",
    "sg:classifiers":[
        {
            "category":"Sports & Exercise",
            "subcategory":"Gym",
            "type":"Entertainment"
        }
    ],
    "sg:phone":"+61 2 4570 1782",
    "sg:postcode":"2753",
    "sg:province":"NSW",
    "sg:tags":[
        "personal",
        "trainer",
        "fitness"
    ],
    "wof:name":"Unifit Health & Leisure Centre",
    "wof:placetype":"venue"
},
  "geometry": {"coordinates":[150.74331665,-33.61170578],"type":"Point"}
}