{
  "type": "Feature",
  "properties": {
    "addr:full":"160 Faulkner St Armidale NSW 2350",
    "addr:housenumber":"160",
    "addr:postcode":"2350",
    "addr:street":"Faulkner St",
    "iso:country":"AU",
    "sg:address":"160 Faulkner St",
    "sg:city":"Armidale",
    "sg:classifiers":[
        {
            "category":"Building & Trades",
            "subcategory":"Landscaping Services",
            "type":"Services"
        }
    ],
    "sg:phone":"+61 2 6771 2812",
    "sg:postcode":"2350",
    "sg:province":"NSW",
    "sg:tags":[
        "grazier"
    ],
    "wof:name":"Coventry A W G",
    "wof:placetype":"venue"
},
  "geometry": {"coordinates":[151.664154053,-30.5214614868],"type":"Point"}
}