{
  "type": "Feature",
  "properties": {
    "iso:country":"AU",
    "sg:address":"418 Murray Rd",
    "sg:city":"Preston",
    "sg:classifiers":[
        {
            "category":"Travel",
            "subcategory":"Hostel",
            "type":"Entertainment"
        }
    ],
    "sg:phone":"+61 3 9470 1006",
    "sg:postcode":"3072",
    "sg:province":"VIC",
    "sg:tags":[
        "home"
    ],
    "wof:name":"Terrace Travellers Hostel Australia The",
    "wof:placetype":"venue"
},
  "geometry": {"coordinates":[144.99723815900001,-37.7370948792],"type":"Point"}
}