{
  "type": "Feature",
  "properties": {
    "iso:country":"AU",
    "sg:address":"2 Collins St",
    "sg:city":"North Ryde",
    "sg:classifiers":[
        {
            "category":"Building & Trades",
            "subcategory":"Plumbing",
            "type":"Services"
        }
    ],
    "sg:phone":"+61 411 112 520",
    "sg:postcode":"2113",
    "sg:province":"NSW",
    "sg:tags":[
        "plumber",
        "gasfitters"
    ],
    "wof:name":"Advance Plumbing Service Pty Ltd",
    "wof:placetype":"venue"
},
  "geometry": {"coordinates":[151.12794494600001,-33.7937698364],"type":"Point"}
}