{
  "type": "Feature",
  "properties": {
    "addr:full":"Shop 1B/ 6 Thomas St Noosaville QLD 4566",
    "addr:housenumber":"shop 1b / 6",
    "addr:postcode":"4566",
    "addr:street":"Thomas St",
    "iso:country":"AU",
    "sg:address":"Shop 1B/ 6 Thomas St",
    "sg:city":"Noosaville",
    "sg:classifiers":[
        {
            "category":"Shopping",
            "subcategory":"Clothing, Apparel, & Fashions",
            "type":"Retail Goods"
        }
    ],
    "sg:phone":"+61 7 5474 3555",
    "sg:postcode":"4566",
    "sg:province":"QLD",
    "sg:tags":[
        "lady",
        "wear"
    ],
    "wof:name":"Vanity Fair",
    "wof:placetype":"venue"
},
  "geometry": {"coordinates":[153.06231689399999,-26.3985118866],"type":"Point"}
}