{
  "type": "Feature",
  "properties": {
    "iso:country":"AU",
    "sg:address":"20- 21 Sleigh Pl",
    "sg:city":"Wetherill Park",
    "sg:classifiers":[
        {
            "category":"Farming",
            "subcategory":"Farm & Veterinary Services",
            "type":"Manufacturing & Wholesale Goods"
        }
    ],
    "sg:phone":"+61 2 8787 4100",
    "sg:postcode":"2164",
    "sg:province":"NSW",
    "sg:tags":[
        "irrigation",
        "reticulation",
        "system"
    ],
    "wof:name":"Toro Australia Pty Ltd",
    "wof:placetype":"venue"
},
  "geometry": {"coordinates":[150.88250732399999,-33.8392066956],"type":"Point"}
}