{
  "type": "Feature",
  "properties": {
    "addr:full":"3 Smeed St Black Rock VIC 3193",
    "addr:housenumber":"3",
    "addr:postcode":"3193",
    "addr:street":"Smeed St",
    "iso:country":"AU",
    "sg:address":"3 Smeed St",
    "sg:city":"Black Rock",
    "sg:classifiers":[
        {
            "category":"Professional",
            "subcategory":"Computer Services",
            "type":"Services"
        }
    ],
    "sg:phone":"+61 3 9521 0323",
    "sg:postcode":"3193",
    "sg:province":"VIC",
    "sg:tags":[
        "consultant",
        "system"
    ],
    "wof:name":"Russell Helen Computer Training Services",
    "wof:placetype":"venue"
},
  "geometry": {"coordinates":[145.01490783700001,-37.9653282166],"type":"Point"}
}