{
  "type": "Feature",
  "properties": {
    "iso:country":"AU",
    "sg:address":"90 Fitzroy St",
    "sg:city":"Grafton",
    "sg:classifiers":[
        {
            "category":"Professional",
            "subcategory":"Accounting & Tax Preparation",
            "type":"Services"
        }
    ],
    "sg:phone":"+61 2 6642 4866",
    "sg:postcode":"2460",
    "sg:province":"NSW",
    "sg:tags":[
        "accountant",
        "auditor"
    ],
    "wof:name":"Trimble Ensbey & Associates",
    "wof:placetype":"venue"
},
  "geometry": {"coordinates":[152.934280395,-29.6916484833],"type":"Point"}
}