{
  "type": "Feature",
  "properties": {
    "addr:full":"1/ 183 Great Eastern Hwy Belmont WA 6104",
    "addr:housenumber":"/ 183",
    "addr:postcode":"6104",
    "addr:street":"Great Eastern Hwy",
    "iso:country":"AU",
    "sg:address":"1/ 183 Great Eastern Hwy",
    "sg:city":"Belmont",
    "sg:classifiers":[
        {
            "category":"Shopping",
            "subcategory":"Mobile Phones",
            "type":"Retail Goods"
        }
    ],
    "sg:phone":"+61 8 9478 8220",
    "sg:postcode":"6104",
    "sg:province":"WA",
    "sg:tags":[
        "telephone",
        "accessory"
    ],
    "wof:name":"Allphones",
    "wof:placetype":"venue"
},
  "geometry": {"coordinates":[115.91990661600001,-31.9457073212],"type":"Point"}
}