{
  "type": "Feature",
  "properties": {
    "addr:full":"Branscombe Rd Walkerston QLD 4751",
    "addr:postcode":"4751",
    "addr:street":"Branscombe Rd",
    "iso:country":"AU",
    "sg:address":"Branscombe Rd",
    "sg:city":"Walkerston",
    "sg:classifiers":[
        {
            "category":"Arena",
            "subcategory":"Sports Club",
            "type":"Entertainment"
        }
    ],
    "sg:phone":"+61 7 4959 2480",
    "sg:postcode":"4751",
    "sg:province":"QLD",
    "sg:tags":[
        "league",
        "rugby"
    ],
    "wof:name":"Western Suburbs Rugby League Football Club",
    "wof:placetype":"venue"
},
  "geometry": {"coordinates":[149.06353799999999,-21.158554],"type":"Point"}
}