{
  "type": "Feature",
  "properties": {
    "iso:country":"AU",
    "sg:address":"Cnr Belmore Rd & Littleton St",
    "sg:city":"Riverwood",
    "sg:classifiers":[
        {
            "category":"Wholesale",
            "subcategory":"Medical Equipment & Supplies",
            "type":"Manufacturing & Wholesale Goods"
        }
    ],
    "sg:phone":"+61 2 9153 6267",
    "sg:postcode":"2210",
    "sg:province":"NSW",
    "sg:tags":[
        "aids",
        "hearing"
    ],
    "wof:name":"Hearing Plus",
    "wof:placetype":"venue"
},
  "geometry": {"coordinates":[151.051666,-33.953705],"type":"Point"}
}