{
  "type": "Feature",
  "properties": {
    "addr:full":"323 Pacific Hwy Lindfield NSW 2070",
    "addr:housenumber":"323",
    "addr:postcode":"2070",
    "addr:street":"Pacific Hwy",
    "iso:country":"AU",
    "sg:address":"323 Pacific Hwy",
    "sg:city":"Lindfield",
    "sg:classifiers":[
        {
            "category":"Professional",
            "subcategory":"Art Services",
            "type":"Services"
        }
    ],
    "sg:phone":"+61 2 9416 7077",
    "sg:postcode":"2070",
    "sg:province":"NSW",
    "sg:tags":[
        "interior",
        "designer"
    ],
    "wof:name":"Cerise Design",
    "wof:placetype":"venue"
},
  "geometry": {"coordinates":[151.16894531200001,-33.7761650085],"type":"Point"}
}