{
  "type": "Feature",
  "properties": {
    "iso:country":"AU",
    "sg:address":"97 Back Brawlin Rd",
    "sg:city":"Cootamundra",
    "sg:classifiers":[
        {
            "category":"Professional",
            "subcategory":"Art Services",
            "type":"Services"
        }
    ],
    "sg:phone":"+61 2 6942 3505",
    "sg:postcode":"2590",
    "sg:province":"NSW",
    "sg:tags":[
        "decorator",
        "painter"
    ],
    "wof:name":"Berkrey W A & M L",
    "wof:placetype":"venue"
},
  "geometry": {"coordinates":[148.01138305699999,-34.6321907043],"type":"Point"}
}