{
  "type": "Feature",
  "properties": {
    "iso:country":"AU",
    "sg:address":"8 Napier St",
    "sg:city":"Concord",
    "sg:classifiers":[
        {
            "category":"Professional",
            "subcategory":"Computer Services",
            "type":"Services"
        }
    ],
    "sg:phone":"+61 2 9746 1500",
    "sg:postcode":"2137",
    "sg:province":"NSW",
    "sg:tags":[
        "consultant",
        "system"
    ],
    "wof:name":"Claireheath Pty Ltd",
    "wof:placetype":"venue"
},
  "geometry": {"coordinates":[151.09237670900001,-33.8620033264],"type":"Point"}
}