{
  "type": "Feature",
  "properties": {
    "addr:full":"51 Main St Maldon VIC 3463",
    "addr:housenumber":"51",
    "addr:postcode":"3463",
    "addr:street":"Main St",
    "iso:country":"AU",
    "sg:address":"51 Main St",
    "sg:city":"Maldon",
    "sg:classifiers":[
        {
            "category":"Food & Beverages",
            "subcategory":"Bakery",
            "type":"Retail Goods"
        }
    ],
    "sg:phone":"+61 3 5475 2713",
    "sg:postcode":"3463",
    "sg:province":"VIC",
    "sg:tags":[
        "baker"
    ],
    "wof:name":"Maldon Historic Bakery",
    "wof:placetype":"venue"
},
  "geometry": {"coordinates":[143.901855469,-36.826675415],"type":"Point"}
}