{
  "type": "Feature",
  "properties": {
    "iso:country":"AU",
    "sg:address":"Boonooroo Park Shopping Centre Shop 1C, Nielsens Rd",
    "sg:city":"Carrara",
    "sg:classifiers":[
        {
            "category":"Professional",
            "subcategory":"Computer Services",
            "type":"Services"
        }
    ],
    "sg:phone":"+61 7 5594 5566",
    "sg:postcode":"4211",
    "sg:province":"QLD",
    "sg:tags":[
        "training"
    ],
    "wof:name":"Arthur Donna",
    "wof:placetype":"venue"
},
  "geometry": {"coordinates":[153.38026428200001,-28.0215435028],"type":"Point"}
}