{
  "type": "Feature",
  "properties": {
    "addr:full":"75 Sheppard St Hume ACT 2620",
    "addr:housenumber":"75",
    "addr:postcode":"2620",
    "addr:street":"Sheppard St",
    "iso:country":"AU",
    "sg:address":"75 Sheppard St",
    "sg:city":"Hume",
    "sg:classifiers":[
        {
            "category":"Home & Garden",
            "subcategory":"Garden Supply",
            "type":"Retail Goods"
        }
    ],
    "sg:phone":"+61 2 6260 1556",
    "sg:postcode":"2620",
    "sg:province":"ACT",
    "sg:tags":[
        "landscape"
    ],
    "wof:name":"O&#039;Rourkes Landscapes Supplies",
    "wof:placetype":"venue"
},
  "geometry": {"coordinates":[149.163574219,-35.3935890198],"type":"Point"}
}