{
  "type": "Feature",
  "properties": {
    "iso:country":"AU",
    "sg:address":"46 Young St",
    "sg:city":"Sylvania",
    "sg:classifiers":[
        {
            "category":"Education",
            "subcategory":"Special Training",
            "type":"Public Place"
        }
    ],
    "sg:phone":"+61 408 143 004",
    "sg:postcode":"2224",
    "sg:province":"NSW",
    "sg:tags":[
        "tuition-educational"
    ],
    "wof:name":"Engineering Solutions",
    "wof:placetype":"venue"
},
  "geometry": {"coordinates":[151.09303283700001,-34.0110702515],"type":"Point"}
}