{
  "type": "Feature",
  "properties": {
    "addr:full":"36 Gibbs St Miranda NSW 2228",
    "addr:housenumber":"36",
    "addr:postcode":"2228",
    "addr:street":"Gibbs St Miranda",
    "iso:country":"AU",
    "sg:address":"36 Gibbs St",
    "sg:city":"Miranda",
    "sg:classifiers":[
        {
            "category":"Personal",
            "subcategory":"Piercing",
            "type":"Services"
        }
    ],
    "sg:phone":"+61 2 9540 2287",
    "sg:postcode":"2228",
    "sg:province":"NSW",
    "sg:tags":[
        "body",
        "ear"
    ],
    "wof:name":"Beauty & Body Care",
    "wof:placetype":"venue"
},
  "geometry": {"coordinates":[151.102096558,-34.0366668701],"type":"Point"}
}