{
  "type": "Feature",
  "properties": {
    "addr:full":"31 Sunderland St Moonah TAS 7009",
    "addr:housenumber":"31",
    "addr:postcode":"7009",
    "addr:street":"Sunderland St",
    "iso:country":"AU",
    "sg:address":"31 Sunderland St",
    "sg:city":"Moonah",
    "sg:classifiers":[
        {
            "category":"Communications",
            "subcategory":"Film & Video Production",
            "type":"Services"
        }
    ],
    "sg:phone":"+61 3 6273 4455",
    "sg:postcode":"7009",
    "sg:province":"TAS",
    "sg:tags":[
        "lighting",
        "emergency",
        "power"
    ],
    "wof:name":"White Lite Industries Pty Ltd",
    "wof:placetype":"venue"
},
  "geometry": {"coordinates":[147.29478454599999,-42.8404121399],"type":"Point"}
}