{
  "type": "Feature",
  "properties": {
    "addr:full":"81 Hudson Rd Albion QLD 4010",
    "addr:housenumber":"81",
    "addr:postcode":"4010",
    "addr:street":"Hudson Rd",
    "iso:country":"AU",
    "sg:address":"81 Hudson Rd",
    "sg:city":"Albion",
    "sg:classifiers":[
        {
            "category":"Retail",
            "subcategory":"Auto Repair",
            "type":"Services"
        }
    ],
    "sg:phone":"+61 7 3262 6955",
    "sg:postcode":"4010",
    "sg:province":"QLD",
    "sg:tags":[
        "muffler",
        "exhaust",
        "system"
    ],
    "wof:name":"A1 Exhausts",
    "wof:placetype":"venue"
},
  "geometry": {"coordinates":[153.04156494099999,-27.4285697937],"type":"Point"}
}