{
  "type": "Feature",
  "properties": {
    "addr:full":"15 Orleana St Flagstaff Hill SA 5159",
    "addr:housenumber":"15",
    "addr:postcode":"5159",
    "addr:street":"Orleana St",
    "iso:country":"AU",
    "sg:address":"15 Orleana St",
    "sg:city":"Flagstaff Hill",
    "sg:classifiers":[
        {
            "category":"Building & Trades",
            "subcategory":"Construction",
            "type":"Services"
        }
    ],
    "sg:phone":"+61 8 8270 2210",
    "sg:postcode":"5159",
    "sg:province":"SA",
    "sg:tags":[
        "tennis court",
        "repair"
    ],
    "wof:name":"Total Court Care",
    "wof:placetype":"venue"
},
  "geometry": {"coordinates":[138.58482360799999,-35.0443153381],"type":"Point"}
}