{
  "type": "Feature",
  "properties": {
    "iso:country":"AU",
    "sg:address":"42 Cavenagh St",
    "sg:city":"Darwin",
    "sg:classifiers":[
        {
            "category":"Industrial Area",
            "type":"Public Place"
        }
    ],
    "sg:phone":"+61 8 8981 8242",
    "sg:postcode":"0800",
    "sg:province":"NT",
    "sg:tags":[
        "protective",
        "clothing"
    ],
    "wof:name":"N.T. General Store The",
    "wof:placetype":"venue"
},
  "geometry": {"coordinates":[130.84226989699999,-12.461388588],"type":"Point"}
}