{
  "type": "Feature",
  "properties": {
    "iso:country":"AU",
    "sg:address":"Shop 3, 21- 29 Bridge St",
    "sg:city":"Muswellbrook",
    "sg:classifiers":[
        {
            "category":"Real Estate",
            "subcategory":"Real Estate Agent",
            "type":"Services"
        }
    ],
    "sg:phone":"+61 2 6541 0555",
    "sg:postcode":"2333",
    "sg:province":"NSW",
    "wof:name":"Century 21 Sharon Jurd Real Estate",
    "wof:placetype":"venue"
},
  "geometry": {"coordinates":[150.888305664,-32.2650222778],"type":"Point"}
}