{
  "type": "Feature",
  "properties": {
    "addr:full":"19 High St Berwick VIC 3806",
    "addr:housenumber":"19",
    "addr:postcode":"3806",
    "addr:street":"High St",
    "iso:country":"AU",
    "sg:address":"19 High St",
    "sg:city":"Berwick",
    "sg:classifiers":[
        {
            "category":"Shopping",
            "subcategory":"Clothing, Apparel, & Fashions",
            "type":"Retail Goods"
        }
    ],
    "sg:phone":"+61 3 9707 3597",
    "sg:postcode":"3806",
    "sg:province":"VIC",
    "sg:tags":[
        "boutique"
    ],
    "wof:name":"Pol Boutique",
    "wof:placetype":"venue"
},
  "geometry": {"coordinates":[145.34492492699999,-38.0307579041],"type":"Point"}
}