{
  "type": "Feature",
  "properties": {
    "iso:country":"AU",
    "sg:address":"Young St",
    "sg:city":"Carrington",
    "sg:classifiers":[
        {
            "category":"Education",
            "subcategory":"School",
            "type":"Public Place"
        }
    ],
    "sg:phone":"+61 2 4969 3707",
    "sg:postcode":"2294",
    "sg:province":"NSW",
    "sg:tags":[
        "state",
        "-",
        "nsw"
    ],
    "wof:name":"Carrington Public",
    "wof:placetype":"venue"
},
  "geometry": {"coordinates":[151.76490783700001,-32.9124794006],"type":"Point"}
}