{
  "type": "Feature",
  "properties": {
    "iso:country":"AU",
    "sg:address":"1487 Main South Rd",
    "sg:city":"Darlington",
    "sg:classifiers":[
        {
            "category":"Fast Food",
            "type":"Food & Drink"
        }
    ],
    "sg:phone":"+61 8 8296 4032",
    "sg:postcode":"5047",
    "sg:province":"SA",
    "sg:tags":[
        "away",
        "take"
    ],
    "wof:name":"Subway",
    "wof:placetype":"venue"
},
  "geometry": {"coordinates":[138.561142,-35.024887],"type":"Point"}
}