{
  "type": "Feature",
  "properties": {
    "iso:country":"AU",
    "sg:address":"Suite A13, 550 Canning Hwy",
    "sg:city":"Attadale",
    "sg:classifiers":[
        {
            "category":"Health Services",
            "subcategory":"Health Practitioner",
            "type":"Services"
        }
    ],
    "sg:phone":"+61 431 656 111",
    "sg:postcode":"6156",
    "sg:province":"WA",
    "sg:tags":[
        "pathologist",
        "speech"
    ],
    "wof:name":"Nicole Street Speech Pathologist",
    "wof:placetype":"venue"
},
  "geometry": {"coordinates":[115.800613,-32.032238],"type":"Point"}
}