{
  "type": "Feature",
  "properties": {
    "addr:full":"70 Surrey Rd Blackburn North VIC 3130",
    "addr:housenumber":"70",
    "addr:postcode":"3130",
    "addr:street":"Surrey Rd",
    "iso:country":"AU",
    "sg:address":"70 Surrey Rd",
    "sg:city":"Blackburn North",
    "sg:classifiers":[
        {
            "category":"Building & Trades",
            "subcategory":"Cleaning & Sanitation",
            "type":"Services"
        }
    ],
    "sg:phone":"+61 414 348 391",
    "sg:postcode":"3130",
    "sg:province":"VIC",
    "sg:tags":[
        "window"
    ],
    "wof:name":"Betta Light Window Cleaning",
    "wof:placetype":"venue"
},
  "geometry": {"coordinates":[145.15861511200001,-37.8055725098],"type":"Point"}
}