{
  "type": "Feature",
  "properties": {
    "addr:full":"2a Kempster Rd Merewether NSW 2291",
    "addr:housenumber":"2a",
    "addr:postcode":"2291",
    "addr:street":"Kempster Rd",
    "iso:country":"AU",
    "sg:address":"2a Kempster Rd",
    "sg:city":"Merewether",
    "sg:classifiers":[
        {
            "category":"Professional",
            "subcategory":"Management & Consulting",
            "type":"Services"
        }
    ],
    "sg:phone":"+61 2 4963 6774",
    "sg:postcode":"2291",
    "sg:province":"NSW",
    "sg:tags":[
        "consultant",
        "relocation"
    ],
    "wof:name":"Hunter Relocations",
    "wof:placetype":"venue"
},
  "geometry": {"coordinates":[151.74801635700001,-32.9422874451],"type":"Point"}
}