{
  "type": "Feature",
  "properties": {
    "iso:country":"AU",
    "sg:address":"Cnr Wyong & Tumbi Creek Rds",
    "sg:city":"Tumbi Umbi",
    "sg:classifiers":[
        {
            "category":"Shopping",
            "subcategory":"Pets & Pet Supplies",
            "type":"Retail Goods"
        }
    ],
    "sg:phone":"+61 2 4388 3832",
    "sg:postcode":"2261",
    "sg:province":"NSW",
    "sg:tags":[
        "food"
    ],
    "wof:name":"Bird Barn & Tumbi Aquarium The",
    "wof:placetype":"venue"
},
  "geometry": {"coordinates":[151.449432,-33.362949],"type":"Point"}
}