{
  "type": "Feature",
  "properties": {
    "addr:full":"Unit 2/ 20 Spine St Sumner Park QLD 4074",
    "addr:housenumber":"20",
    "addr:postcode":"4074",
    "addr:street":"Spine St",
    "iso:country":"AU",
    "sg:address":"Unit 2/ 20 Spine St",
    "sg:city":"Sumner Park",
    "sg:classifiers":[
        {
            "category":"Building & Trades",
            "subcategory":"Equipment Rental",
            "type":"Services"
        }
    ],
    "sg:phone":"+61 7 3715 5477",
    "sg:postcode":"4074",
    "sg:province":"QLD",
    "sg:tags":[
        "party",
        "hire"
    ],
    "sg:website":"http://www.soundlighting.com.au",
    "wof:name":"Sound & Lighting Queensland",
    "wof:placetype":"venue"
},
  "geometry": {"coordinates":[152.93685913100001,-27.5650920868],"type":"Point"}
}