{
  "type": "Feature",
  "properties": {
    "addr:full":"Shp 3 Food Court Westfield Shpng Cntr Hornsby NSW 2077",
    "addr:housenumber":"3",
    "addr:postcode":"2077",
    "addr:street":"Food Court",
    "iso:country":"AU",
    "sg:address":"Shp 3 Food Court Westfield Shpng Cntr",
    "sg:city":"Hornsby",
    "sg:classifiers":[
        {
            "category":"Fast Food",
            "type":"Food & Drink"
        }
    ],
    "sg:phone":"+61 2 9987 0101",
    "sg:postcode":"2077",
    "sg:province":"NSW",
    "sg:tags":[
        "away",
        "take"
    ],
    "wof:name":"Cosmos Subs",
    "wof:placetype":"venue"
},
  "geometry": {"coordinates":[151.09687805199999,-33.7007789612],"type":"Point"}
}