{
  "type": "Feature",
  "properties": {
    "addr:full":"PO Box 3199 Morwell VIC 3841",
    "addr:postcode":"3841",
    "iso:country":"AU",
    "sg:address":"PO Box 3199",
    "sg:city":"Morwell",
    "sg:classifiers":[
        {
            "category":"Professional",
            "subcategory":"Computer Services",
            "type":"Services"
        }
    ],
    "sg:phone":"+61 412 931 747",
    "sg:postcode":"3841",
    "sg:province":"VIC",
    "sg:tags":[
        "technical",
        "support"
    ],
    "wof:name":"Computer Cure",
    "wof:placetype":"venue"
},
  "geometry": {"coordinates":[146.41244506800001,-38.3386192322],"type":"Point"}
}