{
  "type": "Feature",
  "properties": {
    "addr:full":"Shop 3D Salamander Shopng Cntr Salamander Bay NSW 2317",
    "addr:housenumber":"3d",
    "addr:postcode":"2317",
    "iso:country":"AU",
    "sg:address":"Shop 3D Salamander Shopng Cntr",
    "sg:city":"Salamander Bay",
    "sg:classifiers":[
        {
            "category":"Health Services",
            "subcategory":"Doctor",
            "type":"Services"
        }
    ],
    "sg:phone":"+61 2 4982 7660",
    "sg:postcode":"2317",
    "sg:province":"NSW",
    "sg:tags":[
        "medical",
        "practitioner"
    ],
    "wof:name":"Salamander Medical Centre",
    "wof:placetype":"venue"
},
  "geometry": {"coordinates":[152.08209199999999,-32.731091],"type":"Point"}
}