{
  "type": "Feature",
  "properties": {
    "addr:full":"19 Werril St Swan Hill VIC 3585",
    "addr:housenumber":"19",
    "addr:postcode":"3585",
    "addr:street":"Werril St",
    "iso:country":"AU",
    "sg:address":"19 Werril St",
    "sg:city":"Swan Hill",
    "sg:classifiers":[
        {
            "category":"Building & Trades",
            "subcategory":"Construction",
            "type":"Services"
        }
    ],
    "sg:phone":"+61 3 5033 0060",
    "sg:postcode":"3585",
    "sg:province":"VIC",
    "sg:tags":[
        "contractor"
    ],
    "wof:name":"Skinner R J & L M",
    "wof:placetype":"venue"
},
  "geometry": {"coordinates":[143.55946399999999,-35.359589],"type":"Point"}
}