{
  "type": "Feature",
  "properties": {
    "addr:full":"2064 Beaudesert Rd Sunnybank Hills QLD 4109",
    "addr:postcode":"2064;4109",
    "addr:street":"Beaudesert Rd",
    "iso:country":"AU",
    "sg:address":"2064 Beaudesert Rd",
    "sg:city":"Sunnybank Hills",
    "sg:classifiers":[
        {
            "category":"Arts & Performance",
            "subcategory":"Dance",
            "type":"Entertainment"
        }
    ],
    "sg:phone":"+61 7 3273 1535",
    "sg:postcode":"4109",
    "sg:province":"QLD",
    "sg:tags":[
        "theatrical",
        "ballet",
        "tuition"
    ],
    "wof:name":"Petrea Gibbins School Of Dancing",
    "wof:placetype":"venue"
},
  "geometry": {"coordinates":[153.04887390100001,-27.6086997986],"type":"Point"}
}