{
  "type": "Feature",
  "properties": {
    "addr:full":"PO Box 376 West Wyalong NSW 2671",
    "addr:postcode":"2671",
    "addr:street":"West",
    "iso:country":"AU",
    "sg:address":"PO Box 376",
    "sg:city":"West Wyalong",
    "sg:classifiers":[
        {
            "category":"Commercial Area",
            "type":"Public Place"
        }
    ],
    "sg:phone":"+61 427 722 556",
    "sg:postcode":"2671",
    "sg:province":"NSW",
    "sg:tags":[
        "heavy",
        "carrier"
    ],
    "wof:name":"Andersons G D & D R Transport",
    "wof:placetype":"venue"
},
  "geometry": {"coordinates":[147.201416016,-33.9222717285],"type":"Point"}
}