{
  "type": "Feature",
  "properties": {
    "addr:full":"Parabanks John St Salisbury SA 5108",
    "addr:postcode":"5108",
    "addr:street":"John St",
    "iso:country":"AU",
    "sg:address":"Parabanks John St",
    "sg:city":"Salisbury",
    "sg:classifiers":[
        {
            "category":"Food & Beverages",
            "subcategory":"Liquor & Beverages",
            "type":"Retail Goods"
        }
    ],
    "sg:phone":"+61 8 8258 6421",
    "sg:postcode":"5108",
    "sg:province":"SA",
    "sg:tags":[
        "store"
    ],
    "wof:name":"Woolworths Liquor",
    "wof:placetype":"venue"
},
  "geometry": {"coordinates":[138.644363403,-34.7626914978],"type":"Point"}
}