{
  "type": "Feature",
  "properties": {
    "addr:full":"80 Union Rd Kyabram VIC 3620",
    "addr:housenumber":"80",
    "addr:postcode":"3620",
    "addr:street":"Union Rd",
    "iso:country":"AU",
    "sg:address":"80 Union Rd",
    "sg:city":"Kyabram",
    "sg:classifiers":[
        {
            "category":"Health Services",
            "subcategory":"Dentist",
            "type":"Services"
        }
    ],
    "sg:phone":"+61 3 5852 1860",
    "sg:postcode":"3620",
    "sg:province":"VIC",
    "sg:tags":[
        "technician",
        "dental"
    ],
    "wof:name":"Denture Clinic",
    "wof:placetype":"venue"
},
  "geometry": {"coordinates":[145.04725647000001,-36.3114356995],"type":"Point"}
}