{
  "type": "Feature",
  "properties": {
    "iso:country":"AU",
    "sg:address":"5 Dunstans Crt",
    "sg:city":"Keon Park",
    "sg:classifiers":[
        {
            "category":"Manufacturing",
            "subcategory":"Paper Products",
            "type":"Manufacturing & Wholesale Goods"
        }
    ],
    "sg:phone":"+61 3 9469 8111",
    "sg:postcode":"3073",
    "sg:province":"VIC",
    "sg:tags":[
        "disposable"
    ],
    "wof:name":"Deeko",
    "wof:placetype":"venue"
},
  "geometry": {"coordinates":[145.02081298799999,-37.6949577332],"type":"Point"}
}