{
  "type": "Feature",
  "properties": {
    "addr:full":"47 McIntyre Rd Sunshine VIC 3020",
    "addr:housenumber":"47",
    "addr:postcode":"3020",
    "addr:street":"Mcintyre Rd",
    "iso:country":"AU",
    "sg:address":"47 McIntyre Rd",
    "sg:city":"Sunshine",
    "sg:classifiers":[
        {
            "category":"Travel",
            "subcategory":"Hotels & Motels",
            "type":"Entertainment"
        }
    ],
    "sg:phone":"+61 3 9364 9044",
    "sg:postcode":"3020",
    "sg:province":"VIC",
    "sg:tags":[
        "pub"
    ],
    "wof:name":"Westend Hotel",
    "wof:placetype":"venue"
},
  "geometry": {"coordinates":[144.829453,-37.772072],"type":"Point"}
}