{
  "type": "Feature",
  "properties": {
    "iso:country":"AU",
    "sg:address":"73 A O&#039; Sullivan&#039;s Beach Rd",
    "sg:city":"Lonsdale",
    "sg:classifiers":[
        {
            "category":"Coffee & Tea",
            "type":"Food & Drink"
        }
    ],
    "sg:phone":"+61 8 8384 6268",
    "sg:postcode":"5160",
    "sg:province":"SA",
    "sg:tags":[
        "kayak",
        "canoe"
    ],
    "sg:website":"http://www.extremeskiboats.com.au",
    "wof:name":"Extreme Ski Boats",
    "wof:placetype":"venue"
},
  "geometry": {"coordinates":[138.489578247,-35.1064910889],"type":"Point"}
}