{
  "type": "Feature",
  "properties": {
    "addr:full":"2 Sailors Gully Rd Eaglehawk VIC 3556",
    "addr:housenumber":"2",
    "addr:postcode":"3556",
    "addr:street":"Sailors Gully Rd",
    "iso:country":"AU",
    "sg:address":"2 Sailors Gully Rd",
    "sg:city":"Eaglehawk",
    "sg:classifiers":[
        {
            "category":"Home & Garden",
            "subcategory":"Carpets & Floor Coverings",
            "type":"Retail Goods"
        }
    ],
    "sg:phone":"+61 3 5446 8160",
    "sg:postcode":"3556",
    "sg:province":"VIC",
    "wof:name":"Rosiland Carpets Pty Ltd",
    "wof:placetype":"venue"
},
  "geometry": {"coordinates":[144.238967895,-36.7085647583],"type":"Point"}
}