{
  "type": "Feature",
  "properties": {
    "iso:country":"AU",
    "sg:address":"12 Carnea Pl",
    "sg:city":"Regents Park",
    "sg:classifiers":[
        {
            "category":"Utilities",
            "subcategory":"Electric",
            "type":"Services"
        }
    ],
    "sg:phone":"+61 7 3806 6433",
    "sg:postcode":"4118",
    "sg:province":"QLD",
    "sg:tags":[
        "electrical",
        "contractor"
    ],
    "wof:name":"Kerrwynn Electrical",
    "wof:placetype":"venue"
},
  "geometry": {"coordinates":[153.04148864699999,-27.6830596924],"type":"Point"}
}