{
  "type": "Feature",
  "properties": {
    "addr:full":"Pacific Hwy Ballina NSW 2478",
    "addr:postcode":"2478",
    "addr:street":"Pacific Hwy",
    "iso:country":"AU",
    "sg:address":"Pacific Hwy",
    "sg:city":"Ballina",
    "sg:classifiers":[
        {
            "category":"Autos & Motor Vehicles",
            "subcategory":"Automobile Sales",
            "type":"Retail Goods"
        }
    ],
    "sg:phone":"+61 2 6686 2399",
    "sg:postcode":"2478",
    "sg:province":"NSW",
    "sg:tags":[
        "car",
        "new"
    ],
    "wof:name":"Nissan",
    "wof:placetype":"venue"
},
  "geometry": {"coordinates":[153.554962158,-28.8678760529],"type":"Point"}
}