{
  "type": "Feature",
  "properties": {
    "addr:full":"24 Sonia St Ringwood VIC 3134",
    "addr:housenumber":"24",
    "addr:postcode":"3134",
    "addr:street":"Sonia St",
    "iso:country":"AU",
    "sg:address":"24 Sonia St",
    "sg:city":"Ringwood",
    "sg:classifiers":[
        {
            "category":"Professional",
            "subcategory":"Engineering",
            "type":"Services"
        }
    ],
    "sg:phone":"+61 3 9870 7145",
    "sg:postcode":"3134",
    "sg:province":"VIC",
    "sg:tags":[
        "electronic",
        "engineer"
    ],
    "wof:name":"Diverse Electronic Solutions Pty Ltd",
    "wof:placetype":"venue"
},
  "geometry": {"coordinates":[145.24316406200001,-37.8020439148],"type":"Point"}
}