{
  "type": "Feature",
  "properties": {
    "iso:country":"AU",
    "sg:address":"47-53 Hallam Valley Rd",
    "sg:city":"Dandenong South",
    "sg:classifiers":[
        {
            "category":"Communications",
            "subcategory":"Film & Video Production",
            "type":"Services"
        }
    ],
    "sg:phone":"+61 3 9793 8111",
    "sg:postcode":"3175",
    "sg:province":"VIC",
    "sg:tags":[
        "consultant",
        "material",
        "handling"
    ],
    "wof:name":"Warehousing Fulfilment Distribution Solutions Pty Ltd",
    "wof:placetype":"venue"
},
  "geometry": {"coordinates":[145.23274230999999,-38.0128097534],"type":"Point"}
}