{
  "type": "Feature",
  "properties": {
    "addr:full":"200 Edgeware Rd Newtown NSW 2042",
    "addr:housenumber":"200",
    "addr:postcode":"2042",
    "addr:street":"Edgeware Rd",
    "iso:country":"AU",
    "sg:address":"200 Edgeware Rd",
    "sg:city":"Newtown",
    "sg:classifiers":[
        {
            "category":"Utilities",
            "subcategory":"Natural Gas",
            "type":"Services"
        }
    ],
    "sg:phone":"+61 2 9516 3553",
    "sg:postcode":"2042",
    "sg:province":"NSW",
    "sg:tags":[
        "consultant",
        "resource"
    ],
    "wof:name":"Ian Perkins Consultancy Services",
    "wof:placetype":"venue"
},
  "geometry": {"coordinates":[151.17332500000001,-33.904606],"type":"Point"}
}