{
  "type": "Feature",
  "properties": {
    "iso:country":"AU",
    "sg:address":"35 Lindsay Noonan Drv",
    "sg:city":"South West Rocks",
    "sg:classifiers":[
        {
            "category":"Building & Trades",
            "subcategory":"Landscaping Services",
            "type":"Services"
        }
    ],
    "sg:phone":"+61 2 6566 6005",
    "sg:postcode":"2431",
    "sg:province":"NSW",
    "sg:tags":[
        "firebreak",
        "clearing",
        "land",
        "contractor"
    ],
    "wof:name":"South West Rocks Earthmoving",
    "wof:placetype":"venue"
},
  "geometry": {"coordinates":[153.039307,-30.909016],"type":"Point"}
}