{
  "type": "Feature",
  "properties": {
    "iso:country":"AU",
    "sg:address":"250- 254 Princes Hwy",
    "sg:city":"Albion Park Rail",
    "sg:classifiers":[
        {
            "category":"Shopping",
            "subcategory":"Mobile Phones",
            "type":"Retail Goods"
        }
    ],
    "sg:phone":"+61 13 17 60",
    "sg:postcode":"2527",
    "sg:province":"NSW",
    "sg:tags":[
        "telephone",
        "accessory"
    ],
    "wof:name":"Battery World",
    "wof:placetype":"venue"
},
  "geometry": {"coordinates":[150.80311584500001,-34.5680503845],"type":"Point"}
}