{
  "type": "Feature",
  "properties": {
    "addr:full":"Unit 4 17 Maroochy Waters Drv Maroochydore QLD 4558",
    "addr:housenumber":"17",
    "addr:postcode":"4558",
    "addr:street":"Maroochy Waters Drv",
    "iso:country":"AU",
    "sg:address":"Unit 4 17 Maroochy Waters Drv",
    "sg:city":"Maroochydore",
    "sg:classifiers":[
        {
            "category":"Real Estate",
            "subcategory":"Architect",
            "type":"Services"
        }
    ],
    "sg:phone":"+61 414 567 848",
    "sg:postcode":"4558",
    "sg:province":"QLD",
    "sg:tags":[
        "building",
        "designer"
    ],
    "wof:name":"Future World Design Pty Ltd",
    "wof:placetype":"venue"
},
  "geometry": {"coordinates":[153.06915283199999,-26.6447887421],"type":"Point"}
}