{
  "type": "Feature",
  "properties": {
    "iso:country":"AU",
    "sg:address":"135 Barrack St",
    "sg:city":"Perth",
    "sg:classifiers":[
        {
            "category":"Travel",
            "subcategory":"Travel Agent",
            "type":"Entertainment"
        }
    ],
    "sg:phone":"+61 8 6267 0700",
    "sg:postcode":"6000",
    "sg:province":"WA",
    "sg:tags":[
        "consultant"
    ],
    "wof:name":"Travel Forever",
    "wof:placetype":"venue"
},
  "geometry": {"coordinates":[115.861053467,-31.9526042938],"type":"Point"}
}