{
  "type": "Feature",
  "properties": {
    "addr:full":"49 Downs St North Ipswich QLD 4305",
    "addr:housenumber":"49",
    "addr:postcode":"4305",
    "addr:street":"Downs St",
    "iso:country":"AU",
    "sg:address":"49 Downs St",
    "sg:city":"North Ipswich",
    "sg:classifiers":[
        {
            "category":"Shopping",
            "subcategory":"Baby Store",
            "type":"Retail Goods"
        }
    ],
    "sg:phone":"+61 7 3812 1197",
    "sg:postcode":"4305",
    "sg:province":"QLD",
    "sg:tags":[
        "children's",
        "wear"
    ],
    "wof:name":"Our Golden Hands",
    "wof:placetype":"venue"
},
  "geometry": {"coordinates":[152.761627197,-27.603723526],"type":"Point"}
}