{
  "type": "Feature",
  "properties": {
    "addr:full":"21 Havannah St Bathurst NSW 2795",
    "addr:housenumber":"21",
    "addr:postcode":"2795",
    "addr:street":"Havannah St",
    "iso:country":"AU",
    "sg:address":"21 Havannah St",
    "sg:city":"Bathurst",
    "sg:classifiers":[
        {
            "category":"Wholesale",
            "subcategory":"Scrap",
            "type":"Manufacturing & Wholesale Goods"
        }
    ],
    "sg:phone":"+61 2 6332 2525",
    "sg:postcode":"2795",
    "sg:province":"NSW",
    "sg:tags":[
        "merchant",
        "metal"
    ],
    "wof:name":"Chifley Recyclers",
    "wof:placetype":"venue"
},
  "geometry": {"coordinates":[149.563995361,-33.4378700256],"type":"Point"}
}