{
  "type": "Feature",
  "properties": {
    "iso:country":"AU",
    "sg:address":"113 Winona Rd",
    "sg:city":"Mt Eliza",
    "sg:classifiers":[
        {
            "category":"Professional",
            "subcategory":"Employment Agencies",
            "type":"Services"
        }
    ],
    "sg:phone":"+61 3 9787 0366",
    "sg:postcode":"3930",
    "sg:province":"VIC",
    "wof:name":"Specialised Personnel",
    "wof:placetype":"venue"
},
  "geometry": {"coordinates":[145.12002563499999,-38.1955299377],"type":"Point"}
}