{
  "type": "Feature",
  "properties": {
    "addr:full":"895 Forest Rd Lugarno NSW 2210",
    "addr:housenumber":"895",
    "addr:postcode":"2210",
    "addr:street":"Forest Rd",
    "iso:country":"AU",
    "sg:address":"895 Forest Rd",
    "sg:city":"Lugarno",
    "sg:classifiers":[
        {
            "category":"Government",
            "subcategory":"Court House",
            "type":"Public Place"
        }
    ],
    "sg:phone":"+61 400 190 465",
    "sg:postcode":"2210",
    "sg:province":"NSW",
    "sg:tags":[
        "personal",
        "marriage",
        "family",
        "counselling"
    ],
    "wof:name":"Bengston Brooke",
    "wof:placetype":"venue"
},
  "geometry": {"coordinates":[151.04823300000001,-33.975193],"type":"Point"}
}