{
  "type": "Feature",
  "properties": {
    "addr:full":"M S 1448 Chinchilla QLD 4413",
    "addr:housenumber":"1448",
    "addr:postcode":"4413",
    "addr:street":"Chinchilla",
    "iso:country":"AU",
    "sg:address":"M S 1448",
    "sg:city":"Chinchilla",
    "sg:classifiers":[
        {
            "category":"Building & Trades",
            "subcategory":"Construction",
            "type":"Services"
        }
    ],
    "sg:phone":"+61 7 4665 5155",
    "sg:postcode":"4413",
    "sg:province":"QLD",
    "sg:tags":[
        "contractor"
    ],
    "wof:name":"A.D. McIntyre",
    "wof:placetype":"venue"
},
  "geometry": {"coordinates":[150.63063049300001,-26.7399196625],"type":"Point"}
}