{
  "type": "Feature",
  "properties": {
    "iso:country":"AU",
    "sg:address":"Unit 5/ 8 Commodore Drv",
    "sg:city":"Rockingham",
    "sg:classifiers":[
        {
            "category":"Shopping",
            "subcategory":"Pawn Shop",
            "type":"Retail Goods"
        }
    ],
    "sg:phone":"+61 8 9529 3949",
    "sg:postcode":"6168",
    "sg:province":"WA",
    "sg:tags":[
        "pawnbroker"
    ],
    "wof:name":"Cash City Rockingham",
    "wof:placetype":"venue"
},
  "geometry": {"coordinates":[115.736526,-32.27853],"type":"Point"}
}