{
  "type": "Feature",
  "properties": {
    "addr:full":"9 King Edward St South Perth WA 6151",
    "addr:housenumber":"9",
    "addr:postcode":"6151",
    "addr:street":"King Edward St South",
    "iso:country":"AU",
    "sg:address":"9 King Edward St",
    "sg:city":"South Perth",
    "sg:classifiers":[
        {
            "category":"Professional",
            "subcategory":"Engineering",
            "type":"Services"
        }
    ],
    "sg:phone":"+61 8 9368 0649",
    "sg:postcode":"6151",
    "sg:province":"WA",
    "sg:tags":[
        "consulting",
        "engineer"
    ],
    "wof:name":"Process Systems Intelligence Pty Ltd",
    "wof:placetype":"venue"
},
  "geometry": {"coordinates":[115.858261,-31.977478],"type":"Point"}
}