{
  "type": "Feature",
  "properties": {
    "addr:full":"Shop 15 Castle Hill Shppng Crt, Cnr Ogg & Dohles R Murrumba Downs QLD 4503",
    "addr:housenumber":"shop 15",
    "addr:postcode":"4503",
    "addr:street":"Shppng Crt Cnr Ogg &;R",
    "iso:country":"AU",
    "sg:address":"Shop 15 Castle Hill Shppng Crt, Cnr Ogg & Dohles R",
    "sg:city":"Murrumba Downs",
    "sg:classifiers":[
        {
            "category":"Personal",
            "subcategory":"Beauty Salon",
            "type":"Services"
        }
    ],
    "sg:phone":"+61 7 3491 6555",
    "sg:postcode":"4503",
    "sg:province":"QLD",
    "sg:tags":[
        "hairdresser"
    ],
    "wof:name":"Dextress Hair",
    "wof:placetype":"venue"
},
  "geometry": {"coordinates":[153.00868225100001,-27.2627944946],"type":"Point"}
}