{
  "type": "Feature",
  "properties": {
    "addr:full":"63 Main Rd Nairne SA 5252",
    "addr:housenumber":"63",
    "addr:postcode":"5252",
    "addr:street":"Main Rd",
    "iso:country":"AU",
    "sg:address":"63 Main Rd",
    "sg:city":"Nairne",
    "sg:classifiers":[
        {
            "category":"Retail",
            "subcategory":"Auto Repair",
            "type":"Services"
        }
    ],
    "sg:phone":"+61 8 8388 0444",
    "sg:postcode":"5252",
    "sg:province":"SA",
    "sg:tags":[
        "repairer",
        "motor",
        "engineer"
    ],
    "wof:name":"Nairne Complete Auto Care",
    "wof:placetype":"venue"
},
  "geometry": {"coordinates":[138.91070556599999,-35.0348052979],"type":"Point"}
}