{
  "type": "Feature",
  "properties": {
    "iso:country":"AU",
    "sg:address":"18 Bundaroo St",
    "sg:city":"Bowral",
    "sg:classifiers":[
        {
            "category":"Real Estate",
            "subcategory":"Real Estate Agent",
            "type":"Services"
        }
    ],
    "sg:phone":"+61 2 4862 1198",
    "sg:postcode":"2576",
    "sg:province":"NSW",
    "sg:tags":[
        "consultant",
        "heritage"
    ],
    "wof:name":"Donald Johnston",
    "wof:placetype":"venue"
},
  "geometry": {"coordinates":[150.420043945,-34.4766998291],"type":"Point"}
}