{
  "type": "Feature",
  "properties": {
    "iso:country":"AU",
    "sg:address":"38 Hopetoun Rd",
    "sg:city":"Werribee",
    "sg:classifiers":[
        {
            "category":"Manufacturing",
            "subcategory":"Retail Goods",
            "type":"Manufacturing & Wholesale Goods"
        }
    ],
    "sg:phone":"+61 3 9742 2988",
    "sg:postcode":"3030",
    "sg:province":"VIC",
    "sg:tags":[
        "merchant",
        "pump",
        "mfrs"
    ],
    "wof:name":"Flo-Well Pumps",
    "wof:placetype":"venue"
},
  "geometry": {"coordinates":[144.63230899999999,-37.914845],"type":"Point"}
}