{
  "type": "Feature",
  "properties": {
    "addr:full":"Lvl 1, 30 Alfred St Milsons Point NSW 2061",
    "addr:housenumber":"30",
    "addr:postcode":"2061",
    "addr:street":"Alfred St",
    "iso:country":"AU",
    "sg:address":"Lvl 1, 30 Alfred St",
    "sg:city":"Milsons Point",
    "sg:classifiers":[
        {
            "category":"Wholesale",
            "subcategory":"Non-durable Goods",
            "type":"Manufacturing & Wholesale Goods"
        }
    ],
    "sg:phone":"+61 2 9409 7700",
    "sg:postcode":"2061",
    "sg:province":"NSW",
    "sg:tags":[
        "wholesaler",
        "mfrs",
        "cosmetic"
    ],
    "wof:name":"Elizabeth Arden (Australia) Pty Ltd",
    "wof:placetype":"venue"
},
  "geometry": {"coordinates":[151.21136474599999,-33.8470535278],"type":"Point"}
}