{
  "type": "Feature",
  "properties": {
    "addr:full":"259 Bunya Rd Arana Hills QLD 4054",
    "addr:housenumber":"259",
    "addr:postcode":"4054",
    "addr:street":"Bunya Rd",
    "iso:country":"AU",
    "sg:address":"259 Bunya Rd",
    "sg:city":"Arana Hills",
    "sg:classifiers":[
        {
            "category":"Professional",
            "subcategory":"Employment Agencies",
            "type":"Services"
        }
    ],
    "sg:phone":"+61 419 670 545",
    "sg:postcode":"4054",
    "sg:province":"QLD",
    "sg:tags":[
        "entertainer",
        "agent"
    ],
    "wof:name":"Opening Night Promotions & Entertainment Pty Ltd",
    "wof:placetype":"venue"
},
  "geometry": {"coordinates":[152.96182250999999,-27.3878116608],"type":"Point"}
}