{
  "type": "Feature",
  "properties": {
    "iso:country":"AU",
    "sg:address":"77 New Illawarra Rd",
    "sg:city":"Bexley North",
    "sg:classifiers":[
        {
            "category":"Health Services",
            "subcategory":"Health Practitioner",
            "type":"Services"
        }
    ],
    "sg:phone":"+61 2 9150 8227",
    "sg:postcode":"2207",
    "sg:province":"NSW",
    "sg:tags":[
        "physiotherapist"
    ],
    "wof:name":"Leung J",
    "wof:placetype":"venue"
},
  "geometry": {"coordinates":[151.114227,-33.940044],"type":"Point"}
}