{
  "type": "Feature",
  "properties": {
    "addr:full":"33 Whitehill Rd Ipswich QLD 4305",
    "addr:housenumber":"33",
    "addr:postcode":"4305",
    "addr:street":"Whitehill Rd",
    "iso:country":"AU",
    "sg:address":"33 Whitehill Rd",
    "sg:city":"Ipswich",
    "sg:classifiers":[
        {
            "category":"Autos & Motor Vehicles",
            "subcategory":"Auto Supplies",
            "type":"Retail Goods"
        }
    ],
    "sg:phone":"+61 7 3281 2643",
    "sg:postcode":"4305",
    "sg:province":"QLD",
    "sg:tags":[
        "battery",
        "automotive"
    ],
    "wof:name":"Progress Batteries",
    "wof:placetype":"venue"
},
  "geometry": {"coordinates":[152.772674561,-27.6191253662],"type":"Point"}
}