{
  "type": "Feature",
  "properties": {
    "iso:country":"AU",
    "sg:address":"13 Campbell St",
    "sg:city":"Balmain",
    "sg:classifiers":[
        {
            "category":"Building & Trades",
            "subcategory":"Landscaping Services",
            "type":"Services"
        }
    ],
    "sg:phone":"+61 2 9810 5531",
    "sg:postcode":"2041",
    "sg:province":"NSW",
    "sg:tags":[
        "designer",
        "landscape",
        "contractor"
    ],
    "wof:name":"Margaret A.R. Cory",
    "wof:placetype":"venue"
},
  "geometry": {"coordinates":[151.18521100000001,-33.856823],"type":"Point"}
}