{
  "type": "Feature",
  "properties": {
    "iso:country":"AU",
    "sg:address":"O'Loan St",
    "sg:city":"Petrie",
    "sg:classifiers":[
        {
            "category":"Organizations",
            "subcategory":"Non-profit Organization",
            "type":"Services"
        }
    ],
    "sg:phone":"+61 7 3285 6695",
    "sg:postcode":"4502",
    "sg:province":"QLD",
    "sg:tags":[
        "support",
        "disability",
        "organisation"
    ],
    "wof:name":"Backstop Respite Care For Disabled People Inc.",
    "wof:placetype":"venue"
},
  "geometry": {"coordinates":[152.978317261,-27.2708721161],"type":"Point"}
}