{
  "type": "Feature",
  "properties": {
    "iso:country":"AU",
    "sg:address":"Cnr Minchinton St & Omrah Ave",
    "sg:city":"Caloundra",
    "sg:classifiers":[
        {
            "category":"Health Services",
            "subcategory":"Dentist",
            "type":"Services"
        }
    ],
    "sg:phone":"+61 7 5491 2727",
    "sg:postcode":"4551",
    "sg:province":"QLD",
    "wof:name":"Blowers Jenny",
    "wof:placetype":"venue"
},
  "geometry": {"coordinates":[153.13189697300001,-26.8035411835],"type":"Point"}
}