{
  "type": "Feature",
  "properties": {
    "addr:full":"5/ 206 Mary St Mandurah WA 6210",
    "addr:housenumber":"/ 206",
    "addr:postcode":"6210",
    "addr:street":"Mary St",
    "iso:country":"AU",
    "sg:address":"5/ 206 Mary St",
    "sg:city":"Mandurah",
    "sg:classifiers":[
        {
            "category":"Banks & Credit Unions",
            "subcategory":"Financial Services",
            "type":"Services"
        }
    ],
    "sg:phone":"+61 1300 884 825",
    "sg:postcode":"6210",
    "sg:province":"WA",
    "sg:tags":[
        "planning"
    ],
    "wof:name":"Natural Progression Wealth Management",
    "wof:placetype":"venue"
},
  "geometry": {"coordinates":[115.7127,-32.535889],"type":"Point"}
}