{
  "type": "Feature",
  "properties": {
    "addr:full":"35 Arthur St Somerset TAS 7322",
    "addr:housenumber":"35",
    "addr:postcode":"7322",
    "addr:street":"Arthur St",
    "iso:country":"AU",
    "sg:address":"35 Arthur St",
    "sg:city":"Somerset",
    "sg:classifiers":[
        {
            "category":"Wholesale",
            "subcategory":"Machinery & Supplies",
            "type":"Manufacturing & Wholesale Goods"
        }
    ],
    "sg:phone":"+61 419 979 269",
    "sg:postcode":"7322",
    "sg:province":"TAS",
    "sg:tags":[
        "equipment",
        "hydraulic"
    ],
    "wof:name":"Coast 2 Coast Hydraulics",
    "wof:placetype":"venue"
},
  "geometry": {"coordinates":[145.826187,-41.040932],"type":"Point"}
}