{
  "type": "Feature",
  "properties": {
    "iso:country":"AU",
    "sg:address":"54 Commercial St East",
    "sg:city":"Mt Gambier",
    "sg:classifiers":[
        {
            "category":"Shopping",
            "subcategory":"Clothing, Apparel, & Fashions",
            "type":"Retail Goods"
        }
    ],
    "sg:phone":"+61 8 8723 6677",
    "sg:postcode":"5290",
    "sg:province":"SA",
    "sg:tags":[
        "maternity",
        "wear"
    ],
    "wof:name":"Style Fashion On Main",
    "wof:placetype":"venue"
},
  "geometry": {"coordinates":[140.782516,-37.829128],"type":"Point"}
}