{
  "type": "Feature",
  "properties": {
    "addr:full":"54 Commercial St East Mt Gambier SA 5290",
    "addr:housenumber":"54",
    "addr:postcode":"5290",
    "addr:street":"Commercial St East Mt",
    "iso:country":"AU",
    "sg:address":"54 Commercial St East",
    "sg:city":"Mt Gambier",
    "sg:classifiers":[
        {
            "category":"Shopping",
            "subcategory":"Clothing, Apparel, & Fashions",
            "type":"Retail Goods"
        }
    ],
    "sg:phone":"+61 8 8723 6677",
    "sg:postcode":"5290",
    "sg:province":"SA",
    "sg:tags":[
        "maternity",
        "wear"
    ],
    "wof:name":"Style Fashion On Main",
    "wof:placetype":"venue"
},
  "geometry": {"coordinates":[140.78251599999999,-37.829128],"type":"Point"}
}