{
  "type": "Feature",
  "properties": {
    "iso:country":"AU",
    "sg:address":"U14/ 2 Station Rd",
    "sg:city":"Burpengary",
    "sg:classifiers":[
        {
            "category":"Home & Garden",
            "subcategory":"Carpets & Floor Coverings",
            "type":"Retail Goods"
        }
    ],
    "sg:phone":"+61 401 042 033",
    "sg:postcode":"4505",
    "sg:province":"QLD",
    "sg:tags":[
        "tile",
        "wall"
    ],
    "wof:name":"Allcoast Vision Tiles",
    "wof:placetype":"venue"
},
  "geometry": {"coordinates":[152.972900391,-27.1544952393],"type":"Point"}
}