{
  "type": "Feature",
  "properties": {
    "addr:full":"Cnr Hume & Cabramatta Rds Lansvale NSW 2166",
    "addr:postcode":"2166",
    "addr:street":"Cnr",
    "iso:country":"AU",
    "sg:address":"Cnr Hume & Cabramatta Rds",
    "sg:city":"Lansvale",
    "sg:classifiers":[
        {
            "category":"Home & Garden",
            "subcategory":"Carpets & Floor Coverings",
            "type":"Retail Goods"
        }
    ],
    "sg:phone":"+61 2 9724 0141",
    "sg:postcode":"2166",
    "sg:province":"NSW",
    "sg:tags":[
        "tile",
        "wall"
    ],
    "wof:name":"C T M",
    "wof:placetype":"venue"
},
  "geometry": {"coordinates":[150.94920349099999,-33.8985290527],"type":"Point"}
}