{
  "type": "Feature",
  "properties": {
    "addr:full":"Shp 5/ Market Pl Muswellbrook NSW 2333",
    "addr:housenumber":"/",
    "addr:postcode":"2333",
    "addr:street":"Market Pl",
    "iso:country":"AU",
    "sg:address":"Shp 5/ Market Pl",
    "sg:city":"Muswellbrook",
    "sg:classifiers":[
        {
            "category":"Shopping",
            "subcategory":"Clothing, Apparel, & Fashions",
            "type":"Retail Goods"
        }
    ],
    "sg:phone":"+61 2 6541 2204",
    "sg:postcode":"2333",
    "sg:province":"NSW",
    "sg:tags":[
        "lady",
        "wear"
    ],
    "wof:name":"Seven Sins",
    "wof:placetype":"venue"
},
  "geometry": {"coordinates":[150.88832092300001,-32.2649879456],"type":"Point"}
}