{
  "type": "Feature",
  "properties": {
    "addr:full":"17 Stawell Rd Lower Plenty VIC 3093",
    "addr:housenumber":"17",
    "addr:postcode":"3093",
    "addr:street":"Stawell Rd",
    "iso:country":"AU",
    "sg:address":"17 Stawell Rd",
    "sg:city":"Lower Plenty",
    "sg:classifiers":[
        {
            "category":"Building & Trades",
            "subcategory":"Construction",
            "type":"Services"
        }
    ],
    "sg:phone":"+61 3 9439 3557",
    "sg:postcode":"3093",
    "sg:province":"VIC",
    "sg:tags":[
        "scaffolding"
    ],
    "wof:name":"Australian Scaffolding",
    "wof:placetype":"venue"
},
  "geometry": {"coordinates":[145.10870361299999,-37.7430343628],"type":"Point"}
}