{
  "type": "Feature",
  "properties": {
    "iso:country":"AU",
    "sg:address":"22 Ponting St",
    "sg:city":"Tatura",
    "sg:classifiers":[
        {
            "category":"Building & Trades",
            "subcategory":"Construction",
            "type":"Services"
        }
    ],
    "sg:phone":"+61 419 566 508",
    "sg:postcode":"3616",
    "sg:province":"VIC",
    "sg:tags":[
        "contractor"
    ],
    "wof:name":"Peter J Baird",
    "wof:placetype":"venue"
},
  "geometry": {"coordinates":[145.23948669399999,-36.4360847473],"type":"Point"}
}