{
  "type": "Feature",
  "properties": {
    "addr:full":"11 Bennett La Kurrajong NSW 2758",
    "addr:housenumber":"11",
    "addr:postcode":"2758",
    "addr:street":"Bennett La",
    "iso:country":"AU",
    "sg:address":"11 Bennett La",
    "sg:city":"Kurrajong",
    "sg:classifiers":[
        {
            "category":"Health Services",
            "subcategory":"Health Practitioner",
            "type":"Services"
        }
    ],
    "sg:phone":"+61 2 4567 7192",
    "sg:postcode":"2758",
    "sg:province":"NSW",
    "sg:tags":[
        "alternative"
    ],
    "wof:name":"Life Force Natural Therapies",
    "wof:placetype":"venue"
},
  "geometry": {"coordinates":[150.62901306099999,-33.529296875],"type":"Point"}
}