{
  "type": "Feature",
  "properties": {
    "addr:full":"9 Maxim Pl St Marys NSW 2760",
    "addr:housenumber":"9",
    "addr:postcode":"2760",
    "addr:street":"Maxim Pl",
    "iso:country":"AU",
    "sg:address":"9 Maxim Pl St",
    "sg:city":"Marys",
    "sg:classifiers":[
        {
            "category":"Manufacturing",
            "subcategory":"Retail Goods",
            "type":"Manufacturing & Wholesale Goods"
        }
    ],
    "sg:phone":"+61 2 9623 3900",
    "sg:postcode":"2760",
    "sg:province":"NSW",
    "sg:tags":[
        "merchant",
        "pump",
        "mfrs"
    ],
    "wof:name":"Thompsons Kelly & Lewis",
    "wof:placetype":"venue"
},
  "geometry": {"coordinates":[150.772705078,-33.7528572083],"type":"Point"}
}