{
  "type": "Feature",
  "properties": {
    "addr:full":"119- 121 Ryrie St Geelong VIC 3220",
    "addr:housenumber":"121",
    "addr:postcode":"3220",
    "addr:street":"Ryrie St",
    "iso:country":"AU",
    "sg:address":"119- 121 Ryrie St",
    "sg:city":"Geelong",
    "sg:classifiers":[
        {
            "category":"Health Services",
            "subcategory":"Optometrist",
            "type":"Services"
        }
    ],
    "sg:phone":"+61 3 5229 5437",
    "sg:postcode":"3220",
    "sg:province":"VIC",
    "wof:name":"ProVision Optometrists",
    "wof:placetype":"venue"
},
  "geometry": {"coordinates":[144.358994,-38.148884],"type":"Point"}
}