{
  "type": "Feature",
  "properties": {
    "addr:full":"Neil St Harden NSW 2587",
    "addr:postcode":"2587",
    "addr:street":"Neil St",
    "iso:country":"AU",
    "sg:address":"Neil St",
    "sg:city":"Harden",
    "sg:classifiers":[
        {
            "category":"Travel",
            "subcategory":"Hotels & Motels",
            "type":"Entertainment"
        }
    ],
    "sg:phone":"+61 2 6386 2206",
    "sg:postcode":"2587",
    "sg:province":"NSW",
    "sg:tags":[
        "accommodation"
    ],
    "wof:name":"Carrington Hotel",
    "wof:placetype":"venue"
},
  "geometry": {"coordinates":[148.36445617699999,-34.5521392822],"type":"Point"}
}