{
  "type": "Feature",
  "properties": {
    "iso:country":"AU",
    "sg:address":"28 Davlyn Drv",
    "sg:city":"Andergrove",
    "sg:classifiers":[
        {
            "category":"Building & Trades",
            "subcategory":"Construction",
            "type":"Services"
        }
    ],
    "sg:phone":"+61 7 4955 4366",
    "sg:postcode":"4740",
    "sg:province":"QLD",
    "sg:tags":[
        "contractor"
    ],
    "wof:name":"Phillip Bonaventura Builders",
    "wof:placetype":"venue"
},
  "geometry": {"coordinates":[149.18615700000001,-21.091667],"type":"Point"}
}