{
  "type": "Feature",
  "properties": {
    "iso:country":"AU",
    "sg:address":"7 Groom Mews",
    "sg:city":"Wellard",
    "sg:classifiers":[
        {
            "category":"Building & Trades",
            "subcategory":"Plumbing",
            "type":"Services"
        }
    ],
    "sg:phone":"+61 412 190 916",
    "sg:postcode":"6170",
    "sg:province":"WA",
    "sg:tags":[
        "plumber",
        "gasfitters"
    ],
    "wof:name":"P.K. Plumbing & Gas",
    "wof:placetype":"venue"
},
  "geometry": {"coordinates":[115.830559,-32.264908],"type":"Point"}
}