{
  "type": "Feature",
  "properties": {
    "addr:full":"4 Canthium Way Casuarina NSW 2487",
    "addr:housenumber":"4",
    "addr:postcode":"2487",
    "addr:street":"Canthium Way",
    "iso:country":"AU",
    "sg:address":"4 Canthium Way",
    "sg:city":"Casuarina",
    "sg:classifiers":[
        {
            "category":"Structure",
            "subcategory":"Building",
            "type":"Public Place"
        }
    ],
    "sg:phone":"+61 2 6674 4466",
    "sg:postcode":"2487",
    "sg:province":"NSW",
    "sg:tags":[
        "sail",
        "shade"
    ],
    "sg:website":"http://www.fabricstructures.com.au",
    "wof:name":"Universal Fabric Structures",
    "wof:placetype":"venue"
},
  "geometry": {"coordinates":[153.57324218799999,-28.2917861938],"type":"Point"}
}