{
  "type": "Feature",
  "properties": {
    "iso:country":"AU",
    "sg:address":"21/20 Wellington St",
    "sg:city":"Narrabeen",
    "sg:classifiers":[
        {
            "category":"Health Services",
            "subcategory":"Doctor",
            "type":"Services"
        }
    ],
    "sg:phone":"+61 2 9913 7900",
    "sg:postcode":"2101",
    "sg:province":"NSW",
    "sg:tags":[
        "podiatrist"
    ],
    "wof:name":"Ferguson David",
    "wof:placetype":"venue"
},
  "geometry": {"coordinates":[151.298798,-33.711987],"type":"Point"}
}