{
  "type": "Feature",
  "properties": {
    "iso:country":"AU",
    "sg:address":"192- 196 Centre Rd",
    "sg:city":"Narre Warren",
    "sg:classifiers":[
        {
            "category":"Organizations",
            "subcategory":"Community Association",
            "type":"Services"
        }
    ],
    "sg:phone":"+61 3 9704 0015",
    "sg:postcode":"3805",
    "sg:province":"VIC",
    "sg:tags":[
        "club",
        "senior",
        "citizen"
    ],
    "wof:name":"Narre Warren Senior Citizens Centre Inc",
    "wof:placetype":"venue"
},
  "geometry": {"coordinates":[145.300705,-38.028778],"type":"Point"}
}