{
  "type": "Feature",
  "properties": {
    "addr:full":"84B Queen St Busselton WA 6280",
    "addr:housenumber":"84b",
    "addr:postcode":"6280",
    "addr:street":"Queen St",
    "iso:country":"AU",
    "sg:address":"84B Queen St",
    "sg:city":"Busselton",
    "sg:classifiers":[
        {
            "category":"Real Estate",
            "subcategory":"Real Estate Agent",
            "type":"Services"
        }
    ],
    "sg:phone":"+61 8 9752 3588",
    "sg:postcode":"6280",
    "sg:province":"WA",
    "wof:name":"Professionals Real Estate Group The",
    "wof:placetype":"venue"
},
  "geometry": {"coordinates":[115.34475707999999,-33.651222229],"type":"Point"}
}