{
  "type": "Feature",
  "properties": {
    "addr:full":"1 Railway Pde Hurstville NSW 2220",
    "addr:housenumber":"1",
    "addr:postcode":"2220",
    "addr:street":"Railway Pde",
    "iso:country":"AU",
    "sg:address":"1 Railway Pde",
    "sg:city":"Hurstville",
    "sg:classifiers":[
        {
            "category":"Autos & Motor Vehicles",
            "subcategory":"Fuel & Gas Station",
            "type":"Retail Goods"
        }
    ],
    "sg:phone":"+61 2 9579 1006",
    "sg:postcode":"2220",
    "sg:province":"NSW",
    "wof:name":"Hurstville Petrol Stop",
    "wof:placetype":"venue"
},
  "geometry": {"coordinates":[151.103027344,-33.9686851501],"type":"Point"}
}