{
  "type": "Feature",
  "properties": {
    "addr:full":"38 Brown St West Wallsend NSW 2286",
    "addr:housenumber":"38",
    "addr:postcode":"2286",
    "addr:street":"Brown St",
    "iso:country":"AU",
    "sg:address":"38 Brown St",
    "sg:city":"West Wallsend",
    "sg:classifiers":[
        {
            "category":"Building & Trades",
            "subcategory":"Construction",
            "type":"Services"
        }
    ],
    "sg:phone":"+61 412 081 948",
    "sg:postcode":"2286",
    "sg:province":"NSW",
    "sg:tags":[
        "welding"
    ],
    "wof:name":"B & M Mobile Maintenance Pty Ltd",
    "wof:placetype":"venue"
},
  "geometry": {"coordinates":[151.58384704599999,-32.9034843445],"type":"Point"}
}