{
  "type": "Feature",
  "properties": {
    "addr:full":"67 Cascade St Ipswich QLD 4305",
    "addr:housenumber":"67",
    "addr:postcode":"4305",
    "addr:street":"Cascade St",
    "iso:country":"AU",
    "sg:address":"67 Cascade St",
    "sg:city":"Ipswich",
    "sg:classifiers":[
        {
            "category":"Building & Trades",
            "subcategory":"Construction",
            "type":"Services"
        }
    ],
    "sg:phone":"+61 7 3812 2608",
    "sg:postcode":"4305",
    "sg:province":"QLD",
    "sg:tags":[
        "contractor"
    ],
    "wof:name":"Sherwood Constructions & Engineering Pty Ltd",
    "wof:placetype":"venue"
},
  "geometry": {"coordinates":[152.769729614,-27.6374282837],"type":"Point"}
}