{
  "type": "Feature",
  "properties": {
    "addr:full":"Moorleigh Community Centre 92 Bignell Rd Bentleigh East VIC 3165",
    "addr:housenumber":"92",
    "addr:postcode":"3165",
    "addr:street":"Bignell Rd",
    "iso:country":"AU",
    "sg:address":"Moorleigh Community Centre 92 Bignell Rd",
    "sg:city":"Bentleigh East",
    "sg:classifiers":[
        {
            "category":"Education",
            "subcategory":"University",
            "type":"Public Place"
        }
    ],
    "sg:phone":"+61 3 9570 3929",
    "sg:postcode":"3165",
    "sg:province":"VIC",
    "sg:tags":[
        "educational",
        "organisation",
        "cultural"
    ],
    "wof:name":"Universities Of The Third Age (U3A) - Victorian Network",
    "wof:placetype":"venue"
},
  "geometry": {"coordinates":[145.069580078,-37.9335212708],"type":"Point"}
}