{
  "type": "Feature",
  "properties": {
    "iso:country":"AU",
    "sg:address":"61 Hunter St",
    "sg:city":"Hornsby",
    "sg:classifiers":[
        {
            "category":"Building & Trades",
            "subcategory":"Construction",
            "type":"Services"
        }
    ],
    "sg:phone":"+61 2 9476 5481",
    "sg:postcode":"2077",
    "sg:province":"NSW",
    "sg:tags":[
        "contractor"
    ],
    "wof:name":"Edward Gough Pty Ltd",
    "wof:placetype":"venue"
},
  "geometry": {"coordinates":[151.10092163100001,-33.701461792],"type":"Point"}
}