{
  "type": "Feature",
  "properties": {
    "addr:full":"127 Bruce Hwy Edmonton QLD 4869",
    "addr:housenumber":"127",
    "addr:postcode":"4869",
    "addr:street":"Bruce Hwy",
    "iso:country":"AU",
    "sg:address":"127 Bruce Hwy",
    "sg:city":"Edmonton",
    "sg:classifiers":[
        {
            "category":"Travel",
            "subcategory":"Hotels & Motels",
            "type":"Entertainment"
        }
    ],
    "sg:phone":"+61 7 4045 9888",
    "sg:postcode":"4869",
    "sg:province":"QLD",
    "sg:tags":[
        "pub"
    ],
    "wof:name":"Historic Hambledon Hotel",
    "wof:placetype":"venue"
},
  "geometry": {"coordinates":[145.74476623499999,-17.0196247101],"type":"Point"}
}