{
  "type": "Feature",
  "properties": {
    "addr:full":"PO Box 97 Mt Lawley WA 6929",
    "addr:postcode":"6929",
    "iso:country":"AU",
    "sg:address":"PO Box 97",
    "sg:city":"Mt Lawley",
    "sg:classifiers":[
        {
            "category":"Real Estate",
            "subcategory":"Real Estate Agent",
            "type":"Services"
        }
    ],
    "sg:phone":"+61 8 9272 8885",
    "sg:postcode":"6929",
    "sg:province":"WA",
    "wof:name":"Bartels Real Estate",
    "wof:placetype":"venue"
},
  "geometry": {"coordinates":[115.872161865,-31.9344406128],"type":"Point"}
}