{
  "type": "Feature",
  "properties": {
    "addr:full":"Shop 311 -312 Wyong Plaza Wyong NSW 2259",
    "addr:housenumber":"311 -312 wyong",
    "addr:postcode":"2259",
    "iso:country":"AU",
    "sg:address":"Shop 311",
    "sg:city":"-312 Wyong Plaza Wyong",
    "sg:classifiers":[
        {
            "category":"Shopping",
            "subcategory":"Computers & Home Electronics",
            "type":"Retail Goods"
        }
    ],
    "sg:phone":"+61 2 4353 2551",
    "sg:postcode":"2259",
    "sg:province":"NSW",
    "sg:tags":[
        "equipment",
        "part",
        "electronic"
    ],
    "wof:name":"Tandy Electronics",
    "wof:placetype":"venue"
},
  "geometry": {"coordinates":[151.42552185100001,-33.2829093933],"type":"Point"}
}