{
  "type": "Feature",
  "properties": {
    "addr:full":"27 Stonehaven Rd Mt Colah NSW 2079",
    "addr:housenumber":"27",
    "addr:postcode":"2079",
    "addr:street":"Stonehaven Rd;Colah",
    "iso:country":"AU",
    "sg:address":"27 Stonehaven Rd",
    "sg:city":"Mt Colah",
    "sg:classifiers":[
        {
            "category":"Retail",
            "subcategory":"Storage",
            "type":"Services"
        }
    ],
    "sg:phone":"+61 2 9457 8272",
    "sg:postcode":"2079",
    "sg:province":"NSW",
    "sg:tags":[
        "shelving",
        "system"
    ],
    "wof:name":"Tebrax Australasia Pty Ltd",
    "wof:placetype":"venue"
},
  "geometry": {"coordinates":[151.11741638199999,-33.6626396179],"type":"Point"}
}