{
  "type": "Feature",
  "properties": {
    "addr:full":"Macquarie University, 2nd Fl, Becton Dickinson Bldg North Ryde NSW 2113",
    "addr:postcode":"2113",
    "iso:country":"AU",
    "sg:address":"Macquarie University, 2nd Fl, Becton Dickinson Bldg",
    "sg:city":"North Ryde",
    "sg:classifiers":[
        {
            "category":"Shopping",
            "subcategory":"Computers & Home Electronics",
            "type":"Retail Goods"
        }
    ],
    "sg:phone":"+61 2 9850 8792",
    "sg:postcode":"2113",
    "sg:province":"NSW",
    "sg:tags":[
        "small",
        "equipment",
        "business"
    ],
    "wof:name":"Macquarie Educomp",
    "wof:placetype":"venue"
},
  "geometry": {"coordinates":[151.11459350600001,-33.7769622803],"type":"Point"}
}