{
  "type": "Feature",
  "properties": {
    "iso:country":"AU",
    "sg:address":"528 Boundary Rd",
    "sg:city":"Coopers Plains",
    "sg:classifiers":[
        {
            "category":"Retail",
            "subcategory":"Auto Repair",
            "type":"Services"
        }
    ],
    "sg:phone":"+61 7 3275 1222",
    "sg:postcode":"4108",
    "sg:province":"QLD",
    "sg:tags":[
        "beater",
        "painter",
        "panel"
    ],
    "sg:website":"http://www.smashrepairers.com/bradys/",
    "wof:name":"Bradys Body Works",
    "wof:placetype":"venue"
},
  "geometry": {"coordinates":[153.01768493599999,-27.5672111511],"type":"Point"}
}