{
  "type": "Feature",
  "properties": {
    "addr:full":"Shop 6, Mount Street Plaza North Sydney NSW 2060",
    "addr:housenumber":"shop 6",
    "addr:postcode":"2060",
    "addr:street":"Mount Street",
    "iso:country":"AU",
    "sg:address":"Shop 6, Mount Street Plaza",
    "sg:city":"North Sydney",
    "sg:classifiers":[
        {
            "category":"Travel",
            "subcategory":"Travel Agent",
            "type":"Entertainment"
        }
    ],
    "sg:phone":"+61 2 9922 6533",
    "sg:postcode":"2060",
    "sg:province":"NSW",
    "sg:tags":[
        "consultant"
    ],
    "wof:name":"STA Travel",
    "wof:placetype":"venue"
},
  "geometry": {"coordinates":[151.208587647,-33.8395080566],"type":"Point"}
}