{
  "type": "Feature",
  "properties": {
    "iso:country":"AU",
    "sg:address":"4 Le Messurier St",
    "sg:city":"Murray Bridge",
    "sg:classifiers":[
        {
            "category":"Travel",
            "subcategory":"Hotels & Motels",
            "type":"Entertainment"
        }
    ],
    "sg:phone":"+61 8 8532 2388",
    "sg:postcode":"5253",
    "sg:province":"SA",
    "wof:name":"Golden Chain Murray Bridge Oval Motel",
    "wof:placetype":"venue"
},
  "geometry": {"coordinates":[139.26426696799999,-35.1232528687],"type":"Point"}
}