{
  "type": "Feature",
  "properties": {
    "iso:country":"AU",
    "sg:address":"192 Gilbert St",
    "sg:city":"Adelaide",
    "sg:classifiers":[
        {
            "category":"Building & Trades",
            "subcategory":"Construction",
            "type":"Services"
        }
    ],
    "sg:phone":"+61 8 8212 3337",
    "sg:postcode":"5000",
    "sg:province":"SA",
    "sg:tags":[
        "contractor"
    ],
    "wof:name":"COMMERCIAL & GENERAL PTY LTD",
    "wof:placetype":"venue"
},
  "geometry": {"coordinates":[138.592987061,-34.934551239],"type":"Point"}
}