{
  "type": "Feature",
  "properties": {
    "addr:full":"Shop 7 Millstream Cntr, 21 Mends St South Perth WA 6151",
    "addr:housenumber":"shop 7;21",
    "addr:postcode":"6151",
    "addr:street":"Millstream Cntr;St",
    "iso:country":"AU",
    "sg:address":"Shop 7 Millstream Cntr, 21 Mends St",
    "sg:city":"South Perth",
    "sg:classifiers":[
        {
            "category":"Real Estate",
            "subcategory":"Real Estate Agent",
            "type":"Services"
        }
    ],
    "sg:phone":"+61 8 9474 2200",
    "sg:postcode":"6151",
    "sg:province":"WA",
    "wof:name":"Ian Hutchison Real Estate",
    "wof:placetype":"venue"
},
  "geometry": {"coordinates":[115.85272999999999,-31.972006],"type":"Point"}
}