{
  "type": "Feature",
  "properties": {
    "addr:full":"Rear/ 174 Terminus St Liverpool NSW 2170",
    "addr:housenumber":"rear / 174",
    "addr:postcode":"2170",
    "addr:street":"Terminus St",
    "iso:country":"AU",
    "sg:address":"Rear/ 174 Terminus St",
    "sg:city":"Liverpool",
    "sg:classifiers":[
        {
            "category":"Retail",
            "subcategory":"Auto Repair",
            "type":"Services"
        }
    ],
    "sg:phone":"+61 2 9601 4197",
    "sg:postcode":"2170",
    "sg:province":"NSW",
    "sg:tags":[
        "repairer",
        "motor",
        "engineer"
    ],
    "wof:name":"MST Auto Service",
    "wof:placetype":"venue"
},
  "geometry": {"coordinates":[150.91969299300001,-33.9275398254],"type":"Point"}
}