{
  "type": "Feature",
  "properties": {
    "iso:country":"AU",
    "sg:address":"Unit 15 Argonaut Shopping Cntr Cnr Kingston Rd & Noel St",
    "sg:city":"Slacks Creek",
    "sg:classifiers":[
        {
            "category":"Organizations",
            "subcategory":"Community Association",
            "type":"Services"
        }
    ],
    "sg:phone":"+61 7 3290 3011",
    "sg:postcode":"4127",
    "sg:province":"QLD",
    "sg:tags":[
        "organisation",
        "family",
        "welfare"
    ],
    "wof:name":"Adventist Community Care",
    "wof:placetype":"venue"
},
  "geometry": {"coordinates":[153.118682861,-27.6303195953],"type":"Point"}
}