{
  "type": "Feature",
  "properties": {
    "addr:full":"154 Sailors Bay Rd Northbridge NSW 2063",
    "addr:housenumber":"154",
    "addr:postcode":"2063",
    "addr:street":"Sailors Bay Rd",
    "iso:country":"AU",
    "sg:address":"154 Sailors Bay Rd",
    "sg:city":"Northbridge",
    "sg:classifiers":[
        {
            "category":"Health Services",
            "subcategory":"Doctor",
            "type":"Services"
        }
    ],
    "sg:phone":"+61 2 9958 7104",
    "sg:postcode":"2063",
    "sg:province":"NSW",
    "sg:tags":[
        "medical",
        "practitioner"
    ],
    "wof:name":"Burke Michael & Thomas Rodney",
    "wof:placetype":"venue"
},
  "geometry": {"coordinates":[151.211959839,-33.811126709],"type":"Point"}
}