{
  "type": "Feature",
  "properties": {
    "addr:full":"577a Lower North East Rd Campbelltown SA 5074",
    "addr:housenumber":"577a",
    "addr:postcode":"5074",
    "addr:street":"Lower North East Rd",
    "iso:country":"AU",
    "sg:address":"577a Lower North East Rd",
    "sg:city":"Campbelltown",
    "sg:classifiers":[
        {
            "category":"Health Services",
            "subcategory":"Dentist",
            "type":"Services"
        }
    ],
    "sg:phone":"+61 8 8337 5406",
    "sg:postcode":"5074",
    "sg:province":"SA",
    "wof:name":"Robertson Andrew D",
    "wof:placetype":"venue"
},
  "geometry": {"coordinates":[138.66178894000001,-34.8807678223],"type":"Point"}
}