{
  "type": "Feature",
  "properties": {
    "addr:full":"20 Mc Kimmies Rd Lalor VIC 3075",
    "addr:housenumber":"20",
    "addr:postcode":"3075",
    "addr:street":"Mc Kimmies Rd",
    "iso:country":"AU",
    "sg:address":"20 Mc Kimmies Rd",
    "sg:city":"Lalor",
    "sg:classifiers":[
        {
            "category":"Health Services",
            "subcategory":"Dentist",
            "type":"Services"
        }
    ],
    "sg:phone":"+61 3 9465 8222",
    "sg:postcode":"3075",
    "sg:province":"VIC",
    "wof:name":"Simkiss Grant",
    "wof:placetype":"venue"
},
  "geometry": {"coordinates":[145.03436279300001,-37.6751937866],"type":"Point"}
}