{
  "type": "Feature",
  "properties": {
    "addr:full":"123 Lake Rd Elermore Vale NSW 2287",
    "addr:housenumber":"123",
    "addr:postcode":"2287",
    "addr:street":"Lake Rd",
    "iso:country":"AU",
    "sg:address":"123 Lake Rd",
    "sg:city":"Elermore Vale",
    "sg:classifiers":[
        {
            "category":"Food & Beverages",
            "subcategory":"Bakery",
            "type":"Retail Goods"
        }
    ],
    "sg:phone":"+61 2 4951 6318",
    "sg:postcode":"2287",
    "sg:province":"NSW",
    "sg:tags":[
        "cake",
        "shop",
        "pastry"
    ],
    "wof:name":"Darby's Fresh Bake",
    "wof:placetype":"venue"
},
  "geometry": {"coordinates":[151.657150269,-32.9184417725],"type":"Point"}
}