{
  "type": "Feature",
  "properties": {
    "iso:country":"AU",
    "sg:address":"9 Pioneer Rd",
    "sg:city":"Yandina",
    "sg:classifiers":[
        {
            "category":"Wholesale",
            "subcategory":"Auto Parts",
            "type":"Manufacturing & Wholesale Goods"
        }
    ],
    "sg:phone":"+61 7 5472 9282",
    "sg:postcode":"4561",
    "sg:province":"QLD",
    "sg:tags":[
        "recyclers"
    ],
    "wof:name":"Subaru Auto Recyclers",
    "wof:placetype":"venue"
},
  "geometry": {"coordinates":[152.960372925,-26.5576095581],"type":"Point"}
}