{
  "type": "Feature",
  "properties": {
    "addr:full":"176 Hartley Valley Rd Lithgow NSW 2790",
    "addr:housenumber":"176",
    "addr:postcode":"2790",
    "addr:street":"Hartley Valley Rd",
    "iso:country":"AU",
    "sg:address":"176 Hartley Valley Rd",
    "sg:city":"Lithgow",
    "sg:classifiers":[
        {
            "category":"Autos & Motor Vehicles",
            "subcategory":"Auto Supplies",
            "type":"Retail Goods"
        }
    ],
    "sg:phone":"+61 2 6351 3262",
    "sg:postcode":"2790",
    "sg:province":"NSW",
    "sg:tags":[
        "tyre"
    ],
    "wof:name":"Yokohama",
    "wof:placetype":"venue"
},
  "geometry": {"coordinates":[150.174880981,-33.4792518616],"type":"Point"}
}