{
  "type": "Feature",
  "properties": {
    "addr:full":"28 Autumn St Belmont VIC 3216",
    "addr:housenumber":"28",
    "addr:postcode":"3216",
    "addr:street":"Autumn St",
    "iso:country":"AU",
    "sg:address":"28 Autumn St",
    "sg:city":"Belmont",
    "sg:classifiers":[
        {
            "category":"Health Services",
            "subcategory":"Health Practitioner",
            "type":"Services"
        }
    ],
    "sg:phone":"+61 3 5241 3947",
    "sg:postcode":"3216",
    "sg:province":"VIC",
    "sg:tags":[
        "myotherapy"
    ],
    "wof:name":"Rouhard Diana",
    "wof:placetype":"venue"
},
  "geometry": {"coordinates":[144.345458984,-38.1847686768],"type":"Point"}
}