{
  "type": "Feature",
  "properties": {
    "addr:full":"14 Mooltunya Crt Kingsley WA 6026",
    "addr:housenumber":"14",
    "addr:postcode":"6026",
    "addr:street":"Mooltunya Crt",
    "iso:country":"AU",
    "sg:address":"14 Mooltunya Crt",
    "sg:city":"Kingsley",
    "sg:classifiers":[
        {
            "category":"Building & Trades",
            "subcategory":"Construction",
            "type":"Services"
        }
    ],
    "sg:phone":"+61 8 9409 6595",
    "sg:postcode":"6026",
    "sg:province":"WA",
    "sg:tags":[
        "concrete",
        "contractor"
    ],
    "wof:name":"WiL-HiL Concrete Service",
    "wof:placetype":"venue"
},
  "geometry": {"coordinates":[115.808731079,-31.8136024475],"type":"Point"}
}