{
  "type": "Feature",
  "properties": {
    "addr:full":"7 Kadina Rd Cambridge TAS 7170",
    "addr:housenumber":"7",
    "addr:postcode":"7170",
    "addr:street":"Kadina Rd",
    "iso:country":"AU",
    "sg:address":"7 Kadina Rd",
    "sg:city":"Cambridge",
    "sg:classifiers":[
        {
            "category":"Retail",
            "subcategory":"Auto Repair",
            "type":"Services"
        }
    ],
    "sg:phone":"+61 417 597 887",
    "sg:postcode":"7170",
    "sg:province":"TAS",
    "sg:tags":[
        "electrical"
    ],
    "wof:name":"Advanced Auto Electrics",
    "wof:placetype":"venue"
},
  "geometry": {"coordinates":[147.444625855,-42.8295097351],"type":"Point"}
}