{
  "type": "Feature",
  "properties": {
    "iso:country":"AU",
    "sg:address":"67 Gertrude McLeod Crs",
    "sg:city":"Middle Park",
    "sg:classifiers":[
        {
            "category":"Retail",
            "subcategory":"Driving School",
            "type":"Services"
        }
    ],
    "sg:phone":"+61 7 3279 0023",
    "sg:postcode":"4074",
    "sg:province":"QLD",
    "wof:name":"Mortons Driving School Of Excellence",
    "wof:placetype":"venue"
},
  "geometry": {"coordinates":[152.92193603499999,-27.5521202087],"type":"Point"}
}