{
  "type": "Feature",
  "properties": {
    "addr:full":"18 Brownlee St Wollongong NSW 2500",
    "addr:housenumber":"18",
    "addr:postcode":"2500",
    "addr:street":"Brownlee St",
    "iso:country":"AU",
    "sg:address":"18 Brownlee St",
    "sg:city":"Wollongong",
    "sg:classifiers":[
        {
            "category":"Education",
            "subcategory":"Dance Studio",
            "type":"Public Place"
        }
    ],
    "sg:phone":"+61 2 4229 4059",
    "sg:postcode":"2500",
    "sg:province":"NSW",
    "sg:tags":[
        "square",
        "caller",
        "dancing"
    ],
    "wof:name":"Wonson Barry J",
    "wof:placetype":"venue"
},
  "geometry": {"coordinates":[150.87539699999999,-34.428192],"type":"Point"}
}