{
  "type": "Feature",
  "properties": {
    "iso:country":"AU",
    "sg:address":"Griffith University Drv",
    "sg:city":"Nathan",
    "sg:classifiers":[
        {
            "category":"Professional",
            "subcategory":"Research",
            "type":"Services"
        }
    ],
    "sg:phone":"+61 7 3735 5004",
    "sg:postcode":"4111",
    "sg:province":"QLD",
    "sg:tags":[
        "industrial",
        "scientific"
    ],
    "wof:name":"Center for Wireless Monitoring & Applications",
    "wof:placetype":"venue"
},
  "geometry": {"coordinates":[153.06636047399999,-27.5431594849],"type":"Point"}
}