{
  "type": "Feature",
  "properties": {
    "addr:full":"64- 66 Mostyn St Castlemaine VIC 3450",
    "addr:housenumber":"66",
    "addr:postcode":"3450",
    "addr:street":"Mostyn St",
    "iso:country":"AU",
    "sg:address":"64- 66 Mostyn St",
    "sg:city":"Castlemaine",
    "sg:classifiers":[
        {
            "category":"Education",
            "subcategory":"Special Training",
            "type":"Public Place"
        }
    ],
    "sg:phone":"+61 1300 305 977",
    "sg:postcode":"3450",
    "sg:province":"VIC",
    "sg:tags":[
        "development"
    ],
    "wof:name":"The Victorian Training Group",
    "wof:placetype":"venue"
},
  "geometry": {"coordinates":[144.22012329099999,-37.0660896301],"type":"Point"}
}