{
  "type": "Feature",
  "properties": {
    "iso:country":"AU",
    "sg:address":"1209 High St",
    "sg:city":"Armadale",
    "sg:classifiers":[
        {
            "category":"Professional",
            "subcategory":"Art Services",
            "type":"Services"
        }
    ],
    "sg:phone":"+61 3 9822 7971",
    "sg:postcode":"3143",
    "sg:province":"VIC",
    "sg:tags":[
        "interior",
        "decorator"
    ],
    "wof:name":"Royale Interiors (Vic) Pty Ltd",
    "wof:placetype":"venue"
},
  "geometry": {"coordinates":[145.027908325,-37.8562850952],"type":"Point"}
}