{
  "type": "Feature",
  "properties": {
    "iso:country":"AU",
    "sg:address":"Shop 2, 2a Spencer St",
    "sg:city":"Bunbury",
    "sg:classifiers":[
        {
            "category":"Shopping",
            "type":"Retail Goods"
        }
    ],
    "sg:phone":"+61 8 9791 8191",
    "sg:postcode":"6230",
    "sg:province":"WA",
    "sg:tags":[
        "new age",
        "product"
    ],
    "wof:name":"So-Mote-It-Be",
    "wof:placetype":"venue"
},
  "geometry": {"coordinates":[115.639008,-33.327255],"type":"Point"}
}