{
  "type": "Feature",
  "properties": {
    "iso:country":"AU",
    "sg:address":"Shop 110 Stocklands Shellharbour",
    "sg:city":"Shellharbour City Centre",
    "sg:classifiers":[
        {
            "category":"Health Services",
            "subcategory":"Health Practitioner",
            "type":"Services"
        }
    ],
    "sg:phone":"+61 2 4297 0995",
    "sg:postcode":"2529",
    "sg:province":"NSW",
    "sg:tags":[
        "osteopath"
    ],
    "wof:name":"Threlfo Jeffrey",
    "wof:placetype":"venue"
},
  "geometry": {"coordinates":[150.83636474599999,-34.5661811829],"type":"Point"}
}