{
  "type": "Feature",
  "properties": {
    "iso:country":"AU",
    "sg:address":"Shed 1, 27 High St",
    "sg:city":"Kippa-Ring",
    "sg:classifiers":[
        {
            "category":"Retail",
            "subcategory":"Auto Repair",
            "type":"Services"
        }
    ],
    "sg:phone":"+61 7 3284 2233",
    "sg:postcode":"4021",
    "sg:province":"QLD",
    "sg:tags":[
        "beater",
        "painter",
        "panel"
    ],
    "wof:name":"Ferritto V",
    "wof:placetype":"venue"
},
  "geometry": {"coordinates":[153.090836,-27.226023],"type":"Point"}
}