{
  "type": "Feature",
  "properties": {
    "addr:full":"Cnr Campbell St & Ashmore Rd Bundall QLD 4217",
    "addr:postcode":"4217",
    "addr:street":"Cnr Campbell St & Ashmore Rd",
    "iso:country":"AU",
    "sg:address":"Cnr Campbell St & Ashmore Rd",
    "sg:city":"Bundall",
    "sg:classifiers":[
        {
            "category":"Professional",
            "subcategory":"Art Services",
            "type":"Services"
        }
    ],
    "sg:phone":"+61 7 5570 3539",
    "sg:postcode":"4217",
    "sg:province":"QLD",
    "sg:tags":[
        "interior",
        "designer"
    ],
    "wof:name":"Chic Interiors",
    "wof:placetype":"venue"
},
  "geometry": {"coordinates":[153.40425109899999,-28.0105686188],"type":"Point"}
}