{
  "type": "Feature",
  "properties": {
    "addr:full":"Croydon Rd Hurstville NSW 2220",
    "addr:postcode":"2220",
    "addr:street":"Croydon Rd",
    "iso:country":"AU",
    "sg:address":"Croydon Rd",
    "sg:city":"Hurstville",
    "sg:classifiers":[
        {
            "category":"Education",
            "subcategory":"School",
            "type":"Public Place"
        }
    ],
    "sg:phone":"+61 2 9587 2358",
    "sg:postcode":"2220",
    "sg:province":"NSW",
    "wof:name":"St Mary's Star Of The Sea Primary School",
    "wof:placetype":"venue"
},
  "geometry": {"coordinates":[151.11175537099999,-33.9610023499],"type":"Point"}
}