{
  "type": "Feature",
  "properties": {
    "addr:full":"113 Spitfire Ave Strathpine QLD 4500",
    "addr:housenumber":"113",
    "addr:postcode":"4500",
    "addr:street":"Spitfire Ave",
    "iso:country":"AU",
    "sg:address":"113 Spitfire Ave",
    "sg:city":"Strathpine",
    "sg:classifiers":[
        {
            "category":"Professional",
            "type":"Services"
        }
    ],
    "sg:phone":"+61 7 3205 2362",
    "sg:postcode":"4500",
    "sg:province":"QLD",
    "sg:tags":[
        "transport"
    ],
    "wof:name":"Cole's Carrying Service",
    "wof:placetype":"venue"
},
  "geometry": {"coordinates":[152.98980712900001,-27.2977352142],"type":"Point"}
}