{
  "type": "Feature",
  "properties": {
    "addr:full":"Kingsbury Rd Loxton SA 5333",
    "addr:postcode":"5333",
    "addr:street":"Kingsbury Rd",
    "iso:country":"AU",
    "sg:address":"Kingsbury Rd",
    "sg:city":"Loxton",
    "sg:classifiers":[
        {
            "category":"Farming",
            "subcategory":"Orchard",
            "type":"Manufacturing & Wholesale Goods"
        }
    ],
    "sg:phone":"+61 8 8584 6912",
    "sg:postcode":"5333",
    "sg:province":"SA",
    "sg:tags":[
        "citrus",
        "fruit",
        "grower"
    ],
    "wof:name":"Vasey R G & C J",
    "wof:placetype":"venue"
},
  "geometry": {"coordinates":[140.610031128,-34.457901001],"type":"Point"}
}