{
  "type": "Feature",
  "properties": {
    "addr:full":"350 Grieve Pde Brooklyn VIC 3025",
    "addr:housenumber":"350",
    "addr:postcode":"3025",
    "addr:street":"Grieve Pde",
    "iso:country":"AU",
    "sg:address":"350 Grieve Pde",
    "sg:city":"Brooklyn",
    "sg:classifiers":[
        {
            "category":"Retail",
            "subcategory":"Storage",
            "type":"Services"
        }
    ],
    "sg:phone":"+61 3 9318 0566",
    "sg:postcode":"3025",
    "sg:province":"VIC",
    "sg:tags":[
        "shelving",
        "system"
    ],
    "wof:name":"Panorama Office Products Pty Ltd",
    "wof:placetype":"venue"
},
  "geometry": {"coordinates":[144.824692,-37.846592],"type":"Point"}
}