{
  "type": "Feature",
  "properties": {
    "iso:country":"AU",
    "sg:address":"Cnr Brisbane and Gordon Sts",
    "sg:city":"Mackay",
    "sg:classifiers":[
        {
            "category":"Professional",
            "subcategory":"Employment Agencies",
            "type":"Services"
        }
    ],
    "sg:phone":"+61 7 4951 7781",
    "sg:postcode":"4740",
    "sg:province":"QLD",
    "sg:tags":[
        "provider",
        "internet"
    ],
    "wof:name":"Mackay Computer Services Pty Ltd",
    "wof:placetype":"venue"
},
  "geometry": {"coordinates":[149.18760700000001,-21.146685],"type":"Point"}
}