{
  "type": "Feature",
  "properties": {
    "iso:country":"AU",
    "sg:address":"3 Elphingstone Crt",
    "sg:city":"Kew",
    "sg:classifiers":[
        {
            "category":"Professional",
            "subcategory":"Management & Consulting",
            "type":"Services"
        }
    ],
    "sg:phone":"+61 3 9853 2979",
    "sg:postcode":"3101",
    "sg:province":"VIC",
    "sg:tags":[
        "consultant"
    ],
    "wof:name":"Edbiz Pty Ltd",
    "wof:placetype":"venue"
},
  "geometry": {"coordinates":[145.02638244600001,-37.8055229187],"type":"Point"}
}