{
  "type": "Feature",
  "properties": {
    "addr:full":"35 Margaret St Burpengary QLD 4505",
    "addr:housenumber":"35",
    "addr:postcode":"4505",
    "addr:street":"Margaret St",
    "iso:country":"AU",
    "sg:address":"35 Margaret St",
    "sg:city":"Burpengary",
    "sg:classifiers":[
        {
            "category":"Utilities",
            "subcategory":"Electric",
            "type":"Services"
        }
    ],
    "sg:phone":"+61 7 3888 1180",
    "sg:postcode":"4505",
    "sg:province":"QLD",
    "sg:tags":[
        "electrical",
        "contractor"
    ],
    "wof:name":"Jacob R J & J A",
    "wof:placetype":"venue"
},
  "geometry": {"coordinates":[153.009002686,-27.1584033966],"type":"Point"}
}