{
  "type": "Feature",
  "properties": {
    "addr:full":"P.O. Box 3275 Doncaster East VIC 3109",
    "addr:postcode":"3109",
    "iso:country":"AU",
    "sg:address":"P.O. Box 3275",
    "sg:city":"Doncaster East",
    "sg:classifiers":[
        {
            "category":"Building & Trades",
            "subcategory":"Construction",
            "type":"Services"
        }
    ],
    "sg:phone":"+61 419 147 751",
    "sg:postcode":"3109",
    "sg:province":"VIC",
    "sg:tags":[
        "renovation",
        "alterations",
        "extension",
        "contractor"
    ],
    "wof:name":"Delaware Homes",
    "wof:placetype":"venue"
},
  "geometry": {"coordinates":[145.16047668499999,-37.7888908386],"type":"Point"}
}