{
  "type": "Feature",
  "properties": {
    "iso:country":"AU",
    "sg:address":"47 Cardigan Pl",
    "sg:city":"Albert Park",
    "sg:classifiers":[
        {
            "category":"Real Estate",
            "subcategory":"Architect",
            "type":"Services"
        }
    ],
    "sg:phone":"+61 3 9686 4455",
    "sg:postcode":"3206",
    "sg:province":"VIC",
    "wof:name":"Lewitan Shraga Architect",
    "wof:placetype":"venue"
},
  "geometry": {"coordinates":[144.952499,-37.841152],"type":"Point"}
}