{
  "type": "Feature",
  "properties": {
    "addr:full":"144 Gouger St Adelaide SA 5000",
    "addr:housenumber":"144",
    "addr:postcode":"5000",
    "addr:street":"Gouger St",
    "iso:country":"AU",
    "sg:address":"144 Gouger St",
    "sg:city":"Adelaide",
    "sg:classifiers":[
        {
            "category":"Autos & Motor Vehicles",
            "subcategory":"Auto Supplies",
            "type":"Retail Goods"
        }
    ],
    "sg:phone":"+61 8 8231 1001",
    "sg:postcode":"5000",
    "sg:province":"SA",
    "sg:tags":[
        "battery",
        "automotive"
    ],
    "wof:name":"Bob Jane T-Marts",
    "wof:placetype":"venue"
},
  "geometry": {"coordinates":[138.59364318900001,-34.9303131104],"type":"Point"}
}