{
  "type": "Feature",
  "properties": {
    "addr:full":"Corner Tummaville Road & Gore Highway Yarranlea QLD 4356",
    "addr:postcode":"4356",
    "addr:street":"Tummaville Road & Gore Highway",
    "iso:country":"AU",
    "sg:address":"Corner Tummaville Road",
    "sg:city":"& Gore Highway Yarranlea",
    "sg:classifiers":[
        {
            "category":"Wholesale",
            "subcategory":"Machinery & Supplies",
            "type":"Manufacturing & Wholesale Goods"
        }
    ],
    "sg:phone":"+61 408 743 071",
    "sg:postcode":"4356",
    "sg:province":"QLD",
    "sg:tags":[
        "agricultural"
    ],
    "wof:name":"Darling Downs Engineering & Hydraulics",
    "wof:placetype":"venue"
},
  "geometry": {"coordinates":[151.54643200000001,-27.76346],"type":"Point"}
}