{
  "type": "Feature",
  "properties": {
    "addr:full":"Shop 62 Stockland Bay Village The Entrance Rd Bateau Bay NSW 2261",
    "addr:housenumber":"shop 62",
    "addr:postcode":"2261",
    "addr:street":"Stockland Bay;The Entrance Rd",
    "iso:country":"AU",
    "sg:address":"Shop 62 Stockland Bay Village The Entrance Rd",
    "sg:city":"Bateau Bay",
    "sg:classifiers":[
        {
            "category":"Personal",
            "subcategory":"Beauty Salon",
            "type":"Services"
        }
    ],
    "sg:phone":"+61 2 4332 8122",
    "sg:postcode":"2261",
    "sg:province":"NSW",
    "sg:tags":[
        "hairdresser"
    ],
    "wof:name":"Price Attack",
    "wof:placetype":"venue"
},
  "geometry": {"coordinates":[151.47340399999999,-33.380699],"type":"Point"}
}