{
  "type": "Feature",
  "properties": {
    "addr:full":"44 Osborne Ave Bathurst West NSW 2795",
    "addr:housenumber":"44",
    "addr:postcode":"2795",
    "addr:street":"Osborne Ave",
    "iso:country":"AU",
    "sg:address":"44 Osborne Ave",
    "sg:city":"Bathurst West",
    "sg:classifiers":[
        {
            "category":"Government",
            "subcategory":"Court House",
            "type":"Public Place"
        }
    ],
    "sg:phone":"+61 2 6332 4139",
    "sg:postcode":"2795",
    "sg:province":"NSW",
    "sg:tags":[
        "personal",
        "marriage",
        "family",
        "counselling"
    ],
    "wof:name":"Blundell J",
    "wof:placetype":"venue"
},
  "geometry": {"coordinates":[149.55824279800001,-33.4075088501],"type":"Point"}
}