{
  "type": "Feature",
  "properties": {
    "addr:full":"Sydney Private Hospital 12 Robert St (Cnr Victoria St) Ashfield NSW 2131",
    "addr:housenumber":"12",
    "addr:postcode":"2131",
    "addr:street":"Sydney;Robert St Cnr Victoria St",
    "iso:country":"AU",
    "sg:address":"Sydney Private Hospital 12 Robert St",
    "sg:city":"(Cnr Victoria St) Ashfield",
    "sg:classifiers":[
        {
            "category":"Health Services",
            "subcategory":"Doctor",
            "type":"Services"
        }
    ],
    "sg:phone":"+61 2 9716 3567",
    "sg:postcode":"2131",
    "sg:province":"NSW",
    "sg:tags":[
        "medical",
        "practitioner"
    ],
    "wof:name":"Davies Campbell+ de Lambert Pathology",
    "wof:placetype":"venue"
},
  "geometry": {"coordinates":[151.12911987300001,-33.8934593201],"type":"Point"}
}