{
  "type": "Feature",
  "properties": {
    "iso:country":"AU",
    "sg:address":"2c Wells St",
    "sg:city":"Gosford East",
    "sg:classifiers":[
        {
            "category":"Wholesale",
            "subcategory":"Photographic Equipment",
            "type":"Manufacturing & Wholesale Goods"
        }
    ],
    "sg:phone":"+61 2 4324 1706",
    "sg:postcode":"2250",
    "sg:province":"NSW",
    "sg:tags":[
        "wholesaler",
        "mfrs",
        "supply"
    ],
    "wof:name":"Photo Store The",
    "wof:placetype":"venue"
},
  "geometry": {"coordinates":[151.349487305,-33.4362335205],"type":"Point"}
}