{
  "type": "Feature",
  "properties": {
    "addr:full":"6 Breda Crt Salisbury Downs SA 5108",
    "addr:housenumber":"6",
    "addr:postcode":"5108",
    "addr:street":"Breda Crt",
    "iso:country":"AU",
    "sg:address":"6 Breda Crt",
    "sg:city":"Salisbury Downs",
    "sg:classifiers":[
        {
            "category":"Building & Trades",
            "subcategory":"Cleaning & Sanitation",
            "type":"Services"
        }
    ],
    "sg:phone":"+61 8 8250 4400",
    "sg:postcode":"5108",
    "sg:province":"SA",
    "sg:tags":[
        "window"
    ],
    "wof:name":"Imperial Window Cleaning",
    "wof:placetype":"venue"
},
  "geometry": {"coordinates":[138.62884521500001,-34.7797966003],"type":"Point"}
}