{
  "type": "Feature",
  "properties": {
    "addr:full":"11 Sheringham Pl Tingalpa QLD 4173",
    "addr:housenumber":"11",
    "addr:postcode":"4173",
    "addr:street":"Sheringham Pl",
    "iso:country":"AU",
    "sg:address":"11 Sheringham Pl",
    "sg:city":"Tingalpa",
    "sg:classifiers":[
        {
            "category":"Real Estate",
            "subcategory":"Architect",
            "type":"Services"
        }
    ],
    "sg:phone":"+61 7 3890 5590",
    "sg:postcode":"4173",
    "sg:province":"QLD",
    "wof:name":"Gow Robert Architects",
    "wof:placetype":"venue"
},
  "geometry": {"coordinates":[153.134307861,-27.4841556549],"type":"Point"}
}