{
  "type": "Feature",
  "properties": {
    "addr:full":"28 Morrow Pl Bathurst NSW 2795",
    "addr:housenumber":"28",
    "addr:postcode":"2795",
    "addr:street":"Morrow Pl",
    "iso:country":"AU",
    "sg:address":"28 Morrow Pl",
    "sg:city":"Bathurst",
    "sg:classifiers":[
        {
            "category":"Building & Trades",
            "subcategory":"Construction",
            "type":"Services"
        }
    ],
    "sg:phone":"+61 2 6331 4355",
    "sg:postcode":"2795",
    "sg:province":"NSW",
    "sg:tags":[
        "road",
        "contractor"
    ],
    "wof:name":"Graham Constructions Bathurst Pty Ltd",
    "wof:placetype":"venue"
},
  "geometry": {"coordinates":[149.542724609,-33.4208374023],"type":"Point"}
}