{
  "type": "Feature",
  "properties": {
    "iso:country":"AU",
    "sg:address":"80 Jerry Bailey Rd",
    "sg:city":"Shoalhaven Heads",
    "sg:classifiers":[
        {
            "category":"Retail",
            "subcategory":"Auto Repair",
            "type":"Services"
        }
    ],
    "sg:phone":"+61 2 4448 7599",
    "sg:postcode":"2535",
    "sg:province":"NSW",
    "sg:tags":[
        "repairer",
        "motor",
        "engineer"
    ],
    "wof:name":"Shoalhaven Heads Automotive Services Pty Ltd",
    "wof:placetype":"venue"
},
  "geometry": {"coordinates":[150.73405456500001,-34.8542861938],"type":"Point"}
}