{
  "type": "Feature",
  "properties": {
    "iso:country":"AU",
    "sg:address":"29 Yennora Ave",
    "sg:city":"Yennora",
    "sg:classifiers":[
        {
            "category":"Building & Trades",
            "subcategory":"Construction",
            "type":"Services"
        }
    ],
    "sg:phone":"+61 2 9721 3000",
    "sg:postcode":"2161",
    "sg:province":"NSW",
    "sg:tags":[
        "welding"
    ],
    "wof:name":"NWEC Pty Ltd",
    "wof:placetype":"venue"
},
  "geometry": {"coordinates":[150.97129821799999,-33.8620643616],"type":"Point"}
}