{
  "type": "Feature",
  "properties": {
    "addr:full":"12 Capella Drv Hallett Cove SA 5158",
    "addr:housenumber":"12",
    "addr:postcode":"5158",
    "addr:street":"Capella Drv",
    "iso:country":"AU",
    "sg:address":"12 Capella Drv",
    "sg:city":"Hallett Cove",
    "sg:classifiers":[
        {
            "category":"Personal",
            "subcategory":"Massage",
            "type":"Services"
        }
    ],
    "sg:phone":"+61 8 8298 8664",
    "sg:postcode":"5158",
    "sg:province":"SA",
    "sg:tags":[
        "therapy"
    ],
    "wof:name":"Hallett Cove Health & Fitness Centre",
    "wof:placetype":"venue"
},
  "geometry": {"coordinates":[138.51641845699999,-35.0636558533],"type":"Point"}
}