{
  "type": "Feature",
  "properties": {
    "addr:full":"38A Station St Camden NSW 2570",
    "addr:housenumber":"38a",
    "addr:postcode":"2570",
    "addr:street":"Station St",
    "iso:country":"AU",
    "sg:address":"38A Station St",
    "sg:city":"Camden",
    "sg:classifiers":[
        {
            "category":"Retail",
            "subcategory":"Auto Repair",
            "type":"Services"
        }
    ],
    "sg:phone":"+61 2 4655 3242",
    "sg:postcode":"2570",
    "sg:province":"NSW",
    "sg:tags":[
        "repairer",
        "motor",
        "engineer"
    ],
    "wof:name":"Camden Exhaust",
    "wof:placetype":"venue"
},
  "geometry": {"coordinates":[150.697753906,-34.0524978638],"type":"Point"}
}