{
  "type": "Feature",
  "properties": {
    "addr:full":"Tower B, Ste 1501, Lvl 15, 799 Pacific Hwy Chatswood NSW 2057",
    "addr:housenumber":"799",
    "addr:postcode":"2057",
    "addr:street":"Pacific Hwy",
    "iso:country":"AU",
    "sg:address":"Tower B, Ste 1501, Lvl 15, 799 Pacific Hwy",
    "sg:city":"Chatswood",
    "sg:classifiers":[
        {
            "category":"Banks & Credit Unions",
            "subcategory":"Financial Services",
            "type":"Services"
        }
    ],
    "sg:phone":"+61 2 9415 1611",
    "sg:postcode":"2057",
    "sg:province":"NSW",
    "sg:tags":[
        "planning"
    ],
    "wof:name":"Genesys Wealth Advisers",
    "wof:placetype":"venue"
},
  "geometry": {"coordinates":[151.178146,-33.7962],"type":"Point"}
}