{
  "type": "Feature",
  "properties": {
    "iso:country":"AU",
    "sg:address":"74 Punt Rd",
    "sg:city":"Windsor",
    "sg:classifiers":[
        {
            "category":"Professional",
            "subcategory":"Detective & Security Services",
            "type":"Services"
        }
    ],
    "sg:phone":"+61 3 9521 4443",
    "sg:postcode":"3181",
    "sg:province":"VIC",
    "sg:tags":[
        "equipment",
        "window",
        "doors"
    ],
    "wof:name":"Innovative Security",
    "wof:placetype":"venue"
},
  "geometry": {"coordinates":[144.98379516599999,-37.85389328],"type":"Point"}
}