{
  "type": "Feature",
  "properties": {
    "addr:full":"264 Margaret St Toowoomba QLD 4350",
    "addr:housenumber":"264",
    "addr:postcode":"4350",
    "addr:street":"Margaret St",
    "iso:country":"AU",
    "sg:address":"264 Margaret St",
    "sg:city":"Toowoomba",
    "sg:classifiers":[
        {
            "category":"Banks & Credit Unions",
            "subcategory":"Bank",
            "type":"Services"
        }
    ],
    "sg:phone":"+61 7 4639 2250",
    "sg:postcode":"4350",
    "sg:province":"QLD",
    "sg:tags":[
        "broker",
        "mortgage"
    ],
    "wof:name":"Leaselink Business Finance",
    "wof:placetype":"venue"
},
  "geometry": {"coordinates":[151.94563293499999,-27.5600719452],"type":"Point"}
}