{
  "type": "Feature",
  "properties": {
    "iso:country":"AU",
    "sg:address":"Suite 27 140 Church St",
    "sg:city":"Richmond",
    "sg:classifiers":[
        {
            "category":"Health Services",
            "subcategory":"Doctor",
            "type":"Services"
        }
    ],
    "sg:phone":"+61 3 9420 1475",
    "sg:postcode":"3121",
    "sg:province":"VIC",
    "sg:tags":[
        "medical",
        "practitioner"
    ],
    "wof:name":"Ian Katz Dr",
    "wof:placetype":"venue"
},
  "geometry": {"coordinates":[144.999633789,-37.8151512146],"type":"Point"}
}