{
  "type": "Feature",
  "properties": {
    "iso:country":"AU",
    "sg:address":"262-266 Pirie St",
    "sg:city":"Adelaide",
    "sg:classifiers":[
        {
            "category":"Professional",
            "subcategory":"Management & Consulting",
            "type":"Services"
        }
    ],
    "sg:phone":"+61 8 8223 5088",
    "sg:postcode":"5000",
    "sg:province":"SA",
    "sg:tags":[
        "consultant",
        "migration"
    ],
    "wof:name":"McDonald Steed McGrath Migration Lawyers",
    "wof:placetype":"venue"
},
  "geometry": {"coordinates":[138.609573364,-34.9251441956],"type":"Point"}
}