{
  "type": "Feature",
  "properties": {
    "iso:country":"AU",
    "sg:address":"1 Church St",
    "sg:city":"Brisbane",
    "sg:classifiers":[
        {
            "category":"Building & Trades",
            "subcategory":"Construction",
            "type":"Services"
        }
    ],
    "sg:phone":"+61 414 467 546",
    "sg:postcode":"4000",
    "sg:province":"QLD",
    "sg:tags":[
        "concrete",
        "contractor"
    ],
    "wof:name":"Mr Spraycrete",
    "wof:placetype":"venue"
},
  "geometry": {"coordinates":[153.03851318400001,-27.4547042847],"type":"Point"}
}