{
  "type": "Feature",
  "properties": {
    "iso:country":"AU",
    "sg:address":"Princes Rd",
    "sg:city":"East Regents Park",
    "sg:classifiers":[
        {
            "category":"Autos & Motor Vehicles",
            "subcategory":"Auto Supplies",
            "type":"Retail Goods"
        }
    ],
    "sg:phone":"+61 2 9738 4222",
    "sg:postcode":"2143",
    "sg:province":"NSW",
    "sg:tags":[
        "battery",
        "automotive"
    ],
    "wof:name":"Saft Nife Power Systems Australia Pty Ltd",
    "wof:placetype":"venue"
},
  "geometry": {"coordinates":[151.02441406200001,-33.8764381409],"type":"Point"}
}