{
  "type": "Feature",
  "properties": {
    "iso:country":"AU",
    "sg:address":"9 Duke St",
    "sg:city":"Woonona",
    "sg:classifiers":[
        {
            "category":"Building & Trades",
            "subcategory":"Construction",
            "type":"Services"
        }
    ],
    "sg:phone":"+61 418 427 145",
    "sg:postcode":"2517",
    "sg:province":"NSW",
    "sg:tags":[
        "earth",
        "excavating",
        "moving",
        "contractor"
    ],
    "wof:name":"Darren Bitz Earthmoving Pty Ltd",
    "wof:placetype":"venue"
},
  "geometry": {"coordinates":[150.900925,-34.351448],"type":"Point"}
}