{
  "type": "Feature",
  "properties": {
    "iso:country":"AU",
    "sg:address":"144a Buckley St",
    "sg:city":"Essendon",
    "sg:classifiers":[
        {
            "category":"Real Estate",
            "subcategory":"Real Estate Agent",
            "type":"Services"
        }
    ],
    "sg:phone":"+61 3 9337 2777",
    "sg:postcode":"3040",
    "sg:province":"VIC",
    "wof:name":"Harper Real Estate",
    "wof:placetype":"venue"
},
  "geometry": {"coordinates":[144.91267395,-37.7563934326],"type":"Point"}
}