{
  "type": "Feature",
  "properties": {
    "addr:full":"25 Castle St North Parramatta NSW 2151",
    "addr:housenumber":"25",
    "addr:postcode":"2151",
    "addr:street":"Castle St",
    "iso:country":"AU",
    "sg:address":"25 Castle St",
    "sg:city":"North Parramatta",
    "sg:classifiers":[
        {
            "category":"Retail",
            "subcategory":"Repair Shop",
            "type":"Services"
        }
    ],
    "sg:phone":"+61 2 9630 6333",
    "sg:postcode":"2151",
    "sg:province":"NSW",
    "sg:tags":[
        "cleaner",
        "part",
        "vacuum"
    ],
    "wof:name":"Australian Aqua Air Pty Ltd",
    "wof:placetype":"venue"
},
  "geometry": {"coordinates":[151.00453185999999,-33.7980270386],"type":"Point"}
}