{
  "type": "Feature",
  "properties": {
    "iso:country":"AU",
    "sg:address":"Lot 1 Jellicoe St",
    "sg:city":"Nowra South",
    "sg:classifiers":[
        {
            "category":"Professional",
            "type":"Services"
        }
    ],
    "sg:phone":"+61 2 4423 4605",
    "sg:postcode":"2541",
    "sg:province":"NSW",
    "sg:tags":[
        "coating",
        "powder"
    ],
    "wof:name":"The Powder Works",
    "wof:placetype":"venue"
},
  "geometry": {"coordinates":[150.60295105,-34.908618927],"type":"Point"}
}