{
  "type": "Feature",
  "properties": {
    "iso:country":"AU",
    "sg:address":"38 Queen St",
    "sg:city":"Revesby",
    "sg:classifiers":[
        {
            "category":"Building & Trades",
            "subcategory":"Pest Control",
            "type":"Services"
        }
    ],
    "sg:phone":"+61 2 9771 2400",
    "sg:postcode":"2212",
    "sg:province":"NSW",
    "wof:name":"TermiStop Australia Pty Limited",
    "wof:placetype":"venue"
},
  "geometry": {"coordinates":[151.009735,-33.944923],"type":"Point"}
}