{
  "type": "Feature",
  "properties": {
    "addr:full":"PO Box 10232 Gouger St Adelaide SA 5000",
    "addr:postcode":"5000",
    "addr:street":"Gouger St",
    "iso:country":"AU",
    "sg:address":"PO Box 10232 Gouger St",
    "sg:city":"Adelaide",
    "sg:classifiers":[
        {
            "category":"Retail",
            "subcategory":"Auto Rental",
            "type":"Services"
        }
    ],
    "sg:phone":"+61 438 327 051",
    "sg:postcode":"5000",
    "sg:province":"SA",
    "sg:tags":[
        "chauffeur",
        "car",
        "hire",
        "driven",
        "limousine"
    ],
    "wof:name":"Chauffeured Vehicle Association Of SA Inc.",
    "wof:placetype":"venue"
},
  "geometry": {"coordinates":[138.59999084500001,-34.9301147461],"type":"Point"}
}