{
  "type": "Feature",
  "properties": {
    "iso:country":"AU",
    "sg:address":"1 Bennet St",
    "sg:city":"Dandenong",
    "sg:classifiers":[
        {
            "category":"Wholesale",
            "subcategory":"Home Furnishings",
            "type":"Manufacturing & Wholesale Goods"
        }
    ],
    "sg:phone":"+61 3 9791 1388",
    "sg:postcode":"3175",
    "sg:province":"VIC",
    "sg:tags":[
        "tile",
        "wholesaler",
        "mfrs",
        "carpet"
    ],
    "wof:name":"Tuftmaster Carpets Pty Ltd",
    "wof:placetype":"venue"
},
  "geometry": {"coordinates":[145.20019531200001,-37.9841880798],"type":"Point"}
}