{
  "type": "Feature",
  "properties": {
    "addr:full":"Cnr Church & Mead Sts Glen Innes NSW 2370",
    "addr:postcode":"2370",
    "addr:street":"Sts",
    "iso:country":"AU",
    "sg:address":"Cnr Church & Mead Sts",
    "sg:city":"Glen Innes",
    "sg:classifiers":[
        {
            "category":"Retail",
            "subcategory":"Car Wash",
            "type":"Services"
        }
    ],
    "sg:phone":"+61 2 6732 2196",
    "sg:postcode":"2370",
    "sg:province":"NSW",
    "sg:tags":[
        "merchant",
        "oil",
        "refiner"
    ],
    "wof:name":"Caltex",
    "wof:placetype":"venue"
},
  "geometry": {"coordinates":[151.733352661,-29.7349205017],"type":"Point"}
}