{
  "type": "Feature",
  "properties": {
    "addr:full":"PO Box 5451 Alexandra Hills QLD 4161",
    "addr:postcode":"4161",
    "iso:country":"AU",
    "sg:address":"PO Box 5451",
    "sg:city":"Alexandra Hills",
    "sg:classifiers":[
        {
            "category":"Health Services",
            "subcategory":"Doctor",
            "type":"Services"
        }
    ],
    "sg:phone":"+61 7 3822 7700",
    "sg:postcode":"4161",
    "sg:province":"QLD",
    "sg:tags":[
        "occupational",
        "safety"
    ],
    "wof:name":"Verbena Systems",
    "wof:placetype":"venue"
},
  "geometry": {"coordinates":[153.22071838400001,-27.5468406677],"type":"Point"}
}