{
  "type": "Feature",
  "properties": {
    "addr:full":"Templar & Rankin Sts Forbes NSW 2871",
    "addr:postcode":"2871",
    "iso:country":"AU",
    "sg:address":"Templar & Rankin Sts",
    "sg:city":"Forbes",
    "sg:classifiers":[
        {
            "category":"Shopping",
            "subcategory":"Clothing, Apparel, & Fashions",
            "type":"Retail Goods"
        }
    ],
    "sg:phone":"+61 417 209 133",
    "sg:postcode":"2871",
    "sg:province":"NSW",
    "sg:tags":[
        "menswear"
    ],
    "wof:name":"Davis Clothing Company",
    "wof:placetype":"venue"
},
  "geometry": {"coordinates":[148.00711100000001,-33.383919],"type":"Point"}
}