{
  "type": "Feature",
  "properties": {
    "iso:country":"AU",
    "sg:address":"1484 Brisbane Valley Hwy",
    "sg:city":"Fernvale",
    "sg:classifiers":[
        {
            "category":"Real Estate",
            "subcategory":"Real Estate Agent",
            "type":"Services"
        }
    ],
    "sg:phone":"+61 7 5427 0050",
    "sg:postcode":"4306",
    "sg:province":"QLD",
    "wof:name":"Harcourts Fernvale",
    "wof:placetype":"venue"
},
  "geometry": {"coordinates":[152.6509552,-27.4538288116],"type":"Point"}
}