{
  "type": "Feature",
  "properties": {
    "iso:country":"AU",
    "sg:address":"273 Princes Hwy",
    "sg:city":"Bulli",
    "sg:classifiers":[
        {
            "category":"Retail",
            "subcategory":"Auto Repair",
            "type":"Services"
        }
    ],
    "sg:phone":"+61 2 4284 3167",
    "sg:postcode":"2516",
    "sg:province":"NSW",
    "sg:tags":[
        "repairer",
        "motor",
        "engineer"
    ],
    "wof:name":"Bulli Mechanical Repairs",
    "wof:placetype":"venue"
},
  "geometry": {"coordinates":[150.91262800000001,-34.33604],"type":"Point"}
}