{
  "type": "Feature",
  "properties": {
    "addr:full":"Ecclestone Rd Riverside TAS 7250",
    "addr:postcode":"7250",
    "addr:street":"Ecclestone Rd",
    "iso:country":"AU",
    "sg:address":"Ecclestone Rd",
    "sg:city":"Riverside",
    "sg:classifiers":[
        {
            "category":"Farming",
            "subcategory":"Livestock Farm",
            "type":"Manufacturing & Wholesale Goods"
        }
    ],
    "sg:phone":"+61 3 6327 3094",
    "sg:postcode":"7250",
    "sg:province":"TAS",
    "sg:tags":[
        "agistment"
    ],
    "wof:name":"Michele's School Of Riding",
    "wof:placetype":"venue"
},
  "geometry": {"coordinates":[147.09962463400001,-41.4119491577],"type":"Point"}
}