{
  "type": "Feature",
  "properties": {
    "addr:full":"102 Henkel St Brunswick VIC 3056",
    "addr:housenumber":"102",
    "addr:postcode":"3056",
    "addr:street":"Henkel St",
    "iso:country":"AU",
    "sg:address":"102 Henkel St",
    "sg:city":"Brunswick",
    "sg:classifiers":[
        {
            "category":"Manufacturing",
            "subcategory":"Metals",
            "type":"Manufacturing & Wholesale Goods"
        }
    ],
    "sg:phone":"+61 3 9380 4944",
    "sg:postcode":"3056",
    "sg:province":"VIC",
    "sg:tags":[
        "sheet",
        "worker"
    ],
    "wof:name":"A Grade Sheet Metal",
    "wof:placetype":"venue"
},
  "geometry": {"coordinates":[144.95463562,-37.7650184631],"type":"Point"}
}