{
  "type": "Feature",
  "properties": {
    "addr:full":"Lot 6/ Graphite Rd Glenoran WA 6258",
    "addr:housenumber":"6 /",
    "addr:postcode":"6258",
    "addr:street":"Graphite Rd",
    "iso:country":"AU",
    "sg:address":"Lot 6/ Graphite Rd",
    "sg:city":"Glenoran",
    "sg:classifiers":[
        {
            "category":"Cafe",
            "type":"Food & Drink"
        }
    ],
    "sg:phone":"+61 8 9772 1283",
    "sg:postcode":"6258",
    "sg:province":"WA",
    "wof:name":"Graphiti Cafe",
    "wof:placetype":"venue"
},
  "geometry": {"coordinates":[116.14491271999999,-34.2346191406],"type":"Point"}
}