{
  "type": "Feature",
  "properties": {
    "addr:full":"1434- 1458 Sydney Rd Campbellfield VIC 3061",
    "addr:housenumber":"1434 1458",
    "addr:postcode":"3061",
    "addr:street":"Sydney Rd",
    "iso:country":"AU",
    "sg:address":"1434- 1458 Sydney Rd",
    "sg:city":"Campbellfield",
    "sg:classifiers":[
        {
            "category":"Retail",
            "subcategory":"Auto Repair",
            "type":"Services"
        }
    ],
    "sg:phone":"+61 3 9359 6885",
    "sg:postcode":"3061",
    "sg:province":"VIC",
    "sg:tags":[
        "repairer",
        "motor",
        "engineer"
    ],
    "wof:name":"Kmart Tyre & Auto Service",
    "wof:placetype":"venue"
},
  "geometry": {"coordinates":[144.958251953,-37.6883049011],"type":"Point"}
}