{
  "type": "Feature",
  "properties": {
    "addr:full":"27 Morton Rd Lalor Park NSW 2147",
    "addr:housenumber":"27",
    "addr:postcode":"2147",
    "addr:street":"Morton Rd",
    "iso:country":"AU",
    "sg:address":"27 Morton Rd",
    "sg:city":"Lalor Park",
    "sg:classifiers":[
        {
            "category":"Professional",
            "subcategory":"Engineering",
            "type":"Services"
        }
    ],
    "sg:phone":"+61 2 9671 7620",
    "sg:postcode":"2147",
    "sg:province":"NSW",
    "sg:tags":[
        "electronic",
        "engineer"
    ],
    "wof:name":"Cedar Electronics",
    "wof:placetype":"venue"
},
  "geometry": {"coordinates":[150.928756714,-33.7650184631],"type":"Point"}
}