{
  "type": "Feature",
  "properties": {
    "addr:full":"672 Kingston Rd Loganlea QLD 4131",
    "addr:housenumber":"672",
    "addr:postcode":"4131",
    "addr:street":"Kingston Rd",
    "iso:country":"AU",
    "sg:address":"672 Kingston Rd",
    "sg:city":"Loganlea",
    "sg:classifiers":[
        {
            "category":"Manufacturing",
            "subcategory":"Motor Vehicles & Parts",
            "type":"Manufacturing & Wholesale Goods"
        }
    ],
    "sg:phone":"+61 7 3427 3655",
    "sg:postcode":"4131",
    "sg:province":"QLD",
    "sg:tags":[
        "engine",
        "equipment",
        "reconditioning"
    ],
    "wof:name":"S.A.E. Specialised Automotive Equipment",
    "wof:placetype":"venue"
},
  "geometry": {"coordinates":[153.122650147,-27.670173645],"type":"Point"}
}