{
  "type": "Feature",
  "properties": {
    "iso:country":"AU",
    "sg:address":"1 Nangor St",
    "sg:city":"Waramanga",
    "sg:classifiers":[
        {
            "category":"Health Services",
            "subcategory":"Health Practitioner",
            "type":"Services"
        }
    ],
    "sg:phone":"+61 2 6288 3562",
    "sg:postcode":"2611",
    "sg:province":"ACT",
    "sg:tags":[
        "alternative"
    ],
    "wof:name":"Natural Elements",
    "wof:placetype":"venue"
},
  "geometry": {"coordinates":[149.06658935600001,-35.3569717407],"type":"Point"}
}