{
  "type": "Feature",
  "properties": {
    "addr:full":"5 Carson Drv Bunya QLD 4055",
    "addr:housenumber":"5",
    "addr:postcode":"4055",
    "addr:street":"Carson Drv",
    "iso:country":"AU",
    "sg:address":"5 Carson Drv",
    "sg:city":"Bunya",
    "sg:classifiers":[
        {
            "category":"Building & Trades",
            "subcategory":"Construction",
            "type":"Services"
        }
    ],
    "sg:phone":"+61 418 727 601",
    "sg:postcode":"4055",
    "sg:province":"QLD",
    "sg:tags":[
        "contractor"
    ],
    "wof:name":"Brian Smith Residential",
    "wof:placetype":"venue"
},
  "geometry": {"coordinates":[152.928634644,-27.3775119781],"type":"Point"}
}