{
  "type": "Feature",
  "properties": {
    "iso:country":"AU",
    "sg:address":"Cnr Kingsway & Willarong Rd",
    "sg:city":"Caringbah",
    "sg:classifiers":[
        {
            "category":"Real Estate",
            "subcategory":"Real Estate Agent",
            "type":"Services"
        }
    ],
    "sg:phone":"+61 2 9525 7333",
    "sg:postcode":"2229",
    "sg:province":"NSW",
    "wof:name":"Century 21 Realty One",
    "wof:placetype":"venue"
},
  "geometry": {"coordinates":[151.122283936,-34.0424156189],"type":"Point"}
}