{
  "type": "Feature",
  "properties": {
    "addr:full":"352 St Kilda St Brighton VIC 3186",
    "addr:housenumber":"352",
    "addr:postcode":"3186",
    "addr:street":"St Kilda St",
    "iso:country":"AU",
    "sg:address":"352 St Kilda St",
    "sg:city":"Brighton",
    "sg:classifiers":[
        {
            "category":"Health Services",
            "subcategory":"Doctor",
            "type":"Services"
        }
    ],
    "sg:phone":"+61 3 9596 5395",
    "sg:postcode":"3186",
    "sg:province":"VIC",
    "sg:tags":[
        "medical",
        "practitioner"
    ],
    "wof:name":"Chamberlain John N",
    "wof:placetype":"venue"
},
  "geometry": {"coordinates":[144.98912048299999,-37.9009628296],"type":"Point"}
}