{
  "type": "Feature",
  "properties": {
    "addr:full":"340 Kent St Sydney NSW 2000",
    "addr:housenumber":"340",
    "addr:postcode":"2000",
    "addr:street":"Kent St",
    "iso:country":"AU",
    "sg:address":"340 Kent St",
    "sg:city":"Sydney",
    "sg:classifiers":[
        {
            "category":"Restaurant",
            "type":"Food & Drink"
        }
    ],
    "sg:phone":"+61 2 9290 1145",
    "sg:postcode":"2000",
    "sg:province":"NSW",
    "wof:name":"Certo Restaurant",
    "wof:placetype":"venue"
},
  "geometry": {"coordinates":[151.20484924300001,-33.8695411682],"type":"Point"}
}