{
  "type": "Feature",
  "properties": {
    "addr:full":"4th Floor, 175 Collins St Melbourne VIC 3000",
    "addr:housenumber":"175",
    "addr:postcode":"3000",
    "addr:street":"Collins St",
    "iso:country":"AU",
    "sg:address":"4th Floor, 175 Collins St",
    "sg:city":"Melbourne",
    "sg:classifiers":[
        {
            "category":"Health Services",
            "subcategory":"Dentist",
            "type":"Services"
        }
    ],
    "sg:phone":"+61 3 9650 2909",
    "sg:postcode":"3000",
    "sg:province":"VIC",
    "wof:name":"Steel Alistair Dr",
    "wof:placetype":"venue"
},
  "geometry": {"coordinates":[144.968063355,-37.8151626587],"type":"Point"}
}