{
  "type": "Feature",
  "properties": {
    "addr:full":"3 Lionel Donovan Drv Noosaville QLD 4566",
    "addr:housenumber":"3",
    "addr:postcode":"4566",
    "addr:street":"Lionel Donovan Drv",
    "iso:country":"AU",
    "sg:address":"3 Lionel Donovan Drv",
    "sg:city":"Noosaville",
    "sg:classifiers":[
        {
            "category":"Autos & Motor Vehicles",
            "subcategory":"Automobile Sales",
            "type":"Retail Goods"
        }
    ],
    "sg:phone":"+61 7 5430 6100",
    "sg:postcode":"4566",
    "sg:province":"QLD",
    "sg:tags":[
        "car",
        "new"
    ],
    "wof:name":"Sunshine Coast Mazda",
    "wof:placetype":"venue"
},
  "geometry": {"coordinates":[153.04698181099999,-26.4107551575],"type":"Point"}
}