{
  "type": "Feature",
  "properties": {
    "addr:full":"225 Melville Rd Pascoe Vale South VIC 3044",
    "addr:housenumber":"225",
    "addr:postcode":"3044",
    "addr:street":"Melville Rd",
    "iso:country":"AU",
    "sg:address":"225 Melville Rd",
    "sg:city":"Pascoe Vale South",
    "sg:classifiers":[
        {
            "category":"Personal",
            "subcategory":"Beauty Salon",
            "type":"Services"
        }
    ],
    "sg:phone":"+61 3 9354 1011",
    "sg:postcode":"3044",
    "sg:province":"VIC",
    "wof:name":"Zoe's Beauty Works",
    "wof:placetype":"venue"
},
  "geometry": {"coordinates":[144.94537353499999,-37.7395172119],"type":"Point"}
}