{
  "type": "Feature",
  "properties": {
    "iso:country":"AU",
    "sg:address":"337 Maroondah Hwy",
    "sg:city":"Croydon",
    "sg:classifiers":[
        {
            "category":"Insurance",
            "subcategory":"Insurance Agent",
            "type":"Services"
        }
    ],
    "sg:phone":"+61 3 9723 6011",
    "sg:postcode":"3136",
    "sg:province":"VIC",
    "sg:tags":[
        "broker"
    ],
    "wof:name":"Alan Quantrell Insurance Brokers Pty Ltd",
    "wof:placetype":"venue"
},
  "geometry": {"coordinates":[145.291625977,-37.7786026001],"type":"Point"}
}