{
  "type": "Feature",
  "properties": {
    "iso:country":"AU",
    "sg:address":"Auburn St",
    "sg:city":"Coniston",
    "sg:classifiers":[
        {
            "category":"Education",
            "subcategory":"School",
            "type":"Public Place"
        }
    ],
    "sg:phone":"+61 2 4229 1117",
    "sg:postcode":"2500",
    "sg:province":"NSW",
    "sg:tags":[
        "state",
        "-",
        "nsw"
    ],
    "wof:name":"Coniston Primary School",
    "wof:placetype":"venue"
},
  "geometry": {"coordinates":[150.887451,-34.436363],"type":"Point"}
}