{
  "type": "Feature",
  "properties": {
    "addr:full":"Collins Pde Hackham SA 5163",
    "addr:postcode":"5163",
    "addr:street":"Collins",
    "iso:country":"AU",
    "sg:address":"Collins Pde",
    "sg:city":"Hackham",
    "sg:classifiers":[
        {
            "category":"Education",
            "subcategory":"School",
            "type":"Public Place"
        }
    ],
    "sg:phone":"+61 8 8382 3824",
    "sg:postcode":"5163",
    "sg:province":"SA",
    "sg:tags":[
        "state",
        "except",
        "nsw"
    ],
    "wof:name":"Hackham East School",
    "wof:placetype":"venue"
},
  "geometry": {"coordinates":[138.53260803200001,-35.1433410645],"type":"Point"}
}