{
  "type": "Feature",
  "properties": {
    "addr:full":"2 Point St Pyrmont NSW 2009",
    "addr:housenumber":"2",
    "addr:postcode":"2009",
    "addr:street":"Point St",
    "iso:country":"AU",
    "sg:address":"2 Point St",
    "sg:city":"Pyrmont",
    "sg:classifiers":[
        {
            "category":"Autos & Motor Vehicles",
            "subcategory":"Automobile Sales",
            "type":"Retail Goods"
        }
    ],
    "sg:phone":"+61 418 371 777",
    "sg:postcode":"2009",
    "sg:province":"NSW",
    "sg:tags":[
        "car",
        "used"
    ],
    "wof:name":"Macquarie Motors",
    "wof:placetype":"venue"
},
  "geometry": {"coordinates":[151.19281005900001,-33.864276886],"type":"Point"}
}