{
  "type": "Feature",
  "properties": {
    "addr:full":"13 Brisbane Rd Bundamba QLD 4304",
    "addr:housenumber":"13",
    "addr:postcode":"4304",
    "addr:street":"Brisbane Rd",
    "iso:country":"AU",
    "sg:address":"13 Brisbane Rd",
    "sg:city":"Bundamba",
    "sg:classifiers":[
        {
            "category":"Autos & Motor Vehicles",
            "subcategory":"Automobile Sales",
            "type":"Retail Goods"
        }
    ],
    "sg:phone":"+61 7 3282 2722",
    "sg:postcode":"4304",
    "sg:province":"QLD",
    "sg:tags":[
        "car",
        "used"
    ],
    "wof:name":"Boettcher Ian Used Cars",
    "wof:placetype":"venue"
},
  "geometry": {"coordinates":[152.80877685600001,-27.6096038818],"type":"Point"}
}