{
  "type": "Feature",
  "properties": {
    "addr:full":"14 King St Murwillumbah NSW 2484",
    "addr:housenumber":"14",
    "addr:postcode":"2484",
    "addr:street":"King St",
    "iso:country":"AU",
    "sg:address":"14 King St",
    "sg:city":"Murwillumbah",
    "sg:classifiers":[
        {
            "category":"Health Services",
            "subcategory":"Doctor",
            "type":"Services"
        }
    ],
    "sg:phone":"+61 2 6672 4244",
    "sg:postcode":"2484",
    "sg:province":"NSW",
    "sg:tags":[
        "medical",
        "practitioner"
    ],
    "wof:name":"Moran John",
    "wof:placetype":"venue"
},
  "geometry": {"coordinates":[153.396194458,-28.3289299011],"type":"Point"}
}