{
  "type": "Feature",
  "properties": {
    "iso:country":"AU",
    "sg:address":"473- 477 Princes Hwy",
    "sg:city":"Narre Warren",
    "sg:classifiers":[
        {
            "category":"Autos & Motor Vehicles",
            "subcategory":"Fuel & Gas Station",
            "type":"Retail Goods"
        }
    ],
    "sg:phone":"+61 3 9704 7327",
    "sg:postcode":"3805",
    "sg:province":"VIC",
    "wof:name":"Shell Narre Warren Self Service",
    "wof:placetype":"venue"
},
  "geometry": {"coordinates":[145.30587800000001,-38.026077],"type":"Point"}
}