{
  "type": "Feature",
  "properties": {
    "addr:full":"286 Chesterville Rd Moorabbin VIC 3189",
    "addr:housenumber":"286",
    "addr:postcode":"3189",
    "addr:street":"Chesterville Rd",
    "iso:country":"AU",
    "sg:address":"286 Chesterville Rd",
    "sg:city":"Moorabbin",
    "sg:classifiers":[
        {
            "category":"Wholesale",
            "subcategory":"Office Equipment",
            "type":"Manufacturing & Wholesale Goods"
        }
    ],
    "sg:phone":"+61 3 9553 2522",
    "sg:postcode":"3189",
    "sg:province":"VIC",
    "sg:tags":[
        "packaging",
        "consultant"
    ],
    "wof:name":"A Finishing Services",
    "wof:placetype":"venue"
},
  "geometry": {"coordinates":[145.06097412099999,-37.9389801025],"type":"Point"}
}