{
  "type": "Feature",
  "properties": {
    "addr:full":"Fact. 3, 151-159 Princes Hwy Hallam VIC 3803",
    "addr:housenumber":"3",
    "addr:postcode":"151-159;3803",
    "addr:street":"Fact.;Princes Hwy",
    "iso:country":"AU",
    "sg:address":"Fact. 3, 151-159 Princes Hwy",
    "sg:city":"Hallam",
    "sg:classifiers":[
        {
            "category":"Sports & Exercise",
            "subcategory":"Gym",
            "type":"Entertainment"
        }
    ],
    "sg:phone":"+61 3 8786 3111",
    "sg:postcode":"3803",
    "sg:province":"VIC",
    "sg:tags":[
        "health",
        "fitness"
    ],
    "wof:name":"Nitro Gym",
    "wof:placetype":"venue"
},
  "geometry": {"coordinates":[145.26008605999999,-38.0051002502],"type":"Point"}
}