{
  "type": "Feature",
  "properties": {
    "addr:full":"795 Hunter St Newcastle West NSW 2302",
    "addr:housenumber":"795",
    "addr:postcode":"2302",
    "addr:street":"Hunter St",
    "iso:country":"AU",
    "sg:address":"795 Hunter St",
    "sg:city":"Newcastle West",
    "sg:classifiers":[
        {
            "category":"Wholesale",
            "subcategory":"Construction Materials",
            "type":"Manufacturing & Wholesale Goods"
        }
    ],
    "sg:phone":"+61 2 4961 1904",
    "sg:postcode":"2302",
    "sg:province":"NSW",
    "sg:tags":[
        "wholesaler",
        "lighting",
        "mfrs",
        "accessory"
    ],
    "wof:name":"Eurolight",
    "wof:placetype":"venue"
},
  "geometry": {"coordinates":[151.75730899999999,-32.924606],"type":"Point"}
}