{
  "type": "Feature",
  "properties": {
    "addr:full":"14 Historic Drv Highbury SA 5089",
    "addr:housenumber":"14",
    "addr:postcode":"5089",
    "addr:street":"Historic Drv",
    "iso:country":"AU",
    "sg:address":"14 Historic Drv",
    "sg:city":"Highbury",
    "sg:classifiers":[
        {
            "category":"Real Estate",
            "subcategory":"Real Estate Agent",
            "type":"Services"
        }
    ],
    "sg:phone":"+61 438 805 253",
    "sg:postcode":"5089",
    "sg:province":"SA",
    "sg:tags":[
        "export"
    ],
    "wof:name":"SAxcess",
    "wof:placetype":"venue"
},
  "geometry": {"coordinates":[138.704544067,-34.8551063538],"type":"Point"}
}