{
  "type": "Feature",
  "properties": {
    "addr:full":"Unit 2 31- 33 Kylie Pl Cheltenham VIC 3192",
    "addr:housenumber":"31 33",
    "addr:postcode":"3192",
    "addr:street":"Kylie Pl",
    "iso:country":"AU",
    "sg:address":"Unit 2 31- 33 Kylie Pl",
    "sg:city":"Cheltenham",
    "sg:classifiers":[
        {
            "category":"Professional",
            "subcategory":"Engineering",
            "type":"Services"
        }
    ],
    "sg:phone":"+61 3 9555 0488",
    "sg:postcode":"3192",
    "sg:province":"VIC",
    "sg:tags":[
        "engineer"
    ],
    "wof:name":"McCallum General Engineering",
    "wof:placetype":"venue"
},
  "geometry": {"coordinates":[145.06329345699999,-37.9509506226],"type":"Point"}
}