{
  "type": "Feature",
  "properties": {
    "addr:full":"541 Gympie Rd Kedron QLD 4031",
    "addr:housenumber":"541",
    "addr:postcode":"4031",
    "addr:street":"Gympie Rd",
    "iso:country":"AU",
    "sg:address":"541 Gympie Rd",
    "sg:city":"Kedron",
    "sg:classifiers":[
        {
            "category":"Retail",
            "subcategory":"Auto Repair",
            "type":"Services"
        }
    ],
    "sg:phone":"+61 7 3359 4877",
    "sg:postcode":"4031",
    "sg:province":"QLD",
    "sg:tags":[
        "repairer",
        "motor",
        "engineer"
    ],
    "wof:name":"Midas",
    "wof:placetype":"venue"
},
  "geometry": {"coordinates":[153.03132600000001,-27.396013],"type":"Point"}
}