{
  "type": "Feature",
  "properties": {
    "addr:full":"2 Hague Pl Oakhurst NSW 2761",
    "addr:housenumber":"2",
    "addr:postcode":"2761",
    "addr:street":"Hague Pl",
    "iso:country":"AU",
    "sg:address":"2 Hague Pl",
    "sg:city":"Oakhurst",
    "sg:classifiers":[
        {
            "category":"Professional",
            "subcategory":"Detective & Security Services",
            "type":"Services"
        }
    ],
    "sg:phone":"+61 2 9675 7499",
    "sg:postcode":"2761",
    "sg:province":"NSW",
    "sg:tags":[
        "investigator"
    ],
    "wof:name":"Fairfield Investigations",
    "wof:placetype":"venue"
},
  "geometry": {"coordinates":[150.842636,-33.738213],"type":"Point"}
}