{
  "type": "Feature",
  "properties": {
    "addr:full":"184 Halcrows Rd Glenorie NSW 2157",
    "addr:housenumber":"184",
    "addr:postcode":"2157",
    "addr:street":"Halcrows Rd",
    "iso:country":"AU",
    "sg:address":"184 Halcrows Rd",
    "sg:city":"Glenorie",
    "sg:classifiers":[
        {
            "category":"Professional",
            "type":"Services"
        }
    ],
    "sg:phone":"+61 2 9652 0582",
    "sg:postcode":"2157",
    "sg:province":"NSW",
    "sg:tags":[
        "shop",
        "fitting"
    ],
    "wof:name":"Norms Carpentry & Joinery P/L",
    "wof:placetype":"venue"
},
  "geometry": {"coordinates":[150.959884644,-33.5721168518],"type":"Point"}
}