{
  "type": "Feature",
  "properties": {
    "iso:country":"AU",
    "sg:address":"73 High St",
    "sg:city":"Russell Island",
    "sg:classifiers":[
        {
            "category":"Autos & Motor Vehicles",
            "subcategory":"Fuel & Gas Station",
            "type":"Retail Goods"
        }
    ],
    "sg:phone":"+61 7 3409 1269",
    "sg:postcode":"4184",
    "sg:province":"QLD",
    "wof:name":"Russell Island Service Station",
    "wof:placetype":"venue"
},
  "geometry": {"coordinates":[153.38087463400001,-27.6524181366],"type":"Point"}
}