{
  "type": "Feature",
  "properties": {
    "addr:full":"279 Burnside Rd Stapylton QLD 4207",
    "addr:housenumber":"279",
    "addr:postcode":"4207",
    "addr:street":"Burnside Rd",
    "iso:country":"AU",
    "sg:address":"279 Burnside Rd",
    "sg:city":"Stapylton",
    "sg:phone":"+61 7 3382 6011",
    "sg:postcode":"4207",
    "sg:province":"QLD",
    "wof:name":"Superior Precast",
    "wof:placetype":"venue"
},
  "geometry": {"coordinates":[153.24122619600001,-27.7546596527],"type":"Point"}
}