{
  "type": "Feature",
  "properties": {
    "addr:full":"Unit 7, 1451- 1563 Albany Hwy Cannington WA 6107",
    "addr:housenumber":"1451 1563",
    "addr:postcode":"6107",
    "addr:street":"Albany Hwy",
    "iso:country":"AU",
    "sg:address":"Unit 7, 1451- 1563 Albany Hwy",
    "sg:city":"Cannington",
    "sg:classifiers":[
        {
            "category":"Home & Garden",
            "subcategory":"Carpets & Floor Coverings",
            "type":"Retail Goods"
        }
    ],
    "sg:phone":"+61 8 9451 2011",
    "sg:postcode":"6107",
    "sg:province":"WA",
    "sg:tags":[
        "tile",
        "wall"
    ],
    "wof:name":"Tiles &#039;N&#039; Tiles",
    "wof:placetype":"venue"
},
  "geometry": {"coordinates":[115.92656707800001,-32.011932373],"type":"Point"}
}