{
  "type": "Feature",
  "properties": {
    "addr:full":"25-31 Gaine Rd Dandenong South VIC 3164",
    "addr:housenumber":"25-31",
    "addr:postcode":"3164",
    "addr:street":"Gaine Rd",
    "iso:country":"AU",
    "sg:address":"25-31 Gaine Rd",
    "sg:city":"Dandenong South",
    "sg:classifiers":[
        {
            "category":"Wholesale",
            "subcategory":"Hardware",
            "type":"Manufacturing & Wholesale Goods"
        }
    ],
    "sg:phone":"+61 3 8795 5300",
    "sg:postcode":"3164",
    "sg:province":"VIC",
    "wof:name":"Smart Home Products Pty Ltd",
    "wof:placetype":"venue"
},
  "geometry": {"coordinates":[145.24093627900001,-38.0326499939],"type":"Point"}
}