{
  "type": "Feature",
  "properties": {
    "iso:country":"AU",
    "sg:address":"Lot 1722, Witte St",
    "sg:city":"Winnellie",
    "sg:classifiers":[
        {
            "category":"Retail",
            "subcategory":"Auto Repair",
            "type":"Services"
        }
    ],
    "sg:phone":"+61 8 8984 3208",
    "sg:postcode":"0820",
    "sg:province":"NT",
    "sg:tags":[
        "engine",
        "reconditioning"
    ],
    "wof:name":"Repco",
    "wof:placetype":"venue"
},
  "geometry": {"coordinates":[130.88746643100001,-12.4276237488],"type":"Point"}
}