{
  "type": "Feature",
  "properties": {
    "addr:full":"4 Harris Pl West Hoxton NSW 2171",
    "addr:housenumber":"4",
    "addr:postcode":"2171",
    "addr:street":"Harris Pl West",
    "iso:country":"AU",
    "sg:address":"4 Harris Pl",
    "sg:city":"West Hoxton",
    "sg:classifiers":[
        {
            "category":"Retail",
            "subcategory":"Laundry & Dry Cleaning",
            "type":"Services"
        }
    ],
    "sg:phone":"+61 2 9825 8547",
    "sg:postcode":"2171",
    "sg:province":"NSW",
    "sg:tags":[
        "cloth",
        "supply"
    ],
    "wof:name":"O'Brien J L & P Pty Ltd",
    "wof:placetype":"venue"
},
  "geometry": {"coordinates":[150.83889770499999,-33.9370346069],"type":"Point"}
}