{
  "type": "Feature",
  "properties": {
    "iso:country":"AU",
    "sg:address":"147a Penshurst St",
    "sg:city":"Penshurst",
    "sg:classifiers":[
        {
            "category":"Professional",
            "subcategory":"Management & Consulting",
            "type":"Services"
        }
    ],
    "sg:phone":"+61 2 9586 2400",
    "sg:postcode":"2222",
    "sg:province":"NSW",
    "sg:tags":[
        "consultant"
    ],
    "wof:name":"Graydon Davison Consulting Pty Ltd",
    "wof:placetype":"venue"
},
  "geometry": {"coordinates":[151.07977294899999,-33.9557685852],"type":"Point"}
}