{
  "type": "Feature",
  "properties": {
    "addr:full":"46 Fernbrook Pl Castle Hill NSW 2154",
    "addr:housenumber":"46",
    "addr:postcode":"2154",
    "addr:street":"Fernbrook Pl",
    "iso:country":"AU",
    "sg:address":"46 Fernbrook Pl",
    "sg:city":"Castle Hill",
    "sg:classifiers":[
        {
            "category":"Wholesale",
            "subcategory":"Home Furnishings",
            "type":"Manufacturing & Wholesale Goods"
        }
    ],
    "sg:phone":"+61 2 9894 4040",
    "sg:postcode":"2154",
    "sg:province":"NSW",
    "sg:tags":[
        "wholesaler",
        "mfrs",
        "manchester"
    ],
    "wof:name":"Linen Warehouse",
    "wof:placetype":"venue"
},
  "geometry": {"coordinates":[151.02365112300001,-33.7118721008],"type":"Point"}
}