{
  "type": "Feature",
  "properties": {
    "addr:full":"55 Gallipoli Drv Greenmount WA 6056",
    "addr:housenumber":"55",
    "addr:postcode":"6056",
    "addr:street":"Gallipoli Drv",
    "iso:country":"AU",
    "sg:address":"55 Gallipoli Drv",
    "sg:city":"Greenmount",
    "sg:classifiers":[
        {
            "category":"Home & Garden",
            "subcategory":"Household Appliances",
            "type":"Retail Goods"
        }
    ],
    "sg:phone":"+61 8 9255 1323",
    "sg:postcode":"6056",
    "sg:province":"WA",
    "sg:tags":[
        "equipment",
        "gas"
    ],
    "wof:name":"Ron's Gas Fitting Service",
    "wof:placetype":"venue"
},
  "geometry": {"coordinates":[116.043571472,-31.893951416],"type":"Point"}
}