{
  "type": "Feature",
  "properties": {
    "addr:full":"Shop 103 A Fountain Gate Shopping Centre Narre Warren VIC 3805",
    "addr:housenumber":"103 a",
    "addr:postcode":"3805",
    "addr:street":"Fountain Gate Shopping",
    "iso:country":"AU",
    "sg:address":"Shop 103 A Fountain Gate Shopping Centre",
    "sg:city":"Narre Warren",
    "sg:classifiers":[
        {
            "category":"Personal",
            "subcategory":"Beauty Salon",
            "type":"Services"
        }
    ],
    "sg:phone":"+61 3 8790 5999",
    "sg:postcode":"3805",
    "sg:province":"VIC",
    "sg:tags":[
        "hairdresser"
    ],
    "wof:name":"Six Chairs",
    "wof:placetype":"venue"
},
  "geometry": {"coordinates":[145.302155,-38.014935],"type":"Point"}
}