{
  "type": "Feature",
  "properties": {
    "addr:full":"18 Seaside Pde North Shore VIC 3214",
    "addr:housenumber":"18",
    "addr:postcode":"3214",
    "addr:street":"Seaside Pde",
    "iso:country":"AU",
    "sg:address":"18 Seaside Pde",
    "sg:city":"North Shore",
    "sg:classifiers":[
        {
            "category":"Farming",
            "subcategory":"Farm & Veterinary Services",
            "type":"Manufacturing & Wholesale Goods"
        }
    ],
    "sg:phone":"+61 3 5277 2000",
    "sg:postcode":"3214",
    "sg:province":"VIC",
    "sg:tags":[
        "poultry",
        "processing",
        "supply"
    ],
    "wof:name":"Geelong Poultry",
    "wof:placetype":"venue"
},
  "geometry": {"coordinates":[144.36846923799999,-38.0984077454],"type":"Point"}
}