{
  "type": "Feature",
  "properties": {
    "iso:country":"AU",
    "sg:address":"59 Waratah Ave",
    "sg:city":"Dalkeith",
    "sg:classifiers":[
        {
            "category":"Personal",
            "subcategory":"Beauty Salon",
            "type":"Services"
        }
    ],
    "sg:phone":"+61 8 9386 2621",
    "sg:postcode":"6009",
    "sg:province":"WA",
    "wof:name":"Liany Cosmetics & Beauty Clinic",
    "wof:placetype":"venue"
},
  "geometry": {"coordinates":[115.80130800000001,-31.994665],"type":"Point"}
}