{
  "type": "Feature",
  "properties": {
    "addr:full":"Unit 2 79 Bulla Rd Essendon North VIC 3041",
    "addr:housenumber":"79",
    "addr:postcode":"3041",
    "addr:street":"Bulla Rd",
    "iso:country":"AU",
    "sg:address":"Unit 2 79 Bulla Rd",
    "sg:city":"Essendon North",
    "sg:classifiers":[
        {
            "category":"Professional",
            "subcategory":"Computer Services",
            "type":"Services"
        }
    ],
    "sg:phone":"+61 3 9379 6555",
    "sg:postcode":"3041",
    "sg:province":"VIC",
    "sg:tags":[
        "consultant",
        "system"
    ],
    "wof:name":"E J Computer Services Pty Ltd",
    "wof:placetype":"venue"
},
  "geometry": {"coordinates":[144.90541076700001,-37.7375564575],"type":"Point"}
}