{
  "type": "Feature",
  "properties": {
    "addr:full":"964 Glenhuntly Rd Caulfield South VIC 3162",
    "addr:housenumber":"964",
    "addr:postcode":"3162",
    "addr:street":"Glenhuntly Rd",
    "iso:country":"AU",
    "sg:address":"964 Glenhuntly Rd",
    "sg:city":"Caulfield South",
    "sg:classifiers":[
        {
            "category":"Building & Trades",
            "subcategory":"Construction",
            "type":"Services"
        }
    ],
    "sg:phone":"+61 3 9571 9043",
    "sg:postcode":"3162",
    "sg:province":"VIC",
    "sg:tags":[
        "joiner",
        "carpenter"
    ],
    "wof:name":"David Barbuto",
    "wof:placetype":"venue"
},
  "geometry": {"coordinates":[145.030960083,-37.8881225586],"type":"Point"}
}