{
  "type": "Feature",
  "properties": {
    "iso:country":"AU",
    "sg:address":"Roberts Crt",
    "sg:city":"Drouin",
    "sg:classifiers":[
        {
            "category":"Autos & Motor Vehicles",
            "subcategory":"Auto Supplies",
            "type":"Retail Goods"
        }
    ],
    "sg:phone":"+61 3 5625 2304",
    "sg:postcode":"3818",
    "sg:province":"VIC",
    "sg:tags":[
        "battery",
        "automotive"
    ],
    "wof:name":"Burdon Auto Electrics",
    "wof:placetype":"venue"
},
  "geometry": {"coordinates":[145.842285,-38.120373],"type":"Point"}
}