{
  "type": "Feature",
  "properties": {
    "addr:full":"92 Binney St Euroa VIC 3666",
    "addr:housenumber":"92",
    "addr:postcode":"3666",
    "addr:street":"Binney St",
    "iso:country":"AU",
    "sg:address":"92 Binney St",
    "sg:city":"Euroa",
    "sg:classifiers":[
        {
            "category":"Professional",
            "subcategory":"Accounting & Tax Preparation",
            "type":"Services"
        }
    ],
    "sg:phone":"+61 3 5795 2214",
    "sg:postcode":"3666",
    "sg:province":"VIC",
    "sg:tags":[
        "accountant",
        "auditor"
    ],
    "wof:name":"J Quattrocchi & Associates",
    "wof:placetype":"venue"
},
  "geometry": {"coordinates":[145.571075439,-36.7515563965],"type":"Point"}
}