{
  "type": "Feature",
  "properties": {
    "addr:full":"3 Merino St Toowoomba QLD 4350",
    "addr:housenumber":"3",
    "addr:postcode":"4350",
    "addr:street":"Merino St",
    "iso:country":"AU",
    "sg:address":"3 Merino St",
    "sg:city":"Toowoomba",
    "sg:classifiers":[
        {
            "category":"Building & Trades",
            "subcategory":"Cleaning & Sanitation",
            "type":"Services"
        }
    ],
    "sg:phone":"+61 417 146 066",
    "sg:postcode":"4350",
    "sg:province":"QLD",
    "sg:tags":[
        "industrial",
        "commercial",
        "contractor"
    ],
    "wof:name":"Gee -Jay Cleaning",
    "wof:placetype":"venue"
},
  "geometry": {"coordinates":[151.93202199999999,-27.583237],"type":"Point"}
}