{
  "type": "Feature",
  "properties": {
    "addr:full":"149 English St Manunda QLD 4870",
    "addr:housenumber":"149",
    "addr:postcode":"4870",
    "addr:street":"English St",
    "iso:country":"AU",
    "sg:address":"149 English St",
    "sg:city":"Manunda",
    "sg:classifiers":[
        {
            "category":"Shopping",
            "subcategory":"Computers & Home Electronics",
            "type":"Retail Goods"
        }
    ],
    "sg:phone":"+61 7 4032 4533",
    "sg:postcode":"4870",
    "sg:province":"QLD",
    "sg:tags":[
        "equipment",
        "multimedia"
    ],
    "wof:name":"Visual Obsession",
    "wof:placetype":"venue"
},
  "geometry": {"coordinates":[145.746856689,-16.9163246155],"type":"Point"}
}