{
  "type": "Feature",
  "properties": {
    "addr:full":"10 Glassford St Geraldton WA 6530",
    "addr:housenumber":"10",
    "addr:postcode":"6530",
    "addr:street":"Glassford St",
    "iso:country":"AU",
    "sg:address":"10 Glassford St",
    "sg:city":"Geraldton",
    "sg:classifiers":[
        {
            "category":"Utilities",
            "subcategory":"Electric",
            "type":"Services"
        }
    ],
    "sg:phone":"+61 417 963 954",
    "sg:postcode":"6530",
    "sg:province":"WA",
    "sg:tags":[
        "electrical",
        "contractor"
    ],
    "wof:name":"Right Phase Electrical",
    "wof:placetype":"venue"
},
  "geometry": {"coordinates":[114.62590789799999,-28.6684436798],"type":"Point"}
}