{
  "type": "Feature",
  "properties": {
    "addr:full":"Bunya Hwy Kingaroy QLD 4610",
    "addr:postcode":"4610",
    "addr:street":"Bunya Hwy",
    "iso:country":"AU",
    "sg:address":"Bunya Hwy",
    "sg:city":"Kingaroy",
    "sg:classifiers":[
        {
            "category":"Professional",
            "subcategory":"Business Services",
            "type":"Services"
        }
    ],
    "sg:phone":"+61 7 4162 1922",
    "sg:postcode":"4610",
    "sg:province":"QLD",
    "sg:tags":[
        "livestock",
        "transport"
    ],
    "wof:name":"Porters Transport Pty Ltd",
    "wof:placetype":"venue"
},
  "geometry": {"coordinates":[151.82705688499999,-26.5516757965],"type":"Point"}
}