{
  "type": "Feature",
  "properties": {
    "addr:full":"152 Enterprise Drv Beaudesert QLD 4285",
    "addr:housenumber":"152",
    "addr:postcode":"4285",
    "addr:street":"Enterprise Drv",
    "iso:country":"AU",
    "sg:address":"152 Enterprise Drv",
    "sg:city":"Beaudesert",
    "sg:classifiers":[
        {
            "category":"Wholesale",
            "subcategory":"Farm Supplies",
            "type":"Manufacturing & Wholesale Goods"
        }
    ],
    "sg:phone":"+61 7 5541 4555",
    "sg:postcode":"4285",
    "sg:province":"QLD",
    "sg:tags":[
        "feed",
        "supplement",
        "stock"
    ],
    "wof:name":"Rabar Pty Ltd",
    "wof:placetype":"venue"
},
  "geometry": {"coordinates":[152.99212600000001,-27.967649],"type":"Point"}
}