{
  "type": "Feature",
  "properties": {
    "iso:country":"AU",
    "sg:address":"21 Steps Cnr Cavanagh & Knuckey St",
    "sg:city":"Darwin",
    "sg:classifiers":[
        {
            "category":"Health Services",
            "subcategory":"Health Practitioner",
            "type":"Services"
        }
    ],
    "sg:phone":"+61 8 8941 4462",
    "sg:postcode":"0800",
    "sg:province":"NT",
    "sg:tags":[
        "alternative"
    ],
    "wof:name":"Johanna Aura Reading & Healing",
    "wof:placetype":"venue"
},
  "geometry": {"coordinates":[130.84231567399999,-12.4622688293],"type":"Point"}
}