{
  "type": "Feature",
  "properties": {
    "iso:country":"AU",
    "sg:address":"115 Victor Rd",
    "sg:city":"Bentleigh East",
    "sg:classifiers":[
        {
            "category":"Professional",
            "subcategory":"Art Services",
            "type":"Services"
        }
    ],
    "sg:phone":"+61 3 9570 7506",
    "sg:postcode":"3165",
    "sg:province":"VIC",
    "sg:tags":[
        "decorator",
        "painter"
    ],
    "wof:name":"Johansen Painting Service",
    "wof:placetype":"venue"
},
  "geometry": {"coordinates":[145.07928466800001,-37.9238243103],"type":"Point"}
}