{
  "type": "Feature",
  "properties": {
    "iso:country":"AU",
    "sg:address":"449 Snowy Mountains Hwy",
    "sg:city":"Tumut",
    "sg:classifiers":[
        {
            "category":"Building & Trades",
            "subcategory":"Construction",
            "type":"Services"
        }
    ],
    "sg:phone":"+61 2 6947 4477",
    "sg:postcode":"2720",
    "sg:province":"NSW",
    "sg:tags":[
        "fencing",
        "contractor"
    ],
    "wof:name":"Peter Smith Contractors",
    "wof:placetype":"venue"
},
  "geometry": {"coordinates":[148.189255,-35.30949],"type":"Point"}
}