{
  "type": "Feature",
  "properties": {
    "addr:full":"Unit 2, 4/ 5 Frances Parkes Cl Wyoming NSW 2250",
    "addr:housenumber":"4 / 5",
    "addr:postcode":"2250",
    "addr:street":"Parkes Cl",
    "iso:country":"AU",
    "sg:address":"Unit 2, 4/ 5 Frances Parkes Cl",
    "sg:city":"Wyoming",
    "sg:classifiers":[
        {
            "category":"Retail",
            "subcategory":"Auto Repair",
            "type":"Services"
        }
    ],
    "sg:phone":"+61 2 4329 6077",
    "sg:postcode":"2250",
    "sg:province":"NSW",
    "sg:tags":[
        "repairer",
        "motor",
        "engineer"
    ],
    "wof:name":"Greeny's Garage",
    "wof:placetype":"venue"
},
  "geometry": {"coordinates":[151.34925842300001,-33.4094390869],"type":"Point"}
}