{
  "type": "Feature",
  "properties": {
    "iso:country":"AU",
    "sg:address":"Cnr Jindalee & Belah Rds",
    "sg:city":"Port Macquarie",
    "sg:classifiers":[
        {
            "category":"Manufacturing",
            "subcategory":"Tools & Machinery",
            "type":"Manufacturing & Wholesale Goods"
        }
    ],
    "sg:phone":"+61 2 6581 1400",
    "sg:postcode":"2444",
    "sg:province":"NSW",
    "sg:tags":[
        "earth",
        "excavating",
        "moving",
        "equipment"
    ],
    "wof:name":"Kennards Earthmoving Equipment Hire",
    "wof:placetype":"venue"
},
  "geometry": {"coordinates":[152.88545199999999,-31.447729],"type":"Point"}
}