{
  "type": "Feature",
  "properties": {
    "addr:full":"12 Sherwood Crt Lindisfarne TAS 7015",
    "addr:housenumber":"12",
    "addr:postcode":"7015",
    "addr:street":"Sherwood Crt",
    "iso:country":"AU",
    "sg:address":"12 Sherwood Crt",
    "sg:city":"Lindisfarne",
    "sg:classifiers":[
        {
            "category":"Recreation",
            "subcategory":"Amusement Park",
            "type":"Entertainment"
        }
    ],
    "sg:phone":"+61 3 6243 6699",
    "sg:postcode":"7015",
    "sg:province":"TAS",
    "wof:name":"Tommy Choo Choo Train",
    "wof:placetype":"venue"
},
  "geometry": {"coordinates":[147.367584228,-42.844959259],"type":"Point"}
}