{
  "type": "Feature",
  "properties": {
    "iso:country":"AU",
    "sg:address":"18 Ocean St",
    "sg:city":"Bondi",
    "sg:classifiers":[
        {
            "category":"Travel",
            "subcategory":"Hostel",
            "type":"Entertainment"
        }
    ],
    "sg:phone":"+61 2 9389 3660",
    "sg:postcode":"2026",
    "sg:province":"NSW",
    "sg:tags":[
        "home"
    ],
    "wof:name":"Benevolent Society",
    "wof:placetype":"venue"
},
  "geometry": {"coordinates":[151.2631073,-33.8913497925],"type":"Point"}
}