{
  "type": "Feature",
  "properties": {
    "addr:full":"133 Watton St Werribee VIC 3030",
    "addr:housenumber":"133",
    "addr:postcode":"3030",
    "addr:street":"Watton St",
    "iso:country":"AU",
    "sg:address":"133 Watton St",
    "sg:city":"Werribee",
    "sg:classifiers":[
        {
            "category":"Food & Beverages",
            "subcategory":"Bakery",
            "type":"Retail Goods"
        }
    ],
    "sg:phone":"+61 3 9731 1191",
    "sg:postcode":"3030",
    "sg:province":"VIC",
    "sg:tags":[
        "baker"
    ],
    "wof:name":"La Baguette Bakery",
    "wof:placetype":"venue"
},
  "geometry": {"coordinates":[144.65922499999999,-37.902618],"type":"Point"}
}