{
  "type": "Feature",
  "properties": {
    "addr:full":"25 Short St Kangaroo Flat VIC 3555",
    "addr:housenumber":"25",
    "addr:postcode":"3555",
    "addr:street":"Short St",
    "iso:country":"AU",
    "sg:address":"25 Short St",
    "sg:city":"Kangaroo Flat",
    "sg:classifiers":[
        {
            "category":"Professional",
            "type":"Services"
        }
    ],
    "sg:phone":"+61 3 5447 0880",
    "sg:postcode":"3555",
    "sg:province":"VIC",
    "sg:tags":[
        "spray",
        "painting"
    ],
    "wof:name":"Central Auto Paints",
    "wof:placetype":"venue"
},
  "geometry": {"coordinates":[144.248901367,-36.7926063538],"type":"Point"}
}