{
  "type": "Feature",
  "properties": {
    "iso:country":"AU",
    "sg:address":"Lionel St",
    "sg:city":"Kalgoorlie",
    "sg:classifiers":[
        {
            "category":"Education",
            "subcategory":"School",
            "type":"Public Place"
        }
    ],
    "sg:phone":"+61 8 9021 2348",
    "sg:postcode":"6430",
    "sg:province":"WA",
    "sg:tags":[
        "state",
        "except",
        "nsw"
    ],
    "wof:name":"South Kalgoorlie Primary School",
    "wof:placetype":"venue"
},
  "geometry": {"coordinates":[121.46489715600001,-30.7515163422],"type":"Point"}
}