{
  "type": "Feature",
  "properties": {
    "iso:country":"AU",
    "sg:address":"102 Wallace St",
    "sg:city":"Braidwood",
    "sg:classifiers":[
        {
            "category":"Cafe",
            "type":"Food & Drink"
        }
    ],
    "sg:phone":"+61 2 4842 2077",
    "sg:postcode":"2622",
    "sg:province":"NSW",
    "wof:name":"Cafe Altenburg",
    "wof:placetype":"venue"
},
  "geometry": {"coordinates":[149.801147461,-35.4371566772],"type":"Point"}
}