{
  "type": "Feature",
  "properties": {
    "iso:country":"AU",
    "sg:address":"11 Cracknell Rd",
    "sg:city":"Annerley",
    "sg:classifiers":[
        {
            "category":"Personal",
            "subcategory":"Beauty Salon",
            "type":"Services"
        }
    ],
    "sg:phone":"+61 7 3848 4736",
    "sg:postcode":"4103",
    "sg:province":"QLD",
    "wof:name":"Wellington Point Natural Therapy And Beauty Clinic",
    "wof:placetype":"venue"
},
  "geometry": {"coordinates":[153.02976989699999,-27.5185146332],"type":"Point"}
}