{
  "type": "Feature",
  "properties": {
    "addr:full":"86 Boundary St West End QLD 4101",
    "addr:housenumber":"86",
    "addr:postcode":"4101",
    "addr:street":"Boundary St",
    "iso:country":"AU",
    "sg:address":"86 Boundary St",
    "sg:city":"West End",
    "sg:classifiers":[
        {
            "category":"Professional",
            "subcategory":"Art Services",
            "type":"Services"
        }
    ],
    "sg:phone":"+61 7 3255 1855",
    "sg:postcode":"4101",
    "sg:province":"QLD",
    "sg:tags":[
        "graphic",
        "designer"
    ],
    "wof:name":"Maximum-Output",
    "wof:placetype":"venue"
},
  "geometry": {"coordinates":[153.01272582999999,-27.4781093597],"type":"Point"}
}