{
  "type": "Feature",
  "properties": {
    "addr:full":"69 Hamilton Pl Mt Waverley VIC 3149",
    "addr:housenumber":"69",
    "addr:postcode":"3149",
    "addr:street":"Hamilton Pl Mt",
    "iso:country":"AU",
    "sg:address":"69 Hamilton Pl",
    "sg:city":"Mt Waverley",
    "sg:classifiers":[
        {
            "category":"Personal",
            "subcategory":"Beauty Salon",
            "type":"Services"
        }
    ],
    "sg:phone":"+61 3 9807 3005",
    "sg:postcode":"3149",
    "sg:province":"VIC",
    "sg:tags":[
        "hairdresser"
    ],
    "wof:name":"Josmic Hair & Beauty Centre",
    "wof:placetype":"venue"
},
  "geometry": {"coordinates":[145.128295898,-37.877117157],"type":"Point"}
}