{
  "type": "Feature",
  "properties": {
    "addr:full":"2 Embling St Wanniassa ACT 2903",
    "addr:housenumber":"2",
    "addr:postcode":"2903",
    "addr:street":"Embling St",
    "iso:country":"AU",
    "sg:address":"2 Embling St",
    "sg:city":"Wanniassa",
    "sg:classifiers":[
        {
            "category":"Organizations",
            "subcategory":"Professional Association",
            "type":"Services"
        }
    ],
    "sg:phone":"+61 2 6231 6926",
    "sg:postcode":"2903",
    "sg:province":"ACT",
    "sg:tags":[
        "web",
        "internet"
    ],
    "wof:name":"E-Marketing Services Pty Ltd",
    "wof:placetype":"venue"
},
  "geometry": {"coordinates":[149.095214844,-35.3974266052],"type":"Point"}
}