{
  "type": "Feature",
  "properties": {
    "iso:country":"AU",
    "sg:address":"2 Hamilton Ave",
    "sg:city":"Blackburn",
    "sg:classifiers":[
        {
            "category":"Health Services",
            "subcategory":"Health Practitioner",
            "type":"Services"
        }
    ],
    "sg:phone":"+61 3 9894 1826",
    "sg:postcode":"3130",
    "sg:province":"VIC",
    "sg:tags":[
        "alternative"
    ],
    "wof:name":"Estelle Abbas",
    "wof:placetype":"venue"
},
  "geometry": {"coordinates":[145.14302063,-37.8131713867],"type":"Point"}
}