{
  "type": "Feature",
  "properties": {
    "addr:full":"524 Stuart Hwy Winnellie NT 0820",
    "addr:housenumber":"524",
    "addr:postcode":"nt 0820",
    "addr:street":"Stuart Hwy",
    "iso:country":"AU",
    "sg:address":"524 Stuart Hwy",
    "sg:city":"Winnellie",
    "sg:classifiers":[
        {
            "category":"Autos & Motor Vehicles",
            "subcategory":"Motorcycle Sales",
            "type":"Retail Goods"
        }
    ],
    "sg:phone":"+61 8 8984 3277",
    "sg:postcode":"0820",
    "sg:province":"NT",
    "sg:tags":[
        "outboard"
    ],
    "wof:name":"Boatland Winnellie",
    "wof:placetype":"venue"
},
  "geometry": {"coordinates":[130.89160156200001,-12.4257993698],"type":"Point"}
}