{
  "type": "Feature",
  "properties": {
    "iso:country":"AU",
    "sg:address":"8 Grant St",
    "sg:city":"Duncraig",
    "sg:classifiers":[
        {
            "category":"Food & Beverages",
            "subcategory":"Specialty",
            "type":"Retail Goods"
        }
    ],
    "sg:phone":"+61 8 9447 1486",
    "sg:postcode":"6023",
    "sg:province":"WA",
    "sg:tags":[
        "product",
        "health"
    ],
    "wof:name":"Juice Plus",
    "wof:placetype":"venue"
},
  "geometry": {"coordinates":[115.768531799,-31.8294258118],"type":"Point"}
}