{
  "type": "Feature",
  "properties": {
    "iso:country":"AU",
    "sg:address":"140 Marrickville Rd",
    "sg:city":"Marrickville",
    "sg:classifiers":[
        {
            "category":"Home & Garden",
            "subcategory":"Carpets & Floor Coverings",
            "type":"Retail Goods"
        }
    ],
    "sg:phone":"+61 2 9565 2644",
    "sg:postcode":"2204",
    "sg:province":"NSW",
    "sg:tags":[
        "wood"
    ],
    "sg:website":"http://www.blackwattle.com.au",
    "wof:name":"Blackwattle Hardwood Floors",
    "wof:placetype":"venue"
},
  "geometry": {"coordinates":[151.16154499999999,-33.913239],"type":"Point"}
}