{
  "type": "Feature",
  "properties": {
    "addr:full":"17 Fishermans Rd Maroochydore QLD 4558",
    "addr:housenumber":"17",
    "addr:postcode":"4558",
    "addr:street":"Fishermans Rd",
    "iso:country":"AU",
    "sg:address":"17 Fishermans Rd",
    "sg:city":"Maroochydore",
    "sg:classifiers":[
        {
            "category":"Autos & Motor Vehicles",
            "subcategory":"Auto Supplies",
            "type":"Retail Goods"
        }
    ],
    "sg:phone":"+61 7 5443 1036",
    "sg:postcode":"4558",
    "sg:province":"QLD",
    "sg:tags":[
        "accessory"
    ],
    "wof:name":"Suncoast Caravan Service",
    "wof:placetype":"venue"
},
  "geometry": {"coordinates":[153.05467224099999,-26.6549186707],"type":"Point"}
}