{
  "type": "Feature",
  "properties": {
    "addr:full":"OPSM Shp 42 Erina Fair Terrigal Drv Erina NSW 2250",
    "addr:housenumber":"42",
    "addr:postcode":"2250",
    "addr:street":"Erina Fair Terrigal Drv",
    "iso:country":"AU",
    "sg:address":"OPSM Shp 42 Erina Fair Terrigal Drv",
    "sg:city":"Erina",
    "sg:classifiers":[
        {
            "category":"Health Services",
            "subcategory":"Optometrist",
            "type":"Services"
        }
    ],
    "sg:phone":"+61 2 4365 1025",
    "sg:postcode":"2250",
    "sg:province":"NSW",
    "wof:name":"Geoff & Melanie Herron Optometrists",
    "wof:placetype":"venue"
},
  "geometry": {"coordinates":[151.39523315400001,-33.4345855713],"type":"Point"}
}