{
  "type": "Feature",
  "properties": {
    "iso:country":"AU",
    "sg:address":"215 Charters Towers Rd",
    "sg:city":"Hyde Park",
    "sg:classifiers":[
        {
            "category":"Shopping",
            "type":"Retail Goods"
        }
    ],
    "sg:phone":"+61 7 4728 8825",
    "sg:postcode":"4812",
    "sg:province":"QLD",
    "sg:tags":[
        "new age",
        "product"
    ],
    "wof:name":"Callista's Cauldron",
    "wof:placetype":"venue"
},
  "geometry": {"coordinates":[146.79754600000001,-19.284658],"type":"Point"}
}