{
  "type": "Feature",
  "properties": {
    "iso:country":"AU",
    "sg:address":"Unit 2, 4 Severn St St",
    "sg:city":"Marys",
    "sg:classifiers":[
        {
            "category":"Manufacturing",
            "subcategory":"Glass & Minerals",
            "type":"Manufacturing & Wholesale Goods"
        }
    ],
    "sg:phone":"+61 2 9833 8699",
    "sg:postcode":"2760",
    "sg:province":"NSW",
    "sg:tags":[
        "repair",
        "fibreglass",
        "product"
    ],
    "wof:name":"Carys",
    "wof:placetype":"venue"
},
  "geometry": {"coordinates":[150.77491760300001,-33.7450027466],"type":"Point"}
}