{
  "type": "Feature",
  "properties": {
    "iso:country":"AU",
    "sg:address":"465 Olive St",
    "sg:city":"Albury",
    "sg:classifiers":[
        {
            "category":"Real Estate",
            "subcategory":"Real Estate Agent",
            "type":"Services"
        }
    ],
    "sg:phone":"+61 417 230 955",
    "sg:postcode":"2640",
    "sg:province":"NSW",
    "wof:name":"Michael Pieterse",
    "wof:placetype":"venue"
},
  "geometry": {"coordinates":[146.917678833,-36.0828285217],"type":"Point"}
}