{
  "type": "Feature",
  "properties": {
    "iso:country":"AU",
    "sg:address":"U2/ 73 Railway Parade North",
    "sg:city":"Glen Waverley",
    "sg:classifiers":[
        {
            "category":"Real Estate",
            "subcategory":"Real Estate Agent",
            "type":"Services"
        }
    ],
    "sg:phone":"+61 3 9886 1211",
    "sg:postcode":"3150",
    "sg:province":"VIC",
    "wof:name":"JRW Property International",
    "wof:placetype":"venue"
},
  "geometry": {"coordinates":[145.165252686,-37.8797073364],"type":"Point"}
}