{
  "type": "Feature",
  "properties": {
    "addr:full":"50 Murray St Tanunda SA 5352",
    "addr:housenumber":"50",
    "addr:postcode":"5352",
    "addr:street":"Murray St",
    "iso:country":"AU",
    "sg:address":"50 Murray St",
    "sg:city":"Tanunda",
    "sg:classifiers":[
        {
            "category":"Insurance",
            "subcategory":"Hazard Insurance",
            "type":"Services"
        }
    ],
    "sg:phone":"+61 8 8563 2123",
    "sg:postcode":"5352",
    "sg:province":"SA",
    "sg:tags":[
        "motor",
        "vehicle"
    ],
    "wof:name":"RAA Insurance Ltd",
    "wof:placetype":"venue"
},
  "geometry": {"coordinates":[138.96095275900001,-34.5232810974],"type":"Point"}
}