{
  "type": "Feature",
  "properties": {
    "addr:full":"314 Vahland Ave Willetton WA 6155",
    "addr:housenumber":"314",
    "addr:postcode":"6155",
    "addr:street":"Vahland Ave",
    "iso:country":"AU",
    "sg:address":"314 Vahland Ave",
    "sg:city":"Willetton",
    "sg:classifiers":[
        {
            "category":"Health Services",
            "subcategory":"Doctor",
            "type":"Services"
        }
    ],
    "sg:phone":"+61 8 9354 4899",
    "sg:postcode":"6155",
    "sg:province":"WA",
    "sg:tags":[
        "medical",
        "practitioner"
    ],
    "wof:name":"Vahland Avenue Medical Centre",
    "wof:placetype":"venue"
},
  "geometry": {"coordinates":[115.88929,-32.056316],"type":"Point"}
}