{
  "type": "Feature",
  "properties": {
    "addr:full":"87 Macquarie Rd Cardiff NSW 2285",
    "addr:housenumber":"87",
    "addr:postcode":"2285",
    "addr:street":"Macquarie Rd",
    "iso:country":"AU",
    "sg:address":"87 Macquarie Rd",
    "sg:city":"Cardiff",
    "sg:classifiers":[
        {
            "category":"Building & Trades",
            "subcategory":"Cleaning & Sanitation",
            "type":"Services"
        }
    ],
    "sg:phone":"+61 417 446 701",
    "sg:postcode":"2285",
    "sg:province":"NSW",
    "sg:tags":[
        "industrial",
        "commercial",
        "contractor"
    ],
    "wof:name":"Embridge Cleaning Services",
    "wof:placetype":"venue"
},
  "geometry": {"coordinates":[151.657180786,-32.9456176758],"type":"Point"}
}