{
  "type": "Feature",
  "properties": {
    "addr:full":"9/ 160 Bolsover St Rockhampton QLD 4700",
    "addr:housenumber":"/ 160",
    "addr:postcode":"4700",
    "addr:street":"Bolsover St",
    "iso:country":"AU",
    "sg:address":"9/ 160 Bolsover St",
    "sg:city":"Rockhampton",
    "sg:classifiers":[
        {
            "category":"Professional",
            "type":"Services"
        }
    ],
    "sg:phone":"+61 7 4922 5693",
    "sg:postcode":"4700",
    "sg:province":"QLD",
    "sg:tags":[
        "valuer"
    ],
    "wof:name":"M.D. Sheehan Valuer",
    "wof:placetype":"venue"
},
  "geometry": {"coordinates":[150.51661682100001,-23.384929657],"type":"Point"}
}