{
  "type": "Feature",
  "properties": {
    "addr:full":"255 Military Rd West Lakes Shore SA 5020",
    "addr:housenumber":"255",
    "addr:postcode":"5020",
    "addr:street":"Military Rd",
    "iso:country":"AU",
    "sg:address":"255 Military Rd",
    "sg:city":"West Lakes Shore",
    "sg:classifiers":[
        {
            "category":"Retail",
            "subcategory":"Laundry & Dry Cleaning",
            "type":"Services"
        }
    ],
    "sg:phone":"+61 8 8242 0117",
    "sg:postcode":"5020",
    "sg:province":"SA",
    "wof:name":"Seaside Laundry",
    "wof:placetype":"venue"
},
  "geometry": {"coordinates":[138.47962951700001,-34.8656768799],"type":"Point"}
}