{
  "type": "Feature",
  "properties": {
    "addr:full":"Winter Rd Girgarre VIC 3624",
    "addr:postcode":"3624",
    "addr:street":"Winter Rd",
    "iso:country":"AU",
    "sg:address":"Winter Rd",
    "sg:city":"Girgarre",
    "sg:classifiers":[
        {
            "category":"Autos & Motor Vehicles",
            "subcategory":"Auto Supplies",
            "type":"Retail Goods"
        }
    ],
    "sg:phone":"+61 3 5854 6317",
    "sg:postcode":"3624",
    "sg:province":"VIC",
    "sg:tags":[
        "pipe",
        "bending",
        "tube",
        "machinery"
    ],
    "wof:name":"F & S Exhaust Tools",
    "wof:placetype":"venue"
},
  "geometry": {"coordinates":[144.95985412600001,-36.3986167908],"type":"Point"}
}