{
  "type": "Feature",
  "properties": {
    "addr:full":"Shop 4, 27- 31 Lindfield Ave Lindfield NSW 2070",
    "addr:housenumber":"shop;27 31",
    "addr:postcode":"2070",
    "addr:street":"Lindfield Ave",
    "iso:country":"AU",
    "sg:address":"Shop 4, 27- 31 Lindfield Ave",
    "sg:city":"Lindfield",
    "sg:classifiers":[
        {
            "category":"Retail",
            "subcategory":"Repair Shop",
            "type":"Services"
        }
    ],
    "sg:phone":"+61 2 9880 9328",
    "sg:postcode":"2070",
    "sg:province":"NSW",
    "sg:tags":[
        "mending",
        "clothing",
        "alteration"
    ],
    "wof:name":"Jenny's Clothing Alterations",
    "wof:placetype":"venue"
},
  "geometry": {"coordinates":[151.16914367699999,-33.7745170593],"type":"Point"}
}