{
  "type": "Feature",
  "properties": {
    "iso:country":"AU",
    "sg:address":"183 Regent St",
    "sg:city":"Redfern",
    "sg:classifiers":[
        {
            "category":"Arts & Performance",
            "subcategory":"Art Gallery",
            "type":"Entertainment"
        }
    ],
    "sg:phone":"+61 2 9319 3340",
    "sg:postcode":"2016",
    "sg:province":"NSW",
    "wof:name":"Legge Gallery",
    "wof:placetype":"venue"
},
  "geometry": {"coordinates":[151.19953918499999,-33.8946151733],"type":"Point"}
}