{
  "type": "Feature",
  "properties": {
    "addr:full":"2 Wellington St Sans Souci NSW 2219",
    "addr:housenumber":"2",
    "addr:postcode":"2219",
    "addr:street":"Wellington St",
    "iso:country":"AU",
    "sg:address":"2 Wellington St",
    "sg:city":"Sans Souci",
    "sg:classifiers":[
        {
            "category":"Autos & Motor Vehicles",
            "subcategory":"Boat Sales",
            "type":"Retail Goods"
        }
    ],
    "sg:phone":"+61 414 542 548",
    "sg:postcode":"2219",
    "sg:province":"NSW",
    "sg:tags":[
        "builder",
        "yacht",
        "repairer"
    ],
    "wof:name":"A Wright 1 Game & Sport Fishing Charters",
    "wof:placetype":"venue"
},
  "geometry": {"coordinates":[151.12617499999999,-34.000999],"type":"Point"}
}