{
  "type": "Feature",
  "properties": {
    "iso:country":"AU",
    "sg:address":"Ste 3, Lvl 3, 190 Edwards St",
    "sg:city":"Brisbane",
    "sg:classifiers":[
        {
            "category":"Real Estate",
            "subcategory":"Real Estate Services",
            "type":"Services"
        }
    ],
    "sg:phone":"+61 7 3210 6833",
    "sg:postcode":"4001",
    "sg:province":"QLD",
    "sg:tags":[
        "valuer"
    ],
    "wof:name":"Preston Rowe Paterson Qld Pty Ltd",
    "wof:placetype":"venue"
},
  "geometry": {"coordinates":[152.78367614699999,-27.6475582123],"type":"Point"}
}