{
  "type": "Feature",
  "properties": {
    "addr:full":"1353 Mt Rd Burnie TAS 7320",
    "addr:housenumber":"1353",
    "addr:postcode":"7320",
    "addr:street":"Mt Rd",
    "iso:country":"AU",
    "sg:address":"1353 Mt Rd",
    "sg:city":"Burnie",
    "sg:classifiers":[
        {
            "category":"Train Station",
            "subcategory":"Rail",
            "type":"Transportation"
        }
    ],
    "sg:phone":"+61 3 6435 7855",
    "sg:postcode":"7320",
    "sg:province":"TAS",
    "sg:tags":[
        "goat",
        "farmer"
    ],
    "wof:name":"Orronger Heights Goat Stud",
    "wof:placetype":"venue"
},
  "geometry": {"coordinates":[145.896378,-41.081131],"type":"Point"}
}