{
  "type": "Feature",
  "properties": {
    "iso:country":"AU",
    "sg:address":"19 Hotham St",
    "sg:city":"Cranbourne",
    "sg:classifiers":[
        {
            "category":"Fast Food",
            "type":"Food & Drink"
        }
    ],
    "sg:phone":"+61 3 5995 2115",
    "sg:postcode":"3977",
    "sg:province":"VIC",
    "sg:tags":[
        "away",
        "take"
    ],
    "wof:name":"Hotham Street Fish & Chips",
    "wof:placetype":"venue"
},
  "geometry": {"coordinates":[145.28953552199999,-38.10206604],"type":"Point"}
}