{
  "type": "Feature",
  "properties": {
    "iso:country":"AU",
    "sg:address":"10 Ezio Crt",
    "sg:city":"Diamond Creek",
    "sg:classifiers":[
        {
            "category":"Building & Trades",
            "subcategory":"Construction",
            "type":"Services"
        }
    ],
    "sg:phone":"+61 3 9438 1555",
    "sg:postcode":"3089",
    "sg:province":"VIC",
    "sg:tags":[
        "contractor"
    ],
    "wof:name":"Ferrari Building Maintenance Pty Ltd",
    "wof:placetype":"venue"
},
  "geometry": {"coordinates":[145.130157,-37.682007],"type":"Point"}
}