{
  "type": "Feature",
  "properties": {
    "addr:full":"21 South St Ipswich QLD 4305",
    "addr:housenumber":"21",
    "addr:postcode":"4305",
    "addr:street":"South St",
    "iso:country":"AU",
    "sg:address":"21 South St",
    "sg:city":"Ipswich",
    "sg:classifiers":[
        {
            "category":"Retail",
            "subcategory":"Repair Shop",
            "type":"Services"
        }
    ],
    "sg:phone":"+61 7 3812 4055",
    "sg:postcode":"4305",
    "sg:province":"QLD",
    "sg:tags":[
        "mending",
        "clothing",
        "alteration"
    ],
    "wof:name":"Sew Happy",
    "wof:placetype":"venue"
},
  "geometry": {"coordinates":[152.76255798299999,-27.6168632507],"type":"Point"}
}