{
  "type": "Feature",
  "properties": {
    "addr:full":"17 Harker St Burwood VIC 3125",
    "addr:housenumber":"17",
    "addr:postcode":"3125",
    "addr:street":"Harker St",
    "iso:country":"AU",
    "sg:address":"17 Harker St",
    "sg:city":"Burwood",
    "sg:classifiers":[
        {
            "category":"Manufacturing",
            "subcategory":"Jewelry",
            "type":"Manufacturing & Wholesale Goods"
        }
    ],
    "sg:phone":"+61 3 9808 5233",
    "sg:postcode":"3125",
    "sg:province":"VIC",
    "sg:tags":[
        "mfrg",
        "jeweller"
    ],
    "wof:name":"Apecs Investment Castings Pty Ltd",
    "wof:placetype":"venue"
},
  "geometry": {"coordinates":[145.104934692,-37.8534889221],"type":"Point"}
}