{
  "type": "Feature",
  "properties": {
    "iso:country":"AU",
    "sg:address":"44 Clerke St",
    "sg:city":"Old Bar",
    "sg:classifiers":[
        {
            "category":"Manufacturing",
            "subcategory":"Food",
            "type":"Manufacturing & Wholesale Goods"
        }
    ],
    "sg:phone":"+61 2 6553 3002",
    "sg:postcode":"2430",
    "sg:province":"NSW",
    "sg:tags":[
        "function",
        "catering"
    ],
    "wof:name":"Rosie's Catering",
    "wof:placetype":"venue"
},
  "geometry": {"coordinates":[152.58213799999999,-31.973021],"type":"Point"}
}