{
  "type": "Feature",
  "properties": {
    "addr:full":"59 Five Islands Rd Port Kembla NSW 2505",
    "addr:housenumber":"59",
    "addr:postcode":"2505",
    "addr:street":"Five Islands Rd",
    "iso:country":"AU",
    "sg:address":"59 Five Islands Rd",
    "sg:city":"Port Kembla",
    "sg:classifiers":[
        {
            "category":"Manufacturing",
            "subcategory":"Metals",
            "type":"Manufacturing & Wholesale Goods"
        }
    ],
    "sg:phone":"+61 2 4274 2798",
    "sg:postcode":"2505",
    "sg:province":"NSW",
    "sg:tags":[
        "sheet",
        "worker"
    ],
    "wof:name":"O&#039;Briens Sheetmetal & Insulations",
    "wof:placetype":"venue"
},
  "geometry": {"coordinates":[150.89576721200001,-34.4783058167],"type":"Point"}
}