{
  "type": "Feature",
  "properties": {
    "iso:country":"AU",
    "sg:address":"8 Heather St",
    "sg:city":"Heatherbrae",
    "sg:classifiers":[
        {
            "category":"Autos & Motor Vehicles",
            "subcategory":"Automobile Sales",
            "type":"Retail Goods"
        }
    ],
    "sg:phone":"+61 2 4987 6180",
    "sg:postcode":"2324",
    "sg:province":"NSW",
    "sg:tags":[
        "car",
        "used"
    ],
    "wof:name":"Dave Evans Motors",
    "wof:placetype":"venue"
},
  "geometry": {"coordinates":[151.73338317899999,-32.7861251831],"type":"Point"}
}