{
  "type": "Feature",
  "properties": {
    "addr:full":"330 Sydney Rd Balgowlah NSW 2093",
    "addr:housenumber":"330",
    "addr:postcode":"2093",
    "addr:street":"Sydney Rd",
    "iso:country":"AU",
    "sg:address":"330 Sydney Rd",
    "sg:city":"Balgowlah",
    "sg:classifiers":[
        {
            "category":"Personal",
            "subcategory":"Beauty Salon",
            "type":"Services"
        }
    ],
    "sg:phone":"+61 2 9948 8383",
    "sg:postcode":"2093",
    "sg:province":"NSW",
    "sg:tags":[
        "hairdresser"
    ],
    "wof:name":"Halo Hair Studio",
    "wof:placetype":"venue"
},
  "geometry": {"coordinates":[151.26419067399999,-33.7941131592],"type":"Point"}
}