{
  "type": "Feature",
  "properties": {
    "addr:full":"293 River St Ballina NSW 2478",
    "addr:housenumber":"293",
    "addr:postcode":"2478",
    "addr:street":"River St",
    "iso:country":"AU",
    "sg:address":"293 River St",
    "sg:city":"Ballina",
    "sg:classifiers":[
        {
            "category":"Wholesale",
            "subcategory":"Painting Supplies",
            "type":"Manufacturing & Wholesale Goods"
        }
    ],
    "sg:phone":"+61 2 6686 8122",
    "sg:postcode":"2478",
    "sg:province":"NSW",
    "sg:tags":[
        "wholesaler",
        "paint",
        "mfrs"
    ],
    "wof:name":"Wilsons Paint Place",
    "wof:placetype":"venue"
},
  "geometry": {"coordinates":[153.55332946799999,-28.8673782349],"type":"Point"}
}