{
  "type": "Feature",
  "properties": {
    "addr:full":"5 Phoenix St Westdale NSW 2340",
    "addr:housenumber":"5",
    "addr:postcode":"2340",
    "addr:street":"Phoenix St",
    "iso:country":"AU",
    "sg:address":"5 Phoenix St",
    "sg:city":"Westdale",
    "sg:classifiers":[
        {
            "category":"Utilities",
            "subcategory":"Natural Gas",
            "type":"Services"
        }
    ],
    "sg:phone":"+61 1300 306 619",
    "sg:postcode":"2340",
    "sg:province":"NSW",
    "sg:tags":[
        "supplier"
    ],
    "wof:name":"Connect Energy",
    "wof:placetype":"venue"
},
  "geometry": {"coordinates":[150.85877990700001,-31.0754108429],"type":"Point"}
}