{
  "type": "Feature",
  "properties": {
    "iso:country":"AU",
    "sg:address":"1424 Sturt St",
    "sg:city":"Ballarat",
    "sg:classifiers":[
        {
            "category":"Health Services",
            "subcategory":"Dentist",
            "type":"Services"
        }
    ],
    "sg:phone":"+61 3 5331 9489",
    "sg:postcode":"3350",
    "sg:province":"VIC",
    "sg:tags":[
        "state",
        "orthodontist",
        "qld",
        "exc"
    ],
    "sg:website":"http://www.smilesthatsparkle.com.au",
    "wof:name":"Dr Deborah Sykes",
    "wof:placetype":"venue"
},
  "geometry": {"coordinates":[143.84478799999999,-37.560127],"type":"Point"}
}