{
  "type": "Feature",
  "properties": {
    "iso:country":"AU",
    "sg:address":"East Minestone Rd",
    "sg:city":"Scottsdale",
    "sg:classifiers":[
        {
            "category":"Food & Beverages",
            "subcategory":"Fruits & Vegetables",
            "type":"Retail Goods"
        }
    ],
    "sg:phone":"+61 3 6352 2474",
    "sg:postcode":"7260",
    "sg:province":"TAS",
    "sg:tags":[
        "grower"
    ],
    "wof:name":"Calbro Vegetables",
    "wof:placetype":"venue"
},
  "geometry": {"coordinates":[147.502151,-41.172096],"type":"Point"}
}