{
  "type": "Feature",
  "properties": {
    "iso:country":"AU",
    "sg:address":"Lot 11 Reynolds Crt",
    "sg:city":"Burpengary",
    "sg:classifiers":[
        {
            "category":"Manufacturing",
            "subcategory":"Paper Products",
            "type":"Manufacturing & Wholesale Goods"
        }
    ],
    "sg:phone":"+61 7 3888 0566",
    "sg:postcode":"4505",
    "sg:province":"QLD",
    "sg:tags":[
        "container",
        "plastic"
    ],
    "wof:name":"Queensland Straw Factory",
    "wof:placetype":"venue"
},
  "geometry": {"coordinates":[152.98034668,-27.1601428986],"type":"Point"}
}