{
  "type": "Feature",
  "properties": {
    "iso:country":"AU",
    "sg:address":"Shop 3 25 Bridge Rd",
    "sg:city":"Richmond",
    "sg:classifiers":[
        {
            "category":"Shopping",
            "subcategory":"Music",
            "type":"Retail Goods"
        }
    ],
    "sg:phone":"+61 3 9427 1333",
    "sg:postcode":"3121",
    "sg:province":"VIC",
    "sg:tags":[
        "store"
    ],
    "wof:name":"Platinum Records Pty Ltd",
    "wof:placetype":"venue"
},
  "geometry": {"coordinates":[144.99037170400001,-37.8174476624],"type":"Point"}
}