{
  "type": "Feature",
  "properties": {
    "iso:country":"AU",
    "sg:address":"22/ 62 Wyrallah Rd",
    "sg:city":"East Lismore",
    "sg:classifiers":[
        {
            "category":"Organizations",
            "subcategory":"Non-profit Organization",
            "type":"Services"
        }
    ],
    "sg:phone":"+61 2 6622 8383",
    "sg:postcode":"2480",
    "sg:province":"NSW",
    "sg:tags":[
        "support",
        "disability",
        "organisation"
    ],
    "wof:name":"Royal Blind Society Of NSW - Lismore",
    "wof:placetype":"venue"
},
  "geometry": {"coordinates":[153.28533935600001,-28.8200435638],"type":"Point"}
}