{
  "type": "Feature",
  "properties": {
    "addr:full":"PO Box 290 Moss Vale NSW 2577",
    "addr:postcode":"2577",
    "iso:country":"AU",
    "sg:address":"PO Box 290",
    "sg:city":"Moss Vale",
    "sg:classifiers":[
        {
            "category":"Building & Trades",
            "subcategory":"Construction",
            "type":"Services"
        }
    ],
    "sg:phone":"+61 2 4868 1392",
    "sg:postcode":"2577",
    "sg:province":"NSW",
    "sg:tags":[
        "joiner",
        "carpenter"
    ],
    "wof:name":"Adorable Homes",
    "wof:placetype":"venue"
},
  "geometry": {"coordinates":[150.371170044,-34.5501289368],"type":"Point"}
}