{
  "type": "Feature",
  "properties": {
    "addr:full":"23 Luck St Eltham VIC 3095",
    "addr:housenumber":"23",
    "addr:postcode":"3095",
    "addr:street":"Luck St",
    "iso:country":"AU",
    "sg:address":"23 Luck St",
    "sg:city":"Eltham",
    "sg:classifiers":[
        {
            "category":"Health Services",
            "subcategory":"Optometrist",
            "type":"Services"
        }
    ],
    "sg:phone":"+61 3 9439 3936",
    "sg:postcode":"3095",
    "sg:province":"VIC",
    "wof:name":"Cochrane & Debney Optometrist",
    "wof:placetype":"venue"
},
  "geometry": {"coordinates":[145.15153503400001,-37.7125358582],"type":"Point"}
}