{
  "type": "Feature",
  "properties": {
    "addr:full":"5 Coll Pl St Andrews NSW 2566",
    "addr:housenumber":"5",
    "addr:postcode":"2566",
    "addr:street":"Coll Pl",
    "iso:country":"AU",
    "sg:address":"5 Coll Pl",
    "sg:city":"St Andrews",
    "sg:classifiers":[
        {
            "category":"Professional",
            "subcategory":"Art Services",
            "type":"Services"
        }
    ],
    "sg:phone":"+61 411 102 222",
    "sg:postcode":"2566",
    "sg:province":"NSW",
    "sg:tags":[
        "decorator",
        "painter"
    ],
    "wof:name":"D John Painter",
    "wof:placetype":"venue"
},
  "geometry": {"coordinates":[150.83102417000001,-34.0283088684],"type":"Point"}
}