{
  "type": "Feature",
  "properties": {
    "addr:full":"Unit 1- 6 Viewtech Pl Rowville VIC 3178",
    "addr:housenumber":"6",
    "addr:postcode":"3178",
    "addr:street":"Viewtech Pl",
    "iso:country":"AU",
    "sg:address":"Unit 1- 6 Viewtech Pl",
    "sg:city":"Rowville",
    "sg:classifiers":[
        {
            "category":"Shopping",
            "subcategory":"Stationery & Office Supplies",
            "type":"Retail Goods"
        }
    ],
    "sg:phone":"+61 3 9755 5866",
    "sg:postcode":"3178",
    "sg:province":"VIC",
    "sg:tags":[
        "packaging",
        "equipment",
        "sealing",
        "filling"
    ],
    "wof:name":"M.P.I. Pty Ltd",
    "wof:placetype":"venue"
},
  "geometry": {"coordinates":[145.222198486,-37.9274749756],"type":"Point"}
}