{
  "type": "Feature",
  "properties": {
    "addr:full":"15 Parramatta Rd Lidcombe NSW 2141",
    "addr:housenumber":"15",
    "addr:postcode":"2141",
    "addr:street":"Parramatta Rd",
    "iso:country":"AU",
    "sg:address":"15 Parramatta Rd",
    "sg:city":"Lidcombe",
    "sg:classifiers":[
        {
            "category":"Retail",
            "subcategory":"Auto Rental",
            "type":"Services"
        }
    ],
    "sg:phone":"+61 2 9647 2766",
    "sg:postcode":"2141",
    "sg:province":"NSW",
    "sg:tags":[
        "car",
        "hire",
        "minibus"
    ],
    "wof:name":"Hertz.",
    "wof:placetype":"venue"
},
  "geometry": {"coordinates":[151.050323486,-33.8489532471],"type":"Point"}
}