{
  "type": "Feature",
  "properties": {
    "addr:full":"46- 54 Victoria St Taree NSW 2430",
    "addr:housenumber":"54",
    "addr:postcode":"2430",
    "addr:street":"Victoria St",
    "iso:country":"AU",
    "sg:address":"46- 54 Victoria St",
    "sg:city":"Taree",
    "sg:classifiers":[
        {
            "category":"Retail",
            "subcategory":"Auto Repair",
            "type":"Services"
        }
    ],
    "sg:phone":"+61 2 6552 1200",
    "sg:postcode":"2430",
    "sg:province":"NSW",
    "sg:tags":[
        "repairer",
        "motor",
        "engineer"
    ],
    "wof:name":"Toyota Dealers",
    "wof:placetype":"venue"
},
  "geometry": {"coordinates":[152.46639999999999,-31.910309],"type":"Point"}
}