{
  "type": "Feature",
  "properties": {
    "addr:full":"907 Nepean Hwy Mornington VIC 3931",
    "addr:housenumber":"907",
    "addr:postcode":"3931",
    "addr:street":"Nepean Hwy",
    "iso:country":"AU",
    "sg:address":"907 Nepean Hwy",
    "sg:city":"Mornington",
    "sg:classifiers":[
        {
            "category":"Autos & Motor Vehicles",
            "subcategory":"Automobile Sales",
            "type":"Retail Goods"
        }
    ],
    "sg:phone":"+61 3 5973 4566",
    "sg:postcode":"3931",
    "sg:province":"VIC",
    "sg:tags":[
        "car",
        "used"
    ],
    "wof:name":"Car Torque",
    "wof:placetype":"venue"
},
  "geometry": {"coordinates":[145.04737854000001,-38.2270240784],"type":"Point"}
}