{
  "type": "Feature",
  "properties": {
    "addr:full":"3 Allambic St The Gap QLD 4061",
    "addr:housenumber":"3",
    "addr:postcode":"4061",
    "addr:street":"Allambic St",
    "iso:country":"AU",
    "sg:address":"3 Allambic St",
    "sg:city":"The Gap",
    "sg:classifiers":[
        {
            "category":"Personal",
            "subcategory":"Skin Care",
            "type":"Services"
        }
    ],
    "sg:phone":"+61 7 3511 0058",
    "sg:postcode":"4061",
    "sg:province":"QLD",
    "sg:tags":[
        "treatment"
    ],
    "wof:name":"Beauty Techniques",
    "wof:placetype":"venue"
},
  "geometry": {"coordinates":[152.945755005,-27.4419689178],"type":"Point"}
}