{
  "type": "Feature",
  "properties": {
    "addr:full":"35 Northern Hwy Echuca VIC 3564",
    "addr:housenumber":"35",
    "addr:postcode":"3564",
    "addr:street":"Northern Hwy",
    "iso:country":"AU",
    "sg:address":"35 Northern Hwy",
    "sg:city":"Echuca",
    "sg:classifiers":[
        {
            "category":"Autos & Motor Vehicles",
            "subcategory":"Automobile Sales",
            "type":"Retail Goods"
        }
    ],
    "sg:phone":"+61 3 5483 0400",
    "sg:postcode":"3564",
    "sg:province":"VIC",
    "sg:tags":[
        "car",
        "new"
    ],
    "wof:name":"Morley Ford Pty Ltd",
    "wof:placetype":"venue"
},
  "geometry": {"coordinates":[144.72979736299999,-36.1439704895],"type":"Point"}
}