{
  "type": "Feature",
  "properties": {
    "addr:full":"U4/ 713 Military Rd Mosman NSW 2088",
    "addr:housenumber":"713",
    "addr:postcode":"2088",
    "addr:street":"U4 /;Military Rd",
    "iso:country":"AU",
    "sg:address":"U4/ 713 Military Rd",
    "sg:city":"Mosman",
    "sg:classifiers":[
        {
            "category":"Shopping",
            "subcategory":"Clothing, Apparel, & Fashions",
            "type":"Retail Goods"
        }
    ],
    "sg:phone":"+61 2 9968 1388",
    "sg:postcode":"2088",
    "sg:province":"NSW",
    "sg:tags":[
        "lady",
        "wear"
    ],
    "wof:name":"L A Look",
    "wof:placetype":"venue"
},
  "geometry": {"coordinates":[151.24383544899999,-33.8276824951],"type":"Point"}
}