{
  "type": "Feature",
  "properties": {
    "addr:full":"RMB 6331 Old Telegraph Rd East Crossover VIC 3821",
    "addr:postcode":"3821",
    "addr:street":"Old Telegraph Rd East Crossover",
    "iso:country":"AU",
    "sg:address":"RMB 6331 Old Telegraph Rd",
    "sg:city":"East Crossover",
    "sg:classifiers":[
        {
            "category":"Building & Trades",
            "subcategory":"Construction",
            "type":"Services"
        }
    ],
    "sg:phone":"+61 3 5626 8545",
    "sg:postcode":"3821",
    "sg:province":"VIC",
    "sg:tags":[
        "contractor"
    ],
    "wof:name":"Telegraph Rd Builders",
    "wof:placetype":"venue"
},
  "geometry": {"coordinates":[145.92332500000001,-38.076286],"type":"Point"}
}