{
  "type": "Feature",
  "properties": {
    "iso:country":"AU",
    "sg:address":"Cnr Boddington Crs & Carleton St",
    "sg:city":"Kambah",
    "sg:classifiers":[
        {
            "category":"Fast Food",
            "type":"Food & Drink"
        }
    ],
    "sg:phone":"+61 2 6231 6909",
    "sg:postcode":"2902",
    "sg:province":"ACT",
    "sg:tags":[
        "away",
        "take"
    ],
    "wof:name":"Theo's Takeaway Food & Pizza Bar",
    "wof:placetype":"venue"
},
  "geometry": {"coordinates":[149.05056762699999,-35.3829803467],"type":"Point"}
}