{
  "type": "Feature",
  "properties": {
    "addr:full":"Shop 1, 46 Gayford Rd Aspley QLD 4034",
    "addr:housenumber":"shop;46",
    "addr:postcode":"4034",
    "addr:street":"Gayford Rd",
    "iso:country":"AU",
    "sg:address":"Shop 1, 46 Gayford Rd",
    "sg:city":"Aspley",
    "sg:classifiers":[
        {
            "category":"Cafe",
            "type":"Food & Drink"
        }
    ],
    "sg:phone":"+61 7 3263 3006",
    "sg:postcode":"4034",
    "sg:province":"QLD",
    "wof:name":"Coffee Club The",
    "wof:placetype":"venue"
},
  "geometry": {"coordinates":[153.01585399999999,-27.362926],"type":"Point"}
}