{
  "type": "Feature",
  "properties": {
    "iso:country":"AU",
    "sg:address":"Lvl 1/ 119 Hopkins St",
    "sg:city":"Footscray",
    "sg:classifiers":[
        {
            "category":"Professional",
            "subcategory":"Art Services",
            "type":"Services"
        }
    ],
    "sg:phone":"+61 413 357 018",
    "sg:postcode":"3011",
    "sg:province":"VIC",
    "sg:tags":[
        "artist"
    ],
    "wof:name":"Y. Pg 2007",
    "wof:placetype":"venue"
},
  "geometry": {"coordinates":[144.900787353,-37.8000106812],"type":"Point"}
}