{
  "type": "Feature",
  "properties": {
    "iso:country":"AU",
    "sg:address":"128A Katoomba St",
    "sg:city":"Katoomba",
    "sg:classifiers":[
        {
            "category":"Professional",
            "subcategory":"Business Services",
            "type":"Services"
        }
    ],
    "sg:phone":"+61 1300 650 058",
    "sg:postcode":"2780",
    "sg:province":"NSW",
    "sg:tags":[
        "small",
        "advisory"
    ],
    "wof:name":"Greater Nepean Business Advisory Service",
    "wof:placetype":"venue"
},
  "geometry": {"coordinates":[150.31092834500001,-33.716583252],"type":"Point"}
}