{
  "type": "Feature",
  "properties": {
    "addr:full":"386 Martins Rd Green Fields SA 5107",
    "addr:housenumber":"386",
    "addr:postcode":"5107",
    "addr:street":"Martins Rd",
    "iso:country":"AU",
    "sg:address":"386 Martins Rd",
    "sg:city":"Green Fields",
    "sg:classifiers":[
        {
            "category":"Home & Garden",
            "subcategory":"Building Materials",
            "type":"Retail Goods"
        }
    ],
    "sg:phone":"+61 8 8283 0022",
    "sg:postcode":"5107",
    "sg:province":"SA",
    "sg:tags":[
        "secondhand"
    ],
    "wof:name":"Rockin Maria's Recycled Building Materials",
    "wof:placetype":"venue"
},
  "geometry": {"coordinates":[138.598556519,-34.7927818298],"type":"Point"}
}