{
  "type": "Feature",
  "properties": {
    "addr:full":"43 Manchester Rd Mooroolbark VIC 3138",
    "addr:housenumber":"43",
    "addr:postcode":"3138",
    "addr:street":"Manchester Rd",
    "iso:country":"AU",
    "sg:address":"43 Manchester Rd",
    "sg:city":"Mooroolbark",
    "sg:classifiers":[
        {
            "category":"Fast Food",
            "type":"Food & Drink"
        }
    ],
    "sg:phone":"+61 3 9726 9899",
    "sg:postcode":"3138",
    "sg:province":"VIC",
    "sg:tags":[
        "away",
        "take"
    ],
    "wof:name":"Manchester Road Fish & Chips Shop",
    "wof:placetype":"venue"
},
  "geometry": {"coordinates":[145.31098938,-37.7842254639],"type":"Point"}
}