{
  "type": "Feature",
  "properties": {
    "iso:country":"AU",
    "sg:address":"51 Leschenaultia Cl",
    "sg:city":"Donnybrook",
    "sg:classifiers":[
        {
            "category":"Building & Trades",
            "subcategory":"Landscaping Services",
            "type":"Services"
        }
    ],
    "sg:phone":"+61 8 9731 1259",
    "sg:postcode":"6239",
    "sg:province":"WA",
    "sg:tags":[
        "firebreak",
        "clearing",
        "land",
        "contractor"
    ],
    "wof:name":"Donnybrook Bulldozing Contractors",
    "wof:placetype":"venue"
},
  "geometry": {"coordinates":[115.823013,-33.570419],"type":"Point"}
}