{
  "type": "Feature",
  "properties": {
    "iso:country":"AU",
    "sg:address":"9 Grand Ave",
    "sg:city":"Camellia",
    "sg:classifiers":[
        {
            "category":"Professional",
            "type":"Services"
        }
    ],
    "sg:phone":"+61 2 9684 6755",
    "sg:postcode":"2142",
    "sg:province":"NSW",
    "sg:tags":[
        "transport"
    ],
    "wof:name":"Armour Transport",
    "wof:placetype":"venue"
},
  "geometry": {"coordinates":[151.03761291500001,-33.8209838867],"type":"Point"}
}