{
  "type": "Feature",
  "properties": {
    "addr:full":"90 Browns La Plenty VIC 3090",
    "addr:housenumber":"90",
    "addr:postcode":"3090",
    "addr:street":"Browns La Plenty",
    "iso:country":"AU",
    "sg:address":"90 Browns La",
    "sg:city":"Plenty",
    "sg:classifiers":[
        {
            "category":"Building & Trades",
            "subcategory":"Cleaning & Sanitation",
            "type":"Services"
        }
    ],
    "sg:phone":"+61 3 9436 1366",
    "sg:postcode":"3090",
    "sg:province":"VIC",
    "sg:tags":[
        "industrial",
        "commercial",
        "contractor"
    ],
    "wof:name":"Evorall Wayne",
    "wof:placetype":"venue"
},
  "geometry": {"coordinates":[145.116287231,-37.6575202942],"type":"Point"}
}