{
  "type": "Feature",
  "properties": {
    "addr:full":"Stein St Mintaro SA 5415",
    "addr:postcode":"5415",
    "addr:street":"Stein St",
    "iso:country":"AU",
    "sg:address":"Stein St",
    "sg:city":"Mintaro",
    "sg:classifiers":[
        {
            "category":"Education",
            "subcategory":"School",
            "type":"Public Place"
        }
    ],
    "sg:phone":"+61 8 8843 9095",
    "sg:postcode":"5415",
    "sg:province":"SA",
    "sg:tags":[
        "state",
        "except",
        "nsw"
    ],
    "wof:name":"Mintaro Campus",
    "wof:placetype":"venue"
},
  "geometry": {"coordinates":[138.71905517600001,-33.9188575745],"type":"Point"}
}