{
  "type": "Feature",
  "properties": {
    "addr:full":"196 Chapel St Armidale NSW 2350",
    "addr:housenumber":"196",
    "addr:postcode":"2350",
    "addr:street":"Chapel St",
    "iso:country":"AU",
    "sg:address":"196 Chapel St",
    "sg:city":"Armidale",
    "sg:classifiers":[
        {
            "category":"Building & Trades",
            "subcategory":"Construction",
            "type":"Services"
        }
    ],
    "sg:phone":"+61 438 214 197",
    "sg:postcode":"2350",
    "sg:province":"NSW",
    "sg:tags":[
        "renovation",
        "alterations",
        "extension",
        "contractor"
    ],
    "wof:name":"Pat McMillan Building Contractor",
    "wof:placetype":"venue"
},
  "geometry": {"coordinates":[151.67451477,-30.5262947083],"type":"Point"}
}