{
  "type": "Feature",
  "properties": {
    "addr:full":"22 Merchison Crs Clayton VIC 3168",
    "addr:housenumber":"22",
    "addr:postcode":"3168",
    "addr:street":"Merchison Crs",
    "iso:country":"AU",
    "sg:address":"22 Merchison Crs",
    "sg:city":"Clayton",
    "sg:classifiers":[
        {
            "category":"Building & Trades",
            "subcategory":"Construction",
            "type":"Services"
        }
    ],
    "sg:phone":"+61 403 372 523",
    "sg:postcode":"3168",
    "sg:province":"VIC",
    "sg:tags":[
        "fencing",
        "contractor"
    ],
    "wof:name":"Sky Fences",
    "wof:placetype":"venue"
},
  "geometry": {"coordinates":[145.124755859,-37.899181366],"type":"Point"}
}