{
  "type": "Feature",
  "properties": {
    "addr:full":"29 Macquarie St Parramatta NSW 2150",
    "addr:housenumber":"29",
    "addr:postcode":"2150",
    "addr:street":"Macquarie St",
    "iso:country":"AU",
    "sg:address":"29 Macquarie St",
    "sg:city":"Parramatta",
    "sg:classifiers":[
        {
            "category":"Real Estate",
            "subcategory":"Real Estate Agent",
            "type":"Services"
        }
    ],
    "sg:phone":"+61 2 9689 1277",
    "sg:postcode":"2150",
    "sg:province":"NSW",
    "wof:name":"Comres Property Service",
    "wof:placetype":"venue"
},
  "geometry": {"coordinates":[150.94386291500001,-33.8709487915],"type":"Point"}
}