{
  "type": "Feature",
  "properties": {
    "addr:full":"Thistle St Launceston TAS 7250",
    "addr:postcode":"7250",
    "addr:street":"Thistle St",
    "iso:country":"AU",
    "sg:address":"Thistle St",
    "sg:city":"Launceston",
    "sg:classifiers":[
        {
            "category":"Government",
            "subcategory":"Post Office",
            "type":"Public Place"
        }
    ],
    "sg:phone":"+61 3 6344 7373",
    "sg:postcode":"7250",
    "sg:province":"TAS",
    "sg:tags":[
        "postage",
        "meter"
    ],
    "wof:name":"Mail Direct",
    "wof:placetype":"venue"
},
  "geometry": {"coordinates":[147.14186096200001,-41.4520492554],"type":"Point"}
}