{
  "type": "Feature",
  "properties": {
    "addr:full":"Rear 45 Verge St Kempsey NSW 2440",
    "addr:housenumber":"45",
    "addr:postcode":"2440",
    "addr:street":"Verge St",
    "iso:country":"AU",
    "sg:address":"Rear 45 Verge St",
    "sg:city":"Kempsey",
    "sg:classifiers":[
        {
            "category":"Retail",
            "subcategory":"Auto Repair",
            "type":"Services"
        }
    ],
    "sg:phone":"+61 2 6562 5268",
    "sg:postcode":"2440",
    "sg:province":"NSW",
    "sg:tags":[
        "beater",
        "painter",
        "panel"
    ],
    "wof:name":"Stephen King Panelbeating",
    "wof:placetype":"venue"
},
  "geometry": {"coordinates":[152.832764,-31.079973],"type":"Point"}
}