{
  "type": "Feature",
  "properties": {
    "iso:country":"AU",
    "sg:address":"Shop15a/ 112 City Rd",
    "sg:city":"Beenleigh",
    "sg:classifiers":[
        {
            "category":"Personal",
            "subcategory":"Beauty Salon",
            "type":"Services"
        }
    ],
    "sg:phone":"+61 7 3287 3357",
    "sg:postcode":"4207",
    "sg:province":"QLD",
    "sg:tags":[
        "hairdresser"
    ],
    "wof:name":"Tjuz Saloon",
    "wof:placetype":"venue"
},
  "geometry": {"coordinates":[153.20225524899999,-27.7157440186],"type":"Point"}
}