{
  "type": "Feature",
  "properties": {
    "addr:full":"9 Percy Crt Alice Springs NT 0870",
    "addr:housenumber":"9",
    "addr:postcode":"nt 0870",
    "addr:street":"Percy Crt",
    "iso:country":"AU",
    "sg:address":"9 Percy Crt",
    "sg:city":"Alice Springs",
    "sg:classifiers":[
        {
            "category":"Travel",
            "subcategory":"Hostel",
            "type":"Entertainment"
        }
    ],
    "sg:phone":"+61 8 8952 5811",
    "sg:postcode":"0870",
    "sg:province":"NT",
    "sg:tags":[
        "home"
    ],
    "wof:name":"Aboriginal Hostels Limited",
    "wof:placetype":"venue"
},
  "geometry": {"coordinates":[133.87225341800001,-23.7496948242],"type":"Point"}
}