{
  "type": "Feature",
  "properties": {
    "iso:country":"AU",
    "sg:address":"Shop 31, Eastpoint Food Fair 251 New South Head Rd",
    "sg:city":"Edgecliff",
    "sg:classifiers":[
        {
            "category":"Health Services",
            "subcategory":"Doctor",
            "type":"Services"
        }
    ],
    "sg:phone":"+61 2 9362 4111",
    "sg:postcode":"2027",
    "sg:province":"NSW",
    "sg:tags":[
        "podiatrist"
    ],
    "wof:name":"Haydar Ozcan",
    "wof:placetype":"venue"
},
  "geometry": {"coordinates":[151.23631286599999,-33.8788833618],"type":"Point"}
}