{
  "type": "Feature",
  "properties": {
    "addr:full":"102 Yarralea St Alphington VIC 3078",
    "addr:housenumber":"102",
    "addr:postcode":"3078",
    "addr:street":"Yarralea St",
    "iso:country":"AU",
    "sg:address":"102 Yarralea St",
    "sg:city":"Alphington",
    "sg:classifiers":[
        {
            "category":"Organizations",
            "subcategory":"Membership Organization",
            "type":"Services"
        }
    ],
    "sg:phone":"+61 3 9499 5580",
    "sg:postcode":"3078",
    "sg:province":"VIC",
    "sg:tags":[
        "club",
        "bridge"
    ],
    "wof:name":"Alphington Bridge Centre",
    "wof:placetype":"venue"
},
  "geometry": {"coordinates":[145.032806397,-37.7784347534],"type":"Point"}
}