{
  "type": "Feature",
  "properties": {
    "addr:full":"Suite 24/ 239 Magill Rd Maylands SA 5069",
    "addr:housenumber":"24 / 239",
    "addr:postcode":"5069",
    "addr:street":"Magill Rd",
    "iso:country":"AU",
    "sg:address":"Suite 24/ 239 Magill Rd",
    "sg:city":"Maylands",
    "sg:classifiers":[
        {
            "category":"Wholesale",
            "subcategory":"Vending Machines",
            "type":"Manufacturing & Wholesale Goods"
        }
    ],
    "sg:phone":"+61 8 8366 6549",
    "sg:postcode":"5069",
    "sg:province":"SA",
    "sg:tags":[
        "measuring",
        "equipment"
    ],
    "wof:name":"Applied Measurement Australia Pty Ltd",
    "wof:placetype":"venue"
},
  "geometry": {"coordinates":[138.63870239299999,-34.9147567749],"type":"Point"}
}