{
  "type": "Feature",
  "properties": {
    "addr:full":"90 Sutherland St Moonah TAS 7009",
    "addr:housenumber":"90",
    "addr:postcode":"7009",
    "addr:street":"Sutherland St",
    "iso:country":"AU",
    "sg:address":"90 Sutherland St",
    "sg:city":"Moonah",
    "sg:classifiers":[
        {
            "category":"Manufacturing",
            "subcategory":"Motor Vehicles & Parts",
            "type":"Manufacturing & Wholesale Goods"
        }
    ],
    "sg:phone":"+61 3 6272 0306",
    "sg:postcode":"7009",
    "sg:province":"TAS",
    "sg:tags":[
        "replacement"
    ],
    "wof:name":"Action Auto Wreckers",
    "wof:placetype":"venue"
},
  "geometry": {"coordinates":[147.29302978499999,-42.8371734619],"type":"Point"}
}