{
  "type": "Feature",
  "properties": {
    "addr:full":"44a Ararat Rd Stawell VIC 3380",
    "addr:housenumber":"44a",
    "addr:postcode":"3380",
    "addr:street":"Ararat Rd",
    "iso:country":"AU",
    "sg:address":"44a Ararat Rd",
    "sg:city":"Stawell",
    "sg:classifiers":[
        {
            "category":"Manufacturing",
            "subcategory":"Metals",
            "type":"Manufacturing & Wholesale Goods"
        }
    ],
    "sg:phone":"+61 3 5358 4273",
    "sg:postcode":"3380",
    "sg:province":"VIC",
    "sg:tags":[
        "steel",
        "fabricator",
        "mfrs"
    ],
    "wof:name":"C.K.S. Engineering",
    "wof:placetype":"venue"
},
  "geometry": {"coordinates":[142.765625,-37.0643806458],"type":"Point"}
}