{
  "type": "Feature",
  "properties": {
    "addr:full":"162 Wanneroo Rd Yokine WA 6060",
    "addr:housenumber":"162",
    "addr:postcode":"6060",
    "addr:street":"Wanneroo Rd",
    "iso:country":"AU",
    "sg:address":"162 Wanneroo Rd",
    "sg:city":"Yokine",
    "sg:classifiers":[
        {
            "category":"Health Services",
            "subcategory":"Doctor",
            "type":"Services"
        }
    ],
    "sg:phone":"+61 8 9349 6777",
    "sg:postcode":"6060",
    "sg:province":"WA",
    "sg:tags":[
        "medical",
        "practitioner"
    ],
    "wof:name":"Waddell Ainslie Dr",
    "wof:placetype":"venue"
},
  "geometry": {"coordinates":[115.840492248,-31.8954029083],"type":"Point"}
}