{
  "type": "Feature",
  "properties": {
    "addr:full":"Suite 1/ 4 Wentworth Drv Liberty Grove NSW 2138",
    "addr:housenumber":"4",
    "addr:postcode":"2138",
    "addr:street":"Wentworth Drv Liberty Grove",
    "iso:country":"AU",
    "sg:address":"Suite 1/ 4 Wentworth Drv",
    "sg:city":"Liberty Grove",
    "sg:classifiers":[
        {
            "category":"Real Estate",
            "subcategory":"Real Estate Agent",
            "type":"Services"
        }
    ],
    "sg:phone":"+61 2 9743 6544",
    "sg:postcode":"2138",
    "sg:province":"NSW",
    "wof:name":"Liberty Grove Real Estate",
    "wof:placetype":"venue"
},
  "geometry": {"coordinates":[151.083892822,-33.8393325806],"type":"Point"}
}