{
  "type": "Feature",
  "properties": {
    "addr:full":"362 Cornwallis Rd Windsor NSW 2756",
    "addr:housenumber":"362",
    "addr:postcode":"2756",
    "addr:street":"Cornwallis Rd",
    "iso:country":"AU",
    "sg:address":"362 Cornwallis Rd",
    "sg:city":"Windsor",
    "sg:classifiers":[
        {
            "category":"Home & Garden",
            "subcategory":"Garden Supply",
            "type":"Retail Goods"
        }
    ],
    "sg:phone":"+61 2 4577 3907",
    "sg:postcode":"2756",
    "sg:province":"NSW",
    "sg:tags":[
        "turf",
        "lawn"
    ],
    "wof:name":"Grech's Turf Supplies",
    "wof:placetype":"venue"
},
  "geometry": {"coordinates":[150.797119141,-33.5812263489],"type":"Point"}
}