{
  "type": "Feature",
  "properties": {
    "addr:full":"90a Northgate Drv Thomastown VIC 3074",
    "addr:housenumber":"90a",
    "addr:postcode":"3074",
    "addr:street":"Northgate Drv",
    "iso:country":"AU",
    "sg:address":"90a Northgate Drv",
    "sg:city":"Thomastown",
    "sg:classifiers":[
        {
            "category":"Utilities",
            "subcategory":"Mobile Phone",
            "type":"Services"
        }
    ],
    "sg:phone":"+61 3 9466 3740",
    "sg:postcode":"3074",
    "sg:province":"VIC",
    "sg:tags":[
        "assembly",
        "part",
        "electronic"
    ],
    "wof:name":"MMI Electronic Assemblers",
    "wof:placetype":"venue"
},
  "geometry": {"coordinates":[145.03361511200001,-37.6883506775],"type":"Point"}
}