{
  "type": "Feature",
  "properties": {
    "iso:country":"AU",
    "sg:address":"34 Isa St",
    "sg:city":"Fyshwick",
    "sg:classifiers":[
        {
            "category":"Autos & Motor Vehicles",
            "subcategory":"Auto Supplies",
            "type":"Retail Goods"
        }
    ],
    "sg:phone":"+61 2 6280 0897",
    "sg:postcode":"2609",
    "sg:province":"ACT",
    "sg:tags":[
        "part",
        "cycles",
        "accessory"
    ],
    "wof:name":"Go-Bike Pty Ltd",
    "wof:placetype":"venue"
},
  "geometry": {"coordinates":[149.17300415,-35.3259277344],"type":"Point"}
}