{
  "type": "Feature",
  "properties": {
    "addr:full":"31 Cassia St Evans Head NSW 2473",
    "addr:housenumber":"31",
    "addr:postcode":"2473",
    "addr:street":"Cassia St Evans",
    "iso:country":"AU",
    "sg:address":"31 Cassia St",
    "sg:city":"Evans Head",
    "sg:classifiers":[
        {
            "category":"Utilities",
            "subcategory":"Electric",
            "type":"Services"
        }
    ],
    "sg:phone":"+61 2 6682 4356",
    "sg:postcode":"2473",
    "sg:province":"NSW",
    "sg:tags":[
        "advisory",
        "lighting",
        "power"
    ],
    "wof:name":"Partners Electrical Contracting",
    "wof:placetype":"venue"
},
  "geometry": {"coordinates":[153.426147461,-29.1083126068],"type":"Point"}
}