{
  "type": "Feature",
  "properties": {
    "addr:full":"49 March St Richmond NSW 2753",
    "addr:housenumber":"49",
    "addr:postcode":"2753",
    "addr:street":"March St",
    "iso:country":"AU",
    "sg:address":"49 March St",
    "sg:city":"Richmond",
    "sg:classifiers":[
        {
            "category":"Retail",
            "subcategory":"Auto Repair",
            "type":"Services"
        }
    ],
    "sg:phone":"+61 2 4588 5777",
    "sg:postcode":"2753",
    "sg:province":"NSW",
    "sg:tags":[
        "repairer",
        "motor",
        "engineer"
    ],
    "wof:name":"Norman Andrews Automotive Repairs",
    "wof:placetype":"venue"
},
  "geometry": {"coordinates":[150.75384521500001,-33.599899292],"type":"Point"}
}