{
  "type": "Feature",
  "properties": {
    "addr:full":"2a Foden Ave Campbellfield VIC 3061",
    "addr:housenumber":"2a",
    "addr:postcode":"3061",
    "addr:street":"Foden Ave",
    "iso:country":"AU",
    "sg:address":"2a Foden Ave",
    "sg:city":"Campbellfield",
    "sg:classifiers":[
        {
            "category":"Fast Food",
            "type":"Food & Drink"
        }
    ],
    "sg:phone":"+61 3 9305 3196",
    "sg:postcode":"3061",
    "sg:province":"VIC",
    "sg:tags":[
        "away",
        "take"
    ],
    "wof:name":"Andy's Fantastic Food",
    "wof:placetype":"venue"
},
  "geometry": {"coordinates":[144.94615173299999,-37.6484298706],"type":"Point"}
}