{
  "type": "Feature",
  "properties": {
    "addr:full":"Benowa Gardens Shopping Centre Lower Level Carrara St Benowa QLD 4217",
    "addr:postcode":"4217",
    "addr:street":"St",
    "iso:country":"AU",
    "sg:address":"Benowa Gardens Shopping Centre Lower Level Carrara St",
    "sg:city":"Benowa",
    "sg:classifiers":[
        {
            "category":"Health Services",
            "subcategory":"Doctor",
            "type":"Services"
        }
    ],
    "sg:phone":"+61 7 5597 2660",
    "sg:postcode":"4217",
    "sg:province":"QLD",
    "sg:tags":[
        "medical",
        "practitioner"
    ],
    "wof:name":"Isherwood Penelope Dr",
    "wof:placetype":"venue"
},
  "geometry": {"coordinates":[153.39332580600001,-28.0087165833],"type":"Point"}
}