{
  "type": "Feature",
  "properties": {
    "addr:full":"98B Aberdare Rd Shenton Park WA 6008",
    "addr:housenumber":"98b",
    "addr:postcode":"6008",
    "addr:street":"Aberdare Rd",
    "iso:country":"AU",
    "sg:address":"98B Aberdare Rd",
    "sg:city":"Shenton Park",
    "sg:classifiers":[
        {
            "category":"Health Services",
            "subcategory":"Health Practitioner",
            "type":"Services"
        }
    ],
    "sg:phone":"+61 419 043 768",
    "sg:postcode":"6008",
    "sg:province":"WA",
    "sg:tags":[
        "psychotherapist"
    ],
    "wof:name":"Jungian Psychotherapists",
    "wof:placetype":"venue"
},
  "geometry": {"coordinates":[115.809127808,-31.9642391205],"type":"Point"}
}