{
  "type": "Feature",
  "properties": {
    "addr:full":"8 Eclar La Joondalup WA 6027",
    "addr:housenumber":"8",
    "addr:postcode":"6027",
    "addr:street":"Eclar La",
    "iso:country":"AU",
    "sg:address":"8 Eclar La",
    "sg:city":"Joondalup",
    "sg:classifiers":[
        {
            "category":"Recreation",
            "subcategory":"Amusement Park",
            "type":"Entertainment"
        }
    ],
    "sg:phone":"+61 8 9301 5133",
    "sg:postcode":"6027",
    "sg:province":"WA",
    "wof:name":"Go Bananas",
    "wof:placetype":"venue"
},
  "geometry": {"coordinates":[115.762878418,-31.7470417023],"type":"Point"}
}