{
  "type": "Feature",
  "properties": {
    "addr:full":"Hidden Valley Rd Yeppoon QLD 4703",
    "addr:postcode":"4703",
    "addr:street":"Hidden Valley Rd",
    "iso:country":"AU",
    "sg:address":"Hidden Valley Rd",
    "sg:city":"Yeppoon",
    "sg:classifiers":[
        {
            "category":"Sports & Exercise",
            "subcategory":"Sports Center",
            "type":"Entertainment"
        }
    ],
    "sg:phone":"+61 7 4939 2120",
    "sg:postcode":"4703",
    "sg:province":"QLD",
    "sg:tags":[
        "coach",
        "tennis"
    ],
    "wof:name":"Mr T Tennis Coaching",
    "wof:placetype":"venue"
},
  "geometry": {"coordinates":[150.72914123499999,-23.1462078094],"type":"Point"}
}