{
  "type": "Feature",
  "properties": {
    "addr:full":"66a Leah St Forestville SA 5035",
    "addr:housenumber":"66a",
    "addr:postcode":"5035",
    "addr:street":"Leah St",
    "iso:country":"AU",
    "sg:address":"66a Leah St",
    "sg:city":"Forestville",
    "sg:classifiers":[
        {
            "category":"Personal",
            "subcategory":"Beauty Salon",
            "type":"Services"
        }
    ],
    "sg:phone":"+61 8 8297 3517",
    "sg:postcode":"5035",
    "sg:province":"SA",
    "sg:tags":[
        "hairdresser"
    ],
    "wof:name":"Hair Station Hair Design",
    "wof:placetype":"venue"
},
  "geometry": {"coordinates":[138.58125305199999,-34.9534339905],"type":"Point"}
}