{
  "type": "Feature",
  "properties": {
    "addr:full":"62 Netherton St Nambour QLD 4560",
    "addr:housenumber":"62",
    "addr:postcode":"4560",
    "addr:street":"Netherton St",
    "iso:country":"AU",
    "sg:address":"62 Netherton St",
    "sg:city":"Nambour",
    "sg:classifiers":[
        {
            "category":"Health Services",
            "subcategory":"Doctor",
            "type":"Services"
        }
    ],
    "sg:phone":"+61 7 5441 1666",
    "sg:postcode":"4560",
    "sg:province":"QLD",
    "sg:tags":[
        "medical",
        "practitioner"
    ],
    "wof:name":"Sleep Screen",
    "wof:placetype":"venue"
},
  "geometry": {"coordinates":[152.972167969,-26.609369278],"type":"Point"}
}