{
  "type": "Feature",
  "properties": {
    "addr:full":"1 Wavecrest Pl Calamvale QLD 4116",
    "addr:housenumber":"1",
    "addr:postcode":"4116",
    "addr:street":"Wavecrest Pl",
    "iso:country":"AU",
    "sg:address":"1 Wavecrest Pl",
    "sg:city":"Calamvale",
    "sg:classifiers":[
        {
            "category":"Professional",
            "subcategory":"Engineering",
            "type":"Services"
        }
    ],
    "sg:phone":"+61 7 3711 6469",
    "sg:postcode":"4116",
    "sg:province":"QLD",
    "sg:tags":[
        "engineer"
    ],
    "wof:name":"Martell Engineering",
    "wof:placetype":"venue"
},
  "geometry": {"coordinates":[153.044845581,-27.6213607788],"type":"Point"}
}