{
  "type": "Feature",
  "properties": {
    "addr:full":"88 Mornington Rd Mornington TAS 7018",
    "addr:housenumber":"88",
    "addr:postcode":"7018",
    "addr:street":"Mornington Rd",
    "iso:country":"AU",
    "sg:address":"88 Mornington Rd",
    "sg:city":"Mornington",
    "sg:classifiers":[
        {
            "category":"Building & Trades",
            "subcategory":"Construction",
            "type":"Services"
        }
    ],
    "sg:phone":"+61 3 6244 6500",
    "sg:postcode":"7018",
    "sg:province":"TAS",
    "sg:tags":[
        "welding"
    ],
    "wof:name":"Structural & Metal Fabrications Pty Ltd",
    "wof:placetype":"venue"
},
  "geometry": {"coordinates":[147.40110778799999,-42.8611869812],"type":"Point"}
}