{
  "type": "Feature",
  "properties": {
    "addr:full":"Cnr Forrester Rd & Wordoo St St Marys NSW 2760",
    "addr:housenumber":"cnr",
    "addr:postcode":"2760",
    "addr:street":"Forrester Rd & Wordoo St",
    "iso:country":"AU",
    "sg:address":"Cnr Forrester Rd & Wordoo St St",
    "sg:city":"Marys",
    "sg:classifiers":[
        {
            "category":"Autos & Motor Vehicles",
            "subcategory":"Auto Supplies",
            "type":"Retail Goods"
        }
    ],
    "sg:phone":"+61 2 9623 3411",
    "sg:postcode":"2760",
    "sg:province":"NSW",
    "sg:tags":[
        "wheel",
        "automotive",
        "rim"
    ],
    "wof:name":"Tyre Team",
    "wof:placetype":"venue"
},
  "geometry": {"coordinates":[150.776977539,-33.7487945557],"type":"Point"}
}