{
  "type": "Feature",
  "properties": {
    "addr:full":"Glenelg Rd Millthorpe NSW 2798",
    "addr:postcode":"2798",
    "addr:street":"Glenelg Rd",
    "iso:country":"AU",
    "sg:address":"Glenelg Rd",
    "sg:city":"Millthorpe",
    "sg:classifiers":[
        {
            "category":"Building & Trades",
            "subcategory":"Construction",
            "type":"Services"
        }
    ],
    "sg:phone":"+61 412 234 661",
    "sg:postcode":"2798",
    "sg:province":"NSW",
    "sg:tags":[
        "contractor"
    ],
    "wof:name":"Millthorpe Constructions",
    "wof:placetype":"venue"
},
  "geometry": {"coordinates":[149.1847229,-33.4460906982],"type":"Point"}
}