{
  "type": "Feature",
  "properties": {
    "iso:country":"AU",
    "sg:address":"333 Dromana Pde",
    "sg:city":"Safety Beach",
    "sg:classifiers":[
        {
            "category":"Autos & Motor Vehicles",
            "subcategory":"Boat Sales",
            "type":"Retail Goods"
        }
    ],
    "sg:phone":"+61 3 5987 2896",
    "sg:postcode":"3936",
    "sg:province":"VIC",
    "sg:tags":[
        "builder",
        "yacht",
        "repairer"
    ],
    "wof:name":"Evershine Detailing",
    "wof:placetype":"venue"
},
  "geometry": {"coordinates":[144.995925903,-38.3090362549],"type":"Point"}
}