{
  "type": "Feature",
  "properties": {
    "iso:country":"AU",
    "sg:address":"36 Prior St",
    "sg:city":"Charters Towers",
    "sg:classifiers":[
        {
            "category":"Personal",
            "subcategory":"Beauty Salon",
            "type":"Services"
        }
    ],
    "sg:phone":"+61 7 4787 3875",
    "sg:postcode":"4820",
    "sg:province":"QLD",
    "sg:tags":[
        "hairdresser"
    ],
    "wof:name":"Reginas Hair Plaits and Extensions",
    "wof:placetype":"venue"
},
  "geometry": {"coordinates":[146.263382,-20.064379],"type":"Point"}
}