{
  "type": "Feature",
  "properties": {
    "iso:country":"AU",
    "sg:address":"105 Main St",
    "sg:city":"Romsey",
    "sg:classifiers":[
        {
            "category":"Shopping",
            "type":"Retail Goods"
        }
    ],
    "sg:phone":"+61 3 5429 5728",
    "sg:postcode":"3434",
    "sg:province":"VIC",
    "sg:tags":[
        "produce",
        "grain"
    ],
    "wof:name":"Romsey Stockfeeds, Saddlery & Pet Barn",
    "wof:placetype":"venue"
},
  "geometry": {"coordinates":[144.74215698200001,-37.3483467102],"type":"Point"}
}