{
  "type": "Feature",
  "properties": {
    "iso:country":"AU",
    "sg:address":"99 Glenhaven Rd",
    "sg:city":"Glenhaven",
    "sg:classifiers":[
        {
            "category":"Retail",
            "subcategory":"Auto Repair",
            "type":"Services"
        }
    ],
    "sg:phone":"+61 2 9634 2988",
    "sg:postcode":"2156",
    "sg:province":"NSW",
    "sg:tags":[
        "transmission",
        "automotive",
        "car"
    ],
    "wof:name":"Glenhaven Automatic Transmissions",
    "wof:placetype":"venue"
},
  "geometry": {"coordinates":[150.99000549300001,-33.6964645386],"type":"Point"}
}