{
  "type": "Feature",
  "properties": {
    "addr:full":"32 Vinter Ave Croydon VIC 3136",
    "addr:housenumber":"32",
    "addr:postcode":"3136",
    "addr:street":"Vinter Ave",
    "iso:country":"AU",
    "sg:address":"32 Vinter Ave",
    "sg:city":"Croydon",
    "sg:classifiers":[
        {
            "category":"Building & Trades",
            "subcategory":"Landscaping Services",
            "type":"Services"
        }
    ],
    "sg:phone":"+61 3 9725 1700",
    "sg:postcode":"3136",
    "sg:province":"VIC",
    "sg:tags":[
        "consultant"
    ],
    "wof:name":"Home Pre-Purchase Inspection Service",
    "wof:placetype":"venue"
},
  "geometry": {"coordinates":[145.27593994099999,-37.8058395386],"type":"Point"}
}