{
  "type": "Feature",
  "properties": {
    "iso:country":"AU",
    "sg:address":"35 Halifax Drv",
    "sg:city":"Bunbury",
    "sg:classifiers":[
        {
            "category":"Retail",
            "subcategory":"Auto Repair",
            "type":"Services"
        }
    ],
    "sg:phone":"+61 1800 640 342",
    "sg:postcode":"6230",
    "sg:province":"WA",
    "sg:tags":[
        "body",
        "motor",
        "trimmer"
    ],
    "wof:name":"Keith Williams & Co.",
    "wof:placetype":"venue"
},
  "geometry": {"coordinates":[115.669952,-33.365738],"type":"Point"}
}