{
  "type": "Feature",
  "properties": {
    "addr:full":"Government Rd Stockport SA 5410",
    "addr:postcode":"5410",
    "addr:street":"Rd",
    "iso:country":"AU",
    "sg:address":"Government Rd",
    "sg:city":"Stockport",
    "sg:classifiers":[
        {
            "category":"Shopping",
            "subcategory":"Clothing, Apparel, & Fashions",
            "type":"Retail Goods"
        }
    ],
    "sg:phone":"+61 8 8528 2397",
    "sg:postcode":"5410",
    "sg:province":"SA",
    "sg:tags":[
        "style",
        "clothing",
        "western",
        "accessory"
    ],
    "wof:name":"BlueDog Jeans",
    "wof:placetype":"venue"
},
  "geometry": {"coordinates":[138.732345581,-34.3344802856],"type":"Point"}
}