{
  "type": "Feature",
  "properties": {
    "addr:full":"41- 55 Elliot Rd Dandenong VIC 3175",
    "addr:housenumber":"55",
    "addr:postcode":"3175",
    "addr:street":"Elliot Rd",
    "iso:country":"AU",
    "sg:address":"41- 55 Elliot Rd",
    "sg:city":"Dandenong",
    "sg:classifiers":[
        {
            "category":"Home & Garden",
            "subcategory":"Building Materials",
            "type":"Retail Goods"
        }
    ],
    "sg:phone":"+61 1300 274 784",
    "sg:postcode":"3175",
    "sg:province":"VIC",
    "sg:tags":[
        "tile",
        "roofing"
    ],
    "wof:name":"Pioneer Roof Tiles",
    "wof:placetype":"venue"
},
  "geometry": {"coordinates":[145.20426940900001,-38.0227546692],"type":"Point"}
}