{
  "type": "Feature",
  "properties": {
    "addr:full":"5 Gregory Street Sandy Bay TAS 7005",
    "addr:housenumber":"5",
    "addr:postcode":"7005",
    "addr:street":"Gregory Street",
    "iso:country":"AU",
    "sg:address":"5 Gregory Street",
    "sg:city":"Sandy Bay",
    "sg:classifiers":[
        {
            "category":"Restaurant",
            "type":"Food & Drink"
        }
    ],
    "sg:phone":"+61 3 6223 6648",
    "sg:postcode":"7005",
    "sg:province":"TAS",
    "sg:tags":[
        "pizza"
    ],
    "wof:name":"Waxed Bar & Restaurant",
    "wof:placetype":"venue"
},
  "geometry": {"coordinates":[147.327301025,-42.8955726624],"type":"Point"}
}