{
  "type": "Feature",
  "properties": {
    "addr:full":"570 The Entrance Rd Bateau Bay NSW 2261",
    "addr:housenumber":"570",
    "addr:postcode":"2261",
    "addr:street":"The Entrance Rd",
    "iso:country":"AU",
    "sg:address":"570 The Entrance Rd",
    "sg:city":"Bateau Bay",
    "sg:classifiers":[
        {
            "category":"Real Estate",
            "subcategory":"Real Estate Agent",
            "type":"Services"
        }
    ],
    "sg:phone":"+61 2 4332 3777",
    "sg:postcode":"2261",
    "sg:province":"NSW",
    "wof:name":"Bateau Bay Real Estate",
    "wof:placetype":"venue"
},
  "geometry": {"coordinates":[151.473343,-33.389172],"type":"Point"}
}