{
  "type": "Feature",
  "properties": {
    "addr:full":"12 Loftus St Hall ACT 2618",
    "addr:housenumber":"12",
    "addr:postcode":"2618",
    "addr:street":"Loftus St",
    "iso:country":"AU",
    "sg:address":"12 Loftus St",
    "sg:city":"Hall",
    "sg:classifiers":[
        {
            "category":"Utilities",
            "subcategory":"Electric",
            "type":"Services"
        }
    ],
    "sg:phone":"+61 408 644 144",
    "sg:postcode":"2618",
    "sg:province":"ACT",
    "sg:tags":[
        "electrical",
        "contractor"
    ],
    "wof:name":"Greenwood Dennis",
    "wof:placetype":"venue"
},
  "geometry": {"coordinates":[149.06834411599999,-35.1698799133],"type":"Point"}
}