{
  "type": "Feature",
  "properties": {
    "addr:full":"1 Ross St South Melbourne VIC 3205",
    "addr:housenumber":"1",
    "addr:postcode":"3205",
    "addr:street":"Ross St",
    "iso:country":"AU",
    "sg:address":"1 Ross St",
    "sg:city":"South Melbourne",
    "sg:classifiers":[
        {
            "category":"Retail",
            "subcategory":"Auto Repair",
            "type":"Services"
        }
    ],
    "sg:phone":"+61 3 9645 0022",
    "sg:postcode":"3205",
    "sg:province":"VIC",
    "sg:tags":[
        "repairer",
        "motor",
        "engineer"
    ],
    "wof:name":"Motion Automotive",
    "wof:placetype":"venue"
},
  "geometry": {"coordinates":[144.961533,-37.829708],"type":"Point"}
}