{
  "type": "Feature",
  "properties": {
    "iso:country":"AU",
    "sg:address":"443a Willarong Rd",
    "sg:city":"Caringbah",
    "sg:classifiers":[
        {
            "category":"Utilities",
            "subcategory":"Electric",
            "type":"Services"
        }
    ],
    "sg:phone":"+61 2 9531 2317",
    "sg:postcode":"2229",
    "sg:province":"NSW",
    "sg:tags":[
        "electrical",
        "contractor"
    ],
    "wof:name":"I G M A Electrical",
    "wof:placetype":"venue"
},
  "geometry": {"coordinates":[151.11054992699999,-34.0579986572],"type":"Point"}
}