{
  "type": "Feature",
  "properties": {
    "addr:full":"263 Lygon St Carlton VIC 3053",
    "addr:housenumber":"263",
    "addr:postcode":"3053",
    "addr:street":"Lygon St",
    "iso:country":"AU",
    "sg:address":"263 Lygon St",
    "sg:city":"Carlton",
    "sg:classifiers":[
        {
            "category":"Deli",
            "type":"Food & Drink"
        }
    ],
    "sg:phone":"+61 3 9347 6279",
    "sg:postcode":"3053",
    "sg:province":"VIC",
    "sg:tags":[
        "delicatessen"
    ],
    "wof:name":"Lygon Foodstore",
    "wof:placetype":"venue"
},
  "geometry": {"coordinates":[144.96702575699999,-37.7992286682],"type":"Point"}
}