{
  "type": "Feature",
  "properties": {
    "addr:full":"8 Lampton Ave Derwent Park TAS 7009",
    "addr:housenumber":"8",
    "addr:postcode":"7009",
    "addr:street":"Lampton Ave",
    "iso:country":"AU",
    "sg:address":"8 Lampton Ave",
    "sg:city":"Derwent Park",
    "sg:classifiers":[
        {
            "category":"Professional",
            "subcategory":"Business Services",
            "type":"Services"
        }
    ],
    "sg:phone":"+61 13 25 54",
    "sg:postcode":"7009",
    "sg:province":"TAS",
    "sg:tags":[
        "record",
        "management",
        "storage"
    ],
    "wof:name":"Pickfords Records & Information Managers",
    "wof:placetype":"venue"
},
  "geometry": {"coordinates":[147.290771484,-42.8352279663],"type":"Point"}
}