{
  "type": "Feature",
  "properties": {
    "addr:full":"1/ 48 Bullockhead St Sumner Park QLD 4074",
    "addr:housenumber":"/ 48",
    "addr:postcode":"4074",
    "addr:street":"Bullockhead St",
    "iso:country":"AU",
    "sg:address":"1/ 48 Bullockhead St",
    "sg:city":"Sumner Park",
    "sg:classifiers":[
        {
            "category":"Building & Trades",
            "subcategory":"Construction",
            "type":"Services"
        }
    ],
    "sg:phone":"+61 7 3376 5777",
    "sg:postcode":"4074",
    "sg:province":"QLD",
    "sg:tags":[
        "installation",
        "air conditioning"
    ],
    "wof:name":"Bill Norris Air-Conditioning",
    "wof:placetype":"venue"
},
  "geometry": {"coordinates":[152.93934631400001,-27.5663928986],"type":"Point"}
}