{
  "type": "Feature",
  "properties": {
    "iso:country":"AU",
    "sg:address":"26 Aberdeen Crt",
    "sg:city":"South Launceston",
    "sg:classifiers":[
        {
            "category":"Real Estate",
            "subcategory":"Architect",
            "type":"Services"
        }
    ],
    "sg:phone":"+61 3 6343 0295",
    "sg:postcode":"7249",
    "sg:province":"TAS",
    "sg:tags":[
        "building",
        "designer"
    ],
    "wof:name":"MDE Building Designs",
    "wof:placetype":"venue"
},
  "geometry": {"coordinates":[147.135955811,-41.4561653137],"type":"Point"}
}