{
  "type": "Feature",
  "properties": {
    "addr:full":"18 Thompsons Rd Newborough VIC 3825",
    "addr:housenumber":"18",
    "addr:postcode":"3825",
    "addr:street":"Thompsons Rd",
    "iso:country":"AU",
    "sg:address":"18 Thompsons Rd",
    "sg:city":"Newborough",
    "sg:classifiers":[
        {
            "category":"Farming",
            "subcategory":"Poultry Farm",
            "type":"Manufacturing & Wholesale Goods"
        }
    ],
    "sg:phone":"+61 3 5127 3760",
    "sg:postcode":"3825",
    "sg:province":"VIC",
    "sg:tags":[
        "farmer"
    ],
    "wof:name":"Ritz Poultry Farm",
    "wof:placetype":"venue"
},
  "geometry": {"coordinates":[146.28909300000001,-38.170563],"type":"Point"}
}