{
  "type": "Feature",
  "properties": {
    "iso:country":"AU",
    "sg:address":"Unit 4/ 32 Investigator Drv",
    "sg:city":"Unanderra",
    "sg:classifiers":[
        {
            "category":"Home & Garden",
            "subcategory":"Home Furnishings",
            "type":"Retail Goods"
        }
    ],
    "sg:phone":"+61 2 4272 7177",
    "sg:postcode":"2526",
    "sg:province":"NSW",
    "sg:tags":[
        "shower",
        "screen"
    ],
    "wof:name":"Leisure Coast Wardrobes Pty Ltd",
    "wof:placetype":"venue"
},
  "geometry": {"coordinates":[150.843261719,-34.4617729187],"type":"Point"}
}