{
  "type": "Feature",
  "properties": {
    "iso:country":"AU",
    "sg:address":"Level 10/ 12 St",
    "sg:city":"Georges Tce Perth",
    "sg:classifiers":[
        {
            "category":"Banks & Credit Unions",
            "subcategory":"Investment Brokerage",
            "type":"Services"
        }
    ],
    "sg:phone":"+61 8 9325 4099",
    "sg:postcode":"6000",
    "sg:province":"WA",
    "sg:tags":[
        "debt",
        "collection"
    ],
    "wof:name":"Beukhen & Pokhrell",
    "wof:placetype":"venue"
},
  "geometry": {"coordinates":[115.86441803,-31.9571075439],"type":"Point"}
}