{
  "type": "Feature",
  "properties": {
    "addr:full":"Factory F 20 Burgess Rd Bayswater VIC 3153",
    "addr:housenumber":"20",
    "addr:postcode":"3153",
    "addr:street":"Burgess Rd",
    "iso:country":"AU",
    "sg:address":"Factory F 20 Burgess Rd",
    "sg:city":"Bayswater",
    "sg:classifiers":[
        {
            "category":"Home & Garden",
            "subcategory":"Hardware",
            "type":"Retail Goods"
        }
    ],
    "sg:phone":"+61 3 9761 5691",
    "sg:postcode":"3153",
    "sg:province":"VIC",
    "sg:tags":[
        "plumber",
        "supply"
    ],
    "wof:name":"Austworld Commodities Pty Ltd",
    "wof:placetype":"venue"
},
  "geometry": {"coordinates":[145.28901672399999,-37.8223876953],"type":"Point"}
}