{
  "type": "Feature",
  "properties": {
    "addr:full":"5 Second Ave Jannali NSW 2226",
    "addr:housenumber":"5",
    "addr:postcode":"2226",
    "addr:street":"Second Ave",
    "iso:country":"AU",
    "sg:address":"5 Second Ave",
    "sg:city":"Jannali",
    "sg:classifiers":[
        {
            "category":"Utilities",
            "subcategory":"Electric",
            "type":"Services"
        }
    ],
    "sg:phone":"+61 2 9589 3069",
    "sg:postcode":"2226",
    "sg:province":"NSW",
    "sg:tags":[
        "electrical",
        "contractor"
    ],
    "wof:name":"G H & J A Electric",
    "wof:placetype":"venue"
},
  "geometry": {"coordinates":[151.07125854500001,-34.0139846802],"type":"Point"}
}