{
  "type": "Feature",
  "properties": {
    "addr:full":"Joondalup Shopping Centre Joondalup Drv Joondalup WA 6027",
    "addr:postcode":"6027",
    "addr:street":"Joondalup Drv",
    "iso:country":"AU",
    "sg:address":"Joondalup Shopping Centre Joondalup Drv",
    "sg:city":"Joondalup",
    "sg:classifiers":[
        {
            "category":"Shopping",
            "subcategory":"Shoes",
            "type":"Retail Goods"
        }
    ],
    "sg:phone":"+61 8 9300 3744",
    "sg:postcode":"6027",
    "sg:province":"WA",
    "sg:tags":[
        "footwear"
    ],
    "wof:name":"Betts",
    "wof:placetype":"venue"
},
  "geometry": {"coordinates":[115.764228821,-31.7353992462],"type":"Point"}
}