{
  "type": "Feature",
  "properties": {
    "addr:full":"372 Berwick St East Victoria Park WA 6101",
    "addr:housenumber":"372",
    "addr:postcode":"6101",
    "addr:street":"Berwick St",
    "iso:country":"AU",
    "sg:address":"372 Berwick St",
    "sg:city":"East Victoria Park",
    "sg:classifiers":[
        {
            "category":"Manufacturing",
            "subcategory":"Food",
            "type":"Manufacturing & Wholesale Goods"
        }
    ],
    "sg:phone":"+61 8 9361 8875",
    "sg:postcode":"6101",
    "sg:province":"WA",
    "sg:tags":[
        "function",
        "catering"
    ],
    "wof:name":"Indonesian Catering",
    "wof:placetype":"venue"
},
  "geometry": {"coordinates":[115.905158997,-31.993347168],"type":"Point"}
}