{
  "type": "Feature",
  "properties": {
    "addr:full":"Suite 4 15-17 Kildare Rd Blacktown NSW 2148",
    "addr:housenumber":"15-17",
    "addr:postcode":"2148",
    "addr:street":"Kildare Rd",
    "iso:country":"AU",
    "sg:address":"Suite 4 15-17 Kildare Rd",
    "sg:city":"Blacktown",
    "sg:classifiers":[
        {
            "category":"Health Services",
            "subcategory":"Doctor",
            "type":"Services"
        }
    ],
    "sg:phone":"+61 2 9676 8933",
    "sg:postcode":"2148",
    "sg:province":"NSW",
    "sg:tags":[
        "medical",
        "practitioner"
    ],
    "wof:name":"Cranswick Richard Dr",
    "wof:placetype":"venue"
},
  "geometry": {"coordinates":[150.90510559099999,-33.7687606812],"type":"Point"}
}