{
  "type": "Feature",
  "properties": {
    "addr:full":"9/ 9 Brooklyn Ave Dandenong VIC 3175",
    "addr:housenumber":"/ 9",
    "addr:postcode":"3175",
    "addr:street":"Brooklyn Ave",
    "iso:country":"AU",
    "sg:address":"9/ 9 Brooklyn Ave",
    "sg:city":"Dandenong",
    "sg:classifiers":[
        {
            "category":"Retail",
            "subcategory":"Auto Repair",
            "type":"Services"
        }
    ],
    "sg:phone":"+61 3 9794 8577",
    "sg:postcode":"3175",
    "sg:province":"VIC",
    "sg:tags":[
        "engine",
        "reconditioning"
    ],
    "wof:name":"Headmaster Cylinder Head Services",
    "wof:placetype":"venue"
},
  "geometry": {"coordinates":[145.19760131800001,-37.993637085],"type":"Point"}
}