{
  "type": "Feature",
  "properties": {
    "iso:country":"AU",
    "sg:address":"Caringbah Rd",
    "sg:city":"Caringbah",
    "sg:classifiers":[
        {
            "category":"Education",
            "subcategory":"School",
            "type":"Public Place"
        }
    ],
    "sg:phone":"+61 2 9524 3752",
    "sg:postcode":"2229",
    "sg:province":"NSW",
    "sg:tags":[
        "state",
        "-",
        "nsw"
    ],
    "wof:name":"Laguna Street Public School",
    "wof:placetype":"venue"
},
  "geometry": {"coordinates":[151.12147522000001,-34.0465011597],"type":"Point"}
}