{
  "type": "Feature",
  "properties": {
    "addr:full":"365 The Northern Rd Londonderry NSW 2753",
    "addr:housenumber":"365",
    "addr:postcode":"2753",
    "addr:street":"The Northern Rd",
    "iso:country":"AU",
    "sg:address":"365 The Northern Rd",
    "sg:city":"Londonderry",
    "sg:classifiers":[
        {
            "category":"Building & Trades",
            "subcategory":"Construction",
            "type":"Services"
        }
    ],
    "sg:phone":"+61 2 4777 4110",
    "sg:postcode":"2753",
    "sg:province":"NSW",
    "sg:tags":[
        "contractor"
    ],
    "wof:name":"Leard G V",
    "wof:placetype":"venue"
},
  "geometry": {"coordinates":[150.758377075,-33.6649856567],"type":"Point"}
}