{
  "type": "Feature",
  "properties": {
    "addr:full":"Unit 48. Fyshwick Centre Wollongong St Fyshwick ACT 2609",
    "addr:postcode":"2609",
    "addr:street":"Wollongong St",
    "iso:country":"AU",
    "sg:address":"Unit 48. Fyshwick Centre Wollongong St",
    "sg:city":"Fyshwick",
    "sg:classifiers":[
        {
            "category":"Travel",
            "subcategory":"Travel Agent",
            "type":"Entertainment"
        }
    ],
    "sg:phone":"+61 13 18 66",
    "sg:postcode":"2609",
    "sg:province":"ACT",
    "sg:tags":[
        "consultant"
    ],
    "wof:name":"Flight Centre",
    "wof:placetype":"venue"
},
  "geometry": {"coordinates":[149.17758178700001,-35.3275680542],"type":"Point"}
}