{
  "type": "Feature",
  "properties": {
    "addr:full":"338 Highett Rd Highett VIC 3190",
    "addr:housenumber":"338",
    "addr:postcode":"3190",
    "addr:street":"Highett Rd",
    "iso:country":"AU",
    "sg:address":"338 Highett Rd",
    "sg:city":"Highett",
    "sg:classifiers":[
        {
            "category":"Fast Food",
            "type":"Food & Drink"
        }
    ],
    "sg:phone":"+61 3 9553 4886",
    "sg:postcode":"3190",
    "sg:province":"VIC",
    "sg:tags":[
        "away",
        "take"
    ],
    "wof:name":"Demarconis Pizza & Pasta",
    "wof:placetype":"venue"
},
  "geometry": {"coordinates":[145.044067383,-37.9491043091],"type":"Point"}
}