{
  "type": "Feature",
  "properties": {
    "addr:full":"491 Forest Rd Penshurst NSW 2222",
    "addr:housenumber":"491",
    "addr:postcode":"2222",
    "addr:street":"Forest Rd",
    "iso:country":"AU",
    "sg:address":"491 Forest Rd",
    "sg:city":"Penshurst",
    "sg:classifiers":[
        {
            "category":"Shopping",
            "subcategory":"Computers & Home Electronics",
            "type":"Retail Goods"
        }
    ],
    "sg:phone":"+61 2 9580 9888",
    "sg:postcode":"2222",
    "sg:province":"NSW",
    "sg:tags":[
        "hire",
        "video",
        "game"
    ],
    "wof:name":"Gamesmen The",
    "wof:placetype":"venue"
},
  "geometry": {"coordinates":[151.07949829099999,-33.9622535706],"type":"Point"}
}