{
  "type": "Feature",
  "properties": {
    "iso:country":"AU",
    "sg:address":"Unit 11/ 40 Bowman St",
    "sg:city":"Richmond",
    "sg:classifiers":[
        {
            "category":"Retail",
            "subcategory":"Car Wash",
            "type":"Services"
        }
    ],
    "sg:phone":"+61 2 4578 7888",
    "sg:postcode":"2753",
    "sg:province":"NSW",
    "sg:tags":[
        "truck",
        "cleaning"
    ],
    "wof:name":"Hawkesbury Auto Detailing & Carwash",
    "wof:placetype":"venue"
},
  "geometry": {"coordinates":[150.765426636,-33.6000442505],"type":"Point"}
}