{
  "type": "Feature",
  "properties": {
    "addr:full":"22a Rogers St Spring Hill QLD 4000",
    "addr:housenumber":"22a",
    "addr:postcode":"4000",
    "addr:street":"Rogers St",
    "iso:country":"AU",
    "sg:address":"22a Rogers St",
    "sg:city":"Spring Hill",
    "sg:classifiers":[
        {
            "category":"Professional",
            "subcategory":"Employment Agencies",
            "type":"Services"
        }
    ],
    "sg:phone":"+61 7 3832 5177",
    "sg:postcode":"4000",
    "sg:province":"QLD",
    "sg:tags":[
        "provider",
        "internet"
    ],
    "wof:name":"Matrix Mouse",
    "wof:placetype":"venue"
},
  "geometry": {"coordinates":[153.027145386,-27.4596347809],"type":"Point"}
}