{
  "type": "Feature",
  "properties": {
    "addr:full":"29 Box Rd Casula NSW 2170",
    "addr:housenumber":"29",
    "addr:postcode":"2170",
    "addr:street":"Box Rd",
    "iso:country":"AU",
    "sg:address":"29 Box Rd",
    "sg:city":"Casula",
    "sg:classifiers":[
        {
            "category":"Professional",
            "subcategory":"Detective & Security Services",
            "type":"Services"
        }
    ],
    "sg:phone":"+61 2 9587 6671",
    "sg:postcode":"2170",
    "sg:province":"NSW",
    "sg:tags":[
        "consultant",
        "system"
    ],
    "wof:name":"Black Line Protection",
    "wof:placetype":"venue"
},
  "geometry": {"coordinates":[150.89047241200001,-33.9508247375],"type":"Point"}
}