{
  "type": "Feature",
  "properties": {
    "addr:full":"2 Durdans Ave Roseberry NSW 2474",
    "addr:housenumber":"2",
    "addr:postcode":"2474",
    "addr:street":"Durdans Ave",
    "iso:country":"AU",
    "sg:address":"2 Durdans Ave",
    "sg:city":"Roseberry",
    "sg:classifiers":[
        {
            "category":"Wholesale",
            "subcategory":"Machinery & Supplies",
            "type":"Manufacturing & Wholesale Goods"
        }
    ],
    "sg:phone":"+61 2 9313 4013",
    "sg:postcode":"2474",
    "sg:province":"NSW",
    "sg:tags":[
        "instrument"
    ],
    "wof:name":"Alsop John H Engineering Pty Ltd",
    "wof:placetype":"venue"
},
  "geometry": {"coordinates":[152.91421508799999,-28.4815502167],"type":"Point"}
}