{
  "type": "Feature",
  "properties": {
    "iso:country":"AU",
    "sg:address":"25 North Creek Rd",
    "sg:city":"Ballina",
    "sg:classifiers":[
        {
            "category":"Professional",
            "subcategory":"Printing & Photocopies",
            "type":"Services"
        }
    ],
    "sg:phone":"+61 2 6686 5266",
    "sg:postcode":"2478",
    "sg:province":"NSW",
    "sg:tags":[
        "photocopier"
    ],
    "wof:name":"Ricoh Ballina",
    "wof:placetype":"venue"
},
  "geometry": {"coordinates":[153.55581665,-28.8496932983],"type":"Point"}
}