{
  "type": "Feature",
  "properties": {
    "iso:country":"AU",
    "sg:address":"15 Meadowview Drv",
    "sg:city":"Morayfield",
    "sg:classifiers":[
        {
            "category":"Building & Trades",
            "subcategory":"Cleaning & Sanitation",
            "type":"Services"
        }
    ],
    "sg:phone":"+61 408 538 587",
    "sg:postcode":"4506",
    "sg:province":"QLD",
    "sg:tags":[
        "window"
    ],
    "wof:name":"K C Window Cleaning",
    "wof:placetype":"venue"
},
  "geometry": {"coordinates":[152.96432495100001,-27.114490509],"type":"Point"}
}