{
  "type": "Feature",
  "properties": {
    "addr:full":"3 Dalton St Forbes NSW 2871",
    "addr:housenumber":"3",
    "addr:postcode":"2871",
    "addr:street":"Dalton St",
    "iso:country":"AU",
    "sg:address":"3 Dalton St",
    "sg:city":"Forbes",
    "sg:classifiers":[
        {
            "category":"Home & Garden",
            "subcategory":"Household Appliances",
            "type":"Retail Goods"
        }
    ],
    "sg:phone":"+61 428 921 016",
    "sg:postcode":"2871",
    "sg:province":"NSW",
    "sg:tags":[
        "equipment",
        "gas"
    ],
    "wof:name":"Adept Plumbing Services",
    "wof:placetype":"venue"
},
  "geometry": {"coordinates":[148.008835,-33.378059],"type":"Point"}
}