{
  "type": "Feature",
  "properties": {
    "addr:full":"Shp1/ 110 Queen St Campbelltown NSW 2560",
    "addr:housenumber":"110",
    "addr:postcode":"2560",
    "addr:street":"Queen St",
    "iso:country":"AU",
    "sg:address":"Shp1/ 110 Queen St",
    "sg:city":"Campbelltown",
    "sg:classifiers":[
        {
            "category":"Shopping",
            "subcategory":"Clothing, Apparel, & Fashions",
            "type":"Retail Goods"
        }
    ],
    "sg:phone":"+61 2 4627 2552",
    "sg:postcode":"2560",
    "sg:province":"NSW",
    "sg:tags":[
        "lady",
        "wear"
    ],
    "wof:name":"Lyba Design & Spices",
    "wof:placetype":"venue"
},
  "geometry": {"coordinates":[150.81654357900001,-34.0643806458],"type":"Point"}
}