{
  "type": "Feature",
  "properties": {
    "addr:full":"64 Morgan St Bellbird Park QLD 4300",
    "addr:housenumber":"64",
    "addr:postcode":"4300",
    "addr:street":"Morgan St",
    "iso:country":"AU",
    "sg:address":"64 Morgan St",
    "sg:city":"Bellbird Park",
    "sg:classifiers":[
        {
            "category":"Manufacturing",
            "subcategory":"Tools & Machinery",
            "type":"Manufacturing & Wholesale Goods"
        }
    ],
    "sg:phone":"+61 7 3814 4025",
    "sg:postcode":"4300",
    "sg:province":"QLD",
    "wof:name":"Take Away Tools",
    "wof:placetype":"venue"
},
  "geometry": {"coordinates":[152.879394531,-27.634759903],"type":"Point"}
}