{
  "type": "Feature",
  "properties": {
    "iso:country":"AU",
    "sg:address":"PO Box 261",
    "sg:city":"Fairy Meadow",
    "sg:classifiers":[
        {
            "category":"Arts & Performance",
            "subcategory":"Music",
            "type":"Entertainment"
        }
    ],
    "sg:phone":"+61 402 558 887",
    "sg:postcode":"2519",
    "sg:province":"NSW",
    "sg:tags":[
        "mobile",
        "jockey",
        "disc"
    ],
    "wof:name":"MP Entertainment",
    "wof:placetype":"venue"
},
  "geometry": {"coordinates":[150.893326,-34.39167],"type":"Point"}
}