{
  "type": "Feature",
  "properties": {
    "addr:full":"4 McGrath Ave Nowra NSW 2541",
    "addr:housenumber":"4",
    "addr:postcode":"2541",
    "addr:street":"Mcgrath Ave",
    "iso:country":"AU",
    "sg:address":"4 McGrath Ave",
    "sg:city":"Nowra",
    "sg:classifiers":[
        {
            "category":"Health Services",
            "subcategory":"Doctor",
            "type":"Services"
        }
    ],
    "sg:phone":"+61 2 4422 1210",
    "sg:postcode":"2541",
    "sg:province":"NSW",
    "sg:tags":[
        "medical",
        "practitioner"
    ],
    "wof:name":"McCartney V G",
    "wof:placetype":"venue"
},
  "geometry": {"coordinates":[150.603225708,-34.8717308044],"type":"Point"}
}