{
  "type": "Feature",
  "properties": {
    "addr:full":"62 Lawson Pde Highett VIC 3190",
    "addr:housenumber":"62",
    "addr:postcode":"3190",
    "addr:street":"Lawson Pde",
    "iso:country":"AU",
    "sg:address":"62 Lawson Pde",
    "sg:city":"Highett",
    "sg:classifiers":[
        {
            "category":"Home & Garden",
            "subcategory":"Building Materials",
            "type":"Retail Goods"
        }
    ],
    "sg:phone":"+61 3 9502 0443",
    "sg:postcode":"3190",
    "sg:province":"VIC",
    "sg:tags":[
        "lawn",
        "cutting",
        "maintenance"
    ],
    "wof:name":"Tony Martino Lawnmowing & Garden Care",
    "wof:placetype":"venue"
},
  "geometry": {"coordinates":[145.028274536,-37.9529151917],"type":"Point"}
}