{
  "type": "Feature",
  "properties": {
    "iso:country":"AU",
    "sg:address":"5/ 3422 Gold Coast Hwy",
    "sg:city":"Surfers Paradise",
    "sg:classifiers":[
        {
            "category":"Insurance",
            "subcategory":"Hazard Insurance",
            "type":"Services"
        }
    ],
    "sg:phone":"+61 7 5538 1992",
    "sg:postcode":"4217",
    "sg:province":"QLD",
    "sg:tags":[
        "loss",
        "adjuster",
        "assessor"
    ],
    "wof:name":"G.R McIntyre & Assoc",
    "wof:placetype":"venue"
},
  "geometry": {"coordinates":[153.42953491200001,-28.0110912323],"type":"Point"}
}