{
  "type": "Feature",
  "properties": {
    "iso:country":"AU",
    "sg:address":"57 Oceanic Drv",
    "sg:city":"Floreat",
    "sg:classifiers":[
        {
            "category":"Professional",
            "subcategory":"Art Services",
            "type":"Services"
        }
    ],
    "sg:phone":"+61 8 9287 1644",
    "sg:postcode":"6014",
    "sg:province":"WA",
    "sg:tags":[
        "graphic",
        "designer"
    ],
    "wof:name":"Gameren & Hobbs",
    "wof:placetype":"venue"
},
  "geometry": {"coordinates":[115.79344940199999,-31.9405574799],"type":"Point"}
}