{
  "type": "Feature",
  "properties": {
    "addr:full":"Nash Rd Bunyip VIC 3815",
    "addr:postcode":"3815",
    "addr:street":"Nash Rd",
    "iso:country":"AU",
    "sg:address":"Nash Rd",
    "sg:city":"Bunyip",
    "sg:classifiers":[
        {
            "category":"Social Services",
            "subcategory":"Child Care",
            "type":"Services"
        }
    ],
    "sg:phone":"+61 3 5629 5594",
    "sg:postcode":"3815",
    "sg:province":"VIC",
    "sg:tags":[
        "support",
        "health"
    ],
    "wof:name":"Maternal & Child Health Centres",
    "wof:placetype":"venue"
},
  "geometry": {"coordinates":[145.72230500000001,-38.079552],"type":"Point"}
}