{
  "type": "Feature",
  "properties": {
    "addr:full":"Level 10, 443 Toorak Rd Toorak VIC 3142",
    "addr:housenumber":"443",
    "addr:postcode":"3142",
    "addr:street":"Toorak Rd",
    "iso:country":"AU",
    "sg:address":"Level 10, 443 Toorak Rd",
    "sg:city":"Toorak",
    "sg:classifiers":[
        {
            "category":"Professional",
            "subcategory":"Management & Consulting",
            "type":"Services"
        }
    ],
    "sg:phone":"+61 3 9637 7373",
    "sg:postcode":"3142",
    "sg:province":"VIC",
    "sg:tags":[
        "consultant"
    ],
    "wof:name":"Essential Support Services",
    "wof:placetype":"venue"
},
  "geometry": {"coordinates":[145.007720947,-37.8408088684],"type":"Point"}
}