{
  "type": "Feature",
  "properties": {
    "iso:country":"AU",
    "sg:address":"9 Rudder St",
    "sg:city":"Kempsey",
    "sg:classifiers":[
        {
            "category":"Professional",
            "type":"Services"
        }
    ],
    "sg:phone":"+61 402 079 153",
    "sg:postcode":"2440",
    "sg:province":"NSW",
    "sg:tags":[
        "transport"
    ],
    "wof:name":"Peter Samyia Transport",
    "wof:placetype":"venue"
},
  "geometry": {"coordinates":[152.846603,-31.080986],"type":"Point"}
}