{
  "type": "Feature",
  "properties": {
    "iso:country":"AU",
    "sg:address":"PO Box 814",
    "sg:city":"Ocean Grove",
    "sg:classifiers":[
        {
            "category":"Home & Garden",
            "subcategory":"Hardware",
            "type":"Retail Goods"
        }
    ],
    "sg:phone":"+61 418 333 013",
    "sg:postcode":"3226",
    "sg:province":"VIC",
    "sg:tags":[
        "repair",
        "tool",
        "power"
    ],
    "wof:name":"Elec-Test Pty Ltd",
    "wof:placetype":"venue"
},
  "geometry": {"coordinates":[144.538101,-38.265339],"type":"Point"}
}