{
  "type": "Feature",
  "properties": {
    "addr:full":"527 Bridge Rd Richmond VIC 3121",
    "addr:housenumber":"527",
    "addr:postcode":"3121",
    "addr:street":"Bridge Rd",
    "iso:country":"AU",
    "sg:address":"527 Bridge Rd",
    "sg:city":"Richmond",
    "sg:classifiers":[
        {
            "category":"Travel",
            "subcategory":"Hotels & Motels",
            "type":"Entertainment"
        }
    ],
    "sg:phone":"+61 3 9428 4200",
    "sg:postcode":"3121",
    "sg:province":"VIC",
    "sg:tags":[
        "pub"
    ],
    "wof:name":"Royal Oak Richmond",
    "wof:placetype":"venue"
},
  "geometry": {"coordinates":[145.00845336899999,-37.8193740845],"type":"Point"}
}