{
  "type": "Feature",
  "properties": {
    "addr:full":"446 Darling St Cheltenham NSW 2119",
    "addr:housenumber":"446",
    "addr:postcode":"2119",
    "addr:street":"Darling St",
    "iso:country":"AU",
    "sg:address":"446 Darling St",
    "sg:city":"Cheltenham",
    "sg:classifiers":[
        {
            "category":"Banks & Credit Unions",
            "subcategory":"Bureau De Change",
            "type":"Services"
        }
    ],
    "sg:phone":"+61 405 753 805",
    "sg:postcode":"2119",
    "sg:province":"NSW",
    "sg:tags":[
        "motorised",
        "scooter"
    ],
    "wof:name":"Zoot Scooters Bikes Pty Ltd",
    "wof:placetype":"venue"
},
  "geometry": {"coordinates":[151.07943725600001,-33.7558517456],"type":"Point"}
}