{
  "type": "Feature",
  "properties": {
    "addr:full":"729 Heidelberg Rd Alphington VIC 3078",
    "addr:housenumber":"729",
    "addr:postcode":"3078",
    "addr:street":"Heidelberg Rd",
    "iso:country":"AU",
    "sg:address":"729 Heidelberg Rd",
    "sg:city":"Alphington",
    "sg:classifiers":[
        {
            "category":"Food & Beverages",
            "subcategory":"Specialty",
            "type":"Retail Goods"
        }
    ],
    "sg:phone":"+61 3 9499 3328",
    "sg:postcode":"3078",
    "sg:province":"VIC",
    "sg:tags":[
        "product",
        "health"
    ],
    "wof:name":"Destination Health Foods",
    "wof:placetype":"venue"
},
  "geometry": {"coordinates":[145.03077697800001,-37.7806968689],"type":"Point"}
}