{
  "type": "Feature",
  "properties": {
    "addr:full":"415 A King St Newtown NSW 2042",
    "addr:housenumber":"415 a",
    "addr:postcode":"2042",
    "addr:street":"King St",
    "iso:country":"AU",
    "sg:address":"415 A King St",
    "sg:city":"Newtown",
    "sg:classifiers":[
        {
            "category":"Internet Cafe",
            "subcategory":"None",
            "type":"Food & Drink"
        }
    ],
    "sg:phone":"+61 2 9517 4726",
    "sg:postcode":"2042",
    "sg:province":"NSW",
    "wof:name":"Connect On King",
    "wof:placetype":"venue"
},
  "geometry": {"coordinates":[151.17785599999999,-33.898899],"type":"Point"}
}