{
  "type": "Feature",
  "properties": {
    "addr:full":"500 Oxford St Bondi NSW 2026",
    "addr:housenumber":"500",
    "addr:postcode":"2026",
    "addr:street":"Oxford St",
    "iso:country":"AU",
    "sg:address":"500 Oxford St",
    "sg:city":"Bondi",
    "sg:classifiers":[
        {
            "category":"Shopping",
            "subcategory":"Mobile Phones",
            "type":"Retail Goods"
        }
    ],
    "sg:phone":"+61 2 8753 3302",
    "sg:postcode":"2026",
    "sg:province":"NSW",
    "sg:tags":[
        "telephone",
        "accessory"
    ],
    "wof:name":"Vodafone",
    "wof:placetype":"venue"
},
  "geometry": {"coordinates":[151.26303100600001,-33.8938102722],"type":"Point"}
}