{
  "type": "Feature",
  "properties": {
    "addr:full":"3rd Floor 200 Lygon St Carlton VIC 3053",
    "addr:housenumber":"200",
    "addr:postcode":"3053",
    "addr:street":"Lygon St",
    "iso:country":"AU",
    "sg:address":"3rd Floor 200 Lygon St",
    "sg:city":"Carlton",
    "sg:classifiers":[
        {
            "category":"Health Services",
            "subcategory":"Chiropractor",
            "type":"Services"
        }
    ],
    "sg:phone":"+61 3 9399 9322",
    "sg:postcode":"3053",
    "sg:province":"VIC",
    "wof:name":"Hines Greg",
    "wof:placetype":"venue"
},
  "geometry": {"coordinates":[144.96676635700001,-37.8025131226],"type":"Point"}
}