{
  "type": "Feature",
  "properties": {
    "iso:country":"AU",
    "sg:address":"20 Melba Ave",
    "sg:city":"Sunbury",
    "sg:classifiers":[
        {
            "category":"Personal",
            "subcategory":"Beauty Salon",
            "type":"Services"
        }
    ],
    "sg:phone":"+61 3 9740 5811",
    "sg:postcode":"3429",
    "sg:province":"VIC",
    "sg:tags":[
        "hairdresser"
    ],
    "wof:name":"Head Over Heels Hairdressing",
    "wof:placetype":"venue"
},
  "geometry": {"coordinates":[144.70558166500001,-37.5741348267],"type":"Point"}
}