{
  "type": "Feature",
  "properties": {
    "iso:country":"AU",
    "sg:address":"243 Stirling Hwy",
    "sg:city":"Claremont",
    "sg:classifiers":[
        {
            "category":"Education",
            "subcategory":"Dance Studio",
            "type":"Public Place"
        }
    ],
    "sg:phone":"+61 8 9384 8886",
    "sg:postcode":"6010",
    "sg:province":"WA",
    "sg:tags":[
        "venue",
        "tuition"
    ],
    "wof:name":"Alhambra Bellty Dance Academy",
    "wof:placetype":"venue"
},
  "geometry": {"coordinates":[115.787200928,-31.9819335938],"type":"Point"}
}