{
  "type": "Feature",
  "properties": {
    "addr:full":"Stockland Mall Suite 5 Polding St Wetherill Park NSW 2164",
    "addr:postcode":"2164",
    "addr:street":"Polding St",
    "iso:country":"AU",
    "sg:address":"Stockland Mall Suite 5 Polding St",
    "sg:city":"Wetherill Park",
    "sg:classifiers":[
        {
            "category":"Professional",
            "subcategory":"Management & Consulting",
            "type":"Services"
        }
    ],
    "sg:phone":"+61 2 8786 1326",
    "sg:postcode":"2164",
    "sg:province":"NSW",
    "sg:tags":[
        "consultant",
        "educational"
    ],
    "wof:name":"Kip McGrath Education Centres- Fairfield",
    "wof:placetype":"venue"
},
  "geometry": {"coordinates":[150.89511108400001,-33.8563804626],"type":"Point"}
}