{
  "type": "Feature",
  "properties": {
    "iso:country":"AU",
    "sg:address":"2 Ann St",
    "sg:city":"Toowoomba",
    "sg:classifiers":[
        {
            "category":"Wholesale",
            "subcategory":"Machinery & Supplies",
            "type":"Manufacturing & Wholesale Goods"
        }
    ],
    "sg:phone":"+61 7 4632 9366",
    "sg:postcode":"4350",
    "sg:province":"QLD",
    "sg:tags":[
        "equipment",
        "welding"
    ],
    "wof:name":"O'Donnell Electrical Contractors",
    "wof:placetype":"venue"
},
  "geometry": {"coordinates":[151.955063,-27.55587],"type":"Point"}
}