{
  "type": "Feature",
  "properties": {
    "addr:full":"7 Denver St Norlane VIC 3214",
    "addr:housenumber":"7",
    "addr:postcode":"3214",
    "addr:street":"Denver St",
    "iso:country":"AU",
    "sg:address":"7 Denver St",
    "sg:city":"Norlane",
    "sg:classifiers":[
        {
            "category":"Professional",
            "subcategory":"Art Services",
            "type":"Services"
        }
    ],
    "sg:phone":"+61 407 516 326",
    "sg:postcode":"3214",
    "sg:province":"VIC",
    "sg:tags":[
        "decorator",
        "painter"
    ],
    "wof:name":"Robert Benzie",
    "wof:placetype":"venue"
},
  "geometry": {"coordinates":[144.354415894,-38.0959434509],"type":"Point"}
}