{
  "type": "Feature",
  "properties": {
    "addr:full":"Eagleby Shopng Plaza Eagleby QLD 4207",
    "addr:postcode":"4207",
    "iso:country":"AU",
    "sg:address":"Eagleby Shopng Plaza",
    "sg:city":"Eagleby",
    "sg:classifiers":[
        {
            "category":"Food & Beverages",
            "subcategory":"Liquor & Beverages",
            "type":"Retail Goods"
        }
    ],
    "sg:phone":"+61 7 3807 7522",
    "sg:postcode":"4207",
    "sg:province":"QLD",
    "sg:tags":[
        "store"
    ],
    "wof:name":"Liquor King",
    "wof:placetype":"venue"
},
  "geometry": {"coordinates":[153.20533752399999,-27.68542099],"type":"Point"}
}