{
  "type": "Feature",
  "properties": {
    "addr:full":"Suite 110, 272 Victoria Ave Chatswood NSW 2057",
    "addr:housenumber":"272",
    "addr:postcode":"2057",
    "addr:street":"Victoria Ave",
    "iso:country":"AU",
    "sg:address":"Suite 110, 272 Victoria Ave",
    "sg:city":"Chatswood",
    "sg:classifiers":[
        {
            "category":"Professional",
            "subcategory":"Management & Consulting",
            "type":"Services"
        }
    ],
    "sg:phone":"+61 412 488 973",
    "sg:postcode":"2057",
    "sg:province":"NSW",
    "sg:tags":[
        "consultant"
    ],
    "wof:name":"Abacas Consulting Pty Ltd",
    "wof:placetype":"venue"
},
  "geometry": {"coordinates":[151.187073,-33.795212],"type":"Point"}
}