{
  "type": "Feature",
  "properties": {
    "iso:country":"AU",
    "sg:address":"48 Perry Ave",
    "sg:city":"Springwood",
    "sg:classifiers":[
        {
            "category":"Professional",
            "subcategory":"Computer Services",
            "type":"Services"
        }
    ],
    "sg:phone":"+61 2 4751 7190",
    "sg:postcode":"2777",
    "sg:province":"NSW",
    "sg:tags":[
        "consultant",
        "system"
    ],
    "wof:name":"Mal Stone Computer Services",
    "wof:placetype":"venue"
},
  "geometry": {"coordinates":[150.56149292000001,-33.6956214905],"type":"Point"}
}