{
  "type": "Feature",
  "properties": {
    "iso:country":"AU",
    "sg:address":"12 Warburton Rd",
    "sg:city":"Valley View",
    "sg:classifiers":[
        {
            "category":"Real Estate",
            "subcategory":"Real Estate Services",
            "type":"Services"
        }
    ],
    "sg:phone":"+61 8 8264 7391",
    "sg:postcode":"5093",
    "sg:province":"SA",
    "sg:tags":[
        "consultant",
        "property"
    ],
    "wof:name":"Rusak Corporate Conveyancers",
    "wof:placetype":"venue"
},
  "geometry": {"coordinates":[138.66139221200001,-34.8359909058],"type":"Point"}
}