{
  "type": "Feature",
  "properties": {
    "addr:full":"88 John St Salisbury SA 5108",
    "addr:housenumber":"88",
    "addr:postcode":"5108",
    "addr:street":"John St",
    "iso:country":"AU",
    "sg:address":"88 John St",
    "sg:city":"Salisbury",
    "sg:classifiers":[
        {
            "category":"Health Services",
            "subcategory":"Dentist",
            "type":"Services"
        }
    ],
    "sg:phone":"+61 8 8283 3999",
    "sg:postcode":"5108",
    "sg:province":"SA",
    "sg:tags":[
        "dental",
        "prosthetist"
    ],
    "wof:name":"Dentures Direct",
    "wof:placetype":"venue"
},
  "geometry": {"coordinates":[138.64901733400001,-34.7612838745],"type":"Point"}
}