{
  "type": "Feature",
  "properties": {
    "addr:full":"118 Argyle St Hobart TAS 7000",
    "addr:housenumber":"118",
    "addr:postcode":"7000",
    "addr:street":"Argyle St",
    "iso:country":"AU",
    "sg:address":"118 Argyle St",
    "sg:city":"Hobart",
    "sg:classifiers":[
        {
            "category":"Autos & Motor Vehicles",
            "subcategory":"Automobile Sales",
            "type":"Retail Goods"
        }
    ],
    "sg:phone":"+61 3 6234 0350",
    "sg:postcode":"7000",
    "sg:province":"TAS",
    "sg:tags":[
        "car",
        "new"
    ],
    "wof:name":"Jaguar Cars (Hobart Jaguar-Euro Central)",
    "wof:placetype":"venue"
},
  "geometry": {"coordinates":[147.32513427699999,-42.8779602051],"type":"Point"}
}