{
  "type": "Feature",
  "properties": {
    "addr:full":"1330 Powranna Rd Cressy TAS 7302",
    "addr:housenumber":"1330",
    "addr:postcode":"7302",
    "addr:street":"Powranna Rd",
    "iso:country":"AU",
    "sg:address":"1330 Powranna Rd",
    "sg:city":"Cressy",
    "sg:classifiers":[
        {
            "category":"Professional",
            "subcategory":"Business Services",
            "type":"Services"
        }
    ],
    "sg:phone":"+61 3 6397 6461",
    "sg:postcode":"7302",
    "sg:province":"TAS",
    "sg:tags":[
        "livestock",
        "transport"
    ],
    "wof:name":"Cressy Transport",
    "wof:placetype":"venue"
},
  "geometry": {"coordinates":[147.11419677699999,-41.7189674377],"type":"Point"}
}