{
  "type": "Feature",
  "properties": {
    "iso:country":"AU",
    "sg:address":"358 Mann St",
    "sg:city":"Gosford",
    "sg:classifiers":[
        {
            "category":"Retail",
            "subcategory":"Car Wash",
            "type":"Services"
        }
    ],
    "sg:phone":"+61 2 4322 7803",
    "sg:postcode":"2250",
    "sg:province":"NSW",
    "sg:tags":[
        "truck",
        "cleaning"
    ],
    "wof:name":"Gosford Bay Car Detailing",
    "wof:placetype":"venue"
},
  "geometry": {"coordinates":[151.34376525900001,-33.4167709351],"type":"Point"}
}