{
  "type": "Feature",
  "properties": {
    "addr:full":"95 Great Eastern Hwy Sawyers Valley WA 6074",
    "addr:housenumber":"95",
    "addr:postcode":"6074",
    "addr:street":"Great Eastern Hwy",
    "iso:country":"AU",
    "sg:address":"95 Great Eastern Hwy",
    "sg:city":"Sawyers Valley",
    "sg:classifiers":[
        {
            "category":"Retail",
            "subcategory":"Auto Repair",
            "type":"Services"
        }
    ],
    "sg:phone":"+61 8 9295 3818",
    "sg:postcode":"6074",
    "sg:province":"WA",
    "sg:tags":[
        "repairer",
        "motor",
        "engineer"
    ],
    "wof:name":"Allied Automotives",
    "wof:placetype":"venue"
},
  "geometry": {"coordinates":[116.21211242699999,-31.8999404907],"type":"Point"}
}