{
  "type": "Feature",
  "properties": {
    "iso:country":"AU",
    "sg:address":"241 St Georges Rd",
    "sg:city":"Northcote",
    "sg:classifiers":[
        {
            "category":"Personal",
            "subcategory":"Massage",
            "type":"Services"
        }
    ],
    "sg:phone":"+61 3 9410 9826",
    "sg:postcode":"3070",
    "sg:province":"VIC",
    "sg:tags":[
        "therapy"
    ],
    "wof:name":"St Georges Natural Health Therapies",
    "wof:placetype":"venue"
},
  "geometry": {"coordinates":[144.991745,-37.764759],"type":"Point"}
}