{
  "type": "Feature",
  "properties": {
    "iso:country":"AU",
    "sg:address":"22 Mulgoa Crt",
    "sg:city":"Barwon Heads",
    "sg:classifiers":[
        {
            "category":"Building & Trades",
            "subcategory":"Construction",
            "type":"Services"
        }
    ],
    "sg:phone":"+61 411 861 203",
    "sg:postcode":"3227",
    "sg:province":"VIC",
    "sg:tags":[
        "concrete",
        "paving"
    ],
    "wof:name":"Webb Concreting",
    "wof:placetype":"venue"
},
  "geometry": {"coordinates":[144.487183,-38.265781],"type":"Point"}
}