{
  "type": "Feature",
  "properties": {
    "iso:country":"AU",
    "sg:address":"21 Beatrice Ave",
    "sg:city":"Heidelberg West",
    "sg:classifiers":[
        {
            "category":"Manufacturing",
            "subcategory":"Metals",
            "type":"Manufacturing & Wholesale Goods"
        }
    ],
    "sg:phone":"+61 3 9459 9355",
    "sg:postcode":"3081",
    "sg:province":"VIC",
    "sg:tags":[
        "steel",
        "fabricator",
        "mfrs"
    ],
    "wof:name":"Affordable Steelwork Pty Ltd",
    "wof:placetype":"venue"
},
  "geometry": {"coordinates":[145.050613403,-37.7303390503],"type":"Point"}
}