{
  "type": "Feature",
  "properties": {
    "addr:full":"145 Walcott St Mt Lawley WA 6050",
    "addr:housenumber":"145",
    "addr:postcode":"6050",
    "addr:street":"Walcott St",
    "iso:country":"AU",
    "sg:address":"145 Walcott St",
    "sg:city":"Mt Lawley",
    "sg:classifiers":[
        {
            "category":"Retail",
            "subcategory":"Auto Repair",
            "type":"Services"
        }
    ],
    "sg:phone":"+61 8 9328 8229",
    "sg:postcode":"6050",
    "sg:province":"WA",
    "sg:tags":[
        "repairer",
        "motor",
        "engineer"
    ],
    "wof:name":"Repco Authorised Service",
    "wof:placetype":"venue"
},
  "geometry": {"coordinates":[115.86743927000001,-31.9302043915],"type":"Point"}
}