{
  "type": "Feature",
  "properties": {
    "addr:full":"235 Edgar St Condell Park NSW 2200",
    "addr:housenumber":"235",
    "addr:postcode":"2200",
    "addr:street":"Edgar St",
    "iso:country":"AU",
    "sg:address":"235 Edgar St",
    "sg:city":"Condell Park",
    "sg:classifiers":[
        {
            "category":"Building & Trades",
            "subcategory":"Construction",
            "type":"Services"
        }
    ],
    "sg:phone":"+61 2 9709 3551",
    "sg:postcode":"2200",
    "sg:province":"NSW",
    "sg:tags":[
        "renovation",
        "alterations",
        "extension",
        "contractor"
    ],
    "wof:name":"Sam Constructions Pty Ltd",
    "wof:placetype":"venue"
},
  "geometry": {"coordinates":[151.01225299999999,-33.927803],"type":"Point"}
}