{
  "type": "Feature",
  "properties": {
    "addr:full":"362 Edward St Wagga Wagga NSW 2650",
    "addr:housenumber":"362",
    "addr:postcode":"2650",
    "addr:street":"Edward St",
    "iso:country":"AU",
    "sg:address":"362 Edward St",
    "sg:city":"Wagga Wagga",
    "sg:classifiers":[
        {
            "category":"Retail",
            "subcategory":"Auto Repair",
            "type":"Services"
        }
    ],
    "sg:phone":"+61 2 6925 1040",
    "sg:postcode":"2650",
    "sg:province":"NSW",
    "sg:tags":[
        "repairer",
        "motor",
        "engineer"
    ],
    "wof:name":"Mechanical World",
    "wof:placetype":"venue"
},
  "geometry": {"coordinates":[147.346603394,-35.1158332825],"type":"Point"}
}