{
  "type": "Feature",
  "properties": {
    "addr:full":"Shop 32 Goldfields Plz Monkland St Gympie QLD 4570",
    "addr:housenumber":"shop 32",
    "addr:postcode":"4570",
    "addr:street":"Goldfields Plz Monkland St",
    "iso:country":"AU",
    "sg:address":"Shop 32 Goldfields Plz Monkland St",
    "sg:city":"Gympie",
    "sg:classifiers":[
        {
            "category":"Fast Food",
            "type":"Food & Drink"
        }
    ],
    "sg:phone":"+61 7 5482 4400",
    "sg:postcode":"4570",
    "sg:province":"QLD",
    "sg:tags":[
        "away",
        "take"
    ],
    "wof:name":"Fantasy Donuts",
    "wof:placetype":"venue"
},
  "geometry": {"coordinates":[152.65852355999999,-26.1916275024],"type":"Point"}
}