{
  "type": "Feature",
  "properties": {
    "iso:country":"AU",
    "sg:address":"257 Parramatta Rd",
    "sg:city":"Haberfield",
    "sg:classifiers":[
        {
            "category":"Autos & Motor Vehicles",
            "subcategory":"Auto Supplies",
            "type":"Retail Goods"
        }
    ],
    "sg:phone":"+61 2 9716 7955",
    "sg:postcode":"2045",
    "sg:province":"NSW",
    "sg:tags":[
        "wheel",
        "automotive",
        "rim"
    ],
    "wof:name":"JAXQuickfit Tyres",
    "wof:placetype":"venue"
},
  "geometry": {"coordinates":[151.12930299999999,-33.876049],"type":"Point"}
}