{
  "type": "Feature",
  "properties": {
    "iso:country":"AU",
    "sg:address":"4 Gannons Ave",
    "sg:city":"Hurstville",
    "sg:classifiers":[
        {
            "category":"Shopping",
            "subcategory":"Bridal",
            "type":"Retail Goods"
        }
    ],
    "sg:phone":"+61 2 9594 4686",
    "sg:postcode":"2220",
    "sg:province":"NSW",
    "sg:tags":[
        "hire",
        "wear"
    ],
    "wof:name":"Bridal Alterations",
    "wof:placetype":"venue"
},
  "geometry": {"coordinates":[151.106079102,-33.9550552368],"type":"Point"}
}