{
  "type": "Feature",
  "properties": {
    "iso:country":"AU",
    "sg:address":"20 Bailey St",
    "sg:city":"Bairnsdale",
    "sg:classifiers":[
        {
            "category":"Shopping",
            "subcategory":"Crafts & Fabrics",
            "type":"Retail Goods"
        }
    ],
    "sg:phone":"+61 3 5152 2110",
    "sg:postcode":"3875",
    "sg:province":"VIC",
    "sg:tags":[
        "supply"
    ],
    "wof:name":"Ghecko Craft",
    "wof:placetype":"venue"
},
  "geometry": {"coordinates":[147.63154602,-37.8253211975],"type":"Point"}
}