{
  "type": "Feature",
  "properties": {
    "addr:full":"535 Ballarto Rd Skye VIC 3977",
    "addr:housenumber":"535",
    "addr:postcode":"3977",
    "addr:street":"Ballarto Rd",
    "iso:country":"AU",
    "sg:address":"535 Ballarto Rd",
    "sg:city":"Skye",
    "sg:classifiers":[
        {
            "category":"Commercial Area",
            "type":"Public Place"
        }
    ],
    "sg:phone":"+61 3 9782 2922",
    "sg:postcode":"3977",
    "sg:province":"VIC",
    "sg:tags":[
        "heavy",
        "carrier"
    ],
    "wof:name":"Tiltaway Pty Ltd",
    "wof:placetype":"venue"
},
  "geometry": {"coordinates":[145.21641540499999,-38.1197509766],"type":"Point"}
}