{
  "type": "Feature",
  "properties": {
    "iso:country":"AU",
    "sg:address":"177 Koroit St",
    "sg:city":"Warrnambool",
    "sg:classifiers":[
        {
            "category":"Banks & Credit Unions",
            "subcategory":"Financial Services",
            "type":"Services"
        }
    ],
    "sg:phone":"+61 3 5564 0555",
    "sg:postcode":"3280",
    "sg:province":"VIC",
    "sg:tags":[
        "annuity",
        "rollover",
        "superannuation",
        "consultant"
    ],
    "wof:name":"Sinclair & Wilson Investment Services Pty Ltd",
    "wof:placetype":"venue"
},
  "geometry": {"coordinates":[142.482025147,-38.3830299377],"type":"Point"}
}