{
  "type": "Feature",
  "properties": {
    "addr:full":"189 Creek Rd Mt Gravatt QLD 4122",
    "addr:housenumber":"189",
    "addr:postcode":"4122",
    "addr:street":"Creek Rd",
    "iso:country":"AU",
    "sg:address":"189 Creek Rd",
    "sg:city":"Mt Gravatt",
    "sg:classifiers":[
        {
            "category":"Retail",
            "subcategory":"Veterinary Services",
            "type":"Services"
        }
    ],
    "sg:phone":"+61 7 3349 0811",
    "sg:postcode":"4122",
    "sg:province":"QLD",
    "sg:tags":[
        "surgeon"
    ],
    "wof:name":"The Cat Clinic",
    "wof:placetype":"venue"
},
  "geometry": {"coordinates":[153.09371948200001,-27.532081604],"type":"Point"}
}