{
  "type": "Feature",
  "properties": {
    "addr:full":"649 Beaufort St Mt Lawley WA 6050",
    "addr:housenumber":"649",
    "addr:postcode":"6050",
    "addr:street":"Beaufort St",
    "iso:country":"AU",
    "sg:address":"649 Beaufort St",
    "sg:city":"Mt Lawley",
    "sg:classifiers":[
        {
            "category":"Personal",
            "subcategory":"Beauty Salon",
            "type":"Services"
        }
    ],
    "sg:phone":"+61 8 9228 8133",
    "sg:postcode":"6050",
    "sg:province":"WA",
    "sg:tags":[
        "hairdresser"
    ],
    "wof:name":"Christian James Hairdressing",
    "wof:placetype":"venue"
},
  "geometry": {"coordinates":[115.868530273,-31.9404754639],"type":"Point"}
}