{
  "type": "Feature",
  "properties": {
    "iso:country":"AU",
    "sg:address":"1 National Park St",
    "sg:city":"Newcastle West",
    "sg:classifiers":[
        {
            "category":"Education",
            "subcategory":"Music School",
            "type":"Public Place"
        }
    ],
    "sg:phone":"+61 2 4929 2829",
    "sg:postcode":"2302",
    "sg:province":"NSW",
    "sg:tags":[
        "teacher"
    ],
    "wof:name":"Musos Corner",
    "wof:placetype":"venue"
},
  "geometry": {"coordinates":[151.761642,-32.926445],"type":"Point"}
}