{
  "type": "Feature",
  "properties": {
    "iso:country":"AU",
    "sg:address":"616 - 618 Park Rd",
    "sg:city":"Park Orchards",
    "sg:classifiers":[
        {
            "category":"Health Services",
            "subcategory":"Doctor",
            "type":"Services"
        }
    ],
    "sg:phone":"+61 3 9876 1964",
    "sg:postcode":"3114",
    "sg:province":"VIC",
    "sg:tags":[
        "medical",
        "practitioner"
    ],
    "wof:name":"Morris N V",
    "wof:placetype":"venue"
},
  "geometry": {"coordinates":[145.21859741200001,-37.779209137],"type":"Point"}
}