{
  "type": "Feature",
  "properties": {
    "addr:full":"32 Sutton St Mandurah WA 6210",
    "addr:housenumber":"32",
    "addr:postcode":"6210",
    "addr:street":"Sutton St",
    "iso:country":"AU",
    "sg:address":"32 Sutton St",
    "sg:city":"Mandurah",
    "sg:classifiers":[
        {
            "category":"Professional",
            "subcategory":"Employment Agencies",
            "type":"Services"
        }
    ],
    "sg:phone":"+61 8 9581 4606",
    "sg:postcode":"6210",
    "sg:province":"WA",
    "wof:name":"Mandurah Job Link",
    "wof:placetype":"venue"
},
  "geometry": {"coordinates":[115.72277099999999,-32.530827],"type":"Point"}
}