{
  "type": "Feature",
  "properties": {
    "addr:full":"103 Main St Penguin TAS 7316",
    "addr:housenumber":"103",
    "addr:postcode":"7316",
    "addr:street":"Main St",
    "iso:country":"AU",
    "sg:address":"103 Main St",
    "sg:city":"Penguin",
    "sg:classifiers":[
        {
            "category":"Building & Trades",
            "subcategory":"Construction",
            "type":"Services"
        }
    ],
    "sg:phone":"+61 408 552 656",
    "sg:postcode":"7316",
    "sg:province":"TAS",
    "sg:tags":[
        "earth",
        "excavating",
        "moving",
        "contractor"
    ],
    "wof:name":"Gee Tim",
    "wof:placetype":"venue"
},
  "geometry": {"coordinates":[146.074615478,-41.1147003174],"type":"Point"}
}