{
  "type": "Feature",
  "properties": {
    "addr:full":"15 Pound St West Ipswich QLD 4305",
    "addr:housenumber":"15",
    "addr:postcode":"4305",
    "addr:street":"Pound St West",
    "iso:country":"AU",
    "sg:address":"15 Pound St",
    "sg:city":"West Ipswich",
    "sg:classifiers":[
        {
            "category":"Retail",
            "subcategory":"Auto Repair",
            "type":"Services"
        }
    ],
    "sg:phone":"+61 7 3281 4286",
    "sg:postcode":"4305",
    "sg:province":"QLD",
    "sg:tags":[
        "electrical"
    ],
    "wof:name":"Ipswich Auto Electrical Pty Ltd",
    "wof:placetype":"venue"
},
  "geometry": {"coordinates":[152.749603272,-27.6227817535],"type":"Point"}
}