{
  "type": "Feature",
  "properties": {
    "addr:full":"5 Giuffre Pl West Pennant Hills NSW 2125",
    "addr:housenumber":"5",
    "addr:postcode":"2125",
    "addr:street":"Giuffre Pl",
    "iso:country":"AU",
    "sg:address":"5 Giuffre Pl",
    "sg:city":"West Pennant Hills",
    "sg:classifiers":[
        {
            "category":"Professional",
            "subcategory":"Business Services",
            "type":"Services"
        }
    ],
    "sg:phone":"+61 2 9872 1368",
    "sg:postcode":"2125",
    "sg:province":"NSW",
    "sg:tags":[
        "exporter"
    ],
    "wof:name":"Pacific Business Pty Ltd",
    "wof:placetype":"venue"
},
  "geometry": {"coordinates":[151.04556274399999,-33.7521514893],"type":"Point"}
}