{
  "type": "Feature",
  "properties": {
    "addr:full":"54 Watsons Rd Newcomb VIC 3219",
    "addr:housenumber":"54",
    "addr:postcode":"3219",
    "addr:street":"Watsons Rd",
    "iso:country":"AU",
    "sg:address":"54 Watsons Rd",
    "sg:city":"Newcomb",
    "sg:classifiers":[
        {
            "category":"Cafe",
            "type":"Food & Drink"
        }
    ],
    "sg:phone":"+61 3 5248 0055",
    "sg:postcode":"3219",
    "sg:province":"VIC",
    "wof:name":"Sawasdee Thai Cafe",
    "wof:placetype":"venue"
},
  "geometry": {"coordinates":[144.39067077600001,-38.1650009155],"type":"Point"}
}