{
  "type": "Feature",
  "properties": {
    "addr:full":"Shop 11 237- 239 Great Eastern Hwy Belmont WA 6104",
    "addr:housenumber":"shop 11;239",
    "addr:postcode":"237;6104",
    "addr:street":"Great Eastern Hwy",
    "iso:country":"AU",
    "sg:address":"Shop 11 237- 239 Great Eastern Hwy",
    "sg:city":"Belmont",
    "sg:classifiers":[
        {
            "category":"Government",
            "subcategory":"Post Office",
            "type":"Public Place"
        }
    ],
    "sg:phone":"+61 13 13 18",
    "sg:postcode":"6104",
    "sg:province":"WA",
    "sg:tags":[
        "postal"
    ],
    "wof:name":"Australia Post",
    "wof:placetype":"venue"
},
  "geometry": {"coordinates":[115.925598145,-31.9420375824],"type":"Point"}
}