{
  "type": "Feature",
  "properties": {
    "iso:country":"AU",
    "sg:address":"166- 168 Clayton Rd",
    "sg:city":"Clayton",
    "sg:classifiers":[
        {
            "category":"Personal",
            "type":"Services"
        }
    ],
    "sg:phone":"+61 3 9543 8588",
    "sg:postcode":"3168",
    "sg:province":"VIC",
    "sg:tags":[
        "gift"
    ],
    "sg:website":"http://www.busybeeflorist.com.au",
    "wof:name":"Busy Bee Florist",
    "wof:placetype":"venue"
},
  "geometry": {"coordinates":[145.12193298299999,-37.914478302],"type":"Point"}
}