{
  "type": "Feature",
  "properties": {
    "addr:full":"319 Springvale Rd Glen Waverley VIC 3150",
    "addr:housenumber":"319",
    "addr:postcode":"3150",
    "addr:street":"Springvale Rd",
    "iso:country":"AU",
    "sg:address":"319 Springvale Rd",
    "sg:city":"Glen Waverley",
    "sg:classifiers":[
        {
            "category":"Health Services",
            "subcategory":"Health Practitioner",
            "type":"Services"
        }
    ],
    "sg:phone":"+61 3 9560 9799",
    "sg:postcode":"3150",
    "sg:province":"VIC",
    "sg:tags":[
        "acupuncture"
    ],
    "wof:name":"Laser Therapy Centre",
    "wof:placetype":"venue"
},
  "geometry": {"coordinates":[145.16494750999999,-37.8831291199],"type":"Point"}
}