{
  "type": "Feature",
  "properties": {
    "iso:country":"AU",
    "sg:address":"241 Parramatta Rd",
    "sg:city":"Granville",
    "sg:classifiers":[
        {
            "category":"Autos & Motor Vehicles",
            "subcategory":"Automobile Sales",
            "type":"Retail Goods"
        }
    ],
    "sg:phone":"+61 2 9637 1200",
    "sg:postcode":"2142",
    "sg:province":"NSW",
    "sg:tags":[
        "car",
        "used"
    ],
    "wof:name":"R.A. Motors",
    "wof:placetype":"venue"
},
  "geometry": {"coordinates":[151.00575256400001,-33.8276977539],"type":"Point"}
}