{
  "type": "Feature",
  "properties": {
    "addr:full":"PO Box 668 North Sydney NSW 2060",
    "addr:postcode":"2060",
    "iso:country":"AU",
    "sg:address":"PO Box 668",
    "sg:city":"North Sydney",
    "sg:classifiers":[
        {
            "category":"Banks & Credit Unions",
            "subcategory":"Investment Brokerage",
            "type":"Services"
        }
    ],
    "sg:phone":"+61 1300 666 800",
    "sg:postcode":"2060",
    "sg:province":"NSW",
    "sg:tags":[
        "stored",
        "card",
        "value"
    ],
    "wof:name":"Tetel Telecom Pty Ltd",
    "wof:placetype":"venue"
},
  "geometry": {"coordinates":[151.207717895,-33.8398590088],"type":"Point"}
}