{
  "type": "Feature",
  "properties": {
    "iso:country":"AU",
    "sg:address":"222 Edwardes St",
    "sg:city":"Reservoir",
    "sg:classifiers":[
        {
            "category":"Retail",
            "subcategory":"Auto Repair",
            "type":"Services"
        }
    ],
    "sg:phone":"+61 3 9462 4411",
    "sg:postcode":"3073",
    "sg:province":"VIC",
    "sg:tags":[
        "repairer",
        "motor",
        "engineer"
    ],
    "wof:name":"Double JJ's Auto Performance",
    "wof:placetype":"venue"
},
  "geometry": {"coordinates":[144.98797607399999,-37.714214325],"type":"Point"}
}