{
  "type": "Feature",
  "properties": {
    "iso:country":"AU",
    "sg:address":"76 Atkinson St",
    "sg:city":"Liverpool",
    "sg:classifiers":[
        {
            "category":"Retail",
            "subcategory":"Laundry & Dry Cleaning",
            "type":"Services"
        }
    ],
    "sg:phone":"+61 2 9602 1812",
    "sg:postcode":"2170",
    "sg:province":"NSW",
    "sg:tags":[
        "truck",
        "tip",
        "contractor"
    ],
    "wof:name":"Croad A",
    "wof:placetype":"venue"
},
  "geometry": {"coordinates":[150.91627502399999,-33.9305419922],"type":"Point"}
}