{
  "type": "Feature",
  "properties": {
    "addr:full":"404 Barkley St Buninyong VIC 3357",
    "addr:housenumber":"404",
    "addr:postcode":"3357",
    "addr:street":"Barkley St",
    "iso:country":"AU",
    "sg:address":"404 Barkley St",
    "sg:city":"Buninyong",
    "sg:classifiers":[
        {
            "category":"Personal",
            "subcategory":"Beauty Salon",
            "type":"Services"
        }
    ],
    "sg:phone":"+61 3 5341 2628",
    "sg:postcode":"3357",
    "sg:province":"VIC",
    "sg:tags":[
        "hairdresser"
    ],
    "wof:name":"Margaret Chaplin Hairdresser",
    "wof:placetype":"venue"
},
  "geometry": {"coordinates":[143.88536099999999,-37.645348],"type":"Point"}
}