{
  "type": "Feature",
  "properties": {
    "addr:full":"U1/ 318 The Grand Pde Sans Souci NSW 2219",
    "addr:housenumber":"318",
    "addr:postcode":"2219",
    "addr:street":"U1 /;The Grand Pde",
    "iso:country":"AU",
    "sg:address":"U1/ 318 The Grand Pde",
    "sg:city":"Sans Souci",
    "sg:classifiers":[
        {
            "category":"Health Services",
            "subcategory":"Clinic",
            "type":"Services"
        }
    ],
    "sg:phone":"+61 2 9583 9564",
    "sg:postcode":"2219",
    "sg:province":"NSW",
    "sg:tags":[
        "aromatherapy"
    ],
    "wof:name":"Australia Essential Aroma International",
    "wof:placetype":"venue"
},
  "geometry": {"coordinates":[151.146072,-33.991199],"type":"Point"}
}