{
  "type": "Feature",
  "properties": {
    "addr:full":"Unit B 10-20 McEvoy St Waterloo NSW 2017",
    "addr:housenumber":"10-20",
    "addr:postcode":"2017",
    "addr:street":"Mcevoy St",
    "iso:country":"AU",
    "sg:address":"Unit B 10-20 McEvoy St",
    "sg:city":"Waterloo",
    "sg:classifiers":[
        {
            "category":"Manufacturing",
            "subcategory":"Retail Goods",
            "type":"Manufacturing & Wholesale Goods"
        }
    ],
    "sg:phone":"+61 2 9690 2600",
    "sg:postcode":"2017",
    "sg:province":"NSW",
    "sg:tags":[
        "merchant",
        "pump",
        "mfrs"
    ],
    "wof:name":"Contour Ponds & Pumps",
    "wof:placetype":"venue"
},
  "geometry": {"coordinates":[151.207962036,-33.9006118774],"type":"Point"}
}