{
  "type": "Feature",
  "properties": {
    "addr:full":"32a Hopetoun Rd Warrnambool VIC 3280",
    "addr:housenumber":"32a",
    "addr:postcode":"3280",
    "addr:street":"Hopetoun Rd",
    "iso:country":"AU",
    "sg:address":"32a Hopetoun Rd",
    "sg:city":"Warrnambool",
    "sg:classifiers":[
        {
            "category":"Food & Beverages",
            "subcategory":"Groceries & Convenience Stores",
            "type":"Retail Goods"
        }
    ],
    "sg:phone":"+61 3 5561 2376",
    "sg:postcode":"3280",
    "sg:province":"VIC",
    "wof:name":"Hopetoun Road Milkbar",
    "wof:placetype":"venue"
},
  "geometry": {"coordinates":[142.473754883,-38.3681373596],"type":"Point"}
}