{
  "type": "Feature",
  "properties": {
    "addr:full":"3 Jarrah Pl Castle Hill NSW 2154",
    "addr:housenumber":"3",
    "addr:postcode":"2154",
    "addr:street":"Jarrah Pl",
    "iso:country":"AU",
    "sg:address":"3 Jarrah Pl",
    "sg:city":"Castle Hill",
    "sg:classifiers":[
        {
            "category":"Professional",
            "subcategory":"Computer Services",
            "type":"Services"
        }
    ],
    "sg:phone":"+61 2 9894 7526",
    "sg:postcode":"2154",
    "sg:province":"NSW",
    "sg:tags":[
        "information"
    ],
    "wof:name":"Clarke Information Solutions",
    "wof:placetype":"venue"
},
  "geometry": {"coordinates":[151.01405334500001,-33.739654541],"type":"Point"}
}