{
  "type": "Feature",
  "properties": {
    "addr:full":"73 Hamilton Pl Mt Waverley VIC 3149",
    "addr:housenumber":"73",
    "addr:postcode":"3149",
    "addr:street":"Hamilton Pl Mt",
    "iso:country":"AU",
    "sg:address":"73 Hamilton Pl",
    "sg:city":"Mt Waverley",
    "sg:classifiers":[
        {
            "category":"Shopping",
            "subcategory":"Clothing, Apparel, & Fashions",
            "type":"Retail Goods"
        }
    ],
    "sg:phone":"+61 3 9807 4422",
    "sg:postcode":"3149",
    "sg:province":"VIC",
    "sg:tags":[
        "lady",
        "wear"
    ],
    "wof:name":"Fella Hamilton",
    "wof:placetype":"venue"
},
  "geometry": {"coordinates":[145.128417969,-37.8771286011],"type":"Point"}
}