{
  "type": "Feature",
  "properties": {
    "addr:full":"Unit 4 /22 Paramount Drv Wangara WA 6065",
    "addr:housenumber":"22",
    "addr:postcode":"6065",
    "addr:street":"Paramount Drv",
    "iso:country":"AU",
    "sg:address":"Unit 4 /22 Paramount Drv",
    "sg:city":"Wangara",
    "sg:classifiers":[
        {
            "category":"Retail",
            "subcategory":"Auto Repair",
            "type":"Services"
        }
    ],
    "sg:phone":"+61 8 9302 6680",
    "sg:postcode":"6065",
    "sg:province":"WA",
    "sg:tags":[
        "repairer",
        "motor",
        "engineer"
    ],
    "wof:name":"Discovery Automotive Pty Ltd",
    "wof:placetype":"venue"
},
  "geometry": {"coordinates":[115.830780029,-31.7904624939],"type":"Point"}
}