{
  "type": "Feature",
  "properties": {
    "iso:country":"AU",
    "sg:address":"129 Coleman Pde",
    "sg:city":"Glen Waverley",
    "sg:classifiers":[
        {
            "category":"Travel",
            "subcategory":"Hostel",
            "type":"Entertainment"
        }
    ],
    "sg:phone":"+61 3 9560 8244",
    "sg:postcode":"3150",
    "sg:province":"VIC",
    "sg:tags":[
        "home"
    ],
    "wof:name":"Australian Unity Wahroonga Aged Care",
    "wof:placetype":"venue"
},
  "geometry": {"coordinates":[145.1590271,-37.8789329529],"type":"Point"}
}