{
  "type": "Feature",
  "properties": {
    "iso:country":"AU",
    "sg:address":"Units 1 & 2/ 15",
    "sg:city":"Gympie Way Willetton",
    "sg:classifiers":[
        {
            "category":"Professional",
            "subcategory":"Engineering",
            "type":"Services"
        }
    ],
    "sg:phone":"+61 8 9457 4321",
    "sg:postcode":"6155",
    "sg:province":"WA",
    "sg:tags":[
        "refrigeration",
        "engineer"
    ],
    "wof:name":"Reac Systems",
    "wof:placetype":"venue"
},
  "geometry": {"coordinates":[115.882874,-32.040524],"type":"Point"}
}