{
  "type": "Feature",
  "properties": {
    "iso:country":"AU",
    "sg:address":"14 Tipping Rd",
    "sg:city":"Kewdale",
    "sg:classifiers":[
        {
            "category":"Banks & Credit Unions",
            "subcategory":"Financial Services",
            "type":"Services"
        }
    ],
    "sg:phone":"+61 8 9353 6401",
    "sg:postcode":"6105",
    "sg:province":"WA",
    "sg:tags":[
        "franchising"
    ],
    "wof:name":"Fastway Couriers (WA)",
    "wof:placetype":"venue"
},
  "geometry": {"coordinates":[115.967933655,-31.9759597778],"type":"Point"}
}