{
  "type": "Feature",
  "properties": {
    "addr:full":"25 Milne Ave Seaford VIC 3198",
    "addr:housenumber":"25",
    "addr:postcode":"3198",
    "addr:street":"Milne Ave",
    "iso:country":"AU",
    "sg:address":"25 Milne Ave",
    "sg:city":"Seaford",
    "sg:classifiers":[
        {
            "category":"Building & Trades",
            "subcategory":"Construction",
            "type":"Services"
        }
    ],
    "sg:phone":"+61 3 8796 3833",
    "sg:postcode":"3198",
    "sg:province":"VIC",
    "sg:tags":[
        "contractor"
    ],
    "wof:name":"Dema Constructions Pty Ltd",
    "wof:placetype":"venue"
},
  "geometry": {"coordinates":[145.13247680699999,-38.1186218262],"type":"Point"}
}