{
  "type": "Feature",
  "properties": {
    "addr:full":"262 Pascoe Vale Rd Essendon VIC 3040",
    "addr:housenumber":"262",
    "addr:postcode":"3040",
    "addr:street":"Pascoe Vale Rd",
    "iso:country":"AU",
    "sg:address":"262 Pascoe Vale Rd",
    "sg:city":"Essendon",
    "sg:classifiers":[
        {
            "category":"Social Services",
            "subcategory":"Retirement Home",
            "type":"Services"
        }
    ],
    "sg:phone":"+61 3 9326 1405",
    "sg:postcode":"3040",
    "sg:province":"VIC",
    "sg:tags":[
        "village"
    ],
    "wof:name":"Essendon Adult Day Centre",
    "wof:placetype":"venue"
},
  "geometry": {"coordinates":[144.925415039,-37.7500190735],"type":"Point"}
}