{
  "type": "Feature",
  "properties": {
    "addr:full":"18 Bradwardine Rd Bathurst NSW 2795",
    "addr:housenumber":"18",
    "addr:postcode":"2795",
    "addr:street":"Bradwardine Rd",
    "iso:country":"AU",
    "sg:address":"18 Bradwardine Rd",
    "sg:city":"Bathurst",
    "sg:classifiers":[
        {
            "category":"Building & Trades",
            "subcategory":"Construction",
            "type":"Services"
        }
    ],
    "sg:phone":"+61 2 6333 8000",
    "sg:postcode":"2795",
    "sg:province":"NSW",
    "sg:tags":[
        "ceiling"
    ],
    "wof:name":"Supawood",
    "wof:placetype":"venue"
},
  "geometry": {"coordinates":[149.543411255,-33.41639328],"type":"Point"}
}