{
  "type": "Feature",
  "properties": {
    "iso:country":"AU",
    "sg:address":"7 Dormello Drv",
    "sg:city":"Mudgeeraba",
    "sg:classifiers":[
        {
            "category":"Professional",
            "subcategory":"Art Services",
            "type":"Services"
        }
    ],
    "sg:phone":"+61 7 5530 4639",
    "sg:postcode":"4213",
    "sg:province":"QLD",
    "sg:tags":[
        "decorator",
        "painter"
    ],
    "wof:name":"Ashley C. Brook",
    "wof:placetype":"venue"
},
  "geometry": {"coordinates":[153.349777222,-28.0336608887],"type":"Point"}
}