{
  "type": "Feature",
  "properties": {
    "addr:full":"64 Old Belgrave Rd Upper Ferntree Gully VIC 3156",
    "addr:housenumber":"64",
    "addr:postcode":"3156",
    "addr:street":"Old Belgrave Rd",
    "iso:country":"AU",
    "sg:address":"64 Old Belgrave Rd",
    "sg:city":"Upper Ferntree Gully",
    "sg:classifiers":[
        {
            "category":"Shopping",
            "subcategory":"Crafts & Fabrics",
            "type":"Retail Goods"
        }
    ],
    "sg:phone":"+61 3 9758 8647",
    "sg:postcode":"3156",
    "sg:province":"VIC",
    "sg:tags":[
        "synthetic",
        "canvas",
        "product"
    ],
    "wof:name":"J & J Canvas Repairs",
    "wof:placetype":"venue"
},
  "geometry": {"coordinates":[145.320480347,-37.8995780945],"type":"Point"}
}