{
  "type": "Feature",
  "properties": {
    "addr:full":"26 Glynburn Rd Hectorville SA 5073",
    "addr:housenumber":"26",
    "addr:postcode":"5073",
    "addr:street":"Glynburn Rd",
    "iso:country":"AU",
    "sg:address":"26 Glynburn Rd",
    "sg:city":"Hectorville",
    "sg:classifiers":[
        {
            "category":"Professional",
            "subcategory":"Lawyer & Legal Services",
            "type":"Services"
        }
    ],
    "sg:phone":"+61 8 8336 4322",
    "sg:postcode":"5073",
    "sg:province":"SA",
    "sg:tags":[
        "wills",
        "probate",
        "estate"
    ],
    "wof:name":"Carbone, Polvere & Co",
    "wof:placetype":"venue"
},
  "geometry": {"coordinates":[138.656814575,-34.8908729553],"type":"Point"}
}