{
  "type": "Feature",
  "properties": {
    "addr:full":"359 Brunswick St Fitzroy VIC 3065",
    "addr:housenumber":"359",
    "addr:postcode":"3065",
    "addr:street":"Brunswick St",
    "iso:country":"AU",
    "sg:address":"359 Brunswick St",
    "sg:city":"Fitzroy",
    "sg:classifiers":[
        {
            "category":"Restaurant",
            "type":"Food & Drink"
        }
    ],
    "sg:phone":"+61 3 9416 0024",
    "sg:postcode":"3065",
    "sg:province":"VIC",
    "wof:name":"Cherry Lounge Cafe",
    "wof:placetype":"venue"
},
  "geometry": {"coordinates":[144.978607178,-37.7964134216],"type":"Point"}
}