{
  "type": "Feature",
  "properties": {
    "addr:full":"Shop 74 Lakeside Shopping Centre Joondalup WA 6027",
    "addr:housenumber":"shop 74",
    "addr:postcode":"6027",
    "addr:street":"Lakeside",
    "iso:country":"AU",
    "sg:address":"Shop 74",
    "sg:city":"Lakeside Shopping Centre Joondalup",
    "sg:classifiers":[
        {
            "category":"Food & Beverages",
            "subcategory":"Bakery",
            "type":"Retail Goods"
        }
    ],
    "sg:phone":"+61 8 9300 3117",
    "sg:postcode":"6027",
    "sg:province":"WA",
    "sg:tags":[
        "cake",
        "shop",
        "pastry"
    ],
    "wof:name":"Joondalup Pat A Cake",
    "wof:placetype":"venue"
},
  "geometry": {"coordinates":[115.775848389,-31.7488994598],"type":"Point"}
}