{
  "type": "Feature",
  "properties": {
    "addr:full":"Aprt1/ 28 Billyard Ave Elizabeth Bay NSW 2011",
    "addr:postcode":"2011",
    "addr:street":"Billyard Ave",
    "iso:country":"AU",
    "sg:address":"Aprt1/ 28 Billyard Ave",
    "sg:city":"Elizabeth Bay",
    "sg:classifiers":[
        {
            "category":"Banks & Credit Unions",
            "subcategory":"Investment Brokerage",
            "type":"Services"
        }
    ],
    "sg:phone":"+61 2 9331 0411",
    "sg:postcode":"2011",
    "sg:province":"NSW",
    "wof:name":"Herron Holdings Pty Ltd",
    "wof:placetype":"venue"
},
  "geometry": {"coordinates":[151.227005005,-33.8694992065],"type":"Point"}
}