{
  "type": "Feature",
  "properties": {
    "addr:full":"Shp2/ 18 Merrilaine Crs Merrimac QLD 4226",
    "addr:postcode":"4226",
    "addr:street":"Merrilaine Crs",
    "iso:country":"AU",
    "sg:address":"Shp2/ 18 Merrilaine Crs",
    "sg:city":"Merrimac",
    "sg:classifiers":[
        {
            "category":"Fast Food",
            "type":"Food & Drink"
        }
    ],
    "sg:phone":"+61 7 5530 7480",
    "sg:postcode":"4226",
    "sg:province":"QLD",
    "sg:tags":[
        "away",
        "take"
    ],
    "wof:name":"Romeo's Carvery & Pizza",
    "wof:placetype":"venue"
},
  "geometry": {"coordinates":[153.366531372,-28.0469093323],"type":"Point"}
}