{
  "type": "Feature",
  "properties": {
    "iso:country":"AU",
    "sg:address":"PO Box 77",
    "sg:city":"Haberfield",
    "sg:classifiers":[
        {
            "category":"Building & Trades",
            "subcategory":"Construction",
            "type":"Services"
        }
    ],
    "sg:phone":"+61 418 214 800",
    "sg:postcode":"2045",
    "sg:province":"NSW",
    "sg:tags":[
        "management"
    ],
    "wof:name":"PDM Management Services",
    "wof:placetype":"venue"
},
  "geometry": {"coordinates":[151.139267,-33.881031],"type":"Point"}
}