{
  "type": "Feature",
  "properties": {
    "iso:country":"AU",
    "sg:address":"25 Central Park Drv",
    "sg:city":"Yandina",
    "sg:classifiers":[
        {
            "category":"Home & Garden",
            "subcategory":"Building Materials",
            "type":"Retail Goods"
        }
    ],
    "sg:phone":"+61 7 5472 7055",
    "sg:postcode":"4561",
    "sg:province":"QLD",
    "sg:tags":[
        "supply"
    ],
    "wof:name":"Bergs Battens",
    "wof:placetype":"venue"
},
  "geometry": {"coordinates":[152.95933532699999,-26.5716934204],"type":"Point"}
}