{
  "type": "Feature",
  "properties": {
    "addr:full":"36 Victoria St Bunbury WA 6230",
    "addr:housenumber":"36",
    "addr:postcode":"6230",
    "addr:street":"Victoria St",
    "iso:country":"AU",
    "sg:address":"36 Victoria St",
    "sg:city":"Bunbury",
    "sg:classifiers":[
        {
            "category":"Travel",
            "subcategory":"Hotels & Motels",
            "type":"Entertainment"
        }
    ],
    "sg:phone":"+61 8 9721 2600",
    "sg:postcode":"6230",
    "sg:province":"WA",
    "sg:tags":[
        "accommodation"
    ],
    "wof:name":"Trafalgars Hotel",
    "wof:placetype":"venue"
},
  "geometry": {"coordinates":[115.637131,-33.322796],"type":"Point"}
}