{
  "type": "Feature",
  "properties": {
    "iso:country":"AU",
    "sg:address":"Unit 4, 79 Mandoon Rd",
    "sg:city":"Girraween",
    "sg:classifiers":[
        {
            "category":"Professional",
            "subcategory":"Business Services",
            "type":"Services"
        }
    ],
    "sg:phone":"+61 2 9631 4800",
    "sg:postcode":"2145",
    "sg:province":"NSW",
    "sg:tags":[
        "record",
        "management",
        "storage"
    ],
    "wof:name":"Allfiche Australia Pty Ltd",
    "wof:placetype":"venue"
},
  "geometry": {"coordinates":[150.93942260700001,-33.8029403687],"type":"Point"}
}