{
  "type": "Feature",
  "properties": {
    "addr:full":"Yulara Drv Yulara NT 0872",
    "addr:postcode":"nt 0872",
    "addr:street":"Yulara Drv",
    "iso:country":"AU",
    "sg:address":"Yulara Drv",
    "sg:city":"Yulara",
    "sg:classifiers":[
        {
            "category":"Government",
            "subcategory":"Fire Station",
            "type":"Public Place"
        }
    ],
    "sg:phone":"+61 8 8956 2061",
    "sg:postcode":"0872",
    "sg:province":"NT",
    "sg:tags":[
        "brigade"
    ],
    "wof:name":"Fire Service",
    "wof:placetype":"venue"
},
  "geometry": {"coordinates":[130.980377197,-25.2327594757],"type":"Point"}
}