{
  "type": "Feature",
  "properties": {
    "addr:full":"Shop 11 Midland Gate Shopping Centre Midland WA 6056",
    "addr:housenumber":"shop 11",
    "addr:postcode":"6056",
    "addr:street":"Midland Gate",
    "iso:country":"AU",
    "sg:address":"Shop 11 Midland Gate Shopping Centre",
    "sg:city":"Midland",
    "sg:classifiers":[
        {
            "category":"Food & Beverages",
            "subcategory":"Specialty",
            "type":"Retail Goods"
        }
    ],
    "sg:phone":"+61 8 9274 3167",
    "sg:postcode":"6056",
    "sg:province":"WA",
    "sg:tags":[
        "product",
        "health"
    ],
    "wof:name":"Good Life Health Stores",
    "wof:placetype":"venue"
},
  "geometry": {"coordinates":[116.02348327599999,-31.9312286377],"type":"Point"}
}