{
  "type": "Feature",
  "properties": {
    "iso:country":"AU",
    "sg:address":"26 Tepko Rd",
    "sg:city":"Terrey Hills",
    "sg:classifiers":[
        {
            "category":"Building & Trades",
            "subcategory":"Construction",
            "type":"Services"
        }
    ],
    "sg:phone":"+61 2 9450 0355",
    "sg:postcode":"2084",
    "sg:province":"NSW",
    "sg:tags":[
        "contractor"
    ],
    "wof:name":"Aspect Design & Development Pty Ltd",
    "wof:placetype":"venue"
},
  "geometry": {"coordinates":[151.224533081,-33.6829185486],"type":"Point"}
}