{
  "type": "Feature",
  "properties": {
    "iso:country":"AU",
    "sg:address":"58- 60 Williams Rd",
    "sg:city":"Dandenong South",
    "sg:classifiers":[
        {
            "category":"Retail",
            "subcategory":"Auto Repair",
            "type":"Services"
        }
    ],
    "sg:phone":"+61 3 9792 5944",
    "sg:postcode":"3164",
    "sg:province":"VIC",
    "sg:tags":[
        "repairer",
        "motor",
        "engineer"
    ],
    "wof:name":"Repco Authorised Service",
    "wof:placetype":"venue"
},
  "geometry": {"coordinates":[145.221160889,-38.0125694275],"type":"Point"}
}