{
  "type": "Feature",
  "properties": {
    "iso:country":"AU",
    "sg:address":"76 Nicholls Rd",
    "sg:city":"Ross Creek",
    "sg:classifiers":[
        {
            "category":"Home & Garden",
            "subcategory":"Building Materials",
            "type":"Retail Goods"
        }
    ],
    "sg:phone":"+61 408 519 817",
    "sg:postcode":"3351",
    "sg:province":"VIC",
    "sg:tags":[
        "wall",
        "frame",
        "truss",
        "roof"
    ],
    "wof:name":"Wall Frame Specialists Pty Ltd",
    "wof:placetype":"venue"
},
  "geometry": {"coordinates":[143.773087,-37.650112],"type":"Point"}
}