{
  "type": "Feature",
  "properties": {
    "addr:full":"Cnr Bridge & Nebo Rds Mackay QLD 4740",
    "addr:postcode":"4740",
    "addr:street":"Cnr Bridge &;Rds",
    "iso:country":"AU",
    "sg:address":"Cnr Bridge & Nebo Rds",
    "sg:city":"Mackay",
    "sg:classifiers":[
        {
            "category":"Health Services",
            "subcategory":"Doctor",
            "type":"Services"
        }
    ],
    "sg:phone":"+61 7 4957 6999",
    "sg:postcode":"4740",
    "sg:province":"QLD",
    "sg:tags":[
        "medical",
        "practitioner"
    ],
    "wof:name":"Mackay Family Medical Practice",
    "wof:placetype":"venue"
},
  "geometry": {"coordinates":[149.153458,-21.1668],"type":"Point"}
}