{
  "type": "Feature",
  "properties": {
    "iso:country":"AU",
    "sg:address":"74 Hampden Rd",
    "sg:city":"Lakemba",
    "sg:classifiers":[
        {
            "category":"Organizations",
            "subcategory":"Community Association",
            "type":"Services"
        }
    ],
    "sg:phone":"+61 2 9759 6966",
    "sg:postcode":"2195",
    "sg:province":"NSW",
    "sg:tags":[
        "organisation",
        "family",
        "welfare"
    ],
    "wof:name":"Centacare Disability Program Quamby Activity Centre",
    "wof:placetype":"venue"
},
  "geometry": {"coordinates":[151.073715,-33.916103],"type":"Point"}
}