{
  "type": "Feature",
  "properties": {
    "addr:full":"Cnr Channon St & Bruce Hwy Gympie QLD 4570",
    "addr:postcode":"4570",
    "addr:street":"Cnr Channon St & Bruce Hwy",
    "iso:country":"AU",
    "sg:address":"Cnr Channon St & Bruce Hwy",
    "sg:city":"Gympie",
    "sg:classifiers":[
        {
            "category":"Fast Food",
            "type":"Food & Drink"
        }
    ],
    "sg:phone":"+61 7 5482 5144",
    "sg:postcode":"4570",
    "sg:province":"QLD",
    "sg:tags":[
        "away",
        "take"
    ],
    "wof:name":"Brodies B.B.Q. Chicken & Beef Burgers",
    "wof:placetype":"venue"
},
  "geometry": {"coordinates":[152.65736389200001,-26.1891651154],"type":"Point"}
}