{
  "type": "Feature",
  "properties": {
    "addr:full":"14 - 16 Williams Rd Coburg VIC 3058",
    "addr:housenumber":"16",
    "addr:postcode":"3058",
    "addr:street":"Williams Rd",
    "iso:country":"AU",
    "sg:address":"14 - 16 Williams Rd",
    "sg:city":"Coburg",
    "sg:classifiers":[
        {
            "category":"Retail",
            "subcategory":"Auto Repair",
            "type":"Services"
        }
    ],
    "sg:phone":"+61 3 9350 3245",
    "sg:postcode":"3058",
    "sg:province":"VIC",
    "sg:tags":[
        "body",
        "motor",
        "trimmer"
    ],
    "wof:name":"Trimworld Automotive",
    "wof:placetype":"venue"
},
  "geometry": {"coordinates":[144.960250855,-37.7327804565],"type":"Point"}
}