{
  "type": "Feature",
  "properties": {
    "addr:full":"126b Sutherland Rd Beecroft NSW 2119",
    "addr:housenumber":"126b",
    "addr:postcode":"2119",
    "addr:street":"Sutherland Rd",
    "iso:country":"AU",
    "sg:address":"126b Sutherland Rd",
    "sg:city":"Beecroft",
    "sg:classifiers":[
        {
            "category":"Shopping",
            "subcategory":"Stationery & Office Supplies",
            "type":"Retail Goods"
        }
    ],
    "sg:phone":"+61 2 9484 3513",
    "sg:postcode":"2119",
    "sg:province":"NSW",
    "sg:tags":[
        "equipment",
        "display",
        "exhibition"
    ],
    "wof:name":"Catherall Bob Displays",
    "wof:placetype":"venue"
},
  "geometry": {"coordinates":[151.06607055699999,-33.7454681396],"type":"Point"}
}