{
  "type": "Feature",
  "properties": {
    "addr:full":"550 Olive St Albury NSW 2640",
    "addr:housenumber":"550",
    "addr:postcode":"2640",
    "addr:street":"Olive St",
    "iso:country":"AU",
    "sg:address":"550 Olive St",
    "sg:city":"Albury",
    "sg:classifiers":[
        {
            "category":"Shopping",
            "subcategory":"Clothing, Apparel, & Fashions",
            "type":"Retail Goods"
        }
    ],
    "sg:phone":"+61 2 6021 3226",
    "sg:postcode":"2640",
    "sg:province":"NSW",
    "sg:tags":[
        "menswear"
    ],
    "wof:name":"Perl A & Co",
    "wof:placetype":"venue"
},
  "geometry": {"coordinates":[146.918655395,-36.0792236328],"type":"Point"}
}