{
  "type": "Feature",
  "properties": {
    "addr:full":"1 Fleet St Fremantle WA 6160",
    "addr:housenumber":"1",
    "addr:postcode":"6160",
    "addr:street":"Fleet St",
    "iso:country":"AU",
    "sg:address":"1 Fleet St",
    "sg:city":"Fremantle",
    "sg:classifiers":[
        {
            "category":"Food & Beverages",
            "subcategory":"Meat & Fish",
            "type":"Retail Goods"
        }
    ],
    "sg:phone":"+61 8 9239 8000",
    "sg:postcode":"6160",
    "sg:province":"WA",
    "sg:tags":[
        "aquaculture"
    ],
    "wof:name":"The WA Maritime Training Centre",
    "wof:placetype":"venue"
},
  "geometry": {"coordinates":[115.741478,-32.054798],"type":"Point"}
}