{
  "type": "Feature",
  "properties": {
    "iso:country":"AU",
    "sg:address":"Beerwah Shpng Vlge Simpson Rd",
    "sg:city":"Beerwah",
    "sg:classifiers":[
        {
            "category":"Professional",
            "subcategory":"Accounting & Tax Preparation",
            "type":"Services"
        }
    ],
    "sg:phone":"+61 7 5494 6431",
    "sg:postcode":"4519",
    "sg:province":"QLD",
    "sg:tags":[
        "consultant",
        "taxation"
    ],
    "wof:name":"Noel R Box Services P/L",
    "wof:placetype":"venue"
},
  "geometry": {"coordinates":[152.96725499999999,-26.811001],"type":"Point"}
}