{
  "type": "Feature",
  "properties": {
    "iso:country":"AU",
    "sg:address":"Sullivan Drv",
    "sg:city":"Stanthorpe",
    "sg:classifiers":[
        {
            "category":"Wholesale",
            "subcategory":"Auto Parts",
            "type":"Manufacturing & Wholesale Goods"
        }
    ],
    "sg:phone":"+61 7 4681 2744",
    "sg:postcode":"4380",
    "sg:province":"QLD",
    "sg:tags":[
        "recyclers"
    ],
    "wof:name":"Stanthorpe Wreckers",
    "wof:placetype":"venue"
},
  "geometry": {"coordinates":[151.914856,-28.652502],"type":"Point"}
}