{
  "type": "Feature",
  "properties": {
    "iso:country":"AU",
    "sg:address":"3/ 134 Pascoe Vale Rd",
    "sg:city":"Moonee Ponds",
    "sg:classifiers":[
        {
            "category":"Professional",
            "subcategory":"Engineering",
            "type":"Services"
        }
    ],
    "sg:phone":"+61 3 9370 4462",
    "sg:postcode":"3039",
    "sg:province":"VIC",
    "sg:tags":[
        "consulting",
        "engineer"
    ],
    "wof:name":"Maries Production Services",
    "wof:placetype":"venue"
},
  "geometry": {"coordinates":[144.926147,-37.76088],"type":"Point"}
}