{
  "type": "Feature",
  "properties": {
    "iso:country":"AU",
    "sg:address":"55 Little Edward St",
    "sg:city":"Brisbane",
    "sg:classifiers":[
        {
            "category":"Professional",
            "type":"Services"
        }
    ],
    "sg:phone":"+61 1300 360 314",
    "sg:postcode":"4000",
    "sg:province":"QLD",
    "sg:tags":[
        "quality",
        "assurance"
    ],
    "wof:name":"SAI Global Limited",
    "wof:placetype":"venue"
},
  "geometry": {"coordinates":[153.02444457999999,-27.4616909027],"type":"Point"}
}