{
  "type": "Feature",
  "properties": {
    "addr:full":"30 Blenhem St Randwick NSW 2031",
    "addr:housenumber":"30",
    "addr:postcode":"2031",
    "addr:street":"Blenhem St",
    "iso:country":"AU",
    "sg:address":"30 Blenhem St",
    "sg:city":"Randwick",
    "sg:classifiers":[
        {
            "category":"Government",
            "subcategory":"Court House",
            "type":"Public Place"
        }
    ],
    "sg:phone":"+61 2 9130 6019",
    "sg:postcode":"2031",
    "sg:province":"NSW",
    "sg:tags":[
        "personal",
        "marriage",
        "family",
        "counselling"
    ],
    "wof:name":"Langford Trish",
    "wof:placetype":"venue"
},
  "geometry": {"coordinates":[151.239013672,-33.9164085388],"type":"Point"}
}