{
  "type": "Feature",
  "properties": {
    "iso:country":"AU",
    "sg:address":"6 Ocean St",
    "sg:city":"Maroochydore",
    "sg:classifiers":[
        {
            "category":"Professional",
            "subcategory":"Printing & Photocopies",
            "type":"Services"
        }
    ],
    "sg:phone":"+61 7 5479 0152",
    "sg:postcode":"4558",
    "sg:province":"QLD",
    "sg:tags":[
        "photocopying"
    ],
    "wof:name":"Worldwide Online Printing",
    "wof:placetype":"venue"
},
  "geometry": {"coordinates":[153.09156799300001,-26.6519298553],"type":"Point"}
}