{
  "type": "Feature",
  "properties": {
    "addr:full":"Fy 4/ 32 Roberna St Moorabbin VIC 3189",
    "addr:housenumber":"4 / 32",
    "addr:postcode":"3189",
    "addr:street":"Fy;Roberna St",
    "iso:country":"AU",
    "sg:address":"Fy 4/ 32 Roberna St",
    "sg:city":"Moorabbin",
    "sg:classifiers":[
        {
            "category":"Retail",
            "subcategory":"Auto Repair",
            "type":"Services"
        }
    ],
    "sg:phone":"+61 3 9532 5258",
    "sg:postcode":"3189",
    "sg:province":"VIC",
    "sg:tags":[
        "beater",
        "painter",
        "panel"
    ],
    "wof:name":"Renegade Prestige",
    "wof:placetype":"venue"
},
  "geometry": {"coordinates":[145.06802368199999,-37.9448776245],"type":"Point"}
}