{
  "type": "Feature",
  "properties": {
    "addr:full":"PO Box 457 Bellara QLD 4507",
    "addr:postcode":"4507",
    "iso:country":"AU",
    "sg:address":"PO Box 457",
    "sg:city":"Bellara",
    "sg:classifiers":[
        {
            "category":"Professional",
            "subcategory":"Employment Agencies",
            "type":"Services"
        }
    ],
    "sg:phone":"+61 7 3408 7700",
    "sg:postcode":"4507",
    "sg:province":"QLD",
    "sg:tags":[
        "entertainer",
        "agent"
    ],
    "wof:name":"Professor Wallace's Puppet Theatre",
    "wof:placetype":"venue"
},
  "geometry": {"coordinates":[153.147094727,-27.0590400696],"type":"Point"}
}