{
  "type": "Feature",
  "properties": {
    "addr:full":"189 Grange Rd Fairfield VIC 3078",
    "addr:housenumber":"189",
    "addr:postcode":"3078",
    "addr:street":"Grange Rd",
    "iso:country":"AU",
    "sg:address":"189 Grange Rd",
    "sg:city":"Fairfield",
    "sg:classifiers":[
        {
            "category":"Shopping",
            "subcategory":"Clothing, Apparel, & Fashions",
            "type":"Retail Goods"
        }
    ],
    "sg:phone":"+61 3 9499 9844",
    "sg:postcode":"3078",
    "sg:province":"VIC",
    "sg:tags":[
        "accessory"
    ],
    "wof:name":"Catherine Manuell Design",
    "wof:placetype":"venue"
},
  "geometry": {"coordinates":[145.026855469,-37.7683334351],"type":"Point"}
}