{
  "type": "Feature",
  "properties": {
    "addr:full":"32 Hassett St Leongatha VIC 3953",
    "addr:housenumber":"32",
    "addr:postcode":"3953",
    "addr:street":"Hassett St",
    "iso:country":"AU",
    "sg:address":"32 Hassett St",
    "sg:city":"Leongatha",
    "sg:classifiers":[
        {
            "category":"Banks & Credit Unions",
            "subcategory":"Investment Brokerage",
            "type":"Services"
        }
    ],
    "sg:phone":"+61 3 5662 0855",
    "sg:postcode":"3953",
    "sg:province":"VIC",
    "sg:tags":[
        "finance",
        "broker"
    ],
    "wof:name":"AG Peters Finance & Loans",
    "wof:placetype":"venue"
},
  "geometry": {"coordinates":[145.95184326200001,-38.4806175232],"type":"Point"}
}