{
  "type": "Feature",
  "properties": {
    "addr:full":"48 Eyre St Mt Gravatt East QLD 4122",
    "addr:housenumber":"48",
    "addr:postcode":"4122",
    "addr:street":"Eyre St",
    "iso:country":"AU",
    "sg:address":"48 Eyre St",
    "sg:city":"Mt Gravatt East",
    "sg:classifiers":[
        {
            "category":"Education",
            "subcategory":"Special Training",
            "type":"Public Place"
        }
    ],
    "sg:phone":"+61 7 3849 3949",
    "sg:postcode":"4122",
    "sg:province":"QLD",
    "sg:tags":[
        "development"
    ],
    "wof:name":"5 Quadrants",
    "wof:placetype":"venue"
},
  "geometry": {"coordinates":[153.08348083499999,-27.5357894897],"type":"Point"}
}