{
  "type": "Feature",
  "properties": {
    "addr:full":"3 Queen St Bundaberg QLD 4670",
    "addr:housenumber":"3",
    "addr:postcode":"4670",
    "addr:street":"Queen St",
    "iso:country":"AU",
    "sg:address":"3 Queen St",
    "sg:city":"Bundaberg",
    "sg:classifiers":[
        {
            "category":"Food & Beverages",
            "subcategory":"Supermarket",
            "type":"Retail Goods"
        }
    ],
    "sg:phone":"+61 7 4151 2601",
    "sg:postcode":"4670",
    "sg:province":"QLD",
    "sg:tags":[
        "grocery",
        "store"
    ],
    "wof:name":"727 Stores",
    "wof:placetype":"venue"
},
  "geometry": {"coordinates":[152.344406128,-24.8596172333],"type":"Point"}
}