{
  "type": "Feature",
  "properties": {
    "addr:full":"Kmart Plaza, Fitzroy St Carpark Tamworth NSW 2340",
    "addr:postcode":"2340",
    "addr:street":"Fitzroy",
    "iso:country":"AU",
    "sg:address":"Kmart Plaza, Fitzroy St",
    "sg:city":"Carpark Tamworth",
    "sg:classifiers":[
        {
            "category":"Retail",
            "subcategory":"Auto Repair",
            "type":"Services"
        }
    ],
    "sg:phone":"+61 2 6766 3555",
    "sg:postcode":"2340",
    "sg:province":"NSW",
    "sg:tags":[
        "repairer",
        "motor",
        "engineer"
    ],
    "wof:name":"Kmart Tyre & Auto Service Tamworth",
    "wof:placetype":"venue"
},
  "geometry": {"coordinates":[150.93028259299999,-31.0921001434],"type":"Point"}
}