{
  "type": "Feature",
  "properties": {
    "addr:full":"Anzac Ave Swan Reach SA 5354",
    "addr:postcode":"5354",
    "addr:street":"Anzac Ave",
    "iso:country":"AU",
    "sg:address":"Anzac Ave",
    "sg:city":"Swan Reach",
    "sg:classifiers":[
        {
            "category":"Food & Beverages",
            "subcategory":"Supermarket",
            "type":"Retail Goods"
        }
    ],
    "sg:phone":"+61 8 8570 2036",
    "sg:postcode":"5354",
    "sg:province":"SA",
    "sg:tags":[
        "grocery",
        "store"
    ],
    "wof:name":"Swan Reach General Store",
    "wof:placetype":"venue"
},
  "geometry": {"coordinates":[139.59927368199999,-34.5660667419],"type":"Point"}
}