{
  "type": "Feature",
  "properties": {
    "addr:full":"55 Newlands Rd Coburg North VIC 3058",
    "addr:housenumber":"55",
    "addr:postcode":"3058",
    "addr:street":"Newlands Rd",
    "iso:country":"AU",
    "sg:address":"55 Newlands Rd",
    "sg:city":"Coburg North",
    "sg:classifiers":[
        {
            "category":"Retail",
            "subcategory":"Storage",
            "type":"Services"
        }
    ],
    "sg:phone":"+61 3 9354 3059",
    "sg:postcode":"3058",
    "sg:province":"VIC",
    "sg:tags":[
        "removal",
        "furniture"
    ],
    "wof:name":"Clifton Hill Removals & Taxi Trucks",
    "wof:placetype":"venue"
},
  "geometry": {"coordinates":[144.97157287600001,-37.7298851013],"type":"Point"}
}