{
  "type": "Feature",
  "properties": {
    "iso:country":"AU",
    "sg:address":"82 Lyons Rd",
    "sg:city":"Sawtell",
    "sg:classifiers":[
        {
            "category":"Building & Trades",
            "subcategory":"Construction",
            "type":"Services"
        }
    ],
    "sg:phone":"+61 2 6653 2637",
    "sg:postcode":"2452",
    "sg:province":"NSW",
    "sg:tags":[
        "mural"
    ],
    "wof:name":"Aqua Marine Murals",
    "wof:placetype":"venue"
},
  "geometry": {"coordinates":[153.094284,-30.372826],"type":"Point"}
}