{
  "type": "Feature",
  "properties": {
    "iso:country":"AU",
    "sg:address":"Ricca Rd",
    "sg:city":"Ballandean",
    "sg:classifiers":[
        {
            "category":"Farming",
            "subcategory":"Berry Farm",
            "type":"Manufacturing & Wholesale Goods"
        }
    ],
    "sg:phone":"+61 7 4684 1146",
    "sg:postcode":"4382",
    "sg:province":"QLD",
    "sg:tags":[
        "fruit",
        "grower"
    ],
    "wof:name":"Puglisi S J",
    "wof:placetype":"venue"
},
  "geometry": {"coordinates":[151.822968,-28.81584],"type":"Point"}
}