{
  "type": "Feature",
  "properties": {
    "iso:country":"AU",
    "sg:address":"Unit 6/ 132 Queenscliffe St",
    "sg:city":"Queenscliff",
    "sg:classifiers":[
        {
            "category":"Professional",
            "subcategory":"Printing & Photocopies",
            "type":"Services"
        }
    ],
    "sg:phone":"+61 2 9905 5409",
    "sg:postcode":"2096",
    "sg:province":"NSW",
    "sg:tags":[
        "publishing",
        "desktop"
    ],
    "wof:name":"Indelible Proof Solutions",
    "wof:placetype":"venue"
},
  "geometry": {"coordinates":[151.283203125,-33.7822341919],"type":"Point"}
}