{
  "type": "Feature",
  "properties": {
    "addr:full":"60 Harvey St Woodville Park SA 5011",
    "addr:housenumber":"60",
    "addr:postcode":"5011",
    "addr:street":"Harvey St",
    "iso:country":"AU",
    "sg:address":"60 Harvey St",
    "sg:city":"Woodville Park",
    "sg:classifiers":[
        {
            "category":"Utilities",
            "subcategory":"Electric",
            "type":"Services"
        }
    ],
    "sg:phone":"+61 417 836 456",
    "sg:postcode":"5011",
    "sg:province":"SA",
    "sg:tags":[
        "electrical",
        "contractor"
    ],
    "wof:name":"Horak Paul Electrical",
    "wof:placetype":"venue"
},
  "geometry": {"coordinates":[138.54617309599999,-34.8815917969],"type":"Point"}
}