{
  "type": "Feature",
  "properties": {
    "addr:full":"36 Collins St Ceduna SA 5690",
    "addr:housenumber":"36",
    "addr:postcode":"5690",
    "addr:street":"Collins St",
    "iso:country":"AU",
    "sg:address":"36 Collins St",
    "sg:city":"Ceduna",
    "sg:classifiers":[
        {
            "category":"Building & Trades",
            "subcategory":"Landscaping Services",
            "type":"Services"
        }
    ],
    "sg:phone":"+61 408 581 625",
    "sg:postcode":"5690",
    "sg:province":"SA",
    "sg:tags":[
        "stump",
        "tree",
        "felling",
        "removal"
    ],
    "wof:name":"Ceduna Tree Trimming",
    "wof:placetype":"venue"
},
  "geometry": {"coordinates":[133.68511962900001,-32.1265869141],"type":"Point"}
}