{
  "type": "Feature",
  "properties": {
    "addr:full":"9B Bowen St Toowoomba QLD 4350",
    "addr:housenumber":"9b",
    "addr:postcode":"4350",
    "addr:street":"Bowen St",
    "iso:country":"AU",
    "sg:address":"9B Bowen St",
    "sg:city":"Toowoomba",
    "sg:classifiers":[
        {
            "category":"Home & Garden",
            "subcategory":"Furniture",
            "type":"Retail Goods"
        }
    ],
    "sg:phone":"+61 7 4632 1598",
    "sg:postcode":"4350",
    "sg:province":"QLD",
    "sg:tags":[
        "business"
    ],
    "wof:name":"Clem Nicol",
    "wof:placetype":"venue"
},
  "geometry": {"coordinates":[151.95515399999999,-27.558397],"type":"Point"}
}