{
  "type": "Feature",
  "properties": {
    "addr:full":"20 Heathfield Rd Coolum Beach QLD 4573",
    "addr:housenumber":"20",
    "addr:postcode":"4573",
    "addr:street":"Heathfield Rd",
    "iso:country":"AU",
    "sg:address":"20 Heathfield Rd",
    "sg:city":"Coolum Beach",
    "sg:classifiers":[
        {
            "category":"Banks & Credit Unions",
            "subcategory":"Financial Services",
            "type":"Services"
        }
    ],
    "sg:phone":"+61 7 5446 4600",
    "sg:postcode":"4573",
    "sg:province":"QLD",
    "sg:tags":[
        "advisory",
        "planning",
        "retirement"
    ],
    "wof:name":"Barber Ray",
    "wof:placetype":"venue"
},
  "geometry": {"coordinates":[153.08908099999999,-26.527225],"type":"Point"}
}