{
  "type": "Feature",
  "properties": {
    "iso:country":"AU",
    "sg:address":"Lot 51 Luke Road",
    "sg:city":"Clarendon. C/- Clarendon GPO SA 5157 Clarendo",
    "sg:classifiers":[
        {
            "category":"Building & Trades",
            "subcategory":"Landscaping Services",
            "type":"Services"
        }
    ],
    "sg:phone":"+61 414 858 971",
    "sg:postcode":"5157",
    "sg:province":"SA",
    "sg:tags":[
        "inspection"
    ],
    "wof:name":"S B Improvements",
    "wof:placetype":"venue"
},
  "geometry": {"coordinates":[138.617950439,-35.1037483215],"type":"Point"}
}