{
  "type": "Feature",
  "properties": {
    "addr:full":"24 Howard St Box Hill VIC 3128",
    "addr:housenumber":"24",
    "addr:postcode":"3128",
    "addr:street":"Howard St",
    "iso:country":"AU",
    "sg:address":"24 Howard St",
    "sg:city":"Box Hill",
    "sg:classifiers":[
        {
            "category":"Health Services",
            "subcategory":"Health Practitioner",
            "type":"Services"
        }
    ],
    "sg:phone":"+61 3 9898 5710",
    "sg:postcode":"3128",
    "sg:province":"VIC",
    "sg:tags":[
        "psychologist"
    ],
    "wof:name":"Anderson Janine",
    "wof:placetype":"venue"
},
  "geometry": {"coordinates":[145.120697022,-37.8224868774],"type":"Point"}
}