{
  "type": "Feature",
  "properties": {
    "iso:country":"AU",
    "sg:address":"Collins Pl",
    "sg:city":"Melbourne",
    "sg:classifiers":[
        {
            "category":"Food & Beverages",
            "subcategory":"Specialty",
            "type":"Retail Goods"
        }
    ],
    "sg:phone":"+61 3 9654 8790",
    "sg:postcode":"3000",
    "sg:province":"VIC",
    "sg:tags":[
        "product",
        "health"
    ],
    "wof:name":"Great Gourmet Health Food Shop",
    "wof:placetype":"venue"
},
  "geometry": {"coordinates":[144.97329711899999,-37.8142318726],"type":"Point"}
}