{
  "type": "Feature",
  "properties": {
    "addr:full":"4 Hutchinson St Burleigh Heads QLD 4220",
    "addr:housenumber":"4",
    "addr:postcode":"4220",
    "addr:street":"Hutchinson St",
    "iso:country":"AU",
    "sg:address":"4 Hutchinson St",
    "sg:city":"Burleigh Heads",
    "sg:classifiers":[
        {
            "category":"Building & Trades",
            "subcategory":"Construction",
            "type":"Services"
        }
    ],
    "sg:phone":"+61 7 5533 4018",
    "sg:postcode":"4220",
    "sg:province":"QLD",
    "sg:tags":[
        "pool",
        "swimming"
    ],
    "wof:name":"Queensland Pebble & Marblespray",
    "wof:placetype":"venue"
},
  "geometry": {"coordinates":[153.42369079599999,-28.1035747528],"type":"Point"}
}