{
  "type": "Feature",
  "properties": {
    "addr:full":"53 Walton St Cowes VIC 3922",
    "addr:housenumber":"53",
    "addr:postcode":"3922",
    "addr:street":"Walton St",
    "iso:country":"AU",
    "sg:address":"53 Walton St",
    "sg:city":"Cowes",
    "sg:classifiers":[
        {
            "category":"Building & Trades",
            "subcategory":"Construction",
            "type":"Services"
        }
    ],
    "sg:phone":"+61 3 5952 5300",
    "sg:postcode":"3922",
    "sg:province":"VIC",
    "sg:tags":[
        "concrete",
        "contractor"
    ],
    "wof:name":"Phillip Island Concreting Service",
    "wof:placetype":"venue"
},
  "geometry": {"coordinates":[145.24223327600001,-38.4595527649],"type":"Point"}
}