{
  "type": "Feature",
  "properties": {
    "addr:full":"306 Hancock Rd Redwood Park SA 5097",
    "addr:housenumber":"306",
    "addr:postcode":"5097",
    "addr:street":"Hancock Rd",
    "iso:country":"AU",
    "sg:address":"306 Hancock Rd",
    "sg:city":"Redwood Park",
    "sg:classifiers":[
        {
            "category":"Retail",
            "subcategory":"Driving School",
            "type":"Services"
        }
    ],
    "sg:phone":"+61 8 8251 1046",
    "sg:postcode":"5097",
    "sg:province":"SA",
    "wof:name":"Budget School Of Motoring",
    "wof:placetype":"venue"
},
  "geometry": {"coordinates":[138.71731567399999,-34.8059997559],"type":"Point"}
}