{
  "type": "Feature",
  "properties": {
    "addr:full":"Shop 1/ 63 Veterans Pde Collaroy Plateau NSW 2097",
    "addr:housenumber":"shop 1 / 63",
    "addr:postcode":"2097",
    "addr:street":"Veterans Pde",
    "iso:country":"AU",
    "sg:address":"Shop 1/ 63 Veterans Pde",
    "sg:city":"Collaroy Plateau",
    "sg:classifiers":[
        {
            "category":"Health Services",
            "subcategory":"Dentist",
            "type":"Services"
        }
    ],
    "sg:phone":"+61 2 9971 5067",
    "sg:postcode":"2097",
    "sg:province":"NSW",
    "wof:name":"Ng Samuel K",
    "wof:placetype":"venue"
},
  "geometry": {"coordinates":[151.28677368199999,-33.7267837524],"type":"Point"}
}