{
  "type": "Feature",
  "properties": {
    "addr:full":"13 Darter Pl Queens Park WA 6107",
    "addr:housenumber":"13",
    "addr:postcode":"6107",
    "addr:street":"Darter Pl Queens",
    "iso:country":"AU",
    "sg:address":"13 Darter Pl",
    "sg:city":"Queens Park",
    "sg:classifiers":[
        {
            "category":"Utilities",
            "type":"Services"
        }
    ],
    "sg:phone":"+61 418 907 900",
    "sg:postcode":"6107",
    "sg:province":"WA",
    "sg:tags":[
        "refrigeration",
        "industrial",
        "commercial",
        "retail"
    ],
    "wof:name":"Australasia Coolrooms",
    "wof:placetype":"venue"
},
  "geometry": {"coordinates":[115.935440063,-32.0036315918],"type":"Point"}
}