{
  "type": "Feature",
  "properties": {
    "addr:full":"115 Anzac Hwy Kurralta Park SA 5037",
    "addr:housenumber":"115",
    "addr:postcode":"5037",
    "addr:street":"Anzac Hwy",
    "iso:country":"AU",
    "sg:address":"115 Anzac Hwy",
    "sg:city":"Kurralta Park",
    "sg:classifiers":[
        {
            "category":"Health Services",
            "subcategory":"Dentist",
            "type":"Services"
        }
    ],
    "sg:phone":"+61 8 8351 6969",
    "sg:postcode":"5037",
    "sg:province":"SA",
    "wof:name":"Adelaide Teeth Whitening Centre",
    "wof:placetype":"venue"
},
  "geometry": {"coordinates":[138.57148742699999,-34.952911377],"type":"Point"}
}