{
  "type": "Feature",
  "properties": {
    "iso:country":"AU",
    "sg:address":"28 Aldinga St",
    "sg:city":"Blackmans Bay",
    "sg:classifiers":[
        {
            "category":"Shopping",
            "subcategory":"Musical Instruments",
            "type":"Retail Goods"
        }
    ],
    "sg:phone":"+61 3 6229 3081",
    "sg:postcode":"7052",
    "sg:province":"TAS",
    "sg:tags":[
        "musician",
        "agent"
    ],
    "wof:name":"Piccante",
    "wof:placetype":"venue"
},
  "geometry": {"coordinates":[147.32785000000001,-42.990978],"type":"Point"}
}