{
  "type": "Feature",
  "properties": {
    "addr:full":"Suite 17/ 7 Leeds St Footscray VIC 3011",
    "addr:housenumber":"17 / 7",
    "addr:postcode":"3011",
    "addr:street":"Leeds St",
    "iso:country":"AU",
    "sg:address":"Suite 17/ 7 Leeds St",
    "sg:city":"Footscray",
    "sg:classifiers":[
        {
            "category":"Home & Garden",
            "subcategory":"Kitchen Supply",
            "type":"Retail Goods"
        }
    ],
    "sg:phone":"+61 3 9687 8425",
    "sg:postcode":"3011",
    "sg:province":"VIC",
    "sg:tags":[
        "vegetable",
        "fruit",
        "grain",
        "exporter"
    ],
    "wof:name":"Ausfresh Express Pty Ltd",
    "wof:placetype":"venue"
},
  "geometry": {"coordinates":[144.90133667000001,-37.7987480164],"type":"Point"}
}