{
  "type": "Feature",
  "properties": {
    "iso:country":"AU",
    "sg:address":"47 Ashmore Rd",
    "sg:city":"Bundall",
    "sg:classifiers":[
        {
            "category":"Professional",
            "subcategory":"Printing & Photocopies",
            "type":"Services"
        }
    ],
    "sg:phone":"+61 7 5592 5558",
    "sg:postcode":"4217",
    "sg:province":"QLD",
    "sg:tags":[
        "photocopying"
    ],
    "wof:name":"Mac Copy",
    "wof:placetype":"venue"
},
  "geometry": {"coordinates":[153.40742492699999,-28.0104084015],"type":"Point"}
}