{
  "type": "Feature",
  "properties": {
    "iso:country":"AU",
    "sg:address":"61 William St",
    "sg:city":"Caloundra",
    "sg:classifiers":[
        {
            "category":"Manufacturing",
            "subcategory":"Rubber & Plastics",
            "type":"Manufacturing & Wholesale Goods"
        }
    ],
    "sg:phone":"+61 7 5491 3570",
    "sg:postcode":"4551",
    "sg:province":"QLD",
    "sg:tags":[
        "wholesaler",
        "product",
        "mfrs"
    ],
    "wof:name":"ASAP Plastics",
    "wof:placetype":"venue"
},
  "geometry": {"coordinates":[153.13221740700001,-26.7928333282],"type":"Point"}
}