{
  "type": "Feature",
  "properties": {
    "iso:country":"AU",
    "sg:address":"32 Delta St",
    "sg:city":"Geebung",
    "sg:classifiers":[
        {
            "category":"Manufacturing",
            "subcategory":"Building Materials",
            "type":"Manufacturing & Wholesale Goods"
        }
    ],
    "sg:phone":"+61 1300 132 002",
    "sg:postcode":"4034",
    "sg:province":"QLD",
    "sg:tags":[
        "equipment",
        "handling"
    ],
    "wof:name":"Task Australia",
    "wof:placetype":"venue"
},
  "geometry": {"coordinates":[153.049667,-27.365681],"type":"Point"}
}