{
  "type": "Feature",
  "properties": {
    "addr:full":"80 Hastings Pde North Bondi NSW 2026",
    "addr:housenumber":"80",
    "addr:postcode":"2026",
    "addr:street":"Hastings Pde",
    "iso:country":"AU",
    "sg:address":"80 Hastings Pde",
    "sg:city":"North Bondi",
    "sg:classifiers":[
        {
            "category":"Professional",
            "subcategory":"Art Services",
            "type":"Services"
        }
    ],
    "sg:phone":"+61 2 9365 6087",
    "sg:postcode":"2026",
    "sg:province":"NSW",
    "sg:tags":[
        "decorator",
        "painter"
    ],
    "wof:name":"Kevin Hornhardt Painting & Decorating",
    "wof:placetype":"venue"
},
  "geometry": {"coordinates":[151.28179931599999,-33.8877716064],"type":"Point"}
}