{
  "type": "Feature",
  "properties": {
    "addr:full":"46 Hill St Perth WA 6000",
    "addr:housenumber":"46",
    "addr:postcode":"6000",
    "addr:street":"Hill St",
    "iso:country":"AU",
    "sg:address":"46 Hill St",
    "sg:city":"Perth",
    "sg:classifiers":[
        {
            "category":"Retail",
            "subcategory":"Auto Rental",
            "type":"Services"
        }
    ],
    "sg:phone":"+61 8 9325 7677",
    "sg:postcode":"6000",
    "sg:province":"WA",
    "sg:tags":[
        "car",
        "hire",
        "minibus"
    ],
    "wof:name":"Avis",
    "wof:placetype":"venue"
},
  "geometry": {"coordinates":[115.868583679,-31.9580669403],"type":"Point"}
}