{
  "type": "Feature",
  "properties": {
    "iso:country":"AU",
    "sg:address":"399 Blackburn Rd",
    "sg:city":"Burwood East",
    "sg:classifiers":[
        {
            "category":"Retail",
            "subcategory":"Event Space",
            "type":"Services"
        }
    ],
    "sg:phone":"+61 3 9802 2477",
    "sg:postcode":"3151",
    "sg:province":"VIC",
    "sg:tags":[
        "venue",
        "reception",
        "wedding"
    ],
    "wof:name":"Golden Sands Reception Centre",
    "wof:placetype":"venue"
},
  "geometry": {"coordinates":[145.151153564,-37.8586654663],"type":"Point"}
}