{
  "type": "Feature",
  "properties": {
    "addr:full":"106 Wildey St Raceview QLD 4305",
    "addr:housenumber":"106",
    "addr:postcode":"4305",
    "addr:street":"Wildey St",
    "iso:country":"AU",
    "sg:address":"106 Wildey St",
    "sg:city":"Raceview",
    "sg:classifiers":[
        {
            "category":"Shopping",
            "subcategory":"Computers & Home Electronics",
            "type":"Retail Goods"
        }
    ],
    "sg:phone":"+61 7 3288 7244",
    "sg:postcode":"4305",
    "sg:province":"QLD",
    "sg:tags":[
        "hire",
        "video",
        "game"
    ],
    "wof:name":"Ipswich Software Solutions",
    "wof:placetype":"venue"
},
  "geometry": {"coordinates":[152.78216552699999,-27.6420192719],"type":"Point"}
}