{
  "type": "Feature",
  "properties": {
    "iso:country":"AU",
    "sg:address":"Unit 3/ 37 Lorn Rd",
    "sg:city":"Queanbeyan",
    "sg:classifiers":[
        {
            "category":"Retail",
            "subcategory":"Storage",
            "type":"Services"
        }
    ],
    "sg:phone":"+61 2 6299 0252",
    "sg:postcode":"2620",
    "sg:province":"NSW",
    "sg:tags":[
        "shelving",
        "system"
    ],
    "wof:name":"Canberra Shelving & CJ Systems",
    "wof:placetype":"venue"
},
  "geometry": {"coordinates":[149.210540772,-35.347492218],"type":"Point"}
}