{
  "type": "Feature",
  "properties": {
    "addr:full":"OPSM Shp 2 Cessnock City Cntr Cessnock NSW 2325",
    "addr:housenumber":"2",
    "addr:postcode":"2325",
    "addr:street":"Cessnock City Cntr",
    "iso:country":"AU",
    "sg:address":"OPSM Shp 2 Cessnock City Cntr",
    "sg:city":"Cessnock",
    "sg:classifiers":[
        {
            "category":"Health Services",
            "subcategory":"Optometrist",
            "type":"Services"
        }
    ],
    "sg:phone":"+61 2 4990 1766",
    "sg:postcode":"2325",
    "sg:province":"NSW",
    "wof:name":"Louie Loizou Optometrist",
    "wof:placetype":"venue"
},
  "geometry": {"coordinates":[151.35618591299999,-32.8411216736],"type":"Point"}
}