{
  "type": "Feature",
  "properties": {
    "addr:full":"109 Wollombi Rd Cessnock NSW 2325",
    "addr:housenumber":"109",
    "addr:postcode":"2325",
    "addr:street":"Wollombi Rd",
    "iso:country":"AU",
    "sg:address":"109 Wollombi Rd",
    "sg:city":"Cessnock",
    "sg:classifiers":[
        {
            "category":"Restaurant",
            "type":"Food & Drink"
        }
    ],
    "sg:phone":"+61 2 4990 3062",
    "sg:postcode":"2325",
    "sg:province":"NSW",
    "wof:name":"Cottage Restaurant",
    "wof:placetype":"venue"
},
  "geometry": {"coordinates":[151.35336303700001,-32.8333358765],"type":"Point"}
}