{
  "type": "Feature",
  "properties": {
    "addr:full":"Shop 2, 189 Anzac Ave Toowoomba QLD 4350",
    "addr:housenumber":"shop 2 189",
    "addr:postcode":"4350",
    "addr:street":"Anzac Ave",
    "iso:country":"AU",
    "sg:address":"Shop 2, 189 Anzac Ave",
    "sg:city":"Toowoomba",
    "sg:classifiers":[
        {
            "category":"Retail",
            "subcategory":"Auto Repair",
            "type":"Services"
        }
    ],
    "sg:phone":"+61 7 4633 2383",
    "sg:postcode":"4350",
    "sg:province":"QLD",
    "sg:tags":[
        "repairer",
        "motor",
        "engineer"
    ],
    "wof:name":"Ultra Tune",
    "wof:placetype":"venue"
},
  "geometry": {"coordinates":[151.92970299999999,-27.565884],"type":"Point"}
}