{
  "type": "Feature",
  "properties": {
    "addr:full":"118 Niagra St Armidale NSW 2350",
    "addr:housenumber":"118",
    "addr:postcode":"2350",
    "addr:street":"Niagra St",
    "iso:country":"AU",
    "sg:address":"118 Niagra St",
    "sg:city":"Armidale",
    "sg:classifiers":[
        {
            "category":"Industrial Area",
            "type":"Public Place"
        }
    ],
    "sg:phone":"+61 402 431 344",
    "sg:postcode":"2350",
    "sg:province":"NSW",
    "sg:tags":[
        "rural",
        "shed"
    ],
    "wof:name":"New England Sheds & Garages",
    "wof:placetype":"venue"
},
  "geometry": {"coordinates":[151.64991760300001,-30.509935379],"type":"Point"}
}