{
  "type": "Feature",
  "properties": {
    "iso:country":"AU",
    "sg:address":"199 Bondi Rd",
    "sg:city":"Bondi",
    "sg:classifiers":[
        {
            "category":"Restaurant",
            "type":"Food & Drink"
        }
    ],
    "sg:phone":"+61 2 9369 1233",
    "sg:postcode":"2026",
    "sg:province":"NSW",
    "wof:name":"Big John's Pizzas",
    "wof:placetype":"venue"
},
  "geometry": {"coordinates":[151.26498413100001,-33.8942070007],"type":"Point"}
}