{
  "type": "Feature",
  "properties": {
    "iso:country":"AU",
    "sg:address":"29 Kenneth St",
    "sg:city":"Inverloch",
    "sg:classifiers":[
        {
            "category":"Building & Trades",
            "subcategory":"Plumbing",
            "type":"Services"
        }
    ],
    "sg:phone":"+61 3 5674 1078",
    "sg:postcode":"3996",
    "sg:province":"VIC",
    "sg:tags":[
        "plumber",
        "gasfitters"
    ],
    "wof:name":"Parks W.K. & J.M.",
    "wof:placetype":"venue"
},
  "geometry": {"coordinates":[145.733231,-38.629395],"type":"Point"}
}