{
  "type": "Feature",
  "properties": {
    "addr:full":"130 Burwood Rd Burwood NSW 2134",
    "addr:housenumber":"130",
    "addr:postcode":"2134",
    "addr:street":"Burwood Rd",
    "iso:country":"AU",
    "sg:address":"130 Burwood Rd",
    "sg:city":"Burwood",
    "sg:classifiers":[
        {
            "category":"Cafe",
            "type":"Food & Drink"
        }
    ],
    "sg:phone":"+61 2 9744 7371",
    "sg:postcode":"2134",
    "sg:province":"NSW",
    "wof:name":"Cafe Gasparo",
    "wof:placetype":"venue"
},
  "geometry": {"coordinates":[151.10421752900001,-33.8755226135],"type":"Point"}
}