{
  "type": "Feature",
  "properties": {
    "iso:country":"AU",
    "sg:address":"Sanori House 126",
    "sg:city":"Grand Blvd Joondalup",
    "sg:classifiers":[
        {
            "category":"Health Services",
            "subcategory":"Doctor",
            "type":"Services"
        }
    ],
    "sg:phone":"+61 8 9300 3431",
    "sg:postcode":"6027",
    "sg:province":"WA",
    "sg:tags":[
        "medical",
        "practitioner"
    ],
    "wof:name":"Hayes John G",
    "wof:placetype":"venue"
},
  "geometry": {"coordinates":[115.769798279,-31.7418422699],"type":"Point"}
}