{
  "type": "Feature",
  "properties": {
    "addr:full":"169 Grange Rd Beverley SA 5009",
    "addr:housenumber":"169",
    "addr:postcode":"5009",
    "addr:street":"Grange Rd",
    "iso:country":"AU",
    "sg:address":"169 Grange Rd",
    "sg:city":"Beverley",
    "sg:classifiers":[
        {
            "category":"Building & Trades",
            "subcategory":"Construction",
            "type":"Services"
        }
    ],
    "sg:phone":"+61 8 8268 4100",
    "sg:postcode":"5009",
    "sg:province":"SA",
    "sg:tags":[
        "installation",
        "air conditioning"
    ],
    "wof:name":"York",
    "wof:placetype":"venue"
},
  "geometry": {"coordinates":[138.54803466800001,-34.9045639038],"type":"Point"}
}