{
  "type": "Feature",
  "properties": {
    "addr:full":"Suite 4, 2 King St Murwillumbah NSW 2484",
    "addr:housenumber":"2",
    "addr:postcode":"2484",
    "addr:street":"King St",
    "iso:country":"AU",
    "sg:address":"Suite 4, 2 King St",
    "sg:city":"Murwillumbah",
    "sg:classifiers":[
        {
            "category":"Health Services",
            "subcategory":"Doctor",
            "type":"Services"
        }
    ],
    "sg:phone":"+61 2 6672 5400",
    "sg:postcode":"2484",
    "sg:province":"NSW",
    "sg:tags":[
        "medical",
        "practitioner"
    ],
    "wof:name":"Meehan Bob Dr",
    "wof:placetype":"venue"
},
  "geometry": {"coordinates":[153.39718627900001,-28.3290538788],"type":"Point"}
}