{
  "type": "Feature",
  "properties": {
    "addr:full":"8 Minnie St Cairns QLD 4870",
    "addr:housenumber":"8",
    "addr:postcode":"4870",
    "addr:street":"Minnie St",
    "iso:country":"AU",
    "sg:address":"8 Minnie St",
    "sg:city":"Cairns",
    "sg:classifiers":[
        {
            "category":"Travel",
            "subcategory":"Hotels & Motels",
            "type":"Entertainment"
        }
    ],
    "sg:phone":"+61 7 4051 1211",
    "sg:postcode":"4870",
    "sg:province":"QLD",
    "wof:name":"Golden Chain Heritage Cairns",
    "wof:placetype":"venue"
},
  "geometry": {"coordinates":[145.77085876500001,-16.9173126221],"type":"Point"}
}