{
  "type": "Feature",
  "properties": {
    "iso:country":"AU",
    "sg:address":"Shop1, Ground Floor, Food Court, 270",
    "sg:city":"Canterbury Rd, Forest Hill Chase Forest Hill",
    "sg:classifiers":[
        {
            "category":"Shopping",
            "subcategory":"Mobile Phones",
            "type":"Retail Goods"
        }
    ],
    "sg:phone":"+61 13 19 30",
    "sg:postcode":"3131",
    "sg:province":"VIC",
    "sg:tags":[
        "telephone",
        "accessory"
    ],
    "wof:name":"TeleChoice",
    "wof:placetype":"venue"
},
  "geometry": {"coordinates":[145.173065186,-37.8350105286],"type":"Point"}
}