{
  "type": "Feature",
  "properties": {
    "addr:full":"PO Box 1635 Werribee Plaza VIC 3030",
    "addr:postcode":"3030",
    "iso:country":"AU",
    "sg:address":"PO Box 1635",
    "sg:city":"Werribee Plaza",
    "sg:classifiers":[
        {
            "category":"Professional",
            "subcategory":"Art Services",
            "type":"Services"
        }
    ],
    "sg:phone":"+61 415 487 466",
    "sg:postcode":"3030",
    "sg:province":"VIC",
    "sg:tags":[
        "graphic",
        "designer"
    ],
    "wof:name":"Design Solutions",
    "wof:placetype":"venue"
},
  "geometry": {"coordinates":[144.67593400000001,-37.937119],"type":"Point"}
}