{
  "type": "Feature",
  "properties": {
    "addr:full":"54 Terry Rd Box Hill NSW 2765",
    "addr:housenumber":"54",
    "addr:postcode":"2765",
    "addr:street":"Terry Rd",
    "iso:country":"AU",
    "sg:address":"54 Terry Rd",
    "sg:city":"Box Hill",
    "sg:classifiers":[
        {
            "category":"Utilities",
            "subcategory":"Electric",
            "type":"Services"
        }
    ],
    "sg:phone":"+61 2 9679 1384",
    "sg:postcode":"2765",
    "sg:province":"NSW",
    "sg:tags":[
        "electrical",
        "contractor"
    ],
    "wof:name":"Hudson Electronics",
    "wof:placetype":"venue"
},
  "geometry": {"coordinates":[150.89961242699999,-33.6475982666],"type":"Point"}
}