{
  "type": "Feature",
  "properties": {
    "addr:full":"44 Gerrale St Cronulla NSW 2230",
    "addr:housenumber":"44",
    "addr:postcode":"2230",
    "addr:street":"Gerrale St",
    "iso:country":"AU",
    "sg:address":"44 Gerrale St",
    "sg:city":"Cronulla",
    "sg:classifiers":[
        {
            "category":"Building & Trades",
            "subcategory":"Construction",
            "type":"Services"
        }
    ],
    "sg:phone":"+61 2 9544 3077",
    "sg:postcode":"2230",
    "sg:province":"NSW",
    "sg:tags":[
        "contractor"
    ],
    "wof:name":"David Chamberlain Builder",
    "wof:placetype":"venue"
},
  "geometry": {"coordinates":[151.15361023,-34.0542831421],"type":"Point"}
}