{
  "type": "Feature",
  "properties": {
    "addr:full":"4 Fulham Crt Robina QLD 4226",
    "addr:housenumber":"4",
    "addr:postcode":"4226",
    "addr:street":"Fulham Crt",
    "iso:country":"AU",
    "sg:address":"4 Fulham Crt",
    "sg:city":"Robina",
    "sg:classifiers":[
        {
            "category":"Shopping",
            "subcategory":"Optical Goods",
            "type":"Retail Goods"
        }
    ],
    "sg:phone":"+61 7 5580 8801",
    "sg:postcode":"4226",
    "sg:province":"QLD",
    "sg:tags":[
        "supply"
    ],
    "wof:name":"House Of Oz Ko Eyeware Qld Aust",
    "wof:placetype":"venue"
},
  "geometry": {"coordinates":[153.38824462900001,-28.0698471069],"type":"Point"}
}