{
  "type": "Feature",
  "properties": {
    "iso:country":"AU",
    "sg:address":"69 Lakeview Drv",
    "sg:city":"Deebing Heights",
    "sg:classifiers":[
        {
            "category":"Arena",
            "subcategory":"Sports Club",
            "type":"Entertainment"
        }
    ],
    "sg:phone":"+61 417 641 380",
    "sg:postcode":"4306",
    "sg:province":"QLD",
    "sg:tags":[
        "defence",
        "supply",
        "self",
        "instruction",
        "martial art"
    ],
    "wof:name":"Ipswich Kyokushin Karate",
    "wof:placetype":"venue"
},
  "geometry": {"coordinates":[152.754837036,-27.6684837341],"type":"Point"}
}