{
  "type": "Feature",
  "properties": {
    "iso:country":"AU",
    "sg:address":"31 Chesterman St",
    "sg:city":"Moonah",
    "sg:classifiers":[
        {
            "category":"Utilities",
            "type":"Services"
        }
    ],
    "sg:phone":"+61 408 144 217",
    "sg:postcode":"7009",
    "sg:province":"TAS",
    "sg:tags":[
        "refrigeration",
        "industrial",
        "commercial",
        "retail"
    ],
    "wof:name":"Polar-Air Refrigeration",
    "wof:placetype":"venue"
},
  "geometry": {"coordinates":[147.295852661,-42.8409919739],"type":"Point"}
}