{
  "type": "Feature",
  "properties": {
    "iso:country":"AU",
    "sg:address":"62 Ironwood St",
    "sg:city":"Aspley",
    "sg:classifiers":[
        {
            "category":"Real Estate",
            "subcategory":"Architect",
            "type":"Services"
        }
    ],
    "sg:phone":"+61 7 3862 7676",
    "sg:postcode":"4034",
    "sg:province":"QLD",
    "sg:tags":[
        "building",
        "designer"
    ],
    "wof:name":"Metropolitan Design & Drafting",
    "wof:placetype":"venue"
},
  "geometry": {"coordinates":[153.011551,-27.371935],"type":"Point"}
}