{
  "type": "Feature",
  "properties": {
    "addr:full":"Bradman Ave (Opp. Minti St) Maroochydore QLD 4558",
    "addr:postcode":"4558",
    "addr:street":"Bradman Ave Opp. Minti St",
    "iso:country":"AU",
    "sg:address":"Bradman Ave (Opp. Minti St)",
    "sg:city":"Maroochydore",
    "sg:classifiers":[
        {
            "category":"Recreation",
            "subcategory":"Boat Charter",
            "type":"Entertainment"
        }
    ],
    "sg:phone":"+61 419 399 460",
    "sg:postcode":"4558",
    "sg:province":"QLD",
    "sg:tags":[
        "hire",
        "drive"
    ],
    "wof:name":"Maroochy Sail Hire",
    "wof:placetype":"venue"
},
  "geometry": {"coordinates":[153.06602477999999,-26.642747879],"type":"Point"}
}