{
  "type": "Feature",
  "properties": {
    "addr:full":"211 Diagonal Rd Warradale SA 5046",
    "addr:housenumber":"211",
    "addr:postcode":"5046",
    "addr:street":"Diagonal Rd",
    "iso:country":"AU",
    "sg:address":"211 Diagonal Rd",
    "sg:city":"Warradale",
    "sg:classifiers":[
        {
            "category":"Shopping",
            "subcategory":"Pets & Pet Supplies",
            "type":"Retail Goods"
        }
    ],
    "sg:phone":"+61 8 8296 1710",
    "sg:postcode":"5046",
    "sg:province":"SA",
    "sg:tags":[
        "food"
    ],
    "wof:name":"Pet's Pantry Warradale",
    "wof:placetype":"venue"
},
  "geometry": {"coordinates":[138.53698700000001,-35.00597],"type":"Point"}
}