{
  "type": "Feature",
  "properties": {
    "addr:full":"PO Box 242 Kenthurst NSW 2156",
    "addr:postcode":"2156",
    "iso:country":"AU",
    "sg:address":"PO Box 242",
    "sg:city":"Kenthurst",
    "sg:classifiers":[
        {
            "category":"Building & Trades",
            "subcategory":"Construction",
            "type":"Services"
        }
    ],
    "sg:phone":"+61 412 218 784",
    "sg:postcode":"2156",
    "sg:province":"NSW",
    "sg:tags":[
        "concrete",
        "contractor"
    ],
    "wof:name":"Shore Concreting",
    "wof:placetype":"venue"
},
  "geometry": {"coordinates":[151.010818481,-33.6808700562],"type":"Point"}
}