{
  "type": "Feature",
  "properties": {
    "addr:full":"3 Bungendore Rd Queanbeyan NSW 2620",
    "addr:housenumber":"3",
    "addr:postcode":"2620",
    "addr:street":"Bungendore Rd",
    "iso:country":"AU",
    "sg:address":"3 Bungendore Rd",
    "sg:city":"Queanbeyan",
    "sg:classifiers":[
        {
            "category":"Fast Food",
            "type":"Food & Drink"
        }
    ],
    "sg:phone":"+61 2 6299 6837",
    "sg:postcode":"2620",
    "sg:province":"NSW",
    "sg:tags":[
        "away",
        "take"
    ],
    "wof:name":"Red Rooster",
    "wof:placetype":"venue"
},
  "geometry": {"coordinates":[149.24559020999999,-35.3476676941],"type":"Point"}
}