{
  "type": "Feature",
  "properties": {
    "addr:full":"Gray St Hughenden QLD 4821",
    "addr:postcode":"4821",
    "addr:street":"Gray St",
    "iso:country":"AU",
    "sg:address":"Gray St",
    "sg:city":"Hughenden",
    "sg:classifiers":[
        {
            "category":"Autos & Motor Vehicles",
            "subcategory":"Fuel & Gas Station",
            "type":"Retail Goods"
        }
    ],
    "sg:phone":"+61 7 4741 1132",
    "sg:postcode":"4821",
    "sg:province":"QLD",
    "wof:name":"V 8 Service Station",
    "wof:placetype":"venue"
},
  "geometry": {"coordinates":[144.200317383,-20.8438510895],"type":"Point"}
}