{
  "type": "Feature",
  "properties": {
    "iso:country":"AU",
    "sg:address":"46 John St",
    "sg:city":"Lilydale",
    "sg:classifiers":[
        {
            "category":"Retail",
            "subcategory":"Auto Rental",
            "type":"Services"
        }
    ],
    "sg:phone":"+61 1800 335 908",
    "sg:postcode":"3140",
    "sg:province":"VIC",
    "sg:tags":[
        "car",
        "hire",
        "minibus"
    ],
    "wof:name":"Ugly Duckling Rent A Car",
    "wof:placetype":"venue"
},
  "geometry": {"coordinates":[145.34324645999999,-37.7574081421],"type":"Point"}
}