{
  "type": "Feature",
  "properties": {
    "addr:full":"31 Seascape Drv Redhead NSW 2290",
    "addr:housenumber":"31",
    "addr:postcode":"2290",
    "addr:street":"Seascape Drv",
    "iso:country":"AU",
    "sg:address":"31 Seascape Drv",
    "sg:city":"Redhead",
    "sg:classifiers":[
        {
            "category":"Personal",
            "subcategory":"Beauty Salon",
            "type":"Services"
        }
    ],
    "sg:phone":"+61 2 4942 6333",
    "sg:postcode":"2290",
    "sg:province":"NSW",
    "sg:tags":[
        "hairdresser"
    ],
    "wof:name":"Divine Hair And Beauty",
    "wof:placetype":"venue"
},
  "geometry": {"coordinates":[151.71499633799999,-33.007976532],"type":"Point"}
}