{
  "type": "Feature",
  "properties": {
    "addr:full":"Shp 9 Oxley Arc 66 Queen St Marys NSW 2760",
    "addr:housenumber":"9;66",
    "addr:postcode":"2760",
    "addr:street":"Oxley Arc;Queen St",
    "iso:country":"AU",
    "sg:address":"Shp 9 Oxley Arc 66 Queen",
    "sg:city":"St Marys",
    "sg:classifiers":[
        {
            "category":"Health Services",
            "subcategory":"Health Practitioner",
            "type":"Services"
        }
    ],
    "sg:phone":"+61 2 9751 1283",
    "sg:postcode":"2760",
    "sg:province":"NSW",
    "sg:tags":[
        "psychologist"
    ],
    "wof:name":"Simpson Lorraine",
    "wof:placetype":"venue"
},
  "geometry": {"coordinates":[150.77455139200001,-33.7644538879],"type":"Point"}
}