{
  "type": "Feature",
  "properties": {
    "iso:country":"AU",
    "sg:address":"Henry Bailey Drv",
    "sg:city":"Mudgee",
    "sg:classifiers":[
        {
            "category":"Professional",
            "type":"Services"
        }
    ],
    "sg:phone":"+61 2 6372 3715",
    "sg:postcode":"2850",
    "sg:province":"NSW",
    "sg:tags":[
        "transport"
    ],
    "wof:name":"SJ Cook Stock & General Carrier &#034;Glen Ayre&#034;",
    "wof:placetype":"venue"
},
  "geometry": {"coordinates":[149.575943,-32.598938],"type":"Point"}
}