{
  "type": "Feature",
  "properties": {
    "addr:full":"Unit 2, 9 Bearing Rd Seven Hills NSW 2147",
    "addr:housenumber":"9",
    "addr:postcode":"2147",
    "addr:street":"Bearing Rd",
    "iso:country":"AU",
    "sg:address":"Unit 2, 9 Bearing Rd",
    "sg:city":"Seven Hills",
    "sg:classifiers":[
        {
            "category":"Retail",
            "subcategory":"Auto Repair",
            "type":"Services"
        }
    ],
    "sg:phone":"+61 2 9674 6989",
    "sg:postcode":"2147",
    "sg:province":"NSW",
    "sg:tags":[
        "engine",
        "reconditioning"
    ],
    "wof:name":"C & B Performance Reconditioning",
    "wof:placetype":"venue"
},
  "geometry": {"coordinates":[150.957275391,-33.7737731934],"type":"Point"}
}