{
  "type": "Feature",
  "properties": {
    "addr:full":"St John St Prahran VIC 3181",
    "addr:postcode":"3181",
    "addr:street":"St John St",
    "iso:country":"AU",
    "sg:address":"St John St",
    "sg:city":"Prahran",
    "sg:classifiers":[
        {
            "category":"Arts & Performance",
            "subcategory":"Theater",
            "type":"Entertainment"
        }
    ],
    "sg:phone":"+61 3 9214 6739",
    "sg:postcode":"3181",
    "sg:province":"VIC",
    "sg:tags":[
        "theatre"
    ],
    "wof:name":"David Williamson Theatre",
    "wof:placetype":"venue"
},
  "geometry": {"coordinates":[144.99206543,-37.8524017334],"type":"Point"}
}