{
  "type": "Feature",
  "properties": {
    "addr:full":"5 Gladstone Rd Biloela QLD 4715",
    "addr:housenumber":"5",
    "addr:postcode":"4715",
    "addr:street":"Gladstone Rd",
    "iso:country":"AU",
    "sg:address":"5 Gladstone Rd",
    "sg:city":"Biloela",
    "sg:classifiers":[
        {
            "category":"Real Estate",
            "subcategory":"Real Estate Agent",
            "type":"Services"
        }
    ],
    "sg:phone":"+61 7 4992 3366",
    "sg:postcode":"4715",
    "sg:province":"QLD",
    "wof:name":"First National Real Estate",
    "wof:placetype":"venue"
},
  "geometry": {"coordinates":[150.51498413100001,-24.4007301331],"type":"Point"}
}