{
  "type": "Feature",
  "properties": {
    "iso:country":"AU",
    "sg:address":"42 Lionel St",
    "sg:city":"Naval Base",
    "sg:classifiers":[
        {
            "category":"Professional",
            "subcategory":"Research",
            "type":"Services"
        }
    ],
    "sg:phone":"+61 8 9410 1116",
    "sg:postcode":"6165",
    "sg:province":"WA",
    "sg:tags":[
        "analyst"
    ],
    "wof:name":"Kanga & Associates Pty Ltd",
    "wof:placetype":"venue"
},
  "geometry": {"coordinates":[115.787659,-32.195972],"type":"Point"}
}