{
  "type": "Feature",
  "properties": {
    "iso:country":"AU",
    "sg:address":"47 Milsom St",
    "sg:city":"Coorparoo",
    "sg:classifiers":[
        {
            "category":"Building & Trades",
            "subcategory":"Pest Control",
            "type":"Services"
        }
    ],
    "sg:phone":"+61 407 377 761",
    "sg:postcode":"4151",
    "sg:province":"QLD",
    "wof:name":"Coorparoo Pest Control",
    "wof:placetype":"venue"
},
  "geometry": {"coordinates":[153.05667114299999,-27.4874191284],"type":"Point"}
}