{
  "type": "Feature",
  "properties": {
    "iso:country":"AU",
    "sg:address":"Unit 5/ 65 Meadow Ave",
    "sg:city":"Coopers Plains",
    "sg:classifiers":[
        {
            "category":"Retail",
            "subcategory":"Repair Shop",
            "type":"Services"
        }
    ],
    "sg:phone":"+61 7 3277 8842",
    "sg:postcode":"4108",
    "sg:province":"QLD",
    "sg:tags":[
        "upholsterer"
    ],
    "wof:name":"Stitch & Staple Upholstery",
    "wof:placetype":"venue"
},
  "geometry": {"coordinates":[153.02636718799999,-27.5660552979],"type":"Point"}
}