{
  "type": "Feature",
  "properties": {
    "addr:full":"8/ 35 Quirk Rd Manly Vale NSW 2093",
    "addr:housenumber":"/ 35",
    "addr:postcode":"2093",
    "addr:street":"Quirk Rd",
    "iso:country":"AU",
    "sg:address":"8/ 35 Quirk Rd",
    "sg:city":"Manly Vale",
    "sg:classifiers":[
        {
            "category":"Real Estate",
            "subcategory":"Surveying",
            "type":"Services"
        }
    ],
    "sg:phone":"+61 2 9948 3561",
    "sg:postcode":"2093",
    "sg:province":"NSW",
    "sg:tags":[
        "surveyor",
        "land"
    ],
    "wof:name":"Austin T M",
    "wof:placetype":"venue"
},
  "geometry": {"coordinates":[151.270462036,-33.7845306396],"type":"Point"}
}