{
  "type": "Feature",
  "properties": {
    "addr:full":"Lake Road Warehouse Centre 17-25 Lake Albert Rd Wagga Wagga NSW 2650",
    "addr:housenumber":"17-25",
    "addr:postcode":"2650",
    "addr:street":"Road;Lake Albert Rd",
    "iso:country":"AU",
    "sg:address":"Lake Road Warehouse Centre 17-25 Lake Albert Rd",
    "sg:city":"Wagga Wagga",
    "sg:classifiers":[
        {
            "category":"Shopping",
            "subcategory":"Crafts & Fabrics",
            "type":"Retail Goods"
        }
    ],
    "sg:phone":"+61 2 6921 4468",
    "sg:postcode":"2650",
    "sg:province":"NSW",
    "sg:tags":[
        "merchant",
        "cork"
    ],
    "wof:name":"Kooringal Carpet One",
    "wof:placetype":"venue"
},
  "geometry": {"coordinates":[147.37190246599999,-35.1490478516],"type":"Point"}
}