{
  "type": "Feature",
  "properties": {
    "addr:full":"25 Brook St Sunbury VIC 3429",
    "addr:housenumber":"25",
    "addr:postcode":"3429",
    "addr:street":"Brook St",
    "iso:country":"AU",
    "sg:address":"25 Brook St",
    "sg:city":"Sunbury",
    "sg:classifiers":[
        {
            "category":"Health Services",
            "subcategory":"Optometrist",
            "type":"Services"
        }
    ],
    "sg:phone":"+61 3 9744 7113",
    "sg:postcode":"3429",
    "sg:province":"VIC",
    "wof:name":"Tania Hartung",
    "wof:placetype":"venue"
},
  "geometry": {"coordinates":[144.730392456,-37.5800323486],"type":"Point"}
}