{
  "type": "Feature",
  "properties": {
    "addr:full":"3/ 127 Fryers St Shepparton VIC 3630",
    "addr:housenumber":"/ 127",
    "addr:postcode":"3630",
    "addr:street":"Fryers St",
    "iso:country":"AU",
    "sg:address":"3/ 127 Fryers St",
    "sg:city":"Shepparton",
    "sg:classifiers":[
        {
            "category":"Sports & Exercise",
            "subcategory":"Gym",
            "type":"Entertainment"
        }
    ],
    "sg:phone":"+61 438 316 959",
    "sg:postcode":"3630",
    "sg:province":"VIC",
    "sg:tags":[
        "personal",
        "trainer",
        "fitness"
    ],
    "wof:name":"Bliss Fitness & Wellbeing",
    "wof:placetype":"venue"
},
  "geometry": {"coordinates":[145.402999878,-36.3792419434],"type":"Point"}
}