{
  "type": "Feature",
  "properties": {
    "addr:full":"222 Napper Rd Parkwood QLD 4214",
    "addr:housenumber":"222",
    "addr:postcode":"4214",
    "addr:street":"Napper Rd",
    "iso:country":"AU",
    "sg:address":"222 Napper Rd",
    "sg:city":"Parkwood",
    "sg:classifiers":[
        {
            "category":"Health Services",
            "subcategory":"Health Practitioner",
            "type":"Services"
        }
    ],
    "sg:phone":"+61 7 5594 9252",
    "sg:postcode":"4214",
    "sg:province":"QLD",
    "sg:tags":[
        "naturopath"
    ],
    "wof:name":"Halina Oxnard ND, BHSc (Nat)",
    "wof:placetype":"venue"
},
  "geometry": {"coordinates":[153.35430908199999,-27.945690155],"type":"Point"}
}