{
  "type": "Feature",
  "properties": {
    "addr:full":"U11/ 62 Keane St Currajong QLD 4812",
    "addr:postcode":"4812",
    "addr:street":"/ 62 Keane St",
    "iso:country":"AU",
    "sg:address":"U11/ 62 Keane St",
    "sg:city":"Currajong",
    "sg:classifiers":[
        {
            "category":"Fast Food",
            "type":"Food & Drink"
        }
    ],
    "sg:phone":"+61 7 4779 7515",
    "sg:postcode":"4812",
    "sg:province":"QLD",
    "sg:tags":[
        "away",
        "take"
    ],
    "wof:name":"Keane For Food",
    "wof:placetype":"venue"
},
  "geometry": {"coordinates":[146.775543,-19.271448],"type":"Point"}
}