{
  "type": "Feature",
  "properties": {
    "addr:full":"9 Loch St Torquay VIC 3228",
    "addr:housenumber":"9",
    "addr:postcode":"3228",
    "addr:street":"Loch St",
    "iso:country":"AU",
    "sg:address":"9 Loch St",
    "sg:city":"Torquay",
    "sg:classifiers":[
        {
            "category":"Professional",
            "subcategory":"Art Services",
            "type":"Services"
        }
    ],
    "sg:phone":"+61 411 356 911",
    "sg:postcode":"3228",
    "sg:province":"VIC",
    "sg:tags":[
        "interior",
        "designer"
    ],
    "wof:name":"Act One",
    "wof:placetype":"venue"
},
  "geometry": {"coordinates":[144.31811500000001,-38.329899],"type":"Point"}
}