{
  "type": "Feature",
  "properties": {
    "addr:full":"21 Murray St Nuriootpa SA 5355",
    "addr:housenumber":"21",
    "addr:postcode":"5355",
    "addr:street":"Murray St",
    "iso:country":"AU",
    "sg:address":"21 Murray St",
    "sg:city":"Nuriootpa",
    "sg:classifiers":[
        {
            "category":"Shopping",
            "subcategory":"Clothing, Apparel, & Fashions",
            "type":"Retail Goods"
        }
    ],
    "sg:phone":"+61 8 8568 6021",
    "sg:postcode":"5355",
    "sg:province":"SA",
    "sg:tags":[
        "menswear"
    ],
    "wof:name":"Mensland",
    "wof:placetype":"venue"
},
  "geometry": {"coordinates":[138.99546814000001,-34.4732017517],"type":"Point"}
}