{
  "type": "Feature",
  "properties": {
    "addr:full":"Unit 4/ 173 Wellington Rd Clayton VIC 3168",
    "addr:housenumber":"/ 173",
    "addr:postcode":"3168",
    "addr:street":"Wellington Rd",
    "iso:country":"AU",
    "sg:address":"Unit 4/ 173 Wellington Rd",
    "sg:city":"Clayton",
    "sg:classifiers":[
        {
            "category":"Building & Trades",
            "subcategory":"Landscaping Services",
            "type":"Services"
        }
    ],
    "sg:phone":"+61 418 388 113",
    "sg:postcode":"3168",
    "sg:province":"VIC",
    "sg:tags":[
        "stump",
        "tree",
        "felling",
        "removal"
    ],
    "wof:name":"City & Rural Tree Services",
    "wof:placetype":"venue"
},
  "geometry": {"coordinates":[145.145996094,-37.9167709351],"type":"Point"}
}