{
  "type": "Feature",
  "properties": {
    "iso:country":"AU",
    "sg:address":"149 Simpson Ave",
    "sg:city":"Rockingham",
    "sg:classifiers":[
        {
            "category":"Social Services",
            "subcategory":"Child Care",
            "type":"Services"
        }
    ],
    "sg:phone":"+61 8 9591 3240",
    "sg:postcode":"6168",
    "sg:province":"WA",
    "wof:name":"Rockingham Early Learning & Child Care Centre Inc",
    "wof:placetype":"venue"
},
  "geometry": {"coordinates":[115.757698,-32.281448],"type":"Point"}
}