{
  "type": "Feature",
  "properties": {
    "addr:full":"Shp9a/ 95 Mooloolaba Esp Mooloolaba QLD 4557",
    "addr:postcode":"4557",
    "iso:country":"AU",
    "sg:address":"Shp9a/ 95 Mooloolaba Esp",
    "sg:city":"Mooloolaba",
    "sg:classifiers":[
        {
            "category":"Personal",
            "subcategory":"Massage",
            "type":"Services"
        }
    ],
    "sg:phone":"+61 408 435 524",
    "sg:postcode":"4557",
    "sg:province":"QLD",
    "sg:tags":[
        "therapy"
    ],
    "wof:name":"Dynamic Massage",
    "wof:placetype":"venue"
},
  "geometry": {"coordinates":[153.11993408199999,-26.679813385],"type":"Point"}
}