{
  "type": "Feature",
  "properties": {
    "iso:country":"AU",
    "sg:address":"16 Bond St",
    "sg:city":"Ringwood",
    "sg:classifiers":[
        {
            "category":"Government",
            "subcategory":"Court House",
            "type":"Public Place"
        }
    ],
    "sg:phone":"+61 3 9871 6300",
    "sg:postcode":"3134",
    "sg:province":"VIC",
    "sg:tags":[
        "personal",
        "marriage",
        "family",
        "counselling"
    ],
    "wof:name":"Family Relationship Centre",
    "wof:placetype":"venue"
},
  "geometry": {"coordinates":[145.225463867,-37.8138542175],"type":"Point"}
}