{
  "type": "Feature",
  "properties": {
    "iso:country":"AU",
    "sg:address":"112 Thistle St",
    "sg:city":"Gordon Park",
    "sg:classifiers":[
        {
            "category":"Personal",
            "subcategory":"Beauty Salon",
            "type":"Services"
        }
    ],
    "sg:phone":"+61 7 3357 6990",
    "sg:postcode":"4031",
    "sg:province":"QLD",
    "sg:tags":[
        "hairdresser"
    ],
    "wof:name":"Chriss Clip Joint",
    "wof:placetype":"venue"
},
  "geometry": {"coordinates":[153.028976,-27.419758],"type":"Point"}
}