{
  "type": "Feature",
  "properties": {
    "iso:country":"AU",
    "sg:address":"85 Main St",
    "sg:city":"Alstonville",
    "sg:classifiers":[
        {
            "category":"Personal",
            "subcategory":"Beauty Salon",
            "type":"Services"
        }
    ],
    "sg:phone":"+61 2 6628 1622",
    "sg:postcode":"2477",
    "sg:province":"NSW",
    "sg:tags":[
        "hairdresser"
    ],
    "wof:name":"Clarkes On Main Hairdressing",
    "wof:placetype":"venue"
},
  "geometry": {"coordinates":[153.43588256800001,-28.8379631042],"type":"Point"}
}