{
  "type": "Feature",
  "properties": {
    "iso:country":"AU",
    "sg:address":"34 Mooney St",
    "sg:city":"Lane Cove",
    "sg:classifiers":[
        {
            "category":"Professional",
            "subcategory":"Employment Agencies",
            "type":"Services"
        }
    ],
    "sg:phone":"+61 2 9418 9702",
    "sg:postcode":"2066",
    "sg:province":"NSW",
    "sg:tags":[
        "entertainer",
        "agent"
    ],
    "wof:name":"Zurina's Entertainment Agency",
    "wof:placetype":"venue"
},
  "geometry": {"coordinates":[151.159622192,-33.8006210327],"type":"Point"}
}