{
  "type": "Feature",
  "properties": {
    "addr:full":"Bolong Centre, 54 Bolong Rd Bomaderry NSW 2541",
    "addr:housenumber":"54",
    "addr:postcode":"2541",
    "addr:street":"Bolong Rd",
    "iso:country":"AU",
    "sg:address":"Bolong Centre, 54 Bolong Rd",
    "sg:city":"Bomaderry",
    "sg:classifiers":[
        {
            "category":"Building & Trades",
            "subcategory":"Construction",
            "type":"Services"
        }
    ],
    "sg:phone":"+61 2 4423 2655",
    "sg:postcode":"2541",
    "sg:province":"NSW",
    "sg:tags":[
        "window",
        "aluminium"
    ],
    "wof:name":"Sidney Hudson Windows & Doors",
    "wof:placetype":"venue"
},
  "geometry": {"coordinates":[150.62159729000001,-34.8517074585],"type":"Point"}
}