{
  "type": "Feature",
  "properties": {
    "addr:full":"13 Henson St Brighton-le-Sands NSW 2216",
    "addr:housenumber":"13",
    "addr:postcode":"2216",
    "addr:street":"Henson St",
    "iso:country":"AU",
    "sg:address":"13 Henson St",
    "sg:city":"Brighton-le-Sands",
    "sg:classifiers":[
        {
            "category":"Health Services",
            "subcategory":"Nursing And Care Facility",
            "type":"Services"
        }
    ],
    "sg:phone":"+61 2 9599 2219",
    "sg:postcode":"2216",
    "sg:province":"NSW",
    "sg:tags":[
        "home"
    ],
    "wof:name":"Jenny-Lyn Nursing Home",
    "wof:placetype":"venue"
},
  "geometry": {"coordinates":[151.15580700000001,-33.954971],"type":"Point"}
}