{
  "type": "Feature",
  "properties": {
    "iso:country":"AU",
    "sg:address":"1 First St",
    "sg:city":"Clayton",
    "sg:classifiers":[
        {
            "category":"Cafe",
            "type":"Food & Drink"
        }
    ],
    "sg:phone":"+61 3 9545 5035",
    "sg:postcode":"3168",
    "sg:province":"VIC",
    "wof:name":"Cafe Kombi",
    "wof:placetype":"venue"
},
  "geometry": {"coordinates":[145.135375977,-37.9307746887],"type":"Point"}
}