{
  "type": "Feature",
  "properties": {
    "iso:country":"AU",
    "sg:address":"Un 6 110 Spurway St",
    "sg:city":"Ermington",
    "sg:classifiers":[
        {
            "category":"Building & Trades",
            "subcategory":"Construction",
            "type":"Services"
        }
    ],
    "sg:phone":"+61 425 322 993",
    "sg:postcode":"2115",
    "sg:province":"NSW",
    "sg:tags":[
        "contractor"
    ],
    "wof:name":"Modenar Construction Pty Ltd",
    "wof:placetype":"venue"
},
  "geometry": {"coordinates":[151.05436706500001,-33.806312561],"type":"Point"}
}