{
  "type": "Feature",
  "properties": {
    "iso:country":"AU",
    "sg:address":"56 Hedge End Rd",
    "sg:city":"Mitcham",
    "sg:classifiers":[
        {
            "category":"Social Services",
            "subcategory":"Child Care",
            "type":"Services"
        }
    ],
    "sg:phone":"+61 3 9874 6401",
    "sg:postcode":"3132",
    "sg:province":"VIC",
    "wof:name":"Tinkabell Kindergarten & Child Care Centre",
    "wof:placetype":"venue"
},
  "geometry": {"coordinates":[145.184783936,-37.8072242737],"type":"Point"}
}