{
  "type": "Feature",
  "properties": {
    "iso:country":"AU",
    "sg:address":"1 Roseby St",
    "sg:city":"Marrickville",
    "sg:classifiers":[
        {
            "category":"Health Services",
            "subcategory":"Health Practitioner",
            "type":"Services"
        }
    ],
    "sg:phone":"+61 401 997 104",
    "sg:postcode":"2204",
    "sg:province":"NSW",
    "sg:tags":[
        "reiki"
    ],
    "wof:name":"Triple Tranquillity",
    "wof:placetype":"venue"
},
  "geometry": {"coordinates":[151.147583,-33.919296],"type":"Point"}
}