{
  "type": "Feature",
  "properties": {
    "iso:country":"AU",
    "sg:address":"154 Queen St",
    "sg:city":"St Marys",
    "sg:classifiers":[
        {
            "category":"Health Services",
            "subcategory":"Doctor",
            "type":"Services"
        }
    ],
    "sg:phone":"+61 2 9623 9933",
    "sg:postcode":"2760",
    "sg:province":"NSW",
    "sg:tags":[
        "medical",
        "practitioner"
    ],
    "wof:name":"Gabrael A",
    "wof:placetype":"venue"
},
  "geometry": {"coordinates":[150.773895264,-33.7666435242],"type":"Point"}
}