{
  "type": "Feature",
  "properties": {
    "addr:full":"3/ 79 Kelvin Rd Maddington WA 6109",
    "addr:housenumber":"/ 79",
    "addr:postcode":"6109",
    "addr:street":"Kelvin Rd",
    "iso:country":"AU",
    "sg:address":"3/ 79 Kelvin Rd",
    "sg:city":"Maddington",
    "sg:classifiers":[
        {
            "category":"Retail",
            "subcategory":"Auto Repair",
            "type":"Services"
        }
    ],
    "sg:phone":"+61 8 9452 0001",
    "sg:postcode":"6109",
    "sg:province":"WA",
    "sg:tags":[
        "clutch",
        "brake"
    ],
    "wof:name":"Just Right Brake & Clutch",
    "wof:placetype":"venue"
},
  "geometry": {"coordinates":[115.993972778,-32.0404243469],"type":"Point"}
}