{
  "type": "Feature",
  "properties": {
    "addr:full":"56 Rosemont St Wollongong NSW 2500",
    "addr:housenumber":"56",
    "addr:postcode":"2500",
    "addr:street":"Rosemont St",
    "iso:country":"AU",
    "sg:address":"56 Rosemont St",
    "sg:city":"Wollongong",
    "sg:classifiers":[
        {
            "category":"Health Services",
            "subcategory":"Doctor",
            "type":"Services"
        }
    ],
    "sg:phone":"+61 2 4226 5499",
    "sg:postcode":"2500",
    "sg:province":"NSW",
    "sg:tags":[
        "medical",
        "practitioner"
    ],
    "wof:name":"Cusick Peter",
    "wof:placetype":"venue"
},
  "geometry": {"coordinates":[150.87713600000001,-34.42551],"type":"Point"}
}