{
  "type": "Feature",
  "properties": {
    "iso:country":"AU",
    "sg:address":"9 Waldemar Rd",
    "sg:city":"Ivanhoe",
    "sg:classifiers":[
        {
            "category":"Real Estate",
            "subcategory":"Real Estate Agent",
            "type":"Services"
        }
    ],
    "sg:phone":"+61 3 9457 1522",
    "sg:postcode":"3079",
    "sg:province":"VIC",
    "wof:name":"Apostolou Thomas",
    "wof:placetype":"venue"
},
  "geometry": {"coordinates":[145.054244995,-37.7613449097],"type":"Point"}
}