{
  "type": "Feature",
  "properties": {
    "iso:country":"AU",
    "sg:address":"46 Tudor St",
    "sg:city":"Hamilton",
    "sg:classifiers":[
        {
            "category":"Banks & Credit Unions",
            "subcategory":"Bank",
            "type":"Services"
        }
    ],
    "sg:phone":"+61 2 4961 1724",
    "sg:postcode":"2303",
    "sg:province":"NSW",
    "sg:tags":[
        "society"
    ],
    "wof:name":"Newcastle Bus Credit Union",
    "wof:placetype":"venue"
},
  "geometry": {"coordinates":[151.747742,-32.924351],"type":"Point"}
}