{
  "type": "Feature",
  "properties": {
    "addr:full":"122 Boundary Rd Rocklea QLD 4106",
    "addr:housenumber":"122",
    "addr:postcode":"4106",
    "addr:street":"Boundary Rd",
    "iso:country":"AU",
    "sg:address":"122 Boundary Rd",
    "sg:city":"Rocklea",
    "sg:classifiers":[
        {
            "category":"Manufacturing",
            "subcategory":"Wood Products",
            "type":"Manufacturing & Wholesale Goods"
        }
    ],
    "sg:phone":"+61 7 3875 1794",
    "sg:postcode":"4106",
    "sg:province":"QLD",
    "sg:tags":[
        "pallet",
        "platform"
    ],
    "wof:name":"Pallet Maintenance Services Pty Ltd",
    "wof:placetype":"venue"
},
  "geometry": {"coordinates":[152.998168945,-27.5647964478],"type":"Point"}
}