{
  "type": "Feature",
  "properties": {
    "iso:country":"AU",
    "sg:address":"Westfield Marion Shoppingtown Kiosk 103/297 Diagonal Rd",
    "sg:city":"Oaklands Park",
    "sg:classifiers":[
        {
            "category":"Cafe",
            "type":"Food & Drink"
        }
    ],
    "sg:phone":"+61 8 8296 9022",
    "sg:postcode":"5046",
    "sg:province":"SA",
    "wof:name":"Cafe De Paris",
    "wof:placetype":"venue"
},
  "geometry": {"coordinates":[138.547745,-35.015984],"type":"Point"}
}