{
  "type": "Feature",
  "properties": {
    "addr:full":"4/ 35 Merewether St Merewether NSW 2291",
    "addr:housenumber":"/ 35",
    "addr:postcode":"2291",
    "addr:street":"Merewether St",
    "iso:country":"AU",
    "sg:address":"4/ 35 Merewether St",
    "sg:city":"Merewether",
    "sg:classifiers":[
        {
            "category":"Insurance",
            "subcategory":"Hazard Insurance",
            "type":"Services"
        }
    ],
    "sg:phone":"+61 2 4963 5711",
    "sg:postcode":"2291",
    "sg:province":"NSW",
    "sg:tags":[
        "loss",
        "adjuster",
        "assessor"
    ],
    "wof:name":"Anderson C R & Co Pty Ltd",
    "wof:placetype":"venue"
},
  "geometry": {"coordinates":[151.754592895,-32.9415245056],"type":"Point"}
}