{
  "type": "Feature",
  "properties": {
    "addr:full":"130 Main St Pakenham VIC 3810",
    "addr:housenumber":"130",
    "addr:postcode":"3810",
    "addr:street":"Main St",
    "iso:country":"AU",
    "sg:address":"130 Main St",
    "sg:city":"Pakenham",
    "sg:classifiers":[
        {
            "category":"Real Estate",
            "subcategory":"Real Estate Agent",
            "type":"Services"
        }
    ],
    "sg:phone":"+61 3 5941 4444",
    "sg:postcode":"3810",
    "sg:province":"VIC",
    "wof:name":"First National Real Estate",
    "wof:placetype":"venue"
},
  "geometry": {"coordinates":[145.48249799999999,-38.078064],"type":"Point"}
}