{
  "type": "Feature",
  "properties": {
    "addr:full":"145 Ingram Rd Acacia Ridge QLD 4110",
    "addr:housenumber":"145",
    "addr:postcode":"4110",
    "addr:street":"Ingram Rd",
    "iso:country":"AU",
    "sg:address":"145 Ingram Rd",
    "sg:city":"Acacia Ridge",
    "sg:classifiers":[
        {
            "category":"Banks & Credit Unions",
            "subcategory":"Bureau De Change",
            "type":"Services"
        }
    ],
    "sg:phone":"+61 7 3344 2900",
    "sg:postcode":"4110",
    "sg:province":"QLD",
    "sg:tags":[
        "wheel",
        "industrial"
    ],
    "wof:name":"JCS Equipment Pty Ltd",
    "wof:placetype":"venue"
},
  "geometry": {"coordinates":[153.04176330600001,-27.5893669128],"type":"Point"}
}