{
  "type": "Feature",
  "properties": {
    "addr:full":"308 South Gippsland Hwy Dandenong VIC 3175",
    "addr:housenumber":"308",
    "addr:postcode":"3175",
    "addr:street":"South Gippsland Hwy",
    "iso:country":"AU",
    "sg:address":"308 South Gippsland Hwy",
    "sg:city":"Dandenong",
    "sg:classifiers":[
        {
            "category":"Wholesale",
            "subcategory":"Machinery & Supplies",
            "type":"Manufacturing & Wholesale Goods"
        }
    ],
    "sg:phone":"+61 3 9554 4888",
    "sg:postcode":"3175",
    "sg:province":"VIC",
    "sg:tags":[
        "engineer"
    ],
    "wof:name":"Thomas Warburton Pty Ltd",
    "wof:placetype":"venue"
},
  "geometry": {"coordinates":[145.240142822,-38.021900177],"type":"Point"}
}