{
  "type": "Feature",
  "properties": {
    "addr:full":"15 Wentworth Pl Banyo QLD 4014",
    "addr:housenumber":"15",
    "addr:postcode":"4014",
    "addr:street":"Wentworth Pl",
    "iso:country":"AU",
    "sg:address":"15 Wentworth Pl",
    "sg:city":"Banyo",
    "sg:classifiers":[
        {
            "category":"Building & Trades",
            "subcategory":"Construction",
            "type":"Services"
        }
    ],
    "sg:phone":"+61 7 3260 7666",
    "sg:postcode":"4014",
    "sg:province":"QLD",
    "sg:tags":[
        "contractor"
    ],
    "wof:name":"Lavin Constructions",
    "wof:placetype":"venue"
},
  "geometry": {"coordinates":[153.079681397,-27.3882751465],"type":"Point"}
}