{
  "type": "Feature",
  "properties": {
    "addr:full":"Lot 3 Scougall Rd Tully QLD 4854",
    "addr:postcode":"4854",
    "addr:street":"Scougall Rd",
    "iso:country":"AU",
    "sg:address":"Lot 3 Scougall Rd",
    "sg:city":"Tully",
    "sg:classifiers":[
        {
            "category":"Farming",
            "subcategory":"Berry Farm",
            "type":"Manufacturing & Wholesale Goods"
        }
    ],
    "sg:phone":"+61 7 4068 3152",
    "sg:postcode":"4854",
    "sg:province":"QLD",
    "sg:tags":[
        "fruit",
        "grower"
    ],
    "wof:name":"Ken De Berry",
    "wof:placetype":"venue"
},
  "geometry": {"coordinates":[145.83888244600001,-17.9322013855],"type":"Point"}
}