{
  "type": "Feature",
  "properties": {
    "addr:full":"50 Wingara Ave Keilor East VIC 3033",
    "addr:housenumber":"50",
    "addr:postcode":"3033",
    "addr:street":"Wingara Ave",
    "iso:country":"AU",
    "sg:address":"50 Wingara Ave",
    "sg:city":"Keilor East",
    "sg:classifiers":[
        {
            "category":"Personal",
            "subcategory":"Beauty Salon",
            "type":"Services"
        }
    ],
    "sg:phone":"+61 3 9336 0120",
    "sg:postcode":"3033",
    "sg:province":"VIC",
    "sg:tags":[
        "hairdresser"
    ],
    "wof:name":"Blue Crew",
    "wof:placetype":"venue"
},
  "geometry": {"coordinates":[144.86741599999999,-37.732994],"type":"Point"}
}