{
  "type": "Feature",
  "properties": {
    "iso:country":"AU",
    "sg:address":"29 Church St",
    "sg:city":"Milton",
    "sg:classifiers":[
        {
            "category":"Shopping",
            "subcategory":"Antiques",
            "type":"Retail Goods"
        }
    ],
    "sg:phone":"+61 407 260 385",
    "sg:postcode":"2538",
    "sg:province":"NSW",
    "wof:name":"Gary Brill Antiques",
    "wof:placetype":"venue"
},
  "geometry": {"coordinates":[150.43743896500001,-35.3160324097],"type":"Point"}
}