{
  "type": "Feature",
  "properties": {
    "addr:full":"363 Port Hacking Rd Caringbah NSW 2229",
    "addr:housenumber":"363",
    "addr:postcode":"2229",
    "addr:street":"Port Hacking Rd",
    "iso:country":"AU",
    "sg:address":"363 Port Hacking Rd",
    "sg:city":"Caringbah",
    "sg:classifiers":[
        {
            "category":"Real Estate",
            "subcategory":"Developer",
            "type":"Services"
        }
    ],
    "sg:phone":"+61 2 9531 0245",
    "sg:postcode":"2229",
    "sg:province":"NSW",
    "sg:tags":[
        "development"
    ],
    "wof:name":"JPC Developments Pty Ltd",
    "wof:placetype":"venue"
},
  "geometry": {"coordinates":[151.123321533,-34.0438690186],"type":"Point"}
}