{
  "type": "Feature",
  "properties": {
    "iso:country":"AU",
    "sg:address":"27 Tyers Rd",
    "sg:city":"Roleystone",
    "sg:classifiers":[
        {
            "category":"Building & Trades",
            "subcategory":"Plumbing",
            "type":"Services"
        }
    ],
    "sg:phone":"+61 8 9496 1042",
    "sg:postcode":"6111",
    "sg:province":"WA",
    "sg:tags":[
        "plumber",
        "gasfitters"
    ],
    "wof:name":"Brill Plumbing",
    "wof:placetype":"venue"
},
  "geometry": {"coordinates":[116.0728302,-32.1076278687],"type":"Point"}
}