{
  "type": "Feature",
  "properties": {
    "addr:full":"45 Willaroo Ave Woronora Heights NSW 2233",
    "addr:housenumber":"45",
    "addr:postcode":"2233",
    "addr:street":"Willaroo Ave",
    "iso:country":"AU",
    "sg:address":"45 Willaroo Ave",
    "sg:city":"Woronora Heights",
    "sg:classifiers":[
        {
            "category":"Manufacturing",
            "subcategory":"Electronics",
            "type":"Manufacturing & Wholesale Goods"
        }
    ],
    "sg:phone":"+61 2 9521 1629",
    "sg:postcode":"2233",
    "sg:province":"NSW",
    "sg:tags":[
        "equipment",
        "supply"
    ],
    "wof:name":"Utama Sales & Marketing",
    "wof:placetype":"venue"
},
  "geometry": {"coordinates":[151.024124145,-34.0331611633],"type":"Point"}
}