{
  "type": "Feature",
  "properties": {
    "addr:full":"Shop 5 1A Para Rd Nuriootpa SA 5355",
    "addr:housenumber":"shop 5 1a",
    "addr:postcode":"5355",
    "addr:street":"Para Rd",
    "iso:country":"AU",
    "sg:address":"Shop 5 1A Para Rd",
    "sg:city":"Nuriootpa",
    "sg:phone":"+61 8 8562 3227",
    "sg:postcode":"5355",
    "sg:province":"SA",
    "wof:name":"Sun-Gard Barossa Valley",
    "wof:placetype":"venue"
},
  "geometry": {"coordinates":[138.986785889,-34.4711227417],"type":"Point"}
}