{
  "type": "Feature",
  "properties": {
    "addr:full":"Lvl 1, 317 Kingsway Caringbah NSW 2229",
    "addr:housenumber":"317",
    "addr:postcode":"2229",
    "addr:street":"Kingsway",
    "iso:country":"AU",
    "sg:address":"Lvl 1, 317 Kingsway",
    "sg:city":"Caringbah",
    "sg:classifiers":[
        {
            "category":"Banks & Credit Unions",
            "subcategory":"Bank",
            "type":"Services"
        }
    ],
    "sg:phone":"+61 2 9525 0112",
    "sg:postcode":"2229",
    "sg:province":"NSW",
    "sg:tags":[
        "broker",
        "mortgage"
    ],
    "wof:name":"Mortgage Choice",
    "wof:placetype":"venue"
},
  "geometry": {"coordinates":[151.12301635700001,-34.0427131653],"type":"Point"}
}