{
  "type": "Feature",
  "properties": {
    "addr:full":"Wanneroo Rd Wanneroo WA 6065",
    "addr:postcode":"6065",
    "addr:street":"Wanneroo Rd",
    "iso:country":"AU",
    "sg:address":"Wanneroo Rd",
    "sg:city":"Wanneroo",
    "sg:classifiers":[
        {
            "category":"Education",
            "subcategory":"School",
            "type":"Public Place"
        }
    ],
    "sg:phone":"+61 8 9306 1600",
    "sg:postcode":"6065",
    "sg:province":"WA",
    "sg:tags":[
        "state",
        "except",
        "nsw"
    ],
    "wof:name":"Wanneroo Primary",
    "wof:placetype":"venue"
},
  "geometry": {"coordinates":[115.784667969,-31.7202148438],"type":"Point"}
}