{
  "type": "Feature",
  "properties": {
    "addr:full":"Station St Mt Victoria NSW 2786",
    "addr:postcode":"2786",
    "addr:street":"Station St Mt",
    "iso:country":"AU",
    "sg:address":"Station St",
    "sg:city":"Mt Victoria",
    "sg:classifiers":[
        {
            "category":"Travel",
            "subcategory":"Hotels & Motels",
            "type":"Entertainment"
        }
    ],
    "sg:phone":"+61 2 4787 1878",
    "sg:postcode":"2786",
    "sg:province":"NSW",
    "sg:tags":[
        "accommodation"
    ],
    "wof:name":"Imperial Hotel Mount Victoria",
    "wof:placetype":"venue"
},
  "geometry": {"coordinates":[150.256103516,-33.5893783569],"type":"Point"}
}