{
  "type": "Feature",
  "properties": {
    "iso:country":"AU",
    "sg:address":"7 Hi Tech Drv",
    "sg:city":"Toormina",
    "sg:classifiers":[
        {
            "category":"Retail",
            "subcategory":"Auto Repair",
            "type":"Services"
        }
    ],
    "sg:phone":"+61 2 6658 4233",
    "sg:postcode":"2452",
    "sg:province":"NSW",
    "sg:tags":[
        "beater",
        "painter",
        "panel"
    ],
    "wof:name":"Greg Wilson Smash Repairs",
    "wof:placetype":"venue"
},
  "geometry": {"coordinates":[153.091263,-30.341576],"type":"Point"}
}