{
  "type": "Feature",
  "properties": {
    "addr:full":"Level 1/5 Dunlop St Newstead QLD 4006",
    "addr:housenumber":"/ 5",
    "addr:postcode":"4006",
    "addr:street":"Dunlop St",
    "iso:country":"AU",
    "sg:address":"Level 1/5 Dunlop St",
    "sg:city":"Newstead",
    "sg:classifiers":[
        {
            "category":"Professional",
            "subcategory":"Engineering",
            "type":"Services"
        }
    ],
    "sg:phone":"+61 7 3876 5411",
    "sg:postcode":"4006",
    "sg:province":"QLD",
    "sg:tags":[
        "consulting",
        "engineer"
    ],
    "wof:name":"Tabletop Architects Planners Engineers Pty Limited",
    "wof:placetype":"venue"
},
  "geometry": {"coordinates":[153.04176330600001,-27.4470233917],"type":"Point"}
}