{
  "type": "Feature",
  "properties": {
    "iso:country":"AU",
    "sg:address":"650 Chapel St",
    "sg:city":"South Yarra",
    "sg:classifiers":[
        {
            "category":"Professional",
            "subcategory":"Computer Services",
            "type":"Services"
        }
    ],
    "sg:phone":"+61 3 9823 7800",
    "sg:postcode":"3141",
    "sg:province":"VIC",
    "sg:tags":[
        "package",
        "software"
    ],
    "wof:name":"Disney Interactive",
    "wof:placetype":"venue"
},
  "geometry": {"coordinates":[144.996002197,-37.8383636475],"type":"Point"}
}