{
  "type": "Feature",
  "properties": {
    "iso:country":"AU",
    "sg:address":"Shp22/ 235 Milleara Rd",
    "sg:city":"Keilor East",
    "sg:classifiers":[
        {
            "category":"Shopping",
            "subcategory":"Clothing, Apparel, & Fashions",
            "type":"Retail Goods"
        }
    ],
    "sg:phone":"+61 3 9325 4222",
    "sg:postcode":"3033",
    "sg:province":"VIC",
    "sg:tags":[
        "lady",
        "wear"
    ],
    "wof:name":"Andrea's Off The Rack",
    "wof:placetype":"venue"
},
  "geometry": {"coordinates":[144.862152,-37.74876],"type":"Point"}
}