{
  "type": "Feature",
  "properties": {
    "addr:full":"Ral Ral Ave Renmark SA 5341",
    "addr:postcode":"5341",
    "addr:street":"Ral Ave",
    "iso:country":"AU",
    "sg:address":"Ral Ral Ave",
    "sg:city":"Renmark",
    "sg:classifiers":[
        {
            "category":"Government",
            "subcategory":"Post Office",
            "type":"Public Place"
        }
    ],
    "sg:phone":"+61 13 13 18",
    "sg:postcode":"5341",
    "sg:province":"SA",
    "sg:tags":[
        "postal"
    ],
    "wof:name":"Australia Post",
    "wof:placetype":"venue"
},
  "geometry": {"coordinates":[140.75033569300001,-34.1714820862],"type":"Point"}
}