{
  "type": "Feature",
  "properties": {
    "addr:full":"PO Box 63 Wandin VIC 3139",
    "addr:postcode":"3139",
    "iso:country":"AU",
    "sg:address":"PO Box 63",
    "sg:city":"Wandin",
    "sg:classifiers":[
        {
            "category":"Building & Trades",
            "subcategory":"Construction",
            "type":"Services"
        }
    ],
    "sg:phone":"+61 3 5964 9359",
    "sg:postcode":"3139",
    "sg:province":"VIC",
    "sg:tags":[
        "contractor"
    ],
    "wof:name":"Hammond J P",
    "wof:placetype":"venue"
},
  "geometry": {"coordinates":[145.44999694800001,-37.7999992371],"type":"Point"}
}