{
  "type": "Feature",
  "properties": {
    "addr:full":"11 Ronald Ave Harbord NSW 2096",
    "addr:housenumber":"11",
    "addr:postcode":"2096",
    "addr:street":"Ronald Ave",
    "iso:country":"AU",
    "sg:address":"11 Ronald Ave",
    "sg:city":"Harbord",
    "sg:classifiers":[
        {
            "category":"Health Services",
            "subcategory":"Health Practitioner",
            "type":"Services"
        }
    ],
    "sg:phone":"+61 2 9905 1230",
    "sg:postcode":"2096",
    "sg:province":"NSW",
    "sg:tags":[
        "dietitian"
    ],
    "wof:name":"Wier Roger",
    "wof:placetype":"venue"
},
  "geometry": {"coordinates":[151.29103088400001,-33.7760810852],"type":"Point"}
}