{
  "type": "Feature",
  "properties": {
    "iso:country":"AU",
    "sg:address":"Shop 2 / 201 Flinders Rd",
    "sg:city":"Yokine",
    "sg:classifiers":[
        {
            "category":"Shopping",
            "subcategory":"Clothing, Apparel, & Fashions",
            "type":"Retail Goods"
        }
    ],
    "sg:phone":"+61 8 9344 4453",
    "sg:postcode":"6060",
    "sg:province":"WA",
    "sg:tags":[
        "recycled",
        "clothing"
    ],
    "wof:name":"Save The Children Australia Shop",
    "wof:placetype":"venue"
},
  "geometry": {"coordinates":[115.849243164,-31.8943748474],"type":"Point"}
}