{
  "type": "Feature",
  "properties": {
    "addr:full":"Erindale, Gartside St Wanniassa ACT 2903",
    "addr:postcode":"2903",
    "addr:street":"St",
    "iso:country":"AU",
    "sg:address":"Erindale, Gartside St",
    "sg:city":"Wanniassa",
    "sg:classifiers":[
        {
            "category":"Fast Food",
            "type":"Food & Drink"
        }
    ],
    "sg:phone":"+61 2 6231 2365",
    "sg:postcode":"2903",
    "sg:province":"ACT",
    "sg:tags":[
        "away",
        "take"
    ],
    "wof:name":"Thai Basil Restaurant",
    "wof:placetype":"venue"
},
  "geometry": {"coordinates":[149.09992980999999,-35.4055557251],"type":"Point"}
}