{
  "type": "Feature",
  "properties": {
    "iso:country":"AU",
    "sg:address":"Port Rd",
    "sg:city":"Aldinga",
    "sg:classifiers":[
        {
            "category":"Arena",
            "subcategory":"Sports Club",
            "type":"Entertainment"
        }
    ],
    "sg:phone":"+61 8 8557 7291",
    "sg:postcode":"5173",
    "sg:province":"SA",
    "sg:tags":[
        "australian",
        "football",
        "rule"
    ],
    "wof:name":"Aldinga Football Club Incorporated",
    "wof:placetype":"venue"
},
  "geometry": {"coordinates":[138.475997925,-35.2671012878],"type":"Point"}
}