{
  "type": "Feature",
  "properties": {
    "iso:country":"AU",
    "sg:address":"222 Ross River Rd",
    "sg:city":"Aitkenvale",
    "sg:classifiers":[
        {
            "category":"Manufacturing",
            "subcategory":"Retail Goods",
            "type":"Manufacturing & Wholesale Goods"
        }
    ],
    "sg:phone":"+61 7 4725 6500",
    "sg:postcode":"4814",
    "sg:province":"QLD",
    "sg:tags":[
        "merchant",
        "pump",
        "mfrs"
    ],
    "wof:name":"Hansen's Pool Barn",
    "wof:placetype":"venue"
},
  "geometry": {"coordinates":[146.77299500000001,-19.29661],"type":"Point"}
}