{
  "type": "Feature",
  "properties": {
    "addr:full":"Shop 6 North Concourse Beaumaris VIC 3193",
    "addr:housenumber":"shop 6",
    "addr:postcode":"3193",
    "addr:street":"North Concourse",
    "iso:country":"AU",
    "sg:address":"Shop 6 North Concourse",
    "sg:city":"Beaumaris",
    "sg:classifiers":[
        {
            "category":"Utilities",
            "subcategory":"Telephone",
            "type":"Services"
        }
    ],
    "sg:phone":"+61 3 9589 0577",
    "sg:postcode":"3193",
    "sg:province":"VIC",
    "sg:tags":[
        "equipment",
        "system"
    ],
    "wof:name":"Hyett Communications",
    "wof:placetype":"venue"
},
  "geometry": {"coordinates":[145.033477783,-37.9855117798],"type":"Point"}
}