{
  "type": "Feature",
  "properties": {
    "addr:full":"PO Box 2077 Burleigh Heads DC QLD 4220",
    "addr:postcode":"4220",
    "addr:street":"Heads",
    "iso:country":"AU",
    "sg:address":"PO Box 2077",
    "sg:city":"Burleigh Heads DC",
    "sg:classifiers":[
        {
            "category":"Mining & Drilling",
            "type":"Manufacturing & Wholesale Goods"
        }
    ],
    "sg:phone":"+61 418 754 373",
    "sg:postcode":"4220",
    "sg:province":"QLD",
    "sg:tags":[
        "concrete",
        "breaking",
        "grinding",
        "sawing"
    ],
    "wof:name":"Precision Concrete Cutting Pty Ltd",
    "wof:placetype":"venue"
},
  "geometry": {"coordinates":[153.432662964,-28.0981998444],"type":"Point"}
}