{
  "type": "Feature",
  "properties": {
    "addr:full":"177 Johnston St Collingwood VIC 3066",
    "addr:housenumber":"177",
    "addr:postcode":"3066",
    "addr:street":"Johnston St",
    "iso:country":"AU",
    "sg:address":"177 Johnston St",
    "sg:city":"Collingwood",
    "sg:classifiers":[
        {
            "category":"Travel",
            "subcategory":"Hotels & Motels",
            "type":"Entertainment"
        }
    ],
    "sg:phone":"+61 425 796 828",
    "sg:postcode":"3066",
    "sg:province":"VIC",
    "sg:tags":[
        "accommodation"
    ],
    "wof:name":"Barley Corn Hotel",
    "wof:placetype":"venue"
},
  "geometry": {"coordinates":[144.991088867,-37.7997703552],"type":"Point"}
}