{
  "type": "Feature",
  "properties": {
    "addr:full":"12 Mylne St Chermside QLD 4032",
    "addr:housenumber":"12",
    "addr:postcode":"qld 4032",
    "addr:street":"Mylne St",
    "iso:country":"AU",
    "sg:address":"12 Mylne St",
    "sg:city":"Chermside",
    "sg:classifiers":[
        {
            "category":"Personal",
            "subcategory":"Massage",
            "type":"Services"
        }
    ],
    "sg:phone":"+61 7 3350 2266",
    "sg:postcode":"4032",
    "sg:province":"QLD",
    "sg:tags":[
        "therapy"
    ],
    "wof:name":"Mascali R P",
    "wof:placetype":"venue"
},
  "geometry": {"coordinates":[153.043701,-27.386992],"type":"Point"}
}