{
  "type": "Feature",
  "properties": {
    "addr:full":"25 Wycombe Rd Aldgate SA 5154",
    "addr:housenumber":"25",
    "addr:postcode":"5154",
    "addr:street":"Wycombe Rd",
    "iso:country":"AU",
    "sg:address":"25 Wycombe Rd",
    "sg:city":"Aldgate",
    "sg:classifiers":[
        {
            "category":"Utilities",
            "subcategory":"Electric",
            "type":"Services"
        }
    ],
    "sg:phone":"+61 418 834 124",
    "sg:postcode":"5154",
    "sg:province":"SA",
    "sg:tags":[
        "electrical",
        "contractor"
    ],
    "wof:name":"Orana Electrical",
    "wof:placetype":"venue"
},
  "geometry": {"coordinates":[138.742874145,-35.0162811279],"type":"Point"}
}