{
  "type": "Feature",
  "properties": {
    "iso:country":"AU",
    "sg:address":"32 Gap Rd",
    "sg:city":"Alice Springs",
    "sg:classifiers":[
        {
            "category":"Travel",
            "subcategory":"Hotels & Motels",
            "type":"Entertainment"
        }
    ],
    "sg:phone":"+61 8 8952 1616",
    "sg:postcode":"0870",
    "sg:province":"NT",
    "wof:name":"Jessica Court Serviced Apartments",
    "wof:placetype":"venue"
},
  "geometry": {"coordinates":[133.87571716299999,-23.711643219],"type":"Point"}
}