{
  "type": "Feature",
  "properties": {
    "addr:full":"14 Bayview Rd Brighton East VIC 3187",
    "addr:housenumber":"14",
    "addr:postcode":"3187",
    "addr:street":"Bayview Rd",
    "iso:country":"AU",
    "sg:address":"14 Bayview Rd",
    "sg:city":"Brighton East",
    "sg:classifiers":[
        {
            "category":"Utilities",
            "subcategory":"Electric",
            "type":"Services"
        }
    ],
    "sg:phone":"+61 414 496 644",
    "sg:postcode":"3187",
    "sg:province":"VIC",
    "sg:tags":[
        "electrical",
        "contractor"
    ],
    "wof:name":"Flattop Electrics",
    "wof:placetype":"venue"
},
  "geometry": {"coordinates":[145.02481079099999,-37.9069786072],"type":"Point"}
}