{
  "type": "Feature",
  "properties": {
    "addr:full":"PO Box 437 Maroochydore QLD 4558",
    "addr:postcode":"4558",
    "iso:country":"AU",
    "sg:address":"PO Box 437",
    "sg:city":"Maroochydore",
    "sg:classifiers":[
        {
            "category":"Building & Trades",
            "subcategory":"Construction",
            "type":"Services"
        }
    ],
    "sg:phone":"+61 411 696 438",
    "sg:postcode":"4558",
    "sg:province":"QLD",
    "sg:tags":[
        "polishing",
        "sanding",
        "floor"
    ],
    "wof:name":"Kieran Smith",
    "wof:placetype":"venue"
},
  "geometry": {"coordinates":[153.06553649899999,-26.6553192139],"type":"Point"}
}