{
  "type": "Feature",
  "properties": {
    "addr:full":"Unit 6/ 5 Marks St Kiama NSW 2533",
    "addr:housenumber":"5",
    "addr:postcode":"2533",
    "addr:street":"Marks St",
    "iso:country":"AU",
    "sg:address":"Unit 6/ 5 Marks St",
    "sg:city":"Kiama",
    "sg:classifiers":[
        {
            "category":"Manufacturing",
            "subcategory":"Glass & Minerals",
            "type":"Manufacturing & Wholesale Goods"
        }
    ],
    "sg:phone":"+61 2 4232 4477",
    "sg:postcode":"2533",
    "sg:province":"NSW",
    "sg:tags":[
        "repair",
        "fibreglass",
        "product"
    ],
    "wof:name":"Kiama Fibreglassing & Repairs",
    "wof:placetype":"venue"
},
  "geometry": {"coordinates":[150.848220825,-34.6860580444],"type":"Point"}
}