{
  "type": "Feature",
  "properties": {
    "addr:full":"743 Ann St Fortitude Valley QLD 4006",
    "addr:housenumber":"743",
    "addr:postcode":"4006",
    "addr:street":"Ann St",
    "iso:country":"AU",
    "sg:address":"743 Ann St",
    "sg:city":"Fortitude Valley",
    "sg:classifiers":[
        {
            "category":"Personal",
            "subcategory":"Beauty Salon",
            "type":"Services"
        }
    ],
    "sg:phone":"+61 407 008 317",
    "sg:postcode":"4006",
    "sg:province":"QLD",
    "sg:tags":[
        "hairdresser"
    ],
    "wof:name":"Bespoke Hair Face Body",
    "wof:placetype":"venue"
},
  "geometry": {"coordinates":[153.03669738799999,-27.4569644928],"type":"Point"}
}