{
  "type": "Feature",
  "properties": {
    "addr:full":"PO Box 1544 Capalaba QLD 4157",
    "addr:postcode":"4157",
    "iso:country":"AU",
    "sg:address":"PO Box 1544",
    "sg:city":"Capalaba",
    "sg:classifiers":[
        {
            "category":"Building & Trades",
            "subcategory":"Plumbing",
            "type":"Services"
        }
    ],
    "sg:phone":"+61 7 3245 4114",
    "sg:postcode":"4157",
    "sg:province":"QLD",
    "sg:tags":[
        "plumber",
        "gasfitters"
    ],
    "wof:name":"Aqueous Plumbing & Drainage",
    "wof:placetype":"venue"
},
  "geometry": {"coordinates":[153.21090698200001,-27.5379695892],"type":"Point"}
}