{
  "type": "Feature",
  "properties": {
    "iso:country":"AU",
    "sg:address":"PO Box 522 Brighton 3186",
    "sg:city":"Brighton",
    "sg:classifiers":[
        {
            "category":"Personal",
            "type":"Services"
        }
    ],
    "sg:phone":"+61 3 9592 1483",
    "sg:postcode":"3186",
    "sg:province":"VIC",
    "sg:tags":[
        "gift"
    ],
    "wof:name":"Redgrove House Pty Ltd",
    "wof:placetype":"venue"
},
  "geometry": {"coordinates":[144.99707031200001,-37.8837509155],"type":"Point"}
}