{
  "type": "Feature",
  "properties": {
    "iso:country":"AU",
    "sg:address":"38 Narracan Drv",
    "sg:city":"Moe",
    "sg:classifiers":[
        {
            "category":"Autos & Motor Vehicles",
            "subcategory":"Auto Supplies",
            "type":"Retail Goods"
        }
    ],
    "sg:phone":"+61 3 5127 1000",
    "sg:postcode":"3825",
    "sg:province":"VIC",
    "sg:tags":[
        "camper-trailers",
        "caravan",
        "equipment"
    ],
    "wof:name":"Mad Mile Motors",
    "wof:placetype":"venue"
},
  "geometry": {"coordinates":[146.271164,-38.179333],"type":"Point"}
}