{
  "type": "Feature",
  "properties": {
    "addr:full":"Interstate Hotel Patrick St Whitemark TAS 7255",
    "addr:postcode":"7255",
    "iso:country":"AU",
    "sg:address":"Interstate Hotel Patrick St",
    "sg:city":"Whitemark",
    "sg:classifiers":[
        {
            "category":"Food & Beverages",
            "subcategory":"Liquor & Beverages",
            "type":"Retail Goods"
        }
    ],
    "sg:phone":"+61 3 6359 2079",
    "sg:postcode":"7255",
    "sg:province":"TAS",
    "sg:tags":[
        "store"
    ],
    "wof:name":"Liquorwise",
    "wof:placetype":"venue"
},
  "geometry": {"coordinates":[148.01626586899999,-40.1216697693],"type":"Point"}
}