{
  "type": "Feature",
  "properties": {
    "addr:full":"196 Albatross Rd Nowra NSW 2541",
    "addr:housenumber":"196",
    "addr:postcode":"2541",
    "addr:street":"Albatross Rd",
    "iso:country":"AU",
    "sg:address":"196 Albatross Rd",
    "sg:city":"Nowra",
    "sg:classifiers":[
        {
            "category":"Building & Trades",
            "subcategory":"Construction",
            "type":"Services"
        }
    ],
    "sg:phone":"+61 414 470 022",
    "sg:postcode":"2541",
    "sg:province":"NSW",
    "sg:tags":[
        "home",
        "air conditioning"
    ],
    "wof:name":"UtopiAir Airconditioning",
    "wof:placetype":"venue"
},
  "geometry": {"coordinates":[150.55976867699999,-34.9211616516],"type":"Point"}
}