{
  "type": "Feature",
  "properties": {
    "iso:country":"AU",
    "sg:address":"121 Shellharbour Rd",
    "sg:city":"Warilla",
    "sg:classifiers":[
        {
            "category":"Real Estate",
            "subcategory":"Real Estate Agent",
            "type":"Services"
        }
    ],
    "sg:phone":"+61 2 4261 3211",
    "sg:postcode":"2528",
    "sg:province":"NSW",
    "wof:name":"Dougmal Real Estate Warilla",
    "wof:placetype":"venue"
},
  "geometry": {"coordinates":[150.86018371599999,-34.5522079468],"type":"Point"}
}