{
  "type": "Feature",
  "properties": {
    "addr:full":"Suite 1, Sutherlands House 4 Yan Yean Rd Plenty VIC 3090",
    "addr:housenumber":"4",
    "addr:postcode":"3090",
    "addr:street":"Yan Yean Rd",
    "iso:country":"AU",
    "sg:address":"Suite 1, Sutherlands House 4 Yan Yean Rd",
    "sg:city":"Plenty",
    "sg:classifiers":[
        {
            "category":"Recreation",
            "type":"Entertainment"
        }
    ],
    "sg:phone":"+61 3 9438 3454",
    "sg:postcode":"3090",
    "sg:province":"VIC",
    "sg:tags":[
        "children's",
        "play",
        "programme"
    ],
    "wof:name":"GymbaROO",
    "wof:placetype":"venue"
},
  "geometry": {"coordinates":[145.125823975,-37.6766090393],"type":"Point"}
}