{
  "type": "Feature",
  "properties": {
    "iso:country":"AU",
    "sg:address":"Unit 10, 3 Traders La",
    "sg:city":"Noosaville",
    "sg:classifiers":[
        {
            "category":"Communications",
            "type":"Services"
        }
    ],
    "sg:phone":"+61 7 5449 9994",
    "sg:postcode":"4566",
    "sg:province":"QLD",
    "sg:tags":[
        "antenna"
    ],
    "wof:name":"Radio Comm",
    "wof:placetype":"venue"
},
  "geometry": {"coordinates":[153.046875,-26.4081745148],"type":"Point"}
}