{
  "type": "Feature",
  "properties": {
    "iso:country":"AU",
    "sg:address":"Unit 3",
    "sg:city":"/29 Export Drive Molendinar Molendinar",
    "sg:classifiers":[
        {
            "category":"Retail",
            "subcategory":"Auto Repair",
            "type":"Services"
        }
    ],
    "sg:phone":"+61 402 876 952",
    "sg:postcode":"4214",
    "sg:province":"QLD",
    "sg:tags":[
        "fuel",
        "petrol",
        "injection"
    ],
    "wof:name":"Tuned Port Injection Technologies",
    "wof:placetype":"venue"
},
  "geometry": {"coordinates":[153.360031128,-27.967376709],"type":"Point"}
}