{
  "type": "Feature",
  "properties": {
    "iso:country":"AU",
    "sg:address":"163 Federal St",
    "sg:city":"Narrogin",
    "sg:classifiers":[
        {
            "category":"Retail",
            "subcategory":"Auto Repair",
            "type":"Services"
        }
    ],
    "sg:phone":"+61 8 9881 2620",
    "sg:postcode":"6312",
    "sg:province":"WA",
    "sg:tags":[
        "repairer",
        "motor",
        "engineer"
    ],
    "wof:name":"Staphorst E & H",
    "wof:placetype":"venue"
},
  "geometry": {"coordinates":[117.17841339100001,-32.9423408508],"type":"Point"}
}