{
  "type": "Feature",
  "properties": {
    "iso:country":"AU",
    "sg:address":"Carruth Rd",
    "sg:city":"Torrens Park",
    "sg:classifiers":[
        {
            "category":"Education",
            "subcategory":"Music School",
            "type":"Public Place"
        }
    ],
    "sg:phone":"+61 8 8274 4328",
    "sg:postcode":"5062",
    "sg:province":"SA",
    "sg:tags":[
        "choir",
        "bands",
        "orchestra"
    ],
    "wof:name":"Scotch College Orchestra",
    "wof:placetype":"venue"
},
  "geometry": {"coordinates":[138.613006592,-34.9791755676],"type":"Point"}
}