{
  "type": "Feature",
  "properties": {
    "addr:full":"145 Mary St Gympie QLD 4570",
    "addr:housenumber":"145",
    "addr:postcode":"4570",
    "addr:street":"Mary St",
    "iso:country":"AU",
    "sg:address":"145 Mary St",
    "sg:city":"Gympie",
    "sg:classifiers":[
        {
            "category":"Shopping",
            "subcategory":"Clothing, Apparel, & Fashions",
            "type":"Retail Goods"
        }
    ],
    "sg:phone":"+61 7 5481 1982",
    "sg:postcode":"4570",
    "sg:province":"QLD",
    "sg:tags":[
        "lady",
        "wear"
    ],
    "wof:name":"Dreamy Divas",
    "wof:placetype":"venue"
},
  "geometry": {"coordinates":[152.66146850600001,-26.1896247864],"type":"Point"}
}