{
  "type": "Feature",
  "properties": {
    "addr:full":"Barabba Rd Hamley Bridge SA 5401",
    "addr:postcode":"5401",
    "addr:street":"Barabba Rd",
    "iso:country":"AU",
    "sg:address":"Barabba Rd",
    "sg:city":"Hamley Bridge",
    "sg:classifiers":[
        {
            "category":"Farming",
            "subcategory":"Farm",
            "type":"Manufacturing & Wholesale Goods"
        }
    ],
    "sg:phone":"+61 8 8528 2083",
    "sg:postcode":"5401",
    "sg:province":"SA",
    "sg:tags":[
        "farmer"
    ],
    "wof:name":"Humphrys R W & B I",
    "wof:placetype":"venue"
},
  "geometry": {"coordinates":[138.58197021500001,-34.3479156494],"type":"Point"}
}