{
  "type": "Feature",
  "properties": {
    "addr:full":"44 Callistemon St Greenwood WA 6024",
    "addr:housenumber":"44",
    "addr:postcode":"6024",
    "addr:street":"Callistemon St",
    "iso:country":"AU",
    "sg:address":"44 Callistemon St",
    "sg:city":"Greenwood",
    "sg:classifiers":[
        {
            "category":"Real Estate",
            "subcategory":"Architect",
            "type":"Services"
        }
    ],
    "sg:phone":"+61 8 9447 4952",
    "sg:postcode":"6024",
    "sg:province":"WA",
    "sg:tags":[
        "house",
        "damp",
        "waterproofing",
        "repair"
    ],
    "sg:website":"http://www.driaswaterproofing.com.au",
    "wof:name":"Dri-As Waterproofing",
    "wof:placetype":"venue"
},
  "geometry": {"coordinates":[115.80072784399999,-31.8338012695],"type":"Point"}
}