{
  "type": "Feature",
  "properties": {
    "iso:country":"AU",
    "sg:address":"15 Rochester St",
    "sg:city":"Botany",
    "sg:classifiers":[
        {
            "category":"Retail",
            "subcategory":"Auto Repair",
            "type":"Services"
        }
    ],
    "sg:phone":"+61 2 9666 6997",
    "sg:postcode":"2019",
    "sg:province":"NSW",
    "sg:tags":[
        "beater",
        "painter",
        "panel"
    ],
    "wof:name":"McLeods Garage",
    "wof:placetype":"venue"
},
  "geometry": {"coordinates":[151.1980896,-33.9494361877],"type":"Point"}
}