{
  "type": "Feature",
  "properties": {
    "addr:full":"100 Morton St Queanbeyan NSW 2620",
    "addr:housenumber":"100",
    "addr:postcode":"2620",
    "addr:street":"Morton St",
    "iso:country":"AU",
    "sg:address":"100 Morton St",
    "sg:city":"Queanbeyan",
    "sg:classifiers":[
        {
            "category":"Education",
            "subcategory":"School",
            "type":"Public Place"
        }
    ],
    "sg:phone":"+61 2 6297 2020",
    "sg:postcode":"2620",
    "sg:province":"NSW",
    "sg:tags":[
        "state",
        "-",
        "nsw"
    ],
    "wof:name":"Queanbeyan West Public School",
    "wof:placetype":"venue"
},
  "geometry": {"coordinates":[149.21177673299999,-35.3469696045],"type":"Point"}
}