{
  "type": "Feature",
  "properties": {
    "addr:full":"Shop 79, Pacific Fair Shopping Centre, Hooker Boulevard Broadbeach QLD 4218",
    "addr:housenumber":"shop 79",
    "addr:postcode":"4218",
    "addr:street":"Pacific;Hooker Boulevard",
    "iso:country":"AU",
    "sg:address":"Shop 79, Pacific Fair Shopping Centre, Hooker Boulevard",
    "sg:city":"Broadbeach",
    "sg:classifiers":[
        {
            "category":"Airline",
            "type":"Transportation"
        }
    ],
    "sg:phone":"+61 7 5526 1599",
    "sg:postcode":"4218",
    "sg:province":"QLD",
    "sg:tags":[
        "agent"
    ],
    "wof:name":"STA Travel",
    "wof:placetype":"venue"
},
  "geometry": {"coordinates":[153.43174743599999,-28.0374698639],"type":"Point"}
}