{
  "type": "Feature",
  "properties": {
    "addr:full":"4 Crest Rd Albion Park NSW 2527",
    "addr:housenumber":"4",
    "addr:postcode":"2527",
    "addr:street":"Crest Rd",
    "iso:country":"AU",
    "sg:address":"4 Crest Rd",
    "sg:city":"Albion Park",
    "sg:classifiers":[
        {
            "category":"Manufacturing",
            "subcategory":"Retail Goods",
            "type":"Manufacturing & Wholesale Goods"
        }
    ],
    "sg:phone":"+61 2 4256 5084",
    "sg:postcode":"2527",
    "sg:province":"NSW",
    "sg:tags":[
        "merchant",
        "pump",
        "mfrs"
    ],
    "wof:name":"GAAM Emergency Products",
    "wof:placetype":"venue"
},
  "geometry": {"coordinates":[150.76092529300001,-34.574962616],"type":"Point"}
}