{
  "type": "Feature",
  "properties": {
    "iso:country":"AU",
    "sg:address":"82 Kenmare St",
    "sg:city":"Mont Albert North",
    "sg:classifiers":[
        {
            "category":"Professional",
            "subcategory":"Business Services",
            "type":"Services"
        }
    ],
    "sg:phone":"+61 3 9898 1060",
    "sg:postcode":"3129",
    "sg:province":"VIC",
    "sg:tags":[
        "drafting"
    ],
    "wof:name":"A S.C. Murphy Drafting",
    "wof:placetype":"venue"
},
  "geometry": {"coordinates":[145.11346435600001,-37.8123626709],"type":"Point"}
}