{
  "type": "Feature",
  "properties": {
    "addr:full":"26 Devries Rd Pallara QLD 4110",
    "addr:housenumber":"26",
    "addr:postcode":"4110",
    "addr:street":"Devries Rd",
    "iso:country":"AU",
    "sg:address":"26 Devries Rd",
    "sg:city":"Pallara",
    "sg:classifiers":[
        {
            "category":"Commercial Area",
            "type":"Public Place"
        }
    ],
    "sg:phone":"+61 409 525 610",
    "sg:postcode":"4110",
    "sg:province":"QLD",
    "sg:tags":[
        "heavy",
        "carrier"
    ],
    "wof:name":"Hallmack Heavy Haulage",
    "wof:placetype":"venue"
},
  "geometry": {"coordinates":[152.995605469,-27.625289917],"type":"Point"}
}