{
  "type": "Feature",
  "properties": {
    "iso:country":"AU",
    "sg:address":"Level 29 Govenor Phillip Tower 1 Farrer Pl",
    "sg:city":"Sydney",
    "sg:classifiers":[
        {
            "category":"Banks & Credit Unions",
            "subcategory":"Financial Services",
            "type":"Services"
        }
    ],
    "sg:phone":"+61 2 9254 5444",
    "sg:postcode":"2000",
    "sg:province":"NSW",
    "sg:tags":[
        "financier"
    ],
    "wof:name":"Grosvenor Financial Services Pty Ltd",
    "wof:placetype":"venue"
},
  "geometry": {"coordinates":[151.21072387699999,-33.8643341064],"type":"Point"}
}