{
  "type": "Feature",
  "properties": {
    "iso:country":"AU",
    "sg:address":"96 Mulgul Rd",
    "sg:city":"Malaga",
    "sg:classifiers":[
        {
            "category":"Home & Garden",
            "subcategory":"Building Materials",
            "type":"Retail Goods"
        }
    ],
    "sg:phone":"+61 8 9247 8777",
    "sg:postcode":"6090",
    "sg:province":"WA",
    "sg:tags":[
        "shutter",
        "roller",
        "grille"
    ],
    "wof:name":"B & D Doors",
    "wof:placetype":"venue"
},
  "geometry": {"coordinates":[115.90431213399999,-31.8594226837],"type":"Point"}
}