{
  "type": "Feature",
  "properties": {
    "addr:full":"4/ 65 Captain Cook Drv Caringbah NSW 2229",
    "addr:housenumber":"/ 65",
    "addr:postcode":"2229",
    "addr:street":"Captain Cook Drv",
    "iso:country":"AU",
    "sg:address":"4/ 65 Captain Cook Drv",
    "sg:city":"Caringbah",
    "sg:classifiers":[
        {
            "category":"Autos & Motor Vehicles",
            "subcategory":"Boat Sales",
            "type":"Retail Goods"
        }
    ],
    "sg:phone":"+61 2 9540 4811",
    "sg:postcode":"2229",
    "sg:province":"NSW",
    "sg:tags":[
        "equipment",
        "yacht"
    ],
    "wof:name":"Webasto Product Aust Pty Ltd",
    "wof:placetype":"venue"
},
  "geometry": {"coordinates":[151.12098693900001,-34.0318527222],"type":"Point"}
}