{
  "type": "Feature",
  "properties": {
    "addr:full":"PO Box 87 Burswood WA 6100",
    "addr:postcode":"6100",
    "iso:country":"AU",
    "sg:address":"PO Box 87",
    "sg:city":"Burswood",
    "sg:classifiers":[
        {
            "category":"Professional",
            "subcategory":"Business Services",
            "type":"Services"
        }
    ],
    "sg:phone":"+61 8 9470 6408",
    "sg:postcode":"6100",
    "sg:province":"WA",
    "sg:tags":[
        "broker"
    ],
    "wof:name":"Business Brokers Association (WA) Inc.",
    "wof:placetype":"venue"
},
  "geometry": {"coordinates":[115.898071289,-31.9615097046],"type":"Point"}
}