{
  "type": "Feature",
  "properties": {
    "addr:full":"Level 1/ 545 Queen St Brisbane City QLD 4000",
    "addr:housenumber":"/ 545",
    "addr:postcode":"4000",
    "addr:street":"Queen St",
    "iso:country":"AU",
    "sg:address":"Level 1/ 545 Queen St",
    "sg:city":"Brisbane City",
    "sg:classifiers":[
        {
            "category":"Banks & Credit Unions",
            "subcategory":"Investment Brokerage",
            "type":"Services"
        }
    ],
    "sg:phone":"+61 7 3833 6666",
    "sg:postcode":"4000",
    "sg:province":"QLD",
    "sg:tags":[
        "management",
        "property"
    ],
    "wof:name":"Rental Hotline",
    "wof:placetype":"venue"
},
  "geometry": {"coordinates":[153.03138732900001,-27.462890625],"type":"Point"}
}