{
  "type": "Feature",
  "properties": {
    "addr:full":"72 Helen St Sefton NSW 2162",
    "addr:housenumber":"72",
    "addr:postcode":"2162",
    "addr:street":"Helen St",
    "iso:country":"AU",
    "sg:address":"72 Helen St",
    "sg:city":"Sefton",
    "sg:classifiers":[
        {
            "category":"Professional",
            "subcategory":"Detective & Security Services",
            "type":"Services"
        }
    ],
    "sg:phone":"+61 2 9644 9255",
    "sg:postcode":"2162",
    "sg:province":"NSW",
    "sg:tags":[
        "equipment",
        "window",
        "doors"
    ],
    "wof:name":"Walco Aluminium Pty Ltd",
    "wof:placetype":"venue"
},
  "geometry": {"coordinates":[151.012451172,-33.8809623718],"type":"Point"}
}