{
  "type": "Feature",
  "properties": {
    "addr:full":"Suite 7, (Rear) 211 Main St Mornington VIC 3931",
    "addr:housenumber":"211",
    "addr:postcode":"3931",
    "addr:street":"Main St",
    "iso:country":"AU",
    "sg:address":"Suite 7, (Rear) 211 Main St",
    "sg:city":"Mornington",
    "sg:classifiers":[
        {
            "category":"Personal",
            "subcategory":"Tattoo Parlor",
            "type":"Services"
        }
    ],
    "sg:phone":"+61 3 5977 1099",
    "sg:postcode":"3931",
    "sg:province":"VIC",
    "sg:tags":[
        "tattooing"
    ],
    "wof:name":"Ink Fix",
    "wof:placetype":"venue"
},
  "geometry": {"coordinates":[145.04049682600001,-38.2228088379],"type":"Point"}
}