{
  "type": "Feature",
  "properties": {
    "iso:country":"AU",
    "sg:address":"Studio 431 Blackall Range Rd",
    "sg:city":"West Woombye",
    "sg:classifiers":[
        {
            "category":"Education",
            "subcategory":"University",
            "type":"Public Place"
        }
    ],
    "sg:phone":"+61 7 5442 1485",
    "sg:postcode":"4559",
    "sg:province":"QLD",
    "sg:tags":[
        "sewing",
        "dressmaking",
        "tuition"
    ],
    "wof:name":"Lolita Lymer Designing Drafting and Dressmaking Academy",
    "wof:placetype":"venue"
},
  "geometry": {"coordinates":[152.92500305199999,-26.6659793854],"type":"Point"}
}