{
  "type": "Feature",
  "properties": {
    "addr:full":"Unit 2/ 5 Sharon Rd Batemans Bay NSW 2536",
    "addr:housenumber":"5",
    "addr:postcode":"2536",
    "addr:street":"Sharon Rd",
    "iso:country":"AU",
    "sg:address":"Unit 2/ 5 Sharon Rd",
    "sg:city":"Batemans Bay",
    "sg:classifiers":[
        {
            "category":"Professional",
            "type":"Services"
        }
    ],
    "sg:phone":"+61 2 4472 3020",
    "sg:postcode":"2536",
    "sg:province":"NSW",
    "sg:tags":[
        "coating",
        "powder"
    ],
    "wof:name":"Aztec Powder Coating",
    "wof:placetype":"venue"
},
  "geometry": {"coordinates":[150.173431397,-35.7193031311],"type":"Point"}
}