{
  "type": "Feature",
  "properties": {
    "addr:full":"53a Portman St Oakleigh VIC 3166",
    "addr:housenumber":"53a",
    "addr:postcode":"3166",
    "addr:street":"Portman St",
    "iso:country":"AU",
    "sg:address":"53a Portman St",
    "sg:city":"Oakleigh",
    "sg:classifiers":[
        {
            "category":"Food & Beverages",
            "subcategory":"Bakery",
            "type":"Retail Goods"
        }
    ],
    "sg:phone":"+61 3 9569 0020",
    "sg:postcode":"3166",
    "sg:province":"VIC",
    "sg:tags":[
        "baker"
    ],
    "wof:name":"Lien Hiep Bakery",
    "wof:placetype":"venue"
},
  "geometry": {"coordinates":[145.091522217,-37.900138855],"type":"Point"}
}