{
  "type": "Feature",
  "properties": {
    "addr:full":"Shropshire St Miller NSW 2168",
    "addr:postcode":"2168",
    "addr:street":"Shropshire St",
    "iso:country":"AU",
    "sg:address":"Shropshire St",
    "sg:city":"Miller",
    "sg:classifiers":[
        {
            "category":"Education",
            "subcategory":"School",
            "type":"Public Place"
        }
    ],
    "sg:phone":"+61 2 9607 8293",
    "sg:postcode":"2168",
    "sg:province":"NSW",
    "sg:tags":[
        "state",
        "-",
        "nsw"
    ],
    "wof:name":"Miller Public School",
    "wof:placetype":"venue"
},
  "geometry": {"coordinates":[150.883712769,-33.9208946228],"type":"Point"}
}