{
  "type": "Feature",
  "properties": {
    "addr:full":"3 Tebbutt Crt Mill Park VIC 3082",
    "addr:housenumber":"3",
    "addr:postcode":"3082",
    "addr:street":"Tebbutt Crt",
    "iso:country":"AU",
    "sg:address":"3 Tebbutt Crt",
    "sg:city":"Mill Park",
    "sg:classifiers":[
        {
            "category":"Building & Trades",
            "subcategory":"Construction",
            "type":"Services"
        }
    ],
    "sg:phone":"+61 408 367 071",
    "sg:postcode":"3082",
    "sg:province":"VIC",
    "sg:tags":[
        "earth",
        "excavating",
        "moving",
        "contractor"
    ],
    "wof:name":"Straycat Excavations",
    "wof:placetype":"venue"
},
  "geometry": {"coordinates":[145.061203003,-37.6594085693],"type":"Point"}
}