{
  "type": "Feature",
  "properties": {
    "addr:full":"76 Albert St Mordialloc VIC 3195",
    "addr:housenumber":"76",
    "addr:postcode":"3195",
    "addr:street":"Albert St",
    "iso:country":"AU",
    "sg:address":"76 Albert St",
    "sg:city":"Mordialloc",
    "sg:classifiers":[
        {
            "category":"Home & Garden",
            "subcategory":"Building Materials",
            "type":"Retail Goods"
        }
    ],
    "sg:phone":"+61 3 9587 9277",
    "sg:postcode":"3195",
    "sg:province":"VIC",
    "sg:tags":[
        "secondhand"
    ],
    "wof:name":"Beachside Salvage",
    "wof:placetype":"venue"
},
  "geometry": {"coordinates":[145.08877563499999,-38.0074081421],"type":"Point"}
}