{
  "type": "Feature",
  "properties": {
    "iso:country":"AU",
    "sg:address":"4 Mutimer St",
    "sg:city":"Preston",
    "sg:classifiers":[
        {
            "category":"Building & Trades",
            "subcategory":"Construction",
            "type":"Services"
        }
    ],
    "sg:phone":"+61 419 599 334",
    "sg:postcode":"3072",
    "sg:province":"VIC",
    "sg:tags":[
        "contractor"
    ],
    "wof:name":"RMP Home Builders Pty Ltd",
    "wof:placetype":"venue"
},
  "geometry": {"coordinates":[145.01272582999999,-37.7410926819],"type":"Point"}
}