{
  "type": "Feature",
  "properties": {
    "iso:country":"AU",
    "sg:address":"2/ 243 Waverley Rd",
    "sg:city":"Malvern East",
    "sg:classifiers":[
        {
            "category":"Health Services",
            "subcategory":"Health Practitioner",
            "type":"Services"
        }
    ],
    "sg:phone":"+61 409 799 351",
    "sg:postcode":"3145",
    "sg:province":"VIC",
    "sg:tags":[
        "pathologist",
        "speech"
    ],
    "wof:name":"Dyer Lisa",
    "wof:placetype":"venue"
},
  "geometry": {"coordinates":[145.055908203,-37.8767776489],"type":"Point"}
}