{
  "type": "Feature",
  "properties": {
    "addr:full":"120 Beresford Rd Lilydale VIC 3140",
    "addr:housenumber":"120",
    "addr:postcode":"3140",
    "addr:street":"Beresford Rd",
    "iso:country":"AU",
    "sg:address":"120 Beresford Rd",
    "sg:city":"Lilydale",
    "sg:classifiers":[
        {
            "category":"Home & Garden",
            "subcategory":"Building Materials",
            "type":"Retail Goods"
        }
    ],
    "sg:phone":"+61 3 9735 8700",
    "sg:postcode":"3140",
    "sg:province":"VIC",
    "sg:tags":[
        "plaster",
        "plasterboard",
        "supply"
    ],
    "wof:name":"Drywall Direct Victoria Pty Ltd",
    "wof:placetype":"venue"
},
  "geometry": {"coordinates":[145.34454345699999,-37.7507476807],"type":"Point"}
}