{
  "type": "Feature",
  "properties": {
    "addr:full":"2nd Flr Sydney Dental Hospital 2 Chalmers St Surry Hills NSW 2010",
    "addr:housenumber":"2",
    "addr:postcode":"2010",
    "addr:street":"Chalmers St",
    "iso:country":"AU",
    "sg:address":"2nd Flr Sydney Dental Hospital 2 Chalmers St",
    "sg:city":"Surry Hills",
    "sg:classifiers":[
        {
            "category":"Health Services",
            "subcategory":"Dentist",
            "type":"Services"
        }
    ],
    "sg:phone":"+61 2 9351 8314",
    "sg:postcode":"2010",
    "sg:province":"NSW",
    "wof:name":"Darendeliler M.Ali",
    "wof:placetype":"venue"
},
  "geometry": {"coordinates":[151.208084106,-33.8840103149],"type":"Point"}
}