{
  "type": "Feature",
  "properties": {
    "addr:full":"Shop 1/ 37 Sunderland Drv Banksia Beach QLD 4507",
    "addr:housenumber":"shop 1 / 37",
    "addr:postcode":"4507",
    "addr:street":"Sunderland Drv",
    "iso:country":"AU",
    "sg:address":"Shop 1/ 37 Sunderland Drv",
    "sg:city":"Banksia Beach",
    "sg:classifiers":[
        {
            "category":"Personal",
            "subcategory":"Beauty Salon",
            "type":"Services"
        }
    ],
    "sg:phone":"+61 7 3410 7977",
    "sg:postcode":"4507",
    "sg:province":"QLD",
    "sg:tags":[
        "hairdresser"
    ],
    "wof:name":"Island Hair Affair",
    "wof:placetype":"venue"
},
  "geometry": {"coordinates":[153.13963317899999,-27.0448570251],"type":"Point"}
}