{
  "type": "Feature",
  "properties": {
    "iso:country":"AU",
    "sg:address":"144 Camberwell Road, Cnr Redfern Road",
    "sg:city":"Hawthorn East",
    "sg:classifiers":[
        {
            "category":"Home & Garden",
            "subcategory":"Furniture",
            "type":"Retail Goods"
        }
    ],
    "sg:phone":"+61 3 9882 2483",
    "sg:postcode":"3123",
    "sg:province":"VIC",
    "sg:tags":[
        "repair",
        "restoration"
    ],
    "wof:name":"City Office Upholstery",
    "wof:placetype":"venue"
},
  "geometry": {"coordinates":[145.052902222,-37.8303451538],"type":"Point"}
}