{
  "type": "Feature",
  "properties": {
    "addr:full":"13 Shelley Drv Byron Bay NSW 2481",
    "addr:housenumber":"13",
    "addr:postcode":"2481",
    "addr:street":"Shelley Drv",
    "iso:country":"AU",
    "sg:address":"13 Shelley Drv",
    "sg:city":"Byron Bay",
    "sg:classifiers":[
        {
            "category":"Professional",
            "subcategory":"Business Services",
            "type":"Services"
        }
    ],
    "sg:phone":"+61 2 6685 7713",
    "sg:postcode":"2481",
    "sg:province":"NSW",
    "sg:tags":[
        "drafting"
    ],
    "wof:name":"Byron Energy Efficient Design & Drafting",
    "wof:placetype":"venue"
},
  "geometry": {"coordinates":[153.61872863799999,-28.654499054],"type":"Point"}
}