{
  "type": "Feature",
  "properties": {
    "addr:full":"24 Houston Rd Kingsford NSW 2032",
    "addr:housenumber":"24",
    "addr:postcode":"2032",
    "addr:street":"Houston Rd",
    "iso:country":"AU",
    "sg:address":"24 Houston Rd",
    "sg:city":"Kingsford",
    "sg:classifiers":[
        {
            "category":"Education",
            "subcategory":"Kindergarten",
            "type":"Public Place"
        }
    ],
    "sg:phone":"+61 2 9663 2163",
    "sg:postcode":"2032",
    "sg:province":"NSW",
    "sg:tags":[
        "pre-schools"
    ],
    "wof:name":"Greengables Childrens Day Care Centre",
    "wof:placetype":"venue"
},
  "geometry": {"coordinates":[151.225265503,-33.9199295044],"type":"Point"}
}