{
  "type": "Feature",
  "properties": {
    "iso:country":"AU",
    "sg:address":"286 Coward St",
    "sg:city":"Mascot",
    "sg:classifiers":[
        {
            "category":"Professional",
            "type":"Services"
        }
    ],
    "sg:phone":"+61 2 9667 2311",
    "sg:postcode":"2020",
    "sg:province":"NSW",
    "sg:tags":[
        "forwarding",
        "agent",
        "transport"
    ],
    "wof:name":"Pacific Network",
    "wof:placetype":"venue"
},
  "geometry": {"coordinates":[151.18066406200001,-33.9232254028],"type":"Point"}
}