{
  "type": "Feature",
  "properties": {
    "addr:full":"Lvl1/ 318 St Kilda Rd St Kilda VIC 3182",
    "addr:housenumber":"318",
    "addr:postcode":"3182",
    "addr:street":"St Kilda Rd",
    "iso:country":"AU",
    "sg:address":"Lvl1/ 318 St Kilda Rd",
    "sg:city":"St Kilda",
    "sg:classifiers":[
        {
            "category":"Banks & Credit Unions",
            "subcategory":"Investment Brokerage",
            "type":"Services"
        }
    ],
    "sg:phone":"+61 3 9534 1977",
    "sg:postcode":"3182",
    "sg:province":"VIC",
    "wof:name":"Australian Investment Property Corp Pty Ltd",
    "wof:placetype":"venue"
},
  "geometry": {"coordinates":[144.98622131400001,-37.8650245667],"type":"Point"}
}