{
  "type": "Feature",
  "properties": {
    "iso:country":"AU",
    "sg:address":"145 New Town Rd",
    "sg:city":"New Town",
    "sg:classifiers":[
        {
            "category":"Personal",
            "subcategory":"Skin Care",
            "type":"Services"
        }
    ],
    "sg:phone":"+61 13 78 48",
    "sg:postcode":"7008",
    "sg:province":"TAS",
    "sg:tags":[
        "information",
        "treatment",
        "smoker"
    ],
    "wof:name":"Quit Tasmania",
    "wof:placetype":"venue"
},
  "geometry": {"coordinates":[147.30426025400001,-42.8522186279],"type":"Point"}
}