{
  "type": "Feature",
  "properties": {
    "addr:full":"Shop 12, 650 Sydney Rd Brunswick VIC 3056",
    "addr:housenumber":"shop 12 650",
    "addr:postcode":"3056",
    "addr:street":"Sydney Rd",
    "iso:country":"AU",
    "sg:address":"Shop 12, 650 Sydney Rd",
    "sg:city":"Brunswick",
    "sg:classifiers":[
        {
            "category":"Personal",
            "subcategory":"Beauty Salon",
            "type":"Services"
        }
    ],
    "sg:phone":"+61 3 9383 7731",
    "sg:postcode":"3056",
    "sg:province":"VIC",
    "sg:tags":[
        "hairdresser"
    ],
    "wof:name":"Saad's Beauty Palace",
    "wof:placetype":"venue"
},
  "geometry": {"coordinates":[144.963058472,-37.7623405457],"type":"Point"}
}