{
  "type": "Feature",
  "properties": {
    "addr:full":"29 Seabright St North Shore VIC 3214",
    "addr:housenumber":"29",
    "addr:postcode":"3214",
    "addr:street":"Seabright St",
    "iso:country":"AU",
    "sg:address":"29 Seabright St",
    "sg:city":"North Shore",
    "sg:classifiers":[
        {
            "category":"Fast Food",
            "type":"Food & Drink"
        }
    ],
    "sg:phone":"+61 3 5272 1918",
    "sg:postcode":"3214",
    "sg:province":"VIC",
    "sg:tags":[
        "away",
        "take"
    ],
    "wof:name":"Seabright Takeaway",
    "wof:placetype":"venue"
},
  "geometry": {"coordinates":[144.36961364699999,-38.097240448],"type":"Point"}
}