{
  "type": "Feature",
  "properties": {
    "addr:full":"187 Sheridan St Cairns QLD 4870",
    "addr:housenumber":"187",
    "addr:postcode":"4870",
    "addr:street":"Sheridan St",
    "iso:country":"AU",
    "sg:address":"187 Sheridan St",
    "sg:city":"Cairns",
    "sg:classifiers":[
        {
            "category":"Travel",
            "subcategory":"Hotels & Motels",
            "type":"Entertainment"
        }
    ],
    "sg:phone":"+61 7 4051 5166",
    "sg:postcode":"4870",
    "sg:province":"QLD",
    "wof:name":"Cairns Motor Inn",
    "wof:placetype":"venue"
},
  "geometry": {"coordinates":[145.765136719,-16.9139270782],"type":"Point"}
}