{
  "type": "Feature",
  "properties": {
    "addr:full":"58 Bass Hwy Burnie TAS 7320",
    "addr:housenumber":"58",
    "addr:postcode":"7320",
    "addr:street":"Bass Hwy",
    "iso:country":"AU",
    "sg:address":"58 Bass Hwy",
    "sg:city":"Burnie",
    "sg:classifiers":[
        {
            "category":"Professional",
            "subcategory":"Testing Lab",
            "type":"Services"
        }
    ],
    "sg:phone":"+61 3 6432 4350",
    "sg:postcode":"7320",
    "sg:province":"TAS",
    "sg:tags":[
        "soil",
        "investigation"
    ],
    "wof:name":"SFM Pty Ltd",
    "wof:placetype":"venue"
},
  "geometry": {"coordinates":[145.87550400000001,-41.040825],"type":"Point"}
}