{
  "type": "Feature",
  "properties": {
    "iso:country":"AU",
    "sg:address":"Unit 2/ 4 Bellingham St",
    "sg:city":"Narellan",
    "sg:classifiers":[
        {
            "category":"Manufacturing",
            "subcategory":"Motor Vehicles & Parts",
            "type":"Manufacturing & Wholesale Goods"
        }
    ],
    "sg:phone":"+61 2 4646 1111",
    "sg:postcode":"2567",
    "sg:province":"NSW",
    "sg:tags":[
        "wholesaler",
        "cycle",
        "mfrs",
        "accessory"
    ],
    "wof:name":"Philpott Brothers",
    "wof:placetype":"venue"
},
  "geometry": {"coordinates":[150.73127746599999,-34.0374107361],"type":"Point"}
}