{
  "type": "Feature",
  "properties": {
    "addr:full":"45 Church St Penola SA 5277",
    "addr:housenumber":"45",
    "addr:postcode":"5277",
    "addr:street":"Church St",
    "iso:country":"AU",
    "sg:address":"45 Church St",
    "sg:city":"Penola",
    "sg:classifiers":[
        {
            "category":"Shopping",
            "subcategory":"Antiques",
            "type":"Retail Goods"
        }
    ],
    "sg:phone":"+61 8 8737 2077",
    "sg:postcode":"5277",
    "sg:province":"SA",
    "sg:tags":[
        "restoration",
        "reproduction"
    ],
    "wof:name":"Never Too Old",
    "wof:placetype":"venue"
},
  "geometry": {"coordinates":[140.83708200000001,-37.378174],"type":"Point"}
}