{
  "type": "Feature",
  "properties": {
    "addr:full":"153 Mercer St Geelong VIC 3220",
    "addr:housenumber":"153",
    "addr:postcode":"3220",
    "addr:street":"Mercer St",
    "iso:country":"AU",
    "sg:address":"153 Mercer St",
    "sg:city":"Geelong",
    "sg:classifiers":[
        {
            "category":"Professional",
            "subcategory":"Accounting & Tax Preparation",
            "type":"Services"
        }
    ],
    "sg:phone":"+61 3 5222 1048",
    "sg:postcode":"3220",
    "sg:province":"VIC",
    "sg:tags":[
        "accountant",
        "auditor"
    ],
    "wof:name":"Coumans Chartered Accountants",
    "wof:placetype":"venue"
},
  "geometry": {"coordinates":[144.36210600000001,-38.150875],"type":"Point"}
}