{
  "type": "Feature",
  "properties": {
    "iso:country":"AU",
    "sg:address":"Forest Corners 18 Forest St",
    "sg:city":"Bridgetown",
    "sg:classifiers":[
        {
            "category":"Health Services",
            "subcategory":"Chiropractor",
            "type":"Services"
        }
    ],
    "sg:phone":"+61 8 9761 1454",
    "sg:postcode":"6255",
    "sg:province":"WA",
    "wof:name":"Mark Neilson Dr",
    "wof:placetype":"venue"
},
  "geometry": {"coordinates":[116.143180847,-33.9559898376],"type":"Point"}
}