{
  "type": "Feature",
  "properties": {
    "iso:country":"AU",
    "sg:address":"18 St Johns Ave",
    "sg:city":"Mont Albert",
    "sg:classifiers":[
        {
            "category":"Professional",
            "subcategory":"Accounting & Tax Preparation",
            "type":"Services"
        }
    ],
    "sg:phone":"+61 3 9890 3096",
    "sg:postcode":"3127",
    "sg:province":"VIC",
    "sg:tags":[
        "cathodic",
        "protection"
    ],
    "wof:name":"Bruce Ackland & Associates Pty Ltd",
    "wof:placetype":"venue"
},
  "geometry": {"coordinates":[145.10783386200001,-37.8225250244],"type":"Point"}
}