{
  "type": "Feature",
  "properties": {
    "addr:full":"732 - 734 Forest Rd Peakhurst NSW 2210",
    "addr:housenumber":"734",
    "addr:postcode":"2210",
    "addr:street":"Forest Rd",
    "iso:country":"AU",
    "sg:address":"732 - 734 Forest Rd",
    "sg:city":"Peakhurst",
    "sg:classifiers":[
        {
            "category":"Building & Trades",
            "subcategory":"Construction",
            "type":"Services"
        }
    ],
    "sg:phone":"+61 2 9584 7200",
    "sg:postcode":"2210",
    "sg:province":"NSW",
    "sg:tags":[
        "installation",
        "air conditioning"
    ],
    "sg:website":"http://www.coralair.com.au",
    "wof:name":"Coral Air Pty Ltd",
    "wof:placetype":"venue"
},
  "geometry": {"coordinates":[151.069885,-33.958431],"type":"Point"}
}