{
  "type": "Feature",
  "properties": {
    "addr:full":"238 Maude St Mall Shepparton VIC 3630",
    "addr:housenumber":"238",
    "addr:postcode":"3630",
    "addr:street":"Maude St Mall",
    "iso:country":"AU",
    "sg:address":"238 Maude St Mall",
    "sg:city":"Shepparton",
    "sg:classifiers":[
        {
            "category":"Shopping",
            "subcategory":"Shoes",
            "type":"Retail Goods"
        }
    ],
    "sg:phone":"+61 3 5821 6914",
    "sg:postcode":"3630",
    "sg:province":"VIC",
    "sg:tags":[
        "footwear"
    ],
    "wof:name":"Lou's Shoe Repairs",
    "wof:placetype":"venue"
},
  "geometry": {"coordinates":[145.400634766,-36.3811187744],"type":"Point"}
}