{
  "type": "Feature",
  "properties": {
    "iso:country":"AU",
    "sg:address":"60A Waverly Rd",
    "sg:city":"Malvern",
    "sg:classifiers":[
        {
            "category":"Manufacturing",
            "subcategory":"Food",
            "type":"Manufacturing & Wholesale Goods"
        }
    ],
    "sg:phone":"+61 3 9571 0322",
    "sg:postcode":"3144",
    "sg:province":"VIC",
    "sg:tags":[
        "function",
        "catering"
    ],
    "wof:name":"Subway",
    "wof:placetype":"venue"
},
  "geometry": {"coordinates":[145.03689575199999,-37.8525390625],"type":"Point"}
}