{
  "type": "Feature",
  "properties": {
    "addr:full":"295 Manks Rd Five Ways VIC 3977",
    "addr:housenumber":"295",
    "addr:postcode":"3977",
    "addr:street":"Manks Rd",
    "iso:country":"AU",
    "sg:address":"295 Manks Rd",
    "sg:city":"Five Ways",
    "sg:classifiers":[
        {
            "category":"Manufacturing",
            "subcategory":"Tools & Machinery",
            "type":"Manufacturing & Wholesale Goods"
        }
    ],
    "sg:phone":"+61 417 581 731",
    "sg:postcode":"3977",
    "sg:province":"VIC",
    "sg:tags":[
        "earth",
        "excavating",
        "moving",
        "equipment"
    ],
    "wof:name":"Casey Plant Hire",
    "wof:placetype":"venue"
},
  "geometry": {"coordinates":[145.32017517099999,-38.1626205444],"type":"Point"}
}