{
  "type": "Feature",
  "properties": {
    "addr:full":"72 McLennan St Mooroopna VIC 3629",
    "addr:housenumber":"72",
    "addr:postcode":"3629",
    "addr:street":"Mclennan St",
    "iso:country":"AU",
    "sg:address":"72 McLennan St",
    "sg:city":"Mooroopna",
    "sg:classifiers":[
        {
            "category":"Fast Food",
            "type":"Food & Drink"
        }
    ],
    "sg:phone":"+61 3 5825 2598",
    "sg:postcode":"3629",
    "sg:province":"VIC",
    "sg:tags":[
        "away",
        "take"
    ],
    "wof:name":"Peter's Fish Shop",
    "wof:placetype":"venue"
},
  "geometry": {"coordinates":[145.36076355,-36.3941917419],"type":"Point"}
}