{
  "type": "Feature",
  "properties": {
    "addr:full":"357 Cobalt St Broken Hill NSW 2880",
    "addr:housenumber":"357",
    "addr:postcode":"2880",
    "addr:street":"Cobalt St",
    "iso:country":"AU",
    "sg:address":"357 Cobalt St",
    "sg:city":"Broken Hill",
    "sg:classifiers":[
        {
            "category":"Travel",
            "subcategory":"Hotels & Motels",
            "type":"Entertainment"
        }
    ],
    "sg:phone":"+61 8 8087 3679",
    "sg:postcode":"2880",
    "sg:province":"NSW",
    "sg:tags":[
        "accommodation"
    ],
    "wof:name":"Southern Cross Hotel",
    "wof:placetype":"venue"
},
  "geometry": {"coordinates":[141.46539306599999,-31.9544868469],"type":"Point"}
}