{
  "type": "Feature",
  "properties": {
    "addr:full":"Arthur St Tambo QLD 4478",
    "addr:postcode":"4478",
    "addr:street":"Arthur St",
    "iso:country":"AU",
    "sg:address":"Arthur St",
    "sg:city":"Tambo",
    "sg:classifiers":[
        {
            "category":"Autos & Motor Vehicles",
            "subcategory":"Fuel & Gas Station",
            "type":"Retail Goods"
        }
    ],
    "sg:phone":"+61 7 4654 6137",
    "sg:postcode":"4478",
    "sg:province":"QLD",
    "wof:name":"Shell Tambo",
    "wof:placetype":"venue"
},
  "geometry": {"coordinates":[146.254592895,-24.8829174042],"type":"Point"}
}