{
  "type": "Feature",
  "properties": {
    "iso:country":"AU",
    "sg:address":"32 Warren Pl",
    "sg:city":"Mandurah",
    "sg:classifiers":[
        {
            "category":"Professional",
            "subcategory":"Employment Agencies",
            "type":"Services"
        }
    ],
    "sg:phone":"+61 427 198 660",
    "sg:postcode":"6210",
    "sg:province":"WA",
    "sg:tags":[
        "hire",
        "labour",
        "contractor"
    ],
    "wof:name":"About Childcare",
    "wof:placetype":"venue"
},
  "geometry": {"coordinates":[115.72496,-32.547626],"type":"Point"}
}