{
  "type": "Feature",
  "properties": {
    "addr:full":"Lvl 1/ 405 Brunswick St Fitzroy VIC 3065",
    "addr:housenumber":"/ 405",
    "addr:postcode":"3065",
    "addr:street":"Brunswick St",
    "iso:country":"AU",
    "sg:address":"Lvl 1/ 405 Brunswick St",
    "sg:city":"Fitzroy",
    "sg:classifiers":[
        {
            "category":"Health Services",
            "subcategory":"Health Practitioner",
            "type":"Services"
        }
    ],
    "sg:phone":"+61 423 974 134",
    "sg:postcode":"3065",
    "sg:province":"VIC",
    "sg:tags":[
        "acupuncture"
    ],
    "wof:name":"Drok Annalise",
    "wof:placetype":"venue"
},
  "geometry": {"coordinates":[144.97885131800001,-37.7950172424],"type":"Point"}
}