{
  "type": "Feature",
  "properties": {
    "iso:country":"AU",
    "sg:address":"670-678 Bruce Hwy (Service Rd)",
    "sg:city":"Cairns",
    "sg:classifiers":[
        {
            "category":"Travel",
            "subcategory":"Hotels & Motels",
            "type":"Entertainment"
        }
    ],
    "sg:phone":"+61 7 4033 0522",
    "sg:postcode":"4870",
    "sg:province":"QLD",
    "wof:name":"Cairns Reef Apartments And Motel",
    "wof:placetype":"venue"
},
  "geometry": {"coordinates":[145.74354553200001,-17.0017414093],"type":"Point"}
}