{
  "type": "Feature",
  "properties": {
    "iso:country":"AU",
    "sg:address":"Unit 102 396 Scarborough Beach Rd",
    "sg:city":"Osborne Park",
    "sg:classifiers":[
        {
            "category":"Professional",
            "subcategory":"Computer Services",
            "type":"Services"
        }
    ],
    "sg:phone":"+61 8 9201 2021",
    "sg:postcode":"6017",
    "sg:province":"WA",
    "sg:tags":[
        "information"
    ],
    "wof:name":"Deeptech",
    "wof:placetype":"venue"
},
  "geometry": {"coordinates":[115.814582825,-31.9106483459],"type":"Point"}
}