{
  "type": "Feature",
  "properties": {
    "iso:country":"AU",
    "sg:address":"151 Centre St",
    "sg:city":"Casino",
    "sg:classifiers":[
        {
            "category":"Retail",
            "subcategory":"Repair Shop",
            "type":"Services"
        }
    ],
    "sg:phone":"+61 2 6662 2421",
    "sg:postcode":"2470",
    "sg:province":"NSW",
    "sg:tags":[
        "windscreen"
    ],
    "wof:name":"Peart T.J. & F.L.",
    "wof:placetype":"venue"
},
  "geometry": {"coordinates":[153.04721069300001,-28.8565292358],"type":"Point"}
}