{
  "type": "Feature",
  "properties": {
    "iso:country":"AU",
    "sg:address":"Unit 1/ 160 Beechboro Rd",
    "sg:city":"South Bayswater",
    "sg:classifiers":[
        {
            "category":"Wholesale",
            "subcategory":"Machinery & Supplies",
            "type":"Manufacturing & Wholesale Goods"
        }
    ],
    "sg:phone":"+61 8 9271 4626",
    "sg:postcode":"6053",
    "sg:province":"WA",
    "sg:tags":[
        "equipment",
        "hydraulic"
    ],
    "wof:name":"Compri Tube Clean Pty Ltd",
    "wof:placetype":"venue"
},
  "geometry": {"coordinates":[115.919029236,-31.901304245],"type":"Point"}
}