{
  "type": "Feature",
  "properties": {
    "addr:full":"Shp4/ 39 Park St Glenbrook NSW 2773",
    "addr:housenumber":"39",
    "addr:postcode":"2773",
    "addr:street":"Park St",
    "iso:country":"AU",
    "sg:address":"Shp4/ 39 Park St",
    "sg:city":"Glenbrook",
    "sg:classifiers":[
        {
            "category":"Personal",
            "subcategory":"Beauty Salon",
            "type":"Services"
        }
    ],
    "sg:phone":"+61 2 4739 2051",
    "sg:postcode":"2773",
    "sg:province":"NSW",
    "sg:tags":[
        "hairdresser"
    ],
    "wof:name":"Braid - Wood Hair Salon",
    "wof:placetype":"venue"
},
  "geometry": {"coordinates":[150.622802734,-33.7668838501],"type":"Point"}
}