{
  "type": "Feature",
  "properties": {
    "addr:full":"PO Box 1390 Parramatta NSW 2124",
    "addr:postcode":"2124",
    "iso:country":"AU",
    "sg:address":"PO Box 1390",
    "sg:city":"Parramatta",
    "sg:classifiers":[
        {
            "category":"Real Estate",
            "subcategory":"Real Estate Operator",
            "type":"Services"
        }
    ],
    "sg:phone":"+61 2 8839 8222",
    "sg:postcode":"2124",
    "sg:province":"NSW",
    "sg:tags":[
        "building",
        "consultant",
        "management"
    ],
    "wof:name":"Alliance Network International Pty Ltd",
    "wof:placetype":"venue"
},
  "geometry": {"coordinates":[151.003448486,-33.8169593811],"type":"Point"}
}