{
  "type": "Feature",
  "properties": {
    "iso:country":"AU",
    "sg:address":"17 Rokeby Rd",
    "sg:city":"Subiaco",
    "sg:classifiers":[
        {
            "category":"Personal",
            "subcategory":"Beauty Salon",
            "type":"Services"
        }
    ],
    "sg:phone":"+61 8 9382 3004",
    "sg:postcode":"6008",
    "sg:province":"WA",
    "sg:tags":[
        "hairdresser"
    ],
    "sg:website":"http://www.elementac.com.au",
    "wof:name":"Element Aveda Concept",
    "wof:placetype":"venue"
},
  "geometry": {"coordinates":[115.823860169,-31.9460544586],"type":"Point"}
}