{
  "type": "Feature",
  "properties": {
    "addr:full":"Pillar St Toowoomba QLD 4350",
    "addr:postcode":"4350",
    "addr:street":"Pillar St",
    "iso:country":"AU",
    "sg:address":"Pillar St",
    "sg:city":"Toowoomba",
    "sg:classifiers":[
        {
            "category":"Retail",
            "subcategory":"Event Space",
            "type":"Services"
        }
    ],
    "sg:phone":"+61 7 4635 4564",
    "sg:postcode":"4350",
    "sg:province":"QLD",
    "sg:tags":[
        "venue",
        "reception",
        "wedding"
    ],
    "wof:name":"Toowoomba Valley's Rugby League Football Club",
    "wof:placetype":"venue"
},
  "geometry": {"coordinates":[151.95103499999999,-27.604771],"type":"Point"}
}