{
  "type": "Feature",
  "properties": {
    "iso:country":"AU",
    "sg:address":"4 Main St",
    "sg:city":"Upwey",
    "sg:classifiers":[
        {
            "category":"Fast Food",
            "type":"Food & Drink"
        }
    ],
    "sg:phone":"+61 3 9754 2520",
    "sg:postcode":"3158",
    "sg:province":"VIC",
    "sg:tags":[
        "away",
        "take"
    ],
    "wof:name":"Upwey Fish & Chips",
    "wof:placetype":"venue"
},
  "geometry": {"coordinates":[145.32969665499999,-37.9028091431],"type":"Point"}
}