{
  "type": "Feature",
  "properties": {
    "iso:country":"AU",
    "sg:address":"Unit 11 Lot27/ Shearer Drv",
    "sg:city":"Seaford",
    "sg:classifiers":[
        {
            "category":"Building & Trades",
            "subcategory":"Plumbing",
            "type":"Services"
        }
    ],
    "sg:phone":"+61 8 8327 4011",
    "sg:postcode":"5169",
    "sg:province":"SA",
    "sg:tags":[
        "plumber",
        "gasfitters"
    ],
    "wof:name":"Finlay T E & R Plumbing Services Pty Ltd",
    "wof:placetype":"venue"
},
  "geometry": {"coordinates":[138.491165161,-35.1804237366],"type":"Point"}
}