{
  "type": "Feature",
  "properties": {
    "addr:full":"Shop 7 North Mall Arc Rutherford NSW 2320",
    "addr:housenumber":"shop 7",
    "addr:postcode":"2320",
    "addr:street":"North Mall Arc",
    "iso:country":"AU",
    "sg:address":"Shop 7",
    "sg:city":"North Mall Arc Rutherford",
    "sg:classifiers":[
        {
            "category":"Professional",
            "subcategory":"Advertising",
            "type":"Services"
        }
    ],
    "sg:phone":"+61 2 4932 3501",
    "sg:postcode":"2320",
    "sg:province":"NSW",
    "sg:tags":[
        "balloon",
        "novelty"
    ],
    "wof:name":"Earthly Stems Rutherford Florist",
    "wof:placetype":"venue"
},
  "geometry": {"coordinates":[151.52838134800001,-32.7151298523],"type":"Point"}
}