{
  "type": "Feature",
  "properties": {
    "addr:full":"225 Corfe Rd Roma QLD 4455",
    "addr:housenumber":"225",
    "addr:postcode":"4455",
    "addr:street":"Corfe Rd",
    "iso:country":"AU",
    "sg:address":"225 Corfe Rd",
    "sg:city":"Roma",
    "sg:classifiers":[
        {
            "category":"Retail",
            "subcategory":"Auto Repair",
            "type":"Services"
        }
    ],
    "sg:phone":"+61 7 4622 3101",
    "sg:postcode":"4455",
    "sg:province":"QLD",
    "sg:tags":[
        "repairer",
        "motor",
        "engineer"
    ],
    "wof:name":"Pearns Auto",
    "wof:placetype":"venue"
},
  "geometry": {"coordinates":[148.79330444300001,-26.5873374939],"type":"Point"}
}