{
  "type": "Feature",
  "properties": {
    "addr:full":"Lot 1 Station St Maffra VIC 3860",
    "addr:housenumber":"1",
    "addr:postcode":"3860",
    "addr:street":"Station St",
    "iso:country":"AU",
    "sg:address":"Lot 1 Station St",
    "sg:city":"Maffra",
    "sg:phone":"+61 3 5141 1623",
    "sg:postcode":"3860",
    "sg:province":"VIC",
    "wof:name":"Maffra Poly & Pumps",
    "wof:placetype":"venue"
},
  "geometry": {"coordinates":[147.07228088400001,-37.8460273743],"type":"Point"}
}