{
  "type": "Feature",
  "properties": {
    "addr:full":"Lvl 2 80 McLachlan Ave Rushcutters Bay NSW 2011",
    "addr:housenumber":"80",
    "addr:postcode":"2011",
    "addr:street":"Mclachlan Ave",
    "iso:country":"AU",
    "sg:address":"Lvl 2 80 McLachlan Ave",
    "sg:city":"Rushcutters Bay",
    "sg:classifiers":[
        {
            "category":"Professional",
            "subcategory":"Computer Services",
            "type":"Services"
        }
    ],
    "sg:phone":"+61 2 9361 0600",
    "sg:postcode":"2011",
    "sg:province":"NSW",
    "sg:tags":[
        "on-line",
        "provider"
    ],
    "wof:name":"Magnet Internet Connections Pty Limited",
    "wof:placetype":"venue"
},
  "geometry": {"coordinates":[151.228607178,-33.8764648438],"type":"Point"}
}