{
  "type": "Feature",
  "properties": {
    "iso:country":"AU",
    "sg:address":"20 Wilga St",
    "sg:city":"Blacktown",
    "sg:classifiers":[
        {
            "category":"Home & Garden",
            "subcategory":"Garden Supply",
            "type":"Retail Goods"
        }
    ],
    "sg:phone":"+61 2 9679 7024",
    "sg:postcode":"2148",
    "sg:province":"NSW",
    "sg:tags":[
        "equipment"
    ],
    "wof:name":"Ozgro Pty Limited",
    "wof:placetype":"venue"
},
  "geometry": {"coordinates":[150.884597778,-33.7791290283],"type":"Point"}
}