{
  "type": "Feature",
  "properties": {
    "addr:full":"136 Moore St Leichhardt NSW 2040",
    "addr:housenumber":"136",
    "addr:postcode":"2040",
    "addr:street":"Moore St",
    "iso:country":"AU",
    "sg:address":"136 Moore St",
    "sg:city":"Leichhardt",
    "sg:classifiers":[
        {
            "category":"Health Services",
            "subcategory":"Health Practitioner",
            "type":"Services"
        }
    ],
    "sg:phone":"+61 2 9550 9673",
    "sg:postcode":"2040",
    "sg:province":"NSW",
    "sg:tags":[
        "hypnotherapy"
    ],
    "wof:name":"Rhondda Elizabeth Stewart",
    "wof:placetype":"venue"
},
  "geometry": {"coordinates":[151.16090399999999,-33.878628],"type":"Point"}
}