{
  "type": "Feature",
  "properties": {
    "iso:country":"AU",
    "sg:address":"Unit 15, 62-66 Newtown Rd",
    "sg:city":"Wetherill Park",
    "sg:classifiers":[
        {
            "category":"Building & Trades",
            "subcategory":"Plumbing",
            "type":"Services"
        }
    ],
    "sg:phone":"+61 2 8213 8677",
    "sg:postcode":"2164",
    "sg:province":"NSW",
    "sg:tags":[
        "plumber",
        "gasfitters"
    ],
    "sg:website":"http://www.topsplumbing.com.au",
    "wof:name":"Tops Plumbing Services",
    "wof:placetype":"venue"
},
  "geometry": {"coordinates":[150.88775634800001,-33.8489456177],"type":"Point"}
}