{
  "type": "Feature",
  "properties": {
    "iso:country":"AU",
    "sg:address":"52 Pavetta Crs",
    "sg:city":"Forrestfield",
    "sg:classifiers":[
        {
            "category":"Arts & Performance",
            "subcategory":"Music",
            "type":"Entertainment"
        }
    ],
    "sg:phone":"+61 8 9453 1487",
    "sg:postcode":"6058",
    "sg:province":"WA",
    "sg:tags":[
        "hi-fi",
        "equipment"
    ],
    "wof:name":"Video Hi Fi Service",
    "wof:placetype":"venue"
},
  "geometry": {"coordinates":[116.00077819800001,-31.9696292877],"type":"Point"}
}