{
  "type": "Feature",
  "properties": {
    "iso:country":"AU",
    "sg:address":"30 Tulloona St",
    "sg:city":"Mt Druitt",
    "sg:classifiers":[
        {
            "category":"Banks & Credit Unions",
            "subcategory":"Financial Services",
            "type":"Services"
        }
    ],
    "sg:phone":"+61 2 9675 2071",
    "sg:postcode":"2770",
    "sg:province":"NSW",
    "sg:tags":[
        "loan",
        "finance",
        "mortgage"
    ],
    "wof:name":"Denmar Consultants",
    "wof:placetype":"venue"
},
  "geometry": {"coordinates":[150.816497803,-33.7598800659],"type":"Point"}
}