{
  "type": "Feature",
  "properties": {
    "addr:full":"Kenrick St Merewether NSW 2291",
    "addr:postcode":"2291",
    "addr:street":"Kenrick St",
    "iso:country":"AU",
    "sg:address":"Kenrick St",
    "sg:city":"Merewether",
    "sg:classifiers":[
        {
            "category":"Education",
            "subcategory":"School",
            "type":"Public Place"
        }
    ],
    "sg:phone":"+61 2 4969 3795",
    "sg:postcode":"2291",
    "sg:province":"NSW",
    "sg:tags":[
        "state",
        "-",
        "nsw"
    ],
    "wof:name":"Hamilton South Public School",
    "wof:placetype":"venue"
},
  "geometry": {"coordinates":[151.75683593799999,-32.9360580444],"type":"Point"}
}