{
  "type": "Feature",
  "properties": {
    "addr:full":"35 Maroubra St Maroochydore QLD 4558",
    "addr:housenumber":"35",
    "addr:postcode":"4558",
    "addr:street":"Maroubra St",
    "iso:country":"AU",
    "sg:address":"35 Maroubra St",
    "sg:city":"Maroochydore",
    "sg:classifiers":[
        {
            "category":"Health Services",
            "subcategory":"Health Practitioner",
            "type":"Services"
        }
    ],
    "sg:phone":"+61 7 5443 9651",
    "sg:postcode":"4558",
    "sg:province":"QLD",
    "sg:tags":[
        "hypnotherapy"
    ],
    "wof:name":"Mil McCormack Northstar Counselling",
    "wof:placetype":"venue"
},
  "geometry": {"coordinates":[153.10191345199999,-26.6632461548],"type":"Point"}
}