{
  "type": "Feature",
  "properties": {
    "iso:country":"AU",
    "sg:address":"274 Macquarie Rd",
    "sg:city":"Warners Bay",
    "sg:classifiers":[
        {
            "category":"Home & Garden",
            "subcategory":"Carpets & Floor Coverings",
            "type":"Retail Goods"
        }
    ],
    "sg:phone":"+61 2 4954 8947",
    "sg:postcode":"2282",
    "sg:province":"NSW",
    "sg:tags":[
        "mattress"
    ],
    "wof:name":"Sleepys Warnersbay",
    "wof:placetype":"venue"
},
  "geometry": {"coordinates":[151.65267944300001,-32.9663352966],"type":"Point"}
}