{
  "type": "Feature",
  "properties": {
    "addr:full":"Shop 4/ 6 Commercial Drv Springfield QLD 4300",
    "addr:housenumber":"shop 4 / 6",
    "addr:postcode":"4300",
    "addr:street":"Commercial Drv",
    "iso:country":"AU",
    "sg:address":"Shop 4/ 6 Commercial Drv",
    "sg:city":"Springfield",
    "sg:classifiers":[
        {
            "category":"Personal",
            "subcategory":"Beauty Salon",
            "type":"Services"
        }
    ],
    "sg:phone":"+61 7 3288 1422",
    "sg:postcode":"4300",
    "sg:province":"QLD",
    "sg:tags":[
        "hairdresser"
    ],
    "wof:name":"Chipper Hair Pty Ltd",
    "wof:placetype":"venue"
},
  "geometry": {"coordinates":[152.91786193900001,-27.6556854248],"type":"Point"}
}