{
  "type": "Feature",
  "properties": {
    "iso:country":"AU",
    "sg:address":"Shop 1062 Garden City Shopping Centre Logan Rd",
    "sg:city":"Upper Mt Gravatt",
    "sg:classifiers":[
        {
            "category":"Shopping",
            "subcategory":"Clothing, Apparel, & Fashions",
            "type":"Retail Goods"
        }
    ],
    "sg:phone":"+61 7 3343 4477",
    "sg:postcode":"4122",
    "sg:province":"QLD",
    "sg:tags":[
        "jean"
    ],
    "wof:name":"JeansWest",
    "wof:placetype":"venue"
},
  "geometry": {"coordinates":[153.08169555699999,-27.5645084381],"type":"Point"}
}