{
  "type": "Feature",
  "properties": {
    "addr:full":"PO Box 70 Blakehurst NSW 2221",
    "addr:postcode":"2221",
    "iso:country":"AU",
    "sg:address":"PO Box 70",
    "sg:city":"Blakehurst",
    "sg:classifiers":[
        {
            "category":"Professional",
            "subcategory":"Employment Agencies",
            "type":"Services"
        }
    ],
    "sg:phone":"+61 1300 720 723",
    "sg:postcode":"2221",
    "sg:province":"NSW",
    "sg:tags":[
        "provider",
        "internet"
    ],
    "wof:name":"Macrotec Technical Support",
    "wof:placetype":"venue"
},
  "geometry": {"coordinates":[151.11166381800001,-33.9878501892],"type":"Point"}
}