{
  "type": "Feature",
  "properties": {
    "iso:country":"AU",
    "sg:address":"5 Wells St",
    "sg:city":"Penrith South",
    "sg:classifiers":[
        {
            "category":"Education",
            "subcategory":"Music School",
            "type":"Public Place"
        }
    ],
    "sg:phone":"+61 2 4733 1539",
    "sg:postcode":"2750",
    "sg:province":"NSW",
    "sg:tags":[
        "teacher"
    ],
    "wof:name":"Hobbs E A",
    "wof:placetype":"venue"
},
  "geometry": {"coordinates":[150.680130005,-33.7776451111],"type":"Point"}
}