{
  "type": "Feature",
  "properties": {
    "addr:full":"1/ 30 Sudbury St Darra QLD 4076",
    "addr:housenumber":"/ 30",
    "addr:postcode":"4076",
    "addr:street":"Sudbury St",
    "iso:country":"AU",
    "sg:address":"1/ 30 Sudbury St",
    "sg:city":"Darra",
    "sg:classifiers":[
        {
            "category":"Communications",
            "type":"Services"
        }
    ],
    "sg:phone":"+61 7 3376 6299",
    "sg:postcode":"4076",
    "sg:province":"QLD",
    "sg:tags":[
        "data"
    ],
    "wof:name":"Laser Electrical Rocklea",
    "wof:placetype":"venue"
},
  "geometry": {"coordinates":[152.94499206500001,-27.5622367859],"type":"Point"}
}