{
  "type": "Feature",
  "properties": {
    "addr:full":"Unit 4, 11- 13 Arizona Rd Charmhaven NSW 2263",
    "addr:housenumber":"11 13",
    "addr:postcode":"2263",
    "addr:street":"Arizona Rd",
    "iso:country":"AU",
    "sg:address":"Unit 4, 11- 13 Arizona Rd",
    "sg:city":"Charmhaven",
    "sg:classifiers":[
        {
            "category":"Home & Garden",
            "subcategory":"Carpets & Floor Coverings",
            "type":"Retail Goods"
        }
    ],
    "sg:phone":"+61 2 4393 2443",
    "sg:postcode":"2263",
    "sg:province":"NSW",
    "wof:name":"Kellys Carpets",
    "wof:placetype":"venue"
},
  "geometry": {"coordinates":[151.493774,-33.242203],"type":"Point"}
}