{
  "type": "Feature",
  "properties": {
    "addr:full":"Level 2, 397 Liverpool St Darlinghurst NSW 2010",
    "addr:housenumber":"397",
    "addr:postcode":"2010",
    "addr:street":"Liverpool St",
    "iso:country":"AU",
    "sg:address":"Level 2, 397 Liverpool St",
    "sg:city":"Darlinghurst",
    "sg:classifiers":[
        {
            "category":"Personal",
            "subcategory":"Beauty Salon",
            "type":"Services"
        }
    ],
    "sg:phone":"+61 2 9380 6449",
    "sg:postcode":"2010",
    "sg:province":"NSW",
    "sg:tags":[
        "hairdresser"
    ],
    "sg:website":"http://www.lofthair.com.au",
    "wof:name":"Loft Hair",
    "wof:placetype":"venue"
},
  "geometry": {"coordinates":[151.22128295900001,-33.8783874512],"type":"Point"}
}