{
  "type": "Feature",
  "properties": {
    "iso:country":"AU",
    "sg:address":"South Western Hwy",
    "sg:city":"Donnybrook",
    "sg:classifiers":[
        {
            "category":"Farming",
            "subcategory":"Farm",
            "type":"Manufacturing & Wholesale Goods"
        }
    ],
    "sg:phone":"+61 8 9731 1369",
    "sg:postcode":"6239",
    "sg:province":"WA",
    "sg:tags":[
        "farmer"
    ],
    "wof:name":"Terace R V",
    "wof:placetype":"venue"
},
  "geometry": {"coordinates":[115.823036,-33.570427],"type":"Point"}
}