{
  "type": "Feature",
  "properties": {
    "addr:full":"25 Keilambete Rd Rubyvale QLD 4702",
    "addr:housenumber":"25",
    "addr:postcode":"4702",
    "addr:street":"Keilambete Rd",
    "iso:country":"AU",
    "sg:address":"25 Keilambete Rd",
    "sg:city":"Rubyvale",
    "sg:classifiers":[
        {
            "category":"Shopping",
            "subcategory":"Jewelry",
            "type":"Retail Goods"
        }
    ],
    "sg:phone":"+61 7 4985 4269",
    "sg:postcode":"4702",
    "sg:province":"QLD",
    "sg:tags":[
        "jeweller",
        "supply"
    ],
    "wof:name":"Rubyvale Cut & Slice",
    "wof:placetype":"venue"
},
  "geometry": {"coordinates":[147.69830322300001,-23.4197425842],"type":"Point"}
}