{
  "type": "Feature",
  "properties": {
    "addr:full":"19 Rednal St Mona Vale NSW 2103",
    "addr:housenumber":"19",
    "addr:postcode":"2103",
    "addr:street":"Rednal St",
    "iso:country":"AU",
    "sg:address":"19 Rednal St",
    "sg:city":"Mona Vale",
    "sg:classifiers":[
        {
            "category":"Professional",
            "subcategory":"Accounting & Tax Preparation",
            "type":"Services"
        }
    ],
    "sg:phone":"+61 2 9979 7777",
    "sg:postcode":"2103",
    "sg:province":"NSW",
    "sg:tags":[
        "consultant",
        "taxation"
    ],
    "wof:name":"Teacher Taxation Service",
    "wof:placetype":"venue"
},
  "geometry": {"coordinates":[151.3074646,-33.6646461487],"type":"Point"}
}