{
  "type": "Feature",
  "properties": {
    "addr:full":"10 Ellen St Bentleigh East VIC 3165",
    "addr:housenumber":"10",
    "addr:postcode":"3165",
    "addr:street":"Ellen St",
    "iso:country":"AU",
    "sg:address":"10 Ellen St",
    "sg:city":"Bentleigh East",
    "sg:classifiers":[
        {
            "category":"Shopping",
            "subcategory":"Musical Instruments",
            "type":"Retail Goods"
        }
    ],
    "sg:phone":"+61 3 9503 8483",
    "sg:postcode":"3165",
    "sg:province":"VIC",
    "sg:tags":[
        "musician",
        "agent"
    ],
    "wof:name":"Rhapsody String Quartet",
    "wof:placetype":"venue"
},
  "geometry": {"coordinates":[145.05294799800001,-37.9167785645],"type":"Point"}
}