{
  "type": "Feature",
  "properties": {
    "addr:full":"20 Separation St Mornington VIC 3931",
    "addr:housenumber":"20",
    "addr:postcode":"3931",
    "addr:street":"Separation St",
    "iso:country":"AU",
    "sg:address":"20 Separation St",
    "sg:city":"Mornington",
    "sg:classifiers":[
        {
            "category":"Health Services",
            "subcategory":"Health Practitioner",
            "type":"Services"
        }
    ],
    "sg:phone":"+61 418 402 839",
    "sg:postcode":"3931",
    "sg:province":"VIC",
    "sg:tags":[
        "pathologist",
        "speech"
    ],
    "wof:name":"Margot Lindsay Speech Pathology",
    "wof:placetype":"venue"
},
  "geometry": {"coordinates":[145.034713745,-38.2181396484],"type":"Point"}
}