{
  "type": "Feature",
  "properties": {
    "addr:full":"Level 1/ 264 Stephensons Rd Mt Waverley VIC 3149",
    "addr:housenumber":"/ 264",
    "addr:postcode":"3149",
    "addr:street":"Stephensons Rd",
    "iso:country":"AU",
    "sg:address":"Level 1/ 264 Stephensons Rd",
    "sg:city":"Mt Waverley",
    "sg:classifiers":[
        {
            "category":"Real Estate",
            "subcategory":"Real Estate Agent",
            "type":"Services"
        }
    ],
    "sg:phone":"+61 3 9830 8000",
    "sg:postcode":"3149",
    "sg:province":"VIC",
    "wof:name":"Ray White Mount Waverley",
    "wof:placetype":"venue"
},
  "geometry": {"coordinates":[145.12896728499999,-37.8769683838],"type":"Point"}
}