{
  "type": "Feature",
  "properties": {
    "addr:full":"15- 16 Lennox Cntr Emu Plains NSW 2750",
    "addr:housenumber":"16",
    "addr:postcode":"2750",
    "addr:street":"Lennox Cntr",
    "iso:country":"AU",
    "sg:address":"15- 16",
    "sg:city":"Lennox Cntr Emu Plains",
    "sg:classifiers":[
        {
            "category":"Shopping",
            "subcategory":"Beauty & Cosmetics",
            "type":"Retail Goods"
        }
    ],
    "sg:phone":"+61 2 4735 1303",
    "sg:postcode":"2750",
    "sg:province":"NSW",
    "wof:name":"M. Ibrahim",
    "wof:placetype":"venue"
},
  "geometry": {"coordinates":[150.65957641599999,-33.7534790039],"type":"Point"}
}