{
  "type": "Feature",
  "properties": {
    "iso:country":"AU",
    "sg:address":"28 Factory St",
    "sg:city":"Pittsworth",
    "sg:classifiers":[
        {
            "category":"Freight",
            "type":"Transportation"
        }
    ],
    "sg:phone":"+61 7 4693 1294",
    "sg:postcode":"4356",
    "sg:province":"QLD",
    "sg:tags":[
        "light",
        "carrier"
    ],
    "wof:name":"Pittsworth Express Carriers",
    "wof:placetype":"venue"
},
  "geometry": {"coordinates":[151.64291399999999,-27.715275],"type":"Point"}
}