{
  "type": "Feature",
  "properties": {
    "iso:country":"AU",
    "sg:address":"1128 Victoria Hwy",
    "sg:city":"Katherine",
    "sg:classifiers":[
        {
            "category":"Retail",
            "subcategory":"Auto Repair",
            "type":"Services"
        }
    ],
    "sg:phone":"+61 8 8972 1715",
    "sg:postcode":"0850",
    "sg:province":"NT",
    "sg:tags":[
        "bus",
        "truck"
    ],
    "wof:name":"Highway Motors",
    "wof:placetype":"venue"
},
  "geometry": {"coordinates":[132.26104699999999,-14.463711],"type":"Point"}
}