{
  "type": "Feature",
  "properties": {
    "addr:full":"12 Teatree Crt Warner QLD 4500",
    "addr:housenumber":"12",
    "addr:postcode":"4500",
    "addr:street":"Teatree Crt",
    "iso:country":"AU",
    "sg:address":"12 Teatree Crt",
    "sg:city":"Warner",
    "sg:classifiers":[
        {
            "category":"Professional",
            "subcategory":"Art Services",
            "type":"Services"
        }
    ],
    "sg:phone":"+61 7 3882 2624",
    "sg:postcode":"4500",
    "sg:province":"QLD",
    "sg:tags":[
        "picture",
        "frame",
        "framing"
    ],
    "wof:name":"Cutting Edge Framing",
    "wof:placetype":"venue"
},
  "geometry": {"coordinates":[152.94923400900001,-27.2926464081],"type":"Point"}
}