{
  "type": "Feature",
  "properties": {
    "addr:full":"Southgate Shpng Cntr, Cnr Port Hacking Rd & Prince Sylvania NSW 2224",
    "addr:postcode":"2224",
    "addr:street":"Cnr Port Hacking Rd & Prince",
    "iso:country":"AU",
    "sg:address":"Southgate Shpng Cntr, Cnr Port Hacking Rd & Prince",
    "sg:city":"Sylvania",
    "sg:classifiers":[
        {
            "category":"Shopping",
            "type":"Retail Goods"
        }
    ],
    "sg:phone":"+61 2 9544 9366",
    "sg:postcode":"2224",
    "sg:province":"NSW",
    "sg:tags":[
        "repair",
        "travel"
    ],
    "wof:name":"Strandbags Group Pty Limited",
    "wof:placetype":"venue"
},
  "geometry": {"coordinates":[151.10504150400001,-34.0103302002],"type":"Point"}
}