{
  "type": "Feature",
  "properties": {
    "addr:full":"9 franklin St Wakerley QLD 4154",
    "addr:housenumber":"9",
    "addr:postcode":"4154",
    "addr:street":"Franklin St",
    "iso:country":"AU",
    "sg:address":"9 franklin St",
    "sg:city":"Wakerley",
    "sg:classifiers":[
        {
            "category":"Real Estate",
            "subcategory":"Architect",
            "type":"Services"
        }
    ],
    "sg:phone":"+61 7 3348 9500",
    "sg:postcode":"4154",
    "sg:province":"QLD",
    "sg:tags":[
        "building",
        "designer"
    ],
    "wof:name":"Schuur Will Design & Construct",
    "wof:placetype":"venue"
},
  "geometry": {"coordinates":[153.15898132300001,-27.4806518555],"type":"Point"}
}