{
  "type": "Feature",
  "properties": {
    "iso:country":"AU",
    "sg:address":"44 Prince St",
    "sg:city":"Junee",
    "sg:classifiers":[
        {
            "category":"Building & Trades",
            "subcategory":"Construction",
            "type":"Services"
        }
    ],
    "sg:phone":"+61 418 630 436",
    "sg:postcode":"2663",
    "sg:province":"NSW",
    "sg:tags":[
        "renovation",
        "alterations",
        "extension",
        "contractor"
    ],
    "wof:name":"Gardner Stephen",
    "wof:placetype":"venue"
},
  "geometry": {"coordinates":[147.58013915999999,-34.8570632935],"type":"Point"}
}