{
  "type": "Feature",
  "properties": {
    "addr:full":"30 Paringa Rd Murarrie QLD 4172",
    "addr:housenumber":"30",
    "addr:postcode":"4172",
    "addr:street":"Paringa Rd",
    "iso:country":"AU",
    "sg:address":"30 Paringa Rd",
    "sg:city":"Murarrie",
    "sg:classifiers":[
        {
            "category":"Ferry",
            "type":"Transportation"
        }
    ],
    "sg:phone":"+61 7 3390 4729",
    "sg:postcode":"4172",
    "sg:province":"QLD",
    "sg:tags":[
        "barge"
    ],
    "wof:name":"Marine Contracting",
    "wof:placetype":"venue"
},
  "geometry": {"coordinates":[153.10821533199999,-27.4448738098],"type":"Point"}
}