{
  "type": "Feature",
  "properties": {
    "addr:full":"8 - 10 Birralee Rd Regency Park SA 5942",
    "addr:housenumber":"10",
    "addr:postcode":"5942",
    "addr:street":"8;Birralee Rd",
    "iso:country":"AU",
    "sg:address":"8 - 10 Birralee Rd",
    "sg:city":"Regency Park",
    "sg:classifiers":[
        {
            "category":"Retail",
            "subcategory":"Auto Repair",
            "type":"Services"
        }
    ],
    "sg:phone":"+61 8 8445 7798",
    "sg:postcode":"5942",
    "sg:province":"SA",
    "sg:tags":[
        "wheel",
        "balancing",
        "alignment"
    ],
    "wof:name":"Complete Laser Alignment Services",
    "wof:placetype":"venue"
},
  "geometry": {"coordinates":[138.5703125,-34.8574981689],"type":"Point"}
}