{
  "type": "Feature",
  "properties": {
    "addr:full":"7 Follett Rd Cheltenham VIC 3192",
    "addr:housenumber":"7",
    "addr:postcode":"3192",
    "addr:street":"Follett Rd",
    "iso:country":"AU",
    "sg:address":"7 Follett Rd",
    "sg:city":"Cheltenham",
    "sg:classifiers":[
        {
            "category":"Communications",
            "subcategory":"Film & Video Production",
            "type":"Services"
        }
    ],
    "sg:phone":"+61 3 9583 1276",
    "sg:postcode":"3192",
    "sg:province":"VIC",
    "sg:tags":[
        "dvd",
        "library"
    ],
    "wof:name":"Follett Road Videos",
    "wof:placetype":"venue"
},
  "geometry": {"coordinates":[145.068527222,-37.970539093],"type":"Point"}
}