{
  "type": "Feature",
  "properties": {
    "iso:country":"AU",
    "sg:address":"PO Box 3502",
    "sg:city":"South Brisbane",
    "sg:classifiers":[
        {
            "category":"Home & Garden",
            "subcategory":"Carpets & Floor Coverings",
            "type":"Retail Goods"
        }
    ],
    "sg:phone":"+61 7 3891 3502",
    "sg:postcode":"4101",
    "sg:province":"QLD",
    "sg:tags":[
        "club",
        "boat",
        "motor"
    ],
    "wof:name":"Brisbane Outboard Aquatic Touring Club Inc",
    "wof:placetype":"venue"
},
  "geometry": {"coordinates":[153.01502990700001,-27.4757900238],"type":"Point"}
}