{
  "type": "Feature",
  "properties": {
    "addr:full":"12 Liberty St Portsmith QLD 4870",
    "addr:housenumber":"12",
    "addr:postcode":"4870",
    "addr:street":"Liberty St Portsmith",
    "iso:country":"AU",
    "sg:address":"12 Liberty St",
    "sg:city":"Portsmith",
    "sg:classifiers":[
        {
            "category":"Food & Beverages",
            "subcategory":"Fruits & Vegetables",
            "type":"Retail Goods"
        }
    ],
    "sg:phone":"+61 7 4035 0400",
    "sg:postcode":"4870",
    "sg:province":"QLD",
    "sg:tags":[
        "wholesale"
    ],
    "wof:name":"Fresh Network The",
    "wof:placetype":"venue"
},
  "geometry": {"coordinates":[145.769363403,-16.9456443787],"type":"Point"}
}