{
  "type": "Feature",
  "properties": {
    "addr:full":"48 York Drv Flagstaff Hill SA 5159",
    "addr:housenumber":"48",
    "addr:postcode":"5159",
    "addr:street":"York Drv",
    "iso:country":"AU",
    "sg:address":"48 York Drv",
    "sg:city":"Flagstaff Hill",
    "sg:classifiers":[
        {
            "category":"Home & Garden",
            "subcategory":"Building Materials",
            "type":"Retail Goods"
        }
    ],
    "sg:phone":"+61 8 8370 7655",
    "sg:postcode":"5159",
    "sg:province":"SA",
    "sg:tags":[
        "lawn",
        "cutting",
        "maintenance"
    ],
    "wof:name":"City Garden & Household Services",
    "wof:placetype":"venue"
},
  "geometry": {"coordinates":[138.59370422399999,-35.0515708923],"type":"Point"}
}