{
  "type": "Feature",
  "properties": {
    "addr:full":"Shop 3 228-230 Main St Bairnsdale VIC 3875",
    "addr:housenumber":"shop 3 228-230",
    "addr:postcode":"3875",
    "addr:street":"Main St",
    "iso:country":"AU",
    "sg:address":"Shop 3 228-230 Main St",
    "sg:city":"Bairnsdale",
    "sg:classifiers":[
        {
            "category":"Communications",
            "subcategory":"Film & Video Production",
            "type":"Services"
        }
    ],
    "sg:phone":"+61 3 5152 6570",
    "sg:postcode":"3875",
    "sg:province":"VIC",
    "sg:tags":[
        "dvd",
        "library"
    ],
    "wof:name":"Video Ezy",
    "wof:placetype":"venue"
},
  "geometry": {"coordinates":[147.827224731,-37.7086296082],"type":"Point"}
}