{
  "type": "Feature",
  "properties": {
    "iso:country":"AU",
    "sg:address":"18 Wallace St",
    "sg:city":"Glenelg East",
    "sg:classifiers":[
        {
            "category":"Travel",
            "subcategory":"Travel Agent",
            "type":"Entertainment"
        }
    ],
    "sg:phone":"+61 8 8376 2525",
    "sg:postcode":"5045",
    "sg:province":"SA",
    "sg:tags":[
        "consultant"
    ],
    "wof:name":"CTMC- Corporate Travel Management Company",
    "wof:placetype":"venue"
},
  "geometry": {"coordinates":[138.524826,-34.981998],"type":"Point"}
}