{
  "type": "Feature",
  "properties": {
    "addr:full":"Lot 1450 Winnellie Rd Winnellie NT 0820",
    "addr:housenumber":"1450",
    "addr:postcode":"nt 0820",
    "addr:street":"Winnellie Rd",
    "iso:country":"AU",
    "sg:address":"Lot 1450 Winnellie Rd",
    "sg:city":"Winnellie",
    "sg:classifiers":[
        {
            "category":"Retail",
            "subcategory":"Storage",
            "type":"Services"
        }
    ],
    "sg:phone":"+61 1800 819 167",
    "sg:postcode":"0820",
    "sg:province":"NT",
    "sg:tags":[
        "removal",
        "furniture"
    ],
    "wof:name":"Toll Transitions",
    "wof:placetype":"venue"
},
  "geometry": {"coordinates":[130.89242553700001,-12.4266233444],"type":"Point"}
}