{
  "type": "Feature",
  "properties": {
    "iso:country":"AU",
    "sg:address":"5 Boyce Crt",
    "sg:city":"East Toowoomba",
    "sg:classifiers":[
        {
            "category":"Real Estate",
            "subcategory":"Real Estate Agent",
            "type":"Services"
        }
    ],
    "sg:phone":"+61 412 005 007",
    "sg:postcode":"4350",
    "sg:province":"QLD",
    "wof:name":"Murray & Associates Estate Agents",
    "wof:placetype":"venue"
},
  "geometry": {"coordinates":[151.976089,-27.560843],"type":"Point"}
}