{
  "type": "Feature",
  "properties": {
    "addr:full":"344- 348 Annangrove Rd Rouse Hill NSW 2155",
    "addr:housenumber":"348",
    "addr:postcode":"2155",
    "addr:street":"Annangrove Rd",
    "iso:country":"AU",
    "sg:address":"344- 348 Annangrove Rd",
    "sg:city":"Rouse Hill",
    "sg:classifiers":[
        {
            "category":"Building & Trades",
            "subcategory":"Construction",
            "type":"Services"
        }
    ],
    "sg:phone":"+61 2 8824 6650",
    "sg:postcode":"2155",
    "sg:province":"NSW",
    "sg:tags":[
        "installation",
        "air conditioning"
    ],
    "wof:name":"Arctic Air Conditioning",
    "wof:placetype":"venue"
},
  "geometry": {"coordinates":[150.91151428200001,-33.6743011475],"type":"Point"}
}