{
  "type": "Feature",
  "properties": {
    "addr:full":"11 Norfolk Ave Wagga Wagga NSW 2650",
    "addr:housenumber":"11",
    "addr:postcode":"2650",
    "addr:street":"Norfolk Ave",
    "iso:country":"AU",
    "sg:address":"11 Norfolk Ave",
    "sg:city":"Wagga Wagga",
    "sg:classifiers":[
        {
            "category":"Professional",
            "subcategory":"Business Services",
            "type":"Services"
        }
    ],
    "sg:phone":"+61 406 894 102",
    "sg:postcode":"2650",
    "sg:province":"NSW",
    "sg:tags":[
        "drafting"
    ],
    "wof:name":"D Reynolds Laugesen Design and Drafting",
    "wof:placetype":"venue"
},
  "geometry": {"coordinates":[147.37112426799999,-35.1575660706],"type":"Point"}
}