{
  "type": "Feature",
  "properties": {
    "iso:country":"AU",
    "sg:address":"285 Finns Rd",
    "sg:city":"Razorback",
    "sg:classifiers":[
        {
            "category":"Farming",
            "subcategory":"Poultry Farm",
            "type":"Manufacturing & Wholesale Goods"
        }
    ],
    "sg:phone":"+61 2 4636 6184",
    "sg:postcode":"2571",
    "sg:province":"NSW",
    "sg:tags":[
        "farmer"
    ],
    "wof:name":"Red Lea Pty Ltd",
    "wof:placetype":"venue"
},
  "geometry": {"coordinates":[150.70260620100001,-34.1283683777],"type":"Point"}
}