{
  "type": "Feature",
  "properties": {
    "addr:full":"47 Burwood Rd Concord NSW 2137",
    "addr:housenumber":"47",
    "addr:postcode":"2137",
    "addr:street":"Burwood Rd",
    "iso:country":"AU",
    "sg:address":"47 Burwood Rd",
    "sg:city":"Concord",
    "sg:classifiers":[
        {
            "category":"Health Services",
            "subcategory":"Doctor",
            "type":"Services"
        }
    ],
    "sg:phone":"+61 2 9744 2666",
    "sg:postcode":"2137",
    "sg:province":"NSW",
    "sg:tags":[
        "medical",
        "practitioner"
    ],
    "wof:name":"Stanford Ralph E",
    "wof:placetype":"venue"
},
  "geometry": {"coordinates":[151.106323242,-33.8655014038],"type":"Point"}
}