{
  "type": "Feature",
  "properties": {
    "addr:full":"Shop 3/ 1 Trussel St Kingaroy QLD 4610",
    "addr:housenumber":"shop 3 / 1",
    "addr:postcode":"4610",
    "addr:street":"Trussel St",
    "iso:country":"AU",
    "sg:address":"Shop 3/ 1 Trussel St",
    "sg:city":"Kingaroy",
    "sg:classifiers":[
        {
            "category":"Real Estate",
            "subcategory":"Architect",
            "type":"Services"
        }
    ],
    "sg:phone":"+61 438 635 582",
    "sg:postcode":"4610",
    "sg:province":"QLD",
    "sg:tags":[
        "building",
        "designer"
    ],
    "wof:name":"Blueprint Drafting Services",
    "wof:placetype":"venue"
},
  "geometry": {"coordinates":[151.84455871599999,-26.5531177521],"type":"Point"}
}