{
  "type": "Feature",
  "properties": {
    "addr:full":"Southwest Hwy Picton WA 6229",
    "addr:postcode":"6229",
    "addr:street":"Southwest Hwy",
    "iso:country":"AU",
    "sg:address":"Southwest Hwy",
    "sg:city":"Picton",
    "sg:classifiers":[
        {
            "category":"Manufacturing",
            "subcategory":"Tools & Machinery",
            "type":"Manufacturing & Wholesale Goods"
        }
    ],
    "sg:phone":"+61 8 9725 7111",
    "sg:postcode":"6229",
    "sg:province":"WA",
    "sg:tags":[
        "earth",
        "excavating",
        "moving",
        "equipment"
    ],
    "wof:name":"Komatsu",
    "wof:placetype":"venue"
},
  "geometry": {"coordinates":[115.70433800000001,-33.347912],"type":"Point"}
}