{
  "type": "Feature",
  "properties": {
    "addr:full":"93 Gilles St Adelaide SA 5000",
    "addr:housenumber":"93",
    "addr:postcode":"5000",
    "addr:street":"Gilles St",
    "iso:country":"AU",
    "sg:address":"93 Gilles St",
    "sg:city":"Adelaide",
    "sg:classifiers":[
        {
            "category":"Real Estate",
            "subcategory":"Architect",
            "type":"Services"
        }
    ],
    "sg:phone":"+61 8 8359 3194",
    "sg:postcode":"5000",
    "sg:province":"SA",
    "wof:name":"Arco Architecture & Interior Design",
    "wof:placetype":"venue"
},
  "geometry": {"coordinates":[138.60394287099999,-34.9342536926],"type":"Point"}
}