{
  "type": "Feature",
  "properties": {
    "addr:full":"86 Victoria St Grafton NSW 2460",
    "addr:housenumber":"86",
    "addr:postcode":"2460",
    "addr:street":"Victoria St",
    "iso:country":"AU",
    "sg:address":"86 Victoria St",
    "sg:city":"Grafton",
    "sg:classifiers":[
        {
            "category":"Real Estate",
            "subcategory":"Surveying",
            "type":"Services"
        }
    ],
    "sg:phone":"+61 2 6642 3300",
    "sg:postcode":"2460",
    "sg:province":"NSW",
    "sg:tags":[
        "surveyor",
        "land"
    ],
    "wof:name":"A Fletcher & Associates P/L",
    "wof:placetype":"venue"
},
  "geometry": {"coordinates":[152.93104553200001,-29.6910457611],"type":"Point"}
}