{
  "type": "Feature",
  "properties": {
    "iso:country":"AU",
    "sg:address":"Level 11, 313 Latrobe St",
    "sg:city":"Melbourne",
    "sg:classifiers":[
        {
            "category":"Personal",
            "subcategory":"Beauty Salon",
            "type":"Services"
        }
    ],
    "sg:phone":"+61 3 9642 8233",
    "sg:postcode":"3000",
    "sg:province":"VIC",
    "sg:tags":[
        "hair",
        "treatment",
        "replacement"
    ],
    "wof:name":"Clive Clinics",
    "wof:placetype":"venue"
},
  "geometry": {"coordinates":[144.96002197300001,-37.8108406067],"type":"Point"}
}