{
  "type": "Feature",
  "properties": {
    "iso:country":"AU",
    "sg:address":"Shp4/ 92 South Gippsland Hwy",
    "sg:city":"Tooradin",
    "sg:classifiers":[
        {
            "category":"Professional",
            "subcategory":"Testing Lab",
            "type":"Services"
        }
    ],
    "sg:phone":"+61 3 5998 3888",
    "sg:postcode":"3980",
    "sg:province":"VIC",
    "sg:tags":[
        "soil",
        "investigation"
    ],
    "wof:name":"Geocore Pty Ltd",
    "wof:placetype":"venue"
},
  "geometry": {"coordinates":[145.38052368199999,-38.2137794495],"type":"Point"}
}