{
  "type": "Feature",
  "properties": {
    "addr:full":"96b Elder St Lambton NSW 2299",
    "addr:housenumber":"96b",
    "addr:postcode":"2299",
    "addr:street":"Elder St",
    "iso:country":"AU",
    "sg:address":"96b Elder St",
    "sg:city":"Lambton",
    "sg:classifiers":[
        {
            "category":"Fast Food",
            "type":"Food & Drink"
        }
    ],
    "sg:phone":"+61 2 4952 3755",
    "sg:postcode":"2299",
    "sg:province":"NSW",
    "sg:tags":[
        "away",
        "take"
    ],
    "wof:name":"Marlin's Takeaway",
    "wof:placetype":"venue"
},
  "geometry": {"coordinates":[151.70851135300001,-32.9114341736],"type":"Point"}
}