{
  "type": "Feature",
  "properties": {
    "iso:country":"AU",
    "sg:address":"649 Plenty Rd",
    "sg:city":"Preston",
    "sg:classifiers":[
        {
            "category":"Personal",
            "subcategory":"Beauty Salon",
            "type":"Services"
        }
    ],
    "sg:phone":"+61 3 9478 1203",
    "sg:postcode":"3072",
    "sg:province":"VIC",
    "sg:tags":[
        "supply",
        "artist",
        "make-up"
    ],
    "wof:name":"Saphire Makeup & Hair Studio",
    "wof:placetype":"venue"
},
  "geometry": {"coordinates":[145.10252380399999,-37.7291107178],"type":"Point"}
}