{
  "type": "Feature",
  "properties": {
    "addr:full":"6 Wimbledon Crt Wattle Grove NSW 2173",
    "addr:housenumber":"6",
    "addr:postcode":"2173",
    "addr:street":"Wimbledon Crt",
    "iso:country":"AU",
    "sg:address":"6 Wimbledon Crt",
    "sg:city":"Wattle Grove",
    "sg:classifiers":[
        {
            "category":"Retail",
            "subcategory":"Repair Shop",
            "type":"Services"
        }
    ],
    "sg:phone":"+61 416 252 355",
    "sg:postcode":"2173",
    "sg:province":"NSW",
    "sg:tags":[
        "machine",
        "repairs",
        "part",
        "dryer",
        "washing"
    ],
    "wof:name":"M C Washing & Appliance Service",
    "wof:placetype":"venue"
},
  "geometry": {"coordinates":[150.94303894000001,-33.9621162415],"type":"Point"}
}