{
  "type": "Feature",
  "properties": {
    "iso:country":"AU",
    "sg:address":"29 Grattan St",
    "sg:city":"Carlton",
    "sg:classifiers":[
        {
            "category":"Retail",
            "subcategory":"Event Space",
            "type":"Services"
        }
    ],
    "sg:phone":"+61 3 9663 6906",
    "sg:postcode":"3053",
    "sg:province":"VIC",
    "sg:tags":[
        "function",
        "organiser"
    ],
    "wof:name":"La Cacciatore Restaurant",
    "wof:placetype":"venue"
},
  "geometry": {"coordinates":[144.968505859,-37.8010215759],"type":"Point"}
}