{
  "type": "Feature",
  "properties": {
    "iso:country":"AU",
    "sg:address":"45 Chambers Rd",
    "sg:city":"Altona North",
    "sg:classifiers":[
        {
            "category":"Autos & Motor Vehicles",
            "subcategory":"Recreational Vehicle Sales",
            "type":"Retail Goods"
        }
    ],
    "sg:phone":"+61 3 9391 4011",
    "sg:postcode":"3025",
    "sg:province":"VIC",
    "sg:tags":[
        "ducting",
        "ductwork"
    ],
    "wof:name":"Plasticoat",
    "wof:placetype":"venue"
},
  "geometry": {"coordinates":[144.841736,-37.839241],"type":"Point"}
}