{
  "type": "Feature",
  "properties": {
    "iso:country":"AU",
    "sg:address":"263 Liverpool Rd",
    "sg:city":"Ashfield",
    "sg:classifiers":[
        {
            "category":"Shopping",
            "subcategory":"Jewelry",
            "type":"Retail Goods"
        }
    ],
    "sg:phone":"+61 2 9798 7139",
    "sg:postcode":"2131",
    "sg:province":"NSW",
    "sg:tags":[
        "jeweller"
    ],
    "wof:name":"Europa Jewellers",
    "wof:placetype":"venue"
},
  "geometry": {"coordinates":[151.124832153,-33.8885993958],"type":"Point"}
}