{
  "type": "Feature",
  "properties": {
    "addr:full":"42 Macquarie St Parramatta NSW 2124",
    "addr:housenumber":"42",
    "addr:postcode":"2124",
    "addr:street":"Macquarie St",
    "iso:country":"AU",
    "sg:address":"42 Macquarie St",
    "sg:city":"Parramatta",
    "sg:classifiers":[
        {
            "category":"Shopping",
            "subcategory":"Clothing, Apparel, & Fashions",
            "type":"Retail Goods"
        }
    ],
    "sg:phone":"+61 2 9635 5111",
    "sg:postcode":"2124",
    "sg:province":"NSW",
    "sg:tags":[
        "uniform"
    ],
    "wof:name":"NNT Uniforms",
    "wof:placetype":"venue"
},
  "geometry": {"coordinates":[150.942337036,-33.8705024719],"type":"Point"}
}