{
  "type": "Feature",
  "properties": {
    "addr:full":"957 Mill Rd Hamilton VIC 3300",
    "addr:housenumber":"957",
    "addr:postcode":"3300",
    "addr:street":"Mill Rd",
    "iso:country":"AU",
    "sg:address":"957 Mill Rd",
    "sg:city":"Hamilton",
    "sg:classifiers":[
        {
            "category":"Government",
            "subcategory":"Post Office",
            "type":"Public Place"
        }
    ],
    "sg:phone":"+61 3 5573 3303",
    "sg:postcode":"3300",
    "sg:province":"VIC",
    "sg:tags":[
        "yoga"
    ],
    "wof:name":"Arthur Stevens",
    "wof:placetype":"venue"
},
  "geometry": {"coordinates":[142.040115356,-37.7314300537],"type":"Point"}
}