{
  "type": "Feature",
  "properties": {
    "addr:full":"33 Bunker St Minchinbury NSW 2770",
    "addr:housenumber":"33",
    "addr:postcode":"2770",
    "addr:street":"Bunker St",
    "iso:country":"AU",
    "sg:address":"33 Bunker St",
    "sg:city":"Minchinbury",
    "sg:classifiers":[
        {
            "category":"Building & Trades",
            "subcategory":"Construction",
            "type":"Services"
        }
    ],
    "sg:phone":"+61 2 9625 9339",
    "sg:postcode":"2770",
    "sg:province":"NSW",
    "sg:tags":[
        "renovation",
        "alterations",
        "extension",
        "contractor"
    ],
    "wof:name":"Allpex Building Renovations",
    "wof:placetype":"venue"
},
  "geometry": {"coordinates":[150.828521728,-33.7878646851],"type":"Point"}
}