{
  "type": "Feature",
  "properties": {
    "addr:full":"15 Graham Hill Rd Narellan NSW 2567",
    "addr:housenumber":"15",
    "addr:postcode":"2567",
    "addr:street":"Graham Hill Rd",
    "iso:country":"AU",
    "sg:address":"15 Graham Hill Rd",
    "sg:city":"Narellan",
    "sg:classifiers":[
        {
            "category":"Home & Garden",
            "subcategory":"Building Materials",
            "type":"Retail Goods"
        }
    ],
    "sg:phone":"+61 2 4646 1761",
    "sg:postcode":"2567",
    "sg:province":"NSW",
    "sg:tags":[
        "merchant",
        "glass",
        "glazier"
    ],
    "wof:name":"Camden Glass Service",
    "wof:placetype":"venue"
},
  "geometry": {"coordinates":[150.72996520999999,-34.038230896],"type":"Point"}
}