{
  "type": "Feature",
  "properties": {
    "addr:full":"PO Box 633 Sylvania Waters NSW 2224",
    "addr:postcode":"2224",
    "iso:country":"AU",
    "sg:address":"PO Box 633",
    "sg:city":"Sylvania Waters",
    "sg:classifiers":[
        {
            "category":"Professional",
            "subcategory":"Art Services",
            "type":"Services"
        }
    ],
    "sg:phone":"+61 2 9544 7820",
    "sg:postcode":"2224",
    "sg:province":"NSW",
    "sg:tags":[
        "graphic",
        "designer"
    ],
    "wof:name":"Cracked Up Business Cards",
    "wof:placetype":"venue"
},
  "geometry": {"coordinates":[151.10899352999999,-34.0229415894],"type":"Point"}
}