{
  "type": "Feature",
  "properties": {
    "addr:full":"32 Highway Ave West Wollongong NSW 2500",
    "addr:housenumber":"32",
    "addr:postcode":"2500",
    "addr:street":"Highway Ave West",
    "iso:country":"AU",
    "sg:address":"32 Highway Ave",
    "sg:city":"West Wollongong",
    "sg:classifiers":[
        {
            "category":"Education",
            "subcategory":"Kindergarten",
            "type":"Public Place"
        }
    ],
    "sg:phone":"+61 2 4226 1525",
    "sg:postcode":"2500",
    "sg:province":"NSW",
    "sg:tags":[
        "pre-schools"
    ],
    "wof:name":"West Wollongong Pre-School Kindergarten",
    "wof:placetype":"venue"
},
  "geometry": {"coordinates":[150.86811800000001,-34.427105],"type":"Point"}
}