{
  "type": "Feature",
  "properties": {
    "addr:full":"456 Hunter St Newcastle NSW 2300",
    "addr:housenumber":"456",
    "addr:postcode":"2300",
    "addr:street":"Hunter St",
    "iso:country":"AU",
    "sg:address":"456 Hunter St",
    "sg:city":"Newcastle",
    "sg:classifiers":[
        {
            "category":"Shopping",
            "subcategory":"Mobile Phones",
            "type":"Retail Goods"
        }
    ],
    "sg:phone":"+61 2 4929 2111",
    "sg:postcode":"2300",
    "sg:province":"NSW",
    "sg:tags":[
        "telephone",
        "accessory"
    ],
    "wof:name":"In Touch Digital Communications",
    "wof:placetype":"venue"
},
  "geometry": {"coordinates":[151.770905,-32.926968],"type":"Point"}
}