{
  "type": "Feature",
  "properties": {
    "addr:full":"U2/ 116 McCredie Rd Guildford NSW 2161",
    "addr:housenumber":"116",
    "addr:postcode":"2161",
    "addr:street":"U2 /;Mccredie Rd",
    "iso:country":"AU",
    "sg:address":"U2/ 116 McCredie Rd",
    "sg:city":"Guildford",
    "sg:classifiers":[
        {
            "category":"Wholesale",
            "subcategory":"Home Furnishings",
            "type":"Manufacturing & Wholesale Goods"
        }
    ],
    "sg:phone":"+61 2 9632 8031",
    "sg:postcode":"2161",
    "sg:province":"NSW",
    "sg:tags":[
        "wholesaler",
        "bedding",
        "mfrs",
        "bed"
    ],
    "wof:name":"Quality Bedding Co Pty Ltd",
    "wof:placetype":"venue"
},
  "geometry": {"coordinates":[150.960479736,-33.8503189087],"type":"Point"}
}