{
  "type": "Feature",
  "properties": {
    "addr:full":"10 Otaki Pl St Ives NSW 2075",
    "addr:housenumber":"10",
    "addr:postcode":"2075",
    "addr:street":"Pl",
    "iso:country":"AU",
    "sg:address":"10 Otaki Pl",
    "sg:city":"St Ives",
    "sg:classifiers":[
        {
            "category":"Professional",
            "subcategory":"Computer Services",
            "type":"Services"
        }
    ],
    "sg:phone":"+61 2 9440 1135",
    "sg:postcode":"2075",
    "sg:province":"NSW",
    "sg:tags":[
        "consultant",
        "system"
    ],
    "wof:name":"Data-Team Pty Ltd",
    "wof:placetype":"venue"
},
  "geometry": {"coordinates":[151.15750122099999,-33.7085456848],"type":"Point"}
}