{
  "type": "Feature",
  "properties": {
    "addr:full":"Challenge Stadium Stephenson Ave Mt Claremont WA 6010",
    "addr:postcode":"6010",
    "addr:street":"Stephenson Ave",
    "iso:country":"AU",
    "sg:address":"Challenge Stadium Stephenson Ave",
    "sg:city":"Mt Claremont",
    "sg:classifiers":[
        {
            "category":"Health Services",
            "subcategory":"Doctor",
            "type":"Services"
        }
    ],
    "sg:phone":"+61 8 9387 2699",
    "sg:postcode":"6010",
    "sg:province":"WA",
    "sg:tags":[
        "podiatrist"
    ],
    "wof:name":"Egitto Fabio",
    "wof:placetype":"venue"
},
  "geometry": {"coordinates":[115.774559021,-31.9586219788],"type":"Point"}
}