{
  "type": "Feature",
  "properties": {
    "addr:full":"54 Mandurah Tce Mandurah WA 6210",
    "addr:housenumber":"54",
    "addr:postcode":"6210",
    "addr:street":"Mandurah Tce",
    "iso:country":"AU",
    "sg:address":"54 Mandurah Tce",
    "sg:city":"Mandurah",
    "sg:classifiers":[
        {
            "category":"Real Estate",
            "subcategory":"Real Estate Agent",
            "type":"Services"
        }
    ],
    "sg:phone":"+61 8 9535 1822",
    "sg:postcode":"6210",
    "sg:province":"WA",
    "sg:website":"http://www.hnperry.com.au",
    "wof:name":"H & N Perry",
    "wof:placetype":"venue"
},
  "geometry": {"coordinates":[115.720253,-32.531059],"type":"Point"}
}