{
  "type": "Feature",
  "properties": {
    "addr:full":"19 Jennings St Kyneton VIC 3444",
    "addr:housenumber":"19",
    "addr:postcode":"3444",
    "addr:street":"Jennings St",
    "iso:country":"AU",
    "sg:address":"19 Jennings St",
    "sg:city":"Kyneton",
    "sg:classifiers":[
        {
            "category":"Health Services",
            "subcategory":"Doctor",
            "type":"Services"
        }
    ],
    "sg:phone":"+61 3 5422 1412",
    "sg:postcode":"3444",
    "sg:province":"VIC",
    "sg:tags":[
        "medical",
        "practitioner"
    ],
    "wof:name":"Coliban Medical Centre",
    "wof:placetype":"venue"
},
  "geometry": {"coordinates":[144.45112609899999,-37.2478065491],"type":"Point"}
}