{
  "type": "Feature",
  "properties": {
    "addr:full":"Historical Building Molong St Condobolin NSW 2877",
    "addr:postcode":"2877",
    "addr:street":"Molong St",
    "iso:country":"AU",
    "sg:address":"Historical Building Molong St",
    "sg:city":"Condobolin",
    "sg:classifiers":[
        {
            "category":"Social Services",
            "subcategory":"Child Care",
            "type":"Services"
        }
    ],
    "sg:phone":"+61 2 6895 4606",
    "sg:postcode":"2877",
    "sg:province":"NSW",
    "wof:name":"Lachlan Family Day Care After School Care",
    "wof:placetype":"venue"
},
  "geometry": {"coordinates":[147.14596599999999,-33.084064],"type":"Point"}
}