{
  "type": "Feature",
  "properties": {
    "addr:full":"&#034;Wongabeena Park&#034; Mount Mercer Rd Meredith VIC 3333",
    "addr:postcode":"3333",
    "addr:street":"Mount Mercer Rd",
    "iso:country":"AU",
    "sg:address":"&#034;Wongabeena Park&#034; Mount Mercer Rd",
    "sg:city":"Meredith",
    "sg:classifiers":[
        {
            "category":"Professional",
            "type":"Services"
        }
    ],
    "sg:phone":"+61 3 5286 1346",
    "sg:postcode":"3333",
    "sg:province":"VIC",
    "sg:tags":[
        "transport"
    ],
    "wof:name":"A R J Transport",
    "wof:placetype":"venue"
},
  "geometry": {"coordinates":[144.076095581,-37.8419494629],"type":"Point"}
}