{
  "type": "Feature",
  "properties": {
    "addr:full":"99 Stuart St Bulimba QLD 4171",
    "addr:housenumber":"99",
    "addr:postcode":"4171",
    "addr:street":"Stuart St",
    "iso:country":"AU",
    "sg:address":"99 Stuart St",
    "sg:city":"Bulimba",
    "sg:classifiers":[
        {
            "category":"Autos & Motor Vehicles",
            "subcategory":"Boat Sales",
            "type":"Retail Goods"
        }
    ],
    "sg:phone":"+61 7 3899 2433",
    "sg:postcode":"4171",
    "sg:province":"QLD",
    "sg:tags":[
        "builder",
        "yacht",
        "repairer"
    ],
    "wof:name":"Brisbane Ship Constructions Pty Ltd",
    "wof:placetype":"venue"
},
  "geometry": {"coordinates":[153.0574646,-27.4551734924],"type":"Point"}
}