{
  "type": "Feature",
  "properties": {
    "iso:country":"AU",
    "sg:address":"51 McIntyre Rd",
    "sg:city":"Sunshine",
    "sg:classifiers":[
        {
            "category":"Shopping",
            "subcategory":"Stationery & Office Supplies",
            "type":"Retail Goods"
        }
    ],
    "sg:phone":"+61 3 9313 4555",
    "sg:postcode":"3020",
    "sg:province":"VIC",
    "sg:tags":[
        "equipment",
        "coating",
        "powder"
    ],
    "wof:name":"Akzo Nobel Pty Ltd",
    "wof:placetype":"venue"
},
  "geometry": {"coordinates":[144.829803,-37.770302],"type":"Point"}
}