{
  "type": "Feature",
  "properties": {
    "addr:full":"119 Pittwater Rd Manly NSW 2095",
    "addr:housenumber":"119",
    "addr:postcode":"2095",
    "addr:street":"Pittwater Rd",
    "iso:country":"AU",
    "sg:address":"119 Pittwater Rd",
    "sg:city":"Manly",
    "sg:classifiers":[
        {
            "category":"Professional",
            "subcategory":"Computer Services",
            "type":"Services"
        }
    ],
    "sg:phone":"+61 2 9977 6733",
    "sg:postcode":"2095",
    "sg:province":"NSW",
    "sg:tags":[
        "repairs",
        "upgrade",
        "equipment"
    ],
    "wof:name":"Manly Computronics",
    "wof:placetype":"venue"
},
  "geometry": {"coordinates":[151.28500366200001,-33.7908630371],"type":"Point"}
}