{
  "type": "Feature",
  "properties": {
    "iso:country":"AU",
    "sg:address":"Rifle Range Rd",
    "sg:city":"Innisfail",
    "sg:classifiers":[
        {
            "category":"Farming",
            "subcategory":"Farm",
            "type":"Manufacturing & Wholesale Goods"
        }
    ],
    "sg:phone":"+61 7 4061 2235",
    "sg:postcode":"4860",
    "sg:province":"QLD",
    "sg:tags":[
        "farmer"
    ],
    "wof:name":"Louis L H",
    "wof:placetype":"venue"
},
  "geometry": {"coordinates":[146.040557861,-17.5511817932],"type":"Point"}
}