{
  "type": "Feature",
  "properties": {
    "iso:country":"AU",
    "sg:address":"66 b East Esplanade St",
    "sg:city":"Albans",
    "sg:classifiers":[
        {
            "category":"Organizations",
            "subcategory":"Professional Association",
            "type":"Services"
        }
    ],
    "sg:phone":"+61 431 316 301",
    "sg:postcode":"3021",
    "sg:province":"VIC",
    "sg:tags":[
        "web",
        "internet"
    ],
    "wof:name":"Systems & Paradigms Consulting",
    "wof:placetype":"venue"
},
  "geometry": {"coordinates":[144.799637,-37.743694],"type":"Point"}
}