{
  "type": "Feature",
  "properties": {
    "iso:country":"AU",
    "sg:address":"53B King St",
    "sg:city":"Newtown",
    "sg:classifiers":[
        {
            "category":"Personal",
            "subcategory":"Beauty Salon",
            "type":"Services"
        }
    ],
    "sg:phone":"+61 2 9565 4777",
    "sg:postcode":"2042",
    "sg:province":"NSW",
    "wof:name":"Dolce Vita Beaute",
    "wof:placetype":"venue"
},
  "geometry": {"coordinates":[151.186249,-33.892487],"type":"Point"}
}