{
  "type": "Feature",
  "properties": {
    "iso:country":"AU",
    "sg:address":"U6/ 10b Charles St",
    "sg:city":"Canterbury",
    "sg:classifiers":[
        {
            "category":"Retail",
            "subcategory":"Repair Shop",
            "type":"Services"
        }
    ],
    "sg:phone":"+61 2 9787 1717",
    "sg:postcode":"2193",
    "sg:province":"NSW",
    "sg:tags":[
        "upholsterer"
    ],
    "wof:name":"Home Upholstery",
    "wof:placetype":"venue"
},
  "geometry": {"coordinates":[151.11634799999999,-33.911182],"type":"Point"}
}