{
  "type": "Feature",
  "properties": {
    "addr:full":"131a Margate Pde Margate QLD 4019",
    "addr:housenumber":"131a",
    "addr:postcode":"4019",
    "addr:street":"Margate Pde",
    "iso:country":"AU",
    "sg:address":"131a Margate Pde",
    "sg:city":"Margate",
    "sg:classifiers":[
        {
            "category":"Real Estate",
            "subcategory":"Real Estate Agent",
            "type":"Services"
        }
    ],
    "sg:phone":"+61 7 3283 4344",
    "sg:postcode":"4019",
    "sg:province":"QLD",
    "wof:name":"Hermans Real Estate",
    "wof:placetype":"venue"
},
  "geometry": {"coordinates":[153.112792969,-27.240776062],"type":"Point"}
}