{
  "type": "Feature",
  "properties": {
    "addr:full":"Shop 4/ 693 Ann St Fortitude Valley QLD 4006",
    "addr:housenumber":"shop 4 / 693",
    "addr:postcode":"4006",
    "addr:street":"Ann St",
    "iso:country":"AU",
    "sg:address":"Shop 4/ 693 Ann St",
    "sg:city":"Fortitude Valley",
    "sg:classifiers":[
        {
            "category":"Shopping",
            "subcategory":"Clothing, Apparel, & Fashions",
            "type":"Retail Goods"
        }
    ],
    "sg:phone":"+61 7 3666 0708",
    "sg:postcode":"4006",
    "sg:province":"QLD",
    "sg:tags":[
        "lingerie",
        "hosiery",
        "sleepwear"
    ],
    "wof:name":"Puritan",
    "wof:placetype":"venue"
},
  "geometry": {"coordinates":[153.035552978,-27.4581260681],"type":"Point"}
}