{
  "type": "Feature",
  "properties": {
    "addr:full":"253 Bronte St Waverley NSW 2024",
    "addr:housenumber":"253",
    "addr:postcode":"2024",
    "addr:street":"Bronte St",
    "iso:country":"AU",
    "sg:address":"253 Bronte St",
    "sg:city":"Waverley",
    "sg:classifiers":[
        {
            "category":"Shopping",
            "subcategory":"Clothing, Apparel, & Fashions",
            "type":"Retail Goods"
        }
    ],
    "sg:phone":"+61 2 9387 7088",
    "sg:postcode":"2024",
    "sg:province":"NSW",
    "sg:tags":[
        "recycled",
        "clothing"
    ],
    "wof:name":"St Vincent De Paul Society",
    "wof:placetype":"venue"
},
  "geometry": {"coordinates":[151.25416564899999,-33.9016036987],"type":"Point"}
}