{
  "type": "Feature",
  "properties": {
    "iso:country":"AU",
    "sg:address":"160 Captain Cook Drv",
    "sg:city":"Barrack Heights",
    "sg:classifiers":[
        {
            "category":"Home & Garden",
            "subcategory":"Carpets & Floor Coverings",
            "type":"Retail Goods"
        }
    ],
    "sg:phone":"+61 405 147 164",
    "sg:postcode":"2528",
    "sg:province":"NSW",
    "sg:tags":[
        "tile",
        "wall"
    ],
    "wof:name":"South Coast Tiling & Waterproofing Pty Ltd",
    "wof:placetype":"venue"
},
  "geometry": {"coordinates":[150.847732544,-34.5592079163],"type":"Point"}
}