{
  "type": "Feature",
  "properties": {
    "iso:country":"AU",
    "sg:address":"Unit 10/ 40 Brisbane Ave",
    "sg:city":"Barton",
    "sg:classifiers":[
        {
            "category":"Organizations",
            "subcategory":"Labor Organization",
            "type":"Services"
        }
    ],
    "sg:phone":"+61 2 6120 1500",
    "sg:postcode":"2600",
    "sg:province":"ACT",
    "sg:tags":[
        "union"
    ],
    "wof:name":"Independent Education Union (NSW/ACT)",
    "wof:placetype":"venue"
},
  "geometry": {"coordinates":[149.13250732399999,-35.3086776733],"type":"Point"}
}