{
  "type": "Feature",
  "properties": {
    "addr:full":"480 Bourke St Melbourne VIC 3000",
    "addr:housenumber":"480",
    "addr:postcode":"3000",
    "addr:street":"Bourke St",
    "iso:country":"AU",
    "sg:address":"480 Bourke St",
    "sg:city":"Melbourne",
    "sg:classifiers":[
        {
            "category":"Fast Food",
            "type":"Food & Drink"
        }
    ],
    "sg:phone":"+61 3 9670 2640",
    "sg:postcode":"3000",
    "sg:province":"VIC",
    "sg:tags":[
        "away",
        "take"
    ],
    "wof:name":"CBD Catering",
    "wof:placetype":"venue"
},
  "geometry": {"coordinates":[144.959472656,-37.8151893616],"type":"Point"}
}