{
  "type": "Feature",
  "properties": {
    "addr:full":"30 Victoria St Bairnsdale VIC 3875",
    "addr:housenumber":"30",
    "addr:postcode":"3875",
    "addr:street":"Victoria St",
    "iso:country":"AU",
    "sg:address":"30 Victoria St",
    "sg:city":"Bairnsdale",
    "sg:classifiers":[
        {
            "category":"Retail",
            "subcategory":"Funeral Services",
            "type":"Services"
        }
    ],
    "sg:phone":"+61 3 5152 4596",
    "sg:postcode":"3875",
    "sg:province":"VIC",
    "sg:tags":[
        "director"
    ],
    "wof:name":"Tom Dooley Funeral Services",
    "wof:placetype":"venue"
},
  "geometry": {"coordinates":[147.60850524899999,-37.8301124573],"type":"Point"}
}