{
  "type": "Feature",
  "properties": {
    "addr:full":"390 Peel St Tamworth NSW 2340",
    "addr:housenumber":"390",
    "addr:postcode":"2340",
    "addr:street":"Peel St",
    "iso:country":"AU",
    "sg:address":"390 Peel St",
    "sg:city":"Tamworth",
    "sg:classifiers":[
        {
            "category":"Restaurant",
            "type":"Food & Drink"
        }
    ],
    "sg:phone":"+61 2 6766 3993",
    "sg:postcode":"2340",
    "sg:province":"NSW",
    "wof:name":"Cafe Vivaldi",
    "wof:placetype":"venue"
},
  "geometry": {"coordinates":[150.93066406200001,-31.0912837982],"type":"Point"}
}