{
  "type": "Feature",
  "properties": {
    "addr:full":"Lorne Rd Birregurra VIC 3242",
    "addr:postcode":"3242",
    "addr:street":"Lorne Rd",
    "iso:country":"AU",
    "sg:address":"Lorne Rd",
    "sg:city":"Birregurra",
    "sg:classifiers":[
        {
            "category":"Shopping",
            "type":"Retail Goods"
        }
    ],
    "sg:phone":"+61 3 5236 2003",
    "sg:postcode":"3242",
    "sg:province":"VIC",
    "sg:tags":[
        "agent",
        "stock"
    ],
    "wof:name":"Whelan B P",
    "wof:placetype":"venue"
},
  "geometry": {"coordinates":[143.83558654800001,-38.3435096741],"type":"Point"}
}