{
  "type": "Feature",
  "properties": {
    "iso:country":"AU",
    "sg:address":"1 Ellesmere St",
    "sg:city":"Oakleigh South",
    "sg:classifiers":[
        {
            "category":"Professional",
            "subcategory":"Employment Agencies",
            "type":"Services"
        }
    ],
    "sg:phone":"+61 3 8503 7337",
    "sg:postcode":"3167",
    "sg:province":"VIC",
    "wof:name":"Emerel Agency",
    "wof:placetype":"venue"
},
  "geometry": {"coordinates":[145.08401489299999,-37.9360198975],"type":"Point"}
}