{
  "type": "Feature",
  "properties": {
    "addr:full":"St Brendan&#039;s School Hawtree St Moorooka QLD 4105",
    "addr:postcode":"4105",
    "addr:street":"St;S;Hawtree St",
    "iso:country":"AU",
    "sg:address":"St Brendan&#039;s School Hawtree St",
    "sg:city":"Moorooka",
    "sg:classifiers":[
        {
            "category":"Organizations",
            "subcategory":"Non-profit Organization",
            "type":"Services"
        }
    ],
    "sg:phone":"+61 7 3277 3587",
    "sg:postcode":"4105",
    "sg:province":"QLD",
    "sg:tags":[
        "support",
        "disability",
        "organisation"
    ],
    "wof:name":"Early Intervention Centre & Visiting Teachers Service",
    "wof:placetype":"venue"
},
  "geometry": {"coordinates":[153.019332886,-27.5378284454],"type":"Point"}
}