{
  "type": "Feature",
  "properties": {
    "addr:full":"Lot 51 Campbell St Cobar NSW 2835",
    "addr:housenumber":"51",
    "addr:postcode":"2835",
    "addr:street":"Campbell St",
    "iso:country":"AU",
    "sg:address":"Lot 51 Campbell St",
    "sg:city":"Cobar",
    "sg:classifiers":[
        {
            "category":"Freight",
            "type":"Transportation"
        }
    ],
    "sg:phone":"+61 2 6836 3611",
    "sg:postcode":"2835",
    "sg:province":"NSW",
    "sg:tags":[
        "light",
        "carrier"
    ],
    "wof:name":"Mackenzies Transport",
    "wof:placetype":"venue"
},
  "geometry": {"coordinates":[145.84793099999999,-31.497892],"type":"Point"}
}