{
  "type": "Feature",
  "properties": {
    "iso:country":"AU",
    "sg:address":"394 Darling St",
    "sg:city":"Balmain",
    "sg:classifiers":[
        {
            "category":"Health Services",
            "subcategory":"Dentist",
            "type":"Services"
        }
    ],
    "sg:phone":"+61 2 9818 1379",
    "sg:postcode":"2041",
    "sg:province":"NSW",
    "wof:name":"Kadi George P & Kadi Rita",
    "wof:placetype":"venue"
},
  "geometry": {"coordinates":[151.175308,-33.856068],"type":"Point"}
}