{
  "type": "Feature",
  "properties": {
    "iso:country":"AU",
    "sg:address":"Shop 12/ 4 Dutton Rd",
    "sg:city":"Mt Barker",
    "sg:classifiers":[
        {
            "category":"Shopping",
            "subcategory":"Crafts & Fabrics",
            "type":"Retail Goods"
        }
    ],
    "sg:phone":"+61 8 8398 4777",
    "sg:postcode":"5251",
    "sg:province":"SA",
    "sg:tags":[
        "quilting"
    ],
    "wof:name":"Discount Curtains & Lace",
    "wof:placetype":"venue"
},
  "geometry": {"coordinates":[138.867263794,-35.0655479431],"type":"Point"}
}