{
  "type": "Feature",
  "properties": {
    "iso:country":"AU",
    "sg:address":"Unit 23 429 The Boulevarde",
    "sg:city":"Kirrawee",
    "sg:classifiers":[
        {
            "category":"Manufacturing",
            "subcategory":"Apparel",
            "type":"Manufacturing & Wholesale Goods"
        }
    ],
    "sg:phone":"+61 2 9545 1331",
    "sg:postcode":"2232",
    "sg:province":"NSW",
    "sg:tags":[
        "makers-up",
        "clothing"
    ],
    "wof:name":"Clark J & M",
    "wof:placetype":"venue"
},
  "geometry": {"coordinates":[151.07110595699999,-34.0342292786],"type":"Point"}
}