{
  "type": "Feature",
  "properties": {
    "addr:full":"Wongabirrie Rd Crystal Brook SA 5523",
    "addr:postcode":"5523",
    "addr:street":"Wongabirrie Rd",
    "iso:country":"AU",
    "sg:address":"Wongabirrie Rd",
    "sg:city":"Crystal Brook",
    "sg:classifiers":[
        {
            "category":"Wholesale",
            "subcategory":"Machinery & Supplies",
            "type":"Manufacturing & Wholesale Goods"
        }
    ],
    "sg:phone":"+61 8 8636 2772",
    "sg:postcode":"5523",
    "sg:province":"SA",
    "sg:tags":[
        "agricultural"
    ],
    "wof:name":"Rocky River AG Services",
    "wof:placetype":"venue"
},
  "geometry": {"coordinates":[138.20855712900001,-33.3609313965],"type":"Point"}
}