{
  "type": "Feature",
  "properties": {
    "addr:full":"360 Wanneroo Rd Wangara WA 6065",
    "addr:housenumber":"360",
    "addr:postcode":"6065",
    "addr:street":"Wanneroo Rd",
    "iso:country":"AU",
    "sg:address":"360 Wanneroo Rd",
    "sg:city":"Wangara",
    "sg:classifiers":[
        {
            "category":"Home & Garden",
            "subcategory":"Garden Supply",
            "type":"Retail Goods"
        }
    ],
    "sg:phone":"+61 8 9309 2288",
    "sg:postcode":"6065",
    "sg:province":"WA",
    "sg:tags":[
        "landscape"
    ],
    "wof:name":"Noranda Hills Nursery",
    "wof:placetype":"venue"
},
  "geometry": {"coordinates":[115.818023682,-31.801815033],"type":"Point"}
}