{
  "type": "Feature",
  "properties": {
    "iso:country":"AU",
    "sg:address":"4 Tripod Pl",
    "sg:city":"Mullaloo",
    "sg:classifiers":[
        {
            "category":"Building & Trades",
            "subcategory":"Cleaning & Sanitation",
            "type":"Services"
        }
    ],
    "sg:phone":"+61 8 9307 9260",
    "sg:postcode":"6027",
    "sg:province":"WA",
    "sg:tags":[
        "cleaner",
        "repairer",
        "roof"
    ],
    "wof:name":"Ward Roofing",
    "wof:placetype":"venue"
},
  "geometry": {"coordinates":[115.75074768099999,-31.7744998932],"type":"Point"}
}