{
  "type": "Feature",
  "properties": {
    "addr:full":"Shop 2, 26 Channel Hwy Kingston TAS 7050",
    "addr:housenumber":"shop;26",
    "addr:postcode":"7050",
    "addr:street":"Channel Hwy",
    "iso:country":"AU",
    "sg:address":"Shop 2, 26 Channel Hwy",
    "sg:city":"Kingston",
    "sg:classifiers":[
        {
            "category":"Banks & Credit Unions",
            "subcategory":"Financial Services",
            "type":"Services"
        }
    ],
    "sg:phone":"+61 3 6229 8933",
    "sg:postcode":"7050",
    "sg:province":"TAS",
    "sg:tags":[
        "loan",
        "finance",
        "mortgage"
    ],
    "wof:name":"Wizard",
    "wof:placetype":"venue"
},
  "geometry": {"coordinates":[147.310822,-42.975227],"type":"Point"}
}