{
  "type": "Feature",
  "properties": {
    "addr:full":"67 Forest Rd Hurstville NSW 2220",
    "addr:housenumber":"67",
    "addr:postcode":"2220",
    "addr:street":"Forest Rd",
    "iso:country":"AU",
    "sg:address":"67 Forest Rd",
    "sg:city":"Hurstville",
    "sg:classifiers":[
        {
            "category":"Retail",
            "subcategory":"Auto Repair",
            "type":"Services"
        }
    ],
    "sg:phone":"+61 2 9588 4466",
    "sg:postcode":"2220",
    "sg:province":"NSW",
    "sg:tags":[
        "repairer",
        "motor",
        "engineer"
    ],
    "wof:name":"Superb 1 Mechanical Repairs",
    "wof:placetype":"venue"
},
  "geometry": {"coordinates":[151.10418701200001,-33.9677124023],"type":"Point"}
}