{
  "type": "Feature",
  "properties": {
    "addr:full":"PO Box 84 Crafers SA 5152",
    "addr:postcode":"5152",
    "iso:country":"AU",
    "sg:address":"PO Box 84",
    "sg:city":"Crafers",
    "sg:classifiers":[
        {
            "category":"Professional",
            "subcategory":"Management & Consulting",
            "type":"Services"
        }
    ],
    "sg:phone":"+61 8 8370 8270",
    "sg:postcode":"5152",
    "sg:province":"SA",
    "sg:tags":[
        "consultant"
    ],
    "wof:name":"Home Truths Work Myths",
    "wof:placetype":"venue"
},
  "geometry": {"coordinates":[138.70338439899999,-34.9972000122],"type":"Point"}
}