{
  "type": "Feature",
  "properties": {
    "addr:full":"34 King St Bayswater WA 6053",
    "addr:housenumber":"34",
    "addr:postcode":"6053",
    "addr:street":"King St",
    "iso:country":"AU",
    "sg:address":"34 King St",
    "sg:city":"Bayswater",
    "sg:classifiers":[
        {
            "category":"Autos & Motor Vehicles",
            "subcategory":"Boat Sales",
            "type":"Retail Goods"
        }
    ],
    "sg:phone":"+61 8 9271 5015",
    "sg:postcode":"6053",
    "sg:province":"WA",
    "sg:tags":[
        "builder",
        "yacht",
        "repairer"
    ],
    "wof:name":"Glasscraft Boats",
    "wof:placetype":"venue"
},
  "geometry": {"coordinates":[115.919662476,-31.908613205],"type":"Point"}
}