{
  "type": "Feature",
  "properties": {
    "iso:country":"AU",
    "sg:address":"25 Morayfield Rd",
    "sg:city":"Caboolture",
    "sg:classifiers":[
        {
            "category":"Health Services",
            "subcategory":"Doctor",
            "type":"Services"
        }
    ],
    "sg:phone":"+61 7 5499 3224",
    "sg:postcode":"4510",
    "sg:province":"QLD",
    "sg:tags":[
        "medical",
        "practitioner"
    ],
    "wof:name":"Marshall Philip",
    "wof:placetype":"venue"
},
  "geometry": {"coordinates":[152.950134,-27.092611],"type":"Point"}
}