{
  "type": "Feature",
  "properties": {
    "addr:full":"79 Foxglove St Mt Gravatt QLD 4122",
    "addr:housenumber":"79",
    "addr:postcode":"4122",
    "addr:street":"Foxglove St",
    "iso:country":"AU",
    "sg:address":"79 Foxglove St",
    "sg:city":"Mt Gravatt",
    "sg:classifiers":[
        {
            "category":"Health Services",
            "subcategory":"Nursing And Care Facility",
            "type":"Services"
        }
    ],
    "sg:phone":"+61 7 3343 1222",
    "sg:postcode":"4122",
    "sg:province":"QLD",
    "sg:tags":[
        "home"
    ],
    "wof:name":"Carindale Court",
    "wof:placetype":"venue"
},
  "geometry": {"coordinates":[153.090286255,-27.5285453796],"type":"Point"}
}