{
  "type": "Feature",
  "properties": {
    "addr:full":"55 - 61 Tinning St Brunswick VIC 3056",
    "addr:housenumber":"61",
    "addr:postcode":"3056",
    "addr:street":"Tinning St",
    "iso:country":"AU",
    "sg:address":"55 - 61 Tinning St",
    "sg:city":"Brunswick",
    "sg:classifiers":[
        {
            "category":"Manufacturing",
            "subcategory":"Tools & Machinery",
            "type":"Manufacturing & Wholesale Goods"
        }
    ],
    "sg:phone":"+61 3 9383 3488",
    "sg:postcode":"3056",
    "sg:province":"VIC",
    "sg:tags":[
        "wholesaler",
        "mfrs",
        "hosiery"
    ],
    "wof:name":"Winsome Hosiery",
    "wof:placetype":"venue"
},
  "geometry": {"coordinates":[144.959442139,-37.7592506409],"type":"Point"}
}