{
  "type": "Feature",
  "properties": {
    "addr:full":"Cnr Hurricane & Weyba Sts Nudgee QLD 4014",
    "addr:postcode":"4014",
    "iso:country":"AU",
    "sg:address":"Cnr Hurricane & Weyba Sts",
    "sg:city":"Nudgee",
    "sg:classifiers":[
        {
            "category":"Wholesale",
            "subcategory":"Metals & Minerals",
            "type":"Manufacturing & Wholesale Goods"
        }
    ],
    "sg:phone":"+61 7 3267 8588",
    "sg:postcode":"4014",
    "sg:province":"QLD",
    "sg:tags":[
        "steel",
        "stainless",
        "product",
        "equipment"
    ],
    "wof:name":"Superior Sheetmetal Pty. Ltd.",
    "wof:placetype":"venue"
},
  "geometry": {"coordinates":[153.08880615199999,-27.3869571686],"type":"Point"}
}