{
  "type": "Feature",
  "properties": {
    "addr:full":"PO Box 778 Cannonvale QLD 4802",
    "addr:postcode":"4802",
    "iso:country":"AU",
    "sg:address":"PO Box 778",
    "sg:city":"Cannonvale",
    "sg:classifiers":[
        {
            "category":"Professional",
            "subcategory":"Accounting & Tax Preparation",
            "type":"Services"
        }
    ],
    "sg:phone":"+61 7 4948 3114",
    "sg:postcode":"4802",
    "sg:province":"QLD",
    "sg:tags":[
        "bookkeeping"
    ],
    "wof:name":"Smart Biz Bookkeeping",
    "wof:placetype":"venue"
},
  "geometry": {"coordinates":[148.69070434599999,-20.280090332],"type":"Point"}
}