{
  "type": "Feature",
  "properties": {
    "addr:full":"17 Longboat Pl Biggera Waters QLD 4216",
    "addr:housenumber":"17",
    "addr:postcode":"4216",
    "addr:street":"Longboat Pl",
    "iso:country":"AU",
    "sg:address":"17 Longboat Pl",
    "sg:city":"Biggera Waters",
    "sg:classifiers":[
        {
            "category":"Building & Trades",
            "subcategory":"Landscaping Services",
            "type":"Services"
        }
    ],
    "sg:phone":"+61 7 5537 3522",
    "sg:postcode":"4216",
    "sg:province":"QLD",
    "sg:tags":[
        "consultant"
    ],
    "wof:name":"Moor Derek V",
    "wof:placetype":"venue"
},
  "geometry": {"coordinates":[153.393432617,-27.930103302],"type":"Point"}
}