{
  "type": "Feature",
  "properties": {
    "iso:country":"AU",
    "sg:address":"Locn 2214 Great Eastern Hwy",
    "sg:city":"Cunderdin",
    "sg:classifiers":[
        {
            "category":"Professional",
            "subcategory":"Computer Services",
            "type":"Services"
        }
    ],
    "sg:phone":"+61 8 9635 1500",
    "sg:postcode":"6407",
    "sg:province":"WA",
    "sg:tags":[
        "consultant",
        "system"
    ],
    "wof:name":"Canci Consulting Services Pty Ltd",
    "wof:placetype":"venue"
},
  "geometry": {"coordinates":[117.22286987299999,-31.6518554688],"type":"Point"}
}