{
  "type": "Feature",
  "properties": {
    "addr:full":"96 Parramatta Rd Granville NSW 2142",
    "addr:housenumber":"96",
    "addr:postcode":"2142",
    "addr:street":"Parramatta Rd",
    "iso:country":"AU",
    "sg:address":"96 Parramatta Rd",
    "sg:city":"Granville",
    "sg:classifiers":[
        {
            "category":"Autos & Motor Vehicles",
            "subcategory":"Automobile Sales",
            "type":"Retail Goods"
        }
    ],
    "sg:phone":"+61 2 9682 6388",
    "sg:postcode":"2142",
    "sg:province":"NSW",
    "sg:tags":[
        "car",
        "used"
    ],
    "wof:name":"Anthony Lahood Motors Commodore Specialists",
    "wof:placetype":"venue"
},
  "geometry": {"coordinates":[151.01411438,-33.8315658569],"type":"Point"}
}