{
  "type": "Feature",
  "properties": {
    "iso:country":"AU",
    "sg:address":"Bldg 8, Lot 3 Olive Gr",
    "sg:city":"Keysborough",
    "sg:classifiers":[
        {
            "category":"Manufacturing",
            "subcategory":"Motor Vehicles & Parts",
            "type":"Manufacturing & Wholesale Goods"
        }
    ],
    "sg:phone":"+61 429 052 381",
    "sg:postcode":"3173",
    "sg:province":"VIC",
    "sg:tags":[
        "die",
        "casting"
    ],
    "wof:name":"Global Die-Casting Engineers Pty Ltd",
    "wof:placetype":"venue"
},
  "geometry": {"coordinates":[145.181549072,-37.9990081787],"type":"Point"}
}