{
  "type": "Feature",
  "properties": {
    "addr:full":"40 Bodall St Fairfield Heights NSW 2165",
    "addr:housenumber":"40",
    "addr:postcode":"2165",
    "addr:street":"Bodall St",
    "iso:country":"AU",
    "sg:address":"40 Bodall St",
    "sg:city":"Fairfield Heights",
    "sg:classifiers":[
        {
            "category":"Building & Trades",
            "subcategory":"Cleaning & Sanitation",
            "type":"Services"
        }
    ],
    "sg:phone":"+61 2 9729 0103",
    "sg:postcode":"2165",
    "sg:province":"NSW",
    "sg:tags":[
        "industrial",
        "commercial",
        "contractor"
    ],
    "wof:name":"Golden Mops",
    "wof:placetype":"venue"
},
  "geometry": {"coordinates":[150.934646606,-33.862285614],"type":"Point"}
}