{
  "type": "Feature",
  "properties": {
    "iso:country":"AU",
    "sg:address":"11 Adnunda Pl",
    "sg:city":"Beaumont",
    "sg:classifiers":[
        {
            "category":"Wholesale",
            "subcategory":"Home Furnishings",
            "type":"Manufacturing & Wholesale Goods"
        }
    ],
    "sg:phone":"+61 8 8338 3233",
    "sg:postcode":"5066",
    "sg:province":"SA",
    "sg:tags":[
        "wholesaler",
        "mfrs",
        "kitchenware"
    ],
    "wof:name":"Urban Sales & Marketing S.A.",
    "wof:placetype":"venue"
},
  "geometry": {"coordinates":[138.655395508,-34.9454650879],"type":"Point"}
}