{
  "type": "Feature",
  "properties": {
    "addr:full":"505 Raglan Pde Warrnambool VIC 3280",
    "addr:housenumber":"505",
    "addr:postcode":"3280",
    "addr:street":"Raglan Pde",
    "iso:country":"AU",
    "sg:address":"505 Raglan Pde",
    "sg:city":"Warrnambool",
    "sg:classifiers":[
        {
            "category":"Shopping",
            "type":"Retail Goods"
        }
    ],
    "sg:phone":"+61 3 5562 4022",
    "sg:postcode":"3280",
    "sg:province":"VIC",
    "sg:tags":[
        "agent",
        "stock"
    ],
    "wof:name":"Saffin Kerr Bowen Stewart Wilson Pty Ltd",
    "wof:placetype":"venue"
},
  "geometry": {"coordinates":[142.48854064899999,-38.382270813],"type":"Point"}
}