{
  "type": "Feature",
  "properties": {
    "iso:country":"AU",
    "sg:address":"10 Lyall St",
    "sg:city":"Cowra",
    "sg:classifiers":[
        {
            "category":"Building & Trades",
            "subcategory":"Construction",
            "type":"Services"
        }
    ],
    "sg:phone":"+61 419 488 670",
    "sg:postcode":"2794",
    "sg:province":"NSW",
    "sg:tags":[
        "earth",
        "excavating",
        "moving",
        "contractor"
    ],
    "wof:name":"Alan Jones Excavations",
    "wof:placetype":"venue"
},
  "geometry": {"coordinates":[148.67759704599999,-33.8397521973],"type":"Point"}
}