{
  "type": "Feature",
  "properties": {
    "addr:full":"1118 Lady Barron Rd Flinders Island TAS 7255",
    "addr:housenumber":"1118",
    "addr:postcode":"7255",
    "addr:street":"Lady Barron Rd",
    "iso:country":"AU",
    "sg:address":"1118 Lady Barron Rd",
    "sg:city":"Flinders Island",
    "sg:classifiers":[
        {
            "category":"Travel",
            "subcategory":"Travel Agent",
            "type":"Entertainment"
        }
    ],
    "sg:phone":"+61 3 6359 4507",
    "sg:postcode":"7255",
    "sg:province":"TAS",
    "sg:tags":[
        "tour",
        "holiday",
        "adventure"
    ],
    "wof:name":"Flinders Island Adventures",
    "wof:placetype":"venue"
},
  "geometry": {"coordinates":[148.02650451700001,-40.1192169189],"type":"Point"}
}