{
  "type": "Feature",
  "properties": {
    "iso:country":"AU",
    "sg:address":"PO Box 251",
    "sg:city":"Toodyay",
    "sg:classifiers":[
        {
            "category":"Professional",
            "subcategory":"Business Services",
            "type":"Services"
        }
    ],
    "sg:phone":"+61 8 9574 5506",
    "sg:postcode":"6566",
    "sg:province":"WA",
    "sg:tags":[
        "broker"
    ],
    "wof:name":"Fernhurst Realty",
    "wof:placetype":"venue"
},
  "geometry": {"coordinates":[116.4795,-31.56991],"type":"Point"}
}