{
  "type": "Feature",
  "properties": {
    "addr:full":"1258 Gold Coast Hwy Palm Beach QLD 4221",
    "addr:housenumber":"1258",
    "addr:postcode":"4221",
    "addr:street":"Gold Coast Hwy",
    "iso:country":"AU",
    "sg:address":"1258 Gold Coast Hwy",
    "sg:city":"Palm Beach",
    "sg:classifiers":[
        {
            "category":"Health Services",
            "subcategory":"Health Practitioner",
            "type":"Services"
        }
    ],
    "sg:phone":"+61 7 5576 6469",
    "sg:postcode":"4221",
    "sg:province":"QLD",
    "sg:tags":[
        "naturopath"
    ],
    "wof:name":"Geoff Hale",
    "wof:placetype":"venue"
},
  "geometry": {"coordinates":[153.46864318900001,-28.1146202087],"type":"Point"}
}