{
  "type": "Feature",
  "properties": {
    "iso:country":"AU",
    "sg:address":"3rd Floor, Unit 7 66 Albert Rd",
    "sg:city":"South Melbourne",
    "sg:classifiers":[
        {
            "category":"Professional",
            "subcategory":"Accounting & Tax Preparation",
            "type":"Services"
        }
    ],
    "sg:phone":"+61 2 9699 5277",
    "sg:postcode":"3205",
    "sg:province":"VIC",
    "sg:tags":[
        "accountant",
        "auditor"
    ],
    "wof:name":"McLennan Partners Pty Ltd",
    "wof:placetype":"venue"
},
  "geometry": {"coordinates":[144.97108499999999,-37.834663],"type":"Point"}
}