{
  "type": "Feature",
  "properties": {
    "iso:country":"AU",
    "sg:address":"8 Oban St",
    "sg:city":"Frankston",
    "sg:classifiers":[
        {
            "category":"Building & Trades",
            "subcategory":"Landscaping Services",
            "type":"Services"
        }
    ],
    "sg:phone":"+61 3 9783 5455",
    "sg:postcode":"3199",
    "sg:province":"VIC",
    "sg:tags":[
        "designer",
        "landscape",
        "contractor"
    ],
    "wof:name":"McCormick Landscaping & Paving",
    "wof:placetype":"venue"
},
  "geometry": {"coordinates":[145.002716064,-37.8441963196],"type":"Point"}
}