{
  "type": "Feature",
  "properties": {
    "iso:country":"AU",
    "sg:address":"31 Amaroo Pl",
    "sg:city":"Duncraig",
    "sg:classifiers":[
        {
            "category":"Building & Trades",
            "subcategory":"Plumbing",
            "type":"Services"
        }
    ],
    "sg:phone":"+61 418 927 907",
    "sg:postcode":"6023",
    "sg:province":"WA",
    "sg:tags":[
        "plumber",
        "gasfitters"
    ],
    "wof:name":"Glengarry Plumbing",
    "wof:placetype":"venue"
},
  "geometry": {"coordinates":[115.76789856000001,-31.8391418457],"type":"Point"}
}