{
  "type": "Feature",
  "properties": {
    "iso:country":"AU",
    "sg:address":"11 Cross St",
    "sg:city":"Bankstown",
    "sg:classifiers":[
        {
            "category":"Retail",
            "subcategory":"Event Space",
            "type":"Services"
        }
    ],
    "sg:phone":"+61 2 9708 2233",
    "sg:postcode":"2200",
    "sg:province":"NSW",
    "sg:tags":[
        "venue",
        "reception",
        "wedding"
    ],
    "wof:name":"Maxims Wedding Reception",
    "wof:placetype":"venue"
},
  "geometry": {"coordinates":[151.038071,-33.921021],"type":"Point"}
}