{
  "type": "Feature",
  "properties": {
    "iso:country":"AU",
    "sg:address":"1 West Cct",
    "sg:city":"Sunshine West",
    "sg:classifiers":[
        {
            "category":"Communications",
            "subcategory":"Television Station",
            "type":"Services"
        }
    ],
    "sg:phone":"+61 3 9312 2220",
    "sg:postcode":"3020",
    "sg:province":"VIC",
    "sg:tags":[
        "equipment",
        "laser"
    ],
    "sg:website":"http://www.imts.com.au",
    "wof:name":"IMTS Laser Specialists",
    "wof:placetype":"venue"
},
  "geometry": {"coordinates":[144.818756,-37.794312],"type":"Point"}
}