{
  "type": "Feature",
  "properties": {
    "addr:full":"1015 Cureton Ave Irymple VIC 3498",
    "addr:housenumber":"1015",
    "addr:postcode":"3498",
    "addr:street":"Cureton Ave",
    "iso:country":"AU",
    "sg:address":"1015 Cureton Ave",
    "sg:city":"Irymple",
    "sg:classifiers":[
        {
            "category":"Autos & Motor Vehicles",
            "subcategory":"Fuel & Gas Station",
            "type":"Retail Goods"
        }
    ],
    "sg:phone":"+61 3 5024 5545",
    "sg:postcode":"3498",
    "sg:province":"VIC",
    "sg:tags":[
        "injection",
        "diesel"
    ],
    "wof:name":"B. & K. Diesel Service",
    "wof:placetype":"venue"
},
  "geometry": {"coordinates":[142.17286682100001,-34.2372512817],"type":"Point"}
}