{
  "type": "Feature",
  "properties": {
    "iso:country":"AU",
    "sg:address":"Suite 5 16 Moreau Mews",
    "sg:city":"Applecross",
    "sg:classifiers":[
        {
            "category":"Real Estate",
            "subcategory":"Real Estate Services",
            "type":"Services"
        }
    ],
    "sg:phone":"+61 8 9316 8533",
    "sg:postcode":"6153",
    "sg:province":"WA",
    "sg:tags":[
        "consultant",
        "property"
    ],
    "wof:name":"Landlords Advisory Service",
    "wof:placetype":"venue"
},
  "geometry": {"coordinates":[115.84880099999999,-32.011234],"type":"Point"}
}