{
  "type": "Feature",
  "properties": {
    "addr:full":"48 Hovell St Wodonga VIC 3690",
    "addr:housenumber":"48",
    "addr:postcode":"3690",
    "addr:street":"Hovell St",
    "iso:country":"AU",
    "sg:address":"48 Hovell St",
    "sg:city":"Wodonga",
    "sg:classifiers":[
        {
            "category":"Wholesale",
            "subcategory":"Machinery & Supplies",
            "type":"Manufacturing & Wholesale Goods"
        }
    ],
    "sg:phone":"+61 2 6056 2144",
    "sg:postcode":"3690",
    "sg:province":"VIC",
    "sg:tags":[
        "agricultural"
    ],
    "wof:name":"Jappo Donks",
    "wof:placetype":"venue"
},
  "geometry": {"coordinates":[146.89390564000001,-36.1165390015],"type":"Point"}
}