{
  "type": "Feature",
  "properties": {
    "addr:full":"1- 9 Kurnall Rd Welshpool WA 6106",
    "addr:housenumber":"9",
    "addr:postcode":"6106",
    "addr:street":"Kurnall Rd",
    "iso:country":"AU",
    "sg:address":"1- 9 Kurnall Rd",
    "sg:city":"Welshpool",
    "sg:classifiers":[
        {
            "category":"Transit Center",
            "subcategory":"Freight",
            "type":"Transportation"
        }
    ],
    "sg:phone":"+61 8 9352 9200",
    "sg:postcode":"6106",
    "sg:province":"WA",
    "sg:tags":[
        "forklift",
        "truck"
    ],
    "wof:name":"Adapt-A-Lift Forklift Rentals & Sales",
    "wof:placetype":"venue"
},
  "geometry": {"coordinates":[115.95516204800001,-31.9953804016],"type":"Point"}
}