{
  "type": "Feature",
  "properties": {
    "addr:full":"51 Beerwah Pde Beerwah QLD 4519",
    "addr:housenumber":"51",
    "addr:postcode":"4519",
    "addr:street":"Beerwah Pde",
    "iso:country":"AU",
    "sg:address":"51 Beerwah Pde",
    "sg:city":"Beerwah",
    "sg:classifiers":[
        {
            "category":"Manufacturing",
            "subcategory":"Retail Goods",
            "type":"Manufacturing & Wholesale Goods"
        }
    ],
    "sg:phone":"+61 7 5494 6166",
    "sg:postcode":"4519",
    "sg:province":"QLD",
    "sg:tags":[
        "merchant",
        "pump",
        "mfrs"
    ],
    "wof:name":"Pump House The",
    "wof:placetype":"venue"
},
  "geometry": {"coordinates":[152.959091,-26.858221],"type":"Point"}
}