{
  "type": "Feature",
  "properties": {
    "addr:full":"735 Pascoe Vale Rd Glenroy VIC 3046",
    "addr:housenumber":"735",
    "addr:postcode":"3046",
    "addr:street":"Pascoe Vale Rd",
    "iso:country":"AU",
    "sg:address":"735 Pascoe Vale Rd",
    "sg:city":"Glenroy",
    "sg:classifiers":[
        {
            "category":"Health Services",
            "subcategory":"Health Practitioner",
            "type":"Services"
        }
    ],
    "sg:phone":"+61 3 9844 4428",
    "sg:postcode":"3046",
    "sg:province":"VIC",
    "sg:tags":[
        "psychologist"
    ],
    "wof:name":"Deeley Stephanie",
    "wof:placetype":"venue"
},
  "geometry": {"coordinates":[144.916137695,-37.7069244385],"type":"Point"}
}