{
  "type": "Feature",
  "properties": {
    "iso:country":"AU",
    "sg:address":"511 North East Rd",
    "sg:city":"Gilles Plains",
    "sg:classifiers":[
        {
            "category":"Manufacturing",
            "subcategory":"Paper Products",
            "type":"Manufacturing & Wholesale Goods"
        }
    ],
    "sg:phone":"+61 8 8369 2711",
    "sg:postcode":"5086",
    "sg:province":"SA",
    "sg:tags":[
        "machine",
        "shredding",
        "cutting"
    ],
    "wof:name":"Copyfax Stationers",
    "wof:placetype":"venue"
},
  "geometry": {"coordinates":[138.658081055,-34.8555793762],"type":"Point"}
}