{
  "type": "Feature",
  "properties": {
    "addr:full":"50 St Pauls Tce Spring Hill QLD 4000",
    "addr:housenumber":"50",
    "addr:postcode":"4000",
    "addr:street":"St Pauls Tce",
    "iso:country":"AU",
    "sg:address":"50 St Pauls Tce",
    "sg:city":"Spring Hill",
    "sg:classifiers":[
        {
            "category":"Fast Food",
            "type":"Food & Drink"
        }
    ],
    "sg:phone":"+61 7 3839 3867",
    "sg:postcode":"4000",
    "sg:province":"QLD",
    "sg:tags":[
        "away",
        "take"
    ],
    "wof:name":"Spring Hill Fine Foods",
    "wof:placetype":"venue"
},
  "geometry": {"coordinates":[153.02755737300001,-27.4599437714],"type":"Point"}
}