{
  "type": "Feature",
  "properties": {
    "addr:full":"274 Bay St Brighton North VIC 3186",
    "addr:housenumber":"274",
    "addr:postcode":"3186",
    "addr:street":"Bay St",
    "iso:country":"AU",
    "sg:address":"274 Bay St",
    "sg:city":"Brighton North",
    "sg:classifiers":[
        {
            "category":"Health Services",
            "subcategory":"Doctor",
            "type":"Services"
        }
    ],
    "sg:phone":"+61 433 273 352",
    "sg:postcode":"3186",
    "sg:province":"VIC",
    "sg:tags":[
        "medical",
        "practitioner"
    ],
    "wof:name":"McNeilly Robert",
    "wof:placetype":"venue"
},
  "geometry": {"coordinates":[145.001022339,-37.9054260254],"type":"Point"}
}