{
  "type": "Feature",
  "properties": {
    "addr:full":"6 Hann St Fulham Gardens SA 5024",
    "addr:housenumber":"6",
    "addr:postcode":"5024",
    "addr:street":"Hann St",
    "iso:country":"AU",
    "sg:address":"6 Hann St",
    "sg:city":"Fulham Gardens",
    "sg:classifiers":[
        {
            "category":"Utilities",
            "subcategory":"Electric",
            "type":"Services"
        }
    ],
    "sg:phone":"+61 419 810 130",
    "sg:postcode":"5024",
    "sg:province":"SA",
    "sg:tags":[
        "electrical",
        "contractor"
    ],
    "wof:name":"Tip Top Electrical Service",
    "wof:placetype":"venue"
},
  "geometry": {"coordinates":[138.51658630399999,-34.9118614197],"type":"Point"}
}