{
  "type": "Feature",
  "properties": {
    "iso:country":"AU",
    "sg:address":"99 Uralba St",
    "sg:city":"Lismore",
    "sg:classifiers":[
        {
            "category":"Health Services",
            "subcategory":"Doctor",
            "type":"Services"
        }
    ],
    "sg:phone":"+61 2 6621 4465",
    "sg:postcode":"2480",
    "sg:province":"NSW",
    "sg:tags":[
        "medical",
        "practitioner"
    ],
    "wof:name":"Laird P P Dr",
    "wof:placetype":"venue"
},
  "geometry": {"coordinates":[153.29444885300001,-28.8091888428],"type":"Point"}
}