{
  "type": "Feature",
  "properties": {
    "iso:country":"AU",
    "sg:address":"602 Smith St",
    "sg:city":"Clifton Hill",
    "sg:classifiers":[
        {
            "category":"Government",
            "subcategory":"Department Of Motor Vehicles",
            "type":"Public Place"
        }
    ],
    "sg:phone":"+61 417 892 963",
    "sg:postcode":"3068",
    "sg:province":"VIC",
    "sg:tags":[
        "wholesaler",
        "mfrs",
        "accessory"
    ],
    "wof:name":"H.O.",
    "wof:placetype":"venue"
},
  "geometry": {"coordinates":[144.985397339,-37.7933158875],"type":"Point"}
}