{
  "type": "Feature",
  "properties": {
    "iso:country":"AU",
    "sg:address":"28- 32 Trigg St",
    "sg:city":"Geraldton",
    "sg:classifiers":[
        {
            "category":"Travel",
            "subcategory":"Hotels & Motels",
            "type":"Entertainment"
        }
    ],
    "sg:phone":"+61 427 099 847",
    "sg:postcode":"6530",
    "sg:province":"WA",
    "wof:name":"Geraldton Accommodation Providers",
    "wof:placetype":"venue"
},
  "geometry": {"coordinates":[114.622901916,-28.752117157],"type":"Point"}
}