{
  "type": "Feature",
  "properties": {
    "addr:full":"156 Belmore Rd Riverwood NSW 2210",
    "addr:housenumber":"156",
    "addr:postcode":"2210",
    "addr:street":"Belmore Rd",
    "iso:country":"AU",
    "sg:address":"156 Belmore Rd",
    "sg:city":"Riverwood",
    "sg:classifiers":[
        {
            "category":"Shopping",
            "subcategory":"Clothing, Apparel, & Fashions",
            "type":"Retail Goods"
        }
    ],
    "sg:phone":"+61 2 9533 4192",
    "sg:postcode":"2210",
    "sg:province":"NSW",
    "sg:tags":[
        "recycled",
        "clothing"
    ],
    "wof:name":"St Vincent De Paul Society",
    "wof:placetype":"venue"
},
  "geometry": {"coordinates":[151.05174299999999,-33.954025],"type":"Point"}
}