{
  "type": "Feature",
  "properties": {
    "addr:full":"28 Leach Ave Riverton WA 6148",
    "addr:housenumber":"28",
    "addr:postcode":"6148",
    "addr:street":"Leach Ave",
    "iso:country":"AU",
    "sg:address":"28 Leach Ave",
    "sg:city":"Riverton",
    "sg:classifiers":[
        {
            "category":"Utilities",
            "subcategory":"Refuse",
            "type":"Services"
        }
    ],
    "sg:phone":"+61 8 9354 4245",
    "sg:postcode":"6148",
    "sg:province":"WA",
    "sg:tags":[
        "remover",
        "rubbish"
    ],
    "wof:name":"Chris Wade",
    "wof:placetype":"venue"
},
  "geometry": {"coordinates":[115.8965,-32.037132],"type":"Point"}
}