{
  "type": "Feature",
  "properties": {
    "addr:full":"61 Cuthbert Rd Reservoir VIC 3073",
    "addr:housenumber":"61",
    "addr:postcode":"3073",
    "addr:street":"Cuthbert Rd",
    "iso:country":"AU",
    "sg:address":"61 Cuthbert Rd",
    "sg:city":"Reservoir",
    "sg:classifiers":[
        {
            "category":"Professional",
            "subcategory":"Art Services",
            "type":"Services"
        }
    ],
    "sg:phone":"+61 412 777 115",
    "sg:postcode":"3073",
    "sg:province":"VIC",
    "sg:tags":[
        "decorator",
        "painter"
    ],
    "wof:name":"Kingsway Painting",
    "wof:placetype":"venue"
},
  "geometry": {"coordinates":[145.01483154300001,-37.716709137],"type":"Point"}
}