{
  "type": "Feature",
  "properties": {
    "addr:full":"2 Faussett St Albert Park VIC 3206",
    "addr:housenumber":"2",
    "addr:postcode":"3206",
    "addr:street":"Faussett St",
    "iso:country":"AU",
    "sg:address":"2 Faussett St",
    "sg:city":"Albert Park",
    "sg:classifiers":[
        {
            "category":"Health Services",
            "subcategory":"Doctor",
            "type":"Services"
        }
    ],
    "sg:phone":"+61 3 9663 6401",
    "sg:postcode":"3206",
    "sg:province":"VIC",
    "sg:tags":[
        "medical",
        "practitioner"
    ],
    "wof:name":"Fail Dr Leon",
    "wof:placetype":"venue"
},
  "geometry": {"coordinates":[144.95478800000001,-37.841583],"type":"Point"}
}