{
  "type": "Feature",
  "properties": {
    "addr:full":"61 Dundas Pl Albert Park VIC 3206",
    "addr:housenumber":"61",
    "addr:postcode":"3206",
    "addr:street":"Dundas Pl",
    "iso:country":"AU",
    "sg:address":"61 Dundas Pl",
    "sg:city":"Albert Park",
    "sg:classifiers":[
        {
            "category":"Personal",
            "subcategory":"Beauty Salon",
            "type":"Services"
        }
    ],
    "sg:phone":"+61 3 9690 6059",
    "sg:postcode":"3206",
    "sg:province":"VIC",
    "wof:name":"Revive Skin Therapy",
    "wof:placetype":"venue"
},
  "geometry": {"coordinates":[144.95689400000001,-37.841335],"type":"Point"}
}