{
  "type": "Feature",
  "properties": {
    "addr:full":"2 Manor Rd Hornsby NSW 2077",
    "addr:housenumber":"2",
    "addr:postcode":"2077",
    "addr:street":"Manor Rd",
    "iso:country":"AU",
    "sg:address":"2 Manor Rd",
    "sg:city":"Hornsby",
    "sg:classifiers":[
        {
            "category":"Health Services",
            "subcategory":"Doctor",
            "type":"Services"
        }
    ],
    "sg:phone":"+61 2 9847 5000",
    "sg:postcode":"2077",
    "sg:province":"NSW",
    "sg:tags":[
        "medical",
        "practitioner"
    ],
    "wof:name":"Prendergast David",
    "wof:placetype":"venue"
},
  "geometry": {"coordinates":[151.09396362300001,-33.6930656433],"type":"Point"}
}