{
  "type": "Feature",
  "properties": {
    "iso:country":"AU",
    "sg:address":"417 High St",
    "sg:city":"Penrith",
    "sg:classifiers":[
        {
            "category":"Professional",
            "subcategory":"Printing & Photocopies",
            "type":"Services"
        }
    ],
    "sg:phone":"+61 2 4721 7590",
    "sg:postcode":"2750",
    "sg:province":"NSW",
    "sg:tags":[
        "embroidery"
    ],
    "wof:name":"EmbroidMe",
    "wof:placetype":"venue"
},
  "geometry": {"coordinates":[150.91557312,-33.8948898315],"type":"Point"}
}