{
  "type": "Feature",
  "properties": {
    "iso:country":"AU",
    "sg:address":"PO Box 9",
    "sg:city":"Round Corner",
    "sg:classifiers":[
        {
            "category":"Professional",
            "subcategory":"Business Services",
            "type":"Services"
        }
    ],
    "sg:phone":"+61 2 9651 2911",
    "sg:postcode":"2158",
    "sg:province":"NSW",
    "sg:tags":[
        "broker"
    ],
    "wof:name":"John Bentley Business Valuation",
    "wof:placetype":"venue"
},
  "geometry": {"coordinates":[151.048706055,-33.6634178162],"type":"Point"}
}