{
  "type": "Feature",
  "properties": {
    "addr:full":"236 Rossmore Rd Logan Reserve QLD 4133",
    "addr:housenumber":"236",
    "addr:postcode":"4133",
    "addr:street":"Rossmore Rd",
    "iso:country":"AU",
    "sg:address":"236 Rossmore Rd",
    "sg:city":"Logan Reserve",
    "sg:classifiers":[
        {
            "category":"Home & Garden",
            "subcategory":"Carpets & Floor Coverings",
            "type":"Retail Goods"
        }
    ],
    "sg:phone":"+61 403 039 843",
    "sg:postcode":"4133",
    "sg:province":"QLD",
    "sg:tags":[
        "tile",
        "wall"
    ],
    "wof:name":"Benmas",
    "wof:placetype":"venue"
},
  "geometry": {"coordinates":[153.108642578,-27.7416419983],"type":"Point"}
}