{
  "type": "Feature",
  "properties": {
    "addr:full":"35 Hender St Keith SA 5267",
    "addr:housenumber":"35",
    "addr:postcode":"5267",
    "addr:street":"Hender St",
    "iso:country":"AU",
    "sg:address":"35 Hender St",
    "sg:city":"Keith",
    "sg:classifiers":[
        {
            "category":"Food & Beverages",
            "subcategory":"Supermarket",
            "type":"Retail Goods"
        }
    ],
    "sg:phone":"+61 8 8755 1270",
    "sg:postcode":"5267",
    "sg:province":"SA",
    "sg:tags":[
        "grocery",
        "store"
    ],
    "wof:name":"IGA Everyday",
    "wof:placetype":"venue"
},
  "geometry": {"coordinates":[140.35351600000001,-36.097794],"type":"Point"}
}