{
  "type": "Feature",
  "properties": {
    "addr:full":"43 Archer St Rockhampton QLD 4700",
    "addr:housenumber":"43",
    "addr:postcode":"4700",
    "addr:street":"Archer St",
    "iso:country":"AU",
    "sg:address":"43 Archer St",
    "sg:city":"Rockhampton",
    "sg:classifiers":[
        {
            "category":"Fast Food",
            "type":"Food & Drink"
        }
    ],
    "sg:phone":"+61 7 4927 7729",
    "sg:postcode":"4700",
    "sg:province":"QLD",
    "sg:tags":[
        "away",
        "take"
    ],
    "wof:name":"Samos Fish Bar",
    "wof:placetype":"venue"
},
  "geometry": {"coordinates":[150.52232360799999,-23.3991985321],"type":"Point"}
}