{
  "type": "Feature",
  "properties": {
    "addr:full":"58 Marshall St Dapto NSW 2530",
    "addr:housenumber":"58",
    "addr:postcode":"2530",
    "addr:street":"Marshall St",
    "iso:country":"AU",
    "sg:address":"58 Marshall St",
    "sg:city":"Dapto",
    "sg:classifiers":[
        {
            "category":"Professional",
            "subcategory":"Engineering",
            "type":"Services"
        }
    ],
    "sg:phone":"+61 2 4261 1755",
    "sg:postcode":"2530",
    "sg:province":"NSW",
    "sg:tags":[
        "engineer"
    ],
    "wof:name":"Dowde Chris Engineering",
    "wof:placetype":"venue"
},
  "geometry": {"coordinates":[150.78948974599999,-34.4990348816],"type":"Point"}
}