{
  "type": "Feature",
  "properties": {
    "addr:full":"Shop 5, 86 Burnett St Buderim QLD 4556",
    "addr:housenumber":"shop;86",
    "addr:postcode":"4556",
    "addr:street":"Burnett St",
    "iso:country":"AU",
    "sg:address":"Shop 5, 86 Burnett St",
    "sg:city":"Buderim",
    "sg:classifiers":[
        {
            "category":"Health Services",
            "subcategory":"Doctor",
            "type":"Services"
        }
    ],
    "sg:phone":"+61 7 5450 1222",
    "sg:postcode":"4556",
    "sg:province":"QLD",
    "sg:tags":[
        "medical",
        "practitioner"
    ],
    "wof:name":"Body Scan",
    "wof:placetype":"venue"
},
  "geometry": {"coordinates":[153.04823303200001,-26.6878738403],"type":"Point"}
}