{
  "type": "Feature",
  "properties": {
    "addr:full":"Lvl 1/ 116 Hampden Rd Artarmon NSW 2064",
    "addr:housenumber":"/ 116",
    "addr:postcode":"2064",
    "addr:street":"Hampden Rd",
    "iso:country":"AU",
    "sg:address":"Lvl 1/ 116 Hampden Rd",
    "sg:city":"Artarmon",
    "sg:classifiers":[
        {
            "category":"Personal",
            "subcategory":"Massage",
            "type":"Services"
        }
    ],
    "sg:phone":"+61 2 9415 3829",
    "sg:postcode":"2064",
    "sg:province":"NSW",
    "sg:tags":[
        "therapy"
    ],
    "wof:name":"Artarmon Relaxation Centre",
    "wof:placetype":"venue"
},
  "geometry": {"coordinates":[151.1978302,-33.81016922],"type":"Point"}
}