{
  "type": "Feature",
  "properties": {
    "iso:country":"AU",
    "sg:address":"Cnr Ball & Cambooya St",
    "sg:city":"Toowoomba",
    "sg:classifiers":[
        {
            "category":"Manufacturing",
            "subcategory":"Glass & Minerals",
            "type":"Manufacturing & Wholesale Goods"
        }
    ],
    "sg:phone":"+61 402 367 507",
    "sg:postcode":"4350",
    "sg:province":"QLD",
    "sg:tags":[
        "bending",
        "tube"
    ],
    "sg:website":"http://www.rageaustralia.com.au",
    "wof:name":"R.A.G.E. Australia",
    "wof:placetype":"venue"
},
  "geometry": {"coordinates":[151.917068,-27.591625],"type":"Point"}
}