{
  "type": "Feature",
  "properties": {
    "iso:country":"AU",
    "sg:address":"33 Semaphore Rd",
    "sg:city":"Semaphore",
    "sg:classifiers":[
        {
            "category":"Manufacturing",
            "subcategory":"Tools & Machinery",
            "type":"Manufacturing & Wholesale Goods"
        }
    ],
    "sg:phone":"+61 1300 131 396",
    "sg:postcode":"5019",
    "sg:province":"SA",
    "sg:tags":[
        "wholesaler",
        "mfrs",
        "hosiery"
    ],
    "wof:name":"Koronis Koncepts",
    "wof:placetype":"venue"
},
  "geometry": {"coordinates":[138.482666016,-34.8383903503],"type":"Point"}
}