{
  "type": "Feature",
  "properties": {
    "iso:country":"AU",
    "sg:address":"305 Copland St",
    "sg:city":"Wagga Wagga",
    "sg:classifiers":[
        {
            "category":"Wholesale",
            "subcategory":"Furniture",
            "type":"Manufacturing & Wholesale Goods"
        }
    ],
    "sg:phone":"+61 2 6921 4951",
    "sg:postcode":"2650",
    "sg:province":"NSW",
    "sg:tags":[
        "wholesaler",
        "mfrs"
    ],
    "wof:name":"Billy Tea Furniture Pty Ltd",
    "wof:placetype":"venue"
},
  "geometry": {"coordinates":[147.41152954099999,-35.1297187805],"type":"Point"}
}