{
  "type": "Feature",
  "properties": {
    "iso:country":"AU",
    "sg:address":"PO Box 297",
    "sg:city":"Glass House Mountains",
    "sg:classifiers":[
        {
            "category":"Banks & Credit Unions",
            "subcategory":"Financial Services",
            "type":"Services"
        }
    ],
    "sg:phone":"+61 7 5493 0033",
    "sg:postcode":"4518",
    "sg:province":"QLD",
    "sg:tags":[
        "loan",
        "finance",
        "mortgage"
    ],
    "wof:name":"Ambrose Financial Services",
    "wof:placetype":"venue"
},
  "geometry": {"coordinates":[152.959060669,-26.8959293365],"type":"Point"}
}