{
  "type": "Feature",
  "properties": {
    "addr:full":"Unit 1, 17 Gibberd Rd Balcatta WA 6021",
    "addr:housenumber":"17",
    "addr:postcode":"6021",
    "addr:street":"Gibberd Rd",
    "iso:country":"AU",
    "sg:address":"Unit 1, 17 Gibberd Rd",
    "sg:city":"Balcatta",
    "sg:classifiers":[
        {
            "category":"Building & Trades",
            "subcategory":"Construction",
            "type":"Services"
        }
    ],
    "sg:phone":"+61 8 9345 3221",
    "sg:postcode":"6021",
    "sg:province":"WA",
    "sg:tags":[
        "window",
        "aluminium"
    ],
    "wof:name":"Osborne Park Security Products",
    "wof:placetype":"venue"
},
  "geometry": {"coordinates":[115.81169128400001,-31.8645019531],"type":"Point"}
}