{
  "type": "Feature",
  "properties": {
    "addr:full":"99a Manning St Taree NSW 2430",
    "addr:housenumber":"99a",
    "addr:postcode":"2430",
    "addr:street":"Manning St",
    "iso:country":"AU",
    "sg:address":"99a Manning St",
    "sg:city":"Taree",
    "sg:classifiers":[
        {
            "category":"Health Services",
            "subcategory":"Doctor",
            "type":"Services"
        }
    ],
    "sg:phone":"+61 2 6550 1419",
    "sg:postcode":"2430",
    "sg:province":"NSW",
    "sg:tags":[
        "medical",
        "practitioner"
    ],
    "wof:name":"Al-Rubai Dr",
    "wof:placetype":"venue"
},
  "geometry": {"coordinates":[152.45451399999999,-31.911217],"type":"Point"}
}