{
  "type": "Feature",
  "properties": {
    "addr:full":"17 Pavesi St Guildford NSW 2161",
    "addr:housenumber":"17",
    "addr:postcode":"2161",
    "addr:street":"Pavesi St",
    "iso:country":"AU",
    "sg:address":"17 Pavesi St",
    "sg:city":"Guildford",
    "sg:classifiers":[
        {
            "category":"Professional",
            "type":"Services"
        }
    ],
    "sg:phone":"+61 2 9892 4255",
    "sg:postcode":"2161",
    "sg:province":"NSW",
    "sg:tags":[
        "transport"
    ],
    "wof:name":"Valtrans Pty Ltd",
    "wof:placetype":"venue"
},
  "geometry": {"coordinates":[150.957565308,-33.8456993103],"type":"Point"}
}