{
  "type": "Feature",
  "properties": {
    "iso:country":"AU",
    "sg:address":"6 Green St",
    "sg:city":"Brookvale",
    "sg:classifiers":[
        {
            "category":"Building & Trades",
            "subcategory":"Construction",
            "type":"Services"
        }
    ],
    "sg:phone":"+61 2 9938 1011",
    "sg:postcode":"2100",
    "sg:province":"NSW",
    "sg:tags":[
        "joinery"
    ],
    "wof:name":"Framex",
    "wof:placetype":"venue"
},
  "geometry": {"coordinates":[151.26719665499999,-33.7651557922],"type":"Point"}
}