{
  "type": "Feature",
  "properties": {
    "addr:full":"13 Elizabeth Crs North Avoca NSW 2260",
    "addr:housenumber":"13",
    "addr:postcode":"2260",
    "addr:street":"Elizabeth Crs North",
    "iso:country":"AU",
    "sg:address":"13 Elizabeth Crs",
    "sg:city":"North Avoca",
    "sg:classifiers":[
        {
            "category":"Government",
            "subcategory":"Fire Station",
            "type":"Public Place"
        }
    ],
    "sg:phone":"+61 2 4341 6184",
    "sg:postcode":"2260",
    "sg:province":"NSW",
    "sg:tags":[
        "equipment",
        "protection",
        "consultant"
    ],
    "wof:name":"Essential Services Group",
    "wof:placetype":"venue"
},
  "geometry": {"coordinates":[151.438568,-33.45787],"type":"Point"}
}