{
  "type": "Feature",
  "properties": {
    "iso:country":"AU",
    "sg:address":"127 Smart Rd",
    "sg:city":"Modbury",
    "sg:classifiers":[
        {
            "category":"Health Services",
            "subcategory":"Doctor",
            "type":"Services"
        }
    ],
    "sg:phone":"+61 8 8396 0978",
    "sg:postcode":"5092",
    "sg:province":"SA",
    "sg:tags":[
        "medical",
        "practitioner"
    ],
    "wof:name":"Lewis Anne",
    "wof:placetype":"venue"
},
  "geometry": {"coordinates":[138.69778442399999,-34.8330078125],"type":"Point"}
}