{
  "type": "Feature",
  "properties": {
    "iso:country":"AU",
    "sg:address":"10 Kenthurst Rd",
    "sg:city":"Dural",
    "sg:classifiers":[
        {
            "category":"Shopping",
            "subcategory":"Luggage & Leather Goods",
            "type":"Retail Goods"
        }
    ],
    "sg:phone":"+61 2 9651 2337",
    "sg:postcode":"2158",
    "sg:province":"NSW",
    "wof:name":"Dural Village Court Saddleworld",
    "wof:placetype":"venue"
},
  "geometry": {"coordinates":[151.01846313499999,-33.6908950806],"type":"Point"}
}