{
  "type": "Feature",
  "properties": {
    "addr:full":"6 Bardoel Crt Chelsea VIC 3196",
    "addr:housenumber":"6",
    "addr:postcode":"3196",
    "addr:street":"Bardoel Crt",
    "iso:country":"AU",
    "sg:address":"6 Bardoel Crt",
    "sg:city":"Chelsea",
    "sg:classifiers":[
        {
            "category":"Building & Trades",
            "subcategory":"Landscaping Services",
            "type":"Services"
        }
    ],
    "sg:phone":"+61 3 9773 9373",
    "sg:postcode":"3196",
    "sg:province":"VIC",
    "sg:tags":[
        "stump",
        "tree",
        "felling",
        "removal"
    ],
    "wof:name":"Twin Peak Tree Service",
    "wof:placetype":"venue"
},
  "geometry": {"coordinates":[145.11965942399999,-38.0465621948],"type":"Point"}
}