{
  "type": "Feature",
  "properties": {
    "addr:full":"Shop 59b Lockyer Ave Albany WA 6330",
    "addr:housenumber":"59b",
    "addr:postcode":"6330",
    "addr:street":"Shop;Lockyer Ave",
    "iso:country":"AU",
    "sg:address":"Shop 59b Lockyer Ave",
    "sg:city":"Albany",
    "sg:classifiers":[
        {
            "category":"Personal",
            "subcategory":"Beauty Salon",
            "type":"Services"
        }
    ],
    "sg:phone":"+61 8 9841 7880",
    "sg:postcode":"6330",
    "sg:province":"WA",
    "sg:tags":[
        "hairdresser"
    ],
    "wof:name":"Tammie's House Of Hair & Beauty",
    "wof:placetype":"venue"
},
  "geometry": {"coordinates":[117.88368988000001,-35.018825531],"type":"Point"}
}