{
  "type": "Feature",
  "properties": {
    "iso:country":"AU",
    "sg:address":"882 Old Calder Hwy",
    "sg:city":"Keilor",
    "sg:classifiers":[
        {
            "category":"Health Services",
            "subcategory":"Dentist",
            "type":"Services"
        }
    ],
    "sg:phone":"+61 3 9449 1211",
    "sg:postcode":"3036",
    "sg:province":"VIC",
    "wof:name":"Elite Dental",
    "wof:placetype":"venue"
},
  "geometry": {"coordinates":[144.806854,-37.702961],"type":"Point"}
}