{
  "type": "Feature",
  "properties": {
    "iso:country":"AU",
    "sg:address":"5 Westella Ave",
    "sg:city":"Roselands",
    "sg:classifiers":[
        {
            "category":"Retail",
            "subcategory":"Auto Repair",
            "type":"Services"
        }
    ],
    "sg:phone":"+61 2 9759 7400",
    "sg:postcode":"2196",
    "sg:province":"NSW",
    "sg:tags":[
        "body",
        "motor",
        "trimmer"
    ],
    "wof:name":"Bugtrim",
    "wof:placetype":"venue"
},
  "geometry": {"coordinates":[151.078094,-33.932468],"type":"Point"}
}