{
  "type": "Feature",
  "properties": {
    "iso:country":"AU",
    "sg:address":"42 Huddersfield Rd",
    "sg:city":"Deer Park",
    "sg:classifiers":[
        {
            "category":"Manufacturing",
            "subcategory":"Printing",
            "type":"Manufacturing & Wholesale Goods"
        }
    ],
    "sg:phone":"+61 3 9360 5140",
    "sg:postcode":"3023",
    "sg:province":"VIC",
    "sg:tags":[
        "wholesaler",
        "mfrs",
        "greeting",
        "card"
    ],
    "wof:name":"Caring Card Company Pty Ltd",
    "wof:placetype":"venue"
},
  "geometry": {"coordinates":[144.766907,-37.762272],"type":"Point"}
}