{
  "type": "Feature",
  "properties": {
    "iso:country":"AU",
    "sg:address":"Lvl/ 379 Collins St",
    "sg:city":"Melbourne",
    "sg:classifiers":[
        {
            "category":"Professional",
            "subcategory":"Employment Agencies",
            "type":"Services"
        }
    ],
    "sg:phone":"+61 3 9670 6170",
    "sg:postcode":"3000",
    "sg:province":"VIC",
    "wof:name":"Qorom Consulting Pty Ltd",
    "wof:placetype":"venue"
},
  "geometry": {"coordinates":[144.96205139200001,-37.8169212341],"type":"Point"}
}