{
  "type": "Feature",
  "properties": {
    "iso:country":"AU",
    "sg:address":"3 Anembo St",
    "sg:city":"Moss Vale",
    "sg:classifiers":[
        {
            "category":"Autos & Motor Vehicles",
            "subcategory":"Auto Supplies",
            "type":"Retail Goods"
        }
    ],
    "sg:phone":"+61 2 4868 2334",
    "sg:postcode":"2577",
    "sg:province":"NSW",
    "sg:tags":[
        "equipment",
        "part",
        "truck"
    ],
    "wof:name":"Wind Cone",
    "wof:placetype":"venue"
},
  "geometry": {"coordinates":[150.36741638199999,-34.5424423218],"type":"Point"}
}