{
  "type": "Feature",
  "properties": {
    "iso:country":"AU",
    "sg:address":"26A Tina St",
    "sg:city":"Beaudesert",
    "sg:classifiers":[
        {
            "category":"Wholesale",
            "subcategory":"Painting Supplies",
            "type":"Manufacturing & Wholesale Goods"
        }
    ],
    "sg:phone":"+61 7 5541 1627",
    "sg:postcode":"4285",
    "sg:province":"QLD",
    "sg:tags":[
        "product",
        "cleaning"
    ],
    "wof:name":"Vitam Industries",
    "wof:placetype":"venue"
},
  "geometry": {"coordinates":[153.00260900000001,-27.986071],"type":"Point"}
}