{
  "type": "Feature",
  "properties": {
    "addr:full":"Shop 2055 Westpoint Shopping Centre, 17 Patrick St Blacktown NSW 2148",
    "addr:housenumber":"2055;17",
    "addr:postcode":"2148",
    "addr:street":"Westpoint Shopping;Patrick St",
    "iso:country":"AU",
    "sg:address":"Shop 2055 Westpoint Shopping Centre, 17 Patrick St",
    "sg:city":"Blacktown",
    "sg:classifiers":[
        {
            "category":"Health Services",
            "subcategory":"Optometrist",
            "type":"Services"
        }
    ],
    "sg:phone":"+61 2 9831 7107",
    "sg:postcode":"2148",
    "sg:province":"NSW",
    "wof:name":"Laubman & Pank",
    "wof:placetype":"venue"
},
  "geometry": {"coordinates":[150.94903564399999,-33.8248519897],"type":"Point"}
}