{
  "type": "Feature",
  "properties": {
    "iso:country":"AU",
    "sg:address":"Shp2/ 21 Mary St",
    "sg:city":"Brisbane",
    "sg:classifiers":[
        {
            "category":"Cafe",
            "type":"Food & Drink"
        }
    ],
    "sg:phone":"+61 7 3210 6100",
    "sg:postcode":"4000",
    "sg:province":"QLD",
    "wof:name":"Cafe Levanto",
    "wof:placetype":"venue"
},
  "geometry": {"coordinates":[153.02638244600001,-27.4729442596],"type":"Point"}
}