{
  "type": "Feature",
  "properties": {
    "iso:country":"AU",
    "sg:address":"85 Reibey St",
    "sg:city":"Ulverstone",
    "sg:classifiers":[
        {
            "category":"Shopping",
            "subcategory":"Party Supplies",
            "type":"Retail Goods"
        }
    ],
    "sg:phone":"+61 3 6425 4913",
    "sg:postcode":"7315",
    "sg:province":"TAS",
    "wof:name":"deb-lins celebrations",
    "wof:placetype":"venue"
},
  "geometry": {"coordinates":[146.17396545400001,-41.1574516296],"type":"Point"}
}