{
  "type": "Feature",
  "properties": {
    "addr:full":"3/ 177 Kelly St Scone NSW 2337",
    "addr:housenumber":"/ 177",
    "addr:postcode":"2337",
    "addr:street":"Kelly St",
    "iso:country":"AU",
    "sg:address":"3/ 177 Kelly St",
    "sg:city":"Scone",
    "sg:classifiers":[
        {
            "category":"Professional",
            "subcategory":"Art Services",
            "type":"Services"
        }
    ],
    "sg:phone":"+61 2 6545 3155",
    "sg:postcode":"2337",
    "sg:province":"NSW",
    "sg:tags":[
        "picture",
        "frame",
        "framing"
    ],
    "wof:name":"Kodak Express Scone Camera Centre",
    "wof:placetype":"venue"
},
  "geometry": {"coordinates":[150.86712646500001,-32.051864624],"type":"Point"}
}