{
  "type": "Feature",
  "properties": {
    "iso:country":"AU",
    "sg:address":"27 Arthur St",
    "sg:city":"Penola",
    "sg:classifiers":[
        {
            "category":"Landmark",
            "subcategory":"Tourist Information",
            "type":"Public Place"
        }
    ],
    "sg:phone":"+61 8 8737 2391",
    "sg:postcode":"5277",
    "sg:province":"SA",
    "sg:tags":[
        "bureau"
    ],
    "wof:name":"Penola Visitor Information Centre",
    "wof:placetype":"venue"
},
  "geometry": {"coordinates":[140.83775299999999,-37.377724],"type":"Point"}
}