{
  "type": "Feature",
  "properties": {
    "addr:full":"737 Darling St Rozelle NSW 2039",
    "addr:housenumber":"737",
    "addr:postcode":"2039",
    "addr:street":"Darling St",
    "iso:country":"AU",
    "sg:address":"737 Darling St",
    "sg:city":"Rozelle",
    "sg:classifiers":[
        {
            "category":"Health Services",
            "subcategory":"Chiropractor",
            "type":"Services"
        }
    ],
    "sg:phone":"+61 2 9810 8769",
    "sg:postcode":"2039",
    "sg:province":"NSW",
    "sg:website":"http://www.chiropractors.asn.au",
    "wof:name":"Rozelle Chiropractic",
    "wof:placetype":"venue"
},
  "geometry": {"coordinates":[151.16792297399999,-33.8650360107],"type":"Point"}
}