{
  "type": "Feature",
  "properties": {
    "iso:country":"AU",
    "sg:address":"21 Bosworth Rd",
    "sg:city":"Woolgoolga",
    "sg:classifiers":[
        {
            "category":"Home & Garden",
            "subcategory":"Building Materials",
            "type":"Retail Goods"
        }
    ],
    "sg:phone":"+61 2 6654 8122",
    "sg:postcode":"2456",
    "sg:province":"NSW",
    "sg:tags":[
        "merchant",
        "glass",
        "glazier"
    ],
    "wof:name":"Steve Parker Glass Woolgoolga",
    "wof:placetype":"venue"
},
  "geometry": {"coordinates":[153.19477800000001,-30.125105],"type":"Point"}
}