{
  "type": "Feature",
  "properties": {
    "iso:country":"AU",
    "sg:address":"135 Bryants Rd",
    "sg:city":"Loganholme",
    "sg:classifiers":[
        {
            "category":"Fast Food",
            "type":"Food & Drink"
        }
    ],
    "sg:phone":"+61 7 3209 8041",
    "sg:postcode":"4129",
    "sg:province":"QLD",
    "sg:tags":[
        "away",
        "take"
    ],
    "wof:name":"George's International Fish & Chippery",
    "wof:placetype":"venue"
},
  "geometry": {"coordinates":[153.18559265100001,-27.665643692],"type":"Point"}
}