{
  "type": "Feature",
  "properties": {
    "addr:full":"139 Mornington-Tyabb Rd Mornington VIC 3931",
    "addr:housenumber":"139",
    "addr:postcode":"3931",
    "addr:street":"Mornington-Tyabb Rd",
    "iso:country":"AU",
    "sg:address":"139 Mornington-Tyabb Rd",
    "sg:city":"Mornington",
    "sg:classifiers":[
        {
            "category":"Home & Garden",
            "subcategory":"Household Appliances",
            "type":"Retail Goods"
        }
    ],
    "sg:phone":"+61 3 5977 0899",
    "sg:postcode":"3931",
    "sg:province":"VIC",
    "sg:tags":[
        "heating",
        "system"
    ],
    "wof:name":"Woodpecker Pty Ltd",
    "wof:placetype":"venue"
},
  "geometry": {"coordinates":[145.05918884299999,-38.2366256714],"type":"Point"}
}