{
  "type": "Feature",
  "properties": {
    "addr:full":"25 Mountain La Broadway NSW 2007",
    "addr:housenumber":"25",
    "addr:postcode":"2007",
    "addr:street":"Mountain La",
    "iso:country":"AU",
    "sg:address":"25 Mountain La",
    "sg:city":"Broadway",
    "sg:classifiers":[
        {
            "category":"Professional",
            "subcategory":"Art Services",
            "type":"Services"
        }
    ],
    "sg:phone":"+61 2 9280 0069",
    "sg:postcode":"2007",
    "sg:province":"NSW",
    "sg:tags":[
        "graphic",
        "designer"
    ],
    "wof:name":"Wag Design",
    "wof:placetype":"venue"
},
  "geometry": {"coordinates":[151.19578552199999,-33.8826141357],"type":"Point"}
}