{
  "type": "Feature",
  "properties": {
    "iso:country":"AU",
    "sg:address":"41 McCombe Rd",
    "sg:city":"Bunbury",
    "sg:classifiers":[
        {
            "category":"Retail",
            "subcategory":"Auto Repair",
            "type":"Services"
        }
    ],
    "sg:phone":"+61 8 9726 2800",
    "sg:postcode":"6230",
    "sg:province":"WA",
    "sg:tags":[
        "gas",
        "conversion",
        "natural",
        "lp",
        "vehicle"
    ],
    "wof:name":"Alltrak Automotive",
    "wof:placetype":"venue"
},
  "geometry": {"coordinates":[115.676781,-33.360409],"type":"Point"}
}