{
  "type": "Feature",
  "properties": {
    "addr:full":"14 St Albans Drv Burnside SA 5066",
    "addr:housenumber":"14",
    "addr:postcode":"5066",
    "addr:street":"St Albans Drv",
    "iso:country":"AU",
    "sg:address":"14 St Albans Drv",
    "sg:city":"Burnside",
    "sg:classifiers":[
        {
            "category":"Farming",
            "subcategory":"Farm & Veterinary Services",
            "type":"Manufacturing & Wholesale Goods"
        }
    ],
    "sg:phone":"+61 8 8364 7141",
    "sg:postcode":"5066",
    "sg:province":"SA",
    "sg:tags":[
        "agricultural",
        "advisory"
    ],
    "wof:name":"Earthlink Australia Pty Ltd",
    "wof:placetype":"venue"
},
  "geometry": {"coordinates":[138.67213439899999,-34.9386558533],"type":"Point"}
}