{
  "type": "Feature",
  "properties": {
    "iso:country":"AU",
    "sg:address":"Shop 1, 424 Sturt St",
    "sg:city":"Ballarat",
    "sg:classifiers":[
        {
            "category":"Manufacturing",
            "subcategory":"Jewelry",
            "type":"Manufacturing & Wholesale Goods"
        }
    ],
    "sg:phone":"+61 3 5333 4715",
    "sg:postcode":"3350",
    "sg:province":"VIC",
    "sg:tags":[
        "designer",
        "jewellery"
    ],
    "wof:name":"Gems & Jewels",
    "wof:placetype":"venue"
},
  "geometry": {"coordinates":[143.85737599999999,-37.581841],"type":"Point"}
}