{
  "type": "Feature",
  "properties": {
    "addr:full":"Shop A, 239- 241 Main North Rd Sefton Park SA 5083",
    "addr:housenumber":"239 241",
    "addr:postcode":"5083",
    "addr:street":"A;Main North Rd",
    "iso:country":"AU",
    "sg:address":"Shop A, 239- 241 Main North Rd",
    "sg:city":"Sefton Park",
    "sg:classifiers":[
        {
            "category":"Fast Food",
            "type":"Food & Drink"
        }
    ],
    "sg:phone":"+61 8 8269 1322",
    "sg:postcode":"5083",
    "sg:province":"SA",
    "sg:tags":[
        "away",
        "take"
    ],
    "wof:name":"Barnacle Bill",
    "wof:placetype":"venue"
},
  "geometry": {"coordinates":[138.60243225100001,-34.8764877319],"type":"Point"}
}