{
  "type": "Feature",
  "properties": {
    "iso:country":"AU",
    "sg:address":"214 Victoria Ave",
    "sg:city":"Chatswood",
    "sg:classifiers":[
        {
            "category":"Professional",
            "subcategory":"Computer Services",
            "type":"Services"
        }
    ],
    "sg:phone":"+61 2 9413 4788",
    "sg:postcode":"2067",
    "sg:province":"NSW",
    "sg:tags":[
        "package",
        "software"
    ],
    "wof:name":"Systemedica Pty Ltd",
    "wof:placetype":"venue"
},
  "geometry": {"coordinates":[151.190185547,-33.7942276001],"type":"Point"}
}