{
  "type": "Feature",
  "properties": {
    "iso:country":"AU",
    "sg:address":"53 - 55 McClure St",
    "sg:city":"Thornbury",
    "sg:classifiers":[
        {
            "category":"Manufacturing",
            "subcategory":"Tools & Machinery",
            "type":"Manufacturing & Wholesale Goods"
        }
    ],
    "sg:phone":"+61 3 9497 3933",
    "sg:postcode":"3071",
    "sg:province":"VIC",
    "sg:tags":[
        "equipment",
        "scale",
        "weighing"
    ],
    "wof:name":"Wedderburn",
    "wof:placetype":"venue"
},
  "geometry": {"coordinates":[145.02693176299999,-37.7652244568],"type":"Point"}
}