{
  "type": "Feature",
  "properties": {
    "addr:full":"76 Veterans Pde Collaroy Plateau NSW 2097",
    "addr:housenumber":"76",
    "addr:postcode":"2097",
    "addr:street":"Veterans Pde",
    "iso:country":"AU",
    "sg:address":"76 Veterans Pde",
    "sg:city":"Collaroy Plateau",
    "sg:classifiers":[
        {
            "category":"Health Services",
            "subcategory":"Dentist",
            "type":"Services"
        }
    ],
    "sg:phone":"+61 2 9972 2427",
    "sg:postcode":"2097",
    "sg:province":"NSW",
    "sg:tags":[
        "dental",
        "prosthetist"
    ],
    "wof:name":"ProFit Mouthguards",
    "wof:placetype":"venue"
},
  "geometry": {"coordinates":[151.286743164,-33.7255744934],"type":"Point"}
}