{
  "type": "Feature",
  "properties": {
    "addr:full":"51 Forrest St Kalgoorlie WA 6430",
    "addr:housenumber":"51",
    "addr:postcode":"6430",
    "addr:street":"Forrest St",
    "iso:country":"AU",
    "sg:address":"51 Forrest St",
    "sg:city":"Kalgoorlie",
    "sg:classifiers":[
        {
            "category":"Travel",
            "subcategory":"Hotels & Motels",
            "type":"Entertainment"
        }
    ],
    "sg:phone":"+61 8 9088 0000",
    "sg:postcode":"6430",
    "sg:province":"WA",
    "sg:tags":[
        "accommodation"
    ],
    "wof:name":"Quality Inn Railway & Function Centre",
    "wof:placetype":"venue"
},
  "geometry": {"coordinates":[121.468940735,-30.7451972961],"type":"Point"}
}