{
  "type": "Feature",
  "properties": {
    "addr:full":"117 Bundall Rd Southport QLD 4215",
    "addr:housenumber":"117",
    "addr:postcode":"4215",
    "addr:street":"Bundall Rd",
    "iso:country":"AU",
    "sg:address":"117 Bundall Rd",
    "sg:city":"Southport",
    "sg:classifiers":[
        {
            "category":"Autos & Motor Vehicles",
            "subcategory":"Fuel & Gas Station",
            "type":"Retail Goods"
        }
    ],
    "sg:phone":"+61 7 5538 7135",
    "sg:postcode":"4215",
    "sg:province":"QLD",
    "wof:name":"Shell Bundall East",
    "wof:placetype":"venue"
},
  "geometry": {"coordinates":[153.414138794,-27.9975948334],"type":"Point"}
}