{
  "type": "Feature",
  "properties": {
    "addr:full":"Shop 4, 103 Beckett Rd McDowall QLD 4053",
    "addr:housenumber":"shop 4 103",
    "addr:postcode":"4053",
    "addr:street":"Beckett Rd",
    "iso:country":"AU",
    "sg:address":"Shop 4, 103 Beckett Rd",
    "sg:city":"McDowall",
    "sg:classifiers":[
        {
            "category":"Shopping",
            "subcategory":"Computers & Home Electronics",
            "type":"Retail Goods"
        }
    ],
    "sg:phone":"+61 7 3353 9222",
    "sg:postcode":"4053",
    "sg:province":"QLD",
    "sg:tags":[
        "hardware",
        "equipment"
    ],
    "wof:name":"Computers By Design",
    "wof:placetype":"venue"
},
  "geometry": {"coordinates":[152.98880004899999,-27.3805103302],"type":"Point"}
}