{
  "type": "Feature",
  "properties": {
    "iso:country":"AU",
    "sg:address":"Fentondale'' Rd",
    "sg:city":"Clarkefield",
    "sg:classifiers":[
        {
            "category":"Farming",
            "subcategory":"Farm",
            "type":"Manufacturing & Wholesale Goods"
        }
    ],
    "sg:phone":"+61 3 5428 5372",
    "sg:postcode":"3430",
    "sg:province":"VIC",
    "sg:tags":[
        "farmer"
    ],
    "wof:name":"McCormick K M",
    "wof:placetype":"venue"
},
  "geometry": {"coordinates":[144.799957275,-37.4822502136],"type":"Point"}
}