{
  "type": "Feature",
  "properties": {
    "addr:full":"PO Box 5788 Cairns QLD 4870",
    "addr:postcode":"4870",
    "iso:country":"AU",
    "sg:address":"PO Box 5788",
    "sg:city":"Cairns",
    "sg:classifiers":[
        {
            "category":"Recreation",
            "subcategory":"Boat Charter",
            "type":"Entertainment"
        }
    ],
    "sg:phone":"+61 407 969 341",
    "sg:postcode":"4870",
    "sg:province":"QLD",
    "wof:name":"Cairns Reef Charter Services",
    "wof:placetype":"venue"
},
  "geometry": {"coordinates":[145.66958618199999,-17.0185699463],"type":"Point"}
}