{
  "type": "Feature",
  "properties": {
    "iso:country":"AU",
    "sg:address":"53- 63 Burnley St",
    "sg:city":"Richmond",
    "sg:classifiers":[
        {
            "category":"Professional",
            "subcategory":"Management & Consulting",
            "type":"Services"
        }
    ],
    "sg:phone":"+61 3 9427 0188",
    "sg:postcode":"3121",
    "sg:province":"VIC",
    "sg:tags":[
        "consultant",
        "relocation"
    ],
    "wof:name":"Furniture Rentals",
    "wof:placetype":"venue"
},
  "geometry": {"coordinates":[145.00946044899999,-37.8139801025],"type":"Point"}
}