{
  "type": "Feature",
  "properties": {
    "addr:full":"10 Jaffa Rd Round Corner NSW 2158",
    "addr:housenumber":"10",
    "addr:postcode":"2158",
    "addr:street":"Jaffa Rd",
    "iso:country":"AU",
    "sg:address":"10 Jaffa Rd",
    "sg:city":"Round Corner",
    "sg:classifiers":[
        {
            "category":"Government",
            "subcategory":"Department Of Motor Vehicles",
            "type":"Public Place"
        }
    ],
    "sg:phone":"+61 2 9651 3550",
    "sg:postcode":"2158",
    "sg:province":"NSW",
    "sg:tags":[
        "wholesaler",
        "mfrs",
        "accessory"
    ],
    "wof:name":"Max-Wedge Performance",
    "wof:placetype":"venue"
},
  "geometry": {"coordinates":[151.02229309099999,-33.6927070618],"type":"Point"}
}