{
  "type": "Feature",
  "properties": {
    "addr:full":"95 Hubner Rd Park Ridge QLD 4125",
    "addr:housenumber":"95",
    "addr:postcode":"4125",
    "addr:street":"Hubner Rd",
    "iso:country":"AU",
    "sg:address":"95 Hubner Rd",
    "sg:city":"Park Ridge",
    "sg:classifiers":[
        {
            "category":"Manufacturing",
            "subcategory":"Tools & Machinery",
            "type":"Manufacturing & Wholesale Goods"
        }
    ],
    "sg:phone":"+61 7 3802 1718",
    "sg:postcode":"4125",
    "sg:province":"QLD",
    "sg:tags":[
        "earth",
        "excavating",
        "moving",
        "equipment"
    ],
    "wof:name":"Mark Smith",
    "wof:placetype":"venue"
},
  "geometry": {"coordinates":[153.058685303,-27.7116718292],"type":"Point"}
}