{
  "type": "Feature",
  "properties": {
    "addr:full":"Shop 9, 18 Church St Terrigal NSW 2260",
    "addr:housenumber":"shop;18",
    "addr:postcode":"2260",
    "addr:street":"Church St",
    "iso:country":"AU",
    "sg:address":"Shop 9, 18 Church St",
    "sg:city":"Terrigal",
    "sg:classifiers":[
        {
            "category":"Manufacturing",
            "subcategory":"Food",
            "type":"Manufacturing & Wholesale Goods"
        }
    ],
    "sg:phone":"+61 2 4384 1899",
    "sg:postcode":"2260",
    "sg:province":"NSW",
    "sg:tags":[
        "function",
        "catering"
    ],
    "wof:name":"&#039;N Thai Sing",
    "wof:placetype":"venue"
},
  "geometry": {"coordinates":[151.44343599999999,-33.447346],"type":"Point"}
}