{
  "type": "Feature",
  "properties": {
    "addr:full":"377 Springs Rd Mareeba QLD 4880",
    "addr:housenumber":"377",
    "addr:postcode":"4880",
    "addr:street":"Springs Rd",
    "iso:country":"AU",
    "sg:address":"377 Springs Rd",
    "sg:city":"Mareeba",
    "sg:classifiers":[
        {
            "category":"Food & Beverages",
            "subcategory":"Fruits & Vegetables",
            "type":"Retail Goods"
        }
    ],
    "sg:phone":"+61 7 4086 6006",
    "sg:postcode":"4880",
    "sg:province":"QLD",
    "sg:tags":[
        "wholesale"
    ],
    "wof:name":"Valley Fresh Farming",
    "wof:placetype":"venue"
},
  "geometry": {"coordinates":[145.40742492699999,-16.9841136932],"type":"Point"}
}