{
  "type": "Feature",
  "properties": {
    "iso:country":"AU",
    "sg:address":"404-408 Anzac Pde",
    "sg:city":"Kingsford",
    "sg:classifiers":[
        {
            "category":"Wholesale",
            "subcategory":"Construction Materials",
            "type":"Manufacturing & Wholesale Goods"
        }
    ],
    "sg:phone":"+61 2 9663 1214",
    "sg:postcode":"2032",
    "sg:province":"NSW",
    "sg:tags":[
        "wholesaler",
        "lighting",
        "mfrs",
        "accessory"
    ],
    "wof:name":"Light Up Kingsford",
    "wof:placetype":"venue"
},
  "geometry": {"coordinates":[151.226837158,-33.9208831787],"type":"Point"}
}