{
  "type": "Feature",
  "properties": {
    "addr:full":"Level 3 Carlingford Village Shppng Cntr 372 Pennan Carlingford NSW 2118",
    "addr:housenumber":"372",
    "addr:postcode":"2118",
    "addr:street":"Pennan",
    "iso:country":"AU",
    "sg:address":"Level 3 Carlingford Village Shppng Cntr 372 Pennan",
    "sg:city":"Carlingford",
    "sg:classifiers":[
        {
            "category":"Travel",
            "subcategory":"Travel Agent",
            "type":"Entertainment"
        }
    ],
    "sg:phone":"+61 2 9872 8388",
    "sg:postcode":"2118",
    "sg:province":"NSW",
    "sg:tags":[
        "consultant"
    ],
    "wof:name":"Advance Travel Pty Ltd",
    "wof:placetype":"venue"
},
  "geometry": {"coordinates":[151.052276611,-33.7798881531],"type":"Point"}
}