{
  "type": "Feature",
  "properties": {
    "iso:country":"AU",
    "sg:address":"136 Green Oaks Drv",
    "sg:city":"Coolum Beach",
    "sg:classifiers":[
        {
            "category":"Professional",
            "subcategory":"Accounting & Tax Preparation",
            "type":"Services"
        }
    ],
    "sg:phone":"+61 7 5471 7916",
    "sg:postcode":"4573",
    "sg:province":"QLD",
    "sg:tags":[
        "bookkeeping"
    ],
    "wof:name":"Nicholas Jones",
    "wof:placetype":"venue"
},
  "geometry": {"coordinates":[153.07847599999999,-26.536926],"type":"Point"}
}