{
  "type": "Feature",
  "properties": {
    "addr:full":"Warrnambool Hospital Ryot St Warrnambool VIC 3280",
    "addr:postcode":"3280",
    "addr:street":"Ryot St",
    "iso:country":"AU",
    "sg:address":"Warrnambool Hospital Ryot St",
    "sg:city":"Warrnambool",
    "sg:classifiers":[
        {
            "category":"Health Services",
            "subcategory":"Medical Lab",
            "type":"Services"
        }
    ],
    "sg:phone":"+61 3 5563 1515",
    "sg:postcode":"3280",
    "sg:province":"VIC",
    "sg:tags":[
        "laboratory",
        "pathology"
    ],
    "wof:name":"Gribbles Pathology",
    "wof:placetype":"venue"
},
  "geometry": {"coordinates":[142.47393798799999,-38.3802871704],"type":"Point"}
}