{
  "type": "Feature",
  "properties": {
    "iso:country":"AU",
    "sg:address":"25 Lovoni St",
    "sg:city":"Cabramatta",
    "sg:classifiers":[
        {
            "category":"Health Services",
            "subcategory":"Nursing And Care Facility",
            "type":"Services"
        }
    ],
    "sg:phone":"+61 2 9728 6210",
    "sg:postcode":"2166",
    "sg:province":"NSW",
    "sg:tags":[
        "home"
    ],
    "wof:name":"Lansdowne Nursing Home",
    "wof:placetype":"venue"
},
  "geometry": {"coordinates":[150.94390869099999,-33.8992958069],"type":"Point"}
}