{
  "type": "Feature",
  "properties": {
    "iso:country":"AU",
    "sg:address":"Factory 2 60 Barry St",
    "sg:city":"Bayswater",
    "sg:classifiers":[
        {
            "category":"Utilities",
            "subcategory":"Electric",
            "type":"Services"
        }
    ],
    "sg:phone":"+61 3 9415 8667",
    "sg:postcode":"3153",
    "sg:province":"VIC",
    "sg:tags":[
        "electrical",
        "contractor"
    ],
    "wof:name":"Gary's Electrical",
    "wof:placetype":"venue"
},
  "geometry": {"coordinates":[145.28286743199999,-37.8480148315],"type":"Point"}
}