{
  "type": "Feature",
  "properties": {
    "iso:country":"AU",
    "sg:address":"7 Collier Rd",
    "sg:city":"Morley",
    "sg:classifiers":[
        {
            "category":"Real Estate",
            "subcategory":"Real Estate Agent",
            "type":"Services"
        }
    ],
    "sg:phone":"+61 8 9375 4444",
    "sg:postcode":"6062",
    "sg:province":"WA",
    "wof:name":"Torrens Real Estate",
    "wof:placetype":"venue"
},
  "geometry": {"coordinates":[115.902702331,-31.8950958252],"type":"Point"}
}