{
  "type": "Feature",
  "properties": {
    "addr:full":"67 Isabella St Wingham NSW 2429",
    "addr:housenumber":"67",
    "addr:postcode":"2429",
    "addr:street":"Isabella St",
    "iso:country":"AU",
    "sg:address":"67 Isabella St",
    "sg:city":"Wingham",
    "sg:classifiers":[
        {
            "category":"Real Estate",
            "subcategory":"Architect",
            "type":"Services"
        }
    ],
    "sg:phone":"+61 2 6553 5580",
    "sg:postcode":"2429",
    "sg:province":"NSW",
    "wof:name":"Austin Mcfarland Pty Ltd",
    "wof:placetype":"venue"
},
  "geometry": {"coordinates":[152.37413000000001,-31.868864],"type":"Point"}
}