{
  "type": "Feature",
  "properties": {
    "addr:full":"30 Ellesmere Rd Gymea Bay NSW 2227",
    "addr:housenumber":"30",
    "addr:postcode":"2227",
    "addr:street":"Ellesmere Rd",
    "iso:country":"AU",
    "sg:address":"30 Ellesmere Rd",
    "sg:city":"Gymea Bay",
    "sg:classifiers":[
        {
            "category":"Building & Trades",
            "subcategory":"Construction",
            "type":"Services"
        }
    ],
    "sg:phone":"+61 2 9542 8422",
    "sg:postcode":"2227",
    "sg:province":"NSW",
    "sg:tags":[
        "spouting",
        "guttering"
    ],
    "wof:name":"Pacific Leafscreen",
    "wof:placetype":"venue"
},
  "geometry": {"coordinates":[151.090454102,-34.0510444641],"type":"Point"}
}