{
  "type": "Feature",
  "properties": {
    "addr:full":"6 Creswell Rd Largs Bay SA 5016",
    "addr:housenumber":"6",
    "addr:postcode":"5016",
    "addr:street":"Creswell Rd",
    "iso:country":"AU",
    "sg:address":"6 Creswell Rd",
    "sg:city":"Largs Bay",
    "sg:classifiers":[
        {
            "category":"Building & Trades",
            "subcategory":"Construction",
            "type":"Services"
        }
    ],
    "sg:phone":"+61 8 8449 2599",
    "sg:postcode":"5016",
    "sg:province":"SA",
    "sg:tags":[
        "joinery"
    ],
    "wof:name":"Peak Joinery Pty Ltd",
    "wof:placetype":"venue"
},
  "geometry": {"coordinates":[138.50309753400001,-34.8213653564],"type":"Point"}
}