{
  "type": "Feature",
  "properties": {
    "addr:full":"5 Napier St Goonellabah NSW 2480",
    "addr:housenumber":"5",
    "addr:postcode":"2480",
    "addr:street":"Napier St",
    "iso:country":"AU",
    "sg:address":"5 Napier St",
    "sg:city":"Goonellabah",
    "sg:classifiers":[
        {
            "category":"Building & Trades",
            "subcategory":"Plumbing",
            "type":"Services"
        }
    ],
    "sg:phone":"+61 421 342 717",
    "sg:postcode":"2480",
    "sg:province":"NSW",
    "sg:tags":[
        "plumber",
        "gasfitters"
    ],
    "wof:name":"Wayne F Cox",
    "wof:placetype":"venue"
},
  "geometry": {"coordinates":[153.34927368199999,-28.8244094849],"type":"Point"}
}