{
  "type": "Feature",
  "properties": {
    "iso:country":"AU",
    "sg:address":"PO Box 296",
    "sg:city":"Wellington",
    "sg:classifiers":[
        {
            "category":"Professional",
            "subcategory":"Detective & Security Services",
            "type":"Services"
        }
    ],
    "sg:phone":"+61 419 284 877",
    "sg:postcode":"2820",
    "sg:province":"NSW",
    "sg:tags":[
        "guard",
        "patrol"
    ],
    "wof:name":"Wellington Security Services",
    "wof:placetype":"venue"
},
  "geometry": {"coordinates":[148.942962647,-32.5556411743],"type":"Point"}
}