{
  "type": "Feature",
  "properties": {
    "iso:country":"AU",
    "sg:address":"10 McCauley St",
    "sg:city":"Thirroul",
    "sg:classifiers":[
        {
            "category":"Health Services",
            "subcategory":"Optometrist",
            "type":"Services"
        }
    ],
    "sg:phone":"+61 2 4268 1044",
    "sg:postcode":"2515",
    "sg:province":"NSW",
    "wof:name":"Thirroul Optometry",
    "wof:placetype":"venue"
},
  "geometry": {"coordinates":[150.923065,-34.31636],"type":"Point"}
}