{
  "type": "Feature",
  "properties": {
    "addr:full":"8- 10 McDonald Crs Bassendean WA 6054",
    "addr:housenumber":"10",
    "addr:postcode":"6054",
    "addr:street":"8;Mcdonald Crs",
    "iso:country":"AU",
    "sg:address":"8- 10 McDonald Crs",
    "sg:city":"Bassendean",
    "sg:classifiers":[
        {
            "category":"Professional",
            "subcategory":"Engineering",
            "type":"Services"
        }
    ],
    "sg:phone":"+61 8 9279 3500",
    "sg:postcode":"6054",
    "sg:province":"WA",
    "sg:tags":[
        "civil",
        "engineer"
    ],
    "wof:name":"D. & Z. Constructions",
    "wof:placetype":"venue"
},
  "geometry": {"coordinates":[115.941513062,-31.9068336487],"type":"Point"}
}