{
  "type": "Feature",
  "properties": {
    "addr:full":"Burns St Lockington VIC 3563",
    "addr:postcode":"3563",
    "addr:street":"Burns St",
    "iso:country":"AU",
    "sg:address":"Burns St",
    "sg:city":"Lockington",
    "sg:classifiers":[
        {
            "category":"Education",
            "subcategory":"School",
            "type":"Public Place"
        }
    ],
    "sg:phone":"+61 3 5486 2474",
    "sg:postcode":"3563",
    "sg:province":"VIC",
    "sg:tags":[
        "state",
        "except",
        "nsw"
    ],
    "wof:name":"Lockington Primary School",
    "wof:placetype":"venue"
},
  "geometry": {"coordinates":[144.53770399999999,-36.268494],"type":"Point"}
}