{
  "type": "Feature",
  "properties": {
    "iso:country":"AU",
    "sg:address":"PO Box 1088",
    "sg:city":"Canning Vale DC",
    "sg:classifiers":[
        {
            "category":"Social Services",
            "subcategory":"Retirement Home",
            "type":"Services"
        }
    ],
    "sg:phone":"+61 8 9456 5688",
    "sg:postcode":"6970",
    "sg:province":"WA",
    "sg:tags":[
        "environmental",
        "consultant",
        "pollution"
    ],
    "wof:name":"Entech-Renewable Energy Technologies Pty Ltd",
    "wof:placetype":"venue"
},
  "geometry": {"coordinates":[115.920921326,-32.0658683777],"type":"Point"}
}