{
  "type": "Feature",
  "properties": {
    "iso:country":"AU",
    "sg:address":"165a Bourke St",
    "sg:city":"Melbourne",
    "sg:classifiers":[
        {
            "category":"Shopping",
            "subcategory":"Clothing, Apparel, & Fashions",
            "type":"Retail Goods"
        }
    ],
    "sg:phone":"+61 3 9662 1884",
    "sg:postcode":"3000",
    "sg:province":"VIC",
    "sg:tags":[
        "menswear"
    ],
    "wof:name":"Dom Bagnato Boutique",
    "wof:placetype":"venue"
},
  "geometry": {"coordinates":[144.968475342,-37.8128204346],"type":"Point"}
}