{
  "type": "Feature",
  "properties": {
    "addr:full":"50 Evans Rd Rooty Hill NSW 2766",
    "addr:housenumber":"50",
    "addr:postcode":"2766",
    "addr:street":"Evans Rd",
    "iso:country":"AU",
    "sg:address":"50 Evans Rd",
    "sg:city":"Rooty Hill",
    "sg:classifiers":[
        {
            "category":"Utilities",
            "subcategory":"Electric",
            "type":"Services"
        }
    ],
    "sg:phone":"+61 2 9625 4975",
    "sg:postcode":"2766",
    "sg:province":"NSW",
    "sg:tags":[
        "electrical",
        "contractor"
    ],
    "wof:name":"Sams Electrical Contracting",
    "wof:placetype":"venue"
},
  "geometry": {"coordinates":[150.84686279300001,-33.7817192078],"type":"Point"}
}