{
  "type": "Feature",
  "properties": {
    "iso:country":"AU",
    "sg:address":"33 Mabel St",
    "sg:city":"Atherton",
    "sg:classifiers":[
        {
            "category":"Home & Garden",
            "subcategory":"Building Materials",
            "type":"Retail Goods"
        }
    ],
    "sg:phone":"+61 7 4030 5300",
    "sg:postcode":"4883",
    "sg:province":"QLD",
    "sg:tags":[
        "supply"
    ],
    "wof:name":"Atherton Hardware Mitre 10",
    "wof:placetype":"venue"
},
  "geometry": {"coordinates":[145.477127075,-17.2659511566],"type":"Point"}
}