{
  "type": "Feature",
  "properties": {
    "addr:full":"3-5/ 26 Greg Chappell Drv Burleigh Heads QLD 4220",
    "addr:housenumber":"3-5 / 26",
    "addr:postcode":"4220",
    "addr:street":"Greg Chappell Drv",
    "iso:country":"AU",
    "sg:address":"3-5/ 26 Greg Chappell Drv",
    "sg:city":"Burleigh Heads",
    "sg:classifiers":[
        {
            "category":"Home & Garden",
            "subcategory":"Hardware",
            "type":"Retail Goods"
        }
    ],
    "sg:phone":"+61 7 5593 5427",
    "sg:postcode":"4220",
    "sg:province":"QLD",
    "sg:tags":[
        "supply",
        "maker",
        "cabinet"
    ],
    "wof:name":"Future Doors",
    "wof:placetype":"venue"
},
  "geometry": {"coordinates":[153.415557861,-28.1052207947],"type":"Point"}
}