{
  "type": "Feature",
  "properties": {
    "iso:country":"AU",
    "sg:address":"72 Lonsdale St",
    "sg:city":"Hamilton",
    "sg:classifiers":[
        {
            "category":"Food & Beverages",
            "subcategory":"Supermarket",
            "type":"Retail Goods"
        }
    ],
    "sg:phone":"+61 3 5572 1033",
    "sg:postcode":"3300",
    "sg:province":"VIC",
    "sg:tags":[
        "grocery",
        "store"
    ],
    "wof:name":"IGA Hamilton",
    "wof:placetype":"venue"
},
  "geometry": {"coordinates":[142.02230835,-37.7420043945],"type":"Point"}
}