{
  "type": "Feature",
  "properties": {
    "addr:full":"Riddells Rd Riddells Creek VIC 3431",
    "addr:postcode":"3431",
    "addr:street":"Riddells Rd",
    "iso:country":"AU",
    "sg:address":"Riddells Rd",
    "sg:city":"Riddells Creek",
    "sg:classifiers":[
        {
            "category":"Farming",
            "subcategory":"Fish & Marine Products",
            "type":"Manufacturing & Wholesale Goods"
        }
    ],
    "sg:phone":"+61 3 5428 6005",
    "sg:postcode":"3431",
    "sg:province":"VIC",
    "sg:tags":[
        "organic"
    ],
    "wof:name":"Organic Distribution Centre",
    "wof:placetype":"venue"
},
  "geometry": {"coordinates":[144.67208862300001,-37.4657211304],"type":"Point"}
}