{
  "type": "Feature",
  "properties": {
    "addr:full":"Unit 12/ 42 Commerce Ave Armadale WA 6112",
    "addr:housenumber":"/ 42",
    "addr:postcode":"6112",
    "addr:street":"Commerce Ave",
    "iso:country":"AU",
    "sg:address":"Unit 12/ 42 Commerce Ave",
    "sg:city":"Armadale",
    "sg:classifiers":[
        {
            "category":"Professional",
            "subcategory":"Accounting & Tax Preparation",
            "type":"Services"
        }
    ],
    "sg:phone":"+61 8 9399 4302",
    "sg:postcode":"6112",
    "sg:province":"WA",
    "sg:tags":[
        "accountant",
        "auditor"
    ],
    "wof:name":"Lancaster R.D.",
    "wof:placetype":"venue"
},
  "geometry": {"coordinates":[116.01309967,-32.156337738],"type":"Point"}
}