{
  "type": "Feature",
  "properties": {
    "addr:full":"8 Rochester Drv Mt Warren Park QLD 4207",
    "addr:housenumber":"8",
    "addr:postcode":"4207",
    "addr:street":"Rochester Drv Mt Warren",
    "iso:country":"AU",
    "sg:address":"8 Rochester Drv",
    "sg:city":"Mt Warren Park",
    "sg:classifiers":[
        {
            "category":"Health Services",
            "subcategory":"Health Practitioner",
            "type":"Services"
        }
    ],
    "sg:phone":"+61 7 3807 3033",
    "sg:postcode":"4207",
    "sg:province":"QLD",
    "sg:tags":[
        "naturopath"
    ],
    "wof:name":"Beenleigh Health Maintaining Clinic",
    "wof:placetype":"venue"
},
  "geometry": {"coordinates":[153.21244812,-27.7253818512],"type":"Point"}
}