{
  "type": "Feature",
  "properties": {
    "addr:full":"PO Box 40 Broadway NSW 2007",
    "addr:postcode":"2007",
    "iso:country":"AU",
    "sg:address":"PO Box 40",
    "sg:city":"Broadway",
    "sg:classifiers":[
        {
            "category":"Shopping",
            "subcategory":"Musical Instruments",
            "type":"Retail Goods"
        }
    ],
    "sg:phone":"+61 2 9954 7612",
    "sg:postcode":"2007",
    "sg:province":"NSW",
    "sg:tags":[
        "musician",
        "agent"
    ],
    "wof:name":"Sydney Acappella Association Inc",
    "wof:placetype":"venue"
},
  "geometry": {"coordinates":[151.199905395,-33.8842887878],"type":"Point"}
}