{
  "type": "Feature",
  "properties": {
    "iso:country":"AU",
    "sg:address":"RMB 6020",
    "sg:city":"The Ridgeway Holgate",
    "sg:classifiers":[
        {
            "category":"Home & Garden",
            "subcategory":"Building Materials",
            "type":"Retail Goods"
        }
    ],
    "sg:phone":"+61 2 4365 5342",
    "sg:postcode":"2250",
    "sg:province":"NSW",
    "sg:tags":[
        "lawn",
        "cutting",
        "maintenance"
    ],
    "wof:name":"Greener Lawnscapes",
    "wof:placetype":"venue"
},
  "geometry": {"coordinates":[151.396026611,-33.395614624],"type":"Point"}
}