{
  "type": "Feature",
  "properties": {
    "iso:country":"AU",
    "sg:address":"1224 Lytton Rd",
    "sg:city":"Brisbane",
    "sg:classifiers":[
        {
            "category":"Home & Garden",
            "subcategory":"Hardware",
            "type":"Retail Goods"
        }
    ],
    "sg:phone":"+61 7 3390 5522",
    "sg:postcode":"4000",
    "sg:province":"QLD",
    "sg:tags":[
        "generating",
        "set",
        "generator"
    ],
    "wof:name":"Lees Industries Group",
    "wof:placetype":"venue"
},
  "geometry": {"coordinates":[153.041915894,-27.4789066315],"type":"Point"}
}