{
  "type": "Feature",
  "properties": {
    "addr:full":"6 Kilvington Drv Emerald VIC 3782",
    "addr:housenumber":"6",
    "addr:postcode":"3782",
    "addr:street":"Kilvington Drv",
    "iso:country":"AU",
    "sg:address":"6 Kilvington Drv",
    "sg:city":"Emerald",
    "sg:classifiers":[
        {
            "category":"Shopping",
            "subcategory":"Crafts & Fabrics",
            "type":"Retail Goods"
        }
    ],
    "sg:phone":"+61 3 5968 4498",
    "sg:postcode":"3782",
    "sg:province":"VIC",
    "sg:tags":[
        "draper"
    ],
    "wof:name":"Emerald Village Drapery",
    "wof:placetype":"venue"
},
  "geometry": {"coordinates":[145.440628,-37.932812],"type":"Point"}
}