{
  "type": "Feature",
  "properties": {
    "addr:full":"Factory 6 399/401 Old Geelong Rd Hoppers Crossing VIC 3029",
    "addr:housenumber":"399 / 401",
    "addr:postcode":"3029",
    "addr:street":"Old Geelong Rd",
    "iso:country":"AU",
    "sg:address":"Factory 6 399/401 Old Geelong Rd",
    "sg:city":"Hoppers Crossing",
    "sg:classifiers":[
        {
            "category":"Home & Garden",
            "subcategory":"Building Materials",
            "type":"Retail Goods"
        }
    ],
    "sg:phone":"+61 438 698 688",
    "sg:postcode":"3029",
    "sg:province":"VIC",
    "sg:tags":[
        "shutter",
        "roller",
        "grille"
    ],
    "wof:name":"All Seasons Roller Shutters",
    "wof:placetype":"venue"
},
  "geometry": {"coordinates":[144.729446,-37.86953],"type":"Point"}
}