{
  "type": "Feature",
  "properties": {
    "addr:full":"11 Hardy Ave Ocean Shores NSW 2483",
    "addr:housenumber":"11",
    "addr:postcode":"2483",
    "addr:street":"Hardy Ave",
    "iso:country":"AU",
    "sg:address":"11 Hardy Ave",
    "sg:city":"Ocean Shores",
    "sg:classifiers":[
        {
            "category":"Building & Trades",
            "subcategory":"Landscaping Services",
            "type":"Services"
        }
    ],
    "sg:phone":"+61 2 6680 2607",
    "sg:postcode":"2483",
    "sg:province":"NSW",
    "sg:tags":[
        "designer",
        "landscape",
        "contractor"
    ],
    "wof:name":"New Horticulture Pty Ltd",
    "wof:placetype":"venue"
},
  "geometry": {"coordinates":[153.542800903,-28.4909534454],"type":"Point"}
}