{
  "type": "Feature",
  "properties": {
    "iso:country":"AU",
    "sg:address":"1/ 39 Morts Rd",
    "sg:city":"Mortdale",
    "sg:classifiers":[
        {
            "category":"Health Services",
            "subcategory":"Dentist",
            "type":"Services"
        }
    ],
    "sg:phone":"+61 2 9580 2500",
    "sg:postcode":"2223",
    "sg:province":"NSW",
    "wof:name":"Aslan R A & Associates",
    "wof:placetype":"venue"
},
  "geometry": {"coordinates":[151.078735352,-33.969165802],"type":"Point"}
}