{
  "type": "Feature",
  "properties": {
    "addr:full":"6 Pall Mall Ave Currumbin QLD 4223",
    "addr:housenumber":"6",
    "addr:postcode":"4223",
    "addr:street":"Pall Mall Ave",
    "iso:country":"AU",
    "sg:address":"6 Pall Mall Ave",
    "sg:city":"Currumbin",
    "sg:phone":"+61 7 5525 6792",
    "sg:postcode":"4223",
    "sg:province":"QLD",
    "wof:name":"Horizon Tanks",
    "wof:placetype":"venue"
},
  "geometry": {"coordinates":[153.481887817,-28.1355953217],"type":"Point"}
}