{
  "type": "Feature",
  "properties": {
    "addr:full":"Strickland Drv Dalwallinu WA 6609",
    "addr:postcode":"6609",
    "addr:street":"Strickland Drv",
    "iso:country":"AU",
    "sg:address":"Strickland Drv",
    "sg:city":"Dalwallinu",
    "sg:classifiers":[
        {
            "category":"Professional",
            "subcategory":"Art Services",
            "type":"Services"
        }
    ],
    "sg:phone":"+61 8 9661 1058",
    "sg:postcode":"6609",
    "sg:province":"WA",
    "sg:tags":[
        "decorator",
        "painter"
    ],
    "wof:name":"Dutton T J & M F",
    "wof:placetype":"venue"
},
  "geometry": {"coordinates":[116.65573120099999,-30.2780857086],"type":"Point"}
}