{
  "type": "Feature",
  "properties": {
    "addr:full":"32 Industrial Drv Mayfield NSW 2304",
    "addr:housenumber":"32",
    "addr:postcode":"2304",
    "addr:street":"Industrial Drv",
    "iso:country":"AU",
    "sg:address":"32 Industrial Drv",
    "sg:city":"Mayfield",
    "sg:classifiers":[
        {
            "category":"Conference Center",
            "type":"Public Place"
        }
    ],
    "sg:phone":"+61 2 4903 6100",
    "sg:postcode":"2304",
    "sg:province":"NSW",
    "sg:tags":[
        "venue",
        "convention"
    ],
    "wof:name":"Phoenix Sports",
    "wof:placetype":"venue"
},
  "geometry": {"coordinates":[151.744598389,-32.8915786743],"type":"Point"}
}