{
  "type": "Feature",
  "properties": {
    "addr:full":"3 Freight Drv Somerton VIC 3062",
    "addr:postcode":"3062",
    "addr:street":"Freight Drv",
    "iso:country":"AU",
    "sg:address":"3 Freight Drv",
    "sg:city":"Somerton",
    "sg:classifiers":[
        {
            "category":"Shopping",
            "subcategory":"Computers & Home Electronics",
            "type":"Retail Goods"
        }
    ],
    "sg:phone":"+61 3 9305 2200",
    "sg:postcode":"3062",
    "sg:province":"VIC",
    "sg:tags":[
        "global",
        "positioning",
        "system"
    ],
    "sg:website":"http://www.phonespares.com",
    "wof:name":"One X Phone Spares",
    "wof:placetype":"venue"
},
  "geometry": {"coordinates":[144.963378906,-37.6446990967],"type":"Point"}
}