{
  "type": "Feature",
  "properties": {
    "addr:full":"607 Lutwyche Rd Lutwyche QLD 4030",
    "addr:housenumber":"607",
    "addr:postcode":"4030",
    "addr:street":"Lutwyche Rd",
    "iso:country":"AU",
    "sg:address":"607 Lutwyche Rd",
    "sg:city":"Lutwyche",
    "sg:classifiers":[
        {
            "category":"Shopping",
            "subcategory":"Mobile Phones",
            "type":"Retail Goods"
        }
    ],
    "sg:phone":"+61 7 3357 6429",
    "sg:postcode":"4030",
    "sg:province":"QLD",
    "sg:tags":[
        "telephone",
        "accessory"
    ],
    "wof:name":"Denning Car Radio",
    "wof:placetype":"venue"
},
  "geometry": {"coordinates":[153.03509500000001,-27.419409],"type":"Point"}
}