{
  "type": "Feature",
  "properties": {
    "addr:full":"115 Fitzmaurice St Wagga Wagga NSW 2650",
    "addr:housenumber":"115",
    "addr:postcode":"2650",
    "addr:street":"Fitzmaurice St",
    "iso:country":"AU",
    "sg:address":"115 Fitzmaurice St",
    "sg:city":"Wagga Wagga",
    "sg:classifiers":[
        {
            "category":"Retail",
            "subcategory":"Repair Shop",
            "type":"Services"
        }
    ],
    "sg:phone":"+61 2 6921 4978",
    "sg:postcode":"2650",
    "sg:province":"NSW",
    "sg:tags":[
        "restorer",
        "repairer",
        "carpet"
    ],
    "wof:name":"Riverina AAA Carpet Cleaning",
    "wof:placetype":"venue"
},
  "geometry": {"coordinates":[147.36929321299999,-35.104549408],"type":"Point"}
}