{
  "type": "Feature",
  "properties": {
    "addr:full":"336 Churchill Ave Subiaco WA 6008",
    "addr:housenumber":"336",
    "addr:postcode":"6008",
    "addr:street":"Churchill Ave",
    "iso:country":"AU",
    "sg:address":"336 Churchill Ave",
    "sg:city":"Subiaco",
    "sg:classifiers":[
        {
            "category":"Travel",
            "subcategory":"Travel Agent",
            "type":"Entertainment"
        }
    ],
    "sg:phone":"+61 8 9382 4255",
    "sg:postcode":"6008",
    "sg:province":"WA",
    "sg:tags":[
        "consultant"
    ],
    "wof:name":"Brian Bedwells Business Travel",
    "wof:placetype":"venue"
},
  "geometry": {"coordinates":[115.824150085,-31.9477558136],"type":"Point"}
}