{
  "type": "Feature",
  "properties": {
    "addr:full":"655 Freemans Drv Cooranbong NSW 2265",
    "addr:housenumber":"655",
    "addr:postcode":"2265",
    "addr:street":"Freemans Drv",
    "iso:country":"AU",
    "sg:address":"655 Freemans Drv",
    "sg:city":"Cooranbong",
    "sg:classifiers":[
        {
            "category":"Building & Trades",
            "subcategory":"Construction",
            "type":"Services"
        }
    ],
    "sg:phone":"+61 2 4977 2520",
    "sg:postcode":"2265",
    "sg:province":"NSW",
    "sg:tags":[
        "contractor"
    ],
    "wof:name":"Bamborough D M",
    "wof:placetype":"venue"
},
  "geometry": {"coordinates":[151.469742,-33.064804],"type":"Point"}
}