{
  "type": "Feature",
  "properties": {
    "iso:country":"AU",
    "sg:address":"7 Second Ave",
    "sg:city":"Sandgate",
    "sg:classifiers":[
        {
            "category":"Real Estate",
            "subcategory":"Real Estate Agent",
            "type":"Services"
        }
    ],
    "sg:phone":"+61 7 3269 1555",
    "sg:postcode":"4017",
    "sg:province":"QLD",
    "wof:name":"2nd Avenue Realty",
    "wof:placetype":"venue"
},
  "geometry": {"coordinates":[153.07081604000001,-27.3201293945],"type":"Point"}
}