{
  "type": "Feature",
  "properties": {
    "addr:full":"15 Hills Rd St Helens TAS 7216",
    "addr:housenumber":"15",
    "addr:postcode":"7216",
    "addr:street":"Hills Rd",
    "iso:country":"AU",
    "sg:address":"15 Hills Rd",
    "sg:city":"St Helens",
    "sg:classifiers":[
        {
            "category":"Taxi",
            "type":"Transportation"
        }
    ],
    "sg:phone":"+61 3 6376 2999",
    "sg:postcode":"7216",
    "sg:province":"TAS",
    "sg:tags":[
        "cab"
    ],
    "wof:name":"East Coast Taxis",
    "wof:placetype":"venue"
},
  "geometry": {"coordinates":[148.214035,-41.316929],"type":"Point"}
}