{
  "type": "Feature",
  "properties": {
    "iso:country":"AU",
    "sg:address":"Suite 5 Cnr Ferntree Gully & Jells Rds",
    "sg:city":"Wheelers Hill",
    "sg:classifiers":[
        {
            "category":"Personal",
            "subcategory":"Beauty Salon",
            "type":"Services"
        }
    ],
    "sg:phone":"+61 3 9562 2280",
    "sg:postcode":"3150",
    "sg:province":"VIC",
    "wof:name":"Massage Natural Therapy & Beauty Care Centre",
    "wof:placetype":"venue"
},
  "geometry": {"coordinates":[145.189056397,-37.9067306519],"type":"Point"}
}