{
  "type": "Feature",
  "properties": {
    "addr:full":"209 Cathederal Ave Brigadoon WA 6069",
    "addr:housenumber":"209",
    "addr:postcode":"6069",
    "addr:street":"Cathederal Ave",
    "iso:country":"AU",
    "sg:address":"209 Cathederal Ave",
    "sg:city":"Brigadoon",
    "sg:classifiers":[
        {
            "category":"Health Services",
            "subcategory":"Health Practitioner",
            "type":"Services"
        }
    ],
    "sg:phone":"+61 412 994 590",
    "sg:postcode":"6069",
    "sg:province":"WA",
    "sg:tags":[
        "physiotherapist"
    ],
    "wof:name":"Mantu Joanna Physiotherapist",
    "wof:placetype":"venue"
},
  "geometry": {"coordinates":[116.048530579,-31.7834224701],"type":"Point"}
}