{
  "type": "Feature",
  "properties": {
    "addr:full":"88 Bakers Rd Coburg North VIC 3058",
    "addr:housenumber":"88",
    "addr:postcode":"3058",
    "addr:street":"Bakers Rd",
    "iso:country":"AU",
    "sg:address":"88 Bakers Rd",
    "sg:city":"Coburg North",
    "sg:classifiers":[
        {
            "category":"Taxi",
            "type":"Transportation"
        }
    ],
    "sg:phone":"+61 3 9354 8217",
    "sg:postcode":"3058",
    "sg:province":"VIC",
    "sg:tags":[
        "cab"
    ],
    "wof:name":"Capital City Cabs",
    "wof:placetype":"venue"
},
  "geometry": {"coordinates":[144.95396423299999,-37.7261734009],"type":"Point"}
}