{
  "type": "Feature",
  "properties": {
    "iso:country":"AU",
    "sg:address":"2 Railway St",
    "sg:city":"Pennant Hills",
    "sg:classifiers":[
        {
            "category":"Shopping",
            "subcategory":"Crafts & Fabrics",
            "type":"Retail Goods"
        }
    ],
    "sg:phone":"+61 2 9980 8966",
    "sg:postcode":"2120",
    "sg:province":"NSW",
    "sg:tags":[
        "quilting"
    ],
    "wof:name":"Craft Depot",
    "wof:placetype":"venue"
},
  "geometry": {"coordinates":[151.07261657699999,-33.7382926941],"type":"Point"}
}