{
  "type": "Feature",
  "properties": {
    "addr:full":"13 Nioka Pl Cooma NSW 2630",
    "addr:housenumber":"13",
    "addr:postcode":"2630",
    "addr:street":"Nioka Pl",
    "iso:country":"AU",
    "sg:address":"13 Nioka Pl",
    "sg:city":"Cooma",
    "sg:classifiers":[
        {
            "category":"Building & Trades",
            "subcategory":"Construction",
            "type":"Services"
        }
    ],
    "sg:phone":"+61 2 6452 5930",
    "sg:postcode":"2630",
    "sg:province":"NSW",
    "sg:tags":[
        "joiner",
        "carpenter"
    ],
    "wof:name":"Michael Byrne Builder",
    "wof:placetype":"venue"
},
  "geometry": {"coordinates":[149.133010864,-36.2133178711],"type":"Point"}
}