{
  "type": "Feature",
  "properties": {
    "addr:full":"35 Milton St Mackay QLD 4740",
    "addr:housenumber":"35",
    "addr:postcode":"4740",
    "addr:street":"Milton St",
    "iso:country":"AU",
    "sg:address":"35 Milton St",
    "sg:city":"Mackay",
    "sg:classifiers":[
        {
            "category":"Health Services",
            "subcategory":"Doctor",
            "type":"Services"
        }
    ],
    "sg:phone":"+61 1300 785 533",
    "sg:postcode":"4740",
    "sg:province":"QLD",
    "sg:tags":[
        "medical",
        "practitioner"
    ],
    "wof:name":"Skin Alert Skin Cancer Clinics",
    "wof:placetype":"venue"
},
  "geometry": {"coordinates":[149.17536899999999,-21.160938],"type":"Point"}
}