{
  "type": "Feature",
  "properties": {
    "addr:full":"2 McPherson Rd Tuggerah NSW 2259",
    "addr:housenumber":"2",
    "addr:postcode":"2259",
    "addr:street":"Mcpherson Rd",
    "iso:country":"AU",
    "sg:address":"2 McPherson Rd",
    "sg:city":"Tuggerah",
    "sg:classifiers":[
        {
            "category":"Home & Garden",
            "subcategory":"Building Materials",
            "type":"Retail Goods"
        }
    ],
    "sg:phone":"+61 1300 306 223",
    "sg:postcode":"2259",
    "sg:province":"NSW",
    "sg:tags":[
        "plaster",
        "plasterboard",
        "supply"
    ],
    "wof:name":"Australian Plasterboard Company",
    "wof:placetype":"venue"
},
  "geometry": {"coordinates":[151.421676636,-33.2911376953],"type":"Point"}
}