{
  "type": "Feature",
  "properties": {
    "addr:full":"178 Kingaroy St Kingaroy QLD 4610",
    "addr:housenumber":"178",
    "addr:postcode":"4610",
    "addr:street":"Kingaroy St",
    "iso:country":"AU",
    "sg:address":"178 Kingaroy St",
    "sg:city":"Kingaroy",
    "sg:classifiers":[
        {
            "category":"Real Estate",
            "subcategory":"Real Estate Agent",
            "type":"Services"
        }
    ],
    "sg:phone":"+61 7 4163 6006",
    "sg:postcode":"4610",
    "sg:province":"QLD",
    "wof:name":"Real Way Property Consultants",
    "wof:placetype":"venue"
},
  "geometry": {"coordinates":[151.83946227999999,-26.5406799316],"type":"Point"}
}