{
  "type": "Feature",
  "properties": {
    "iso:country":"AU",
    "sg:address":"48-52 Sydenham Rd",
    "sg:city":"Marrickville",
    "sg:classifiers":[
        {
            "category":"Wholesale",
            "subcategory":"Painting Supplies",
            "type":"Manufacturing & Wholesale Goods"
        }
    ],
    "sg:phone":"+61 2 9565 2222",
    "sg:postcode":"2204",
    "sg:province":"NSW",
    "sg:tags":[
        "wholesaler",
        "paint",
        "mfrs"
    ],
    "wof:name":"Milhaus Australia Pty Ltd",
    "wof:placetype":"venue"
},
  "geometry": {"coordinates":[151.164658,-33.911671],"type":"Point"}
}