{
  "type": "Feature",
  "properties": {
    "addr:full":"10a Raworth Ave Morpeth NSW 2321",
    "addr:housenumber":"10a",
    "addr:postcode":"2321",
    "addr:street":"Raworth Ave",
    "iso:country":"AU",
    "sg:address":"10a Raworth Ave",
    "sg:city":"Morpeth",
    "sg:classifiers":[
        {
            "category":"Personal",
            "subcategory":"Massage",
            "type":"Services"
        }
    ],
    "sg:phone":"+61 2 4934 3322",
    "sg:postcode":"2321",
    "sg:province":"NSW",
    "sg:tags":[
        "therapy"
    ],
    "wof:name":"Wallin Margaret",
    "wof:placetype":"venue"
},
  "geometry": {"coordinates":[151.613845825,-32.7274208069],"type":"Point"}
}