{
  "type": "Feature",
  "properties": {
    "addr:full":"42 Stimson St Smithfield NSW 2164",
    "addr:housenumber":"42",
    "addr:postcode":"2164",
    "addr:street":"Stimson St",
    "iso:country":"AU",
    "sg:address":"42 Stimson St",
    "sg:city":"Smithfield",
    "sg:classifiers":[
        {
            "category":"Building & Trades",
            "subcategory":"Plumbing",
            "type":"Services"
        }
    ],
    "sg:phone":"+61 2 9604 4191",
    "sg:postcode":"2164",
    "sg:province":"NSW",
    "sg:tags":[
        "plumber",
        "gasfitters"
    ],
    "wof:name":"Storey K J",
    "wof:placetype":"venue"
},
  "geometry": {"coordinates":[150.943817139,-33.8560295105],"type":"Point"}
}