{
  "type": "Feature",
  "properties": {
    "addr:full":"24 Oroya St Boulder WA 6432",
    "addr:housenumber":"24",
    "addr:postcode":"6432",
    "addr:street":"Oroya St",
    "iso:country":"AU",
    "sg:address":"24 Oroya St",
    "sg:city":"Boulder",
    "sg:classifiers":[
        {
            "category":"Building & Trades",
            "subcategory":"Construction",
            "type":"Services"
        }
    ],
    "sg:phone":"+61 419 941 909",
    "sg:postcode":"6432",
    "sg:province":"WA",
    "sg:tags":[
        "earth",
        "excavating",
        "moving",
        "contractor"
    ],
    "wof:name":"Miles Contracting",
    "wof:placetype":"venue"
},
  "geometry": {"coordinates":[121.498771667,-30.7917251587],"type":"Point"}
}