{
  "type": "Feature",
  "properties": {
    "iso:country":"AU",
    "sg:address":"Level 1, 55 Kembla St",
    "sg:city":"Wollongong",
    "sg:classifiers":[
        {
            "category":"Insurance",
            "subcategory":"Hazard Insurance",
            "type":"Services"
        }
    ],
    "sg:phone":"+61 2 9806 0922",
    "sg:postcode":"2500",
    "sg:province":"NSW",
    "sg:tags":[
        "fire",
        "accident",
        "marine"
    ],
    "wof:name":"Wesfarmers Federation Insurance",
    "wof:placetype":"venue"
},
  "geometry": {"coordinates":[150.897934,-34.423855],"type":"Point"}
}