{
  "type": "Feature",
  "properties": {
    "addr:full":"Lexington Pde Adamstown Heights NSW 2289",
    "addr:postcode":"2289",
    "addr:street":"Lexington",
    "iso:country":"AU",
    "sg:address":"Lexington Pde",
    "sg:city":"Adamstown Heights",
    "sg:classifiers":[
        {
            "category":"Education",
            "subcategory":"School",
            "type":"Public Place"
        }
    ],
    "sg:phone":"+61 2 4943 3044",
    "sg:postcode":"2289",
    "sg:province":"NSW",
    "sg:tags":[
        "state",
        "-",
        "nsw"
    ],
    "wof:name":"Kotara High School",
    "wof:placetype":"venue"
},
  "geometry": {"coordinates":[151.708053589,-32.9465484619],"type":"Point"}
}