{
  "type": "Feature",
  "properties": {
    "iso:country":"AU",
    "sg:address":"90 Main St",
    "sg:city":"Romsey",
    "sg:classifiers":[
        {
            "category":"Travel",
            "subcategory":"Hotels & Motels",
            "type":"Entertainment"
        }
    ],
    "sg:phone":"+61 3 5429 5260",
    "sg:postcode":"3434",
    "sg:province":"VIC",
    "sg:tags":[
        "accommodation"
    ],
    "wof:name":"Romsey Hotel",
    "wof:placetype":"venue"
},
  "geometry": {"coordinates":[144.74334716800001,-37.3505592346],"type":"Point"}
}