{
  "type": "Feature",
  "properties": {
    "addr:full":"155 Greville St Prahran VIC 3181",
    "addr:housenumber":"155",
    "addr:postcode":"3181",
    "addr:street":"Greville St",
    "iso:country":"AU",
    "sg:address":"155 Greville St",
    "sg:city":"Prahran",
    "sg:classifiers":[
        {
            "category":"Shopping",
            "subcategory":"Clothing, Apparel, & Fashions",
            "type":"Retail Goods"
        }
    ],
    "sg:phone":"+61 3 9521 4470",
    "sg:postcode":"3181",
    "sg:province":"VIC",
    "sg:tags":[
        "boutique"
    ],
    "wof:name":"Schatzi",
    "wof:placetype":"venue"
},
  "geometry": {"coordinates":[144.99180602999999,-37.8491859436],"type":"Point"}
}