{
  "type": "Feature",
  "properties": {
    "iso:country":"AU",
    "sg:address":"1 Levanswell Rd",
    "sg:city":"Moorabbin",
    "sg:classifiers":[
        {
            "category":"Professional",
            "subcategory":"Printing & Photocopies",
            "type":"Services"
        }
    ],
    "sg:phone":"+61 3 9532 0541",
    "sg:postcode":"3189",
    "sg:province":"VIC",
    "sg:tags":[
        "rubber",
        "stamp",
        "metal"
    ],
    "wof:name":"Australia Wide Rubber Stamps",
    "wof:placetype":"venue"
},
  "geometry": {"coordinates":[145.060150147,-37.9439506531],"type":"Point"}
}