{
  "type": "Feature",
  "properties": {
    "addr:full":"Unit 3, 22- 28 Melbourne Rd North Adelaide SA 5006",
    "addr:housenumber":"22 28",
    "addr:postcode":"5006",
    "addr:street":"Melbourne Rd",
    "iso:country":"AU",
    "sg:address":"Unit 3, 22- 28 Melbourne Rd",
    "sg:city":"North Adelaide",
    "sg:classifiers":[
        {
            "category":"Utilities",
            "subcategory":"Cable",
            "type":"Services"
        }
    ],
    "sg:phone":"+61 1300 737 726",
    "sg:postcode":"5006",
    "sg:province":"SA",
    "sg:tags":[
        "headset"
    ],
    "wof:name":"Australian Business Telephone Company",
    "wof:placetype":"venue"
},
  "geometry": {"coordinates":[138.60476684599999,-34.9090423584],"type":"Point"}
}