{
  "type": "Feature",
  "properties": {
    "iso:country":"AU",
    "sg:address":"39 Maxwell Rd",
    "sg:city":"Hackham West",
    "sg:classifiers":[
        {
            "category":"Communications",
            "type":"Services"
        }
    ],
    "sg:phone":"+61 411 118 067",
    "sg:postcode":"5163",
    "sg:province":"SA",
    "sg:tags":[
        "public",
        "system",
        "address"
    ],
    "wof:name":"Scaresbrook D",
    "wof:placetype":"venue"
},
  "geometry": {"coordinates":[138.51881408700001,-35.1378135681],"type":"Point"}
}