{
  "type": "Feature",
  "properties": {
    "addr:full":"Suite 6,level 1/ 322 Bourke St Taylor Square NSW 2010",
    "addr:housenumber":"/ 322",
    "addr:postcode":"2010",
    "addr:street":"Bourke St Taylor Square",
    "iso:country":"AU",
    "sg:address":"Suite 6,level 1/ 322 Bourke St",
    "sg:city":"Taylor Square",
    "sg:classifiers":[
        {
            "category":"Professional",
            "subcategory":"Employment Agencies",
            "type":"Services"
        }
    ],
    "sg:phone":"+61 2 9361 4136",
    "sg:postcode":"2010",
    "sg:province":"NSW",
    "wof:name":"Grant James Consulting",
    "wof:placetype":"venue"
},
  "geometry": {"coordinates":[151.216598511,-33.8821296692],"type":"Point"}
}