{
  "type": "Feature",
  "properties": {
    "addr:full":"PO Box 1933 Byron Bay NSW 2481",
    "addr:postcode":"2481",
    "iso:country":"AU",
    "sg:address":"PO Box 1933",
    "sg:city":"Byron Bay",
    "sg:classifiers":[
        {
            "category":"Social Services",
            "subcategory":"Retirement Home",
            "type":"Services"
        }
    ],
    "sg:phone":"+61 2 6685 7198",
    "sg:postcode":"2481",
    "sg:province":"NSW",
    "sg:tags":[
        "environmental",
        "consultant",
        "pollution"
    ],
    "wof:name":"Sustainable Futures Australia",
    "wof:placetype":"venue"
},
  "geometry": {"coordinates":[153.612823486,-28.6468906403],"type":"Point"}
}