{
  "type": "Feature",
  "properties": {
    "addr:full":"213 Clovelly Rd Clovelly NSW 2031",
    "addr:housenumber":"213",
    "addr:postcode":"2031",
    "addr:street":"Clovelly Rd",
    "iso:country":"AU",
    "sg:address":"213 Clovelly Rd",
    "sg:city":"Clovelly",
    "sg:classifiers":[
        {
            "category":"Health Services",
            "subcategory":"Optometrist",
            "type":"Services"
        }
    ],
    "sg:phone":"+61 2 9665 3344",
    "sg:postcode":"2031",
    "sg:province":"NSW",
    "wof:name":"Clovelly Optical",
    "wof:placetype":"venue"
},
  "geometry": {"coordinates":[151.25396728499999,-33.9113044739],"type":"Point"}
}