{
  "type": "Feature",
  "properties": {
    "iso:country":"AU",
    "sg:address":"79 Stewart Rd",
    "sg:city":"Ashgrove",
    "sg:classifiers":[
        {
            "category":"Autos & Motor Vehicles",
            "subcategory":"Boat Sales",
            "type":"Retail Goods"
        }
    ],
    "sg:phone":"+61 7 3366 4041",
    "sg:postcode":"4060",
    "sg:province":"QLD",
    "sg:tags":[
        "machine",
        "dishwashing"
    ],
    "sg:website":"http://www.stocksretravision.com.au",
    "wof:name":"Stocks Retravision",
    "wof:placetype":"venue"
},
  "geometry": {"coordinates":[152.990325928,-27.441493988],"type":"Point"}
}