{
  "type": "Feature",
  "properties": {
    "addr:full":"163 Sydney Rd Brunswick VIC 3056",
    "addr:housenumber":"163",
    "addr:postcode":"3056",
    "addr:street":"Sydney Rd",
    "iso:country":"AU",
    "sg:address":"163 Sydney Rd",
    "sg:city":"Brunswick",
    "sg:classifiers":[
        {
            "category":"Restaurant",
            "type":"Food & Drink"
        }
    ],
    "sg:phone":"+61 3 9387 6914",
    "sg:postcode":"3056",
    "sg:province":"VIC",
    "wof:name":"Alasya Restaurant",
    "wof:placetype":"venue"
},
  "geometry": {"coordinates":[144.96089172399999,-37.7733573914],"type":"Point"}
}