{
  "type": "Feature",
  "properties": {
    "iso:country":"AU",
    "sg:address":"Burrum St",
    "sg:city":"Howard",
    "sg:classifiers":[
        {
            "category":"Museum",
            "type":"Entertainment"
        }
    ],
    "sg:phone":"+61 7 4129 0677",
    "sg:postcode":"4659",
    "sg:province":"QLD",
    "wof:name":"Burrum District Museum",
    "wof:placetype":"venue"
},
  "geometry": {"coordinates":[152.561737,-25.318697],"type":"Point"}
}