{
  "type": "Feature",
  "properties": {
    "iso:country":"AU",
    "sg:address":"125 Military Rd",
    "sg:city":"Neutral Bay",
    "sg:classifiers":[
        {
            "category":"Restaurant",
            "type":"Food & Drink"
        }
    ],
    "sg:phone":"+61 2 8969 6219",
    "sg:postcode":"2089",
    "sg:province":"NSW",
    "wof:name":"Basil & Mint",
    "wof:placetype":"venue"
},
  "geometry": {"coordinates":[151.22088623100001,-33.8311042786],"type":"Point"}
}