{
  "type": "Feature",
  "properties": {
    "iso:country":"AU",
    "sg:address":"85 Governor Macquarie Drv",
    "sg:city":"Chipping Norton",
    "sg:classifiers":[
        {
            "category":"Building & Trades",
            "subcategory":"Construction",
            "type":"Services"
        }
    ],
    "sg:phone":"+61 1800 004 964",
    "sg:postcode":"2170",
    "sg:province":"NSW",
    "sg:tags":[
        "industrial",
        "commercial",
        "air conditioning"
    ],
    "wof:name":"Colorworks Mobile Painting",
    "wof:placetype":"venue"
},
  "geometry": {"coordinates":[150.96107482900001,-33.9156951904],"type":"Point"}
}