{
  "type": "Feature",
  "properties": {
    "iso:country":"AU",
    "sg:address":"Shop 2001",
    "sg:city":"C Westfield Marion Shopping Centre Oaklands P",
    "sg:classifiers":[
        {
            "category":"Recreation",
            "type":"Entertainment"
        }
    ],
    "sg:phone":"+61 8 8296 7700",
    "sg:postcode":"5046",
    "sg:province":"SA",
    "sg:tags":[
        "supply",
        "outdoor",
        "adventure",
        "activity"
    ],
    "wof:name":"Mitchells Adventure",
    "wof:placetype":"venue"
},
  "geometry": {"coordinates":[138.53732299999999,-35.002277],"type":"Point"}
}