{
  "type": "Feature",
  "properties": {
    "iso:country":"AU",
    "sg:address":"7 Kent St",
    "sg:city":"Rockingham",
    "sg:classifiers":[
        {
            "category":"Professional",
            "subcategory":"Computer Services",
            "type":"Services"
        }
    ],
    "sg:phone":"+61 8 9591 3733",
    "sg:postcode":"6168",
    "sg:province":"WA",
    "sg:tags":[
        "repairs",
        "upgrade",
        "equipment"
    ],
    "wof:name":"Computer Ambulance Services",
    "wof:placetype":"venue"
},
  "geometry": {"coordinates":[115.730453,-32.276665],"type":"Point"}
}