{
  "type": "Feature",
  "properties": {
    "addr:full":"148 Ogilive Ave Echuca VIC 3564",
    "addr:housenumber":"148",
    "addr:postcode":"3564",
    "addr:street":"Ogilive Ave",
    "iso:country":"AU",
    "sg:address":"148 Ogilive Ave",
    "sg:city":"Echuca",
    "sg:classifiers":[
        {
            "category":"Communications",
            "subcategory":"Film & Video Production",
            "type":"Services"
        }
    ],
    "sg:phone":"+61 3 5482 1618",
    "sg:postcode":"3564",
    "sg:province":"VIC",
    "sg:tags":[
        "colour",
        "pigment"
    ],
    "wof:name":"A Ability Building Chemicals Co",
    "wof:placetype":"venue"
},
  "geometry": {"coordinates":[144.74827575699999,-36.1404953003],"type":"Point"}
}