{
  "type": "Feature",
  "properties": {
    "addr:full":"11 Sleigh Pl Hume ACT 2620",
    "addr:housenumber":"11",
    "addr:postcode":"2620",
    "addr:street":"Sleigh Pl",
    "iso:country":"AU",
    "sg:address":"11 Sleigh Pl",
    "sg:city":"Hume",
    "sg:classifiers":[
        {
            "category":"Utilities",
            "subcategory":"Recycling",
            "type":"Services"
        }
    ],
    "sg:phone":"+61 2 6260 1727",
    "sg:postcode":"2620",
    "sg:province":"ACT",
    "wof:name":"Visy Recycling",
    "wof:placetype":"venue"
},
  "geometry": {"coordinates":[149.169845581,-35.389793396],"type":"Point"}
}