{
  "type": "Feature",
  "properties": {
    "iso:country":"AU",
    "sg:address":"176 Clayton Rd",
    "sg:city":"Clayton",
    "sg:classifiers":[
        {
            "category":"Fast Food",
            "type":"Food & Drink"
        }
    ],
    "sg:phone":"+61 3 9544 0520",
    "sg:postcode":"3168",
    "sg:province":"VIC",
    "sg:tags":[
        "away",
        "take"
    ],
    "wof:name":"Cremona Pizza",
    "wof:placetype":"venue"
},
  "geometry": {"coordinates":[145.121856689,-37.914932251],"type":"Point"}
}