{
  "type": "Feature",
  "properties": {
    "addr:full":"55 Adderton Rd Telopea NSW 2117",
    "addr:housenumber":"55",
    "addr:postcode":"2117",
    "addr:street":"Adderton Rd",
    "iso:country":"AU",
    "sg:address":"55 Adderton Rd",
    "sg:city":"Telopea",
    "sg:classifiers":[
        {
            "category":"Food & Beverages",
            "subcategory":"Liquor & Beverages",
            "type":"Retail Goods"
        }
    ],
    "sg:phone":"+61 2 9871 4295",
    "sg:postcode":"2117",
    "sg:province":"NSW",
    "sg:tags":[
        "store"
    ],
    "wof:name":"Telopea Liquor Store Pty Ltd",
    "wof:placetype":"venue"
},
  "geometry": {"coordinates":[151.04124450699999,-33.7936096191],"type":"Point"}
}