{
  "type": "Feature",
  "properties": {
    "addr:full":"Bay 5 211 High St Wauchope NSW 2446",
    "addr:housenumber":"211",
    "addr:postcode":"2446",
    "addr:street":"High St",
    "iso:country":"AU",
    "sg:address":"Bay 5 211 High St",
    "sg:city":"Wauchope",
    "sg:classifiers":[
        {
            "category":"Building & Trades",
            "subcategory":"Construction",
            "type":"Services"
        }
    ],
    "sg:phone":"+61 412 804 204",
    "sg:postcode":"2446",
    "sg:province":"NSW",
    "sg:tags":[
        "fencing",
        "contractor"
    ],
    "wof:name":"Country Style Concrete Post & Rail Fencing",
    "wof:placetype":"venue"
},
  "geometry": {"coordinates":[152.71975699999999,-31.46628],"type":"Point"}
}