{
  "type": "Feature",
  "properties": {
    "iso:country":"AU",
    "sg:address":"16 View St",
    "sg:city":"Essendon",
    "sg:classifiers":[
        {
            "category":"Banks & Credit Unions",
            "subcategory":"Financial Services",
            "type":"Services"
        }
    ],
    "sg:phone":"+61 412 549 141",
    "sg:postcode":"3040",
    "sg:province":"VIC",
    "sg:tags":[
        "loan",
        "finance",
        "mortgage"
    ],
    "wof:name":"Hales Darren",
    "wof:placetype":"venue"
},
  "geometry": {"coordinates":[144.88414001500001,-37.7539596558],"type":"Point"}
}