{
  "type": "Feature",
  "properties": {
    "iso:country":"AU",
    "sg:address":"Suite6, 65 Canberra Ave",
    "sg:city":"Canberra",
    "sg:classifiers":[
        {
            "category":"Real Estate",
            "subcategory":"Real Estate Agent",
            "type":"Services"
        }
    ],
    "sg:phone":"+61 3 6283 8105",
    "sg:postcode":"2600",
    "sg:province":"ACT",
    "sg:tags":[
        "consultant",
        "heritage"
    ],
    "wof:name":"Godden Mackay Logan Pty Ltd",
    "wof:placetype":"venue"
},
  "geometry": {"coordinates":[149.136474609,-35.3194122314],"type":"Point"}
}