{
  "type": "Feature",
  "properties": {
    "iso:country":"AU",
    "sg:address":"97 Market St",
    "sg:city":"Mudgee",
    "sg:classifiers":[
        {
            "category":"Travel",
            "subcategory":"Hotels & Motels",
            "type":"Entertainment"
        }
    ],
    "sg:phone":"+61 2 6372 7245",
    "sg:postcode":"2850",
    "sg:province":"NSW",
    "wof:name":"Cobb & Co. Court Boutique Hotel",
    "wof:placetype":"venue"
},
  "geometry": {"coordinates":[149.575348,-32.587681],"type":"Point"}
}