{
  "type": "Feature",
  "properties": {
    "addr:full":"Shp 1/ 194 Prospect Rd Prospect SA 5082",
    "addr:housenumber":"/ 194",
    "addr:postcode":"5082",
    "addr:street":"Prospect Rd",
    "iso:country":"AU",
    "sg:address":"Shp 1/ 194 Prospect Rd",
    "sg:city":"Prospect",
    "sg:classifiers":[
        {
            "category":"Professional",
            "subcategory":"Art Services",
            "type":"Services"
        }
    ],
    "sg:phone":"+61 8 8269 3445",
    "sg:postcode":"5082",
    "sg:province":"SA",
    "sg:tags":[
        "picture",
        "frame",
        "framing"
    ],
    "wof:name":"Aesthetic Picture Framing",
    "wof:placetype":"venue"
},
  "geometry": {"coordinates":[138.593551636,-34.8823699951],"type":"Point"}
}