{
  "type": "Feature",
  "properties": {
    "addr:full":"20 Chewton St Oxford Park QLD 4053",
    "addr:housenumber":"20",
    "addr:postcode":"4053",
    "addr:street":"Chewton St",
    "iso:country":"AU",
    "sg:address":"20 Chewton St",
    "sg:city":"Oxford Park",
    "sg:classifiers":[
        {
            "category":"Education",
            "subcategory":"Special Training",
            "type":"Public Place"
        }
    ],
    "sg:phone":"+61 405 582 333",
    "sg:postcode":"4053",
    "sg:province":"QLD",
    "sg:tags":[
        "tuition-educational"
    ],
    "wof:name":"Contract-Free Tutoring",
    "wof:placetype":"venue"
},
  "geometry": {"coordinates":[152.970703125,-27.4017467499],"type":"Point"}
}