{
  "type": "Feature",
  "properties": {
    "addr:full":"Unit 12, 15 Terminus St Castle Hill NSW 2154",
    "addr:housenumber":"15",
    "addr:postcode":"2154",
    "addr:street":"Terminus St",
    "iso:country":"AU",
    "sg:address":"Unit 12, 15 Terminus St",
    "sg:city":"Castle Hill",
    "sg:classifiers":[
        {
            "category":"Wholesale",
            "subcategory":"Medical Equipment & Supplies",
            "type":"Manufacturing & Wholesale Goods"
        }
    ],
    "sg:phone":"+61 2 8114 1590",
    "sg:postcode":"2154",
    "sg:province":"NSW",
    "sg:tags":[
        "aids",
        "hearing"
    ],
    "wof:name":"National Hearing Care",
    "wof:placetype":"venue"
},
  "geometry": {"coordinates":[151.00581359899999,-33.734161377],"type":"Point"}
}