{
  "type": "Feature",
  "properties": {
    "iso:country":"AU",
    "sg:address":"Pilkington St",
    "sg:city":"Garbutt",
    "sg:classifiers":[
        {
            "category":"Autos & Motor Vehicles",
            "subcategory":"Fuel & Gas Station",
            "type":"Retail Goods"
        }
    ],
    "sg:phone":"+61 7 4779 2119",
    "sg:postcode":"4814",
    "sg:province":"QLD",
    "wof:name":"BP Australia Limited",
    "wof:placetype":"venue"
},
  "geometry": {"coordinates":[146.767944,-19.264347],"type":"Point"}
}