{
  "type": "Feature",
  "properties": {
    "addr:full":"711 Princes Hwy Tempe NSW 2044",
    "addr:housenumber":"711",
    "addr:postcode":"2044",
    "addr:street":"Princes Hwy",
    "iso:country":"AU",
    "sg:address":"711 Princes Hwy",
    "sg:city":"Tempe",
    "sg:classifiers":[
        {
            "category":"Health Services",
            "subcategory":"Dentist",
            "type":"Services"
        }
    ],
    "sg:phone":"+61 2 9558 2434",
    "sg:postcode":"2044",
    "sg:province":"NSW",
    "sg:tags":[
        "dental",
        "prosthetist"
    ],
    "wof:name":"Gosling Denture Clinic",
    "wof:placetype":"venue"
},
  "geometry": {"coordinates":[151.16180399999999,-33.923683],"type":"Point"}
}