{
  "type": "Feature",
  "properties": {
    "iso:country":"AU",
    "sg:address":"43 Pacific Pde",
    "sg:city":"Dee Why",
    "sg:classifiers":[
        {
            "category":"Health Services",
            "subcategory":"Dentist",
            "type":"Services"
        }
    ],
    "sg:phone":"+61 2 9982 2564",
    "sg:postcode":"2099",
    "sg:province":"NSW",
    "wof:name":"Bryant P",
    "wof:placetype":"venue"
},
  "geometry": {"coordinates":[151.28709411599999,-33.7548713684],"type":"Point"}
}