{
  "type": "Feature",
  "properties": {
    "addr:full":"1 Spencer St Toowoomba QLD 4350",
    "addr:housenumber":"1",
    "addr:postcode":"4350",
    "addr:street":"Spencer St",
    "iso:country":"AU",
    "sg:address":"1 Spencer St",
    "sg:city":"Toowoomba",
    "sg:classifiers":[
        {
            "category":"Utilities",
            "subcategory":"Water",
            "type":"Services"
        }
    ],
    "sg:phone":"+61 419 665 989",
    "sg:postcode":"4350",
    "sg:province":"QLD",
    "sg:tags":[
        "hot",
        "system"
    ],
    "wof:name":"D.C.I. Electrical",
    "wof:placetype":"venue"
},
  "geometry": {"coordinates":[151.92628500000001,-27.578636],"type":"Point"}
}