{
  "type": "Feature",
  "properties": {
    "addr:full":"27 Page Rd Kelmscott WA 6111",
    "addr:housenumber":"27",
    "addr:postcode":"6111",
    "addr:street":"Page Rd",
    "iso:country":"AU",
    "sg:address":"27 Page Rd",
    "sg:city":"Kelmscott",
    "sg:classifiers":[
        {
            "category":"Banks & Credit Unions",
            "subcategory":"Financial Services",
            "type":"Services"
        }
    ],
    "sg:phone":"+61 8 9390 9520",
    "sg:postcode":"6111",
    "sg:province":"WA",
    "sg:tags":[
        "settlement",
        "nt",
        "agent",
        "wa"
    ],
    "wof:name":"Jaguar Settlements",
    "wof:placetype":"venue"
},
  "geometry": {"coordinates":[116.017120361,-32.1193199158],"type":"Point"}
}