{
  "type": "Feature",
  "properties": {
    "addr:full":"1st Floor 16 Fuller St Essendon VIC 3040",
    "addr:housenumber":"16",
    "addr:postcode":"3040",
    "addr:street":"Fuller St",
    "iso:country":"AU",
    "sg:address":"1st Floor 16 Fuller St",
    "sg:city":"Essendon",
    "sg:classifiers":[
        {
            "category":"Real Estate",
            "subcategory":"Architect",
            "type":"Services"
        }
    ],
    "sg:phone":"+61 3 9379 8214",
    "sg:postcode":"3040",
    "sg:province":"VIC",
    "wof:name":"Wignall Robert",
    "wof:placetype":"venue"
},
  "geometry": {"coordinates":[144.914794922,-37.743976593],"type":"Point"}
}