{
  "type": "Feature",
  "properties": {
    "iso:country":"AU",
    "sg:address":"4 Gypsy Cl",
    "sg:city":"Coolum Beach",
    "sg:classifiers":[
        {
            "category":"Health Services",
            "subcategory":"Health Practitioner",
            "type":"Services"
        }
    ],
    "sg:phone":"+61 7 5446 3860",
    "sg:postcode":"4573",
    "sg:province":"QLD",
    "sg:tags":[
        "psychologist"
    ],
    "wof:name":"Conscious Solutions",
    "wof:placetype":"venue"
},
  "geometry": {"coordinates":[153.07545500000001,-26.53541],"type":"Point"}
}