{
  "type": "Feature",
  "properties": {
    "iso:country":"AU",
    "sg:address":"1015 Latrobe St",
    "sg:city":"Ballarat",
    "sg:classifiers":[
        {
            "category":"Travel",
            "subcategory":"Hotels & Motels",
            "type":"Entertainment"
        }
    ],
    "sg:phone":"+61 3 5335 8040",
    "sg:postcode":"3350",
    "sg:province":"VIC",
    "sg:tags":[
        "accommodation"
    ],
    "wof:name":"Cattle Yards Inn",
    "wof:placetype":"venue"
},
  "geometry": {"coordinates":[143.818405,-37.570831],"type":"Point"}
}