{
  "type": "Feature",
  "properties": {
    "addr:full":"303 -305 Pitt St Sydney NSW 2000",
    "addr:housenumber":"-305",
    "addr:postcode":"2000",
    "addr:street":"Pitt St",
    "iso:country":"AU",
    "sg:address":"303 -305 Pitt St",
    "sg:city":"Sydney",
    "sg:classifiers":[
        {
            "category":"Fast Food",
            "type":"Food & Drink"
        }
    ],
    "sg:phone":"+61 2 9267 8056",
    "sg:postcode":"2000",
    "sg:province":"NSW",
    "sg:tags":[
        "away",
        "take"
    ],
    "wof:name":"Saigon Ville",
    "wof:placetype":"venue"
},
  "geometry": {"coordinates":[151.20791625999999,-33.8735694885],"type":"Point"}
}