{
  "type": "Feature",
  "properties": {
    "addr:full":"22 Howell Crs Windsor South NSW 2756",
    "addr:housenumber":"22",
    "addr:postcode":"2756",
    "addr:street":"Howell Crs",
    "iso:country":"AU",
    "sg:address":"22 Howell Crs",
    "sg:city":"Windsor South",
    "sg:classifiers":[
        {
            "category":"Utilities",
            "subcategory":"Water",
            "type":"Services"
        }
    ],
    "sg:phone":"+61 1800 683 908",
    "sg:postcode":"2756",
    "sg:province":"NSW",
    "sg:tags":[
        "hot",
        "system"
    ],
    "wof:name":"Hawkesbury City Plumbing P/L",
    "wof:placetype":"venue"
},
  "geometry": {"coordinates":[150.82957458499999,-33.6107597351],"type":"Point"}
}