{
  "type": "Feature",
  "properties": {
    "addr:full":"2/ 19 Underwood Ave Botany NSW 2019",
    "addr:housenumber":"/ 19",
    "addr:postcode":"2019",
    "addr:street":"Underwood Ave",
    "iso:country":"AU",
    "sg:address":"2/ 19 Underwood Ave",
    "sg:city":"Botany",
    "sg:classifiers":[
        {
            "category":"Wholesale",
            "subcategory":"Construction Materials",
            "type":"Manufacturing & Wholesale Goods"
        }
    ],
    "sg:phone":"+61 2 9666 3433",
    "sg:postcode":"2019",
    "sg:province":"NSW",
    "sg:tags":[
        "wholesaler",
        "felt",
        "mfrs"
    ],
    "wof:name":"Felt Distribution (Aust) Pty Ltd",
    "wof:placetype":"venue"
},
  "geometry": {"coordinates":[151.19529724099999,-33.9462776184],"type":"Point"}
}