{
  "type": "Feature",
  "properties": {
    "addr:full":"353 St Georges Rd Fitzroy North VIC 3068",
    "addr:housenumber":"353",
    "addr:postcode":"3068",
    "addr:street":"St Georges Rd",
    "iso:country":"AU",
    "sg:address":"353 St Georges Rd",
    "sg:city":"Fitzroy North",
    "sg:classifiers":[
        {
            "category":"Personal",
            "subcategory":"Beauty Salon",
            "type":"Services"
        }
    ],
    "sg:phone":"+61 3 9489 8856",
    "sg:postcode":"3068",
    "sg:province":"VIC",
    "sg:tags":[
        "hairdresser"
    ],
    "wof:name":"Hair On Georges Salon & Day Spa",
    "wof:placetype":"venue"
},
  "geometry": {"coordinates":[144.98704528799999,-37.7793769836],"type":"Point"}
}