{
  "type": "Feature",
  "properties": {
    "addr:full":"7 Hobson St South Yarra VIC 3141",
    "addr:housenumber":"7",
    "addr:postcode":"3141",
    "addr:street":"Hobson St",
    "iso:country":"AU",
    "sg:address":"7 Hobson St",
    "sg:city":"South Yarra",
    "sg:classifiers":[
        {
            "category":"Health Services",
            "subcategory":"Health Practitioner",
            "type":"Services"
        }
    ],
    "sg:phone":"+61 434 922 143",
    "sg:postcode":"3141",
    "sg:province":"VIC",
    "sg:tags":[
        "psychotherapist"
    ],
    "wof:name":"Constantinou Harry",
    "wof:placetype":"venue"
},
  "geometry": {"coordinates":[145.001190186,-37.8470954895],"type":"Point"}
}