{
  "type": "Feature",
  "properties": {
    "addr:full":"Lot 122 Excelsior Drv Morayfield QLD 4506",
    "addr:postcode":"4506",
    "addr:street":"Excelsior Drv",
    "iso:country":"AU",
    "sg:address":"Lot 122 Excelsior Drv",
    "sg:city":"Morayfield",
    "sg:classifiers":[
        {
            "category":"Building & Trades",
            "subcategory":"Construction",
            "type":"Services"
        }
    ],
    "sg:phone":"+61 7 5498 7712",
    "sg:postcode":"4506",
    "sg:province":"QLD",
    "sg:tags":[
        "joiner",
        "carpenter"
    ],
    "wof:name":"J.R. Caldwell's",
    "wof:placetype":"venue"
},
  "geometry": {"coordinates":[152.919555664,-27.1373310089],"type":"Point"}
}