{
  "type": "Feature",
  "properties": {
    "addr:full":"679 Boronia Rd Wantirna VIC 3152",
    "addr:housenumber":"679",
    "addr:postcode":"3152",
    "addr:street":"Boronia Rd",
    "iso:country":"AU",
    "sg:address":"679 Boronia Rd",
    "sg:city":"Wantirna",
    "sg:classifiers":[
        {
            "category":"Professional",
            "subcategory":"Accounting & Tax Preparation",
            "type":"Services"
        }
    ],
    "sg:phone":"+61 3 9800 3433",
    "sg:postcode":"3152",
    "sg:province":"VIC",
    "sg:tags":[
        "accountant",
        "auditor"
    ],
    "wof:name":"A T M Consultants Pty Ltd",
    "wof:placetype":"venue"
},
  "geometry": {"coordinates":[145.22795105,-37.847530365],"type":"Point"}
}