{
  "type": "Feature",
  "properties": {
    "addr:full":"362 Springvale Rd Springvale VIC 3171",
    "addr:housenumber":"362",
    "addr:postcode":"3171",
    "addr:street":"Springvale Rd",
    "iso:country":"AU",
    "sg:address":"362 Springvale Rd",
    "sg:city":"Springvale",
    "sg:classifiers":[
        {
            "category":"Health Services",
            "subcategory":"Doctor",
            "type":"Services"
        }
    ],
    "sg:phone":"+61 3 9546 7777",
    "sg:postcode":"3171",
    "sg:province":"VIC",
    "sg:tags":[
        "medical",
        "practitioner"
    ],
    "wof:name":"Ho Jessica",
    "wof:placetype":"venue"
},
  "geometry": {"coordinates":[145.15080261200001,-37.9588317871],"type":"Point"}
}