{
  "type": "Feature",
  "properties": {
    "addr:full":"12 Wetherill St Lidcombe NSW 2141",
    "addr:housenumber":"12",
    "addr:postcode":"2141",
    "addr:street":"Wetherill St",
    "iso:country":"AU",
    "sg:address":"12 Wetherill St",
    "sg:city":"Lidcombe",
    "sg:classifiers":[
        {
            "category":"Wholesale",
            "subcategory":"Machinery & Supplies",
            "type":"Manufacturing & Wholesale Goods"
        }
    ],
    "sg:phone":"+61 2 9648 1345",
    "sg:postcode":"2141",
    "sg:province":"NSW",
    "sg:tags":[
        "equipment",
        "welding"
    ],
    "wof:name":"Weldforce",
    "wof:placetype":"venue"
},
  "geometry": {"coordinates":[151.04473876899999,-33.8452301025],"type":"Point"}
}