{
  "type": "Feature",
  "properties": {
    "addr:full":"663 Nicholson St Carlton North VIC 3054",
    "addr:housenumber":"663",
    "addr:postcode":"3054",
    "addr:street":"Nicholson St",
    "iso:country":"AU",
    "sg:address":"663 Nicholson St",
    "sg:city":"Carlton North",
    "sg:classifiers":[
        {
            "category":"Personal",
            "subcategory":"Beauty Salon",
            "type":"Services"
        }
    ],
    "sg:phone":"+61 3 9380 6803",
    "sg:postcode":"3054",
    "sg:province":"VIC",
    "wof:name":"Dollhouse Beauty Salon",
    "wof:placetype":"venue"
},
  "geometry": {"coordinates":[144.977172852,-37.7838592529],"type":"Point"}
}