{
  "type": "Feature",
  "properties": {
    "iso:country":"AU",
    "sg:address":"1 Bay Rd",
    "sg:city":"Mt Gambier",
    "sg:classifiers":[
        {
            "category":"Arts & Performance",
            "subcategory":"Dance",
            "type":"Entertainment"
        }
    ],
    "sg:phone":"+61 8 8723 0991",
    "sg:postcode":"5290",
    "sg:province":"SA",
    "sg:tags":[
        "theatrical",
        "ballet",
        "tuition"
    ],
    "wof:name":"M J Dance Studio",
    "wof:placetype":"venue"
},
  "geometry": {"coordinates":[140.78076200000001,-37.828659],"type":"Point"}
}