{
  "type": "Feature",
  "properties": {
    "addr:full":"Lvl 3,Petrie House 80 Petrie Tce Brisbane QLD 4006",
    "addr:housenumber":"80",
    "addr:postcode":"4006",
    "addr:street":"Petrie Tce",
    "iso:country":"AU",
    "sg:address":"Lvl 3,Petrie House 80 Petrie Tce",
    "sg:city":"Brisbane",
    "sg:classifiers":[
        {
            "category":"Professional",
            "subcategory":"Computer Services",
            "type":"Services"
        }
    ],
    "sg:phone":"+61 7 3368 0836",
    "sg:postcode":"4006",
    "sg:province":"QLD",
    "sg:tags":[
        "package",
        "software"
    ],
    "wof:name":"Computer Spectrum Business Systems",
    "wof:placetype":"venue"
},
  "geometry": {"coordinates":[153.01364135700001,-27.4645004272],"type":"Point"}
}