{
  "type": "Feature",
  "properties": {
    "iso:country":"AU",
    "sg:address":"9 Killara Ave",
    "sg:city":"Riverwood",
    "sg:classifiers":[
        {
            "category":"Health Services",
            "subcategory":"Health Practitioner",
            "type":"Services"
        }
    ],
    "sg:phone":"+61 418 415 807",
    "sg:postcode":"2210",
    "sg:province":"NSW",
    "sg:tags":[
        "alternative"
    ],
    "wof:name":"Crystal Stargate",
    "wof:placetype":"venue"
},
  "geometry": {"coordinates":[151.05186499999999,-33.948975],"type":"Point"}
}