{
  "type": "Feature",
  "properties": {
    "iso:country":"AU",
    "sg:address":"Nelson Building Admiralty Drv",
    "sg:city":"Paradise Waters",
    "sg:classifiers":[
        {
            "category":"Personal",
            "subcategory":"Beauty Salon",
            "type":"Services"
        }
    ],
    "sg:phone":"+61 7 5532 0596",
    "sg:postcode":"4217",
    "sg:province":"QLD",
    "sg:tags":[
        "hairdresser"
    ],
    "wof:name":"Waterloo Hair",
    "wof:placetype":"venue"
},
  "geometry": {"coordinates":[153.42652893100001,-27.98736763],"type":"Point"}
}