{
  "type": "Feature",
  "properties": {
    "addr:full":"1552 Frankson-Flinders Rd Tyabb VIC 3913",
    "addr:housenumber":"1552",
    "addr:postcode":"3913",
    "addr:street":"Frankson-Flinders Rd",
    "iso:country":"AU",
    "sg:address":"1552 Frankson-Flinders Rd",
    "sg:city":"Tyabb",
    "sg:classifiers":[
        {
            "category":"Health Services",
            "subcategory":"Podiatrist",
            "type":"Services"
        }
    ],
    "sg:phone":"+61 3 5977 4447",
    "sg:postcode":"3913",
    "sg:province":"VIC",
    "sg:tags":[
        "cap",
        "hat",
        "renovation",
        "retail"
    ],
    "wof:name":"Luton Hatters",
    "wof:placetype":"venue"
},
  "geometry": {"coordinates":[145.18951415999999,-38.2605934143],"type":"Point"}
}