{
  "type": "Feature",
  "properties": {
    "addr:full":"16 - 18 Murray Rd Welshpool WA 6106",
    "addr:housenumber":"18",
    "addr:postcode":"6106",
    "addr:street":"Murray Rd",
    "iso:country":"AU",
    "sg:address":"16 - 18 Murray Rd",
    "sg:city":"Welshpool",
    "sg:classifiers":[
        {
            "category":"Building & Trades",
            "subcategory":"Construction",
            "type":"Services"
        }
    ],
    "sg:phone":"+61 8 9258 4555",
    "sg:postcode":"6106",
    "sg:province":"WA",
    "sg:tags":[
        "equipment",
        "system",
        "automation"
    ],
    "wof:name":"Auto Control Systems",
    "wof:placetype":"venue"
},
  "geometry": {"coordinates":[115.955627441,-31.9981746674],"type":"Point"}
}