{
  "type": "Feature",
  "properties": {
    "addr:full":"397 Monbulk Rd Monbulk VIC 3793",
    "addr:housenumber":"397",
    "addr:postcode":"3793",
    "addr:street":"Monbulk Rd",
    "iso:country":"AU",
    "sg:address":"397 Monbulk Rd",
    "sg:city":"Monbulk",
    "sg:classifiers":[
        {
            "category":"Farming",
            "subcategory":"Farm & Veterinary Services",
            "type":"Manufacturing & Wholesale Goods"
        }
    ],
    "sg:phone":"+61 3 9756 6522",
    "sg:postcode":"3793",
    "sg:province":"VIC",
    "sg:tags":[
        "irrigation",
        "reticulation",
        "system"
    ],
    "wof:name":"The Irrigation Shed & Rural Supplies",
    "wof:placetype":"venue"
},
  "geometry": {"coordinates":[145.420013428,-37.8545684814],"type":"Point"}
}