{
  "type": "Feature",
  "properties": {
    "addr:full":"Unit 1 27 Croydon St Petersham NSW 2049",
    "addr:housenumber":"27",
    "addr:postcode":"2049",
    "addr:street":"Croydon St",
    "iso:country":"AU",
    "sg:address":"Unit 1 27 Croydon St",
    "sg:city":"Petersham",
    "sg:classifiers":[
        {
            "category":"Professional",
            "subcategory":"Management & Consulting",
            "type":"Services"
        }
    ],
    "sg:phone":"+61 412 068 652",
    "sg:postcode":"2049",
    "sg:province":"NSW",
    "sg:tags":[
        "consultant",
        "migration"
    ],
    "wof:name":"Agus Arifin S",
    "wof:placetype":"venue"
},
  "geometry": {"coordinates":[151.155609,-33.891148],"type":"Point"}
}