{
  "type": "Feature",
  "properties": {
    "addr:full":"14 Ingham Drv Casula NSW 2170",
    "addr:housenumber":"14",
    "addr:postcode":"2170",
    "addr:street":"Ingham Drv",
    "iso:country":"AU",
    "sg:address":"14 Ingham Drv",
    "sg:city":"Casula",
    "sg:classifiers":[
        {
            "category":"Health Services",
            "subcategory":"Dentist",
            "type":"Services"
        }
    ],
    "sg:phone":"+61 2 9600 9625",
    "sg:postcode":"2170",
    "sg:province":"NSW",
    "wof:name":"Advanced Dental Care",
    "wof:placetype":"venue"
},
  "geometry": {"coordinates":[150.901412964,-33.948474884],"type":"Point"}
}