{
  "type": "Feature",
  "properties": {
    "addr:full":"Vervo Chambers 1st Floor The Mall 78 Station St Seymour VIC 3660",
    "addr:housenumber":"floor;78",
    "addr:postcode":"3660",
    "addr:street":"The Mall;Station St",
    "iso:country":"AU",
    "sg:address":"Vervo Chambers 1st Floor The Mall 78 Station St",
    "sg:city":"Seymour",
    "sg:classifiers":[
        {
            "category":"Professional",
            "subcategory":"Accounting & Tax Preparation",
            "type":"Services"
        }
    ],
    "sg:phone":"+61 3 5792 2886",
    "sg:postcode":"3660",
    "sg:province":"VIC",
    "sg:tags":[
        "consultant",
        "taxation"
    ],
    "wof:name":"Andrews Neil",
    "wof:placetype":"venue"
},
  "geometry": {"coordinates":[145.13616943400001,-37.0246543884],"type":"Point"}
}