{
  "type": "Feature",
  "properties": {
    "addr:full":"Shop 3/ 36 Meenan St Garbutt QLD 4814",
    "addr:housenumber":"shop 3 / 36",
    "addr:postcode":"4814",
    "addr:street":"Meenan St",
    "iso:country":"AU",
    "sg:address":"Shop 3/ 36 Meenan St",
    "sg:city":"Garbutt",
    "sg:classifiers":[
        {
            "category":"Education",
            "subcategory":"Special Training",
            "type":"Public Place"
        }
    ],
    "sg:phone":"+61 7 4725 6401",
    "sg:postcode":"4814",
    "sg:province":"QLD",
    "sg:tags":[
        "school",
        "art"
    ],
    "wof:name":"In-Ages School Of Fine Art",
    "wof:placetype":"venue"
},
  "geometry": {"coordinates":[146.775024,-19.260374],"type":"Point"}
}