{
  "type": "Feature",
  "properties": {
    "addr:full":"981 Wellington St West Perth WA 6005",
    "addr:housenumber":"981",
    "addr:postcode":"6005",
    "addr:street":"Wellington St",
    "iso:country":"AU",
    "sg:address":"981 Wellington St",
    "sg:city":"West Perth",
    "sg:classifiers":[
        {
            "category":"Insurance",
            "subcategory":"Insurance Agent",
            "type":"Services"
        }
    ],
    "sg:phone":"+61 8 9481 2804",
    "sg:postcode":"6005",
    "sg:province":"WA",
    "sg:tags":[
        "broker"
    ],
    "wof:name":"Rigden & Douse Insurance Brokers",
    "wof:placetype":"venue"
},
  "geometry": {"coordinates":[115.844367981,-31.9465866089],"type":"Point"}
}