{
  "type": "Feature",
  "properties": {
    "addr:full":"41 Robert St Tenambit NSW 2323",
    "addr:housenumber":"41",
    "addr:postcode":"2323",
    "addr:street":"Robert St",
    "iso:country":"AU",
    "sg:address":"41 Robert St",
    "sg:city":"Tenambit",
    "sg:classifiers":[
        {
            "category":"Home & Garden",
            "subcategory":"Building Materials",
            "type":"Retail Goods"
        }
    ],
    "sg:phone":"+61 2 4933 6128",
    "sg:postcode":"2323",
    "sg:province":"NSW",
    "sg:tags":[
        "lawn",
        "cutting",
        "maintenance"
    ],
    "wof:name":"Noonies Lawn Care",
    "wof:placetype":"venue"
},
  "geometry": {"coordinates":[151.61082458499999,-32.7408676147],"type":"Point"}
}