{
  "type": "Feature",
  "properties": {
    "addr:full":"3/ 76 Mornington Rd Mornington TAS 7018",
    "addr:housenumber":"/ 76",
    "addr:postcode":"7018",
    "addr:street":"Mornington Rd",
    "iso:country":"AU",
    "sg:address":"3/ 76 Mornington Rd",
    "sg:city":"Mornington",
    "sg:classifiers":[
        {
            "category":"Wholesale",
            "subcategory":"Machinery & Supplies",
            "type":"Manufacturing & Wholesale Goods"
        }
    ],
    "sg:phone":"+61 3 6244 5244",
    "sg:postcode":"7018",
    "sg:province":"TAS",
    "sg:tags":[
        "equipment",
        "system",
        "elevating",
        "conveying"
    ],
    "wof:name":"Onsite Belting Service Pty Ltd",
    "wof:placetype":"venue"
},
  "geometry": {"coordinates":[147.40037536599999,-42.8609008789],"type":"Point"}
}