{
  "type": "Feature",
  "properties": {
    "addr:full":"1/90 King St Perth WA 6000",
    "addr:housenumber":"/ 90",
    "addr:postcode":"6000",
    "addr:street":"King St",
    "iso:country":"AU",
    "sg:address":"1/90 King St",
    "sg:city":"Perth",
    "sg:classifiers":[
        {
            "category":"Personal",
            "subcategory":"Beauty Salon",
            "type":"Services"
        }
    ],
    "sg:phone":"+61 8 9485 1546",
    "sg:postcode":"6000",
    "sg:province":"WA",
    "sg:tags":[
        "supply",
        "artist",
        "make-up"
    ],
    "wof:name":"Make-Up Training Academy",
    "wof:placetype":"venue"
},
  "geometry": {"coordinates":[115.85585021999999,-31.9507274628],"type":"Point"}
}