{
  "type": "Feature",
  "properties": {
    "iso:country":"AU",
    "sg:address":"Blaikie Rd",
    "sg:city":"Jamisontown",
    "sg:classifiers":[
        {
            "category":"Building & Trades",
            "subcategory":"Cleaning & Sanitation",
            "type":"Services"
        }
    ],
    "sg:phone":"+61 2 4733 6327",
    "sg:postcode":"2750",
    "sg:province":"NSW",
    "sg:tags":[
        "industrial",
        "commercial",
        "contractor"
    ],
    "wof:name":"Barrett Cleaner",
    "wof:placetype":"venue"
},
  "geometry": {"coordinates":[150.676239014,-33.7689971924],"type":"Point"}
}