{
  "type": "Feature",
  "properties": {
    "addr:full":"PO Box 1364 Milton Business Centre QLD 4064",
    "addr:postcode":"4064",
    "addr:street":"Milton",
    "iso:country":"AU",
    "sg:address":"PO Box 1364",
    "sg:city":"Milton Business Centre",
    "sg:classifiers":[
        {
            "category":"Manufacturing",
            "subcategory":"Petroleum Products",
            "type":"Manufacturing & Wholesale Goods"
        }
    ],
    "sg:phone":"+61 7 3837 3400",
    "sg:postcode":"4064",
    "sg:province":"QLD",
    "sg:tags":[
        "magnesium",
        "supply"
    ],
    "wof:name":"Australian Magnesium Corporation Ltd.",
    "wof:placetype":"venue"
},
  "geometry": {"coordinates":[153.00137329099999,-27.4699516296],"type":"Point"}
}