{
  "type": "Feature",
  "properties": {
    "iso:country":"AU",
    "sg:address":"2 Ocean Crt",
    "sg:city":"Shelly Beach",
    "sg:classifiers":[
        {
            "category":"Real Estate",
            "subcategory":"Architect",
            "type":"Services"
        }
    ],
    "sg:phone":"+61 7 5492 5356",
    "sg:postcode":"4551",
    "sg:province":"QLD",
    "wof:name":"Jackson Bill",
    "wof:placetype":"venue"
},
  "geometry": {"coordinates":[153.147506714,-26.7947235107],"type":"Point"}
}