{
  "type": "Feature",
  "properties": {
    "iso:country":"AU",
    "sg:address":"129 Victoria Ave",
    "sg:city":"Chatswood",
    "sg:classifiers":[
        {
            "category":"Education",
            "subcategory":"Music School",
            "type":"Public Place"
        }
    ],
    "sg:phone":"+61 2 9499 5955",
    "sg:postcode":"2067",
    "sg:province":"NSW",
    "sg:tags":[
        "teacher"
    ],
    "wof:name":"Forte School Of Music",
    "wof:placetype":"venue"
},
  "geometry": {"coordinates":[151.19590759299999,-33.7921714783],"type":"Point"}
}