{
  "type": "Feature",
  "properties": {
    "iso:country":"AU",
    "sg:address":"7 John St",
    "sg:city":"Kempsey",
    "sg:classifiers":[
        {
            "category":"Retail",
            "subcategory":"Auto Repair",
            "type":"Services"
        }
    ],
    "sg:phone":"+61 2 6563 1100",
    "sg:postcode":"2440",
    "sg:province":"NSW",
    "sg:tags":[
        "transmission",
        "automotive",
        "car"
    ],
    "wof:name":"Manning's Service Centre",
    "wof:placetype":"venue"
},
  "geometry": {"coordinates":[152.840363,-31.081362],"type":"Point"}
}