{
  "type": "Feature",
  "properties": {
    "iso:country":"AU",
    "sg:address":"3 Teal Pl",
    "sg:city":"Boambee",
    "sg:classifiers":[
        {
            "category":"Professional",
            "subcategory":"Printing & Photocopies",
            "type":"Services"
        }
    ],
    "sg:phone":"+61 2 6658 2246",
    "sg:postcode":"2450",
    "sg:province":"NSW",
    "sg:tags":[
        "trophy"
    ],
    "wof:name":"Ex-treme Engraving & Awards",
    "wof:placetype":"venue"
},
  "geometry": {"coordinates":[153.082291,-30.34524],"type":"Point"}
}