{
  "type": "Feature",
  "properties": {
    "iso:country":"AU",
    "sg:address":"2 Chepstow St",
    "sg:city":"Randwick",
    "sg:classifiers":[
        {
            "category":"Professional",
            "subcategory":"Management & Consulting",
            "type":"Services"
        }
    ],
    "sg:phone":"+61 2 9326 4911",
    "sg:postcode":"2031",
    "sg:province":"NSW",
    "sg:tags":[
        "consultant"
    ],
    "wof:name":"Success Cycle",
    "wof:placetype":"venue"
},
  "geometry": {"coordinates":[151.24310302699999,-33.90599823],"type":"Point"}
}