{
  "type": "Feature",
  "properties": {
    "addr:full":"180 Walsh St Mareeba QLD 4880",
    "addr:housenumber":"180",
    "addr:postcode":"4880",
    "addr:street":"Walsh St",
    "iso:country":"AU",
    "sg:address":"180 Walsh St",
    "sg:city":"Mareeba",
    "sg:classifiers":[
        {
            "category":"Health Services",
            "subcategory":"Health Practitioner",
            "type":"Services"
        }
    ],
    "sg:phone":"+61 7 4092 4492",
    "sg:postcode":"4880",
    "sg:province":"QLD",
    "sg:tags":[
        "physiotherapist"
    ],
    "wof:name":"Mareeba Physiotherapy Centre",
    "wof:placetype":"venue"
},
  "geometry": {"coordinates":[145.42404174800001,-16.9960918427],"type":"Point"}
}