{
  "type": "Feature",
  "properties": {
    "addr:full":"56 Edebohls Rd Narre Warren East VIC 3804",
    "addr:housenumber":"56",
    "addr:postcode":"3804",
    "addr:street":"Edebohls Rd",
    "iso:country":"AU",
    "sg:address":"56 Edebohls Rd",
    "sg:city":"Narre Warren East",
    "sg:classifiers":[
        {
            "category":"Building & Trades",
            "subcategory":"Landscaping Services",
            "type":"Services"
        }
    ],
    "sg:phone":"+61 3 9796 8581",
    "sg:postcode":"3804",
    "sg:province":"VIC",
    "sg:tags":[
        "gardener"
    ],
    "wof:name":"Eric Evans Pty Ltd",
    "wof:placetype":"venue"
},
  "geometry": {"coordinates":[145.36465454099999,-37.9639892578],"type":"Point"}
}