{
  "type": "Feature",
  "properties": {
    "addr:full":"Cnr Perak St & Tengah Crs Mona Vale NSW 2103",
    "addr:postcode":"2103",
    "addr:street":"Cnr Perak St & Tengah Crs",
    "iso:country":"AU",
    "sg:address":"Cnr Perak St & Tengah Crs",
    "sg:city":"Mona Vale",
    "sg:classifiers":[
        {
            "category":"Professional",
            "subcategory":"Engineering",
            "type":"Services"
        }
    ],
    "sg:phone":"+61 2 9999 4044",
    "sg:postcode":"2103",
    "sg:province":"NSW",
    "sg:tags":[
        "engineer",
        "mechanical"
    ],
    "wof:name":"Advanced Automotive Services",
    "wof:placetype":"venue"
},
  "geometry": {"coordinates":[151.30824279800001,-33.6737365723],"type":"Point"}
}