{
  "type": "Feature",
  "properties": {
    "addr:full":"64 Avenue Rd Mosman NSW 2088",
    "addr:housenumber":"64",
    "addr:postcode":"2088",
    "addr:street":"Avenue Rd",
    "iso:country":"AU",
    "sg:address":"64 Avenue Rd",
    "sg:city":"Mosman",
    "sg:classifiers":[
        {
            "category":"Health Services",
            "subcategory":"Health Practitioner",
            "type":"Services"
        }
    ],
    "sg:phone":"+61 2 9969 0884",
    "sg:postcode":"2088",
    "sg:province":"NSW",
    "sg:tags":[
        "physiotherapist"
    ],
    "wof:name":"Avenue Road Physiotherapy",
    "wof:placetype":"venue"
},
  "geometry": {"coordinates":[151.238815308,-33.8316612244],"type":"Point"}
}