{
  "type": "Feature",
  "properties": {
    "addr:full":"113 Brandis Rd Munno Para West SA 5115",
    "addr:housenumber":"113",
    "addr:postcode":"5115",
    "addr:street":"Brandis Rd",
    "iso:country":"AU",
    "sg:address":"113 Brandis Rd",
    "sg:city":"Munno Para West",
    "sg:classifiers":[
        {
            "category":"Professional",
            "subcategory":"Engineering",
            "type":"Services"
        }
    ],
    "sg:phone":"+61 8 8284 7910",
    "sg:postcode":"5115",
    "sg:province":"SA",
    "sg:tags":[
        "engineer"
    ],
    "wof:name":"Iken Engineering",
    "wof:placetype":"venue"
},
  "geometry": {"coordinates":[138.67124939000001,-34.6569137573],"type":"Point"}
}