{
  "type": "Feature",
  "properties": {
    "addr:full":"14 Secker Rd Mt Barker SA 5251",
    "addr:housenumber":"14",
    "addr:postcode":"5251",
    "addr:street":"Secker Rd",
    "iso:country":"AU",
    "sg:address":"14 Secker Rd",
    "sg:city":"Mt Barker",
    "sg:classifiers":[
        {
            "category":"Building & Trades",
            "subcategory":"Landscaping Services",
            "type":"Services"
        }
    ],
    "sg:phone":"+61 8 8398 2055",
    "sg:postcode":"5251",
    "sg:province":"SA",
    "sg:tags":[
        "designer",
        "landscape",
        "contractor"
    ],
    "wof:name":"Hills Paving & Home Improvement Centre",
    "wof:placetype":"venue"
},
  "geometry": {"coordinates":[138.87464904800001,-35.0756835938],"type":"Point"}
}