{
  "type": "Feature",
  "properties": {
    "addr:full":"Jack Grant Ave Warnervale NSW 2259",
    "addr:postcode":"2259",
    "addr:street":"Grant Ave",
    "iso:country":"AU",
    "sg:address":"Jack Grant Ave",
    "sg:city":"Warnervale",
    "sg:classifiers":[
        {
            "category":"Education",
            "subcategory":"Special Training",
            "type":"Public Place"
        }
    ],
    "sg:phone":"+61 2 4392 2632",
    "sg:postcode":"2259",
    "sg:province":"NSW",
    "sg:tags":[
        "school",
        "flying"
    ],
    "wof:name":"Central Coast Aero Club",
    "wof:placetype":"venue"
},
  "geometry": {"coordinates":[151.43391418499999,-33.2386665344],"type":"Point"}
}