{
  "type": "Feature",
  "properties": {
    "iso:country":"AU",
    "sg:address":"16 Amelia St",
    "sg:city":"Waterloo",
    "sg:classifiers":[
        {
            "category":"Professional",
            "type":"Services"
        }
    ],
    "sg:phone":"+61 2 9698 8908",
    "sg:postcode":"2017",
    "sg:province":"NSW",
    "sg:tags":[
        "industrial",
        "commercial",
        "catering"
    ],
    "wof:name":"Lunches On Amelia",
    "wof:placetype":"venue"
},
  "geometry": {"coordinates":[151.21385192899999,-33.9009513855],"type":"Point"}
}