{
  "type": "Feature",
  "properties": {
    "iso:country":"AU",
    "sg:address":"23 Redcliffe Pde",
    "sg:city":"Redcliffe",
    "sg:classifiers":[
        {
            "category":"Health Services",
            "subcategory":"Dentist",
            "type":"Services"
        }
    ],
    "sg:phone":"+61 7 3889 3337",
    "sg:postcode":"4020",
    "sg:province":"QLD",
    "wof:name":"Seaside Dental Redcliffe",
    "wof:placetype":"venue"
},
  "geometry": {"coordinates":[153.11537200000001,-27.228485],"type":"Point"}
}