{
  "type": "Feature",
  "properties": {
    "iso:country":"AU",
    "sg:address":"19 McCallum St",
    "sg:city":"Carseldine",
    "sg:classifiers":[
        {
            "category":"Home & Garden",
            "subcategory":"Building Materials",
            "type":"Retail Goods"
        }
    ],
    "sg:phone":"+61 7 3863 4861",
    "sg:postcode":"4034",
    "sg:province":"QLD",
    "sg:tags":[
        "fitting",
        "door"
    ],
    "wof:name":"Folding Walls & Doors By Lotus",
    "wof:placetype":"venue"
},
  "geometry": {"coordinates":[153.01847799999999,-27.348421],"type":"Point"}
}