{
  "type": "Feature",
  "properties": {
    "addr:full":"5/13 Carrington Rd Toowoomba QLD 4350",
    "addr:housenumber":"/ 13",
    "addr:postcode":"4350",
    "addr:street":"Carrington Rd",
    "iso:country":"AU",
    "sg:address":"5/13 Carrington Rd",
    "sg:city":"Toowoomba",
    "sg:classifiers":[
        {
            "category":"Wholesale",
            "subcategory":"Machinery & Supplies",
            "type":"Manufacturing & Wholesale Goods"
        }
    ],
    "sg:phone":"+61 7 4633 3399",
    "sg:postcode":"4350",
    "sg:province":"QLD",
    "sg:tags":[
        "equipment",
        "hydraulic"
    ],
    "wof:name":"HDR Workshop Solutions",
    "wof:placetype":"venue"
},
  "geometry": {"coordinates":[151.878433,-27.542313],"type":"Point"}
}