{
  "type": "Feature",
  "properties": {
    "addr:full":"Cnr Golden Way & Sunnybrook Drv Golden Grove SA 5125",
    "addr:postcode":"5125",
    "addr:street":"Cnr Golden Way & Sunnybrook Drv",
    "iso:country":"AU",
    "sg:address":"Cnr Golden Way & Sunnybrook Drv",
    "sg:city":"Golden Grove",
    "sg:classifiers":[
        {
            "category":"Autos & Motor Vehicles",
            "subcategory":"Fuel & Gas Station",
            "type":"Retail Goods"
        }
    ],
    "sg:phone":"+61 8 8289 0044",
    "sg:postcode":"5125",
    "sg:province":"SA",
    "wof:name":"Tip Top Mobil Service Stations",
    "wof:placetype":"venue"
},
  "geometry": {"coordinates":[138.72288499999999,-34.769993],"type":"Point"}
}