{
  "type": "Feature",
  "properties": {
    "addr:full":"1st Floor Unit 9, 46 Smith St Southport QLD 4215",
    "addr:housenumber":"46",
    "addr:postcode":"4215",
    "addr:street":"Smith St",
    "iso:country":"AU",
    "sg:address":"1st Floor Unit 9, 46 Smith St",
    "sg:city":"Southport",
    "sg:classifiers":[
        {
            "category":"Professional",
            "subcategory":"Computer Services",
            "type":"Services"
        }
    ],
    "sg:phone":"+61 7 5591 4722",
    "sg:postcode":"4215",
    "sg:province":"QLD",
    "sg:tags":[
        "repairs",
        "upgrade",
        "equipment"
    ],
    "wof:name":"G C I Systems",
    "wof:placetype":"venue"
},
  "geometry": {"coordinates":[153.404785156,-27.9635047913],"type":"Point"}
}