{
  "type": "Feature",
  "properties": {
    "addr:full":"Sacred Heart School Langton Rd Mt Barker WA 6324",
    "addr:postcode":"6324",
    "addr:street":"Langton Rd",
    "iso:country":"AU",
    "sg:address":"Sacred Heart School Langton Rd",
    "sg:city":"Mt Barker",
    "sg:classifiers":[
        {
            "category":"Education",
            "subcategory":"Vocational School",
            "type":"Public Place"
        }
    ],
    "sg:phone":"+61 8 9851 2055",
    "sg:postcode":"6324",
    "sg:province":"WA",
    "sg:tags":[
        "tafe",
        "college",
        "training"
    ],
    "wof:name":"Mt Barker TAFE Centre",
    "wof:placetype":"venue"
},
  "geometry": {"coordinates":[117.66178893999999,-34.6277198792],"type":"Point"}
}