{
  "type": "Feature",
  "properties": {
    "addr:full":"5 Thornbill Pl Burleigh Waters QLD 4220",
    "addr:housenumber":"5",
    "addr:postcode":"4220",
    "addr:street":"Thornbill Pl",
    "iso:country":"AU",
    "sg:address":"5 Thornbill Pl",
    "sg:city":"Burleigh Waters",
    "sg:classifiers":[
        {
            "category":"Building & Trades",
            "subcategory":"Cleaning & Sanitation",
            "type":"Services"
        }
    ],
    "sg:phone":"+61 7 5535 7969",
    "sg:postcode":"4220",
    "sg:province":"QLD",
    "sg:tags":[
        "window"
    ],
    "wof:name":"Eugene Fielding Services",
    "wof:placetype":"venue"
},
  "geometry": {"coordinates":[153.42562866200001,-28.0770111084],"type":"Point"}
}