{
  "type": "Feature",
  "properties": {
    "iso:country":"AU",
    "sg:address":"29 Forbes St",
    "sg:city":"Devonport",
    "sg:classifiers":[
        {
            "category":"Professional",
            "subcategory":"Accounting & Tax Preparation",
            "type":"Services"
        }
    ],
    "sg:phone":"+61 3 6423 1199",
    "sg:postcode":"7310",
    "sg:province":"TAS",
    "sg:tags":[
        "consultant",
        "taxation"
    ],
    "wof:name":"Neil Wilkinson Pty Ltd",
    "wof:placetype":"venue"
},
  "geometry": {"coordinates":[146.35552978499999,-41.1839370728],"type":"Point"}
}