{
  "type": "Feature",
  "properties": {
    "iso:country":"AU",
    "sg:address":"5 Mopoke Crt",
    "sg:city":"Wulagi",
    "sg:classifiers":[
        {
            "category":"Arena",
            "subcategory":"Sports Club",
            "type":"Entertainment"
        }
    ],
    "sg:phone":"+61 417 821 502",
    "sg:postcode":"0812",
    "sg:province":"NT",
    "sg:tags":[
        "defence",
        "supply",
        "self",
        "instruction",
        "martial art"
    ],
    "wof:name":"NT Chungdokwan Taekwondo &Thai Boxing",
    "wof:placetype":"venue"
},
  "geometry": {"coordinates":[130.891693,-12.383728],"type":"Point"}
}