{
  "type": "Feature",
  "properties": {
    "addr:full":"5 Coronation Ave Pottsville Beach NSW 2489",
    "addr:housenumber":"5",
    "addr:postcode":"2489",
    "addr:street":"Coronation Ave",
    "iso:country":"AU",
    "sg:address":"5 Coronation Ave",
    "sg:city":"Pottsville Beach",
    "sg:classifiers":[
        {
            "category":"Real Estate",
            "subcategory":"Real Estate Agent",
            "type":"Services"
        }
    ],
    "sg:phone":"+61 2 6676 1053",
    "sg:postcode":"2489",
    "sg:province":"NSW",
    "wof:name":"Pottsville Beach First National",
    "wof:placetype":"venue"
},
  "geometry": {"coordinates":[153.56455993599999,-28.3888645172],"type":"Point"}
}