{
  "type": "Feature",
  "properties": {
    "addr:full":"Alfred St St George QLD 4487",
    "addr:postcode":"4487",
    "addr:street":"Alfred St",
    "iso:country":"AU",
    "sg:address":"Alfred St St",
    "sg:city":"George",
    "sg:classifiers":[
        {
            "category":"Health Services",
            "subcategory":"Doctor",
            "type":"Services"
        }
    ],
    "sg:phone":"+61 7 4625 3899",
    "sg:postcode":"4487",
    "sg:province":"QLD",
    "sg:tags":[
        "nurse",
        "nursing"
    ],
    "wof:name":"Warrawee Nursing Service & Day Respite Centre",
    "wof:placetype":"venue"
},
  "geometry": {"coordinates":[148.580444336,-28.0387020111],"type":"Point"}
}