{
  "type": "Feature",
  "properties": {
    "addr:full":"22 Sweny Drv Australind WA 6233",
    "addr:housenumber":"22",
    "addr:postcode":"6233",
    "addr:street":"Sweny Drv",
    "iso:country":"AU",
    "sg:address":"22 Sweny Drv",
    "sg:city":"Australind",
    "sg:classifiers":[
        {
            "category":"Home & Garden",
            "subcategory":"Building Materials",
            "type":"Retail Goods"
        }
    ],
    "sg:phone":"+61 8 9797 0410",
    "sg:postcode":"6233",
    "sg:province":"WA",
    "sg:tags":[
        "supply"
    ],
    "wof:name":"Community Building Supplies",
    "wof:placetype":"venue"
},
  "geometry": {"coordinates":[115.746071,-33.277893],"type":"Point"}
}