{
  "type": "Feature",
  "properties": {
    "addr:full":"17 Tina St Beaudesert QLD 4285",
    "addr:housenumber":"17",
    "addr:postcode":"4285",
    "addr:street":"Tina St",
    "iso:country":"AU",
    "sg:address":"17 Tina St",
    "sg:city":"Beaudesert",
    "sg:classifiers":[
        {
            "category":"Education",
            "subcategory":"School",
            "type":"Public Place"
        }
    ],
    "sg:phone":"+61 7 5540 1111",
    "sg:postcode":"4285",
    "sg:province":"QLD",
    "sg:tags":[
        "state",
        "except",
        "nsw"
    ],
    "wof:name":"Beaudesert Primary",
    "wof:placetype":"venue"
},
  "geometry": {"coordinates":[153.00242600000001,-27.988506],"type":"Point"}
}