{
  "type": "Feature",
  "properties": {
    "addr:full":"Central Districts Private Hospital Jarvis Rd Elizabeth Vale SA 5112",
    "addr:postcode":"5112",
    "addr:street":"Jarvis Rd",
    "iso:country":"AU",
    "sg:address":"Central Districts Private Hospital Jarvis Rd",
    "sg:city":"Elizabeth Vale",
    "sg:classifiers":[
        {
            "category":"Health Services",
            "subcategory":"Health Practitioner",
            "type":"Services"
        }
    ],
    "sg:phone":"+61 8 8282 5263",
    "sg:postcode":"5112",
    "sg:province":"SA",
    "sg:tags":[
        "physiotherapist"
    ],
    "wof:name":"Fuller Richard",
    "wof:placetype":"venue"
},
  "geometry": {"coordinates":[138.65635681099999,-34.7522468567],"type":"Point"}
}