{
  "type": "Feature",
  "properties": {
    "addr:full":"21 Regatta Ave Forster NSW 2428",
    "addr:housenumber":"21",
    "addr:postcode":"2428",
    "addr:street":"Regatta Ave",
    "iso:country":"AU",
    "sg:address":"21 Regatta Ave",
    "sg:city":"Forster",
    "sg:classifiers":[
        {
            "category":"Building & Trades",
            "subcategory":"Construction",
            "type":"Services"
        }
    ],
    "sg:phone":"+61 408 654 778",
    "sg:postcode":"2428",
    "sg:province":"NSW",
    "sg:tags":[
        "concrete",
        "contractor"
    ],
    "wof:name":"Great Lakes Decorative Concrete",
    "wof:placetype":"venue"
},
  "geometry": {"coordinates":[152.531555,-32.201797],"type":"Point"}
}