{
  "type": "Feature",
  "properties": {
    "addr:full":"9 Banks Pl Keilor VIC 3036",
    "addr:housenumber":"9",
    "addr:postcode":"3036",
    "addr:street":"Banks Pl",
    "iso:country":"AU",
    "sg:address":"9 Banks Pl",
    "sg:city":"Keilor",
    "sg:classifiers":[
        {
            "category":"Building & Trades",
            "subcategory":"Landscaping Services",
            "type":"Services"
        }
    ],
    "sg:phone":"+61 3 9331 5353",
    "sg:postcode":"3036",
    "sg:province":"VIC",
    "sg:tags":[
        "gardener"
    ],
    "wof:name":"Keilor Gardening Home Improvements",
    "wof:placetype":"venue"
},
  "geometry": {"coordinates":[144.823364,-37.715252],"type":"Point"}
}