{
  "type": "Feature",
  "properties": {
    "addr:full":"198 Lake Edge Ave Berkeley Vale NSW 2261",
    "addr:housenumber":"198",
    "addr:postcode":"2261",
    "addr:street":"Lake Edge Ave",
    "iso:country":"AU",
    "sg:address":"198 Lake Edge Ave",
    "sg:city":"Berkeley Vale",
    "sg:classifiers":[
        {
            "category":"Autos & Motor Vehicles",
            "subcategory":"Auto Supplies",
            "type":"Retail Goods"
        }
    ],
    "sg:phone":"+61 409 659 728",
    "sg:postcode":"2261",
    "sg:province":"NSW",
    "sg:tags":[
        "equipment",
        "part",
        "truck"
    ],
    "wof:name":"Gear Up Used Truck Parts",
    "wof:placetype":"venue"
},
  "geometry": {"coordinates":[151.47868299999999,-33.362904],"type":"Point"}
}