{
  "type": "Feature",
  "properties": {
    "addr:full":"3/ 101 Richmond Rd Morningside QLD 4170",
    "addr:housenumber":"/ 101",
    "addr:postcode":"4170",
    "addr:street":"Richmond Rd",
    "iso:country":"AU",
    "sg:address":"3/ 101 Richmond Rd",
    "sg:city":"Morningside",
    "sg:classifiers":[
        {
            "category":"Utilities",
            "subcategory":"Water",
            "type":"Services"
        }
    ],
    "sg:phone":"+61 7 3217 9529",
    "sg:postcode":"4170",
    "sg:province":"QLD",
    "sg:tags":[
        "equipment",
        "treatment"
    ],
    "wof:name":"M M S Fluid Filtration",
    "wof:placetype":"venue"
},
  "geometry": {"coordinates":[153.074676514,-27.4715423584],"type":"Point"}
}