{
  "type": "Feature",
  "properties": {
    "addr:full":"Adelaide St Ayr QLD 4807",
    "addr:postcode":"4807",
    "addr:street":"Adelaide St",
    "iso:country":"AU",
    "sg:address":"Adelaide St",
    "sg:city":"Ayr",
    "sg:classifiers":[
        {
            "category":"Farming",
            "subcategory":"Nursery",
            "type":"Manufacturing & Wholesale Goods"
        }
    ],
    "sg:phone":"+61 7 4783 5307",
    "sg:postcode":"4807",
    "sg:province":"QLD",
    "wof:name":"Pedigree Seedlings",
    "wof:placetype":"venue"
},
  "geometry": {"coordinates":[147.41392517099999,-19.57762146],"type":"Point"}
}