{
  "type": "Feature",
  "properties": {
    "iso:country":"AU",
    "sg:address":"86 Calume St",
    "sg:city":"Hillman",
    "sg:classifiers":[
        {
            "category":"Professional",
            "subcategory":"Business Services",
            "type":"Services"
        }
    ],
    "sg:phone":"+61 8 9592 6283",
    "sg:postcode":"6168",
    "sg:province":"WA",
    "sg:tags":[
        "drafting"
    ],
    "wof:name":"Electrotech",
    "wof:placetype":"venue"
},
  "geometry": {"coordinates":[115.765327,-32.279518],"type":"Point"}
}