{
  "type": "Feature",
  "properties": {
    "iso:country":"AU",
    "sg:address":"30 Burwood Rd",
    "sg:city":"Belfield",
    "sg:classifiers":[
        {
            "category":"Health Services",
            "subcategory":"Doctor",
            "type":"Services"
        }
    ],
    "sg:phone":"+61 2 9642 5285",
    "sg:postcode":"2191",
    "sg:province":"NSW",
    "sg:tags":[
        "medical",
        "practitioner"
    ],
    "wof:name":"Lahood J",
    "wof:placetype":"venue"
},
  "geometry": {"coordinates":[151.08419799999999,-33.903469],"type":"Point"}
}