{
  "type": "Feature",
  "properties": {
    "addr:full":"Unit 11/ 219 Pacific Hwy Hornsby NSW 2077",
    "addr:housenumber":"/ 219",
    "addr:postcode":"2077",
    "addr:street":"Pacific Hwy",
    "iso:country":"AU",
    "sg:address":"Unit 11/ 219 Pacific Hwy",
    "sg:city":"Hornsby",
    "sg:classifiers":[
        {
            "category":"Utilities",
            "subcategory":"Electric",
            "type":"Services"
        }
    ],
    "sg:phone":"+61 2 9477 3196",
    "sg:postcode":"2077",
    "sg:province":"NSW",
    "sg:tags":[
        "vehicle"
    ],
    "wof:name":"Elroy Engineering Pty Ltd",
    "wof:placetype":"venue"
},
  "geometry": {"coordinates":[151.097732544,-33.6983451843],"type":"Point"}
}