{
  "type": "Feature",
  "properties": {
    "iso:country":"AU",
    "sg:address":"68 Young St",
    "sg:city":"Frankston",
    "sg:classifiers":[
        {
            "category":"Fast Food",
            "type":"Food & Drink"
        }
    ],
    "sg:phone":"+61 3 9781 3969",
    "sg:postcode":"3199",
    "sg:province":"VIC",
    "sg:tags":[
        "away",
        "take"
    ],
    "wof:name":"Cafe Depo Express",
    "wof:placetype":"venue"
},
  "geometry": {"coordinates":[144.97845459000001,-37.8061065674],"type":"Point"}
}