{
  "type": "Feature",
  "properties": {
    "iso:country":"AU",
    "sg:address":"162 Blackwood St",
    "sg:city":"Mitchelton",
    "sg:classifiers":[
        {
            "category":"Professional",
            "subcategory":"Management & Consulting",
            "type":"Services"
        }
    ],
    "sg:phone":"+61 7 3355 2608",
    "sg:postcode":"4053",
    "sg:province":"QLD",
    "sg:tags":[
        "consultant",
        "energy"
    ],
    "wof:name":"Solar Logic",
    "wof:placetype":"venue"
},
  "geometry": {"coordinates":[152.97531127900001,-27.4060153961],"type":"Point"}
}