{
  "type": "Feature",
  "properties": {
    "iso:country":"AU",
    "sg:address":"Suite 4, Ground Floor 205 Clarence St",
    "sg:city":"Sydney",
    "sg:classifiers":[
        {
            "category":"Professional",
            "subcategory":"Employment Agencies",
            "type":"Services"
        }
    ],
    "sg:phone":"+61 2 8836 1331",
    "sg:postcode":"2000",
    "sg:province":"NSW",
    "wof:name":"Smart Staff Pty Ltd",
    "wof:placetype":"venue"
},
  "geometry": {"coordinates":[151.205245972,-33.8697242737],"type":"Point"}
}