{
  "type": "Feature",
  "properties": {
    "iso:country":"AU",
    "sg:address":"1 Tomlinson St",
    "sg:city":"Bundaberg",
    "sg:classifiers":[
        {
            "category":"Utilities",
            "subcategory":"Electric",
            "type":"Services"
        }
    ],
    "sg:phone":"+61 7 4153 1700",
    "sg:postcode":"4670",
    "sg:province":"QLD",
    "sg:tags":[
        "electrical",
        "contractor"
    ],
    "wof:name":"Hill T G & L M",
    "wof:placetype":"venue"
},
  "geometry": {"coordinates":[152.36601257300001,-24.8629398346],"type":"Point"}
}