{
  "type": "Feature",
  "properties": {
    "iso:country":"AU",
    "sg:address":"30 Hall St",
    "sg:city":"Sherwood",
    "sg:classifiers":[
        {
            "category":"Building & Trades",
            "subcategory":"Construction",
            "type":"Services"
        }
    ],
    "sg:phone":"+61 419 647 925",
    "sg:postcode":"4075",
    "sg:province":"QLD",
    "sg:tags":[
        "contractor"
    ],
    "wof:name":"Corbin C M & M M",
    "wof:placetype":"venue"
},
  "geometry": {"coordinates":[152.98489379899999,-27.5310668945],"type":"Point"}
}