{
  "type": "Feature",
  "properties": {
    "iso:country":"AU",
    "sg:address":"13 MacDonald Drv",
    "sg:city":"Armidale",
    "sg:classifiers":[
        {
            "category":"Retail",
            "subcategory":"Driving School",
            "type":"Services"
        }
    ],
    "sg:phone":"+61 2 6772 1222",
    "sg:postcode":"2350",
    "sg:province":"NSW",
    "wof:name":"Mitchell's Driver Training",
    "wof:placetype":"venue"
},
  "geometry": {"coordinates":[151.686843872,-30.5082454681],"type":"Point"}
}