{
  "type": "Feature",
  "properties": {
    "iso:country":"AU",
    "sg:address":"55 Hargreaves St",
    "sg:city":"Cairns",
    "sg:classifiers":[
        {
            "category":"Professional",
            "type":"Services"
        }
    ],
    "sg:phone":"+61 1800 994 597",
    "sg:postcode":"4870",
    "sg:province":"QLD",
    "sg:tags":[
        "shop",
        "fitting"
    ],
    "wof:name":"The Rack&#039;n Stack Warehouse",
    "wof:placetype":"venue"
},
  "geometry": {"coordinates":[145.74476623499999,-17.0009822845],"type":"Point"}
}