{
  "type": "Feature",
  "properties": {
    "addr:full":"4 Amesbury Crt Mt Waverley VIC 3149",
    "addr:housenumber":"4",
    "addr:postcode":"3149",
    "addr:street":"Amesbury Crt Mt",
    "iso:country":"AU",
    "sg:address":"4 Amesbury Crt",
    "sg:city":"Mt Waverley",
    "sg:classifiers":[
        {
            "category":"Building & Trades",
            "subcategory":"Plumbing",
            "type":"Services"
        }
    ],
    "sg:phone":"+61 3 9807 8093",
    "sg:postcode":"3149",
    "sg:province":"VIC",
    "sg:tags":[
        "plumber",
        "gasfitters"
    ],
    "wof:name":"Amendola J & I",
    "wof:placetype":"venue"
},
  "geometry": {"coordinates":[145.11436462399999,-37.8858642578],"type":"Point"}
}