{
  "type": "Feature",
  "properties": {
    "addr:full":"Lot 1 Deep Creek Rd Arthurs Creek VIC 3099",
    "addr:postcode":"3099",
    "addr:street":"Deep Creek Rd",
    "iso:country":"AU",
    "sg:address":"Lot 1 Deep Creek Rd",
    "sg:city":"Arthurs Creek",
    "sg:classifiers":[
        {
            "category":"Arena",
            "subcategory":"Horse Racetrack",
            "type":"Entertainment"
        }
    ],
    "sg:phone":"+61 3 9714 8511",
    "sg:postcode":"3099",
    "sg:province":"VIC",
    "sg:tags":[
        "rotary",
        "hoeing"
    ],
    "wof:name":"Barber's Bin Hire",
    "wof:placetype":"venue"
},
  "geometry": {"coordinates":[145.194824219,-37.5757293701],"type":"Point"}
}