{
  "type": "Feature",
  "properties": {
    "addr:full":"190 Newell St Bungalow QLD 4870",
    "addr:housenumber":"190",
    "addr:postcode":"4870",
    "addr:street":"Newell St",
    "iso:country":"AU",
    "sg:address":"190 Newell St",
    "sg:city":"Bungalow",
    "sg:classifiers":[
        {
            "category":"Shopping",
            "subcategory":"Pets & Pet Supplies",
            "type":"Retail Goods"
        }
    ],
    "sg:phone":"+61 7 4033 0775",
    "sg:postcode":"4870",
    "sg:province":"QLD",
    "sg:tags":[
        "food"
    ],
    "wof:name":"Ben's Pet Barn",
    "wof:placetype":"venue"
},
  "geometry": {"coordinates":[145.75094604500001,-16.9380435944],"type":"Point"}
}