{
  "type": "Feature",
  "properties": {
    "addr:full":"6 Karabil St Chapel Hill QLD 4069",
    "addr:housenumber":"6",
    "addr:postcode":"4069",
    "addr:street":"Karabil St",
    "iso:country":"AU",
    "sg:address":"6 Karabil St",
    "sg:city":"Chapel Hill",
    "sg:classifiers":[
        {
            "category":"Real Estate",
            "subcategory":"Developer",
            "type":"Services"
        }
    ],
    "sg:phone":"+61 7 3878 7255",
    "sg:postcode":"4069",
    "sg:province":"QLD",
    "sg:tags":[
        "development"
    ],
    "wof:name":"Serra Property Group",
    "wof:placetype":"venue"
},
  "geometry": {"coordinates":[152.94598388700001,-27.5061798096],"type":"Point"}
}