{
  "type": "Feature",
  "properties": {
    "addr:full":"Farm 2430 Walla Ave Griffith NSW 2680",
    "addr:housenumber":"2430",
    "addr:postcode":"2680",
    "addr:street":"Walla Ave",
    "iso:country":"AU",
    "sg:address":"Farm 2430 Walla Ave",
    "sg:city":"Griffith",
    "sg:classifiers":[
        {
            "category":"Farming",
            "subcategory":"Farm & Veterinary Services",
            "type":"Manufacturing & Wholesale Goods"
        }
    ],
    "sg:phone":"+61 2 6964 1175",
    "sg:postcode":"2680",
    "sg:province":"NSW",
    "sg:tags":[
        "irrigation",
        "reticulation",
        "system"
    ],
    "wof:name":"Armstrongs Plant Hire",
    "wof:placetype":"venue"
},
  "geometry": {"coordinates":[146.02088900000001,-34.295769],"type":"Point"}
}