{
  "type": "Feature",
  "properties": {
    "addr:full":"U3/ 201 Evans Rd Salisbury QLD 4107",
    "addr:housenumber":"201",
    "addr:postcode":"4107",
    "addr:street":"U3 /;Evans Rd",
    "iso:country":"AU",
    "sg:address":"U3/ 201 Evans Rd",
    "sg:city":"Salisbury",
    "sg:classifiers":[
        {
            "category":"Professional",
            "subcategory":"Engineering",
            "type":"Services"
        }
    ],
    "sg:phone":"+61 7 3255 6164",
    "sg:postcode":"4107",
    "sg:province":"QLD",
    "sg:tags":[
        "engineer"
    ],
    "wof:name":"Tec-Mach Pty Ltd",
    "wof:placetype":"venue"
},
  "geometry": {"coordinates":[153.03060913100001,-27.5450305939],"type":"Point"}
}