{
  "type": "Feature",
  "properties": {
    "iso:country":"AU",
    "sg:address":"167 Swan St",
    "sg:city":"Yokine",
    "sg:classifiers":[
        {
            "category":"Organizations",
            "subcategory":"Non-profit Organization",
            "type":"Services"
        }
    ],
    "sg:phone":"+61 8 9349 2393",
    "sg:postcode":"6060",
    "sg:province":"WA",
    "sg:tags":[
        "support",
        "disability",
        "organisation"
    ],
    "wof:name":"Abilympics W A Association Inc",
    "wof:placetype":"venue"
},
  "geometry": {"coordinates":[115.85154724100001,-31.8924617767],"type":"Point"}
}