{
  "type": "Feature",
  "properties": {
    "iso:country":"AU",
    "sg:address":"12 Manna Ave",
    "sg:city":"Figtree",
    "sg:classifiers":[
        {
            "category":"Building & Trades",
            "subcategory":"Construction",
            "type":"Services"
        }
    ],
    "sg:phone":"+61 1300 143 366",
    "sg:postcode":"2525",
    "sg:province":"NSW",
    "sg:tags":[
        "earth",
        "excavating",
        "moving",
        "contractor"
    ],
    "wof:name":"Jericho Demolition & Excavation",
    "wof:placetype":"venue"
},
  "geometry": {"coordinates":[150.845336914,-34.4231147766],"type":"Point"}
}