{
  "type": "Feature",
  "properties": {
    "addr:full":"282 Belgravia St Cloverdale WA 6105",
    "addr:housenumber":"282",
    "addr:postcode":"6105",
    "addr:street":"Belgravia St",
    "iso:country":"AU",
    "sg:address":"282 Belgravia St",
    "sg:city":"Cloverdale",
    "sg:classifiers":[
        {
            "category":"Personal",
            "type":"Services"
        }
    ],
    "sg:phone":"+61 8 9277 3732",
    "sg:postcode":"6105",
    "sg:province":"WA",
    "sg:tags":[
        "wallpapering",
        "wallcovering"
    ],
    "wof:name":"M.J.R. Godsell Pty Ltd",
    "wof:placetype":"venue"
},
  "geometry": {"coordinates":[115.939903259,-31.9584846497],"type":"Point"}
}