{
  "type": "Feature",
  "properties": {
    "iso:country":"AU",
    "sg:address":"23 Blackett Drv",
    "sg:city":"Castle Hill",
    "sg:classifiers":[
        {
            "category":"Education",
            "subcategory":"Special Training",
            "type":"Public Place"
        }
    ],
    "sg:phone":"+61 2 9686 1978",
    "sg:postcode":"2154",
    "sg:province":"NSW",
    "sg:tags":[
        "development"
    ],
    "wof:name":"Chiropractic Resource Centre",
    "wof:placetype":"venue"
},
  "geometry": {"coordinates":[150.98826599099999,-33.7428970337],"type":"Point"}
}