{
  "type": "Feature",
  "properties": {
    "addr:full":"1631 Sydney Rd Campbellfield VIC 3061",
    "addr:housenumber":"1631",
    "addr:postcode":"3061",
    "addr:street":"Sydney Rd",
    "iso:country":"AU",
    "sg:address":"1631 Sydney Rd",
    "sg:city":"Campbellfield",
    "sg:classifiers":[
        {
            "category":"Travel",
            "subcategory":"Hotels & Motels",
            "type":"Entertainment"
        }
    ],
    "sg:phone":"+61 3 9359 4099",
    "sg:postcode":"3061",
    "sg:province":"VIC",
    "sg:tags":[
        "accommodation"
    ],
    "wof:name":"Liquor Xpress",
    "wof:placetype":"venue"
},
  "geometry": {"coordinates":[144.955612183,-37.6739692688],"type":"Point"}
}