{
  "type": "Feature",
  "properties": {
    "addr:full":"Shop 136 Carindale Shopng Cntr, Creek Rd Carindale QLD 4152",
    "addr:housenumber":"136",
    "addr:postcode":"4152",
    "addr:street":"Creek Rd",
    "iso:country":"AU",
    "sg:address":"Shop 136 Carindale Shopng Cntr, Creek Rd",
    "sg:city":"Carindale",
    "sg:classifiers":[
        {
            "category":"Shopping",
            "subcategory":"Music",
            "type":"Retail Goods"
        }
    ],
    "sg:phone":"+61 7 3398 5788",
    "sg:postcode":"4152",
    "sg:province":"QLD",
    "sg:tags":[
        "instrument",
        "musical"
    ],
    "wof:name":"Brashs Pty Ltd",
    "wof:placetype":"venue"
},
  "geometry": {"coordinates":[153.10345459000001,-27.5023994446],"type":"Point"}
}