{
  "type": "Feature",
  "properties": {
    "addr:full":"277 Murray St Finley NSW 2713",
    "addr:housenumber":"277",
    "addr:postcode":"2713",
    "addr:street":"Murray St",
    "iso:country":"AU",
    "sg:address":"277 Murray St",
    "sg:city":"Finley",
    "sg:classifiers":[
        {
            "category":"Autos & Motor Vehicles",
            "subcategory":"Automobile Sales",
            "type":"Retail Goods"
        }
    ],
    "sg:phone":"+61 3 5883 1433",
    "sg:postcode":"2713",
    "sg:province":"NSW",
    "sg:tags":[
        "car",
        "new"
    ],
    "wof:name":"Riverina Landrover",
    "wof:placetype":"venue"
},
  "geometry": {"coordinates":[145.57409668,-35.6473922729],"type":"Point"}
}