{
  "type": "Feature",
  "properties": {
    "addr:full":"29- 31 Auscan Crs Garbutt QLD 4814",
    "addr:housenumber":"31",
    "addr:postcode":"4814",
    "addr:street":"Auscan Crs",
    "iso:country":"AU",
    "sg:address":"29- 31 Auscan Crs",
    "sg:city":"Garbutt",
    "sg:classifiers":[
        {
            "category":"Building & Trades",
            "subcategory":"Construction",
            "type":"Services"
        }
    ],
    "sg:phone":"+61 7 4725 6003",
    "sg:postcode":"4814",
    "sg:province":"QLD",
    "sg:tags":[
        "fencing",
        "contractor"
    ],
    "wof:name":"Fencing Factory The",
    "wof:placetype":"venue"
},
  "geometry": {"coordinates":[146.78376800000001,-19.26436],"type":"Point"}
}