{
  "type": "Feature",
  "properties": {
    "addr:full":"Shop 14 Murray Arc, 127- 133 Burwood Rd Burwood NSW 2134",
    "addr:housenumber":"shop 14;127 133",
    "addr:postcode":"2134",
    "addr:street":"Murray Arc;Burwood Rd",
    "iso:country":"AU",
    "sg:address":"Shop 14 Murray Arc, 127- 133 Burwood Rd",
    "sg:city":"Burwood",
    "sg:classifiers":[
        {
            "category":"Wholesale",
            "subcategory":"Medical Equipment & Supplies",
            "type":"Manufacturing & Wholesale Goods"
        }
    ],
    "sg:phone":"+61 2 9715 2399",
    "sg:postcode":"2134",
    "sg:province":"NSW",
    "sg:tags":[
        "aids",
        "hearing"
    ],
    "wof:name":"AudioClinic",
    "wof:placetype":"venue"
},
  "geometry": {"coordinates":[151.103713989,-33.8764686584],"type":"Point"}
}