{
  "type": "Feature",
  "properties": {
    "addr:full":"106 Smith St Alice Springs NT 0871",
    "addr:housenumber":"106",
    "addr:postcode":"nt 0871",
    "addr:street":"Smith St",
    "iso:country":"AU",
    "sg:address":"106 Smith St",
    "sg:city":"Alice Springs",
    "sg:classifiers":[
        {
            "category":"Building & Trades",
            "subcategory":"Construction",
            "type":"Services"
        }
    ],
    "sg:phone":"+61 412 898 165",
    "sg:postcode":"0871",
    "sg:province":"NT",
    "sg:tags":[
        "stonework",
        "stone",
        "mason"
    ],
    "wof:name":"Stonemasonry Pty Ltd",
    "wof:placetype":"venue"
},
  "geometry": {"coordinates":[133.85839843799999,-23.6862812042],"type":"Point"}
}