{
  "type": "Feature",
  "properties": {
    "addr:full":"17 Maribor St Westlake QLD 4074",
    "addr:housenumber":"17",
    "addr:postcode":"4074",
    "addr:street":"Maribor St",
    "iso:country":"AU",
    "sg:address":"17 Maribor St",
    "sg:city":"Westlake",
    "sg:classifiers":[
        {
            "category":"Health Services",
            "subcategory":"Health Practitioner",
            "type":"Services"
        }
    ],
    "sg:phone":"+61 7 3376 3336",
    "sg:postcode":"4074",
    "sg:province":"QLD",
    "sg:tags":[
        "pathologist",
        "speech"
    ],
    "wof:name":"Spells",
    "wof:placetype":"venue"
},
  "geometry": {"coordinates":[152.91949462900001,-27.5477561951],"type":"Point"}
}