{
  "type": "Feature",
  "properties": {
    "addr:full":"813 South Rd Clarence Gardens SA 5039",
    "addr:housenumber":"813",
    "addr:postcode":"5039",
    "addr:street":"South Rd",
    "iso:country":"AU",
    "sg:address":"813 South Rd",
    "sg:city":"Clarence Gardens",
    "sg:classifiers":[
        {
            "category":"Structure",
            "subcategory":"Building",
            "type":"Public Place"
        }
    ],
    "sg:phone":"+61 8 8351 6718",
    "sg:postcode":"5039",
    "sg:province":"SA",
    "sg:tags":[
        "sail",
        "shade"
    ],
    "wof:name":"All Spas",
    "wof:placetype":"venue"
},
  "geometry": {"coordinates":[138.573364258,-34.9684867859],"type":"Point"}
}