{
  "type": "Feature",
  "properties": {
    "iso:country":"AU",
    "sg:address":"189 High St",
    "sg:city":"Northcote",
    "sg:classifiers":[
        {
            "category":"Arts & Performance",
            "subcategory":"Theater",
            "type":"Entertainment"
        }
    ],
    "sg:phone":"+61 3 9481 9500",
    "sg:postcode":"3070",
    "sg:province":"VIC",
    "sg:tags":[
        "theatre"
    ],
    "wof:name":"Northcote Town Hall",
    "wof:placetype":"venue"
},
  "geometry": {"coordinates":[144.99771100000001,-37.774899],"type":"Point"}
}