{
  "type": "Feature",
  "properties": {
    "iso:country":"AU",
    "sg:address":"Ste 4/ 10 Station Rd",
    "sg:city":"Cheltenham",
    "sg:classifiers":[
        {
            "category":"Professional",
            "subcategory":"Secretarial Services",
            "type":"Services"
        }
    ],
    "sg:phone":"+61 3 9583 1899",
    "sg:postcode":"3192",
    "sg:province":"VIC",
    "sg:tags":[
        "typing"
    ],
    "wof:name":"Book Of You The",
    "wof:placetype":"venue"
},
  "geometry": {"coordinates":[145.05604553200001,-37.9671630859],"type":"Point"}
}