{
  "type": "Feature",
  "properties": {
    "iso:country":"AU",
    "sg:address":"Shop GD, 94",
    "sg:city":"Casuarina Sq Casuarina",
    "sg:classifiers":[
        {
            "category":"Shopping",
            "subcategory":"Mobile Phones",
            "type":"Retail Goods"
        }
    ],
    "sg:phone":"+61 8 8927 9222",
    "sg:postcode":"0810",
    "sg:province":"NT",
    "sg:tags":[
        "telephone",
        "accessory"
    ],
    "wof:name":"AAPT Mobile",
    "wof:placetype":"venue"
},
  "geometry": {"coordinates":[130.846832275,-12.3787002563],"type":"Point"}
}