{
  "type": "Feature",
  "properties": {
    "iso:country":"AU",
    "sg:address":"6 Edwin St",
    "sg:city":"Urangan",
    "sg:classifiers":[
        {
            "category":"Professional",
            "subcategory":"Art Services",
            "type":"Services"
        }
    ],
    "sg:phone":"+61 409 286 364",
    "sg:postcode":"4655",
    "sg:province":"QLD",
    "sg:tags":[
        "artist"
    ],
    "wof:name":"Chris Postle",
    "wof:placetype":"venue"
},
  "geometry": {"coordinates":[152.905945,-25.289701],"type":"Point"}
}