{
  "type": "Feature",
  "properties": {
    "addr:full":"50 Arnold Drv Scoresby VIC 3179",
    "addr:housenumber":"50",
    "addr:postcode":"3179",
    "addr:street":"Arnold Drv",
    "iso:country":"AU",
    "sg:address":"50 Arnold Drv",
    "sg:city":"Scoresby",
    "sg:classifiers":[
        {
            "category":"Manufacturing",
            "subcategory":"Tools & Machinery",
            "type":"Manufacturing & Wholesale Goods"
        }
    ],
    "sg:phone":"+61 411 447 349",
    "sg:postcode":"3179",
    "sg:province":"VIC",
    "wof:name":"Eastern District Tool Supplies",
    "wof:placetype":"venue"
},
  "geometry": {"coordinates":[145.23411560100001,-37.8932304382],"type":"Point"}
}