{
  "type": "Feature",
  "properties": {
    "iso:country":"AU",
    "sg:address":"7 Penola Rd",
    "sg:city":"Mt Gambier",
    "sg:classifiers":[
        {
            "category":"Professional",
            "subcategory":"Accounting & Tax Preparation",
            "type":"Services"
        }
    ],
    "sg:phone":"+61 8 8725 0711",
    "sg:postcode":"5290",
    "sg:province":"SA",
    "sg:tags":[
        "accountant",
        "auditor"
    ],
    "wof:name":"Walker D C",
    "wof:placetype":"venue"
},
  "geometry": {"coordinates":[140.78106700000001,-37.827381],"type":"Point"}
}