{
  "type": "Feature",
  "properties": {
    "iso:country":"AU",
    "sg:address":"93 Bath Rd",
    "sg:city":"Kirrawee",
    "sg:classifiers":[
        {
            "category":"Retail",
            "subcategory":"Auto Repair",
            "type":"Services"
        }
    ],
    "sg:phone":"+61 418 610 004",
    "sg:postcode":"2232",
    "sg:province":"NSW",
    "sg:tags":[
        "electrical"
    ],
    "wof:name":"Paterson Auto Electrics",
    "wof:placetype":"venue"
},
  "geometry": {"coordinates":[151.07742309599999,-34.0254745483],"type":"Point"}
}