{
  "type": "Feature",
  "properties": {
    "iso:country":"AU",
    "sg:address":"PO Box 132",
    "sg:city":"Wangi Wangi",
    "sg:classifiers":[
        {
            "category":"Building & Trades",
            "subcategory":"Plumbing",
            "type":"Services"
        }
    ],
    "sg:phone":"+61 2 4975 3679",
    "sg:postcode":"2267",
    "sg:province":"NSW",
    "sg:tags":[
        "plumber",
        "gasfitters"
    ],
    "wof:name":"Rathmines Plumbing Services",
    "wof:placetype":"venue"
},
  "geometry": {"coordinates":[151.561676,-33.060799],"type":"Point"}
}