{
  "type": "Feature",
  "properties": {
    "iso:country":"AU",
    "sg:address":"25 Frederick St",
    "sg:city":"Busselton",
    "sg:classifiers":[
        {
            "category":"Retail",
            "subcategory":"Car Wash",
            "type":"Services"
        }
    ],
    "sg:phone":"+61 8 9754 8444",
    "sg:postcode":"6280",
    "sg:province":"WA",
    "sg:tags":[
        "truck",
        "cleaning"
    ],
    "wof:name":"Geographe Car Detailing",
    "wof:placetype":"venue"
},
  "geometry": {"coordinates":[115.34396362299999,-33.6607475281],"type":"Point"}
}