{
  "type": "Feature",
  "properties": {
    "addr:full":"4 Russell St Balnarring VIC 3926",
    "addr:housenumber":"4",
    "addr:postcode":"3926",
    "addr:street":"Russell St",
    "iso:country":"AU",
    "sg:address":"4 Russell St",
    "sg:city":"Balnarring",
    "sg:classifiers":[
        {
            "category":"Health Services",
            "subcategory":"Dentist",
            "type":"Services"
        }
    ],
    "sg:phone":"+61 3 5983 5348",
    "sg:postcode":"3926",
    "sg:province":"VIC",
    "wof:name":"Churcher David Dr",
    "wof:placetype":"venue"
},
  "geometry": {"coordinates":[145.124465942,-38.3726234436],"type":"Point"}
}