{
  "type": "Feature",
  "properties": {
    "addr:full":"U7/ 46 Jedda Rd Prestons NSW 2170",
    "addr:housenumber":"46",
    "addr:postcode":"2170",
    "addr:street":"U7 /;Jedda Rd",
    "iso:country":"AU",
    "sg:address":"U7/ 46 Jedda Rd",
    "sg:city":"Prestons",
    "sg:classifiers":[
        {
            "category":"Freight",
            "type":"Transportation"
        }
    ],
    "sg:phone":"+61 2 9826 6388",
    "sg:postcode":"2170",
    "sg:province":"NSW",
    "sg:tags":[
        "cargo",
        "container"
    ],
    "wof:name":"Nexus Corp International",
    "wof:placetype":"venue"
},
  "geometry": {"coordinates":[150.88752746599999,-33.9348106384],"type":"Point"}
}