{
  "type": "Feature",
  "properties": {
    "addr:full":"7 Silver Crt Tanah Merah QLD 4128",
    "addr:housenumber":"7",
    "addr:postcode":"4128",
    "addr:street":"Silver Crt",
    "iso:country":"AU",
    "sg:address":"7 Silver Crt",
    "sg:city":"Tanah Merah",
    "sg:classifiers":[
        {
            "category":"Professional",
            "subcategory":"Employment Agencies",
            "type":"Services"
        }
    ],
    "sg:phone":"+61 7 3806 3099",
    "sg:postcode":"4128",
    "sg:province":"QLD",
    "wof:name":"Profile Personnel",
    "wof:placetype":"venue"
},
  "geometry": {"coordinates":[153.17070007300001,-27.6738491058],"type":"Point"}
}