{
  "type": "Feature",
  "properties": {
    "iso:country":"AU",
    "sg:address":"217A Carlingford Crt",
    "sg:city":"Carlingford",
    "sg:classifiers":[
        {
            "category":"Personal",
            "subcategory":"Beauty Salon",
            "type":"Services"
        }
    ],
    "sg:phone":"+61 2 9871 6087",
    "sg:postcode":"2118",
    "sg:province":"NSW",
    "wof:name":"Marys House Of Beauty",
    "wof:placetype":"venue"
},
  "geometry": {"coordinates":[151.05511474599999,-33.7771148682],"type":"Point"}
}