{
  "type": "Feature",
  "properties": {
    "addr:full":"Suites 16-18 Ashley Medical Cntr 1a Ashley La Westmead NSW 2145",
    "addr:housenumber":"16-18;1a",
    "addr:postcode":"2145",
    "addr:street":"Ashley Medical Cntr;Ashley La",
    "iso:country":"AU",
    "sg:address":"Suites 16-18 Ashley Medical Cntr 1a Ashley La",
    "sg:city":"Westmead",
    "sg:classifiers":[
        {
            "category":"Health Services",
            "subcategory":"Doctor",
            "type":"Services"
        }
    ],
    "sg:phone":"+61 2 9633 2244",
    "sg:postcode":"2145",
    "sg:province":"NSW",
    "sg:tags":[
        "medical",
        "practitioner"
    ],
    "wof:name":"Tanswell Graham",
    "wof:placetype":"venue"
},
  "geometry": {"coordinates":[150.98919677699999,-33.8064880371],"type":"Point"}
}