{
  "type": "Feature",
  "properties": {
    "iso:country":"AU",
    "sg:address":"269/ 271 Old Northern Rd",
    "sg:city":"Castle Hill",
    "sg:classifiers":[
        {
            "category":"Wholesale",
            "subcategory":"Medical Equipment & Supplies",
            "type":"Manufacturing & Wholesale Goods"
        }
    ],
    "sg:phone":"+61 2 9899 5477",
    "sg:postcode":"2154",
    "sg:province":"NSW",
    "sg:tags":[
        "aids",
        "hearing"
    ],
    "wof:name":"Better Hearing Specialists",
    "wof:placetype":"venue"
},
  "geometry": {"coordinates":[151.00431823700001,-33.7337875366],"type":"Point"}
}