{
  "type": "Feature",
  "properties": {
    "addr:full":"152 Lake Rd Port Macquarie NSW 2444",
    "addr:housenumber":"152",
    "addr:postcode":"2444",
    "addr:street":"Lake Rd",
    "iso:country":"AU",
    "sg:address":"152 Lake Rd",
    "sg:city":"Port Macquarie",
    "sg:classifiers":[
        {
            "category":"Professional",
            "subcategory":"Detective & Security Services",
            "type":"Services"
        }
    ],
    "sg:phone":"+61 2 6583 2827",
    "sg:postcode":"2444",
    "sg:province":"NSW",
    "sg:tags":[
        "consultant",
        "system"
    ],
    "wof:name":"Security Network",
    "wof:placetype":"venue"
},
  "geometry": {"coordinates":[152.88767999999999,-31.44805],"type":"Point"}
}