{
  "type": "Feature",
  "properties": {
    "addr:full":"6 Bridge St West Benalla VIC 3672",
    "addr:housenumber":"6",
    "addr:postcode":"3672",
    "addr:street":"Bridge St West",
    "iso:country":"AU",
    "sg:address":"6 Bridge St West",
    "sg:city":"Benalla",
    "sg:classifiers":[
        {
            "category":"Retail",
            "subcategory":"Auto Repair",
            "type":"Services"
        }
    ],
    "sg:phone":"+61 3 5762 1266",
    "sg:postcode":"3672",
    "sg:province":"VIC",
    "sg:tags":[
        "muffler",
        "exhaust",
        "system"
    ],
    "wof:name":"Mike Glynn Motors",
    "wof:placetype":"venue"
},
  "geometry": {"coordinates":[145.976471,-36.55484],"type":"Point"}
}