{
  "type": "Feature",
  "properties": {
    "iso:country":"AU",
    "sg:address":"4/146 - 152 Cleveland St",
    "sg:city":"Chippendale",
    "sg:classifiers":[
        {
            "category":"Professional",
            "subcategory":"Printing & Photocopies",
            "type":"Services"
        }
    ],
    "sg:phone":"+61 2 9880 8089",
    "sg:postcode":"2008",
    "sg:province":"NSW",
    "sg:tags":[
        "embroidery"
    ],
    "wof:name":"L?Mark Embroidery",
    "wof:placetype":"venue"
},
  "geometry": {"coordinates":[151.198394775,-33.8883781433],"type":"Point"}
}