{
  "type": "Feature",
  "properties": {
    "iso:country":"AU",
    "sg:address":"231 Brunswick St",
    "sg:city":"Fortitude Valley",
    "sg:classifiers":[
        {
            "category":"Health Services",
            "subcategory":"Dentist",
            "type":"Services"
        }
    ],
    "sg:phone":"+61 7 3216 0216",
    "sg:postcode":"4006",
    "sg:province":"QLD",
    "wof:name":"Liu Eileen",
    "wof:placetype":"venue"
},
  "geometry": {"coordinates":[153.03268432600001,-27.4567947388],"type":"Point"}
}