{
  "type": "Feature",
  "properties": {
    "addr:full":"4 Cotter Pl Leumeah NSW 2560",
    "addr:housenumber":"4",
    "addr:postcode":"2560",
    "addr:street":"Pl",
    "iso:country":"AU",
    "sg:address":"4 Cotter Pl",
    "sg:city":"Leumeah",
    "sg:classifiers":[
        {
            "category":"Government",
            "subcategory":"Post Office",
            "type":"Public Place"
        }
    ],
    "sg:phone":"+61 2 4628 2768",
    "sg:postcode":"2560",
    "sg:province":"NSW",
    "sg:tags":[
        "chair",
        "manufacturer"
    ],
    "wof:name":"Cosmos Chairs",
    "wof:placetype":"venue"
},
  "geometry": {"coordinates":[150.83872985799999,-34.0501976013],"type":"Point"}
}