{
  "type": "Feature",
  "properties": {
    "addr:full":"16 Low St Bundaberg QLD 4670",
    "addr:housenumber":"16",
    "addr:postcode":"4670",
    "addr:street":"Low St",
    "iso:country":"AU",
    "sg:address":"16 Low St",
    "sg:city":"Bundaberg",
    "sg:classifiers":[
        {
            "category":"Home & Garden",
            "subcategory":"Carpets & Floor Coverings",
            "type":"Retail Goods"
        }
    ],
    "sg:phone":"+61 7 4155 2294",
    "sg:postcode":"4670",
    "sg:province":"QLD",
    "sg:tags":[
        "tile",
        "wall",
        "layer"
    ],
    "wof:name":"Bundaberg Concrete Cutting",
    "wof:placetype":"venue"
},
  "geometry": {"coordinates":[152.31719970699999,-24.9122753143],"type":"Point"}
}