{
  "type": "Feature",
  "properties": {
    "addr:full":"1/ 24 Thorne St Wynnum QLD 4178",
    "addr:housenumber":"/ 24",
    "addr:postcode":"4178",
    "addr:street":"Thorne St",
    "iso:country":"AU",
    "sg:address":"1/ 24 Thorne St",
    "sg:city":"Wynnum",
    "sg:classifiers":[
        {
            "category":"Real Estate",
            "subcategory":"Surveying",
            "type":"Services"
        }
    ],
    "sg:phone":"+61 7 3396 2655",
    "sg:postcode":"4178",
    "sg:province":"QLD",
    "sg:tags":[
        "surveyor",
        "marine",
        "cargo"
    ],
    "wof:name":"MCC Marine Pty Ltd",
    "wof:placetype":"venue"
},
  "geometry": {"coordinates":[153.16754150400001,-27.4394359589],"type":"Point"}
}