{
  "type": "Feature",
  "properties": {
    "addr:full":"Lot 4 Nells Rd Gosford West NSW 2250",
    "addr:postcode":"2250",
    "addr:street":"Nells Rd",
    "iso:country":"AU",
    "sg:address":"Lot 4 Nells Rd",
    "sg:city":"Gosford West",
    "sg:classifiers":[
        {
            "category":"Professional",
            "type":"Services"
        }
    ],
    "sg:phone":"+61 2 4324 4411",
    "sg:postcode":"2250",
    "sg:province":"NSW",
    "sg:tags":[
        "transport"
    ],
    "wof:name":"Toll Express",
    "wof:placetype":"venue"
},
  "geometry": {"coordinates":[151.32089233400001,-33.4184112549],"type":"Point"}
}