{
  "type": "Feature",
  "properties": {
    "iso:country":"AU",
    "sg:address":"19 Deanbilla St",
    "sg:city":"Tingalpa",
    "sg:classifiers":[
        {
            "category":"Health Services",
            "subcategory":"Doctor",
            "type":"Services"
        }
    ],
    "sg:phone":"+61 1300 669 465",
    "sg:postcode":"4173",
    "sg:province":"QLD",
    "sg:tags":[
        "occupational",
        "safety"
    ],
    "wof:name":"ABC Test & Tag Australia",
    "wof:placetype":"venue"
},
  "geometry": {"coordinates":[153.14308166500001,-27.4740753174],"type":"Point"}
}