{
  "type": "Feature",
  "properties": {
    "iso:country":"AU",
    "sg:address":"37 Fenton St",
    "sg:city":"Huntingdale",
    "sg:classifiers":[
        {
            "category":"Wholesale",
            "subcategory":"Painting Supplies",
            "type":"Manufacturing & Wholesale Goods"
        }
    ],
    "sg:phone":"+61 407 235 553",
    "sg:postcode":"3166",
    "sg:province":"VIC",
    "sg:tags":[
        "product",
        "cleaning"
    ],
    "wof:name":"Cleanco",
    "wof:placetype":"venue"
},
  "geometry": {"coordinates":[145.10958862300001,-37.9112014771],"type":"Point"}
}