{
  "type": "Feature",
  "properties": {
    "iso:country":"AU",
    "sg:address":"9 Spring St",
    "sg:city":"Forbes",
    "sg:classifiers":[
        {
            "category":"Mining & Drilling",
            "type":"Manufacturing & Wholesale Goods"
        }
    ],
    "sg:phone":"+61 2 6852 1222",
    "sg:postcode":"2871",
    "sg:province":"NSW",
    "sg:tags":[
        "boring",
        "contractor"
    ],
    "wof:name":"Department of Natural Resources",
    "wof:placetype":"venue"
},
  "geometry": {"coordinates":[148.009705,-33.384109],"type":"Point"}
}