{
  "type": "Feature",
  "properties": {
    "addr:full":"10/ 133 Terralong St Kiama NSW 2533",
    "addr:housenumber":"10 / 133",
    "addr:postcode":"2533",
    "addr:street":"Terralong St",
    "iso:country":"AU",
    "sg:address":"10/ 133 Terralong St",
    "sg:city":"Kiama",
    "sg:classifiers":[
        {
            "category":"Health Services",
            "subcategory":"Doctor",
            "type":"Services"
        }
    ],
    "sg:phone":"+61 2 4233 1155",
    "sg:postcode":"2533",
    "sg:province":"NSW",
    "sg:tags":[
        "medical",
        "practitioner"
    ],
    "wof:name":"Bakhilova Natalia Dr",
    "wof:placetype":"venue"
},
  "geometry": {"coordinates":[150.85145568900001,-34.668182373],"type":"Point"}
}