{
  "type": "Feature",
  "properties": {
    "addr:full":"3/ 20 Tradelink Rd Hillcrest QLD 4118",
    "addr:housenumber":"/ 20",
    "addr:postcode":"4118",
    "addr:street":"Tradelink Rd",
    "iso:country":"AU",
    "sg:address":"3/ 20 Tradelink Rd",
    "sg:city":"Hillcrest",
    "sg:classifiers":[
        {
            "category":"Retail",
            "subcategory":"Auto Repair",
            "type":"Services"
        }
    ],
    "sg:phone":"+61 7 3806 7260",
    "sg:postcode":"4118",
    "sg:province":"QLD",
    "sg:tags":[
        "repairer",
        "motor",
        "engineer"
    ],
    "wof:name":"Neils Automotive Servicing",
    "wof:placetype":"venue"
},
  "geometry": {"coordinates":[153.03407287600001,-27.6648235321],"type":"Point"}
}