{
  "type": "Feature",
  "properties": {
    "addr:full":"21 Denman St Eastwood NSW 2122",
    "addr:housenumber":"21",
    "addr:postcode":"2122",
    "addr:street":"Denman St",
    "iso:country":"AU",
    "sg:address":"21 Denman St",
    "sg:city":"Eastwood",
    "sg:classifiers":[
        {
            "category":"Health Services",
            "subcategory":"Health Practitioner",
            "type":"Services"
        }
    ],
    "sg:phone":"+61 2 9801 2548",
    "sg:postcode":"2122",
    "sg:province":"NSW",
    "sg:tags":[
        "naturopath"
    ],
    "wof:name":"Northern Suburbs Natural Medicine Clinic",
    "wof:placetype":"venue"
},
  "geometry": {"coordinates":[151.07043457,-33.796333313],"type":"Point"}
}