{
  "type": "Feature",
  "properties": {
    "addr:full":"283 Old Geelong Rd Hoppers Crossing VIC 3029",
    "addr:housenumber":"283",
    "addr:postcode":"3029",
    "addr:street":"Old Geelong Rd",
    "iso:country":"AU",
    "sg:address":"283 Old Geelong Rd",
    "sg:city":"Hoppers Crossing",
    "sg:classifiers":[
        {
            "category":"Building & Trades",
            "subcategory":"Construction",
            "type":"Services"
        }
    ],
    "sg:phone":"+61 3 9748 4511",
    "sg:postcode":"3029",
    "sg:province":"VIC",
    "sg:tags":[
        "concrete",
        "contractor"
    ],
    "wof:name":"Motto Nominees Pty Ltd",
    "wof:placetype":"venue"
},
  "geometry": {"coordinates":[144.719528,-37.874035],"type":"Point"}
}