{
  "type": "Feature",
  "properties": {
    "addr:full":"93 Moorindil St Tewantin QLD 4565",
    "addr:housenumber":"93",
    "addr:postcode":"4565",
    "addr:street":"Moorindil St",
    "iso:country":"AU",
    "sg:address":"93 Moorindil St",
    "sg:city":"Tewantin",
    "sg:classifiers":[
        {
            "category":"Building & Trades",
            "subcategory":"Landscaping Services",
            "type":"Services"
        }
    ],
    "sg:phone":"+61 409 793 593",
    "sg:postcode":"4565",
    "sg:province":"QLD",
    "sg:tags":[
        "designer",
        "landscape",
        "contractor"
    ],
    "wof:name":"Armfield Barrie Landscaping",
    "wof:placetype":"venue"
},
  "geometry": {"coordinates":[153.036010742,-26.385471344],"type":"Point"}
}