{
  "type": "Feature",
  "properties": {
    "addr:full":"1 Oliver St Crafers SA 5152",
    "addr:housenumber":"1",
    "addr:postcode":"5152",
    "addr:street":"Oliver St",
    "iso:country":"AU",
    "sg:address":"1 Oliver St",
    "sg:city":"Crafers",
    "sg:classifiers":[
        {
            "category":"Home & Garden",
            "subcategory":"Building Materials",
            "type":"Retail Goods"
        }
    ],
    "sg:phone":"+61 414 433 580",
    "sg:postcode":"5152",
    "sg:province":"SA",
    "sg:tags":[
        "lawn",
        "cutting",
        "maintenance"
    ],
    "wof:name":"Sutton's Lawnmowing",
    "wof:placetype":"venue"
},
  "geometry": {"coordinates":[138.72874450699999,-34.9859542847],"type":"Point"}
}