{
  "type": "Feature",
  "properties": {
    "addr:full":"Shop 2/ 348 Sydney Rd Balgowlah NSW 2093",
    "addr:housenumber":"shop 2 / 348",
    "addr:postcode":"2093",
    "addr:street":"Sydney Rd",
    "iso:country":"AU",
    "sg:address":"Shop 2/ 348 Sydney Rd",
    "sg:city":"Balgowlah",
    "sg:classifiers":[
        {
            "category":"Health Services",
            "subcategory":"Health Practitioner",
            "type":"Services"
        }
    ],
    "sg:phone":"+61 2 9907 6046",
    "sg:postcode":"2093",
    "sg:province":"NSW",
    "sg:tags":[
        "acupuncture"
    ],
    "wof:name":"Adams Ann",
    "wof:placetype":"venue"
},
  "geometry": {"coordinates":[151.26385498100001,-33.7940711975],"type":"Point"}
}