{
  "type": "Feature",
  "properties": {
    "iso:country":"AU",
    "sg:address":"278 Glenferrie Rd",
    "sg:city":"Malvern",
    "sg:classifiers":[
        {
            "category":"Retail",
            "subcategory":"Repair Shop",
            "type":"Services"
        }
    ],
    "sg:phone":"+61 3 9576 2388",
    "sg:postcode":"3144",
    "sg:province":"VIC",
    "sg:tags":[
        "mending",
        "clothing",
        "alteration"
    ],
    "wof:name":"Sew Quick",
    "wof:placetype":"venue"
},
  "geometry": {"coordinates":[145.02943420400001,-37.8567428589],"type":"Point"}
}