{
  "type": "Feature",
  "properties": {
    "iso:country":"AU",
    "sg:address":"8 Sunlight Crs",
    "sg:city":"Brighton East",
    "sg:classifiers":[
        {
            "category":"Real Estate",
            "subcategory":"Architect",
            "type":"Services"
        }
    ],
    "sg:phone":"+61 3 9553 8178",
    "sg:postcode":"3187",
    "sg:province":"VIC",
    "sg:tags":[
        "raw",
        "material",
        "plastic"
    ],
    "wof:name":"Advanced Polymer Alloys Aust Asia Pty Ltd",
    "wof:placetype":"venue"
},
  "geometry": {"coordinates":[145.01942443900001,-37.9164085388],"type":"Point"}
}