{
  "type": "Feature",
  "properties": {
    "addr:full":"28 Reid St Wangaratta VIC 3676",
    "addr:housenumber":"28",
    "addr:postcode":"3676",
    "addr:street":"Reid St",
    "iso:country":"AU",
    "sg:address":"28 Reid St",
    "sg:city":"Wangaratta",
    "sg:classifiers":[
        {
            "category":"Professional",
            "subcategory":"Engineering",
            "type":"Services"
        }
    ],
    "sg:phone":"+61 3 5721 8199",
    "sg:postcode":"3676",
    "sg:province":"VIC",
    "sg:tags":[
        "consulting",
        "engineer"
    ],
    "wof:name":"Ralph Roberts Consulting",
    "wof:placetype":"venue"
},
  "geometry": {"coordinates":[146.32681299999999,-36.355709],"type":"Point"}
}