{
  "type": "Feature",
  "properties": {
    "addr:full":"584 Malvern Rd Prahran VIC 3181",
    "addr:housenumber":"584",
    "addr:postcode":"3181",
    "addr:street":"Malvern Rd",
    "iso:country":"AU",
    "sg:address":"584 Malvern Rd",
    "sg:city":"Prahran",
    "sg:classifiers":[
        {
            "category":"Shopping",
            "subcategory":"Baby Store",
            "type":"Retail Goods"
        }
    ],
    "sg:phone":"+61 3 9533 2995",
    "sg:postcode":"3181",
    "sg:province":"VIC",
    "sg:tags":[
        "children's",
        "wear"
    ],
    "wof:name":"House For Kids",
    "wof:placetype":"venue"
},
  "geometry": {"coordinates":[145.005737305,-37.8485298157],"type":"Point"}
}