{
  "type": "Feature",
  "properties": {
    "addr:full":"8 Woodside Rd Lobethal SA 5241",
    "addr:housenumber":"8",
    "addr:postcode":"5241",
    "addr:street":"Woodside Rd",
    "iso:country":"AU",
    "sg:address":"8 Woodside Rd",
    "sg:city":"Lobethal",
    "sg:classifiers":[
        {
            "category":"Travel",
            "subcategory":"Hostel",
            "type":"Entertainment"
        }
    ],
    "sg:phone":"+61 8 8389 6212",
    "sg:postcode":"5241",
    "sg:province":"SA",
    "sg:tags":[
        "home"
    ],
    "wof:name":"Restvale Lobethal & District Aged Homes Inc.",
    "wof:placetype":"venue"
},
  "geometry": {"coordinates":[138.87542724599999,-34.9088439941],"type":"Point"}
}