{
  "type": "Feature",
  "properties": {
    "addr:full":"1/ 20 Canham Way Greenwood WA 6024",
    "addr:housenumber":"/ 20",
    "addr:postcode":"6024",
    "addr:street":"Canham Way",
    "iso:country":"AU",
    "sg:address":"1/ 20",
    "sg:city":"Canham Way Greenwood",
    "sg:classifiers":[
        {
            "category":"Building & Trades",
            "subcategory":"Construction",
            "type":"Services"
        }
    ],
    "sg:phone":"+61 417 770 010",
    "sg:postcode":"6024",
    "sg:province":"WA",
    "sg:tags":[
        "tennis court",
        "repair"
    ],
    "wof:name":"Evergreen Synthetic Grass Surfacing",
    "wof:placetype":"venue"
},
  "geometry": {"coordinates":[115.818992615,-31.8213481903],"type":"Point"}
}