{
  "type": "Feature",
  "properties": {
    "addr:full":"30 Curl Curl Pde Curl Curl NSW 2096",
    "addr:housenumber":"30",
    "addr:postcode":"2096",
    "addr:street":"Curl Pde",
    "iso:country":"AU",
    "sg:address":"30 Curl Curl Pde",
    "sg:city":"Curl Curl",
    "sg:classifiers":[
        {
            "category":"Manufacturing",
            "subcategory":"Metals",
            "type":"Manufacturing & Wholesale Goods"
        }
    ],
    "sg:phone":"+61 2 9939 1250",
    "sg:postcode":"2096",
    "sg:province":"NSW",
    "sg:tags":[
        "steel",
        "fabricator",
        "mfrs"
    ],
    "wof:name":"Mark Taylor Engineering Pty Ltd",
    "wof:placetype":"venue"
},
  "geometry": {"coordinates":[151.29060363799999,-33.7707328796],"type":"Point"}
}