{
  "type": "Feature",
  "properties": {
    "addr:full":"12 Ithaca Rd Elizabeth Bay NSW 2011",
    "addr:housenumber":"12",
    "addr:postcode":"2011",
    "addr:street":"Ithaca Rd",
    "iso:country":"AU",
    "sg:address":"12 Ithaca Rd",
    "sg:city":"Elizabeth Bay",
    "sg:classifiers":[
        {
            "category":"Banks & Credit Unions",
            "subcategory":"Bank",
            "type":"Services"
        }
    ],
    "sg:phone":"+61 2 9358 4745",
    "sg:postcode":"2011",
    "sg:province":"NSW",
    "sg:tags":[
        "broker",
        "mortgage"
    ],
    "wof:name":"Residential One",
    "wof:placetype":"venue"
},
  "geometry": {"coordinates":[151.22883605999999,-33.8721008301],"type":"Point"}
}