{
  "type": "Feature",
  "properties": {
    "addr:full":"121 William St Melbourne VIC 3000",
    "addr:housenumber":"121",
    "addr:postcode":"3000",
    "addr:street":"William St",
    "iso:country":"AU",
    "sg:address":"121 William St",
    "sg:city":"Melbourne",
    "sg:classifiers":[
        {
            "category":"Personal",
            "subcategory":"Beauty Salon",
            "type":"Services"
        }
    ],
    "sg:phone":"+61 3 9614 2508",
    "sg:postcode":"3000",
    "sg:province":"VIC",
    "sg:tags":[
        "hairdresser"
    ],
    "wof:name":"Maggio Laurence",
    "wof:placetype":"venue"
},
  "geometry": {"coordinates":[144.958496094,-37.8166122437],"type":"Point"}
}