{
  "type": "Feature",
  "properties": {
    "addr:full":"25 Lydiate Rd Noarlunga Downs SA 5168",
    "addr:housenumber":"25",
    "addr:postcode":"5168",
    "addr:street":"Lydiate Rd",
    "iso:country":"AU",
    "sg:address":"25 Lydiate Rd",
    "sg:city":"Noarlunga Downs",
    "sg:classifiers":[
        {
            "category":"Professional",
            "subcategory":"Business Services",
            "type":"Services"
        }
    ],
    "sg:phone":"+61 8 8326 5999",
    "sg:postcode":"5168",
    "sg:province":"SA",
    "sg:tags":[
        "drafting"
    ],
    "wof:name":"Ellis Drafting Services",
    "wof:placetype":"venue"
},
  "geometry": {"coordinates":[138.50283813499999,-35.1581840515],"type":"Point"}
}