{
  "type": "Feature",
  "properties": {
    "addr:full":"Unit 5/ 75 Main South Rd O&#039;Halloran Hill SA 5158",
    "addr:housenumber":"75",
    "addr:postcode":"5158",
    "addr:street":"Main South Rd;Halloran Hill",
    "iso:country":"AU",
    "sg:address":"Unit 5/ 75 Main South Rd",
    "sg:city":"O&#039;Halloran Hill",
    "sg:classifiers":[
        {
            "category":"Personal",
            "subcategory":"Massage",
            "type":"Services"
        }
    ],
    "sg:phone":"+61 417 884 364",
    "sg:postcode":"5158",
    "sg:province":"SA",
    "sg:tags":[
        "therapy"
    ],
    "wof:name":"Hilltop Natural Therapies",
    "wof:placetype":"venue"
},
  "geometry": {"coordinates":[138.555419922,-35.066619873],"type":"Point"}
}