{
  "type": "Feature",
  "properties": {
    "addr:full":"U1/ 4 Clyde St Kew East VIC 3102",
    "addr:housenumber":"4",
    "addr:postcode":"3102",
    "addr:street":"U1 /;Clyde St",
    "iso:country":"AU",
    "sg:address":"U1/ 4 Clyde St",
    "sg:city":"Kew East",
    "sg:classifiers":[
        {
            "category":"Arts & Performance",
            "subcategory":"Music",
            "type":"Entertainment"
        }
    ],
    "sg:phone":"+61 3 9859 6501",
    "sg:postcode":"3102",
    "sg:province":"VIC",
    "sg:tags":[
        "mobile",
        "jockey",
        "disc"
    ],
    "wof:name":"Entire Sound",
    "wof:placetype":"venue"
},
  "geometry": {"coordinates":[145.05516052199999,-37.7967529297],"type":"Point"}
}