{
  "type": "Feature",
  "properties": {
    "addr:full":"Drouin Rd Poowong VIC 3988",
    "addr:postcode":"3988",
    "addr:street":"Drouin Rd",
    "iso:country":"AU",
    "sg:address":"Drouin Rd",
    "sg:city":"Poowong",
    "sg:classifiers":[
        {
            "category":"Farming",
            "subcategory":"Farm",
            "type":"Manufacturing & Wholesale Goods"
        }
    ],
    "sg:phone":"+61 3 5659 2256",
    "sg:postcode":"3988",
    "sg:province":"VIC",
    "sg:tags":[
        "farmer"
    ],
    "wof:name":"Douglas J G & M L",
    "wof:placetype":"venue"
},
  "geometry": {"coordinates":[145.76388549800001,-38.3430290222],"type":"Point"}
}