{
  "type": "Feature",
  "properties": {
    "addr:full":"20 Nagle St Wagga Wagga NSW 2650",
    "addr:housenumber":"20",
    "addr:postcode":"2650",
    "addr:street":"Nagle St",
    "iso:country":"AU",
    "sg:address":"20 Nagle St",
    "sg:city":"Wagga Wagga",
    "sg:classifiers":[
        {
            "category":"Wholesale",
            "subcategory":"Machinery & Supplies",
            "type":"Manufacturing & Wholesale Goods"
        }
    ],
    "sg:phone":"+61 2 6921 7298",
    "sg:postcode":"2650",
    "sg:province":"NSW",
    "sg:tags":[
        "engineer"
    ],
    "wof:name":"Blutung Industries",
    "wof:placetype":"venue"
},
  "geometry": {"coordinates":[147.38230895999999,-35.1234207153],"type":"Point"}
}