{
  "type": "Feature",
  "properties": {
    "addr:full":"4 Rusham Pl Morley WA 6062",
    "addr:housenumber":"4",
    "addr:postcode":"6062",
    "addr:street":"Rusham Pl",
    "iso:country":"AU",
    "sg:address":"4 Rusham Pl",
    "sg:city":"Morley",
    "sg:classifiers":[
        {
            "category":"Building & Trades",
            "subcategory":"Plumbing",
            "type":"Services"
        }
    ],
    "sg:phone":"+61 408 001 337",
    "sg:postcode":"6062",
    "sg:province":"WA",
    "sg:tags":[
        "plumber",
        "gasfitters"
    ],
    "wof:name":"Brams Plumbing and Gas",
    "wof:placetype":"venue"
},
  "geometry": {"coordinates":[115.90952301,-31.8814945221],"type":"Point"}
}