{
  "type": "Feature",
  "properties": {
    "addr:full":"4 Moffat St Goondiwindi QLD 4390",
    "addr:housenumber":"4",
    "addr:postcode":"4390",
    "addr:street":"Moffat St",
    "iso:country":"AU",
    "sg:address":"4 Moffat St",
    "sg:city":"Goondiwindi",
    "sg:classifiers":[
        {
            "category":"Autos & Motor Vehicles",
            "subcategory":"Automobile Sales",
            "type":"Retail Goods"
        }
    ],
    "sg:phone":"+61 7 4671 1194",
    "sg:postcode":"4390",
    "sg:province":"QLD",
    "sg:tags":[
        "car",
        "new"
    ],
    "wof:name":"Jack Roses Garage Pty Ltd",
    "wof:placetype":"venue"
},
  "geometry": {"coordinates":[150.302856445,-28.5471286774],"type":"Point"}
}