{
  "type": "Feature",
  "properties": {
    "addr:full":"17a Market St South Melbourne VIC 3205",
    "addr:housenumber":"17a",
    "addr:postcode":"3205",
    "addr:street":"Market St",
    "iso:country":"AU",
    "sg:address":"17a Market St",
    "sg:city":"South Melbourne",
    "sg:classifiers":[
        {
            "category":"Shopping",
            "subcategory":"Computers & Home Electronics",
            "type":"Retail Goods"
        }
    ],
    "sg:phone":"+61 3 9690 5499",
    "sg:postcode":"3205",
    "sg:province":"VIC",
    "sg:tags":[
        "equipment",
        "multimedia"
    ],
    "wof:name":"Video Copy Centre Pty Ltd",
    "wof:placetype":"venue"
},
  "geometry": {"coordinates":[144.96315000000001,-37.833374],"type":"Point"}
}