{
  "type": "Feature",
  "properties": {
    "addr:full":"Shop GA 16, Gallery Level Toowong Village Shopping Toowong QLD 4066",
    "addr:housenumber":"16",
    "addr:postcode":"4066",
    "addr:street":"Ga",
    "iso:country":"AU",
    "sg:address":"Shop GA 16, Gallery Level Toowong Village Shopping",
    "sg:city":"Toowong",
    "sg:classifiers":[
        {
            "category":"Wholesale",
            "subcategory":"Apparel",
            "type":"Manufacturing & Wholesale Goods"
        }
    ],
    "sg:phone":"+61 7 3870 2393",
    "sg:postcode":"4066",
    "sg:province":"QLD",
    "sg:tags":[
        "wholesaler",
        "mfrs",
        "sportswear",
        "women's"
    ],
    "sg:website":"http://www.ozactivewear.com.au",
    "wof:name":"Oz Activewear Pty Ltd",
    "wof:placetype":"venue"
},
  "geometry": {"coordinates":[152.99188232399999,-27.4853534698],"type":"Point"}
}