{
  "type": "Feature",
  "properties": {
    "addr:full":"Level 6 241 Commonwealth St Surry Hills NSW 2010",
    "addr:housenumber":"241",
    "addr:postcode":"2010",
    "addr:street":"Commonwealth St",
    "iso:country":"AU",
    "sg:address":"Level 6 241 Commonwealth St",
    "sg:city":"Surry Hills",
    "sg:classifiers":[
        {
            "category":"Education",
            "subcategory":"Special Training",
            "type":"Public Place"
        }
    ],
    "sg:phone":"+61 2 9005 0700",
    "sg:postcode":"2010",
    "sg:province":"NSW",
    "sg:tags":[
        "development"
    ],
    "wof:name":"Terrapinn (Australia) Pty Ltd",
    "wof:placetype":"venue"
},
  "geometry": {"coordinates":[151.20979309099999,-33.8835067749],"type":"Point"}
}