{
  "type": "Feature",
  "properties": {
    "addr:full":"21 Hewish Rd Croydon VIC 3136",
    "addr:housenumber":"21",
    "addr:postcode":"3136",
    "addr:street":"Hewish Rd",
    "iso:country":"AU",
    "sg:address":"21 Hewish Rd",
    "sg:city":"Croydon",
    "sg:classifiers":[
        {
            "category":"Retail",
            "subcategory":"Auto Repair",
            "type":"Services"
        }
    ],
    "sg:phone":"+61 3 9723 2108",
    "sg:postcode":"3136",
    "sg:province":"VIC",
    "sg:tags":[
        "beater",
        "painter",
        "panel"
    ],
    "wof:name":"Clark's Body Works Pty Ltd",
    "wof:placetype":"venue"
},
  "geometry": {"coordinates":[145.284866333,-37.7962837219],"type":"Point"}
}