{
  "type": "Feature",
  "properties": {
    "addr:full":"53 Frenches Forest Rd Seaforth NSW 2092",
    "addr:housenumber":"53",
    "addr:postcode":"2092",
    "addr:street":"Frenches Forest Rd",
    "iso:country":"AU",
    "sg:address":"53 Frenches Forest Rd",
    "sg:city":"Seaforth",
    "sg:classifiers":[
        {
            "category":"Professional",
            "subcategory":"Business Services",
            "type":"Services"
        }
    ],
    "sg:phone":"+61 431 972 759",
    "sg:postcode":"2092",
    "sg:province":"NSW",
    "sg:tags":[
        "drafting"
    ],
    "wof:name":"Teknick Drafting",
    "wof:placetype":"venue"
},
  "geometry": {"coordinates":[151.24876403799999,-33.7934303284],"type":"Point"}
}