{
  "type": "Feature",
  "properties": {
    "addr:full":"5 Ludgate St Concord NSW 2137",
    "addr:housenumber":"5",
    "addr:postcode":"2137",
    "addr:street":"Ludgate St",
    "iso:country":"AU",
    "sg:address":"5 Ludgate St",
    "sg:city":"Concord",
    "sg:classifiers":[
        {
            "category":"Building & Trades",
            "subcategory":"Construction",
            "type":"Services"
        }
    ],
    "sg:phone":"+61 2 9743 2659",
    "sg:postcode":"2137",
    "sg:province":"NSW",
    "sg:tags":[
        "contractor"
    ],
    "wof:name":"Richards Darren & Norm Building Contractors",
    "wof:placetype":"venue"
},
  "geometry": {"coordinates":[151.10122680699999,-33.858631134],"type":"Point"}
}