{
  "type": "Feature",
  "properties": {
    "addr:full":"7/ 131 St Pauls Tce Spring Hill QLD 4000",
    "addr:housenumber":"/ 131",
    "addr:postcode":"4000",
    "addr:street":"St Pauls Tce",
    "iso:country":"AU",
    "sg:address":"7/ 131 St Pauls Tce",
    "sg:city":"Spring Hill",
    "sg:classifiers":[
        {
            "category":"Shopping",
            "subcategory":"Clothing, Apparel, & Fashions",
            "type":"Retail Goods"
        }
    ],
    "sg:phone":"+61 423 260 964",
    "sg:postcode":"4000",
    "sg:province":"QLD",
    "sg:tags":[
        "textile",
        "designer"
    ],
    "wof:name":"SIZEdesign",
    "wof:placetype":"venue"
},
  "geometry": {"coordinates":[153.02885437,-27.4590435028],"type":"Point"}
}