{
  "type": "Feature",
  "properties": {
    "addr:full":"41 Kyeema Ave Cumberland Park SA 5041",
    "addr:housenumber":"41",
    "addr:postcode":"5041",
    "addr:street":"Kyeema Ave",
    "iso:country":"AU",
    "sg:address":"41 Kyeema Ave",
    "sg:city":"Cumberland Park",
    "sg:classifiers":[
        {
            "category":"Professional",
            "subcategory":"Employment Agencies",
            "type":"Services"
        }
    ],
    "sg:phone":"+61 8 8271 8690",
    "sg:postcode":"5041",
    "sg:province":"SA",
    "sg:tags":[
        "entertainer",
        "agent"
    ],
    "wof:name":"Magic For All Occasions",
    "wof:placetype":"venue"
},
  "geometry": {"coordinates":[138.58689899999999,-34.97451],"type":"Point"}
}