{
  "type": "Feature",
  "properties": {
    "addr:full":"3/16 Nelson St Fairfield NSW 2165",
    "addr:housenumber":"/ 16",
    "addr:postcode":"2165",
    "addr:street":"Nelson St",
    "iso:country":"AU",
    "sg:address":"3/16 Nelson St",
    "sg:city":"Fairfield",
    "sg:classifiers":[
        {
            "category":"Real Estate",
            "subcategory":"Real Estate Agent",
            "type":"Services"
        }
    ],
    "sg:phone":"+61 2 9727 5122",
    "sg:postcode":"2165",
    "sg:province":"NSW",
    "wof:name":"Professionals Real Estate",
    "wof:placetype":"venue"
},
  "geometry": {"coordinates":[150.94796752900001,-33.8717460632],"type":"Point"}
}