{
  "type": "Feature",
  "properties": {
    "addr:full":"1 Vernon Ave Heidelberg Heights VIC 3081",
    "addr:housenumber":"1",
    "addr:postcode":"3081",
    "addr:street":"Vernon Ave",
    "iso:country":"AU",
    "sg:address":"1 Vernon Ave",
    "sg:city":"Heidelberg Heights",
    "sg:classifiers":[
        {
            "category":"Home & Garden",
            "subcategory":"Household Appliances",
            "type":"Retail Goods"
        }
    ],
    "sg:phone":"+61 3 9457 2912",
    "sg:postcode":"3081",
    "sg:province":"VIC",
    "sg:tags":[
        "equipment",
        "gas"
    ],
    "wof:name":"Northern Gas & Electric",
    "wof:placetype":"venue"
},
  "geometry": {"coordinates":[145.05406189000001,-37.7326507568],"type":"Point"}
}