{
  "type": "Feature",
  "properties": {
    "addr:full":"305 Kelvin Grove Rd Kelvin Grove QLD 4059",
    "addr:housenumber":"305",
    "addr:postcode":"4059",
    "addr:street":"Kelvin Grove Rd",
    "iso:country":"AU",
    "sg:address":"305 Kelvin Grove Rd",
    "sg:city":"Kelvin Grove",
    "sg:classifiers":[
        {
            "category":"Retail",
            "subcategory":"Auto Repair",
            "type":"Services"
        }
    ],
    "sg:phone":"+61 7 3356 5999",
    "sg:postcode":"4059",
    "sg:province":"QLD",
    "sg:tags":[
        "repairer",
        "motor",
        "engineer"
    ],
    "wof:name":"Kelvin Grove Cab Centre",
    "wof:placetype":"venue"
},
  "geometry": {"coordinates":[153.00828552199999,-27.4452171326],"type":"Point"}
}