{
  "type": "Feature",
  "properties": {
    "iso:country":"AU",
    "sg:address":"72 Henderson Rd",
    "sg:city":"Saratoga",
    "sg:classifiers":[
        {
            "category":"Personal",
            "subcategory":"Beauty Salon",
            "type":"Services"
        }
    ],
    "sg:phone":"+61 2 4369 1512",
    "sg:postcode":"2251",
    "sg:province":"NSW",
    "sg:tags":[
        "hairdresser"
    ],
    "wof:name":"The Chill Zone",
    "wof:placetype":"venue"
},
  "geometry": {"coordinates":[151.344192505,-33.4804191589],"type":"Point"}
}