{
  "type": "Feature",
  "properties": {
    "iso:country":"AU",
    "sg:address":"828 Ocean Drv",
    "sg:city":"Bonny Hills",
    "sg:classifiers":[
        {
            "category":"Professional",
            "subcategory":"Art Services",
            "type":"Services"
        }
    ],
    "sg:phone":"+61 2 6584 8259",
    "sg:postcode":"2445",
    "sg:province":"NSW",
    "sg:tags":[
        "picture",
        "frame",
        "framing"
    ],
    "wof:name":"Legends On The Wall",
    "wof:placetype":"venue"
},
  "geometry": {"coordinates":[152.840927,-31.598455],"type":"Point"}
}