{
  "type": "Feature",
  "properties": {
    "addr:full":"32 Cromie St Rupanyup VIC 3388",
    "addr:housenumber":"32",
    "addr:postcode":"3388",
    "addr:street":"Cromie St",
    "iso:country":"AU",
    "sg:address":"32 Cromie St",
    "sg:city":"Rupanyup",
    "sg:classifiers":[
        {
            "category":"Banks & Credit Unions",
            "subcategory":"Bank",
            "type":"Services"
        }
    ],
    "sg:phone":"+61 3 5385 5320",
    "sg:postcode":"3388",
    "sg:province":"VIC",
    "wof:name":"Rupanyup/Minyip Community Bank Branch Of Bendigo Bank",
    "wof:placetype":"venue"
},
  "geometry": {"coordinates":[142.63075256400001,-36.6311531067],"type":"Point"}
}