{
  "type": "Feature",
  "properties": {
    "iso:country":"AU",
    "sg:address":"46 King St",
    "sg:city":"Prahran",
    "sg:classifiers":[
        {
            "category":"Professional",
            "subcategory":"Engineering",
            "type":"Services"
        }
    ],
    "sg:phone":"+61 3 9529 3250",
    "sg:postcode":"3181",
    "sg:province":"VIC",
    "sg:tags":[
        "engineer",
        "mechanical"
    ],
    "wof:name":"Prahran Motors Pty Ltd",
    "wof:placetype":"venue"
},
  "geometry": {"coordinates":[144.99661254899999,-37.8502922058],"type":"Point"}
}