{
  "type": "Feature",
  "properties": {
    "addr:full":"62 Lt Collins St Melbourne VIC 3000",
    "addr:housenumber":"62",
    "addr:postcode":"3000",
    "addr:street":"Lt Collins St",
    "iso:country":"AU",
    "sg:address":"62 Lt Collins St",
    "sg:city":"Melbourne",
    "sg:classifiers":[
        {
            "category":"Travel",
            "subcategory":"Hotels & Motels",
            "type":"Entertainment"
        }
    ],
    "sg:phone":"+61 3 9650 0840",
    "sg:postcode":"3000",
    "sg:province":"VIC",
    "sg:tags":[
        "pub"
    ],
    "wof:name":"Bridie O&#039;Reillys",
    "wof:placetype":"venue"
},
  "geometry": {"coordinates":[144.970611572,-37.8142967224],"type":"Point"}
}