{
  "type": "Feature",
  "properties": {
    "iso:country":"AU",
    "sg:address":"Shop 38, The Village Centre, Charles Hackett Drv",
    "sg:city":"St Marys",
    "sg:classifiers":[
        {
            "category":"Food & Beverages",
            "subcategory":"Bakery",
            "type":"Retail Goods"
        }
    ],
    "sg:phone":"+61 2 9833 4466",
    "sg:postcode":"2760",
    "sg:province":"NSW",
    "sg:tags":[
        "baker"
    ],
    "wof:name":"Bakers Delight Ltd",
    "wof:placetype":"venue"
},
  "geometry": {"coordinates":[150.77325439399999,-33.7656478882],"type":"Point"}
}