{
  "type": "Feature",
  "properties": {
    "addr:full":"484 Blackbutt Rd Herons Creek NSW 2443",
    "addr:housenumber":"484",
    "addr:postcode":"2443",
    "addr:street":"Blackbutt Rd",
    "iso:country":"AU",
    "sg:address":"484 Blackbutt Rd",
    "sg:city":"Herons Creek",
    "sg:classifiers":[
        {
            "category":"Banks & Credit Unions",
            "subcategory":"Bureau De Change",
            "type":"Services"
        }
    ],
    "sg:phone":"+61 2 6585 7160",
    "sg:postcode":"2443",
    "sg:province":"NSW",
    "sg:tags":[
        "escort",
        "transport",
        "pilot"
    ],
    "wof:name":"Blackbutt Pilot Service",
    "wof:placetype":"venue"
},
  "geometry": {"coordinates":[152.689514,-31.564177],"type":"Point"}
}