{
  "type": "Feature",
  "properties": {
    "addr:full":"104 Woods St Donald VIC 3480",
    "addr:housenumber":"104",
    "addr:postcode":"3480",
    "addr:street":"Woods St",
    "iso:country":"AU",
    "sg:address":"104 Woods St",
    "sg:city":"Donald",
    "sg:classifiers":[
        {
            "category":"Autos & Motor Vehicles",
            "subcategory":"Auto Supplies",
            "type":"Retail Goods"
        }
    ],
    "sg:phone":"+61 3 5497 1150",
    "sg:postcode":"3480",
    "sg:province":"VIC",
    "sg:tags":[
        "oil",
        "spirit"
    ],
    "wof:name":"Woolman Petroleum",
    "wof:placetype":"venue"
},
  "geometry": {"coordinates":[142.983444214,-36.3717689514],"type":"Point"}
}