{
  "type": "Feature",
  "properties": {
    "addr:full":"42 Mudgee St Burwood East VIC 3151",
    "addr:housenumber":"42",
    "addr:postcode":"3151",
    "addr:street":"Mudgee St",
    "iso:country":"AU",
    "sg:address":"42 Mudgee St",
    "sg:city":"Burwood East",
    "sg:classifiers":[
        {
            "category":"Professional",
            "subcategory":"Management & Consulting",
            "type":"Services"
        }
    ],
    "sg:phone":"+61 417 351 146",
    "sg:postcode":"3151",
    "sg:province":"VIC",
    "sg:tags":[
        "consultant",
        "business"
    ],
    "wof:name":"Clearview Business Advisory",
    "wof:placetype":"venue"
},
  "geometry": {"coordinates":[145.14083862300001,-37.8558273315],"type":"Point"}
}