{
  "type": "Feature",
  "properties": {
    "iso:country":"AU",
    "sg:address":"Suite 105, 91 O'Sullivan Rd",
    "sg:city":"Rose Bay",
    "sg:classifiers":[
        {
            "category":"Sports & Exercise",
            "subcategory":"Gym",
            "type":"Entertainment"
        }
    ],
    "sg:phone":"+61 2 9327 2498",
    "sg:postcode":"2029",
    "sg:province":"NSW",
    "sg:tags":[
        "pilate",
        "method"
    ],
    "wof:name":"Integrated Movement Studio",
    "wof:placetype":"venue"
},
  "geometry": {"coordinates":[151.267852783,-33.8850021362],"type":"Point"}
}