{
  "type": "Feature",
  "properties": {
    "iso:country":"AU",
    "sg:address":"Unit 2 34 Elystan Rd",
    "sg:city":"New Farm",
    "sg:classifiers":[
        {
            "category":"Personal",
            "subcategory":"Beauty Salon",
            "type":"Services"
        }
    ],
    "sg:phone":"+61 7 3254 1606",
    "sg:postcode":"4005",
    "sg:province":"QLD",
    "wof:name":"New Farm Nail Studio, The",
    "wof:placetype":"venue"
},
  "geometry": {"coordinates":[153.049591064,-27.4711475372],"type":"Point"}
}