{
  "type": "Feature",
  "properties": {
    "addr:full":"5/ 9 Campbell St Frankston VIC 3199",
    "addr:housenumber":"/ 9",
    "addr:postcode":"3199",
    "addr:street":"Campbell St",
    "iso:country":"AU",
    "sg:address":"5/ 9 Campbell St",
    "sg:city":"Frankston",
    "sg:classifiers":[
        {
            "category":"Professional",
            "subcategory":"Art Services",
            "type":"Services"
        }
    ],
    "sg:phone":"+61 419 399 968",
    "sg:postcode":"3199",
    "sg:province":"VIC",
    "sg:tags":[
        "decorator",
        "painter"
    ],
    "wof:name":"All Painting & Decoration",
    "wof:placetype":"venue"
},
  "geometry": {"coordinates":[145.3568573,-38.0335044861],"type":"Point"}
}