{
  "type": "Feature",
  "properties": {
    "addr:full":"122 Charters Towers Rd Hermit Park QLD 4812",
    "addr:housenumber":"122",
    "addr:postcode":"4812",
    "addr:street":"Charters Towers Rd",
    "iso:country":"AU",
    "sg:address":"122 Charters Towers Rd",
    "sg:city":"Hermit Park",
    "sg:classifiers":[
        {
            "category":"Professional",
            "subcategory":"Business Services",
            "type":"Services"
        }
    ],
    "sg:phone":"+61 7 4771 3555",
    "sg:postcode":"4812",
    "sg:province":"QLD",
    "sg:tags":[
        "management",
        "event"
    ],
    "wof:name":"Wedding Works Qld",
    "wof:placetype":"venue"
},
  "geometry": {"coordinates":[146.800095,-19.277212],"type":"Point"}
}