{
  "type": "Feature",
  "properties": {
    "iso:country":"AU",
    "sg:address":"Cordwell Rd",
    "sg:city":"Yandina",
    "sg:classifiers":[
        {
            "category":"Home & Garden",
            "subcategory":"Building Materials",
            "type":"Retail Goods"
        }
    ],
    "sg:phone":"+61 7 5446 7204",
    "sg:postcode":"4561",
    "sg:province":"QLD",
    "sg:tags":[
        "supply"
    ],
    "wof:name":"Cordwells Concrete",
    "wof:placetype":"venue"
},
  "geometry": {"coordinates":[152.95625305199999,-26.5696144104],"type":"Point"}
}