{
  "type": "Feature",
  "properties": {
    "addr:full":"83 Barrabool Rd Highton VIC 3216",
    "addr:housenumber":"83",
    "addr:postcode":"3216",
    "addr:street":"Barrabool Rd",
    "iso:country":"AU",
    "sg:address":"83 Barrabool Rd",
    "sg:city":"Highton",
    "sg:classifiers":[
        {
            "category":"Airline",
            "type":"Transportation"
        }
    ],
    "sg:phone":"+61 3 5243 9311",
    "sg:postcode":"3216",
    "sg:province":"VIC",
    "sg:tags":[
        "agent"
    ],
    "wof:name":"Highton Travel Fishing Tours",
    "wof:placetype":"venue"
},
  "geometry": {"coordinates":[144.323486328,-38.1719932556],"type":"Point"}
}