{
  "type": "Feature",
  "properties": {
    "addr:full":"41 Ealing Crs Springvale South VIC 3172",
    "addr:housenumber":"41",
    "addr:postcode":"3172",
    "addr:street":"Ealing Crs",
    "iso:country":"AU",
    "sg:address":"41 Ealing Crs",
    "sg:city":"Springvale South",
    "sg:classifiers":[
        {
            "category":"Wholesale",
            "subcategory":"Music Publishers",
            "type":"Manufacturing & Wholesale Goods"
        }
    ],
    "sg:phone":"+61 3 9547 0503",
    "sg:postcode":"3172",
    "sg:province":"VIC",
    "sg:tags":[
        "wholesaler",
        "dvd",
        "mfrs",
        "cd"
    ],
    "wof:name":"Copyrom",
    "wof:placetype":"venue"
},
  "geometry": {"coordinates":[145.147583008,-37.9785614014],"type":"Point"}
}