{
  "type": "Feature",
  "properties": {
    "addr:full":"99 Marshall St Goondiwindi QLD 4390",
    "addr:housenumber":"99",
    "addr:postcode":"4390",
    "addr:street":"Marshall St",
    "iso:country":"AU",
    "sg:address":"99 Marshall St",
    "sg:city":"Goondiwindi",
    "sg:classifiers":[
        {
            "category":"Shopping",
            "subcategory":"Clothing, Apparel, & Fashions",
            "type":"Retail Goods"
        }
    ],
    "sg:phone":"+61 7 4671 1311",
    "sg:postcode":"4390",
    "sg:province":"QLD",
    "sg:tags":[
        "lady",
        "wear"
    ],
    "wof:name":"Stage One Fashions",
    "wof:placetype":"venue"
},
  "geometry": {"coordinates":[150.30633544899999,-28.5469398499],"type":"Point"}
}