{
  "type": "Feature",
  "properties": {
    "iso:country":"AU",
    "sg:address":"177 Railway Pde",
    "sg:city":"Mt Lawley",
    "sg:classifiers":[
        {
            "category":"Home & Garden",
            "subcategory":"Carpets & Floor Coverings",
            "type":"Retail Goods"
        }
    ],
    "sg:phone":"+61 8 9271 4363",
    "sg:postcode":"6050",
    "sg:province":"WA",
    "sg:tags":[
        "flooring",
        "parquet"
    ],
    "wof:name":"Perth Timber Floors",
    "wof:placetype":"venue"
},
  "geometry": {"coordinates":[115.888343811,-31.9303665161],"type":"Point"}
}