{
  "type": "Feature",
  "properties": {
    "addr:full":"Shop 25 MacTaggarts Place, 53 Vernon Terrace, Teneriffe QLD 4005",
    "addr:housenumber":"shop 25;53",
    "addr:postcode":"4005",
    "addr:street":"Mactaggarts Place;Vernon Terrace",
    "iso:country":"AU",
    "sg:address":"Shop 25 MacTaggarts Place, 53",
    "sg:city":"Vernon Terrace, Teneriffe",
    "sg:classifiers":[
        {
            "category":"Retail",
            "subcategory":"Event Space",
            "type":"Services"
        }
    ],
    "sg:phone":"+61 7 3216 0726",
    "sg:postcode":"4005",
    "sg:province":"QLD",
    "sg:tags":[
        "venue",
        "reception",
        "wedding"
    ],
    "wof:name":"Eves On The River",
    "wof:placetype":"venue"
},
  "geometry": {"coordinates":[153.04974365199999,-27.4550590515],"type":"Point"}
}