{
  "type": "Feature",
  "properties": {
    "addr:full":"24 Bissenberger Crs Kambah ACT 2902",
    "addr:housenumber":"24",
    "addr:postcode":"2902",
    "addr:street":"Bissenberger Crs",
    "iso:country":"AU",
    "sg:address":"24 Bissenberger Crs",
    "sg:city":"Kambah",
    "sg:classifiers":[
        {
            "category":"Retail",
            "subcategory":"Repair Shop",
            "type":"Services"
        }
    ],
    "sg:phone":"+61 2 6231 7527",
    "sg:postcode":"2902",
    "sg:province":"ACT",
    "sg:tags":[
        "repairing",
        "piano",
        "tuning"
    ],
    "wof:name":"Greig I",
    "wof:placetype":"venue"
},
  "geometry": {"coordinates":[149.06053161599999,-35.3863983154],"type":"Point"}
}