{
  "type": "Feature",
  "properties": {
    "addr:full":"Shp 6a/ 22 Salmon Gum Rd Kambalda West WA 6442",
    "addr:housenumber":"6a / 22",
    "addr:postcode":"6442",
    "addr:street":"Salmon Gum Rd",
    "iso:country":"AU",
    "sg:address":"Shp 6a/ 22 Salmon Gum Rd",
    "sg:city":"Kambalda West",
    "sg:classifiers":[
        {
            "category":"Fast Food",
            "type":"Food & Drink"
        }
    ],
    "sg:phone":"+61 8 9027 3880",
    "sg:postcode":"6442",
    "sg:province":"WA",
    "sg:tags":[
        "away",
        "take"
    ],
    "wof:name":"Eat Pizza Kambalda",
    "wof:placetype":"venue"
},
  "geometry": {"coordinates":[121.622817993,-31.210269928],"type":"Point"}
}