{
  "type": "Feature",
  "properties": {
    "addr:full":"PO Box 7051 Spearwood WA 6163",
    "addr:postcode":"6163",
    "iso:country":"AU",
    "sg:address":"PO Box 7051",
    "sg:city":"Spearwood",
    "sg:classifiers":[
        {
            "category":"Shopping",
            "subcategory":"Stationery & Office Supplies",
            "type":"Retail Goods"
        }
    ],
    "sg:phone":"+61 413 475 837",
    "sg:postcode":"6163",
    "sg:province":"WA",
    "sg:tags":[
        "equipment",
        "display",
        "exhibition"
    ],
    "wof:name":"W.A. Exhibition Rentals",
    "wof:placetype":"venue"
},
  "geometry": {"coordinates":[115.78273,-32.114769],"type":"Point"}
}