{
  "type": "Feature",
  "properties": {
    "addr:full":"Unit 1, 4 Dalrymple Drv Gladstone QLD 4680",
    "addr:housenumber":"4",
    "addr:postcode":"4680",
    "addr:street":"Dalrymple Drv",
    "iso:country":"AU",
    "sg:address":"Unit 1, 4 Dalrymple Drv",
    "sg:city":"Gladstone",
    "sg:classifiers":[
        {
            "category":"Retail",
            "subcategory":"Photofinishing",
            "type":"Services"
        }
    ],
    "sg:phone":"+61 7 4979 3877",
    "sg:postcode":"4680",
    "sg:province":"QLD",
    "sg:tags":[
        "refractory"
    ],
    "wof:name":"York Linings International Pty Ltd",
    "wof:placetype":"venue"
},
  "geometry": {"coordinates":[151.27073669399999,-23.8815746307],"type":"Point"}
}