{
  "type": "Feature",
  "properties": {
    "iso:country":"AU",
    "sg:address":"169 Wynyard St",
    "sg:city":"Tumut",
    "sg:classifiers":[
        {
            "category":"Organizations",
            "subcategory":"Community Association",
            "type":"Services"
        }
    ],
    "sg:phone":"+61 2 6947 3733",
    "sg:postcode":"2720",
    "sg:province":"NSW",
    "sg:tags":[
        "organisation",
        "family",
        "welfare"
    ],
    "wof:name":"Home & Community Care Centre (HACC)",
    "wof:placetype":"venue"
},
  "geometry": {"coordinates":[148.21167,-35.30608],"type":"Point"}
}