{
  "type": "Feature",
  "properties": {
    "addr:full":"Bridge St Tumbarumba NSW 2653",
    "addr:postcode":"2653",
    "addr:street":"Bridge St",
    "iso:country":"AU",
    "sg:address":"Bridge St",
    "sg:city":"Tumbarumba",
    "sg:classifiers":[
        {
            "category":"Autos & Motor Vehicles",
            "subcategory":"Fuel & Gas Station",
            "type":"Retail Goods"
        }
    ],
    "sg:phone":"+61 2 6948 2700",
    "sg:postcode":"2653",
    "sg:province":"NSW",
    "wof:name":"Tumba Valley Service Station",
    "wof:placetype":"venue"
},
  "geometry": {"coordinates":[148.012481689,-35.777381897],"type":"Point"}
}