{
  "type": "Feature",
  "properties": {
    "addr:full":"838 Old Cleveland Rd Carina QLD 4152",
    "addr:housenumber":"838",
    "addr:postcode":"4152",
    "addr:street":"Old Cleveland Rd",
    "iso:country":"AU",
    "sg:address":"838 Old Cleveland Rd",
    "sg:city":"Carina",
    "sg:classifiers":[
        {
            "category":"Banks & Credit Unions",
            "subcategory":"Investment Brokerage",
            "type":"Services"
        }
    ],
    "sg:phone":"+61 7 3395 1211",
    "sg:postcode":"4152",
    "sg:province":"QLD",
    "sg:tags":[
        "management",
        "property"
    ],
    "wof:name":"Professionals Vogue Real Estate",
    "wof:placetype":"venue"
},
  "geometry": {"coordinates":[153.091873169,-27.4952106476],"type":"Point"}
}