{
  "type": "Feature",
  "properties": {
    "addr:full":"765 Highbury Rd Vermont South VIC 3133",
    "addr:housenumber":"765",
    "addr:postcode":"3133",
    "addr:street":"Highbury Rd",
    "iso:country":"AU",
    "sg:address":"765 Highbury Rd",
    "sg:city":"Vermont South",
    "sg:classifiers":[
        {
            "category":"Education",
            "subcategory":"School",
            "type":"Public Place"
        }
    ],
    "sg:phone":"+61 3 9803 6828",
    "sg:postcode":"3133",
    "sg:province":"VIC",
    "sg:tags":[
        "co-educational"
    ],
    "wof:name":"Holy Saviour Primary",
    "wof:placetype":"venue"
},
  "geometry": {"coordinates":[145.17572021500001,-37.8626022339],"type":"Point"}
}