{
  "type": "Feature",
  "properties": {
    "iso:country":"AU",
    "sg:address":"2 Dell Rd",
    "sg:city":"Gosford West",
    "sg:classifiers":[
        {
            "category":"Retail",
            "subcategory":"Auto Repair",
            "type":"Services"
        }
    ],
    "sg:phone":"+61 2 4323 6002",
    "sg:postcode":"2250",
    "sg:province":"NSW",
    "sg:tags":[
        "bus",
        "truck"
    ],
    "wof:name":"R.A.M. Truck Repairs",
    "wof:placetype":"venue"
},
  "geometry": {"coordinates":[151.332687378,-33.4136657715],"type":"Point"}
}