{
  "type": "Feature",
  "properties": {
    "addr:full":"18425 Moonie Hwy Westmar QLD 4406",
    "addr:housenumber":"18425",
    "addr:postcode":"4406",
    "addr:street":"Moonie Hwy Westmar",
    "iso:country":"AU",
    "sg:address":"18425 Moonie Hwy",
    "sg:city":"Westmar",
    "sg:classifiers":[
        {
            "category":"Education",
            "subcategory":"School",
            "type":"Public Place"
        }
    ],
    "sg:phone":"+61 7 4663 0777",
    "sg:postcode":"4406",
    "sg:province":"QLD",
    "sg:tags":[
        "state",
        "except",
        "nsw"
    ],
    "wof:name":"Westmar Primary",
    "wof:placetype":"venue"
},
  "geometry": {"coordinates":[150.374755859,-27.711479187],"type":"Point"}
}