{
  "type": "Feature",
  "properties": {
    "iso:country":"AU",
    "sg:address":"99 Morayfield Rd",
    "sg:city":"Caboolture",
    "sg:classifiers":[
        {
            "category":"Personal",
            "subcategory":"Beauty Salon",
            "type":"Services"
        }
    ],
    "sg:phone":"+61 7 5495 7037",
    "sg:postcode":"4510",
    "sg:province":"QLD",
    "sg:tags":[
        "hairdresser"
    ],
    "wof:name":"JPS Hair & Beauty",
    "wof:placetype":"venue"
},
  "geometry": {"coordinates":[152.949417,-27.096718],"type":"Point"}
}