{
  "type": "Feature",
  "properties": {
    "addr:full":"23 Westside Drv Laverton North VIC 3026",
    "addr:housenumber":"23",
    "addr:postcode":"3026",
    "addr:street":"Westside Drv",
    "iso:country":"AU",
    "sg:address":"23 Westside Drv",
    "sg:city":"Laverton North",
    "sg:classifiers":[
        {
            "category":"Wholesale",
            "subcategory":"Auto Parts",
            "type":"Manufacturing & Wholesale Goods"
        }
    ],
    "sg:phone":"+61 1800 451 270",
    "sg:postcode":"3026",
    "sg:province":"VIC",
    "sg:tags":[
        "tyre"
    ],
    "wof:name":"Kenda Tyres",
    "wof:placetype":"venue"
},
  "geometry": {"coordinates":[144.82334900000001,-37.819237],"type":"Point"}
}