{
  "type": "Feature",
  "properties": {
    "iso:country":"AU",
    "sg:address":"64 Cocos Drv",
    "sg:city":"Bibra Lake",
    "sg:classifiers":[
        {
            "category":"Wholesale",
            "subcategory":"Painting Supplies",
            "type":"Manufacturing & Wholesale Goods"
        }
    ],
    "sg:phone":"+61 8 9434 2942",
    "sg:postcode":"6163",
    "sg:province":"WA",
    "sg:tags":[
        "product",
        "cleaning"
    ],
    "wof:name":"Gold Leaf Enterprises",
    "wof:placetype":"venue"
},
  "geometry": {"coordinates":[115.816383,-32.11034],"type":"Point"}
}