{
  "type": "Feature",
  "properties": {
    "iso:country":"AU",
    "sg:address":"89 Cecil St",
    "sg:city":"Williamstown",
    "sg:classifiers":[
        {
            "category":"Education",
            "subcategory":"Music School",
            "type":"Public Place"
        }
    ],
    "sg:phone":"+61 3 9399 2502",
    "sg:postcode":"3016",
    "sg:province":"VIC",
    "sg:tags":[
        "teacher"
    ],
    "wof:name":"Dream Academy",
    "wof:placetype":"venue"
},
  "geometry": {"coordinates":[144.90306091299999,-37.8649406433],"type":"Point"}
}