{
  "type": "Feature",
  "properties": {
    "addr:full":"Shop 4 108 Civic Centre Mall Coffs Harbour NSW 2450",
    "addr:housenumber":"shop 4 108 civic",
    "addr:postcode":"2450",
    "addr:street":"Mall",
    "iso:country":"AU",
    "sg:address":"Shop 4 108",
    "sg:city":"Civic Centre Mall Coffs Harbour",
    "sg:classifiers":[
        {
            "category":"Food & Beverages",
            "subcategory":"Bakery",
            "type":"Retail Goods"
        }
    ],
    "sg:phone":"+61 2 6652 5294",
    "sg:postcode":"2450",
    "sg:province":"NSW",
    "sg:tags":[
        "baker"
    ],
    "wof:name":"Shaws Hot Bake",
    "wof:placetype":"venue"
},
  "geometry": {"coordinates":[153.11515800000001,-30.29701],"type":"Point"}
}