{
  "type": "Feature",
  "properties": {
    "addr:full":"81 Cedar Rd Palm Cove QLD 4879",
    "addr:housenumber":"81",
    "addr:postcode":"4879",
    "addr:street":"Cedar Rd",
    "iso:country":"AU",
    "sg:address":"81 Cedar Rd",
    "sg:city":"Palm Cove",
    "sg:classifiers":[
        {
            "category":"Personal",
            "subcategory":"Day Spa",
            "type":"Services"
        }
    ],
    "sg:phone":"+61 7 4055 3400",
    "sg:postcode":"4879",
    "sg:province":"QLD",
    "wof:name":"Mango Lagoon Resort & Wellness Spa",
    "wof:placetype":"venue"
},
  "geometry": {"coordinates":[145.66937255900001,-16.7429046631],"type":"Point"}
}