{
  "type": "Feature",
  "properties": {
    "addr:full":"348 High St Prahran VIC 3181",
    "addr:housenumber":"348",
    "addr:postcode":"3181",
    "addr:street":"High St",
    "iso:country":"AU",
    "sg:address":"348 High St",
    "sg:city":"Prahran",
    "sg:classifiers":[
        {
            "category":"Banks & Credit Unions",
            "subcategory":"Bank",
            "type":"Services"
        }
    ],
    "sg:phone":"+61 1300 667 575",
    "sg:postcode":"3181",
    "sg:province":"VIC",
    "sg:tags":[
        "equipment",
        "sale",
        "point"
    ],
    "wof:name":"Macro Solutions Pty Ltd",
    "wof:placetype":"venue"
},
  "geometry": {"coordinates":[144.999542236,-37.8528022766],"type":"Point"}
}