{
  "type": "Feature",
  "properties": {
    "iso:country":"AU",
    "sg:address":"PO Box 2740",
    "sg:city":"Logan City",
    "sg:classifiers":[
        {
            "category":"Building & Trades",
            "subcategory":"Locksmith",
            "type":"Services"
        }
    ],
    "sg:phone":"+61 7 3804 1635",
    "sg:postcode":"4114",
    "sg:province":"QLD",
    "sg:tags":[
        "equipment",
        "operating",
        "door",
        "gate"
    ],
    "wof:name":"Correct Garage Doors",
    "wof:placetype":"venue"
},
  "geometry": {"coordinates":[153.11332702600001,-27.6484107971],"type":"Point"}
}