{
  "type": "Feature",
  "properties": {
    "iso:country":"AU",
    "sg:address":"75 Princes Hwy",
    "sg:city":"Dandenong South",
    "sg:classifiers":[
        {
            "category":"Retail",
            "subcategory":"Auto Repair",
            "type":"Services"
        }
    ],
    "sg:phone":"+61 3 9791 6533",
    "sg:postcode":"3175",
    "sg:province":"VIC",
    "sg:tags":[
        "bus",
        "truck"
    ],
    "wof:name":"Whitehorse Trucks Gippsland",
    "wof:placetype":"venue"
},
  "geometry": {"coordinates":[145.24171447800001,-38.0026626587],"type":"Point"}
}