{
  "type": "Feature",
  "properties": {
    "addr:full":"77 Crozier Ave Daw Park SA 5041",
    "addr:housenumber":"77",
    "addr:postcode":"5041",
    "addr:street":"Crozier Ave",
    "iso:country":"AU",
    "sg:address":"77 Crozier Ave",
    "sg:city":"Daw Park",
    "sg:classifiers":[
        {
            "category":"Building & Trades",
            "subcategory":"Plumbing",
            "type":"Services"
        }
    ],
    "sg:phone":"+61 409 094 847",
    "sg:postcode":"5041",
    "sg:province":"SA",
    "sg:tags":[
        "pump",
        "repairer"
    ],
    "wof:name":"Adelaide Pumps & Gardens",
    "wof:placetype":"venue"
},
  "geometry": {"coordinates":[138.584824,-34.987358],"type":"Point"}
}