{
  "type": "Feature",
  "properties": {
    "iso:country":"AU",
    "sg:address":"353c Church St",
    "sg:city":"Parramatta",
    "sg:classifiers":[
        {
            "category":"Professional",
            "type":"Services"
        }
    ],
    "sg:phone":"+61 2 9630 0511",
    "sg:postcode":"2150",
    "sg:province":"NSW",
    "sg:tags":[
        "industrial",
        "commercial",
        "catering"
    ],
    "wof:name":"Amadeus Catering",
    "wof:placetype":"venue"
},
  "geometry": {"coordinates":[151.00477600100001,-33.8100128174],"type":"Point"}
}