{
  "type": "Feature",
  "properties": {
    "iso:country":"AU",
    "sg:address":"103 Greens Rd",
    "sg:city":"Dandenong",
    "sg:classifiers":[
        {
            "category":"Manufacturing",
            "subcategory":"Motor Vehicles & Parts",
            "type":"Manufacturing & Wholesale Goods"
        }
    ],
    "sg:phone":"+61 3 9791 5500",
    "sg:postcode":"3175",
    "sg:province":"VIC",
    "sg:tags":[
        "replacement"
    ],
    "wof:name":"Auto Salvage Vic T.D. Pty. Ltd.",
    "wof:placetype":"venue"
},
  "geometry": {"coordinates":[145.21466064399999,-38.0143737793],"type":"Point"}
}