{
  "type": "Feature",
  "properties": {
    "iso:country":"AU",
    "sg:address":"2/ 290 Unley Rd",
    "sg:city":"Hyde Park",
    "sg:classifiers":[
        {
            "category":"Shopping",
            "subcategory":"Shoes",
            "type":"Retail Goods"
        }
    ],
    "sg:phone":"+61 8 8357 9133",
    "sg:postcode":"5061",
    "sg:province":"SA",
    "sg:tags":[
        "footwear"
    ],
    "wof:name":"Ian's Shoes",
    "wof:placetype":"venue"
},
  "geometry": {"coordinates":[138.607788086,-34.9562606812],"type":"Point"}
}