{
  "type": "Feature",
  "properties": {
    "addr:full":"Ste 8 Royal Melb Hosp Parkville VIC 3052",
    "addr:postcode":"3052",
    "iso:country":"AU",
    "sg:address":"Ste 8",
    "sg:city":"Royal Melb Hosp Parkville",
    "sg:classifiers":[
        {
            "category":"Health Services",
            "subcategory":"Doctor",
            "type":"Services"
        }
    ],
    "sg:phone":"+61 3 9349 3599",
    "sg:postcode":"3052",
    "sg:province":"VIC",
    "sg:tags":[
        "medical",
        "practitioner"
    ],
    "wof:name":"Parkville Medical Consultants",
    "wof:placetype":"venue"
},
  "geometry": {"coordinates":[144.88792419399999,-37.7896614075],"type":"Point"}
}