{
  "type": "Feature",
  "properties": {
    "iso:country":"AU",
    "sg:address":"236 Harbour Drv",
    "sg:city":"Coffs Harbour",
    "sg:classifiers":[
        {
            "category":"Professional",
            "subcategory":"Engineering",
            "type":"Services"
        }
    ],
    "sg:phone":"+61 2 6652 1700",
    "sg:postcode":"2450",
    "sg:province":"NSW",
    "sg:tags":[
        "consulting",
        "engineer"
    ],
    "wof:name":"Benson Greg",
    "wof:placetype":"venue"
},
  "geometry": {"coordinates":[153.12202500000001,-30.302032],"type":"Point"}
}