{
  "type": "Feature",
  "properties": {
    "addr:full":"20 Leane St Hughes ACT 2605",
    "addr:housenumber":"20",
    "addr:postcode":"2605",
    "addr:street":"Leane St",
    "iso:country":"AU",
    "sg:address":"20 Leane St",
    "sg:city":"Hughes",
    "sg:classifiers":[
        {
            "category":"Education",
            "subcategory":"Music School",
            "type":"Public Place"
        }
    ],
    "sg:phone":"+61 2 6282 5797",
    "sg:postcode":"2605",
    "sg:province":"ACT",
    "sg:tags":[
        "teacher"
    ],
    "wof:name":"Malikides Stephanos",
    "wof:placetype":"venue"
},
  "geometry": {"coordinates":[149.10003662099999,-35.3341522217],"type":"Point"}
}