{
  "type": "Feature",
  "properties": {
    "addr:full":"58 Moncur Ave Springvale VIC 3171",
    "addr:housenumber":"58",
    "addr:postcode":"3171",
    "addr:street":"Moncur Ave",
    "iso:country":"AU",
    "sg:address":"58 Moncur Ave",
    "sg:city":"Springvale",
    "sg:classifiers":[
        {
            "category":"Autos & Motor Vehicles",
            "subcategory":"Auto Supplies",
            "type":"Retail Goods"
        }
    ],
    "sg:phone":"+61 3 8502 8240",
    "sg:postcode":"3171",
    "sg:province":"VIC",
    "sg:tags":[
        "automotive",
        "stereo",
        "radio"
    ],
    "wof:name":"Complete Options Car Audio & Alarms",
    "wof:placetype":"venue"
},
  "geometry": {"coordinates":[145.14730835,-37.9616165161],"type":"Point"}
}