{
  "type": "Feature",
  "properties": {
    "addr:full":"42 Ross St Glebe NSW 2037",
    "addr:housenumber":"42",
    "addr:postcode":"2037",
    "addr:street":"Ross St",
    "iso:country":"AU",
    "sg:address":"42 Ross St",
    "sg:city":"Glebe",
    "sg:classifiers":[
        {
            "category":"Shopping",
            "subcategory":"Antiques",
            "type":"Retail Goods"
        }
    ],
    "sg:phone":"+61 2 9660 2184",
    "sg:postcode":"2037",
    "sg:province":"NSW",
    "wof:name":"Salvage 42",
    "wof:placetype":"venue"
},
  "geometry": {"coordinates":[151.18089294399999,-33.880657196],"type":"Point"}
}