{
  "type": "Feature",
  "properties": {
    "addr:full":"Factory 4/ 35 Power Rd Bayswater VIC 3153",
    "addr:housenumber":"/ 35",
    "addr:postcode":"3153",
    "addr:street":"Power Rd",
    "iso:country":"AU",
    "sg:address":"Factory 4/ 35 Power Rd",
    "sg:city":"Bayswater",
    "sg:classifiers":[
        {
            "category":"Retail",
            "subcategory":"Auto Repair",
            "type":"Services"
        }
    ],
    "sg:phone":"+61 3 9720 8731",
    "sg:postcode":"3153",
    "sg:province":"VIC",
    "sg:tags":[
        "repairer",
        "motor",
        "engineer"
    ],
    "wof:name":"John Norder Motors",
    "wof:placetype":"venue"
},
  "geometry": {"coordinates":[145.27432250999999,-37.847454071],"type":"Point"}
}