{
  "type": "Feature",
  "properties": {
    "addr:full":"191 Kingaroy St Kingaroy QLD 4610",
    "addr:housenumber":"191",
    "addr:postcode":"4610",
    "addr:street":"Kingaroy St",
    "iso:country":"AU",
    "sg:address":"191 Kingaroy St",
    "sg:city":"Kingaroy",
    "sg:classifiers":[
        {
            "category":"Insurance",
            "subcategory":"Insurance Agent",
            "type":"Services"
        }
    ],
    "sg:phone":"+61 408 718 843",
    "sg:postcode":"4610",
    "sg:province":"QLD",
    "wof:name":"Darrel RobertsElders Agents",
    "wof:placetype":"venue"
},
  "geometry": {"coordinates":[151.839233398,-26.5402679443],"type":"Point"}
}