{
  "type": "Feature",
  "properties": {
    "iso:country":"AU",
    "sg:address":"28 Henderson St",
    "sg:city":"Fremantle",
    "sg:classifiers":[
        {
            "category":"Real Estate",
            "subcategory":"Developer",
            "type":"Services"
        }
    ],
    "sg:phone":"+61 8 9336 4671",
    "sg:postcode":"6160",
    "sg:province":"WA",
    "sg:tags":[
        "development"
    ],
    "wof:name":"Spm Project Marketing Pty Ltd",
    "wof:placetype":"venue"
},
  "geometry": {"coordinates":[115.749702,-32.054684],"type":"Point"}
}