{
  "type": "Feature",
  "properties": {
    "iso:country":"AU",
    "sg:address":"66 Princes Hwy",
    "sg:city":"Fairy Meadow",
    "sg:classifiers":[
        {
            "category":"Food & Beverages",
            "subcategory":"Supermarket",
            "type":"Retail Goods"
        }
    ],
    "sg:phone":"+61 2 4284 7099",
    "sg:postcode":"2519",
    "sg:province":"NSW",
    "sg:tags":[
        "grocery",
        "store"
    ],
    "wof:name":"Woolworths Ltd",
    "wof:placetype":"venue"
},
  "geometry": {"coordinates":[150.893463,-34.391811],"type":"Point"}
}