{
  "type": "Feature",
  "properties": {
    "iso:country":"AU",
    "sg:address":"Ste 2 314A Thomas St",
    "sg:city":"Dandenong",
    "sg:classifiers":[
        {
            "category":"Organizations",
            "subcategory":"Professional Association",
            "type":"Services"
        }
    ],
    "sg:phone":"+61 3 9791 8572",
    "sg:postcode":"3175",
    "sg:province":"VIC",
    "sg:tags":[
        "organisation",
        "business"
    ],
    "wof:name":"Small Business Victoria",
    "wof:placetype":"venue"
},
  "geometry": {"coordinates":[145.21255493199999,-37.9849128723],"type":"Point"}
}