{
  "type": "Feature",
  "properties": {
    "addr:full":"9 City Pl Sunshine VIC 3020",
    "addr:postcode":"3020",
    "addr:street":"Pl",
    "iso:country":"AU",
    "sg:address":"9 City Pl",
    "sg:city":"Sunshine",
    "sg:classifiers":[
        {
            "category":"Health Services",
            "subcategory":"Health Practitioner",
            "type":"Services"
        }
    ],
    "sg:phone":"+61 3 9364 7008",
    "sg:postcode":"3020",
    "sg:province":"VIC",
    "sg:tags":[
        "acupuncture"
    ],
    "wof:name":"Health Concious Healthcare Clinic",
    "wof:placetype":"venue"
},
  "geometry": {"coordinates":[144.83142100000001,-37.787609],"type":"Point"}
}