{
  "type": "Feature",
  "properties": {
    "iso:country":"AU",
    "sg:address":"20 Great Eastern Hwy",
    "sg:city":"Glen Forrest",
    "sg:classifiers":[
        {
            "category":"Autos & Motor Vehicles",
            "subcategory":"Fuel & Gas Station",
            "type":"Retail Goods"
        }
    ],
    "sg:phone":"+61 8 9298 8319",
    "sg:postcode":"6071",
    "sg:province":"WA",
    "wof:name":"Bilgoman Workshop",
    "wof:placetype":"venue"
},
  "geometry": {"coordinates":[116.114631653,-31.90051651],"type":"Point"}
}