{
  "type": "Feature",
  "properties": {
    "iso:country":"AU",
    "sg:address":"PO Box 2291",
    "sg:city":"Boulder",
    "sg:classifiers":[
        {
            "category":"Professional",
            "subcategory":"Computer Services",
            "type":"Services"
        }
    ],
    "sg:phone":"+61 408 093 062",
    "sg:postcode":"6432",
    "sg:province":"WA",
    "sg:tags":[
        "repairs",
        "upgrade",
        "equipment"
    ],
    "wof:name":"LAN Computer Upgrade",
    "wof:placetype":"venue"
},
  "geometry": {"coordinates":[121.489463806,-30.7818393707],"type":"Point"}
}