{
  "type": "Feature",
  "properties": {
    "addr:full":"Hervey Bay Rd Pialba QLD 4655",
    "addr:postcode":"4655",
    "addr:street":"Hervey Bay Rd",
    "iso:country":"AU",
    "sg:address":"Hervey Bay Rd",
    "sg:city":"Pialba",
    "sg:classifiers":[
        {
            "category":"Autos & Motor Vehicles",
            "subcategory":"Fuel & Gas Station",
            "type":"Retail Goods"
        }
    ],
    "sg:phone":"+61 7 4124 1677",
    "sg:postcode":"4655",
    "sg:province":"QLD",
    "wof:name":"United Service Station",
    "wof:placetype":"venue"
},
  "geometry": {"coordinates":[152.83393899999999,-25.289679],"type":"Point"}
}