{
  "type": "Feature",
  "properties": {
    "addr:full":"Dunlop Rd Mulgrave VIC 3170",
    "addr:postcode":"3170",
    "addr:street":"Dunlop Rd",
    "iso:country":"AU",
    "sg:address":"Dunlop Rd",
    "sg:city":"Mulgrave",
    "sg:classifiers":[
        {
            "category":"Home & Garden",
            "subcategory":"Hardware",
            "type":"Retail Goods"
        }
    ],
    "sg:phone":"+61 3 9574 3400",
    "sg:postcode":"3170",
    "sg:province":"VIC",
    "sg:tags":[
        "nut",
        "bolt"
    ],
    "wof:name":"Thomas Warburton Pty Ltd",
    "wof:placetype":"venue"
},
  "geometry": {"coordinates":[145.15777587900001,-37.9104766846],"type":"Point"}
}