{
  "type": "Feature",
  "properties": {
    "addr:full":"6a Australia Drv Crawley WA 6009",
    "addr:postcode":"6009",
    "addr:street":"Australia Drv",
    "iso:country":"AU",
    "sg:address":"6a Australia Drv",
    "sg:city":"Crawley",
    "sg:classifiers":[
        {
            "category":"Autos & Motor Vehicles",
            "subcategory":"Boat Sales",
            "type":"Retail Goods"
        }
    ],
    "sg:phone":"+61 8 9386 7059",
    "sg:postcode":"6009",
    "sg:province":"WA",
    "sg:tags":[
        "builder",
        "yacht",
        "repairer"
    ],
    "wof:name":"Bay Marine Maintenance",
    "wof:placetype":"venue"
},
  "geometry": {"coordinates":[115.82151,-31.98617],"type":"Point"}
}