{
  "type": "Feature",
  "properties": {
    "iso:country":"AU",
    "sg:address":"1/ 4 North Rocks Rd",
    "sg:city":"North Parramatta",
    "sg:classifiers":[
        {
            "category":"Banks & Credit Unions",
            "subcategory":"Financial Services",
            "type":"Services"
        }
    ],
    "sg:phone":"+61 2 9890 4080",
    "sg:postcode":"2151",
    "sg:province":"NSW",
    "sg:tags":[
        "loan",
        "finance",
        "mortgage"
    ],
    "wof:name":"King Mortgages Pty Ltd",
    "wof:placetype":"venue"
},
  "geometry": {"coordinates":[151.000564575,-33.7930526733],"type":"Point"}
}