{
  "type": "Feature",
  "properties": {
    "addr:full":"14 Wattle Ave Macquarie Fields NSW 2564",
    "addr:housenumber":"14",
    "addr:postcode":"2564",
    "addr:street":"Wattle Ave",
    "iso:country":"AU",
    "sg:address":"14 Wattle Ave",
    "sg:city":"Macquarie Fields",
    "sg:classifiers":[
        {
            "category":"Building & Trades",
            "subcategory":"Pest Control",
            "type":"Services"
        }
    ],
    "sg:phone":"+61 2 9829 4730",
    "sg:postcode":"2564",
    "sg:province":"NSW",
    "wof:name":"Bowl-a-Bug Pest Control",
    "wof:placetype":"venue"
},
  "geometry": {"coordinates":[150.884841919,-33.9937438965],"type":"Point"}
}