{
  "type": "Feature",
  "properties": {
    "addr:full":"PO Box 434 Macksville NSW 2447",
    "addr:postcode":"2447",
    "iso:country":"AU",
    "sg:address":"PO Box 434",
    "sg:city":"Macksville",
    "sg:classifiers":[
        {
            "category":"Building & Trades",
            "subcategory":"Landscaping Services",
            "type":"Services"
        }
    ],
    "sg:phone":"+61 2 6568 2571",
    "sg:postcode":"2447",
    "sg:province":"NSW",
    "sg:tags":[
        "designer",
        "landscape",
        "contractor"
    ],
    "wof:name":"Yards Of Art",
    "wof:placetype":"venue"
},
  "geometry": {"coordinates":[152.920624,-30.707781],"type":"Point"}
}