{
  "type": "Feature",
  "properties": {
    "addr:full":"3 Abbott St Cammeray NSW 2062",
    "addr:housenumber":"3",
    "addr:postcode":"2062",
    "addr:street":"Abbott St",
    "iso:country":"AU",
    "sg:address":"3 Abbott St",
    "sg:city":"Cammeray",
    "sg:classifiers":[
        {
            "category":"Health Services",
            "subcategory":"Doctor",
            "type":"Services"
        }
    ],
    "sg:phone":"+61 2 9958 0280",
    "sg:postcode":"2062",
    "sg:province":"NSW",
    "sg:tags":[
        "medical",
        "practitioner"
    ],
    "wof:name":"Wijesena Senani Dr",
    "wof:placetype":"venue"
},
  "geometry": {"coordinates":[151.21023559599999,-33.8224372864],"type":"Point"}
}