{
  "type": "Feature",
  "properties": {
    "addr:full":"7 Syme Rd Alexander Heights WA 6064",
    "addr:housenumber":"7",
    "addr:postcode":"6064",
    "addr:street":"Syme Rd",
    "iso:country":"AU",
    "sg:address":"7 Syme Rd",
    "sg:city":"Alexander Heights",
    "sg:classifiers":[
        {
            "category":"Utilities",
            "subcategory":"Electric",
            "type":"Services"
        }
    ],
    "sg:phone":"+61 8 9343 3425",
    "sg:postcode":"6064",
    "sg:province":"WA",
    "sg:tags":[
        "electrical",
        "contractor"
    ],
    "wof:name":"Richard Marsh Electrics",
    "wof:placetype":"venue"
},
  "geometry": {"coordinates":[115.85668182400001,-31.8252182007],"type":"Point"}
}