{
  "type": "Feature",
  "properties": {
    "addr:full":"162 Koornang Rd Carnegie VIC 3163",
    "addr:housenumber":"162",
    "addr:postcode":"3163",
    "addr:street":"Koornang Rd",
    "iso:country":"AU",
    "sg:address":"162 Koornang Rd",
    "sg:city":"Carnegie",
    "sg:classifiers":[
        {
            "category":"Health Services",
            "subcategory":"Chiropractor",
            "type":"Services"
        }
    ],
    "sg:phone":"+61 3 9568 4308",
    "sg:postcode":"3163",
    "sg:province":"VIC",
    "wof:name":"Golden Key Chiropractor & Acupuncture",
    "wof:placetype":"venue"
},
  "geometry": {"coordinates":[145.05708313,-37.8899993896],"type":"Point"}
}