{
  "type": "Feature",
  "properties": {
    "iso:country":"AU",
    "sg:address":"20 Alfred St",
    "sg:city":"Blackburn",
    "sg:classifiers":[
        {
            "category":"Home & Garden",
            "subcategory":"Carpets & Floor Coverings",
            "type":"Retail Goods"
        }
    ],
    "sg:phone":"+61 3 9878 3311",
    "sg:postcode":"3130",
    "sg:province":"VIC",
    "wof:name":"Composil (Vic) Pty Ltd",
    "wof:placetype":"venue"
},
  "geometry": {"coordinates":[145.15841674800001,-37.8192481995],"type":"Point"}
}