{
  "type": "Feature",
  "properties": {
    "addr:full":"10 Lenore St Williamstown VIC 3016",
    "addr:housenumber":"10",
    "addr:postcode":"3016",
    "addr:street":"Lenore St",
    "iso:country":"AU",
    "sg:address":"10 Lenore St",
    "sg:city":"Williamstown",
    "sg:classifiers":[
        {
            "category":"Banks & Credit Unions",
            "subcategory":"Bureau De Change",
            "type":"Services"
        }
    ],
    "sg:phone":"+61 3 9393 9311",
    "sg:postcode":"3016",
    "sg:province":"VIC",
    "sg:tags":[
        "planning",
        "family"
    ],
    "wof:name":"Family Planning Clinics",
    "wof:placetype":"venue"
},
  "geometry": {"coordinates":[144.89541625999999,-37.8573875427],"type":"Point"}
}