{
  "type": "Feature",
  "properties": {
    "iso:country":"AU",
    "sg:address":"8 Skull Rd",
    "sg:city":"White Rock",
    "sg:classifiers":[
        {
            "category":"Farming",
            "subcategory":"Nursery",
            "type":"Manufacturing & Wholesale Goods"
        }
    ],
    "sg:phone":"+61 7 4036 2262",
    "sg:postcode":"4868",
    "sg:province":"QLD",
    "wof:name":"White Rock Nursery",
    "wof:placetype":"venue"
},
  "geometry": {"coordinates":[145.746185303,-16.9708786011],"type":"Point"}
}