{
  "type": "Feature",
  "properties": {
    "addr:full":"Unit 6, 12 Stuart St Bunbury WA 6230",
    "addr:housenumber":"12",
    "addr:postcode":"6230",
    "addr:street":"Stuart St",
    "iso:country":"AU",
    "sg:address":"Unit 6, 12 Stuart St",
    "sg:city":"Bunbury",
    "sg:classifiers":[
        {
            "category":"Manufacturing",
            "subcategory":"Motor Vehicles & Parts",
            "type":"Manufacturing & Wholesale Goods"
        }
    ],
    "sg:phone":"+61 8 9721 3038",
    "sg:postcode":"6230",
    "sg:province":"WA",
    "sg:tags":[
        "replacement"
    ],
    "wof:name":"Bunbury Batteries",
    "wof:placetype":"venue"
},
  "geometry": {"coordinates":[115.642273,-33.333607],"type":"Point"}
}