{
  "type": "Feature",
  "properties": {
    "addr:full":"Unit 2 90 Capital Link Drv Campbellfield VIC 3061",
    "addr:housenumber":"90",
    "addr:postcode":"3061",
    "addr:street":"Capital Link Drv",
    "iso:country":"AU",
    "sg:address":"Unit 2 90 Capital Link Drv",
    "sg:city":"Campbellfield",
    "sg:classifiers":[
        {
            "category":"Professional",
            "type":"Services"
        }
    ],
    "sg:phone":"+61 3 9357 0709",
    "sg:postcode":"3061",
    "sg:province":"VIC",
    "sg:tags":[
        "coating",
        "powder"
    ],
    "wof:name":"Unique Powder Coating Pty Ltd",
    "wof:placetype":"venue"
},
  "geometry": {"coordinates":[144.957199097,-37.6524925232],"type":"Point"}
}