{
  "type": "Feature",
  "properties": {
    "iso:country":"AU",
    "sg:address":"PO Box 8",
    "sg:city":"Mulgoa",
    "sg:classifiers":[
        {
            "category":"Autos & Motor Vehicles",
            "subcategory":"Fuel & Gas Station",
            "type":"Retail Goods"
        }
    ],
    "sg:phone":"+61 2 4774 2775",
    "sg:postcode":"2745",
    "sg:province":"NSW",
    "sg:tags":[
        "petrol",
        "marketing",
        "pump",
        "equipment"
    ],
    "wof:name":"Petrolink Pty Ltd",
    "wof:placetype":"venue"
},
  "geometry": {"coordinates":[150.64923095699999,-33.8418083191],"type":"Point"}
}