{
  "type": "Feature",
  "properties": {
    "iso:country":"AU",
    "sg:address":"1/ 211 Windsor Rd",
    "sg:city":"McGraths Hill",
    "sg:classifiers":[
        {
            "category":"Real Estate",
            "subcategory":"Real Estate Agent",
            "type":"Services"
        }
    ],
    "sg:phone":"+61 2 4587 8855",
    "sg:postcode":"2756",
    "sg:province":"NSW",
    "wof:name":"Cutcliffe",
    "wof:placetype":"venue"
},
  "geometry": {"coordinates":[150.83750915499999,-33.6227493286],"type":"Point"}
}