{
  "type": "Feature",
  "properties": {
    "iso:country":"AU",
    "sg:address":"11 Barber Ave",
    "sg:city":"Kingswood",
    "sg:classifiers":[
        {
            "category":"Government",
            "subcategory":"Court House",
            "type":"Public Place"
        }
    ],
    "sg:phone":"+61 2 4732 3011",
    "sg:postcode":"2747",
    "sg:province":"NSW",
    "sg:tags":[
        "personal",
        "marriage",
        "family",
        "counselling"
    ],
    "wof:name":"Lifecare Counselling & Family Services",
    "wof:placetype":"venue"
},
  "geometry": {"coordinates":[150.71209716800001,-33.7578926086],"type":"Point"}
}