{
  "type": "Feature",
  "properties": {
    "iso:country":"AU",
    "sg:address":"302 Pitt St",
    "sg:city":"Sydney",
    "sg:classifiers":[
        {
            "category":"Shopping",
            "subcategory":"Beauty & Cosmetics",
            "type":"Retail Goods"
        }
    ],
    "sg:phone":"+61 2 9267 6461",
    "sg:postcode":"2000",
    "sg:province":"NSW",
    "wof:name":"Aesthetic School Of Beauty",
    "wof:placetype":"venue"
},
  "geometry": {"coordinates":[151.20811462399999,-33.8749160767],"type":"Point"}
}