{
  "type": "Feature",
  "properties": {
    "addr:full":"151 Darley St Newtown NSW 2042",
    "addr:housenumber":"151",
    "addr:postcode":"2042",
    "addr:street":"Darley St",
    "iso:country":"AU",
    "sg:address":"151 Darley St",
    "sg:city":"Newtown",
    "sg:classifiers":[
        {
            "category":"Wholesale",
            "subcategory":"Home Furnishings",
            "type":"Manufacturing & Wholesale Goods"
        }
    ],
    "sg:phone":"+61 2 9516 1722",
    "sg:postcode":"2042",
    "sg:province":"NSW",
    "sg:tags":[
        "wholesaler",
        "mfrs",
        "manchester"
    ],
    "wof:name":"Unique Manchester Pty Ltd",
    "wof:placetype":"venue"
},
  "geometry": {"coordinates":[151.17553699999999,-33.907425],"type":"Point"}
}