{
  "type": "Feature",
  "properties": {
    "addr:full":"25 Penong Ave Camden Park SA 5038",
    "addr:housenumber":"25",
    "addr:postcode":"5038",
    "addr:street":"Penong Ave",
    "iso:country":"AU",
    "sg:address":"25 Penong Ave",
    "sg:city":"Camden Park",
    "sg:classifiers":[
        {
            "category":"Building & Trades",
            "subcategory":"Construction",
            "type":"Services"
        }
    ],
    "sg:phone":"+61 8 8295 4660",
    "sg:postcode":"5038",
    "sg:province":"SA",
    "sg:tags":[
        "contractor"
    ],
    "wof:name":"Vallco Developments Pty Ltd",
    "wof:placetype":"venue"
},
  "geometry": {"coordinates":[138.542572022,-34.9639053345],"type":"Point"}
}