{
  "type": "Feature",
  "properties": {
    "addr:full":"Shp9/ 47 High Central Rd Macleay Island QLD 4184",
    "addr:housenumber":"47",
    "addr:postcode":"4184",
    "addr:street":"High Central Rd",
    "iso:country":"AU",
    "sg:address":"Shp9/ 47 High Central Rd",
    "sg:city":"Macleay Island",
    "sg:classifiers":[
        {
            "category":"Fast Food",
            "type":"Food & Drink"
        }
    ],
    "sg:phone":"+61 7 3409 5511",
    "sg:postcode":"4184",
    "sg:province":"QLD",
    "sg:tags":[
        "away",
        "take"
    ],
    "wof:name":"MacLeay Island Seafoods",
    "wof:placetype":"venue"
},
  "geometry": {"coordinates":[153.363037109,-27.6275405884],"type":"Point"}
}