{
  "type": "Feature",
  "properties": {
    "iso:country":"AU",
    "sg:address":"PO Box 1053",
    "sg:city":"Park Ridge",
    "sg:classifiers":[
        {
            "category":"Retail",
            "subcategory":"Auto Rental",
            "type":"Services"
        }
    ],
    "sg:phone":"+61 7 3802 1467",
    "sg:postcode":"4125",
    "sg:province":"QLD",
    "sg:tags":[
        "car",
        "wedding"
    ],
    "wof:name":"Hi Way Hogg&#039;n Bike Tours",
    "wof:placetype":"venue"
},
  "geometry": {"coordinates":[153.06152343799999,-27.703950882],"type":"Point"}
}