{
  "type": "Feature",
  "properties": {
    "iso:country":"AU",
    "sg:address":"5 Hopetoun Ave",
    "sg:city":"Morwell",
    "sg:classifiers":[
        {
            "category":"Health Services",
            "subcategory":"Doctor",
            "type":"Services"
        }
    ],
    "sg:phone":"+61 3 5133 7388",
    "sg:postcode":"3840",
    "sg:province":"VIC",
    "sg:tags":[
        "podiatrist"
    ],
    "wof:name":"Gippsland Foot Clinic",
    "wof:placetype":"venue"
},
  "geometry": {"coordinates":[146.40228271500001,-38.2370681763],"type":"Point"}
}