{
  "type": "Feature",
  "properties": {
    "addr:full":"33 King St Norwood SA 5067",
    "addr:housenumber":"33",
    "addr:postcode":"5067",
    "addr:street":"King St",
    "iso:country":"AU",
    "sg:address":"33 King St",
    "sg:city":"Norwood",
    "sg:classifiers":[
        {
            "category":"Food & Beverages",
            "subcategory":"Liquor & Beverages",
            "type":"Retail Goods"
        }
    ],
    "sg:phone":"+61 8 8363 5400",
    "sg:postcode":"5067",
    "sg:province":"SA",
    "sg:tags":[
        "merchant",
        "spirit",
        "wine"
    ],
    "wof:name":"Options Wine Merchants Pty Ltd",
    "wof:placetype":"venue"
},
  "geometry": {"coordinates":[138.62672424300001,-34.9176216125],"type":"Point"}
}