{
  "type": "Feature",
  "properties": {
    "iso:country":"AU",
    "sg:address":"P.O. Box 783",
    "sg:city":"Newlands Estate Coburg",
    "sg:classifiers":[
        {
            "category":"Real Estate",
            "subcategory":"Real Estate Operator",
            "type":"Services"
        }
    ],
    "sg:phone":"+61 3 9355 7788",
    "sg:postcode":"3058",
    "sg:province":"VIC",
    "sg:tags":[
        "concrete",
        "pumping"
    ],
    "wof:name":"Supreme Concrete Pumping & Machinery Pty. Ltd.",
    "wof:placetype":"venue"
},
  "geometry": {"coordinates":[144.97235107399999,-37.7351646423],"type":"Point"}
}