{
  "type": "Feature",
  "properties": {
    "addr:full":"Alfred St Mittagong NSW 2575",
    "addr:postcode":"2575",
    "addr:street":"Alfred St",
    "iso:country":"AU",
    "sg:address":"Alfred St",
    "sg:city":"Mittagong",
    "sg:classifiers":[
        {
            "category":"Education",
            "subcategory":"School",
            "type":"Public Place"
        }
    ],
    "sg:phone":"+61 2 4871 2279",
    "sg:postcode":"2575",
    "sg:province":"NSW",
    "sg:tags":[
        "co-educational"
    ],
    "wof:name":"St Michaels School",
    "wof:placetype":"venue"
},
  "geometry": {"coordinates":[150.44769287099999,-34.4473495483],"type":"Point"}
}