{
  "type": "Feature",
  "properties": {
    "addr:full":"Suite 12/ 7 Kintail Rd Applecross WA 6153",
    "addr:housenumber":"12 / 7",
    "addr:postcode":"6153",
    "addr:street":"Kintail Rd",
    "iso:country":"AU",
    "sg:address":"Suite 12/ 7 Kintail Rd",
    "sg:city":"Applecross",
    "sg:classifiers":[
        {
            "category":"Professional",
            "subcategory":"Accounting & Tax Preparation",
            "type":"Services"
        }
    ],
    "sg:phone":"+61 8 9316 1421",
    "sg:postcode":"6153",
    "sg:province":"WA",
    "sg:tags":[
        "consultant",
        "taxation"
    ],
    "wof:name":"Canning Accounting",
    "wof:placetype":"venue"
},
  "geometry": {"coordinates":[115.84989899999999,-32.011211],"type":"Point"}
}