{
  "type": "Feature",
  "properties": {
    "addr:full":"Shop 1 C Leonard Ave Noble Park VIC 3174",
    "addr:housenumber":"shop 1 c",
    "addr:postcode":"3174",
    "addr:street":"Leonard Ave",
    "iso:country":"AU",
    "sg:address":"Shop 1 C Leonard Ave",
    "sg:city":"Noble Park",
    "sg:classifiers":[
        {
            "category":"Health Services",
            "subcategory":"Dentist",
            "type":"Services"
        }
    ],
    "sg:phone":"+61 3 9547 6913",
    "sg:postcode":"3174",
    "sg:province":"VIC",
    "sg:tags":[
        "dental",
        "prosthetist"
    ],
    "wof:name":"Andrew Lindsay",
    "wof:placetype":"venue"
},
  "geometry": {"coordinates":[145.176147461,-37.9673461914],"type":"Point"}
}