{
  "type": "Feature",
  "properties": {
    "addr:full":"54 Thiedeke Rd Beaudesert QLD 4285",
    "addr:housenumber":"54",
    "addr:postcode":"4285",
    "addr:street":"Thiedeke Rd",
    "iso:country":"AU",
    "sg:address":"54 Thiedeke Rd",
    "sg:city":"Beaudesert",
    "sg:classifiers":[
        {
            "category":"Building & Trades",
            "subcategory":"Construction",
            "type":"Services"
        }
    ],
    "sg:phone":"+61 7 5541 1811",
    "sg:postcode":"4285",
    "sg:province":"QLD",
    "sg:tags":[
        "earth",
        "excavating",
        "moving",
        "contractor"
    ],
    "wof:name":"Calam Plant Pty Ltd",
    "wof:placetype":"venue"
},
  "geometry": {"coordinates":[152.97569300000001,-27.997568],"type":"Point"}
}