{
  "type": "Feature",
  "properties": {
    "addr:full":"286 Railway St Woy Woy NSW 2256",
    "addr:housenumber":"286",
    "addr:postcode":"2256",
    "addr:street":"Railway St",
    "iso:country":"AU",
    "sg:address":"286 Railway St",
    "sg:city":"Woy Woy",
    "sg:classifiers":[
        {
            "category":"Health Services",
            "subcategory":"Nursing And Care Facility",
            "type":"Services"
        }
    ],
    "sg:phone":"+61 2 4379 9000",
    "sg:postcode":"2256",
    "sg:province":"NSW",
    "sg:tags":[
        "home"
    ],
    "wof:name":"Hammond Care Group",
    "wof:placetype":"venue"
},
  "geometry": {"coordinates":[151.302734375,-33.4979553223],"type":"Point"}
}