{
  "type": "Feature",
  "properties": {
    "iso:country":"AU",
    "sg:address":"Sea World Drv",
    "sg:city":"Main Beach",
    "sg:classifiers":[
        {
            "category":"Shopping",
            "subcategory":"Luggage & Leather Goods",
            "type":"Retail Goods"
        }
    ],
    "sg:phone":"+61 7 5532 2217",
    "sg:postcode":"4217",
    "sg:province":"QLD",
    "wof:name":"Eelectra Leather From The Sea",
    "wof:placetype":"venue"
},
  "geometry": {"coordinates":[153.42718505900001,-27.9657707214],"type":"Point"}
}