{
  "type": "Feature",
  "properties": {
    "addr:full":"17 The Drv Harbord NSW 2096",
    "addr:housenumber":"17",
    "addr:postcode":"2096",
    "addr:street":"The Drv",
    "iso:country":"AU",
    "sg:address":"17 The Drv",
    "sg:city":"Harbord",
    "sg:classifiers":[
        {
            "category":"Shopping",
            "subcategory":"Bicycles & Sporting Goods",
            "type":"Retail Goods"
        }
    ],
    "sg:phone":"+61 2 9907 3158",
    "sg:postcode":"2096",
    "sg:province":"NSW",
    "sg:tags":[
        "chemical",
        "equipment",
        "pool",
        "swimming"
    ],
    "wof:name":"Taylor Made Pools",
    "wof:placetype":"venue"
},
  "geometry": {"coordinates":[151.292572022,-33.7776412964],"type":"Point"}
}