{
  "type": "Feature",
  "properties": {
    "iso:country":"AU",
    "sg:address":"48 First Ave",
    "sg:city":"Gundagai",
    "sg:classifiers":[
        {
            "category":"Building & Trades",
            "subcategory":"Construction",
            "type":"Services"
        }
    ],
    "sg:phone":"+61 417 432 932",
    "sg:postcode":"2722",
    "sg:province":"NSW",
    "sg:tags":[
        "concrete",
        "contractor"
    ],
    "wof:name":"PJ & CA Herring Concrete Contractors",
    "wof:placetype":"venue"
},
  "geometry": {"coordinates":[148.108536,-35.064861],"type":"Point"}
}