{
  "type": "Feature",
  "properties": {
    "iso:country":"AU",
    "sg:address":"63 Schulze Rd",
    "sg:city":"Athelstone",
    "sg:classifiers":[
        {
            "category":"School Buses",
            "type":"Transportation"
        }
    ],
    "sg:phone":"+61 8 8365 9132",
    "sg:postcode":"5076",
    "sg:province":"SA",
    "sg:tags":[
        "nanny"
    ],
    "wof:name":"Cinderella's Children Costume Parties",
    "wof:placetype":"venue"
},
  "geometry": {"coordinates":[138.69430542000001,-34.8688240051],"type":"Point"}
}