{
  "type": "Feature",
  "properties": {
    "addr:full":"26 Tambor St Exmouth WA 6707",
    "addr:housenumber":"26",
    "addr:postcode":"6707",
    "addr:street":"Tambor St",
    "iso:country":"AU",
    "sg:address":"26 Tambor St",
    "sg:city":"Exmouth",
    "sg:classifiers":[
        {
            "category":"Recreation",
            "subcategory":"Boat Charter",
            "type":"Entertainment"
        }
    ],
    "sg:phone":"+61 8 9949 1764",
    "sg:postcode":"6707",
    "sg:province":"WA",
    "wof:name":"The Gun Charters",
    "wof:placetype":"venue"
},
  "geometry": {"coordinates":[114.122703552,-21.9241485596],"type":"Point"}
}