{
  "type": "Feature",
  "properties": {
    "addr:full":"14 Coronation Pde Enfield NSW 2136",
    "addr:housenumber":"14",
    "addr:postcode":"2136",
    "addr:street":"Coronation Pde",
    "iso:country":"AU",
    "sg:address":"14 Coronation Pde",
    "sg:city":"Enfield",
    "sg:classifiers":[
        {
            "category":"Travel",
            "subcategory":"Hotels & Motels",
            "type":"Entertainment"
        }
    ],
    "sg:phone":"+61 2 9747 8196",
    "sg:postcode":"2136",
    "sg:province":"NSW",
    "sg:tags":[
        "accommodation"
    ],
    "wof:name":"Boulevarde Hotel Enfield",
    "wof:placetype":"venue"
},
  "geometry": {"coordinates":[151.091705322,-33.8881340027],"type":"Point"}
}