{
  "type": "Feature",
  "properties": {
    "iso:country":"AU",
    "sg:address":"292 Kingsgrove St",
    "sg:city":"Kingsgrove",
    "sg:classifiers":[
        {
            "category":"Fast Food",
            "type":"Food & Drink"
        }
    ],
    "sg:phone":"+61 2 9502 1068",
    "sg:postcode":"2208",
    "sg:province":"NSW",
    "sg:tags":[
        "away",
        "take"
    ],
    "wof:name":"Charcoal Chicken Kingsgrove",
    "wof:placetype":"venue"
},
  "geometry": {"coordinates":[151.101669,-33.942581],"type":"Point"}
}