{
  "type": "Feature",
  "properties": {
    "addr:full":"292 Kingsgrove St Kingsgrove NSW 2208",
    "addr:housenumber":"292",
    "addr:postcode":"2208",
    "addr:street":"Kingsgrove St",
    "iso:country":"AU",
    "sg:address":"292 Kingsgrove St",
    "sg:city":"Kingsgrove",
    "sg:classifiers":[
        {
            "category":"Fast Food",
            "type":"Food & Drink"
        }
    ],
    "sg:phone":"+61 2 9502 1068",
    "sg:postcode":"2208",
    "sg:province":"NSW",
    "sg:tags":[
        "away",
        "take"
    ],
    "wof:name":"Charcoal Chicken Kingsgrove",
    "wof:placetype":"venue"
},
  "geometry": {"coordinates":[151.10166899999999,-33.942581],"type":"Point"}
}