{
  "type": "Feature",
  "properties": {
    "addr:full":"65 Forest Ave Newton SA 5074",
    "addr:housenumber":"65",
    "addr:postcode":"5074",
    "addr:street":"Forest Ave",
    "iso:country":"AU",
    "sg:address":"65 Forest Ave",
    "sg:city":"Newton",
    "sg:classifiers":[
        {
            "category":"Health Services",
            "subcategory":"Health Practitioner",
            "type":"Services"
        }
    ],
    "sg:phone":"+61 8 8165 2346",
    "sg:postcode":"5074",
    "sg:province":"SA",
    "sg:tags":[
        "alternative"
    ],
    "wof:name":"Scott-Mills Remedial Therapies",
    "wof:placetype":"venue"
},
  "geometry": {"coordinates":[138.68104553200001,-34.8846244812],"type":"Point"}
}