{
  "type": "Feature",
  "properties": {
    "iso:country":"AU",
    "sg:address":"144 Jetty Rd",
    "sg:city":"Glenelg",
    "sg:classifiers":[
        {
            "category":"Shopping",
            "subcategory":"Computers & Home Electronics",
            "type":"Retail Goods"
        }
    ],
    "sg:phone":"+61 8 8295 4181",
    "sg:postcode":"5045",
    "sg:province":"SA",
    "sg:tags":[
        "equipment",
        "part",
        "electronic"
    ],
    "wof:name":"Tandy",
    "wof:placetype":"venue"
},
  "geometry": {"coordinates":[138.51817299999999,-34.980267],"type":"Point"}
}