{
  "type": "Feature",
  "properties": {
    "addr:full":"Exchange Courtyard, Grosvenor Place 225 George Street Sydney NSW 2001",
    "addr:housenumber":"225",
    "addr:postcode":"2001",
    "addr:street":"Grosvenor;George Street",
    "iso:country":"AU",
    "sg:address":"Exchange Courtyard, Grosvenor Place 225",
    "sg:city":"George Street Sydney",
    "sg:classifiers":[
        {
            "category":"Health Services",
            "subcategory":"Dentist",
            "type":"Services"
        }
    ],
    "sg:phone":"+61 2 9251 8889",
    "sg:postcode":"2001",
    "sg:province":"NSW",
    "wof:name":"A Active Dental Centre",
    "wof:placetype":"venue"
},
  "geometry": {"coordinates":[151.20735168499999,-33.8631744385],"type":"Point"}
}