{
  "type": "Feature",
  "properties": {
    "iso:country":"AU",
    "sg:address":"52 Oaklands Rd",
    "sg:city":"Pambula",
    "sg:classifiers":[
        {
            "category":"Professional",
            "type":"Services"
        }
    ],
    "sg:phone":"+61 403 778 790",
    "sg:postcode":"2549",
    "sg:province":"NSW",
    "sg:tags":[
        "shop",
        "fitting"
    ],
    "wof:name":"Gerry Holligan",
    "wof:placetype":"venue"
},
  "geometry": {"coordinates":[149.86257934599999,-36.9297485352],"type":"Point"}
}