{
  "type": "Feature",
  "properties": {
    "addr:full":"15 Bourbong St Bundaberg QLD 4670",
    "addr:housenumber":"15",
    "addr:postcode":"4670",
    "addr:street":"Bourbong St",
    "iso:country":"AU",
    "sg:address":"15 Bourbong St",
    "sg:city":"Bundaberg",
    "sg:classifiers":[
        {
            "category":"Autos & Motor Vehicles",
            "subcategory":"Automobile Sales",
            "type":"Retail Goods"
        }
    ],
    "sg:phone":"+61 7 4151 1923",
    "sg:postcode":"4670",
    "sg:province":"QLD",
    "sg:tags":[
        "car",
        "new"
    ],
    "wof:name":"Chrysler",
    "wof:placetype":"venue"
},
  "geometry": {"coordinates":[152.35072326700001,-24.8653640747],"type":"Point"}
}