{
  "type": "Feature",
  "properties": {
    "addr:full":"36 Cole St Alderley QLD 4051",
    "addr:housenumber":"36",
    "addr:postcode":"4051",
    "addr:street":"Cole St",
    "iso:country":"AU",
    "sg:address":"36 Cole St",
    "sg:city":"Alderley",
    "sg:classifiers":[
        {
            "category":"Professional",
            "subcategory":"Engineering",
            "type":"Services"
        }
    ],
    "sg:phone":"+61 7 3856 3966",
    "sg:postcode":"4051",
    "sg:province":"QLD",
    "sg:tags":[
        "manufacturing",
        "engineer"
    ],
    "wof:name":"Supply Source International",
    "wof:placetype":"venue"
},
  "geometry": {"coordinates":[152.995803833,-27.4264945984],"type":"Point"}
}