{
  "type": "Feature",
  "properties": {
    "iso:country":"AU",
    "sg:address":"Unit 1, Building A Portside Distribution Centre 2-",
    "sg:city":"Banksmeadow",
    "sg:classifiers":[
        {
            "category":"Shopping",
            "subcategory":"Gifts & Souvenirs",
            "type":"Retail Goods"
        }
    ],
    "sg:phone":"+61 1300 309 924",
    "sg:postcode":"2019",
    "sg:province":"NSW",
    "sg:tags":[
        "shop",
        "supply"
    ],
    "wof:name":"Russ Berrie",
    "wof:placetype":"venue"
},
  "geometry": {"coordinates":[151.20953369099999,-33.9572257996],"type":"Point"}
}