{
  "type": "Feature",
  "properties": {
    "iso:country":"AU",
    "sg:address":"Level 3, 825 Hay St",
    "sg:city":"Perth",
    "sg:classifiers":[
        {
            "category":"Professional",
            "subcategory":"Employment Agencies",
            "type":"Services"
        }
    ],
    "sg:phone":"+61 8 9278 8999",
    "sg:postcode":"6000",
    "sg:province":"WA",
    "sg:tags":[
        "theatrical",
        "managers",
        "agent",
        "producer"
    ],
    "wof:name":"West Australian Opera Perth",
    "wof:placetype":"venue"
},
  "geometry": {"coordinates":[115.851257324,-31.9518013],"type":"Point"}
}