{
  "type": "Feature",
  "properties": {
    "addr:full":"Shp7/ 9 Elizabeth Ave Clontarf QLD 4019",
    "addr:housenumber":"9",
    "addr:postcode":"4019",
    "addr:street":"Elizabeth Ave",
    "iso:country":"AU",
    "sg:address":"Shp7/ 9 Elizabeth Ave",
    "sg:city":"Clontarf",
    "sg:classifiers":[
        {
            "category":"Food & Beverages",
            "subcategory":"Fruits & Vegetables",
            "type":"Retail Goods"
        }
    ],
    "sg:phone":"+61 7 3284 7787",
    "sg:postcode":"4019",
    "sg:province":"QLD",
    "sg:tags":[
        "greengrocer",
        "fruiterer"
    ],
    "wof:name":"Fine Fruits On Bayside",
    "wof:placetype":"venue"
},
  "geometry": {"coordinates":[153.079833984,-27.2613754272],"type":"Point"}
}