{
  "type": "Feature",
  "properties": {
    "iso:country":"AU",
    "sg:address":"16 Ryan St",
    "sg:city":"Lilyfield",
    "sg:classifiers":[
        {
            "category":"Professional",
            "subcategory":"Art Services",
            "type":"Services"
        }
    ],
    "sg:phone":"+61 2 9818 4763",
    "sg:postcode":"2040",
    "sg:province":"NSW",
    "sg:tags":[
        "interior",
        "decorator"
    ],
    "wof:name":"Indigo Colour & Design",
    "wof:placetype":"venue"
},
  "geometry": {"coordinates":[151.16738899999999,-33.871288],"type":"Point"}
}