{
  "type": "Feature",
  "properties": {
    "iso:country":"AU",
    "sg:address":"8- 12 Bullivant St",
    "sg:city":"Wangaratta",
    "sg:classifiers":[
        {
            "category":"Retail",
            "subcategory":"Auto Rental",
            "type":"Services"
        }
    ],
    "sg:phone":"+61 3 5721 6611",
    "sg:postcode":"3677",
    "sg:province":"VIC",
    "sg:tags":[
        "car",
        "hire",
        "minibus"
    ],
    "wof:name":"Cullen's Wangaratta",
    "wof:placetype":"venue"
},
  "geometry": {"coordinates":[146.325881958,-36.355632782],"type":"Point"}
}