{
  "type": "Feature",
  "properties": {
    "addr:full":"153- 155 Lords Pl Orange NSW 2800",
    "addr:housenumber":"155",
    "addr:postcode":"2800",
    "addr:street":"Lords Pl",
    "iso:country":"AU",
    "sg:address":"153- 155 Lords Pl",
    "sg:city":"Orange",
    "sg:classifiers":[
        {
            "category":"Real Estate",
            "subcategory":"Real Estate Services",
            "type":"Services"
        }
    ],
    "sg:phone":"+61 2 6361 0133",
    "sg:postcode":"2800",
    "sg:province":"NSW",
    "sg:tags":[
        "consultant",
        "property"
    ],
    "wof:name":"John Cook Real Estate",
    "wof:placetype":"venue"
},
  "geometry": {"coordinates":[149.10081481899999,-33.2847938538],"type":"Point"}
}