{
  "type": "Feature",
  "properties": {
    "addr:full":"4/ 172 St Brigids Tce Scarborough WA 6019",
    "addr:housenumber":"/ 172",
    "addr:postcode":"6019",
    "addr:street":"St Brigids Tce",
    "iso:country":"AU",
    "sg:address":"4/ 172 St",
    "sg:city":"Brigids Tce Scarborough",
    "sg:classifiers":[
        {
            "category":"Travel",
            "subcategory":"Hotels & Motels",
            "type":"Entertainment"
        }
    ],
    "sg:phone":"+61 8 9245 5269",
    "sg:postcode":"6019",
    "sg:province":"WA",
    "sg:tags":[
        "accommodation"
    ],
    "wof:name":"Scarborough Holiday Apartments",
    "wof:placetype":"venue"
},
  "geometry": {"coordinates":[115.774986267,-31.8978881836],"type":"Point"}
}