{
  "type": "Feature",
  "properties": {
    "iso:country":"AU",
    "sg:address":"25 Scott St",
    "sg:city":"Caulfield South",
    "sg:classifiers":[
        {
            "category":"Real Estate",
            "subcategory":"Architect",
            "type":"Services"
        }
    ],
    "sg:phone":"+61 3 9578 3188",
    "sg:postcode":"3162",
    "sg:province":"VIC",
    "wof:name":"Bowe Australia",
    "wof:placetype":"venue"
},
  "geometry": {"coordinates":[145.03045654300001,-37.9010925293],"type":"Point"}
}