{
  "type": "Feature",
  "properties": {
    "addr:full":"106 Main Rd McLaren Vale SA 5171",
    "addr:housenumber":"106",
    "addr:postcode":"5171",
    "addr:street":"Main Rd",
    "iso:country":"AU",
    "sg:address":"106 Main Rd",
    "sg:city":"McLaren Vale",
    "sg:classifiers":[
        {
            "category":"Health Services",
            "subcategory":"Health Practitioner",
            "type":"Services"
        }
    ],
    "sg:phone":"+61 8 8323 8058",
    "sg:postcode":"5171",
    "sg:province":"SA",
    "sg:tags":[
        "physiotherapist"
    ],
    "wof:name":"Prider Sue",
    "wof:placetype":"venue"
},
  "geometry": {"coordinates":[138.53706359899999,-35.2149085999],"type":"Point"}
}