{
  "type": "Feature",
  "properties": {
    "addr:full":"63 Bardo Rd Newport NSW 2106",
    "addr:housenumber":"63",
    "addr:postcode":"2106",
    "addr:street":"Bardo Rd",
    "iso:country":"AU",
    "sg:address":"63 Bardo Rd",
    "sg:city":"Newport",
    "sg:classifiers":[
        {
            "category":"Building & Trades",
            "subcategory":"Plumbing",
            "type":"Services"
        }
    ],
    "sg:phone":"+61 2 9999 2147",
    "sg:postcode":"2106",
    "sg:province":"NSW",
    "sg:tags":[
        "plumber",
        "gasfitters"
    ],
    "wof:name":"Mark Holmes Plumbing Service Pty Ltd",
    "wof:placetype":"venue"
},
  "geometry": {"coordinates":[151.31190490700001,-33.6567726135],"type":"Point"}
}