{
  "type": "Feature",
  "properties": {
    "iso:country":"AU",
    "sg:address":"21 Fairbrother St",
    "sg:city":"Belmont",
    "sg:classifiers":[
        {
            "category":"Retail",
            "subcategory":"Auto Repair",
            "type":"Services"
        }
    ],
    "sg:phone":"+61 8 9277 2153",
    "sg:postcode":"6104",
    "sg:province":"WA",
    "sg:tags":[
        "beater",
        "painter",
        "panel"
    ],
    "wof:name":"Belmont Panel & Paint",
    "wof:placetype":"venue"
},
  "geometry": {"coordinates":[115.92794799799999,-31.9519252777],"type":"Point"}
}