{
  "type": "Feature",
  "properties": {
    "iso:country":"AU",
    "sg:address":"1076 Yarramalong Rd",
    "sg:city":"Wyong Creek",
    "sg:classifiers":[
        {
            "category":"Home & Garden",
            "subcategory":"Garden Supply",
            "type":"Retail Goods"
        }
    ],
    "sg:phone":"+61 2 4353 2947",
    "sg:postcode":"2259",
    "sg:province":"NSW",
    "sg:tags":[
        "landscape"
    ],
    "wof:name":"Mardi Park Turf",
    "wof:placetype":"venue"
},
  "geometry": {"coordinates":[151.32417297399999,-33.2536354065],"type":"Point"}
}