{
  "type": "Feature",
  "properties": {
    "iso:country":"AU",
    "sg:address":"26 Milparinka Ave",
    "sg:city":"Glenwood",
    "sg:classifiers":[
        {
            "category":"Retail",
            "subcategory":"Auto Repair",
            "type":"Services"
        }
    ],
    "sg:phone":"+61 422 133 685",
    "sg:postcode":"2768",
    "sg:province":"NSW",
    "sg:tags":[
        "beater",
        "painter",
        "panel"
    ],
    "wof:name":"Dent Squad",
    "wof:placetype":"venue"
},
  "geometry": {"coordinates":[150.93177800000001,-33.736401],"type":"Point"}
}