{
  "type": "Feature",
  "properties": {
    "addr:full":"350 Charman Rd Cheltenham VIC 3192",
    "addr:housenumber":"350",
    "addr:postcode":"3192",
    "addr:street":"Charman Rd",
    "iso:country":"AU",
    "sg:address":"350 Charman Rd",
    "sg:city":"Cheltenham",
    "sg:classifiers":[
        {
            "category":"Professional",
            "subcategory":"Accounting & Tax Preparation",
            "type":"Services"
        }
    ],
    "sg:phone":"+61 3 9585 7009",
    "sg:postcode":"3192",
    "sg:province":"VIC",
    "sg:tags":[
        "accountant",
        "auditor"
    ],
    "wof:name":"Rispin Financial",
    "wof:placetype":"venue"
},
  "geometry": {"coordinates":[145.05589294399999,-37.9651947021],"type":"Point"}
}