{
  "type": "Feature",
  "properties": {
    "addr:full":"31 Norseman Rd Esperance WA 6450",
    "addr:housenumber":"31",
    "addr:postcode":"6450",
    "addr:street":"Norseman Rd",
    "iso:country":"AU",
    "sg:address":"31 Norseman Rd",
    "sg:city":"Esperance",
    "sg:classifiers":[
        {
            "category":"Autos & Motor Vehicles",
            "subcategory":"Automobile Sales",
            "type":"Retail Goods"
        }
    ],
    "sg:phone":"+61 8 9071 1722",
    "sg:postcode":"6450",
    "sg:province":"WA",
    "sg:tags":[
        "car",
        "used"
    ],
    "wof:name":"Norfolk Motors",
    "wof:placetype":"venue"
},
  "geometry": {"coordinates":[121.90003967299999,-33.8440132141],"type":"Point"}
}