{
  "type": "Feature",
  "properties": {
    "addr:full":"Suite 4/ 2 Gilbert St Lyndoch SA 5351",
    "addr:postcode":"5351",
    "addr:street":"Gilbert St",
    "iso:country":"AU",
    "sg:address":"Suite 4/ 2 Gilbert St",
    "sg:city":"Lyndoch",
    "sg:classifiers":[
        {
            "category":"Professional",
            "subcategory":"Engineering",
            "type":"Services"
        }
    ],
    "sg:phone":"+61 8 8524 5577",
    "sg:postcode":"5351",
    "sg:province":"SA",
    "sg:tags":[
        "consulting",
        "engineer"
    ],
    "wof:name":"Russell Consulting Engineers",
    "wof:placetype":"venue"
},
  "geometry": {"coordinates":[138.89077758799999,-34.6016387939],"type":"Point"}
}