{
  "type": "Feature",
  "properties": {
    "addr:full":"6 Culcairn Drv Frankston South VIC 3199",
    "addr:housenumber":"6",
    "addr:postcode":"3199",
    "addr:street":"Culcairn Drv",
    "iso:country":"AU",
    "sg:address":"6 Culcairn Drv",
    "sg:city":"Frankston South",
    "sg:classifiers":[
        {
            "category":"Professional",
            "subcategory":"Accounting & Tax Preparation",
            "type":"Services"
        }
    ],
    "sg:phone":"+61 3 9770 0566",
    "sg:postcode":"3199",
    "sg:province":"VIC",
    "sg:tags":[
        "accountant",
        "auditor"
    ],
    "wof:name":"Vergona Richard",
    "wof:placetype":"venue"
},
  "geometry": {"coordinates":[145.13648986800001,-38.1664161682],"type":"Point"}
}