{
  "type": "Feature",
  "properties": {
    "addr:full":"140 Bridge Rd Keysborough VIC 3173",
    "addr:housenumber":"140",
    "addr:postcode":"3173",
    "addr:street":"Bridge Rd",
    "iso:country":"AU",
    "sg:address":"140 Bridge Rd",
    "sg:city":"Keysborough",
    "sg:classifiers":[
        {
            "category":"Manufacturing",
            "subcategory":"Motor Vehicles & Parts",
            "type":"Manufacturing & Wholesale Goods"
        }
    ],
    "sg:phone":"+61 3 9701 8740",
    "sg:postcode":"3173",
    "sg:province":"VIC",
    "sg:tags":[
        "replacement"
    ],
    "wof:name":"Comm Ford Recyclers",
    "wof:placetype":"venue"
},
  "geometry": {"coordinates":[145.19227600100001,-37.9865379333],"type":"Point"}
}