{
  "type": "Feature",
  "properties": {
    "addr:full":"Cnr Princes Hwy & Leesons Rd Traralgon VIC 3844",
    "addr:postcode":"3844",
    "addr:street":"Cnr Princes Hwy & Leesons Rd",
    "iso:country":"AU",
    "sg:address":"Cnr Princes Hwy & Leesons Rd",
    "sg:city":"Traralgon",
    "sg:classifiers":[
        {
            "category":"Building & Trades",
            "subcategory":"Construction",
            "type":"Services"
        }
    ],
    "sg:phone":"+61 3 5176 2066",
    "sg:postcode":"3844",
    "sg:province":"VIC",
    "sg:tags":[
        "fencing",
        "contractor"
    ],
    "wof:name":"Gippsland Fencing Supplies",
    "wof:placetype":"venue"
},
  "geometry": {"coordinates":[146.541107178,-38.1958122253],"type":"Point"}
}