{
  "type": "Feature",
  "properties": {
    "addr:full":"PO Box 1495 Southport QLD 4215",
    "addr:postcode":"4215",
    "iso:country":"AU",
    "sg:address":"PO Box 1495",
    "sg:city":"Southport",
    "sg:classifiers":[
        {
            "category":"Building & Trades",
            "subcategory":"Construction",
            "type":"Services"
        }
    ],
    "sg:phone":"+61 404 462 496",
    "sg:postcode":"4215",
    "sg:province":"QLD",
    "sg:tags":[
        "stonework",
        "stone",
        "mason"
    ],
    "wof:name":"Artistone Custom Stone Design",
    "wof:placetype":"venue"
},
  "geometry": {"coordinates":[153.415557861,-27.9655303955],"type":"Point"}
}