{
  "type": "Feature",
  "properties": {
    "addr:full":"Cnr Nicholson & Vostan Rd Canning Vale WA 6155",
    "addr:postcode":"6155",
    "addr:street":"Cnr;Rd",
    "iso:country":"AU",
    "sg:address":"Cnr Nicholson & Vostan Rd",
    "sg:city":"Canning Vale",
    "sg:classifiers":[
        {
            "category":"Health Services",
            "subcategory":"Optometrist",
            "type":"Services"
        }
    ],
    "sg:phone":"+61 8 6252 0057",
    "sg:postcode":"6155",
    "sg:province":"WA",
    "wof:name":"My Optometrist",
    "wof:placetype":"venue"
},
  "geometry": {"coordinates":[115.920441,-32.080193],"type":"Point"}
}