{
  "type": "Feature",
  "properties": {
    "addr:full":"228 Woolooware Rd South Woolooware NSW 2230",
    "addr:housenumber":"228",
    "addr:postcode":"2230",
    "addr:street":"Woolooware Rd South",
    "iso:country":"AU",
    "sg:address":"228 Woolooware Rd South",
    "sg:city":"Woolooware",
    "sg:classifiers":[
        {
            "category":"Retail",
            "subcategory":"Event Space",
            "type":"Services"
        }
    ],
    "sg:phone":"+61 2 9523 9300",
    "sg:postcode":"2230",
    "sg:province":"NSW",
    "sg:tags":[
        "venue",
        "reception",
        "wedding"
    ],
    "wof:name":"Royal Motor Yacht Club Port Hacking",
    "wof:placetype":"venue"
},
  "geometry": {"coordinates":[151.13899230999999,-34.0620002747],"type":"Point"}
}