{
  "type": "Feature",
  "properties": {
    "addr:full":"55 Infantry Pde Holsworthy NSW 2173",
    "addr:housenumber":"55",
    "addr:postcode":"2173",
    "addr:street":"Infantry Pde",
    "iso:country":"AU",
    "sg:address":"55 Infantry Pde",
    "sg:city":"Holsworthy",
    "sg:classifiers":[
        {
            "category":"Social Services",
            "subcategory":"Child Care",
            "type":"Services"
        }
    ],
    "sg:phone":"+61 2 9825 3687",
    "sg:postcode":"2173",
    "sg:province":"NSW",
    "wof:name":"Holsworthy Children's Centre",
    "wof:placetype":"venue"
},
  "geometry": {"coordinates":[150.95542907699999,-33.9559326172],"type":"Point"}
}