{
  "type": "Feature",
  "properties": {
    "addr:full":"14 Dean St Bairnsdale VIC 3875",
    "addr:housenumber":"14",
    "addr:postcode":"3875",
    "addr:street":"Dean St",
    "iso:country":"AU",
    "sg:address":"14 Dean St",
    "sg:city":"Bairnsdale",
    "sg:classifiers":[
        {
            "category":"Building & Trades",
            "subcategory":"Cleaning & Sanitation",
            "type":"Services"
        }
    ],
    "sg:phone":"+61 3 5153 0835",
    "sg:postcode":"3875",
    "sg:province":"VIC",
    "sg:tags":[
        "window"
    ],
    "wof:name":"Bright Light Window Cleaning Service",
    "wof:placetype":"venue"
},
  "geometry": {"coordinates":[147.60810852,-37.8279304504],"type":"Point"}
}