{
  "type": "Feature",
  "properties": {
    "addr:full":"14a Chenery St Mansfield VIC 3722",
    "addr:housenumber":"14a",
    "addr:postcode":"3722",
    "addr:street":"Chenery St",
    "iso:country":"AU",
    "sg:address":"14a Chenery St",
    "sg:city":"Mansfield",
    "sg:classifiers":[
        {
            "category":"Retail",
            "subcategory":"Auto Repair",
            "type":"Services"
        }
    ],
    "sg:phone":"+61 3 5775 1540",
    "sg:postcode":"3722",
    "sg:province":"VIC",
    "sg:tags":[
        "repairer",
        "motor",
        "engineer"
    ],
    "wof:name":"Kirleys Automotive & Exhaust",
    "wof:placetype":"venue"
},
  "geometry": {"coordinates":[146.09266662600001,-37.0540771484],"type":"Point"}
}