{
  "type": "Feature",
  "properties": {
    "iso:country":"AU",
    "sg:address":"Shop 7/ 204 Warrandyte Rd",
    "sg:city":"Ringwood North",
    "sg:classifiers":[
        {
            "category":"Banks & Credit Unions",
            "subcategory":"Investment Brokerage",
            "type":"Services"
        }
    ],
    "sg:phone":"+61 1300 790 273",
    "sg:postcode":"3134",
    "sg:province":"VIC",
    "sg:tags":[
        "finance",
        "broker"
    ],
    "wof:name":"Australian Professional Finance",
    "wof:placetype":"venue"
},
  "geometry": {"coordinates":[145.23631286599999,-37.7889900208],"type":"Point"}
}