{
  "type": "Feature",
  "properties": {
    "addr:full":"141 Mentone Rd Mentone VIC 3194",
    "addr:housenumber":"141",
    "addr:postcode":"3194",
    "addr:street":"Mentone Rd",
    "iso:country":"AU",
    "sg:address":"141 Mentone Rd",
    "sg:city":"Mentone",
    "sg:classifiers":[
        {
            "category":"Shopping",
            "type":"Retail Goods"
        }
    ],
    "sg:phone":"+61 3 9583 7117",
    "sg:postcode":"3194",
    "sg:province":"VIC",
    "sg:tags":[
        "clearance",
        "factory",
        "outlet"
    ],
    "wof:name":"Mordy Surf & Sail",
    "wof:placetype":"venue"
},
  "geometry": {"coordinates":[145.064727783,-37.9825744629],"type":"Point"}
}