{
  "type": "Feature",
  "properties": {
    "addr:full":"Cnr Wetherill St (South) & Adderley St Lidcombe NSW 2141",
    "addr:postcode":"2141",
    "addr:street":"Wetherill St South & Adderley St",
    "iso:country":"AU",
    "sg:address":"Cnr Wetherill St (South) & Adderley St",
    "sg:city":"Lidcombe",
    "sg:classifiers":[
        {
            "category":"Wholesale",
            "subcategory":"Music Publishers",
            "type":"Manufacturing & Wholesale Goods"
        }
    ],
    "sg:phone":"+61 2 9748 6055",
    "sg:postcode":"2141",
    "sg:province":"NSW",
    "sg:tags":[
        "wholesaler",
        "dvd",
        "mfrs",
        "cd"
    ],
    "wof:name":"Audio Cassette Duplicating Co The",
    "wof:placetype":"venue"
},
  "geometry": {"coordinates":[151.04487609899999,-33.8452987671],"type":"Point"}
}