{
  "type": "Feature",
  "properties": {
    "iso:country":"AU",
    "sg:address":"Shop 1/ 161 Military Rd",
    "sg:city":"Dover Heights",
    "sg:classifiers":[
        {
            "category":"Health Services",
            "subcategory":"Dentist",
            "type":"Services"
        }
    ],
    "sg:phone":"+61 2 9388 1988",
    "sg:postcode":"2030",
    "sg:province":"NSW",
    "wof:name":"Wayne-Shevchuk Sophia",
    "wof:placetype":"venue"
},
  "geometry": {"coordinates":[151.28094482399999,-33.8724441528],"type":"Point"}
}