{
  "type": "Feature",
  "properties": {
    "iso:country":"AU",
    "sg:address":"23 Molloy Street",
    "sg:city":"Toowoomba",
    "sg:classifiers":[
        {
            "category":"Building & Trades",
            "subcategory":"Cleaning & Sanitation",
            "type":"Services"
        }
    ],
    "sg:phone":"+61 7 4633 4555",
    "sg:postcode":"4350",
    "sg:province":"QLD",
    "sg:tags":[
        "abrasive",
        "blasting"
    ],
    "wof:name":"Toowoomba Sandblasting",
    "wof:placetype":"venue"
},
  "geometry": {"coordinates":[151.89830000000001,-27.55509],"type":"Point"}
}