{
  "type": "Feature",
  "properties": {
    "iso:country":"AU",
    "sg:address":"304 Tuggerawong Rd",
    "sg:city":"Tuggerawong",
    "sg:classifiers":[
        {
            "category":"Building & Trades",
            "subcategory":"Construction",
            "type":"Services"
        }
    ],
    "sg:phone":"+61 2 4393 2380",
    "sg:postcode":"2259",
    "sg:province":"NSW",
    "sg:tags":[
        "joiner",
        "carpenter"
    ],
    "wof:name":"Holmes P & J",
    "wof:placetype":"venue"
},
  "geometry": {"coordinates":[151.47691345199999,-33.2807197571],"type":"Point"}
}