{
  "type": "Feature",
  "properties": {
    "addr:full":"300 Queen St Brisbane QLD 4000",
    "addr:housenumber":"300",
    "addr:postcode":"4000",
    "addr:street":"Queen St",
    "iso:country":"AU",
    "sg:address":"300 Queen St",
    "sg:city":"Brisbane",
    "sg:classifiers":[
        {
            "category":"Structure",
            "subcategory":"Office Building",
            "type":"Public Place"
        }
    ],
    "sg:phone":"+61 7 3023 5000",
    "sg:postcode":"4000",
    "sg:province":"QLD",
    "sg:tags":[
        "serviced"
    ],
    "wof:name":"International Business Corporation",
    "wof:placetype":"venue"
},
  "geometry": {"coordinates":[153.02821350100001,-27.4671478271],"type":"Point"}
}