{
  "type": "Feature",
  "properties": {
    "iso:country":"AU",
    "sg:address":"Lv 2/ 65 - 67 Burelli St",
    "sg:city":"Wollongong",
    "sg:classifiers":[
        {
            "category":"Personal",
            "subcategory":"Beauty Salon",
            "type":"Services"
        }
    ],
    "sg:phone":"+61 2 4226 9455",
    "sg:postcode":"2500",
    "sg:province":"NSW",
    "wof:name":"Beautylicious Nails & Beauty",
    "wof:placetype":"venue"
},
  "geometry": {"coordinates":[150.895233,-34.426453],"type":"Point"}
}