{
  "type": "Feature",
  "properties": {
    "iso:country":"AU",
    "sg:address":"Suite 15, Queensland Arc, 181 Church St",
    "sg:city":"Parramatta",
    "sg:classifiers":[
        {
            "category":"Health Services",
            "subcategory":"Dentist",
            "type":"Services"
        }
    ],
    "sg:phone":"+61 2 9891 4393",
    "sg:postcode":"2150",
    "sg:province":"NSW",
    "wof:name":"Tan Franciskus",
    "wof:placetype":"venue"
},
  "geometry": {"coordinates":[151.11892700199999,-33.8752441406],"type":"Point"}
}