{
  "type": "Feature",
  "properties": {
    "iso:country":"AU",
    "sg:address":"38 Fuller Rd",
    "sg:city":"Wonthaggi",
    "sg:classifiers":[
        {
            "category":"Utilities",
            "subcategory":"Refuse",
            "type":"Services"
        }
    ],
    "sg:phone":"+61 3 5672 2056",
    "sg:postcode":"3995",
    "sg:province":"VIC",
    "sg:tags":[
        "remover",
        "rubbish"
    ],
    "wof:name":"Phillip Island Waste",
    "wof:placetype":"venue"
},
  "geometry": {"coordinates":[145.590591,-38.587227],"type":"Point"}
}