{
  "type": "Feature",
  "properties": {
    "addr:full":"38 Sunningdale Ave Rochedale QLD 4123",
    "addr:housenumber":"38",
    "addr:postcode":"4123",
    "addr:street":"Sunningdale Ave",
    "iso:country":"AU",
    "sg:address":"38 Sunningdale Ave",
    "sg:city":"Rochedale",
    "sg:classifiers":[
        {
            "category":"Social Services",
            "subcategory":"Child Care",
            "type":"Services"
        }
    ],
    "sg:phone":"+61 7 3341 0440",
    "sg:postcode":"4123",
    "sg:province":"QLD",
    "wof:name":"Rochedale Community Centre Inc",
    "wof:placetype":"venue"
},
  "geometry": {"coordinates":[153.125854492,-27.5989189148],"type":"Point"}
}