{
  "type": "Feature",
  "properties": {
    "addr:full":"190- 192 Muller Rd Taigum QLD 4018",
    "addr:housenumber":"192",
    "addr:postcode":"4018",
    "addr:street":"Muller Rd",
    "iso:country":"AU",
    "sg:address":"190- 192 Muller Rd",
    "sg:city":"Taigum",
    "sg:classifiers":[
        {
            "category":"Organizations",
            "subcategory":"Non-profit Organization",
            "type":"Services"
        }
    ],
    "sg:phone":"+61 7 3633 0177",
    "sg:postcode":"4018",
    "sg:province":"QLD",
    "sg:tags":[
        "support",
        "disability",
        "organisation"
    ],
    "wof:name":"Qualtime Association Incorporated",
    "wof:placetype":"venue"
},
  "geometry": {"coordinates":[153.053146,-27.348667],"type":"Point"}
}