{
  "type": "Feature",
  "properties": {
    "iso:country":"AU",
    "sg:address":"185 Wellington St",
    "sg:city":"Launceston",
    "sg:classifiers":[
        {
            "category":"Fast Food",
            "type":"Food & Drink"
        }
    ],
    "sg:phone":"+61 3 6334 6955",
    "sg:postcode":"7250",
    "sg:province":"TAS",
    "sg:tags":[
        "away",
        "take"
    ],
    "wof:name":"Tandoor & Curry House",
    "wof:placetype":"venue"
},
  "geometry": {"coordinates":[147.13934326200001,-41.4454460144],"type":"Point"}
}