{
  "type": "Feature",
  "properties": {
    "addr:full":"Shop SPI, Auburn Central Shopping Ctnr,128-136 South Pde Auburn NSW 2144",
    "addr:housenumber":"128-136",
    "addr:postcode":"2144",
    "addr:street":"South Pde",
    "iso:country":"AU",
    "sg:address":"Shop SPI, Auburn Central Shopping Ctnr,128-136 South Pde",
    "sg:city":"Auburn",
    "sg:classifiers":[
        {
            "category":"Shopping",
            "subcategory":"Shoes",
            "type":"Retail Goods"
        }
    ],
    "sg:phone":"+61 2 9649 3008",
    "sg:postcode":"2144",
    "sg:province":"NSW",
    "sg:tags":[
        "footwear"
    ],
    "wof:name":"Direct Shoe Warehouse",
    "wof:placetype":"venue"
},
  "geometry": {"coordinates":[151.031173706,-33.8482246399],"type":"Point"}
}