{
  "type": "Feature",
  "properties": {
    "addr:full":"Wandary La Forbes NSW 2871",
    "addr:postcode":"2871",
    "iso:country":"AU",
    "sg:address":"Wandary La",
    "sg:city":"Forbes",
    "sg:classifiers":[
        {
            "category":"Education",
            "subcategory":"Special Training",
            "type":"Public Place"
        }
    ],
    "sg:phone":"+61 2 6852 1221",
    "sg:postcode":"2871",
    "sg:province":"NSW",
    "sg:tags":[
        "instruction",
        "display",
        "parachuting"
    ],
    "wof:name":"Western Districts Parachute Club",
    "wof:placetype":"venue"
},
  "geometry": {"coordinates":[148.02220199999999,-33.402283],"type":"Point"}
}