{
  "type": "Feature",
  "properties": {
    "addr:full":"43 Sheehan Rd Heidelberg West VIC 3081",
    "addr:housenumber":"43",
    "addr:postcode":"3081",
    "addr:street":"Sheehan Rd",
    "iso:country":"AU",
    "sg:address":"43 Sheehan Rd",
    "sg:city":"Heidelberg West",
    "sg:classifiers":[
        {
            "category":"Utilities",
            "subcategory":"Electric",
            "type":"Services"
        }
    ],
    "sg:phone":"+61 3 9450 1300",
    "sg:postcode":"3081",
    "sg:province":"VIC",
    "sg:tags":[
        "electrical",
        "contractor"
    ],
    "wof:name":"Nilsen",
    "wof:placetype":"venue"
},
  "geometry": {"coordinates":[145.043136597,-37.7313537598],"type":"Point"}
}