{
  "type": "Feature",
  "properties": {
    "addr:full":"10 South West Hwy Waroona WA 6215",
    "addr:housenumber":"10",
    "addr:postcode":"6215",
    "addr:street":"South West Hwy",
    "iso:country":"AU",
    "sg:address":"10 South West Hwy",
    "sg:city":"Waroona",
    "sg:classifiers":[
        {
            "category":"Home & Garden",
            "subcategory":"Building Materials",
            "type":"Retail Goods"
        }
    ],
    "sg:phone":"+61 8 9733 1010",
    "sg:postcode":"6215",
    "sg:province":"WA",
    "sg:tags":[
        "merchant",
        "glass",
        "glazier"
    ],
    "wof:name":"Waroona Glass",
    "wof:placetype":"venue"
},
  "geometry": {"coordinates":[115.92150100000001,-32.842999],"type":"Point"}
}