{
  "type": "Feature",
  "properties": {
    "addr:full":"Shop 4, Marina Pier Building, Holdfast Shores Glenelg SA 5045",
    "addr:housenumber":"shop 4",
    "addr:postcode":"5045",
    "addr:street":"Marina",
    "iso:country":"AU",
    "sg:address":"Shop 4, Marina Pier Building, Holdfast Shores",
    "sg:city":"Glenelg",
    "sg:classifiers":[
        {
            "category":"Retail",
            "subcategory":"Event Space",
            "type":"Services"
        }
    ],
    "sg:phone":"+61 8 8376 6266",
    "sg:postcode":"5045",
    "sg:province":"SA",
    "sg:tags":[
        "function",
        "organiser"
    ],
    "wof:name":"Santa Fe Cuisine",
    "wof:placetype":"venue"
},
  "geometry": {"coordinates":[138.51989699999999,-34.985046],"type":"Point"}
}