{
  "type": "Feature",
  "properties": {
    "addr:full":"141 Walcott St Mt Lawley WA 6050",
    "addr:housenumber":"141",
    "addr:postcode":"6050",
    "addr:street":"Walcott St",
    "iso:country":"AU",
    "sg:address":"141 Walcott St",
    "sg:city":"Mt Lawley",
    "sg:classifiers":[
        {
            "category":"Health Services",
            "subcategory":"Health Practitioner",
            "type":"Services"
        }
    ],
    "sg:phone":"+61 8 9227 5579",
    "sg:postcode":"6050",
    "sg:province":"WA",
    "sg:tags":[
        "physiotherapist"
    ],
    "wof:name":"Cleary David J",
    "wof:placetype":"venue"
},
  "geometry": {"coordinates":[115.867477417,-31.9306278229],"type":"Point"}
}