{
  "type": "Feature",
  "properties": {
    "addr:full":"16 Lance Hill Ave Dunlop ACT 2615",
    "addr:housenumber":"16",
    "addr:postcode":"2615",
    "addr:street":"Lance Hill Ave",
    "iso:country":"AU",
    "sg:address":"16 Lance Hill Ave",
    "sg:city":"Dunlop",
    "sg:classifiers":[
        {
            "category":"Building & Trades",
            "subcategory":"Construction",
            "type":"Services"
        }
    ],
    "sg:phone":"+61 416 985 524",
    "sg:postcode":"2615",
    "sg:province":"ACT",
    "sg:tags":[
        "roof"
    ],
    "wof:name":"Boss Metal Roofing",
    "wof:placetype":"venue"
},
  "geometry": {"coordinates":[149.019973755,-35.1986351013],"type":"Point"}
}