{
  "type": "Feature",
  "properties": {
    "iso:country":"AU",
    "sg:address":"70 Browns Rd",
    "sg:city":"Kingston",
    "sg:classifiers":[
        {
            "category":"Building & Trades",
            "subcategory":"Construction",
            "type":"Services"
        }
    ],
    "sg:phone":"+61 3 6211 8449",
    "sg:postcode":"7050",
    "sg:province":"TAS",
    "sg:tags":[
        "management"
    ],
    "wof:name":"Vos Construction & Joinery Pty Ltd",
    "wof:placetype":"venue"
},
  "geometry": {"coordinates":[147.31282,-42.968136],"type":"Point"}
}