{
  "type": "Feature",
  "properties": {
    "iso:country":"AU",
    "sg:address":"Suite 1, Morley Medical Centre, 310 Walter Rd",
    "sg:city":"Morley",
    "sg:classifiers":[
        {
            "category":"Wholesale",
            "subcategory":"Medical Equipment & Supplies",
            "type":"Manufacturing & Wholesale Goods"
        }
    ],
    "sg:phone":"+61 8 9375 1633",
    "sg:postcode":"6062",
    "sg:province":"WA",
    "sg:tags":[
        "aids",
        "hearing"
    ],
    "wof:name":"AudioClinic",
    "wof:placetype":"venue"
},
  "geometry": {"coordinates":[115.891052246,-31.8979511261],"type":"Point"}
}