{
  "type": "Feature",
  "properties": {
    "addr:full":"258 Lower Heidelberg Rd Ivanhoe East VIC 3079",
    "addr:housenumber":"258",
    "addr:postcode":"3079",
    "addr:street":"Lower Heidelberg Rd",
    "iso:country":"AU",
    "sg:address":"258 Lower Heidelberg Rd",
    "sg:city":"Ivanhoe East",
    "sg:classifiers":[
        {
            "category":"Government",
            "subcategory":"Post Office",
            "type":"Public Place"
        }
    ],
    "sg:phone":"+61 3 9458 3992",
    "sg:postcode":"3079",
    "sg:province":"VIC",
    "sg:tags":[
        "yoga"
    ],
    "wof:name":"Pilates",
    "wof:placetype":"venue"
},
  "geometry": {"coordinates":[145.05973815900001,-37.7729873657],"type":"Point"}
}