{
  "type": "Feature",
  "properties": {
    "addr:full":"18 Sallows St Alexandra Hills QLD 4161",
    "addr:housenumber":"18",
    "addr:postcode":"4161",
    "addr:street":"Sallows St",
    "iso:country":"AU",
    "sg:address":"18 Sallows St",
    "sg:city":"Alexandra Hills",
    "sg:classifiers":[
        {
            "category":"Building & Trades",
            "subcategory":"Construction",
            "type":"Services"
        }
    ],
    "sg:phone":"+61 411 847 403",
    "sg:postcode":"4161",
    "sg:province":"QLD",
    "sg:tags":[
        "concrete",
        "contractor"
    ],
    "wof:name":"S & C Inches",
    "wof:placetype":"venue"
},
  "geometry": {"coordinates":[153.227752686,-27.5244865417],"type":"Point"}
}