{
  "type": "Feature",
  "properties": {
    "addr:full":"PO Box 233 Singleton NSW 2330",
    "addr:postcode":"2330",
    "iso:country":"AU",
    "sg:address":"PO Box 233",
    "sg:city":"Singleton",
    "sg:classifiers":[
        {
            "category":"Real Estate",
            "subcategory":"Real Estate Agent",
            "type":"Services"
        }
    ],
    "sg:phone":"+61 410 331 133",
    "sg:postcode":"2330",
    "sg:province":"NSW",
    "sg:tags":[
        "handyman's",
        "equipment",
        "hire",
        "builders",
        "contractor"
    ],
    "wof:name":"TVG Pty Ltd",
    "wof:placetype":"venue"
},
  "geometry": {"coordinates":[151.07446300000001,-32.660648],"type":"Point"}
}