{
  "type": "Feature",
  "properties": {
    "iso:country":"AU",
    "sg:address":"Lot 66",
    "sg:city":"Gunningba Parkway Warren",
    "sg:classifiers":[
        {
            "category":"Building & Trades",
            "subcategory":"Plumbing",
            "type":"Services"
        }
    ],
    "sg:phone":"+61 419 275 004",
    "sg:postcode":"2824",
    "sg:province":"NSW",
    "sg:tags":[
        "plumber",
        "gasfitters"
    ],
    "wof:name":"Frank Leach",
    "wof:placetype":"venue"
},
  "geometry": {"coordinates":[147.83132934599999,-31.7053203583],"type":"Point"}
}