{
  "type": "Feature",
  "properties": {
    "addr:full":"12 Bulrush Drv Bibra Lake WA 6163",
    "addr:housenumber":"12",
    "addr:postcode":"6163",
    "addr:street":"Bulrush Drv",
    "iso:country":"AU",
    "sg:address":"12 Bulrush Drv",
    "sg:city":"Bibra Lake",
    "sg:classifiers":[
        {
            "category":"Building & Trades",
            "subcategory":"Cleaning & Sanitation",
            "type":"Services"
        }
    ],
    "sg:phone":"+61 437 168 159",
    "sg:postcode":"6163",
    "sg:province":"WA",
    "sg:tags":[
        "industrial",
        "commercial",
        "contractor"
    ],
    "wof:name":"Margaret's Home Services",
    "wof:placetype":"venue"
},
  "geometry": {"coordinates":[115.832718,-32.102219],"type":"Point"}
}