{
  "type": "Feature",
  "properties": {
    "iso:country":"AU",
    "sg:address":"251 Collins St",
    "sg:city":"Melbourne",
    "sg:classifiers":[
        {
            "category":"Shopping",
            "subcategory":"Optical Goods",
            "type":"Retail Goods"
        }
    ],
    "sg:phone":"+61 3 9650 7955",
    "sg:postcode":"3000",
    "sg:province":"VIC",
    "sg:tags":[
        "dispenser",
        "prescription"
    ],
    "wof:name":"Eyes on collins",
    "wof:placetype":"venue"
},
  "geometry": {"coordinates":[144.96542358400001,-37.8159408569],"type":"Point"}
}