{
  "type": "Feature",
  "properties": {
    "addr:full":"64 Fingal Rd Fingal Head NSW 2487",
    "addr:housenumber":"64",
    "addr:postcode":"2487",
    "addr:street":"Fingal Rd",
    "iso:country":"AU",
    "sg:address":"64 Fingal Rd",
    "sg:city":"Fingal Head",
    "sg:classifiers":[
        {
            "category":"Cafe",
            "type":"Food & Drink"
        }
    ],
    "sg:phone":"+61 7 5523 1130",
    "sg:postcode":"2487",
    "sg:province":"NSW",
    "wof:name":"Sheoak Shack Gallery Cafe",
    "wof:placetype":"venue"
},
  "geometry": {"coordinates":[153.56570434599999,-28.2045001984],"type":"Point"}
}