{
  "type": "Feature",
  "properties": {
    "addr:full":"Chapel St Richmond NSW 2753",
    "addr:postcode":"2753",
    "addr:street":"Chapel St",
    "iso:country":"AU",
    "sg:address":"Chapel St",
    "sg:city":"Richmond",
    "sg:classifiers":[
        {
            "category":"Social Services",
            "subcategory":"Retirement Home",
            "type":"Services"
        }
    ],
    "sg:phone":"+61 2 4578 3188",
    "sg:postcode":"2753",
    "sg:province":"NSW",
    "sg:tags":[
        "village"
    ],
    "wof:name":"Hawkesbury Retirement Village",
    "wof:placetype":"venue"
},
  "geometry": {"coordinates":[150.744995117,-33.5949668884],"type":"Point"}
}