{
  "type": "Feature",
  "properties": {
    "addr:full":"5/ 451 Rocky Point Rd Sans Souci NSW 2219",
    "addr:housenumber":"/ 451",
    "addr:postcode":"2219",
    "addr:street":"Rocky Point Rd",
    "iso:country":"AU",
    "sg:address":"5/ 451 Rocky Point Rd",
    "sg:city":"Sans Souci",
    "sg:classifiers":[
        {
            "category":"Retail",
            "subcategory":"Auto Rental",
            "type":"Services"
        }
    ],
    "sg:phone":"+61 2 9519 3344",
    "sg:postcode":"2219",
    "sg:province":"NSW",
    "sg:tags":[
        "chauffeur",
        "car",
        "hire",
        "driven",
        "limousine"
    ],
    "wof:name":"Corporate Cars Australia Pty Ltd",
    "wof:placetype":"venue"
},
  "geometry": {"coordinates":[151.128387,-33.997871],"type":"Point"}
}