{
  "type": "Feature",
  "properties": {
    "addr:full":"81 Canterbury Rd Kilsyth VIC 3137",
    "addr:housenumber":"81",
    "addr:postcode":"3137",
    "addr:street":"Canterbury Rd",
    "iso:country":"AU",
    "sg:address":"81 Canterbury Rd",
    "sg:city":"Kilsyth",
    "sg:classifiers":[
        {
            "category":"Home & Garden",
            "subcategory":"Building Materials",
            "type":"Retail Goods"
        }
    ],
    "sg:phone":"+61 3 9761 9266",
    "sg:postcode":"3137",
    "sg:province":"VIC",
    "sg:tags":[
        "wall",
        "frame",
        "truss",
        "roof"
    ],
    "wof:name":"A G Building Supplies",
    "wof:placetype":"venue"
},
  "geometry": {"coordinates":[145.322875977,-37.8163261414],"type":"Point"}
}