{
  "type": "Feature",
  "properties": {
    "addr:full":"32 Palm St Maleny QLD 4552",
    "addr:housenumber":"32",
    "addr:postcode":"4552",
    "addr:street":"Palm St",
    "iso:country":"AU",
    "sg:address":"32 Palm St",
    "sg:city":"Maleny",
    "sg:classifiers":[
        {
            "category":"Building & Trades",
            "subcategory":"Cleaning & Sanitation",
            "type":"Services"
        }
    ],
    "sg:phone":"+61 404 094 045",
    "sg:postcode":"4552",
    "sg:province":"QLD",
    "sg:tags":[
        "window"
    ],
    "wof:name":"Blackall Window Cleaning",
    "wof:placetype":"venue"
},
  "geometry": {"coordinates":[152.847854614,-26.751285553],"type":"Point"}
}