{
  "type": "Feature",
  "properties": {
    "addr:full":"9 Whitehorse Rd Mt Clear VIC 3350",
    "addr:housenumber":"9",
    "addr:postcode":"3350",
    "addr:street":"Whitehorse Rd;Clear",
    "iso:country":"AU",
    "sg:address":"9 Whitehorse Rd",
    "sg:city":"Mt Clear",
    "sg:classifiers":[
        {
            "category":"Structure",
            "subcategory":"Office Building",
            "type":"Public Place"
        }
    ],
    "sg:phone":"+61 3 5330 1030",
    "sg:postcode":"3350",
    "sg:province":"VIC",
    "sg:tags":[
        "slater",
        "tiler",
        "roof"
    ],
    "wof:name":"Speedy Roofing Pty Ltd",
    "wof:placetype":"venue"
},
  "geometry": {"coordinates":[143.866623,-37.60334],"type":"Point"}
}