{
  "type": "Feature",
  "properties": {
    "iso:country":"AU",
    "sg:address":"1011 Mair St",
    "sg:city":"Ballarat",
    "sg:classifiers":[
        {
            "category":"Health Services",
            "subcategory":"Doctor",
            "type":"Services"
        }
    ],
    "sg:phone":"+61 3 5331 2988",
    "sg:postcode":"3350",
    "sg:province":"VIC",
    "sg:tags":[
        "medical",
        "practitioner"
    ],
    "wof:name":"Maher M H",
    "wof:placetype":"venue"
},
  "geometry": {"coordinates":[143.845306,-37.558376],"type":"Point"}
}