{
  "type": "Feature",
  "properties": {
    "iso:country":"AU",
    "sg:address":"Suite 5, 44 Kings Park Rd",
    "sg:city":"West Perth",
    "sg:classifiers":[
        {
            "category":"Health Services",
            "subcategory":"Health Practitioner",
            "type":"Services"
        }
    ],
    "sg:phone":"+61 8 9321 9544",
    "sg:postcode":"6005",
    "sg:province":"WA",
    "sg:tags":[
        "psychotherapist"
    ],
    "wof:name":"Tarpey Grace Dr",
    "wof:placetype":"venue"
},
  "geometry": {"coordinates":[115.837020874,-31.9514598846],"type":"Point"}
}