{
  "type": "Feature",
  "properties": {
    "addr:full":"193 Goonoo Goonoo Rd Tamworth NSW 2340",
    "addr:housenumber":"193",
    "addr:postcode":"2340",
    "addr:street":"Goonoo Goonoo Rd",
    "iso:country":"AU",
    "sg:address":"193 Goonoo Goonoo Rd",
    "sg:city":"Tamworth",
    "sg:classifiers":[
        {
            "category":"Travel",
            "subcategory":"Hotels & Motels",
            "type":"Entertainment"
        }
    ],
    "sg:phone":"+61 2 6765 5966",
    "sg:postcode":"2340",
    "sg:province":"NSW",
    "wof:name":"Country Capital Motel",
    "wof:placetype":"venue"
},
  "geometry": {"coordinates":[150.92286682100001,-31.1074504852],"type":"Point"}
}