{
  "type": "Feature",
  "properties": {
    "iso:country":"AU",
    "sg:address":"48 Railway St",
    "sg:city":"Liverpool",
    "sg:classifiers":[
        {
            "category":"Personal",
            "subcategory":"Beauty Salon",
            "type":"Services"
        }
    ],
    "sg:phone":"+61 2 9602 7585",
    "sg:postcode":"2170",
    "sg:province":"NSW",
    "sg:tags":[
        "hairdresser"
    ],
    "wof:name":"Adam Hairdressing Salon",
    "wof:placetype":"venue"
},
  "geometry": {"coordinates":[150.924728394,-33.9242630005],"type":"Point"}
}