{
  "type": "Feature",
  "properties": {
    "addr:full":"155- 157 Camberwell Rd Hawthorn East VIC 3123",
    "addr:housenumber":"155 157",
    "addr:postcode":"3123",
    "addr:street":"Camberwell Rd",
    "iso:country":"AU",
    "sg:address":"155- 157 Camberwell Rd",
    "sg:city":"Hawthorn East",
    "sg:classifiers":[
        {
            "category":"Shopping",
            "subcategory":"Computers & Home Electronics",
            "type":"Retail Goods"
        }
    ],
    "sg:phone":"+61 3 9813 3533",
    "sg:postcode":"3123",
    "sg:province":"VIC",
    "sg:tags":[
        "hi-fi",
        "equipment"
    ],
    "wof:name":"Tivoli Hi Fi",
    "wof:placetype":"venue"
},
  "geometry": {"coordinates":[145.054397583,-37.8290939331],"type":"Point"}
}