{
  "type": "Feature",
  "properties": {
    "addr:full":"354 The Park Drv Sanctuary Point NSW 2540",
    "addr:housenumber":"354",
    "addr:postcode":"2540",
    "addr:street":"The Park Drv",
    "iso:country":"AU",
    "sg:address":"354 The Park Drv",
    "sg:city":"Sanctuary Point",
    "sg:classifiers":[
        {
            "category":"Manufacturing",
            "subcategory":"Furniture",
            "type":"Manufacturing & Wholesale Goods"
        }
    ],
    "sg:phone":"+61 2 4443 9577",
    "sg:postcode":"2540",
    "sg:province":"NSW",
    "sg:tags":[
        "builder",
        "designer",
        "custom"
    ],
    "wof:name":"The Park Joinery",
    "wof:placetype":"venue"
},
  "geometry": {"coordinates":[150.63526916500001,-35.0956115723],"type":"Point"}
}