{
  "type": "Feature",
  "properties": {
    "iso:country":"AU",
    "sg:address":"Fcty3/ 8 Childs Rd",
    "sg:city":"Epping",
    "sg:classifiers":[
        {
            "category":"Home & Garden",
            "subcategory":"Carpets & Floor Coverings",
            "type":"Retail Goods"
        }
    ],
    "sg:phone":"+61 3 9408 4552",
    "sg:postcode":"3076",
    "sg:province":"VIC",
    "sg:tags":[
        "tile",
        "wall"
    ],
    "wof:name":"Plenty Valley Tile & Stone Co",
    "wof:placetype":"venue"
},
  "geometry": {"coordinates":[145.01512145999999,-37.6591758728],"type":"Point"}
}