{
  "type": "Feature",
  "properties": {
    "addr:full":"2/ 13 Barklya Pl Marsden QLD 4132",
    "addr:housenumber":"/ 13",
    "addr:postcode":"4132",
    "addr:street":"Barklya Pl",
    "iso:country":"AU",
    "sg:address":"2/ 13 Barklya Pl",
    "sg:city":"Marsden",
    "sg:classifiers":[
        {
            "category":"Health Services",
            "subcategory":"Dentist",
            "type":"Services"
        }
    ],
    "sg:phone":"+61 7 3200 4666",
    "sg:postcode":"4132",
    "sg:province":"QLD",
    "wof:name":"Lanh Vu",
    "wof:placetype":"venue"
},
  "geometry": {"coordinates":[153.11427307100001,-27.6805438995],"type":"Point"}
}