{
  "type": "Feature",
  "properties": {
    "iso:country":"AU",
    "sg:address":"PO Box 801",
    "sg:city":"Brighton",
    "sg:classifiers":[
        {
            "category":"Sports & Exercise",
            "subcategory":"Gym",
            "type":"Entertainment"
        }
    ],
    "sg:phone":"+61 414 806 691",
    "sg:postcode":"5048",
    "sg:province":"SA",
    "sg:tags":[
        "personal",
        "trainer",
        "fitness"
    ],
    "wof:name":"Be The Dream Health & Fitness Consultants",
    "wof:placetype":"venue"
},
  "geometry": {"coordinates":[138.517792,-35.01717],"type":"Point"}
}