{
  "type": "Feature",
  "properties": {
    "addr:full":"172 St Georges Tce Perth WA 6000",
    "addr:housenumber":"172",
    "addr:postcode":"6000",
    "addr:street":"St Georges Tce",
    "iso:country":"AU",
    "sg:address":"172 St",
    "sg:city":"Georges Tce Perth",
    "sg:classifiers":[
        {
            "category":"Travel",
            "subcategory":"Travel Agent",
            "type":"Entertainment"
        }
    ],
    "sg:phone":"+61 13 18 66",
    "sg:postcode":"6000",
    "sg:province":"WA",
    "sg:tags":[
        "consultant"
    ],
    "wof:name":"Flight Centre",
    "wof:placetype":"venue"
},
  "geometry": {"coordinates":[115.85389709499999,-31.9536895752],"type":"Point"}
}