{
  "type": "Feature",
  "properties": {
    "addr:full":"Winton House Winton La Ballina NSW 2478",
    "addr:postcode":"2478",
    "addr:street":"Winton",
    "iso:country":"AU",
    "sg:address":"Winton House Winton La",
    "sg:city":"Ballina",
    "sg:classifiers":[
        {
            "category":"Organizations",
            "subcategory":"Community Association",
            "type":"Services"
        }
    ],
    "sg:phone":"+61 2 6686 4686",
    "sg:postcode":"2478",
    "sg:province":"NSW",
    "sg:tags":[
        "organisation",
        "family",
        "welfare"
    ],
    "wof:name":"Home Care Service Of NSW",
    "wof:placetype":"venue"
},
  "geometry": {"coordinates":[153.554962158,-28.8678798676],"type":"Point"}
}