{
  "type": "Feature",
  "properties": {
    "addr:full":"U1/ 17-19 Orange St Williamstown North VIC 3016",
    "addr:housenumber":"17-19",
    "addr:postcode":"3016",
    "addr:street":"U1 /;Orange St",
    "iso:country":"AU",
    "sg:address":"U1/ 17-19 Orange St",
    "sg:city":"Williamstown North",
    "sg:classifiers":[
        {
            "category":"Education",
            "subcategory":"Special Training",
            "type":"Public Place"
        }
    ],
    "sg:phone":"+61 3 9397 1656",
    "sg:postcode":"3016",
    "sg:province":"VIC",
    "sg:tags":[
        "development"
    ],
    "wof:name":"Atmp Pty Ltd",
    "wof:placetype":"venue"
},
  "geometry": {"coordinates":[144.86521911599999,-37.8530731201],"type":"Point"}
}