{
  "type": "Feature",
  "properties": {
    "addr:full":"Shop 6 Wyndham Village 380 Wyndham Village Shopping Centre Sayers Rd Tarneit VIC 3029",
    "addr:housenumber":"shop 6;380",
    "addr:postcode":"3029",
    "addr:street":"Wyndham Village;Sayers Rd",
    "iso:country":"AU",
    "sg:address":"Shop 6 Wyndham Village 380 Wyndham Village Shopping Centre Sayers Rd",
    "sg:city":"Tarneit",
    "sg:classifiers":[
        {
            "category":"Health Services",
            "subcategory":"Optometrist",
            "type":"Services"
        }
    ],
    "sg:phone":"+61 3 8742 7811",
    "sg:postcode":"3029",
    "sg:province":"VIC",
    "wof:name":"Visioncrest Optometrists",
    "wof:placetype":"venue"
},
  "geometry": {"coordinates":[144.66691599999999,-37.846031],"type":"Point"}
}