{
  "type": "Feature",
  "properties": {
    "addr:full":"Upper Floor,Shop 1 10 Bannister Drv Lake Haven Shopng Cntr Lake Haven NSW 2263",
    "addr:housenumber":"1 10",
    "addr:postcode":"2263",
    "addr:street":"Upper;Bannister Drv Lake;Lake",
    "iso:country":"AU",
    "sg:address":"Upper Floor,Shop 1 10 Bannister Drv",
    "sg:city":"Lake Haven Shopng Cntr Lake Haven",
    "sg:classifiers":[
        {
            "category":"Health Services",
            "subcategory":"Dentist",
            "type":"Services"
        }
    ],
    "sg:phone":"+61 2 4392 9911",
    "sg:postcode":"2263",
    "sg:province":"NSW",
    "wof:name":"Advance Family Dental",
    "wof:placetype":"venue"
},
  "geometry": {"coordinates":[151.500137,-33.243942],"type":"Point"}
}