{
  "type": "Feature",
  "properties": {
    "iso:country":"AU",
    "sg:address":"157 Moray St",
    "sg:city":"South Melbourne",
    "sg:classifiers":[
        {
            "category":"Travel",
            "subcategory":"Hotels & Motels",
            "type":"Entertainment"
        }
    ],
    "sg:phone":"+61 3 9690 4511",
    "sg:postcode":"3205",
    "sg:province":"VIC",
    "sg:tags":[
        "pub"
    ],
    "wof:name":"Bell's Hotel & Brewery",
    "wof:placetype":"venue"
},
  "geometry": {"coordinates":[144.962616,-37.830956],"type":"Point"}
}