{
  "type": "Feature",
  "properties": {
    "addr:full":"5 Friswell Pl Frankston VIC 3199",
    "addr:housenumber":"5",
    "addr:postcode":"3199",
    "addr:street":"Friswell Pl",
    "iso:country":"AU",
    "sg:address":"5 Friswell Pl",
    "sg:city":"Frankston",
    "sg:classifiers":[
        {
            "category":"Health Services",
            "subcategory":"Doctor",
            "type":"Services"
        }
    ],
    "sg:phone":"+61 3 9783 7167",
    "sg:postcode":"3199",
    "sg:province":"VIC",
    "sg:tags":[
        "medical",
        "practitioner"
    ],
    "wof:name":"Stevens Thomas",
    "wof:placetype":"venue"
},
  "geometry": {"coordinates":[145.122024536,-38.154209137],"type":"Point"}
}