{
  "type": "Feature",
  "properties": {
    "iso:country":"AU",
    "sg:address":"8 Malua St",
    "sg:city":"Reservoir",
    "sg:classifiers":[
        {
            "category":"Wholesale",
            "subcategory":"Metals & Minerals",
            "type":"Manufacturing & Wholesale Goods"
        }
    ],
    "sg:phone":"+61 3 9462 5099",
    "sg:postcode":"3073",
    "sg:province":"VIC",
    "sg:tags":[
        "steel",
        "stainless",
        "product",
        "equipment"
    ],
    "wof:name":"Veitch Stainless Steel Products",
    "wof:placetype":"venue"
},
  "geometry": {"coordinates":[144.982147217,-37.7191123962],"type":"Point"}
}