{
  "type": "Feature",
  "properties": {
    "addr:full":"45 Durong Rd Mundubbera QLD 4626",
    "addr:housenumber":"45",
    "addr:postcode":"4626",
    "addr:street":"Durong Rd",
    "iso:country":"AU",
    "sg:address":"45 Durong Rd",
    "sg:city":"Mundubbera",
    "sg:classifiers":[
        {
            "category":"Wholesale",
            "subcategory":"Metals & Minerals",
            "type":"Manufacturing & Wholesale Goods"
        }
    ],
    "sg:phone":"+61 7 4165 4766",
    "sg:postcode":"4626",
    "sg:province":"QLD",
    "sg:tags":[
        "steel",
        "merchant"
    ],
    "wof:name":"R.G. MOBBS & CO. PTY. LTD.",
    "wof:placetype":"venue"
},
  "geometry": {"coordinates":[151.31167600000001,-25.573799],"type":"Point"}
}