{
  "type": "Feature",
  "properties": {
    "addr:full":"PO Box 1194 Milton QLD 4064",
    "addr:postcode":"4064",
    "iso:country":"AU",
    "sg:address":"PO Box 1194",
    "sg:city":"Milton",
    "sg:classifiers":[
        {
            "category":"Professional",
            "subcategory":"Computer Services",
            "type":"Services"
        }
    ],
    "sg:phone":"+61 7 3852 5811",
    "sg:postcode":"4064",
    "sg:province":"QLD",
    "sg:tags":[
        "package",
        "software"
    ],
    "wof:name":"Advantech Software Pty Ltd",
    "wof:placetype":"venue"
},
  "geometry": {"coordinates":[153.0052948,-27.4685897827],"type":"Point"}
}