{
  "type": "Feature",
  "properties": {
    "iso:country":"AU",
    "sg:address":"8/ 3 Dunlop Crt",
    "sg:city":"Bayswater",
    "sg:classifiers":[
        {
            "category":"Government",
            "subcategory":"Department Of Motor Vehicles",
            "type":"Public Place"
        }
    ],
    "sg:phone":"+61 3 9738 1099",
    "sg:postcode":"3153",
    "sg:province":"VIC",
    "sg:tags":[
        "body",
        "supply",
        "trimmer"
    ],
    "wof:name":"B.A.S International",
    "wof:placetype":"venue"
},
  "geometry": {"coordinates":[145.275588989,-37.8391723633],"type":"Point"}
}