{
  "type": "Feature",
  "properties": {
    "addr:full":"108a Mollison St Bendigo VIC 3550",
    "addr:housenumber":"108a",
    "addr:postcode":"3550",
    "addr:street":"Mollison St",
    "iso:country":"AU",
    "sg:address":"108a Mollison St",
    "sg:city":"Bendigo",
    "sg:classifiers":[
        {
            "category":"Professional",
            "subcategory":"Business Services",
            "type":"Services"
        }
    ],
    "sg:phone":"+61 3 5444 5268",
    "sg:postcode":"3550",
    "sg:province":"VIC",
    "sg:tags":[
        "drafting"
    ],
    "wof:name":"Narell Peacock Design",
    "wof:placetype":"venue"
},
  "geometry": {"coordinates":[144.284393311,-36.7620735168],"type":"Point"}
}