{
  "type": "Feature",
  "properties": {
    "iso:country":"AU",
    "sg:address":"3 Bale St",
    "sg:city":"Ascot",
    "sg:classifiers":[
        {
            "category":"Health Services",
            "subcategory":"Doctor",
            "type":"Services"
        }
    ],
    "sg:phone":"+61 7 3262 2126",
    "sg:postcode":"4007",
    "sg:province":"QLD",
    "sg:tags":[
        "medical",
        "practitioner"
    ],
    "wof:name":"Quayle John",
    "wof:placetype":"venue"
},
  "geometry": {"coordinates":[153.05439799999999,-27.43272],"type":"Point"}
}