{
  "type": "Feature",
  "properties": {
    "addr:full":"485 High St Preston VIC 3072",
    "addr:housenumber":"485",
    "addr:postcode":"3072",
    "addr:street":"High St",
    "iso:country":"AU",
    "sg:address":"485 High St",
    "sg:city":"Preston",
    "sg:classifiers":[
        {
            "category":"Fast Food",
            "type":"Food & Drink"
        }
    ],
    "sg:phone":"+61 3 9471 1401",
    "sg:postcode":"3072",
    "sg:province":"VIC",
    "sg:tags":[
        "away",
        "take"
    ],
    "wof:name":"Ottas Fine Seafood",
    "wof:placetype":"venue"
},
  "geometry": {"coordinates":[145.00386047399999,-37.737613678],"type":"Point"}
}