{
  "type": "Feature",
  "properties": {
    "addr:full":"Ackers St Hermit Park QLD 4812",
    "addr:postcode":"4812",
    "addr:street":"Ackers St",
    "iso:country":"AU",
    "sg:address":"Ackers St",
    "sg:city":"Hermit Park",
    "sg:classifiers":[
        {
            "category":"Personal",
            "subcategory":"Beauty Salon",
            "type":"Services"
        }
    ],
    "sg:phone":"+61 7 4771 4954",
    "sg:postcode":"4812",
    "sg:province":"QLD",
    "sg:tags":[
        "hairdresser"
    ],
    "wof:name":"Nathan's Salon",
    "wof:placetype":"venue"
},
  "geometry": {"coordinates":[146.80595400000001,-19.27944],"type":"Point"}
}