{
  "type": "Feature",
  "properties": {
    "addr:full":"198 High St Ashburton VIC 3147",
    "addr:housenumber":"198",
    "addr:postcode":"3147",
    "addr:street":"High St",
    "iso:country":"AU",
    "sg:address":"198 High St",
    "sg:city":"Ashburton",
    "sg:classifiers":[
        {
            "category":"Building & Trades",
            "subcategory":"Construction",
            "type":"Services"
        }
    ],
    "sg:phone":"+61 3 9885 6432",
    "sg:postcode":"3147",
    "sg:province":"VIC",
    "sg:tags":[
        "home",
        "air conditioning"
    ],
    "wof:name":"E & S Trading Co.",
    "wof:placetype":"venue"
},
  "geometry": {"coordinates":[145.07879638700001,-37.8634300232],"type":"Point"}
}