{
  "type": "Feature",
  "properties": {
    "addr:full":"141 Bay Rd Bolton Point NSW 2283",
    "addr:housenumber":"141",
    "addr:postcode":"2283",
    "addr:street":"Bay Rd",
    "iso:country":"AU",
    "sg:address":"141 Bay Rd",
    "sg:city":"Bolton Point",
    "sg:classifiers":[
        {
            "category":"Personal",
            "subcategory":"Massage",
            "type":"Services"
        }
    ],
    "sg:phone":"+61 2 4959 2949",
    "sg:postcode":"2283",
    "sg:province":"NSW",
    "sg:tags":[
        "therapy"
    ],
    "wof:name":"Padgett Lisa",
    "wof:placetype":"venue"
},
  "geometry": {"coordinates":[151.59568786599999,-33.0091590881],"type":"Point"}
}