{
  "type": "Feature",
  "properties": {
    "iso:country":"AU",
    "sg:address":"263 Coward St",
    "sg:city":"Mascot",
    "sg:classifiers":[
        {
            "category":"Retail",
            "subcategory":"Auto Rental",
            "type":"Services"
        }
    ],
    "sg:phone":"+61 1800 670 232",
    "sg:postcode":"2020",
    "sg:province":"NSW",
    "sg:tags":[
        "car",
        "hire",
        "minibus"
    ],
    "wof:name":"Backpacker Campervan Rentals",
    "wof:placetype":"venue"
},
  "geometry": {"coordinates":[151.18309020999999,-33.9237823486],"type":"Point"}
}