{
  "type": "Feature",
  "properties": {
    "iso:country":"AU",
    "sg:address":"PO Box 731",
    "sg:city":"Salisbury",
    "sg:classifiers":[
        {
            "category":"Autos & Motor Vehicles",
            "subcategory":"Boat Sales",
            "type":"Retail Goods"
        }
    ],
    "sg:phone":"+61 8 8280 8040",
    "sg:postcode":"5108",
    "sg:province":"SA",
    "sg:tags":[
        "yacht"
    ],
    "wof:name":"Clayton Marine Pty Ltd",
    "wof:placetype":"venue"
},
  "geometry": {"coordinates":[138.642120361,-34.7604484558],"type":"Point"}
}