{
  "type": "Feature",
  "properties": {
    "addr:full":"122 Newell St Bungalow QLD 4870",
    "addr:housenumber":"122",
    "addr:postcode":"4870",
    "addr:street":"Newell St",
    "iso:country":"AU",
    "sg:address":"122 Newell St",
    "sg:city":"Bungalow",
    "sg:classifiers":[
        {
            "category":"Professional",
            "type":"Services"
        }
    ],
    "sg:phone":"+61 7 4035 3677",
    "sg:postcode":"4870",
    "sg:province":"QLD",
    "sg:tags":[
        "spray",
        "painting"
    ],
    "wof:name":"Nico Nea Paintless Dent Repair",
    "wof:placetype":"venue"
},
  "geometry": {"coordinates":[145.75421142600001,-16.9451122284],"type":"Point"}
}