{
  "type": "Feature",
  "properties": {
    "addr:full":"38 Wright Crt Adelaide SA 5000",
    "addr:housenumber":"38",
    "addr:postcode":"5000",
    "addr:street":"Wright Crt",
    "iso:country":"AU",
    "sg:address":"38 Wright Crt",
    "sg:city":"Adelaide",
    "sg:classifiers":[
        {
            "category":"Retail",
            "subcategory":"Car Wash",
            "type":"Services"
        }
    ],
    "sg:phone":"+61 8 8231 6564",
    "sg:postcode":"5000",
    "sg:province":"SA",
    "sg:tags":[
        "truck",
        "cleaning"
    ],
    "wof:name":"Spotless Professional Automotive Detailers",
    "wof:placetype":"venue"
},
  "geometry": {"coordinates":[138.595626831,-34.9312286377],"type":"Point"}
}