{
  "type": "Feature",
  "properties": {
    "addr:full":"125 Herries St Toowoomba QLD 4350",
    "addr:housenumber":"125",
    "addr:postcode":"4350",
    "addr:street":"Herries St",
    "iso:country":"AU",
    "sg:address":"125 Herries St",
    "sg:city":"Toowoomba",
    "sg:classifiers":[
        {
            "category":"Fast Food",
            "type":"Food & Drink"
        }
    ],
    "sg:phone":"+61 7 4639 2817",
    "sg:postcode":"4350",
    "sg:province":"QLD",
    "sg:tags":[
        "away",
        "take"
    ],
    "wof:name":"NewDeli",
    "wof:placetype":"venue"
},
  "geometry": {"coordinates":[151.93713399999999,-27.562155],"type":"Point"}
}