{
  "type": "Feature",
  "properties": {
    "iso:country":"AU",
    "sg:address":"662 Coleridge Rd",
    "sg:city":"Bateau Bay",
    "sg:classifiers":[
        {
            "category":"Cafe",
            "type":"Food & Drink"
        }
    ],
    "sg:phone":"+61 2 4332 0462",
    "sg:postcode":"2261",
    "sg:province":"NSW",
    "wof:name":"Aspiration Cafe",
    "wof:placetype":"venue"
},
  "geometry": {"coordinates":[151.475555,-33.395088],"type":"Point"}
}