{
  "type": "Feature",
  "properties": {
    "addr:full":"6 Hession Rd Nelson NSW 2765",
    "addr:housenumber":"6",
    "addr:postcode":"2765",
    "addr:street":"Hession Rd",
    "iso:country":"AU",
    "sg:address":"6 Hession Rd",
    "sg:city":"Nelson",
    "sg:classifiers":[
        {
            "category":"Professional",
            "subcategory":"Detective & Security Services",
            "type":"Services"
        }
    ],
    "sg:phone":"+61 2 9679 1045",
    "sg:postcode":"2765",
    "sg:province":"NSW",
    "sg:tags":[
        "inspector",
        "boiler"
    ],
    "wof:name":"Wallis D J",
    "wof:placetype":"venue"
},
  "geometry": {"coordinates":[150.92083740199999,-33.6593437195],"type":"Point"}
}