{
  "type": "Feature",
  "properties": {
    "iso:country":"AU",
    "sg:address":"Fcty2/ 11 Charnfield Crt",
    "sg:city":"Thomastown",
    "sg:classifiers":[
        {
            "category":"Wholesale",
            "subcategory":"Furniture",
            "type":"Manufacturing & Wholesale Goods"
        }
    ],
    "sg:phone":"+61 3 9465 3229",
    "sg:postcode":"3074",
    "sg:province":"VIC",
    "sg:tags":[
        "metal"
    ],
    "wof:name":"Method Metal Furniture",
    "wof:placetype":"venue"
},
  "geometry": {"coordinates":[145.02101135300001,-37.6906356812],"type":"Point"}
}