{
  "type": "Feature",
  "properties": {
    "iso:country":"AU",
    "sg:address":"61 Kilkenny Pde",
    "sg:city":"Berkeley Vale",
    "sg:classifiers":[
        {
            "category":"Retail",
            "subcategory":"Repair Shop",
            "type":"Services"
        }
    ],
    "sg:phone":"+61 412 323 581",
    "sg:postcode":"2261",
    "sg:province":"NSW",
    "sg:tags":[
        "maintenance",
        "pool",
        "swimming"
    ],
    "wof:name":"PoolWerx Corporation",
    "wof:placetype":"venue"
},
  "geometry": {"coordinates":[151.437714,-33.344055],"type":"Point"}
}