{
  "type": "Feature",
  "properties": {
    "addr:full":"Unit 3/ 6 Torrens Ave Cardiff NSW 2285",
    "addr:housenumber":"6",
    "addr:postcode":"2285",
    "addr:street":"Torrens Ave",
    "iso:country":"AU",
    "sg:address":"Unit 3/ 6 Torrens Ave",
    "sg:city":"Cardiff",
    "sg:classifiers":[
        {
            "category":"Professional",
            "type":"Services"
        }
    ],
    "sg:phone":"+61 2 4954 2545",
    "sg:postcode":"2285",
    "sg:province":"NSW",
    "sg:tags":[
        "shop",
        "fitting"
    ],
    "wof:name":"Wilsons Plastering Service",
    "wof:placetype":"venue"
},
  "geometry": {"coordinates":[151.65182495100001,-32.9478378296],"type":"Point"}
}