{
  "type": "Feature",
  "properties": {
    "iso:country":"AU",
    "sg:address":"11 Pulman Pl",
    "sg:city":"Emu Plains",
    "sg:classifiers":[
        {
            "category":"Home & Garden",
            "subcategory":"Carpets & Floor Coverings",
            "type":"Retail Goods"
        }
    ],
    "sg:phone":"+61 2 4728 7444",
    "sg:postcode":"2750",
    "sg:province":"NSW",
    "sg:tags":[
        "mat",
        "matting"
    ],
    "wof:name":"Kenware Products",
    "wof:placetype":"venue"
},
  "geometry": {"coordinates":[150.65745544399999,-33.7464179993],"type":"Point"}
}