{
  "type": "Feature",
  "properties": {
    "addr:full":"2/ 5 Wave St Mermaid Beach QLD 4218",
    "addr:housenumber":"/ 5",
    "addr:postcode":"4218",
    "addr:street":"Wave St",
    "iso:country":"AU",
    "sg:address":"2/ 5 Wave St",
    "sg:city":"Mermaid Beach",
    "sg:classifiers":[
        {
            "category":"Professional",
            "subcategory":"Management & Consulting",
            "type":"Services"
        }
    ],
    "sg:phone":"+61 412 494 626",
    "sg:postcode":"4218",
    "sg:province":"QLD",
    "sg:tags":[
        "consultant",
        "business"
    ],
    "wof:name":"Clark Nicole",
    "wof:placetype":"venue"
},
  "geometry": {"coordinates":[153.44046020499999,-28.0570201874],"type":"Point"}
}