{
  "type": "Feature",
  "properties": {
    "addr:full":"Doust St Boyup Brook WA 6244",
    "addr:postcode":"6244",
    "addr:street":"St",
    "iso:country":"AU",
    "sg:address":"Doust St",
    "sg:city":"Boyup Brook",
    "sg:classifiers":[
        {
            "category":"Professional",
            "type":"Services"
        }
    ],
    "sg:phone":"+61 8 9765 1228",
    "sg:postcode":"6244",
    "sg:province":"WA",
    "sg:tags":[
        "transport"
    ],
    "wof:name":"Mead K & B",
    "wof:placetype":"venue"
},
  "geometry": {"coordinates":[116.385559082,-33.8246078491],"type":"Point"}
}