{
  "type": "Feature",
  "properties": {
    "addr:full":"61 Calder Crs Holder ACT 2611",
    "addr:housenumber":"61",
    "addr:postcode":"2611",
    "addr:street":"Calder Crs",
    "iso:country":"AU",
    "sg:address":"61 Calder Crs",
    "sg:city":"Holder",
    "sg:classifiers":[
        {
            "category":"Manufacturing",
            "subcategory":"Musical Instruments",
            "type":"Manufacturing & Wholesale Goods"
        }
    ],
    "sg:phone":"+61 2 6288 8006",
    "sg:postcode":"2611",
    "sg:province":"ACT",
    "sg:tags":[
        "repair",
        "maker"
    ],
    "wof:name":"McGee Terry",
    "wof:placetype":"venue"
},
  "geometry": {"coordinates":[149.04637145999999,-35.3322486877],"type":"Point"}
}