{
  "type": "Feature",
  "properties": {
    "addr:full":"Lot 800 Stuart Hwy Berrimah NT 0828",
    "addr:postcode":"nt 0828",
    "addr:street":"Stuart Hwy",
    "iso:country":"AU",
    "sg:address":"Lot 800 Stuart Hwy",
    "sg:city":"Berrimah",
    "sg:classifiers":[
        {
            "category":"Professional",
            "subcategory":"Accounting & Tax Preparation",
            "type":"Services"
        }
    ],
    "sg:phone":"+61 8 8984 4070",
    "sg:postcode":"0828",
    "sg:province":"NT",
    "sg:tags":[
        "insulation",
        "wholesaler",
        "material",
        "mfrs"
    ],
    "wof:name":"Bradford Insulation",
    "wof:placetype":"venue"
},
  "geometry": {"coordinates":[130.95050048799999,-12.4440021515],"type":"Point"}
}