{
  "type": "Feature",
  "properties": {
    "addr:full":"7 Bayfield St Rosny TAS 7018",
    "addr:housenumber":"7",
    "addr:postcode":"7018",
    "addr:street":"Bayfield St",
    "iso:country":"AU",
    "sg:address":"7 Bayfield St",
    "sg:city":"Rosny",
    "sg:classifiers":[
        {
            "category":"Health Services",
            "subcategory":"Dentist",
            "type":"Services"
        }
    ],
    "sg:phone":"+61 3 6244 7953",
    "sg:postcode":"7018",
    "sg:province":"TAS",
    "wof:name":"Peters David Dr",
    "wof:placetype":"venue"
},
  "geometry": {"coordinates":[147.37005615199999,-42.866558075],"type":"Point"}
}