{
  "type": "Feature",
  "properties": {
    "iso:country":"AU",
    "sg:address":"Cnr Farrant & Jarvis St & Jarvis St",
    "sg:city":"Stafford Heights",
    "sg:classifiers":[
        {
            "category":"Health Services",
            "subcategory":"Dentist",
            "type":"Services"
        }
    ],
    "sg:phone":"+61 7 3359 6824",
    "sg:postcode":"4053",
    "sg:province":"QLD",
    "wof:name":"Life Dental",
    "wof:placetype":"venue"
},
  "geometry": {"coordinates":[153.009674072,-27.3948402405],"type":"Point"}
}