{
  "type": "Feature",
  "properties": {
    "addr:full":"7 Cavanagh Drv Blacks Beach QLD 4740",
    "addr:housenumber":"7",
    "addr:postcode":"4740",
    "addr:street":"Cavanagh Drv",
    "iso:country":"AU",
    "sg:address":"7 Cavanagh Drv",
    "sg:city":"Blacks Beach",
    "sg:classifiers":[
        {
            "category":"Home & Garden",
            "subcategory":"Building Materials",
            "type":"Retail Goods"
        }
    ],
    "sg:phone":"+61 409 643 605",
    "sg:postcode":"4740",
    "sg:province":"QLD",
    "sg:tags":[
        "retaining",
        "wall"
    ],
    "wof:name":"Salubrious Excavations",
    "wof:placetype":"venue"
},
  "geometry": {"coordinates":[149.18862899999999,-21.053595],"type":"Point"}
}