{
  "type": "Feature",
  "properties": {
    "iso:country":"AU",
    "sg:address":"Unit 26 rear 788 Marion Rd",
    "sg:city":"Marion",
    "sg:classifiers":[
        {
            "category":"Manufacturing",
            "subcategory":"Petroleum Products",
            "type":"Manufacturing & Wholesale Goods"
        }
    ],
    "sg:phone":"+61 8 8377 3322",
    "sg:postcode":"5043",
    "sg:province":"SA",
    "sg:tags":[
        "lubricant"
    ],
    "wof:name":"Torco Oils SA",
    "wof:placetype":"venue"
},
  "geometry": {"coordinates":[138.557266,-34.994862],"type":"Point"}
}