{
  "type": "Feature",
  "properties": {
    "addr:full":"Suite 5 Hampton Park Shopping Square Hampton Park VIC 3976",
    "addr:postcode":"3976",
    "iso:country":"AU",
    "sg:address":"Suite 5 Hampton Park Shopping Square",
    "sg:city":"Hampton Park",
    "sg:classifiers":[
        {
            "category":"Professional",
            "subcategory":"Accounting & Tax Preparation",
            "type":"Services"
        }
    ],
    "sg:phone":"+61 3 9702 8344",
    "sg:postcode":"3976",
    "sg:province":"VIC",
    "sg:tags":[
        "accountant",
        "auditor"
    ],
    "wof:name":"Worcester & Co Pty Ltd",
    "wof:placetype":"venue"
},
  "geometry": {"coordinates":[145.25865173299999,-38.0276908875],"type":"Point"}
}