{
  "type": "Feature",
  "properties": {
    "addr:full":"10 Irvine Crs Frankston VIC 3199",
    "addr:housenumber":"10",
    "addr:postcode":"3199",
    "addr:street":"Irvine Crs",
    "iso:country":"AU",
    "sg:address":"10 Irvine Crs",
    "sg:city":"Frankston",
    "sg:classifiers":[
        {
            "category":"Government",
            "subcategory":"Court House",
            "type":"Public Place"
        }
    ],
    "sg:phone":"+61 412 377 948",
    "sg:postcode":"3199",
    "sg:province":"VIC",
    "sg:tags":[
        "personal",
        "marriage",
        "family",
        "counselling"
    ],
    "wof:name":"Ingrid Glenn - Counselling & Ministry",
    "wof:placetype":"venue"
},
  "geometry": {"coordinates":[145.211593628,-37.820400238],"type":"Point"}
}