{
  "type": "Feature",
  "properties": {
    "addr:full":"33- 35 William St Orange NSW 2800",
    "addr:housenumber":"35",
    "addr:postcode":"2800",
    "addr:street":"William St",
    "iso:country":"AU",
    "sg:address":"33- 35 William St",
    "sg:city":"Orange",
    "sg:classifiers":[
        {
            "category":"Retail",
            "subcategory":"Funeral Services",
            "type":"Services"
        }
    ],
    "sg:phone":"+61 2 6361 7777",
    "sg:postcode":"2800",
    "sg:province":"NSW",
    "sg:tags":[
        "director"
    ],
    "wof:name":"Norman J Penhall Funerals",
    "wof:placetype":"venue"
},
  "geometry": {"coordinates":[149.10568237300001,-33.2834396362],"type":"Point"}
}