{
  "type": "Feature",
  "properties": {
    "iso:country":"AU",
    "sg:address":"77 Parke St",
    "sg:city":"Katoomba",
    "sg:classifiers":[
        {
            "category":"Health Services",
            "subcategory":"Doctor",
            "type":"Services"
        }
    ],
    "sg:phone":"+61 2 4782 3259",
    "sg:postcode":"2780",
    "sg:province":"NSW",
    "sg:tags":[
        "medical",
        "practitioner"
    ],
    "wof:name":"Castlereagh Radiology",
    "wof:placetype":"venue"
},
  "geometry": {"coordinates":[150.309158325,-33.7168922424],"type":"Point"}
}