{
  "type": "Feature",
  "properties": {
    "addr:full":"58 Manchester Rd Mooroolbark VIC 3138",
    "addr:housenumber":"58",
    "addr:postcode":"3138",
    "addr:street":"Manchester Rd",
    "iso:country":"AU",
    "sg:address":"58 Manchester Rd",
    "sg:city":"Mooroolbark",
    "sg:classifiers":[
        {
            "category":"Fast Food",
            "type":"Food & Drink"
        }
    ],
    "sg:phone":"+61 13 11 66",
    "sg:postcode":"3138",
    "sg:province":"VIC",
    "sg:tags":[
        "away",
        "take"
    ],
    "wof:name":"Pizza Hut Delivery",
    "wof:placetype":"venue"
},
  "geometry": {"coordinates":[145.311279297,-37.7850265503],"type":"Point"}
}