{
  "type": "Feature",
  "properties": {
    "iso:country":"AU",
    "sg:address":"228 Elizabeth St",
    "sg:city":"Surry Hills",
    "sg:classifiers":[
        {
            "category":"Health Services",
            "subcategory":"Health Practitioner",
            "type":"Services"
        }
    ],
    "sg:phone":"+61 2 9281 1229",
    "sg:postcode":"2010",
    "sg:province":"NSW",
    "sg:tags":[
        "acupuncture"
    ],
    "wof:name":"Leung Pok",
    "wof:placetype":"venue"
},
  "geometry": {"coordinates":[151.20901489299999,-33.8807258606],"type":"Point"}
}