{
  "type": "Feature",
  "properties": {
    "addr:full":"24/ 354 Tooronga Rd Hawthorn East VIC 3123",
    "addr:housenumber":"24 / 354",
    "addr:postcode":"3123",
    "addr:street":"Tooronga Rd",
    "iso:country":"AU",
    "sg:address":"24/ 354 Tooronga Rd",
    "sg:city":"Hawthorn East",
    "sg:classifiers":[
        {
            "category":"Professional",
            "subcategory":"Management & Consulting",
            "type":"Services"
        }
    ],
    "sg:phone":"+61 3 9821 0847",
    "sg:postcode":"3123",
    "sg:province":"VIC",
    "sg:tags":[
        "consultant",
        "migration"
    ],
    "wof:name":"Wise Migration Services",
    "wof:placetype":"venue"
},
  "geometry": {"coordinates":[145.04481506400001,-37.8472824097],"type":"Point"}
}