{
  "type": "Feature",
  "properties": {
    "iso:country":"AU",
    "sg:address":"34 Duntroon St",
    "sg:city":"Hurlstone Park",
    "sg:classifiers":[
        {
            "category":"Home & Garden",
            "subcategory":"Carpets & Floor Coverings",
            "type":"Retail Goods"
        }
    ],
    "sg:phone":"+61 2 9558 2053",
    "sg:postcode":"2193",
    "sg:province":"NSW",
    "sg:tags":[
        "tile",
        "wall",
        "layer"
    ],
    "wof:name":"Ross-Vince Tiles",
    "wof:placetype":"venue"
},
  "geometry": {"coordinates":[151.133179,-33.906673],"type":"Point"}
}