{
  "type": "Feature",
  "properties": {
    "addr:full":"50 Malcolm St Erskineville NSW 2043",
    "addr:housenumber":"50",
    "addr:postcode":"2043",
    "addr:street":"Malcolm St",
    "iso:country":"AU",
    "sg:address":"50 Malcolm St",
    "sg:city":"Erskineville",
    "sg:classifiers":[
        {
            "category":"Real Estate",
            "subcategory":"Architect",
            "type":"Services"
        }
    ],
    "sg:phone":"+61 2 9519 7474",
    "sg:postcode":"2043",
    "sg:province":"NSW",
    "wof:name":"Identity Design",
    "wof:placetype":"venue"
},
  "geometry": {"coordinates":[151.18644699999999,-33.901623],"type":"Point"}
}