{
  "type": "Feature",
  "properties": {
    "addr:full":"Aprt2/ 338 Military Rd Vaucluse NSW 2030",
    "addr:housenumber":"338",
    "addr:postcode":"2030",
    "addr:street":"Military Rd",
    "iso:country":"AU",
    "sg:address":"Aprt2/ 338 Military Rd",
    "sg:city":"Vaucluse",
    "sg:classifiers":[
        {
            "category":"Professional",
            "subcategory":"Art Services",
            "type":"Services"
        }
    ],
    "sg:phone":"+61 2 9337 1308",
    "sg:postcode":"2030",
    "sg:province":"NSW",
    "sg:tags":[
        "graphic",
        "designer"
    ],
    "wof:name":"Passion Design",
    "wof:placetype":"venue"
},
  "geometry": {"coordinates":[151.28091430699999,-33.8638343811],"type":"Point"}
}