{
  "type": "Feature",
  "properties": {
    "iso:country":"AU",
    "sg:address":"8 Krummel St Mt Gambier",
    "sg:city":"Mt Gambier",
    "sg:classifiers":[
        {
            "category":"Retail",
            "subcategory":"Laundry & Dry Cleaning",
            "type":"Services"
        }
    ],
    "sg:phone":"+61 8 8725 4427",
    "sg:postcode":"5290",
    "sg:province":"SA",
    "wof:name":"The Banque Laundrette",
    "wof:placetype":"venue"
},
  "geometry": {"coordinates":[140.784882,-37.830944],"type":"Point"}
}