{
  "type": "Feature",
  "properties": {
    "iso:country":"AU",
    "sg:address":"21 Econo Pl",
    "sg:city":"Silverdale",
    "sg:classifiers":[
        {
            "category":"Retail",
            "subcategory":"Auto Repair",
            "type":"Services"
        }
    ],
    "sg:phone":"+61 2 4773 8080",
    "sg:postcode":"2752",
    "sg:province":"NSW",
    "sg:tags":[
        "beater",
        "painter",
        "panel"
    ],
    "wof:name":"Silverdale Wallacia Smash Repairs",
    "wof:placetype":"venue"
},
  "geometry": {"coordinates":[150.613082886,-33.8917160034],"type":"Point"}
}