{
  "type": "Feature",
  "properties": {
    "iso:country":"AU",
    "sg:address":"36 Wilterna Crs",
    "sg:city":"Smithfield",
    "sg:classifiers":[
        {
            "category":"Social Services",
            "subcategory":"Job Training",
            "type":"Services"
        }
    ],
    "sg:phone":"+61 8 8287 6690",
    "sg:postcode":"5114",
    "sg:province":"SA",
    "sg:tags":[
        "hire",
        "computer",
        "leasing"
    ],
    "wof:name":"Micro Systems Hire Pty Ltd",
    "wof:placetype":"venue"
},
  "geometry": {"coordinates":[138.69219970699999,-34.6852302551],"type":"Point"}
}