{
  "type": "Feature",
  "properties": {
    "addr:full":"PO Box 310 North Ryde Prvte Boxes NSW 1670",
    "addr:postcode":"1670",
    "iso:country":"AU",
    "sg:address":"PO Box 310",
    "sg:city":"North Ryde Prvte Boxes",
    "sg:classifiers":[
        {
            "category":"Government",
            "subcategory":"Fire Station",
            "type":"Public Place"
        }
    ],
    "sg:phone":"+61 2 9490 5453",
    "sg:postcode":"1670",
    "sg:province":"NSW",
    "sg:tags":[
        "equipment",
        "protection",
        "consultant"
    ],
    "wof:name":"CSIRO-Division Of Manufacturing, Infrastructure & Technology",
    "wof:placetype":"venue"
},
  "geometry": {"coordinates":[151.124343872,-33.7967681885],"type":"Point"}
}