{
  "type": "Feature",
  "properties": {
    "addr:full":"7 Alveston St Acacia Ridge QLD 4110",
    "addr:housenumber":"7",
    "addr:postcode":"4110",
    "addr:street":"Alveston St",
    "iso:country":"AU",
    "sg:address":"7 Alveston St",
    "sg:city":"Acacia Ridge",
    "sg:classifiers":[
        {
            "category":"Building & Trades",
            "subcategory":"Construction",
            "type":"Services"
        }
    ],
    "sg:phone":"+61 7 3275 1408",
    "sg:postcode":"4110",
    "sg:province":"QLD",
    "sg:tags":[
        "earth",
        "excavating",
        "moving",
        "contractor"
    ],
    "wof:name":"D & P Quinn",
    "wof:placetype":"venue"
},
  "geometry": {"coordinates":[153.02903747600001,-27.5778083801],"type":"Point"}
}