{
  "type": "Feature",
  "properties": {
    "addr:full":"Bruce Hwy Cardwell QLD 4849",
    "addr:postcode":"4849",
    "addr:street":"Bruce Hwy",
    "iso:country":"AU",
    "sg:address":"Bruce Hwy",
    "sg:city":"Cardwell",
    "sg:classifiers":[
        {
            "category":"Retail",
            "subcategory":"Auto Repair",
            "type":"Services"
        }
    ],
    "sg:phone":"+61 7 4066 8618",
    "sg:postcode":"4849",
    "sg:province":"QLD",
    "sg:tags":[
        "repairer",
        "motor",
        "engineer"
    ],
    "wof:name":"Cardwell Automotive & Towing Service",
    "wof:placetype":"venue"
},
  "geometry": {"coordinates":[146.01738,-18.256409],"type":"Point"}
}