{
  "type": "Feature",
  "properties": {
    "addr:full":"Level 10, 118 Alfred St Milsons Point NSW 2061",
    "addr:housenumber":"118",
    "addr:postcode":"2061",
    "addr:street":"Alfred St",
    "iso:country":"AU",
    "sg:address":"Level 10, 118 Alfred St",
    "sg:city":"Milsons Point",
    "sg:classifiers":[
        {
            "category":"Professional",
            "subcategory":"Business Services",
            "type":"Services"
        }
    ],
    "sg:phone":"+61 1300 656 541",
    "sg:postcode":"2061",
    "sg:province":"NSW",
    "sg:tags":[
        "record",
        "management",
        "storage"
    ],
    "wof:name":"DigiGuard",
    "wof:placetype":"venue"
},
  "geometry": {"coordinates":[151.210403442,-33.8438682556],"type":"Point"}
}