{
  "type": "Feature",
  "properties": {
    "iso:country":"AU",
    "sg:address":"Shop 1 & 2 Main Rd",
    "sg:city":"Olinda",
    "sg:classifiers":[
        {
            "category":"Shopping",
            "subcategory":"Crafts & Fabrics",
            "type":"Retail Goods"
        }
    ],
    "sg:phone":"+61 3 9751 1814",
    "sg:postcode":"3788",
    "sg:province":"VIC",
    "sg:tags":[
        "merchant",
        "lace"
    ],
    "wof:name":"Lace Shop The",
    "wof:placetype":"venue"
},
  "geometry": {"coordinates":[145.359467,-37.854752],"type":"Point"}
}