{
  "type": "Feature",
  "properties": {
    "addr:full":"Daylesford Railway Station Raglan St Daylesford VIC 3460",
    "addr:postcode":"3460",
    "addr:street":"Raglan St",
    "iso:country":"AU",
    "sg:address":"Daylesford Railway Station Raglan St",
    "sg:city":"Daylesford",
    "sg:classifiers":[
        {
            "category":"Building & Trades",
            "subcategory":"Landscaping Services",
            "type":"Services"
        }
    ],
    "sg:phone":"+61 3 5348 3503",
    "sg:postcode":"3460",
    "sg:province":"VIC",
    "sg:tags":[
        "market"
    ],
    "wof:name":"Daylesford Sunday Market",
    "wof:placetype":"venue"
},
  "geometry": {"coordinates":[144.144287109,-37.3395614624],"type":"Point"}
}