{
  "type": "Feature",
  "properties": {
    "addr:full":"246 Canterbury Rd Bayswater VIC 3153",
    "addr:housenumber":"246",
    "addr:postcode":"3153",
    "addr:street":"Canterbury Rd",
    "iso:country":"AU",
    "sg:address":"246 Canterbury Rd",
    "sg:city":"Bayswater",
    "sg:classifiers":[
        {
            "category":"Retail",
            "subcategory":"Auto Rental",
            "type":"Services"
        }
    ],
    "sg:phone":"+61 3 9738 1000",
    "sg:postcode":"3153",
    "sg:province":"VIC",
    "sg:tags":[
        "car",
        "hire",
        "minibus"
    ],
    "wof:name":"Skygrove Car Sales & Rentals",
    "wof:placetype":"venue"
},
  "geometry": {"coordinates":[145.276519775,-37.8295516968],"type":"Point"}
}