{
  "type": "Feature",
  "properties": {
    "iso:country":"AU",
    "sg:address":"103 Graham St",
    "sg:city":"Wonthaggi",
    "sg:classifiers":[
        {
            "category":"Cafe",
            "type":"Food & Drink"
        }
    ],
    "sg:phone":"+61 3 5672 5871",
    "sg:postcode":"3995",
    "sg:province":"VIC",
    "wof:name":"Picasso's On Graham",
    "wof:placetype":"venue"
},
  "geometry": {"coordinates":[145.59201,-38.606098],"type":"Point"}
}