{
  "type": "Feature",
  "properties": {
    "iso:country":"AU",
    "sg:address":"308 Thomas St",
    "sg:city":"Dandenong",
    "sg:classifiers":[
        {
            "category":"Casinos & Gambling",
            "type":"Entertainment"
        }
    ],
    "sg:phone":"+61 3 9793 2951",
    "sg:postcode":"3175",
    "sg:province":"VIC",
    "sg:tags":[
        "lottery",
        "agent"
    ],
    "wof:name":"Dande Lotto",
    "wof:placetype":"venue"
},
  "geometry": {"coordinates":[145.21258544899999,-37.9852294922],"type":"Point"}
}