{
  "type": "Feature",
  "properties": {
    "addr:full":"Level 28/ 140 St Georges Tce Perth WA 6000",
    "addr:housenumber":"/ 140",
    "addr:postcode":"6000",
    "addr:street":"St Georges Tce",
    "iso:country":"AU",
    "sg:address":"Level 28/ 140 St",
    "sg:city":"Georges Tce Perth",
    "sg:classifiers":[
        {
            "category":"Home & Garden",
            "subcategory":"Household Appliances",
            "type":"Retail Goods"
        }
    ],
    "sg:phone":"+61 8 9278 2467",
    "sg:postcode":"6000",
    "sg:province":"WA",
    "sg:tags":[
        "wholesale",
        "mfrs",
        "air conditioning"
    ],
    "wof:name":"Holyoake Industries (WA)",
    "wof:placetype":"venue"
},
  "geometry": {"coordinates":[115.856391907,-31.954492569],"type":"Point"}
}