{
  "type": "Feature",
  "properties": {
    "addr:full":"8 Reardon St Port Fairy VIC 3284",
    "addr:housenumber":"8",
    "addr:postcode":"3284",
    "addr:street":"Reardon St",
    "iso:country":"AU",
    "sg:address":"8 Reardon St",
    "sg:city":"Port Fairy",
    "sg:classifiers":[
        {
            "category":"Building & Trades",
            "subcategory":"Landscaping Services",
            "type":"Services"
        }
    ],
    "sg:phone":"+61 3 5568 1116",
    "sg:postcode":"3284",
    "sg:province":"VIC",
    "sg:tags":[
        "designer",
        "landscape",
        "contractor"
    ],
    "wof:name":"Mels Bobcat Service",
    "wof:placetype":"venue"
},
  "geometry": {"coordinates":[142.22634887699999,-38.3903694153],"type":"Point"}
}