{
  "type": "Feature",
  "properties": {
    "iso:country":"AU",
    "sg:address":"6/ 7 Narabang Way",
    "sg:city":"Belrose",
    "sg:classifiers":[
        {
            "category":"Professional",
            "subcategory":"Printing & Photocopies",
            "type":"Services"
        }
    ],
    "sg:phone":"+61 2 9986 3727",
    "sg:postcode":"2085",
    "sg:province":"NSW",
    "sg:tags":[
        "photocopying"
    ],
    "wof:name":"Alltype Printing Pty Ltd",
    "wof:placetype":"venue"
},
  "geometry": {"coordinates":[151.212356567,-33.70520401],"type":"Point"}
}