{
  "type": "Feature",
  "properties": {
    "addr:full":"4 Sixth Ave Mt Isa QLD 4825",
    "addr:housenumber":"4",
    "addr:postcode":"4825",
    "addr:street":"Sixth Ave",
    "iso:country":"AU",
    "sg:address":"4 Sixth Ave",
    "sg:city":"Mt Isa",
    "sg:classifiers":[
        {
            "category":"Real Estate",
            "subcategory":"Real Estate Agent",
            "type":"Services"
        }
    ],
    "sg:phone":"+61 7 4743 3108",
    "sg:postcode":"4825",
    "sg:province":"QLD",
    "sg:tags":[
        "handyman's",
        "equipment",
        "hire",
        "builders",
        "contractor"
    ],
    "wof:name":"Norman Grader Hire",
    "wof:placetype":"venue"
},
  "geometry": {"coordinates":[139.48928799999999,-20.735666],"type":"Point"}
}