{
  "type": "Feature",
  "properties": {
    "iso:country":"AU",
    "sg:address":"City Campus, 23 Mundy St",
    "sg:city":"Bendigo",
    "sg:classifiers":[
        {
            "category":"Education",
            "subcategory":"Vocational School",
            "type":"Public Place"
        }
    ],
    "sg:phone":"+61 1300 554 248",
    "sg:postcode":"3550",
    "sg:province":"VIC",
    "sg:tags":[
        "tafe",
        "college",
        "training"
    ],
    "wof:name":"Bendigo Regional Institute Of Tafe",
    "wof:placetype":"venue"
},
  "geometry": {"coordinates":[144.283599853,-36.7578887939],"type":"Point"}
}