{
  "type": "Feature",
  "properties": {
    "addr:full":"PO Box 5128 Lyneham ACT 2602",
    "addr:postcode":"2602",
    "iso:country":"AU",
    "sg:address":"PO Box 5128",
    "sg:city":"Lyneham",
    "sg:classifiers":[
        {
            "category":"Professional",
            "type":"Services"
        }
    ],
    "sg:phone":"+61 2 6257 7966",
    "sg:postcode":"2602",
    "sg:province":"ACT",
    "sg:tags":[
        "shop",
        "fitting"
    ],
    "wof:name":"Complete Constructions Aust Pty Ltd",
    "wof:placetype":"venue"
},
  "geometry": {"coordinates":[149.12710571299999,-35.2443618774],"type":"Point"}
}