{
  "type": "Feature",
  "properties": {
    "addr:full":"Mummery Rd Myrtleford VIC 3737",
    "addr:postcode":"3737",
    "addr:street":"Mummery Rd",
    "iso:country":"AU",
    "sg:address":"Mummery Rd",
    "sg:city":"Myrtleford",
    "sg:classifiers":[
        {
            "category":"Building & Trades",
            "subcategory":"Construction",
            "type":"Services"
        }
    ],
    "sg:phone":"+61 3 5751 1419",
    "sg:postcode":"3737",
    "sg:province":"VIC",
    "sg:tags":[
        "earth",
        "excavating",
        "moving",
        "contractor"
    ],
    "wof:name":"Kings Earthworks Pty Ltd",
    "wof:placetype":"venue"
},
  "geometry": {"coordinates":[146.72967529300001,-36.5505828857],"type":"Point"}
}