{
  "type": "Feature",
  "properties": {
    "iso:country":"AU",
    "sg:address":"17 Powelett St",
    "sg:city":"Sunbury",
    "sg:classifiers":[
        {
            "category":"Banks & Credit Unions",
            "subcategory":"Financial Services",
            "type":"Services"
        }
    ],
    "sg:phone":"+61 3 9740 2443",
    "sg:postcode":"3429",
    "sg:province":"VIC",
    "sg:tags":[
        "advisory",
        "planning",
        "retirement"
    ],
    "wof:name":"Thompson L D & Associates Pty Ltd",
    "wof:placetype":"venue"
},
  "geometry": {"coordinates":[144.74087524399999,-37.5827674866],"type":"Point"}
}