{
  "type": "Feature",
  "properties": {
    "iso:country":"AU",
    "sg:address":"PO Box 553",
    "sg:city":"Round Corner",
    "sg:classifiers":[
        {
            "category":"Building & Trades",
            "subcategory":"Construction",
            "type":"Services"
        }
    ],
    "sg:phone":"+61 2 9651 7550",
    "sg:postcode":"2158",
    "sg:province":"NSW",
    "sg:tags":[
        "concrete",
        "contractor"
    ],
    "wof:name":"Arundale Bros Pty Ltd",
    "wof:placetype":"venue"
},
  "geometry": {"coordinates":[151.01791381800001,-33.695098877],"type":"Point"}
}