{
  "type": "Feature",
  "properties": {
    "iso:country":"AU",
    "sg:address":"1 Riverbank Pde",
    "sg:city":"Gulfview Heights",
    "sg:classifiers":[
        {
            "category":"Building & Trades",
            "subcategory":"Cleaning & Sanitation",
            "type":"Services"
        }
    ],
    "sg:phone":"+61 8 8285 9419",
    "sg:postcode":"5096",
    "sg:province":"SA",
    "sg:tags":[
        "industrial",
        "commercial",
        "contractor"
    ],
    "wof:name":"Assembler Export International Cleaning Service",
    "wof:placetype":"venue"
},
  "geometry": {"coordinates":[138.66908264200001,-34.7986297607],"type":"Point"}
}