{
  "type": "Feature",
  "properties": {
    "iso:country":"AU",
    "sg:address":"35 Old Northern Rd",
    "sg:city":"Baulkham Hills",
    "sg:classifiers":[
        {
            "category":"Professional",
            "subcategory":"Detective & Security Services",
            "type":"Services"
        }
    ],
    "sg:phone":"+61 2 9688 7366",
    "sg:postcode":"2153",
    "sg:province":"NSW",
    "sg:tags":[
        "investigator"
    ],
    "wof:name":"P & L Commercial & Mercantile",
    "wof:placetype":"venue"
},
  "geometry": {"coordinates":[150.99273681599999,-33.7577667236],"type":"Point"}
}