{
  "type": "Feature",
  "properties": {
    "addr:full":"Unit 8/ 46 Camuglia St Garbutt QLD 4814",
    "addr:postcode":"4814",
    "addr:street":"46 Camuglia St",
    "iso:country":"AU",
    "sg:address":"Unit 8/ 46 Camuglia St",
    "sg:city":"Garbutt",
    "sg:classifiers":[
        {
            "category":"Retail",
            "subcategory":"Auto Repair",
            "type":"Services"
        }
    ],
    "sg:phone":"+61 7 4774 4611",
    "sg:postcode":"4814",
    "sg:province":"QLD",
    "sg:tags":[
        "repairer",
        "motor",
        "engineer"
    ],
    "wof:name":"Eric's Auto Transmissions",
    "wof:placetype":"venue"
},
  "geometry": {"coordinates":[146.74859599999999,-19.269346],"type":"Point"}
}