{
  "type": "Feature",
  "properties": {
    "addr:full":"29 Louden Ave Haberfield NSW 2045",
    "addr:housenumber":"29",
    "addr:postcode":"2045",
    "addr:street":"Louden Ave",
    "iso:country":"AU",
    "sg:address":"29 Louden Ave",
    "sg:city":"Haberfield",
    "sg:classifiers":[
        {
            "category":"Personal",
            "subcategory":"Massage",
            "type":"Services"
        }
    ],
    "sg:phone":"+61 411 861 713",
    "sg:postcode":"2045",
    "sg:province":"NSW",
    "sg:tags":[
        "therapy"
    ],
    "wof:name":"Body Sense Naturopathic Clinic",
    "wof:placetype":"venue"
},
  "geometry": {"coordinates":[151.140198,-33.873463],"type":"Point"}
}