{
  "type": "Feature",
  "properties": {
    "addr:full":"27 Hassall St Parramatta NSW 2150",
    "addr:housenumber":"27",
    "addr:postcode":"2150",
    "addr:street":"Hassall St",
    "iso:country":"AU",
    "sg:address":"27 Hassall St",
    "sg:city":"Parramatta",
    "sg:classifiers":[
        {
            "category":"Insurance",
            "subcategory":"Insurance Agent",
            "type":"Services"
        }
    ],
    "sg:phone":"+61 2 9635 4277",
    "sg:postcode":"2150",
    "sg:province":"NSW",
    "sg:tags":[
        "broker"
    ],
    "wof:name":"Action Assessing (Aust)",
    "wof:placetype":"venue"
},
  "geometry": {"coordinates":[150.98832702600001,-33.8102760315],"type":"Point"}
}