{
  "type": "Feature",
  "properties": {
    "addr:full":"18 Bundeena Rd Berkeley Vale NSW 2261",
    "addr:housenumber":"18",
    "addr:postcode":"2261",
    "addr:street":"Bundeena Rd",
    "iso:country":"AU",
    "sg:address":"18 Bundeena Rd",
    "sg:city":"Berkeley Vale",
    "sg:classifiers":[
        {
            "category":"Building & Trades",
            "subcategory":"Cleaning & Sanitation",
            "type":"Services"
        }
    ],
    "sg:phone":"+61 416 018 056",
    "sg:postcode":"2261",
    "sg:province":"NSW",
    "sg:tags":[
        "cleaner",
        "repairer",
        "roof"
    ],
    "wof:name":"All Coast Roofing Pty Ltd",
    "wof:placetype":"venue"
},
  "geometry": {"coordinates":[151.42791700000001,-33.336811],"type":"Point"}
}