{
  "type": "Feature",
  "properties": {
    "addr:full":"24 Hunter Rd Chinchilla QLD 4413",
    "addr:housenumber":"24",
    "addr:postcode":"4413",
    "addr:street":"Hunter Rd",
    "iso:country":"AU",
    "sg:address":"24 Hunter Rd",
    "sg:city":"Chinchilla",
    "sg:classifiers":[
        {
            "category":"Manufacturing",
            "subcategory":"Buildings",
            "type":"Manufacturing & Wholesale Goods"
        }
    ],
    "sg:phone":"+61 7 4668 9182",
    "sg:postcode":"4413",
    "sg:province":"QLD",
    "sg:tags":[
        "transportable",
        "domestic",
        "relocatable"
    ],
    "wof:name":"Chinchilla Westland Transportables & Homes",
    "wof:placetype":"venue"
},
  "geometry": {"coordinates":[150.63063049300001,-26.7399196625],"type":"Point"}
}