{
  "type": "Feature",
  "properties": {
    "iso:country":"AU",
    "sg:address":"18 Vernon Ave",
    "sg:city":"Alphington",
    "sg:classifiers":[
        {
            "category":"Retail",
            "subcategory":"Auto Repair",
            "type":"Services"
        }
    ],
    "sg:phone":"+61 3 9457 7612",
    "sg:postcode":"3078",
    "sg:province":"VIC",
    "sg:tags":[
        "beater",
        "painter",
        "panel"
    ],
    "wof:name":"Automotive Panel Surgeons",
    "wof:placetype":"venue"
},
  "geometry": {"coordinates":[145.02494812,-37.7798194885],"type":"Point"}
}