{
  "type": "Feature",
  "properties": {
    "addr:full":"204 High St Cranbourne VIC 3977",
    "addr:housenumber":"204",
    "addr:postcode":"3977",
    "addr:street":"High St",
    "iso:country":"AU",
    "sg:address":"204 High St",
    "sg:city":"Cranbourne",
    "sg:classifiers":[
        {
            "category":"Retail",
            "subcategory":"Auto Repair",
            "type":"Services"
        }
    ],
    "sg:phone":"+61 3 5996 6666",
    "sg:postcode":"3977",
    "sg:province":"VIC",
    "sg:tags":[
        "repairer",
        "motor",
        "engineer"
    ],
    "wof:name":"Midas",
    "wof:placetype":"venue"
},
  "geometry": {"coordinates":[145.28248596200001,-38.1029701233],"type":"Point"}
}