{
  "type": "Feature",
  "properties": {
    "iso:country":"AU",
    "sg:address":"1 Kathleen St",
    "sg:city":"Rosanna",
    "sg:classifiers":[
        {
            "category":"Personal",
            "subcategory":"Massage",
            "type":"Services"
        }
    ],
    "sg:phone":"+61 3 9459 8420",
    "sg:postcode":"3084",
    "sg:province":"VIC",
    "sg:tags":[
        "therapy"
    ],
    "wof:name":"Rosanna Remedial Masseurs",
    "wof:placetype":"venue"
},
  "geometry": {"coordinates":[145.07223510700001,-37.7478485107],"type":"Point"}
}