{
  "type": "Feature",
  "properties": {
    "addr:full":"PO Box 114 Killarney QLD 4373",
    "addr:postcode":"4373",
    "iso:country":"AU",
    "sg:address":"PO Box 114",
    "sg:city":"Killarney",
    "sg:classifiers":[
        {
            "category":"Arts & Performance",
            "subcategory":"Dance",
            "type":"Entertainment"
        }
    ],
    "sg:phone":"+61 7 4664 1576",
    "sg:postcode":"4373",
    "sg:province":"QLD",
    "sg:tags":[
        "theatrical",
        "ballet",
        "tuition"
    ],
    "wof:name":"Burgess Academy Of Irish Dancing",
    "wof:placetype":"venue"
},
  "geometry": {"coordinates":[152.29348754899999,-28.3397293091],"type":"Point"}
}