{
  "type": "Feature",
  "properties": {
    "iso:country":"AU",
    "sg:address":"Level 3/ 251 Wharf Rd",
    "sg:city":"Newcastle",
    "sg:classifiers":[
        {
            "category":"Professional",
            "subcategory":"Management & Consulting",
            "type":"Services"
        }
    ],
    "sg:phone":"+61 2 4908 7333",
    "sg:postcode":"2300",
    "sg:province":"NSW",
    "sg:tags":[
        "consultant"
    ],
    "wof:name":"NSW ISO Ltd - Hunter Region",
    "wof:placetype":"venue"
},
  "geometry": {"coordinates":[151.778458,-32.925819],"type":"Point"}
}