{
  "type": "Feature",
  "properties": {
    "iso:country":"AU",
    "sg:address":"390 Griffith Rd",
    "sg:city":"Lavington",
    "sg:classifiers":[
        {
            "category":"Building & Trades",
            "subcategory":"Construction",
            "type":"Services"
        }
    ],
    "sg:phone":"+61 418 229 648",
    "sg:postcode":"2641",
    "sg:province":"NSW",
    "sg:tags":[
        "welding"
    ],
    "wof:name":"Steel Fusion",
    "wof:placetype":"venue"
},
  "geometry": {"coordinates":[146.942169189,-36.0444221497],"type":"Point"}
}