{
  "type": "Feature",
  "properties": {
    "iso:country":"AU",
    "sg:address":"16 Giffnock Ave",
    "sg:city":"North Ryde",
    "sg:classifiers":[
        {
            "category":"Communications",
            "type":"Services"
        }
    ],
    "sg:phone":"+61 2 8879 2266",
    "sg:postcode":"2113",
    "sg:province":"NSW",
    "sg:tags":[
        "equipment",
        "radio"
    ],
    "wof:name":"Kenwood Electronics Australia Pty Ltd",
    "wof:placetype":"venue"
},
  "geometry": {"coordinates":[151.12521362300001,-33.784526825],"type":"Point"}
}