{
  "type": "Feature",
  "properties": {
    "iso:country":"AU",
    "sg:address":"327 Pacific Hwy",
    "sg:city":"Lindfield",
    "sg:classifiers":[
        {
            "category":"Shopping",
            "subcategory":"Clothing, Apparel, & Fashions",
            "type":"Retail Goods"
        }
    ],
    "sg:phone":"+61 2 9416 4608",
    "sg:postcode":"2070",
    "sg:province":"NSW",
    "sg:tags":[
        "boutique"
    ],
    "wof:name":"Kassa's Klothes",
    "wof:placetype":"venue"
},
  "geometry": {"coordinates":[151.16894531200001,-33.7760467529],"type":"Point"}
}