{
  "type": "Feature",
  "properties": {
    "addr:full":"14 Benronalds St Seventeen Mile Rocks QLD 4073",
    "addr:housenumber":"14",
    "addr:postcode":"4073",
    "addr:street":"Benronalds St",
    "iso:country":"AU",
    "sg:address":"14 Benronalds St",
    "sg:city":"Seventeen Mile Rocks",
    "sg:classifiers":[
        {
            "category":"Building & Trades",
            "subcategory":"Construction",
            "type":"Services"
        }
    ],
    "sg:phone":"+61 7 3376 2800",
    "sg:postcode":"4073",
    "sg:province":"QLD",
    "sg:tags":[
        "window",
        "aluminium"
    ],
    "sg:website":"http://www.wintecaluminium.com",
    "wof:name":"Streamline Windows",
    "wof:placetype":"venue"
},
  "geometry": {"coordinates":[152.957122803,-27.5400104523],"type":"Point"}
}