{
  "type": "Feature",
  "properties": {
    "iso:country":"AU",
    "sg:address":"Cnr Otranto Ave",
    "sg:city":"& Bulcock Esp Caloundra",
    "sg:classifiers":[
        {
            "category":"Retail",
            "subcategory":"Event Space",
            "type":"Services"
        }
    ],
    "sg:phone":"+61 7 5492 8155",
    "sg:postcode":"4551",
    "sg:province":"QLD",
    "sg:tags":[
        "venue",
        "reception",
        "wedding"
    ],
    "wof:name":"Mooo Char + Bar",
    "wof:placetype":"venue"
},
  "geometry": {"coordinates":[153.13038635300001,-26.8047161102],"type":"Point"}
}