{
  "type": "Feature",
  "properties": {
    "addr:full":"25 Nepean Hwy Mentone VIC 3194",
    "addr:housenumber":"25",
    "addr:postcode":"3194",
    "addr:street":"Nepean Hwy",
    "iso:country":"AU",
    "sg:address":"25 Nepean Hwy",
    "sg:city":"Mentone",
    "sg:classifiers":[
        {
            "category":"Shopping",
            "type":"Retail Goods"
        }
    ],
    "sg:phone":"+61 3 9581 0234",
    "sg:postcode":"3194",
    "sg:province":"VIC",
    "sg:tags":[
        "product",
        "plastic"
    ],
    "wof:name":"Nylex Corporation Ltd",
    "wof:placetype":"venue"
},
  "geometry": {"coordinates":[145.06724548299999,-37.9767494202],"type":"Point"}
}