{
  "type": "Feature",
  "properties": {
    "iso:country":"AU",
    "sg:address":"Queen Victoria Museum Wellington St",
    "sg:city":"Launceston",
    "sg:classifiers":[
        {
            "category":"Education",
            "subcategory":"University",
            "type":"Public Place"
        }
    ],
    "sg:phone":"+61 3 6337 1392",
    "sg:postcode":"7250",
    "sg:province":"TAS",
    "sg:tags":[
        "educational",
        "organisation",
        "cultural"
    ],
    "wof:name":"Oral History Association of Australia (Tas)",
    "wof:placetype":"venue"
},
  "geometry": {"coordinates":[147.13923645,-41.445930481],"type":"Point"}
}