{
  "type": "Feature",
  "properties": {
    "addr:full":"Unit 5/ 55 Coogee Bay Rd Randwick NSW 2031",
    "addr:housenumber":"55",
    "addr:postcode":"2031",
    "addr:street":"Coogee Bay Rd",
    "iso:country":"AU",
    "sg:address":"Unit 5/ 55 Coogee Bay Rd",
    "sg:city":"Randwick",
    "sg:classifiers":[
        {
            "category":"Professional",
            "subcategory":"Detective & Security Services",
            "type":"Services"
        }
    ],
    "sg:phone":"+61 414 964 808",
    "sg:postcode":"2031",
    "sg:province":"NSW",
    "sg:tags":[
        "consultant",
        "system"
    ],
    "wof:name":"Dunphy Technology",
    "wof:placetype":"venue"
},
  "geometry": {"coordinates":[151.246017456,-33.9191665649],"type":"Point"}
}