{
  "type": "Feature",
  "properties": {
    "iso:country":"AU",
    "sg:address":"Shop 3 78 Pacific Hwy",
    "sg:city":"Swansea",
    "sg:classifiers":[
        {
            "category":"Personal",
            "subcategory":"Beauty Salon",
            "type":"Services"
        }
    ],
    "sg:phone":"+61 2 4972 1344",
    "sg:postcode":"2281",
    "sg:province":"NSW",
    "sg:tags":[
        "hairdresser"
    ],
    "wof:name":"Tonys Hair Design",
    "wof:placetype":"venue"
},
  "geometry": {"coordinates":[151.63783264200001,-33.0905990601],"type":"Point"}
}