{
  "type": "Feature",
  "properties": {
    "addr:full":"PO Box 63 Terowie SA 5421",
    "addr:postcode":"5421",
    "iso:country":"AU",
    "sg:address":"PO Box 63",
    "sg:city":"Terowie",
    "sg:classifiers":[
        {
            "category":"Education",
            "subcategory":"School",
            "type":"Public Place"
        }
    ],
    "sg:phone":"+61 8 8659 1080",
    "sg:postcode":"5421",
    "sg:province":"SA",
    "sg:tags":[
        "state",
        "except",
        "nsw"
    ],
    "wof:name":"Terowie Rural School",
    "wof:placetype":"venue"
},
  "geometry": {"coordinates":[138.923065186,-33.1527709961],"type":"Point"}
}