{
  "type": "Feature",
  "properties": {
    "addr:full":"4 View St Mansfield VIC 3722",
    "addr:housenumber":"4",
    "addr:postcode":"3722",
    "addr:street":"View St",
    "iso:country":"AU",
    "sg:address":"4 View St",
    "sg:city":"Mansfield",
    "sg:classifiers":[
        {
            "category":"Building & Trades",
            "subcategory":"Construction",
            "type":"Services"
        }
    ],
    "sg:phone":"+61 3 5779 1191",
    "sg:postcode":"3722",
    "sg:province":"VIC",
    "sg:tags":[
        "joiner",
        "carpenter"
    ],
    "wof:name":"Wall E",
    "wof:placetype":"venue"
},
  "geometry": {"coordinates":[146.08663940400001,-37.0618782043],"type":"Point"}
}