{
  "type": "Feature",
  "properties": {
    "addr:full":"868 Beaufort St Inglewood WA 6052",
    "addr:housenumber":"868",
    "addr:postcode":"6052",
    "addr:street":"Beaufort St",
    "iso:country":"AU",
    "sg:address":"868 Beaufort St",
    "sg:city":"Inglewood",
    "sg:classifiers":[
        {
            "category":"Wholesale",
            "subcategory":"Non-durable Goods",
            "type":"Manufacturing & Wholesale Goods"
        }
    ],
    "sg:phone":"+61 8 9370 2132",
    "sg:postcode":"6052",
    "sg:province":"WA",
    "sg:tags":[
        "wholesaler",
        "craft",
        "mfrs"
    ],
    "wof:name":"Benjamins Crafts",
    "wof:placetype":"venue"
},
  "geometry": {"coordinates":[115.884971619,-31.9223594666],"type":"Point"}
}