{
  "type": "Feature",
  "properties": {
    "iso:country":"AU",
    "sg:address":"Benjamin Drv",
    "sg:city":"Raymond Terrace",
    "sg:classifiers":[
        {
            "category":"Fast Food",
            "type":"Food & Drink"
        }
    ],
    "sg:phone":"+61 2 4987 4147",
    "sg:postcode":"2324",
    "sg:province":"NSW",
    "sg:tags":[
        "away",
        "take"
    ],
    "wof:name":"Lakeside Village Family Takeaway Restaurant",
    "wof:placetype":"venue"
},
  "geometry": {"coordinates":[151.76373290999999,-32.7550582886],"type":"Point"}
}