{
  "type": "Feature",
  "properties": {
    "addr:full":"10 Chilvers Rd Thornleigh NSW 2120",
    "addr:housenumber":"10",
    "addr:postcode":"2120",
    "addr:street":"Chilvers Rd",
    "iso:country":"AU",
    "sg:address":"10 Chilvers Rd",
    "sg:city":"Thornleigh",
    "sg:classifiers":[
        {
            "category":"Utilities",
            "subcategory":"Electric",
            "type":"Services"
        }
    ],
    "sg:phone":"+61 2 9875 5333",
    "sg:postcode":"2120",
    "sg:province":"NSW",
    "sg:tags":[
        "electrical",
        "contractor"
    ],
    "wof:name":"Controltek Services Pty Ltd",
    "wof:placetype":"venue"
},
  "geometry": {"coordinates":[151.081420898,-33.7224998474],"type":"Point"}
}