{
  "type": "Feature",
  "properties": {
    "iso:country":"AU",
    "sg:address":"2 Regent Crt",
    "sg:city":"Wantirna",
    "sg:classifiers":[
        {
            "category":"Shopping",
            "subcategory":"Computers & Home Electronics",
            "type":"Retail Goods"
        }
    ],
    "sg:phone":"+61 3 9887 5000",
    "sg:postcode":"3152",
    "sg:province":"VIC",
    "sg:tags":[
        "hardware",
        "equipment"
    ],
    "wof:name":"Mundaru Computer Services",
    "wof:placetype":"venue"
},
  "geometry": {"coordinates":[145.241363525,-37.8641586304],"type":"Point"}
}