{
  "type": "Feature",
  "properties": {
    "iso:country":"AU",
    "sg:address":"245 Browns Rd",
    "sg:city":"Noble Park",
    "sg:classifiers":[
        {
            "category":"Education",
            "subcategory":"Special Training",
            "type":"Public Place"
        }
    ],
    "sg:phone":"+61 3 9561 9499",
    "sg:postcode":"3174",
    "sg:province":"VIC",
    "sg:tags":[
        "development"
    ],
    "wof:name":"Top Cat Motivation",
    "wof:placetype":"venue"
},
  "geometry": {"coordinates":[145.18055725100001,-37.9530487061],"type":"Point"}
}