{
  "type": "Feature",
  "properties": {
    "addr:full":"305 Trafalgar St Petersham NSW 2049",
    "addr:housenumber":"305",
    "addr:postcode":"2049",
    "addr:street":"Trafalgar St",
    "iso:country":"AU",
    "sg:address":"305 Trafalgar St",
    "sg:city":"Petersham",
    "sg:classifiers":[
        {
            "category":"Home & Garden",
            "subcategory":"Hardware",
            "type":"Retail Goods"
        }
    ],
    "sg:phone":"+61 2 9560 2599",
    "sg:postcode":"2049",
    "sg:province":"NSW",
    "sg:tags":[
        "manufacturer"
    ],
    "wof:name":"McCallum & Co Pty Ltd",
    "wof:placetype":"venue"
},
  "geometry": {"coordinates":[151.15481600000001,-33.894588],"type":"Point"}
}