{
  "type": "Feature",
  "properties": {
    "addr:full":"66 Lynette Ave Warrandyte VIC 3113",
    "addr:housenumber":"66",
    "addr:postcode":"3113",
    "addr:street":"Lynette Ave",
    "iso:country":"AU",
    "sg:address":"66 Lynette Ave",
    "sg:city":"Warrandyte",
    "sg:classifiers":[
        {
            "category":"Building & Trades",
            "subcategory":"Construction",
            "type":"Services"
        }
    ],
    "sg:phone":"+61 3 9844 1359",
    "sg:postcode":"3113",
    "sg:province":"VIC",
    "sg:tags":[
        "renovation",
        "alterations",
        "extension",
        "contractor"
    ],
    "wof:name":"Tradan Constructions",
    "wof:placetype":"venue"
},
  "geometry": {"coordinates":[145.20205688499999,-37.7442474365],"type":"Point"}
}