{
  "type": "Feature",
  "properties": {
    "addr:full":"68c South Pde Blackburn VIC 3130",
    "addr:housenumber":"68c",
    "addr:postcode":"3130",
    "addr:street":"South Pde",
    "iso:country":"AU",
    "sg:address":"68c South Pde",
    "sg:city":"Blackburn",
    "sg:classifiers":[
        {
            "category":"Professional",
            "subcategory":"Art Services",
            "type":"Services"
        }
    ],
    "sg:phone":"+61 3 9894 7770",
    "sg:postcode":"3130",
    "sg:province":"VIC",
    "sg:tags":[
        "picture",
        "frame",
        "framing"
    ],
    "wof:name":"P K Picture Framing",
    "wof:placetype":"venue"
},
  "geometry": {"coordinates":[145.149902344,-37.8206634521],"type":"Point"}
}