{
  "type": "Feature",
  "properties": {
    "addr:full":"22 Delaware Rd Ermington NSW 2115",
    "addr:housenumber":"22",
    "addr:postcode":"2115",
    "addr:street":"Delaware Rd",
    "iso:country":"AU",
    "sg:address":"22 Delaware Rd",
    "sg:city":"Ermington",
    "sg:classifiers":[
        {
            "category":"Autos & Motor Vehicles",
            "subcategory":"Boat Sales",
            "type":"Retail Goods"
        }
    ],
    "sg:phone":"+61 2 9858 1430",
    "sg:postcode":"2115",
    "sg:province":"NSW",
    "sg:tags":[
        "equipment",
        "yacht"
    ],
    "wof:name":"Dinghy Trolley Company",
    "wof:placetype":"venue"
},
  "geometry": {"coordinates":[151.059204102,-33.8028640747],"type":"Point"}
}