{
  "type": "Feature",
  "properties": {
    "addr:full":"8 Grevillea Ave Roleystone WA 6111",
    "addr:housenumber":"8",
    "addr:postcode":"6111",
    "addr:street":"Grevillea Ave",
    "iso:country":"AU",
    "sg:address":"8 Grevillea Ave",
    "sg:city":"Roleystone",
    "sg:classifiers":[
        {
            "category":"Building & Trades",
            "subcategory":"Construction",
            "type":"Services"
        }
    ],
    "sg:phone":"+61 413 096 498",
    "sg:postcode":"6111",
    "sg:province":"WA",
    "sg:tags":[
        "joiner",
        "carpenter"
    ],
    "wof:name":"Stewart Warne Carpentry Services",
    "wof:placetype":"venue"
},
  "geometry": {"coordinates":[116.082717895,-32.1193351746],"type":"Point"}
}