{
  "type": "Feature",
  "properties": {
    "addr:full":"1/ 7 Melissa Pl Kings Park NSW 2148",
    "addr:housenumber":"/ 7",
    "addr:postcode":"2148",
    "addr:street":"Pl",
    "iso:country":"AU",
    "sg:address":"1/ 7 Melissa Pl",
    "sg:city":"Kings Park",
    "sg:classifiers":[
        {
            "category":"Building & Trades",
            "subcategory":"Construction",
            "type":"Services"
        }
    ],
    "sg:phone":"+61 2 9672 8222",
    "sg:postcode":"2148",
    "sg:province":"NSW",
    "sg:tags":[
        "concrete",
        "treatment",
        "repair"
    ],
    "wof:name":"Sherrys Industrial Coatings Pty Ltd",
    "wof:placetype":"venue"
},
  "geometry": {"coordinates":[150.908691406,-33.747177124],"type":"Point"}
}