{
  "type": "Feature",
  "properties": {
    "iso:country":"AU",
    "sg:address":"39 Kate St",
    "sg:city":"Indooroopilly",
    "sg:classifiers":[
        {
            "category":"Professional",
            "subcategory":"Art Services",
            "type":"Services"
        }
    ],
    "sg:phone":"+61 7 3378 6130",
    "sg:postcode":"4068",
    "sg:province":"QLD",
    "wof:name":"Affordable Aboriginal Arts",
    "wof:placetype":"venue"
},
  "geometry": {"coordinates":[152.964599609,-27.5066547394],"type":"Point"}
}