{
  "type": "Feature",
  "properties": {
    "addr:full":"Lot 4 Stirling Crescent Hazelmere WA 6055",
    "addr:housenumber":"4",
    "addr:postcode":"6055",
    "addr:street":"Stirling Crescent",
    "iso:country":"AU",
    "sg:address":"Lot 4 Stirling Crescent",
    "sg:city":"Hazelmere",
    "sg:classifiers":[
        {
            "category":"Professional",
            "type":"Services"
        }
    ],
    "sg:phone":"+61 8 9442 2333",
    "sg:postcode":"6055",
    "sg:province":"WA",
    "sg:tags":[
        "transport"
    ],
    "wof:name":"BGC Transport",
    "wof:placetype":"venue"
},
  "geometry": {"coordinates":[116.009041,-31.912975],"type":"Point"}
}