{
  "type": "Feature",
  "properties": {
    "addr:full":"Unit 1/ 13 Lodge La Harbord NSW 2096",
    "addr:housenumber":"13",
    "addr:postcode":"2096",
    "addr:street":"Lodge La Harbord",
    "iso:country":"AU",
    "sg:address":"Unit 1/ 13 Lodge La",
    "sg:city":"Harbord",
    "sg:classifiers":[
        {
            "category":"Personal",
            "type":"Services"
        }
    ],
    "sg:phone":"+61 2 9907 2253",
    "sg:postcode":"2096",
    "sg:province":"NSW",
    "sg:tags":[
        "career",
        "counselling"
    ],
    "wof:name":"Amos Consulting",
    "wof:placetype":"venue"
},
  "geometry": {"coordinates":[151.28416442899999,-33.7750587463],"type":"Point"}
}