{
  "type": "Feature",
  "properties": {
    "addr:full":"2 Milford St Randwick NSW 2031",
    "addr:housenumber":"2",
    "addr:postcode":"2031",
    "addr:street":"Milford St",
    "iso:country":"AU",
    "sg:address":"2 Milford St",
    "sg:city":"Randwick",
    "sg:classifiers":[
        {
            "category":"Health Services",
            "subcategory":"Nursing And Care Facility",
            "type":"Services"
        }
    ],
    "sg:phone":"+61 2 9398 3659",
    "sg:postcode":"2031",
    "sg:province":"NSW",
    "sg:tags":[
        "home"
    ],
    "wof:name":"Milford House Nursing Home",
    "wof:placetype":"venue"
},
  "geometry": {"coordinates":[151.24180602999999,-33.9151077271],"type":"Point"}
}