{
  "type": "Feature",
  "properties": {
    "addr:full":"RMB 1832 McBain Rd Tongala VIC 3621",
    "addr:postcode":"3621",
    "addr:street":"Mcbain Rd",
    "iso:country":"AU",
    "sg:address":"RMB 1832 McBain Rd",
    "sg:city":"Tongala",
    "sg:classifiers":[
        {
            "category":"Farming",
            "subcategory":"Farm",
            "type":"Manufacturing & Wholesale Goods"
        }
    ],
    "sg:phone":"+61 3 5859 1443",
    "sg:postcode":"3621",
    "sg:province":"VIC",
    "sg:tags":[
        "farmer"
    ],
    "wof:name":"C D & A N Cox",
    "wof:placetype":"venue"
},
  "geometry": {"coordinates":[144.92729187,-36.2253303528],"type":"Point"}
}