{
  "type": "Feature",
  "properties": {
    "addr:full":"10/81- 83 Cantebury Rd Kilsyth VIC 3137",
    "addr:housenumber":"10 / 81 83",
    "addr:postcode":"3137",
    "addr:street":"Cantebury Rd",
    "iso:country":"AU",
    "sg:address":"10/81- 83 Cantebury Rd",
    "sg:city":"Kilsyth",
    "sg:classifiers":[
        {
            "category":"Home & Garden",
            "subcategory":"Building Materials",
            "type":"Retail Goods"
        }
    ],
    "sg:phone":"+61 3 9728 2144",
    "sg:postcode":"3137",
    "sg:province":"VIC",
    "sg:tags":[
        "wall",
        "frame",
        "truss",
        "roof"
    ],
    "wof:name":"Apex Wall & Truss",
    "wof:placetype":"venue"
},
  "geometry": {"coordinates":[145.323120117,-37.8162651062],"type":"Point"}
}