{
  "type": "Feature",
  "properties": {
    "addr:full":"176 Gordon St Port Macquarie NSW 2444",
    "addr:housenumber":"176",
    "addr:postcode":"2444",
    "addr:street":"Gordon St",
    "iso:country":"AU",
    "sg:address":"176 Gordon St",
    "sg:city":"Port Macquarie",
    "sg:classifiers":[
        {
            "category":"Autos & Motor Vehicles",
            "subcategory":"Auto Supplies",
            "type":"Retail Goods"
        }
    ],
    "sg:phone":"+61 2 6584 5799",
    "sg:postcode":"2444",
    "sg:province":"NSW",
    "sg:tags":[
        "camper-trailers",
        "caravan",
        "equipment"
    ],
    "wof:name":"Caramart",
    "wof:placetype":"venue"
},
  "geometry": {"coordinates":[152.898865,-31.435062],"type":"Point"}
}