{
  "type": "Feature",
  "properties": {
    "iso:country":"AU",
    "sg:address":"4385 South Gippsland Hwy Caldermeade",
    "sg:city":"Caldermeade",
    "sg:classifiers":[
        {
            "category":"Restaurant",
            "type":"Food & Drink"
        }
    ],
    "sg:phone":"+61 3 5997 5000",
    "sg:postcode":"3984",
    "sg:province":"VIC",
    "wof:name":"Caldermeade Farm & Cafe",
    "wof:placetype":"venue"
},
  "geometry": {"coordinates":[145.533126831,-38.2436218262],"type":"Point"}
}