{
  "type": "Feature",
  "properties": {
    "addr:full":"39 Greenwith Rd Golden Grove SA 5125",
    "addr:housenumber":"39",
    "addr:postcode":"5125",
    "addr:street":"Greenwith Rd",
    "iso:country":"AU",
    "sg:address":"39 Greenwith Rd",
    "sg:city":"Golden Grove",
    "sg:classifiers":[
        {
            "category":"Retail",
            "subcategory":"Storage",
            "type":"Services"
        }
    ],
    "sg:phone":"+61 8 7221 2339",
    "sg:postcode":"5125",
    "sg:province":"SA",
    "wof:name":"Storage Adelaide",
    "wof:placetype":"venue"
},
  "geometry": {"coordinates":[138.72245799999999,-34.784519],"type":"Point"}
}