{
  "type": "Feature",
  "properties": {
    "iso:country":"AU",
    "sg:address":"Level 1, 188 Oxford St",
    "sg:city":"Paddington",
    "sg:classifiers":[
        {
            "category":"Organizations",
            "subcategory":"Community Association",
            "type":"Services"
        }
    ],
    "sg:phone":"+61 1800 819 633",
    "sg:postcode":"2021",
    "sg:province":"NSW",
    "sg:tags":[
        "organisation",
        "family",
        "welfare"
    ],
    "wof:name":"Benevolent Society, The",
    "wof:placetype":"venue"
},
  "geometry": {"coordinates":[151.22439575199999,-33.8844985962],"type":"Point"}
}