{
  "type": "Feature",
  "properties": {
    "iso:country":"AU",
    "sg:address":"Sippy Creek Rd",
    "sg:city":"Tanawha",
    "sg:classifiers":[
        {
            "category":"Building & Trades",
            "subcategory":"Cleaning & Sanitation",
            "type":"Services"
        }
    ],
    "sg:phone":"+61 1800 812 156",
    "sg:postcode":"4556",
    "sg:province":"QLD",
    "sg:tags":[
        "grease",
        "trap"
    ],
    "wof:name":"Cleanaway",
    "wof:placetype":"venue"
},
  "geometry": {"coordinates":[153.04258727999999,-26.7218494415],"type":"Point"}
}