{
  "type": "Feature",
  "properties": {
    "iso:country":"AU",
    "sg:address":"154 Hutt St",
    "sg:city":"Adelaide",
    "sg:classifiers":[
        {
            "category":"Health Services",
            "subcategory":"Doctor",
            "type":"Services"
        }
    ],
    "sg:phone":"+61 8 8223 7242",
    "sg:postcode":"5000",
    "sg:province":"SA",
    "sg:tags":[
        "medical",
        "practitioner"
    ],
    "wof:name":"Peters Brian Dr",
    "wof:placetype":"venue"
},
  "geometry": {"coordinates":[138.61248779300001,-34.9305992126],"type":"Point"}
}