{
  "type": "Feature",
  "properties": {
    "addr:full":"Cnr Park Ridge and Beaudesert Rds Park Ridge QLD 4125",
    "addr:postcode":"4125",
    "iso:country":"AU",
    "sg:address":"Cnr Park Ridge and Beaudesert Rds",
    "sg:city":"Park Ridge",
    "sg:classifiers":[
        {
            "category":"Health Services",
            "subcategory":"Dentist",
            "type":"Services"
        }
    ],
    "sg:phone":"+61 7 3297 0153",
    "sg:postcode":"4125",
    "sg:province":"QLD",
    "wof:name":"Lazorka Jakub",
    "wof:placetype":"venue"
},
  "geometry": {"coordinates":[153.06153869600001,-27.7039222717],"type":"Point"}
}