{
  "type": "Feature",
  "properties": {
    "iso:country":"AU",
    "sg:address":"28 Tolga Rd",
    "sg:city":"Atherton",
    "sg:classifiers":[
        {
            "category":"Autos & Motor Vehicles",
            "subcategory":"Automobile Sales",
            "type":"Retail Goods"
        }
    ],
    "sg:phone":"+61 7 4030 5555",
    "sg:postcode":"4883",
    "sg:province":"QLD",
    "sg:tags":[
        "car",
        "new"
    ],
    "wof:name":"Toyota Dealers of North Queensland",
    "wof:placetype":"venue"
},
  "geometry": {"coordinates":[145.47622680699999,-17.2582778931],"type":"Point"}
}