{
  "type": "Feature",
  "properties": {
    "addr:full":"29 Bevan Pl Carlingford NSW 2118",
    "addr:housenumber":"29",
    "addr:postcode":"2118",
    "addr:street":"Bevan Pl",
    "iso:country":"AU",
    "sg:address":"29 Bevan Pl",
    "sg:city":"Carlingford",
    "sg:classifiers":[
        {
            "category":"Building & Trades",
            "subcategory":"Construction",
            "type":"Services"
        }
    ],
    "sg:phone":"+61 2 9873 1182",
    "sg:postcode":"2118",
    "sg:province":"NSW",
    "sg:tags":[
        "pool",
        "swimming"
    ],
    "wof:name":"Freestyle Pools",
    "wof:placetype":"venue"
},
  "geometry": {"coordinates":[151.050537109,-33.7729148865],"type":"Point"}
}