{
  "type": "Feature",
  "properties": {
    "addr:full":"PO Box 821 Littlehampton SA 5250",
    "addr:postcode":"5250",
    "iso:country":"AU",
    "sg:address":"PO Box 821",
    "sg:city":"Littlehampton",
    "sg:classifiers":[
        {
            "category":"Sports & Exercise",
            "subcategory":"Gym",
            "type":"Entertainment"
        }
    ],
    "sg:phone":"+61 417 844 842",
    "sg:postcode":"5250",
    "sg:province":"SA",
    "sg:tags":[
        "personal",
        "trainer",
        "fitness"
    ],
    "wof:name":"Fizz Mobile Fitness",
    "wof:placetype":"venue"
},
  "geometry": {"coordinates":[138.853713989,-35.0545082092],"type":"Point"}
}