{
  "type": "Feature",
  "properties": {
    "addr:full":"9 Chesterman St Moonah TAS 7009",
    "addr:housenumber":"9",
    "addr:postcode":"7009",
    "addr:street":"Chesterman St",
    "iso:country":"AU",
    "sg:address":"9 Chesterman St",
    "sg:city":"Moonah",
    "sg:classifiers":[
        {
            "category":"Shopping",
            "subcategory":"Stationery & Office Supplies",
            "type":"Retail Goods"
        }
    ],
    "sg:phone":"+61 3 6272 3088",
    "sg:postcode":"7009",
    "sg:province":"TAS",
    "sg:tags":[
        "screen",
        "printing"
    ],
    "wof:name":"Marsden Bros",
    "wof:placetype":"venue"
},
  "geometry": {"coordinates":[147.29551696799999,-42.8395195007],"type":"Point"}
}