{
  "type": "Feature",
  "properties": {
    "addr:full":"27 Summerlea Rd Mt Dandenong VIC 3767",
    "addr:housenumber":"27",
    "addr:postcode":"3767",
    "addr:street":"Summerlea Rd",
    "iso:country":"AU",
    "sg:address":"27 Summerlea Rd",
    "sg:city":"Mt Dandenong",
    "sg:classifiers":[
        {
            "category":"Utilities",
            "subcategory":"Natural Gas",
            "type":"Services"
        }
    ],
    "sg:phone":"+61 3 9751 0150",
    "sg:postcode":"3767",
    "sg:province":"VIC",
    "sg:tags":[
        "consultant",
        "resource"
    ],
    "wof:name":"Aquatic Systems Management Pty Ltd",
    "wof:placetype":"venue"
},
  "geometry": {"coordinates":[145.35757446299999,-37.8428382874],"type":"Point"}
}