{
  "type": "Feature",
  "properties": {
    "iso:country":"AU",
    "sg:address":"3/ 15 Packard St",
    "sg:city":"North Plympton",
    "sg:classifiers":[
        {
            "category":"Manufacturing",
            "subcategory":"Apparel",
            "type":"Manufacturing & Wholesale Goods"
        }
    ],
    "sg:phone":"+61 8 8297 9240",
    "sg:postcode":"5037",
    "sg:province":"SA",
    "sg:tags":[
        "wholesaler",
        "mfrs",
        "footwear"
    ],
    "wof:name":"Boutique Identi",
    "wof:placetype":"venue"
},
  "geometry": {"coordinates":[138.55778503400001,-34.9503898621],"type":"Point"}
}