{
  "type": "Feature",
  "properties": {
    "addr:full":"172 Springfield Ave Moonah TAS 7009",
    "addr:housenumber":"172",
    "addr:postcode":"7009",
    "addr:street":"Springfield Ave",
    "iso:country":"AU",
    "sg:address":"172 Springfield Ave",
    "sg:city":"Moonah",
    "sg:classifiers":[
        {
            "category":"Health Services",
            "subcategory":"Health Practitioner",
            "type":"Services"
        }
    ],
    "sg:phone":"+61 3 6273 8203",
    "sg:postcode":"7009",
    "sg:province":"TAS",
    "sg:tags":[
        "acupuncture"
    ],
    "wof:name":"He Qing Hua",
    "wof:placetype":"venue"
},
  "geometry": {"coordinates":[147.282440186,-42.853302002],"type":"Point"}
}