{
  "type": "Feature",
  "properties": {
    "addr:full":"58 Railway Pde Granville NSW 2142",
    "addr:housenumber":"58",
    "addr:postcode":"2142",
    "addr:street":"Railway Pde",
    "iso:country":"AU",
    "sg:address":"58 Railway Pde",
    "sg:city":"Granville",
    "sg:classifiers":[
        {
            "category":"Health Services",
            "subcategory":"Doctor",
            "type":"Services"
        }
    ],
    "sg:phone":"+61 2 9637 7322",
    "sg:postcode":"2142",
    "sg:province":"NSW",
    "sg:tags":[
        "medical",
        "practitioner"
    ],
    "wof:name":"Granville Bridge Medical Centre",
    "wof:placetype":"venue"
},
  "geometry": {"coordinates":[151.00878906200001,-33.8314781189],"type":"Point"}
}