{
  "type": "Feature",
  "properties": {
    "iso:country":"AU",
    "sg:address":"31 Hollywood Ave",
    "sg:city":"Ulladulla",
    "sg:classifiers":[
        {
            "category":"Social Services",
            "subcategory":"Child Care",
            "type":"Services"
        }
    ],
    "sg:phone":"+61 2 4455 1006",
    "sg:postcode":"2539",
    "sg:province":"NSW",
    "wof:name":"Ulladulla Childrens Centre",
    "wof:placetype":"venue"
},
  "geometry": {"coordinates":[150.47532653799999,-35.3656692505],"type":"Point"}
}