{
  "type": "Feature",
  "properties": {
    "addr:full":"18b Goggs St Toowoomba QLD 4350",
    "addr:housenumber":"18b",
    "addr:postcode":"4350",
    "addr:street":"Goggs St",
    "iso:country":"AU",
    "sg:address":"18b Goggs St",
    "sg:city":"Toowoomba",
    "sg:classifiers":[
        {
            "category":"Professional",
            "subcategory":"Detective & Security Services",
            "type":"Services"
        }
    ],
    "sg:phone":"+61 7 4632 4931",
    "sg:postcode":"4350",
    "sg:province":"QLD",
    "sg:tags":[
        "protective",
        "rustproofing"
    ],
    "wof:name":"Toowoomba Car Detailers",
    "wof:placetype":"venue"
},
  "geometry": {"coordinates":[151.94528199999999,-27.566341],"type":"Point"}
}