{
  "type": "Feature",
  "properties": {
    "iso:country":"AU",
    "sg:address":"60 Waverley St",
    "sg:city":"Moonee Ponds",
    "sg:classifiers":[
        {
            "category":"Real Estate",
            "subcategory":"Architect",
            "type":"Services"
        }
    ],
    "sg:phone":"+61 3 9331 3011",
    "sg:postcode":"3039",
    "sg:province":"VIC",
    "wof:name":"Edgerton Derek R & Associates",
    "wof:placetype":"venue"
},
  "geometry": {"coordinates":[144.906204,-37.760712],"type":"Point"}
}