{
  "type": "Feature",
  "properties": {
    "addr:full":"176/ 178 Aumuller St Cairns QLD 4870",
    "addr:housenumber":"176 / 178",
    "addr:postcode":"4870",
    "addr:street":"Aumuller St",
    "iso:country":"AU",
    "sg:address":"176/ 178 Aumuller St",
    "sg:city":"Cairns",
    "sg:classifiers":[
        {
            "category":"Building & Trades",
            "subcategory":"Construction",
            "type":"Services"
        }
    ],
    "sg:phone":"+61 7 4031 1277",
    "sg:postcode":"4870",
    "sg:province":"QLD",
    "sg:tags":[
        "ceiling"
    ],
    "wof:name":"Plastamasta Centre",
    "wof:placetype":"venue"
},
  "geometry": {"coordinates":[145.76028442399999,-16.9323863983],"type":"Point"}
}