{
  "type": "Feature",
  "properties": {
    "addr:full":"53b Woodville Rd Woodville SA 5011",
    "addr:housenumber":"53b",
    "addr:postcode":"5011",
    "addr:street":"Woodville Rd",
    "iso:country":"AU",
    "sg:address":"53b Woodville Rd",
    "sg:city":"Woodville",
    "sg:classifiers":[
        {
            "category":"Health Services",
            "subcategory":"Dentist",
            "type":"Services"
        }
    ],
    "sg:phone":"+61 8 8244 4020",
    "sg:postcode":"5011",
    "sg:province":"SA",
    "sg:tags":[
        "dental",
        "prosthetist"
    ],
    "wof:name":"Howard Weber Denture Clinic",
    "wof:placetype":"venue"
},
  "geometry": {"coordinates":[138.536621094,-34.8790054321],"type":"Point"}
}