{
  "type": "Feature",
  "properties": {
    "iso:country":"AU",
    "sg:address":"Gateway Centre 86 Willandra Ave",
    "sg:city":"Griffith",
    "sg:classifiers":[
        {
            "category":"Home & Garden",
            "subcategory":"Furniture",
            "type":"Retail Goods"
        }
    ],
    "sg:phone":"+61 2 6962 5510",
    "sg:postcode":"2680",
    "sg:province":"NSW",
    "sg:tags":[
        "outdoor"
    ],
    "wof:name":"Barbeques Galore (Griffith)",
    "wof:placetype":"venue"
},
  "geometry": {"coordinates":[146.043182,-34.295002],"type":"Point"}
}