{
  "type": "Feature",
  "properties": {
    "addr:full":"9 Foamcrest Ave Newport NSW 2106",
    "addr:housenumber":"9",
    "addr:postcode":"2106",
    "addr:street":"Foamcrest Ave",
    "iso:country":"AU",
    "sg:address":"9 Foamcrest Ave",
    "sg:city":"Newport",
    "sg:classifiers":[
        {
            "category":"Health Services",
            "subcategory":"Doctor",
            "type":"Services"
        }
    ],
    "sg:phone":"+61 2 9997 8731",
    "sg:postcode":"2106",
    "sg:province":"NSW",
    "sg:tags":[
        "medical",
        "practitioner"
    ],
    "wof:name":"Newton Beverley M",
    "wof:placetype":"venue"
},
  "geometry": {"coordinates":[151.318527222,-33.6553268433],"type":"Point"}
}