{
  "type": "Feature",
  "properties": {
    "addr:full":"410a Bell St Pascoe Vale South VIC 3044",
    "addr:housenumber":"410a",
    "addr:postcode":"3044",
    "addr:street":"Bell St",
    "iso:country":"AU",
    "sg:address":"410a Bell St",
    "sg:city":"Pascoe Vale South",
    "sg:classifiers":[
        {
            "category":"Personal",
            "subcategory":"Massage",
            "type":"Services"
        }
    ],
    "sg:phone":"+61 416 273 452",
    "sg:postcode":"3044",
    "sg:province":"VIC",
    "sg:tags":[
        "therapy"
    ],
    "wof:name":"Bella Donna Massage & Beauty",
    "wof:placetype":"venue"
},
  "geometry": {"coordinates":[144.94427490199999,-37.7388763428],"type":"Point"}
}