{
  "type": "Feature",
  "properties": {
    "addr:full":"Shp2/ 2 Piggot & Bellmere Rd Bellmere QLD 4510",
    "addr:postcode":"4510",
    "addr:street":"Bellmere Rd",
    "iso:country":"AU",
    "sg:address":"Shp2/ 2 Piggot & Bellmere Rd",
    "sg:city":"Bellmere",
    "sg:classifiers":[
        {
            "category":"Personal",
            "subcategory":"Beauty Salon",
            "type":"Services"
        }
    ],
    "sg:phone":"+61 7 5499 4545",
    "sg:postcode":"4510",
    "sg:province":"QLD",
    "sg:tags":[
        "hairdresser"
    ],
    "wof:name":"Bring It On Hair",
    "wof:placetype":"venue"
},
  "geometry": {"coordinates":[152.926636,-27.087912],"type":"Point"}
}