{
  "type": "Feature",
  "properties": {
    "addr:full":"1952 Beechworth Wodonga Rd Indigo Valley NSW 3685",
    "addr:housenumber":"1952",
    "addr:postcode":"3685",
    "addr:street":"Wodonga Rd",
    "iso:country":"AU",
    "sg:address":"1952 Beechworth Wodonga Rd",
    "sg:city":"Indigo Valley",
    "sg:classifiers":[
        {
            "category":"Building & Trades",
            "subcategory":"Construction",
            "type":"Services"
        }
    ],
    "sg:phone":"+61 418 499 269",
    "sg:postcode":"3685",
    "sg:province":"NSW",
    "sg:tags":[
        "earth",
        "excavating",
        "moving",
        "contractor"
    ],
    "wof:name":"Dirt Action Bobcat",
    "wof:placetype":"venue"
},
  "geometry": {"coordinates":[146.45783996599999,-36.058921814],"type":"Point"}
}