{
  "type": "Feature",
  "properties": {
    "addr:full":"6/ 25 Grafton St Cairns QLD 4870",
    "addr:housenumber":"/ 25",
    "addr:postcode":"4870",
    "addr:street":"Grafton St",
    "iso:country":"AU",
    "sg:address":"6/ 25 Grafton St",
    "sg:city":"Cairns",
    "sg:classifiers":[
        {
            "category":"Real Estate",
            "subcategory":"Real Estate Agent",
            "type":"Services"
        }
    ],
    "sg:phone":"+61 7 4031 3100",
    "sg:postcode":"4870",
    "sg:province":"QLD",
    "wof:name":"Tony Roberts Real Estate",
    "wof:placetype":"venue"
},
  "geometry": {"coordinates":[145.77749633799999,-16.9262142181],"type":"Point"}
}