{
  "type": "Feature",
  "properties": {
    "iso:country":"AU",
    "sg:address":"124 Chandos St",
    "sg:city":"Haberfield",
    "sg:classifiers":[
        {
            "category":"Utilities",
            "subcategory":"Electric",
            "type":"Services"
        }
    ],
    "sg:phone":"+61 2 9799 2206",
    "sg:postcode":"2045",
    "sg:province":"NSW",
    "sg:tags":[
        "electrical",
        "contractor"
    ],
    "wof:name":"Anytime Industrial Services Pty Ltd",
    "wof:placetype":"venue"
},
  "geometry": {"coordinates":[151.135529,-33.880997],"type":"Point"}
}