{
  "type": "Feature",
  "properties": {
    "iso:country":"AU",
    "sg:address":"36 Blue Range Crs",
    "sg:city":"Lynbrook",
    "sg:classifiers":[
        {
            "category":"Professional",
            "subcategory":"Art Services",
            "type":"Services"
        }
    ],
    "sg:phone":"+61 408 037 784",
    "sg:postcode":"3975",
    "sg:province":"VIC",
    "sg:tags":[
        "decorator",
        "painter"
    ],
    "wof:name":"Carra's Painting Service",
    "wof:placetype":"venue"
},
  "geometry": {"coordinates":[145.253173828,-38.0530204773],"type":"Point"}
}