{
  "type": "Feature",
  "properties": {
    "iso:country":"AU",
    "sg:address":"20 Radford Ave",
    "sg:city":"Clearview",
    "sg:classifiers":[
        {
            "category":"Building & Trades",
            "subcategory":"Construction",
            "type":"Services"
        }
    ],
    "sg:phone":"+61 418 842 711",
    "sg:postcode":"5085",
    "sg:province":"SA",
    "sg:tags":[
        "fencing",
        "contractor"
    ],
    "wof:name":"Hill David",
    "wof:placetype":"venue"
},
  "geometry": {"coordinates":[138.615325928,-34.8516921997],"type":"Point"}
}