{
  "type": "Feature",
  "properties": {
    "addr:full":"10 Tenth St Mildura VIC 3500",
    "addr:housenumber":"10",
    "addr:postcode":"3500",
    "addr:street":"Tenth St",
    "iso:country":"AU",
    "sg:address":"10 Tenth St",
    "sg:city":"Mildura",
    "sg:classifiers":[
        {
            "category":"Building & Trades",
            "subcategory":"Construction",
            "type":"Services"
        }
    ],
    "sg:phone":"+61 3 5021 2527",
    "sg:postcode":"3500",
    "sg:province":"VIC",
    "sg:tags":[
        "ceiling"
    ],
    "wof:name":"Boral Australia Gypsum Pty Ltd",
    "wof:placetype":"venue"
},
  "geometry": {"coordinates":[142.168655395,-34.1957588196],"type":"Point"}
}