{
  "type": "Feature",
  "properties": {
    "iso:country":"AU",
    "sg:address":"PO Box 295",
    "sg:city":"Ballan",
    "sg:classifiers":[
        {
            "category":"Professional",
            "subcategory":"Detective & Security Services",
            "type":"Services"
        }
    ],
    "sg:phone":"+61 418 565 560",
    "sg:postcode":"3342",
    "sg:province":"VIC",
    "sg:tags":[
        "investigator"
    ],
    "wof:name":"Citiwest Investigations",
    "wof:placetype":"venue"
},
  "geometry": {"coordinates":[144.22869900000001,-37.60014],"type":"Point"}
}