{
  "type": "Feature",
  "properties": {
    "addr:full":"165 Holbrooks Rd Underdale SA 5032",
    "addr:housenumber":"165",
    "addr:postcode":"5032",
    "addr:street":"Holbrooks Rd",
    "iso:country":"AU",
    "sg:address":"165 Holbrooks Rd",
    "sg:city":"Underdale",
    "sg:classifiers":[
        {
            "category":"Professional",
            "subcategory":"Accounting & Tax Preparation",
            "type":"Services"
        }
    ],
    "sg:phone":"+61 8 8354 3450",
    "sg:postcode":"5032",
    "sg:province":"SA",
    "sg:tags":[
        "manager",
        "secretary"
    ],
    "wof:name":"Focus-On Quality Services Pty Ltd",
    "wof:placetype":"venue"
},
  "geometry": {"coordinates":[138.54879760700001,-34.9192504883],"type":"Point"}
}