{
  "type": "Feature",
  "properties": {
    "iso:country":"AU",
    "sg:address":"38 Balfour St",
    "sg:city":"Fairy Meadow",
    "sg:classifiers":[
        {
            "category":"Building & Trades",
            "subcategory":"Plumbing",
            "type":"Services"
        }
    ],
    "sg:phone":"+61 2 4284 3702",
    "sg:postcode":"2519",
    "sg:province":"NSW",
    "sg:tags":[
        "drainers"
    ],
    "wof:name":"Cook P D & L M",
    "wof:placetype":"venue"
},
  "geometry": {"coordinates":[150.886551,-34.385731],"type":"Point"}
}