{
  "type": "Feature",
  "properties": {
    "iso:country":"AU",
    "sg:address":"126 Jetty Rd",
    "sg:city":"Glenelg",
    "sg:classifiers":[
        {
            "category":"Shopping",
            "subcategory":"Clothing, Apparel, & Fashions",
            "type":"Retail Goods"
        }
    ],
    "sg:phone":"+61 8 8295 1975",
    "sg:postcode":"5045",
    "sg:province":"SA",
    "sg:tags":[
        "lady",
        "wear"
    ],
    "wof:name":"Sussan Corporation Australia Ltd",
    "wof:placetype":"venue"
},
  "geometry": {"coordinates":[138.51712000000001,-34.980316],"type":"Point"}
}