{
  "type": "Feature",
  "properties": {
    "addr:full":"53/ 176 South Creek Rd Dee Why NSW 2099",
    "addr:housenumber":"53 / 176",
    "addr:postcode":"2099",
    "addr:street":"South Creek Rd",
    "iso:country":"AU",
    "sg:address":"53/ 176 South Creek Rd",
    "sg:city":"Dee Why",
    "sg:classifiers":[
        {
            "category":"Building & Trades",
            "subcategory":"Locksmith",
            "type":"Services"
        }
    ],
    "sg:phone":"+61 2 9971 9609",
    "sg:postcode":"2099",
    "sg:province":"NSW",
    "sg:tags":[
        "equipment",
        "operating",
        "door",
        "gate"
    ],
    "wof:name":"Peninsula Automated Doors And Gates Pty Ltd",
    "wof:placetype":"venue"
},
  "geometry": {"coordinates":[151.279663086,-33.7342834473],"type":"Point"}
}