{
  "type": "Feature",
  "properties": {
    "addr:full":"64 Koloona Ave Figtree NSW 2525",
    "addr:housenumber":"64",
    "addr:postcode":"2525",
    "addr:street":"Koloona Ave",
    "iso:country":"AU",
    "sg:address":"64 Koloona Ave",
    "sg:city":"Figtree",
    "sg:classifiers":[
        {
            "category":"Home & Garden",
            "subcategory":"Carpets & Floor Coverings",
            "type":"Retail Goods"
        }
    ],
    "sg:phone":"+61 2 4229 3562",
    "sg:postcode":"2525",
    "sg:province":"NSW",
    "sg:tags":[
        "mat",
        "matting"
    ],
    "wof:name":"Foskett Services Pty Ltd",
    "wof:placetype":"venue"
},
  "geometry": {"coordinates":[150.855224609,-34.420085907],"type":"Point"}
}