{
  "type": "Feature",
  "properties": {
    "addr:full":"40 Beresford Ave Greenacre NSW 2190",
    "addr:housenumber":"40",
    "addr:postcode":"2190",
    "addr:street":"Beresford Ave",
    "iso:country":"AU",
    "sg:address":"40 Beresford Ave",
    "sg:city":"Greenacre",
    "sg:classifiers":[
        {
            "category":"Autos & Motor Vehicles",
            "subcategory":"Auto Supplies",
            "type":"Retail Goods"
        }
    ],
    "sg:phone":"+61 2 9790 8948",
    "sg:postcode":"2190",
    "sg:province":"NSW",
    "sg:tags":[
        "tyre"
    ],
    "wof:name":"Beresford Tyre & Service Centre",
    "wof:placetype":"venue"
},
  "geometry": {"coordinates":[151.03949,-33.902008],"type":"Point"}
}