{
  "type": "Feature",
  "properties": {
    "iso:country":"AU",
    "sg:address":"93 Cambridge Rd",
    "sg:city":"Bellerive",
    "sg:classifiers":[
        {
            "category":"Retail",
            "subcategory":"Funeral Services",
            "type":"Services"
        }
    ],
    "sg:phone":"+61 3 6244 2896",
    "sg:postcode":"7018",
    "sg:province":"TAS",
    "sg:tags":[
        "director"
    ],
    "wof:name":"Millingtons",
    "wof:placetype":"venue"
},
  "geometry": {"coordinates":[147.371368408,-42.8694648743],"type":"Point"}
}