{
  "type": "Feature",
  "properties": {
    "addr:full":"Plover Pde Caloundra QLD 4551",
    "addr:postcode":"4551",
    "addr:street":"Plover",
    "iso:country":"AU",
    "sg:address":"Plover Pde",
    "sg:city":"Caloundra",
    "sg:classifiers":[
        {
            "category":"Arena",
            "subcategory":"Sports Club",
            "type":"Entertainment"
        }
    ],
    "sg:phone":"+61 7 5491 4322",
    "sg:postcode":"4551",
    "sg:province":"QLD",
    "sg:tags":[
        "league",
        "rugby"
    ],
    "wof:name":"Caloundra Junior Rugby League Club",
    "wof:placetype":"venue"
},
  "geometry": {"coordinates":[153.127807617,-26.7962188721],"type":"Point"}
}