{
  "type": "Feature",
  "properties": {
    "iso:country":"AU",
    "sg:address":"100 Guildford Rd",
    "sg:city":"Mt Lawley",
    "sg:classifiers":[
        {
            "category":"Travel",
            "subcategory":"Hostel",
            "type":"Entertainment"
        }
    ],
    "sg:phone":"+61 8 9272 5979",
    "sg:postcode":"6050",
    "sg:province":"WA",
    "sg:tags":[
        "home"
    ],
    "wof:name":"Riverslea Hostel",
    "wof:placetype":"venue"
},
  "geometry": {"coordinates":[115.88584136999999,-31.9339847565],"type":"Point"}
}