{
  "type": "Feature",
  "properties": {
    "addr:full":"102 Keightly Rd Shenton Park WA 6008",
    "addr:housenumber":"102",
    "addr:postcode":"6008",
    "addr:street":"Keightly Rd",
    "iso:country":"AU",
    "sg:address":"102 Keightly Rd",
    "sg:city":"Shenton Park",
    "sg:classifiers":[
        {
            "category":"Building & Trades",
            "subcategory":"Landscaping Services",
            "type":"Services"
        }
    ],
    "sg:phone":"+61 8 9382 2482",
    "sg:postcode":"6008",
    "sg:province":"WA",
    "sg:tags":[
        "stump",
        "tree",
        "felling",
        "removal"
    ],
    "wof:name":"Shenton Outside Services",
    "wof:placetype":"venue"
},
  "geometry": {"coordinates":[115.81810760499999,-31.9584178925],"type":"Point"}
}