{
  "type": "Feature",
  "properties": {
    "addr:full":"1045 Doncaster Rd Doncaster East VIC 3109",
    "addr:housenumber":"1045",
    "addr:postcode":"3109",
    "addr:street":"Doncaster Rd",
    "iso:country":"AU",
    "sg:address":"1045 Doncaster Rd",
    "sg:city":"Doncaster East",
    "sg:classifiers":[
        {
            "category":"Health Services",
            "subcategory":"Doctor",
            "type":"Services"
        }
    ],
    "sg:phone":"+61 3 9841 8636",
    "sg:postcode":"3109",
    "sg:province":"VIC",
    "sg:tags":[
        "medical",
        "practitioner"
    ],
    "wof:name":"Naldu Sri Dr",
    "wof:placetype":"venue"
},
  "geometry": {"coordinates":[145.16307067899999,-37.7891044617],"type":"Point"}
}