{
  "type": "Feature",
  "properties": {
    "addr:full":"Cnr Winterslow & Peachey Rds Elizabeth West SA 5113",
    "addr:postcode":"5113",
    "addr:street":"Cnr",
    "iso:country":"AU",
    "sg:address":"Cnr Winterslow & Peachey Rds",
    "sg:city":"Elizabeth West",
    "sg:classifiers":[
        {
            "category":"Farming",
            "subcategory":"Orchard",
            "type":"Manufacturing & Wholesale Goods"
        }
    ],
    "sg:phone":"+61 8 8209 3501",
    "sg:postcode":"5113",
    "sg:province":"SA",
    "sg:tags":[
        "wholesaler",
        "jean",
        "mfrs"
    ],
    "wof:name":"Levi Strauss (Australia) Pty Ltd",
    "wof:placetype":"venue"
},
  "geometry": {"coordinates":[138.66232299800001,-34.710773468],"type":"Point"}
}