{
  "type": "Feature",
  "properties": {
    "addr:full":"Level 3, 167 Eagle St Brisbane QLD 4000",
    "addr:housenumber":"167",
    "addr:postcode":"4000",
    "addr:street":"Eagle St",
    "iso:country":"AU",
    "sg:address":"Level 3, 167 Eagle St",
    "sg:city":"Brisbane",
    "sg:classifiers":[
        {
            "category":"Professional",
            "type":"Services"
        }
    ],
    "sg:phone":"+61 7 3137 3111",
    "sg:postcode":"4000",
    "sg:province":"QLD",
    "sg:tags":[
        "transport"
    ],
    "wof:name":"Toll Resources",
    "wof:placetype":"venue"
},
  "geometry": {"coordinates":[153.03045654300001,-27.4660186768],"type":"Point"}
}