{
  "type": "Feature",
  "properties": {
    "addr:full":"14/160 Hartley Rd Smeaton Grange NSW 2567",
    "addr:housenumber":"14 / 160",
    "addr:postcode":"2567",
    "addr:street":"Hartley Rd",
    "iso:country":"AU",
    "sg:address":"14/160 Hartley Rd",
    "sg:city":"Smeaton Grange",
    "sg:classifiers":[
        {
            "category":"Home & Garden",
            "subcategory":"Building Materials",
            "type":"Retail Goods"
        }
    ],
    "sg:phone":"+61 2 4648 1372",
    "sg:postcode":"2567",
    "sg:province":"NSW",
    "sg:tags":[
        "gate"
    ],
    "wof:name":"Ozgate Automation Pty Ltd",
    "wof:placetype":"venue"
},
  "geometry": {"coordinates":[150.75564575199999,-34.0383491516],"type":"Point"}
}