{
  "type": "Feature",
  "properties": {
    "addr:full":"Jacka St Macleod VIC 3085",
    "addr:postcode":"3085",
    "addr:street":"Jacka St",
    "iso:country":"AU",
    "sg:address":"Jacka St",
    "sg:city":"Macleod",
    "sg:classifiers":[
        {
            "category":"Building & Trades",
            "subcategory":"Construction",
            "type":"Services"
        }
    ],
    "sg:phone":"+61 412 812 144",
    "sg:postcode":"3085",
    "sg:province":"VIC",
    "sg:tags":[
        "stonework",
        "stone",
        "mason"
    ],
    "wof:name":"Millstone Stonework",
    "wof:placetype":"venue"
},
  "geometry": {"coordinates":[145.06455993599999,-37.7266159058],"type":"Point"}
}