{
  "type": "Feature",
  "properties": {
    "addr:full":"5 Vondeest St Bundaberg QLD 4670",
    "addr:housenumber":"5",
    "addr:postcode":"4670",
    "addr:street":"Vondeest St",
    "iso:country":"AU",
    "sg:address":"5 Vondeest St",
    "sg:city":"Bundaberg",
    "sg:classifiers":[
        {
            "category":"Utilities",
            "subcategory":"Electric",
            "type":"Services"
        }
    ],
    "sg:phone":"+61 407 961 111",
    "sg:postcode":"4670",
    "sg:province":"QLD",
    "sg:tags":[
        "electrical",
        "contractor"
    ],
    "wof:name":"W & M Ellison Electrical",
    "wof:placetype":"venue"
},
  "geometry": {"coordinates":[152.30119323700001,-24.9138641357],"type":"Point"}
}