{
  "type": "Feature",
  "properties": {
    "iso:country":"AU",
    "sg:address":"822 Howitt St",
    "sg:city":"Ballarat",
    "sg:classifiers":[
        {
            "category":"Building & Trades",
            "subcategory":"Equipment Rental",
            "type":"Services"
        }
    ],
    "sg:phone":"+61 3 5339 2211",
    "sg:postcode":"3350",
    "sg:province":"VIC",
    "sg:tags":[
        "saw"
    ],
    "wof:name":"Day E. E. & Sons Pty Ltd",
    "wof:placetype":"venue"
},
  "geometry": {"coordinates":[143.846161,-37.541752],"type":"Point"}
}