{
  "type": "Feature",
  "properties": {
    "iso:country":"AU",
    "sg:address":"Suite 4, 410 Burwood Hwy",
    "sg:city":"Wantirna",
    "sg:classifiers":[
        {
            "category":"Banks & Credit Unions",
            "subcategory":"Financial Services",
            "type":"Services"
        }
    ],
    "sg:phone":"+61 3 9800 1552",
    "sg:postcode":"3152",
    "sg:province":"VIC",
    "sg:tags":[
        "advisory",
        "planning",
        "retirement"
    ],
    "wof:name":"RetireInvest",
    "wof:placetype":"venue"
},
  "geometry": {"coordinates":[145.236328125,-37.8694572449],"type":"Point"}
}