{
  "type": "Feature",
  "properties": {
    "addr:full":"Cnr Portarlington & Coppards Rds Newcomb VIC 3219",
    "addr:postcode":"3219",
    "addr:street":"Cnr",
    "iso:country":"AU",
    "sg:address":"Cnr Portarlington & Coppards Rds",
    "sg:city":"Newcomb",
    "sg:classifiers":[
        {
            "category":"Retail",
            "subcategory":"Funeral Services",
            "type":"Services"
        }
    ],
    "sg:phone":"+61 3 5248 5500",
    "sg:postcode":"3219",
    "sg:province":"VIC",
    "sg:tags":[
        "director"
    ],
    "wof:name":"Charles Crawford & Sons",
    "wof:placetype":"venue"
},
  "geometry": {"coordinates":[144.403839111,-38.1666793823],"type":"Point"}
}