{
  "type": "Feature",
  "properties": {
    "addr:full":"10 Allira Crt Pomona QLD 4568",
    "addr:housenumber":"10",
    "addr:postcode":"4568",
    "addr:street":"Allira Crt",
    "iso:country":"AU",
    "sg:address":"10 Allira Crt",
    "sg:city":"Pomona",
    "sg:classifiers":[
        {
            "category":"Ice Cream",
            "type":"Food & Drink"
        }
    ],
    "sg:phone":"+61 411 129 432",
    "sg:postcode":"4568",
    "sg:province":"QLD",
    "sg:tags":[
        "cone",
        "wafer"
    ],
    "wof:name":"Sno Shack",
    "wof:placetype":"venue"
},
  "geometry": {"coordinates":[152.88768005399999,-26.345905304],"type":"Point"}
}