{
  "type": "Feature",
  "properties": {
    "addr:full":"124 - 126 Montague St South Melbourne VIC 3205",
    "addr:housenumber":"124 126",
    "addr:postcode":"3205",
    "addr:street":"Montague St",
    "iso:country":"AU",
    "sg:address":"124 - 126 Montague St",
    "sg:city":"South Melbourne",
    "sg:classifiers":[
        {
            "category":"Retail",
            "subcategory":"Auto Repair",
            "type":"Services"
        }
    ],
    "sg:phone":"+61 3 9686 9121",
    "sg:postcode":"3205",
    "sg:province":"VIC",
    "sg:tags":[
        "testing",
        "inspection",
        "motor",
        "vehicle"
    ],
    "wof:name":"B M Serv",
    "wof:placetype":"venue"
},
  "geometry": {"coordinates":[144.95051599999999,-37.83131],"type":"Point"}
}