{
  "type": "Feature",
  "properties": {
    "iso:country":"AU",
    "sg:address":"8 Derna Rd",
    "sg:city":"Holsworthy",
    "sg:classifiers":[
        {
            "category":"Health Services",
            "subcategory":"Doctor",
            "type":"Services"
        }
    ],
    "sg:phone":"+61 417 253 954",
    "sg:postcode":"2173",
    "sg:province":"NSW",
    "sg:tags":[
        "occupational",
        "safety"
    ],
    "wof:name":"Saunders Rod",
    "wof:placetype":"venue"
},
  "geometry": {"coordinates":[150.94696044899999,-33.9481048584],"type":"Point"}
}