{
  "type": "Feature",
  "properties": {
    "iso:country":"AU",
    "sg:address":"203 Warrandyte Rd",
    "sg:city":"Ringwood",
    "sg:classifiers":[
        {
            "category":"Social Services",
            "subcategory":"Child Care",
            "type":"Services"
        }
    ],
    "sg:phone":"+61 3 9876 5686",
    "sg:postcode":"3134",
    "sg:province":"VIC",
    "wof:name":"ABC Learning Centres",
    "wof:placetype":"venue"
},
  "geometry": {"coordinates":[145.235397339,-37.7923965454],"type":"Point"}
}