{
  "type": "Feature",
  "properties": {
    "addr:full":"Ste 6/ 9 Plaza Rd Maroochydore QLD 4558",
    "addr:postcode":"4558",
    "addr:street":"Plaza Rd",
    "iso:country":"AU",
    "sg:address":"Ste 6/ 9 Plaza Rd",
    "sg:city":"Maroochydore",
    "sg:classifiers":[
        {
            "category":"Communications",
            "subcategory":"Film & Video Production",
            "type":"Services"
        }
    ],
    "sg:phone":"+61 7 5409 6455",
    "sg:postcode":"4558",
    "sg:province":"QLD",
    "sg:tags":[
        "society",
        "housing",
        "co-operative"
    ],
    "wof:name":"Home Equity Associates",
    "wof:placetype":"venue"
},
  "geometry": {"coordinates":[153.09042358400001,-26.6564216614],"type":"Point"}
}