{
  "type": "Feature",
  "properties": {
    "addr:full":"10B Wighton St Margate QLD 4019",
    "addr:housenumber":"10b",
    "addr:postcode":"4019",
    "addr:street":"Wighton St",
    "iso:country":"AU",
    "sg:address":"10B Wighton St",
    "sg:city":"Margate",
    "sg:classifiers":[
        {
            "category":"Sports & Exercise",
            "subcategory":"Gym",
            "type":"Entertainment"
        }
    ],
    "sg:phone":"+61 408 736 739",
    "sg:postcode":"4019",
    "sg:province":"QLD",
    "sg:tags":[
        "personal",
        "trainer",
        "fitness"
    ],
    "wof:name":"Fit Wish Personal Training",
    "wof:placetype":"venue"
},
  "geometry": {"coordinates":[153.10743713400001,-27.2432823181],"type":"Point"}
}