{
  "type": "Feature",
  "properties": {
    "addr:full":"146 Kent St Rockhampton QLD 4700",
    "addr:housenumber":"146",
    "addr:postcode":"4700",
    "addr:street":"Kent St",
    "iso:country":"AU",
    "sg:address":"146 Kent St",
    "sg:city":"Rockhampton",
    "sg:classifiers":[
        {
            "category":"Utilities",
            "subcategory":"Telephone",
            "type":"Services"
        }
    ],
    "sg:phone":"+61 7 4927 1422",
    "sg:postcode":"4700",
    "sg:province":"QLD",
    "sg:tags":[
        "installation",
        "system",
        "maintenance"
    ],
    "wof:name":"RBM I.T. Pty Ltd",
    "wof:placetype":"venue"
},
  "geometry": {"coordinates":[150.51963806099999,-23.3956718445],"type":"Point"}
}