{
  "type": "Feature",
  "properties": {
    "addr:full":"12 Baker St East Botany NSW 2019",
    "addr:housenumber":"12",
    "addr:postcode":"2019",
    "addr:street":"Baker St East",
    "iso:country":"AU",
    "sg:address":"12 Baker St",
    "sg:city":"East Botany",
    "sg:classifiers":[
        {
            "category":"Utilities",
            "subcategory":"Refuse",
            "type":"Services"
        }
    ],
    "sg:phone":"+61 2 9666 5944",
    "sg:postcode":"2019",
    "sg:province":"NSW",
    "sg:tags":[
        "wholesale",
        "glassware",
        "china",
        "earthenware"
    ],
    "wof:name":"Glenwood Trading Corp Pty Ltd",
    "wof:placetype":"venue"
},
  "geometry": {"coordinates":[151.21572875999999,-33.9451828003],"type":"Point"}
}