{
  "type": "Feature",
  "properties": {
    "addr:full":"Suite 12 Noosa Central 4-12 Bottlebrush Ave Noosa Heads QLD 4567",
    "addr:housenumber":"4-12",
    "addr:postcode":"4567",
    "addr:street":"Bottlebrush Ave",
    "iso:country":"AU",
    "sg:address":"Suite 12 Noosa Central 4-12 Bottlebrush Ave",
    "sg:city":"Noosa Heads",
    "sg:classifiers":[
        {
            "category":"Professional",
            "subcategory":"Accounting & Tax Preparation",
            "type":"Services"
        }
    ],
    "sg:phone":"+61 7 5474 8955",
    "sg:postcode":"4567",
    "sg:province":"QLD",
    "sg:tags":[
        "consultant",
        "taxation"
    ],
    "wof:name":"McAdam Siemon",
    "wof:placetype":"venue"
},
  "geometry": {"coordinates":[153.09022522000001,-26.3957252502],"type":"Point"}
}