{
  "type": "Feature",
  "properties": {
    "addr:full":"15 Janelle St Bellbird Park QLD 4300",
    "addr:housenumber":"15",
    "addr:postcode":"4300",
    "addr:street":"Janelle St",
    "iso:country":"AU",
    "sg:address":"15 Janelle St",
    "sg:city":"Bellbird Park",
    "sg:classifiers":[
        {
            "category":"Shopping",
            "subcategory":"Bridal",
            "type":"Retail Goods"
        }
    ],
    "sg:phone":"+61 7 3818 6150",
    "sg:postcode":"4300",
    "sg:province":"QLD",
    "sg:tags":[
        "hire",
        "wear"
    ],
    "wof:name":"A Fantasy Reigns",
    "wof:placetype":"venue"
},
  "geometry": {"coordinates":[152.89669799800001,-27.6249675751],"type":"Point"}
}