{
  "type": "Feature",
  "properties": {
    "addr:full":"38a Belmont Rd Mosman NSW 2088",
    "addr:housenumber":"38a",
    "addr:postcode":"2088",
    "addr:street":"Belmont Rd",
    "iso:country":"AU",
    "sg:address":"38a Belmont Rd",
    "sg:city":"Mosman",
    "sg:classifiers":[
        {
            "category":"Education",
            "subcategory":"Kindergarten",
            "type":"Public Place"
        }
    ],
    "sg:phone":"+61 2 9969 3070",
    "sg:postcode":"2088",
    "sg:province":"NSW",
    "sg:tags":[
        "pre-schools"
    ],
    "wof:name":"KU Children's Services",
    "wof:placetype":"venue"
},
  "geometry": {"coordinates":[151.23817443900001,-33.8283195496],"type":"Point"}
}