{
  "type": "Feature",
  "properties": {
    "addr:full":"Shop 2, 851- 855 Point Nepean Rd Rosebud VIC 3939",
    "addr:housenumber":"shop 2;855",
    "addr:postcode":"851;3939",
    "addr:street":"Point Nepean Rd",
    "iso:country":"AU",
    "sg:address":"Shop 2, 851- 855 Point Nepean Rd",
    "sg:city":"Rosebud",
    "sg:classifiers":[
        {
            "category":"Building & Trades",
            "subcategory":"Locksmith",
            "type":"Services"
        }
    ],
    "sg:phone":"+61 3 5982 2555",
    "sg:postcode":"3939",
    "sg:province":"VIC",
    "sg:tags":[
        "lock"
    ],
    "wof:name":"Nepean Security Solutions",
    "wof:placetype":"venue"
},
  "geometry": {"coordinates":[144.91177368199999,-38.3540077209],"type":"Point"}
}