{
  "type": "Feature",
  "properties": {
    "iso:country":"AU",
    "sg:address":"7 Tarrilli St",
    "sg:city":"Beverly Hills",
    "sg:classifiers":[
        {
            "category":"Home & Garden",
            "subcategory":"Carpets & Floor Coverings",
            "type":"Retail Goods"
        }
    ],
    "sg:phone":"+61 2 9554 3118",
    "sg:postcode":"2209",
    "sg:province":"NSW",
    "sg:tags":[
        "layer",
        "planner"
    ],
    "wof:name":"AAA Ardvaark Super Carpets",
    "wof:placetype":"venue"
},
  "geometry": {"coordinates":[151.080063,-33.945988],"type":"Point"}
}