{
  "type": "Feature",
  "properties": {
    "iso:country":"AU",
    "sg:address":"4 Tawonga Crt",
    "sg:city":"Glen Waverley",
    "sg:classifiers":[
        {
            "category":"Building & Trades",
            "subcategory":"Landscaping Services",
            "type":"Services"
        }
    ],
    "sg:phone":"+61 3 9802 1316",
    "sg:postcode":"3150",
    "sg:province":"VIC",
    "sg:tags":[
        "designer",
        "landscape",
        "contractor"
    ],
    "wof:name":"Wills D J",
    "wof:placetype":"venue"
},
  "geometry": {"coordinates":[145.152877808,-37.8684577942],"type":"Point"}
}