{
  "type": "Feature",
  "properties": {
    "addr:full":"108 Prince Charles Rd Frenchs Forest NSW 2086",
    "addr:housenumber":"108",
    "addr:postcode":"2086",
    "addr:street":"Prince Charles Rd",
    "iso:country":"AU",
    "sg:address":"108 Prince Charles Rd",
    "sg:city":"Frenchs Forest",
    "sg:classifiers":[
        {
            "category":"Professional",
            "subcategory":"Computer Services",
            "type":"Services"
        }
    ],
    "sg:phone":"+61 2 9975 3690",
    "sg:postcode":"2086",
    "sg:province":"NSW",
    "sg:tags":[
        "consultant",
        "system"
    ],
    "wof:name":"Collective Minds Pty Ltd",
    "wof:placetype":"venue"
},
  "geometry": {"coordinates":[151.22105407699999,-33.7407989502],"type":"Point"}
}