{
  "type": "Feature",
  "properties": {
    "addr:full":"Darlington Pde Richmond VIC 3121",
    "addr:postcode":"3121",
    "addr:street":"Darlington Pde",
    "iso:country":"AU",
    "sg:address":"Darlington Pde",
    "sg:city":"Richmond",
    "sg:classifiers":[
        {
            "category":"Education",
            "subcategory":"School",
            "type":"Public Place"
        }
    ],
    "sg:phone":"+61 3 9429 4544",
    "sg:postcode":"3121",
    "sg:province":"VIC",
    "sg:tags":[
        "girl"
    ],
    "wof:name":"Vaucluse College F.C.J.",
    "wof:placetype":"venue"
},
  "geometry": {"coordinates":[144.997680664,-37.8208274841],"type":"Point"}
}