{
  "type": "Feature",
  "properties": {
    "iso:country":"AU",
    "sg:address":"400 Lane Cove Rd",
    "sg:city":"North Ryde",
    "sg:classifiers":[
        {
            "category":"Autos & Motor Vehicles",
            "subcategory":"Fuel & Gas Station",
            "type":"Retail Goods"
        }
    ],
    "sg:phone":"+61 2 9888 3399",
    "sg:postcode":"2113",
    "sg:province":"NSW",
    "wof:name":"Quix Food Stores",
    "wof:placetype":"venue"
},
  "geometry": {"coordinates":[151.12840270999999,-33.7848434448],"type":"Point"}
}