{
  "type": "Feature",
  "properties": {
    "addr:full":"129 Payneham Rd St Peters SA 5069",
    "addr:housenumber":"129",
    "addr:postcode":"5069",
    "addr:street":"Payneham Rd",
    "iso:country":"AU",
    "sg:address":"129 Payneham Rd St",
    "sg:city":"Peters",
    "sg:classifiers":[
        {
            "category":"Shopping",
            "subcategory":"Clothing, Apparel, & Fashions",
            "type":"Retail Goods"
        }
    ],
    "sg:phone":"+61 8 8362 4652",
    "sg:postcode":"5069",
    "sg:province":"SA",
    "sg:tags":[
        "recycled",
        "clothing"
    ],
    "wof:name":"BCS Op-Shops",
    "wof:placetype":"venue"
},
  "geometry": {"coordinates":[138.6275177,-34.9097442627],"type":"Point"}
}