{
  "type": "Feature",
  "properties": {
    "iso:country":"AU",
    "sg:address":"308a High St",
    "sg:city":"Kew",
    "sg:classifiers":[
        {
            "category":"Professional",
            "subcategory":"Printing & Photocopies",
            "type":"Services"
        }
    ],
    "sg:phone":"+61 3 9853 3800",
    "sg:postcode":"3101",
    "sg:province":"VIC",
    "sg:tags":[
        "photocopying"
    ],
    "wof:name":"Phillips & Father Printing Pty Ltd",
    "wof:placetype":"venue"
},
  "geometry": {"coordinates":[145.03550720199999,-37.805229187],"type":"Point"}
}