{
  "type": "Feature",
  "properties": {
    "addr:full":"170 Railway Pde Bassendean WA 6054",
    "addr:housenumber":"170",
    "addr:postcode":"6054",
    "addr:street":"Railway Pde",
    "iso:country":"AU",
    "sg:address":"170 Railway Pde",
    "sg:city":"Bassendean",
    "sg:classifiers":[
        {
            "category":"Train Station",
            "subcategory":"Rail",
            "type":"Transportation"
        }
    ],
    "sg:phone":"+61 8 9449 8333",
    "sg:postcode":"6054",
    "sg:province":"WA",
    "sg:tags":[
        "rolling",
        "railway",
        "tramway",
        "stock"
    ],
    "wof:name":"Bradken",
    "wof:placetype":"venue"
},
  "geometry": {"coordinates":[115.93582916299999,-31.9124011993],"type":"Point"}
}