{
  "type": "Feature",
  "properties": {
    "addr:full":"108 Burnett St Buderim QLD 4556",
    "addr:housenumber":"108",
    "addr:postcode":"4556",
    "addr:street":"Burnett St",
    "iso:country":"AU",
    "sg:address":"108 Burnett St",
    "sg:city":"Buderim",
    "sg:classifiers":[
        {
            "category":"Personal",
            "subcategory":"Beauty Salon",
            "type":"Services"
        }
    ],
    "sg:phone":"+61 7 5445 2900",
    "sg:postcode":"4556",
    "sg:province":"QLD",
    "wof:name":"Deborahs Touch of Beauty",
    "wof:placetype":"venue"
},
  "geometry": {"coordinates":[153.04655456500001,-26.6887187958],"type":"Point"}
}