{
  "type": "Feature",
  "properties": {
    "iso:country":"AU",
    "sg:address":"Shop 4/ 51 Marina Blv",
    "sg:city":"Cullen Bay",
    "sg:classifiers":[
        {
            "category":"Personal",
            "subcategory":"Beauty Salon",
            "type":"Services"
        }
    ],
    "sg:phone":"+61 8 8941 7878",
    "sg:postcode":"0820",
    "sg:province":"NT",
    "sg:tags":[
        "hairdresser"
    ],
    "wof:name":"Edge Hair Designers",
    "wof:placetype":"venue"
},
  "geometry": {"coordinates":[130.822555542,-12.4504518509],"type":"Point"}
}