{
  "type": "Feature",
  "properties": {
    "addr:full":"Level 1 26-28 Cook Rd Marrickville NSW 2204",
    "addr:housenumber":"26-28",
    "addr:postcode":"2204",
    "addr:street":"Cook Rd",
    "iso:country":"AU",
    "sg:address":"Level 1 26-28 Cook Rd",
    "sg:city":"Marrickville",
    "sg:classifiers":[
        {
            "category":"Arena",
            "subcategory":"Sports Club",
            "type":"Entertainment"
        }
    ],
    "sg:phone":"+61 2 9660 1012",
    "sg:postcode":"2204",
    "sg:province":"NSW",
    "sg:tags":[
        "defence",
        "supply",
        "self",
        "instruction",
        "martial art"
    ],
    "wof:name":"Australian Freestyle Martial Art Academ Inner West Sydney",
    "wof:placetype":"venue"
},
  "geometry": {"coordinates":[151.16639699999999,-33.904747],"type":"Point"}
}