{
  "type": "Feature",
  "properties": {
    "iso:country":"AU",
    "sg:address":"377 High St",
    "sg:city":"Maitland",
    "sg:classifiers":[
        {
            "category":"Personal",
            "subcategory":"Beauty Salon",
            "type":"Services"
        }
    ],
    "sg:phone":"+61 2 4933 5054",
    "sg:postcode":"2320",
    "sg:province":"NSW",
    "sg:tags":[
        "hairdresser"
    ],
    "wof:name":"McIntyre Leigh",
    "wof:placetype":"venue"
},
  "geometry": {"coordinates":[151.5572052,-32.7334671021],"type":"Point"}
}