{
  "type": "Feature",
  "properties": {
    "addr:full":"134 Watley Crs Maylands WA 6051",
    "addr:housenumber":"134",
    "addr:postcode":"6051",
    "addr:street":"Watley Crs",
    "iso:country":"AU",
    "sg:address":"134 Watley Crs",
    "sg:city":"Maylands",
    "sg:classifiers":[
        {
            "category":"Arena",
            "subcategory":"Sports Club",
            "type":"Entertainment"
        }
    ],
    "sg:phone":"+61 409 327 195",
    "sg:postcode":"6051",
    "sg:province":"WA",
    "sg:tags":[
        "defence",
        "supply",
        "self",
        "instruction",
        "martial art"
    ],
    "wof:name":"Hakarac Boxing",
    "wof:placetype":"venue"
},
  "geometry": {"coordinates":[115.900459,-31.935789],"type":"Point"}
}