{
  "type": "Feature",
  "properties": {
    "addr:full":"31 Old Port Rd Queenstown SA 5014",
    "addr:housenumber":"31",
    "addr:postcode":"5014",
    "addr:street":"Old Port Rd",
    "iso:country":"AU",
    "sg:address":"31 Old Port Rd",
    "sg:city":"Queenstown",
    "sg:classifiers":[
        {
            "category":"Home & Garden",
            "subcategory":"Carpets & Floor Coverings",
            "type":"Retail Goods"
        }
    ],
    "sg:phone":"+61 8 8241 1109",
    "sg:postcode":"5014",
    "sg:province":"SA",
    "wof:name":"Port Adelaide Carpet Choice",
    "wof:placetype":"venue"
},
  "geometry": {"coordinates":[138.50692749000001,-34.8623390198],"type":"Point"}
}