{
  "type": "Feature",
  "properties": {
    "addr:full":"5/ B Lavarack Ave Eagle Farm QLD 4009",
    "addr:housenumber":"/ b",
    "addr:postcode":"4009",
    "addr:street":"Lavarack Ave",
    "iso:country":"AU",
    "sg:address":"5/ B Lavarack Ave",
    "sg:city":"Eagle Farm",
    "sg:classifiers":[
        {
            "category":"Shopping",
            "subcategory":"Bicycles & Sporting Goods",
            "type":"Retail Goods"
        }
    ],
    "sg:phone":"+61 7 3268 3866",
    "sg:postcode":"4009",
    "sg:province":"QLD",
    "sg:tags":[
        "chemical",
        "equipment",
        "pool",
        "swimming"
    ],
    "wof:name":"Pegguses Pool Products",
    "wof:placetype":"venue"
},
  "geometry": {"coordinates":[153.098587036,-27.4312667847],"type":"Point"}
}