{
  "type": "Feature",
  "properties": {
    "addr:full":"34 Playne St Frankston VIC 3199",
    "addr:housenumber":"34",
    "addr:postcode":"3199",
    "addr:street":"Playne St",
    "iso:country":"AU",
    "sg:address":"34 Playne St",
    "sg:city":"Frankston",
    "sg:classifiers":[
        {
            "category":"Manufacturing",
            "subcategory":"Food",
            "type":"Manufacturing & Wholesale Goods"
        }
    ],
    "sg:phone":"+61 3 9770 5511",
    "sg:postcode":"3199",
    "sg:province":"VIC",
    "sg:tags":[
        "function",
        "catering"
    ],
    "wof:name":"Great Flavours",
    "wof:placetype":"venue"
},
  "geometry": {"coordinates":[145.12213134800001,-38.1449661255],"type":"Point"}
}