{
  "type": "Feature",
  "properties": {
    "iso:country":"AU",
    "sg:address":"40 Bandara St",
    "sg:city":"Richlands",
    "sg:classifiers":[
        {
            "category":"Building & Trades",
            "subcategory":"Equipment Rental",
            "type":"Services"
        }
    ],
    "sg:phone":"+61 7 3879 3191",
    "sg:postcode":"4077",
    "sg:province":"QLD",
    "sg:tags":[
        "fitness"
    ],
    "wof:name":"Powerpole Manufacturing Pty Ltd",
    "wof:placetype":"venue"
},
  "geometry": {"coordinates":[152.94198608400001,-27.5899887085],"type":"Point"}
}