{
  "type": "Feature",
  "properties": {
    "addr:full":"Factory 21 15 Macquarie Pl Boronia VIC 3155",
    "addr:housenumber":"15",
    "addr:postcode":"3155",
    "addr:street":"Macquarie Pl",
    "iso:country":"AU",
    "sg:address":"Factory 21 15 Macquarie Pl",
    "sg:city":"Boronia",
    "sg:classifiers":[
        {
            "category":"Food & Beverages",
            "subcategory":"Bakery",
            "type":"Retail Goods"
        }
    ],
    "sg:phone":"+61 3 9720 7346",
    "sg:postcode":"3155",
    "sg:province":"VIC",
    "sg:tags":[
        "baker"
    ],
    "wof:name":"Culina Bakery",
    "wof:placetype":"venue"
},
  "geometry": {"coordinates":[145.289505005,-37.8358840942],"type":"Point"}
}