{
  "type": "Feature",
  "properties": {
    "addr:full":"Mutu St Woy Woy NSW 2256",
    "addr:postcode":"2256",
    "addr:street":"St",
    "iso:country":"AU",
    "sg:address":"Mutu St",
    "sg:city":"Woy Woy",
    "sg:classifiers":[
        {
            "category":"Manufacturing",
            "subcategory":"Motor Vehicles & Parts",
            "type":"Manufacturing & Wholesale Goods"
        }
    ],
    "sg:phone":"+61 2 4341 4979",
    "sg:postcode":"2256",
    "sg:province":"NSW",
    "sg:tags":[
        "replacement"
    ],
    "wof:name":"Allcoast Radiator Repairs",
    "wof:placetype":"venue"
},
  "geometry": {"coordinates":[151.320144653,-33.4929161072],"type":"Point"}
}