{
  "type": "Feature",
  "properties": {
    "iso:country":"AU",
    "sg:address":"Yandilla St",
    "sg:city":"Pittsworth",
    "sg:classifiers":[
        {
            "category":"Home & Garden",
            "subcategory":"Garden Supply",
            "type":"Retail Goods"
        }
    ],
    "sg:phone":"+61 7 4693 2477",
    "sg:postcode":"4356",
    "sg:province":"QLD",
    "sg:tags":[
        "fertilizer"
    ],
    "wof:name":"DFC Agri Services",
    "wof:placetype":"venue"
},
  "geometry": {"coordinates":[151.63580300000001,-27.71553],"type":"Point"}
}