{
  "type": "Feature",
  "properties": {
    "iso:country":"AU",
    "sg:address":"Factory 2/ 34 Kolora Rd",
    "sg:city":"Heidelberg West",
    "sg:classifiers":[
        {
            "category":"Building & Trades",
            "subcategory":"Equipment Rental",
            "type":"Services"
        }
    ],
    "sg:phone":"+61 3 9458 4777",
    "sg:postcode":"3081",
    "sg:province":"VIC",
    "sg:tags":[
        "supply",
        "catering"
    ],
    "wof:name":"Ritter General Electric",
    "wof:placetype":"venue"
},
  "geometry": {"coordinates":[145.04589843799999,-37.7333679199],"type":"Point"}
}