{
  "type": "Feature",
  "properties": {
    "iso:country":"AU",
    "sg:address":"86 Wee Waa St",
    "sg:city":"Boggabri",
    "sg:classifiers":[
        {
            "category":"Retail",
            "subcategory":"Auto Repair",
            "type":"Services"
        }
    ],
    "sg:phone":"+61 2 6743 4697",
    "sg:postcode":"2382",
    "sg:province":"NSW",
    "sg:tags":[
        "repairer",
        "motor",
        "engineer"
    ],
    "wof:name":"McKechnie N J & H T",
    "wof:placetype":"venue"
},
  "geometry": {"coordinates":[150.04122924800001,-30.7116012573],"type":"Point"}
}