{
  "type": "Feature",
  "properties": {
    "addr:full":"Bogong High Plain Rd Falls Creek VIC 3699",
    "addr:postcode":"3699",
    "addr:street":"Plain Rd",
    "iso:country":"AU",
    "sg:address":"Bogong High Plain Rd",
    "sg:city":"Falls Creek",
    "sg:classifiers":[
        {
            "category":"Travel",
            "subcategory":"Hotels & Motels",
            "type":"Entertainment"
        }
    ],
    "sg:phone":"+61 3 5758 3391",
    "sg:postcode":"3699",
    "sg:province":"VIC",
    "sg:tags":[
        "accommodation"
    ],
    "wof:name":"Falls Creek Country Club",
    "wof:placetype":"venue"
},
  "geometry": {"coordinates":[147.17315673799999,-36.74426651],"type":"Point"}
}