{
  "type": "Feature",
  "properties": {
    "addr:full":"Suite 104, 11 Spring St Chatswood NSW 2067",
    "addr:housenumber":"11",
    "addr:postcode":"2067",
    "addr:street":"Spring St",
    "iso:country":"AU",
    "sg:address":"Suite 104, 11 Spring St",
    "sg:city":"Chatswood",
    "sg:classifiers":[
        {
            "category":"Real Estate",
            "subcategory":"Architect",
            "type":"Services"
        }
    ],
    "sg:phone":"+61 2 9419 6100",
    "sg:postcode":"2067",
    "sg:province":"NSW",
    "sg:tags":[
        "magnet",
        "magnetic",
        "material"
    ],
    "wof:name":"Hitachi Metals Aust Pty Ltd",
    "wof:placetype":"venue"
},
  "geometry": {"coordinates":[151.18487548799999,-33.7965545654],"type":"Point"}
}