{
  "type": "Feature",
  "properties": {
    "addr:full":"260-262 Church St Richmond VIC 3121",
    "addr:housenumber":"260-262",
    "addr:postcode":"3121",
    "addr:street":"Church St",
    "iso:country":"AU",
    "sg:address":"260-262 Church St",
    "sg:city":"Richmond",
    "sg:classifiers":[
        {
            "category":"Wholesale",
            "subcategory":"Construction Materials",
            "type":"Manufacturing & Wholesale Goods"
        }
    ],
    "sg:phone":"+61 3 9429 1866",
    "sg:postcode":"3121",
    "sg:province":"VIC",
    "sg:tags":[
        "wholesaler",
        "lighting",
        "mfrs",
        "accessory"
    ],
    "wof:name":"Oldworld Chandeliers/Royalty Lightning",
    "wof:placetype":"venue"
},
  "geometry": {"coordinates":[144.99891662600001,-37.8191146851],"type":"Point"}
}