{
  "type": "Feature",
  "properties": {
    "addr:full":"1 Culverston Rd Minto NSW 2566",
    "addr:housenumber":"1",
    "addr:postcode":"2566",
    "addr:street":"Culverston Rd",
    "iso:country":"AU",
    "sg:address":"1 Culverston Rd",
    "sg:city":"Minto",
    "sg:classifiers":[
        {
            "category":"Wholesale",
            "subcategory":"Machinery & Supplies",
            "type":"Manufacturing & Wholesale Goods"
        }
    ],
    "sg:phone":"+61 1300 727 696",
    "sg:postcode":"2566",
    "sg:province":"NSW",
    "sg:tags":[
        "equipment",
        "laboratory"
    ],
    "wof:name":"Crown Scientific",
    "wof:placetype":"venue"
},
  "geometry": {"coordinates":[150.83506774899999,-34.0387268066],"type":"Point"}
}