{
  "type": "Feature",
  "properties": {
    "addr:full":"Lot 503 Henderson Rd Serpentine WA 6125",
    "addr:postcode":"6125",
    "addr:street":"Henderson Rd",
    "iso:country":"AU",
    "sg:address":"Lot 503 Henderson Rd",
    "sg:city":"Serpentine",
    "sg:classifiers":[
        {
            "category":"Home & Garden",
            "subcategory":"Garden Supply",
            "type":"Retail Goods"
        }
    ],
    "sg:phone":"+61 8 9525 2400",
    "sg:postcode":"6125",
    "sg:province":"WA",
    "sg:tags":[
        "turf",
        "lawn"
    ],
    "wof:name":"Greenacres Turf Farm",
    "wof:placetype":"venue"
},
  "geometry": {"coordinates":[115.925720215,-32.4047164917],"type":"Point"}
}