{
  "type": "Feature",
  "properties": {
    "iso:country":"AU",
    "sg:address":"Suite 10 / 3 Knox St",
    "sg:city":"Double Bay",
    "sg:classifiers":[
        {
            "category":"Home & Garden",
            "subcategory":"Home Furnishings",
            "type":"Retail Goods"
        }
    ],
    "sg:phone":"+61 2 9363 9991",
    "sg:postcode":"2028",
    "sg:province":"NSW",
    "sg:tags":[
        "storage",
        "rack",
        "wine"
    ],
    "wof:name":"Cellarit Wine Storage",
    "wof:placetype":"venue"
},
  "geometry": {"coordinates":[151.24282836899999,-33.8772506714],"type":"Point"}
}