{
  "type": "Feature",
  "properties": {
    "iso:country":"AU",
    "sg:address":"114 Beverley St",
    "sg:city":"Doncaster East",
    "sg:classifiers":[
        {
            "category":"Professional",
            "subcategory":"Art Services",
            "type":"Services"
        }
    ],
    "sg:phone":"+61 3 9841 5965",
    "sg:postcode":"3109",
    "sg:province":"VIC",
    "sg:tags":[
        "decorator",
        "painter"
    ],
    "wof:name":"C & G Painting",
    "wof:placetype":"venue"
},
  "geometry": {"coordinates":[145.164596558,-37.7915916443],"type":"Point"}
}