{
  "type": "Feature",
  "properties": {
    "addr:full":"Suite 6, 9 Bowman St South Perth WA 6151",
    "addr:housenumber":"9",
    "addr:postcode":"6151",
    "addr:street":"Bowman St South",
    "iso:country":"AU",
    "sg:address":"Suite 6, 9 Bowman St",
    "sg:city":"South Perth",
    "sg:classifiers":[
        {
            "category":"Professional",
            "subcategory":"Secretarial Services",
            "type":"Services"
        }
    ],
    "sg:phone":"+61 8 9367 1444",
    "sg:postcode":"6151",
    "sg:province":"WA",
    "sg:tags":[
        "typing"
    ],
    "wof:name":"Administrative Business Centre",
    "wof:placetype":"venue"
},
  "geometry": {"coordinates":[115.849113,-31.973969],"type":"Point"}
}