{
  "type": "Feature",
  "properties": {
    "addr:full":"Cnr Bannister Rd & Sherman St Canning Vale WA 6155",
    "addr:postcode":"6155",
    "addr:street":"Cnr Bannister Rd & Sherman St",
    "iso:country":"AU",
    "sg:address":"Cnr Bannister Rd & Sherman St",
    "sg:city":"Canning Vale",
    "sg:classifiers":[
        {
            "category":"Professional",
            "subcategory":"Detective & Security Services",
            "type":"Services"
        }
    ],
    "sg:phone":"+61 8 9455 1555",
    "sg:postcode":"6155",
    "sg:province":"WA",
    "sg:tags":[
        "equipment",
        "window",
        "doors"
    ],
    "wof:name":"Westral Home Improvements",
    "wof:placetype":"venue"
},
  "geometry": {"coordinates":[115.90928599999999,-32.058804],"type":"Point"}
}