{
  "type": "Feature",
  "properties": {
    "iso:country":"AU",
    "sg:address":"61 Matilda St",
    "sg:city":"Port Lincoln",
    "sg:classifiers":[
        {
            "category":"Building & Trades",
            "subcategory":"Construction",
            "type":"Services"
        }
    ],
    "sg:phone":"+61 8 8683 0555",
    "sg:postcode":"5606",
    "sg:province":"SA",
    "sg:tags":[
        "monumental",
        "mason"
    ],
    "wof:name":"Peter Hagen Granite",
    "wof:placetype":"venue"
},
  "geometry": {"coordinates":[135.852463,-34.735092],"type":"Point"}
}