{
  "type": "Feature",
  "properties": {
    "addr:full":"712 Nudgee Rd Northgate QLD 4013",
    "addr:housenumber":"712",
    "addr:postcode":"4013",
    "addr:street":"Nudgee Rd",
    "iso:country":"AU",
    "sg:address":"712 Nudgee Rd",
    "sg:city":"Northgate",
    "sg:classifiers":[
        {
            "category":"Retail",
            "subcategory":"Auto Rental",
            "type":"Services"
        }
    ],
    "sg:phone":"+61 7 5591 7611",
    "sg:postcode":"4013",
    "sg:province":"QLD",
    "sg:tags":[
        "car",
        "hire",
        "minibus"
    ],
    "wof:name":"Gold Coast Rent-a-Car Pty Ltd",
    "wof:placetype":"venue"
},
  "geometry": {"coordinates":[153.07614135700001,-27.3961753845],"type":"Point"}
}