{
  "type": "Feature",
  "properties": {
    "iso:country":"AU",
    "sg:address":"38 Huene Ave",
    "sg:city":"Budgewoi",
    "sg:classifiers":[
        {
            "category":"Building & Trades",
            "subcategory":"Plumbing",
            "type":"Services"
        }
    ],
    "sg:phone":"+61 2 4399 1111",
    "sg:postcode":"2262",
    "sg:province":"NSW",
    "sg:tags":[
        "plumber",
        "gasfitters"
    ],
    "wof:name":"ABCB Plumbing & Drainage",
    "wof:placetype":"venue"
},
  "geometry": {"coordinates":[151.55244400000001,-33.22319],"type":"Point"}
}