{
  "type": "Feature",
  "properties": {
    "addr:full":"10 Laver Crt Alice Springs NT 0870",
    "addr:housenumber":"10",
    "addr:postcode":"nt 0870",
    "addr:street":"Laver Crt",
    "iso:country":"AU",
    "sg:address":"10 Laver Crt",
    "sg:city":"Alice Springs",
    "sg:classifiers":[
        {
            "category":"Professional",
            "subcategory":"Accounting & Tax Preparation",
            "type":"Services"
        }
    ],
    "sg:phone":"+61 8 8953 0926",
    "sg:postcode":"0870",
    "sg:province":"NT",
    "sg:tags":[
        "consultant",
        "taxation"
    ],
    "wof:name":"Accounting & Taxation Service",
    "wof:placetype":"venue"
},
  "geometry": {"coordinates":[133.900756836,-23.7017173767],"type":"Point"}
}