{
  "type": "Feature",
  "properties": {
    "iso:country":"AU",
    "sg:address":"33 Windsor Rd",
    "sg:city":"Kellyville",
    "sg:classifiers":[
        {
            "category":"Fast Food",
            "type":"Food & Drink"
        }
    ],
    "sg:phone":"+61 2 8824 8868",
    "sg:postcode":"2153",
    "sg:province":"NSW",
    "sg:tags":[
        "away",
        "take"
    ],
    "wof:name":"Kellyville Chinese Restaurant",
    "wof:placetype":"venue"
},
  "geometry": {"coordinates":[150.981567383,-33.7456817627],"type":"Point"}
}