{
  "type": "Feature",
  "properties": {
    "addr:full":"24-95 South Rd King Island TAS 7256",
    "addr:housenumber":"24-95",
    "addr:postcode":"7256",
    "addr:street":"South Rd",
    "iso:country":"AU",
    "sg:address":"24-95 South Rd",
    "sg:city":"King Island",
    "sg:classifiers":[
        {
            "category":"Farming",
            "subcategory":"Farm",
            "type":"Manufacturing & Wholesale Goods"
        }
    ],
    "sg:phone":"+61 3 6461 1384",
    "sg:postcode":"7256",
    "sg:province":"TAS",
    "sg:tags":[
        "farmer"
    ],
    "wof:name":"Surprise Bay Pastoral Company Pty Ltd",
    "wof:placetype":"venue"
},
  "geometry": {"coordinates":[143.90359497099999,-39.9571113586],"type":"Point"}
}