{
  "type": "Feature",
  "properties": {
    "iso:country":"AU",
    "sg:address":"294 Forest Rd",
    "sg:city":"Kirrawee",
    "sg:classifiers":[
        {
            "category":"Manufacturing",
            "subcategory":"Rubber & Plastics",
            "type":"Manufacturing & Wholesale Goods"
        }
    ],
    "sg:phone":"+61 2 9524 4837",
    "sg:postcode":"2232",
    "sg:province":"NSW",
    "sg:tags":[
        "equipment",
        "card"
    ],
    "wof:name":"C.R.C. Marketing",
    "wof:placetype":"venue"
},
  "geometry": {"coordinates":[151.07502746599999,-34.040763855],"type":"Point"}
}