{
  "type": "Feature",
  "properties": {
    "addr:full":"14 Todds Rd Lawnton QLD 4501",
    "addr:housenumber":"14",
    "addr:postcode":"4501",
    "addr:street":"Todds Rd",
    "iso:country":"AU",
    "sg:address":"14 Todds Rd",
    "sg:city":"Lawnton",
    "sg:classifiers":[
        {
            "category":"Communications",
            "subcategory":"Film & Video Production",
            "type":"Services"
        }
    ],
    "sg:phone":"+61 7 3285 6696",
    "sg:postcode":"4501",
    "sg:province":"QLD",
    "sg:tags":[
        "dvd",
        "library"
    ],
    "wof:name":"Video 2000",
    "wof:placetype":"venue"
},
  "geometry": {"coordinates":[152.98031616200001,-27.282623291],"type":"Point"}
}