{
  "type": "Feature",
  "properties": {
    "addr:full":"34 Washington St Essendon VIC 3040",
    "addr:housenumber":"34",
    "addr:postcode":"3040",
    "addr:street":"Washington St",
    "iso:country":"AU",
    "sg:address":"34 Washington St",
    "sg:city":"Essendon",
    "sg:classifiers":[
        {
            "category":"Home & Garden",
            "subcategory":"Building Materials",
            "type":"Retail Goods"
        }
    ],
    "sg:phone":"+61 3 9337 0106",
    "sg:postcode":"3040",
    "sg:province":"VIC",
    "sg:tags":[
        "concrete",
        "gutter",
        "kerb"
    ],
    "wof:name":"Kwik Kerb Essendon",
    "wof:placetype":"venue"
},
  "geometry": {"coordinates":[144.910064697,-37.7532196045],"type":"Point"}
}