{
  "type": "Feature",
  "properties": {
    "addr:full":"18- 22 Tempest St Gunnedah NSW 2380",
    "addr:housenumber":"22",
    "addr:postcode":"2380",
    "addr:street":"Tempest St",
    "iso:country":"AU",
    "sg:address":"18- 22 Tempest St",
    "sg:city":"Gunnedah",
    "sg:classifiers":[
        {
            "category":"Autos & Motor Vehicles",
            "subcategory":"Fuel & Gas Station",
            "type":"Retail Goods"
        }
    ],
    "sg:phone":"+61 2 6742 7416",
    "sg:postcode":"2380",
    "sg:province":"NSW",
    "wof:name":"Woolworths Plus Petrol",
    "wof:placetype":"venue"
},
  "geometry": {"coordinates":[150.24856567399999,-30.9760322571],"type":"Point"}
}