{
  "type": "Feature",
  "properties": {
    "addr:full":"12 Garling Rd Blacktown NSW 2148",
    "addr:housenumber":"12",
    "addr:postcode":"2148",
    "addr:street":"Garling Rd",
    "iso:country":"AU",
    "sg:address":"12 Garling Rd",
    "sg:city":"Blacktown",
    "sg:classifiers":[
        {
            "category":"Autos & Motor Vehicles",
            "subcategory":"Auto Supplies",
            "type":"Retail Goods"
        }
    ],
    "sg:phone":"+61 2 9622 1103",
    "sg:postcode":"2148",
    "sg:province":"NSW",
    "sg:tags":[
        "wheel",
        "four",
        "equipment",
        "drive",
        "accessory"
    ],
    "wof:name":"4WD Megastores",
    "wof:placetype":"venue"
},
  "geometry": {"coordinates":[150.912033081,-33.7452583313],"type":"Point"}
}