{
  "type": "Feature",
  "properties": {
    "addr:full":"Unit 2\\\\ 390 Pacific Hwy Belmont North NSW 2280",
    "addr:housenumber":"390",
    "addr:postcode":"2280",
    "addr:street":"Pacific Hwy",
    "iso:country":"AU",
    "sg:address":"Unit 2\\\\ 390 Pacific Hwy",
    "sg:city":"Belmont North",
    "sg:classifiers":[
        {
            "category":"Shopping",
            "subcategory":"Clothing, Apparel, & Fashions",
            "type":"Retail Goods"
        }
    ],
    "sg:phone":"+61 1300 765 514",
    "sg:postcode":"2280",
    "sg:province":"NSW",
    "sg:tags":[
        "uniform"
    ],
    "wof:name":"Tactical Shop",
    "wof:placetype":"venue"
},
  "geometry": {"coordinates":[151.663208008,-33.0238647461],"type":"Point"}
}