{
  "type": "Feature",
  "properties": {
    "addr:full":"5 Linden Pl Doveton VIC 3177",
    "addr:housenumber":"5",
    "addr:postcode":"3177",
    "addr:street":"Linden Pl",
    "iso:country":"AU",
    "sg:address":"5 Linden Pl",
    "sg:city":"Doveton",
    "sg:classifiers":[
        {
            "category":"Retail",
            "subcategory":"Self-service Laundry",
            "type":"Services"
        }
    ],
    "sg:phone":"+61 3 9793 9886",
    "sg:postcode":"3177",
    "sg:province":"VIC",
    "wof:name":"Linden Laundrette",
    "wof:placetype":"venue"
},
  "geometry": {"coordinates":[145.23907470699999,-37.9851341248],"type":"Point"}
}