{
  "type": "Feature",
  "properties": {
    "addr:full":"14 Valley Drv Doonan QLD 4562",
    "addr:housenumber":"14",
    "addr:postcode":"4562",
    "addr:street":"Valley Drv",
    "iso:country":"AU",
    "sg:address":"14 Valley Drv",
    "sg:city":"Doonan",
    "sg:classifiers":[
        {
            "category":"Sports & Exercise",
            "subcategory":"Golf",
            "type":"Entertainment"
        }
    ],
    "sg:phone":"+61 7 5449 1411",
    "sg:postcode":"4562",
    "sg:province":"QLD",
    "sg:tags":[
        "club"
    ],
    "wof:name":"Noosa Valley Country Club",
    "wof:placetype":"venue"
},
  "geometry": {"coordinates":[152.98701477,-26.4425811768],"type":"Point"}
}