{
  "type": "Feature",
  "properties": {
    "iso:country":"AU",
    "sg:address":"32 Cowper St",
    "sg:city":"Sandringham",
    "sg:classifiers":[
        {
            "category":"Real Estate",
            "subcategory":"Architect",
            "type":"Services"
        }
    ],
    "sg:phone":"+61 3 9533 5532",
    "sg:postcode":"3191",
    "sg:province":"VIC",
    "wof:name":"Duggan Jonathan",
    "wof:placetype":"venue"
},
  "geometry": {"coordinates":[145.00889587399999,-37.9564552307],"type":"Point"}
}