{
  "type": "Feature",
  "properties": {
    "iso:country":"AU",
    "sg:address":"76 Woodstock St",
    "sg:city":"Newman",
    "sg:classifiers":[
        {
            "category":"Building & Trades",
            "subcategory":"Construction",
            "type":"Services"
        }
    ],
    "sg:phone":"+61 400 763 253",
    "sg:postcode":"6753",
    "sg:province":"WA",
    "sg:tags":[
        "earth",
        "excavating",
        "moving",
        "contractor"
    ],
    "wof:name":"Tribute Earthmoving & Kwik Kerb",
    "wof:placetype":"venue"
},
  "geometry": {"coordinates":[119.72879791299999,-23.3729076385],"type":"Point"}
}