{
  "type": "Feature",
  "properties": {
    "addr:full":"13 Laffers Rd Belair SA 5052",
    "addr:housenumber":"13",
    "addr:postcode":"5052",
    "addr:street":"Laffers Rd",
    "iso:country":"AU",
    "sg:address":"13 Laffers Rd",
    "sg:city":"Belair",
    "sg:classifiers":[
        {
            "category":"Health Services",
            "subcategory":"Doctor",
            "type":"Services"
        }
    ],
    "sg:phone":"+61 8 8278 0400",
    "sg:postcode":"5052",
    "sg:province":"SA",
    "sg:tags":[
        "medical",
        "practitioner"
    ],
    "wof:name":"Blackwood Hospital",
    "wof:placetype":"venue"
},
  "geometry": {"coordinates":[138.62991299999999,-35.005947],"type":"Point"}
}