{
  "type": "Feature",
  "properties": {
    "addr:full":"76 Beecroft Rd Epping NSW 2121",
    "addr:housenumber":"76",
    "addr:postcode":"2121",
    "addr:street":"Beecroft Rd",
    "iso:country":"AU",
    "sg:address":"76 Beecroft Rd",
    "sg:city":"Epping",
    "sg:classifiers":[
        {
            "category":"Home & Garden",
            "subcategory":"Garden Supply",
            "type":"Retail Goods"
        }
    ],
    "sg:phone":"+61 2 9869 3011",
    "sg:postcode":"2121",
    "sg:province":"NSW",
    "sg:tags":[
        "equipment",
        "hydroponics"
    ],
    "wof:name":"Hydro-Masta",
    "wof:placetype":"venue"
},
  "geometry": {"coordinates":[151.08105468799999,-33.7714233398],"type":"Point"}
}