{
  "type": "Feature",
  "properties": {
    "addr:full":"25 Winton Rd Joondalup WA 6027",
    "addr:housenumber":"25",
    "addr:postcode":"6027",
    "addr:street":"Winton Rd",
    "iso:country":"AU",
    "sg:address":"25 Winton Rd",
    "sg:city":"Joondalup",
    "sg:classifiers":[
        {
            "category":"Recreation",
            "subcategory":"Fishing",
            "type":"Entertainment"
        }
    ],
    "sg:phone":"+61 8 9301 5873",
    "sg:postcode":"6027",
    "sg:province":"WA",
    "sg:tags":[
        "tackle"
    ],
    "wof:name":"Lure Fishing Tackle & Camping Co.The",
    "wof:placetype":"venue"
},
  "geometry": {"coordinates":[115.762809753,-31.7512645721],"type":"Point"}
}