{
  "type": "Feature",
  "properties": {
    "addr:full":"96 Howe St Osborne Park WA 6017",
    "addr:housenumber":"96",
    "addr:postcode":"6017",
    "addr:street":"Howe St",
    "iso:country":"AU",
    "sg:address":"96 Howe St",
    "sg:city":"Osborne Park",
    "sg:classifiers":[
        {
            "category":"Real Estate",
            "subcategory":"Real Estate Agent",
            "type":"Services"
        }
    ],
    "sg:phone":"+61 8 9443 1234",
    "sg:postcode":"6017",
    "sg:province":"WA",
    "sg:tags":[
        "handyman's",
        "equipment",
        "hire",
        "builders",
        "contractor"
    ],
    "wof:name":"Electric Hire",
    "wof:placetype":"venue"
},
  "geometry": {"coordinates":[115.815742493,-31.9086093903],"type":"Point"}
}