{
  "type": "Feature",
  "properties": {
    "addr:full":"14 Evans Drv Benowa QLD 4217",
    "addr:housenumber":"14",
    "addr:postcode":"4217",
    "addr:street":"Evans Drv",
    "iso:country":"AU",
    "sg:address":"14 Evans Drv",
    "sg:city":"Benowa",
    "sg:classifiers":[
        {
            "category":"Utilities",
            "subcategory":"Electric",
            "type":"Services"
        }
    ],
    "sg:phone":"+61 417 334 158",
    "sg:postcode":"4217",
    "sg:province":"QLD",
    "sg:tags":[
        "electrical",
        "contractor"
    ],
    "wof:name":"Dav Contracting Pty Ltd",
    "wof:placetype":"venue"
},
  "geometry": {"coordinates":[153.387283325,-28.0007705688],"type":"Point"}
}