{
  "type": "Feature",
  "properties": {
    "addr:full":"95 Sladen St Cranbourne VIC 3977",
    "addr:housenumber":"95",
    "addr:postcode":"3977",
    "addr:street":"Sladen St",
    "iso:country":"AU",
    "sg:address":"95 Sladen St",
    "sg:city":"Cranbourne",
    "sg:classifiers":[
        {
            "category":"Utilities",
            "subcategory":"Natural Gas",
            "type":"Services"
        }
    ],
    "sg:phone":"+61 418 325 652",
    "sg:postcode":"3977",
    "sg:province":"VIC",
    "sg:tags":[
        "solid",
        "plasterer"
    ],
    "wof:name":"Jessop Maurice",
    "wof:placetype":"venue"
},
  "geometry": {"coordinates":[145.275222778,-38.1118621826],"type":"Point"}
}