{
  "type": "Feature",
  "properties": {
    "addr:full":"4 Doolan Crt Rowville VIC 3178",
    "addr:housenumber":"4",
    "addr:postcode":"3178",
    "addr:street":"Doolan Crt",
    "iso:country":"AU",
    "sg:address":"4 Doolan Crt",
    "sg:city":"Rowville",
    "sg:classifiers":[
        {
            "category":"Building & Trades",
            "subcategory":"Locksmith",
            "type":"Services"
        }
    ],
    "sg:phone":"+61 3 9755 5053",
    "sg:postcode":"3178",
    "sg:province":"VIC",
    "sg:tags":[
        "lock"
    ],
    "wof:name":"Wantirna Locksmiths",
    "wof:placetype":"venue"
},
  "geometry": {"coordinates":[145.25654602,-37.9270324707],"type":"Point"}
}