{
  "type": "Feature",
  "properties": {
    "addr:full":"1 Rathdowne St Carlton VIC 3053",
    "addr:housenumber":"1",
    "addr:postcode":"3053",
    "addr:street":"Rathdowne St",
    "iso:country":"AU",
    "sg:address":"1 Rathdowne St",
    "sg:city":"Carlton",
    "sg:classifiers":[
        {
            "category":"Organizations",
            "subcategory":"Membership Organization",
            "type":"Services"
        }
    ],
    "sg:phone":"+61 13 18 48",
    "sg:postcode":"3053",
    "sg:province":"VIC",
    "sg:tags":[
        "support",
        "health",
        "organisation"
    ],
    "wof:name":"Quitline",
    "wof:placetype":"venue"
},
  "geometry": {"coordinates":[144.96864318900001,-37.8072471619],"type":"Point"}
}