{
  "type": "Feature",
  "properties": {
    "addr:full":"Godley Pl Stanhope VIC 3623",
    "addr:postcode":"3623",
    "iso:country":"AU",
    "sg:address":"Godley Pl",
    "sg:city":"Stanhope",
    "sg:classifiers":[
        {
            "category":"Organizations",
            "subcategory":"Professional Association",
            "type":"Services"
        }
    ],
    "sg:phone":"+61 3 5857 2784",
    "sg:postcode":"3623",
    "sg:province":"VIC",
    "sg:tags":[
        "rural",
        "organisation",
        "production",
        "primary"
    ],
    "wof:name":"Goulburn Valley Dairy & Machinery Field Days",
    "wof:placetype":"venue"
},
  "geometry": {"coordinates":[144.984375,-36.4465293884],"type":"Point"}
}