{
  "type": "Feature",
  "properties": {
    "addr:full":"Unit 26/ 70 Roberts St East Osborne Park WA 6017",
    "addr:housenumber":"/ 70",
    "addr:postcode":"6017",
    "addr:street":"Roberts St East",
    "iso:country":"AU",
    "sg:address":"Unit 26/ 70 Roberts St East",
    "sg:city":"Osborne Park",
    "sg:classifiers":[
        {
            "category":"Professional",
            "subcategory":"Accounting & Tax Preparation",
            "type":"Services"
        }
    ],
    "sg:phone":"+61 8 9444 2885",
    "sg:postcode":"6017",
    "sg:province":"WA",
    "sg:tags":[
        "accountant",
        "auditor"
    ],
    "wof:name":"Versaci's",
    "wof:placetype":"venue"
},
  "geometry": {"coordinates":[115.824462891,-31.9079647064],"type":"Point"}
}