{
  "type": "Feature",
  "properties": {
    "iso:country":"AU",
    "sg:address":"1 Keith Campbell Crt",
    "sg:city":"Scoresby",
    "sg:classifiers":[
        {
            "category":"Food & Beverages",
            "subcategory":"Supermarket",
            "type":"Retail Goods"
        }
    ],
    "sg:phone":"+61 3 9839 9111",
    "sg:postcode":"3179",
    "sg:province":"VIC",
    "sg:tags":[
        "grocery",
        "store"
    ],
    "wof:name":"Bi-Lo Pty Ltd",
    "wof:placetype":"venue"
},
  "geometry": {"coordinates":[145.21795654300001,-37.9017715454],"type":"Point"}
}