{
  "type": "Feature",
  "properties": {
    "addr:full":"Shop 4 Lakelands Shopping Centre 31 Moorhen Drive Yangebup WA 6164",
    "addr:housenumber":"shop 4;31",
    "addr:postcode":"6164",
    "addr:street":"Lakelands Shopping;Moorhen Drive",
    "iso:country":"AU",
    "sg:address":"Shop 4 Lakelands Shopping Centre 31",
    "sg:city":"Moorhen Drive Yangebup",
    "sg:classifiers":[
        {
            "category":"Health Services",
            "subcategory":"Dentist",
            "type":"Services"
        }
    ],
    "sg:phone":"+61 8 9417 9888",
    "sg:postcode":"6164",
    "sg:province":"WA",
    "wof:name":"Cockburn City Dental",
    "wof:placetype":"venue"
},
  "geometry": {"coordinates":[115.81783299999999,-32.119915],"type":"Point"}
}