{
  "type": "Feature",
  "properties": {
    "addr:full":"48 Sydney St Mogo NSW 2536",
    "addr:housenumber":"48",
    "addr:postcode":"2536",
    "addr:street":"Sydney St",
    "iso:country":"AU",
    "sg:address":"48 Sydney St",
    "sg:city":"Mogo",
    "sg:classifiers":[
        {
            "category":"Shopping",
            "subcategory":"Crafts & Fabrics",
            "type":"Retail Goods"
        }
    ],
    "sg:phone":"+61 2 4474 3492",
    "sg:postcode":"2536",
    "sg:province":"NSW",
    "sg:tags":[
        "supply"
    ],
    "wof:name":"Mogo Trading Post",
    "wof:placetype":"venue"
},
  "geometry": {"coordinates":[150.14146423299999,-35.7847518921],"type":"Point"}
}