{
  "type": "Feature",
  "properties": {
    "addr:full":"15 Royal St Kenwick WA 6107",
    "addr:housenumber":"15",
    "addr:postcode":"6107",
    "addr:street":"Royal St",
    "iso:country":"AU",
    "sg:address":"15 Royal St",
    "sg:city":"Kenwick",
    "sg:classifiers":[
        {
            "category":"Retail",
            "subcategory":"Veterinary Services",
            "type":"Services"
        }
    ],
    "sg:phone":"+61 8 9459 7999",
    "sg:postcode":"6107",
    "sg:province":"WA",
    "sg:tags":[
        "surgeon"
    ],
    "wof:name":"Kenwick Veterinary Hospital",
    "wof:placetype":"venue"
},
  "geometry": {"coordinates":[115.96790313699999,-32.0379142761],"type":"Point"}
}