{
  "type": "Feature",
  "properties": {
    "addr:full":"Guava Way Halls Head WA 6210",
    "addr:postcode":"6210",
    "addr:street":"Guava Way",
    "iso:country":"AU",
    "sg:address":"Guava Way",
    "sg:city":"Halls Head",
    "sg:classifiers":[
        {
            "category":"Fast Food",
            "type":"Food & Drink"
        }
    ],
    "sg:phone":"+61 8 9581 2222",
    "sg:postcode":"6210",
    "sg:province":"WA",
    "sg:tags":[
        "away",
        "take"
    ],
    "wof:name":"Red Rooster",
    "wof:placetype":"venue"
},
  "geometry": {"coordinates":[115.700844,-32.548771],"type":"Point"}
}