{
  "type": "Feature",
  "properties": {
    "addr:full":"4 Smith St Merbein VIC 3505",
    "addr:housenumber":"4",
    "addr:postcode":"3505",
    "addr:street":"Smith St",
    "iso:country":"AU",
    "sg:address":"4 Smith St",
    "sg:city":"Merbein",
    "sg:classifiers":[
        {
            "category":"Personal",
            "subcategory":"Massage",
            "type":"Services"
        }
    ],
    "sg:phone":"+61 3 5025 3181",
    "sg:postcode":"3505",
    "sg:province":"VIC",
    "sg:tags":[
        "therapy"
    ],
    "wof:name":"Hopkins Kara",
    "wof:placetype":"venue"
},
  "geometry": {"coordinates":[142.056442261,-34.1675796509],"type":"Point"}
}