{
  "type": "Feature",
  "properties": {
    "addr:full":"Level 3 178 St Georges Tce Perth WA 6000",
    "addr:housenumber":"178",
    "addr:postcode":"6000",
    "addr:street":"St Georges Tce",
    "iso:country":"AU",
    "sg:address":"Level 3 178 St Georges Tce",
    "sg:city":"Perth",
    "sg:classifiers":[
        {
            "category":"Travel",
            "subcategory":"Travel Agent",
            "type":"Entertainment"
        }
    ],
    "sg:phone":"+61 8 9442 6000",
    "sg:postcode":"6000",
    "sg:province":"WA",
    "sg:tags":[
        "consultant"
    ],
    "wof:name":"Consolidated Travel Pty Ltd",
    "wof:placetype":"venue"
},
  "geometry": {"coordinates":[115.853660584,-31.9536056519],"type":"Point"}
}