{
  "type": "Feature",
  "properties": {
    "iso:country":"AU",
    "sg:address":"155 Carlisle St",
    "sg:city":"Balaclava",
    "sg:classifiers":[
        {
            "category":"Shopping",
            "subcategory":"Jewelry",
            "type":"Retail Goods"
        }
    ],
    "sg:phone":"+61 3 9531 1025",
    "sg:postcode":"3183",
    "sg:province":"VIC",
    "sg:tags":[
        "fashion",
        "jewellery"
    ],
    "wof:name":"Amber Jewellery Distributors",
    "wof:placetype":"venue"
},
  "geometry": {"coordinates":[144.992019653,-37.8686981201],"type":"Point"}
}