{
  "type": "Feature",
  "properties": {
    "iso:country":"AU",
    "sg:address":"71 Stead St",
    "sg:city":"South Melbourne",
    "sg:classifiers":[
        {
            "category":"Professional",
            "subcategory":"Computer Services",
            "type":"Services"
        }
    ],
    "sg:phone":"+61 3 9699 1999",
    "sg:postcode":"3205",
    "sg:province":"VIC",
    "sg:tags":[
        "package",
        "software"
    ],
    "wof:name":"Taylor & Stewart Computer Services Pty Ltd",
    "wof:placetype":"venue"
},
  "geometry": {"coordinates":[144.969482,-37.836208],"type":"Point"}
}