{
  "type": "Feature",
  "properties": {
    "addr:full":"304 Flinders Lane Melbourne VIC 3000",
    "addr:housenumber":"304",
    "addr:postcode":"3000",
    "addr:street":"Flinders Lane",
    "iso:country":"AU",
    "sg:address":"304 Flinders Lane",
    "sg:city":"Melbourne",
    "sg:classifiers":[
        {
            "category":"Personal",
            "subcategory":"Beauty Salon",
            "type":"Services"
        }
    ],
    "sg:phone":"+61 3 9614 0400",
    "sg:postcode":"3000",
    "sg:province":"VIC",
    "sg:tags":[
        "hairdresser"
    ],
    "sg:website":"http://www.clairefrancoise.com.au",
    "wof:name":"Claire-Fran\ufffdoise Salon",
    "wof:placetype":"venue"
},
  "geometry": {"coordinates":[144.963943481,-37.8172302246],"type":"Point"}
}