{
  "type": "Feature",
  "properties": {
    "iso:country":"AU",
    "sg:address":"10 Ferngully St",
    "sg:city":"White Rock",
    "sg:classifiers":[
        {
            "category":"Real Estate",
            "subcategory":"Real Estate Agent",
            "type":"Services"
        }
    ],
    "sg:phone":"+61 402 818 379",
    "sg:postcode":"4868",
    "sg:province":"QLD",
    "sg:tags":[
        "handyman's",
        "equipment",
        "hire",
        "builders",
        "contractor"
    ],
    "wof:name":"Dynamite Earthmoving",
    "wof:placetype":"venue"
},
  "geometry": {"coordinates":[145.74627685600001,-16.9906272888],"type":"Point"}
}