{
  "type": "Feature",
  "properties": {
    "addr:full":"RMB 5325 Bona-Vista Via Warragul Warragul VIC 3820",
    "addr:postcode":"3820",
    "addr:street":"Via Warragul",
    "iso:country":"AU",
    "sg:address":"RMB 5325",
    "sg:city":"Bona-Vista Via Warragul Warragul",
    "sg:classifiers":[
        {
            "category":"Retail",
            "subcategory":"Laundry & Dry Cleaning",
            "type":"Services"
        }
    ],
    "sg:phone":"+61 3 5627 8210",
    "sg:postcode":"3820",
    "sg:province":"VIC",
    "sg:tags":[
        "truck",
        "tip",
        "contractor"
    ],
    "wof:name":"Kent R V & Son",
    "wof:placetype":"venue"
},
  "geometry": {"coordinates":[145.932098,-38.173306],"type":"Point"}
}