{
  "type": "Feature",
  "properties": {
    "iso:country":"AU",
    "sg:address":"32 Tallyan Point Rd",
    "sg:city":"Basin View",
    "sg:classifiers":[
        {
            "category":"Utilities",
            "subcategory":"Electric",
            "type":"Services"
        }
    ],
    "sg:phone":"+61 430 379 462",
    "sg:postcode":"2540",
    "sg:province":"NSW",
    "sg:tags":[
        "electrical",
        "contractor"
    ],
    "wof:name":"Jon Lee Electrical",
    "wof:placetype":"venue"
},
  "geometry": {"coordinates":[150.56477355999999,-35.0921783447],"type":"Point"}
}