{
  "type": "Feature",
  "properties": {
    "iso:country":"AU",
    "sg:address":"382 Somerville Rd",
    "sg:city":"Footscray West",
    "sg:classifiers":[
        {
            "category":"Professional",
            "subcategory":"Engineering",
            "type":"Services"
        }
    ],
    "sg:phone":"+61 3 9314 7597",
    "sg:postcode":"3012",
    "sg:province":"VIC",
    "sg:tags":[
        "diesel",
        "engineer"
    ],
    "wof:name":"Da-Vale Diesel Injection Service Pty Ltd",
    "wof:placetype":"venue"
},
  "geometry": {"coordinates":[144.86544799800001,-37.8105964661],"type":"Point"}
}