{
  "type": "Feature",
  "properties": {
    "addr:full":"3 Cambourne Ave St Ives NSW 2075",
    "addr:housenumber":"3",
    "addr:postcode":"2075",
    "addr:street":"Cambourne Ave",
    "iso:country":"AU",
    "sg:address":"3 Cambourne Ave",
    "sg:city":"St Ives",
    "sg:classifiers":[
        {
            "category":"Professional",
            "subcategory":"Accounting & Tax Preparation",
            "type":"Services"
        }
    ],
    "sg:phone":"+61 2 9983 9682",
    "sg:postcode":"2075",
    "sg:province":"NSW",
    "sg:tags":[
        "accountant",
        "auditor"
    ],
    "wof:name":"I.G. Petty",
    "wof:placetype":"venue"
},
  "geometry": {"coordinates":[151.179153442,-33.7186431885],"type":"Point"}
}