{
  "type": "Feature",
  "properties": {
    "iso:country":"AU",
    "sg:address":"U1083/ 80 Lower Gay Tce",
    "sg:city":"Caloundra",
    "sg:classifiers":[
        {
            "category":"Real Estate",
            "subcategory":"Real Estate Agent",
            "type":"Services"
        }
    ],
    "sg:phone":"+61 7 5491 1889",
    "sg:postcode":"4551",
    "sg:province":"QLD",
    "wof:name":"Kangaroo Point Real Estate",
    "wof:placetype":"venue"
},
  "geometry": {"coordinates":[153.13548278799999,-26.8059997559],"type":"Point"}
}