{
  "type": "Feature",
  "properties": {
    "iso:country":"AU",
    "sg:address":"9 Roper St",
    "sg:city":"Moorabbin",
    "sg:classifiers":[
        {
            "category":"Retail",
            "subcategory":"Auto Repair",
            "type":"Services"
        }
    ],
    "sg:phone":"+61 3 9553 5975",
    "sg:postcode":"3189",
    "sg:province":"VIC",
    "sg:tags":[
        "beater",
        "painter",
        "panel"
    ],
    "wof:name":"Damage Body Works",
    "wof:placetype":"venue"
},
  "geometry": {"coordinates":[145.05563354500001,-37.9451141357],"type":"Point"}
}