{
  "type": "Feature",
  "properties": {
    "iso:country":"AU",
    "sg:address":"375 Sussex St",
    "sg:city":"Sydney",
    "sg:classifiers":[
        {
            "category":"Cafe",
            "type":"Food & Drink"
        }
    ],
    "sg:phone":"+61 2 9267 1215",
    "sg:postcode":"2000",
    "sg:province":"NSW",
    "wof:name":"Fitzys & Friends",
    "wof:placetype":"venue"
},
  "geometry": {"coordinates":[151.20443725600001,-33.8765983582],"type":"Point"}
}