{
  "type": "Feature",
  "properties": {
    "iso:country":"AU",
    "sg:address":"1 Bald St",
    "sg:city":"Smithfield Plains",
    "sg:classifiers":[
        {
            "category":"Education",
            "subcategory":"Kindergarten",
            "type":"Public Place"
        }
    ],
    "sg:phone":"+61 8 8254 6848",
    "sg:postcode":"5114",
    "sg:province":"SA",
    "sg:tags":[
        "pre-schools"
    ],
    "wof:name":"Smithfield Plains Kindergarten",
    "wof:placetype":"venue"
},
  "geometry": {"coordinates":[138.678863525,-34.6766815186],"type":"Point"}
}