{
  "type": "Feature",
  "properties": {
    "iso:country":"AU",
    "sg:address":"1st Floor 443 Magill Rd",
    "sg:city":"St Morris",
    "sg:classifiers":[
        {
            "category":"Sports & Exercise",
            "subcategory":"Gym",
            "type":"Entertainment"
        }
    ],
    "sg:phone":"+61 8 8364 3264",
    "sg:postcode":"5068",
    "sg:province":"SA",
    "sg:tags":[
        "health",
        "fitness"
    ],
    "wof:name":"Contours St Morris",
    "wof:placetype":"venue"
},
  "geometry": {"coordinates":[138.65733337399999,-34.9138298035],"type":"Point"}
}