{
  "type": "Feature",
  "properties": {
    "addr:full":"Fcty 4 / 28 Johnston Crt Dandenong South VIC 3175",
    "addr:housenumber":"/ 28",
    "addr:postcode":"3175",
    "addr:street":"Johnston Crt",
    "iso:country":"AU",
    "sg:address":"Fcty 4 / 28 Johnston Crt",
    "sg:city":"Dandenong South",
    "sg:classifiers":[
        {
            "category":"Manufacturing",
            "subcategory":"Metals",
            "type":"Manufacturing & Wholesale Goods"
        }
    ],
    "sg:phone":"+61 3 9794 8879",
    "sg:postcode":"3175",
    "sg:province":"VIC",
    "sg:tags":[
        "wholesaler",
        "aluminium",
        "mfrs"
    ],
    "wof:name":"A B Aluminium Supplies",
    "wof:placetype":"venue"
},
  "geometry": {"coordinates":[145.22039794899999,-38.0068893433],"type":"Point"}
}