{
  "type": "Feature",
  "properties": {
    "addr:full":"Mount Dandenong Tourist Rd Kalorama VIC 3766",
    "addr:postcode":"3766",
    "addr:street":"Tourist Rd",
    "iso:country":"AU",
    "sg:address":"Mount Dandenong Tourist Rd",
    "sg:city":"Kalorama",
    "sg:classifiers":[
        {
            "category":"Food & Beverages",
            "subcategory":"Groceries & Convenience Stores",
            "type":"Retail Goods"
        }
    ],
    "sg:phone":"+61 3 9728 1000",
    "sg:postcode":"3766",
    "sg:province":"VIC",
    "wof:name":"Silvandale General Store & Tearoom",
    "wof:placetype":"venue"
},
  "geometry": {"coordinates":[145.36671447800001,-37.8179512024],"type":"Point"}
}