{
  "type": "Feature",
  "properties": {
    "addr:full":"1001a Ipswich Rd Moorooka QLD 4105",
    "addr:housenumber":"1001a",
    "addr:postcode":"4105",
    "addr:street":"Ipswich Rd",
    "iso:country":"AU",
    "sg:address":"1001a Ipswich Rd",
    "sg:city":"Moorooka",
    "sg:classifiers":[
        {
            "category":"Personal",
            "subcategory":"Tattoo Parlor",
            "type":"Services"
        }
    ],
    "sg:phone":"+61 7 3848 9400",
    "sg:postcode":"4105",
    "sg:province":"QLD",
    "sg:tags":[
        "tattooing"
    ],
    "wof:name":"Tattooed Warrior Tattoo Studio",
    "wof:placetype":"venue"
},
  "geometry": {"coordinates":[153.01805114699999,-27.5303096771],"type":"Point"}
}