{
  "type": "Feature",
  "properties": {
    "addr:full":"63 Lygon St Brunswick East VIC 3057",
    "addr:housenumber":"63",
    "addr:postcode":"3057",
    "addr:street":"Lygon St",
    "iso:country":"AU",
    "sg:address":"63 Lygon St",
    "sg:city":"Brunswick East",
    "sg:classifiers":[
        {
            "category":"Professional",
            "subcategory":"Computer Services",
            "type":"Services"
        }
    ],
    "sg:phone":"+61 3 8317 0356",
    "sg:postcode":"3057",
    "sg:province":"VIC",
    "sg:tags":[
        "package",
        "software"
    ],
    "wof:name":"Redgum",
    "wof:placetype":"venue"
},
  "geometry": {"coordinates":[144.970703125,-37.7771186829],"type":"Point"}
}