{
  "type": "Feature",
  "properties": {
    "iso:country":"AU",
    "sg:address":"1106 Nepean Hwy",
    "sg:city":"Cheltenham",
    "sg:classifiers":[
        {
            "category":"Health Services",
            "subcategory":"Health Practitioner",
            "type":"Services"
        }
    ],
    "sg:phone":"+61 3 9555 6678",
    "sg:postcode":"3192",
    "sg:province":"VIC",
    "sg:tags":[
        "acupuncture"
    ],
    "wof:name":"Venn Juanita",
    "wof:placetype":"venue"
},
  "geometry": {"coordinates":[145.045196533,-37.9485435486],"type":"Point"}
}