{
  "type": "Feature",
  "properties": {
    "addr:full":"84 Glen Eira Rd Ripponlea VIC 3185",
    "addr:housenumber":"84",
    "addr:postcode":"3185",
    "addr:street":"Glen Eira Rd",
    "iso:country":"AU",
    "sg:address":"84 Glen Eira Rd",
    "sg:city":"Ripponlea",
    "sg:classifiers":[
        {
            "category":"Professional",
            "subcategory":"Engineering",
            "type":"Services"
        }
    ],
    "sg:phone":"+61 3 9527 5086",
    "sg:postcode":"3185",
    "sg:province":"VIC",
    "sg:tags":[
        "consulting",
        "engineer"
    ],
    "wof:name":"Designtronics",
    "wof:placetype":"venue"
},
  "geometry": {"coordinates":[144.997848511,-37.8767471313],"type":"Point"}
}