{
  "type": "Feature",
  "properties": {
    "addr:full":"4 Flagstaff Ave Robina QLD 4226",
    "addr:housenumber":"4",
    "addr:postcode":"4226",
    "addr:street":"Flagstaff Ave",
    "iso:country":"AU",
    "sg:address":"4 Flagstaff Ave",
    "sg:city":"Robina",
    "sg:classifiers":[
        {
            "category":"Building & Trades",
            "subcategory":"Construction",
            "type":"Services"
        }
    ],
    "sg:phone":"+61 408 450 083",
    "sg:postcode":"4226",
    "sg:province":"QLD",
    "sg:tags":[
        "decking",
        "contractor"
    ],
    "wof:name":"D&#039;n&#039;A Carpentry Services",
    "wof:placetype":"venue"
},
  "geometry": {"coordinates":[153.38862609899999,-28.0702857971],"type":"Point"}
}