{
  "type": "Feature",
  "properties": {
    "iso:country":"AU",
    "sg:address":"U1/ 48 Export Drv",
    "sg:city":"Molendinar",
    "sg:classifiers":[
        {
            "category":"Building & Trades",
            "subcategory":"Construction",
            "type":"Services"
        }
    ],
    "sg:phone":"+61 7 5594 6499",
    "sg:postcode":"4214",
    "sg:province":"QLD",
    "sg:tags":[
        "contractor"
    ],
    "wof:name":"Davies Projects Pty Ltd",
    "wof:placetype":"venue"
},
  "geometry": {"coordinates":[153.35995483400001,-27.9664764404],"type":"Point"}
}