{
  "type": "Feature",
  "properties": {
    "addr:full":"78 Central Ave Oak Flats NSW 2529",
    "addr:housenumber":"78",
    "addr:postcode":"2529",
    "addr:street":"Central Ave Oak Flats",
    "iso:country":"AU",
    "sg:address":"78 Central Ave",
    "sg:city":"Oak Flats",
    "sg:classifiers":[
        {
            "category":"Banks & Credit Unions",
            "subcategory":"Bank",
            "type":"Services"
        }
    ],
    "sg:phone":"+61 2 4256 9511",
    "sg:postcode":"2529",
    "sg:province":"NSW",
    "wof:name":"Oak Flats Community Bank Branch of Bendigo Bank",
    "wof:placetype":"venue"
},
  "geometry": {"coordinates":[150.819259644,-34.5630378723],"type":"Point"}
}