{
  "type": "Feature",
  "properties": {
    "addr:full":"Suite 8, 9 Coolibah Drv Greenwood WA 6024",
    "addr:housenumber":"9",
    "addr:postcode":"6024",
    "addr:street":"Coolibah Drv",
    "iso:country":"AU",
    "sg:address":"Suite 8, 9 Coolibah Drv",
    "sg:city":"Greenwood",
    "sg:classifiers":[
        {
            "category":"Travel",
            "subcategory":"Travel Agent",
            "type":"Entertainment"
        }
    ],
    "sg:phone":"+61 1800 625 000",
    "sg:postcode":"6024",
    "sg:province":"WA",
    "sg:tags":[
        "consultant"
    ],
    "wof:name":"Four Corners Travel",
    "wof:placetype":"venue"
},
  "geometry": {"coordinates":[115.80248260499999,-31.8328342438],"type":"Point"}
}