{
  "type": "Feature",
  "properties": {
    "addr:full":"9 Miller St Fitzroy North VIC 3068",
    "addr:housenumber":"9",
    "addr:postcode":"3068",
    "addr:street":"Miller St",
    "iso:country":"AU",
    "sg:address":"9 Miller St",
    "sg:city":"Fitzroy North",
    "sg:classifiers":[
        {
            "category":"Professional",
            "subcategory":"Detective & Security Services",
            "type":"Services"
        }
    ],
    "sg:phone":"+61 3 9486 8708",
    "sg:postcode":"3068",
    "sg:province":"VIC",
    "sg:tags":[
        "consultant",
        "system"
    ],
    "wof:name":"Roka Security",
    "wof:placetype":"venue"
},
  "geometry": {"coordinates":[144.97920227,-37.7761535645],"type":"Point"}
}