{
  "type": "Feature",
  "properties": {
    "addr:full":"Shp7/ 9 Bradfield St Leumeah NSW 2560",
    "addr:housenumber":"9",
    "addr:postcode":"2560",
    "addr:street":"Bradfield St",
    "iso:country":"AU",
    "sg:address":"Shp7/ 9 Bradfield St",
    "sg:city":"Leumeah",
    "sg:classifiers":[
        {
            "category":"Fast Food",
            "type":"Food & Drink"
        }
    ],
    "sg:phone":"+61 2 4626 7768",
    "sg:postcode":"2560",
    "sg:province":"NSW",
    "sg:tags":[
        "away",
        "take"
    ],
    "wof:name":"Shane's Place",
    "wof:placetype":"venue"
},
  "geometry": {"coordinates":[150.838058472,-34.0574188232],"type":"Point"}
}