{
  "type": "Feature",
  "properties": {
    "iso:country":"AU",
    "sg:address":"26 Neridah Ave",
    "sg:city":"Belrose",
    "sg:classifiers":[
        {
            "category":"Professional",
            "subcategory":"Management & Consulting",
            "type":"Services"
        }
    ],
    "sg:phone":"+61 2 9975 5689",
    "sg:postcode":"2085",
    "sg:province":"NSW",
    "sg:tags":[
        "consultant"
    ],
    "wof:name":"Beauregard Consulting Services Pty Ltd",
    "wof:placetype":"venue"
},
  "geometry": {"coordinates":[151.21954345699999,-33.7265281677],"type":"Point"}
}