{
  "type": "Feature",
  "properties": {
    "iso:country":"AU",
    "sg:address":"58 Sea Pde",
    "sg:city":"Port MacDonnell",
    "sg:classifiers":[
        {
            "category":"Real Estate",
            "subcategory":"Real Estate Agent",
            "type":"Services"
        }
    ],
    "sg:phone":"+61 8 8738 2133",
    "sg:postcode":"5291",
    "sg:province":"SA",
    "wof:name":"Malseeds.Com.Au",
    "wof:placetype":"venue"
},
  "geometry": {"coordinates":[140.700226,-38.054153],"type":"Point"}
}