{
  "type": "Feature",
  "properties": {
    "iso:country":"AU",
    "sg:address":"22 Moss St",
    "sg:city":"Springwood",
    "sg:classifiers":[
        {
            "category":"Shopping",
            "subcategory":"Computers & Home Electronics",
            "type":"Retail Goods"
        }
    ],
    "sg:phone":"+61 7 3299 5011",
    "sg:postcode":"4127",
    "sg:province":"QLD",
    "sg:tags":[
        "equipment",
        "supply"
    ],
    "wof:name":"CY Computermart",
    "wof:placetype":"venue"
},
  "geometry": {"coordinates":[153.119415283,-27.6240234375],"type":"Point"}
}