{
  "type": "Feature",
  "properties": {
    "iso:country":"AU",
    "sg:address":"Dixon St",
    "sg:city":"Stratford",
    "sg:classifiers":[
        {
            "category":"Education",
            "subcategory":"Kindergarten",
            "type":"Public Place"
        }
    ],
    "sg:phone":"+61 3 5145 6446",
    "sg:postcode":"3862",
    "sg:province":"VIC",
    "sg:tags":[
        "pre-schools"
    ],
    "wof:name":"Stratford Kindergarten",
    "wof:placetype":"venue"
},
  "geometry": {"coordinates":[147.080474853,-37.9673461914],"type":"Point"}
}