{
  "type": "Feature",
  "properties": {
    "addr:full":"8 Pecks Rd North Richmond NSW 2754",
    "addr:housenumber":"8",
    "addr:postcode":"2754",
    "addr:street":"Pecks Rd",
    "iso:country":"AU",
    "sg:address":"8 Pecks Rd",
    "sg:city":"North Richmond",
    "sg:classifiers":[
        {
            "category":"Building & Trades",
            "subcategory":"Pest Control",
            "type":"Services"
        }
    ],
    "sg:phone":"+61 2 4571 3035",
    "sg:postcode":"2754",
    "sg:province":"NSW",
    "wof:name":"Ponderosa Pest Control",
    "wof:placetype":"venue"
},
  "geometry": {"coordinates":[150.713012695,-33.583240509],"type":"Point"}
}