{
  "type": "Feature",
  "properties": {
    "addr:full":"19a Hinkler Rd Mordialloc VIC 3195",
    "addr:housenumber":"19a",
    "addr:postcode":"3195",
    "addr:street":"Hinkler Rd",
    "iso:country":"AU",
    "sg:address":"19a Hinkler Rd",
    "sg:city":"Mordialloc",
    "sg:classifiers":[
        {
            "category":"Professional",
            "subcategory":"Engineering",
            "type":"Services"
        }
    ],
    "sg:phone":"+61 3 9587 2566",
    "sg:postcode":"3195",
    "sg:province":"VIC",
    "sg:tags":[
        "engineer"
    ],
    "wof:name":"Clydesdale Manufacturing Pty Ltd",
    "wof:placetype":"venue"
},
  "geometry": {"coordinates":[145.09889221200001,-37.9883728027],"type":"Point"}
}