{
  "type": "Feature",
  "properties": {
    "iso:country":"AU",
    "sg:address":"128 Warrimoo Ave St",
    "sg:city":"Ives",
    "sg:classifiers":[
        {
            "category":"Building & Trades",
            "subcategory":"Construction",
            "type":"Services"
        }
    ],
    "sg:phone":"+61 2 9488 8121",
    "sg:postcode":"2075",
    "sg:province":"NSW",
    "sg:tags":[
        "joiner",
        "carpenter"
    ],
    "wof:name":"John Pacetta",
    "wof:placetype":"venue"
},
  "geometry": {"coordinates":[151.15934753400001,-33.7142944336],"type":"Point"}
}