{
  "type": "Feature",
  "properties": {
    "iso:country":"AU",
    "sg:address":"C/- Post Office Fitzroy Crossing 6765",
    "sg:city":"Halls Creek",
    "sg:classifiers":[
        {
            "category":"Building & Trades",
            "subcategory":"Landscaping Services",
            "type":"Services"
        }
    ],
    "sg:phone":"+61 8 9168 8898",
    "sg:postcode":"6770",
    "sg:province":"WA",
    "sg:tags":[
        "grazier"
    ],
    "wof:name":"Madigan Lakes Station",
    "wof:placetype":"venue"
},
  "geometry": {"coordinates":[127.66699218799999,-18.2247505188],"type":"Point"}
}