{
  "type": "Feature",
  "properties": {
    "addr:full":"3 Alexandra Pde Collingwood VIC 3066",
    "addr:housenumber":"3",
    "addr:postcode":"3066",
    "addr:street":"Alexandra Pde",
    "iso:country":"AU",
    "sg:address":"3 Alexandra Pde",
    "sg:city":"Collingwood",
    "sg:classifiers":[
        {
            "category":"Professional",
            "subcategory":"Accounting & Tax Preparation",
            "type":"Services"
        }
    ],
    "sg:phone":"+61 3 9417 0851",
    "sg:postcode":"3066",
    "sg:province":"VIC",
    "sg:tags":[
        "accountant",
        "auditor"
    ],
    "wof:name":"Hoffman & Stops",
    "wof:placetype":"venue"
},
  "geometry": {"coordinates":[144.98541259800001,-37.7942123413],"type":"Point"}
}