{
  "type": "Feature",
  "properties": {
    "addr:full":"Shop 1112A, Westfield Parramatta Parramatta NSW 2150",
    "addr:housenumber":"1112a",
    "addr:postcode":"2150",
    "addr:street":"Westfield Parramatta",
    "iso:country":"AU",
    "sg:address":"Shop 1112A, Westfield Parramatta",
    "sg:city":"Parramatta",
    "sg:classifiers":[
        {
            "category":"Shopping",
            "subcategory":"Bicycles & Sporting Goods",
            "type":"Retail Goods"
        }
    ],
    "sg:phone":"+61 2 9635 9315",
    "sg:postcode":"2150",
    "sg:province":"NSW",
    "sg:tags":[
        "dance",
        "accessory",
        "wear",
        "supply"
    ],
    "wof:name":"Bloch Australia",
    "wof:placetype":"venue"
},
  "geometry": {"coordinates":[151.115325928,-33.9243507385],"type":"Point"}
}