{
  "type": "Feature",
  "properties": {
    "addr:full":"Cooks Rd Glenworth Valley NSW 2250",
    "addr:postcode":"2250",
    "addr:street":"Cooks Rd",
    "iso:country":"AU",
    "sg:address":"Cooks Rd",
    "sg:city":"Glenworth Valley",
    "sg:classifiers":[
        {
            "category":"Coffee & Tea",
            "type":"Food & Drink"
        }
    ],
    "sg:phone":"+61 2 4342 2222",
    "sg:postcode":"2250",
    "sg:province":"NSW",
    "sg:tags":[
        "kayak",
        "canoe"
    ],
    "wof:name":"Ocean Planet Kayak Tours",
    "wof:placetype":"venue"
},
  "geometry": {"coordinates":[151.20950317399999,-33.4015541077],"type":"Point"}
}