{
  "type": "Feature",
  "properties": {
    "addr:full":"119 Petra St East Fremantle WA 6158",
    "addr:housenumber":"119",
    "addr:postcode":"6158",
    "addr:street":"Petra St",
    "iso:country":"AU",
    "sg:address":"119 Petra St",
    "sg:city":"East Fremantle",
    "sg:classifiers":[
        {
            "category":"Personal",
            "subcategory":"Massage",
            "type":"Services"
        }
    ],
    "sg:phone":"+61 8 9339 1193",
    "sg:postcode":"6158",
    "sg:province":"WA",
    "sg:tags":[
        "therapy"
    ],
    "wof:name":"Bence Tony",
    "wof:placetype":"venue"
},
  "geometry": {"coordinates":[115.775993,-32.0369],"type":"Point"}
}