{
  "type": "Feature",
  "properties": {
    "iso:country":"AU",
    "sg:address":"unit 1, 780 South Rd",
    "sg:city":"Glandore",
    "sg:classifiers":[
        {
            "category":"Building & Trades",
            "subcategory":"Pest Control",
            "type":"Services"
        }
    ],
    "sg:phone":"+61 8 8351 4122",
    "sg:postcode":"5037",
    "sg:province":"SA",
    "sg:tags":[
        "robot"
    ],
    "wof:name":"Robot Technologies - Systems Australia Pty .Ltd.",
    "wof:placetype":"venue"
},
  "geometry": {"coordinates":[138.572463989,-34.9614143372],"type":"Point"}
}