{
  "type": "Feature",
  "properties": {
    "addr:full":"236 Illawarra Rd Marrickville NSW 2204",
    "addr:housenumber":"236",
    "addr:postcode":"2204",
    "addr:street":"Illawarra Rd",
    "iso:country":"AU",
    "sg:address":"236 Illawarra Rd",
    "sg:city":"Marrickville",
    "sg:classifiers":[
        {
            "category":"Shopping",
            "subcategory":"Crafts & Fabrics",
            "type":"Retail Goods"
        }
    ],
    "sg:phone":"+61 2 9554 6939",
    "sg:postcode":"2204",
    "sg:province":"NSW",
    "sg:tags":[
        "material",
        "dress"
    ],
    "wof:name":"Hai Ha Fabrics",
    "wof:placetype":"venue"
},
  "geometry": {"coordinates":[151.156113,-33.910633],"type":"Point"}
}