{
  "type": "Feature",
  "properties": {
    "iso:country":"AU",
    "sg:address":"PO Box 320",
    "sg:city":"The Entrance",
    "sg:classifiers":[
        {
            "category":"Arts & Performance",
            "subcategory":"Dance",
            "type":"Entertainment"
        }
    ],
    "sg:phone":"+61 2 4369 1744",
    "sg:postcode":"2261",
    "sg:province":"NSW",
    "sg:tags":[
        "theatrical",
        "ballet",
        "tuition"
    ],
    "wof:name":"Central Dance Company Australia",
    "wof:placetype":"venue"
},
  "geometry": {"coordinates":[151.496628,-33.344341],"type":"Point"}
}