{
  "type": "Feature",
  "properties": {
    "addr:full":"31 James St Charlestown NSW 2290",
    "addr:housenumber":"31",
    "addr:postcode":"2290",
    "addr:street":"James St",
    "iso:country":"AU",
    "sg:address":"31 James St",
    "sg:city":"Charlestown",
    "sg:classifiers":[
        {
            "category":"Health Services",
            "subcategory":"Health Practitioner",
            "type":"Services"
        }
    ],
    "sg:phone":"+61 2 4943 2833",
    "sg:postcode":"2290",
    "sg:province":"NSW",
    "sg:tags":[
        "osteopath"
    ],
    "wof:name":"Porter Stephen M & Young Graham",
    "wof:placetype":"venue"
},
  "geometry": {"coordinates":[151.69778442399999,-32.9690742493],"type":"Point"}
}