{
  "type": "Feature",
  "properties": {
    "iso:country":"AU",
    "sg:address":"12/ 640 Geelong Rd",
    "sg:city":"Brooklyn",
    "sg:classifiers":[
        {
            "category":"Professional",
            "subcategory":"Printing & Photocopies",
            "type":"Services"
        }
    ],
    "sg:phone":"+61 3 9318 9792",
    "sg:postcode":"3025",
    "sg:province":"VIC",
    "sg:tags":[
        "trophy"
    ],
    "wof:name":"Maddocks Sports",
    "wof:placetype":"venue"
},
  "geometry": {"coordinates":[144.841431,-37.819237],"type":"Point"}
}