{
  "type": "Feature",
  "properties": {
    "addr:full":"2/ 25 Kayleigh Drv Maroochydore QLD 4558",
    "addr:housenumber":"/ 25",
    "addr:postcode":"4558",
    "addr:street":"Kayleigh Drv",
    "iso:country":"AU",
    "sg:address":"2/ 25 Kayleigh Drv",
    "sg:city":"Maroochydore",
    "sg:classifiers":[
        {
            "category":"Retail",
            "subcategory":"Auto Repair",
            "type":"Services"
        }
    ],
    "sg:phone":"+61 7 5475 4450",
    "sg:postcode":"4558",
    "sg:province":"QLD",
    "sg:tags":[
        "testing",
        "inspection",
        "motor",
        "vehicle"
    ],
    "wof:name":"David Yates Automotive",
    "wof:placetype":"venue"
},
  "geometry": {"coordinates":[153.08987426799999,-26.6698608398],"type":"Point"}
}