{
  "type": "Feature",
  "properties": {
    "iso:country":"AU",
    "sg:address":"55 Salamanca Pl",
    "sg:city":"Hobart",
    "sg:classifiers":[
        {
            "category":"Manufacturing",
            "subcategory":"Food",
            "type":"Manufacturing & Wholesale Goods"
        }
    ],
    "sg:phone":"+61 3 6224 2007",
    "sg:postcode":"7000",
    "sg:province":"TAS",
    "sg:tags":[
        "function",
        "catering"
    ],
    "wof:name":"FiTforU",
    "wof:placetype":"venue"
},
  "geometry": {"coordinates":[147.33291625999999,-42.8868026733],"type":"Point"}
}