{
  "type": "Feature",
  "properties": {
    "addr:full":"Shed 8/ 25 Fishermans Rd Maroochydore QLD 4558",
    "addr:housenumber":"8 / 25",
    "addr:postcode":"4558",
    "addr:street":"Fishermans Rd",
    "iso:country":"AU",
    "sg:address":"Shed 8/ 25 Fishermans Rd",
    "sg:city":"Maroochydore",
    "sg:classifiers":[
        {
            "category":"Professional",
            "subcategory":"Detective & Security Services",
            "type":"Services"
        }
    ],
    "sg:phone":"+61 7 5443 7772",
    "sg:postcode":"4558",
    "sg:province":"QLD",
    "sg:tags":[
        "equipment",
        "window",
        "doors"
    ],
    "wof:name":"Discount Glass",
    "wof:placetype":"venue"
},
  "geometry": {"coordinates":[153.054962158,-26.6543521881],"type":"Point"}
}