{
  "type": "Feature",
  "properties": {
    "addr:full":"Shp2/ 66-68 Main St Pakenham VIC 3810",
    "addr:housenumber":"66-68",
    "addr:postcode":"3810",
    "addr:street":"Main St",
    "iso:country":"AU",
    "sg:address":"Shp2/ 66-68 Main St",
    "sg:city":"Pakenham",
    "sg:classifiers":[
        {
            "category":"Shopping",
            "subcategory":"Clothing, Apparel, & Fashions",
            "type":"Retail Goods"
        }
    ],
    "sg:phone":"+61 3 5941 1455",
    "sg:postcode":"3810",
    "sg:province":"VIC",
    "sg:tags":[
        "menswear"
    ],
    "wof:name":"Pakenham Menswear & Manchester Pty Ltd",
    "wof:placetype":"venue"
},
  "geometry": {"coordinates":[145.48048399999999,-38.076199],"type":"Point"}
}