{
  "type": "Feature",
  "properties": {
    "iso:country":"AU",
    "sg:address":"311 Honour Ave",
    "sg:city":"Graceville",
    "sg:classifiers":[
        {
            "category":"Building & Trades",
            "subcategory":"Locksmith",
            "type":"Services"
        }
    ],
    "sg:phone":"+61 7 3379 8839",
    "sg:postcode":"4075",
    "sg:province":"QLD",
    "sg:tags":[
        "lock"
    ],
    "wof:name":"SLS Locksmiths",
    "wof:placetype":"venue"
},
  "geometry": {"coordinates":[152.97540283199999,-27.5205211639],"type":"Point"}
}