{
  "type": "Feature",
  "properties": {
    "iso:country":"AU",
    "sg:address":"Lot 1, Powers Rd",
    "sg:city":"Seven Hills",
    "sg:classifiers":[
        {
            "category":"Home & Garden",
            "subcategory":"Building Materials",
            "type":"Retail Goods"
        }
    ],
    "sg:phone":"+61 2 9838 8700",
    "sg:postcode":"2147",
    "sg:province":"NSW",
    "sg:tags":[
        "pre-mixed",
        "concrete"
    ],
    "wof:name":"Metromix Concrete",
    "wof:placetype":"venue"
},
  "geometry": {"coordinates":[150.93878173799999,-33.7739181519],"type":"Point"}
}