{
  "type": "Feature",
  "properties": {
    "iso:country":"AU",
    "sg:address":"480- 482 Hunter St",
    "sg:city":"Newcastle",
    "sg:classifiers":[
        {
            "category":"Real Estate",
            "subcategory":"Real Estate Agent",
            "type":"Services"
        }
    ],
    "sg:phone":"+61 2 4915 3000",
    "sg:postcode":"2300",
    "sg:province":"NSW",
    "wof:name":"L.J. Hooker",
    "wof:placetype":"venue"
},
  "geometry": {"coordinates":[151.770294,-32.927029],"type":"Point"}
}