{
  "type": "Feature",
  "properties": {
    "iso:country":"AU",
    "sg:address":"Geelong Rd",
    "sg:city":"Mt Clear",
    "sg:classifiers":[
        {
            "category":"Education",
            "subcategory":"School",
            "type":"Public Place"
        }
    ],
    "sg:phone":"+61 3 5330 1844",
    "sg:postcode":"3350",
    "sg:province":"VIC",
    "sg:tags":[
        "state",
        "except",
        "nsw"
    ],
    "wof:name":"Mt Clear Primary School",
    "wof:placetype":"venue"
},
  "geometry": {"coordinates":[143.868683,-37.603401],"type":"Point"}
}