{
  "type": "Feature",
  "properties": {
    "addr:full":"12 Scarborough St Somerton Park SA 5044",
    "addr:housenumber":"12",
    "addr:postcode":"5044",
    "addr:street":"Scarborough St",
    "iso:country":"AU",
    "sg:address":"12 Scarborough St",
    "sg:city":"Somerton Park",
    "sg:classifiers":[
        {
            "category":"Building & Trades",
            "subcategory":"Plumbing",
            "type":"Services"
        }
    ],
    "sg:phone":"+61 423 598 903",
    "sg:postcode":"5044",
    "sg:province":"SA",
    "sg:tags":[
        "plumber",
        "gasfitters"
    ],
    "wof:name":"Beavis Plumbing Services P/L",
    "wof:placetype":"venue"
},
  "geometry": {"coordinates":[138.51870700000001,-34.991749],"type":"Point"}
}