{
  "type": "Feature",
  "properties": {
    "addr:full":"61 Eramosa Rd (West) Somerville VIC 3912",
    "addr:housenumber":"61",
    "addr:postcode":"3912",
    "addr:street":"Eramosa Rd",
    "iso:country":"AU",
    "sg:address":"61 Eramosa Rd (West)",
    "sg:city":"Somerville",
    "sg:classifiers":[
        {
            "category":"Health Services",
            "subcategory":"Doctor",
            "type":"Services"
        }
    ],
    "sg:phone":"+61 407 310 138",
    "sg:postcode":"3912",
    "sg:province":"VIC",
    "sg:tags":[
        "reflexology"
    ],
    "wof:name":"Holly Clarke",
    "wof:placetype":"venue"
},
  "geometry": {"coordinates":[145.176177978,-38.2239265442],"type":"Point"}
}