{
  "type": "Feature",
  "properties": {
    "iso:country":"AU",
    "sg:address":"364 Shepherds Hill Rd",
    "sg:city":"Blackwood",
    "sg:classifiers":[
        {
            "category":"Shopping",
            "subcategory":"Clothing, Apparel, & Fashions",
            "type":"Retail Goods"
        }
    ],
    "sg:phone":"+61 8 8278 4509",
    "sg:postcode":"5051",
    "sg:province":"SA",
    "sg:tags":[
        "lingerie",
        "hosiery",
        "sleepwear"
    ],
    "wof:name":"Blackwood Lingerie",
    "wof:placetype":"venue"
},
  "geometry": {"coordinates":[138.615753,-35.021446],"type":"Point"}
}