{
  "type": "Feature",
  "properties": {
    "addr:full":"Cnr Parraween & Willarong Rds Caringbah NSW 2229",
    "addr:postcode":"2229",
    "addr:street":"Cnr Parraween & Willarong Rds",
    "iso:country":"AU",
    "sg:address":"Cnr Parraween & Willarong Rds",
    "sg:city":"Caringbah",
    "sg:classifiers":[
        {
            "category":"Building & Trades",
            "subcategory":"Construction",
            "type":"Services"
        }
    ],
    "sg:phone":"+61 2 9540 4044",
    "sg:postcode":"2229",
    "sg:province":"NSW",
    "sg:tags":[
        "brick",
        "paving"
    ],
    "wof:name":"Miranda Landscape Supplies",
    "wof:placetype":"venue"
},
  "geometry": {"coordinates":[151.11955261200001,-34.0421333313],"type":"Point"}
}