{
  "type": "Feature",
  "properties": {
    "addr:full":"2 Longview St Balmain NSW 2041",
    "addr:housenumber":"2",
    "addr:postcode":"2041",
    "addr:street":"Longview St",
    "iso:country":"AU",
    "sg:address":"2 Longview St",
    "sg:city":"Balmain",
    "sg:classifiers":[
        {
            "category":"Education",
            "subcategory":"Special Training",
            "type":"Public Place"
        }
    ],
    "sg:phone":"+61 2 9810 6413",
    "sg:postcode":"2041",
    "sg:province":"NSW",
    "sg:tags":[
        "development"
    ],
    "wof:name":"AGS Consulting & Training",
    "wof:placetype":"venue"
},
  "geometry": {"coordinates":[151.169937,-33.856724],"type":"Point"}
}