{
  "type": "Feature",
  "properties": {
    "addr:full":"346 Mann St Gosford NSW 2250",
    "addr:housenumber":"346",
    "addr:postcode":"2250",
    "addr:street":"Mann St",
    "iso:country":"AU",
    "sg:address":"346 Mann St",
    "sg:city":"Gosford",
    "sg:classifiers":[
        {
            "category":"Autos & Motor Vehicles",
            "subcategory":"Auto Supplies",
            "type":"Retail Goods"
        }
    ],
    "sg:phone":"+61 2 4324 5533",
    "sg:postcode":"2250",
    "sg:province":"NSW",
    "sg:tags":[
        "tyre"
    ],
    "wof:name":"Bridgestone Tyre Centres",
    "wof:placetype":"venue"
},
  "geometry": {"coordinates":[151.34344482399999,-33.4183235168],"type":"Point"}
}