{
  "type": "Feature",
  "properties": {
    "iso:country":"AU",
    "sg:address":"Suite 11 Level 7 250 Pitt St",
    "sg:city":"Sydney",
    "sg:classifiers":[
        {
            "category":"Real Estate",
            "subcategory":"Real Estate Agent",
            "type":"Services"
        }
    ],
    "sg:phone":"+61 2 9267 4884",
    "sg:postcode":"2000",
    "sg:province":"NSW",
    "sg:tags":[
        "export"
    ],
    "wof:name":"Southern Sunshine International Australia Pty Ltd",
    "wof:placetype":"venue"
},
  "geometry": {"coordinates":[151.20828247099999,-33.8728370667],"type":"Point"}
}