{
  "type": "Feature",
  "properties": {
    "iso:country":"AU",
    "sg:address":"75 Beechboro Rd",
    "sg:city":"Bayswater",
    "sg:classifiers":[
        {
            "category":"Manufacturing",
            "subcategory":"Electronics",
            "type":"Manufacturing & Wholesale Goods"
        }
    ],
    "sg:phone":"+61 8 9272 8977",
    "sg:postcode":"6053",
    "sg:province":"WA",
    "sg:tags":[
        "wholesaler",
        "equipment",
        "part",
        "mfrs",
        "refrigeration"
    ],
    "wof:name":"Airefrig Australia Pty. Ltd.",
    "wof:placetype":"venue"
},
  "geometry": {"coordinates":[115.91368866000001,-31.9096889496],"type":"Point"}
}