{
  "type": "Feature",
  "properties": {
    "addr:full":"200 Fallon St Albury NSW 2640",
    "addr:housenumber":"200",
    "addr:postcode":"2640",
    "addr:street":"Fallon St",
    "iso:country":"AU",
    "sg:address":"200 Fallon St",
    "sg:city":"Albury",
    "sg:classifiers":[
        {
            "category":"Professional",
            "subcategory":"Printing & Photocopies",
            "type":"Services"
        }
    ],
    "sg:phone":"+61 2 6040 6722",
    "sg:postcode":"2640",
    "sg:province":"NSW",
    "sg:tags":[
        "screen",
        "printer"
    ],
    "wof:name":"Albury-Wodonga Screenprinting",
    "wof:placetype":"venue"
},
  "geometry": {"coordinates":[146.92742919899999,-36.0622825623],"type":"Point"}
}