{
  "type": "Feature",
  "properties": {
    "iso:country":"AU",
    "sg:address":"480 Maroondah Hwy",
    "sg:city":"Lilydale",
    "sg:classifiers":[
        {
            "category":"Retail",
            "subcategory":"Auto Repair",
            "type":"Services"
        }
    ],
    "sg:phone":"+61 3 9739 5444",
    "sg:postcode":"3140",
    "sg:province":"VIC",
    "sg:tags":[
        "transmission",
        "automotive",
        "car"
    ],
    "wof:name":"Yarra Valley Automatic Transmission Specialist",
    "wof:placetype":"venue"
},
  "geometry": {"coordinates":[145.37161254899999,-37.7617797852],"type":"Point"}
}