{
  "type": "Feature",
  "properties": {
    "iso:country":"AU",
    "sg:address":"3 McNamara Rd",
    "sg:city":"Avonsleigh",
    "sg:classifiers":[
        {
            "category":"Education",
            "subcategory":"Music School",
            "type":"Public Place"
        }
    ],
    "sg:phone":"+61 3 5968 6030",
    "sg:postcode":"3782",
    "sg:province":"VIC",
    "sg:tags":[
        "teacher"
    ],
    "wof:name":"Avonsleigh Music Tuition",
    "wof:placetype":"venue"
},
  "geometry": {"coordinates":[145.47366299999999,-37.923176],"type":"Point"}
}