{
  "type": "Feature",
  "properties": {
    "addr:full":"10 Fiesta Crt Everton Hills QLD 4053",
    "addr:housenumber":"10",
    "addr:postcode":"4053",
    "addr:street":"Fiesta Crt",
    "iso:country":"AU",
    "sg:address":"10 Fiesta Crt",
    "sg:city":"Everton Hills",
    "sg:classifiers":[
        {
            "category":"Building & Trades",
            "subcategory":"Construction",
            "type":"Services"
        }
    ],
    "sg:phone":"+61 7 3353 5472",
    "sg:postcode":"4053",
    "sg:province":"QLD",
    "sg:tags":[
        "joiner",
        "carpenter"
    ],
    "wof:name":"Dominic Montague",
    "wof:placetype":"venue"
},
  "geometry": {"coordinates":[152.97750854500001,-27.3834342957],"type":"Point"}
}