{
  "type": "Feature",
  "properties": {
    "iso:country":"AU",
    "sg:address":"70 Conway St",
    "sg:city":"Lismore",
    "sg:classifiers":[
        {
            "category":"Food & Beverages",
            "subcategory":"Bakery",
            "type":"Retail Goods"
        }
    ],
    "sg:phone":"+61 2 6621 5665",
    "sg:postcode":"2480",
    "sg:province":"NSW",
    "sg:tags":[
        "cake",
        "shop",
        "pastry"
    ],
    "wof:name":"Steves Bakery & Cake Shop",
    "wof:placetype":"venue"
},
  "geometry": {"coordinates":[153.27914428700001,-28.8128013611],"type":"Point"}
}