{
  "type": "Feature",
  "properties": {
    "addr:full":"324 Unley Rd Hyde Park SA 5061",
    "addr:housenumber":"324",
    "addr:postcode":"5061",
    "addr:street":"Unley Rd",
    "iso:country":"AU",
    "sg:address":"324 Unley Rd",
    "sg:city":"Hyde Park",
    "sg:classifiers":[
        {
            "category":"Health Services",
            "subcategory":"Dentist",
            "type":"Services"
        }
    ],
    "sg:phone":"+61 8 8272 9087",
    "sg:postcode":"5061",
    "sg:province":"SA",
    "wof:name":"Antoniazzi Roger",
    "wof:placetype":"venue"
},
  "geometry": {"coordinates":[138.60792541500001,-34.957901001],"type":"Point"}
}