{
  "type": "Feature",
  "properties": {
    "addr:full":"36 Enterprise St Bohle QLD 4818",
    "addr:housenumber":"36",
    "addr:postcode":"4818",
    "addr:street":"Enterprise St",
    "iso:country":"AU",
    "sg:address":"36 Enterprise St",
    "sg:city":"Bohle",
    "sg:classifiers":[
        {
            "category":"Retail",
            "subcategory":"Storage",
            "type":"Services"
        }
    ],
    "sg:phone":"+61 7 4774 4422",
    "sg:postcode":"4818",
    "sg:province":"QLD",
    "sg:tags":[
        "removal",
        "furniture"
    ],
    "wof:name":"Kent Moving & Storage",
    "wof:placetype":"venue"
},
  "geometry": {"coordinates":[146.71167,-19.258987],"type":"Point"}
}