{
  "type": "Feature",
  "properties": {
    "addr:full":"Shp 2/ 33 High St Wauchope NSW 2446",
    "addr:housenumber":"/ 33",
    "addr:postcode":"2446",
    "addr:street":"High St",
    "iso:country":"AU",
    "sg:address":"Shp 2/ 33 High St",
    "sg:city":"Wauchope",
    "sg:classifiers":[
        {
            "category":"Shopping",
            "subcategory":"Clothing, Apparel, & Fashions",
            "type":"Retail Goods"
        }
    ],
    "sg:phone":"+61 2 6586 4994",
    "sg:postcode":"2446",
    "sg:province":"NSW",
    "sg:tags":[
        "lingerie",
        "hosiery",
        "sleepwear"
    ],
    "wof:name":"Heart To Heart Lingerie",
    "wof:placetype":"venue"
},
  "geometry": {"coordinates":[152.73298600000001,-31.457466],"type":"Point"}
}