{
  "type": "Feature",
  "properties": {
    "addr:full":"148 Manifold St Camperdown VIC 3260",
    "addr:housenumber":"148",
    "addr:postcode":"3260",
    "addr:street":"Manifold St",
    "iso:country":"AU",
    "sg:address":"148 Manifold St",
    "sg:city":"Camperdown",
    "sg:classifiers":[
        {
            "category":"Fast Food",
            "type":"Food & Drink"
        }
    ],
    "sg:phone":"+61 3 5593 2380",
    "sg:postcode":"3260",
    "sg:province":"VIC",
    "sg:tags":[
        "away",
        "take"
    ],
    "wof:name":"Camperdown Seafoods",
    "wof:placetype":"venue"
},
  "geometry": {"coordinates":[143.14830017099999,-38.2328567505],"type":"Point"}
}