{
  "type": "Feature",
  "properties": {
    "addr:full":"189 Gladstone St Fyshwick ACT 2609",
    "addr:housenumber":"189",
    "addr:postcode":"2609",
    "addr:street":"Gladstone St",
    "iso:country":"AU",
    "sg:address":"189 Gladstone St",
    "sg:city":"Fyshwick",
    "sg:classifiers":[
        {
            "category":"Professional",
            "subcategory":"Management & Consulting",
            "type":"Services"
        }
    ],
    "sg:phone":"+61 2 6295 5444",
    "sg:postcode":"2609",
    "sg:province":"ACT",
    "sg:tags":[
        "consultant",
        "energy"
    ],
    "wof:name":"Agility Team Build",
    "wof:placetype":"venue"
},
  "geometry": {"coordinates":[149.185058594,-35.3312339783],"type":"Point"}
}