{
  "type": "Feature",
  "properties": {
    "iso:country":"AU",
    "sg:address":"Unit 22/ 7 Carrington Rd",
    "sg:city":"Castle Hill",
    "sg:classifiers":[
        {
            "category":"Real Estate",
            "subcategory":"Real Estate Services",
            "type":"Services"
        }
    ],
    "sg:phone":"+61 2 9899 3612",
    "sg:postcode":"2154",
    "sg:province":"NSW",
    "sg:tags":[
        "valuer"
    ],
    "wof:name":"Sydney Norwest Property Valuations",
    "wof:placetype":"venue"
},
  "geometry": {"coordinates":[150.98846435600001,-33.7275924683],"type":"Point"}
}