{
  "type": "Feature",
  "properties": {
    "iso:country":"AU",
    "sg:address":"29 Trawalla Ave",
    "sg:city":"Thomastown",
    "sg:classifiers":[
        {
            "category":"Wholesale",
            "subcategory":"Scrap",
            "type":"Manufacturing & Wholesale Goods"
        }
    ],
    "sg:phone":"+61 3 9359 5255",
    "sg:postcode":"3074",
    "sg:province":"VIC",
    "sg:tags":[
        "merchant",
        "metal"
    ],
    "wof:name":"Herz G & Son",
    "wof:placetype":"venue"
},
  "geometry": {"coordinates":[144.97671508799999,-37.6878128052],"type":"Point"}
}