{
  "type": "Feature",
  "properties": {
    "iso:country":"AU",
    "sg:address":"51 Grafton St",
    "sg:city":"Coffs Harbour",
    "sg:classifiers":[
        {
            "category":"Government",
            "subcategory":"Customs House",
            "type":"Public Place"
        }
    ],
    "sg:phone":"+61 2 6648 7600",
    "sg:postcode":"2450",
    "sg:province":"NSW",
    "sg:tags":[
        "title",
        "management",
        "stratum"
    ],
    "wof:name":"Katalin Savage",
    "wof:placetype":"venue"
},
  "geometry": {"coordinates":[153.113037,-30.297443],"type":"Point"}
}