{
  "type": "Feature",
  "properties": {
    "iso:country":"AU",
    "sg:address":"Unit 8/ 2 Brandwood St",
    "sg:city":"Royal Park",
    "sg:classifiers":[
        {
            "category":"Wholesale",
            "subcategory":"Home Furnishings",
            "type":"Manufacturing & Wholesale Goods"
        }
    ],
    "sg:phone":"+61 8 8341 3033",
    "sg:postcode":"5014",
    "sg:province":"SA",
    "sg:tags":[
        "wholesaler",
        "curtain",
        "mfrs"
    ],
    "wof:name":"Pelmets Plus",
    "wof:placetype":"venue"
},
  "geometry": {"coordinates":[138.50392150900001,-34.8654823303],"type":"Point"}
}