{
  "type": "Feature",
  "properties": {
    "addr:full":"Shed 2C/ 153 St Vincents Rd Northgate QLD 4013",
    "addr:housenumber":"153",
    "addr:postcode":"4013",
    "addr:street":"St Vincents Rd",
    "iso:country":"AU",
    "sg:address":"Shed 2C/ 153 St Vincents Rd",
    "sg:city":"Northgate",
    "sg:classifiers":[
        {
            "category":"Retail",
            "subcategory":"Storage",
            "type":"Services"
        }
    ],
    "sg:phone":"+61 7 3267 8697",
    "sg:postcode":"4013",
    "sg:province":"QLD",
    "sg:tags":[
        "removal",
        "furniture"
    ],
    "wof:name":"Gs Furniture Transport",
    "wof:placetype":"venue"
},
  "geometry": {"coordinates":[153.07000732399999,-27.3802890778],"type":"Point"}
}