{
  "type": "Feature",
  "properties": {
    "iso:country":"AU",
    "sg:address":"View St",
    "sg:city":"Koondrook",
    "sg:classifiers":[
        {
            "category":"Commercial Area",
            "type":"Public Place"
        }
    ],
    "sg:phone":"+61 3 5453 2433",
    "sg:postcode":"3580",
    "sg:province":"VIC",
    "sg:tags":[
        "heavy",
        "carrier"
    ],
    "wof:name":"Frankling Transport",
    "wof:placetype":"venue"
},
  "geometry": {"coordinates":[144.126342773,-35.634185791],"type":"Point"}
}