{
  "type": "Feature",
  "properties": {
    "iso:country":"AU",
    "sg:address":"Riverton Hospital 23 Moorhouse Tce",
    "sg:city":"Riverton",
    "sg:classifiers":[
        {
            "category":"Health Services",
            "subcategory":"Doctor",
            "type":"Services"
        }
    ],
    "sg:phone":"+61 8 8847 2300",
    "sg:postcode":"5412",
    "sg:province":"SA",
    "sg:tags":[
        "podiatrist"
    ],
    "wof:name":"Halliday Kaye F",
    "wof:placetype":"venue"
},
  "geometry": {"coordinates":[138.74642944300001,-34.1604347229],"type":"Point"}
}