{
  "type": "Feature",
  "properties": {
    "addr:full":"13 Peacock Crt Birkdale QLD 4159",
    "addr:housenumber":"13",
    "addr:postcode":"4159",
    "addr:street":"Peacock Crt",
    "iso:country":"AU",
    "sg:address":"13 Peacock Crt",
    "sg:city":"Birkdale",
    "sg:classifiers":[
        {
            "category":"Professional",
            "subcategory":"Computer Services",
            "type":"Services"
        }
    ],
    "sg:phone":"+61 7 3207 2119",
    "sg:postcode":"4159",
    "sg:province":"QLD",
    "sg:tags":[
        "repairs",
        "upgrade",
        "equipment"
    ],
    "wof:name":"Daytech Computer",
    "wof:placetype":"venue"
},
  "geometry": {"coordinates":[153.22280883799999,-27.5013656616],"type":"Point"}
}