{
  "type": "Feature",
  "properties": {
    "iso:country":"AU",
    "sg:address":"Suite 5, Level 1, 345 Pacific Hwy",
    "sg:city":"Crows Nest",
    "sg:classifiers":[
        {
            "category":"Professional",
            "subcategory":"Accounting & Tax Preparation",
            "type":"Services"
        }
    ],
    "sg:phone":"+61 2 9929 3663",
    "sg:postcode":"2065",
    "sg:province":"NSW",
    "sg:tags":[
        "bookkeeping"
    ],
    "sg:website":"http://www.a2books.com.au",
    "wof:name":"A 2 Bookkeeping",
    "wof:placetype":"venue"
},
  "geometry": {"coordinates":[151.198730469,-33.8253364563],"type":"Point"}
}