{
  "type": "Feature",
  "properties": {
    "iso:country":"AU",
    "sg:address":"474 Hunter St",
    "sg:city":"Newcastle",
    "sg:classifiers":[
        {
            "category":"Building & Trades",
            "subcategory":"Equipment Rental",
            "type":"Services"
        }
    ],
    "sg:phone":"+61 2 4929 1200",
    "sg:postcode":"2300",
    "sg:province":"NSW",
    "sg:tags":[
        "party",
        "hire"
    ],
    "wof:name":"Cupids Corner Wedding HIre & Event Designs",
    "wof:placetype":"venue"
},
  "geometry": {"coordinates":[151.770462,-32.927013],"type":"Point"}
}