{
  "type": "Feature",
  "properties": {
    "addr:full":"87 Boundary Rd Wahroonga NSW 2076",
    "addr:housenumber":"87",
    "addr:postcode":"2076",
    "addr:street":"Boundary Rd",
    "iso:country":"AU",
    "sg:address":"87 Boundary Rd",
    "sg:city":"Wahroonga",
    "sg:classifiers":[
        {
            "category":"Building & Trades",
            "subcategory":"Construction",
            "type":"Services"
        }
    ],
    "sg:phone":"+61 2 9489 7045",
    "sg:postcode":"2076",
    "sg:province":"NSW",
    "sg:tags":[
        "stonework",
        "stone",
        "mason"
    ],
    "wof:name":"Francis & Sons",
    "wof:placetype":"venue"
},
  "geometry": {"coordinates":[151.12905883799999,-33.7065315247],"type":"Point"}
}