{
  "type": "Feature",
  "properties": {
    "iso:country":"AU",
    "sg:address":"26 Wiltshire La",
    "sg:city":"Delacombe",
    "sg:classifiers":[
        {
            "category":"Retail",
            "subcategory":"Auto Repair",
            "type":"Services"
        }
    ],
    "sg:phone":"+61 3 5336 2630",
    "sg:postcode":"3356",
    "sg:province":"VIC",
    "sg:tags":[
        "repairer",
        "motor",
        "engineer"
    ],
    "wof:name":"Wiltshire Automotive Repairs",
    "wof:placetype":"venue"
},
  "geometry": {"coordinates":[143.80877699999999,-37.576889],"type":"Point"}
}