{
  "type": "Feature",
  "properties": {
    "iso:country":"AU",
    "sg:address":"24 Windorah St",
    "sg:city":"Stafford",
    "sg:classifiers":[
        {
            "category":"Wholesale",
            "subcategory":"Electrical",
            "type":"Manufacturing & Wholesale Goods"
        }
    ],
    "sg:phone":"+61 7 3356 3123",
    "sg:postcode":"4053",
    "sg:province":"QLD",
    "sg:tags":[
        "control",
        "equipment",
        "switch"
    ],
    "wof:name":"Dynalite",
    "wof:placetype":"venue"
},
  "geometry": {"coordinates":[153.01121520999999,-27.4110984802],"type":"Point"}
}