{
  "type": "Feature",
  "properties": {
    "iso:country":"AU",
    "sg:address":"64 Percy St",
    "sg:city":"Portland",
    "sg:classifiers":[
        {
            "category":"Health Services",
            "subcategory":"Optometrist",
            "type":"Services"
        }
    ],
    "sg:phone":"+61 3 5523 1189",
    "sg:postcode":"3305",
    "sg:province":"VIC",
    "wof:name":"Eyecare Plus Optometrists",
    "wof:placetype":"venue"
},
  "geometry": {"coordinates":[141.60385131800001,-38.3473052979],"type":"Point"}
}