{
  "type": "Feature",
  "properties": {
    "iso:country":"AU",
    "sg:address":"6 Ferry Ave",
    "sg:city":"Melrose Park",
    "sg:classifiers":[
        {
            "category":"Parking",
            "type":"Transportation"
        }
    ],
    "sg:phone":"+61 8 8277 8222",
    "sg:postcode":"5039",
    "sg:province":"SA",
    "sg:tags":[
        "equipment",
        "system"
    ],
    "wof:name":"Burley Hardware Pty Ltd",
    "wof:placetype":"venue"
},
  "geometry": {"coordinates":[138.57661438,-34.9893608093],"type":"Point"}
}