{
  "type": "Feature",
  "properties": {
    "addr:full":"80a Wickham St Fortitude Valley QLD 4006",
    "addr:housenumber":"80a",
    "addr:postcode":"4006",
    "addr:street":"Wickham St",
    "iso:country":"AU",
    "sg:address":"80a Wickham St",
    "sg:city":"Fortitude Valley",
    "sg:classifiers":[
        {
            "category":"Real Estate",
            "subcategory":"Architect",
            "type":"Services"
        }
    ],
    "sg:phone":"+61 7 3839 6111",
    "sg:postcode":"4006",
    "sg:province":"QLD",
    "wof:name":"Shane Plazibat Architect Pty Ltd",
    "wof:placetype":"venue"
},
  "geometry": {"coordinates":[153.03147888199999,-27.4607105255],"type":"Point"}
}