{
  "type": "Feature",
  "properties": {
    "iso:country":"AU",
    "sg:address":"Suite 2/ 2 Philippine Parade",
    "sg:city":"Palm Beach",
    "sg:classifiers":[
        {
            "category":"Manufacturing",
            "subcategory":"Jewelry",
            "type":"Manufacturing & Wholesale Goods"
        }
    ],
    "sg:phone":"+61 7 5598 4811",
    "sg:postcode":"4221",
    "sg:province":"QLD",
    "sg:tags":[
        "designer",
        "jewellery"
    ],
    "wof:name":"Jewellers Workshop Gallery",
    "wof:placetype":"venue"
},
  "geometry": {"coordinates":[153.47067260700001,-28.1257228851],"type":"Point"}
}