{
  "type": "Feature",
  "properties": {
    "addr:full":"27 Climie St Campania TAS 7026",
    "addr:housenumber":"27",
    "addr:postcode":"7026",
    "addr:street":"Climie St",
    "iso:country":"AU",
    "sg:address":"27 Climie St",
    "sg:city":"Campania",
    "sg:classifiers":[
        {
            "category":"Government",
            "subcategory":"Post Office",
            "type":"Public Place"
        }
    ],
    "sg:phone":"+61 3 6260 4188",
    "sg:postcode":"7026",
    "sg:province":"TAS",
    "sg:tags":[
        "postal"
    ],
    "wof:name":"Australia Post Offices",
    "wof:placetype":"venue"
},
  "geometry": {"coordinates":[147.42172241200001,-42.664390564],"type":"Point"}
}