{
  "type": "Feature",
  "properties": {
    "addr:full":"17- 47 Turner St Port Melbourne VIC 3207",
    "addr:housenumber":"47",
    "addr:postcode":"3207",
    "addr:street":"Turner St",
    "iso:country":"AU",
    "sg:address":"17- 47 Turner St",
    "sg:city":"Port Melbourne",
    "sg:classifiers":[
        {
            "category":"Home & Garden",
            "subcategory":"Building Materials",
            "type":"Retail Goods"
        }
    ],
    "sg:phone":"+61 3 9645 1877",
    "sg:postcode":"3207",
    "sg:province":"VIC",
    "sg:tags":[
        "plaster",
        "plasterboard",
        "supply"
    ],
    "wof:name":"Boral Plasterboard",
    "wof:placetype":"venue"
},
  "geometry": {"coordinates":[144.92285200000001,-37.823715],"type":"Point"}
}