{
  "type": "Feature",
  "properties": {
    "addr:full":"26 Winbin Crs Gwandalan NSW 2259",
    "addr:housenumber":"26",
    "addr:postcode":"2259",
    "addr:street":"Winbin Crs",
    "iso:country":"AU",
    "sg:address":"26 Winbin Crs",
    "sg:city":"Gwandalan",
    "sg:classifiers":[
        {
            "category":"Building & Trades",
            "subcategory":"Landscaping Services",
            "type":"Services"
        }
    ],
    "sg:phone":"+61 2 4976 1497",
    "sg:postcode":"2259",
    "sg:province":"NSW",
    "sg:tags":[
        "stump",
        "tree",
        "felling",
        "removal"
    ],
    "wof:name":"Tree Wise Men",
    "wof:placetype":"venue"
},
  "geometry": {"coordinates":[151.580276489,-33.1394309998],"type":"Point"}
}