{
  "type": "Feature",
  "properties": {
    "iso:country":"AU",
    "sg:address":"141 Hampden Rd",
    "sg:city":"Hobart",
    "sg:classifiers":[
        {
            "category":"Health Services",
            "subcategory":"Doctor",
            "type":"Services"
        }
    ],
    "sg:phone":"+61 3 6224 1808",
    "sg:postcode":"7000",
    "sg:province":"TAS",
    "sg:tags":[
        "medical",
        "practitioner"
    ],
    "sg:website":"http://www.tasivf.com.au",
    "wof:name":"Tas IVF",
    "wof:placetype":"venue"
},
  "geometry": {"coordinates":[147.32781982399999,-42.8879356384],"type":"Point"}
}