{
  "type": "Feature",
  "properties": {
    "addr:full":"436 Elizabeth St North Hobart TAS 7000",
    "addr:housenumber":"436",
    "addr:postcode":"7000",
    "addr:street":"Elizabeth St",
    "iso:country":"AU",
    "sg:address":"436 Elizabeth St",
    "sg:city":"North Hobart",
    "sg:classifiers":[
        {
            "category":"Health Services",
            "subcategory":"Health Practitioner",
            "type":"Services"
        }
    ],
    "sg:phone":"+61 417 316 406",
    "sg:postcode":"7000",
    "sg:province":"TAS",
    "sg:tags":[
        "psychologist"
    ],
    "wof:name":"Storchheim, Dr Lisa",
    "wof:placetype":"venue"
},
  "geometry": {"coordinates":[147.31300354000001,-42.8711624146],"type":"Point"}
}