{
  "type": "Feature",
  "properties": {
    "iso:country":"AU",
    "sg:address":"141 Victoria Ave",
    "sg:city":"Albert Park",
    "sg:classifiers":[
        {
            "category":"Banks & Credit Unions",
            "subcategory":"Financial Services",
            "type":"Services"
        }
    ],
    "sg:phone":"+61 1300 135 560",
    "sg:postcode":"3206",
    "sg:province":"VIC",
    "sg:tags":[
        "loan",
        "finance",
        "mortgage"
    ],
    "wof:name":"Loans Cafe The",
    "wof:placetype":"venue"
},
  "geometry": {"coordinates":[144.949905,-37.845966],"type":"Point"}
}