{
  "type": "Feature",
  "properties": {
    "iso:country":"AU",
    "sg:address":"1 Marcus Pl",
    "sg:city":"Singleton",
    "sg:classifiers":[
        {
            "category":"Social Services",
            "subcategory":"Child Care",
            "type":"Services"
        }
    ],
    "sg:phone":"+61 2 6573 2000",
    "sg:postcode":"2330",
    "sg:province":"NSW",
    "wof:name":"Colleen Gale Childrens Centre",
    "wof:placetype":"venue"
},
  "geometry": {"coordinates":[151.17657500000001,-32.544666],"type":"Point"}
}