{
  "type": "Feature",
  "properties": {
    "addr:full":"Suite 6, 21 McCabe St North Fremantle WA 6159",
    "addr:housenumber":"21",
    "addr:postcode":"6159",
    "addr:street":"Mccabe St",
    "iso:country":"AU",
    "sg:address":"Suite 6, 21 McCabe St",
    "sg:city":"North Fremantle",
    "sg:classifiers":[
        {
            "category":"Building & Trades",
            "subcategory":"Cleaning & Sanitation",
            "type":"Services"
        }
    ],
    "sg:phone":"+61 8 9336 7123",
    "sg:postcode":"6159",
    "sg:province":"WA",
    "sg:tags":[
        "window"
    ],
    "wof:name":"Home Services Australia",
    "wof:placetype":"venue"
},
  "geometry": {"coordinates":[115.75453899999999,-32.0233],"type":"Point"}
}