{
  "type": "Feature",
  "properties": {
    "addr:full":"516- 518 Grand Junction Rd Northfield SA 5085",
    "addr:housenumber":"518",
    "addr:postcode":"5085",
    "addr:street":"Grand Junction Rd",
    "iso:country":"AU",
    "sg:address":"516- 518 Grand Junction Rd",
    "sg:city":"Northfield",
    "sg:classifiers":[
        {
            "category":"Wholesale",
            "subcategory":"Home Furnishings",
            "type":"Manufacturing & Wholesale Goods"
        }
    ],
    "sg:phone":"+61 8 8262 5033",
    "sg:postcode":"5085",
    "sg:province":"SA",
    "wof:name":"Remlap Tracking Pty Ltd",
    "wof:placetype":"venue"
},
  "geometry": {"coordinates":[138.62408447300001,-34.8475112915],"type":"Point"}
}