{
  "type": "Feature",
  "properties": {
    "addr:full":"92 Wheatsheaf Rd Morphett Vale SA 5162",
    "addr:housenumber":"92",
    "addr:postcode":"5162",
    "addr:street":"Wheatsheaf Rd",
    "iso:country":"AU",
    "sg:address":"92 Wheatsheaf Rd",
    "sg:city":"Morphett Vale",
    "sg:classifiers":[
        {
            "category":"Arts & Performance",
            "subcategory":"Dance",
            "type":"Entertainment"
        }
    ],
    "sg:phone":"+61 8 8348 4491",
    "sg:postcode":"5162",
    "sg:province":"SA",
    "sg:tags":[
        "theatrical",
        "ballet",
        "tuition"
    ],
    "wof:name":"Jennifer Marshall School Of Dance",
    "wof:placetype":"venue"
},
  "geometry": {"coordinates":[138.53007507300001,-35.1260490417],"type":"Point"}
}