{
  "type": "Feature",
  "properties": {
    "addr:full":"67 Sainsbury Ave Greensborough VIC 3088",
    "addr:housenumber":"67",
    "addr:postcode":"3088",
    "addr:street":"Sainsbury Ave",
    "iso:country":"AU",
    "sg:address":"67 Sainsbury Ave",
    "sg:city":"Greensborough",
    "sg:classifiers":[
        {
            "category":"Insurance",
            "subcategory":"Hazard Insurance",
            "type":"Services"
        }
    ],
    "sg:phone":"+61 3 9432 1667",
    "sg:postcode":"3088",
    "sg:province":"VIC",
    "sg:tags":[
        "fire",
        "accident",
        "marine"
    ],
    "wof:name":"Lanham Russell",
    "wof:placetype":"venue"
},
  "geometry": {"coordinates":[145.097045898,-37.7119674683],"type":"Point"}
}