{
  "type": "Feature",
  "properties": {
    "iso:country":"AU",
    "sg:address":"54 Barker Drv",
    "sg:city":"Duncraig",
    "sg:classifiers":[
        {
            "category":"Education",
            "subcategory":"Special Training",
            "type":"Public Place"
        }
    ],
    "sg:phone":"+61 8 9246 5389",
    "sg:postcode":"6023",
    "sg:province":"WA",
    "sg:tags":[
        "development"
    ],
    "wof:name":"Top Trainers",
    "wof:placetype":"venue"
},
  "geometry": {"coordinates":[115.76875305199999,-31.8269500732],"type":"Point"}
}