{
  "type": "Feature",
  "properties": {
    "addr:full":"PO Box 485 Alstonville NSW 2477",
    "addr:postcode":"2477",
    "iso:country":"AU",
    "sg:address":"PO Box 485",
    "sg:city":"Alstonville",
    "sg:classifiers":[
        {
            "category":"Building & Trades",
            "subcategory":"Landscaping Services",
            "type":"Services"
        }
    ],
    "sg:phone":"+61 428 413 721",
    "sg:postcode":"2477",
    "sg:province":"NSW",
    "sg:tags":[
        "designer",
        "landscape",
        "contractor"
    ],
    "wof:name":"Tropical Trends",
    "wof:placetype":"venue"
},
  "geometry": {"coordinates":[153.44003295900001,-28.8416900635],"type":"Point"}
}