{
  "type": "Feature",
  "properties": {
    "iso:country":"AU",
    "sg:address":"PO Box 327",
    "sg:city":"Box Hill",
    "sg:classifiers":[
        {
            "category":"Professional",
            "subcategory":"Employment Agencies",
            "type":"Services"
        }
    ],
    "sg:phone":"+61 3 9877 9666",
    "sg:postcode":"3128",
    "sg:province":"VIC",
    "wof:name":"A Inter-Chefs & Staff Pty Ltd",
    "wof:placetype":"venue"
},
  "geometry": {"coordinates":[145.12399292000001,-37.8176612854],"type":"Point"}
}