{
  "type": "Feature",
  "properties": {
    "addr:full":"Cnr Kelly & Montague Rds Modbury SA 5092",
    "addr:postcode":"5092",
    "addr:street":"Cnr",
    "iso:country":"AU",
    "sg:address":"Cnr Kelly & Montague Rds",
    "sg:city":"Modbury",
    "sg:classifiers":[
        {
            "category":"Retail",
            "subcategory":"Auto Repair",
            "type":"Services"
        }
    ],
    "sg:phone":"+61 8 8264 1864",
    "sg:postcode":"5092",
    "sg:province":"SA",
    "sg:tags":[
        "repairer",
        "motor",
        "engineer"
    ],
    "wof:name":"Mobil Car Care",
    "wof:placetype":"venue"
},
  "geometry": {"coordinates":[138.692306519,-34.8279724121],"type":"Point"}
}