{
  "type": "Feature",
  "properties": {
    "addr:full":"9 Oporto Rd Mudgee NSW 2850",
    "addr:housenumber":"9",
    "addr:postcode":"2850",
    "addr:street":"Oporto Rd",
    "iso:country":"AU",
    "sg:address":"9 Oporto Rd",
    "sg:city":"Mudgee",
    "sg:classifiers":[
        {
            "category":"Health Services",
            "subcategory":"Doctor",
            "type":"Services"
        }
    ],
    "sg:phone":"+61 2 6372 4355",
    "sg:postcode":"2850",
    "sg:province":"NSW",
    "sg:tags":[
        "medical",
        "practitioner"
    ],
    "wof:name":"Moore G Dr",
    "wof:placetype":"venue"
},
  "geometry": {"coordinates":[149.58201600000001,-32.607475],"type":"Point"}
}