{
  "type": "Feature",
  "properties": {
    "addr:full":"50 Balaclava Rd Shepparton VIC 3630",
    "addr:housenumber":"50",
    "addr:postcode":"3630",
    "addr:street":"Balaclava Rd",
    "iso:country":"AU",
    "sg:address":"50 Balaclava Rd",
    "sg:city":"Shepparton",
    "sg:classifiers":[
        {
            "category":"Shopping",
            "subcategory":"Computers & Home Electronics",
            "type":"Retail Goods"
        }
    ],
    "sg:phone":"+61 3 5821 5449",
    "sg:postcode":"3630",
    "sg:province":"VIC",
    "sg:tags":[
        "equipment",
        "multimedia"
    ],
    "wof:name":"GV Multimedia",
    "wof:placetype":"venue"
},
  "geometry": {"coordinates":[145.39616394000001,-36.3659210205],"type":"Point"}
}