{
  "type": "Feature",
  "properties": {
    "iso:country":"AU",
    "sg:address":"73 Lake Rd",
    "sg:city":"Port Macquarie",
    "sg:classifiers":[
        {
            "category":"Health Services",
            "subcategory":"Chiropractor",
            "type":"Services"
        }
    ],
    "sg:phone":"+61 2 6583 1449",
    "sg:postcode":"2444",
    "sg:province":"NSW",
    "wof:name":"Lake Rd Centre for Spine-Related Disorders",
    "wof:placetype":"venue"
},
  "geometry": {"coordinates":[152.90799,-31.442751],"type":"Point"}
}