{
  "type": "Feature",
  "properties": {
    "addr:full":"Shop 3 41, Level 3, Castle Hill Shopping Centre Cast NSW 2154",
    "addr:housenumber":"shop;41 level 3",
    "addr:postcode":"2154",
    "addr:street":"Castle",
    "iso:country":"AU",
    "sg:address":"Shop 3",
    "sg:city":"41, Level 3, Castle Hill Shopping Centre Cast",
    "sg:classifiers":[
        {
            "category":"Health Services",
            "subcategory":"Doctor",
            "type":"Services"
        }
    ],
    "sg:phone":"+61 1300 889 935",
    "sg:postcode":"2154",
    "sg:province":"NSW",
    "sg:tags":[
        "medical",
        "practitioner"
    ],
    "wof:name":"IPL/Laser & Facial Rejuvenation Medical Cosmetic Clinic",
    "wof:placetype":"venue"
},
  "geometry": {"coordinates":[151.02679443400001,-33.7328033447],"type":"Point"}
}