{
  "type": "Feature",
  "properties": {
    "iso:country":"AU",
    "sg:address":"2b Clements St",
    "sg:city":"Moranbah",
    "sg:classifiers":[
        {
            "category":"Banks & Credit Unions",
            "subcategory":"Bank",
            "type":"Services"
        }
    ],
    "sg:phone":"+61 7 4941 5753",
    "sg:postcode":"4744",
    "sg:province":"QLD",
    "sg:tags":[
        "society"
    ],
    "wof:name":"Big Sky Credit Union",
    "wof:placetype":"venue"
},
  "geometry": {"coordinates":[148.06106567399999,-22.0001983643],"type":"Point"}
}