{
  "type": "Feature",
  "properties": {
    "addr:full":"4 Delmont Pl Mandurah WA 6210",
    "addr:housenumber":"4",
    "addr:postcode":"6210",
    "addr:street":"Delmont Pl",
    "iso:country":"AU",
    "sg:address":"4 Delmont Pl",
    "sg:city":"Mandurah",
    "sg:classifiers":[
        {
            "category":"Wholesale",
            "subcategory":"Metals & Minerals",
            "type":"Manufacturing & Wholesale Goods"
        }
    ],
    "sg:phone":"+61 8 9581 8281",
    "sg:postcode":"6210",
    "sg:province":"WA",
    "sg:tags":[
        "steel",
        "stainless",
        "product",
        "equipment"
    ],
    "wof:name":"Bouvard Marine",
    "wof:placetype":"venue"
},
  "geometry": {"coordinates":[115.751289,-32.512779],"type":"Point"}
}