{
  "type": "Feature",
  "properties": {
    "iso:country":"AU",
    "sg:address":"Unit2/ 6 Ranton St",
    "sg:city":"Cardiff",
    "sg:classifiers":[
        {
            "category":"Professional",
            "subcategory":"Detective & Security Services",
            "type":"Services"
        }
    ],
    "sg:phone":"+61 2 4956 5179",
    "sg:postcode":"2285",
    "sg:province":"NSW",
    "sg:tags":[
        "protective",
        "rustproofing"
    ],
    "wof:name":"Cardiff Body Shop",
    "wof:placetype":"venue"
},
  "geometry": {"coordinates":[151.64747619600001,-32.9445343018],"type":"Point"}
}