{
  "type": "Feature",
  "properties": {
    "iso:country":"AU",
    "sg:address":"30 Duke St",
    "sg:city":"Karrinyup",
    "sg:classifiers":[
        {
            "category":"Education",
            "subcategory":"Special Training",
            "type":"Public Place"
        }
    ],
    "sg:phone":"+61 8 9245 8555",
    "sg:postcode":"6018",
    "sg:province":"WA",
    "sg:tags":[
        "development"
    ],
    "wof:name":"Purple Performance",
    "wof:placetype":"venue"
},
  "geometry": {"coordinates":[115.77179717999999,-31.883348465],"type":"Point"}
}