{
  "type": "Feature",
  "properties": {
    "iso:country":"AU",
    "sg:address":"1/ 32 Kessling Ave",
    "sg:city":"Kunda Park",
    "sg:classifiers":[
        {
            "category":"Building & Trades",
            "subcategory":"Equipment Rental",
            "type":"Services"
        }
    ],
    "sg:phone":"+61 7 5476 7774",
    "sg:postcode":"4556",
    "sg:province":"QLD",
    "sg:tags":[
        "fitness"
    ],
    "sg:website":"http://www.futurefit.tv",
    "wof:name":"Future Fitness Equipment",
    "wof:placetype":"venue"
},
  "geometry": {"coordinates":[153.03111267099999,-26.6673641205],"type":"Point"}
}