{
  "type": "Feature",
  "properties": {
    "iso:country":"AU",
    "sg:address":"St Huberts Rd",
    "sg:city":"Yering",
    "sg:classifiers":[
        {
            "category":"Farming",
            "subcategory":"Vineyard",
            "type":"Manufacturing & Wholesale Goods"
        }
    ],
    "sg:phone":"+61 417 301 570",
    "sg:postcode":"3770",
    "sg:province":"VIC",
    "sg:tags":[
        "winery"
    ],
    "wof:name":"Yering Farm Wines",
    "wof:placetype":"venue"
},
  "geometry": {"coordinates":[145.38436899999999,-37.691952],"type":"Point"}
}