{
  "type": "Feature",
  "properties": {
    "addr:full":"Shop 3/ 515 Brighton Rd Brighton SA 5048",
    "addr:housenumber":"shop 3 / 515",
    "addr:postcode":"5048",
    "addr:street":"Brighton Rd",
    "iso:country":"AU",
    "sg:address":"Shop 3/ 515 Brighton Rd",
    "sg:city":"Brighton",
    "sg:classifiers":[
        {
            "category":"Real Estate",
            "subcategory":"Real Estate Agent",
            "type":"Services"
        }
    ],
    "sg:phone":"+61 8 8298 3655",
    "sg:postcode":"5048",
    "sg:province":"SA",
    "wof:name":"Annette Bradshaw Real Estate",
    "wof:placetype":"venue"
},
  "geometry": {"coordinates":[138.52311700000001,-35.021118],"type":"Point"}
}