{
  "type": "Feature",
  "properties": {
    "addr:full":"6 Antill St Yennora NSW 2161",
    "addr:housenumber":"6",
    "addr:postcode":"2161",
    "addr:street":"Antill St",
    "iso:country":"AU",
    "sg:address":"6 Antill St",
    "sg:city":"Yennora",
    "sg:classifiers":[
        {
            "category":"Shopping",
            "type":"Retail Goods"
        }
    ],
    "sg:phone":"+61 2 9632 0865",
    "sg:postcode":"2161",
    "sg:province":"NSW",
    "sg:tags":[
        "product",
        "plastic"
    ],
    "wof:name":"Rose Supplies",
    "wof:placetype":"venue"
},
  "geometry": {"coordinates":[150.97750854500001,-33.8636207581],"type":"Point"}
}