{
  "type": "Feature",
  "properties": {
    "addr:full":"526 Swift St Albury NSW 2640",
    "addr:housenumber":"526",
    "addr:postcode":"2640",
    "addr:street":"Swift St",
    "iso:country":"AU",
    "sg:address":"526 Swift St",
    "sg:city":"Albury",
    "sg:classifiers":[
        {
            "category":"Banks & Credit Unions",
            "subcategory":"Financial Services",
            "type":"Services"
        }
    ],
    "sg:phone":"+61 2 6041 4755",
    "sg:postcode":"2640",
    "sg:province":"NSW",
    "sg:tags":[
        "planning"
    ],
    "wof:name":"Axa Financial Planning",
    "wof:placetype":"venue"
},
  "geometry": {"coordinates":[146.91702270499999,-36.0785980225],"type":"Point"}
}