{
  "type": "Feature",
  "properties": {
    "addr:full":"74 Fitzgerald St Northam WA 6401",
    "addr:housenumber":"74",
    "addr:postcode":"6401",
    "addr:street":"Fitzgerald St",
    "iso:country":"AU",
    "sg:address":"74 Fitzgerald St",
    "sg:city":"Northam",
    "sg:classifiers":[
        {
            "category":"Deli",
            "type":"Food & Drink"
        }
    ],
    "sg:phone":"+61 8 9622 1121",
    "sg:postcode":"6401",
    "sg:province":"WA",
    "sg:tags":[
        "delicatessen"
    ],
    "wof:name":"Northam Quickserve",
    "wof:placetype":"venue"
},
  "geometry": {"coordinates":[116.67347717299999,-31.6505146027],"type":"Point"}
}