{
  "type": "Feature",
  "properties": {
    "iso:country":"AU",
    "sg:address":"322b Pakington St",
    "sg:city":"Newtown",
    "sg:classifiers":[
        {
            "category":"Shopping",
            "subcategory":"Clothing, Apparel, & Fashions",
            "type":"Retail Goods"
        }
    ],
    "sg:phone":"+61 3 5221 6159",
    "sg:postcode":"3220",
    "sg:province":"VIC",
    "sg:tags":[
        "lady",
        "wear"
    ],
    "wof:name":"Jean Jones",
    "wof:placetype":"venue"
},
  "geometry": {"coordinates":[144.34556599999999,-38.155975],"type":"Point"}
}