{
  "type": "Feature",
  "properties": {
    "iso:country":"AU",
    "sg:address":"Estate Plaza 68 Sydney St",
    "sg:city":"Mackay",
    "sg:classifiers":[
        {
            "category":"Manufacturing",
            "subcategory":"Jewelry",
            "type":"Manufacturing & Wholesale Goods"
        }
    ],
    "sg:phone":"+61 7 4953 0616",
    "sg:postcode":"4740",
    "sg:province":"QLD",
    "sg:tags":[
        "mfrg",
        "jeweller"
    ],
    "wof:name":"Unique Memories",
    "wof:placetype":"venue"
},
  "geometry": {"coordinates":[149.185959,-21.150127],"type":"Point"}
}