{
  "type": "Feature",
  "properties": {
    "addr:full":"Rocks Arcade, Shop 1, 214 Memorial Ave Ettalong Beach NSW 2257",
    "addr:housenumber":"1 214",
    "addr:postcode":"2257",
    "addr:street":"Memorial Ave",
    "iso:country":"AU",
    "sg:address":"Rocks Arcade, Shop 1, 214 Memorial Ave",
    "sg:city":"Ettalong Beach",
    "sg:classifiers":[
        {
            "category":"Personal",
            "subcategory":"Beauty Salon",
            "type":"Services"
        }
    ],
    "sg:phone":"+61 419 414 393",
    "sg:postcode":"2257",
    "sg:province":"NSW",
    "sg:tags":[
        "hairdresser"
    ],
    "wof:name":"Beth's Hair Affair",
    "wof:placetype":"venue"
},
  "geometry": {"coordinates":[151.334747314,-33.5104789734],"type":"Point"}
}