{
  "type": "Feature",
  "properties": {
    "addr:full":"35A Branstons Rd Middle Dural NSW 2158",
    "addr:housenumber":"35a",
    "addr:postcode":"2158",
    "addr:street":"Branstons Rd",
    "iso:country":"AU",
    "sg:address":"35A Branstons Rd",
    "sg:city":"Middle Dural",
    "sg:classifiers":[
        {
            "category":"Professional",
            "subcategory":"Computer Services",
            "type":"Services"
        }
    ],
    "sg:phone":"+61 2 9651 3084",
    "sg:postcode":"2158",
    "sg:province":"NSW",
    "sg:tags":[
        "repairs",
        "upgrade",
        "equipment"
    ],
    "wof:name":"Lame Consulting Pty Ltd",
    "wof:placetype":"venue"
},
  "geometry": {"coordinates":[151.022247314,-33.6392784119],"type":"Point"}
}