{
  "type": "Feature",
  "properties": {
    "iso:country":"AU",
    "sg:address":"1A/ 288 Great Eastern Hwy",
    "sg:city":"Ascot",
    "sg:classifiers":[
        {
            "category":"Organizations",
            "subcategory":"Labor Organization",
            "type":"Services"
        }
    ],
    "sg:phone":"+61 8 9479 6029",
    "sg:postcode":"6104",
    "sg:province":"WA",
    "sg:tags":[
        "union"
    ],
    "wof:name":"Australiasian Meat Industry",
    "wof:placetype":"venue"
},
  "geometry": {"coordinates":[115.945671081,-31.929271698],"type":"Point"}
}