{
  "type": "Feature",
  "properties": {
    "addr:full":"Shute Harbour Rd Cannonvale QLD 4802",
    "addr:postcode":"4802",
    "addr:street":"Shute Harbour Rd",
    "iso:country":"AU",
    "sg:address":"Shute Harbour Rd",
    "sg:city":"Cannonvale",
    "sg:classifiers":[
        {
            "category":"Autos & Motor Vehicles",
            "subcategory":"Fuel & Gas Station",
            "type":"Retail Goods"
        }
    ],
    "sg:phone":"+61 7 4946 6259",
    "sg:postcode":"4802",
    "sg:province":"QLD",
    "wof:name":"BP Australia Limited",
    "wof:placetype":"venue"
},
  "geometry": {"coordinates":[148.69070434599999,-20.2801074982],"type":"Point"}
}