{
  "type": "Feature",
  "properties": {
    "iso:country":"AU",
    "sg:address":"Suite 11 Silverdale Shopping Centre Silverdale Rd",
    "sg:city":"Silverdale",
    "sg:classifiers":[
        {
            "category":"Professional",
            "subcategory":"Accounting & Tax Preparation",
            "type":"Services"
        }
    ],
    "sg:phone":"+61 2 4774 2844",
    "sg:postcode":"2752",
    "sg:province":"NSW",
    "sg:tags":[
        "consultant",
        "taxation"
    ],
    "wof:name":"elg accounting & taxation",
    "wof:placetype":"venue"
},
  "geometry": {"coordinates":[150.60534668,-33.9075469971],"type":"Point"}
}