{
  "type": "Feature",
  "properties": {
    "addr:full":"Suite 1/ 529 Police Rd Mulgrave VIC 3170",
    "addr:housenumber":"/ 529",
    "addr:postcode":"3170",
    "addr:street":"Police Rd",
    "iso:country":"AU",
    "sg:address":"Suite 1/ 529 Police Rd",
    "sg:city":"Mulgrave",
    "sg:classifiers":[
        {
            "category":"Health Services",
            "subcategory":"Doctor",
            "type":"Services"
        }
    ],
    "sg:phone":"+61 3 9707 5799",
    "sg:postcode":"3170",
    "sg:province":"VIC",
    "sg:tags":[
        "medical",
        "practitioner"
    ],
    "wof:name":"Linsell Malcolm D",
    "wof:placetype":"venue"
},
  "geometry": {"coordinates":[145.211303711,-37.939037323],"type":"Point"}
}