{
  "type": "Feature",
  "properties": {
    "iso:country":"AU",
    "sg:address":"142 Aumuller St",
    "sg:city":"Cairns",
    "sg:classifiers":[
        {
            "category":"Wholesale",
            "subcategory":"Painting Supplies",
            "type":"Manufacturing & Wholesale Goods"
        }
    ],
    "sg:phone":"+61 7 4051 5474",
    "sg:postcode":"4870",
    "sg:province":"QLD",
    "sg:tags":[
        "product",
        "cleaning"
    ],
    "wof:name":"Allans Cleaning Supplies",
    "wof:placetype":"venue"
},
  "geometry": {"coordinates":[145.761917114,-16.9342975616],"type":"Point"}
}