{
  "type": "Feature",
  "properties": {
    "addr:full":"37 North St Maryborough QLD 4650",
    "addr:housenumber":"37",
    "addr:postcode":"4650",
    "addr:street":"North St",
    "iso:country":"AU",
    "sg:address":"37 North St",
    "sg:city":"Maryborough",
    "sg:classifiers":[
        {
            "category":"Professional",
            "subcategory":"Engineering",
            "type":"Services"
        }
    ],
    "sg:phone":"+61 7 4123 3113",
    "sg:postcode":"4650",
    "sg:province":"QLD",
    "sg:tags":[
        "engineer"
    ],
    "wof:name":"R.W.L. Hardchrome & Engineering",
    "wof:placetype":"venue"
},
  "geometry": {"coordinates":[152.699005,-25.527624],"type":"Point"}
}