{
  "type": "Feature",
  "properties": {
    "addr:full":"2/ 17 Teatree Ave Currumbin QLD 4223",
    "addr:housenumber":"/ 17",
    "addr:postcode":"4223",
    "addr:street":"Teatree Ave",
    "iso:country":"AU",
    "sg:address":"2/ 17 Teatree Ave",
    "sg:city":"Currumbin",
    "sg:classifiers":[
        {
            "category":"Professional",
            "subcategory":"Printing & Photocopies",
            "type":"Services"
        }
    ],
    "sg:phone":"+61 7 5534 1344",
    "sg:postcode":"4223",
    "sg:province":"QLD",
    "sg:tags":[
        "screen",
        "printer"
    ],
    "wof:name":"MNJ Designs",
    "wof:placetype":"venue"
},
  "geometry": {"coordinates":[153.47346496599999,-28.1452713013],"type":"Point"}
}