{
  "type": "Feature",
  "properties": {
    "addr:full":"181 Orlando St Coffs Harbour NSW 2450",
    "addr:housenumber":"181",
    "addr:postcode":"2450",
    "addr:street":"Orlando St",
    "iso:country":"AU",
    "sg:address":"181 Orlando St",
    "sg:city":"Coffs Harbour",
    "sg:classifiers":[
        {
            "category":"Home & Garden",
            "subcategory":"Carpets & Floor Coverings",
            "type":"Retail Goods"
        }
    ],
    "sg:phone":"+61 2 6652 5611",
    "sg:postcode":"2450",
    "sg:province":"NSW",
    "sg:tags":[
        "tile",
        "wall"
    ],
    "wof:name":"Coffs Ceramic Centre",
    "wof:placetype":"venue"
},
  "geometry": {"coordinates":[153.12849399999999,-30.28606],"type":"Point"}
}