{
  "type": "Feature",
  "properties": {
    "addr:full":"5 Aztec Crt Mulgrave VIC 3170",
    "addr:housenumber":"5",
    "addr:postcode":"3170",
    "addr:street":"Aztec Crt",
    "iso:country":"AU",
    "sg:address":"5 Aztec Crt",
    "sg:city":"Mulgrave",
    "sg:classifiers":[
        {
            "category":"Building & Trades",
            "subcategory":"Plumbing",
            "type":"Services"
        }
    ],
    "sg:phone":"+61 3 9561 8368",
    "sg:postcode":"3170",
    "sg:province":"VIC",
    "sg:tags":[
        "plumber",
        "gasfitters"
    ],
    "wof:name":"A. AAABA Aztec Plumbing",
    "wof:placetype":"venue"
},
  "geometry": {"coordinates":[145.18716430699999,-37.905380249],"type":"Point"}
}