{
  "type": "Feature",
  "properties": {
    "addr:full":"13 Boughton Ave Yellow Rock (Wollongong) NSW 2527",
    "addr:housenumber":"13",
    "addr:postcode":"2527",
    "addr:street":"Boughton Ave",
    "iso:country":"AU",
    "sg:address":"13 Boughton Ave",
    "sg:city":"Yellow Rock (Wollongong)",
    "sg:classifiers":[
        {
            "category":"Real Estate",
            "subcategory":"Developer",
            "type":"Services"
        }
    ],
    "sg:phone":"+61 2 4256 1677",
    "sg:postcode":"2527",
    "sg:province":"NSW",
    "sg:tags":[
        "development"
    ],
    "wof:name":"Tullimbar Village Information Centre",
    "wof:placetype":"venue"
},
  "geometry": {"coordinates":[150.754516602,-34.5782699585],"type":"Point"}
}