{
  "type": "Feature",
  "properties": {
    "iso:country":"AU",
    "sg:address":"Unit 6 651 Victoria St",
    "sg:city":"Abbotsford",
    "sg:classifiers":[
        {
            "category":"Health Services",
            "subcategory":"Health Practitioner",
            "type":"Services"
        }
    ],
    "sg:phone":"+61 3 9429 1799",
    "sg:postcode":"3067",
    "sg:province":"VIC",
    "sg:tags":[
        "physiotherapist"
    ],
    "wof:name":"Australian Physiotherapy Association+ (Victorian Branch)",
    "wof:placetype":"venue"
},
  "geometry": {"coordinates":[145.01045227,-37.8112831116],"type":"Point"}
}