{
  "type": "Feature",
  "properties": {
    "addr:full":"Royal St Maroubra NSW 2035",
    "addr:postcode":"2035",
    "addr:street":"Royal St",
    "iso:country":"AU",
    "sg:address":"Royal St",
    "sg:city":"Maroubra",
    "sg:classifiers":[
        {
            "category":"Travel",
            "subcategory":"Travel Agent",
            "type":"Entertainment"
        }
    ],
    "sg:phone":"+61 2 9349 6900",
    "sg:postcode":"2035",
    "sg:province":"NSW",
    "sg:tags":[
        "tour",
        "holiday",
        "adventure"
    ],
    "wof:name":"Southern Cross Safaris",
    "wof:placetype":"venue"
},
  "geometry": {"coordinates":[151.23200988799999,-33.9401931763],"type":"Point"}
}