{
  "type": "Feature",
  "properties": {
    "addr:full":"5-13 Hartley St Garbutt QLD 4814",
    "addr:housenumber":"5-13",
    "addr:postcode":"4814",
    "addr:street":"Hartley St",
    "iso:country":"AU",
    "sg:address":"5-13 Hartley St",
    "sg:city":"Garbutt",
    "sg:classifiers":[
        {
            "category":"Building & Trades",
            "subcategory":"Equipment Rental",
            "type":"Services"
        }
    ],
    "sg:phone":"+61 7 4775 3588",
    "sg:postcode":"4814",
    "sg:province":"QLD",
    "sg:tags":[
        "crane",
        "hire"
    ],
    "wof:name":"North Queensland Loading Agents",
    "wof:placetype":"venue"
},
  "geometry": {"coordinates":[146.775665,-19.267807],"type":"Point"}
}