{
  "type": "Feature",
  "properties": {
    "addr:full":"Unit 1, 185 Fairfield Rd Guildford NSW 2161",
    "addr:housenumber":"185",
    "addr:postcode":"2161",
    "addr:street":"Fairfield Rd",
    "iso:country":"AU",
    "sg:address":"Unit 1, 185 Fairfield Rd",
    "sg:city":"Guildford",
    "sg:classifiers":[
        {
            "category":"Retail",
            "subcategory":"Repair Shop",
            "type":"Services"
        }
    ],
    "sg:phone":"+61 2 9892 1610",
    "sg:postcode":"2161",
    "sg:province":"NSW",
    "sg:tags":[
        "upholsterer"
    ],
    "wof:name":"Mackenzie Peter",
    "wof:placetype":"venue"
},
  "geometry": {"coordinates":[150.959640503,-33.853767395],"type":"Point"}
}