{
  "type": "Feature",
  "properties": {
    "addr:full":"7 Loftus St Leederville WA 6007",
    "addr:housenumber":"7",
    "addr:postcode":"6007",
    "addr:street":"Loftus St",
    "iso:country":"AU",
    "sg:address":"7 Loftus St",
    "sg:city":"Leederville",
    "sg:classifiers":[
        {
            "category":"Shopping",
            "subcategory":"Stationery & Office Supplies",
            "type":"Retail Goods"
        }
    ],
    "sg:phone":"+61 8 9388 8999",
    "sg:postcode":"6007",
    "sg:province":"WA",
    "sg:tags":[
        "equipment",
        "display",
        "exhibition"
    ],
    "wof:name":"Expo Digital Solutions",
    "wof:placetype":"venue"
},
  "geometry": {"coordinates":[115.845039368,-31.9400501251],"type":"Point"}
}