{
  "type": "Feature",
  "properties": {
    "iso:country":"AU",
    "sg:address":"15 Kalawa Rd",
    "sg:city":"Wyee",
    "sg:classifiers":[
        {
            "category":"Utilities",
            "subcategory":"Water",
            "type":"Services"
        }
    ],
    "sg:phone":"+61 2 4357 2811",
    "sg:postcode":"2259",
    "sg:province":"NSW",
    "sg:tags":[
        "cartage"
    ],
    "wof:name":"McLean Logistics",
    "wof:placetype":"venue"
},
  "geometry": {"coordinates":[151.47529602,-33.1749191284],"type":"Point"}
}