{
  "type": "Feature",
  "properties": {
    "addr:full":"36 McLennan St West Mackay QLD 4740",
    "addr:housenumber":"36",
    "addr:postcode":"4740",
    "addr:street":"Mclennan St",
    "iso:country":"AU",
    "sg:address":"36 McLennan St",
    "sg:city":"West Mackay",
    "sg:classifiers":[
        {
            "category":"Utilities",
            "subcategory":"Fuel Oil & Lpg",
            "type":"Services"
        }
    ],
    "sg:phone":"+61 7 4968 5100",
    "sg:postcode":"4740",
    "sg:province":"QLD",
    "sg:tags":[
        "merchant"
    ],
    "wof:name":"McDonald Murphy Fuel Services",
    "wof:placetype":"venue"
},
  "geometry": {"coordinates":[149.15057400000001,-21.164963],"type":"Point"}
}