{
  "type": "Feature",
  "properties": {
    "addr:full":"40 Wharf St Tweed Heads NSW 2485",
    "addr:housenumber":"40",
    "addr:postcode":"2485",
    "addr:street":"Wharf St",
    "iso:country":"AU",
    "sg:address":"40 Wharf St",
    "sg:city":"Tweed Heads",
    "sg:classifiers":[
        {
            "category":"Health Services",
            "subcategory":"Chiropractor",
            "type":"Services"
        }
    ],
    "sg:phone":"+61 7 5536 4249",
    "sg:postcode":"2485",
    "sg:province":"NSW",
    "wof:name":"Tripp G J",
    "wof:placetype":"venue"
},
  "geometry": {"coordinates":[153.54298400900001,-28.1725997925],"type":"Point"}
}