{
  "type": "Feature",
  "properties": {
    "addr:full":"22 Main St Cobram NSW 3644",
    "addr:housenumber":"22",
    "addr:postcode":"3644",
    "addr:street":"Main St",
    "iso:country":"AU",
    "sg:address":"22 Main St",
    "sg:city":"Cobram",
    "sg:classifiers":[
        {
            "category":"Banks & Credit Unions",
            "subcategory":"Financial Services",
            "type":"Services"
        }
    ],
    "sg:phone":"+61 3 5872 2211",
    "sg:postcode":"3644",
    "sg:province":"NSW",
    "sg:tags":[
        "loan",
        "finance",
        "mortgage"
    ],
    "wof:name":"Yellow Home Loans",
    "wof:placetype":"venue"
},
  "geometry": {"coordinates":[145.64988708499999,-35.9207954407],"type":"Point"}
}