{
  "type": "Feature",
  "properties": {
    "addr:full":"4 Herbert St Mortlake NSW 2137",
    "addr:housenumber":"4",
    "addr:postcode":"2137",
    "addr:street":"Herbert St",
    "iso:country":"AU",
    "sg:address":"4 Herbert St",
    "sg:city":"Mortlake",
    "sg:classifiers":[
        {
            "category":"Shopping",
            "subcategory":"Party Supplies",
            "type":"Retail Goods"
        }
    ],
    "sg:phone":"+61 2 9736 1469",
    "sg:postcode":"2137",
    "sg:province":"NSW",
    "sg:tags":[
        "toilet",
        "portable"
    ],
    "wof:name":"Sani Hire Pty Ltd",
    "wof:placetype":"venue"
},
  "geometry": {"coordinates":[151.10833740199999,-33.846206665],"type":"Point"}
}