{
  "type": "Feature",
  "properties": {
    "addr:full":"35 Enfield Ave Preston VIC 3072",
    "addr:housenumber":"35",
    "addr:postcode":"3072",
    "addr:street":"Enfield Ave",
    "iso:country":"AU",
    "sg:address":"35 Enfield Ave",
    "sg:city":"Preston",
    "sg:classifiers":[
        {
            "category":"Fast Food",
            "type":"Food & Drink"
        }
    ],
    "sg:phone":"+61 3 9478 8343",
    "sg:postcode":"3072",
    "sg:province":"VIC",
    "sg:tags":[
        "away",
        "take"
    ],
    "wof:name":"Preston Fish Shop",
    "wof:placetype":"venue"
},
  "geometry": {"coordinates":[145.022384644,-37.7415428162],"type":"Point"}
}