{
  "type": "Feature",
  "properties": {
    "iso:country":"AU",
    "sg:address":"Tasman Hwy",
    "sg:city":"Branxholm",
    "sg:classifiers":[
        {
            "category":"Food & Beverages",
            "subcategory":"Supermarket",
            "type":"Retail Goods"
        }
    ],
    "sg:phone":"+61 3 6354 6168",
    "sg:postcode":"7261",
    "sg:province":"TAS",
    "sg:tags":[
        "grocery",
        "store"
    ],
    "wof:name":"Branxholm Shopping Centre",
    "wof:placetype":"venue"
},
  "geometry": {"coordinates":[147.73597699999999,-41.168156],"type":"Point"}
}