{
  "type": "Feature",
  "properties": {
    "iso:country":"AU",
    "sg:address":"12 Case St",
    "sg:city":"Southport",
    "sg:classifiers":[
        {
            "category":"Building & Trades",
            "subcategory":"Construction",
            "type":"Services"
        }
    ],
    "sg:phone":"+61 7 5531 1966",
    "sg:postcode":"4215",
    "sg:province":"QLD",
    "sg:tags":[
        "scaffolding"
    ],
    "wof:name":"Superhire Pty Ltd",
    "wof:placetype":"venue"
},
  "geometry": {"coordinates":[153.40974426299999,-27.97747612],"type":"Point"}
}