{
  "type": "Feature",
  "properties": {
    "addr:full":"17 Johnson St Chatswood NSW 1502",
    "addr:housenumber":"17",
    "addr:postcode":"1502",
    "addr:street":"Johnson St",
    "iso:country":"AU",
    "sg:address":"17 Johnson St",
    "sg:city":"Chatswood",
    "sg:classifiers":[
        {
            "category":"Social Services",
            "subcategory":"Child Care",
            "type":"Services"
        }
    ],
    "sg:phone":"+61 2 9411 1759",
    "sg:postcode":"1502",
    "sg:province":"NSW",
    "wof:name":"Bambini House",
    "wof:placetype":"venue"
},
  "geometry": {"coordinates":[151.18635559099999,-33.7992401123],"type":"Point"}
}