{
  "type": "Feature",
  "properties": {
    "iso:country":"AU",
    "sg:address":"Shp 1/ 922 David Low Way",
    "sg:city":"Marcoola",
    "sg:classifiers":[
        {
            "category":"Personal",
            "subcategory":"Beauty Salon",
            "type":"Services"
        }
    ],
    "sg:phone":"+61 7 5448 7525",
    "sg:postcode":"4564",
    "sg:province":"QLD",
    "sg:tags":[
        "hairdresser"
    ],
    "wof:name":"Surf Hair",
    "wof:placetype":"venue"
},
  "geometry": {"coordinates":[153.09548950199999,-26.5990600586],"type":"Point"}
}