{
  "type": "Feature",
  "properties": {
    "iso:country":"AU",
    "sg:address":"1304 Pacific Highway St",
    "sg:city":"Turramurra",
    "sg:classifiers":[
        {
            "category":"Professional",
            "subcategory":"Computer Services",
            "type":"Services"
        }
    ],
    "sg:phone":"+61 2 9988 3746",
    "sg:postcode":"2074",
    "sg:province":"NSW",
    "sg:tags":[
        "consultant",
        "system"
    ],
    "wof:name":"Panmach Computer Services Pty Ltd",
    "wof:placetype":"venue"
},
  "geometry": {"coordinates":[151.13209533700001,-33.734752655],"type":"Point"}
}