{
  "type": "Feature",
  "properties": {
    "iso:country":"AU",
    "sg:address":"79 Monger St",
    "sg:city":"Bencubbin",
    "sg:classifiers":[
        {
            "category":"Health Services",
            "subcategory":"Doctor",
            "type":"Services"
        }
    ],
    "sg:phone":"+61 8 9685 1229",
    "sg:postcode":"6477",
    "sg:province":"WA",
    "sg:tags":[
        "nurse",
        "nursing"
    ],
    "wof:name":"Silver Chain",
    "wof:placetype":"venue"
},
  "geometry": {"coordinates":[117.863288879,-30.814573288],"type":"Point"}
}