{
  "type": "Feature",
  "properties": {
    "addr:full":"151 McLeans Rd Bundoora VIC 3083",
    "addr:housenumber":"151",
    "addr:postcode":"3083",
    "addr:street":"Mcleans Rd",
    "iso:country":"AU",
    "sg:address":"151 McLeans Rd",
    "sg:city":"Bundoora",
    "sg:classifiers":[
        {
            "category":"Education",
            "subcategory":"Kindergarten",
            "type":"Public Place"
        }
    ],
    "sg:phone":"+61 3 9467 5993",
    "sg:postcode":"3083",
    "sg:province":"VIC",
    "sg:tags":[
        "pre-schools"
    ],
    "wof:name":"McLeans Rd Kindergarten Inc.",
    "wof:placetype":"venue"
},
  "geometry": {"coordinates":[145.04417419399999,-37.6951522827],"type":"Point"}
}