{
  "type": "Feature",
  "properties": {
    "addr:full":"PO Box 131 Prospect SA 5082",
    "addr:postcode":"5082",
    "iso:country":"AU",
    "sg:address":"PO Box 131",
    "sg:city":"Prospect",
    "sg:classifiers":[
        {
            "category":"Personal",
            "type":"Services"
        }
    ],
    "sg:phone":"+61 8 8344 9994",
    "sg:postcode":"5082",
    "sg:province":"SA",
    "sg:tags":[
        "gift"
    ],
    "wof:name":"Tigerlily Floral Designers",
    "wof:placetype":"venue"
},
  "geometry": {"coordinates":[138.59417724599999,-34.8868789673],"type":"Point"}
}