{
  "type": "Feature",
  "properties": {
    "addr:full":"15 Mill Hill Rd Bondi Junction NSW 2022",
    "addr:housenumber":"15",
    "addr:postcode":"2022",
    "addr:street":"Mill Hill Rd",
    "iso:country":"AU",
    "sg:address":"15 Mill Hill Rd",
    "sg:city":"Bondi Junction",
    "sg:classifiers":[
        {
            "category":"Real Estate",
            "subcategory":"Architect",
            "type":"Services"
        }
    ],
    "sg:phone":"+61 2 9387 6133",
    "sg:postcode":"2022",
    "sg:province":"NSW",
    "wof:name":"Ormsby Kerrins Freeman Pty Ltd",
    "wof:placetype":"venue"
},
  "geometry": {"coordinates":[151.244064331,-33.8913841248],"type":"Point"}
}