{
  "type": "Feature",
  "properties": {
    "iso:country":"AU",
    "sg:address":"2a Major St",
    "sg:city":"Coogee",
    "sg:classifiers":[
        {
            "category":"Sports & Exercise",
            "subcategory":"Sports Center",
            "type":"Entertainment"
        }
    ],
    "sg:phone":"+61 2 9966 1188",
    "sg:postcode":"2034",
    "sg:province":"NSW",
    "sg:tags":[
        "coach",
        "tennis"
    ],
    "wof:name":"Tennis Professionals Marketing Pty Ltd",
    "wof:placetype":"venue"
},
  "geometry": {"coordinates":[151.26104736299999,-33.9167022705],"type":"Point"}
}