{
  "type": "Feature",
  "properties": {
    "addr:full":"4 George St Swan Hill VIC 3585",
    "addr:housenumber":"4",
    "addr:postcode":"3585",
    "addr:street":"George St",
    "iso:country":"AU",
    "sg:address":"4 George St",
    "sg:city":"Swan Hill",
    "sg:classifiers":[
        {
            "category":"Utilities",
            "type":"Services"
        }
    ],
    "sg:phone":"+61 3 5033 1822",
    "sg:postcode":"3585",
    "sg:province":"VIC",
    "sg:tags":[
        "refrigeration",
        "industrial",
        "commercial",
        "retail"
    ],
    "wof:name":"Swan Hill Refrigeration Pty Ltd",
    "wof:placetype":"venue"
},
  "geometry": {"coordinates":[143.55396999999999,-35.330498],"type":"Point"}
}