{
  "type": "Feature",
  "properties": {
    "iso:country":"AU",
    "sg:address":"46 James St",
    "sg:city":"Hamilton",
    "sg:classifiers":[
        {
            "category":"Health Services",
            "subcategory":"Doctor",
            "type":"Services"
        }
    ],
    "sg:phone":"+61 2 4961 3017",
    "sg:postcode":"2303",
    "sg:province":"NSW",
    "sg:tags":[
        "medical",
        "practitioner"
    ],
    "wof:name":"Van Leeuwen Fiona Dr",
    "wof:placetype":"venue"
},
  "geometry": {"coordinates":[151.747635,-32.922939],"type":"Point"}
}