{
  "type": "Feature",
  "properties": {
    "iso:country":"AU",
    "sg:address":"2/ 6 Parr Pl",
    "sg:city":"Karabar",
    "sg:classifiers":[
        {
            "category":"Professional",
            "subcategory":"Art Services",
            "type":"Services"
        }
    ],
    "sg:phone":"+61 2 6297 8170",
    "sg:postcode":"2620",
    "sg:province":"ACT",
    "sg:tags":[
        "graphic",
        "designer"
    ],
    "wof:name":"Mark 1 Designs",
    "wof:placetype":"venue"
},
  "geometry": {"coordinates":[149.228027344,-35.3601341248],"type":"Point"}
}