{
  "type": "Feature",
  "properties": {
    "addr:full":"2 Willeys Rd Mt Macedon VIC 3441",
    "addr:housenumber":"2",
    "addr:postcode":"3441",
    "addr:street":"Willeys Rd",
    "iso:country":"AU",
    "sg:address":"2 Willeys Rd",
    "sg:city":"Mt Macedon",
    "sg:classifiers":[
        {
            "category":"Building & Trades",
            "subcategory":"Plumbing",
            "type":"Services"
        }
    ],
    "sg:phone":"+61 3 5426 4243",
    "sg:postcode":"3441",
    "sg:province":"VIC",
    "sg:tags":[
        "plumber",
        "gasfitters"
    ],
    "wof:name":"Advanced Plumbing",
    "wof:placetype":"venue"
},
  "geometry": {"coordinates":[144.59248352,-37.389881134],"type":"Point"}
}