{
  "type": "Feature",
  "properties": {
    "iso:country":"AU",
    "sg:address":"69 Sherwood Rd",
    "sg:city":"Toowong",
    "sg:classifiers":[
        {
            "category":"Health Services",
            "subcategory":"Doctor",
            "type":"Services"
        }
    ],
    "sg:phone":"+61 7 3217 7066",
    "sg:postcode":"4066",
    "sg:province":"QLD",
    "sg:tags":[
        "medical",
        "practitioner"
    ],
    "wof:name":"Ah Yui Leslie",
    "wof:placetype":"venue"
},
  "geometry": {"coordinates":[152.98963928200001,-27.4850215912],"type":"Point"}
}