{
  "type": "Feature",
  "properties": {
    "addr:full":"6 Douglas St Noble Park VIC 3174",
    "addr:housenumber":"6",
    "addr:postcode":"3174",
    "addr:street":"Douglas St",
    "iso:country":"AU",
    "sg:address":"6 Douglas St",
    "sg:city":"Noble Park",
    "sg:classifiers":[
        {
            "category":"Restaurant",
            "type":"Food & Drink"
        }
    ],
    "sg:phone":"+61 3 9547 4747",
    "sg:postcode":"3174",
    "sg:province":"VIC",
    "wof:name":"Charlies Pizza Restaurant",
    "wof:placetype":"venue"
},
  "geometry": {"coordinates":[145.17369079599999,-37.9655227661],"type":"Point"}
}