{
  "type": "Feature",
  "properties": {
    "addr:full":"Suite 24/ 550 Bunnerong Rd Matraville NSW 2036",
    "addr:housenumber":"24 / 550",
    "addr:postcode":"2036",
    "addr:street":"Bunnerong Rd",
    "iso:country":"AU",
    "sg:address":"Suite 24/ 550 Bunnerong Rd",
    "sg:city":"Matraville",
    "sg:classifiers":[
        {
            "category":"Shopping",
            "subcategory":"Computers & Home Electronics",
            "type":"Retail Goods"
        }
    ],
    "sg:phone":"+61 2 9311 7714",
    "sg:postcode":"2036",
    "sg:province":"NSW",
    "sg:tags":[
        "equipment",
        "supply"
    ],
    "wof:name":"Jet Tec Australia",
    "wof:placetype":"venue"
},
  "geometry": {"coordinates":[151.23106384299999,-33.9601135254],"type":"Point"}
}