{
  "type": "Feature",
  "properties": {
    "iso:country":"AU",
    "sg:address":"404 North East Rd",
    "sg:city":"Windsor Gardens",
    "sg:classifiers":[
        {
            "category":"Personal",
            "subcategory":"Beauty Salon",
            "type":"Services"
        }
    ],
    "sg:phone":"+61 8 8369 0100",
    "sg:postcode":"5087",
    "sg:province":"SA",
    "wof:name":"Temporal Beauty",
    "wof:placetype":"venue"
},
  "geometry": {"coordinates":[138.64468383799999,-34.8656921387],"type":"Point"}
}