{
  "type": "Feature",
  "properties": {
    "iso:country":"AU",
    "sg:address":"Cnr Broke Rd & Wine Country Drv",
    "sg:city":"Pokolbin",
    "sg:classifiers":[
        {
            "category":"Farming",
            "subcategory":"Vineyard",
            "type":"Manufacturing & Wholesale Goods"
        }
    ],
    "sg:phone":"+61 2 4998 7881",
    "sg:postcode":"2320",
    "sg:province":"NSW",
    "sg:tags":[
        "winery"
    ],
    "wof:name":"Peterson's Champagne House Limited",
    "wof:placetype":"venue"
},
  "geometry": {"coordinates":[151.33836364699999,-32.7768173218],"type":"Point"}
}