{
  "type": "Feature",
  "properties": {
    "addr:full":"PO Box 481 Littlehampton SA 5250",
    "addr:postcode":"5250",
    "iso:country":"AU",
    "sg:address":"PO Box 481",
    "sg:city":"Littlehampton",
    "sg:classifiers":[
        {
            "category":"Shopping",
            "subcategory":"Party Supplies",
            "type":"Retail Goods"
        }
    ],
    "sg:phone":"+61 8 8188 0337",
    "sg:postcode":"5250",
    "sg:province":"SA",
    "wof:name":"Howard & Sons Pyrotechnic Displays",
    "wof:placetype":"venue"
},
  "geometry": {"coordinates":[138.853713989,-35.0545082092],"type":"Point"}
}