{
  "type": "Feature",
  "properties": {
    "iso:country":"AU",
    "sg:address":"82a Henderson Rd",
    "sg:city":"Alexandria",
    "sg:classifiers":[
        {
            "category":"Arts & Performance",
            "subcategory":"Theater",
            "type":"Entertainment"
        }
    ],
    "sg:phone":"+61 2 9319 6909",
    "sg:postcode":"2015",
    "sg:province":"NSW",
    "sg:tags":[
        "theatrical",
        "supply"
    ],
    "wof:name":"Stretch Mk# 1",
    "wof:placetype":"venue"
},
  "geometry": {"coordinates":[151.19497680699999,-33.8977546692],"type":"Point"}
}