{
  "type": "Feature",
  "properties": {
    "iso:country":"AU",
    "sg:address":"PO Box 10",
    "sg:city":"Revesby North",
    "sg:classifiers":[
        {
            "category":"Home & Garden",
            "subcategory":"Furniture",
            "type":"Retail Goods"
        }
    ],
    "sg:phone":"+61 418 416 788",
    "sg:postcode":"2212",
    "sg:province":"NSW",
    "sg:tags":[
        "business"
    ],
    "wof:name":"Peter's Spray Painting Services",
    "wof:placetype":"venue"
},
  "geometry": {"coordinates":[151.007294,-33.943581],"type":"Point"}
}