{
  "type": "Feature",
  "properties": {
    "addr:full":"73 Sutton St North Melbourne VIC 3051",
    "addr:housenumber":"73",
    "addr:postcode":"3051",
    "addr:street":"Sutton St",
    "iso:country":"AU",
    "sg:address":"73 Sutton St",
    "sg:city":"North Melbourne",
    "sg:classifiers":[
        {
            "category":"Utilities",
            "subcategory":"Recycling",
            "type":"Services"
        }
    ],
    "sg:phone":"+61 1300 765 376",
    "sg:postcode":"3051",
    "sg:province":"VIC",
    "wof:name":"In Confidence P/L",
    "wof:placetype":"venue"
},
  "geometry": {"coordinates":[144.93904113799999,-37.7922172546],"type":"Point"}
}