{
  "type": "Feature",
  "properties": {
    "iso:country":"AU",
    "sg:address":"114 Doherty Rd",
    "sg:city":"Laverton North",
    "sg:classifiers":[
        {
            "category":"Building & Trades",
            "subcategory":"Equipment Rental",
            "type":"Services"
        }
    ],
    "sg:phone":"+61 1300 555 217",
    "sg:postcode":"3026",
    "sg:province":"VIC",
    "sg:tags":[
        "crane",
        "hire"
    ],
    "wof:name":"Williamstown Crane Hire",
    "wof:placetype":"venue"
},
  "geometry": {"coordinates":[144.79556299999999,-37.828667],"type":"Point"}
}