{
  "type": "Feature",
  "properties": {
    "addr:full":"174 Church St Parramatta NSW 2150",
    "addr:housenumber":"174",
    "addr:postcode":"2150",
    "addr:street":"Church St",
    "iso:country":"AU",
    "sg:address":"174 Church St",
    "sg:city":"Parramatta",
    "sg:classifiers":[
        {
            "category":"Shopping",
            "subcategory":"Clothing, Apparel, & Fashions",
            "type":"Retail Goods"
        }
    ],
    "sg:phone":"+61 2 9635 6016",
    "sg:postcode":"2150",
    "sg:province":"NSW",
    "sg:tags":[
        "lady",
        "wear"
    ],
    "wof:name":"Miller's Fashion Club",
    "wof:placetype":"venue"
},
  "geometry": {"coordinates":[151.17979431099999,-33.8921051025],"type":"Point"}
}