{
  "type": "Feature",
  "properties": {
    "addr:full":"121 Auburn St Goulburn NSW 2580",
    "addr:housenumber":"121",
    "addr:postcode":"2580",
    "addr:street":"Auburn St",
    "iso:country":"AU",
    "sg:address":"121 Auburn St",
    "sg:city":"Goulburn",
    "sg:classifiers":[
        {
            "category":"Farming",
            "subcategory":"Fish & Marine Products",
            "type":"Manufacturing & Wholesale Goods"
        }
    ],
    "sg:phone":"+61 2 4823 5789",
    "sg:postcode":"2580",
    "sg:province":"NSW",
    "sg:tags":[
        "organic"
    ],
    "wof:name":"Cedars Organics",
    "wof:placetype":"venue"
},
  "geometry": {"coordinates":[149.71653747600001,-34.7570648193],"type":"Point"}
}