{
  "type": "Feature",
  "properties": {
    "addr:full":"3 Faulks St Kingscliff NSW 2487",
    "addr:housenumber":"3",
    "addr:postcode":"2487",
    "addr:street":"Faulks St",
    "iso:country":"AU",
    "sg:address":"3 Faulks St",
    "sg:city":"Kingscliff",
    "sg:classifiers":[
        {
            "category":"Building & Trades",
            "subcategory":"Construction",
            "type":"Services"
        }
    ],
    "sg:phone":"+61 2 6674 2323",
    "sg:postcode":"2487",
    "sg:province":"NSW",
    "sg:tags":[
        "contractor"
    ],
    "wof:name":"Barnes Peter",
    "wof:placetype":"venue"
},
  "geometry": {"coordinates":[153.57469177199999,-28.2621574402],"type":"Point"}
}