{
  "type": "Feature",
  "properties": {
    "addr:full":"54 Auburn Rd Auburn NSW 2144",
    "addr:housenumber":"54",
    "addr:postcode":"2144",
    "addr:street":"Auburn Rd",
    "iso:country":"AU",
    "sg:address":"54 Auburn Rd",
    "sg:city":"Auburn",
    "sg:classifiers":[
        {
            "category":"Real Estate",
            "subcategory":"Real Estate Agent",
            "type":"Services"
        }
    ],
    "sg:phone":"+61 2 9649 6999",
    "sg:postcode":"2144",
    "sg:province":"NSW",
    "wof:name":"Peter Shipway",
    "wof:placetype":"venue"
},
  "geometry": {"coordinates":[151.032546997,-33.8534164429],"type":"Point"}
}