{
  "type": "Feature",
  "properties": {
    "addr:full":"17 McEntee Crt Traralgon VIC 3844",
    "addr:housenumber":"17",
    "addr:postcode":"3844",
    "addr:street":"Mcentee Crt",
    "iso:country":"AU",
    "sg:address":"17 McEntee Crt",
    "sg:city":"Traralgon",
    "sg:classifiers":[
        {
            "category":"Building & Trades",
            "subcategory":"Cleaning & Sanitation",
            "type":"Services"
        }
    ],
    "sg:phone":"+61 3 5174 4436",
    "sg:postcode":"3844",
    "sg:province":"VIC",
    "sg:tags":[
        "wall",
        "brick"
    ],
    "wof:name":"CAS Brickcleaning Contractors",
    "wof:placetype":"venue"
},
  "geometry": {"coordinates":[146.55340576200001,-38.2062339783],"type":"Point"}
}