{
  "type": "Feature",
  "properties": {
    "addr:full":"Nightwell Rd Borden WA 6338",
    "addr:postcode":"6338",
    "addr:street":"Nightwell Rd",
    "iso:country":"AU",
    "sg:address":"Nightwell Rd",
    "sg:city":"Borden",
    "sg:classifiers":[
        {
            "category":"Farming",
            "subcategory":"Farm",
            "type":"Manufacturing & Wholesale Goods"
        }
    ],
    "sg:phone":"+61 8 9828 9050",
    "sg:postcode":"6338",
    "sg:province":"WA",
    "sg:tags":[
        "farmer"
    ],
    "wof:name":"McLennan M A",
    "wof:placetype":"venue"
},
  "geometry": {"coordinates":[118.27417755099999,-34.0956802368],"type":"Point"}
}