{
  "type": "Feature",
  "properties": {
    "addr:full":"4 Ashwater Crs Penguin TAS 7316",
    "addr:housenumber":"4",
    "addr:postcode":"7316",
    "addr:street":"Ashwater Crs",
    "iso:country":"AU",
    "sg:address":"4 Ashwater Crs",
    "sg:city":"Penguin",
    "sg:classifiers":[
        {
            "category":"Building & Trades",
            "subcategory":"Landscaping Services",
            "type":"Services"
        }
    ],
    "sg:phone":"+61 3 6437 0906",
    "sg:postcode":"7316",
    "sg:province":"TAS",
    "sg:tags":[
        "gardener"
    ],
    "wof:name":"Penguin Home & Garden Maintenance",
    "wof:placetype":"venue"
},
  "geometry": {"coordinates":[146.06695556599999,-41.1111183167],"type":"Point"}
}