{
  "type": "Feature",
  "properties": {
    "addr:full":"Bellminer Downs 351 Lysterfield Rd Lysterfield VIC 3156",
    "addr:housenumber":"351",
    "addr:postcode":"3156",
    "addr:street":"Lysterfield Rd",
    "iso:country":"AU",
    "sg:address":"Bellminer Downs 351 Lysterfield Rd",
    "sg:city":"Lysterfield",
    "sg:classifiers":[
        {
            "category":"Building & Trades",
            "subcategory":"Landscaping Services",
            "type":"Services"
        }
    ],
    "sg:phone":"+61 3 9758 0101",
    "sg:postcode":"3156",
    "sg:province":"VIC",
    "sg:tags":[
        "control",
        "weed"
    ],
    "wof:name":"Ascat Pty Ltd",
    "wof:placetype":"venue"
},
  "geometry": {"coordinates":[145.300018311,-37.9162712097],"type":"Point"}
}