{
  "type": "Feature",
  "properties": {
    "addr:full":"89 Dunne St Kingsbury VIC 3083",
    "addr:housenumber":"89",
    "addr:postcode":"3083",
    "addr:street":"Dunne St",
    "iso:country":"AU",
    "sg:address":"89 Dunne St",
    "sg:city":"Kingsbury",
    "sg:classifiers":[
        {
            "category":"Autos & Motor Vehicles",
            "subcategory":"Fuel & Gas Station",
            "type":"Retail Goods"
        }
    ],
    "sg:phone":"+61 3 9469 4720",
    "sg:postcode":"3083",
    "sg:province":"VIC",
    "wof:name":"Kingsbury Motors",
    "wof:placetype":"venue"
},
  "geometry": {"coordinates":[145.03408813499999,-37.7135276794],"type":"Point"}
}