{
  "type": "Feature",
  "properties": {
    "addr:full":"PO Box 365 Horsley Park NSW 2175",
    "addr:postcode":"2175",
    "iso:country":"AU",
    "sg:address":"PO Box 365",
    "sg:city":"Horsley Park",
    "sg:classifiers":[
        {
            "category":"Shopping",
            "subcategory":"Party Supplies",
            "type":"Retail Goods"
        }
    ],
    "sg:phone":"+61 417 677 305",
    "sg:postcode":"2175",
    "sg:province":"NSW",
    "sg:tags":[
        "selling",
        "plan"
    ],
    "wof:name":"Pure Mist Fragrances & Accessories",
    "wof:placetype":"venue"
},
  "geometry": {"coordinates":[150.85403442399999,-33.8411483765],"type":"Point"}
}