{
  "type": "Feature",
  "properties": {
    "iso:country":"AU",
    "sg:address":"2 Ross Crt",
    "sg:city":"Mt Waverley",
    "sg:classifiers":[
        {
            "category":"Shopping",
            "type":"Retail Goods"
        }
    ],
    "sg:phone":"+61 3 9803 1592",
    "sg:postcode":"3149",
    "sg:province":"VIC",
    "sg:tags":[
        "supply",
        "religious",
        "church"
    ],
    "wof:name":"L G Religious Requisites",
    "wof:placetype":"venue"
},
  "geometry": {"coordinates":[145.14112854000001,-37.8929290771],"type":"Point"}
}