{
  "type": "Feature",
  "properties": {
    "addr:full":"10 Onyx Crt Narre Warren North VIC 3804",
    "addr:housenumber":"10",
    "addr:postcode":"3804",
    "addr:street":"Onyx Crt",
    "iso:country":"AU",
    "sg:address":"10 Onyx Crt",
    "sg:city":"Narre Warren North",
    "sg:classifiers":[
        {
            "category":"Professional",
            "subcategory":"Accounting & Tax Preparation",
            "type":"Services"
        }
    ],
    "sg:phone":"+61 3 9796 7242",
    "sg:postcode":"3804",
    "sg:province":"VIC",
    "sg:tags":[
        "bookkeeping"
    ],
    "wof:name":"Commercial Bookkeeping & Accounting Services",
    "wof:placetype":"venue"
},
  "geometry": {"coordinates":[145.31333923299999,-37.9981079102],"type":"Point"}
}