{
  "type": "Feature",
  "properties": {
    "iso:country":"AU",
    "sg:address":"13/ 1a Carrington Rd",
    "sg:city":"Toowoomba City",
    "sg:classifiers":[
        {
            "category":"Wholesale",
            "subcategory":"Machinery & Supplies",
            "type":"Manufacturing & Wholesale Goods"
        }
    ],
    "sg:phone":"+61 1800 108 909",
    "sg:postcode":"4350",
    "sg:province":"QLD",
    "sg:tags":[
        "agricultural"
    ],
    "wof:name":"Wolff Equipment",
    "wof:placetype":"venue"
},
  "geometry": {"coordinates":[151.879074,-27.542391],"type":"Point"}
}