{
  "type": "Feature",
  "properties": {
    "addr:full":"23 Gascoigne St Willow Vale NSW 2575",
    "addr:housenumber":"23",
    "addr:postcode":"2575",
    "addr:street":"Gascoigne St",
    "iso:country":"AU",
    "sg:address":"23 Gascoigne St",
    "sg:city":"Willow Vale",
    "sg:classifiers":[
        {
            "category":"Building & Trades",
            "subcategory":"Construction",
            "type":"Services"
        }
    ],
    "sg:phone":"+61 418 280 699",
    "sg:postcode":"2575",
    "sg:province":"NSW",
    "sg:tags":[
        "stonework",
        "stone",
        "mason"
    ],
    "wof:name":"Keeley Ian & Son",
    "wof:placetype":"venue"
},
  "geometry": {"coordinates":[150.46881103499999,-34.433719635],"type":"Point"}
}