{
  "type": "Feature",
  "properties": {
    "iso:country":"AU",
    "sg:address":"40 Orr St",
    "sg:city":"Maddington",
    "sg:classifiers":[
        {
            "category":"Organizations",
            "subcategory":"Community Association",
            "type":"Services"
        }
    ],
    "sg:phone":"+61 8 9493 7200",
    "sg:postcode":"6109",
    "sg:province":"WA",
    "sg:tags":[
        "organisation",
        "family",
        "welfare"
    ],
    "wof:name":"CLAN (Community Link and Network)",
    "wof:placetype":"venue"
},
  "geometry": {"coordinates":[115.982711792,-32.0520248413],"type":"Point"}
}