{
  "type": "Feature",
  "properties": {
    "addr:full":"188 Ward St North Adelaide SA 5006",
    "addr:housenumber":"188",
    "addr:postcode":"5006",
    "addr:street":"Ward St",
    "iso:country":"AU",
    "sg:address":"188 Ward St",
    "sg:city":"North Adelaide",
    "sg:classifiers":[
        {
            "category":"Professional",
            "subcategory":"Accounting & Tax Preparation",
            "type":"Services"
        }
    ],
    "sg:phone":"+61 8 8267 1955",
    "sg:postcode":"5006",
    "sg:province":"SA",
    "sg:tags":[
        "accountant",
        "auditor"
    ],
    "wof:name":"Adam M R & Co Pty",
    "wof:placetype":"venue"
},
  "geometry": {"coordinates":[138.594360352,-34.9090766907],"type":"Point"}
}