{
  "type": "Feature",
  "properties": {
    "addr:full":"Kirkwood St Armidale NSW 2350",
    "addr:postcode":"2350",
    "addr:street":"St",
    "iso:country":"AU",
    "sg:address":"Kirkwood St",
    "sg:city":"Armidale",
    "sg:classifiers":[
        {
            "category":"Education",
            "subcategory":"School",
            "type":"Public Place"
        }
    ],
    "sg:phone":"+61 2 6772 1666",
    "sg:postcode":"2350",
    "sg:province":"NSW",
    "sg:tags":[
        "co-educational"
    ],
    "wof:name":"O'Connor Catholic High School",
    "wof:placetype":"venue"
},
  "geometry": {"coordinates":[151.66940307600001,-30.5103588104],"type":"Point"}
}