{
  "type": "Feature",
  "properties": {
    "addr:full":"PO Box 403 Sandy Bay TAS 7006",
    "addr:postcode":"7006",
    "iso:country":"AU",
    "sg:address":"PO Box 403",
    "sg:city":"Sandy Bay",
    "sg:classifiers":[
        {
            "category":"Communications",
            "subcategory":"News Services",
            "type":"Services"
        }
    ],
    "sg:phone":"+61 3 6239 1080",
    "sg:postcode":"7006",
    "sg:province":"TAS",
    "sg:tags":[
        "information",
        "tourist",
        "attractions"
    ],
    "wof:name":"Rafting Tasmania",
    "wof:placetype":"venue"
},
  "geometry": {"coordinates":[147.35438537600001,-42.9128265381],"type":"Point"}
}