{
  "type": "Feature",
  "properties": {
    "iso:country":"AU",
    "sg:address":"5/ 334 Highbury Rd",
    "sg:city":"Mt Waverley",
    "sg:classifiers":[
        {
            "category":"Professional",
            "subcategory":"Computer Services",
            "type":"Services"
        }
    ],
    "sg:phone":"+61 3 9881 9881",
    "sg:postcode":"3149",
    "sg:province":"VIC",
    "sg:tags":[
        "consultant",
        "system"
    ],
    "wof:name":"Permian World Class Systems",
    "wof:placetype":"venue"
},
  "geometry": {"coordinates":[145.13203430199999,-37.8577346802],"type":"Point"}
}