{
  "type": "Feature",
  "properties": {
    "addr:full":"Cnr Childs & Epson Rds Chipping Norton NSW 2170",
    "addr:postcode":"2170",
    "addr:street":"Cnr",
    "iso:country":"AU",
    "sg:address":"Cnr Childs & Epson Rds",
    "sg:city":"Chipping Norton",
    "sg:classifiers":[
        {
            "category":"Food & Beverages",
            "subcategory":"Supermarket",
            "type":"Retail Goods"
        }
    ],
    "sg:phone":"+61 2 9724 0046",
    "sg:postcode":"2170",
    "sg:province":"NSW",
    "sg:tags":[
        "grocery",
        "store"
    ],
    "wof:name":"IGA Rite-Way Supermarkets",
    "wof:placetype":"venue"
},
  "geometry": {"coordinates":[150.96168518100001,-33.919002533],"type":"Point"}
}