{
  "type": "Feature",
  "properties": {
    "addr:full":"Shop 6 Kalander St Nowra East NSW 2541",
    "addr:housenumber":"shop 6",
    "addr:postcode":"2541",
    "addr:street":"Kalander St",
    "iso:country":"AU",
    "sg:address":"Shop 6 Kalander St",
    "sg:city":"Nowra East",
    "sg:classifiers":[
        {
            "category":"Fast Food",
            "type":"Food & Drink"
        }
    ],
    "sg:phone":"+61 2 4421 8977",
    "sg:postcode":"2541",
    "sg:province":"NSW",
    "sg:tags":[
        "away",
        "take"
    ],
    "wof:name":"East Nowra Chinese Take-Away",
    "wof:placetype":"venue"
},
  "geometry": {"coordinates":[150.60786438,-34.8881645203],"type":"Point"}
}