{
  "type": "Feature",
  "properties": {
    "iso:country":"AU",
    "sg:address":"150 St Leonards Rd St",
    "sg:city":"Leonards",
    "sg:classifiers":[
        {
            "category":"Shopping",
            "subcategory":"Bicycles & Sporting Goods",
            "type":"Retail Goods"
        }
    ],
    "sg:phone":"+61 3 6339 2072",
    "sg:postcode":"7250",
    "sg:province":"TAS",
    "sg:tags":[
        "chemical",
        "equipment",
        "pool",
        "swimming"
    ],
    "wof:name":"Quality Steel Fencing",
    "wof:placetype":"venue"
},
  "geometry": {"coordinates":[147.18678283700001,-41.4477043152],"type":"Point"}
}