{
  "type": "Feature",
  "properties": {
    "addr:full":"10 Dividend St Mansfield QLD 4122",
    "addr:housenumber":"10",
    "addr:postcode":"4122",
    "addr:street":"Dividend St",
    "iso:country":"AU",
    "sg:address":"10 Dividend St",
    "sg:city":"Mansfield",
    "sg:classifiers":[
        {
            "category":"Wholesale",
            "subcategory":"Metals & Minerals",
            "type":"Manufacturing & Wholesale Goods"
        }
    ],
    "sg:phone":"+61 7 3422 8100",
    "sg:postcode":"4122",
    "sg:province":"QLD",
    "sg:tags":[
        "steel",
        "stainless",
        "product",
        "equipment"
    ],
    "wof:name":"Lennard J.L. Engineering P/L",
    "wof:placetype":"venue"
},
  "geometry": {"coordinates":[153.10365295400001,-27.5329627991],"type":"Point"}
}