{
  "type": "Feature",
  "properties": {
    "iso:country":"AU",
    "sg:address":"4 Newmam St",
    "sg:city":"Ringwood",
    "sg:classifiers":[
        {
            "category":"Manufacturing",
            "subcategory":"Rubber & Plastics",
            "type":"Manufacturing & Wholesale Goods"
        }
    ],
    "sg:phone":"+61 3 9870 3403",
    "sg:postcode":"3134",
    "sg:province":"VIC",
    "sg:tags":[
        "moulders"
    ],
    "wof:name":"Affordable Plastics Pty Ltd",
    "wof:placetype":"venue"
},
  "geometry": {"coordinates":[145.215866089,-37.8198547363],"type":"Point"}
}