{
  "type": "Feature",
  "properties": {
    "addr:full":"Lvl 1/ 25 Unley Rd Parkside SA 5063",
    "addr:housenumber":"/ 25",
    "addr:postcode":"5063",
    "addr:street":"Unley Rd",
    "iso:country":"AU",
    "sg:address":"Lvl 1/ 25 Unley Rd",
    "sg:city":"Parkside",
    "sg:classifiers":[
        {
            "category":"Professional",
            "subcategory":"Research",
            "type":"Services"
        }
    ],
    "sg:phone":"+61 8 8373 5022",
    "sg:postcode":"5063",
    "sg:province":"SA",
    "sg:tags":[
        "market"
    ],
    "wof:name":"Adelaide Focus Groups",
    "wof:placetype":"venue"
},
  "geometry": {"coordinates":[138.60711669899999,-34.9429206848],"type":"Point"}
}