{
  "type": "Feature",
  "properties": {
    "addr:full":"Unit 2 55 Park Rd Slacks Creek QLD 4127",
    "addr:housenumber":"55",
    "addr:postcode":"4127",
    "addr:street":"Park Rd",
    "iso:country":"AU",
    "sg:address":"Unit 2 55 Park Rd",
    "sg:city":"Slacks Creek",
    "sg:classifiers":[
        {
            "category":"Professional",
            "subcategory":"Research",
            "type":"Services"
        }
    ],
    "sg:phone":"+61 7 3209 4111",
    "sg:postcode":"4127",
    "sg:province":"QLD",
    "sg:tags":[
        "market"
    ],
    "wof:name":"Sheila Storrs & Associates",
    "wof:placetype":"venue"
},
  "geometry": {"coordinates":[153.12403869600001,-27.6269817352],"type":"Point"}
}