{
  "type": "Feature",
  "properties": {
    "iso:country":"AU",
    "sg:address":"3 Robyn Crt",
    "sg:city":"Drouin",
    "sg:classifiers":[
        {
            "category":"Building & Trades",
            "subcategory":"Plumbing",
            "type":"Services"
        }
    ],
    "sg:phone":"+61 3 5625 3060",
    "sg:postcode":"3818",
    "sg:province":"VIC",
    "sg:tags":[
        "pipe",
        "line",
        "contractor"
    ],
    "wof:name":"K & J Rees",
    "wof:placetype":"venue"
},
  "geometry": {"coordinates":[145.850525,-38.111504],"type":"Point"}
}