{
  "type": "Feature",
  "properties": {
    "addr:full":"10/ 180 Pacific Hwy North Sydney NSW 2060",
    "addr:housenumber":"10 / 180",
    "addr:postcode":"2060",
    "addr:street":"Pacific Hwy",
    "iso:country":"AU",
    "sg:address":"10/ 180 Pacific Hwy",
    "sg:city":"North Sydney",
    "sg:classifiers":[
        {
            "category":"Real Estate",
            "subcategory":"Architect",
            "type":"Services"
        }
    ],
    "sg:phone":"+61 2 9956 5454",
    "sg:postcode":"2060",
    "sg:province":"NSW",
    "wof:name":"Nicholas Dunn & Associates",
    "wof:placetype":"venue"
},
  "geometry": {"coordinates":[151.204956055,-33.8348693848],"type":"Point"}
}