{
  "type": "Feature",
  "properties": {
    "addr:full":"34 Newman Rd Capalaba QLD 4157",
    "addr:housenumber":"34",
    "addr:postcode":"4157",
    "addr:street":"Newman Rd",
    "iso:country":"AU",
    "sg:address":"34 Newman Rd",
    "sg:city":"Capalaba",
    "sg:classifiers":[
        {
            "category":"Manufacturing",
            "subcategory":"Tools & Machinery",
            "type":"Manufacturing & Wholesale Goods"
        }
    ],
    "sg:phone":"+61 7 3823 4720",
    "sg:postcode":"4157",
    "sg:province":"QLD",
    "wof:name":"S & Y Agencies",
    "wof:placetype":"venue"
},
  "geometry": {"coordinates":[153.206130981,-27.5313396454],"type":"Point"}
}