{
  "type": "Feature",
  "properties": {
    "addr:full":"163 Ingram Rd Acacia Ridge QLD 4110",
    "addr:housenumber":"163",
    "addr:postcode":"4110",
    "addr:street":"Ingram Rd",
    "iso:country":"AU",
    "sg:address":"163 Ingram Rd",
    "sg:city":"Acacia Ridge",
    "sg:classifiers":[
        {
            "category":"Banks & Credit Unions",
            "subcategory":"Investment Brokerage",
            "type":"Services"
        }
    ],
    "sg:phone":"+61 7 3344 4544",
    "sg:postcode":"4110",
    "sg:province":"QLD",
    "sg:tags":[
        "builder",
        "coach",
        "carriage"
    ],
    "wof:name":"Coachworks Pty Ltd",
    "wof:placetype":"venue"
},
  "geometry": {"coordinates":[153.04199218799999,-27.5880355835],"type":"Point"}
}