{
  "type": "Feature",
  "properties": {
    "addr:full":"34 Bydown St Neutral Bay NSW 2089",
    "addr:housenumber":"34",
    "addr:postcode":"2089",
    "addr:street":"Bydown St",
    "iso:country":"AU",
    "sg:address":"34 Bydown St",
    "sg:city":"Neutral Bay",
    "sg:classifiers":[
        {
            "category":"Shopping",
            "subcategory":"Computers & Home Electronics",
            "type":"Retail Goods"
        }
    ],
    "sg:phone":"+61 2 9908 8036",
    "sg:postcode":"2089",
    "sg:province":"NSW",
    "sg:tags":[
        "equipment",
        "multimedia"
    ],
    "wof:name":"Pacific Advance Media Studios",
    "wof:placetype":"venue"
},
  "geometry": {"coordinates":[151.22012329099999,-33.8314933777],"type":"Point"}
}