{
  "type": "Feature",
  "properties": {
    "addr:full":"Kennedys Drv Delacombe VIC 3356",
    "addr:postcode":"3356",
    "addr:street":"Kennedys Drv",
    "iso:country":"AU",
    "sg:address":"Kennedys Drv",
    "sg:city":"Delacombe",
    "sg:classifiers":[
        {
            "category":"Shopping",
            "subcategory":"Mobile Phones",
            "type":"Retail Goods"
        }
    ],
    "sg:phone":"+61 3 5336 2018",
    "sg:postcode":"3356",
    "sg:province":"VIC",
    "sg:tags":[
        "wholesaler",
        "mfrs",
        "electrical",
        "switchboard"
    ],
    "wof:name":"D W Controls & Automation Pty Ltd",
    "wof:placetype":"venue"
},
  "geometry": {"coordinates":[143.80708300000001,-37.572384],"type":"Point"}
}