{
  "type": "Feature",
  "properties": {
    "addr:full":"3/ 33 Hargreaves St Edmonton QLD 4869",
    "addr:housenumber":"/ 33",
    "addr:postcode":"4869",
    "addr:street":"Hargreaves St",
    "iso:country":"AU",
    "sg:address":"3/ 33 Hargreaves St",
    "sg:city":"Edmonton",
    "sg:classifiers":[
        {
            "category":"Professional",
            "subcategory":"Detective & Security Services",
            "type":"Services"
        }
    ],
    "sg:phone":"+61 418 896 143",
    "sg:postcode":"4869",
    "sg:province":"QLD",
    "sg:tags":[
        "consultant",
        "system"
    ],
    "wof:name":"Saturn Electrics",
    "wof:placetype":"venue"
},
  "geometry": {"coordinates":[145.74468994099999,-17.0004787445],"type":"Point"}
}