{
  "type": "Feature",
  "properties": {
    "addr:full":"Unit 6, 40 - 44 Munster St Port Macquarie NSW 2444",
    "addr:housenumber":"40 44",
    "addr:postcode":"2444",
    "addr:street":"Munster St",
    "iso:country":"AU",
    "sg:address":"Unit 6, 40 - 44 Munster St",
    "sg:city":"Port Macquarie",
    "sg:classifiers":[
        {
            "category":"Education",
            "subcategory":"Vocational School",
            "type":"Public Place"
        }
    ],
    "sg:phone":"+61 417 405 102",
    "sg:postcode":"2444",
    "sg:province":"NSW",
    "sg:tags":[
        "beauty"
    ],
    "wof:name":"Angel Health & Beauty Supplies",
    "wof:placetype":"venue"
},
  "geometry": {"coordinates":[152.91267400000001,-31.433968],"type":"Point"}
}