{
  "type": "Feature",
  "properties": {
    "addr:full":"11 Carrington St Adelaide SA 5000",
    "addr:housenumber":"11",
    "addr:postcode":"5000",
    "addr:street":"Carrington St",
    "iso:country":"AU",
    "sg:address":"11 Carrington St",
    "sg:city":"Adelaide",
    "sg:classifiers":[
        {
            "category":"Retail",
            "subcategory":"Event Space",
            "type":"Services"
        }
    ],
    "sg:phone":"+61 8 8212 3767",
    "sg:postcode":"5000",
    "sg:province":"SA",
    "sg:tags":[
        "function",
        "organiser"
    ],
    "wof:name":"Irish Australian Assoc Inc",
    "wof:placetype":"venue"
},
  "geometry": {"coordinates":[138.600906372,-34.9316062927],"type":"Point"}
}