{
  "type": "Feature",
  "properties": {
    "addr:full":"505 Regency Rd Sefton Park SA 5083",
    "addr:housenumber":"505",
    "addr:postcode":"5083",
    "addr:street":"Regency Rd",
    "iso:country":"AU",
    "sg:address":"505 Regency Rd",
    "sg:city":"Sefton Park",
    "sg:classifiers":[
        {
            "category":"Building & Trades",
            "subcategory":"Construction",
            "type":"Services"
        }
    ],
    "sg:phone":"+61 411 536 305",
    "sg:postcode":"5083",
    "sg:province":"SA",
    "sg:tags":[
        "brick",
        "paving"
    ],
    "wof:name":"G. & E. Landscaping",
    "wof:placetype":"venue"
},
  "geometry": {"coordinates":[138.60499572800001,-34.8736076355],"type":"Point"}
}