{
  "type": "Feature",
  "properties": {
    "addr:full":"17 Essington St Mitchell ACT 2911",
    "addr:housenumber":"17",
    "addr:postcode":"2911",
    "addr:street":"Essington St",
    "iso:country":"AU",
    "sg:address":"17 Essington St",
    "sg:city":"Mitchell",
    "sg:classifiers":[
        {
            "category":"Wholesale",
            "subcategory":"Home Furnishings",
            "type":"Manufacturing & Wholesale Goods"
        }
    ],
    "sg:phone":"+61 2 6255 5577",
    "sg:postcode":"2911",
    "sg:province":"ACT",
    "sg:tags":[
        "wholesaler",
        "mfrs",
        "kitchenware"
    ],
    "wof:name":"Axis Joinery",
    "wof:placetype":"venue"
},
  "geometry": {"coordinates":[149.14120483400001,-35.2135810852],"type":"Point"}
}