{
  "type": "Feature",
  "properties": {
    "addr:full":"48 Cronulla St Cronulla NSW 2230",
    "addr:housenumber":"48",
    "addr:postcode":"2230",
    "addr:street":"Cronulla St",
    "iso:country":"AU",
    "sg:address":"48 Cronulla St",
    "sg:city":"Cronulla",
    "sg:classifiers":[
        {
            "category":"Health Services",
            "subcategory":"Doctor",
            "type":"Services"
        }
    ],
    "sg:phone":"+61 2 9523 6822",
    "sg:postcode":"2230",
    "sg:province":"NSW",
    "sg:tags":[
        "medical",
        "practitioner"
    ],
    "wof:name":"Van Huffel W H",
    "wof:placetype":"venue"
},
  "geometry": {"coordinates":[151.152786255,-34.0529022217],"type":"Point"}
}