{
  "type": "Feature",
  "properties": {
    "addr:full":"Unit 2, 235 Finucane Rd Alexandra Hills QLD 4161",
    "addr:housenumber":"235",
    "addr:postcode":"4161",
    "addr:street":"Finucane Rd",
    "iso:country":"AU",
    "sg:address":"Unit 2, 235 Finucane Rd",
    "sg:city":"Alexandra Hills",
    "sg:classifiers":[
        {
            "category":"Education",
            "subcategory":"Music School",
            "type":"Public Place"
        }
    ],
    "sg:phone":"+61 7 3824 8564",
    "sg:postcode":"4161",
    "sg:province":"QLD",
    "sg:tags":[
        "teacher"
    ],
    "wof:name":"Weir Kathryn",
    "wof:placetype":"venue"
},
  "geometry": {"coordinates":[153.22621154800001,-27.5237598419],"type":"Point"}
}