{
  "type": "Feature",
  "properties": {
    "addr:full":"72 Dart St Oberon NSW 2787",
    "addr:housenumber":"72",
    "addr:postcode":"2787",
    "addr:street":"Dart St",
    "iso:country":"AU",
    "sg:address":"72 Dart St",
    "sg:city":"Oberon",
    "sg:classifiers":[
        {
            "category":"Health Services",
            "subcategory":"Dentist",
            "type":"Services"
        }
    ],
    "sg:phone":"+61 2 6336 0902",
    "sg:postcode":"2787",
    "sg:province":"NSW",
    "wof:name":"Kroone Dental Surgery",
    "wof:placetype":"venue"
},
  "geometry": {"coordinates":[149.85627746599999,-33.7029190063],"type":"Point"}
}