{
  "type": "Feature",
  "properties": {
    "addr:full":"51 Pitt St Parramatta NSW 2150",
    "addr:housenumber":"51",
    "addr:postcode":"2150",
    "addr:street":"Pitt St",
    "iso:country":"AU",
    "sg:address":"51 Pitt St",
    "sg:city":"Parramatta",
    "sg:classifiers":[
        {
            "category":"Personal",
            "subcategory":"Beauty Salon",
            "type":"Services"
        }
    ],
    "sg:phone":"+61 2 9633 4499",
    "sg:postcode":"2150",
    "sg:province":"NSW",
    "sg:tags":[
        "hairdresser"
    ],
    "wof:name":"Image Directions Wigs",
    "wof:placetype":"venue"
},
  "geometry": {"coordinates":[150.994308472,-33.8259963989],"type":"Point"}
}