{
  "type": "Feature",
  "properties": {
    "iso:country":"AU",
    "sg:address":"10 Wingrove Ave",
    "sg:city":"Epping",
    "sg:classifiers":[
        {
            "category":"Education",
            "subcategory":"Special Training",
            "type":"Public Place"
        }
    ],
    "sg:phone":"+61 2 9876 3210",
    "sg:postcode":"2121",
    "sg:province":"NSW",
    "sg:tags":[
        "development"
    ],
    "wof:name":"Katrina Bettington Life Coaching",
    "wof:placetype":"venue"
},
  "geometry": {"coordinates":[151.07192993199999,-33.7643165588],"type":"Point"}
}