{
  "type": "Feature",
  "properties": {
    "iso:country":"AU",
    "sg:address":"4 Scribbly Gum Crs",
    "sg:city":"Ulladulla",
    "sg:classifiers":[
        {
            "category":"Building & Trades",
            "subcategory":"Construction",
            "type":"Services"
        }
    ],
    "sg:phone":"+61 2 4455 6331",
    "sg:postcode":"2539",
    "sg:province":"NSW",
    "sg:tags":[
        "contractor"
    ],
    "wof:name":"PJH Design and Construction",
    "wof:placetype":"venue"
},
  "geometry": {"coordinates":[150.475631714,-35.3509788513],"type":"Point"}
}