{
  "type": "Feature",
  "properties": {
    "iso:country":"AU",
    "sg:address":"140 Commercial St",
    "sg:city":"East Mt Gambier",
    "sg:classifiers":[
        {
            "category":"Banks & Credit Unions",
            "subcategory":"Bureau De Change",
            "type":"Services"
        }
    ],
    "sg:phone":"+61 8 8723 2877",
    "sg:postcode":"5290",
    "sg:province":"SA",
    "sg:tags":[
        "supply",
        "equipment",
        "beating",
        "panel"
    ],
    "wof:name":"Ultrapaint Supplies.",
    "wof:placetype":"venue"
},
  "geometry": {"coordinates":[140.789536,-37.831379],"type":"Point"}
}