{
  "type": "Feature",
  "properties": {
    "addr:full":"P.O. Box 64 Quakers Hill NSW 2763",
    "addr:postcode":"2763",
    "iso:country":"AU",
    "sg:address":"P.O. Box 64",
    "sg:city":"Quakers Hill",
    "sg:classifiers":[
        {
            "category":"Professional",
            "subcategory":"Employment Agencies",
            "type":"Services"
        }
    ],
    "sg:phone":"+61 414 465 233",
    "sg:postcode":"2763",
    "sg:province":"NSW",
    "sg:tags":[
        "provider",
        "internet"
    ],
    "wof:name":"jade media",
    "wof:placetype":"venue"
},
  "geometry": {"coordinates":[150.88087463400001,-33.7347640991],"type":"Point"}
}