{
  "type": "Feature",
  "properties": {
    "addr:full":"140 Warriewood St Chandler QLD 4155",
    "addr:housenumber":"140",
    "addr:postcode":"4155",
    "addr:street":"Warriewood St",
    "iso:country":"AU",
    "sg:address":"140 Warriewood St",
    "sg:city":"Chandler",
    "sg:classifiers":[
        {
            "category":"Wholesale",
            "subcategory":"Home Furnishings",
            "type":"Manufacturing & Wholesale Goods"
        }
    ],
    "sg:phone":"+61 7 3390 3251",
    "sg:postcode":"4155",
    "sg:province":"QLD",
    "sg:tags":[
        "wholesaler",
        "bedding",
        "mfrs",
        "bed"
    ],
    "wof:name":"Flex-O-Pedic",
    "wof:placetype":"venue"
},
  "geometry": {"coordinates":[153.167236328,-27.5162029266],"type":"Point"}
}