{
  "type": "Feature",
  "properties": {
    "iso:country":"AU",
    "sg:address":"38 Stoney Creek Rd",
    "sg:city":"St Marys",
    "sg:classifiers":[
        {
            "category":"Retail",
            "subcategory":"Auto Repair",
            "type":"Services"
        }
    ],
    "sg:phone":"+61 2 9628 5549",
    "sg:postcode":"2760",
    "sg:province":"NSW",
    "sg:tags":[
        "body",
        "motor",
        "trimmer"
    ],
    "wof:name":"Class Motor Trimming",
    "wof:placetype":"venue"
},
  "geometry": {"coordinates":[150.781982422,-33.7195129395],"type":"Point"}
}