{
  "type": "Feature",
  "properties": {
    "addr:full":"97 Stoneleigh Rd Mansfield VIC 3722",
    "addr:housenumber":"97",
    "addr:postcode":"3722",
    "addr:street":"Stoneleigh Rd",
    "iso:country":"AU",
    "sg:address":"97 Stoneleigh Rd",
    "sg:city":"Mansfield",
    "sg:classifiers":[
        {
            "category":"Home & Garden",
            "subcategory":"Carpets & Floor Coverings",
            "type":"Retail Goods"
        }
    ],
    "sg:phone":"+61 3 5779 1370",
    "sg:postcode":"3722",
    "sg:province":"VIC",
    "sg:tags":[
        "tile",
        "wall",
        "layer"
    ],
    "wof:name":"Dyer Stan",
    "wof:placetype":"venue"
},
  "geometry": {"coordinates":[146.08482360799999,-37.0654716492],"type":"Point"}
}