{
  "type": "Feature",
  "properties": {
    "iso:country":"AU",
    "sg:address":"Unit 3- 14",
    "sg:city":"Holder Way Malaga",
    "sg:classifiers":[
        {
            "category":"Utilities",
            "subcategory":"Electric",
            "type":"Services"
        }
    ],
    "sg:phone":"+61 8 9248 8299",
    "sg:postcode":"6090",
    "sg:province":"WA",
    "sg:tags":[
        "transformer"
    ],
    "wof:name":"Ausquip Engineering",
    "wof:placetype":"venue"
},
  "geometry": {"coordinates":[115.89189148,-31.8569564819],"type":"Point"}
}