{
  "type": "Feature",
  "properties": {
    "addr:full":"Ramsay School Rd Ramsay QLD 4352",
    "addr:postcode":"4352",
    "addr:street":"School Rd",
    "iso:country":"AU",
    "sg:address":"Ramsay School Rd",
    "sg:city":"Ramsay",
    "sg:classifiers":[
        {
            "category":"Education",
            "subcategory":"School",
            "type":"Public Place"
        }
    ],
    "sg:phone":"+61 7 4630 9140",
    "sg:postcode":"4352",
    "sg:province":"QLD",
    "sg:tags":[
        "state",
        "except",
        "nsw"
    ],
    "wof:name":"Ramsay Primary",
    "wof:placetype":"venue"
},
  "geometry": {"coordinates":[151.949814,-27.72117],"type":"Point"}
}