{
  "type": "Feature",
  "properties": {
    "addr:full":"Maude St Meandarra QLD 4422",
    "addr:postcode":"4422",
    "addr:street":"Maude St",
    "iso:country":"AU",
    "sg:address":"Maude St",
    "sg:city":"Meandarra",
    "sg:classifiers":[
        {
            "category":"Retail",
            "subcategory":"Auto Repair",
            "type":"Services"
        }
    ],
    "sg:phone":"+61 7 4665 6011",
    "sg:postcode":"4422",
    "sg:province":"QLD",
    "sg:tags":[
        "repairer",
        "motor",
        "engineer"
    ],
    "wof:name":"Meandarra Motors",
    "wof:placetype":"venue"
},
  "geometry": {"coordinates":[149.87776184099999,-27.3249206543],"type":"Point"}
}