{
  "type": "Feature",
  "properties": {
    "iso:country":"AU",
    "sg:address":"19 Billungah Pl",
    "sg:city":"Burnside",
    "sg:classifiers":[
        {
            "category":"Retail",
            "subcategory":"Auto Repair",
            "type":"Services"
        }
    ],
    "sg:phone":"+61 404 876 031",
    "sg:postcode":"3023",
    "sg:province":"VIC",
    "sg:tags":[
        "electrical"
    ],
    "wof:name":"V.S. Mobile Mechanic",
    "wof:placetype":"venue"
},
  "geometry": {"coordinates":[144.755005,-37.752995],"type":"Point"}
}