{
  "type": "Feature",
  "properties": {
    "addr:full":"1 Lewis St Schofields NSW 2762",
    "addr:housenumber":"1",
    "addr:postcode":"2762",
    "addr:street":"Lewis St",
    "iso:country":"AU",
    "sg:address":"1 Lewis St",
    "sg:city":"Schofields",
    "sg:classifiers":[
        {
            "category":"Building & Trades",
            "subcategory":"Construction",
            "type":"Services"
        }
    ],
    "sg:phone":"+61 2 9627 1355",
    "sg:postcode":"2762",
    "sg:province":"NSW",
    "sg:tags":[
        "renovation",
        "alterations",
        "extension",
        "contractor"
    ],
    "wof:name":"Alert Building Services",
    "wof:placetype":"venue"
},
  "geometry": {"coordinates":[150.872390747,-33.6958580017],"type":"Point"}
}