{
  "type": "Feature",
  "properties": {
    "addr:full":"379 Springvale Rd Springvale VIC 3171",
    "addr:housenumber":"379",
    "addr:postcode":"3171",
    "addr:street":"Springvale Rd",
    "iso:country":"AU",
    "sg:address":"379 Springvale Rd",
    "sg:city":"Springvale",
    "sg:classifiers":[
        {
            "category":"Health Services",
            "subcategory":"Health Practitioner",
            "type":"Services"
        }
    ],
    "sg:phone":"+61 3 9558 5688",
    "sg:postcode":"3171",
    "sg:province":"VIC",
    "sg:tags":[
        "acupuncture"
    ],
    "wof:name":"Aust Sino Acupuncture & Chinese Medical Centre Pty Ltd",
    "wof:placetype":"venue"
},
  "geometry": {"coordinates":[145.15213012699999,-37.954208374],"type":"Point"}
}