{
  "type": "Feature",
  "properties": {
    "addr:full":"20 Bell St Moe VIC 3825",
    "addr:housenumber":"20",
    "addr:postcode":"3825",
    "addr:street":"Bell St",
    "iso:country":"AU",
    "sg:address":"20 Bell St",
    "sg:city":"Moe",
    "sg:classifiers":[
        {
            "category":"Social Services",
            "subcategory":"Child Care",
            "type":"Services"
        }
    ],
    "sg:phone":"+61 3 5127 7466",
    "sg:postcode":"3825",
    "sg:province":"VIC",
    "wof:name":"Moe Central Child Care & Kindergarten Centre",
    "wof:placetype":"venue"
},
  "geometry": {"coordinates":[146.259354,-38.172752],"type":"Point"}
}