{
  "type": "Feature",
  "properties": {
    "addr:full":"Wanneroo Central Shopng Cntr Cnr Wanneroo & Dundebar Rds Wanneroo WA 6065",
    "addr:postcode":"6065",
    "iso:country":"AU",
    "sg:address":"Wanneroo Central Shopng Cntr Cnr Wanneroo & Dundebar Rds",
    "sg:city":"Wanneroo",
    "sg:classifiers":[
        {
            "category":"Food & Beverages",
            "subcategory":"Bakery",
            "type":"Retail Goods"
        }
    ],
    "sg:phone":"+61 8 9306 3146",
    "sg:postcode":"6065",
    "sg:province":"WA",
    "sg:tags":[
        "baker"
    ],
    "wof:name":"Bakers Delight",
    "wof:placetype":"venue"
},
  "geometry": {"coordinates":[115.803771973,-31.7504901886],"type":"Point"}
}