{
  "type": "Feature",
  "properties": {
    "addr:full":"100 Lambeth Glen Innes NSW 2370",
    "addr:housenumber":"100",
    "addr:postcode":"2370",
    "addr:street":"Lambeth",
    "iso:country":"AU",
    "sg:address":"100 Lambeth",
    "sg:city":"Glen Innes",
    "sg:classifiers":[
        {
            "category":"Home & Garden",
            "subcategory":"Carpets & Floor Coverings",
            "type":"Retail Goods"
        }
    ],
    "sg:phone":"+61 2 6732 3644",
    "sg:postcode":"2370",
    "sg:province":"NSW",
    "wof:name":"Andersens",
    "wof:placetype":"venue"
},
  "geometry": {"coordinates":[151.734542847,-29.7352371216],"type":"Point"}
}