{
  "type": "Feature",
  "properties": {
    "addr:full":"16 Belstead Ave Noranda WA 6062",
    "addr:housenumber":"16",
    "addr:postcode":"6062",
    "addr:street":"Belstead Ave",
    "iso:country":"AU",
    "sg:address":"16 Belstead Ave",
    "sg:city":"Noranda",
    "sg:classifiers":[
        {
            "category":"Building & Trades",
            "subcategory":"Cleaning & Sanitation",
            "type":"Services"
        }
    ],
    "sg:phone":"+61 1800 624 054",
    "sg:postcode":"6062",
    "sg:province":"WA",
    "sg:tags":[
        "window"
    ],
    "wof:name":"Cleanwest",
    "wof:placetype":"venue"
},
  "geometry": {"coordinates":[115.91497039799999,-31.8744602203],"type":"Point"}
}