{
  "type": "Feature",
  "properties": {
    "iso:country":"AU",
    "sg:address":"1 Royal Drv",
    "sg:city":"Hervey Bay",
    "sg:classifiers":[
        {
            "category":"Building & Trades",
            "subcategory":"Construction",
            "type":"Services"
        }
    ],
    "sg:phone":"+61 408 708 788",
    "sg:postcode":"4655",
    "sg:province":"QLD",
    "sg:tags":[
        "earth",
        "excavating",
        "moving",
        "contractor"
    ],
    "wof:name":"Maccas Excavation",
    "wof:placetype":"venue"
},
  "geometry": {"coordinates":[152.847534,-25.29513],"type":"Point"}
}