{
  "type": "Feature",
  "properties": {
    "addr:full":"159b, First Ave Bongaree QLD 4507",
    "addr:housenumber":"159b",
    "addr:postcode":"4507",
    "addr:street":"First Ave",
    "iso:country":"AU",
    "sg:address":"159b, First Ave",
    "sg:city":"Bongaree",
    "sg:classifiers":[
        {
            "category":"Manufacturing",
            "subcategory":"Furniture",
            "type":"Manufacturing & Wholesale Goods"
        }
    ],
    "sg:phone":"+61 7 3408 3124",
    "sg:postcode":"4507",
    "sg:province":"QLD",
    "sg:tags":[
        "builder",
        "designer",
        "custom"
    ],
    "wof:name":"Shelman Woodworks",
    "wof:placetype":"venue"
},
  "geometry": {"coordinates":[153.17567443900001,-27.0800666809],"type":"Point"}
}