{
  "type": "Feature",
  "properties": {
    "addr:full":"105 Tamboura Ave Baulkham Hills NSW 2153",
    "addr:housenumber":"105",
    "addr:postcode":"2153",
    "addr:street":"Tamboura Ave",
    "iso:country":"AU",
    "sg:address":"105 Tamboura Ave",
    "sg:city":"Baulkham Hills",
    "sg:classifiers":[
        {
            "category":"Professional",
            "subcategory":"Art Services",
            "type":"Services"
        }
    ],
    "sg:phone":"+61 2 9624 2909",
    "sg:postcode":"2153",
    "sg:province":"NSW",
    "sg:tags":[
        "decorator",
        "painter"
    ],
    "wof:name":"B Team Maintenance Service",
    "wof:placetype":"venue"
},
  "geometry": {"coordinates":[150.97476196299999,-33.7684211731],"type":"Point"}
}