{
  "type": "Feature",
  "properties": {
    "addr:full":"112 High St Mascot NSW 2020",
    "addr:housenumber":"112",
    "addr:postcode":"2020",
    "addr:street":"High St",
    "iso:country":"AU",
    "sg:address":"112 High St",
    "sg:city":"Mascot",
    "sg:classifiers":[
        {
            "category":"Wholesale",
            "subcategory":"Medical Equipment & Supplies",
            "type":"Manufacturing & Wholesale Goods"
        }
    ],
    "sg:phone":"+61 2 9667 3724",
    "sg:postcode":"2020",
    "sg:province":"NSW",
    "sg:tags":[
        "mfrs",
        "footwear"
    ],
    "wof:name":"Andrews Albert Pty Ltd",
    "wof:placetype":"venue"
},
  "geometry": {"coordinates":[151.18754577600001,-33.9298629761],"type":"Point"}
}