{
  "type": "Feature",
  "properties": {
    "addr:full":"966 High St Armadale VIC 3143",
    "addr:housenumber":"966",
    "addr:postcode":"3143",
    "addr:street":"High St",
    "iso:country":"AU",
    "sg:address":"966 High St",
    "sg:city":"Armadale",
    "sg:classifiers":[
        {
            "category":"Retail",
            "subcategory":"Repair Shop",
            "type":"Services"
        }
    ],
    "sg:phone":"+61 3 9509 7355",
    "sg:postcode":"3143",
    "sg:province":"VIC",
    "sg:tags":[
        "upholsterer"
    ],
    "wof:name":"Howell C W Upholstery",
    "wof:placetype":"venue"
},
  "geometry": {"coordinates":[145.01995849599999,-37.8555107117],"type":"Point"}
}