{
  "type": "Feature",
  "properties": {
    "addr:full":"2 Industry La Weipa QLD 4874",
    "addr:housenumber":"2",
    "addr:postcode":"4874",
    "addr:street":"Industry La Weipa",
    "iso:country":"AU",
    "sg:address":"2 Industry La",
    "sg:city":"Weipa",
    "sg:classifiers":[
        {
            "category":"Retail",
            "subcategory":"Auto Repair",
            "type":"Services"
        }
    ],
    "sg:phone":"+61 7 4069 9557",
    "sg:postcode":"4874",
    "sg:province":"QLD",
    "sg:tags":[
        "electrical"
    ],
    "wof:name":"Stray Auto Electrical",
    "wof:placetype":"venue"
},
  "geometry": {"coordinates":[141.87167358400001,-12.6334495544],"type":"Point"}
}