{
  "type": "Feature",
  "properties": {
    "addr:full":"2/ 17 Bishopgate St Wickham NSW 2293",
    "addr:housenumber":"/ 17",
    "addr:postcode":"2293",
    "addr:street":"Bishopgate St",
    "iso:country":"AU",
    "sg:address":"2/ 17 Bishopgate St",
    "sg:city":"Wickham",
    "sg:classifiers":[
        {
            "category":"Professional",
            "subcategory":"Accounting & Tax Preparation",
            "type":"Services"
        }
    ],
    "sg:phone":"+61 2 4969 7772",
    "sg:postcode":"2293",
    "sg:province":"NSW",
    "sg:tags":[
        "insulation",
        "wholesaler",
        "material",
        "mfrs"
    ],
    "wof:name":"Shinagawa Thermal Ceramics Pty Ltd",
    "wof:placetype":"venue"
},
  "geometry": {"coordinates":[151.75762939399999,-32.9223136902],"type":"Point"}
}