{
  "type": "Feature",
  "properties": {
    "iso:country":"AU",
    "sg:address":"Warringah Mall Shopping Centre, Shop 62, Cnr Old Pittwater Rd and Condamine St",
    "sg:city":"Brookvale",
    "sg:classifiers":[
        {
            "category":"Banks & Credit Unions",
            "subcategory":"Bureau De Change",
            "type":"Services"
        }
    ],
    "sg:phone":"+61 2 9939 0033",
    "sg:postcode":"2100",
    "sg:province":"NSW",
    "sg:tags":[
        "repairs",
        "part",
        "appliance",
        "electrical"
    ],
    "wof:name":"Shaver Shop",
    "wof:placetype":"venue"
},
  "geometry": {"coordinates":[151.27456665,-33.7550392151],"type":"Point"}
}