{
  "type": "Feature",
  "properties": {
    "addr:full":"140 Logan Rd Buranda QLD 4102",
    "addr:housenumber":"140",
    "addr:postcode":"4102",
    "addr:street":"Logan Rd",
    "iso:country":"AU",
    "sg:address":"140 Logan Rd",
    "sg:city":"Buranda",
    "sg:classifiers":[
        {
            "category":"Utilities",
            "subcategory":"Mobile Phone",
            "type":"Services"
        }
    ],
    "sg:phone":"+61 7 3393 1721",
    "sg:postcode":"4102",
    "sg:province":"QLD",
    "sg:tags":[
        "repair",
        "telephone"
    ],
    "wof:name":"All Fix N Bits",
    "wof:placetype":"venue"
},
  "geometry": {"coordinates":[153.041625977,-27.4972229004],"type":"Point"}
}