{
  "type": "Feature",
  "properties": {
    "addr:full":"2a Royal Pde Reservoir VIC 3073",
    "addr:housenumber":"2a",
    "addr:postcode":"3073",
    "addr:street":"Royal Pde",
    "iso:country":"AU",
    "sg:address":"2a Royal Pde",
    "sg:city":"Reservoir",
    "sg:classifiers":[
        {
            "category":"Health Services",
            "subcategory":"Dentist",
            "type":"Services"
        }
    ],
    "sg:phone":"+61 3 9460 4922",
    "sg:postcode":"3073",
    "sg:province":"VIC",
    "wof:name":"Royal Parade Dental Clinic",
    "wof:placetype":"venue"
},
  "geometry": {"coordinates":[145.00869750999999,-37.7162742615],"type":"Point"}
}