{
  "type": "Feature",
  "properties": {
    "addr:full":"53 Swift St Wellington NSW 2820",
    "addr:housenumber":"53",
    "addr:postcode":"2820",
    "addr:street":"Swift St",
    "iso:country":"AU",
    "sg:address":"53 Swift St",
    "sg:city":"Wellington",
    "sg:classifiers":[
        {
            "category":"Health Services",
            "subcategory":"Doctor",
            "type":"Services"
        }
    ],
    "sg:phone":"+61 2 6845 2084",
    "sg:postcode":"2820",
    "sg:province":"NSW",
    "sg:tags":[
        "medical",
        "practitioner"
    ],
    "wof:name":"Spencer Ian",
    "wof:placetype":"venue"
},
  "geometry": {"coordinates":[148.945877075,-32.5539970398],"type":"Point"}
}