{
  "type": "Feature",
  "properties": {
    "addr:full":"Shp 28 Phoenix Shopping Cntr Spearwood WA 6163",
    "addr:housenumber":"28",
    "addr:postcode":"6163",
    "addr:street":"Phoenix Shopping Cntr",
    "iso:country":"AU",
    "sg:address":"Shp 28 Phoenix Shopping Cntr",
    "sg:city":"Spearwood",
    "sg:classifiers":[
        {
            "category":"Shopping",
            "subcategory":"Clothing, Apparel, & Fashions",
            "type":"Retail Goods"
        }
    ],
    "sg:phone":"+61 8 9418 3181",
    "sg:postcode":"6163",
    "sg:province":"WA",
    "sg:tags":[
        "jean"
    ],
    "wof:name":"Just Jeans",
    "wof:placetype":"venue"
},
  "geometry": {"coordinates":[115.77977,-32.093395],"type":"Point"}
}