{
  "type": "Feature",
  "properties": {
    "addr:full":"Level 3 400 Queen St Brisbane QLD 4000",
    "addr:housenumber":"400",
    "addr:postcode":"4000",
    "addr:street":"Queen St",
    "iso:country":"AU",
    "sg:address":"Level 3 400 Queen St",
    "sg:city":"Brisbane",
    "sg:classifiers":[
        {
            "category":"Professional",
            "subcategory":"Accounting & Tax Preparation",
            "type":"Services"
        }
    ],
    "sg:phone":"+61 7 3221 6200",
    "sg:postcode":"4000",
    "sg:province":"QLD",
    "sg:tags":[
        "consultant",
        "taxation"
    ],
    "wof:name":"Bennett Partners",
    "wof:placetype":"venue"
},
  "geometry": {"coordinates":[153.03057861299999,-27.4652767181],"type":"Point"}
}