{
  "type": "Feature",
  "properties": {
    "addr:full":"Napoleon St Sans Souci NSW 2219",
    "addr:postcode":"2219",
    "addr:street":"Napoleon St",
    "iso:country":"AU",
    "sg:address":"Napoleon St",
    "sg:city":"Sans Souci",
    "sg:classifiers":[
        {
            "category":"Shopping",
            "subcategory":"Crafts & Fabrics",
            "type":"Retail Goods"
        }
    ],
    "sg:phone":"+61 2 9529 8077",
    "sg:postcode":"2219",
    "sg:province":"NSW",
    "sg:tags":[
        "florist",
        "supply"
    ],
    "wof:name":"Heavenly Sent Floral Couriers",
    "wof:placetype":"venue"
},
  "geometry": {"coordinates":[151.13656599999999,-33.994076],"type":"Point"}
}