{
  "type": "Feature",
  "properties": {
    "iso:country":"AU",
    "sg:address":"6 Second St",
    "sg:city":"Orroroo",
    "sg:classifiers":[
        {
            "category":"Travel",
            "subcategory":"Hotels & Motels",
            "type":"Entertainment"
        }
    ],
    "sg:phone":"+61 8 8658 1018",
    "sg:postcode":"5431",
    "sg:province":"SA",
    "sg:tags":[
        "accommodation"
    ],
    "wof:name":"Orroroo Hotel",
    "wof:placetype":"venue"
},
  "geometry": {"coordinates":[138.61184692399999,-32.7335319519],"type":"Point"}
}