{
  "type": "Feature",
  "properties": {
    "iso:country":"AU",
    "sg:address":"50 Wellington St",
    "sg:city":"Launceston",
    "sg:classifiers":[
        {
            "category":"Travel",
            "subcategory":"Hotels & Motels",
            "type":"Entertainment"
        }
    ],
    "sg:phone":"+61 3 6331 0844",
    "sg:postcode":"7250",
    "sg:province":"TAS",
    "sg:tags":[
        "accommodation"
    ],
    "wof:name":"Cock N Bull British Pub",
    "wof:placetype":"venue"
},
  "geometry": {"coordinates":[147.13739013700001,-41.4409370422],"type":"Point"}
}