{
  "type": "Feature",
  "properties": {
    "addr:full":"44 Deering St Ulladulla NSW 2539",
    "addr:housenumber":"44",
    "addr:postcode":"2539",
    "addr:street":"Deering St",
    "iso:country":"AU",
    "sg:address":"44 Deering St",
    "sg:city":"Ulladulla",
    "sg:classifiers":[
        {
            "category":"Shopping",
            "subcategory":"Mobile Phones",
            "type":"Retail Goods"
        }
    ],
    "sg:phone":"+61 2 4454 3973",
    "sg:postcode":"2539",
    "sg:province":"NSW",
    "sg:tags":[
        "telephone",
        "accessory"
    ],
    "wof:name":"Betta Electrical",
    "wof:placetype":"venue"
},
  "geometry": {"coordinates":[150.47564697300001,-35.3510398865],"type":"Point"}
}