{
  "type": "Feature",
  "properties": {
    "addr:full":"194a High St Wodonga NSW 3690",
    "addr:housenumber":"194a",
    "addr:postcode":"3690",
    "addr:street":"High St",
    "iso:country":"AU",
    "sg:address":"194a High St",
    "sg:city":"Wodonga",
    "sg:classifiers":[
        {
            "category":"Shopping",
            "subcategory":"Clothing, Apparel, & Fashions",
            "type":"Retail Goods"
        }
    ],
    "sg:phone":"+61 2 6056 4232",
    "sg:postcode":"3690",
    "sg:province":"NSW",
    "sg:tags":[
        "lady",
        "wear"
    ],
    "wof:name":"K-Serrah Fashions",
    "wof:placetype":"venue"
},
  "geometry": {"coordinates":[146.888305664,-36.123878479],"type":"Point"}
}