{
  "type": "Feature",
  "properties": {
    "iso:country":"AU",
    "sg:address":"Moonta Rd",
    "sg:city":"Kadina",
    "sg:classifiers":[
        {
            "category":"Professional",
            "subcategory":"Business Services",
            "type":"Services"
        }
    ],
    "sg:phone":"+61 8 8821 2848",
    "sg:postcode":"5554",
    "sg:province":"SA",
    "sg:tags":[
        "consultant",
        "promoter",
        "entertainment"
    ],
    "wof:name":"Kadina Agricultural Horticultural & Flora Society Inc",
    "wof:placetype":"venue"
},
  "geometry": {"coordinates":[137.714187622,-33.9668579102],"type":"Point"}
}