{
  "type": "Feature",
  "properties": {
    "iso:country":"AU",
    "sg:address":"Shop 3 Livingston Market Place",
    "sg:city":"Canning Vale",
    "sg:classifiers":[
        {
            "category":"Food & Beverages",
            "subcategory":"Specialty",
            "type":"Retail Goods"
        }
    ],
    "sg:phone":"+61 8 9456 2011",
    "sg:postcode":"6155",
    "sg:province":"WA",
    "sg:tags":[
        "product",
        "health"
    ],
    "wof:name":"Healthy Life Livingston",
    "wof:placetype":"venue"
},
  "geometry": {"coordinates":[115.92858099999999,-32.080261],"type":"Point"}
}