{
  "type": "Feature",
  "properties": {
    "addr:full":"58 Wingecarribee St Bowral NSW 2576",
    "addr:housenumber":"58",
    "addr:postcode":"2576",
    "addr:street":"Wingecarribee St",
    "iso:country":"AU",
    "sg:address":"58 Wingecarribee St",
    "sg:city":"Bowral",
    "sg:classifiers":[
        {
            "category":"Health Services",
            "subcategory":"Doctor",
            "type":"Services"
        }
    ],
    "sg:phone":"+61 2 4862 1344",
    "sg:postcode":"2576",
    "sg:province":"NSW",
    "sg:tags":[
        "medical",
        "practitioner"
    ],
    "wof:name":"Dr Peter Spitzer",
    "wof:placetype":"venue"
},
  "geometry": {"coordinates":[150.42149352999999,-34.4793891907],"type":"Point"}
}