{
  "type": "Feature",
  "properties": {
    "addr:full":"1 Webber St Moonah TAS 7009",
    "addr:housenumber":"1",
    "addr:postcode":"7009",
    "addr:street":"Webber St",
    "iso:country":"AU",
    "sg:address":"1 Webber St",
    "sg:city":"Moonah",
    "sg:classifiers":[
        {
            "category":"Wholesale",
            "subcategory":"Home Furnishings",
            "type":"Manufacturing & Wholesale Goods"
        }
    ],
    "sg:phone":"+61 3 6278 2737",
    "sg:postcode":"7009",
    "sg:province":"TAS",
    "sg:tags":[
        "wholesaler",
        "curtain",
        "mfrs"
    ],
    "wof:name":"Ela's Specialty Curtains & Blinds",
    "wof:placetype":"venue"
},
  "geometry": {"coordinates":[147.291213989,-42.8483467102],"type":"Point"}
}