{
  "type": "Feature",
  "properties": {
    "addr:full":"The Loft on Evans Lane St Leonards NSW 2065",
    "addr:postcode":"2065",
    "addr:street":"Lane",
    "iso:country":"AU",
    "sg:address":"The Loft on Evans Lane St",
    "sg:city":"Leonards",
    "sg:classifiers":[
        {
            "category":"Education",
            "subcategory":"Special Training",
            "type":"Public Place"
        }
    ],
    "sg:phone":"+61 2 8436 7888",
    "sg:postcode":"2065",
    "sg:province":"NSW",
    "sg:tags":[
        "development"
    ],
    "wof:name":"Artescape",
    "wof:placetype":"venue"
},
  "geometry": {"coordinates":[151.19468689000001,-33.8214874268],"type":"Point"}
}