{
  "type": "Feature",
  "properties": {
    "addr:full":"166 Avoca Drv Kincumber NSW 2251",
    "addr:housenumber":"166",
    "addr:postcode":"2251",
    "addr:street":"Avoca Drv",
    "iso:country":"AU",
    "sg:address":"166 Avoca Drv",
    "sg:city":"Kincumber",
    "sg:classifiers":[
        {
            "category":"Building & Trades",
            "subcategory":"Construction",
            "type":"Services"
        }
    ],
    "sg:phone":"+61 2 4369 0957",
    "sg:postcode":"2251",
    "sg:province":"NSW",
    "sg:tags":[
        "plasterboard",
        "plasterer",
        "fixer"
    ],
    "wof:name":"Lake Edge Plasterboard",
    "wof:placetype":"venue"
},
  "geometry": {"coordinates":[151.37263488799999,-33.4659347534],"type":"Point"}
}