{
  "type": "Feature",
  "properties": {
    "iso:country":"AU",
    "sg:address":"106 Pacific Hwy",
    "sg:city":"Tuggerah",
    "sg:classifiers":[
        {
            "category":"Home & Garden",
            "subcategory":"Building Materials",
            "type":"Retail Goods"
        }
    ],
    "sg:phone":"+61 2 4353 5454",
    "sg:postcode":"2259",
    "sg:province":"NSW",
    "sg:tags":[
        "roofing"
    ],
    "wof:name":"Complete Roofing Warehouse",
    "wof:placetype":"venue"
},
  "geometry": {"coordinates":[151.42022705100001,-33.3051605225],"type":"Point"}
}