{
  "type": "Feature",
  "properties": {
    "addr:full":"20 Pollack Drv Mill Park VIC 3082",
    "addr:housenumber":"20",
    "addr:postcode":"3082",
    "addr:street":"Pollack Drv",
    "iso:country":"AU",
    "sg:address":"20 Pollack Drv",
    "sg:city":"Mill Park",
    "sg:classifiers":[
        {
            "category":"Building & Trades",
            "subcategory":"Construction",
            "type":"Services"
        }
    ],
    "sg:phone":"+61 3 9436 5333",
    "sg:postcode":"3082",
    "sg:province":"VIC",
    "sg:tags":[
        "contractor"
    ],
    "wof:name":"Fringe Dweller Developments",
    "wof:placetype":"venue"
},
  "geometry": {"coordinates":[145.06381225600001,-37.6509284973],"type":"Point"}
}