{
  "type": "Feature",
  "properties": {
    "iso:country":"AU",
    "sg:address":"Unit 2A 824 Beeliar Drv",
    "sg:city":"Success",
    "sg:classifiers":[
        {
            "category":"Restaurant",
            "type":"Food & Drink"
        }
    ],
    "sg:phone":"+61 8 9498 7455",
    "sg:postcode":"6164",
    "sg:province":"WA",
    "sg:tags":[
        "pizza"
    ],
    "wof:name":"Eagle Boys Pizza",
    "wof:placetype":"venue"
},
  "geometry": {"coordinates":[115.837608,-32.125259],"type":"Point"}
}