{
  "type": "Feature",
  "properties": {
    "addr:full":"PO Box 518 Mooloolaba QLD 4557",
    "addr:postcode":"4557",
    "iso:country":"AU",
    "sg:address":"PO Box 518",
    "sg:city":"Mooloolaba",
    "sg:classifiers":[
        {
            "category":"Building & Trades",
            "subcategory":"Landscaping Services",
            "type":"Services"
        }
    ],
    "sg:phone":"+61 410 649 420",
    "sg:postcode":"4557",
    "sg:province":"QLD",
    "sg:tags":[
        "designer",
        "landscape",
        "contractor"
    ],
    "wof:name":"Naturform Sunshine Coast",
    "wof:placetype":"venue"
},
  "geometry": {"coordinates":[153.117797852,-26.6837902069],"type":"Point"}
}