{
  "type": "Feature",
  "properties": {
    "addr:full":"136 Barkley St St Kilda VIC 3182",
    "addr:housenumber":"136",
    "addr:postcode":"3182",
    "addr:street":"Barkley St",
    "iso:country":"AU",
    "sg:address":"136 Barkley St",
    "sg:city":"St Kilda",
    "sg:classifiers":[
        {
            "category":"Retail",
            "subcategory":"Auto Rental",
            "type":"Services"
        }
    ],
    "sg:phone":"+61 1800 658 658",
    "sg:postcode":"3182",
    "sg:province":"VIC",
    "sg:tags":[
        "car",
        "hire",
        "minibus"
    ],
    "wof:name":"Let 2 Agent",
    "wof:placetype":"venue"
},
  "geometry": {"coordinates":[144.98161315900001,-37.8658866882],"type":"Point"}
}