{
  "type": "Feature",
  "properties": {
    "iso:country":"AU",
    "sg:address":"18 River St",
    "sg:city":"Richmond",
    "sg:classifiers":[
        {
            "category":"Food & Beverages",
            "subcategory":"Liquor & Beverages",
            "type":"Retail Goods"
        }
    ],
    "sg:phone":"+61 3 9429 4744",
    "sg:postcode":"3121",
    "sg:province":"VIC",
    "sg:tags":[
        "merchant",
        "spirit",
        "wine"
    ],
    "wof:name":"Mayall Wine Pty Ltd",
    "wof:placetype":"venue"
},
  "geometry": {"coordinates":[145.01315307600001,-37.8170890808],"type":"Point"}
}