{
  "type": "Feature",
  "properties": {
    "addr:full":"221 Victoria Drv Thomastown VIC 3074",
    "addr:housenumber":"221",
    "addr:postcode":"3074",
    "addr:street":"Victoria Drv",
    "iso:country":"AU",
    "sg:address":"221 Victoria Drv",
    "sg:city":"Thomastown",
    "sg:classifiers":[
        {
            "category":"Professional",
            "subcategory":"Printing & Photocopies",
            "type":"Services"
        }
    ],
    "sg:phone":"+61 3 9466 2150",
    "sg:postcode":"3074",
    "sg:province":"VIC",
    "sg:tags":[
        "publishing",
        "desktop"
    ],
    "wof:name":"Politi & Co",
    "wof:placetype":"venue"
},
  "geometry": {"coordinates":[144.99920654300001,-37.685256958],"type":"Point"}
}