{
  "type": "Feature",
  "properties": {
    "addr:full":"Lvl 2, 86 Mann St Gosford NSW 2250",
    "addr:housenumber":"86",
    "addr:postcode":"2250",
    "addr:street":"Mann St",
    "iso:country":"AU",
    "sg:address":"Lvl 2, 86 Mann St",
    "sg:city":"Gosford",
    "sg:classifiers":[
        {
            "category":"Professional",
            "subcategory":"Accounting & Tax Preparation",
            "type":"Services"
        }
    ],
    "sg:phone":"+61 2 4325 0314",
    "sg:postcode":"2250",
    "sg:province":"NSW",
    "sg:tags":[
        "accountant",
        "auditor"
    ],
    "wof:name":"O&#039;Donoghue Services Pty Ltd",
    "wof:placetype":"venue"
},
  "geometry": {"coordinates":[151.34158325199999,-33.4273681641],"type":"Point"}
}