{
  "type": "Feature",
  "properties": {
    "addr:full":"25/ 288 Casuarina Drv Nightcliff NT 0810",
    "addr:housenumber":"25 / 288",
    "addr:postcode":"nt 0810",
    "addr:street":"Casuarina Drv",
    "iso:country":"AU",
    "sg:address":"25/ 288 Casuarina Drv",
    "sg:city":"Nightcliff",
    "sg:classifiers":[
        {
            "category":"Sports & Exercise",
            "subcategory":"Gym",
            "type":"Entertainment"
        }
    ],
    "sg:phone":"+61 407 281 295",
    "sg:postcode":"0810",
    "sg:province":"NT",
    "sg:tags":[
        "pilate",
        "method"
    ],
    "wof:name":"Pilates in Motion",
    "wof:placetype":"venue"
},
  "geometry": {"coordinates":[130.85244750999999,-12.3754806519],"type":"Point"}
}