{
  "type": "Feature",
  "properties": {
    "addr:full":"Ste 4, 14 Gibbens Rd Gosford West NSW 2250",
    "addr:housenumber":"14",
    "addr:postcode":"2250",
    "addr:street":"Gibbens Rd",
    "iso:country":"AU",
    "sg:address":"Ste 4, 14 Gibbens Rd",
    "sg:city":"Gosford West",
    "sg:classifiers":[
        {
            "category":"Wholesale",
            "subcategory":"Machinery & Supplies",
            "type":"Manufacturing & Wholesale Goods"
        }
    ],
    "sg:phone":"+61 2 4323 2924",
    "sg:postcode":"2250",
    "sg:province":"NSW",
    "sg:tags":[
        "instrument",
        "scientific"
    ],
    "wof:name":"Spectro Analytical Australia Pty Ltd",
    "wof:placetype":"venue"
},
  "geometry": {"coordinates":[151.32194519000001,-33.4152603149],"type":"Point"}
}