{
  "type": "Feature",
  "properties": {
    "addr:full":"Lot2/ Reserve Rd Robigana TAS 7275",
    "addr:postcode":"7275",
    "addr:street":"Rd",
    "iso:country":"AU",
    "sg:address":"Lot2/ Reserve Rd",
    "sg:city":"Robigana",
    "sg:classifiers":[
        {
            "category":"Home & Garden",
            "subcategory":"Household Appliances",
            "type":"Retail Goods"
        }
    ],
    "sg:phone":"+61 428 381 803",
    "sg:postcode":"7275",
    "sg:province":"TAS",
    "sg:tags":[
        "equipment",
        "gas"
    ],
    "wof:name":"Tamar Gas",
    "wof:placetype":"venue"
},
  "geometry": {"coordinates":[146.95571899399999,-41.2665710449],"type":"Point"}
}