{
  "type": "Feature",
  "properties": {
    "addr:full":"257 Bourbong St Bundaberg QLD 4670",
    "addr:housenumber":"257",
    "addr:postcode":"4670",
    "addr:street":"Bourbong St",
    "iso:country":"AU",
    "sg:address":"257 Bourbong St",
    "sg:city":"Bundaberg",
    "sg:classifiers":[
        {
            "category":"Autos & Motor Vehicles",
            "subcategory":"Fuel & Gas Station",
            "type":"Retail Goods"
        }
    ],
    "sg:phone":"+61 7 4152 1842",
    "sg:postcode":"4670",
    "sg:province":"QLD",
    "wof:name":"Caltex Central Service Station",
    "wof:placetype":"venue"
},
  "geometry": {"coordinates":[152.33949279800001,-24.8684444427],"type":"Point"}
}