{
  "type": "Feature",
  "properties": {
    "addr:full":"17 Tulloh St Willoughby NSW 2068",
    "addr:housenumber":"17",
    "addr:postcode":"2068",
    "addr:street":"Tulloh St",
    "iso:country":"AU",
    "sg:address":"17 Tulloh St",
    "sg:city":"Willoughby",
    "sg:classifiers":[
        {
            "category":"Building & Trades",
            "subcategory":"Construction",
            "type":"Services"
        }
    ],
    "sg:phone":"+61 2 9958 7721",
    "sg:postcode":"2068",
    "sg:province":"NSW",
    "sg:tags":[
        "contractor"
    ],
    "wof:name":"Garnett & Co Pty Ltd",
    "wof:placetype":"venue"
},
  "geometry": {"coordinates":[151.20065307600001,-33.8098678589],"type":"Point"}
}