{
  "type": "Feature",
  "properties": {
    "addr:full":"35 Terry St Rozelle NSW 2039",
    "addr:housenumber":"35",
    "addr:postcode":"2039",
    "addr:street":"Terry St",
    "iso:country":"AU",
    "sg:address":"35 Terry St",
    "sg:city":"Rozelle",
    "sg:classifiers":[
        {
            "category":"Social Services",
            "subcategory":"Child Care",
            "type":"Services"
        }
    ],
    "sg:phone":"+61 2 9818 6199",
    "sg:postcode":"2039",
    "sg:province":"NSW",
    "wof:name":"Balmain Cove Childrens Centre",
    "wof:placetype":"venue"
},
  "geometry": {"coordinates":[151.16801452600001,-33.8605155945],"type":"Point"}
}