{
  "type": "Feature",
  "properties": {
    "addr:full":"68 Bangalee St Lauderdale TAS 7021",
    "addr:housenumber":"68",
    "addr:postcode":"7021",
    "addr:street":"Bangalee St",
    "iso:country":"AU",
    "sg:address":"68 Bangalee St",
    "sg:city":"Lauderdale",
    "sg:classifiers":[
        {
            "category":"Building & Trades",
            "subcategory":"Construction",
            "type":"Services"
        }
    ],
    "sg:phone":"+61 3 6248 6881",
    "sg:postcode":"7021",
    "sg:province":"TAS",
    "sg:tags":[
        "joiner",
        "carpenter"
    ],
    "wof:name":"Mason L D",
    "wof:placetype":"venue"
},
  "geometry": {"coordinates":[147.494216919,-42.901309967],"type":"Point"}
}