{
  "type": "Feature",
  "properties": {
    "iso:country":"AU",
    "sg:address":"1 5 Fielding Drv",
    "sg:city":"West Hobart",
    "sg:classifiers":[
        {
            "category":"Professional",
            "type":"Services"
        }
    ],
    "sg:phone":"+61 407 124 523",
    "sg:postcode":"7000",
    "sg:province":"TAS",
    "sg:tags":[
        "marine",
        "contractor"
    ],
    "wof:name":"Marine Construction & Towing Services Pty Ltd",
    "wof:placetype":"venue"
},
  "geometry": {"coordinates":[147.30641174300001,-42.8816719055],"type":"Point"}
}