{
  "type": "Feature",
  "properties": {
    "iso:country":"AU",
    "sg:address":"431 Gardeners Rd",
    "sg:city":"Rosebery",
    "sg:classifiers":[
        {
            "category":"Home & Garden",
            "subcategory":"Carpets & Floor Coverings",
            "type":"Retail Goods"
        }
    ],
    "sg:phone":"+61 2 8338 1800",
    "sg:postcode":"2018",
    "sg:province":"NSW",
    "sg:tags":[
        "tile",
        "wall"
    ],
    "wof:name":"ABC Rosebery Tiles",
    "wof:placetype":"venue"
},
  "geometry": {"coordinates":[151.20083618199999,-33.9221954346],"type":"Point"}
}