{
  "type": "Feature",
  "properties": {
    "addr:full":"62 Kingston Rd Underwood QLD 4119",
    "addr:housenumber":"62",
    "addr:postcode":"4119",
    "addr:street":"Kingston Rd",
    "iso:country":"AU",
    "sg:address":"62 Kingston Rd",
    "sg:city":"Underwood",
    "sg:classifiers":[
        {
            "category":"Manufacturing",
            "subcategory":"Motor Vehicles & Parts",
            "type":"Manufacturing & Wholesale Goods"
        }
    ],
    "sg:phone":"+61 7 3841 0066",
    "sg:postcode":"4119",
    "sg:province":"QLD",
    "sg:tags":[
        "replacement"
    ],
    "wof:name":"Alljap Auto Parts",
    "wof:placetype":"venue"
},
  "geometry": {"coordinates":[153.11415100100001,-27.6141223907],"type":"Point"}
}