{
  "type": "Feature",
  "properties": {
    "iso:country":"AU",
    "sg:address":"Corner Pacific Hwy & Hornsby Rd",
    "sg:city":"Hornsby",
    "sg:classifiers":[
        {
            "category":"Banks & Credit Unions",
            "subcategory":"Financial Services",
            "type":"Services"
        }
    ],
    "sg:phone":"+61 2 9472 2100",
    "sg:postcode":"2077",
    "sg:province":"NSW",
    "sg:tags":[
        "finance",
        "motor",
        "vehicle"
    ],
    "wof:name":"Hornsby Honda",
    "wof:placetype":"venue"
},
  "geometry": {"coordinates":[151.09898376500001,-33.7070388794],"type":"Point"}
}