{
  "type": "Feature",
  "properties": {
    "addr:full":"4 Mitchell Rd Brookvale NSW 2100",
    "addr:housenumber":"4",
    "addr:postcode":"2100",
    "addr:street":"Mitchell Rd",
    "iso:country":"AU",
    "sg:address":"4 Mitchell Rd",
    "sg:city":"Brookvale",
    "sg:classifiers":[
        {
            "category":"Autos & Motor Vehicles",
            "subcategory":"Automobile Sales",
            "type":"Retail Goods"
        }
    ],
    "sg:phone":"+61 2 9939 5777",
    "sg:postcode":"2100",
    "sg:province":"NSW",
    "sg:tags":[
        "car",
        "used"
    ],
    "wof:name":"Prestige Auto Warehouse",
    "wof:placetype":"venue"
},
  "geometry": {"coordinates":[151.274536133,-33.762172699],"type":"Point"}
}