{
  "type": "Feature",
  "properties": {
    "addr:full":"23 Hocking St Coburg North VIC 3058",
    "addr:housenumber":"23",
    "addr:postcode":"3058",
    "addr:street":"Hocking St",
    "iso:country":"AU",
    "sg:address":"23 Hocking St",
    "sg:city":"Coburg North",
    "sg:classifiers":[
        {
            "category":"Professional",
            "subcategory":"Engineering",
            "type":"Services"
        }
    ],
    "sg:phone":"+61 3 9354 2567",
    "sg:postcode":"3058",
    "sg:province":"VIC",
    "sg:tags":[
        "installation",
        "maintenance",
        "engineer"
    ],
    "wof:name":"S.I. Engineering Pty Ltd",
    "wof:placetype":"venue"
},
  "geometry": {"coordinates":[144.95428466800001,-37.7275733948],"type":"Point"}
}