{
  "type": "Feature",
  "properties": {
    "addr:full":"41b Francis St Moama NSW 2731",
    "addr:housenumber":"41b",
    "addr:postcode":"2731",
    "addr:street":"Francis St",
    "iso:country":"AU",
    "sg:address":"41b Francis St",
    "sg:city":"Moama",
    "sg:classifiers":[
        {
            "category":"Communications",
            "subcategory":"Film & Video Production",
            "type":"Services"
        }
    ],
    "sg:phone":"+61 3 5480 0829",
    "sg:postcode":"2731",
    "sg:province":"NSW",
    "sg:tags":[
        "dvd",
        "library"
    ],
    "wof:name":"Network Video Moama",
    "wof:placetype":"venue"
},
  "geometry": {"coordinates":[144.75694300000001,-36.107941],"type":"Point"}
}