{
  "type": "Feature",
  "properties": {
    "addr:full":"Shop 3 208 The Mall Leura NSW 2780",
    "addr:housenumber":"shop 3 208",
    "addr:postcode":"2780",
    "addr:street":"The Mall",
    "iso:country":"AU",
    "sg:address":"Shop 3 208 The Mall",
    "sg:city":"Leura",
    "sg:classifiers":[
        {
            "category":"Communications",
            "subcategory":"News Services",
            "type":"Services"
        }
    ],
    "sg:phone":"+61 2 4784 2222",
    "sg:postcode":"2780",
    "sg:province":"NSW",
    "sg:tags":[
        "information",
        "tourist",
        "attractions"
    ],
    "wof:name":"Blue Mountains Accommodation Centre",
    "wof:placetype":"venue"
},
  "geometry": {"coordinates":[150.33172607399999,-33.7098350525],"type":"Point"}
}