{
  "type": "Feature",
  "properties": {
    "iso:country":"AU",
    "sg:address":"2 Seaview St",
    "sg:city":"Nambucca Heads",
    "sg:classifiers":[
        {
            "category":"Building & Trades",
            "subcategory":"Cleaning & Sanitation",
            "type":"Services"
        }
    ],
    "sg:phone":"+61 428 694 689",
    "sg:postcode":"2448",
    "sg:province":"NSW",
    "sg:tags":[
        "industrial",
        "commercial",
        "contractor"
    ],
    "wof:name":"A1 Duct Cleaning Services",
    "wof:placetype":"venue"
},
  "geometry": {"coordinates":[152.99392700000001,-30.648167],"type":"Point"}
}