{
  "type": "Feature",
  "properties": {
    "iso:country":"AU",
    "sg:address":"1320 North East Rd",
    "sg:city":"Tea Tree Gully",
    "sg:classifiers":[
        {
            "category":"Farming",
            "subcategory":"Vineyard",
            "type":"Manufacturing & Wholesale Goods"
        }
    ],
    "sg:phone":"+61 8 8264 2366",
    "sg:postcode":"5091",
    "sg:province":"SA",
    "sg:tags":[
        "winery"
    ],
    "wof:name":"Angoves- St Agnes Reception",
    "wof:placetype":"venue"
},
  "geometry": {"coordinates":[138.72698974599999,-34.8209075928],"type":"Point"}
}