{
  "type": "Feature",
  "properties": {
    "iso:country":"AU",
    "sg:address":"1/ 67 Araluen St",
    "sg:city":"Kedron",
    "sg:classifiers":[
        {
            "category":"Professional",
            "subcategory":"Art Services",
            "type":"Services"
        }
    ],
    "sg:phone":"+61 7 3359 9989",
    "sg:postcode":"4031",
    "sg:province":"QLD",
    "sg:tags":[
        "decorator",
        "painter"
    ],
    "wof:name":"Whyte Master Painters Pty Ltd",
    "wof:placetype":"venue"
},
  "geometry": {"coordinates":[153.02255199999999,-27.397465],"type":"Point"}
}