{
  "type": "Feature",
  "properties": {
    "addr:full":"388-390 Kororoit Creek Rd Williamstown VIC 3016",
    "addr:housenumber":"388-390",
    "addr:postcode":"3016",
    "addr:street":"Kororoit Creek Rd",
    "iso:country":"AU",
    "sg:address":"388-390 Kororoit Creek Rd",
    "sg:city":"Williamstown",
    "sg:classifiers":[
        {
            "category":"Sports & Exercise",
            "subcategory":"Gym",
            "type":"Entertainment"
        }
    ],
    "sg:phone":"+61 3 9391 9233",
    "sg:postcode":"3016",
    "sg:province":"VIC",
    "sg:tags":[
        "health",
        "fitness"
    ],
    "wof:name":"Beach House Health & Fitness",
    "wof:placetype":"venue"
},
  "geometry": {"coordinates":[144.85853576700001,-37.8537483215],"type":"Point"}
}