{
  "type": "Feature",
  "properties": {
    "addr:full":"696 Boundary Rd Coopers Plains QLD 4108",
    "addr:housenumber":"696",
    "addr:postcode":"4108",
    "addr:street":"Boundary Rd",
    "iso:country":"AU",
    "sg:address":"696 Boundary Rd",
    "sg:city":"Coopers Plains",
    "sg:classifiers":[
        {
            "category":"Wholesale",
            "subcategory":"Painting Supplies",
            "type":"Manufacturing & Wholesale Goods"
        }
    ],
    "sg:phone":"+61 7 3216 6996",
    "sg:postcode":"4108",
    "sg:province":"QLD",
    "sg:tags":[
        "product",
        "polyurethane"
    ],
    "wof:name":"Advanced Thermoforming Technologies Pty Ltd",
    "wof:placetype":"venue"
},
  "geometry": {"coordinates":[153.02491760300001,-27.5683193207],"type":"Point"}
}