{
  "type": "Feature",
  "properties": {
    "addr:full":"Shop 96 Westfield Shopngtwn Dickson St Strathpine QLD 4500",
    "addr:housenumber":"shop 96",
    "addr:postcode":"4500",
    "addr:street":"Westfield Shopngtwn Dickson St",
    "iso:country":"AU",
    "sg:address":"Shop 96 Westfield Shopngtwn Dickson St",
    "sg:city":"Strathpine",
    "sg:classifiers":[
        {
            "category":"Fast Food",
            "type":"Food & Drink"
        }
    ],
    "sg:phone":"+61 7 3881 1120",
    "sg:postcode":"4500",
    "sg:province":"QLD",
    "sg:tags":[
        "away",
        "take"
    ],
    "wof:name":"McDonald's Family Restaurants",
    "wof:placetype":"venue"
},
  "geometry": {"coordinates":[153.009963989,-27.3256072998],"type":"Point"}
}