{
  "type": "Feature",
  "properties": {
    "addr:full":"Memorial Drv Kalgoorlie WA 6430",
    "addr:postcode":"6430",
    "addr:street":"Memorial Drv",
    "iso:country":"AU",
    "sg:address":"Memorial Drv",
    "sg:city":"Kalgoorlie",
    "sg:classifiers":[
        {
            "category":"Retail",
            "subcategory":"Funeral Services",
            "type":"Services"
        }
    ],
    "sg:phone":"+61 8 9091 1693",
    "sg:postcode":"6430",
    "sg:province":"WA",
    "sg:tags":[
        "cemetery"
    ],
    "wof:name":"Kalgoorlie-Boulder Cemetery Board",
    "wof:placetype":"venue"
},
  "geometry": {"coordinates":[121.457702637,-30.738948822],"type":"Point"}
}