{
  "type": "Feature",
  "properties": {
    "iso:country":"AU",
    "sg:address":"9 Hawkesbury Crs",
    "sg:city":"Lameroo",
    "sg:classifiers":[
        {
            "category":"Commercial Area",
            "type":"Public Place"
        }
    ],
    "sg:phone":"+61 8 8576 3349",
    "sg:postcode":"5302",
    "sg:province":"SA",
    "sg:tags":[
        "heavy",
        "carrier"
    ],
    "wof:name":"Noll R D & R M",
    "wof:placetype":"venue"
},
  "geometry": {"coordinates":[140.51742553700001,-35.3293418884],"type":"Point"}
}