{
  "type": "Feature",
  "properties": {
    "addr:full":"Comur Court Shop 4/ 175 Comur St Yass NSW 2582",
    "addr:housenumber":"4 / 175",
    "addr:postcode":"2582",
    "addr:street":"Comur;Comur St",
    "iso:country":"AU",
    "sg:address":"Comur Court Shop 4/ 175 Comur St",
    "sg:city":"Yass",
    "sg:classifiers":[
        {
            "category":"Health Services",
            "subcategory":"Optometrist",
            "type":"Services"
        }
    ],
    "sg:phone":"+61 2 6226 1136",
    "sg:postcode":"2582",
    "sg:province":"NSW",
    "wof:name":"Geoff Day Optometrist",
    "wof:placetype":"venue"
},
  "geometry": {"coordinates":[148.91215515100001,-34.8429107666],"type":"Point"}
}