{
  "type": "Feature",
  "properties": {
    "addr:full":"Shop 2, 145 Remembrance Drv Tahmoor NSW 2573",
    "addr:housenumber":"shop 2 145",
    "addr:postcode":"2573",
    "addr:street":"Remembrance Drv",
    "iso:country":"AU",
    "sg:address":"Shop 2, 145 Remembrance Drv",
    "sg:city":"Tahmoor",
    "sg:classifiers":[
        {
            "category":"Manufacturing",
            "subcategory":"Musical Instruments",
            "type":"Manufacturing & Wholesale Goods"
        }
    ],
    "sg:phone":"+61 2 4681 0522",
    "sg:postcode":"2573",
    "sg:province":"NSW",
    "sg:tags":[
        "repair",
        "maker"
    ],
    "wof:name":"R & B Music",
    "wof:placetype":"venue"
},
  "geometry": {"coordinates":[150.59248352,-34.2248840332],"type":"Point"}
}