{
  "type": "Feature",
  "properties": {
    "addr:full":"2/ 85 West St Balgowlah NSW 2093",
    "addr:housenumber":"/ 85",
    "addr:postcode":"2093",
    "addr:street":"West St",
    "iso:country":"AU",
    "sg:address":"2/ 85 West St",
    "sg:city":"Balgowlah",
    "sg:classifiers":[
        {
            "category":"Personal",
            "subcategory":"Massage",
            "type":"Services"
        }
    ],
    "sg:phone":"+61 2 9949 7315",
    "sg:postcode":"2093",
    "sg:province":"NSW",
    "sg:tags":[
        "therapy"
    ],
    "wof:name":"Richard O&#039;Kane",
    "wof:placetype":"venue"
},
  "geometry": {"coordinates":[151.26057434099999,-33.7928581238],"type":"Point"}
}