{
  "type": "Feature",
  "properties": {
    "addr:full":"38 Cromwell St Battery Point TAS 7004",
    "addr:housenumber":"38",
    "addr:postcode":"7004",
    "addr:street":"Cromwell St",
    "iso:country":"AU",
    "sg:address":"38 Cromwell St",
    "sg:city":"Battery Point",
    "sg:classifiers":[
        {
            "category":"Organizations",
            "subcategory":"Membership Organization",
            "type":"Services"
        }
    ],
    "sg:phone":"+61 3 6223 7550",
    "sg:postcode":"7004",
    "sg:province":"TAS",
    "sg:tags":[
        "support",
        "health",
        "organisation"
    ],
    "wof:name":"CanTeen (Australian Organisation For Young People Living With Cancer)",
    "wof:placetype":"venue"
},
  "geometry": {"coordinates":[147.33206176799999,-42.8909301758],"type":"Point"}
}