{
  "type": "Feature",
  "properties": {
    "addr:full":"70 Heatherton Rd Endeavour Hills VIC 3802",
    "addr:housenumber":"70",
    "addr:postcode":"3802",
    "addr:street":"Heatherton Rd",
    "iso:country":"AU",
    "sg:address":"70 Heatherton Rd",
    "sg:city":"Endeavour Hills",
    "sg:classifiers":[
        {
            "category":"Health Services",
            "subcategory":"Health Practitioner",
            "type":"Services"
        }
    ],
    "sg:phone":"+61 3 9700 0416",
    "sg:postcode":"3802",
    "sg:province":"VIC",
    "sg:tags":[
        "naturopath"
    ],
    "wof:name":"Family Naturopath",
    "wof:placetype":"venue"
},
  "geometry": {"coordinates":[145.25135803200001,-37.9744491577],"type":"Point"}
}