{
  "type": "Feature",
  "properties": {
    "iso:country":"AU",
    "sg:address":"Shop 3, 57A Buena Vista Drv",
    "sg:city":"Montmorency",
    "sg:classifiers":[
        {
            "category":"Professional",
            "subcategory":"Detective & Security Services",
            "type":"Services"
        }
    ],
    "sg:phone":"+61 3 9439 8717",
    "sg:postcode":"3094",
    "sg:province":"VIC",
    "sg:tags":[
        "consultant",
        "system"
    ],
    "wof:name":"Richard Waters Electronics",
    "wof:placetype":"venue"
},
  "geometry": {"coordinates":[145.129760742,-37.7241973877],"type":"Point"}
}