{
  "type": "Feature",
  "properties": {
    "addr:full":"U1/ 15b Machinery Drv Tweed Heads South NSW 2486",
    "addr:housenumber":"15b",
    "addr:postcode":"2486",
    "addr:street":"U1 /;Machinery Drv",
    "iso:country":"AU",
    "sg:address":"U1/ 15b Machinery Drv",
    "sg:city":"Tweed Heads South",
    "sg:classifiers":[
        {
            "category":"Professional",
            "subcategory":"Printing & Photocopies",
            "type":"Services"
        }
    ],
    "sg:phone":"+61 7 5513 1244",
    "sg:postcode":"2486",
    "sg:province":"NSW",
    "sg:tags":[
        "embroidery"
    ],
    "wof:name":"Tweed Coast Embroidery",
    "wof:placetype":"venue"
},
  "geometry": {"coordinates":[153.539886475,-28.2032413483],"type":"Point"}
}