{
  "type": "Feature",
  "properties": {
    "addr:full":"52 Terrace St Toowong QLD 4066",
    "addr:housenumber":"52",
    "addr:postcode":"4066",
    "addr:street":"Terrace St",
    "iso:country":"AU",
    "sg:address":"52 Terrace St",
    "sg:city":"Toowong",
    "sg:classifiers":[
        {
            "category":"Professional",
            "subcategory":"Management & Consulting",
            "type":"Services"
        }
    ],
    "sg:phone":"+61 7 3870 2660",
    "sg:postcode":"4066",
    "sg:province":"QLD",
    "sg:tags":[
        "consultant"
    ],
    "wof:name":"PRODEX Systems Pty Ltd",
    "wof:placetype":"venue"
},
  "geometry": {"coordinates":[152.980377197,-27.4816265106],"type":"Point"}
}