{
  "type": "Feature",
  "properties": {
    "iso:country":"AU",
    "sg:address":"444 Mitcham Rd",
    "sg:city":"Mitcham",
    "sg:classifiers":[
        {
            "category":"Health Services",
            "subcategory":"Doctor",
            "type":"Services"
        }
    ],
    "sg:phone":"+61 3 9874 1300",
    "sg:postcode":"3132",
    "sg:province":"VIC",
    "sg:tags":[
        "podiatrist"
    ],
    "wof:name":"Eastern Podiatry Clinic",
    "wof:placetype":"venue"
},
  "geometry": {"coordinates":[145.19369506800001,-37.8186607361],"type":"Point"}
}