{
  "type": "Feature",
  "properties": {
    "addr:full":"620 Glenferrie Rd Hawthorn VIC 3122",
    "addr:housenumber":"620",
    "addr:postcode":"3122",
    "addr:street":"Glenferrie Rd",
    "iso:country":"AU",
    "sg:address":"620 Glenferrie Rd",
    "sg:city":"Hawthorn",
    "sg:classifiers":[
        {
            "category":"Shopping",
            "subcategory":"Computers & Home Electronics",
            "type":"Retail Goods"
        }
    ],
    "sg:phone":"+61 3 9819 7321",
    "sg:postcode":"3122",
    "sg:province":"VIC",
    "sg:tags":[
        "hardware",
        "equipment"
    ],
    "wof:name":"Advanced Logic Systems",
    "wof:placetype":"venue"
},
  "geometry": {"coordinates":[145.035354614,-37.8234367371],"type":"Point"}
}