{
  "type": "Feature",
  "properties": {
    "addr:full":"159 Fisher North Rd Cromer NSW 2099",
    "addr:housenumber":"159",
    "addr:postcode":"2099",
    "addr:street":"Fisher North Rd",
    "iso:country":"AU",
    "sg:address":"159 Fisher North Rd",
    "sg:city":"Cromer",
    "sg:classifiers":[
        {
            "category":"Professional",
            "subcategory":"Art Services",
            "type":"Services"
        }
    ],
    "sg:phone":"+61 2 9981 6405",
    "sg:postcode":"2099",
    "sg:province":"NSW",
    "sg:tags":[
        "graphic",
        "designer"
    ],
    "wof:name":"Martian Studio",
    "wof:placetype":"venue"
},
  "geometry": {"coordinates":[151.28352355999999,-33.7424240112],"type":"Point"}
}