{
  "type": "Feature",
  "properties": {
    "addr:full":"Shop 147 Victoria Street (Queen Victoria Market Site) VIC 3000",
    "addr:housenumber":"147",
    "addr:postcode":"3000",
    "addr:street":"Victoria Street",
    "iso:country":"AU",
    "sg:address":"Shop 147",
    "sg:city":"Victoria Street (Queen Victoria Market Site)",
    "sg:classifiers":[
        {
            "category":"Personal",
            "type":"Services"
        }
    ],
    "sg:phone":"+61 3 9326 7844",
    "sg:postcode":"3000",
    "sg:province":"VIC",
    "sg:tags":[
        "gift"
    ],
    "wof:name":"Moulin Rouge Lingerie",
    "wof:placetype":"venue"
},
  "geometry": {"coordinates":[144.956542969,-37.8060569763],"type":"Point"}
}