{
  "type": "Feature",
  "properties": {
    "addr:full":"80- 84 Parramatta Rd Croydon NSW 2132",
    "addr:housenumber":"84",
    "addr:postcode":"2132",
    "addr:street":"Parramatta Rd",
    "iso:country":"AU",
    "sg:address":"80- 84 Parramatta Rd",
    "sg:city":"Croydon",
    "sg:classifiers":[
        {
            "category":"Autos & Motor Vehicles",
            "subcategory":"Auto Supplies",
            "type":"Retail Goods"
        }
    ],
    "sg:phone":"+61 2 9715 3100",
    "sg:postcode":"2132",
    "sg:province":"NSW",
    "sg:tags":[
        "accessory"
    ],
    "wof:name":"Euroticar Car Bra's & Auto Accessories",
    "wof:placetype":"venue"
},
  "geometry": {"coordinates":[151.11549377399999,-33.8705558777],"type":"Point"}
}