{
  "type": "Feature",
  "properties": {
    "iso:country":"AU",
    "sg:address":"1c Leonard Ave",
    "sg:city":"Noble Park",
    "sg:classifiers":[
        {
            "category":"Fast Food",
            "type":"Food & Drink"
        }
    ],
    "sg:phone":"+61 3 9574 1538",
    "sg:postcode":"3174",
    "sg:province":"VIC",
    "sg:tags":[
        "away",
        "take"
    ],
    "wof:name":"The Curry Hut",
    "wof:placetype":"venue"
},
  "geometry": {"coordinates":[145.176239014,-37.9676017761],"type":"Point"}
}