{
  "type": "Feature",
  "properties": {
    "iso:country":"AU",
    "sg:address":"Shop 1/ 121 Lawes St",
    "sg:city":"East Maitland",
    "sg:classifiers":[
        {
            "category":"Fast Food",
            "type":"Food & Drink"
        }
    ],
    "sg:phone":"+61 2 4933 4308",
    "sg:postcode":"2323",
    "sg:province":"NSW",
    "sg:tags":[
        "away",
        "take"
    ],
    "wof:name":"Walk In 4 Shaw Kebabs & Gourmet Take Away",
    "wof:placetype":"venue"
},
  "geometry": {"coordinates":[151.59005737300001,-32.7513923645],"type":"Point"}
}