{
  "type": "Feature",
  "properties": {
    "addr:full":"Unit 3, 4 Narabang Way Belrose NSW 2085",
    "addr:housenumber":"4",
    "addr:postcode":"2085",
    "addr:street":"Narabang Way",
    "iso:country":"AU",
    "sg:address":"Unit 3, 4 Narabang Way",
    "sg:city":"Belrose",
    "sg:classifiers":[
        {
            "category":"Social Services",
            "subcategory":"Child Care",
            "type":"Services"
        }
    ],
    "sg:phone":"+61 2 9485 0455",
    "sg:postcode":"2085",
    "sg:province":"NSW",
    "sg:tags":[
        "equipment",
        "identification"
    ],
    "sg:website":"http://www.idsupplies.com.au",
    "wof:name":"ID Supplies Pty Ltd",
    "wof:placetype":"venue"
},
  "geometry": {"coordinates":[151.21232605,-33.7051506042],"type":"Point"}
}