{
  "type": "Feature",
  "properties": {
    "addr:full":"Shop T13 Orana Mall Cnr Wheelers La & Mitchell Hwy Dubbo NSW 2830",
    "addr:postcode":"2830",
    "addr:street":"Cnr Wheelers La & Mitchell Hwy",
    "iso:country":"AU",
    "sg:address":"Shop T13 Orana Mall Cnr Wheelers La & Mitchell Hwy",
    "sg:city":"Dubbo",
    "sg:classifiers":[
        {
            "category":"Retail",
            "subcategory":"Repair Shop",
            "type":"Services"
        }
    ],
    "sg:phone":"+61 2 6882 7996",
    "sg:postcode":"2830",
    "sg:province":"NSW",
    "sg:tags":[
        "handbag"
    ],
    "wof:name":"Kays Bag Stores (NSW) Pty Ltd",
    "wof:placetype":"venue"
},
  "geometry": {"coordinates":[148.59625244099999,-32.2509803772],"type":"Point"}
}