{
  "type": "Feature",
  "properties": {
    "addr:full":"Shp20/ 25 Durlacher St Geraldton WA 6530",
    "addr:postcode":"6530",
    "addr:street":"Durlacher St",
    "iso:country":"AU",
    "sg:address":"Shp20/ 25 Durlacher St",
    "sg:city":"Geraldton",
    "sg:classifiers":[
        {
            "category":"Professional",
            "subcategory":"Engineering",
            "type":"Services"
        }
    ],
    "sg:phone":"+61 8 9965 2922",
    "sg:postcode":"6530",
    "sg:province":"WA",
    "sg:tags":[
        "engineer"
    ],
    "wof:name":"Peak Consultants Pty Ltd",
    "wof:placetype":"venue"
},
  "geometry": {"coordinates":[114.610939026,-28.7729873657],"type":"Point"}
}