{
  "type": "Feature",
  "properties": {
    "iso:country":"AU",
    "sg:address":"Lakehaven Drv",
    "sg:city":"Kanwal",
    "sg:classifiers":[
        {
            "category":"Arena",
            "subcategory":"Sports Club",
            "type":"Entertainment"
        }
    ],
    "sg:phone":"+61 2 4392 2799",
    "sg:postcode":"2259",
    "sg:province":"NSW",
    "sg:tags":[
        "league",
        "rugby"
    ],
    "wof:name":"Wyong Rugby League Club",
    "wof:placetype":"venue"
},
  "geometry": {"coordinates":[151.49688720699999,-33.2538490295],"type":"Point"}
}