{
  "type": "Feature",
  "properties": {
    "iso:country":"AU",
    "sg:address":"39 Cairns St",
    "sg:city":"Kangaroo Point",
    "sg:classifiers":[
        {
            "category":"Real Estate",
            "subcategory":"Developer",
            "type":"Services"
        }
    ],
    "sg:phone":"+61 7 3392 1900",
    "sg:postcode":"4169",
    "sg:province":"QLD",
    "sg:tags":[
        "development"
    ],
    "wof:name":"Foster Richard & Associates Pty Ltd",
    "wof:placetype":"venue"
},
  "geometry": {"coordinates":[153.03732299800001,-27.4733829498],"type":"Point"}
}