{
  "type": "Feature",
  "properties": {
    "addr:full":"Fitzroy St Walcha NSW 2354",
    "addr:postcode":"2354",
    "addr:street":"Fitzroy St",
    "iso:country":"AU",
    "sg:address":"Fitzroy St",
    "sg:city":"Walcha",
    "sg:classifiers":[
        {
            "category":"Food & Beverages",
            "subcategory":"Supermarket",
            "type":"Retail Goods"
        }
    ],
    "sg:phone":"+61 2 6777 2211",
    "sg:postcode":"2354",
    "sg:province":"NSW",
    "sg:tags":[
        "grocery",
        "store"
    ],
    "wof:name":"Tucker Bag Supermarket",
    "wof:placetype":"venue"
},
  "geometry": {"coordinates":[151.58757019000001,-30.9842853546],"type":"Point"}
}