{
  "type": "Feature",
  "properties": {
    "addr:full":"58 Main St Foster VIC 3960",
    "addr:housenumber":"58",
    "addr:postcode":"3960",
    "addr:street":"Main St",
    "iso:country":"AU",
    "sg:address":"58 Main St",
    "sg:city":"Foster",
    "sg:classifiers":[
        {
            "category":"Food & Beverages",
            "subcategory":"Supermarket",
            "type":"Retail Goods"
        }
    ],
    "sg:phone":"+61 3 5682 2495",
    "sg:postcode":"3960",
    "sg:province":"VIC",
    "sg:tags":[
        "grocery",
        "store"
    ],
    "wof:name":"Foster Food-Rite",
    "wof:placetype":"venue"
},
  "geometry": {"coordinates":[146.38706970199999,-38.7091407776],"type":"Point"}
}