{
  "type": "Feature",
  "properties": {
    "iso:country":"AU",
    "sg:address":"85c Jetty Rd",
    "sg:city":"Glenelg",
    "sg:classifiers":[
        {
            "category":"Arena",
            "subcategory":"Horse Racetrack",
            "type":"Entertainment"
        }
    ],
    "sg:phone":"+61 8 8295 5166",
    "sg:postcode":"5045",
    "sg:province":"SA",
    "sg:tags":[
        "retail",
        "swimwear"
    ],
    "wof:name":"Serenety Lingerie",
    "wof:placetype":"venue"
},
  "geometry": {"coordinates":[138.516953,-34.980061],"type":"Point"}
}