{
  "type": "Feature",
  "properties": {
    "iso:country":"AU",
    "sg:address":"8 Koola Drv",
    "sg:city":"Nerang",
    "sg:classifiers":[
        {
            "category":"Retail",
            "subcategory":"Repair Shop",
            "type":"Services"
        }
    ],
    "sg:phone":"+61 413 114 669",
    "sg:postcode":"4211",
    "sg:province":"QLD",
    "sg:tags":[
        "machine",
        "repairs",
        "part",
        "dryer",
        "washing"
    ],
    "wof:name":"L & R Appliance Service",
    "wof:placetype":"venue"
},
  "geometry": {"coordinates":[153.303131103,-28.0007839203],"type":"Point"}
}