{
  "type": "Feature",
  "properties": {
    "addr:full":"6 Gartfern Ave Five Dock NSW 2046",
    "addr:housenumber":"6",
    "addr:postcode":"2046",
    "addr:street":"Gartfern Ave",
    "iso:country":"AU",
    "sg:address":"6 Gartfern Ave",
    "sg:city":"Five Dock",
    "sg:classifiers":[
        {
            "category":"Health Services",
            "subcategory":"Health Practitioner",
            "type":"Services"
        }
    ],
    "sg:phone":"+61 2 9963 1485",
    "sg:postcode":"2046",
    "sg:province":"NSW",
    "sg:tags":[
        "dietitian"
    ],
    "wof:name":"Ryan Liz (APD)",
    "wof:placetype":"venue"
},
  "geometry": {"coordinates":[151.13330099999999,-33.85968],"type":"Point"}
}