{
  "type": "Feature",
  "properties": {
    "addr:full":"82-90 Mosman St Charters Towers QLD 4820",
    "addr:housenumber":"82-90",
    "addr:postcode":"4820",
    "addr:street":"Mosman St",
    "iso:country":"AU",
    "sg:address":"82-90 Mosman St",
    "sg:city":"Charters Towers",
    "sg:classifiers":[
        {
            "category":"Arts & Performance",
            "subcategory":"Theater",
            "type":"Entertainment"
        }
    ],
    "sg:phone":"+61 7 4787 4344",
    "sg:postcode":"4820",
    "sg:province":"QLD",
    "sg:tags":[
        "theatre"
    ],
    "wof:name":"World Theatre",
    "wof:placetype":"venue"
},
  "geometry": {"coordinates":[146.25676000000001,-20.076357],"type":"Point"}
}