{
  "type": "Feature",
  "properties": {
    "addr:full":"47 Mitchell St Cobden VIC 3266",
    "addr:housenumber":"47",
    "addr:postcode":"3266",
    "addr:street":"Mitchell St",
    "iso:country":"AU",
    "sg:address":"47 Mitchell St",
    "sg:city":"Cobden",
    "sg:classifiers":[
        {
            "category":"Building & Trades",
            "subcategory":"Construction",
            "type":"Services"
        }
    ],
    "sg:phone":"+61 438 018 801",
    "sg:postcode":"3266",
    "sg:province":"VIC",
    "sg:tags":[
        "contractor"
    ],
    "wof:name":"Kelson L V & Sons",
    "wof:placetype":"venue"
},
  "geometry": {"coordinates":[143.06883239699999,-38.3304481506],"type":"Point"}
}