{
  "type": "Feature",
  "properties": {
    "addr:full":"763 Nicholson St Carlton North VIC 3054",
    "addr:housenumber":"763",
    "addr:postcode":"3054",
    "addr:street":"Nicholson St",
    "iso:country":"AU",
    "sg:address":"763 Nicholson St",
    "sg:city":"Carlton North",
    "sg:classifiers":[
        {
            "category":"Shopping",
            "subcategory":"Clothing, Apparel, & Fashions",
            "type":"Retail Goods"
        }
    ],
    "sg:phone":"+61 3 9388 9100",
    "sg:postcode":"3054",
    "sg:province":"VIC",
    "sg:tags":[
        "recycled",
        "clothing"
    ],
    "wof:name":"Second Hand Lane Way The",
    "wof:placetype":"venue"
},
  "geometry": {"coordinates":[144.97764587399999,-37.7814903259],"type":"Point"}
}