{
  "type": "Feature",
  "properties": {
    "iso:country":"AU",
    "sg:address":"50- 56 Ham St",
    "sg:city":"Kangaroo Flat",
    "sg:classifiers":[
        {
            "category":"Home & Garden",
            "subcategory":"Building Materials",
            "type":"Retail Goods"
        }
    ],
    "sg:phone":"+61 3 5447 9133",
    "sg:postcode":"3555",
    "sg:province":"VIC",
    "sg:tags":[
        "merchant",
        "glass",
        "glazier"
    ],
    "wof:name":"Golden City Glass",
    "wof:placetype":"venue"
},
  "geometry": {"coordinates":[144.25677490199999,-36.7924537659],"type":"Point"}
}