{
  "type": "Feature",
  "properties": {
    "iso:country":"AU",
    "sg:address":"Daikyo House Level 5 33 Elkhorn Ave",
    "sg:city":"Surfers Paradise",
    "sg:classifiers":[
        {
            "category":"Professional",
            "subcategory":"Employment Agencies",
            "type":"Services"
        }
    ],
    "sg:phone":"+61 7 5561 0131",
    "sg:postcode":"4217",
    "sg:province":"QLD",
    "sg:tags":[
        "model"
    ],
    "wof:name":"Boss Models",
    "wof:placetype":"venue"
},
  "geometry": {"coordinates":[153.42759704599999,-27.9986419678],"type":"Point"}
}