{
  "type": "Feature",
  "properties": {
    "addr:full":"20a Maple St Cooroy QLD 4563",
    "addr:housenumber":"20a",
    "addr:postcode":"4563",
    "addr:street":"Maple St",
    "iso:country":"AU",
    "sg:address":"20a Maple St",
    "sg:city":"Cooroy",
    "sg:classifiers":[
        {
            "category":"Manufacturing",
            "subcategory":"Textiles",
            "type":"Manufacturing & Wholesale Goods"
        }
    ],
    "sg:phone":"+61 7 5447 6145",
    "sg:postcode":"4563",
    "sg:province":"QLD",
    "sg:tags":[
        "knitted",
        "woven",
        "fabric"
    ],
    "wof:name":"Cooroy Drapery",
    "wof:placetype":"venue"
},
  "geometry": {"coordinates":[152.910324097,-26.4168376923],"type":"Point"}
}