{
  "type": "Feature",
  "properties": {
    "addr:full":"148 Eleventh St Mildura VIC 3500",
    "addr:housenumber":"148",
    "addr:postcode":"3500",
    "addr:street":"Eleventh St",
    "iso:country":"AU",
    "sg:address":"148 Eleventh St",
    "sg:city":"Mildura",
    "sg:classifiers":[
        {
            "category":"Building & Trades",
            "subcategory":"Construction",
            "type":"Services"
        }
    ],
    "sg:phone":"+61 13 23 12",
    "sg:postcode":"3500",
    "sg:province":"VIC",
    "sg:tags":[
        "earth",
        "excavating",
        "moving",
        "contractor"
    ],
    "wof:name":"A.H. Plant Hire",
    "wof:placetype":"venue"
},
  "geometry": {"coordinates":[142.165557861,-34.1961097717],"type":"Point"}
}