{
  "type": "Feature",
  "properties": {
    "iso:country":"AU",
    "sg:address":"51 Russell St",
    "sg:city":"Newtown",
    "sg:classifiers":[
        {
            "category":"Social Services",
            "subcategory":"Child Care",
            "type":"Services"
        }
    ],
    "sg:phone":"+61 3 5221 5696",
    "sg:postcode":"3220",
    "sg:province":"VIC",
    "sg:tags":[
        "support",
        "health"
    ],
    "wof:name":"Newtown",
    "wof:placetype":"venue"
},
  "geometry": {"coordinates":[144.34683200000001,-38.157078],"type":"Point"}
}