{
  "type": "Feature",
  "properties": {
    "addr:full":"1 Valentine St Kewdale WA 6105",
    "addr:housenumber":"1",
    "addr:postcode":"6105",
    "addr:street":"Valentine St",
    "iso:country":"AU",
    "sg:address":"1 Valentine St",
    "sg:city":"Kewdale",
    "sg:classifiers":[
        {
            "category":"Railroad",
            "type":"Transportation"
        }
    ],
    "sg:phone":"+61 8 9353 1566",
    "sg:postcode":"6105",
    "sg:province":"WA",
    "sg:tags":[
        "equipment",
        "railway",
        "construction",
        "material"
    ],
    "wof:name":"TKL Rail",
    "wof:placetype":"venue"
},
  "geometry": {"coordinates":[115.95728302000001,-31.9713554382],"type":"Point"}
}