{
  "type": "Feature",
  "properties": {
    "addr:full":"7 Corio St Bulimba QLD 4171",
    "addr:housenumber":"7",
    "addr:postcode":"4171",
    "addr:street":"Corio St",
    "iso:country":"AU",
    "sg:address":"7 Corio St",
    "sg:city":"Bulimba",
    "sg:classifiers":[
        {
            "category":"Manufacturing",
            "subcategory":"Metals",
            "type":"Manufacturing & Wholesale Goods"
        }
    ],
    "sg:phone":"+61 7 3399 8804",
    "sg:postcode":"4171",
    "sg:province":"QLD",
    "sg:tags":[
        "steel",
        "fabricator",
        "mfrs"
    ],
    "wof:name":"N S Fabrications",
    "wof:placetype":"venue"
},
  "geometry": {"coordinates":[153.056396484,-27.4539928436],"type":"Point"}
}