{
  "type": "Feature",
  "properties": {
    "addr:full":"Factory 2/ 34 Dehavilland Rd Mordialloc VIC 3195",
    "addr:housenumber":"/ 34",
    "addr:postcode":"3195",
    "addr:street":"Dehavilland Rd",
    "iso:country":"AU",
    "sg:address":"Factory 2/ 34 Dehavilland Rd",
    "sg:city":"Mordialloc",
    "sg:classifiers":[
        {
            "category":"Food & Beverages",
            "subcategory":"Fruits & Vegetables",
            "type":"Retail Goods"
        }
    ],
    "sg:phone":"+61 3 9580 0519",
    "sg:postcode":"3195",
    "sg:province":"VIC",
    "sg:tags":[
        "consultant",
        "catering"
    ],
    "wof:name":"Tim George Catering",
    "wof:placetype":"venue"
},
  "geometry": {"coordinates":[145.100875855,-37.9889640808],"type":"Point"}
}