{
  "type": "Feature",
  "properties": {
    "addr:full":"101 Wheatsheaf Rd Glenroy VIC 3046",
    "addr:housenumber":"101",
    "addr:postcode":"3046",
    "addr:street":"Wheatsheaf Rd",
    "iso:country":"AU",
    "sg:address":"101 Wheatsheaf Rd",
    "sg:city":"Glenroy",
    "sg:classifiers":[
        {
            "category":"Personal",
            "subcategory":"Massage",
            "type":"Services"
        }
    ],
    "sg:phone":"+61 3 9306 7822",
    "sg:postcode":"3046",
    "sg:province":"VIC",
    "sg:tags":[
        "therapy"
    ],
    "wof:name":"Glamour & Beauty",
    "wof:placetype":"venue"
},
  "geometry": {"coordinates":[144.92013549800001,-37.7069206238],"type":"Point"}
}