{
  "type": "Feature",
  "properties": {
    "iso:country":"AU",
    "sg:address":"25 Aitken St",
    "sg:city":"Williamstown",
    "sg:classifiers":[
        {
            "category":"Home & Garden",
            "subcategory":"Hardware",
            "type":"Retail Goods"
        }
    ],
    "sg:phone":"+61 3 9397 6099",
    "sg:postcode":"3016",
    "sg:province":"VIC",
    "sg:tags":[
        "pipe",
        "fitting",
        "plastic"
    ],
    "wof:name":"Plastic Pipe Fabrication (Aus) Pty Ltd",
    "wof:placetype":"venue"
},
  "geometry": {"coordinates":[144.90757751500001,-37.86536026],"type":"Point"}
}