{
  "type": "Feature",
  "properties": {
    "addr:full":"Cnr Nissen St & Boat Harbour Drv Pialba QLD 4655",
    "addr:postcode":"4655",
    "addr:street":"Nissen St & Boat Harbour Drv",
    "iso:country":"AU",
    "sg:address":"Cnr Nissen St & Boat Harbour Drv",
    "sg:city":"Pialba",
    "sg:classifiers":[
        {
            "category":"Autos & Motor Vehicles",
            "subcategory":"Automobile Sales",
            "type":"Retail Goods"
        }
    ],
    "sg:phone":"+61 7 4124 0000",
    "sg:postcode":"4655",
    "sg:province":"QLD",
    "sg:tags":[
        "car",
        "new"
    ],
    "wof:name":"Bay City Nissan, Honda, Kia & Suzuki",
    "wof:placetype":"venue"
},
  "geometry": {"coordinates":[152.827484,-25.285702],"type":"Point"}
}