{
  "type": "Feature",
  "properties": {
    "iso:country":"AU",
    "sg:address":"2 Pier St",
    "sg:city":"Walpole",
    "sg:classifiers":[
        {
            "category":"Health Services",
            "subcategory":"Doctor",
            "type":"Services"
        }
    ],
    "sg:phone":"+61 8 9840 0900",
    "sg:postcode":"6398",
    "sg:province":"WA",
    "sg:tags":[
        "nurse",
        "nursing"
    ],
    "wof:name":"Silver Chain",
    "wof:placetype":"venue"
},
  "geometry": {"coordinates":[116.734107971,-34.9755554199],"type":"Point"}
}