{
  "type": "Feature",
  "properties": {
    "addr:full":"Battunga Rd Echunga SA 5153",
    "addr:postcode":"5153",
    "addr:street":"Battunga Rd",
    "iso:country":"AU",
    "sg:address":"Battunga Rd",
    "sg:city":"Echunga",
    "sg:classifiers":[
        {
            "category":"Retail",
            "subcategory":"Event Space",
            "type":"Services"
        }
    ],
    "sg:phone":"+61 8 8388 8385",
    "sg:postcode":"5153",
    "sg:province":"SA",
    "sg:tags":[
        "venue",
        "reception",
        "wedding"
    ],
    "wof:name":"Hazelmere Homestead",
    "wof:placetype":"venue"
},
  "geometry": {"coordinates":[138.79302978499999,-35.1015167236],"type":"Point"}
}