{
  "type": "Feature",
  "properties": {
    "addr:full":"17 Abruzzo Crs Thomastown VIC 3074",
    "addr:housenumber":"17",
    "addr:postcode":"3074",
    "addr:street":"Abruzzo Crs",
    "iso:country":"AU",
    "sg:address":"17 Abruzzo Crs",
    "sg:city":"Thomastown",
    "sg:classifiers":[
        {
            "category":"Retail",
            "subcategory":"Auto Repair",
            "type":"Services"
        }
    ],
    "sg:phone":"+61 3 9465 8044",
    "sg:postcode":"3074",
    "sg:province":"VIC",
    "sg:tags":[
        "repairer",
        "motor",
        "engineer"
    ],
    "wof:name":"Melbourne Autocare Centre",
    "wof:placetype":"venue"
},
  "geometry": {"coordinates":[145.01148986800001,-37.6832199097],"type":"Point"}
}