{
  "type": "Feature",
  "properties": {
    "iso:country":"AU",
    "sg:address":"13- 15 Enterprise Rd",
    "sg:city":"Bohle",
    "sg:classifiers":[
        {
            "category":"Food & Beverages",
            "subcategory":"Bakery",
            "type":"Retail Goods"
        }
    ],
    "sg:phone":"+61 7 4774 6300",
    "sg:postcode":"4818",
    "sg:province":"QLD",
    "sg:tags":[
        "baker"
    ],
    "wof:name":"QLD Country Bakeries Townsville",
    "wof:placetype":"venue"
},
  "geometry": {"coordinates":[146.71212800000001,-19.261566],"type":"Point"}
}