{
  "type": "Feature",
  "properties": {
    "iso:country":"AU",
    "sg:address":"116 Bungarribee Rd",
    "sg:city":"Blacktown",
    "sg:classifiers":[
        {
            "category":"Retail",
            "subcategory":"Auto Repair",
            "type":"Services"
        }
    ],
    "sg:phone":"+61 2 9622 5511",
    "sg:postcode":"2148",
    "sg:province":"NSW",
    "sg:tags":[
        "repairer",
        "motor",
        "engineer"
    ],
    "wof:name":"Goodyear Auto Service Centre",
    "wof:placetype":"venue"
},
  "geometry": {"coordinates":[150.907958984,-33.7773742676],"type":"Point"}
}