{
  "type": "Feature",
  "properties": {
    "iso:country":"AU",
    "sg:address":"Unit 18, 365 West Botany St",
    "sg:city":"Rockdale",
    "sg:classifiers":[
        {
            "category":"Building & Trades",
            "subcategory":"Construction",
            "type":"Services"
        }
    ],
    "sg:phone":"+61 2 9599 9975",
    "sg:postcode":"2216",
    "sg:province":"NSW",
    "sg:tags":[
        "builder",
        "designer",
        "room",
        "cool"
    ],
    "wof:name":"Royal Refrigeration Pty Ltd",
    "wof:placetype":"venue"
},
  "geometry": {"coordinates":[151.155731,-33.96069],"type":"Point"}
}