{
  "type": "Feature",
  "properties": {
    "addr:full":"11 Crosskeys Rd Salisbury SA 5108",
    "addr:housenumber":"11",
    "addr:postcode":"5108",
    "addr:street":"Crosskeys Rd",
    "iso:country":"AU",
    "sg:address":"11 Crosskeys Rd",
    "sg:city":"Salisbury",
    "sg:classifiers":[
        {
            "category":"Autos & Motor Vehicles",
            "subcategory":"Auto Supplies",
            "type":"Retail Goods"
        }
    ],
    "sg:phone":"+61 8 8285 6600",
    "sg:postcode":"5108",
    "sg:province":"SA",
    "sg:tags":[
        "tyre"
    ],
    "wof:name":"Salisbury Tyre & Mag Centre",
    "wof:placetype":"venue"
},
  "geometry": {"coordinates":[138.65127563499999,-34.7689285278],"type":"Point"}
}