{
  "type": "Feature",
  "properties": {
    "addr:full":"1/ 407 McClelland Drv Langwarrin VIC 3910",
    "addr:housenumber":"/ 407",
    "addr:postcode":"3910",
    "addr:street":"Mcclelland Drv",
    "iso:country":"AU",
    "sg:address":"1/ 407 McClelland Drv",
    "sg:city":"Langwarrin",
    "sg:classifiers":[
        {
            "category":"Banks & Credit Unions",
            "subcategory":"Bureau De Change",
            "type":"Services"
        }
    ],
    "sg:phone":"+61 3 9776 6628",
    "sg:postcode":"3910",
    "sg:province":"VIC",
    "sg:tags":[
        "gas",
        "natural",
        "lp",
        "equipment"
    ],
    "wof:name":"Compujection Pty Ltd",
    "wof:placetype":"venue"
},
  "geometry": {"coordinates":[145.168212891,-38.168346405],"type":"Point"}
}