{
  "type": "Feature",
  "properties": {
    "addr:full":"Level 11/ 61 Lavender St Milsons Point NSW 2061",
    "addr:housenumber":"/ 61",
    "addr:postcode":"2061",
    "addr:street":"Lavender St",
    "iso:country":"AU",
    "sg:address":"Level 11/ 61 Lavender St",
    "sg:city":"Milsons Point",
    "sg:classifiers":[
        {
            "category":"Utilities",
            "subcategory":"Natural Gas",
            "type":"Services"
        }
    ],
    "sg:phone":"+61 2 9954 5111",
    "sg:postcode":"2061",
    "sg:province":"NSW",
    "sg:tags":[
        "supplier"
    ],
    "wof:name":"CNG International Corporation",
    "wof:placetype":"venue"
},
  "geometry": {"coordinates":[151.209884644,-33.8436012268],"type":"Point"}
}