{
  "type": "Feature",
  "properties": {
    "addr:full":"PO Box 320 Ryde NSW 2112",
    "addr:postcode":"2112",
    "iso:country":"AU",
    "sg:address":"PO Box 320",
    "sg:city":"Ryde",
    "sg:classifiers":[
        {
            "category":"Retail",
            "subcategory":"Auto Repair",
            "type":"Services"
        }
    ],
    "sg:phone":"+61 2 9874 9393",
    "sg:postcode":"2112",
    "sg:province":"NSW",
    "sg:tags":[
        "repairer",
        "motor",
        "engineer"
    ],
    "wof:name":"Taurus Mobile Mechanic",
    "wof:placetype":"venue"
},
  "geometry": {"coordinates":[151.11233520499999,-33.8131599426],"type":"Point"}
}