{
  "type": "Feature",
  "properties": {
    "addr:full":"Springfield Ave Blacktown NSW 2148",
    "addr:postcode":"2148",
    "addr:street":"Springfield Ave",
    "iso:country":"AU",
    "sg:address":"Springfield Ave",
    "sg:city":"Blacktown",
    "sg:classifiers":[
        {
            "category":"Sports & Exercise",
            "subcategory":"Golf",
            "type":"Entertainment"
        }
    ],
    "sg:phone":"+61 2 9622 4300",
    "sg:postcode":"2148",
    "sg:province":"NSW",
    "sg:tags":[
        "club"
    ],
    "wof:name":"Ashlar Golf Club Ltd",
    "wof:placetype":"venue"
},
  "geometry": {"coordinates":[150.903686523,-33.7646522522],"type":"Point"}
}