{
  "type": "Feature",
  "properties": {
    "iso:country":"AU",
    "sg:address":"PO Box 9",
    "sg:city":"Kingston",
    "sg:classifiers":[
        {
            "category":"Airport",
            "subcategory":"International",
            "type":"Transportation"
        }
    ],
    "sg:phone":"+61 417 792 685",
    "sg:postcode":"4114",
    "sg:province":"QLD",
    "sg:tags":[
        "diving",
        "commercial"
    ],
    "wof:name":"Bottoms Up Marine Services",
    "wof:placetype":"venue"
},
  "geometry": {"coordinates":[153.11424255399999,-27.6566905975],"type":"Point"}
}