{
  "type": "Feature",
  "properties": {
    "addr:full":"Suite 1.3, 34 Erin St Richmond VIC 3121",
    "addr:housenumber":"34",
    "addr:postcode":"3121",
    "addr:street":"1.3;Erin St",
    "iso:country":"AU",
    "sg:address":"Suite 1.3, 34 Erin St",
    "sg:city":"Richmond",
    "sg:classifiers":[
        {
            "category":"Health Services",
            "subcategory":"Doctor",
            "type":"Services"
        }
    ],
    "sg:phone":"+61 3 9318 8100",
    "sg:postcode":"3121",
    "sg:province":"VIC",
    "sg:tags":[
        "medical",
        "practitioner"
    ],
    "wof:name":"Agarwal Dinesh Mr",
    "wof:placetype":"venue"
},
  "geometry": {"coordinates":[144.99261474599999,-37.8166999817],"type":"Point"}
}