{
  "type": "Feature",
  "properties": {
    "addr:full":"Soldiers Rd Sandy Point VIC 3959",
    "addr:postcode":"3959",
    "addr:street":"Soldiers Rd",
    "iso:country":"AU",
    "sg:address":"Soldiers Rd",
    "sg:city":"Sandy Point",
    "sg:classifiers":[
        {
            "category":"Building & Trades",
            "subcategory":"Landscaping Services",
            "type":"Services"
        }
    ],
    "sg:phone":"+61 3 5684 1215",
    "sg:postcode":"3959",
    "sg:province":"VIC",
    "sg:tags":[
        "grazier"
    ],
    "wof:name":"Heywood M.G. & L.R.",
    "wof:placetype":"venue"
},
  "geometry": {"coordinates":[146.08709716800001,-38.7908058167],"type":"Point"}
}