{
  "type": "Feature",
  "properties": {
    "iso:country":"AU",
    "sg:address":"Livingstone La",
    "sg:city":"Ironbark",
    "sg:classifiers":[
        {
            "category":"Building & Trades",
            "subcategory":"Equipment Rental",
            "type":"Services"
        }
    ],
    "sg:phone":"+61 7 5464 5332",
    "sg:postcode":"4306",
    "sg:province":"QLD",
    "sg:tags":[
        "crane",
        "hire"
    ],
    "wof:name":"G J Transport Management Pty Ltd",
    "wof:placetype":"venue"
},
  "geometry": {"coordinates":[152.662399292,-27.5684642792],"type":"Point"}
}