{
  "type": "Feature",
  "properties": {
    "addr:full":"41- 45 Tingira St Portsmith QLD 4870",
    "addr:housenumber":"45",
    "addr:postcode":"4870",
    "addr:street":"Tingira St Portsmith",
    "iso:country":"AU",
    "sg:address":"41- 45 Tingira St",
    "sg:city":"Portsmith",
    "sg:classifiers":[
        {
            "category":"Transit Center",
            "subcategory":"Freight",
            "type":"Transportation"
        }
    ],
    "sg:phone":"+61 7 4035 1234",
    "sg:postcode":"4870",
    "sg:province":"QLD",
    "sg:tags":[
        "agent",
        "shipping"
    ],
    "wof:name":"Sea Swift Pty Ltd",
    "wof:placetype":"venue"
},
  "geometry": {"coordinates":[145.77218627900001,-16.9450912476],"type":"Point"}
}