{
  "type": "Feature",
  "properties": {
    "iso:country":"AU",
    "sg:address":"19 Jamieson St",
    "sg:city":"Warrnambool",
    "sg:classifiers":[
        {
            "category":"Professional",
            "subcategory":"Business Services",
            "type":"Services"
        }
    ],
    "sg:phone":"+61 3 5561 3444",
    "sg:postcode":"3280",
    "sg:province":"VIC",
    "sg:tags":[
        "drafting"
    ],
    "wof:name":"Steel & Tippett Building Designers & Drafting Services",
    "wof:placetype":"venue"
},
  "geometry": {"coordinates":[142.484085083,-38.3769645691],"type":"Point"}
}