{
  "type": "Feature",
  "properties": {
    "addr:full":"31 Reynolds Drv Paralowie SA 5108",
    "addr:housenumber":"31",
    "addr:postcode":"5108",
    "addr:street":"Reynolds Drv",
    "iso:country":"AU",
    "sg:address":"31 Reynolds Drv",
    "sg:city":"Paralowie",
    "sg:classifiers":[
        {
            "category":"Utilities",
            "subcategory":"Electric",
            "type":"Services"
        }
    ],
    "sg:phone":"+61 419 030 572",
    "sg:postcode":"5108",
    "sg:province":"SA",
    "sg:tags":[
        "electrical",
        "contractor"
    ],
    "wof:name":"Kenrich Electrical",
    "wof:placetype":"venue"
},
  "geometry": {"coordinates":[138.603057861,-34.7551612854],"type":"Point"}
}