{
  "type": "Feature",
  "properties": {
    "iso:country":"AU",
    "sg:address":"79a Fitzroy St",
    "sg:city":"St Kilda",
    "sg:classifiers":[
        {
            "category":"Professional",
            "subcategory":"Business Services",
            "type":"Services"
        }
    ],
    "sg:phone":"+61 3 9534 5288",
    "sg:postcode":"3182",
    "sg:province":"VIC",
    "sg:tags":[
        "exporter"
    ],
    "wof:name":"P.J.S.T Importers & Exporters Pty Ltd",
    "wof:placetype":"venue"
},
  "geometry": {"coordinates":[144.976104736,-37.8606643677],"type":"Point"}
}