{
  "type": "Feature",
  "properties": {
    "iso:country":"AU",
    "sg:address":"Cnr Flynn Drv & Mather St",
    "sg:city":"Wanneroo",
    "sg:classifiers":[
        {
            "category":"Home & Garden",
            "subcategory":"Building Materials",
            "type":"Retail Goods"
        }
    ],
    "sg:phone":"+61 8 9306 2722",
    "sg:postcode":"6065",
    "sg:province":"WA",
    "sg:tags":[
        "roofing"
    ],
    "wof:name":"Whittakers Craigie Park Timber Supplies",
    "wof:placetype":"venue"
},
  "geometry": {"coordinates":[115.803771973,-31.7504901886],"type":"Point"}
}