{
  "type": "Feature",
  "properties": {
    "addr:full":"Jarvis St Alice Springs NT 0870",
    "addr:postcode":"nt 0870",
    "addr:street":"Jarvis St",
    "iso:country":"AU",
    "sg:address":"Jarvis St",
    "sg:city":"Alice Springs",
    "sg:classifiers":[
        {
            "category":"Real Estate",
            "subcategory":"Architect",
            "type":"Services"
        }
    ],
    "sg:phone":"+61 8 8952 0135",
    "sg:postcode":"0870",
    "sg:province":"NT",
    "wof:name":"Corbett Hill",
    "wof:placetype":"venue"
},
  "geometry": {"coordinates":[133.871917725,-23.6867809296],"type":"Point"}
}