{
  "type": "Feature",
  "properties": {
    "addr:full":"Unit9/ 87 Hector St Osborne Park WA 6017",
    "addr:housenumber":"87",
    "addr:postcode":"6017",
    "addr:street":"Hector St",
    "iso:country":"AU",
    "sg:address":"Unit9/ 87 Hector St",
    "sg:city":"Osborne Park",
    "sg:classifiers":[
        {
            "category":"Retail",
            "subcategory":"Auto Rental",
            "type":"Services"
        }
    ],
    "sg:phone":"+61 433 776 615",
    "sg:postcode":"6017",
    "sg:province":"WA",
    "sg:tags":[
        "camper-trailers",
        "caravan",
        "hire"
    ],
    "wof:name":"Total Camper Hire",
    "wof:placetype":"venue"
},
  "geometry": {"coordinates":[115.82350921600001,-31.9043045044],"type":"Point"}
}