{
  "type": "Feature",
  "properties": {
    "iso:country":"AU",
    "sg:address":"67 Condon St",
    "sg:city":"Bendigo",
    "sg:classifiers":[
        {
            "category":"Arena",
            "subcategory":"Sports Club",
            "type":"Entertainment"
        }
    ],
    "sg:phone":"+61 3 5443 1426",
    "sg:postcode":"3550",
    "sg:province":"VIC",
    "sg:tags":[
        "defence",
        "supply",
        "self",
        "instruction",
        "martial art"
    ],
    "wof:name":"Bendigo Self Defence",
    "wof:placetype":"venue"
},
  "geometry": {"coordinates":[144.29179382300001,-36.7694320679],"type":"Point"}
}