{
  "type": "Feature",
  "properties": {
    "iso:country":"AU",
    "sg:address":"121 Wright St",
    "sg:city":"Adelaide",
    "sg:classifiers":[
        {
            "category":"Social Services",
            "subcategory":"Retirement Home",
            "type":"Services"
        }
    ],
    "sg:phone":"+61 8 8212 9733",
    "sg:postcode":"5000",
    "sg:province":"SA",
    "sg:tags":[
        "environmental",
        "consultant",
        "pollution"
    ],
    "wof:name":"Ecosol Pty Ltd",
    "wof:placetype":"venue"
},
  "geometry": {"coordinates":[138.595703125,-34.9318695068],"type":"Point"}
}