{
  "type": "Feature",
  "properties": {
    "addr:full":"14 Norton St Leichhardt NSW 2040",
    "addr:housenumber":"14",
    "addr:postcode":"2040",
    "addr:street":"Norton St",
    "iso:country":"AU",
    "sg:address":"14 Norton St",
    "sg:city":"Leichhardt",
    "sg:classifiers":[
        {
            "category":"Health Services",
            "subcategory":"Health Practitioner",
            "type":"Services"
        }
    ],
    "sg:phone":"+61 2 9560 0061",
    "sg:postcode":"2040",
    "sg:province":"NSW",
    "sg:tags":[
        "physiotherapist"
    ],
    "sg:website":"http://www.arphysio4all.com",
    "wof:name":"Leichhardt Physiotherapy Clinic",
    "wof:placetype":"venue"
},
  "geometry": {"coordinates":[151.15739400000001,-33.887421],"type":"Point"}
}