{
  "type": "Feature",
  "properties": {
    "iso:country":"AU",
    "sg:address":"GPO Box 2728",
    "sg:city":"Brisbane",
    "sg:classifiers":[
        {
            "category":"Professional",
            "type":"Services"
        }
    ],
    "sg:phone":"+61 417 714 403",
    "sg:postcode":"4001",
    "sg:province":"QLD",
    "sg:tags":[
        "courier"
    ],
    "wof:name":"Docexpress Pushbike Couriers",
    "wof:placetype":"venue"
},
  "geometry": {"coordinates":[152.88861084000001,-27.5975933075],"type":"Point"}
}