{
  "type": "Feature",
  "properties": {
    "iso:country":"AU",
    "sg:address":"7 Govett St",
    "sg:city":"Randwick",
    "sg:classifiers":[
        {
            "category":"Retail",
            "subcategory":"Repair Shop",
            "type":"Services"
        }
    ],
    "sg:phone":"+61 2 9398 9689",
    "sg:postcode":"2031",
    "sg:province":"NSW",
    "sg:tags":[
        "upholsterer"
    ],
    "wof:name":"Budget Chair Covers",
    "wof:placetype":"venue"
},
  "geometry": {"coordinates":[151.23692321799999,-33.9051895142],"type":"Point"}
}