{
  "type": "Feature",
  "properties": {
    "iso:country":"AU",
    "sg:address":"58 Pinewood Drv",
    "sg:city":"Mt Waverley",
    "sg:classifiers":[
        {
            "category":"Health Services",
            "subcategory":"Doctor",
            "type":"Services"
        }
    ],
    "sg:phone":"+61 3 9802 8000",
    "sg:postcode":"3149",
    "sg:province":"VIC",
    "sg:tags":[
        "medical",
        "practitioner"
    ],
    "wof:name":"Cunneen Alan",
    "wof:placetype":"venue"
},
  "geometry": {"coordinates":[145.14457702600001,-37.8902435303],"type":"Point"}
}