{
  "type": "Feature",
  "properties": {
    "iso:country":"AU",
    "sg:address":"19 Market St",
    "sg:city":"Goulburn",
    "sg:classifiers":[
        {
            "category":"Retail",
            "subcategory":"Event Space",
            "type":"Services"
        }
    ],
    "sg:phone":"+61 2 4821 2043",
    "sg:postcode":"2580",
    "sg:province":"NSW",
    "sg:tags":[
        "venue",
        "reception",
        "wedding"
    ],
    "wof:name":"Goulburn Club",
    "wof:placetype":"venue"
},
  "geometry": {"coordinates":[149.72067260700001,-34.754573822],"type":"Point"}
}