{
  "type": "Feature",
  "properties": {
    "addr:full":"Sutton Rd Maryborough VIC 3465",
    "addr:postcode":"3465",
    "addr:street":"Sutton Rd",
    "iso:country":"AU",
    "sg:address":"Sutton Rd",
    "sg:city":"Maryborough",
    "sg:classifiers":[
        {
            "category":"Building & Trades",
            "subcategory":"Construction",
            "type":"Services"
        }
    ],
    "sg:phone":"+61 3 5460 4434",
    "sg:postcode":"3465",
    "sg:province":"VIC",
    "sg:tags":[
        "fitting",
        "line",
        "electric",
        "power"
    ],
    "wof:name":"Central Power Pty Ltd",
    "wof:placetype":"venue"
},
  "geometry": {"coordinates":[143.74508667000001,-37.0493431091],"type":"Point"}
}