{
  "type": "Feature",
  "properties": {
    "addr:full":"15 Wood Ave Brompton SA 5007",
    "addr:housenumber":"15",
    "addr:postcode":"5007",
    "addr:street":"Wood Ave",
    "iso:country":"AU",
    "sg:address":"15 Wood Ave",
    "sg:city":"Brompton",
    "sg:classifiers":[
        {
            "category":"Retail",
            "subcategory":"Event Space",
            "type":"Services"
        }
    ],
    "sg:phone":"+61 8 8346 4099",
    "sg:postcode":"5007",
    "sg:province":"SA",
    "sg:tags":[
        "venue",
        "reception",
        "wedding"
    ],
    "wof:name":"Croatian Function Centre",
    "wof:placetype":"venue"
},
  "geometry": {"coordinates":[138.56950378400001,-34.8991584778],"type":"Point"}
}