{
  "type": "Feature",
  "properties": {
    "addr:full":"1 Creighton Crt Alexandra VIC 3714",
    "addr:housenumber":"1",
    "addr:postcode":"3714",
    "addr:street":"Creighton Crt",
    "iso:country":"AU",
    "sg:address":"1 Creighton Crt",
    "sg:city":"Alexandra",
    "sg:classifiers":[
        {
            "category":"Building & Trades",
            "subcategory":"Cleaning & Sanitation",
            "type":"Services"
        }
    ],
    "sg:phone":"+61 3 5772 2316",
    "sg:postcode":"3714",
    "sg:province":"VIC",
    "sg:tags":[
        "sweep",
        "chimney"
    ],
    "wof:name":"Alexandra Chimney Sweep",
    "wof:placetype":"venue"
},
  "geometry": {"coordinates":[145.70585632300001,-37.1986045837],"type":"Point"}
}