{
  "type": "Feature",
  "properties": {
    "iso:country":"AU",
    "sg:address":"197 Dalgety Rd",
    "sg:city":"Middle Swan",
    "sg:classifiers":[
        {
            "category":"Utilities",
            "subcategory":"Electric",
            "type":"Services"
        }
    ],
    "sg:phone":"+61 8 9274 5370",
    "sg:postcode":"6056",
    "sg:province":"WA",
    "sg:tags":[
        "electrical",
        "contractor"
    ],
    "wof:name":"Swanside Electrical",
    "wof:placetype":"venue"
},
  "geometry": {"coordinates":[116.04473877,-31.8496932983],"type":"Point"}
}