{
  "type": "Feature",
  "properties": {
    "addr:full":"12 / 21 Myrtle St Botany NSW 2019",
    "addr:housenumber":"12 / 21",
    "addr:postcode":"2019",
    "addr:street":"Myrtle St",
    "iso:country":"AU",
    "sg:address":"12 / 21 Myrtle St",
    "sg:city":"Botany",
    "sg:classifiers":[
        {
            "category":"Organizations",
            "subcategory":"Professional Association",
            "type":"Services"
        }
    ],
    "sg:phone":"+61 2 9666 3044",
    "sg:postcode":"2019",
    "sg:province":"NSW",
    "sg:tags":[
        "organisation",
        "business"
    ],
    "wof:name":"Business World Corporate Club",
    "wof:placetype":"venue"
},
  "geometry": {"coordinates":[151.20463562,-33.9403610229],"type":"Point"}
}