{
  "type": "Feature",
  "properties": {
    "iso:country":"AU",
    "sg:address":"6 Bombay Crt",
    "sg:city":"Strathpine",
    "sg:classifiers":[
        {
            "category":"Utilities",
            "subcategory":"Telephone",
            "type":"Services"
        }
    ],
    "sg:phone":"+61 7 3205 4751",
    "sg:postcode":"4500",
    "sg:province":"QLD",
    "sg:tags":[
        "installation",
        "system",
        "maintenance"
    ],
    "sg:website":"http://www.devtel.com.au",
    "wof:name":"Devtel Communications",
    "wof:placetype":"venue"
},
  "geometry": {"coordinates":[152.9740448,-27.2995872498],"type":"Point"}
}