{
  "type": "Feature",
  "properties": {
    "addr:full":"32-42 Ivy St Killarney QLD 4373",
    "addr:housenumber":"32-42",
    "addr:postcode":"4373",
    "addr:street":"Ivy St",
    "iso:country":"AU",
    "sg:address":"32-42 Ivy St",
    "sg:city":"Killarney",
    "sg:classifiers":[
        {
            "category":"Banks & Credit Unions",
            "subcategory":"Bank",
            "type":"Services"
        }
    ],
    "sg:phone":"+61 13 20 32",
    "sg:postcode":"4373",
    "sg:province":"QLD",
    "wof:name":"Westpac",
    "wof:placetype":"venue"
},
  "geometry": {"coordinates":[152.29830932600001,-28.332572937],"type":"Point"}
}