{
  "type": "Feature",
  "properties": {
    "addr:full":"252 St.Georges Rd Fitzroy North VIC 3068",
    "addr:housenumber":"252",
    "addr:postcode":"3068",
    "addr:street":"St.Georges Rd",
    "iso:country":"AU",
    "sg:address":"252 St.Georges Rd",
    "sg:city":"Fitzroy North",
    "sg:classifiers":[
        {
            "category":"Real Estate",
            "subcategory":"Real Estate Agent",
            "type":"Services"
        }
    ],
    "sg:phone":"+61 3 9489 9888",
    "sg:postcode":"3068",
    "sg:province":"VIC",
    "wof:name":"Chambers Real Estate (Vic) Pty Ltd",
    "wof:placetype":"venue"
},
  "geometry": {"coordinates":[144.984176636,-37.7831420898],"type":"Point"}
}