{
  "type": "Feature",
  "properties": {
    "iso:country":"AU",
    "sg:address":"114 Denham St",
    "sg:city":"Rockhampton",
    "sg:classifiers":[
        {
            "category":"Health Services",
            "subcategory":"Doctor",
            "type":"Services"
        }
    ],
    "sg:phone":"+61 7 4927 6388",
    "sg:postcode":"4700",
    "sg:province":"QLD",
    "sg:tags":[
        "medical",
        "practitioner"
    ],
    "wof:name":"Galley R L",
    "wof:placetype":"venue"
},
  "geometry": {"coordinates":[150.49847412099999,-23.3877182007],"type":"Point"}
}