{
  "type": "Feature",
  "properties": {
    "iso:country":"AU",
    "sg:address":"13 Pitts Rd",
    "sg:city":"Portland",
    "sg:classifiers":[
        {
            "category":"Building & Trades",
            "subcategory":"Construction",
            "type":"Services"
        }
    ],
    "sg:phone":"+61 3 5523 3281",
    "sg:postcode":"3305",
    "sg:province":"VIC",
    "sg:tags":[
        "contractor"
    ],
    "wof:name":"Edwards G F & C H",
    "wof:placetype":"venue"
},
  "geometry": {"coordinates":[141.57270813,-38.3380622864],"type":"Point"}
}