{
  "type": "Feature",
  "properties": {
    "addr:full":"180 Pacific Hwy Hornsby NSW 2077",
    "addr:housenumber":"180",
    "addr:postcode":"2077",
    "addr:street":"Pacific Hwy",
    "iso:country":"AU",
    "sg:address":"180 Pacific Hwy",
    "sg:city":"Hornsby",
    "sg:classifiers":[
        {
            "category":"Retail",
            "subcategory":"Funeral Services",
            "type":"Services"
        }
    ],
    "sg:phone":"+61 2 9477 1514",
    "sg:postcode":"2077",
    "sg:province":"NSW",
    "sg:tags":[
        "cremation"
    ],
    "wof:name":"Allan Walsh-Hornsby",
    "wof:placetype":"venue"
},
  "geometry": {"coordinates":[151.09901428200001,-33.7068252563],"type":"Point"}
}