{
  "type": "Feature",
  "properties": {
    "addr:full":"52a Marion St Harris Park NSW 2150",
    "addr:housenumber":"52a",
    "addr:postcode":"2150",
    "addr:street":"Marion St",
    "iso:country":"AU",
    "sg:address":"52a Marion St",
    "sg:city":"Harris Park",
    "sg:classifiers":[
        {
            "category":"Professional",
            "subcategory":"Management & Consulting",
            "type":"Services"
        }
    ],
    "sg:phone":"+61 2 9635 9450",
    "sg:postcode":"2150",
    "sg:province":"NSW",
    "sg:tags":[
        "consultant",
        "migration"
    ],
    "wof:name":"Anz Immigration Consultancy",
    "wof:placetype":"venue"
},
  "geometry": {"coordinates":[151.00880432100001,-33.8225402832],"type":"Point"}
}