{
  "type": "Feature",
  "properties": {
    "addr:full":"16 Birmingham St Mile End SA 5031",
    "addr:housenumber":"16",
    "addr:postcode":"5031",
    "addr:street":"Birmingham St",
    "iso:country":"AU",
    "sg:address":"16 Birmingham St",
    "sg:city":"Mile End",
    "sg:classifiers":[
        {
            "category":"Government",
            "subcategory":"Department Of Motor Vehicles",
            "type":"Public Place"
        }
    ],
    "sg:phone":"+61 8 8234 9344",
    "sg:postcode":"5031",
    "sg:province":"SA",
    "sg:tags":[
        "wholesaler",
        "mfrs",
        "accessory"
    ],
    "wof:name":"SA Auto Accessories Pty Ltd",
    "wof:placetype":"venue"
},
  "geometry": {"coordinates":[138.57145690900001,-34.9404220581],"type":"Point"}
}