{
  "type": "Feature",
  "properties": {
    "addr:full":"Unit 1A, 183 Macquarie Rd Warners Bay NSW 2282",
    "addr:housenumber":"unit 1a 183",
    "addr:postcode":"2282",
    "addr:street":"Macquarie Rd",
    "iso:country":"AU",
    "sg:address":"Unit 1A, 183 Macquarie Rd",
    "sg:city":"Warners Bay",
    "sg:classifiers":[
        {
            "category":"Retail",
            "subcategory":"Auto Repair",
            "type":"Services"
        }
    ],
    "sg:phone":"+61 2 4954 5303",
    "sg:postcode":"2282",
    "sg:province":"NSW",
    "sg:tags":[
        "repairer",
        "motor",
        "engineer"
    ],
    "wof:name":"Brakes At The Bay",
    "wof:placetype":"venue"
},
  "geometry": {"coordinates":[151.65289306599999,-32.9655456543],"type":"Point"}
}