{
  "type": "Feature",
  "properties": {
    "addr:full":"136 Charles St Launceston TAS 7250",
    "addr:housenumber":"136",
    "addr:postcode":"7250",
    "addr:street":"Charles St",
    "iso:country":"AU",
    "sg:address":"136 Charles St",
    "sg:city":"Launceston",
    "sg:classifiers":[
        {
            "category":"Fast Food",
            "type":"Food & Drink"
        }
    ],
    "sg:phone":"+61 3 6334 6331",
    "sg:postcode":"7250",
    "sg:province":"TAS",
    "sg:tags":[
        "away",
        "take"
    ],
    "wof:name":"Oz Pizza's",
    "wof:placetype":"venue"
},
  "geometry": {"coordinates":[147.13865661599999,-41.4395294189],"type":"Point"}
}