{
  "type": "Feature",
  "properties": {
    "addr:full":"1666 Old Cleveland Rd Chandler QLD 4155",
    "addr:housenumber":"1666",
    "addr:postcode":"4155",
    "addr:street":"Old Cleveland Rd",
    "iso:country":"AU",
    "sg:address":"1666 Old Cleveland Rd",
    "sg:city":"Chandler",
    "sg:classifiers":[
        {
            "category":"Building & Trades",
            "subcategory":"Construction",
            "type":"Services"
        }
    ],
    "sg:phone":"+61 7 3245 2111",
    "sg:postcode":"4155",
    "sg:province":"QLD",
    "sg:tags":[
        "pool",
        "swimming"
    ],
    "wof:name":"Majestic Pools & Landscapes Pty. Ltd.",
    "wof:placetype":"venue"
},
  "geometry": {"coordinates":[153.145950317,-27.5087413788],"type":"Point"}
}