{
  "type": "Feature",
  "properties": {
    "addr:full":"330 Carlisle St Balaclava VIC 3183",
    "addr:housenumber":"330",
    "addr:postcode":"3183",
    "addr:street":"Carlisle St",
    "iso:country":"AU",
    "sg:address":"330 Carlisle St",
    "sg:city":"Balaclava",
    "sg:classifiers":[
        {
            "category":"Food & Beverages",
            "subcategory":"Bakery",
            "type":"Retail Goods"
        }
    ],
    "sg:phone":"+61 3 9527 2198",
    "sg:postcode":"3183",
    "sg:province":"VIC",
    "sg:tags":[
        "baker"
    ],
    "wof:name":"Glick's Cakes & Bagels",
    "wof:placetype":"venue"
},
  "geometry": {"coordinates":[144.99610900900001,-37.8689231873],"type":"Point"}
}