{
  "type": "Feature",
  "properties": {
    "addr:full":"78 Mine Rd Korumburra VIC 3950",
    "addr:housenumber":"78",
    "addr:postcode":"3950",
    "addr:street":"Mine Rd",
    "iso:country":"AU",
    "sg:address":"78 Mine Rd",
    "sg:city":"Korumburra",
    "sg:classifiers":[
        {
            "category":"Retail",
            "subcategory":"Driving School",
            "type":"Services"
        }
    ],
    "sg:phone":"+61 417 383 336",
    "sg:postcode":"3950",
    "sg:province":"VIC",
    "wof:name":"Korumburra Driving School",
    "wof:placetype":"venue"
},
  "geometry": {"coordinates":[145.832763672,-38.4398384094],"type":"Point"}
}