{
  "type": "Feature",
  "properties": {
    "addr:full":"129 Marshalltown Rd Grovedale VIC 3216",
    "addr:housenumber":"129",
    "addr:postcode":"3216",
    "addr:street":"Marshalltown Rd",
    "iso:country":"AU",
    "sg:address":"129 Marshalltown Rd",
    "sg:city":"Grovedale",
    "sg:classifiers":[
        {
            "category":"Retail",
            "subcategory":"Repair Shop",
            "type":"Services"
        }
    ],
    "sg:phone":"+61 3 5241 6333",
    "sg:postcode":"3216",
    "sg:province":"VIC",
    "sg:tags":[
        "restorer",
        "repairer",
        "carpet"
    ],
    "wof:name":"Steamatic Geelong",
    "wof:placetype":"venue"
},
  "geometry": {"coordinates":[144.347290039,-38.1960639954],"type":"Point"}
}