{
  "type": "Feature",
  "properties": {
    "addr:full":"1a Manor St Brighton VIC 3186",
    "addr:housenumber":"1a",
    "addr:postcode":"3186",
    "addr:street":"Manor St",
    "iso:country":"AU",
    "sg:address":"1a Manor St",
    "sg:city":"Brighton",
    "sg:classifiers":[
        {
            "category":"Shopping",
            "subcategory":"Bicycles & Sporting Goods",
            "type":"Retail Goods"
        }
    ],
    "sg:phone":"+61 3 9592 2094",
    "sg:postcode":"3186",
    "sg:province":"VIC",
    "sg:tags":[
        "chemical",
        "equipment",
        "pool",
        "swimming"
    ],
    "wof:name":"Putt's Pool Services Pty Ltd",
    "wof:placetype":"venue"
},
  "geometry": {"coordinates":[144.98971557600001,-37.9188957214],"type":"Point"}
}