{
  "type": "Feature",
  "properties": {
    "addr:full":"4 Sandergrove Rd Strathalbyn SA 5255",
    "addr:housenumber":"4",
    "addr:postcode":"5255",
    "addr:street":"Sandergrove Rd",
    "iso:country":"AU",
    "sg:address":"4 Sandergrove Rd",
    "sg:city":"Strathalbyn",
    "sg:classifiers":[
        {
            "category":"Building & Trades",
            "subcategory":"Construction",
            "type":"Services"
        }
    ],
    "sg:phone":"+61 8 8536 2185",
    "sg:postcode":"5255",
    "sg:province":"SA",
    "sg:tags":[
        "contractor"
    ],
    "wof:name":"L. J. Constructions",
    "wof:placetype":"venue"
},
  "geometry": {"coordinates":[138.88975524899999,-35.2618255615],"type":"Point"}
}