{
  "type": "Feature",
  "properties": {
    "iso:country":"AU",
    "sg:address":"5 Darghan St",
    "sg:city":"Glebe",
    "sg:classifiers":[
        {
            "category":"Professional",
            "subcategory":"Computer Services",
            "type":"Services"
        }
    ],
    "sg:phone":"+61 403 309 481",
    "sg:postcode":"2037",
    "sg:province":"NSW",
    "sg:tags":[
        "training"
    ],
    "wof:name":"Computer Training at Your Home",
    "wof:placetype":"venue"
},
  "geometry": {"coordinates":[151.191162109,-33.878692627],"type":"Point"}
}