{
  "type": "Feature",
  "properties": {
    "addr:full":"140 Liebig St Warrnambool VIC 3280",
    "addr:housenumber":"140",
    "addr:postcode":"3280",
    "addr:street":"Liebig St",
    "iso:country":"AU",
    "sg:address":"140 Liebig St",
    "sg:city":"Warrnambool",
    "sg:classifiers":[
        {
            "category":"Shopping",
            "subcategory":"Clothing, Apparel, & Fashions",
            "type":"Retail Goods"
        }
    ],
    "sg:phone":"+61 3 5561 4782",
    "sg:postcode":"3280",
    "sg:province":"VIC",
    "sg:tags":[
        "lady",
        "wear"
    ],
    "wof:name":"Carisma Boutique",
    "wof:placetype":"venue"
},
  "geometry": {"coordinates":[142.48452758799999,-38.3827285767],"type":"Point"}
}