{
  "type": "Feature",
  "properties": {
    "addr:full":"33 - 35 Progress Rd Burpengary QLD 4505",
    "addr:housenumber":"35",
    "addr:postcode":"4505",
    "addr:street":"Progress Rd",
    "iso:country":"AU",
    "sg:address":"33 - 35 Progress Rd",
    "sg:city":"Burpengary",
    "sg:classifiers":[
        {
            "category":"Professional",
            "subcategory":"Accounting & Tax Preparation",
            "type":"Services"
        }
    ],
    "sg:phone":"+61 7 3888 1477",
    "sg:postcode":"4505",
    "sg:province":"QLD",
    "sg:tags":[
        "accountant",
        "auditor"
    ],
    "sg:website":"http://www.thomsonaccounting.com.au",
    "wof:name":"Thomson Munro Chartered Accountants",
    "wof:placetype":"venue"
},
  "geometry": {"coordinates":[152.977096558,-27.1561641693],"type":"Point"}
}