{
  "type": "Feature",
  "properties": {
    "iso:country":"AU",
    "sg:address":"Lavarack Rd",
    "sg:city":"Bray Park",
    "sg:classifiers":[
        {
            "category":"Education",
            "subcategory":"School",
            "type":"Public Place"
        }
    ],
    "sg:phone":"+61 7 3881 6666",
    "sg:postcode":"4500",
    "sg:province":"QLD",
    "sg:tags":[
        "state",
        "except",
        "nsw"
    ],
    "wof:name":"Bray Park High",
    "wof:placetype":"venue"
},
  "geometry": {"coordinates":[152.965133667,-27.297618866],"type":"Point"}
}