{
  "type": "Feature",
  "properties": {
    "addr:full":"15 Georges River Rd Lansvale NSW 2166",
    "addr:housenumber":"15",
    "addr:postcode":"2166",
    "addr:street":"Georges River Rd",
    "iso:country":"AU",
    "sg:address":"15 Georges River Rd",
    "sg:city":"Lansvale",
    "sg:classifiers":[
        {
            "category":"Education",
            "subcategory":"Kindergarten",
            "type":"Public Place"
        }
    ],
    "sg:phone":"+61 2 9727 9029",
    "sg:postcode":"2166",
    "sg:province":"NSW",
    "sg:tags":[
        "pre-schools"
    ],
    "wof:name":"Lansvale Pre-School Kindergarten",
    "wof:placetype":"venue"
},
  "geometry": {"coordinates":[150.959884644,-33.898223877],"type":"Point"}
}