{
  "type": "Feature",
  "properties": {
    "addr:full":"164 Marine Pde Lakes Entrance VIC 3909",
    "addr:housenumber":"164",
    "addr:postcode":"3909",
    "addr:street":"Marine Pde",
    "iso:country":"AU",
    "sg:address":"164 Marine Pde",
    "sg:city":"Lakes Entrance",
    "sg:classifiers":[
        {
            "category":"Travel",
            "subcategory":"Hotels & Motels",
            "type":"Entertainment"
        }
    ],
    "sg:phone":"+61 3 5155 1811",
    "sg:postcode":"3909",
    "sg:province":"VIC",
    "wof:name":"Lakeside Motel",
    "wof:placetype":"venue"
},
  "geometry": {"coordinates":[147.98162841800001,-37.8796615601],"type":"Point"}
}