{
  "type": "Feature",
  "properties": {
    "addr:full":"Lvl 10 St Kilda Rd Towers 1 Queens Rd Melbourne VIC 3004",
    "addr:housenumber":"1",
    "addr:postcode":"3004",
    "addr:street":"St Kilda Rd Towers;Queens Rd",
    "iso:country":"AU",
    "sg:address":"Lvl 10 St Kilda Rd Towers 1 Queens Rd",
    "sg:city":"Melbourne",
    "sg:classifiers":[
        {
            "category":"Professional",
            "subcategory":"Employment Agencies",
            "type":"Services"
        }
    ],
    "sg:phone":"+61 3 9863 8887",
    "sg:postcode":"3004",
    "sg:province":"VIC",
    "wof:name":"Marker Consulting",
    "wof:placetype":"venue"
},
  "geometry": {"coordinates":[144.97369384800001,-37.8357315063],"type":"Point"}
}