{
  "type": "Feature",
  "properties": {
    "iso:country":"AU",
    "sg:address":"Alexandra Hills Shopng Cntr Cnr Finucane Rd & Cambridge Drv",
    "sg:city":"Alexandra Hills",
    "sg:classifiers":[
        {
            "category":"Health Services",
            "subcategory":"Dentist",
            "type":"Services"
        }
    ],
    "sg:phone":"+61 7 3824 4211",
    "sg:postcode":"4161",
    "sg:province":"QLD",
    "wof:name":"Leong Debbie",
    "wof:placetype":"venue"
},
  "geometry": {"coordinates":[153.22972106899999,-27.5240459442],"type":"Point"}
}