{
  "type": "Feature",
  "properties": {
    "addr:full":"Shop 18, 119 McLachlan St Fortitude Valley QLD 4006",
    "addr:housenumber":"shop 18",
    "addr:postcode":"119;4006",
    "addr:street":"Mclachlan St",
    "iso:country":"AU",
    "sg:address":"Shop 18, 119 McLachlan St",
    "sg:city":"Fortitude Valley",
    "sg:classifiers":[
        {
            "category":"Professional",
            "subcategory":"Printing & Photocopies",
            "type":"Services"
        }
    ],
    "sg:phone":"+61 7 3852 2440",
    "sg:postcode":"4006",
    "sg:province":"QLD",
    "sg:tags":[
        "photocopying"
    ],
    "wof:name":"Worldwide Online Printing",
    "wof:placetype":"venue"
},
  "geometry": {"coordinates":[153.03880310100001,-27.4561862946],"type":"Point"}
}