{
  "type": "Feature",
  "properties": {
    "addr:full":"Lot 161, Railway Crs Lisarow NSW 2250",
    "addr:housenumber":"161",
    "addr:postcode":"2250",
    "addr:street":"Railway Crs",
    "iso:country":"AU",
    "sg:address":"Lot 161, Railway Crs",
    "sg:city":"Lisarow",
    "sg:classifiers":[
        {
            "category":"Social Services",
            "subcategory":"Retirement Home",
            "type":"Services"
        }
    ],
    "sg:phone":"+61 2 4329 3244",
    "sg:postcode":"2250",
    "sg:province":"NSW",
    "sg:tags":[
        "environmental",
        "consultant",
        "pollution"
    ],
    "wof:name":"Aust-Pol International Pty Ltd",
    "wof:placetype":"venue"
},
  "geometry": {"coordinates":[151.306030273,-33.4976272583],"type":"Point"}
}