{
  "type": "Feature",
  "properties": {
    "addr:full":"201 St Albans Rd Breakwater VIC 3219",
    "addr:housenumber":"201",
    "addr:postcode":"3219",
    "addr:street":"St Albans Rd",
    "iso:country":"AU",
    "sg:address":"201 St Albans Rd",
    "sg:city":"Breakwater",
    "sg:classifiers":[
        {
            "category":"Education",
            "subcategory":"Kindergarten",
            "type":"Public Place"
        }
    ],
    "sg:phone":"+61 3 5221 2705",
    "sg:postcode":"3219",
    "sg:province":"VIC",
    "sg:tags":[
        "pre-schools"
    ],
    "wof:name":"Breakwater Pre-School Centre",
    "wof:placetype":"venue"
},
  "geometry": {"coordinates":[144.37953185999999,-38.1758003235],"type":"Point"}
}