{
  "type": "Feature",
  "properties": {
    "addr:full":"81 Liverpool St Scone NSW 2337",
    "addr:housenumber":"81",
    "addr:postcode":"2337",
    "addr:street":"Liverpool St",
    "iso:country":"AU",
    "sg:address":"81 Liverpool St",
    "sg:city":"Scone",
    "sg:classifiers":[
        {
            "category":"Building & Trades",
            "subcategory":"Cleaning & Sanitation",
            "type":"Services"
        }
    ],
    "sg:phone":"+61 408 492 274",
    "sg:postcode":"2337",
    "sg:province":"NSW",
    "sg:tags":[
        "cleaner",
        "repairer",
        "roof"
    ],
    "wof:name":"A & S Ball",
    "wof:placetype":"venue"
},
  "geometry": {"coordinates":[150.86964416500001,-32.0512619019],"type":"Point"}
}