{
  "type": "Feature",
  "properties": {
    "addr:full":"3 George Rd Salamander Bay NSW 2317",
    "addr:housenumber":"3",
    "addr:postcode":"2317",
    "addr:street":"George Rd",
    "iso:country":"AU",
    "sg:address":"3 George Rd",
    "sg:city":"Salamander Bay",
    "sg:classifiers":[
        {
            "category":"Retail",
            "subcategory":"Auto Repair",
            "type":"Services"
        }
    ],
    "sg:phone":"+61 2 4982 0009",
    "sg:postcode":"2317",
    "sg:province":"NSW",
    "sg:tags":[
        "repairer",
        "motor",
        "engineer"
    ],
    "wof:name":"J L Mechanical Services",
    "wof:placetype":"venue"
},
  "geometry": {"coordinates":[152.07498200000001,-32.726547],"type":"Point"}
}