{
  "type": "Feature",
  "properties": {
    "iso:country":"AU",
    "sg:address":"74 Pitt St",
    "sg:city":"Redfern",
    "sg:classifiers":[
        {
            "category":"Deli",
            "type":"Food & Drink"
        }
    ],
    "sg:phone":"+61 2 9690 1166",
    "sg:postcode":"2016",
    "sg:province":"NSW",
    "sg:tags":[
        "delicatessen"
    ],
    "wof:name":"Quirk's Groceries",
    "wof:placetype":"venue"
},
  "geometry": {"coordinates":[151.20390319800001,-33.8919906616],"type":"Point"}
}