{
  "type": "Feature",
  "properties": {
    "addr:full":"65 Kelletts Rd Rowville VIC 3178",
    "addr:housenumber":"65",
    "addr:postcode":"3178",
    "addr:street":"Kelletts Rd",
    "iso:country":"AU",
    "sg:address":"65 Kelletts Rd",
    "sg:city":"Rowville",
    "sg:classifiers":[
        {
            "category":"Autos & Motor Vehicles",
            "subcategory":"Auto Supplies",
            "type":"Retail Goods"
        }
    ],
    "sg:phone":"+61 3 9764 0572",
    "sg:postcode":"3178",
    "sg:province":"VIC",
    "sg:tags":[
        "tyre"
    ],
    "wof:name":"Traction Tyre & Suspension Centre",
    "wof:placetype":"venue"
},
  "geometry": {"coordinates":[145.24270629899999,-37.9110374451],"type":"Point"}
}