{
  "type": "Feature",
  "properties": {
    "addr:full":"615 Sydney Rd Brunswick VIC 3055",
    "addr:housenumber":"615",
    "addr:postcode":"3055",
    "addr:street":"Sydney Rd",
    "iso:country":"AU",
    "sg:address":"615 Sydney Rd",
    "sg:city":"Brunswick",
    "sg:classifiers":[
        {
            "category":"Travel",
            "subcategory":"Hotels & Motels",
            "type":"Entertainment"
        }
    ],
    "sg:phone":"+61 3 9380 1804",
    "sg:postcode":"3055",
    "sg:province":"VIC",
    "sg:tags":[
        "pub"
    ],
    "wof:name":"Couthouse Hotel Brunswick",
    "wof:placetype":"venue"
},
  "geometry": {"coordinates":[144.96290588400001,-37.7631607056],"type":"Point"}
}