{
  "type": "Feature",
  "properties": {
    "addr:full":"216 Days Rd Ferryden Park SA 5010",
    "addr:housenumber":"216",
    "addr:postcode":"5010",
    "addr:street":"Days Rd",
    "iso:country":"AU",
    "sg:address":"216 Days Rd",
    "sg:city":"Ferryden Park",
    "sg:classifiers":[
        {
            "category":"Professional",
            "subcategory":"Detective & Security Services",
            "type":"Services"
        }
    ],
    "sg:phone":"+61 8 8244 6889",
    "sg:postcode":"5010",
    "sg:province":"SA",
    "sg:tags":[
        "consultant",
        "system"
    ],
    "wof:name":"Ip Surveillance Solutions",
    "wof:placetype":"venue"
},
  "geometry": {"coordinates":[138.565475464,-34.8658943176],"type":"Point"}
}