{
  "type": "Feature",
  "properties": {
    "addr:full":"20 Leanne Crs Lawnton QLD 4501",
    "addr:housenumber":"20",
    "addr:postcode":"4501",
    "addr:street":"Leanne Crs",
    "iso:country":"AU",
    "sg:address":"20 Leanne Crs",
    "sg:city":"Lawnton",
    "sg:classifiers":[
        {
            "category":"Shopping",
            "type":"Retail Goods"
        }
    ],
    "sg:phone":"+61 7 3205 4675",
    "sg:postcode":"4501",
    "sg:province":"QLD",
    "sg:tags":[
        "produce",
        "grain"
    ],
    "wof:name":"AGS Produce",
    "wof:placetype":"venue"
},
  "geometry": {"coordinates":[152.98260498100001,-27.2805633545],"type":"Point"}
}