{
  "type": "Feature",
  "properties": {
    "iso:country":"AU",
    "sg:address":"123 Marine Pde",
    "sg:city":"San Remo",
    "sg:classifiers":[
        {
            "category":"Health Services",
            "subcategory":"Medical Lab",
            "type":"Services"
        }
    ],
    "sg:phone":"+61 3 5678 5787",
    "sg:postcode":"3925",
    "sg:province":"VIC",
    "sg:tags":[
        "laboratory",
        "pathology"
    ],
    "wof:name":"Gippsland Pathology",
    "wof:placetype":"venue"
},
  "geometry": {"coordinates":[145.369506836,-38.5210571289],"type":"Point"}
}