{
  "type": "Feature",
  "properties": {
    "addr:full":"Cnr Browns Rd & Princes Hwy Noble Park VIC 3174",
    "addr:postcode":"3174",
    "addr:street":"Cnr Browns Rd & Princes Hwy",
    "iso:country":"AU",
    "sg:address":"Cnr Browns Rd & Princes Hwy",
    "sg:city":"Noble Park",
    "sg:classifiers":[
        {
            "category":"Fast Food",
            "type":"Food & Drink"
        }
    ],
    "sg:phone":"+61 3 9790 6466",
    "sg:postcode":"3174",
    "sg:province":"VIC",
    "sg:tags":[
        "away",
        "take"
    ],
    "wof:name":"Subway Sandwiches & Salads",
    "wof:placetype":"venue"
},
  "geometry": {"coordinates":[145.17927551299999,-37.9537582397],"type":"Point"}
}