{
  "type": "Feature",
  "properties": {
    "addr:full":"Kings Wharf Forster Street Invermay TAS 7248",
    "addr:postcode":"7248",
    "addr:street":"Forster Street",
    "iso:country":"AU",
    "sg:address":"Kings Wharf Forster Street",
    "sg:city":"Invermay",
    "sg:classifiers":[
        {
            "category":"Real Estate",
            "subcategory":"Architect",
            "type":"Services"
        }
    ],
    "sg:phone":"+61 3 6334 0222",
    "sg:postcode":"7248",
    "sg:province":"TAS",
    "sg:tags":[
        "builder",
        "repairer",
        "ship"
    ],
    "sg:website":"http://www.shiprepair.com.au",
    "wof:name":"Southern Marine Shiplift Pty Ltd",
    "wof:placetype":"venue"
},
  "geometry": {"coordinates":[147.13824462900001,-41.4235076904],"type":"Point"}
}