{
  "type": "Feature",
  "properties": {
    "addr:full":"5 Cowrie Drv Seaford Rise SA 5169",
    "addr:housenumber":"5",
    "addr:postcode":"5169",
    "addr:street":"Cowrie Drv Seaford",
    "iso:country":"AU",
    "sg:address":"5 Cowrie Drv",
    "sg:city":"Seaford Rise",
    "sg:classifiers":[
        {
            "category":"Utilities",
            "type":"Services"
        }
    ],
    "sg:phone":"+61 8 8327 0166",
    "sg:postcode":"5169",
    "sg:province":"SA",
    "sg:tags":[
        "refrigeration",
        "industrial",
        "commercial",
        "retail"
    ],
    "wof:name":"Fleurieu Refrigeration",
    "wof:placetype":"venue"
},
  "geometry": {"coordinates":[138.483688355,-35.1938438416],"type":"Point"}
}