{
  "type": "Feature",
  "properties": {
    "iso:country":"AU",
    "sg:address":"Sherlocks Rd",
    "sg:city":"Pine Mountain",
    "sg:classifiers":[
        {
            "category":"Professional",
            "subcategory":"Art Services",
            "type":"Services"
        }
    ],
    "sg:phone":"+61 7 5464 3742",
    "sg:postcode":"4306",
    "sg:province":"QLD",
    "sg:tags":[
        "artist"
    ],
    "wof:name":"Alan Purnell",
    "wof:placetype":"venue"
},
  "geometry": {"coordinates":[152.71743774399999,-27.5587978363],"type":"Point"}
}