{
  "type": "Feature",
  "properties": {
    "iso:country":"AU",
    "sg:address":"Suite: 2/51-55 City Rd",
    "sg:city":"Southbank",
    "sg:classifiers":[
        {
            "category":"Health Services",
            "subcategory":"Optometrist",
            "type":"Services"
        }
    ],
    "sg:phone":"+61 3 9699 3288",
    "sg:postcode":"3006",
    "sg:province":"VIC",
    "wof:name":"Netlearn",
    "wof:placetype":"venue"
},
  "geometry": {"coordinates":[144.966033936,-37.8218841553],"type":"Point"}
}