{
  "type": "Feature",
  "properties": {
    "addr:full":"109 Tenth St Mildura VIC 3500",
    "addr:housenumber":"109",
    "addr:postcode":"3500",
    "addr:street":"Tenth St",
    "iso:country":"AU",
    "sg:address":"109 Tenth St",
    "sg:city":"Mildura",
    "sg:classifiers":[
        {
            "category":"Autos & Motor Vehicles",
            "subcategory":"Auto Supplies",
            "type":"Retail Goods"
        }
    ],
    "sg:phone":"+61 3 5023 5223",
    "sg:postcode":"3500",
    "sg:province":"VIC",
    "sg:tags":[
        "camper-trailers",
        "caravan",
        "equipment"
    ],
    "wof:name":"Currans Outback Campers",
    "wof:placetype":"venue"
},
  "geometry": {"coordinates":[142.16085815400001,-34.1896514893],"type":"Point"}
}