{
  "type": "Feature",
  "properties": {
    "addr:full":"89 Trangmar St Coleraine VIC 3315",
    "addr:housenumber":"89",
    "addr:postcode":"3315",
    "addr:street":"Trangmar St",
    "iso:country":"AU",
    "sg:address":"89 Trangmar St",
    "sg:city":"Coleraine",
    "sg:classifiers":[
        {
            "category":"Building & Trades",
            "subcategory":"Construction",
            "type":"Services"
        }
    ],
    "sg:phone":"+61 3 5575 2156",
    "sg:postcode":"3315",
    "sg:province":"VIC",
    "sg:tags":[
        "contractor"
    ],
    "wof:name":"James M H",
    "wof:placetype":"venue"
},
  "geometry": {"coordinates":[141.68971252399999,-37.6052970886],"type":"Point"}
}