{
  "type": "Feature",
  "properties": {
    "addr:full":"94 Berriman Drv Wangara WA 6065",
    "addr:housenumber":"94",
    "addr:postcode":"6065",
    "addr:street":"Berriman Drv",
    "iso:country":"AU",
    "sg:address":"94 Berriman Drv",
    "sg:city":"Wangara",
    "sg:classifiers":[
        {
            "category":"Shopping",
            "subcategory":"Crafts & Fabrics",
            "type":"Retail Goods"
        }
    ],
    "sg:phone":"+61 8 9309 2029",
    "sg:postcode":"6065",
    "sg:province":"WA",
    "sg:tags":[
        "adhesive"
    ],
    "wof:name":"Coloro",
    "wof:placetype":"venue"
},
  "geometry": {"coordinates":[115.82711792000001,-31.7915897369],"type":"Point"}
}