{
  "type": "Feature",
  "properties": {
    "addr:full":"1 St Peters St Glenelg East SA 5045",
    "addr:housenumber":"1",
    "addr:postcode":"5045",
    "addr:street":"St Peters St Glenelg East",
    "iso:country":"AU",
    "sg:address":"1 St Peters St",
    "sg:city":"Glenelg East",
    "sg:classifiers":[
        {
            "category":"Communications",
            "subcategory":"News Services",
            "type":"Services"
        }
    ],
    "sg:phone":"+61 8 8294 6042",
    "sg:postcode":"5045",
    "sg:province":"SA",
    "sg:tags":[
        "information",
        "tourist",
        "attractions"
    ],
    "wof:name":"Cultural Tourism Professionals",
    "wof:placetype":"venue"
},
  "geometry": {"coordinates":[138.52458200000001,-34.983604],"type":"Point"}
}