{
  "type": "Feature",
  "properties": {
    "addr:full":"21/ 217 Kororoit Creek Rd Williamstown VIC 3016",
    "addr:housenumber":"21 / 217",
    "addr:postcode":"3016",
    "addr:street":"Kororoit Creek Rd",
    "iso:country":"AU",
    "sg:address":"21/ 217 Kororoit Creek Rd",
    "sg:city":"Williamstown",
    "sg:classifiers":[
        {
            "category":"Taxi",
            "type":"Transportation"
        }
    ],
    "sg:phone":"+61 3 9399 9877",
    "sg:postcode":"3016",
    "sg:province":"VIC",
    "sg:tags":[
        "truck"
    ],
    "wof:name":"R B K Transport Management",
    "wof:placetype":"venue"
},
  "geometry": {"coordinates":[144.859771728,-37.8545379639],"type":"Point"}
}