{
  "type": "Feature",
  "properties": {
    "iso:country":"AU",
    "sg:address":"3 Storey St",
    "sg:city":"Whyalla Norrie",
    "sg:classifiers":[
        {
            "category":"Utilities",
            "subcategory":"Electric",
            "type":"Services"
        }
    ],
    "sg:phone":"+61 8 8644 2200",
    "sg:postcode":"5608",
    "sg:province":"SA",
    "sg:tags":[
        "electrical",
        "contractor"
    ],
    "wof:name":"Phillis Electrical Services",
    "wof:placetype":"venue"
},
  "geometry": {"coordinates":[137.549164,-33.036263],"type":"Point"}
}