{
  "type": "Feature",
  "properties": {
    "addr:full":"37 Mathews St Frenchs Forest NSW 2086",
    "addr:housenumber":"37",
    "addr:postcode":"2086",
    "addr:street":"Mathews St",
    "iso:country":"AU",
    "sg:address":"37 Mathews St",
    "sg:city":"Frenchs Forest",
    "sg:classifiers":[
        {
            "category":"Communications",
            "subcategory":"Film & Video Production",
            "type":"Services"
        }
    ],
    "sg:phone":"+61 2 9452 4057",
    "sg:postcode":"2086",
    "sg:province":"NSW",
    "sg:tags":[
        "cost",
        "estimator"
    ],
    "wof:name":"Quik-Est",
    "wof:placetype":"venue"
},
  "geometry": {"coordinates":[151.23475647000001,-33.7508201599],"type":"Point"}
}