{
  "type": "Feature",
  "properties": {
    "addr:full":"43 Snook St Clontarf QLD 4019",
    "addr:housenumber":"43",
    "addr:postcode":"4019",
    "addr:street":"Snook St",
    "iso:country":"AU",
    "sg:address":"43 Snook St",
    "sg:city":"Clontarf",
    "sg:classifiers":[
        {
            "category":"Manufacturing",
            "subcategory":"Tools & Machinery",
            "type":"Manufacturing & Wholesale Goods"
        }
    ],
    "sg:phone":"+61 7 3284 9322",
    "sg:postcode":"4019",
    "sg:province":"QLD",
    "wof:name":"Tampico Tools",
    "wof:placetype":"venue"
},
  "geometry": {"coordinates":[153.084274292,-27.2413253784],"type":"Point"}
}