{
  "type": "Feature",
  "properties": {
    "addr:full":"9 Church St Geeveston TAS 7116",
    "addr:housenumber":"9",
    "addr:postcode":"7116",
    "addr:street":"Church St",
    "iso:country":"AU",
    "sg:address":"9 Church St",
    "sg:city":"Geeveston",
    "sg:classifiers":[
        {
            "category":"Government",
            "subcategory":"Post Office",
            "type":"Public Place"
        }
    ],
    "sg:phone":"+61 3 6297 1102",
    "sg:postcode":"7116",
    "sg:province":"TAS",
    "sg:tags":[
        "postal"
    ],
    "wof:name":"Australia Post Offices",
    "wof:placetype":"venue"
},
  "geometry": {"coordinates":[146.926803589,-43.1641349792],"type":"Point"}
}