{
  "type": "Feature",
  "properties": {
    "addr:full":"7 Lackey Rd Moss Vale NSW 2577",
    "addr:housenumber":"7",
    "addr:postcode":"2577",
    "addr:street":"Lackey Rd",
    "iso:country":"AU",
    "sg:address":"7 Lackey Rd",
    "sg:city":"Moss Vale",
    "sg:classifiers":[
        {
            "category":"Building & Trades",
            "subcategory":"Pest Control",
            "type":"Services"
        }
    ],
    "sg:phone":"+61 2 4869 1441",
    "sg:postcode":"2577",
    "sg:province":"NSW",
    "sg:tags":[
        "technical",
        "consultant"
    ],
    "wof:name":"A & I Coatings",
    "wof:placetype":"venue"
},
  "geometry": {"coordinates":[150.37559509299999,-34.5391349792],"type":"Point"}
}