{
  "type": "Feature",
  "properties": {
    "addr:full":"80 City Rd Southbank VIC 3006",
    "addr:housenumber":"80",
    "addr:postcode":"3006",
    "addr:street":"City Rd",
    "iso:country":"AU",
    "sg:address":"80 City Rd",
    "sg:city":"Southbank",
    "sg:classifiers":[
        {
            "category":"Autos & Motor Vehicles",
            "subcategory":"Automobile Sales",
            "type":"Retail Goods"
        }
    ],
    "sg:phone":"+61 3 8866 3111",
    "sg:postcode":"3006",
    "sg:province":"VIC",
    "sg:tags":[
        "car",
        "new"
    ],
    "wof:name":"Trivett Classic Aston Martin",
    "wof:placetype":"venue"
},
  "geometry": {"coordinates":[144.965042114,-37.8220443726],"type":"Point"}
}