{
  "type": "Feature",
  "properties": {
    "addr:full":"Suite 222, 1 Katherine St Chatswood NSW 2067",
    "addr:housenumber":"1",
    "addr:postcode":"2067",
    "addr:street":"Katherine St",
    "iso:country":"AU",
    "sg:address":"Suite 222, 1 Katherine St",
    "sg:city":"Chatswood",
    "sg:classifiers":[
        {
            "category":"Health Services",
            "subcategory":"Medical Lab",
            "type":"Services"
        }
    ],
    "sg:phone":"+61 2 9419 8094",
    "sg:postcode":"2067",
    "sg:province":"NSW",
    "sg:tags":[
        "laboratory",
        "dental"
    ],
    "wof:name":"Shain Michael Orthodontic Laboratory",
    "wof:placetype":"venue"
},
  "geometry": {"coordinates":[151.17962646500001,-33.7977561951],"type":"Point"}
}