{
  "type": "Feature",
  "properties": {
    "addr:full":"2a/ 127 Greville St Prahran VIC 3181",
    "addr:housenumber":"2a / 127",
    "addr:postcode":"3181",
    "addr:street":"Greville St",
    "iso:country":"AU",
    "sg:address":"2a/ 127 Greville St",
    "sg:city":"Prahran",
    "sg:classifiers":[
        {
            "category":"Personal",
            "subcategory":"Barber",
            "type":"Services"
        }
    ],
    "sg:phone":"+61 3 9521 5324",
    "sg:postcode":"3181",
    "sg:province":"VIC",
    "wof:name":"Joe's Mens Haircutters",
    "wof:placetype":"venue"
},
  "geometry": {"coordinates":[144.99095153799999,-37.849067688],"type":"Point"}
}