{
  "type": "Feature",
  "properties": {
    "iso:country":"AU",
    "sg:address":"PO Box 5203",
    "sg:city":"Middle Park",
    "sg:classifiers":[
        {
            "category":"Professional",
            "subcategory":"Employment Agencies",
            "type":"Services"
        }
    ],
    "sg:phone":"+61 3 9682 2155",
    "sg:postcode":"3206",
    "sg:province":"VIC",
    "wof:name":"Creative Recruiting Pty Limited",
    "wof:placetype":"venue"
},
  "geometry": {"coordinates":[144.96163899999999,-37.849442],"type":"Point"}
}