{
  "type": "Feature",
  "properties": {
    "addr:full":"21 Queen Elizabeth Drv Dysart QLD 4745",
    "addr:housenumber":"21",
    "addr:postcode":"4745",
    "addr:street":"Queen Elizabeth Drv",
    "iso:country":"AU",
    "sg:address":"21 Queen Elizabeth Drv",
    "sg:city":"Dysart",
    "sg:classifiers":[
        {
            "category":"Organizations",
            "subcategory":"Community Association",
            "type":"Services"
        }
    ],
    "sg:phone":"+61 7 4958 2461",
    "sg:postcode":"4745",
    "sg:province":"QLD",
    "sg:tags":[
        "organisation",
        "family",
        "welfare"
    ],
    "wof:name":"Dysart Community Health & Support Centre",
    "wof:placetype":"venue"
},
  "geometry": {"coordinates":[148.34858700000001,-22.590931],"type":"Point"}
}