{
  "type": "Feature",
  "properties": {
    "addr:full":"158 Timor St Warrnambool VIC 3280",
    "addr:housenumber":"158",
    "addr:postcode":"3280",
    "addr:street":"Timor St",
    "iso:country":"AU",
    "sg:address":"158 Timor St",
    "sg:city":"Warrnambool",
    "sg:classifiers":[
        {
            "category":"Restaurant",
            "type":"Food & Drink"
        }
    ],
    "sg:phone":"+61 3 5562 0900",
    "sg:postcode":"3280",
    "sg:province":"VIC",
    "wof:name":"Balenas",
    "wof:placetype":"venue"
},
  "geometry": {"coordinates":[142.48220825199999,-38.3852272034],"type":"Point"}
}