{
  "type": "Feature",
  "properties": {
    "addr:full":"37 Activity Crs Molendinar QLD 4214",
    "addr:housenumber":"37",
    "addr:postcode":"4214",
    "addr:street":"Activity Crs",
    "iso:country":"AU",
    "sg:address":"37 Activity Crs",
    "sg:city":"Molendinar",
    "sg:classifiers":[
        {
            "category":"Professional",
            "subcategory":"Detective & Security Services",
            "type":"Services"
        }
    ],
    "sg:phone":"+61 7 5597 1494",
    "sg:postcode":"4214",
    "sg:province":"QLD",
    "sg:tags":[
        "consultant",
        "laser"
    ],
    "wof:name":"Lasertron & The Plastics People",
    "wof:placetype":"venue"
},
  "geometry": {"coordinates":[153.36187744099999,-27.9781703949],"type":"Point"}
}