{
  "type": "Feature",
  "properties": {
    "iso:country":"AU",
    "sg:address":"164 Dalgetty Rd",
    "sg:city":"Beaumaris",
    "sg:classifiers":[
        {
            "category":"Utilities",
            "subcategory":"Electric",
            "type":"Services"
        }
    ],
    "sg:phone":"+61 3 9589 4568",
    "sg:postcode":"3193",
    "sg:province":"VIC",
    "sg:tags":[
        "electrical",
        "contractor"
    ],
    "wof:name":"Healy K C & I S",
    "wof:placetype":"venue"
},
  "geometry": {"coordinates":[145.03918457,-37.9795417786],"type":"Point"}
}