{
  "type": "Feature",
  "properties": {
    "addr:full":"Unit 3/ 1445 Main North Rd Para Hills West SA 5096",
    "addr:housenumber":"/ 1445",
    "addr:postcode":"5096",
    "addr:street":"Main North Rd Para Hills West",
    "iso:country":"AU",
    "sg:address":"Unit 3/ 1445 Main North Rd",
    "sg:city":"Para Hills West",
    "sg:classifiers":[
        {
            "category":"Manufacturing",
            "subcategory":"Signs",
            "type":"Manufacturing & Wholesale Goods"
        }
    ],
    "sg:phone":"+61 8 8285 4100",
    "sg:postcode":"5096",
    "sg:province":"SA",
    "sg:tags":[
        "traffic",
        "safety"
    ],
    "wof:name":"Infinity Signs",
    "wof:placetype":"venue"
},
  "geometry": {"coordinates":[138.64579773,-34.7936439514],"type":"Point"}
}