{
  "type": "Feature",
  "properties": {
    "iso:country":"AU",
    "sg:address":"59 Adelaide St",
    "sg:city":"Blayney",
    "sg:classifiers":[
        {
            "category":"Travel",
            "subcategory":"Hotels & Motels",
            "type":"Entertainment"
        }
    ],
    "sg:phone":"+61 2 6368 2210",
    "sg:postcode":"2799",
    "sg:province":"NSW",
    "sg:tags":[
        "accommodation"
    ],
    "wof:name":"Royal Hotel.",
    "wof:placetype":"venue"
},
  "geometry": {"coordinates":[149.256714,-33.525414],"type":"Point"}
}