{
  "type": "Feature",
  "properties": {
    "addr:full":"PO Box 500 Brisbane Markets QLD 4106",
    "addr:postcode":"4106",
    "iso:country":"AU",
    "sg:address":"PO Box 500",
    "sg:city":"Brisbane Markets",
    "sg:classifiers":[
        {
            "category":"Food & Beverages",
            "subcategory":"Fruits & Vegetables",
            "type":"Retail Goods"
        }
    ],
    "sg:phone":"+61 7 3278 2666",
    "sg:postcode":"4106",
    "sg:province":"QLD",
    "sg:tags":[
        "wholesale"
    ],
    "wof:name":"Heather H E & Co",
    "wof:placetype":"venue"
},
  "geometry": {"coordinates":[153.00386047399999,-27.5508708954],"type":"Point"}
}