{
  "type": "Feature",
  "properties": {
    "iso:country":"AU",
    "sg:address":"Shop 3 Metropole Shopping Centre Cnr Creek & Pine",
    "sg:city":"Carindale",
    "sg:classifiers":[
        {
            "category":"Real Estate",
            "subcategory":"Real Estate Agent",
            "type":"Services"
        }
    ],
    "sg:phone":"+61 7 3849 5355",
    "sg:postcode":"4152",
    "sg:province":"QLD",
    "wof:name":"HARCOURTS QUEENSLAND PTY LTD",
    "wof:placetype":"venue"
},
  "geometry": {"coordinates":[153.101760864,-27.5173435211],"type":"Point"}
}