{
  "type": "Feature",
  "properties": {
    "addr:full":"2 Piping La Lonsdale SA 5160",
    "addr:housenumber":"2",
    "addr:postcode":"5160",
    "addr:street":"Piping La",
    "iso:country":"AU",
    "sg:address":"2 Piping La",
    "sg:city":"Lonsdale",
    "sg:classifiers":[
        {
            "category":"Manufacturing",
            "subcategory":"Metals",
            "type":"Manufacturing & Wholesale Goods"
        }
    ],
    "sg:phone":"+61 8 8382 6990",
    "sg:postcode":"5160",
    "sg:province":"SA",
    "sg:tags":[
        "sheet",
        "worker"
    ],
    "wof:name":"Southern Metal Spinners Pty. Ltd.",
    "wof:placetype":"venue"
},
  "geometry": {"coordinates":[138.499176025,-35.1081924438],"type":"Point"}
}