{
  "type": "Feature",
  "properties": {
    "iso:country":"AU",
    "sg:address":"22 Regency Rd",
    "sg:city":"Kilkenny",
    "sg:classifiers":[
        {
            "category":"Retail",
            "subcategory":"Auto Repair",
            "type":"Services"
        }
    ],
    "sg:phone":"+61 8 8445 2755",
    "sg:postcode":"5009",
    "sg:province":"SA",
    "sg:tags":[
        "muffler",
        "exhaust",
        "system"
    ],
    "wof:name":"Complete Exhaust Specialists",
    "wof:placetype":"venue"
},
  "geometry": {"coordinates":[138.554153442,-34.8757743835],"type":"Point"}
}