{
  "type": "Feature",
  "properties": {
    "addr:full":"38 Veronica St Warilla NSW 2528",
    "addr:housenumber":"38",
    "addr:postcode":"2528",
    "addr:street":"Veronica St",
    "iso:country":"AU",
    "sg:address":"38 Veronica St",
    "sg:city":"Warilla",
    "sg:classifiers":[
        {
            "category":"Home & Garden",
            "subcategory":"Carpets & Floor Coverings",
            "type":"Retail Goods"
        }
    ],
    "sg:phone":"+61 2 4296 8097",
    "sg:postcode":"2528",
    "sg:province":"NSW",
    "sg:tags":[
        "wood"
    ],
    "wof:name":"Warilla Wholesale Carpet Court",
    "wof:placetype":"venue"
},
  "geometry": {"coordinates":[150.86730957,-34.5482902527],"type":"Point"}
}