{
  "type": "Feature",
  "properties": {
    "addr:full":"9- 13 Lamana St Mordialloc VIC 3195",
    "addr:housenumber":"13",
    "addr:postcode":"3195",
    "addr:street":"9;Lamana St",
    "iso:country":"AU",
    "sg:address":"9- 13 Lamana St",
    "sg:city":"Mordialloc",
    "sg:classifiers":[
        {
            "category":"Wholesale",
            "subcategory":"Metals & Minerals",
            "type":"Manufacturing & Wholesale Goods"
        }
    ],
    "sg:phone":"+61 3 9587 2100",
    "sg:postcode":"3195",
    "sg:province":"VIC",
    "sg:tags":[
        "steel",
        "merchant"
    ],
    "wof:name":"Econo-Steel",
    "wof:placetype":"venue"
},
  "geometry": {"coordinates":[145.09771728499999,-38.0072631836],"type":"Point"}
}