{
  "type": "Feature",
  "properties": {
    "iso:country":"AU",
    "sg:address":"260 Toorak Rd",
    "sg:city":"South Yarra",
    "sg:classifiers":[
        {
            "category":"Personal",
            "subcategory":"Skin Care",
            "type":"Services"
        }
    ],
    "sg:phone":"+61 3 9827 5129",
    "sg:postcode":"3141",
    "sg:province":"VIC",
    "sg:tags":[
        "hair",
        "product"
    ],
    "wof:name":"Ardell Haircare",
    "wof:placetype":"venue"
},
  "geometry": {"coordinates":[144.99586486800001,-37.839630127],"type":"Point"}
}