{
  "type": "Feature",
  "properties": {
    "iso:country":"AU",
    "sg:address":"Shop 27 Level A Myer Centre",
    "sg:city":"Brisbane",
    "sg:classifiers":[
        {
            "category":"Personal",
            "subcategory":"Tanning Parlor",
            "type":"Services"
        }
    ],
    "sg:phone":"+61 7 3229 9500",
    "sg:postcode":"4000",
    "sg:province":"QLD",
    "sg:tags":[
        "solarium"
    ],
    "wof:name":"Deborah's Tuscan Tan Salon",
    "wof:placetype":"venue"
},
  "geometry": {"coordinates":[153.02276611299999,-27.4651203156],"type":"Point"}
}