{
  "type": "Feature",
  "properties": {
    "addr:full":"412a Milton Rd Auchenflower QLD 4066",
    "addr:housenumber":"412a",
    "addr:postcode":"4066",
    "addr:street":"Milton Rd",
    "iso:country":"AU",
    "sg:address":"412a Milton Rd",
    "sg:city":"Auchenflower",
    "sg:classifiers":[
        {
            "category":"Fast Food",
            "type":"Food & Drink"
        }
    ],
    "sg:phone":"+61 7 3870 9072",
    "sg:postcode":"4066",
    "sg:province":"QLD",
    "sg:tags":[
        "away",
        "take"
    ],
    "wof:name":"Tien Tsin Chinese Take Away",
    "wof:placetype":"venue"
},
  "geometry": {"coordinates":[152.99530029300001,-27.4742164612],"type":"Point"}
}