{
  "type": "Feature",
  "properties": {
    "addr:full":"90 Horton St Port Macquarie NSW 2444",
    "addr:housenumber":"90",
    "addr:postcode":"2444",
    "addr:street":"Horton St",
    "iso:country":"AU",
    "sg:address":"90 Horton St",
    "sg:city":"Port Macquarie",
    "sg:classifiers":[
        {
            "category":"Shopping",
            "subcategory":"Jewelry",
            "type":"Retail Goods"
        }
    ],
    "sg:phone":"+61 2 6583 2044",
    "sg:postcode":"2444",
    "sg:province":"NSW",
    "sg:tags":[
        "jeweller"
    ],
    "wof:name":"Jon's Family Jewellers",
    "wof:placetype":"venue"
},
  "geometry": {"coordinates":[152.90846300000001,-31.430969],"type":"Point"}
}