{
  "type": "Feature",
  "properties": {
    "addr:full":"6a Secker Rd Mt Barker SA 5251",
    "addr:housenumber":"6a",
    "addr:postcode":"5251",
    "addr:street":"Secker Rd",
    "iso:country":"AU",
    "sg:address":"6a Secker Rd",
    "sg:city":"Mt Barker",
    "sg:classifiers":[
        {
            "category":"Autos & Motor Vehicles",
            "subcategory":"Motorcycle Sales",
            "type":"Retail Goods"
        }
    ],
    "sg:phone":"+61 8 8391 5058",
    "sg:postcode":"5251",
    "sg:province":"SA",
    "sg:tags":[
        "part",
        "recyclers",
        "cycle"
    ],
    "wof:name":"Tucker Motorcycles",
    "wof:placetype":"venue"
},
  "geometry": {"coordinates":[138.87458801299999,-35.0759010315],"type":"Point"}
}