{
  "type": "Feature",
  "properties": {
    "iso:country":"AU",
    "sg:address":"25 Kennedy St St",
    "sg:city":"Agnes",
    "sg:classifiers":[
        {
            "category":"Building & Trades",
            "subcategory":"Cleaning & Sanitation",
            "type":"Services"
        }
    ],
    "sg:phone":"+61 8 8396 2167",
    "sg:postcode":"5097",
    "sg:province":"SA",
    "sg:tags":[
        "industrial",
        "commercial",
        "contractor"
    ],
    "wof:name":"Triple S Cleaning",
    "wof:placetype":"venue"
},
  "geometry": {"coordinates":[138.714019775,-34.824760437],"type":"Point"}
}