{
  "type": "Feature",
  "properties": {
    "addr:full":"Shop 41 Noranda Shopng Cntr Benara Rd Noranda WA 6062",
    "addr:housenumber":"shop 41",
    "addr:postcode":"6062",
    "addr:street":"Benara Rd",
    "iso:country":"AU",
    "sg:address":"Shop 41 Noranda Shopng Cntr Benara Rd",
    "sg:city":"Noranda",
    "sg:classifiers":[
        {
            "category":"Communications",
            "subcategory":"Film & Video Production",
            "type":"Services"
        }
    ],
    "sg:phone":"+61 8 9275 6050",
    "sg:postcode":"6062",
    "sg:province":"WA",
    "sg:tags":[
        "dvd",
        "library"
    ],
    "wof:name":"Video Ezy",
    "wof:placetype":"venue"
},
  "geometry": {"coordinates":[115.895889282,-31.8754997253],"type":"Point"}
}