{
  "type": "Feature",
  "properties": {
    "iso:country":"AU",
    "sg:address":"25 Kapara Rd",
    "sg:city":"Gillman",
    "sg:classifiers":[
        {
            "category":"Home & Garden",
            "subcategory":"Building Materials",
            "type":"Retail Goods"
        }
    ],
    "sg:phone":"+61 8 8341 1666",
    "sg:postcode":"5013",
    "sg:province":"SA",
    "sg:tags":[
        "supply"
    ],
    "wof:name":"Allmat Pty Ltd",
    "wof:placetype":"venue"
},
  "geometry": {"coordinates":[138.532714844,-34.8382873535],"type":"Point"}
}