{
  "type": "Feature",
  "properties": {
    "addr:full":"Shp 3081 Indooroopilly Shopping Cntr Indooroopilly QLD 4068",
    "addr:housenumber":"3081",
    "addr:postcode":"4068",
    "addr:street":"Indooroopilly Shopping Cntr",
    "iso:country":"AU",
    "sg:address":"Shp 3081 Indooroopilly Shopping Cntr",
    "sg:city":"Indooroopilly",
    "sg:classifiers":[
        {
            "category":"Retail",
            "subcategory":"Repair Shop",
            "type":"Services"
        }
    ],
    "sg:phone":"+61 7 3878 9098",
    "sg:postcode":"4068",
    "sg:province":"QLD",
    "sg:tags":[
        "cleaner",
        "part",
        "vacuum"
    ],
    "wof:name":"Godfreys",
    "wof:placetype":"venue"
},
  "geometry": {"coordinates":[152.99017334000001,-27.4945602417],"type":"Point"}
}