{
  "type": "Feature",
  "properties": {
    "addr:full":"15 Morrissey St Woolloongabba QLD 4102",
    "addr:housenumber":"15",
    "addr:postcode":"4102",
    "addr:street":"Morrissey St",
    "iso:country":"AU",
    "sg:address":"15 Morrissey St",
    "sg:city":"Woolloongabba",
    "sg:classifiers":[
        {
            "category":"Government",
            "subcategory":"Court House",
            "type":"Public Place"
        }
    ],
    "sg:phone":"+61 7 3391 0004",
    "sg:postcode":"4102",
    "sg:province":"QLD",
    "sg:tags":[
        "personal",
        "marriage",
        "family",
        "counselling"
    ],
    "wof:name":"Brisbane Rape & Incest Survivors Support Centre",
    "wof:placetype":"venue"
},
  "geometry": {"coordinates":[153.03538513199999,-27.4941215515],"type":"Point"}
}