{
  "type": "Feature",
  "properties": {
    "addr:full":"13 Sheoak Crt Cashmere QLD 4500",
    "addr:housenumber":"13",
    "addr:postcode":"4500",
    "addr:street":"Sheoak Crt",
    "iso:country":"AU",
    "sg:address":"13 Sheoak Crt",
    "sg:city":"Cashmere",
    "sg:classifiers":[
        {
            "category":"Utilities",
            "subcategory":"Water",
            "type":"Services"
        }
    ],
    "sg:phone":"+61 7 3298 5888",
    "sg:postcode":"4500",
    "sg:province":"QLD",
    "sg:tags":[
        "hot",
        "system"
    ],
    "wof:name":"Harrison Plumbing & Gas Services",
    "wof:placetype":"venue"
},
  "geometry": {"coordinates":[152.92965698200001,-27.3155136108],"type":"Point"}
}