{
  "type": "Feature",
  "properties": {
    "iso:country":"AU",
    "sg:address":"268 Central Ave",
    "sg:city":"Shepparton",
    "sg:phone":"+61 3 5829 2325",
    "sg:postcode":"3630",
    "sg:province":"VIC",
    "wof:name":"Solarglass Window Tinting",
    "wof:placetype":"venue"
},
  "geometry": {"coordinates":[145.46174621599999,-36.3893623352],"type":"Point"}
}