{
  "type": "Feature",
  "properties": {
    "addr:full":"4 Ward St Eastwood NSW 2122",
    "addr:housenumber":"4",
    "addr:postcode":"2122",
    "addr:street":"Ward St",
    "iso:country":"AU",
    "sg:address":"4 Ward St",
    "sg:city":"Eastwood",
    "sg:classifiers":[
        {
            "category":"Retail",
            "subcategory":"Repair Shop",
            "type":"Services"
        }
    ],
    "sg:phone":"+61 2 9858 4771",
    "sg:postcode":"2122",
    "sg:province":"NSW",
    "sg:tags":[
        "machine",
        "repairs",
        "part",
        "dryer",
        "washing"
    ],
    "wof:name":"Appliance Doctor The",
    "wof:placetype":"venue"
},
  "geometry": {"coordinates":[151.07400512699999,-33.7876281738],"type":"Point"}
}