{
  "type": "Feature",
  "properties": {
    "iso:country":"AU",
    "sg:address":"39 Dunmore St",
    "sg:city":"Wentworthville",
    "sg:classifiers":[
        {
            "category":"Fast Food",
            "type":"Food & Drink"
        }
    ],
    "sg:phone":"+61 2 9896 5517",
    "sg:postcode":"2145",
    "sg:province":"NSW",
    "sg:tags":[
        "away",
        "take"
    ],
    "wof:name":"Aegean Way Seafoods",
    "wof:placetype":"venue"
},
  "geometry": {"coordinates":[150.97149658199999,-33.8075752258],"type":"Point"}
}