{
  "type": "Feature",
  "properties": {
    "iso:country":"AU",
    "sg:address":"64C Holbrooks Rd",
    "sg:city":"Flinders Park",
    "sg:classifiers":[
        {
            "category":"Real Estate",
            "subcategory":"Real Estate Agent",
            "type":"Services"
        }
    ],
    "sg:phone":"+61 8 8443 5350",
    "sg:postcode":"5025",
    "sg:province":"SA",
    "wof:name":"Brock Harcourts",
    "wof:placetype":"venue"
},
  "geometry": {"coordinates":[138.54887390100001,-34.9105186462],"type":"Point"}
}