{
  "type": "Feature",
  "properties": {
    "addr:full":"169 Pringles Rd Kobble Creek QLD 4520",
    "addr:housenumber":"169",
    "addr:postcode":"4520",
    "addr:street":"Pringles Rd",
    "iso:country":"AU",
    "sg:address":"169 Pringles Rd",
    "sg:city":"Kobble Creek",
    "sg:classifiers":[
        {
            "category":"Building & Trades",
            "subcategory":"Landscaping Services",
            "type":"Services"
        }
    ],
    "sg:phone":"+61 7 3289 9134",
    "sg:postcode":"4520",
    "sg:province":"QLD",
    "sg:tags":[
        "designer",
        "landscape",
        "contractor"
    ],
    "wof:name":"Kobble Gardens",
    "wof:placetype":"venue"
},
  "geometry": {"coordinates":[152.81634500000001,-27.258919],"type":"Point"}
}