{
  "type": "Feature",
  "properties": {
    "iso:country":"AU",
    "sg:address":"7/ 10 Brook St",
    "sg:city":"Crows Nest",
    "sg:classifiers":[
        {
            "category":"Building & Trades",
            "subcategory":"Construction",
            "type":"Services"
        }
    ],
    "sg:phone":"+61 410 490 275",
    "sg:postcode":"2065",
    "sg:province":"NSW",
    "sg:tags":[
        "tennis court",
        "repair"
    ],
    "wof:name":"Faultless Court Care",
    "wof:placetype":"venue"
},
  "geometry": {"coordinates":[151.204055786,-33.8222885132],"type":"Point"}
}