{
  "type": "Feature",
  "properties": {
    "iso:country":"AU",
    "sg:address":"91 View St",
    "sg:city":"Bendigo",
    "sg:classifiers":[
        {
            "category":"Shopping",
            "subcategory":"Antiques",
            "type":"Retail Goods"
        }
    ],
    "sg:phone":"+61 3 5442 9951",
    "sg:postcode":"3550",
    "sg:province":"VIC",
    "wof:name":"View Street Bazaar",
    "wof:placetype":"venue"
},
  "geometry": {"coordinates":[144.27650451700001,-36.7580032349],"type":"Point"}
}