{
  "type": "Feature",
  "properties": {
    "addr:full":"57- 59 Cheriton St East Perth WA 6004",
    "addr:housenumber":"59",
    "addr:postcode":"6004",
    "addr:street":"Cheriton St East",
    "iso:country":"AU",
    "sg:address":"57- 59 Cheriton St",
    "sg:city":"East Perth",
    "sg:classifiers":[
        {
            "category":"Shopping",
            "subcategory":"Stationery & Office Supplies",
            "type":"Retail Goods"
        }
    ],
    "sg:phone":"+61 8 9319 6555",
    "sg:postcode":"6004",
    "sg:province":"WA",
    "sg:tags":[
        "packaging",
        "material"
    ],
    "wof:name":"Percival Print & Packaging",
    "wof:placetype":"venue"
},
  "geometry": {"coordinates":[115.87352752699999,-31.9463272095],"type":"Point"}
}