{
  "type": "Feature",
  "properties": {
    "iso:country":"AU",
    "sg:address":"5/ 1 Bray St",
    "sg:city":"Hastings",
    "sg:classifiers":[
        {
            "category":"Autos & Motor Vehicles",
            "subcategory":"Auto Supplies",
            "type":"Retail Goods"
        }
    ],
    "sg:phone":"+61 3 5979 4722",
    "sg:postcode":"3915",
    "sg:province":"VIC",
    "sg:tags":[
        "part",
        "cycles",
        "accessory"
    ],
    "wof:name":"Westernport Mowerpower",
    "wof:placetype":"venue"
},
  "geometry": {"coordinates":[145.18307495100001,-38.3142242432],"type":"Point"}
}