{
  "type": "Feature",
  "properties": {
    "addr:full":"26 Hartog Drv Werrington County NSW 2747",
    "addr:housenumber":"26",
    "addr:postcode":"2747",
    "addr:street":"Hartog Drv",
    "iso:country":"AU",
    "sg:address":"26 Hartog Drv",
    "sg:city":"Werrington County",
    "sg:classifiers":[
        {
            "category":"Communications",
            "type":"Services"
        }
    ],
    "sg:phone":"+61 2 9833 9050",
    "sg:postcode":"2747",
    "sg:province":"NSW",
    "sg:tags":[
        "antenna"
    ],
    "wof:name":"Pro-Tel Antenna Service",
    "wof:placetype":"venue"
},
  "geometry": {"coordinates":[150.750930786,-33.7433319092],"type":"Point"}
}