{
  "type": "Feature",
  "properties": {
    "iso:country":"AU",
    "sg:address":"222 Merrylands Rd",
    "sg:city":"Merrylands",
    "sg:classifiers":[
        {
            "category":"Shopping",
            "subcategory":"Shoes",
            "type":"Retail Goods"
        }
    ],
    "sg:phone":"+61 2 9682 5188",
    "sg:postcode":"2160",
    "sg:province":"NSW",
    "sg:tags":[
        "footwear"
    ],
    "wof:name":"Direct Shoe Warehouse",
    "wof:placetype":"venue"
},
  "geometry": {"coordinates":[150.98849487300001,-33.8363113403],"type":"Point"}
}