{
  "type": "Feature",
  "properties": {
    "addr:full":"563 Ingham Rd Bohle QLD 4818",
    "addr:housenumber":"563",
    "addr:postcode":"4818",
    "addr:street":"Ingham Rd",
    "iso:country":"AU",
    "sg:address":"563 Ingham Rd",
    "sg:city":"Bohle",
    "sg:classifiers":[
        {
            "category":"Utilities",
            "subcategory":"Refuse",
            "type":"Services"
        }
    ],
    "sg:phone":"+61 7 4774 7300",
    "sg:postcode":"4818",
    "sg:province":"QLD",
    "sg:tags":[
        "pulverising",
        "crushing"
    ],
    "wof:name":"Markwell Plant Hire",
    "wof:placetype":"venue"
},
  "geometry": {"coordinates":[146.707886,-19.263386],"type":"Point"}
}