{
  "type": "Feature",
  "properties": {
    "addr:full":"497 Morayfield Rd Burpengary QLD 4505",
    "addr:housenumber":"497",
    "addr:postcode":"4505",
    "addr:street":"Morayfield Rd",
    "iso:country":"AU",
    "sg:address":"497 Morayfield Rd",
    "sg:city":"Burpengary",
    "sg:classifiers":[
        {
            "category":"Farming",
            "subcategory":"Nursery",
            "type":"Manufacturing & Wholesale Goods"
        }
    ],
    "sg:phone":"+61 7 5498 5665",
    "sg:postcode":"4505",
    "sg:province":"QLD",
    "wof:name":"Js Nursery",
    "wof:placetype":"venue"
},
  "geometry": {"coordinates":[152.97753906200001,-27.1482868195],"type":"Point"}
}