{
  "type": "Feature",
  "properties": {
    "iso:country":"AU",
    "sg:address":"PO Box 2050",
    "sg:city":"Wellington Point",
    "sg:classifiers":[
        {
            "category":"Professional",
            "subcategory":"Detective & Security Services",
            "type":"Services"
        }
    ],
    "sg:phone":"+61 400 024 767",
    "sg:postcode":"4160",
    "sg:province":"QLD",
    "sg:tags":[
        "consultant",
        "system"
    ],
    "wof:name":"Secure A Building",
    "wof:placetype":"venue"
},
  "geometry": {"coordinates":[153.24041748100001,-27.5097808838],"type":"Point"}
}