{
  "type": "Feature",
  "properties": {
    "addr:full":"20 Albert St Creswick VIC 3363",
    "addr:housenumber":"20",
    "addr:postcode":"3363",
    "addr:street":"Albert St",
    "iso:country":"AU",
    "sg:address":"20 Albert St",
    "sg:city":"Creswick",
    "sg:classifiers":[
        {
            "category":"Personal",
            "subcategory":"Beauty Salon",
            "type":"Services"
        }
    ],
    "sg:phone":"+61 3 5345 2460",
    "sg:postcode":"3363",
    "sg:province":"VIC",
    "sg:tags":[
        "hairdresser"
    ],
    "wof:name":"Creswick Hair Care",
    "wof:placetype":"venue"
},
  "geometry": {"coordinates":[143.895065308,-37.4202613831],"type":"Point"}
}