{
  "type": "Feature",
  "properties": {
    "addr:full":"230 June St Grantville VIC 3984",
    "addr:housenumber":"230",
    "addr:postcode":"3984",
    "addr:street":"June St",
    "iso:country":"AU",
    "sg:address":"230 June St",
    "sg:city":"Grantville",
    "sg:classifiers":[
        {
            "category":"Building & Trades",
            "subcategory":"Construction",
            "type":"Services"
        }
    ],
    "sg:phone":"+61 3 5678 8407",
    "sg:postcode":"3984",
    "sg:province":"VIC",
    "sg:tags":[
        "stonework",
        "stone",
        "mason"
    ],
    "wof:name":"S.E.A. Stone Masonry",
    "wof:placetype":"venue"
},
  "geometry": {"coordinates":[145.529220581,-38.4253120422],"type":"Point"}
}