{
  "type": "Feature",
  "properties": {
    "iso:country":"AU",
    "sg:address":"Bay 14",
    "sg:city":"Bayside Circuit Laurieton",
    "sg:classifiers":[
        {
            "category":"Professional",
            "type":"Services"
        }
    ],
    "sg:phone":"+61 2 6559 7199",
    "sg:postcode":"2443",
    "sg:province":"NSW",
    "sg:tags":[
        "spray",
        "painting"
    ],
    "wof:name":"Goodison B & B Smash Repairs Pty Ltd",
    "wof:placetype":"venue"
},
  "geometry": {"coordinates":[152.796646,-31.643936],"type":"Point"}
}