{
  "type": "Feature",
  "properties": {
    "iso:country":"AU",
    "sg:address":"Suite 29,Mount Isa House Mary St",
    "sg:city":"Mt Isa",
    "sg:classifiers":[
        {
            "category":"Professional",
            "subcategory":"Business Services",
            "type":"Services"
        }
    ],
    "sg:phone":"+61 7 4749 5011",
    "sg:postcode":"4825",
    "sg:province":"QLD",
    "sg:tags":[
        "broker"
    ],
    "wof:name":"Department of Tourism,Small Business and Industry",
    "wof:placetype":"venue"
},
  "geometry": {"coordinates":[139.490814,-20.721407],"type":"Point"}
}