{
  "type": "Feature",
  "properties": {
    "addr:full":"80 Mcdougall St Kirribilli NSW 2061",
    "addr:housenumber":"80",
    "addr:postcode":"2061",
    "addr:street":"Mcdougall St",
    "iso:country":"AU",
    "sg:address":"80 Mcdougall St",
    "sg:city":"Kirribilli",
    "sg:classifiers":[
        {
            "category":"Wholesale",
            "subcategory":"Construction Materials",
            "type":"Manufacturing & Wholesale Goods"
        }
    ],
    "sg:phone":"+61 2 9417 8287",
    "sg:postcode":"2061",
    "sg:province":"NSW",
    "sg:tags":[
        "wholesaler",
        "lighting",
        "mfrs",
        "accessory"
    ],
    "wof:name":"Aureol Lighting Australia Pty Ltd",
    "wof:placetype":"venue"
},
  "geometry": {"coordinates":[151.21531677199999,-33.8454780579],"type":"Point"}
}