{
  "type": "Feature",
  "properties": {
    "addr:full":"Swanbrook Rd Inverell NSW 2360",
    "addr:postcode":"2360",
    "addr:street":"Swanbrook Rd",
    "iso:country":"AU",
    "sg:address":"Swanbrook Rd",
    "sg:city":"Inverell",
    "sg:classifiers":[
        {
            "category":"Education",
            "subcategory":"School",
            "type":"Public Place"
        }
    ],
    "sg:phone":"+61 2 6722 1555",
    "sg:postcode":"2360",
    "sg:province":"NSW",
    "sg:tags":[
        "state",
        "-",
        "nsw"
    ],
    "wof:name":"MacIntyre High School",
    "wof:placetype":"venue"
},
  "geometry": {"coordinates":[151.12159729000001,-29.7680587769],"type":"Point"}
}