{
  "type": "Feature",
  "properties": {
    "addr:full":"506 Pelican Creek Rd Caniaba NSW 2480",
    "addr:housenumber":"506",
    "addr:postcode":"2480",
    "addr:street":"Pelican Creek Rd",
    "iso:country":"AU",
    "sg:address":"506 Pelican Creek Rd",
    "sg:city":"Caniaba",
    "sg:classifiers":[
        {
            "category":"Building & Trades",
            "subcategory":"Construction",
            "type":"Services"
        }
    ],
    "sg:phone":"+61 2 6663 1552",
    "sg:postcode":"2480",
    "sg:province":"NSW",
    "sg:tags":[
        "plasterboard",
        "plasterer",
        "fixer"
    ],
    "wof:name":"Frank Forzan Plasterer",
    "wof:placetype":"venue"
},
  "geometry": {"coordinates":[153.208786011,-28.8473701477],"type":"Point"}
}