{
  "type": "Feature",
  "properties": {
    "iso:country":"AU",
    "sg:address":"492 Toorak Rd",
    "sg:city":"Toorak",
    "sg:classifiers":[
        {
            "category":"Health Services",
            "subcategory":"Doctor",
            "type":"Services"
        }
    ],
    "sg:phone":"+61 3 9827 3300",
    "sg:postcode":"3142",
    "sg:province":"VIC",
    "sg:tags":[
        "medical",
        "practitioner"
    ],
    "wof:name":"Jeffery Paul E",
    "wof:placetype":"venue"
},
  "geometry": {"coordinates":[145.01184082,-37.8415374756],"type":"Point"}
}