{
  "type": "Feature",
  "properties": {
    "iso:country":"AU",
    "sg:address":"19 Elm Pl",
    "sg:city":"Heathwood",
    "sg:classifiers":[
        {
            "category":"Utilities",
            "subcategory":"Electric",
            "type":"Services"
        }
    ],
    "sg:phone":"+61 418 198 369",
    "sg:postcode":"4110",
    "sg:province":"QLD",
    "sg:tags":[
        "electrical",
        "contractor"
    ],
    "wof:name":"Harrison D & J Electrical",
    "wof:placetype":"venue"
},
  "geometry": {"coordinates":[152.99137878400001,-27.6318073273],"type":"Point"}
}