{
  "type": "Feature",
  "properties": {
    "iso:country":"AU",
    "sg:address":"774 Albany Hwy",
    "sg:city":"East Victoria Park",
    "sg:classifiers":[
        {
            "category":"Travel",
            "subcategory":"Hotels & Motels",
            "type":"Entertainment"
        }
    ],
    "sg:phone":"+61 8 9470 5818",
    "sg:postcode":"6101",
    "sg:province":"WA",
    "sg:tags":[
        "accommodation"
    ],
    "wof:name":"Joe Blacks Bar & Food",
    "wof:placetype":"venue"
},
  "geometry": {"coordinates":[115.90219116199999,-31.9829463959],"type":"Point"}
}