{
  "type": "Feature",
  "properties": {
    "iso:country":"AU",
    "sg:address":"Shop 3/ 30 Punt Rd",
    "sg:city":"Cobram",
    "sg:classifiers":[
        {
            "category":"Food & Beverages",
            "subcategory":"Bakery",
            "type":"Retail Goods"
        }
    ],
    "sg:phone":"+61 3 5871 1055",
    "sg:postcode":"3644",
    "sg:province":"VIC",
    "sg:tags":[
        "baker"
    ],
    "wof:name":"Bakers Delight Cobram",
    "wof:placetype":"venue"
},
  "geometry": {"coordinates":[145.64854431099999,-35.9194488525],"type":"Point"}
}