{
  "type": "Feature",
  "properties": {
    "addr:full":"2/ 1 Pannikin St Rochedale South QLD 4123",
    "addr:housenumber":"/ 1",
    "addr:postcode":"4123",
    "addr:street":"Pannikin St",
    "iso:country":"AU",
    "sg:address":"2/ 1 Pannikin St",
    "sg:city":"Rochedale South",
    "sg:classifiers":[
        {
            "category":"Real Estate",
            "subcategory":"Real Estate Agent",
            "type":"Services"
        }
    ],
    "sg:phone":"+61 7 3841 8418",
    "sg:postcode":"4123",
    "sg:province":"QLD",
    "wof:name":"Go Gecko",
    "wof:placetype":"venue"
},
  "geometry": {"coordinates":[153.12428283700001,-27.6096363068],"type":"Point"}
}