{
  "type": "Feature",
  "properties": {
    "addr:full":"8/ 20 Twickenham Rd Burswood WA 6100",
    "addr:housenumber":"/ 20",
    "addr:postcode":"6100",
    "addr:street":"Twickenham Rd",
    "iso:country":"AU",
    "sg:address":"8/ 20 Twickenham Rd",
    "sg:city":"Burswood",
    "sg:classifiers":[
        {
            "category":"Building & Trades",
            "subcategory":"Construction",
            "type":"Services"
        }
    ],
    "sg:phone":"+61 8 9362 5411",
    "sg:postcode":"6100",
    "sg:province":"WA",
    "sg:tags":[
        "contractor"
    ],
    "wof:name":"Komemo Constructions",
    "wof:placetype":"venue"
},
  "geometry": {"coordinates":[115.89302063,-31.9686603546],"type":"Point"}
}