{
  "type": "Feature",
  "properties": {
    "iso:country":"AU",
    "sg:address":"3/ 10 Lorraine Ave",
    "sg:city":"Berkeley Vale",
    "sg:classifiers":[
        {
            "category":"Health Services",
            "subcategory":"Doctor",
            "type":"Services"
        }
    ],
    "sg:phone":"+61 2 4388 3985",
    "sg:postcode":"2261",
    "sg:province":"NSW",
    "sg:tags":[
        "medical",
        "practitioner"
    ],
    "wof:name":"Family Doctors",
    "wof:placetype":"venue"
},
  "geometry": {"coordinates":[151.43249499999999,-33.338757],"type":"Point"}
}