{
  "type": "Feature",
  "properties": {
    "addr:full":"2 Cobb Crt Newborough VIC 3825",
    "addr:housenumber":"2",
    "addr:postcode":"3825",
    "addr:street":"Cobb Crt",
    "iso:country":"AU",
    "sg:address":"2 Cobb Crt",
    "sg:city":"Newborough",
    "sg:classifiers":[
        {
            "category":"Building & Trades",
            "subcategory":"Plumbing",
            "type":"Services"
        }
    ],
    "sg:phone":"+61 407 875 957",
    "sg:postcode":"3825",
    "sg:province":"VIC",
    "sg:tags":[
        "plumber",
        "gasfitters"
    ],
    "wof:name":"J & M Plumbing",
    "wof:placetype":"venue"
},
  "geometry": {"coordinates":[146.27681000000001,-38.180607],"type":"Point"}
}