{
  "type": "Feature",
  "properties": {
    "addr:full":"597 Darling St Balmain NSW 2041",
    "addr:housenumber":"597",
    "addr:postcode":"2041",
    "addr:street":"Darling St",
    "iso:country":"AU",
    "sg:address":"597 Darling St",
    "sg:city":"Balmain",
    "sg:classifiers":[
        {
            "category":"Real Estate",
            "subcategory":"Real Estate Agent",
            "type":"Services"
        }
    ],
    "sg:phone":"+61 2 9555 8244",
    "sg:postcode":"2041",
    "sg:province":"NSW",
    "wof:name":"Balmain Richardson & Wrench",
    "wof:placetype":"venue"
},
  "geometry": {"coordinates":[151.17166137699999,-33.8604927063],"type":"Point"}
}