{
  "type": "Feature",
  "properties": {
    "addr:full":"Factory 1/ 7 Newlands Rd Reservoir VIC 3073",
    "addr:housenumber":"/ 7",
    "addr:postcode":"3073",
    "addr:street":"Newlands Rd",
    "iso:country":"AU",
    "sg:address":"Factory 1/ 7 Newlands Rd",
    "sg:city":"Reservoir",
    "sg:classifiers":[
        {
            "category":"Retail",
            "subcategory":"Auto Repair",
            "type":"Services"
        }
    ],
    "sg:phone":"+61 3 9460 8503",
    "sg:postcode":"3073",
    "sg:province":"VIC",
    "sg:tags":[
        "repairer",
        "motor",
        "engineer"
    ],
    "wof:name":"BM European",
    "wof:placetype":"venue"
},
  "geometry": {"coordinates":[144.98324585,-37.7157096863],"type":"Point"}
}