{
  "type": "Feature",
  "properties": {
    "addr:full":"Factory 2 18 Melrich Rd Bayswater VIC 3153",
    "addr:housenumber":"18",
    "addr:postcode":"3153",
    "addr:street":"Melrich Rd",
    "iso:country":"AU",
    "sg:address":"Factory 2 18 Melrich Rd",
    "sg:city":"Bayswater",
    "sg:classifiers":[
        {
            "category":"Professional",
            "subcategory":"Printing & Photocopies",
            "type":"Services"
        }
    ],
    "sg:phone":"+61 3 9762 9522",
    "sg:postcode":"3153",
    "sg:province":"VIC",
    "sg:tags":[
        "screen",
        "printer"
    ],
    "wof:name":"Screen Graffiti Vic Pty Ltd",
    "wof:placetype":"venue"
},
  "geometry": {"coordinates":[145.28224182100001,-37.8459663391],"type":"Point"}
}