{
  "type": "Feature",
  "properties": {
    "iso:country":"AU",
    "sg:address":"405 Lake Albert Rd",
    "sg:city":"Kooringal",
    "sg:classifiers":[
        {
            "category":"Personal",
            "subcategory":"Beauty Salon",
            "type":"Services"
        }
    ],
    "sg:phone":"+61 2 6922 3037",
    "sg:postcode":"2650",
    "sg:province":"NSW",
    "sg:tags":[
        "hairdresser"
    ],
    "wof:name":"Hair Intuition",
    "wof:placetype":"venue"
},
  "geometry": {"coordinates":[147.372756958,-35.1513175964],"type":"Point"}
}