{
  "type": "Feature",
  "properties": {
    "addr:full":"3 Meadow Crt Wandin VIC 3139",
    "addr:housenumber":"3",
    "addr:postcode":"3139",
    "addr:street":"Meadow Crt",
    "iso:country":"AU",
    "sg:address":"3 Meadow Crt",
    "sg:city":"Wandin",
    "sg:classifiers":[
        {
            "category":"Professional",
            "subcategory":"Engineering",
            "type":"Services"
        }
    ],
    "sg:phone":"+61 3 5964 2708",
    "sg:postcode":"3139",
    "sg:province":"VIC",
    "sg:tags":[
        "engineer",
        "mechanical"
    ],
    "wof:name":"Mullins Automotive Services",
    "wof:placetype":"venue"
},
  "geometry": {"coordinates":[145.42483520499999,-37.7802581787],"type":"Point"}
}