{
  "type": "Feature",
  "properties": {
    "addr:full":"Suite 4 95 Henry St Penrith NSW 2750",
    "addr:housenumber":"95",
    "addr:postcode":"2750",
    "addr:street":"Henry St",
    "iso:country":"AU",
    "sg:address":"Suite 4 95 Henry St",
    "sg:city":"Penrith",
    "sg:classifiers":[
        {
            "category":"Professional",
            "subcategory":"Accounting & Tax Preparation",
            "type":"Services"
        }
    ],
    "sg:phone":"+61 2 4722 9999",
    "sg:postcode":"2750",
    "sg:province":"NSW",
    "sg:tags":[
        "accountant",
        "auditor"
    ],
    "wof:name":"Azzopardi Diane",
    "wof:placetype":"venue"
},
  "geometry": {"coordinates":[150.982254028,-33.8592681885],"type":"Point"}
}