{
  "type": "Feature",
  "properties": {
    "iso:country":"AU",
    "sg:address":"82 Industrial Ave",
    "sg:city":"Toowoomba",
    "sg:classifiers":[
        {
            "category":"Professional",
            "subcategory":"Engineering",
            "type":"Services"
        }
    ],
    "sg:phone":"+61 7 4633 0456",
    "sg:postcode":"4350",
    "sg:province":"QLD",
    "sg:tags":[
        "engineer"
    ],
    "wof:name":"All-Turnit Engineering",
    "wof:placetype":"venue"
},
  "geometry": {"coordinates":[151.90600599999999,-27.542938],"type":"Point"}
}