{
  "type": "Feature",
  "properties": {
    "addr:full":"Shop 140 Waverley Gardens Shopping Centre Mulgrave VIC 3170",
    "addr:housenumber":"140",
    "addr:postcode":"3170",
    "addr:street":"Waverley Gardens",
    "iso:country":"AU",
    "sg:address":"Shop 140",
    "sg:city":"Waverley Gardens Shopping Centre Mulgrave",
    "sg:classifiers":[
        {
            "category":"Personal",
            "subcategory":"Beauty Salon",
            "type":"Services"
        }
    ],
    "sg:phone":"+61 3 9547 6543",
    "sg:postcode":"3170",
    "sg:province":"VIC",
    "sg:tags":[
        "hairdresser"
    ],
    "wof:name":"Menz Plus",
    "wof:placetype":"venue"
},
  "geometry": {"coordinates":[145.12420654300001,-37.884437561],"type":"Point"}
}