{
  "type": "Feature",
  "properties": {
    "addr:full":"5 Brooke St Invermay TAS 7248",
    "addr:housenumber":"5",
    "addr:postcode":"7248",
    "addr:street":"Brooke St",
    "iso:country":"AU",
    "sg:address":"5 Brooke St",
    "sg:city":"Invermay",
    "sg:classifiers":[
        {
            "category":"Professional",
            "type":"Services"
        }
    ],
    "sg:phone":"+61 3 6331 9055",
    "sg:postcode":"7248",
    "sg:province":"TAS",
    "sg:tags":[
        "transport"
    ],
    "wof:name":"Bridport Carrier",
    "wof:placetype":"venue"
},
  "geometry": {"coordinates":[147.13177490199999,-41.4219551086],"type":"Point"}
}