{
  "type": "Feature",
  "properties": {
    "addr:full":"Shop 26/ 21 Hansford Rd Coombabah QLD 4216",
    "addr:housenumber":"shop 26 / 21",
    "addr:postcode":"4216",
    "addr:street":"Hansford Rd",
    "iso:country":"AU",
    "sg:address":"Shop 26/ 21 Hansford Rd",
    "sg:city":"Coombabah",
    "sg:classifiers":[
        {
            "category":"Communications",
            "subcategory":"Film & Video Production",
            "type":"Services"
        }
    ],
    "sg:phone":"+61 7 5529 6999",
    "sg:postcode":"4216",
    "sg:province":"QLD",
    "sg:tags":[
        "dvd",
        "library"
    ],
    "wof:name":"Leading Edge Video",
    "wof:placetype":"venue"
},
  "geometry": {"coordinates":[153.386184692,-27.8999176025],"type":"Point"}
}