{
  "type": "Feature",
  "properties": {
    "addr:full":"Shp5/ 146 Main South Rd Morphett Vale SA 5162",
    "addr:housenumber":"146",
    "addr:postcode":"5162",
    "addr:street":"Main South Rd",
    "iso:country":"AU",
    "sg:address":"Shp5/ 146 Main South Rd",
    "sg:city":"Morphett Vale",
    "sg:classifiers":[
        {
            "category":"Food & Beverages",
            "subcategory":"Bakery",
            "type":"Retail Goods"
        }
    ],
    "sg:phone":"+61 8 8186 1311",
    "sg:postcode":"5162",
    "sg:province":"SA",
    "sg:tags":[
        "baker"
    ],
    "wof:name":"Villa Pie Coffee",
    "wof:placetype":"venue"
},
  "geometry": {"coordinates":[138.523834228,-35.1265258789],"type":"Point"}
}