{
  "type": "Feature",
  "properties": {
    "addr:full":"10 Lorrean Ave Brighton East VIC 3187",
    "addr:housenumber":"10",
    "addr:postcode":"3187",
    "addr:street":"Lorrean Ave",
    "iso:country":"AU",
    "sg:address":"10 Lorrean Ave",
    "sg:city":"Brighton East",
    "sg:classifiers":[
        {
            "category":"Professional",
            "subcategory":"Art Services",
            "type":"Services"
        }
    ],
    "sg:phone":"+61 401 545 566",
    "sg:postcode":"3187",
    "sg:province":"VIC",
    "sg:tags":[
        "decorator",
        "painter"
    ],
    "wof:name":"Brighton Painting & Building Maintenance Services",
    "wof:placetype":"venue"
},
  "geometry": {"coordinates":[145.02182006800001,-37.9041900635],"type":"Point"}
}