{
  "type": "Feature",
  "properties": {
    "addr:full":"Suite 2, 16 East St Ipswich QLD 4305",
    "addr:housenumber":"16",
    "addr:postcode":"4305",
    "addr:street":"East St",
    "iso:country":"AU",
    "sg:address":"Suite 2, 16 East St",
    "sg:city":"Ipswich",
    "sg:classifiers":[
        {
            "category":"Professional",
            "subcategory":"Employment Agencies",
            "type":"Services"
        }
    ],
    "sg:phone":"+61 7 3281 3633",
    "sg:postcode":"4305",
    "sg:province":"QLD",
    "wof:name":"Bullseye Recruitment & HR Services",
    "wof:placetype":"venue"
},
  "geometry": {"coordinates":[152.76129150400001,-27.6136989594],"type":"Point"}
}