{
  "type": "Feature",
  "properties": {
    "addr:full":"151 Boundary Rd Bardon QLD 4065",
    "addr:housenumber":"151",
    "addr:postcode":"4065",
    "addr:street":"Boundary Rd",
    "iso:country":"AU",
    "sg:address":"151 Boundary Rd",
    "sg:city":"Bardon",
    "sg:classifiers":[
        {
            "category":"Sports & Exercise",
            "subcategory":"Gym",
            "type":"Entertainment"
        }
    ],
    "sg:phone":"+61 7 3300 6438",
    "sg:postcode":"4065",
    "sg:province":"QLD",
    "sg:tags":[
        "health",
        "fitness"
    ],
    "wof:name":"O&#039;Donnell Ernest",
    "wof:placetype":"venue"
},
  "geometry": {"coordinates":[152.98448181099999,-27.4665851593],"type":"Point"}
}