{
  "type": "Feature",
  "properties": {
    "addr:full":"Shop 56 , Park Beach Plz Coffs Harbour NSW 2450",
    "addr:housenumber":"shop 56",
    "addr:postcode":"2450",
    "addr:street":"Park Beach Plz",
    "iso:country":"AU",
    "sg:address":"Shop 56",
    "sg:city":", Park Beach Plz Coffs Harbour",
    "sg:classifiers":[
        {
            "category":"Personal",
            "subcategory":"Beauty Salon",
            "type":"Services"
        }
    ],
    "sg:phone":"+61 2 6652 5722",
    "sg:postcode":"2450",
    "sg:province":"NSW",
    "sg:tags":[
        "hairdresser"
    ],
    "wof:name":"Time For Hair",
    "wof:placetype":"venue"
},
  "geometry": {"coordinates":[153.13047800000001,-30.285416],"type":"Point"}
}