{
  "type": "Feature",
  "properties": {
    "addr:full":"4 Knuckey Drv Roleystone WA 6111",
    "addr:housenumber":"4",
    "addr:postcode":"6111",
    "addr:street":"Knuckey Drv",
    "iso:country":"AU",
    "sg:address":"4 Knuckey Drv",
    "sg:city":"Roleystone",
    "sg:classifiers":[
        {
            "category":"Utilities",
            "subcategory":"Electric",
            "type":"Services"
        }
    ],
    "sg:phone":"+61 8 9496 1776",
    "sg:postcode":"6111",
    "sg:province":"WA",
    "sg:tags":[
        "electrical",
        "contractor"
    ],
    "wof:name":"Eddys Electrical",
    "wof:placetype":"venue"
},
  "geometry": {"coordinates":[116.06301116900001,-32.1231040955],"type":"Point"}
}