{
  "type": "Feature",
  "properties": {
    "iso:country":"AU",
    "sg:address":"PO Box 225",
    "sg:city":"Kalamunda",
    "sg:classifiers":[
        {
            "category":"Professional",
            "subcategory":"Lawyer & Legal Services",
            "type":"Services"
        }
    ],
    "sg:phone":"+61 8 9257 1245",
    "sg:postcode":"6076",
    "sg:province":"WA",
    "sg:tags":[
        "process",
        "server"
    ],
    "wof:name":"Cannington Process Service",
    "wof:placetype":"venue"
},
  "geometry": {"coordinates":[116.153198242,-32.0055885315],"type":"Point"}
}