{
  "type": "Feature",
  "properties": {
    "addr:full":"Cnr Church, Briens & Boundary Rds North Parramatta NSW 2151",
    "addr:postcode":"2151",
    "iso:country":"AU",
    "sg:address":"Cnr Church, Briens & Boundary Rds",
    "sg:city":"North Parramatta",
    "sg:classifiers":[
        {
            "category":"Fast Food",
            "type":"Food & Drink"
        }
    ],
    "sg:phone":"+61 2 9683 4176",
    "sg:postcode":"2151",
    "sg:province":"NSW",
    "sg:tags":[
        "away",
        "take"
    ],
    "wof:name":"Hungry Jacks Pty Ltd",
    "wof:placetype":"venue"
},
  "geometry": {"coordinates":[150.998336792,-33.7949790955],"type":"Point"}
}