{
  "type": "Feature",
  "properties": {
    "addr:full":"91 Munster Tce North Melbourne VIC 3051",
    "addr:housenumber":"91",
    "addr:postcode":"3051",
    "addr:street":"Munster Tce",
    "iso:country":"AU",
    "sg:address":"91 Munster Tce",
    "sg:city":"North Melbourne",
    "sg:classifiers":[
        {
            "category":"Wholesale",
            "subcategory":"Apparel",
            "type":"Manufacturing & Wholesale Goods"
        }
    ],
    "sg:phone":"+61 3 9322 1820",
    "sg:postcode":"3051",
    "sg:province":"VIC",
    "sg:tags":[
        "wholesaler",
        "mfrs",
        "cap",
        "hat"
    ],
    "sg:website":"http://www.lookdirect.com.au",
    "wof:name":"Look Direct",
    "wof:placetype":"venue"
},
  "geometry": {"coordinates":[144.94267273,-37.8014259338],"type":"Point"}
}