{
  "type": "Feature",
  "properties": {
    "addr:full":"6a Joyce St Pendle Hill NSW 2145",
    "addr:housenumber":"6a",
    "addr:postcode":"2145",
    "addr:street":"Joyce St",
    "iso:country":"AU",
    "sg:address":"6a Joyce St",
    "sg:city":"Pendle Hill",
    "sg:classifiers":[
        {
            "category":"Professional",
            "subcategory":"Accounting & Tax Preparation",
            "type":"Services"
        }
    ],
    "sg:phone":"+61 2 9631 4660",
    "sg:postcode":"2145",
    "sg:province":"NSW",
    "sg:tags":[
        "accountant",
        "auditor"
    ],
    "wof:name":"Micro Nation Pty Ltd",
    "wof:placetype":"venue"
},
  "geometry": {"coordinates":[150.95606994600001,-33.8018035889],"type":"Point"}
}