{
  "type": "Feature",
  "properties": {
    "iso:country":"AU",
    "sg:address":"Shop 14/ 175 Montery Keys Drv",
    "sg:city":"Monterey Keys",
    "sg:classifiers":[
        {
            "category":"Fast Food",
            "type":"Food & Drink"
        }
    ],
    "sg:phone":"+61 7 5573 5506",
    "sg:postcode":"4210",
    "sg:province":"QLD",
    "sg:tags":[
        "away",
        "take"
    ],
    "wof:name":"Monterey Keys Fish & Chips",
    "wof:placetype":"venue"
},
  "geometry": {"coordinates":[153.33319091800001,-27.8832054138],"type":"Point"}
}