{
  "type": "Feature",
  "properties": {
    "iso:country":"AU",
    "sg:address":"Tucker St",
    "sg:city":"Ryde",
    "sg:classifiers":[
        {
            "category":"Social Services",
            "subcategory":"Child Care",
            "type":"Services"
        }
    ],
    "sg:phone":"+61 2 9809 0018",
    "sg:postcode":"2112",
    "sg:province":"NSW",
    "wof:name":"Ryde Occasional Care Centre",
    "wof:placetype":"venue"
},
  "geometry": {"coordinates":[151.106964111,-33.8127441406],"type":"Point"}
}