{
  "type": "Feature",
  "properties": {
    "iso:country":"AU",
    "sg:address":"80 McCrae Drv",
    "sg:city":"Camden",
    "sg:classifiers":[
        {
            "category":"Home & Garden",
            "subcategory":"Building Materials",
            "type":"Retail Goods"
        }
    ],
    "sg:phone":"+61 2 4655 5206",
    "sg:postcode":"2570",
    "sg:province":"NSW",
    "sg:tags":[
        "lawn",
        "cutting",
        "maintenance"
    ],
    "wof:name":"Ducks Cuts",
    "wof:placetype":"venue"
},
  "geometry": {"coordinates":[150.690673828,-34.0775947571],"type":"Point"}
}