{
  "type": "Feature",
  "properties": {
    "addr:full":"129 Bridge St Uralla NSW 2358",
    "addr:housenumber":"129",
    "addr:postcode":"2358",
    "addr:street":"Bridge St",
    "iso:country":"AU",
    "sg:address":"129 Bridge St",
    "sg:city":"Uralla",
    "sg:classifiers":[
        {
            "category":"Retail",
            "subcategory":"Repair Shop",
            "type":"Services"
        }
    ],
    "sg:phone":"+61 2 6778 4062",
    "sg:postcode":"2358",
    "sg:province":"NSW",
    "sg:tags":[
        "machine",
        "repairs",
        "part",
        "dryer",
        "washing"
    ],
    "wof:name":"Howard's Neal Electrical Service",
    "wof:placetype":"venue"
},
  "geometry": {"coordinates":[151.498214722,-30.642950058],"type":"Point"}
}