{
  "type": "Feature",
  "properties": {
    "addr:full":"Shop 7-9 Pinnaroo St Hope Island QLD 4212",
    "addr:housenumber":"shop 7-9",
    "addr:postcode":"4212",
    "addr:street":"Pinnaroo St",
    "iso:country":"AU",
    "sg:address":"Shop 7-9 Pinnaroo St",
    "sg:city":"Hope Island",
    "sg:classifiers":[
        {
            "category":"Personal",
            "subcategory":"Beauty Salon",
            "type":"Services"
        }
    ],
    "sg:phone":"+61 7 5514 0899",
    "sg:postcode":"4212",
    "sg:province":"QLD",
    "sg:tags":[
        "hairdresser"
    ],
    "wof:name":"Vanilla Hair Studio",
    "wof:placetype":"venue"
},
  "geometry": {"coordinates":[153.35144043,-27.8557300568],"type":"Point"}
}