{
  "type": "Feature",
  "properties": {
    "iso:country":"AU",
    "sg:address":"8-10 Marine Pde",
    "sg:city":"Ocean Grove",
    "sg:classifiers":[
        {
            "category":"Retail",
            "subcategory":"Auto Repair",
            "type":"Services"
        }
    ],
    "sg:phone":"+61 3 5255 1990",
    "sg:postcode":"3226",
    "sg:province":"VIC",
    "sg:tags":[
        "repairer",
        "motor",
        "engineer"
    ],
    "wof:name":"Niss Serv",
    "wof:placetype":"venue"
},
  "geometry": {"coordinates":[144.537964,-38.251022],"type":"Point"}
}