{
  "type": "Feature",
  "properties": {
    "addr:full":"24 Cary St Wyoming NSW 2250",
    "addr:housenumber":"24",
    "addr:postcode":"2250",
    "addr:street":"Cary St",
    "iso:country":"AU",
    "sg:address":"24 Cary St",
    "sg:city":"Wyoming",
    "sg:classifiers":[
        {
            "category":"Retail",
            "subcategory":"Veterinary Services",
            "type":"Services"
        }
    ],
    "sg:phone":"+61 2 4325 2374",
    "sg:postcode":"2250",
    "sg:province":"NSW",
    "sg:tags":[
        "surgeon"
    ],
    "wof:name":"Thompson Geoff Dr",
    "wof:placetype":"venue"
},
  "geometry": {"coordinates":[151.348678589,-33.4116096497],"type":"Point"}
}