{
  "type": "Feature",
  "properties": {
    "addr:full":"Shop 3/ 459 Old Cleveland Rd Camp Hill QLD 4152",
    "addr:housenumber":"shop 3 / 459",
    "addr:postcode":"4152",
    "addr:street":"Old Cleveland Rd",
    "iso:country":"AU",
    "sg:address":"Shop 3/ 459 Old Cleveland Rd",
    "sg:city":"Camp Hill",
    "sg:classifiers":[
        {
            "category":"Personal",
            "subcategory":"Hair Removal",
            "type":"Services"
        }
    ],
    "sg:phone":"+61 7 3843 0999",
    "sg:postcode":"4152",
    "sg:province":"QLD",
    "wof:name":"Absolute Skin & Body Clinic",
    "wof:placetype":"venue"
},
  "geometry": {"coordinates":[153.06674194300001,-27.4918899536],"type":"Point"}
}