{
  "type": "Feature",
  "properties": {
    "iso:country":"AU",
    "sg:address":"55 Alambie Rd",
    "sg:city":"Allambie",
    "sg:classifiers":[
        {
            "category":"Professional",
            "subcategory":"Employment Agencies",
            "type":"Services"
        }
    ],
    "sg:phone":"+61 408 860 198",
    "sg:postcode":"2100",
    "sg:province":"NSW",
    "sg:tags":[
        "occupational",
        "therapist"
    ],
    "wof:name":"Helen Stone Paediatric",
    "wof:placetype":"venue"
},
  "geometry": {"coordinates":[151.25875854500001,-33.7703819275],"type":"Point"}
}