{
  "type": "Feature",
  "properties": {
    "addr:full":"570 George St Sydney NSW 2000",
    "addr:housenumber":"570",
    "addr:postcode":"2000",
    "addr:street":"George St",
    "iso:country":"AU",
    "sg:address":"570 George St",
    "sg:city":"Sydney",
    "sg:classifiers":[
        {
            "category":"Utilities",
            "subcategory":"Natural Gas",
            "type":"Services"
        }
    ],
    "sg:phone":"+61 13 15 35",
    "sg:postcode":"2000",
    "sg:province":"NSW",
    "sg:tags":[
        "supplier"
    ],
    "sg:website":"http://www.energy.com.au",
    "wof:name":"Energy Australia",
    "wof:placetype":"venue"
},
  "geometry": {"coordinates":[151.20701599099999,-33.8742179871],"type":"Point"}
}