{
  "type": "Feature",
  "properties": {
    "addr:full":"26-28 Hewish Rd Croydon VIC 3136",
    "addr:housenumber":"26-28",
    "addr:postcode":"3136",
    "addr:street":"Hewish Rd",
    "iso:country":"AU",
    "sg:address":"26-28 Hewish Rd",
    "sg:city":"Croydon",
    "sg:classifiers":[
        {
            "category":"Shopping",
            "subcategory":"Clothing, Apparel, & Fashions",
            "type":"Retail Goods"
        }
    ],
    "sg:phone":"+61 3 9725 7921",
    "sg:postcode":"3136",
    "sg:province":"VIC",
    "sg:tags":[
        "recycled",
        "clothing"
    ],
    "wof:name":"Brotherhood of St Laurence",
    "wof:placetype":"venue"
},
  "geometry": {"coordinates":[145.28137207,-37.7961387634],"type":"Point"}
}