{
  "type": "Feature",
  "properties": {
    "addr:full":"2 Station St Katoomba NSW 2780",
    "addr:housenumber":"2",
    "addr:postcode":"2780",
    "addr:street":"Station St",
    "iso:country":"AU",
    "sg:address":"2 Station St",
    "sg:city":"Katoomba",
    "sg:classifiers":[
        {
            "category":"Social Services",
            "subcategory":"Child Care",
            "type":"Services"
        }
    ],
    "sg:phone":"+61 2 4780 5688",
    "sg:postcode":"2780",
    "sg:province":"NSW",
    "wof:name":"Family Day Care Scheme",
    "wof:placetype":"venue"
},
  "geometry": {"coordinates":[150.313354492,-33.7106590271],"type":"Point"}
}