{
  "type": "Feature",
  "properties": {
    "iso:country":"AU",
    "sg:address":"2/ 1 Thorsborne St",
    "sg:city":"Beenleigh",
    "sg:classifiers":[
        {
            "category":"Retail",
            "subcategory":"Auto Repair",
            "type":"Services"
        }
    ],
    "sg:phone":"+61 7 3287 3499",
    "sg:postcode":"4207",
    "sg:province":"QLD",
    "sg:tags":[
        "repairer",
        "motor",
        "engineer"
    ],
    "wof:name":"H.S. Motors",
    "wof:placetype":"venue"
},
  "geometry": {"coordinates":[153.19155883799999,-27.7130203247],"type":"Point"}
}