{
  "type": "Feature",
  "properties": {
    "addr:full":"20 Beatty Ave Armadale VIC 3143",
    "addr:housenumber":"20",
    "addr:postcode":"3143",
    "addr:street":"Beatty Ave",
    "iso:country":"AU",
    "sg:address":"20 Beatty Ave",
    "sg:city":"Armadale",
    "sg:classifiers":[
        {
            "category":"Health Services",
            "subcategory":"Chiropractor",
            "type":"Services"
        }
    ],
    "sg:phone":"+61 3 9822 9900",
    "sg:postcode":"3143",
    "sg:province":"VIC",
    "wof:name":"Beatty Avenue-Toorak Station",
    "wof:placetype":"venue"
},
  "geometry": {"coordinates":[145.01409912099999,-37.8504142761],"type":"Point"}
}