{
  "type": "Feature",
  "properties": {
    "addr:full":"29 Bramcote St Chermside West QLD 4032",
    "addr:housenumber":"29",
    "addr:postcode":"4032",
    "addr:street":"Bramcote St",
    "iso:country":"AU",
    "sg:address":"29 Bramcote St",
    "sg:city":"Chermside West",
    "sg:classifiers":[
        {
            "category":"Utilities",
            "subcategory":"Electric",
            "type":"Services"
        }
    ],
    "sg:phone":"+61 7 3861 5167",
    "sg:postcode":"4032",
    "sg:province":"QLD",
    "sg:tags":[
        "electrical",
        "contractor"
    ],
    "wof:name":"Peter Johnson",
    "wof:placetype":"venue"
},
  "geometry": {"coordinates":[153.020386,-27.390121],"type":"Point"}
}