{
  "type": "Feature",
  "properties": {
    "addr:full":"Shop 26 Sunray Vlg Rockingham WA 6168",
    "addr:housenumber":"shop 26",
    "addr:postcode":"6168",
    "addr:street":"Sunray Vlg",
    "iso:country":"AU",
    "sg:address":"Shop 26 Sunray Vlg",
    "sg:city":"Rockingham",
    "sg:classifiers":[
        {
            "category":"Shopping",
            "subcategory":"Jewelry",
            "type":"Retail Goods"
        }
    ],
    "sg:phone":"+61 8 9592 1446",
    "sg:postcode":"6168",
    "sg:province":"WA",
    "sg:tags":[
        "jeweller"
    ],
    "wof:name":"Lovell Jewellers",
    "wof:placetype":"venue"
},
  "geometry": {"coordinates":[115.741028,-32.280399],"type":"Point"}
}