{
  "type": "Feature",
  "properties": {
    "addr:full":"2/774 Canning Hwy Applecross WA 6153",
    "addr:housenumber":"/ 774",
    "addr:postcode":"6153",
    "addr:street":"Canning Hwy",
    "iso:country":"AU",
    "sg:address":"2/774 Canning Hwy",
    "sg:city":"Applecross",
    "sg:classifiers":[
        {
            "category":"Communications",
            "type":"Services"
        }
    ],
    "sg:phone":"+61 414 406 108",
    "sg:postcode":"6153",
    "sg:province":"WA",
    "sg:tags":[
        "translation"
    ],
    "wof:name":"Japanese Language Specialist",
    "wof:placetype":"venue"
},
  "geometry": {"coordinates":[115.84446,-32.014687],"type":"Point"}
}