{
  "type": "Feature",
  "properties": {
    "addr:full":"Lot2/ Sturt Hwy Nuriootpa SA 5355",
    "addr:postcode":"5355",
    "addr:street":"Sturt Hwy",
    "iso:country":"AU",
    "sg:address":"Lot2/ Sturt Hwy",
    "sg:city":"Nuriootpa",
    "sg:classifiers":[
        {
            "category":"Building & Trades",
            "subcategory":"Equipment Rental",
            "type":"Services"
        }
    ],
    "sg:phone":"+61 8 8562 2063",
    "sg:postcode":"5355",
    "sg:province":"SA",
    "sg:tags":[
        "crane",
        "hire"
    ],
    "wof:name":"Impact Rigging & Crane Services",
    "wof:placetype":"venue"
},
  "geometry": {"coordinates":[138.98794555699999,-34.46068573],"type":"Point"}
}