{
  "type": "Feature",
  "properties": {
    "addr:full":"9 Success St Acacia Ridge QLD 4110",
    "addr:housenumber":"9",
    "addr:postcode":"4110",
    "addr:street":"Success St",
    "iso:country":"AU",
    "sg:address":"9 Success St",
    "sg:city":"Acacia Ridge",
    "sg:classifiers":[
        {
            "category":"Structure",
            "subcategory":"Factory",
            "type":"Public Place"
        }
    ],
    "sg:phone":"+61 7 3272 7550",
    "sg:postcode":"4110",
    "sg:province":"QLD",
    "sg:tags":[
        "seating",
        "system"
    ],
    "wof:name":"Styleride Seating Systems",
    "wof:placetype":"venue"
},
  "geometry": {"coordinates":[153.00813293499999,-27.5812759399],"type":"Point"}
}