{
  "type": "Feature",
  "properties": {
    "addr:full":"18 Millhouse St Millicent SA 5280",
    "addr:housenumber":"18",
    "addr:postcode":"5280",
    "addr:street":"Millhouse St",
    "iso:country":"AU",
    "sg:address":"18 Millhouse St",
    "sg:city":"Millicent",
    "sg:classifiers":[
        {
            "category":"Utilities",
            "subcategory":"Electric",
            "type":"Services"
        }
    ],
    "sg:phone":"+61 8 8733 2951",
    "sg:postcode":"5280",
    "sg:province":"SA",
    "sg:tags":[
        "electrical",
        "contractor"
    ],
    "wof:name":"Wally's Electrical Service",
    "wof:placetype":"venue"
},
  "geometry": {"coordinates":[140.34410099999999,-37.599003],"type":"Point"}
}