{
  "type": "Feature",
  "properties": {
    "addr:full":"Katanning-Dumbleyung Rd Glencoe WA 6316",
    "addr:postcode":"6316",
    "addr:street":"Katanning-Dumbleyung Rd",
    "iso:country":"AU",
    "sg:address":"Katanning-Dumbleyung Rd",
    "sg:city":"Glencoe",
    "sg:classifiers":[
        {
            "category":"Farming",
            "subcategory":"Farm",
            "type":"Manufacturing & Wholesale Goods"
        }
    ],
    "sg:phone":"+61 8 9822 7035",
    "sg:postcode":"6316",
    "sg:province":"WA",
    "sg:tags":[
        "farmer"
    ],
    "wof:name":"R M & E H Crosby",
    "wof:placetype":"venue"
},
  "geometry": {"coordinates":[117.624450684,-33.5044059753],"type":"Point"}
}