{
  "type": "Feature",
  "properties": {
    "addr:full":"Shop 10- 20 Albert St Taree NSW 2430",
    "addr:housenumber":"shop 10 20",
    "addr:postcode":"2430",
    "addr:street":"Albert St",
    "iso:country":"AU",
    "sg:address":"Shop 10- 20 Albert St",
    "sg:city":"Taree",
    "sg:classifiers":[
        {
            "category":"Education",
            "subcategory":"Music School",
            "type":"Public Place"
        }
    ],
    "sg:phone":"+61 2 6551 5067",
    "sg:postcode":"2430",
    "sg:province":"NSW",
    "sg:tags":[
        "teacher"
    ],
    "wof:name":"Bass 'n' Blues Music Professionals",
    "wof:placetype":"venue"
},
  "geometry": {"coordinates":[152.46087600000001,-31.911144],"type":"Point"}
}