{
  "type": "Feature",
  "properties": {
    "addr:full":"Head Office Level 1 -75 Doncaster Road Balwyn VIC 3103",
    "addr:housenumber":"-75",
    "addr:postcode":"3103",
    "addr:street":"Doncaster Road",
    "iso:country":"AU",
    "sg:address":"Head Office Level 1 -75 Doncaster Road",
    "sg:city":"Balwyn",
    "sg:classifiers":[
        {
            "category":"Retail",
            "subcategory":"Auto Repair",
            "type":"Services"
        }
    ],
    "sg:phone":"+61 1300 728 584",
    "sg:postcode":"3103",
    "sg:province":"VIC",
    "sg:tags":[
        "beater",
        "painter",
        "panel"
    ],
    "wof:name":"Complete Collision Group",
    "wof:placetype":"venue"
},
  "geometry": {"coordinates":[145.071212769,-37.7925682068],"type":"Point"}
}