{
  "type": "Feature",
  "properties": {
    "addr:full":"215 Newcastle Rd East Maitland NSW 2323",
    "addr:housenumber":"215",
    "addr:postcode":"2323",
    "addr:street":"Newcastle Rd",
    "iso:country":"AU",
    "sg:address":"215 Newcastle Rd",
    "sg:city":"East Maitland",
    "sg:classifiers":[
        {
            "category":"Travel",
            "subcategory":"Travel Agent",
            "type":"Entertainment"
        }
    ],
    "sg:phone":"+61 2 4933 6777",
    "sg:postcode":"2323",
    "sg:province":"NSW",
    "sg:tags":[
        "consultant"
    ],
    "wof:name":"Andys World Travel",
    "wof:placetype":"venue"
},
  "geometry": {"coordinates":[151.58648681599999,-32.7524909973],"type":"Point"}
}