{
  "type": "Feature",
  "properties": {
    "iso:country":"AU",
    "sg:address":"21 Holmes Rd",
    "sg:city":"Moonee Ponds",
    "sg:classifiers":[
        {
            "category":"Personal",
            "subcategory":"Beauty Salon",
            "type":"Services"
        }
    ],
    "sg:phone":"+61 3 9375 3788",
    "sg:postcode":"3039",
    "sg:province":"VIC",
    "sg:tags":[
        "hairdresser"
    ],
    "wof:name":"Vandio Hair & Beauty Studio",
    "wof:placetype":"venue"
},
  "geometry": {"coordinates":[144.91842700000001,-37.766579],"type":"Point"}
}