{
  "type": "Feature",
  "properties": {
    "addr:full":"36 Regent St Kensington SA 5068",
    "addr:housenumber":"36",
    "addr:postcode":"5068",
    "addr:street":"Regent St",
    "iso:country":"AU",
    "sg:address":"36 Regent St",
    "sg:city":"Kensington",
    "sg:classifiers":[
        {
            "category":"Shopping",
            "subcategory":"Computers & Home Electronics",
            "type":"Retail Goods"
        }
    ],
    "sg:phone":"+61 8 8332 6513",
    "sg:postcode":"5068",
    "sg:province":"SA",
    "sg:tags":[
        "hardware",
        "equipment"
    ],
    "wof:name":"P.C. Computers",
    "wof:placetype":"venue"
},
  "geometry": {"coordinates":[138.64646911599999,-34.9226036072],"type":"Point"}
}