{
  "type": "Feature",
  "properties": {
    "addr:full":"1109 Stockleigh Rd Logan Village QLD 4207",
    "addr:postcode":"1109;4207",
    "addr:street":"Stockleigh Rd",
    "iso:country":"AU",
    "sg:address":"1109 Stockleigh Rd",
    "sg:city":"Logan Village",
    "sg:classifiers":[
        {
            "category":"Shopping",
            "subcategory":"Gifts & Souvenirs",
            "type":"Retail Goods"
        }
    ],
    "sg:phone":"+61 7 5546 3065",
    "sg:postcode":"4207",
    "sg:province":"QLD",
    "sg:tags":[
        "shop",
        "supply"
    ],
    "wof:name":"Subang Pty Ltd",
    "wof:placetype":"venue"
},
  "geometry": {"coordinates":[153.08987426799999,-27.7771263123],"type":"Point"}
}