{
  "type": "Feature",
  "properties": {
    "iso:country":"AU",
    "sg:address":"Bass St",
    "sg:city":"Flinders",
    "sg:classifiers":[
        {
            "category":"Social Services",
            "subcategory":"Child Care",
            "type":"Services"
        }
    ],
    "sg:phone":"+61 3 5983 5595",
    "sg:postcode":"3929",
    "sg:province":"VIC",
    "sg:tags":[
        "support",
        "health"
    ],
    "wof:name":"Maternal & Child Health Centres",
    "wof:placetype":"venue"
},
  "geometry": {"coordinates":[145.01670837399999,-38.4750404358],"type":"Point"}
}