{
  "type": "Feature",
  "properties": {
    "iso:country":"AU",
    "sg:address":"46 Knight St",
    "sg:city":"North Rockhampton",
    "sg:classifiers":[
        {
            "category":"Home & Garden",
            "subcategory":"Hardware",
            "type":"Retail Goods"
        }
    ],
    "sg:phone":"+61 7 4928 4488",
    "sg:postcode":"4701",
    "sg:province":"QLD",
    "sg:tags":[
        "tarpaulin"
    ],
    "wof:name":"Bell's Canvas",
    "wof:placetype":"venue"
},
  "geometry": {"coordinates":[150.51380920400001,-23.3603744507],"type":"Point"}
}