{
  "type": "Feature",
  "properties": {
    "addr:full":"38 Benelong Rd Cremorne NSW 2090",
    "addr:housenumber":"38",
    "addr:postcode":"2090",
    "addr:street":"Benelong Rd",
    "iso:country":"AU",
    "sg:address":"38 Benelong Rd",
    "sg:city":"Cremorne",
    "sg:classifiers":[
        {
            "category":"Arena",
            "subcategory":"Sports Club",
            "type":"Entertainment"
        }
    ],
    "sg:phone":"+61 2 9953 3239",
    "sg:postcode":"2090",
    "sg:province":"NSW",
    "sg:tags":[
        "defence",
        "supply",
        "self",
        "instruction",
        "martial art"
    ],
    "wof:name":"Safety Strategies",
    "wof:placetype":"venue"
},
  "geometry": {"coordinates":[151.229003906,-33.8261108398],"type":"Point"}
}