{
  "type": "Feature",
  "properties": {
    "addr:full":"Chatswood Rd Daisy Hill QLD 4127",
    "addr:postcode":"4127",
    "addr:street":"Chatswood Rd",
    "iso:country":"AU",
    "sg:address":"Chatswood Rd",
    "sg:city":"Daisy Hill",
    "sg:classifiers":[
        {
            "category":"Social Services",
            "subcategory":"Child Care",
            "type":"Services"
        }
    ],
    "sg:phone":"+61 7 3808 6657",
    "sg:postcode":"4127",
    "sg:province":"QLD",
    "wof:name":"Family Day Care Schemes",
    "wof:placetype":"venue"
},
  "geometry": {"coordinates":[153.152954102,-27.6357440948],"type":"Point"}
}