{
  "type": "Feature",
  "properties": {
    "addr:full":"42 Urben St Urbenville NSW 2475",
    "addr:housenumber":"42",
    "addr:postcode":"2475",
    "addr:street":"Urben St",
    "iso:country":"AU",
    "sg:address":"42 Urben St",
    "sg:city":"Urbenville",
    "sg:classifiers":[
        {
            "category":"Shopping",
            "subcategory":"Crafts & Fabrics",
            "type":"Retail Goods"
        }
    ],
    "sg:phone":"+61 2 6634 1201",
    "sg:postcode":"2475",
    "sg:province":"NSW",
    "sg:tags":[
        "supply"
    ],
    "wof:name":"Urbenville Arts & Crafts",
    "wof:placetype":"venue"
},
  "geometry": {"coordinates":[152.547149658,-28.4738273621],"type":"Point"}
}