{
  "type": "Feature",
  "properties": {
    "addr:full":"Cnr Boundry & WIndsor Rds Box Hill NSW 2765",
    "addr:postcode":"2765",
    "addr:street":"Cnr",
    "iso:country":"AU",
    "sg:address":"Cnr Boundry & WIndsor Rds",
    "sg:city":"Box Hill",
    "sg:classifiers":[
        {
            "category":"Wholesale",
            "subcategory":"Machinery & Supplies",
            "type":"Manufacturing & Wholesale Goods"
        }
    ],
    "sg:phone":"+61 2 9627 7333",
    "sg:postcode":"2765",
    "sg:province":"NSW",
    "sg:tags":[
        "agricultural"
    ],
    "wof:name":"Auzquip Pty Ltd",
    "wof:placetype":"venue"
},
  "geometry": {"coordinates":[150.893234253,-33.6623153687],"type":"Point"}
}