{
  "type": "Feature",
  "properties": {
    "addr:full":"1 Glebe Point Rd Glebe NSW 2037",
    "addr:housenumber":"1",
    "addr:postcode":"2037",
    "addr:street":"Glebe Point Rd",
    "iso:country":"AU",
    "sg:address":"1 Glebe Point Rd",
    "sg:city":"Glebe",
    "sg:classifiers":[
        {
            "category":"Travel",
            "subcategory":"Travel Agent",
            "type":"Entertainment"
        }
    ],
    "sg:phone":"+61 2 9660 5736",
    "sg:postcode":"2037",
    "sg:province":"NSW",
    "sg:tags":[
        "consultant"
    ],
    "wof:name":"Alfa Travel Agency Pty Ltd",
    "wof:placetype":"venue"
},
  "geometry": {"coordinates":[151.19305419899999,-33.8844146729],"type":"Point"}
}