{
  "type": "Feature",
  "properties": {
    "addr:full":"19 Penola Rd Mt Gambier SA 5290",
    "addr:housenumber":"19",
    "addr:postcode":"5290",
    "addr:street":"Penola Rd",
    "iso:country":"AU",
    "sg:address":"19 Penola Rd",
    "sg:city":"Mt Gambier",
    "sg:classifiers":[
        {
            "category":"Education",
            "subcategory":"Special Training",
            "type":"Public Place"
        }
    ],
    "sg:phone":"+61 8 8723 1050",
    "sg:postcode":"5290",
    "sg:province":"SA",
    "sg:tags":[
        "development"
    ],
    "wof:name":"Serde Inc.",
    "wof:placetype":"venue"
},
  "geometry": {"coordinates":[140.78173799999999,-37.826057],"type":"Point"}
}