{
  "type": "Feature",
  "properties": {
    "addr:full":"17 Lillypilly Pl Mooloolaba QLD 4557",
    "addr:housenumber":"17",
    "addr:postcode":"4557",
    "addr:street":"Lillypilly Pl",
    "iso:country":"AU",
    "sg:address":"17 Lillypilly Pl",
    "sg:city":"Mooloolaba",
    "sg:classifiers":[
        {
            "category":"Shopping",
            "subcategory":"Computers & Home Electronics",
            "type":"Retail Goods"
        }
    ],
    "sg:phone":"+61 7 5444 8122",
    "sg:postcode":"4557",
    "sg:province":"QLD",
    "sg:tags":[
        "hi-fi",
        "equipment"
    ],
    "wof:name":"Audio Dreams Australia",
    "wof:placetype":"venue"
},
  "geometry": {"coordinates":[153.10534668,-26.6773548126],"type":"Point"}
}