{
  "type": "Feature",
  "properties": {
    "addr:full":"10 Crompton Rd Rockingham WA 6168",
    "addr:housenumber":"10",
    "addr:postcode":"6168",
    "addr:street":"Crompton Rd",
    "iso:country":"AU",
    "sg:address":"10 Crompton Rd",
    "sg:city":"Rockingham",
    "sg:classifiers":[
        {
            "category":"Professional",
            "subcategory":"Employment Agencies",
            "type":"Services"
        }
    ],
    "sg:phone":"+61 8 9592 2949",
    "sg:postcode":"6168",
    "sg:province":"WA",
    "wof:name":"South Metropolitan Youth Link",
    "wof:placetype":"venue"
},
  "geometry": {"coordinates":[115.76561700000001,-32.275105],"type":"Point"}
}