{
  "type": "Feature",
  "properties": {
    "addr:full":"2/ 5 Cranbrook Rd Batemans Bay NSW 2536",
    "addr:housenumber":"/ 5",
    "addr:postcode":"2536",
    "addr:street":"Cranbrook Rd",
    "iso:country":"AU",
    "sg:address":"2/ 5 Cranbrook Rd",
    "sg:city":"Batemans Bay",
    "sg:classifiers":[
        {
            "category":"Professional",
            "subcategory":"Detective & Security Services",
            "type":"Services"
        }
    ],
    "sg:phone":"+61 2 4472 4469",
    "sg:postcode":"2536",
    "sg:province":"NSW",
    "sg:tags":[
        "consultant",
        "system"
    ],
    "wof:name":"Euro Car Systems & Communications Aust.",
    "wof:placetype":"venue"
},
  "geometry": {"coordinates":[150.17494201700001,-35.7201118469],"type":"Point"}
}