{
  "type": "Feature",
  "properties": {
    "iso:country":"AU",
    "sg:address":"15 Duncan St",
    "sg:city":"Sturt",
    "sg:classifiers":[
        {
            "category":"Shopping",
            "type":"Retail Goods"
        }
    ],
    "sg:phone":"+61 402 167 530",
    "sg:postcode":"5047",
    "sg:province":"SA",
    "sg:tags":[
        "equipment",
        "safety",
        "accessory"
    ],
    "wof:name":"Safety Management Systems",
    "wof:placetype":"venue"
},
  "geometry": {"coordinates":[138.552948,-35.019222],"type":"Point"}
}