{
  "type": "Feature",
  "properties": {
    "addr:full":"PO Box 1278 Tully QLD 4854",
    "addr:postcode":"4854",
    "iso:country":"AU",
    "sg:address":"PO Box 1278",
    "sg:city":"Tully",
    "sg:classifiers":[
        {
            "category":"Building & Trades",
            "subcategory":"Construction",
            "type":"Services"
        }
    ],
    "sg:phone":"+61 7 4066 9001",
    "sg:postcode":"4854",
    "sg:province":"QLD",
    "sg:tags":[
        "earth",
        "excavating",
        "moving",
        "contractor"
    ],
    "wof:name":"Marshall's Earthmoving",
    "wof:placetype":"venue"
},
  "geometry": {"coordinates":[145.93263244600001,-17.933889389],"type":"Point"}
}