{
  "type": "Feature",
  "properties": {
    "addr:full":"11/ 369 Victoria St Wetherill Park NSW 2164",
    "addr:housenumber":"11 / 369",
    "addr:postcode":"2164",
    "addr:street":"Victoria St",
    "iso:country":"AU",
    "sg:address":"11/ 369 Victoria St",
    "sg:city":"Wetherill Park",
    "sg:classifiers":[
        {
            "category":"Autos & Motor Vehicles",
            "subcategory":"Auto Supplies",
            "type":"Retail Goods"
        }
    ],
    "sg:phone":"+61 2 9604 6799",
    "sg:postcode":"2164",
    "sg:province":"NSW",
    "sg:tags":[
        "paint",
        "automotive"
    ],
    "wof:name":"Marouns Auto Panel & Paint",
    "wof:placetype":"venue"
},
  "geometry": {"coordinates":[150.90513610799999,-33.8463630676],"type":"Point"}
}