{
  "type": "Feature",
  "properties": {
    "addr:full":"31 Loudon Rd Port Augusta SA 5700",
    "addr:housenumber":"31",
    "addr:postcode":"5700",
    "addr:street":"Loudon Rd",
    "iso:country":"AU",
    "sg:address":"31 Loudon Rd",
    "sg:city":"Port Augusta",
    "sg:classifiers":[
        {
            "category":"Organizations",
            "subcategory":"Community Association",
            "type":"Services"
        }
    ],
    "sg:phone":"+61 8 8642 6243",
    "sg:postcode":"5700",
    "sg:province":"SA",
    "sg:tags":[
        "organisation",
        "family",
        "welfare"
    ],
    "wof:name":"St Vincent De Paul Society",
    "wof:placetype":"venue"
},
  "geometry": {"coordinates":[137.7578125,-32.482875824],"type":"Point"}
}