{
  "type": "Feature",
  "properties": {
    "addr:full":"28 Glenwood Drv Thornton NSW 2322",
    "addr:housenumber":"28",
    "addr:postcode":"2322",
    "addr:street":"Glenwood Drv",
    "iso:country":"AU",
    "sg:address":"28 Glenwood Drv",
    "sg:city":"Thornton",
    "sg:classifiers":[
        {
            "category":"Home & Garden",
            "subcategory":"Hardware",
            "type":"Retail Goods"
        }
    ],
    "sg:phone":"+61 2 4966 4079",
    "sg:postcode":"2322",
    "sg:province":"NSW",
    "sg:tags":[
        "generating",
        "set",
        "generator"
    ],
    "wof:name":"JDC-Thomson Electrical Systems",
    "wof:placetype":"venue"
},
  "geometry": {"coordinates":[151.63331604000001,-32.7884178162],"type":"Point"}
}