{
  "type": "Feature",
  "properties": {
    "iso:country":"AU",
    "sg:address":"215- 219 High St",
    "sg:city":"Kew",
    "sg:classifiers":[
        {
            "category":"Food & Beverages",
            "subcategory":"Fruits & Vegetables",
            "type":"Retail Goods"
        }
    ],
    "sg:phone":"+61 3 9853 7762",
    "sg:postcode":"3101",
    "sg:province":"VIC",
    "sg:tags":[
        "greengrocer",
        "fruiterer"
    ],
    "wof:name":"Toscano's Of Kew",
    "wof:placetype":"venue"
},
  "geometry": {"coordinates":[145.03257751500001,-37.8060073853],"type":"Point"}
}