{
  "type": "Feature",
  "properties": {
    "iso:country":"AU",
    "sg:address":"2/ 41 Jones St",
    "sg:city":"Kingswood",
    "sg:classifiers":[
        {
            "category":"Autos & Motor Vehicles",
            "subcategory":"Automobile Sales",
            "type":"Retail Goods"
        }
    ],
    "sg:phone":"+61 2 4736 6881",
    "sg:postcode":"2747",
    "sg:province":"NSW",
    "sg:tags":[
        "car",
        "new"
    ],
    "wof:name":"Action Auto Brokers",
    "wof:placetype":"venue"
},
  "geometry": {"coordinates":[150.723052978,-33.7644729614],"type":"Point"}
}