{
  "type": "Feature",
  "properties": {
    "addr:full":"Unit 10/ 49 Waterloo St Joondanna WA 6060",
    "addr:housenumber":"/ 49",
    "addr:postcode":"6060",
    "addr:street":"Waterloo St",
    "iso:country":"AU",
    "sg:address":"Unit 10/ 49 Waterloo St",
    "sg:city":"Joondanna",
    "sg:classifiers":[
        {
            "category":"Banks & Credit Unions",
            "subcategory":"Bank",
            "type":"Services"
        }
    ],
    "sg:phone":"+61 8 9443 4388",
    "sg:postcode":"6060",
    "sg:province":"WA",
    "sg:tags":[
        "broker",
        "mortgage"
    ],
    "wof:name":"Freymann Britta",
    "wof:placetype":"venue"
},
  "geometry": {"coordinates":[115.82936859100001,-31.9092006683],"type":"Point"}
}