{
  "type": "Feature",
  "properties": {
    "iso:country":"AU",
    "sg:address":"53 Langridge St",
    "sg:city":"Collingwood",
    "sg:classifiers":[
        {
            "category":"Professional",
            "subcategory":"Art Services",
            "type":"Services"
        }
    ],
    "sg:phone":"+61 3 9417 4094",
    "sg:postcode":"3066",
    "sg:province":"VIC",
    "sg:tags":[
        "graphic",
        "designer"
    ],
    "wof:name":"Mustard Design",
    "wof:placetype":"venue"
},
  "geometry": {"coordinates":[144.98626709000001,-37.8067169189],"type":"Point"}
}