{
  "type": "Feature",
  "properties": {
    "iso:country":"AU",
    "sg:address":"70 Males Rd",
    "sg:city":"Moorooduc",
    "sg:classifiers":[
        {
            "category":"Manufacturing",
            "subcategory":"Rubber & Plastics",
            "type":"Manufacturing & Wholesale Goods"
        }
    ],
    "sg:phone":"+61 3 5978 8524",
    "sg:postcode":"3933",
    "sg:province":"VIC",
    "sg:tags":[
        "wholesaler",
        "product",
        "mfrs"
    ],
    "wof:name":"About Moulds",
    "wof:placetype":"venue"
},
  "geometry": {"coordinates":[145.08326721200001,-38.2581748962],"type":"Point"}
}