{
  "type": "Feature",
  "properties": {
    "addr:full":"256 York St Sale VIC 3850",
    "addr:housenumber":"256",
    "addr:postcode":"3850",
    "addr:street":"York St",
    "iso:country":"AU",
    "sg:address":"256 York St",
    "sg:city":"Sale",
    "sg:classifiers":[
        {
            "category":"Building & Trades",
            "subcategory":"Cleaning & Sanitation",
            "type":"Services"
        }
    ],
    "sg:phone":"+61 438 338 347",
    "sg:postcode":"3850",
    "sg:province":"VIC",
    "sg:tags":[
        "duct"
    ],
    "wof:name":"Gippsland Clean Air",
    "wof:placetype":"venue"
},
  "geometry": {"coordinates":[147.068267822,-38.1034851074],"type":"Point"}
}