{
  "type": "Feature",
  "properties": {
    "addr:full":"10 Orr St Queenstown TAS 7467",
    "addr:housenumber":"10",
    "addr:postcode":"7467",
    "addr:street":"Orr St",
    "iso:country":"AU",
    "sg:address":"10 Orr St",
    "sg:city":"Queenstown",
    "sg:classifiers":[
        {
            "category":"Fast Food",
            "type":"Food & Drink"
        }
    ],
    "sg:phone":"+61 3 6471 1152",
    "sg:postcode":"7467",
    "sg:province":"TAS",
    "sg:tags":[
        "away",
        "take"
    ],
    "wof:name":"Miners Cribroom",
    "wof:placetype":"venue"
},
  "geometry": {"coordinates":[145.55540466299999,-42.0797157288],"type":"Point"}
}