{
  "type": "Feature",
  "properties": {
    "addr:full":"115 - 117 Winter St Ballarat VIC 3350",
    "addr:housenumber":"117",
    "addr:postcode":"3350",
    "addr:street":"Winter St",
    "iso:country":"AU",
    "sg:address":"115 - 117 Winter St",
    "sg:city":"Ballarat",
    "sg:classifiers":[
        {
            "category":"Personal",
            "subcategory":"Day Spa",
            "type":"Services"
        }
    ],
    "sg:phone":"+61 3 5336 1343",
    "sg:postcode":"3350",
    "sg:province":"VIC",
    "wof:name":"Serenity Tranquility",
    "wof:placetype":"venue"
},
  "geometry": {"coordinates":[143.83088699999999,-37.570435],"type":"Point"}
}