{
  "type": "Feature",
  "properties": {
    "addr:full":"342 Midland Hwy Epsom VIC 3551",
    "addr:housenumber":"342",
    "addr:postcode":"3551",
    "addr:street":"Midland Hwy",
    "iso:country":"AU",
    "sg:address":"342 Midland Hwy",
    "sg:city":"Epsom",
    "sg:classifiers":[
        {
            "category":"Manufacturing",
            "subcategory":"Tools & Machinery",
            "type":"Manufacturing & Wholesale Goods"
        }
    ],
    "sg:phone":"+61 3 5448 8999",
    "sg:postcode":"3551",
    "sg:province":"VIC",
    "sg:tags":[
        "earth",
        "excavating",
        "moving",
        "equipment"
    ],
    "wof:name":"Bendigo Excavators",
    "wof:placetype":"venue"
},
  "geometry": {"coordinates":[144.31919860799999,-36.6901092529],"type":"Point"}
}