{
  "type": "Feature",
  "properties": {
    "addr:full":"Shed 2D 424 Bilsen Rd Geebung QLD 4034",
    "addr:housenumber":"2d",
    "addr:postcode":"424;4034",
    "addr:street":"Bilsen Rd",
    "iso:country":"AU",
    "sg:address":"Shed 2D 424 Bilsen Rd",
    "sg:city":"Geebung",
    "sg:classifiers":[
        {
            "category":"Shopping",
            "subcategory":"Antiques",
            "type":"Retail Goods"
        }
    ],
    "sg:phone":"+61 7 3865 8496",
    "sg:postcode":"4034",
    "sg:province":"QLD",
    "sg:tags":[
        "restoration",
        "reproduction"
    ],
    "wof:name":"Wood&#039;n It Be Nice",
    "wof:placetype":"venue"
},
  "geometry": {"coordinates":[153.05592300000001,-27.371004],"type":"Point"}
}