{
  "type": "Feature",
  "properties": {
    "addr:full":"117a Brook St Muswellbrook NSW 2333",
    "addr:housenumber":"117a",
    "addr:postcode":"2333",
    "addr:street":"Brook St",
    "iso:country":"AU",
    "sg:address":"117a Brook St",
    "sg:city":"Muswellbrook",
    "sg:classifiers":[
        {
            "category":"Building & Trades",
            "subcategory":"Construction",
            "type":"Services"
        }
    ],
    "sg:phone":"+61 2 6543 3559",
    "sg:postcode":"2333",
    "sg:province":"NSW",
    "sg:tags":[
        "contractor"
    ],
    "wof:name":"Kane Building Inspection Services",
    "wof:placetype":"venue"
},
  "geometry": {"coordinates":[150.889938355,-32.2636375427],"type":"Point"}
}