{
  "type": "Feature",
  "properties": {
    "addr:full":"Port Augusta Rd Wilmington SA 5485",
    "addr:postcode":"5485",
    "addr:street":"Port Augusta Rd",
    "iso:country":"AU",
    "sg:address":"Port Augusta Rd",
    "sg:city":"Wilmington",
    "sg:classifiers":[
        {
            "category":"Farming",
            "subcategory":"Farm",
            "type":"Manufacturing & Wholesale Goods"
        }
    ],
    "sg:phone":"+61 8 8667 5046",
    "sg:postcode":"5485",
    "sg:province":"SA",
    "sg:tags":[
        "farmer"
    ],
    "wof:name":"Modystach John M",
    "wof:placetype":"venue"
},
  "geometry": {"coordinates":[138.106399536,-32.6602516174],"type":"Point"}
}