{
  "type": "Feature",
  "properties": {
    "iso:country":"AU",
    "sg:address":"Lot 75 Wheeldon Crt",
    "sg:city":"Traralgon",
    "sg:classifiers":[
        {
            "category":"Home & Garden",
            "subcategory":"Building Materials",
            "type":"Retail Goods"
        }
    ],
    "sg:phone":"+61 3 5174 7978",
    "sg:postcode":"3844",
    "sg:province":"VIC",
    "sg:tags":[
        "wall",
        "frame",
        "truss",
        "roof"
    ],
    "wof:name":"Dahlsens",
    "wof:placetype":"venue"
},
  "geometry": {"coordinates":[146.55827331500001,-38.1923332214],"type":"Point"}
}