{
  "type": "Feature",
  "properties": {
    "addr:full":"9 Enterprise Way Browns Plains QLD 4118",
    "addr:housenumber":"9",
    "addr:postcode":"4118",
    "addr:street":"Enterprise Way",
    "iso:country":"AU",
    "sg:address":"9 Enterprise Way",
    "sg:city":"Browns Plains",
    "sg:classifiers":[
        {
            "category":"Commercial Area",
            "type":"Public Place"
        }
    ],
    "sg:phone":"+61 7 3800 1893",
    "sg:postcode":"4118",
    "sg:province":"QLD",
    "sg:tags":[
        "heavy",
        "carrier"
    ],
    "sg:website":"http://www.richardsonexcavations.com.au",
    "wof:name":"Richardson Excavations.",
    "wof:placetype":"venue"
},
  "geometry": {"coordinates":[153.04832458499999,-27.6628723145],"type":"Point"}
}