{
  "type": "Feature",
  "properties": {
    "addr:full":"Barrack St Bega NSW 2550",
    "addr:postcode":"2550",
    "addr:street":"Barrack St",
    "iso:country":"AU",
    "sg:address":"Barrack St",
    "sg:city":"Bega",
    "sg:classifiers":[
        {
            "category":"Fast Food",
            "type":"Food & Drink"
        }
    ],
    "sg:phone":"+61 2 6492 2397",
    "sg:postcode":"2550",
    "sg:province":"NSW",
    "sg:tags":[
        "away",
        "take"
    ],
    "wof:name":"Highway Store The",
    "wof:placetype":"venue"
},
  "geometry": {"coordinates":[149.84051513700001,-36.682346344],"type":"Point"}
}