{
  "type": "Feature",
  "properties": {
    "addr:full":"10 West St Brookvale NSW 2100",
    "addr:housenumber":"10",
    "addr:postcode":"2100",
    "addr:street":"West St",
    "iso:country":"AU",
    "sg:address":"10 West St",
    "sg:city":"Brookvale",
    "sg:classifiers":[
        {
            "category":"Retail",
            "subcategory":"Car Wash",
            "type":"Services"
        }
    ],
    "sg:phone":"+61 2 9905 0858",
    "sg:postcode":"2100",
    "sg:province":"NSW",
    "sg:tags":[
        "truck",
        "cleaning"
    ],
    "wof:name":"As New Vehicle Detailing",
    "wof:placetype":"venue"
},
  "geometry": {"coordinates":[151.277435303,-33.7613449097],"type":"Point"}
}