{
  "type": "Feature",
  "properties": {
    "iso:country":"AU",
    "sg:address":"108 Gouger St",
    "sg:city":"Adelaide",
    "sg:classifiers":[
        {
            "category":"Manufacturing",
            "subcategory":"Food",
            "type":"Manufacturing & Wholesale Goods"
        }
    ],
    "sg:phone":"+61 8 8231 3223",
    "sg:postcode":"5000",
    "sg:province":"SA",
    "sg:tags":[
        "function",
        "catering"
    ],
    "wof:name":"The Greek Mezze",
    "wof:placetype":"venue"
},
  "geometry": {"coordinates":[138.595336914,-34.930229187],"type":"Point"}
}