{
  "type": "Feature",
  "properties": {
    "addr:full":"Shop 5 64 Manning St Tuncurry NSW 2428",
    "addr:housenumber":"shop;64",
    "addr:postcode":"2428",
    "addr:street":"Manning St",
    "iso:country":"AU",
    "sg:address":"Shop 5 64 Manning St",
    "sg:city":"Tuncurry",
    "sg:classifiers":[
        {
            "category":"Shopping",
            "subcategory":"Party Supplies",
            "type":"Retail Goods"
        }
    ],
    "sg:phone":"+61 2 6557 2012",
    "sg:postcode":"2428",
    "sg:province":"NSW",
    "sg:tags":[
        "hire",
        "costume"
    ],
    "wof:name":"Forster/Tuncurry Toy Library",
    "wof:placetype":"venue"
},
  "geometry": {"coordinates":[152.499786,-32.17598],"type":"Point"}
}