{
  "type": "Feature",
  "properties": {
    "iso:country":"AU",
    "sg:address":"6 Potter Ave",
    "sg:city":"Earlwood",
    "sg:classifiers":[
        {
            "category":"Building & Trades",
            "subcategory":"Construction",
            "type":"Services"
        }
    ],
    "sg:phone":"+61 2 9718 6202",
    "sg:postcode":"2206",
    "sg:province":"NSW",
    "sg:tags":[
        "contractor"
    ],
    "wof:name":"Metcam Industries Pty Ltd",
    "wof:placetype":"venue"
},
  "geometry": {"coordinates":[151.11874399999999,-33.918327],"type":"Point"}
}