{
  "type": "Feature",
  "properties": {
    "addr:full":"8 Parkinson St Weston ACT 2611",
    "addr:housenumber":"8",
    "addr:postcode":"2611",
    "addr:street":"Parkinson St",
    "iso:country":"AU",
    "sg:address":"8 Parkinson St",
    "sg:city":"Weston",
    "sg:classifiers":[
        {
            "category":"Social Services",
            "subcategory":"Child Care",
            "type":"Services"
        }
    ],
    "sg:phone":"+61 2 6288 5380",
    "sg:postcode":"2611",
    "sg:province":"ACT",
    "wof:name":"Weston Creek Childrens Centre",
    "wof:placetype":"venue"
},
  "geometry": {"coordinates":[149.05564880399999,-35.342956543],"type":"Point"}
}