{
  "type": "Feature",
  "properties": {
    "addr:full":"1st Floor 426 Mt Alexander Rd Moonee Ponds VIC 3039",
    "addr:housenumber":"426",
    "addr:postcode":"3039",
    "addr:street":"Mt Alexander Rd",
    "iso:country":"AU",
    "sg:address":"1st Floor 426 Mt Alexander Rd",
    "sg:city":"Moonee Ponds",
    "sg:classifiers":[
        {
            "category":"Professional",
            "subcategory":"Accounting & Tax Preparation",
            "type":"Services"
        }
    ],
    "sg:phone":"+61 3 9372 0855",
    "sg:postcode":"3039",
    "sg:province":"VIC",
    "sg:tags":[
        "accountant",
        "auditor"
    ],
    "wof:name":"Brown & Co Pty Ltd",
    "wof:placetype":"venue"
},
  "geometry": {"coordinates":[144.927246,-37.773712],"type":"Point"}
}