{
  "type": "Feature",
  "properties": {
    "iso:country":"AU",
    "sg:address":"Suite 3 62 Clarence St",
    "sg:city":"Port Macquarie",
    "sg:classifiers":[
        {
            "category":"Professional",
            "subcategory":"Employment Agencies",
            "type":"Services"
        }
    ],
    "sg:phone":"+61 2 6583 6658",
    "sg:postcode":"2444",
    "sg:province":"NSW",
    "sg:tags":[
        "hire",
        "labour",
        "contractor"
    ],
    "wof:name":"MHS Group Pty Ltd",
    "wof:placetype":"venue"
},
  "geometry": {"coordinates":[152.907486,-31.429337],"type":"Point"}
}