{
  "type": "Feature",
  "properties": {
    "iso:country":"AU",
    "sg:address":"PO Box 231",
    "sg:city":"Monto",
    "sg:classifiers":[
        {
            "category":"Building & Trades",
            "subcategory":"Construction",
            "type":"Services"
        }
    ],
    "sg:phone":"+61 7 4166 1481",
    "sg:postcode":"4630",
    "sg:province":"QLD",
    "sg:tags":[
        "earth",
        "excavating",
        "moving",
        "contractor"
    ],
    "wof:name":"Doug Evans Earthmoving",
    "wof:placetype":"venue"
},
  "geometry": {"coordinates":[151.11920165999999,-24.866060257],"type":"Point"}
}