{
  "type": "Feature",
  "properties": {
    "addr:full":"485 Main North Rd Gawler SA 5118",
    "addr:housenumber":"485",
    "addr:postcode":"5118",
    "addr:street":"Main North Rd",
    "iso:country":"AU",
    "sg:address":"485 Main North Rd",
    "sg:city":"Gawler",
    "sg:classifiers":[
        {
            "category":"Home & Garden",
            "subcategory":"Carpets & Floor Coverings",
            "type":"Retail Goods"
        }
    ],
    "sg:phone":"+61 8 8523 1550",
    "sg:postcode":"5118",
    "sg:province":"SA",
    "sg:tags":[
        "tile",
        "wall"
    ],
    "wof:name":"Beaumont Tiles",
    "wof:placetype":"venue"
},
  "geometry": {"coordinates":[138.74923699999999,-34.596706],"type":"Point"}
}