{
  "type": "Feature",
  "properties": {
    "addr:full":"Cnr Walter Rd & Russell St Morley WA 6062",
    "addr:postcode":"6062",
    "addr:street":"Walter Rd & Russell St",
    "iso:country":"AU",
    "sg:address":"Cnr Walter Rd & Russell St",
    "sg:city":"Morley",
    "sg:classifiers":[
        {
            "category":"Health Services",
            "subcategory":"Dentist",
            "type":"Services"
        }
    ],
    "sg:phone":"+61 8 9276 9888",
    "sg:postcode":"6062",
    "sg:province":"WA",
    "wof:name":"Lam Tim Y W Orthodontist",
    "wof:placetype":"venue"
},
  "geometry": {"coordinates":[115.896659851,-31.8949699402],"type":"Point"}
}