{
  "type": "Feature",
  "properties": {
    "addr:full":"Lot 354/, Falls Rd Strath Creek VIC 3658",
    "addr:postcode":"3658",
    "addr:street":"Falls Rd",
    "iso:country":"AU",
    "sg:address":"Lot 354/, Falls Rd",
    "sg:city":"Strath Creek",
    "sg:classifiers":[
        {
            "category":"Farming",
            "subcategory":"Livestock Farm",
            "type":"Manufacturing & Wholesale Goods"
        }
    ],
    "sg:phone":"+61 427 623 319",
    "sg:postcode":"3658",
    "sg:province":"VIC",
    "sg:tags":[
        "breeder",
        "horse",
        "stud"
    ],
    "wof:name":"Timbindi Stud",
    "wof:placetype":"venue"
},
  "geometry": {"coordinates":[145.212646484,-37.2446327209],"type":"Point"}
}