{
  "type": "Feature",
  "properties": {
    "addr:full":"PO Box 120 Wentworth NSW 2648",
    "addr:postcode":"2648",
    "iso:country":"AU",
    "sg:address":"PO Box 120",
    "sg:city":"Wentworth",
    "sg:classifiers":[
        {
            "category":"Utilities",
            "subcategory":"Sewage",
            "type":"Services"
        }
    ],
    "sg:phone":"+61 3 5027 6406",
    "sg:postcode":"2648",
    "sg:province":"NSW",
    "sg:tags":[
        "water",
        "waste",
        "treatment"
    ],
    "wof:name":"H2O Consulting",
    "wof:placetype":"venue"
},
  "geometry": {"coordinates":[141.92012,-34.09449],"type":"Point"}
}