{
  "type": "Feature",
  "properties": {
    "iso:country":"AU",
    "sg:address":"9 Ramah Ave",
    "sg:city":"Mt Ousley",
    "sg:classifiers":[
        {
            "category":"Building & Trades",
            "subcategory":"Construction",
            "type":"Services"
        }
    ],
    "sg:phone":"+61 2 4284 9329",
    "sg:postcode":"2519",
    "sg:province":"NSW",
    "sg:tags":[
        "contractor"
    ],
    "wof:name":"Kuulkers F",
    "wof:placetype":"venue"
},
  "geometry": {"coordinates":[150.878922,-34.397621],"type":"Point"}
}