{
  "type": "Feature",
  "properties": {
    "addr:full":"290 Ford St North Rockhampton QLD 4701",
    "addr:housenumber":"290",
    "addr:postcode":"4701",
    "addr:street":"Ford St North",
    "iso:country":"AU",
    "sg:address":"290 Ford St",
    "sg:city":"North Rockhampton",
    "sg:classifiers":[
        {
            "category":"Building & Trades",
            "subcategory":"Construction",
            "type":"Services"
        }
    ],
    "sg:phone":"+61 7 4928 7065",
    "sg:postcode":"4701",
    "sg:province":"QLD",
    "sg:tags":[
        "repair",
        "maintenance",
        "contractor"
    ],
    "wof:name":"Sonny Tihema",
    "wof:placetype":"venue"
},
  "geometry": {"coordinates":[150.526443481,-23.3543300629],"type":"Point"}
}