{
  "type": "Feature",
  "properties": {
    "addr:full":"Tareena St Renmark North SA 5341",
    "addr:postcode":"5341",
    "addr:street":"St",
    "iso:country":"AU",
    "sg:address":"Tareena St",
    "sg:city":"Renmark North",
    "sg:classifiers":[
        {
            "category":"Professional",
            "type":"Services"
        }
    ],
    "sg:phone":"+61 412 295 540",
    "sg:postcode":"5341",
    "sg:province":"SA",
    "sg:tags":[
        "transport"
    ],
    "wof:name":"A.M.D.G. Trucking",
    "wof:placetype":"venue"
},
  "geometry": {"coordinates":[140.693634033,-34.126209259],"type":"Point"}
}