{
  "type": "Feature",
  "properties": {
    "addr:full":"48 York St Gosford East NSW 2250",
    "addr:housenumber":"48",
    "addr:postcode":"2250",
    "addr:street":"York St",
    "iso:country":"AU",
    "sg:address":"48 York St",
    "sg:city":"Gosford East",
    "sg:classifiers":[
        {
            "category":"Retail",
            "subcategory":"Repair Shop",
            "type":"Services"
        }
    ],
    "sg:phone":"+61 13 13 50",
    "sg:postcode":"2250",
    "sg:province":"NSW",
    "sg:tags":[
        "machine",
        "repairs",
        "part",
        "dryer",
        "washing"
    ],
    "wof:name":"Electrolux",
    "wof:placetype":"venue"
},
  "geometry": {"coordinates":[151.348144531,-33.4361763],"type":"Point"}
}