{
  "type": "Feature",
  "properties": {
    "addr:full":"Suite 503,Lvl 5/ 69 Christie St St Leonards NSW 2065",
    "addr:housenumber":"/ 69",
    "addr:postcode":"2065",
    "addr:street":"Christie St",
    "iso:country":"AU",
    "sg:address":"Suite 503,Lvl 5/ 69 Christie St St",
    "sg:city":"Leonards",
    "sg:classifiers":[
        {
            "category":"Health Services",
            "subcategory":"Doctor",
            "type":"Services"
        }
    ],
    "sg:phone":"+61 2 9437 9200",
    "sg:postcode":"2065",
    "sg:province":"NSW",
    "sg:tags":[
        "medical",
        "practitioner"
    ],
    "sg:website":"http://www.plasticsurgery.org.au",
    "wof:name":"Australian Society of Plastic Surgeons",
    "wof:placetype":"venue"
},
  "geometry": {"coordinates":[151.195755005,-33.8237457275],"type":"Point"}
}