{
  "type": "Feature",
  "properties": {
    "addr:full":"Shp 2/ 10 Otranto Ave Caloundra QLD 4551",
    "addr:housenumber":"/ 10",
    "addr:postcode":"4551",
    "addr:street":"Otranto Ave",
    "iso:country":"AU",
    "sg:address":"Shp 2/ 10 Otranto Ave",
    "sg:city":"Caloundra",
    "sg:classifiers":[
        {
            "category":"Manufacturing",
            "subcategory":"Food",
            "type":"Manufacturing & Wholesale Goods"
        }
    ],
    "sg:phone":"+61 7 5438 1180",
    "sg:postcode":"4551",
    "sg:province":"QLD",
    "sg:tags":[
        "function",
        "catering"
    ],
    "wof:name":"Do Drop Inn Cafe",
    "wof:placetype":"venue"
},
  "geometry": {"coordinates":[153.130249023,-26.8043403625],"type":"Point"}
}