{
  "type": "Feature",
  "properties": {
    "iso:country":"AU",
    "sg:address":"1 Sheffield Rd",
    "sg:city":"Bowral",
    "sg:classifiers":[
        {
            "category":"Health Services",
            "subcategory":"Doctor",
            "type":"Services"
        }
    ],
    "sg:phone":"+61 2 4862 1991",
    "sg:postcode":"2576",
    "sg:province":"NSW",
    "sg:tags":[
        "medical",
        "practitioner"
    ],
    "wof:name":"Wenden Roger W",
    "wof:placetype":"venue"
},
  "geometry": {"coordinates":[150.42221069300001,-34.4838752747],"type":"Point"}
}