{
  "type": "Feature",
  "properties": {
    "iso:country":"AU",
    "sg:address":"360 Argent St",
    "sg:city":"Broken Hill",
    "sg:classifiers":[
        {
            "category":"Food & Beverages",
            "subcategory":"Bakery",
            "type":"Retail Goods"
        }
    ],
    "sg:phone":"+61 8 8088 4774",
    "sg:postcode":"2880",
    "sg:province":"NSW",
    "sg:tags":[
        "baker"
    ],
    "wof:name":"Food Affair",
    "wof:placetype":"venue"
},
  "geometry": {"coordinates":[141.46681213400001,-31.9573860168],"type":"Point"}
}