{
  "type": "Feature",
  "properties": {
    "addr:full":"The Basement 80 Oxford St Darlinghurst NSW 2010",
    "addr:housenumber":"80",
    "addr:postcode":"2010",
    "addr:street":"Oxford St",
    "iso:country":"AU",
    "sg:address":"The Basement 80 Oxford St",
    "sg:city":"Darlinghurst",
    "sg:classifiers":[
        {
            "category":"Shopping",
            "subcategory":"Music",
            "type":"Retail Goods"
        }
    ],
    "sg:phone":"+61 2 9380 5378",
    "sg:postcode":"2010",
    "sg:province":"NSW",
    "sg:tags":[
        "store"
    ],
    "wof:name":"Reachin Records",
    "wof:placetype":"venue"
},
  "geometry": {"coordinates":[151.21522522000001,-33.8790054321],"type":"Point"}
}