{
  "type": "Feature",
  "properties": {
    "addr:full":"Shop 8a, 48 Thuringowa Drv Kirwan QLD 4817",
    "addr:housenumber":"shop 8a 48",
    "addr:postcode":"4817",
    "addr:street":"Thuringowa Drv",
    "iso:country":"AU",
    "sg:address":"Shop 8a, 48 Thuringowa Drv",
    "sg:city":"Kirwan",
    "sg:classifiers":[
        {
            "category":"Personal",
            "subcategory":"Beauty Salon",
            "type":"Services"
        }
    ],
    "sg:phone":"+61 7 4723 2120",
    "sg:postcode":"4817",
    "sg:province":"QLD",
    "wof:name":"Cutting Point Hair Studio",
    "wof:placetype":"venue"
},
  "geometry": {"coordinates":[146.72950700000001,-19.312632],"type":"Point"}
}