{
  "type": "Feature",
  "properties": {
    "addr:full":"671 Sherwood Rd Sherwood QLD 4075",
    "addr:housenumber":"671",
    "addr:postcode":"4075",
    "addr:street":"Sherwood Rd",
    "iso:country":"AU",
    "sg:address":"671 Sherwood Rd",
    "sg:city":"Sherwood",
    "sg:classifiers":[
        {
            "category":"Government",
            "subcategory":"Court House",
            "type":"Public Place"
        }
    ],
    "sg:phone":"+61 407 020 475",
    "sg:postcode":"4075",
    "sg:province":"QLD",
    "sg:tags":[
        "personal",
        "marriage",
        "family",
        "counselling"
    ],
    "wof:name":"Axford Sharon",
    "wof:placetype":"venue"
},
  "geometry": {"coordinates":[152.98126220699999,-27.5320358276],"type":"Point"}
}