{
  "type": "Feature",
  "properties": {
    "addr:full":"3 Riley St Tenterfield NSW 2372",
    "addr:housenumber":"3",
    "addr:postcode":"2372",
    "addr:street":"Riley St",
    "iso:country":"AU",
    "sg:address":"3 Riley St",
    "sg:city":"Tenterfield",
    "sg:classifiers":[
        {
            "category":"Building & Trades",
            "subcategory":"Construction",
            "type":"Services"
        }
    ],
    "sg:phone":"+61 2 6736 2192",
    "sg:postcode":"2372",
    "sg:province":"NSW",
    "sg:tags":[
        "contractor"
    ],
    "wof:name":"Murphy WJ (Bill)",
    "wof:placetype":"venue"
},
  "geometry": {"coordinates":[152.006988525,-29.0414123535],"type":"Point"}
}