{
  "type": "Feature",
  "properties": {
    "iso:country":"AU",
    "sg:address":"2 Christina Pl",
    "sg:city":"Aitkenvale",
    "sg:classifiers":[
        {
            "category":"Professional",
            "subcategory":"Art Services",
            "type":"Services"
        }
    ],
    "sg:phone":"+61 7 4779 3378",
    "sg:postcode":"4814",
    "sg:province":"QLD",
    "sg:tags":[
        "picture",
        "frame",
        "framing"
    ],
    "wof:name":"Just Frames",
    "wof:placetype":"venue"
},
  "geometry": {"coordinates":[146.771164,-19.307737],"type":"Point"}
}