{
  "type": "Feature",
  "properties": {
    "addr:full":"U1/ 11 Holbeche Rd Arndell Park NSW 2148",
    "addr:housenumber":"11",
    "addr:postcode":"2148",
    "addr:street":"U1 /;Holbeche Rd",
    "iso:country":"AU",
    "sg:address":"U1/ 11 Holbeche Rd",
    "sg:city":"Arndell Park",
    "sg:classifiers":[
        {
            "category":"Wholesale",
            "subcategory":"Scrap",
            "type":"Manufacturing & Wholesale Goods"
        }
    ],
    "sg:phone":"+61 2 9679 9490",
    "sg:postcode":"2148",
    "sg:province":"NSW",
    "sg:tags":[
        "merchant",
        "metal"
    ],
    "wof:name":"Just Scrap Metal Pty Ltd",
    "wof:placetype":"venue"
},
  "geometry": {"coordinates":[150.88328552199999,-33.7886009216],"type":"Point"}
}