{
  "type": "Feature",
  "properties": {
    "addr:full":"Unit 4, 7 Union St Stepney SA 5069",
    "addr:housenumber":"7",
    "addr:postcode":"5069",
    "addr:street":"Union St",
    "iso:country":"AU",
    "sg:address":"Unit 4, 7 Union St",
    "sg:city":"Stepney",
    "sg:classifiers":[
        {
            "category":"Health Services",
            "subcategory":"Health Practitioner",
            "type":"Services"
        }
    ],
    "sg:phone":"+61 8 8362 8830",
    "sg:postcode":"5069",
    "sg:province":"SA",
    "sg:tags":[
        "acupuncture"
    ],
    "wof:name":"Acuhealth Pty Ltd",
    "wof:placetype":"venue"
},
  "geometry": {"coordinates":[138.62901306099999,-34.9137191772],"type":"Point"}
}