{
  "type": "Feature",
  "properties": {
    "iso:country":"AU",
    "sg:address":"PO Box 397",
    "sg:city":"Hall",
    "sg:classifiers":[
        {
            "category":"Building & Trades",
            "subcategory":"Construction",
            "type":"Services"
        }
    ],
    "sg:phone":"+61 410 515 010",
    "sg:postcode":"2618",
    "sg:province":"ACT",
    "sg:tags":[
        "tennis court",
        "repair"
    ],
    "wof:name":"Ausblu Fencing",
    "wof:placetype":"venue"
},
  "geometry": {"coordinates":[149.06988525400001,-35.1702308655],"type":"Point"}
}