{
  "type": "Feature",
  "properties": {
    "addr:full":"Shop 3, 36 Sunshine Beach Rd Noosa Junction QLD 4567",
    "addr:housenumber":"shop;36",
    "addr:postcode":"4567",
    "addr:street":"Sunshine Beach Rd",
    "iso:country":"AU",
    "sg:address":"Shop 3, 36 Sunshine Beach Rd",
    "sg:city":"Noosa Junction",
    "sg:classifiers":[
        {
            "category":"Shopping",
            "type":"Retail Goods"
        }
    ],
    "sg:phone":"+61 7 5448 0166",
    "sg:postcode":"4567",
    "sg:province":"QLD",
    "sg:tags":[
        "new age",
        "product"
    ],
    "wof:name":"Symbolic Journey",
    "wof:placetype":"venue"
},
  "geometry": {"coordinates":[153.09115600600001,-26.3980731964],"type":"Point"}
}