{
  "type": "Feature",
  "properties": {
    "addr:full":"339 Condamine St Manly Vale NSW 2093",
    "addr:housenumber":"339",
    "addr:postcode":"2093",
    "addr:street":"Condamine St",
    "iso:country":"AU",
    "sg:address":"339 Condamine St",
    "sg:city":"Manly Vale",
    "sg:classifiers":[
        {
            "category":"Personal",
            "subcategory":"Beauty Salon",
            "type":"Services"
        }
    ],
    "sg:phone":"+61 2 9949 4983",
    "sg:postcode":"2093",
    "sg:province":"NSW",
    "wof:name":"Beauty Beach",
    "wof:placetype":"venue"
},
  "geometry": {"coordinates":[151.267303467,-33.7831001282],"type":"Point"}
}