{
  "type": "Feature",
  "properties": {
    "addr:full":"383 Mann St Gosford NSW 2250",
    "addr:housenumber":"383",
    "addr:postcode":"2250",
    "addr:street":"Mann St",
    "iso:country":"AU",
    "sg:address":"383 Mann St",
    "sg:city":"Gosford",
    "sg:classifiers":[
        {
            "category":"Autos & Motor Vehicles",
            "subcategory":"Automobile Sales",
            "type":"Retail Goods"
        }
    ],
    "sg:phone":"+61 2 4323 7700",
    "sg:postcode":"2250",
    "sg:province":"NSW",
    "sg:tags":[
        "car",
        "new"
    ],
    "wof:name":"Central Coast Nissan",
    "wof:placetype":"venue"
},
  "geometry": {"coordinates":[151.344192505,-33.4162559509],"type":"Point"}
}