{
  "type": "Feature",
  "properties": {
    "iso:country":"AU",
    "sg:address":"Torquay Rd",
    "sg:city":"Latrobe",
    "sg:classifiers":[
        {
            "category":"Health Services",
            "subcategory":"Doctor",
            "type":"Services"
        }
    ],
    "sg:phone":"+61 3 6426 5440",
    "sg:postcode":"7307",
    "sg:province":"TAS",
    "sg:tags":[
        "medical",
        "practitioner"
    ],
    "wof:name":"Regional Imaging Tasmania",
    "wof:placetype":"venue"
},
  "geometry": {"coordinates":[146.423187,-41.228958],"type":"Point"}
}