{
  "type": "Feature",
  "properties": {
    "addr:full":"84 Keys Rd Cheltenham VIC 3192",
    "addr:housenumber":"84",
    "addr:postcode":"3192",
    "addr:street":"Keys Rd",
    "iso:country":"AU",
    "sg:address":"84 Keys Rd",
    "sg:city":"Cheltenham",
    "sg:classifiers":[
        {
            "category":"Professional",
            "subcategory":"Engineering",
            "type":"Services"
        }
    ],
    "sg:phone":"+61 3 9555 5153",
    "sg:postcode":"3192",
    "sg:province":"VIC",
    "sg:tags":[
        "electronic",
        "engineer"
    ],
    "wof:name":"Daley Electronics Pty Ltd",
    "wof:placetype":"venue"
},
  "geometry": {"coordinates":[145.068267822,-37.9488487244],"type":"Point"}
}