{
  "type": "Feature",
  "properties": {
    "addr:full":"108 Parraween St Cremorne NSW 2090",
    "addr:housenumber":"108",
    "addr:postcode":"2090",
    "addr:street":"Parraween St",
    "iso:country":"AU",
    "sg:address":"108 Parraween St",
    "sg:city":"Cremorne",
    "sg:classifiers":[
        {
            "category":"Social Services",
            "subcategory":"Child Care",
            "type":"Services"
        }
    ],
    "sg:phone":"+61 2 9953 7042",
    "sg:postcode":"2090",
    "sg:province":"NSW",
    "sg:tags":[
        "support",
        "health"
    ],
    "wof:name":"Early Childhood Health Centres",
    "wof:placetype":"venue"
},
  "geometry": {"coordinates":[151.22625732399999,-33.8295898438],"type":"Point"}
}