{
  "type": "Feature",
  "properties": {
    "addr:full":"65 Stewart Ave Hamilton South NSW 2303",
    "addr:housenumber":"65",
    "addr:postcode":"2303",
    "addr:street":"Stewart Ave",
    "iso:country":"AU",
    "sg:address":"65 Stewart Ave",
    "sg:city":"Hamilton South",
    "sg:classifiers":[
        {
            "category":"Personal",
            "subcategory":"Beauty Salon",
            "type":"Services"
        }
    ],
    "sg:phone":"+61 2 4961 3987",
    "sg:postcode":"2303",
    "sg:province":"NSW",
    "sg:tags":[
        "hairdresser"
    ],
    "wof:name":"Stewart Avenue Hair Care",
    "wof:placetype":"venue"
},
  "geometry": {"coordinates":[151.75318899999999,-32.931992],"type":"Point"}
}