{
  "type": "Feature",
  "properties": {
    "addr:full":"11 Commercial St Marleston SA 5033",
    "addr:housenumber":"11",
    "addr:postcode":"5033",
    "addr:street":"Commercial St",
    "iso:country":"AU",
    "sg:address":"11 Commercial St",
    "sg:city":"Marleston",
    "sg:classifiers":[
        {
            "category":"Banks & Credit Unions",
            "subcategory":"Bank",
            "type":"Services"
        }
    ],
    "sg:phone":"+61 8 8351 5122",
    "sg:postcode":"5033",
    "sg:province":"SA",
    "sg:tags":[
        "castor"
    ],
    "wof:name":"Cornall Merchandise",
    "wof:placetype":"venue"
},
  "geometry": {"coordinates":[138.56393432600001,-34.9447975159],"type":"Point"}
}