{
  "type": "Feature",
  "properties": {
    "addr:full":"16 Galbraith Ave Toronto NSW 2283",
    "addr:housenumber":"16",
    "addr:postcode":"2283",
    "addr:street":"Galbraith Ave",
    "iso:country":"AU",
    "sg:address":"16 Galbraith Ave",
    "sg:city":"Toronto",
    "sg:classifiers":[
        {
            "category":"Building & Trades",
            "subcategory":"Landscaping Services",
            "type":"Services"
        }
    ],
    "sg:phone":"+61 2 4959 8849",
    "sg:postcode":"2283",
    "sg:province":"NSW",
    "sg:tags":[
        "stump",
        "tree",
        "felling",
        "removal"
    ],
    "wof:name":"Friendly Tree Removal",
    "wof:placetype":"venue"
},
  "geometry": {"coordinates":[151.58468627900001,-33.010055542],"type":"Point"}
}