{
  "type": "Feature",
  "properties": {
    "addr:full":"U 16 /1- 7 Canterbury Rd Braeside VIC 3195",
    "addr:housenumber":"16 / 1 7",
    "addr:postcode":"3195",
    "addr:street":"Canterbury Rd",
    "iso:country":"AU",
    "sg:address":"U 16 /1- 7 Canterbury Rd",
    "sg:city":"Braeside",
    "sg:classifiers":[
        {
            "category":"Home & Garden",
            "subcategory":"Kitchen Supply",
            "type":"Retail Goods"
        }
    ],
    "sg:phone":"+61 3 9580 5666",
    "sg:postcode":"3195",
    "sg:province":"VIC",
    "sg:tags":[
        "equipment",
        "diving"
    ],
    "wof:name":"Divers Supplies Pty Ltd",
    "wof:placetype":"venue"
},
  "geometry": {"coordinates":[145.10386657699999,-38.009475708],"type":"Point"}
}