{
  "type": "Feature",
  "properties": {
    "addr:full":"64 Stanley St Toora VIC 3962",
    "addr:housenumber":"64",
    "addr:postcode":"3962",
    "addr:street":"Stanley St",
    "iso:country":"AU",
    "sg:address":"64 Stanley St",
    "sg:city":"Toora",
    "sg:classifiers":[
        {
            "category":"Professional",
            "type":"Services"
        }
    ],
    "sg:phone":"+61 3 5686 2333",
    "sg:postcode":"3962",
    "sg:province":"VIC",
    "sg:tags":[
        "auctioneer"
    ],
    "wof:name":"Demaria Auctions",
    "wof:placetype":"venue"
},
  "geometry": {"coordinates":[146.323730469,-38.6649856567],"type":"Point"}
}