{
  "type": "Feature",
  "properties": {
    "addr:full":"146 Wood St Mackay QLD 4740",
    "addr:housenumber":"146",
    "addr:postcode":"4740",
    "addr:street":"Wood St",
    "iso:country":"AU",
    "sg:address":"146 Wood St",
    "sg:city":"Mackay",
    "sg:classifiers":[
        {
            "category":"Personal",
            "subcategory":"Tattoo Parlor",
            "type":"Services"
        }
    ],
    "sg:phone":"+61 7 4953 2127",
    "sg:postcode":"4740",
    "sg:province":"QLD",
    "sg:tags":[
        "tattooing"
    ],
    "wof:name":"Fletchs Tattoo Studio",
    "wof:placetype":"venue"
},
  "geometry": {"coordinates":[149.18499800000001,-21.146296],"type":"Point"}
}