{
  "type": "Feature",
  "properties": {
    "addr:full":"Shop 1/ 37 Oak St Gympie QLD 4570",
    "addr:housenumber":"shop 1 / 37",
    "addr:postcode":"4570",
    "addr:street":"Oak St",
    "iso:country":"AU",
    "sg:address":"Shop 1/ 37 Oak St",
    "sg:city":"Gympie",
    "sg:classifiers":[
        {
            "category":"Professional",
            "subcategory":"Detective & Security Services",
            "type":"Services"
        }
    ],
    "sg:phone":"+61 7 5482 1122",
    "sg:postcode":"4570",
    "sg:province":"QLD",
    "sg:tags":[
        "equipment",
        "window",
        "doors"
    ],
    "wof:name":"Gympie Gold City Glass",
    "wof:placetype":"venue"
},
  "geometry": {"coordinates":[152.65235900900001,-26.178861618],"type":"Point"}
}