{
  "type": "Feature",
  "properties": {
    "addr:full":"Cnr Eastern Valley Way & Edinburgh Rd Castlecrag NSW 2068",
    "addr:postcode":"2068",
    "addr:street":"Cnr Eastern Valley Way & Edinburgh Rd",
    "iso:country":"AU",
    "sg:address":"Cnr Eastern Valley Way & Edinburgh Rd",
    "sg:city":"Castlecrag",
    "sg:classifiers":[
        {
            "category":"Personal",
            "subcategory":"Beauty Salon",
            "type":"Services"
        }
    ],
    "sg:phone":"+61 2 9958 0546",
    "sg:postcode":"2068",
    "sg:province":"NSW",
    "wof:name":"Beaute Boutique Yours Beautifully",
    "wof:placetype":"venue"
},
  "geometry": {"coordinates":[151.211547852,-33.8024330139],"type":"Point"}
}