{
  "type": "Feature",
  "properties": {
    "iso:country":"AU",
    "sg:address":"15 Studley St",
    "sg:city":"Abbotsford",
    "sg:classifiers":[
        {
            "category":"Real Estate",
            "subcategory":"Architect",
            "type":"Services"
        }
    ],
    "sg:phone":"+61 3 9417 2700",
    "sg:postcode":"3067",
    "sg:province":"VIC",
    "wof:name":"Croxon Ramsay Pty Ltd",
    "wof:placetype":"venue"
},
  "geometry": {"coordinates":[144.99366760300001,-37.8013916016],"type":"Point"}
}