{
  "type": "Feature",
  "properties": {
    "iso:country":"AU",
    "sg:address":"90 Barton St",
    "sg:city":"Mayfield",
    "sg:classifiers":[
        {
            "category":"Building & Trades",
            "subcategory":"Construction",
            "type":"Services"
        }
    ],
    "sg:phone":"+61 2 4968 4668",
    "sg:postcode":"2304",
    "sg:province":"NSW",
    "sg:tags":[
        "joiner",
        "carpenter"
    ],
    "wof:name":"Marcus Williams",
    "wof:placetype":"venue"
},
  "geometry": {"coordinates":[151.73675537099999,-32.8907279968],"type":"Point"}
}