{
  "type": "Feature",
  "properties": {
    "addr:full":"18 Brendan Drv Nerang QLD 4211",
    "addr:housenumber":"18",
    "addr:postcode":"4211",
    "addr:street":"Brendan Drv",
    "iso:country":"AU",
    "sg:address":"18 Brendan Drv",
    "sg:city":"Nerang",
    "sg:classifiers":[
        {
            "category":"Shopping",
            "subcategory":"Bicycles & Sporting Goods",
            "type":"Retail Goods"
        }
    ],
    "sg:phone":"+61 7 5596 4766",
    "sg:postcode":"4211",
    "sg:province":"QLD",
    "sg:tags":[
        "chemical",
        "equipment",
        "pool",
        "swimming"
    ],
    "wof:name":"King Neptune Pool Centre",
    "wof:placetype":"venue"
},
  "geometry": {"coordinates":[153.34295654300001,-27.9983177185],"type":"Point"}
}