{
  "type": "Feature",
  "properties": {
    "addr:full":"Shop 3, Sherwood House Arcade 39 Sherwood Rd Toowong QLD 4066",
    "addr:housenumber":"shop 3;39",
    "addr:postcode":"4066",
    "addr:street":"Sherwood House Arcade;Sherwood Rd",
    "iso:country":"AU",
    "sg:address":"Shop 3, Sherwood House Arcade 39 Sherwood Rd",
    "sg:city":"Toowong",
    "sg:classifiers":[
        {
            "category":"Health Services",
            "subcategory":"Dentist",
            "type":"Services"
        }
    ],
    "sg:phone":"+61 7 3371 5441",
    "sg:postcode":"4066",
    "sg:province":"QLD",
    "wof:name":"Eric Wong",
    "wof:placetype":"venue"
},
  "geometry": {"coordinates":[152.99107360799999,-27.4852333069],"type":"Point"}
}