{
  "type": "Feature",
  "properties": {
    "addr:full":"100-128 Ferris Rd Melton VIC 3337",
    "addr:housenumber":"100-128",
    "addr:postcode":"3337",
    "addr:street":"Ferris Rd",
    "iso:country":"AU",
    "sg:address":"100-128 Ferris Rd",
    "sg:city":"Melton",
    "sg:classifiers":[
        {
            "category":"Manufacturing",
            "subcategory":"Textiles",
            "type":"Manufacturing & Wholesale Goods"
        }
    ],
    "sg:phone":"+61 3 9971 7777",
    "sg:postcode":"3337",
    "sg:province":"VIC",
    "sg:tags":[
        "wholesaler",
        "knitwear",
        "mfrs"
    ],
    "wof:name":"ABMT Textiles",
    "wof:placetype":"venue"
},
  "geometry": {"coordinates":[144.601654,-37.706024],"type":"Point"}
}