{
  "type": "Feature",
  "properties": {
    "addr:full":"Witt St Tea Gardens NSW 2324",
    "addr:postcode":"2324",
    "addr:street":"Witt St",
    "iso:country":"AU",
    "sg:address":"Witt St",
    "sg:city":"Tea Gardens",
    "sg:classifiers":[
        {
            "category":"Education",
            "subcategory":"School",
            "type":"Public Place"
        }
    ],
    "sg:phone":"+61 2 4997 0286",
    "sg:postcode":"2324",
    "sg:province":"NSW",
    "sg:tags":[
        "state",
        "-",
        "nsw"
    ],
    "wof:name":"Tea Gardens Public School",
    "wof:placetype":"venue"
},
  "geometry": {"coordinates":[152.15582275400001,-32.6648330688],"type":"Point"}
}