{
  "type": "Feature",
  "properties": {
    "iso:country":"AU",
    "sg:address":"36 Alex Pde",
    "sg:city":"Roma",
    "sg:classifiers":[
        {
            "category":"Building & Trades",
            "subcategory":"Cleaning & Sanitation",
            "type":"Services"
        }
    ],
    "sg:phone":"+61 7 4622 1092",
    "sg:postcode":"4455",
    "sg:province":"QLD",
    "sg:tags":[
        "industrial",
        "commercial",
        "contractor"
    ],
    "wof:name":"B & Bs Cleaning Carpet Cleaning & Handymans Services",
    "wof:placetype":"venue"
},
  "geometry": {"coordinates":[148.78732299800001,-26.5734291077],"type":"Point"}
}