{
  "type": "Feature",
  "properties": {
    "iso:country":"AU",
    "sg:address":"2/ 543 Warrigal Rd",
    "sg:city":"Ashwood",
    "sg:classifiers":[
        {
            "category":"Health Services",
            "subcategory":"Health Practitioner",
            "type":"Services"
        }
    ],
    "sg:phone":"+61 3 9885 5592",
    "sg:postcode":"3147",
    "sg:province":"VIC",
    "sg:tags":[
        "acupuncture"
    ],
    "wof:name":"Reid Hamish",
    "wof:placetype":"venue"
},
  "geometry": {"coordinates":[145.09300231899999,-37.8656311035],"type":"Point"}
}