{
  "type": "Feature",
  "properties": {
    "iso:country":"AU",
    "sg:address":"Unit 4/ 97 Delta St",
    "sg:city":"Geebung",
    "sg:classifiers":[
        {
            "category":"Autos & Motor Vehicles",
            "subcategory":"Auto Supplies",
            "type":"Retail Goods"
        }
    ],
    "sg:phone":"+61 7 3623 8400",
    "sg:postcode":"4034",
    "sg:province":"QLD",
    "sg:tags":[
        "wheel",
        "four",
        "equipment",
        "drive",
        "accessory"
    ],
    "wof:name":"Coleman Tyre Company",
    "wof:placetype":"venue"
},
  "geometry": {"coordinates":[153.051865,-27.366358],"type":"Point"}
}