{
  "type": "Feature",
  "properties": {
    "addr:full":"U3 10-12 South Link Dandenong South VIC 3175",
    "addr:housenumber":"10-12",
    "addr:postcode":"3175",
    "addr:street":"U3;South Link",
    "iso:country":"AU",
    "sg:address":"U3 10-12 South Link",
    "sg:city":"Dandenong South",
    "sg:classifiers":[
        {
            "category":"Home & Garden",
            "subcategory":"Garden Supply",
            "type":"Retail Goods"
        }
    ],
    "sg:phone":"+61 3 9799 7459",
    "sg:postcode":"3175",
    "sg:province":"VIC",
    "sg:tags":[
        "shed"
    ],
    "wof:name":"Sheds N More",
    "wof:placetype":"venue"
},
  "geometry": {"coordinates":[145.238555908,-38.0215873718],"type":"Point"}
}