{
  "type": "Feature",
  "properties": {
    "iso:country":"AU",
    "sg:address":"Green St",
    "sg:city":"Kingsbury",
    "sg:classifiers":[
        {
            "category":"Arena",
            "subcategory":"Sports Club",
            "type":"Entertainment"
        }
    ],
    "sg:phone":"+61 407 855 344",
    "sg:postcode":"3083",
    "sg:province":"VIC",
    "sg:tags":[
        "defence",
        "supply",
        "self",
        "instruction",
        "martial art"
    ],
    "wof:name":"Advance Martial Arts Academy",
    "wof:placetype":"venue"
},
  "geometry": {"coordinates":[145.037872314,-37.6925392151],"type":"Point"}
}