{
  "type": "Feature",
  "properties": {
    "iso:country":"AU",
    "sg:address":"Suite 4, 265 Pakington St",
    "sg:city":"Newtown",
    "sg:classifiers":[
        {
            "category":"Banks & Credit Unions",
            "subcategory":"Financial Services",
            "type":"Services"
        }
    ],
    "sg:phone":"+61 3 5229 2900",
    "sg:postcode":"3220",
    "sg:province":"VIC",
    "sg:tags":[
        "loan",
        "finance",
        "mortgage"
    ],
    "wof:name":"Minerva Financial Strategies",
    "wof:placetype":"venue"
},
  "geometry": {"coordinates":[144.346405,-38.149738],"type":"Point"}
}