{
  "type": "Feature",
  "properties": {
    "addr:full":"9 Alfred St South Turramurra NSW 2074",
    "addr:housenumber":"9",
    "addr:postcode":"2074",
    "addr:street":"Alfred St South",
    "iso:country":"AU",
    "sg:address":"9 Alfred St",
    "sg:city":"South Turramurra",
    "sg:classifiers":[
        {
            "category":"Building & Trades",
            "subcategory":"Plumbing",
            "type":"Services"
        }
    ],
    "sg:phone":"+61 412 544 153",
    "sg:postcode":"2074",
    "sg:province":"NSW",
    "sg:tags":[
        "plumber",
        "gasfitters"
    ],
    "wof:name":"Dirty Deeds Plumbing",
    "wof:placetype":"venue"
},
  "geometry": {"coordinates":[151.10711669899999,-33.7553253174],"type":"Point"}
}