{
  "type": "Feature",
  "properties": {
    "addr:full":"218 Harbord Rd Brookvale NSW 2100",
    "addr:housenumber":"218",
    "addr:postcode":"2100",
    "addr:street":"Harbord Rd",
    "iso:country":"AU",
    "sg:address":"218 Harbord Rd",
    "sg:city":"Brookvale",
    "sg:classifiers":[
        {
            "category":"Wholesale",
            "subcategory":"Auto Parts",
            "type":"Manufacturing & Wholesale Goods"
        }
    ],
    "sg:phone":"+61 2 9938 6500",
    "sg:postcode":"2100",
    "sg:province":"NSW",
    "sg:tags":[
        "recyclers"
    ],
    "wof:name":"Harbord Road Motor Wreckers",
    "wof:placetype":"venue"
},
  "geometry": {"coordinates":[151.27993774399999,-33.7612419128],"type":"Point"}
}