{
  "type": "Feature",
  "properties": {
    "iso:country":"AU",
    "sg:address":"203 Armstrong St",
    "sg:city":"North Ballarat",
    "sg:classifiers":[
        {
            "category":"Personal",
            "subcategory":"Beauty Salon",
            "type":"Services"
        }
    ],
    "sg:phone":"+61 3 5332 3349",
    "sg:postcode":"3350",
    "sg:province":"VIC",
    "sg:tags":[
        "wig",
        "hairpiece"
    ],
    "wof:name":"Edwards Noel",
    "wof:placetype":"venue"
},
  "geometry": {"coordinates":[143.857132,-37.556293],"type":"Point"}
}