{
  "type": "Feature",
  "properties": {
    "iso:country":"AU",
    "sg:address":"23 Ailsa St",
    "sg:city":"Fullarton",
    "sg:classifiers":[
        {
            "category":"Retail",
            "subcategory":"Auto Rental",
            "type":"Services"
        }
    ],
    "sg:phone":"+61 8 8379 2700",
    "sg:postcode":"5063",
    "sg:province":"SA",
    "sg:tags":[
        "chauffeur",
        "car",
        "hire",
        "driven",
        "limousine"
    ],
    "wof:name":"Benson's Limousines",
    "wof:placetype":"venue"
},
  "geometry": {"coordinates":[138.62922668499999,-34.9518013],"type":"Point"}
}