{
  "type": "Feature",
  "properties": {
    "addr:full":"Shop 20/ 20 Hudson Rd Albion QLD 4010",
    "addr:housenumber":"shop 20 / 20",
    "addr:postcode":"4010",
    "addr:street":"Hudson Rd",
    "iso:country":"AU",
    "sg:address":"Shop 20/ 20 Hudson Rd",
    "sg:city":"Albion",
    "sg:classifiers":[
        {
            "category":"Shopping",
            "subcategory":"Antiques",
            "type":"Retail Goods"
        }
    ],
    "sg:phone":"+61 7 3262 4185",
    "sg:postcode":"4010",
    "sg:province":"QLD",
    "wof:name":"Ashley Hay Antiques",
    "wof:placetype":"venue"
},
  "geometry": {"coordinates":[153.04098510700001,-27.4318733215],"type":"Point"}
}