{
  "type": "Feature",
  "properties": {
    "addr:full":"108 Kennedy Drv Port Macquarie NSW 2444",
    "addr:housenumber":"108",
    "addr:postcode":"2444",
    "addr:street":"Kennedy Drv",
    "iso:country":"AU",
    "sg:address":"108 Kennedy Drv",
    "sg:city":"Port Macquarie",
    "sg:classifiers":[
        {
            "category":"Education",
            "subcategory":"Special Training",
            "type":"Public Place"
        }
    ],
    "sg:phone":"+61 429 723 633",
    "sg:postcode":"2444",
    "sg:province":"NSW",
    "sg:tags":[
        "tuition-educational"
    ],
    "wof:name":"Creative Learning Matters",
    "wof:placetype":"venue"
},
  "geometry": {"coordinates":[152.92248499999999,-31.4582],"type":"Point"}
}