{
  "type": "Feature",
  "properties": {
    "addr:full":"31 Fitzmaurice St Wagga Wagga NSW 2650",
    "addr:housenumber":"31",
    "addr:postcode":"2650",
    "addr:street":"Fitzmaurice St",
    "iso:country":"AU",
    "sg:address":"31 Fitzmaurice St",
    "sg:city":"Wagga Wagga",
    "sg:classifiers":[
        {
            "category":"Organizations",
            "subcategory":"Non-profit Organization",
            "type":"Services"
        }
    ],
    "sg:phone":"+61 2 6921 9225",
    "sg:postcode":"2650",
    "sg:province":"NSW",
    "sg:tags":[
        "support",
        "disability",
        "organisation"
    ],
    "wof:name":"Disability Advocacy Network Inc.",
    "wof:placetype":"venue"
},
  "geometry": {"coordinates":[147.370727539,-35.1075897217],"type":"Point"}
}