{
  "type": "Feature",
  "properties": {
    "addr:full":"33 Ilex St Red Cliffs VIC 3496",
    "addr:housenumber":"33",
    "addr:postcode":"3496",
    "addr:street":"Ilex St",
    "iso:country":"AU",
    "sg:address":"33 Ilex St",
    "sg:city":"Red Cliffs",
    "sg:classifiers":[
        {
            "category":"Shopping",
            "subcategory":"Clothing, Apparel, & Fashions",
            "type":"Retail Goods"
        }
    ],
    "sg:phone":"+61 3 5024 2269",
    "sg:postcode":"3496",
    "sg:province":"VIC",
    "sg:tags":[
        "menswear"
    ],
    "wof:name":"Room 33",
    "wof:placetype":"venue"
},
  "geometry": {"coordinates":[142.18817138700001,-34.3059959412],"type":"Point"}
}