{
  "type": "Feature",
  "properties": {
    "addr:full":"Shp 4/ 302 Maroondah Hwy Healesville VIC 3777",
    "addr:housenumber":"/ 302",
    "addr:postcode":"3777",
    "addr:street":"Maroondah Hwy",
    "iso:country":"AU",
    "sg:address":"Shp 4/ 302 Maroondah Hwy",
    "sg:city":"Healesville",
    "sg:classifiers":[
        {
            "category":"Travel",
            "subcategory":"Travel Agent",
            "type":"Entertainment"
        }
    ],
    "sg:phone":"+61 3 5962 2999",
    "sg:postcode":"3777",
    "sg:province":"VIC",
    "sg:tags":[
        "consultant"
    ],
    "wof:name":"Timeout Travel Pty Ltd",
    "wof:placetype":"venue"
},
  "geometry": {"coordinates":[145.518677,-37.653461],"type":"Point"}
}