{
  "type": "Feature",
  "properties": {
    "iso:country":"AU",
    "sg:address":"91 Moore Rd",
    "sg:city":"Dardanup",
    "sg:classifiers":[
        {
            "category":"Commercial Area",
            "type":"Public Place"
        }
    ],
    "sg:phone":"+61 8 9725 4400",
    "sg:postcode":"6236",
    "sg:province":"WA",
    "sg:tags":[
        "heavy",
        "carrier"
    ],
    "wof:name":"Brookes Transport Co",
    "wof:placetype":"venue"
},
  "geometry": {"coordinates":[115.713097,-33.398842],"type":"Point"}
}