{
  "type": "Feature",
  "properties": {
    "addr:full":"25 Lyall Rd Berwick VIC 3806",
    "addr:housenumber":"25",
    "addr:postcode":"3806",
    "addr:street":"Lyall Rd",
    "iso:country":"AU",
    "sg:address":"25 Lyall Rd",
    "sg:city":"Berwick",
    "sg:classifiers":[
        {
            "category":"Health Services",
            "subcategory":"Dentist",
            "type":"Services"
        }
    ],
    "sg:phone":"+61 3 9707 2299",
    "sg:postcode":"3806",
    "sg:province":"VIC",
    "wof:name":"Ng Trevor Dr",
    "wof:placetype":"venue"
},
  "geometry": {"coordinates":[145.346603394,-38.0290184021],"type":"Point"}
}