{
  "type": "Feature",
  "properties": {
    "iso:country":"AU",
    "sg:address":"62 Kingscliff St",
    "sg:city":"Kingscliff",
    "sg:classifiers":[
        {
            "category":"Education",
            "subcategory":"Kindergarten",
            "type":"Public Place"
        }
    ],
    "sg:phone":"+61 2 6674 2750",
    "sg:postcode":"2487",
    "sg:province":"NSW",
    "sg:tags":[
        "pre-schools"
    ],
    "wof:name":"Kingscliff Mini School",
    "wof:placetype":"venue"
},
  "geometry": {"coordinates":[153.56788635300001,-28.2454071045],"type":"Point"}
}