{
  "type": "Feature",
  "properties": {
    "addr:full":"22 Pine Av Newstead TAS 7250",
    "addr:housenumber":"22",
    "addr:postcode":"7250",
    "addr:street":"Pine Av",
    "iso:country":"AU",
    "sg:address":"22 Pine Av",
    "sg:city":"Newstead",
    "sg:classifiers":[
        {
            "category":"Health Services",
            "subcategory":"Doctor",
            "type":"Services"
        }
    ],
    "sg:phone":"+61 3 6334 0333",
    "sg:postcode":"7250",
    "sg:province":"TAS",
    "sg:tags":[
        "occupational",
        "safety"
    ],
    "wof:name":"Tasmanian Occupational Health & Safety Services",
    "wof:placetype":"venue"
},
  "geometry": {"coordinates":[147.16603088400001,-41.4398002625],"type":"Point"}
}