{
  "type": "Feature",
  "properties": {
    "addr:full":"23 Suffolk St Footscray West VIC 3012",
    "addr:housenumber":"23",
    "addr:postcode":"3012",
    "addr:street":"Suffolk St",
    "iso:country":"AU",
    "sg:address":"23 Suffolk St",
    "sg:city":"Footscray West",
    "sg:classifiers":[
        {
            "category":"Utilities",
            "subcategory":"Water",
            "type":"Services"
        }
    ],
    "sg:phone":"+61 3 9689 1735",
    "sg:postcode":"3012",
    "sg:province":"VIC",
    "sg:tags":[
        "hot",
        "system"
    ],
    "wof:name":"Red Robin Plumbing Service Pty Ltd",
    "wof:placetype":"venue"
},
  "geometry": {"coordinates":[144.88026428200001,-37.790348053],"type":"Point"}
}