{
  "type": "Feature",
  "properties": {
    "addr:full":"Cnr York St & Henry Parry Drv Gosford East NSW 2250",
    "addr:postcode":"2250",
    "addr:street":"Cnr York St & Henry Parry Drv",
    "iso:country":"AU",
    "sg:address":"Cnr York St & Henry Parry Drv",
    "sg:city":"Gosford East",
    "sg:classifiers":[
        {
            "category":"Autos & Motor Vehicles",
            "subcategory":"Automobile Sales",
            "type":"Retail Goods"
        }
    ],
    "sg:phone":"+61 2 4324 7796",
    "sg:postcode":"2250",
    "sg:province":"NSW",
    "sg:tags":[
        "car",
        "used"
    ],
    "wof:name":"Michael Clayton Motors",
    "wof:placetype":"venue"
},
  "geometry": {"coordinates":[151.34246826200001,-33.4354362488],"type":"Point"}
}