{
  "type": "Feature",
  "properties": {
    "iso:country":"AU",
    "sg:address":"111 Adelaide St",
    "sg:city":"Blayney",
    "sg:classifiers":[
        {
            "category":"Banks & Credit Unions",
            "subcategory":"Bank",
            "type":"Services"
        }
    ],
    "sg:phone":"+61 13 24 40",
    "sg:postcode":"2799",
    "sg:province":"NSW",
    "sg:tags":[
        "society"
    ],
    "wof:name":"Reliance Credit Union",
    "wof:placetype":"venue"
},
  "geometry": {"coordinates":[149.25671399999999,-33.525414],"type":"Point"}
}