{
  "type": "Feature",
  "properties": {
    "addr:full":"50 Gould St Enfield NSW 2136",
    "addr:housenumber":"50",
    "addr:postcode":"2136",
    "addr:street":"Gould St",
    "iso:country":"AU",
    "sg:address":"50 Gould St",
    "sg:city":"Enfield",
    "sg:classifiers":[
        {
            "category":"Real Estate",
            "subcategory":"Architect",
            "type":"Services"
        }
    ],
    "sg:phone":"+61 2 9742 5666",
    "sg:postcode":"2136",
    "sg:province":"NSW",
    "sg:tags":[
        "magnet",
        "magnetic",
        "material"
    ],
    "wof:name":"Paramag",
    "wof:placetype":"venue"
},
  "geometry": {"coordinates":[151.07229614299999,-33.8896827698],"type":"Point"}
}