{
  "type": "Feature",
  "properties": {
    "addr:full":"U1/ 1409 Burke Rd Kew East VIC 3102",
    "addr:housenumber":"1409",
    "addr:postcode":"3102",
    "addr:street":"U1 /;Burke Rd",
    "iso:country":"AU",
    "sg:address":"U1/ 1409 Burke Rd",
    "sg:city":"Kew East",
    "sg:classifiers":[
        {
            "category":"Banks & Credit Unions",
            "subcategory":"Investment Brokerage",
            "type":"Services"
        }
    ],
    "sg:phone":"+61 3 9017 4686",
    "sg:postcode":"3102",
    "sg:province":"VIC",
    "sg:tags":[
        "finance",
        "broker"
    ],
    "wof:name":"SRG Finance & Investments",
    "wof:placetype":"venue"
},
  "geometry": {"coordinates":[145.06370544399999,-37.7938804626],"type":"Point"}
}