{
  "type": "Feature",
  "properties": {
    "addr:full":"120 Reichardt Rd Winnellie NT 0820",
    "addr:housenumber":"120",
    "addr:postcode":"nt 0820",
    "addr:street":"Reichardt Rd",
    "iso:country":"AU",
    "sg:address":"120 Reichardt Rd",
    "sg:city":"Winnellie",
    "sg:classifiers":[
        {
            "category":"Wholesale",
            "subcategory":"Machinery & Supplies",
            "type":"Manufacturing & Wholesale Goods"
        }
    ],
    "sg:phone":"+61 8 8984 4939",
    "sg:postcode":"0820",
    "sg:province":"NT",
    "sg:tags":[
        "agricultural"
    ],
    "wof:name":"Winnellie Hydraulics",
    "wof:placetype":"venue"
},
  "geometry": {"coordinates":[130.871017456,-12.4287500381],"type":"Point"}
}