{
  "type": "Feature",
  "properties": {
    "addr:full":"193a Lava St Warrnambool VIC 3280",
    "addr:housenumber":"193a",
    "addr:postcode":"3280",
    "addr:street":"Lava St",
    "iso:country":"AU",
    "sg:address":"193a Lava St",
    "sg:city":"Warrnambool",
    "sg:classifiers":[
        {
            "category":"Insurance",
            "subcategory":"Hazard Insurance",
            "type":"Services"
        }
    ],
    "sg:phone":"+61 1300 308 803",
    "sg:postcode":"3280",
    "sg:province":"VIC",
    "sg:tags":[
        "fire",
        "accident",
        "marine"
    ],
    "wof:name":"QBE Insurance (Australia) Limited",
    "wof:placetype":"venue"
},
  "geometry": {"coordinates":[142.48248290999999,-38.3807830811],"type":"Point"}
}