{
  "type": "Feature",
  "properties": {
    "addr:full":"Lv1 1-25 Harbour St Darling Harbour NSW 2000",
    "addr:housenumber":"1-25",
    "addr:postcode":"2000",
    "addr:street":"Harbour St",
    "iso:country":"AU",
    "sg:address":"Lv1 1-25 Harbour St",
    "sg:city":"Darling Harbour",
    "sg:classifiers":[
        {
            "category":"Retail",
            "subcategory":"Event Space",
            "type":"Services"
        }
    ],
    "sg:phone":"+61 2 9318 1917",
    "sg:postcode":"2000",
    "sg:province":"NSW",
    "sg:tags":[
        "function",
        "organiser"
    ],
    "wof:name":"Darling Space",
    "wof:placetype":"venue"
},
  "geometry": {"coordinates":[151.20280456500001,-33.8745536804],"type":"Point"}
}