{
  "type": "Feature",
  "properties": {
    "addr:full":"114 Montpelier Rd Fortitude Valley QLD 4006",
    "addr:housenumber":"114",
    "addr:postcode":"4006",
    "addr:street":"Montpelier Rd",
    "iso:country":"AU",
    "sg:address":"114 Montpelier Rd",
    "sg:city":"Fortitude Valley",
    "sg:classifiers":[
        {
            "category":"Home & Garden",
            "subcategory":"Home Furnishings",
            "type":"Retail Goods"
        }
    ],
    "sg:phone":"+61 7 3854 1566",
    "sg:postcode":"4006",
    "sg:province":"QLD",
    "sg:tags":[
        "storage",
        "rack",
        "wine"
    ],
    "wof:name":"National Storage",
    "wof:placetype":"venue"
},
  "geometry": {"coordinates":[153.03910827600001,-27.4488182068],"type":"Point"}
}