{
  "type": "Feature",
  "properties": {
    "iso:country":"AU",
    "sg:address":"1681 Albany Hwy",
    "sg:city":"Kenwick",
    "sg:classifiers":[
        {
            "category":"Manufacturing",
            "subcategory":"Metals",
            "type":"Manufacturing & Wholesale Goods"
        }
    ],
    "sg:phone":"+61 8 9493 2883",
    "sg:postcode":"6107",
    "sg:province":"WA",
    "sg:tags":[
        "sheet",
        "worker"
    ],
    "wof:name":"Coverall Sheetmetal",
    "wof:placetype":"venue"
},
  "geometry": {"coordinates":[115.969451904,-32.0376815796],"type":"Point"}
}