{
  "type": "Feature",
  "properties": {
    "addr:full":"Peregian Beach Medical Centre Kingfisher Drv Peregian Beach QLD 4573",
    "addr:postcode":"4573",
    "addr:street":"Kingfisher Drv",
    "iso:country":"AU",
    "sg:address":"Peregian Beach Medical Centre Kingfisher Drv",
    "sg:city":"Peregian Beach",
    "sg:classifiers":[
        {
            "category":"Health Services",
            "subcategory":"Doctor",
            "type":"Services"
        }
    ],
    "sg:phone":"+61 7 5448 1381",
    "sg:postcode":"4573",
    "sg:province":"QLD",
    "sg:tags":[
        "medical",
        "practitioner"
    ],
    "wof:name":"Greening Anne Dr",
    "wof:placetype":"venue"
},
  "geometry": {"coordinates":[153.09707599999999,-26.478045],"type":"Point"}
}