{
  "type": "Feature",
  "properties": {
    "addr:full":"17 Oxford St Bondi Junction NSW 2022",
    "addr:housenumber":"17",
    "addr:postcode":"2022",
    "addr:street":"Oxford St",
    "iso:country":"AU",
    "sg:address":"17 Oxford St",
    "sg:city":"Bondi Junction",
    "sg:classifiers":[
        {
            "category":"Real Estate",
            "subcategory":"Real Estate Services",
            "type":"Services"
        }
    ],
    "sg:phone":"+61 2 9386 1122",
    "sg:postcode":"2022",
    "sg:province":"NSW",
    "sg:tags":[
        "consultant",
        "property"
    ],
    "wof:name":"Cardy & Company Pty Ltd",
    "wof:placetype":"venue"
},
  "geometry": {"coordinates":[151.24537658700001,-33.8913078308],"type":"Point"}
}