{
  "type": "Feature",
  "properties": {
    "addr:full":"Barrington House Barrington Rd Silverdale NSW 2752",
    "addr:postcode":"2752",
    "addr:street":"Barrington Rd",
    "iso:country":"AU",
    "sg:address":"Barrington House Barrington Rd",
    "sg:city":"Silverdale",
    "sg:classifiers":[
        {
            "category":"Building & Trades",
            "subcategory":"Construction",
            "type":"Services"
        }
    ],
    "sg:phone":"+61 2 4774 1770",
    "sg:postcode":"2752",
    "sg:province":"NSW",
    "sg:tags":[
        "contractor"
    ],
    "wof:name":"Fairlight Developments",
    "wof:placetype":"venue"
},
  "geometry": {"coordinates":[150.61686706500001,-33.9178581238],"type":"Point"}
}