{
  "type": "Feature",
  "properties": {
    "addr:full":"118A Dangar St Armidale NSW 2350",
    "addr:housenumber":"118a",
    "addr:postcode":"2350",
    "addr:street":"Dangar St",
    "iso:country":"AU",
    "sg:address":"118A Dangar St",
    "sg:city":"Armidale",
    "sg:classifiers":[
        {
            "category":"Real Estate",
            "subcategory":"Real Estate Agent",
            "type":"Services"
        }
    ],
    "sg:phone":"+61 2 6772 6626",
    "sg:postcode":"2350",
    "sg:province":"NSW",
    "wof:name":"Kurt Eggert Real Estate P/L",
    "wof:placetype":"venue"
},
  "geometry": {"coordinates":[151.66485595699999,-30.5141487122],"type":"Point"}
}