{
  "type": "Feature",
  "properties": {
    "addr:full":"Shop 9/ 17 Howard Ave Dee Why NSW 2099",
    "addr:housenumber":"shop 9 / 17",
    "addr:postcode":"2099",
    "addr:street":"Howard Ave",
    "iso:country":"AU",
    "sg:address":"Shop 9/ 17 Howard Ave",
    "sg:city":"Dee Why",
    "sg:classifiers":[
        {
            "category":"Professional",
            "subcategory":"Advertising",
            "type":"Services"
        }
    ],
    "sg:phone":"+61 2 9972 1574",
    "sg:postcode":"2099",
    "sg:province":"NSW",
    "sg:tags":[
        "balloon",
        "novelty"
    ],
    "wof:name":"D Y Bloomin' Balloons",
    "wof:placetype":"venue"
},
  "geometry": {"coordinates":[151.28822326700001,-33.7528038025],"type":"Point"}
}