{
  "type": "Feature",
  "properties": {
    "iso:country":"AU",
    "sg:address":"399 Centre Rd",
    "sg:city":"Bentleigh",
    "sg:classifiers":[
        {
            "category":"Shopping",
            "subcategory":"Clothing, Apparel, & Fashions",
            "type":"Retail Goods"
        }
    ],
    "sg:phone":"+61 3 9557 2751",
    "sg:postcode":"3204",
    "sg:province":"VIC",
    "sg:tags":[
        "menswear"
    ],
    "wof:name":"Stanley's Menswear",
    "wof:placetype":"venue"
},
  "geometry": {"coordinates":[145.03829999999999,-37.91824],"type":"Point"}
}