{
  "type": "Feature",
  "properties": {
    "addr:full":"10 Werwick St Hobart TAS 7000",
    "addr:housenumber":"10",
    "addr:postcode":"7000",
    "addr:street":"Werwick St",
    "iso:country":"AU",
    "sg:address":"10 Werwick St",
    "sg:city":"Hobart",
    "sg:classifiers":[
        {
            "category":"Building & Trades",
            "subcategory":"Construction",
            "type":"Services"
        }
    ],
    "sg:phone":"+61 3 6234 1400",
    "sg:postcode":"7000",
    "sg:province":"TAS",
    "sg:tags":[
        "industrial",
        "commercial",
        "air conditioning"
    ],
    "wof:name":"Haden",
    "wof:placetype":"venue"
},
  "geometry": {"coordinates":[147.31910705600001,-42.8710517883],"type":"Point"}
}