{
  "type": "Feature",
  "properties": {
    "addr:full":"16 Bluett Drv Smeaton Grange NSW 2567",
    "addr:housenumber":"16",
    "addr:postcode":"2567",
    "addr:street":"Bluett Drv",
    "iso:country":"AU",
    "sg:address":"16 Bluett Drv",
    "sg:city":"Smeaton Grange",
    "sg:classifiers":[
        {
            "category":"Mining & Drilling",
            "type":"Manufacturing & Wholesale Goods"
        }
    ],
    "sg:phone":"+61 2 4647 4680",
    "sg:postcode":"2567",
    "sg:province":"NSW",
    "sg:tags":[
        "equipment",
        "quarrying",
        "supply"
    ],
    "sg:website":"http://www.reoco.com.au",
    "wof:name":"Reoco",
    "wof:placetype":"venue"
},
  "geometry": {"coordinates":[150.761230469,-34.0374221802],"type":"Point"}
}