{
  "type": "Feature",
  "properties": {
    "iso:country":"AU",
    "sg:address":"73-77 Marlin St (West End)",
    "sg:city":"Smiths Beach",
    "sg:classifiers":[
        {
            "category":"Sports & Exercise",
            "subcategory":"Gym",
            "type":"Entertainment"
        }
    ],
    "sg:phone":"+61 3 5952 2467",
    "sg:postcode":"3922",
    "sg:province":"VIC",
    "sg:tags":[
        "health",
        "fitness"
    ],
    "wof:name":"Phillip Island Coastal Discovery Camp",
    "wof:placetype":"venue"
},
  "geometry": {"coordinates":[145.25758361800001,-38.5015449524],"type":"Point"}
}