{
  "type": "Feature",
  "properties": {
    "addr:full":"Gunnedah Rd Tamworth NSW 2340",
    "addr:postcode":"2340",
    "addr:street":"Gunnedah Rd",
    "iso:country":"AU",
    "sg:address":"Gunnedah Rd",
    "sg:city":"Tamworth",
    "sg:classifiers":[
        {
            "category":"Autos & Motor Vehicles",
            "subcategory":"Fuel & Gas Station",
            "type":"Retail Goods"
        }
    ],
    "sg:phone":"+61 2 6765 9092",
    "sg:postcode":"2340",
    "sg:province":"NSW",
    "wof:name":"BP Australia Limited",
    "wof:placetype":"venue"
},
  "geometry": {"coordinates":[150.9090271,-31.0956897736],"type":"Point"}
}