{
  "type": "Feature",
  "properties": {
    "iso:country":"AU",
    "sg:address":"31- 33 Park St",
    "sg:city":"North Rockhampton",
    "sg:classifiers":[
        {
            "category":"Industrial Area",
            "type":"Public Place"
        }
    ],
    "sg:phone":"+61 7 4922 3760",
    "sg:postcode":"4701",
    "sg:province":"QLD",
    "sg:tags":[
        "rural",
        "shed"
    ],
    "wof:name":"Steelpac Building Systems",
    "wof:placetype":"venue"
},
  "geometry": {"coordinates":[150.512908936,-23.3589611053],"type":"Point"}
}