{
  "type": "Feature",
  "properties": {
    "addr:full":"Shop 5 Dunn Bay Rd Dunsborough WA 6281",
    "addr:housenumber":"shop 5",
    "addr:postcode":"6281",
    "addr:street":"Dunn Bay Rd",
    "iso:country":"AU",
    "sg:address":"Shop 5 Dunn Bay Rd",
    "sg:city":"Dunsborough",
    "sg:classifiers":[
        {
            "category":"Food & Beverages",
            "subcategory":"Supermarket",
            "type":"Retail Goods"
        }
    ],
    "sg:phone":"+61 8 9755 3711",
    "sg:postcode":"6281",
    "sg:province":"WA",
    "sg:tags":[
        "grocery",
        "store"
    ],
    "wof:name":"Newmart",
    "wof:placetype":"venue"
},
  "geometry": {"coordinates":[115.11013794,-33.6140823364],"type":"Point"}
}