{
  "type": "Feature",
  "properties": {
    "addr:full":"109 Albany Creek Rd Aspley QLD 4034",
    "addr:housenumber":"109",
    "addr:postcode":"4034",
    "addr:street":"Albany Creek Rd",
    "iso:country":"AU",
    "sg:address":"109 Albany Creek Rd",
    "sg:city":"Aspley",
    "sg:classifiers":[
        {
            "category":"Social Services",
            "subcategory":"Retirement Home",
            "type":"Services"
        }
    ],
    "sg:phone":"+61 7 3862 8948",
    "sg:postcode":"4034",
    "sg:province":"QLD",
    "sg:tags":[
        "village"
    ],
    "wof:name":"Katandra (Compton Gardens)",
    "wof:placetype":"venue"
},
  "geometry": {"coordinates":[153.00973500000001,-27.362728],"type":"Point"}
}