{
  "type": "Feature",
  "properties": {
    "addr:full":"10 Kirwan Crt Kalgoorlie WA 6430",
    "addr:housenumber":"10",
    "addr:postcode":"6430",
    "addr:street":"Kirwan Crt",
    "iso:country":"AU",
    "sg:address":"10 Kirwan Crt",
    "sg:city":"Kalgoorlie",
    "sg:classifiers":[
        {
            "category":"Mining & Drilling",
            "type":"Manufacturing & Wholesale Goods"
        }
    ],
    "sg:phone":"+61 8 9021 1187",
    "sg:postcode":"6430",
    "sg:province":"WA",
    "sg:tags":[
        "boring",
        "contractor"
    ],
    "wof:name":"Sayers Drilling Pty Ltd",
    "wof:placetype":"venue"
},
  "geometry": {"coordinates":[121.455070496,-30.7249488831],"type":"Point"}
}