{
  "type": "Feature",
  "properties": {
    "iso:country":"AU",
    "sg:address":"97 Forrest Ave",
    "sg:city":"Bunbury",
    "sg:classifiers":[
        {
            "category":"Retail",
            "subcategory":"Auto Rental",
            "type":"Services"
        }
    ],
    "sg:phone":"+61 8 9791 8911",
    "sg:postcode":"6230",
    "sg:province":"WA",
    "sg:tags":[
        "car",
        "hire",
        "minibus"
    ],
    "wof:name":"Hertz",
    "wof:placetype":"venue"
},
  "geometry": {"coordinates":[115.651871,-33.339153],"type":"Point"}
}