{
  "type": "Feature",
  "properties": {
    "addr:full":"13 Darley St Forestville NSW 2087",
    "addr:housenumber":"13",
    "addr:postcode":"2087",
    "addr:street":"Darley St",
    "iso:country":"AU",
    "sg:address":"13 Darley St",
    "sg:city":"Forestville",
    "sg:classifiers":[
        {
            "category":"Health Services",
            "subcategory":"Doctor",
            "type":"Services"
        }
    ],
    "sg:phone":"+61 2 9451 3232",
    "sg:postcode":"2087",
    "sg:province":"NSW",
    "sg:tags":[
        "medical",
        "practitioner"
    ],
    "wof:name":"Tatomirovic Ruzica",
    "wof:placetype":"venue"
},
  "geometry": {"coordinates":[151.21377563499999,-33.7625732422],"type":"Point"}
}