{
  "type": "Feature",
  "properties": {
    "iso:country":"AU",
    "sg:address":"High St",
    "sg:city":"Eildon",
    "sg:classifiers":[
        {
            "category":"Health Services",
            "subcategory":"Nursing And Care Facility",
            "type":"Services"
        }
    ],
    "sg:phone":"+61 3 5774 2711",
    "sg:postcode":"3713",
    "sg:province":"VIC",
    "sg:tags":[
        "home"
    ],
    "wof:name":"Darlingford Upper Goulburn Nursing Home",
    "wof:placetype":"venue"
},
  "geometry": {"coordinates":[145.904373169,-37.2360801697],"type":"Point"}
}