{
  "type": "Feature",
  "properties": {
    "addr:full":"69 Grandview Drv Newport NSW 2106",
    "addr:housenumber":"69",
    "addr:postcode":"2106",
    "addr:street":"Grandview Drv",
    "iso:country":"AU",
    "sg:address":"69 Grandview Drv",
    "sg:city":"Newport",
    "sg:classifiers":[
        {
            "category":"Personal",
            "subcategory":"Massage",
            "type":"Services"
        }
    ],
    "sg:phone":"+61 2 9918 6326",
    "sg:postcode":"2106",
    "sg:province":"NSW",
    "sg:tags":[
        "therapy"
    ],
    "wof:name":"Carroll Alison",
    "wof:placetype":"venue"
},
  "geometry": {"coordinates":[151.315673828,-33.6511955261],"type":"Point"}
}