{
  "type": "Feature",
  "properties": {
    "addr:full":"Waratah St Cronulla NSW 2230",
    "addr:postcode":"2230",
    "addr:street":"Waratah St",
    "iso:country":"AU",
    "sg:address":"Waratah St",
    "sg:city":"Cronulla",
    "sg:classifiers":[
        {
            "category":"Recreation",
            "subcategory":"Sailing Club",
            "type":"Entertainment"
        }
    ],
    "sg:phone":"+61 2 9523 6114",
    "sg:postcode":"2230",
    "sg:province":"NSW",
    "sg:tags":[
        "yacht"
    ],
    "wof:name":"Cronulla Sailing Club Ltd",
    "wof:placetype":"venue"
},
  "geometry": {"coordinates":[151.15074157699999,-34.0574302673],"type":"Point"}
}