{
  "type": "Feature",
  "properties": {
    "addr:full":"Jacobs Well Rd Woongoolba QLD 4207",
    "addr:postcode":"4207",
    "addr:street":"Well Rd",
    "iso:country":"AU",
    "sg:address":"Jacobs Well Rd",
    "sg:city":"Woongoolba",
    "sg:classifiers":[
        {
            "category":"Social Services",
            "subcategory":"Child Care",
            "type":"Services"
        }
    ],
    "sg:phone":"+61 7 5546 1600",
    "sg:postcode":"4207",
    "sg:province":"QLD",
    "wof:name":"Woongoolba Limited Hours Child Care Centre",
    "wof:placetype":"venue"
},
  "geometry": {"coordinates":[153.318283081,-27.7451400757],"type":"Point"}
}