{
  "type": "Feature",
  "properties": {
    "iso:country":"AU",
    "sg:address":"Ste 1/41- 45 Rickard Rd",
    "sg:city":"Bankstown",
    "sg:classifiers":[
        {
            "category":"Personal",
            "subcategory":"Massage",
            "type":"Services"
        }
    ],
    "sg:phone":"+61 2 9708 3611",
    "sg:postcode":"2200",
    "sg:province":"NSW",
    "sg:tags":[
        "therapy"
    ],
    "wof:name":"Turner Tom",
    "wof:placetype":"venue"
},
  "geometry": {"coordinates":[151.03782699999999,-33.91457],"type":"Point"}
}