{
  "type": "Feature",
  "properties": {
    "addr:full":"21 Jemmy Pl Tamworth NSW 2340",
    "addr:housenumber":"21",
    "addr:postcode":"2340",
    "addr:street":"Jemmy Pl",
    "iso:country":"AU",
    "sg:address":"21 Jemmy Pl",
    "sg:city":"Tamworth",
    "sg:classifiers":[
        {
            "category":"Communications",
            "type":"Services"
        }
    ],
    "sg:phone":"+61 2 6761 8233",
    "sg:postcode":"2340",
    "sg:province":"NSW",
    "sg:tags":[
        "equipment",
        "satellite"
    ],
    "wof:name":"Peddell T & K",
    "wof:placetype":"venue"
},
  "geometry": {"coordinates":[150.895584106,-31.0604629517],"type":"Point"}
}