{
  "type": "Feature",
  "properties": {
    "addr:full":"Unit 9- 11 Lismore Ave Telarah NSW 2320",
    "addr:housenumber":"11",
    "addr:postcode":"2320",
    "addr:street":"Lismore Ave",
    "iso:country":"AU",
    "sg:address":"Unit 9- 11 Lismore Ave",
    "sg:city":"Telarah",
    "sg:classifiers":[
        {
            "category":"Building & Trades",
            "subcategory":"Construction",
            "type":"Services"
        }
    ],
    "sg:phone":"+61 2 4932 0499",
    "sg:postcode":"2320",
    "sg:province":"NSW",
    "sg:tags":[
        "concrete",
        "paving"
    ],
    "wof:name":"Hunter Press-Crete",
    "wof:placetype":"venue"
},
  "geometry": {"coordinates":[151.53099060100001,-32.7268028259],"type":"Point"}
}