{
  "type": "Feature",
  "properties": {
    "addr:full":"Eastern Business Centre Factory 57, 41-49 Norcal R Nunawading VIC 3131",
    "addr:housenumber":"57",
    "addr:postcode":"41-49;3131",
    "addr:street":"R",
    "iso:country":"AU",
    "sg:address":"Eastern Business Centre Factory 57, 41-49 Norcal R",
    "sg:city":"Nunawading",
    "sg:classifiers":[
        {
            "category":"Professional",
            "subcategory":"Computer Services",
            "type":"Services"
        }
    ],
    "sg:phone":"+61 1800 266 466",
    "sg:postcode":"3131",
    "sg:province":"VIC",
    "sg:tags":[
        "repairs",
        "upgrade",
        "equipment"
    ],
    "wof:name":"ABC Computer Support",
    "wof:placetype":"venue"
},
  "geometry": {"coordinates":[145.18138122600001,-37.8227958679],"type":"Point"}
}