{
  "type": "Feature",
  "properties": {
    "iso:country":"AU",
    "sg:address":"40 Crestwood Drv",
    "sg:city":"Goulburn",
    "sg:classifiers":[
        {
            "category":"Arena",
            "subcategory":"Sports Club",
            "type":"Entertainment"
        }
    ],
    "sg:phone":"+61 408 440 615",
    "sg:postcode":"2580",
    "sg:province":"NSW",
    "sg:tags":[
        "defence",
        "supply",
        "self",
        "instruction",
        "martial art"
    ],
    "wof:name":"Taekido Kai Martial Arts",
    "wof:placetype":"venue"
},
  "geometry": {"coordinates":[149.71485900900001,-34.7334480286],"type":"Point"}
}