{
  "type": "Feature",
  "properties": {
    "addr:full":"85 Macquarie Gr Caves Beach NSW 2281",
    "addr:housenumber":"85",
    "addr:postcode":"2281",
    "addr:street":"Macquarie Gr",
    "iso:country":"AU",
    "sg:address":"85 Macquarie Gr",
    "sg:city":"Caves Beach",
    "sg:classifiers":[
        {
            "category":"Building & Trades",
            "subcategory":"Construction",
            "type":"Services"
        }
    ],
    "sg:phone":"+61 2 4971 6251",
    "sg:postcode":"2281",
    "sg:province":"NSW",
    "sg:tags":[
        "contractor"
    ],
    "wof:name":"G M & S M Building Services",
    "wof:placetype":"venue"
},
  "geometry": {"coordinates":[151.642333984,-33.1087303162],"type":"Point"}
}