{
  "type": "Feature",
  "properties": {
    "addr:full":"47 Epsom Ave Belmont WA 6104",
    "addr:housenumber":"47",
    "addr:postcode":"6104",
    "addr:street":"Epsom Ave",
    "iso:country":"AU",
    "sg:address":"47 Epsom Ave",
    "sg:city":"Belmont",
    "sg:classifiers":[
        {
            "category":"Retail",
            "subcategory":"Veterinary Services",
            "type":"Services"
        }
    ],
    "sg:phone":"+61 8 9277 2231",
    "sg:postcode":"6104",
    "sg:province":"WA",
    "sg:tags":[
        "surgeon"
    ],
    "wof:name":"Epsom Ave Vet Clinic & Epsom Equine Centre",
    "wof:placetype":"venue"
},
  "geometry": {"coordinates":[115.932739258,-31.9364109039],"type":"Point"}
}