{
  "type": "Feature",
  "properties": {
    "addr:full":"32 Sagars Rd Kenthurst NSW 2156",
    "addr:housenumber":"32",
    "addr:postcode":"2156",
    "addr:street":"Sagars Rd",
    "iso:country":"AU",
    "sg:address":"32 Sagars Rd",
    "sg:city":"Kenthurst",
    "sg:classifiers":[
        {
            "category":"Building & Trades",
            "subcategory":"Construction",
            "type":"Services"
        }
    ],
    "sg:phone":"+61 2 9654 1158",
    "sg:postcode":"2156",
    "sg:province":"NSW",
    "sg:tags":[
        "contractor"
    ],
    "wof:name":"Bonneville Constructions Pty Ltd",
    "wof:placetype":"venue"
},
  "geometry": {"coordinates":[151.001953125,-33.6892814636],"type":"Point"}
}