{
  "type": "Feature",
  "properties": {
    "addr:full":"73 Woolwich Rd Hunters Hill NSW 2110",
    "addr:housenumber":"73",
    "addr:postcode":"2110",
    "addr:street":"Woolwich Rd",
    "iso:country":"AU",
    "sg:address":"73 Woolwich Rd",
    "sg:city":"Hunters Hill",
    "sg:classifiers":[
        {
            "category":"Real Estate",
            "subcategory":"Architect",
            "type":"Services"
        }
    ],
    "sg:phone":"+61 2 9879 4065",
    "sg:postcode":"2110",
    "sg:province":"NSW",
    "wof:name":"Belltec Pty Ltd",
    "wof:placetype":"venue"
},
  "geometry": {"coordinates":[151.168426514,-33.8401374817],"type":"Point"}
}