{
  "type": "Feature",
  "properties": {
    "iso:country":"AU",
    "sg:address":"15 Smith St",
    "sg:city":"Kalbarri",
    "sg:classifiers":[
        {
            "category":"Professional",
            "subcategory":"Accounting & Tax Preparation",
            "type":"Services"
        }
    ],
    "sg:phone":"+61 8 9937 1360",
    "sg:postcode":"6536",
    "sg:province":"WA",
    "sg:tags":[
        "consultant",
        "taxation"
    ],
    "wof:name":"Kalbarri Taxation Services",
    "wof:placetype":"venue"
},
  "geometry": {"coordinates":[114.17070007300001,-27.7035617828],"type":"Point"}
}