{
  "type": "Feature",
  "properties": {
    "addr:full":"35 William St Alexandria NSW 2015",
    "addr:housenumber":"35",
    "addr:postcode":"2015",
    "addr:street":"William St",
    "iso:country":"AU",
    "sg:address":"35 William St",
    "sg:city":"Alexandria",
    "sg:classifiers":[
        {
            "category":"Retail",
            "subcategory":"Auto Repair",
            "type":"Services"
        }
    ],
    "sg:phone":"+61 2 9698 8822",
    "sg:postcode":"2015",
    "sg:province":"NSW",
    "sg:tags":[
        "repairer",
        "motor",
        "engineer"
    ],
    "wof:name":"John Vawser Motors Pty Ltd",
    "wof:placetype":"venue"
},
  "geometry": {"coordinates":[151.198364258,-33.9125175476],"type":"Point"}
}