{
  "type": "Feature",
  "properties": {
    "addr:full":"Unit 2, 55 Piper Drv Ballina NSW 2478",
    "addr:housenumber":"55",
    "addr:postcode":"2478",
    "addr:street":"Piper Drv",
    "iso:country":"AU",
    "sg:address":"Unit 2, 55 Piper Drv",
    "sg:city":"Ballina",
    "sg:classifiers":[
        {
            "category":"Industrial Area",
            "type":"Public Place"
        }
    ],
    "sg:phone":"+61 418 458 758",
    "sg:postcode":"2478",
    "sg:province":"NSW",
    "sg:tags":[
        "floor"
    ],
    "wof:name":"Advanx Polyflek Seamless Flooring",
    "wof:placetype":"venue"
},
  "geometry": {"coordinates":[153.55540466299999,-28.8467082977],"type":"Point"}
}