{
  "type": "Feature",
  "properties": {
    "addr:full":"90 Murrumbeena Rd Murrumbeena VIC 3163",
    "addr:housenumber":"90",
    "addr:postcode":"3163",
    "addr:street":"Murrumbeena Rd",
    "iso:country":"AU",
    "sg:address":"90 Murrumbeena Rd",
    "sg:city":"Murrumbeena",
    "sg:classifiers":[
        {
            "category":"Fast Food",
            "type":"Food & Drink"
        }
    ],
    "sg:phone":"+61 3 9568 1530",
    "sg:postcode":"3163",
    "sg:province":"VIC",
    "sg:tags":[
        "away",
        "take"
    ],
    "wof:name":"Toscana Pizza",
    "wof:placetype":"venue"
},
  "geometry": {"coordinates":[145.066482544,-37.8905715942],"type":"Point"}
}