{
  "type": "Feature",
  "properties": {
    "iso:country":"AU",
    "sg:address":"Suite 8 191 Melbourne St",
    "sg:city":"North Adelaide",
    "sg:classifiers":[
        {
            "category":"Professional",
            "subcategory":"Accounting & Tax Preparation",
            "type":"Services"
        }
    ],
    "sg:phone":"+61 8 8367 0255",
    "sg:postcode":"5006",
    "sg:province":"SA",
    "sg:tags":[
        "deduction",
        "payroll"
    ],
    "wof:name":"Nursing Home Payroll Bureau",
    "wof:placetype":"venue"
},
  "geometry": {"coordinates":[138.604812622,-34.9086036682],"type":"Point"}
}