{
  "type": "Feature",
  "properties": {
    "addr:full":"5 Robertson La Crookwell NSW 2583",
    "addr:housenumber":"5",
    "addr:postcode":"2583",
    "addr:street":"Robertson La",
    "iso:country":"AU",
    "sg:address":"5 Robertson La",
    "sg:city":"Crookwell",
    "sg:classifiers":[
        {
            "category":"Retail",
            "subcategory":"Funeral Services",
            "type":"Services"
        }
    ],
    "sg:phone":"+61 2 4832 1352",
    "sg:postcode":"2583",
    "sg:province":"NSW",
    "sg:tags":[
        "director"
    ],
    "wof:name":"Kennedy R J & Co",
    "wof:placetype":"venue"
},
  "geometry": {"coordinates":[149.474685669,-34.4609298706],"type":"Point"}
}