{
  "type": "Feature",
  "properties": {
    "addr:full":"70 High St Kyneton VIC 3444",
    "addr:housenumber":"70",
    "addr:postcode":"3444",
    "addr:street":"High St",
    "iso:country":"AU",
    "sg:address":"70 High St",
    "sg:city":"Kyneton",
    "sg:classifiers":[
        {
            "category":"Professional",
            "subcategory":"Employment Agencies",
            "type":"Services"
        }
    ],
    "sg:phone":"+61 3 5422 0500",
    "sg:postcode":"3444",
    "sg:province":"VIC",
    "wof:name":"MAETS (JOBfutures)",
    "wof:placetype":"venue"
},
  "geometry": {"coordinates":[144.45684814399999,-37.2511940002],"type":"Point"}
}