{
  "type": "Feature",
  "properties": {
    "addr:full":"Shop 119 Brandon Park Shopng Cntr Glen Waverley VIC 3150",
    "addr:housenumber":"119",
    "addr:postcode":"3150",
    "addr:street":"Brandon Park Shopng Cntr",
    "iso:country":"AU",
    "sg:address":"Shop 119",
    "sg:city":"Brandon Park Shopng Cntr Glen Waverley",
    "sg:classifiers":[
        {
            "category":"Communications",
            "subcategory":"Film & Video Production",
            "type":"Services"
        }
    ],
    "sg:phone":"+61 3 9562 0126",
    "sg:postcode":"3150",
    "sg:province":"VIC",
    "sg:tags":[
        "dvd",
        "library"
    ],
    "wof:name":"Video Ezy",
    "wof:placetype":"venue"
},
  "geometry": {"coordinates":[145.16761779800001,-37.9133911133],"type":"Point"}
}