{
  "type": "Feature",
  "properties": {
    "addr:full":"60 Gray St Mt Gambier SA 5290",
    "addr:housenumber":"60",
    "addr:postcode":"5290",
    "addr:street":"Gray St",
    "iso:country":"AU",
    "sg:address":"60 Gray St",
    "sg:city":"Mt Gambier",
    "sg:classifiers":[
        {
            "category":"Shopping",
            "subcategory":"Pawn Shop",
            "type":"Retail Goods"
        }
    ],
    "sg:phone":"+61 8 8723 4652",
    "sg:postcode":"5290",
    "sg:province":"SA",
    "sg:tags":[
        "pawnbroker"
    ],
    "wof:name":"Cash Zone",
    "wof:placetype":"venue"
},
  "geometry": {"coordinates":[140.778412,-37.82851],"type":"Point"}
}