{
  "type": "Feature",
  "properties": {
    "addr:full":"Caxton St Milton QLD 4064",
    "addr:postcode":"4064",
    "addr:street":"Caxton St",
    "iso:country":"AU",
    "sg:address":"Caxton St",
    "sg:city":"Milton",
    "sg:classifiers":[
        {
            "category":"Arena",
            "subcategory":"Sports Club",
            "type":"Entertainment"
        }
    ],
    "sg:phone":"+61 7 3369 8955",
    "sg:postcode":"4064",
    "sg:province":"QLD",
    "sg:tags":[
        "organisation",
        "sporting"
    ],
    "wof:name":"Sports Federation of Qld Inc",
    "wof:placetype":"venue"
},
  "geometry": {"coordinates":[153.00906372099999,-27.4624919891],"type":"Point"}
}