{
  "type": "Feature",
  "properties": {
    "iso:country":"AU",
    "sg:address":"Kwinana Hub Shopping Centre, Gilmore Ave",
    "sg:city":"Kwinana",
    "sg:classifiers":[
        {
            "category":"Communications",
            "subcategory":"Film & Video Production",
            "type":"Services"
        }
    ],
    "sg:phone":"+61 8 9439 5599",
    "sg:postcode":"6167",
    "sg:province":"WA",
    "sg:tags":[
        "dvd",
        "library"
    ],
    "wof:name":"Video Ezy",
    "wof:placetype":"venue"
},
  "geometry": {"coordinates":[115.809517,-32.226868],"type":"Point"}
}