{
  "type": "Feature",
  "properties": {
    "addr:full":"888 Tallebudgera Creek Rd Tallebudgera QLD 4228",
    "addr:housenumber":"888",
    "addr:postcode":"4228",
    "addr:street":"Tallebudgera Creek Rd",
    "iso:country":"AU",
    "sg:address":"888 Tallebudgera Creek Rd",
    "sg:city":"Tallebudgera",
    "sg:classifiers":[
        {
            "category":"Building & Trades",
            "subcategory":"Construction",
            "type":"Services"
        }
    ],
    "sg:phone":"+61 7 5533 8100",
    "sg:postcode":"4228",
    "sg:province":"QLD",
    "sg:tags":[
        "contractor"
    ],
    "wof:name":"Cramp Brian Homes",
    "wof:placetype":"venue"
},
  "geometry": {"coordinates":[153.380584717,-28.1669712067],"type":"Point"}
}