{
  "type": "Feature",
  "properties": {
    "addr:full":"Lonergan Rd Cobram NSW 3644",
    "addr:postcode":"3644",
    "addr:street":"Lonergan Rd",
    "iso:country":"AU",
    "sg:address":"Lonergan Rd",
    "sg:city":"Cobram",
    "sg:classifiers":[
        {
            "category":"Farming",
            "subcategory":"Berry Farm",
            "type":"Manufacturing & Wholesale Goods"
        }
    ],
    "sg:phone":"+61 3 5873 2384",
    "sg:postcode":"3644",
    "sg:province":"NSW",
    "sg:tags":[
        "fruit",
        "grower"
    ],
    "wof:name":"Mete P & L",
    "wof:placetype":"venue"
},
  "geometry": {"coordinates":[145.66885375999999,-35.9553108215],"type":"Point"}
}