{
  "type": "Feature",
  "properties": {
    "iso:country":"AU",
    "sg:address":"103 Newbridge Rd",
    "sg:city":"Moorebank",
    "sg:classifiers":[
        {
            "category":"Recreation",
            "subcategory":"Boat Charter",
            "type":"Entertainment"
        }
    ],
    "sg:phone":"+61 2 9821 3633",
    "sg:postcode":"2170",
    "sg:province":"NSW",
    "sg:tags":[
        "canopy",
        "motor"
    ],
    "wof:name":"Brahma Canopies",
    "wof:placetype":"venue"
},
  "geometry": {"coordinates":[150.940185547,-33.9296112061],"type":"Point"}
}