{
  "type": "Feature",
  "properties": {
    "addr:full":"15 Purrumbete Ave Manifold Heights VIC 3218",
    "addr:housenumber":"15",
    "addr:postcode":"3218",
    "addr:street":"Purrumbete Ave",
    "iso:country":"AU",
    "sg:address":"15 Purrumbete Ave",
    "sg:city":"Manifold Heights",
    "sg:classifiers":[
        {
            "category":"Home & Garden",
            "subcategory":"Carpets & Floor Coverings",
            "type":"Retail Goods"
        }
    ],
    "sg:phone":"+61 3 5221 1266",
    "sg:postcode":"3218",
    "sg:province":"VIC",
    "sg:tags":[
        "tile",
        "wall"
    ],
    "wof:name":"Walker Frank",
    "wof:placetype":"venue"
},
  "geometry": {"coordinates":[144.33282470699999,-38.1343078613],"type":"Point"}
}