{
  "type": "Feature",
  "properties": {
    "iso:country":"AU",
    "sg:address":"28a Ryrie St",
    "sg:city":"Geelong",
    "sg:classifiers":[
        {
            "category":"Cafe",
            "type":"Food & Drink"
        }
    ],
    "sg:phone":"+61 3 5229 5540",
    "sg:postcode":"3220",
    "sg:province":"VIC",
    "wof:name":"Ms Rubys Cafe",
    "wof:placetype":"venue"
},
  "geometry": {"coordinates":[144.354355,-38.147945],"type":"Point"}
}