{
  "type": "Feature",
  "properties": {
    "addr:full":"18 Careebong Rd Frenchs Forest NSW 2086",
    "addr:housenumber":"18",
    "addr:postcode":"2086",
    "addr:street":"Careebong Rd",
    "iso:country":"AU",
    "sg:address":"18 Careebong Rd",
    "sg:city":"Frenchs Forest",
    "sg:classifiers":[
        {
            "category":"Health Services",
            "subcategory":"Health Practitioner",
            "type":"Services"
        }
    ],
    "sg:phone":"+61 2 9975 3153",
    "sg:postcode":"2086",
    "sg:province":"NSW",
    "sg:tags":[
        "homoeopath"
    ],
    "wof:name":"Daisley Snow Jane",
    "wof:placetype":"venue"
},
  "geometry": {"coordinates":[151.224487305,-33.7557144165],"type":"Point"}
}