{
  "type": "Feature",
  "properties": {
    "addr:full":"7 Braidwood St Nelligen NSW 2536",
    "addr:housenumber":"7",
    "addr:postcode":"2536",
    "addr:street":"Braidwood St",
    "iso:country":"AU",
    "sg:address":"7 Braidwood St",
    "sg:city":"Nelligen",
    "sg:classifiers":[
        {
            "category":"Cafe",
            "type":"Food & Drink"
        }
    ],
    "sg:phone":"+61 2 4478 1109",
    "sg:postcode":"2536",
    "sg:province":"NSW",
    "wof:name":"Cafe Nelligen",
    "wof:placetype":"venue"
},
  "geometry": {"coordinates":[150.14109802199999,-35.6480979919],"type":"Point"}
}