{
  "type": "Feature",
  "properties": {
    "addr:full":"181 - 189 Fison Avenue West Eagle Farm QLD 4009",
    "addr:housenumber":"189",
    "addr:postcode":"4009",
    "addr:street":"Fison Avenue West",
    "iso:country":"AU",
    "sg:address":"181 - 189",
    "sg:city":"Fison Avenue West Eagle Farm",
    "sg:classifiers":[
        {
            "category":"Home & Garden",
            "subcategory":"Home Furnishings",
            "type":"Retail Goods"
        }
    ],
    "sg:phone":"+61 1300 303 279",
    "sg:postcode":"4009",
    "sg:province":"QLD",
    "sg:tags":[
        "shower",
        "screen"
    ],
    "wof:name":"Euro Direct",
    "wof:placetype":"venue"
},
  "geometry": {"coordinates":[153.09205627399999,-27.4366970062],"type":"Point"}
}