{
  "type": "Feature",
  "properties": {
    "iso:country":"AU",
    "sg:address":"204 Excelsior Ave",
    "sg:city":"Castle Hill",
    "sg:classifiers":[
        {
            "category":"Banks & Credit Unions",
            "subcategory":"Investment Brokerage",
            "type":"Services"
        }
    ],
    "sg:phone":"+61 2 9899 4211",
    "sg:postcode":"2154",
    "sg:province":"NSW",
    "wof:name":"Lifespan Financial Planning Pty Ltd",
    "wof:placetype":"venue"
},
  "geometry": {"coordinates":[151.002716064,-33.7458839417],"type":"Point"}
}