{
  "type": "Feature",
  "properties": {
    "iso:country":"AU",
    "sg:address":"153 Stahls Rd",
    "sg:city":"Oakville",
    "sg:classifiers":[
        {
            "category":"Building & Trades",
            "subcategory":"Construction",
            "type":"Services"
        }
    ],
    "sg:phone":"+61 2 9627 1501",
    "sg:postcode":"2765",
    "sg:province":"NSW",
    "sg:tags":[
        "contractor"
    ],
    "wof:name":"Riverford Homes Pty Ltd",
    "wof:placetype":"venue"
},
  "geometry": {"coordinates":[150.86250305199999,-33.6239128113],"type":"Point"}
}