{
  "type": "Feature",
  "properties": {
    "addr:full":"20 Allowrie St Jamberoo NSW 2533",
    "addr:housenumber":"20",
    "addr:postcode":"2533",
    "addr:street":"Allowrie St",
    "iso:country":"AU",
    "sg:address":"20 Allowrie St",
    "sg:city":"Jamberoo",
    "sg:classifiers":[
        {
            "category":"Wholesale",
            "subcategory":"Farm Supplies",
            "type":"Manufacturing & Wholesale Goods"
        }
    ],
    "sg:phone":"+61 2 4236 0854",
    "sg:postcode":"2533",
    "sg:province":"NSW",
    "sg:tags":[
        "feed",
        "supplement",
        "stock"
    ],
    "wof:name":"Fallsview Horse Herbs",
    "wof:placetype":"venue"
},
  "geometry": {"coordinates":[150.77580261200001,-34.6484985352],"type":"Point"}
}