{
  "type": "Feature",
  "properties": {
    "iso:country":"AU",
    "sg:address":"PO Box 4091",
    "sg:city":"Tregear",
    "sg:classifiers":[
        {
            "category":"Organizations",
            "subcategory":"Professional Association",
            "type":"Services"
        }
    ],
    "sg:phone":"+61 2 8572 8284",
    "sg:postcode":"2770",
    "sg:province":"NSW",
    "sg:tags":[
        "web",
        "internet"
    ],
    "wof:name":"Family Deals",
    "wof:placetype":"venue"
},
  "geometry": {"coordinates":[150.79685974099999,-33.7514190674],"type":"Point"}
}