{
  "type": "Feature",
  "properties": {
    "addr:full":"McMahons Reef Rd Galong NSW 2585",
    "addr:postcode":"2585",
    "addr:street":"Mcmahons Reef Rd",
    "iso:country":"AU",
    "sg:address":"McMahons Reef Rd",
    "sg:city":"Galong",
    "sg:classifiers":[
        {
            "category":"Retail",
            "subcategory":"Auto Repair",
            "type":"Services"
        }
    ],
    "sg:phone":"+61 2 6386 7219",
    "sg:postcode":"2585",
    "sg:province":"NSW",
    "sg:tags":[
        "repairer",
        "motor",
        "engineer"
    ],
    "wof:name":"Luke's Garage",
    "wof:placetype":"venue"
},
  "geometry": {"coordinates":[148.507644653,-34.6060714722],"type":"Point"}
}