{
  "type": "Feature",
  "properties": {
    "addr:full":"8-10 Victoria St Dubbo West NSW 2830",
    "addr:housenumber":"8-10",
    "addr:postcode":"2830",
    "addr:street":"Victoria St",
    "iso:country":"AU",
    "sg:address":"8-10 Victoria St",
    "sg:city":"Dubbo West",
    "sg:classifiers":[
        {
            "category":"Building & Trades",
            "subcategory":"Construction",
            "type":"Services"
        }
    ],
    "sg:phone":"+61 1800 023 380",
    "sg:postcode":"2830",
    "sg:province":"NSW",
    "sg:tags":[
        "insulation",
        "contractor"
    ],
    "wof:name":"Bradford Insulation",
    "wof:placetype":"venue"
},
  "geometry": {"coordinates":[148.59437560999999,-32.2494926453],"type":"Point"}
}