{
  "type": "Feature",
  "properties": {
    "addr:full":"2/ 410 Queen St Brisbane QLD 4000",
    "addr:housenumber":"/ 410",
    "addr:postcode":"4000",
    "addr:street":"Queen St",
    "iso:country":"AU",
    "sg:address":"2/ 410 Queen St",
    "sg:city":"Brisbane",
    "sg:classifiers":[
        {
            "category":"Airline",
            "type":"Transportation"
        }
    ],
    "sg:phone":"+61 1800 642 438",
    "sg:postcode":"4000",
    "sg:province":"QLD",
    "sg:tags":[
        "agent"
    ],
    "wof:name":"Austrian Airlines",
    "wof:placetype":"venue"
},
  "geometry": {"coordinates":[153.03074645999999,-27.4651298523],"type":"Point"}
}