{
  "type": "Feature",
  "properties": {
    "iso:country":"AU",
    "sg:address":"8 Flirtation Ave",
    "sg:city":"Mudgee",
    "sg:classifiers":[
        {
            "category":"Building & Trades",
            "subcategory":"Equipment Rental",
            "type":"Services"
        }
    ],
    "sg:phone":"+61 2 6372 9272",
    "sg:postcode":"2850",
    "sg:province":"NSW",
    "sg:tags":[
        "party",
        "hire"
    ],
    "wof:name":"Mudgee Marquees",
    "wof:placetype":"venue"
},
  "geometry": {"coordinates":[149.57759100000001,-32.601513],"type":"Point"}
}