{
  "type": "Feature",
  "properties": {
    "addr:full":"Tim Hill Reserve Wandana Heights Rd Wandana Heights VIC 3216",
    "addr:postcode":"3216",
    "addr:street":"Wandana Heights Rd",
    "iso:country":"AU",
    "sg:address":"Tim Hill Reserve Wandana Heights Rd",
    "sg:city":"Wandana Heights",
    "sg:classifiers":[
        {
            "category":"Government",
            "subcategory":"City Hall",
            "type":"Public Place"
        }
    ],
    "sg:phone":"+61 3 5272 4732",
    "sg:postcode":"3216",
    "sg:province":"VIC",
    "wof:name":"Wandana Heights Hall",
    "wof:placetype":"venue"
},
  "geometry": {"coordinates":[144.29991149899999,-38.1742477417],"type":"Point"}
}