{
  "type": "Feature",
  "properties": {
    "addr:full":"Level 20, St Martins Tower, Market St Sydney NSW 2000",
    "addr:postcode":"2000",
    "addr:street":"Market St",
    "iso:country":"AU",
    "sg:address":"Level 20, St Martins Tower, Market St",
    "sg:city":"Sydney",
    "sg:classifiers":[
        {
            "category":"Banks & Credit Unions",
            "subcategory":"Investment Brokerage",
            "type":"Services"
        }
    ],
    "sg:phone":"+61 2 9264 4900",
    "sg:postcode":"2000",
    "sg:province":"NSW",
    "wof:name":"Lifespan Financial Planning Pty Ltd",
    "wof:placetype":"venue"
},
  "geometry": {"coordinates":[151.210113525,-33.870716095],"type":"Point"}
}