{
  "type": "Feature",
  "properties": {
    "iso:country":"AU",
    "sg:address":"Annie St",
    "sg:city":"Wickham",
    "sg:classifiers":[
        {
            "category":"Shopping",
            "type":"Retail Goods"
        }
    ],
    "sg:phone":"+61 2 4969 2650",
    "sg:postcode":"2293",
    "sg:province":"NSW",
    "sg:tags":[
        "agent",
        "stock"
    ],
    "wof:name":"Elders Limited",
    "wof:placetype":"venue"
},
  "geometry": {"coordinates":[151.75779724099999,-32.9168357849],"type":"Point"}
}