{
  "type": "Feature",
  "properties": {
    "addr:full":"402 Torquay Rd Grovedale VIC 3216",
    "addr:housenumber":"402",
    "addr:postcode":"3216",
    "addr:street":"Torquay Rd",
    "iso:country":"AU",
    "sg:address":"402 Torquay Rd",
    "sg:city":"Grovedale",
    "sg:classifiers":[
        {
            "category":"Industrial Area",
            "type":"Public Place"
        }
    ],
    "sg:phone":"+61 415 228 633",
    "sg:postcode":"3216",
    "sg:province":"VIC",
    "sg:tags":[
        "floor"
    ],
    "wof:name":"Geelong Floor Sanders",
    "wof:placetype":"venue"
},
  "geometry": {"coordinates":[144.343505859,-38.1889305115],"type":"Point"}
}