{
  "type": "Feature",
  "properties": {
    "addr:full":"70 Darley Rd Paradise SA 5075",
    "addr:housenumber":"70",
    "addr:postcode":"5075",
    "addr:street":"Darley Rd",
    "iso:country":"AU",
    "sg:address":"70 Darley Rd",
    "sg:city":"Paradise",
    "sg:classifiers":[
        {
            "category":"Banks & Credit Unions",
            "subcategory":"Financial Services",
            "type":"Services"
        }
    ],
    "sg:phone":"+61 8 8365 9282",
    "sg:postcode":"5075",
    "sg:province":"SA",
    "sg:tags":[
        "planning"
    ],
    "wof:name":"Gupta Satish",
    "wof:placetype":"venue"
},
  "geometry": {"coordinates":[138.66529846200001,-34.8697967529],"type":"Point"}
}