{
  "type": "Feature",
  "properties": {
    "iso:country":"AU",
    "sg:address":"10 Phyllis Ave",
    "sg:city":"Picnic Point",
    "sg:classifiers":[
        {
            "category":"Autos & Motor Vehicles",
            "subcategory":"Boat Sales",
            "type":"Retail Goods"
        }
    ],
    "sg:phone":"+61 430 439 914",
    "sg:postcode":"2213",
    "sg:province":"NSW",
    "sg:tags":[
        "equipment",
        "yacht"
    ],
    "wof:name":"Ojprops Australia",
    "wof:placetype":"venue"
},
  "geometry": {"coordinates":[151.01083399999999,-33.96368],"type":"Point"}
}