{
  "type": "Feature",
  "properties": {
    "iso:country":"AU",
    "sg:address":"89 Giblett St",
    "sg:city":"Manjimup",
    "sg:classifiers":[
        {
            "category":"Food & Beverages",
            "subcategory":"Groceries & Convenience Stores",
            "type":"Retail Goods"
        }
    ],
    "sg:phone":"+61 8 9777 1821",
    "sg:postcode":"6258",
    "sg:province":"WA",
    "wof:name":"Manjimup Community Food Centre Inc",
    "wof:placetype":"venue"
},
  "geometry": {"coordinates":[116.148231506,-34.2384338379],"type":"Point"}
}