{
  "type": "Feature",
  "properties": {
    "addr:full":"16 Gheringhap St Geelong VIC 3220",
    "addr:housenumber":"16",
    "addr:postcode":"3220",
    "addr:street":"Gheringhap St",
    "iso:country":"AU",
    "sg:address":"16 Gheringhap St",
    "sg:city":"Geelong",
    "sg:classifiers":[
        {
            "category":"Travel",
            "subcategory":"Travel Agent",
            "type":"Entertainment"
        }
    ],
    "sg:phone":"+61 3 5222 2855",
    "sg:postcode":"3220",
    "sg:province":"VIC",
    "sg:tags":[
        "tour",
        "holiday",
        "adventure"
    ],
    "wof:name":"Swagman Tours",
    "wof:placetype":"venue"
},
  "geometry": {"coordinates":[144.35876500000001,-38.145061],"type":"Point"}
}