{
  "type": "Feature",
  "properties": {
    "addr:full":"11 Fox St Granville NSW 2142",
    "addr:housenumber":"11",
    "addr:postcode":"2142",
    "addr:street":"Fox St",
    "iso:country":"AU",
    "sg:address":"11 Fox St",
    "sg:city":"Granville",
    "sg:classifiers":[
        {
            "category":"Professional",
            "subcategory":"Printing & Photocopies",
            "type":"Services"
        }
    ],
    "sg:phone":"+61 2 9897 5377",
    "sg:postcode":"2142",
    "sg:province":"NSW",
    "sg:tags":[
        "textile",
        "clothing"
    ],
    "wof:name":"Screengraphics Printing",
    "wof:placetype":"venue"
},
  "geometry": {"coordinates":[150.99693298299999,-33.8289260864],"type":"Point"}
}