{
  "type": "Feature",
  "properties": {
    "addr:full":"199 Victoria St Taree NSW 2430",
    "addr:housenumber":"199",
    "addr:postcode":"2430",
    "addr:street":"Victoria St",
    "iso:country":"AU",
    "sg:address":"199 Victoria St",
    "sg:city":"Taree",
    "sg:classifiers":[
        {
            "category":"Real Estate",
            "subcategory":"Real Estate Agent",
            "type":"Services"
        }
    ],
    "sg:phone":"+61 2 6552 3733",
    "sg:postcode":"2430",
    "sg:province":"NSW",
    "wof:name":"Professionals The (Taree)",
    "wof:placetype":"venue"
},
  "geometry": {"coordinates":[152.45985400000001,-31.913967],"type":"Point"}
}