{
  "type": "Feature",
  "properties": {
    "iso:country":"AU",
    "sg:address":"2 Farnell St",
    "sg:city":"Bunbury",
    "sg:classifiers":[
        {
            "category":"Personal",
            "subcategory":"Massage",
            "type":"Services"
        }
    ],
    "sg:phone":"+61 8 9791 6666",
    "sg:postcode":"6230",
    "sg:province":"WA",
    "sg:tags":[
        "therapy"
    ],
    "wof:name":"Eddie Forrest",
    "wof:placetype":"venue"
},
  "geometry": {"coordinates":[115.63195,-33.358025],"type":"Point"}
}