{
  "type": "Feature",
  "properties": {
    "addr:full":"4 Eadie St Sunbury VIC 3429",
    "addr:housenumber":"4",
    "addr:postcode":"3429",
    "addr:street":"Eadie St",
    "iso:country":"AU",
    "sg:address":"4 Eadie St",
    "sg:city":"Sunbury",
    "sg:classifiers":[
        {
            "category":"Banks & Credit Unions",
            "subcategory":"Investment Brokerage",
            "type":"Services"
        }
    ],
    "sg:phone":"+61 3 9740 9966",
    "sg:postcode":"3429",
    "sg:province":"VIC",
    "sg:tags":[
        "finance",
        "broker"
    ],
    "wof:name":"Sunbury Finance",
    "wof:placetype":"venue"
},
  "geometry": {"coordinates":[144.740432739,-37.5818595886],"type":"Point"}
}