{
  "type": "Feature",
  "properties": {
    "addr:full":"28 Phillis St Maylands SA 5069",
    "addr:housenumber":"28",
    "addr:postcode":"5069",
    "addr:street":"Phillis St",
    "iso:country":"AU",
    "sg:address":"28 Phillis St",
    "sg:city":"Maylands",
    "sg:classifiers":[
        {
            "category":"Building & Trades",
            "subcategory":"Landscaping Services",
            "type":"Services"
        }
    ],
    "sg:phone":"+61 8 8362 1444",
    "sg:postcode":"5069",
    "sg:province":"SA",
    "sg:tags":[
        "designer",
        "landscape",
        "contractor"
    ],
    "wof:name":"Cielens & Partners Pty Ltd",
    "wof:placetype":"venue"
},
  "geometry": {"coordinates":[138.63714599599999,-34.913066864],"type":"Point"}
}