{
  "type": "Feature",
  "properties": {
    "iso:country":"AU",
    "sg:address":"96 Rankin St",
    "sg:city":"Innisfail",
    "sg:classifiers":[
        {
            "category":"Education",
            "subcategory":"School",
            "type":"Public Place"
        }
    ],
    "sg:phone":"+61 7 4061 2994",
    "sg:postcode":"4860",
    "sg:province":"QLD",
    "wof:name":"Good Counsel Primary Catholic School",
    "wof:placetype":"venue"
},
  "geometry": {"coordinates":[146.02961730999999,-17.5202865601],"type":"Point"}
}