{
  "type": "Feature",
  "properties": {
    "addr:full":"35 George Rd Geraldton WA 6530",
    "addr:housenumber":"35",
    "addr:postcode":"6530",
    "addr:street":"George Rd",
    "iso:country":"AU",
    "sg:address":"35 George Rd",
    "sg:city":"Geraldton",
    "sg:classifiers":[
        {
            "category":"Farming",
            "subcategory":"Fish & Marine Products",
            "type":"Manufacturing & Wholesale Goods"
        }
    ],
    "sg:phone":"+61 8 9964 2202",
    "sg:postcode":"6530",
    "sg:province":"WA",
    "sg:tags":[
        "fisherman"
    ],
    "wof:name":"Laine V",
    "wof:placetype":"venue"
},
  "geometry": {"coordinates":[114.615577698,-28.7720737457],"type":"Point"}
}