{
  "type": "Feature",
  "properties": {
    "iso:country":"AU",
    "sg:address":"2 Talford St",
    "sg:city":"Rockhampton",
    "sg:classifiers":[
        {
            "category":"Health Services",
            "subcategory":"Doctor",
            "type":"Services"
        }
    ],
    "sg:phone":"+61 7 4921 3211",
    "sg:postcode":"4700",
    "sg:province":"QLD",
    "sg:tags":[
        "medical",
        "practitioner"
    ],
    "wof:name":"Kwong Robert N K Dr",
    "wof:placetype":"venue"
},
  "geometry": {"coordinates":[150.49734497099999,-23.3780651093],"type":"Point"}
}