{
  "type": "Feature",
  "properties": {
    "iso:country":"AU",
    "sg:address":"Level 2, Ambit House, 101 Northbourne Ave",
    "sg:city":"Canberra",
    "sg:classifiers":[
        {
            "category":"Professional",
            "subcategory":"Employment Agencies",
            "type":"Services"
        }
    ],
    "sg:phone":"+61 2 6245 1700",
    "sg:postcode":"2600",
    "sg:province":"ACT",
    "wof:name":"Ambit Recruitment",
    "wof:placetype":"venue"
},
  "geometry": {"coordinates":[149.1300354,-35.2711601257],"type":"Point"}
}