{
  "type": "Feature",
  "properties": {
    "addr:full":"Ste2/ 520 Swift St Albury NSW 2640",
    "addr:housenumber":"520",
    "addr:postcode":"2640",
    "addr:street":"Swift St",
    "iso:country":"AU",
    "sg:address":"Ste2/ 520 Swift St",
    "sg:city":"Albury",
    "sg:classifiers":[
        {
            "category":"Banks & Credit Unions",
            "subcategory":"Financial Services",
            "type":"Services"
        }
    ],
    "sg:phone":"+61 2 6041 6044",
    "sg:postcode":"2640",
    "sg:province":"NSW",
    "sg:tags":[
        "planning"
    ],
    "wof:name":"Futuro Financial Services",
    "wof:placetype":"venue"
},
  "geometry": {"coordinates":[146.91612243599999,-36.0787696838],"type":"Point"}
}