{
  "type": "Feature",
  "properties": {
    "addr:full":"521 Bridge Rd Richmond VIC 3121",
    "addr:housenumber":"521",
    "addr:postcode":"3121",
    "addr:street":"Bridge Rd",
    "iso:country":"AU",
    "sg:address":"521 Bridge Rd",
    "sg:city":"Richmond",
    "sg:classifiers":[
        {
            "category":"Utilities",
            "subcategory":"Telephone",
            "type":"Services"
        }
    ],
    "sg:phone":"+61 3 8420 9333",
    "sg:postcode":"3121",
    "sg:province":"VIC",
    "sg:tags":[
        "equipment",
        "system"
    ],
    "wof:name":"CDM Communications",
    "wof:placetype":"venue"
},
  "geometry": {"coordinates":[145.00770568900001,-37.8192977905],"type":"Point"}
}