{
  "type": "Feature",
  "properties": {
    "iso:country":"AU",
    "sg:address":"PO Box 122",
    "sg:city":"Milton",
    "sg:classifiers":[
        {
            "category":"Shopping",
            "subcategory":"Hobbies, Toys, & Games",
            "type":"Retail Goods"
        }
    ],
    "sg:phone":"+61 2 4455 4011",
    "sg:postcode":"2538",
    "sg:province":"NSW",
    "sg:tags":[
        "stamp"
    ],
    "wof:name":"Sydney Philatelics",
    "wof:placetype":"venue"
},
  "geometry": {"coordinates":[150.43661499000001,-35.316860199],"type":"Point"}
}