{
  "type": "Feature",
  "properties": {
    "addr:full":"Flat 2/ 789 Burwood Rd Hawthorn East VIC 3123",
    "addr:housenumber":"/ 789",
    "addr:postcode":"3123",
    "addr:street":"Burwood Rd",
    "iso:country":"AU",
    "sg:address":"Flat 2/ 789 Burwood Rd",
    "sg:city":"Hawthorn East",
    "sg:classifiers":[
        {
            "category":"Professional",
            "subcategory":"Accounting & Tax Preparation",
            "type":"Services"
        }
    ],
    "sg:phone":"+61 3 9882 4463",
    "sg:postcode":"3123",
    "sg:province":"VIC",
    "sg:tags":[
        "consultant",
        "taxation"
    ],
    "wof:name":"Amberstone Consulting",
    "wof:placetype":"venue"
},
  "geometry": {"coordinates":[145.05201721200001,-37.82447052],"type":"Point"}
}