{
  "type": "Feature",
  "properties": {
    "iso:country":"AU",
    "sg:address":"33 Murray St",
    "sg:city":"Wonthaggi",
    "sg:classifiers":[
        {
            "category":"Food & Beverages",
            "subcategory":"Supermarket",
            "type":"Retail Goods"
        }
    ],
    "sg:phone":"+61 3 5672 3584",
    "sg:postcode":"3995",
    "sg:province":"VIC",
    "sg:tags":[
        "grocery",
        "store"
    ],
    "wof:name":"NQR Supermarket Clearance Outlets",
    "wof:placetype":"venue"
},
  "geometry": {"coordinates":[145.58912699999999,-38.605198],"type":"Point"}
}