{
  "type": "Feature",
  "properties": {
    "addr:full":"17 Nowill St Condell Park NSW 2200",
    "addr:housenumber":"17",
    "addr:postcode":"2200",
    "addr:street":"Nowill St",
    "iso:country":"AU",
    "sg:address":"17 Nowill St",
    "sg:city":"Condell Park",
    "sg:classifiers":[
        {
            "category":"Shopping",
            "subcategory":"Stationery & Office Supplies",
            "type":"Retail Goods"
        }
    ],
    "sg:phone":"+61 2 9790 1666",
    "sg:postcode":"2200",
    "sg:province":"NSW",
    "sg:tags":[
        "equipment",
        "display",
        "exhibition"
    ],
    "wof:name":"Displays The Answer",
    "wof:placetype":"venue"
},
  "geometry": {"coordinates":[151.01359600000001,-33.930168],"type":"Point"}
}