{
  "type": "Feature",
  "properties": {
    "addr:full":"19 Nepean Hwy Seaford VIC 3198",
    "addr:housenumber":"19",
    "addr:postcode":"3198",
    "addr:street":"Nepean Hwy",
    "iso:country":"AU",
    "sg:address":"19 Nepean Hwy",
    "sg:city":"Seaford",
    "sg:classifiers":[
        {
            "category":"Retail",
            "subcategory":"Auto Repair",
            "type":"Services"
        }
    ],
    "sg:phone":"+61 418 535 287",
    "sg:postcode":"3198",
    "sg:province":"VIC",
    "sg:tags":[
        "repairer",
        "motor",
        "engineer"
    ],
    "wof:name":"Williams Brett",
    "wof:placetype":"venue"
},
  "geometry": {"coordinates":[145.12510681099999,-38.087928772],"type":"Point"}
}