{
  "type": "Feature",
  "properties": {
    "addr:full":"56 Woodrow Drv Coorparoo QLD 4151",
    "addr:housenumber":"56",
    "addr:postcode":"4151",
    "addr:street":"Woodrow Drv",
    "iso:country":"AU",
    "sg:address":"56 Woodrow Drv",
    "sg:city":"Coorparoo",
    "sg:classifiers":[
        {
            "category":"Building & Trades",
            "subcategory":"Construction",
            "type":"Services"
        }
    ],
    "sg:phone":"+61 423 982 625",
    "sg:postcode":"4151",
    "sg:province":"QLD",
    "sg:tags":[
        "renovation",
        "alterations",
        "extension",
        "contractor"
    ],
    "sg:website":"http://www.mcd.net.au",
    "wof:name":"MCD Construction",
    "wof:placetype":"venue"
},
  "geometry": {"coordinates":[153.06271362300001,-27.4875774384],"type":"Point"}
}