{
  "type": "Feature",
  "properties": {
    "addr:full":"727 Glen Huntly Rd Caulfield VIC 3162",
    "addr:housenumber":"727",
    "addr:postcode":"3162",
    "addr:street":"Glen Huntly Rd",
    "iso:country":"AU",
    "sg:address":"727 Glen Huntly Rd",
    "sg:city":"Caulfield",
    "sg:classifiers":[
        {
            "category":"Building & Trades",
            "subcategory":"Construction",
            "type":"Services"
        }
    ],
    "sg:phone":"+61 3 9532 4468",
    "sg:postcode":"3162",
    "sg:province":"VIC",
    "sg:tags":[
        "management"
    ],
    "wof:name":"Aige Property Services",
    "wof:placetype":"venue"
},
  "geometry": {"coordinates":[145.02011108400001,-37.886516571],"type":"Point"}
}