{
  "type": "Feature",
  "properties": {
    "addr:full":"62 Delmere St Canley Vale NSW 2166",
    "addr:housenumber":"62",
    "addr:postcode":"2166",
    "addr:street":"Delmere St",
    "iso:country":"AU",
    "sg:address":"62 Delmere St",
    "sg:city":"Canley Vale",
    "sg:classifiers":[
        {
            "category":"Personal",
            "type":"Services"
        }
    ],
    "sg:phone":"+61 2 9724 3555",
    "sg:postcode":"2166",
    "sg:province":"NSW",
    "sg:tags":[
        "career",
        "counselling"
    ],
    "wof:name":"Job Skills",
    "wof:placetype":"venue"
},
  "geometry": {"coordinates":[150.94099426299999,-33.8808250427],"type":"Point"}
}