{
  "type": "Feature",
  "properties": {
    "addr:full":"347 Buckley St Essendon West VIC 3040",
    "addr:housenumber":"347",
    "addr:postcode":"3040",
    "addr:street":"Buckley St",
    "iso:country":"AU",
    "sg:address":"347 Buckley St",
    "sg:city":"Essendon West",
    "sg:classifiers":[
        {
            "category":"Food & Beverages",
            "subcategory":"Supermarket",
            "type":"Retail Goods"
        }
    ],
    "sg:phone":"+61 3 9337 8228",
    "sg:postcode":"3040",
    "sg:province":"VIC",
    "sg:tags":[
        "grocery",
        "store"
    ],
    "wof:name":"Boundy's Supermarkets",
    "wof:placetype":"venue"
},
  "geometry": {"coordinates":[144.89726257300001,-37.7548713684],"type":"Point"}
}