{
  "type": "Feature",
  "properties": {
    "addr:full":"PO Box 86 Orford TAS 7190",
    "addr:postcode":"7190",
    "iso:country":"AU",
    "sg:address":"PO Box 86",
    "sg:city":"Orford",
    "sg:classifiers":[
        {
            "category":"Building & Trades",
            "subcategory":"Landscaping Services",
            "type":"Services"
        }
    ],
    "sg:phone":"+61 417 591 536",
    "sg:postcode":"7190",
    "sg:province":"TAS",
    "sg:tags":[
        "gardener"
    ],
    "wof:name":"Triabunna Garden Service",
    "wof:placetype":"venue"
},
  "geometry": {"coordinates":[147.90542600000001,-42.570992],"type":"Point"}
}