{
  "type": "Feature",
  "properties": {
    "addr:full":"3/ 31 Park St Glenbrook NSW 2773",
    "addr:housenumber":"/ 31",
    "addr:postcode":"2773",
    "addr:street":"Park St",
    "iso:country":"AU",
    "sg:address":"3/ 31 Park St",
    "sg:city":"Glenbrook",
    "sg:classifiers":[
        {
            "category":"Health Services",
            "subcategory":"Dentist",
            "type":"Services"
        }
    ],
    "sg:phone":"+61 2 4739 8422",
    "sg:postcode":"2773",
    "sg:province":"NSW",
    "wof:name":"Triantafyllou John,# Tsougranis Helen,# Lee Sue#-Jean#",
    "wof:placetype":"venue"
},
  "geometry": {"coordinates":[150.62208557100001,-33.7667961121],"type":"Point"}
}