{
  "type": "Feature",
  "properties": {
    "addr:full":"Shop 8, Cnr Bellarine Hwy & Coppards Rd Newcomb VIC 3219",
    "addr:housenumber":"shop 8 cnr",
    "addr:postcode":"3219",
    "addr:street":"Bellarine Hwy & Coppards Rd",
    "iso:country":"AU",
    "sg:address":"Shop 8, Cnr Bellarine Hwy & Coppards Rd",
    "sg:city":"Newcomb",
    "sg:classifiers":[
        {
            "category":"Banks & Credit Unions",
            "subcategory":"Financial Services",
            "type":"Services"
        }
    ],
    "sg:phone":"+61 3 5248 1092",
    "sg:postcode":"3219",
    "sg:province":"VIC",
    "sg:tags":[
        "planning"
    ],
    "wof:name":"Results Financial Services Pty Ltd",
    "wof:placetype":"venue"
},
  "geometry": {"coordinates":[144.390533447,-38.1701660156],"type":"Point"}
}