{
  "type": "Feature",
  "properties": {
    "addr:full":"Byron St Bangalow NSW 2479",
    "addr:postcode":"2479",
    "addr:street":"Byron St",
    "iso:country":"AU",
    "sg:address":"Byron St",
    "sg:city":"Bangalow",
    "sg:classifiers":[
        {
            "category":"Autos & Motor Vehicles",
            "subcategory":"Fuel & Gas Station",
            "type":"Retail Goods"
        }
    ],
    "sg:phone":"+61 2 6687 1447",
    "sg:postcode":"2479",
    "sg:province":"NSW",
    "wof:name":"BP Australia Limited",
    "wof:placetype":"venue"
},
  "geometry": {"coordinates":[153.528396606,-28.6856098175],"type":"Point"}
}