{
  "type": "Feature",
  "properties": {
    "addr:full":"Level 3/ 339 Coronation Drv Milton QLD 4064",
    "addr:housenumber":"/ 339",
    "addr:postcode":"4064",
    "addr:street":"Coronation Drv",
    "iso:country":"AU",
    "sg:address":"Level 3/ 339 Coronation Drv",
    "sg:city":"Milton",
    "sg:classifiers":[
        {
            "category":"Building & Trades",
            "subcategory":"Construction",
            "type":"Services"
        }
    ],
    "sg:phone":"+61 7 3858 9999",
    "sg:postcode":"4064",
    "sg:province":"QLD",
    "sg:tags":[
        "management"
    ],
    "wof:name":"Walter Construction Group Limited",
    "wof:placetype":"venue"
},
  "geometry": {"coordinates":[153.00311279300001,-27.474899292],"type":"Point"}
}