{
  "type": "Feature",
  "properties": {
    "addr:full":"31 Second St Magill SA 5072",
    "addr:housenumber":"31",
    "addr:postcode":"5072",
    "addr:street":"Second St",
    "iso:country":"AU",
    "sg:address":"31 Second St",
    "sg:city":"Magill",
    "sg:classifiers":[
        {
            "category":"Professional",
            "subcategory":"Art Services",
            "type":"Services"
        }
    ],
    "sg:phone":"+61 8 8431 7029",
    "sg:postcode":"5072",
    "sg:province":"SA",
    "sg:tags":[
        "interior",
        "decorator"
    ],
    "wof:name":"Inhouse Interiors",
    "wof:placetype":"venue"
},
  "geometry": {"coordinates":[138.67106628400001,-34.9037475586],"type":"Point"}
}