{
  "type": "Feature",
  "properties": {
    "addr:full":"19 Goldsmith St Goulburn NSW 2580",
    "addr:housenumber":"19",
    "addr:postcode":"2580",
    "addr:street":"Goldsmith St",
    "iso:country":"AU",
    "sg:address":"19 Goldsmith St",
    "sg:city":"Goulburn",
    "sg:classifiers":[
        {
            "category":"Retail",
            "subcategory":"Auto Rental",
            "type":"Services"
        }
    ],
    "sg:phone":"+61 2 4821 5566",
    "sg:postcode":"2580",
    "sg:province":"NSW",
    "sg:tags":[
        "car",
        "hire",
        "minibus"
    ],
    "wof:name":"Avis",
    "wof:placetype":"venue"
},
  "geometry": {"coordinates":[149.721893311,-34.7515144348],"type":"Point"}
}