{
  "type": "Feature",
  "properties": {
    "iso:country":"AU",
    "sg:address":"Suite 18 / 12 Tyron Rd",
    "sg:city":"Lindfield",
    "sg:classifiers":[
        {
            "category":"Health Services",
            "subcategory":"Health Practitioner",
            "type":"Services"
        }
    ],
    "sg:phone":"+61 2 9415 6144",
    "sg:postcode":"2070",
    "sg:province":"NSW",
    "sg:tags":[
        "psychologist"
    ],
    "wof:name":"ADHD Social Skills Counselling Group",
    "wof:placetype":"venue"
},
  "geometry": {"coordinates":[151.169525147,-33.7761230469],"type":"Point"}
}