{
  "type": "Feature",
  "properties": {
    "iso:country":"AU",
    "sg:address":"Room 1315 Holiday Inn 334 Flinders Mall",
    "sg:city":"Townsville",
    "sg:classifiers":[
        {
            "category":"Personal",
            "subcategory":"Massage",
            "type":"Services"
        }
    ],
    "sg:phone":"+61 7 4721 4754",
    "sg:postcode":"4810",
    "sg:province":"QLD",
    "sg:tags":[
        "therapy"
    ],
    "wof:name":"City Massage Clinic",
    "wof:placetype":"venue"
},
  "geometry": {"coordinates":[146.817123,-19.259705],"type":"Point"}
}