{
  "type": "Feature",
  "properties": {
    "addr:full":"Unit 2/8 Iffley Crt Ivanhoe VIC 3079",
    "addr:postcode":"3079",
    "addr:street":"Iffley Crt",
    "iso:country":"AU",
    "sg:address":"Unit 2/8 Iffley Crt",
    "sg:city":"Ivanhoe",
    "sg:classifiers":[
        {
            "category":"Bars & Pubs",
            "subcategory":"Dive Bar",
            "type":"Food & Drink"
        }
    ],
    "sg:phone":"+61 3 9499 1270",
    "sg:postcode":"3079",
    "sg:province":"VIC",
    "sg:tags":[
        "knitwear",
        "retail"
    ],
    "wof:name":"Glens Designs",
    "wof:placetype":"venue"
},
  "geometry": {"coordinates":[145.042404175,-37.7581253052],"type":"Point"}
}