{
  "type": "Feature",
  "properties": {
    "iso:country":"AU",
    "sg:address":"66a Broadarrow Rd",
    "sg:city":"Narwee",
    "sg:classifiers":[
        {
            "category":"Health Services",
            "subcategory":"Dentist",
            "type":"Services"
        }
    ],
    "sg:phone":"+61 2 9533 5895",
    "sg:postcode":"2209",
    "sg:province":"NSW",
    "wof:name":"Narwee Dental Surgery",
    "wof:placetype":"venue"
},
  "geometry": {"coordinates":[151.070312,-33.948624],"type":"Point"}
}