{
  "type": "Feature",
  "properties": {
    "addr:full":"25 Northern Ave Mentone VIC 3194",
    "addr:housenumber":"25",
    "addr:postcode":"3194",
    "addr:street":"Northern Ave",
    "iso:country":"AU",
    "sg:address":"25 Northern Ave",
    "sg:city":"Mentone",
    "sg:classifiers":[
        {
            "category":"Banks & Credit Unions",
            "subcategory":"Investment Brokerage",
            "type":"Services"
        }
    ],
    "sg:phone":"+61 3 9580 8000",
    "sg:postcode":"3194",
    "sg:province":"VIC",
    "sg:tags":[
        "baby",
        "wholesaler",
        "mfrs",
        "wear"
    ],
    "wof:name":"Koala Securities Pty Ltd",
    "wof:placetype":"venue"
},
  "geometry": {"coordinates":[145.08839416500001,-37.97265625],"type":"Point"}
}