{
  "type": "Feature",
  "properties": {
    "iso:country":"AU",
    "sg:address":"251 Concorde St",
    "sg:city":"North Strathfield",
    "sg:classifiers":[
        {
            "category":"Education",
            "subcategory":"Dance Studio",
            "type":"Public Place"
        }
    ],
    "sg:phone":"+61 421 802 303",
    "sg:postcode":"2137",
    "sg:province":"NSW",
    "sg:tags":[
        "venue",
        "tuition"
    ],
    "wof:name":"Stella Studios",
    "wof:placetype":"venue"
},
  "geometry": {"coordinates":[151.091064453,-33.8536376953],"type":"Point"}
}