{
  "type": "Feature",
  "properties": {
    "addr:full":"119 Charters Towers Rd Hermit Park QLD 4812",
    "addr:housenumber":"119",
    "addr:postcode":"4812",
    "addr:street":"Charters Towers Rd",
    "iso:country":"AU",
    "sg:address":"119 Charters Towers Rd",
    "sg:city":"Hermit Park",
    "sg:classifiers":[
        {
            "category":"Insurance",
            "subcategory":"Hazard Insurance",
            "type":"Services"
        }
    ],
    "sg:phone":"+61 7 4755 2122",
    "sg:postcode":"4812",
    "sg:province":"QLD",
    "sg:tags":[
        "loss",
        "adjuster",
        "assessor"
    ],
    "wof:name":"McLarens Young International",
    "wof:placetype":"venue"
},
  "geometry": {"coordinates":[146.80015599999999,-19.27704],"type":"Point"}
}