{
  "type": "Feature",
  "properties": {
    "addr:full":"39 Taurus St Southern Cross WA 6426",
    "addr:housenumber":"39",
    "addr:postcode":"6426",
    "addr:street":"Taurus St",
    "iso:country":"AU",
    "sg:address":"39 Taurus St",
    "sg:city":"Southern Cross",
    "sg:classifiers":[
        {
            "category":"Shopping",
            "type":"Retail Goods"
        }
    ],
    "sg:phone":"+61 8 9049 1057",
    "sg:postcode":"6426",
    "sg:province":"WA",
    "sg:tags":[
        "agent",
        "stock"
    ],
    "wof:name":"Elders Limited",
    "wof:placetype":"venue"
},
  "geometry": {"coordinates":[119.319878,-31.226349],"type":"Point"}
}