{
  "type": "Feature",
  "properties": {
    "addr:full":"Gillies St Rochester VIC 3561",
    "addr:postcode":"3561",
    "addr:street":"Gillies St",
    "iso:country":"AU",
    "sg:address":"Gillies St",
    "sg:city":"Rochester",
    "sg:classifiers":[
        {
            "category":"Food & Beverages",
            "subcategory":"Supermarket",
            "type":"Retail Goods"
        }
    ],
    "sg:phone":"+61 3 5484 1309",
    "sg:postcode":"3561",
    "sg:province":"VIC",
    "sg:tags":[
        "grocery",
        "store"
    ],
    "wof:name":"Majors Supermarket IGA",
    "wof:placetype":"venue"
},
  "geometry": {"coordinates":[144.70201110799999,-36.3616752625],"type":"Point"}
}