{
  "type": "Feature",
  "properties": {
    "iso:country":"AU",
    "sg:address":"9 Alister St",
    "sg:city":"Highbury",
    "sg:classifiers":[
        {
            "category":"Communications",
            "subcategory":"Film & Video Production",
            "type":"Services"
        }
    ],
    "sg:phone":"+61 8 8264 3604",
    "sg:postcode":"5089",
    "sg:province":"SA",
    "sg:tags":[
        "television",
        "system",
        "circuit",
        "closed"
    ],
    "wof:name":"Viatron Electrical",
    "wof:placetype":"venue"
},
  "geometry": {"coordinates":[138.70993042000001,-34.8501815796],"type":"Point"}
}