{
  "type": "Feature",
  "properties": {
    "addr:full":"124 Bass Meadows Blv St Andrews Beach VIC 3941",
    "addr:housenumber":"124",
    "addr:postcode":"3941",
    "addr:street":"Bass Meadows Blv St Andrews Beach",
    "iso:country":"AU",
    "sg:address":"124 Bass Meadows Blv St",
    "sg:city":"Andrews Beach",
    "sg:classifiers":[
        {
            "category":"Food & Beverages",
            "subcategory":"Groceries & Convenience Stores",
            "type":"Retail Goods"
        }
    ],
    "sg:phone":"+61 3 5988 6004",
    "sg:postcode":"3941",
    "sg:province":"VIC",
    "wof:name":"St Andrews Beach General Store",
    "wof:placetype":"venue"
},
  "geometry": {"coordinates":[144.832427978,-38.4191360474],"type":"Point"}
}