{
  "type": "Feature",
  "properties": {
    "addr:full":"8- 10 David St Doyalson NSW 2262",
    "addr:housenumber":"10",
    "addr:postcode":"2262",
    "addr:street":"8;David St",
    "iso:country":"AU",
    "sg:address":"8- 10 David St",
    "sg:city":"Doyalson",
    "sg:classifiers":[
        {
            "category":"Professional",
            "subcategory":"Engineering",
            "type":"Services"
        }
    ],
    "sg:phone":"+61 2 4390 0999",
    "sg:postcode":"2262",
    "sg:province":"NSW",
    "sg:tags":[
        "engineer"
    ],
    "wof:name":"Kmar Engineering Pty Ltd",
    "wof:placetype":"venue"
},
  "geometry": {"coordinates":[151.52314799999999,-33.203545],"type":"Point"}
}