{
  "type": "Feature",
  "properties": {
    "iso:country":"AU",
    "sg:address":"13 Hicks St",
    "sg:city":"Emerald",
    "sg:classifiers":[
        {
            "category":"Utilities",
            "subcategory":"Electric",
            "type":"Services"
        }
    ],
    "sg:phone":"+61 7 4982 3069",
    "sg:postcode":"4720",
    "sg:province":"QLD",
    "sg:tags":[
        "electrical",
        "contractor"
    ],
    "wof:name":"John Goss Projects",
    "wof:placetype":"venue"
},
  "geometry": {"coordinates":[148.14622499999999,-23.525003],"type":"Point"}
}