{
  "type": "Feature",
  "properties": {
    "addr:full":"372 Military Rd Cremorne NSW 2090",
    "addr:housenumber":"372",
    "addr:postcode":"2090",
    "addr:street":"Military Rd",
    "iso:country":"AU",
    "sg:address":"372 Military Rd",
    "sg:city":"Cremorne",
    "sg:classifiers":[
        {
            "category":"Utilities",
            "subcategory":"Telephone",
            "type":"Services"
        }
    ],
    "sg:phone":"+61 2 9904 1007",
    "sg:postcode":"2090",
    "sg:province":"NSW",
    "sg:tags":[
        "accessory"
    ],
    "wof:name":"Phonies",
    "wof:placetype":"venue"
},
  "geometry": {"coordinates":[151.22920227,-33.8284645081],"type":"Point"}
}