{
  "type": "Feature",
  "properties": {
    "addr:full":"Ruby Rd Gymea NSW 2227",
    "addr:postcode":"2227",
    "addr:street":"Ruby Rd",
    "iso:country":"AU",
    "sg:address":"Ruby Rd",
    "sg:city":"Gymea",
    "sg:classifiers":[
        {
            "category":"Social Services",
            "subcategory":"Child Care",
            "type":"Services"
        }
    ],
    "sg:phone":"+61 2 9524 3711",
    "sg:postcode":"2227",
    "sg:province":"NSW",
    "wof:name":"Tom Thumb Kindergarten",
    "wof:placetype":"venue"
},
  "geometry": {"coordinates":[151.089355469,-34.0255622864],"type":"Point"}
}