{
  "type": "Feature",
  "properties": {
    "addr:full":"424 Malvern Rd Prahran VIC 3181",
    "addr:housenumber":"424",
    "addr:postcode":"3181",
    "addr:street":"Malvern Rd",
    "iso:country":"AU",
    "sg:address":"424 Malvern Rd",
    "sg:city":"Prahran",
    "sg:classifiers":[
        {
            "category":"Manufacturing",
            "subcategory":"Chemicals & Compounds",
            "type":"Manufacturing & Wholesale Goods"
        }
    ],
    "sg:phone":"+61 3 9510 7586",
    "sg:postcode":"3181",
    "sg:province":"VIC",
    "sg:tags":[
        "electroplating"
    ],
    "wof:name":"Prahran Platers",
    "wof:placetype":"venue"
},
  "geometry": {"coordinates":[145.000854492,-37.8478851318],"type":"Point"}
}