{
  "type": "Feature",
  "properties": {
    "addr:full":"8- 14 Upper Dawson Rd Rockhampton QLD 4700",
    "addr:housenumber":"14",
    "addr:postcode":"4700",
    "addr:street":"8;Upper Dawson Rd",
    "iso:country":"AU",
    "sg:address":"8- 14 Upper Dawson Rd",
    "sg:city":"Rockhampton",
    "sg:classifiers":[
        {
            "category":"Travel",
            "subcategory":"Hotels & Motels",
            "type":"Entertainment"
        }
    ],
    "sg:phone":"+61 7 4922 1853",
    "sg:postcode":"4700",
    "sg:province":"QLD",
    "sg:tags":[
        "accommodation"
    ],
    "wof:name":"Allenstown Hotel",
    "wof:placetype":"venue"
},
  "geometry": {"coordinates":[150.50099182100001,-23.3992958069],"type":"Point"}
}