{
  "type": "Feature",
  "properties": {
    "addr:full":"197- 199 Military Rd Semaphore SA 5019",
    "addr:housenumber":"199",
    "addr:postcode":"5019",
    "addr:street":"Military Rd",
    "iso:country":"AU",
    "sg:address":"197- 199 Military Rd",
    "sg:city":"Semaphore",
    "sg:classifiers":[
        {
            "category":"Retail",
            "subcategory":"Auto Repair",
            "type":"Services"
        }
    ],
    "sg:phone":"+61 8 8341 5550",
    "sg:postcode":"5019",
    "sg:province":"SA",
    "sg:tags":[
        "muffler",
        "exhaust",
        "system"
    ],
    "wof:name":"Carline Mufflers",
    "wof:placetype":"venue"
},
  "geometry": {"coordinates":[138.483810425,-34.8388633728],"type":"Point"}
}