{
  "type": "Feature",
  "properties": {
    "addr:full":"22 Woodville Rd Granville NSW 2142",
    "addr:housenumber":"22",
    "addr:postcode":"2142",
    "addr:street":"Woodville Rd",
    "iso:country":"AU",
    "sg:address":"22 Woodville Rd",
    "sg:city":"Granville",
    "sg:classifiers":[
        {
            "category":"Building & Trades",
            "subcategory":"Landscaping Services",
            "type":"Services"
        }
    ],
    "sg:phone":"+61 415 108 494",
    "sg:postcode":"2142",
    "sg:province":"NSW",
    "sg:tags":[
        "stump",
        "tree",
        "felling",
        "removal"
    ],
    "wof:name":"Alligator Tree Lopping",
    "wof:placetype":"venue"
},
  "geometry": {"coordinates":[151.00369262699999,-33.8302078247],"type":"Point"}
}