{
  "type": "Feature",
  "properties": {
    "addr:full":"Suite17/ 423 King Georges Rds Beverly Hills NSW 2209",
    "addr:housenumber":"423",
    "addr:postcode":"2209",
    "addr:street":"King Georges Rds",
    "iso:country":"AU",
    "sg:address":"Suite17/ 423 King Georges Rds",
    "sg:city":"Beverly Hills",
    "sg:classifiers":[
        {
            "category":"Manufacturing",
            "subcategory":"Tools & Machinery",
            "type":"Manufacturing & Wholesale Goods"
        }
    ],
    "sg:phone":"+61 2 9570 7268",
    "sg:postcode":"2209",
    "sg:province":"NSW",
    "sg:tags":[
        "earth",
        "excavating",
        "moving",
        "equipment"
    ],
    "wof:name":"Austramac Australia Pty Ltd",
    "wof:placetype":"venue"
},
  "geometry": {"coordinates":[151.08073400000001,-33.949657],"type":"Point"}
}