{
  "type": "Feature",
  "properties": {
    "iso:country":"AU",
    "sg:address":"895 Canterbury Rd",
    "sg:city":"Box Hill",
    "sg:classifiers":[
        {
            "category":"Building & Trades",
            "subcategory":"Construction",
            "type":"Services"
        }
    ],
    "sg:phone":"+61 3 9898 7422",
    "sg:postcode":"3128",
    "sg:province":"VIC",
    "sg:tags":[
        "brick",
        "paving"
    ],
    "wof:name":"Phil's Paving & Landscaping",
    "wof:placetype":"venue"
},
  "geometry": {"coordinates":[145.12289428700001,-37.8286819458],"type":"Point"}
}