{
  "type": "Feature",
  "properties": {
    "addr:full":"Worthing Rd Devon Meadows VIC 3977",
    "addr:postcode":"3977",
    "addr:street":"Worthing Rd",
    "iso:country":"AU",
    "sg:address":"Worthing Rd",
    "sg:city":"Devon Meadows",
    "sg:classifiers":[
        {
            "category":"Education",
            "subcategory":"School",
            "type":"Public Place"
        }
    ],
    "sg:phone":"+61 3 5998 2304",
    "sg:postcode":"3977",
    "sg:province":"VIC",
    "sg:tags":[
        "state",
        "except",
        "nsw"
    ],
    "wof:name":"Devon Meadows Primary School",
    "wof:placetype":"venue"
},
  "geometry": {"coordinates":[145.310089111,-38.1626243591],"type":"Point"}
}