{
  "type": "Feature",
  "properties": {
    "addr:full":"Level 5, Manningham Medical Centre, 200 High St Doncaster VIC 3108",
    "addr:housenumber":"200",
    "addr:postcode":"3108",
    "addr:street":"High St",
    "iso:country":"AU",
    "sg:address":"Level 5, Manningham Medical Centre, 200 High St",
    "sg:city":"Doncaster",
    "sg:classifiers":[
        {
            "category":"Health Services",
            "subcategory":"Doctor",
            "type":"Services"
        }
    ],
    "sg:phone":"+61 3 9852 1199",
    "sg:postcode":"3108",
    "sg:province":"VIC",
    "sg:tags":[
        "medical",
        "practitioner"
    ],
    "wof:name":"Qureshi Salmaan Dr",
    "wof:placetype":"venue"
},
  "geometry": {"coordinates":[145.12306213400001,-37.7792663574],"type":"Point"}
}