{
  "type": "Feature",
  "properties": {
    "addr:full":"11 Regency Crt Benalla VIC 3672",
    "addr:housenumber":"11",
    "addr:postcode":"3672",
    "addr:street":"Regency Crt",
    "iso:country":"AU",
    "sg:address":"11 Regency Crt",
    "sg:city":"Benalla",
    "sg:classifiers":[
        {
            "category":"Home & Garden",
            "subcategory":"Household Appliances",
            "type":"Retail Goods"
        }
    ],
    "sg:phone":"+61 3 5762 5195",
    "sg:postcode":"3672",
    "sg:province":"VIC",
    "sg:tags":[
        "equipment",
        "gas"
    ],
    "wof:name":"Staffords Rose City Gas Services",
    "wof:placetype":"venue"
},
  "geometry": {"coordinates":[145.96253999999999,-36.561817],"type":"Point"}
}