{
  "type": "Feature",
  "properties": {
    "addr:full":"Olm St Caloundra QLD 4551",
    "addr:postcode":"4551",
    "addr:street":"Olm St",
    "iso:country":"AU",
    "sg:address":"Olm St",
    "sg:city":"Caloundra",
    "sg:classifiers":[
        {
            "category":"Organizations",
            "subcategory":"Community Association",
            "type":"Services"
        }
    ],
    "sg:phone":"+61 7 5491 6466",
    "sg:postcode":"4551",
    "sg:province":"QLD",
    "sg:tags":[
        "organisation",
        "family",
        "welfare"
    ],
    "wof:name":"Meals On Wheels",
    "wof:placetype":"venue"
},
  "geometry": {"coordinates":[153.12481689399999,-26.7998371124],"type":"Point"}
}