{
  "type": "Feature",
  "properties": {
    "addr:full":"Suite 3 4 Langrigg Ave Mt Martha VIC 3934",
    "addr:housenumber":"4",
    "addr:postcode":"3934",
    "addr:street":"Langrigg Ave Mt Martha",
    "iso:country":"AU",
    "sg:address":"Suite 3 4 Langrigg Ave",
    "sg:city":"Mt Martha",
    "sg:classifiers":[
        {
            "category":"Health Services",
            "subcategory":"Dentist",
            "type":"Services"
        }
    ],
    "sg:phone":"+61 3 5974 3699",
    "sg:postcode":"3934",
    "sg:province":"VIC",
    "wof:name":"Farmer Cameron Dr",
    "wof:placetype":"venue"
},
  "geometry": {"coordinates":[145.01448059099999,-38.2676429749],"type":"Point"}
}