{
  "type": "Feature",
  "properties": {
    "iso:country":"AU",
    "sg:address":"8 Sundowner Ave",
    "sg:city":"Berrara",
    "sg:classifiers":[
        {
            "category":"Building & Trades",
            "subcategory":"Construction",
            "type":"Services"
        }
    ],
    "sg:phone":"+61 2 4441 1477",
    "sg:postcode":"2540",
    "sg:province":"NSW",
    "sg:tags":[
        "concrete",
        "paving"
    ],
    "wof:name":"Berrara Beach Concreting",
    "wof:placetype":"venue"
},
  "geometry": {"coordinates":[150.548065186,-35.2032394409],"type":"Point"}
}