{
  "type": "Feature",
  "properties": {
    "addr:full":"22 709 Barkly St West Footscray VIC 3012",
    "addr:housenumber":"709",
    "addr:postcode":"3012",
    "addr:street":"22;Barkly St",
    "iso:country":"AU",
    "sg:address":"22 709 Barkly St",
    "sg:city":"West Footscray",
    "sg:classifiers":[
        {
            "category":"Professional",
            "subcategory":"Engineering",
            "type":"Services"
        }
    ],
    "sg:phone":"+61 417 386 603",
    "sg:postcode":"3012",
    "sg:province":"VIC",
    "sg:tags":[
        "engineer",
        "structural"
    ],
    "wof:name":"DSZ Partners",
    "wof:placetype":"venue"
},
  "geometry": {"coordinates":[144.86671447800001,-37.7962799072],"type":"Point"}
}