{
  "type": "Feature",
  "properties": {
    "addr:full":"10 Cygnet Pl Illawong NSW 2234",
    "addr:housenumber":"10",
    "addr:postcode":"2234",
    "addr:street":"Cygnet Pl",
    "iso:country":"AU",
    "sg:address":"10 Cygnet Pl",
    "sg:city":"Illawong",
    "sg:classifiers":[
        {
            "category":"Health Services",
            "subcategory":"Health Practitioner",
            "type":"Services"
        }
    ],
    "sg:phone":"+61 2 9541 1066",
    "sg:postcode":"2234",
    "sg:province":"NSW",
    "sg:tags":[
        "alternative"
    ],
    "wof:name":"Aura-Soma Australia Pty Ltd",
    "wof:placetype":"venue"
},
  "geometry": {"coordinates":[151.025466919,-33.9998168945],"type":"Point"}
}