{
  "type": "Feature",
  "properties": {
    "addr:full":"353a Flinders La Melbourne VIC 3000",
    "addr:housenumber":"353a",
    "addr:postcode":"3000",
    "addr:street":"Flinders La",
    "iso:country":"AU",
    "sg:address":"353a Flinders La",
    "sg:city":"Melbourne",
    "sg:classifiers":[
        {
            "category":"Cafe",
            "type":"Food & Drink"
        }
    ],
    "sg:phone":"+61 3 9629 2859",
    "sg:postcode":"3000",
    "sg:province":"VIC",
    "wof:name":"Cafe Millennium",
    "wof:placetype":"venue"
},
  "geometry": {"coordinates":[144.962768555,-37.8178329468],"type":"Point"}
}