{
  "type": "Feature",
  "properties": {
    "addr:full":"63 Nish St Echuca VIC 3564",
    "addr:housenumber":"63",
    "addr:postcode":"3564",
    "addr:street":"Nish St",
    "iso:country":"AU",
    "sg:address":"63 Nish St",
    "sg:city":"Echuca",
    "sg:classifiers":[
        {
            "category":"Health Services",
            "subcategory":"Health Practitioner",
            "type":"Services"
        }
    ],
    "sg:phone":"+61 3 5480 6719",
    "sg:postcode":"3564",
    "sg:province":"VIC",
    "sg:tags":[
        "psychologist"
    ],
    "wof:name":"Guy Robbins Psychologist",
    "wof:placetype":"venue"
},
  "geometry": {"coordinates":[144.750564575,-36.1278877258],"type":"Point"}
}