{
  "type": "Feature",
  "properties": {
    "iso:country":"AU",
    "sg:address":"229 Hume Hwy",
    "sg:city":"Lansvale",
    "sg:classifiers":[
        {
            "category":"Autos & Motor Vehicles",
            "subcategory":"Automobile Sales",
            "type":"Retail Goods"
        }
    ],
    "sg:phone":"+61 2 9794 2500",
    "sg:postcode":"2166",
    "sg:province":"NSW",
    "sg:tags":[
        "car",
        "used"
    ],
    "wof:name":"Australian Fleet Sales",
    "wof:placetype":"venue"
},
  "geometry": {"coordinates":[150.95350647000001,-33.8966712952],"type":"Point"}
}