{
  "type": "Feature",
  "properties": {
    "iso:country":"AU",
    "sg:address":"Bay Rd",
    "sg:city":"Waverton",
    "sg:classifiers":[
        {
            "category":"Education",
            "subcategory":"School",
            "type":"Public Place"
        }
    ],
    "sg:phone":"+61 2 9955 2822",
    "sg:postcode":"2060",
    "sg:province":"NSW",
    "sg:tags":[
        "state",
        "-",
        "nsw"
    ],
    "wof:name":"North Sydney Demonstration School",
    "wof:placetype":"venue"
},
  "geometry": {"coordinates":[151.19682312,-33.8376655579],"type":"Point"}
}