{
  "type": "Feature",
  "properties": {
    "addr:full":"286 Brunswick St North Fitzroy VIC 3065",
    "addr:housenumber":"286",
    "addr:postcode":"3065",
    "addr:street":"Brunswick St",
    "iso:country":"AU",
    "sg:address":"286 Brunswick St North",
    "sg:city":"Fitzroy",
    "sg:classifiers":[
        {
            "category":"Shopping",
            "subcategory":"Shoes",
            "type":"Retail Goods"
        }
    ],
    "sg:phone":"+61 3 9416 1271",
    "sg:postcode":"3065",
    "sg:province":"VIC",
    "sg:tags":[
        "footwear"
    ],
    "wof:name":"I Shoes",
    "wof:placetype":"venue"
},
  "geometry": {"coordinates":[144.97854614299999,-37.7987327576],"type":"Point"}
}