{
  "type": "Feature",
  "properties": {
    "addr:full":"5/ 60 Glenwood Park Drv Glenwood NSW 2768",
    "addr:housenumber":"/ 60",
    "addr:postcode":"2768",
    "addr:street":"Glenwood Park Drv",
    "iso:country":"AU",
    "sg:address":"5/ 60 Glenwood Park Drv",
    "sg:city":"Glenwood",
    "sg:classifiers":[
        {
            "category":"Health Services",
            "subcategory":"Doctor",
            "type":"Services"
        }
    ],
    "sg:phone":"+61 2 9629 7222",
    "sg:postcode":"2768",
    "sg:province":"NSW",
    "sg:tags":[
        "medical",
        "practitioner"
    ],
    "wof:name":"Kheray Jasvinder Dr",
    "wof:placetype":"venue"
},
  "geometry": {"coordinates":[150.927795,-33.734093],"type":"Point"}
}