{
  "type": "Feature",
  "properties": {
    "iso:country":"AU",
    "sg:address":"44a Wilmot St",
    "sg:city":"Burnie",
    "sg:classifiers":[
        {
            "category":"Health Services",
            "subcategory":"Dentist",
            "type":"Services"
        }
    ],
    "sg:phone":"+61 3 6432 1188",
    "sg:postcode":"7320",
    "sg:province":"TAS",
    "wof:name":"Burnie Smile Care",
    "wof:placetype":"venue"
},
  "geometry": {"coordinates":[145.905197,-41.050674],"type":"Point"}
}