{
  "type": "Feature",
  "properties": {
    "addr:full":"PO Box 3520 North Mackay QLD 4740",
    "addr:postcode":"4740",
    "iso:country":"AU",
    "sg:address":"PO Box 3520",
    "sg:city":"North Mackay",
    "sg:classifiers":[
        {
            "category":"Industrial Area",
            "type":"Public Place"
        }
    ],
    "sg:phone":"+61 7 4951 1295",
    "sg:postcode":"4740",
    "sg:province":"QLD",
    "sg:tags":[
        "rural",
        "shed"
    ],
    "wof:name":"Tropical Scapes & Garden Sheds",
    "wof:placetype":"venue"
},
  "geometry": {"coordinates":[149.18261699999999,-21.123739],"type":"Point"}
}