{
  "type": "Feature",
  "properties": {
    "iso:country":"AU",
    "sg:address":"275 Canterbury Rd",
    "sg:city":"Forest Hill",
    "sg:classifiers":[
        {
            "category":"Professional",
            "subcategory":"Business Services",
            "type":"Services"
        }
    ],
    "sg:phone":"+61 3 9878 3009",
    "sg:postcode":"3131",
    "sg:province":"VIC",
    "sg:tags":[
        "processing",
        "word"
    ],
    "wof:name":"Forest Hill Typing & Duplicating Service",
    "wof:placetype":"venue"
},
  "geometry": {"coordinates":[145.16920471200001,-37.834236145],"type":"Point"}
}