{
  "type": "Feature",
  "properties": {
    "addr:full":"PO Box 302 Yarraville VIC 3013",
    "addr:postcode":"3013",
    "iso:country":"AU",
    "sg:address":"PO Box 302",
    "sg:city":"Yarraville",
    "sg:classifiers":[
        {
            "category":"Professional",
            "subcategory":"Detective & Security Services",
            "type":"Services"
        }
    ],
    "sg:phone":"+61 3 9689 0033",
    "sg:postcode":"3013",
    "sg:province":"VIC",
    "sg:tags":[
        "investigator"
    ],
    "wof:name":"Western Suburbs Detective Services",
    "wof:placetype":"venue"
},
  "geometry": {"coordinates":[144.882202148,-37.8180885315],"type":"Point"}
}