{
  "type": "Feature",
  "properties": {
    "iso:country":"AU",
    "sg:address":"81 Way St",
    "sg:city":"Kilburn",
    "sg:classifiers":[
        {
            "category":"Manufacturing",
            "subcategory":"Metals",
            "type":"Manufacturing & Wholesale Goods"
        }
    ],
    "sg:phone":"+61 407 394 268",
    "sg:postcode":"5084",
    "sg:province":"SA",
    "sg:tags":[
        "sheet",
        "worker"
    ],
    "wof:name":"Malmo Sheet Metal Works",
    "wof:placetype":"venue"
},
  "geometry": {"coordinates":[138.58732605,-34.8609962463],"type":"Point"}
}