{
  "type": "Feature",
  "properties": {
    "addr:full":"98 Wilsons Rd Mornington VIC 3931",
    "addr:housenumber":"98",
    "addr:postcode":"3931",
    "addr:street":"Wilsons Rd",
    "iso:country":"AU",
    "sg:address":"98 Wilsons Rd",
    "sg:city":"Mornington",
    "sg:classifiers":[
        {
            "category":"Personal",
            "subcategory":"Beauty Salon",
            "type":"Services"
        }
    ],
    "sg:phone":"+61 3 5975 8011",
    "sg:postcode":"3931",
    "sg:province":"VIC",
    "sg:tags":[
        "hairdresser"
    ],
    "wof:name":"Designs One Of Mornington",
    "wof:placetype":"venue"
},
  "geometry": {"coordinates":[145.03802490199999,-38.2304649353],"type":"Point"}
}