{
  "type": "Feature",
  "properties": {
    "iso:country":"AU",
    "sg:address":"Hume Hwy",
    "sg:city":"Liverpool",
    "sg:classifiers":[
        {
            "category":"Retail",
            "subcategory":"Event Space",
            "type":"Services"
        }
    ],
    "sg:phone":"+61 2 9601 5088",
    "sg:postcode":"2170",
    "sg:province":"NSW",
    "sg:tags":[
        "venue",
        "reception",
        "wedding"
    ],
    "sg:website":"http://www.hunts.com.au",
    "wof:name":"Comfort Inn Hunts Motel",
    "wof:placetype":"venue"
},
  "geometry": {"coordinates":[150.91700744600001,-33.9320106506],"type":"Point"}
}