{
  "type": "Feature",
  "properties": {
    "addr:full":"11 Viewtech Pl Rowville VIC 3178",
    "addr:housenumber":"11",
    "addr:postcode":"3178",
    "addr:street":"Viewtech Pl",
    "iso:country":"AU",
    "sg:address":"11 Viewtech Pl",
    "sg:city":"Rowville",
    "sg:classifiers":[
        {
            "category":"Farming",
            "subcategory":"Farm & Veterinary Services",
            "type":"Manufacturing & Wholesale Goods"
        }
    ],
    "sg:phone":"+61 3 9755 8699",
    "sg:postcode":"3178",
    "sg:province":"VIC",
    "sg:tags":[
        "poultry",
        "processing",
        "supply"
    ],
    "wof:name":"Universal Poultry Products",
    "wof:placetype":"venue"
},
  "geometry": {"coordinates":[145.22210693400001,-37.9286003113],"type":"Point"}
}