{
  "type": "Feature",
  "properties": {
    "iso:country":"AU",
    "sg:address":"New England Hwy Cnr Mt Marshall Rd",
    "sg:city":"Warwick",
    "sg:classifiers":[
        {
            "category":"Landmark",
            "subcategory":"Square",
            "type":"Public Place"
        }
    ],
    "sg:phone":"+61 7 4666 3111",
    "sg:postcode":"4370",
    "sg:province":"QLD",
    "sg:tags":[
        "product",
        "ostrich",
        "farmer"
    ],
    "wof:name":"Ostrich Incubation Centre",
    "wof:placetype":"venue"
},
  "geometry": {"coordinates":[152.020019531,-28.2196712494],"type":"Point"}
}