{
  "type": "Feature",
  "properties": {
    "iso:country":"AU",
    "sg:address":"47 Walkers Rd",
    "sg:city":"Mt Eliza",
    "sg:classifiers":[
        {
            "category":"Education",
            "subcategory":"Kindergarten",
            "type":"Public Place"
        }
    ],
    "sg:phone":"+61 3 9787 6746",
    "sg:postcode":"3930",
    "sg:province":"VIC",
    "sg:tags":[
        "pre-schools"
    ],
    "wof:name":"Walkers Rd Pre School",
    "wof:placetype":"venue"
},
  "geometry": {"coordinates":[145.10406494099999,-38.1890525818],"type":"Point"}
}