{
  "type": "Feature",
  "properties": {
    "iso:country":"AU",
    "sg:address":"1st Floor 33 Macquarie St",
    "sg:city":"Dubbo",
    "sg:classifiers":[
        {
            "category":"Arena",
            "subcategory":"Sports Club",
            "type":"Entertainment"
        }
    ],
    "sg:phone":"+61 2 6881 6404",
    "sg:postcode":"2830",
    "sg:province":"NSW",
    "sg:tags":[
        "defence",
        "supply",
        "self",
        "instruction",
        "martial art"
    ],
    "wof:name":"Chizen Taekwondo !Ki Tai Chi & Body Combat",
    "wof:placetype":"venue"
},
  "geometry": {"coordinates":[148.6015625,-32.2450904846],"type":"Point"}
}