{
  "type": "Feature",
  "properties": {
    "iso:country":"AU",
    "sg:address":"160 Argyle St",
    "sg:city":"Hobart",
    "sg:classifiers":[
        {
            "category":"Government",
            "subcategory":"Post Office",
            "type":"Public Place"
        }
    ],
    "sg:phone":"+61 13 11 18",
    "sg:postcode":"7000",
    "sg:province":"TAS",
    "sg:tags":[
        "postal"
    ],
    "wof:name":"Australia Post Offices",
    "wof:placetype":"venue"
},
  "geometry": {"coordinates":[147.32324218799999,-42.8762435913],"type":"Point"}
}