{
  "type": "Feature",
  "properties": {
    "addr:full":"98 Rodger St Chinchilla QLD 4413",
    "addr:housenumber":"98",
    "addr:postcode":"4413",
    "addr:street":"Rodger St",
    "iso:country":"AU",
    "sg:address":"98 Rodger St",
    "sg:city":"Chinchilla",
    "sg:classifiers":[
        {
            "category":"Building & Trades",
            "subcategory":"Construction",
            "type":"Services"
        }
    ],
    "sg:phone":"+61 7 4662 8162",
    "sg:postcode":"4413",
    "sg:province":"QLD",
    "sg:tags":[
        "contractor"
    ],
    "wof:name":"Roy Woods Builder",
    "wof:placetype":"venue"
},
  "geometry": {"coordinates":[150.64236450199999,-26.7353153229],"type":"Point"}
}