{
  "type": "Feature",
  "properties": {
    "iso:country":"AU",
    "sg:address":"32a King Albert Rd",
    "sg:city":"Trigg",
    "sg:classifiers":[
        {
            "category":"Real Estate",
            "subcategory":"Real Estate Agent",
            "type":"Services"
        }
    ],
    "sg:phone":"+61 411 729 529",
    "sg:postcode":"6029",
    "sg:province":"WA",
    "wof:name":"Peter Farris Real Estate Agent",
    "wof:placetype":"venue"
},
  "geometry": {"coordinates":[115.755599976,-31.8761997223],"type":"Point"}
}