{
  "type": "Feature",
  "properties": {
    "addr:full":"385 St Pauls Tce Fortitude Valley QLD 4006",
    "addr:housenumber":"385",
    "addr:postcode":"4006",
    "addr:street":"St Pauls Tce",
    "iso:country":"AU",
    "sg:address":"385 St",
    "sg:city":"Pauls Tce Fortitude Valley",
    "sg:classifiers":[
        {
            "category":"Insurance",
            "subcategory":"Hazard Insurance",
            "type":"Services"
        }
    ],
    "sg:phone":"+61 7 3246 1125",
    "sg:postcode":"4006",
    "sg:province":"QLD",
    "sg:tags":[
        "loss",
        "adjuster",
        "assessor"
    ],
    "wof:name":"Action Assessing (Aust)",
    "wof:placetype":"venue"
},
  "geometry": {"coordinates":[153.032546997,-27.455242157],"type":"Point"}
}