{
  "type": "Feature",
  "properties": {
    "addr:full":"36 Tuffy Ave Sans Souci NSW 2219",
    "addr:housenumber":"36",
    "addr:postcode":"2219",
    "addr:street":"Tuffy Ave",
    "iso:country":"AU",
    "sg:address":"36 Tuffy Ave",
    "sg:city":"Sans Souci",
    "sg:classifiers":[
        {
            "category":"Personal",
            "subcategory":"Beauty Salon",
            "type":"Services"
        }
    ],
    "sg:phone":"+61 2 9593 4777",
    "sg:postcode":"2219",
    "sg:province":"NSW",
    "sg:tags":[
        "hairdresser"
    ],
    "wof:name":"Wedlocs Hair & Beauty",
    "wof:placetype":"venue"
},
  "geometry": {"coordinates":[151.133545,-34.002052],"type":"Point"}
}