{
  "type": "Feature",
  "properties": {
    "addr:full":"26 Allied Drv Tullamarine VIC 3043",
    "addr:housenumber":"26",
    "addr:postcode":"3043",
    "addr:street":"Allied Drv",
    "iso:country":"AU",
    "sg:address":"26 Allied Drv",
    "sg:city":"Tullamarine",
    "sg:classifiers":[
        {
            "category":"Wholesale",
            "subcategory":"Construction Materials",
            "type":"Manufacturing & Wholesale Goods"
        }
    ],
    "sg:phone":"+61 3 9330 2830",
    "sg:postcode":"3043",
    "sg:province":"VIC",
    "sg:tags":[
        "lift"
    ],
    "wof:name":"Elevator Design Solutions",
    "wof:placetype":"venue"
},
  "geometry": {"coordinates":[144.87327575699999,-37.7099113464],"type":"Point"}
}