{
  "type": "Feature",
  "properties": {
    "iso:country":"AU",
    "sg:address":"9 Barrsmith St",
    "sg:city":"Tusmore",
    "sg:classifiers":[
        {
            "category":"Education",
            "subcategory":"Music School",
            "type":"Public Place"
        }
    ],
    "sg:phone":"+61 8 8431 8468",
    "sg:postcode":"5065",
    "sg:province":"SA",
    "sg:tags":[
        "teacher"
    ],
    "wof:name":"Reynolds Lyn",
    "wof:placetype":"venue"
},
  "geometry": {"coordinates":[138.64341735799999,-34.933506012],"type":"Point"}
}