{
  "type": "Feature",
  "properties": {
    "addr:full":"59A Roseberry Ave Preston VIC 3072",
    "addr:housenumber":"59a",
    "addr:postcode":"3072",
    "addr:street":"Roseberry Ave",
    "iso:country":"AU",
    "sg:address":"59A Roseberry Ave",
    "sg:city":"Preston",
    "sg:classifiers":[
        {
            "category":"Social Services",
            "subcategory":"Retirement Home",
            "type":"Services"
        }
    ],
    "sg:phone":"+61 3 9470 2311",
    "sg:postcode":"3072",
    "sg:province":"VIC",
    "sg:tags":[
        "visa"
    ],
    "wof:name":"Spectrum Immigration Services",
    "wof:placetype":"venue"
},
  "geometry": {"coordinates":[145.00575256400001,-37.7390975952],"type":"Point"}
}