{
  "type": "Feature",
  "properties": {
    "iso:country":"AU",
    "sg:address":"Waugoola Rd",
    "sg:city":"Wyangala Dam",
    "sg:classifiers":[
        {
            "category":"Education",
            "subcategory":"School",
            "type":"Public Place"
        }
    ],
    "sg:phone":"+61 2 6345 0804",
    "sg:postcode":"2808",
    "sg:province":"NSW",
    "sg:tags":[
        "state",
        "-",
        "nsw"
    ],
    "wof:name":"Wyangala Dam Public School",
    "wof:placetype":"venue"
},
  "geometry": {"coordinates":[148.94935599999999,-33.968109],"type":"Point"}
}