{
  "type": "Feature",
  "properties": {
    "addr:full":"Unit 5/ 33 Buckingham Drv Wangara WA 6065",
    "addr:housenumber":"33",
    "addr:postcode":"6065",
    "addr:street":"Buckingham Drv",
    "iso:country":"AU",
    "sg:address":"Unit 5/ 33 Buckingham Drv",
    "sg:city":"Wangara",
    "sg:classifiers":[
        {
            "category":"Retail",
            "subcategory":"Auto Repair",
            "type":"Services"
        }
    ],
    "sg:phone":"+61 8 9409 8503",
    "sg:postcode":"6065",
    "sg:province":"WA",
    "sg:tags":[
        "electrical"
    ],
    "wof:name":"Al's Mobile Auto Electronics",
    "wof:placetype":"venue"
},
  "geometry": {"coordinates":[115.818321228,-31.7869186401],"type":"Point"}
}