{
  "type": "Feature",
  "properties": {
    "addr:full":"Unit 11, 10 Dooley St North Rockhampton QLD 4701",
    "addr:housenumber":"10",
    "addr:postcode":"4701",
    "addr:street":"Dooley St North",
    "iso:country":"AU",
    "sg:address":"Unit 11, 10 Dooley St",
    "sg:city":"North Rockhampton",
    "sg:classifiers":[
        {
            "category":"Transit Center",
            "subcategory":"Freight",
            "type":"Transportation"
        }
    ],
    "sg:phone":"+61 7 3457 4500",
    "sg:postcode":"4701",
    "sg:province":"QLD",
    "sg:tags":[
        "forklift",
        "truck"
    ],
    "wof:name":"Crown Equipment",
    "wof:placetype":"venue"
},
  "geometry": {"coordinates":[150.51097106899999,-23.3618278503],"type":"Point"}
}