{
  "type": "Feature",
  "properties": {
    "iso:country":"AU",
    "sg:address":"23 Gisborne Village, Brantome St",
    "sg:city":"Gisborne",
    "sg:classifiers":[
        {
            "category":"Health Services",
            "subcategory":"Doctor",
            "type":"Services"
        }
    ],
    "sg:phone":"+61 3 5428 3355",
    "sg:postcode":"3437",
    "sg:province":"VIC",
    "sg:tags":[
        "medical",
        "practitioner"
    ],
    "wof:name":"Guy Rodney",
    "wof:placetype":"venue"
},
  "geometry": {"coordinates":[144.589767456,-37.4867095947],"type":"Point"}
}