{
  "type": "Feature",
  "properties": {
    "addr:full":"10 a Helm St Mt Pleasant WA 6153",
    "addr:housenumber":"10 a",
    "addr:postcode":"6153",
    "addr:street":"Helm St",
    "iso:country":"AU",
    "sg:address":"10 a Helm St",
    "sg:city":"Mt Pleasant",
    "sg:classifiers":[
        {
            "category":"Personal",
            "subcategory":"Massage",
            "type":"Services"
        }
    ],
    "sg:phone":"+61 8 9316 1021",
    "sg:postcode":"6153",
    "sg:province":"WA",
    "sg:tags":[
        "therapy"
    ],
    "wof:name":"Nimala Gable",
    "wof:placetype":"venue"
},
  "geometry": {"coordinates":[115.85038,-32.01516],"type":"Point"}
}