{
  "type": "Feature",
  "properties": {
    "addr:full":"35 Douglas Mawson Rd Dubbo NSW 2830",
    "addr:housenumber":"35",
    "addr:postcode":"2830",
    "addr:street":"Douglas Mawson Rd",
    "iso:country":"AU",
    "sg:address":"35 Douglas Mawson Rd",
    "sg:city":"Dubbo",
    "sg:classifiers":[
        {
            "category":"Building & Trades",
            "subcategory":"Construction",
            "type":"Services"
        }
    ],
    "sg:phone":"+61 2 6882 0620",
    "sg:postcode":"2830",
    "sg:province":"NSW",
    "sg:tags":[
        "joinery"
    ],
    "wof:name":"L.A. Wardrobes",
    "wof:placetype":"venue"
},
  "geometry": {"coordinates":[148.633544922,-32.2473526001],"type":"Point"}
}