{
  "type": "Feature",
  "properties": {
    "iso:country":"AU",
    "sg:address":"177- 179 Gympie Rd",
    "sg:city":"Kedron",
    "sg:classifiers":[
        {
            "category":"Structure",
            "subcategory":"Bridge",
            "type":"Public Place"
        }
    ],
    "sg:phone":"+61 7 3357 6996",
    "sg:postcode":"4031",
    "sg:province":"QLD",
    "sg:tags":[
        "chainsaw",
        "brushcutters"
    ],
    "wof:name":"Kedron Mower Centre",
    "wof:placetype":"venue"
},
  "geometry": {"coordinates":[153.033005,-27.410004],"type":"Point"}
}