{
  "type": "Feature",
  "properties": {
    "addr:full":"PO Box 1024 Tewantin QLD 4565",
    "addr:postcode":"4565",
    "iso:country":"AU",
    "sg:address":"PO Box 1024",
    "sg:city":"Tewantin",
    "sg:classifiers":[
        {
            "category":"Real Estate",
            "subcategory":"Surveying",
            "type":"Services"
        }
    ],
    "sg:phone":"+61 412 603 286",
    "sg:postcode":"4565",
    "sg:province":"QLD",
    "sg:tags":[
        "surveyor",
        "land"
    ],
    "wof:name":"Sight Surveys",
    "wof:placetype":"venue"
},
  "geometry": {"coordinates":[153.02789306599999,-26.3908996582],"type":"Point"}
}