{
  "type": "Feature",
  "properties": {
    "addr:full":"3a Spit Rd Mosman NSW 2088",
    "addr:housenumber":"3a",
    "addr:postcode":"2088",
    "addr:street":"Spit Rd",
    "iso:country":"AU",
    "sg:address":"3a Spit Rd",
    "sg:city":"Mosman",
    "sg:classifiers":[
        {
            "category":"Personal",
            "subcategory":"Skin Care",
            "type":"Services"
        }
    ],
    "sg:phone":"+61 2 9588 9888",
    "sg:postcode":"2088",
    "sg:province":"NSW",
    "sg:tags":[
        "treatment"
    ],
    "wof:name":"Skin Disorder Clinic Herbal Solutions",
    "wof:placetype":"venue"
},
  "geometry": {"coordinates":[151.24124145499999,-33.8244361877],"type":"Point"}
}