{
  "type": "Feature",
  "properties": {
    "iso:country":"AU",
    "sg:address":"155 Clarence Rd",
    "sg:city":"Indooroopilly",
    "sg:classifiers":[
        {
            "category":"Health Services",
            "subcategory":"Dentist",
            "type":"Services"
        }
    ],
    "sg:phone":"+61 7 3371 2233",
    "sg:postcode":"4068",
    "sg:province":"QLD",
    "wof:name":"McNee Mervyn D",
    "wof:placetype":"venue"
},
  "geometry": {"coordinates":[152.97697448700001,-27.5026092529],"type":"Point"}
}