{
  "type": "Feature",
  "properties": {
    "addr:full":"14 Dale Drv Midland WA 6056",
    "addr:housenumber":"14",
    "addr:postcode":"6056",
    "addr:street":"Dale Drv",
    "iso:country":"AU",
    "sg:address":"14 Dale Drv",
    "sg:city":"Midland",
    "sg:classifiers":[
        {
            "category":"Retail",
            "subcategory":"Driving School",
            "type":"Services"
        }
    ],
    "sg:phone":"+61 8 9274 3858",
    "sg:postcode":"6056",
    "sg:province":"WA",
    "wof:name":"Combined Driving Schools",
    "wof:placetype":"venue"
},
  "geometry": {"coordinates":[116.000587463,-31.8527393341],"type":"Point"}
}