{
  "type": "Feature",
  "properties": {
    "addr:full":"101 Murilla St Miles QLD 4415",
    "addr:housenumber":"101",
    "addr:postcode":"4415",
    "addr:street":"Murilla St",
    "iso:country":"AU",
    "sg:address":"101 Murilla St",
    "sg:city":"Miles",
    "sg:classifiers":[
        {
            "category":"Autos & Motor Vehicles",
            "subcategory":"Fuel & Gas Station",
            "type":"Retail Goods"
        }
    ],
    "sg:phone":"+61 7 4627 1401",
    "sg:postcode":"4415",
    "sg:province":"QLD",
    "wof:name":"Shell Miles Roadhouse",
    "wof:placetype":"venue"
},
  "geometry": {"coordinates":[150.18960571299999,-26.6599121094],"type":"Point"}
}