{
  "type": "Feature",
  "properties": {
    "addr:full":"Unit 3/ 35 Gillam Drv Kelmscott WA 6111",
    "addr:housenumber":"35",
    "addr:postcode":"6111",
    "addr:street":"Gillam Drv",
    "iso:country":"AU",
    "sg:address":"Unit 3/ 35 Gillam Drv",
    "sg:city":"Kelmscott",
    "sg:classifiers":[
        {
            "category":"Autos & Motor Vehicles",
            "subcategory":"Automobile Sales",
            "type":"Retail Goods"
        }
    ],
    "sg:phone":"+61 8 9390 0945",
    "sg:postcode":"6111",
    "sg:province":"WA",
    "sg:tags":[
        "equipment",
        "trailer"
    ],
    "wof:name":"Stagg Boats",
    "wof:placetype":"venue"
},
  "geometry": {"coordinates":[116.00592804,-32.1273765564],"type":"Point"}
}