{
  "type": "Feature",
  "properties": {
    "iso:country":"AU",
    "sg:address":"Unit 2 10 Wittenberg Drv",
    "sg:city":"Canning Vale",
    "sg:classifiers":[
        {
            "category":"Building & Trades",
            "subcategory":"Construction",
            "type":"Services"
        }
    ],
    "sg:phone":"+61 8 9455 5711",
    "sg:postcode":"6155",
    "sg:province":"WA",
    "sg:tags":[
        "contractor"
    ],
    "wof:name":"Laneway Construction",
    "wof:placetype":"venue"
},
  "geometry": {"coordinates":[115.927048,-32.064831],"type":"Point"}
}