{
  "type": "Feature",
  "properties": {
    "addr:full":"20 Findon Rd Epping VIC 3076",
    "addr:housenumber":"20",
    "addr:postcode":"3076",
    "addr:street":"Findon Rd",
    "iso:country":"AU",
    "sg:address":"20 Findon Rd",
    "sg:city":"Epping",
    "sg:classifiers":[
        {
            "category":"Food & Beverages",
            "subcategory":"Groceries & Convenience Stores",
            "type":"Retail Goods"
        }
    ],
    "sg:phone":"+61 3 9408 8008",
    "sg:postcode":"3076",
    "sg:province":"VIC",
    "wof:name":"Findon Convenience Store",
    "wof:placetype":"venue"
},
  "geometry": {"coordinates":[145.02967834500001,-37.637802124],"type":"Point"}
}