{
  "type": "Feature",
  "properties": {
    "iso:country":"AU",
    "sg:address":"PO Box 462",
    "sg:city":"Bega",
    "sg:classifiers":[
        {
            "category":"Utilities",
            "subcategory":"Water",
            "type":"Services"
        }
    ],
    "sg:phone":"+61 2 6492 3544",
    "sg:postcode":"2550",
    "sg:province":"NSW",
    "sg:tags":[
        "hot",
        "system"
    ],
    "wof:name":"David Scott Electrical",
    "wof:placetype":"venue"
},
  "geometry": {"coordinates":[149.84138488799999,-36.6739883423],"type":"Point"}
}