{
  "type": "Feature",
  "properties": {
    "addr:full":"6 Sheen Pl Bayswater WA 6053",
    "addr:housenumber":"6",
    "addr:postcode":"6053",
    "addr:street":"Sheen Pl",
    "iso:country":"AU",
    "sg:address":"6 Sheen Pl",
    "sg:city":"Bayswater",
    "sg:classifiers":[
        {
            "category":"Manufacturing",
            "subcategory":"Metals",
            "type":"Manufacturing & Wholesale Goods"
        }
    ],
    "sg:phone":"+61 8 9377 2887",
    "sg:postcode":"6053",
    "sg:province":"WA",
    "sg:tags":[
        "sheet",
        "worker"
    ],
    "wof:name":"Revell Engineering",
    "wof:placetype":"venue"
},
  "geometry": {"coordinates":[115.922431946,-31.8966464996],"type":"Point"}
}