{
  "type": "Feature",
  "properties": {
    "addr:full":"7 Lloyds Rd Bathurst NSW 2795",
    "addr:housenumber":"7",
    "addr:postcode":"2795",
    "addr:street":"Lloyds Rd",
    "iso:country":"AU",
    "sg:address":"7 Lloyds Rd",
    "sg:city":"Bathurst",
    "sg:classifiers":[
        {
            "category":"Professional",
            "type":"Services"
        }
    ],
    "sg:phone":"+61 2 6331 7800",
    "sg:postcode":"2795",
    "sg:province":"NSW",
    "sg:tags":[
        "buyer",
        "merchant",
        "wool"
    ],
    "wof:name":"R. & B. Smith (Aust.) Pty. Ltd.",
    "wof:placetype":"venue"
},
  "geometry": {"coordinates":[149.57635498100001,-33.4396362305],"type":"Point"}
}