{
  "type": "Feature",
  "properties": {
    "iso:country":"AU",
    "sg:address":"46 Pine Hill Drv",
    "sg:city":"Doncaster East",
    "sg:classifiers":[
        {
            "category":"Shopping",
            "subcategory":"Party Supplies",
            "type":"Retail Goods"
        }
    ],
    "sg:phone":"+61 3 9841 9032",
    "sg:postcode":"3109",
    "sg:province":"VIC",
    "sg:tags":[
        "children's"
    ],
    "wof:name":"Childrens Theme Parties",
    "wof:placetype":"venue"
},
  "geometry": {"coordinates":[145.176681519,-37.7709960938],"type":"Point"}
}