{
  "type": "Feature",
  "properties": {
    "addr:full":"175 Hotham St East Melbourne VIC 3002",
    "addr:housenumber":"175",
    "addr:postcode":"3002",
    "addr:street":"Hotham St",
    "iso:country":"AU",
    "sg:address":"175 Hotham St",
    "sg:city":"East Melbourne",
    "sg:classifiers":[
        {
            "category":"Professional",
            "subcategory":"Art Services",
            "type":"Services"
        }
    ],
    "sg:phone":"+61 3 9419 3726",
    "sg:postcode":"3002",
    "sg:province":"VIC",
    "sg:tags":[
        "artist"
    ],
    "wof:name":"Masters Diane",
    "wof:placetype":"venue"
},
  "geometry": {"coordinates":[144.98425293,-37.8140792847],"type":"Point"}
}