{
  "type": "Feature",
  "properties": {
    "addr:full":"137- 139 Graham St Wonthaggi VIC 3995",
    "addr:housenumber":"139",
    "addr:postcode":"3995",
    "addr:street":"Graham St",
    "iso:country":"AU",
    "sg:address":"137- 139 Graham St",
    "sg:city":"Wonthaggi",
    "sg:classifiers":[
        {
            "category":"Shopping",
            "subcategory":"Clothing, Apparel, & Fashions",
            "type":"Retail Goods"
        }
    ],
    "sg:phone":"+61 3 5672 1485",
    "sg:postcode":"3995",
    "sg:province":"VIC",
    "sg:tags":[
        "lingerie",
        "hosiery",
        "sleepwear"
    ],
    "wof:name":"Julie Wade",
    "wof:placetype":"venue"
},
  "geometry": {"coordinates":[145.58976699999999,-38.606319],"type":"Point"}
}