{
  "type": "Feature",
  "properties": {
    "addr:full":"Shop 3, Glenelg Ave Mermaid Beach QLD 4218",
    "addr:housenumber":"shop 3",
    "addr:postcode":"4218",
    "addr:street":"Glenelg Ave",
    "iso:country":"AU",
    "sg:address":"Shop 3, Glenelg Ave",
    "sg:city":"Mermaid Beach",
    "sg:classifiers":[
        {
            "category":"Arts & Performance",
            "subcategory":"Art Gallery",
            "type":"Entertainment"
        }
    ],
    "sg:phone":"+61 7 5572 4589",
    "sg:postcode":"4218",
    "sg:province":"QLD",
    "sg:tags":[
        "aboriginal",
        "craft"
    ],
    "wof:name":"Dhala Creations",
    "wof:placetype":"venue"
},
  "geometry": {"coordinates":[153.434692383,-28.0448684692],"type":"Point"}
}