{
  "type": "Feature",
  "properties": {
    "addr:full":"Lot 35 Amsterdam Cct Wyong NSW 2259",
    "addr:postcode":"2259",
    "iso:country":"AU",
    "sg:address":"Lot 35",
    "sg:city":"Amsterdam Cct Wyong",
    "sg:classifiers":[
        {
            "category":"Shopping",
            "subcategory":"Antiques",
            "type":"Retail Goods"
        }
    ],
    "sg:phone":"+61 409 985 569",
    "sg:postcode":"2259",
    "sg:province":"NSW",
    "wof:name":"Angels Antiques & Collectables",
    "wof:placetype":"venue"
},
  "geometry": {"coordinates":[151.45196533199999,-33.2639961243],"type":"Point"}
}