{
  "type": "Feature",
  "properties": {
    "addr:full":"271 North East Rd Hampstead Gardens SA 5086",
    "addr:housenumber":"271",
    "addr:postcode":"5086",
    "addr:street":"North East Rd",
    "iso:country":"AU",
    "sg:address":"271 North East Rd",
    "sg:city":"Hampstead Gardens",
    "sg:classifiers":[
        {
            "category":"Manufacturing",
            "subcategory":"Food",
            "type":"Manufacturing & Wholesale Goods"
        }
    ],
    "sg:phone":"+61 8 8266 0711",
    "sg:postcode":"5086",
    "sg:province":"SA",
    "sg:tags":[
        "function",
        "catering"
    ],
    "wof:name":"Adelaide Gourmet Platters & More",
    "wof:placetype":"venue"
},
  "geometry": {"coordinates":[138.632568359,-34.8744888306],"type":"Point"}
}