{
  "type": "Feature",
  "properties": {
    "addr:full":"300 Frenchville Rd North Rockhampton QLD 4701",
    "addr:housenumber":"300",
    "addr:postcode":"4701",
    "addr:street":"Frenchville Rd North",
    "iso:country":"AU",
    "sg:address":"300 Frenchville Rd",
    "sg:city":"North Rockhampton",
    "sg:classifiers":[
        {
            "category":"Building & Trades",
            "subcategory":"Construction",
            "type":"Services"
        }
    ],
    "sg:phone":"+61 7 4928 1049",
    "sg:postcode":"4701",
    "sg:province":"QLD",
    "sg:tags":[
        "contractor"
    ],
    "wof:name":"Handley N J & L J",
    "wof:placetype":"venue"
},
  "geometry": {"coordinates":[150.55148315400001,-23.3443202972],"type":"Point"}
}