{
  "type": "Feature",
  "properties": {
    "iso:country":"AU",
    "sg:address":"5 Patricia Crt",
    "sg:city":"Golden Square",
    "sg:classifiers":[
        {
            "category":"Professional",
            "subcategory":"Computer Services",
            "type":"Services"
        }
    ],
    "sg:phone":"+61 414 414 467",
    "sg:postcode":"3555",
    "sg:province":"VIC",
    "sg:tags":[
        "consultant",
        "system"
    ],
    "wof:name":"Vaughan Williams",
    "wof:placetype":"venue"
},
  "geometry": {"coordinates":[144.24803161599999,-36.7748031616],"type":"Point"}
}