{
  "type": "Feature",
  "properties": {
    "addr:full":"Suite 114 / 24 -32 Lexington Drv Bella Vista NSW 2153",
    "addr:housenumber":"/;-32",
    "addr:postcode":"2153",
    "addr:street":"24;Lexington Drv",
    "iso:country":"AU",
    "sg:address":"Suite 114 / 24 -32 Lexington Drv",
    "sg:city":"Bella Vista",
    "sg:classifiers":[
        {
            "category":"Health Services",
            "subcategory":"Doctor",
            "type":"Services"
        }
    ],
    "sg:phone":"+61 2 8824 4716",
    "sg:postcode":"2153",
    "sg:province":"NSW",
    "sg:tags":[
        "medical",
        "practitioner"
    ],
    "wof:name":"Tham Dr Jeremy",
    "wof:placetype":"venue"
},
  "geometry": {"coordinates":[150.94593810999999,-33.7338409424],"type":"Point"}
}