{
  "type": "Feature",
  "properties": {
    "addr:full":"18 Wilson St Burnie TAS 7320",
    "addr:housenumber":"18",
    "addr:postcode":"7320",
    "addr:street":"Wilson St",
    "iso:country":"AU",
    "sg:address":"18 Wilson St",
    "sg:city":"Burnie",
    "sg:classifiers":[
        {
            "category":"Casinos & Gambling",
            "type":"Entertainment"
        }
    ],
    "sg:phone":"+61 3 6431 3513",
    "sg:postcode":"7320",
    "sg:province":"TAS",
    "sg:tags":[
        "lottery",
        "agent"
    ],
    "wof:name":"Burnie Newsagency",
    "wof:placetype":"venue"
},
  "geometry": {"coordinates":[145.906509,-41.051193],"type":"Point"}
}