{
  "type": "Feature",
  "properties": {
    "addr:full":"14 Voyager Crt Cooloongup WA 6168",
    "addr:housenumber":"14",
    "addr:postcode":"6168",
    "addr:street":"Voyager Crt",
    "iso:country":"AU",
    "sg:address":"14 Voyager Crt",
    "sg:city":"Cooloongup",
    "sg:classifiers":[
        {
            "category":"Social Services",
            "subcategory":"Adult Care",
            "type":"Services"
        }
    ],
    "sg:phone":"+61 407 925 262",
    "sg:postcode":"6168",
    "sg:province":"WA",
    "sg:tags":[
        "towing"
    ],
    "wof:name":"Rocky City Towing",
    "wof:placetype":"venue"
},
  "geometry": {"coordinates":[115.758972,-32.293133],"type":"Point"}
}