{
  "type": "Feature",
  "properties": {
    "iso:country":"AU",
    "sg:address":"89 McCoy St",
    "sg:city":"Myaree",
    "sg:classifiers":[
        {
            "category":"Building & Trades",
            "subcategory":"Construction",
            "type":"Services"
        }
    ],
    "sg:phone":"+61 8 9330 2282",
    "sg:postcode":"6154",
    "sg:province":"WA",
    "sg:tags":[
        "joiner",
        "carpenter"
    ],
    "wof:name":"Cockburn Joinery",
    "wof:placetype":"venue"
},
  "geometry": {"coordinates":[115.821968,-32.043346],"type":"Point"}
}