{
  "type": "Feature",
  "properties": {
    "addr:full":"120 Island Point Rd St Georges Basin NSW 2540",
    "addr:housenumber":"120",
    "addr:postcode":"2540",
    "addr:street":"Island Point Rd",
    "iso:country":"AU",
    "sg:address":"120 Island Point Rd",
    "sg:city":"St Georges Basin",
    "sg:classifiers":[
        {
            "category":"Retail",
            "subcategory":"Auto Repair",
            "type":"Services"
        }
    ],
    "sg:phone":"+61 2 4443 4444",
    "sg:postcode":"2540",
    "sg:province":"NSW",
    "sg:tags":[
        "testing",
        "inspection",
        "motor",
        "vehicle"
    ],
    "wof:name":"St Georges Basin Auto Repairs Pty Ltd",
    "wof:placetype":"venue"
},
  "geometry": {"coordinates":[150.598022461,-35.0904808044],"type":"Point"}
}