{
  "type": "Feature",
  "properties": {
    "addr:full":"16 Bushmead St Nerang QLD 4211",
    "addr:housenumber":"16",
    "addr:postcode":"4211",
    "addr:street":"Bushmead St",
    "iso:country":"AU",
    "sg:address":"16 Bushmead St",
    "sg:city":"Nerang",
    "sg:classifiers":[
        {
            "category":"Building & Trades",
            "subcategory":"Construction",
            "type":"Services"
        }
    ],
    "sg:phone":"+61 418 757 982",
    "sg:postcode":"4211",
    "sg:province":"QLD",
    "sg:tags":[
        "fencing",
        "contractor"
    ],
    "wof:name":"Colin D Evans Fencing",
    "wof:placetype":"venue"
},
  "geometry": {"coordinates":[153.330444336,-27.9879417419],"type":"Point"}
}