{
  "type": "Feature",
  "properties": {
    "iso:country":"AU",
    "sg:address":"U5/ 13 Villiers Drv",
    "sg:city":"Currumbin Waters",
    "sg:classifiers":[
        {
            "category":"Autos & Motor Vehicles",
            "subcategory":"Auto Supplies",
            "type":"Retail Goods"
        }
    ],
    "sg:phone":"+61 7 5525 0387",
    "sg:postcode":"4223",
    "sg:province":"QLD",
    "sg:tags":[
        "wheel",
        "automotive",
        "rim"
    ],
    "wof:name":"The Wheel Wizard",
    "wof:placetype":"venue"
},
  "geometry": {"coordinates":[153.47383117699999,-28.1511001587],"type":"Point"}
}