{
  "type": "Feature",
  "properties": {
    "addr:full":"Unit2/ 40a O'Dea Ave Waterloo NSW 2017",
    "addr:housenumber":"40a",
    "addr:postcode":"2017",
    "addr:street":"O'Dea Ave",
    "iso:country":"AU",
    "sg:address":"Unit2/ 40a O'Dea Ave",
    "sg:city":"Waterloo",
    "sg:classifiers":[
        {
            "category":"Communications",
            "type":"Services"
        }
    ],
    "sg:phone":"+61 2 9699 9485",
    "sg:postcode":"2017",
    "sg:province":"NSW",
    "sg:tags":[
        "data"
    ],
    "wof:name":"Elecdata Australia",
    "wof:placetype":"venue"
},
  "geometry": {"coordinates":[151.210861206,-33.9033050537],"type":"Point"}
}