{
  "type": "Feature",
  "properties": {
    "iso:country":"AU",
    "sg:address":"123 Mort St (Cnr Campbell St)",
    "sg:city":"Toowoomba",
    "sg:classifiers":[
        {
            "category":"Professional",
            "subcategory":"Printing & Photocopies",
            "type":"Services"
        }
    ],
    "sg:phone":"+61 7 4632 5761",
    "sg:postcode":"4350",
    "sg:province":"QLD",
    "sg:tags":[
        "trophy"
    ],
    "wof:name":"A1 Badge & Trophy Centre",
    "wof:placetype":"venue"
},
  "geometry": {"coordinates":[151.949554,-27.555033],"type":"Point"}
}