{
  "type": "Feature",
  "properties": {
    "addr:full":"454- 462 Oxford St Bondi Junction DC NSW 2022",
    "addr:housenumber":"462",
    "addr:postcode":"2022",
    "addr:street":"Oxford St",
    "iso:country":"AU",
    "sg:address":"454- 462 Oxford St",
    "sg:city":"Bondi Junction DC",
    "sg:classifiers":[
        {
            "category":"Fast Food",
            "type":"Food & Drink"
        }
    ],
    "sg:phone":"+61 2 9388 0591",
    "sg:postcode":"2022",
    "sg:province":"NSW",
    "sg:tags":[
        "away",
        "take"
    ],
    "wof:name":"Hungry Jacks Pty Ltd",
    "wof:placetype":"venue"
},
  "geometry": {"coordinates":[151.249176025,-33.891872406],"type":"Point"}
}