{
  "type": "Feature",
  "properties": {
    "addr:full":"Suite 630 1 Queens Rd Melbourne VIC 3004",
    "addr:housenumber":"1",
    "addr:postcode":"3004",
    "addr:street":"Queens Rd",
    "iso:country":"AU",
    "sg:address":"Suite 630 1 Queens Rd",
    "sg:city":"Melbourne",
    "sg:classifiers":[
        {
            "category":"Banks & Credit Unions",
            "subcategory":"Financial Services",
            "type":"Services"
        }
    ],
    "sg:phone":"+61 3 9867 2811",
    "sg:postcode":"3004",
    "sg:province":"VIC",
    "sg:tags":[
        "financier"
    ],
    "wof:name":"CVC Venture Managers Pty Ltd",
    "wof:placetype":"venue"
},
  "geometry": {"coordinates":[144.96234130900001,-37.8188362122],"type":"Point"}
}