{
  "type": "Feature",
  "properties": {
    "addr:full":"9 Alex Ave Wheelers Hill VIC 3150",
    "addr:housenumber":"9",
    "addr:postcode":"3150",
    "addr:street":"Alex Ave",
    "iso:country":"AU",
    "sg:address":"9 Alex Ave",
    "sg:city":"Wheelers Hill",
    "sg:classifiers":[
        {
            "category":"Manufacturing",
            "subcategory":"Jewelry",
            "type":"Manufacturing & Wholesale Goods"
        }
    ],
    "sg:phone":"+61 3 9562 5614",
    "sg:postcode":"3150",
    "sg:province":"VIC",
    "sg:tags":[
        "mfrg",
        "jeweller"
    ],
    "wof:name":"U-M-I International",
    "wof:placetype":"venue"
},
  "geometry": {"coordinates":[145.19105529800001,-37.9041137695],"type":"Point"}
}