{
  "type": "Feature",
  "properties": {
    "addr:full":"17 Princess St Kew VIC 3101",
    "addr:housenumber":"17",
    "addr:postcode":"3101",
    "addr:street":"Princess St",
    "iso:country":"AU",
    "sg:address":"17 Princess St",
    "sg:city":"Kew",
    "sg:classifiers":[
        {
            "category":"Health Services",
            "subcategory":"Health Practitioner",
            "type":"Services"
        }
    ],
    "sg:phone":"+61 3 9855 2425",
    "sg:postcode":"3101",
    "sg:province":"VIC",
    "sg:tags":[
        "psychologist"
    ],
    "wof:name":"Psychometric Solutions & Innovations Pty Ltd",
    "wof:placetype":"venue"
},
  "geometry": {"coordinates":[145.02871704099999,-37.8066177368],"type":"Point"}
}