{
  "type": "Feature",
  "properties": {
    "addr:full":"Shp2/ 4 Walpole St Kew VIC 3101",
    "addr:housenumber":"4",
    "addr:postcode":"3101",
    "addr:street":"Walpole",
    "iso:country":"AU",
    "sg:address":"Shp2/ 4 Walpole St",
    "sg:city":"Kew",
    "sg:classifiers":[
        {
            "category":"Personal",
            "subcategory":"Beauty Salon",
            "type":"Services"
        }
    ],
    "sg:phone":"+61 3 9853 7477",
    "sg:postcode":"3101",
    "sg:province":"VIC",
    "sg:tags":[
        "hairdresser"
    ],
    "wof:name":"Inigo Haircutters",
    "wof:placetype":"venue"
},
  "geometry": {"coordinates":[145.03158569300001,-37.8063201904],"type":"Point"}
}