{
  "type": "Feature",
  "properties": {
    "addr:full":"155 Barracks Flat Drv Karabar ACT 2620",
    "addr:housenumber":"155",
    "addr:postcode":"2620",
    "addr:street":"Barracks Flat Drv",
    "iso:country":"AU",
    "sg:address":"155 Barracks Flat Drv",
    "sg:city":"Karabar",
    "sg:classifiers":[
        {
            "category":"Building & Trades",
            "subcategory":"Construction",
            "type":"Services"
        }
    ],
    "sg:phone":"+61 2 6297 4448",
    "sg:postcode":"2620",
    "sg:province":"ACT",
    "sg:tags":[
        "scaffolding"
    ],
    "wof:name":"Trojan Scaffolding Pty Ltd",
    "wof:placetype":"venue"
},
  "geometry": {"coordinates":[149.228027344,-35.3601341248],"type":"Point"}
}