{
  "type": "Feature",
  "properties": {
    "iso:country":"AU",
    "sg:address":"12 Chester St",
    "sg:city":"Newstead",
    "sg:classifiers":[
        {
            "category":"Manufacturing",
            "subcategory":"Furniture",
            "type":"Manufacturing & Wholesale Goods"
        }
    ],
    "sg:phone":"+61 7 3257 7333",
    "sg:postcode":"4006",
    "sg:province":"QLD",
    "sg:tags":[
        "builder",
        "designer",
        "custom"
    ],
    "wof:name":"DVO Furniture Design",
    "wof:placetype":"venue"
},
  "geometry": {"coordinates":[153.041213989,-27.4543533325],"type":"Point"}
}