{
  "type": "Feature",
  "properties": {
    "addr:full":"26 King St Newcastle NSW 2300",
    "addr:housenumber":"26",
    "addr:postcode":"2300",
    "addr:street":"King St",
    "iso:country":"AU",
    "sg:address":"26 King St",
    "sg:city":"Newcastle",
    "sg:classifiers":[
        {
            "category":"Insurance",
            "subcategory":"Title Insurance",
            "type":"Services"
        }
    ],
    "sg:phone":"+61 2 4925 2722",
    "sg:postcode":"2300",
    "sg:province":"NSW",
    "sg:tags":[
        "searcher"
    ],
    "wof:name":"Newcastle City Agents",
    "wof:placetype":"venue"
},
  "geometry": {"coordinates":[151.783569,-32.928558],"type":"Point"}
}