{
  "type": "Feature",
  "properties": {
    "addr:full":"24 Vimy St Rainworth QLD 4065",
    "addr:housenumber":"24",
    "addr:postcode":"4065",
    "addr:street":"Vimy St",
    "iso:country":"AU",
    "sg:address":"24 Vimy St",
    "sg:city":"Rainworth",
    "sg:classifiers":[
        {
            "category":"Professional",
            "subcategory":"Detective & Security Services",
            "type":"Services"
        }
    ],
    "sg:phone":"+61 7 3870 2982",
    "sg:postcode":"4065",
    "sg:province":"QLD",
    "sg:tags":[
        "equipment",
        "window",
        "doors"
    ],
    "wof:name":"Martins Security Etch & Service",
    "wof:placetype":"venue"
},
  "geometry": {"coordinates":[152.98684692399999,-27.4695205688],"type":"Point"}
}