{
  "type": "Feature",
  "properties": {
    "addr:full":"Victoria St Georges Plains NSW 2795",
    "addr:postcode":"2795",
    "addr:street":"Victoria St",
    "iso:country":"AU",
    "sg:address":"Victoria St",
    "sg:city":"Georges Plains",
    "sg:classifiers":[
        {
            "category":"Manufacturing",
            "subcategory":"Glass & Minerals",
            "type":"Manufacturing & Wholesale Goods"
        }
    ],
    "sg:phone":"+61 2 6337 2403",
    "sg:postcode":"2795",
    "sg:province":"NSW",
    "sg:tags":[
        "merchant",
        "granite",
        "marble"
    ],
    "wof:name":"Marble Aggregate Distributors",
    "wof:placetype":"venue"
},
  "geometry": {"coordinates":[149.52534484899999,-33.515247345],"type":"Point"}
}