{
  "type": "Feature",
  "properties": {
    "addr:full":"50 McLachlan St Fortitude Valley QLD 4006",
    "addr:housenumber":"50",
    "addr:postcode":"4006",
    "addr:street":"Mclachlan St",
    "iso:country":"AU",
    "sg:address":"50 McLachlan St",
    "sg:city":"Fortitude Valley",
    "sg:classifiers":[
        {
            "category":"Banks & Credit Unions",
            "subcategory":"Investment Brokerage",
            "type":"Services"
        }
    ],
    "sg:phone":"+61 7 3253 1670",
    "sg:postcode":"4006",
    "sg:province":"QLD",
    "sg:tags":[
        "management",
        "property"
    ],
    "wof:name":"Team Property Management Pty Ltd",
    "wof:placetype":"venue"
},
  "geometry": {"coordinates":[153.03630065900001,-27.4582977295],"type":"Point"}
}