{
  "type": "Feature",
  "properties": {
    "addr:full":"49 County Drv Cherrybrook NSW 2126",
    "addr:housenumber":"49",
    "addr:postcode":"2126",
    "addr:street":"County Drv",
    "iso:country":"AU",
    "sg:address":"49 County Drv",
    "sg:city":"Cherrybrook",
    "sg:classifiers":[
        {
            "category":"Health Services",
            "subcategory":"Doctor",
            "type":"Services"
        }
    ],
    "sg:phone":"+61 412 249 574",
    "sg:postcode":"2126",
    "sg:province":"NSW",
    "sg:tags":[
        "medical",
        "practitioner"
    ],
    "wof:name":"Oldfield L J Dr",
    "wof:placetype":"venue"
},
  "geometry": {"coordinates":[151.03099060100001,-33.7295379639],"type":"Point"}
}