{
  "type": "Feature",
  "properties": {
    "iso:country":"AU",
    "sg:address":"PO Box 6911",
    "sg:city":"East Perth",
    "sg:classifiers":[
        {
            "category":"Banks & Credit Unions",
            "subcategory":"Financial Services",
            "type":"Services"
        }
    ],
    "sg:phone":"+61 8 6461 5470",
    "sg:postcode":"6892",
    "sg:province":"WA",
    "sg:tags":[
        "settlement",
        "nt",
        "agent",
        "wa"
    ],
    "wof:name":"Simply Settlements",
    "wof:placetype":"venue"
},
  "geometry": {"coordinates":[115.87187194800001,-31.9584293365],"type":"Point"}
}