{
  "type": "Feature",
  "properties": {
    "addr:full":"Baulch Rd Dhurringile VIC 3610",
    "addr:postcode":"3610",
    "addr:street":"Baulch Rd",
    "iso:country":"AU",
    "sg:address":"Baulch Rd",
    "sg:city":"Dhurringile",
    "sg:classifiers":[
        {
            "category":"Farming",
            "subcategory":"Farm",
            "type":"Manufacturing & Wholesale Goods"
        }
    ],
    "sg:phone":"+61 3 5826 6296",
    "sg:postcode":"3610",
    "sg:province":"VIC",
    "sg:tags":[
        "farmer"
    ],
    "wof:name":"Chessells SP & KM &#034;The Willows&#034;",
    "wof:placetype":"venue"
},
  "geometry": {"coordinates":[145.23194885300001,-36.5283966064],"type":"Point"}
}