{
  "type": "Feature",
  "properties": {
    "addr:full":"Level 4, 12 Pirie St Adelaide SA 5000",
    "addr:housenumber":"12",
    "addr:postcode":"5000",
    "addr:street":"Pirie St",
    "iso:country":"AU",
    "sg:address":"Level 4, 12 Pirie St",
    "sg:city":"Adelaide",
    "sg:classifiers":[
        {
            "category":"Professional",
            "subcategory":"Employment Agencies",
            "type":"Services"
        }
    ],
    "sg:phone":"+61 8 8468 8080",
    "sg:postcode":"5000",
    "sg:province":"SA",
    "sg:tags":[
        "hire",
        "labour",
        "contractor"
    ],
    "wof:name":"Select Industrial",
    "wof:placetype":"venue"
},
  "geometry": {"coordinates":[138.60008239699999,-34.9256324768],"type":"Point"}
}