{
  "type": "Feature",
  "properties": {
    "addr:full":"3 Anne St Koroit VIC 3282",
    "addr:housenumber":"3",
    "addr:postcode":"3282",
    "addr:street":"Anne St",
    "iso:country":"AU",
    "sg:address":"3 Anne St",
    "sg:city":"Koroit",
    "sg:classifiers":[
        {
            "category":"Building & Trades",
            "subcategory":"Construction",
            "type":"Services"
        }
    ],
    "sg:phone":"+61 428 528 971",
    "sg:postcode":"3282",
    "sg:province":"VIC",
    "sg:tags":[
        "welding"
    ],
    "wof:name":"O&#039;Rourke J",
    "wof:placetype":"venue"
},
  "geometry": {"coordinates":[142.37315368599999,-38.3029327393],"type":"Point"}
}