{
  "type": "Feature",
  "properties": {
    "addr:full":"South Rd Cape Jervis SA 5204",
    "addr:postcode":"5204",
    "addr:street":"South Rd",
    "iso:country":"AU",
    "sg:address":"South Rd",
    "sg:city":"Cape Jervis",
    "sg:classifiers":[
        {
            "category":"Building & Trades",
            "subcategory":"Construction",
            "type":"Services"
        }
    ],
    "sg:phone":"+61 8 8598 0150",
    "sg:postcode":"5204",
    "sg:province":"SA",
    "sg:tags":[
        "earth",
        "excavating",
        "moving",
        "contractor"
    ],
    "wof:name":"Hill Civil",
    "wof:placetype":"venue"
},
  "geometry": {"coordinates":[138.298583984,-35.4722137451],"type":"Point"}
}