{
  "type": "Feature",
  "properties": {
    "addr:full":"Goodman St Nakara NT 0810",
    "addr:postcode":"nt 0810",
    "addr:street":"Goodman St",
    "iso:country":"AU",
    "sg:address":"Goodman St",
    "sg:city":"Nakara",
    "sg:classifiers":[
        {
            "category":"Education",
            "subcategory":"School",
            "type":"Public Place"
        }
    ],
    "sg:phone":"+61 8 8927 9823",
    "sg:postcode":"0810",
    "sg:province":"NT",
    "sg:tags":[
        "state",
        "except",
        "nsw"
    ],
    "wof:name":"Nakara Primary School",
    "wof:placetype":"venue"
},
  "geometry": {"coordinates":[130.87759399399999,-12.3728809357],"type":"Point"}
}