{
  "type": "Feature",
  "properties": {
    "addr:full":"28 St Helens Rd Hawthorn East VIC 3123",
    "addr:housenumber":"28",
    "addr:postcode":"3123",
    "addr:street":"St Helens Rd",
    "iso:country":"AU",
    "sg:address":"28 St Helens Rd",
    "sg:city":"Hawthorn East",
    "sg:classifiers":[
        {
            "category":"Professional",
            "subcategory":"Art Services",
            "type":"Services"
        }
    ],
    "sg:phone":"+61 3 9882 4477",
    "sg:postcode":"3123",
    "sg:province":"VIC",
    "sg:tags":[
        "graphic",
        "designer"
    ],
    "wof:name":"Diana Platt Design & Illustration",
    "wof:placetype":"venue"
},
  "geometry": {"coordinates":[145.04898071299999,-37.8363876343],"type":"Point"}
}