{
  "type": "Feature",
  "properties": {
    "iso:country":"AU",
    "sg:address":"15a Beltana St",
    "sg:city":"Ryde",
    "sg:classifiers":[
        {
            "category":"Building & Trades",
            "subcategory":"Construction",
            "type":"Services"
        }
    ],
    "sg:phone":"+61 2 9807 2636",
    "sg:postcode":"2112",
    "sg:province":"NSW",
    "sg:tags":[
        "contractor"
    ],
    "wof:name":"Denistone Constructions Pty Ltd",
    "wof:placetype":"venue"
},
  "geometry": {"coordinates":[151.09732055699999,-33.8012199402],"type":"Point"}
}