{
  "type": "Feature",
  "properties": {
    "iso:country":"AU",
    "sg:address":"5 Crompton Rd",
    "sg:city":"Littlehampton",
    "sg:classifiers":[
        {
            "category":"Manufacturing",
            "subcategory":"Rubber & Plastics",
            "type":"Manufacturing & Wholesale Goods"
        }
    ],
    "sg:phone":"+61 8 8391 0288",
    "sg:postcode":"5250",
    "sg:province":"SA",
    "sg:tags":[
        "wholesaler",
        "product",
        "mfrs"
    ],
    "wof:name":"Clear Creations",
    "wof:placetype":"venue"
},
  "geometry": {"coordinates":[138.845504761,-35.0543479919],"type":"Point"}
}