{
  "type": "Feature",
  "properties": {
    "addr:full":"42b Charlton Rd Olympic Dam SA 5725",
    "addr:housenumber":"42b",
    "addr:postcode":"5725",
    "addr:street":"Charlton Rd",
    "iso:country":"AU",
    "sg:address":"42b Charlton Rd",
    "sg:city":"Olympic Dam",
    "sg:classifiers":[
        {
            "category":"Autos & Motor Vehicles",
            "subcategory":"Auto Supplies",
            "type":"Retail Goods"
        }
    ],
    "sg:phone":"+61 8 8671 1096",
    "sg:postcode":"5725",
    "sg:province":"SA",
    "sg:tags":[
        "tyre"
    ],
    "wof:name":"Mining And Industrial Tyre Services",
    "wof:placetype":"venue"
},
  "geometry": {"coordinates":[136.872955322,-30.5030097961],"type":"Point"}
}