{
  "type": "Feature",
  "properties": {
    "iso:country":"AU",
    "sg:address":"184 Clarinda St",
    "sg:city":"Parkes",
    "sg:classifiers":[
        {
            "category":"Food & Beverages",
            "subcategory":"Bakery",
            "type":"Retail Goods"
        }
    ],
    "sg:phone":"+61 2 6862 2515",
    "sg:postcode":"2870",
    "sg:province":"NSW",
    "sg:tags":[
        "baker"
    ],
    "wof:name":"Smeaton's Bakery (Parkes)",
    "wof:placetype":"venue"
},
  "geometry": {"coordinates":[148.17514,-33.139072],"type":"Point"}
}