{
  "type": "Feature",
  "properties": {
    "iso:country":"AU",
    "sg:address":"9 Highland Ave",
    "sg:city":"Highett",
    "sg:classifiers":[
        {
            "category":"Professional",
            "subcategory":"Engineering",
            "type":"Services"
        }
    ],
    "sg:phone":"+61 3 9598 8934",
    "sg:postcode":"3190",
    "sg:province":"VIC",
    "sg:tags":[
        "engineer"
    ],
    "wof:name":"Facet Engineering Pty Ltd",
    "wof:placetype":"venue"
},
  "geometry": {"coordinates":[145.02842712399999,-37.953327179],"type":"Point"}
}