{
  "type": "Feature",
  "properties": {
    "addr:full":"5 Glen St Millicent SA 5280",
    "addr:housenumber":"5",
    "addr:postcode":"5280",
    "addr:street":"Glen St",
    "iso:country":"AU",
    "sg:address":"5 Glen St",
    "sg:city":"Millicent",
    "sg:classifiers":[
        {
            "category":"Shopping",
            "subcategory":"Stationery & Office Supplies",
            "type":"Retail Goods"
        }
    ],
    "sg:phone":"+61 8 8733 2461",
    "sg:postcode":"5280",
    "sg:province":"SA",
    "sg:tags":[
        "equipment",
        "facsimile"
    ],
    "wof:name":"Millicent Newsagency",
    "wof:placetype":"venue"
},
  "geometry": {"coordinates":[140.354095,-37.595322],"type":"Point"}
}