{
  "type": "Feature",
  "properties": {
    "addr:full":"PO Box 49 Sandown Village VIC 3171",
    "addr:postcode":"3171",
    "iso:country":"AU",
    "sg:address":"PO Box 49",
    "sg:city":"Sandown Village",
    "sg:classifiers":[
        {
            "category":"Shopping",
            "subcategory":"Gifts & Souvenirs",
            "type":"Retail Goods"
        }
    ],
    "sg:phone":"+61 3 9557 0667",
    "sg:postcode":"3171",
    "sg:province":"VIC",
    "sg:tags":[
        "shop",
        "supply"
    ],
    "wof:name":"Ricci International Pty Ltd",
    "wof:placetype":"venue"
},
  "geometry": {"coordinates":[145.167526245,-37.9366416931],"type":"Point"}
}