{
  "type": "Feature",
  "properties": {
    "iso:country":"AU",
    "sg:address":"11 Langford St",
    "sg:city":"Pooraka",
    "sg:classifiers":[
        {
            "category":"Retail",
            "subcategory":"Auto Repair",
            "type":"Services"
        }
    ],
    "sg:phone":"+61 8 8262 4033",
    "sg:postcode":"5095",
    "sg:province":"SA",
    "sg:tags":[
        "repairer",
        "motor",
        "engineer"
    ],
    "wof:name":"Precision Cylinder Heads",
    "wof:placetype":"venue"
},
  "geometry": {"coordinates":[138.62931823700001,-34.8166046143],"type":"Point"}
}