{
  "type": "Feature",
  "properties": {
    "addr:full":"PO Box 96 Coolangatta QLD 4225",
    "addr:postcode":"4225",
    "iso:country":"AU",
    "sg:address":"PO Box 96",
    "sg:city":"Coolangatta",
    "sg:classifiers":[
        {
            "category":"Manufacturing",
            "subcategory":"Metals",
            "type":"Manufacturing & Wholesale Goods"
        }
    ],
    "sg:phone":"+61 1300 166 673",
    "sg:postcode":"4225",
    "sg:province":"QLD",
    "sg:tags":[
        "anodisers"
    ],
    "wof:name":"Aussie Anodes",
    "wof:placetype":"venue"
},
  "geometry": {"coordinates":[153.537841797,-28.1684398651],"type":"Point"}
}