{
  "type": "Feature",
  "properties": {
    "addr:full":"45- 48 Williams Esp Palm Cove QLD 4879",
    "addr:housenumber":"48",
    "addr:postcode":"4879",
    "iso:country":"AU",
    "sg:address":"45- 48 Williams Esp",
    "sg:city":"Palm Cove",
    "sg:classifiers":[
        {
            "category":"Personal",
            "subcategory":"Day Spa",
            "type":"Services"
        }
    ],
    "sg:phone":"+61 7 4059 3211",
    "sg:postcode":"4879",
    "sg:province":"QLD",
    "wof:name":"Amphora Spa",
    "wof:placetype":"venue"
},
  "geometry": {"coordinates":[145.67089843799999,-16.7444133759],"type":"Point"}
}