{
  "type": "Feature",
  "properties": {
    "iso:country":"AU",
    "sg:address":"25 Queen St",
    "sg:city":"Peterborough",
    "sg:classifiers":[
        {
            "category":"Travel",
            "subcategory":"Hotels & Motels",
            "type":"Entertainment"
        }
    ],
    "sg:phone":"+61 8 8651 2078",
    "sg:postcode":"5422",
    "sg:province":"SA",
    "wof:name":"Golden Chain Peterborough Motor Inn",
    "wof:placetype":"venue"
},
  "geometry": {"coordinates":[138.84201049800001,-32.9773406982],"type":"Point"}
}