{
  "type": "Feature",
  "properties": {
    "addr:full":"2 Curtain Crt Morayfield QLD 4506",
    "addr:housenumber":"2",
    "addr:postcode":"4506",
    "addr:street":"Curtain Crt",
    "iso:country":"AU",
    "sg:address":"2 Curtain Crt",
    "sg:city":"Morayfield",
    "sg:classifiers":[
        {
            "category":"Building & Trades",
            "subcategory":"Pest Control",
            "type":"Services"
        }
    ],
    "sg:phone":"+61 7 5428 7828",
    "sg:postcode":"4506",
    "sg:province":"QLD",
    "wof:name":"PMP Pest Control",
    "wof:placetype":"venue"
},
  "geometry": {"coordinates":[152.963088989,-27.1175498962],"type":"Point"}
}