{
  "type": "Feature",
  "properties": {
    "addr:full":"Shop 6 Cessnock Market Place Cessnock NSW 2325",
    "addr:housenumber":"shop 6",
    "addr:postcode":"2325",
    "addr:street":"Market Place",
    "iso:country":"AU",
    "sg:address":"Shop 6 Cessnock Market Place",
    "sg:city":"Cessnock",
    "sg:classifiers":[
        {
            "category":"Fast Food",
            "type":"Food & Drink"
        }
    ],
    "sg:phone":"+61 2 4990 4034",
    "sg:postcode":"2325",
    "sg:province":"NSW",
    "sg:tags":[
        "away",
        "take"
    ],
    "wof:name":"Subway",
    "wof:placetype":"venue"
},
  "geometry": {"coordinates":[151.35743713400001,-32.8414001465],"type":"Point"}
}