{
  "type": "Feature",
  "properties": {
    "iso:country":"AU",
    "sg:address":"Unit 5/ 8 Thornborough Rd",
    "sg:city":"Mandurah",
    "sg:classifiers":[
        {
            "category":"Education",
            "subcategory":"Dance Studio",
            "type":"Public Place"
        }
    ],
    "sg:phone":"+61 8 9582 2708",
    "sg:postcode":"6210",
    "sg:province":"WA",
    "sg:tags":[
        "venue",
        "tuition"
    ],
    "wof:name":"Dianne Wood School Of Dancing",
    "wof:placetype":"venue"
},
  "geometry": {"coordinates":[115.752739,-32.512726],"type":"Point"}
}