{
  "type": "Feature",
  "properties": {
    "iso:country":"AU",
    "sg:address":"14 Bangor Pl",
    "sg:city":"Beldon",
    "sg:classifiers":[
        {
            "category":"Home & Garden",
            "subcategory":"Carpets & Floor Coverings",
            "type":"Retail Goods"
        }
    ],
    "sg:phone":"+61 418 190 018",
    "sg:postcode":"6027",
    "sg:province":"WA",
    "sg:tags":[
        "tile",
        "wall",
        "layer"
    ],
    "wof:name":"Fair & Square Tiling Service",
    "wof:placetype":"venue"
},
  "geometry": {"coordinates":[115.76361084,-31.7755298615],"type":"Point"}
}