{
  "type": "Feature",
  "properties": {
    "addr:full":"8 Macgregory St Parkdale VIC 3194",
    "addr:housenumber":"8",
    "addr:postcode":"3194",
    "addr:street":"Macgregory St",
    "iso:country":"AU",
    "sg:address":"8 Macgregory St",
    "sg:city":"Parkdale",
    "sg:classifiers":[
        {
            "category":"Building & Trades",
            "subcategory":"Construction",
            "type":"Services"
        }
    ],
    "sg:phone":"+61 407 308 608",
    "sg:postcode":"3194",
    "sg:province":"VIC",
    "sg:tags":[
        "joiner",
        "carpenter"
    ],
    "wof:name":"C.J.G. Construction",
    "wof:placetype":"venue"
},
  "geometry": {"coordinates":[145.08160400400001,-37.9821205139],"type":"Point"}
}