{
  "type": "Feature",
  "properties": {
    "addr:full":"Shop T38 Plumpton Market Place Hyatts Rd (cnr Jersey Rd) Plumpton NSW 2761",
    "addr:postcode":"2761",
    "addr:street":"Market Place Hyatts Rd Cnr Jersey Rd",
    "iso:country":"AU",
    "sg:address":"Shop T38 Plumpton Market Place Hyatts Rd",
    "sg:city":"(cnr Jersey Rd) Plumpton",
    "sg:classifiers":[
        {
            "category":"Fast Food",
            "type":"Food & Drink"
        }
    ],
    "sg:phone":"+61 2 9832 8302",
    "sg:postcode":"2761",
    "sg:province":"NSW",
    "sg:tags":[
        "away",
        "take"
    ],
    "wof:name":"Doner Kebabs 2000",
    "wof:placetype":"venue"
},
  "geometry": {"coordinates":[150.83424400000001,-33.74704],"type":"Point"}
}