{
  "type": "Feature",
  "properties": {
    "iso:country":"AU",
    "sg:address":"15 Norman Pl",
    "sg:city":"Innaloo",
    "sg:classifiers":[
        {
            "category":"Social Services",
            "subcategory":"Child Care",
            "type":"Services"
        }
    ],
    "sg:phone":"+61 8 9446 7597",
    "sg:postcode":"6018",
    "sg:province":"WA",
    "sg:tags":[
        "baby",
        "sitter"
    ],
    "wof:name":"Mother Hen Caring For Children",
    "wof:placetype":"venue"
},
  "geometry": {"coordinates":[115.794761658,-31.8834838867],"type":"Point"}
}