{
  "type": "Feature",
  "properties": {
    "addr:full":"Cnr Shadbolt & Ferguson Sts Mukinbudin WA 6479",
    "addr:postcode":"6479",
    "addr:street":"Cnr Shadbolt & Ferguson Sts",
    "iso:country":"AU",
    "sg:address":"Cnr Shadbolt & Ferguson Sts",
    "sg:city":"Mukinbudin",
    "sg:classifiers":[
        {
            "category":"Banks & Credit Unions",
            "subcategory":"Bank",
            "type":"Services"
        }
    ],
    "sg:phone":"+61 13 20 32",
    "sg:postcode":"6479",
    "sg:province":"WA",
    "wof:name":"Westpac",
    "wof:placetype":"venue"
},
  "geometry": {"coordinates":[118.20892334,-30.914560318],"type":"Point"}
}