{
  "type": "Feature",
  "properties": {
    "addr:full":"Bribie Island Rd Sandstone Point QLD 4511",
    "addr:postcode":"4511",
    "addr:street":"Island Rd",
    "iso:country":"AU",
    "sg:address":"Bribie Island Rd",
    "sg:city":"Sandstone Point",
    "sg:classifiers":[
        {
            "category":"Food & Beverages",
            "subcategory":"Meat & Fish",
            "type":"Retail Goods"
        }
    ],
    "sg:phone":"+61 7 5497 6444",
    "sg:postcode":"4511",
    "sg:province":"QLD",
    "sg:tags":[
        "seafood"
    ],
    "wof:name":"Spinnaker Seafood Market",
    "wof:placetype":"venue"
},
  "geometry": {"coordinates":[153.13085899999999,-27.068165],"type":"Point"}
}