{
  "type": "Feature",
  "properties": {
    "iso:country":"AU",
    "sg:address":"448 St Kilda Rd",
    "sg:city":"Melbourne",
    "sg:classifiers":[
        {
            "category":"Real Estate",
            "subcategory":"Real Estate Agent",
            "type":"Services"
        }
    ],
    "sg:phone":"+61 418 320 964",
    "sg:postcode":"3000",
    "sg:province":"VIC",
    "wof:name":"Anderson S",
    "wof:placetype":"venue"
},
  "geometry": {"coordinates":[144.97604370100001,-37.8386077881],"type":"Point"}
}