{
  "type": "Feature",
  "properties": {
    "iso:country":"AU",
    "sg:address":"Unit 8,6- 10 Booralee St",
    "sg:city":"Botany",
    "sg:classifiers":[
        {
            "category":"Professional",
            "subcategory":"Business Services",
            "type":"Services"
        }
    ],
    "sg:phone":"+61 2 9316 6292",
    "sg:postcode":"2019",
    "sg:province":"NSW",
    "sg:tags":[
        "exporter"
    ],
    "wof:name":"Jolly Roger Exports Pty Ltd",
    "wof:placetype":"venue"
},
  "geometry": {"coordinates":[151.191314697,-33.9467048645],"type":"Point"}
}