{
  "type": "Feature",
  "properties": {
    "iso:country":"AU",
    "sg:address":"D 2/ 303 The Horsley Drv",
    "sg:city":"Fairfield",
    "sg:classifiers":[
        {
            "category":"Retail",
            "subcategory":"Auto Repair",
            "type":"Services"
        }
    ],
    "sg:phone":"+61 2 9728 3094",
    "sg:postcode":"2165",
    "sg:province":"NSW",
    "sg:tags":[
        "engine",
        "reconditioning"
    ],
    "wof:name":"Fairfield Cylinder Head Services",
    "wof:placetype":"venue"
},
  "geometry": {"coordinates":[150.95979309099999,-33.8690834045],"type":"Point"}
}