{
  "type": "Feature",
  "properties": {
    "iso:country":"AU",
    "sg:address":"40 Hickson St",
    "sg:city":"Merewether",
    "sg:classifiers":[
        {
            "category":"Health Services",
            "subcategory":"Health Practitioner",
            "type":"Services"
        }
    ],
    "sg:phone":"+61 425 216 141",
    "sg:postcode":"2291",
    "sg:province":"NSW",
    "sg:tags":[
        "naturopath"
    ],
    "wof:name":"Marsha Tamplin",
    "wof:placetype":"venue"
},
  "geometry": {"coordinates":[151.74949645999999,-32.9515533447],"type":"Point"}
}