{
  "type": "Feature",
  "properties": {
    "iso:country":"AU",
    "sg:address":"322 Canning Hwy",
    "sg:city":"Bicton",
    "sg:classifiers":[
        {
            "category":"Health Services",
            "subcategory":"Doctor",
            "type":"Services"
        }
    ],
    "sg:phone":"+61 8 9319 2333",
    "sg:postcode":"6157",
    "sg:province":"WA",
    "sg:tags":[
        "medical",
        "practitioner"
    ],
    "wof:name":"Point Walter Medical Centre",
    "wof:placetype":"venue"
},
  "geometry": {"coordinates":[115.792603,-32.034538],"type":"Point"}
}