{
  "type": "Feature",
  "properties": {
    "addr:full":"87 Chifley Drv Preston VIC 3072",
    "addr:housenumber":"87",
    "addr:postcode":"3072",
    "addr:street":"Chifley Drv",
    "iso:country":"AU",
    "sg:address":"87 Chifley Drv",
    "sg:city":"Preston",
    "sg:classifiers":[
        {
            "category":"Shopping",
            "type":"Retail Goods"
        }
    ],
    "sg:phone":"+61 3 9479 4252",
    "sg:postcode":"3072",
    "sg:province":"VIC",
    "sg:tags":[
        "clearance",
        "factory",
        "outlet"
    ],
    "wof:name":"Stafford Factory Outlet",
    "wof:placetype":"venue"
},
  "geometry": {"coordinates":[145.03033447300001,-37.7432022095],"type":"Point"}
}