{
  "type": "Feature",
  "properties": {
    "iso:country":"AU",
    "sg:address":"Cnr Crook & Low St",
    "sg:city":"Bundaberg",
    "sg:classifiers":[
        {
            "category":"Wholesale",
            "subcategory":"Auto Parts",
            "type":"Manufacturing & Wholesale Goods"
        }
    ],
    "sg:phone":"+61 7 4155 1915",
    "sg:postcode":"4670",
    "sg:province":"QLD",
    "sg:tags":[
        "recyclers"
    ],
    "wof:name":"Bundaberg Auto Wreckers",
    "wof:placetype":"venue"
},
  "geometry": {"coordinates":[152.337280273,-24.9148368835],"type":"Point"}
}