{
  "type": "Feature",
  "properties": {
    "iso:country":"AU",
    "sg:address":"66 Reid Ave",
    "sg:city":"Tranmere North",
    "sg:classifiers":[
        {
            "category":"Government",
            "subcategory":"Post Office",
            "type":"Public Place"
        }
    ],
    "sg:phone":"+61 8 8337 1981",
    "sg:postcode":"5073",
    "sg:province":"SA",
    "sg:tags":[
        "postal"
    ],
    "wof:name":"Australia Post",
    "wof:placetype":"venue"
},
  "geometry": {"coordinates":[138.664306641,-34.8972702026],"type":"Point"}
}