{
  "type": "Feature",
  "properties": {
    "addr:full":"23- 27 Marquet St Rhodes NSW 2138",
    "addr:housenumber":"27",
    "addr:postcode":"2138",
    "addr:street":"Marquet St",
    "iso:country":"AU",
    "sg:address":"23- 27 Marquet St",
    "sg:city":"Rhodes",
    "sg:classifiers":[
        {
            "category":"Education",
            "subcategory":"Special Training",
            "type":"Public Place"
        }
    ],
    "sg:phone":"+61 2 9736 1777",
    "sg:postcode":"2138",
    "sg:province":"NSW",
    "sg:tags":[
        "development"
    ],
    "wof:name":"Electrotech Skill Centre",
    "wof:placetype":"venue"
},
  "geometry": {"coordinates":[151.08570861800001,-33.8292808533],"type":"Point"}
}