{
  "type": "Feature",
  "properties": {
    "iso:country":"AU",
    "sg:address":"133 Blossom Park Drv",
    "sg:city":"Mill Park",
    "sg:classifiers":[
        {
            "category":"Building & Trades",
            "subcategory":"Construction",
            "type":"Services"
        }
    ],
    "sg:phone":"+61 409 215 866",
    "sg:postcode":"3082",
    "sg:province":"VIC",
    "sg:tags":[
        "earth",
        "excavating",
        "moving",
        "contractor"
    ],
    "wof:name":"Metro Mini Diggers",
    "wof:placetype":"venue"
},
  "geometry": {"coordinates":[145.07771301299999,-37.6723136902],"type":"Point"}
}