{
  "type": "Feature",
  "properties": {
    "addr:full":"Cnr Nicklin Way & Main Drv Warana QLD 4575",
    "addr:postcode":"4575",
    "addr:street":"Cnr Nicklin Way & Main Drv",
    "iso:country":"AU",
    "sg:address":"Cnr Nicklin Way & Main Drv",
    "sg:city":"Warana",
    "sg:classifiers":[
        {
            "category":"Health Services",
            "subcategory":"Doctor",
            "type":"Services"
        }
    ],
    "sg:phone":"+61 7 5493 3800",
    "sg:postcode":"4575",
    "sg:province":"QLD",
    "sg:tags":[
        "medical",
        "practitioner"
    ],
    "wof:name":"Parsons Scott Dr",
    "wof:placetype":"venue"
},
  "geometry": {"coordinates":[153.12973,-26.719622],"type":"Point"}
}