{
  "type": "Feature",
  "properties": {
    "addr:full":"Shp 4/ 5 Beckmans Rd Noosaville QLD 4566",
    "addr:housenumber":"/ 5",
    "addr:postcode":"4566",
    "addr:street":"Beckmans Rd",
    "iso:country":"AU",
    "sg:address":"Shp 4/ 5 Beckmans Rd",
    "sg:city":"Noosaville",
    "sg:classifiers":[
        {
            "category":"Food & Beverages",
            "subcategory":"Groceries & Convenience Stores",
            "type":"Retail Goods"
        }
    ],
    "sg:phone":"+61 7 5455 6751",
    "sg:postcode":"4566",
    "sg:province":"QLD",
    "wof:name":"The Noosaville IGA",
    "wof:placetype":"venue"
},
  "geometry": {"coordinates":[153.03225707999999,-26.410993576],"type":"Point"}
}