{
  "type": "Feature",
  "properties": {
    "iso:country":"AU",
    "sg:address":"7 Forestville Crt",
    "sg:city":"Kallaroo",
    "sg:classifiers":[
        {
            "category":"Building & Trades",
            "subcategory":"Construction",
            "type":"Services"
        }
    ],
    "sg:phone":"+61 8 9307 4596",
    "sg:postcode":"6025",
    "sg:province":"WA",
    "sg:tags":[
        "contractor"
    ],
    "wof:name":"Show Homes",
    "wof:placetype":"venue"
},
  "geometry": {"coordinates":[115.741249084,-31.7868652344],"type":"Point"}
}