{
  "type": "Feature",
  "properties": {
    "iso:country":"AU",
    "sg:address":"Shop 4 36- 40 Milligan St",
    "sg:city":"Perth",
    "sg:classifiers":[
        {
            "category":"Banks & Credit Unions",
            "subcategory":"Bureau De Change",
            "type":"Services"
        }
    ],
    "sg:phone":"+61 8 9324 1755",
    "sg:postcode":"6000",
    "sg:province":"WA",
    "sg:tags":[
        "repairs",
        "part",
        "appliance",
        "electrical"
    ],
    "wof:name":"Morrow Electrical Services",
    "wof:placetype":"venue"
},
  "geometry": {"coordinates":[115.851852417,-31.9515094757],"type":"Point"}
}