{
  "type": "Feature",
  "properties": {
    "iso:country":"AU",
    "sg:address":"13 Daly Ave",
    "sg:city":"Rye",
    "sg:classifiers":[
        {
            "category":"Shopping",
            "subcategory":"Musical Instruments",
            "type":"Retail Goods"
        }
    ],
    "sg:phone":"+61 3 5985 5990",
    "sg:postcode":"3941",
    "sg:province":"VIC",
    "sg:tags":[
        "piano",
        "organ"
    ],
    "wof:name":"Mitchells Pianos",
    "wof:placetype":"venue"
},
  "geometry": {"coordinates":[144.834716797,-38.3738174438],"type":"Point"}
}