{
  "type": "Feature",
  "properties": {
    "addr:full":"44 Invermay Rd Invermay TAS 7248",
    "addr:housenumber":"44",
    "addr:postcode":"7248",
    "addr:street":"Invermay Rd",
    "iso:country":"AU",
    "sg:address":"44 Invermay Rd",
    "sg:city":"Invermay",
    "sg:classifiers":[
        {
            "category":"Food & Beverages",
            "subcategory":"Supermarket",
            "type":"Retail Goods"
        }
    ],
    "sg:phone":"+61 3 6331 3795",
    "sg:postcode":"7248",
    "sg:province":"TAS",
    "sg:tags":[
        "grocery",
        "store"
    ],
    "wof:name":"Value Plus IGA Stores",
    "wof:placetype":"venue"
},
  "geometry": {"coordinates":[147.13587951700001,-41.4216041565],"type":"Point"}
}