{
  "type": "Feature",
  "properties": {
    "iso:country":"AU",
    "sg:address":"29 Main St",
    "sg:city":"Osborne Park",
    "sg:classifiers":[
        {
            "category":"Travel",
            "subcategory":"Hotels & Motels",
            "type":"Entertainment"
        }
    ],
    "sg:phone":"+61 8 9201 9190",
    "sg:postcode":"6017",
    "sg:province":"WA",
    "wof:name":"Perth City Motel Osborne Park & Thornlie",
    "wof:placetype":"venue"
},
  "geometry": {"coordinates":[115.828018188,-31.9111690521],"type":"Point"}
}