{
  "type": "Feature",
  "properties": {
    "addr:full":"69 Chapel Hill Rd Chapel Hill QLD 4069",
    "addr:housenumber":"69",
    "addr:postcode":"4069",
    "addr:street":"Chapel Hill Rd",
    "iso:country":"AU",
    "sg:address":"69 Chapel Hill Rd",
    "sg:city":"Chapel Hill",
    "sg:classifiers":[
        {
            "category":"Utilities",
            "subcategory":"Water",
            "type":"Services"
        }
    ],
    "sg:phone":"+61 7 3378 0676",
    "sg:postcode":"4069",
    "sg:province":"QLD",
    "sg:tags":[
        "equipment",
        "treatment"
    ],
    "wof:name":"Smith Donald F & Associates",
    "wof:placetype":"venue"
},
  "geometry": {"coordinates":[152.95115661599999,-27.5041904449],"type":"Point"}
}