{
  "type": "Feature",
  "properties": {
    "iso:country":"AU",
    "sg:address":"1582 Centre Rd",
    "sg:city":"Springvale",
    "sg:classifiers":[
        {
            "category":"Wholesale",
            "subcategory":"Toys & Hobbies",
            "type":"Manufacturing & Wholesale Goods"
        }
    ],
    "sg:phone":"+61 3 9549 7070",
    "sg:postcode":"3171",
    "sg:province":"VIC",
    "sg:tags":[
        "mfrs"
    ],
    "wof:name":"Learning Curve Australia Pty Ltd",
    "wof:placetype":"venue"
},
  "geometry": {"coordinates":[145.143875122,-37.9317436218],"type":"Point"}
}