{
  "type": "Feature",
  "properties": {
    "addr:full":"Lot 94 Dunns Rd Balaklava SA 5461",
    "addr:postcode":"5461",
    "addr:street":"Dunns Rd",
    "iso:country":"AU",
    "sg:address":"Lot 94 Dunns Rd",
    "sg:city":"Balaklava",
    "sg:classifiers":[
        {
            "category":"Building & Trades",
            "subcategory":"Construction",
            "type":"Services"
        }
    ],
    "sg:phone":"+61 8 8862 2047",
    "sg:postcode":"5461",
    "sg:province":"SA",
    "sg:tags":[
        "stonework",
        "stone",
        "mason"
    ],
    "wof:name":"D.R. Cook Monumental Works",
    "wof:placetype":"venue"
},
  "geometry": {"coordinates":[138.43116800000001,-34.141449],"type":"Point"}
}