{
  "type": "Feature",
  "properties": {
    "addr:full":"73 Ardargie St Sunnybank QLD 4109",
    "addr:housenumber":"73",
    "addr:postcode":"4109",
    "addr:street":"Ardargie St",
    "iso:country":"AU",
    "sg:address":"73 Ardargie St",
    "sg:city":"Sunnybank",
    "sg:classifiers":[
        {
            "category":"Health Services",
            "subcategory":"Dentist",
            "type":"Services"
        }
    ],
    "sg:phone":"+61 7 3216 9667",
    "sg:postcode":"4109",
    "sg:province":"QLD",
    "sg:tags":[
        "dental",
        "prosthetist"
    ],
    "wof:name":"Mark Hayes Denture Clinic",
    "wof:placetype":"venue"
},
  "geometry": {"coordinates":[153.06347656200001,-27.5848350525],"type":"Point"}
}