{
  "type": "Feature",
  "properties": {
    "addr:full":"23 James Henty Drv Dural NSW 2158",
    "addr:housenumber":"23",
    "addr:postcode":"2158",
    "addr:street":"James Henty Drv",
    "iso:country":"AU",
    "sg:address":"23 James Henty Drv",
    "sg:city":"Dural",
    "sg:classifiers":[
        {
            "category":"Building & Trades",
            "subcategory":"Plumbing",
            "type":"Services"
        }
    ],
    "sg:phone":"+61 2 9651 4099",
    "sg:postcode":"2158",
    "sg:province":"NSW",
    "sg:tags":[
        "plumber",
        "gasfitters"
    ],
    "wof:name":"Krumbeck J & Co",
    "wof:placetype":"venue"
},
  "geometry": {"coordinates":[151.03167724599999,-33.7113761902],"type":"Point"}
}