{
  "type": "Feature",
  "properties": {
    "iso:country":"AU",
    "sg:address":"Level 1/ 521 Warrigal Rd",
    "sg:city":"Ashwood",
    "sg:classifiers":[
        {
            "category":"Real Estate",
            "subcategory":"Surveying",
            "type":"Services"
        }
    ],
    "sg:phone":"+61 3 9813 8022",
    "sg:postcode":"3147",
    "sg:province":"VIC",
    "sg:tags":[
        "surveyor",
        "land"
    ],
    "wof:name":"Bortoli Wellington Pty Ltd",
    "wof:placetype":"venue"
},
  "geometry": {"coordinates":[145.093093872,-37.8651618958],"type":"Point"}
}