{
  "type": "Feature",
  "properties": {
    "addr:full":"550 Newcastle St West Perth WA 6005",
    "addr:housenumber":"550",
    "addr:postcode":"6005",
    "addr:street":"Newcastle St",
    "iso:country":"AU",
    "sg:address":"550 Newcastle St",
    "sg:city":"West Perth",
    "sg:classifiers":[
        {
            "category":"Fast Food",
            "type":"Food & Drink"
        }
    ],
    "sg:phone":"+61 8 9328 6793",
    "sg:postcode":"6005",
    "sg:province":"WA",
    "sg:tags":[
        "away",
        "take"
    ],
    "wof:name":"North Shaw Lunch Bar",
    "wof:placetype":"venue"
},
  "geometry": {"coordinates":[115.84844207800001,-31.9402828217],"type":"Point"}
}