{
  "type": "Feature",
  "properties": {
    "iso:country":"AU",
    "sg:address":"4 Delvin Crt",
    "sg:city":"Arana Hills",
    "sg:classifiers":[
        {
            "category":"Building & Trades",
            "subcategory":"Plumbing",
            "type":"Services"
        }
    ],
    "sg:phone":"+61 7 3351 6226",
    "sg:postcode":"4054",
    "sg:province":"QLD",
    "sg:tags":[
        "plumber",
        "gasfitters"
    ],
    "wof:name":"Anthony McMahon Plumbing",
    "wof:placetype":"venue"
},
  "geometry": {"coordinates":[152.954315186,-27.3863334656],"type":"Point"}
}