{
  "type": "Feature",
  "properties": {
    "addr:full":"PO Box 996 Newcastle NSW 2300",
    "addr:postcode":"2300",
    "iso:country":"AU",
    "sg:address":"PO Box 996",
    "sg:city":"Newcastle",
    "sg:classifiers":[
        {
            "category":"Professional",
            "subcategory":"Business Services",
            "type":"Services"
        }
    ],
    "sg:phone":"+61 2 4952 4219",
    "sg:postcode":"2300",
    "sg:province":"NSW",
    "sg:tags":[
        "management",
        "event"
    ],
    "wof:name":"Gillies Public Relations",
    "wof:placetype":"venue"
},
  "geometry": {"coordinates":[151.780136,-32.930859],"type":"Point"}
}