{
  "type": "Feature",
  "properties": {
    "addr:full":"117 Liverpool Rd Burwood NSW 2134",
    "addr:housenumber":"117",
    "addr:postcode":"2134",
    "addr:street":"Liverpool Rd",
    "iso:country":"AU",
    "sg:address":"117 Liverpool Rd",
    "sg:city":"Burwood",
    "sg:classifiers":[
        {
            "category":"Travel",
            "subcategory":"Hotels & Motels",
            "type":"Entertainment"
        }
    ],
    "sg:phone":"+61 2 9744 0521",
    "sg:postcode":"2134",
    "sg:province":"NSW",
    "wof:name":"Comfort Inn & Suites Burwood",
    "wof:placetype":"venue"
},
  "geometry": {"coordinates":[151.09982299800001,-33.8873138428],"type":"Point"}
}