{
  "type": "Feature",
  "properties": {
    "addr:full":"PO Box 1982 Milton QLD 4064",
    "addr:postcode":"4064",
    "iso:country":"AU",
    "sg:address":"PO Box 1982",
    "sg:city":"Milton",
    "sg:classifiers":[
        {
            "category":"Building & Trades",
            "subcategory":"Plumbing",
            "type":"Services"
        }
    ],
    "sg:phone":"+61 1300 885 170",
    "sg:postcode":"4064",
    "sg:province":"QLD",
    "sg:tags":[
        "plumber",
        "gasfitters"
    ],
    "wof:name":"We&#039;ve Got Gas",
    "wof:placetype":"venue"
},
  "geometry": {"coordinates":[153.0052948,-27.4685897827],"type":"Point"}
}