{
  "type": "Feature",
  "properties": {
    "addr:full":"15 Stanley St Derby WA 6728",
    "addr:housenumber":"15",
    "addr:postcode":"6728",
    "addr:street":"Stanley St",
    "iso:country":"AU",
    "sg:address":"15 Stanley St",
    "sg:city":"Derby",
    "sg:classifiers":[
        {
            "category":"Professional",
            "subcategory":"Printing & Photocopies",
            "type":"Services"
        }
    ],
    "sg:phone":"+61 8 9191 1128",
    "sg:postcode":"6728",
    "sg:province":"WA",
    "sg:tags":[
        "screen",
        "printer"
    ],
    "wof:name":"Ngunga Designs",
    "wof:placetype":"venue"
},
  "geometry": {"coordinates":[123.63918304400001,-17.3076076508],"type":"Point"}
}