{
  "type": "Feature",
  "properties": {
    "iso:country":"AU",
    "sg:address":"320 Parramatta Rd",
    "sg:city":"Stanmore",
    "sg:classifiers":[
        {
            "category":"Shopping",
            "type":"Retail Goods"
        }
    ],
    "sg:phone":"+61 2 9560 7336",
    "sg:postcode":"2048",
    "sg:province":"NSW",
    "sg:tags":[
        "clearance",
        "factory",
        "outlet"
    ],
    "wof:name":"Kolotex Factory Shop",
    "wof:placetype":"venue"
},
  "geometry": {"coordinates":[151.163544,-33.888386],"type":"Point"}
}