{
  "type": "Feature",
  "properties": {
    "addr:full":"Shop 6 188 Yarra St Warrandyte VIC 3113",
    "addr:housenumber":"shop 6",
    "addr:postcode":"188;3113",
    "addr:street":"Yarra St",
    "iso:country":"AU",
    "sg:address":"Shop 6 188 Yarra St",
    "sg:city":"Warrandyte",
    "sg:classifiers":[
        {
            "category":"Government",
            "subcategory":"Post Office",
            "type":"Public Place"
        }
    ],
    "sg:phone":"+61 3 9844 5858",
    "sg:postcode":"3113",
    "sg:province":"VIC",
    "sg:tags":[
        "house",
        "doll"
    ],
    "wof:name":"Dolls Den Pty",
    "wof:placetype":"venue"
},
  "geometry": {"coordinates":[145.22036743199999,-37.7370834351],"type":"Point"}
}