{
  "type": "Feature",
  "properties": {
    "iso:country":"AU",
    "sg:address":"1274 Hay St",
    "sg:city":"West Perth",
    "sg:classifiers":[
        {
            "category":"Personal",
            "type":"Services"
        }
    ],
    "sg:phone":"+61 8 9324 2200",
    "sg:postcode":"6005",
    "sg:province":"WA",
    "sg:tags":[
        "career",
        "counselling"
    ],
    "wof:name":"Careerlife",
    "wof:placetype":"venue"
},
  "geometry": {"coordinates":[115.840087891,-31.9478874207],"type":"Point"}
}