{
  "type": "Feature",
  "properties": {
    "addr:full":"Shop 3, 112- 114 Boyce Rd Maroubra NSW 2035",
    "addr:housenumber":"shop 3;114",
    "addr:postcode":"112;2035",
    "addr:street":"Boyce Rd",
    "iso:country":"AU",
    "sg:address":"Shop 3, 112- 114 Boyce Rd",
    "sg:city":"Maroubra",
    "sg:classifiers":[
        {
            "category":"Health Services",
            "subcategory":"Dentist",
            "type":"Services"
        }
    ],
    "sg:phone":"+61 2 8300 1753",
    "sg:postcode":"2035",
    "sg:province":"NSW",
    "wof:name":"Mann Mark Dr",
    "wof:placetype":"venue"
},
  "geometry": {"coordinates":[151.238555908,-33.9398078918],"type":"Point"}
}