{
  "type": "Feature",
  "properties": {
    "iso:country":"AU",
    "sg:address":"Shop 1 & 2, 8 Piper Drv",
    "sg:city":"Ballina",
    "sg:classifiers":[
        {
            "category":"Retail",
            "subcategory":"Repair Shop",
            "type":"Services"
        }
    ],
    "sg:phone":"+61 2 6686 5453",
    "sg:postcode":"2478",
    "sg:province":"NSW",
    "sg:tags":[
        "machine",
        "repairs",
        "part",
        "dryer",
        "washing"
    ],
    "wof:name":"Ballina Appliance Repair Centre",
    "wof:placetype":"venue"
},
  "geometry": {"coordinates":[153.557296753,-28.847858429],"type":"Point"}
}