{
  "type": "Feature",
  "properties": {
    "addr:full":"23 Coachwood Drv Warabrook NSW 2304",
    "addr:housenumber":"23",
    "addr:postcode":"2304",
    "addr:street":"Coachwood Drv",
    "iso:country":"AU",
    "sg:address":"23 Coachwood Drv",
    "sg:city":"Warabrook",
    "sg:classifiers":[
        {
            "category":"Professional",
            "subcategory":"Engineering",
            "type":"Services"
        }
    ],
    "sg:phone":"+61 2 4967 5744",
    "sg:postcode":"2304",
    "sg:province":"NSW",
    "sg:tags":[
        "consulting",
        "engineer"
    ],
    "wof:name":"Fred Gardner Services Pty Ltd",
    "wof:placetype":"venue"
},
  "geometry": {"coordinates":[151.713287353,-32.8850364685],"type":"Point"}
}