{
  "type": "Feature",
  "properties": {
    "addr:full":"Old North Rd Clare SA 5453",
    "addr:postcode":"5453",
    "addr:street":"North Rd",
    "iso:country":"AU",
    "sg:address":"Old North Rd",
    "sg:city":"Clare",
    "sg:classifiers":[
        {
            "category":"Retail",
            "subcategory":"Auto Repair",
            "type":"Services"
        }
    ],
    "sg:phone":"+61 8 8842 3188",
    "sg:postcode":"5453",
    "sg:province":"SA",
    "sg:tags":[
        "repairer",
        "motor",
        "engineer"
    ],
    "wof:name":"Petes Tyre Centre",
    "wof:placetype":"venue"
},
  "geometry": {"coordinates":[138.611954,-33.832649],"type":"Point"}
}