{
  "type": "Feature",
  "properties": {
    "addr:full":"46 King St Dundas Valley NSW 2117",
    "addr:housenumber":"46",
    "addr:postcode":"2117",
    "addr:street":"King St",
    "iso:country":"AU",
    "sg:address":"46 King St",
    "sg:city":"Dundas Valley",
    "sg:classifiers":[
        {
            "category":"Building & Trades",
            "subcategory":"Plumbing",
            "type":"Services"
        }
    ],
    "sg:phone":"+61 2 9874 9766",
    "sg:postcode":"2117",
    "sg:province":"NSW",
    "sg:tags":[
        "plumber",
        "gasfitters"
    ],
    "wof:name":"B J Howard Plumbing",
    "wof:placetype":"venue"
},
  "geometry": {"coordinates":[151.059249878,-33.7937736511],"type":"Point"}
}