{
  "type": "Feature",
  "properties": {
    "iso:country":"AU",
    "sg:address":"11 Primula Pl",
    "sg:city":"Port Macquarie",
    "sg:classifiers":[
        {
            "category":"Building & Trades",
            "subcategory":"Construction",
            "type":"Services"
        }
    ],
    "sg:phone":"+61 2 6582 0585",
    "sg:postcode":"2444",
    "sg:province":"NSW",
    "sg:tags":[
        "contractor"
    ],
    "wof:name":"Lawrence P & K",
    "wof:placetype":"venue"
},
  "geometry": {"coordinates":[152.923676,-31.465376],"type":"Point"}
}