{
  "type": "Feature",
  "properties": {
    "addr:full":"Rosemount Rd Denman NSW 2328",
    "addr:postcode":"2328",
    "addr:street":"Rosemount Rd",
    "iso:country":"AU",
    "sg:address":"Rosemount Rd",
    "sg:city":"Denman",
    "sg:classifiers":[
        {
            "category":"Food & Beverages",
            "subcategory":"Liquor & Beverages",
            "type":"Retail Goods"
        }
    ],
    "sg:phone":"+61 2 6549 6400",
    "sg:postcode":"2328",
    "sg:province":"NSW",
    "sg:tags":[
        "merchant",
        "spirit",
        "wine"
    ],
    "wof:name":"Rosemount Estate Cellar Door Sales",
    "wof:placetype":"venue"
},
  "geometry": {"coordinates":[150.682861328,-32.3939971924],"type":"Point"}
}