{
  "type": "Feature",
  "properties": {
    "addr:full":"39 Bellevue St Blacktown NSW 2148",
    "addr:housenumber":"39",
    "addr:postcode":"2148",
    "addr:street":"Bellevue St",
    "iso:country":"AU",
    "sg:address":"39 Bellevue St",
    "sg:city":"Blacktown",
    "sg:phone":"+61 2 9622 9132",
    "sg:postcode":"2148",
    "sg:province":"NSW",
    "wof:name":"ultrafilter Pty Ltd",
    "wof:placetype":"venue"
},
  "geometry": {"coordinates":[150.892654419,-33.7792053223],"type":"Point"}
}