{
  "type": "Feature",
  "properties": {
    "iso:country":"AU",
    "sg:address":"PO Box 610",
    "sg:city":"Hurstbridge",
    "sg:classifiers":[
        {
            "category":"Manufacturing",
            "subcategory":"Textiles",
            "type":"Manufacturing & Wholesale Goods"
        }
    ],
    "sg:phone":"+61 3 9714 8428",
    "sg:postcode":"3099",
    "sg:province":"VIC",
    "sg:tags":[
        "agent"
    ],
    "wof:name":"Fabrotex Pty Ltd",
    "wof:placetype":"venue"
},
  "geometry": {"coordinates":[145.193817139,-37.6382904053],"type":"Point"}
}