{
  "type": "Feature",
  "properties": {
    "addr:full":"Shop 6/ 120 Burgundy St Heidelberg VIC 3084",
    "addr:housenumber":"shop 6 / 120",
    "addr:postcode":"3084",
    "addr:street":"Burgundy St",
    "iso:country":"AU",
    "sg:address":"Shop 6/ 120 Burgundy St",
    "sg:city":"Heidelberg",
    "sg:classifiers":[
        {
            "category":"Utilities",
            "subcategory":"Electric",
            "type":"Services"
        }
    ],
    "sg:phone":"+61 412 722 447",
    "sg:postcode":"3084",
    "sg:province":"VIC",
    "sg:tags":[
        "element"
    ],
    "wof:name":"Michaels Electrical Services",
    "wof:placetype":"venue"
},
  "geometry": {"coordinates":[145.06614685100001,-37.7560386658],"type":"Point"}
}