{
  "type": "Feature",
  "properties": {
    "addr:full":"Cnr Gladstone Rd & Grevillea St Biloela QLD 4715",
    "addr:postcode":"4715",
    "addr:street":"Cnr Gladstone Rd & Grevillea St",
    "iso:country":"AU",
    "sg:address":"Cnr Gladstone Rd & Grevillea St",
    "sg:city":"Biloela",
    "sg:classifiers":[
        {
            "category":"Health Services",
            "subcategory":"Doctor",
            "type":"Services"
        }
    ],
    "sg:phone":"+61 7 4992 2166",
    "sg:postcode":"4715",
    "sg:province":"QLD",
    "sg:tags":[
        "medical",
        "practitioner"
    ],
    "wof:name":"Griffith-Oxley Clinic",
    "wof:placetype":"venue"
},
  "geometry": {"coordinates":[150.51252746599999,-24.4025764465],"type":"Point"}
}