{
  "type": "Feature",
  "properties": {
    "addr:full":"302- 308 Pacific Hwy Hornsby NSW 2077",
    "addr:housenumber":"302 308",
    "addr:postcode":"2077",
    "addr:street":"Pacific Hwy",
    "iso:country":"AU",
    "sg:address":"302- 308 Pacific Hwy",
    "sg:city":"Hornsby",
    "sg:classifiers":[
        {
            "category":"Building & Trades",
            "subcategory":"Locksmith",
            "type":"Services"
        }
    ],
    "sg:phone":"+61 2 9477 7999",
    "sg:postcode":"2077",
    "sg:province":"NSW",
    "sg:tags":[
        "lock"
    ],
    "wof:name":"Hornsby & District Alarms",
    "wof:placetype":"venue"
},
  "geometry": {"coordinates":[151.09776306099999,-33.6992378235],"type":"Point"}
}