{
  "type": "Feature",
  "properties": {
    "iso:country":"AU",
    "sg:address":"49 Langie Draha St",
    "sg:city":"Bamaga",
    "sg:classifiers":[
        {
            "category":"Food & Beverages",
            "subcategory":"Groceries & Convenience Stores",
            "type":"Retail Goods"
        }
    ],
    "sg:phone":"+61 7 4069 3013",
    "sg:postcode":"4876",
    "sg:province":"QLD",
    "wof:name":"New Mapoon General Store & Take Away",
    "wof:placetype":"venue"
},
  "geometry": {"coordinates":[142.38938903799999,-10.8705301285],"type":"Point"}
}