{
  "type": "Feature",
  "properties": {
    "iso:country":"AU",
    "sg:address":"92 Commercial St",
    "sg:city":"West Mt Gambier",
    "sg:classifiers":[
        {
            "category":"Autos & Motor Vehicles",
            "subcategory":"Auto Supplies",
            "type":"Retail Goods"
        }
    ],
    "sg:phone":"+61 8 8724 9111",
    "sg:postcode":"5290",
    "sg:province":"SA",
    "sg:tags":[
        "automotive",
        "stereo",
        "radio"
    ],
    "wof:name":"Autobarn Pty Ltd",
    "wof:placetype":"venue"
},
  "geometry": {"coordinates":[140.775574,-37.826603],"type":"Point"}
}