{
  "type": "Feature",
  "properties": {
    "iso:country":"AU",
    "sg:address":"PO Box 233",
    "sg:city":"Kingston",
    "sg:classifiers":[
        {
            "category":"Professional",
            "subcategory":"Computer Services",
            "type":"Services"
        }
    ],
    "sg:phone":"+61 3 6229 1169",
    "sg:postcode":"7051",
    "sg:province":"TAS",
    "sg:tags":[
        "consultant",
        "system"
    ],
    "wof:name":"Eclipse Open Systems Pty Ltd",
    "wof:placetype":"venue"
},
  "geometry": {"coordinates":[147.308395,-42.97686],"type":"Point"}
}