{
  "type": "Feature",
  "properties": {
    "addr:full":"Hemming St Parafield Gardens SA 5107",
    "addr:postcode":"5107",
    "addr:street":"Hemming St",
    "iso:country":"AU",
    "sg:address":"Hemming St",
    "sg:city":"Parafield Gardens",
    "sg:classifiers":[
        {
            "category":"Social Services",
            "subcategory":"Child Care",
            "type":"Services"
        }
    ],
    "sg:phone":"+61 8 8250 7010",
    "sg:postcode":"5107",
    "sg:province":"SA",
    "wof:name":"Pines Community Child Care",
    "wof:placetype":"venue"
},
  "geometry": {"coordinates":[138.608612061,-34.7744903564],"type":"Point"}
}