{
  "type": "Feature",
  "properties": {
    "addr:full":"St Vincents Medical Specialist Centre 20 Dalley St Lismore NSW 2480",
    "addr:housenumber":"20",
    "addr:postcode":"2480",
    "addr:street":"St;Dalley St",
    "iso:country":"AU",
    "sg:address":"St Vincents Medical Specialist Centre 20 Dalley St",
    "sg:city":"Lismore",
    "sg:classifiers":[
        {
            "category":"Health Services",
            "subcategory":"Doctor",
            "type":"Services"
        }
    ],
    "sg:phone":"+61 2 6621 8277",
    "sg:postcode":"2480",
    "sg:province":"NSW",
    "sg:tags":[
        "medical",
        "practitioner"
    ],
    "wof:name":"Simon Robert Dr",
    "wof:placetype":"venue"
},
  "geometry": {"coordinates":[153.28619384800001,-28.8206577301],"type":"Point"}
}