{
  "type": "Feature",
  "properties": {
    "iso:country":"AU",
    "sg:address":"198 Grange Rd",
    "sg:city":"Flinders Park",
    "sg:classifiers":[
        {
            "category":"Building & Trades",
            "subcategory":"Construction",
            "type":"Services"
        }
    ],
    "sg:phone":"+61 8 8351 9444",
    "sg:postcode":"5025",
    "sg:province":"SA",
    "sg:tags":[
        "contractor"
    ],
    "wof:name":"Bella Build & Design",
    "wof:placetype":"venue"
},
  "geometry": {"coordinates":[138.54559326200001,-34.9049339294],"type":"Point"}
}