{
  "type": "Feature",
  "properties": {
    "addr:full":"12 Stacey St Bankstown NSW 2200",
    "addr:housenumber":"12",
    "addr:postcode":"2200",
    "addr:street":"Stacey St",
    "iso:country":"AU",
    "sg:address":"12 Stacey St",
    "sg:city":"Bankstown",
    "sg:classifiers":[
        {
            "category":"Wholesale",
            "subcategory":"Apparel",
            "type":"Manufacturing & Wholesale Goods"
        }
    ],
    "sg:phone":"+61 2 9790 8236",
    "sg:postcode":"2200",
    "sg:province":"NSW",
    "sg:tags":[
        "wholesaler",
        "mfrs",
        "menswear"
    ],
    "wof:name":"Sphinx Australia Pty Ltd",
    "wof:placetype":"venue"
},
  "geometry": {"coordinates":[151.040131,-33.906685],"type":"Point"}
}