{
  "type": "Feature",
  "properties": {
    "iso:country":"AU",
    "sg:address":"7 Lagoon Rd",
    "sg:city":"Waterford",
    "sg:classifiers":[
        {
            "category":"Farming",
            "subcategory":"Livestock Farm",
            "type":"Manufacturing & Wholesale Goods"
        }
    ],
    "sg:phone":"+61 7 3200 5167",
    "sg:postcode":"4133",
    "sg:province":"QLD",
    "sg:tags":[
        "breeder",
        "horse",
        "stud"
    ],
    "wof:name":"Talika Arab Stud",
    "wof:placetype":"venue"
},
  "geometry": {"coordinates":[153.13302612300001,-27.6982479095],"type":"Point"}
}