{
  "type": "Feature",
  "properties": {
    "addr:full":"8 Rigby Mews Rowville VIC 3178",
    "addr:housenumber":"8",
    "addr:postcode":"3178",
    "addr:street":"Rigby Mews",
    "iso:country":"AU",
    "sg:address":"8 Rigby Mews",
    "sg:city":"Rowville",
    "sg:classifiers":[
        {
            "category":"Real Estate",
            "subcategory":"Real Estate Services",
            "type":"Services"
        }
    ],
    "sg:phone":"+61 3 9764 5575",
    "sg:postcode":"3178",
    "sg:province":"VIC",
    "sg:tags":[
        "consultant",
        "property"
    ],
    "wof:name":"Daly International Pty Ltd",
    "wof:placetype":"venue"
},
  "geometry": {"coordinates":[145.232498169,-37.9251823425],"type":"Point"}
}