{
  "type": "Feature",
  "properties": {
    "addr:full":"30 Almurta Rd Bentleigh East VIC 3165",
    "addr:housenumber":"30",
    "addr:postcode":"3165",
    "addr:street":"Almurta Rd",
    "iso:country":"AU",
    "sg:address":"30 Almurta Rd",
    "sg:city":"Bentleigh East",
    "sg:classifiers":[
        {
            "category":"Professional",
            "subcategory":"Accounting & Tax Preparation",
            "type":"Services"
        }
    ],
    "sg:phone":"+61 419 391 109",
    "sg:postcode":"3165",
    "sg:province":"VIC",
    "sg:tags":[
        "bookkeeping"
    ],
    "wof:name":"G & D Business Services",
    "wof:placetype":"venue"
},
  "geometry": {"coordinates":[145.06652832,-37.9241294861],"type":"Point"}
}