{
  "type": "Feature",
  "properties": {
    "addr:full":"151 Pinjarra Rd Mandurah WA 6210",
    "addr:housenumber":"151",
    "addr:postcode":"6210",
    "addr:street":"Pinjarra Rd",
    "iso:country":"AU",
    "sg:address":"151 Pinjarra Rd",
    "sg:city":"Mandurah",
    "sg:classifiers":[
        {
            "category":"Banks & Credit Unions",
            "subcategory":"Investment Brokerage",
            "type":"Services"
        }
    ],
    "sg:phone":"+61 8 9535 5211",
    "sg:postcode":"6210",
    "sg:province":"WA",
    "wof:name":"Mandurah Murray Investment Services",
    "wof:placetype":"venue"
},
  "geometry": {"coordinates":[115.773163,-32.54723],"type":"Point"}
}