{
  "type": "Feature",
  "properties": {
    "addr:full":"99 Sunbury St Buccan QLD 4207",
    "addr:housenumber":"99",
    "addr:postcode":"4207",
    "addr:street":"Sunbury St",
    "iso:country":"AU",
    "sg:address":"99 Sunbury St",
    "sg:city":"Buccan",
    "sg:classifiers":[
        {
            "category":"Manufacturing",
            "subcategory":"Metals",
            "type":"Manufacturing & Wholesale Goods"
        }
    ],
    "sg:phone":"+61 412 876 914",
    "sg:postcode":"4207",
    "sg:province":"QLD",
    "sg:tags":[
        "steel",
        "fabricator",
        "mfrs"
    ],
    "wof:name":"Beckers Fabrications Pty Ltd",
    "wof:placetype":"venue"
},
  "geometry": {"coordinates":[153.12496948200001,-27.7235946655],"type":"Point"}
}