{
  "type": "Feature",
  "properties": {
    "addr:full":"51 Country Rd Cannonvale QLD 4802",
    "addr:housenumber":"51",
    "addr:postcode":"4802",
    "addr:street":"Country Rd",
    "iso:country":"AU",
    "sg:address":"51 Country Rd",
    "sg:city":"Cannonvale",
    "sg:classifiers":[
        {
            "category":"Home & Garden",
            "subcategory":"Building Materials",
            "type":"Retail Goods"
        }
    ],
    "sg:phone":"+61 7 4946 5226",
    "sg:postcode":"4802",
    "sg:province":"QLD",
    "sg:tags":[
        "lawn",
        "cutting",
        "maintenance"
    ],
    "wof:name":"Lawnbusters",
    "wof:placetype":"venue"
},
  "geometry": {"coordinates":[148.68765258799999,-20.2869606018],"type":"Point"}
}