{
  "type": "Feature",
  "properties": {
    "addr:full":"2 Undula Pl Belrose NSW 2085",
    "addr:housenumber":"2",
    "addr:postcode":"2085",
    "addr:street":"Undula Pl",
    "iso:country":"AU",
    "sg:address":"2 Undula Pl",
    "sg:city":"Belrose",
    "sg:classifiers":[
        {
            "category":"Shopping",
            "subcategory":"News",
            "type":"Retail Goods"
        }
    ],
    "sg:phone":"+61 2 9452 1708",
    "sg:postcode":"2085",
    "sg:province":"NSW",
    "sg:tags":[
        "magazine",
        "periodical"
    ],
    "wof:name":"Droncross Pty Ltd",
    "wof:placetype":"venue"
},
  "geometry": {"coordinates":[151.20933532699999,-33.7313766479],"type":"Point"}
}