{
  "type": "Feature",
  "properties": {
    "addr:full":"94 Lawlers La Merriwa NSW 2329",
    "addr:housenumber":"94",
    "addr:postcode":"2329",
    "addr:street":"Lawlers La Merriwa",
    "iso:country":"AU",
    "sg:address":"94 Lawlers La",
    "sg:city":"Merriwa",
    "sg:classifiers":[
        {
            "category":"Manufacturing",
            "subcategory":"Tools & Machinery",
            "type":"Manufacturing & Wholesale Goods"
        }
    ],
    "sg:phone":"+61 2 6548 3080",
    "sg:postcode":"2329",
    "sg:province":"NSW",
    "sg:tags":[
        "earth",
        "excavating",
        "moving",
        "equipment"
    ],
    "wof:name":"Jamin Enterprises Bobcat Hire",
    "wof:placetype":"venue"
},
  "geometry": {"coordinates":[150.35670471200001,-32.1395492554],"type":"Point"}
}