{
  "type": "Feature",
  "properties": {
    "iso:country":"AU",
    "sg:address":"1 North Ave",
    "sg:city":"Yenda",
    "sg:classifiers":[
        {
            "category":"Wholesale",
            "subcategory":"Farm Supplies",
            "type":"Manufacturing & Wholesale Goods"
        }
    ],
    "sg:phone":"+61 2 6968 1338",
    "sg:postcode":"2681",
    "sg:province":"NSW",
    "sg:tags":[
        "feed",
        "supplement",
        "stock"
    ],
    "wof:name":"Nu-Marc Industries Pty Ltd",
    "wof:placetype":"venue"
},
  "geometry": {"coordinates":[146.195709,-34.248852],"type":"Point"}
}