{
  "type": "Feature",
  "properties": {
    "iso:country":"AU",
    "sg:address":"15 Christensen Rd",
    "sg:city":"Stapylton",
    "sg:classifiers":[
        {
            "category":"Manufacturing",
            "subcategory":"Tools & Machinery",
            "type":"Manufacturing & Wholesale Goods"
        }
    ],
    "sg:phone":"+61 7 3807 0211",
    "sg:postcode":"4207",
    "sg:province":"QLD",
    "sg:tags":[
        "abrasive"
    ],
    "wof:name":"Abrasive Services",
    "wof:placetype":"venue"
},
  "geometry": {"coordinates":[153.23077392600001,-27.7358264923],"type":"Point"}
}