{
  "type": "Feature",
  "properties": {
    "iso:country":"AU",
    "sg:address":"11 Nimitz Rd",
    "sg:city":"Elizabeth East",
    "sg:classifiers":[
        {
            "category":"Arena",
            "subcategory":"Sports Club",
            "type":"Entertainment"
        }
    ],
    "sg:phone":"+61 8 8287 3668",
    "sg:postcode":"5112",
    "sg:province":"SA",
    "sg:tags":[
        "organisation",
        "sporting"
    ],
    "wof:name":"Elizabeth Netball Umpires Association",
    "wof:placetype":"venue"
},
  "geometry": {"coordinates":[138.67520141599999,-34.7246665955],"type":"Point"}
}