{
  "type": "Feature",
  "properties": {
    "iso:country":"AU",
    "sg:address":"Ripon St",
    "sg:city":"Young",
    "sg:classifiers":[
        {
            "category":"Education",
            "subcategory":"School",
            "type":"Public Place"
        }
    ],
    "sg:phone":"+61 2 6382 1486",
    "sg:postcode":"2594",
    "sg:province":"NSW",
    "sg:tags":[
        "co-educational"
    ],
    "wof:name":"Hennessy Catholic College",
    "wof:placetype":"venue"
},
  "geometry": {"coordinates":[148.29232788100001,-34.3152427673],"type":"Point"}
}