{
  "type": "Feature",
  "properties": {
    "iso:country":"AU",
    "sg:address":"150 Walcott St",
    "sg:city":"Mt Lawley",
    "sg:classifiers":[
        {
            "category":"Health Services",
            "subcategory":"Health Practitioner",
            "type":"Services"
        }
    ],
    "sg:phone":"+61 8 9371 2569",
    "sg:postcode":"6050",
    "sg:province":"WA",
    "sg:tags":[
        "psychologist"
    ],
    "wof:name":"Mt Lawley Family Psychology Centre",
    "wof:placetype":"venue"
},
  "geometry": {"coordinates":[115.868179321,-31.9308452606],"type":"Point"}
}