{
  "type": "Feature",
  "properties": {
    "addr:full":"13 Yvonne Crt Maiden Gully VIC 3551",
    "addr:housenumber":"13",
    "addr:postcode":"3551",
    "addr:street":"Yvonne Crt",
    "iso:country":"AU",
    "sg:address":"13 Yvonne Crt",
    "sg:city":"Maiden Gully",
    "sg:classifiers":[
        {
            "category":"Social Services",
            "subcategory":"Child Care",
            "type":"Services"
        }
    ],
    "sg:phone":"+61 3 5449 6914",
    "sg:postcode":"3551",
    "sg:province":"VIC",
    "sg:tags":[
        "shearer"
    ],
    "wof:name":"Lionel Baber",
    "wof:placetype":"venue"
},
  "geometry": {"coordinates":[144.195770264,-36.7494468689],"type":"Point"}
}