{
  "type": "Feature",
  "properties": {
    "addr:full":"3 Hillary Pde Matraville NSW 2036",
    "addr:housenumber":"3",
    "addr:postcode":"2036",
    "addr:street":"Hillary Pde",
    "iso:country":"AU",
    "sg:address":"3 Hillary Pde",
    "sg:city":"Matraville",
    "sg:classifiers":[
        {
            "category":"Building & Trades",
            "subcategory":"Equipment Rental",
            "type":"Services"
        }
    ],
    "sg:phone":"+61 2 9661 5920",
    "sg:postcode":"2036",
    "sg:province":"NSW",
    "sg:tags":[
        "party",
        "hire"
    ],
    "wof:name":"Floorex Promotions",
    "wof:placetype":"venue"
},
  "geometry": {"coordinates":[151.24281310999999,-33.961101532],"type":"Point"}
}