{
  "type": "Feature",
  "properties": {
    "iso:country":"AU",
    "sg:address":"2/ 20 Somer St",
    "sg:city":"Hyde Park",
    "sg:classifiers":[
        {
            "category":"Shopping",
            "subcategory":"Computers & Home Electronics",
            "type":"Retail Goods"
        }
    ],
    "sg:phone":"+61 7 4771 4211",
    "sg:postcode":"4812",
    "sg:province":"QLD",
    "sg:tags":[
        "equipment",
        "part",
        "electronic"
    ],
    "wof:name":"Solex",
    "wof:placetype":"venue"
},
  "geometry": {"coordinates":[146.800201,-19.273027],"type":"Point"}
}