{
  "type": "Feature",
  "properties": {
    "addr:full":"PO Box 157 Modbury North SA 5092",
    "addr:postcode":"5092",
    "iso:country":"AU",
    "sg:address":"PO Box 157",
    "sg:city":"Modbury North",
    "sg:classifiers":[
        {
            "category":"Sports & Exercise",
            "subcategory":"Race Track",
            "type":"Entertainment"
        }
    ],
    "sg:phone":"+61 1300 765 226",
    "sg:postcode":"5092",
    "sg:province":"SA",
    "sg:tags":[
        "access",
        "cover",
        "grating"
    ],
    "wof:name":"ACO Polycrete Pty Ltd",
    "wof:placetype":"venue"
},
  "geometry": {"coordinates":[138.68907165499999,-34.8213615417],"type":"Point"}
}