{
  "type": "Feature",
  "properties": {
    "iso:country":"AU",
    "sg:address":"217 Clarendon St",
    "sg:city":"South Melbourne",
    "sg:classifiers":[
        {
            "category":"Personal",
            "subcategory":"Beauty Salon",
            "type":"Services"
        }
    ],
    "sg:phone":"+61 3 9682 0400",
    "sg:postcode":"3205",
    "sg:province":"VIC",
    "sg:tags":[
        "hairdresser"
    ],
    "wof:name":"Zucci Hairdressing",
    "wof:placetype":"venue"
},
  "geometry": {"coordinates":[144.959824,-37.83102],"type":"Point"}
}