{
  "type": "Feature",
  "properties": {
    "addr:full":"3 Devon Crt Casino NSW 2470",
    "addr:housenumber":"3",
    "addr:postcode":"2470",
    "addr:street":"Devon Crt",
    "iso:country":"AU",
    "sg:address":"3 Devon Crt",
    "sg:city":"Casino",
    "sg:classifiers":[
        {
            "category":"Utilities",
            "subcategory":"Water",
            "type":"Services"
        }
    ],
    "sg:phone":"+61 2 6662 2510",
    "sg:postcode":"2470",
    "sg:province":"NSW",
    "sg:tags":[
        "cartage"
    ],
    "wof:name":"Richmond Valley Water Supplies",
    "wof:placetype":"venue"
},
  "geometry": {"coordinates":[153.01373290999999,-28.8642883301],"type":"Point"}
}