{
  "type": "Feature",
  "properties": {
    "addr:full":"61 Rowe Ave Northfield SA 5085",
    "addr:housenumber":"61",
    "addr:postcode":"5085",
    "addr:street":"Rowe Ave",
    "iso:country":"AU",
    "sg:address":"61 Rowe Ave",
    "sg:city":"Northfield",
    "sg:classifiers":[
        {
            "category":"Home & Garden",
            "subcategory":"Carpets & Floor Coverings",
            "type":"Retail Goods"
        }
    ],
    "sg:phone":"+61 421 819 266",
    "sg:postcode":"5085",
    "sg:province":"SA",
    "sg:tags":[
        "tile",
        "wall",
        "layer"
    ],
    "wof:name":"Emerald Tiling",
    "wof:placetype":"venue"
},
  "geometry": {"coordinates":[138.62240600600001,-34.8493232727],"type":"Point"}
}