{
  "type": "Feature",
  "properties": {
    "iso:country":"AU",
    "sg:address":"5/ 145 Stirling Hwy",
    "sg:city":"Nedlands",
    "sg:classifiers":[
        {
            "category":"Shopping",
            "subcategory":"Crafts & Fabrics",
            "type":"Retail Goods"
        }
    ],
    "sg:phone":"+61 1300 361 836",
    "sg:postcode":"6009",
    "sg:province":"WA",
    "sg:tags":[
        "upholstering",
        "supply"
    ],
    "wof:name":"Wortley Group Pty Ltd",
    "wof:placetype":"venue"
},
  "geometry": {"coordinates":[115.815811,-31.976608],"type":"Point"}
}