{
  "type": "Feature",
  "properties": {
    "iso:country":"AU",
    "sg:address":"Shop 13, Ivanhoe Plaza, 4 Livingstone St",
    "sg:city":"Ivanhoe",
    "sg:classifiers":[
        {
            "category":"Travel",
            "subcategory":"Travel Agent",
            "type":"Entertainment"
        }
    ],
    "sg:phone":"+61 3 9499 7711",
    "sg:postcode":"3079",
    "sg:province":"VIC",
    "sg:tags":[
        "consultant"
    ],
    "wof:name":"Jetset Travel",
    "wof:placetype":"venue"
},
  "geometry": {"coordinates":[145.042694092,-37.7679901123],"type":"Point"}
}