{
  "type": "Feature",
  "properties": {
    "iso:country":"AU",
    "sg:address":"5 South Pacific Ave",
    "sg:city":"Mt Pritchard",
    "sg:classifiers":[
        {
            "category":"Professional",
            "subcategory":"Art Services",
            "type":"Services"
        }
    ],
    "sg:phone":"+61 2 9602 7797",
    "sg:postcode":"2170",
    "sg:province":"NSW",
    "sg:tags":[
        "decorator",
        "painter"
    ],
    "wof:name":"Ross R & J Pty Ltd",
    "wof:placetype":"venue"
},
  "geometry": {"coordinates":[150.905319214,-33.9115867615],"type":"Point"}
}