{
  "type": "Feature",
  "properties": {
    "addr:full":"Cnr Samuel St & Curtis Rd Smithfield SA 5114",
    "addr:postcode":"5114",
    "addr:street":"Cnr Samuel St & Curtis Rd",
    "iso:country":"AU",
    "sg:address":"Cnr Samuel St & Curtis Rd",
    "sg:city":"Smithfield",
    "sg:classifiers":[
        {
            "category":"Farming",
            "subcategory":"Farm & Veterinary Services",
            "type":"Manufacturing & Wholesale Goods"
        }
    ],
    "sg:phone":"+61 8 8284 1311",
    "sg:postcode":"5114",
    "sg:province":"SA",
    "sg:tags":[
        "irrigation",
        "reticulation",
        "system"
    ],
    "wof:name":"Acacia Garden Supplies",
    "wof:placetype":"venue"
},
  "geometry": {"coordinates":[138.68516540499999,-34.6798820496],"type":"Point"}
}