{
  "type": "Feature",
  "properties": {
    "addr:full":"1/ 8 Ereton Drv Labrador QLD 4215",
    "addr:housenumber":"/ 8",
    "addr:postcode":"4215",
    "addr:street":"Ereton Drv",
    "iso:country":"AU",
    "sg:address":"1/ 8 Ereton Drv",
    "sg:city":"Labrador",
    "sg:classifiers":[
        {
            "category":"Home & Garden",
            "subcategory":"Furniture",
            "type":"Retail Goods"
        }
    ],
    "sg:phone":"+61 7 5537 5999",
    "sg:postcode":"4215",
    "sg:province":"QLD",
    "sg:tags":[
        "business"
    ],
    "wof:name":"Precision",
    "wof:placetype":"venue"
},
  "geometry": {"coordinates":[153.38624572800001,-27.9345798492],"type":"Point"}
}