{
  "type": "Feature",
  "properties": {
    "iso:country":"AU",
    "sg:address":"unit 1/ 73 Dobney Ave",
    "sg:city":"Wagga Wagga",
    "sg:classifiers":[
        {
            "category":"Retail",
            "subcategory":"Auto Repair",
            "type":"Services"
        }
    ],
    "sg:phone":"+61 2 6925 3749",
    "sg:postcode":"2650",
    "sg:province":"NSW",
    "sg:tags":[
        "repairer",
        "motor",
        "engineer"
    ],
    "wof:name":"Precision Auto Centre Wagga Wagga",
    "wof:placetype":"venue"
},
  "geometry": {"coordinates":[147.34104919399999,-35.1242179871],"type":"Point"}
}