{
  "type": "Feature",
  "properties": {
    "addr:full":"11/ 22 Reliance Drv Tuggerah NSW 2259",
    "addr:housenumber":"11 / 22",
    "addr:postcode":"2259",
    "addr:street":"Reliance Drv",
    "iso:country":"AU",
    "sg:address":"11/ 22 Reliance Drv",
    "sg:city":"Tuggerah",
    "sg:classifiers":[
        {
            "category":"Shopping",
            "subcategory":"Beauty & Cosmetics",
            "type":"Retail Goods"
        }
    ],
    "sg:phone":"+61 2 4351 7122",
    "sg:postcode":"2259",
    "sg:province":"NSW",
    "sg:tags":[
        "equipment",
        "salon",
        "supply"
    ],
    "wof:name":"Vivorah Pty Ltd",
    "wof:placetype":"venue"
},
  "geometry": {"coordinates":[151.423995972,-33.3202171326],"type":"Point"}
}