{
  "type": "Feature",
  "properties": {
    "addr:full":"11 Fisher St Belmont WA 6104",
    "addr:housenumber":"11",
    "addr:postcode":"6104",
    "addr:street":"Fisher St",
    "iso:country":"AU",
    "sg:address":"11 Fisher St",
    "sg:city":"Belmont",
    "sg:classifiers":[
        {
            "category":"Autos & Motor Vehicles",
            "subcategory":"Auto Supplies",
            "type":"Retail Goods"
        }
    ],
    "sg:phone":"+61 13 21 91",
    "sg:postcode":"6104",
    "sg:province":"WA",
    "sg:tags":[
        "wheel",
        "automotive",
        "rim"
    ],
    "wof:name":"Tyrepower",
    "wof:placetype":"venue"
},
  "geometry": {"coordinates":[115.93347930900001,-31.9564228058],"type":"Point"}
}