{
  "type": "Feature",
  "properties": {
    "iso:country":"AU",
    "sg:address":"41a License Rd",
    "sg:city":"Diggers Rest",
    "sg:classifiers":[
        {
            "category":"Professional",
            "subcategory":"Art Services",
            "type":"Services"
        }
    ],
    "sg:phone":"+61 414 490 814",
    "sg:postcode":"3427",
    "sg:province":"VIC",
    "sg:tags":[
        "artist"
    ],
    "wof:name":"Myst Custom Art",
    "wof:placetype":"venue"
},
  "geometry": {"coordinates":[144.71241760300001,-37.6249542236],"type":"Point"}
}