{
  "type": "Feature",
  "properties": {
    "addr:full":"43 Gordon St Milton NSW 2538",
    "addr:housenumber":"43",
    "addr:postcode":"2538",
    "addr:street":"Gordon St",
    "iso:country":"AU",
    "sg:address":"43 Gordon St",
    "sg:city":"Milton",
    "sg:classifiers":[
        {
            "category":"Utilities",
            "subcategory":"Electric",
            "type":"Services"
        }
    ],
    "sg:phone":"+61 2 4455 3872",
    "sg:postcode":"2538",
    "sg:province":"NSW",
    "sg:tags":[
        "electrical",
        "contractor"
    ],
    "wof:name":"Rooney Steve",
    "wof:placetype":"venue"
},
  "geometry": {"coordinates":[150.440109253,-35.3174057007],"type":"Point"}
}