{
  "type": "Feature",
  "properties": {
    "iso:country":"AU",
    "sg:address":"Cnr Nowland & Station Sts",
    "sg:city":"Quirindi",
    "sg:classifiers":[
        {
            "category":"Manufacturing",
            "subcategory":"Glass & Minerals",
            "type":"Manufacturing & Wholesale Goods"
        }
    ],
    "sg:phone":"+61 2 6746 3555",
    "sg:postcode":"2343",
    "sg:province":"NSW",
    "sg:tags":[
        "earth"
    ],
    "wof:name":"Castle Mountain Zeolites",
    "wof:placetype":"venue"
},
  "geometry": {"coordinates":[150.67579650900001,-31.5191898346],"type":"Point"}
}