{
  "type": "Feature",
  "properties": {
    "iso:country":"AU",
    "sg:address":"282 Burwood Rd",
    "sg:city":"Burwood",
    "sg:classifiers":[
        {
            "category":"Health Services",
            "subcategory":"Doctor",
            "type":"Services"
        }
    ],
    "sg:phone":"+61 500 880 083",
    "sg:postcode":"2134",
    "sg:province":"NSW",
    "sg:tags":[
        "medical",
        "practitioner"
    ],
    "wof:name":"Nghi Phung Dr",
    "wof:placetype":"venue"
},
  "geometry": {"coordinates":[151.10299682600001,-33.8815917969],"type":"Point"}
}