{
  "type": "Feature",
  "properties": {
    "addr:full":"3/ 5 Katoomba St Katoomba NSW 2780",
    "addr:housenumber":"/ 5",
    "addr:postcode":"2780",
    "addr:street":"Katoomba St",
    "iso:country":"AU",
    "sg:address":"3/ 5 Katoomba St",
    "sg:city":"Katoomba",
    "sg:classifiers":[
        {
            "category":"Education",
            "subcategory":"Special Training",
            "type":"Public Place"
        }
    ],
    "sg:phone":"+61 2 4782 9075",
    "sg:postcode":"2780",
    "sg:province":"NSW",
    "sg:tags":[
        "development"
    ],
    "wof:name":"Peak Achievements",
    "wof:placetype":"venue"
},
  "geometry": {"coordinates":[150.31141662600001,-33.7141532898],"type":"Point"}
}