{
  "type": "Feature",
  "properties": {
    "addr:full":"45 Glen Huntly Rd Elwood VIC 3184",
    "addr:housenumber":"45",
    "addr:postcode":"3184",
    "addr:street":"Glen Huntly Rd",
    "iso:country":"AU",
    "sg:address":"45 Glen Huntly Rd",
    "sg:city":"Elwood",
    "sg:classifiers":[
        {
            "category":"Health Services",
            "subcategory":"Health Practitioner",
            "type":"Services"
        }
    ],
    "sg:phone":"+61 3 9531 5256",
    "sg:postcode":"3184",
    "sg:province":"VIC",
    "sg:tags":[
        "osteopath"
    ],
    "wof:name":"Bodyunity Osteopathic Medicine",
    "wof:placetype":"venue"
},
  "geometry": {"coordinates":[144.98153686500001,-37.8819503784],"type":"Point"}
}