{
  "type": "Feature",
  "properties": {
    "addr:full":"43 Barnes Ave Burwood VIC 3125",
    "addr:housenumber":"43",
    "addr:postcode":"3125",
    "addr:street":"Barnes Ave",
    "iso:country":"AU",
    "sg:address":"43 Barnes Ave",
    "sg:city":"Burwood",
    "sg:classifiers":[
        {
            "category":"Health Services",
            "subcategory":"Health Practitioner",
            "type":"Services"
        }
    ],
    "sg:phone":"+61 3 9808 4868",
    "sg:postcode":"3125",
    "sg:province":"VIC",
    "sg:tags":[
        "naturopath"
    ],
    "wof:name":"Margaret Crutch",
    "wof:placetype":"venue"
},
  "geometry": {"coordinates":[145.09817504899999,-37.8574333191],"type":"Point"}
}