{
  "type": "Feature",
  "properties": {
    "addr:full":"352 King St Newtown NSW 2042",
    "addr:housenumber":"352",
    "addr:postcode":"2042",
    "addr:street":"King St",
    "iso:country":"AU",
    "sg:address":"352 King St",
    "sg:city":"Newtown",
    "sg:classifiers":[
        {
            "category":"Manufacturing",
            "subcategory":"Food",
            "type":"Manufacturing & Wholesale Goods"
        }
    ],
    "sg:phone":"+61 418 473 669",
    "sg:postcode":"2042",
    "sg:province":"NSW",
    "sg:tags":[
        "function",
        "catering"
    ],
    "wof:name":"Innovative Cuisine Catering",
    "wof:placetype":"venue"
},
  "geometry": {"coordinates":[151.17811599999999,-33.898273],"type":"Point"}
}