{
  "type": "Feature",
  "properties": {
    "addr:full":"Shp 4 / Wodonga Sports & Leisure Center Wodonga Wes VIC 3690",
    "addr:housenumber":"/ wodonga",
    "addr:postcode":"3690",
    "iso:country":"AU",
    "sg:address":"Shp 4",
    "sg:city":"/ Wodonga Sports & Leisure Center Wodonga Wes",
    "sg:classifiers":[
        {
            "category":"Shopping",
            "subcategory":"Clothing, Apparel, & Fashions",
            "type":"Retail Goods"
        }
    ],
    "sg:phone":"+61 2 6059 2424",
    "sg:postcode":"3690",
    "sg:province":"VIC",
    "sg:tags":[
        "sportswear"
    ],
    "wof:name":"Hoop Tech 24",
    "wof:placetype":"venue"
},
  "geometry": {"coordinates":[146.86509704599999,-36.1267433167],"type":"Point"}
}