{
  "type": "Feature",
  "properties": {
    "iso:country":"AU",
    "sg:address":"29 Guilfoyle St",
    "sg:city":"Yarralumla",
    "sg:classifiers":[
        {
            "category":"Sports & Exercise",
            "subcategory":"Sports Center",
            "type":"Entertainment"
        }
    ],
    "sg:phone":"+61 2 6281 3414",
    "sg:postcode":"2600",
    "sg:province":"ACT",
    "sg:tags":[
        "coach",
        "tennis"
    ],
    "wof:name":"D B Tennis",
    "wof:placetype":"venue"
},
  "geometry": {"coordinates":[149.104644775,-35.3117027283],"type":"Point"}
}