{
  "type": "Feature",
  "properties": {
    "addr:full":"55 Halstead St Hurstville NSW 2220",
    "addr:housenumber":"55",
    "addr:postcode":"2220",
    "addr:street":"Halstead St",
    "iso:country":"AU",
    "sg:address":"55 Halstead St",
    "sg:city":"Hurstville",
    "sg:classifiers":[
        {
            "category":"Manufacturing",
            "subcategory":"Chemicals & Compounds",
            "type":"Manufacturing & Wholesale Goods"
        }
    ],
    "sg:phone":"+61 2 9580 2400",
    "sg:postcode":"2220",
    "sg:province":"NSW",
    "sg:tags":[
        "industrial"
    ],
    "wof:name":"T.R. (Chemicals Aust) Pty Ltd",
    "wof:placetype":"venue"
},
  "geometry": {"coordinates":[151.099075317,-33.9777069092],"type":"Point"}
}