{
  "type": "Feature",
  "properties": {
    "addr:full":"28 Lee St Frankston VIC 3199",
    "addr:housenumber":"28",
    "addr:postcode":"3199",
    "addr:street":"Lee St",
    "iso:country":"AU",
    "sg:address":"28 Lee St",
    "sg:city":"Frankston",
    "sg:classifiers":[
        {
            "category":"Building & Trades",
            "subcategory":"Construction",
            "type":"Services"
        }
    ],
    "sg:phone":"+61 418 378 594",
    "sg:postcode":"3199",
    "sg:province":"VIC",
    "sg:tags":[
        "bitumen",
        "paving",
        "asphalt"
    ],
    "wof:name":"Peninsula Asphalt",
    "wof:placetype":"venue"
},
  "geometry": {"coordinates":[144.974487305,-37.7913398743],"type":"Point"}
}