{
  "type": "Feature",
  "properties": {
    "addr:full":"Timboon Colac Rd Scott's Creek VIC 3267",
    "addr:postcode":"3267",
    "addr:street":"Colac Rd",
    "iso:country":"AU",
    "sg:address":"Timboon Colac Rd",
    "sg:city":"Scott's Creek",
    "sg:classifiers":[
        {
            "category":"Farming",
            "subcategory":"Farm",
            "type":"Manufacturing & Wholesale Goods"
        }
    ],
    "sg:phone":"+61 3 5595 9305",
    "sg:postcode":"3267",
    "sg:province":"VIC",
    "sg:tags":[
        "farmer"
    ],
    "wof:name":"McGlade T A & S A",
    "wof:placetype":"venue"
},
  "geometry": {"coordinates":[143.09242248499999,-38.4529418945],"type":"Point"}
}