{
  "type": "Feature",
  "properties": {
    "addr:full":"68 Effingham St Tarragindi QLD 4121",
    "addr:housenumber":"68",
    "addr:postcode":"4121",
    "addr:street":"Effingham St",
    "iso:country":"AU",
    "sg:address":"68 Effingham St",
    "sg:city":"Tarragindi",
    "sg:classifiers":[
        {
            "category":"Shopping",
            "subcategory":"Gifts & Souvenirs",
            "type":"Retail Goods"
        }
    ],
    "sg:phone":"+61 7 3255 8334",
    "sg:postcode":"4121",
    "sg:province":"QLD",
    "sg:tags":[
        "shop",
        "supply"
    ],
    "wof:name":"Unique Special Touch",
    "wof:placetype":"venue"
},
  "geometry": {"coordinates":[153.04380798299999,-27.5222797394],"type":"Point"}
}