{
  "type": "Feature",
  "properties": {
    "iso:country":"AU",
    "sg:address":"13 Irrawang St",
    "sg:city":"Raymond Terrace",
    "sg:classifiers":[
        {
            "category":"Shopping",
            "subcategory":"Musical Instruments",
            "type":"Retail Goods"
        }
    ],
    "sg:phone":"+61 2 4987 1454",
    "sg:postcode":"2324",
    "sg:province":"NSW",
    "sg:tags":[
        "musician",
        "agent"
    ],
    "wof:name":"Fish Fry",
    "wof:placetype":"venue"
},
  "geometry": {"coordinates":[151.751220703,-32.7621421814],"type":"Point"}
}