{
  "type": "Feature",
  "properties": {
    "addr:full":"89 Cameron St Rockdale NSW 2216",
    "addr:housenumber":"89",
    "addr:postcode":"2216",
    "addr:street":"Cameron St",
    "iso:country":"AU",
    "sg:address":"89 Cameron St",
    "sg:city":"Rockdale",
    "sg:classifiers":[
        {
            "category":"Social Services",
            "subcategory":"Child Care",
            "type":"Services"
        }
    ],
    "sg:phone":"+61 2 9597 3111",
    "sg:postcode":"2216",
    "sg:province":"NSW",
    "wof:name":"Kogarah Family Day Care",
    "wof:placetype":"venue"
},
  "geometry": {"coordinates":[151.14262400000001,-33.953056],"type":"Point"}
}