{
  "type": "Feature",
  "properties": {
    "iso:country":"AU",
    "sg:address":"23 Schinkel Rd",
    "sg:city":"Naracoorte",
    "sg:classifiers":[
        {
            "category":"Utilities",
            "subcategory":"Refuse",
            "type":"Services"
        }
    ],
    "sg:phone":"+61 438 623 779",
    "sg:postcode":"5271",
    "sg:province":"SA",
    "sg:tags":[
        "remover",
        "rubbish"
    ],
    "wof:name":"Allans Waste Removal & Lawn Mowing",
    "wof:placetype":"venue"
},
  "geometry": {"coordinates":[140.743744,-36.976185],"type":"Point"}
}