{
  "type": "Feature",
  "properties": {
    "addr:full":"30 Roberston Ave Margate QLD 4019",
    "addr:housenumber":"30",
    "addr:postcode":"4019",
    "addr:street":"Roberston Ave",
    "iso:country":"AU",
    "sg:address":"30 Roberston Ave",
    "sg:city":"Margate",
    "sg:classifiers":[
        {
            "category":"Building & Trades",
            "subcategory":"Construction",
            "type":"Services"
        }
    ],
    "sg:phone":"+61 409 372 625",
    "sg:postcode":"4019",
    "sg:province":"QLD",
    "sg:tags":[
        "contractor"
    ],
    "wof:name":"Hall J R",
    "wof:placetype":"venue"
},
  "geometry": {"coordinates":[153.109771728,-27.2397232056],"type":"Point"}
}