{
  "type": "Feature",
  "properties": {
    "iso:country":"AU",
    "sg:address":"131 Lisbon St",
    "sg:city":"Fairfield",
    "sg:classifiers":[
        {
            "category":"Manufacturing",
            "subcategory":"Apparel",
            "type":"Manufacturing & Wholesale Goods"
        }
    ],
    "sg:phone":"+61 2 9724 1488",
    "sg:postcode":"2165",
    "sg:province":"NSW",
    "sg:tags":[
        "makers-up",
        "clothing"
    ],
    "wof:name":"Linhduy Fashion",
    "wof:placetype":"venue"
},
  "geometry": {"coordinates":[150.97096252399999,-33.8702392578],"type":"Point"}
}