{
  "type": "Feature",
  "properties": {
    "iso:country":"AU",
    "sg:address":"7 Woolcock St",
    "sg:city":"Hyde Park",
    "sg:classifiers":[
        {
            "category":"Professional",
            "subcategory":"Business Services",
            "type":"Services"
        }
    ],
    "sg:phone":"+61 408 144 482",
    "sg:postcode":"4812",
    "sg:province":"QLD",
    "sg:tags":[
        "drafting"
    ],
    "wof:name":"Dan Thomson Architectural Drafting",
    "wof:placetype":"venue"
},
  "geometry": {"coordinates":[146.799744,-19.271963],"type":"Point"}
}