{
  "type": "Feature",
  "properties": {
    "iso:country":"AU",
    "sg:address":"111 Normanby Drv",
    "sg:city":"Greenvale",
    "sg:classifiers":[
        {
            "category":"Utilities",
            "subcategory":"Refuse",
            "type":"Services"
        }
    ],
    "sg:phone":"+61 3 9333 2442",
    "sg:postcode":"3059",
    "sg:province":"VIC",
    "sg:tags":[
        "remover",
        "rubbish"
    ],
    "wof:name":"BD Harvest Pty Ltd",
    "wof:placetype":"venue"
},
  "geometry": {"coordinates":[144.902175903,-37.6576919556],"type":"Point"}
}