{
  "type": "Feature",
  "properties": {
    "addr:full":"2 Murchison St Lenah Valley TAS 7008",
    "addr:housenumber":"2",
    "addr:postcode":"7008",
    "addr:street":"Murchison St",
    "iso:country":"AU",
    "sg:address":"2 Murchison St",
    "sg:city":"Lenah Valley",
    "sg:classifiers":[
        {
            "category":"Shopping",
            "subcategory":"Crafts & Fabrics",
            "type":"Retail Goods"
        }
    ],
    "sg:phone":"+61 3 6278 7507",
    "sg:postcode":"7008",
    "sg:province":"TAS",
    "sg:tags":[
        "supply"
    ],
    "wof:name":"Hugs &#039;n Kisses",
    "wof:placetype":"venue"
},
  "geometry": {"coordinates":[147.29820251500001,-42.865940094],"type":"Point"}
}