{
  "type": "Feature",
  "properties": {
    "addr:full":"Lvl 11 17 Castlereagh St Sydney NSW 2000",
    "addr:housenumber":"17",
    "addr:postcode":"2000",
    "addr:street":"Castlereagh St",
    "iso:country":"AU",
    "sg:address":"Lvl 11 17 Castlereagh St",
    "sg:city":"Sydney",
    "sg:classifiers":[
        {
            "category":"Professional",
            "subcategory":"Employment Agencies",
            "type":"Services"
        }
    ],
    "sg:phone":"+61 2 9237 2333",
    "sg:postcode":"2000",
    "sg:province":"NSW",
    "wof:name":"Hughes-Castell Pty Ltd",
    "wof:placetype":"venue"
},
  "geometry": {"coordinates":[151.20979309099999,-33.867023468],"type":"Point"}
}