{
  "type": "Feature",
  "properties": {
    "addr:full":"79 Bingley Crs Fraser ACT 2615",
    "addr:housenumber":"79",
    "addr:postcode":"2615",
    "addr:street":"Bingley Crs",
    "iso:country":"AU",
    "sg:address":"79 Bingley Crs",
    "sg:city":"Fraser",
    "sg:classifiers":[
        {
            "category":"Home & Garden",
            "subcategory":"Building Materials",
            "type":"Retail Goods"
        }
    ],
    "sg:phone":"+61 417 244 414",
    "sg:postcode":"2615",
    "sg:province":"ACT",
    "sg:tags":[
        "lawn",
        "cutting",
        "maintenance"
    ],
    "wof:name":"Grays Garden Service",
    "wof:placetype":"venue"
},
  "geometry": {"coordinates":[149.04498290999999,-35.1913299561],"type":"Point"}
}