{
  "type": "Feature",
  "properties": {
    "addr:full":"23 Queen St Murwillumbah NSW 2484",
    "addr:housenumber":"23",
    "addr:postcode":"2484",
    "addr:street":"Queen St",
    "iso:country":"AU",
    "sg:address":"23 Queen St",
    "sg:city":"Murwillumbah",
    "sg:classifiers":[
        {
            "category":"Professional",
            "subcategory":"Engineering",
            "type":"Services"
        }
    ],
    "sg:phone":"+61 2 6672 3115",
    "sg:postcode":"2484",
    "sg:province":"NSW",
    "sg:tags":[
        "engineer"
    ],
    "wof:name":"Garners Automotive Engineering",
    "wof:placetype":"venue"
},
  "geometry": {"coordinates":[153.399856567,-28.3258323669],"type":"Point"}
}