{
  "type": "Feature",
  "properties": {
    "addr:full":"37 John St Salisbury SA 5108",
    "addr:housenumber":"37",
    "addr:postcode":"5108",
    "addr:street":"John St",
    "iso:country":"AU",
    "sg:address":"37 John St",
    "sg:city":"Salisbury",
    "sg:classifiers":[
        {
            "category":"Shopping",
            "subcategory":"Clothing, Apparel, & Fashions",
            "type":"Retail Goods"
        }
    ],
    "sg:phone":"+61 8 8258 4609",
    "sg:postcode":"5108",
    "sg:province":"SA",
    "sg:tags":[
        "recycled",
        "clothing"
    ],
    "wof:name":"St Vincent De Paul Society",
    "wof:placetype":"venue"
},
  "geometry": {"coordinates":[138.644622803,-34.7627296448],"type":"Point"}
}