{
  "type": "Feature",
  "properties": {
    "iso:country":"AU",
    "sg:address":"68 Clyde St",
    "sg:city":"Granville",
    "sg:classifiers":[
        {
            "category":"Building & Trades",
            "subcategory":"Equipment Rental",
            "type":"Services"
        }
    ],
    "sg:phone":"+61 2 9637 5875",
    "sg:postcode":"2142",
    "sg:province":"NSW",
    "sg:tags":[
        "demolition",
        "contractor"
    ],
    "wof:name":"Khoury N",
    "wof:placetype":"venue"
},
  "geometry": {"coordinates":[151.01400756800001,-33.839881897],"type":"Point"}
}