{
  "type": "Feature",
  "properties": {
    "addr:full":"176 Peel St West Summerhill TAS 7250",
    "addr:housenumber":"176",
    "addr:postcode":"7250",
    "addr:street":"Peel St West",
    "iso:country":"AU",
    "sg:address":"176 Peel St West",
    "sg:city":"Summerhill",
    "sg:classifiers":[
        {
            "category":"Wholesale",
            "subcategory":"Medical Equipment & Supplies",
            "type":"Manufacturing & Wholesale Goods"
        }
    ],
    "sg:phone":"+61 3 6344 9750",
    "sg:postcode":"7250",
    "sg:province":"TAS",
    "sg:tags":[
        "aid",
        "care",
        "health",
        "home"
    ],
    "wof:name":"Summerhill Pharmacy",
    "wof:placetype":"venue"
},
  "geometry": {"coordinates":[147.12985229500001,-41.4666976929],"type":"Point"}
}