{
  "type": "Feature",
  "properties": {
    "addr:full":"92 Boundary St Railway Estate QLD 4810",
    "addr:housenumber":"92",
    "addr:postcode":"4810",
    "addr:street":"Boundary St",
    "iso:country":"AU",
    "sg:address":"92 Boundary St",
    "sg:city":"Railway Estate",
    "sg:classifiers":[
        {
            "category":"Retail",
            "subcategory":"Veterinary Services",
            "type":"Services"
        }
    ],
    "sg:phone":"+61 7 4721 6144",
    "sg:postcode":"4810",
    "sg:province":"QLD",
    "sg:tags":[
        "surgeon"
    ],
    "wof:name":"Skeat Judy",
    "wof:placetype":"venue"
},
  "geometry": {"coordinates":[146.81822199999999,-19.270506],"type":"Point"}
}