{
  "type": "Feature",
  "properties": {
    "addr:full":"Level 1/ 26-54 River St Ballina NSW 2478",
    "addr:housenumber":"/ 26-54",
    "addr:postcode":"2478",
    "addr:street":"River St",
    "iso:country":"AU",
    "sg:address":"Level 1/ 26-54 River St",
    "sg:city":"Ballina",
    "sg:classifiers":[
        {
            "category":"Banks & Credit Unions",
            "subcategory":"Financial Services",
            "type":"Services"
        }
    ],
    "sg:phone":"+61 2 6686 6624",
    "sg:postcode":"2478",
    "sg:province":"NSW",
    "sg:tags":[
        "planning"
    ],
    "wof:name":"Prince Peter CFP",
    "wof:placetype":"venue"
},
  "geometry": {"coordinates":[153.56265258799999,-28.8715362549],"type":"Point"}
}