{
  "type": "Feature",
  "properties": {
    "iso:country":"AU",
    "sg:address":"12 Brunswick Rd",
    "sg:city":"Thornlie",
    "sg:classifiers":[
        {
            "category":"Utilities",
            "subcategory":"Electric",
            "type":"Services"
        }
    ],
    "sg:phone":"+61 8 9455 3638",
    "sg:postcode":"6108",
    "sg:province":"WA",
    "sg:tags":[
        "electrical",
        "contractor"
    ],
    "wof:name":"D N D Electrical Gas Services",
    "wof:placetype":"venue"
},
  "geometry": {"coordinates":[115.94088745099999,-32.0613594055],"type":"Point"}
}