{
  "type": "Feature",
  "properties": {
    "addr:full":"146 Chetwynd St North Melbourne VIC 3051",
    "addr:housenumber":"146",
    "addr:postcode":"3051",
    "addr:street":"Chetwynd St",
    "iso:country":"AU",
    "sg:address":"146 Chetwynd St",
    "sg:city":"North Melbourne",
    "sg:classifiers":[
        {
            "category":"Retail",
            "subcategory":"Auto Repair",
            "type":"Services"
        }
    ],
    "sg:phone":"+61 3 9326 6522",
    "sg:postcode":"3051",
    "sg:province":"VIC",
    "sg:tags":[
        "repairer",
        "motor",
        "engineer"
    ],
    "wof:name":"Leo's Way Auto Repairs",
    "wof:placetype":"venue"
},
  "geometry": {"coordinates":[144.95260620100001,-37.8042030334],"type":"Point"}
}