{
  "type": "Feature",
  "properties": {
    "iso:country":"AU",
    "sg:address":"U3/ 15 Dixon Rd",
    "sg:city":"Rockingham",
    "sg:classifiers":[
        {
            "category":"Banks & Credit Unions",
            "subcategory":"Bureau De Change",
            "type":"Services"
        }
    ],
    "sg:phone":"+61 8 9527 9744",
    "sg:postcode":"6168",
    "sg:province":"WA",
    "sg:tags":[
        "supply",
        "equipment",
        "beating",
        "panel"
    ],
    "wof:name":"Anchor Paint Place",
    "wof:placetype":"venue"
},
  "geometry": {"coordinates":[115.746841,-32.277122],"type":"Point"}
}