{
  "type": "Feature",
  "properties": {
    "addr:full":"Kiora Mall, Kiora Rd Miranda NSW 2228",
    "addr:postcode":"2228",
    "addr:street":"Kiora Rd",
    "iso:country":"AU",
    "sg:address":"Kiora Mall, Kiora Rd",
    "sg:city":"Miranda",
    "sg:classifiers":[
        {
            "category":"Sports & Exercise",
            "subcategory":"Gym",
            "type":"Entertainment"
        }
    ],
    "sg:phone":"+61 2 9531 4535",
    "sg:postcode":"2228",
    "sg:province":"NSW",
    "sg:tags":[
        "health",
        "fitness"
    ],
    "wof:name":"Fitness Firm Miranda",
    "wof:placetype":"venue"
},
  "geometry": {"coordinates":[151.102493286,-34.0339202881],"type":"Point"}
}