{
  "type": "Feature",
  "properties": {
    "addr:full":"24 Main St North Tamborine QLD 4272",
    "addr:housenumber":"24",
    "addr:postcode":"4272",
    "addr:street":"Main St North",
    "iso:country":"AU",
    "sg:address":"24 Main St",
    "sg:city":"North Tamborine",
    "sg:classifiers":[
        {
            "category":"Autos & Motor Vehicles",
            "subcategory":"Auto Supplies",
            "type":"Retail Goods"
        }
    ],
    "sg:phone":"+61 7 5545 1988",
    "sg:postcode":"4272",
    "sg:province":"QLD",
    "sg:tags":[
        "accessory"
    ],
    "wof:name":"Autopro",
    "wof:placetype":"venue"
},
  "geometry": {"coordinates":[153.185256958,-27.925359726],"type":"Point"}
}