{
  "type": "Feature",
  "properties": {
    "iso:country":"AU",
    "sg:address":"24- 28 River St",
    "sg:city":"Richmond",
    "sg:classifiers":[
        {
            "category":"Building & Trades",
            "subcategory":"Plumbing",
            "type":"Services"
        }
    ],
    "sg:phone":"+61 3 9428 1051",
    "sg:postcode":"3121",
    "sg:province":"VIC",
    "sg:tags":[
        "equipment",
        "valves"
    ],
    "wof:name":"Tradelink Industrial Centres",
    "wof:placetype":"venue"
},
  "geometry": {"coordinates":[145.013504028,-37.8168754578],"type":"Point"}
}