{
  "type": "Feature",
  "properties": {
    "addr:full":"83 Carnation Drv Mooroobool QLD 4870",
    "addr:housenumber":"83",
    "addr:postcode":"4870",
    "addr:street":"Carnation Drv",
    "iso:country":"AU",
    "sg:address":"83 Carnation Drv",
    "sg:city":"Mooroobool",
    "sg:classifiers":[
        {
            "category":"Utilities",
            "subcategory":"Electric",
            "type":"Services"
        }
    ],
    "sg:phone":"+61 427 225 130",
    "sg:postcode":"4870",
    "sg:province":"QLD",
    "sg:tags":[
        "electrical",
        "contractor"
    ],
    "wof:name":"Suretech Electrical",
    "wof:placetype":"venue"
},
  "geometry": {"coordinates":[145.73004150400001,-16.9351406097],"type":"Point"}
}