{
  "type": "Feature",
  "properties": {
    "iso:country":"AU",
    "sg:address":"38 Station St",
    "sg:city":"Werribee",
    "sg:classifiers":[
        {
            "category":"Fast Food",
            "type":"Food & Drink"
        }
    ],
    "sg:phone":"+61 3 9741 7101",
    "sg:postcode":"3030",
    "sg:province":"VIC",
    "sg:tags":[
        "away",
        "take"
    ],
    "wof:name":"Golden Grill Turkish Restaurant",
    "wof:placetype":"venue"
},
  "geometry": {"coordinates":[144.661774,-37.900448],"type":"Point"}
}