{
  "type": "Feature",
  "properties": {
    "iso:country":"AU",
    "sg:address":"519/ 38 Bruce Hwy",
    "sg:city":"Benaraby",
    "sg:classifiers":[
        {
            "category":"Real Estate",
            "subcategory":"Surveying",
            "type":"Services"
        }
    ],
    "sg:phone":"+61 7 4975 0100",
    "sg:postcode":"4680",
    "sg:province":"QLD",
    "sg:tags":[
        "surveyor",
        "marine",
        "cargo"
    ],
    "wof:name":"Beale Robert",
    "wof:placetype":"venue"
},
  "geometry": {"coordinates":[151.31169128400001,-23.9965343475],"type":"Point"}
}