{
  "type": "Feature",
  "properties": {
    "iso:country":"AU",
    "sg:address":"Unit 3, 17 Burwood Rd",
    "sg:city":"Burwood",
    "sg:classifiers":[
        {
            "category":"Social Services",
            "subcategory":"Retirement Home",
            "type":"Services"
        }
    ],
    "sg:phone":"+61 2 9747 4732",
    "sg:postcode":"2134",
    "sg:province":"NSW",
    "sg:tags":[
        "village"
    ],
    "wof:name":"Retirement Village Association Ltd.",
    "wof:placetype":"venue"
},
  "geometry": {"coordinates":[151.10488891599999,-33.8704948425],"type":"Point"}
}