{
  "type": "Feature",
  "properties": {
    "addr:full":"Shop 2/ 703 Raglan Pde Warrnambool VIC 3280",
    "addr:housenumber":"shop 2 / 703",
    "addr:postcode":"3280",
    "addr:street":"Raglan Pde",
    "iso:country":"AU",
    "sg:address":"Shop 2/ 703 Raglan Pde",
    "sg:city":"Warrnambool",
    "sg:classifiers":[
        {
            "category":"Retail",
            "subcategory":"Auto Repair",
            "type":"Services"
        }
    ],
    "sg:phone":"+61 3 5562 9046",
    "sg:postcode":"3280",
    "sg:province":"VIC",
    "sg:tags":[
        "testing",
        "inspection",
        "motor",
        "vehicle"
    ],
    "wof:name":"Jeff Heards Automotive Services",
    "wof:placetype":"venue"
},
  "geometry": {"coordinates":[142.48321533199999,-38.3797645569],"type":"Point"}
}