{
  "type": "Feature",
  "properties": {
    "iso:country":"AU",
    "sg:address":"Suite 5/ 185D Forest Rd",
    "sg:city":"Hurstville",
    "sg:classifiers":[
        {
            "category":"Farming",
            "subcategory":"Farm & Veterinary Services",
            "type":"Manufacturing & Wholesale Goods"
        }
    ],
    "sg:phone":"+61 2 9585 2254",
    "sg:postcode":"2220",
    "sg:province":"NSW",
    "sg:tags":[
        "irrigation",
        "reticulation",
        "system"
    ],
    "wof:name":"Exotica Aquascape",
    "wof:placetype":"venue"
},
  "geometry": {"coordinates":[151.10313415499999,-33.9671707153],"type":"Point"}
}