{
  "type": "Feature",
  "properties": {
    "addr:full":"Bldg3/ 788 Old Illawarra Rd Menai NSW 2234",
    "addr:housenumber":"788",
    "addr:postcode":"2234",
    "addr:street":"Old Illawarra Rd",
    "iso:country":"AU",
    "sg:address":"Bldg3/ 788 Old Illawarra Rd",
    "sg:city":"Menai",
    "sg:classifiers":[
        {
            "category":"Retail",
            "subcategory":"Auto Repair",
            "type":"Services"
        }
    ],
    "sg:phone":"+61 2 9543 5007",
    "sg:postcode":"2234",
    "sg:province":"NSW",
    "sg:tags":[
        "repairer",
        "motor",
        "engineer"
    ],
    "wof:name":"Pulse Racing",
    "wof:placetype":"venue"
},
  "geometry": {"coordinates":[151.0103302,-34.0179252625],"type":"Point"}
}