{
  "type": "Feature",
  "properties": {
    "iso:country":"AU",
    "sg:address":"220 Charters Towers Rd",
    "sg:city":"Townsville",
    "sg:classifiers":[
        {
            "category":"Retail",
            "subcategory":"Repair Shop",
            "type":"Services"
        }
    ],
    "sg:phone":"+61 7 4725 4599",
    "sg:postcode":"4810",
    "sg:province":"QLD",
    "sg:tags":[
        "machine",
        "repairs",
        "part",
        "dryer",
        "washing"
    ],
    "wof:name":"Archer L & J Electrical",
    "wof:placetype":"venue"
},
  "geometry": {"coordinates":[146.79747,-19.285093],"type":"Point"}
}