{
  "type": "Feature",
  "properties": {
    "addr:full":"24 Hastings Pde Bensville NSW 2251",
    "addr:housenumber":"24",
    "addr:postcode":"2251",
    "addr:street":"Hastings Pde",
    "iso:country":"AU",
    "sg:address":"24 Hastings Pde",
    "sg:city":"Bensville",
    "sg:classifiers":[
        {
            "category":"Building & Trades",
            "subcategory":"Construction",
            "type":"Services"
        }
    ],
    "sg:phone":"+61 2 4369 4972",
    "sg:postcode":"2251",
    "sg:province":"NSW",
    "sg:tags":[
        "contractor"
    ],
    "wof:name":"DM & LD Conlon",
    "wof:placetype":"venue"
},
  "geometry": {"coordinates":[151.38136291500001,-33.4967269897],"type":"Point"}
}