{
  "type": "Feature",
  "properties": {
    "iso:country":"AU",
    "sg:address":"20 Bowen St",
    "sg:city":"Narrabri",
    "sg:classifiers":[
        {
            "category":"Freight",
            "type":"Transportation"
        }
    ],
    "sg:phone":"+61 2 6792 4777",
    "sg:postcode":"2390",
    "sg:province":"NSW",
    "sg:tags":[
        "cargo",
        "container"
    ],
    "wof:name":"Adams Packing Pty Ltd",
    "wof:placetype":"venue"
},
  "geometry": {"coordinates":[149.789352417,-30.3265991211],"type":"Point"}
}