{
  "type": "Feature",
  "properties": {
    "iso:country":"AU",
    "sg:address":"189 High St",
    "sg:city":"Ashburton",
    "sg:classifiers":[
        {
            "category":"Shopping",
            "subcategory":"Clothing, Apparel, & Fashions",
            "type":"Retail Goods"
        }
    ],
    "sg:phone":"+61 3 9885 0234",
    "sg:postcode":"3147",
    "sg:province":"VIC",
    "sg:tags":[
        "lady",
        "wear"
    ],
    "wof:name":"Lisa Jane",
    "wof:placetype":"venue"
},
  "geometry": {"coordinates":[145.09161376899999,-37.8646812439],"type":"Point"}
}