{
  "type": "Feature",
  "properties": {
    "addr:full":"1015 Ipswich Rd Moorooka QLD 4105",
    "addr:housenumber":"1015",
    "addr:postcode":"4105",
    "addr:street":"Ipswich Rd",
    "iso:country":"AU",
    "sg:address":"1015 Ipswich Rd",
    "sg:city":"Moorooka",
    "sg:classifiers":[
        {
            "category":"Autos & Motor Vehicles",
            "subcategory":"Automobile Sales",
            "type":"Retail Goods"
        }
    ],
    "sg:phone":"+61 7 3393 0355",
    "sg:postcode":"4105",
    "sg:province":"QLD",
    "sg:tags":[
        "car",
        "used"
    ],
    "wof:name":"Supa Carz",
    "wof:placetype":"venue"
},
  "geometry": {"coordinates":[153.01751709000001,-27.530954361],"type":"Point"}
}