{
  "type": "Feature",
  "properties": {
    "addr:full":"96 Warrandyte Rd Langwarrin VIC 3910",
    "addr:housenumber":"96",
    "addr:postcode":"3910",
    "addr:street":"Warrandyte Rd",
    "iso:country":"AU",
    "sg:address":"96 Warrandyte Rd",
    "sg:city":"Langwarrin",
    "sg:classifiers":[
        {
            "category":"Health Services",
            "subcategory":"Chiropractor",
            "type":"Services"
        }
    ],
    "sg:phone":"+61 3 9785 6611",
    "sg:postcode":"3910",
    "sg:province":"VIC",
    "wof:name":"Rasch Carl Dr",
    "wof:placetype":"venue"
},
  "geometry": {"coordinates":[145.18951415999999,-38.1610794067],"type":"Point"}
}