{
  "type": "Feature",
  "properties": {
    "addr:full":"1371 Doherty&#039;s Rd Werribee VIC 3030",
    "addr:housenumber":"1371",
    "addr:postcode":"3030",
    "addr:street":"Doherty &;039 S Rd",
    "iso:country":"AU",
    "sg:address":"1371 Doherty&#039;s Rd",
    "sg:city":"Werribee",
    "sg:classifiers":[
        {
            "category":"Retail",
            "subcategory":"Auto Rental",
            "type":"Services"
        }
    ],
    "sg:phone":"+61 1300 550 443",
    "sg:postcode":"3030",
    "sg:province":"VIC",
    "sg:tags":[
        "chauffeur",
        "car",
        "hire",
        "driven",
        "limousine"
    ],
    "wof:name":"Champagne Carriages & Limousines",
    "wof:placetype":"venue"
},
  "geometry": {"coordinates":[144.68414300000001,-37.901951],"type":"Point"}
}