{
  "type": "Feature",
  "properties": {
    "addr:full":"371 Enmore Rd Enmore NSW 2042",
    "addr:housenumber":"371",
    "addr:postcode":"2042",
    "addr:street":"Enmore Rd",
    "iso:country":"AU",
    "sg:address":"371 Enmore Rd",
    "sg:city":"Enmore",
    "sg:classifiers":[
        {
            "category":"Travel",
            "subcategory":"Hostel",
            "type":"Entertainment"
        }
    ],
    "sg:phone":"+61 1800 888 887",
    "sg:postcode":"2042",
    "sg:province":"NSW",
    "sg:tags":[
        "home"
    ],
    "wof:name":"Sydney CBD Serviced Townhouses",
    "wof:placetype":"venue"
},
  "geometry": {"coordinates":[151.16830400000001,-33.903816],"type":"Point"}
}