{
  "type": "Feature",
  "properties": {
    "addr:full":"Tarwin Rd Meeniyan VIC 3956",
    "addr:postcode":"3956",
    "addr:street":"Tarwin Rd",
    "iso:country":"AU",
    "sg:address":"Tarwin Rd",
    "sg:city":"Meeniyan",
    "sg:classifiers":[
        {
            "category":"Autos & Motor Vehicles",
            "subcategory":"Automobile Sales",
            "type":"Retail Goods"
        }
    ],
    "sg:phone":"+61 3 5664 0037",
    "sg:postcode":"3956",
    "sg:province":"VIC",
    "sg:tags":[
        "car",
        "used"
    ],
    "wof:name":"Nesci Holdings Pty Ltd",
    "wof:placetype":"venue"
},
  "geometry": {"coordinates":[145.982421875,-38.5826530457],"type":"Point"}
}