{
  "type": "Feature",
  "properties": {
    "addr:full":"Dandaloo La Narromine NSW 2821",
    "addr:postcode":"2821",
    "iso:country":"AU",
    "sg:address":"Dandaloo La",
    "sg:city":"Narromine",
    "sg:classifiers":[
        {
            "category":"Manufacturing",
            "subcategory":"Apparel",
            "type":"Manufacturing & Wholesale Goods"
        }
    ],
    "sg:phone":"+61 2 6889 4444",
    "sg:postcode":"2821",
    "sg:province":"NSW",
    "sg:tags":[
        "wholesaler",
        "mfrs",
        "footwear"
    ],
    "wof:name":"Kingtread Pty Ltd",
    "wof:placetype":"venue"
},
  "geometry": {"coordinates":[148.24449157699999,-32.2355308533],"type":"Point"}
}