{
  "type": "Feature",
  "properties": {
    "addr:full":"38 Harbour St Sydney NSW 2000",
    "addr:housenumber":"38",
    "addr:postcode":"2000",
    "addr:street":"Harbour St",
    "iso:country":"AU",
    "sg:address":"38 Harbour St",
    "sg:city":"Sydney",
    "sg:classifiers":[
        {
            "category":"Travel",
            "subcategory":"Hotels & Motels",
            "type":"Entertainment"
        }
    ],
    "sg:phone":"+61 2 9268 5888",
    "sg:postcode":"2000",
    "sg:province":"NSW",
    "sg:tags":[
        "accommodation"
    ],
    "wof:name":"Southern Cross Suites,Darling Harbour",
    "wof:placetype":"venue"
},
  "geometry": {"coordinates":[151.20375060999999,-33.8773193359],"type":"Point"}
}