{
  "type": "Feature",
  "properties": {
    "addr:full":"36 Chickerell St Morwell VIC 3840",
    "addr:housenumber":"36",
    "addr:postcode":"3840",
    "addr:street":"Chickerell St",
    "iso:country":"AU",
    "sg:address":"36 Chickerell St",
    "sg:city":"Morwell",
    "sg:classifiers":[
        {
            "category":"Manufacturing",
            "subcategory":"Metals",
            "type":"Manufacturing & Wholesale Goods"
        }
    ],
    "sg:phone":"+61 1800 806 796",
    "sg:postcode":"3840",
    "sg:province":"VIC",
    "sg:tags":[
        "steel",
        "fabricator",
        "mfrs"
    ],
    "wof:name":"E J Steel Constructions Pty Ltd",
    "wof:placetype":"venue"
},
  "geometry": {"coordinates":[146.43634033199999,-38.2319564819],"type":"Point"}
}