{
  "type": "Feature",
  "properties": {
    "addr:full":"Unit 1, 52 Wells St Gosford East NSW 2250",
    "addr:housenumber":"52",
    "addr:postcode":"2250",
    "addr:street":"Wells St",
    "iso:country":"AU",
    "sg:address":"Unit 1, 52 Wells St",
    "sg:city":"Gosford East",
    "sg:classifiers":[
        {
            "category":"Professional",
            "subcategory":"Art Services",
            "type":"Services"
        }
    ],
    "sg:phone":"+61 413 360 754",
    "sg:postcode":"2250",
    "sg:province":"NSW",
    "sg:tags":[
        "decorator",
        "painter"
    ],
    "wof:name":"Yes We Will Turn Up",
    "wof:placetype":"venue"
},
  "geometry": {"coordinates":[151.35374450699999,-33.433757782],"type":"Point"}
}