{
  "type": "Feature",
  "properties": {
    "addr:full":"15 Victoria Ave Mall Broadbeach QLD 4218",
    "addr:housenumber":"15",
    "addr:postcode":"4218",
    "addr:street":"Victoria Ave Mall",
    "iso:country":"AU",
    "sg:address":"15 Victoria Ave",
    "sg:city":"Mall Broadbeach",
    "sg:classifiers":[
        {
            "category":"Building & Trades",
            "subcategory":"Construction",
            "type":"Services"
        }
    ],
    "sg:phone":"+61 7 5538 0933",
    "sg:postcode":"4218",
    "sg:province":"QLD",
    "sg:tags":[
        "contractor"
    ],
    "wof:name":"Edwards A W Pty Ltd",
    "wof:placetype":"venue"
},
  "geometry": {"coordinates":[153.43365478499999,-28.0286426544],"type":"Point"}
}