{
  "type": "Feature",
  "properties": {
    "iso:country":"AU",
    "sg:address":"Ste2/ 46 Tennyson Rd",
    "sg:city":"Mortlake",
    "sg:classifiers":[
        {
            "category":"Airline",
            "type":"Transportation"
        }
    ],
    "sg:phone":"+61 1800 800 867",
    "sg:postcode":"2137",
    "sg:province":"NSW",
    "sg:tags":[
        "agent"
    ],
    "wof:name":"Alpine Air Services Pty Ltd",
    "wof:placetype":"venue"
},
  "geometry": {"coordinates":[151.10786438,-33.8431282043],"type":"Point"}
}