{
  "type": "Feature",
  "properties": {
    "iso:country":"AU",
    "sg:address":"21 Nardoo St",
    "sg:city":"Wagga Wagga",
    "sg:classifiers":[
        {
            "category":"Building & Trades",
            "subcategory":"Construction",
            "type":"Services"
        }
    ],
    "sg:phone":"+61 407 223 757",
    "sg:postcode":"2650",
    "sg:province":"NSW",
    "sg:tags":[
        "contractor"
    ],
    "wof:name":"R A & D A Semmler",
    "wof:placetype":"venue"
},
  "geometry": {"coordinates":[147.33859252900001,-35.1307487488],"type":"Point"}
}