{
  "type": "Feature",
  "properties": {
    "addr:full":"Factory 2, 33- 35 Elliott Rd Dandenong VIC 3175",
    "addr:housenumber":"33 35",
    "addr:postcode":"3175",
    "addr:street":"Elliott Rd",
    "iso:country":"AU",
    "sg:address":"Factory 2, 33- 35 Elliott Rd",
    "sg:city":"Dandenong",
    "sg:classifiers":[
        {
            "category":"Building & Trades",
            "subcategory":"Construction",
            "type":"Services"
        }
    ],
    "sg:phone":"+61 3 9794 7022",
    "sg:postcode":"3175",
    "sg:province":"VIC",
    "sg:tags":[
        "renovation",
        "alterations",
        "extension",
        "contractor"
    ],
    "wof:name":"The Professional Group Pty Ltd",
    "wof:placetype":"venue"
},
  "geometry": {"coordinates":[145.20758056599999,-38.0230789185],"type":"Point"}
}