{
  "type": "Feature",
  "properties": {
    "addr:full":"61 Reservoir St Surry Hills NSW 2010",
    "addr:housenumber":"61",
    "addr:postcode":"2010",
    "addr:street":"Reservoir St",
    "iso:country":"AU",
    "sg:address":"61 Reservoir St",
    "sg:city":"Surry Hills",
    "sg:classifiers":[
        {
            "category":"Professional",
            "subcategory":"Art Services",
            "type":"Services"
        }
    ],
    "sg:phone":"+61 2 9212 6796",
    "sg:postcode":"2010",
    "sg:province":"NSW",
    "sg:tags":[
        "graphic",
        "designer"
    ],
    "wof:name":"DFM Design Fix Media",
    "wof:placetype":"venue"
},
  "geometry": {"coordinates":[151.21058654800001,-33.881401062],"type":"Point"}
}