{
  "type": "Feature",
  "properties": {
    "iso:country":"AU",
    "sg:address":"681 Bellarine Hwy",
    "sg:city":"Leopold",
    "sg:classifiers":[
        {
            "category":"Health Services",
            "subcategory":"Health Practitioner",
            "type":"Services"
        }
    ],
    "sg:phone":"+61 3 5250 3886",
    "sg:postcode":"3224",
    "sg:province":"VIC",
    "sg:tags":[
        "alternative"
    ],
    "wof:name":"Bellarine Acupuncture Centre",
    "wof:placetype":"venue"
},
  "geometry": {"coordinates":[144.455795,-38.186844],"type":"Point"}
}