{
  "type": "Feature",
  "properties": {
    "addr:full":"41- 43 Goulburn St Liverpool NSW 2170",
    "addr:housenumber":"43",
    "addr:postcode":"2170",
    "addr:street":"Goulburn St",
    "iso:country":"AU",
    "sg:address":"41- 43 Goulburn St",
    "sg:city":"Liverpool",
    "sg:classifiers":[
        {
            "category":"Health Services",
            "subcategory":"Doctor",
            "type":"Services"
        }
    ],
    "sg:phone":"+61 2 9600 8685",
    "sg:postcode":"2170",
    "sg:province":"NSW",
    "sg:tags":[
        "medical",
        "practitioner"
    ],
    "wof:name":"Douglass Hanly Moir Pathology",
    "wof:placetype":"venue"
},
  "geometry": {"coordinates":[150.92898559599999,-33.9180412292],"type":"Point"}
}