{
  "type": "Feature",
  "properties": {
    "addr:full":"46 Queensland Rd Darra QLD 4076",
    "addr:housenumber":"46",
    "addr:postcode":"4076",
    "addr:street":"Queensland Rd",
    "iso:country":"AU",
    "sg:address":"46 Queensland Rd",
    "sg:city":"Darra",
    "sg:classifiers":[
        {
            "category":"Home & Garden",
            "subcategory":"Carpets & Floor Coverings",
            "type":"Retail Goods"
        }
    ],
    "sg:phone":"+61 7 3375 9044",
    "sg:postcode":"4076",
    "sg:province":"QLD",
    "wof:name":"Flooring Queensland Pty Ltd",
    "wof:placetype":"venue"
},
  "geometry": {"coordinates":[152.95161438,-27.562543869],"type":"Point"}
}