{
  "type": "Feature",
  "properties": {
    "addr:full":"12 Grandview St Naremburn NSW 2065",
    "addr:housenumber":"12",
    "addr:postcode":"2065",
    "addr:street":"Grandview St",
    "iso:country":"AU",
    "sg:address":"12 Grandview St",
    "sg:city":"Naremburn",
    "sg:classifiers":[
        {
            "category":"Professional",
            "subcategory":"Engineering",
            "type":"Services"
        }
    ],
    "sg:phone":"+61 2 9405 2221",
    "sg:postcode":"2065",
    "sg:province":"NSW",
    "sg:tags":[
        "engineer",
        "mechanical"
    ],
    "wof:name":"Karlo Kittl Motors",
    "wof:placetype":"venue"
},
  "geometry": {"coordinates":[151.195556641,-33.8142471313],"type":"Point"}
}