{
  "type": "Feature",
  "properties": {
    "addr:full":"978 Devereux Creek Rd Mirani QLD 4754",
    "addr:housenumber":"978",
    "addr:postcode":"4754",
    "addr:street":"Devereux Creek Rd",
    "iso:country":"AU",
    "sg:address":"978 Devereux Creek Rd",
    "sg:city":"Mirani",
    "sg:classifiers":[
        {
            "category":"Retail",
            "subcategory":"Auto Repair",
            "type":"Services"
        }
    ],
    "sg:phone":"+61 7 4959 1790",
    "sg:postcode":"4754",
    "sg:province":"QLD",
    "sg:tags":[
        "camper-trailers",
        "caravan",
        "servicing"
    ],
    "wof:name":"M & J's Mobile Caravan Repairs",
    "wof:placetype":"venue"
},
  "geometry": {"coordinates":[148.863708,-21.122929],"type":"Point"}
}