{
  "type": "Feature",
  "properties": {
    "addr:full":"14 Telford Pl Labrador QLD 4215",
    "addr:housenumber":"14",
    "addr:postcode":"4215",
    "addr:street":"Telford Pl",
    "iso:country":"AU",
    "sg:address":"14 Telford Pl",
    "sg:city":"Labrador",
    "sg:classifiers":[
        {
            "category":"Home & Garden",
            "subcategory":"Building Materials",
            "type":"Retail Goods"
        }
    ],
    "sg:phone":"+61 7 5500 6111",
    "sg:postcode":"4215",
    "sg:province":"QLD",
    "sg:tags":[
        "laminate",
        "laminated",
        "panel"
    ],
    "wof:name":"Design Compact Solutions",
    "wof:placetype":"venue"
},
  "geometry": {"coordinates":[153.380859375,-27.9334030151],"type":"Point"}
}