{
  "type": "Feature",
  "properties": {
    "addr:full":"17 Bowman St South Perth WA 6151",
    "addr:housenumber":"17",
    "addr:postcode":"6151",
    "addr:street":"Bowman St South",
    "iso:country":"AU",
    "sg:address":"17 Bowman St",
    "sg:city":"South Perth",
    "sg:classifiers":[
        {
            "category":"Health Services",
            "subcategory":"Dentist",
            "type":"Services"
        }
    ],
    "sg:phone":"+61 8 9367 9883",
    "sg:postcode":"6151",
    "sg:province":"WA",
    "wof:name":"Lee K Paul",
    "wof:placetype":"venue"
},
  "geometry": {"coordinates":[115.849968,-31.973707],"type":"Point"}
}