{
  "type": "Feature",
  "properties": {
    "addr:full":"30 Elbow St Kempsey West NSW 2440",
    "addr:housenumber":"30",
    "addr:postcode":"2440",
    "addr:street":"Elbow St",
    "iso:country":"AU",
    "sg:address":"30 Elbow St",
    "sg:city":"Kempsey West",
    "sg:classifiers":[
        {
            "category":"Personal",
            "subcategory":"Beauty Salon",
            "type":"Services"
        }
    ],
    "sg:phone":"+61 2 6562 1338",
    "sg:postcode":"2440",
    "sg:province":"NSW",
    "sg:tags":[
        "hairdresser"
    ],
    "wof:name":"Kempsey Clippers",
    "wof:placetype":"venue"
},
  "geometry": {"coordinates":[152.83064300000001,-31.079838],"type":"Point"}
}