{
  "type": "Feature",
  "properties": {
    "addr:full":"595 Mains Rd MacGregor QLD 4109",
    "addr:housenumber":"595",
    "addr:postcode":"4109",
    "addr:street":"Mains Rd",
    "iso:country":"AU",
    "sg:address":"595 Mains Rd",
    "sg:city":"MacGregor",
    "sg:classifiers":[
        {
            "category":"Retail",
            "subcategory":"Auto Repair",
            "type":"Services"
        }
    ],
    "sg:phone":"+61 7 3349 8388",
    "sg:postcode":"4109",
    "sg:province":"QLD",
    "sg:tags":[
        "repairer",
        "motor",
        "engineer"
    ],
    "wof:name":"RACQ Rapid Parts",
    "wof:placetype":"venue"
},
  "geometry": {"coordinates":[153.06636047399999,-27.5605106354],"type":"Point"}
}