{
  "type": "Feature",
  "properties": {
    "addr:full":"32 Birmingham St Alexandria NSW 2015",
    "addr:housenumber":"32",
    "addr:postcode":"2015",
    "addr:street":"Birmingham St",
    "iso:country":"AU",
    "sg:address":"32 Birmingham St",
    "sg:city":"Alexandria",
    "sg:classifiers":[
        {
            "category":"Utilities",
            "subcategory":"Refuse",
            "type":"Services"
        }
    ],
    "sg:phone":"+61 2 9693 1055",
    "sg:postcode":"2015",
    "sg:province":"NSW",
    "sg:tags":[
        "wholesale",
        "glassware",
        "china",
        "earthenware"
    ],
    "wof:name":"Bramor Trading International Co Pty Ltd",
    "wof:placetype":"venue"
},
  "geometry": {"coordinates":[151.19546508799999,-33.920425415],"type":"Point"}
}