{
  "type": "Feature",
  "properties": {
    "iso:country":"AU",
    "sg:address":"11 Springsure St",
    "sg:city":"Eight Mile Plains",
    "sg:classifiers":[
        {
            "category":"Home & Garden",
            "subcategory":"Carpets & Floor Coverings",
            "type":"Retail Goods"
        }
    ],
    "sg:phone":"+61 7 3341 0982",
    "sg:postcode":"4113",
    "sg:province":"QLD",
    "wof:name":"A. Artistic Tiling Pty Ltd",
    "wof:placetype":"venue"
},
  "geometry": {"coordinates":[153.088012695,-27.5916175842],"type":"Point"}
}