{
  "type": "Feature",
  "properties": {
    "addr:full":"4 Gray St Sutherland NSW 2232",
    "addr:housenumber":"4",
    "addr:postcode":"2232",
    "addr:street":"Gray St",
    "iso:country":"AU",
    "sg:address":"4 Gray St",
    "sg:city":"Sutherland",
    "sg:classifiers":[
        {
            "category":"Retail",
            "subcategory":"Auto Repair",
            "type":"Services"
        }
    ],
    "sg:phone":"+61 2 9521 4925",
    "sg:postcode":"2232",
    "sg:province":"NSW",
    "sg:tags":[
        "repairer",
        "motor",
        "engineer"
    ],
    "wof:name":"Pender's Auto Service",
    "wof:placetype":"venue"
},
  "geometry": {"coordinates":[151.05723571799999,-34.034488678],"type":"Point"}
}