{
  "type": "Feature",
  "properties": {
    "iso:country":"AU",
    "sg:address":"62 Dayman St",
    "sg:city":"Urangan",
    "sg:classifiers":[
        {
            "category":"Shopping",
            "subcategory":"Stationery & Office Supplies",
            "type":"Retail Goods"
        }
    ],
    "sg:phone":"+61 407 354 679",
    "sg:postcode":"4655",
    "sg:province":"QLD",
    "sg:tags":[
        "packaging",
        "material"
    ],
    "wof:name":"Wide Bay Removals",
    "wof:placetype":"venue"
},
  "geometry": {"coordinates":[152.901459,-25.288416],"type":"Point"}
}