{
  "type": "Feature",
  "properties": {
    "addr:full":"Shp1/ 452 Enoggera Rd Alderley QLD 4051",
    "addr:housenumber":"452",
    "addr:postcode":"4051",
    "addr:street":"Enoggera Rd",
    "iso:country":"AU",
    "sg:address":"Shp1/ 452 Enoggera Rd",
    "sg:city":"Alderley",
    "sg:classifiers":[
        {
            "category":"Building & Trades",
            "subcategory":"Construction",
            "type":"Services"
        }
    ],
    "sg:phone":"+61 7 3856 4333",
    "sg:postcode":"4051",
    "sg:province":"QLD",
    "sg:tags":[
        "contractor"
    ],
    "wof:name":"Fresh Design",
    "wof:placetype":"venue"
},
  "geometry": {"coordinates":[153.00169372600001,-27.4265174866],"type":"Point"}
}