{
  "type": "Feature",
  "properties": {
    "addr:full":"143 Fowler Rd Illawong NSW 2234",
    "addr:housenumber":"143",
    "addr:postcode":"2234",
    "addr:street":"Fowler Rd",
    "iso:country":"AU",
    "sg:address":"143 Fowler Rd",
    "sg:city":"Illawong",
    "sg:classifiers":[
        {
            "category":"Wholesale",
            "subcategory":"Machinery & Supplies",
            "type":"Manufacturing & Wholesale Goods"
        }
    ],
    "sg:phone":"+61 2 9543 9232",
    "sg:postcode":"2234",
    "sg:province":"NSW",
    "wof:name":"Daytec Engineering",
    "wof:placetype":"venue"
},
  "geometry": {"coordinates":[151.053787231,-33.9950294495],"type":"Point"}
}