{
  "type": "Feature",
  "properties": {
    "addr:full":"23 Dangar St Randwick NSW 2031",
    "addr:housenumber":"23",
    "addr:postcode":"2031",
    "addr:street":"Dangar St",
    "iso:country":"AU",
    "sg:address":"23 Dangar St",
    "sg:city":"Randwick",
    "sg:classifiers":[
        {
            "category":"Building & Trades",
            "subcategory":"Construction",
            "type":"Services"
        }
    ],
    "sg:phone":"+61 2 9398 4103",
    "sg:postcode":"2031",
    "sg:province":"NSW",
    "sg:tags":[
        "contractor"
    ],
    "wof:name":"Paine K",
    "wof:placetype":"venue"
},
  "geometry": {"coordinates":[151.240036011,-33.9043083191],"type":"Point"}
}