{
  "type": "Feature",
  "properties": {
    "iso:country":"AU",
    "sg:address":"Koolindah Shopping Centre Shop 11 President Wilson Wlk",
    "sg:city":"Tanilba Bay",
    "sg:classifiers":[
        {
            "category":"Communications",
            "subcategory":"Film & Video Production",
            "type":"Services"
        }
    ],
    "sg:phone":"+61 2 4982 5544",
    "sg:postcode":"2319",
    "sg:province":"NSW",
    "sg:tags":[
        "dvd",
        "library"
    ],
    "wof:name":"Video Ezy Tanilba Bay",
    "wof:placetype":"venue"
},
  "geometry": {"coordinates":[152.003387,-32.728523],"type":"Point"}
}