{
  "type": "Feature",
  "properties": {
    "iso:country":"AU",
    "sg:address":"357 Gan Gan Rd",
    "sg:city":"Boat Harbour",
    "sg:classifiers":[
        {
            "category":"Building & Trades",
            "subcategory":"Construction",
            "type":"Services"
        }
    ],
    "sg:phone":"+61 2 4982 2955",
    "sg:postcode":"2316",
    "sg:province":"NSW",
    "sg:tags":[
        "contractor"
    ],
    "wof:name":"J & J Killalea Constructions Pty Ltd",
    "wof:placetype":"venue"
},
  "geometry": {"coordinates":[152.085724,-32.777634],"type":"Point"}
}