{
  "type": "Feature",
  "properties": {
    "addr:full":"Shop 28 Cannon Central Shopping Plaza 1145 Wynnum Rd Cannon Hill QLD 4170",
    "addr:housenumber":"shop 28;1145",
    "addr:postcode":"4170",
    "addr:street":"Wynnum Rd",
    "iso:country":"AU",
    "sg:address":"Shop 28 Cannon Central Shopping Plaza 1145 Wynnum Rd",
    "sg:city":"Cannon Hill",
    "sg:classifiers":[
        {
            "category":"Health Services",
            "subcategory":"Optometrist",
            "type":"Services"
        }
    ],
    "sg:phone":"+61 7 3890 3310",
    "sg:postcode":"4170",
    "sg:province":"QLD",
    "wof:name":"David Stahmer",
    "wof:placetype":"venue"
},
  "geometry": {"coordinates":[153.089447022,-27.4577693939],"type":"Point"}
}