{
  "type": "Feature",
  "properties": {
    "addr:full":"Highpoint, 120 -200 Rosamond Rd, Maribyrnong VIC 3032",
    "addr:housenumber":"120 -200",
    "addr:postcode":"3032",
    "addr:street":"Highpoint;Rosamond Rd",
    "iso:country":"AU",
    "sg:address":"Highpoint, 120",
    "sg:city":"-200 Rosamond Rd, Maribyrnong",
    "sg:classifiers":[
        {
            "category":"Shopping",
            "subcategory":"Mobile Phones",
            "type":"Retail Goods"
        }
    ],
    "sg:phone":"+61 3 9317 4844",
    "sg:postcode":"3032",
    "sg:province":"VIC",
    "sg:tags":[
        "telephone",
        "accessory"
    ],
    "wof:name":"Fone Zone",
    "wof:placetype":"venue"
},
  "geometry": {"coordinates":[144.886414,-37.771812],"type":"Point"}
}