{
  "type": "Feature",
  "properties": {
    "addr:full":"7 Sallaway Pl West Pennant Hills NSW 2125",
    "addr:housenumber":"7",
    "addr:postcode":"2125",
    "addr:street":"Sallaway Pl",
    "iso:country":"AU",
    "sg:address":"7 Sallaway Pl",
    "sg:city":"West Pennant Hills",
    "sg:classifiers":[
        {
            "category":"Manufacturing",
            "subcategory":"Food",
            "type":"Manufacturing & Wholesale Goods"
        }
    ],
    "sg:phone":"+61 2 9894 0170",
    "sg:postcode":"2125",
    "sg:province":"NSW",
    "sg:tags":[
        "function",
        "catering"
    ],
    "wof:name":"A Gourmet Experience",
    "wof:placetype":"venue"
},
  "geometry": {"coordinates":[151.02915954599999,-33.7393226624],"type":"Point"}
}