{
  "type": "Feature",
  "properties": {
    "addr:full":"75 Doncaster Rd Balwyn North VIC 3104",
    "addr:housenumber":"75",
    "addr:postcode":"3104",
    "addr:street":"Doncaster Rd",
    "iso:country":"AU",
    "sg:address":"75 Doncaster Rd",
    "sg:city":"Balwyn North",
    "sg:classifiers":[
        {
            "category":"Retail",
            "subcategory":"Repair Shop",
            "type":"Services"
        }
    ],
    "sg:phone":"+61 3 9859 8449",
    "sg:postcode":"3104",
    "sg:province":"VIC",
    "sg:tags":[
        "mending",
        "clothing",
        "alteration"
    ],
    "wof:name":"Butler Dry Cleaners The",
    "wof:placetype":"venue"
},
  "geometry": {"coordinates":[145.071212769,-37.7925682068],"type":"Point"}
}