{
  "type": "Feature",
  "properties": {
    "addr:full":"Shop 9 Cat & Fiddle Arcade Hobart TAS 7000",
    "addr:housenumber":"shop 9",
    "addr:postcode":"7000",
    "iso:country":"AU",
    "sg:address":"Shop 9",
    "sg:city":"Cat & Fiddle Arcade Hobart",
    "sg:classifiers":[
        {
            "category":"Fast Food",
            "type":"Food & Drink"
        }
    ],
    "sg:phone":"+61 3 6231 4433",
    "sg:postcode":"7000",
    "sg:province":"TAS",
    "sg:tags":[
        "away",
        "take"
    ],
    "wof:name":"Cafe Namaskar",
    "wof:placetype":"venue"
},
  "geometry": {"coordinates":[147.31495666500001,-42.8748512268],"type":"Point"}
}