{
  "type": "Feature",
  "properties": {
    "addr:full":"82 Norma Rd Booragoon WA 6154",
    "addr:housenumber":"82",
    "addr:postcode":"6154",
    "addr:street":"Norma Rd",
    "iso:country":"AU",
    "sg:address":"82 Norma Rd",
    "sg:city":"Booragoon",
    "sg:classifiers":[
        {
            "category":"Home & Garden",
            "subcategory":"Furniture",
            "type":"Retail Goods"
        }
    ],
    "sg:phone":"+61 8 9330 1199",
    "sg:postcode":"6154",
    "sg:province":"WA",
    "sg:tags":[
        "outdoor"
    ],
    "wof:name":"Foam Sales.",
    "wof:placetype":"venue"
},
  "geometry": {"coordinates":[115.822472,-32.041039],"type":"Point"}
}