{
  "type": "Feature",
  "properties": {
    "iso:country":"AU",
    "sg:address":"20 Paringa Ave",
    "sg:city":"Somerton Park",
    "sg:classifiers":[
        {
            "category":"Wholesale",
            "subcategory":"Durable Goods & Equipment",
            "type":"Manufacturing & Wholesale Goods"
        }
    ],
    "sg:phone":"+61 8 8294 9733",
    "sg:postcode":"5044",
    "sg:province":"SA",
    "sg:tags":[
        "wholesaler",
        "mfrs",
        "lubrication"
    ],
    "wof:name":"Lubrication Engineers Pty. Ltd.",
    "wof:placetype":"venue"
},
  "geometry": {"coordinates":[138.524033,-34.998878],"type":"Point"}
}