{
  "type": "Feature",
  "properties": {
    "iso:country":"AU",
    "sg:address":"Unit 3/ 80 Regentville Rd",
    "sg:city":"Penrith",
    "sg:classifiers":[
        {
            "category":"Building & Trades",
            "subcategory":"Cleaning & Sanitation",
            "type":"Services"
        }
    ],
    "sg:phone":"+61 2 4737 9511",
    "sg:postcode":"2750",
    "sg:province":"NSW",
    "sg:tags":[
        "chemical",
        "pressure",
        "steam",
        "contractor"
    ],
    "wof:name":"Enviro-Chill Factor",
    "wof:placetype":"venue"
},
  "geometry": {"coordinates":[150.68238830600001,-33.7661552429],"type":"Point"}
}