{
  "type": "Feature",
  "properties": {
    "iso:country":"AU",
    "sg:address":"2779 Gold Coast Hwy",
    "sg:city":"Broadbeach",
    "sg:classifiers":[
        {
            "category":"Fast Food",
            "type":"Food & Drink"
        }
    ],
    "sg:phone":"+61 7 5538 2144",
    "sg:postcode":"4218",
    "sg:province":"QLD",
    "sg:tags":[
        "away",
        "take"
    ],
    "wof:name":"Chiangmai Thai Restaurants",
    "wof:placetype":"venue"
},
  "geometry": {"coordinates":[153.42897033700001,-28.0214862823],"type":"Point"}
}