{
  "type": "Feature",
  "properties": {
    "addr:full":"13 Beckett St Rye VIC 3941",
    "addr:housenumber":"13",
    "addr:postcode":"3941",
    "addr:street":"Beckett St",
    "iso:country":"AU",
    "sg:address":"13 Beckett St",
    "sg:city":"Rye",
    "sg:classifiers":[
        {
            "category":"Professional",
            "subcategory":"Art Services",
            "type":"Services"
        }
    ],
    "sg:phone":"+61 3 5985 5651",
    "sg:postcode":"3941",
    "sg:province":"VIC",
    "sg:tags":[
        "decorator",
        "painter"
    ],
    "wof:name":"Southern Peninsula Painting",
    "wof:placetype":"venue"
},
  "geometry": {"coordinates":[144.794723511,-38.3753623962],"type":"Point"}
}