{
  "type": "Feature",
  "properties": {
    "iso:country":"AU",
    "sg:address":"Shop 7/51- 60 York Rd",
    "sg:city":"Penrith",
    "sg:classifiers":[
        {
            "category":"Industrial Area",
            "type":"Public Place"
        }
    ],
    "sg:phone":"+61 2 4721 3033",
    "sg:postcode":"2750",
    "sg:province":"NSW",
    "sg:tags":[
        "rural",
        "shed"
    ],
    "wof:name":"Ranbuild Sheds Penrith",
    "wof:placetype":"venue"
},
  "geometry": {"coordinates":[150.68797302199999,-33.7672691345],"type":"Point"}
}