{
  "type": "Feature",
  "properties": {
    "addr:full":"16 Pitt St Mortdale NSW 2223",
    "addr:housenumber":"16",
    "addr:postcode":"2223",
    "addr:street":"Pitt St",
    "iso:country":"AU",
    "sg:address":"16 Pitt St",
    "sg:city":"Mortdale",
    "sg:classifiers":[
        {
            "category":"Fast Food",
            "type":"Food & Drink"
        }
    ],
    "sg:phone":"+61 2 9579 4063",
    "sg:postcode":"2223",
    "sg:province":"NSW",
    "sg:tags":[
        "away",
        "take"
    ],
    "wof:name":"Non Finito Pizzeria",
    "wof:placetype":"venue"
},
  "geometry": {"coordinates":[151.079833984,-33.9715652466],"type":"Point"}
}