{
  "type": "Feature",
  "properties": {
    "addr:full":"40 Walter Crs Banora Point NSW 2486",
    "addr:housenumber":"40",
    "addr:postcode":"2486",
    "addr:street":"Walter Crs",
    "iso:country":"AU",
    "sg:address":"40 Walter Crs",
    "sg:city":"Banora Point",
    "sg:classifiers":[
        {
            "category":"Building & Trades",
            "subcategory":"Construction",
            "type":"Services"
        }
    ],
    "sg:phone":"+61 433 285 262",
    "sg:postcode":"2486",
    "sg:province":"NSW",
    "sg:tags":[
        "waterproofing",
        "contractor"
    ],
    "wof:name":"Sure Shield",
    "wof:placetype":"venue"
},
  "geometry": {"coordinates":[153.54563903799999,-28.2131099701],"type":"Point"}
}