{
  "type": "Feature",
  "properties": {
    "iso:country":"AU",
    "sg:address":"19 Mount Druitt Rd",
    "sg:city":"Mt Druitt",
    "sg:classifiers":[
        {
            "category":"Food & Beverages",
            "subcategory":"Bakery",
            "type":"Retail Goods"
        }
    ],
    "sg:phone":"+61 2 9625 3236",
    "sg:postcode":"2770",
    "sg:province":"NSW",
    "sg:tags":[
        "cake",
        "shop",
        "pastry"
    ],
    "wof:name":"Best Choice Cakes",
    "wof:placetype":"venue"
},
  "geometry": {"coordinates":[150.81262207,-33.7691993713],"type":"Point"}
}