{
  "type": "Feature",
  "properties": {
    "addr:full":"291 Princes Hwy Morwell VIC 3840",
    "addr:housenumber":"291",
    "addr:postcode":"3840",
    "addr:street":"Princes Hwy",
    "iso:country":"AU",
    "sg:address":"291 Princes Hwy",
    "sg:city":"Morwell",
    "sg:classifiers":[
        {
            "category":"Food & Beverages",
            "subcategory":"Groceries & Convenience Stores",
            "type":"Retail Goods"
        }
    ],
    "sg:phone":"+61 3 5134 4930",
    "sg:postcode":"3840",
    "sg:province":"VIC",
    "wof:name":"Morwell 24 Hour Hot Spot",
    "wof:placetype":"venue"
},
  "geometry": {"coordinates":[146.39389038100001,-38.2434005737],"type":"Point"}
}