{
  "type": "Feature",
  "properties": {
    "addr:full":"4/ 66 Edgar St North Glen Iris VIC 3146",
    "addr:housenumber":"/ 66",
    "addr:postcode":"3146",
    "addr:street":"Edgar St North",
    "iso:country":"AU",
    "sg:address":"4/ 66 Edgar St North",
    "sg:city":"Glen Iris",
    "sg:classifiers":[
        {
            "category":"Social Services",
            "type":"Services"
        }
    ],
    "sg:phone":"+61 418 135 450",
    "sg:postcode":"3146",
    "sg:province":"VIC",
    "sg:tags":[
        "kinesiology"
    ],
    "wof:name":"Barnett Mary-Lou",
    "wof:placetype":"venue"
},
  "geometry": {"coordinates":[145.046478272,-37.8499946594],"type":"Point"}
}