{
  "type": "Feature",
  "properties": {
    "addr:full":"5 Russell St Rosewater SA 5013",
    "addr:housenumber":"5",
    "addr:postcode":"5013",
    "addr:street":"Russell St",
    "iso:country":"AU",
    "sg:address":"5 Russell St",
    "sg:city":"Rosewater",
    "sg:classifiers":[
        {
            "category":"Health Services",
            "subcategory":"Health Practitioner",
            "type":"Services"
        }
    ],
    "sg:phone":"+61 8 8447 4586",
    "sg:postcode":"5013",
    "sg:province":"SA",
    "sg:tags":[
        "pathologist",
        "speech"
    ],
    "wof:name":"Julie Jensen",
    "wof:placetype":"venue"
},
  "geometry": {"coordinates":[138.52308654800001,-34.8589324951],"type":"Point"}
}