{
  "type": "Feature",
  "properties": {
    "addr:full":"23- 25 Main St Lithgow NSW 2790",
    "addr:housenumber":"25",
    "addr:postcode":"2790",
    "addr:street":"Main St",
    "iso:country":"AU",
    "sg:address":"23- 25 Main St",
    "sg:city":"Lithgow",
    "sg:classifiers":[
        {
            "category":"Home & Garden",
            "subcategory":"Building Materials",
            "type":"Retail Goods"
        }
    ],
    "sg:phone":"+61 2 6351 3102",
    "sg:postcode":"2790",
    "sg:province":"NSW",
    "sg:tags":[
        "supply"
    ],
    "wof:name":"Collins Hardware & Lighting",
    "wof:placetype":"venue"
},
  "geometry": {"coordinates":[150.154464722,-33.4822425842],"type":"Point"}
}