{
  "type": "Feature",
  "properties": {
    "addr:full":"Suit 1 37 Commerce Drv Robina QLD 4226",
    "addr:housenumber":"37",
    "addr:postcode":"4226",
    "addr:street":"Commerce Drv",
    "iso:country":"AU",
    "sg:address":"Suit 1 37 Commerce Drv",
    "sg:city":"Robina",
    "sg:classifiers":[
        {
            "category":"Social Services",
            "subcategory":"Retirement Home",
            "type":"Services"
        }
    ],
    "sg:phone":"+61 7 5578 7040",
    "sg:postcode":"4226",
    "sg:province":"QLD",
    "sg:tags":[
        "environmental",
        "consultant",
        "pollution"
    ],
    "wof:name":"Mark Rigby & Associates Pty Ltd",
    "wof:placetype":"venue"
},
  "geometry": {"coordinates":[153.404129028,-28.0645484924],"type":"Point"}
}