{
  "type": "Feature",
  "properties": {
    "addr:full":"Shop 9 Yeperenye Centre Hartley St Alice Springs NT 0870",
    "addr:housenumber":"shop 9",
    "addr:postcode":"nt 0870",
    "addr:street":"Yeperenye Centre Hartley St",
    "iso:country":"AU",
    "sg:address":"Shop 9 Yeperenye Centre Hartley St",
    "sg:city":"Alice Springs",
    "sg:classifiers":[
        {
            "category":"Personal",
            "type":"Services"
        }
    ],
    "sg:phone":"+61 8 8952 3886",
    "sg:postcode":"0870",
    "sg:province":"NT",
    "sg:tags":[
        "gift"
    ],
    "wof:name":"June Smith Florist",
    "wof:placetype":"venue"
},
  "geometry": {"coordinates":[133.87965393100001,-23.7028026581],"type":"Point"}
}