{
  "type": "Feature",
  "properties": {
    "addr:full":"21 Roberts St Wellington Point QLD 4160",
    "addr:housenumber":"21",
    "addr:postcode":"4160",
    "addr:street":"Roberts St",
    "iso:country":"AU",
    "sg:address":"21 Roberts St",
    "sg:city":"Wellington Point",
    "sg:classifiers":[
        {
            "category":"Organizations",
            "subcategory":"Non-profit Organization",
            "type":"Services"
        }
    ],
    "sg:phone":"+61 7 3822 7088",
    "sg:postcode":"4160",
    "sg:province":"QLD",
    "sg:tags":[
        "support",
        "disability",
        "organisation"
    ],
    "wof:name":"Redland Respite Care Committee Inc",
    "wof:placetype":"venue"
},
  "geometry": {"coordinates":[153.24163818400001,-27.4915828705],"type":"Point"}
}