{
  "type": "Feature",
  "properties": {
    "addr:full":"26 Prichard St Thornleigh NSW 2120",
    "addr:housenumber":"26",
    "addr:postcode":"2120",
    "addr:street":"Prichard St",
    "iso:country":"AU",
    "sg:address":"26 Prichard St",
    "sg:city":"Thornleigh",
    "sg:classifiers":[
        {
            "category":"Utilities",
            "subcategory":"Electric",
            "type":"Services"
        }
    ],
    "sg:phone":"+61 2 9484 3024",
    "sg:postcode":"2120",
    "sg:province":"NSW",
    "sg:tags":[
        "electrical",
        "contractor"
    ],
    "wof:name":"PJS Electrical Pty Ltd",
    "wof:placetype":"venue"
},
  "geometry": {"coordinates":[151.074295044,-33.7314758301],"type":"Point"}
}