{
  "type": "Feature",
  "properties": {
    "iso:country":"AU",
    "sg:address":"29 Sackville St",
    "sg:city":"Port Fairy",
    "sg:classifiers":[
        {
            "category":"Shopping",
            "subcategory":"Clothing, Apparel, & Fashions",
            "type":"Retail Goods"
        }
    ],
    "sg:phone":"+61 3 5568 1775",
    "sg:postcode":"3284",
    "sg:province":"VIC",
    "sg:tags":[
        "recycled",
        "clothing"
    ],
    "wof:name":"Lifeline South West Vic Inc.",
    "wof:placetype":"venue"
},
  "geometry": {"coordinates":[142.2368927,-38.3853645325],"type":"Point"}
}