{
  "type": "Feature",
  "properties": {
    "addr:full":"42 Albert Rd Auburn NSW 2144",
    "addr:housenumber":"42",
    "addr:postcode":"2144",
    "addr:street":"Albert Rd",
    "iso:country":"AU",
    "sg:address":"42 Albert Rd",
    "sg:city":"Auburn",
    "sg:classifiers":[
        {
            "category":"Food & Beverages",
            "subcategory":"Supermarket",
            "type":"Retail Goods"
        }
    ],
    "sg:phone":"+61 2 9649 4249",
    "sg:postcode":"2144",
    "sg:province":"NSW",
    "sg:tags":[
        "grocery",
        "store"
    ],
    "wof:name":"Mini Stars Market",
    "wof:placetype":"venue"
},
  "geometry": {"coordinates":[151.02229309099999,-33.8682098389],"type":"Point"}
}