{
  "type": "Feature",
  "properties": {
    "addr:full":"Lot 11 Somerset Dve, Miallo via Mossman Mossman QLD 4873",
    "addr:postcode":"4873",
    "addr:street":"Somerset Dve Miallo Via Mossman",
    "iso:country":"AU",
    "sg:address":"Lot 11 Somerset Dve, Miallo via Mossman",
    "sg:city":"Mossman",
    "sg:classifiers":[
        {
            "category":"Government",
            "subcategory":"Court House",
            "type":"Public Place"
        }
    ],
    "sg:phone":"+61 7 4098 8052",
    "sg:postcode":"4873",
    "sg:province":"QLD",
    "sg:tags":[
        "personal",
        "marriage",
        "family",
        "counselling"
    ],
    "wof:name":"Confidential Counselling",
    "wof:placetype":"venue"
},
  "geometry": {"coordinates":[145.373657227,-16.4572353363],"type":"Point"}
}