{
  "type": "Feature",
  "properties": {
    "addr:full":"9 Plaza Pde Maroochydore QLD 4558",
    "addr:postcode":"4558",
    "addr:street":"Plaza",
    "iso:country":"AU",
    "sg:address":"9 Plaza Pde",
    "sg:city":"Maroochydore",
    "sg:classifiers":[
        {
            "category":"Organizations",
            "subcategory":"Professional Association",
            "type":"Services"
        }
    ],
    "sg:phone":"+61 7 5479 3800",
    "sg:postcode":"4558",
    "sg:province":"QLD",
    "sg:tags":[
        "web",
        "internet"
    ],
    "wof:name":"Copywizz CW Creative",
    "wof:placetype":"venue"
},
  "geometry": {"coordinates":[153.09042358400001,-26.6564216614],"type":"Point"}
}