{
  "type": "Feature",
  "properties": {
    "iso:country":"AU",
    "sg:address":"Waratah St",
    "sg:city":"Haberfield",
    "sg:classifiers":[
        {
            "category":"Education",
            "subcategory":"School",
            "type":"Public Place"
        }
    ],
    "sg:phone":"+61 2 9797 8249",
    "sg:postcode":"2045",
    "sg:province":"NSW",
    "sg:tags":[
        "state",
        "-",
        "nsw"
    ],
    "wof:name":"Dobroyd Point Public School",
    "wof:placetype":"venue"
},
  "geometry": {"coordinates":[151.14212,-33.875629],"type":"Point"}
}