{
  "type": "Feature",
  "properties": {
    "iso:country":"AU",
    "sg:address":"Mc Kay Rd",
    "sg:city":"Glossop",
    "sg:classifiers":[
        {
            "category":"Professional",
            "subcategory":"Engineering",
            "type":"Services"
        }
    ],
    "sg:phone":"+61 8 8583 2230",
    "sg:postcode":"5344",
    "sg:province":"SA",
    "sg:tags":[
        "engineer"
    ],
    "wof:name":"Wilksch W A & D J Agricultural Engineers",
    "wof:placetype":"venue"
},
  "geometry": {"coordinates":[140.55079650900001,-34.2715072632],"type":"Point"}
}