{
  "type": "Feature",
  "properties": {
    "addr:full":"15 Prospect St Fortitude Valley QLD 4006",
    "addr:housenumber":"15",
    "addr:postcode":"4006",
    "addr:street":"Prospect St",
    "iso:country":"AU",
    "sg:address":"15 Prospect St",
    "sg:city":"Fortitude Valley",
    "sg:classifiers":[
        {
            "category":"Professional",
            "type":"Services"
        }
    ],
    "sg:phone":"+61 7 3251 8080",
    "sg:postcode":"4006",
    "sg:province":"QLD",
    "sg:tags":[
        "mail",
        "contractor"
    ],
    "wof:name":"Median",
    "wof:placetype":"venue"
},
  "geometry": {"coordinates":[153.03765869099999,-27.4519882202],"type":"Point"}
}