{
  "type": "Feature",
  "properties": {
    "iso:country":"AU",
    "sg:address":"22 Kewdale Rd",
    "sg:city":"Kewdale",
    "sg:classifiers":[
        {
            "category":"Professional",
            "type":"Services"
        }
    ],
    "sg:phone":"+61 8 9353 6878",
    "sg:postcode":"6105",
    "sg:province":"WA",
    "sg:tags":[
        "transport"
    ],
    "wof:name":"O&#039;Dowd Transport Service Pty Ltd",
    "wof:placetype":"venue"
},
  "geometry": {"coordinates":[115.954811096,-31.9841480255],"type":"Point"}
}