{
  "type": "Feature",
  "properties": {
    "addr:full":"14 Station St Wentworthville NSW 2145",
    "addr:housenumber":"14",
    "addr:postcode":"2145",
    "addr:street":"Station St",
    "iso:country":"AU",
    "sg:address":"14 Station St",
    "sg:city":"Wentworthville",
    "sg:classifiers":[
        {
            "category":"Personal",
            "subcategory":"Shoe Repair & Shine",
            "type":"Services"
        }
    ],
    "sg:phone":"+61 2 9688 4545",
    "sg:postcode":"2145",
    "sg:province":"NSW",
    "sg:tags":[
        "footwear"
    ],
    "wof:name":"Como Peter Shoe Repairs",
    "wof:placetype":"venue"
},
  "geometry": {"coordinates":[150.97239685100001,-33.8076934814],"type":"Point"}
}