{
  "type": "Feature",
  "properties": {
    "addr:full":"18a Fountain Plaza, 148-158 The Entrance Rd Erina NSW 2250",
    "addr:housenumber":"18a;148-158",
    "addr:postcode":"2250",
    "addr:street":"Fountain Plaza;The Entrance Rd",
    "iso:country":"AU",
    "sg:address":"18a Fountain Plaza, 148-158 The Entrance Rd",
    "sg:city":"Erina",
    "sg:classifiers":[
        {
            "category":"Health Services",
            "subcategory":"Doctor",
            "type":"Services"
        }
    ],
    "sg:phone":"+61 2 4363 9300",
    "sg:postcode":"2250",
    "sg:province":"NSW",
    "sg:tags":[
        "medical",
        "practitioner"
    ],
    "sg:website":"http://www.diagnosticimagingassociates.com.au",
    "wof:name":"Erina Diagnostic Imaging",
    "wof:placetype":"venue"
},
  "geometry": {"coordinates":[151.384643555,-33.4362449646],"type":"Point"}
}