{
  "type": "Feature",
  "properties": {
    "addr:full":"218 Gt Western Hwy Wentworth Falls NSW 2782",
    "addr:housenumber":"218",
    "addr:postcode":"2782",
    "addr:street":"Gt Western Hwy",
    "iso:country":"AU",
    "sg:address":"218 Gt Western Hwy",
    "sg:city":"Wentworth Falls",
    "sg:classifiers":[
        {
            "category":"Health Services",
            "subcategory":"Doctor",
            "type":"Services"
        }
    ],
    "sg:phone":"+61 2 4757 1618",
    "sg:postcode":"2782",
    "sg:province":"NSW",
    "sg:tags":[
        "medical",
        "practitioner"
    ],
    "wof:name":"Lee A Dr",
    "wof:placetype":"venue"
},
  "geometry": {"coordinates":[150.383209228,-33.720161438],"type":"Point"}
}