{
  "type": "Feature",
  "properties": {
    "addr:full":"4/ 30 Barlee St Busselton WA 6280",
    "addr:housenumber":"/ 30",
    "addr:postcode":"6280",
    "addr:street":"Barlee St",
    "iso:country":"AU",
    "sg:address":"4/ 30 Barlee St",
    "sg:city":"Busselton",
    "sg:classifiers":[
        {
            "category":"Professional",
            "subcategory":"Printing & Photocopies",
            "type":"Services"
        }
    ],
    "sg:phone":"+61 8 9754 4430",
    "sg:postcode":"6280",
    "sg:province":"WA",
    "sg:tags":[
        "screen",
        "printer"
    ],
    "wof:name":"Signsmiths",
    "wof:placetype":"venue"
},
  "geometry": {"coordinates":[115.34648132300001,-33.6610870361],"type":"Point"}
}