{
  "type": "Feature",
  "properties": {
    "addr:full":"Lot 328 Arthur Kaine Drv Pambula NSW 2549",
    "addr:housenumber":"328",
    "addr:postcode":"2549",
    "addr:street":"Arthur Kaine Drv",
    "iso:country":"AU",
    "sg:address":"Lot 328 Arthur Kaine Drv",
    "sg:city":"Pambula",
    "sg:classifiers":[
        {
            "category":"Retail",
            "subcategory":"Storage",
            "type":"Services"
        }
    ],
    "sg:phone":"+61 2 6495 3555",
    "sg:postcode":"2549",
    "sg:province":"NSW",
    "wof:name":"Sapphire Coast Self Storage",
    "wof:placetype":"venue"
},
  "geometry": {"coordinates":[149.891555786,-36.9249572754],"type":"Point"}
}