{
  "type": "Feature",
  "properties": {
    "iso:country":"AU",
    "sg:address":"2/ 6 Harvard Wy",
    "sg:city":"Canning Vale",
    "sg:classifiers":[
        {
            "category":"Wholesale",
            "subcategory":"Machinery & Supplies",
            "type":"Manufacturing & Wholesale Goods"
        }
    ],
    "sg:phone":"+61 8 9455 2298",
    "sg:postcode":"6155",
    "sg:province":"WA",
    "sg:tags":[
        "instrument"
    ],
    "wof:name":"Brainchild",
    "wof:placetype":"venue"
},
  "geometry": {"coordinates":[115.923203,-32.064281],"type":"Point"}
}