{
  "type": "Feature",
  "properties": {
    "addr:full":"13 Crice St Paradise Point QLD 4216",
    "addr:housenumber":"13",
    "addr:postcode":"4216",
    "addr:street":"Crice St",
    "iso:country":"AU",
    "sg:address":"13 Crice St",
    "sg:city":"Paradise Point",
    "sg:classifiers":[
        {
            "category":"Real Estate",
            "subcategory":"Real Estate Agent",
            "type":"Services"
        }
    ],
    "sg:phone":"+61 7 5501 5577",
    "sg:postcode":"4216",
    "sg:province":"QLD",
    "wof:name":"Paradise Rentals",
    "wof:placetype":"venue"
},
  "geometry": {"coordinates":[153.39254760700001,-27.8864994049],"type":"Point"}
}