{
  "type": "Feature",
  "properties": {
    "addr:full":"5 Saunders St Coburg VIC 3058",
    "addr:housenumber":"5",
    "addr:postcode":"3058",
    "addr:street":"Saunders St",
    "iso:country":"AU",
    "sg:address":"5 Saunders St",
    "sg:city":"Coburg",
    "sg:classifiers":[
        {
            "category":"Professional",
            "subcategory":"Detective & Security Services",
            "type":"Services"
        }
    ],
    "sg:phone":"+61 411 395 321",
    "sg:postcode":"3058",
    "sg:province":"VIC",
    "sg:tags":[
        "consultant",
        "system"
    ],
    "wof:name":"SKI Security Services",
    "wof:placetype":"venue"
},
  "geometry": {"coordinates":[144.95033264200001,-37.7532844543],"type":"Point"}
}