{
  "type": "Feature",
  "properties": {
    "addr:full":"Suite 3/ 338 Main St Mornington VIC 3931",
    "addr:housenumber":"/ 338",
    "addr:postcode":"3931",
    "addr:street":"Main St",
    "iso:country":"AU",
    "sg:address":"Suite 3/ 338 Main St",
    "sg:city":"Mornington",
    "sg:classifiers":[
        {
            "category":"Health Services",
            "subcategory":"Health Practitioner",
            "type":"Services"
        }
    ],
    "sg:phone":"+61 3 5975 8844",
    "sg:postcode":"3931",
    "sg:province":"VIC",
    "sg:tags":[
        "psychologist"
    ],
    "wof:name":"Ian Macmillan & Associates Pty Ltd",
    "wof:placetype":"venue"
},
  "geometry": {"coordinates":[145.043334961,-38.2267837524],"type":"Point"}
}