{
  "type": "Feature",
  "properties": {
    "addr:full":"200A Canterbury Rd Canterbury VIC 3126",
    "addr:housenumber":"200a",
    "addr:postcode":"3126",
    "addr:street":"Canterbury Rd",
    "iso:country":"AU",
    "sg:address":"200A Canterbury Rd",
    "sg:city":"Canterbury",
    "sg:classifiers":[
        {
            "category":"Fast Food",
            "type":"Food & Drink"
        }
    ],
    "sg:phone":"+61 3 9888 6564",
    "sg:postcode":"3126",
    "sg:province":"VIC",
    "sg:tags":[
        "away",
        "take"
    ],
    "wof:name":"Canterbury Station Fish Shop",
    "wof:placetype":"venue"
},
  "geometry": {"coordinates":[145.081634522,-37.8241882324],"type":"Point"}
}