{
  "type": "Feature",
  "properties": {
    "iso:country":"AU",
    "sg:address":"114 Calista Ave",
    "sg:city":"Calista",
    "sg:classifiers":[
        {
            "category":"Social Services",
            "subcategory":"Adult Care",
            "type":"Services"
        }
    ],
    "sg:phone":"+61 8 9419 3287",
    "sg:postcode":"6167",
    "sg:province":"WA",
    "sg:tags":[
        "disadvantaged",
        "aid",
        "organisation",
        "group"
    ],
    "wof:name":"Isolated Island Outreach Inc",
    "wof:placetype":"venue"
},
  "geometry": {"coordinates":[115.807289,-32.25164],"type":"Point"}
}