{
  "type": "Feature",
  "properties": {
    "addr:full":"Level 2, 3 River St South Yarra VIC 3141",
    "addr:housenumber":"3",
    "addr:postcode":"3141",
    "addr:street":"River St",
    "iso:country":"AU",
    "sg:address":"Level 2, 3 River St",
    "sg:city":"South Yarra",
    "sg:classifiers":[
        {
            "category":"Education",
            "subcategory":"University",
            "type":"Public Place"
        }
    ],
    "sg:phone":"+61 3 9826 6266",
    "sg:postcode":"3141",
    "sg:province":"VIC",
    "sg:tags":[
        "educational",
        "organisation",
        "cultural"
    ],
    "wof:name":"Gap Activity Projects Australia",
    "wof:placetype":"venue"
},
  "geometry": {"coordinates":[144.99734497099999,-37.8395271301],"type":"Point"}
}