{
  "type": "Feature",
  "properties": {
    "iso:country":"AU",
    "sg:address":"1 Robertson St",
    "sg:city":"Naracoorte",
    "sg:classifiers":[
        {
            "category":"Health Services",
            "subcategory":"Chiropractor",
            "type":"Services"
        }
    ],
    "sg:phone":"+61 8 8762 0255",
    "sg:postcode":"5271",
    "sg:province":"SA",
    "wof:name":"Naracoorte Chiropractic Clinic",
    "wof:placetype":"venue"
},
  "geometry": {"coordinates":[140.739853,-36.95734],"type":"Point"}
}