{
  "type": "Feature",
  "properties": {
    "addr:full":"Barlow St Sawyers Valley WA 6074",
    "addr:postcode":"6074",
    "addr:street":"Barlow St",
    "iso:country":"AU",
    "sg:address":"Barlow St",
    "sg:city":"Sawyers Valley",
    "sg:classifiers":[
        {
            "category":"Education",
            "subcategory":"School",
            "type":"Public Place"
        }
    ],
    "sg:phone":"+61 8 9295 1434",
    "sg:postcode":"6074",
    "sg:province":"WA",
    "sg:tags":[
        "state",
        "except",
        "nsw"
    ],
    "wof:name":"Sawyers Valley Primary",
    "wof:placetype":"venue"
},
  "geometry": {"coordinates":[116.201400757,-31.9016895294],"type":"Point"}
}