{
  "type": "Feature",
  "properties": {
    "addr:full":"PO Box 73 Kurmond NSW 2757",
    "addr:postcode":"2757",
    "iso:country":"AU",
    "sg:address":"PO Box 73",
    "sg:city":"Kurmond",
    "sg:classifiers":[
        {
            "category":"Shopping",
            "subcategory":"News",
            "type":"Retail Goods"
        }
    ],
    "sg:phone":"+61 2 4573 0888",
    "sg:postcode":"2757",
    "sg:province":"NSW",
    "sg:tags":[
        "magazine",
        "periodical"
    ],
    "wof:name":"Country Property Magazine",
    "wof:placetype":"venue"
},
  "geometry": {"coordinates":[150.70112609899999,-33.5494499207],"type":"Point"}
}