{
  "type": "Feature",
  "properties": {
    "addr:full":"Gill St Charters Towers QLD 4820",
    "addr:postcode":"4820",
    "addr:street":"Gill St",
    "iso:country":"AU",
    "sg:address":"Gill St",
    "sg:city":"Charters Towers",
    "sg:classifiers":[
        {
            "category":"Autos & Motor Vehicles",
            "subcategory":"Auto Supplies",
            "type":"Retail Goods"
        }
    ],
    "sg:phone":"+61 7 4787 7999",
    "sg:postcode":"4820",
    "sg:province":"QLD",
    "sg:tags":[
        "accessory"
    ],
    "wof:name":"Autopro",
    "wof:placetype":"venue"
},
  "geometry": {"coordinates":[146.26237499999999,-20.076679],"type":"Point"}
}