{
  "type": "Feature",
  "properties": {
    "addr:full":"Collins Place, Suite 11, 45 Collins St Melbourne VIC 3000",
    "addr:housenumber":"45",
    "addr:postcode":"3000",
    "addr:street":"Collins Place;Collins St",
    "iso:country":"AU",
    "sg:address":"Collins Place, Suite 11, 45 Collins St",
    "sg:city":"Melbourne",
    "sg:classifiers":[
        {
            "category":"Health Services",
            "subcategory":"Doctor",
            "type":"Services"
        }
    ],
    "sg:phone":"+61 3 9650 4393",
    "sg:postcode":"3000",
    "sg:province":"VIC",
    "sg:tags":[
        "medical",
        "practitioner"
    ],
    "wof:name":"Hotel Medical Service",
    "wof:placetype":"venue"
},
  "geometry": {"coordinates":[144.97233581500001,-37.8139076233],"type":"Point"}
}