{
  "type": "Feature",
  "properties": {
    "addr:full":"227 Peel St Tamworth NSW 2340",
    "addr:housenumber":"227",
    "addr:postcode":"2340",
    "addr:street":"Peel St",
    "iso:country":"AU",
    "sg:address":"227 Peel St",
    "sg:city":"Tamworth",
    "sg:classifiers":[
        {
            "category":"Shopping",
            "subcategory":"Jewelry",
            "type":"Retail Goods"
        }
    ],
    "sg:phone":"+61 2 6766 6186",
    "sg:postcode":"2340",
    "sg:province":"NSW",
    "sg:tags":[
        "jeweller"
    ],
    "wof:name":"Utopian Bazaar",
    "wof:placetype":"venue"
},
  "geometry": {"coordinates":[150.92732238799999,-31.0881080627],"type":"Point"}
}