{
  "type": "Feature",
  "properties": {
    "addr:full":"103 Hastings River Drv Port Macquarie NSW 2444",
    "addr:housenumber":"103",
    "addr:postcode":"2444",
    "addr:street":"Hastings River Drv",
    "iso:country":"AU",
    "sg:address":"103 Hastings River Drv",
    "sg:city":"Port Macquarie",
    "sg:classifiers":[
        {
            "category":"Manufacturing",
            "subcategory":"Food",
            "type":"Manufacturing & Wholesale Goods"
        }
    ],
    "sg:phone":"+61 2 6583 5333",
    "sg:postcode":"2444",
    "sg:province":"NSW",
    "sg:tags":[
        "function",
        "catering"
    ],
    "wof:name":"Best Western Macquarie Barracks Motor Inn",
    "wof:placetype":"venue"
},
  "geometry": {"coordinates":[152.88810699999999,-31.431116],"type":"Point"}
}