{
  "type": "Feature",
  "properties": {
    "addr:full":"140a Deanmore Rd Scarborough WA 6019",
    "addr:housenumber":"140a",
    "addr:postcode":"6019",
    "addr:street":"Deanmore Rd",
    "iso:country":"AU",
    "sg:address":"140a Deanmore Rd",
    "sg:city":"Scarborough",
    "sg:classifiers":[
        {
            "category":"Professional",
            "subcategory":"Business Services",
            "type":"Services"
        }
    ],
    "sg:phone":"+61 8 9245 1776",
    "sg:postcode":"6019",
    "sg:province":"WA",
    "sg:tags":[
        "drafting"
    ],
    "wof:name":"PlanFact",
    "wof:placetype":"venue"
},
  "geometry": {"coordinates":[115.76789092999999,-31.8953857422],"type":"Point"}
}