{
  "type": "Feature",
  "properties": {
    "addr:full":"36 Harrow Ave Lansvale NSW 2166",
    "addr:housenumber":"36",
    "addr:postcode":"2166",
    "addr:street":"Harrow Ave",
    "iso:country":"AU",
    "sg:address":"36 Harrow Ave",
    "sg:city":"Lansvale",
    "sg:classifiers":[
        {
            "category":"Home & Garden",
            "subcategory":"Building Materials",
            "type":"Retail Goods"
        }
    ],
    "sg:phone":"+61 2 9724 2244",
    "sg:postcode":"2166",
    "sg:province":"NSW",
    "sg:tags":[
        "roofing"
    ],
    "wof:name":"Melnik Projects Mobile Building Supplies",
    "wof:placetype":"venue"
},
  "geometry": {"coordinates":[150.951263428,-33.8997192383],"type":"Point"}
}