{
  "type": "Feature",
  "properties": {
    "iso:country":"AU",
    "sg:address":"176 Boundary Rd",
    "sg:city":"Mordialloc",
    "sg:classifiers":[
        {
            "category":"Shopping",
            "subcategory":"Mobile Phones",
            "type":"Retail Goods"
        }
    ],
    "sg:phone":"+61 3 9588 0808",
    "sg:postcode":"3195",
    "sg:province":"VIC",
    "sg:tags":[
        "telephone",
        "accessory"
    ],
    "wof:name":"Leading Edge Telecoms Mordialloc",
    "wof:placetype":"venue"
},
  "geometry": {"coordinates":[145.107055664,-37.9896469116],"type":"Point"}
}