{
  "type": "Feature",
  "properties": {
    "iso:country":"AU",
    "sg:address":"1 Cliff Rd",
    "sg:city":"North Wollongong",
    "sg:classifiers":[
        {
            "category":"Fast Food",
            "type":"Food & Drink"
        }
    ],
    "sg:phone":"+61 2 4226 2688",
    "sg:postcode":"2500",
    "sg:province":"NSW",
    "sg:tags":[
        "away",
        "take"
    ],
    "wof:name":"North Kiosk",
    "wof:placetype":"venue"
},
  "geometry": {"coordinates":[150.89979600000001,-34.409473],"type":"Point"}
}