{
  "type": "Feature",
  "properties": {
    "addr:full":"1205 Botany Rd Mascot NSW 2020",
    "addr:housenumber":"1205",
    "addr:postcode":"2020",
    "addr:street":"Botany Rd",
    "iso:country":"AU",
    "sg:address":"1205 Botany Rd",
    "sg:city":"Mascot",
    "sg:classifiers":[
        {
            "category":"Shopping",
            "subcategory":"Clothing, Apparel, & Fashions",
            "type":"Retail Goods"
        }
    ],
    "sg:phone":"+61 2 9669 4509",
    "sg:postcode":"2020",
    "sg:province":"NSW",
    "sg:tags":[
        "lady",
        "wear"
    ],
    "wof:name":"Craftx",
    "wof:placetype":"venue"
},
  "geometry": {"coordinates":[151.19435119600001,-33.9315605164],"type":"Point"}
}