{
  "type": "Feature",
  "properties": {
    "addr:full":"4/ 50 Hoopers Rd Kunda Park QLD 4556",
    "addr:housenumber":"/ 50",
    "addr:postcode":"4556",
    "addr:street":"Hoopers Rd",
    "iso:country":"AU",
    "sg:address":"4/ 50 Hoopers Rd",
    "sg:city":"Kunda Park",
    "sg:classifiers":[
        {
            "category":"Autos & Motor Vehicles",
            "subcategory":"Auto Supplies",
            "type":"Retail Goods"
        }
    ],
    "sg:phone":"+61 7 5453 7666",
    "sg:postcode":"4556",
    "sg:province":"QLD",
    "sg:tags":[
        "part",
        "cycles",
        "accessory"
    ],
    "wof:name":"Performance Decals & Signage",
    "wof:placetype":"venue"
},
  "geometry": {"coordinates":[153.04281616200001,-26.6594753265],"type":"Point"}
}