{
  "type": "Feature",
  "properties": {
    "addr:full":"26 Rene St Noosaville QLD 4566",
    "addr:housenumber":"26",
    "addr:postcode":"4566",
    "addr:street":"Rene St",
    "iso:country":"AU",
    "sg:address":"26 Rene St",
    "sg:city":"Noosaville",
    "sg:classifiers":[
        {
            "category":"Wholesale",
            "subcategory":"Non-durable Goods",
            "type":"Manufacturing & Wholesale Goods"
        }
    ],
    "sg:phone":"+61 7 5474 0818",
    "sg:postcode":"4566",
    "sg:province":"QLD",
    "sg:tags":[
        "wholesaler",
        "mfrs",
        "cosmetic"
    ],
    "wof:name":"Primex International Marketing",
    "wof:placetype":"venue"
},
  "geometry": {"coordinates":[153.042312622,-26.4148464203],"type":"Point"}
}