{
  "type": "Feature",
  "properties": {
    "iso:country":"AU",
    "sg:address":"3 Calista Ave (Cnr Summerston Rd)",
    "sg:city":"Kwinana",
    "sg:classifiers":[
        {
            "category":"Shopping",
            "subcategory":"Clothing, Apparel, & Fashions",
            "type":"Retail Goods"
        }
    ],
    "sg:phone":"+61 8 9419 4285",
    "sg:postcode":"6167",
    "sg:province":"WA",
    "sg:tags":[
        "recycled",
        "clothing"
    ],
    "wof:name":"Vinnies Retail Centres",
    "wof:placetype":"venue"
},
  "geometry": {"coordinates":[115.807838,-32.240803],"type":"Point"}
}