{
  "type": "Feature",
  "properties": {
    "iso:country":"AU",
    "sg:address":"PO Box 5016",
    "sg:city":"Algester",
    "sg:classifiers":[
        {
            "category":"Bars & Pubs",
            "subcategory":"Biergarten",
            "type":"Food & Drink"
        }
    ],
    "sg:phone":"+61 7 3711 6422",
    "sg:postcode":"4115",
    "sg:province":"QLD",
    "sg:tags":[
        "eucalyptus",
        "oil",
        "tree",
        "essential",
        "tea"
    ],
    "wof:name":"Continental Flavours & Fragrances Pty Ltd",
    "wof:placetype":"venue"
},
  "geometry": {"coordinates":[153.03521728499999,-27.6165008545],"type":"Point"}
}