{
  "type": "Feature",
  "properties": {
    "iso:country":"AU",
    "sg:address":"388 Burwood Rd",
    "sg:city":"Belmore",
    "sg:classifiers":[
        {
            "category":"Real Estate",
            "subcategory":"Real Estate Agent",
            "type":"Services"
        }
    ],
    "sg:phone":"+61 418 642 116",
    "sg:postcode":"2192",
    "sg:province":"NSW",
    "wof:name":"Belmore Real Estate",
    "wof:placetype":"venue"
},
  "geometry": {"coordinates":[151.088776,-33.918503],"type":"Point"}
}