{
  "type": "Feature",
  "properties": {
    "addr:full":"38 Arnott St Horsham VIC 3400",
    "addr:housenumber":"38",
    "addr:postcode":"3400",
    "addr:street":"Arnott St",
    "iso:country":"AU",
    "sg:address":"38 Arnott St",
    "sg:city":"Horsham",
    "sg:classifiers":[
        {
            "category":"Building & Trades",
            "subcategory":"Construction",
            "type":"Services"
        }
    ],
    "sg:phone":"+61 3 5382 3220",
    "sg:postcode":"3400",
    "sg:province":"VIC",
    "sg:tags":[
        "contractor"
    ],
    "wof:name":"McConville Builders",
    "wof:placetype":"venue"
},
  "geometry": {"coordinates":[142.211791992,-36.7137527466],"type":"Point"}
}