{
  "type": "Feature",
  "properties": {
    "iso:country":"AU",
    "sg:address":"118 High St",
    "sg:city":"Glen Iris",
    "sg:classifiers":[
        {
            "category":"Health Services",
            "subcategory":"Doctor",
            "type":"Services"
        }
    ],
    "sg:phone":"+61 3 9885 4562",
    "sg:postcode":"3146",
    "sg:province":"VIC",
    "sg:tags":[
        "medical",
        "practitioner"
    ],
    "wof:name":"Gerendasi R",
    "wof:placetype":"venue"
},
  "geometry": {"coordinates":[145.072265625,-37.8626213074],"type":"Point"}
}