{
  "type": "Feature",
  "properties": {
    "addr:full":"295 Marrickville Rd Marrickville NSW 2204",
    "addr:housenumber":"295",
    "addr:postcode":"2204",
    "addr:street":"Marrickville Rd",
    "iso:country":"AU",
    "sg:address":"295 Marrickville Rd",
    "sg:city":"Marrickville",
    "sg:classifiers":[
        {
            "category":"Shopping",
            "subcategory":"Clothing, Apparel, & Fashions",
            "type":"Retail Goods"
        }
    ],
    "sg:phone":"+61 2 9564 6392",
    "sg:postcode":"2204",
    "sg:province":"NSW",
    "sg:tags":[
        "recycled",
        "clothing"
    ],
    "wof:name":"Re-Mix & Match",
    "wof:placetype":"venue"
},
  "geometry": {"coordinates":[151.154831,-33.909943],"type":"Point"}
}