{
  "type": "Feature",
  "properties": {
    "addr:full":"272 Crawford St Queanbeyan NSW 2620",
    "addr:housenumber":"272",
    "addr:postcode":"2620",
    "addr:street":"Crawford St",
    "iso:country":"AU",
    "sg:address":"272 Crawford St",
    "sg:city":"Queanbeyan",
    "sg:classifiers":[
        {
            "category":"Health Services",
            "subcategory":"Optometrist",
            "type":"Services"
        }
    ],
    "sg:phone":"+61 2 6297 3339",
    "sg:postcode":"2620",
    "sg:province":"NSW",
    "wof:name":"Mason-Cox Wendy",
    "wof:placetype":"venue"
},
  "geometry": {"coordinates":[149.23562622099999,-35.3547706604],"type":"Point"}
}