{
  "type": "Feature",
  "properties": {
    "iso:country":"AU",
    "sg:address":"87 Glebe Point Rd",
    "sg:city":"Glebe",
    "sg:classifiers":[
        {
            "category":"Travel",
            "subcategory":"Travel Agent",
            "type":"Entertainment"
        }
    ],
    "sg:phone":"+61 2 8512 9600",
    "sg:postcode":"2037",
    "sg:province":"NSW",
    "sg:tags":[
        "consultant"
    ],
    "wof:name":"Student Flights",
    "wof:placetype":"venue"
},
  "geometry": {"coordinates":[151.190475464,-33.8824653625],"type":"Point"}
}