{
  "type": "Feature",
  "properties": {
    "addr:full":"2061 Princes Hwy Clayton VIC 3168",
    "addr:housenumber":"2061",
    "addr:postcode":"3168",
    "addr:street":"Princes Hwy",
    "iso:country":"AU",
    "sg:address":"2061 Princes Hwy",
    "sg:city":"Clayton",
    "sg:classifiers":[
        {
            "category":"Wholesale",
            "subcategory":"Auto Parts",
            "type":"Manufacturing & Wholesale Goods"
        }
    ],
    "sg:phone":"+61 3 9562 8288",
    "sg:postcode":"3168",
    "sg:province":"VIC",
    "sg:tags":[
        "recyclers"
    ],
    "wof:name":"Jagayre",
    "wof:placetype":"venue"
},
  "geometry": {"coordinates":[145.13592529300001,-37.9194412231],"type":"Point"}
}