{
  "type": "Feature",
  "properties": {
    "iso:country":"AU",
    "sg:address":"Shop 19",
    "sg:city":"Kwinana Hub Shopng Cntr Kwinana",
    "sg:classifiers":[
        {
            "category":"Communications",
            "subcategory":"Film & Video Production",
            "type":"Services"
        }
    ],
    "sg:phone":"+61 8 9419 4635",
    "sg:postcode":"6167",
    "sg:province":"WA",
    "sg:tags":[
        "dvd",
        "library"
    ],
    "wof:name":"Home World Video Library",
    "wof:placetype":"venue"
},
  "geometry": {"coordinates":[115.82785,-32.220089],"type":"Point"}
}