{
  "type": "Feature",
  "properties": {
    "addr:full":"622 Forest Rd Bexley NSW 2207",
    "addr:housenumber":"622",
    "addr:postcode":"2207",
    "addr:street":"Forest Rd",
    "iso:country":"AU",
    "sg:address":"622 Forest Rd",
    "sg:city":"Bexley",
    "sg:classifiers":[
        {
            "category":"Retail",
            "subcategory":"Auto Repair",
            "type":"Services"
        }
    ],
    "sg:phone":"+61 2 9587 8192",
    "sg:postcode":"2207",
    "sg:province":"NSW",
    "sg:tags":[
        "beater",
        "painter",
        "panel"
    ],
    "wof:name":"Lennon & Barton Smash Repairs",
    "wof:placetype":"venue"
},
  "geometry": {"coordinates":[151.117874,-33.958546],"type":"Point"}
}