{
  "type": "Feature",
  "properties": {
    "addr:full":"PO Box 400 Windsor NSW 2756",
    "addr:postcode":"2756",
    "iso:country":"AU",
    "sg:address":"PO Box 400",
    "sg:city":"Windsor",
    "sg:classifiers":[
        {
            "category":"Building & Trades",
            "subcategory":"Construction",
            "type":"Services"
        }
    ],
    "sg:phone":"+61 2 4577 7775",
    "sg:postcode":"2756",
    "sg:province":"NSW",
    "sg:tags":[
        "contractor"
    ],
    "wof:name":"Ultra Developments Pty Ltd",
    "wof:placetype":"venue"
},
  "geometry": {"coordinates":[150.81382751500001,-33.6134490967],"type":"Point"}
}