{
  "type": "Feature",
  "properties": {
    "addr:full":"11 Jumal Pl Smithfield NSW 2164",
    "addr:housenumber":"11",
    "addr:postcode":"2164",
    "addr:street":"Jumal Pl",
    "iso:country":"AU",
    "sg:address":"11 Jumal Pl",
    "sg:city":"Smithfield",
    "sg:classifiers":[
        {
            "category":"Wholesale",
            "subcategory":"Machinery & Supplies",
            "type":"Manufacturing & Wholesale Goods"
        }
    ],
    "sg:phone":"+61 2 9604 4348",
    "sg:postcode":"2164",
    "sg:province":"NSW",
    "sg:tags":[
        "belting",
        "mfrs"
    ],
    "wof:name":"Chiorino Australia Pty Ltd",
    "wof:placetype":"venue"
},
  "geometry": {"coordinates":[150.95103454599999,-33.8405227661],"type":"Point"}
}