{
  "type": "Feature",
  "properties": {
    "iso:country":"AU",
    "sg:address":"37 Silver St",
    "sg:city":"Marrickville",
    "sg:classifiers":[
        {
            "category":"Building & Trades",
            "subcategory":"Construction",
            "type":"Services"
        }
    ],
    "sg:phone":"+61 2 9569 1404",
    "sg:postcode":"2204",
    "sg:province":"NSW",
    "sg:tags":[
        "contractor"
    ],
    "wof:name":"On Constructions",
    "wof:placetype":"venue"
},
  "geometry": {"coordinates":[151.157288,-33.910713],"type":"Point"}
}