{
  "type": "Feature",
  "properties": {
    "addr:full":"Marine Pde Kingscliff NSW 2487",
    "addr:postcode":"2487",
    "addr:street":"Marine",
    "iso:country":"AU",
    "sg:address":"Marine Pde",
    "sg:city":"Kingscliff",
    "sg:classifiers":[
        {
            "category":"Arena",
            "subcategory":"Sports Club",
            "type":"Entertainment"
        }
    ],
    "sg:phone":"+61 2 6674 1573",
    "sg:postcode":"2487",
    "sg:province":"NSW",
    "sg:tags":[
        "life",
        "surfing",
        "saving"
    ],
    "wof:name":"Cudgen Headland Surf Life Saving Club",
    "wof:placetype":"venue"
},
  "geometry": {"coordinates":[153.57815551799999,-28.2564487457],"type":"Point"}
}