{
  "type": "Feature",
  "properties": {
    "addr:full":"311 Cambridge Rd Warrane TAS 7018",
    "addr:housenumber":"311",
    "addr:postcode":"7018",
    "addr:street":"Cambridge Rd",
    "iso:country":"AU",
    "sg:address":"311 Cambridge Rd",
    "sg:city":"Warrane",
    "sg:classifiers":[
        {
            "category":"Professional",
            "subcategory":"Engineering",
            "type":"Services"
        }
    ],
    "sg:phone":"+61 3 6244 1418",
    "sg:postcode":"7018",
    "sg:province":"TAS",
    "sg:tags":[
        "manufacturing",
        "engineer"
    ],
    "wof:name":"Purdon K & R",
    "wof:placetype":"venue"
},
  "geometry": {"coordinates":[147.39317321799999,-42.8569030762],"type":"Point"}
}