{
  "type": "Feature",
  "properties": {
    "iso:country":"AU",
    "sg:address":"8 Greenhill Rd",
    "sg:city":"Wayville",
    "sg:classifiers":[
        {
            "category":"Government",
            "subcategory":"Fire Station",
            "type":"Public Place"
        }
    ],
    "sg:phone":"+61 8 8372 7815",
    "sg:postcode":"5034",
    "sg:province":"SA",
    "sg:tags":[
        "equipment",
        "protection",
        "consultant"
    ],
    "wof:name":"Glen Murray Emergency Response Training",
    "wof:placetype":"venue"
},
  "geometry": {"coordinates":[138.58509826700001,-34.9422645569],"type":"Point"}
}