{
  "type": "Feature",
  "properties": {
    "addr:full":"96 Condamine St Dalby QLD 4405",
    "addr:housenumber":"96",
    "addr:postcode":"4405",
    "addr:street":"Condamine St",
    "iso:country":"AU",
    "sg:address":"96 Condamine St",
    "sg:city":"Dalby",
    "sg:classifiers":[
        {
            "category":"Farming",
            "subcategory":"Farm",
            "type":"Manufacturing & Wholesale Goods"
        }
    ],
    "sg:phone":"+61 7 4662 3090",
    "sg:postcode":"4405",
    "sg:province":"QLD",
    "sg:tags":[
        "farmer"
    ],
    "wof:name":"O'Keeffe E J & M M",
    "wof:placetype":"venue"
},
  "geometry": {"coordinates":[151.26202392600001,-27.1820049286],"type":"Point"}
}