{
  "type": "Feature",
  "properties": {
    "addr:full":"Laffers Rd Belair SA 5052",
    "addr:postcode":"5052",
    "addr:street":"Laffers Rd",
    "iso:country":"AU",
    "sg:address":"Laffers Rd",
    "sg:city":"Belair",
    "sg:classifiers":[
        {
            "category":"Health Services",
            "subcategory":"Doctor",
            "type":"Services"
        }
    ],
    "sg:phone":"+61 8 8278 0400",
    "sg:postcode":"5052",
    "sg:province":"SA",
    "sg:tags":[
        "medical",
        "practitioner"
    ],
    "wof:name":"Australasian Pacific Health Care",
    "wof:placetype":"venue"
},
  "geometry": {"coordinates":[138.632614136,-35.0059432983],"type":"Point"}
}