{
  "type": "Feature",
  "properties": {
    "addr:full":"593 Ingham Rd Townsville QLD 4810",
    "addr:housenumber":"593",
    "addr:postcode":"4810",
    "addr:street":"Ingham Rd",
    "iso:country":"AU",
    "sg:address":"593 Ingham Rd",
    "sg:city":"Townsville",
    "sg:classifiers":[
        {
            "category":"Autos & Motor Vehicles",
            "subcategory":"Automobile Sales",
            "type":"Retail Goods"
        }
    ],
    "sg:phone":"+61 7 4774 5366",
    "sg:postcode":"4810",
    "sg:province":"QLD",
    "sg:tags":[
        "bus",
        "truck",
        "new"
    ],
    "wof:name":"Premier Trucks NQ",
    "wof:placetype":"venue"
},
  "geometry": {"coordinates":[146.743042,-19.262222],"type":"Point"}
}