{
  "type": "Feature",
  "properties": {
    "addr:full":"381 Scarborough Beach Rd Osborne Park WA 6017",
    "addr:housenumber":"381",
    "addr:postcode":"6017",
    "addr:street":"Scarborough Beach Rd",
    "iso:country":"AU",
    "sg:address":"381 Scarborough Beach Rd",
    "sg:city":"Osborne Park",
    "sg:classifiers":[
        {
            "category":"Professional",
            "subcategory":"Printing & Photocopies",
            "type":"Services"
        }
    ],
    "sg:phone":"+61 8 9444 0755",
    "sg:postcode":"6017",
    "sg:province":"WA",
    "sg:tags":[
        "photocopying"
    ],
    "wof:name":"Snap Printing",
    "wof:placetype":"venue"
},
  "geometry": {"coordinates":[115.816337585,-31.9119091034],"type":"Point"}
}