{
  "type": "Feature",
  "properties": {
    "addr:full":"63B Kendal St Cowra NSW 2794",
    "addr:housenumber":"63b",
    "addr:postcode":"2794",
    "addr:street":"Kendal St",
    "iso:country":"AU",
    "sg:address":"63B Kendal St",
    "sg:city":"Cowra",
    "sg:classifiers":[
        {
            "category":"Cafe",
            "type":"Food & Drink"
        }
    ],
    "sg:phone":"+61 2 6342 6422",
    "sg:postcode":"2794",
    "sg:province":"NSW",
    "wof:name":"Cuppa On Kendal",
    "wof:placetype":"venue"
},
  "geometry": {"coordinates":[148.69776916500001,-33.8355636597],"type":"Point"}
}