{
  "type": "Feature",
  "properties": {
    "addr:full":"14 Beckett Ave Keilor East VIC 3033",
    "addr:housenumber":"14",
    "addr:postcode":"3033",
    "addr:street":"Beckett Ave",
    "iso:country":"AU",
    "sg:address":"14 Beckett Ave",
    "sg:city":"Keilor East",
    "sg:classifiers":[
        {
            "category":"Home & Garden",
            "subcategory":"Garden Supply",
            "type":"Retail Goods"
        }
    ],
    "sg:phone":"+61 3 9331 7612",
    "sg:postcode":"3033",
    "sg:province":"VIC",
    "sg:tags":[
        "shadecloth"
    ],
    "wof:name":"TA Distributors P/L",
    "wof:placetype":"venue"
},
  "geometry": {"coordinates":[144.85841400000001,-37.731068],"type":"Point"}
}