{
  "type": "Feature",
  "properties": {
    "iso:country":"AU",
    "sg:address":"33 Wood St",
    "sg:city":"Emu Park",
    "sg:classifiers":[
        {
            "category":"Organizations",
            "subcategory":"Non-profit Organization",
            "type":"Services"
        }
    ],
    "sg:phone":"+61 7 4938 8400",
    "sg:postcode":"4702",
    "sg:province":"QLD",
    "sg:tags":[
        "support",
        "disability",
        "organisation"
    ],
    "wof:name":"Keppel Community Care Association Inc",
    "wof:placetype":"venue"
},
  "geometry": {"coordinates":[150.13778686500001,-23.0309944153],"type":"Point"}
}