{
  "type": "Feature",
  "properties": {
    "addr:full":"52 Jonson St Byron Bay NSW 2481",
    "addr:housenumber":"52",
    "addr:postcode":"2481",
    "addr:street":"Jonson St",
    "iso:country":"AU",
    "sg:address":"52 Jonson St",
    "sg:city":"Byron Bay",
    "sg:classifiers":[
        {
            "category":"Real Estate",
            "subcategory":"Real Estate Agent",
            "type":"Services"
        }
    ],
    "sg:phone":"+61 2 6685 6588",
    "sg:postcode":"2481",
    "sg:province":"NSW",
    "wof:name":"Ray White Real Estate",
    "wof:placetype":"venue"
},
  "geometry": {"coordinates":[153.61285400400001,-28.6480236053],"type":"Point"}
}