{
  "type": "Feature",
  "properties": {
    "iso:country":"AU",
    "sg:address":"87 Collins St",
    "sg:city":"Melbourne",
    "sg:classifiers":[
        {
            "category":"Health Services",
            "subcategory":"Dentist",
            "type":"Services"
        }
    ],
    "sg:phone":"+61 1300 661 158",
    "sg:postcode":"3000",
    "sg:province":"VIC",
    "wof:name":"A Whiter Smiley",
    "wof:placetype":"venue"
},
  "geometry": {"coordinates":[144.97067260700001,-37.8144073486],"type":"Point"}
}