{
  "type": "Feature",
  "properties": {
    "iso:country":"AU",
    "sg:address":"2 Fort St",
    "sg:city":"Buderim",
    "sg:classifiers":[
        {
            "category":"Health Services",
            "subcategory":"Health Practitioner",
            "type":"Services"
        }
    ],
    "sg:phone":"+61 7 5445 1707",
    "sg:postcode":"4556",
    "sg:province":"QLD",
    "sg:tags":[
        "bowen",
        "therapy"
    ],
    "wof:name":"Erica Berry-Higgins",
    "wof:placetype":"venue"
},
  "geometry": {"coordinates":[153.05827331500001,-26.6814079285],"type":"Point"}
}