{
  "type": "Feature",
  "properties": {
    "iso:country":"AU",
    "sg:address":"765 Marion Rd",
    "sg:city":"Ascot Park",
    "sg:classifiers":[
        {
            "category":"Real Estate",
            "subcategory":"Real Estate Agent",
            "type":"Services"
        }
    ],
    "sg:phone":"+61 411 509 612",
    "sg:postcode":"5043",
    "sg:province":"SA",
    "wof:name":"Holland Chris",
    "wof:placetype":"venue"
},
  "geometry": {"coordinates":[138.55708300000001,-34.99239],"type":"Point"}
}