{
  "type": "Feature",
  "properties": {
    "addr:full":"40 City Rd Southgate VIC 3006",
    "addr:housenumber":"40",
    "addr:postcode":"3006",
    "addr:street":"City Rd",
    "iso:country":"AU",
    "sg:address":"40 City Rd",
    "sg:city":"Southgate",
    "sg:classifiers":[
        {
            "category":"Health Services",
            "subcategory":"Health Practitioner",
            "type":"Services"
        }
    ],
    "sg:phone":"+61 409 789 580",
    "sg:postcode":"3006",
    "sg:province":"VIC",
    "sg:tags":[
        "psychologist"
    ],
    "wof:name":"Leonie Hehir",
    "wof:placetype":"venue"
},
  "geometry": {"coordinates":[144.96701049800001,-37.8211326599],"type":"Point"}
}