{
  "type": "Feature",
  "properties": {
    "addr:full":"516 Guildford Rd Bayswater WA 6053",
    "addr:housenumber":"516",
    "addr:postcode":"6053",
    "addr:street":"Guildford Rd",
    "iso:country":"AU",
    "sg:address":"516 Guildford Rd",
    "sg:city":"Bayswater",
    "sg:classifiers":[
        {
            "category":"Wholesale",
            "subcategory":"Machinery & Supplies",
            "type":"Manufacturing & Wholesale Goods"
        }
    ],
    "sg:phone":"+61 8 9316 9980",
    "sg:postcode":"6053",
    "sg:province":"WA",
    "sg:tags":[
        "agricultural"
    ],
    "wof:name":"Marjan",
    "wof:placetype":"venue"
},
  "geometry": {"coordinates":[115.92133331300001,-31.9237918854],"type":"Point"}
}