{
  "type": "Feature",
  "properties": {
    "addr:full":"59A 26 Dixon St Strathpine QLD 4500",
    "addr:housenumber":"59a 26",
    "addr:postcode":"4500",
    "addr:street":"Dixon St",
    "iso:country":"AU",
    "sg:address":"59A 26 Dixon St",
    "sg:city":"Strathpine",
    "sg:classifiers":[
        {
            "category":"Building & Trades",
            "subcategory":"Cleaning & Sanitation",
            "type":"Services"
        }
    ],
    "sg:phone":"+61 403 494 274",
    "sg:postcode":"4500",
    "sg:province":"QLD",
    "sg:tags":[
        "chemical",
        "pressure",
        "steam",
        "contractor"
    ],
    "wof:name":"Alert Pressure Cleaning",
    "wof:placetype":"venue"
},
  "geometry": {"coordinates":[152.99530029300001,-27.3083229065],"type":"Point"}
}