{
  "type": "Feature",
  "properties": {
    "addr:full":"Unit 2/ 156 Gilmore Rd Queanbeyan NSW 2620",
    "addr:housenumber":"/ 156",
    "addr:postcode":"2620",
    "addr:street":"Gilmore Rd",
    "iso:country":"AU",
    "sg:address":"Unit 2/ 156 Gilmore Rd",
    "sg:city":"Queanbeyan",
    "sg:classifiers":[
        {
            "category":"Bars & Pubs",
            "subcategory":"Dive Bar",
            "type":"Food & Drink"
        }
    ],
    "sg:phone":"+61 2 6297 0489",
    "sg:postcode":"2620",
    "sg:province":"NSW",
    "sg:tags":[
        "knitwear",
        "retail"
    ],
    "wof:name":"Nullarbor nights Pty Ltd",
    "wof:placetype":"venue"
},
  "geometry": {"coordinates":[149.207763672,-35.3525352478],"type":"Point"}
}