{
  "type": "Feature",
  "properties": {
    "addr:full":"4/ 7 Enterprise Crt Forster NSW 2428",
    "addr:housenumber":"/ 7",
    "addr:postcode":"2428",
    "addr:street":"Enterprise Crt",
    "iso:country":"AU",
    "sg:address":"4/ 7 Enterprise Crt",
    "sg:city":"Forster",
    "sg:classifiers":[
        {
            "category":"Home & Garden",
            "subcategory":"Hardware",
            "type":"Retail Goods"
        }
    ],
    "sg:phone":"+61 2 6555 7202",
    "sg:postcode":"2428",
    "sg:province":"NSW",
    "sg:tags":[
        "repair",
        "tool",
        "power"
    ],
    "wof:name":"Flashback Repairs",
    "wof:placetype":"venue"
},
  "geometry": {"coordinates":[152.52316300000001,-32.199608],"type":"Point"}
}