{
  "type": "Feature",
  "properties": {
    "iso:country":"AU",
    "sg:address":"Shop 23",
    "sg:city":"Park Beach Plz Coffs Harbour",
    "sg:classifiers":[
        {
            "category":"Personal",
            "subcategory":"Beauty Salon",
            "type":"Services"
        }
    ],
    "sg:phone":"+61 2 6652 6046",
    "sg:postcode":"2450",
    "sg:province":"NSW",
    "wof:name":"Complete Beauty",
    "wof:placetype":"venue"
},
  "geometry": {"coordinates":[153.128983,-30.283106],"type":"Point"}
}