{
  "type": "Feature",
  "properties": {
    "iso:country":"AU",
    "sg:address":"15/51- 55 Kembla St",
    "sg:city":"Fyshwick",
    "sg:classifiers":[
        {
            "category":"Shopping",
            "subcategory":"Stationery & Office Supplies",
            "type":"Retail Goods"
        }
    ],
    "sg:phone":"+61 2 6239 1210",
    "sg:postcode":"2609",
    "sg:province":"ACT",
    "wof:name":"Toner Express (A'Asia) Pty Ltd",
    "wof:placetype":"venue"
},
  "geometry": {"coordinates":[149.18711852999999,-35.332698822],"type":"Point"}
}