{
  "type": "Feature",
  "properties": {
    "addr:full":"30 Church St Whittlesea VIC 3757",
    "addr:housenumber":"30",
    "addr:postcode":"3757",
    "addr:street":"Church St",
    "iso:country":"AU",
    "sg:address":"30 Church St",
    "sg:city":"Whittlesea",
    "sg:classifiers":[
        {
            "category":"Personal",
            "subcategory":"Shoe Repair & Shine",
            "type":"Services"
        }
    ],
    "sg:phone":"+61 3 9716 2279",
    "sg:postcode":"3757",
    "sg:province":"VIC",
    "sg:tags":[
        "footwear"
    ],
    "wof:name":"Andy's Shoe Repairs Plus",
    "wof:placetype":"venue"
},
  "geometry": {"coordinates":[145.11802700000001,-37.513008],"type":"Point"}
}