{
  "type": "Feature",
  "properties": {
    "iso:country":"AU",
    "sg:address":"30 Church St",
    "sg:city":"Whittlesea",
    "sg:classifiers":[
        {
            "category":"Personal",
            "subcategory":"Shoe Repair & Shine",
            "type":"Services"
        }
    ],
    "sg:phone":"+61 3 9716 2279",
    "sg:postcode":"3757",
    "sg:province":"VIC",
    "sg:tags":[
        "footwear"
    ],
    "wof:name":"Andy's Shoe Repairs Plus",
    "wof:placetype":"venue"
},
  "geometry": {"coordinates":[145.118027,-37.513008],"type":"Point"}
}