{
  "type": "Feature",
  "properties": {
    "addr:full":"Unit 4, 93- 99 South Creek Rd Dee Why NSW 2099",
    "addr:housenumber":"93 99",
    "addr:postcode":"2099",
    "addr:street":"South Creek Rd",
    "iso:country":"AU",
    "sg:address":"Unit 4, 93- 99 South Creek Rd",
    "sg:city":"Dee Why",
    "sg:classifiers":[
        {
            "category":"Manufacturing",
            "subcategory":"Building Materials",
            "type":"Manufacturing & Wholesale Goods"
        }
    ],
    "sg:phone":"+61 2 9982 2536",
    "sg:postcode":"2099",
    "sg:province":"NSW",
    "sg:tags":[
        "concrete",
        "product"
    ],
    "wof:name":"Besser North Shore Depot",
    "wof:placetype":"venue"
},
  "geometry": {"coordinates":[151.288772583,-33.7410011292],"type":"Point"}
}