{
  "type": "Feature",
  "properties": {
    "iso:country":"AU",
    "sg:address":"1968 Sandgate Rd",
    "sg:city":"Virginia",
    "sg:classifiers":[
        {
            "category":"Retail",
            "subcategory":"Car Wash",
            "type":"Services"
        }
    ],
    "sg:phone":"+61 1300 227 927",
    "sg:postcode":"4014",
    "sg:province":"QLD",
    "sg:tags":[
        "truck",
        "cleaning"
    ],
    "wof:name":"Carlovers Car Wash",
    "wof:placetype":"venue"
},
  "geometry": {"coordinates":[153.06141662600001,-27.3642635345],"type":"Point"}
}