{
  "type": "Feature",
  "properties": {
    "addr:full":"U 1/ 10 Alliance Ave Morisset NSW 2264",
    "addr:housenumber":"10",
    "addr:postcode":"2264",
    "addr:street":"Alliance Ave",
    "iso:country":"AU",
    "sg:address":"U 1/ 10 Alliance Ave",
    "sg:city":"Morisset",
    "sg:classifiers":[
        {
            "category":"Home & Garden",
            "subcategory":"Carpets & Floor Coverings",
            "type":"Retail Goods"
        }
    ],
    "sg:phone":"+61 2 4970 4255",
    "sg:postcode":"2264",
    "sg:province":"NSW",
    "wof:name":"Coastal Commercial Flooring Pty Ltd",
    "wof:placetype":"venue"
},
  "geometry": {"coordinates":[151.472824,-33.11586],"type":"Point"}
}