{
  "type": "Feature",
  "properties": {
    "iso:country":"AU",
    "sg:address":"1084 Pemberton St",
    "sg:city":"Albury",
    "sg:classifiers":[
        {
            "category":"Health Services",
            "subcategory":"Doctor",
            "type":"Services"
        }
    ],
    "sg:phone":"+61 2 6041 3018",
    "sg:postcode":"2640",
    "sg:province":"NSW",
    "sg:tags":[
        "medical",
        "practitioner"
    ],
    "wof:name":"Rennick Gordon",
    "wof:placetype":"venue"
},
  "geometry": {"coordinates":[146.88519287099999,-36.0737571716],"type":"Point"}
}