{
  "type": "Feature",
  "properties": {
    "iso:country":"AU",
    "sg:address":"1/ 464 Port Hacking Rd",
    "sg:city":"Caringbah",
    "sg:classifiers":[
        {
            "category":"Health Services",
            "subcategory":"Chiropractor",
            "type":"Services"
        }
    ],
    "sg:phone":"+61 2 9524 0037",
    "sg:postcode":"2229",
    "sg:province":"NSW",
    "wof:name":"Cilia Natalie",
    "wof:placetype":"venue"
},
  "geometry": {"coordinates":[151.122146606,-34.0520401001],"type":"Point"}
}