{
  "type": "Feature",
  "properties": {
    "addr:full":"10 Education Rd Happy Valley SA 5159",
    "addr:housenumber":"10",
    "addr:postcode":"5159",
    "addr:street":"Education Rd",
    "iso:country":"AU",
    "sg:address":"10 Education Rd",
    "sg:city":"Happy Valley",
    "sg:classifiers":[
        {
            "category":"Travel",
            "subcategory":"Hostel",
            "type":"Entertainment"
        }
    ],
    "sg:phone":"+61 8 8321 0300",
    "sg:postcode":"5159",
    "sg:province":"SA",
    "sg:tags":[
        "home"
    ],
    "wof:name":"Bethsalem Care",
    "wof:placetype":"venue"
},
  "geometry": {"coordinates":[138.584838867,-35.0880737305],"type":"Point"}
}