{
  "type": "Feature",
  "properties": {
    "iso:country":"AU",
    "sg:address":"8 Birrilee Crt",
    "sg:city":"Grovedale",
    "sg:classifiers":[
        {
            "category":"Professional",
            "subcategory":"Art Services",
            "type":"Services"
        }
    ],
    "sg:phone":"+61 412 878 102",
    "sg:postcode":"3216",
    "sg:province":"VIC",
    "sg:tags":[
        "decorator",
        "painter"
    ],
    "wof:name":"Hey Painter",
    "wof:placetype":"venue"
},
  "geometry": {"coordinates":[144.338012695,-38.1971931458],"type":"Point"}
}