{
  "type": "Feature",
  "properties": {
    "addr:full":"15 Bank St Yarrawonga VIC 3730",
    "addr:housenumber":"15",
    "addr:postcode":"3730",
    "addr:street":"Bank St",
    "iso:country":"AU",
    "sg:address":"15 Bank St",
    "sg:city":"Yarrawonga",
    "sg:classifiers":[
        {
            "category":"Recreation",
            "subcategory":"Boat Charter",
            "type":"Entertainment"
        }
    ],
    "sg:phone":"+61 3 5744 1843",
    "sg:postcode":"3730",
    "sg:province":"VIC",
    "wof:name":"Paradise Queen Cruise Boat",
    "wof:placetype":"venue"
},
  "geometry": {"coordinates":[146.01020813,-36.0070037842],"type":"Point"}
}