{
  "type": "Feature",
  "properties": {
    "iso:country":"AU",
    "sg:address":"Room 3/ 97 Bathurst St",
    "sg:city":"Condobolin",
    "sg:classifiers":[
        {
            "category":"Social Services",
            "subcategory":"Adult Care",
            "type":"Services"
        }
    ],
    "sg:phone":"+61 2 6895 4190",
    "sg:postcode":"2877",
    "sg:province":"NSW",
    "sg:tags":[
        "aged"
    ],
    "wof:name":"Condobolin Community Transport",
    "wof:placetype":"venue"
},
  "geometry": {"coordinates":[147.14662200000001,-33.088192],"type":"Point"}
}