{
  "type": "Feature",
  "properties": {
    "addr:full":"Shop 7, Cnr. Quarry & Mimosa Rds Bossley Park NSW 2176",
    "addr:housenumber":"shop 7",
    "addr:postcode":"2176",
    "addr:street":"Cnr. Quarry & Mimosa Rds",
    "iso:country":"AU",
    "sg:address":"Shop 7, Cnr. Quarry & Mimosa Rds",
    "sg:city":"Bossley Park",
    "sg:classifiers":[
        {
            "category":"Personal",
            "subcategory":"Beauty Salon",
            "type":"Services"
        }
    ],
    "sg:phone":"+61 2 9823 2308",
    "sg:postcode":"2176",
    "sg:province":"NSW",
    "wof:name":"Elle Bache",
    "wof:placetype":"venue"
},
  "geometry": {"coordinates":[150.88653564399999,-33.8567695618],"type":"Point"}
}