{
  "type": "Feature",
  "properties": {
    "addr:full":"Shp 4/ 2281 Sandgate Rd Boondall QLD 4034",
    "addr:housenumber":"/ 2281",
    "addr:postcode":"4034",
    "addr:street":"Sandgate Rd",
    "iso:country":"AU",
    "sg:address":"Shp 4/ 2281 Sandgate Rd",
    "sg:city":"Boondall",
    "sg:classifiers":[
        {
            "category":"Professional",
            "subcategory":"Accounting & Tax Preparation",
            "type":"Services"
        }
    ],
    "sg:phone":"+61 7 3265 7772",
    "sg:postcode":"4034",
    "sg:province":"QLD",
    "sg:tags":[
        "accountant",
        "auditor"
    ],
    "wof:name":"Hinkler Accounting",
    "wof:placetype":"venue"
},
  "geometry": {"coordinates":[153.06088299999999,-27.352222],"type":"Point"}
}