{
  "type": "Feature",
  "properties": {
    "iso:country":"AU",
    "sg:address":"4/ 33 Fisher Pde",
    "sg:city":"Ascot Vale",
    "sg:classifiers":[
        {
            "category":"Government",
            "subcategory":"Court House",
            "type":"Public Place"
        }
    ],
    "sg:phone":"+61 438 166 956",
    "sg:postcode":"3032",
    "sg:province":"VIC",
    "sg:tags":[
        "personal",
        "marriage",
        "family",
        "counselling"
    ],
    "wof:name":"Patricia Barbaro",
    "wof:placetype":"venue"
},
  "geometry": {"coordinates":[144.904922,-37.786537],"type":"Point"}
}