{
  "type": "Feature",
  "properties": {
    "iso:country":"AU",
    "sg:address":"Level 10, 233 Macquarie St",
    "sg:city":"Sydney",
    "sg:classifiers":[
        {
            "category":"Professional",
            "subcategory":"Secretarial Services",
            "type":"Services"
        }
    ],
    "sg:phone":"+61 2 9221 6660",
    "sg:postcode":"2000",
    "sg:province":"NSW",
    "sg:tags":[
        "typing"
    ],
    "wof:name":"Computer Reporters",
    "wof:placetype":"venue"
},
  "geometry": {"coordinates":[151.21191406200001,-33.8691635132],"type":"Point"}
}