{
  "type": "Feature",
  "properties": {
    "iso:country":"AU",
    "sg:address":"Unit 3 92 Watt Rd",
    "sg:city":"Mornington",
    "sg:classifiers":[
        {
            "category":"Manufacturing",
            "subcategory":"Apparel",
            "type":"Manufacturing & Wholesale Goods"
        }
    ],
    "sg:phone":"+61 3 5976 1300",
    "sg:postcode":"3931",
    "sg:province":"VIC",
    "sg:tags":[
        "wholesaler",
        "mfrs",
        "footwear"
    ],
    "wof:name":"Fearncove Pty Ltd",
    "wof:placetype":"venue"
},
  "geometry": {"coordinates":[145.05987548799999,-38.2330322266],"type":"Point"}
}