{
  "type": "Feature",
  "properties": {
    "addr:full":"59 Stanbel Rd Salisbury Plain SA 5109",
    "addr:housenumber":"59",
    "addr:postcode":"5109",
    "addr:street":"Stanbel Rd",
    "iso:country":"AU",
    "sg:address":"59 Stanbel Rd",
    "sg:city":"Salisbury Plain",
    "sg:classifiers":[
        {
            "category":"Sports & Exercise",
            "subcategory":"Gym",
            "type":"Entertainment"
        }
    ],
    "sg:phone":"+61 8 8258 4542",
    "sg:postcode":"5109",
    "sg:province":"SA",
    "sg:tags":[
        "health",
        "fitness"
    ],
    "wof:name":"Pro Fitness",
    "wof:placetype":"venue"
},
  "geometry": {"coordinates":[138.662841797,-34.7716827393],"type":"Point"}
}