{
  "type": "Feature",
  "properties": {
    "addr:full":"71 Eyre St North Ward QLD 4810",
    "addr:housenumber":"71",
    "addr:postcode":"4810",
    "addr:street":"Eyre St",
    "iso:country":"AU",
    "sg:address":"71 Eyre St",
    "sg:city":"North Ward",
    "sg:classifiers":[
        {
            "category":"Banks & Credit Unions",
            "subcategory":"Bank",
            "type":"Services"
        }
    ],
    "sg:phone":"+61 7 4781 0523",
    "sg:postcode":"4810",
    "sg:province":"QLD",
    "sg:tags":[
        "broker",
        "mortgage"
    ],
    "wof:name":"The Loan Market",
    "wof:placetype":"venue"
},
  "geometry": {"coordinates":[146.80380199999999,-19.24201],"type":"Point"}
}