{
  "type": "Feature",
  "properties": {
    "iso:country":"AU",
    "sg:address":"Post Office Square 115 Brisbane St",
    "sg:city":"Beaudesert",
    "sg:classifiers":[
        {
            "category":"Professional",
            "subcategory":"Accounting & Tax Preparation",
            "type":"Services"
        }
    ],
    "sg:phone":"+61 7 5541 2011",
    "sg:postcode":"4285",
    "sg:province":"QLD",
    "sg:tags":[
        "consultant",
        "taxation"
    ],
    "wof:name":"Gillow & Teese",
    "wof:placetype":"venue"
},
  "geometry": {"coordinates":[152.995865,-27.986572],"type":"Point"}
}