{
  "type": "Feature",
  "properties": {
    "iso:country":"AU",
    "sg:address":"35 Power St",
    "sg:city":"Hawthorn",
    "sg:classifiers":[
        {
            "category":"Professional",
            "subcategory":"Art Services",
            "type":"Services"
        }
    ],
    "sg:phone":"+61 3 9883 5739",
    "sg:postcode":"3122",
    "sg:province":"VIC",
    "sg:tags":[
        "decorator",
        "painter"
    ],
    "wof:name":"Next Interior",
    "wof:placetype":"venue"
},
  "geometry": {"coordinates":[145.02755737300001,-37.8161964417],"type":"Point"}
}