{
  "type": "Feature",
  "properties": {
    "iso:country":"AU",
    "sg:address":"Unit 4, 73 Governor Macquarie Drv",
    "sg:city":"Chipping Norton",
    "sg:classifiers":[
        {
            "category":"Retail",
            "subcategory":"Auto Repair",
            "type":"Services"
        }
    ],
    "sg:phone":"+61 2 9755 1729",
    "sg:postcode":"2170",
    "sg:province":"NSW",
    "sg:tags":[
        "electrical"
    ],
    "wof:name":"Bucks Auto LPG",
    "wof:placetype":"venue"
},
  "geometry": {"coordinates":[150.96194457999999,-33.9178962708],"type":"Point"}
}