{
  "type": "Feature",
  "properties": {
    "iso:country":"AU",
    "sg:address":"50 Elderslie St",
    "sg:city":"Winton",
    "sg:classifiers":[
        {
            "category":"Arts & Performance",
            "subcategory":"Art Gallery",
            "type":"Entertainment"
        }
    ],
    "sg:phone":"+61 7 4657 1466",
    "sg:postcode":"4735",
    "sg:province":"QLD",
    "wof:name":"Waltzing Matilda Centre",
    "wof:placetype":"venue"
},
  "geometry": {"coordinates":[143.040009,-22.390404],"type":"Point"}
}