{
  "type": "Feature",
  "properties": {
    "addr:full":"Gympie Rd Chermside QLD 4032",
    "addr:postcode":"qld 4032",
    "addr:street":"Gympie Rd",
    "iso:country":"AU",
    "sg:address":"Gympie Rd",
    "sg:city":"Chermside",
    "sg:classifiers":[
        {
            "category":"Health Services",
            "subcategory":"Dentist",
            "type":"Services"
        }
    ],
    "sg:phone":"+61 7 3359 1920",
    "sg:postcode":"4032",
    "sg:province":"QLD",
    "wof:name":"McCann John J Dr",
    "wof:placetype":"venue"
},
  "geometry": {"coordinates":[153.031113,-27.386387],"type":"Point"}
}