{
  "type": "Feature",
  "properties": {
    "addr:full":"PO Box 610 Clare SA 5453",
    "addr:postcode":"5453",
    "iso:country":"AU",
    "sg:address":"PO Box 610",
    "sg:city":"Clare",
    "sg:classifiers":[
        {
            "category":"Farming",
            "subcategory":"Vineyard",
            "type":"Manufacturing & Wholesale Goods"
        }
    ],
    "sg:phone":"+61 419 032 018",
    "sg:postcode":"5453",
    "sg:province":"SA",
    "sg:tags":[
        "winery"
    ],
    "wof:name":"Schultz Vineyard Services",
    "wof:placetype":"venue"
},
  "geometry": {"coordinates":[138.61077900000001,-33.83239],"type":"Point"}
}