{
  "type": "Feature",
  "properties": {
    "iso:country":"AU",
    "sg:address":"93 Bellambi La",
    "sg:city":"Bellambi",
    "sg:classifiers":[
        {
            "category":"Manufacturing",
            "subcategory":"Metals",
            "type":"Manufacturing & Wholesale Goods"
        }
    ],
    "sg:phone":"+61 2 4285 2644",
    "sg:postcode":"2518",
    "sg:province":"NSW",
    "sg:tags":[
        "steel",
        "fabricator",
        "mfrs"
    ],
    "wof:name":"Antax Steel Constructions Pty Ltd",
    "wof:placetype":"venue"
},
  "geometry": {"coordinates":[150.900803,-34.36124],"type":"Point"}
}