{
  "type": "Feature",
  "properties": {
    "iso:country":"AU",
    "sg:address":"46 Goodwood Pde",
    "sg:city":"Burswood",
    "sg:classifiers":[
        {
            "category":"Professional",
            "subcategory":"Employment Agencies",
            "type":"Services"
        }
    ],
    "sg:phone":"+61 8 9472 4338",
    "sg:postcode":"6100",
    "sg:province":"WA",
    "sg:tags":[
        "hire",
        "labour",
        "contractor"
    ],
    "wof:name":"Byers Labour Hire",
    "wof:placetype":"venue"
},
  "geometry": {"coordinates":[115.89927673299999,-31.9559440613],"type":"Point"}
}