{
  "type": "Feature",
  "properties": {
    "iso:country":"AU",
    "sg:address":"Cnr William & Albany North Sts",
    "sg:city":"Gosford",
    "sg:classifiers":[
        {
            "category":"Health Services",
            "subcategory":"Doctor",
            "type":"Services"
        }
    ],
    "sg:phone":"+61 2 4324 6599",
    "sg:postcode":"2250",
    "sg:province":"NSW",
    "sg:tags":[
        "medical",
        "practitioner"
    ],
    "wof:name":"Central Coast Radiology and Nuclear Medicine",
    "wof:placetype":"venue"
},
  "geometry": {"coordinates":[151.34686279300001,-33.4259223938],"type":"Point"}
}