{
  "type": "Feature",
  "properties": {
    "addr:full":"Shp 2/ 28 Paradise Beach Rd Sanctuary Point NSW 2540",
    "addr:housenumber":"/ 28",
    "addr:postcode":"2540",
    "addr:street":"Paradise Beach Rd",
    "iso:country":"AU",
    "sg:address":"Shp 2/ 28 Paradise Beach Rd",
    "sg:city":"Sanctuary Point",
    "sg:classifiers":[
        {
            "category":"Autos & Motor Vehicles",
            "subcategory":"Auto Supplies",
            "type":"Retail Goods"
        }
    ],
    "sg:phone":"+61 2 4443 8549",
    "sg:postcode":"2540",
    "sg:province":"NSW",
    "sg:tags":[
        "accessory"
    ],
    "wof:name":"Jimbos Auto & Mower Parts",
    "wof:placetype":"venue"
},
  "geometry": {"coordinates":[150.626831055,-35.1043243408],"type":"Point"}
}