{
  "type": "Feature",
  "properties": {
    "addr:full":"44 Wells St Frankston VIC 3199",
    "addr:housenumber":"44",
    "addr:postcode":"3199",
    "addr:street":"Wells St",
    "iso:country":"AU",
    "sg:address":"44 Wells St",
    "sg:city":"Frankston",
    "sg:classifiers":[
        {
            "category":"Shopping",
            "subcategory":"Computers & Home Electronics",
            "type":"Retail Goods"
        }
    ],
    "sg:phone":"+61 3 9783 5557",
    "sg:postcode":"3199",
    "sg:province":"VIC",
    "sg:tags":[
        "hire",
        "video",
        "game"
    ],
    "wof:name":"Fone & Games",
    "wof:placetype":"venue"
},
  "geometry": {"coordinates":[144.96870422399999,-37.8269920349],"type":"Point"}
}