{
  "type": "Feature",
  "properties": {
    "iso:country":"AU",
    "sg:address":"4 Pentland Crs",
    "sg:city":"Dudley Park",
    "sg:classifiers":[
        {
            "category":"Building & Trades",
            "subcategory":"Construction",
            "type":"Services"
        }
    ],
    "sg:phone":"+61 429 813 517",
    "sg:postcode":"6210",
    "sg:province":"WA",
    "sg:tags":[
        "concrete",
        "treatment",
        "repair"
    ],
    "wof:name":"South East Spray Pave",
    "wof:placetype":"venue"
},
  "geometry": {"coordinates":[115.727608,-32.543209],"type":"Point"}
}