{
  "type": "Feature",
  "properties": {
    "iso:country":"AU",
    "sg:address":"15 Kipling Pl",
    "sg:city":"Delahey",
    "sg:classifiers":[
        {
            "category":"Building & Trades",
            "subcategory":"Construction",
            "type":"Services"
        }
    ],
    "sg:phone":"+61 411 236 549",
    "sg:postcode":"3037",
    "sg:province":"VIC",
    "sg:tags":[
        "contractor"
    ],
    "wof:name":"Renaissance Constructions",
    "wof:placetype":"venue"
},
  "geometry": {"coordinates":[144.776276,-37.724972],"type":"Point"}
}