{
  "type": "Feature",
  "properties": {
    "addr:full":"39-41 Mill St Horsham VIC 3400",
    "addr:housenumber":"39-41",
    "addr:postcode":"3400",
    "addr:street":"Mill St",
    "iso:country":"AU",
    "sg:address":"39-41 Mill St",
    "sg:city":"Horsham",
    "sg:classifiers":[
        {
            "category":"Autos & Motor Vehicles",
            "subcategory":"Auto Supplies",
            "type":"Retail Goods"
        }
    ],
    "sg:phone":"+61 3 5382 6927",
    "sg:postcode":"3400",
    "sg:province":"VIC",
    "sg:tags":[
        "oil",
        "spirit"
    ],
    "wof:name":"Access Fuel & Lubricants",
    "wof:placetype":"venue"
},
  "geometry": {"coordinates":[142.20233154300001,-36.7064857483],"type":"Point"}
}