{
  "type": "Feature",
  "properties": {
    "iso:country":"AU",
    "sg:address":"Gingin St",
    "sg:city":"Lancelin",
    "sg:classifiers":[
        {
            "category":"Farming",
            "subcategory":"Fish & Marine Products",
            "type":"Manufacturing & Wholesale Goods"
        }
    ],
    "sg:phone":"+61 8 9655 1102",
    "sg:postcode":"6044",
    "sg:province":"WA",
    "sg:tags":[
        "production",
        "seafood",
        "processing"
    ],
    "wof:name":"Kailis & France Foods Pty Ltd",
    "wof:placetype":"venue"
},
  "geometry": {"coordinates":[115.33174896200001,-31.0218753815],"type":"Point"}
}