{
  "type": "Feature",
  "properties": {
    "addr:full":"1 Naughton Ave Birmingham Gardens NSW 2287",
    "addr:housenumber":"1",
    "addr:postcode":"2287",
    "addr:street":"Naughton Ave",
    "iso:country":"AU",
    "sg:address":"1 Naughton Ave",
    "sg:city":"Birmingham Gardens",
    "sg:classifiers":[
        {
            "category":"Personal",
            "subcategory":"Beauty Salon",
            "type":"Services"
        }
    ],
    "sg:phone":"+61 2 4955 9961",
    "sg:postcode":"2287",
    "sg:province":"NSW",
    "sg:tags":[
        "hairdresser"
    ],
    "wof:name":"Normas Technical Hair Profiles",
    "wof:placetype":"venue"
},
  "geometry": {"coordinates":[151.693084717,-32.8955802917],"type":"Point"}
}