{
  "type": "Feature",
  "properties": {
    "iso:country":"AU",
    "sg:address":"7 Sycamore Pl",
    "sg:city":"Palm Beach",
    "sg:classifiers":[
        {
            "category":"Arts & Performance",
            "subcategory":"Music",
            "type":"Entertainment"
        }
    ],
    "sg:phone":"+61 7 5520 7014",
    "sg:postcode":"4221",
    "sg:province":"QLD",
    "sg:tags":[
        "mobile",
        "jockey",
        "disc"
    ],
    "wof:name":"Heartbeats Gold Coast",
    "wof:placetype":"venue"
},
  "geometry": {"coordinates":[153.459640503,-28.1157245636],"type":"Point"}
}