{
  "type": "Feature",
  "properties": {
    "iso:country":"AU",
    "sg:address":"425 Macauley St",
    "sg:city":"Albury",
    "sg:classifiers":[
        {
            "category":"Health Services",
            "subcategory":"Health Practitioner",
            "type":"Services"
        }
    ],
    "sg:phone":"+61 2 6023 1623",
    "sg:postcode":"2640",
    "sg:province":"NSW",
    "sg:tags":[
        "hypnotherapy"
    ],
    "wof:name":"Dylory Enterprises",
    "wof:placetype":"venue"
},
  "geometry": {"coordinates":[146.92190551799999,-36.0817298889],"type":"Point"}
}