{
  "type": "Feature",
  "properties": {
    "iso:country":"AU",
    "sg:address":"1/ 18 Philippine Pde",
    "sg:city":"Palm Beach",
    "sg:classifiers":[
        {
            "category":"Shopping",
            "subcategory":"Shoes",
            "type":"Retail Goods"
        }
    ],
    "sg:phone":"+61 7 5534 6518",
    "sg:postcode":"4221",
    "sg:province":"QLD",
    "sg:tags":[
        "footwear"
    ],
    "wof:name":"Comfort & Fit",
    "wof:placetype":"venue"
},
  "geometry": {"coordinates":[153.470413208,-28.1252841949],"type":"Point"}
}