{
  "type": "Feature",
  "properties": {
    "iso:country":"AU",
    "sg:address":"17 Walker St",
    "sg:city":"Mt Barker",
    "sg:classifiers":[
        {
            "category":"Building & Trades",
            "subcategory":"Locksmith",
            "type":"Services"
        }
    ],
    "sg:phone":"+61 412 204 911",
    "sg:postcode":"5251",
    "sg:province":"SA",
    "sg:tags":[
        "lock"
    ],
    "wof:name":"Lock Around the Clock",
    "wof:placetype":"venue"
},
  "geometry": {"coordinates":[138.857055664,-35.0660934448],"type":"Point"}
}