{
  "type": "Feature",
  "properties": {
    "iso:country":"AU",
    "sg:address":"PO Box 121",
    "sg:city":"South Hobart",
    "sg:classifiers":[
        {
            "category":"Building & Trades",
            "subcategory":"Landscaping Services",
            "type":"Services"
        }
    ],
    "sg:phone":"+61 3 6224 0511",
    "sg:postcode":"7004",
    "sg:province":"TAS",
    "sg:tags":[
        "consultant"
    ],
    "wof:name":"Phil O&#039;Halloran & Associates",
    "wof:placetype":"venue"
},
  "geometry": {"coordinates":[147.31483459500001,-42.895160675],"type":"Point"}
}