{
  "type": "Feature",
  "properties": {
    "iso:country":"AU",
    "sg:address":"41 Lonsdale St",
    "sg:city":"Dandenong",
    "sg:classifiers":[
        {
            "category":"Wholesale",
            "subcategory":"Painting Supplies",
            "type":"Manufacturing & Wholesale Goods"
        }
    ],
    "sg:phone":"+61 3 9793 3847",
    "sg:postcode":"3175",
    "sg:province":"VIC",
    "sg:tags":[
        "wholesaler",
        "paint",
        "mfrs"
    ],
    "wof:name":"Du Pont",
    "wof:placetype":"venue"
},
  "geometry": {"coordinates":[145.21449279800001,-37.9907417297],"type":"Point"}
}