{
  "type": "Feature",
  "properties": {
    "iso:country":"AU",
    "sg:address":"12 brisbane Rd",
    "sg:city":"Riverview",
    "sg:classifiers":[
        {
            "category":"Communications",
            "subcategory":"Film & Video Production",
            "type":"Services"
        }
    ],
    "sg:phone":"+61 402 795 891",
    "sg:postcode":"4303",
    "sg:province":"QLD",
    "sg:tags":[
        "yacht",
        "transport",
        "boat"
    ],
    "wof:name":"Aquatic Boat Transport",
    "wof:placetype":"venue"
},
  "geometry": {"coordinates":[152.83004760700001,-27.5987243652],"type":"Point"}
}