{
  "type": "Feature",
  "properties": {
    "addr:full":"10 Smith Ave Warrnambool VIC 3280",
    "addr:housenumber":"10",
    "addr:postcode":"3280",
    "addr:street":"Smith Ave",
    "iso:country":"AU",
    "sg:address":"10 Smith Ave",
    "sg:city":"Warrnambool",
    "sg:classifiers":[
        {
            "category":"Building & Trades",
            "subcategory":"Plumbing",
            "type":"Services"
        }
    ],
    "sg:phone":"+61 3 5561 3859",
    "sg:postcode":"3280",
    "sg:province":"VIC",
    "sg:tags":[
        "plumber",
        "gasfitters"
    ],
    "wof:name":"Len Mann & Co Pty Ltd",
    "wof:placetype":"venue"
},
  "geometry": {"coordinates":[142.48274230999999,-38.3867225647],"type":"Point"}
}