{
  "type": "Feature",
  "properties": {
    "addr:full":"Level 1, Quay Central, 95 North Quay Brisbane QLD 4000",
    "addr:housenumber":"95",
    "addr:postcode":"4000",
    "addr:street":"North Quay",
    "iso:country":"AU",
    "sg:address":"Level 1, Quay Central, 95 North Quay",
    "sg:city":"Brisbane",
    "sg:classifiers":[
        {
            "category":"Professional",
            "subcategory":"Business Services",
            "type":"Services"
        }
    ],
    "sg:phone":"+61 7 3837 3600",
    "sg:postcode":"4000",
    "sg:province":"QLD",
    "sg:tags":[
        "small",
        "advisory"
    ],
    "sg:website":"http://www.ntlawyers.com.au",
    "wof:name":"Neumann & Turnour Lawyers",
    "wof:placetype":"venue"
},
  "geometry": {"coordinates":[153.02101135300001,-27.4698314667],"type":"Point"}
}