{
  "type": "Feature",
  "properties": {
    "iso:country":"AU",
    "sg:address":"23 Knight St",
    "sg:city":"Portsmith",
    "sg:classifiers":[
        {
            "category":"Building & Trades",
            "subcategory":"Construction",
            "type":"Services"
        }
    ],
    "sg:phone":"+61 7 4035 6988",
    "sg:postcode":"4870",
    "sg:province":"QLD",
    "sg:tags":[
        "window",
        "aluminium"
    ],
    "wof:name":"Boral Window Systems-Dowell",
    "wof:placetype":"venue"
},
  "geometry": {"coordinates":[145.761962891,-16.9412612915],"type":"Point"}
}