{
  "type": "Feature",
  "properties": {
    "iso:country":"AU",
    "sg:address":"PO Box 1249",
    "sg:city":"Cairns",
    "sg:classifiers":[
        {
            "category":"Home & Garden",
            "subcategory":"Building Materials",
            "type":"Retail Goods"
        }
    ],
    "sg:phone":"+61 413 405 267",
    "sg:postcode":"4870",
    "sg:province":"QLD",
    "sg:tags":[
        "decorative",
        "coating"
    ],
    "wof:name":"TLC Decorative Texture Coatings",
    "wof:placetype":"venue"
},
  "geometry": {"coordinates":[145.66958618199999,-17.0185699463],"type":"Point"}
}