{
  "type": "Feature",
  "properties": {
    "addr:full":"Rear 347 Barrenjoey Rd Newport NSW 2106",
    "addr:housenumber":"347",
    "addr:postcode":"2106",
    "addr:street":"Barrenjoey Rd",
    "iso:country":"AU",
    "sg:address":"Rear 347 Barrenjoey Rd",
    "sg:city":"Newport",
    "sg:classifiers":[
        {
            "category":"Health Services",
            "subcategory":"Health Practitioner",
            "type":"Services"
        }
    ],
    "sg:phone":"+61 2 9907 0742",
    "sg:postcode":"2106",
    "sg:province":"NSW",
    "sg:tags":[
        "pathologist",
        "speech"
    ],
    "wof:name":"Clark Rebecca",
    "wof:placetype":"venue"
},
  "geometry": {"coordinates":[151.32005310100001,-33.6551475525],"type":"Point"}
}