{
  "type": "Feature",
  "properties": {
    "addr:full":"5 Kiata Crt Mt Eliza VIC 3930",
    "addr:housenumber":"5",
    "addr:postcode":"3930",
    "addr:street":"Kiata Crt",
    "iso:country":"AU",
    "sg:address":"5 Kiata Crt",
    "sg:city":"Mt Eliza",
    "sg:classifiers":[
        {
            "category":"Building & Trades",
            "subcategory":"Cleaning & Sanitation",
            "type":"Services"
        }
    ],
    "sg:phone":"+61 403 850 653",
    "sg:postcode":"3930",
    "sg:province":"VIC",
    "sg:tags":[
        "window"
    ],
    "wof:name":"Fussy Window Cleaning",
    "wof:placetype":"venue"
},
  "geometry": {"coordinates":[145.083129883,-38.196346283],"type":"Point"}
}