{
  "type": "Feature",
  "properties": {
    "addr:full":"39 Gamon St Yarraville VIC 3013",
    "addr:housenumber":"39",
    "addr:postcode":"3013",
    "addr:street":"Gamon St",
    "iso:country":"AU",
    "sg:address":"39 Gamon St",
    "sg:city":"Yarraville",
    "sg:classifiers":[
        {
            "category":"Home & Garden",
            "subcategory":"Furniture",
            "type":"Retail Goods"
        }
    ],
    "sg:phone":"+61 433 931 283",
    "sg:postcode":"3013",
    "sg:province":"VIC",
    "sg:tags":[
        "repair",
        "restoration"
    ],
    "wof:name":"As Good As Old",
    "wof:placetype":"venue"
},
  "geometry": {"coordinates":[144.89028930699999,-37.8082847595],"type":"Point"}
}