{
  "type": "Feature",
  "properties": {
    "iso:country":"AU",
    "sg:address":"220a Clovelly Rd",
    "sg:city":"Clovelly",
    "sg:classifiers":[
        {
            "category":"Food & Beverages",
            "subcategory":"Fruits & Vegetables",
            "type":"Retail Goods"
        }
    ],
    "sg:phone":"+61 2 9665 8362",
    "sg:postcode":"2031",
    "sg:province":"NSW",
    "sg:tags":[
        "greengrocer",
        "fruiterer"
    ],
    "wof:name":"Denavis",
    "wof:placetype":"venue"
},
  "geometry": {"coordinates":[151.254669189,-33.9116706848],"type":"Point"}
}