{
  "type": "Feature",
  "properties": {
    "addr:full":"14 York St South Melbourne VIC 3205",
    "addr:housenumber":"14",
    "addr:postcode":"3205",
    "addr:street":"York St",
    "iso:country":"AU",
    "sg:address":"14 York St",
    "sg:city":"South Melbourne",
    "sg:classifiers":[
        {
            "category":"Banks & Credit Unions",
            "subcategory":"Investment Brokerage",
            "type":"Services"
        }
    ],
    "sg:phone":"+61 3 9695 8666",
    "sg:postcode":"3205",
    "sg:province":"VIC",
    "sg:tags":[
        "finance",
        "broker"
    ],
    "wof:name":"Rapid Finance (Aust) Pty Ltd",
    "wof:placetype":"venue"
},
  "geometry": {"coordinates":[144.962875,-37.829678],"type":"Point"}
}