{
  "type": "Feature",
  "properties": {
    "iso:country":"AU",
    "sg:address":"42 Ingleston St",
    "sg:city":"Wynnum West",
    "sg:classifiers":[
        {
            "category":"Education",
            "subcategory":"Music School",
            "type":"Public Place"
        }
    ],
    "sg:phone":"+61 7 3348 7116",
    "sg:postcode":"4178",
    "sg:province":"QLD",
    "sg:tags":[
        "teacher"
    ],
    "wof:name":"Small Darren",
    "wof:placetype":"venue"
},
  "geometry": {"coordinates":[153.15672302199999,-27.4441318512],"type":"Point"}
}