{
  "type": "Feature",
  "properties": {
    "addr:full":"53 Puckle St Moonee Ponds VIC 3039",
    "addr:housenumber":"53",
    "addr:postcode":"3039",
    "addr:street":"Puckle St",
    "iso:country":"AU",
    "sg:address":"53 Puckle St",
    "sg:city":"Moonee Ponds",
    "sg:classifiers":[
        {
            "category":"Shopping",
            "subcategory":"Clothing, Apparel, & Fashions",
            "type":"Retail Goods"
        }
    ],
    "sg:phone":"+61 3 9370 0808",
    "sg:postcode":"3039",
    "sg:province":"VIC",
    "sg:tags":[
        "lady",
        "wear"
    ],
    "wof:name":"Absolute Fashion Pty Limited",
    "wof:placetype":"venue"
},
  "geometry": {"coordinates":[144.92274499999999,-37.766998],"type":"Point"}
}