{
  "type": "Feature",
  "properties": {
    "iso:country":"AU",
    "sg:address":"361 Swan St",
    "sg:city":"Richmond",
    "sg:classifiers":[
        {
            "category":"Home & Garden",
            "subcategory":"Carpets & Floor Coverings",
            "type":"Retail Goods"
        }
    ],
    "sg:phone":"+61 3 9421 5144",
    "sg:postcode":"3121",
    "sg:province":"VIC",
    "wof:name":"AAA Simon Carpets",
    "wof:placetype":"venue"
},
  "geometry": {"coordinates":[145.00526428200001,-37.8263206482],"type":"Point"}
}