{
  "type": "Feature",
  "properties": {
    "addr:full":"768 Boundary Rd Coopers Plains QLD 4108",
    "addr:housenumber":"768",
    "addr:postcode":"4108",
    "addr:street":"Boundary Rd",
    "iso:country":"AU",
    "sg:address":"768 Boundary Rd",
    "sg:city":"Coopers Plains",
    "sg:classifiers":[
        {
            "category":"School Buses",
            "type":"Transportation"
        }
    ],
    "sg:phone":"+61 7 3246 5600",
    "sg:postcode":"4108",
    "sg:province":"QLD",
    "sg:tags":[
        "brick"
    ],
    "wof:name":"Monier PGH",
    "wof:placetype":"venue"
},
  "geometry": {"coordinates":[153.02708435100001,-27.5686683655],"type":"Point"}
}