{
  "type": "Feature",
  "properties": {
    "iso:country":"AU",
    "sg:address":"Shp1/ 6 Newman Ave",
    "sg:city":"Camp Hill",
    "sg:classifiers":[
        {
            "category":"Arts & Performance",
            "subcategory":"Art Gallery",
            "type":"Entertainment"
        }
    ],
    "sg:phone":"+61 7 3398 9370",
    "sg:postcode":"4152",
    "sg:province":"QLD",
    "wof:name":"Creativity Centre The",
    "wof:placetype":"venue"
},
  "geometry": {"coordinates":[153.06817626899999,-27.4975643158],"type":"Point"}
}