{
  "type": "Feature",
  "properties": {
    "addr:full":"Vaux St Cowra NSW 2794",
    "addr:postcode":"2794",
    "addr:street":"Vaux St",
    "iso:country":"AU",
    "sg:address":"Vaux St",
    "sg:city":"Cowra",
    "sg:classifiers":[
        {
            "category":"Wholesale",
            "subcategory":"Fruits & Vegetables",
            "type":"Manufacturing & Wholesale Goods"
        }
    ],
    "sg:phone":"+61 2 6342 2911",
    "sg:postcode":"2794",
    "sg:province":"NSW",
    "sg:tags":[
        "produce",
        "grain"
    ],
    "wof:name":"Lucerne Foods Pty Ltd Cowra",
    "wof:placetype":"venue"
},
  "geometry": {"coordinates":[148.69029235799999,-33.836643219],"type":"Point"}
}