{
  "type": "Feature",
  "properties": {
    "iso:country":"AU",
    "sg:address":"65 Hunter St",
    "sg:city":"Newcastle",
    "sg:classifiers":[
        {
            "category":"Restaurant",
            "type":"Food & Drink"
        }
    ],
    "sg:phone":"+61 2 4929 5961",
    "sg:postcode":"2300",
    "sg:province":"NSW",
    "wof:name":"Bali Corner",
    "wof:placetype":"venue"
},
  "geometry": {"coordinates":[151.783615,-32.927753],"type":"Point"}
}