{
  "type": "Feature",
  "properties": {
    "addr:full":"65 Humevale Rd Whittlesea VIC 3757",
    "addr:housenumber":"65",
    "addr:postcode":"3757",
    "addr:street":"Humevale Rd",
    "iso:country":"AU",
    "sg:address":"65 Humevale Rd",
    "sg:city":"Whittlesea",
    "sg:classifiers":[
        {
            "category":"Retail",
            "subcategory":"Auto Repair",
            "type":"Services"
        }
    ],
    "sg:phone":"+61 3 9716 2819",
    "sg:postcode":"3757",
    "sg:province":"VIC",
    "sg:tags":[
        "beater",
        "painter",
        "panel"
    ],
    "wof:name":"Van Weenan & Sons",
    "wof:placetype":"venue"
},
  "geometry": {"coordinates":[145.16246000000001,-37.495483],"type":"Point"}
}