{
  "type": "Feature",
  "properties": {
    "addr:full":"1 Nicholson St Melbourne VIC 3000",
    "addr:housenumber":"1",
    "addr:postcode":"3000",
    "addr:street":"Nicholson St",
    "iso:country":"AU",
    "sg:address":"1 Nicholson St",
    "sg:city":"Melbourne",
    "sg:classifiers":[
        {
            "category":"Wholesale",
            "subcategory":"Drugs",
            "type":"Manufacturing & Wholesale Goods"
        }
    ],
    "sg:phone":"+61 3 9665 7111",
    "sg:postcode":"3000",
    "sg:province":"VIC",
    "sg:tags":[
        "wholesaler",
        "pharmaceutical",
        "product",
        "mfrs"
    ],
    "wof:name":"ICI Australia Operations Pty Ltd",
    "wof:placetype":"venue"
},
  "geometry": {"coordinates":[144.953567505,-37.8135299683],"type":"Point"}
}