{
  "type": "Feature",
  "properties": {
    "addr:full":"4 Layton Pl Mill Park VIC 3082",
    "addr:housenumber":"4",
    "addr:postcode":"3082",
    "addr:street":"Pl",
    "iso:country":"AU",
    "sg:address":"4 Layton Pl",
    "sg:city":"Mill Park",
    "sg:classifiers":[
        {
            "category":"Professional",
            "subcategory":"Art Services",
            "type":"Services"
        }
    ],
    "sg:phone":"+61 3 9437 6358",
    "sg:postcode":"3082",
    "sg:province":"VIC",
    "sg:tags":[
        "graphic",
        "designer"
    ],
    "wof:name":"Colour Max",
    "wof:placetype":"venue"
},
  "geometry": {"coordinates":[145.05305480999999,-37.6728096008],"type":"Point"}
}