{
  "type": "Feature",
  "properties": {
    "iso:country":"AU",
    "sg:address":"108 Delta St",
    "sg:city":"Geebung",
    "sg:classifiers":[
        {
            "category":"Commercial Area",
            "type":"Public Place"
        }
    ],
    "sg:phone":"+61 7 3265 7033",
    "sg:postcode":"4034",
    "sg:province":"QLD",
    "sg:tags":[
        "heavy",
        "carrier"
    ],
    "wof:name":"Emerald Carrying Co",
    "wof:placetype":"venue"
},
  "geometry": {"coordinates":[153.053223,-27.366371],"type":"Point"}
}