{
  "type": "Feature",
  "properties": {
    "addr:full":"56 Karalta Rd Erina NSW 2250",
    "addr:housenumber":"56",
    "addr:postcode":"2250",
    "addr:street":"Karalta Rd",
    "iso:country":"AU",
    "sg:address":"56 Karalta Rd",
    "sg:city":"Erina",
    "sg:classifiers":[
        {
            "category":"Health Services",
            "subcategory":"Doctor",
            "type":"Services"
        }
    ],
    "sg:phone":"+61 2 4365 2983",
    "sg:postcode":"2250",
    "sg:province":"NSW",
    "sg:tags":[
        "medical",
        "practitioner"
    ],
    "wof:name":"Charters Hayley Dr",
    "wof:placetype":"venue"
},
  "geometry": {"coordinates":[151.38911438,-33.4392852783],"type":"Point"}
}