{
  "type": "Feature",
  "properties": {
    "iso:country":"AU",
    "sg:address":"Cairns Specialist Medical Centre Unit 5 193-197 Lake St",
    "sg:city":"Cairns",
    "sg:classifiers":[
        {
            "category":"Health Services",
            "subcategory":"Doctor",
            "type":"Services"
        }
    ],
    "sg:phone":"+61 7 4051 6366",
    "sg:postcode":"4870",
    "sg:province":"QLD",
    "sg:tags":[
        "medical",
        "practitioner"
    ],
    "wof:name":"Wells John L",
    "wof:placetype":"venue"
},
  "geometry": {"coordinates":[145.77012634299999,-16.9156475067],"type":"Point"}
}