{
  "type": "Feature",
  "properties": {
    "addr:full":"Wilson St West End (Townsville) QLD 4810",
    "addr:postcode":"4810",
    "addr:street":"Wilson St",
    "iso:country":"AU",
    "sg:address":"Wilson St",
    "sg:city":"West End (Townsville)",
    "sg:classifiers":[
        {
            "category":"Education",
            "subcategory":"School",
            "type":"Public Place"
        }
    ],
    "sg:phone":"+61 7 4750 7222",
    "sg:postcode":"4810",
    "sg:province":"QLD",
    "sg:tags":[
        "state",
        "except",
        "nsw"
    ],
    "wof:name":"Townsville West Primary",
    "wof:placetype":"venue"
},
  "geometry": {"coordinates":[146.80444299999999,-19.266731],"type":"Point"}
}