{
  "type": "Feature",
  "properties": {
    "addr:full":"1a Jersey Pde Carnegie VIC 3163",
    "addr:housenumber":"1a",
    "addr:postcode":"3163",
    "addr:street":"Jersey Pde",
    "iso:country":"AU",
    "sg:address":"1a Jersey Pde",
    "sg:city":"Carnegie",
    "sg:classifiers":[
        {
            "category":"Insurance",
            "subcategory":"Life Insurance",
            "type":"Services"
        }
    ],
    "sg:phone":"+61 3 9569 4319",
    "sg:postcode":"3163",
    "sg:province":"VIC",
    "wof:name":"G J Thomson & Associates",
    "wof:placetype":"venue"
},
  "geometry": {"coordinates":[145.057662964,-37.8872489929],"type":"Point"}
}