{
  "type": "Feature",
  "properties": {
    "iso:country":"AU",
    "sg:address":"126 Weaponess Rd",
    "sg:city":"Wembley Downs",
    "sg:classifiers":[
        {
            "category":"Social Services",
            "subcategory":"Child Care",
            "type":"Services"
        }
    ],
    "sg:phone":"+61 8 9245 3255",
    "sg:postcode":"6019",
    "sg:province":"WA",
    "wof:name":"Mulberry Tree Childcare",
    "wof:placetype":"venue"
},
  "geometry": {"coordinates":[115.773376465,-31.910068512],"type":"Point"}
}