{
  "type": "Feature",
  "properties": {
    "addr:full":"180 Mcfarlane Rd Yinnar VIC 3869",
    "addr:housenumber":"180",
    "addr:postcode":"3869",
    "addr:street":"Mcfarlane Rd",
    "iso:country":"AU",
    "sg:address":"180 Mcfarlane Rd",
    "sg:city":"Yinnar",
    "sg:classifiers":[
        {
            "category":"Professional",
            "subcategory":"Art Services",
            "type":"Services"
        }
    ],
    "sg:phone":"+61 3 5163 1391",
    "sg:postcode":"3869",
    "sg:province":"VIC",
    "sg:tags":[
        "decorator",
        "painter"
    ],
    "wof:name":"Brush&#039;n Awesome",
    "wof:placetype":"venue"
},
  "geometry": {"coordinates":[146.341888428,-38.309135437],"type":"Point"}
}