{
  "type": "Feature",
  "properties": {
    "iso:country":"AU",
    "sg:address":"166 High St",
    "sg:city":"Avoca",
    "sg:classifiers":[
        {
            "category":"Professional",
            "type":"Services"
        }
    ],
    "sg:phone":"+61 3 5465 3174",
    "sg:postcode":"3467",
    "sg:province":"VIC",
    "sg:tags":[
        "transport"
    ],
    "wof:name":"Barkers Transport Service",
    "wof:placetype":"venue"
},
  "geometry": {"coordinates":[143.473678589,-37.0858917236],"type":"Point"}
}