{
  "type": "Feature",
  "properties": {
    "addr:full":"4 Calais Crt Sydenham VIC 3037",
    "addr:housenumber":"4",
    "addr:postcode":"3037",
    "addr:street":"Calais Crt",
    "iso:country":"AU",
    "sg:address":"4 Calais Crt",
    "sg:city":"Sydenham",
    "sg:classifiers":[
        {
            "category":"Building & Trades",
            "subcategory":"Plumbing",
            "type":"Services"
        }
    ],
    "sg:phone":"+61 416 150 126",
    "sg:postcode":"3037",
    "sg:province":"VIC",
    "sg:tags":[
        "plumber",
        "gasfitters"
    ],
    "wof:name":"Hillside Plumbing & Gasfitting Service",
    "wof:placetype":"venue"
},
  "geometry": {"coordinates":[144.761673,-37.698612],"type":"Point"}
}