{
  "type": "Feature",
  "properties": {
    "addr:full":"14 Benbroke Ave Mont Albert North VIC 3129",
    "addr:housenumber":"14",
    "addr:postcode":"3129",
    "addr:street":"Benbroke Ave",
    "iso:country":"AU",
    "sg:address":"14 Benbroke Ave",
    "sg:city":"Mont Albert North",
    "sg:classifiers":[
        {
            "category":"Building & Trades",
            "subcategory":"Landscaping Services",
            "type":"Services"
        }
    ],
    "sg:phone":"+61 419 200 116",
    "sg:postcode":"3129",
    "sg:province":"VIC",
    "sg:tags":[
        "designer",
        "landscape",
        "contractor"
    ],
    "wof:name":"Imperial Gardens",
    "wof:placetype":"venue"
},
  "geometry": {"coordinates":[145.11460876500001,-37.8014411926],"type":"Point"}
}