{
  "type": "Feature",
  "properties": {
    "addr:full":"351 King St Newtown NSW 2042",
    "addr:housenumber":"351",
    "addr:postcode":"2042",
    "addr:street":"King St",
    "iso:country":"AU",
    "sg:address":"351 King St",
    "sg:city":"Newtown",
    "sg:classifiers":[
        {
            "category":"Personal",
            "subcategory":"Tattoo Parlor",
            "type":"Services"
        }
    ],
    "sg:phone":"+61 2 9557 0002",
    "sg:postcode":"2042",
    "sg:province":"NSW",
    "sg:tags":[
        "tattooing"
    ],
    "wof:name":"Skin Deep Tattoo",
    "wof:placetype":"venue"
},
  "geometry": {"coordinates":[151.17802399999999,-33.898388],"type":"Point"}
}