{
  "type": "Feature",
  "properties": {
    "addr:full":"Ulawanna Drv Goondiwindi QLD 4390",
    "addr:postcode":"4390",
    "addr:street":"Ulawanna Drv",
    "iso:country":"AU",
    "sg:address":"Ulawanna Drv",
    "sg:city":"Goondiwindi",
    "sg:classifiers":[
        {
            "category":"Building & Trades",
            "subcategory":"Construction",
            "type":"Services"
        }
    ],
    "sg:phone":"+61 7 4671 0768",
    "sg:postcode":"4390",
    "sg:province":"QLD",
    "sg:tags":[
        "fencing",
        "contractor"
    ],
    "wof:name":"SMC Contractors",
    "wof:placetype":"venue"
},
  "geometry": {"coordinates":[150.27813720699999,-28.5389938354],"type":"Point"}
}