{
  "type": "Feature",
  "properties": {
    "iso:country":"AU",
    "sg:address":"8 Marden St",
    "sg:city":"Artarmon",
    "sg:classifiers":[
        {
            "category":"Home & Garden",
            "subcategory":"Building Materials",
            "type":"Retail Goods"
        }
    ],
    "sg:phone":"+61 2 9439 7744",
    "sg:postcode":"2064",
    "sg:province":"NSW",
    "sg:tags":[
        "pre-mixed",
        "concrete"
    ],
    "wof:name":"CSR Readymix",
    "wof:placetype":"venue"
},
  "geometry": {"coordinates":[151.17965698200001,-33.8137130737],"type":"Point"}
}