{
  "type": "Feature",
  "properties": {
    "addr:full":"49 Oaklands Rd Somerton Park SA 5044",
    "addr:housenumber":"49",
    "addr:postcode":"5044",
    "addr:street":"Oaklands Rd",
    "iso:country":"AU",
    "sg:address":"49 Oaklands Rd",
    "sg:city":"Somerton Park",
    "sg:classifiers":[
        {
            "category":"Retail",
            "subcategory":"Laundry & Dry Cleaning",
            "type":"Services"
        }
    ],
    "sg:phone":"+61 8 8376 0588",
    "sg:postcode":"5044",
    "sg:province":"SA",
    "wof:name":"All Laundry & Linen Pty Ltd",
    "wof:placetype":"venue"
},
  "geometry": {"coordinates":[138.52728271500001,-34.9970092773],"type":"Point"}
}