{
  "type": "Feature",
  "properties": {
    "iso:country":"AU",
    "sg:address":"PO Box 631 Collins St",
    "sg:city":"West Melbourne West Melbourne",
    "sg:classifiers":[
        {
            "category":"Utilities",
            "subcategory":"Telephone",
            "type":"Services"
        }
    ],
    "sg:phone":"+61 1300 858 585",
    "sg:postcode":"3003",
    "sg:province":"VIC",
    "wof:name":"Primus Telecom",
    "wof:placetype":"venue"
},
  "geometry": {"coordinates":[144.93093872099999,-37.8105697632],"type":"Point"}
}