{
  "type": "Feature",
  "properties": {
    "addr:full":"40 Elm Park Drv Hoppers Crossing VIC 3029",
    "addr:housenumber":"40",
    "addr:postcode":"3029",
    "addr:street":"Elm Park Drv",
    "iso:country":"AU",
    "sg:address":"40 Elm Park Drv",
    "sg:city":"Hoppers Crossing",
    "sg:classifiers":[
        {
            "category":"Building & Trades",
            "subcategory":"Construction",
            "type":"Services"
        }
    ],
    "sg:phone":"+61 3 9748 3555",
    "sg:postcode":"3029",
    "sg:province":"VIC",
    "sg:tags":[
        "contractor"
    ],
    "wof:name":"Walker Construction",
    "wof:placetype":"venue"
},
  "geometry": {"coordinates":[144.71859699999999,-37.871429],"type":"Point"}
}