{
  "type": "Feature",
  "properties": {
    "iso:country":"AU",
    "sg:address":"212 Balaclava Rd",
    "sg:city":"Caulfield",
    "sg:classifiers":[
        {
            "category":"Professional",
            "subcategory":"Detective & Security Services",
            "type":"Services"
        }
    ],
    "sg:phone":"+61 3 9570 1990",
    "sg:postcode":"3162",
    "sg:province":"VIC",
    "sg:tags":[
        "domestic",
        "alarm",
        "commercial",
        "burglar"
    ],
    "wof:name":"Ultra Security",
    "wof:placetype":"venue"
},
  "geometry": {"coordinates":[145.023040772,-37.8723068237],"type":"Point"}
}