{
  "type": "Feature",
  "properties": {
    "addr:full":"2 Baron St Cooma NSW 2630",
    "addr:housenumber":"2",
    "addr:postcode":"2630",
    "addr:street":"Baron St",
    "iso:country":"AU",
    "sg:address":"2 Baron St",
    "sg:city":"Cooma",
    "sg:classifiers":[
        {
            "category":"Retail",
            "subcategory":"Auto Repair",
            "type":"Services"
        }
    ],
    "sg:phone":"+61 2 6452 5671",
    "sg:postcode":"2630",
    "sg:province":"NSW",
    "sg:tags":[
        "beater",
        "painter",
        "panel"
    ],
    "wof:name":"Tonini G & N",
    "wof:placetype":"venue"
},
  "geometry": {"coordinates":[149.135665894,-36.2395439148],"type":"Point"}
}