{
  "type": "Feature",
  "properties": {
    "iso:country":"AU",
    "sg:address":"740 Cabramatta Rd",
    "sg:city":"Bonnyrigg",
    "sg:classifiers":[
        {
            "category":"Food & Beverages",
            "subcategory":"Supermarket",
            "type":"Retail Goods"
        }
    ],
    "sg:phone":"+61 2 9610 6525",
    "sg:postcode":"2177",
    "sg:province":"NSW",
    "sg:tags":[
        "grocery",
        "store"
    ],
    "wof:name":"Cut Price Food Markets",
    "wof:placetype":"venue"
},
  "geometry": {"coordinates":[150.889068603,-33.8931350708],"type":"Point"}
}