{
  "type": "Feature",
  "properties": {
    "iso:country":"AU",
    "sg:address":"10-12 Aspen Crt",
    "sg:city":"Morayfield",
    "sg:classifiers":[
        {
            "category":"Professional",
            "subcategory":"Printing & Photocopies",
            "type":"Services"
        }
    ],
    "sg:phone":"+61 7 3886 9692",
    "sg:postcode":"4506",
    "sg:province":"QLD",
    "sg:tags":[
        "laminating"
    ],
    "wof:name":"Sprint Print & Laminating",
    "wof:placetype":"venue"
},
  "geometry": {"coordinates":[152.92344665499999,-27.1622486115],"type":"Point"}
}