{
  "type": "Feature",
  "properties": {
    "addr:full":"Bow St Merriwa NSW 2329",
    "addr:postcode":"2329",
    "addr:street":"Bow St",
    "iso:country":"AU",
    "sg:address":"Bow St",
    "sg:city":"Merriwa",
    "sg:classifiers":[
        {
            "category":"Education",
            "subcategory":"School",
            "type":"Public Place"
        }
    ],
    "sg:phone":"+61 2 6548 2119",
    "sg:postcode":"2329",
    "sg:province":"NSW",
    "sg:tags":[
        "state",
        "-",
        "nsw"
    ],
    "wof:name":"Merriwa Central School",
    "wof:placetype":"venue"
},
  "geometry": {"coordinates":[150.35325622600001,-32.1396636963],"type":"Point"}
}