{
  "type": "Feature",
  "properties": {
    "addr:full":"PO Box 724 Goulburn NSW 2580",
    "addr:postcode":"2580",
    "iso:country":"AU",
    "sg:address":"PO Box 724",
    "sg:city":"Goulburn",
    "sg:classifiers":[
        {
            "category":"Retail",
            "subcategory":"Repair Shop",
            "type":"Services"
        }
    ],
    "sg:phone":"+61 2 4822 8898",
    "sg:postcode":"2580",
    "sg:province":"NSW",
    "sg:tags":[
        "machine",
        "repairs",
        "part",
        "dryer",
        "washing"
    ],
    "wof:name":"H & M Appliance Repairs",
    "wof:placetype":"venue"
},
  "geometry": {"coordinates":[149.716262817,-34.7571792603],"type":"Point"}
}