{
  "type": "Feature",
  "properties": {
    "addr:full":"Shp 45, St Ives Shopping Centre Goodna QLD 4300",
    "addr:housenumber":"45",
    "addr:postcode":"4300",
    "iso:country":"AU",
    "sg:address":"Shp 45, St",
    "sg:city":"Ives Shopping Centre Goodna",
    "sg:classifiers":[
        {
            "category":"Shopping",
            "subcategory":"Clothing, Apparel, & Fashions",
            "type":"Retail Goods"
        }
    ],
    "sg:phone":"+61 7 3288 2665",
    "sg:postcode":"4300",
    "sg:province":"QLD",
    "sg:tags":[
        "lady",
        "wear"
    ],
    "wof:name":"Penni Fashions",
    "wof:placetype":"venue"
},
  "geometry": {"coordinates":[152.97096252399999,-27.6296195984],"type":"Point"}
}