{
  "type": "Feature",
  "properties": {
    "addr:full":"Cnr L Graylands & Warrnambool Rd Cobden VIC 3266",
    "addr:postcode":"3266",
    "addr:street":"Cnr L;Rd",
    "iso:country":"AU",
    "sg:address":"Cnr L Graylands & Warrnambool Rd",
    "sg:city":"Cobden",
    "sg:classifiers":[
        {
            "category":"Wholesale",
            "subcategory":"Farm Supplies",
            "type":"Manufacturing & Wholesale Goods"
        }
    ],
    "sg:phone":"+61 3 5558 2500",
    "sg:postcode":"3266",
    "sg:province":"VIC",
    "sg:tags":[
        "feed",
        "supplement",
        "stock"
    ],
    "wof:name":"Ausfeed",
    "wof:placetype":"venue"
},
  "geometry": {"coordinates":[143.057006836,-38.3365592957],"type":"Point"}
}