{
  "type": "Feature",
  "properties": {
    "addr:full":"Thomas St Chermside QLD 4032",
    "addr:postcode":"qld 4032",
    "addr:street":"Thomas St",
    "iso:country":"AU",
    "sg:address":"Thomas St",
    "sg:city":"Chermside",
    "sg:classifiers":[
        {
            "category":"Retail",
            "subcategory":"Auto Repair",
            "type":"Services"
        }
    ],
    "sg:phone":"+61 7 3248 3333",
    "sg:postcode":"4032",
    "sg:province":"QLD",
    "sg:tags":[
        "repairer",
        "motor",
        "engineer"
    ],
    "wof:name":"Byrne Ford Pty Ltd",
    "wof:placetype":"venue"
},
  "geometry": {"coordinates":[153.03228799999999,-27.387291],"type":"Point"}
}