{
  "type": "Feature",
  "properties": {
    "iso:country":"AU",
    "sg:address":"47 Forest St",
    "sg:city":"Woodend",
    "sg:classifiers":[
        {
            "category":"Organizations",
            "subcategory":"Non-profit Organization",
            "type":"Services"
        }
    ],
    "sg:phone":"+61 3 5427 1000",
    "sg:postcode":"3442",
    "sg:province":"VIC",
    "sg:tags":[
        "environmental",
        "organisation",
        "conservation"
    ],
    "wof:name":"Woodend Sustainable Living Community The",
    "wof:placetype":"venue"
},
  "geometry": {"coordinates":[144.52865600600001,-37.3546943665],"type":"Point"}
}