{
  "type": "Feature",
  "properties": {
    "addr:full":"Great Southern Hwy Katanning WA 6317",
    "addr:postcode":"6317",
    "addr:street":"Great Southern Hwy",
    "iso:country":"AU",
    "sg:address":"Great Southern Hwy",
    "sg:city":"Katanning",
    "sg:classifiers":[
        {
            "category":"Retail",
            "subcategory":"Veterinary Services",
            "type":"Services"
        }
    ],
    "sg:phone":"+61 8 9821 1655",
    "sg:postcode":"6317",
    "sg:province":"WA",
    "sg:tags":[
        "surgeon"
    ],
    "wof:name":"Katanning Regional Veterinary Hospital",
    "wof:placetype":"venue"
},
  "geometry": {"coordinates":[117.549026489,-33.6978683472],"type":"Point"}
}