{
  "type": "Feature",
  "properties": {
    "iso:country":"AU",
    "sg:address":"D'Aguilar Hwy",
    "sg:city":"Kilcoy",
    "sg:classifiers":[
        {
            "category":"Home & Garden",
            "subcategory":"Building Materials",
            "type":"Retail Goods"
        }
    ],
    "sg:phone":"+61 7 5497 1858",
    "sg:postcode":"4515",
    "sg:province":"QLD",
    "sg:tags":[
        "fencing"
    ],
    "wof:name":"Easy Lock",
    "wof:placetype":"venue"
},
  "geometry": {"coordinates":[152.545593,-26.945066],"type":"Point"}
}