{
  "type": "Feature",
  "properties": {
    "addr:full":"48 Peppertree Drv Erskine Park NSW 2759",
    "addr:housenumber":"48",
    "addr:postcode":"2759",
    "addr:street":"Peppertree Drv",
    "iso:country":"AU",
    "sg:address":"48 Peppertree Drv",
    "sg:city":"Erskine Park",
    "sg:classifiers":[
        {
            "category":"Shopping",
            "subcategory":"Clothing, Apparel, & Fashions",
            "type":"Retail Goods"
        }
    ],
    "sg:phone":"+61 2 9834 4039",
    "sg:postcode":"2759",
    "sg:province":"NSW",
    "sg:tags":[
        "hire",
        "men's",
        "wear",
        "formal"
    ],
    "wof:name":"Formalwear Express",
    "wof:placetype":"venue"
},
  "geometry": {"coordinates":[150.802536011,-33.8044891357],"type":"Point"}
}