{
  "type": "Feature",
  "properties": {
    "addr:full":"221 Lindsay Rd Buderim QLD 4556",
    "addr:housenumber":"221",
    "addr:postcode":"4556",
    "addr:street":"Lindsay Rd",
    "iso:country":"AU",
    "sg:address":"221 Lindsay Rd",
    "sg:city":"Buderim",
    "sg:classifiers":[
        {
            "category":"Manufacturing",
            "subcategory":"Pottery",
            "type":"Manufacturing & Wholesale Goods"
        }
    ],
    "sg:phone":"+61 7 5445 4223",
    "sg:postcode":"4556",
    "sg:province":"QLD",
    "wof:name":"M & J Pugh",
    "wof:placetype":"venue"
},
  "geometry": {"coordinates":[153.04071044899999,-26.6785526276],"type":"Point"}
}