{
  "type": "Feature",
  "properties": {
    "addr:full":"Ste151a/ 211 La Trobe St Melbourne VIC 3000",
    "addr:housenumber":"211",
    "addr:postcode":"3000",
    "addr:street":"La Trobe St",
    "iso:country":"AU",
    "sg:address":"Ste151a/ 211 La Trobe St",
    "sg:city":"Melbourne",
    "sg:classifiers":[
        {
            "category":"Ice Cream",
            "type":"Food & Drink"
        }
    ],
    "sg:phone":"+61 3 9654 4188",
    "sg:postcode":"3000",
    "sg:province":"VIC",
    "sg:tags":[
        "retail"
    ],
    "wof:name":"Lix Pty Ltd",
    "wof:placetype":"venue"
},
  "geometry": {"coordinates":[144.963424683,-37.8098258972],"type":"Point"}
}