{
  "type": "Feature",
  "properties": {
    "iso:country":"AU",
    "sg:address":"1st Floor, Suite 49",
    "sg:city":", Colonial Arcade, Hay Street, Port Macquarie",
    "sg:classifiers":[
        {
            "category":"Banks & Credit Unions",
            "subcategory":"Financial Services",
            "type":"Services"
        }
    ],
    "sg:phone":"+61 2 6583 5377",
    "sg:postcode":"2444",
    "sg:province":"NSW",
    "sg:tags":[
        "planning"
    ],
    "wof:name":"Advantage Financial Services",
    "wof:placetype":"venue"
},
  "geometry": {"coordinates":[152.909515,-31.429291],"type":"Point"}
}