{
  "type": "Feature",
  "properties": {
    "addr:full":"43 Kembla St Fyshwick ACT 2609",
    "addr:housenumber":"43",
    "addr:postcode":"2609",
    "addr:street":"Kembla St",
    "iso:country":"AU",
    "sg:address":"43 Kembla St",
    "sg:city":"Fyshwick",
    "sg:classifiers":[
        {
            "category":"Home & Garden",
            "subcategory":"Household Appliances",
            "type":"Retail Goods"
        }
    ],
    "sg:phone":"+61 2 6280 8199",
    "sg:postcode":"2609",
    "sg:province":"ACT",
    "sg:tags":[
        "heating",
        "system"
    ],
    "wof:name":"Warmtech Heating Systems",
    "wof:placetype":"venue"
},
  "geometry": {"coordinates":[149.17706298799999,-35.3247833252],"type":"Point"}
}