{
  "type": "Feature",
  "properties": {
    "iso:country":"AU",
    "sg:address":"59 Thomsons Rd",
    "sg:city":"Kingsholme",
    "sg:classifiers":[
        {
            "category":"Wholesale",
            "subcategory":"Metals & Minerals",
            "type":"Manufacturing & Wholesale Goods"
        }
    ],
    "sg:phone":"+61 7 5546 6573",
    "sg:postcode":"4208",
    "sg:province":"QLD",
    "sg:tags":[
        "steel",
        "stainless",
        "product",
        "equipment"
    ],
    "wof:name":"Fien Engineering Pty Ltd",
    "wof:placetype":"venue"
},
  "geometry": {"coordinates":[153.240997314,-27.8173217773],"type":"Point"}
}