{
  "type": "Feature",
  "properties": {
    "addr:full":"Level 1, 393 Gardeners St Roseberry NSW 2474",
    "addr:housenumber":"393",
    "addr:postcode":"2474",
    "addr:street":"Gardeners St",
    "iso:country":"AU",
    "sg:address":"Level 1, 393 Gardeners St",
    "sg:city":"Roseberry",
    "sg:classifiers":[
        {
            "category":"Education",
            "subcategory":"Special Training",
            "type":"Public Place"
        }
    ],
    "sg:phone":"+61 2 9341 5624",
    "sg:postcode":"2474",
    "sg:province":"NSW",
    "sg:tags":[
        "tuition-educational"
    ],
    "wof:name":"North Shore Development Centre",
    "wof:placetype":"venue"
},
  "geometry": {"coordinates":[153.18576049800001,-28.6896190643],"type":"Point"}
}