{
  "type": "Feature",
  "properties": {
    "addr:full":"29 James Small Drv Korora NSW 2450",
    "addr:housenumber":"29",
    "addr:postcode":"2450",
    "addr:street":"James Small Drv",
    "iso:country":"AU",
    "sg:address":"29 James Small Drv",
    "sg:city":"Korora",
    "sg:classifiers":[
        {
            "category":"Building & Trades",
            "subcategory":"Construction",
            "type":"Services"
        }
    ],
    "sg:phone":"+61 2 6653 6250",
    "sg:postcode":"2450",
    "sg:province":"NSW",
    "sg:tags":[
        "contractor"
    ],
    "wof:name":"Bennett Michael",
    "wof:placetype":"venue"
},
  "geometry": {"coordinates":[153.13351440400001,-30.2531547546],"type":"Point"}
}