{
  "type": "Feature",
  "properties": {
    "addr:full":"PO BOX 290 Manly NSW 2095",
    "addr:postcode":"2095",
    "iso:country":"AU",
    "sg:address":"PO BOX 290",
    "sg:city":"Manly",
    "sg:classifiers":[
        {
            "category":"Professional",
            "subcategory":"Computer Services",
            "type":"Services"
        }
    ],
    "sg:postcode":"NSW 2095",
    "sg:tags":[
        "surfing",
        "surf-forecast"
    ],
    "sg:website":"http://globalsurfari.com",
    "wof:name":"Global Surfari",
    "wof:placetype":"venue"
},
  "geometry": {"coordinates":[151.28804,-33.797144],"type":"Point"}
}