{
  "type": "Feature",
  "properties": {
    "iso:country":"AU",
    "sg:address":"Ste1/ 1 Elizabeth Ave",
    "sg:city":"Mascot",
    "sg:classifiers":[
        {
            "category":"Building & Trades",
            "subcategory":"Construction",
            "type":"Services"
        }
    ],
    "sg:phone":"+61 2 9667 4841",
    "sg:postcode":"2020",
    "sg:province":"NSW",
    "sg:tags":[
        "contractor"
    ],
    "wof:name":"Vcorp Constructions",
    "wof:placetype":"venue"
},
  "geometry": {"coordinates":[151.19380188,-33.9312057495],"type":"Point"}
}