{
  "type": "Feature",
  "properties": {
    "addr:full":"50 Korong Rd Heidelberg West VIC 3081",
    "addr:housenumber":"50",
    "addr:postcode":"3081",
    "addr:street":"Korong Rd",
    "iso:country":"AU",
    "sg:address":"50 Korong Rd",
    "sg:city":"Heidelberg West",
    "sg:classifiers":[
        {
            "category":"Shopping",
            "subcategory":"Computers & Home Electronics",
            "type":"Retail Goods"
        }
    ],
    "sg:phone":"+61 3 9455 2044",
    "sg:postcode":"3081",
    "sg:province":"VIC",
    "sg:tags":[
        "equipment",
        "supply"
    ],
    "wof:name":"Melbourne Corporate Business Services",
    "wof:placetype":"venue"
},
  "geometry": {"coordinates":[145.047119141,-37.7332305908],"type":"Point"}
}