{
  "type": "Feature",
  "properties": {
    "iso:country":"AU",
    "sg:address":"2 Albert St",
    "sg:city":"Williamstown",
    "sg:classifiers":[
        {
            "category":"Arts & Performance",
            "subcategory":"Theater",
            "type":"Entertainment"
        }
    ],
    "sg:phone":"+61 3 9397 6705",
    "sg:postcode":"3016",
    "sg:province":"VIC",
    "sg:tags":[
        "theatre"
    ],
    "wof:name":"Williamstown Little Theatre",
    "wof:placetype":"venue"
},
  "geometry": {"coordinates":[144.896026611,-37.8533172607],"type":"Point"}
}