{
  "type": "Feature",
  "properties": {
    "iso:country":"AU",
    "sg:address":"6 Ludlow Rd",
    "sg:city":"Castle Hill",
    "sg:classifiers":[
        {
            "category":"Professional",
            "subcategory":"Computer Services",
            "type":"Services"
        }
    ],
    "sg:phone":"+61 414 334 889",
    "sg:postcode":"2154",
    "sg:province":"NSW",
    "sg:tags":[
        "consultant",
        "system"
    ],
    "wof:name":"XP Electronics",
    "wof:placetype":"venue"
},
  "geometry": {"coordinates":[151.00944519000001,-33.7361412048],"type":"Point"}
}