{
  "type": "Feature",
  "properties": {
    "addr:full":"28 Reynolds Crt Burpengary QLD 4505",
    "addr:housenumber":"28",
    "addr:postcode":"4505",
    "addr:street":"Reynolds Crt",
    "iso:country":"AU",
    "sg:address":"28 Reynolds Crt",
    "sg:city":"Burpengary",
    "sg:classifiers":[
        {
            "category":"Building & Trades",
            "subcategory":"Equipment Rental",
            "type":"Services"
        }
    ],
    "sg:phone":"+61 427 010 865",
    "sg:postcode":"4505",
    "sg:province":"QLD",
    "sg:tags":[
        "crane",
        "hire"
    ],
    "wof:name":"Caboolture Crane Hire",
    "wof:placetype":"venue"
},
  "geometry": {"coordinates":[152.98098754899999,-27.160528183],"type":"Point"}
}