{
  "type": "Feature",
  "properties": {
    "iso:country":"AU",
    "sg:address":"Shop 1/ 237 Hamilton Rd",
    "sg:city":"Coogee",
    "sg:classifiers":[
        {
            "category":"Communications",
            "subcategory":"Film & Video Production",
            "type":"Services"
        }
    ],
    "sg:phone":"+61 8 9434 6656",
    "sg:postcode":"6166",
    "sg:province":"WA",
    "sg:tags":[
        "dvd",
        "library"
    ],
    "wof:name":"Network Video Coogee",
    "wof:placetype":"venue"
},
  "geometry": {"coordinates":[115.774849,-32.112583],"type":"Point"}
}