{
  "type": "Feature",
  "properties": {
    "addr:full":"16 Mosey St (Cnr Rimmer Rd) Landsdale WA 6065",
    "addr:housenumber":"16",
    "addr:postcode":"6065",
    "addr:street":"Mosey St Cnr Rimmer Rd",
    "iso:country":"AU",
    "sg:address":"16 Mosey St (Cnr Rimmer Rd)",
    "sg:city":"Landsdale",
    "sg:classifiers":[
        {
            "category":"Retail",
            "subcategory":"Auto Repair",
            "type":"Services"
        }
    ],
    "sg:phone":"+61 8 9409 9944",
    "sg:postcode":"6065",
    "sg:province":"WA",
    "sg:tags":[
        "beater",
        "painter",
        "panel"
    ],
    "wof:name":"Adaptable Panel Beaters",
    "wof:placetype":"venue"
},
  "geometry": {"coordinates":[115.84105682400001,-31.8030662537],"type":"Point"}
}