{
  "type": "Feature",
  "properties": {
    "addr:full":"Ste 12/ 325 Pitt St Sydney NSW 2000",
    "addr:housenumber":"/ 325",
    "addr:postcode":"2000",
    "addr:street":"Pitt St",
    "iso:country":"AU",
    "sg:address":"Ste 12/ 325 Pitt St",
    "sg:city":"Sydney",
    "sg:classifiers":[
        {
            "category":"Professional",
            "subcategory":"Computer Services",
            "type":"Services"
        }
    ],
    "sg:phone":"+61 2 9283 8844",
    "sg:postcode":"2000",
    "sg:province":"NSW",
    "sg:tags":[
        "package",
        "software"
    ],
    "wof:name":"Charm Solutions",
    "wof:placetype":"venue"
},
  "geometry": {"coordinates":[151.207855225,-33.8741722107],"type":"Point"}
}