{
  "type": "Feature",
  "properties": {
    "iso:country":"AU",
    "sg:address":"Level 1/ 63 Majors Bay Rd",
    "sg:city":"Concord",
    "sg:classifiers":[
        {
            "category":"Real Estate",
            "subcategory":"Real Estate Agent",
            "type":"Services"
        }
    ],
    "sg:phone":"+61 2 9743 3553",
    "sg:postcode":"2137",
    "sg:province":"NSW",
    "wof:name":"Ray White Concord",
    "wof:placetype":"venue"
},
  "geometry": {"coordinates":[151.10340881400001,-33.8560600281],"type":"Point"}
}