{
  "type": "Feature",
  "properties": {
    "addr:full":"Suite 1, Level 1, 1 Newcastle St Rose Bay NSW 2029",
    "addr:housenumber":"1",
    "addr:postcode":"2029",
    "addr:street":"Newcastle St",
    "iso:country":"AU",
    "sg:address":"Suite 1, Level 1, 1 Newcastle St",
    "sg:city":"Rose Bay",
    "sg:classifiers":[
        {
            "category":"Building & Trades",
            "subcategory":"Equipment Rental",
            "type":"Services"
        }
    ],
    "sg:phone":"+61 412 222 222",
    "sg:postcode":"2029",
    "sg:province":"NSW",
    "sg:tags":[
        "supply",
        "catering"
    ],
    "wof:name":"Absolute Cafe Equipment",
    "wof:placetype":"venue"
},
  "geometry": {"coordinates":[151.26934814399999,-33.8701553345],"type":"Point"}
}