{
  "type": "Feature",
  "properties": {
    "addr:full":"102 Anderson St Geraldton WA 6530",
    "addr:housenumber":"102",
    "addr:postcode":"6530",
    "addr:street":"Anderson St",
    "iso:country":"AU",
    "sg:address":"102 Anderson St",
    "sg:city":"Geraldton",
    "sg:classifiers":[
        {
            "category":"Retail",
            "subcategory":"Auto Repair",
            "type":"Services"
        }
    ],
    "sg:phone":"+61 8 9964 3500",
    "sg:postcode":"6530",
    "sg:province":"WA",
    "sg:tags":[
        "repairer",
        "motor",
        "engineer"
    ],
    "wof:name":"Burney's Auto Repairs",
    "wof:placetype":"venue"
},
  "geometry": {"coordinates":[114.634002685,-28.7509708405],"type":"Point"}
}