{
  "type": "Feature",
  "properties": {
    "addr:full":"10a Stuart Rd Dulwich SA 5065",
    "addr:housenumber":"10a",
    "addr:postcode":"5065",
    "addr:street":"Stuart Rd",
    "iso:country":"AU",
    "sg:address":"10a Stuart Rd",
    "sg:city":"Dulwich",
    "sg:classifiers":[
        {
            "category":"Professional",
            "subcategory":"Business Services",
            "type":"Services"
        }
    ],
    "sg:phone":"+61 8 8331 7966",
    "sg:postcode":"5065",
    "sg:province":"SA",
    "sg:tags":[
        "consultant",
        "promoter",
        "entertainment"
    ],
    "wof:name":"Star Entertainment Pty Ltd",
    "wof:placetype":"venue"
},
  "geometry": {"coordinates":[138.631515503,-34.9355354309],"type":"Point"}
}