{
  "type": "Feature",
  "properties": {
    "addr:full":"PO Box 1066 Pearcedale VIC 3912",
    "addr:postcode":"3912",
    "iso:country":"AU",
    "sg:address":"PO Box 1066",
    "sg:city":"Pearcedale",
    "sg:classifiers":[
        {
            "category":"Building & Trades",
            "subcategory":"Construction",
            "type":"Services"
        }
    ],
    "sg:phone":"+61 3 5978 7450",
    "sg:postcode":"3912",
    "sg:province":"VIC",
    "sg:tags":[
        "mural"
    ],
    "wof:name":"3 Dog Design",
    "wof:placetype":"venue"
},
  "geometry": {"coordinates":[145.23365783700001,-38.2027511597],"type":"Point"}
}