{
  "type": "Feature",
  "properties": {
    "addr:full":"PO Box 4505 Lake Haven NSW 2263",
    "addr:postcode":"2263",
    "addr:street":"Lake",
    "iso:country":"AU",
    "sg:address":"PO Box 4505",
    "sg:city":"Lake Haven",
    "sg:classifiers":[
        {
            "category":"Shopping",
            "subcategory":"Bicycles & Sporting Goods",
            "type":"Retail Goods"
        }
    ],
    "sg:phone":"+61 416 041 617",
    "sg:postcode":"2263",
    "sg:province":"NSW",
    "sg:tags":[
        "chemical",
        "equipment",
        "pool",
        "swimming"
    ],
    "wof:name":"Manstone",
    "wof:placetype":"venue"
},
  "geometry": {"coordinates":[151.500137,-33.243938],"type":"Point"}
}