{
  "type": "Feature",
  "properties": {
    "iso:country":"AU",
    "sg:address":"PO Box 839",
    "sg:city":"Geelong",
    "sg:classifiers":[
        {
            "category":"Building & Trades",
            "subcategory":"Plumbing",
            "type":"Services"
        }
    ],
    "sg:phone":"+61 3 5221 7753",
    "sg:postcode":"3220",
    "sg:province":"VIC",
    "sg:tags":[
        "plumber",
        "gasfitters"
    ],
    "wof:name":"O'Brien G.L. Plumbing Pty Ltd",
    "wof:placetype":"venue"
},
  "geometry": {"coordinates":[144.346054,-38.157108],"type":"Point"}
}