{
  "type": "Feature",
  "properties": {
    "addr:full":"12 Johnston St Annandale NSW 2038",
    "addr:housenumber":"12",
    "addr:postcode":"2038",
    "addr:street":"Johnston St",
    "iso:country":"AU",
    "sg:address":"12 Johnston St",
    "sg:city":"Annandale",
    "sg:classifiers":[
        {
            "category":"Home & Garden",
            "subcategory":"Furniture",
            "type":"Retail Goods"
        }
    ],
    "sg:phone":"+61 2 9569 0711",
    "sg:postcode":"2038",
    "sg:province":"NSW",
    "sg:tags":[
        "outdoor"
    ],
    "wof:name":"Reuben's Barbeques & Heating",
    "wof:placetype":"venue"
},
  "geometry": {"coordinates":[151.167694092,-33.8874855042],"type":"Point"}
}