{
  "type": "Feature",
  "properties": {
    "addr:full":"275 Myers St Geelong East VIC 3219",
    "addr:housenumber":"275",
    "addr:postcode":"3219",
    "addr:street":"Myers St",
    "iso:country":"AU",
    "sg:address":"275 Myers St",
    "sg:city":"Geelong East",
    "sg:classifiers":[
        {
            "category":"Health Services",
            "subcategory":"Health Practitioner",
            "type":"Services"
        }
    ],
    "sg:phone":"+61 3 5222 1113",
    "sg:postcode":"3219",
    "sg:province":"VIC",
    "sg:tags":[
        "herbalist"
    ],
    "wof:name":"Lim Seng Heng",
    "wof:placetype":"venue"
},
  "geometry": {"coordinates":[144.372512817,-38.1551055908],"type":"Point"}
}