{
  "type": "Feature",
  "properties": {
    "iso:country":"AU",
    "sg:address":"PO Box 150",
    "sg:city":"Edge Hill",
    "sg:classifiers":[
        {
            "category":"Education",
            "subcategory":"Dance Studio",
            "type":"Public Place"
        }
    ],
    "sg:phone":"+61 7 4034 1414",
    "sg:postcode":"4870",
    "sg:province":"QLD",
    "sg:tags":[
        "venue",
        "tuition"
    ],
    "wof:name":"Cheeky Monkey Club",
    "wof:placetype":"venue"
},
  "geometry": {"coordinates":[145.740066528,-16.9015407562],"type":"Point"}
}