{
  "type": "Feature",
  "properties": {
    "addr:full":"1 Penna Rd Macclesfield SA 5153",
    "addr:housenumber":"1",
    "addr:postcode":"5153",
    "addr:street":"Penna Rd",
    "iso:country":"AU",
    "sg:address":"1 Penna Rd",
    "sg:city":"Macclesfield",
    "sg:classifiers":[
        {
            "category":"Wholesale",
            "subcategory":"Machinery & Supplies",
            "type":"Manufacturing & Wholesale Goods"
        }
    ],
    "sg:phone":"+61 418 840 773",
    "sg:postcode":"5153",
    "sg:province":"SA",
    "sg:tags":[
        "instrument",
        "scientific"
    ],
    "wof:name":"Scientific Equipment Repairs",
    "wof:placetype":"venue"
},
  "geometry": {"coordinates":[138.842926025,-35.1698646545],"type":"Point"}
}