{
  "type": "Feature",
  "properties": {
    "addr:full":"Cnr Gordon & Elisabeth Sts Ararat VIC 3377",
    "addr:housenumber":"cnr",
    "addr:postcode":"3377",
    "addr:street":"Gordon",
    "iso:country":"AU",
    "sg:address":"Cnr Gordon & Elisabeth Sts",
    "sg:city":"Ararat",
    "sg:classifiers":[
        {
            "category":"Mining & Drilling",
            "type":"Manufacturing & Wholesale Goods"
        }
    ],
    "sg:phone":"+61 3 5352 2482",
    "sg:postcode":"3377",
    "sg:province":"VIC",
    "sg:tags":[
        "boring",
        "contractor"
    ],
    "wof:name":"KHS Contract",
    "wof:placetype":"venue"
},
  "geometry": {"coordinates":[142.93130493199999,-37.2824211121],"type":"Point"}
}