{
  "type": "Feature",
  "properties": {
    "addr:full":"Shop 28, Baylis St (Opp Woolworths) The Marketplace Wagga Wagga NSW 2650",
    "addr:housenumber":"shop 28",
    "addr:postcode":"2650",
    "addr:street":"Baylis St Opp Woolworths The",
    "iso:country":"AU",
    "sg:address":"Shop 28, Baylis St (Opp Woolworths) The Marketplace",
    "sg:city":"Wagga Wagga",
    "sg:classifiers":[
        {
            "category":"Travel",
            "subcategory":"Travel Agent",
            "type":"Entertainment"
        }
    ],
    "sg:phone":"+61 2 6921 2000",
    "sg:postcode":"2650",
    "sg:province":"NSW",
    "sg:tags":[
        "consultant"
    ],
    "wof:name":"Harvey World Travel - Wagga Wagga",
    "wof:placetype":"venue"
},
  "geometry": {"coordinates":[147.36915588400001,-35.1179275513],"type":"Point"}
}