{
  "type": "Feature",
  "properties": {
    "addr:full":"145- 147 Weld St Beaconsfield TAS 7270",
    "addr:housenumber":"147",
    "addr:postcode":"7270",
    "addr:street":"Weld St",
    "iso:country":"AU",
    "sg:address":"145- 147 Weld St",
    "sg:city":"Beaconsfield",
    "sg:classifiers":[
        {
            "category":"Travel",
            "subcategory":"Hotels & Motels",
            "type":"Entertainment"
        }
    ],
    "sg:phone":"+61 3 6383 1191",
    "sg:postcode":"7270",
    "sg:province":"TAS",
    "sg:tags":[
        "accommodation"
    ],
    "wof:name":"Club Hotel",
    "wof:placetype":"venue"
},
  "geometry": {"coordinates":[146.81512451200001,-41.1992988586],"type":"Point"}
}