{
  "type": "Feature",
  "properties": {
    "addr:full":"9 Warman St Wanneroo North WA 6065",
    "addr:housenumber":"9",
    "addr:postcode":"6065",
    "addr:street":"Warman St;North",
    "iso:country":"AU",
    "sg:address":"9 Warman St",
    "sg:city":"Wanneroo North",
    "sg:classifiers":[
        {
            "category":"Home & Garden",
            "subcategory":"Building Materials",
            "type":"Retail Goods"
        }
    ],
    "sg:phone":"+61 8 9404 6111",
    "sg:postcode":"6065",
    "sg:province":"WA",
    "sg:tags":[
        "roofing"
    ],
    "wof:name":"The Truss Factory",
    "wof:placetype":"venue"
},
  "geometry": {"coordinates":[115.784667969,-31.7202148438],"type":"Point"}
}