{
  "type": "Feature",
  "properties": {
    "iso:country":"AU",
    "sg:address":"22 Kyabra St",
    "sg:city":"Newstead",
    "sg:classifiers":[
        {
            "category":"Professional",
            "subcategory":"Engineering",
            "type":"Services"
        }
    ],
    "sg:phone":"+61 7 3216 0616",
    "sg:postcode":"4006",
    "sg:province":"QLD",
    "sg:tags":[
        "consulting",
        "engineer"
    ],
    "wof:name":"CLA Consultants",
    "wof:placetype":"venue"
},
  "geometry": {"coordinates":[153.04275512699999,-27.4513835907],"type":"Point"}
}