{
  "type": "Feature",
  "properties": {
    "addr:full":"14 Ashton Ave Claremont WA 6010",
    "addr:housenumber":"14",
    "addr:postcode":"6010",
    "addr:street":"Ashton Ave",
    "iso:country":"AU",
    "sg:address":"14 Ashton Ave",
    "sg:city":"Claremont",
    "sg:classifiers":[
        {
            "category":"Health Services",
            "subcategory":"Health Practitioner",
            "type":"Services"
        }
    ],
    "sg:phone":"+61 8 9380 9077",
    "sg:postcode":"6010",
    "sg:province":"WA",
    "sg:tags":[
        "psychologist"
    ],
    "wof:name":"Rudge Dr Ruth and John Rudge",
    "wof:placetype":"venue"
},
  "geometry": {"coordinates":[115.788291931,-31.9728965759],"type":"Point"}
}