{
  "type": "Feature",
  "properties": {
    "iso:country":"AU",
    "sg:address":"13 Industry Crt",
    "sg:city":"Lilydale",
    "sg:classifiers":[
        {
            "category":"Manufacturing",
            "subcategory":"Metals",
            "type":"Manufacturing & Wholesale Goods"
        }
    ],
    "sg:phone":"+61 3 9735 0744",
    "sg:postcode":"3140",
    "sg:province":"VIC",
    "sg:tags":[
        "cutting"
    ],
    "wof:name":"Castella Sheet Metal",
    "wof:placetype":"venue"
},
  "geometry": {"coordinates":[145.35377502399999,-37.7486610413],"type":"Point"}
}