{
  "type": "Feature",
  "properties": {
    "addr:full":"PO Box 556 Richlands QLD 4077",
    "addr:postcode":"4077",
    "iso:country":"AU",
    "sg:address":"PO Box 556",
    "sg:city":"Richlands",
    "sg:classifiers":[
        {
            "category":"Bus Stop",
            "subcategory":"None",
            "type":"Transportation"
        }
    ],
    "sg:phone":"+61 7 3712 7000",
    "sg:postcode":"4077",
    "sg:province":"QLD",
    "sg:tags":[
        "galvanising",
        "tinning"
    ],
    "wof:name":"John Holland Pty Ltd",
    "wof:placetype":"venue"
},
  "geometry": {"coordinates":[152.95428466800001,-27.5964202881],"type":"Point"}
}