{
  "type": "Feature",
  "properties": {
    "addr:full":"45 Hoddle St Richmond VIC 3121",
    "addr:housenumber":"45",
    "addr:postcode":"3121",
    "addr:street":"Hoddle St",
    "iso:country":"AU",
    "sg:address":"45 Hoddle St",
    "sg:city":"Richmond",
    "sg:classifiers":[
        {
            "category":"Fast Food",
            "type":"Food & Drink"
        }
    ],
    "sg:phone":"+61 3 9417 5526",
    "sg:postcode":"3121",
    "sg:province":"VIC",
    "sg:tags":[
        "away",
        "take"
    ],
    "wof:name":"Hungry Jacks Pty Ltd",
    "wof:placetype":"venue"
},
  "geometry": {"coordinates":[144.991287231,-37.8113136292],"type":"Point"}
}