{
  "type": "Feature",
  "properties": {
    "iso:country":"AU",
    "sg:address":"29 Hotham St",
    "sg:city":"St Kilda East",
    "sg:classifiers":[
        {
            "category":"Education",
            "subcategory":"Music School",
            "type":"Public Place"
        }
    ],
    "sg:phone":"+61 3 9527 4257",
    "sg:postcode":"3183",
    "sg:province":"VIC",
    "sg:tags":[
        "teacher"
    ],
    "wof:name":"Tania Chalko",
    "wof:placetype":"venue"
},
  "geometry": {"coordinates":[145.00047302199999,-37.8630065918],"type":"Point"}
}