{
  "type": "Feature",
  "properties": {
    "addr:full":"18 Burrawang St Cherrybrook NSW 2126",
    "addr:housenumber":"18",
    "addr:postcode":"2126",
    "addr:street":"Burrawang St",
    "iso:country":"AU",
    "sg:address":"18 Burrawang St",
    "sg:city":"Cherrybrook",
    "sg:classifiers":[
        {
            "category":"Professional",
            "subcategory":"Computer Services",
            "type":"Services"
        }
    ],
    "sg:phone":"+61 2 9875 5522",
    "sg:postcode":"2126",
    "sg:province":"NSW",
    "sg:tags":[
        "consultant",
        "system"
    ],
    "wof:name":"Nexcorp Offshore Technology",
    "wof:placetype":"venue"
},
  "geometry": {"coordinates":[151.05308532699999,-33.7112884521],"type":"Point"}
}