{
  "type": "Feature",
  "properties": {
    "addr:full":"Cnr Albion & Endeavour Sts Oberon NSW 2787",
    "addr:postcode":"2787",
    "addr:street":"Cnr;Sts Oberon",
    "iso:country":"AU",
    "sg:address":"Cnr Albion & Endeavour Sts",
    "sg:city":"Oberon",
    "sg:classifiers":[
        {
            "category":"Wholesale",
            "subcategory":"Farm Supplies",
            "type":"Manufacturing & Wholesale Goods"
        }
    ],
    "sg:phone":"+61 2 6336 1800",
    "sg:postcode":"2787",
    "sg:province":"NSW",
    "sg:tags":[
        "equipment"
    ],
    "wof:name":"Aprilla Stock Grids",
    "wof:placetype":"venue"
},
  "geometry": {"coordinates":[149.86082458499999,-33.6992645264],"type":"Point"}
}