{
  "type": "Feature",
  "properties": {
    "iso:country":"AU",
    "sg:address":"56 Sunnybank Rd",
    "sg:city":"Lisarow",
    "sg:classifiers":[
        {
            "category":"Home & Garden",
            "subcategory":"Furniture",
            "type":"Retail Goods"
        }
    ],
    "sg:phone":"+61 2 4329 5599",
    "sg:postcode":"2250",
    "sg:province":"NSW",
    "sg:tags":[
        "business"
    ],
    "wof:name":"Office Furniture Design",
    "wof:placetype":"venue"
},
  "geometry": {"coordinates":[151.359573364,-33.3780441284],"type":"Point"}
}