{
  "type": "Feature",
  "properties": {
    "addr:full":"The &#039; Stables&#039; Salisbury St Uralla NSW 2358",
    "addr:postcode":"2358",
    "addr:street":"Salisbury St",
    "iso:country":"AU",
    "sg:address":"The &#039; Stables&#039; Salisbury St",
    "sg:city":"Uralla",
    "sg:classifiers":[
        {
            "category":"Professional",
            "subcategory":"Accounting & Tax Preparation",
            "type":"Services"
        }
    ],
    "sg:phone":"+61 2 6778 4333",
    "sg:postcode":"2358",
    "sg:province":"NSW",
    "sg:tags":[
        "accountant",
        "auditor"
    ],
    "wof:name":"Press Carl",
    "wof:placetype":"venue"
},
  "geometry": {"coordinates":[151.49873352,-30.641500473],"type":"Point"}
}