{
  "type": "Feature",
  "properties": {
    "addr:full":"Shop 221/ Dandenong Plz Dandenong VIC 3175",
    "addr:housenumber":"221 / dandenong",
    "addr:postcode":"3175",
    "addr:street":"Plz",
    "iso:country":"AU",
    "sg:address":"Shop 221/ Dandenong Plz",
    "sg:city":"Dandenong",
    "sg:classifiers":[
        {
            "category":"Shopping",
            "subcategory":"Clothing, Apparel, & Fashions",
            "type":"Retail Goods"
        }
    ],
    "sg:phone":"+61 3 9792 0922",
    "sg:postcode":"3175",
    "sg:province":"VIC",
    "sg:tags":[
        "lady",
        "wear"
    ],
    "wof:name":"Unik Clothing",
    "wof:placetype":"venue"
},
  "geometry": {"coordinates":[145.200042725,-37.9915618896],"type":"Point"}
}