{
  "type": "Feature",
  "properties": {
    "addr:full":"Brisbane St Ipswich QLD 4305",
    "addr:postcode":"4305",
    "addr:street":"St",
    "iso:country":"AU",
    "sg:address":"Brisbane St",
    "sg:city":"Ipswich",
    "sg:classifiers":[
        {
            "category":"Education",
            "subcategory":"School",
            "type":"Public Place"
        }
    ],
    "sg:phone":"+61 7 3810 4333",
    "sg:postcode":"4305",
    "sg:province":"QLD",
    "sg:tags":[
        "state",
        "except",
        "nsw"
    ],
    "wof:name":"Churchill State Preschool",
    "wof:placetype":"venue"
},
  "geometry": {"coordinates":[152.760375977,-27.6144561768],"type":"Point"}
}