{
  "type": "Feature",
  "properties": {
    "addr:full":"12 Potts St East Brisbane QLD 4169",
    "addr:housenumber":"12",
    "addr:postcode":"4169",
    "addr:street":"Potts St",
    "iso:country":"AU",
    "sg:address":"12 Potts St",
    "sg:city":"East Brisbane",
    "sg:classifiers":[
        {
            "category":"Professional",
            "subcategory":"Computer Services",
            "type":"Services"
        }
    ],
    "sg:phone":"+61 7 3891 2547",
    "sg:postcode":"4169",
    "sg:province":"QLD",
    "sg:tags":[
        "training"
    ],
    "wof:name":"A 1 Advice Faultline",
    "wof:placetype":"venue"
},
  "geometry": {"coordinates":[153.040847778,-27.4864349365],"type":"Point"}
}