{
  "type": "Feature",
  "properties": {
    "iso:country":"AU",
    "sg:address":"48 Fenwick St",
    "sg:city":"Portarlington",
    "sg:classifiers":[
        {
            "category":"Shopping",
            "subcategory":"Antiques",
            "type":"Retail Goods"
        }
    ],
    "sg:phone":"+61 3 5259 1417",
    "sg:postcode":"3223",
    "sg:province":"VIC",
    "wof:name":"Balla-Wein Antiques",
    "wof:placetype":"venue"
},
  "geometry": {"coordinates":[144.652695,-38.116257],"type":"Point"}
}