{
  "type": "Feature",
  "properties": {
    "iso:country":"AU",
    "sg:address":"1/ 2 Avalon Rd",
    "sg:city":"Marion",
    "sg:classifiers":[
        {
            "category":"Health Services",
            "subcategory":"Health Practitioner",
            "type":"Services"
        }
    ],
    "sg:phone":"+61 8 8177 0563",
    "sg:postcode":"5043",
    "sg:province":"SA",
    "sg:tags":[
        "homoeopath"
    ],
    "wof:name":"Nahid Khalili",
    "wof:placetype":"venue"
},
  "geometry": {"coordinates":[138.556885,-34.999348],"type":"Point"}
}