{
  "type": "Feature",
  "properties": {
    "addr:full":"Market Rd Pottsville Beach NSW 2489",
    "addr:postcode":"2489",
    "addr:street":"Market Rd",
    "iso:country":"AU",
    "sg:address":"Market Rd",
    "sg:city":"Pottsville Beach",
    "sg:classifiers":[
        {
            "category":"Building & Trades",
            "subcategory":"Construction",
            "type":"Services"
        }
    ],
    "sg:phone":"+61 418 770 340",
    "sg:postcode":"2489",
    "sg:province":"NSW",
    "sg:tags":[
        "pool",
        "swimming"
    ],
    "wof:name":"All-Sun Pristine Pools & Patios",
    "wof:placetype":"venue"
},
  "geometry": {"coordinates":[153.564163208,-28.3891506195],"type":"Point"}
}