{
  "type": "Feature",
  "properties": {
    "iso:country":"AU",
    "sg:address":"17 Woodburn St",
    "sg:city":"Evans Head",
    "sg:classifiers":[
        {
            "category":"Fast Food",
            "type":"Food & Drink"
        }
    ],
    "sg:phone":"+61 2 6682 6826",
    "sg:postcode":"2473",
    "sg:province":"NSW",
    "sg:tags":[
        "away",
        "take"
    ],
    "wof:name":"Yates Pizza & Takeaway",
    "wof:placetype":"venue"
},
  "geometry": {"coordinates":[153.43121337900001,-29.1187801361],"type":"Point"}
}