{
  "type": "Feature",
  "properties": {
    "addr:full":"Shed 3 Dau Drv Granville QLD 4650",
    "addr:housenumber":"3",
    "addr:postcode":"4650",
    "addr:street":"Dau Drv",
    "iso:country":"AU",
    "sg:address":"Shed 3 Dau Drv",
    "sg:city":"Granville",
    "sg:classifiers":[
        {
            "category":"Building & Trades",
            "subcategory":"Construction",
            "type":"Services"
        }
    ],
    "sg:phone":"+61 7 4121 4951",
    "sg:postcode":"4650",
    "sg:province":"QLD",
    "sg:tags":[
        "welding"
    ],
    "wof:name":"Granville Aluminium Welding",
    "wof:placetype":"venue"
},
  "geometry": {"coordinates":[152.71551500000001,-25.538303],"type":"Point"}
}