{
  "type": "Feature",
  "properties": {
    "addr:full":"3/ 10 Endeavour Drv Kunda Park QLD 4556",
    "addr:housenumber":"/ 10",
    "addr:postcode":"4556",
    "addr:street":"Endeavour Drv",
    "iso:country":"AU",
    "sg:address":"3/ 10 Endeavour Drv",
    "sg:city":"Kunda Park",
    "sg:classifiers":[
        {
            "category":"Building & Trades",
            "subcategory":"Construction",
            "type":"Services"
        }
    ],
    "sg:phone":"+61 7 5445 4399",
    "sg:postcode":"4556",
    "sg:province":"QLD",
    "sg:tags":[
        "contractor"
    ],
    "wof:name":"Marshall Builders",
    "wof:placetype":"venue"
},
  "geometry": {"coordinates":[153.029663086,-26.6683254242],"type":"Point"}
}