{
  "type": "Feature",
  "properties": {
    "addr:full":"12 Princess St Camp Hill QLD 4152",
    "addr:housenumber":"12",
    "addr:postcode":"4152",
    "addr:street":"Princess St",
    "iso:country":"AU",
    "sg:address":"12 Princess St",
    "sg:city":"Camp Hill",
    "sg:classifiers":[
        {
            "category":"Building & Trades",
            "subcategory":"Landscaping Services",
            "type":"Services"
        }
    ],
    "sg:phone":"+61 7 3278 1997",
    "sg:postcode":"4152",
    "sg:province":"QLD",
    "sg:tags":[
        "gardener"
    ],
    "wof:name":"Jarvis M & M",
    "wof:placetype":"venue"
},
  "geometry": {"coordinates":[153.07548523,-27.4936542511],"type":"Point"}
}