{
  "type": "Feature",
  "properties": {
    "addr:full":"3/ 525 Kings Way Miranda NSW 2228",
    "addr:housenumber":"/ 525",
    "addr:postcode":"2228",
    "addr:street":"Kings Way",
    "iso:country":"AU",
    "sg:address":"3/ 525",
    "sg:city":"Kings Way Miranda",
    "sg:classifiers":[
        {
            "category":"Education",
            "subcategory":"Special Training",
            "type":"Public Place"
        }
    ],
    "sg:phone":"+61 1300 124 125",
    "sg:postcode":"2228",
    "sg:province":"NSW",
    "sg:tags":[
        "development"
    ],
    "wof:name":"Real Coach Pty Ltd",
    "wof:placetype":"venue"
},
  "geometry": {"coordinates":[151.102493286,-34.033908844],"type":"Point"}
}