{
  "type": "Feature",
  "properties": {
    "iso:country":"AU",
    "sg:address":"Lvl1/ 296 St Vincent St",
    "sg:city":"Port Adelaide",
    "sg:classifiers":[
        {
            "category":"Transit Center",
            "subcategory":"Freight",
            "type":"Transportation"
        }
    ],
    "sg:phone":"+61 8 8240 1881",
    "sg:postcode":"5015",
    "sg:province":"SA",
    "sg:tags":[
        "agent",
        "shipping"
    ],
    "wof:name":"OOCL (Australia) Pty Ltd",
    "wof:placetype":"venue"
},
  "geometry": {"coordinates":[138.508743286,-34.8438453674],"type":"Point"}
}