{
  "type": "Feature",
  "properties": {
    "addr:full":"23 Hennessy St Croydon NSW 2132",
    "addr:housenumber":"23",
    "addr:postcode":"2132",
    "addr:street":"Hennessy St",
    "iso:country":"AU",
    "sg:address":"23 Hennessy St",
    "sg:city":"Croydon",
    "sg:classifiers":[
        {
            "category":"Professional",
            "subcategory":"Accounting & Tax Preparation",
            "type":"Services"
        }
    ],
    "sg:phone":"+61 2 9716 9200",
    "sg:postcode":"2132",
    "sg:province":"NSW",
    "sg:tags":[
        "accountant",
        "auditor"
    ],
    "wof:name":"Alex Ebert Financial Services",
    "wof:placetype":"venue"
},
  "geometry": {"coordinates":[151.11640930199999,-33.8831634521],"type":"Point"}
}