{
  "type": "Feature",
  "properties": {
    "addr:full":"57 Montague St North Wollongong NSW 2500",
    "addr:housenumber":"57",
    "addr:postcode":"2500",
    "addr:street":"Montague St North",
    "iso:country":"AU",
    "sg:address":"57 Montague St",
    "sg:city":"North Wollongong",
    "sg:classifiers":[
        {
            "category":"Manufacturing",
            "subcategory":"Furniture",
            "type":"Manufacturing & Wholesale Goods"
        }
    ],
    "sg:phone":"+61 2 4226 3633",
    "sg:postcode":"2500",
    "sg:province":"NSW",
    "sg:tags":[
        "builder",
        "designer",
        "custom"
    ],
    "wof:name":"Betta Industries",
    "wof:placetype":"venue"
},
  "geometry": {"coordinates":[150.895523,-34.40144],"type":"Point"}
}