{
  "type": "Feature",
  "properties": {
    "iso:country":"AU",
    "sg:address":"31 Springvale Rd",
    "sg:city":"Springvale",
    "sg:classifiers":[
        {
            "category":"Food & Beverages",
            "subcategory":"Groceries & Convenience Stores",
            "type":"Retail Goods"
        }
    ],
    "sg:phone":"+61 3 9562 4668",
    "sg:postcode":"3171",
    "sg:province":"VIC",
    "wof:name":"Ampol",
    "wof:placetype":"venue"
},
  "geometry": {"coordinates":[145.155563355,-37.9355926514],"type":"Point"}
}