{
  "type": "Feature",
  "properties": {
    "addr:full":"102 Great Ryrie St Heathmont VIC 3135",
    "addr:housenumber":"102",
    "addr:postcode":"3135",
    "addr:street":"Great Ryrie St",
    "iso:country":"AU",
    "sg:address":"102 Great Ryrie St",
    "sg:city":"Heathmont",
    "sg:classifiers":[
        {
            "category":"Personal",
            "subcategory":"Massage",
            "type":"Services"
        }
    ],
    "sg:phone":"+61 3 9870 1534",
    "sg:postcode":"3135",
    "sg:province":"VIC",
    "sg:tags":[
        "therapy"
    ],
    "wof:name":"AA David W Walker Masseur",
    "wof:placetype":"venue"
},
  "geometry": {"coordinates":[145.23716735799999,-37.8315696716],"type":"Point"}
}