{
  "type": "Feature",
  "properties": {
    "addr:full":"Unit 114/ 95 Rouse St Port Melbourne VIC 3207",
    "addr:housenumber":"/ 95",
    "addr:postcode":"3207",
    "addr:street":"Rouse St",
    "iso:country":"AU",
    "sg:address":"Unit 114/ 95 Rouse St",
    "sg:city":"Port Melbourne",
    "sg:classifiers":[
        {
            "category":"Professional",
            "subcategory":"Accounting & Tax Preparation",
            "type":"Services"
        }
    ],
    "sg:phone":"+61 414 568 532",
    "sg:postcode":"3207",
    "sg:province":"VIC",
    "sg:tags":[
        "consultant",
        "taxation"
    ],
    "wof:name":"Chris Jackson",
    "wof:placetype":"venue"
},
  "geometry": {"coordinates":[144.94117700000001,-37.843262],"type":"Point"}
}