{
  "type": "Feature",
  "properties": {
    "iso:country":"AU",
    "sg:address":"4 Wilga Ave",
    "sg:city":"Selby",
    "sg:classifiers":[
        {
            "category":"Education",
            "subcategory":"Dance Studio",
            "type":"Public Place"
        }
    ],
    "sg:phone":"+61 408 521 734",
    "sg:postcode":"3159",
    "sg:province":"VIC",
    "sg:tags":[
        "venue",
        "tuition"
    ],
    "wof:name":"Arabesque Middle Eastern Dance School",
    "wof:placetype":"venue"
},
  "geometry": {"coordinates":[145.37559509299999,-37.9189147949],"type":"Point"}
}