{
  "type": "Feature",
  "properties": {
    "addr:full":"50 Phillipson St Wangaratta VIC 3677",
    "addr:housenumber":"50",
    "addr:postcode":"3677",
    "addr:street":"Phillipson St",
    "iso:country":"AU",
    "sg:address":"50 Phillipson St",
    "sg:city":"Wangaratta",
    "sg:classifiers":[
        {
            "category":"Building & Trades",
            "subcategory":"Construction",
            "type":"Services"
        }
    ],
    "sg:phone":"+61 3 5721 4621",
    "sg:postcode":"3677",
    "sg:province":"VIC",
    "sg:tags":[
        "monumental",
        "mason"
    ],
    "wof:name":"W H Bussell Memorials",
    "wof:placetype":"venue"
},
  "geometry": {"coordinates":[146.30502319300001,-36.354850769],"type":"Point"}
}