{
  "type": "Feature",
  "properties": {
    "addr:full":"80 Beach Rd Bunbury WA 6230",
    "addr:housenumber":"80",
    "addr:postcode":"6230",
    "addr:street":"Beach Rd",
    "iso:country":"AU",
    "sg:address":"80 Beach Rd",
    "sg:city":"Bunbury",
    "sg:classifiers":[
        {
            "category":"Health Services",
            "subcategory":"Chiropractor",
            "type":"Services"
        }
    ],
    "sg:phone":"+61 8 9721 4500",
    "sg:postcode":"6230",
    "sg:province":"WA",
    "wof:name":"Willmore Damon",
    "wof:placetype":"venue"
},
  "geometry": {"coordinates":[115.636703,-33.336254],"type":"Point"}
}