{
  "type": "Feature",
  "properties": {
    "addr:full":"44 Marcia St Coffs Harbour NSW 2450",
    "addr:housenumber":"44",
    "addr:postcode":"2450",
    "addr:street":"Marcia St",
    "iso:country":"AU",
    "sg:address":"44 Marcia St",
    "sg:city":"Coffs Harbour",
    "sg:classifiers":[
        {
            "category":"Shopping",
            "subcategory":"Mobile Phones",
            "type":"Retail Goods"
        }
    ],
    "sg:phone":"+61 2 6652 4455",
    "sg:postcode":"2450",
    "sg:province":"NSW",
    "sg:tags":[
        "battery",
        "equipment",
        "charging"
    ],
    "wof:name":"Bananacoast Batteries",
    "wof:placetype":"venue"
},
  "geometry": {"coordinates":[153.11965900000001,-30.289818],"type":"Point"}
}