{
  "type": "Feature",
  "properties": {
    "addr:full":"230 Summer St Orange NSW 2800",
    "addr:housenumber":"230",
    "addr:postcode":"2800",
    "addr:street":"Summer St",
    "iso:country":"AU",
    "sg:address":"230 Summer St",
    "sg:city":"Orange",
    "sg:classifiers":[
        {
            "category":"Insurance",
            "subcategory":"Hazard Insurance",
            "type":"Services"
        }
    ],
    "sg:phone":"+61 2 6363 7195",
    "sg:postcode":"2800",
    "sg:province":"NSW",
    "sg:tags":[
        "fire",
        "accident",
        "marine"
    ],
    "wof:name":"Wesfarmers Federation Insurance",
    "wof:placetype":"venue"
},
  "geometry": {"coordinates":[149.099533081,-33.2836380005],"type":"Point"}
}