{
  "type": "Feature",
  "properties": {
    "iso:country":"AU",
    "sg:address":"36 Ainsdale St",
    "sg:city":"Chermside West",
    "sg:classifiers":[
        {
            "category":"Personal",
            "subcategory":"Beauty Salon",
            "type":"Services"
        }
    ],
    "sg:phone":"+61 7 3359 6794",
    "sg:postcode":"4032",
    "sg:province":"QLD",
    "sg:tags":[
        "hairdresser"
    ],
    "wof:name":"Charne Hair Fashions",
    "wof:placetype":"venue"
},
  "geometry": {"coordinates":[153.00962799999999,-27.388477],"type":"Point"}
}