{
  "type": "Feature",
  "properties": {
    "addr:full":"69 Jull St Armadale WA 6112",
    "addr:housenumber":"69",
    "addr:postcode":"6112",
    "addr:street":"Jull St",
    "iso:country":"AU",
    "sg:address":"69 Jull St",
    "sg:city":"Armadale",
    "sg:classifiers":[
        {
            "category":"Fast Food",
            "type":"Food & Drink"
        }
    ],
    "sg:phone":"+61 8 9399 3599",
    "sg:postcode":"6112",
    "sg:province":"WA",
    "sg:tags":[
        "away",
        "take"
    ],
    "wof:name":"McDonald's Family Restaurants",
    "wof:placetype":"venue"
},
  "geometry": {"coordinates":[116.020782471,-32.1502876282],"type":"Point"}
}