{
  "type": "Feature",
  "properties": {
    "iso:country":"AU",
    "sg:address":"20 Burrowes St",
    "sg:city":"Golden Square",
    "sg:classifiers":[
        {
            "category":"Organizations",
            "subcategory":"Non-profit Organization",
            "type":"Services"
        }
    ],
    "sg:phone":"+61 3 5441 8535",
    "sg:postcode":"3555",
    "sg:province":"VIC",
    "sg:tags":[
        "support",
        "disability",
        "organisation"
    ],
    "wof:name":"Burrowes Respite House",
    "wof:placetype":"venue"
},
  "geometry": {"coordinates":[144.254180908,-36.7698059082],"type":"Point"}
}