{
  "type": "Feature",
  "properties": {
    "iso:country":"AU",
    "sg:address":"10 Jesmond Rd",
    "sg:city":"Croydon",
    "sg:classifiers":[
        {
            "category":"Retail",
            "subcategory":"Storage",
            "type":"Services"
        }
    ],
    "sg:phone":"+61 3 9724 9333",
    "sg:postcode":"3136",
    "sg:province":"VIC",
    "sg:tags":[
        "removal",
        "furniture"
    ],
    "wof:name":"Maroondah Removals & Storage Pty Ltd",
    "wof:placetype":"venue"
},
  "geometry": {"coordinates":[145.28298950199999,-37.8062744141],"type":"Point"}
}