{
  "type": "Feature",
  "properties": {
    "iso:country":"AU",
    "sg:address":"6 Ryans Crt",
    "sg:city":"Warragul",
    "sg:classifiers":[
        {
            "category":"Professional",
            "subcategory":"Engineering",
            "type":"Services"
        }
    ],
    "sg:phone":"+61 3 5622 1795",
    "sg:postcode":"3820",
    "sg:province":"VIC",
    "sg:tags":[
        "manufacturing",
        "engineer"
    ],
    "wof:name":"J A Engineering",
    "wof:placetype":"venue"
},
  "geometry": {"coordinates":[145.92242400000001,-38.157486],"type":"Point"}
}