{
  "type": "Feature",
  "properties": {
    "addr:full":"Cnr Saltfleet St & Esplanade Port Noarlunga SA 5167",
    "addr:postcode":"5167",
    "addr:street":"Cnr Saltfleet St & Esplanade",
    "iso:country":"AU",
    "sg:address":"Cnr Saltfleet St & Esplanade",
    "sg:city":"Port Noarlunga",
    "sg:classifiers":[
        {
            "category":"Retail",
            "subcategory":"Event Space",
            "type":"Services"
        }
    ],
    "sg:phone":"+61 8 8382 1376",
    "sg:postcode":"5167",
    "sg:province":"SA",
    "sg:tags":[
        "function",
        "organiser"
    ],
    "wof:name":"Port Noarlunga Surf Life Saving Club Incorporated",
    "wof:placetype":"venue"
},
  "geometry": {"coordinates":[138.470825195,-35.1491394043],"type":"Point"}
}