{
  "type": "Feature",
  "properties": {
    "iso:country":"AU",
    "sg:address":"10 Everaise Crt",
    "sg:city":"Laverton North",
    "sg:classifiers":[
        {
            "category":"Wholesale",
            "subcategory":"Auto Parts",
            "type":"Manufacturing & Wholesale Goods"
        }
    ],
    "sg:phone":"+61 3 9931 1090",
    "sg:postcode":"3026",
    "sg:province":"VIC",
    "sg:tags":[
        "recyclers"
    ],
    "wof:name":"Laverton Motor Wreckers",
    "wof:placetype":"venue"
},
  "geometry": {"coordinates":[144.784775,-37.83997],"type":"Point"}
}