{
  "type": "Feature",
  "properties": {
    "addr:full":"GPO Box 186 Brisbane QLD 4001",
    "addr:postcode":"4001",
    "iso:country":"AU",
    "sg:address":"GPO Box 186",
    "sg:city":"Brisbane",
    "sg:classifiers":[
        {
            "category":"Real Estate",
            "subcategory":"Real Estate Agent",
            "type":"Services"
        }
    ],
    "sg:phone":"+61 7 3840 5555",
    "sg:postcode":"4001",
    "sg:province":"QLD",
    "wof:name":"Elders Real Estate",
    "wof:placetype":"venue"
},
  "geometry": {"coordinates":[153.06158447300001,-27.4484176636],"type":"Point"}
}