{
  "type": "Feature",
  "properties": {
    "addr:full":"28 Cheetham St Kalgoorlie WA 6430",
    "addr:housenumber":"28",
    "addr:postcode":"6430",
    "addr:street":"Cheetham St",
    "iso:country":"AU",
    "sg:address":"28 Cheetham St",
    "sg:city":"Kalgoorlie",
    "sg:classifiers":[
        {
            "category":"Real Estate",
            "subcategory":"Real Estate Services",
            "type":"Services"
        }
    ],
    "sg:phone":"+61 8 9021 7711",
    "sg:postcode":"6430",
    "sg:province":"WA",
    "sg:tags":[
        "valuer"
    ],
    "wof:name":"Kalgoorlie City Valuers",
    "wof:placetype":"venue"
},
  "geometry": {"coordinates":[121.469421387,-30.7555904388],"type":"Point"}
}