{
  "type": "Feature",
  "properties": {
    "iso:country":"AU",
    "sg:address":"73 Hanson Rd",
    "sg:city":"Gladstone",
    "sg:classifiers":[
        {
            "category":"Building & Trades",
            "subcategory":"Equipment Rental",
            "type":"Services"
        }
    ],
    "sg:phone":"+61 7 4972 3166",
    "sg:postcode":"4680",
    "sg:province":"QLD",
    "sg:tags":[
        "crane",
        "hire"
    ],
    "wof:name":"Lee Crane Hire",
    "wof:placetype":"venue"
},
  "geometry": {"coordinates":[151.24485778799999,-23.840669632],"type":"Point"}
}