{
  "type": "Feature",
  "properties": {
    "addr:full":"291 The Parade Beulah Park SA 5067",
    "addr:housenumber":"291",
    "addr:postcode":"5067",
    "addr:street":"The Parade",
    "iso:country":"AU",
    "sg:address":"291 The Parade",
    "sg:city":"Beulah Park",
    "sg:classifiers":[
        {
            "category":"Health Services",
            "subcategory":"Doctor",
            "type":"Services"
        }
    ],
    "sg:phone":"+61 8 8364 1133",
    "sg:postcode":"5067",
    "sg:province":"SA",
    "sg:tags":[
        "medical",
        "practitioner"
    ],
    "wof:name":"Parade Medical Centre",
    "wof:placetype":"venue"
},
  "geometry": {"coordinates":[138.64410400400001,-34.9209785461],"type":"Point"}
}