{
  "type": "Feature",
  "properties": {
    "addr:full":"260 Queen St Brisbane QLD 4000",
    "addr:housenumber":"260",
    "addr:postcode":"4000",
    "addr:street":"Queen St",
    "iso:country":"AU",
    "sg:address":"260 Queen St",
    "sg:city":"Brisbane",
    "sg:classifiers":[
        {
            "category":"Professional",
            "subcategory":"Computer Services",
            "type":"Services"
        }
    ],
    "sg:phone":"+61 7 3229 2002",
    "sg:postcode":"4000",
    "sg:province":"QLD",
    "sg:tags":[
        "consultant",
        "system"
    ],
    "wof:name":"Empson Computer Consulting Pty Ltd",
    "wof:placetype":"venue"
},
  "geometry": {"coordinates":[153.02764892600001,-27.4675750732],"type":"Point"}
}