{
  "type": "Feature",
  "properties": {
    "iso:country":"AU",
    "sg:address":"Unit 5, 13 Priestley St",
    "sg:city":"Mittagong",
    "sg:classifiers":[
        {
            "category":"Retail",
            "subcategory":"Auto Repair",
            "type":"Services"
        }
    ],
    "sg:phone":"+61 2 4872 2321",
    "sg:postcode":"2575",
    "sg:province":"NSW",
    "sg:tags":[
        "automotive",
        "air conditioning"
    ],
    "wof:name":"Mittagong Radiators",
    "wof:placetype":"venue"
},
  "geometry": {"coordinates":[150.43486023,-34.4501457214],"type":"Point"}
}