{
  "type": "Feature",
  "properties": {
    "iso:country":"AU",
    "sg:address":"Cnr Burrendah Blvd & Pinetree Gully Rd",
    "sg:city":"Willetton",
    "sg:classifiers":[
        {
            "category":"Health Services",
            "subcategory":"Doctor",
            "type":"Services"
        }
    ],
    "sg:phone":"+61 8 9332 3961",
    "sg:postcode":"6155",
    "sg:province":"WA",
    "sg:tags":[
        "medical",
        "practitioner"
    ],
    "wof:name":"Willetton Medical Centre",
    "wof:placetype":"venue"
},
  "geometry": {"coordinates":[115.88134,-32.055344],"type":"Point"}
}