{
  "type": "Feature",
  "properties": {
    "iso:country":"AU",
    "sg:address":"87 Dower St",
    "sg:city":"Mandurah",
    "sg:classifiers":[
        {
            "category":"Sports & Exercise",
            "subcategory":"Sports Center",
            "type":"Entertainment"
        }
    ],
    "sg:phone":"+61 8 9535 2512",
    "sg:postcode":"6210",
    "sg:province":"WA",
    "sg:tags":[
        "ground"
    ],
    "wof:name":"WA Indoor Beach Volleyball Federation",
    "wof:placetype":"venue"
},
  "geometry": {"coordinates":[115.739952,-32.53046],"type":"Point"}
}