{
  "type": "Feature",
  "properties": {
    "addr:full":"1361 Burke Rd Kew East VIC 3102",
    "addr:housenumber":"1361",
    "addr:postcode":"3102",
    "addr:street":"Burke Rd",
    "iso:country":"AU",
    "sg:address":"1361 Burke Rd",
    "sg:city":"Kew East",
    "sg:classifiers":[
        {
            "category":"Health Services",
            "subcategory":"Doctor",
            "type":"Services"
        }
    ],
    "sg:phone":"+61 3 9817 5250",
    "sg:postcode":"3102",
    "sg:province":"VIC",
    "sg:tags":[
        "occupational",
        "safety"
    ],
    "wof:name":"Stretch Now",
    "wof:placetype":"venue"
},
  "geometry": {"coordinates":[145.06288147000001,-37.7981338501],"type":"Point"}
}