{
  "type": "Feature",
  "properties": {
    "addr:full":"55 Corangamite St Colac VIC 3250",
    "addr:housenumber":"55",
    "addr:postcode":"3250",
    "addr:street":"Corangamite St",
    "iso:country":"AU",
    "sg:address":"55 Corangamite St",
    "sg:city":"Colac",
    "sg:classifiers":[
        {
            "category":"Professional",
            "subcategory":"Printing & Photocopies",
            "type":"Services"
        }
    ],
    "sg:phone":"+61 3 5232 1531",
    "sg:postcode":"3250",
    "sg:province":"VIC",
    "sg:tags":[
        "photocopying"
    ],
    "wof:name":"Colac Printworks",
    "wof:placetype":"venue"
},
  "geometry": {"coordinates":[143.58421300000001,-38.340256],"type":"Point"}
}