{
  "type": "Feature",
  "properties": {
    "addr:full":"Unit 11/ 120 Lake St Northbridge WA 6003",
    "addr:housenumber":"/ 120",
    "addr:postcode":"6003",
    "addr:street":"Lake St",
    "iso:country":"AU",
    "sg:address":"Unit 11/ 120 Lake St",
    "sg:city":"Northbridge",
    "sg:classifiers":[
        {
            "category":"Professional",
            "subcategory":"Employment Agencies",
            "type":"Services"
        }
    ],
    "sg:phone":"+61 8 9328 6555",
    "sg:postcode":"6003",
    "sg:province":"WA",
    "sg:tags":[
        "consultant",
        "casting"
    ],
    "wof:name":"Frog Management",
    "wof:placetype":"venue"
},
  "geometry": {"coordinates":[115.85874176,-31.9449977875],"type":"Point"}
}