{
  "type": "Feature",
  "properties": {
    "iso:country":"AU",
    "sg:address":"91 Rankin St",
    "sg:city":"Forbes",
    "sg:classifiers":[
        {
            "category":"Shopping",
            "subcategory":"Clothing, Apparel, & Fashions",
            "type":"Retail Goods"
        }
    ],
    "sg:phone":"+61 2 6852 3591",
    "sg:postcode":"2871",
    "sg:province":"NSW",
    "sg:tags":[
        "lady",
        "wear"
    ],
    "wof:name":"Bella Donna Boutique",
    "wof:placetype":"venue"
},
  "geometry": {"coordinates":[148.007126,-33.383762],"type":"Point"}
}