{
  "type": "Feature",
  "properties": {
    "addr:full":"114 Tolley Rd St Agnes SA 5097",
    "addr:housenumber":"114",
    "addr:postcode":"5097",
    "addr:street":"Tolley Rd",
    "iso:country":"AU",
    "sg:address":"114 Tolley Rd St",
    "sg:city":"Agnes",
    "sg:classifiers":[
        {
            "category":"Building & Trades",
            "subcategory":"Equipment Rental",
            "type":"Services"
        }
    ],
    "sg:phone":"+61 8 8396 5777",
    "sg:postcode":"5097",
    "sg:province":"SA",
    "sg:tags":[
        "renting",
        "trailer"
    ],
    "wof:name":"U-Haul Trailers Pty Ltd",
    "wof:placetype":"venue"
},
  "geometry": {"coordinates":[138.706787109,-34.8312416077],"type":"Point"}
}