{
  "type": "Feature",
  "properties": {
    "addr:full":"492A High St Penrith NSW 2750",
    "addr:housenumber":"492a",
    "addr:postcode":"2750",
    "addr:street":"High St",
    "iso:country":"AU",
    "sg:address":"492A High St",
    "sg:city":"Penrith",
    "sg:classifiers":[
        {
            "category":"Shopping",
            "subcategory":"Shoes",
            "type":"Retail Goods"
        }
    ],
    "sg:phone":"+61 2 4722 2137",
    "sg:postcode":"2750",
    "sg:province":"NSW",
    "sg:tags":[
        "footwear"
    ],
    "wof:name":"Chicken Express",
    "wof:placetype":"venue"
},
  "geometry": {"coordinates":[150.91554260300001,-33.8949890137],"type":"Point"}
}