{
  "type": "Feature",
  "properties": {
    "iso:country":"AU",
    "sg:address":"664 Parramatta Rd",
    "sg:city":"Ashfield",
    "sg:classifiers":[
        {
            "category":"Retail",
            "subcategory":"Auto Rental",
            "type":"Services"
        }
    ],
    "sg:phone":"+61 2 9716 7052",
    "sg:postcode":"2131",
    "sg:province":"NSW",
    "sg:tags":[
        "bus",
        "truck"
    ],
    "wof:name":"Avis",
    "wof:placetype":"venue"
},
  "geometry": {"coordinates":[151.123703003,-33.8717689514],"type":"Point"}
}