{
  "type": "Feature",
  "properties": {
    "addr:full":"1120 Beechwood Drv Hope Island QLD 4212",
    "addr:housenumber":"1120",
    "addr:postcode":"4212",
    "addr:street":"Beechwood Drv",
    "iso:country":"AU",
    "sg:address":"1120 Beechwood Drv",
    "sg:city":"Hope Island",
    "sg:classifiers":[
        {
            "category":"Wholesale",
            "subcategory":"Painting Supplies",
            "type":"Manufacturing & Wholesale Goods"
        }
    ],
    "sg:phone":"+61 7 5530 1070",
    "sg:postcode":"4212",
    "sg:province":"QLD",
    "sg:tags":[
        "product",
        "cleaning"
    ],
    "wof:name":"Amway of Australia",
    "wof:placetype":"venue"
},
  "geometry": {"coordinates":[153.34707641599999,-27.8618202209],"type":"Point"}
}