{
  "type": "Feature",
  "properties": {
    "addr:full":"PO Box 757 Capalaba QLD 4157",
    "addr:postcode":"4157",
    "iso:country":"AU",
    "sg:address":"PO Box 757",
    "sg:city":"Capalaba",
    "sg:classifiers":[
        {
            "category":"Sports & Exercise",
            "subcategory":"Gym",
            "type":"Entertainment"
        }
    ],
    "sg:phone":"+61 7 3257 1307",
    "sg:postcode":"4157",
    "sg:province":"QLD",
    "sg:tags":[
        "health",
        "fitness"
    ],
    "wof:name":"Life Be In It",
    "wof:placetype":"venue"
},
  "geometry": {"coordinates":[153.21090698200001,-27.5379695892],"type":"Point"}
}