{
  "type": "Feature",
  "properties": {
    "addr:full":"38 Brisbane St Ipswich QLD 4305",
    "addr:housenumber":"38",
    "addr:postcode":"4305",
    "addr:street":"Brisbane St",
    "iso:country":"AU",
    "sg:address":"38 Brisbane St",
    "sg:city":"Ipswich",
    "sg:classifiers":[
        {
            "category":"Banks & Credit Unions",
            "subcategory":"Investment Brokerage",
            "type":"Services"
        }
    ],
    "sg:phone":"+61 7 3281 7444",
    "sg:postcode":"4305",
    "sg:province":"QLD",
    "sg:tags":[
        "management",
        "property"
    ],
    "wof:name":"L.J. Hooker Ipswich",
    "wof:placetype":"venue"
},
  "geometry": {"coordinates":[152.76316833499999,-27.6151943207],"type":"Point"}
}