{
  "type": "Feature",
  "properties": {
    "addr:full":"Lvl 14/ 122 Arthur St North Sydney NSW 2060",
    "addr:housenumber":"/ 122",
    "addr:postcode":"2060",
    "addr:street":"Arthur St",
    "iso:country":"AU",
    "sg:address":"Lvl 14/ 122 Arthur St",
    "sg:city":"North Sydney",
    "sg:classifiers":[
        {
            "category":"Professional",
            "subcategory":"Management & Consulting",
            "type":"Services"
        }
    ],
    "sg:phone":"+61 419 268 560",
    "sg:postcode":"2060",
    "sg:province":"NSW",
    "sg:tags":[
        "consultant",
        "business"
    ],
    "wof:name":"Inspiro Consulting Group Pty Ltd",
    "wof:placetype":"venue"
},
  "geometry": {"coordinates":[151.21002197300001,-33.8385162354],"type":"Point"}
}