{
  "type": "Feature",
  "properties": {
    "iso:country":"AU",
    "sg:address":"54b Cockburn Rd",
    "sg:city":"Albany",
    "sg:classifiers":[
        {
            "category":"Professional",
            "subcategory":"Detective & Security Services",
            "type":"Services"
        }
    ],
    "sg:phone":"+61 8 9841 7616",
    "sg:postcode":"6330",
    "sg:province":"WA",
    "sg:tags":[
        "protective",
        "rustproofing"
    ],
    "wof:name":"Inside & Out Car Care",
    "wof:placetype":"venue"
},
  "geometry": {"coordinates":[117.892127991,-35.0151405334],"type":"Point"}
}