{
  "type": "Feature",
  "properties": {
    "addr:full":"688 Old Calder Hwy Keilor VIC 3036",
    "addr:housenumber":"688",
    "addr:postcode":"3036",
    "addr:street":"Old Calder Hwy",
    "iso:country":"AU",
    "sg:address":"688 Old Calder Hwy",
    "sg:city":"Keilor",
    "sg:classifiers":[
        {
            "category":"Food & Beverages",
            "subcategory":"Supermarket",
            "type":"Retail Goods"
        }
    ],
    "sg:phone":"+61 3 9336 7054",
    "sg:postcode":"3036",
    "sg:province":"VIC",
    "sg:tags":[
        "grocery",
        "store"
    ],
    "wof:name":"Abdallah Bill",
    "wof:placetype":"venue"
},
  "geometry": {"coordinates":[144.834946,-37.719135],"type":"Point"}
}