{
  "type": "Feature",
  "properties": {
    "addr:full":"Shop 6/ 1 Harvey Range Rd Thuringowa Central QLD 4817",
    "addr:housenumber":"shop 6 / 1",
    "addr:postcode":"4817",
    "addr:street":"Harvey Range Rd",
    "iso:country":"AU",
    "sg:address":"Shop 6/ 1 Harvey Range Rd",
    "sg:city":"Thuringowa Central",
    "sg:classifiers":[
        {
            "category":"Fast Food",
            "type":"Food & Drink"
        }
    ],
    "sg:phone":"+61 7 4773 9199",
    "sg:postcode":"4817",
    "sg:province":"QLD",
    "sg:tags":[
        "away",
        "take"
    ],
    "wof:name":"Subway",
    "wof:placetype":"venue"
},
  "geometry": {"coordinates":[146.72125199999999,-19.319578],"type":"Point"}
}