{
  "type": "Feature",
  "properties": {
    "iso:country":"AU",
    "sg:address":"56 Lake St",
    "sg:city":"Cairns",
    "sg:classifiers":[
        {
            "category":"Shopping",
            "subcategory":"Clothing, Apparel, & Fashions",
            "type":"Retail Goods"
        }
    ],
    "sg:phone":"+61 7 4051 8170",
    "sg:postcode":"4870",
    "sg:province":"QLD",
    "sg:tags":[
        "jean"
    ],
    "wof:name":"JeansWest",
    "wof:placetype":"venue"
},
  "geometry": {"coordinates":[145.777099609,-16.9233894348],"type":"Point"}
}