{
  "type": "Feature",
  "properties": {
    "addr:full":"Narambi Rd Mornington VIC 3931",
    "addr:postcode":"3931",
    "addr:street":"Narambi Rd",
    "iso:country":"AU",
    "sg:address":"Narambi Rd",
    "sg:city":"Mornington",
    "sg:classifiers":[
        {
            "category":"Arena",
            "subcategory":"Sports Club",
            "type":"Entertainment"
        }
    ],
    "sg:phone":"+61 3 5975 0530",
    "sg:postcode":"3931",
    "sg:province":"VIC",
    "sg:tags":[
        "australian",
        "football",
        "rule"
    ],
    "wof:name":"Mornington Junior Football Club",
    "wof:placetype":"venue"
},
  "geometry": {"coordinates":[145.05735778799999,-38.2282104492],"type":"Point"}
}