{
  "type": "Feature",
  "properties": {
    "addr:full":"11 Baker St Pinjarra WA 6208",
    "addr:housenumber":"11",
    "addr:postcode":"6208",
    "addr:street":"Baker St",
    "iso:country":"AU",
    "sg:address":"11 Baker St",
    "sg:city":"Pinjarra",
    "sg:classifiers":[
        {
            "category":"Real Estate",
            "subcategory":"Real Estate Agent",
            "type":"Services"
        }
    ],
    "sg:phone":"+61 8 9531 1107",
    "sg:postcode":"6208",
    "sg:province":"WA",
    "sg:tags":[
        "handyman's",
        "equipment",
        "hire",
        "builders",
        "contractor"
    ],
    "wof:name":"Geoff's Hire Service",
    "wof:placetype":"venue"
},
  "geometry": {"coordinates":[115.84951,-32.615444],"type":"Point"}
}