{
  "type": "Feature",
  "properties": {
    "addr:full":"Suite 3-8 Freeborn House 92a Main St Alstonville NSW 2477",
    "addr:housenumber":"92a",
    "addr:postcode":"2477",
    "addr:street":"Main St",
    "iso:country":"AU",
    "sg:address":"Suite 3-8 Freeborn House 92a Main St",
    "sg:city":"Alstonville",
    "sg:classifiers":[
        {
            "category":"Professional",
            "subcategory":"Accounting & Tax Preparation",
            "type":"Services"
        }
    ],
    "sg:phone":"+61 2 6628 0155",
    "sg:postcode":"2477",
    "sg:province":"NSW",
    "sg:tags":[
        "accountant",
        "auditor"
    ],
    "wof:name":"Bruno Ivan",
    "wof:placetype":"venue"
},
  "geometry": {"coordinates":[153.435836792,-28.8379192352],"type":"Point"}
}