{
  "type": "Feature",
  "properties": {
    "addr:full":"PO Box 52 Collinswood SA 5081",
    "addr:postcode":"5081",
    "iso:country":"AU",
    "sg:address":"PO Box 52",
    "sg:city":"Collinswood",
    "sg:classifiers":[
        {
            "category":"Building & Trades",
            "subcategory":"Cleaning & Sanitation",
            "type":"Services"
        }
    ],
    "sg:phone":"+61 419 828 827",
    "sg:postcode":"5081",
    "sg:province":"SA",
    "sg:tags":[
        "chemical",
        "pressure",
        "steam",
        "contractor"
    ],
    "wof:name":"Maintec Grounds Property Maintenance",
    "wof:placetype":"venue"
},
  "geometry": {"coordinates":[138.612915039,-34.8871498108],"type":"Point"}
}