{
  "type": "Feature",
  "properties": {
    "iso:country":"AU",
    "sg:address":"B1 Williams Rd",
    "sg:city":"Strathmerton",
    "sg:classifiers":[
        {
            "category":"Farming",
            "subcategory":"Poultry Farm",
            "type":"Manufacturing & Wholesale Goods"
        }
    ],
    "sg:phone":"+61 3 5868 2319",
    "sg:postcode":"3641",
    "sg:province":"VIC",
    "sg:tags":[
        "farmer"
    ],
    "wof:name":"Marven Poultry Pty Ltd",
    "wof:placetype":"venue"
},
  "geometry": {"coordinates":[145.40408325199999,-35.922580719],"type":"Point"}
}