{
  "type": "Feature",
  "properties": {
    "addr:full":"11 Railway St Guildford NSW 2161",
    "addr:housenumber":"11",
    "addr:postcode":"2161",
    "addr:street":"Railway St",
    "iso:country":"AU",
    "sg:address":"11 Railway St",
    "sg:city":"Guildford",
    "sg:classifiers":[
        {
            "category":"Banks & Credit Unions",
            "subcategory":"Investment Brokerage",
            "type":"Services"
        }
    ],
    "sg:phone":"+61 2 9892 4322",
    "sg:postcode":"2161",
    "sg:province":"NSW",
    "sg:tags":[
        "finance",
        "broker"
    ],
    "wof:name":"Brumby John",
    "wof:placetype":"venue"
},
  "geometry": {"coordinates":[150.98153686500001,-33.8588409424],"type":"Point"}
}