{
  "type": "Feature",
  "properties": {
    "addr:full":"140 Melbourne St North Adelaide SA 5006",
    "addr:housenumber":"140",
    "addr:postcode":"5006",
    "addr:street":"Melbourne St",
    "iso:country":"AU",
    "sg:address":"140 Melbourne St",
    "sg:city":"North Adelaide",
    "sg:classifiers":[
        {
            "category":"Shopping",
            "subcategory":"Clothing, Apparel, & Fashions",
            "type":"Retail Goods"
        }
    ],
    "sg:phone":"+61 8 8267 4638",
    "sg:postcode":"5006",
    "sg:province":"SA",
    "sg:tags":[
        "boutique"
    ],
    "wof:name":"Intimode Fashion Boutique",
    "wof:placetype":"venue"
},
  "geometry": {"coordinates":[138.60667419399999,-34.9075622559],"type":"Point"}
}