{
  "type": "Feature",
  "properties": {
    "addr:full":"305 Commercial Rd Yarram VIC 3971",
    "addr:housenumber":"305",
    "addr:postcode":"3971",
    "addr:street":"Commercial Rd",
    "iso:country":"AU",
    "sg:address":"305 Commercial Rd",
    "sg:city":"Yarram",
    "sg:classifiers":[
        {
            "category":"Cafe",
            "type":"Food & Drink"
        }
    ],
    "sg:phone":"+61 3 5182 6464",
    "sg:postcode":"3971",
    "sg:province":"VIC",
    "wof:name":"Federal Coffee Palace",
    "wof:placetype":"venue"
},
  "geometry": {"coordinates":[146.67590332,-38.5650024414],"type":"Point"}
}