{
  "type": "Feature",
  "properties": {
    "addr:full":"53- 73 Churchhill Rd Dry Creek SA 5094",
    "addr:housenumber":"73",
    "addr:postcode":"5094",
    "addr:street":"Churchhill Rd Dry",
    "iso:country":"AU",
    "sg:address":"53- 73 Churchhill Rd",
    "sg:city":"Dry Creek",
    "sg:classifiers":[
        {
            "category":"Home & Garden",
            "subcategory":"Garden Supply",
            "type":"Retail Goods"
        }
    ],
    "sg:phone":"+61 1800 888 365",
    "sg:postcode":"5094",
    "sg:province":"SA",
    "sg:tags":[
        "nursery"
    ],
    "wof:name":"Masrac Plastics Pty Ltd",
    "wof:placetype":"venue"
},
  "geometry": {"coordinates":[138.594848633,-34.830871582],"type":"Point"}
}