{
  "type": "Feature",
  "properties": {
    "addr:full":"109 Great North Rd Five Dock NSW 2046",
    "addr:housenumber":"109",
    "addr:postcode":"2046",
    "addr:street":"Great North Rd",
    "iso:country":"AU",
    "sg:address":"109 Great North Rd",
    "sg:city":"Five Dock",
    "sg:classifiers":[
        {
            "category":"Real Estate",
            "subcategory":"Real Estate Agent",
            "type":"Services"
        }
    ],
    "sg:phone":"+61 2 9712 3822",
    "sg:postcode":"2046",
    "sg:province":"NSW",
    "wof:name":"Richardson & Wrench Five Dock",
    "wof:placetype":"venue"
},
  "geometry": {"coordinates":[151.12936400000001,-33.86903],"type":"Point"}
}