{
  "type": "Feature",
  "properties": {
    "addr:full":"33 Elizabeth St Maitland SA 5573",
    "addr:housenumber":"33",
    "addr:postcode":"5573",
    "addr:street":"Elizabeth St",
    "iso:country":"AU",
    "sg:address":"33 Elizabeth St",
    "sg:city":"Maitland",
    "sg:classifiers":[
        {
            "category":"Wholesale",
            "subcategory":"Machinery & Supplies",
            "type":"Manufacturing & Wholesale Goods"
        }
    ],
    "sg:phone":"+61 8 8832 2801",
    "sg:postcode":"5573",
    "sg:province":"SA",
    "sg:tags":[
        "agricultural"
    ],
    "wof:name":"Larwoods Ag Services",
    "wof:placetype":"venue"
},
  "geometry": {"coordinates":[137.672241211,-34.3735389709],"type":"Point"}
}