{
  "type": "Feature",
  "properties": {
    "addr:full":"Shp 5, Narellan Supa Cntr, Cnr Exchange Pde & Nare Narellan NSW 2567",
    "addr:housenumber":"5",
    "addr:postcode":"2567",
    "addr:street":"Exchange",
    "iso:country":"AU",
    "sg:address":"Shp 5, Narellan Supa Cntr, Cnr Exchange Pde & Nare",
    "sg:city":"Narellan",
    "sg:classifiers":[
        {
            "category":"Professional",
            "subcategory":"Accounting & Tax Preparation",
            "type":"Services"
        }
    ],
    "sg:phone":"+61 2 4648 5000",
    "sg:postcode":"2567",
    "sg:province":"NSW",
    "sg:tags":[
        "accountant",
        "auditor"
    ],
    "wof:name":"Redman Partners Pty Ltd",
    "wof:placetype":"venue"
},
  "geometry": {"coordinates":[150.748703003,-34.0394439697],"type":"Point"}
}