{
  "type": "Feature",
  "properties": {
    "addr:full":"1st Floor, 29 High St Toowong QLD 4066",
    "addr:housenumber":"29",
    "addr:postcode":"4066",
    "addr:street":"High St",
    "iso:country":"AU",
    "sg:address":"1st Floor, 29 High St",
    "sg:city":"Toowong",
    "sg:classifiers":[
        {
            "category":"Professional",
            "subcategory":"Accounting & Tax Preparation",
            "type":"Services"
        }
    ],
    "sg:phone":"+61 7 3371 6733",
    "sg:postcode":"4066",
    "sg:province":"QLD",
    "sg:tags":[
        "consultant",
        "taxation"
    ],
    "wof:name":"H & R Block",
    "wof:placetype":"venue"
},
  "geometry": {"coordinates":[152.991943359,-27.4860401154],"type":"Point"}
}