{
  "type": "Feature",
  "properties": {
    "addr:full":"PO Box 3079 Dural NSW 2158",
    "addr:postcode":"2158",
    "iso:country":"AU",
    "sg:address":"PO Box 3079",
    "sg:city":"Dural",
    "sg:classifiers":[
        {
            "category":"Home & Garden",
            "subcategory":"Carpets & Floor Coverings",
            "type":"Retail Goods"
        }
    ],
    "sg:phone":"+61 418 447 238",
    "sg:postcode":"2158",
    "sg:province":"NSW",
    "sg:tags":[
        "tile",
        "wall",
        "layer"
    ],
    "wof:name":"Progress Tiling Pty Ltd",
    "wof:placetype":"venue"
},
  "geometry": {"coordinates":[151.029296875,-33.6800613403],"type":"Point"}
}