{
  "type": "Feature",
  "properties": {
    "iso:country":"AU",
    "sg:address":"Shop 7, Cnr Sandford & Brooks Sts",
    "sg:city":"Mitchell",
    "sg:classifiers":[
        {
            "category":"Fast Food",
            "type":"Food & Drink"
        }
    ],
    "sg:phone":"+61 2 6242 6556",
    "sg:postcode":"2911",
    "sg:province":"ACT",
    "sg:tags":[
        "away",
        "take"
    ],
    "wof:name":"King Arthur's Feast",
    "wof:placetype":"venue"
},
  "geometry": {"coordinates":[149.134765625,-35.2194900513],"type":"Point"}
}