{
  "type": "Feature",
  "properties": {
    "addr:full":"524 Fitzgerald St North Perth WA 6006",
    "addr:housenumber":"524",
    "addr:postcode":"6006",
    "addr:street":"Fitzgerald St",
    "iso:country":"AU",
    "sg:address":"524 Fitzgerald St",
    "sg:city":"North Perth",
    "sg:classifiers":[
        {
            "category":"Professional",
            "subcategory":"Management & Consulting",
            "type":"Services"
        }
    ],
    "sg:phone":"+61 1800 008 472",
    "sg:postcode":"6006",
    "sg:province":"WA",
    "sg:tags":[
        "consultant",
        "migration"
    ],
    "wof:name":"AAA Australian Migration",
    "wof:placetype":"venue"
},
  "geometry": {"coordinates":[115.85939025899999,-31.9268608093],"type":"Point"}
}