{
  "type": "Feature",
  "properties": {
    "addr:full":"222 Mitcham Rd Mitcham VIC 3132",
    "addr:housenumber":"222",
    "addr:postcode":"3132",
    "addr:street":"Mitcham Rd",
    "iso:country":"AU",
    "sg:address":"222 Mitcham Rd",
    "sg:city":"Mitcham",
    "sg:classifiers":[
        {
            "category":"Fast Food",
            "type":"Food & Drink"
        }
    ],
    "sg:phone":"+61 3 9873 4611",
    "sg:postcode":"3132",
    "sg:province":"VIC",
    "sg:tags":[
        "away",
        "take"
    ],
    "wof:name":"Pizza Bella",
    "wof:placetype":"venue"
},
  "geometry": {"coordinates":[145.189254761,-37.8042144775],"type":"Point"}
}