{
  "type": "Feature",
  "properties": {
    "addr:full":"Government Rd Carpenter Rocks SA 5291",
    "addr:postcode":"5291",
    "addr:street":"Rd",
    "iso:country":"AU",
    "sg:address":"Government Rd",
    "sg:city":"Carpenter Rocks",
    "sg:classifiers":[
        {
            "category":"Farming",
            "subcategory":"Fish & Marine Products",
            "type":"Manufacturing & Wholesale Goods"
        }
    ],
    "sg:phone":"+61 8 8738 0184",
    "sg:postcode":"5291",
    "sg:province":"SA",
    "sg:tags":[
        "fisherman"
    ],
    "wof:name":"Von Stanke S W & C",
    "wof:placetype":"venue"
},
  "geometry": {"coordinates":[140.43331900000001,-37.897491],"type":"Point"}
}