{
  "type": "Feature",
  "properties": {
    "addr:full":"230 Marius St Tamworth NSW 2340",
    "addr:housenumber":"230",
    "addr:postcode":"2340",
    "addr:street":"Marius St",
    "iso:country":"AU",
    "sg:address":"230 Marius St",
    "sg:city":"Tamworth",
    "sg:classifiers":[
        {
            "category":"Insurance",
            "subcategory":"Life Insurance",
            "type":"Services"
        }
    ],
    "sg:phone":"+61 2 6766 9655",
    "sg:postcode":"2340",
    "sg:province":"NSW",
    "wof:name":"Dome Financial Group",
    "wof:placetype":"venue"
},
  "geometry": {"coordinates":[150.935012817,-31.0925388336],"type":"Point"}
}