{
  "type": "Feature",
  "properties": {
    "iso:country":"AU",
    "sg:address":"3 Wirriga St",
    "sg:city":"Regency Park",
    "sg:classifiers":[
        {
            "category":"Wholesale",
            "subcategory":"Home Furnishings",
            "type":"Manufacturing & Wholesale Goods"
        }
    ],
    "sg:phone":"+61 8 8347 3000",
    "sg:postcode":"5010",
    "sg:province":"SA",
    "sg:tags":[
        "wholesaler",
        "mfrs",
        "manchester"
    ],
    "wof:name":"DOWNUNDER TEXTILES PTY LTD",
    "wof:placetype":"venue"
},
  "geometry": {"coordinates":[138.56544494600001,-34.8534164429],"type":"Point"}
}