{
  "type": "Feature",
  "properties": {
    "addr:full":"Black Mountain Drv Acton ACT 2601",
    "addr:postcode":"2601",
    "addr:street":"Black Mountain Drv",
    "iso:country":"AU",
    "sg:address":"Black Mountain Drv",
    "sg:city":"Acton",
    "sg:classifiers":[
        {
            "category":"Communications",
            "subcategory":"News Services",
            "type":"Services"
        }
    ],
    "sg:phone":"+61 2 6248 1911",
    "sg:postcode":"2601",
    "sg:province":"ACT",
    "sg:tags":[
        "information",
        "tourist",
        "attractions"
    ],
    "wof:name":"Telstra Tower",
    "wof:placetype":"venue"
},
  "geometry": {"coordinates":[149.11015319800001,-35.2802238464],"type":"Point"}
}