{
  "type": "Feature",
  "properties": {
    "iso:country":"AU",
    "sg:address":"9 Nyora St",
    "sg:city":"Everton Hills",
    "sg:classifiers":[
        {
            "category":"Utilities",
            "subcategory":"Water",
            "type":"Services"
        }
    ],
    "sg:phone":"+61 7 3353 2022",
    "sg:postcode":"4053",
    "sg:province":"QLD",
    "sg:tags":[
        "hot",
        "system"
    ],
    "wof:name":"A. Northern Suburbs Hot Water",
    "wof:placetype":"venue"
},
  "geometry": {"coordinates":[152.97654724099999,-27.3830299377],"type":"Point"}
}