{
  "type": "Feature",
  "properties": {
    "iso:country":"AU",
    "sg:address":"Barton St",
    "sg:city":"Bell Park",
    "sg:classifiers":[
        {
            "category":"Education",
            "subcategory":"School",
            "type":"Public Place"
        }
    ],
    "sg:phone":"+61 3 5278 3548",
    "sg:postcode":"3215",
    "sg:province":"VIC",
    "sg:tags":[
        "state",
        "except",
        "nsw"
    ],
    "wof:name":"Bell Park Nth Primary School",
    "wof:placetype":"venue"
},
  "geometry": {"coordinates":[144.33627319300001,-38.1062049866],"type":"Point"}
}