{
  "type": "Feature",
  "properties": {
    "addr:full":"75 Acland St St Kilda VIC 3182",
    "addr:housenumber":"75",
    "addr:postcode":"3182",
    "addr:street":"Acland St",
    "iso:country":"AU",
    "sg:address":"75 Acland St",
    "sg:city":"St Kilda",
    "sg:classifiers":[
        {
            "category":"Ice Cream",
            "type":"Food & Drink"
        }
    ],
    "sg:phone":"+61 3 9537 3633",
    "sg:postcode":"3182",
    "sg:province":"VIC",
    "sg:tags":[
        "retail"
    ],
    "wof:name":"Seven Apples Gelato",
    "wof:placetype":"venue"
},
  "geometry": {"coordinates":[144.978805542,-37.8677902222],"type":"Point"}
}