{
  "type": "Feature",
  "properties": {
    "iso:country":"AU",
    "sg:address":"2 Ernest St",
    "sg:city":"Crows Nest",
    "sg:classifiers":[
        {
            "category":"Social Services",
            "subcategory":"Child Care",
            "type":"Services"
        }
    ],
    "sg:phone":"+61 2 9438 3019",
    "sg:postcode":"2065",
    "sg:province":"NSW",
    "sg:tags":[
        "support",
        "health"
    ],
    "wof:name":"Early Childhood Health Centres",
    "wof:placetype":"venue"
},
  "geometry": {"coordinates":[151.20297241200001,-33.8260803223],"type":"Point"}
}