{
  "type": "Feature",
  "properties": {
    "addr:full":"106 Ryrie St Geelong VIC 3220",
    "addr:housenumber":"106",
    "addr:postcode":"3220",
    "addr:street":"Ryrie St",
    "iso:country":"AU",
    "sg:address":"106 Ryrie St",
    "sg:city":"Geelong",
    "sg:classifiers":[
        {
            "category":"Shopping",
            "subcategory":"Crafts & Fabrics",
            "type":"Retail Goods"
        }
    ],
    "sg:phone":"+61 3 5221 0099",
    "sg:postcode":"3220",
    "sg:province":"VIC",
    "sg:tags":[
        "wool",
        "knitting",
        "accessory"
    ],
    "wof:name":"Stitchery Blue",
    "wof:placetype":"venue"
},
  "geometry": {"coordinates":[144.35777300000001,-38.148895],"type":"Point"}
}