{
  "type": "Feature",
  "properties": {
    "addr:full":"Lot 120 Modigunn Rd Karratha WA 6714",
    "addr:postcode":"6714",
    "addr:street":"Modigunn Rd",
    "iso:country":"AU",
    "sg:address":"Lot 120 Modigunn Rd",
    "sg:city":"Karratha",
    "sg:classifiers":[
        {
            "category":"Local Transit",
            "type":"Transportation"
        }
    ],
    "sg:phone":"+61 1300 722 999",
    "sg:postcode":"6714",
    "sg:province":"WA",
    "sg:tags":[
        "winch"
    ],
    "wof:name":"Bullivants Sling-Rig",
    "wof:placetype":"venue"
},
  "geometry": {"coordinates":[116.843971252,-20.7356300354],"type":"Point"}
}