{
  "type": "Feature",
  "properties": {
    "iso:country":"AU",
    "sg:address":"798 Upper Macdonald Rd",
    "sg:city":"St Albans",
    "sg:classifiers":[
        {
            "category":"Farming",
            "subcategory":"Farm",
            "type":"Manufacturing & Wholesale Goods"
        }
    ],
    "sg:phone":"+61 2 4568 2177",
    "sg:postcode":"2775",
    "sg:province":"NSW",
    "sg:tags":[
        "farmer"
    ],
    "wof:name":"St Albans Nut Company",
    "wof:placetype":"venue"
},
  "geometry": {"coordinates":[150.97114563,-33.2920608521],"type":"Point"}
}