{
  "type": "Feature",
  "properties": {
    "addr:full":"4 Short St Millicent SA 5280",
    "addr:housenumber":"4",
    "addr:postcode":"5280",
    "addr:street":"Short St",
    "iso:country":"AU",
    "sg:address":"4 Short St",
    "sg:city":"Millicent",
    "sg:classifiers":[
        {
            "category":"Building & Trades",
            "subcategory":"Construction",
            "type":"Services"
        }
    ],
    "sg:phone":"+61 8 8733 2799",
    "sg:postcode":"5280",
    "sg:province":"SA",
    "sg:tags":[
        "welding"
    ],
    "wof:name":"AbbSteel Industries Pty Ltd",
    "wof:placetype":"venue"
},
  "geometry": {"coordinates":[140.35618600000001,-37.597164],"type":"Point"}
}