{
  "type": "Feature",
  "properties": {
    "addr:full":"Thames St Wollongong NSW 2500",
    "addr:postcode":"2500",
    "addr:street":"Thames St",
    "iso:country":"AU",
    "sg:address":"Thames St",
    "sg:city":"Wollongong",
    "sg:classifiers":[
        {
            "category":"Education",
            "subcategory":"School",
            "type":"Public Place"
        }
    ],
    "sg:phone":"+61 2 4229 2487",
    "sg:postcode":"2500",
    "sg:province":"NSW",
    "sg:tags":[
        "state",
        "-",
        "nsw"
    ],
    "wof:name":"Lindsay Park Public School",
    "wof:placetype":"venue"
},
  "geometry": {"coordinates":[150.86192299999999,-34.429298],"type":"Point"}
}