{
  "type": "Feature",
  "properties": {
    "addr:full":"Shop 5, 108 Penshurst St Willoughby NSW 2068",
    "addr:housenumber":"shop 5 108",
    "addr:postcode":"2068",
    "addr:street":"Penshurst St",
    "iso:country":"AU",
    "sg:address":"Shop 5, 108 Penshurst St",
    "sg:city":"Willoughby",
    "sg:classifiers":[
        {
            "category":"Health Services",
            "subcategory":"Dentist",
            "type":"Services"
        }
    ],
    "sg:phone":"+61 2 9958 2227",
    "sg:postcode":"2068",
    "sg:province":"NSW",
    "wof:name":"Ian K.K. Lin Pty Ltd",
    "wof:placetype":"venue"
},
  "geometry": {"coordinates":[151.198455811,-33.8013420105],"type":"Point"}
}