{
  "type": "Feature",
  "properties": {
    "addr:full":"90 Beach Rd Hervey Bay QLD 4655",
    "addr:housenumber":"90",
    "addr:postcode":"4655",
    "addr:street":"Beach Rd",
    "iso:country":"AU",
    "sg:address":"90 Beach Rd",
    "sg:city":"Hervey Bay",
    "sg:classifiers":[
        {
            "category":"Professional",
            "subcategory":"Art Services",
            "type":"Services"
        }
    ],
    "sg:phone":"+61 7 4124 2300",
    "sg:postcode":"4655",
    "sg:province":"QLD",
    "sg:tags":[
        "interior",
        "decorator"
    ],
    "wof:name":"The Bay Emporium",
    "wof:placetype":"venue"
},
  "geometry": {"coordinates":[152.83175700000001,-25.285276],"type":"Point"}
}