{
  "type": "Feature",
  "properties": {
    "addr:full":"7 Alison Rd Wyong NSW 2259",
    "addr:housenumber":"7",
    "addr:postcode":"2259",
    "addr:street":"Alison Rd",
    "iso:country":"AU",
    "sg:address":"7 Alison Rd",
    "sg:city":"Wyong",
    "sg:classifiers":[
        {
            "category":"Home & Garden",
            "subcategory":"Building Materials",
            "type":"Retail Goods"
        }
    ],
    "sg:phone":"+61 2 4353 5799",
    "sg:postcode":"2259",
    "sg:province":"NSW",
    "sg:tags":[
        "merchant",
        "glass",
        "glazier"
    ],
    "wof:name":"Fandec Stained Glass",
    "wof:placetype":"venue"
},
  "geometry": {"coordinates":[151.424224853,-33.2841720581],"type":"Point"}
}