{
  "type": "Feature",
  "properties": {
    "addr:full":"Unit 7/ 102 Centennial Cct Byron Bay NSW 2481",
    "addr:housenumber":"/ 102",
    "addr:postcode":"2481",
    "addr:street":"Centennial Cct",
    "iso:country":"AU",
    "sg:address":"Unit 7/ 102",
    "sg:city":"Centennial Cct Byron Bay",
    "sg:classifiers":[
        {
            "category":"Manufacturing",
            "subcategory":"Paper Products",
            "type":"Manufacturing & Wholesale Goods"
        }
    ],
    "sg:phone":"+61 2 6680 9905",
    "sg:postcode":"2481",
    "sg:province":"NSW",
    "sg:tags":[
        "box",
        "fibre",
        "carton",
        "cardboard"
    ],
    "wof:name":"Super Moves Byron Bay",
    "wof:placetype":"venue"
},
  "geometry": {"coordinates":[153.58088684099999,-28.6367015839],"type":"Point"}
}