{
  "type": "Feature",
  "properties": {
    "iso:country":"AU",
    "sg:address":"10 George St",
    "sg:city":"Bundaberg",
    "sg:classifiers":[
        {
            "category":"Arena",
            "subcategory":"Sports Club",
            "type":"Entertainment"
        }
    ],
    "sg:phone":"+61 7 4152 7739",
    "sg:postcode":"4670",
    "sg:province":"QLD",
    "sg:tags":[
        "defence",
        "supply",
        "self",
        "instruction",
        "martial art"
    ],
    "wof:name":"Australian Academy Of Tai Chi",
    "wof:placetype":"venue"
},
  "geometry": {"coordinates":[152.36363220199999,-24.8682098389],"type":"Point"}
}