{
  "type": "Feature",
  "properties": {
    "addr:full":"43 Tennyson St Elwood VIC 3184",
    "addr:housenumber":"43",
    "addr:postcode":"3184",
    "addr:street":"Tennyson St",
    "iso:country":"AU",
    "sg:address":"43 Tennyson St",
    "sg:city":"Elwood",
    "sg:classifiers":[
        {
            "category":"Professional",
            "subcategory":"Computer Services",
            "type":"Services"
        }
    ],
    "sg:phone":"+61 3 9531 6644",
    "sg:postcode":"3184",
    "sg:province":"VIC",
    "sg:tags":[
        "consultant",
        "system"
    ],
    "wof:name":"Atlantis Communications Pty Ltd",
    "wof:placetype":"venue"
},
  "geometry": {"coordinates":[144.98866272000001,-37.8762741089],"type":"Point"}
}