{
  "type": "Feature",
  "properties": {
    "iso:country":"AU",
    "sg:address":"36 Hasler Rd",
    "sg:city":"Osborne Park",
    "sg:classifiers":[
        {
            "category":"Building & Trades",
            "subcategory":"Construction",
            "type":"Services"
        }
    ],
    "sg:phone":"+61 8 6241 7000",
    "sg:postcode":"6017",
    "sg:province":"WA",
    "sg:tags":[
        "contractor"
    ],
    "sg:website":"http://www.ruralbuilding.com.au",
    "wof:name":"Rural Building Company",
    "wof:placetype":"venue"
},
  "geometry": {"coordinates":[115.80950164799999,-31.9112625122],"type":"Point"}
}