{
  "type": "Feature",
  "properties": {
    "iso:country":"AU",
    "sg:address":"Factory 13, 12 Adina St",
    "sg:city":"Ferntree Gully",
    "sg:classifiers":[
        {
            "category":"Building & Trades",
            "subcategory":"Plumbing",
            "type":"Services"
        }
    ],
    "sg:phone":"+61 412 384 747",
    "sg:postcode":"3156",
    "sg:province":"VIC",
    "sg:tags":[
        "plumber",
        "gasfitters"
    ],
    "wof:name":"Aquablock Plumbing",
    "wof:placetype":"venue"
},
  "geometry": {"coordinates":[145.25209045400001,-37.9300498962],"type":"Point"}
}