{
  "type": "Feature",
  "properties": {
    "iso:country":"AU",
    "sg:address":"Shop 26",
    "sg:city":"Post Office Sq Brisbane",
    "sg:classifiers":[
        {
            "category":"Personal",
            "subcategory":"Beauty Salon",
            "type":"Services"
        }
    ],
    "sg:phone":"+61 7 3229 7003",
    "sg:postcode":"4000",
    "sg:province":"QLD",
    "sg:tags":[
        "hairdresser"
    ],
    "sg:website":"http://www.myspace.com/cadillacbarbie",
    "wof:name":"Cadillac Barbie",
    "wof:placetype":"venue"
},
  "geometry": {"coordinates":[153.027175903,-27.4674472809],"type":"Point"}
}