{
  "type": "Feature",
  "properties": {
    "addr:full":"51 Great Northern Hwy Middle Swan WA 6056",
    "addr:housenumber":"51",
    "addr:postcode":"6056",
    "addr:street":"Great Northern Hwy Middle",
    "iso:country":"AU",
    "sg:address":"51 Great Northern Hwy",
    "sg:city":"Middle Swan",
    "sg:classifiers":[
        {
            "category":"Farming",
            "subcategory":"Poultry Farm",
            "type":"Manufacturing & Wholesale Goods"
        }
    ],
    "sg:phone":"+61 8 9250 3980",
    "sg:postcode":"6056",
    "sg:province":"WA",
    "sg:tags":[
        "breeder",
        "bird"
    ],
    "wof:name":"Swan Valley Birds",
    "wof:placetype":"venue"
},
  "geometry": {"coordinates":[116.014389038,-31.8684253693],"type":"Point"}
}