{
  "type": "Feature",
  "properties": {
    "addr:full":"Factory 1/7 Barrie Rd Tullamarine VIC 3043",
    "addr:housenumber":"/ 7",
    "addr:postcode":"3043",
    "addr:street":"Barrie Rd",
    "iso:country":"AU",
    "sg:address":"Factory 1/7 Barrie Rd",
    "sg:city":"Tullamarine",
    "sg:classifiers":[
        {
            "category":"Wholesale",
            "subcategory":"Scrap",
            "type":"Manufacturing & Wholesale Goods"
        }
    ],
    "sg:phone":"+61 3 9338 2128",
    "sg:postcode":"3043",
    "sg:province":"VIC",
    "sg:tags":[
        "merchant",
        "metal"
    ],
    "sg:website":"http://www.scrapbatteriesrus.com.au",
    "wof:name":"Scrap Batteries R Us Pty Ltd",
    "wof:placetype":"venue"
},
  "geometry": {"coordinates":[144.877197266,-37.7102508545],"type":"Point"}
}