{
  "type": "Feature",
  "properties": {
    "addr:full":"4 Hughes Ave Richmond NSW 2753",
    "addr:housenumber":"4",
    "addr:postcode":"2753",
    "addr:street":"Hughes Ave",
    "iso:country":"AU",
    "sg:address":"4 Hughes Ave",
    "sg:city":"Richmond",
    "sg:classifiers":[
        {
            "category":"Wholesale",
            "subcategory":"Machinery & Supplies",
            "type":"Manufacturing & Wholesale Goods"
        }
    ],
    "sg:phone":"+61 2 4578 1056",
    "sg:postcode":"2753",
    "sg:province":"NSW",
    "sg:tags":[
        "chemist"
    ],
    "wof:name":"W.T.C. Sales Broker",
    "wof:placetype":"venue"
},
  "geometry": {"coordinates":[150.73965454099999,-33.6033554077],"type":"Point"}
}