{
  "type": "Feature",
  "properties": {
    "addr:full":"62-64 Main St Upwey VIC 3158",
    "addr:housenumber":"62-64",
    "addr:postcode":"3158",
    "addr:street":"Main St",
    "iso:country":"AU",
    "sg:address":"62-64 Main St",
    "sg:city":"Upwey",
    "sg:classifiers":[
        {
            "category":"Professional",
            "subcategory":"Management & Consulting",
            "type":"Services"
        }
    ],
    "sg:phone":"+61 3 9752 6436",
    "sg:postcode":"3158",
    "sg:province":"VIC",
    "sg:tags":[
        "consultant",
        "migration"
    ],
    "wof:name":"Australian Migration Solutions Pty Ltd",
    "wof:placetype":"venue"
},
  "geometry": {"coordinates":[145.33102417000001,-37.9037971497],"type":"Point"}
}