{
  "type": "Feature",
  "properties": {
    "addr:full":"287 Draper St Cairns QLD 4870",
    "addr:housenumber":"287",
    "addr:postcode":"4870",
    "addr:street":"Draper St",
    "iso:country":"AU",
    "sg:address":"287 Draper St",
    "sg:city":"Cairns",
    "sg:classifiers":[
        {
            "category":"Recreation",
            "subcategory":"Boat Charter",
            "type":"Entertainment"
        }
    ],
    "sg:phone":"+61 7 4052 8300",
    "sg:postcode":"4870",
    "sg:province":"QLD",
    "wof:name":"Down Under Cruise & Dive",
    "wof:placetype":"venue"
},
  "geometry": {"coordinates":[145.760894775,-16.9172878265],"type":"Point"}
}