{
  "type": "Feature",
  "properties": {
    "iso:country":"AU",
    "sg:address":"335 Moray St",
    "sg:city":"South Melbourne",
    "sg:classifiers":[
        {
            "category":"Travel",
            "subcategory":"Travel Agent",
            "type":"Entertainment"
        }
    ],
    "sg:phone":"+61 3 9699 3955",
    "sg:postcode":"3205",
    "sg:province":"VIC",
    "sg:tags":[
        "consultant"
    ],
    "wof:name":"Travel Associates Pty Ltd",
    "wof:placetype":"venue"
},
  "geometry": {"coordinates":[144.96530200000001,-37.83675],"type":"Point"}
}