{
  "type": "Feature",
  "properties": {
    "addr:full":"Berserker Village Unit 3, Duthie Ave North Rockhampton QLD 4701",
    "addr:housenumber":"3",
    "addr:postcode":"4701",
    "addr:street":"Duthie Ave North",
    "iso:country":"AU",
    "sg:address":"Berserker Village Unit 3, Duthie Ave",
    "sg:city":"North Rockhampton",
    "sg:classifiers":[
        {
            "category":"Health Services",
            "subcategory":"Health Practitioner",
            "type":"Services"
        }
    ],
    "sg:phone":"+61 7 4928 7880",
    "sg:postcode":"4701",
    "sg:province":"QLD",
    "sg:tags":[
        "physiotherapist"
    ],
    "wof:name":"Tempest A D",
    "wof:placetype":"venue"
},
  "geometry": {"coordinates":[150.54264831500001,-23.3483505249],"type":"Point"}
}