{
  "type": "Feature",
  "properties": {
    "iso:country":"AU",
    "sg:address":"2 Maroondah Hwy",
    "sg:city":"Ringwood",
    "sg:classifiers":[
        {
            "category":"Retail",
            "subcategory":"Auto Rental",
            "type":"Services"
        }
    ],
    "sg:phone":"+61 13 24 94",
    "sg:postcode":"3134",
    "sg:province":"VIC",
    "sg:tags":[
        "car",
        "hire",
        "minibus"
    ],
    "wof:name":"Ascot Car & Ute Rentals",
    "wof:placetype":"venue"
},
  "geometry": {"coordinates":[145.21432495100001,-37.8175315857],"type":"Point"}
}