{
  "type": "Feature",
  "properties": {
    "iso:country":"AU",
    "sg:address":"2-10 Camberwell Rd",
    "sg:city":"Hawthorn East",
    "sg:classifiers":[
        {
            "category":"Education",
            "subcategory":"Special Training",
            "type":"Public Place"
        }
    ],
    "sg:phone":"+61 3 9882 7644",
    "sg:postcode":"3123",
    "sg:province":"VIC",
    "sg:tags":[
        "development"
    ],
    "wof:name":"Mayfield Education",
    "wof:placetype":"venue"
},
  "geometry": {"coordinates":[145.04879760700001,-37.8247261047],"type":"Point"}
}