{
  "type": "Feature",
  "properties": {
    "iso:country":"AU",
    "sg:address":"PO Box 338",
    "sg:city":"Terrigal",
    "sg:classifiers":[
        {
            "category":"Home & Garden",
            "subcategory":"Building Materials",
            "type":"Retail Goods"
        }
    ],
    "sg:phone":"+61 427 888 800",
    "sg:postcode":"2260",
    "sg:province":"NSW",
    "sg:tags":[
        "lawn",
        "cutting",
        "maintenance"
    ],
    "wof:name":"Big Teds Garden Care",
    "wof:placetype":"venue"
},
  "geometry": {"coordinates":[151.445709,-33.4478],"type":"Point"}
}