{
  "type": "Feature",
  "properties": {
    "iso:country":"AU",
    "sg:address":"Shopping Centre Central Ave",
    "sg:city":"Weipa",
    "sg:classifiers":[
        {
            "category":"Food & Beverages",
            "subcategory":"Supermarket",
            "type":"Retail Goods"
        }
    ],
    "sg:phone":"+61 7 4069 7330",
    "sg:postcode":"4874",
    "sg:province":"QLD",
    "sg:tags":[
        "grocery",
        "store"
    ],
    "wof:name":"Woolworths Limited",
    "wof:placetype":"venue"
},
  "geometry": {"coordinates":[141.873703003,-12.636964798],"type":"Point"}
}