{
  "type": "Feature",
  "properties": {
    "addr:full":"1/35- 37 Cormack Rd Wingfield SA 5013",
    "addr:housenumber":"/;37",
    "addr:postcode":"5013",
    "addr:street":"35;Cormack Rd",
    "iso:country":"AU",
    "sg:address":"1/35- 37 Cormack Rd",
    "sg:city":"Wingfield",
    "sg:classifiers":[
        {
            "category":"Shopping",
            "subcategory":"Stationery & Office Supplies",
            "type":"Retail Goods"
        }
    ],
    "sg:phone":"+61 8 8243 9000",
    "sg:postcode":"5013",
    "sg:province":"SA",
    "sg:tags":[
        "packaging",
        "material"
    ],
    "wof:name":"Cospak (SA) Pty Ltd",
    "wof:placetype":"venue"
},
  "geometry": {"coordinates":[138.567825317,-34.8402252197],"type":"Point"}
}