{
  "type": "Feature",
  "properties": {
    "addr:full":"69 Gahans Ave Woonona NSW 2517",
    "addr:housenumber":"69",
    "addr:postcode":"2517",
    "addr:street":"Gahans Ave",
    "iso:country":"AU",
    "sg:address":"69 Gahans Ave",
    "sg:city":"Woonona",
    "sg:classifiers":[
        {
            "category":"Education",
            "subcategory":"Music School",
            "type":"Public Place"
        }
    ],
    "sg:phone":"+61 2 4283 1277",
    "sg:postcode":"2517",
    "sg:province":"NSW",
    "sg:tags":[
        "choir",
        "bands",
        "orchestra"
    ],
    "wof:name":"Ripple Soul Shufflers",
    "wof:placetype":"venue"
},
  "geometry": {"coordinates":[150.89463799999999,-34.34325],"type":"Point"}
}