{
  "type": "Feature",
  "properties": {
    "addr:full":"258 Maribyrnong Rd Moonee Ponds VIC 3039",
    "addr:housenumber":"258",
    "addr:postcode":"3039",
    "addr:street":"Maribyrnong Rd",
    "iso:country":"AU",
    "sg:address":"258 Maribyrnong Rd",
    "sg:city":"Moonee Ponds",
    "sg:classifiers":[
        {
            "category":"Health Services",
            "subcategory":"Health Practitioner",
            "type":"Services"
        }
    ],
    "sg:phone":"+61 3 9370 8885",
    "sg:postcode":"3039",
    "sg:province":"VIC",
    "sg:tags":[
        "herbalist"
    ],
    "wof:name":"Moonee Ponds Wellness Centre",
    "wof:placetype":"venue"
},
  "geometry": {"coordinates":[144.905869,-37.770695],"type":"Point"}
}