{
  "type": "Feature",
  "properties": {
    "addr:full":"101 Byrnes Rd Wagga Wagga North NSW 2650",
    "addr:housenumber":"101",
    "addr:postcode":"2650",
    "addr:street":"Byrnes Rd",
    "iso:country":"AU",
    "sg:address":"101 Byrnes Rd",
    "sg:city":"Wagga Wagga North",
    "sg:classifiers":[
        {
            "category":"Wholesale",
            "subcategory":"Machinery & Supplies",
            "type":"Manufacturing & Wholesale Goods"
        }
    ],
    "sg:phone":"+61 2 6923 0800",
    "sg:postcode":"2650",
    "sg:province":"NSW",
    "sg:tags":[
        "agricultural"
    ],
    "wof:name":"Countrywide Engineering",
    "wof:placetype":"venue"
},
  "geometry": {"coordinates":[147.40443420400001,-35.0917930603],"type":"Point"}
}