{
  "type": "Feature",
  "properties": {
    "addr:full":"Laings Rd Nayook VIC 3821",
    "addr:postcode":"3821",
    "addr:street":"Laings Rd",
    "iso:country":"AU",
    "sg:address":"Laings Rd",
    "sg:city":"Nayook",
    "sg:classifiers":[
        {
            "category":"Food & Beverages",
            "subcategory":"Fruits & Vegetables",
            "type":"Retail Goods"
        }
    ],
    "sg:phone":"+61 3 5628 4258",
    "sg:postcode":"3821",
    "sg:province":"VIC",
    "sg:tags":[
        "grower",
        "potato"
    ],
    "wof:name":"Pisa F J",
    "wof:placetype":"venue"
},
  "geometry": {"coordinates":[146.018677,-38.108879],"type":"Point"}
}