{
  "type": "Feature",
  "properties": {
    "addr:full":"Cnr Winnima Way & Parkway Ave Berkeley NSW 2506",
    "addr:postcode":"2506",
    "addr:street":"Cnr Winnima Way & Parkway Ave",
    "iso:country":"AU",
    "sg:address":"Cnr Winnima Way & Parkway Ave",
    "sg:city":"Berkeley",
    "sg:classifiers":[
        {
            "category":"Wholesale",
            "subcategory":"Medical Equipment & Supplies",
            "type":"Manufacturing & Wholesale Goods"
        }
    ],
    "sg:phone":"+61 2 4271 1258",
    "sg:postcode":"2506",
    "sg:province":"NSW",
    "sg:tags":[
        "aid",
        "care",
        "health",
        "home"
    ],
    "wof:name":"Berkeley Pharmacy",
    "wof:placetype":"venue"
},
  "geometry": {"coordinates":[150.84785500000001,-34.479057],"type":"Point"}
}