{
  "type": "Feature",
  "properties": {
    "iso:country":"AU",
    "sg:address":"Suite 52",
    "sg:city":"/Ground Floor Sanford Jackson Building Wesley",
    "sg:classifiers":[
        {
            "category":"Health Services",
            "subcategory":"Doctor",
            "type":"Services"
        }
    ],
    "sg:phone":"+61 7 3232 6566",
    "sg:postcode":"4066",
    "sg:province":"QLD",
    "sg:tags":[
        "medical",
        "practitioner"
    ],
    "wof:name":"Kua Boon Dr",
    "wof:placetype":"venue"
},
  "geometry": {"coordinates":[152.99612426799999,-27.4734096527],"type":"Point"}
}