{
  "type": "Feature",
  "properties": {
    "addr:full":"Shop 15 Camberwell Market 519 Riversdale Rd Camberwell VIC 3124",
    "addr:housenumber":"shop 15;519",
    "addr:postcode":"3124",
    "addr:street":"Camberwell Market;Riversdale Rd",
    "iso:country":"AU",
    "sg:address":"Shop 15 Camberwell Market 519 Riversdale Rd",
    "sg:city":"Camberwell",
    "sg:classifiers":[
        {
            "category":"Food & Beverages",
            "subcategory":"Fruits & Vegetables",
            "type":"Retail Goods"
        }
    ],
    "sg:phone":"+61 3 9813 1736",
    "sg:postcode":"3124",
    "sg:province":"VIC",
    "sg:tags":[
        "greengrocer",
        "fruiterer"
    ],
    "wof:name":"Camberwell Fruit Basket",
    "wof:placetype":"venue"
},
  "geometry": {"coordinates":[145.05763244600001,-37.8313217163],"type":"Point"}
}