{
  "type": "Feature",
  "properties": {
    "addr:full":"6b Pine Ave Hahndorf SA 5245",
    "addr:housenumber":"6b",
    "addr:postcode":"5245",
    "addr:street":"Pine Ave",
    "iso:country":"AU",
    "sg:address":"6b Pine Ave",
    "sg:city":"Hahndorf",
    "sg:classifiers":[
        {
            "category":"Professional",
            "subcategory":"Accounting & Tax Preparation",
            "type":"Services"
        }
    ],
    "sg:phone":"+61 8 8388 7340",
    "sg:postcode":"5245",
    "sg:province":"SA",
    "sg:tags":[
        "accountant",
        "auditor"
    ],
    "wof:name":"O&#039;Donnell & Richardson",
    "wof:placetype":"venue"
},
  "geometry": {"coordinates":[138.80955505399999,-35.0306587219],"type":"Point"}
}