{
  "type": "Feature",
  "properties": {
    "addr:full":"Cnr 19th Ave & Saffron St Elanora QLD 4221",
    "addr:postcode":"4221",
    "addr:street":"Cnr 19Th Ave & Saffron",
    "iso:country":"AU",
    "sg:address":"Cnr 19th Ave & Saffron St",
    "sg:city":"Elanora",
    "sg:classifiers":[
        {
            "category":"Personal",
            "subcategory":"Beauty Salon",
            "type":"Services"
        }
    ],
    "sg:phone":"+61 7 5533 9233",
    "sg:postcode":"4221",
    "sg:province":"QLD",
    "sg:tags":[
        "hairdresser"
    ],
    "wof:name":"Shockwaves Hair Studio",
    "wof:placetype":"venue"
},
  "geometry": {"coordinates":[153.45449829099999,-28.1298217773],"type":"Point"}
}