{
  "type": "Feature",
  "properties": {
    "addr:full":"89 Fullarton Rd Kent Town SA 5067",
    "addr:housenumber":"89",
    "addr:postcode":"5067",
    "addr:street":"Fullarton Rd",
    "iso:country":"AU",
    "sg:address":"89 Fullarton Rd",
    "sg:city":"Kent Town",
    "sg:classifiers":[
        {
            "category":"Shopping",
            "subcategory":"Stationery & Office Supplies",
            "type":"Retail Goods"
        }
    ],
    "sg:phone":"+61 8 8431 6755",
    "sg:postcode":"5067",
    "sg:province":"SA",
    "sg:tags":[
        "equipment",
        "display",
        "exhibition"
    ],
    "wof:name":"AtkinsTechnicolour",
    "wof:placetype":"venue"
},
  "geometry": {"coordinates":[138.62342834500001,-34.9267921448],"type":"Point"}
}