{
  "type": "Feature",
  "properties": {
    "addr:full":"Level 5 88 Phillip St Sydney NSW 2000",
    "addr:housenumber":"88",
    "addr:postcode":"2000",
    "addr:street":"Phillip St",
    "iso:country":"AU",
    "sg:address":"Level 5 88 Phillip St",
    "sg:city":"Sydney",
    "sg:classifiers":[
        {
            "category":"Professional",
            "subcategory":"Art Services",
            "type":"Services"
        }
    ],
    "sg:phone":"+61 2 9252 3810",
    "sg:postcode":"2000",
    "sg:province":"NSW",
    "sg:tags":[
        "graphic",
        "designer"
    ],
    "wof:name":"Gentil Eckersley Pty Ltd",
    "wof:placetype":"venue"
},
  "geometry": {"coordinates":[151.211791992,-33.8648147583],"type":"Point"}
}