{
  "type": "Feature",
  "properties": {
    "addr:full":"239 New Line Rd Dural NSW 2158",
    "addr:housenumber":"239",
    "addr:postcode":"2158",
    "addr:street":"New Line Rd",
    "iso:country":"AU",
    "sg:address":"239 New Line Rd",
    "sg:city":"Dural",
    "sg:classifiers":[
        {
            "category":"Building & Trades",
            "subcategory":"Landscaping Services",
            "type":"Services"
        }
    ],
    "sg:phone":"+61 2 9651 2007",
    "sg:postcode":"2158",
    "sg:province":"NSW",
    "sg:tags":[
        "designer",
        "landscape",
        "contractor"
    ],
    "wof:name":"Urban & Rural Design",
    "wof:placetype":"venue"
},
  "geometry": {"coordinates":[151.03053283700001,-33.6962051392],"type":"Point"}
}