{
  "type": "Feature",
  "properties": {
    "addr:full":"City Link Plaza 24- 36 Morisset St Queanbeyan ACT 2620",
    "addr:housenumber":"36",
    "addr:postcode":"2620",
    "addr:street":"Morisset St",
    "iso:country":"AU",
    "sg:address":"City Link Plaza 24- 36 Morisset St",
    "sg:city":"Queanbeyan",
    "sg:classifiers":[
        {
            "category":"Real Estate",
            "subcategory":"Real Estate Agent",
            "type":"Services"
        }
    ],
    "sg:phone":"+61 2 6297 2222",
    "sg:postcode":"2620",
    "sg:province":"ACT",
    "wof:name":"Realty World Queanbeyan",
    "wof:placetype":"venue"
},
  "geometry": {"coordinates":[149.234100342,-35.3507766724],"type":"Point"}
}