{
  "type": "Feature",
  "properties": {
    "iso:country":"AU",
    "sg:address":"18 Carron Rd",
    "sg:city":"Applecross",
    "sg:classifiers":[
        {
            "category":"Retail",
            "subcategory":"Auto Rental",
            "type":"Services"
        }
    ],
    "sg:phone":"+61 8 9316 2396",
    "sg:postcode":"6153",
    "sg:province":"WA",
    "sg:tags":[
        "chauffeur",
        "car",
        "hire",
        "driven",
        "limousine"
    ],
    "wof:name":"Celebrity Enterprises",
    "wof:placetype":"venue"
},
  "geometry": {"coordinates":[115.845833,-32.007294],"type":"Point"}
}