{
  "type": "Feature",
  "properties": {
    "addr:full":"PO Box 1135 Golden Grove SA 5125",
    "addr:postcode":"5125",
    "iso:country":"AU",
    "sg:address":"PO Box 1135",
    "sg:city":"Golden Grove",
    "sg:classifiers":[
        {
            "category":"Shopping",
            "subcategory":"Party Supplies",
            "type":"Retail Goods"
        }
    ],
    "sg:phone":"+61 408 841 624",
    "sg:postcode":"5125",
    "sg:province":"SA",
    "sg:tags":[
        "children's"
    ],
    "wof:name":"Mr B Giggles",
    "wof:placetype":"venue"
},
  "geometry": {"coordinates":[138.693893,-34.791088],"type":"Point"}
}