{
  "type": "Feature",
  "properties": {
    "iso:country":"AU",
    "sg:address":"97 Darley St",
    "sg:city":"Mona Vale",
    "sg:classifiers":[
        {
            "category":"Autos & Motor Vehicles",
            "subcategory":"Boat Sales",
            "type":"Retail Goods"
        }
    ],
    "sg:phone":"+61 2 9997 7797",
    "sg:postcode":"2103",
    "sg:province":"NSW",
    "sg:tags":[
        "yacht"
    ],
    "wof:name":"Haines Signature",
    "wof:placetype":"venue"
},
  "geometry": {"coordinates":[151.304489136,-33.6740951538],"type":"Point"}
}