{
  "type": "Feature",
  "properties": {
    "iso:country":"AU",
    "sg:address":"4/ 128 Melbourne St",
    "sg:city":"East Maitland",
    "sg:classifiers":[
        {
            "category":"Building & Trades",
            "subcategory":"Construction",
            "type":"Services"
        }
    ],
    "sg:phone":"+61 2 4934 1522",
    "sg:postcode":"2323",
    "sg:province":"NSW",
    "sg:tags":[
        "spouting",
        "guttering"
    ],
    "wof:name":"JT Guttering Pty Ltd",
    "wof:placetype":"venue"
},
  "geometry": {"coordinates":[151.58140564000001,-32.7469406128],"type":"Point"}
}