{
  "type": "Feature",
  "properties": {
    "addr:full":"5th Floor National Australia Bank House 22 King William St Adelaide SA 5000",
    "addr:housenumber":"22",
    "addr:postcode":"5000",
    "addr:street":"King William St",
    "iso:country":"AU",
    "sg:address":"5th Floor National Australia Bank House 22 King William St",
    "sg:city":"Adelaide",
    "sg:classifiers":[
        {
            "category":"Health Services",
            "subcategory":"Dentist",
            "type":"Services"
        }
    ],
    "sg:phone":"+61 8 8212 2332",
    "sg:postcode":"5000",
    "sg:province":"SA",
    "wof:name":"Lockwood Kym W",
    "wof:placetype":"venue"
},
  "geometry": {"coordinates":[138.59971618599999,-34.9223823547],"type":"Point"}
}