{
  "type": "Feature",
  "properties": {
    "addr:full":"50 Melbourne St North Adelaide SA 5006",
    "addr:housenumber":"50",
    "addr:postcode":"5006",
    "addr:street":"Melbourne St",
    "iso:country":"AU",
    "sg:address":"50 Melbourne St",
    "sg:city":"North Adelaide",
    "sg:classifiers":[
        {
            "category":"Health Services",
            "subcategory":"Health Practitioner",
            "type":"Services"
        }
    ],
    "sg:phone":"+61 8 8267 1188",
    "sg:postcode":"5006",
    "sg:province":"SA",
    "sg:tags":[
        "physiotherapist"
    ],
    "wof:name":"Physio One",
    "wof:placetype":"venue"
},
  "geometry": {"coordinates":[138.60896301299999,-34.9060134888],"type":"Point"}
}