{
  "type": "Feature",
  "properties": {
    "addr:full":"9/88 Cnr Pimpama Jacobs Well Rd & Old Pacific Hwy Pimpama QLD 4209",
    "addr:housenumber":"/ 88",
    "addr:postcode":"4209",
    "addr:street":"Cnr Pimpama Jacobs Well Rd & Old Pacific Hwy",
    "iso:country":"AU",
    "sg:address":"9/88 Cnr Pimpama Jacobs Well Rd & Old Pacific Hwy",
    "sg:city":"Pimpama",
    "sg:classifiers":[
        {
            "category":"Real Estate",
            "subcategory":"Real Estate Agent",
            "type":"Services"
        }
    ],
    "sg:phone":"+61 7 5547 5577",
    "sg:postcode":"4209",
    "sg:province":"QLD",
    "wof:name":"Natgroup Real Estate",
    "wof:placetype":"venue"
},
  "geometry": {"coordinates":[153.314361572,-27.883808136],"type":"Point"}
}