{
  "type": "Feature",
  "properties": {
    "addr:full":"77 Henry St Quirindi NSW 2343",
    "addr:housenumber":"77",
    "addr:postcode":"2343",
    "addr:street":"Henry St",
    "iso:country":"AU",
    "sg:address":"77 Henry St",
    "sg:city":"Quirindi",
    "sg:classifiers":[
        {
            "category":"Retail",
            "subcategory":"Auto Repair",
            "type":"Services"
        }
    ],
    "sg:phone":"+61 2 6746 1808",
    "sg:postcode":"2343",
    "sg:province":"NSW",
    "sg:tags":[
        "repairer",
        "motor",
        "engineer"
    ],
    "wof:name":"Rick Jones Automotive",
    "wof:placetype":"venue"
},
  "geometry": {"coordinates":[150.681472778,-31.5082397461],"type":"Point"}
}