{
  "type": "Feature",
  "properties": {
    "addr:full":"286 Hay St Perth WA 6000",
    "addr:housenumber":"286",
    "addr:postcode":"6000",
    "addr:street":"Hay St",
    "iso:country":"AU",
    "sg:address":"286 Hay St",
    "sg:city":"Perth",
    "sg:classifiers":[
        {
            "category":"Banks & Credit Unions",
            "subcategory":"Investment Brokerage",
            "type":"Services"
        }
    ],
    "sg:phone":"+61 8 9225 5044",
    "sg:postcode":"6000",
    "sg:province":"WA",
    "wof:name":"The Rare Coin Company",
    "wof:placetype":"venue"
},
  "geometry": {"coordinates":[115.856163025,-31.9533920288],"type":"Point"}
}