{
  "type": "Feature",
  "properties": {
    "addr:full":"267 Stewart St Bathurst NSW 2795",
    "addr:housenumber":"267",
    "addr:postcode":"2795",
    "addr:street":"Stewart St",
    "iso:country":"AU",
    "sg:address":"267 Stewart St",
    "sg:city":"Bathurst",
    "sg:classifiers":[
        {
            "category":"Autos & Motor Vehicles",
            "subcategory":"Automobile Sales",
            "type":"Retail Goods"
        }
    ],
    "sg:phone":"+61 2 6332 3716",
    "sg:postcode":"2795",
    "sg:province":"NSW",
    "sg:tags":[
        "car",
        "used"
    ],
    "wof:name":"Dean's Quality Cars & Commercials",
    "wof:placetype":"venue"
},
  "geometry": {"coordinates":[149.508575439,-33.4366264343],"type":"Point"}
}