{
  "type": "Feature",
  "properties": {
    "iso:country":"AU",
    "sg:address":"10 Parsons La",
    "sg:city":"Olinda",
    "sg:classifiers":[
        {
            "category":"Arts & Performance",
            "subcategory":"Art Gallery",
            "type":"Entertainment"
        }
    ],
    "sg:phone":"+61 3 9751 1813",
    "sg:postcode":"3788",
    "sg:province":"VIC",
    "wof:name":"Olinda Art Gallery",
    "wof:placetype":"venue"
},
  "geometry": {"coordinates":[145.365341,-37.855042],"type":"Point"}
}