{
  "type": "Feature",
  "properties": {
    "iso:country":"AU",
    "sg:address":"35 Lee St",
    "sg:city":"Wellington",
    "sg:classifiers":[
        {
            "category":"Retail",
            "subcategory":"Car Wash",
            "type":"Services"
        }
    ],
    "sg:phone":"+61 2 6845 1203",
    "sg:postcode":"2820",
    "sg:province":"NSW",
    "sg:tags":[
        "merchant",
        "oil",
        "refiner"
    ],
    "wof:name":"Notts Rural & Domestic",
    "wof:placetype":"venue"
},
  "geometry": {"coordinates":[148.94145202600001,-32.5521812439],"type":"Point"}
}