{
  "type": "Feature",
  "properties": {
    "iso:country":"AU",
    "sg:address":"6 Tay St",
    "sg:city":"South Mackay",
    "sg:classifiers":[
        {
            "category":"Building & Trades",
            "subcategory":"Construction",
            "type":"Services"
        }
    ],
    "sg:phone":"+61 7 4957 3715",
    "sg:postcode":"4740",
    "sg:province":"QLD",
    "sg:tags":[
        "contractor"
    ],
    "wof:name":"Dean, IW & GM",
    "wof:placetype":"venue"
},
  "geometry": {"coordinates":[149.180679,-21.151546],"type":"Point"}
}