{
  "type": "Feature",
  "properties": {
    "addr:full":"20 Oakwood Drv Keysborough VIC 3173",
    "addr:housenumber":"20",
    "addr:postcode":"3173",
    "addr:street":"Oakwood Drv",
    "iso:country":"AU",
    "sg:address":"20 Oakwood Drv",
    "sg:city":"Keysborough",
    "sg:classifiers":[
        {
            "category":"Professional",
            "subcategory":"Computer Services",
            "type":"Services"
        }
    ],
    "sg:phone":"+61 411 525 239",
    "sg:postcode":"3173",
    "sg:province":"VIC",
    "sg:tags":[
        "training"
    ],
    "wof:name":"Springvale Word Processing Bureau",
    "wof:placetype":"venue"
},
  "geometry": {"coordinates":[145.15721130399999,-37.9937744141],"type":"Point"}
}