{
  "type": "Feature",
  "properties": {
    "addr:full":"PO Box 132 Exeter TAS 7275",
    "addr:postcode":"7275",
    "iso:country":"AU",
    "sg:address":"PO Box 132",
    "sg:city":"Exeter",
    "sg:classifiers":[
        {
            "category":"Government",
            "subcategory":"Court House",
            "type":"Public Place"
        }
    ],
    "sg:phone":"+61 418 541 164",
    "sg:postcode":"7275",
    "sg:province":"TAS",
    "sg:tags":[
        "personal",
        "marriage",
        "family",
        "counselling"
    ],
    "wof:name":"Crewes Ruth",
    "wof:placetype":"venue"
},
  "geometry": {"coordinates":[146.95248413100001,-41.2995185852],"type":"Point"}
}