{
  "type": "Feature",
  "properties": {
    "iso:country":"AU",
    "sg:address":"PO Box 514",
    "sg:city":"Hamilton",
    "sg:classifiers":[
        {
            "category":"Education",
            "subcategory":"Dance Studio",
            "type":"Public Place"
        }
    ],
    "sg:phone":"+61 438 428 221",
    "sg:postcode":"2303",
    "sg:province":"NSW",
    "sg:tags":[
        "venue",
        "tuition"
    ],
    "wof:name":"Belly Dancing School Freespirit",
    "wof:placetype":"venue"
},
  "geometry": {"coordinates":[151.746994,-32.923489],"type":"Point"}
}