{
  "type": "Feature",
  "properties": {
    "iso:country":"AU",
    "sg:address":"16 George St",
    "sg:city":"Hornsby",
    "sg:classifiers":[
        {
            "category":"Professional",
            "subcategory":"Accounting & Tax Preparation",
            "type":"Services"
        }
    ],
    "sg:phone":"+61 2 9482 1095",
    "sg:postcode":"2077",
    "sg:province":"NSW",
    "sg:tags":[
        "consultant",
        "taxation"
    ],
    "wof:name":"Elton & Associates",
    "wof:placetype":"venue"
},
  "geometry": {"coordinates":[151.09916687,-33.7035064697],"type":"Point"}
}