{
  "type": "Feature",
  "properties": {
    "iso:country":"AU",
    "sg:address":"77 Carlisle St St",
    "sg:city":"Kilda",
    "sg:classifiers":[
        {
            "category":"Health Services",
            "subcategory":"Health Practitioner",
            "type":"Services"
        }
    ],
    "sg:phone":"+61 3 9534 7127",
    "sg:postcode":"3182",
    "sg:province":"VIC",
    "sg:tags":[
        "acupuncture"
    ],
    "wof:name":"D&#039;Amico Nicola",
    "wof:placetype":"venue"
},
  "geometry": {"coordinates":[144.98452758799999,-37.86769104],"type":"Point"}
}