{
  "type": "Feature",
  "properties": {
    "addr:full":"29 Healey Rd Dandenong VIC 3175",
    "addr:housenumber":"29",
    "addr:postcode":"3175",
    "addr:street":"Healey Rd",
    "iso:country":"AU",
    "sg:address":"29 Healey Rd",
    "sg:city":"Dandenong",
    "sg:classifiers":[
        {
            "category":"Home & Garden",
            "subcategory":"Building Materials",
            "type":"Retail Goods"
        }
    ],
    "sg:phone":"+61 3 9706 5488",
    "sg:postcode":"3175",
    "sg:province":"VIC",
    "sg:tags":[
        "supply"
    ],
    "wof:name":"Pryda (Aust) Pty Ltd",
    "wof:placetype":"venue"
},
  "geometry": {"coordinates":[145.22642517099999,-38.028793335],"type":"Point"}
}