{
  "type": "Feature",
  "properties": {
    "iso:country":"AU",
    "sg:address":"10 Banach St",
    "sg:city":"Maddington",
    "sg:classifiers":[
        {
            "category":"Building & Trades",
            "subcategory":"Landscaping Services",
            "type":"Services"
        }
    ],
    "sg:phone":"+61 417 912 939",
    "sg:postcode":"6109",
    "sg:province":"WA",
    "sg:tags":[
        "stump",
        "tree",
        "felling",
        "removal"
    ],
    "wof:name":"T.A.G. Tree Service",
    "wof:placetype":"venue"
},
  "geometry": {"coordinates":[116.001037598,-32.0611381531],"type":"Point"}
}