{
  "type": "Feature",
  "properties": {
    "addr:full":"13b Eileen Rd Clayton VIC 3168",
    "addr:housenumber":"13b",
    "addr:postcode":"3168",
    "addr:street":"Eileen Rd",
    "iso:country":"AU",
    "sg:address":"13b Eileen Rd",
    "sg:city":"Clayton",
    "sg:classifiers":[
        {
            "category":"Professional",
            "type":"Services"
        }
    ],
    "sg:phone":"+61 3 9540 3400",
    "sg:postcode":"3168",
    "sg:province":"VIC",
    "sg:tags":[
        "transport"
    ],
    "wof:name":"D&#039;Alterio L Transport Pty Ltd",
    "wof:placetype":"venue"
},
  "geometry": {"coordinates":[145.124755859,-37.899181366],"type":"Point"}
}