{
  "type": "Feature",
  "properties": {
    "iso:country":"AU",
    "sg:address":"169 Kinghorne St",
    "sg:city":"Nowra",
    "sg:classifiers":[
        {
            "category":"Autos & Motor Vehicles",
            "subcategory":"Auto Supplies",
            "type":"Retail Goods"
        }
    ],
    "sg:phone":"+61 2 4423 5939",
    "sg:postcode":"2541",
    "sg:province":"NSW",
    "sg:tags":[
        "tyre"
    ],
    "wof:name":"Nowra Tyre & 4WD Centre",
    "wof:placetype":"venue"
},
  "geometry": {"coordinates":[150.60038757300001,-34.8867645264],"type":"Point"}
}