{
  "type": "Feature",
  "properties": {
    "addr:full":"69 Bay St Mosman NSW 2088",
    "addr:housenumber":"69",
    "addr:postcode":"2088",
    "addr:street":"Bay St",
    "iso:country":"AU",
    "sg:address":"69 Bay St",
    "sg:city":"Mosman",
    "sg:classifiers":[
        {
            "category":"Professional",
            "subcategory":"Engineering",
            "type":"Services"
        }
    ],
    "sg:phone":"+61 2 9960 6820",
    "sg:postcode":"2088",
    "sg:province":"NSW",
    "sg:tags":[
        "consulting",
        "engineer"
    ],
    "wof:name":"MacLeod Consultants Pty Ltd",
    "wof:placetype":"venue"
},
  "geometry": {"coordinates":[151.23823547399999,-33.8129272461],"type":"Point"}
}