{
  "type": "Feature",
  "properties": {
    "addr:full":"2a Waters Rd Neutral Bay NSW 2089",
    "addr:housenumber":"2a",
    "addr:postcode":"2089",
    "addr:street":"Waters Rd",
    "iso:country":"AU",
    "sg:address":"2a Waters Rd",
    "sg:city":"Neutral Bay",
    "sg:classifiers":[
        {
            "category":"Shopping",
            "subcategory":"Clothing, Apparel, & Fashions",
            "type":"Retail Goods"
        }
    ],
    "sg:phone":"+61 2 9953 9221",
    "sg:postcode":"2089",
    "sg:province":"NSW",
    "sg:tags":[
        "recycled",
        "clothing"
    ],
    "wof:name":"Re Cycology",
    "wof:placetype":"venue"
},
  "geometry": {"coordinates":[151.223220825,-33.8313331604],"type":"Point"}
}