{
  "type": "Feature",
  "properties": {
    "addr:full":"14 Cusack St Wangaratta VIC 3677",
    "addr:housenumber":"14",
    "addr:postcode":"3677",
    "addr:street":"Cusack St",
    "iso:country":"AU",
    "sg:address":"14 Cusack St",
    "sg:city":"Wangaratta",
    "sg:classifiers":[
        {
            "category":"Banks & Credit Unions",
            "subcategory":"Investment Brokerage",
            "type":"Services"
        }
    ],
    "sg:phone":"+61 3 5721 7879",
    "sg:postcode":"3677",
    "sg:province":"VIC",
    "sg:tags":[
        "care",
        "day",
        "family",
        "child"
    ],
    "wof:name":"Family Day Care",
    "wof:placetype":"venue"
},
  "geometry": {"coordinates":[146.318847656,-36.3561668396],"type":"Point"}
}