{
  "type": "Feature",
  "properties": {
    "addr:full":"15 Kallista Rd Rochedale QLD 4123",
    "addr:housenumber":"15",
    "addr:postcode":"4123",
    "addr:street":"Kallista Rd",
    "iso:country":"AU",
    "sg:address":"15 Kallista Rd",
    "sg:city":"Rochedale",
    "sg:classifiers":[
        {
            "category":"Professional",
            "subcategory":"Engineering",
            "type":"Services"
        }
    ],
    "sg:phone":"+61 418 985 522",
    "sg:postcode":"4123",
    "sg:province":"QLD",
    "sg:tags":[
        "engineer",
        "mechanical"
    ],
    "wof:name":"Mechanical Magic",
    "wof:placetype":"venue"
},
  "geometry": {"coordinates":[153.142776489,-27.593624115],"type":"Point"}
}