{
  "type": "Feature",
  "properties": {
    "iso:country":"AU",
    "sg:address":"Unit 5/31- 37 Howleys Rd",
    "sg:city":"Notting Hill",
    "sg:classifiers":[
        {
            "category":"Manufacturing",
            "subcategory":"Paper Products",
            "type":"Manufacturing & Wholesale Goods"
        }
    ],
    "sg:phone":"+61 1300 363 380",
    "sg:postcode":"3168",
    "sg:province":"VIC",
    "sg:tags":[
        "disposable"
    ],
    "wof:name":"Detpak",
    "wof:placetype":"venue"
},
  "geometry": {"coordinates":[145.13752746599999,-37.9041213989],"type":"Point"}
}