{
  "type": "Feature",
  "properties": {
    "addr:full":"2 Kuru Crt Brinkin NT 0810",
    "addr:housenumber":"2",
    "addr:postcode":"nt 0810",
    "addr:street":"Kuru Crt",
    "iso:country":"AU",
    "sg:address":"2 Kuru Crt",
    "sg:city":"Brinkin",
    "sg:classifiers":[
        {
            "category":"Building & Trades",
            "subcategory":"Construction",
            "type":"Services"
        }
    ],
    "sg:phone":"+61 8 8945 4175",
    "sg:postcode":"0810",
    "sg:province":"NT",
    "sg:tags":[
        "concrete",
        "contractor"
    ],
    "wof:name":"JGA Concreting",
    "wof:placetype":"venue"
},
  "geometry": {"coordinates":[130.86752319300001,-12.3665714264],"type":"Point"}
}