{
  "type": "Feature",
  "properties": {
    "addr:full":"12 Schiller St Wagga Wagga NSW 2650",
    "addr:postcode":"2650",
    "addr:street":"Schiller St",
    "iso:country":"AU",
    "sg:address":"12 Schiller St",
    "sg:city":"Wagga Wagga",
    "sg:classifiers":[
        {
            "category":"Freight",
            "type":"Transportation"
        }
    ],
    "sg:phone":"+61 2 6971 7200",
    "sg:postcode":"2650",
    "sg:province":"NSW",
    "sg:tags":[
        "light",
        "carrier"
    ],
    "wof:name":"JWS Transport Pty Ltd",
    "wof:placetype":"venue"
},
  "geometry": {"coordinates":[147.41371154800001,-35.1266708374],"type":"Point"}
}