{
  "type": "Feature",
  "properties": {
    "addr:full":"Unit 10/ 25 George St North Strathfield NSW 2137",
    "addr:housenumber":"/ 25",
    "addr:postcode":"2137",
    "addr:street":"George St",
    "iso:country":"AU",
    "sg:address":"Unit 10/ 25 George St",
    "sg:city":"North Strathfield",
    "sg:classifiers":[
        {
            "category":"Home & Garden",
            "subcategory":"Furniture",
            "type":"Retail Goods"
        }
    ],
    "sg:phone":"+61 2 9743 5751",
    "sg:postcode":"2137",
    "sg:province":"NSW",
    "sg:tags":[
        "business"
    ],
    "wof:name":"Ultimate Furniture Pty Ltd",
    "wof:placetype":"venue"
},
  "geometry": {"coordinates":[151.08526611299999,-33.85364151],"type":"Point"}
}