{
  "type": "Feature",
  "properties": {
    "iso:country":"AU",
    "sg:address":"129 Mentone Pde",
    "sg:city":"Mentone",
    "sg:classifiers":[
        {
            "category":"Food & Beverages",
            "subcategory":"Bakery",
            "type":"Retail Goods"
        }
    ],
    "sg:phone":"+61 3 9583 2091",
    "sg:postcode":"3194",
    "sg:province":"VIC",
    "sg:tags":[
        "cake",
        "shop",
        "pastry"
    ],
    "wof:name":"Sunbeam Cakes",
    "wof:placetype":"venue"
},
  "geometry": {"coordinates":[145.06471252399999,-37.9830513],"type":"Point"}
}