{
  "type": "Feature",
  "properties": {
    "iso:country":"AU",
    "sg:address":"465 Fitzgerald St",
    "sg:city":"North Perth",
    "sg:classifiers":[
        {
            "category":"Manufacturing",
            "subcategory":"Motor Vehicles & Parts",
            "type":"Manufacturing & Wholesale Goods"
        }
    ],
    "sg:phone":"+61 8 9228 3688",
    "sg:postcode":"6006",
    "sg:province":"WA",
    "sg:tags":[
        "replacement"
    ],
    "wof:name":"Perth Spare Parts Centre",
    "wof:placetype":"venue"
},
  "geometry": {"coordinates":[115.859031677,-31.9304580688],"type":"Point"}
}