{
  "type": "Feature",
  "properties": {
    "addr:full":"486 Pacific Hwy Belmont NSW 2280",
    "addr:housenumber":"486",
    "addr:postcode":"2280",
    "addr:street":"Pacific Hwy",
    "iso:country":"AU",
    "sg:address":"486 Pacific Hwy",
    "sg:city":"Belmont",
    "sg:classifiers":[
        {
            "category":"Health Services",
            "subcategory":"Dentist",
            "type":"Services"
        }
    ],
    "sg:phone":"+61 2 4945 4331",
    "sg:postcode":"2280",
    "sg:province":"NSW",
    "wof:name":"Driver A K",
    "wof:placetype":"venue"
},
  "geometry": {"coordinates":[151.660598755,-33.0324668884],"type":"Point"}
}