{
  "type": "Feature",
  "properties": {
    "addr:full":"261 Morayfield Rd Morayfield QLD 4506",
    "addr:housenumber":"261",
    "addr:postcode":"4506",
    "addr:street":"Morayfield Rd",
    "iso:country":"AU",
    "sg:address":"261 Morayfield Rd",
    "sg:city":"Morayfield",
    "sg:classifiers":[
        {
            "category":"Autos & Motor Vehicles",
            "subcategory":"Auto Supplies",
            "type":"Retail Goods"
        }
    ],
    "sg:phone":"+61 7 5433 0811",
    "sg:postcode":"4506",
    "sg:province":"QLD",
    "sg:tags":[
        "camper-trailers",
        "caravan",
        "equipment"
    ],
    "wof:name":"Sunland Caravans",
    "wof:placetype":"venue"
},
  "geometry": {"coordinates":[152.95159912099999,-27.1124744415],"type":"Point"}
}