{
  "type": "Feature",
  "properties": {
    "iso:country":"AU",
    "sg:address":"PCYC Building Cnr Wickham & Church Sts",
    "sg:city":"Fortitude Valley",
    "sg:classifiers":[
        {
            "category":"Education",
            "subcategory":"Dance Studio",
            "type":"Public Place"
        }
    ],
    "sg:phone":"+61 7 3252 2617",
    "sg:postcode":"4006",
    "sg:province":"QLD",
    "sg:tags":[
        "venue",
        "tuition"
    ],
    "sg:website":"http://www.orchardsdance.om",
    "wof:name":"Orchards Dancing Academy",
    "wof:placetype":"venue"
},
  "geometry": {"coordinates":[153.03384399399999,-27.457277298],"type":"Point"}
}