{
  "type": "Feature",
  "properties": {
    "addr:full":"58 Oramzi Rd Girraween NSW 2145",
    "addr:housenumber":"58",
    "addr:postcode":"2145",
    "addr:street":"Oramzi Rd",
    "iso:country":"AU",
    "sg:address":"58 Oramzi Rd",
    "sg:city":"Girraween",
    "sg:classifiers":[
        {
            "category":"Recreation",
            "type":"Entertainment"
        }
    ],
    "sg:phone":"+61 2 9863 4543",
    "sg:postcode":"2145",
    "sg:province":"NSW",
    "sg:tags":[
        "children's",
        "play",
        "programme"
    ],
    "wof:name":"Mainart and Mullins Entertainment",
    "wof:placetype":"venue"
},
  "geometry": {"coordinates":[150.94627380399999,-33.7951545715],"type":"Point"}
}