{
  "type": "Feature",
  "properties": {
    "addr:full":"Arcadia Rd (cnr Sooning St) Nelly Bay QLD 4819",
    "addr:postcode":"4819",
    "addr:street":"Arcadia Rd Cnr Sooning St",
    "iso:country":"AU",
    "sg:address":"Arcadia Rd (cnr Sooning St)",
    "sg:city":"Nelly Bay",
    "sg:classifiers":[
        {
            "category":"Real Estate",
            "subcategory":"Real Estate Agent",
            "type":"Services"
        }
    ],
    "sg:phone":"+61 7 4778 5588",
    "sg:postcode":"4819",
    "sg:province":"QLD",
    "wof:name":"Compass Property Group",
    "wof:placetype":"venue"
},
  "geometry": {"coordinates":[146.85690299999999,-19.157665],"type":"Point"}
}