{
  "type": "Feature",
  "properties": {
    "addr:full":"Shop 3/ 327 Nudgee Rd Hendra QLD 4011",
    "addr:housenumber":"shop 3 / 327",
    "addr:postcode":"4011",
    "addr:street":"Nudgee Rd",
    "iso:country":"AU",
    "sg:address":"Shop 3/ 327 Nudgee Rd",
    "sg:city":"Hendra",
    "sg:classifiers":[
        {
            "category":"Personal",
            "subcategory":"Beauty Salon",
            "type":"Services"
        }
    ],
    "sg:phone":"+61 7 3868 2770",
    "sg:postcode":"4011",
    "sg:province":"QLD",
    "sg:tags":[
        "hair",
        "wedding"
    ],
    "wof:name":"Lucia's Place Hair & Beauty",
    "wof:placetype":"venue"
},
  "geometry": {"coordinates":[153.073624,-27.419725],"type":"Point"}
}