{
  "type": "Feature",
  "properties": {
    "addr:full":"31 Crombie Ave Bundall QLD 4217",
    "addr:housenumber":"31",
    "addr:postcode":"4217",
    "addr:street":"Crombie Ave",
    "iso:country":"AU",
    "sg:address":"31 Crombie Ave",
    "sg:city":"Bundall",
    "sg:classifiers":[
        {
            "category":"Real Estate",
            "subcategory":"Real Estate Agent",
            "type":"Services"
        }
    ],
    "sg:phone":"+61 7 5574 2033",
    "sg:postcode":"4217",
    "sg:province":"QLD",
    "wof:name":"Coldwell Banker Commercial Chateaux Realty",
    "wof:placetype":"venue"
},
  "geometry": {"coordinates":[153.412200928,-28.0029468536],"type":"Point"}
}