{
  "type": "Feature",
  "properties": {
    "addr:full":"Shp7/ 105 Longueville Rd Lane Cove NSW 2066",
    "addr:housenumber":"105",
    "addr:postcode":"2066",
    "addr:street":"Longueville Rd",
    "iso:country":"AU",
    "sg:address":"Shp7/ 105 Longueville Rd",
    "sg:city":"Lane Cove",
    "sg:classifiers":[
        {
            "category":"Shopping",
            "subcategory":"Clothing, Apparel, & Fashions",
            "type":"Retail Goods"
        }
    ],
    "sg:phone":"+61 2 9418 6139",
    "sg:postcode":"2066",
    "sg:province":"NSW",
    "sg:tags":[
        "lady",
        "wear"
    ],
    "wof:name":"Emily Collections",
    "wof:placetype":"venue"
},
  "geometry": {"coordinates":[151.170043945,-33.8142242432],"type":"Point"}
}