{
  "type": "Feature",
  "properties": {
    "iso:country":"AU",
    "sg:address":"2337 Sandgate Rd",
    "sg:city":"Boondall",
    "sg:classifiers":[
        {
            "category":"Personal",
            "subcategory":"Beauty Salon",
            "type":"Services"
        }
    ],
    "sg:phone":"+61 7 3265 3388",
    "sg:postcode":"4034",
    "sg:province":"QLD",
    "sg:tags":[
        "hairdresser"
    ],
    "wof:name":"Boondall Hairdressing",
    "wof:placetype":"venue"
},
  "geometry": {"coordinates":[153.060486,-27.348919],"type":"Point"}
}