{
  "type": "Feature",
  "properties": {
    "addr:full":"2 Hugh Guinea Crt Mudgeeraba QLD 4213",
    "addr:housenumber":"2",
    "addr:postcode":"4213",
    "addr:street":"Hugh Guinea Crt",
    "iso:country":"AU",
    "sg:address":"2 Hugh Guinea Crt",
    "sg:city":"Mudgeeraba",
    "sg:classifiers":[
        {
            "category":"Building & Trades",
            "subcategory":"Landscaping Services",
            "type":"Services"
        }
    ],
    "sg:phone":"+61 405 057 101",
    "sg:postcode":"4213",
    "sg:province":"QLD",
    "sg:tags":[
        "stump",
        "tree",
        "felling",
        "removal"
    ],
    "wof:name":"Clean Cut Tree Services",
    "wof:placetype":"venue"
},
  "geometry": {"coordinates":[153.32908630399999,-28.0453586578],"type":"Point"}
}