{
  "type": "Feature",
  "properties": {
    "addr:full":"Shop 7 Rintoull St Morwell VIC 3840",
    "addr:housenumber":"shop 7",
    "addr:postcode":"3840",
    "addr:street":"Rintoull St",
    "iso:country":"AU",
    "sg:address":"Shop 7 Rintoull St",
    "sg:city":"Morwell",
    "sg:classifiers":[
        {
            "category":"Personal",
            "subcategory":"Beauty Salon",
            "type":"Services"
        }
    ],
    "sg:phone":"+61 3 5133 9398",
    "sg:postcode":"3840",
    "sg:province":"VIC",
    "sg:tags":[
        "hairdresser"
    ],
    "wof:name":"Shear Perfection Hair Design",
    "wof:placetype":"venue"
},
  "geometry": {"coordinates":[146.41444397000001,-38.2334442139],"type":"Point"}
}