{
  "type": "Feature",
  "properties": {
    "addr:full":"56 Hockings St Clayfield QLD 4011",
    "addr:housenumber":"56",
    "addr:postcode":"4011",
    "addr:street":"Hockings St",
    "iso:country":"AU",
    "sg:address":"56 Hockings St",
    "sg:city":"Clayfield",
    "sg:classifiers":[
        {
            "category":"Communications",
            "subcategory":"News Services",
            "type":"Services"
        }
    ],
    "sg:phone":"+61 420 813 967",
    "sg:postcode":"4011",
    "sg:province":"QLD",
    "sg:tags":[
        "information",
        "tourist",
        "attractions"
    ],
    "wof:name":"Brisbane Raceday Tours",
    "wof:placetype":"venue"
},
  "geometry": {"coordinates":[153.055283,-27.412607],"type":"Point"}
}