{
  "type": "Feature",
  "properties": {
    "iso:country":"AU",
    "sg:address":"Un 18/ 134 Ocean St",
    "sg:city":"Narrabeen",
    "sg:classifiers":[
        {
            "category":"Building & Trades",
            "subcategory":"Construction",
            "type":"Services"
        }
    ],
    "sg:phone":"+61 2 9913 2753",
    "sg:postcode":"2101",
    "sg:province":"NSW",
    "sg:tags":[
        "contractor"
    ],
    "wof:name":"Rytek Constructions Pty Ltd",
    "wof:placetype":"venue"
},
  "geometry": {"coordinates":[151.30088799999999,-33.711098],"type":"Point"}
}