{
  "type": "Feature",
  "properties": {
    "addr:full":"301 George St Sydney NSW 2000",
    "addr:housenumber":"301",
    "addr:postcode":"2000",
    "addr:street":"George St",
    "iso:country":"AU",
    "sg:address":"301 George St",
    "sg:city":"Sydney",
    "sg:classifiers":[
        {
            "category":"Personal",
            "subcategory":"Beauty Salon",
            "type":"Services"
        }
    ],
    "sg:phone":"+61 2 9262 3215",
    "sg:postcode":"2000",
    "sg:province":"NSW",
    "wof:name":"Lady Tang's Beauty Salon",
    "wof:placetype":"venue"
},
  "geometry": {"coordinates":[151.20701599099999,-33.8658905029],"type":"Point"}
}