{
  "type": "Feature",
  "properties": {
    "addr:full":"60 Liverpool St Hobart TAS 7000",
    "addr:housenumber":"60",
    "addr:postcode":"7000",
    "addr:street":"Liverpool St",
    "iso:country":"AU",
    "sg:address":"60 Liverpool St",
    "sg:city":"Hobart",
    "sg:classifiers":[
        {
            "category":"Travel",
            "subcategory":"Travel Agent",
            "type":"Entertainment"
        }
    ],
    "sg:phone":"+61 3 6231 1522",
    "sg:postcode":"7000",
    "sg:province":"TAS",
    "sg:tags":[
        "consultant"
    ],
    "wof:name":"Harvey World Travel",
    "wof:placetype":"venue"
},
  "geometry": {"coordinates":[147.32818603499999,-42.8805656433],"type":"Point"}
}