{
  "type": "Feature",
  "properties": {
    "addr:full":"3/ 84 Musgrave St Indooroopilly QLD 4068",
    "addr:housenumber":"/ 84",
    "addr:postcode":"4068",
    "addr:street":"Musgrave St",
    "iso:country":"AU",
    "sg:address":"3/ 84 Musgrave St",
    "sg:city":"Indooroopilly",
    "sg:classifiers":[
        {
            "category":"Professional",
            "subcategory":"Management & Consulting",
            "type":"Services"
        }
    ],
    "sg:phone":"+61 7 3378 4620",
    "sg:postcode":"4068",
    "sg:province":"QLD",
    "sg:tags":[
        "consultant"
    ],
    "wof:name":"Sice, Shane",
    "wof:placetype":"venue"
},
  "geometry": {"coordinates":[152.9715271,-27.50248909],"type":"Point"}
}