{
  "type": "Feature",
  "properties": {
    "addr:full":"118b Bradley St Guyra NSW 2365",
    "addr:housenumber":"118b",
    "addr:postcode":"2365",
    "addr:street":"Bradley St",
    "iso:country":"AU",
    "sg:address":"118b Bradley St",
    "sg:city":"Guyra",
    "sg:classifiers":[
        {
            "category":"Personal",
            "subcategory":"Beauty Salon",
            "type":"Services"
        }
    ],
    "sg:phone":"+61 2 6779 2224",
    "sg:postcode":"2365",
    "sg:province":"NSW",
    "wof:name":"Body & Soul Sanctum",
    "wof:placetype":"venue"
},
  "geometry": {"coordinates":[151.67161560100001,-30.2187671661],"type":"Point"}
}