{
  "type": "Feature",
  "properties": {
    "addr:full":"PO Box 305 Padstow NSW 2211",
    "addr:postcode":"2211",
    "iso:country":"AU",
    "sg:address":"PO Box 305",
    "sg:city":"Padstow",
    "sg:classifiers":[
        {
            "category":"Building & Trades",
            "subcategory":"Cleaning & Sanitation",
            "type":"Services"
        }
    ],
    "sg:phone":"+61 2 9758 5331",
    "sg:postcode":"2211",
    "sg:province":"NSW",
    "sg:tags":[
        "asbestos",
        "treatment",
        "removal"
    ],
    "wof:name":"Allstate Asbestos & Demolition Pty Ltd",
    "wof:placetype":"venue"
},
  "geometry": {"coordinates":[151.03239400000001,-33.952171],"type":"Point"}
}