{
  "type": "Feature",
  "properties": {
    "addr:full":"4 Beenak Rd Wandin North VIC 3139",
    "addr:housenumber":"4",
    "addr:postcode":"3139",
    "addr:street":"Beenak Rd",
    "iso:country":"AU",
    "sg:address":"4 Beenak Rd",
    "sg:city":"Wandin North",
    "sg:classifiers":[
        {
            "category":"Organizations",
            "subcategory":"Professional Association",
            "type":"Services"
        }
    ],
    "sg:phone":"+61 3 5964 3344",
    "sg:postcode":"3139",
    "sg:province":"VIC",
    "sg:tags":[
        "web",
        "internet"
    ],
    "wof:name":"Internet Xtreme",
    "wof:placetype":"venue"
},
  "geometry": {"coordinates":[145.43234252900001,-37.7819137573],"type":"Point"}
}