{
  "type": "Feature",
  "properties": {
    "iso:country":"AU",
    "sg:address":"260 Princes Hwy",
    "sg:city":"Bulli",
    "sg:classifiers":[
        {
            "category":"Professional",
            "subcategory":"Art Services",
            "type":"Services"
        }
    ],
    "sg:phone":"+61 2 4284 1363",
    "sg:postcode":"2516",
    "sg:province":"NSW",
    "sg:tags":[
        "picture",
        "frame",
        "framing"
    ],
    "wof:name":"Bulli Historical Art Gallery & Picture Framing",
    "wof:placetype":"venue"
},
  "geometry": {"coordinates":[150.912949,-34.335121],"type":"Point"}
}