{
  "type": "Feature",
  "properties": {
    "addr:full":"Shop 2 Niagara Park Shopping Centre Washington Ave Niagara Park NSW 2250",
    "addr:housenumber":"shop 2",
    "addr:postcode":"2250",
    "addr:street":"Niagara Park;Washington Ave Niagara Park",
    "iso:country":"AU",
    "sg:address":"Shop 2 Niagara Park Shopping Centre Washington Ave",
    "sg:city":"Niagara Park",
    "sg:classifiers":[
        {
            "category":"Education",
            "subcategory":"University",
            "type":"Public Place"
        }
    ],
    "sg:phone":"+61 2 4328 5960",
    "sg:postcode":"2250",
    "sg:province":"NSW",
    "sg:tags":[
        "educational",
        "organisation",
        "cultural"
    ],
    "wof:name":"Historical & Genealogical Society",
    "wof:placetype":"venue"
},
  "geometry": {"coordinates":[151.35308837900001,-33.3823204041],"type":"Point"}
}