{
  "type": "Feature",
  "properties": {
    "iso:country":"AU",
    "sg:address":"444 Burwood Rd",
    "sg:city":"Hawthorn",
    "sg:classifiers":[
        {
            "category":"Shopping",
            "subcategory":"Clothing, Apparel, & Fashions",
            "type":"Retail Goods"
        }
    ],
    "sg:phone":"+61 3 9819 9691",
    "sg:postcode":"3122",
    "sg:province":"VIC",
    "sg:tags":[
        "sportswear"
    ],
    "wof:name":"Diadora",
    "wof:placetype":"venue"
},
  "geometry": {"coordinates":[145.03924560600001,-37.8231887817],"type":"Point"}
}