{
  "type": "Feature",
  "properties": {
    "iso:country":"AU",
    "sg:address":"117b Sydney St",
    "sg:city":"Mackay",
    "sg:classifiers":[
        {
            "category":"Wholesale",
            "subcategory":"Machinery & Supplies",
            "type":"Manufacturing & Wholesale Goods"
        }
    ],
    "sg:phone":"+61 7 4951 0022",
    "sg:postcode":"4740",
    "sg:province":"QLD",
    "sg:tags":[
        "instrument"
    ],
    "wof:name":"Industrial Instrument Service",
    "wof:placetype":"venue"
},
  "geometry": {"coordinates":[149.18588299999999,-21.150663],"type":"Point"}
}