{
  "type": "Feature",
  "properties": {
    "addr:full":"Shop 23, Springvale Central Shopping Centre Springvale VIC 3171",
    "addr:housenumber":"shop 23",
    "addr:postcode":"3171",
    "addr:street":"Springvale Central",
    "iso:country":"AU",
    "sg:address":"Shop 23, Springvale Central Shopping Centre",
    "sg:city":"Springvale",
    "sg:classifiers":[
        {
            "category":"Health Services",
            "subcategory":"Optometrist",
            "type":"Services"
        }
    ],
    "sg:phone":"+61 3 9547 0688",
    "sg:postcode":"3171",
    "sg:province":"VIC",
    "wof:name":"Icontact Optometrist Pty Ltd",
    "wof:placetype":"venue"
},
  "geometry": {"coordinates":[145.15573120100001,-37.9346847534],"type":"Point"}
}