{
  "type": "Feature",
  "properties": {
    "addr:full":"Mercer St Geelong VIC 3220",
    "addr:postcode":"3220",
    "addr:street":"Mercer St",
    "iso:country":"AU",
    "sg:address":"Mercer St",
    "sg:city":"Geelong",
    "sg:classifiers":[
        {
            "category":"Shopping",
            "subcategory":"Mobile Phones",
            "type":"Retail Goods"
        }
    ],
    "sg:phone":"+61 3 5221 1600",
    "sg:postcode":"3220",
    "sg:province":"VIC",
    "sg:tags":[
        "telephone",
        "accessory"
    ],
    "wof:name":"Optus World",
    "wof:placetype":"venue"
},
  "geometry": {"coordinates":[144.35787999999999,-38.146015],"type":"Point"}
}