{
  "type": "Feature",
  "properties": {
    "addr:full":"29 Brunswick Pde Ashfield NSW 2131",
    "addr:housenumber":"29",
    "addr:postcode":"2131",
    "addr:street":"Brunswick Pde",
    "iso:country":"AU",
    "sg:address":"29 Brunswick Pde",
    "sg:city":"Ashfield",
    "sg:classifiers":[
        {
            "category":"Professional",
            "subcategory":"Computer Services",
            "type":"Services"
        }
    ],
    "sg:phone":"+61 2 9798 2044",
    "sg:postcode":"2131",
    "sg:province":"NSW",
    "sg:tags":[
        "information"
    ],
    "wof:name":"445N Pty Ltd",
    "wof:placetype":"venue"
},
  "geometry": {"coordinates":[151.119262695,-33.8921852112],"type":"Point"}
}