{
  "type": "Feature",
  "properties": {
    "iso:country":"AU",
    "sg:address":"310/ 130 Cresswell Rd",
    "sg:city":"Dianella",
    "sg:classifiers":[
        {
            "category":"Education",
            "subcategory":"Music School",
            "type":"Public Place"
        }
    ],
    "sg:phone":"+61 8 9275 8063",
    "sg:postcode":"6059",
    "sg:province":"WA",
    "sg:tags":[
        "teacher"
    ],
    "wof:name":"Kooperman David",
    "wof:placetype":"venue"
},
  "geometry": {"coordinates":[115.865737915,-31.9017391205],"type":"Point"}
}