{
  "type": "Feature",
  "properties": {
    "iso:country":"AU",
    "sg:address":"4 Hood Crt",
    "sg:city":"Mermaid Waters",
    "sg:classifiers":[
        {
            "category":"Utilities",
            "subcategory":"Electric",
            "type":"Services"
        }
    ],
    "sg:phone":"+61 417 600 216",
    "sg:postcode":"4218",
    "sg:province":"QLD",
    "sg:tags":[
        "electrical",
        "contractor"
    ],
    "wof:name":"Mermaid Electrical Pty Ltd",
    "wof:placetype":"venue"
},
  "geometry": {"coordinates":[153.426971436,-28.0572052002],"type":"Point"}
}