{
  "type": "Feature",
  "properties": {
    "iso:country":"AU",
    "sg:address":"281 Jacobs Well Rd",
    "sg:city":"Alberton",
    "sg:classifiers":[
        {
            "category":"Home & Garden",
            "subcategory":"Garden Supply",
            "type":"Retail Goods"
        }
    ],
    "sg:phone":"+61 7 3807 0190",
    "sg:postcode":"4207",
    "sg:province":"QLD",
    "sg:tags":[
        "shed"
    ],
    "wof:name":"W.M.'s Garden Sheds",
    "wof:placetype":"venue"
},
  "geometry": {"coordinates":[153.258636475,-27.7074604034],"type":"Point"}
}