{
  "type": "Feature",
  "properties": {
    "addr:full":"33 Pier St Perth WA 6000",
    "addr:housenumber":"33",
    "addr:postcode":"6000",
    "addr:street":"Pier St",
    "iso:country":"AU",
    "sg:address":"33 Pier St",
    "sg:city":"Perth",
    "sg:classifiers":[
        {
            "category":"Cafe",
            "type":"Food & Drink"
        }
    ],
    "sg:phone":"+61 8 9225 4342",
    "sg:postcode":"6000",
    "sg:province":"WA",
    "wof:name":"Chef Hans Cafe",
    "wof:placetype":"venue"
},
  "geometry": {"coordinates":[115.86312866199999,-31.9538497925],"type":"Point"}
}