{
  "type": "Feature",
  "properties": {
    "addr:full":"10 Stone St Bunbury WA 6230",
    "addr:housenumber":"10",
    "addr:postcode":"6230",
    "addr:street":"Stone St",
    "iso:country":"AU",
    "sg:address":"10 Stone St",
    "sg:city":"Bunbury",
    "sg:classifiers":[
        {
            "category":"Communications",
            "type":"Services"
        }
    ],
    "sg:phone":"+61 8 9721 7579",
    "sg:postcode":"6230",
    "sg:province":"WA",
    "sg:tags":[
        "equipment",
        "radio"
    ],
    "wof:name":"Bunbury Communications",
    "wof:placetype":"venue"
},
  "geometry": {"coordinates":[115.64173099999999,-33.332386],"type":"Point"}
}