{
  "type": "Feature",
  "properties": {
    "iso:country":"AU",
    "sg:address":"412 The Entrance Rd",
    "sg:city":"Long Jetty",
    "sg:classifiers":[
        {
            "category":"Health Services",
            "subcategory":"Doctor",
            "type":"Services"
        }
    ],
    "sg:phone":"+61 2 4334 6022",
    "sg:postcode":"2261",
    "sg:province":"NSW",
    "sg:tags":[
        "medical",
        "practitioner"
    ],
    "wof:name":"Jagavkar Shantaram Dr",
    "wof:placetype":"venue"
},
  "geometry": {"coordinates":[151.480484,-33.362354],"type":"Point"}
}