{
  "type": "Feature",
  "properties": {
    "addr:full":"3/ 6 Lansell Crt Toorak VIC 3142",
    "addr:housenumber":"/ 6",
    "addr:postcode":"3142",
    "addr:street":"Lansell Crt",
    "iso:country":"AU",
    "sg:address":"3/ 6 Lansell Crt",
    "sg:city":"Toorak",
    "sg:classifiers":[
        {
            "category":"Shopping",
            "subcategory":"Clothing, Apparel, & Fashions",
            "type":"Retail Goods"
        }
    ],
    "sg:phone":"+61 3 9827 0277",
    "sg:postcode":"3142",
    "sg:province":"VIC",
    "sg:tags":[
        "textile",
        "designer"
    ],
    "wof:name":"Roger Grinstead Design",
    "wof:placetype":"venue"
},
  "geometry": {"coordinates":[145.01539611800001,-37.8398132324],"type":"Point"}
}