{
  "type": "Feature",
  "properties": {
    "addr:full":"12 Normanby St Robina QLD 4226",
    "addr:housenumber":"12",
    "addr:postcode":"4226",
    "addr:street":"Normanby St",
    "iso:country":"AU",
    "sg:address":"12 Normanby St",
    "sg:city":"Robina",
    "sg:classifiers":[
        {
            "category":"Professional",
            "subcategory":"Engineering",
            "type":"Services"
        }
    ],
    "sg:phone":"+61 7 5572 3320",
    "sg:postcode":"4226",
    "sg:province":"QLD",
    "sg:tags":[
        "consulting",
        "engineer"
    ],
    "wof:name":"Robina CAD",
    "wof:placetype":"venue"
},
  "geometry": {"coordinates":[153.410980225,-28.0489616394],"type":"Point"}
}