{
  "type": "Feature",
  "properties": {
    "iso:country":"AU",
    "sg:address":"Shop2, 2 Macquarie St",
    "sg:city":"Newstead",
    "sg:classifiers":[
        {
            "category":"Personal",
            "subcategory":"Beauty Salon",
            "type":"Services"
        }
    ],
    "sg:phone":"+61 7 3254 4800",
    "sg:postcode":"4006",
    "sg:province":"QLD",
    "sg:tags":[
        "hairdresser"
    ],
    "wof:name":"Lucca Hair Design",
    "wof:placetype":"venue"
},
  "geometry": {"coordinates":[153.05007934599999,-27.4621925354],"type":"Point"}
}