{
  "type": "Feature",
  "properties": {
    "iso:country":"AU",
    "sg:address":"57B Best St",
    "sg:city":"Devonport",
    "sg:classifiers":[
        {
            "category":"Personal",
            "subcategory":"Beauty Salon",
            "type":"Services"
        }
    ],
    "sg:phone":"+61 3 6424 5003",
    "sg:postcode":"7310",
    "sg:province":"TAS",
    "wof:name":"Tasmanian Skin And Body Centre",
    "wof:placetype":"venue"
},
  "geometry": {"coordinates":[146.35548400900001,-41.1777229309],"type":"Point"}
}