{
  "type": "Feature",
  "properties": {
    "addr:full":"40 Seventh Street East, Mildura, Victoria 3502 Mildura VIC 3502",
    "addr:housenumber":"40",
    "addr:postcode":"3502;3502",
    "addr:street":"Seventh Street East",
    "iso:country":"AU",
    "sg:address":"40 Seventh Street East, Mildura, Victoria 3502",
    "sg:city":"Mildura",
    "sg:classifiers":[
        {
            "category":"Retail",
            "subcategory":"Storage",
            "type":"Services"
        }
    ],
    "sg:phone":"+61 3 5022 7799",
    "sg:postcode":"3502",
    "sg:province":"VIC",
    "wof:name":"A J Self Storage",
    "wof:placetype":"venue"
},
  "geometry": {"coordinates":[142.16343689000001,-34.1990318298],"type":"Point"}
}