{
  "type": "Feature",
  "properties": {
    "addr:full":"Broadwater Medical Centre Bussell Hwy Busselton WA 6280",
    "addr:postcode":"6280",
    "addr:street":"Bussell Hwy",
    "iso:country":"AU",
    "sg:address":"Broadwater Medical Centre Bussell Hwy",
    "sg:city":"Busselton",
    "sg:classifiers":[
        {
            "category":"Health Services",
            "subcategory":"Health Practitioner",
            "type":"Services"
        }
    ],
    "sg:phone":"+61 8 9754 6244",
    "sg:postcode":"6280",
    "sg:province":"WA",
    "sg:tags":[
        "physiotherapist"
    ],
    "wof:name":"Vasse Physiotherapy",
    "wof:placetype":"venue"
},
  "geometry": {"coordinates":[115.340232849,-33.6530761719],"type":"Point"}
}