{
  "type": "Feature",
  "properties": {
    "addr:full":"299 Morayfield Rd Morayfield QLD 4506",
    "addr:housenumber":"299",
    "addr:postcode":"4506",
    "addr:street":"Morayfield Rd",
    "iso:country":"AU",
    "sg:address":"299 Morayfield Rd",
    "sg:city":"Morayfield",
    "sg:classifiers":[
        {
            "category":"Manufacturing",
            "subcategory":"Chemicals & Compounds",
            "type":"Manufacturing & Wholesale Goods"
        }
    ],
    "sg:phone":"+61 7 5498 5911",
    "sg:postcode":"4506",
    "sg:province":"QLD",
    "sg:tags":[
        "electroplating"
    ],
    "wof:name":"Argo Plating",
    "wof:placetype":"venue"
},
  "geometry": {"coordinates":[152.95242309599999,-27.11460495],"type":"Point"}
}