{
  "type": "Feature",
  "properties": {
    "addr:full":"140 Peel St Kew VIC 3101",
    "addr:housenumber":"140",
    "addr:postcode":"3101",
    "addr:street":"Peel St",
    "iso:country":"AU",
    "sg:address":"140 Peel St",
    "sg:city":"Kew",
    "sg:classifiers":[
        {
            "category":"Building & Trades",
            "subcategory":"Plumbing",
            "type":"Services"
        }
    ],
    "sg:phone":"+61 418 391 700",
    "sg:postcode":"3101",
    "sg:province":"VIC",
    "sg:tags":[
        "plumber",
        "gasfitters"
    ],
    "wof:name":"C Makris Plumbing",
    "wof:placetype":"venue"
},
  "geometry": {"coordinates":[145.03465270999999,-37.7971496582],"type":"Point"}
}