{
  "type": "Feature",
  "properties": {
    "addr:full":"Johnpaul Drv Daisy Hill QLD 4127",
    "addr:postcode":"4127",
    "addr:street":"Johnpaul Drv",
    "iso:country":"AU",
    "sg:address":"Johnpaul Drv",
    "sg:city":"Daisy Hill",
    "sg:classifiers":[
        {
            "category":"Shopping",
            "subcategory":"Computers & Home Electronics",
            "type":"Retail Goods"
        }
    ],
    "sg:phone":"+61 7 3826 3589",
    "sg:postcode":"4127",
    "sg:province":"QLD",
    "sg:tags":[
        "equipment",
        "multimedia"
    ],
    "wof:name":"Mediasphere",
    "wof:placetype":"venue"
},
  "geometry": {"coordinates":[153.14837646500001,-27.6339435577],"type":"Point"}
}