{
  "type": "Feature",
  "properties": {
    "addr:full":"56 Burnett St Hobart TAS 7000",
    "addr:housenumber":"56",
    "addr:postcode":"7000",
    "addr:street":"Burnett St",
    "iso:country":"AU",
    "sg:address":"56 Burnett St",
    "sg:city":"Hobart",
    "sg:classifiers":[
        {
            "category":"Professional",
            "subcategory":"Accounting & Tax Preparation",
            "type":"Services"
        }
    ],
    "sg:phone":"+61 1300 856 181",
    "sg:postcode":"7000",
    "sg:province":"TAS",
    "sg:tags":[
        "bookkeeping"
    ],
    "wof:name":"The Institute Of Certified Bookkeepers",
    "wof:placetype":"venue"
},
  "geometry": {"coordinates":[147.31809997600001,-42.8742141724],"type":"Point"}
}