{
  "type": "Feature",
  "properties": {
    "addr:full":"56 Curdie St Cobden VIC 3266",
    "addr:housenumber":"56",
    "addr:postcode":"3266",
    "addr:street":"Curdie St",
    "iso:country":"AU",
    "sg:address":"56 Curdie St",
    "sg:city":"Cobden",
    "sg:classifiers":[
        {
            "category":"Manufacturing",
            "subcategory":"Furniture",
            "type":"Manufacturing & Wholesale Goods"
        }
    ],
    "sg:phone":"+61 3 5595 1949",
    "sg:postcode":"3266",
    "sg:province":"VIC",
    "sg:tags":[
        "builder",
        "designer",
        "custom"
    ],
    "wof:name":"Cobden Kitchens and Joinery",
    "wof:placetype":"venue"
},
  "geometry": {"coordinates":[143.07496643100001,-38.3281173706],"type":"Point"}
}