{
  "type": "Feature",
  "properties": {
    "addr:full":"PO Box 27 Fulham Gardens SA 5024",
    "addr:postcode":"5024",
    "iso:country":"AU",
    "sg:address":"PO Box 27",
    "sg:city":"Fulham Gardens",
    "sg:classifiers":[
        {
            "category":"Arena",
            "subcategory":"Sports Club",
            "type":"Entertainment"
        }
    ],
    "sg:phone":"+61 8 8235 2625",
    "sg:postcode":"5024",
    "sg:province":"SA",
    "sg:tags":[
        "organisation",
        "sporting"
    ],
    "wof:name":"Roller Sports S.A. Inc.",
    "wof:placetype":"venue"
},
  "geometry": {"coordinates":[138.51495361299999,-34.9204788208],"type":"Point"}
}