{
  "type": "Feature",
  "properties": {
    "addr:full":"19 Kitchener St Toowoomba QLD 4350",
    "addr:housenumber":"19",
    "addr:postcode":"4350",
    "addr:street":"Kitchener St",
    "iso:country":"AU",
    "sg:address":"19 Kitchener St",
    "sg:city":"Toowoomba",
    "sg:classifiers":[
        {
            "category":"Health Services",
            "subcategory":"Dentist",
            "type":"Services"
        }
    ],
    "sg:phone":"+61 7 4638 5111",
    "sg:postcode":"4350",
    "sg:province":"QLD",
    "wof:name":"Sukhnundan Sudhesh",
    "wof:placetype":"venue"
},
  "geometry": {"coordinates":[151.96086099999999,-27.565346],"type":"Point"}
}