{
  "type": "Feature",
  "properties": {
    "addr:full":"3 Scott St Bridgetown WA 6255",
    "addr:housenumber":"3",
    "addr:postcode":"6255",
    "addr:street":"Scott St",
    "iso:country":"AU",
    "sg:address":"3 Scott St",
    "sg:city":"Bridgetown",
    "sg:classifiers":[
        {
            "category":"Travel",
            "subcategory":"Hostel",
            "type":"Entertainment"
        }
    ],
    "sg:phone":"+61 8 9761 1366",
    "sg:postcode":"6255",
    "sg:province":"WA",
    "sg:tags":[
        "home"
    ],
    "wof:name":"Geegeelup Village Hostel",
    "wof:placetype":"venue"
},
  "geometry": {"coordinates":[116.12882232699999,-33.9553337097],"type":"Point"}
}