{
  "type": "Feature",
  "properties": {
    "iso:country":"AU",
    "sg:address":"65 Rosella St",
    "sg:city":"Doncaster East",
    "sg:classifiers":[
        {
            "category":"Professional",
            "subcategory":"Computer Services",
            "type":"Services"
        }
    ],
    "sg:phone":"+61 3 9891 7216",
    "sg:postcode":"3109",
    "sg:province":"VIC",
    "sg:tags":[
        "consultant",
        "system"
    ],
    "wof:name":"P C Management Pty Ltd",
    "wof:placetype":"venue"
},
  "geometry": {"coordinates":[145.15377807600001,-37.7960586548],"type":"Point"}
}