{
  "type": "Feature",
  "properties": {
    "addr:full":"Level 7, 477 Collins St Melbourne VIC 3000",
    "addr:housenumber":"477",
    "addr:postcode":"3000",
    "addr:street":"Collins St",
    "iso:country":"AU",
    "sg:address":"Level 7, 477 Collins St",
    "sg:city":"Melbourne",
    "sg:classifiers":[
        {
            "category":"Banks & Credit Unions",
            "subcategory":"Investment Brokerage",
            "type":"Services"
        }
    ],
    "sg:phone":"+61 3 9610 4960",
    "sg:postcode":"3000",
    "sg:province":"VIC",
    "sg:tags":[
        "debt",
        "collection"
    ],
    "wof:name":"Collection House Limited",
    "wof:placetype":"venue"
},
  "geometry": {"coordinates":[144.95828247099999,-37.8180046082],"type":"Point"}
}