{
  "type": "Feature",
  "properties": {
    "addr:full":"104 Gaskill St Canowindra NSW 2804",
    "addr:housenumber":"104",
    "addr:postcode":"2804",
    "addr:street":"Gaskill St",
    "iso:country":"AU",
    "sg:address":"104 Gaskill St",
    "sg:city":"Canowindra",
    "sg:classifiers":[
        {
            "category":"Food & Beverages",
            "subcategory":"Bakery",
            "type":"Retail Goods"
        }
    ],
    "sg:phone":"+61 2 6344 2525",
    "sg:postcode":"2804",
    "sg:province":"NSW",
    "sg:tags":[
        "cake",
        "shop",
        "pastry"
    ],
    "wof:name":"Canowindra Country Bakehouse",
    "wof:placetype":"venue"
},
  "geometry": {"coordinates":[148.660324097,-33.5634803772],"type":"Point"}
}