{
  "type": "Feature",
  "properties": {
    "addr:full":"608 Glebe Rd Adamstown NSW 2289",
    "addr:housenumber":"608",
    "addr:postcode":"2289",
    "addr:street":"Glebe Rd",
    "iso:country":"AU",
    "sg:address":"608 Glebe Rd",
    "sg:city":"Adamstown",
    "sg:classifiers":[
        {
            "category":"Education",
            "subcategory":"Dance Studio",
            "type":"Public Place"
        }
    ],
    "sg:phone":"+61 2 4943 2985",
    "sg:postcode":"2289",
    "sg:province":"NSW",
    "sg:tags":[
        "venue",
        "tuition"
    ],
    "wof:name":"Northcott Dance",
    "wof:placetype":"venue"
},
  "geometry": {"coordinates":[151.72564697300001,-32.9340553284],"type":"Point"}
}