{
  "type": "Feature",
  "properties": {
    "addr:full":"14 Torneys Rd Beauty Point TAS 7270",
    "addr:housenumber":"14",
    "addr:postcode":"7270",
    "addr:street":"Torneys Rd",
    "iso:country":"AU",
    "sg:address":"14 Torneys Rd",
    "sg:city":"Beauty Point",
    "sg:classifiers":[
        {
            "category":"Professional",
            "subcategory":"Management & Consulting",
            "type":"Services"
        }
    ],
    "sg:phone":"+61 3 6383 4797",
    "sg:postcode":"7270",
    "sg:province":"TAS",
    "sg:tags":[
        "consultant",
        "business"
    ],
    "wof:name":"Gavan Murphy Associates Pty Ltd",
    "wof:placetype":"venue"
},
  "geometry": {"coordinates":[146.81666564899999,-41.1714172363],"type":"Point"}
}