{
  "type": "Feature",
  "properties": {
    "addr:full":"2 Piovesan Crt Kidman Park SA 5025",
    "addr:housenumber":"2",
    "addr:postcode":"5025",
    "addr:street":"Piovesan Crt",
    "iso:country":"AU",
    "sg:address":"2 Piovesan Crt",
    "sg:city":"Kidman Park",
    "sg:classifiers":[
        {
            "category":"Building & Trades",
            "subcategory":"Construction",
            "type":"Services"
        }
    ],
    "sg:phone":"+61 8 8235 0683",
    "sg:postcode":"5025",
    "sg:province":"SA",
    "sg:tags":[
        "contractor"
    ],
    "wof:name":"Kidman Contractors Pty Ltd",
    "wof:placetype":"venue"
},
  "geometry": {"coordinates":[138.52687072800001,-34.9083366394],"type":"Point"}
}