{
  "type": "Feature",
  "properties": {
    "addr:full":"72 Burringbar St Mullumbimby NSW 2482",
    "addr:housenumber":"72",
    "addr:postcode":"2482",
    "addr:street":"Burringbar St",
    "iso:country":"AU",
    "sg:address":"72 Burringbar St",
    "sg:city":"Mullumbimby",
    "sg:classifiers":[
        {
            "category":"Fast Food",
            "type":"Food & Drink"
        }
    ],
    "sg:phone":"+61 2 6684 2915",
    "sg:postcode":"2482",
    "sg:province":"NSW",
    "sg:tags":[
        "away",
        "take"
    ],
    "wof:name":"Mellos Gourmet Sandwich Bar",
    "wof:placetype":"venue"
},
  "geometry": {"coordinates":[153.501861572,-28.5533123016],"type":"Point"}
}