{
  "type": "Feature",
  "properties": {
    "addr:full":"Freezers Rd Port Lincoln SA 5606",
    "addr:postcode":"5606",
    "addr:street":"Freezers Rd",
    "iso:country":"AU",
    "sg:address":"Freezers Rd",
    "sg:city":"Port Lincoln",
    "sg:classifiers":[
        {
            "category":"Recreation",
            "subcategory":"Fishing",
            "type":"Entertainment"
        }
    ],
    "sg:phone":"+61 8 8682 6839",
    "sg:postcode":"5606",
    "sg:province":"SA",
    "sg:tags":[
        "bait"
    ],
    "wof:name":"Australian Southern Exporters Pty Ltd",
    "wof:placetype":"venue"
},
  "geometry": {"coordinates":[135.852036,-34.728481],"type":"Point"}
}