{
  "type": "Feature",
  "properties": {
    "iso:country":"AU",
    "sg:address":"Pitt St",
    "sg:city":"Georgetown",
    "sg:classifiers":[
        {
            "category":"Food & Beverages",
            "subcategory":"Groceries & Convenience Stores",
            "type":"Retail Goods"
        }
    ],
    "sg:phone":"+61 8 8662 4011",
    "sg:postcode":"5472",
    "sg:province":"SA",
    "wof:name":"Georgetown General Store",
    "wof:placetype":"venue"
},
  "geometry": {"coordinates":[138.39447,-33.359001],"type":"Point"}
}