{
  "type": "Feature",
  "properties": {
    "addr:full":"Suite 4,1st Floor 18- 22 Webb St Narre Warren VIC 3805",
    "addr:housenumber":"4,1;22",
    "addr:postcode":"3805",
    "addr:street":"St;Webb St",
    "iso:country":"AU",
    "sg:address":"Suite 4,1st Floor 18- 22 Webb St",
    "sg:city":"Narre Warren",
    "sg:classifiers":[
        {
            "category":"Building & Trades",
            "subcategory":"Landscaping Services",
            "type":"Services"
        }
    ],
    "sg:phone":"+61 3 9705 1728",
    "sg:postcode":"3805",
    "sg:province":"VIC",
    "sg:tags":[
        "consultant"
    ],
    "wof:name":"Graeme Buchan & Associates",
    "wof:placetype":"venue"
},
  "geometry": {"coordinates":[145.30436700000001,-38.026451],"type":"Point"}
}