{
  "type": "Feature",
  "properties": {
    "addr:full":"100 Miller St North Sydney NSW 1522",
    "addr:housenumber":"100",
    "addr:postcode":"1522",
    "addr:street":"Miller St",
    "iso:country":"AU",
    "sg:address":"100 Miller St",
    "sg:city":"North Sydney",
    "sg:classifiers":[
        {
            "category":"Shopping",
            "subcategory":"Music",
            "type":"Retail Goods"
        }
    ],
    "sg:phone":"+61 2 9954 3300",
    "sg:postcode":"1522",
    "sg:province":"NSW",
    "sg:tags":[
        "instrument",
        "musical"
    ],
    "wof:name":"Trumps Music",
    "wof:placetype":"venue"
},
  "geometry": {"coordinates":[151.206954956,-33.8375396729],"type":"Point"}
}