{
  "type": "Feature",
  "properties": {
    "addr:full":"36 Trade Pl Coburg VIC 3058",
    "addr:housenumber":"36",
    "addr:postcode":"3058",
    "addr:street":"Trade Pl",
    "iso:country":"AU",
    "sg:address":"36 Trade Pl",
    "sg:city":"Coburg",
    "sg:classifiers":[
        {
            "category":"Banks & Credit Unions",
            "subcategory":"Investment Brokerage",
            "type":"Services"
        }
    ],
    "sg:phone":"+61 413 777 273",
    "sg:postcode":"3058",
    "sg:province":"VIC",
    "sg:tags":[
        "baby",
        "wholesaler",
        "mfrs",
        "wear"
    ],
    "wof:name":"Freddy's Co Ltd",
    "wof:placetype":"venue"
},
  "geometry": {"coordinates":[144.97137451200001,-37.7241859436],"type":"Point"}
}