{
  "type": "Feature",
  "properties": {
    "addr:full":"11/ 21 Barry St Bayswater VIC 3153",
    "addr:housenumber":"11 / 21",
    "addr:postcode":"3153",
    "addr:street":"Barry St",
    "iso:country":"AU",
    "sg:address":"11/ 21 Barry St",
    "sg:city":"Bayswater",
    "sg:classifiers":[
        {
            "category":"Manufacturing",
            "subcategory":"Metals",
            "type":"Manufacturing & Wholesale Goods"
        }
    ],
    "sg:phone":"+61 3 9720 1234",
    "sg:postcode":"3153",
    "sg:province":"VIC",
    "sg:tags":[
        "steel",
        "fabricator",
        "mfrs"
    ],
    "sg:website":"http://www.conomatic.com.au",
    "wof:name":"Conomatic Pty Ltd",
    "wof:placetype":"venue"
},
  "geometry": {"coordinates":[145.27554321299999,-37.8469009399],"type":"Point"}
}