{
  "type": "Feature",
  "properties": {
    "iso:country":"AU",
    "sg:address":"3/ 9 Apprentice Drv",
    "sg:city":"Berkeley Vale",
    "sg:classifiers":[
        {
            "category":"Banks & Credit Unions",
            "subcategory":"Investment Brokerage",
            "type":"Services"
        }
    ],
    "sg:phone":"+61 2 4389 2307",
    "sg:postcode":"2261",
    "sg:province":"NSW",
    "sg:tags":[
        "shutter",
        "louvre"
    ],
    "wof:name":"Timberstyle",
    "wof:placetype":"venue"
},
  "geometry": {"coordinates":[151.422546,-33.328857],"type":"Point"}
}