{
  "type": "Feature",
  "properties": {
    "addr:full":"Shop 1 / 264 Rode Rd Wavell Heights QLD 4012",
    "addr:housenumber":"shop 1 / 264",
    "addr:postcode":"4012",
    "addr:street":"Rode Rd",
    "iso:country":"AU",
    "sg:address":"Shop 1 / 264 Rode Rd",
    "sg:city":"Wavell Heights",
    "sg:classifiers":[
        {
            "category":"Personal",
            "subcategory":"Beauty Salon",
            "type":"Services"
        }
    ],
    "sg:phone":"+61 7 3266 5988",
    "sg:postcode":"4012",
    "sg:province":"QLD",
    "sg:tags":[
        "hairdresser"
    ],
    "wof:name":"Cameo Rose Hair Boutique",
    "wof:placetype":"venue"
},
  "geometry": {"coordinates":[153.04168701200001,-27.3951015472],"type":"Point"}
}