{
  "type": "Feature",
  "properties": {
    "iso:country":"AU",
    "sg:address":"38 Meadowvale Drv",
    "sg:city":"Grovedale",
    "sg:classifiers":[
        {
            "category":"Shopping",
            "subcategory":"Crafts & Fabrics",
            "type":"Retail Goods"
        }
    ],
    "sg:phone":"+61 3 5241 1295",
    "sg:postcode":"3216",
    "sg:province":"VIC",
    "sg:tags":[
        "supply"
    ],
    "wof:name":"Lace Inspirations",
    "wof:placetype":"venue"
},
  "geometry": {"coordinates":[144.31924438499999,-38.202999115],"type":"Point"}
}