{
  "type": "Feature",
  "properties": {
    "iso:country":"AU",
    "sg:address":"Junction St",
    "sg:city":"Maitland",
    "sg:classifiers":[
        {
            "category":"Education",
            "subcategory":"Special Training",
            "type":"Public Place"
        }
    ],
    "sg:phone":"+61 2 4932 4184",
    "sg:postcode":"2320",
    "sg:province":"NSW",
    "sg:tags":[
        "development"
    ],
    "wof:name":"Hunter-V-Tec",
    "wof:placetype":"venue"
},
  "geometry": {"coordinates":[151.539337158,-32.7346038818],"type":"Point"}
}