{
  "type": "Feature",
  "properties": {
    "addr:full":"95 Auburn Rd Hawthorn East VIC 3123",
    "addr:housenumber":"95",
    "addr:postcode":"3123",
    "addr:street":"Auburn Rd",
    "iso:country":"AU",
    "sg:address":"95 Auburn Rd",
    "sg:city":"Hawthorn East",
    "sg:classifiers":[
        {
            "category":"Wholesale",
            "subcategory":"Metals & Minerals",
            "type":"Manufacturing & Wholesale Goods"
        }
    ],
    "sg:phone":"+61 3 9882 0665",
    "sg:postcode":"3123",
    "sg:province":"VIC",
    "sg:tags":[
        "steel",
        "stainless",
        "product",
        "equipment"
    ],
    "wof:name":"Auburn Sheet Metal Pty Ltd",
    "wof:placetype":"venue"
},
  "geometry": {"coordinates":[145.04525756800001,-37.8221626282],"type":"Point"}
}