{
  "type": "Feature",
  "properties": {
    "addr:full":"1233 Victoria Rd West Ryde NSW 2114",
    "addr:housenumber":"1233",
    "addr:postcode":"2114",
    "addr:street":"Victoria Rd",
    "iso:country":"AU",
    "sg:address":"1233 Victoria Rd",
    "sg:city":"West Ryde",
    "sg:classifiers":[
        {
            "category":"Autos & Motor Vehicles",
            "subcategory":"Fuel & Gas Station",
            "type":"Retail Goods"
        }
    ],
    "sg:phone":"+61 2 9804 6504",
    "sg:postcode":"2114",
    "sg:province":"NSW",
    "wof:name":"BP Australia Pty Ltd",
    "wof:placetype":"venue"
},
  "geometry": {"coordinates":[151.071075439,-33.8067932129],"type":"Point"}
}