{
  "type": "Feature",
  "properties": {
    "addr:full":"84 Sydney St St Marys NSW 2760",
    "addr:housenumber":"84",
    "addr:postcode":"2760",
    "addr:street":"Sydney St",
    "iso:country":"AU",
    "sg:address":"84 Sydney St St",
    "sg:city":"Marys",
    "sg:classifiers":[
        {
            "category":"Personal",
            "subcategory":"Beauty Salon",
            "type":"Services"
        }
    ],
    "sg:phone":"+61 2 9833 9447",
    "sg:postcode":"2760",
    "sg:province":"NSW",
    "sg:tags":[
        "hairdresser"
    ],
    "wof:name":"Melinas Creative Image",
    "wof:placetype":"venue"
},
  "geometry": {"coordinates":[150.78753662099999,-33.7710876465],"type":"Point"}
}