{
  "type": "Feature",
  "properties": {
    "addr:full":"PO Box 14 Airlie Beach QLD 4802",
    "addr:postcode":"4802",
    "iso:country":"AU",
    "sg:address":"PO Box 14",
    "sg:city":"Airlie Beach",
    "sg:classifiers":[
        {
            "category":"Wholesale",
            "subcategory":"Apparel",
            "type":"Manufacturing & Wholesale Goods"
        }
    ],
    "sg:phone":"+61 7 4946 6154",
    "sg:postcode":"4802",
    "sg:province":"QLD",
    "sg:tags":[
        "wholesaler",
        "mfrs",
        "uniform"
    ],
    "wof:name":"Airlie Design Studios",
    "wof:placetype":"venue"
},
  "geometry": {"coordinates":[148.71969604500001,-20.2692394257],"type":"Point"}
}