{
  "type": "Feature",
  "properties": {
    "iso:country":"AU",
    "sg:address":"Lot 348/ Roger Moore Crs",
    "sg:city":"Warialda",
    "sg:classifiers":[
        {
            "category":"Building & Trades",
            "subcategory":"Construction",
            "type":"Services"
        }
    ],
    "sg:phone":"+61 2 6729 1332",
    "sg:postcode":"2402",
    "sg:province":"NSW",
    "sg:tags":[
        "welding"
    ],
    "wof:name":"Bill Coote",
    "wof:placetype":"venue"
},
  "geometry": {"coordinates":[150.57289123499999,-29.5426692963],"type":"Point"}
}