{
  "type": "Feature",
  "properties": {
    "iso:country":"AU",
    "sg:address":"Unit 2/ 707 Mt Alexander Rd",
    "sg:city":"Moonee Ponds",
    "sg:classifiers":[
        {
            "category":"Government",
            "subcategory":"Customs House",
            "type":"Public Place"
        }
    ],
    "sg:phone":"+61 3 9372 7768",
    "sg:postcode":"3039",
    "sg:province":"VIC",
    "sg:tags":[
        "title",
        "management",
        "stratum"
    ],
    "wof:name":"Melbourne Body Corporate Management - Essendon",
    "wof:placetype":"venue"
},
  "geometry": {"coordinates":[144.922729,-37.763996],"type":"Point"}
}