{
  "type": "Feature",
  "properties": {
    "addr:full":"PO Box 378 Mont Albert VIC 3127",
    "addr:postcode":"3127",
    "iso:country":"AU",
    "sg:address":"PO Box 378",
    "sg:city":"Mont Albert",
    "sg:classifiers":[
        {
            "category":"Professional",
            "subcategory":"Employment Agencies",
            "type":"Services"
        }
    ],
    "sg:phone":"+61 3 9890 9646",
    "sg:postcode":"3127",
    "sg:province":"VIC",
    "wof:name":"Priorities Flexible Employment",
    "wof:placetype":"venue"
},
  "geometry": {"coordinates":[145.109207153,-37.8161888123],"type":"Point"}
}