{
  "type": "Feature",
  "properties": {
    "iso:country":"AU",
    "sg:address":"3 Neils Rd",
    "sg:city":"Belgrave South",
    "sg:classifiers":[
        {
            "category":"Building & Trades",
            "subcategory":"Equipment Rental",
            "type":"Services"
        }
    ],
    "sg:phone":"+61 3 9551 9550",
    "sg:postcode":"3160",
    "sg:province":"VIC",
    "sg:tags":[
        "demolition",
        "contractor"
    ],
    "wof:name":"AAA PNS Demolition",
    "wof:placetype":"venue"
},
  "geometry": {"coordinates":[145.35317993199999,-37.931968689],"type":"Point"}
}