{
  "type": "Feature",
  "properties": {
    "iso:country":"AU",
    "sg:address":"58 Bass Hwy",
    "sg:city":"Hagley",
    "sg:classifiers":[
        {
            "category":"Professional",
            "subcategory":"Business Services",
            "type":"Services"
        }
    ],
    "sg:phone":"+61 3 6393 6777",
    "sg:postcode":"7292",
    "sg:province":"TAS",
    "sg:tags":[
        "livestock",
        "transport"
    ],
    "wof:name":"Page Transport Pty Ltd",
    "wof:placetype":"venue"
},
  "geometry": {"coordinates":[146.897338867,-41.5339241028],"type":"Point"}
}