{
  "type": "Feature",
  "properties": {
    "addr:full":"Suite 3 &4 Sydney Chambers, Elizabeth Shopping Centre SA 5112",
    "addr:housenumber":"& 4",
    "addr:postcode":"5112",
    "iso:country":"AU",
    "sg:address":"Suite 3",
    "sg:city":"&4 Sydney Chambers, Elizabeth Shopping Centre",
    "sg:classifiers":[
        {
            "category":"Health Services",
            "subcategory":"Health Practitioner",
            "type":"Services"
        }
    ],
    "sg:phone":"+61 8 8255 6100",
    "sg:postcode":"5112",
    "sg:province":"SA",
    "sg:tags":[
        "physiotherapist"
    ],
    "wof:name":"Physio 4 Life",
    "wof:placetype":"venue"
},
  "geometry": {"coordinates":[138.68284606899999,-34.7567710876],"type":"Point"}
}