{
  "type": "Feature",
  "properties": {
    "iso:country":"AU",
    "sg:address":"Unit 1, 734 Marshall Rd",
    "sg:city":"Malaga",
    "sg:classifiers":[
        {
            "category":"Retail",
            "subcategory":"Auto Repair",
            "type":"Services"
        }
    ],
    "sg:phone":"+61 8 9209 2098",
    "sg:postcode":"6090",
    "sg:province":"WA",
    "sg:tags":[
        "electrical"
    ],
    "wof:name":"T.A Auto Electrical & Air Conditioning",
    "wof:placetype":"venue"
},
  "geometry": {"coordinates":[115.902618408,-31.8568267822],"type":"Point"}
}