{
  "type": "Feature",
  "properties": {
    "iso:country":"AU",
    "sg:address":"Bookmark Ave",
    "sg:city":"Renmark West",
    "sg:classifiers":[
        {
            "category":"Farming",
            "subcategory":"Nursery",
            "type":"Manufacturing & Wholesale Goods"
        }
    ],
    "sg:phone":"+61 8 8595 1399",
    "sg:postcode":"5341",
    "sg:province":"SA",
    "wof:name":"K.J. Nurseries",
    "wof:placetype":"venue"
},
  "geometry": {"coordinates":[140.72726440400001,-34.1730613708],"type":"Point"}
}