{
  "type": "Feature",
  "properties": {
    "iso:country":"AU",
    "sg:address":"3 Sherwood Crt",
    "sg:city":"Lindisfarne",
    "sg:classifiers":[
        {
            "category":"Building & Trades",
            "subcategory":"Construction",
            "type":"Services"
        }
    ],
    "sg:phone":"+61 3 6243 6824",
    "sg:postcode":"7015",
    "sg:province":"TAS",
    "sg:tags":[
        "plasterboard",
        "plasterer",
        "fixer"
    ],
    "wof:name":"Cowley John S",
    "wof:placetype":"venue"
},
  "geometry": {"coordinates":[147.368774414,-42.8454742432],"type":"Point"}
}