{
  "type": "Feature",
  "properties": {
    "addr:full":"4 Station St Seaford VIC 3198",
    "addr:housenumber":"4",
    "addr:postcode":"3198",
    "addr:street":"Station St",
    "iso:country":"AU",
    "sg:address":"4 Station St",
    "sg:city":"Seaford",
    "sg:classifiers":[
        {
            "category":"Communications",
            "subcategory":"Film & Video Production",
            "type":"Services"
        }
    ],
    "sg:phone":"+61 3 9786 1666",
    "sg:postcode":"3198",
    "sg:province":"VIC",
    "sg:tags":[
        "dvd",
        "library"
    ],
    "wof:name":"Family Videoland Seaford",
    "wof:placetype":"venue"
},
  "geometry": {"coordinates":[145.14170837399999,-38.1113357544],"type":"Point"}
}