{
  "type": "Feature",
  "properties": {
    "addr:full":"Graeme Heggie St Outer Harbour QLD 4740",
    "addr:postcode":"4740",
    "addr:street":"St;Harbour",
    "iso:country":"AU",
    "sg:address":"Graeme Heggie St",
    "sg:city":"Outer Harbour",
    "sg:classifiers":[
        {
            "category":"Wholesale",
            "subcategory":"Farm Supplies",
            "type":"Manufacturing & Wholesale Goods"
        }
    ],
    "sg:phone":"+61 7 4955 1000",
    "sg:postcode":"4740",
    "sg:province":"QLD",
    "sg:tags":[
        "equipment"
    ],
    "wof:name":"Batrosa Concrete Products",
    "wof:placetype":"venue"
},
  "geometry": {"coordinates":[149.21824599999999,-21.113539],"type":"Point"}
}