{
  "type": "Feature",
  "properties": {
    "iso:country":"AU",
    "sg:address":"99 Wallarah Rd",
    "sg:city":"Gorokan",
    "sg:classifiers":[
        {
            "category":"Health Services",
            "subcategory":"Dentist",
            "type":"Services"
        }
    ],
    "sg:phone":"+61 2 4392 3999",
    "sg:postcode":"2263",
    "sg:province":"NSW",
    "wof:name":"Collins A",
    "wof:placetype":"venue"
},
  "geometry": {"coordinates":[151.505157,-33.255215],"type":"Point"}
}