{
  "type": "Feature",
  "properties": {
    "addr:full":"cnr McCotton & School Rd Capalaba QLD 4157",
    "addr:postcode":"4157",
    "addr:street":"Cnr Mccotton;Rd",
    "iso:country":"AU",
    "sg:address":"cnr McCotton & School Rd",
    "sg:city":"Capalaba",
    "sg:classifiers":[
        {
            "category":"Education",
            "subcategory":"School",
            "type":"Public Place"
        }
    ],
    "sg:phone":"+61 7 3823 9333",
    "sg:postcode":"4157",
    "sg:province":"QLD",
    "sg:tags":[
        "state",
        "except",
        "nsw"
    ],
    "wof:name":"Capalaba Preschool",
    "wof:placetype":"venue"
},
  "geometry": {"coordinates":[153.19999694800001,-27.5358467102],"type":"Point"}
}