{
  "type": "Feature",
  "properties": {
    "iso:country":"AU",
    "sg:address":"Level 3/Wharf 7 Pirrama Rd",
    "sg:city":"Pyrmont",
    "sg:classifiers":[
        {
            "category":"Organizations",
            "subcategory":"Professional Association",
            "type":"Services"
        }
    ],
    "sg:phone":"+61 2 8596 4444",
    "sg:postcode":"2009",
    "sg:province":"NSW",
    "sg:tags":[
        "web",
        "internet"
    ],
    "wof:name":"Fairfax Digital",
    "wof:placetype":"venue"
},
  "geometry": {"coordinates":[151.19515991200001,-33.8666915894],"type":"Point"}
}