{
  "type": "Feature",
  "properties": {
    "addr:full":"56A Thomas Drv Chevron Island QLD 4217",
    "addr:housenumber":"56a",
    "addr:postcode":"4217",
    "addr:street":"Thomas Drv Chevron",
    "iso:country":"AU",
    "sg:address":"56A Thomas Drv",
    "sg:city":"Chevron Island",
    "sg:classifiers":[
        {
            "category":"Shopping",
            "subcategory":"Clothing, Apparel, & Fashions",
            "type":"Retail Goods"
        }
    ],
    "sg:phone":"+61 7 5531 7688",
    "sg:postcode":"4217",
    "sg:province":"QLD",
    "sg:tags":[
        "lady",
        "wear"
    ],
    "wof:name":"etre#",
    "wof:placetype":"venue"
},
  "geometry": {"coordinates":[153.41908264200001,-27.9981021881],"type":"Point"}
}