{
  "type": "Feature",
  "properties": {
    "iso:country":"AU",
    "sg:address":"PO Box 302",
    "sg:city":"Deepdene",
    "sg:classifiers":[
        {
            "category":"Government",
            "subcategory":"Court House",
            "type":"Public Place"
        }
    ],
    "sg:phone":"+61 3 9830 7377",
    "sg:postcode":"3103",
    "sg:province":"VIC",
    "sg:tags":[
        "personal",
        "marriage",
        "family",
        "counselling"
    ],
    "wof:name":"Counselling For Healthy Living",
    "wof:placetype":"venue"
},
  "geometry": {"coordinates":[145.083694458,-37.8129920959],"type":"Point"}
}