{
  "type": "Feature",
  "properties": {
    "addr:full":"Unit 15a/ 566 High St Penrith NSW 2750",
    "addr:housenumber":"unit 15a / 566",
    "addr:postcode":"2750",
    "addr:street":"High St",
    "iso:country":"AU",
    "sg:address":"Unit 15a/ 566 High St",
    "sg:city":"Penrith",
    "sg:classifiers":[
        {
            "category":"Shopping",
            "subcategory":"Music",
            "type":"Retail Goods"
        }
    ],
    "sg:phone":"+61 2 4732 6070",
    "sg:postcode":"2750",
    "sg:province":"NSW",
    "sg:tags":[
        "store"
    ],
    "wof:name":"Ideal Records",
    "wof:placetype":"venue"
},
  "geometry": {"coordinates":[150.91554260300001,-33.8950843811],"type":"Point"}
}