{
  "type": "Feature",
  "properties": {
    "iso:country":"AU",
    "sg:address":"80 Lutwyche Rd",
    "sg:city":"Windsor",
    "sg:classifiers":[
        {
            "category":"Banks & Credit Unions",
            "subcategory":"Financial Services",
            "type":"Services"
        }
    ],
    "sg:phone":"+61 7 3357 3487",
    "sg:postcode":"4030",
    "sg:province":"QLD",
    "sg:tags":[
        "finance",
        "motor",
        "vehicle"
    ],
    "wof:name":"My Style Cars",
    "wof:placetype":"venue"
},
  "geometry": {"coordinates":[153.029984,-27.44318],"type":"Point"}
}