{
  "type": "Feature",
  "properties": {
    "iso:country":"AU",
    "sg:address":"68 Doncaster Rd",
    "sg:city":"Balwyn North",
    "sg:classifiers":[
        {
            "category":"Shopping",
            "subcategory":"Clothing, Apparel, & Fashions",
            "type":"Retail Goods"
        }
    ],
    "sg:phone":"+61 3 9859 6885",
    "sg:postcode":"3104",
    "sg:province":"VIC",
    "sg:tags":[
        "menswear"
    ],
    "wof:name":"Martin Moloney",
    "wof:placetype":"venue"
},
  "geometry": {"coordinates":[145.071212769,-37.7928314209],"type":"Point"}
}