{
  "type": "Feature",
  "properties": {
    "iso:country":"AU",
    "sg:address":"Rear 21 Lisburn St",
    "sg:city":"Shepparton",
    "sg:classifiers":[
        {
            "category":"Retail",
            "subcategory":"Auto Repair",
            "type":"Services"
        }
    ],
    "sg:phone":"+61 3 5821 5518",
    "sg:postcode":"3630",
    "sg:province":"VIC",
    "sg:tags":[
        "electrical"
    ],
    "wof:name":"Shepparton Auto Electrical Service",
    "wof:placetype":"venue"
},
  "geometry": {"coordinates":[145.41513061500001,-36.3816146851],"type":"Point"}
}