{
  "type": "Feature",
  "properties": {
    "addr:full":"Suite 2a, The Chancellory, 155 Missenden Rd Newtown NSW 2042",
    "addr:housenumber":"155",
    "addr:postcode":"2042",
    "addr:street":"Missenden Rd",
    "iso:country":"AU",
    "sg:address":"Suite 2a, The Chancellory, 155 Missenden Rd",
    "sg:city":"Newtown",
    "sg:classifiers":[
        {
            "category":"Wholesale",
            "subcategory":"Medical Equipment & Supplies",
            "type":"Manufacturing & Wholesale Goods"
        }
    ],
    "sg:phone":"+61 2 9565 2521",
    "sg:postcode":"2042",
    "sg:province":"NSW",
    "sg:tags":[
        "aids",
        "hearing"
    ],
    "wof:name":"milliAmp Hearing",
    "wof:placetype":"venue"
},
  "geometry": {"coordinates":[151.18283099999999,-33.892147],"type":"Point"}
}