{
  "type": "Feature",
  "properties": {
    "iso:country":"AU",
    "sg:address":"30- 40 Alfred Rd",
    "sg:city":"Chipping Norton",
    "sg:classifiers":[
        {
            "category":"Freight",
            "type":"Transportation"
        }
    ],
    "sg:phone":"+61 2 9724 2215",
    "sg:postcode":"2170",
    "sg:province":"NSW",
    "sg:tags":[
        "transport",
        "refrigerated"
    ],
    "wof:name":"Robinvale Transport Group (S.A.) Pty Ltd",
    "wof:placetype":"venue"
},
  "geometry": {"coordinates":[150.96348571799999,-33.9232635498],"type":"Point"}
}