{
  "type": "Feature",
  "properties": {
    "addr:full":"Shop 3004, Westfield Shopping Town Parramatta NSW 2150",
    "addr:housenumber":"3004",
    "addr:postcode":"2150",
    "addr:street":"Westfield",
    "iso:country":"AU",
    "sg:address":"Shop 3004, Westfield Shopping Town",
    "sg:city":"Parramatta",
    "sg:classifiers":[
        {
            "category":"Banks & Credit Unions",
            "subcategory":"Financial Services",
            "type":"Services"
        }
    ],
    "sg:phone":"+61 2 9633 1333",
    "sg:postcode":"2150",
    "sg:province":"NSW",
    "sg:tags":[
        "coin"
    ],
    "wof:name":"Sydney Coins & Jewellery",
    "wof:placetype":"venue"
},
  "geometry": {"coordinates":[151.00668335,-33.81483078],"type":"Point"}
}