{
  "type": "Feature",
  "properties": {
    "addr:full":"27 Dunfield Drv Tullamarine VIC 3043",
    "addr:housenumber":"27",
    "addr:postcode":"3043",
    "addr:street":"Dunfield Drv",
    "iso:country":"AU",
    "sg:address":"27 Dunfield Drv",
    "sg:city":"Tullamarine",
    "sg:classifiers":[
        {
            "category":"Building & Trades",
            "subcategory":"Cleaning & Sanitation",
            "type":"Services"
        }
    ],
    "sg:phone":"+61 3 9338 5481",
    "sg:postcode":"3043",
    "sg:province":"VIC",
    "sg:tags":[
        "cleaner",
        "repairer",
        "roof"
    ],
    "wof:name":"A & J Roofing",
    "wof:placetype":"venue"
},
  "geometry": {"coordinates":[144.89532470699999,-37.6861114502],"type":"Point"}
}