{
  "type": "Feature",
  "properties": {
    "addr:full":"178 Macquarie St Hobart TAS 7000",
    "addr:housenumber":"178",
    "addr:postcode":"7000",
    "addr:street":"Macquarie St",
    "iso:country":"AU",
    "sg:address":"178 Macquarie St",
    "sg:city":"Hobart",
    "sg:classifiers":[
        {
            "category":"Education",
            "subcategory":"Special Training",
            "type":"Public Place"
        }
    ],
    "sg:phone":"+61 3 6223 6522",
    "sg:postcode":"7000",
    "sg:province":"TAS",
    "sg:tags":[
        "development"
    ],
    "wof:name":"Training Consultancy Network",
    "wof:placetype":"venue"
},
  "geometry": {"coordinates":[147.32569885300001,-42.8864135742],"type":"Point"}
}