{
  "type": "Feature",
  "properties": {
    "addr:full":"1 Robin Crt Singleton WA 6175",
    "addr:housenumber":"1",
    "addr:postcode":"6175",
    "addr:street":"Robin Crt",
    "iso:country":"AU",
    "sg:address":"1 Robin Crt",
    "sg:city":"Singleton",
    "sg:classifiers":[
        {
            "category":"Manufacturing",
            "subcategory":"Glass & Minerals",
            "type":"Manufacturing & Wholesale Goods"
        }
    ],
    "sg:phone":"+61 8 9537 3601",
    "sg:postcode":"6175",
    "sg:province":"WA",
    "sg:tags":[
        "stained"
    ],
    "wof:name":"Armadale Leadlights",
    "wof:placetype":"venue"
},
  "geometry": {"coordinates":[115.752342,-32.448898],"type":"Point"}
}