{
  "type": "Feature",
  "properties": {
    "addr:full":"Colamba St Chinchilla QLD 4413",
    "addr:postcode":"4413",
    "addr:street":"St",
    "iso:country":"AU",
    "sg:address":"Colamba St",
    "sg:city":"Chinchilla",
    "sg:classifiers":[
        {
            "category":"Retail",
            "subcategory":"Auto Repair",
            "type":"Services"
        }
    ],
    "sg:phone":"+61 7 4662 7042",
    "sg:postcode":"4413",
    "sg:province":"QLD",
    "sg:tags":[
        "beater",
        "painter",
        "panel"
    ],
    "wof:name":"Lattimores&#039; Carey Ford",
    "wof:placetype":"venue"
},
  "geometry": {"coordinates":[150.6277771,-26.7396907806],"type":"Point"}
}