{
  "type": "Feature",
  "properties": {
    "iso:country":"AU",
    "sg:address":"47 Anderson Wlk",
    "sg:city":"Smithfield",
    "sg:classifiers":[
        {
            "category":"Professional",
            "subcategory":"Printing & Photocopies",
            "type":"Services"
        }
    ],
    "sg:phone":"+61 8 8284 4011",
    "sg:postcode":"5114",
    "sg:province":"SA",
    "sg:tags":[
        "embroidery"
    ],
    "wof:name":"Amaja Embroidery",
    "wof:placetype":"venue"
},
  "geometry": {"coordinates":[138.68887329099999,-34.681842804],"type":"Point"}
}