{
  "type": "Feature",
  "properties": {
    "addr:full":"61 Sturt St Angaston SA 5353",
    "addr:housenumber":"61",
    "addr:postcode":"5353",
    "addr:street":"Sturt St",
    "iso:country":"AU",
    "sg:address":"61 Sturt St",
    "sg:city":"Angaston",
    "sg:classifiers":[
        {
            "category":"Utilities",
            "type":"Services"
        }
    ],
    "sg:phone":"+61 8 8564 3172",
    "sg:postcode":"5353",
    "sg:province":"SA",
    "sg:tags":[
        "refrigeration",
        "industrial",
        "commercial",
        "retail"
    ],
    "wof:name":"Angaston Refrigeration & Airconditioning",
    "wof:placetype":"venue"
},
  "geometry": {"coordinates":[139.049118042,-34.5072975159],"type":"Point"}
}