{
  "type": "Feature",
  "properties": {
    "iso:country":"AU",
    "sg:address":"3/ 21 Anthony St",
    "sg:city":"Mt Gambier",
    "sg:classifiers":[
        {
            "category":"Retail",
            "subcategory":"Repair Shop",
            "type":"Services"
        }
    ],
    "sg:phone":"+61 8 8723 9044",
    "sg:postcode":"5290",
    "sg:province":"SA",
    "sg:tags":[
        "windscreen"
    ],
    "wof:name":"South East Windscreens",
    "wof:placetype":"venue"
},
  "geometry": {"coordinates":[140.790024,-37.828278],"type":"Point"}
}