{
  "type": "Feature",
  "properties": {
    "iso:country":"AU",
    "sg:address":"20 Selhurst St",
    "sg:city":"Coopers Plains",
    "sg:classifiers":[
        {
            "category":"Wholesale",
            "subcategory":"Machinery & Supplies",
            "type":"Manufacturing & Wholesale Goods"
        }
    ],
    "sg:phone":"+61 7 3344 1113",
    "sg:postcode":"4108",
    "sg:province":"QLD",
    "sg:tags":[
        "agricultural"
    ],
    "wof:name":"Bepco Australasia",
    "wof:placetype":"venue"
},
  "geometry": {"coordinates":[153.03631591800001,-27.5715656281],"type":"Point"}
}