{
  "type": "Feature",
  "properties": {
    "iso:country":"AU",
    "sg:address":"Kiosk 2",
    "sg:city":"Belmont Forum Belmont",
    "sg:classifiers":[
        {
            "category":"Ice Cream",
            "type":"Food & Drink"
        }
    ],
    "sg:phone":"+61 8 9277 6590",
    "sg:postcode":"6104",
    "sg:province":"WA",
    "sg:tags":[
        "retail"
    ],
    "wof:name":"Wendys Supa Sundaes",
    "wof:placetype":"venue"
},
  "geometry": {"coordinates":[115.917236328,-31.951751709],"type":"Point"}
}