{
  "type": "Feature",
  "properties": {
    "addr:full":"Lot 56 Cunalea Rd Moresby WA 6530",
    "addr:postcode":"6530",
    "addr:street":"Cunalea Rd",
    "iso:country":"AU",
    "sg:address":"Lot 56 Cunalea Rd",
    "sg:city":"Moresby",
    "sg:classifiers":[
        {
            "category":"Social Services",
            "subcategory":"Retirement Home",
            "type":"Services"
        }
    ],
    "sg:phone":"+61 8 9938 2639",
    "sg:postcode":"6530",
    "sg:province":"WA",
    "sg:tags":[
        "accommodation",
        "special"
    ],
    "wof:name":"Moresby Range Farmstay & Chalets",
    "wof:placetype":"venue"
},
  "geometry": {"coordinates":[114.67301178,-28.713470459],"type":"Point"}
}