{
  "type": "Feature",
  "properties": {
    "addr:full":"U4 35 Ethel St Yeerongpilly QLD 4105",
    "addr:housenumber":"35",
    "addr:postcode":"4105",
    "addr:street":"U4;Ethel St",
    "iso:country":"AU",
    "sg:address":"U4 35 Ethel St",
    "sg:city":"Yeerongpilly",
    "sg:classifiers":[
        {
            "category":"Professional",
            "subcategory":"Computer Services",
            "type":"Services"
        }
    ],
    "sg:phone":"+61 7 3892 9100",
    "sg:postcode":"4105",
    "sg:province":"QLD",
    "sg:tags":[
        "tele-communications",
        "consultant"
    ],
    "wof:name":"Mantel Solutions",
    "wof:placetype":"venue"
},
  "geometry": {"coordinates":[153.01121520999999,-27.5275249481],"type":"Point"}
}