{
  "type": "Feature",
  "properties": {
    "iso:country":"AU",
    "sg:address":"59 Bourke St",
    "sg:city":"West Launceston",
    "sg:classifiers":[
        {
            "category":"Education",
            "subcategory":"Music School",
            "type":"Public Place"
        }
    ],
    "sg:phone":"+61 3 6331 7343",
    "sg:postcode":"7250",
    "sg:province":"TAS",
    "sg:tags":[
        "teacher"
    ],
    "wof:name":"Tyson Matthews S.",
    "wof:placetype":"venue"
},
  "geometry": {"coordinates":[147.133422852,-41.4443244934],"type":"Point"}
}