{
  "type": "Feature",
  "properties": {
    "addr:full":"210 Prospect Hill Rd Surrey Hills VIC 3127",
    "addr:housenumber":"210",
    "addr:postcode":"3127",
    "addr:street":"Prospect Hill Rd",
    "iso:country":"AU",
    "sg:address":"210 Prospect Hill Rd",
    "sg:city":"Surrey Hills",
    "sg:classifiers":[
        {
            "category":"Building & Trades",
            "subcategory":"Landscaping Services",
            "type":"Services"
        }
    ],
    "sg:phone":"+61 407 166 425",
    "sg:postcode":"3127",
    "sg:province":"VIC",
    "sg:tags":[
        "designer",
        "landscape",
        "contractor"
    ],
    "wof:name":"Sally Tulloch Gardens",
    "wof:placetype":"venue"
},
  "geometry": {"coordinates":[145.086959839,-37.831943512],"type":"Point"}
}