{
  "type": "Feature",
  "properties": {
    "addr:full":"Shp 1/ 2 North Colville St Lyneham ACT 2602",
    "addr:housenumber":"/ 2",
    "addr:postcode":"2602",
    "addr:street":"North Colville St",
    "iso:country":"AU",
    "sg:address":"Shp 1/ 2 North Colville St",
    "sg:city":"Lyneham",
    "sg:classifiers":[
        {
            "category":"Sports & Exercise",
            "subcategory":"Gym",
            "type":"Entertainment"
        }
    ],
    "sg:phone":"+61 2 6257 1483",
    "sg:postcode":"2602",
    "sg:province":"ACT",
    "sg:tags":[
        "health",
        "fitness"
    ],
    "wof:name":"Flames Fitness",
    "wof:placetype":"venue"
},
  "geometry": {"coordinates":[149.124511719,-35.2402954102],"type":"Point"}
}