{
  "type": "Feature",
  "properties": {
    "addr:full":"Suite 1, Level 1, 368 Hawthorn Rd Caulfield South VIC 3162",
    "addr:housenumber":"368",
    "addr:postcode":"3162",
    "addr:street":"Hawthorn Rd",
    "iso:country":"AU",
    "sg:address":"Suite 1, Level 1, 368 Hawthorn Rd",
    "sg:city":"Caulfield South",
    "sg:classifiers":[
        {
            "category":"Professional",
            "subcategory":"Printing & Photocopies",
            "type":"Services"
        }
    ],
    "sg:phone":"+61 3 9528 2660",
    "sg:postcode":"3162",
    "sg:province":"VIC",
    "sg:tags":[
        "photocopying"
    ],
    "wof:name":"Copy Plus",
    "wof:placetype":"venue"
},
  "geometry": {"coordinates":[145.02162170400001,-37.8877983093],"type":"Point"}
}