{
  "type": "Feature",
  "properties": {
    "addr:full":"Shp 8/ 187 Bourke St Darlinghurst NSW 2010",
    "addr:housenumber":"/ 187",
    "addr:postcode":"2010",
    "addr:street":"Bourke St",
    "iso:country":"AU",
    "sg:address":"Shp 8/ 187 Bourke St",
    "sg:city":"Darlinghurst",
    "sg:classifiers":[
        {
            "category":"Personal",
            "subcategory":"Beauty Salon",
            "type":"Services"
        }
    ],
    "sg:phone":"+61 2 9332 1112",
    "sg:postcode":"2010",
    "sg:province":"NSW",
    "sg:tags":[
        "hairdresser"
    ],
    "wof:name":"Get Hair & Beauty",
    "wof:placetype":"venue"
},
  "geometry": {"coordinates":[151.217849731,-33.8748245239],"type":"Point"}
}