{
  "type": "Feature",
  "properties": {
    "addr:full":"36 Lucida Pl Ilkley QLD 4554",
    "addr:housenumber":"36",
    "addr:postcode":"4554",
    "addr:street":"Lucida Pl",
    "iso:country":"AU",
    "sg:address":"36 Lucida Pl",
    "sg:city":"Ilkley",
    "sg:classifiers":[
        {
            "category":"Building & Trades",
            "subcategory":"Construction",
            "type":"Services"
        }
    ],
    "sg:phone":"+61 411 870 268",
    "sg:postcode":"4554",
    "sg:province":"QLD",
    "sg:tags":[
        "concrete",
        "contractor"
    ],
    "wof:name":"Cellucrete Concreting Pty Ltd",
    "wof:placetype":"venue"
},
  "geometry": {"coordinates":[153.004104614,-26.7153282166],"type":"Point"}
}