{
  "type": "Feature",
  "properties": {
    "addr:full":"4 Giaour St Byron Bay NSW 2481",
    "addr:housenumber":"4",
    "addr:postcode":"2481",
    "addr:street":"Giaour St",
    "iso:country":"AU",
    "sg:address":"4 Giaour St",
    "sg:city":"Byron Bay",
    "sg:classifiers":[
        {
            "category":"Utilities",
            "subcategory":"Electric",
            "type":"Services"
        }
    ],
    "sg:phone":"+61 2 6685 8691",
    "sg:postcode":"2481",
    "sg:province":"NSW",
    "sg:tags":[
        "electrical",
        "contractor"
    ],
    "wof:name":"Alfred Burley",
    "wof:placetype":"venue"
},
  "geometry": {"coordinates":[153.59840393100001,-28.6341972351],"type":"Point"}
}