{
  "type": "Feature",
  "properties": {
    "addr:full":"The Rec. Club, Barclay Dr Casuarina NSW 2487",
    "addr:postcode":"2487",
    "addr:street":"Barclay Dr",
    "iso:country":"AU",
    "sg:address":"The Rec. Club, Barclay Dr",
    "sg:city":"Casuarina",
    "sg:classifiers":[
        {
            "category":"Health Services",
            "subcategory":"Doctor",
            "type":"Services"
        }
    ],
    "sg:phone":"+61 1300 361 238",
    "sg:postcode":"2487",
    "sg:province":"NSW",
    "sg:tags":[
        "podiatrist"
    ],
    "wof:name":"Foot Analysis Centre",
    "wof:placetype":"venue"
},
  "geometry": {"coordinates":[153.57000732399999,-28.3040294647],"type":"Point"}
}