{
  "type": "Feature",
  "properties": {
    "iso:country":"AU",
    "sg:address":"132 Canterbury Rd",
    "sg:city":"Heathmont",
    "sg:classifiers":[
        {
            "category":"Shopping",
            "subcategory":"Clothing, Apparel, & Fashions",
            "type":"Retail Goods"
        }
    ],
    "sg:phone":"+61 3 9720 0866",
    "sg:postcode":"3135",
    "sg:province":"VIC",
    "sg:tags":[
        "recycled",
        "clothing"
    ],
    "wof:name":"Elegant Vintage",
    "wof:placetype":"venue"
},
  "geometry": {"coordinates":[145.246582031,-37.8284606934],"type":"Point"}
}