{
  "type": "Feature",
  "properties": {
    "addr:full":"100 Wahroonga Rd Kanwal NSW 2259",
    "addr:housenumber":"100",
    "addr:postcode":"2259",
    "addr:street":"Wahroonga Rd",
    "iso:country":"AU",
    "sg:address":"100 Wahroonga Rd",
    "sg:city":"Kanwal",
    "sg:classifiers":[
        {
            "category":"Health Services",
            "subcategory":"Nursing And Care Facility",
            "type":"Services"
        }
    ],
    "sg:phone":"+61 2 4393 1888",
    "sg:postcode":"2259",
    "sg:province":"NSW",
    "sg:tags":[
        "home"
    ],
    "wof:name":"Glenmere Residential Aged Care Facility",
    "wof:placetype":"venue"
},
  "geometry": {"coordinates":[151.47622680699999,-33.2679595947],"type":"Point"}
}