{
  "type": "Feature",
  "properties": {
    "addr:full":"53 Lockwood St Yokine WA 6060",
    "addr:housenumber":"53",
    "addr:postcode":"6060",
    "addr:street":"Lockwood St",
    "iso:country":"AU",
    "sg:address":"53 Lockwood St",
    "sg:city":"Yokine",
    "sg:classifiers":[
        {
            "category":"Real Estate",
            "subcategory":"Real Estate Agent",
            "type":"Services"
        }
    ],
    "sg:phone":"+61 8 9207 1100",
    "sg:postcode":"6060",
    "sg:province":"WA",
    "wof:name":"Perth Real Estate Centre",
    "wof:placetype":"venue"
},
  "geometry": {"coordinates":[115.84654235799999,-31.9034671783],"type":"Point"}
}