{
  "type": "Feature",
  "properties": {
    "iso:country":"AU",
    "sg:address":"Shop 9 Safeway Plz",
    "sg:city":"Warrnambool",
    "sg:classifiers":[
        {
            "category":"Personal",
            "subcategory":"Beauty Salon",
            "type":"Services"
        }
    ],
    "sg:phone":"+61 3 5562 2841",
    "sg:postcode":"3280",
    "sg:province":"VIC",
    "sg:tags":[
        "hairdresser"
    ],
    "wof:name":"Bruce Purcell Hair Designs",
    "wof:placetype":"venue"
},
  "geometry": {"coordinates":[142.48323059099999,-38.3842582703],"type":"Point"}
}