{
  "type": "Feature",
  "properties": {
    "iso:country":"AU",
    "sg:address":"43 McKillop St",
    "sg:city":"Geelong",
    "sg:classifiers":[
        {
            "category":"Shopping",
            "subcategory":"Computers & Home Electronics",
            "type":"Retail Goods"
        }
    ],
    "sg:phone":"+61 3 5225 0066",
    "sg:postcode":"3220",
    "sg:province":"VIC",
    "sg:tags":[
        "hardware",
        "equipment"
    ],
    "wof:name":"Think Technology",
    "wof:placetype":"venue"
},
  "geometry": {"coordinates":[144.356476,-38.152802],"type":"Point"}
}