{
  "type": "Feature",
  "properties": {
    "addr:full":"7 Howard St Moonah TAS 7009",
    "addr:housenumber":"7",
    "addr:postcode":"7009",
    "addr:street":"Howard St",
    "iso:country":"AU",
    "sg:address":"7 Howard St",
    "sg:city":"Moonah",
    "sg:classifiers":[
        {
            "category":"Shopping",
            "subcategory":"Computers & Home Electronics",
            "type":"Retail Goods"
        }
    ],
    "sg:phone":"+61 3 6272 8955",
    "sg:postcode":"7009",
    "sg:province":"TAS",
    "sg:tags":[
        "hardware",
        "equipment"
    ],
    "wof:name":"Power & Automation",
    "wof:placetype":"venue"
},
  "geometry": {"coordinates":[147.29824829099999,-42.8384780884],"type":"Point"}
}