{
  "type": "Feature",
  "properties": {
    "addr:full":"11 Boulder Rd Malaga WA 6090",
    "addr:housenumber":"11",
    "addr:postcode":"6090",
    "addr:street":"Boulder Rd",
    "iso:country":"AU",
    "sg:address":"11 Boulder Rd",
    "sg:city":"Malaga",
    "sg:classifiers":[
        {
            "category":"Manufacturing",
            "subcategory":"Retail Goods",
            "type":"Manufacturing & Wholesale Goods"
        }
    ],
    "sg:phone":"+61 8 9249 2511",
    "sg:postcode":"6090",
    "sg:province":"WA",
    "sg:tags":[
        "merchant",
        "pump",
        "mfrs"
    ],
    "wof:name":"M.H.S. Pumps",
    "wof:placetype":"venue"
},
  "geometry": {"coordinates":[115.900558472,-31.8647613525],"type":"Point"}
}