{
  "type": "Feature",
  "properties": {
    "iso:country":"AU",
    "sg:address":"Amiens Rd",
    "sg:city":"Thulimbah",
    "sg:classifiers":[
        {
            "category":"Farming",
            "subcategory":"Orchard",
            "type":"Manufacturing & Wholesale Goods"
        }
    ],
    "sg:phone":"+61 7 4685 2279",
    "sg:postcode":"4376",
    "sg:province":"QLD",
    "sg:tags":[
        "pear",
        "apple",
        "grower"
    ],
    "wof:name":"Bardini J A F",
    "wof:placetype":"venue"
},
  "geometry": {"coordinates":[151.94015502900001,-28.5501213074],"type":"Point"}
}