{
  "type": "Feature",
  "properties": {
    "iso:country":"AU",
    "sg:address":"35 Golding Ave",
    "sg:city":"Rowville",
    "sg:classifiers":[
        {
            "category":"Organizations",
            "subcategory":"Professional Association",
            "type":"Services"
        }
    ],
    "sg:phone":"+61 3 9755 6854",
    "sg:postcode":"3178",
    "sg:province":"VIC",
    "sg:tags":[
        "web",
        "internet"
    ],
    "wof:name":"TNF Multimedia & IT Solutions",
    "wof:placetype":"venue"
},
  "geometry": {"coordinates":[145.25190734899999,-37.9393119812],"type":"Point"}
}