{
  "type": "Feature",
  "properties": {
    "addr:full":"7/ 12 Nissen St Pialba QLD 4655",
    "addr:housenumber":"/ 12",
    "addr:postcode":"4655",
    "addr:street":"Nissen St",
    "iso:country":"AU",
    "sg:address":"7/ 12 Nissen St",
    "sg:city":"Pialba",
    "sg:classifiers":[
        {
            "category":"Building & Trades",
            "subcategory":"Landscaping Services",
            "type":"Services"
        }
    ],
    "sg:phone":"+61 7 4125 9799",
    "sg:postcode":"4655",
    "sg:province":"QLD",
    "sg:tags":[
        "consultant"
    ],
    "wof:name":"Wide Bay Building Consultants",
    "wof:placetype":"venue"
},
  "geometry": {"coordinates":[152.82711800000001,-25.287399],"type":"Point"}
}