{
  "type": "Feature",
  "properties": {
    "addr:full":"1/ 547 Great North Rd Abbotsford NSW 2046",
    "addr:housenumber":"/ 547",
    "addr:postcode":"2046",
    "addr:street":"Great North Rd",
    "iso:country":"AU",
    "sg:address":"1/ 547 Great North Rd",
    "sg:city":"Abbotsford",
    "sg:classifiers":[
        {
            "category":"Utilities",
            "subcategory":"Telephone",
            "type":"Services"
        }
    ],
    "sg:phone":"+61 2 9712 3333",
    "sg:postcode":"2046",
    "sg:province":"NSW",
    "sg:tags":[
        "equipment",
        "system"
    ],
    "wof:name":"Total Telecommunication Services & Maintenance Pty Ltd",
    "wof:placetype":"venue"
},
  "geometry": {"coordinates":[151.12808200000001,-33.84811],"type":"Point"}
}