{
  "type": "Feature",
  "properties": {
    "addr:full":"184 Forbes St Darlinghurst NSW 2010",
    "addr:housenumber":"184",
    "addr:postcode":"2010",
    "addr:street":"Forbes St",
    "iso:country":"AU",
    "sg:address":"184 Forbes St",
    "sg:city":"Darlinghurst",
    "sg:classifiers":[
        {
            "category":"Professional",
            "subcategory":"Art Services",
            "type":"Services"
        }
    ],
    "sg:phone":"+61 2 9357 2707",
    "sg:postcode":"2010",
    "sg:province":"NSW",
    "sg:tags":[
        "graphic",
        "designer"
    ],
    "wof:name":"Creative Lounge",
    "wof:placetype":"venue"
},
  "geometry": {"coordinates":[151.21925354000001,-33.8752403259],"type":"Point"}
}