{
  "type": "Feature",
  "properties": {
    "addr:full":"Shp7, Halls Head Shpng Cntr, cnr Peelwood & Glencoe Pde Halls Head WA 6210",
    "addr:postcode":"6210",
    "addr:street":"Cnr;Pde",
    "iso:country":"AU",
    "sg:address":"Shp7, Halls Head Shpng Cntr, cnr Peelwood & Glencoe Pde",
    "sg:city":"Halls Head",
    "sg:classifiers":[
        {
            "category":"Banks & Credit Unions",
            "subcategory":"Bank",
            "type":"Services"
        }
    ],
    "sg:phone":"+61 8 9586 1399",
    "sg:postcode":"6210",
    "sg:province":"WA",
    "wof:name":"Bendigo Community Bank",
    "wof:placetype":"venue"
},
  "geometry": {"coordinates":[115.699608,-32.547634],"type":"Point"}
}