{
  "type": "Feature",
  "properties": {
    "iso:country":"AU",
    "sg:address":"89 Wyndham St",
    "sg:city":"Shepparton",
    "sg:classifiers":[
        {
            "category":"Food & Beverages",
            "subcategory":"Groceries & Convenience Stores",
            "type":"Retail Goods"
        }
    ],
    "sg:phone":"+61 3 5831 5860",
    "sg:postcode":"3630",
    "sg:province":"VIC",
    "wof:name":"Marshalls Corner",
    "wof:placetype":"venue"
},
  "geometry": {"coordinates":[145.40097045900001,-36.3739700317],"type":"Point"}
}