{
  "type": "Feature",
  "properties": {
    "addr:full":"4 Fisher St Cabramatta NSW 2166",
    "addr:housenumber":"4",
    "addr:postcode":"2166",
    "addr:street":"Fisher St",
    "iso:country":"AU",
    "sg:address":"4 Fisher St",
    "sg:city":"Cabramatta",
    "sg:classifiers":[
        {
            "category":"Retail",
            "subcategory":"Laundry & Dry Cleaning",
            "type":"Services"
        }
    ],
    "sg:phone":"+61 2 9727 0424",
    "sg:postcode":"2166",
    "sg:province":"NSW",
    "sg:tags":[
        "equipment",
        "supply"
    ],
    "wof:name":"South West Laundry",
    "wof:placetype":"venue"
},
  "geometry": {"coordinates":[150.94183349599999,-33.894115448],"type":"Point"}
}