{
  "type": "Feature",
  "properties": {
    "addr:full":"Shop 4 Tropical Arcade Shield St Cairns QLD 4870",
    "addr:housenumber":"shop 4",
    "addr:postcode":"4870",
    "addr:street":"Tropical Arcade Shield St",
    "iso:country":"AU",
    "sg:address":"Shop 4 Tropical Arcade Shield St",
    "sg:city":"Cairns",
    "sg:classifiers":[
        {
            "category":"Arts & Performance",
            "subcategory":"Art Gallery",
            "type":"Entertainment"
        }
    ],
    "sg:phone":"+61 7 4041 2800",
    "sg:postcode":"4870",
    "sg:province":"QLD",
    "sg:tags":[
        "aboriginal",
        "craft"
    ],
    "wof:name":"Queensland Aborigine The",
    "wof:placetype":"venue"
},
  "geometry": {"coordinates":[145.66958618199999,-17.0185699463],"type":"Point"}
}