{
  "type": "Feature",
  "properties": {
    "addr:full":"Shop 77 Carlingford Crt Carlingford NSW 2118",
    "addr:housenumber":"shop 77",
    "addr:postcode":"2118",
    "addr:street":"Carlingford Crt",
    "iso:country":"AU",
    "sg:address":"Shop 77 Carlingford Crt",
    "sg:city":"Carlingford",
    "sg:classifiers":[
        {
            "category":"Shopping",
            "subcategory":"Clothing, Apparel, & Fashions",
            "type":"Retail Goods"
        }
    ],
    "sg:phone":"+61 2 9872 4428",
    "sg:postcode":"2118",
    "sg:province":"NSW",
    "sg:tags":[
        "lady",
        "wear"
    ],
    "wof:name":"Cue",
    "wof:placetype":"venue"
},
  "geometry": {"coordinates":[151.06393432600001,-33.7748069763],"type":"Point"}
}