{
  "type": "Feature",
  "properties": {
    "iso:country":"AU",
    "sg:address":"4 Barney St",
    "sg:city":"Arana Hills",
    "sg:classifiers":[
        {
            "category":"Retail",
            "subcategory":"Repair Shop",
            "type":"Services"
        }
    ],
    "sg:phone":"+61 7 3851 4057",
    "sg:postcode":"4054",
    "sg:province":"QLD",
    "sg:tags":[
        "upholsterer"
    ],
    "wof:name":"Topline Upholstery Shops",
    "wof:placetype":"venue"
},
  "geometry": {"coordinates":[152.958984375,-27.3896808624],"type":"Point"}
}