{
  "type": "Feature",
  "properties": {
    "addr:full":"Lvl 6 / Ste 8/ 410 Chapel Rd Bankstown NSW 2200",
    "addr:housenumber":"/ 410",
    "addr:postcode":"2200",
    "addr:street":"/;Chapel Rd",
    "iso:country":"AU",
    "sg:address":"Lvl 6 / Ste 8/ 410 Chapel Rd",
    "sg:city":"Bankstown",
    "sg:classifiers":[
        {
            "category":"Professional",
            "subcategory":"Detective & Security Services",
            "type":"Services"
        }
    ],
    "sg:phone":"+61 2 9709 8400",
    "sg:postcode":"2200",
    "sg:province":"NSW",
    "sg:tags":[
        "consultant",
        "system"
    ],
    "wof:name":"Taylordante",
    "wof:placetype":"venue"
},
  "geometry": {"coordinates":[151.03376800000001,-33.915237],"type":"Point"}
}