{
  "type": "Feature",
  "properties": {
    "addr:full":"Cnr Bowen St & Tiger Brennan Dr Winnellie NT 0820",
    "addr:postcode":"nt 0820",
    "addr:street":"Cnr Bowen St &;Brennan Dr Winnellie",
    "iso:country":"AU",
    "sg:address":"Cnr Bowen St & Tiger Brennan Dr",
    "sg:city":"Winnellie",
    "sg:classifiers":[
        {
            "category":"Communications",
            "subcategory":"Film & Video Production",
            "type":"Services"
        }
    ],
    "sg:phone":"+61 8 8984 3840",
    "sg:postcode":"0820",
    "sg:province":"NT",
    "sg:tags":[
        "fan",
        "blower"
    ],
    "wof:name":"Fantech",
    "wof:placetype":"venue"
},
  "geometry": {"coordinates":[130.87355041500001,-12.431473732],"type":"Point"}
}