{
  "type": "Feature",
  "properties": {
    "addr:full":"123 Colburn Ave Victoria Point QLD 4165",
    "addr:housenumber":"123",
    "addr:postcode":"4165",
    "addr:street":"Colburn Ave",
    "iso:country":"AU",
    "sg:address":"123 Colburn Ave",
    "sg:city":"Victoria Point",
    "sg:classifiers":[
        {
            "category":"Health Services",
            "subcategory":"Doctor",
            "type":"Services"
        }
    ],
    "sg:phone":"+61 7 3207 7299",
    "sg:postcode":"4165",
    "sg:province":"QLD",
    "sg:tags":[
        "medical",
        "practitioner"
    ],
    "wof:name":"Redlands Clinic",
    "wof:placetype":"venue"
},
  "geometry": {"coordinates":[153.28436279300001,-27.5844020844],"type":"Point"}
}