{
  "type": "Feature",
  "properties": {
    "addr:full":"8 Havelock St Wodonga VIC 3690",
    "addr:housenumber":"8",
    "addr:postcode":"3690",
    "addr:street":"Havelock St",
    "iso:country":"AU",
    "sg:address":"8 Havelock St",
    "sg:city":"Wodonga",
    "sg:classifiers":[
        {
            "category":"Health Services",
            "subcategory":"Health Practitioner",
            "type":"Services"
        }
    ],
    "sg:phone":"+61 2 6024 4759",
    "sg:postcode":"3690",
    "sg:province":"VIC",
    "sg:tags":[
        "psychologist"
    ],
    "wof:name":"Langmead Les",
    "wof:placetype":"venue"
},
  "geometry": {"coordinates":[146.89100647000001,-36.1229972839],"type":"Point"}
}