{
  "type": "Feature",
  "properties": {
    "addr:full":"Shop 30 Grnd Flr Penrith Plz Penrith NSW 2750",
    "addr:housenumber":"shop 30;flr",
    "addr:postcode":"2750",
    "addr:street":"Grnd;Plz",
    "iso:country":"AU",
    "sg:address":"Shop 30",
    "sg:city":"Grnd Flr Penrith Plz Penrith",
    "sg:classifiers":[
        {
            "category":"Shopping",
            "subcategory":"Music",
            "type":"Retail Goods"
        }
    ],
    "sg:phone":"+61 2 4721 0365",
    "sg:postcode":"2750",
    "sg:province":"NSW",
    "sg:tags":[
        "store"
    ],
    "wof:name":"Leading Edge Music",
    "wof:placetype":"venue"
},
  "geometry": {"coordinates":[150.68374633799999,-33.7659645081],"type":"Point"}
}