{
  "type": "Feature",
  "properties": {
    "addr:full":"3a George St Hindmarsh SA 5007",
    "addr:housenumber":"3a",
    "addr:postcode":"5007",
    "addr:street":"George St",
    "iso:country":"AU",
    "sg:address":"3a George St",
    "sg:city":"Hindmarsh",
    "sg:classifiers":[
        {
            "category":"Wholesale",
            "subcategory":"Office Equipment",
            "type":"Manufacturing & Wholesale Goods"
        }
    ],
    "sg:phone":"+61 8 8340 4088",
    "sg:postcode":"5007",
    "sg:province":"SA",
    "sg:tags":[
        "staple",
        "stapling"
    ],
    "wof:name":"Paslode Australia",
    "wof:placetype":"venue"
},
  "geometry": {"coordinates":[138.56869506800001,-34.9040756226],"type":"Point"}
}