{
  "type": "Feature",
  "properties": {
    "addr:full":"126 John St Singleton NSW 2330",
    "addr:housenumber":"126",
    "addr:postcode":"2330",
    "addr:street":"John St",
    "iso:country":"AU",
    "sg:address":"126 John St",
    "sg:city":"Singleton",
    "sg:classifiers":[
        {
            "category":"Professional",
            "subcategory":"Business Services",
            "type":"Services"
        }
    ],
    "sg:phone":"+61 2 6572 1877",
    "sg:postcode":"2330",
    "sg:province":"NSW",
    "sg:tags":[
        "small",
        "advisory"
    ],
    "wof:name":"Business Enterprise Centre",
    "wof:placetype":"venue"
},
  "geometry": {"coordinates":[151.16716,-32.565056],"type":"Point"}
}