{
  "type": "Feature",
  "properties": {
    "addr:full":"U2/ 151 Princes Hwy Hallam VIC 3803",
    "addr:housenumber":"151",
    "addr:postcode":"3803",
    "addr:street":"U2 /;Princes Hwy",
    "iso:country":"AU",
    "sg:address":"U2/ 151 Princes Hwy",
    "sg:city":"Hallam",
    "sg:classifiers":[
        {
            "category":"Professional",
            "subcategory":"Engineering",
            "type":"Services"
        }
    ],
    "sg:phone":"+61 3 9796 5087",
    "sg:postcode":"3803",
    "sg:province":"VIC",
    "sg:tags":[
        "electrical",
        "engineer"
    ],
    "wof:name":"LEN Electrical Pty Ltd",
    "wof:placetype":"venue"
},
  "geometry": {"coordinates":[145.25852966299999,-38.0049362183],"type":"Point"}
}