{
  "type": "Feature",
  "properties": {
    "addr:full":"Story St Parkville VIC 3052",
    "addr:postcode":"3052",
    "addr:street":"Story St",
    "iso:country":"AU",
    "sg:address":"Story St",
    "sg:city":"Parkville",
    "sg:classifiers":[
        {
            "category":"Education",
            "subcategory":"School",
            "type":"Public Place"
        }
    ],
    "sg:phone":"+61 3 9347 2022",
    "sg:postcode":"3052",
    "sg:province":"VIC",
    "sg:tags":[
        "state",
        "except",
        "nsw"
    ],
    "wof:name":"University High School",
    "wof:placetype":"venue"
},
  "geometry": {"coordinates":[144.956542969,-37.7968025208],"type":"Point"}
}