{
  "type": "Feature",
  "properties": {
    "iso:country":"AU",
    "sg:address":"48 Bulolo Drv",
    "sg:city":"Whalan",
    "sg:classifiers":[
        {
            "category":"Education",
            "subcategory":"Special Training",
            "type":"Public Place"
        }
    ],
    "sg:phone":"+61 2 9832 4775",
    "sg:postcode":"2770",
    "sg:province":"NSW",
    "sg:tags":[
        "development"
    ],
    "wof:name":"Western Sydney Training & Education Centre",
    "wof:placetype":"venue"
},
  "geometry": {"coordinates":[150.81149292000001,-33.7539215088],"type":"Point"}
}