{
  "type": "Feature",
  "properties": {
    "addr:full":"289 MacDonnell Rd Clontarf QLD 4019",
    "addr:housenumber":"289",
    "addr:postcode":"4019",
    "addr:street":"Macdonnell Rd",
    "iso:country":"AU",
    "sg:address":"289 MacDonnell Rd",
    "sg:city":"Clontarf",
    "sg:classifiers":[
        {
            "category":"Wholesale",
            "subcategory":"Machinery & Supplies",
            "type":"Manufacturing & Wholesale Goods"
        }
    ],
    "sg:phone":"+61 7 3284 7900",
    "sg:postcode":"4019",
    "sg:province":"QLD",
    "sg:tags":[
        "equipment",
        "welding"
    ],
    "wof:name":"Berco Industrial Sales",
    "wof:placetype":"venue"
},
  "geometry": {"coordinates":[153.084594727,-27.2342090607],"type":"Point"}
}