{
  "type": "Feature",
  "properties": {
    "iso:country":"AU",
    "sg:address":"8/ 191 Ramsey St",
    "sg:city":"Haberfield",
    "sg:classifiers":[
        {
            "category":"Personal",
            "subcategory":"Beauty Salon",
            "type":"Services"
        }
    ],
    "sg:phone":"+61 2 9797 8384",
    "sg:postcode":"2045",
    "sg:province":"NSW",
    "sg:tags":[
        "hairdresser"
    ],
    "wof:name":"Luke Karadag Hair",
    "wof:placetype":"venue"
},
  "geometry": {"coordinates":[151.137665,-33.878792],"type":"Point"}
}