{
  "type": "Feature",
  "properties": {
    "addr:full":"98 Fletcher St Essendon VIC 3040",
    "addr:housenumber":"98",
    "addr:postcode":"3040",
    "addr:street":"Fletcher St",
    "iso:country":"AU",
    "sg:address":"98 Fletcher St",
    "sg:city":"Essendon",
    "sg:classifiers":[
        {
            "category":"Professional",
            "subcategory":"Accounting & Tax Preparation",
            "type":"Services"
        }
    ],
    "sg:phone":"+61 3 9370 0177",
    "sg:postcode":"3040",
    "sg:province":"VIC",
    "sg:tags":[
        "consultant",
        "taxation"
    ],
    "wof:name":"Hedley Paul A",
    "wof:placetype":"venue"
},
  "geometry": {"coordinates":[144.918136597,-37.7549514771],"type":"Point"}
}