{
  "type": "Feature",
  "properties": {
    "iso:country":"AU",
    "sg:address":"Unit 7 & 8 61 Albert Rd",
    "sg:city":"Bunbury",
    "sg:classifiers":[
        {
            "category":"Building & Trades",
            "subcategory":"Equipment Rental",
            "type":"Services"
        }
    ],
    "sg:phone":"+61 8 9791 2214",
    "sg:postcode":"6230",
    "sg:province":"WA",
    "sg:tags":[
        "party",
        "hire"
    ],
    "wof:name":"Bunbury Party Hire",
    "wof:placetype":"venue"
},
  "geometry": {"coordinates":[115.648422,-33.336048],"type":"Point"}
}