{
  "type": "Feature",
  "properties": {
    "addr:full":"45 Ipswich St Riverview QLD 4303",
    "addr:housenumber":"45",
    "addr:postcode":"4303",
    "addr:street":"Ipswich St",
    "iso:country":"AU",
    "sg:address":"45 Ipswich St",
    "sg:city":"Riverview",
    "sg:classifiers":[
        {
            "category":"Manufacturing",
            "subcategory":"Printing",
            "type":"Manufacturing & Wholesale Goods"
        }
    ],
    "sg:phone":"+61 7 3282 4482",
    "sg:postcode":"4303",
    "sg:province":"QLD",
    "sg:tags":[
        "wholesaler",
        "mfrs",
        "greeting",
        "card"
    ],
    "wof:name":"Sunshine Greetings",
    "wof:placetype":"venue"
},
  "geometry": {"coordinates":[152.850875855,-27.6036605835],"type":"Point"}
}