{
  "type": "Feature",
  "properties": {
    "addr:full":"381 High St Melton VIC 3337",
    "addr:housenumber":"381",
    "addr:postcode":"3337",
    "addr:street":"High St",
    "iso:country":"AU",
    "sg:address":"381 High St",
    "sg:city":"Melton",
    "sg:classifiers":[
        {
            "category":"Food & Beverages",
            "subcategory":"Bakery",
            "type":"Retail Goods"
        }
    ],
    "sg:phone":"+61 3 9747 0044",
    "sg:postcode":"3337",
    "sg:province":"VIC",
    "sg:tags":[
        "cake",
        "shop",
        "pastry"
    ],
    "wof:name":"Ferguson Plarre Bakehouses Pty Ltd",
    "wof:placetype":"venue"
},
  "geometry": {"coordinates":[144.58114599999999,-37.683487],"type":"Point"}
}