{
  "type": "Feature",
  "properties": {
    "addr:full":"10 Tennyson St Kurralta Park SA 5037",
    "addr:housenumber":"10",
    "addr:postcode":"5037",
    "addr:street":"Tennyson St",
    "iso:country":"AU",
    "sg:address":"10 Tennyson St",
    "sg:city":"Kurralta Park",
    "sg:classifiers":[
        {
            "category":"Personal",
            "subcategory":"Massage",
            "type":"Services"
        }
    ],
    "sg:phone":"+61 8 8351 2462",
    "sg:postcode":"5037",
    "sg:province":"SA",
    "sg:tags":[
        "therapy"
    ],
    "wof:name":"Sanctuary Therapeutic Massage",
    "wof:placetype":"venue"
},
  "geometry": {"coordinates":[138.57020568900001,-34.9494667053],"type":"Point"}
}