{
  "type": "Feature",
  "properties": {
    "addr:full":"34 Queen St Campbelltown NSW 2560",
    "addr:housenumber":"34",
    "addr:postcode":"2560",
    "addr:street":"Queen St",
    "iso:country":"AU",
    "sg:address":"34 Queen St",
    "sg:city":"Campbelltown",
    "sg:classifiers":[
        {
            "category":"Shopping",
            "subcategory":"Mobile Phones",
            "type":"Retail Goods"
        }
    ],
    "sg:phone":"+61 2 4628 0300",
    "sg:postcode":"2560",
    "sg:province":"NSW",
    "sg:tags":[
        "telephone",
        "accessory"
    ],
    "wof:name":"Strathfield",
    "wof:placetype":"venue"
},
  "geometry": {"coordinates":[150.82130432100001,-34.0589141846],"type":"Point"}
}