{
  "type": "Feature",
  "properties": {
    "addr:full":"Drive Inn Rd Moree NSW 2400",
    "addr:postcode":"2400",
    "addr:street":"Inn Rd",
    "iso:country":"AU",
    "sg:address":"Drive Inn Rd",
    "sg:city":"Moree",
    "sg:classifiers":[
        {
            "category":"Wholesale",
            "subcategory":"Fruits & Vegetables",
            "type":"Manufacturing & Wholesale Goods"
        }
    ],
    "sg:phone":"+61 2 6752 7666",
    "sg:postcode":"2400",
    "sg:province":"NSW",
    "sg:tags":[
        "produce",
        "grain"
    ],
    "wof:name":"Seed & Grain Sales Pty Ltd",
    "wof:placetype":"venue"
},
  "geometry": {"coordinates":[149.841598511,-29.4661998749],"type":"Point"}
}