{
  "type": "Feature",
  "properties": {
    "addr:full":"2 Victoria St Katoomba NSW 2780",
    "addr:housenumber":"2",
    "addr:postcode":"2780",
    "addr:street":"Victoria St",
    "iso:country":"AU",
    "sg:address":"2 Victoria St",
    "sg:city":"Katoomba",
    "sg:classifiers":[
        {
            "category":"Food & Beverages",
            "subcategory":"Groceries & Convenience Stores",
            "type":"Retail Goods"
        }
    ],
    "sg:phone":"+61 2 4782 2303",
    "sg:postcode":"2780",
    "sg:province":"NSW",
    "wof:name":"Handy Store The",
    "wof:placetype":"venue"
},
  "geometry": {"coordinates":[150.311599731,-33.705821991],"type":"Point"}
}