{
  "type": "Feature",
  "properties": {
    "addr:full":"3 Reddall Pde Lake Illawarra NSW 2528",
    "addr:housenumber":"3",
    "addr:postcode":"2528",
    "addr:street":"Reddall Pde",
    "iso:country":"AU",
    "sg:address":"3 Reddall Pde",
    "sg:city":"Lake Illawarra",
    "sg:classifiers":[
        {
            "category":"Fast Food",
            "type":"Food & Drink"
        }
    ],
    "sg:phone":"+61 2 4296 8303",
    "sg:postcode":"2528",
    "sg:province":"NSW",
    "sg:tags":[
        "away",
        "take"
    ],
    "wof:name":"Pep's Takeaway",
    "wof:placetype":"venue"
},
  "geometry": {"coordinates":[150.86961364699999,-34.5459251404],"type":"Point"}
}