{
  "type": "Feature",
  "properties": {
    "addr:full":"72 Lipscombe Ave Sandy Bay TAS 7005",
    "addr:housenumber":"72",
    "addr:postcode":"7005",
    "addr:street":"Lipscombe Ave",
    "iso:country":"AU",
    "sg:address":"72 Lipscombe Ave",
    "sg:city":"Sandy Bay",
    "sg:classifiers":[
        {
            "category":"Building & Trades",
            "subcategory":"Plumbing",
            "type":"Services"
        }
    ],
    "sg:phone":"+61 3 6225 4435",
    "sg:postcode":"7005",
    "sg:province":"TAS",
    "sg:tags":[
        "plumber",
        "gasfitters"
    ],
    "wof:name":"Shepperd B R & D",
    "wof:placetype":"venue"
},
  "geometry": {"coordinates":[147.34861755399999,-42.9171142578],"type":"Point"}
}