{
  "type": "Feature",
  "properties": {
    "addr:full":"47A Talkalvan St Bundaberg QLD 4670",
    "addr:housenumber":"47a",
    "addr:postcode":"4670",
    "addr:street":"Talkalvan St",
    "iso:country":"AU",
    "sg:address":"47A Talkalvan St",
    "sg:city":"Bundaberg",
    "sg:classifiers":[
        {
            "category":"Professional",
            "subcategory":"Accounting & Tax Preparation",
            "type":"Services"
        }
    ],
    "sg:phone":"+61 7 4151 1049",
    "sg:postcode":"4670",
    "sg:province":"QLD",
    "sg:tags":[
        "accountant",
        "auditor"
    ],
    "wof:name":"Adcock Wayne J",
    "wof:placetype":"venue"
},
  "geometry": {"coordinates":[152.32955932600001,-24.8774909973],"type":"Point"}
}