{
  "type": "Feature",
  "properties": {
    "iso:country":"AU",
    "sg:address":"12 Balmain Rd",
    "sg:city":"McGraths Hill",
    "sg:classifiers":[
        {
            "category":"Real Estate",
            "subcategory":"Real Estate Operator",
            "type":"Services"
        }
    ],
    "sg:phone":"+61 407 015 489",
    "sg:postcode":"2756",
    "sg:province":"NSW",
    "sg:tags":[
        "concrete",
        "pumping"
    ],
    "wof:name":"RJ & DM Pamplin Concrete Pumping",
    "wof:placetype":"venue"
},
  "geometry": {"coordinates":[150.839019775,-33.6194877625],"type":"Point"}
}