{
  "type": "Feature",
  "properties": {
    "addr:full":"2 Kirksway Pl Battery Point TAS 7004",
    "addr:housenumber":"2",
    "addr:postcode":"7004",
    "addr:street":"Kirksway Pl",
    "iso:country":"AU",
    "sg:address":"2 Kirksway Pl",
    "sg:city":"Battery Point",
    "sg:classifiers":[
        {
            "category":"Health Services",
            "subcategory":"Doctor",
            "type":"Services"
        }
    ],
    "sg:phone":"+61 3 6224 0133",
    "sg:postcode":"7004",
    "sg:province":"TAS",
    "sg:tags":[
        "medical",
        "practitioner"
    ],
    "wof:name":"X-Ray Hobart",
    "wof:placetype":"venue"
},
  "geometry": {"coordinates":[147.33085632300001,-42.8882293701],"type":"Point"}
}