{
  "type": "Feature",
  "properties": {
    "addr:full":"73 Parramatta Rd (Cnr Trafalgar St) Annandale NSW 2038",
    "addr:housenumber":"73",
    "addr:postcode":"2038",
    "addr:street":"Parramatta Rd Cnr Trafalgar St",
    "iso:country":"AU",
    "sg:address":"73 Parramatta Rd (Cnr Trafalgar St)",
    "sg:city":"Annandale",
    "sg:classifiers":[
        {
            "category":"Autos & Motor Vehicles",
            "subcategory":"Auto Supplies",
            "type":"Retail Goods"
        }
    ],
    "sg:phone":"+61 2 9519 8487",
    "sg:postcode":"2038",
    "sg:province":"NSW",
    "sg:tags":[
        "battery",
        "automotive"
    ],
    "wof:name":"Beaurepaires",
    "wof:placetype":"venue"
},
  "geometry": {"coordinates":[151.16911315900001,-33.8876876831],"type":"Point"}
}