{
  "type": "Feature",
  "properties": {
    "addr:full":"PO Box 716 Narellan NSW 2567",
    "addr:postcode":"2567",
    "iso:country":"AU",
    "sg:address":"PO Box 716",
    "sg:city":"Narellan",
    "sg:classifiers":[
        {
            "category":"Shopping",
            "subcategory":"Baby Store",
            "type":"Retail Goods"
        }
    ],
    "sg:phone":"+61 2 4647 0055",
    "sg:postcode":"2567",
    "sg:province":"NSW",
    "sg:tags":[
        "wear"
    ],
    "wof:name":"Baby Rascals",
    "wof:placetype":"venue"
},
  "geometry": {"coordinates":[150.73526000999999,-34.0400390625],"type":"Point"}
}