{
  "type": "Feature",
  "properties": {
    "iso:country":"AU",
    "sg:address":"Cnr Prince & Woodward St 208 Woodward St",
    "sg:city":"Orange",
    "sg:classifiers":[
        {
            "category":"Fast Food",
            "type":"Food & Drink"
        }
    ],
    "sg:phone":"+61 2 6361 7844",
    "sg:postcode":"2800",
    "sg:province":"NSW",
    "sg:tags":[
        "away",
        "take"
    ],
    "wof:name":"Greengate Takeaway",
    "wof:placetype":"venue"
},
  "geometry": {"coordinates":[149.086303711,-33.2827415466],"type":"Point"}
}