{
  "type": "Feature",
  "properties": {
    "addr:full":"102A Railway Pde Kogarah NSW 2217",
    "addr:housenumber":"102a",
    "addr:postcode":"2217",
    "addr:street":"Railway Pde",
    "iso:country":"AU",
    "sg:address":"102A Railway Pde",
    "sg:city":"Kogarah",
    "sg:classifiers":[
        {
            "category":"Professional",
            "subcategory":"Accounting & Tax Preparation",
            "type":"Services"
        }
    ],
    "sg:phone":"+61 2 9587 4987",
    "sg:postcode":"2217",
    "sg:province":"NSW",
    "sg:tags":[
        "accountant",
        "auditor"
    ],
    "wof:name":"Jones Kenneth C., LLM, FCA",
    "wof:placetype":"venue"
},
  "geometry": {"coordinates":[151.13256799999999,-33.964031],"type":"Point"}
}