{
  "type": "Feature",
  "properties": {
    "iso:country":"AU",
    "sg:address":"130 Church St",
    "sg:city":"Brighton",
    "sg:classifiers":[
        {
            "category":"Restaurant",
            "type":"Food & Drink"
        }
    ],
    "sg:phone":"+61 3 9592 2979",
    "sg:postcode":"3186",
    "sg:province":"VIC",
    "wof:name":"Brighton: China",
    "wof:placetype":"venue"
},
  "geometry": {"coordinates":[144.99627685600001,-37.9157867432],"type":"Point"}
}