{
  "type": "Feature",
  "properties": {
    "addr:full":"412 Fitzgerald St North Perth WA 6006",
    "addr:housenumber":"412",
    "addr:postcode":"6006",
    "addr:street":"Fitzgerald St",
    "iso:country":"AU",
    "sg:address":"412 Fitzgerald St",
    "sg:city":"North Perth",
    "sg:classifiers":[
        {
            "category":"Communications",
            "subcategory":"Film & Video Production",
            "type":"Services"
        }
    ],
    "sg:phone":"+61 8 9328 8600",
    "sg:postcode":"6006",
    "sg:province":"WA",
    "sg:tags":[
        "dvd",
        "library"
    ],
    "wof:name":"Video Ezy",
    "wof:placetype":"venue"
},
  "geometry": {"coordinates":[115.85932922400001,-31.932302475],"type":"Point"}
}