{
  "type": "Feature",
  "properties": {
    "addr:full":"36 Mary St Dungog NSW 2420",
    "addr:housenumber":"36",
    "addr:postcode":"2420",
    "addr:street":"Mary St",
    "iso:country":"AU",
    "sg:address":"36 Mary St",
    "sg:city":"Dungog",
    "sg:classifiers":[
        {
            "category":"Commercial Area",
            "type":"Public Place"
        }
    ],
    "sg:phone":"+61 2 4992 1386",
    "sg:postcode":"2420",
    "sg:province":"NSW",
    "sg:tags":[
        "heavy",
        "carrier"
    ],
    "wof:name":"Banister B F & A E Pty Ltd",
    "wof:placetype":"venue"
},
  "geometry": {"coordinates":[151.75758400000001,-32.410389],"type":"Point"}
}