{
  "type": "Feature",
  "properties": {
    "iso:country":"AU",
    "sg:address":"Shop 16 & 17 Lillybrook SC 118 Old Gympie Rd",
    "sg:city":"Kallangur",
    "sg:classifiers":[
        {
            "category":"Food & Beverages",
            "subcategory":"Liquor & Beverages",
            "type":"Retail Goods"
        }
    ],
    "sg:phone":"+61 7 3491 7910",
    "sg:postcode":"4503",
    "sg:province":"QLD",
    "sg:tags":[
        "store"
    ],
    "wof:name":"BWS Liquor Stores",
    "wof:placetype":"venue"
},
  "geometry": {"coordinates":[152.992263794,-27.2425251007],"type":"Point"}
}