{
  "type": "Feature",
  "properties": {
    "iso:country":"AU",
    "sg:address":"461 Glympie Rd",
    "sg:city":"Kedron",
    "sg:classifiers":[
        {
            "category":"Retail",
            "subcategory":"Auto Repair",
            "type":"Services"
        }
    ],
    "sg:phone":"+61 13 19 65",
    "sg:postcode":"4031",
    "sg:province":"QLD",
    "sg:tags":[
        "muffler",
        "exhaust",
        "system"
    ],
    "wof:name":"DP Auto Parts",
    "wof:placetype":"venue"
},
  "geometry": {"coordinates":[153.03179900000001,-27.40023],"type":"Point"}
}