{
  "type": "Feature",
  "properties": {
    "addr:full":"13 Coleman Pde Syndal VIC 3149",
    "addr:housenumber":"13",
    "addr:postcode":"3149",
    "addr:street":"Coleman Pde",
    "iso:country":"AU",
    "sg:address":"13 Coleman Pde",
    "sg:city":"Syndal",
    "sg:classifiers":[
        {
            "category":"Shopping",
            "subcategory":"Music",
            "type":"Retail Goods"
        }
    ],
    "sg:phone":"+61 3 9887 9858",
    "sg:postcode":"3149",
    "sg:province":"VIC",
    "sg:tags":[
        "instrument",
        "musical"
    ],
    "wof:name":"Syndal Music",
    "wof:placetype":"venue"
},
  "geometry": {"coordinates":[145.14831543,-37.8766860962],"type":"Point"}
}