{
  "type": "Feature",
  "properties": {
    "iso:country":"AU",
    "sg:address":"Factory 3 3A Kilpa Rd",
    "sg:city":"Moorabbin",
    "sg:classifiers":[
        {
            "category":"Community Center",
            "subcategory":"Social",
            "type":"Public Place"
        }
    ],
    "sg:phone":"+61 3 9532 3166",
    "sg:postcode":"3189",
    "sg:province":"VIC",
    "sg:tags":[
        "precision",
        "grinding"
    ],
    "wof:name":"A G Grinding & Tooling Pty Ltd",
    "wof:placetype":"venue"
},
  "geometry": {"coordinates":[145.07269287099999,-37.9487838745],"type":"Point"}
}