{
  "type": "Feature",
  "properties": {
    "iso:country":"AU",
    "sg:address":"55 Coonawarra Rd",
    "sg:city":"Winnellie",
    "sg:classifiers":[
        {
            "category":"Retail",
            "subcategory":"Auto Repair",
            "type":"Services"
        }
    ],
    "sg:phone":"+61 8 8984 3922",
    "sg:postcode":"0820",
    "sg:province":"NT",
    "sg:tags":[
        "clutch",
        "brake"
    ],
    "sg:website":"http://www.cescont.com.au",
    "wof:name":"Cesco P/L",
    "wof:placetype":"venue"
},
  "geometry": {"coordinates":[130.876342773,-12.4303159714],"type":"Point"}
}