{
  "type": "Feature",
  "properties": {
    "iso:country":"AU",
    "sg:address":"9B Park St",
    "sg:city":"Peakhurst",
    "sg:classifiers":[
        {
            "category":"Health Services",
            "subcategory":"Health Practitioner",
            "type":"Services"
        }
    ],
    "sg:phone":"+61 2 9584 8485",
    "sg:postcode":"2210",
    "sg:province":"NSW",
    "sg:tags":[
        "acupuncture"
    ],
    "wof:name":"Scully Emma Jaye",
    "wof:placetype":"venue"
},
  "geometry": {"coordinates":[151.056946,-33.964066],"type":"Point"}
}