{
  "type": "Feature",
  "properties": {
    "addr:full":"Lvl 2/ 232 Victoria Pde East Melbourne VIC 3002",
    "addr:housenumber":"/ 232",
    "addr:postcode":"3002",
    "addr:street":"Victoria Pde",
    "iso:country":"AU",
    "sg:address":"Lvl 2/ 232 Victoria Pde",
    "sg:city":"East Melbourne",
    "sg:classifiers":[
        {
            "category":"Arena",
            "subcategory":"Sports Club",
            "type":"Entertainment"
        }
    ],
    "sg:phone":"+61 3 9412 4053",
    "sg:postcode":"3002",
    "sg:province":"VIC",
    "sg:tags":[
        "defence",
        "supply",
        "self",
        "instruction",
        "martial art"
    ],
    "wof:name":"Taekwondo Victoria Inc",
    "wof:placetype":"venue"
},
  "geometry": {"coordinates":[144.979858398,-37.8089332581],"type":"Point"}
}