{
  "type": "Feature",
  "properties": {
    "iso:country":"AU",
    "sg:address":"249 Rowe St",
    "sg:city":"Eastwood",
    "sg:classifiers":[
        {
            "category":"Fast Food",
            "type":"Food & Drink"
        }
    ],
    "sg:phone":"+61 2 9858 3808",
    "sg:postcode":"2122",
    "sg:province":"NSW",
    "sg:tags":[
        "away",
        "take"
    ],
    "wof:name":"Red Rooster of Eastwood",
    "wof:placetype":"venue"
},
  "geometry": {"coordinates":[151.078125,-33.7921142578],"type":"Point"}
}