{
  "type": "Feature",
  "properties": {
    "addr:full":"26- 32 Pyrmont Bridge Rd Pyrmont NSW 2009",
    "addr:housenumber":"32",
    "addr:postcode":"2009",
    "addr:street":"Pyrmont Bridge Rd",
    "iso:country":"AU",
    "sg:address":"26- 32 Pyrmont Bridge Rd",
    "sg:city":"Pyrmont",
    "sg:classifiers":[
        {
            "category":"Professional",
            "subcategory":"Art Services",
            "type":"Services"
        }
    ],
    "sg:phone":"+61 2 9562 6660",
    "sg:postcode":"2009",
    "sg:province":"NSW",
    "sg:tags":[
        "commercial",
        "artist"
    ],
    "wof:name":"Serious Business Pty Ltd",
    "wof:placetype":"venue"
},
  "geometry": {"coordinates":[151.19520568900001,-33.8708381653],"type":"Point"}
}