{
  "type": "Feature",
  "properties": {
    "addr:full":"205 Hay St Subiaco WA 6008",
    "addr:housenumber":"205",
    "addr:postcode":"6008",
    "addr:street":"Hay St",
    "iso:country":"AU",
    "sg:address":"205 Hay St",
    "sg:city":"Subiaco",
    "sg:classifiers":[
        {
            "category":"Shopping",
            "type":"Retail Goods"
        }
    ],
    "sg:phone":"+61 8 9382 3333",
    "sg:postcode":"6008",
    "sg:province":"WA",
    "sg:tags":[
        "new age",
        "product"
    ],
    "wof:name":"Crystal Universe",
    "wof:placetype":"venue"
},
  "geometry": {"coordinates":[115.831832886,-31.9472026825],"type":"Point"}
}