{
  "type": "Feature",
  "properties": {
    "addr:full":"3/2- 6 Etheridge St Eumundi QLD 4562",
    "addr:housenumber":"/ 2 6",
    "addr:postcode":"4562",
    "addr:street":"Etheridge St",
    "iso:country":"AU",
    "sg:address":"3/2- 6 Etheridge St",
    "sg:city":"Eumundi",
    "sg:classifiers":[
        {
            "category":"Health Services",
            "subcategory":"Doctor",
            "type":"Services"
        }
    ],
    "sg:phone":"+61 7 5442 7577",
    "sg:postcode":"4562",
    "sg:province":"QLD",
    "sg:tags":[
        "medical",
        "practitioner"
    ],
    "wof:name":"Eumundi Family Medical Centre",
    "wof:placetype":"venue"
},
  "geometry": {"coordinates":[152.95018005399999,-26.4759559631],"type":"Point"}
}