{
  "type": "Feature",
  "properties": {
    "iso:country":"AU",
    "sg:address":"Unit 1b, 37- 39 Douglas Mawson Rd",
    "sg:city":"Dubbo",
    "sg:classifiers":[
        {
            "category":"Wholesale",
            "subcategory":"Painting Supplies",
            "type":"Manufacturing & Wholesale Goods"
        }
    ],
    "sg:phone":"+61 2 6882 9433",
    "sg:postcode":"2830",
    "sg:province":"NSW",
    "sg:tags":[
        "product",
        "cleaning"
    ],
    "wof:name":"Cleveland Cleaning Supplies Pty Ltd",
    "wof:placetype":"venue"
},
  "geometry": {"coordinates":[148.613479614,-32.2498397827],"type":"Point"}
}