{
  "type": "Feature",
  "properties": {
    "iso:country":"AU",
    "sg:address":"Shop C31, Northland Shopping Cnt, Murray Rd",
    "sg:city":"Preston",
    "sg:classifiers":[
        {
            "category":"Shopping",
            "subcategory":"Mobile Phones",
            "type":"Retail Goods"
        }
    ],
    "sg:phone":"+61 3 9471 7099",
    "sg:postcode":"3072",
    "sg:province":"VIC",
    "sg:tags":[
        "telephone",
        "accessory"
    ],
    "wof:name":"Vodafone Northland",
    "wof:placetype":"venue"
},
  "geometry": {"coordinates":[145.009277344,-37.7384376526],"type":"Point"}
}