{
  "type": "Feature",
  "properties": {
    "addr:full":"8 Louise Ave Baulkham Hills NSW 2153",
    "addr:housenumber":"8",
    "addr:postcode":"2153",
    "addr:street":"Louise Ave",
    "iso:country":"AU",
    "sg:address":"8 Louise Ave",
    "sg:city":"Baulkham Hills",
    "sg:classifiers":[
        {
            "category":"Manufacturing",
            "subcategory":"Glass & Minerals",
            "type":"Manufacturing & Wholesale Goods"
        }
    ],
    "sg:phone":"+61 2 9686 7914",
    "sg:postcode":"2153",
    "sg:province":"NSW",
    "sg:tags":[
        "case",
        "counter",
        "show"
    ],
    "wof:name":"Project Pac",
    "wof:placetype":"venue"
},
  "geometry": {"coordinates":[150.97787475600001,-33.7571525574],"type":"Point"}
}