{
  "type": "Feature",
  "properties": {
    "addr:full":"32 Cheviot St Dianella WA 6059",
    "addr:housenumber":"32",
    "addr:postcode":"6059",
    "addr:street":"Cheviot St",
    "iso:country":"AU",
    "sg:address":"32 Cheviot St",
    "sg:city":"Dianella",
    "sg:classifiers":[
        {
            "category":"Professional",
            "subcategory":"Computer Services",
            "type":"Services"
        }
    ],
    "sg:phone":"+61 419 908 788",
    "sg:postcode":"6059",
    "sg:province":"WA",
    "sg:tags":[
        "consultant",
        "system"
    ],
    "wof:name":"Beyond Software Solutions",
    "wof:placetype":"venue"
},
  "geometry": {"coordinates":[115.884376526,-31.8847103119],"type":"Point"}
}