{
  "type": "Feature",
  "properties": {
    "iso:country":"AU",
    "sg:address":"PO Box 234",
    "sg:city":"Cooranbong",
    "sg:classifiers":[
        {
            "category":"Building & Trades",
            "subcategory":"Construction",
            "type":"Services"
        }
    ],
    "sg:phone":"+61 2 4977 1280",
    "sg:postcode":"2265",
    "sg:province":"NSW",
    "sg:tags":[
        "pool",
        "swimming"
    ],
    "wof:name":"Power Pebblecrete",
    "wof:placetype":"venue"
},
  "geometry": {"coordinates":[151.467621,-33.06699],"type":"Point"}
}