{
  "type": "Feature",
  "properties": {
    "addr:full":"46 Barnes St Tamworth NSW 2340",
    "addr:housenumber":"46",
    "addr:postcode":"2340",
    "addr:street":"Barnes St",
    "iso:country":"AU",
    "sg:address":"46 Barnes St",
    "sg:city":"Tamworth",
    "sg:classifiers":[
        {
            "category":"Manufacturing",
            "subcategory":"Electronics",
            "type":"Manufacturing & Wholesale Goods"
        }
    ],
    "sg:phone":"+61 2 6765 4706",
    "sg:postcode":"2340",
    "sg:province":"NSW",
    "sg:tags":[
        "wholesaler",
        "equipment",
        "part",
        "mfrs",
        "refrigeration"
    ],
    "wof:name":"RES Refrigeration Equipment Sales",
    "wof:placetype":"venue"
},
  "geometry": {"coordinates":[150.91252136200001,-31.0913009644],"type":"Point"}
}