{
  "type": "Feature",
  "properties": {
    "iso:country":"AU",
    "sg:address":"75 Sullivans Rd",
    "sg:city":"Yamba",
    "sg:classifiers":[
        {
            "category":"Building & Trades",
            "subcategory":"Plumbing",
            "type":"Services"
        }
    ],
    "sg:phone":"+61 417 755 689",
    "sg:postcode":"2464",
    "sg:province":"NSW",
    "sg:tags":[
        "plumber",
        "gasfitters"
    ],
    "wof:name":"A Plumber In Yamba",
    "wof:placetype":"venue"
},
  "geometry": {"coordinates":[153.335205078,-29.4474868774],"type":"Point"}
}