{
  "type": "Feature",
  "properties": {
    "addr:full":"n/a St Albans VIC 3021",
    "addr:housenumber":"n / a",
    "addr:postcode":"3021",
    "iso:country":"AU",
    "sg:address":"n/a",
    "sg:city":"St Albans",
    "sg:classifiers":[
        {
            "category":"Building & Trades",
            "subcategory":"Construction",
            "type":"Services"
        }
    ],
    "sg:phone":"+61 3 9369 1392",
    "sg:postcode":"3021",
    "sg:province":"VIC",
    "sg:tags":[
        "contractor"
    ],
    "wof:name":"Marty's Maintenance Services",
    "wof:placetype":"venue"
},
  "geometry": {"coordinates":[144.800217,-37.744259],"type":"Point"}
}