{
  "type": "Feature",
  "properties": {
    "iso:country":"AU",
    "sg:address":"360 Norton St",
    "sg:city":"Leichhardt",
    "sg:classifiers":[
        {
            "category":"Professional",
            "subcategory":"Accounting & Tax Preparation",
            "type":"Services"
        }
    ],
    "sg:phone":"+61 2 9564 0375",
    "sg:postcode":"2040",
    "sg:province":"NSW",
    "sg:tags":[
        "accountant",
        "auditor"
    ],
    "wof:name":"Christian Fox",
    "wof:placetype":"venue"
},
  "geometry": {"coordinates":[151.155884,-33.874683],"type":"Point"}
}