{
  "type": "Feature",
  "properties": {
    "iso:country":"AU",
    "sg:address":"40 Cranwell St",
    "sg:city":"Braybrook",
    "sg:classifiers":[
        {
            "category":"Shopping",
            "subcategory":"Antiques",
            "type":"Retail Goods"
        }
    ],
    "sg:phone":"+61 3 9318 1276",
    "sg:postcode":"3019",
    "sg:province":"VIC",
    "sg:tags":[
        "collectable",
        "memorabilia"
    ],
    "wof:name":"Collectors Aircraft Models Australia Pty Ltd",
    "wof:placetype":"venue"
},
  "geometry": {"coordinates":[144.86190795900001,-37.7785224915],"type":"Point"}
}