{
  "type": "Feature",
  "properties": {
    "addr:full":"202 Belair Rd Hawthorn SA 5062",
    "addr:housenumber":"202",
    "addr:postcode":"5062",
    "addr:street":"Belair Rd",
    "iso:country":"AU",
    "sg:address":"202 Belair Rd",
    "sg:city":"Hawthorn",
    "sg:classifiers":[
        {
            "category":"Retail",
            "subcategory":"Self-service Laundry",
            "type":"Services"
        }
    ],
    "sg:phone":"+61 8 8373 1433",
    "sg:postcode":"5062",
    "sg:province":"SA",
    "wof:name":"Mitcham Supawash",
    "wof:placetype":"venue"
},
  "geometry": {"coordinates":[138.60896301299999,-34.971988678],"type":"Point"}
}