{
  "type": "Feature",
  "properties": {
    "iso:country":"AU",
    "sg:address":"19 Bellevale Crt",
    "sg:city":"Mt Gambier",
    "sg:classifiers":[
        {
            "category":"Building & Trades",
            "subcategory":"Construction",
            "type":"Services"
        }
    ],
    "sg:phone":"+61 429 840 578",
    "sg:postcode":"5290",
    "sg:province":"SA",
    "sg:tags":[
        "contractor"
    ],
    "wof:name":"S K Homes",
    "wof:placetype":"venue"
},
  "geometry": {"coordinates":[140.797836,-37.825169],"type":"Point"}
}