{
  "type": "Feature",
  "properties": {
    "addr:full":"Suite 2, 126 Margaret St Toowoomba QLD 4350",
    "addr:housenumber":"126",
    "addr:postcode":"4350",
    "addr:street":"Margaret St",
    "iso:country":"AU",
    "sg:address":"Suite 2, 126 Margaret St",
    "sg:city":"Toowoomba",
    "sg:classifiers":[
        {
            "category":"Health Services",
            "subcategory":"Health Practitioner",
            "type":"Services"
        }
    ],
    "sg:phone":"+61 7 4639 4996",
    "sg:postcode":"4350",
    "sg:province":"QLD",
    "sg:tags":[
        "acupuncture"
    ],
    "wof:name":"Ming Rui Traditional Chinese Medicine Toowoomba",
    "wof:placetype":"venue"
},
  "geometry": {"coordinates":[151.95469700000001,-27.561031],"type":"Point"}
}