{
  "type": "Feature",
  "properties": {
    "iso:country":"AU",
    "sg:address":"Brimbank Central Shop Cntr Cnr Neale & Station Rds",
    "sg:city":"Deer Park",
    "sg:classifiers":[
        {
            "category":"Cafe",
            "type":"Food & Drink"
        }
    ],
    "sg:phone":"+61 3 8390 2235",
    "sg:postcode":"3023",
    "sg:province":"VIC",
    "wof:name":"Starbucks Coffee Company (Australia) Pty Ltd",
    "wof:placetype":"venue"
},
  "geometry": {"coordinates":[144.776657,-37.752533],"type":"Point"}
}