{
  "type": "Feature",
  "properties": {
    "addr:full":"85 Coombes Rd Torquay VIC 3228",
    "addr:housenumber":"85",
    "addr:postcode":"3228",
    "addr:street":"Coombes Rd",
    "iso:country":"AU",
    "sg:address":"85 Coombes Rd",
    "sg:city":"Torquay",
    "sg:classifiers":[
        {
            "category":"Retail",
            "subcategory":"Veterinary Services",
            "type":"Services"
        }
    ],
    "sg:phone":"+61 428 393 465",
    "sg:postcode":"3228",
    "sg:province":"VIC",
    "sg:tags":[
        "surgeon"
    ],
    "wof:name":"Mobile Veterinary Service",
    "wof:placetype":"venue"
},
  "geometry": {"coordinates":[144.30534399999999,-38.313362],"type":"Point"}
}