{
  "type": "Feature",
  "properties": {
    "addr:full":"259 Main St Osborne Park WA 6017",
    "addr:housenumber":"259",
    "addr:postcode":"6017",
    "addr:street":"Main St",
    "iso:country":"AU",
    "sg:address":"259 Main St",
    "sg:city":"Osborne Park",
    "sg:classifiers":[
        {
            "category":"Health Services",
            "subcategory":"Dentist",
            "type":"Services"
        }
    ],
    "sg:phone":"+61 8 9344 5522",
    "sg:postcode":"6017",
    "sg:province":"WA",
    "wof:name":"Tan Felix E.L.",
    "wof:placetype":"venue"
},
  "geometry": {"coordinates":[115.82814025899999,-31.8926029205],"type":"Point"}
}