{
  "type": "Feature",
  "properties": {
    "iso:country":"AU",
    "sg:address":"44 Brickwood St",
    "sg:city":"Gardenvale",
    "sg:classifiers":[
        {
            "category":"Building & Trades",
            "subcategory":"Construction",
            "type":"Services"
        }
    ],
    "sg:phone":"+61 3 9596 5784",
    "sg:postcode":"3185",
    "sg:province":"VIC",
    "sg:tags":[
        "fencing",
        "contractor"
    ],
    "wof:name":"Weassbacher Nominees Pty Ltd",
    "wof:placetype":"venue"
},
  "geometry": {"coordinates":[144.99864196799999,-37.8911247253],"type":"Point"}
}