{
  "type": "Feature",
  "properties": {
    "addr:full":"493 Hammond Rd Dandenong VIC 3175",
    "addr:housenumber":"493",
    "addr:postcode":"3175",
    "addr:street":"Hammond Rd",
    "iso:country":"AU",
    "sg:address":"493 Hammond Rd",
    "sg:city":"Dandenong",
    "sg:classifiers":[
        {
            "category":"Building & Trades",
            "subcategory":"Equipment Rental",
            "type":"Services"
        }
    ],
    "sg:phone":"+61 3 9768 3738",
    "sg:postcode":"3175",
    "sg:province":"VIC",
    "sg:tags":[
        "party",
        "hire"
    ],
    "wof:name":"A Quality Event Hire Pty Ltd",
    "wof:placetype":"venue"
},
  "geometry": {"coordinates":[145.20216369600001,-38.0324516296],"type":"Point"}
}