{
  "type": "Feature",
  "properties": {
    "addr:full":"62 Victoria St Mackay QLD 4740",
    "addr:housenumber":"62",
    "addr:postcode":"4740",
    "addr:street":"Victoria St",
    "iso:country":"AU",
    "sg:address":"62 Victoria St",
    "sg:city":"Mackay",
    "sg:classifiers":[
        {
            "category":"Organizations",
            "subcategory":"Non-profit Organization",
            "type":"Services"
        }
    ],
    "sg:phone":"+61 7 4953 2292",
    "sg:postcode":"4740",
    "sg:province":"QLD",
    "sg:tags":[
        "support",
        "disability",
        "organisation"
    ],
    "wof:name":"Pioneer Employment Service",
    "wof:placetype":"venue"
},
  "geometry": {"coordinates":[149.188232,-21.141336],"type":"Point"}
}