{
  "type": "Feature",
  "properties": {
    "addr:full":"122 Edinborough St Mt Hawthorn WA 6016",
    "addr:housenumber":"122",
    "addr:postcode":"6016",
    "addr:street":"Edinborough St Mt",
    "iso:country":"AU",
    "sg:address":"122 Edinborough St",
    "sg:city":"Mt Hawthorn",
    "sg:classifiers":[
        {
            "category":"Travel",
            "subcategory":"Travel Agent",
            "type":"Entertainment"
        }
    ],
    "sg:phone":"+61 418 950 607",
    "sg:postcode":"6016",
    "sg:province":"WA",
    "sg:tags":[
        "consultant"
    ],
    "wof:name":"Lemnell Carl H",
    "wof:placetype":"venue"
},
  "geometry": {"coordinates":[115.837333679,-31.9206905365],"type":"Point"}
}