{
  "type": "Feature",
  "properties": {
    "iso:country":"AU",
    "sg:address":"5 Fifeshire Rd",
    "sg:city":"Goodhope",
    "sg:classifiers":[
        {
            "category":"Utilities",
            "subcategory":"Electric",
            "type":"Services"
        }
    ],
    "sg:phone":"+61 407 948 898",
    "sg:postcode":"2582",
    "sg:province":"NSW",
    "sg:tags":[
        "electrical",
        "contractor"
    ],
    "wof:name":"John Pethybridge Electrical",
    "wof:placetype":"venue"
},
  "geometry": {"coordinates":[148.803497314,-34.9184875488],"type":"Point"}
}