{
  "type": "Feature",
  "properties": {
    "iso:country":"AU",
    "sg:address":"2 Azalea Crt",
    "sg:city":"Kyabram",
    "sg:classifiers":[
        {
            "category":"Farming",
            "subcategory":"Farm & Veterinary Services",
            "type":"Manufacturing & Wholesale Goods"
        }
    ],
    "sg:phone":"+61 3 5852 3429",
    "sg:postcode":"3619",
    "sg:province":"VIC",
    "sg:tags":[
        "agricultural",
        "advisory"
    ],
    "wof:name":"Farmanco Pty Ltd",
    "wof:placetype":"venue"
},
  "geometry": {"coordinates":[145.03779602,-36.3201713562],"type":"Point"}
}