{
  "type": "Feature",
  "properties": {
    "addr:full":"Shop 2 Links Rd North Lakes Shopping Centre Marrara NT 0812",
    "addr:housenumber":"shop 2",
    "addr:postcode":"nt 0812",
    "addr:street":"Links Rd",
    "iso:country":"AU",
    "sg:address":"Shop 2 Links Rd North Lakes Shopping Centre",
    "sg:city":"Marrara",
    "sg:classifiers":[
        {
            "category":"Personal",
            "subcategory":"Beauty Salon",
            "type":"Services"
        }
    ],
    "sg:phone":"+61 8 8945 9471",
    "sg:postcode":"0812",
    "sg:province":"NT",
    "wof:name":"Carmen's Nails",
    "wof:placetype":"venue"
},
  "geometry": {"coordinates":[130.89711,-12.396231],"type":"Point"}
}