{
  "type": "Feature",
  "properties": {
    "addr:full":"240 South Boundary East Rd Pearcedale VIC 3912",
    "addr:housenumber":"240",
    "addr:postcode":"3912",
    "addr:street":"South Boundary East Rd",
    "iso:country":"AU",
    "sg:address":"240 South Boundary East Rd",
    "sg:city":"Pearcedale",
    "sg:classifiers":[
        {
            "category":"Farming",
            "subcategory":"Livestock Farm",
            "type":"Manufacturing & Wholesale Goods"
        }
    ],
    "sg:phone":"+61 3 5978 6856",
    "sg:postcode":"3912",
    "sg:province":"VIC",
    "sg:tags":[
        "agistment"
    ],
    "wof:name":"Peninsula Equestrian Centre",
    "wof:placetype":"venue"
},
  "geometry": {"coordinates":[145.24232482900001,-38.2139778137],"type":"Point"}
}