{
  "type": "Feature",
  "properties": {
    "addr:full":"53 Market St Fremantle WA 6160",
    "addr:housenumber":"53",
    "addr:postcode":"6160",
    "addr:street":"Market St",
    "iso:country":"AU",
    "sg:address":"53 Market St",
    "sg:city":"Fremantle",
    "sg:classifiers":[
        {
            "category":"Travel",
            "subcategory":"Travel Agent",
            "type":"Entertainment"
        }
    ],
    "sg:phone":"+61 8 9430 5553",
    "sg:postcode":"6160",
    "sg:province":"WA",
    "sg:tags":[
        "consultant"
    ],
    "wof:name":"STA Travel",
    "wof:placetype":"venue"
},
  "geometry": {"coordinates":[115.746246,-32.054348],"type":"Point"}
}