{
  "type": "Feature",
  "properties": {
    "addr:full":"3 Bramble St Ridgeway TAS 7054",
    "addr:housenumber":"3",
    "addr:postcode":"7054",
    "addr:street":"Bramble St",
    "iso:country":"AU",
    "sg:address":"3 Bramble St",
    "sg:city":"Ridgeway",
    "sg:classifiers":[
        {
            "category":"Shopping",
            "subcategory":"Musical Instruments",
            "type":"Retail Goods"
        }
    ],
    "sg:phone":"+61 3 6239 1495",
    "sg:postcode":"7054",
    "sg:province":"TAS",
    "sg:tags":[
        "musician",
        "agent"
    ],
    "wof:name":"Steptoe Bush Band",
    "wof:placetype":"venue"
},
  "geometry": {"coordinates":[147.29037500000001,-42.926441],"type":"Point"}
}