{
  "type": "Feature",
  "properties": {
    "iso:country":"AU",
    "sg:address":"187 High St",
    "sg:city":"East Maitland",
    "sg:classifiers":[
        {
            "category":"Building & Trades",
            "subcategory":"Landscaping Services",
            "type":"Services"
        }
    ],
    "sg:phone":"+61 2 4933 5575",
    "sg:postcode":"2323",
    "sg:province":"NSW",
    "sg:tags":[
        "architect",
        "landscape"
    ],
    "wof:name":"Wendfrey Gardens",
    "wof:placetype":"venue"
},
  "geometry": {"coordinates":[151.58335876500001,-32.7549438477],"type":"Point"}
}