{
  "type": "Feature",
  "properties": {
    "addr:full":"Shp 3/ 2 Burrum Heads Rd Burrum Heads QLD 4659",
    "addr:housenumber":"/ 2",
    "addr:postcode":"4659",
    "addr:street":"Burrum Heads Rd",
    "iso:country":"AU",
    "sg:address":"Shp 3/ 2 Burrum Heads Rd",
    "sg:city":"Burrum Heads",
    "sg:classifiers":[
        {
            "category":"Food & Beverages",
            "subcategory":"Meat & Fish",
            "type":"Retail Goods"
        }
    ],
    "sg:phone":"+61 7 4129 5809",
    "sg:postcode":"4659",
    "sg:province":"QLD",
    "sg:tags":[
        "seafood"
    ],
    "wof:name":"Simpsons Seafood",
    "wof:placetype":"venue"
},
  "geometry": {"coordinates":[152.61158800000001,-25.189762],"type":"Point"}
}