{
  "type": "Feature",
  "properties": {
    "iso:country":"AU",
    "sg:address":"66 Chameleon Drv",
    "sg:city":"Erskine Park",
    "sg:classifiers":[
        {
            "category":"Building & Trades",
            "subcategory":"Landscaping Services",
            "type":"Services"
        }
    ],
    "sg:phone":"+61 424 659 434",
    "sg:postcode":"2759",
    "sg:province":"NSW",
    "sg:tags":[
        "gardener"
    ],
    "wof:name":"Chameleon Garden Care",
    "wof:placetype":"venue"
},
  "geometry": {"coordinates":[150.79124450699999,-33.8103027344],"type":"Point"}
}