{
  "type": "Feature",
  "properties": {
    "addr:full":"L1/Toukley Mall 227 Main Rd Toukley NSW 2263",
    "addr:housenumber":"l1;toukley;227",
    "addr:postcode":"2263",
    "addr:street":"Main Rd",
    "iso:country":"AU",
    "sg:address":"L1/Toukley Mall 227 Main Rd",
    "sg:city":"Toukley",
    "sg:classifiers":[
        {
            "category":"Sports & Exercise",
            "subcategory":"Gym",
            "type":"Entertainment"
        }
    ],
    "sg:phone":"+61 2 4397 2881",
    "sg:postcode":"2263",
    "sg:province":"NSW",
    "sg:tags":[
        "health",
        "fitness"
    ],
    "wof:name":"Curves",
    "wof:placetype":"venue"
},
  "geometry": {"coordinates":[151.544983,-33.264496],"type":"Point"}
}