{
  "type": "Feature",
  "properties": {
    "addr:full":"Shop 235 Westfield Shoppingtown Anderson St Chatswood NSW 2057",
    "addr:housenumber":"235",
    "addr:postcode":"2057",
    "addr:street":"Westfield Shoppingtown Anderson St",
    "iso:country":"AU",
    "sg:address":"Shop 235 Westfield Shoppingtown Anderson St",
    "sg:city":"Chatswood",
    "sg:classifiers":[
        {
            "category":"Insurance",
            "subcategory":"Health Insurance",
            "type":"Services"
        }
    ],
    "sg:phone":"+61 13 14 63",
    "sg:postcode":"2057",
    "sg:province":"NSW",
    "wof:name":"NIB Health Funds Limited",
    "wof:placetype":"venue"
},
  "geometry": {"coordinates":[151.18533300000001,-33.79562],"type":"Point"}
}