{
  "type": "Feature",
  "properties": {
    "addr:full":"80 Lannercost St Ingham QLD 4850",
    "addr:housenumber":"80",
    "addr:postcode":"4850",
    "addr:street":"Lannercost St",
    "iso:country":"AU",
    "sg:address":"80 Lannercost St",
    "sg:city":"Ingham",
    "sg:classifiers":[
        {
            "category":"Shopping",
            "subcategory":"Clothing, Apparel, & Fashions",
            "type":"Retail Goods"
        }
    ],
    "sg:phone":"+61 7 4776 1740",
    "sg:postcode":"4850",
    "sg:province":"QLD",
    "sg:tags":[
        "jean"
    ],
    "wof:name":"Let It Be Blues",
    "wof:placetype":"venue"
},
  "geometry": {"coordinates":[146.153564453,-18.6501026154],"type":"Point"}
}