{
  "type": "Feature",
  "properties": {
    "iso:country":"AU",
    "sg:address":"PO Box 4244",
    "sg:city":"Raceview",
    "sg:classifiers":[
        {
            "category":"Building & Trades",
            "subcategory":"Landscaping Services",
            "type":"Services"
        }
    ],
    "sg:phone":"+61 1300 734 996",
    "sg:postcode":"4305",
    "sg:province":"QLD",
    "sg:tags":[
        "fertilizer",
        "spreading",
        "insecticide"
    ],
    "wof:name":"Supagreen Lawn Programmes",
    "wof:placetype":"venue"
},
  "geometry": {"coordinates":[152.786834717,-27.6423206329],"type":"Point"}
}