{
  "type": "Feature",
  "properties": {
    "addr:full":"16 Abaxas Crt Aberfoyle Park SA 5159",
    "addr:housenumber":"16",
    "addr:postcode":"5159",
    "addr:street":"Abaxas Crt",
    "iso:country":"AU",
    "sg:address":"16 Abaxas Crt",
    "sg:city":"Aberfoyle Park",
    "sg:classifiers":[
        {
            "category":"Wholesale",
            "subcategory":"Machinery & Supplies",
            "type":"Manufacturing & Wholesale Goods"
        }
    ],
    "sg:phone":"+61 8 8322 6600",
    "sg:postcode":"5159",
    "sg:province":"SA",
    "sg:tags":[
        "process",
        "instrument",
        "control"
    ],
    "wof:name":"Tayton Controls",
    "wof:placetype":"venue"
},
  "geometry": {"coordinates":[138.58552551299999,-35.0795898438],"type":"Point"}
}