{
  "type": "Feature",
  "properties": {
    "iso:country":"AU",
    "sg:address":"72 Cutter St",
    "sg:city":"Richmond",
    "sg:classifiers":[
        {
            "category":"Professional",
            "subcategory":"Computer Services",
            "type":"Services"
        }
    ],
    "sg:phone":"+61 412 494 215",
    "sg:postcode":"3121",
    "sg:province":"VIC",
    "sg:tags":[
        "consultant",
        "system"
    ],
    "wof:name":"AAA Computer Consultants",
    "wof:placetype":"venue"
},
  "geometry": {"coordinates":[145.00823974599999,-37.8259963989],"type":"Point"}
}