{
  "type": "Feature",
  "properties": {
    "addr:full":"137 Lake St Cairns QLD 4870",
    "addr:housenumber":"137",
    "addr:postcode":"4870",
    "addr:street":"Lake St",
    "iso:country":"AU",
    "sg:address":"137 Lake St",
    "sg:city":"Cairns",
    "sg:classifiers":[
        {
            "category":"Retail",
            "subcategory":"Auto Rental",
            "type":"Services"
        }
    ],
    "sg:phone":"+61 7 4051 6077",
    "sg:postcode":"4870",
    "sg:province":"QLD",
    "sg:tags":[
        "bus",
        "truck"
    ],
    "wof:name":"Cairns Autorent",
    "wof:placetype":"venue"
},
  "geometry": {"coordinates":[145.77401733400001,-16.9201774597],"type":"Point"}
}