{
  "type": "Feature",
  "properties": {
    "addr:full":"Shop15/ 1 Nanda St Marmong Point NSW 2284",
    "addr:housenumber":"1",
    "addr:postcode":"2284",
    "addr:street":"Nanda St",
    "iso:country":"AU",
    "sg:address":"Shop15/ 1 Nanda St",
    "sg:city":"Marmong Point",
    "sg:classifiers":[
        {
            "category":"Cafe",
            "type":"Food & Drink"
        }
    ],
    "sg:phone":"+61 2 4965 8157",
    "sg:postcode":"2284",
    "sg:province":"NSW",
    "wof:name":"The Point Cafe",
    "wof:placetype":"venue"
},
  "geometry": {"coordinates":[151.619049072,-32.9781074524],"type":"Point"}
}