{
  "type": "Feature",
  "properties": {
    "addr:full":"Unit 4/ 60 Queen St Moruya NSW 2537",
    "addr:housenumber":"60",
    "addr:postcode":"2537",
    "addr:street":"Queen St",
    "iso:country":"AU",
    "sg:address":"Unit 4/ 60 Queen St",
    "sg:city":"Moruya",
    "sg:classifiers":[
        {
            "category":"Shopping",
            "subcategory":"Music",
            "type":"Retail Goods"
        }
    ],
    "sg:phone":"+61 2 4474 5000",
    "sg:postcode":"2537",
    "sg:province":"NSW",
    "sg:tags":[
        "instrument",
        "musical"
    ],
    "wof:name":"Planet TX-Music Store & Promotions",
    "wof:placetype":"venue"
},
  "geometry": {"coordinates":[150.080978394,-35.910068512],"type":"Point"}
}