{
  "type": "Feature",
  "properties": {
    "iso:country":"AU",
    "sg:address":"1252 Old Cleveland Rd",
    "sg:city":"Belmont",
    "sg:classifiers":[
        {
            "category":"Food & Beverages",
            "subcategory":"Bakery",
            "type":"Retail Goods"
        }
    ],
    "sg:phone":"+61 7 3395 3317",
    "sg:postcode":"4153",
    "sg:province":"QLD",
    "sg:tags":[
        "cake",
        "shop",
        "pastry"
    ],
    "wof:name":"K P Gourmet Bakery",
    "wof:placetype":"venue"
},
  "geometry": {"coordinates":[153.12562560999999,-27.503074646],"type":"Point"}
}