{
  "type": "Feature",
  "properties": {
    "addr:full":"Illawarra Crs South Ballajura WA 6066",
    "addr:postcode":"6066",
    "addr:street":"Illawarra Crs South",
    "iso:country":"AU",
    "sg:address":"Illawarra Crs South",
    "sg:city":"Ballajura",
    "sg:classifiers":[
        {
            "category":"Education",
            "subcategory":"School",
            "type":"Public Place"
        }
    ],
    "sg:phone":"+61 8 9262 7777",
    "sg:postcode":"6066",
    "sg:province":"WA",
    "sg:tags":[
        "state",
        "except",
        "nsw"
    ],
    "wof:name":"Ballajura Community College",
    "wof:placetype":"venue"
},
  "geometry": {"coordinates":[116.125228882,-32.0877494812],"type":"Point"}
}