{
  "type": "Feature",
  "properties": {
    "iso:country":"AU",
    "sg:address":"Rockvale Rd",
    "sg:city":"Armidale",
    "sg:classifiers":[
        {
            "category":"Building & Trades",
            "subcategory":"Landscaping Services",
            "type":"Services"
        }
    ],
    "sg:phone":"+61 2 6772 3031",
    "sg:postcode":"2350",
    "sg:province":"NSW",
    "sg:tags":[
        "grazier"
    ],
    "wof:name":"Gates A R & J",
    "wof:placetype":"venue"
},
  "geometry": {"coordinates":[151.67347717300001,-30.5023727417],"type":"Point"}
}