{
  "type": "Feature",
  "properties": {
    "addr:full":"188 Middle St Cleveland QLD 4163",
    "addr:housenumber":"188",
    "addr:postcode":"4163",
    "addr:street":"Middle St",
    "iso:country":"AU",
    "sg:address":"188 Middle St",
    "sg:city":"Cleveland",
    "sg:classifiers":[
        {
            "category":"Retail",
            "subcategory":"Auto Repair",
            "type":"Services"
        }
    ],
    "sg:phone":"+61 7 3286 2135",
    "sg:postcode":"4163",
    "sg:province":"QLD",
    "sg:tags":[
        "repairer",
        "motor",
        "engineer"
    ],
    "wof:name":"Millers Garage",
    "wof:placetype":"venue"
},
  "geometry": {"coordinates":[153.27700805699999,-27.5262126923],"type":"Point"}
}