{
  "type": "Feature",
  "properties": {
    "iso:country":"AU",
    "sg:address":"8 Warby St",
    "sg:city":"Campbelltown",
    "sg:classifiers":[
        {
            "category":"Health Services",
            "subcategory":"Health Practitioner",
            "type":"Services"
        }
    ],
    "sg:phone":"+61 2 4625 5447",
    "sg:postcode":"2560",
    "sg:province":"NSW",
    "sg:tags":[
        "physiotherapist"
    ],
    "sg:website":"http://www.dellem.com.au",
    "wof:name":"Warby St Physiotherapy, Hydrotherapy & Spinal Injuries Centre",
    "wof:placetype":"venue"
},
  "geometry": {"coordinates":[150.81990051299999,-34.0613708496],"type":"Point"}
}