{
  "type": "Feature",
  "properties": {
    "iso:country":"AU",
    "sg:address":"Cnr Springvale Rd & Coleham Pde",
    "sg:city":"Glen Waverley",
    "sg:classifiers":[
        {
            "category":"Food & Beverages",
            "subcategory":"Groceries & Convenience Stores",
            "type":"Retail Goods"
        }
    ],
    "sg:phone":"+61 3 9560 8426",
    "sg:postcode":"3150",
    "sg:province":"VIC",
    "wof:name":"Double &#039;M&#039; Convenience Stores",
    "wof:placetype":"venue"
},
  "geometry": {"coordinates":[145.16513061500001,-37.8829498291],"type":"Point"}
}