{
  "type": "Feature",
  "properties": {
    "addr:full":"Kin Kora Centre, Philip St Gladstone QLD 4680",
    "addr:postcode":"4680",
    "addr:street":"Philip St",
    "iso:country":"AU",
    "sg:address":"Kin Kora Centre, Philip St",
    "sg:city":"Gladstone",
    "sg:classifiers":[
        {
            "category":"Shopping",
            "subcategory":"Mobile Phones",
            "type":"Retail Goods"
        }
    ],
    "sg:phone":"+61 7 4978 4311",
    "sg:postcode":"4680",
    "sg:province":"QLD",
    "sg:tags":[
        "telephone",
        "accessory"
    ],
    "wof:name":"Fone Zone",
    "wof:placetype":"venue"
},
  "geometry": {"coordinates":[151.248413086,-23.8713226318],"type":"Point"}
}