{
  "type": "Feature",
  "properties": {
    "addr:full":"551 Whitehorse Rd Mitcham VIC 3132",
    "addr:housenumber":"551",
    "addr:postcode":"3132",
    "addr:street":"Whitehorse Rd",
    "iso:country":"AU",
    "sg:address":"551 Whitehorse Rd",
    "sg:city":"Mitcham",
    "sg:classifiers":[
        {
            "category":"Shopping",
            "subcategory":"Bridal",
            "type":"Retail Goods"
        }
    ],
    "sg:phone":"+61 3 9874 8333",
    "sg:postcode":"3132",
    "sg:province":"VIC",
    "sg:tags":[
        "hire",
        "wear"
    ],
    "wof:name":"Ferrari Bridal",
    "wof:placetype":"venue"
},
  "geometry": {"coordinates":[145.19581604000001,-37.8157043457],"type":"Point"}
}