{
  "type": "Feature",
  "properties": {
    "addr:full":"48 Arabella St Longueville NSW 2066",
    "addr:housenumber":"48",
    "addr:postcode":"2066",
    "addr:street":"Arabella St",
    "iso:country":"AU",
    "sg:address":"48 Arabella St",
    "sg:city":"Longueville",
    "sg:classifiers":[
        {
            "category":"Health Services",
            "subcategory":"Doctor",
            "type":"Services"
        }
    ],
    "sg:phone":"+61 2 9427 8876",
    "sg:postcode":"2066",
    "sg:province":"NSW",
    "sg:tags":[
        "medical",
        "practitioner"
    ],
    "wof:name":"Lake Max Dr",
    "wof:placetype":"venue"
},
  "geometry": {"coordinates":[151.17175293,-33.8278694153],"type":"Point"}
}