{
  "type": "Feature",
  "properties": {
    "addr:full":"Cook Pde Lemon Tree Passage NSW 2319",
    "addr:postcode":"2319",
    "addr:street":"Cook Pde",
    "iso:country":"AU",
    "sg:address":"Cook Pde",
    "sg:city":"Lemon Tree Passage",
    "sg:classifiers":[
        {
            "category":"Real Estate",
            "subcategory":"Developer",
            "type":"Services"
        }
    ],
    "sg:phone":"+61 2 4982 4040",
    "sg:postcode":"2319",
    "sg:province":"NSW",
    "sg:tags":[
        "chartering",
        "ship",
        "broker"
    ],
    "wof:name":"Mike Colecliffe Marine",
    "wof:placetype":"venue"
},
  "geometry": {"coordinates":[152.03723099999999,-32.728466],"type":"Point"}
}