{
  "type": "Feature",
  "properties": {
    "addr:full":"PO Box 74 Mordialloc VIC 3195",
    "addr:postcode":"3195",
    "iso:country":"AU",
    "sg:address":"PO Box 74",
    "sg:city":"Mordialloc",
    "sg:classifiers":[
        {
            "category":"Real Estate",
            "subcategory":"Real Estate Agent",
            "type":"Services"
        }
    ],
    "sg:phone":"+61 3 9580 5470",
    "sg:postcode":"3195",
    "sg:province":"VIC",
    "sg:tags":[
        "handyman's",
        "equipment",
        "hire",
        "builders",
        "contractor"
    ],
    "wof:name":"Epsom Hire Services",
    "wof:placetype":"venue"
},
  "geometry": {"coordinates":[145.09371948200001,-38.0011711121],"type":"Point"}
}