{
  "type": "Feature",
  "properties": {
    "addr:full":"Astley Centre Cnr G W Hwy & Mamre Rd St Marys NSW 2760",
    "addr:postcode":"2760",
    "addr:street":"Cnr G W Hwy & Mamre Rd",
    "iso:country":"AU",
    "sg:address":"Astley Centre Cnr G W Hwy & Mamre Rd",
    "sg:city":"St Marys",
    "sg:classifiers":[
        {
            "category":"Health Services",
            "subcategory":"Health Practitioner",
            "type":"Services"
        }
    ],
    "sg:phone":"+61 2 9623 2220",
    "sg:postcode":"2760",
    "sg:province":"NSW",
    "sg:tags":[
        "physiotherapist"
    ],
    "wof:name":"Precision Physio",
    "wof:placetype":"venue"
},
  "geometry": {"coordinates":[150.76948547399999,-33.7695007324],"type":"Point"}
}