{
  "type": "Feature",
  "properties": {
    "addr:full":"8 Hayden Pl Edensor Park NSW 2176",
    "addr:housenumber":"8",
    "addr:postcode":"2176",
    "addr:street":"Hayden Pl",
    "iso:country":"AU",
    "sg:address":"8 Hayden Pl",
    "sg:city":"Edensor Park",
    "sg:classifiers":[
        {
            "category":"Retail",
            "subcategory":"Driving School",
            "type":"Services"
        }
    ],
    "sg:phone":"+61 2 9602 1177",
    "sg:postcode":"2176",
    "sg:province":"NSW",
    "wof:name":"All Truck Driving School",
    "wof:placetype":"venue"
},
  "geometry": {"coordinates":[150.878372192,-33.8819122314],"type":"Point"}
}