{
  "type": "Feature",
  "properties": {
    "iso:country":"AU",
    "sg:address":"Unit 3/ 8 Premier St",
    "sg:city":"Bunbury",
    "sg:classifiers":[
        {
            "category":"Shopping",
            "subcategory":"Musical Instruments",
            "type":"Retail Goods"
        }
    ],
    "sg:phone":"+61 408 958 632",
    "sg:postcode":"6230",
    "sg:province":"WA",
    "sg:tags":[
        "musician",
        "agent"
    ],
    "wof:name":"Michael Cambrea",
    "wof:placetype":"venue"
},
  "geometry": {"coordinates":[115.64019,-33.343117],"type":"Point"}
}