{
  "type": "Feature",
  "properties": {
    "addr:full":"15 Gawler Rd Two Wells SA 5501",
    "addr:housenumber":"15",
    "addr:postcode":"5501",
    "addr:street":"Gawler Rd",
    "iso:country":"AU",
    "sg:address":"15 Gawler Rd",
    "sg:city":"Two Wells",
    "sg:classifiers":[
        {
            "category":"Social Services",
            "subcategory":"Child Care",
            "type":"Services"
        }
    ],
    "sg:phone":"+61 8 8520 2111",
    "sg:postcode":"5501",
    "sg:province":"SA",
    "wof:name":"Stepping Stone SA Childcare & Early Development Centres",
    "wof:placetype":"venue"
},
  "geometry": {"coordinates":[138.51686100000001,-34.59285],"type":"Point"}
}