{
  "type": "Feature",
  "properties": {
    "addr:full":"132 High St Fremantle WA 6160",
    "addr:housenumber":"132",
    "addr:postcode":"6160",
    "addr:street":"High St",
    "iso:country":"AU",
    "sg:address":"132 High St",
    "sg:city":"Fremantle",
    "sg:classifiers":[
        {
            "category":"Cafe",
            "type":"Food & Drink"
        }
    ],
    "sg:phone":"+61 8 9335 4733",
    "sg:postcode":"6160",
    "sg:province":"WA",
    "wof:name":"Noshes Lunch Bar",
    "wof:placetype":"venue"
},
  "geometry": {"coordinates":[115.74951900000001,-32.053391],"type":"Point"}
}