{
  "type": "Feature",
  "properties": {
    "addr:full":"Cnr King Albert Ave & King George St Leitchville VIC 3567",
    "addr:postcode":"3567",
    "addr:street":"Cnr King Albert Ave & King;St",
    "iso:country":"AU",
    "sg:address":"Cnr King Albert Ave & King George St",
    "sg:city":"Leitchville",
    "sg:classifiers":[
        {
            "category":"Banks & Credit Unions",
            "subcategory":"Bank",
            "type":"Services"
        }
    ],
    "sg:phone":"+61 13 20 32",
    "sg:postcode":"3567",
    "sg:province":"VIC",
    "wof:name":"Westpac",
    "wof:placetype":"venue"
},
  "geometry": {"coordinates":[144.30108642600001,-35.9039001465],"type":"Point"}
}