{
  "type": "Feature",
  "properties": {
    "iso:country":"AU",
    "sg:address":"31 Wainhouse St",
    "sg:city":"Torrensville",
    "sg:classifiers":[
        {
            "category":"Building & Trades",
            "subcategory":"Cleaning & Sanitation",
            "type":"Services"
        }
    ],
    "sg:phone":"+61 411 717 277",
    "sg:postcode":"5031",
    "sg:province":"SA",
    "sg:tags":[
        "cleaner",
        "repairer",
        "roof"
    ],
    "wof:name":"Adelaide Waterproofing Services",
    "wof:placetype":"venue"
},
  "geometry": {"coordinates":[138.56561279300001,-34.9198265076],"type":"Point"}
}