{
  "type": "Feature",
  "properties": {
    "addr:full":"Suite 1a & 1b 20 Young St Neutral Bay NSW 2089",
    "addr:housenumber":"1a & 1b 20",
    "addr:postcode":"2089",
    "addr:street":"Young St",
    "iso:country":"AU",
    "sg:address":"Suite 1a & 1b 20 Young St",
    "sg:city":"Neutral Bay",
    "sg:classifiers":[
        {
            "category":"Real Estate",
            "subcategory":"Real Estate Agent",
            "type":"Services"
        }
    ],
    "sg:phone":"+61 2 9909 0399",
    "sg:postcode":"2089",
    "sg:province":"NSW",
    "wof:name":"Laing + Simmons Residential Investment Services",
    "wof:placetype":"venue"
},
  "geometry": {"coordinates":[151.221359253,-33.8301811218],"type":"Point"}
}