{
  "type": "Feature",
  "properties": {
    "addr:full":"723 Sandgate Rd Clayfield QLD 4011",
    "addr:housenumber":"723",
    "addr:postcode":"4011",
    "addr:street":"Sandgate Rd",
    "iso:country":"AU",
    "sg:address":"723 Sandgate Rd",
    "sg:city":"Clayfield",
    "sg:classifiers":[
        {
            "category":"Health Services",
            "subcategory":"Doctor",
            "type":"Services"
        }
    ],
    "sg:phone":"+61 7 3262 2077",
    "sg:postcode":"4011",
    "sg:province":"QLD",
    "sg:tags":[
        "medical",
        "practitioner"
    ],
    "wof:name":"English Kevin P Dr",
    "wof:placetype":"venue"
},
  "geometry": {"coordinates":[153.05545000000001,-27.418661],"type":"Point"}
}