{
  "type": "Feature",
  "properties": {
    "iso:country":"AU",
    "sg:address":"Shop 4/ 99 Mooney St",
    "sg:city":"Gulliver",
    "sg:classifiers":[
        {
            "category":"Fast Food",
            "type":"Food & Drink"
        }
    ],
    "sg:phone":"+61 7 4775 2897",
    "sg:postcode":"4812",
    "sg:province":"QLD",
    "sg:tags":[
        "away",
        "take"
    ],
    "wof:name":"P.T.'s Fish & Snack Bar",
    "wof:placetype":"venue"
},
  "geometry": {"coordinates":[146.771378,-19.283386],"type":"Point"}
}