{
  "type": "Feature",
  "properties": {
    "addr:full":"Level 10, 32 Walker St North Sydney NSW 2060",
    "addr:housenumber":"32",
    "addr:postcode":"2060",
    "addr:street":"Walker St",
    "iso:country":"AU",
    "sg:address":"Level 10, 32 Walker St",
    "sg:city":"North Sydney",
    "sg:classifiers":[
        {
            "category":"Real Estate",
            "subcategory":"Real Estate Agent",
            "type":"Services"
        }
    ],
    "sg:phone":"+61 2 9954 3333",
    "sg:postcode":"2060",
    "sg:province":"NSW",
    "wof:name":"CB Richard Ellis Pty Ltd",
    "wof:placetype":"venue"
},
  "geometry": {"coordinates":[151.20840454099999,-33.8401641846],"type":"Point"}
}