{
  "type": "Feature",
  "properties": {
    "addr:full":"41 Bide St Taringa QLD 4068",
    "addr:housenumber":"41",
    "addr:postcode":"4068",
    "addr:street":"Bide St",
    "iso:country":"AU",
    "sg:address":"41 Bide St",
    "sg:city":"Taringa",
    "sg:classifiers":[
        {
            "category":"Professional",
            "subcategory":"Accounting & Tax Preparation",
            "type":"Services"
        }
    ],
    "sg:phone":"+61 7 3371 8500",
    "sg:postcode":"4068",
    "sg:province":"QLD",
    "sg:tags":[
        "consultant",
        "taxation"
    ],
    "wof:name":"Douglass Stephen",
    "wof:placetype":"venue"
},
  "geometry": {"coordinates":[152.971435547,-27.4902496338],"type":"Point"}
}