{
  "type": "Feature",
  "properties": {
    "addr:full":"83 Ochard Ave Eltham VIC 3095",
    "addr:housenumber":"83",
    "addr:postcode":"3095",
    "addr:street":"Ochard Ave",
    "iso:country":"AU",
    "sg:address":"83 Ochard Ave",
    "sg:city":"Eltham",
    "sg:classifiers":[
        {
            "category":"Social Services",
            "subcategory":"Retirement Home",
            "type":"Services"
        }
    ],
    "sg:phone":"+61 3 9439 7785",
    "sg:postcode":"3095",
    "sg:province":"VIC",
    "sg:tags":[
        "environmental",
        "consultant",
        "pollution"
    ],
    "wof:name":"Streamline Research",
    "wof:placetype":"venue"
},
  "geometry": {"coordinates":[145.146972656,-37.7010917664],"type":"Point"}
}