{
  "type": "Feature",
  "properties": {
    "iso:country":"AU",
    "sg:address":"5 Montague St",
    "sg:city":"St Arnaud",
    "sg:classifiers":[
        {
            "category":"Building & Trades",
            "subcategory":"Construction",
            "type":"Services"
        }
    ],
    "sg:phone":"+61 3 5495 1716",
    "sg:postcode":"3478",
    "sg:province":"VIC",
    "sg:tags":[
        "contractor"
    ],
    "wof:name":"Donaldson Wayne",
    "wof:placetype":"venue"
},
  "geometry": {"coordinates":[143.263549805,-36.6177978516],"type":"Point"}
}