{
  "type": "Feature",
  "properties": {
    "addr:full":"265 Little Bourke St Melbourne VIC 3000",
    "addr:housenumber":"265",
    "addr:postcode":"3000",
    "addr:street":"Little Bourke St",
    "iso:country":"AU",
    "sg:address":"265 Little Bourke St",
    "sg:city":"Melbourne",
    "sg:classifiers":[
        {
            "category":"Shopping",
            "subcategory":"Shoes",
            "type":"Retail Goods"
        }
    ],
    "sg:phone":"+61 3 9663 2300",
    "sg:postcode":"3000",
    "sg:province":"VIC",
    "sg:tags":[
        "footwear"
    ],
    "wof:name":"Alan Pinkus Shoes",
    "wof:placetype":"venue"
},
  "geometry": {"coordinates":[144.96473693900001,-37.8127937317],"type":"Point"}
}