{
  "type": "Feature",
  "properties": {
    "iso:country":"AU",
    "sg:address":"Shop 16, Midland Gate Shopping Cntr",
    "sg:city":"Midland",
    "sg:classifiers":[
        {
            "category":"Travel",
            "subcategory":"Travel Agent",
            "type":"Entertainment"
        }
    ],
    "sg:phone":"+61 8 9274 5866",
    "sg:postcode":"6056",
    "sg:province":"WA",
    "sg:tags":[
        "consultant"
    ],
    "wof:name":"Jetset",
    "wof:placetype":"venue"
},
  "geometry": {"coordinates":[116.02348327599999,-31.9312286377],"type":"Point"}
}