{
  "type": "Feature",
  "properties": {
    "addr:full":"252 Wynnum Rd Norman Park QLD 4170",
    "addr:housenumber":"252",
    "addr:postcode":"4170",
    "addr:street":"Wynnum Rd",
    "iso:country":"AU",
    "sg:address":"252 Wynnum Rd",
    "sg:city":"Norman Park",
    "sg:classifiers":[
        {
            "category":"Professional",
            "subcategory":"Management & Consulting",
            "type":"Services"
        }
    ],
    "sg:phone":"+61 7 3902 0288",
    "sg:postcode":"4170",
    "sg:province":"QLD",
    "sg:tags":[
        "consultant",
        "energy"
    ],
    "wof:name":"Thor Energy Services Pty Ltd",
    "wof:placetype":"venue"
},
  "geometry": {"coordinates":[153.06080627399999,-27.4724788666],"type":"Point"}
}