{
  "type": "Feature",
  "properties": {
    "iso:country":"AU",
    "sg:address":"649 Lutwyche Rd",
    "sg:city":"Lutwyche",
    "sg:classifiers":[
        {
            "category":"Real Estate",
            "subcategory":"Real Estate Agent",
            "type":"Services"
        }
    ],
    "sg:phone":"+61 7 3622 1000",
    "sg:postcode":"4030",
    "sg:province":"QLD",
    "wof:name":"Property Office Pty Ltd The",
    "wof:placetype":"venue"
},
  "geometry": {"coordinates":[153.03625500000001,-27.417744],"type":"Point"}
}