{
  "type": "Feature",
  "properties": {
    "addr:full":"2 castle St Castle Hill NSW 2154",
    "addr:housenumber":"2",
    "addr:postcode":"2154",
    "addr:street":"Castle St",
    "iso:country":"AU",
    "sg:address":"2 castle St",
    "sg:city":"Castle Hill",
    "sg:classifiers":[
        {
            "category":"Personal",
            "subcategory":"Beauty Salon",
            "type":"Services"
        }
    ],
    "sg:phone":"+61 2 9634 2411",
    "sg:postcode":"2154",
    "sg:province":"NSW",
    "sg:website":"http://www.templeskincare.com.au",
    "wof:name":".The Temple Skincare",
    "wof:placetype":"venue"
},
  "geometry": {"coordinates":[151.005859375,-33.7320365906],"type":"Point"}
}