{
  "type": "Feature",
  "properties": {
    "iso:country":"AU",
    "sg:address":"Level 11, 2 Mill St",
    "sg:city":"Perth",
    "sg:classifiers":[
        {
            "category":"Banks & Credit Unions",
            "subcategory":"Financial Services",
            "type":"Services"
        }
    ],
    "sg:phone":"+61 8 9321 1211",
    "sg:postcode":"6000",
    "sg:province":"WA",
    "sg:tags":[
        "franchising"
    ],
    "sg:website":"http://www.downings.com.au",
    "wof:name":"Downings Legal",
    "wof:placetype":"venue"
},
  "geometry": {"coordinates":[115.852630615,-31.954957962],"type":"Point"}
}