{
  "type": "Feature",
  "properties": {
    "addr:full":"128 Lagoon St Narrabeen NSW 2101",
    "addr:housenumber":"128",
    "addr:postcode":"2101",
    "addr:street":"Lagoon St",
    "iso:country":"AU",
    "sg:address":"128 Lagoon St",
    "sg:city":"Narrabeen",
    "sg:classifiers":[
        {
            "category":"Utilities",
            "subcategory":"Water",
            "type":"Services"
        }
    ],
    "sg:phone":"+61 2 9970 7031",
    "sg:postcode":"2101",
    "sg:province":"NSW",
    "sg:tags":[
        "hot",
        "system"
    ],
    "wof:name":"A. Universal Electrical Services",
    "wof:placetype":"venue"
},
  "geometry": {"coordinates":[151.30195599999999,-33.705662],"type":"Point"}
}