{
  "type": "Feature",
  "properties": {
    "addr:full":"158 Norton St Leichhardt NSW 2040",
    "addr:housenumber":"158",
    "addr:postcode":"2040",
    "addr:street":"Norton St",
    "iso:country":"AU",
    "sg:address":"158 Norton St",
    "sg:city":"Leichhardt",
    "sg:classifiers":[
        {
            "category":"Cafe",
            "type":"Food & Drink"
        }
    ],
    "sg:phone":"+61 2 9560 2434",
    "sg:postcode":"2040",
    "sg:province":"NSW",
    "wof:name":"Cafe Jolly",
    "wof:placetype":"venue"
},
  "geometry": {"coordinates":[151.156677,-33.881775],"type":"Point"}
}