{
  "type": "Feature",
  "properties": {
    "addr:full":"179 Chuter Ave Sans Souci NSW 2219",
    "addr:housenumber":"179",
    "addr:postcode":"2219",
    "addr:street":"Chuter Ave",
    "iso:country":"AU",
    "sg:address":"179 Chuter Ave",
    "sg:city":"Sans Souci",
    "sg:classifiers":[
        {
            "category":"Building & Trades",
            "subcategory":"Construction",
            "type":"Services"
        }
    ],
    "sg:phone":"+61 418 278 409",
    "sg:postcode":"2219",
    "sg:province":"NSW",
    "sg:tags":[
        "contractor"
    ],
    "wof:name":"S K Constructions Pty Ltd",
    "wof:placetype":"venue"
},
  "geometry": {"coordinates":[151.142563,-33.989567],"type":"Point"}
}