{
  "type": "Feature",
  "properties": {
    "iso:country":"AU",
    "sg:address":"15a Little Burwood Hwy",
    "sg:city":"Wantirna South",
    "sg:classifiers":[
        {
            "category":"Health Services",
            "subcategory":"Optometrist",
            "type":"Services"
        }
    ],
    "sg:phone":"+61 3 9887 0677",
    "sg:postcode":"3152",
    "sg:province":"VIC",
    "wof:name":"Poh-Lee Tang",
    "wof:placetype":"venue"
},
  "geometry": {"coordinates":[145.24395751899999,-37.8711738586],"type":"Point"}
}