{
  "type": "Feature",
  "properties": {
    "iso:country":"AU",
    "sg:address":"32 Avalon St",
    "sg:city":"Oxley",
    "sg:classifiers":[
        {
            "category":"Health Services",
            "subcategory":"Dentist",
            "type":"Services"
        }
    ],
    "sg:phone":"+61 7 3375 9977",
    "sg:postcode":"4075",
    "sg:province":"QLD",
    "sg:tags":[
        "dental",
        "prosthetist"
    ],
    "wof:name":"Avalon Custom Denture Clinic",
    "wof:placetype":"venue"
},
  "geometry": {"coordinates":[152.96742248499999,-27.5610599518],"type":"Point"}
}