{
  "type": "Feature",
  "properties": {
    "addr:full":"32 Douglas St Manunda QLD 4870",
    "addr:housenumber":"32",
    "addr:postcode":"4870",
    "addr:street":"Douglas St",
    "iso:country":"AU",
    "sg:address":"32 Douglas St",
    "sg:city":"Manunda",
    "sg:classifiers":[
        {
            "category":"Building & Trades",
            "subcategory":"Construction",
            "type":"Services"
        }
    ],
    "sg:phone":"+61 7 4053 3669",
    "sg:postcode":"4870",
    "sg:province":"QLD",
    "sg:tags":[
        "welding"
    ],
    "wof:name":"Lawson's Workshop",
    "wof:placetype":"venue"
},
  "geometry": {"coordinates":[145.74664306599999,-16.91198349],"type":"Point"}
}