{
  "type": "Feature",
  "properties": {
    "addr:full":"19 Churchill St Buranda QLD 4102",
    "addr:housenumber":"19",
    "addr:postcode":"4102",
    "addr:street":"Churchill St",
    "iso:country":"AU",
    "sg:address":"19 Churchill St",
    "sg:city":"Buranda",
    "sg:classifiers":[
        {
            "category":"Organizations",
            "subcategory":"Non-profit Organization",
            "type":"Services"
        }
    ],
    "sg:phone":"+61 7 3391 1612",
    "sg:postcode":"4102",
    "sg:province":"QLD",
    "sg:tags":[
        "support",
        "disability",
        "organisation"
    ],
    "wof:name":"Lady Grey House",
    "wof:placetype":"venue"
},
  "geometry": {"coordinates":[153.046432495,-27.4962673187],"type":"Point"}
}