{
  "type": "Feature",
  "properties": {
    "addr:full":"594 Great Northern Hwy Herne Hill WA 6056",
    "addr:housenumber":"594",
    "addr:postcode":"6056",
    "addr:street":"Great Northern Hwy",
    "iso:country":"AU",
    "sg:address":"594 Great Northern Hwy",
    "sg:city":"Herne Hill",
    "sg:classifiers":[
        {
            "category":"Professional",
            "type":"Services"
        }
    ],
    "sg:phone":"+61 406 894 983",
    "sg:postcode":"6056",
    "sg:province":"WA",
    "sg:tags":[
        "transport"
    ],
    "wof:name":"City West Transport Pty Ltd",
    "wof:placetype":"venue"
},
  "geometry": {"coordinates":[116.01709747300001,-31.8257369995],"type":"Point"}
}