{
  "type": "Feature",
  "properties": {
    "iso:country":"AU",
    "sg:address":"11 Moore St",
    "sg:city":"Ulverstone",
    "sg:classifiers":[
        {
            "category":"Education",
            "subcategory":"Special Training",
            "type":"Public Place"
        }
    ],
    "sg:phone":"+61 3 6425 6524",
    "sg:postcode":"7315",
    "sg:province":"TAS",
    "sg:tags":[
        "development"
    ],
    "wof:name":"Stepping Ahead Training & Development",
    "wof:placetype":"venue"
},
  "geometry": {"coordinates":[146.16189575199999,-41.1472167969],"type":"Point"}
}