{
  "type": "Feature",
  "properties": {
    "addr:full":"38 Cardigan Rd Mooroolbark VIC 3138",
    "addr:housenumber":"38",
    "addr:postcode":"3138",
    "addr:street":"Cardigan Rd",
    "iso:country":"AU",
    "sg:address":"38 Cardigan Rd",
    "sg:city":"Mooroolbark",
    "sg:classifiers":[
        {
            "category":"Personal",
            "subcategory":"Massage",
            "type":"Services"
        }
    ],
    "sg:phone":"+61 3 9725 6672",
    "sg:postcode":"3138",
    "sg:province":"VIC",
    "sg:tags":[
        "therapy"
    ],
    "wof:name":"Collins Laurie",
    "wof:placetype":"venue"
},
  "geometry": {"coordinates":[145.32164001500001,-37.7884712219],"type":"Point"}
}