{
  "type": "Feature",
  "properties": {
    "iso:country":"AU",
    "sg:address":"14- 16 Williamson St",
    "sg:city":"Bendigo",
    "sg:classifiers":[
        {
            "category":"Fast Food",
            "type":"Food & Drink"
        }
    ],
    "sg:phone":"+61 3 5442 8400",
    "sg:postcode":"3550",
    "sg:province":"VIC",
    "sg:tags":[
        "away",
        "take"
    ],
    "wof:name":"Subway",
    "wof:placetype":"venue"
},
  "geometry": {"coordinates":[144.28024292000001,-36.7587928772],"type":"Point"}
}