{
  "type": "Feature",
  "properties": {
    "addr:full":"191 Church St Newtown NSW 2042",
    "addr:housenumber":"191",
    "addr:postcode":"2042",
    "addr:street":"Church St",
    "iso:country":"AU",
    "sg:address":"191 Church St",
    "sg:city":"Newtown",
    "sg:classifiers":[
        {
            "category":"Government",
            "subcategory":"City Hall",
            "type":"Public Place"
        }
    ],
    "sg:phone":"+61 2 9557 2098",
    "sg:postcode":"2042",
    "sg:province":"NSW",
    "wof:name":"Newtown Baptist Church Dance & Music Studio",
    "wof:placetype":"venue"
},
  "geometry": {"coordinates":[151.180725,-33.89502],"type":"Point"}
}