{
  "type": "Feature",
  "properties": {
    "iso:country":"AU",
    "sg:address":"34 Lynrob Pl",
    "sg:city":"Thornleigh",
    "sg:classifiers":[
        {
            "category":"Real Estate",
            "subcategory":"Architect",
            "type":"Services"
        }
    ],
    "sg:phone":"+61 2 9484 0288",
    "sg:postcode":"2120",
    "sg:province":"NSW",
    "sg:tags":[
        "naval"
    ],
    "wof:name":"AMD Marine Consulting Pty Ltd",
    "wof:placetype":"venue"
},
  "geometry": {"coordinates":[151.0703125,-33.7267417908],"type":"Point"}
}