{
  "type": "Feature",
  "properties": {
    "iso:country":"AU",
    "sg:address":"2 Essex St",
    "sg:city":"Bayswater",
    "sg:classifiers":[
        {
            "category":"Health Services",
            "subcategory":"Nursing And Care Facility",
            "type":"Services"
        }
    ],
    "sg:phone":"+61 8 9370 1199",
    "sg:postcode":"6053",
    "sg:province":"WA",
    "sg:tags":[
        "home"
    ],
    "wof:name":"St Georges Home",
    "wof:placetype":"venue"
},
  "geometry": {"coordinates":[115.905456543,-31.9155883789],"type":"Point"}
}