{
  "type": "Feature",
  "properties": {
    "iso:country":"AU",
    "sg:address":"8 Challis Ave",
    "sg:city":"Potts Point",
    "sg:classifiers":[
        {
            "category":"Travel",
            "subcategory":"Hotels & Motels",
            "type":"Entertainment"
        }
    ],
    "sg:phone":"+61 2 9356 2199",
    "sg:postcode":"2011",
    "sg:province":"NSW",
    "sg:tags":[
        "pub"
    ],
    "wof:name":"Simpsons Hotel of Potts Point",
    "wof:placetype":"venue"
},
  "geometry": {"coordinates":[151.22369384800001,-33.8685951233],"type":"Point"}
}