{
  "type": "Feature",
  "properties": {
    "addr:full":"139 Great Ocean Rd Apollo Bay VIC 3233",
    "addr:housenumber":"139",
    "addr:postcode":"3233",
    "addr:street":"Great Ocean Rd",
    "iso:country":"AU",
    "sg:address":"139 Great Ocean Rd",
    "sg:city":"Apollo Bay",
    "sg:classifiers":[
        {
            "category":"Cafe",
            "type":"Food & Drink"
        }
    ],
    "sg:phone":"+61 3 5237 6995",
    "sg:postcode":"3233",
    "sg:province":"VIC",
    "wof:name":"Sandy Feet Cafe & Health Foods",
    "wof:placetype":"venue"
},
  "geometry": {"coordinates":[143.65963745100001,-38.7785835266],"type":"Point"}
}