{
  "type": "Feature",
  "properties": {
    "addr:full":"29/ 5 Benalla Ave Ashfield NSW 2131",
    "addr:housenumber":"29 / 5",
    "addr:postcode":"2131",
    "addr:street":"Benalla Ave",
    "iso:country":"AU",
    "sg:address":"29/ 5 Benalla Ave",
    "sg:city":"Ashfield",
    "sg:classifiers":[
        {
            "category":"Professional",
            "subcategory":"Employment Agencies",
            "type":"Services"
        }
    ],
    "sg:phone":"+61 2 9716 6142",
    "sg:postcode":"2131",
    "sg:province":"NSW",
    "sg:tags":[
        "provider",
        "internet"
    ],
    "wof:name":"C.A.S.I.T Services",
    "wof:placetype":"venue"
},
  "geometry": {"coordinates":[151.121185303,-33.8850479126],"type":"Point"}
}