{
  "type": "Feature",
  "properties": {
    "addr:full":"116 a Boyce Rd Maroubra Junction NSW 2035",
    "addr:housenumber":"116 a",
    "addr:postcode":"2035",
    "addr:street":"Boyce Rd",
    "iso:country":"AU",
    "sg:address":"116 a Boyce Rd",
    "sg:city":"Maroubra Junction",
    "sg:classifiers":[
        {
            "category":"Health Services",
            "subcategory":"Chiropractor",
            "type":"Services"
        }
    ],
    "sg:phone":"+61 2 9314 1022",
    "sg:postcode":"2035",
    "sg:province":"NSW",
    "wof:name":"Samerski Sascha",
    "wof:placetype":"venue"
},
  "geometry": {"coordinates":[151.243209839,-33.9405593872],"type":"Point"}
}