{
  "type": "Feature",
  "properties": {
    "iso:country":"AU",
    "sg:address":"5 Wentworth St",
    "sg:city":"Bellerive",
    "sg:classifiers":[
        {
            "category":"Sports & Exercise",
            "subcategory":"Sports Center",
            "type":"Entertainment"
        }
    ],
    "sg:phone":"+61 3 6244 5115",
    "sg:postcode":"7018",
    "sg:province":"TAS",
    "sg:tags":[
        "coach",
        "tennis"
    ],
    "wof:name":"Andrew McCormack Tennis",
    "wof:placetype":"venue"
},
  "geometry": {"coordinates":[147.387176514,-42.8808517456],"type":"Point"}
}