{
  "type": "Feature",
  "properties": {
    "addr:full":"8 Pratts Park Rd Junortoun VIC 3551",
    "addr:housenumber":"8",
    "addr:postcode":"3551",
    "addr:street":"Pratts Park Rd",
    "iso:country":"AU",
    "sg:address":"8 Pratts Park Rd",
    "sg:city":"Junortoun",
    "sg:classifiers":[
        {
            "category":"Professional",
            "subcategory":"Business Services",
            "type":"Services"
        }
    ],
    "sg:phone":"+61 3 5449 3218",
    "sg:postcode":"3551",
    "sg:province":"VIC",
    "sg:tags":[
        "livestock",
        "transport"
    ],
    "wof:name":"Wignall Transport",
    "wof:placetype":"venue"
},
  "geometry": {"coordinates":[144.325042725,-36.7599449158],"type":"Point"}
}