{
  "type": "Feature",
  "properties": {
    "addr:full":"RMB 3115 Princes Hwy Portland VIC 3305",
    "addr:postcode":"3305",
    "addr:street":"Princes Hwy",
    "iso:country":"AU",
    "sg:address":"RMB 3115 Princes Hwy",
    "sg:city":"Portland",
    "sg:classifiers":[
        {
            "category":"Social Services",
            "subcategory":"Retirement Home",
            "type":"Services"
        }
    ],
    "sg:phone":"+61 3 5529 2112",
    "sg:postcode":"3305",
    "sg:province":"VIC",
    "sg:tags":[
        "environmental",
        "consultant",
        "pollution"
    ],
    "wof:name":"Australian Ecological Research Services Pty Ltd",
    "wof:placetype":"venue"
},
  "geometry": {"coordinates":[141.600631714,-38.3016777039],"type":"Point"}
}