{
  "type": "Feature",
  "properties": {
    "addr:full":"92 Nepean Hwy Mentone VIC 3194",
    "addr:housenumber":"92",
    "addr:postcode":"3194",
    "addr:street":"Nepean Hwy",
    "iso:country":"AU",
    "sg:address":"92 Nepean Hwy",
    "sg:city":"Mentone",
    "sg:classifiers":[
        {
            "category":"Fast Food",
            "type":"Food & Drink"
        }
    ],
    "sg:phone":"+61 3 9583 9801",
    "sg:postcode":"3194",
    "sg:province":"VIC",
    "sg:tags":[
        "away",
        "take"
    ],
    "wof:name":"Pizza Connection",
    "wof:placetype":"venue"
},
  "geometry": {"coordinates":[145.070068359,-37.9802436829],"type":"Point"}
}