{
  "type": "Feature",
  "properties": {
    "iso:country":"AU",
    "sg:address":"62 Orchardtown Rd",
    "sg:city":"New Lambton",
    "sg:classifiers":[
        {
            "category":"Manufacturing",
            "subcategory":"Food",
            "type":"Manufacturing & Wholesale Goods"
        }
    ],
    "sg:phone":"+61 2 4957 2445",
    "sg:postcode":"2305",
    "sg:province":"NSW",
    "sg:tags":[
        "function",
        "catering"
    ],
    "wof:name":"Dunns Butchers",
    "wof:placetype":"venue"
},
  "geometry": {"coordinates":[151.707779,-32.933926],"type":"Point"}
}