{
  "type": "Feature",
  "properties": {
    "addr:full":"40 Ramsgate Ave Christies Beach SA 5165",
    "addr:housenumber":"40",
    "addr:postcode":"5165",
    "addr:street":"Ramsgate Ave",
    "iso:country":"AU",
    "sg:address":"40 Ramsgate Ave",
    "sg:city":"Christies Beach",
    "sg:classifiers":[
        {
            "category":"Building & Trades",
            "subcategory":"Construction",
            "type":"Services"
        }
    ],
    "sg:phone":"+61 8 8384 4246",
    "sg:postcode":"5165",
    "sg:province":"SA",
    "sg:tags":[
        "concrete",
        "contractor"
    ],
    "wof:name":"Bridgman John",
    "wof:placetype":"venue"
},
  "geometry": {"coordinates":[138.47552490199999,-35.134223938],"type":"Point"}
}