{
  "type": "Feature",
  "properties": {
    "iso:country":"AU",
    "sg:address":"71 Liverpool St",
    "sg:city":"Hobart",
    "sg:classifiers":[
        {
            "category":"Government",
            "subcategory":"Court House",
            "type":"Public Place"
        }
    ],
    "sg:phone":"+61 408 292 762",
    "sg:postcode":"7000",
    "sg:province":"TAS",
    "sg:tags":[
        "personal",
        "marriage",
        "family",
        "counselling"
    ],
    "wof:name":"Thomas Steve",
    "wof:placetype":"venue"
},
  "geometry": {"coordinates":[147.32745361299999,-42.8808288574],"type":"Point"}
}