{
  "type": "Feature",
  "properties": {
    "addr:full":"86- 90 Aumuller St Cairns QLD 4870",
    "addr:housenumber":"90",
    "addr:postcode":"4870",
    "addr:street":"Aumuller St",
    "iso:country":"AU",
    "sg:address":"86- 90 Aumuller St",
    "sg:city":"Cairns",
    "sg:classifiers":[
        {
            "category":"Wholesale",
            "subcategory":"Painting Supplies",
            "type":"Manufacturing & Wholesale Goods"
        }
    ],
    "sg:phone":"+61 7 4035 2345",
    "sg:postcode":"4870",
    "sg:province":"QLD",
    "sg:tags":[
        "product",
        "cleaning"
    ],
    "sg:website":"http://www.cleaningsupplies.com.au",
    "wof:name":"Cairns Cleaning Supplies",
    "wof:placetype":"venue"
},
  "geometry": {"coordinates":[145.76614379899999,-16.9400596619],"type":"Point"}
}