{
  "type": "Feature",
  "properties": {
    "addr:full":"U1/ 22 Beesley St West End QLD 4101",
    "addr:postcode":"4101",
    "addr:street":"U1 / 22 Beesley St",
    "iso:country":"AU",
    "sg:address":"U1/ 22 Beesley St",
    "sg:city":"West End",
    "sg:classifiers":[
        {
            "category":"Professional",
            "subcategory":"Computer Services",
            "type":"Services"
        }
    ],
    "sg:phone":"+61 7 3844 4460",
    "sg:postcode":"4101",
    "sg:province":"QLD",
    "sg:tags":[
        "consultant",
        "system"
    ],
    "wof:name":"Next Space Technologies Pty Ltd",
    "wof:placetype":"venue"
},
  "geometry": {"coordinates":[153.003417969,-27.4813423157],"type":"Point"}
}