{
  "type": "Feature",
  "properties": {
    "addr:full":"364 Main Rd Glenorchy TAS 7010",
    "addr:housenumber":"364",
    "addr:postcode":"7010",
    "addr:street":"Main Rd",
    "iso:country":"AU",
    "sg:address":"364 Main Rd",
    "sg:city":"Glenorchy",
    "sg:classifiers":[
        {
            "category":"Professional",
            "subcategory":"Employment Agencies",
            "type":"Services"
        }
    ],
    "sg:phone":"+61 3 6272 5386",
    "sg:postcode":"7010",
    "sg:province":"TAS",
    "wof:name":"Workskills",
    "wof:placetype":"venue"
},
  "geometry": {"coordinates":[147.27619934099999,-42.8332519531],"type":"Point"}
}