{
  "type": "Feature",
  "properties": {
    "addr:full":"80 Commercial St Walla Walla NSW 2659",
    "addr:housenumber":"80",
    "addr:postcode":"2659",
    "addr:street":"Commercial St",
    "iso:country":"AU",
    "sg:address":"80 Commercial St",
    "sg:city":"Walla Walla",
    "sg:classifiers":[
        {
            "category":"Real Estate",
            "subcategory":"Real Estate Agent",
            "type":"Services"
        }
    ],
    "sg:phone":"+61 2 6029 2174",
    "sg:postcode":"2659",
    "sg:province":"NSW",
    "wof:name":"Grosse Jeff",
    "wof:placetype":"venue"
},
  "geometry": {"coordinates":[146.900634766,-35.7678985596],"type":"Point"}
}