{
  "type": "Feature",
  "properties": {
    "addr:full":"5 Shamrock Crt Middle Ridge QLD 4350",
    "addr:housenumber":"5",
    "addr:postcode":"4350",
    "addr:street":"Shamrock Crt",
    "iso:country":"AU",
    "sg:address":"5 Shamrock Crt",
    "sg:city":"Middle Ridge",
    "sg:classifiers":[
        {
            "category":"Farming",
            "subcategory":"Farm & Veterinary Services",
            "type":"Manufacturing & Wholesale Goods"
        }
    ],
    "sg:phone":"+61 7 4636 3227",
    "sg:postcode":"4350",
    "sg:province":"QLD",
    "sg:tags":[
        "agricultural",
        "advisory"
    ],
    "wof:name":"Ridge Peter E & Associates Pty Ltd",
    "wof:placetype":"venue"
},
  "geometry": {"coordinates":[151.965485,-27.597776],"type":"Point"}
}