{
  "type": "Feature",
  "properties": {
    "addr:full":"Level 1/ 60 Macquarie St Parramatta NSW 2150",
    "addr:housenumber":"/ 60",
    "addr:postcode":"2150",
    "addr:street":"Macquarie St",
    "iso:country":"AU",
    "sg:address":"Level 1/ 60 Macquarie St",
    "sg:city":"Parramatta",
    "sg:classifiers":[
        {
            "category":"Shopping",
            "subcategory":"Bridal",
            "type":"Retail Goods"
        }
    ],
    "sg:phone":"+61 2 9635 3311",
    "sg:postcode":"2150",
    "sg:province":"NSW",
    "sg:tags":[
        "hire",
        "wear"
    ],
    "wof:name":"Bridal Serects",
    "wof:placetype":"venue"
},
  "geometry": {"coordinates":[151.06301879899999,-33.9104270935],"type":"Point"}
}