{
  "type": "Feature",
  "properties": {
    "addr:full":"Shop 22, Currambine Shopping Centre Marmian Ave Currambine WA 6028",
    "addr:housenumber":"shop 22",
    "addr:postcode":"6028",
    "addr:street":"Ave",
    "iso:country":"AU",
    "sg:address":"Shop 22, Currambine Shopping Centre Marmian Ave",
    "sg:city":"Currambine",
    "sg:classifiers":[
        {
            "category":"Health Services",
            "subcategory":"Dentist",
            "type":"Services"
        }
    ],
    "sg:phone":"+61 8 9304 0300",
    "sg:postcode":"6028",
    "sg:province":"WA",
    "wof:name":"Dehghan Farnaz Dr",
    "wof:placetype":"venue"
},
  "geometry": {"coordinates":[115.744903565,-31.7306308746],"type":"Point"}
}