{
  "type": "Feature",
  "properties": {
    "addr:full":"18 Lee-Anne Crs Monterey Keys QLD 4212",
    "addr:housenumber":"18",
    "addr:postcode":"4212",
    "addr:street":"Lee-Anne Crs",
    "iso:country":"AU",
    "sg:address":"18 Lee-Anne Crs",
    "sg:city":"Monterey Keys",
    "sg:classifiers":[
        {
            "category":"Organizations",
            "subcategory":"Professional Association",
            "type":"Services"
        }
    ],
    "sg:phone":"+61 7 5573 4441",
    "sg:postcode":"4212",
    "sg:province":"QLD",
    "sg:tags":[
        "web",
        "internet"
    ],
    "wof:name":"Surf Pacific",
    "wof:placetype":"venue"
},
  "geometry": {"coordinates":[153.340942383,-27.8899898529],"type":"Point"}
}