{
  "type": "Feature",
  "properties": {
    "iso:country":"AU",
    "sg:address":"35 Spring Bank Rd",
    "sg:city":"Colonel Light Gardens",
    "sg:classifiers":[
        {
            "category":"Personal",
            "type":"Services"
        }
    ],
    "sg:phone":"+61 8 8177 1548",
    "sg:postcode":"5041",
    "sg:province":"SA",
    "sg:tags":[
        "reducing",
        "treatment",
        "weight"
    ],
    "wof:name":"Herbalife Colonel Light Gardens",
    "wof:placetype":"venue"
},
  "geometry": {"coordinates":[138.597641,-34.990421],"type":"Point"}
}