{
  "type": "Feature",
  "properties": {
    "iso:country":"AU",
    "sg:address":"Sea World Drv",
    "sg:city":"Main Beach",
    "sg:classifiers":[
        {
            "category":"Sports & Exercise",
            "subcategory":"Gym",
            "type":"Entertainment"
        }
    ],
    "sg:phone":"+61 7 5532 6464",
    "sg:postcode":"4217",
    "sg:province":"QLD",
    "sg:tags":[
        "health",
        "fitness"
    ],
    "wof:name":"Salus Per Aquum Spa",
    "wof:placetype":"venue"
},
  "geometry": {"coordinates":[153.42718505900001,-27.9657707214],"type":"Point"}
}