{
  "type": "Feature",
  "properties": {
    "addr:full":"84 Halifax St Adelaide SA 5000",
    "addr:housenumber":"84",
    "addr:postcode":"5000",
    "addr:street":"Halifax St",
    "iso:country":"AU",
    "sg:address":"84 Halifax St",
    "sg:city":"Adelaide",
    "sg:classifiers":[
        {
            "category":"Banks & Credit Unions",
            "subcategory":"Financial Services",
            "type":"Services"
        }
    ],
    "sg:phone":"+61 8 8223 3242",
    "sg:postcode":"5000",
    "sg:province":"SA",
    "sg:tags":[
        "advisory",
        "planning",
        "retirement"
    ],
    "wof:name":"Bluestone Financial Services",
    "wof:placetype":"venue"
},
  "geometry": {"coordinates":[138.603424072,-34.9325370789],"type":"Point"}
}