{
  "type": "Feature",
  "properties": {
    "addr:full":"Lvl 1/ 15 Hampden St Paddington NSW 2021",
    "addr:housenumber":"/ 15",
    "addr:postcode":"2021",
    "addr:street":"Hampden St",
    "iso:country":"AU",
    "sg:address":"Lvl 1/ 15 Hampden St",
    "sg:city":"Paddington",
    "sg:classifiers":[
        {
            "category":"Manufacturing",
            "subcategory":"Furniture",
            "type":"Manufacturing & Wholesale Goods"
        }
    ],
    "sg:phone":"+61 2 9380 4454",
    "sg:postcode":"2021",
    "sg:province":"NSW",
    "sg:tags":[
        "builder",
        "designer",
        "custom"
    ],
    "wof:name":"Ara Collections",
    "wof:placetype":"venue"
},
  "geometry": {"coordinates":[151.23301696799999,-33.8815155029],"type":"Point"}
}