{
  "type": "Feature",
  "properties": {
    "iso:country":"AU",
    "sg:address":"397 Anson St",
    "sg:city":"Orange",
    "sg:classifiers":[
        {
            "category":"Building & Trades",
            "subcategory":"Construction",
            "type":"Services"
        }
    ],
    "sg:phone":"+61 2 6369 1487",
    "sg:postcode":"2800",
    "sg:province":"NSW",
    "sg:tags":[
        "contractor"
    ],
    "wof:name":"Niven Fletcher",
    "wof:placetype":"venue"
},
  "geometry": {"coordinates":[149.099075317,-33.2809410095],"type":"Point"}
}