{
  "type": "Feature",
  "properties": {
    "iso:country":"AU",
    "sg:address":"Middle Rd",
    "sg:city":"Woodstock",
    "sg:classifiers":[
        {
            "category":"Shopping",
            "type":"Retail Goods"
        }
    ],
    "sg:phone":"+61 2 6342 4788",
    "sg:postcode":"2793",
    "sg:province":"NSW",
    "sg:tags":[
        "agent",
        "stock"
    ],
    "wof:name":"Dresser P J",
    "wof:placetype":"venue"
},
  "geometry": {"coordinates":[148.84800720199999,-33.7448692322],"type":"Point"}
}