{
  "type": "Feature",
  "properties": {
    "addr:full":"565 South Rd Bentleigh VIC 3204",
    "addr:housenumber":"565",
    "addr:postcode":"3204",
    "addr:street":"South Rd",
    "iso:country":"AU",
    "sg:address":"565 South Rd",
    "sg:city":"Bentleigh",
    "sg:classifiers":[
        {
            "category":"Retail",
            "subcategory":"Veterinary Services",
            "type":"Services"
        }
    ],
    "sg:phone":"+61 3 9555 1899",
    "sg:postcode":"3204",
    "sg:province":"VIC",
    "sg:tags":[
        "surgeon"
    ],
    "wof:name":"Nevill Ann",
    "wof:placetype":"venue"
},
  "geometry": {"coordinates":[145.04705799999999,-37.934292],"type":"Point"}
}