{
  "type": "Feature",
  "properties": {
    "addr:full":"28 Pirie St Fyshwick ACT 2609",
    "addr:housenumber":"28",
    "addr:postcode":"2609",
    "addr:street":"Pirie St",
    "iso:country":"AU",
    "sg:address":"28 Pirie St",
    "sg:city":"Fyshwick",
    "sg:classifiers":[
        {
            "category":"Professional",
            "subcategory":"Printing & Photocopies",
            "type":"Services"
        }
    ],
    "sg:phone":"+61 2 6280 5265",
    "sg:postcode":"2609",
    "sg:province":"ACT",
    "sg:tags":[
        "photocopying"
    ],
    "wof:name":"Canberra Publishing & Printing",
    "wof:placetype":"venue"
},
  "geometry": {"coordinates":[149.170852661,-35.3251228333],"type":"Point"}
}