{
  "type": "Feature",
  "properties": {
    "addr:full":"62 Riverside Rd Chipping Norton NSW 2170",
    "addr:housenumber":"62",
    "addr:postcode":"2170",
    "addr:street":"Riverside Rd",
    "iso:country":"AU",
    "sg:address":"62 Riverside Rd",
    "sg:city":"Chipping Norton",
    "sg:classifiers":[
        {
            "category":"Retail",
            "subcategory":"Auto Repair",
            "type":"Services"
        }
    ],
    "sg:phone":"+61 2 9755 1807",
    "sg:postcode":"2170",
    "sg:province":"NSW",
    "sg:tags":[
        "beater",
        "painter",
        "panel"
    ],
    "wof:name":"C-Us-First Smash Repairs",
    "wof:placetype":"venue"
},
  "geometry": {"coordinates":[150.96842956500001,-33.9197158813],"type":"Point"}
}