{
  "type": "Feature",
  "properties": {
    "iso:country":"AU",
    "sg:address":"Northland S/C Shop KK8, 2-50 Murray Rd",
    "sg:city":"Preston",
    "sg:classifiers":[
        {
            "category":"Ice Cream",
            "type":"Food & Drink"
        }
    ],
    "sg:phone":"+61 3 9470 4406",
    "sg:postcode":"3072",
    "sg:province":"VIC",
    "sg:tags":[
        "retail"
    ],
    "wof:name":"New Zealand Natural Ice Cream",
    "wof:placetype":"venue"
},
  "geometry": {"coordinates":[145.02931213400001,-37.740650177],"type":"Point"}
}