{
  "type": "Feature",
  "properties": {
    "addr:full":"380 Wyndham St Shepparton VIC 3630",
    "addr:housenumber":"380",
    "addr:postcode":"3630",
    "addr:street":"Wyndham St",
    "iso:country":"AU",
    "sg:address":"380 Wyndham St",
    "sg:city":"Shepparton",
    "sg:classifiers":[
        {
            "category":"Fast Food",
            "type":"Food & Drink"
        }
    ],
    "sg:phone":"+61 3 5821 6928",
    "sg:postcode":"3630",
    "sg:province":"VIC",
    "sg:tags":[
        "away",
        "take"
    ],
    "wof:name":"Goulburn Valley Charcoal Chicken",
    "wof:placetype":"venue"
},
  "geometry": {"coordinates":[145.39895629899999,-36.3820266724],"type":"Point"}
}