{
  "type": "Feature",
  "properties": {
    "iso:country":"AU",
    "sg:address":"Unit 3, 30 Piper Drv",
    "sg:city":"Ballina",
    "sg:classifiers":[
        {
            "category":"Shopping",
            "subcategory":"Beauty & Cosmetics",
            "type":"Retail Goods"
        }
    ],
    "sg:phone":"+61 2 6686 2755",
    "sg:postcode":"2478",
    "sg:province":"NSW",
    "sg:tags":[
        "equipment",
        "salon",
        "supply"
    ],
    "wof:name":"The Back Room Hair Body - Beauty Supplies The",
    "wof:placetype":"venue"
},
  "geometry": {"coordinates":[153.55714416500001,-28.8477230072],"type":"Point"}
}