{
  "type": "Feature",
  "properties": {
    "iso:country":"AU",
    "sg:address":"5 Ijong St",
    "sg:city":"Kenmore",
    "sg:classifiers":[
        {
            "category":"Building & Trades",
            "subcategory":"Cleaning & Sanitation",
            "type":"Services"
        }
    ],
    "sg:phone":"+61 401 775 463",
    "sg:postcode":"4069",
    "sg:province":"QLD",
    "sg:tags":[
        "industrial",
        "commercial",
        "contractor"
    ],
    "wof:name":"Boring Chores",
    "wof:placetype":"venue"
},
  "geometry": {"coordinates":[152.94956970199999,-27.512550354],"type":"Point"}
}