{
  "type": "Feature",
  "properties": {
    "addr:full":"19 Claudia St Kingston QLD 4114",
    "addr:housenumber":"19",
    "addr:postcode":"4114",
    "addr:street":"Claudia St",
    "iso:country":"AU",
    "sg:address":"19 Claudia St",
    "sg:city":"Kingston",
    "sg:classifiers":[
        {
            "category":"Retail",
            "subcategory":"Storage",
            "type":"Services"
        }
    ],
    "sg:phone":"+61 417 756 828",
    "sg:postcode":"4114",
    "sg:province":"QLD",
    "sg:tags":[
        "removal",
        "furniture"
    ],
    "wof:name":"Anything Anywhere Removals",
    "wof:placetype":"venue"
},
  "geometry": {"coordinates":[153.11900329599999,-27.6535186768],"type":"Point"}
}