{
  "type": "Feature",
  "properties": {
    "addr:full":"U1/ 27 Virginia St Virginia QLD 4014",
    "addr:housenumber":"27",
    "addr:postcode":"4014",
    "addr:street":"U1 /;Virginia St",
    "iso:country":"AU",
    "sg:address":"U1/ 27 Virginia St",
    "sg:city":"Virginia",
    "sg:classifiers":[
        {
            "category":"Building & Trades",
            "subcategory":"Construction",
            "type":"Services"
        }
    ],
    "sg:phone":"+61 7 3865 8555",
    "sg:postcode":"4014",
    "sg:province":"QLD",
    "sg:tags":[
        "scaffolding"
    ],
    "wof:name":"Action Access Pty Ltd",
    "wof:placetype":"venue"
},
  "geometry": {"coordinates":[153.05857849099999,-27.3636112213],"type":"Point"}
}