{
  "type": "Feature",
  "properties": {
    "addr:full":"Wills Crt Mooroolbark VIC 3138",
    "addr:postcode":"3138",
    "addr:street":"Wills Crt",
    "iso:country":"AU",
    "sg:address":"Wills Crt",
    "sg:city":"Mooroolbark",
    "sg:classifiers":[
        {
            "category":"Health Services",
            "subcategory":"Podiatrist",
            "type":"Services"
        }
    ],
    "sg:phone":"+61 3 9727 3441",
    "sg:postcode":"3138",
    "sg:province":"VIC",
    "sg:tags":[
        "cap",
        "hat",
        "renovation",
        "retail"
    ],
    "wof:name":"Promotional Headwear",
    "wof:placetype":"venue"
},
  "geometry": {"coordinates":[145.33729553200001,-37.7795181274],"type":"Point"}
}