{
  "type": "Feature",
  "properties": {
    "addr:full":"5/ 20 Valediction Rd Kings Park NSW 2148",
    "addr:housenumber":"/ 20",
    "addr:postcode":"2148",
    "addr:street":"Valediction Rd",
    "iso:country":"AU",
    "sg:address":"5/ 20 Valediction Rd",
    "sg:city":"Kings Park",
    "sg:classifiers":[
        {
            "category":"Building & Trades",
            "subcategory":"Construction",
            "type":"Services"
        }
    ],
    "sg:phone":"+61 421 977 638",
    "sg:postcode":"2148",
    "sg:province":"NSW",
    "sg:tags":[
        "builder",
        "designer",
        "room",
        "cool"
    ],
    "wof:name":"Complete Coolroom Suppliers",
    "wof:placetype":"venue"
},
  "geometry": {"coordinates":[150.91308593799999,-33.7453536987],"type":"Point"}
}