{
  "type": "Feature",
  "properties": {
    "addr:full":"Yamba Rd Maclean NSW 2463",
    "addr:postcode":"2463",
    "addr:street":"Yamba Rd",
    "iso:country":"AU",
    "sg:address":"Yamba Rd",
    "sg:city":"Maclean",
    "sg:classifiers":[
        {
            "category":"Home & Garden",
            "subcategory":"Building Materials",
            "type":"Retail Goods"
        }
    ],
    "sg:phone":"+61 2 6645 2229",
    "sg:postcode":"2463",
    "sg:province":"NSW",
    "sg:tags":[
        "pre-mixed",
        "concrete"
    ],
    "wof:name":"Boral Country-Concrete & Quarries",
    "wof:placetype":"venue"
},
  "geometry": {"coordinates":[153.21217346200001,-29.4423408508],"type":"Point"}
}