{
  "type": "Feature",
  "properties": {
    "addr:full":"4/ 18 Maiella St Stapylton QLD 4207",
    "addr:housenumber":"/ 18",
    "addr:postcode":"4207",
    "addr:street":"Maiella St",
    "iso:country":"AU",
    "sg:address":"4/ 18 Maiella St",
    "sg:city":"Stapylton",
    "sg:classifiers":[
        {
            "category":"Building & Trades",
            "subcategory":"Construction",
            "type":"Services"
        }
    ],
    "sg:phone":"+61 1300 137 081",
    "sg:postcode":"4207",
    "sg:province":"QLD",
    "sg:tags":[
        "pool",
        "swimming"
    ],
    "wof:name":"Suncoast Enclosures",
    "wof:placetype":"venue"
},
  "geometry": {"coordinates":[153.23449707,-27.7374534607],"type":"Point"}
}