{
  "type": "Feature",
  "properties": {
    "addr:full":"Shop7/ 58 Hesse St Colac VIC 3250",
    "addr:housenumber":"58",
    "addr:postcode":"3250",
    "addr:street":"Hesse St",
    "iso:country":"AU",
    "sg:address":"Shop7/ 58 Hesse St",
    "sg:city":"Colac",
    "sg:classifiers":[
        {
            "category":"Shopping",
            "subcategory":"Computers & Home Electronics",
            "type":"Retail Goods"
        }
    ],
    "sg:phone":"+61 3 5231 5579",
    "sg:postcode":"3250",
    "sg:province":"VIC",
    "sg:tags":[
        "small",
        "equipment",
        "business"
    ],
    "wof:name":"Coltek Computers",
    "wof:placetype":"venue"
},
  "geometry": {"coordinates":[143.58990499999999,-38.33971],"type":"Point"}
}