{
  "type": "Feature",
  "properties": {
    "iso:country":"AU",
    "sg:address":"36 Stanley St",
    "sg:city":"Blacktown",
    "sg:classifiers":[
        {
            "category":"Professional",
            "subcategory":"Employment Agencies",
            "type":"Services"
        }
    ],
    "sg:phone":"+61 402 247 736",
    "sg:postcode":"2148",
    "sg:province":"NSW",
    "sg:tags":[
        "occupational",
        "therapist"
    ],
    "wof:name":"Occupational Therapy For Kids",
    "wof:placetype":"venue"
},
  "geometry": {"coordinates":[150.91078185999999,-33.7865257263],"type":"Point"}
}