{
  "type": "Feature",
  "properties": {
    "addr:full":"28 Ereton Drv Labrador QLD 4215",
    "addr:housenumber":"28",
    "addr:postcode":"4215",
    "addr:street":"Ereton Drv",
    "iso:country":"AU",
    "sg:address":"28 Ereton Drv",
    "sg:city":"Labrador",
    "sg:classifiers":[
        {
            "category":"Cafe",
            "type":"Food & Drink"
        }
    ],
    "sg:phone":"+61 7 5529 1087",
    "sg:postcode":"4215",
    "sg:province":"QLD",
    "wof:name":"Cuppas Takeaway",
    "wof:placetype":"venue"
},
  "geometry": {"coordinates":[153.385787964,-27.9368991852],"type":"Point"}
}