{
  "type": "Feature",
  "properties": {
    "iso:country":"AU",
    "sg:address":"243 Princes Hwy",
    "sg:city":"Corrimal",
    "sg:classifiers":[
        {
            "category":"Wholesale",
            "subcategory":"Farm Supplies",
            "type":"Manufacturing & Wholesale Goods"
        }
    ],
    "sg:phone":"+61 2 4284 2200",
    "sg:postcode":"2518",
    "sg:province":"NSW",
    "sg:tags":[
        "feed",
        "supplement",
        "stock"
    ],
    "wof:name":"Corrimal Treasured Pets",
    "wof:placetype":"venue"
},
  "geometry": {"coordinates":[150.89662200000001,-34.373413],"type":"Point"}
}