{
  "type": "Feature",
  "properties": {
    "addr:full":"9 Station St Wentworth Falls NSW 2782",
    "addr:housenumber":"9",
    "addr:postcode":"2782",
    "addr:street":"Station St",
    "iso:country":"AU",
    "sg:address":"9 Station St",
    "sg:city":"Wentworth Falls",
    "sg:classifiers":[
        {
            "category":"Food & Beverages",
            "subcategory":"Supermarket",
            "type":"Retail Goods"
        }
    ],
    "sg:phone":"+61 2 4757 1099",
    "sg:postcode":"2782",
    "sg:province":"NSW",
    "sg:tags":[
        "grocery",
        "store"
    ],
    "wof:name":"Wentworth Falls Welcomemart",
    "wof:placetype":"venue"
},
  "geometry": {"coordinates":[150.375762939,-33.7100296021],"type":"Point"}
}