{
  "type": "Feature",
  "properties": {
    "iso:country":"AU",
    "sg:address":"Illawong Village Shopping Centre Fowler Road",
    "sg:city":"Illawong",
    "sg:classifiers":[
        {
            "category":"Personal",
            "subcategory":"Beauty Salon",
            "type":"Services"
        }
    ],
    "sg:phone":"+61 2 9543 3366",
    "sg:postcode":"2234",
    "sg:province":"NSW",
    "wof:name":"Pure Indulgence",
    "wof:placetype":"venue"
},
  "geometry": {"coordinates":[151.04199218799999,-33.998626709],"type":"Point"}
}