{
  "type": "Feature",
  "properties": {
    "addr:full":"37 Avalon Pde Avalon Beach NSW 2107",
    "addr:housenumber":"37",
    "addr:postcode":"2107",
    "addr:street":"Avalon Pde",
    "iso:country":"AU",
    "sg:address":"37 Avalon Pde",
    "sg:city":"Avalon Beach",
    "sg:classifiers":[
        {
            "category":"Shopping",
            "subcategory":"Clothing, Apparel, & Fashions",
            "type":"Retail Goods"
        }
    ],
    "sg:phone":"+61 2 9918 6981",
    "sg:postcode":"2107",
    "sg:province":"NSW",
    "sg:tags":[
        "lady",
        "wear"
    ],
    "wof:name":"Ark House The",
    "wof:placetype":"venue"
},
  "geometry": {"coordinates":[151.330352783,-33.6368331909],"type":"Point"}
}