{
  "type": "Feature",
  "properties": {
    "addr:full":"1/ 12 Georgia Crs Werribee VIC 3030",
    "addr:housenumber":"/ 12",
    "addr:postcode":"3030",
    "addr:street":"Georgia Crs",
    "iso:country":"AU",
    "sg:address":"1/ 12 Georgia Crs",
    "sg:city":"Werribee",
    "sg:classifiers":[
        {
            "category":"Professional",
            "subcategory":"Computer Services",
            "type":"Services"
        }
    ],
    "sg:phone":"+61 3 8685 8225",
    "sg:postcode":"3030",
    "sg:province":"VIC",
    "sg:tags":[
        "consultant",
        "system"
    ],
    "wof:name":"Wartook Professional Computing",
    "wof:placetype":"venue"
},
  "geometry": {"coordinates":[144.659637,-37.903702],"type":"Point"}
}