{
  "type": "Feature",
  "properties": {
    "addr:full":"1 Flint Crt Burleigh QLD 4220",
    "addr:housenumber":"1",
    "addr:postcode":"4220",
    "addr:street":"Flint Crt",
    "iso:country":"AU",
    "sg:address":"1 Flint Crt",
    "sg:city":"Burleigh",
    "sg:classifiers":[
        {
            "category":"Home & Garden",
            "subcategory":"Hardware",
            "type":"Retail Goods"
        }
    ],
    "sg:phone":"+61 7 5593 4899",
    "sg:postcode":"4220",
    "sg:province":"QLD",
    "sg:tags":[
        "generating",
        "set",
        "generator"
    ],
    "wof:name":"Karls Mower Service",
    "wof:placetype":"venue"
},
  "geometry": {"coordinates":[153.432662964,-28.0981998444],"type":"Point"}
}