{
  "type": "Feature",
  "properties": {
    "addr:full":"37 Birchwood Ave Woodlands WA 6018",
    "addr:housenumber":"37",
    "addr:postcode":"6018",
    "addr:street":"Birchwood Ave",
    "iso:country":"AU",
    "sg:address":"37 Birchwood Ave",
    "sg:city":"Woodlands",
    "sg:classifiers":[
        {
            "category":"Shopping",
            "subcategory":"Gifts & Souvenirs",
            "type":"Retail Goods"
        }
    ],
    "sg:phone":"+61 8 9446 6239",
    "sg:postcode":"6018",
    "sg:province":"WA",
    "sg:tags":[
        "shop",
        "supply"
    ],
    "wof:name":"K H Pottery & China",
    "wof:placetype":"venue"
},
  "geometry": {"coordinates":[115.79158783,-31.9061203003],"type":"Point"}
}