{
  "type": "Feature",
  "properties": {
    "addr:full":"27 Eton St Sutherland NSW 2232",
    "addr:housenumber":"27",
    "addr:postcode":"2232",
    "addr:street":"Eton St",
    "iso:country":"AU",
    "sg:address":"27 Eton St",
    "sg:city":"Sutherland",
    "sg:classifiers":[
        {
            "category":"Personal",
            "subcategory":"Beauty Salon",
            "type":"Services"
        }
    ],
    "sg:phone":"+61 2 9545 4488",
    "sg:postcode":"2232",
    "sg:province":"NSW",
    "sg:tags":[
        "hairdresser"
    ],
    "wof:name":"L&#039;Azz Complete Salon",
    "wof:placetype":"venue"
},
  "geometry": {"coordinates":[151.05870056099999,-34.0312919617],"type":"Point"}
}