{
  "type": "Feature",
  "properties": {
    "iso:country":"AU",
    "sg:address":"53 Union Rd",
    "sg:city":"Carmel",
    "sg:classifiers":[
        {
            "category":"Health Services",
            "subcategory":"Health Practitioner",
            "type":"Services"
        }
    ],
    "sg:phone":"+61 8 9293 5190",
    "sg:postcode":"6076",
    "sg:province":"WA",
    "sg:tags":[
        "naturopath"
    ],
    "wof:name":"Gabriel Andrea",
    "wof:placetype":"venue"
},
  "geometry": {"coordinates":[116.101089477,-32.0193634033],"type":"Point"}
}