{
  "type": "Feature",
  "properties": {
    "addr:full":"519 Bells Line Of Road Kurmond NSW 2757",
    "addr:housenumber":"519",
    "addr:postcode":"2757",
    "addr:street":"Bells Line Of Road",
    "iso:country":"AU",
    "sg:address":"519 Bells Line Of Road",
    "sg:city":"Kurmond",
    "sg:classifiers":[
        {
            "category":"Real Estate",
            "subcategory":"Real Estate Agent",
            "type":"Services"
        }
    ],
    "sg:phone":"+61 2 4573 2666",
    "sg:postcode":"2757",
    "sg:province":"NSW",
    "wof:name":"Thompsons The Real Estate People",
    "wof:placetype":"venue"
},
  "geometry": {"coordinates":[150.68971252399999,-33.5507316589],"type":"Point"}
}