{
  "type": "Feature",
  "properties": {
    "addr:full":"128 Chapman Rd Geraldton WA 6530",
    "addr:housenumber":"128",
    "addr:postcode":"6530",
    "addr:street":"Chapman Rd",
    "iso:country":"AU",
    "sg:address":"128 Chapman Rd",
    "sg:city":"Geraldton",
    "sg:classifiers":[
        {
            "category":"Banks & Credit Unions",
            "subcategory":"Financial Services",
            "type":"Services"
        }
    ],
    "sg:phone":"+61 8 9964 5930",
    "sg:postcode":"6530",
    "sg:province":"WA",
    "sg:tags":[
        "planning"
    ],
    "wof:name":"Andrew J Michael",
    "wof:placetype":"venue"
},
  "geometry": {"coordinates":[114.61634826700001,-28.7654056549],"type":"Point"}
}