{
  "type": "Feature",
  "properties": {
    "addr:full":"8 Jaeger Crt High Wycombe WA 6057",
    "addr:housenumber":"8",
    "addr:postcode":"6057",
    "addr:street":"Jaeger Crt",
    "iso:country":"AU",
    "sg:address":"8 Jaeger Crt",
    "sg:city":"High Wycombe",
    "sg:classifiers":[
        {
            "category":"Home & Garden",
            "subcategory":"Building Materials",
            "type":"Retail Goods"
        }
    ],
    "sg:phone":"+61 8 9454 6414",
    "sg:postcode":"6057",
    "sg:province":"WA",
    "sg:tags":[
        "concrete",
        "panel",
        "pre-cast"
    ],
    "wof:name":"Triad Concrete Services",
    "wof:placetype":"venue"
},
  "geometry": {"coordinates":[116.00190734900001,-31.9517498016],"type":"Point"}
}