{
  "type": "Feature",
  "properties": {
    "addr:full":"1st Floor Jane St Morwell VIC 3840",
    "addr:postcode":"3840",
    "addr:street":"St",
    "iso:country":"AU",
    "sg:address":"1st Floor Jane St",
    "sg:city":"Morwell",
    "sg:classifiers":[
        {
            "category":"Bars & Pubs",
            "subcategory":"Lounge",
            "type":"Food & Drink"
        }
    ],
    "sg:phone":"+61 1800 555 525",
    "sg:postcode":"3840",
    "sg:province":"VIC",
    "sg:tags":[
        "water",
        "filter",
        "drinking"
    ],
    "wof:name":"Cool Aqua Springs",
    "wof:placetype":"venue"
},
  "geometry": {"coordinates":[146.39884948700001,-38.2378196716],"type":"Point"}
}