{
  "type": "Feature",
  "properties": {
    "addr:full":"54-62 Gertrude St Fitzroy VIC 3065",
    "addr:housenumber":"54-62",
    "addr:postcode":"3065",
    "addr:street":"Gertrude St",
    "iso:country":"AU",
    "sg:address":"54-62 Gertrude St",
    "sg:city":"Fitzroy",
    "sg:classifiers":[
        {
            "category":"Personal",
            "type":"Services"
        }
    ],
    "sg:phone":"+61 3 8413 8413",
    "sg:postcode":"3065",
    "sg:province":"VIC",
    "sg:tags":[
        "counselling",
        "alcohol",
        "drug"
    ],
    "wof:name":"Turning Point Alcohol & Drug Centre Inc",
    "wof:placetype":"venue"
},
  "geometry": {"coordinates":[144.97596740700001,-37.8057327271],"type":"Point"}
}