{
  "type": "Feature",
  "properties": {
    "iso:country":"AU",
    "sg:address":"1/ 45 Rangers Rd",
    "sg:city":"Cremorne",
    "sg:classifiers":[
        {
            "category":"Professional",
            "subcategory":"Employment Agencies",
            "type":"Services"
        }
    ],
    "sg:phone":"+61 2 9953 0599",
    "sg:postcode":"2090",
    "sg:province":"NSW",
    "wof:name":"Creative Placements",
    "wof:placetype":"venue"
},
  "geometry": {"coordinates":[151.22779846200001,-33.8336257935],"type":"Point"}
}