{
  "type": "Feature",
  "properties": {
    "addr:full":"5 Mindi Crt Cashmere QLD 4500",
    "addr:housenumber":"5",
    "addr:postcode":"4500",
    "addr:street":"Mindi Crt",
    "iso:country":"AU",
    "sg:address":"5 Mindi Crt",
    "sg:city":"Cashmere",
    "sg:classifiers":[
        {
            "category":"Building & Trades",
            "subcategory":"Construction",
            "type":"Services"
        }
    ],
    "sg:phone":"+61 7 3882 4440",
    "sg:postcode":"4500",
    "sg:province":"QLD",
    "sg:tags":[
        "home",
        "air conditioning"
    ],
    "wof:name":"Ambient Air Pty Ltd",
    "wof:placetype":"venue"
},
  "geometry": {"coordinates":[152.937225342,-27.2958393097],"type":"Point"}
}