{
  "type": "Feature",
  "properties": {
    "addr:full":"214 Mulgrave Rd Westcourt QLD 4870",
    "addr:housenumber":"214",
    "addr:postcode":"4870",
    "addr:street":"Mulgrave Rd",
    "iso:country":"AU",
    "sg:address":"214 Mulgrave Rd",
    "sg:city":"Westcourt",
    "sg:classifiers":[
        {
            "category":"Fast Food",
            "type":"Food & Drink"
        }
    ],
    "sg:phone":"+61 7 4031 4321",
    "sg:postcode":"4870",
    "sg:province":"QLD",
    "sg:tags":[
        "away",
        "take"
    ],
    "wof:name":"Kebab King",
    "wof:placetype":"venue"
},
  "geometry": {"coordinates":[145.75152587900001,-16.9360332489],"type":"Point"}
}