{
  "type": "Feature",
  "properties": {
    "addr:full":"7 Hackney Rd Hackney SA 5069",
    "addr:housenumber":"7",
    "addr:postcode":"5069",
    "addr:street":"Hackney Rd",
    "iso:country":"AU",
    "sg:address":"7 Hackney Rd",
    "sg:city":"Hackney",
    "sg:classifiers":[
        {
            "category":"Professional",
            "subcategory":"Accounting & Tax Preparation",
            "type":"Services"
        }
    ],
    "sg:phone":"+61 8 8363 0499",
    "sg:postcode":"5069",
    "sg:province":"SA",
    "sg:tags":[
        "consultant",
        "taxation"
    ],
    "wof:name":"Advantage Accountants (SA)",
    "wof:placetype":"venue"
},
  "geometry": {"coordinates":[138.61508178700001,-34.9184341431],"type":"Point"}
}