{
  "type": "Feature",
  "properties": {
    "iso:country":"AU",
    "sg:address":"55 Benara Rd",
    "sg:city":"Caversham",
    "sg:classifiers":[
        {
            "category":"Shopping",
            "subcategory":"Crafts & Fabrics",
            "type":"Retail Goods"
        }
    ],
    "sg:phone":"+61 8 9378 6035",
    "sg:postcode":"6055",
    "sg:province":"WA",
    "sg:tags":[
        "supply"
    ],
    "wof:name":"Arts Crafts & Cuppas",
    "wof:placetype":"venue"
},
  "geometry": {"coordinates":[115.969017,-31.875845],"type":"Point"}
}