{
  "type": "Feature",
  "properties": {
    "iso:country":"AU",
    "sg:address":"231 Anderson Creek Rd",
    "sg:city":"Doncaster East",
    "sg:classifiers":[
        {
            "category":"Food & Beverages",
            "subcategory":"Groceries & Convenience Stores",
            "type":"Retail Goods"
        }
    ],
    "sg:phone":"+61 3 9846 1988",
    "sg:postcode":"3109",
    "sg:province":"VIC",
    "wof:name":"Yu Lei Milk Bar",
    "wof:placetype":"venue"
},
  "geometry": {"coordinates":[145.173431397,-37.7559509277],"type":"Point"}
}