{
  "type": "Feature",
  "properties": {
    "iso:country":"AU",
    "sg:address":"40 Melview Drv",
    "sg:city":"Werribee",
    "sg:classifiers":[
        {
            "category":"Education",
            "subcategory":"School",
            "type":"Public Place"
        }
    ],
    "sg:phone":"+61 3 9742 7524",
    "sg:postcode":"3030",
    "sg:province":"VIC",
    "wof:name":"Home Schooling Supplies (Aust)",
    "wof:placetype":"venue"
},
  "geometry": {"coordinates":[144.61677599999999,-37.894718],"type":"Point"}
}