{
  "type": "Feature",
  "properties": {
    "iso:country":"AU",
    "sg:address":"1- 3 Greenaway St",
    "sg:city":"Bulleen",
    "sg:classifiers":[
        {
            "category":"Retail",
            "subcategory":"Auto Repair",
            "type":"Services"
        }
    ],
    "sg:phone":"+61 3 9852 0811",
    "sg:postcode":"3105",
    "sg:province":"VIC",
    "sg:tags":[
        "clutch",
        "brake"
    ],
    "wof:name":"DBS Disk Brake Services",
    "wof:placetype":"venue"
},
  "geometry": {"coordinates":[145.082489014,-37.7609291077],"type":"Point"}
}