{
  "type": "Feature",
  "properties": {
    "addr:full":"Cnr Market St & Pitt Street Mall Sydney NSW 2000",
    "addr:postcode":"2000",
    "addr:street":"Market St & Pitt Street Mall",
    "iso:country":"AU",
    "sg:address":"Cnr Market St",
    "sg:city":"& Pitt Street Mall Sydney",
    "sg:classifiers":[
        {
            "category":"Fast Food",
            "type":"Food & Drink"
        }
    ],
    "sg:phone":"+61 2 9223 1400",
    "sg:postcode":"2000",
    "sg:province":"NSW",
    "sg:tags":[
        "away",
        "take"
    ],
    "wof:name":"Khao Thai Pty Ltd",
    "wof:placetype":"venue"
},
  "geometry": {"coordinates":[151.210113525,-33.870716095],"type":"Point"}
}