{
  "type": "Feature",
  "properties": {
    "addr:full":"Shop 68 Golden Grove SA 5125",
    "addr:housenumber":"shop 68",
    "addr:postcode":"5125",
    "iso:country":"AU",
    "sg:address":"Shop 68",
    "sg:city":"Golden Grove",
    "sg:classifiers":[
        {
            "category":"Shopping",
            "subcategory":"Jewelry",
            "type":"Retail Goods"
        }
    ],
    "sg:phone":"+61 8 8289 3222",
    "sg:postcode":"5125",
    "sg:province":"SA",
    "sg:tags":[
        "jeweller"
    ],
    "wof:name":"Shiels",
    "wof:placetype":"venue"
},
  "geometry": {"coordinates":[138.715958,-34.775261],"type":"Point"}
}