{
  "type": "Feature",
  "properties": {
    "addr:full":"Lv 1, 300 George St Windsor NSW 2756",
    "addr:housenumber":"300",
    "addr:postcode":"2756",
    "addr:street":"George St",
    "iso:country":"AU",
    "sg:address":"Lv 1, 300 George St",
    "sg:city":"Windsor",
    "sg:classifiers":[
        {
            "category":"Sports & Exercise",
            "subcategory":"Gym",
            "type":"Entertainment"
        }
    ],
    "sg:phone":"+61 1300 287 837",
    "sg:postcode":"2756",
    "sg:province":"NSW",
    "sg:tags":[
        "health",
        "fitness"
    ],
    "wof:name":"Curves Windsor",
    "wof:placetype":"venue"
},
  "geometry": {"coordinates":[150.817428589,-33.6090126038],"type":"Point"}
}