{
  "type": "Feature",
  "properties": {
    "addr:full":"2765 Kararra Rd Cambooya QLD 4358",
    "addr:housenumber":"2765",
    "addr:postcode":"4358",
    "addr:street":"Kararra Rd",
    "iso:country":"AU",
    "sg:address":"2765 Kararra Rd",
    "sg:city":"Cambooya",
    "sg:classifiers":[
        {
            "category":"Utilities",
            "subcategory":"Fuel Oil & Lpg",
            "type":"Services"
        }
    ],
    "sg:phone":"+61 7 4695 8190",
    "sg:postcode":"4358",
    "sg:province":"QLD",
    "sg:tags":[
        "merchant"
    ],
    "wof:name":"Felton Fuel Supplies",
    "wof:placetype":"venue"
},
  "geometry": {"coordinates":[151.873627,-27.708389],"type":"Point"}
}