{
  "type": "Feature",
  "properties": {
    "iso:country":"AU",
    "sg:address":"29 Kedron Ave",
    "sg:city":"Mitchelton",
    "sg:classifiers":[
        {
            "category":"Education",
            "subcategory":"Kindergarten",
            "type":"Public Place"
        }
    ],
    "sg:phone":"+61 7 3355 2535",
    "sg:postcode":"4053",
    "sg:province":"QLD",
    "sg:tags":[
        "pre-schools"
    ],
    "wof:name":"Mitchelton Preschooling Centre",
    "wof:placetype":"venue"
},
  "geometry": {"coordinates":[152.97561645499999,-27.4133415222],"type":"Point"}
}