{
  "type": "Feature",
  "properties": {
    "addr:full":"Kelso St Coldstream VIC 3770",
    "addr:postcode":"3770",
    "addr:street":"Kelso St",
    "iso:country":"AU",
    "sg:address":"Kelso St",
    "sg:city":"Coldstream",
    "sg:classifiers":[
        {
            "category":"Social Services",
            "subcategory":"Child Care",
            "type":"Services"
        }
    ],
    "sg:phone":"+61 3 9739 1343",
    "sg:postcode":"3770",
    "sg:province":"VIC",
    "sg:tags":[
        "support",
        "health"
    ],
    "wof:name":"Maternal & Child Health Centres",
    "wof:placetype":"venue"
},
  "geometry": {"coordinates":[145.382812,-37.731621],"type":"Point"}
}