{
  "type": "Feature",
  "properties": {
    "iso:country":"AU",
    "sg:address":"13 Riverside Drv",
    "sg:city":"Narooma",
    "sg:classifiers":[
        {
            "category":"Cafe",
            "type":"Food & Drink"
        }
    ],
    "sg:phone":"+61 2 4476 2723",
    "sg:postcode":"2546",
    "sg:province":"NSW",
    "wof:name":"Narooma Quarterdeck Marina",
    "wof:placetype":"venue"
},
  "geometry": {"coordinates":[150.122436523,-36.2123184204],"type":"Point"}
}