{
  "type": "Feature",
  "properties": {
    "addr:full":"U1/ 13 Cook Pde Lemon Tree Passage NSW 2319",
    "addr:housenumber":"13",
    "addr:postcode":"2319",
    "addr:street":"U1 /;Pde",
    "iso:country":"AU",
    "sg:address":"U1/ 13 Cook Pde",
    "sg:city":"Lemon Tree Passage",
    "sg:classifiers":[
        {
            "category":"Communications",
            "subcategory":"Film & Video Production",
            "type":"Services"
        }
    ],
    "sg:phone":"+61 2 4982 4230",
    "sg:postcode":"2319",
    "sg:province":"NSW",
    "sg:tags":[
        "dvd",
        "library"
    ],
    "wof:name":"Lemon Tree Passage Video Barn",
    "wof:placetype":"venue"
},
  "geometry": {"coordinates":[152.03945899999999,-32.731068],"type":"Point"}
}