{
  "type": "Feature",
  "properties": {
    "addr:full":"116a Darling St Dubbo NSW 2830",
    "addr:housenumber":"116a",
    "addr:postcode":"2830",
    "addr:street":"Darling St",
    "iso:country":"AU",
    "sg:address":"116a Darling St",
    "sg:city":"Dubbo",
    "sg:classifiers":[
        {
            "category":"Social Services",
            "type":"Services"
        }
    ],
    "sg:phone":"+61 2 6881 8755",
    "sg:postcode":"2830",
    "sg:province":"NSW",
    "sg:tags":[
        "disabled",
        "person",
        "equipment"
    ],
    "wof:name":"Bike Shoppe The",
    "wof:placetype":"venue"
},
  "geometry": {"coordinates":[148.60604858400001,-32.2486076355],"type":"Point"}
}