{
  "type": "Feature",
  "properties": {
    "iso:country":"AU",
    "sg:address":"1 Raasay Pl",
    "sg:city":"Warwick",
    "sg:classifiers":[
        {
            "category":"Shopping",
            "subcategory":"Stationery & Office Supplies",
            "type":"Retail Goods"
        }
    ],
    "sg:phone":"+61 8 9447 3712",
    "sg:postcode":"6024",
    "sg:province":"WA",
    "sg:tags":[
        "equipment",
        "sailboarding"
    ],
    "wof:name":"Shoreline Sails & Marine",
    "wof:placetype":"venue"
},
  "geometry": {"coordinates":[115.79950714100001,-31.8415565491],"type":"Point"}
}