{
  "type": "Feature",
  "properties": {
    "addr:full":"483 Great Eastern Hwy Redcliffe WA 6104",
    "addr:housenumber":"483",
    "addr:postcode":"6104",
    "addr:street":"Great Eastern Hwy",
    "iso:country":"AU",
    "sg:address":"483 Great Eastern Hwy",
    "sg:city":"Redcliffe",
    "sg:classifiers":[
        {
            "category":"Building & Trades",
            "subcategory":"Construction",
            "type":"Services"
        }
    ],
    "sg:phone":"+61 8 9478 2633",
    "sg:postcode":"6104",
    "sg:province":"WA",
    "sg:tags":[
        "monumental",
        "mason"
    ],
    "wof:name":"Perth Monumental Works",
    "wof:placetype":"venue"
},
  "geometry": {"coordinates":[115.949836731,-31.9273948669],"type":"Point"}
}