{
  "type": "Feature",
  "properties": {
    "addr:full":"RMB 320 Sutton Rd via Queanbeyan Queanbeyan NSW 2620",
    "addr:postcode":"2620",
    "addr:street":"Sutton Rd Via Queanbeyan",
    "iso:country":"AU",
    "sg:address":"RMB 320 Sutton Rd via Queanbeyan",
    "sg:city":"Queanbeyan",
    "sg:classifiers":[
        {
            "category":"Professional",
            "subcategory":"Computer Services",
            "type":"Services"
        }
    ],
    "sg:phone":"+61 2 6297 1160",
    "sg:postcode":"2620",
    "sg:province":"NSW",
    "sg:tags":[
        "consultant",
        "system"
    ],
    "wof:name":"Data Science Pty Ltd",
    "wof:placetype":"venue"
},
  "geometry": {"coordinates":[149.26255798299999,-35.2560195923],"type":"Point"}
}