{
  "type": "Feature",
  "properties": {
    "iso:country":"AU",
    "sg:address":"PO Box 120",
    "sg:city":"Drysdale",
    "sg:classifiers":[
        {
            "category":"Building & Trades",
            "subcategory":"Plumbing",
            "type":"Services"
        }
    ],
    "sg:phone":"+61 3 5251 3193",
    "sg:postcode":"3222",
    "sg:province":"VIC",
    "sg:tags":[
        "plumber",
        "gasfitters"
    ],
    "wof:name":"Peter Christiaans Plumbing & Gasfitting",
    "wof:placetype":"venue"
},
  "geometry": {"coordinates":[144.590103,-38.153461],"type":"Point"}
}