{
  "type": "Feature",
  "properties": {
    "addr:full":"21 High St Kimba SA 5641",
    "addr:housenumber":"21",
    "addr:postcode":"5641",
    "addr:street":"High St",
    "iso:country":"AU",
    "sg:address":"21 High St",
    "sg:city":"Kimba",
    "sg:classifiers":[
        {
            "category":"Health Services",
            "subcategory":"Dentist",
            "type":"Services"
        }
    ],
    "sg:phone":"+61 8 8627 2445",
    "sg:postcode":"5641",
    "sg:province":"SA",
    "wof:name":"Dental On Eyre",
    "wof:placetype":"venue"
},
  "geometry": {"coordinates":[136.41874694800001,-33.1405754089],"type":"Point"}
}