{
  "type": "Feature",
  "properties": {
    "iso:country":"AU",
    "sg:address":"750 Gympie Rd",
    "sg:city":"Chermside",
    "sg:classifiers":[
        {
            "category":"Autos & Motor Vehicles",
            "subcategory":"Auto Supplies",
            "type":"Retail Goods"
        }
    ],
    "sg:phone":"+61 7 3359 4930",
    "sg:postcode":"4032",
    "sg:province":"QLD",
    "sg:tags":[
        "accessory"
    ],
    "wof:name":"Super Cheap Auto",
    "wof:placetype":"venue"
},
  "geometry": {"coordinates":[153.030914,-27.387705],"type":"Point"}
}