{
  "type": "Feature",
  "properties": {
    "iso:country":"AU",
    "sg:address":"45 Thornbill Drv",
    "sg:city":"Carrum Downs",
    "sg:classifiers":[
        {
            "category":"Building & Trades",
            "subcategory":"Construction",
            "type":"Services"
        }
    ],
    "sg:phone":"+61 415 329 839",
    "sg:postcode":"3201",
    "sg:province":"VIC",
    "sg:tags":[
        "contractor"
    ],
    "wof:name":"W & L Rennovations",
    "wof:placetype":"venue"
},
  "geometry": {"coordinates":[145.18277,-38.111862],"type":"Point"}
}