{
  "type": "Feature",
  "properties": {
    "iso:country":"AU",
    "sg:address":"40 Lemnos North Rd",
    "sg:city":"Lemnos",
    "sg:classifiers":[
        {
            "category":"Home & Garden",
            "subcategory":"Building Materials",
            "type":"Retail Goods"
        }
    ],
    "sg:phone":"+61 3 5829 9209",
    "sg:postcode":"3631",
    "sg:province":"VIC",
    "sg:tags":[
        "pre-mixed",
        "concrete"
    ],
    "wof:name":"Country Concrete Pty Ltd",
    "wof:placetype":"venue"
},
  "geometry": {"coordinates":[145.462234497,-36.361076355],"type":"Point"}
}