{
  "type": "Feature",
  "properties": {
    "iso:country":"AU",
    "sg:address":"14 Locke St",
    "sg:city":"Orana",
    "sg:classifiers":[
        {
            "category":"Professional",
            "type":"Services"
        }
    ],
    "sg:phone":"+61 8 9842 2422",
    "sg:postcode":"6330",
    "sg:province":"WA",
    "sg:tags":[
        "spray",
        "painting"
    ],
    "wof:name":"Dawes Richard",
    "wof:placetype":"venue"
},
  "geometry": {"coordinates":[117.863449097,-34.9985198975],"type":"Point"}
}