{
  "type": "Feature",
  "properties": {
    "iso:country":"AU",
    "sg:address":"7 Franklin Crt",
    "sg:city":"Golden Grove",
    "sg:classifiers":[
        {
            "category":"Building & Trades",
            "subcategory":"Landscaping Services",
            "type":"Services"
        }
    ],
    "sg:phone":"+61 419 852 027",
    "sg:postcode":"5125",
    "sg:province":"SA",
    "sg:tags":[
        "designer",
        "landscape",
        "contractor"
    ],
    "wof:name":"Graceland Gardeners & Landscapers",
    "wof:placetype":"venue"
},
  "geometry": {"coordinates":[138.705505,-34.781609],"type":"Point"}
}