{
  "type": "Feature",
  "properties": {
    "iso:country":"AU",
    "sg:address":"43 Planet St",
    "sg:city":"Carlisle",
    "sg:classifiers":[
        {
            "category":"Shopping",
            "subcategory":"Music",
            "type":"Retail Goods"
        }
    ],
    "sg:phone":"+61 8 9361 9469",
    "sg:postcode":"6101",
    "sg:province":"WA",
    "sg:tags":[
        "store"
    ],
    "wof:name":"Soundwave Distributors (WA)",
    "wof:placetype":"venue"
},
  "geometry": {"coordinates":[115.912742615,-31.9765987396],"type":"Point"}
}