{
  "type": "Feature",
  "properties": {
    "addr:full":"U4/ 8 Royal St Kenwick WA 6107",
    "addr:housenumber":"8",
    "addr:postcode":"6107",
    "addr:street":"U4 /;Royal St",
    "iso:country":"AU",
    "sg:address":"U4/ 8 Royal St",
    "sg:city":"Kenwick",
    "sg:classifiers":[
        {
            "category":"Autos & Motor Vehicles",
            "subcategory":"Auto Supplies",
            "type":"Retail Goods"
        }
    ],
    "sg:phone":"+61 8 9459 3469",
    "sg:postcode":"6107",
    "sg:province":"WA",
    "sg:tags":[
        "part",
        "cycles",
        "accessory"
    ],
    "wof:name":"Marias Custom Leather",
    "wof:placetype":"venue"
},
  "geometry": {"coordinates":[115.96824646,-32.0377616882],"type":"Point"}
}