{
  "type": "Feature",
  "properties": {
    "iso:country":"AU",
    "sg:address":"Shop 622",
    "sg:city":"Chirnside Park Shopng Cntr Chirnside Park",
    "sg:classifiers":[
        {
            "category":"Personal",
            "subcategory":"Beauty Salon",
            "type":"Services"
        }
    ],
    "sg:phone":"+61 3 9726 5440",
    "sg:postcode":"3116",
    "sg:province":"VIC",
    "sg:tags":[
        "hairdresser"
    ],
    "wof:name":"Ians Hairdressing",
    "wof:placetype":"venue"
},
  "geometry": {"coordinates":[145.321655273,-37.7562484741],"type":"Point"}
}