{
  "type": "Feature",
  "properties": {
    "addr:full":"Gardens Oval Gilruth Ave Darwin NT 0800",
    "addr:postcode":"nt 0800",
    "addr:street":"Ave",
    "iso:country":"AU",
    "sg:address":"Gardens Oval Gilruth Ave",
    "sg:city":"Darwin",
    "sg:classifiers":[
        {
            "category":"Retail",
            "subcategory":"Event Space",
            "type":"Services"
        }
    ],
    "sg:phone":"+61 8 8981 6326",
    "sg:postcode":"0800",
    "sg:province":"NT",
    "sg:tags":[
        "function",
        "organiser"
    ],
    "wof:name":"Waratah Sports Club Inc",
    "wof:placetype":"venue"
},
  "geometry": {"coordinates":[130.83052063,-12.4521808624],"type":"Point"}
}