{
  "type": "Feature",
  "properties": {
    "iso:country":"AU",
    "sg:address":"48 Central Ave",
    "sg:city":"Oak Flats",
    "sg:classifiers":[
        {
            "category":"Professional",
            "subcategory":"Computer Services",
            "type":"Services"
        }
    ],
    "sg:phone":"+61 1800 052 222",
    "sg:postcode":"2529",
    "sg:province":"NSW",
    "sg:tags":[
        "information"
    ],
    "wof:name":"Commonwealth Carelink Centre",
    "wof:placetype":"venue"
},
  "geometry": {"coordinates":[150.81959533700001,-34.5654678345],"type":"Point"}
}