{
  "type": "Feature",
  "properties": {
    "iso:country":"AU",
    "sg:address":"7 Riverview Drv",
    "sg:city":"Berri",
    "sg:classifiers":[
        {
            "category":"Professional",
            "subcategory":"Business Services",
            "type":"Services"
        }
    ],
    "sg:phone":"+61 8 8582 2311",
    "sg:postcode":"5343",
    "sg:province":"SA",
    "sg:tags":[
        "small",
        "advisory"
    ],
    "wof:name":"G P A Accounting Pty Ltd",
    "wof:placetype":"venue"
},
  "geometry": {"coordinates":[140.601394653,-34.2879219055],"type":"Point"}
}