{
  "type": "Feature",
  "properties": {
    "addr:full":"328 Gooch St Thornbury VIC 3071",
    "addr:housenumber":"328",
    "addr:postcode":"3071",
    "addr:street":"Gooch St",
    "iso:country":"AU",
    "sg:address":"328 Gooch St",
    "sg:city":"Thornbury",
    "sg:classifiers":[
        {
            "category":"Retail",
            "subcategory":"Auto Repair",
            "type":"Services"
        }
    ],
    "sg:phone":"+61 3 9484 7787",
    "sg:postcode":"3071",
    "sg:province":"VIC",
    "sg:tags":[
        "beater",
        "painter",
        "panel"
    ],
    "wof:name":"C N D Automotive Repairs Pty Ltd",
    "wof:placetype":"venue"
},
  "geometry": {"coordinates":[145.02574157699999,-37.7606582642],"type":"Point"}
}