{
  "type": "Feature",
  "properties": {
    "addr:full":"Suite 1/ 6 Abbotsford St Leederville WA 6007",
    "addr:postcode":"6007",
    "addr:street":"Abbotsford St",
    "iso:country":"AU",
    "sg:address":"Suite 1/ 6 Abbotsford St",
    "sg:city":"Leederville",
    "sg:classifiers":[
        {
            "category":"Health Services",
            "subcategory":"Health Practitioner",
            "type":"Services"
        }
    ],
    "sg:phone":"+61 8 9388 3767",
    "sg:postcode":"6007",
    "sg:province":"WA",
    "sg:tags":[
        "psychologist"
    ],
    "wof:name":"Menaglio Darryl Dr",
    "wof:placetype":"venue"
},
  "geometry": {"coordinates":[115.837982178,-31.9410839081],"type":"Point"}
}