{
  "type": "Feature",
  "properties": {
    "addr:full":"20 Anderson St Mooroopna VIC 3629",
    "addr:housenumber":"20",
    "addr:postcode":"3629",
    "addr:street":"Anderson St",
    "iso:country":"AU",
    "sg:address":"20 Anderson St",
    "sg:city":"Mooroopna",
    "sg:classifiers":[
        {
            "category":"Personal",
            "type":"Services"
        }
    ],
    "sg:phone":"+61 3 5825 3763",
    "sg:postcode":"3629",
    "sg:province":"VIC",
    "sg:tags":[
        "dressmaker"
    ],
    "wof:name":"Liola 1",
    "wof:placetype":"venue"
},
  "geometry": {"coordinates":[145.348220825,-36.3774414062],"type":"Point"}
}