{
  "type": "Feature",
  "properties": {
    "addr:full":"Unit 1/ 44 Proprietory St Tingalpa QLD 4173",
    "addr:postcode":"4173",
    "addr:street":"44 Proprietory St",
    "iso:country":"AU",
    "sg:address":"Unit 1/ 44 Proprietory St",
    "sg:city":"Tingalpa",
    "sg:classifiers":[
        {
            "category":"Professional",
            "type":"Services"
        }
    ],
    "sg:phone":"+61 7 3390 8377",
    "sg:postcode":"4173",
    "sg:province":"QLD",
    "sg:tags":[
        "forwarding",
        "agent",
        "transport"
    ],
    "wof:name":"Intergroup Australia Pty Ltd",
    "wof:placetype":"venue"
},
  "geometry": {"coordinates":[153.10723876899999,-27.4742565155],"type":"Point"}
}