{
  "type": "Feature",
  "properties": {
    "iso:country":"AU",
    "sg:address":"127 Archer St",
    "sg:city":"North Adelaide",
    "sg:classifiers":[
        {
            "category":"Shopping",
            "subcategory":"Clothing, Apparel, & Fashions",
            "type":"Retail Goods"
        }
    ],
    "sg:phone":"+61 8 8239 0434",
    "sg:postcode":"5006",
    "sg:province":"SA",
    "sg:tags":[
        "recycled",
        "clothing"
    ],
    "wof:name":"The Siren Room",
    "wof:placetype":"venue"
},
  "geometry": {"coordinates":[138.59614563,-34.9074783325],"type":"Point"}
}