{
  "type": "Feature",
  "properties": {
    "iso:country":"AU",
    "sg:address":"Shp1/ 7 Pendrigh Pl",
    "sg:city":"St Helens",
    "sg:classifiers":[
        {
            "category":"Cafe",
            "type":"Food & Drink"
        }
    ],
    "sg:phone":"+61 3 6376 1001",
    "sg:postcode":"7216",
    "sg:province":"TAS",
    "wof:name":"Something Fabulous",
    "wof:placetype":"venue"
},
  "geometry": {"coordinates":[148.25074799999999,-41.322685],"type":"Point"}
}