{
  "type": "Feature",
  "properties": {
    "addr:full":"Taylor Rd One Tree Hill SA 5114",
    "addr:postcode":"5114",
    "addr:street":"Taylor Rd One",
    "iso:country":"AU",
    "sg:address":"Taylor Rd",
    "sg:city":"One Tree Hill",
    "sg:classifiers":[
        {
            "category":"Building & Trades",
            "subcategory":"Cleaning & Sanitation",
            "type":"Services"
        }
    ],
    "sg:phone":"+61 8 8280 7348",
    "sg:postcode":"5114",
    "sg:province":"SA",
    "sg:tags":[
        "cleaner",
        "repairer",
        "roof"
    ],
    "wof:name":"Town & Country Roofing",
    "wof:placetype":"venue"
},
  "geometry": {"coordinates":[138.791473389,-34.7100143433],"type":"Point"}
}