{
  "type": "Feature",
  "properties": {
    "iso:country":"AU",
    "sg:address":"Level 10, 114 Albert Rd",
    "sg:city":"South Melbourne",
    "sg:classifiers":[
        {
            "category":"Health Services",
            "subcategory":"Health Practitioner",
            "type":"Services"
        }
    ],
    "sg:phone":"+61 3 9693 6488",
    "sg:postcode":"3205",
    "sg:province":"VIC",
    "sg:tags":[
        "hypnotherapy"
    ],
    "wof:name":"Equilibrium Counselling & Hypnotherapy",
    "wof:placetype":"venue"
},
  "geometry": {"coordinates":[144.96992499999999,-37.835842],"type":"Point"}
}