{
  "type": "Feature",
  "properties": {
    "iso:country":"AU",
    "sg:address":"Cnr Fulham Rd & Nathan St",
    "sg:city":"Vincent",
    "sg:classifiers":[
        {
            "category":"Health Services",
            "subcategory":"Doctor",
            "type":"Services"
        }
    ],
    "sg:phone":"+61 7 4779 3333",
    "sg:postcode":"4814",
    "sg:province":"QLD",
    "sg:tags":[
        "medical",
        "practitioner"
    ],
    "wof:name":"Skinworx",
    "wof:placetype":"venue"
},
  "geometry": {"coordinates":[146.765182,-19.288883],"type":"Point"}
}