{
  "type": "Feature",
  "properties": {
    "iso:country":"AU",
    "sg:address":"138 Mollison St",
    "sg:city":"Bendigo",
    "sg:classifiers":[
        {
            "category":"Sports & Exercise",
            "subcategory":"Gym",
            "type":"Entertainment"
        }
    ],
    "sg:phone":"+61 3 5441 4054",
    "sg:postcode":"3550",
    "sg:province":"VIC",
    "sg:tags":[
        "personal",
        "trainer",
        "fitness"
    ],
    "wof:name":"One Stop Mobile Fitness",
    "wof:placetype":"venue"
},
  "geometry": {"coordinates":[144.28306579599999,-36.7630577087],"type":"Point"}
}