{
  "type": "Feature",
  "properties": {
    "addr:full":"8 Jonstone St Annandale NSW 2038",
    "addr:housenumber":"8",
    "addr:postcode":"2038",
    "addr:street":"Jonstone St",
    "iso:country":"AU",
    "sg:address":"8 Jonstone St",
    "sg:city":"Annandale",
    "sg:classifiers":[
        {
            "category":"Real Estate",
            "subcategory":"Real Estate Agent",
            "type":"Services"
        }
    ],
    "sg:phone":"+61 2 9550 0200",
    "sg:postcode":"2038",
    "sg:province":"NSW",
    "wof:name":"Raine & Horne Annandale",
    "wof:placetype":"venue"
},
  "geometry": {"coordinates":[151.16763305699999,-33.8876609802],"type":"Point"}
}