{
  "type": "Feature",
  "properties": {
    "iso:country":"AU",
    "sg:address":"PO Box 901",
    "sg:city":"Strathalbyn",
    "sg:classifiers":[
        {
            "category":"Home & Garden",
            "subcategory":"Carpets & Floor Coverings",
            "type":"Retail Goods"
        }
    ],
    "sg:phone":"+61 418 805 321",
    "sg:postcode":"5255",
    "sg:province":"SA",
    "sg:tags":[
        "layer",
        "planner"
    ],
    "wof:name":"Solitaire Floors",
    "wof:placetype":"venue"
},
  "geometry": {"coordinates":[138.892333984,-35.2590713501],"type":"Point"}
}