{
  "type": "Feature",
  "properties": {
    "addr:full":"10 Simms Rd Greensborough VIC 3088",
    "addr:housenumber":"10",
    "addr:postcode":"3088",
    "addr:street":"Simms Rd",
    "iso:country":"AU",
    "sg:address":"10 Simms Rd",
    "sg:city":"Greensborough",
    "sg:classifiers":[
        {
            "category":"Building & Trades",
            "subcategory":"Pest Control",
            "type":"Services"
        }
    ],
    "sg:phone":"+61 3 9434 4588",
    "sg:postcode":"3088",
    "sg:province":"VIC",
    "sg:tags":[
        "controller",
        "automatic"
    ],
    "wof:name":"Ronan Engineering (Aust) Pty Ltd",
    "wof:placetype":"venue"
},
  "geometry": {"coordinates":[145.113815308,-37.7118682861],"type":"Point"}
}