{
  "type": "Feature",
  "properties": {
    "addr:full":"7 Frank St Newton SA 5074",
    "addr:housenumber":"7",
    "addr:postcode":"5074",
    "addr:street":"Frank St",
    "iso:country":"AU",
    "sg:address":"7 Frank St",
    "sg:city":"Newton",
    "sg:classifiers":[
        {
            "category":"Building & Trades",
            "subcategory":"Construction",
            "type":"Services"
        }
    ],
    "sg:phone":"+61 8 8336 8268",
    "sg:postcode":"5074",
    "sg:province":"SA",
    "sg:tags":[
        "contractor"
    ],
    "wof:name":"De Ieso Olinto",
    "wof:placetype":"venue"
},
  "geometry": {"coordinates":[138.67918395999999,-34.8769226074],"type":"Point"}
}