{
  "type": "Feature",
  "properties": {
    "iso:country":"AU",
    "sg:address":"Bowra St",
    "sg:city":"Urunga",
    "sg:classifiers":[
        {
            "category":"Banks & Credit Unions",
            "subcategory":"Financial Services",
            "type":"Services"
        }
    ],
    "sg:phone":"+61 2 6655 6677",
    "sg:postcode":"2455",
    "sg:province":"NSW",
    "sg:tags":[
        "loan",
        "finance",
        "mortgage"
    ],
    "wof:name":"BCU Bananacoast Community Credit Union Ltd",
    "wof:placetype":"venue"
},
  "geometry": {"coordinates":[153.01876799999999,-30.495607],"type":"Point"}
}