{
  "type": "Feature",
  "properties": {
    "iso:country":"AU",
    "sg:address":"Red Hill Rd",
    "sg:city":"Bacchus Marsh",
    "sg:classifiers":[
        {
            "category":"Commercial Area",
            "type":"Public Place"
        }
    ],
    "sg:phone":"+61 3 5367 1496",
    "sg:postcode":"3340",
    "sg:province":"VIC",
    "sg:tags":[
        "heavy",
        "carrier"
    ],
    "wof:name":"Bacchus Marsh Water Cartage",
    "wof:placetype":"venue"
},
  "geometry": {"coordinates":[144.435562,-37.67474],"type":"Point"}
}