{
  "type": "Feature",
  "properties": {
    "iso:country":"AU",
    "sg:address":"Unit 7, 335 Hillsborough Rd",
    "sg:city":"Warners Bay",
    "sg:classifiers":[
        {
            "category":"Real Estate",
            "subcategory":"Surveying",
            "type":"Services"
        }
    ],
    "sg:phone":"+61 2 4978 5100",
    "sg:postcode":"2282",
    "sg:province":"NSW",
    "sg:tags":[
        "surveyor",
        "land"
    ],
    "wof:name":"Asquith & deWitt Pty Ltd",
    "wof:placetype":"venue"
},
  "geometry": {"coordinates":[151.65530395499999,-32.9660644531],"type":"Point"}
}