{
  "type": "Feature",
  "properties": {
    "iso:country":"AU",
    "sg:address":"214 Great Western Hwy",
    "sg:city":"Kingswood",
    "sg:classifiers":[
        {
            "category":"Shopping",
            "subcategory":"Clothing, Apparel, & Fashions",
            "type":"Retail Goods"
        }
    ],
    "sg:phone":"+61 2 4721 2457",
    "sg:postcode":"2747",
    "sg:province":"NSW",
    "sg:tags":[
        "lingerie",
        "hosiery",
        "sleepwear"
    ],
    "wof:name":"Jeanine-Maries Clinic Of Beauty Therapy",
    "wof:placetype":"venue"
},
  "geometry": {"coordinates":[150.71875,-33.7585220337],"type":"Point"}
}