{
  "type": "Feature",
  "properties": {
    "addr:full":"3 Creswell Rd Largs North SA 5016",
    "addr:housenumber":"3",
    "addr:postcode":"5016",
    "addr:street":"Creswell Rd",
    "iso:country":"AU",
    "sg:address":"3 Creswell Rd",
    "sg:city":"Largs North",
    "sg:classifiers":[
        {
            "category":"Building & Trades",
            "subcategory":"Construction",
            "type":"Services"
        }
    ],
    "sg:phone":"+61 8 8249 9799",
    "sg:postcode":"5016",
    "sg:province":"SA",
    "sg:tags":[
        "brick",
        "paving"
    ],
    "wof:name":"Landscape Construction Services",
    "wof:placetype":"venue"
},
  "geometry": {"coordinates":[138.504592895,-34.8231658936],"type":"Point"}
}