{
  "type": "Feature",
  "properties": {
    "addr:full":"76a Agincourt Rd North Ryde NSW 2113",
    "addr:housenumber":"76a",
    "addr:postcode":"2113",
    "addr:street":"Agincourt Rd",
    "iso:country":"AU",
    "sg:address":"76a Agincourt Rd",
    "sg:city":"North Ryde",
    "sg:classifiers":[
        {
            "category":"Cafe",
            "type":"Food & Drink"
        }
    ],
    "sg:phone":"+61 2 9889 8977",
    "sg:postcode":"2113",
    "sg:province":"NSW",
    "wof:name":"Gourmet Express",
    "wof:placetype":"venue"
},
  "geometry": {"coordinates":[151.10403442399999,-33.7827033997],"type":"Point"}
}