{
  "type": "Feature",
  "properties": {
    "addr:full":"48 Wingewarra St Dubbo NSW 2830",
    "addr:housenumber":"48",
    "addr:postcode":"2830",
    "addr:street":"Wingewarra St",
    "iso:country":"AU",
    "sg:address":"48 Wingewarra St",
    "sg:city":"Dubbo",
    "sg:classifiers":[
        {
            "category":"Education",
            "subcategory":"Special Training",
            "type":"Public Place"
        }
    ],
    "sg:phone":"+61 2 6885 5000",
    "sg:postcode":"2830",
    "sg:province":"NSW",
    "sg:tags":[
        "development"
    ],
    "wof:name":"OEC Employment",
    "wof:placetype":"venue"
},
  "geometry": {"coordinates":[148.601364136,-32.2488975525],"type":"Point"}
}