{
  "type": "Feature",
  "properties": {
    "iso:country":"AU",
    "sg:address":"2 William St",
    "sg:city":"Rose Bay",
    "sg:classifiers":[
        {
            "category":"Retail",
            "subcategory":"Auto Repair",
            "type":"Services"
        }
    ],
    "sg:phone":"+61 2 9371 5708",
    "sg:postcode":"2029",
    "sg:province":"NSW",
    "sg:tags":[
        "beater",
        "painter",
        "panel"
    ],
    "wof:name":"G F H Smash Repairs Rose Bay",
    "wof:placetype":"venue"
},
  "geometry": {"coordinates":[151.27200317399999,-33.878162384],"type":"Point"}
}