{
  "type": "Feature",
  "properties": {
    "addr:full":"PO Box 433 Caringbah NSW 1495",
    "addr:postcode":"1495",
    "iso:country":"AU",
    "sg:address":"PO Box 433",
    "sg:city":"Caringbah",
    "sg:classifiers":[
        {
            "category":"Real Estate",
            "subcategory":"Real Estate Services",
            "type":"Services"
        }
    ],
    "sg:phone":"+61 412 828 466",
    "sg:postcode":"1495",
    "sg:province":"NSW",
    "sg:tags":[
        "auctioneer"
    ],
    "wof:name":"Professional Property Auctions",
    "wof:placetype":"venue"
},
  "geometry": {"coordinates":[151.121475,-34.046501],"type":"Point"}
}