{
  "type": "Feature",
  "properties": {
    "iso:country":"AU",
    "sg:address":"35- 39 Qantas Drv",
    "sg:city":"Eagle Farm",
    "sg:classifiers":[
        {
            "category":"Freight",
            "type":"Transportation"
        }
    ],
    "sg:phone":"+61 7 3860 5838",
    "sg:postcode":"4009",
    "sg:province":"QLD",
    "sg:tags":[
        "cargo",
        "air"
    ],
    "wof:name":"IEC Express (Australia) Pty Ltd",
    "wof:placetype":"venue"
},
  "geometry": {"coordinates":[153.095413208,-27.4115447998],"type":"Point"}
}