{
  "type": "Feature",
  "properties": {
    "addr:full":"46 Carina Rd Oyster Bay NSW 2225",
    "addr:housenumber":"46",
    "addr:postcode":"2225",
    "addr:street":"Carina Rd",
    "iso:country":"AU",
    "sg:address":"46 Carina Rd",
    "sg:city":"Oyster Bay",
    "sg:classifiers":[
        {
            "category":"Professional",
            "subcategory":"Art Services",
            "type":"Services"
        }
    ],
    "sg:phone":"+61 2 9528 4080",
    "sg:postcode":"2225",
    "sg:province":"NSW",
    "sg:tags":[
        "decorator",
        "painter"
    ],
    "wof:name":"Peach & Peach",
    "wof:placetype":"venue"
},
  "geometry": {"coordinates":[151.08509826700001,-33.9999313354],"type":"Point"}
}