{
  "type": "Feature",
  "properties": {
    "addr:full":"26 Mary St Essendon VIC 3040",
    "addr:housenumber":"26",
    "addr:postcode":"3040",
    "addr:street":"Mary St",
    "iso:country":"AU",
    "sg:address":"26 Mary St",
    "sg:city":"Essendon",
    "sg:classifiers":[
        {
            "category":"Building & Trades",
            "subcategory":"Construction",
            "type":"Services"
        }
    ],
    "sg:phone":"+61 439 991 428",
    "sg:postcode":"3040",
    "sg:province":"VIC",
    "sg:tags":[
        "concrete",
        "contractor"
    ],
    "wof:name":"Professional Paving",
    "wof:placetype":"venue"
},
  "geometry": {"coordinates":[144.89355468799999,-37.7487106323],"type":"Point"}
}