{
  "type": "Feature",
  "properties": {
    "addr:full":"32 Francis St Carlton NSW 2218",
    "addr:housenumber":"32",
    "addr:postcode":"2218",
    "addr:street":"Francis St",
    "iso:country":"AU",
    "sg:address":"32 Francis St",
    "sg:city":"Carlton",
    "sg:classifiers":[
        {
            "category":"Building & Trades",
            "subcategory":"Plumbing",
            "type":"Services"
        }
    ],
    "sg:phone":"+61 407 216 713",
    "sg:postcode":"2218",
    "sg:province":"NSW",
    "sg:tags":[
        "plumber",
        "gasfitters"
    ],
    "wof:name":"Allawah Plumbing Services",
    "wof:placetype":"venue"
},
  "geometry": {"coordinates":[151.123245,-33.974197],"type":"Point"}
}