{
  "type": "Feature",
  "properties": {
    "addr:full":"Shed 2/ 344 Annagrove Rd Rouse Hill NSW 2155",
    "addr:housenumber":"2 / 344",
    "addr:postcode":"2155",
    "addr:street":"Annagrove Rd",
    "iso:country":"AU",
    "sg:address":"Shed 2/ 344 Annagrove Rd",
    "sg:city":"Rouse Hill",
    "sg:classifiers":[
        {
            "category":"Farming",
            "subcategory":"Farm & Veterinary Services",
            "type":"Manufacturing & Wholesale Goods"
        }
    ],
    "sg:phone":"+61 1300 761 781",
    "sg:postcode":"2155",
    "sg:province":"NSW",
    "sg:tags":[
        "irrigation",
        "reticulation",
        "system"
    ],
    "wof:name":"Irrigation & Water Technology Pty Ltd",
    "wof:placetype":"venue"
},
  "geometry": {"coordinates":[150.911575317,-33.674243927],"type":"Point"}
}