{
  "type": "Feature",
  "properties": {
    "iso:country":"AU",
    "sg:address":"18/ 98 Old Pittwater Rd",
    "sg:city":"Brookvale",
    "sg:classifiers":[
        {
            "category":"Wholesale",
            "subcategory":"Construction Materials",
            "type":"Manufacturing & Wholesale Goods"
        }
    ],
    "sg:phone":"+61 2 9907 4634",
    "sg:postcode":"2100",
    "sg:province":"NSW",
    "sg:tags":[
        "lift"
    ],
    "sg:website":"http://www.easy-living.com.au",
    "wof:name":"Easy Living Home Elevators",
    "wof:placetype":"venue"
},
  "geometry": {"coordinates":[151.26356506400001,-33.7635498047],"type":"Point"}
}