{
  "type": "Feature",
  "properties": {
    "iso:country":"AU",
    "sg:address":"4/ 17 Short St",
    "sg:city":"Port Macquarie",
    "sg:classifiers":[
        {
            "category":"Professional",
            "subcategory":"Business Services",
            "type":"Services"
        }
    ],
    "sg:phone":"+61 2 6584 9444",
    "sg:postcode":"2444",
    "sg:province":"NSW",
    "sg:tags":[
        "broker"
    ],
    "wof:name":"NSW Business Sales",
    "wof:placetype":"venue"
},
  "geometry": {"coordinates":[152.90670800000001,-31.430433],"type":"Point"}
}