{
  "type": "Feature",
  "properties": {
    "addr:full":"Corner Southpine & Kremzow Rd Strathpine QLD 4500",
    "addr:postcode":"4500",
    "addr:street":"Kremzow Rd",
    "iso:country":"AU",
    "sg:address":"Corner Southpine & Kremzow Rd",
    "sg:city":"Strathpine",
    "sg:classifiers":[
        {
            "category":"Retail",
            "subcategory":"Car Wash",
            "type":"Services"
        }
    ],
    "sg:phone":"+61 7 3205 5222",
    "sg:postcode":"4500",
    "sg:province":"QLD",
    "sg:tags":[
        "truck",
        "cleaning"
    ],
    "wof:name":"Wash &#039;N&#039; Go",
    "wof:placetype":"venue"
},
  "geometry": {"coordinates":[152.99511718799999,-27.3150901794],"type":"Point"}
}