{
  "type": "Feature",
  "properties": {
    "iso:country":"AU",
    "sg:address":"PO Box 29",
    "sg:city":"Old Bar",
    "sg:classifiers":[
        {
            "category":"Professional",
            "subcategory":"Art Services",
            "type":"Services"
        }
    ],
    "sg:phone":"+61 2 6553 3586",
    "sg:postcode":"2430",
    "sg:province":"NSW",
    "sg:tags":[
        "interior",
        "designer"
    ],
    "wof:name":"Out Of The Bay Designs",
    "wof:placetype":"venue"
},
  "geometry": {"coordinates":[152.551727,-31.964689],"type":"Point"}
}