{
  "type": "Feature",
  "properties": {
    "addr:full":"888 Sydney Rd Coburg North VIC 3058",
    "addr:housenumber":"888",
    "addr:postcode":"3058",
    "addr:street":"Sydney Rd",
    "iso:country":"AU",
    "sg:address":"888 Sydney Rd",
    "sg:city":"Coburg North",
    "sg:classifiers":[
        {
            "category":"Retail",
            "subcategory":"Auto Repair",
            "type":"Services"
        }
    ],
    "sg:phone":"+61 3 9354 1046",
    "sg:postcode":"3058",
    "sg:province":"VIC",
    "sg:tags":[
        "beater",
        "painter",
        "panel"
    ],
    "wof:name":"Sun Motor & Body Works",
    "wof:placetype":"venue"
},
  "geometry": {"coordinates":[144.963745117,-37.7255477905],"type":"Point"}
}