{
  "type": "Feature",
  "properties": {
    "addr:full":"47a Dover St Richmond VIC 3121",
    "addr:housenumber":"47a",
    "addr:postcode":"3121",
    "addr:street":"Dover St",
    "iso:country":"AU",
    "sg:address":"47a Dover St",
    "sg:city":"Richmond",
    "sg:classifiers":[
        {
            "category":"Professional",
            "subcategory":"Art Services",
            "type":"Services"
        }
    ],
    "sg:phone":"+61 3 9421 1295",
    "sg:postcode":"3121",
    "sg:province":"VIC",
    "sg:tags":[
        "graphic",
        "designer"
    ],
    "wof:name":"Studio Binocular",
    "wof:placetype":"venue"
},
  "geometry": {"coordinates":[144.99212646500001,-37.8267021179],"type":"Point"}
}