{
  "type": "Feature",
  "properties": {
    "addr:full":"Level 1/ 1227 Glen Huntly Rd Glen Huntly VIC 3163",
    "addr:housenumber":"/ 1227",
    "addr:postcode":"3163",
    "addr:street":"Glen Huntly Rd",
    "iso:country":"AU",
    "sg:address":"Level 1/ 1227 Glen Huntly Rd",
    "sg:city":"Glen Huntly",
    "sg:classifiers":[
        {
            "category":"Arts & Performance",
            "subcategory":"Music",
            "type":"Entertainment"
        }
    ],
    "sg:phone":"+61 3 9572 8900",
    "sg:postcode":"3163",
    "sg:province":"VIC",
    "sg:tags":[
        "hi-fi",
        "equipment"
    ],
    "wof:name":"Cableman",
    "wof:placetype":"venue"
},
  "geometry": {"coordinates":[145.04498290999999,-37.8896102905],"type":"Point"}
}