{
  "type": "Feature",
  "properties": {
    "addr:full":"79 Bay St Port Melbourne VIC 3207",
    "addr:housenumber":"79",
    "addr:postcode":"3207",
    "addr:street":"Bay St",
    "iso:country":"AU",
    "sg:address":"79 Bay St",
    "sg:city":"Port Melbourne",
    "sg:classifiers":[
        {
            "category":"Professional",
            "subcategory":"Detective & Security Services",
            "type":"Services"
        }
    ],
    "sg:phone":"+61 3 9646 4922",
    "sg:postcode":"3207",
    "sg:province":"VIC",
    "sg:tags":[
        "domestic",
        "alarm",
        "commercial",
        "burglar"
    ],
    "wof:name":"International Security Electronics",
    "wof:placetype":"venue"
},
  "geometry": {"coordinates":[144.939697,-37.841228],"type":"Point"}
}