{
  "type": "Feature",
  "properties": {
    "addr:full":"Factory 2/ 60 Industrial Drv Braeside VIC 3195",
    "addr:housenumber":"/ 60",
    "addr:postcode":"3195",
    "addr:street":"Industrial Drv",
    "iso:country":"AU",
    "sg:address":"Factory 2/ 60 Industrial Drv",
    "sg:city":"Braeside",
    "sg:classifiers":[
        {
            "category":"Food & Beverages",
            "subcategory":"Specialty",
            "type":"Retail Goods"
        }
    ],
    "sg:phone":"+61 3 9587 2269",
    "sg:postcode":"3195",
    "sg:province":"VIC",
    "sg:tags":[
        "product",
        "health"
    ],
    "wof:name":"Vbk Foods",
    "wof:placetype":"venue"
},
  "geometry": {"coordinates":[145.11239624000001,-38.0056610107],"type":"Point"}
}