{
  "type": "Feature",
  "properties": {
    "addr:full":"16 Dome St Eight Mile Plains QLD 4113",
    "addr:housenumber":"16",
    "addr:postcode":"4113",
    "addr:street":"Dome St",
    "iso:country":"AU",
    "sg:address":"16 Dome St",
    "sg:city":"Eight Mile Plains",
    "sg:classifiers":[
        {
            "category":"Mining & Drilling",
            "type":"Manufacturing & Wholesale Goods"
        }
    ],
    "sg:phone":"+61 7 3841 3865",
    "sg:postcode":"4113",
    "sg:province":"QLD",
    "sg:tags":[
        "geologist"
    ],
    "wof:name":"Lance Grimstone & Associates(Consulting) Pty Ltd",
    "wof:placetype":"venue"
},
  "geometry": {"coordinates":[153.07843017600001,-27.5786399841],"type":"Point"}
}