{
  "type": "Feature",
  "properties": {
    "iso:country":"AU",
    "sg:address":"46- 48 Kilby Rd",
    "sg:city":"Kew East",
    "sg:classifiers":[
        {
            "category":"Insurance",
            "subcategory":"Life Insurance",
            "type":"Services"
        }
    ],
    "sg:phone":"+61 1800 722 274",
    "sg:postcode":"3102",
    "sg:province":"VIC",
    "wof:name":"Cashback Life Insurance Pty Ltd",
    "wof:placetype":"venue"
},
  "geometry": {"coordinates":[145.04757690400001,-37.7917633057],"type":"Point"}
}