{
  "type": "Feature",
  "properties": {
    "iso:country":"AU",
    "sg:address":"Shp1/ 568 Forest Rd",
    "sg:city":"Penshurst",
    "sg:classifiers":[
        {
            "category":"Personal",
            "subcategory":"Beauty Salon",
            "type":"Services"
        }
    ],
    "sg:phone":"+61 2 9570 9494",
    "sg:postcode":"2222",
    "sg:province":"NSW",
    "sg:tags":[
        "hairdresser"
    ],
    "wof:name":"Blush Hair Artistry",
    "wof:placetype":"venue"
},
  "geometry": {"coordinates":[151.081375122,-33.9628868103],"type":"Point"}
}