{
  "type": "Feature",
  "properties": {
    "iso:country":"AU",
    "sg:address":"Sextons Rd",
    "sg:city":"Te Kowai",
    "sg:classifiers":[
        {
            "category":"Farming",
            "subcategory":"Farm",
            "type":"Manufacturing & Wholesale Goods"
        }
    ],
    "sg:phone":"+61 7 4954 5162",
    "sg:postcode":"4740",
    "sg:province":"QLD",
    "sg:tags":[
        "farmer"
    ],
    "wof:name":"Trueman W N",
    "wof:placetype":"venue"
},
  "geometry": {"coordinates":[149.121658,-21.164165],"type":"Point"}
}