{
  "type": "Feature",
  "properties": {
    "addr:full":"533 Prospect Rd Gepps Cross SA 5094",
    "addr:housenumber":"533",
    "addr:postcode":"5094",
    "addr:street":"Prospect Rd",
    "iso:country":"AU",
    "sg:address":"533 Prospect Rd",
    "sg:city":"Gepps Cross",
    "sg:classifiers":[
        {
            "category":"Building & Trades",
            "subcategory":"Construction",
            "type":"Services"
        }
    ],
    "sg:phone":"+61 8 8349 6067",
    "sg:postcode":"5094",
    "sg:province":"SA",
    "sg:tags":[
        "window",
        "aluminium"
    ],
    "wof:name":"Precision Windows",
    "wof:placetype":"venue"
},
  "geometry": {"coordinates":[138.59141540499999,-34.8466644287],"type":"Point"}
}