{
  "type": "Feature",
  "properties": {
    "addr:full":"276 George St Liverpool NSW 2170",
    "addr:housenumber":"276",
    "addr:postcode":"2170",
    "addr:street":"George St",
    "iso:country":"AU",
    "sg:address":"276 George St",
    "sg:city":"Liverpool",
    "sg:classifiers":[
        {
            "category":"Professional",
            "subcategory":"Employment Agencies",
            "type":"Services"
        }
    ],
    "sg:phone":"+61 2 9602 7788",
    "sg:postcode":"2170",
    "sg:province":"NSW",
    "wof:name":"Frontline Human Resources",
    "wof:placetype":"venue"
},
  "geometry": {"coordinates":[150.92466735799999,-33.9247245789],"type":"Point"}
}