{
  "type": "Feature",
  "properties": {
    "addr:full":"500 Tooan-Mitre Rd Mitre VIC 3401",
    "addr:housenumber":"500",
    "addr:postcode":"3401",
    "addr:street":"Tooan-Mitre Rd",
    "iso:country":"AU",
    "sg:address":"500 Tooan-Mitre Rd",
    "sg:city":"Mitre",
    "sg:classifiers":[
        {
            "category":"Farming",
            "subcategory":"Poultry Farm",
            "type":"Manufacturing & Wholesale Goods"
        }
    ],
    "sg:phone":"+61 3 5387 4278",
    "sg:postcode":"3401",
    "sg:province":"VIC",
    "sg:tags":[
        "farmer"
    ],
    "wof:name":"Grow-A-Duck Pty Ltd",
    "wof:placetype":"venue"
},
  "geometry": {"coordinates":[141.76495361299999,-36.7702903748],"type":"Point"}
}