{
  "type": "Feature",
  "properties": {
    "addr:full":"Unit 2, 50 Lawrence Drv Nerang QLD 4211",
    "addr:housenumber":"50",
    "addr:postcode":"4211",
    "addr:street":"Lawrence Drv",
    "iso:country":"AU",
    "sg:address":"Unit 2, 50 Lawrence Drv",
    "sg:city":"Nerang",
    "sg:classifiers":[
        {
            "category":"Home & Garden",
            "subcategory":"Building Materials",
            "type":"Retail Goods"
        }
    ],
    "sg:phone":"+61 7 5596 3570",
    "sg:postcode":"4211",
    "sg:province":"QLD",
    "sg:tags":[
        "fitting",
        "door"
    ],
    "wof:name":"Garage Door Shoppe Pty. Ltd.",
    "wof:placetype":"venue"
},
  "geometry": {"coordinates":[153.34274292000001,-27.9983024597],"type":"Point"}
}