{
  "type": "Feature",
  "properties": {
    "iso:country":"AU",
    "sg:address":"Showroom 334 St Georges Rd",
    "sg:city":"Fitzroy North",
    "sg:classifiers":[
        {
            "category":"Professional",
            "subcategory":"Art Services",
            "type":"Services"
        }
    ],
    "sg:phone":"+61 3 9017 0658",
    "sg:postcode":"3068",
    "sg:province":"VIC",
    "sg:tags":[
        "interior",
        "designer"
    ],
    "wof:name":"Empire Red",
    "wof:placetype":"venue"
},
  "geometry": {"coordinates":[144.98674011200001,-37.7801856995],"type":"Point"}
}