{
  "type": "Feature",
  "properties": {
    "addr:full":"60 Kensington Rd Rose Park SA 5067",
    "addr:housenumber":"60",
    "addr:postcode":"5067",
    "addr:street":"Kensington Rd Rose",
    "iso:country":"AU",
    "sg:address":"60 Kensington Rd",
    "sg:city":"Rose Park",
    "sg:classifiers":[
        {
            "category":"Conference Center",
            "type":"Public Place"
        }
    ],
    "sg:phone":"+61 8 8332 4068",
    "sg:postcode":"5067",
    "sg:province":"SA",
    "sg:tags":[
        "venue",
        "convention"
    ],
    "wof:name":"Elliservice Convention Management",
    "wof:placetype":"venue"
},
  "geometry": {"coordinates":[138.630096436,-34.9276199341],"type":"Point"}
}