{
  "type": "Feature",
  "properties": {
    "iso:country":"AU",
    "sg:address":"32 George St",
    "sg:city":"Bowen",
    "sg:classifiers":[
        {
            "category":"Real Estate",
            "subcategory":"Real Estate Agent",
            "type":"Services"
        }
    ],
    "sg:phone":"+61 7 4786 1132",
    "sg:postcode":"4805",
    "sg:province":"QLD",
    "wof:name":"Century 21 Coral Coast Realty Bowen",
    "wof:placetype":"venue"
},
  "geometry": {"coordinates":[148.244598389,-20.0160274506],"type":"Point"}
}