{
  "type": "Feature",
  "properties": {
    "iso:country":"AU",
    "sg:address":"181 Mornington Tyabb Rd",
    "sg:city":"Mornington",
    "sg:classifiers":[
        {
            "category":"Retail",
            "subcategory":"Auto Repair",
            "type":"Services"
        }
    ],
    "sg:phone":"+61 3 5970 5970",
    "sg:postcode":"3931",
    "sg:province":"VIC",
    "sg:tags":[
        "repairer",
        "motor",
        "engineer"
    ],
    "wof:name":"Mornington BMW",
    "wof:placetype":"venue"
},
  "geometry": {"coordinates":[145.06468200699999,-38.2386322021],"type":"Point"}
}