{
  "type": "Feature",
  "properties": {
    "addr:full":"7 Hill St Cremorne VIC 3121",
    "addr:housenumber":"7",
    "addr:postcode":"3121",
    "addr:street":"Hill St",
    "iso:country":"AU",
    "sg:address":"7 Hill St",
    "sg:city":"Cremorne",
    "sg:classifiers":[
        {
            "category":"Shopping",
            "subcategory":"Antiques",
            "type":"Retail Goods"
        }
    ],
    "sg:phone":"+61 3 9427 1148",
    "sg:postcode":"3121",
    "sg:province":"VIC",
    "wof:name":"Kazari",
    "wof:placetype":"venue"
},
  "geometry": {"coordinates":[144.99609375,-37.827835083],"type":"Point"}
}