{
  "type": "Feature",
  "properties": {
    "iso:country":"AU",
    "sg:address":"35 Sharp St",
    "sg:city":"Cooma",
    "sg:classifiers":[
        {
            "category":"Travel",
            "subcategory":"Hotels & Motels",
            "type":"Entertainment"
        }
    ],
    "sg:phone":"+61 2 6452 1366",
    "sg:postcode":"2630",
    "sg:province":"NSW",
    "wof:name":"Sovereign Inn Cooma",
    "wof:placetype":"venue"
},
  "geometry": {"coordinates":[149.13409423799999,-36.2312316895],"type":"Point"}
}