{
  "type": "Feature",
  "properties": {
    "iso:country":"AU",
    "sg:address":"Railway St",
    "sg:city":"Dirranbandi",
    "sg:classifiers":[
        {
            "category":"Government",
            "subcategory":"Post Office",
            "type":"Public Place"
        }
    ],
    "sg:phone":"+61 7 4625 8211",
    "sg:postcode":"4486",
    "sg:province":"QLD",
    "sg:tags":[
        "postal"
    ],
    "wof:name":"Australia Post",
    "wof:placetype":"venue"
},
  "geometry": {"coordinates":[148.223190308,-28.58527565],"type":"Point"}
}