{
  "type": "Feature",
  "properties": {
    "addr:full":"264 Main Rd Toukley NSW 2263",
    "addr:housenumber":"264",
    "addr:postcode":"2263",
    "addr:street":"Main Rd",
    "iso:country":"AU",
    "sg:address":"264 Main Rd",
    "sg:city":"Toukley",
    "sg:classifiers":[
        {
            "category":"Personal",
            "subcategory":"Beauty Salon",
            "type":"Services"
        }
    ],
    "sg:phone":"+61 2 4396 5438",
    "sg:postcode":"2263",
    "sg:province":"NSW",
    "sg:website":"http://www.ambiance.net.au",
    "wof:name":"Ambiance Urban Spa",
    "wof:placetype":"venue"
},
  "geometry": {"coordinates":[151.54547099999999,-33.264309],"type":"Point"}
}