{
  "type": "Feature",
  "properties": {
    "addr:full":"Shop 115, Westfiel Hurstville Hurstville NSW 2220",
    "addr:housenumber":"115",
    "addr:postcode":"2220",
    "addr:street":"Westfiel",
    "iso:country":"AU",
    "sg:address":"Shop 115, Westfiel Hurstville",
    "sg:city":"Hurstville",
    "sg:classifiers":[
        {
            "category":"Food & Beverages",
            "subcategory":"Specialty",
            "type":"Retail Goods"
        }
    ],
    "sg:phone":"+61 2 9570 2572",
    "sg:postcode":"2220",
    "sg:province":"NSW",
    "sg:tags":[
        "product",
        "health"
    ],
    "wof:name":"GNC Live Well",
    "wof:placetype":"venue"
},
  "geometry": {"coordinates":[151.10104370100001,-33.9671897888],"type":"Point"}
}