{
  "type": "Feature",
  "properties": {
    "addr:full":"4 Catherine St Leichhardt NSW 2040",
    "addr:housenumber":"4",
    "addr:postcode":"2040",
    "addr:street":"Catherine St",
    "iso:country":"AU",
    "sg:address":"4 Catherine St",
    "sg:city":"Leichhardt",
    "sg:classifiers":[
        {
            "category":"Health Services",
            "subcategory":"Dentist",
            "type":"Services"
        }
    ],
    "sg:phone":"+61 2 9564 6111",
    "sg:postcode":"2040",
    "sg:province":"NSW",
    "sg:tags":[
        "technician",
        "dental"
    ],
    "wof:name":"Leichhardt Denture Clinic",
    "wof:placetype":"venue"
},
  "geometry": {"coordinates":[151.16134600000001,-33.887295],"type":"Point"}
}