{
  "type": "Feature",
  "properties": {
    "addr:full":"28 Bridge St Muswellbrook NSW 2333",
    "addr:housenumber":"28",
    "addr:postcode":"2333",
    "addr:street":"Bridge St",
    "iso:country":"AU",
    "sg:address":"28 Bridge St",
    "sg:city":"Muswellbrook",
    "sg:classifiers":[
        {
            "category":"Personal",
            "subcategory":"Piercing",
            "type":"Services"
        }
    ],
    "sg:phone":"+61 2 6541 2270",
    "sg:postcode":"2333",
    "sg:province":"NSW",
    "sg:tags":[
        "body",
        "ear"
    ],
    "wof:name":"Muswellbrook Nail & Beauty",
    "wof:placetype":"venue"
},
  "geometry": {"coordinates":[150.888305664,-32.2650299072],"type":"Point"}
}