{
  "type": "Feature",
  "properties": {
    "addr:full":"674 High St Kew East VIC 3102",
    "addr:housenumber":"674",
    "addr:postcode":"3102",
    "addr:street":"High St",
    "iso:country":"AU",
    "sg:address":"674 High St",
    "sg:city":"Kew East",
    "sg:classifiers":[
        {
            "category":"Travel",
            "subcategory":"Travel Agent",
            "type":"Entertainment"
        }
    ],
    "sg:phone":"+61 3 9859 9521",
    "sg:postcode":"3102",
    "sg:province":"VIC",
    "sg:tags":[
        "consultant"
    ],
    "wof:name":"Solo Traveller",
    "wof:placetype":"venue"
},
  "geometry": {"coordinates":[145.052124023,-37.798789978],"type":"Point"}
}