{
  "type": "Feature",
  "properties": {
    "iso:country":"AU",
    "sg:address":"20 King St",
    "sg:city":"Rockdale",
    "sg:classifiers":[
        {
            "category":"Industrial Area",
            "type":"Public Place"
        }
    ],
    "sg:phone":"+61 2 9597 7115",
    "sg:postcode":"2216",
    "sg:province":"NSW",
    "sg:tags":[
        "consulting",
        "chemist"
    ],
    "wof:name":"Technical Consultancy Services Pty Ltd",
    "wof:placetype":"venue"
},
  "geometry": {"coordinates":[151.13949600000001,-33.952644],"type":"Point"}
}