{
  "type": "Feature",
  "properties": {
    "addr:full":"U10/ 44 Carrington Rd Castle Hill NSW 2154",
    "addr:housenumber":"44",
    "addr:postcode":"2154",
    "addr:street":"/;Carrington Rd",
    "iso:country":"AU",
    "sg:address":"U10/ 44 Carrington Rd",
    "sg:city":"Castle Hill",
    "sg:classifiers":[
        {
            "category":"Building & Trades",
            "subcategory":"Construction",
            "type":"Services"
        }
    ],
    "sg:phone":"+61 2 9680 3634",
    "sg:postcode":"2154",
    "sg:province":"NSW",
    "sg:tags":[
        "window",
        "tinting"
    ],
    "wof:name":"Prestige Valet Car Centre",
    "wof:placetype":"venue"
},
  "geometry": {"coordinates":[150.985305786,-33.7288513184],"type":"Point"}
}