{
  "type": "Feature",
  "properties": {
    "addr:full":"28 Tombarra St Mooloolaba QLD 4557",
    "addr:housenumber":"28",
    "addr:postcode":"4557",
    "addr:street":"Tombarra St",
    "iso:country":"AU",
    "sg:address":"28 Tombarra St",
    "sg:city":"Mooloolaba",
    "sg:classifiers":[
        {
            "category":"Professional",
            "subcategory":"Printing & Photocopies",
            "type":"Services"
        }
    ],
    "sg:phone":"+61 7 5444 7027",
    "sg:postcode":"4557",
    "sg:province":"QLD",
    "sg:tags":[
        "textile",
        "clothing"
    ],
    "wof:name":"G & R Signs & Screenprints",
    "wof:placetype":"venue"
},
  "geometry": {"coordinates":[153.10916137699999,-26.6796913147],"type":"Point"}
}