{
  "type": "Feature",
  "properties": {
    "addr:full":"PO Box 211 Queenstown TAS 7467",
    "addr:postcode":"7467",
    "iso:country":"AU",
    "sg:address":"PO Box 211",
    "sg:city":"Queenstown",
    "sg:classifiers":[
        {
            "category":"Manufacturing",
            "subcategory":"Lumber",
            "type":"Manufacturing & Wholesale Goods"
        }
    ],
    "sg:phone":"+61 3 6471 2510",
    "sg:postcode":"7467",
    "sg:province":"TAS",
    "sg:tags":[
        "sawmillers"
    ],
    "wof:name":"Tasmanian Special Timbers Pty Ltd",
    "wof:placetype":"venue"
},
  "geometry": {"coordinates":[145.55894470199999,-42.0771598816],"type":"Point"}
}