{
  "type": "Feature",
  "properties": {
    "addr:full":"88 Lower Plenty Rd Rosanna VIC 3084",
    "addr:housenumber":"88",
    "addr:postcode":"3084",
    "addr:street":"Lower Plenty Rd",
    "iso:country":"AU",
    "sg:address":"88 Lower Plenty Rd",
    "sg:city":"Rosanna",
    "sg:classifiers":[
        {
            "category":"Health Services",
            "subcategory":"Doctor",
            "type":"Services"
        }
    ],
    "sg:phone":"+61 3 9457 1463",
    "sg:postcode":"3084",
    "sg:province":"VIC",
    "sg:tags":[
        "medical",
        "practitioner"
    ],
    "wof:name":"Rosanna Medical Group",
    "wof:placetype":"venue"
},
  "geometry": {"coordinates":[145.064361572,-37.7435874939],"type":"Point"}
}