{
  "type": "Feature",
  "properties": {
    "addr:full":"49b Marlston Drv Bunbury WA 6230",
    "addr:housenumber":"49b",
    "addr:postcode":"6230",
    "addr:street":"Marlston Drv",
    "iso:country":"AU",
    "sg:address":"49b Marlston Drv",
    "sg:city":"Bunbury",
    "sg:classifiers":[
        {
            "category":"Building & Trades",
            "subcategory":"Plumbing",
            "type":"Services"
        }
    ],
    "sg:phone":"+61 8 9791 8311",
    "sg:postcode":"6230",
    "sg:province":"WA",
    "sg:tags":[
        "plumber",
        "gasfitters"
    ],
    "wof:name":"James Plumbing",
    "wof:placetype":"venue"
},
  "geometry": {"coordinates":[115.63700900000001,-33.318218],"type":"Point"}
}