{
  "type": "Feature",
  "properties": {
    "addr:full":"5 Lewis Crt Mooroopna VIC 3629",
    "addr:housenumber":"5",
    "addr:postcode":"3629",
    "addr:street":"Lewis Crt",
    "iso:country":"AU",
    "sg:address":"5 Lewis Crt",
    "sg:city":"Mooroopna",
    "sg:classifiers":[
        {
            "category":"Building & Trades",
            "subcategory":"Plumbing",
            "type":"Services"
        }
    ],
    "sg:phone":"+61 418 598 208",
    "sg:postcode":"3629",
    "sg:province":"VIC",
    "sg:tags":[
        "plumber",
        "gasfitters"
    ],
    "wof:name":"D&S Kilpatrick Plumbing",
    "wof:placetype":"venue"
},
  "geometry": {"coordinates":[145.34487915,-36.3934936523],"type":"Point"}
}