{
  "type": "Feature",
  "properties": {
    "addr:full":"2- 296 Ross River Rd Aitkenvale QLD 4814",
    "addr:housenumber":"2 296",
    "addr:postcode":"4814",
    "addr:street":"Ross River Rd",
    "iso:country":"AU",
    "sg:address":"2- 296 Ross River Rd",
    "sg:city":"Aitkenvale",
    "sg:classifiers":[
        {
            "category":"Education",
            "subcategory":"School",
            "type":"Public Place"
        }
    ],
    "sg:phone":"+61 7 4779 2199",
    "sg:postcode":"4814",
    "sg:province":"QLD",
    "sg:tags":[
        "co-educational"
    ],
    "sg:website":"http://www.atcnq.edu.au",
    "wof:name":"Australian Technical College North Queensland",
    "wof:placetype":"venue"
},
  "geometry": {"coordinates":[146.76559399999999,-19.297638],"type":"Point"}
}