{
  "type": "Feature",
  "properties": {
    "addr:full":"6 Leomeruno Rd Newton SA 5074",
    "addr:housenumber":"6",
    "addr:postcode":"5074",
    "addr:street":"Leomeruno Rd",
    "iso:country":"AU",
    "sg:address":"6 Leomeruno Rd",
    "sg:city":"Newton",
    "sg:classifiers":[
        {
            "category":"Home & Garden",
            "subcategory":"Carpets & Floor Coverings",
            "type":"Retail Goods"
        }
    ],
    "sg:phone":"+61 414 842 092",
    "sg:postcode":"5074",
    "sg:province":"SA",
    "sg:tags":[
        "tile",
        "wall",
        "layer"
    ],
    "wof:name":"A & R Princi",
    "wof:placetype":"venue"
},
  "geometry": {"coordinates":[138.69046020499999,-34.8818626404],"type":"Point"}
}