{
  "type": "Feature",
  "properties": {
    "addr:full":"67 John St Leichhardt NSW 2040",
    "addr:housenumber":"67",
    "addr:postcode":"2040",
    "addr:street":"John St",
    "iso:country":"AU",
    "sg:address":"67 John St",
    "sg:city":"Leichhardt",
    "sg:classifiers":[
        {
            "category":"Manufacturing",
            "subcategory":"Apparel",
            "type":"Manufacturing & Wholesale Goods"
        }
    ],
    "sg:phone":"+61 2 9660 3455",
    "sg:postcode":"2040",
    "sg:province":"NSW",
    "sg:tags":[
        "wholesaler",
        "mfrs",
        "belt"
    ],
    "wof:name":"Apparel Fittings Pty Ltd",
    "wof:placetype":"venue"
},
  "geometry": {"coordinates":[151.166214,-33.880424],"type":"Point"}
}