{
  "type": "Feature",
  "properties": {
    "iso:country":"AU",
    "sg:address":"65 Osten Drv",
    "sg:city":"Langford",
    "sg:classifiers":[
        {
            "category":"Shopping",
            "subcategory":"Stationery & Office Supplies",
            "type":"Retail Goods"
        }
    ],
    "sg:phone":"+61 423 599 189",
    "sg:postcode":"6147",
    "sg:province":"WA",
    "sg:tags":[
        "partition"
    ],
    "wof:name":"Century Ceilings Pty Ltd",
    "wof:placetype":"venue"
},
  "geometry": {"coordinates":[115.938339,-32.043278],"type":"Point"}
}