{
  "type": "Feature",
  "properties": {
    "iso:country":"AU",
    "sg:address":"5 Norfolk St",
    "sg:city":"Fremantle",
    "sg:classifiers":[
        {
            "category":"Professional",
            "type":"Services"
        }
    ],
    "sg:phone":"+61 8 9335 5528",
    "sg:postcode":"6160",
    "sg:province":"WA",
    "sg:tags":[
        "buyer",
        "merchant",
        "wool"
    ],
    "wof:name":"Sojitz Australia Ltd",
    "wof:placetype":"venue"
},
  "geometry": {"coordinates":[115.748451,-32.05769],"type":"Point"}
}