{
  "type": "Feature",
  "properties": {
    "iso:country":"AU",
    "sg:address":"Cnr Temple Tce & Roystonea Ave",
    "sg:city":"Palmerston",
    "sg:classifiers":[
        {
            "category":"Health Services",
            "subcategory":"Doctor",
            "type":"Services"
        }
    ],
    "sg:phone":"+61 8 8931 2518",
    "sg:postcode":"0830",
    "sg:province":"NT",
    "sg:tags":[
        "medical",
        "practitioner"
    ],
    "wof:name":"Mayne Western Diagnostic Pathology Collection Centres",
    "wof:placetype":"venue"
},
  "geometry": {"coordinates":[130.978561,-12.468045],"type":"Point"}
}