{
  "type": "Feature",
  "properties": {
    "addr:full":"5 Murphy St Corrigin WA 6375",
    "addr:housenumber":"5",
    "addr:postcode":"6375",
    "addr:street":"Murphy St",
    "iso:country":"AU",
    "sg:address":"5 Murphy St",
    "sg:city":"Corrigin",
    "sg:classifiers":[
        {
            "category":"Health Services",
            "subcategory":"Doctor",
            "type":"Services"
        }
    ],
    "sg:phone":"+61 8 9063 2107",
    "sg:postcode":"6375",
    "sg:province":"WA",
    "sg:tags":[
        "medical",
        "practitioner"
    ],
    "wof:name":"Corrigin Medical Surgery",
    "wof:placetype":"venue"
},
  "geometry": {"coordinates":[117.875519,-32.32423],"type":"Point"}
}