{
  "type": "Feature",
  "properties": {
    "addr:full":"25 Bradley Rd Clontarf QLD 4019",
    "addr:housenumber":"25",
    "addr:postcode":"4019",
    "addr:street":"Bradley Rd",
    "iso:country":"AU",
    "sg:address":"25 Bradley Rd",
    "sg:city":"Clontarf",
    "sg:classifiers":[
        {
            "category":"Building & Trades",
            "subcategory":"Plumbing",
            "type":"Services"
        }
    ],
    "sg:phone":"+61 417 606 848",
    "sg:postcode":"4019",
    "sg:province":"QLD",
    "sg:tags":[
        "drainers"
    ],
    "wof:name":"Al's Plumbing Professionals & Drain Cleaning Service",
    "wof:placetype":"venue"
},
  "geometry": {"coordinates":[153.08792114299999,-27.2415237427],"type":"Point"}
}