{
  "type": "Feature",
  "properties": {
    "iso:country":"AU",
    "sg:address":"Unit 9, 12- 18 Fairfield St",
    "sg:city":"Fairfield East",
    "sg:classifiers":[
        {
            "category":"Professional",
            "subcategory":"Computer Services",
            "type":"Services"
        }
    ],
    "sg:phone":"+61 2 9632 7700",
    "sg:postcode":"2165",
    "sg:province":"NSW",
    "sg:tags":[
        "consultant",
        "system"
    ],
    "wof:name":"Vision Tech Pty Ltd",
    "wof:placetype":"venue"
},
  "geometry": {"coordinates":[150.983184814,-33.8702316284],"type":"Point"}
}