{
  "type": "Feature",
  "properties": {
    "addr:full":"132 New Town Rd New Town TAS 7008",
    "addr:housenumber":"132",
    "addr:postcode":"7008",
    "addr:street":"New Town Rd",
    "iso:country":"AU",
    "sg:address":"132 New Town Rd",
    "sg:city":"New Town",
    "sg:classifiers":[
        {
            "category":"Health Services",
            "subcategory":"Dentist",
            "type":"Services"
        }
    ],
    "sg:phone":"+61 3 6278 7188",
    "sg:postcode":"7008",
    "sg:province":"TAS",
    "sg:tags":[
        "dental",
        "prosthetist"
    ],
    "wof:name":"Ferguson Andrew",
    "wof:placetype":"venue"
},
  "geometry": {"coordinates":[147.30714416500001,-42.8603172302],"type":"Point"}
}