{
  "type": "Feature",
  "properties": {
    "addr:full":"2/ 65 Stephens Ave Torrensville SA 5031",
    "addr:housenumber":"/ 65",
    "addr:postcode":"5031",
    "addr:street":"Stephens Ave",
    "iso:country":"AU",
    "sg:address":"2/ 65 Stephens Ave",
    "sg:city":"Torrensville",
    "sg:classifiers":[
        {
            "category":"Professional",
            "subcategory":"Accounting & Tax Preparation",
            "type":"Services"
        }
    ],
    "sg:phone":"+61 8 8352 5588",
    "sg:postcode":"5031",
    "sg:province":"SA",
    "sg:tags":[
        "insulation",
        "wholesaler",
        "material",
        "mfrs"
    ],
    "wof:name":"Cool Or Cosy",
    "wof:placetype":"venue"
},
  "geometry": {"coordinates":[138.555175781,-34.9161491394],"type":"Point"}
}