{
  "type": "Feature",
  "properties": {
    "addr:full":"102 Dawson St South Ballarat VIC 3350",
    "addr:housenumber":"102",
    "addr:postcode":"3350",
    "addr:street":"Dawson St South",
    "iso:country":"AU",
    "sg:address":"102 Dawson St South",
    "sg:city":"Ballarat",
    "sg:classifiers":[
        {
            "category":"Professional",
            "subcategory":"Engineering",
            "type":"Services"
        }
    ],
    "sg:phone":"+61 3 5333 3589",
    "sg:postcode":"3350",
    "sg:province":"VIC",
    "sg:tags":[
        "consulting",
        "engineer"
    ],
    "wof:name":"Dinning Engineering Consultants",
    "wof:placetype":"venue"
},
  "geometry": {"coordinates":[143.85273699999999,-37.563812],"type":"Point"}
}