{
  "type": "Feature",
  "properties": {
    "iso:country":"AU",
    "sg:address":"Calrose Ave",
    "sg:city":"Coleambally",
    "sg:classifiers":[
        {
            "category":"Shopping",
            "type":"Retail Goods"
        }
    ],
    "sg:phone":"+61 2 6954 4473",
    "sg:postcode":"2707",
    "sg:province":"NSW",
    "sg:tags":[
        "agent",
        "stock"
    ],
    "wof:name":"Jones Grain",
    "wof:placetype":"venue"
},
  "geometry": {"coordinates":[145.89584350600001,-34.7950363159],"type":"Point"}
}