{
  "type": "Feature",
  "properties": {
    "addr:full":"218 Derby St Penrith NSW 2750",
    "addr:housenumber":"218",
    "addr:postcode":"2750",
    "addr:street":"Derby St",
    "iso:country":"AU",
    "sg:address":"218 Derby St",
    "sg:city":"Penrith",
    "sg:classifiers":[
        {
            "category":"Health Services",
            "subcategory":"Doctor",
            "type":"Services"
        }
    ],
    "sg:phone":"+61 2 4721 4387",
    "sg:postcode":"2750",
    "sg:province":"NSW",
    "sg:tags":[
        "medical",
        "practitioner"
    ],
    "wof:name":"Cartmill John",
    "wof:placetype":"venue"
},
  "geometry": {"coordinates":[150.69659423799999,-33.7573165894],"type":"Point"}
}