{
  "type": "Feature",
  "properties": {
    "iso:country":"AU",
    "sg:address":"PO Box 9143",
    "sg:city":"Mt Gambier",
    "sg:classifiers":[
        {
            "category":"Professional",
            "subcategory":"Art Services",
            "type":"Services"
        }
    ],
    "sg:phone":"+61 409 699 686",
    "sg:postcode":"5291",
    "sg:province":"SA",
    "sg:tags":[
        "decorator",
        "painter"
    ],
    "wof:name":"Adam Hammond",
    "wof:placetype":"venue"
},
  "geometry": {"coordinates":[140.35760500000001,-37.813221],"type":"Point"}
}