{
  "type": "Feature",
  "properties": {
    "addr:full":"Shp 8/ 5 Pipit Cl Huntingdale WA 6110",
    "addr:housenumber":"/ 5",
    "addr:postcode":"6110",
    "addr:street":"Pipit Cl",
    "iso:country":"AU",
    "sg:address":"Shp 8/ 5 Pipit Cl",
    "sg:city":"Huntingdale",
    "sg:classifiers":[
        {
            "category":"Cafe",
            "type":"Food & Drink"
        }
    ],
    "sg:phone":"+61 8 9490 8823",
    "sg:postcode":"6110",
    "sg:province":"WA",
    "wof:name":"Cafe 8",
    "wof:placetype":"venue"
},
  "geometry": {"coordinates":[115.962661743,-32.0764694214],"type":"Point"}
}