{
  "type": "Feature",
  "properties": {
    "iso:country":"AU",
    "sg:address":"10 / 11 Morton St",
    "sg:city":"Chinderah",
    "sg:classifiers":[
        {
            "category":"Autos & Motor Vehicles",
            "subcategory":"Boat Sales",
            "type":"Retail Goods"
        }
    ],
    "sg:phone":"+61 438 953 212",
    "sg:postcode":"2487",
    "sg:province":"NSW",
    "sg:tags":[
        "yacht"
    ],
    "wof:name":"Sleekline Marine",
    "wof:placetype":"venue"
},
  "geometry": {"coordinates":[153.55494689899999,-28.2457904816],"type":"Point"}
}