{
  "type": "Feature",
  "properties": {
    "addr:full":"Factory 4/3 Collons Rd Melton VIC 3337",
    "addr:housenumber":"/ 3",
    "addr:postcode":"3337",
    "addr:street":"Collons Rd",
    "iso:country":"AU",
    "sg:address":"Factory 4/3 Collons Rd",
    "sg:city":"Melton",
    "sg:classifiers":[
        {
            "category":"Building & Trades",
            "subcategory":"Construction",
            "type":"Services"
        }
    ],
    "sg:phone":"+61 3 9743 2118",
    "sg:postcode":"3337",
    "sg:province":"VIC",
    "sg:tags":[
        "home",
        "air conditioning"
    ],
    "wof:name":"K & J Refrigeration & Airconditioning P/L",
    "wof:placetype":"venue"
},
  "geometry": {"coordinates":[144.60136399999999,-37.690361],"type":"Point"}
}