{
  "type": "Feature",
  "properties": {
    "addr:full":"18 Macquarie St Cowra NSW 2794",
    "addr:housenumber":"18",
    "addr:postcode":"2794",
    "addr:street":"Macquarie St",
    "iso:country":"AU",
    "sg:address":"18 Macquarie St",
    "sg:city":"Cowra",
    "sg:classifiers":[
        {
            "category":"Organizations",
            "subcategory":"Community Association",
            "type":"Services"
        }
    ],
    "sg:phone":"+61 2 6340 2901",
    "sg:postcode":"2794",
    "sg:province":"NSW",
    "sg:tags":[
        "organisation",
        "family",
        "welfare"
    ],
    "wof:name":"Home Care Service Of NSW",
    "wof:placetype":"venue"
},
  "geometry": {"coordinates":[148.688430786,-33.835067749],"type":"Point"}
}