{
  "type": "Feature",
  "properties": {
    "iso:country":"AU",
    "sg:address":"58 Beach Rd",
    "sg:city":"Bunbury",
    "sg:classifiers":[
        {
            "category":"Health Services",
            "subcategory":"Health Practitioner",
            "type":"Services"
        }
    ],
    "sg:phone":"+61 8 9792 4248",
    "sg:postcode":"6230",
    "sg:province":"WA",
    "sg:tags":[
        "naturopath"
    ],
    "wof:name":"Bunbury Natural Health Centre The",
    "wof:placetype":"venue"
},
  "geometry": {"coordinates":[115.638779,-33.335823],"type":"Point"}
}