{
  "type": "Feature",
  "properties": {
    "addr:full":"170 Robertson St Fortitude Valley QLD 4006",
    "addr:housenumber":"170",
    "addr:postcode":"4006",
    "addr:street":"Robertson St",
    "iso:country":"AU",
    "sg:address":"170 Robertson St",
    "sg:city":"Fortitude Valley",
    "sg:classifiers":[
        {
            "category":"Wholesale",
            "subcategory":"Construction Materials",
            "type":"Manufacturing & Wholesale Goods"
        }
    ],
    "sg:phone":"+61 7 3666 0955",
    "sg:postcode":"4006",
    "sg:province":"QLD",
    "sg:tags":[
        "wholesaler",
        "lighting",
        "mfrs",
        "accessory"
    ],
    "wof:name":"Zumtobel Lighting Pty Ltd",
    "wof:placetype":"venue"
},
  "geometry": {"coordinates":[153.039672852,-27.4574985504],"type":"Point"}
}