{
  "type": "Feature",
  "properties": {
    "addr:full":"Unit 3/ 211 Railway Ave Kelmscott WA 6111",
    "addr:housenumber":"/ 211",
    "addr:postcode":"6111",
    "addr:street":"Railway Ave",
    "iso:country":"AU",
    "sg:address":"Unit 3/ 211 Railway Ave",
    "sg:city":"Kelmscott",
    "sg:classifiers":[
        {
            "category":"Shopping",
            "subcategory":"Crafts & Fabrics",
            "type":"Retail Goods"
        }
    ],
    "sg:phone":"+61 8 9495 1876",
    "sg:postcode":"6111",
    "sg:province":"WA",
    "sg:tags":[
        "supply"
    ],
    "wof:name":"CottonWool",
    "wof:placetype":"venue"
},
  "geometry": {"coordinates":[116.013221741,-32.124786377],"type":"Point"}
}