{
  "type": "Feature",
  "properties": {
    "iso:country":"AU",
    "sg:address":"135 Macdonnell Rd",
    "sg:city":"Margate",
    "sg:classifiers":[
        {
            "category":"Home & Garden",
            "subcategory":"Building Materials",
            "type":"Retail Goods"
        }
    ],
    "sg:phone":"+61 412 300 603",
    "sg:postcode":"4019",
    "sg:province":"QLD",
    "sg:tags":[
        "lawn",
        "cutting",
        "maintenance"
    ],
    "wof:name":"The Gardening Professionals Redcliffe",
    "wof:placetype":"venue"
},
  "geometry": {"coordinates":[153.098999023,-27.2363643646],"type":"Point"}
}