{
  "type": "Feature",
  "properties": {
    "addr:full":"17 McIntyre St Mornington TAS 7018",
    "addr:housenumber":"17",
    "addr:postcode":"7018",
    "addr:street":"Mcintyre St",
    "iso:country":"AU",
    "sg:address":"17 McIntyre St",
    "sg:city":"Mornington",
    "sg:classifiers":[
        {
            "category":"Farming",
            "subcategory":"Fish & Marine Products",
            "type":"Manufacturing & Wholesale Goods"
        }
    ],
    "sg:phone":"+61 3 6245 1744",
    "sg:postcode":"7018",
    "sg:province":"TAS",
    "sg:tags":[
        "production",
        "seafood",
        "processing"
    ],
    "wof:name":"Tas Live Abalone Pty Ltd",
    "wof:placetype":"venue"
},
  "geometry": {"coordinates":[147.39500427199999,-42.8617210388],"type":"Point"}
}