{
  "type": "Feature",
  "properties": {
    "addr:full":"Takalvan St West Bundaberg QLD 4670",
    "addr:postcode":"4670",
    "addr:street":"Takalvan St West",
    "iso:country":"AU",
    "sg:address":"Takalvan St",
    "sg:city":"West Bundaberg",
    "sg:classifiers":[
        {
            "category":"Autos & Motor Vehicles",
            "subcategory":"Automobile Sales",
            "type":"Retail Goods"
        }
    ],
    "sg:phone":"+61 7 4150 1333",
    "sg:postcode":"4670",
    "sg:province":"QLD",
    "sg:tags":[
        "car",
        "used"
    ],
    "wof:name":"Ross Gray Used Cars",
    "wof:placetype":"venue"
},
  "geometry": {"coordinates":[152.33720398,-24.8693771362],"type":"Point"}
}