{
  "type": "Feature",
  "properties": {
    "addr:full":"278 Warrigal Rd Cheltenham VIC 3192",
    "addr:housenumber":"278",
    "addr:postcode":"3192",
    "addr:street":"Warrigal Rd",
    "iso:country":"AU",
    "sg:address":"278 Warrigal Rd",
    "sg:city":"Cheltenham",
    "sg:classifiers":[
        {
            "category":"Communications",
            "subcategory":"Television Station",
            "type":"Services"
        }
    ],
    "sg:phone":"+61 3 9584 5492",
    "sg:postcode":"3192",
    "sg:province":"VIC",
    "sg:tags":[
        "wholesaler",
        "spare",
        "part",
        "mfrs"
    ],
    "wof:name":"A & S Profix",
    "wof:placetype":"venue"
},
  "geometry": {"coordinates":[145.07408142099999,-37.9687652588],"type":"Point"}
}