{
  "type": "Feature",
  "properties": {
    "addr:full":"187 Riversdale Rd Hawthorn VIC 3122",
    "addr:housenumber":"187",
    "addr:postcode":"3122",
    "addr:street":"Riversdale Rd",
    "iso:country":"AU",
    "sg:address":"187 Riversdale Rd",
    "sg:city":"Hawthorn",
    "sg:classifiers":[
        {
            "category":"Autos & Motor Vehicles",
            "subcategory":"Fuel & Gas Station",
            "type":"Retail Goods"
        }
    ],
    "sg:phone":"+61 3 9818 6401",
    "sg:postcode":"3122",
    "sg:province":"VIC",
    "wof:name":"Shell Auburn",
    "wof:placetype":"venue"
},
  "geometry": {"coordinates":[145.0418396,-37.8294906616],"type":"Point"}
}