{
  "type": "Feature",
  "properties": {
    "iso:country":"AU",
    "sg:address":"Lvl 1, 185 Faraday St",
    "sg:city":"Carlton",
    "sg:classifiers":[
        {
            "category":"Building & Trades",
            "subcategory":"Pest Control",
            "type":"Services"
        }
    ],
    "sg:phone":"+61 3 9349 1200",
    "sg:postcode":"3053",
    "sg:province":"VIC",
    "sg:tags":[
        "wholesaler",
        "mfrs",
        "walking",
        "umbrella",
        "stick"
    ],
    "wof:name":"Boston Umbrella Company",
    "wof:placetype":"venue"
},
  "geometry": {"coordinates":[144.968475342,-37.7989044189],"type":"Point"}
}