{
  "type": "Feature",
  "properties": {
    "iso:country":"AU",
    "sg:address":"8 Henley Rd",
    "sg:city":"Homebush West",
    "sg:classifiers":[
        {
            "category":"Health Services",
            "subcategory":"Optometrist",
            "type":"Services"
        }
    ],
    "sg:phone":"+61 2 9746 6016",
    "sg:postcode":"2140",
    "sg:province":"NSW",
    "wof:name":"Tan A Soo Optmtrst",
    "wof:placetype":"venue"
},
  "geometry": {"coordinates":[151.070144653,-33.8658027649],"type":"Point"}
}