{
  "type": "Feature",
  "properties": {
    "iso:country":"AU",
    "sg:address":"1 Sheehan St",
    "sg:city":"Milton",
    "sg:classifiers":[
        {
            "category":"Travel",
            "subcategory":"Hotels & Motels",
            "type":"Entertainment"
        }
    ],
    "sg:phone":"+61 7 3870 8411",
    "sg:postcode":"4064",
    "sg:province":"QLD",
    "wof:name":"Casa Vivere",
    "wof:placetype":"venue"
},
  "geometry": {"coordinates":[153.00355529800001,-27.470615387],"type":"Point"}
}