{
  "type": "Feature",
  "properties": {
    "addr:full":"14 St. Lawrence Drv Beechboro WA 6063",
    "addr:housenumber":"14",
    "addr:postcode":"6063",
    "addr:street":"St. Lawrence Drv",
    "iso:country":"AU",
    "sg:address":"14 St. Lawrence Drv",
    "sg:city":"Beechboro",
    "sg:classifiers":[
        {
            "category":"Communications",
            "subcategory":"Film & Video Production",
            "type":"Services"
        }
    ],
    "sg:phone":"+61 419 967 872",
    "sg:postcode":"6063",
    "sg:province":"WA",
    "sg:tags":[
        "information",
        "recorded",
        "telephone"
    ],
    "wof:name":"On Hold FM Australia",
    "wof:placetype":"venue"
},
  "geometry": {"coordinates":[115.93155670199999,-31.8641738892],"type":"Point"}
}