{
  "type": "Feature",
  "properties": {
    "iso:country":"AU",
    "sg:address":"125 Great Western Hwy",
    "sg:city":"Westmead",
    "sg:classifiers":[
        {
            "category":"Autos & Motor Vehicles",
            "subcategory":"Fuel & Gas Station",
            "type":"Retail Goods"
        }
    ],
    "sg:phone":"+61 2 9635 7566",
    "sg:postcode":"2145",
    "sg:province":"NSW",
    "wof:name":"Ampol",
    "wof:placetype":"venue"
},
  "geometry": {"coordinates":[150.99203491200001,-33.8189048767],"type":"Point"}
}