{
  "type": "Feature",
  "properties": {
    "addr:full":"53 Upper St Bega NSW 2550",
    "addr:housenumber":"53",
    "addr:postcode":"2550",
    "addr:street":"Upper St",
    "iso:country":"AU",
    "sg:address":"53 Upper St",
    "sg:city":"Bega",
    "sg:classifiers":[
        {
            "category":"Health Services",
            "subcategory":"Health Practitioner",
            "type":"Services"
        }
    ],
    "sg:phone":"+61 2 6492 1106",
    "sg:postcode":"2550",
    "sg:province":"NSW",
    "sg:tags":[
        "physiotherapist"
    ],
    "wof:name":"Wills Jenni",
    "wof:placetype":"venue"
},
  "geometry": {"coordinates":[149.84361267099999,-36.6769485474],"type":"Point"}
}