{
  "type": "Feature",
  "properties": {
    "addr:full":"1 Hornsey Rd Homebush West NSW 2140",
    "addr:housenumber":"1",
    "addr:postcode":"2140",
    "addr:street":"Hornsey Rd",
    "iso:country":"AU",
    "sg:address":"1 Hornsey Rd",
    "sg:city":"Homebush West",
    "sg:classifiers":[
        {
            "category":"Shopping",
            "subcategory":"Musical Instruments",
            "type":"Retail Goods"
        }
    ],
    "sg:phone":"+61 2 9746 9775",
    "sg:postcode":"2140",
    "sg:province":"NSW",
    "sg:tags":[
        "musician",
        "agent"
    ],
    "wof:name":"Paul Burjan",
    "wof:placetype":"venue"
},
  "geometry": {"coordinates":[151.06849670400001,-33.8649864197],"type":"Point"}
}