{
  "type": "Feature",
  "properties": {
    "addr:full":"59 Gordon St Clontarf NSW 2093",
    "addr:housenumber":"59",
    "addr:postcode":"2093",
    "addr:street":"Gordon St",
    "iso:country":"AU",
    "sg:address":"59 Gordon St",
    "sg:city":"Clontarf",
    "sg:classifiers":[
        {
            "category":"Utilities",
            "subcategory":"Electric",
            "type":"Services"
        }
    ],
    "sg:phone":"+61 2 9907 6388",
    "sg:postcode":"2093",
    "sg:province":"NSW",
    "sg:tags":[
        "electrical",
        "contractor"
    ],
    "wof:name":"MacMil Electrical",
    "wof:placetype":"venue"
},
  "geometry": {"coordinates":[151.25581359899999,-33.8009796143],"type":"Point"}
}