{
  "type": "Feature",
  "properties": {
    "addr:full":"444 Glebe Rd Adamstown NSW 2289",
    "addr:housenumber":"444",
    "addr:postcode":"2289",
    "addr:street":"Glebe Rd",
    "iso:country":"AU",
    "sg:address":"444 Glebe Rd",
    "sg:city":"Adamstown",
    "sg:classifiers":[
        {
            "category":"Building & Trades",
            "subcategory":"Construction",
            "type":"Services"
        }
    ],
    "sg:phone":"+61 408 268 894",
    "sg:postcode":"2289",
    "sg:province":"NSW",
    "sg:tags":[
        "polishing",
        "sanding",
        "floor"
    ],
    "wof:name":"Brad's Floors Sanding & Polishing",
    "wof:placetype":"venue"
},
  "geometry": {"coordinates":[151.73570251500001,-32.9358673096],"type":"Point"}
}