{
  "type": "Feature",
  "properties": {
    "addr:full":"629 Princes Hwy Rockdale NSW 2216",
    "addr:housenumber":"629",
    "addr:postcode":"2216",
    "addr:street":"Princes Hwy",
    "iso:country":"AU",
    "sg:address":"629 Princes Hwy",
    "sg:city":"Rockdale",
    "sg:classifiers":[
        {
            "category":"Sports & Exercise",
            "subcategory":"Gym",
            "type":"Entertainment"
        }
    ],
    "sg:phone":"+61 2 9567 4994",
    "sg:postcode":"2216",
    "sg:province":"NSW",
    "sg:tags":[
        "health",
        "fitness"
    ],
    "wof:name":"Titan Fitness Centre",
    "wof:placetype":"venue"
},
  "geometry": {"coordinates":[151.13772599999999,-33.957954],"type":"Point"}
}