{
  "type": "Feature",
  "properties": {
    "addr:full":"PO Box 48 Coffin Bay SA 5607",
    "addr:postcode":"5607",
    "iso:country":"AU",
    "sg:address":"PO Box 48",
    "sg:city":"Coffin Bay",
    "sg:classifiers":[
        {
            "category":"Recreation",
            "subcategory":"Boat Charter",
            "type":"Entertainment"
        }
    ],
    "sg:phone":"+61 8 8685 4355",
    "sg:postcode":"5607",
    "sg:province":"SA",
    "wof:name":"Coffin Bay Fishing Charters",
    "wof:placetype":"venue"
},
  "geometry": {"coordinates":[135.462906,-34.62001],"type":"Point"}
}