{
  "type": "Feature",
  "properties": {
    "addr:full":"285 Cressy St Deniliquin NSW 2710",
    "addr:housenumber":"285",
    "addr:postcode":"2710",
    "addr:street":"Cressy St",
    "iso:country":"AU",
    "sg:address":"285 Cressy St",
    "sg:city":"Deniliquin",
    "sg:classifiers":[
        {
            "category":"Cafe",
            "type":"Food & Drink"
        }
    ],
    "sg:phone":"+61 3 5881 8584",
    "sg:postcode":"2710",
    "sg:province":"NSW",
    "wof:name":"Cafe Bakery 285",
    "wof:placetype":"venue"
},
  "geometry": {"coordinates":[144.961700439,-35.5277824402],"type":"Point"}
}