{
  "type": "Feature",
  "properties": {
    "iso:country":"AU",
    "sg:address":"1 Queen St",
    "sg:city":"Bendigo",
    "sg:classifiers":[
        {
            "category":"Home & Garden",
            "subcategory":"Carpets & Floor Coverings",
            "type":"Retail Goods"
        }
    ],
    "sg:phone":"+61 3 5441 5111",
    "sg:postcode":"3550",
    "sg:province":"VIC",
    "sg:tags":[
        "mattress"
    ],
    "wof:name":"Bedding Wholesalers",
    "wof:placetype":"venue"
},
  "geometry": {"coordinates":[144.281814575,-36.7604141235],"type":"Point"}
}