{
  "type": "Feature",
  "properties": {
    "iso:country":"AU",
    "sg:address":"163 A Pacific Hwy",
    "sg:city":"Charlestown",
    "sg:classifiers":[
        {
            "category":"Personal",
            "subcategory":"Beauty Salon",
            "type":"Services"
        }
    ],
    "sg:phone":"+61 2 4947 8877",
    "sg:postcode":"2290",
    "sg:province":"NSW",
    "sg:tags":[
        "hairdresser"
    ],
    "wof:name":"Woo Hoo The Colour Salon",
    "wof:placetype":"venue"
},
  "geometry": {"coordinates":[151.69642639200001,-32.9615097046],"type":"Point"}
}