{
  "type": "Feature",
  "properties": {
    "addr:full":"14 Mallee Rd Wagga Wagga NSW 2650",
    "addr:housenumber":"14",
    "addr:postcode":"2650",
    "addr:street":"Mallee Rd",
    "iso:country":"AU",
    "sg:address":"14 Mallee Rd",
    "sg:city":"Wagga Wagga",
    "sg:classifiers":[
        {
            "category":"Professional",
            "subcategory":"Art Services",
            "type":"Services"
        }
    ],
    "sg:phone":"+61 408 692 559",
    "sg:postcode":"2650",
    "sg:province":"NSW",
    "sg:tags":[
        "decorator",
        "painter"
    ],
    "wof:name":"Howarth K & M",
    "wof:placetype":"venue"
},
  "geometry": {"coordinates":[147.35003662099999,-35.1748199463],"type":"Point"}
}