{
  "type": "Feature",
  "properties": {
    "iso:country":"AU",
    "sg:address":"199 Abernethy Rd",
    "sg:city":"Belmont",
    "sg:classifiers":[
        {
            "category":"Communications",
            "type":"Services"
        }
    ],
    "sg:phone":"+61 8 9478 3875",
    "sg:postcode":"6104",
    "sg:province":"WA",
    "sg:tags":[
        "equipment",
        "radio"
    ],
    "wof:name":"Radio One Communications",
    "wof:placetype":"venue"
},
  "geometry": {"coordinates":[115.930488586,-31.9572544098],"type":"Point"}
}