{
  "type": "Feature",
  "properties": {
    "addr:full":"133 Parramatta Rd Granville NSW 2142",
    "addr:housenumber":"133",
    "addr:postcode":"2142",
    "addr:street":"Parramatta Rd",
    "iso:country":"AU",
    "sg:address":"133 Parramatta Rd",
    "sg:city":"Granville",
    "sg:classifiers":[
        {
            "category":"Organizations",
            "subcategory":"Labor Organization",
            "type":"Services"
        }
    ],
    "sg:phone":"+61 1300 732 698",
    "sg:postcode":"2142",
    "sg:province":"NSW",
    "sg:tags":[
        "union"
    ],
    "wof:name":"Australian Manufacturing Workers Union",
    "wof:placetype":"venue"
},
  "geometry": {"coordinates":[151.011627197,-33.8302154541],"type":"Point"}
}