{
  "type": "Feature",
  "properties": {
    "addr:full":"334/ Fletcher St Byron Bay NSW 2481",
    "addr:housenumber":"334 /",
    "addr:postcode":"2481",
    "addr:street":"Fletcher St",
    "iso:country":"AU",
    "sg:address":"334/ Fletcher St",
    "sg:city":"Byron Bay",
    "sg:classifiers":[
        {
            "category":"Manufacturing",
            "subcategory":"Jewelry",
            "type":"Manufacturing & Wholesale Goods"
        }
    ],
    "sg:phone":"+61 2 6680 9722",
    "sg:postcode":"2481",
    "sg:province":"NSW",
    "sg:tags":[
        "mfrg",
        "jeweller"
    ],
    "wof:name":"Kon Tiki Trading Co",
    "wof:placetype":"venue"
},
  "geometry": {"coordinates":[153.61323547399999,-28.6447486877],"type":"Point"}
}