{
  "type": "Feature",
  "properties": {
    "addr:full":"Shop 48 Nepean Square Shopping Cente Penrith NSW 2750",
    "addr:housenumber":"shop 48",
    "addr:postcode":"2750",
    "addr:street":"Nepean Square",
    "iso:country":"AU",
    "sg:address":"Shop 48",
    "sg:city":"Nepean Square Shopping Cente Penrith",
    "sg:classifiers":[
        {
            "category":"Personal",
            "subcategory":"Beauty Salon",
            "type":"Services"
        }
    ],
    "sg:phone":"+61 2 4722 5885",
    "sg:postcode":"2750",
    "sg:province":"NSW",
    "wof:name":"Boutique Skin",
    "wof:placetype":"venue"
},
  "geometry": {"coordinates":[150.66265869099999,-33.7568893433],"type":"Point"}
}