{
  "type": "Feature",
  "properties": {
    "iso:country":"AU",
    "sg:address":"Sunshine Hospital Furlong Rd",
    "sg:city":"Sunshine",
    "sg:classifiers":[
        {
            "category":"Health Services",
            "subcategory":"Doctor",
            "type":"Services"
        }
    ],
    "sg:phone":"+61 3 8345 0302",
    "sg:postcode":"3020",
    "sg:province":"VIC",
    "sg:tags":[
        "medical",
        "practitioner"
    ],
    "wof:name":"Bell Imaging Group",
    "wof:placetype":"venue"
},
  "geometry": {"coordinates":[144.830933,-37.762566],"type":"Point"}
}