{
  "type": "Feature",
  "properties": {
    "addr:full":"70 Peter St Box Hill North VIC 3129",
    "addr:housenumber":"70",
    "addr:postcode":"3129",
    "addr:street":"Peter St",
    "iso:country":"AU",
    "sg:address":"70 Peter St",
    "sg:city":"Box Hill North",
    "sg:classifiers":[
        {
            "category":"Building & Trades",
            "subcategory":"Construction",
            "type":"Services"
        }
    ],
    "sg:phone":"+61 3 9898 3363",
    "sg:postcode":"3129",
    "sg:province":"VIC",
    "sg:tags":[
        "polishing",
        "sanding",
        "floor"
    ],
    "wof:name":"Jacobs Phil",
    "wof:placetype":"venue"
},
  "geometry": {"coordinates":[145.12637329099999,-37.7992897034],"type":"Point"}
}