{
  "type": "Feature",
  "properties": {
    "iso:country":"AU",
    "sg:address":"16 Cadell St",
    "sg:city":"Goolwa",
    "sg:classifiers":[
        {
            "category":"Social Services",
            "type":"Services"
        }
    ],
    "sg:phone":"+61 412 370 945",
    "sg:postcode":"5214",
    "sg:province":"SA",
    "sg:tags":[
        "kinesiology"
    ],
    "wof:name":"Australian Kinesiology Association (S.A.)",
    "wof:placetype":"venue"
},
  "geometry": {"coordinates":[138.782745361,-35.501914978],"type":"Point"}
}