{
  "type": "Feature",
  "properties": {
    "addr:full":"110 Willoughby Rd Crows Nest NSW 2065",
    "addr:housenumber":"110",
    "addr:postcode":"2065",
    "addr:street":"Willoughby Rd",
    "iso:country":"AU",
    "sg:address":"110 Willoughby Rd",
    "sg:city":"Crows Nest",
    "sg:classifiers":[
        {
            "category":"Shopping",
            "subcategory":"Stationery & Office Supplies",
            "type":"Retail Goods"
        }
    ],
    "sg:phone":"+61 2 9439 0399",
    "sg:postcode":"2065",
    "sg:province":"NSW",
    "sg:tags":[
        "partition"
    ],
    "wof:name":"Multicon Interiors Pty Ltd",
    "wof:placetype":"venue"
},
  "geometry": {"coordinates":[151.20074462900001,-33.824432373],"type":"Point"}
}