{
  "type": "Feature",
  "properties": {
    "addr:full":"Fctry 2/ 2 Tuscan Crt Thomastown VIC 3074",
    "addr:housenumber":"2 / 2",
    "addr:postcode":"3074",
    "addr:street":"Fctry;Tuscan Crt",
    "iso:country":"AU",
    "sg:address":"Fctry 2/ 2 Tuscan Crt",
    "sg:city":"Thomastown",
    "sg:classifiers":[
        {
            "category":"Retail",
            "subcategory":"Auto Repair",
            "type":"Services"
        }
    ],
    "sg:phone":"+61 3 9460 8866",
    "sg:postcode":"3074",
    "sg:province":"VIC",
    "sg:tags":[
        "repairer",
        "motor",
        "engineer"
    ],
    "wof:name":"GZM Automotive",
    "wof:placetype":"venue"
},
  "geometry": {"coordinates":[145.00401306099999,-37.6883087158],"type":"Point"}
}