{
  "type": "Feature",
  "properties": {
    "addr:full":"Gorman House Ainslie Ave Braddon ACT 2612",
    "addr:postcode":"2612",
    "addr:street":"Ainslie Ave",
    "iso:country":"AU",
    "sg:address":"Gorman House Ainslie Ave",
    "sg:city":"Braddon",
    "sg:classifiers":[
        {
            "category":"Arts & Performance",
            "subcategory":"Dance",
            "type":"Entertainment"
        }
    ],
    "sg:phone":"+61 2 6247 9103",
    "sg:postcode":"2612",
    "sg:province":"ACT",
    "sg:tags":[
        "theatrical",
        "ballet",
        "tuition"
    ],
    "wof:name":"Ausdance ACT Inc.",
    "wof:placetype":"venue"
},
  "geometry": {"coordinates":[149.13929748499999,-35.2776870728],"type":"Point"}
}