{
  "type": "Feature",
  "properties": {
    "iso:country":"AU",
    "sg:address":"291a Hammond Rd",
    "sg:city":"Dandenong",
    "sg:classifiers":[
        {
            "category":"Fast Food",
            "type":"Food & Drink"
        }
    ],
    "sg:phone":"+61 3 9793 3431",
    "sg:postcode":"3175",
    "sg:province":"VIC",
    "sg:tags":[
        "away",
        "take"
    ],
    "wof:name":"Chris's Lunch Box",
    "wof:placetype":"venue"
},
  "geometry": {"coordinates":[145.20622253400001,-38.012046814],"type":"Point"}
}