{
  "type": "Feature",
  "properties": {
    "iso:country":"AU",
    "sg:address":"Cnr College Rd",
    "sg:city":"& Tanderra Way Karana Downs",
    "sg:classifiers":[
        {
            "category":"Food & Beverages",
            "subcategory":"Supermarket",
            "type":"Retail Goods"
        }
    ],
    "sg:phone":"+61 7 3201 2477",
    "sg:postcode":"4306",
    "sg:province":"QLD",
    "sg:tags":[
        "grocery",
        "store"
    ],
    "wof:name":"Buy-Rite Fresh Foodmarket",
    "wof:placetype":"venue"
},
  "geometry": {"coordinates":[152.82296752900001,-27.5472297668],"type":"Point"}
}