{
  "type": "Feature",
  "properties": {
    "iso:country":"AU",
    "sg:address":"46 Bonville St",
    "sg:city":"Urunga",
    "sg:classifiers":[
        {
            "category":"Health Services",
            "subcategory":"Doctor",
            "type":"Services"
        }
    ],
    "sg:phone":"+61 2 6655 6331",
    "sg:postcode":"2455",
    "sg:province":"NSW",
    "sg:tags":[
        "medical",
        "practitioner"
    ],
    "wof:name":"Marsden St John Dr",
    "wof:placetype":"venue"
},
  "geometry": {"coordinates":[153.020645,-30.498262],"type":"Point"}
}