{
  "type": "Feature",
  "properties": {
    "addr:full":"PO Box 1634 Green Valley NSW 2168",
    "addr:postcode":"2168",
    "iso:country":"AU",
    "sg:address":"PO Box 1634",
    "sg:city":"Green Valley",
    "sg:classifiers":[
        {
            "category":"Building & Trades",
            "subcategory":"Construction",
            "type":"Services"
        }
    ],
    "sg:phone":"+61 2 9608 9755",
    "sg:postcode":"2168",
    "sg:province":"NSW",
    "sg:tags":[
        "home",
        "air conditioning"
    ],
    "wof:name":"Tesla Electrical & Air Conditioning Pty Ltd",
    "wof:placetype":"venue"
},
  "geometry": {"coordinates":[150.86651611299999,-33.9027404785],"type":"Point"}
}