{
  "type": "Feature",
  "properties": {
    "addr:full":"13 Kingston St Gulliver QLD 4812",
    "addr:housenumber":"13",
    "addr:postcode":"4812",
    "addr:street":"Kingston St",
    "iso:country":"AU",
    "sg:address":"13 Kingston St",
    "sg:city":"Gulliver",
    "sg:classifiers":[
        {
            "category":"Personal",
            "subcategory":"Beauty Salon",
            "type":"Services"
        }
    ],
    "sg:phone":"+61 7 4779 1102",
    "sg:postcode":"4812",
    "sg:province":"QLD",
    "sg:tags":[
        "hairdresser"
    ],
    "wof:name":"Nola's Clip & Curl",
    "wof:placetype":"venue"
},
  "geometry": {"coordinates":[146.77896100000001,-19.284357],"type":"Point"}
}