{
  "type": "Feature",
  "properties": {
    "addr:full":"Dalry Rd Launching Place VIC 3139",
    "addr:postcode":"3139",
    "addr:street":"Dalry Rd",
    "iso:country":"AU",
    "sg:address":"Dalry Rd",
    "sg:city":"Launching Place",
    "sg:classifiers":[
        {
            "category":"Food & Beverages",
            "subcategory":"Fruits & Vegetables",
            "type":"Retail Goods"
        }
    ],
    "sg:phone":"+61 3 5967 3381",
    "sg:postcode":"3139",
    "sg:province":"VIC",
    "sg:tags":[
        "grower"
    ],
    "wof:name":"Ismail S",
    "wof:placetype":"venue"
},
  "geometry": {"coordinates":[145.580566406,-37.7594337463],"type":"Point"}
}