{
  "type": "Feature",
  "properties": {
    "addr:full":"Ophir Rd Orange NSW 2800",
    "addr:postcode":"2800",
    "addr:street":"Ophir Rd",
    "iso:country":"AU",
    "sg:address":"Ophir Rd",
    "sg:city":"Orange",
    "sg:classifiers":[
        {
            "category":"Building & Trades",
            "subcategory":"Construction",
            "type":"Services"
        }
    ],
    "sg:phone":"+61 2 6362 7004",
    "sg:postcode":"2800",
    "sg:province":"NSW",
    "sg:tags":[
        "earth",
        "excavating",
        "moving",
        "contractor"
    ],
    "wof:name":"Ralph Harvey",
    "wof:placetype":"venue"
},
  "geometry": {"coordinates":[149.12376403799999,-33.2824363708],"type":"Point"}
}