{
  "type": "Feature",
  "properties": {
    "addr:full":"575 Hunter St Newcastle West NSW 2302",
    "addr:housenumber":"575",
    "addr:postcode":"2302",
    "addr:street":"Hunter St",
    "iso:country":"AU",
    "sg:address":"575 Hunter St",
    "sg:city":"Newcastle West",
    "sg:classifiers":[
        {
            "category":"Banks & Credit Unions",
            "subcategory":"Investment Brokerage",
            "type":"Services"
        }
    ],
    "sg:phone":"+61 2 4927 8611",
    "sg:postcode":"2302",
    "sg:province":"NSW",
    "sg:tags":[
        "management",
        "property"
    ],
    "wof:name":"Newcastle Prestige Property",
    "wof:placetype":"venue"
},
  "geometry": {"coordinates":[151.76045199999999,-32.9258],"type":"Point"}
}