{
  "type": "Feature",
  "properties": {
    "iso:country":"AU",
    "sg:address":"55 crofts Crs",
    "sg:city":"Spence",
    "sg:classifiers":[
        {
            "category":"Organizations",
            "subcategory":"Non-profit Organization",
            "type":"Services"
        }
    ],
    "sg:phone":"+61 2 6258 8723",
    "sg:postcode":"2615",
    "sg:province":"ACT",
    "sg:tags":[
        "support",
        "disability",
        "organisation"
    ],
    "wof:name":"Spastic Centre of ACT & Southern Districts",
    "wof:placetype":"venue"
},
  "geometry": {"coordinates":[149.061447144,-35.1971511841],"type":"Point"}
}