{
  "type": "Feature",
  "properties": {
    "addr:full":"Shp3/ 17 Bridge St Sydney NSW 2000",
    "addr:housenumber":"17",
    "addr:postcode":"2000",
    "addr:street":"Bridge St",
    "iso:country":"AU",
    "sg:address":"Shp3/ 17 Bridge St",
    "sg:city":"Sydney",
    "sg:classifiers":[
        {
            "category":"Fast Food",
            "type":"Food & Drink"
        }
    ],
    "sg:phone":"+61 2 9252 3380",
    "sg:postcode":"2000",
    "sg:province":"NSW",
    "sg:tags":[
        "away",
        "take"
    ],
    "wof:name":"Jimmy's Recipe Malaysia",
    "wof:placetype":"venue"
},
  "geometry": {"coordinates":[151.20884704599999,-33.8637466431],"type":"Point"}
}