{
  "type": "Feature",
  "properties": {
    "addr:full":"Level 11 , 418A Elizabeth St Surry Hills NSW 2010",
    "addr:housenumber":"418a",
    "addr:postcode":"2010",
    "addr:street":"Elizabeth St",
    "iso:country":"AU",
    "sg:address":"Level 11 , 418A Elizabeth St",
    "sg:city":"Surry Hills",
    "sg:classifiers":[
        {
            "category":"Professional",
            "subcategory":"Computer Services",
            "type":"Services"
        }
    ],
    "sg:phone":"+61 2 9282 6926",
    "sg:postcode":"2010",
    "sg:province":"NSW",
    "sg:tags":[
        "training"
    ],
    "wof:name":"Global IT Technologies",
    "wof:placetype":"venue"
},
  "geometry": {"coordinates":[151.20840454099999,-33.8863525391],"type":"Point"}
}