{
  "type": "Feature",
  "properties": {
    "iso:country":"AU",
    "sg:address":"88- 120 Saunders St",
    "sg:city":"Pyrmont",
    "sg:classifiers":[
        {
            "category":"Shopping",
            "subcategory":"Computers & Home Electronics",
            "type":"Retail Goods"
        }
    ],
    "sg:phone":"+61 2 9518 4918",
    "sg:postcode":"2009",
    "sg:province":"NSW",
    "sg:tags":[
        "equipment",
        "multimedia"
    ],
    "wof:name":"Senses Interactive Pty Ltd",
    "wof:placetype":"venue"
},
  "geometry": {"coordinates":[151.191482544,-33.8703041077],"type":"Point"}
}