{
  "type": "Feature",
  "properties": {
    "iso:country":"AU",
    "sg:address":"83 Rundle Rd",
    "sg:city":"Salisbury South",
    "sg:classifiers":[
        {
            "category":"Building & Trades",
            "subcategory":"Construction",
            "type":"Services"
        }
    ],
    "sg:phone":"+61 8 8281 4300",
    "sg:postcode":"5106",
    "sg:province":"SA",
    "sg:tags":[
        "contractor"
    ],
    "wof:name":"V & A Builders & Contractors Pty Ltd",
    "wof:placetype":"venue"
},
  "geometry": {"coordinates":[138.64477500000001,-34.786339],"type":"Point"}
}