{
  "type": "Feature",
  "properties": {
    "iso:country":"AU",
    "sg:address":"1 Neptune Crt",
    "sg:city":"Shepparton",
    "sg:classifiers":[
        {
            "category":"Wholesale",
            "subcategory":"Machinery & Supplies",
            "type":"Manufacturing & Wholesale Goods"
        }
    ],
    "sg:phone":"+61 3 5831 8181",
    "sg:postcode":"3630",
    "sg:province":"VIC",
    "sg:tags":[
        "process",
        "instrument",
        "control"
    ],
    "wof:name":"Shepelec Instrumentation",
    "wof:placetype":"venue"
},
  "geometry": {"coordinates":[145.40045165999999,-36.3533439636],"type":"Point"}
}