{
  "type": "Feature",
  "properties": {
    "addr:full":"3/ 4 Mildon Rd Tuggerah NSW 2259",
    "addr:housenumber":"/ 4",
    "addr:postcode":"2259",
    "addr:street":"Mildon Rd",
    "iso:country":"AU",
    "sg:address":"3/ 4 Mildon Rd",
    "sg:city":"Tuggerah",
    "sg:classifiers":[
        {
            "category":"Home & Garden",
            "subcategory":"Building Materials",
            "type":"Retail Goods"
        }
    ],
    "sg:phone":"+61 2 4353 2787",
    "sg:postcode":"2259",
    "sg:province":"NSW",
    "sg:tags":[
        "lawn",
        "cutting",
        "maintenance"
    ],
    "wof:name":"Central Coast Crewcuts",
    "wof:placetype":"venue"
},
  "geometry": {"coordinates":[151.41960144000001,-33.3030471802],"type":"Point"}
}