{
  "type": "Feature",
  "properties": {
    "addr:full":"Port Welshpool Rd Welshpool VIC 3966",
    "addr:postcode":"3966",
    "addr:street":"Port Welshpool Rd",
    "iso:country":"AU",
    "sg:address":"Port Welshpool Rd",
    "sg:city":"Welshpool",
    "sg:classifiers":[
        {
            "category":"Utilities",
            "subcategory":"Refuse",
            "type":"Services"
        }
    ],
    "sg:phone":"+61 3 5688 1221",
    "sg:postcode":"3966",
    "sg:province":"VIC",
    "sg:tags":[
        "disposal",
        "reduction",
        "waste"
    ],
    "wof:name":"Welshpool Waste Disposal",
    "wof:placetype":"venue"
},
  "geometry": {"coordinates":[146.43754577600001,-38.6659889221],"type":"Point"}
}