{
  "type": "Feature",
  "properties": {
    "addr:full":"Shop 15 325 Hancock Rd Fairview Park SA 5126",
    "addr:housenumber":"shop 15 325",
    "addr:postcode":"5126",
    "addr:street":"Hancock Rd",
    "iso:country":"AU",
    "sg:address":"Shop 15 325 Hancock Rd",
    "sg:city":"Fairview Park",
    "sg:classifiers":[
        {
            "category":"Fast Food",
            "type":"Food & Drink"
        }
    ],
    "sg:phone":"+61 8 8289 5999",
    "sg:postcode":"5126",
    "sg:province":"SA",
    "sg:tags":[
        "away",
        "take"
    ],
    "wof:name":"Pizza Time",
    "wof:placetype":"venue"
},
  "geometry": {"coordinates":[138.71743774399999,-34.801525116],"type":"Point"}
}