{
  "type": "Feature",
  "properties": {
    "addr:full":"120 Princes Hwy Milton NSW 2538",
    "addr:housenumber":"120",
    "addr:postcode":"2538",
    "addr:street":"Princes Hwy",
    "iso:country":"AU",
    "sg:address":"120 Princes Hwy",
    "sg:city":"Milton",
    "sg:classifiers":[
        {
            "category":"Health Services",
            "subcategory":"Health Practitioner",
            "type":"Services"
        }
    ],
    "sg:phone":"+61 2 4455 7389",
    "sg:postcode":"2538",
    "sg:province":"NSW",
    "sg:tags":[
        "physiotherapist"
    ],
    "wof:name":"Milton Physiotherapist The",
    "wof:placetype":"venue"
},
  "geometry": {"coordinates":[150.44003295900001,-35.3176307678],"type":"Point"}
}