{
  "type": "Feature",
  "properties": {
    "addr:full":"PO Box 137 Corinda QLD 4075",
    "addr:postcode":"4075",
    "iso:country":"AU",
    "sg:address":"PO Box 137",
    "sg:city":"Corinda",
    "sg:classifiers":[
        {
            "category":"Building & Trades",
            "subcategory":"Construction",
            "type":"Services"
        }
    ],
    "sg:phone":"+61 7 3715 8771",
    "sg:postcode":"4075",
    "sg:province":"QLD",
    "sg:tags":[
        "pool",
        "swimming"
    ],
    "wof:name":"Prestige Pools Paving & Landscapes Pty Ltd",
    "wof:placetype":"venue"
},
  "geometry": {"coordinates":[152.98170471200001,-27.5393600464],"type":"Point"}
}