{
  "type": "Feature",
  "properties": {
    "addr:full":"Factory 3, 50 Holloway Drv Bayswater VIC 3153",
    "addr:housenumber":"50",
    "addr:postcode":"3153",
    "addr:street":"Holloway Drv",
    "iso:country":"AU",
    "sg:address":"Factory 3, 50 Holloway Drv",
    "sg:city":"Bayswater",
    "sg:classifiers":[
        {
            "category":"Home & Garden",
            "subcategory":"Building Materials",
            "type":"Retail Goods"
        }
    ],
    "sg:phone":"+61 3 9762 6561",
    "sg:postcode":"3153",
    "sg:province":"VIC",
    "sg:tags":[
        "skylight"
    ],
    "wof:name":"B J S Metal Industries Pty Ltd",
    "wof:placetype":"venue"
},
  "geometry": {"coordinates":[145.27981567399999,-37.8489494324],"type":"Point"}
}