{
  "type": "Feature",
  "properties": {
    "iso:country":"AU",
    "sg:address":"5 Greenwich Rd",
    "sg:city":"Greenwich",
    "sg:classifiers":[
        {
            "category":"Professional",
            "subcategory":"Employment Agencies",
            "type":"Services"
        }
    ],
    "sg:phone":"+61 2 9436 2111",
    "sg:postcode":"2065",
    "sg:province":"NSW",
    "sg:tags":[
        "entertainer",
        "agent"
    ],
    "wof:name":"Calling All Crew Pty Ltd",
    "wof:placetype":"venue"
},
  "geometry": {"coordinates":[151.187896728,-33.8255157471],"type":"Point"}
}