{
  "type": "Feature",
  "properties": {
    "addr:full":"21 The Concord Bundoora VIC 3083",
    "addr:housenumber":"21",
    "addr:postcode":"3083",
    "addr:street":"The Concord",
    "iso:country":"AU",
    "sg:address":"21 The Concord",
    "sg:city":"Bundoora",
    "sg:classifiers":[
        {
            "category":"Home & Garden",
            "subcategory":"Building Materials",
            "type":"Retail Goods"
        }
    ],
    "sg:phone":"+61 3 9467 6577",
    "sg:postcode":"3083",
    "sg:province":"VIC",
    "sg:tags":[
        "supply"
    ],
    "sg:website":"http://www.fifers.com.au",
    "wof:name":"Fifer's Building Supplies",
    "wof:placetype":"venue"
},
  "geometry": {"coordinates":[145.06933593799999,-37.7019271851],"type":"Point"}
}