{
  "type": "Feature",
  "properties": {
    "iso:country":"AU",
    "sg:address":"Sickle St",
    "sg:city":"Hope Island",
    "sg:classifiers":[
        {
            "category":"Fast Food",
            "type":"Food & Drink"
        }
    ],
    "sg:phone":"+61 7 5509 3437",
    "sg:postcode":"4212",
    "sg:province":"QLD",
    "sg:tags":[
        "away",
        "take"
    ],
    "wof:name":"Monzo's Tucker Box",
    "wof:placetype":"venue"
},
  "geometry": {"coordinates":[153.362457275,-27.8769645691],"type":"Point"}
}