{
  "type": "Feature",
  "properties": {
    "iso:country":"AU",
    "sg:address":"Unit 2/ 32 Bertram St",
    "sg:city":"Elsternwick",
    "sg:classifiers":[
        {
            "category":"Utilities",
            "subcategory":"Mobile Phone",
            "type":"Services"
        }
    ],
    "sg:phone":"+61 409 150 585",
    "sg:postcode":"3185",
    "sg:province":"VIC",
    "sg:tags":[
        "repair",
        "telephone"
    ],
    "wof:name":"Raf Electronics",
    "wof:placetype":"venue"
},
  "geometry": {"coordinates":[145.01017761200001,-37.8942604065],"type":"Point"}
}