{
  "type": "Feature",
  "properties": {
    "addr:full":"38-40 Export Drv Ernest QLD 4214",
    "addr:housenumber":"38-40",
    "addr:postcode":"4214",
    "addr:street":"Export Drv Ernest",
    "iso:country":"AU",
    "sg:address":"38-40 Export Drv",
    "sg:city":"Ernest",
    "sg:classifiers":[
        {
            "category":"Manufacturing",
            "subcategory":"Tools & Machinery",
            "type":"Manufacturing & Wholesale Goods"
        }
    ],
    "sg:phone":"+61 7 5563 1877",
    "sg:postcode":"4214",
    "sg:province":"QLD",
    "sg:tags":[
        "manufactured",
        "specially",
        "designed"
    ],
    "wof:name":"Hayes International Pty Ltd",
    "wof:placetype":"venue"
},
  "geometry": {"coordinates":[153.358932495,-27.9670162201],"type":"Point"}
}