{
  "type": "Feature",
  "properties": {
    "iso:country":"AU",
    "sg:address":"66 Marine Pde",
    "sg:city":"Elwood",
    "sg:classifiers":[
        {
            "category":"Professional",
            "subcategory":"Art Services",
            "type":"Services"
        }
    ],
    "sg:phone":"+61 3 9525 6350",
    "sg:postcode":"3184",
    "sg:province":"VIC",
    "sg:tags":[
        "interior",
        "decorator"
    ],
    "wof:name":"Decortech Pty Ltd",
    "wof:placetype":"venue"
},
  "geometry": {"coordinates":[144.97740173299999,-37.8772659302],"type":"Point"}
}