{
  "type": "Feature",
  "properties": {
    "addr:full":"6 Lexington Pde Green Point NSW 2251",
    "addr:housenumber":"6",
    "addr:postcode":"2251",
    "addr:street":"Lexington Pde",
    "iso:country":"AU",
    "sg:address":"6 Lexington Pde",
    "sg:city":"Green Point",
    "sg:classifiers":[
        {
            "category":"Banks & Credit Unions",
            "subcategory":"Investment Brokerage",
            "type":"Services"
        }
    ],
    "sg:phone":"+61 2 4363 1087",
    "sg:postcode":"2251",
    "sg:province":"NSW",
    "sg:tags":[
        "finance",
        "broker"
    ],
    "wof:name":"Fast Approval Finance Solutions",
    "wof:placetype":"venue"
},
  "geometry": {"coordinates":[151.356521606,-33.4602584839],"type":"Point"}
}