{
  "type": "Feature",
  "properties": {
    "iso:country":"AU",
    "sg:address":"Shop 2 797 Old Cleveland Rd",
    "sg:city":"Carina",
    "sg:classifiers":[
        {
            "category":"Personal",
            "subcategory":"Beauty Salon",
            "type":"Services"
        }
    ],
    "sg:phone":"+61 7 3398 3136",
    "sg:postcode":"4152",
    "sg:province":"QLD",
    "sg:tags":[
        "hairdresser"
    ],
    "wof:name":"Singletons Hair & Art Studio",
    "wof:placetype":"venue"
},
  "geometry": {"coordinates":[153.090576172,-27.4956417084],"type":"Point"}
}