{
  "type": "Feature",
  "properties": {
    "iso:country":"AU",
    "sg:address":"North Teven Rd",
    "sg:city":"North Teven",
    "sg:classifiers":[
        {
            "category":"Organizations",
            "subcategory":"Non-profit Organization",
            "type":"Services"
        }
    ],
    "sg:phone":"+61 2 6687 8580",
    "sg:postcode":"2478",
    "sg:province":"NSW",
    "sg:tags":[
        "support",
        "disability",
        "organisation"
    ],
    "wof:name":"The Riding For The Disabled Association (NSW)",
    "wof:placetype":"venue"
},
  "geometry": {"coordinates":[153.49531555199999,-28.8118534088],"type":"Point"}
}