{
  "type": "Feature",
  "properties": {
    "iso:country":"AU",
    "sg:address":"20 Armentieres St",
    "sg:city":"Kedron",
    "sg:classifiers":[
        {
            "category":"Home & Garden",
            "subcategory":"Carpets & Floor Coverings",
            "type":"Retail Goods"
        }
    ],
    "sg:phone":"+61 7 3861 0132",
    "sg:postcode":"4031",
    "sg:province":"QLD",
    "sg:tags":[
        "tile",
        "wall",
        "layer"
    ],
    "wof:name":"Ralph Serra & Co Pty Ltd",
    "wof:placetype":"venue"
},
  "geometry": {"coordinates":[153.030304,-27.407206],"type":"Point"}
}