{
  "type": "Feature",
  "properties": {
    "addr:full":"Cnr Cordeaux & Central Rds Figtree NSW 2525",
    "addr:postcode":"2525",
    "addr:street":"Cnr Cordeaux & Central Rds",
    "iso:country":"AU",
    "sg:address":"Cnr Cordeaux & Central Rds",
    "sg:city":"Figtree",
    "sg:classifiers":[
        {
            "category":"Building & Trades",
            "subcategory":"Construction",
            "type":"Services"
        }
    ],
    "sg:phone":"+61 2 4271 5621",
    "sg:postcode":"2525",
    "sg:province":"NSW",
    "sg:tags":[
        "earth",
        "excavating",
        "moving",
        "contractor"
    ],
    "wof:name":"Barnes G S",
    "wof:placetype":"venue"
},
  "geometry": {"coordinates":[150.83685302699999,-34.436340332],"type":"Point"}
}