{
  "type": "Feature",
  "properties": {
    "iso:country":"AU",
    "sg:address":"323 Canning Hwy",
    "sg:city":"Palmyra",
    "sg:classifiers":[
        {
            "category":"Autos & Motor Vehicles",
            "subcategory":"Auto Supplies",
            "type":"Retail Goods"
        }
    ],
    "sg:phone":"+61 8 9339 4455",
    "sg:postcode":"6157",
    "sg:province":"WA",
    "sg:tags":[
        "part",
        "cycles",
        "accessory"
    ],
    "wof:name":"Bolwell Scoota World",
    "wof:placetype":"venue"
},
  "geometry": {"coordinates":[115.783401,-32.036671],"type":"Point"}
}