{
  "type": "Feature",
  "properties": {
    "iso:country":"AU",
    "sg:address":"10 Langler St",
    "sg:city":"Victoria Park East",
    "sg:classifiers":[
        {
            "category":"Building & Trades",
            "subcategory":"Construction",
            "type":"Services"
        }
    ],
    "sg:phone":"+61 8 9470 3509",
    "sg:postcode":"6101",
    "sg:province":"WA",
    "sg:tags":[
        "installation",
        "air conditioning"
    ],
    "wof:name":"B & S Installations",
    "wof:placetype":"venue"
},
  "geometry": {"coordinates":[115.907569885,-31.9904537201],"type":"Point"}
}