{
  "type": "Feature",
  "properties": {
    "iso:country":"AU",
    "sg:address":"31 Grosvenor St",
    "sg:city":"Woollahra",
    "sg:classifiers":[
        {
            "category":"Health Services",
            "subcategory":"Doctor",
            "type":"Services"
        }
    ],
    "sg:phone":"+61 2 9386 5222",
    "sg:postcode":"2025",
    "sg:province":"NSW",
    "sg:tags":[
        "medical",
        "practitioner"
    ],
    "wof:name":"Pouw William J Dr",
    "wof:placetype":"venue"
},
  "geometry": {"coordinates":[151.249755859,-33.8904762268],"type":"Point"}
}