{
  "type": "Feature",
  "properties": {
    "iso:country":"AU",
    "sg:address":"57 Moss St",
    "sg:city":"Slacks Creek",
    "sg:classifiers":[
        {
            "category":"Home & Garden",
            "subcategory":"Building Materials",
            "type":"Retail Goods"
        }
    ],
    "sg:phone":"+61 7 3208 7766",
    "sg:postcode":"4127",
    "sg:province":"QLD",
    "sg:tags":[
        "supply"
    ],
    "wof:name":"Concrete Mixer Centre The",
    "wof:placetype":"venue"
},
  "geometry": {"coordinates":[153.123123169,-27.6217479706],"type":"Point"}
}