{
  "type": "Feature",
  "properties": {
    "iso:country":"AU",
    "sg:address":"33 Donaldson St",
    "sg:city":"Queens Park",
    "sg:classifiers":[
        {
            "category":"Building & Trades",
            "subcategory":"Landscaping Services",
            "type":"Services"
        }
    ],
    "sg:phone":"+61 414 345 939",
    "sg:postcode":"6107",
    "sg:province":"WA",
    "sg:tags":[
        "designer",
        "landscape",
        "contractor"
    ],
    "sg:website":"http://www.greenerlandscaping.com.au",
    "wof:name":"Greener Landscaping",
    "wof:placetype":"venue"
},
  "geometry": {"coordinates":[115.949256897,-32.0009880066],"type":"Point"}
}