{
  "type": "Feature",
  "properties": {
    "iso:country":"AU",
    "sg:address":"4 Palmer St",
    "sg:city":"Katherine",
    "sg:classifiers":[
        {
            "category":"Wholesale",
            "subcategory":"Machinery & Supplies",
            "type":"Manufacturing & Wholesale Goods"
        }
    ],
    "sg:phone":"+61 8 8971 0717",
    "sg:postcode":"0850",
    "sg:province":"NT",
    "sg:tags":[
        "engineer"
    ],
    "wof:name":"Katherine Machining",
    "wof:placetype":"venue"
},
  "geometry": {"coordinates":[132.29040499999999,-14.47601],"type":"Point"}
}