{
  "type": "Feature",
  "properties": {
    "addr:full":"2 Frank Crt Berrimah NT 0828",
    "addr:housenumber":"2",
    "addr:postcode":"nt 0828",
    "addr:street":"Frank Crt",
    "iso:country":"AU",
    "sg:address":"2 Frank Crt",
    "sg:city":"Berrimah",
    "sg:classifiers":[
        {
            "category":"Autos & Motor Vehicles",
            "subcategory":"Auto Supplies",
            "type":"Retail Goods"
        }
    ],
    "sg:phone":"+61 8 8984 4794",
    "sg:postcode":"0828",
    "sg:province":"NT",
    "sg:tags":[
        "part",
        "cycles",
        "accessory"
    ],
    "wof:name":"Baxters Motorcycle Engineering",
    "wof:placetype":"venue"
},
  "geometry": {"coordinates":[130.920089722,-12.4361953735],"type":"Point"}
}