{
  "type": "Feature",
  "properties": {
    "iso:country":"AU",
    "sg:address":"25 Steel St",
    "sg:city":"Redhead",
    "sg:classifiers":[
        {
            "category":"Personal",
            "subcategory":"Massage",
            "type":"Services"
        }
    ],
    "sg:phone":"+61 2 4944 7324",
    "sg:postcode":"2290",
    "sg:province":"NSW",
    "sg:tags":[
        "therapy"
    ],
    "wof:name":"Reeves C & V",
    "wof:placetype":"venue"
},
  "geometry": {"coordinates":[151.714447022,-33.012512207],"type":"Point"}
}