{
  "type": "Feature",
  "properties": {
    "addr:full":"88 Thomas St West Perth WA 6005",
    "addr:housenumber":"88",
    "addr:postcode":"6005",
    "addr:street":"Thomas St",
    "iso:country":"AU",
    "sg:address":"88 Thomas St",
    "sg:city":"West Perth",
    "sg:classifiers":[
        {
            "category":"Manufacturing",
            "subcategory":"Metals",
            "type":"Manufacturing & Wholesale Goods"
        }
    ],
    "sg:phone":"+61 1300 724 271",
    "sg:postcode":"6005",
    "sg:province":"WA",
    "sg:tags":[
        "metallurgist"
    ],
    "wof:name":"Independent Metallurgical Operations Pty Ltd",
    "wof:placetype":"venue"
},
  "geometry": {"coordinates":[115.840042114,-31.9510040283],"type":"Point"}
}