{
  "type": "Feature",
  "properties": {
    "addr:full":"Shop 4/ 13 Hay St Port Macquarie NSW 2444",
    "addr:housenumber":"shop 4 / 13",
    "addr:postcode":"2444",
    "addr:street":"Hay St",
    "iso:country":"AU",
    "sg:address":"Shop 4/ 13 Hay St",
    "sg:city":"Port Macquarie",
    "sg:classifiers":[
        {
            "category":"Food & Beverages",
            "subcategory":"Meat & Fish",
            "type":"Retail Goods"
        }
    ],
    "sg:phone":"+61 2 6583 7721",
    "sg:postcode":"2444",
    "sg:province":"NSW",
    "sg:tags":[
        "seafood"
    ],
    "wof:name":"Mike's Seafoods",
    "wof:placetype":"venue"
},
  "geometry": {"coordinates":[152.909515,-31.429291],"type":"Point"}
}