{
  "type": "Feature",
  "properties": {
    "iso:country":"AU",
    "sg:address":"11 Chifley Crt",
    "sg:city":"Dingley",
    "sg:classifiers":[
        {
            "category":"Building & Trades",
            "subcategory":"Construction",
            "type":"Services"
        }
    ],
    "sg:phone":"+61 3 9558 1755",
    "sg:postcode":"3172",
    "sg:province":"VIC",
    "sg:tags":[
        "renovation",
        "alterations",
        "extension",
        "contractor"
    ],
    "wof:name":"Moorcroft Master Builders",
    "wof:placetype":"venue"
},
  "geometry": {"coordinates":[145.12538147000001,-37.9818649292],"type":"Point"}
}