{
  "type": "Feature",
  "properties": {
    "addr:full":"6 Myall Ave Blackwood SA 5051",
    "addr:housenumber":"6",
    "addr:postcode":"5051",
    "addr:street":"Myall Ave",
    "iso:country":"AU",
    "sg:address":"6 Myall Ave",
    "sg:city":"Blackwood",
    "sg:classifiers":[
        {
            "category":"Wholesale",
            "subcategory":"Drugs",
            "type":"Manufacturing & Wholesale Goods"
        }
    ],
    "sg:phone":"+61 418 815 552",
    "sg:postcode":"5051",
    "sg:province":"SA",
    "sg:tags":[
        "wholesaler",
        "pharmaceutical",
        "product",
        "mfrs"
    ],
    "wof:name":"McGloins Pty Ltd",
    "wof:placetype":"venue"
},
  "geometry": {"coordinates":[138.619247,-35.012814],"type":"Point"}
}