{
  "type": "Feature",
  "properties": {
    "iso:country":"AU",
    "sg:address":"2/52 Hammad St",
    "sg:city":"Palmyra",
    "sg:classifiers":[
        {
            "category":"Communications",
            "type":"Services"
        }
    ],
    "sg:phone":"+61 8 9438 3619",
    "sg:postcode":"6157",
    "sg:province":"WA",
    "sg:tags":[
        "translation"
    ],
    "wof:name":"Chinese Language & Translation Services",
    "wof:placetype":"venue"
},
  "geometry": {"coordinates":[115.78656,-32.039154],"type":"Point"}
}