{
  "type": "Feature",
  "properties": {
    "iso:country":"AU",
    "sg:address":"Geradis Building Shop 5 Old Port Wakefield Rd",
    "sg:city":"Virginia",
    "sg:classifiers":[
        {
            "category":"Home & Garden",
            "subcategory":"Garden Supply",
            "type":"Retail Goods"
        }
    ],
    "sg:phone":"+61 8 8380 8554",
    "sg:postcode":"5120",
    "sg:province":"SA",
    "sg:tags":[
        "fertilizer"
    ],
    "wof:name":"Bio-Tech Organics",
    "wof:placetype":"venue"
},
  "geometry": {"coordinates":[138.561203003,-34.668132782],"type":"Point"}
}