{
  "type": "Feature",
  "properties": {
    "addr:full":"Shop 2 38 William St Bathurst NSW 2795",
    "addr:housenumber":"shop;38",
    "addr:postcode":"2795",
    "addr:street":"William St",
    "iso:country":"AU",
    "sg:address":"Shop 2 38 William St",
    "sg:city":"Bathurst",
    "sg:classifiers":[
        {
            "category":"Fast Food",
            "type":"Food & Drink"
        }
    ],
    "sg:phone":"+61 2 6331 3722",
    "sg:postcode":"2795",
    "sg:province":"NSW",
    "sg:tags":[
        "away",
        "take"
    ],
    "wof:name":"Domino's Pizza",
    "wof:placetype":"venue"
},
  "geometry": {"coordinates":[149.578323364,-33.4198226929],"type":"Point"}
}