{
  "type": "Feature",
  "properties": {
    "addr:full":"Clarice Ave Enfield SA 5085",
    "addr:postcode":"5085",
    "addr:street":"Clarice Ave",
    "iso:country":"AU",
    "sg:address":"Clarice Ave",
    "sg:city":"Enfield",
    "sg:classifiers":[
        {
            "category":"Education",
            "subcategory":"School",
            "type":"Public Place"
        }
    ],
    "sg:phone":"+61 8 8343 6555",
    "sg:postcode":"5085",
    "sg:province":"SA",
    "sg:tags":[
        "state",
        "except",
        "nsw"
    ],
    "wof:name":"Enfield Primary",
    "wof:placetype":"venue"
},
  "geometry": {"coordinates":[138.60292053200001,-34.865940094],"type":"Point"}
}