{
  "type": "Feature",
  "properties": {
    "addr:full":"12 Chapple St Gympie QLD 4570",
    "addr:housenumber":"12",
    "addr:postcode":"4570",
    "addr:street":"Chapple St",
    "iso:country":"AU",
    "sg:address":"12 Chapple St",
    "sg:city":"Gympie",
    "sg:classifiers":[
        {
            "category":"Retail",
            "subcategory":"Repair Shop",
            "type":"Services"
        }
    ],
    "sg:phone":"+61 7 5482 3523",
    "sg:postcode":"4570",
    "sg:province":"QLD",
    "sg:tags":[
        "upholsterer"
    ],
    "wof:name":"Bradys Upholsterers",
    "wof:placetype":"venue"
},
  "geometry": {"coordinates":[152.67088317899999,-26.1861534119],"type":"Point"}
}