{
  "type": "Feature",
  "properties": {
    "addr:full":"148 Bluff Rd Black Rock VIC 3193",
    "addr:housenumber":"148",
    "addr:postcode":"3193",
    "addr:street":"Bluff Rd",
    "iso:country":"AU",
    "sg:address":"148 Bluff Rd",
    "sg:city":"Black Rock",
    "sg:classifiers":[
        {
            "category":"Education",
            "subcategory":"Special Training",
            "type":"Public Place"
        }
    ],
    "sg:phone":"+61 3 9533 4311",
    "sg:postcode":"3193",
    "sg:province":"VIC",
    "sg:tags":[
        "development"
    ],
    "wof:name":"Successful Organisation Strategies",
    "wof:placetype":"venue"
},
  "geometry": {"coordinates":[145.01795959500001,-37.9660568237],"type":"Point"}
}