{
  "type": "Feature",
  "properties": {
    "iso:country":"AU",
    "sg:address":"83 Princes Hwy",
    "sg:city":"Fairy Meadow",
    "sg:classifiers":[
        {
            "category":"Government",
            "subcategory":"Department Of Motor Vehicles",
            "type":"Public Place"
        }
    ],
    "sg:phone":"+61 2 4226 9344",
    "sg:postcode":"2519",
    "sg:province":"NSW",
    "sg:tags":[
        "wholesaler",
        "mfrs",
        "accessory"
    ],
    "wof:name":"Tidy Trays",
    "wof:placetype":"venue"
},
  "geometry": {"coordinates":[150.892212,-34.397148],"type":"Point"}
}