{
  "type": "Feature",
  "properties": {
    "addr:full":"133 Elizabeth Drv Liverpool NSW 2170",
    "addr:housenumber":"133",
    "addr:postcode":"2170",
    "addr:street":"Elizabeth Drv",
    "iso:country":"AU",
    "sg:address":"133 Elizabeth Drv",
    "sg:city":"Liverpool",
    "sg:classifiers":[
        {
            "category":"Professional",
            "subcategory":"Art Services",
            "type":"Services"
        }
    ],
    "sg:phone":"+61 2 9601 4766",
    "sg:postcode":"2170",
    "sg:province":"NSW",
    "sg:tags":[
        "graphic",
        "designer"
    ],
    "wof:name":"Coll Creativity Pty Ltd",
    "wof:placetype":"venue"
},
  "geometry": {"coordinates":[150.91328430199999,-33.9178581238],"type":"Point"}
}