{
  "type": "Feature",
  "properties": {
    "addr:full":"71 Pearson St Kangaroo Point QLD 4169",
    "addr:housenumber":"71",
    "addr:postcode":"4169",
    "addr:street":"Pearson St",
    "iso:country":"AU",
    "sg:address":"71 Pearson St",
    "sg:city":"Kangaroo Point",
    "sg:classifiers":[
        {
            "category":"Government",
            "subcategory":"Customs House",
            "type":"Public Place"
        }
    ],
    "sg:phone":"+61 7 3891 6733",
    "sg:postcode":"4169",
    "sg:province":"QLD",
    "sg:tags":[
        "title",
        "management",
        "stratum"
    ],
    "wof:name":"Brisbane Building Unit Management",
    "wof:placetype":"venue"
},
  "geometry": {"coordinates":[153.037277222,-27.4775657654],"type":"Point"}
}