{
  "type": "Feature",
  "properties": {
    "iso:country":"AU",
    "sg:address":"1- 3 Church St",
    "sg:city":"Traralgon",
    "sg:classifiers":[
        {
            "category":"Professional",
            "subcategory":"Engineering",
            "type":"Services"
        }
    ],
    "sg:phone":"+61 3 5174 1921",
    "sg:postcode":"3844",
    "sg:province":"VIC",
    "sg:tags":[
        "consulting",
        "engineer"
    ],
    "wof:name":"W A Moore & Associates",
    "wof:placetype":"venue"
},
  "geometry": {"coordinates":[146.53483581500001,-38.1985549927],"type":"Point"}
}