{
  "type": "Feature",
  "properties": {
    "addr:full":"9 Brown St Cervantes WA 6511",
    "addr:housenumber":"9",
    "addr:postcode":"6511",
    "addr:street":"Brown St",
    "iso:country":"AU",
    "sg:address":"9 Brown St",
    "sg:city":"Cervantes",
    "sg:classifiers":[
        {
            "category":"Building & Trades",
            "subcategory":"Construction",
            "type":"Services"
        }
    ],
    "sg:phone":"+61 8 9652 7066",
    "sg:postcode":"6511",
    "sg:province":"WA",
    "sg:tags":[
        "contractor"
    ],
    "wof:name":"Nambung Stabilised Earth",
    "wof:placetype":"venue"
},
  "geometry": {"coordinates":[115.068466,-30.496508],"type":"Point"}
}