{
  "type": "Feature",
  "properties": {
    "addr:full":"6/ 2 Rennie St Wetherill Park NSW 2164",
    "addr:housenumber":"/ 2",
    "addr:postcode":"2164",
    "addr:street":"Rennie St",
    "iso:country":"AU",
    "sg:address":"6/ 2 Rennie St",
    "sg:city":"Wetherill Park",
    "sg:classifiers":[
        {
            "category":"Retail",
            "subcategory":"Auto Rental",
            "type":"Services"
        }
    ],
    "sg:phone":"+61 2 9757 2161",
    "sg:postcode":"2164",
    "sg:province":"NSW",
    "sg:tags":[
        "chauffeur",
        "car",
        "hire",
        "driven",
        "limousine"
    ],
    "wof:name":"Sydney Limousines & Wedding Cars",
    "wof:placetype":"venue"
},
  "geometry": {"coordinates":[150.88746643100001,-33.852897644],"type":"Point"}
}