{
  "type": "Feature",
  "properties": {
    "addr:full":"1347 Tumoulin Rd Tumoulin QLD 4872",
    "addr:housenumber":"1347",
    "addr:postcode":"4872",
    "addr:street":"Tumoulin Rd",
    "iso:country":"AU",
    "sg:address":"1347 Tumoulin Rd",
    "sg:city":"Tumoulin",
    "sg:classifiers":[
        {
            "category":"Transit Center",
            "subcategory":"Freight",
            "type":"Transportation"
        }
    ],
    "sg:phone":"+61 7 4097 6468",
    "sg:postcode":"4872",
    "sg:province":"QLD",
    "sg:tags":[
        "honey",
        "merchant"
    ],
    "wof:name":"Gagarra Honey",
    "wof:placetype":"venue"
},
  "geometry": {"coordinates":[145.461425781,-17.5868415833],"type":"Point"}
}