{
  "type": "Feature",
  "properties": {
    "iso:country":"AU",
    "sg:address":"1 Minya Crt",
    "sg:city":"Rowville",
    "sg:classifiers":[
        {
            "category":"Education",
            "subcategory":"Music School",
            "type":"Public Place"
        }
    ],
    "sg:phone":"+61 3 9752 9428",
    "sg:postcode":"3178",
    "sg:province":"VIC",
    "sg:tags":[
        "singing",
        "teacher"
    ],
    "wof:name":"Monstar Music Singing Tuition",
    "wof:placetype":"venue"
},
  "geometry": {"coordinates":[145.26094055199999,-37.9080123901],"type":"Point"}
}