{
  "type": "Feature",
  "properties": {
    "iso:country":"AU",
    "sg:address":"11 Bralla Crt",
    "sg:city":"Ringwood North",
    "sg:classifiers":[
        {
            "category":"Building & Trades",
            "subcategory":"Construction",
            "type":"Services"
        }
    ],
    "sg:phone":"+61 3 9876 7078",
    "sg:postcode":"3134",
    "sg:province":"VIC",
    "sg:tags":[
        "fencing",
        "contractor"
    ],
    "wof:name":"JWC Fence Design",
    "wof:placetype":"venue"
},
  "geometry": {"coordinates":[145.254104614,-37.7878837585],"type":"Point"}
}