{
  "type": "Feature",
  "properties": {
    "addr:full":"Unit 38 The Anchorage 18 Masthead Drv Raby Bay QLD 4163",
    "addr:housenumber":"18",
    "addr:postcode":"4163",
    "addr:street":"Masthead Drv",
    "iso:country":"AU",
    "sg:address":"Unit 38 The Anchorage 18 Masthead Drv",
    "sg:city":"Raby Bay",
    "sg:classifiers":[
        {
            "category":"Shopping",
            "subcategory":"Mobile Phones",
            "type":"Retail Goods"
        }
    ],
    "sg:phone":"+61 500 800 831",
    "sg:postcode":"4163",
    "sg:province":"QLD",
    "sg:tags":[
        "telephone",
        "accessory"
    ],
    "wof:name":"Tony Webber Mobile Phones & Accessories",
    "wof:placetype":"venue"
},
  "geometry": {"coordinates":[153.268188477,-27.5224552155],"type":"Point"}
}