{
  "type": "Feature",
  "properties": {
    "addr:full":"Unit 10 398 Marion St Condell Park NSW 2200",
    "addr:housenumber":"398",
    "addr:postcode":"2200",
    "addr:street":"Marion St",
    "iso:country":"AU",
    "sg:address":"Unit 10 398 Marion St",
    "sg:city":"Condell Park",
    "sg:classifiers":[
        {
            "category":"Professional",
            "subcategory":"Engineering",
            "type":"Services"
        }
    ],
    "sg:phone":"+61 2 9791 0193",
    "sg:postcode":"2200",
    "sg:province":"NSW",
    "sg:tags":[
        "engineer"
    ],
    "wof:name":"Zanut Engineering Pty Ltd",
    "wof:placetype":"venue"
},
  "geometry": {"coordinates":[151.00176999999999,-33.916405],"type":"Point"}
}