{
  "type": "Feature",
  "properties": {
    "addr:full":"14 Conway Crs Blackbutt NSW 2529",
    "addr:housenumber":"14",
    "addr:postcode":"2529",
    "addr:street":"Conway Crs",
    "iso:country":"AU",
    "sg:address":"14 Conway Crs",
    "sg:city":"Blackbutt",
    "sg:classifiers":[
        {
            "category":"Personal",
            "subcategory":"Beauty Salon",
            "type":"Services"
        }
    ],
    "sg:phone":"+61 2 4257 0503",
    "sg:postcode":"2529",
    "sg:province":"NSW",
    "wof:name":"Mistique Nail Artistry & Beauty",
    "wof:placetype":"venue"
},
  "geometry": {"coordinates":[150.83128356899999,-34.5723190308],"type":"Point"}
}