{
  "type": "Feature",
  "properties": {
    "addr:full":"6 Manning Ave Eaglehawk VIC 3556",
    "addr:housenumber":"6",
    "addr:postcode":"3556",
    "addr:street":"Manning Ave",
    "iso:country":"AU",
    "sg:address":"6 Manning Ave",
    "sg:city":"Eaglehawk",
    "sg:classifiers":[
        {
            "category":"Utilities",
            "subcategory":"Water",
            "type":"Services"
        }
    ],
    "sg:phone":"+61 408 507 715",
    "sg:postcode":"3556",
    "sg:province":"VIC",
    "sg:tags":[
        "hot",
        "system"
    ],
    "wof:name":"John Cross Plumbing Service",
    "wof:placetype":"venue"
},
  "geometry": {"coordinates":[144.263595581,-36.7337036133],"type":"Point"}
}