{
  "type": "Feature",
  "properties": {
    "addr:full":"Shop 31 Logan Central Plaza Wembley Rd Woodridge QLD 4114",
    "addr:housenumber":"shop 31",
    "addr:postcode":"4114",
    "addr:street":"Wembley Rd",
    "iso:country":"AU",
    "sg:address":"Shop 31 Logan Central Plaza Wembley Rd",
    "sg:city":"Woodridge",
    "sg:classifiers":[
        {
            "category":"Banks & Credit Unions",
            "subcategory":"Bank",
            "type":"Services"
        }
    ],
    "sg:phone":"+61 7 3808 6852",
    "sg:postcode":"4114",
    "sg:province":"QLD",
    "wof:name":"Colonial State Bank",
    "wof:placetype":"venue"
},
  "geometry": {"coordinates":[153.107254028,-27.6409168243],"type":"Point"}
}