{
  "type": "Feature",
  "properties": {
    "addr:full":"2 Raglan Ave Edwardstown SA 5039",
    "addr:housenumber":"2",
    "addr:postcode":"5039",
    "addr:street":"Raglan Ave",
    "iso:country":"AU",
    "sg:address":"2 Raglan Ave",
    "sg:city":"Edwardstown",
    "sg:classifiers":[
        {
            "category":"Retail",
            "subcategory":"Auto Repair",
            "type":"Services"
        }
    ],
    "sg:phone":"+61 8 8293 4552",
    "sg:postcode":"5039",
    "sg:province":"SA",
    "sg:tags":[
        "testing",
        "inspection",
        "motor",
        "vehicle"
    ],
    "wof:name":"Hold Serv",
    "wof:placetype":"venue"
},
  "geometry": {"coordinates":[138.573562622,-34.9794883728],"type":"Point"}
}