{
  "type": "Feature",
  "properties": {
    "addr:full":"36 Fourteenth St Hepburn Springs VIC 3461",
    "addr:housenumber":"36",
    "addr:postcode":"3461",
    "addr:street":"Fourteenth St Hepburn Springs",
    "iso:country":"AU",
    "sg:address":"36 Fourteenth St",
    "sg:city":"Hepburn Springs",
    "sg:classifiers":[
        {
            "category":"Health Services",
            "subcategory":"Health Practitioner",
            "type":"Services"
        }
    ],
    "sg:phone":"+61 3 5348 3776",
    "sg:postcode":"3461",
    "sg:province":"VIC",
    "sg:tags":[
        "alternative"
    ],
    "wof:name":"Mai Yura Mai",
    "wof:placetype":"venue"
},
  "geometry": {"coordinates":[144.13174438499999,-37.3099403381],"type":"Point"}
}