{
  "type": "Feature",
  "properties": {
    "addr:full":"Shop 7, Myer City Centre 525 David St Albury NSW 2640",
    "addr:housenumber":"shop 7;525",
    "addr:postcode":"2640",
    "addr:street":"Myer City;David St",
    "iso:country":"AU",
    "sg:address":"Shop 7, Myer City Centre 525 David St",
    "sg:city":"Albury",
    "sg:classifiers":[
        {
            "category":"Utilities",
            "subcategory":"Mobile Phone",
            "type":"Services"
        }
    ],
    "sg:phone":"+61 2 6023 2937",
    "sg:postcode":"2640",
    "sg:province":"NSW",
    "sg:tags":[
        "repair",
        "telephone"
    ],
    "wof:name":"Network Communications",
    "wof:placetype":"venue"
},
  "geometry": {"coordinates":[146.92100524899999,-36.0806694031],"type":"Point"}
}