{
  "type": "Feature",
  "properties": {
    "addr:full":"Level 10, 234 George St Sydney NSW 2000",
    "addr:housenumber":"234",
    "addr:postcode":"2000",
    "addr:street":"George St",
    "iso:country":"AU",
    "sg:address":"Level 10, 234 George St",
    "sg:city":"Sydney",
    "sg:classifiers":[
        {
            "category":"Professional",
            "subcategory":"Employment Agencies",
            "type":"Services"
        }
    ],
    "sg:phone":"+61 2 8247 5700",
    "sg:postcode":"2000",
    "sg:province":"NSW",
    "wof:name":"Porterallen Hendren Pty Limited",
    "wof:placetype":"venue"
},
  "geometry": {"coordinates":[151.20765685999999,-33.8633384705],"type":"Point"}
}