{
  "type": "Feature",
  "properties": {
    "addr:full":"2 / 17 Wrights Pl Labrador QLD 4215",
    "addr:housenumber":"/ 17",
    "addr:postcode":"4215",
    "addr:street":"Wrights Pl",
    "iso:country":"AU",
    "sg:address":"2 / 17 Wrights Pl",
    "sg:city":"Labrador",
    "sg:classifiers":[
        {
            "category":"Transit Center",
            "subcategory":"Freight",
            "type":"Transportation"
        }
    ],
    "sg:phone":"+61 7 5500 5466",
    "sg:postcode":"4215",
    "sg:province":"QLD",
    "sg:tags":[
        "turner",
        "wood"
    ],
    "wof:name":"Anthony Hansen Woodworks",
    "wof:placetype":"venue"
},
  "geometry": {"coordinates":[153.38154602,-27.9355258942],"type":"Point"}
}