{
  "type": "Feature",
  "properties": {
    "addr:full":"1/ 48 O'Sullivans Beach Rd Lonsdale SA 5160",
    "addr:housenumber":"/ 48",
    "addr:postcode":"5160",
    "addr:street":"O'Sullivans Beach Rd",
    "iso:country":"AU",
    "sg:address":"1/ 48 O'Sullivans Beach Rd",
    "sg:city":"Lonsdale",
    "sg:classifiers":[
        {
            "category":"Autos & Motor Vehicles",
            "subcategory":"Auto Supplies",
            "type":"Retail Goods"
        }
    ],
    "sg:phone":"+61 8 8326 5459",
    "sg:postcode":"5160",
    "sg:province":"SA",
    "sg:tags":[
        "transmission",
        "equipment",
        "power"
    ],
    "wof:name":"BSC Motion Technology",
    "wof:placetype":"venue"
},
  "geometry": {"coordinates":[138.50384521500001,-35.1168632507],"type":"Point"}
}