{
  "type": "Feature",
  "properties": {
    "iso:country":"AU",
    "sg:address":"5 Albert St",
    "sg:city":"Blackburn",
    "sg:classifiers":[
        {
            "category":"Insurance",
            "subcategory":"Life Insurance",
            "type":"Services"
        }
    ],
    "sg:phone":"+61 3 9877 0623",
    "sg:postcode":"3130",
    "sg:province":"VIC",
    "wof:name":"Garretty J",
    "wof:placetype":"venue"
},
  "geometry": {"coordinates":[145.15289306599999,-37.8183097839],"type":"Point"}
}