{
  "type": "Feature",
  "properties": {
    "addr:full":"73 Mcintyre Rd Sunshine North VIC 3020",
    "addr:housenumber":"73",
    "addr:postcode":"3020",
    "addr:street":"Mcintyre Rd",
    "iso:country":"AU",
    "sg:address":"73 Mcintyre Rd",
    "sg:city":"Sunshine North",
    "sg:classifiers":[
        {
            "category":"Fast Food",
            "type":"Food & Drink"
        }
    ],
    "sg:phone":"+61 3 9364 9470",
    "sg:postcode":"3020",
    "sg:province":"VIC",
    "sg:tags":[
        "away",
        "take"
    ],
    "wof:name":"Verukas Gourmet Cafe",
    "wof:placetype":"venue"
},
  "geometry": {"coordinates":[144.83003199999999,-37.769131],"type":"Point"}
}