{
  "type": "Feature",
  "properties": {
    "iso:country":"AU",
    "sg:address":"Factory 10/ 477 Warrigal Rd",
    "sg:city":"Moorabbin",
    "sg:classifiers":[
        {
            "category":"Education",
            "subcategory":"Special Training",
            "type":"Public Place"
        }
    ],
    "sg:phone":"+61 3 9532 0542",
    "sg:postcode":"3189",
    "sg:province":"VIC",
    "sg:tags":[
        "school",
        "art"
    ],
    "wof:name":"K a l i n o w s k i",
    "wof:placetype":"venue"
},
  "geometry": {"coordinates":[145.07818603499999,-37.944934845],"type":"Point"}
}