{
  "type": "Feature",
  "properties": {
    "iso:country":"AU",
    "sg:address":"14 Rushdale St",
    "sg:city":"Knoxfield",
    "sg:classifiers":[
        {
            "category":"Wholesale",
            "subcategory":"Machinery & Supplies",
            "type":"Manufacturing & Wholesale Goods"
        }
    ],
    "sg:phone":"+61 3 9763 8255",
    "sg:postcode":"3180",
    "sg:province":"VIC",
    "sg:tags":[
        "agricultural"
    ],
    "wof:name":"Glenmac Sales & Service P/L",
    "wof:placetype":"venue"
},
  "geometry": {"coordinates":[145.2552948,-37.8953475952],"type":"Point"}
}