{
  "type": "Feature",
  "properties": {
    "iso:country":"AU",
    "sg:address":"199 Carp St",
    "sg:city":"Bega",
    "sg:classifiers":[
        {
            "category":"Shopping",
            "subcategory":"Mobile Phones",
            "type":"Retail Goods"
        }
    ],
    "sg:phone":"+61 2 6492 6711",
    "sg:postcode":"2550",
    "sg:province":"NSW",
    "sg:tags":[
        "telephone",
        "accessory"
    ],
    "wof:name":"TeleChoice",
    "wof:placetype":"venue"
},
  "geometry": {"coordinates":[149.84518432600001,-36.6743431091],"type":"Point"}
}