{
  "type": "Feature",
  "properties": {
    "iso:country":"AU",
    "sg:address":"Office 2B Canterbury Place 2 Kern Brothers Drv",
    "sg:city":"Kirwan",
    "sg:classifiers":[
        {
            "category":"Building & Trades",
            "subcategory":"Construction",
            "type":"Services"
        }
    ],
    "sg:phone":"+61 7 4723 6611",
    "sg:postcode":"4817",
    "sg:province":"QLD",
    "sg:tags":[
        "contractor"
    ],
    "wof:name":"Perry J. McDonald Constructions Pty Ltd",
    "wof:placetype":"venue"
},
  "geometry": {"coordinates":[146.72442599999999,-19.316826],"type":"Point"}
}