{
  "type": "Feature",
  "properties": {
    "addr:full":"PO Box 220 Mt Martha VIC 3934",
    "addr:postcode":"3934",
    "iso:country":"AU",
    "sg:address":"PO Box 220",
    "sg:city":"Mt Martha",
    "sg:classifiers":[
        {
            "category":"Organizations",
            "subcategory":"Professional Association",
            "type":"Services"
        }
    ],
    "sg:phone":"+61 421 889 750",
    "sg:postcode":"3934",
    "sg:province":"VIC",
    "sg:tags":[
        "web",
        "internet"
    ],
    "wof:name":"Harvey Media",
    "wof:placetype":"venue"
},
  "geometry": {"coordinates":[145.030853272,-38.2737808228],"type":"Point"}
}