{
  "type": "Feature",
  "properties": {
    "iso:country":"AU",
    "sg:address":"30 Uplands Drv",
    "sg:city":"Arundel",
    "sg:classifiers":[
        {
            "category":"Utilities",
            "subcategory":"Electric",
            "type":"Services"
        }
    ],
    "sg:phone":"+61 7 5563 3533",
    "sg:postcode":"4214",
    "sg:province":"QLD",
    "sg:tags":[
        "electrical",
        "contractor"
    ],
    "wof:name":"MEC Miami Electric Co",
    "wof:placetype":"venue"
},
  "geometry": {"coordinates":[153.35797119099999,-27.9554710388],"type":"Point"}
}