{
  "type": "Feature",
  "properties": {
    "addr:full":"34 Meyers St Bendigo VIC 3550",
    "addr:housenumber":"34",
    "addr:postcode":"3550",
    "addr:street":"Meyers St",
    "iso:country":"AU",
    "sg:address":"34 Meyers St",
    "sg:city":"Bendigo",
    "sg:classifiers":[
        {
            "category":"Organizations",
            "subcategory":"Membership Organization",
            "type":"Services"
        }
    ],
    "sg:phone":"+61 3 5443 8355",
    "sg:postcode":"3550",
    "sg:province":"VIC",
    "sg:tags":[
        "support",
        "health",
        "organisation"
    ],
    "wof:name":"Country AIDS Network",
    "wof:placetype":"venue"
},
  "geometry": {"coordinates":[144.28533935600001,-36.7601852417],"type":"Point"}
}