{
  "type": "Feature",
  "properties": {
    "addr:full":"Shed 2, 1 Krauss Ave, South Lismore NSW 2480",
    "addr:housenumber":"1",
    "addr:postcode":"2480",
    "addr:street":"Krauss Ave South",
    "iso:country":"AU",
    "sg:address":"Shed 2, 1",
    "sg:city":"Krauss Ave, South Lismore",
    "sg:classifiers":[
        {
            "category":"Retail",
            "subcategory":"Auto Repair",
            "type":"Services"
        }
    ],
    "sg:phone":"+61 412 485 900",
    "sg:postcode":"2480",
    "sg:province":"NSW",
    "sg:tags":[
        "automotive",
        "air conditioning"
    ],
    "wof:name":"Adrian Marsh On Farm Auto Air",
    "wof:placetype":"venue"
},
  "geometry": {"coordinates":[153.26449585,-28.8213119507],"type":"Point"}
}