{
  "type": "Feature",
  "properties": {
    "addr:full":"44- 60 Jacksons Rd Mulgrave VIC 3170",
    "addr:housenumber":"60",
    "addr:postcode":"3170",
    "addr:street":"Jacksons Rd",
    "iso:country":"AU",
    "sg:address":"44- 60 Jacksons Rd",
    "sg:city":"Mulgrave",
    "sg:classifiers":[
        {
            "category":"Farming",
            "subcategory":"Livestock Farm",
            "type":"Manufacturing & Wholesale Goods"
        }
    ],
    "sg:phone":"+61 3 9790 1000",
    "sg:postcode":"3170",
    "sg:province":"VIC",
    "sg:tags":[
        "school",
        "theological"
    ],
    "wof:name":"Churches of Christ Theological College",
    "wof:placetype":"venue"
},
  "geometry": {"coordinates":[145.194747925,-37.9280891418],"type":"Point"}
}