{
  "type": "Feature",
  "properties": {
    "addr:full":"17- 21 Lisbon St Fairfield East NSW 2165",
    "addr:housenumber":"21",
    "addr:postcode":"2165",
    "addr:street":"Lisbon St",
    "iso:country":"AU",
    "sg:address":"17- 21 Lisbon St",
    "sg:city":"Fairfield East",
    "sg:classifiers":[
        {
            "category":"Commercial Area",
            "type":"Public Place"
        }
    ],
    "sg:phone":"+61 2 9724 1795",
    "sg:postcode":"2165",
    "sg:province":"NSW",
    "sg:tags":[
        "heavy",
        "carrier"
    ],
    "wof:name":"Carways Pty Ltd",
    "wof:placetype":"venue"
},
  "geometry": {"coordinates":[150.98298645,-33.8716697693],"type":"Point"}
}