{
  "type": "Feature",
  "properties": {
    "addr:full":"126 Wallumatta Rd Newport NSW 2106",
    "addr:housenumber":"126",
    "addr:postcode":"2106",
    "addr:street":"Wallumatta Rd",
    "iso:country":"AU",
    "sg:address":"126 Wallumatta Rd",
    "sg:city":"Newport",
    "sg:classifiers":[
        {
            "category":"Building & Trades",
            "subcategory":"Construction",
            "type":"Services"
        }
    ],
    "sg:phone":"+61 2 9970 5050",
    "sg:postcode":"2106",
    "sg:province":"NSW",
    "sg:tags":[
        "spouting",
        "guttering"
    ],
    "wof:name":"Simpsons Home Improvements",
    "wof:placetype":"venue"
},
  "geometry": {"coordinates":[151.306030273,-33.6511688232],"type":"Point"}
}