{
  "type": "Feature",
  "properties": {
    "addr:full":"36 Lidgett St Bacchus Marsh VIC 3340",
    "addr:housenumber":"36",
    "addr:postcode":"3340",
    "addr:street":"Lidgett St",
    "iso:country":"AU",
    "sg:address":"36 Lidgett St",
    "sg:city":"Bacchus Marsh",
    "sg:classifiers":[
        {
            "category":"Building & Trades",
            "subcategory":"Landscaping Services",
            "type":"Services"
        }
    ],
    "sg:phone":"+61 425 370 100",
    "sg:postcode":"3340",
    "sg:province":"VIC",
    "sg:tags":[
        "stump",
        "tree",
        "felling",
        "removal"
    ],
    "wof:name":"Far Lane Tree & Stump Removals",
    "wof:placetype":"venue"
},
  "geometry": {"coordinates":[144.43319700000001,-37.671303],"type":"Point"}
}