{
  "type": "Feature",
  "properties": {
    "addr:full":"20 Illaiangi St Carlingford NSW 2118",
    "addr:housenumber":"20",
    "addr:postcode":"2118",
    "addr:street":"Illaiangi St",
    "iso:country":"AU",
    "sg:address":"20 Illaiangi St",
    "sg:city":"Carlingford",
    "sg:classifiers":[
        {
            "category":"Utilities",
            "subcategory":"Electric",
            "type":"Services"
        }
    ],
    "sg:phone":"+61 417 007 088",
    "sg:postcode":"2118",
    "sg:province":"NSW",
    "sg:tags":[
        "electrical",
        "contractor"
    ],
    "wof:name":"SMP Electrics",
    "wof:placetype":"venue"
},
  "geometry": {"coordinates":[151.058685303,-33.788936615],"type":"Point"}
}