{
  "type": "Feature",
  "properties": {
    "addr:full":"Unit 1/ 8 Kelray Pl Asquith NSW 2077",
    "addr:housenumber":"8",
    "addr:postcode":"2077",
    "addr:street":"Kelray Pl",
    "iso:country":"AU",
    "sg:address":"Unit 1/ 8 Kelray Pl",
    "sg:city":"Asquith",
    "sg:classifiers":[
        {
            "category":"Banks & Credit Unions",
            "subcategory":"Atm",
            "type":"Services"
        }
    ],
    "sg:phone":"+61 2 9477 7219",
    "sg:postcode":"2077",
    "sg:province":"NSW",
    "sg:tags":[
        "wholesaler",
        "mfrs",
        "shirt",
        "pyjama"
    ],
    "wof:name":"Tradition Country Clothing",
    "wof:placetype":"venue"
},
  "geometry": {"coordinates":[151.110137939,-33.6944236755],"type":"Point"}
}