{
  "type": "Feature",
  "properties": {
    "addr:full":"256 Abercrombie St Redfern NSW 2016",
    "addr:housenumber":"256",
    "addr:postcode":"2016",
    "addr:street":"Abercrombie St",
    "iso:country":"AU",
    "sg:address":"256 Abercrombie St",
    "sg:city":"Redfern",
    "sg:classifiers":[
        {
            "category":"Deli",
            "type":"Food & Drink"
        }
    ],
    "sg:phone":"+61 2 9699 2292",
    "sg:postcode":"2016",
    "sg:province":"NSW",
    "sg:tags":[
        "delicatessen"
    ],
    "wof:name":"Zervos A",
    "wof:placetype":"venue"
},
  "geometry": {"coordinates":[151.197021484,-33.8907394409],"type":"Point"}
}