{
  "type": "Feature",
  "properties": {
    "addr:full":"266 C Charters Towers Rd Hermit Park QLD 4812",
    "addr:housenumber":"266",
    "addr:postcode":"4812",
    "addr:street":"C Charters Towers Rd",
    "iso:country":"AU",
    "sg:address":"266 C Charters Towers Rd",
    "sg:city":"Hermit Park",
    "sg:classifiers":[
        {
            "category":"Real Estate",
            "subcategory":"Real Estate Agent",
            "type":"Services"
        }
    ],
    "sg:phone":"+61 7 4775 7777",
    "sg:postcode":"4812",
    "sg:province":"QLD",
    "wof:name":"Virgo Patterson Realty",
    "wof:placetype":"venue"
},
  "geometry": {"coordinates":[146.798889,-19.28104],"type":"Point"}
}