{
  "type": "Feature",
  "properties": {
    "addr:full":"Shop 3 Hunter Connection 109 Pitt St Sydney NSW 2000",
    "addr:housenumber":"shop 3;109",
    "addr:postcode":"2000",
    "addr:street":"Hunter Connection;Pitt St",
    "iso:country":"AU",
    "sg:address":"Shop 3 Hunter Connection 109 Pitt St",
    "sg:city":"Sydney",
    "sg:classifiers":[
        {
            "category":"Personal",
            "subcategory":"Beauty Salon",
            "type":"Services"
        }
    ],
    "sg:phone":"+61 2 9223 8435",
    "sg:postcode":"2000",
    "sg:province":"NSW",
    "sg:tags":[
        "hairdresser"
    ],
    "wof:name":"B Js Hair Care",
    "wof:placetype":"venue"
},
  "geometry": {"coordinates":[151.208450317,-33.8661270142],"type":"Point"}
}