{
  "type": "Feature",
  "properties": {
    "addr:full":"5 Rosslyn St Mile End South SA 5031",
    "addr:housenumber":"5",
    "addr:postcode":"5031",
    "addr:street":"Rosslyn St",
    "iso:country":"AU",
    "sg:address":"5 Rosslyn St",
    "sg:city":"Mile End South",
    "sg:classifiers":[
        {
            "category":"Manufacturing",
            "subcategory":"Retail Goods",
            "type":"Manufacturing & Wholesale Goods"
        }
    ],
    "sg:phone":"+61 8 8234 5677",
    "sg:postcode":"5031",
    "sg:province":"SA",
    "sg:tags":[
        "merchant",
        "pump",
        "mfrs"
    ],
    "wof:name":"Plasflo Irrigation",
    "wof:placetype":"venue"
},
  "geometry": {"coordinates":[138.571243286,-34.9326133728],"type":"Point"}
}