{
  "type": "Feature",
  "properties": {
    "addr:full":"78 Horne St Campbellfield VIC 3061",
    "addr:housenumber":"78",
    "addr:postcode":"3061",
    "addr:street":"Horne St",
    "iso:country":"AU",
    "sg:address":"78 Horne St",
    "sg:city":"Campbellfield",
    "sg:classifiers":[
        {
            "category":"Wholesale",
            "subcategory":"Auto Parts",
            "type":"Manufacturing & Wholesale Goods"
        }
    ],
    "sg:phone":"+61 3 9357 1435",
    "sg:postcode":"3061",
    "sg:province":"VIC",
    "sg:tags":[
        "recyclers"
    ],
    "wof:name":"T & H Wreckers",
    "wof:placetype":"venue"
},
  "geometry": {"coordinates":[144.96531677199999,-37.6804275513],"type":"Point"}
}