{
  "type": "Feature",
  "properties": {
    "addr:full":"Shop 5 225 Main Rd Blackwood SA 5051",
    "addr:housenumber":"shop 5 225",
    "addr:postcode":"5051",
    "addr:street":"Main Rd",
    "iso:country":"AU",
    "sg:address":"Shop 5 225 Main Rd",
    "sg:city":"Blackwood",
    "sg:classifiers":[
        {
            "category":"Health Services",
            "subcategory":"Chiropractor",
            "type":"Services"
        }
    ],
    "sg:phone":"+61 8 8278 6057",
    "sg:postcode":"5051",
    "sg:province":"SA",
    "wof:name":"Eden Hills Chiropractic Clinic",
    "wof:placetype":"venue"
},
  "geometry": {"coordinates":[138.61642499999999,-35.018879],"type":"Point"}
}