{
  "type": "Feature",
  "properties": {
    "iso:country":"AU",
    "sg:address":"May St",
    "sg:city":"Macleod",
    "sg:classifiers":[
        {
            "category":"Education",
            "subcategory":"School",
            "type":"Public Place"
        }
    ],
    "sg:phone":"+61 3 9459 0222",
    "sg:postcode":"3085",
    "sg:province":"VIC",
    "sg:tags":[
        "state",
        "except",
        "nsw"
    ],
    "wof:name":"Macleod College",
    "wof:placetype":"venue"
},
  "geometry": {"coordinates":[145.07301330600001,-37.7258110046],"type":"Point"}
}