{
  "type": "Feature",
  "properties": {
    "addr:full":"Elizabeth Ave Kippa-Ring QLD 4021",
    "addr:postcode":"4021",
    "addr:street":"Elizabeth Ave",
    "iso:country":"AU",
    "sg:address":"Elizabeth Ave",
    "sg:city":"Kippa-Ring",
    "sg:classifiers":[
        {
            "category":"Health Services",
            "subcategory":"Dentist",
            "type":"Services"
        }
    ],
    "sg:phone":"+61 7 3284 3867",
    "sg:postcode":"4021",
    "sg:province":"QLD",
    "wof:name":"School Dental Clinics",
    "wof:placetype":"venue"
},
  "geometry": {"coordinates":[153.084824,-27.22739],"type":"Point"}
}