{
  "type": "Feature",
  "properties": {
    "iso:country":"AU",
    "sg:address":"PO Box 566",
    "sg:city":"Revesby",
    "sg:classifiers":[
        {
            "category":"Health Services",
            "subcategory":"Dentist",
            "type":"Services"
        }
    ],
    "sg:phone":"+61 2 9349 6166",
    "sg:postcode":"2212",
    "sg:province":"NSW",
    "sg:tags":[
        "technician",
        "dental"
    ],
    "wof:name":"Southern Orthodontic Laboratories Pty Ltd",
    "wof:placetype":"venue"
},
  "geometry": {"coordinates":[151.01676900000001,-33.956928],"type":"Point"}
}