{
  "type": "Feature",
  "properties": {
    "addr:full":"Gowrie St Annerley QLD 4103",
    "addr:postcode":"4103",
    "addr:street":"Gowrie St",
    "iso:country":"AU",
    "sg:address":"Gowrie St",
    "sg:city":"Annerley",
    "sg:classifiers":[
        {
            "category":"Organizations",
            "subcategory":"Community Association",
            "type":"Services"
        }
    ],
    "sg:phone":"+61 7 3391 0709",
    "sg:postcode":"4103",
    "sg:province":"QLD",
    "sg:tags":[
        "organisation",
        "family",
        "welfare"
    ],
    "wof:name":"Management of Young Children Program",
    "wof:placetype":"venue"
},
  "geometry": {"coordinates":[153.03515625,-27.5088233948],"type":"Point"}
}