{
  "type": "Feature",
  "properties": {
    "addr:full":"3 / 2 Boston St Tea Gardens NSW 2324",
    "addr:housenumber":"/ 2",
    "addr:postcode":"2324",
    "addr:street":"Boston St",
    "iso:country":"AU",
    "sg:address":"3 / 2 Boston St",
    "sg:city":"Tea Gardens",
    "sg:classifiers":[
        {
            "category":"Building & Trades",
            "subcategory":"Construction",
            "type":"Services"
        }
    ],
    "sg:phone":"+61 2 4981 7211",
    "sg:postcode":"2324",
    "sg:province":"NSW",
    "sg:tags":[
        "contractor"
    ],
    "wof:name":"Cavalier Homes (Port Stephens) Pty Ltd",
    "wof:placetype":"venue"
},
  "geometry": {"coordinates":[152.15057373100001,-32.65599823],"type":"Point"}
}