{
  "type": "Feature",
  "properties": {
    "iso:country":"AU",
    "sg:address":"Shop 1 144 Camberwell Rd",
    "sg:city":"Hawthorn East",
    "sg:classifiers":[
        {
            "category":"Fast Food",
            "type":"Food & Drink"
        }
    ],
    "sg:phone":"+61 3 9882 5360",
    "sg:postcode":"3123",
    "sg:province":"VIC",
    "sg:tags":[
        "away",
        "take"
    ],
    "wof:name":"Powerline Cafe",
    "wof:placetype":"venue"
},
  "geometry": {"coordinates":[145.053756714,-37.8289375305],"type":"Point"}
}