{
  "type": "Feature",
  "properties": {
    "addr:full":"Suite 6, Mirrabooka Medical Centre cnr Yirrigan Dr & Ilkeston Pl Mirrabooka WA 6061",
    "addr:postcode":"6061",
    "addr:street":"Cnr Yirrigan Dr &;Pl",
    "iso:country":"AU",
    "sg:address":"Suite 6, Mirrabooka Medical Centre cnr Yirrigan Dr & Ilkeston Pl",
    "sg:city":"Mirrabooka",
    "sg:classifiers":[
        {
            "category":"Health Services",
            "subcategory":"Health Practitioner",
            "type":"Services"
        }
    ],
    "sg:phone":"+61 8 9345 1512",
    "sg:postcode":"6061",
    "sg:province":"WA",
    "sg:tags":[
        "physiotherapist"
    ],
    "wof:name":"Mirrabooka Physiotherapy Clinic",
    "wof:placetype":"venue"
},
  "geometry": {"coordinates":[115.859207153,-31.8719520569],"type":"Point"}
}