{
  "type": "Feature",
  "properties": {
    "iso:country":"AU",
    "sg:address":"Units 1-3/ 119 Fairey Rd",
    "sg:city":"Windsor",
    "sg:classifiers":[
        {
            "category":"Professional",
            "type":"Services"
        }
    ],
    "sg:phone":"+61 2 4587 8421",
    "sg:postcode":"2756",
    "sg:province":"NSW",
    "sg:tags":[
        "coating",
        "powder"
    ],
    "wof:name":"Snowflake Blast & Powder Coat",
    "wof:placetype":"venue"
},
  "geometry": {"coordinates":[150.81497192399999,-33.6248283386],"type":"Point"}
}