{
  "type": "Feature",
  "properties": {
    "addr:full":"13 Union Rd Dandenong VIC 3175",
    "addr:housenumber":"13",
    "addr:postcode":"3175",
    "addr:street":"Union Rd",
    "iso:country":"AU",
    "sg:address":"13 Union Rd",
    "sg:city":"Dandenong",
    "sg:classifiers":[
        {
            "category":"Professional",
            "subcategory":"Accounting & Tax Preparation",
            "type":"Services"
        }
    ],
    "sg:phone":"+61 3 9769 2840",
    "sg:postcode":"3175",
    "sg:province":"VIC",
    "sg:tags":[
        "record",
        "business",
        "destruction"
    ],
    "wof:name":"Allpaper Destruction",
    "wof:placetype":"venue"
},
  "geometry": {"coordinates":[145.20420837399999,-38.0076980591],"type":"Point"}
}