{
  "type": "Feature",
  "properties": {
    "addr:full":"Cnr Sth Gippsland Hwy & McDowell Rd Hampton Park VIC 3976",
    "addr:postcode":"3976",
    "addr:street":"Cnr Sth Gippsland Hwy & Mcdowell Rd",
    "iso:country":"AU",
    "sg:address":"Cnr Sth Gippsland Hwy & McDowell Rd",
    "sg:city":"Hampton Park",
    "sg:classifiers":[
        {
            "category":"Autos & Motor Vehicles",
            "subcategory":"Fuel & Gas Station",
            "type":"Retail Goods"
        }
    ],
    "sg:phone":"+61 3 9799 0139",
    "sg:postcode":"3976",
    "sg:province":"VIC",
    "wof:name":"Shell Hampton Park",
    "wof:placetype":"venue"
},
  "geometry": {"coordinates":[145.25514221200001,-38.0467033386],"type":"Point"}
}