{
  "type": "Feature",
  "properties": {
    "addr:full":"561 Main Rd Glendale NSW 2285",
    "addr:housenumber":"561",
    "addr:postcode":"2285",
    "addr:street":"Main Rd",
    "iso:country":"AU",
    "sg:address":"561 Main Rd",
    "sg:city":"Glendale",
    "sg:classifiers":[
        {
            "category":"Shopping",
            "subcategory":"Bicycles & Sporting Goods",
            "type":"Retail Goods"
        }
    ],
    "sg:phone":"+61 2 4953 7766",
    "sg:postcode":"2285",
    "sg:province":"NSW",
    "sg:tags":[
        "chemical",
        "equipment",
        "pool",
        "swimming"
    ],
    "wof:name":"Driclad",
    "wof:placetype":"venue"
},
  "geometry": {"coordinates":[151.62396240199999,-32.9445037842],"type":"Point"}
}