{
  "type": "Feature",
  "properties": {
    "addr:full":"PO Box 1171 Hampton North VIC 3188",
    "addr:postcode":"3188",
    "iso:country":"AU",
    "sg:address":"PO Box 1171",
    "sg:city":"Hampton North",
    "sg:classifiers":[
        {
            "category":"Transit Center",
            "subcategory":"Passenger",
            "type":"Transportation"
        }
    ],
    "sg:phone":"+61 3 9598 2315",
    "sg:postcode":"3188",
    "sg:province":"VIC",
    "sg:tags":[
        "wholesaler",
        "mfrs",
        "toiletry",
        "perfume"
    ],
    "wof:name":"Perfume On Tap",
    "wof:placetype":"venue"
},
  "geometry": {"coordinates":[144.998123169,-37.9300117493],"type":"Point"}
}