{
  "type": "Feature",
  "properties": {
    "addr:full":"72 Lillydale Rd North Boyanup WA 6237",
    "addr:housenumber":"72",
    "addr:postcode":"6237",
    "addr:street":"Lillydale Rd North Boyanup",
    "iso:country":"AU",
    "sg:address":"72 Lillydale Rd",
    "sg:city":"North Boyanup",
    "sg:classifiers":[
        {
            "category":"Building & Trades",
            "subcategory":"Construction",
            "type":"Services"
        }
    ],
    "sg:phone":"+61 8 9795 8209",
    "sg:postcode":"6237",
    "sg:province":"WA",
    "sg:tags":[
        "concrete",
        "contractor"
    ],
    "wof:name":"Bunbury Concrete Contractors",
    "wof:placetype":"venue"
},
  "geometry": {"coordinates":[115.690071,-33.401222],"type":"Point"}
}