{
  "type": "Feature",
  "properties": {
    "iso:country":"AU",
    "sg:address":"Level 3, Diagonal Rd",
    "sg:city":"Oaklands Park",
    "sg:classifiers":[
        {
            "category":"Cinema",
            "subcategory":"Movie Theater",
            "type":"Entertainment"
        }
    ],
    "sg:phone":"+61 8 8296 7788",
    "sg:postcode":"5046",
    "sg:province":"SA",
    "wof:name":"Greater Union Organisation Pty Ltd",
    "wof:placetype":"venue"
},
  "geometry": {"coordinates":[138.543442,-35.012669],"type":"Point"}
}