{
  "type": "Feature",
  "properties": {
    "iso:country":"AU",
    "sg:address":"96 Victoria Rd",
    "sg:city":"Hawthorn East",
    "sg:classifiers":[
        {
            "category":"Professional",
            "subcategory":"Engineering",
            "type":"Services"
        }
    ],
    "sg:phone":"+61 3 9882 3843",
    "sg:postcode":"3123",
    "sg:province":"VIC",
    "sg:tags":[
        "consulting",
        "engineer"
    ],
    "wof:name":"D K Goddard Enterprises",
    "wof:placetype":"venue"
},
  "geometry": {"coordinates":[145.051803589,-37.8228607178],"type":"Point"}
}