{
  "type": "Feature",
  "properties": {
    "addr:full":"Shp13/ 41 Shepherds Drv Cherrybrook NSW 2126",
    "addr:housenumber":"41",
    "addr:postcode":"2126",
    "addr:street":"Shepherds Drv",
    "iso:country":"AU",
    "sg:address":"Shp13/ 41 Shepherds Drv",
    "sg:city":"Cherrybrook",
    "sg:classifiers":[
        {
            "category":"Shopping",
            "subcategory":"Jewelry",
            "type":"Retail Goods"
        }
    ],
    "sg:phone":"+61 2 9980 7962",
    "sg:postcode":"2126",
    "sg:province":"NSW",
    "sg:tags":[
        "jeweller"
    ],
    "wof:name":"Chloe Hart",
    "wof:placetype":"venue"
},
  "geometry": {"coordinates":[151.04318237300001,-33.7216873169],"type":"Point"}
}