{
  "type": "Feature",
  "properties": {
    "addr:full":"PO Box 270 Hornsby NSW 2077",
    "addr:postcode":"2077",
    "iso:country":"AU",
    "sg:address":"PO Box 270",
    "sg:city":"Hornsby",
    "sg:classifiers":[
        {
            "category":"Professional",
            "subcategory":"Art Services",
            "type":"Services"
        }
    ],
    "sg:phone":"+61 406 122 831",
    "sg:postcode":"2077",
    "sg:province":"NSW",
    "sg:tags":[
        "decorator",
        "painter"
    ],
    "wof:name":"Aust Johns Painting & Decorating Pty Ltd",
    "wof:placetype":"venue"
},
  "geometry": {"coordinates":[151.09687805199999,-33.7007789612],"type":"Point"}
}