{
  "type": "Feature",
  "properties": {
    "iso:country":"AU",
    "sg:address":"Port Germein Rd",
    "sg:city":"Port Pirie",
    "sg:classifiers":[
        {
            "category":"Building & Trades",
            "subcategory":"Construction",
            "type":"Services"
        }
    ],
    "sg:phone":"+61 419 214 300",
    "sg:postcode":"5540",
    "sg:province":"SA",
    "sg:tags":[
        "earth",
        "excavating",
        "moving",
        "contractor"
    ],
    "wof:name":"Flinders Earthmoving & Blue Metal Supplies",
    "wof:placetype":"venue"
},
  "geometry": {"coordinates":[138.02720642099999,-33.1833839417],"type":"Point"}
}