{
  "type": "Feature",
  "properties": {
    "addr:full":"Cummins St Unanderra NSW 2526",
    "addr:postcode":"2526",
    "addr:street":"Cummins St",
    "iso:country":"AU",
    "sg:address":"Cummins St",
    "sg:city":"Unanderra",
    "sg:classifiers":[
        {
            "category":"Education",
            "subcategory":"School",
            "type":"Public Place"
        }
    ],
    "sg:phone":"+61 2 4271 3550",
    "sg:postcode":"2526",
    "sg:province":"NSW",
    "wof:name":"St Pius X School",
    "wof:placetype":"venue"
},
  "geometry": {"coordinates":[150.841873169,-34.4520301819],"type":"Point"}
}