{
  "type": "Feature",
  "properties": {
    "addr:full":"8 Riverview Rd East Victoria Park WA 6101",
    "addr:housenumber":"8",
    "addr:postcode":"6101",
    "addr:street":"Riverview Rd",
    "iso:country":"AU",
    "sg:address":"8 Riverview Rd",
    "sg:city":"East Victoria Park",
    "sg:classifiers":[
        {
            "category":"Utilities",
            "subcategory":"Electric",
            "type":"Services"
        }
    ],
    "sg:phone":"+61 401 300 999",
    "sg:postcode":"6101",
    "sg:province":"WA",
    "sg:tags":[
        "electrical",
        "contractor"
    ],
    "sg:website":"http://www.hanlec.com.au",
    "wof:name":"Hanlec Electrical Pty Ltd",
    "wof:placetype":"venue"
},
  "geometry": {"coordinates":[115.897346497,-31.9946250916],"type":"Point"}
}