{
  "type": "Feature",
  "properties": {
    "addr:full":"117 Cunningham St Dalby QLD 4405",
    "addr:housenumber":"117",
    "addr:postcode":"4405",
    "addr:street":"Cunningham St",
    "iso:country":"AU",
    "sg:address":"117 Cunningham St",
    "sg:city":"Dalby",
    "sg:classifiers":[
        {
            "category":"Professional",
            "subcategory":"Employment Agencies",
            "type":"Services"
        }
    ],
    "sg:phone":"+61 7 4662 0066",
    "sg:postcode":"4405",
    "sg:province":"QLD",
    "wof:name":"Skill Centred Queensland",
    "wof:placetype":"venue"
},
  "geometry": {"coordinates":[151.26448059099999,-27.1825447083],"type":"Point"}
}