{
  "type": "Feature",
  "properties": {
    "iso:country":"AU",
    "sg:address":"Shp111/ 48 Atchison St",
    "sg:city":"St Leonards",
    "sg:classifiers":[
        {
            "category":"Personal",
            "subcategory":"Beauty Salon",
            "type":"Services"
        }
    ],
    "sg:phone":"+61 2 9906 8366",
    "sg:postcode":"2065",
    "sg:province":"NSW",
    "wof:name":"BECE Skincare & Beauty",
    "wof:placetype":"venue"
},
  "geometry": {"coordinates":[151.19822692899999,-33.8227577209],"type":"Point"}
}