{
  "type": "Feature",
  "properties": {
    "iso:country":"AU",
    "sg:address":"31 Saunders St",
    "sg:city":"North Beach",
    "sg:classifiers":[
        {
            "category":"Building & Trades",
            "subcategory":"Plumbing",
            "type":"Services"
        }
    ],
    "sg:phone":"+61 8 9448 4400",
    "sg:postcode":"6020",
    "sg:province":"WA",
    "sg:tags":[
        "drainers"
    ],
    "wof:name":"Atkins Ian Plumber",
    "wof:placetype":"venue"
},
  "geometry": {"coordinates":[115.755867004,-31.8652667999],"type":"Point"}
}