{
  "type": "Feature",
  "properties": {
    "iso:country":"AU",
    "sg:address":"8 Lake Ave",
    "sg:city":"Cardiff South",
    "sg:classifiers":[
        {
            "category":"Education",
            "subcategory":"Dance Studio",
            "type":"Public Place"
        }
    ],
    "sg:phone":"+61 2 4954 5615",
    "sg:postcode":"2285",
    "sg:province":"NSW",
    "sg:tags":[
        "venue",
        "tuition"
    ],
    "wof:name":"Kicks",
    "wof:placetype":"venue"
},
  "geometry": {"coordinates":[151.66517639200001,-32.9540748596],"type":"Point"}
}