{
  "type": "Feature",
  "properties": {
    "iso:country":"AU",
    "sg:address":"1/ 444 Gardeners Rd",
    "sg:city":"Alexandria",
    "sg:classifiers":[
        {
            "category":"Social Services",
            "subcategory":"Job Training",
            "type":"Services"
        }
    ],
    "sg:phone":"+61 2 9330 0444",
    "sg:postcode":"2015",
    "sg:province":"NSW",
    "sg:tags":[
        "hire",
        "computer",
        "leasing"
    ],
    "wof:name":"Trilogy Technology Rentals",
    "wof:placetype":"venue"
},
  "geometry": {"coordinates":[151.19627380399999,-33.9212608337],"type":"Point"}
}