{
  "type": "Feature",
  "properties": {
    "addr:full":"105 Union Rd Surrey Hills VIC 3127",
    "addr:housenumber":"105",
    "addr:postcode":"3127",
    "addr:street":"Union Rd",
    "iso:country":"AU",
    "sg:address":"105 Union Rd",
    "sg:city":"Surrey Hills",
    "sg:classifiers":[
        {
            "category":"Building & Trades",
            "subcategory":"Cleaning & Sanitation",
            "type":"Services"
        }
    ],
    "sg:phone":"+61 1300 139 981",
    "sg:postcode":"3127",
    "sg:province":"VIC",
    "sg:tags":[
        "window"
    ],
    "wof:name":"C4 Clean",
    "wof:placetype":"venue"
},
  "geometry": {"coordinates":[145.09750366200001,-37.8253974915],"type":"Point"}
}