{
  "type": "Feature",
  "properties": {
    "addr:full":"28 Olive St Nundah QLD 4012",
    "addr:housenumber":"28",
    "addr:postcode":"4012",
    "addr:street":"Olive St",
    "iso:country":"AU",
    "sg:address":"28 Olive St",
    "sg:city":"Nundah",
    "sg:classifiers":[
        {
            "category":"Building & Trades",
            "subcategory":"Construction",
            "type":"Services"
        }
    ],
    "sg:phone":"+61 7 3266 9182",
    "sg:postcode":"4012",
    "sg:province":"QLD",
    "sg:tags":[
        "stonework",
        "stone",
        "mason"
    ],
    "wof:name":"Steve Topping",
    "wof:placetype":"venue"
},
  "geometry": {"coordinates":[153.054153442,-27.4004821777],"type":"Point"}
}