{
  "type": "Feature",
  "properties": {
    "addr:full":"379 Thynne Rd Morningside QLD 4170",
    "addr:housenumber":"379",
    "addr:postcode":"4170",
    "addr:street":"Thynne Rd",
    "iso:country":"AU",
    "sg:address":"379 Thynne Rd",
    "sg:city":"Morningside",
    "sg:classifiers":[
        {
            "category":"Shopping",
            "subcategory":"Mobile Phones",
            "type":"Retail Goods"
        }
    ],
    "sg:phone":"+61 7 3899 8866",
    "sg:postcode":"4170",
    "sg:province":"QLD",
    "sg:tags":[
        "wholesaler",
        "mfrs",
        "electrical",
        "switchboard"
    ],
    "wof:name":"Nilsen (QLD) Pty Ltd",
    "wof:placetype":"venue"
},
  "geometry": {"coordinates":[153.09259033199999,-27.4661808014],"type":"Point"}
}