{
  "type": "Feature",
  "properties": {
    "iso:country":"AU",
    "sg:address":"373 Bells Line of Rd",
    "sg:city":"Kurmond",
    "sg:classifiers":[
        {
            "category":"Retail",
            "subcategory":"Veterinary Services",
            "type":"Services"
        }
    ],
    "sg:phone":"+61 2 4573 1980",
    "sg:postcode":"2757",
    "sg:province":"NSW",
    "sg:tags":[
        "surgeon"
    ],
    "wof:name":"Kurmond Veterinary Clinic",
    "wof:placetype":"venue"
},
  "geometry": {"coordinates":[150.70086669899999,-33.5582084656],"type":"Point"}
}