{
  "type": "Feature",
  "properties": {
    "iso:country":"AU",
    "sg:address":"570 Grieve Pde",
    "sg:city":"Brooklyn",
    "sg:classifiers":[
        {
            "category":"Home & Garden",
            "subcategory":"Furniture",
            "type":"Retail Goods"
        }
    ],
    "sg:phone":"+61 3 9318 0566",
    "sg:postcode":"3012",
    "sg:province":"VIC",
    "sg:tags":[
        "business"
    ],
    "wof:name":"Active Office Furniture",
    "wof:placetype":"venue"
},
  "geometry": {"coordinates":[144.82986450199999,-37.8239631653],"type":"Point"}
}