{
  "type": "Feature",
  "properties": {
    "addr:full":"2- 6 Thomas Pl Prahran VIC 3181",
    "addr:housenumber":"6",
    "addr:postcode":"3181",
    "addr:street":"Thomas Pl",
    "iso:country":"AU",
    "sg:address":"2- 6 Thomas Pl",
    "sg:city":"Prahran",
    "sg:classifiers":[
        {
            "category":"Communications",
            "type":"Services"
        }
    ],
    "sg:phone":"+61 3 9510 9555",
    "sg:postcode":"3181",
    "sg:province":"VIC",
    "sg:tags":[
        "data"
    ],
    "wof:name":"C & G Technologies - VIC",
    "wof:placetype":"venue"
},
  "geometry": {"coordinates":[144.98985290499999,-37.8480682373],"type":"Point"}
}