{
  "type": "Feature",
  "properties": {
    "addr:full":"Shop 10 Brantome St Gisborne VIC 3437",
    "addr:housenumber":"shop 10",
    "addr:postcode":"3437",
    "addr:street":"Brantome St",
    "iso:country":"AU",
    "sg:address":"Shop 10 Brantome St",
    "sg:city":"Gisborne",
    "sg:classifiers":[
        {
            "category":"Cafe",
            "type":"Food & Drink"
        }
    ],
    "sg:phone":"+61 3 5428 4017",
    "sg:postcode":"3437",
    "sg:province":"VIC",
    "wof:name":"Enyahs Caff",
    "wof:placetype":"venue"
},
  "geometry": {"coordinates":[144.59016418499999,-37.4855041504],"type":"Point"}
}