{
  "type": "Feature",
  "properties": {
    "addr:full":"116- 120 Old Bathurst Rd Emu Plains NSW 2750",
    "addr:housenumber":"120",
    "addr:postcode":"2750",
    "addr:street":"Old Bathurst Rd",
    "iso:country":"AU",
    "sg:address":"116- 120 Old Bathurst Rd",
    "sg:city":"Emu Plains",
    "sg:classifiers":[
        {
            "category":"Retail",
            "subcategory":"Auto Repair",
            "type":"Services"
        }
    ],
    "sg:phone":"+61 2 4735 1500",
    "sg:postcode":"2750",
    "sg:province":"NSW",
    "sg:tags":[
        "repairer",
        "motor",
        "engineer"
    ],
    "wof:name":"A.B.C. Mechanical Repairs",
    "wof:placetype":"venue"
},
  "geometry": {"coordinates":[150.65388488799999,-33.7427482605],"type":"Point"}
}