{
  "type": "Feature",
  "properties": {
    "iso:country":"AU",
    "sg:address":"Lot 53 Flower Cct",
    "sg:city":"Akolele",
    "sg:classifiers":[
        {
            "category":"Building & Trades",
            "subcategory":"Construction",
            "type":"Services"
        }
    ],
    "sg:phone":"+61 2 4473 7301",
    "sg:postcode":"2546",
    "sg:province":"NSW",
    "sg:tags":[
        "contractor"
    ],
    "wof:name":"Drakos Bros Construction",
    "wof:placetype":"venue"
},
  "geometry": {"coordinates":[150.07717895499999,-36.3571090698],"type":"Point"}
}