{
  "type": "Feature",
  "properties": {
    "addr:full":"356 Canterbury Rd Surrey Hills VIC 3127",
    "addr:housenumber":"356",
    "addr:postcode":"3127",
    "addr:street":"Canterbury Rd",
    "iso:country":"AU",
    "sg:address":"356 Canterbury Rd",
    "sg:city":"Surrey Hills",
    "sg:classifiers":[
        {
            "category":"Health Services",
            "subcategory":"Health Practitioner",
            "type":"Services"
        }
    ],
    "sg:phone":"+61 3 9888 5855",
    "sg:postcode":"3127",
    "sg:province":"VIC",
    "sg:tags":[
        "naturopath"
    ],
    "wof:name":"LifeSource Centres",
    "wof:placetype":"venue"
},
  "geometry": {"coordinates":[145.09634399399999,-37.8259620667],"type":"Point"}
}