{
  "type": "Feature",
  "properties": {
    "iso:country":"AU",
    "sg:address":"89 Kendall Ave",
    "sg:city":"Queanbeyan",
    "sg:classifiers":[
        {
            "category":"Building & Trades",
            "subcategory":"Landscaping Services",
            "type":"Services"
        }
    ],
    "sg:phone":"+61 2 6297 4888",
    "sg:postcode":"2620",
    "sg:province":"NSW",
    "sg:tags":[
        "designer",
        "landscape",
        "contractor"
    ],
    "wof:name":"Able Landscaping",
    "wof:placetype":"venue"
},
  "geometry": {"coordinates":[149.203323364,-35.3506507874],"type":"Point"}
}