{
  "type": "Feature",
  "properties": {
    "iso:country":"AU",
    "sg:address":"61 Waratah St",
    "sg:city":"Haberfield",
    "sg:classifiers":[
        {
            "category":"Organizations",
            "subcategory":"Non-profit Organization",
            "type":"Services"
        }
    ],
    "sg:phone":"+61 2 9798 8419",
    "sg:postcode":"2045",
    "sg:province":"NSW",
    "sg:tags":[
        "support",
        "disability",
        "organisation"
    ],
    "wof:name":"Handital NSW Inc",
    "wof:placetype":"venue"
},
  "geometry": {"coordinates":[151.14253199999999,-33.875603],"type":"Point"}
}