{
  "type": "Feature",
  "properties": {
    "addr:full":"26b Smart St Fairfield NSW 2165",
    "addr:housenumber":"26b",
    "addr:postcode":"2165",
    "addr:street":"Smart St",
    "iso:country":"AU",
    "sg:address":"26b Smart St",
    "sg:city":"Fairfield",
    "sg:classifiers":[
        {
            "category":"Travel",
            "subcategory":"Travel Agent",
            "type":"Entertainment"
        }
    ],
    "sg:phone":"+61 2 9726 7066",
    "sg:postcode":"2165",
    "sg:province":"NSW",
    "sg:tags":[
        "consultant"
    ],
    "wof:name":"Galaxy World Travel",
    "wof:placetype":"venue"
},
  "geometry": {"coordinates":[150.956634522,-33.8708724976],"type":"Point"}
}