{
  "type": "Feature",
  "properties": {
    "addr:full":"Cnr Charles St & Bamford Lane Kirwan QLD 4817",
    "addr:postcode":"4817",
    "addr:street":"Cnr Charles St & Bamford Lane",
    "iso:country":"AU",
    "sg:address":"Cnr Charles St",
    "sg:city":"& Bamford Lane Kirwan",
    "sg:classifiers":[
        {
            "category":"Food & Beverages",
            "subcategory":"Liquor & Beverages",
            "type":"Retail Goods"
        }
    ],
    "sg:phone":"+61 7 4773 1150",
    "sg:postcode":"4817",
    "sg:province":"QLD",
    "sg:tags":[
        "store"
    ],
    "wof:name":"Parkside Gardens Bottle Shop",
    "wof:placetype":"venue"
},
  "geometry": {"coordinates":[146.735153,-19.303686],"type":"Point"}
}