{
  "type": "Feature",
  "properties": {
    "addr:full":"2 College Ave Southport QLD 4215",
    "addr:housenumber":"2",
    "addr:postcode":"4215",
    "addr:street":"College Ave",
    "iso:country":"AU",
    "sg:address":"2 College Ave",
    "sg:city":"Southport",
    "sg:classifiers":[
        {
            "category":"Professional",
            "subcategory":"Art Services",
            "type":"Services"
        }
    ],
    "sg:phone":"+61 408 383 348",
    "sg:postcode":"4215",
    "sg:province":"QLD",
    "sg:tags":[
        "interior",
        "decorator"
    ],
    "wof:name":"Como Interiors",
    "wof:placetype":"venue"
},
  "geometry": {"coordinates":[153.409698486,-27.9825935364],"type":"Point"}
}