{
  "type": "Feature",
  "properties": {
    "iso:country":"AU",
    "sg:address":"128 West Coast Drv",
    "sg:city":"Sorrento",
    "sg:classifiers":[
        {
            "category":"Autos & Motor Vehicles",
            "subcategory":"Fuel & Gas Station",
            "type":"Retail Goods"
        }
    ],
    "sg:phone":"+61 8 9448 1424",
    "sg:postcode":"6020",
    "sg:province":"WA",
    "wof:name":"BP",
    "wof:placetype":"venue"
},
  "geometry": {"coordinates":[115.750038147,-31.8375015259],"type":"Point"}
}