{
  "type": "Feature",
  "properties": {
    "iso:country":"AU",
    "sg:address":"9 Nicole Way",
    "sg:city":"Dandenong",
    "sg:classifiers":[
        {
            "category":"Professional",
            "subcategory":"Computer Services",
            "type":"Services"
        }
    ],
    "sg:phone":"+61 1800 634 307",
    "sg:postcode":"3175",
    "sg:province":"VIC",
    "sg:tags":[
        "equipment",
        "networking",
        "installation"
    ],
    "sg:website":"http://www.upsonic.com.au",
    "wof:name":"Upsonic Power Pty Ltd",
    "wof:placetype":"venue"
},
  "geometry": {"coordinates":[145.219482422,-38.0164756775],"type":"Point"}
}