{
  "type": "Feature",
  "properties": {
    "addr:full":"Unit 19 64 Drummond St South Windsor NSW 2756",
    "addr:housenumber":"64",
    "addr:postcode":"2756",
    "addr:street":"Drummond St",
    "iso:country":"AU",
    "sg:address":"Unit 19 64 Drummond St",
    "sg:city":"South Windsor",
    "sg:classifiers":[
        {
            "category":"Shopping",
            "subcategory":"Pets & Pet Supplies",
            "type":"Retail Goods"
        }
    ],
    "sg:phone":"+61 2 4577 4868",
    "sg:postcode":"2756",
    "sg:province":"NSW",
    "sg:tags":[
        "shop",
        "supplier"
    ],
    "wof:name":"TJR Pet Supplies",
    "wof:placetype":"venue"
},
  "geometry": {"coordinates":[150.80575561500001,-33.6241950989],"type":"Point"}
}