{
  "type": "Feature",
  "properties": {
    "addr:full":"Shop 3 Manny's Market 168 Commercial Rd Morwell VIC 3840",
    "addr:housenumber":"shop 3;168",
    "addr:postcode":"3840",
    "addr:street":"Commercial Rd",
    "iso:country":"AU",
    "sg:address":"Shop 3 Manny's Market 168 Commercial Rd",
    "sg:city":"Morwell",
    "sg:classifiers":[
        {
            "category":"Personal",
            "subcategory":"Piercing",
            "type":"Services"
        }
    ],
    "sg:phone":"+61 3 5134 3233",
    "sg:postcode":"3840",
    "sg:province":"VIC",
    "sg:tags":[
        "body",
        "ear"
    ],
    "wof:name":"Brendan Jays Hair & Beauty",
    "wof:placetype":"venue"
},
  "geometry": {"coordinates":[146.396087647,-38.2370948792],"type":"Point"}
}