{
  "type": "Feature",
  "properties": {
    "iso:country":"AU",
    "sg:address":"349 Point Nepean Rd",
    "sg:city":"Dromana",
    "sg:classifiers":[
        {
            "category":"Real Estate",
            "subcategory":"Real Estate Agent",
            "type":"Services"
        }
    ],
    "sg:phone":"+61 3 5981 9155",
    "sg:postcode":"3936",
    "sg:province":"VIC",
    "wof:name":"Russell Ord's Bay Real Estate",
    "wof:placetype":"venue"
},
  "geometry": {"coordinates":[144.95921325699999,-38.3355255127],"type":"Point"}
}