{
  "type": "Feature",
  "properties": {
    "addr:full":"1 Dawson St Ferntree Gully Upper VIC 3156",
    "addr:housenumber":"1",
    "addr:postcode":"3156",
    "addr:street":"Dawson St",
    "iso:country":"AU",
    "sg:address":"1 Dawson St",
    "sg:city":"Ferntree Gully Upper",
    "sg:classifiers":[
        {
            "category":"Health Services",
            "subcategory":"Doctor",
            "type":"Services"
        }
    ],
    "sg:phone":"+61 3 9758 9155",
    "sg:postcode":"3156",
    "sg:province":"VIC",
    "sg:tags":[
        "medical",
        "practitioner"
    ],
    "wof:name":"Gay Terry",
    "wof:placetype":"venue"
},
  "geometry": {"coordinates":[145.30940246599999,-37.8946418762],"type":"Point"}
}