{
  "type": "Feature",
  "properties": {
    "addr:full":"Avalon Airport Beach Rd Lara VIC 3212",
    "addr:postcode":"3212",
    "addr:street":"Beach Rd",
    "iso:country":"AU",
    "sg:address":"Avalon Airport Beach Rd",
    "sg:city":"Lara",
    "sg:classifiers":[
        {
            "category":"Professional",
            "subcategory":"Business Services",
            "type":"Services"
        }
    ],
    "sg:phone":"+61 3 5282 0500",
    "sg:postcode":"3212",
    "sg:province":"VIC",
    "sg:tags":[
        "management",
        "event"
    ],
    "wof:name":"Aerospace Australia Ltd",
    "wof:placetype":"venue"
},
  "geometry": {"coordinates":[144.42897033700001,-38.0265045166],"type":"Point"}
}