{
  "type": "Feature",
  "properties": {
    "iso:country":"AU",
    "sg:address":"11 Olsen Crt",
    "sg:city":"Leeming",
    "sg:classifiers":[
        {
            "category":"Farming",
            "subcategory":"Farm & Veterinary Services",
            "type":"Manufacturing & Wholesale Goods"
        }
    ],
    "sg:phone":"+61 412 920 149",
    "sg:postcode":"6149",
    "sg:province":"WA",
    "sg:tags":[
        "irrigation",
        "reticulation",
        "system"
    ],
    "wof:name":"Bowie Irrigation Pty Ltd",
    "wof:placetype":"venue"
},
  "geometry": {"coordinates":[115.876801,-32.072132],"type":"Point"}
}