{
  "type": "Feature",
  "properties": {
    "addr:full":"515 Anzac Ave Rothwell QLD 4022",
    "addr:housenumber":"515",
    "addr:postcode":"4022",
    "addr:street":"Anzac Ave",
    "iso:country":"AU",
    "sg:address":"515 Anzac Ave",
    "sg:city":"Rothwell",
    "sg:classifiers":[
        {
            "category":"Professional",
            "subcategory":"Testing Lab",
            "type":"Services"
        }
    ],
    "sg:phone":"+61 7 3203 5945",
    "sg:postcode":"4022",
    "sg:province":"QLD",
    "sg:tags":[
        "inspection"
    ],
    "wof:name":"Metrology Calibration Service Pty Ltd",
    "wof:placetype":"venue"
},
  "geometry": {"coordinates":[153.051422,-27.215504],"type":"Point"}
}