{
  "type": "Feature",
  "properties": {
    "addr:full":"Whitewood St Greenwood WA 6024",
    "addr:postcode":"6024",
    "addr:street":"Whitewood St",
    "iso:country":"AU",
    "sg:address":"Whitewood St",
    "sg:city":"Greenwood",
    "sg:classifiers":[
        {
            "category":"Commercial Area",
            "type":"Public Place"
        }
    ],
    "sg:phone":"+61 412 606 498",
    "sg:postcode":"6024",
    "sg:province":"WA",
    "sg:tags":[
        "heavy",
        "carrier"
    ],
    "wof:name":"Mammoliti R J & N M",
    "wof:placetype":"venue"
},
  "geometry": {"coordinates":[115.79741668699999,-31.8272724152],"type":"Point"}
}