{
  "type": "Feature",
  "properties": {
    "iso:country":"AU",
    "sg:address":"37 Holloway Drv",
    "sg:city":"Bayswater",
    "sg:classifiers":[
        {
            "category":"Manufacturing",
            "subcategory":"Metals",
            "type":"Manufacturing & Wholesale Goods"
        }
    ],
    "sg:phone":"+61 3 9762 5477",
    "sg:postcode":"3153",
    "sg:province":"VIC",
    "sg:tags":[
        "merchant",
        "silver",
        "gold"
    ],
    "wof:name":"SBA Amalgamated Pty Ltd",
    "wof:placetype":"venue"
},
  "geometry": {"coordinates":[145.27993774399999,-37.850315094],"type":"Point"}
}