{
  "type": "Feature",
  "properties": {
    "addr:full":"Level 1/ 218 Church St Parramatta NSW 2150",
    "addr:housenumber":"/ 218",
    "addr:postcode":"2150",
    "addr:street":"Church St",
    "iso:country":"AU",
    "sg:address":"Level 1/ 218 Church St",
    "sg:city":"Parramatta",
    "sg:classifiers":[
        {
            "category":"Arts & Performance",
            "subcategory":"Dance",
            "type":"Entertainment"
        }
    ],
    "sg:phone":"+61 2 9635 3744",
    "sg:postcode":"2150",
    "sg:province":"NSW",
    "sg:tags":[
        "theatrical",
        "ballet",
        "tuition"
    ],
    "wof:name":"NSW Ballet Company The",
    "wof:placetype":"venue"
},
  "geometry": {"coordinates":[151.18023681599999,-33.893157959],"type":"Point"}
}