{
  "type": "Feature",
  "properties": {
    "addr:full":"Unit 30 / 26 Cessna Drv Caboolture QLD 4510",
    "addr:housenumber":"/ 26",
    "addr:postcode":"4510",
    "addr:street":"Cessna Drv",
    "iso:country":"AU",
    "sg:address":"Unit 30 / 26 Cessna Drv",
    "sg:city":"Caboolture",
    "sg:classifiers":[
        {
            "category":"Building & Trades",
            "subcategory":"Construction",
            "type":"Services"
        }
    ],
    "sg:phone":"+61 1300 763 008",
    "sg:postcode":"4510",
    "sg:province":"QLD",
    "sg:tags":[
        "installation",
        "air conditioning"
    ],
    "wof:name":"Air Miester",
    "wof:placetype":"venue"
},
  "geometry": {"coordinates":[152.98384100000001,-27.085512],"type":"Point"}
}