{
  "type": "Feature",
  "properties": {
    "iso:country":"AU",
    "sg:address":"62- 70 Export Drv",
    "sg:city":"Brooklyn",
    "sg:classifiers":[
        {
            "category":"Manufacturing",
            "subcategory":"Glass & Minerals",
            "type":"Manufacturing & Wholesale Goods"
        }
    ],
    "sg:phone":"+61 3 9314 8626",
    "sg:postcode":"3012",
    "sg:province":"VIC",
    "sg:tags":[
        "merchant",
        "granite",
        "marble"
    ],
    "wof:name":"Paz Stone",
    "wof:placetype":"venue"
},
  "geometry": {"coordinates":[144.8543396,-37.8233032227],"type":"Point"}
}