{
  "type": "Feature",
  "properties": {
    "addr:full":"37 Brown St Hamilton VIC 3300",
    "addr:housenumber":"37",
    "addr:postcode":"3300",
    "addr:street":"Brown St",
    "iso:country":"AU",
    "sg:address":"37 Brown St",
    "sg:city":"Hamilton",
    "sg:classifiers":[
        {
            "category":"Shopping",
            "subcategory":"Clothing, Apparel, & Fashions",
            "type":"Retail Goods"
        }
    ],
    "sg:phone":"+61 3 5571 1529",
    "sg:postcode":"3300",
    "sg:province":"VIC",
    "sg:tags":[
        "recycled",
        "clothing"
    ],
    "wof:name":"Salvation Army Family Store & Home Collection",
    "wof:placetype":"venue"
},
  "geometry": {"coordinates":[142.02626037600001,-37.7441558838],"type":"Point"}
}