{
  "type": "Feature",
  "properties": {
    "iso:country":"AU",
    "sg:address":"25 Beerburrum Rd",
    "sg:city":"Caboolture",
    "sg:classifiers":[
        {
            "category":"Wholesale",
            "subcategory":"Machinery & Supplies",
            "type":"Manufacturing & Wholesale Goods"
        }
    ],
    "sg:phone":"+61 7 5495 1161",
    "sg:postcode":"4510",
    "sg:province":"QLD",
    "sg:tags":[
        "agricultural"
    ],
    "wof:name":"Gillespies Pty Ltd",
    "wof:placetype":"venue"
},
  "geometry": {"coordinates":[152.950623,-27.077103],"type":"Point"}
}