{
  "type": "Feature",
  "properties": {
    "addr:full":"Cnr Byfield & Oliver Sts Northam WA 6401",
    "addr:postcode":"6401",
    "addr:street":"Cnr",
    "iso:country":"AU",
    "sg:address":"Cnr Byfield & Oliver Sts",
    "sg:city":"Northam",
    "sg:classifiers":[
        {
            "category":"Utilities",
            "type":"Services"
        }
    ],
    "sg:phone":"+61 8 9622 1980",
    "sg:postcode":"6401",
    "sg:province":"WA",
    "sg:tags":[
        "refrigeration",
        "industrial",
        "commercial",
        "retail"
    ],
    "wof:name":"Hill's Refrigeration (WA) Pty Ltd",
    "wof:placetype":"venue"
},
  "geometry": {"coordinates":[116.68115997300001,-31.6564025879],"type":"Point"}
}