{
  "type": "Feature",
  "properties": {
    "iso:country":"AU",
    "sg:address":"225 Boundary St",
    "sg:city":"Port Melbourne",
    "sg:classifiers":[
        {
            "category":"Professional",
            "type":"Services"
        }
    ],
    "sg:phone":"+61 3 9646 6322",
    "sg:postcode":"3207",
    "sg:province":"VIC",
    "sg:tags":[
        "transport"
    ],
    "wof:name":"Allifts Transport Co Pty Ltd",
    "wof:placetype":"venue"
},
  "geometry": {"coordinates":[144.938644,-37.824623],"type":"Point"}
}