{
  "type": "Feature",
  "properties": {
    "addr:full":"15 High St Sunshine VIC 3020",
    "addr:housenumber":"15",
    "addr:postcode":"3020",
    "addr:street":"High St",
    "iso:country":"AU",
    "sg:address":"15 High St",
    "sg:city":"Sunshine",
    "sg:classifiers":[
        {
            "category":"Home & Garden",
            "subcategory":"Building Materials",
            "type":"Retail Goods"
        }
    ],
    "sg:phone":"+61 3 9311 1298",
    "sg:postcode":"3020",
    "sg:province":"VIC",
    "sg:tags":[
        "lawn",
        "cutting",
        "maintenance"
    ],
    "wof:name":"Metro Gardens",
    "wof:placetype":"venue"
},
  "geometry": {"coordinates":[144.84298699999999,-37.78838],"type":"Point"}
}