{
  "type": "Feature",
  "properties": {
    "addr:full":"55 hay St Port Macquarie NSW 2444",
    "addr:housenumber":"55",
    "addr:postcode":"2444",
    "addr:street":"Hay St",
    "iso:country":"AU",
    "sg:address":"55 hay St",
    "sg:city":"Port Macquarie",
    "sg:classifiers":[
        {
            "category":"Shopping",
            "subcategory":"Clothing, Apparel, & Fashions",
            "type":"Retail Goods"
        }
    ],
    "sg:phone":"+61 2 6583 2150",
    "sg:postcode":"2444",
    "sg:province":"NSW",
    "sg:tags":[
        "lingerie",
        "hosiery",
        "sleepwear"
    ],
    "wof:name":"Sussan Lingerie & Sportswear",
    "wof:placetype":"venue"
},
  "geometry": {"coordinates":[152.90966800000001,-31.433437],"type":"Point"}
}