{
  "type": "Feature",
  "properties": {
    "addr:full":"PO Box 166 Hyde Park QLD 4812",
    "addr:postcode":"4812",
    "iso:country":"AU",
    "sg:address":"PO Box 166",
    "sg:city":"Hyde Park",
    "sg:classifiers":[
        {
            "category":"Professional",
            "subcategory":"Art Services",
            "type":"Services"
        }
    ],
    "sg:phone":"+61 7 4755 0488",
    "sg:postcode":"4812",
    "sg:province":"QLD",
    "sg:tags":[
        "decorator",
        "painter"
    ],
    "wof:name":"Denman & Co Pty Ltd",
    "wof:placetype":"venue"
},
  "geometry": {"coordinates":[146.79513549800001,-19.2769298553],"type":"Point"}
}