{
  "type": "Feature",
  "properties": {
    "addr:full":"Level 1 Merthyr Village 85 Merthyr Rd New Farm QLD 4005",
    "addr:housenumber":"85",
    "addr:postcode":"4005",
    "addr:street":"Merthyr Rd",
    "iso:country":"AU",
    "sg:address":"Level 1 Merthyr Village 85 Merthyr Rd",
    "sg:city":"New Farm",
    "sg:classifiers":[
        {
            "category":"Health Services",
            "subcategory":"Health Practitioner",
            "type":"Services"
        }
    ],
    "sg:phone":"+61 7 3254 1137",
    "sg:postcode":"4005",
    "sg:province":"QLD",
    "sg:tags":[
        "psychologist"
    ],
    "wof:name":"Elizabeth Gwynne Psychologist",
    "wof:placetype":"venue"
},
  "geometry": {"coordinates":[153.04672241200001,-27.4667472839],"type":"Point"}
}