{
  "type": "Feature",
  "properties": {
    "addr:full":"700 Inkerman Rd Caulfield North VIC 3161",
    "addr:housenumber":"700",
    "addr:postcode":"3161",
    "addr:street":"Inkerman Rd",
    "iso:country":"AU",
    "sg:address":"700 Inkerman Rd",
    "sg:city":"Caulfield North",
    "sg:classifiers":[
        {
            "category":"Health Services",
            "subcategory":"Dentist",
            "type":"Services"
        }
    ],
    "sg:phone":"+61 3 9509 1856",
    "sg:postcode":"3161",
    "sg:province":"VIC",
    "wof:name":"David Casper, Meyer Menahem & Hayward Lewis",
    "wof:placetype":"venue"
},
  "geometry": {"coordinates":[145.02507019000001,-37.8694229126],"type":"Point"}
}