{
  "type": "Feature",
  "properties": {
    "iso:country":"AU",
    "sg:address":"3 Harford St",
    "sg:city":"Penrith",
    "sg:classifiers":[
        {
            "category":"Manufacturing",
            "subcategory":"Metals",
            "type":"Manufacturing & Wholesale Goods"
        }
    ],
    "sg:phone":"+61 2 4721 3116",
    "sg:postcode":"2750",
    "sg:province":"NSW",
    "sg:tags":[
        "steel",
        "fabricator",
        "mfrs"
    ],
    "wof:name":"Ferrcom Engineering Pty Ltd",
    "wof:placetype":"venue"
},
  "geometry": {"coordinates":[150.68588256800001,-33.7646255493],"type":"Point"}
}