{
  "type": "Feature",
  "properties": {
    "addr:full":"40 Ingleston Rd Wakerley QLD 4154",
    "addr:housenumber":"40",
    "addr:postcode":"4154",
    "addr:street":"Ingleston Rd",
    "iso:country":"AU",
    "sg:address":"40 Ingleston Rd",
    "sg:city":"Wakerley",
    "sg:classifiers":[
        {
            "category":"Professional",
            "subcategory":"Engineering",
            "type":"Services"
        }
    ],
    "sg:phone":"+61 7 3390 8399",
    "sg:postcode":"4154",
    "sg:province":"QLD",
    "sg:tags":[
        "manufacturing",
        "engineer"
    ],
    "wof:name":"McConnell Industries",
    "wof:placetype":"venue"
},
  "geometry": {"coordinates":[153.142303467,-27.4785461426],"type":"Point"}
}