{
  "type": "Feature",
  "properties": {
    "addr:full":"Shop 124 Pacific Fair St Broadbeach QLD 4218",
    "addr:housenumber":"124",
    "addr:postcode":"4218",
    "addr:street":"Pacific Fair St",
    "iso:country":"AU",
    "sg:address":"Shop 124 Pacific Fair St",
    "sg:city":"Broadbeach",
    "sg:classifiers":[
        {
            "category":"Cafe",
            "type":"Food & Drink"
        }
    ],
    "sg:phone":"+61 7 5538 2183",
    "sg:postcode":"4218",
    "sg:province":"QLD",
    "wof:name":"The Wildlife Cafe",
    "wof:placetype":"venue"
},
  "geometry": {"coordinates":[153.43174743599999,-28.0374698639],"type":"Point"}
}