{
  "type": "Feature",
  "properties": {
    "addr:full":"Shop G11B Toowong Village Shopping Centre, 9 Sherwood Rd Toowong QLD 4066",
    "addr:housenumber":"g11b;9",
    "addr:postcode":"4066",
    "addr:street":"Village;Sherwood Rd",
    "iso:country":"AU",
    "sg:address":"Shop G11B Toowong Village Shopping Centre, 9 Sherwood Rd",
    "sg:city":"Toowong",
    "sg:classifiers":[
        {
            "category":"Building & Trades",
            "subcategory":"Locksmith",
            "type":"Services"
        }
    ],
    "sg:phone":"+61 7 3217 8015",
    "sg:postcode":"4066",
    "sg:province":"QLD",
    "sg:tags":[
        "lock"
    ],
    "wof:name":"Mister Minit",
    "wof:placetype":"venue"
},
  "geometry": {"coordinates":[152.99188232399999,-27.4853534698],"type":"Point"}
}