{
  "type": "Feature",
  "properties": {
    "addr:full":"Concord High School Stanley St Concord NSW 2137",
    "addr:postcode":"2137",
    "addr:street":"Stanley St",
    "iso:country":"AU",
    "sg:address":"Concord High School Stanley St",
    "sg:city":"Concord",
    "sg:classifiers":[
        {
            "category":"Organizations",
            "subcategory":"Membership Organization",
            "type":"Services"
        }
    ],
    "sg:phone":"+61 2 9713 8213",
    "sg:postcode":"2137",
    "sg:province":"NSW",
    "sg:tags":[
        "club",
        "bridge"
    ],
    "wof:name":"Concord Bridge Club",
    "wof:placetype":"venue"
},
  "geometry": {"coordinates":[151.105560303,-33.8632926941],"type":"Point"}
}