{
  "type": "Feature",
  "properties": {
    "iso:country":"AU",
    "sg:address":"Level 1 14 Cox Rd",
    "sg:city":"Windsor",
    "sg:classifiers":[
        {
            "category":"Building & Trades",
            "subcategory":"Landscaping Services",
            "type":"Services"
        }
    ],
    "sg:phone":"+61 7 3857 8422",
    "sg:postcode":"4030",
    "sg:province":"QLD",
    "sg:tags":[
        "designer",
        "landscape",
        "contractor"
    ],
    "wof:name":"Eureka Landscapes Pty Ltd",
    "wof:placetype":"venue"
},
  "geometry": {"coordinates":[153.026993,-27.436701],"type":"Point"}
}