{
  "type": "Feature",
  "properties": {
    "iso:country":"AU",
    "sg:address":"123 Church Rd",
    "sg:city":"Doncaster",
    "sg:classifiers":[
        {
            "category":"Education",
            "subcategory":"School",
            "type":"Public Place"
        }
    ],
    "sg:phone":"+61 3 9848 4677",
    "sg:postcode":"3108",
    "sg:province":"VIC",
    "sg:tags":[
        "state",
        "except",
        "nsw"
    ],
    "wof:name":"Doncaster Secondary College",
    "wof:placetype":"venue"
},
  "geometry": {"coordinates":[145.13795471200001,-37.7853813171],"type":"Point"}
}