{
  "type": "Feature",
  "properties": {
    "iso:country":"AU",
    "sg:address":"12 Wattle Tree Ave",
    "sg:city":"Wonga Park",
    "sg:classifiers":[
        {
            "category":"Building & Trades",
            "subcategory":"Cleaning & Sanitation",
            "type":"Services"
        }
    ],
    "sg:phone":"+61 3 9722 1040",
    "sg:postcode":"3115",
    "sg:province":"VIC",
    "sg:tags":[
        "wall",
        "brick"
    ],
    "wof:name":"Neeleman R C",
    "wof:placetype":"venue"
},
  "geometry": {"coordinates":[145.27735900900001,-37.7406425476],"type":"Point"}
}