{
  "type": "Feature",
  "properties": {
    "addr:full":"U4/ 245 Bay St Brighton VIC 3186",
    "addr:housenumber":"245",
    "addr:postcode":"3186",
    "addr:street":"U4 /;Bay St",
    "iso:country":"AU",
    "sg:address":"U4/ 245 Bay St",
    "sg:city":"Brighton",
    "sg:classifiers":[
        {
            "category":"Insurance",
            "subcategory":"Insurance Agent",
            "type":"Services"
        }
    ],
    "sg:phone":"+61 3 9596 9688",
    "sg:postcode":"3186",
    "sg:province":"VIC",
    "sg:tags":[
        "broker"
    ],
    "wof:name":"Djd Broking Pty Ltd",
    "wof:placetype":"venue"
},
  "geometry": {"coordinates":[145.000396728,-37.9050712585],"type":"Point"}
}