{
  "type": "Feature",
  "properties": {
    "addr:full":"145 Fison Ave West Eagle Farm QLD 4009",
    "addr:housenumber":"145",
    "addr:postcode":"4009",
    "addr:street":"Fison Ave West",
    "iso:country":"AU",
    "sg:address":"145 Fison Ave West",
    "sg:city":"Eagle Farm",
    "sg:classifiers":[
        {
            "category":"Manufacturing",
            "subcategory":"Tools & Machinery",
            "type":"Manufacturing & Wholesale Goods"
        }
    ],
    "sg:phone":"+61 7 3630 2600",
    "sg:postcode":"4009",
    "sg:province":"QLD",
    "sg:tags":[
        "earth",
        "excavating",
        "moving",
        "equipment"
    ],
    "wof:name":"Liebherr Australia Pty Ltd",
    "wof:placetype":"venue"
},
  "geometry": {"coordinates":[153.087768555,-27.4364814758],"type":"Point"}
}