{
  "type": "Feature",
  "properties": {
    "iso:country":"AU",
    "sg:address":"58 Mollison St",
    "sg:city":"West End (Brisbane)",
    "sg:classifiers":[
        {
            "category":"Cafe",
            "type":"Food & Drink"
        }
    ],
    "sg:phone":"+61 7 3844 6045",
    "sg:postcode":"4101",
    "sg:province":"QLD",
    "wof:name":"The Three Monkeys Coffee & Tea House",
    "wof:placetype":"venue"
},
  "geometry": {"coordinates":[153.011520386,-27.4768981934],"type":"Point"}
}