{
  "type": "Feature",
  "properties": {
    "addr:full":"Unit 1, 85 The Promenade (Cnr Queens Rd) Mt Pleasant WA 6153",
    "addr:housenumber":"85",
    "addr:postcode":"6153",
    "addr:street":"The Promenade Cnr Queens Rd",
    "iso:country":"AU",
    "sg:address":"Unit 1, 85 The Promenade (Cnr Queens Rd)",
    "sg:city":"Mt Pleasant",
    "sg:classifiers":[
        {
            "category":"Real Estate",
            "subcategory":"Surveying",
            "type":"Services"
        }
    ],
    "sg:phone":"+61 8 9316 2508",
    "sg:postcode":"6153",
    "sg:province":"WA",
    "sg:tags":[
        "building",
        "surveyor"
    ],
    "wof:name":"ABSC",
    "wof:placetype":"venue"
},
  "geometry": {"coordinates":[115.84683200000001,-32.015434],"type":"Point"}
}