{
  "type": "Feature",
  "properties": {
    "iso:country":"AU",
    "sg:address":"256 Darby St",
    "sg:city":"Newcastle",
    "sg:classifiers":[
        {
            "category":"Professional",
            "subcategory":"Computer Services",
            "type":"Services"
        }
    ],
    "sg:phone":"+61 2 4927 3999",
    "sg:postcode":"2300",
    "sg:province":"NSW",
    "sg:tags":[
        "consultant",
        "system"
    ],
    "wof:name":"Forsythes Information Technology",
    "wof:placetype":"venue"
},
  "geometry": {"coordinates":[151.767593,-32.935688],"type":"Point"}
}