{
  "type": "Feature",
  "properties": {
    "addr:full":"St Brigids Primary Campus 120 Prinsep St Collie WA 6225",
    "addr:housenumber":"120",
    "addr:postcode":"6225",
    "addr:street":"Prinsep St",
    "iso:country":"AU",
    "sg:address":"St Brigids Primary Campus 120 Prinsep St",
    "sg:city":"Collie",
    "sg:classifiers":[
        {
            "category":"Education",
            "subcategory":"School",
            "type":"Public Place"
        }
    ],
    "sg:phone":"+61 8 9734 1097",
    "sg:postcode":"6225",
    "sg:province":"WA",
    "sg:tags":[
        "co-educational"
    ],
    "wof:name":"Collie Catholic College",
    "wof:placetype":"venue"
},
  "geometry": {"coordinates":[116.160973,-33.344097],"type":"Point"}
}