{
  "type": "Feature",
  "properties": {
    "addr:full":"20 Endeavour Crt Thornlie WA 6108",
    "addr:housenumber":"20",
    "addr:postcode":"6108",
    "addr:street":"Endeavour Crt",
    "iso:country":"AU",
    "sg:address":"20 Endeavour Crt",
    "sg:city":"Thornlie",
    "sg:classifiers":[
        {
            "category":"Building & Trades",
            "subcategory":"Landscaping Services",
            "type":"Services"
        }
    ],
    "sg:phone":"+61 8 9459 7318",
    "sg:postcode":"6108",
    "sg:province":"WA",
    "sg:tags":[
        "designer",
        "landscape",
        "contractor"
    ],
    "wof:name":"Bloomin Landscapes",
    "wof:placetype":"venue"
},
  "geometry": {"coordinates":[115.96251678500001,-32.0719871521],"type":"Point"}
}