{
  "type": "Feature",
  "properties": {
    "iso:country":"AU",
    "sg:address":"11/ 26 Terrace Rd",
    "sg:city":"North Richmond",
    "sg:classifiers":[
        {
            "category":"Building & Trades",
            "subcategory":"Cleaning & Sanitation",
            "type":"Services"
        }
    ],
    "sg:phone":"+61 2 4571 4428",
    "sg:postcode":"2754",
    "sg:province":"NSW",
    "sg:tags":[
        "chemical",
        "pressure",
        "steam",
        "contractor"
    ],
    "wof:name":"Natural Graffiti Solutions",
    "wof:placetype":"venue"
},
  "geometry": {"coordinates":[150.72056579599999,-33.5792541504],"type":"Point"}
}