{
  "type": "Feature",
  "properties": {
    "iso:country":"AU",
    "sg:address":"19 Thurso Rd",
    "sg:city":"Myaree",
    "sg:classifiers":[
        {
            "category":"Retail",
            "subcategory":"Auto Repair",
            "type":"Services"
        }
    ],
    "sg:phone":"+61 8 9330 6785",
    "sg:postcode":"6154",
    "sg:province":"WA",
    "sg:tags":[
        "repairer",
        "motor",
        "engineer"
    ],
    "wof:name":"Eurosprint Auto",
    "wof:placetype":"venue"
},
  "geometry": {"coordinates":[115.808792,-32.045536],"type":"Point"}
}