{
  "type": "Feature",
  "properties": {
    "iso:country":"AU",
    "sg:address":"47 Marshall St",
    "sg:city":"Cobar",
    "sg:classifiers":[
        {
            "category":"Banks & Credit Unions",
            "subcategory":"Bank",
            "type":"Services"
        }
    ],
    "sg:phone":"+61 2 6836 4666",
    "sg:postcode":"2835",
    "sg:province":"NSW",
    "sg:tags":[
        "society"
    ],
    "wof:name":"Orana Credit Union Ltd",
    "wof:placetype":"venue"
},
  "geometry": {"coordinates":[145.838867,-31.497869],"type":"Point"}
}