{
  "type": "Feature",
  "properties": {
    "iso:country":"AU",
    "sg:address":"9 Brook St",
    "sg:city":"Gerringong",
    "sg:classifiers":[
        {
            "category":"Building & Trades",
            "subcategory":"Construction",
            "type":"Services"
        }
    ],
    "sg:phone":"+61 401 800 983",
    "sg:postcode":"2534",
    "sg:province":"NSW",
    "sg:tags":[
        "stonework",
        "stone",
        "mason"
    ],
    "wof:name":"In Stone",
    "wof:placetype":"venue"
},
  "geometry": {"coordinates":[150.82192993199999,-34.7451400757],"type":"Point"}
}