{
  "type": "Feature",
  "properties": {
    "iso:country":"AU",
    "sg:address":"141 Cathundril St",
    "sg:city":"Narromine",
    "sg:classifiers":[
        {
            "category":"Professional",
            "subcategory":"Art Services",
            "type":"Services"
        }
    ],
    "sg:phone":"+61 2 6889 1109",
    "sg:postcode":"2821",
    "sg:province":"NSW",
    "sg:tags":[
        "decorator",
        "painter"
    ],
    "wof:name":"Everett Tom Painter & Decorator",
    "wof:placetype":"venue"
},
  "geometry": {"coordinates":[148.241622925,-32.2422676086],"type":"Point"}
}