{
  "type": "Feature",
  "properties": {
    "addr:full":"4 Laurel St Willoughby NSW 2068",
    "addr:housenumber":"4",
    "addr:postcode":"2068",
    "addr:street":"Laurel St",
    "iso:country":"AU",
    "sg:address":"4 Laurel St",
    "sg:city":"Willoughby",
    "sg:classifiers":[
        {
            "category":"Shopping",
            "subcategory":"Crafts & Fabrics",
            "type":"Retail Goods"
        }
    ],
    "sg:phone":"+61 2 9958 8766",
    "sg:postcode":"2068",
    "sg:province":"NSW",
    "sg:tags":[
        "supply"
    ],
    "wof:name":"Patchwork & Primitives",
    "wof:placetype":"venue"
},
  "geometry": {"coordinates":[151.206497192,-33.8002090454],"type":"Point"}
}