{
  "type": "Feature",
  "properties": {
    "addr:full":"47 Townsend St Finley NSW 2713",
    "addr:housenumber":"47",
    "addr:postcode":"2713",
    "addr:street":"Townsend St",
    "iso:country":"AU",
    "sg:address":"47 Townsend St",
    "sg:city":"Finley",
    "sg:classifiers":[
        {
            "category":"Utilities",
            "subcategory":"Electric",
            "type":"Services"
        }
    ],
    "sg:phone":"+61 3 5883 1571",
    "sg:postcode":"2713",
    "sg:province":"NSW",
    "sg:tags":[
        "electrical",
        "contractor"
    ],
    "wof:name":"Scott P A & J L",
    "wof:placetype":"venue"
},
  "geometry": {"coordinates":[145.57344055199999,-35.6467781067],"type":"Point"}
}