{
  "type": "Feature",
  "properties": {
    "addr:full":"19 Camden Rd Newtown VIC 3220",
    "addr:housenumber":"19",
    "addr:postcode":"3220",
    "addr:street":"Camden Rd",
    "iso:country":"AU",
    "sg:address":"19 Camden Rd",
    "sg:city":"Newtown",
    "sg:classifiers":[
        {
            "category":"Professional",
            "subcategory":"Business Services",
            "type":"Services"
        }
    ],
    "sg:phone":"+61 407 341 801",
    "sg:postcode":"3220",
    "sg:province":"VIC",
    "sg:tags":[
        "drafting"
    ],
    "wof:name":"Agilla Design & Drafting",
    "wof:placetype":"venue"
},
  "geometry": {"coordinates":[144.33157299999999,-38.155193],"type":"Point"}
}