{
  "type": "Feature",
  "properties": {
    "addr:full":"2120 Logan Rd Upper Mt Gravatt QLD 4122",
    "addr:housenumber":"2120",
    "addr:postcode":"4122",
    "addr:street":"Logan Rd Upper",
    "iso:country":"AU",
    "sg:address":"2120 Logan Rd",
    "sg:city":"Upper Mt Gravatt",
    "sg:classifiers":[
        {
            "category":"Health Services",
            "subcategory":"Doctor",
            "type":"Services"
        }
    ],
    "sg:phone":"+61 7 3343 6522",
    "sg:postcode":"4122",
    "sg:province":"QLD",
    "sg:tags":[
        "medical",
        "practitioner"
    ],
    "wof:name":"Blomeley Neville",
    "wof:placetype":"venue"
},
  "geometry": {"coordinates":[153.084152222,-27.561750412],"type":"Point"}
}