{
  "type": "Feature",
  "properties": {
    "iso:country":"AU",
    "sg:address":"Penelope Crs",
    "sg:city":"Arndell Park",
    "sg:classifiers":[
        {
            "category":"Utilities",
            "subcategory":"Refuse",
            "type":"Services"
        }
    ],
    "sg:phone":"+61 2 9676 6721",
    "sg:postcode":"2148",
    "sg:province":"NSW",
    "sg:tags":[
        "remover",
        "rubbish"
    ],
    "wof:name":"Dump It Bins",
    "wof:placetype":"venue"
},
  "geometry": {"coordinates":[150.88104248100001,-33.78855896],"type":"Point"}
}