{
  "type": "Feature",
  "properties": {
    "iso:country":"AU",
    "sg:address":"50- 52 Carrier St",
    "sg:city":"Benalla",
    "sg:classifiers":[
        {
            "category":"Professional",
            "subcategory":"Employment Agencies",
            "type":"Services"
        }
    ],
    "sg:phone":"+61 3 5823 3400",
    "sg:postcode":"3671",
    "sg:province":"VIC",
    "wof:name":"CVGT Employment & Training Specialists",
    "wof:placetype":"venue"
},
  "geometry": {"coordinates":[145.985367,-36.55022],"type":"Point"}
}