{
  "type": "Feature",
  "properties": {
    "addr:full":"507 Ipswich Rd Annerley QLD 4103",
    "addr:housenumber":"507",
    "addr:postcode":"4103",
    "addr:street":"Ipswich Rd",
    "iso:country":"AU",
    "sg:address":"507 Ipswich Rd",
    "sg:city":"Annerley",
    "sg:classifiers":[
        {
            "category":"Organizations",
            "subcategory":"Non-profit Organization",
            "type":"Services"
        }
    ],
    "sg:phone":"+61 7 3848 5257",
    "sg:postcode":"4103",
    "sg:province":"QLD",
    "sg:tags":[
        "support",
        "disability",
        "organisation"
    ],
    "wof:name":"Braille Library",
    "wof:placetype":"venue"
},
  "geometry": {"coordinates":[153.031082153,-27.5128974915],"type":"Point"}
}