{
  "type": "Feature",
  "properties": {
    "addr:full":"Upstairs 118 Palmerin St Warwick QLD 4370",
    "addr:housenumber":"118",
    "addr:postcode":"4370",
    "addr:street":"Palmerin St",
    "iso:country":"AU",
    "sg:address":"Upstairs 118 Palmerin St",
    "sg:city":"Warwick",
    "sg:classifiers":[
        {
            "category":"Sports & Exercise",
            "subcategory":"Gym",
            "type":"Entertainment"
        }
    ],
    "sg:phone":"+61 7 4667 1211",
    "sg:postcode":"4370",
    "sg:province":"QLD",
    "sg:tags":[
        "health",
        "fitness"
    ],
    "wof:name":"Vitality Fitness Centre",
    "wof:placetype":"venue"
},
  "geometry": {"coordinates":[152.03250122099999,-28.2175807953],"type":"Point"}
}