{
  "type": "Feature",
  "properties": {
    "addr:full":"629 Morphett Rd Seacombe Heights SA 5047",
    "addr:housenumber":"629",
    "addr:postcode":"5047",
    "addr:street":"Morphett Rd",
    "iso:country":"AU",
    "sg:address":"629 Morphett Rd",
    "sg:city":"Seacombe Heights",
    "sg:classifiers":[
        {
            "category":"Professional",
            "subcategory":"Art Services",
            "type":"Services"
        }
    ],
    "sg:phone":"+61 8 8298 7983",
    "sg:postcode":"5047",
    "sg:province":"SA",
    "sg:tags":[
        "decorator",
        "painter"
    ],
    "wof:name":"Kontos Michael",
    "wof:placetype":"venue"
},
  "geometry": {"coordinates":[138.54234299999999,-35.033966],"type":"Point"}
}