{
  "type": "Feature",
  "properties": {
    "addr:full":"Shop 1/ 238 Princes Hwy Bulli NSW 2516",
    "addr:housenumber":"shop 1 / 238",
    "addr:postcode":"2516",
    "addr:street":"Princes Hwy",
    "iso:country":"AU",
    "sg:address":"Shop 1/ 238 Princes Hwy",
    "sg:city":"Bulli",
    "sg:classifiers":[
        {
            "category":"Personal",
            "subcategory":"Massage",
            "type":"Services"
        }
    ],
    "sg:phone":"+61 409 392 538",
    "sg:postcode":"2516",
    "sg:province":"NSW",
    "sg:tags":[
        "therapy"
    ],
    "wof:name":"Balanced World",
    "wof:placetype":"venue"
},
  "geometry": {"coordinates":[150.91314700000001,-34.333675],"type":"Point"}
}