{
  "type": "Feature",
  "properties": {
    "iso:country":"AU",
    "sg:address":"Lvl2/ 15 Labouchere Rd",
    "sg:city":"South Perth",
    "sg:classifiers":[
        {
            "category":"Banks & Credit Unions",
            "subcategory":"Financial Services",
            "type":"Services"
        }
    ],
    "sg:phone":"+61 8 9474 2278",
    "sg:postcode":"6151",
    "sg:province":"WA",
    "sg:tags":[
        "planning"
    ],
    "wof:name":"Fortress Financial",
    "wof:placetype":"venue"
},
  "geometry": {"coordinates":[115.850922,-31.973946],"type":"Point"}
}