{
  "type": "Feature",
  "properties": {
    "addr:full":"1A Church St Moruya NSW 2537",
    "addr:housenumber":"1a",
    "addr:postcode":"2537",
    "addr:street":"Church St",
    "iso:country":"AU",
    "sg:address":"1A Church St",
    "sg:city":"Moruya",
    "sg:classifiers":[
        {
            "category":"Retail",
            "subcategory":"Funeral Services",
            "type":"Services"
        }
    ],
    "sg:phone":"+61 2 4474 3555",
    "sg:postcode":"2537",
    "sg:province":"NSW",
    "sg:tags":[
        "director"
    ],
    "wof:name":"Moruya District Funerals",
    "wof:placetype":"venue"
},
  "geometry": {"coordinates":[150.081207275,-35.9092636108],"type":"Point"}
}