{
  "type": "Feature",
  "properties": {
    "iso:country":"AU",
    "sg:address":"168 Byrnes Rd",
    "sg:city":"Wagga Wagga",
    "sg:classifiers":[
        {
            "category":"Building & Trades",
            "subcategory":"Landscaping Services",
            "type":"Services"
        }
    ],
    "sg:phone":"+61 417 260 044",
    "sg:postcode":"2650",
    "sg:province":"NSW",
    "sg:tags":[
        "slashing",
        "contractor"
    ],
    "wof:name":"Meluwa Services",
    "wof:placetype":"venue"
},
  "geometry": {"coordinates":[147.405593872,-35.0848388672],"type":"Point"}
}