{
  "type": "Feature",
  "properties": {
    "addr:full":"13 Griffen Ave Tamworth NSW 2340",
    "addr:housenumber":"13",
    "addr:postcode":"2340",
    "addr:street":"Griffen Ave",
    "iso:country":"AU",
    "sg:address":"13 Griffen Ave",
    "sg:city":"Tamworth",
    "sg:classifiers":[
        {
            "category":"Manufacturing",
            "subcategory":"Food",
            "type":"Manufacturing & Wholesale Goods"
        }
    ],
    "sg:phone":"+61 2 6766 9441",
    "sg:postcode":"2340",
    "sg:province":"NSW",
    "sg:tags":[
        "function",
        "catering"
    ],
    "wof:name":"Coupe's Catering Pty. Ltd.",
    "wof:placetype":"venue"
},
  "geometry": {"coordinates":[150.92799377399999,-31.0832138062],"type":"Point"}
}