{
  "type": "Feature",
  "properties": {
    "iso:country":"AU",
    "sg:address":"Shop 6, 136- 146 Ormond Rd",
    "sg:city":"East Geelong",
    "sg:classifiers":[
        {
            "category":"Professional",
            "subcategory":"Printing & Photocopies",
            "type":"Services"
        }
    ],
    "sg:phone":"+61 3 5222 3436",
    "sg:postcode":"3219",
    "sg:province":"VIC",
    "sg:tags":[
        "embroidery"
    ],
    "wof:name":"C & C Originals Embroidery Geelong",
    "wof:placetype":"venue"
},
  "geometry": {"coordinates":[144.38096618599999,-38.1652793884],"type":"Point"}
}