{
  "type": "Feature",
  "properties": {
    "iso:country":"AU",
    "sg:address":"Brookside Shopping Centre Osborne Rd",
    "sg:city":"Mitchelton",
    "sg:classifiers":[
        {
            "category":"Retail",
            "subcategory":"Driving School",
            "type":"Services"
        }
    ],
    "sg:phone":"+61 7 3855 5959",
    "sg:postcode":"4053",
    "sg:province":"QLD",
    "wof:name":"Morgan & Wacker Motorcycle Training Centre",
    "wof:placetype":"venue"
},
  "geometry": {"coordinates":[152.976928711,-27.4133472443],"type":"Point"}
}