{
  "type": "Feature",
  "properties": {
    "iso:country":"AU",
    "sg:address":"9- 11 Jade St",
    "sg:city":"Maddington",
    "sg:classifiers":[
        {
            "category":"Shopping",
            "subcategory":"Stationery & Office Supplies",
            "type":"Retail Goods"
        }
    ],
    "sg:phone":"+61 8 9493 4677",
    "sg:postcode":"6109",
    "sg:province":"WA",
    "sg:tags":[
        "packaging",
        "material"
    ],
    "sg:website":"http://www.waplastic.com.au",
    "wof:name":"W.A. Plastic Packaging",
    "wof:placetype":"venue"
},
  "geometry": {"coordinates":[115.997756958,-32.0389938354],"type":"Point"}
}