{
  "type": "Feature",
  "properties": {
    "addr:full":"392 George Bass Drv Malua Bay NSW 2536",
    "addr:housenumber":"392",
    "addr:postcode":"2536",
    "addr:street":"George Bass Drv",
    "iso:country":"AU",
    "sg:address":"392 George Bass Drv",
    "sg:city":"Malua Bay",
    "sg:classifiers":[
        {
            "category":"Home & Garden",
            "subcategory":"Building Materials",
            "type":"Retail Goods"
        }
    ],
    "sg:phone":"+61 2 4471 1904",
    "sg:postcode":"2536",
    "sg:province":"NSW",
    "sg:tags":[
        "lawn",
        "cutting",
        "maintenance"
    ],
    "wof:name":"Country Lawns",
    "wof:placetype":"venue"
},
  "geometry": {"coordinates":[150.22772216800001,-35.7896575928],"type":"Point"}
}