{
  "type": "Feature",
  "properties": {
    "iso:country":"AU",
    "sg:address":"180 Caroline Chisholm Drv",
    "sg:city":"Winston Hills",
    "sg:classifiers":[
        {
            "category":"Personal",
            "subcategory":"Beauty Salon",
            "type":"Services"
        }
    ],
    "sg:phone":"+61 2 9620 4253",
    "sg:postcode":"2153",
    "sg:province":"NSW",
    "wof:name":"Choyez Pty ltd",
    "wof:placetype":"venue"
},
  "geometry": {"coordinates":[150.967926025,-33.7730827332],"type":"Point"}
}