{
  "type": "Feature",
  "properties": {
    "iso:country":"AU",
    "sg:address":"8 Percy St",
    "sg:city":"Bellerive",
    "sg:classifiers":[
        {
            "category":"Organizations",
            "subcategory":"Community Association",
            "type":"Services"
        }
    ],
    "sg:phone":"+61 3 6244 5520",
    "sg:postcode":"7018",
    "sg:province":"TAS",
    "sg:tags":[
        "equipment",
        "system",
        "vacuum"
    ],
    "wof:name":"Astrovac",
    "wof:placetype":"venue"
},
  "geometry": {"coordinates":[147.369018555,-42.875415802],"type":"Point"}
}