{
  "type": "Feature",
  "properties": {
    "iso:country":"AU",
    "sg:address":"Foleys Rd",
    "sg:city":"Gwynneville",
    "sg:classifiers":[
        {
            "category":"Health Services",
            "subcategory":"Health Practitioner",
            "type":"Services"
        }
    ],
    "sg:phone":"+61 2 4229 4964",
    "sg:postcode":"2500",
    "sg:province":"NSW",
    "sg:tags":[
        "physiotherapist"
    ],
    "wof:name":"McGhee Deirdre",
    "wof:placetype":"venue"
},
  "geometry": {"coordinates":[150.886475,-34.409912],"type":"Point"}
}