{
  "type": "Feature",
  "properties": {
    "addr:full":"15 Telford Pl Morayfield QLD 4506",
    "addr:housenumber":"15",
    "addr:postcode":"4506",
    "addr:street":"Telford Pl",
    "iso:country":"AU",
    "sg:address":"15 Telford Pl",
    "sg:city":"Morayfield",
    "sg:classifiers":[
        {
            "category":"Building & Trades",
            "subcategory":"Construction",
            "type":"Services"
        }
    ],
    "sg:phone":"+61 419 652 302",
    "sg:postcode":"4506",
    "sg:province":"QLD",
    "sg:tags":[
        "contractor"
    ],
    "wof:name":"Superior Homes (Qld) Pty Ltd",
    "wof:placetype":"venue"
},
  "geometry": {"coordinates":[152.92608642600001,-27.1423110962],"type":"Point"}
}