{
  "type": "Feature",
  "properties": {
    "addr:full":"17 Moresby Ave Seaford VIC 3198",
    "addr:housenumber":"17",
    "addr:postcode":"3198",
    "addr:street":"Moresby Ave",
    "iso:country":"AU",
    "sg:address":"17 Moresby Ave",
    "sg:city":"Seaford",
    "sg:classifiers":[
        {
            "category":"Building & Trades",
            "subcategory":"Landscaping Services",
            "type":"Services"
        }
    ],
    "sg:phone":"+61 1300 367 774",
    "sg:postcode":"3198",
    "sg:province":"VIC",
    "sg:tags":[
        "inspection"
    ],
    "wof:name":"A MPPPI",
    "wof:placetype":"venue"
},
  "geometry": {"coordinates":[145.132644653,-38.1166915894],"type":"Point"}
}