{
  "type": "Feature",
  "properties": {
    "addr:full":"20 Wangara Rd Sandringham VIC 3191",
    "addr:housenumber":"20",
    "addr:postcode":"3191",
    "addr:street":"Wangara Rd",
    "iso:country":"AU",
    "sg:address":"20 Wangara Rd",
    "sg:city":"Sandringham",
    "sg:classifiers":[
        {
            "category":"Restaurant",
            "type":"Food & Drink"
        }
    ],
    "sg:phone":"+61 3 9583 5559",
    "sg:postcode":"3191",
    "sg:province":"VIC",
    "wof:name":"Birdies Bar N Bistro",
    "wof:placetype":"venue"
},
  "geometry": {"coordinates":[145.030853272,-37.9579696655],"type":"Point"}
}