{
  "type": "Feature",
  "properties": {
    "addr:full":"63 Rose St Blackall QLD 4472",
    "addr:housenumber":"63",
    "addr:postcode":"4472",
    "addr:street":"Rose St Blackall",
    "iso:country":"AU",
    "sg:address":"63 Rose St",
    "sg:city":"Blackall",
    "sg:classifiers":[
        {
            "category":"Building & Trades",
            "subcategory":"Construction",
            "type":"Services"
        }
    ],
    "sg:phone":"+61 7 4657 4866",
    "sg:postcode":"4472",
    "sg:province":"QLD",
    "sg:tags":[
        "contractor"
    ],
    "wof:name":"Henderson J K",
    "wof:placetype":"venue"
},
  "geometry": {"coordinates":[145.46510314899999,-24.4198322296],"type":"Point"}
}