{
  "type": "Feature",
  "properties": {
    "iso:country":"AU",
    "sg:address":"27/108 Royal St",
    "sg:city":"East Perth",
    "sg:classifiers":[
        {
            "category":"Personal",
            "subcategory":"Beauty Salon",
            "type":"Services"
        }
    ],
    "sg:phone":"+61 8 9325 8890",
    "sg:postcode":"6004",
    "sg:province":"WA",
    "sg:tags":[
        "hair",
        "wedding"
    ],
    "wof:name":"Safarii Skin and Body Care Centre",
    "wof:placetype":"venue"
},
  "geometry": {"coordinates":[115.87551116900001,-31.9529037476],"type":"Point"}
}