{
  "type": "Feature",
  "properties": {
    "addr:full":"25 Pratt St Moonee Ponds VIC 3039",
    "addr:housenumber":"25",
    "addr:postcode":"3039",
    "addr:street":"Pratt St",
    "iso:country":"AU",
    "sg:address":"25 Pratt St",
    "sg:city":"Moonee Ponds",
    "sg:classifiers":[
        {
            "category":"Health Services",
            "subcategory":"Optometrist",
            "type":"Services"
        }
    ],
    "sg:phone":"+61 3 9370 5684",
    "sg:postcode":"3039",
    "sg:province":"VIC",
    "wof:name":"Anthony K N Smith",
    "wof:placetype":"venue"
},
  "geometry": {"coordinates":[144.92176799999999,-37.767052],"type":"Point"}
}