{
  "type": "Feature",
  "properties": {
    "addr:full":"136 Arthur St Fairfield VIC 3078",
    "addr:housenumber":"136",
    "addr:postcode":"3078",
    "addr:street":"Arthur St",
    "iso:country":"AU",
    "sg:address":"136 Arthur St",
    "sg:city":"Fairfield",
    "sg:classifiers":[
        {
            "category":"Home & Garden",
            "subcategory":"Furniture",
            "type":"Retail Goods"
        }
    ],
    "sg:phone":"+61 3 9489 2895",
    "sg:postcode":"3078",
    "sg:province":"VIC",
    "sg:tags":[
        "repair",
        "restoration"
    ],
    "wof:name":"Fairbern Restorations",
    "wof:placetype":"venue"
},
  "geometry": {"coordinates":[145.01974487300001,-37.775302887],"type":"Point"}
}