{
  "type": "Feature",
  "properties": {
    "addr:full":"304 Seven Hills Rd Kings Langley NSW 2147",
    "addr:housenumber":"304",
    "addr:postcode":"2147",
    "addr:street":"Seven Hills Rd",
    "iso:country":"AU",
    "sg:address":"304 Seven Hills Rd",
    "sg:city":"Kings Langley",
    "sg:classifiers":[
        {
            "category":"Retail",
            "subcategory":"Veterinary Services",
            "type":"Services"
        }
    ],
    "sg:phone":"+61 2 9624 1018",
    "sg:postcode":"2147",
    "sg:province":"NSW",
    "sg:tags":[
        "surgeon"
    ],
    "wof:name":"Seven Hills Veterinary Clinic",
    "wof:placetype":"venue"
},
  "geometry": {"coordinates":[150.95408630399999,-33.7597198486],"type":"Point"}
}