{
  "type": "Feature",
  "properties": {
    "addr:full":"436 Peel St Tamworth NSW 2340",
    "addr:housenumber":"436",
    "addr:postcode":"2340",
    "addr:street":"Peel St",
    "iso:country":"AU",
    "sg:address":"436 Peel St",
    "sg:city":"Tamworth",
    "sg:classifiers":[
        {
            "category":"Fast Food",
            "type":"Food & Drink"
        }
    ],
    "sg:phone":"+61 2 6766 2499",
    "sg:postcode":"2340",
    "sg:province":"NSW",
    "sg:tags":[
        "away",
        "take"
    ],
    "wof:name":"Chook Shop The",
    "wof:placetype":"venue"
},
  "geometry": {"coordinates":[150.932693481,-31.0935745239],"type":"Point"}
}