{
  "type": "Feature",
  "properties": {
    "addr:full":"2/ 10 Villiers St New Farm QLD 4005",
    "addr:housenumber":"/ 10",
    "addr:postcode":"4005",
    "addr:street":"Villiers St",
    "iso:country":"AU",
    "sg:address":"2/ 10 Villiers St",
    "sg:city":"New Farm",
    "sg:classifiers":[
        {
            "category":"Real Estate",
            "subcategory":"Real Estate Agent",
            "type":"Services"
        }
    ],
    "sg:phone":"+61 7 3358 5544",
    "sg:postcode":"4005",
    "sg:province":"QLD",
    "sg:tags":[
        "consultant",
        "heritage"
    ],
    "wof:name":"McDonald Ivan Architects",
    "wof:placetype":"venue"
},
  "geometry": {"coordinates":[153.04505920400001,-27.4658584595],"type":"Point"}
}