{
  "type": "Feature",
  "properties": {
    "addr:full":"213 Botany St Kingsford NSW 2032",
    "addr:housenumber":"213",
    "addr:postcode":"2032",
    "addr:street":"Botany St",
    "iso:country":"AU",
    "sg:address":"213 Botany St",
    "sg:city":"Kingsford",
    "sg:classifiers":[
        {
            "category":"Professional",
            "subcategory":"Management & Consulting",
            "type":"Services"
        }
    ],
    "sg:phone":"+61 2 9398 7181",
    "sg:postcode":"2032",
    "sg:province":"NSW",
    "sg:tags":[
        "consultant",
        "energy"
    ],
    "wof:name":"Aminga Holdings Pty Ltd",
    "wof:placetype":"venue"
},
  "geometry": {"coordinates":[151.23425293,-33.9261665344],"type":"Point"}
}