{
  "type": "Feature",
  "properties": {
    "addr:full":"135 High St Penrith NSW 2750",
    "addr:housenumber":"135",
    "addr:postcode":"2750",
    "addr:street":"High St",
    "iso:country":"AU",
    "sg:address":"135 High St",
    "sg:city":"Penrith",
    "sg:classifiers":[
        {
            "category":"Social Services",
            "subcategory":"Child Care",
            "type":"Services"
        }
    ],
    "sg:phone":"+61 2 4721 7607",
    "sg:postcode":"2750",
    "sg:province":"NSW",
    "wof:name":"High St Pre-School",
    "wof:placetype":"venue"
},
  "geometry": {"coordinates":[150.916412353,-33.8903312683],"type":"Point"}
}