{
  "type": "Feature",
  "properties": {
    "addr:full":"1457 Centre Rd Clayton VIC 3168",
    "addr:housenumber":"1457",
    "addr:postcode":"3168",
    "addr:street":"Centre Rd",
    "iso:country":"AU",
    "sg:address":"1457 Centre Rd",
    "sg:city":"Clayton",
    "sg:classifiers":[
        {
            "category":"Professional",
            "subcategory":"Engineering",
            "type":"Services"
        }
    ],
    "sg:phone":"+61 3 9544 9115",
    "sg:postcode":"3168",
    "sg:province":"VIC",
    "sg:tags":[
        "engineer"
    ],
    "wof:name":"E & N Engineering",
    "wof:placetype":"venue"
},
  "geometry": {"coordinates":[145.12786865199999,-37.9294891357],"type":"Point"}
}