{
  "type": "Feature",
  "properties": {
    "addr:full":"1 Bruce St Dandenong VIC 3175",
    "addr:housenumber":"1",
    "addr:postcode":"3175",
    "addr:street":"Bruce St",
    "iso:country":"AU",
    "sg:address":"1 Bruce St",
    "sg:city":"Dandenong",
    "sg:classifiers":[
        {
            "category":"Health Services",
            "subcategory":"Doctor",
            "type":"Services"
        }
    ],
    "sg:phone":"+61 3 9791 1599",
    "sg:postcode":"3175",
    "sg:province":"VIC",
    "sg:tags":[
        "medical",
        "practitioner"
    ],
    "wof:name":"Kempster P.A. Dr",
    "wof:placetype":"venue"
},
  "geometry": {"coordinates":[145.21609497099999,-37.9778518677],"type":"Point"}
}