{
  "type": "Feature",
  "properties": {
    "iso:country":"AU",
    "sg:address":"46 Gondola Rd",
    "sg:city":"Narrabeen",
    "sg:classifiers":[
        {
            "category":"Building & Trades",
            "subcategory":"Locksmith",
            "type":"Services"
        }
    ],
    "sg:phone":"+61 414 851 858",
    "sg:postcode":"2101",
    "sg:province":"NSW",
    "sg:tags":[
        "lock"
    ],
    "wof:name":"AAA Locksmith",
    "wof:placetype":"venue"
},
  "geometry": {"coordinates":[151.290955,-33.706928],"type":"Point"}
}