{
  "type": "Feature",
  "properties": {
    "iso:country":"AU",
    "sg:address":"131 Meade St",
    "sg:city":"Glen Innes",
    "sg:classifiers":[
        {
            "category":"Travel",
            "subcategory":"Hotels & Motels",
            "type":"Entertainment"
        }
    ],
    "sg:phone":"+61 2 6732 2200",
    "sg:postcode":"2370",
    "sg:province":"NSW",
    "wof:name":"Central Motel",
    "wof:placetype":"venue"
},
  "geometry": {"coordinates":[151.73776245100001,-29.7373809814],"type":"Point"}
}