{
  "type": "Feature",
  "properties": {
    "iso:country":"AU",
    "sg:address":"Beachwood Cox Rd",
    "sg:city":"Aldinga Beach",
    "sg:classifiers":[
        {
            "category":"Building & Trades",
            "subcategory":"Construction",
            "type":"Services"
        }
    ],
    "sg:phone":"+61 8 8556 3596",
    "sg:postcode":"5173",
    "sg:province":"SA",
    "sg:tags":[
        "plasterboard",
        "plasterer",
        "fixer"
    ],
    "wof:name":"Gerrits B",
    "wof:placetype":"venue"
},
  "geometry": {"coordinates":[138.45973205600001,-35.297580719],"type":"Point"}
}