{
  "type": "Feature",
  "properties": {
    "addr:full":"33 Bishop St Kelvin Grove QLD 4059",
    "addr:housenumber":"33",
    "addr:postcode":"4059",
    "addr:street":"Bishop St",
    "iso:country":"AU",
    "sg:address":"33 Bishop St",
    "sg:city":"Kelvin Grove",
    "sg:classifiers":[
        {
            "category":"Building & Trades",
            "subcategory":"Construction",
            "type":"Services"
        }
    ],
    "sg:phone":"+61 7 3352 6995",
    "sg:postcode":"4059",
    "sg:province":"QLD",
    "sg:tags":[
        "contractor"
    ],
    "wof:name":"Penfold Constructions (Qld) Pty Ltd",
    "wof:placetype":"venue"
},
  "geometry": {"coordinates":[153.009155273,-27.4431610107],"type":"Point"}
}