{
  "type": "Feature",
  "properties": {
    "addr:full":"48 Edward St Norwood SA 5067",
    "addr:housenumber":"48",
    "addr:postcode":"5067",
    "addr:street":"Edward St",
    "iso:country":"AU",
    "sg:address":"48 Edward St",
    "sg:city":"Norwood",
    "sg:classifiers":[
        {
            "category":"Health Services",
            "subcategory":"Health Practitioner",
            "type":"Services"
        }
    ],
    "sg:phone":"+61 8 8431 4488",
    "sg:postcode":"5067",
    "sg:province":"SA",
    "sg:tags":[
        "psychologist"
    ],
    "wof:name":"Rinaldi Ali",
    "wof:placetype":"venue"
},
  "geometry": {"coordinates":[138.634475708,-34.9198036194],"type":"Point"}
}