{
  "type": "Feature",
  "properties": {
    "addr:full":"42 Allambie Rd Allambie NSW 2100",
    "addr:housenumber":"42",
    "addr:postcode":"2100",
    "addr:street":"Allambie Rd",
    "iso:country":"AU",
    "sg:address":"42 Allambie Rd",
    "sg:city":"Allambie",
    "sg:classifiers":[
        {
            "category":"Professional",
            "subcategory":"Art Services",
            "type":"Services"
        }
    ],
    "sg:phone":"+61 2 9938 5648",
    "sg:postcode":"2100",
    "sg:province":"NSW",
    "sg:tags":[
        "decorator",
        "painter"
    ],
    "wof:name":"Prime Painting",
    "wof:placetype":"venue"
},
  "geometry": {"coordinates":[151.259033203,-33.7705535889],"type":"Point"}
}