{
  "type": "Feature",
  "properties": {
    "addr:full":"Shp1/ 52 Indi Ave Red Cliffs VIC 3496",
    "addr:postcode":"3496",
    "addr:street":"Indi Ave",
    "iso:country":"AU",
    "sg:address":"Shp1/ 52 Indi Ave",
    "sg:city":"Red Cliffs",
    "sg:classifiers":[
        {
            "category":"Health Services",
            "subcategory":"Doctor",
            "type":"Services"
        }
    ],
    "sg:phone":"+61 3 5024 3070",
    "sg:postcode":"3496",
    "sg:province":"VIC",
    "sg:tags":[
        "medical",
        "practitioner"
    ],
    "wof:name":"Bradey Dr S",
    "wof:placetype":"venue"
},
  "geometry": {"coordinates":[142.18942260700001,-34.3072128296],"type":"Point"}
}