{
  "type": "Feature",
  "properties": {
    "iso:country":"AU",
    "sg:address":"3a Ingara Ave",
    "sg:city":"Miranda",
    "sg:classifiers":[
        {
            "category":"Home & Garden",
            "subcategory":"Building Materials",
            "type":"Retail Goods"
        }
    ],
    "sg:phone":"+61 2 9524 5065",
    "sg:postcode":"2228",
    "sg:province":"NSW",
    "sg:tags":[
        "lawn",
        "cutting",
        "maintenance"
    ],
    "wof:name":"AAB Lawnmowing Service",
    "wof:placetype":"venue"
},
  "geometry": {"coordinates":[151.11134338400001,-34.0276412964],"type":"Point"}
}