{
  "type": "Feature",
  "properties": {
    "addr:full":"Level 1/ 50 Sylvan Rd Toowong QLD 4066",
    "addr:housenumber":"/ 50",
    "addr:postcode":"4066",
    "addr:street":"Sylvan Rd",
    "iso:country":"AU",
    "sg:address":"Level 1/ 50 Sylvan Rd",
    "sg:city":"Toowong",
    "sg:classifiers":[
        {
            "category":"Professional",
            "subcategory":"Computer Services",
            "type":"Services"
        }
    ],
    "sg:phone":"+61 7 3721 2600",
    "sg:postcode":"4066",
    "sg:province":"QLD",
    "sg:tags":[
        "package",
        "software"
    ],
    "wof:name":"Concord Australia Pty Ltd",
    "wof:placetype":"venue"
},
  "geometry": {"coordinates":[152.99269104000001,-27.4812526703],"type":"Point"}
}