{
  "type": "Feature",
  "properties": {
    "iso:country":"AU",
    "sg:address":"2 / 73 Market St",
    "sg:city":"Wollongong",
    "sg:classifiers":[
        {
            "category":"Professional",
            "subcategory":"Accounting & Tax Preparation",
            "type":"Services"
        }
    ],
    "sg:phone":"+61 2 4225 7779",
    "sg:postcode":"2500",
    "sg:province":"NSW",
    "sg:tags":[
        "accountant",
        "auditor"
    ],
    "wof:name":"Poulton & Associates",
    "wof:placetype":"venue"
},
  "geometry": {"coordinates":[150.89233400000001,-34.423347],"type":"Point"}
}