{
  "type": "Feature",
  "properties": {
    "iso:country":"AU",
    "sg:address":"Cnr Bridge Rd & Church St",
    "sg:city":"Richmond",
    "sg:classifiers":[
        {
            "category":"Health Services",
            "subcategory":"Optometrist",
            "type":"Services"
        }
    ],
    "sg:phone":"+61 3 9429 9292",
    "sg:postcode":"3121",
    "sg:province":"VIC",
    "wof:name":"Teh Michelle C H",
    "wof:placetype":"venue"
},
  "geometry": {"coordinates":[144.99920654300001,-37.8185768127],"type":"Point"}
}