{
  "type": "Feature",
  "properties": {
    "iso:country":"AU",
    "sg:address":"151 Islington St",
    "sg:city":"Collingwood",
    "sg:classifiers":[
        {
            "category":"Manufacturing",
            "subcategory":"Motor Vehicles & Parts",
            "type":"Manufacturing & Wholesale Goods"
        }
    ],
    "sg:phone":"+61 3 9415 8787",
    "sg:postcode":"3066",
    "sg:province":"VIC",
    "sg:tags":[
        "replacement"
    ],
    "wof:name":"BM Autoteile",
    "wof:placetype":"venue"
},
  "geometry": {"coordinates":[144.99111938499999,-37.8046913147],"type":"Point"}
}