{
  "type": "Feature",
  "properties": {
    "addr:full":"50 Beenak Rd Wandin VIC 3139",
    "addr:housenumber":"50",
    "addr:postcode":"3139",
    "addr:street":"Beenak Rd",
    "iso:country":"AU",
    "sg:address":"50 Beenak Rd",
    "sg:city":"Wandin",
    "sg:classifiers":[
        {
            "category":"Utilities",
            "subcategory":"Fuel Oil & Lpg",
            "type":"Services"
        }
    ],
    "sg:phone":"+61 3 5964 3506",
    "sg:postcode":"3139",
    "sg:province":"VIC",
    "sg:tags":[
        "merchant"
    ],
    "wof:name":"Lynden Fuel Transport Pty Ltd",
    "wof:placetype":"venue"
},
  "geometry": {"coordinates":[145.43272399899999,-37.7862586975],"type":"Point"}
}