{
  "type": "Feature",
  "properties": {
    "iso:country":"AU",
    "sg:address":"16/ 305 Maloney St",
    "sg:city":"Rosebery",
    "sg:classifiers":[
        {
            "category":"Professional",
            "subcategory":"Detective & Security Services",
            "type":"Services"
        }
    ],
    "sg:phone":"+61 2 9667 2507",
    "sg:postcode":"2018",
    "sg:province":"NSW",
    "sg:tags":[
        "guard",
        "patrol"
    ],
    "wof:name":"Mehmet Balicok Security Systems",
    "wof:placetype":"venue"
},
  "geometry": {"coordinates":[151.20687866200001,-33.9236907959],"type":"Point"}
}