{
  "type": "Feature",
  "properties": {
    "addr:full":"4/ 17 Cook Drv Coffs Harbour NSW 2450",
    "addr:housenumber":"/ 17",
    "addr:postcode":"2450",
    "addr:street":"Cook Drv",
    "iso:country":"AU",
    "sg:address":"4/ 17 Cook Drv",
    "sg:city":"Coffs Harbour",
    "sg:classifiers":[
        {
            "category":"Sports & Exercise",
            "subcategory":"Playing Field",
            "type":"Entertainment"
        }
    ],
    "sg:phone":"+61 1300 552 265",
    "sg:postcode":"2450",
    "sg:province":"NSW",
    "sg:tags":[
        "repair",
        "walking",
        "retail",
        "umbrella",
        "stick"
    ],
    "wof:name":"Sapphire Shades (Aust.)",
    "wof:placetype":"venue"
},
  "geometry": {"coordinates":[153.09878499999999,-30.315405],"type":"Point"}
}