{
  "type": "Feature",
  "properties": {
    "addr:full":"42 Walker St North Sydney NSW 2060",
    "addr:housenumber":"42",
    "addr:postcode":"2060",
    "addr:street":"Walker St",
    "iso:country":"AU",
    "sg:address":"42 Walker St",
    "sg:city":"North Sydney",
    "sg:classifiers":[
        {
            "category":"Professional",
            "subcategory":"Printing & Photocopies",
            "type":"Services"
        }
    ],
    "sg:phone":"+61 2 9956 8599",
    "sg:postcode":"2060",
    "sg:province":"NSW",
    "sg:tags":[
        "publishing",
        "desktop"
    ],
    "wof:name":"Flash Graphics Pty Ltd",
    "wof:placetype":"venue"
},
  "geometry": {"coordinates":[151.208526611,-33.8397674561],"type":"Point"}
}