{
  "type": "Feature",
  "properties": {
    "iso:country":"AU",
    "sg:address":"38 Moonee St",
    "sg:city":"Coffs Harbour",
    "sg:classifiers":[
        {
            "category":"Food & Beverages",
            "subcategory":"Bakery",
            "type":"Retail Goods"
        }
    ],
    "sg:phone":"+61 2 6651 4313",
    "sg:postcode":"2450",
    "sg:province":"NSW",
    "sg:tags":[
        "cake",
        "shop",
        "pastry"
    ],
    "wof:name":"Cafe Bonne Sante",
    "wof:placetype":"venue"
},
  "geometry": {"coordinates":[153.112717,-30.296415],"type":"Point"}
}