{
  "type": "Feature",
  "properties": {
    "addr:full":"109 Parker St Dunkeld VIC 3294",
    "addr:housenumber":"109",
    "addr:postcode":"3294",
    "addr:street":"Parker St",
    "iso:country":"AU",
    "sg:address":"109 Parker St",
    "sg:city":"Dunkeld",
    "sg:classifiers":[
        {
            "category":"Cafe",
            "type":"Food & Drink"
        }
    ],
    "sg:phone":"+61 3 5577 2288",
    "sg:postcode":"3294",
    "sg:province":"VIC",
    "wof:name":"Dunkeld Gourmet Pantry",
    "wof:placetype":"venue"
},
  "geometry": {"coordinates":[142.339477539,-37.6489715576],"type":"Point"}
}