{
  "type": "Feature",
  "properties": {
    "iso:country":"AU",
    "sg:address":"1 / 4 Eady St",
    "sg:city":"Glenorchy",
    "sg:classifiers":[
        {
            "category":"Banks & Credit Unions",
            "subcategory":"Financial Services",
            "type":"Services"
        }
    ],
    "sg:phone":"+61 3 6214 7833",
    "sg:postcode":"7010",
    "sg:province":"TAS",
    "sg:tags":[
        "loan",
        "finance",
        "mortgage"
    ],
    "wof:name":"Wizard",
    "wof:placetype":"venue"
},
  "geometry": {"coordinates":[147.27789306599999,-42.8345222473],"type":"Point"}
}