{
  "type": "Feature",
  "properties": {
    "addr:full":"Shop 1, 103 Hobart Rd Kings Meadows TAS 7249",
    "addr:housenumber":"shop 1 103",
    "addr:postcode":"7249",
    "addr:street":"Hobart Rd",
    "iso:country":"AU",
    "sg:address":"Shop 1, 103 Hobart Rd",
    "sg:city":"Kings Meadows",
    "sg:classifiers":[
        {
            "category":"Shopping",
            "subcategory":"Pets & Pet Supplies",
            "type":"Retail Goods"
        }
    ],
    "sg:phone":"+61 3 6343 3770",
    "sg:postcode":"7249",
    "sg:province":"TAS",
    "sg:tags":[
        "food"
    ],
    "wof:name":"Tassie Pet Meats",
    "wof:placetype":"venue"
},
  "geometry": {"coordinates":[147.15914917000001,-41.4649734497],"type":"Point"}
}