{
  "type": "Feature",
  "properties": {
    "iso:country":"AU",
    "sg:address":"18 Elizabeth St",
    "sg:city":"Castlemaine",
    "sg:classifiers":[
        {
            "category":"Home & Garden",
            "subcategory":"Carpets & Floor Coverings",
            "type":"Retail Goods"
        }
    ],
    "sg:phone":"+61 3 5472 5225",
    "sg:postcode":"3450",
    "sg:province":"VIC",
    "wof:name":"Central Carpet Clearance Pty Ltd",
    "wof:placetype":"venue"
},
  "geometry": {"coordinates":[144.216552734,-37.0669288635],"type":"Point"}
}