{
  "type": "Feature",
  "properties": {
    "iso:country":"AU",
    "sg:address":"St John of God Hospital 80 Myers St",
    "sg:city":"Geelong Geelong",
    "sg:classifiers":[
        {
            "category":"Health Services",
            "subcategory":"Doctor",
            "type":"Services"
        }
    ],
    "sg:phone":"+61 3 5273 1200",
    "sg:postcode":"3220",
    "sg:province":"VIC",
    "sg:tags":[
        "medical",
        "practitioner"
    ],
    "wof:name":"MRI Centre",
    "wof:placetype":"venue"
},
  "geometry": {"coordinates":[144.357971,-38.151211],"type":"Point"}
}