{
  "type": "Feature",
  "properties": {
    "addr:full":"River Park Rd Cowra NSW 2794",
    "addr:postcode":"2794",
    "addr:street":"Park Rd",
    "iso:country":"AU",
    "sg:address":"River Park Rd",
    "sg:city":"Cowra",
    "sg:classifiers":[
        {
            "category":"Freight",
            "type":"Transportation"
        }
    ],
    "sg:phone":"+61 2 6342 2962",
    "sg:postcode":"2794",
    "sg:province":"NSW",
    "sg:tags":[
        "light",
        "carrier"
    ],
    "wof:name":"IPEC",
    "wof:placetype":"venue"
},
  "geometry": {"coordinates":[148.663009644,-33.8295478821],"type":"Point"}
}