{
  "type": "Feature",
  "properties": {
    "addr:full":"Pine St West Wyalong NSW 2671",
    "addr:postcode":"2671",
    "addr:street":"Pine St West",
    "iso:country":"AU",
    "sg:address":"Pine St",
    "sg:city":"West Wyalong",
    "sg:classifiers":[
        {
            "category":"Education",
            "subcategory":"Kindergarten",
            "type":"Public Place"
        }
    ],
    "sg:phone":"+61 2 6972 2795",
    "sg:postcode":"2671",
    "sg:province":"NSW",
    "sg:tags":[
        "pre-schools"
    ],
    "wof:name":"West Wyalong Bland Pre-School",
    "wof:placetype":"venue"
},
  "geometry": {"coordinates":[147.211105347,-33.9189414978],"type":"Point"}
}