{
  "type": "Feature",
  "properties": {
    "addr:full":"Inala Town Centre, 156 Inala Ave Inala QLD 4077",
    "addr:housenumber":"156",
    "addr:postcode":"4077",
    "addr:street":"Inala Ave Inala",
    "iso:country":"AU",
    "sg:address":"Inala Town Centre, 156 Inala Ave",
    "sg:city":"Inala",
    "sg:classifiers":[
        {
            "category":"Professional",
            "subcategory":"Accounting & Tax Preparation",
            "type":"Services"
        }
    ],
    "sg:phone":"+61 7 3879 7196",
    "sg:postcode":"4077",
    "sg:province":"QLD",
    "sg:tags":[
        "consultant",
        "taxation"
    ],
    "wof:name":"ITP Income Tax Professionals",
    "wof:placetype":"venue"
},
  "geometry": {"coordinates":[152.974212647,-27.5973911285],"type":"Point"}
}