{
  "type": "Feature",
  "properties": {
    "addr:full":"4 Xavier Drv Wheelers Hill VIC 3150",
    "addr:housenumber":"4",
    "addr:postcode":"3150",
    "addr:street":"Xavier Drv",
    "iso:country":"AU",
    "sg:address":"4 Xavier Drv",
    "sg:city":"Wheelers Hill",
    "sg:classifiers":[
        {
            "category":"Professional",
            "subcategory":"Accounting & Tax Preparation",
            "type":"Services"
        }
    ],
    "sg:phone":"+61 3 9560 0122",
    "sg:postcode":"3150",
    "sg:province":"VIC",
    "sg:tags":[
        "consultant",
        "taxation"
    ],
    "wof:name":"Riddle J J",
    "wof:placetype":"venue"
},
  "geometry": {"coordinates":[145.183395386,-37.92004776],"type":"Point"}
}