{
  "type": "Feature",
  "properties": {
    "iso:country":"AU",
    "sg:address":"5 Dennis Ave",
    "sg:city":"Mildura",
    "sg:classifiers":[
        {
            "category":"Professional",
            "subcategory":"Art Services",
            "type":"Services"
        }
    ],
    "sg:phone":"+61 417 322 252",
    "sg:postcode":"3500",
    "sg:province":"VIC",
    "sg:tags":[
        "decorator",
        "painter"
    ],
    "wof:name":"K & V Manning",
    "wof:placetype":"venue"
},
  "geometry": {"coordinates":[142.15507507300001,-34.2028999329],"type":"Point"}
}