{
  "type": "Feature",
  "properties": {
    "addr:full":"Biggs Rd Withcott QLD 4352",
    "addr:postcode":"4352",
    "addr:street":"Biggs Rd",
    "iso:country":"AU",
    "sg:address":"Biggs Rd",
    "sg:city":"Withcott",
    "sg:classifiers":[
        {
            "category":"Education",
            "subcategory":"School",
            "type":"Public Place"
        }
    ],
    "sg:phone":"+61 7 4614 9314",
    "sg:postcode":"4352",
    "sg:province":"QLD",
    "sg:tags":[
        "state",
        "except",
        "nsw"
    ],
    "wof:name":"Withcott Preschool",
    "wof:placetype":"venue"
},
  "geometry": {"coordinates":[152.022873,-27.554136],"type":"Point"}
}