{
  "type": "Feature",
  "properties": {
    "iso:country":"AU",
    "sg:address":"508 Brookton Hwy",
    "sg:city":"Roleystone",
    "sg:classifiers":[
        {
            "category":"Personal",
            "subcategory":"Beauty Salon",
            "type":"Services"
        }
    ],
    "sg:phone":"+61 8 9496 1132",
    "sg:postcode":"6111",
    "sg:province":"WA",
    "sg:tags":[
        "hairdresser"
    ],
    "wof:name":"Hairrods For Hair",
    "wof:placetype":"venue"
},
  "geometry": {"coordinates":[116.070487976,-32.1255950928],"type":"Point"}
}