{
  "type": "Feature",
  "properties": {
    "iso:country":"AU",
    "sg:address":"2/ 12 Lagoon St",
    "sg:city":"Sandgate",
    "sg:classifiers":[
        {
            "category":"Health Services",
            "subcategory":"Optometrist",
            "type":"Services"
        }
    ],
    "sg:phone":"+61 7 3269 6799",
    "sg:postcode":"4017",
    "sg:province":"QLD",
    "wof:name":"Muller Scott",
    "wof:placetype":"venue"
},
  "geometry": {"coordinates":[153.06825256400001,-27.3203792572],"type":"Point"}
}