{
  "type": "Feature",
  "properties": {
    "addr:full":"Shp 2/ 10 Albert St Darley VIC 3340",
    "addr:housenumber":"/ 10",
    "addr:postcode":"3340",
    "addr:street":"Albert St",
    "iso:country":"AU",
    "sg:address":"Shp 2/ 10 Albert St",
    "sg:city":"Darley",
    "sg:classifiers":[
        {
            "category":"Retail",
            "subcategory":"Self-service Laundry",
            "type":"Services"
        }
    ],
    "sg:phone":"+61 3 5367 0711",
    "sg:postcode":"3340",
    "sg:province":"VIC",
    "wof:name":"Brights &#039;N&#039; Whites",
    "wof:placetype":"venue"
},
  "geometry": {"coordinates":[144.44868500000001,-37.654976],"type":"Point"}
}