{
  "type": "Feature",
  "properties": {
    "iso:country":"AU",
    "sg:address":"Bayswater St",
    "sg:city":"Milton",
    "sg:classifiers":[
        {
            "category":"Education",
            "subcategory":"School",
            "type":"Public Place"
        }
    ],
    "sg:phone":"+61 7 3514 6333",
    "sg:postcode":"4064",
    "sg:province":"QLD",
    "sg:tags":[
        "state",
        "except",
        "nsw"
    ],
    "wof:name":"Milton Primary",
    "wof:placetype":"venue"
},
  "geometry": {"coordinates":[152.99873352,-27.4676704407],"type":"Point"}
}