{
  "type": "Feature",
  "properties": {
    "iso:country":"AU",
    "sg:address":"9 Kernot St",
    "sg:city":"Dickson",
    "sg:classifiers":[
        {
            "category":"Professional",
            "subcategory":"Art Services",
            "type":"Services"
        }
    ],
    "sg:phone":"+61 2 6247 8904",
    "sg:postcode":"2602",
    "sg:province":"ACT",
    "sg:tags":[
        "decorator",
        "painter"
    ],
    "wof:name":"Dominant Industries",
    "wof:placetype":"venue"
},
  "geometry": {"coordinates":[149.145629883,-35.2527694702],"type":"Point"}
}