{
  "type": "Feature",
  "properties": {
    "addr:full":"Cnr Dowton & Rolleston Ave Salisbury North SA 5108",
    "addr:postcode":"5108",
    "addr:street":"Cnr Dowton;Ave",
    "iso:country":"AU",
    "sg:address":"Cnr Dowton & Rolleston Ave",
    "sg:city":"Salisbury North",
    "sg:classifiers":[
        {
            "category":"Education",
            "subcategory":"School",
            "type":"Public Place"
        }
    ],
    "sg:phone":"+61 8 8285 3109",
    "sg:postcode":"5108",
    "sg:province":"SA",
    "sg:tags":[
        "state",
        "except",
        "nsw"
    ],
    "wof:name":"Bowden Brompton Community School",
    "wof:placetype":"venue"
},
  "geometry": {"coordinates":[138.63406372099999,-34.7535324097],"type":"Point"}
}