{
  "type": "Feature",
  "properties": {
    "iso:country":"AU",
    "sg:address":"Factory 5, 25 Wise Ave",
    "sg:city":"Seaford",
    "sg:classifiers":[
        {
            "category":"Retail",
            "subcategory":"Auto Repair",
            "type":"Services"
        }
    ],
    "sg:phone":"+61 3 9786 7469",
    "sg:postcode":"3198",
    "sg:province":"VIC",
    "sg:tags":[
        "repairer",
        "motor",
        "engineer"
    ],
    "wof:name":"Modern Auto Repairs",
    "wof:placetype":"venue"
},
  "geometry": {"coordinates":[145.134674072,-38.1131896973],"type":"Point"}
}