{
  "type": "Feature",
  "properties": {
    "addr:full":"10 Reservoir Ave Greenacre NSW 2190",
    "addr:housenumber":"10",
    "addr:postcode":"2190",
    "addr:street":"Reservoir Ave",
    "iso:country":"AU",
    "sg:address":"10 Reservoir Ave",
    "sg:city":"Greenacre",
    "sg:classifiers":[
        {
            "category":"Autos & Motor Vehicles",
            "subcategory":"Auto Supplies",
            "type":"Retail Goods"
        }
    ],
    "sg:phone":"+61 2 9790 7344",
    "sg:postcode":"2190",
    "sg:province":"NSW",
    "sg:tags":[
        "equipment",
        "part",
        "truck"
    ],
    "wof:name":"Sydney Driveline",
    "wof:placetype":"venue"
},
  "geometry": {"coordinates":[151.03825399999999,-33.903526],"type":"Point"}
}