{
  "type": "Feature",
  "properties": {
    "addr:full":"Shp2/ 5 Makin St Keith SA 5267",
    "addr:postcode":"5267",
    "addr:street":"Makin St",
    "iso:country":"AU",
    "sg:address":"Shp2/ 5 Makin St",
    "sg:city":"Keith",
    "sg:classifiers":[
        {
            "category":"Farming",
            "subcategory":"Fish & Marine Products",
            "type":"Manufacturing & Wholesale Goods"
        }
    ],
    "sg:phone":"+61 8 8755 1577",
    "sg:postcode":"5267",
    "sg:province":"SA",
    "sg:tags":[
        "organic"
    ],
    "wof:name":"The Green Frog Tea House",
    "wof:placetype":"venue"
},
  "geometry": {"coordinates":[140.35488899999999,-36.098141],"type":"Point"}
}