{
  "type": "Feature",
  "properties": {
    "addr:full":"46 Cumberland St Cessnock NSW 2325",
    "addr:housenumber":"46",
    "addr:postcode":"2325",
    "addr:street":"Cumberland St",
    "iso:country":"AU",
    "sg:address":"46 Cumberland St",
    "sg:city":"Cessnock",
    "sg:classifiers":[
        {
            "category":"Professional",
            "subcategory":"Art Services",
            "type":"Services"
        }
    ],
    "sg:phone":"+61 2 4991 4780",
    "sg:postcode":"2325",
    "sg:province":"NSW",
    "sg:tags":[
        "work",
        "metal"
    ],
    "wof:name":"Steve Johns",
    "wof:placetype":"venue"
},
  "geometry": {"coordinates":[151.356933594,-32.8364257812],"type":"Point"}
}