{
  "type": "Feature",
  "properties": {
    "addr:full":"678 Botany Rd Alexandria NSW 2015",
    "addr:housenumber":"678",
    "addr:postcode":"2015",
    "addr:street":"Botany Rd",
    "iso:country":"AU",
    "sg:address":"678 Botany Rd",
    "sg:city":"Alexandria",
    "sg:classifiers":[
        {
            "category":"Building & Trades",
            "subcategory":"Construction",
            "type":"Services"
        }
    ],
    "sg:phone":"+61 2 9693 2000",
    "sg:postcode":"2015",
    "sg:province":"NSW",
    "sg:tags":[
        "industrial",
        "commercial",
        "air conditioning"
    ],
    "wof:name":"Solarite Air Conditioning",
    "wof:placetype":"venue"
},
  "geometry": {"coordinates":[151.19645690900001,-33.9211769104],"type":"Point"}
}