{
  "type": "Feature",
  "properties": {
    "addr:full":"PO Box 1831 Bunbury WA 6230",
    "addr:postcode":"6230",
    "iso:country":"AU",
    "sg:address":"PO Box 1831",
    "sg:city":"Bunbury",
    "sg:classifiers":[
        {
            "category":"Building & Trades",
            "subcategory":"Pest Control",
            "type":"Services"
        }
    ],
    "sg:phone":"+61 418 932 198",
    "sg:postcode":"6230",
    "sg:province":"WA",
    "wof:name":"Action Pest Control",
    "wof:placetype":"venue"
},
  "geometry": {"coordinates":[115.645348,-33.380112],"type":"Point"}
}