{
  "type": "Feature",
  "properties": {
    "addr:full":"409 Tannery La Strathfieldsaye VIC 3551",
    "addr:housenumber":"409",
    "addr:postcode":"3551",
    "addr:street":"Tannery La",
    "iso:country":"AU",
    "sg:address":"409 Tannery La",
    "sg:city":"Strathfieldsaye",
    "sg:classifiers":[
        {
            "category":"Building & Trades",
            "subcategory":"Construction",
            "type":"Services"
        }
    ],
    "sg:phone":"+61 418 510 553",
    "sg:postcode":"3551",
    "sg:province":"VIC",
    "sg:tags":[
        "contractor"
    ],
    "wof:name":"Griffin JX & HC",
    "wof:placetype":"venue"
},
  "geometry": {"coordinates":[144.349319458,-36.8063659668],"type":"Point"}
}