{
  "type": "Feature",
  "properties": {
    "iso:country":"AU",
    "sg:address":"1a Mort St",
    "sg:city":"Toowoomba",
    "sg:classifiers":[
        {
            "category":"Home & Garden",
            "subcategory":"Building Materials",
            "type":"Retail Goods"
        }
    ],
    "sg:phone":"+61 7 4634 1222",
    "sg:postcode":"4350",
    "sg:province":"QLD",
    "sg:tags":[
        "fencing"
    ],
    "wof:name":"Makano Timber Pty Ltd",
    "wof:placetype":"venue"
},
  "geometry": {"coordinates":[151.943649,-27.540089],"type":"Point"}
}