{
  "type": "Feature",
  "properties": {
    "addr:full":"30 Station St Nunawading VIC 3131",
    "addr:housenumber":"30",
    "addr:postcode":"3131",
    "addr:street":"Station St",
    "iso:country":"AU",
    "sg:address":"30 Station St",
    "sg:city":"Nunawading",
    "sg:classifiers":[
        {
            "category":"Food & Beverages",
            "subcategory":"Bakery",
            "type":"Retail Goods"
        }
    ],
    "sg:phone":"+61 3 9878 3517",
    "sg:postcode":"3131",
    "sg:province":"VIC",
    "sg:tags":[
        "baker"
    ],
    "wof:name":"Ta Ta Hot Bread & Cake Kitchen",
    "wof:placetype":"venue"
},
  "geometry": {"coordinates":[145.17689514200001,-37.8206138611],"type":"Point"}
}