{
  "type": "Feature",
  "properties": {
    "addr:full":"Feros Arcade 3/ 2 Lawson St Byron Bay NSW 2481",
    "addr:housenumber":"3 / 2",
    "addr:postcode":"2481",
    "addr:street":"Lawson St",
    "iso:country":"AU",
    "sg:address":"Feros Arcade 3/ 2 Lawson St",
    "sg:city":"Byron Bay",
    "sg:classifiers":[
        {
            "category":"Shopping",
            "subcategory":"Clothing, Apparel, & Fashions",
            "type":"Retail Goods"
        }
    ],
    "sg:phone":"+61 2 6685 7733",
    "sg:postcode":"2481",
    "sg:province":"NSW",
    "sg:tags":[
        "lingerie",
        "hosiery",
        "sleepwear"
    ],
    "wof:name":"The Lingerie Drawer",
    "wof:placetype":"venue"
},
  "geometry": {"coordinates":[153.612625122,-28.6423187256],"type":"Point"}
}