{
  "type": "Feature",
  "properties": {
    "iso:country":"AU",
    "sg:address":"6 Roseman Rd",
    "sg:city":"Chirnside Park",
    "sg:classifiers":[
        {
            "category":"Farming",
            "subcategory":"Vineyard",
            "type":"Manufacturing & Wholesale Goods"
        }
    ],
    "sg:phone":"+61 3 9735 1819",
    "sg:postcode":"3116",
    "sg:province":"VIC",
    "sg:tags":[
        "winery"
    ],
    "wof:name":"Yarra Vale Wines",
    "wof:placetype":"venue"
},
  "geometry": {"coordinates":[145.33297729500001,-37.7526168823],"type":"Point"}
}