{
  "type": "Feature",
  "properties": {
    "iso:country":"AU",
    "sg:address":"151 West Burleigh Rd",
    "sg:city":"Burleigh Heads",
    "sg:classifiers":[
        {
            "category":"Shopping",
            "subcategory":"Party Supplies",
            "type":"Retail Goods"
        }
    ],
    "sg:phone":"+61 7 5520 0212",
    "sg:postcode":"4220",
    "sg:province":"QLD",
    "sg:tags":[
        "children's"
    ],
    "wof:name":"2B Kids",
    "wof:placetype":"venue"
},
  "geometry": {"coordinates":[153.44236755399999,-28.1017856598],"type":"Point"}
}