{
  "type": "Feature",
  "properties": {
    "addr:full":"Cnr Marmion Ave & Bellville Gardens Clarkson WA 6030",
    "addr:postcode":"6030",
    "addr:street":"Cnr Marmion Ave &",
    "iso:country":"AU",
    "sg:address":"Cnr Marmion Ave",
    "sg:city":"& Bellville Gardens Clarkson",
    "sg:classifiers":[
        {
            "category":"Shopping",
            "subcategory":"Music",
            "type":"Retail Goods"
        }
    ],
    "sg:phone":"+61 8 9305 9533",
    "sg:postcode":"6030",
    "sg:province":"WA",
    "sg:tags":[
        "instrument",
        "musical"
    ],
    "wof:name":"Mindarie Music Centre",
    "wof:placetype":"venue"
},
  "geometry": {"coordinates":[115.71568298299999,-31.6889667511],"type":"Point"}
}