{
  "type": "Feature",
  "properties": {
    "iso:country":"AU",
    "sg:address":"Suite 324/ 20 Dale St",
    "sg:city":"Brookvale",
    "sg:classifiers":[
        {
            "category":"Building & Trades",
            "subcategory":"Landscaping Services",
            "type":"Services"
        }
    ],
    "sg:phone":"+61 2 9907 1099",
    "sg:postcode":"2100",
    "sg:province":"NSW",
    "sg:tags":[
        "designer",
        "landscape",
        "contractor"
    ],
    "wof:name":"Daniell Dagger Design Landscapes",
    "wof:placetype":"venue"
},
  "geometry": {"coordinates":[151.268234253,-33.7652168274],"type":"Point"}
}