{
  "type": "Feature",
  "properties": {
    "iso:country":"AU",
    "sg:address":"5 Swallow Crt",
    "sg:city":"Ballajura",
    "sg:classifiers":[
        {
            "category":"Professional",
            "subcategory":"Art Services",
            "type":"Services"
        }
    ],
    "sg:phone":"+61 415 758 138",
    "sg:postcode":"6066",
    "sg:province":"WA",
    "sg:tags":[
        "decorator",
        "painter"
    ],
    "wof:name":"Marry's Painting",
    "wof:placetype":"venue"
},
  "geometry": {"coordinates":[115.900093079,-31.8362731934],"type":"Point"}
}