{
  "type": "Feature",
  "properties": {
    "addr:full":"Shop 8 Stokes Hill Wharf Darwin NT 0800",
    "addr:housenumber":"shop 8",
    "addr:postcode":"nt 0800",
    "addr:street":"Stokes Hill",
    "iso:country":"AU",
    "sg:address":"Shop 8",
    "sg:city":"Stokes Hill Wharf Darwin",
    "sg:classifiers":[
        {
            "category":"Ice Cream",
            "type":"Food & Drink"
        }
    ],
    "sg:phone":"+61 8 8941 3705",
    "sg:postcode":"0800",
    "sg:province":"NT",
    "sg:tags":[
        "retail"
    ],
    "wof:name":"Biglick The",
    "wof:placetype":"venue"
},
  "geometry": {"coordinates":[130.84202575699999,-12.43592453],"type":"Point"}
}