{
  "type": "Feature",
  "properties": {
    "addr:full":"252 High St Prahran VIC 3181",
    "addr:housenumber":"252",
    "addr:postcode":"3181",
    "addr:street":"High St",
    "iso:country":"AU",
    "sg:address":"252 High St",
    "sg:city":"Prahran",
    "sg:classifiers":[
        {
            "category":"Shopping",
            "subcategory":"Jewelry",
            "type":"Retail Goods"
        }
    ],
    "sg:phone":"+61 3 9533 7222",
    "sg:postcode":"3181",
    "sg:province":"VIC",
    "sg:tags":[
        "jeweller"
    ],
    "wof:name":"J A B Jewellers",
    "wof:placetype":"venue"
},
  "geometry": {"coordinates":[144.99621582,-37.852355957],"type":"Point"}
}