{
  "type": "Feature",
  "properties": {
    "addr:full":"72 Palmerin St Warwick QLD 4370",
    "addr:housenumber":"72",
    "addr:postcode":"4370",
    "addr:street":"Palmerin St",
    "iso:country":"AU",
    "sg:address":"72 Palmerin St",
    "sg:city":"Warwick",
    "sg:classifiers":[
        {
            "category":"Retail",
            "subcategory":"Event Space",
            "type":"Services"
        }
    ],
    "sg:phone":"+61 7 4661 0300",
    "sg:postcode":"4370",
    "sg:province":"QLD",
    "sg:tags":[
        "venue",
        "reception",
        "wedding"
    ],
    "wof:name":"Warwick Town Hall",
    "wof:placetype":"venue"
},
  "geometry": {"coordinates":[152.03297424300001,-28.2150783539],"type":"Point"}
}