{
  "type": "Feature",
  "properties": {
    "iso:country":"AU",
    "sg:address":"Bywong St",
    "sg:city":"Toowong",
    "sg:classifiers":[
        {
            "category":"Education",
            "subcategory":"School",
            "type":"Public Place"
        }
    ],
    "sg:phone":"+61 7 3377 9333",
    "sg:postcode":"4066",
    "sg:province":"QLD",
    "sg:tags":[
        "state",
        "except",
        "nsw"
    ],
    "wof:name":"Toowong College",
    "wof:placetype":"venue"
},
  "geometry": {"coordinates":[152.97885131800001,-27.4854755402],"type":"Point"}
}