{
  "type": "Feature",
  "properties": {
    "addr:full":"208 Browning St Bathurst NSW 2795",
    "addr:housenumber":"208",
    "addr:postcode":"2795",
    "addr:street":"Browning St",
    "iso:country":"AU",
    "sg:address":"208 Browning St",
    "sg:city":"Bathurst",
    "sg:classifiers":[
        {
            "category":"Retail",
            "subcategory":"Laundry & Dry Cleaning",
            "type":"Services"
        }
    ],
    "sg:phone":"+61 2 6331 4804",
    "sg:postcode":"2795",
    "sg:province":"NSW",
    "wof:name":"The Wash Shop",
    "wof:placetype":"venue"
},
  "geometry": {"coordinates":[149.566574097,-33.4252624512],"type":"Point"}
}