{
  "type": "Feature",
  "properties": {
    "iso:country":"AU",
    "sg:address":"71 Thurlgona Rd",
    "sg:city":"Engadine",
    "sg:classifiers":[
        {
            "category":"Building & Trades",
            "subcategory":"Plumbing",
            "type":"Services"
        }
    ],
    "sg:phone":"+61 2 9520 9560",
    "sg:postcode":"2233",
    "sg:province":"NSW",
    "sg:tags":[
        "plumber",
        "gasfitters"
    ],
    "wof:name":"Top Cat Plumbing Pty Ltd",
    "wof:placetype":"venue"
},
  "geometry": {"coordinates":[151.01034545900001,-34.0504951477],"type":"Point"}
}