{
  "type": "Feature",
  "properties": {
    "iso:country":"AU",
    "sg:address":"30 Biggs Ave",
    "sg:city":"Beachmere",
    "sg:classifiers":[
        {
            "category":"Travel",
            "subcategory":"Hotels & Motels",
            "type":"Entertainment"
        }
    ],
    "sg:phone":"+61 7 5496 8577",
    "sg:postcode":"4510",
    "sg:province":"QLD",
    "wof:name":"Beachmere Palms Motel",
    "wof:placetype":"venue"
},
  "geometry": {"coordinates":[153.052628,-27.132244],"type":"Point"}
}