{
  "type": "Feature",
  "properties": {
    "addr:full":"Institute Rd Westmead NSW 2145",
    "addr:postcode":"2145",
    "addr:street":"Institute Rd",
    "iso:country":"AU",
    "sg:address":"Institute Rd",
    "sg:city":"Westmead",
    "sg:classifiers":[
        {
            "category":"Education",
            "subcategory":"School",
            "type":"Public Place"
        }
    ],
    "sg:phone":"+61 2 9633 1030",
    "sg:postcode":"2145",
    "sg:province":"NSW",
    "wof:name":"Redbank Special School",
    "wof:placetype":"venue"
},
  "geometry": {"coordinates":[150.986206055,-33.8026618958],"type":"Point"}
}