{
  "type": "Feature",
  "properties": {
    "addr:full":"Strickland St Denmark WA 6333",
    "addr:postcode":"6333",
    "addr:street":"Strickland St",
    "iso:country":"AU",
    "sg:address":"Strickland St",
    "sg:city":"Denmark",
    "sg:classifiers":[
        {
            "category":"Food & Beverages",
            "subcategory":"Supermarket",
            "type":"Retail Goods"
        }
    ],
    "sg:phone":"+61 8 9848 1200",
    "sg:postcode":"6333",
    "sg:province":"WA",
    "sg:tags":[
        "grocery",
        "store"
    ],
    "wof:name":"IGA Supermarkets",
    "wof:placetype":"venue"
},
  "geometry": {"coordinates":[117.355232239,-34.9604454041],"type":"Point"}
}