{
  "type": "Feature",
  "properties": {
    "iso:country":"AU",
    "sg:address":"Unit 5/ 33 Coath Rd",
    "sg:city":"Kalgoorlie",
    "sg:classifiers":[
        {
            "category":"Building & Trades",
            "subcategory":"Cleaning & Sanitation",
            "type":"Services"
        }
    ],
    "sg:phone":"+61 8 9022 7297",
    "sg:postcode":"6430",
    "sg:province":"WA",
    "sg:tags":[
        "abrasive",
        "blasting"
    ],
    "wof:name":"A-Z Sandblasting and Industrial Painting",
    "wof:placetype":"venue"
},
  "geometry": {"coordinates":[121.43142700200001,-30.7796783447],"type":"Point"}
}