{
  "type": "Feature",
  "properties": {
    "iso:country":"AU",
    "sg:address":"3 By The Sea Rd",
    "sg:city":"Mona Vale",
    "sg:classifiers":[
        {
            "category":"Retail",
            "subcategory":"Auto Repair",
            "type":"Services"
        }
    ],
    "sg:phone":"+61 2 9999 2968",
    "sg:postcode":"2103",
    "sg:province":"NSW",
    "sg:tags":[
        "repairer",
        "motor",
        "engineer"
    ],
    "wof:name":"KJ Motors",
    "wof:placetype":"venue"
},
  "geometry": {"coordinates":[151.30780029300001,-33.6756668091],"type":"Point"}
}