{
  "type": "Feature",
  "properties": {
    "iso:country":"AU",
    "sg:address":"McMahon St",
    "sg:city":"Lake Grace",
    "sg:classifiers":[
        {
            "category":"Social Services",
            "subcategory":"Child Care",
            "type":"Services"
        }
    ],
    "sg:phone":"+61 8 9865 1251",
    "sg:postcode":"6353",
    "sg:province":"WA",
    "sg:tags":[
        "support",
        "health"
    ],
    "wof:name":"Child Health Services",
    "wof:placetype":"venue"
},
  "geometry": {"coordinates":[118.46221199999999,-33.101154],"type":"Point"}
}