{
  "type": "Feature",
  "properties": {
    "addr:full":"Ste2/ 280 Bong Bong St Bowral NSW 2576",
    "addr:housenumber":"280",
    "addr:postcode":"2576",
    "addr:street":"Bong Bong St",
    "iso:country":"AU",
    "sg:address":"Ste2/ 280 Bong Bong St",
    "sg:city":"Bowral",
    "sg:classifiers":[
        {
            "category":"Professional",
            "subcategory":"Business Services",
            "type":"Services"
        }
    ],
    "sg:phone":"+61 2 4861 4218",
    "sg:postcode":"2576",
    "sg:province":"NSW",
    "sg:tags":[
        "management",
        "event"
    ],
    "wof:name":"Shaun Martyn Agency",
    "wof:placetype":"venue"
},
  "geometry": {"coordinates":[150.41807556099999,-34.4786682129],"type":"Point"}
}