{
  "type": "Feature",
  "properties": {
    "iso:country":"AU",
    "sg:address":"38 Crescent St",
    "sg:city":"Gatton",
    "sg:classifiers":[
        {
            "category":"Shopping",
            "subcategory":"Computers & Home Electronics",
            "type":"Retail Goods"
        }
    ],
    "sg:phone":"+61 7 5462 1288",
    "sg:postcode":"4343",
    "sg:province":"QLD",
    "sg:tags":[
        "equipment",
        "part",
        "electronic"
    ],
    "wof:name":"Retravision (Qld) Ltd",
    "wof:placetype":"venue"
},
  "geometry": {"coordinates":[152.278244019,-27.5556373596],"type":"Point"}
}