{
  "type": "Feature",
  "properties": {
    "addr:full":"Footner Rd Stirling North SA 5710",
    "addr:postcode":"5710",
    "addr:street":"Footner Rd",
    "iso:country":"AU",
    "sg:address":"Footner Rd",
    "sg:city":"Stirling North",
    "sg:classifiers":[
        {
            "category":"Building & Trades",
            "subcategory":"Construction",
            "type":"Services"
        }
    ],
    "sg:phone":"+61 8 8643 6101",
    "sg:postcode":"5710",
    "sg:province":"SA",
    "sg:tags":[
        "contractor"
    ],
    "wof:name":"B.W. Constructions Pty Ltd",
    "wof:placetype":"venue"
},
  "geometry": {"coordinates":[137.812423706,-32.5016403198],"type":"Point"}
}