{
  "type": "Feature",
  "properties": {
    "addr:full":"2/ 126 South Pine Rd Brendale QLD 4500",
    "addr:housenumber":"/ 126",
    "addr:postcode":"4500",
    "addr:street":"South Pine Rd",
    "iso:country":"AU",
    "sg:address":"2/ 126 South Pine Rd",
    "sg:city":"Brendale",
    "sg:classifiers":[
        {
            "category":"Autos & Motor Vehicles",
            "subcategory":"Auto Supplies",
            "type":"Retail Goods"
        }
    ],
    "sg:phone":"+61 7 3881 1444",
    "sg:postcode":"4500",
    "sg:province":"QLD",
    "sg:tags":[
        "battery",
        "automotive"
    ],
    "sg:website":"http://www.turbobatteries.com.au",
    "wof:name":"Turbo Batteries Pty Ltd",
    "wof:placetype":"venue"
},
  "geometry": {"coordinates":[152.981887817,-27.3265838623],"type":"Point"}
}