{
  "type": "Feature",
  "properties": {
    "addr:full":"Suite 1/1st Floor Devonshire House 406 King Newcastle West NSW 2302",
    "addr:housenumber":"devonshire;406",
    "addr:postcode":"2302",
    "addr:street":"King",
    "iso:country":"AU",
    "sg:address":"Suite 1/1st Floor Devonshire House 406 King",
    "sg:city":"Newcastle West",
    "sg:classifiers":[
        {
            "category":"Organizations",
            "subcategory":"Labor Organization",
            "type":"Services"
        }
    ],
    "sg:phone":"+61 2 4929 1162",
    "sg:postcode":"2302",
    "sg:province":"NSW",
    "sg:tags":[
        "union"
    ],
    "wof:name":"Newcastle Trades Hall Council",
    "wof:placetype":"venue"
},
  "geometry": {"coordinates":[151.75964400000001,-32.926853],"type":"Point"}
}