{
  "type": "Feature",
  "properties": {
    "iso:country":"AU",
    "sg:address":"Shop G43 Maroondah Hwy",
    "sg:city":"Ringwood",
    "sg:classifiers":[
        {
            "category":"Shopping",
            "subcategory":"Optical Goods",
            "type":"Retail Goods"
        }
    ],
    "sg:phone":"+61 3 9879 2966",
    "sg:postcode":"3134",
    "sg:province":"VIC",
    "sg:tags":[
        "dispenser",
        "prescription"
    ],
    "wof:name":"Kays Optical Pty Ltd",
    "wof:placetype":"venue"
},
  "geometry": {"coordinates":[145.224685669,-37.816619873],"type":"Point"}
}