{
  "type": "Feature",
  "properties": {
    "addr:full":"78 Kinghorn St Nowra NSW 2541",
    "addr:housenumber":"78",
    "addr:postcode":"2541",
    "addr:street":"Kinghorn St",
    "iso:country":"AU",
    "sg:address":"78 Kinghorn St",
    "sg:city":"Nowra",
    "sg:classifiers":[
        {
            "category":"Real Estate",
            "subcategory":"Real Estate Agent",
            "type":"Services"
        }
    ],
    "sg:phone":"+61 2 4423 4600",
    "sg:postcode":"2541",
    "sg:province":"NSW",
    "wof:name":"Elders Real Estate NSW",
    "wof:placetype":"venue"
},
  "geometry": {"coordinates":[150.60304260300001,-34.875453949],"type":"Point"}
}