{
  "type": "Feature",
  "properties": {
    "addr:full":"164 James St Toowoomba QLD 4350",
    "addr:housenumber":"164",
    "addr:postcode":"4350",
    "addr:street":"James St",
    "iso:country":"AU",
    "sg:address":"164 James St",
    "sg:city":"Toowoomba",
    "sg:classifiers":[
        {
            "category":"Home & Garden",
            "subcategory":"Building Materials",
            "type":"Retail Goods"
        }
    ],
    "sg:phone":"+61 7 4659 5966",
    "sg:postcode":"4350",
    "sg:province":"QLD",
    "sg:tags":[
        "concrete",
        "additive"
    ],
    "wof:name":"Decorative Concrete Products",
    "wof:placetype":"venue"
},
  "geometry": {"coordinates":[151.95135500000001,-27.568724],"type":"Point"}
}