{
  "type": "Feature",
  "properties": {
    "addr:full":"&#034;International House&#034; 26 St Georges Tce Perth WA 6000",
    "addr:housenumber":"26",
    "addr:postcode":"6000",
    "addr:street":"St Georges Tce",
    "iso:country":"AU",
    "sg:address":"&#034;International House&#034; 26 St",
    "sg:city":"Georges Tce Perth",
    "sg:classifiers":[
        {
            "category":"Professional",
            "subcategory":"Printing & Photocopies",
            "type":"Services"
        }
    ],
    "sg:phone":"+61 8 9325 5955",
    "sg:postcode":"6000",
    "sg:province":"WA",
    "sg:tags":[
        "photocopying"
    ],
    "wof:name":"Docuprint",
    "wof:placetype":"venue"
},
  "geometry": {"coordinates":[115.863182068,-31.9567337036],"type":"Point"}
}