{
  "type": "Feature",
  "properties": {
    "iso:country":"AU",
    "sg:address":"U 14/ 137 Rooks Rd",
    "sg:city":"Nunawading",
    "sg:classifiers":[
        {
            "category":"Manufacturing",
            "subcategory":"Building Materials",
            "type":"Manufacturing & Wholesale Goods"
        }
    ],
    "sg:phone":"+61 3 9872 6172",
    "sg:postcode":"3131",
    "sg:province":"VIC",
    "sg:tags":[
        "concrete",
        "product"
    ],
    "wof:name":"Protecrete Australia Pty Ltd",
    "wof:placetype":"venue"
},
  "geometry": {"coordinates":[145.18707275400001,-37.8298034668],"type":"Point"}
}