{
  "type": "Feature",
  "properties": {
    "addr:full":"Lvl 1/ 30-38 King St Perth WA 6000",
    "addr:housenumber":"/ 30-38",
    "addr:postcode":"6000",
    "addr:street":"King St",
    "iso:country":"AU",
    "sg:address":"Lvl 1/ 30-38 King St",
    "sg:city":"Perth",
    "sg:classifiers":[
        {
            "category":"Real Estate",
            "subcategory":"Real Estate Agent",
            "type":"Services"
        }
    ],
    "sg:phone":"+61 8 9422 3600",
    "sg:postcode":"6000",
    "sg:province":"WA",
    "wof:name":"Churchill Knight",
    "wof:placetype":"venue"
},
  "geometry": {"coordinates":[115.859466553,-31.9560146332],"type":"Point"}
}