{
  "type": "Feature",
  "properties": {
    "addr:full":"54 Memorial Ave Liverpool NSW 2170",
    "addr:housenumber":"54",
    "addr:postcode":"2170",
    "addr:street":"Memorial Ave",
    "iso:country":"AU",
    "sg:address":"54 Memorial Ave",
    "sg:city":"Liverpool",
    "sg:classifiers":[
        {
            "category":"Organizations",
            "subcategory":"Community Association",
            "type":"Services"
        }
    ],
    "sg:phone":"+61 2 9821 4087",
    "sg:postcode":"2170",
    "sg:province":"NSW",
    "sg:tags":[
        "organisation",
        "family",
        "welfare"
    ],
    "wof:name":"Centacare Catholic Community Youth Accommodation Services",
    "wof:placetype":"venue"
},
  "geometry": {"coordinates":[150.921051025,-33.9246864319],"type":"Point"}
}