{
  "type": "Feature",
  "properties": {
    "addr:full":"136 Lilburne Rd Duncraig WA 6023",
    "addr:housenumber":"136",
    "addr:postcode":"6023",
    "addr:street":"Lilburne Rd",
    "iso:country":"AU",
    "sg:address":"136 Lilburne Rd",
    "sg:city":"Duncraig",
    "sg:classifiers":[
        {
            "category":"Structure",
            "subcategory":"Tunnel",
            "type":"Public Place"
        }
    ],
    "sg:phone":"+61 412 989 837",
    "sg:postcode":"6023",
    "sg:province":"WA",
    "sg:tags":[
        "cleaner",
        "industrial",
        "vacuum"
    ],
    "wof:name":"The Vacuum Doctor",
    "wof:placetype":"venue"
},
  "geometry": {"coordinates":[115.772247315,-31.827091217],"type":"Point"}
}