{
  "type": "Feature",
  "properties": {
    "addr:full":"64 Currawa Drv Boronia VIC 3155",
    "addr:housenumber":"64",
    "addr:postcode":"3155",
    "addr:street":"Currawa Drv",
    "iso:country":"AU",
    "sg:address":"64 Currawa Drv",
    "sg:city":"Boronia",
    "sg:classifiers":[
        {
            "category":"Professional",
            "subcategory":"Engineering",
            "type":"Services"
        }
    ],
    "sg:phone":"+61 3 9761 1155",
    "sg:postcode":"3155",
    "sg:province":"VIC",
    "sg:tags":[
        "consulting",
        "engineer"
    ],
    "wof:name":"Wheatland Lance W & Associates Pty Ltd",
    "wof:placetype":"venue"
},
  "geometry": {"coordinates":[145.28602600100001,-37.8724365234],"type":"Point"}
}