{
  "type": "Feature",
  "properties": {
    "iso:country":"AU",
    "sg:address":"35 Myers St",
    "sg:city":"Geelong",
    "sg:classifiers":[
        {
            "category":"Banks & Credit Unions",
            "subcategory":"Financial Services",
            "type":"Services"
        }
    ],
    "sg:phone":"+61 3 5222 2577",
    "sg:postcode":"3220",
    "sg:province":"VIC",
    "sg:tags":[
        "planning"
    ],
    "wof:name":"Ellis Jan",
    "wof:placetype":"venue"
},
  "geometry": {"coordinates":[144.355606,-38.150269],"type":"Point"}
}