{
  "type": "Feature",
  "properties": {
    "iso:country":"AU",
    "sg:address":"Shop 7/ 57 Avalon Pde",
    "sg:city":"Avalon",
    "sg:classifiers":[
        {
            "category":"Restaurant",
            "type":"Food & Drink"
        }
    ],
    "sg:phone":"+61 2 9918 8350",
    "sg:postcode":"2107",
    "sg:province":"NSW",
    "wof:name":"Ashiana Indian Restaurant",
    "wof:placetype":"venue"
},
  "geometry": {"coordinates":[151.327682495,-33.6357765198],"type":"Point"}
}