{
  "type": "Feature",
  "properties": {
    "addr:full":"54 Park Rd Cabramatta NSW 2166",
    "addr:housenumber":"54",
    "addr:postcode":"2166",
    "addr:street":"Park Rd",
    "iso:country":"AU",
    "sg:address":"54 Park Rd",
    "sg:city":"Cabramatta",
    "sg:classifiers":[
        {
            "category":"Health Services",
            "subcategory":"Dentist",
            "type":"Services"
        }
    ],
    "sg:phone":"+61 2 9726 3170",
    "sg:postcode":"2166",
    "sg:province":"NSW",
    "wof:name":"Hai Dovan Dr",
    "wof:placetype":"venue"
},
  "geometry": {"coordinates":[150.93707275400001,-33.894657135],"type":"Point"}
}