{
  "type": "Feature",
  "properties": {
    "iso:country":"AU",
    "sg:address":"4- 6 Brompton St",
    "sg:city":"Marrickville",
    "sg:classifiers":[
        {
            "category":"Manufacturing",
            "subcategory":"Building Materials",
            "type":"Manufacturing & Wholesale Goods"
        }
    ],
    "sg:phone":"+61 2 9569 3644",
    "sg:postcode":"2204",
    "sg:province":"NSW",
    "sg:tags":[
        "adhesive",
        "tape"
    ],
    "wof:name":"JR Packaging Aust Pty Ltd",
    "wof:placetype":"venue"
},
  "geometry": {"coordinates":[151.165436,-33.90527],"type":"Point"}
}