{
  "type": "Feature",
  "properties": {
    "addr:full":"33 Hanover St Fitzroy VIC 3065",
    "addr:housenumber":"33",
    "addr:postcode":"3065",
    "addr:street":"Hanover St",
    "iso:country":"AU",
    "sg:address":"33 Hanover St",
    "sg:city":"Fitzroy",
    "sg:classifiers":[
        {
            "category":"Organizations",
            "subcategory":"Community Association",
            "type":"Services"
        }
    ],
    "sg:phone":"+61 3 9417 0581",
    "sg:postcode":"3065",
    "sg:province":"VIC",
    "sg:tags":[
        "shiatsu",
        "therapy"
    ],
    "wof:name":"Shiatsu Therapist-Akira Oshima",
    "wof:placetype":"venue"
},
  "geometry": {"coordinates":[144.97558593799999,-37.802696228],"type":"Point"}
}