{
  "type": "Feature",
  "properties": {
    "addr:full":"Turners Rd Stawell VIC 3380",
    "addr:postcode":"3380",
    "addr:street":"Turners Rd",
    "iso:country":"AU",
    "sg:address":"Turners Rd",
    "sg:city":"Stawell",
    "sg:classifiers":[
        {
            "category":"Utilities",
            "subcategory":"Electric",
            "type":"Services"
        }
    ],
    "sg:phone":"+61 3 5356 4413",
    "sg:postcode":"3380",
    "sg:province":"VIC",
    "sg:tags":[
        "electrical",
        "contractor"
    ],
    "wof:name":"Vos T & M",
    "wof:placetype":"venue"
},
  "geometry": {"coordinates":[142.765625,-37.0643806458],"type":"Point"}
}