{
  "type": "Feature",
  "properties": {
    "iso:country":"AU",
    "sg:address":"83 Glenayr Ave",
    "sg:city":"Bondi",
    "sg:classifiers":[
        {
            "category":"Food & Beverages",
            "subcategory":"Supermarket",
            "type":"Retail Goods"
        }
    ],
    "sg:phone":"+61 2 9130 8036",
    "sg:postcode":"2026",
    "sg:province":"NSW",
    "sg:tags":[
        "grocery",
        "store"
    ],
    "wof:name":"Seven Ways Supermarket",
    "wof:placetype":"venue"
},
  "geometry": {"coordinates":[151.27418518100001,-33.8850822449],"type":"Point"}
}