{
  "type": "Feature",
  "properties": {
    "addr:full":"39 Murray Farm St Carlingford NSW 2118",
    "addr:housenumber":"39",
    "addr:postcode":"2118",
    "addr:street":"Murray Farm St",
    "iso:country":"AU",
    "sg:address":"39 Murray Farm St",
    "sg:city":"Carlingford",
    "sg:classifiers":[
        {
            "category":"Home & Garden",
            "subcategory":"Carpets & Floor Coverings",
            "type":"Retail Goods"
        }
    ],
    "sg:phone":"+61 2 9873 1432",
    "sg:postcode":"2118",
    "sg:province":"NSW",
    "sg:tags":[
        "wood"
    ],
    "wof:name":"Graham A E Pty Ltd",
    "wof:placetype":"venue"
},
  "geometry": {"coordinates":[151.04255676299999,-33.7633743286],"type":"Point"}
}