{
  "type": "Feature",
  "properties": {
    "addr:full":"485 Ballarat Rd Sunshine VIC 3020",
    "addr:housenumber":"485",
    "addr:postcode":"3020",
    "addr:street":"Ballarat Rd",
    "iso:country":"AU",
    "sg:address":"485 Ballarat Rd",
    "sg:city":"Sunshine",
    "sg:classifiers":[
        {
            "category":"Fast Food",
            "type":"Food & Drink"
        }
    ],
    "sg:phone":"+61 3 9311 6253",
    "sg:postcode":"3020",
    "sg:province":"VIC",
    "sg:tags":[
        "away",
        "take"
    ],
    "wof:name":"Red Rooster",
    "wof:placetype":"venue"
},
  "geometry": {"coordinates":[144.833923,-37.777802],"type":"Point"}
}