{
  "type": "Feature",
  "properties": {
    "iso:country":"AU",
    "sg:address":"Shp2/ 347 Rocky Point Rd",
    "sg:city":"Sans Souci",
    "sg:classifiers":[
        {
            "category":"Social Services",
            "type":"Services"
        }
    ],
    "sg:phone":"+61 2 9583 2192",
    "sg:postcode":"2219",
    "sg:province":"NSW",
    "sg:tags":[
        "domestic",
        "help"
    ],
    "wof:name":"Zetas Cleaning & Ironing Services",
    "wof:placetype":"venue"
},
  "geometry": {"coordinates":[151.132095,-33.991837],"type":"Point"}
}