{
  "type": "Feature",
  "properties": {
    "iso:country":"AU",
    "sg:address":"32 - 34 Napier St",
    "sg:city":"Essendon",
    "sg:classifiers":[
        {
            "category":"Retail",
            "subcategory":"Auto Repair",
            "type":"Services"
        }
    ],
    "sg:phone":"+61 3 9370 7040",
    "sg:postcode":"3040",
    "sg:province":"VIC",
    "sg:tags":[
        "testing",
        "inspection",
        "motor",
        "vehicle"
    ],
    "wof:name":"Serv Group (AUST)",
    "wof:placetype":"venue"
},
  "geometry": {"coordinates":[144.91810607900001,-37.7540664673],"type":"Point"}
}