{
  "type": "Feature",
  "properties": {
    "addr:full":"15 Highland Crs Maitland NSW 2320",
    "addr:housenumber":"15",
    "addr:postcode":"2320",
    "addr:street":"Highland Crs",
    "iso:country":"AU",
    "sg:address":"15 Highland Crs",
    "sg:city":"Maitland",
    "sg:classifiers":[
        {
            "category":"Home & Garden",
            "subcategory":"Garden Supply",
            "type":"Retail Goods"
        }
    ],
    "sg:phone":"+61 402 762 264",
    "sg:postcode":"2320",
    "sg:province":"NSW",
    "sg:tags":[
        "turf",
        "lawn"
    ],
    "wof:name":"Dirt &#039;n&#039; Turf",
    "wof:placetype":"venue"
},
  "geometry": {"coordinates":[151.570114136,-32.7078857422],"type":"Point"}
}