{
  "type": "Feature",
  "properties": {
    "addr:full":"251 Newbed Rd Railton TAS 7305",
    "addr:housenumber":"251",
    "addr:postcode":"7305",
    "addr:street":"Newbed Rd",
    "iso:country":"AU",
    "sg:address":"251 Newbed Rd",
    "sg:city":"Railton",
    "sg:classifiers":[
        {
            "category":"Professional",
            "type":"Services"
        }
    ],
    "sg:phone":"+61 419 323 364",
    "sg:postcode":"7305",
    "sg:province":"TAS",
    "sg:tags":[
        "transport"
    ],
    "wof:name":"Caroline Quarries Pty Ltd",
    "wof:placetype":"venue"
},
  "geometry": {"coordinates":[146.391953,-41.347977],"type":"Point"}
}