{
  "type": "Feature",
  "properties": {
    "addr:full":"11 Bellbird Rd Mt Eliza VIC 3930",
    "addr:housenumber":"11",
    "addr:postcode":"3930",
    "addr:street":"Bellbird Rd",
    "iso:country":"AU",
    "sg:address":"11 Bellbird Rd",
    "sg:city":"Mt Eliza",
    "sg:classifiers":[
        {
            "category":"Utilities",
            "subcategory":"Mobile Phone",
            "type":"Services"
        }
    ],
    "sg:phone":"+61 3 9787 7649",
    "sg:postcode":"3930",
    "sg:province":"VIC",
    "sg:tags":[
        "aviation",
        "consultant"
    ],
    "wof:name":"Civil Aircraft Sales",
    "wof:placetype":"venue"
},
  "geometry": {"coordinates":[145.104248047,-38.2001037598],"type":"Point"}
}