{
  "type": "Feature",
  "properties": {
    "addr:full":"Suite 6/ 41 Bridge Rd Richmond VIC 3121",
    "addr:housenumber":"41",
    "addr:postcode":"3121",
    "addr:street":"Bridge Rd",
    "iso:country":"AU",
    "sg:address":"Suite 6/ 41 Bridge Rd",
    "sg:city":"Richmond",
    "sg:classifiers":[
        {
            "category":"Real Estate",
            "subcategory":"Architect",
            "type":"Services"
        }
    ],
    "sg:phone":"+61 3 9428 2499",
    "sg:postcode":"3121",
    "sg:province":"VIC",
    "wof:name":"Lateral Dimension",
    "wof:placetype":"venue"
},
  "geometry": {"coordinates":[144.991333008,-37.8175430298],"type":"Point"}
}