{
  "type": "Feature",
  "properties": {
    "iso:country":"AU",
    "sg:address":"282 Collins St",
    "sg:city":"Melbourne",
    "sg:classifiers":[
        {
            "category":"Health Services",
            "subcategory":"Health Practitioner",
            "type":"Services"
        }
    ],
    "sg:phone":"+61 3 9650 0777",
    "sg:postcode":"3000",
    "sg:province":"VIC",
    "sg:tags":[
        "naturopath"
    ],
    "wof:name":"Colin Dansey N.D.",
    "wof:placetype":"venue"
},
  "geometry": {"coordinates":[144.964767456,-37.8158721924],"type":"Point"}
}