{
  "type": "Feature",
  "properties": {
    "addr:full":"PO Box 2905 Bundaberg QLD 4670",
    "addr:postcode":"4670",
    "iso:country":"AU",
    "sg:address":"PO Box 2905",
    "sg:city":"Bundaberg",
    "sg:classifiers":[
        {
            "category":"Building & Trades",
            "subcategory":"Construction",
            "type":"Services"
        }
    ],
    "sg:phone":"+61 414 792 505",
    "sg:postcode":"4670",
    "sg:province":"QLD",
    "sg:tags":[
        "contractor"
    ],
    "wof:name":"Meech Constructions",
    "wof:placetype":"venue"
},
  "geometry": {"coordinates":[152.34669494600001,-24.8670501709],"type":"Point"}
}