{
  "type": "Feature",
  "properties": {
    "iso:country":"AU",
    "sg:address":"Shop 2/ 14 Maple La",
    "sg:city":"Cooroy",
    "sg:classifiers":[
        {
            "category":"Professional",
            "subcategory":"Computer Services",
            "type":"Services"
        }
    ],
    "sg:phone":"+61 7 5442 5900",
    "sg:postcode":"4563",
    "sg:province":"QLD",
    "sg:tags":[
        "repairs",
        "upgrade",
        "equipment"
    ],
    "wof:name":"BTN computers#",
    "wof:placetype":"venue"
},
  "geometry": {"coordinates":[152.90945434599999,-26.4165935516],"type":"Point"}
}