{
  "type": "Feature",
  "properties": {
    "addr:full":"56 Blackwood Ave Augusta WA 6290",
    "addr:housenumber":"56",
    "addr:postcode":"6290",
    "addr:street":"Blackwood Ave",
    "iso:country":"AU",
    "sg:address":"56 Blackwood Ave",
    "sg:city":"Augusta",
    "sg:classifiers":[
        {
            "category":"Real Estate",
            "subcategory":"Real Estate Agent",
            "type":"Services"
        }
    ],
    "sg:phone":"+61 8 9758 1667",
    "sg:postcode":"6290",
    "sg:province":"WA",
    "wof:name":"Augusta Real Estate First National",
    "wof:placetype":"venue"
},
  "geometry": {"coordinates":[115.159919739,-34.3165779114],"type":"Point"}
}