{
  "type": "Feature",
  "properties": {
    "addr:full":"Cnr Waverley Drv & Sirius Rd Unanderra NSW 2526",
    "addr:postcode":"2526",
    "addr:street":"Cnr Waverley Drv & Sirius Rd",
    "iso:country":"AU",
    "sg:address":"Cnr Waverley Drv & Sirius Rd",
    "sg:city":"Unanderra",
    "sg:classifiers":[
        {
            "category":"Manufacturing",
            "subcategory":"Glass & Minerals",
            "type":"Manufacturing & Wholesale Goods"
        }
    ],
    "sg:phone":"+61 2 4271 8725",
    "sg:postcode":"2526",
    "sg:province":"NSW",
    "sg:tags":[
        "merchant",
        "granite",
        "marble"
    ],
    "wof:name":"De Santis Marble & Granite",
    "wof:placetype":"venue"
},
  "geometry": {"coordinates":[150.84512329099999,-34.4588127136],"type":"Point"}
}