{
  "type": "Feature",
  "properties": {
    "addr:full":"U4/ 30 Chelmsford St Williamstown North VIC 3016",
    "addr:housenumber":"30",
    "addr:postcode":"3016",
    "addr:street":"U4 /;Chelmsford St",
    "iso:country":"AU",
    "sg:address":"U4/ 30 Chelmsford St",
    "sg:city":"Williamstown North",
    "sg:classifiers":[
        {
            "category":"Building & Trades",
            "subcategory":"Construction",
            "type":"Services"
        }
    ],
    "sg:phone":"+61 3 9397 3588",
    "sg:postcode":"3016",
    "sg:province":"VIC",
    "sg:tags":[
        "plasterboard",
        "plasterer",
        "fixer"
    ],
    "wof:name":"Willamstown Plaster",
    "wof:placetype":"venue"
},
  "geometry": {"coordinates":[144.863449097,-37.8518257141],"type":"Point"}
}