{
  "type": "Feature",
  "properties": {
    "iso:country":"AU",
    "sg:address":"88 Sydney Pde",
    "sg:city":"Geelong",
    "sg:classifiers":[
        {
            "category":"Banks & Credit Unions",
            "subcategory":"Financial Services",
            "type":"Services"
        }
    ],
    "sg:phone":"+61 3 5222 8224",
    "sg:postcode":"3220",
    "sg:province":"VIC",
    "sg:tags":[
        "annuity",
        "rollover",
        "superannuation",
        "consultant"
    ],
    "wof:name":"Terracall John",
    "wof:placetype":"venue"
},
  "geometry": {"coordinates":[144.371048,-38.154774],"type":"Point"}
}