{
  "type": "Feature",
  "properties": {
    "addr:full":"6 Gleno Crt Ballarat VIC 3352",
    "addr:housenumber":"6",
    "addr:postcode":"3352",
    "addr:street":"Gleno Crt",
    "iso:country":"AU",
    "sg:address":"6 Gleno Crt",
    "sg:city":"Ballarat",
    "sg:classifiers":[
        {
            "category":"Manufacturing",
            "subcategory":"Wood Products",
            "type":"Manufacturing & Wholesale Goods"
        }
    ],
    "sg:phone":"+61 3 5344 8372",
    "sg:postcode":"3352",
    "sg:province":"VIC",
    "sg:tags":[
        "polisher",
        "french"
    ],
    "wof:name":"Bomitali Renato Antique Furniture Restorations",
    "wof:placetype":"venue"
},
  "geometry": {"coordinates":[143.76915,-37.532326],"type":"Point"}
}