{
  "type": "Feature",
  "properties": {
    "addr:full":"1 Arundel Crt Ormiston QLD 4160",
    "addr:housenumber":"1",
    "addr:postcode":"4160",
    "addr:street":"Arundel Crt",
    "iso:country":"AU",
    "sg:address":"1 Arundel Crt",
    "sg:city":"Ormiston",
    "sg:classifiers":[
        {
            "category":"Shopping",
            "subcategory":"Stationery & Office Supplies",
            "type":"Retail Goods"
        }
    ],
    "sg:phone":"+61 1800 773 321",
    "sg:postcode":"4160",
    "sg:province":"QLD",
    "sg:tags":[
        "equipment",
        "badge",
        "making"
    ],
    "wof:name":"Allbadges",
    "wof:placetype":"venue"
},
  "geometry": {"coordinates":[153.25567626899999,-27.5095214844],"type":"Point"}
}