{
  "type": "Feature",
  "properties": {
    "iso:country":"AU",
    "sg:address":"32 Kosky St",
    "sg:city":"Sunshine West",
    "sg:classifiers":[
        {
            "category":"Retail",
            "subcategory":"Driving School",
            "type":"Services"
        }
    ],
    "sg:phone":"+61 3 9311 0628",
    "sg:postcode":"3020",
    "sg:province":"VIC",
    "wof:name":"Sunny Driving School",
    "wof:placetype":"venue"
},
  "geometry": {"coordinates":[144.819473,-37.788216],"type":"Point"}
}