{
  "type": "Feature",
  "properties": {
    "iso:country":"AU",
    "sg:address":"28 Dew St",
    "sg:city":"Thebarton",
    "sg:classifiers":[
        {
            "category":"Personal",
            "subcategory":"Nail Salon",
            "type":"Services"
        }
    ],
    "sg:phone":"+61 8 8234 2648",
    "sg:postcode":"5031",
    "sg:province":"SA",
    "sg:tags":[
        "foil",
        "printing",
        "stamping"
    ],
    "wof:name":"Trinnes Bookbinders",
    "wof:placetype":"venue"
},
  "geometry": {"coordinates":[138.57327270499999,-34.9190711975],"type":"Point"}
}