{
  "type": "Feature",
  "properties": {
    "addr:full":"190 Forestdale Drv Forestdale QLD 4118",
    "addr:housenumber":"190",
    "addr:postcode":"4118",
    "addr:street":"Forestdale Drv",
    "iso:country":"AU",
    "sg:address":"190 Forestdale Drv",
    "sg:city":"Forestdale",
    "sg:classifiers":[
        {
            "category":"Utilities",
            "subcategory":"Electric",
            "type":"Services"
        }
    ],
    "sg:phone":"+61 7 3809 4868",
    "sg:postcode":"4118",
    "sg:province":"QLD",
    "sg:tags":[
        "electrical",
        "contractor"
    ],
    "wof:name":"F.A.S.T. Electrical",
    "wof:placetype":"venue"
},
  "geometry": {"coordinates":[153.002807617,-27.6687774658],"type":"Point"}
}