{
  "type": "Feature",
  "properties": {
    "iso:country":"AU",
    "sg:address":"4/ 166 Main South Rd",
    "sg:city":"Morphett Vale",
    "sg:classifiers":[
        {
            "category":"Professional",
            "subcategory":"Accounting & Tax Preparation",
            "type":"Services"
        }
    ],
    "sg:phone":"+61 8 8186 6006",
    "sg:postcode":"5162",
    "sg:province":"SA",
    "sg:tags":[
        "accountant",
        "auditor"
    ],
    "wof:name":"Andrew Rushworth- Chartered Accountant",
    "wof:placetype":"venue"
},
  "geometry": {"coordinates":[138.523727417,-35.124370575],"type":"Point"}
}