{
  "type": "Feature",
  "properties": {
    "iso:country":"AU",
    "sg:address":"25a Bakers Rd",
    "sg:city":"Church Point",
    "sg:classifiers":[
        {
            "category":"Professional",
            "subcategory":"Employment Agencies",
            "type":"Services"
        }
    ],
    "sg:phone":"+61 2 9979 5999",
    "sg:postcode":"2105",
    "sg:province":"NSW",
    "wof:name":"Teams Recruitment Service Pty Ltd",
    "wof:placetype":"venue"
},
  "geometry": {"coordinates":[151.286621,-33.651596],"type":"Point"}
}