{
  "type": "Feature",
  "properties": {
    "addr:full":"Cnr Mc Cullough & Romulus Sts Robertson QLD 4109",
    "addr:postcode":"4109",
    "addr:street":"Cnr Mc",
    "iso:country":"AU",
    "sg:address":"Cnr Mc Cullough & Romulus Sts",
    "sg:city":"Robertson",
    "sg:classifiers":[
        {
            "category":"Social Services",
            "subcategory":"Retirement Home",
            "type":"Services"
        }
    ],
    "sg:phone":"+61 7 3345 9143",
    "sg:postcode":"4109",
    "sg:province":"QLD",
    "sg:tags":[
        "village"
    ],
    "wof:name":"Brookland Retirement Village",
    "wof:placetype":"venue"
},
  "geometry": {"coordinates":[153.05523681599999,-27.5673522949],"type":"Point"}
}