{
  "type": "Feature",
  "properties": {
    "addr:full":"Shop 1 Charlestown Square 30 Pearson St Charlestown NSW 2290",
    "addr:housenumber":"shop 1;30",
    "addr:postcode":"2290",
    "addr:street":"Charlestown Square;Pearson St",
    "iso:country":"AU",
    "sg:address":"Shop 1 Charlestown Square 30 Pearson St",
    "sg:city":"Charlestown",
    "sg:classifiers":[
        {
            "category":"Shopping",
            "subcategory":"Computers & Home Electronics",
            "type":"Retail Goods"
        }
    ],
    "sg:phone":"+61 2 4943 0651",
    "sg:postcode":"2290",
    "sg:province":"NSW",
    "sg:tags":[
        "equipment",
        "part",
        "electronic"
    ],
    "wof:name":"Tandy",
    "wof:placetype":"venue"
},
  "geometry": {"coordinates":[151.685821533,-32.954875946],"type":"Point"}
}