{
  "type": "Feature",
  "properties": {
    "addr:full":"354 Pacific Hwy Hexham NSW 2322",
    "addr:housenumber":"354",
    "addr:postcode":"2322",
    "addr:street":"Pacific Hwy",
    "iso:country":"AU",
    "sg:address":"354 Pacific Hwy",
    "sg:city":"Hexham",
    "sg:classifiers":[
        {
            "category":"Home & Garden",
            "subcategory":"Mobile Homes",
            "type":"Retail Goods"
        }
    ],
    "sg:phone":"+61 2 4964 8888",
    "sg:postcode":"2322",
    "sg:province":"NSW",
    "sg:tags":[
        "motor",
        "campervans"
    ],
    "wof:name":"Parravans Caravan World",
    "wof:placetype":"venue"
},
  "geometry": {"coordinates":[151.72354125999999,-32.7926177979],"type":"Point"}
}