{
  "type": "Feature",
  "properties": {
    "iso:country":"AU",
    "sg:address":"12 Diamond St",
    "sg:city":"Cooroy",
    "sg:classifiers":[
        {
            "category":"Social Services",
            "subcategory":"Child Care",
            "type":"Services"
        }
    ],
    "sg:phone":"+61 7 5447 6042",
    "sg:postcode":"4563",
    "sg:province":"QLD",
    "sg:tags":[
        "breeding",
        "artificial"
    ],
    "wof:name":"Cooroora Veterinary Surgery",
    "wof:placetype":"venue"
},
  "geometry": {"coordinates":[152.91290283199999,-26.4168663025],"type":"Point"}
}