{
  "type": "Feature",
  "properties": {
    "iso:country":"AU",
    "sg:address":"145 Rooke St",
    "sg:city":"Devonport",
    "sg:classifiers":[
        {
            "category":"Cafe",
            "type":"Food & Drink"
        }
    ],
    "sg:phone":"+61 3 6423 5373",
    "sg:postcode":"7310",
    "sg:province":"TAS",
    "wof:name":"Peelz Courthouse Cafe",
    "wof:placetype":"venue"
},
  "geometry": {"coordinates":[146.36091613799999,-41.1774520874],"type":"Point"}
}