{
  "type": "Feature",
  "properties": {
    "addr:full":"102 Albert St Geelong West VIC 3218",
    "addr:housenumber":"102",
    "addr:postcode":"3218",
    "addr:street":"Albert St",
    "iso:country":"AU",
    "sg:address":"102 Albert St",
    "sg:city":"Geelong West",
    "sg:classifiers":[
        {
            "category":"Professional",
            "subcategory":"Business Services",
            "type":"Services"
        }
    ],
    "sg:phone":"+61 3 5229 8750",
    "sg:postcode":"3218",
    "sg:province":"VIC",
    "sg:tags":[
        "drafting"
    ],
    "wof:name":"Elva Johnsson",
    "wof:placetype":"venue"
},
  "geometry": {"coordinates":[144.33926391599999,-38.1395225525],"type":"Point"}
}