{
  "type": "Feature",
  "properties": {
    "iso:country":"AU",
    "sg:address":"141 Sturt St",
    "sg:city":"Townsville",
    "sg:classifiers":[
        {
            "category":"Health Services",
            "subcategory":"Health Practitioner",
            "type":"Services"
        }
    ],
    "sg:phone":"+61 428 242 205",
    "sg:postcode":"4810",
    "sg:province":"QLD",
    "sg:tags":[
        "psychologist"
    ],
    "wof:name":"Davey Glen",
    "wof:placetype":"venue"
},
  "geometry": {"coordinates":[146.814117,-19.261494],"type":"Point"}
}