{
  "type": "Feature",
  "properties": {
    "iso:country":"AU",
    "sg:address":"32 Solomon St",
    "sg:city":"Mosman Park",
    "sg:classifiers":[
        {
            "category":"Banks & Credit Unions",
            "subcategory":"Investment Brokerage",
            "type":"Services"
        }
    ],
    "sg:phone":"+61 8 9385 3282",
    "sg:postcode":"6012",
    "sg:province":"WA",
    "sg:tags":[
        "course",
        "designer",
        "golf"
    ],
    "wof:name":"Coate Michael Golf Design",
    "wof:placetype":"venue"
},
  "geometry": {"coordinates":[115.763511658,-32.0085792542],"type":"Point"}
}