{
  "type": "Feature",
  "properties": {
    "addr:full":"62 Avenue Rd Mosman NSW 2088",
    "addr:housenumber":"62",
    "addr:postcode":"2088",
    "addr:street":"Avenue Rd",
    "iso:country":"AU",
    "sg:address":"62 Avenue Rd",
    "sg:city":"Mosman",
    "sg:classifiers":[
        {
            "category":"Health Services",
            "subcategory":"Health Practitioner",
            "type":"Services"
        }
    ],
    "sg:phone":"+61 2 9969 4700",
    "sg:postcode":"2088",
    "sg:province":"NSW",
    "sg:tags":[
        "naturopath"
    ],
    "wof:name":"Crane's Practitioner",
    "wof:placetype":"venue"
},
  "geometry": {"coordinates":[151.238723755,-33.8316955566],"type":"Point"}
}