{
  "type": "Feature",
  "properties": {
    "addr:full":"23 Through Rd Burwood VIC 3125",
    "addr:housenumber":"23",
    "addr:postcode":"3125",
    "addr:street":"Through Rd",
    "iso:country":"AU",
    "sg:address":"23 Through Rd",
    "sg:city":"Burwood",
    "sg:classifiers":[
        {
            "category":"Health Services",
            "subcategory":"Health Practitioner",
            "type":"Services"
        }
    ],
    "sg:phone":"+61 3 9889 3394",
    "sg:postcode":"3125",
    "sg:province":"VIC",
    "sg:tags":[
        "psychologist"
    ],
    "wof:name":"Banfai Anna",
    "wof:placetype":"venue"
},
  "geometry": {"coordinates":[145.08848571799999,-37.8472671509],"type":"Point"}
}