{
  "type": "Feature",
  "properties": {
    "addr:full":"Suite 23b, 255 Drummond St Carlton South VIC 3053",
    "addr:housenumber":"23b 255",
    "addr:postcode":"3053",
    "addr:street":"Drummond St",
    "iso:country":"AU",
    "sg:address":"Suite 23b, 255 Drummond St",
    "sg:city":"Carlton South",
    "sg:classifiers":[
        {
            "category":"Professional",
            "subcategory":"Secretarial Services",
            "type":"Services"
        }
    ],
    "sg:phone":"+61 3 9347 0599",
    "sg:postcode":"3053",
    "sg:province":"VIC",
    "sg:tags":[
        "typing"
    ],
    "wof:name":"Advanced Administration Services Pty Ltd",
    "wof:placetype":"venue"
},
  "geometry": {"coordinates":[144.968353272,-37.8002700806],"type":"Point"}
}