{
  "type": "Feature",
  "properties": {
    "addr:full":"7 Tozer Park Rd Gympie QLD 4570",
    "addr:housenumber":"7",
    "addr:postcode":"4570",
    "addr:street":"Tozer Park Rd",
    "iso:country":"AU",
    "sg:address":"7 Tozer Park Rd",
    "sg:city":"Gympie",
    "sg:classifiers":[
        {
            "category":"Shopping",
            "subcategory":"Stationery & Office Supplies",
            "type":"Retail Goods"
        }
    ],
    "sg:phone":"+61 7 5483 6155",
    "sg:postcode":"4570",
    "sg:province":"QLD",
    "sg:tags":[
        "packaging",
        "material"
    ],
    "wof:name":"Styro Products",
    "wof:placetype":"venue"
},
  "geometry": {"coordinates":[152.673339844,-26.1861572266],"type":"Point"}
}