{
  "type": "Feature",
  "properties": {
    "addr:full":"2/ 32 Macbeth St Braeside VIC 3195",
    "addr:housenumber":"/ 32",
    "addr:postcode":"3195",
    "addr:street":"Macbeth St",
    "iso:country":"AU",
    "sg:address":"2/ 32 Macbeth St",
    "sg:city":"Braeside",
    "sg:classifiers":[
        {
            "category":"Manufacturing",
            "subcategory":"Rubber & Plastics",
            "type":"Manufacturing & Wholesale Goods"
        }
    ],
    "sg:phone":"+61 3 9587 4723",
    "sg:postcode":"3195",
    "sg:province":"VIC",
    "sg:tags":[
        "moulders"
    ],
    "wof:name":"Spencer Plastics Pty Ltd",
    "wof:placetype":"venue"
},
  "geometry": {"coordinates":[145.11219787600001,-38.0033721924],"type":"Point"}
}