{
  "type": "Feature",
  "properties": {
    "addr:full":"41 Epsom Ave Ascot WA 6104",
    "addr:housenumber":"41",
    "addr:postcode":"6104",
    "addr:street":"Epsom Ave",
    "iso:country":"AU",
    "sg:address":"41 Epsom Ave",
    "sg:city":"Ascot",
    "sg:classifiers":[
        {
            "category":"Professional",
            "type":"Services"
        }
    ],
    "sg:phone":"+61 417 177 541",
    "sg:postcode":"6104",
    "sg:province":"WA",
    "sg:tags":[
        "auctioneer"
    ],
    "wof:name":"Statewide Auctions WA Pty Ltd",
    "wof:placetype":"venue"
},
  "geometry": {"coordinates":[115.931869507,-31.9356937408],"type":"Point"}
}