{
  "type": "Feature",
  "properties": {
    "addr:full":"31 West Melton Dr Melton VIC 3337",
    "addr:housenumber":"31",
    "addr:postcode":"3337",
    "addr:street":"West Melton Dr",
    "iso:country":"AU",
    "sg:address":"31 West Melton Dr",
    "sg:city":"Melton",
    "sg:classifiers":[
        {
            "category":"Wholesale",
            "subcategory":"Auto Parts",
            "type":"Manufacturing & Wholesale Goods"
        }
    ],
    "sg:phone":"+61 1300 762 628",
    "sg:postcode":"3337",
    "sg:province":"VIC",
    "sg:tags":[
        "recyclers"
    ],
    "wof:name":"Auto Smart Car Recyclers",
    "wof:placetype":"venue"
},
  "geometry": {"coordinates":[144.58189400000001,-37.683289],"type":"Point"}
}