{
  "type": "Feature",
  "properties": {
    "addr:full":"31 Westminster St Oakleigh VIC 3166",
    "addr:housenumber":"31",
    "addr:postcode":"3166",
    "addr:street":"Westminster St",
    "iso:country":"AU",
    "sg:address":"31 Westminster St",
    "sg:city":"Oakleigh",
    "sg:classifiers":[
        {
            "category":"Professional",
            "subcategory":"Engineering",
            "type":"Services"
        }
    ],
    "sg:phone":"+61 3 9564 7193",
    "sg:postcode":"3166",
    "sg:province":"VIC",
    "sg:tags":[
        "consulting",
        "engineer"
    ],
    "wof:name":"TouchLink Engineering",
    "wof:placetype":"venue"
},
  "geometry": {"coordinates":[145.09527587900001,-37.901889801],"type":"Point"}
}