{
  "type": "Feature",
  "properties": {
    "addr:full":"Unit 1 210 Grange Rd Flinders Park SA 5025",
    "addr:housenumber":"210",
    "addr:postcode":"5025",
    "addr:street":"Grange Rd",
    "iso:country":"AU",
    "sg:address":"Unit 1 210 Grange Rd",
    "sg:city":"Flinders Park",
    "sg:classifiers":[
        {
            "category":"Building & Trades",
            "subcategory":"Construction",
            "type":"Services"
        }
    ],
    "sg:phone":"+61 8 8354 4611",
    "sg:postcode":"5025",
    "sg:province":"SA",
    "sg:tags":[
        "contractor"
    ],
    "wof:name":"Fusco Building Co. Pty Ltd",
    "wof:placetype":"venue"
},
  "geometry": {"coordinates":[138.54411315900001,-34.9050254822],"type":"Point"}
}