{
  "type": "Feature",
  "properties": {
    "addr:full":"39 Wellington St Riverstone NSW 2765",
    "addr:housenumber":"39",
    "addr:postcode":"2765",
    "addr:street":"Wellington St",
    "iso:country":"AU",
    "sg:address":"39 Wellington St",
    "sg:city":"Riverstone",
    "sg:classifiers":[
        {
            "category":"Shopping",
            "subcategory":"Computers & Home Electronics",
            "type":"Retail Goods"
        }
    ],
    "sg:phone":"+61 2 9627 2100",
    "sg:postcode":"2765",
    "sg:province":"NSW",
    "sg:tags":[
        "equipment",
        "supply"
    ],
    "wof:name":"Copycoat Rollers Pty Ltd",
    "wof:placetype":"venue"
},
  "geometry": {"coordinates":[150.859939575,-33.6665458679],"type":"Point"}
}