{
  "type": "Feature",
  "properties": {
    "iso:country":"AU",
    "sg:address":"17 Arthurson St",
    "sg:city":"Mt Waverley",
    "sg:classifiers":[
        {
            "category":"Health Services",
            "subcategory":"Dentist",
            "type":"Services"
        }
    ],
    "sg:phone":"+61 3 9807 1741",
    "sg:postcode":"3149",
    "sg:province":"VIC",
    "wof:name":"Walpole Tom D",
    "wof:placetype":"venue"
},
  "geometry": {"coordinates":[145.126342773,-37.8760566711],"type":"Point"}
}