{
  "type": "Feature",
  "properties": {
    "addr:full":"14 Lakewood Drv Merimbula NSW 2548",
    "addr:housenumber":"14",
    "addr:postcode":"2548",
    "addr:street":"Lakewood Drv",
    "iso:country":"AU",
    "sg:address":"14 Lakewood Drv",
    "sg:city":"Merimbula",
    "sg:classifiers":[
        {
            "category":"Building & Trades",
            "subcategory":"Construction",
            "type":"Services"
        }
    ],
    "sg:phone":"+61 2 6495 4660",
    "sg:postcode":"2548",
    "sg:province":"NSW",
    "sg:tags":[
        "plasterboard",
        "plasterer",
        "fixer"
    ],
    "wof:name":"D & M Westcott",
    "wof:placetype":"venue"
},
  "geometry": {"coordinates":[149.896392822,-36.8912887573],"type":"Point"}
}