{
  "type": "Feature",
  "properties": {
    "addr:full":"24 Steane St Bendigo VIC 3550",
    "addr:housenumber":"24",
    "addr:postcode":"3550",
    "addr:street":"Steane St",
    "iso:country":"AU",
    "sg:address":"24 Steane St",
    "sg:city":"Bendigo",
    "sg:classifiers":[
        {
            "category":"Health Services",
            "subcategory":"Doctor",
            "type":"Services"
        }
    ],
    "sg:phone":"+61 3 5443 6201",
    "sg:postcode":"3550",
    "sg:province":"VIC",
    "sg:tags":[
        "occupational",
        "safety"
    ],
    "wof:name":"Brown David W & Associates",
    "wof:placetype":"venue"
},
  "geometry": {"coordinates":[144.301635742,-36.7608108521],"type":"Point"}
}