{
  "type": "Feature",
  "properties": {
    "addr:full":"Northbridge Marina Widgiewa Rd Northbridge NSW 2063",
    "addr:postcode":"2063",
    "addr:street":"Widgiewa Rd",
    "iso:country":"AU",
    "sg:address":"Northbridge Marina Widgiewa Rd",
    "sg:city":"Northbridge",
    "sg:classifiers":[
        {
            "category":"Train Station",
            "subcategory":"Rail",
            "type":"Transportation"
        }
    ],
    "sg:phone":"+61 2 9958 0433",
    "sg:postcode":"2063",
    "sg:province":"NSW",
    "sg:tags":[
        "marine",
        "engineer"
    ],
    "wof:name":"National Marine Services",
    "wof:placetype":"venue"
},
  "geometry": {"coordinates":[151.22140502900001,-33.8068313599],"type":"Point"}
}