{
  "type": "Feature",
  "properties": {
    "iso:country":"AU",
    "sg:address":"PO Box 11",
    "sg:city":"Harrisville",
    "sg:classifiers":[
        {
            "category":"Farming",
            "subcategory":"Farm & Veterinary Services",
            "type":"Manufacturing & Wholesale Goods"
        }
    ],
    "sg:phone":"+61 7 5467 1076",
    "sg:postcode":"4307",
    "sg:province":"QLD",
    "sg:tags":[
        "irrigation",
        "reticulation",
        "system"
    ],
    "wof:name":"Rain Bird Australia",
    "wof:placetype":"venue"
},
  "geometry": {"coordinates":[152.67303466800001,-27.8121490479],"type":"Point"}
}