{
  "type": "Feature",
  "properties": {
    "addr:full":"416 Wilson St Albury NSW 2640",
    "addr:housenumber":"416",
    "addr:postcode":"2640",
    "addr:street":"Wilson St",
    "iso:country":"AU",
    "sg:address":"416 Wilson St",
    "sg:city":"Albury",
    "sg:classifiers":[
        {
            "category":"Autos & Motor Vehicles",
            "subcategory":"Auto Supplies",
            "type":"Retail Goods"
        }
    ],
    "sg:phone":"+61 2 6041 3041",
    "sg:postcode":"2640",
    "sg:province":"NSW",
    "sg:tags":[
        "accessory"
    ],
    "wof:name":"Hopea Vinyl Services P/L",
    "wof:placetype":"venue"
},
  "geometry": {"coordinates":[146.9246521,-36.0774345398],"type":"Point"}
}