{
  "type": "Feature",
  "properties": {
    "addr:full":"124 Langridge St Collingwood VIC 3066",
    "addr:housenumber":"124",
    "addr:postcode":"3066",
    "addr:street":"Langridge St",
    "iso:country":"AU",
    "sg:address":"124 Langridge St",
    "sg:city":"Collingwood",
    "sg:classifiers":[
        {
            "category":"Health Services",
            "subcategory":"Health Practitioner",
            "type":"Services"
        }
    ],
    "sg:phone":"+61 3 9486 0070",
    "sg:postcode":"3066",
    "sg:province":"VIC",
    "sg:tags":[
        "naturopath"
    ],
    "wof:name":"Ondine Spitzer",
    "wof:placetype":"venue"
},
  "geometry": {"coordinates":[144.989181519,-37.8067626953],"type":"Point"}
}