{
  "type": "Feature",
  "properties": {
    "addr:full":"Lvl 1/ 62 Little Malop St Geelong VIC 3220",
    "addr:housenumber":"/ 62",
    "addr:postcode":"3220",
    "addr:street":"Little Malop St",
    "iso:country":"AU",
    "sg:address":"Lvl 1/ 62 Little Malop St",
    "sg:city":"Geelong",
    "sg:classifiers":[
        {
            "category":"Professional",
            "subcategory":"Accounting & Tax Preparation",
            "type":"Services"
        }
    ],
    "sg:phone":"+61 3 5222 1569",
    "sg:postcode":"3220",
    "sg:province":"VIC",
    "sg:tags":[
        "accountant",
        "auditor"
    ],
    "wof:name":"Symes Business Consulting",
    "wof:placetype":"venue"
},
  "geometry": {"coordinates":[144.35835299999999,-38.147865],"type":"Point"}
}