{
  "type": "Feature",
  "properties": {
    "iso:country":"AU",
    "sg:address":"14 Moani St",
    "sg:city":"Eleebana",
    "sg:classifiers":[
        {
            "category":"Professional",
            "subcategory":"Engineering",
            "type":"Services"
        }
    ],
    "sg:phone":"+61 2 4946 7791",
    "sg:postcode":"2282",
    "sg:province":"NSW",
    "sg:tags":[
        "consulting",
        "engineer"
    ],
    "wof:name":"Manufacturing Resources",
    "wof:placetype":"venue"
},
  "geometry": {"coordinates":[151.63905334500001,-32.9959182739],"type":"Point"}
}