{
  "type": "Feature",
  "properties": {
    "iso:country":"AU",
    "sg:address":"PO Box 474",
    "sg:city":"Mowbray",
    "sg:classifiers":[
        {
            "category":"Shopping",
            "subcategory":"Computers & Home Electronics",
            "type":"Retail Goods"
        }
    ],
    "sg:phone":"+61 409 025 116",
    "sg:postcode":"7248",
    "sg:province":"TAS",
    "sg:tags":[
        "equipment",
        "supply"
    ],
    "wof:name":"TAZ PC Bits",
    "wof:placetype":"venue"
},
  "geometry": {"coordinates":[147.13265991200001,-41.4055099487],"type":"Point"}
}