{
  "type": "Feature",
  "properties": {
    "addr:full":"Unt 1/ 29 Carey St Pinjarra WA 6208",
    "addr:housenumber":"29",
    "addr:postcode":"6208",
    "addr:street":"Carey St",
    "iso:country":"AU",
    "sg:address":"Unt 1/ 29 Carey St",
    "sg:city":"Pinjarra",
    "sg:classifiers":[
        {
            "category":"Building & Trades",
            "subcategory":"Cleaning & Sanitation",
            "type":"Services"
        }
    ],
    "sg:phone":"+61 410 212 455",
    "sg:postcode":"6208",
    "sg:province":"WA",
    "sg:tags":[
        "chemical",
        "pressure",
        "steam",
        "contractor"
    ],
    "wof:name":"Pressure Blasting Service",
    "wof:placetype":"venue"
},
  "geometry": {"coordinates":[115.86657,-32.629391],"type":"Point"}
}