{
  "type": "Feature",
  "properties": {
    "addr:full":"16-18 Windsor Rd Croydon VIC 3136",
    "addr:housenumber":"16-18",
    "addr:postcode":"3136",
    "addr:street":"Windsor Rd",
    "iso:country":"AU",
    "sg:address":"16-18 Windsor Rd",
    "sg:city":"Croydon",
    "sg:classifiers":[
        {
            "category":"Building & Trades",
            "subcategory":"Construction",
            "type":"Services"
        }
    ],
    "sg:phone":"+61 3 9724 9111",
    "sg:postcode":"3136",
    "sg:province":"VIC",
    "sg:tags":[
        "window",
        "tinting"
    ],
    "wof:name":"All About Window Tinting",
    "wof:placetype":"venue"
},
  "geometry": {"coordinates":[145.285690308,-37.7946815491],"type":"Point"}
}