{
  "type": "Feature",
  "properties": {
    "addr:full":"53 York St Gosford East NSW 2250",
    "addr:housenumber":"53",
    "addr:postcode":"2250",
    "addr:street":"York St",
    "iso:country":"AU",
    "sg:address":"53 York St",
    "sg:city":"Gosford East",
    "sg:classifiers":[
        {
            "category":"Health Services",
            "subcategory":"Doctor",
            "type":"Services"
        }
    ],
    "sg:phone":"+61 2 4325 5660",
    "sg:postcode":"2250",
    "sg:province":"NSW",
    "sg:tags":[
        "medical",
        "practitioner"
    ],
    "wof:name":"Central Coast Skin Cancer Clinic",
    "wof:placetype":"venue"
},
  "geometry": {"coordinates":[151.34909057600001,-33.4365768433],"type":"Point"}
}