{
  "type": "Feature",
  "properties": {
    "iso:country":"AU",
    "sg:address":"162 Enterprise Drv",
    "sg:city":"Beaudesert",
    "sg:classifiers":[
        {
            "category":"Retail",
            "subcategory":"Auto Repair",
            "type":"Services"
        }
    ],
    "sg:phone":"+61 7 5541 4540",
    "sg:postcode":"4285",
    "sg:province":"QLD",
    "sg:tags":[
        "repairer",
        "motor",
        "engineer"
    ],
    "wof:name":"Gerard Wilkie Mechanical Repairs",
    "wof:placetype":"venue"
},
  "geometry": {"coordinates":[152.991943,-27.967625],"type":"Point"}
}