{
  "type": "Feature",
  "properties": {
    "addr:full":"4c Cromwell St Burwood VIC 3125",
    "addr:housenumber":"4c",
    "addr:postcode":"3125",
    "addr:street":"Cromwell St",
    "iso:country":"AU",
    "sg:address":"4c Cromwell St",
    "sg:city":"Burwood",
    "sg:classifiers":[
        {
            "category":"Fast Food",
            "type":"Food & Drink"
        }
    ],
    "sg:phone":"+61 3 9808 7001",
    "sg:postcode":"3125",
    "sg:province":"VIC",
    "sg:tags":[
        "away",
        "take"
    ],
    "wof:name":"Burwood Lunch Box",
    "wof:placetype":"venue"
},
  "geometry": {"coordinates":[145.10458374000001,-37.8510055542],"type":"Point"}
}