{
  "type": "Feature",
  "properties": {
    "iso:country":"AU",
    "sg:address":"1 Dominion Pl",
    "sg:city":"Queanbeyan",
    "sg:classifiers":[
        {
            "category":"Autos & Motor Vehicles",
            "subcategory":"Auto Supplies",
            "type":"Retail Goods"
        }
    ],
    "sg:phone":"+61 2 6299 3996",
    "sg:postcode":"2620",
    "sg:province":"ACT",
    "sg:tags":[
        "oil",
        "spirit"
    ],
    "wof:name":"Valvoline (Aust) Pty Ltd",
    "wof:placetype":"venue"
},
  "geometry": {"coordinates":[149.249908447,-35.340927124],"type":"Point"}
}