{
  "type": "Feature",
  "properties": {
    "addr:full":"Suite 2, 15 Dumaresq St Campbelltown NSW 2560",
    "addr:housenumber":"15",
    "addr:postcode":"2560",
    "addr:street":"Dumaresq St",
    "iso:country":"AU",
    "sg:address":"Suite 2, 15 Dumaresq St",
    "sg:city":"Campbelltown",
    "sg:classifiers":[
        {
            "category":"Education",
            "subcategory":"Special Training",
            "type":"Public Place"
        }
    ],
    "sg:phone":"+61 2 4627 7707",
    "sg:postcode":"2560",
    "sg:province":"NSW",
    "sg:tags":[
        "tuition-educational"
    ],
    "wof:name":"&#039;A&#039; 4 Maths Learning Centre (Campbelltown)",
    "wof:placetype":"venue"
},
  "geometry": {"coordinates":[150.81199645999999,-34.0670204163],"type":"Point"}
}