{
  "type": "Feature",
  "properties": {
    "iso:country":"AU",
    "sg:address":"40 Storie St",
    "sg:city":"Clontarf",
    "sg:classifiers":[
        {
            "category":"Retail",
            "subcategory":"Storage",
            "type":"Services"
        }
    ],
    "sg:phone":"+61 412 993 841",
    "sg:postcode":"4019",
    "sg:province":"QLD",
    "wof:name":"Clontarf & Kippa Ring Self Storage",
    "wof:placetype":"venue"
},
  "geometry": {"coordinates":[153.083984375,-27.2353668213],"type":"Point"}
}