{
  "type": "Feature",
  "properties": {
    "addr:full":"Thompson St Hamilton VIC 3300",
    "addr:postcode":"3300",
    "addr:street":"Thompson St",
    "iso:country":"AU",
    "sg:address":"Thompson St",
    "sg:city":"Hamilton",
    "sg:classifiers":[
        {
            "category":"Health Services",
            "subcategory":"Dentist",
            "type":"Services"
        }
    ],
    "sg:phone":"+61 3 5572 1667",
    "sg:postcode":"3300",
    "sg:province":"VIC",
    "wof:name":"Tripovich PJ",
    "wof:placetype":"venue"
},
  "geometry": {"coordinates":[142.02218627900001,-37.7427177429],"type":"Point"}
}