{
  "type": "Feature",
  "properties": {
    "addr:full":"U3/ 2 Parsons St Alice Springs NT 0870",
    "addr:housenumber":"2",
    "addr:postcode":"nt 0870",
    "addr:street":"U3 /;Parsons St",
    "iso:country":"AU",
    "sg:address":"U3/ 2 Parsons St",
    "sg:city":"Alice Springs",
    "sg:classifiers":[
        {
            "category":"Personal",
            "subcategory":"Beauty Salon",
            "type":"Services"
        }
    ],
    "sg:phone":"+61 8 8953 2333",
    "sg:postcode":"0870",
    "sg:province":"NT",
    "wof:name":"Jenny Jane's Beauty & Skincare",
    "wof:placetype":"venue"
},
  "geometry": {"coordinates":[133.879516602,-23.6972293854],"type":"Point"}
}