{
  "type": "Feature",
  "properties": {
    "addr:full":"Ramsay Crt Kangaroo Flat VIC 3555",
    "addr:postcode":"3555",
    "addr:street":"Ramsay Crt",
    "iso:country":"AU",
    "sg:address":"Ramsay Crt",
    "sg:city":"Kangaroo Flat",
    "sg:classifiers":[
        {
            "category":"Home & Garden",
            "subcategory":"Building Materials",
            "type":"Retail Goods"
        }
    ],
    "sg:phone":"+61 3 5447 8455",
    "sg:postcode":"3555",
    "sg:province":"VIC",
    "sg:tags":[
        "roofing"
    ],
    "wof:name":"Stramit Industries",
    "wof:placetype":"venue"
},
  "geometry": {"coordinates":[144.23150634800001,-36.7943344116],"type":"Point"}
}