{
  "type": "Feature",
  "properties": {
    "addr:full":"Shop 3 /25 Hastings St Noosa Heads QLD 4567",
    "addr:housenumber":"shop 3 / 25",
    "addr:postcode":"4567",
    "addr:street":"Hastings St",
    "iso:country":"AU",
    "sg:address":"Shop 3 /25 Hastings St",
    "sg:city":"Noosa Heads",
    "sg:classifiers":[
        {
            "category":"Shopping",
            "subcategory":"Baby Store",
            "type":"Retail Goods"
        }
    ],
    "sg:phone":"+61 7 5474 5577",
    "sg:postcode":"4567",
    "sg:province":"QLD",
    "sg:tags":[
        "children's",
        "wear"
    ],
    "wof:name":"Noosa Juniors",
    "wof:placetype":"venue"
},
  "geometry": {"coordinates":[153.087356567,-26.3860454559],"type":"Point"}
}