{
  "type": "Feature",
  "properties": {
    "addr:full":"38 Vinnicombe Drv Canning Vale WA 6155",
    "addr:housenumber":"38",
    "addr:postcode":"6155",
    "addr:street":"Vinnicombe Drv",
    "iso:country":"AU",
    "sg:address":"38 Vinnicombe Drv",
    "sg:city":"Canning Vale",
    "sg:classifiers":[
        {
            "category":"Home & Garden",
            "subcategory":"Hardware",
            "type":"Retail Goods"
        }
    ],
    "sg:phone":"+61 8 9455 3588",
    "sg:postcode":"6155",
    "sg:province":"WA",
    "sg:tags":[
        "plumber",
        "supply"
    ],
    "wof:name":"Tradelink Plumbing Centres",
    "wof:placetype":"venue"
},
  "geometry": {"coordinates":[115.916107,-32.058907],"type":"Point"}
}