{
  "type": "Feature",
  "properties": {
    "addr:full":"723- 731 Springvale Rd Keysborough VIC 3173",
    "addr:housenumber":"731",
    "addr:postcode":"3173",
    "addr:street":"Springvale Rd",
    "iso:country":"AU",
    "sg:address":"723- 731 Springvale Rd",
    "sg:city":"Keysborough",
    "sg:classifiers":[
        {
            "category":"Sports & Exercise",
            "subcategory":"Ski Resort",
            "type":"Entertainment"
        }
    ],
    "sg:phone":"+61 3 9798 3955",
    "sg:postcode":"3173",
    "sg:province":"VIC",
    "sg:tags":[
        "propelled",
        "jet"
    ],
    "wof:name":"Personal Watercraft World",
    "wof:placetype":"venue"
},
  "geometry": {"coordinates":[145.14596557600001,-37.9850196838],"type":"Point"}
}