{
  "type": "Feature",
  "properties": {
    "iso:country":"AU",
    "sg:address":"104 Elizabeth Drv",
    "sg:city":"Liverpool",
    "sg:classifiers":[
        {
            "category":"Autos & Motor Vehicles",
            "subcategory":"Fuel & Gas Station",
            "type":"Retail Goods"
        }
    ],
    "sg:phone":"+61 2 9602 3136",
    "sg:postcode":"2170",
    "sg:province":"NSW",
    "wof:name":"Tonys Petroleum",
    "wof:placetype":"venue"
},
  "geometry": {"coordinates":[150.91317749000001,-33.9182014465],"type":"Point"}
}