{
  "type": "Feature",
  "properties": {
    "addr:full":"30a Kerrigan St Fraser ACT 2615",
    "addr:housenumber":"30a",
    "addr:postcode":"2615",
    "addr:street":"Kerrigan St",
    "iso:country":"AU",
    "sg:address":"30a Kerrigan St",
    "sg:city":"Fraser",
    "sg:classifiers":[
        {
            "category":"Organizations",
            "subcategory":"Non-profit Organization",
            "type":"Services"
        }
    ],
    "sg:phone":"+61 2 6259 9555",
    "sg:postcode":"2615",
    "sg:province":"ACT",
    "sg:tags":[
        "support",
        "disability",
        "organisation"
    ],
    "wof:name":"CARERS ACT - FRASER HOUSE",
    "wof:placetype":"venue"
},
  "geometry": {"coordinates":[149.038375855,-35.193447113],"type":"Point"}
}