{
  "type": "Feature",
  "properties": {
    "addr:full":"Shopp 22, Ground Floor, Queen Victoria Building, G Sydney NSW 2000",
    "addr:housenumber":"22",
    "addr:postcode":"2000",
    "addr:street":"Shopp",
    "iso:country":"AU",
    "sg:address":"Shopp 22, Ground Floor, Queen Victoria Building, G",
    "sg:city":"Sydney",
    "sg:classifiers":[
        {
            "category":"Shopping",
            "subcategory":"Baby Store",
            "type":"Retail Goods"
        }
    ],
    "sg:phone":"+61 2 9267 6187",
    "sg:postcode":"2000",
    "sg:province":"NSW",
    "sg:tags":[
        "children's",
        "wear"
    ],
    "wof:name":"Oshkosh B&#039;Gosh",
    "wof:placetype":"venue"
},
  "geometry": {"coordinates":[151.206954956,-33.8691902161],"type":"Point"}
}