{
  "type": "Feature",
  "properties": {
    "addr:full":"Rear 124, James St Templestowe VIC 3106",
    "addr:housenumber":"124",
    "addr:postcode":"3106",
    "addr:street":"James St",
    "iso:country":"AU",
    "sg:address":"Rear 124, James St",
    "sg:city":"Templestowe",
    "sg:classifiers":[
        {
            "category":"Sports & Exercise",
            "subcategory":"Gym",
            "type":"Entertainment"
        }
    ],
    "sg:phone":"+61 3 9846 6559",
    "sg:postcode":"3106",
    "sg:province":"VIC",
    "sg:tags":[
        "personal",
        "trainer",
        "fitness"
    ],
    "wof:name":"Templestowe Train Station",
    "wof:placetype":"venue"
},
  "geometry": {"coordinates":[145.12924194300001,-37.756980896],"type":"Point"}
}