{
  "type": "Feature",
  "properties": {
    "addr:full":"Shop 3 & 4, 350 Bong Bong St Bowral NSW 2576",
    "addr:housenumber":"shop 3 & 4",
    "addr:postcode":"350;2576",
    "addr:street":"Bong St",
    "iso:country":"AU",
    "sg:address":"Shop 3 & 4, 350 Bong Bong St",
    "sg:city":"Bowral",
    "sg:classifiers":[
        {
            "category":"Health Services",
            "subcategory":"Optometrist",
            "type":"Services"
        }
    ],
    "sg:phone":"+61 2 4862 1190",
    "sg:postcode":"2576",
    "sg:province":"NSW",
    "wof:name":"Trevor Matley Optometrist",
    "wof:placetype":"venue"
},
  "geometry": {"coordinates":[150.417694092,-34.4804267883],"type":"Point"}
}