{
  "type": "Feature",
  "properties": {
    "addr:full":"25 Ringlands Rd Narooma NSW 2546",
    "addr:housenumber":"25",
    "addr:postcode":"2546",
    "addr:street":"Ringlands Rd",
    "iso:country":"AU",
    "sg:address":"25 Ringlands Rd",
    "sg:city":"Narooma",
    "sg:classifiers":[
        {
            "category":"Shopping",
            "subcategory":"Stationery & Office Supplies",
            "type":"Retail Goods"
        }
    ],
    "sg:phone":"+61 2 4476 1818",
    "sg:postcode":"2546",
    "sg:province":"NSW",
    "sg:tags":[
        "partition"
    ],
    "wof:name":"Wood Work Wonders",
    "wof:placetype":"venue"
},
  "geometry": {"coordinates":[150.10789489699999,-36.2307128906],"type":"Point"}
}