{
  "type": "Feature",
  "properties": {
    "addr:full":"129 Merrindale Drv Croydon South VIC 3136",
    "addr:housenumber":"129",
    "addr:postcode":"3136",
    "addr:street":"Merrindale Drv",
    "iso:country":"AU",
    "sg:address":"129 Merrindale Drv",
    "sg:city":"Croydon South",
    "sg:classifiers":[
        {
            "category":"Manufacturing",
            "subcategory":"Rubber & Plastics",
            "type":"Manufacturing & Wholesale Goods"
        }
    ],
    "sg:phone":"+61 3 9761 5757",
    "sg:postcode":"3136",
    "sg:province":"VIC",
    "sg:tags":[
        "moulders"
    ],
    "wof:name":"Technical Moulders Australia P/L",
    "wof:placetype":"venue"
},
  "geometry": {"coordinates":[145.28828430199999,-37.8132667542],"type":"Point"}
}