{
  "type": "Feature",
  "properties": {
    "addr:full":"173 Hillside Rd Avoca Beach NSW 2251",
    "addr:housenumber":"173",
    "addr:postcode":"2251",
    "addr:street":"Hillside Rd",
    "iso:country":"AU",
    "sg:address":"173 Hillside Rd",
    "sg:city":"Avoca Beach",
    "sg:classifiers":[
        {
            "category":"Professional",
            "subcategory":"Accounting & Tax Preparation",
            "type":"Services"
        }
    ],
    "sg:phone":"+61 2 4382 6918",
    "sg:postcode":"2251",
    "sg:province":"NSW",
    "sg:tags":[
        "accountant",
        "auditor"
    ],
    "wof:name":"George Boettiger",
    "wof:placetype":"venue"
},
  "geometry": {"coordinates":[151.42562866200001,-33.4639854431],"type":"Point"}
}