{
  "type": "Feature",
  "properties": {
    "addr:full":"10 Dalton St Jurien WA 6516",
    "addr:housenumber":"10",
    "addr:postcode":"6516",
    "addr:street":"Dalton St",
    "iso:country":"AU",
    "sg:address":"10 Dalton St",
    "sg:city":"Jurien",
    "sg:classifiers":[
        {
            "category":"Food & Beverages",
            "subcategory":"Specialty",
            "type":"Retail Goods"
        }
    ],
    "sg:phone":"+61 8 9652 1158",
    "sg:postcode":"6516",
    "sg:province":"WA",
    "sg:tags":[
        "ice",
        "supply"
    ],
    "wof:name":"Jurien Ice Supply",
    "wof:placetype":"venue"
},
  "geometry": {"coordinates":[115.04083300000001,-30.300224],"type":"Point"}
}