{
  "type": "Feature",
  "properties": {
    "iso:country":"AU",
    "sg:address":"135 Landrigan Rd",
    "sg:city":"Carisbrook",
    "sg:classifiers":[
        {
            "category":"Building & Trades",
            "subcategory":"Construction",
            "type":"Services"
        }
    ],
    "sg:phone":"+61 3 5464 2496",
    "sg:postcode":"3464",
    "sg:province":"VIC",
    "sg:tags":[
        "contractor"
    ],
    "wof:name":"Carisbrook Home Improvement Services",
    "wof:placetype":"venue"
},
  "geometry": {"coordinates":[143.80705261200001,-37.0638618469],"type":"Point"}
}