{
  "type": "Feature",
  "properties": {
    "iso:country":"AU",
    "sg:address":"22 Hethersett Rd",
    "sg:city":"Sassafras",
    "sg:classifiers":[
        {
            "category":"Professional",
            "subcategory":"Management & Consulting",
            "type":"Services"
        }
    ],
    "sg:phone":"+61 3 9755 1153",
    "sg:postcode":"3787",
    "sg:province":"VIC",
    "sg:tags":[
        "consultant"
    ],
    "wof:name":"Russell MacAndrew Consulting Pty Ltd",
    "wof:placetype":"venue"
},
  "geometry": {"coordinates":[145.347107,-37.869041],"type":"Point"}
}