{
  "type": "Feature",
  "properties": {
    "addr:full":"PO Box 5308 Erina Fair NSW 2250",
    "addr:postcode":"2250",
    "iso:country":"AU",
    "sg:address":"PO Box 5308",
    "sg:city":"Erina Fair",
    "sg:classifiers":[
        {
            "category":"Utilities",
            "subcategory":"Mobile Phone",
            "type":"Services"
        }
    ],
    "sg:phone":"+61 2 4365 5357",
    "sg:postcode":"2250",
    "sg:province":"NSW",
    "sg:tags":[
        "aviation",
        "consultant"
    ],
    "wof:name":"Baines Simmons Australasia Limited",
    "wof:placetype":"venue"
},
  "geometry": {"coordinates":[151.341720581,-33.4248847961],"type":"Point"}
}