{
  "type": "Feature",
  "properties": {
    "iso:country":"AU",
    "sg:address":"160 Union Rd",
    "sg:city":"Ascot Vale",
    "sg:classifiers":[
        {
            "category":"Manufacturing",
            "subcategory":"Metals",
            "type":"Manufacturing & Wholesale Goods"
        }
    ],
    "sg:phone":"+61 3 9370 3908",
    "sg:postcode":"3032",
    "sg:province":"VIC",
    "sg:tags":[
        "steel",
        "fabricator",
        "mfrs"
    ],
    "wof:name":"Multi Steel Fabrications",
    "wof:placetype":"venue"
},
  "geometry": {"coordinates":[144.915863,-37.775028],"type":"Point"}
}