{
  "type": "Feature",
  "properties": {
    "iso:country":"AU",
    "sg:address":"75 Mitchell St",
    "sg:city":"Bendigo",
    "sg:classifiers":[
        {
            "category":"Shopping",
            "subcategory":"Music",
            "type":"Retail Goods"
        }
    ],
    "sg:phone":"+61 3 5443 3299",
    "sg:postcode":"3550",
    "sg:province":"VIC",
    "sg:tags":[
        "instrument",
        "musical"
    ],
    "wof:name":"Easdens",
    "wof:placetype":"venue"
},
  "geometry": {"coordinates":[144.280853272,-36.7615509033],"type":"Point"}
}