{
  "type": "Feature",
  "properties": {
    "addr:full":"23 Robertson Rd Newport NSW 2106",
    "addr:housenumber":"23",
    "addr:postcode":"2106",
    "addr:street":"Robertson Rd",
    "iso:country":"AU",
    "sg:address":"23 Robertson Rd",
    "sg:city":"Newport",
    "sg:classifiers":[
        {
            "category":"Health Services",
            "subcategory":"Health Practitioner",
            "type":"Services"
        }
    ],
    "sg:phone":"+61 2 9997 4970",
    "sg:postcode":"2106",
    "sg:province":"NSW",
    "sg:tags":[
        "physiotherapist"
    ],
    "wof:name":"Robertson Road Physiotherapy",
    "wof:placetype":"venue"
},
  "geometry": {"coordinates":[151.318847656,-33.6541442871],"type":"Point"}
}