{
  "type": "Feature",
  "properties": {
    "iso:country":"AU",
    "sg:address":"15 Batman St",
    "sg:city":"West Melbourne",
    "sg:classifiers":[
        {
            "category":"Building & Trades",
            "subcategory":"Construction",
            "type":"Services"
        }
    ],
    "sg:phone":"+61 3 9320 4700",
    "sg:postcode":"3003",
    "sg:province":"VIC",
    "sg:tags":[
        "contractor"
    ],
    "wof:name":"Concrete Constructions (Victoria)",
    "wof:placetype":"venue"
},
  "geometry": {"coordinates":[144.952560425,-37.810585022],"type":"Point"}
}