{
  "type": "Feature",
  "properties": {
    "iso:country":"AU",
    "sg:address":"7B Lachlan Court, George St",
    "sg:city":"Windsor",
    "sg:classifiers":[
        {
            "category":"Personal",
            "subcategory":"Beauty Salon",
            "type":"Services"
        }
    ],
    "sg:phone":"+61 2 4587 8848",
    "sg:postcode":"2756",
    "sg:province":"NSW",
    "sg:tags":[
        "hairdresser"
    ],
    "wof:name":"Vivo I Do Hair",
    "wof:placetype":"venue"
},
  "geometry": {"coordinates":[150.81301879899999,-33.6125946045],"type":"Point"}
}