{
  "type": "Feature",
  "properties": {
    "iso:country":"AU",
    "sg:address":"34 Morgan St",
    "sg:city":"Rockingham",
    "sg:classifiers":[
        {
            "category":"Retail",
            "subcategory":"Auto Repair",
            "type":"Services"
        }
    ],
    "sg:phone":"+61 8 9527 1101",
    "sg:postcode":"6168",
    "sg:province":"WA",
    "sg:tags":[
        "repairer",
        "motor",
        "engineer"
    ],
    "wof:name":"D & M Waste Services",
    "wof:placetype":"venue"
},
  "geometry": {"coordinates":[115.757393,-32.275597],"type":"Point"}
}