{
  "type": "Feature",
  "properties": {
    "addr:full":"Shop 9, Gateway Shopping Village 230 Cranbourne Rd Langwarrin VIC 3910",
    "addr:housenumber":"shop 9;230",
    "addr:postcode":"3910",
    "addr:street":"Gateway;Cranbourne Rd",
    "iso:country":"AU",
    "sg:address":"Shop 9, Gateway Shopping Village 230 Cranbourne Rd",
    "sg:city":"Langwarrin",
    "sg:classifiers":[
        {
            "category":"Personal",
            "type":"Services"
        }
    ],
    "sg:phone":"+61 3 9775 8844",
    "sg:postcode":"3910",
    "sg:province":"VIC",
    "sg:tags":[
        "gift"
    ],
    "wof:name":"Bumble Bee Florist",
    "wof:placetype":"venue"
},
  "geometry": {"coordinates":[145.19543457,-38.1506347656],"type":"Point"}
}