{
  "type": "Feature",
  "properties": {
    "addr:full":"77 Burdett St Hornsby NSW 2077",
    "addr:housenumber":"77",
    "addr:postcode":"2077",
    "addr:street":"Burdett St",
    "iso:country":"AU",
    "sg:address":"77 Burdett St",
    "sg:city":"Hornsby",
    "sg:classifiers":[
        {
            "category":"Health Services",
            "subcategory":"Doctor",
            "type":"Services"
        }
    ],
    "sg:phone":"+61 2 9477 6288",
    "sg:postcode":"2077",
    "sg:province":"NSW",
    "sg:tags":[
        "medical",
        "practitioner"
    ],
    "wof:name":"Smart Denis W",
    "wof:placetype":"venue"
},
  "geometry": {"coordinates":[151.110031128,-33.7036819458],"type":"Point"}
}