{
  "type": "Feature",
  "properties": {
    "addr:full":"28- 30 Greenway Drv Tweed Heads South QLD 2486",
    "addr:housenumber":"30",
    "addr:postcode":"2486",
    "addr:street":"Greenway Drv",
    "iso:country":"AU",
    "sg:address":"28- 30 Greenway Drv",
    "sg:city":"Tweed Heads South",
    "sg:classifiers":[
        {
            "category":"Coffee & Tea",
            "type":"Food & Drink"
        }
    ],
    "sg:phone":"+61 7 5524 6969",
    "sg:postcode":"2486",
    "sg:province":"QLD",
    "sg:tags":[
        "kayak",
        "canoe"
    ],
    "wof:name":"Bunyips Great Outdoors Centre",
    "wof:placetype":"venue"
},
  "geometry": {"coordinates":[153.491744995,-28.213344574],"type":"Point"}
}