{
  "type": "Feature",
  "properties": {
    "iso:country":"AU",
    "sg:address":"118 O&#039;Mara Rd",
    "sg:city":"Toowoomba",
    "sg:classifiers":[
        {
            "category":"Retail",
            "subcategory":"Car Wash",
            "type":"Services"
        }
    ],
    "sg:phone":"+61 7 4630 4496",
    "sg:postcode":"4350",
    "sg:province":"QLD",
    "sg:tags":[
        "merchant",
        "oil",
        "refiner"
    ],
    "wof:name":"David Bateman Oil Recovery",
    "wof:placetype":"venue"
},
  "geometry": {"coordinates":[151.84608499999999,-27.536545],"type":"Point"}
}