{
  "type": "Feature",
  "properties": {
    "addr:full":"PO Box 9110 Bathurst NSW 2795",
    "addr:postcode":"2795",
    "iso:country":"AU",
    "sg:address":"PO Box 9110",
    "sg:city":"Bathurst",
    "sg:classifiers":[
        {
            "category":"Professional",
            "type":"Services"
        }
    ],
    "sg:phone":"+61 408 894 695",
    "sg:postcode":"2795",
    "sg:province":"NSW",
    "sg:tags":[
        "transport"
    ],
    "wof:name":"Brettski Transport",
    "wof:placetype":"venue"
},
  "geometry": {"coordinates":[149.55354309099999,-33.5437316895],"type":"Point"}
}