{
  "type": "Feature",
  "properties": {
    "iso:country":"AU",
    "sg:address":"1/ 69 Jonson St",
    "sg:city":"Byron Bay",
    "sg:classifiers":[
        {
            "category":"Arts & Performance",
            "subcategory":"Art Gallery",
            "type":"Entertainment"
        }
    ],
    "sg:phone":"+61 2 6680 7884",
    "sg:postcode":"2481",
    "sg:province":"NSW",
    "sg:tags":[
        "aboriginal",
        "craft"
    ],
    "wof:name":"Planet Corroborre",
    "wof:placetype":"venue"
},
  "geometry": {"coordinates":[153.61285400400001,-28.6481990814],"type":"Point"}
}