{
  "type": "Feature",
  "properties": {
    "iso:country":"AU",
    "sg:address":"316 Edward St",
    "sg:city":"Moree",
    "sg:classifiers":[
        {
            "category":"Building & Trades",
            "subcategory":"Construction",
            "type":"Services"
        }
    ],
    "sg:phone":"+61 427 011 346",
    "sg:postcode":"2400",
    "sg:province":"NSW",
    "sg:tags":[
        "plasterboard",
        "plasterer",
        "fixer"
    ],
    "wof:name":"Norrie Scott",
    "wof:placetype":"venue"
},
  "geometry": {"coordinates":[149.836135864,-29.473274231],"type":"Point"}
}