{
  "type": "Feature",
  "properties": {
    "addr:full":"203 Windsor St Richmond NSW 2753",
    "addr:housenumber":"203",
    "addr:postcode":"2753",
    "addr:street":"Windsor St",
    "iso:country":"AU",
    "sg:address":"203 Windsor St",
    "sg:city":"Richmond",
    "sg:classifiers":[
        {
            "category":"Health Services",
            "subcategory":"Optometrist",
            "type":"Services"
        }
    ],
    "sg:phone":"+61 2 4578 4924",
    "sg:postcode":"2753",
    "sg:province":"NSW",
    "wof:name":"A. Nassif Optometrist",
    "wof:placetype":"venue"
},
  "geometry": {"coordinates":[150.75177001899999,-33.5970535278],"type":"Point"}
}