{
  "type": "Feature",
  "properties": {
    "addr:full":"58A Derby St Kingswood NSW 2747",
    "addr:housenumber":"58a",
    "addr:postcode":"2747",
    "addr:street":"Derby St",
    "iso:country":"AU",
    "sg:address":"58A Derby St",
    "sg:city":"Kingswood",
    "sg:classifiers":[
        {
            "category":"Health Services",
            "subcategory":"Doctor",
            "type":"Services"
        }
    ],
    "sg:phone":"+61 2 4732 4557",
    "sg:postcode":"2747",
    "sg:province":"NSW",
    "sg:tags":[
        "medical",
        "practitioner"
    ],
    "wof:name":"Kuo Warren Dr",
    "wof:placetype":"venue"
},
  "geometry": {"coordinates":[150.71333313,-33.7612724304],"type":"Point"}
}