{
  "type": "Feature",
  "properties": {
    "iso:country":"AU",
    "sg:address":"20 Taminga St",
    "sg:city":"Regency Park",
    "sg:classifiers":[
        {
            "category":"Utilities",
            "subcategory":"Water",
            "type":"Services"
        }
    ],
    "sg:phone":"+61 1800 805 372",
    "sg:postcode":"5010",
    "sg:province":"SA",
    "sg:tags":[
        "ventilating",
        "hot",
        "heating",
        "engineer"
    ],
    "wof:name":"Raychem Heat Tracing Systems",
    "wof:placetype":"venue"
},
  "geometry": {"coordinates":[138.571899414,-34.8599472046],"type":"Point"}
}