{
  "type": "Feature",
  "properties": {
    "iso:country":"AU",
    "sg:address":"Tanunda St",
    "sg:city":"Tom Price",
    "sg:classifiers":[
        {
            "category":"Education",
            "subcategory":"School",
            "type":"Public Place"
        }
    ],
    "sg:phone":"+61 8 9189 1299",
    "sg:postcode":"6751",
    "sg:province":"WA",
    "sg:tags":[
        "state",
        "except",
        "nsw"
    ],
    "wof:name":"North Tom Price Primary School",
    "wof:placetype":"venue"
},
  "geometry": {"coordinates":[117.785148621,-22.6829833984],"type":"Point"}
}