{
  "type": "Feature",
  "properties": {
    "iso:country":"AU",
    "sg:address":"Shop 5086, Elizabeth City Centre Cnr Phillip Hwy",
    "sg:city":"& Elizabeth Way Elizabeth",
    "sg:classifiers":[
        {
            "category":"Personal",
            "subcategory":"Beauty Salon",
            "type":"Services"
        }
    ],
    "sg:phone":"+61 8 8252 7465",
    "sg:postcode":"5112",
    "sg:province":"SA",
    "sg:tags":[
        "hairdresser"
    ],
    "wof:name":"Hairhouse Warehouse",
    "wof:placetype":"venue"
},
  "geometry": {"coordinates":[138.66896057100001,-34.7217102051],"type":"Point"}
}