{
  "type": "Feature",
  "properties": {
    "addr:full":"28 Alice St Bundaberg QLD 4670",
    "addr:housenumber":"28",
    "addr:postcode":"4670",
    "addr:street":"Alice St",
    "iso:country":"AU",
    "sg:address":"28 Alice St",
    "sg:city":"Bundaberg",
    "sg:classifiers":[
        {
            "category":"Professional",
            "subcategory":"Detective & Security Services",
            "type":"Services"
        }
    ],
    "sg:phone":"+61 7 4153 5427",
    "sg:postcode":"4670",
    "sg:province":"QLD",
    "sg:tags":[
        "equipment",
        "window",
        "doors"
    ],
    "wof:name":"Rum City Locks & Security",
    "wof:placetype":"venue"
},
  "geometry": {"coordinates":[152.359863281,-24.882648468],"type":"Point"}
}