{
  "type": "Feature",
  "properties": {
    "iso:country":"AU",
    "sg:address":"Lot 4 South West Hwy",
    "sg:city":"Picton",
    "sg:classifiers":[
        {
            "category":"Wholesale",
            "subcategory":"Machinery & Supplies",
            "type":"Manufacturing & Wholesale Goods"
        }
    ],
    "sg:phone":"+61 8 9725 7900",
    "sg:postcode":"6229",
    "sg:province":"WA",
    "sg:tags":[
        "rigging",
        "equipment",
        "hoisting"
    ],
    "wof:name":"Millennium Hire Company Pty Ltd",
    "wof:placetype":"venue"
},
  "geometry": {"coordinates":[115.704338,-33.347912],"type":"Point"}
}