{
  "type": "Feature",
  "properties": {
    "iso:country":"AU",
    "sg:address":"Shop 8 Highway Court 119-121 Beach Rd",
    "sg:city":"Bunbury",
    "sg:classifiers":[
        {
            "category":"Health Services",
            "subcategory":"Dentist",
            "type":"Services"
        }
    ],
    "sg:phone":"+61 1300 557 677",
    "sg:postcode":"6230",
    "sg:province":"WA",
    "wof:name":"Peel & South West Orthodontics",
    "wof:placetype":"venue"
},
  "geometry": {"coordinates":[115.639641,-33.336094],"type":"Point"}
}