{
  "type": "Feature",
  "properties": {
    "iso:country":"AU",
    "sg:address":"6 Malcolm Ave",
    "sg:city":"Mt Pritchard",
    "sg:classifiers":[
        {
            "category":"Professional",
            "subcategory":"Art Services",
            "type":"Services"
        }
    ],
    "sg:phone":"+61 2 9823 3457",
    "sg:postcode":"2170",
    "sg:province":"NSW",
    "sg:tags":[
        "artist"
    ],
    "wof:name":"Studio Bundaleer",
    "wof:placetype":"venue"
},
  "geometry": {"coordinates":[150.901855469,-33.8983612061],"type":"Point"}
}