{
  "type": "Feature",
  "properties": {
    "addr:full":"49 Banksia Rd Welshpool WA 6106",
    "addr:housenumber":"49",
    "addr:postcode":"6106",
    "addr:street":"Banksia Rd",
    "iso:country":"AU",
    "sg:address":"49 Banksia Rd",
    "sg:city":"Welshpool",
    "sg:classifiers":[
        {
            "category":"Wholesale",
            "subcategory":"Hardware",
            "type":"Manufacturing & Wholesale Goods"
        }
    ],
    "sg:phone":"+61 8 9350 6565",
    "sg:postcode":"6106",
    "sg:province":"WA",
    "wof:name":"Palm Industries Australia Pty Ltd",
    "wof:placetype":"venue"
},
  "geometry": {"coordinates":[115.96376800500001,-31.9949531555],"type":"Point"}
}