{
  "type": "Feature",
  "properties": {
    "iso:country":"AU",
    "sg:address":"Unit 72, Coventry, 2 Cape St",
    "sg:city":"Dickson",
    "sg:classifiers":[
        {
            "category":"Real Estate",
            "subcategory":"Real Estate Agent",
            "type":"Services"
        }
    ],
    "sg:phone":"+61 2 6209 4000",
    "sg:postcode":"2602",
    "sg:province":"ACT",
    "wof:name":"Independent Property Group",
    "wof:placetype":"venue"
},
  "geometry": {"coordinates":[149.135894775,-35.2513237],"type":"Point"}
}