{
  "type": "Feature",
  "properties": {
    "addr:full":"506 Hargreaves St Bendigo VIC 3550",
    "addr:housenumber":"506",
    "addr:postcode":"3550",
    "addr:street":"Hargreaves St",
    "iso:country":"AU",
    "sg:address":"506 Hargreaves St",
    "sg:city":"Bendigo",
    "sg:classifiers":[
        {
            "category":"Personal",
            "subcategory":"Massage",
            "type":"Services"
        }
    ],
    "sg:phone":"+61 3 5442 2249",
    "sg:postcode":"3550",
    "sg:province":"VIC",
    "sg:tags":[
        "therapy"
    ],
    "wof:name":"Bendigo Bowen Centre",
    "wof:placetype":"venue"
},
  "geometry": {"coordinates":[144.27784729000001,-36.7642059326],"type":"Point"}
}