{
  "type": "Feature",
  "properties": {
    "addr:full":"57 Lakemba St Belmore NSW 2192",
    "addr:housenumber":"57",
    "addr:postcode":"2192",
    "addr:street":"Lakemba St",
    "iso:country":"AU",
    "sg:address":"57 Lakemba St",
    "sg:city":"Belmore",
    "sg:classifiers":[
        {
            "category":"Autos & Motor Vehicles",
            "subcategory":"Fuel & Gas Station",
            "type":"Retail Goods"
        }
    ],
    "sg:phone":"+61 2 9758 9892",
    "sg:postcode":"2192",
    "sg:province":"NSW",
    "wof:name":"Belmore Auto Pit",
    "wof:placetype":"venue"
},
  "geometry": {"coordinates":[151.08476300000001,-33.914368],"type":"Point"}
}