{
  "type": "Feature",
  "properties": {
    "addr:full":"1 Wood St Swansea NSW 2281",
    "addr:housenumber":"1",
    "addr:postcode":"2281",
    "addr:street":"Wood St",
    "iso:country":"AU",
    "sg:address":"1 Wood St",
    "sg:city":"Swansea",
    "sg:classifiers":[
        {
            "category":"Health Services",
            "subcategory":"Health Practitioner",
            "type":"Services"
        }
    ],
    "sg:phone":"+61 2 4971 3541",
    "sg:postcode":"2281",
    "sg:province":"NSW",
    "sg:tags":[
        "physiotherapist"
    ],
    "wof:name":"Mangos Kym",
    "wof:placetype":"venue"
},
  "geometry": {"coordinates":[151.63684082,-33.0896148682],"type":"Point"}
}