{
  "type": "Feature",
  "properties": {
    "iso:country":"AU",
    "sg:address":"26 Balmoral Drv",
    "sg:city":"Golden Square",
    "sg:classifiers":[
        {
            "category":"Building & Trades",
            "subcategory":"Cleaning & Sanitation",
            "type":"Services"
        }
    ],
    "sg:phone":"+61 3 5447 8225",
    "sg:postcode":"3555",
    "sg:province":"VIC",
    "sg:tags":[
        "grease",
        "trap"
    ],
    "wof:name":"Bendigo Desludging",
    "wof:placetype":"venue"
},
  "geometry": {"coordinates":[144.238891602,-36.7708778381],"type":"Point"}
}