{
  "type": "Feature",
  "properties": {
    "addr:full":"Suite 4/Level 5, 33 moore St Liverpool NSW 2170",
    "addr:housenumber":"33",
    "addr:postcode":"2170",
    "addr:street":"Moore St",
    "iso:country":"AU",
    "sg:address":"Suite 4/Level 5, 33 moore St",
    "sg:city":"Liverpool",
    "sg:classifiers":[
        {
            "category":"Structure",
            "subcategory":"Office Building",
            "type":"Public Place"
        }
    ],
    "sg:phone":"+61 2 8777 5555",
    "sg:postcode":"2170",
    "sg:province":"NSW",
    "sg:tags":[
        "serviced"
    ],
    "sg:website":"http://www.lso.com.au",
    "wof:name":"Liverpool Serviced Offices",
    "wof:placetype":"venue"
},
  "geometry": {"coordinates":[150.91244506800001,-33.921005249],"type":"Point"}
}