{
  "type": "Feature",
  "properties": {
    "addr:full":"60 Tamarind St Maleny QLD 4552",
    "addr:housenumber":"60",
    "addr:postcode":"4552",
    "addr:street":"Tamarind St",
    "iso:country":"AU",
    "sg:address":"60 Tamarind St",
    "sg:city":"Maleny",
    "sg:classifiers":[
        {
            "category":"Building & Trades",
            "subcategory":"Plumbing",
            "type":"Services"
        }
    ],
    "sg:phone":"+61 428 767 973",
    "sg:postcode":"4552",
    "sg:province":"QLD",
    "sg:tags":[
        "plumber",
        "gasfitters"
    ],
    "wof:name":"Hydes Plumbing Service",
    "wof:placetype":"venue"
},
  "geometry": {"coordinates":[152.851104736,-26.7537231445],"type":"Point"}
}