{
  "type": "Feature",
  "properties": {
    "addr:full":"15 Hibiscus Ave Mooloolaba QLD 4557",
    "addr:housenumber":"15",
    "addr:postcode":"4557",
    "addr:street":"Hibiscus Ave",
    "iso:country":"AU",
    "sg:address":"15 Hibiscus Ave",
    "sg:city":"Mooloolaba",
    "sg:classifiers":[
        {
            "category":"Professional",
            "subcategory":"Art Services",
            "type":"Services"
        }
    ],
    "sg:phone":"+61 7 5444 2945",
    "sg:postcode":"4557",
    "sg:province":"QLD",
    "sg:tags":[
        "decorator",
        "painter"
    ],
    "wof:name":"A. & V. Ravazzano",
    "wof:placetype":"venue"
},
  "geometry": {"coordinates":[153.10438537600001,-26.677318573],"type":"Point"}
}