{
  "type": "Feature",
  "properties": {
    "addr:full":"One Tree Hill Rd Gould Creek SA 5114",
    "addr:postcode":"5114",
    "addr:street":"One Tree Hill Rd",
    "iso:country":"AU",
    "sg:address":"One Tree Hill Rd",
    "sg:city":"Gould Creek",
    "sg:classifiers":[
        {
            "category":"Building & Trades",
            "subcategory":"Plumbing",
            "type":"Services"
        }
    ],
    "sg:phone":"+61 418 844 804",
    "sg:postcode":"5114",
    "sg:province":"SA",
    "sg:tags":[
        "plumber",
        "gasfitters"
    ],
    "wof:name":"Dodd Gavin K",
    "wof:placetype":"venue"
},
  "geometry": {"coordinates":[138.73741149899999,-34.773059845],"type":"Point"}
}