{
  "type": "Feature",
  "properties": {
    "addr:full":"150 Railway Pde Kogarah NSW 2217",
    "addr:housenumber":"150",
    "addr:postcode":"2217",
    "addr:street":"Railway Pde",
    "iso:country":"AU",
    "sg:address":"150 Railway Pde",
    "sg:city":"Kogarah",
    "sg:classifiers":[
        {
            "category":"Health Services",
            "subcategory":"Doctor",
            "type":"Services"
        }
    ],
    "sg:phone":"+61 2 9588 3330",
    "sg:postcode":"2217",
    "sg:province":"NSW",
    "sg:tags":[
        "medical",
        "practitioner"
    ],
    "wof:name":"Low S",
    "wof:placetype":"venue"
},
  "geometry": {"coordinates":[151.13180500000001,-33.96542],"type":"Point"}
}