{
  "type": "Feature",
  "properties": {
    "addr:full":"Suite 3 166 Hume St Toowoomba QLD 4350",
    "addr:housenumber":"166",
    "addr:postcode":"4350",
    "addr:street":"Hume St",
    "iso:country":"AU",
    "sg:address":"Suite 3 166 Hume St",
    "sg:city":"Toowoomba",
    "sg:classifiers":[
        {
            "category":"Travel",
            "subcategory":"Travel Agent",
            "type":"Entertainment"
        }
    ],
    "sg:phone":"+61 1800 269 034",
    "sg:postcode":"4350",
    "sg:province":"QLD",
    "sg:tags":[
        "consultant"
    ],
    "wof:name":"Gunther & Turner Travel Associates",
    "wof:placetype":"venue"
},
  "geometry": {"coordinates":[151.957504,-27.56356],"type":"Point"}
}