{
  "type": "Feature",
  "properties": {
    "addr:full":"19 Ord St West Perth WA 6005",
    "addr:housenumber":"19",
    "addr:postcode":"6005",
    "addr:street":"Ord St",
    "iso:country":"AU",
    "sg:address":"19 Ord St",
    "sg:city":"West Perth",
    "sg:classifiers":[
        {
            "category":"Health Services",
            "subcategory":"Doctor",
            "type":"Services"
        }
    ],
    "sg:phone":"+61 8 9485 0700",
    "sg:postcode":"6005",
    "sg:province":"WA",
    "sg:tags":[
        "podiatrist"
    ],
    "wof:name":"Dunjey Michael",
    "wof:placetype":"venue"
},
  "geometry": {"coordinates":[115.841537476,-31.9509849548],"type":"Point"}
}