{
  "type": "Feature",
  "properties": {
    "iso:country":"AU",
    "sg:address":"38 Richardson St",
    "sg:city":"West Perth",
    "sg:classifiers":[
        {
            "category":"Professional",
            "subcategory":"Engineering",
            "type":"Services"
        }
    ],
    "sg:phone":"+61 8 9481 4255",
    "sg:postcode":"6005",
    "sg:province":"WA",
    "sg:tags":[
        "civil",
        "engineer"
    ],
    "wof:name":"The Civil Group WA Pty Ltd",
    "wof:placetype":"venue"
},
  "geometry": {"coordinates":[115.841499329,-31.94972229],"type":"Point"}
}