{
  "type": "Feature",
  "properties": {
    "addr:full":"26 Lawrence St Harbord NSW 2096",
    "addr:housenumber":"26",
    "addr:postcode":"2096",
    "addr:street":"Lawrence St",
    "iso:country":"AU",
    "sg:address":"26 Lawrence St",
    "sg:city":"Harbord",
    "sg:classifiers":[
        {
            "category":"Fast Food",
            "type":"Food & Drink"
        }
    ],
    "sg:phone":"+61 2 9939 1171",
    "sg:postcode":"2096",
    "sg:province":"NSW",
    "sg:tags":[
        "away",
        "take"
    ],
    "wof:name":"Freshwater Pizza Kitchen",
    "wof:placetype":"venue"
},
  "geometry": {"coordinates":[151.28407287600001,-33.7789573669],"type":"Point"}
}