{
  "type": "Feature",
  "properties": {
    "iso:country":"AU",
    "sg:address":"\"The Church\" 37 Orsmond St",
    "sg:city":"Hindmarsh",
    "sg:classifiers":[
        {
            "category":"Shopping",
            "subcategory":"Discount & Variety Stores",
            "type":"Retail Goods"
        }
    ],
    "sg:phone":"+61 8 8346 6888",
    "sg:postcode":"5007",
    "sg:province":"SA",
    "sg:tags":[
        "recording",
        "equipment",
        "supply"
    ],
    "wof:name":"Chapel Lane Studios",
    "wof:placetype":"venue"
},
  "geometry": {"coordinates":[138.572357178,-34.9069976807],"type":"Point"}
}