{
  "type": "Feature",
  "properties": {
    "iso:country":"AU",
    "sg:address":"PO Box 5732",
    "sg:city":"Falcon",
    "sg:classifiers":[
        {
            "category":"Building & Trades",
            "subcategory":"Cleaning & Sanitation",
            "type":"Services"
        }
    ],
    "sg:phone":"+61 8 9535 3686",
    "sg:postcode":"6210",
    "sg:province":"WA",
    "sg:tags":[
        "grease",
        "trap"
    ],
    "wof:name":"Mandurah Liquid Waste Disposal",
    "wof:placetype":"venue"
},
  "geometry": {"coordinates":[115.662193,-32.581299],"type":"Point"}
}