{
  "type": "Feature",
  "properties": {
    "addr:full":"24 Pradella St Darra QLD 4076",
    "addr:housenumber":"24",
    "addr:postcode":"4076",
    "addr:street":"Pradella St",
    "iso:country":"AU",
    "sg:address":"24 Pradella St",
    "sg:city":"Darra",
    "sg:classifiers":[
        {
            "category":"Retail",
            "subcategory":"Auto Repair",
            "type":"Services"
        }
    ],
    "sg:phone":"+61 7 3375 7557",
    "sg:postcode":"4076",
    "sg:province":"QLD",
    "sg:tags":[
        "body",
        "builder",
        "motor"
    ],
    "wof:name":"Homealloy Bodyworks",
    "wof:placetype":"venue"
},
  "geometry": {"coordinates":[152.95147705100001,-27.5766963959],"type":"Point"}
}