{
  "type": "Feature",
  "properties": {
    "iso:country":"AU",
    "sg:address":"3/ 20 Fortune St",
    "sg:city":"Geebung",
    "sg:classifiers":[
        {
            "category":"Professional",
            "subcategory":"Testing Lab",
            "type":"Services"
        }
    ],
    "sg:phone":"+61 7 3865 3212",
    "sg:postcode":"4034",
    "sg:province":"QLD",
    "sg:tags":[
        "soil",
        "investigation"
    ],
    "wof:name":"Bowler Geotechnical",
    "wof:placetype":"venue"
},
  "geometry": {"coordinates":[153.047104,-27.365402],"type":"Point"}
}