{
  "type": "Feature",
  "properties": {
    "addr:full":"9 Eaves St Holt ACT 2615",
    "addr:housenumber":"9",
    "addr:postcode":"2615",
    "addr:street":"Eaves St",
    "iso:country":"AU",
    "sg:address":"9 Eaves St",
    "sg:city":"Holt",
    "sg:classifiers":[
        {
            "category":"Building & Trades",
            "subcategory":"Construction",
            "type":"Services"
        }
    ],
    "sg:phone":"+61 412 625 166",
    "sg:postcode":"2615",
    "sg:province":"ACT",
    "sg:tags":[
        "plasterboard",
        "plasterer",
        "fixer"
    ],
    "wof:name":"Murwillunmbah Plasters Pty Ltd",
    "wof:placetype":"venue"
},
  "geometry": {"coordinates":[149.01429748499999,-35.2280158997],"type":"Point"}
}