{
  "type": "Feature",
  "properties": {
    "addr:full":"80 John St Rosewood QLD 4340",
    "addr:housenumber":"80",
    "addr:postcode":"4340",
    "addr:street":"John St",
    "iso:country":"AU",
    "sg:address":"80 John St",
    "sg:city":"Rosewood",
    "sg:classifiers":[
        {
            "category":"Social Services",
            "subcategory":"Child Care",
            "type":"Services"
        }
    ],
    "sg:phone":"+61 7 5464 2033",
    "sg:postcode":"4340",
    "sg:province":"QLD",
    "wof:name":"Rosewood Early Education Centre",
    "wof:placetype":"venue"
},
  "geometry": {"coordinates":[152.59016418499999,-27.6346473694],"type":"Point"}
}