{
  "type": "Feature",
  "properties": {
    "iso:country":"AU",
    "sg:address":"1C Medway Rd",
    "sg:city":"Keilor East",
    "sg:classifiers":[
        {
            "category":"Real Estate",
            "subcategory":"Surveying",
            "type":"Services"
        }
    ],
    "sg:phone":"+61 3 9325 4456",
    "sg:postcode":"3033",
    "sg:province":"VIC",
    "sg:tags":[
        "surveyor",
        "land"
    ],
    "wof:name":"Horizon Surveyors Pty Ltd",
    "wof:placetype":"venue"
},
  "geometry": {"coordinates":[144.873993,-37.751656],"type":"Point"}
}