{
  "type": "Feature",
  "properties": {
    "addr:full":"13 Lamington St Ingle Farm SA 5098",
    "addr:housenumber":"13",
    "addr:postcode":"5098",
    "addr:street":"Lamington St",
    "iso:country":"AU",
    "sg:address":"13 Lamington St",
    "sg:city":"Ingle Farm",
    "sg:classifiers":[
        {
            "category":"Home & Garden",
            "subcategory":"Building Materials",
            "type":"Retail Goods"
        }
    ],
    "sg:phone":"+61 8 8265 1830",
    "sg:postcode":"5098",
    "sg:province":"SA",
    "sg:tags":[
        "lawn",
        "cutting",
        "maintenance"
    ],
    "wof:name":"Lloyd A & B",
    "wof:placetype":"venue"
},
  "geometry": {"coordinates":[138.64811706500001,-34.8207130432],"type":"Point"}
}