{
  "type": "Feature",
  "properties": {
    "addr:full":"166 Faulkners Rd Glenlusk TAS 7012",
    "addr:housenumber":"166",
    "addr:postcode":"7012",
    "addr:street":"Faulkners Rd",
    "iso:country":"AU",
    "sg:address":"166 Faulkners Rd",
    "sg:city":"Glenlusk",
    "sg:classifiers":[
        {
            "category":"Real Estate",
            "subcategory":"Surveying",
            "type":"Services"
        }
    ],
    "sg:phone":"+61 3 6249 8865",
    "sg:postcode":"7012",
    "sg:province":"TAS",
    "sg:tags":[
        "surveyor",
        "land"
    ],
    "wof:name":"Morley Family Trust",
    "wof:placetype":"venue"
},
  "geometry": {"coordinates":[147.204147339,-42.8218765259],"type":"Point"}
}