{
  "type": "Feature",
  "properties": {
    "addr:full":"19 Ryrie St Geelong VIC 3220",
    "addr:housenumber":"19",
    "addr:postcode":"3220",
    "addr:street":"Ryrie St",
    "iso:country":"AU",
    "sg:address":"19 Ryrie St",
    "sg:city":"Geelong",
    "sg:classifiers":[
        {
            "category":"Professional",
            "subcategory":"Art Services",
            "type":"Services"
        }
    ],
    "sg:phone":"+61 3 5278 8324",
    "sg:postcode":"3220",
    "sg:province":"VIC",
    "sg:tags":[
        "decorator",
        "painter"
    ],
    "wof:name":"LD & E Hornsey Painting Contractors",
    "wof:placetype":"venue"
},
  "geometry": {"coordinates":[144.35348500000001,-38.147327],"type":"Point"}
}