{
  "type": "Feature",
  "properties": {
    "addr:full":"40 Park Crs Williamstown VIC 3016",
    "addr:housenumber":"40",
    "addr:postcode":"3016",
    "addr:street":"Park Crs",
    "iso:country":"AU",
    "sg:address":"40 Park Crs",
    "sg:city":"Williamstown",
    "sg:classifiers":[
        {
            "category":"Building & Trades",
            "subcategory":"Cleaning & Sanitation",
            "type":"Services"
        }
    ],
    "sg:phone":"+61 414 351 700",
    "sg:postcode":"3016",
    "sg:province":"VIC",
    "sg:tags":[
        "window"
    ],
    "wof:name":"Apache Window Cleaning",
    "wof:placetype":"venue"
},
  "geometry": {"coordinates":[144.902587891,-37.8615112305],"type":"Point"}
}