{
  "type": "Feature",
  "properties": {
    "addr:full":"4/ 995 Victoria Rd West Ryde NSW 2114",
    "addr:housenumber":"/ 995",
    "addr:postcode":"2114",
    "addr:street":"Victoria Rd",
    "iso:country":"AU",
    "sg:address":"4/ 995 Victoria Rd",
    "sg:city":"West Ryde",
    "sg:classifiers":[
        {
            "category":"Building & Trades",
            "subcategory":"Construction",
            "type":"Services"
        }
    ],
    "sg:phone":"+61 2 9807 8998",
    "sg:postcode":"2114",
    "sg:province":"NSW",
    "sg:tags":[
        "window",
        "tinting"
    ],
    "wof:name":"Shinsun Decoration",
    "wof:placetype":"venue"
},
  "geometry": {"coordinates":[151.08810424800001,-33.8074798584],"type":"Point"}
}