{
  "type": "Feature",
  "properties": {
    "addr:full":"Unit 3, 64 Hassal St Smithfield NSW 2164",
    "addr:housenumber":"64",
    "addr:postcode":"2164",
    "addr:street":"Hassal St",
    "iso:country":"AU",
    "sg:address":"Unit 3, 64 Hassal St",
    "sg:city":"Smithfield",
    "sg:classifiers":[
        {
            "category":"Wholesale",
            "subcategory":"Machinery & Supplies",
            "type":"Manufacturing & Wholesale Goods"
        }
    ],
    "sg:phone":"+61 2 9757 4367",
    "sg:postcode":"2164",
    "sg:province":"NSW",
    "sg:tags":[
        "engineer"
    ],
    "wof:name":"L M Fasteners",
    "wof:placetype":"venue"
},
  "geometry": {"coordinates":[150.922775269,-33.8473205566],"type":"Point"}
}