{
  "type": "Feature",
  "properties": {
    "addr:full":"37 Poppet Rd Wamboin ACT 2620",
    "addr:housenumber":"37",
    "addr:postcode":"2620",
    "addr:street":"Poppet Rd",
    "iso:country":"AU",
    "sg:address":"37 Poppet Rd",
    "sg:city":"Wamboin",
    "sg:classifiers":[
        {
            "category":"Manufacturing",
            "subcategory":"Lumber",
            "type":"Manufacturing & Wholesale Goods"
        }
    ],
    "sg:phone":"+61 2 6238 3308",
    "sg:postcode":"2620",
    "sg:province":"ACT",
    "sg:tags":[
        "sawmillers"
    ],
    "wof:name":"Wiyagiba Trading",
    "wof:placetype":"venue"
},
  "geometry": {"coordinates":[149.29010009800001,-35.2573051453],"type":"Point"}
}