{
  "type": "Feature",
  "properties": {
    "iso:country":"AU",
    "sg:address":"43 Old Port Wakefield Rd",
    "sg:city":"Two Wells",
    "sg:classifiers":[
        {
            "category":"Government",
            "subcategory":"Post Office",
            "type":"Public Place"
        }
    ],
    "sg:phone":"+61 8 8520 2249",
    "sg:postcode":"5501",
    "sg:province":"SA",
    "sg:tags":[
        "postal"
    ],
    "wof:name":"Australia Post",
    "wof:placetype":"venue"
},
  "geometry": {"coordinates":[138.51676900000001,-34.595196],"type":"Point"}
}