{
  "type": "Feature",
  "properties": {
    "iso:country":"AU",
    "sg:address":"486 Port Rd",
    "sg:city":"Hindmarsh West",
    "sg:classifiers":[
        {
            "category":"Autos & Motor Vehicles",
            "subcategory":"Automobile Sales",
            "type":"Retail Goods"
        }
    ],
    "sg:phone":"+61 8 8346 6503",
    "sg:postcode":"5007",
    "sg:province":"SA",
    "sg:tags":[
        "car",
        "used"
    ],
    "wof:name":"Manta Car Sales",
    "wof:placetype":"venue"
},
  "geometry": {"coordinates":[138.56040954599999,-34.898021698],"type":"Point"}
}