{
  "type": "Feature",
  "properties": {
    "addr:full":"25 Weroo Pl Stirling WA 6021",
    "addr:housenumber":"25",
    "addr:postcode":"6021",
    "addr:street":"Weroo Pl",
    "iso:country":"AU",
    "sg:address":"25 Weroo Pl",
    "sg:city":"Stirling",
    "sg:classifiers":[
        {
            "category":"Health Services",
            "subcategory":"Dentist",
            "type":"Services"
        }
    ],
    "sg:phone":"+61 418 944 759",
    "sg:postcode":"6021",
    "sg:province":"WA",
    "sg:tags":[
        "technician",
        "dental"
    ],
    "wof:name":"D&#039;n&#039;D",
    "wof:placetype":"venue"
},
  "geometry": {"coordinates":[115.815910339,-31.881652832],"type":"Point"}
}