{
  "type": "Feature",
  "properties": {
    "addr:full":"14 Lambert St (Cnr. Clarence) Indooroopilly QLD 4068",
    "addr:housenumber":"14",
    "addr:postcode":"4068",
    "addr:street":"Lambert St Cnr.",
    "iso:country":"AU",
    "sg:address":"14 Lambert St",
    "sg:city":"(Cnr. Clarence) Indooroopilly",
    "sg:classifiers":[
        {
            "category":"Food & Beverages",
            "subcategory":"Liquor & Beverages",
            "type":"Retail Goods"
        }
    ],
    "sg:phone":"+61 7 3720 8861",
    "sg:postcode":"4068",
    "sg:province":"QLD",
    "sg:tags":[
        "store"
    ],
    "wof:name":"Vegas Liquor Indooroopilly",
    "wof:placetype":"venue"
},
  "geometry": {"coordinates":[152.976654053,-27.5032157898],"type":"Point"}
}