{
  "type": "Feature",
  "properties": {
    "addr:full":"268c Main North Rd Prospect SA 5082",
    "addr:housenumber":"268c",
    "addr:postcode":"5082",
    "addr:street":"Main North Rd",
    "iso:country":"AU",
    "sg:address":"268c Main North Rd",
    "sg:city":"Prospect",
    "sg:classifiers":[
        {
            "category":"Retail",
            "subcategory":"Storage",
            "type":"Services"
        }
    ],
    "sg:phone":"+61 8 8344 6555",
    "sg:postcode":"5082",
    "sg:province":"SA",
    "sg:tags":[
        "removal",
        "furniture"
    ],
    "wof:name":"Awesome Second Hand Furniture",
    "wof:placetype":"venue"
},
  "geometry": {"coordinates":[138.602386475,-34.8823242188],"type":"Point"}
}