{
  "type": "Feature",
  "properties": {
    "addr:full":"25 Fourteenth St Gawler South SA 5118",
    "addr:housenumber":"25",
    "addr:postcode":"5118",
    "addr:street":"Fourteenth St",
    "iso:country":"AU",
    "sg:address":"25 Fourteenth St",
    "sg:city":"Gawler South",
    "sg:classifiers":[
        {
            "category":"Professional",
            "subcategory":"Computer Services",
            "type":"Services"
        }
    ],
    "sg:phone":"+61 8 8523 4927",
    "sg:postcode":"5118",
    "sg:province":"SA",
    "sg:tags":[
        "package",
        "software"
    ],
    "wof:name":"Bluegum Software",
    "wof:placetype":"venue"
},
  "geometry": {"coordinates":[138.74229399999999,-34.603546],"type":"Point"}
}