{
  "type": "Feature",
  "properties": {
    "addr:full":"Suite 1, 57 Denison St Camperdown NSW 2050",
    "addr:housenumber":"57",
    "addr:postcode":"2050",
    "addr:street":"Denison St",
    "iso:country":"AU",
    "sg:address":"Suite 1, 57 Denison St",
    "sg:city":"Camperdown",
    "sg:classifiers":[
        {
            "category":"Education",
            "subcategory":"Special Training",
            "type":"Public Place"
        }
    ],
    "sg:phone":"+61 2 9557 2748",
    "sg:postcode":"2050",
    "sg:province":"NSW",
    "sg:tags":[
        "tuition-educational"
    ],
    "wof:name":"Kip McGrath Education Centres",
    "wof:placetype":"venue"
},
  "geometry": {"coordinates":[151.174362,-33.88953],"type":"Point"}
}