{
  "type": "Feature",
  "properties": {
    "addr:full":"Unit 5 224 Wishart Rd Wishart QLD 4122",
    "addr:housenumber":"224",
    "addr:postcode":"4122",
    "addr:street":"Wishart Rd",
    "iso:country":"AU",
    "sg:address":"Unit 5 224 Wishart Rd",
    "sg:city":"Wishart",
    "sg:classifiers":[
        {
            "category":"Shopping",
            "subcategory":"Computers & Home Electronics",
            "type":"Retail Goods"
        }
    ],
    "sg:phone":"+61 7 3849 7099",
    "sg:postcode":"4122",
    "sg:province":"QLD",
    "sg:tags":[
        "hardware",
        "equipment"
    ],
    "wof:name":"Scsi-Tek",
    "wof:placetype":"venue"
},
  "geometry": {"coordinates":[153.09266662600001,-27.5471153259],"type":"Point"}
}