{
  "type": "Feature",
  "properties": {
    "addr:full":"14 Springfield Ave Kotara NSW 2289",
    "addr:housenumber":"14",
    "addr:postcode":"2289",
    "addr:street":"Springfield Ave",
    "iso:country":"AU",
    "sg:address":"14 Springfield Ave",
    "sg:city":"Kotara",
    "sg:classifiers":[
        {
            "category":"Professional",
            "subcategory":"Business Services",
            "type":"Services"
        }
    ],
    "sg:phone":"+61 413 314 303",
    "sg:postcode":"2289",
    "sg:province":"NSW",
    "sg:tags":[
        "drafting"
    ],
    "wof:name":"Allmech Project Services Pty Ltd",
    "wof:placetype":"venue"
},
  "geometry": {"coordinates":[151.703735352,-32.9432296753],"type":"Point"}
}