{
  "type": "Feature",
  "properties": {
    "addr:full":"Shop 2/ 114 Anstruther Rd Mandurah WA 6210",
    "addr:housenumber":"shop 2 / 114",
    "addr:postcode":"6210",
    "addr:street":"Anstruther Rd",
    "iso:country":"AU",
    "sg:address":"Shop 2/ 114 Anstruther Rd",
    "sg:city":"Mandurah",
    "sg:classifiers":[
        {
            "category":"Shopping",
            "subcategory":"Computers & Home Electronics",
            "type":"Retail Goods"
        }
    ],
    "sg:phone":"+61 8 9582 9066",
    "sg:postcode":"6210",
    "sg:province":"WA",
    "sg:tags":[
        "hardware",
        "equipment"
    ],
    "wof:name":"Mandurah Comp-U-Teq",
    "wof:placetype":"venue"
},
  "geometry": {"coordinates":[115.731934,-32.521114],"type":"Point"}
}