{
  "type": "Feature",
  "properties": {
    "addr:full":"Asia-Pacific Head Office 47 Darling St South Yarra VIC 3141",
    "addr:housenumber":"47",
    "addr:postcode":"3141",
    "addr:street":"Darling St",
    "iso:country":"AU",
    "sg:address":"Asia-Pacific Head Office 47 Darling St",
    "sg:city":"South Yarra",
    "sg:classifiers":[
        {
            "category":"Education",
            "subcategory":"Special Training",
            "type":"Public Place"
        }
    ],
    "sg:phone":"+61 3 9820 4449",
    "sg:postcode":"3141",
    "sg:province":"VIC",
    "sg:tags":[
        "development"
    ],
    "wof:name":"Image Group International",
    "wof:placetype":"venue"
},
  "geometry": {"coordinates":[144.99183654800001,-37.8354797363],"type":"Point"}
}