{
  "type": "Feature",
  "properties": {
    "addr:full":"Unit 12, 2 Production Rd Taren Point NSW 2229",
    "addr:housenumber":"2",
    "addr:postcode":"2229",
    "addr:street":"Production Rd",
    "iso:country":"AU",
    "sg:address":"Unit 12, 2 Production Rd",
    "sg:city":"Taren Point",
    "sg:classifiers":[
        {
            "category":"Professional",
            "subcategory":"Employment Agencies",
            "type":"Services"
        }
    ],
    "sg:phone":"+61 2 9526 5101",
    "sg:postcode":"2229",
    "sg:province":"NSW",
    "sg:tags":[
        "broker",
        "custom"
    ],
    "wof:name":"Dyson Tradelink Pty Ltd",
    "wof:placetype":"venue"
},
  "geometry": {"coordinates":[151.12614440900001,-34.0233840942],"type":"Point"}
}