{
  "type": "Feature",
  "properties": {
    "addr:full":"Shop 3 Basement 265 Murray St Perth WA 6000",
    "addr:housenumber":"shop 3;265",
    "addr:postcode":"6000",
    "addr:street":"Murray St",
    "iso:country":"AU",
    "sg:address":"Shop 3 Basement 265 Murray St",
    "sg:city":"Perth",
    "sg:classifiers":[
        {
            "category":"Fast Food",
            "type":"Food & Drink"
        }
    ],
    "sg:phone":"+61 8 9322 7723",
    "sg:postcode":"6000",
    "sg:province":"WA",
    "sg:tags":[
        "away",
        "take"
    ],
    "wof:name":"Christine Food Power",
    "wof:placetype":"venue"
},
  "geometry": {"coordinates":[115.854187012,-31.9514923096],"type":"Point"}
}