{
  "type": "Feature",
  "properties": {
    "iso:country":"AU",
    "sg:address":"187 Sylvania Rd",
    "sg:city":"Miranda",
    "sg:classifiers":[
        {
            "category":"Professional",
            "subcategory":"Art Services",
            "type":"Services"
        }
    ],
    "sg:phone":"+61 2 9524 5924",
    "sg:postcode":"2228",
    "sg:province":"NSW",
    "sg:tags":[
        "graphic",
        "designer"
    ],
    "wof:name":"Keith Morris Design Pty Ltd",
    "wof:placetype":"venue"
},
  "geometry": {"coordinates":[151.09138488799999,-34.0374259949],"type":"Point"}
}