{
  "type": "Feature",
  "properties": {
    "addr:full":"31/ 30 Lindeman Pl Eight Mile Plains QLD 4113",
    "addr:housenumber":"31 / 30",
    "addr:postcode":"4113",
    "addr:street":"Lindeman Pl",
    "iso:country":"AU",
    "sg:address":"31/ 30 Lindeman Pl",
    "sg:city":"Eight Mile Plains",
    "sg:classifiers":[
        {
            "category":"Professional",
            "subcategory":"Art Services",
            "type":"Services"
        }
    ],
    "sg:phone":"+61 7 3423 3835",
    "sg:postcode":"4113",
    "sg:province":"QLD",
    "sg:tags":[
        "graphic",
        "designer"
    ],
    "wof:name":"2020 Impact Design & Marketing",
    "wof:placetype":"venue"
},
  "geometry": {"coordinates":[153.102386475,-27.5728187561],"type":"Point"}
}