{
  "type": "Feature",
  "properties": {
    "addr:full":"10 Keats Pl Melba ACT 2615",
    "addr:housenumber":"10",
    "addr:postcode":"2615",
    "addr:street":"Keats Pl Melba",
    "iso:country":"AU",
    "sg:address":"10 Keats Pl",
    "sg:city":"Melba",
    "sg:classifiers":[
        {
            "category":"Building & Trades",
            "subcategory":"Landscaping Services",
            "type":"Services"
        }
    ],
    "sg:phone":"+61 2 6258 4936",
    "sg:postcode":"2615",
    "sg:province":"ACT",
    "sg:tags":[
        "inspection"
    ],
    "wof:name":"Pascons",
    "wof:placetype":"venue"
},
  "geometry": {"coordinates":[149.05226135300001,-35.2050666809],"type":"Point"}
}