{
  "type": "Feature",
  "properties": {
    "addr:full":"13 Roberts St Bayswater WA 6053",
    "addr:housenumber":"13",
    "addr:postcode":"6053",
    "addr:street":"Roberts St",
    "iso:country":"AU",
    "sg:address":"13 Roberts St",
    "sg:city":"Bayswater",
    "sg:classifiers":[
        {
            "category":"Social Services",
            "subcategory":"Child Care",
            "type":"Services"
        }
    ],
    "sg:phone":"+61 8 9272 4948",
    "sg:postcode":"6053",
    "sg:province":"WA",
    "wof:name":"Bayswater Out of School Care",
    "wof:placetype":"venue"
},
  "geometry": {"coordinates":[115.90957641599999,-31.9210243225],"type":"Point"}
}