{
  "type": "Feature",
  "properties": {
    "iso:country":"AU",
    "sg:address":"102 Kepler St",
    "sg:city":"Warrnambool",
    "sg:classifiers":[
        {
            "category":"Manufacturing",
            "subcategory":"Signs",
            "type":"Manufacturing & Wholesale Goods"
        }
    ],
    "sg:phone":"+61 3 5562 7077",
    "sg:postcode":"3280",
    "sg:province":"VIC",
    "sg:tags":[
        "traffic",
        "safety"
    ],
    "wof:name":"Autografix Warrnambool",
    "wof:placetype":"venue"
},
  "geometry": {"coordinates":[142.48268127399999,-38.3811187744],"type":"Point"}
}