{
  "type": "Feature",
  "properties": {
    "addr:full":"54 Rosedale Ave Greenacre NSW 2190",
    "addr:housenumber":"54",
    "addr:postcode":"2190",
    "addr:street":"Rosedale Ave",
    "iso:country":"AU",
    "sg:address":"54 Rosedale Ave",
    "sg:city":"Greenacre",
    "sg:classifiers":[
        {
            "category":"Retail",
            "subcategory":"Auto Repair",
            "type":"Services"
        }
    ],
    "sg:phone":"+61 2 9707 3541",
    "sg:postcode":"2190",
    "sg:province":"NSW",
    "sg:tags":[
        "repairer",
        "motor",
        "engineer"
    ],
    "wof:name":"Sunway Motors",
    "wof:placetype":"venue"
},
  "geometry": {"coordinates":[151.04116821299999,-33.9006614685],"type":"Point"}
}