{
  "type": "Feature",
  "properties": {
    "iso:country":"AU",
    "sg:address":"Calleen Farm Midlands Rd",
    "sg:city":"Coorow",
    "sg:classifiers":[
        {
            "category":"Farming",
            "subcategory":"Farm",
            "type":"Manufacturing & Wholesale Goods"
        }
    ],
    "sg:phone":"+61 8 9952 1032",
    "sg:postcode":"6515",
    "sg:province":"WA",
    "sg:tags":[
        "farmer"
    ],
    "wof:name":"O&#039;Callaghan Bevan",
    "wof:placetype":"venue"
},
  "geometry": {"coordinates":[116.021698,-29.882521],"type":"Point"}
}