{
  "type": "Feature",
  "properties": {
    "iso:country":"AU",
    "sg:address":"607 Anzac Hwy",
    "sg:city":"Glenelg",
    "sg:classifiers":[
        {
            "category":"Real Estate",
            "subcategory":"Real Estate Agent",
            "type":"Services"
        }
    ],
    "sg:phone":"+61 8 8295 5818",
    "sg:postcode":"5045",
    "sg:province":"SA",
    "wof:name":"Phil McMahon Real Estate",
    "wof:placetype":"venue"
},
  "geometry": {"coordinates":[138.518997192,-34.9904289246],"type":"Point"}
}