{
  "type": "Feature",
  "properties": {
    "addr:full":"9 Commonwealth Crt Penguin TAS 7316",
    "addr:housenumber":"9",
    "addr:postcode":"7316",
    "addr:street":"Commonwealth Crt",
    "iso:country":"AU",
    "sg:address":"9 Commonwealth Crt",
    "sg:city":"Penguin",
    "sg:classifiers":[
        {
            "category":"Utilities",
            "subcategory":"Electric",
            "type":"Services"
        }
    ],
    "sg:phone":"+61 409 385 419",
    "sg:postcode":"7316",
    "sg:province":"TAS",
    "sg:tags":[
        "electrical",
        "contractor"
    ],
    "wof:name":"A.L.S Electrical",
    "wof:placetype":"venue"
},
  "geometry": {"coordinates":[146.074142456,-41.1241416931],"type":"Point"}
}