{
  "type": "Feature",
  "properties": {
    "addr:full":"Cnr Belmore & Winfield Rd Balwyn North VIC 3104",
    "addr:postcode":"3104",
    "addr:street":"Cnr Belmore & Winfield Rd",
    "iso:country":"AU",
    "sg:address":"Cnr Belmore & Winfield Rd",
    "sg:city":"Balwyn North",
    "sg:classifiers":[
        {
            "category":"Arts & Performance",
            "subcategory":"Theater",
            "type":"Entertainment"
        }
    ],
    "sg:phone":"+61 400 007 278",
    "sg:postcode":"3104",
    "sg:province":"VIC",
    "sg:tags":[
        "theatre"
    ],
    "wof:name":"Hats Inc Theatre Company",
    "wof:placetype":"venue"
},
  "geometry": {"coordinates":[145.10414123499999,-37.80210495],"type":"Point"}
}