{
  "type": "Feature",
  "properties": {
    "addr:full":"48 Albany Crs Surrey Hills VIC 3127",
    "addr:housenumber":"48",
    "addr:postcode":"3127",
    "addr:street":"Albany Crs",
    "iso:country":"AU",
    "sg:address":"48 Albany Crs",
    "sg:city":"Surrey Hills",
    "sg:classifiers":[
        {
            "category":"Professional",
            "subcategory":"Art Services",
            "type":"Services"
        }
    ],
    "sg:phone":"+61 412 302 377",
    "sg:postcode":"3127",
    "sg:province":"VIC",
    "sg:tags":[
        "interior",
        "decorator"
    ],
    "wof:name":"Greygum Interiors",
    "wof:placetype":"venue"
},
  "geometry": {"coordinates":[145.09730529800001,-37.8255195618],"type":"Point"}
}