{
  "type": "Feature",
  "properties": {
    "addr:full":"553 Bussell Hwy Busselton WA 6280",
    "addr:housenumber":"553",
    "addr:postcode":"6280",
    "addr:street":"Bussell Hwy",
    "iso:country":"AU",
    "sg:address":"553 Bussell Hwy",
    "sg:city":"Busselton",
    "sg:classifiers":[
        {
            "category":"Travel",
            "subcategory":"Hotels & Motels",
            "type":"Entertainment"
        }
    ],
    "sg:phone":"+61 1800 443 544",
    "sg:postcode":"6280",
    "sg:province":"WA",
    "sg:tags":[
        "accommodation"
    ],
    "wof:name":"Broadwater Bungalows Resort",
    "wof:placetype":"venue"
},
  "geometry": {"coordinates":[115.278846741,-33.6599082947],"type":"Point"}
}