{
  "type": "Feature",
  "properties": {
    "addr:full":"264 Lord St Perth WA 6000",
    "addr:housenumber":"264",
    "addr:postcode":"6000",
    "addr:street":"Lord St",
    "iso:country":"AU",
    "sg:address":"264 Lord St",
    "sg:city":"Perth",
    "sg:classifiers":[
        {
            "category":"Autos & Motor Vehicles",
            "subcategory":"Automobile Sales",
            "type":"Retail Goods"
        }
    ],
    "sg:phone":"+61 8 9227 6352",
    "sg:postcode":"6000",
    "sg:province":"WA",
    "sg:tags":[
        "car",
        "used"
    ],
    "wof:name":"A & A Wholesale",
    "wof:placetype":"venue"
},
  "geometry": {"coordinates":[115.87256622300001,-31.9452629089],"type":"Point"}
}