{
  "type": "Feature",
  "properties": {
    "iso:country":"AU",
    "sg:address":"65 Tharwa Rd",
    "sg:city":"Queanbeyan",
    "sg:classifiers":[
        {
            "category":"Retail",
            "subcategory":"Auto Repair",
            "type":"Services"
        }
    ],
    "sg:phone":"+61 2 6299 0099",
    "sg:postcode":"2620",
    "sg:province":"NSW",
    "sg:tags":[
        "repairer",
        "motor",
        "engineer"
    ],
    "wof:name":"Rob's Auto Repairs Pty Ltd",
    "wof:placetype":"venue"
},
  "geometry": {"coordinates":[149.22103881800001,-35.3582878113],"type":"Point"}
}