{
  "type": "Feature",
  "properties": {
    "addr:full":"50 Dundundra Drv Clifton Springs VIC 3222",
    "addr:housenumber":"50",
    "addr:postcode":"3222",
    "addr:street":"Dundundra Drv",
    "iso:country":"AU",
    "sg:address":"50 Dundundra Drv",
    "sg:city":"Clifton Springs",
    "sg:classifiers":[
        {
            "category":"Building & Trades",
            "subcategory":"Construction",
            "type":"Services"
        }
    ],
    "sg:phone":"+61 3 5251 1965",
    "sg:postcode":"3222",
    "sg:province":"VIC",
    "sg:tags":[
        "earth",
        "excavating",
        "moving",
        "contractor"
    ],
    "wof:name":"Gary Bowd Excavations & Earthworks",
    "wof:placetype":"venue"
},
  "geometry": {"coordinates":[144.577133,-38.155003],"type":"Point"}
}