{
  "type": "Feature",
  "properties": {
    "addr:full":"14 Henry St St George QLD 4487",
    "addr:housenumber":"14",
    "addr:postcode":"4487",
    "addr:street":"Henry St",
    "iso:country":"AU",
    "sg:address":"14 Henry St",
    "sg:city":"St George",
    "sg:classifiers":[
        {
            "category":"Communications",
            "subcategory":"Film & Video Production",
            "type":"Services"
        }
    ],
    "sg:phone":"+61 7 4625 5559",
    "sg:postcode":"4487",
    "sg:province":"QLD",
    "sg:tags":[
        "dvd",
        "library"
    ],
    "wof:name":"Wandland Pty Ltd",
    "wof:placetype":"venue"
},
  "geometry": {"coordinates":[148.58102417000001,-28.0350990295],"type":"Point"}
}