{
  "type": "Feature",
  "properties": {
    "addr:full":"99 Coogee Bay Rd Coogee NSW 2034",
    "addr:housenumber":"99",
    "addr:postcode":"2034",
    "addr:street":"Coogee Bay Rd",
    "iso:country":"AU",
    "sg:address":"99 Coogee Bay Rd",
    "sg:city":"Coogee",
    "sg:classifiers":[
        {
            "category":"Health Services",
            "subcategory":"Chiropractor",
            "type":"Services"
        }
    ],
    "sg:phone":"+61 2 9665 1707",
    "sg:postcode":"2034",
    "sg:province":"NSW",
    "wof:name":"Brandtman Paul",
    "wof:placetype":"venue"
},
  "geometry": {"coordinates":[151.249465942,-33.9198570251],"type":"Point"}
}