{
  "type": "Feature",
  "properties": {
    "addr:full":"370 Pascoe Vale Rd Strathmore VIC 3041",
    "addr:housenumber":"370",
    "addr:postcode":"3041",
    "addr:street":"Pascoe Vale Rd",
    "iso:country":"AU",
    "sg:address":"370 Pascoe Vale Rd",
    "sg:city":"Strathmore",
    "sg:classifiers":[
        {
            "category":"Health Services",
            "subcategory":"Health Practitioner",
            "type":"Services"
        }
    ],
    "sg:phone":"+61 3 9379 0637",
    "sg:postcode":"3041",
    "sg:province":"VIC",
    "sg:tags":[
        "alternative"
    ],
    "wof:name":"Elite Natural Therapies",
    "wof:placetype":"venue"
},
  "geometry": {"coordinates":[144.928497314,-37.7430725098],"type":"Point"}
}