{
  "type": "Feature",
  "properties": {
    "addr:full":"580 High St Thornbury VIC 3071",
    "addr:housenumber":"580",
    "addr:postcode":"3071",
    "addr:street":"High St",
    "iso:country":"AU",
    "sg:address":"580 High St",
    "sg:city":"Thornbury",
    "sg:classifiers":[
        {
            "category":"Shopping",
            "subcategory":"Clothing, Apparel, & Fashions",
            "type":"Retail Goods"
        }
    ],
    "sg:phone":"+61 3 9480 4244",
    "sg:postcode":"3071",
    "sg:province":"VIC",
    "sg:tags":[
        "sportswear"
    ],
    "wof:name":"Aywon Crestknit Pty Ltd",
    "wof:placetype":"venue"
},
  "geometry": {"coordinates":[145.00015258799999,-37.7621459961],"type":"Point"}
}