{
  "type": "Feature",
  "properties": {
    "iso:country":"AU",
    "sg:address":"PO Box 575",
    "sg:city":"Northcote",
    "sg:classifiers":[
        {
            "category":"Utilities",
            "subcategory":"Electric",
            "type":"Services"
        }
    ],
    "sg:phone":"+61 411 420 621",
    "sg:postcode":"3070",
    "sg:province":"VIC",
    "sg:tags":[
        "electrical",
        "contractor"
    ],
    "wof:name":"J.A.E. Electrics",
    "wof:placetype":"venue"
},
  "geometry": {"coordinates":[144.99939000000001,-37.772289],"type":"Point"}
}