{
  "type": "Feature",
  "properties": {
    "iso:country":"AU",
    "sg:address":"17 Nicholson St",
    "sg:city":"Bentleigh",
    "sg:classifiers":[
        {
            "category":"Health Services",
            "subcategory":"Dentist",
            "type":"Services"
        }
    ],
    "sg:phone":"+61 3 9557 6630",
    "sg:postcode":"3204",
    "sg:province":"VIC",
    "wof:name":"Hadzakis Desi",
    "wof:placetype":"venue"
},
  "geometry": {"coordinates":[145.036362,-37.917339],"type":"Point"}
}