{
  "type": "Feature",
  "properties": {
    "addr:full":"Cnr Victoria & Katherine St Chatswood NSW 2067",
    "addr:postcode":"2067",
    "addr:street":"Cnr",
    "iso:country":"AU",
    "sg:address":"Cnr Victoria & Katherine St",
    "sg:city":"Chatswood",
    "sg:classifiers":[
        {
            "category":"Shopping",
            "subcategory":"Music",
            "type":"Retail Goods"
        }
    ],
    "sg:phone":"+61 2 9411 2900",
    "sg:postcode":"2067",
    "sg:province":"NSW",
    "sg:tags":[
        "instrument",
        "musical"
    ],
    "wof:name":"Gospel Pianos & Organs",
    "wof:placetype":"venue"
},
  "geometry": {"coordinates":[151.183868408,-33.796081543],"type":"Point"}
}