{
  "type": "Feature",
  "properties": {
    "addr:full":"10 Lovett St Scarborough WA 6019",
    "addr:housenumber":"10",
    "addr:postcode":"6019",
    "addr:street":"Lovett St",
    "iso:country":"AU",
    "sg:address":"10 Lovett St",
    "sg:city":"Scarborough",
    "sg:classifiers":[
        {
            "category":"Shopping",
            "subcategory":"Party Supplies",
            "type":"Retail Goods"
        }
    ],
    "sg:phone":"+61 8 9245 6397",
    "sg:postcode":"6019",
    "sg:province":"WA",
    "wof:name":"Party Success",
    "wof:placetype":"venue"
},
  "geometry": {"coordinates":[115.762756348,-31.885269165],"type":"Point"}
}