{
  "type": "Feature",
  "properties": {
    "addr:full":"17 Cousin St Winnellie NT 0820",
    "addr:housenumber":"17",
    "addr:postcode":"nt 0820",
    "addr:street":"Cousin St",
    "iso:country":"AU",
    "sg:address":"17 Cousin St",
    "sg:city":"Winnellie",
    "sg:classifiers":[
        {
            "category":"Utilities",
            "subcategory":"Electric",
            "type":"Services"
        }
    ],
    "sg:phone":"+61 8 8984 3955",
    "sg:postcode":"0820",
    "sg:province":"NT",
    "sg:tags":[
        "electrical",
        "contractor"
    ],
    "wof:name":"Nightcliff Electrical Pty Ltd",
    "wof:placetype":"venue"
},
  "geometry": {"coordinates":[130.87260437,-12.4273843765],"type":"Point"}
}