{
  "type": "Feature",
  "properties": {
    "iso:country":"AU",
    "sg:address":"Tingirana Complex Hastings St",
    "sg:city":"Noosa Heads",
    "sg:classifiers":[
        {
            "category":"Arena",
            "subcategory":"Horse Racetrack",
            "type":"Entertainment"
        }
    ],
    "sg:phone":"+61 7 5455 3399",
    "sg:postcode":"4567",
    "sg:province":"QLD",
    "sg:tags":[
        "retail",
        "swimwear"
    ],
    "wof:name":"Waterlily (Noosa)",
    "wof:placetype":"venue"
},
  "geometry": {"coordinates":[153.086105347,-26.3990192413],"type":"Point"}
}