{
  "type": "Feature",
  "properties": {
    "addr:full":"100 Lower Plenty Rd Rosanna VIC 3084",
    "addr:housenumber":"100",
    "addr:postcode":"3084",
    "addr:street":"Lower Plenty Rd",
    "iso:country":"AU",
    "sg:address":"100 Lower Plenty Rd",
    "sg:city":"Rosanna",
    "sg:classifiers":[
        {
            "category":"Farming",
            "subcategory":"Farm & Veterinary Services",
            "type":"Manufacturing & Wholesale Goods"
        }
    ],
    "sg:phone":"+61 3 9499 4574",
    "sg:postcode":"3084",
    "sg:province":"VIC",
    "sg:tags":[
        "seedsman"
    ],
    "wof:name":"Germinox (Aust) Pty Ltd",
    "wof:placetype":"venue"
},
  "geometry": {"coordinates":[145.064849853,-37.7433547974],"type":"Point"}
}