{
  "type": "Feature",
  "properties": {
    "addr:full":"20 James Pl Adelaide SA 5000",
    "addr:housenumber":"20",
    "addr:postcode":"5000",
    "addr:street":"James Pl",
    "iso:country":"AU",
    "sg:address":"20 James Pl",
    "sg:city":"Adelaide",
    "sg:classifiers":[
        {
            "category":"Shopping",
            "subcategory":"Jewelry",
            "type":"Retail Goods"
        }
    ],
    "sg:phone":"+61 8 8211 9950",
    "sg:postcode":"5000",
    "sg:province":"SA",
    "sg:tags":[
        "jeweller"
    ],
    "wof:name":"Fusion Jewellery",
    "wof:placetype":"venue"
},
  "geometry": {"coordinates":[138.60086059599999,-34.9235801697],"type":"Point"}
}