{
  "type": "Feature",
  "properties": {
    "addr:full":"Unit 2, 8 India St Capalaba QLD 4157",
    "addr:housenumber":"8",
    "addr:postcode":"4157",
    "addr:street":"India St",
    "iso:country":"AU",
    "sg:address":"Unit 2, 8 India St",
    "sg:city":"Capalaba",
    "sg:classifiers":[
        {
            "category":"Building & Trades",
            "subcategory":"Cleaning & Sanitation",
            "type":"Services"
        }
    ],
    "sg:phone":"+61 7 3823 6888",
    "sg:postcode":"4157",
    "sg:province":"QLD",
    "sg:tags":[
        "cleaner",
        "repairer",
        "roof"
    ],
    "wof:name":"Certified Roofing",
    "wof:placetype":"venue"
},
  "geometry": {"coordinates":[153.20208740199999,-27.5303535461],"type":"Point"}
}