{
  "type": "Feature",
  "properties": {
    "addr:full":"488a Main North Rd Blair Athol SA 5084",
    "addr:housenumber":"488a",
    "addr:postcode":"5084",
    "addr:street":"Main North Rd",
    "iso:country":"AU",
    "sg:address":"488a Main North Rd",
    "sg:city":"Blair Athol",
    "sg:classifiers":[
        {
            "category":"Fast Food",
            "type":"Food & Drink"
        }
    ],
    "sg:phone":"+61 8 8262 1732",
    "sg:postcode":"5084",
    "sg:province":"SA",
    "sg:tags":[
        "away",
        "take"
    ],
    "wof:name":"Robert's Snack Bar",
    "wof:placetype":"venue"
},
  "geometry": {"coordinates":[138.60029602,-34.8528022766],"type":"Point"}
}