{
  "type": "Feature",
  "properties": {
    "addr:full":"Tenancy C, Showroom A Development Cnr Robina Town Centre Drv & Christine Ave Robina QLD 4226",
    "addr:postcode":"4226",
    "addr:street":"Robina Town Centre Drv & Christine Ave",
    "iso:country":"AU",
    "sg:address":"Tenancy C, Showroom A Development Cnr Robina Town Centre Drv & Christine Ave",
    "sg:city":"Robina",
    "sg:classifiers":[
        {
            "category":"Fast Food",
            "type":"Food & Drink"
        }
    ],
    "sg:phone":"+61 7 5583 4388",
    "sg:postcode":"4226",
    "sg:province":"QLD",
    "sg:tags":[
        "away",
        "take"
    ],
    "wof:name":"Domino's Pizza",
    "wof:placetype":"venue"
},
  "geometry": {"coordinates":[153.38667297399999,-28.0812683105],"type":"Point"}
}