{
  "type": "Feature",
  "properties": {
    "addr:full":"11 Havelock Ave Coogee NSW 2034",
    "addr:housenumber":"11",
    "addr:postcode":"2034",
    "addr:street":"Havelock Ave",
    "iso:country":"AU",
    "sg:address":"11 Havelock Ave",
    "sg:city":"Coogee",
    "sg:classifiers":[
        {
            "category":"Personal",
            "subcategory":"Beauty Salon",
            "type":"Services"
        }
    ],
    "sg:phone":"+61 2 9665 5735",
    "sg:postcode":"2034",
    "sg:province":"NSW",
    "sg:tags":[
        "hairdresser"
    ],
    "wof:name":"Cazac The Art Of Hair & Makeup",
    "wof:placetype":"venue"
},
  "geometry": {"coordinates":[151.255493164,-33.9243125916],"type":"Point"}
}