{
  "type": "Feature",
  "properties": {
    "addr:full":"150 Arnold St Bendigo VIC 3550",
    "addr:housenumber":"150",
    "addr:postcode":"3550",
    "addr:street":"Arnold St",
    "iso:country":"AU",
    "sg:address":"150 Arnold St",
    "sg:city":"Bendigo",
    "sg:classifiers":[
        {
            "category":"Shopping",
            "subcategory":"Beauty & Cosmetics",
            "type":"Retail Goods"
        }
    ],
    "sg:phone":"+61 3 5443 4514",
    "sg:postcode":"3550",
    "sg:province":"VIC",
    "wof:name":"Arnold St Pharmacy The",
    "wof:placetype":"venue"
},
  "geometry": {"coordinates":[144.28590393100001,-36.7518005371],"type":"Point"}
}