{
  "type": "Feature",
  "properties": {
    "iso:country":"AU",
    "sg:address":"1 Peacock Crt",
    "sg:city":"Coolum Beach",
    "sg:classifiers":[
        {
            "category":"Retail",
            "subcategory":"Driving School",
            "type":"Services"
        }
    ],
    "sg:phone":"+61 7 5446 2927",
    "sg:postcode":"4573",
    "sg:province":"QLD",
    "wof:name":"Pye's Driving School",
    "wof:placetype":"venue"
},
  "geometry": {"coordinates":[153.081284,-26.556028],"type":"Point"}
}