{
  "type": "Feature",
  "properties": {
    "addr:full":"172 Belmore Rd North Riverwood NSW 2210",
    "addr:housenumber":"172",
    "addr:postcode":"2210",
    "addr:street":"Belmore Rd North",
    "iso:country":"AU",
    "sg:address":"172 Belmore Rd North",
    "sg:city":"Riverwood",
    "sg:classifiers":[
        {
            "category":"Retail",
            "subcategory":"Repair Shop",
            "type":"Services"
        }
    ],
    "sg:phone":"+61 2 9584 9673",
    "sg:postcode":"2210",
    "sg:province":"NSW",
    "sg:tags":[
        "stove",
        "part",
        "range"
    ],
    "wof:name":"Repairline F & J Appliances",
    "wof:placetype":"venue"
},
  "geometry": {"coordinates":[151.05183400000001,-33.95359],"type":"Point"}
}