{
  "type": "Feature",
  "properties": {
    "addr:full":"U21/ 121 Kerry Rd Archerfield QLD 4108",
    "addr:housenumber":"121",
    "addr:postcode":"4108",
    "addr:street":"/;Kerry Rd",
    "iso:country":"AU",
    "sg:address":"U21/ 121 Kerry Rd",
    "sg:city":"Archerfield",
    "sg:classifiers":[
        {
            "category":"Building & Trades",
            "subcategory":"Construction",
            "type":"Services"
        }
    ],
    "sg:phone":"+61 7 3274 2283",
    "sg:postcode":"4108",
    "sg:province":"QLD",
    "sg:tags":[
        "plasterboard",
        "plasterer",
        "fixer"
    ],
    "wof:name":"Precision Interior Walls & Ceilings Pty Ltd",
    "wof:placetype":"venue"
},
  "geometry": {"coordinates":[153.03288269000001,-27.5652084351],"type":"Point"}
}