{
  "type": "Feature",
  "properties": {
    "addr:full":"13 Waugh St Chinderah NSW 2487",
    "addr:housenumber":"13",
    "addr:postcode":"2487",
    "addr:street":"Waugh St",
    "iso:country":"AU",
    "sg:address":"13 Waugh St",
    "sg:city":"Chinderah",
    "sg:classifiers":[
        {
            "category":"Farming",
            "subcategory":"Nursery",
            "type":"Manufacturing & Wholesale Goods"
        }
    ],
    "sg:phone":"+61 2 6674 1516",
    "sg:postcode":"2487",
    "sg:province":"NSW",
    "wof:name":"Dragon Trees Australia",
    "wof:placetype":"venue"
},
  "geometry": {"coordinates":[153.559448242,-28.2335033417],"type":"Point"}
}