{
  "type": "Feature",
  "properties": {
    "addr:full":"30 Trade Park Drv Tullamarine VIC 3043",
    "addr:housenumber":"30",
    "addr:postcode":"3043",
    "addr:street":"Trade Park Drv",
    "iso:country":"AU",
    "sg:address":"30 Trade Park Drv",
    "sg:city":"Tullamarine",
    "sg:classifiers":[
        {
            "category":"Banks & Credit Unions",
            "subcategory":"Investment Brokerage",
            "type":"Services"
        }
    ],
    "sg:phone":"+61 3 9335 5525",
    "sg:postcode":"3043",
    "sg:province":"VIC",
    "sg:tags":[
        "shutter",
        "louvre"
    ],
    "wof:name":"Kelligan (Australia) Pty Ltd T/A Sunex Louvre Systems",
    "wof:placetype":"venue"
},
  "geometry": {"coordinates":[144.86984252900001,-37.6936950684],"type":"Point"}
}