{
  "type": "Feature",
  "properties": {
    "addr:full":"Cnr Lyell & Priestley Sts Mittagong NSW 2575",
    "addr:postcode":"2575",
    "iso:country":"AU",
    "sg:address":"Cnr Lyell & Priestley Sts",
    "sg:city":"Mittagong",
    "sg:classifiers":[
        {
            "category":"Professional",
            "subcategory":"Printing & Photocopies",
            "type":"Services"
        }
    ],
    "sg:phone":"+61 2 4871 2683",
    "sg:postcode":"2575",
    "sg:province":"NSW",
    "sg:tags":[
        "photocopying"
    ],
    "wof:name":"John Wheeler Printing",
    "wof:placetype":"venue"
},
  "geometry": {"coordinates":[150.43130493199999,-34.4490127563],"type":"Point"}
}