{
  "type": "Feature",
  "properties": {
    "addr:full":"1st Floor, 1268 High St Armadale VIC 3143",
    "addr:housenumber":"1268",
    "addr:postcode":"3143",
    "addr:street":"High St",
    "iso:country":"AU",
    "sg:address":"1st Floor, 1268 High St",
    "sg:city":"Armadale",
    "sg:classifiers":[
        {
            "category":"Professional",
            "type":"Services"
        }
    ],
    "sg:phone":"+61 3 8508 9777",
    "sg:postcode":"3143",
    "sg:province":"VIC",
    "sg:tags":[
        "message",
        "answering",
        "telephone"
    ],
    "wof:name":"Message Centre The",
    "wof:placetype":"venue"
},
  "geometry": {"coordinates":[145.02877807600001,-37.8566513062],"type":"Point"}
}