{
  "type": "Feature",
  "properties": {
    "iso:country":"AU",
    "sg:address":"559 Hampton St",
    "sg:city":"Hampton",
    "sg:classifiers":[
        {
            "category":"Retail",
            "subcategory":"Repair Shop",
            "type":"Services"
        }
    ],
    "sg:phone":"+61 3 9597 0758",
    "sg:postcode":"3188",
    "sg:province":"VIC",
    "sg:tags":[
        "upholsterer"
    ],
    "wof:name":"Tony's Traditional Upholstery",
    "wof:placetype":"venue"
},
  "geometry": {"coordinates":[145.00360107399999,-37.9307594299],"type":"Point"}
}