{
  "type": "Feature",
  "properties": {
    "iso:country":"AU",
    "sg:address":"1 Kimberley Drv",
    "sg:city":"Chirnside Park",
    "sg:classifiers":[
        {
            "category":"Health Services",
            "subcategory":"Doctor",
            "type":"Services"
        }
    ],
    "sg:phone":"+61 3 9726 4566",
    "sg:postcode":"3116",
    "sg:province":"VIC",
    "sg:tags":[
        "medical",
        "practitioner"
    ],
    "wof:name":"Ward Paul D Dr",
    "wof:placetype":"venue"
},
  "geometry": {"coordinates":[145.311035156,-37.7575454712],"type":"Point"}
}