{
  "type": "Feature",
  "properties": {
    "addr:full":"409 Wyndham St Shepparton VIC 3630",
    "addr:housenumber":"409",
    "addr:postcode":"3630",
    "addr:street":"Wyndham St",
    "iso:country":"AU",
    "sg:address":"409 Wyndham St",
    "sg:city":"Shepparton",
    "sg:classifiers":[
        {
            "category":"Retail",
            "subcategory":"Auto Rental",
            "type":"Services"
        }
    ],
    "sg:phone":"+61 3 5821 2138",
    "sg:postcode":"3630",
    "sg:province":"VIC",
    "sg:tags":[
        "bus",
        "truck"
    ],
    "wof:name":"Hertz",
    "wof:placetype":"venue"
},
  "geometry": {"coordinates":[145.399093628,-36.3828964233],"type":"Point"}
}