{
  "type": "Feature",
  "properties": {
    "addr:full":"Unit 4/ 139 Sandgate Rd Albion QLD 4010",
    "addr:housenumber":"/ 139",
    "addr:postcode":"4010",
    "addr:street":"Sandgate Rd",
    "iso:country":"AU",
    "sg:address":"Unit 4/ 139 Sandgate Rd",
    "sg:city":"Albion",
    "sg:classifiers":[
        {
            "category":"Health Services",
            "subcategory":"Doctor",
            "type":"Services"
        }
    ],
    "sg:phone":"+61 7 3256 0455",
    "sg:postcode":"4010",
    "sg:province":"QLD",
    "sg:tags":[
        "podiatrist"
    ],
    "wof:name":"Footpoint Podiatry",
    "wof:placetype":"venue"
},
  "geometry": {"coordinates":[153.043655395,-27.4346904755],"type":"Point"}
}