{
  "type": "Feature",
  "properties": {
    "iso:country":"AU",
    "sg:address":"Cresswell Rd",
    "sg:city":"Dianella",
    "sg:classifiers":[
        {
            "category":"Education",
            "subcategory":"School",
            "type":"Public Place"
        }
    ],
    "sg:phone":"+61 8 9276 1644",
    "sg:postcode":"6059",
    "sg:province":"WA",
    "sg:tags":[
        "co-educational"
    ],
    "wof:name":"G Korsunski Carmel School & Seeligson Kindergarten INC",
    "wof:placetype":"venue"
},
  "geometry": {"coordinates":[115.861129761,-31.8976764679],"type":"Point"}
}