{
  "type": "Feature",
  "properties": {
    "addr:full":"260 Frankston-Dandenong Rd Dandenong South VIC 3175",
    "addr:housenumber":"260",
    "addr:postcode":"3175",
    "addr:street":"Frankston-Dandenong Rd",
    "iso:country":"AU",
    "sg:address":"260 Frankston-Dandenong Rd",
    "sg:city":"Dandenong South",
    "sg:classifiers":[
        {
            "category":"Autos & Motor Vehicles",
            "subcategory":"Automobile Sales",
            "type":"Retail Goods"
        }
    ],
    "sg:phone":"+61 1800 009 008",
    "sg:postcode":"3175",
    "sg:province":"VIC",
    "sg:tags":[
        "car",
        "new"
    ],
    "wof:name":"Renault",
    "wof:placetype":"venue"
},
  "geometry": {"coordinates":[145.21255493199999,-38.0270614624],"type":"Point"}
}