{
  "type": "Feature",
  "properties": {
    "addr:full":"7 Pauldon Drv Sandy Bay TAS 7005",
    "addr:housenumber":"7",
    "addr:postcode":"7005",
    "addr:street":"Pauldon Drv",
    "iso:country":"AU",
    "sg:address":"7 Pauldon Drv",
    "sg:city":"Sandy Bay",
    "sg:classifiers":[
        {
            "category":"Health Services",
            "subcategory":"Health Practitioner",
            "type":"Services"
        }
    ],
    "sg:phone":"+61 3 6225 4353",
    "sg:postcode":"7005",
    "sg:province":"TAS",
    "sg:tags":[
        "pathologist",
        "speech"
    ],
    "wof:name":"Hobart Speech Pathology",
    "wof:placetype":"venue"
},
  "geometry": {"coordinates":[147.359176636,-42.9241142273],"type":"Point"}
}