{
  "type": "Feature",
  "properties": {
    "iso:country":"AU",
    "sg:address":"3 Florence St",
    "sg:city":"Bridport",
    "sg:classifiers":[
        {
            "category":"Building & Trades",
            "subcategory":"Construction",
            "type":"Services"
        }
    ],
    "sg:phone":"+61 419 846 391",
    "sg:postcode":"7262",
    "sg:province":"TAS",
    "sg:tags":[
        "contractor"
    ],
    "wof:name":"Bingley TJ & J Pty Ltd",
    "wof:placetype":"venue"
},
  "geometry": {"coordinates":[147.40126,-41.014812],"type":"Point"}
}