{
  "type": "Feature",
  "properties": {
    "addr:full":"20 Airy St Wacol QLD 4076",
    "addr:housenumber":"20",
    "addr:postcode":"4076",
    "addr:street":"Airy St",
    "iso:country":"AU",
    "sg:address":"20 Airy St",
    "sg:city":"Wacol",
    "sg:classifiers":[
        {
            "category":"Manufacturing",
            "subcategory":"Building Materials",
            "type":"Manufacturing & Wholesale Goods"
        }
    ],
    "sg:phone":"+61 7 3271 1433",
    "sg:postcode":"4076",
    "sg:province":"QLD",
    "sg:tags":[
        "concrete",
        "product"
    ],
    "wof:name":"Wagners Concrete",
    "wof:placetype":"venue"
},
  "geometry": {"coordinates":[152.924957275,-27.587480545],"type":"Point"}
}