{
  "type": "Feature",
  "properties": {
    "addr:full":"27 Keirath St Henty NSW 2658",
    "addr:housenumber":"27",
    "addr:postcode":"2658",
    "addr:street":"Keirath St",
    "iso:country":"AU",
    "sg:address":"27 Keirath St",
    "sg:city":"Henty",
    "sg:classifiers":[
        {
            "category":"Retail",
            "subcategory":"Repair Shop",
            "type":"Services"
        }
    ],
    "sg:phone":"+61 2 6929 3385",
    "sg:postcode":"2658",
    "sg:province":"NSW",
    "sg:tags":[
        "stove",
        "part",
        "range"
    ],
    "wof:name":"Gabriel Rodney B",
    "wof:placetype":"venue"
},
  "geometry": {"coordinates":[147.033477783,-35.5233421326],"type":"Point"}
}