{
  "type": "Feature",
  "properties": {
    "addr:full":"Flinders St Adelaide SA 5000",
    "addr:postcode":"5000",
    "addr:street":"Flinders St",
    "iso:country":"AU",
    "sg:address":"Flinders St",
    "sg:city":"Adelaide",
    "sg:classifiers":[
        {
            "category":"Health Services",
            "subcategory":"Dentist",
            "type":"Services"
        }
    ],
    "sg:phone":"+61 8 8232 1034",
    "sg:postcode":"5000",
    "sg:province":"SA",
    "wof:name":"Dental-S.A. Dental Service",
    "wof:placetype":"venue"
},
  "geometry": {"coordinates":[138.60093689000001,-34.9271087646],"type":"Point"}
}