{
  "type": "Feature",
  "properties": {
    "addr:full":"23 Dennis Crs South West Rocks NSW 2431",
    "addr:housenumber":"23",
    "addr:postcode":"2431",
    "addr:street":"Dennis Crs South West Rocks",
    "iso:country":"AU",
    "sg:address":"23 Dennis Crs",
    "sg:city":"South West Rocks",
    "sg:classifiers":[
        {
            "category":"Arts & Performance",
            "subcategory":"Dance",
            "type":"Entertainment"
        }
    ],
    "sg:phone":"+61 2 6566 5005",
    "sg:postcode":"2431",
    "sg:province":"NSW",
    "sg:tags":[
        "theatrical",
        "ballet",
        "tuition"
    ],
    "wof:name":"Susan Murray School Of Dance",
    "wof:placetype":"venue"
},
  "geometry": {"coordinates":[153.04188500000001,-30.88685],"type":"Point"}
}