{
  "type": "Feature",
  "properties": {
    "addr:full":"PO Box 656 Manunda QLD 4870",
    "addr:postcode":"4870",
    "iso:country":"AU",
    "sg:address":"PO Box 656",
    "sg:city":"Manunda",
    "sg:classifiers":[
        {
            "category":"Communications",
            "type":"Services"
        }
    ],
    "sg:phone":"+61 417 606 388",
    "sg:postcode":"4870",
    "sg:province":"QLD",
    "sg:tags":[
        "equipment",
        "satellite"
    ],
    "wof:name":"Antennas Today",
    "wof:placetype":"venue"
},
  "geometry": {"coordinates":[145.74989318900001,-16.9132595062],"type":"Point"}
}