{
  "type": "Feature",
  "properties": {
    "addr:full":"17 Lochee St Mosman Park WA 6012",
    "addr:housenumber":"17",
    "addr:postcode":"6012",
    "addr:street":"Lochee St",
    "iso:country":"AU",
    "sg:address":"17 Lochee St",
    "sg:city":"Mosman Park",
    "sg:classifiers":[
        {
            "category":"Fast Food",
            "type":"Food & Drink"
        }
    ],
    "sg:phone":"+61 8 9384 5697",
    "sg:postcode":"6012",
    "sg:province":"WA",
    "sg:tags":[
        "away",
        "take"
    ],
    "wof:name":"Wok Androll",
    "wof:placetype":"venue"
},
  "geometry": {"coordinates":[115.763496399,-32.0090103149],"type":"Point"}
}