{
  "type": "Feature",
  "properties": {
    "addr:full":"2/ 6 Fowler Rd Dandenong VIC 3175",
    "addr:housenumber":"/ 6",
    "addr:postcode":"3175",
    "addr:street":"Fowler Rd",
    "iso:country":"AU",
    "sg:address":"2/ 6 Fowler Rd",
    "sg:city":"Dandenong",
    "sg:classifiers":[
        {
            "category":"Landmark",
            "subcategory":"Fountain",
            "type":"Public Place"
        }
    ],
    "sg:phone":"+61 3 9706 8322",
    "sg:postcode":"3175",
    "sg:province":"VIC",
    "sg:tags":[
        "wholesaler",
        "spring",
        "mfrs"
    ],
    "wof:name":"Road Hug Springs",
    "wof:placetype":"venue"
},
  "geometry": {"coordinates":[145.228393555,-38.0046043396],"type":"Point"}
}