{
  "type": "Feature",
  "properties": {
    "iso:country":"AU",
    "sg:address":"12 Melbourne St",
    "sg:city":"Gosford East",
    "sg:classifiers":[
        {
            "category":"Retail",
            "subcategory":"Repair Shop",
            "type":"Services"
        }
    ],
    "sg:phone":"+61 2 4323 1163",
    "sg:postcode":"2250",
    "sg:province":"NSW",
    "sg:tags":[
        "machine",
        "repairs",
        "part",
        "dryer",
        "washing"
    ],
    "wof:name":"Rob Moffat Appliance Repairs",
    "wof:placetype":"venue"
},
  "geometry": {"coordinates":[151.35429382300001,-33.4407043457],"type":"Point"}
}