{
  "type": "Feature",
  "properties": {
    "addr:full":"Ste2/ 21a Victoria Ave Castle Hill NSW 2154",
    "addr:housenumber":"21a",
    "addr:postcode":"2154",
    "addr:street":"Victoria Ave",
    "iso:country":"AU",
    "sg:address":"Ste2/ 21a Victoria Ave",
    "sg:city":"Castle Hill",
    "sg:classifiers":[
        {
            "category":"Manufacturing",
            "subcategory":"Tools & Machinery",
            "type":"Manufacturing & Wholesale Goods"
        }
    ],
    "sg:phone":"+61 2 9899 7005",
    "sg:postcode":"2154",
    "sg:province":"NSW",
    "wof:name":"Sydney Tools",
    "wof:placetype":"venue"
},
  "geometry": {"coordinates":[150.97947692899999,-33.7297973633],"type":"Point"}
}