{
  "type": "Feature",
  "properties": {
    "iso:country":"AU",
    "sg:address":"PO Box 674",
    "sg:city":"Mulgrave North",
    "sg:classifiers":[
        {
            "category":"Insurance",
            "subcategory":"Insurance Agent",
            "type":"Services"
        }
    ],
    "sg:phone":"+61 3 9558 5429",
    "sg:postcode":"3170",
    "sg:province":"VIC",
    "wof:name":"Palcorp Marketing & Consulting Service",
    "wof:placetype":"venue"
},
  "geometry": {"coordinates":[145.165252686,-37.9214286804],"type":"Point"}
}