{
  "type": "Feature",
  "properties": {
    "addr:full":"Floreat Forum Shopng Cntr, 5 How Tree Pl Floreat WA 6014",
    "addr:housenumber":"5",
    "addr:postcode":"6014",
    "addr:street":"How Tree Pl",
    "iso:country":"AU",
    "sg:address":"Floreat Forum Shopng Cntr, 5 How Tree Pl",
    "sg:city":"Floreat",
    "sg:classifiers":[
        {
            "category":"Sports & Exercise",
            "subcategory":"Gym",
            "type":"Entertainment"
        }
    ],
    "sg:phone":"+61 1300 557 799",
    "sg:postcode":"6014",
    "sg:province":"WA",
    "sg:tags":[
        "health",
        "fitness"
    ],
    "wof:name":"Fitness First Floreat",
    "wof:placetype":"venue"
},
  "geometry": {"coordinates":[115.79232788100001,-31.9389381409],"type":"Point"}
}