{
  "type": "Feature",
  "properties": {
    "addr:full":"26 Tall Tree Rd Lethbridge VIC 3332",
    "addr:housenumber":"26",
    "addr:postcode":"3332",
    "addr:street":"Tall Tree Rd",
    "iso:country":"AU",
    "sg:address":"26 Tall Tree Rd",
    "sg:city":"Lethbridge",
    "sg:classifiers":[
        {
            "category":"Building & Trades",
            "subcategory":"Landscaping Services",
            "type":"Services"
        }
    ],
    "sg:phone":"+61 439 348 003",
    "sg:postcode":"3332",
    "sg:province":"VIC",
    "sg:tags":[
        "fertilizer",
        "spreading",
        "insecticide"
    ],
    "wof:name":"B & M Spreading",
    "wof:placetype":"venue"
},
  "geometry": {"coordinates":[144.126190186,-37.9676856995],"type":"Point"}
}