{
  "type": "Feature",
  "properties": {
    "addr:full":"2/ 16 Vera St Ballina NSW 2478",
    "addr:housenumber":"/ 16",
    "addr:postcode":"2478",
    "addr:street":"Vera St",
    "iso:country":"AU",
    "sg:address":"2/ 16 Vera St",
    "sg:city":"Ballina",
    "sg:classifiers":[
        {
            "category":"Professional",
            "subcategory":"Accounting & Tax Preparation",
            "type":"Services"
        }
    ],
    "sg:phone":"+61 2 6686 9912",
    "sg:postcode":"2478",
    "sg:province":"NSW",
    "sg:tags":[
        "accountant",
        "auditor"
    ],
    "wof:name":"Hauenstein Accounting Services",
    "wof:placetype":"venue"
},
  "geometry": {"coordinates":[153.551437378,-28.859495163],"type":"Point"}
}