{
  "type": "Feature",
  "properties": {
    "addr:full":"80 Orr St Shepparton VIC 3630",
    "addr:housenumber":"80",
    "addr:postcode":"3630",
    "addr:street":"Orr St",
    "iso:country":"AU",
    "sg:address":"80 Orr St",
    "sg:city":"Shepparton",
    "sg:classifiers":[
        {
            "category":"Professional",
            "subcategory":"Accounting & Tax Preparation",
            "type":"Services"
        }
    ],
    "sg:phone":"+61 3 5821 0826",
    "sg:postcode":"3630",
    "sg:province":"VIC",
    "sg:tags":[
        "pregnancy",
        "related",
        "counselling"
    ],
    "wof:name":"Pregnancy Support Service Caroline Chisholm Society",
    "wof:placetype":"venue"
},
  "geometry": {"coordinates":[145.40342712399999,-36.3738899231],"type":"Point"}
}