{
  "type": "Feature",
  "properties": {
    "iso:country":"AU",
    "sg:address":"1 / 23 Dunstan St",
    "sg:city":"Clayton",
    "sg:classifiers":[
        {
            "category":"Recreation",
            "subcategory":"Picnic Area",
            "type":"Entertainment"
        }
    ],
    "sg:phone":"+61 3 9544 3563",
    "sg:postcode":"3168",
    "sg:province":"VIC",
    "sg:tags":[
        "snap",
        "fastener",
        "slide"
    ],
    "wof:name":"Pegasus Print Group",
    "wof:placetype":"venue"
},
  "geometry": {"coordinates":[145.11773681599999,-37.9250297546],"type":"Point"}
}