{
  "type": "Feature",
  "properties": {
    "addr:full":"PO Box 5101 Alice Springs NT 0870",
    "addr:postcode":"nt 0870",
    "iso:country":"AU",
    "sg:address":"PO Box 5101",
    "sg:city":"Alice Springs",
    "sg:classifiers":[
        {
            "category":"Utilities",
            "subcategory":"Refuse",
            "type":"Services"
        }
    ],
    "sg:phone":"+61 8 8952 0966",
    "sg:postcode":"0870",
    "sg:province":"NT",
    "sg:tags":[
        "remover",
        "rubbish"
    ],
    "wof:name":"Dial A Garbo",
    "wof:placetype":"venue"
},
  "geometry": {"coordinates":[133.85372924800001,-23.7290496826],"type":"Point"}
}