{
  "type": "Feature",
  "properties": {
    "iso:country":"AU",
    "sg:address":"PO Box 1229",
    "sg:city":"Aitkenvale BC",
    "sg:classifiers":[
        {
            "category":"Real Estate",
            "subcategory":"Real Estate Agent",
            "type":"Services"
        }
    ],
    "sg:phone":"+61 434 407 069",
    "sg:postcode":"4814",
    "sg:province":"QLD",
    "wof:name":"Prop-R-T SMS",
    "wof:placetype":"venue"
},
  "geometry": {"coordinates":[146.768982,-19.29184],"type":"Point"}
}