{
  "type": "Feature",
  "properties": {
    "addr:full":"52 Queen St Bendigo VIC 3550",
    "addr:housenumber":"52",
    "addr:postcode":"3550",
    "addr:street":"Queen St",
    "iso:country":"AU",
    "sg:address":"52 Queen St",
    "sg:city":"Bendigo",
    "sg:classifiers":[
        {
            "category":"Professional",
            "subcategory":"Employment Agencies",
            "type":"Services"
        }
    ],
    "sg:phone":"+61 13 14 48",
    "sg:postcode":"3550",
    "sg:province":"VIC",
    "sg:tags":[
        "hire",
        "labour",
        "contractor"
    ],
    "wof:name":"Drake",
    "wof:placetype":"venue"
},
  "geometry": {"coordinates":[144.282806397,-36.7575454712],"type":"Point"}
}