{
  "type": "Feature",
  "properties": {
    "addr:full":"99- 107 Manchester Rd Gymea NSW 2227",
    "addr:housenumber":"107",
    "addr:postcode":"2227",
    "addr:street":"99;Manchester Rd",
    "iso:country":"AU",
    "sg:address":"99- 107 Manchester Rd",
    "sg:city":"Gymea",
    "sg:classifiers":[
        {
            "category":"Education",
            "subcategory":"School",
            "type":"Public Place"
        }
    ],
    "sg:phone":"+61 2 9540 4851",
    "sg:postcode":"2227",
    "sg:province":"NSW",
    "wof:name":"Montessori Childrens World Gymea",
    "wof:placetype":"venue"
},
  "geometry": {"coordinates":[151.087890625,-34.0377426147],"type":"Point"}
}