{
  "type": "Feature",
  "properties": {
    "iso:country":"AU",
    "sg:address":"1 Amsted Rd",
    "sg:city":"Bayswater",
    "sg:classifiers":[
        {
            "category":"Autos & Motor Vehicles",
            "subcategory":"Automobile Sales",
            "type":"Retail Goods"
        }
    ],
    "sg:phone":"+61 3 9761 1234",
    "sg:postcode":"3153",
    "sg:province":"VIC",
    "sg:tags":[
        "equipment",
        "trailer"
    ],
    "wof:name":"Eagle Trailers",
    "wof:placetype":"venue"
},
  "geometry": {"coordinates":[145.28474426299999,-37.8449554443],"type":"Point"}
}