{
  "type": "Feature",
  "properties": {
    "iso:country":"AU",
    "sg:address":"Mulherin Drv",
    "sg:city":"Mackay Harbour",
    "sg:classifiers":[
        {
            "category":"Restaurant",
            "type":"Food & Drink"
        }
    ],
    "sg:phone":"+61 7 4955 9400",
    "sg:postcode":"4740",
    "sg:province":"QLD",
    "wof:name":"Clarion Hotel Mackay Marina",
    "wof:placetype":"venue"
},
  "geometry": {"coordinates":[149.22177099999999,-21.114086],"type":"Point"}
}