{
  "type": "Feature",
  "properties": {
    "addr:full":"24 Victoria Ave Somers VIC 3927",
    "addr:housenumber":"24",
    "addr:postcode":"3927",
    "addr:street":"Victoria Ave",
    "iso:country":"AU",
    "sg:address":"24 Victoria Ave",
    "sg:city":"Somers",
    "sg:classifiers":[
        {
            "category":"Professional",
            "subcategory":"Detective & Security Services",
            "type":"Services"
        }
    ],
    "sg:phone":"+61 3 5983 2224",
    "sg:postcode":"3927",
    "sg:province":"VIC",
    "sg:tags":[
        "equipment",
        "window",
        "doors"
    ],
    "wof:name":"Blow - In Home Insulation",
    "wof:placetype":"venue"
},
  "geometry": {"coordinates":[145.154205322,-38.3910140991],"type":"Point"}
}