{
  "type": "Feature",
  "properties": {
    "iso:country":"AU",
    "sg:address":"62 Byron St",
    "sg:city":"Bangalow",
    "sg:classifiers":[
        {
            "category":"Shopping",
            "subcategory":"Antiques",
            "type":"Retail Goods"
        }
    ],
    "sg:phone":"+61 2 6687 1601",
    "sg:postcode":"2479",
    "sg:province":"NSW",
    "wof:name":"Country House Antiques",
    "wof:placetype":"venue"
},
  "geometry": {"coordinates":[153.52597045900001,-28.6862812042],"type":"Point"}
}