{
  "type": "Feature",
  "properties": {
    "addr:full":"Suite 3, 177-181 Moray St South Melbourne VIC 3205",
    "addr:housenumber":"177-181",
    "addr:postcode":"3205",
    "addr:street":"Moray St",
    "iso:country":"AU",
    "sg:address":"Suite 3, 177-181 Moray St",
    "sg:city":"South Melbourne",
    "sg:classifiers":[
        {
            "category":"Personal",
            "subcategory":"Beauty Salon",
            "type":"Services"
        }
    ],
    "sg:phone":"+61 3 9682 9988",
    "sg:postcode":"3205",
    "sg:province":"VIC",
    "sg:tags":[
        "hairdresser"
    ],
    "wof:name":"Ryder",
    "wof:placetype":"venue"
},
  "geometry": {"coordinates":[144.96307400000001,-37.831898],"type":"Point"}
}