{
  "type": "Feature",
  "properties": {
    "iso:country":"AU",
    "sg:address":"34/ 501 Queen St",
    "sg:city":"Brisbane",
    "sg:classifiers":[
        {
            "category":"Professional",
            "subcategory":"Art Services",
            "type":"Services"
        }
    ],
    "sg:phone":"+61 7 3832 8488",
    "sg:postcode":"4000",
    "sg:province":"QLD",
    "sg:tags":[
        "graphic",
        "designer"
    ],
    "sg:website":"http://www.gravitycentral.com.au",
    "wof:name":"Gravity Central",
    "wof:placetype":"venue"
},
  "geometry": {"coordinates":[153.031524658,-27.4635791779],"type":"Point"}
}