{
  "type": "Feature",
  "properties": {
    "addr:full":"152 Flockton St Everton Park QLD 4053",
    "addr:housenumber":"152",
    "addr:postcode":"4053",
    "addr:street":"Flockton St",
    "iso:country":"AU",
    "sg:address":"152 Flockton St",
    "sg:city":"Everton Park",
    "sg:classifiers":[
        {
            "category":"Building & Trades",
            "subcategory":"Construction",
            "type":"Services"
        }
    ],
    "sg:phone":"+61 419 026 584",
    "sg:postcode":"4053",
    "sg:province":"QLD",
    "sg:tags":[
        "renovation",
        "alterations",
        "extension",
        "contractor"
    ],
    "wof:name":"Cappiello Nick",
    "wof:placetype":"venue"
},
  "geometry": {"coordinates":[152.991165161,-27.3945407867],"type":"Point"}
}