{
  "type": "Feature",
  "properties": {
    "addr:full":"686 Sherwood Rd Sherwood QLD 4075",
    "addr:housenumber":"686",
    "addr:postcode":"4075",
    "addr:street":"Sherwood Rd",
    "iso:country":"AU",
    "sg:address":"686 Sherwood Rd",
    "sg:city":"Sherwood",
    "sg:classifiers":[
        {
            "category":"Health Services",
            "subcategory":"Doctor",
            "type":"Services"
        }
    ],
    "sg:phone":"+61 7 3379 2834",
    "sg:postcode":"4075",
    "sg:province":"QLD",
    "sg:tags":[
        "medical",
        "practitioner"
    ],
    "wof:name":"Crawford M G",
    "wof:placetype":"venue"
},
  "geometry": {"coordinates":[152.980377197,-27.5321807861],"type":"Point"}
}