{
  "type": "Feature",
  "properties": {
    "addr:full":"2038 Wanneroo Rd Neerabup WA 6031",
    "addr:housenumber":"2038",
    "addr:postcode":"6031",
    "addr:street":"Wanneroo Rd",
    "iso:country":"AU",
    "sg:address":"2038 Wanneroo Rd",
    "sg:city":"Neerabup",
    "sg:classifiers":[
        {
            "category":"Retail",
            "subcategory":"Auto Repair",
            "type":"Services"
        }
    ],
    "sg:phone":"+61 8 9407 4113",
    "sg:postcode":"6031",
    "sg:province":"WA",
    "sg:tags":[
        "repairer",
        "motor",
        "engineer"
    ],
    "wof:name":"Pinos Mechanical Repairs",
    "wof:placetype":"venue"
},
  "geometry": {"coordinates":[115.74286651600001,-31.6726284027],"type":"Point"}
}