{
  "type": "Feature",
  "properties": {
    "iso:country":"AU",
    "sg:address":"287 Edinburgh Rd",
    "sg:city":"Castlecrag",
    "sg:classifiers":[
        {
            "category":"Professional",
            "subcategory":"Employment Agencies",
            "type":"Services"
        }
    ],
    "sg:phone":"+61 2 9958 7792",
    "sg:postcode":"2068",
    "sg:province":"NSW",
    "sg:tags":[
        "consultant",
        "corrosion"
    ],
    "wof:name":"Elvina Pty Ltd",
    "wof:placetype":"venue"
},
  "geometry": {"coordinates":[151.22625732399999,-33.7985801697],"type":"Point"}
}