{
  "type": "Feature",
  "properties": {
    "addr:full":"148 Invermay Rd Invermay TAS 7248",
    "addr:housenumber":"148",
    "addr:postcode":"7248",
    "addr:street":"Invermay Rd",
    "iso:country":"AU",
    "sg:address":"148 Invermay Rd",
    "sg:city":"Invermay",
    "sg:classifiers":[
        {
            "category":"Wholesale",
            "subcategory":"Stationery",
            "type":"Manufacturing & Wholesale Goods"
        }
    ],
    "sg:phone":"+61 3 6326 1777",
    "sg:postcode":"7248",
    "sg:province":"TAS",
    "sg:tags":[
        "mfrg"
    ],
    "wof:name":"Flying Colours Office National",
    "wof:placetype":"venue"
},
  "geometry": {"coordinates":[147.13331604000001,-41.4134368896],"type":"Point"}
}