{
  "type": "Feature",
  "properties": {
    "addr:full":"51 Sammut St Smithfield NSW 2164",
    "addr:housenumber":"51",
    "addr:postcode":"2164",
    "addr:street":"Sammut St",
    "iso:country":"AU",
    "sg:address":"51 Sammut St",
    "sg:city":"Smithfield",
    "sg:classifiers":[
        {
            "category":"Manufacturing",
            "subcategory":"Metals",
            "type":"Manufacturing & Wholesale Goods"
        }
    ],
    "sg:phone":"+61 2 9756 0090",
    "sg:postcode":"2164",
    "sg:province":"NSW",
    "sg:tags":[
        "sheet",
        "worker"
    ],
    "wof:name":"K S Metal Fabrication",
    "wof:placetype":"venue"
},
  "geometry": {"coordinates":[150.93632507300001,-33.838508606],"type":"Point"}
}