{
  "type": "Feature",
  "properties": {
    "addr:full":"117d Birkdale St Floreat WA 6014",
    "addr:housenumber":"117d",
    "addr:postcode":"6014",
    "addr:street":"Birkdale St",
    "iso:country":"AU",
    "sg:address":"117d Birkdale St",
    "sg:city":"Floreat",
    "sg:classifiers":[
        {
            "category":"Shopping",
            "subcategory":"Clothing, Apparel, & Fashions",
            "type":"Retail Goods"
        }
    ],
    "sg:phone":"+61 8 9287 1661",
    "sg:postcode":"6014",
    "sg:province":"WA",
    "sg:tags":[
        "lady",
        "wear"
    ],
    "wof:name":"Locale Clothing Pty Ltd",
    "wof:placetype":"venue"
},
  "geometry": {"coordinates":[115.80152893099999,-31.9402961731],"type":"Point"}
}