{
  "type": "Feature",
  "properties": {
    "iso:country":"AU",
    "sg:address":"8 Alexander St",
    "sg:city":"Crows Nest",
    "sg:classifiers":[
        {
            "category":"Retail",
            "subcategory":"Auto Repair",
            "type":"Services"
        }
    ],
    "sg:phone":"+61 2 9460 7288",
    "sg:postcode":"1582",
    "sg:province":"NSW",
    "sg:tags":[
        "repairer",
        "motor",
        "engineer"
    ],
    "wof:name":"UltraTune Australia Pty Ltd",
    "wof:placetype":"venue"
},
  "geometry": {"coordinates":[151.20172119099999,-33.827999115],"type":"Point"}
}