{
  "type": "Feature",
  "properties": {
    "addr:full":"7 Newington St Toowoomba City QLD 4350",
    "addr:housenumber":"7",
    "addr:postcode":"4350",
    "addr:street":"Newington St",
    "iso:country":"AU",
    "sg:address":"7 Newington St",
    "sg:city":"Toowoomba City",
    "sg:classifiers":[
        {
            "category":"Freight",
            "type":"Transportation"
        }
    ],
    "sg:phone":"+61 7 4638 1066",
    "sg:postcode":"4350",
    "sg:province":"QLD",
    "sg:tags":[
        "light",
        "carrier"
    ],
    "wof:name":"Followmont Transport Pty Ltd",
    "wof:placetype":"venue"
},
  "geometry": {"coordinates":[151.95465100000001,-27.547569],"type":"Point"}
}