{
  "type": "Feature",
  "properties": {
    "addr:full":"Shop 2, Liardet St Weston ACT 2611",
    "addr:housenumber":"shop 2",
    "addr:postcode":"2611",
    "addr:street":"Liardet St",
    "iso:country":"AU",
    "sg:address":"Shop 2, Liardet St",
    "sg:city":"Weston",
    "sg:classifiers":[
        {
            "category":"Fast Food",
            "type":"Food & Drink"
        }
    ],
    "sg:phone":"+61 2 6288 8439",
    "sg:postcode":"2611",
    "sg:province":"ACT",
    "sg:tags":[
        "away",
        "take"
    ],
    "wof:name":"Kingsley's Chicken",
    "wof:placetype":"venue"
},
  "geometry": {"coordinates":[149.05165100100001,-35.3424682617],"type":"Point"}
}