{
  "type": "Feature",
  "properties": {
    "iso:country":"AU",
    "sg:address":"unit 1 / 4 Textile Ave",
    "sg:city":"Warana",
    "sg:classifiers":[
        {
            "category":"Professional",
            "subcategory":"Accounting & Tax Preparation",
            "type":"Services"
        }
    ],
    "sg:phone":"+61 7 5436 9150",
    "sg:postcode":"4575",
    "sg:province":"QLD",
    "sg:tags":[
        "consultant",
        "taxation"
    ],
    "wof:name":"Tax On The Go",
    "wof:placetype":"venue"
},
  "geometry": {"coordinates":[153.124115,-26.727795],"type":"Point"}
}