{
  "type": "Feature",
  "properties": {
    "addr:full":"172 Oxford St Woollahra NSW 2025",
    "addr:housenumber":"172",
    "addr:postcode":"2025",
    "addr:street":"Oxford St",
    "iso:country":"AU",
    "sg:address":"172 Oxford St",
    "sg:city":"Woollahra",
    "sg:classifiers":[
        {
            "category":"Retail",
            "subcategory":"Funeral Services",
            "type":"Services"
        }
    ],
    "sg:phone":"+61 2 9363 2248",
    "sg:postcode":"2025",
    "sg:province":"NSW",
    "sg:tags":[
        "director"
    ],
    "wof:name":"Chevra Kadisha",
    "wof:placetype":"venue"
},
  "geometry": {"coordinates":[151.240325928,-33.8897705078],"type":"Point"}
}