{
  "type": "Feature",
  "properties": {
    "addr:full":"14 Moseley St Port Hedland WA 6721",
    "addr:housenumber":"14",
    "addr:postcode":"6721",
    "addr:street":"Moseley St",
    "iso:country":"AU",
    "sg:address":"14 Moseley St",
    "sg:city":"Port Hedland",
    "sg:classifiers":[
        {
            "category":"Building & Trades",
            "subcategory":"Construction",
            "type":"Services"
        }
    ],
    "sg:phone":"+61 8 9173 4917",
    "sg:postcode":"6721",
    "sg:province":"WA",
    "sg:tags":[
        "installation",
        "air conditioning"
    ],
    "wof:name":"Complete Climate Control",
    "wof:placetype":"venue"
},
  "geometry": {"coordinates":[118.61750030499999,-20.3065071106],"type":"Point"}
}