{
  "type": "Feature",
  "properties": {
    "iso:country":"AU",
    "sg:address":"42 Adelaide St",
    "sg:city":"Bondi Junction",
    "sg:classifiers":[
        {
            "category":"Health Services",
            "subcategory":"Health Practitioner",
            "type":"Services"
        }
    ],
    "sg:phone":"+61 2 9369 4684",
    "sg:postcode":"2022",
    "sg:province":"NSW",
    "sg:tags":[
        "dietitian"
    ],
    "wof:name":"Cumines Linda APD",
    "wof:placetype":"venue"
},
  "geometry": {"coordinates":[151.251296997,-33.8900527954],"type":"Point"}
}