{
  "type": "Feature",
  "properties": {
    "addr:full":"60 Fourth Ave Maroochydore QLD 4558",
    "addr:housenumber":"60",
    "addr:postcode":"4558",
    "addr:street":"Fourth Ave",
    "iso:country":"AU",
    "sg:address":"60 Fourth Ave",
    "sg:city":"Maroochydore",
    "sg:classifiers":[
        {
            "category":"Sports & Exercise",
            "subcategory":"Gym",
            "type":"Entertainment"
        }
    ],
    "sg:phone":"+61 7 5479 5767",
    "sg:postcode":"4558",
    "sg:province":"QLD",
    "sg:tags":[
        "pilate",
        "method"
    ],
    "wof:name":"Studio Pilates",
    "wof:placetype":"venue"
},
  "geometry": {"coordinates":[153.09950256400001,-26.6595726013],"type":"Point"}
}