{
  "type": "Feature",
  "properties": {
    "addr:full":"12/108D Industrial Rd Oak Flats NSW 2529",
    "addr:housenumber":"12 / 108d",
    "addr:postcode":"2529",
    "addr:street":"Industrial Rd",
    "iso:country":"AU",
    "sg:address":"12/108D Industrial Rd",
    "sg:city":"Oak Flats",
    "sg:classifiers":[
        {
            "category":"Real Estate",
            "subcategory":"Real Estate Operator",
            "type":"Services"
        }
    ],
    "sg:phone":"+61 2 4256 3111",
    "sg:postcode":"2529",
    "sg:province":"NSW",
    "sg:tags":[
        "concrete",
        "pumping"
    ],
    "wof:name":"Wollongong Concrete Pumping Pty Ltd",
    "wof:placetype":"venue"
},
  "geometry": {"coordinates":[150.813995361,-34.569065094],"type":"Point"}
}