{
  "type": "Feature",
  "properties": {
    "addr:full":"11 Manns Ave North Sydney NSW 2060",
    "addr:housenumber":"11",
    "addr:postcode":"2060",
    "addr:street":"Manns Ave",
    "iso:country":"AU",
    "sg:address":"11 Manns Ave",
    "sg:city":"North Sydney",
    "sg:classifiers":[
        {
            "category":"Shopping",
            "subcategory":"Stationery & Office Supplies",
            "type":"Retail Goods"
        }
    ],
    "sg:phone":"+61 2 9955 5484",
    "sg:postcode":"2060",
    "sg:province":"NSW",
    "sg:tags":[
        "equipment",
        "facsimile"
    ],
    "wof:name":"Fax Action",
    "wof:placetype":"venue"
},
  "geometry": {"coordinates":[151.21832275400001,-33.8408432007],"type":"Point"}
}