{
  "type": "Feature",
  "properties": {
    "addr:full":"10 Station St Yarloop WA 6218",
    "addr:housenumber":"10",
    "addr:postcode":"6218",
    "addr:street":"Station St",
    "iso:country":"AU",
    "sg:address":"10 Station St",
    "sg:city":"Yarloop",
    "sg:classifiers":[
        {
            "category":"Travel",
            "subcategory":"Hotels & Motels",
            "type":"Entertainment"
        }
    ],
    "sg:phone":"+61 8 9733 5055",
    "sg:postcode":"6218",
    "sg:province":"WA",
    "sg:tags":[
        "accommodation"
    ],
    "wof:name":"Yarloop Hotel",
    "wof:placetype":"venue"
},
  "geometry": {"coordinates":[115.899117,-32.953911],"type":"Point"}
}