{
  "type": "Feature",
  "properties": {
    "iso:country":"AU",
    "sg:address":"106 Riverside Dr",
    "sg:city":"Tunglebung",
    "sg:classifiers":[
        {
            "category":"Arts & Performance",
            "subcategory":"Art Gallery",
            "type":"Entertainment"
        }
    ],
    "sg:phone":"+61 421 079 088",
    "sg:postcode":"2469",
    "sg:province":"NSW",
    "wof:name":"Adrian Robert Turner Gallery",
    "wof:placetype":"venue"
},
  "geometry": {"coordinates":[153.05351257300001,-28.8628787994],"type":"Point"}
}