{
  "type": "Feature",
  "properties": {
    "iso:country":"AU",
    "sg:address":"10 Paraclete Ave",
    "sg:city":"Mt Stuart",
    "sg:classifiers":[
        {
            "category":"Education",
            "subcategory":"Special Training",
            "type":"Public Place"
        }
    ],
    "sg:phone":"+61 409 367 000",
    "sg:postcode":"7000",
    "sg:province":"TAS",
    "sg:tags":[
        "development"
    ],
    "wof:name":"Emergency Management Solutions",
    "wof:placetype":"venue"
},
  "geometry": {"coordinates":[147.301635742,-42.8740577698],"type":"Point"}
}