{
  "type": "Feature",
  "properties": {
    "iso:country":"AU",
    "sg:address":"PO Box 392",
    "sg:city":"Balmain",
    "sg:classifiers":[
        {
            "category":"Social Services",
            "subcategory":"Child Care",
            "type":"Services"
        }
    ],
    "sg:phone":"+61 2 9810 7912",
    "sg:postcode":"2041",
    "sg:province":"NSW",
    "sg:tags":[
        "support",
        "health"
    ],
    "wof:name":"Luv-Bub",
    "wof:placetype":"venue"
},
  "geometry": {"coordinates":[151.176025,-33.85603],"type":"Point"}
}