{
  "type": "Feature",
  "properties": {
    "addr:full":"18 Violet St Hemmant QLD 4174",
    "addr:housenumber":"18",
    "addr:postcode":"4174",
    "addr:street":"Violet St",
    "iso:country":"AU",
    "sg:address":"18 Violet St",
    "sg:city":"Hemmant",
    "sg:classifiers":[
        {
            "category":"Military Area",
            "subcategory":"Army Base",
            "type":"Public Place"
        }
    ],
    "sg:phone":"+61 7 3390 5821",
    "sg:postcode":"4174",
    "sg:province":"QLD",
    "sg:tags":[
        "repairing",
        "keyboards-tuning",
        "organ"
    ],
    "wof:name":"W J Simon Pierce Pipe Organ Builder",
    "wof:placetype":"venue"
},
  "geometry": {"coordinates":[153.13435363799999,-27.4605445862],"type":"Point"}
}