{
  "type": "Feature",
  "properties": {
    "addr:full":"10 Perry Rd Arcadia NSW 2159",
    "addr:housenumber":"10",
    "addr:postcode":"2159",
    "addr:street":"Perry Rd",
    "iso:country":"AU",
    "sg:address":"10 Perry Rd",
    "sg:city":"Arcadia",
    "sg:classifiers":[
        {
            "category":"Professional",
            "subcategory":"Engineering",
            "type":"Services"
        }
    ],
    "sg:phone":"+61 2 9656 1457",
    "sg:postcode":"2159",
    "sg:province":"NSW",
    "sg:tags":[
        "consulting",
        "engineer"
    ],
    "wof:name":"Donnelly Warwick Pty Ltd",
    "wof:placetype":"venue"
},
  "geometry": {"coordinates":[151.051239014,-33.6102828979],"type":"Point"}
}