{
  "type": "Feature",
  "properties": {
    "addr:full":"Bennett St Wentworthville NSW 2145",
    "addr:postcode":"2145",
    "addr:street":"Bennett St",
    "iso:country":"AU",
    "sg:address":"Bennett St",
    "sg:city":"Wentworthville",
    "sg:classifiers":[
        {
            "category":"Education",
            "subcategory":"School",
            "type":"Public Place"
        }
    ],
    "sg:phone":"+61 2 9631 8442",
    "sg:postcode":"2145",
    "sg:province":"NSW",
    "wof:name":"Our Lady Of Mount Carmel Primary School",
    "wof:placetype":"venue"
},
  "geometry": {"coordinates":[150.969680786,-33.8116874695],"type":"Point"}
}