{
  "type": "Feature",
  "properties": {
    "addr:full":"\"Enterprise Park\" 33 Paramount Drv Wangara WA 6065",
    "addr:housenumber":"33",
    "addr:postcode":"6065",
    "addr:street":"Paramount Drv",
    "iso:country":"AU",
    "sg:address":"\"Enterprise Park\" 33 Paramount Drv",
    "sg:city":"Wangara",
    "sg:classifiers":[
        {
            "category":"Manufacturing",
            "subcategory":"Glass & Minerals",
            "type":"Manufacturing & Wholesale Goods"
        }
    ],
    "sg:phone":"+61 8 9302 2299",
    "sg:postcode":"6065",
    "sg:province":"WA",
    "sg:tags":[
        "exploration"
    ],
    "wof:name":"Mt Magnet Drilling",
    "wof:placetype":"venue"
},
  "geometry": {"coordinates":[115.83128356900001,-31.7906265259],"type":"Point"}
}