{
  "type": "Feature",
  "properties": {
    "addr:full":"27 Bellevue La Glebe NSW 2037",
    "addr:housenumber":"27",
    "addr:postcode":"2037",
    "addr:street":"Bellevue La",
    "iso:country":"AU",
    "sg:address":"27 Bellevue La",
    "sg:city":"Glebe",
    "sg:classifiers":[
        {
            "category":"Government",
            "subcategory":"Court House",
            "type":"Public Place"
        }
    ],
    "sg:phone":"+61 2 9660 0178",
    "sg:postcode":"2037",
    "sg:province":"NSW",
    "sg:tags":[
        "personal",
        "marriage",
        "family",
        "counselling"
    ],
    "wof:name":"Relationship Counselling & Psychotherapy Service",
    "wof:placetype":"venue"
},
  "geometry": {"coordinates":[151.191482544,-33.8778686523],"type":"Point"}
}