{
  "type": "Feature",
  "properties": {
    "addr:full":"12 Queen St Campbelltown NSW 2560",
    "addr:housenumber":"12",
    "addr:postcode":"2560",
    "addr:street":"Queen St",
    "iso:country":"AU",
    "sg:address":"12 Queen St",
    "sg:city":"Campbelltown",
    "sg:classifiers":[
        {
            "category":"Manufacturing",
            "subcategory":"Food",
            "type":"Manufacturing & Wholesale Goods"
        }
    ],
    "sg:phone":"+61 2 4625 4521",
    "sg:postcode":"2560",
    "sg:province":"NSW",
    "sg:tags":[
        "function",
        "catering"
    ],
    "wof:name":"Barn Restaurant The",
    "wof:placetype":"venue"
},
  "geometry": {"coordinates":[150.82247924800001,-34.0576477051],"type":"Point"}
}