{
  "type": "Feature",
  "properties": {
    "addr:full":"24 Eunamara Rd Mandurah WA 6210",
    "addr:housenumber":"24",
    "addr:postcode":"6210",
    "addr:street":"Eunamara Rd",
    "iso:country":"AU",
    "sg:address":"24 Eunamara Rd",
    "sg:city":"Mandurah",
    "sg:classifiers":[
        {
            "category":"Building & Trades",
            "subcategory":"Construction",
            "type":"Services"
        }
    ],
    "sg:phone":"+61 8 9535 6047",
    "sg:postcode":"6210",
    "sg:province":"WA",
    "sg:tags":[
        "contractor"
    ],
    "wof:name":"Glossop R J & Co Pty Ltd",
    "wof:placetype":"venue"
},
  "geometry": {"coordinates":[115.698578,-32.557579],"type":"Point"}
}