{
  "type": "Feature",
  "properties": {
    "iso:country":"AU",
    "sg:address":"Warrego Hwy",
    "sg:city":"Roma",
    "sg:classifiers":[
        {
            "category":"Mining & Drilling",
            "type":"Manufacturing & Wholesale Goods"
        }
    ],
    "sg:phone":"+61 7 4622 2543",
    "sg:postcode":"4455",
    "sg:province":"QLD",
    "sg:tags":[
        "boring",
        "contractor"
    ],
    "wof:name":"Johnson Drilling",
    "wof:placetype":"venue"
},
  "geometry": {"coordinates":[148.79913330100001,-26.5750217438],"type":"Point"}
}