{
  "type": "Feature",
  "properties": {
    "addr:full":"657 Port Rush Rd Glen Osmond SA 5064",
    "addr:housenumber":"657",
    "addr:postcode":"5064",
    "addr:street":"Port Rush Rd",
    "iso:country":"AU",
    "sg:address":"657 Port Rush Rd",
    "sg:city":"Glen Osmond",
    "sg:classifiers":[
        {
            "category":"Personal",
            "subcategory":"Beauty Salon",
            "type":"Services"
        }
    ],
    "sg:phone":"+61 8 8338 1188",
    "sg:postcode":"5064",
    "sg:province":"SA",
    "sg:tags":[
        "hairdresser"
    ],
    "wof:name":"Rachel Louise Hair Design",
    "wof:placetype":"venue"
},
  "geometry": {"coordinates":[138.64405822800001,-34.9622116089],"type":"Point"}
}