{
  "type": "Feature",
  "properties": {
    "iso:country":"AU",
    "sg:address":"10 Torres St",
    "sg:city":"Kurnell",
    "sg:classifiers":[
        {
            "category":"Fast Food",
            "type":"Food & Drink"
        }
    ],
    "sg:phone":"+61 2 9668 9559",
    "sg:postcode":"2231",
    "sg:province":"NSW",
    "sg:tags":[
        "away",
        "take"
    ],
    "wof:name":"Captains Pies & Cakes The",
    "wof:placetype":"venue"
},
  "geometry": {"coordinates":[151.209518433,-34.0110321045],"type":"Point"}
}