{
  "type": "Feature",
  "properties": {
    "addr:full":"1/ 36 Leigh St Adelaide SA 5000",
    "addr:housenumber":"/ 36",
    "addr:postcode":"5000",
    "addr:street":"Leigh St",
    "iso:country":"AU",
    "sg:address":"1/ 36 Leigh St",
    "sg:city":"Adelaide",
    "sg:classifiers":[
        {
            "category":"Travel",
            "subcategory":"Travel Agent",
            "type":"Entertainment"
        }
    ],
    "sg:phone":"+61 13 18 66",
    "sg:postcode":"5000",
    "sg:province":"SA",
    "sg:tags":[
        "consultant"
    ],
    "wof:name":"Flight Centre",
    "wof:placetype":"venue"
},
  "geometry": {"coordinates":[138.597488403,-34.9242210388],"type":"Point"}
}