{
  "type": "Feature",
  "properties": {
    "addr:full":"Shop 11 Golden Grove Village Shopping Centre Golden Grove Village SA 5125",
    "addr:housenumber":"shop 11",
    "addr:postcode":"5125",
    "addr:street":"Golden Grove;Golden Grove",
    "iso:country":"AU",
    "sg:address":"Shop 11 Golden Grove Village Shopping Centre",
    "sg:city":"Golden Grove Village",
    "sg:classifiers":[
        {
            "category":"Food & Beverages",
            "subcategory":"Fruits & Vegetables",
            "type":"Retail Goods"
        }
    ],
    "sg:phone":"+61 8 8289 4000",
    "sg:postcode":"5125",
    "sg:province":"SA",
    "sg:tags":[
        "greengrocer",
        "fruiterer"
    ],
    "wof:name":"Adelaide Fresh Fruiter",
    "wof:placetype":"venue"
},
  "geometry": {"coordinates":[138.71096800000001,-34.765877],"type":"Point"}
}