{
  "type": "Feature",
  "properties": {
    "addr:full":"3 Beach St Grange SA 5022",
    "addr:housenumber":"3",
    "addr:postcode":"5022",
    "addr:street":"Beach St",
    "iso:country":"AU",
    "sg:address":"3 Beach St",
    "sg:city":"Grange",
    "sg:classifiers":[
        {
            "category":"Personal",
            "subcategory":"Skin Care",
            "type":"Services"
        }
    ],
    "sg:phone":"+61 8 8235 2679",
    "sg:postcode":"5022",
    "sg:province":"SA",
    "sg:tags":[
        "information",
        "treatment",
        "smoker"
    ],
    "wof:name":"Abbotts Psychologist Hypnotherapist",
    "wof:placetype":"venue"
},
  "geometry": {"coordinates":[138.491744995,-34.9052085876],"type":"Point"}
}