{
  "type": "Feature",
  "properties": {
    "addr:full":"1316 Toorak Rd Camberwell VIC 3124",
    "addr:housenumber":"1316",
    "addr:postcode":"3124",
    "addr:street":"Toorak Rd",
    "iso:country":"AU",
    "sg:address":"1316 Toorak Rd",
    "sg:city":"Camberwell",
    "sg:classifiers":[
        {
            "category":"Health Services",
            "subcategory":"Health Practitioner",
            "type":"Services"
        }
    ],
    "sg:phone":"+61 3 9889 4666",
    "sg:postcode":"3124",
    "sg:province":"VIC",
    "sg:tags":[
        "naturopath"
    ],
    "wof:name":"Steel Erica",
    "wof:placetype":"venue"
},
  "geometry": {"coordinates":[145.09016418499999,-37.8498954773],"type":"Point"}
}