{
  "type": "Feature",
  "properties": {
    "addr:full":"Level 8, 10 Spring St Sydney NSW 2000",
    "addr:housenumber":"10",
    "addr:postcode":"2000",
    "addr:street":"Spring St",
    "iso:country":"AU",
    "sg:address":"Level 8, 10 Spring St",
    "sg:city":"Sydney",
    "sg:classifiers":[
        {
            "category":"Banks & Credit Unions",
            "subcategory":"Financial Services",
            "type":"Services"
        }
    ],
    "sg:phone":"+61 2 9232 7500",
    "sg:postcode":"2000",
    "sg:province":"NSW",
    "sg:tags":[
        "financier"
    ],
    "wof:name":"Investors Mutual Limited",
    "wof:placetype":"venue"
},
  "geometry": {"coordinates":[151.209274292,-33.864692688],"type":"Point"}
}