{
  "type": "Feature",
  "properties": {
    "addr:full":"361 Lonsdale St Dandenong VIC 3175",
    "addr:housenumber":"361",
    "addr:postcode":"3175",
    "addr:street":"Lonsdale St",
    "iso:country":"AU",
    "sg:address":"361 Lonsdale St",
    "sg:city":"Dandenong",
    "sg:classifiers":[
        {
            "category":"Personal",
            "subcategory":"Beauty Salon",
            "type":"Services"
        }
    ],
    "sg:phone":"+61 3 9793 9177",
    "sg:postcode":"3175",
    "sg:province":"VIC",
    "wof:name":"Barley Bronze Beauty Therapy",
    "wof:placetype":"venue"
},
  "geometry": {"coordinates":[145.21383667000001,-37.9850883484],"type":"Point"}
}