{
  "type": "Feature",
  "properties": {
    "addr:full":"14 Collie St Fremantle WA 6160",
    "addr:housenumber":"14",
    "addr:postcode":"6160",
    "addr:street":"Collie St",
    "iso:country":"AU",
    "sg:address":"14 Collie St",
    "sg:city":"Fremantle",
    "sg:classifiers":[
        {
            "category":"Real Estate",
            "subcategory":"Surveying",
            "type":"Services"
        }
    ],
    "sg:phone":"+61 8 9335 8665",
    "sg:postcode":"6160",
    "sg:province":"WA",
    "sg:tags":[
        "map",
        "mapping"
    ],
    "wof:name":"The Chart and Map Shop",
    "wof:placetype":"venue"
},
  "geometry": {"coordinates":[115.746323,-32.056477],"type":"Point"}
}