{
  "type": "Feature",
  "properties": {
    "iso:country":"AU",
    "sg:address":"130 Como Rd",
    "sg:city":"Oyster Bay",
    "sg:classifiers":[
        {
            "category":"Health Services",
            "subcategory":"Doctor",
            "type":"Services"
        }
    ],
    "sg:phone":"+61 2 9528 6480",
    "sg:postcode":"2225",
    "sg:province":"NSW",
    "sg:tags":[
        "medical",
        "practitioner"
    ],
    "wof:name":"Oyster Bay/Como Family Practice",
    "wof:placetype":"venue"
},
  "geometry": {"coordinates":[151.08102417000001,-34.0066337585],"type":"Point"}
}