{
  "type": "Feature",
  "properties": {
    "iso:country":"AU",
    "sg:address":"25 Herbert Ave",
    "sg:city":"Hoppers Crossing",
    "sg:classifiers":[
        {
            "category":"Professional",
            "subcategory":"Art Services",
            "type":"Services"
        }
    ],
    "sg:phone":"+61 3 9749 6989",
    "sg:postcode":"3029",
    "sg:province":"VIC",
    "sg:tags":[
        "decorator",
        "painter"
    ],
    "wof:name":"Wyndham Painting",
    "wof:placetype":"venue"
},
  "geometry": {"coordinates":[144.698441,-37.8769],"type":"Point"}
}