{
  "type": "Feature",
  "properties": {
    "iso:country":"AU",
    "sg:address":"25a Tenth St",
    "sg:city":"Bowden",
    "sg:classifiers":[
        {
            "category":"Manufacturing",
            "subcategory":"Metals",
            "type":"Manufacturing & Wholesale Goods"
        }
    ],
    "sg:phone":"+61 8 8340 3466",
    "sg:postcode":"5007",
    "sg:province":"SA",
    "sg:tags":[
        "metallurgist"
    ],
    "wof:name":"Optimet Laboratories",
    "wof:placetype":"venue"
},
  "geometry": {"coordinates":[138.57992553700001,-34.9015235901],"type":"Point"}
}