{
  "type": "Feature",
  "properties": {
    "iso:country":"AU",
    "sg:address":"21 Kennedy St",
    "sg:city":"Kingston",
    "sg:classifiers":[
        {
            "category":"Travel",
            "subcategory":"Hotels & Motels",
            "type":"Entertainment"
        }
    ],
    "sg:phone":"+61 2 6295 1949",
    "sg:postcode":"2604",
    "sg:province":"ACT",
    "sg:tags":[
        "pub"
    ],
    "wof:name":"The B Bar",
    "wof:placetype":"venue"
},
  "geometry": {"coordinates":[149.140792847,-35.3164176941],"type":"Point"}
}