{
  "type": "Feature",
  "properties": {
    "iso:country":"AU",
    "sg:address":"Level 4, 55 McLachlan St",
    "sg:city":"Fortitude Valley",
    "sg:classifiers":[
        {
            "category":"Professional",
            "subcategory":"Art Services",
            "type":"Services"
        }
    ],
    "sg:phone":"+61 7 3666 0077",
    "sg:postcode":"4006",
    "sg:province":"QLD",
    "sg:tags":[
        "graphic",
        "designer"
    ],
    "wof:name":"Fugu Design",
    "wof:placetype":"venue"
},
  "geometry": {"coordinates":[153.03697204599999,-27.4580230713],"type":"Point"}
}