{
  "type": "Feature",
  "properties": {
    "iso:country":"AU",
    "sg:address":"Shop 33 Greensborough Shopping Centre",
    "sg:city":"Greensborough",
    "sg:classifiers":[
        {
            "category":"Shopping",
            "subcategory":"Clothing, Apparel, & Fashions",
            "type":"Retail Goods"
        }
    ],
    "sg:phone":"+61 3 9434 3426",
    "sg:postcode":"3088",
    "sg:province":"VIC",
    "sg:tags":[
        "lady",
        "wear"
    ],
    "wof:name":"Jacqui E",
    "wof:placetype":"venue"
},
  "geometry": {"coordinates":[145.09190368599999,-37.7033882141],"type":"Point"}
}