{
  "type": "Feature",
  "properties": {
    "addr:full":"4 MacNeil Pl Kambah ACT 2902",
    "addr:housenumber":"4",
    "addr:postcode":"2902",
    "addr:street":"Macneil Pl",
    "iso:country":"AU",
    "sg:address":"4 MacNeil Pl",
    "sg:city":"Kambah",
    "sg:classifiers":[
        {
            "category":"Organizations",
            "subcategory":"Professional Association",
            "type":"Services"
        }
    ],
    "sg:phone":"+61 2 6231 9399",
    "sg:postcode":"2902",
    "sg:province":"ACT",
    "sg:tags":[
        "organisation",
        "business"
    ],
    "wof:name":"Australia South Pacific Centre",
    "wof:placetype":"venue"
},
  "geometry": {"coordinates":[149.034057617,-35.3905639648],"type":"Point"}
}