{
  "type": "Feature",
  "properties": {
    "iso:country":"AU",
    "sg:address":"Shop 2 95 Partridge St",
    "sg:city":"Glenelg South",
    "sg:classifiers":[
        {
            "category":"Wholesale",
            "subcategory":"Seafood",
            "type":"Manufacturing & Wholesale Goods"
        }
    ],
    "sg:phone":"+61 8 8376 9233",
    "sg:postcode":"5045",
    "sg:province":"SA",
    "sg:tags":[
        "fish"
    ],
    "wof:name":"Seafood Indulgence on Glenelg",
    "wof:placetype":"venue"
},
  "geometry": {"coordinates":[138.518326,-34.989555],"type":"Point"}
}