{
  "type": "Feature",
  "properties": {
    "addr:full":"4 Annan Pl Templestowe VIC 3106",
    "addr:housenumber":"4",
    "addr:postcode":"3106",
    "addr:street":"Annan Pl",
    "iso:country":"AU",
    "sg:address":"4 Annan Pl",
    "sg:city":"Templestowe",
    "sg:classifiers":[
        {
            "category":"Retail",
            "subcategory":"Event Space",
            "type":"Services"
        }
    ],
    "sg:phone":"+61 3 9846 7124",
    "sg:postcode":"3106",
    "sg:province":"VIC",
    "sg:tags":[
        "function",
        "organiser"
    ],
    "wof:name":"Cato Club",
    "wof:placetype":"venue"
},
  "geometry": {"coordinates":[145.16215515100001,-37.7625389099],"type":"Point"}
}