{
  "type": "Feature",
  "properties": {
    "iso:country":"AU",
    "sg:address":"428 Ryans Rd",
    "sg:city":"Diamond Creek",
    "sg:classifiers":[
        {
            "category":"Professional",
            "subcategory":"Art Services",
            "type":"Services"
        }
    ],
    "sg:phone":"+61 3 9438 2094",
    "sg:postcode":"3089",
    "sg:province":"VIC",
    "sg:tags":[
        "graphic",
        "designer"
    ],
    "wof:name":"Contemporary Imaging & Desgin",
    "wof:placetype":"venue"
},
  "geometry": {"coordinates":[145.144226,-37.679115],"type":"Point"}
}