{
  "type": "Feature",
  "properties": {
    "iso:country":"AU",
    "sg:address":"62 Wilson St",
    "sg:city":"Horsham",
    "sg:classifiers":[
        {
            "category":"Personal",
            "subcategory":"Beauty Salon",
            "type":"Services"
        }
    ],
    "sg:phone":"+61 3 5382 2851",
    "sg:postcode":"3400",
    "sg:province":"VIC",
    "sg:tags":[
        "hairdresser"
    ],
    "wof:name":"Heavy Hair Unisex Salon",
    "wof:placetype":"venue"
},
  "geometry": {"coordinates":[142.19891357399999,-36.7167739868],"type":"Point"}
}