{
  "type": "Feature",
  "properties": {
    "iso:country":"AU",
    "sg:address":"PO Box 230",
    "sg:city":"Kangaroo Ground",
    "sg:classifiers":[
        {
            "category":"Professional",
            "subcategory":"Computer Services",
            "type":"Services"
        }
    ],
    "sg:phone":"+61 3 9719 7337",
    "sg:postcode":"3097",
    "sg:province":"VIC",
    "sg:tags":[
        "technical",
        "support"
    ],
    "wof:name":"Bytecorp",
    "wof:placetype":"venue"
},
  "geometry": {"coordinates":[145.215667725,-37.6913490295],"type":"Point"}
}