{
  "type": "Feature",
  "properties": {
    "addr:full":"306- 308 Malvern Rd Prahran VIC 3181",
    "addr:housenumber":"308",
    "addr:postcode":"3181",
    "addr:street":"Malvern Rd",
    "iso:country":"AU",
    "sg:address":"306- 308 Malvern Rd",
    "sg:city":"Prahran",
    "sg:classifiers":[
        {
            "category":"Health Services",
            "subcategory":"Health Practitioner",
            "type":"Services"
        }
    ],
    "sg:phone":"+61 3 9521 2733",
    "sg:postcode":"3181",
    "sg:province":"VIC",
    "sg:tags":[
        "hypnotherapy"
    ],
    "wof:name":"Anne Sinclair",
    "wof:placetype":"venue"
},
  "geometry": {"coordinates":[144.997116089,-37.8473739624],"type":"Point"}
}