{
  "type": "Feature",
  "properties": {
    "addr:full":"Shp6/ 73 Magellan St Lismore NSW 2480",
    "addr:housenumber":"73",
    "addr:postcode":"2480",
    "addr:street":"Magellan St",
    "iso:country":"AU",
    "sg:address":"Shp6/ 73 Magellan St",
    "sg:city":"Lismore",
    "sg:classifiers":[
        {
            "category":"Real Estate",
            "subcategory":"Real Estate Agent",
            "type":"Services"
        }
    ],
    "sg:phone":"+61 2 6622 4622",
    "sg:postcode":"2480",
    "sg:province":"NSW",
    "wof:name":"Major Perspectives",
    "wof:placetype":"venue"
},
  "geometry": {"coordinates":[153.27734375,-28.8096885681],"type":"Point"}
}