{
  "type": "Feature",
  "properties": {
    "iso:country":"AU",
    "sg:address":"472 Little River Rd",
    "sg:city":"Ensay",
    "sg:classifiers":[
        {
            "category":"Museum",
            "type":"Entertainment"
        }
    ],
    "sg:phone":"+61 3 5157 3377",
    "sg:postcode":"3895",
    "sg:province":"VIC",
    "wof:name":"Australian Printing Museum Pty Ltd The",
    "wof:placetype":"venue"
},
  "geometry": {"coordinates":[147.83505249000001,-37.3315544128],"type":"Point"}
}