{
  "type": "Feature",
  "properties": {
    "addr:full":"Shop 10 Cherrybrook Shopping Centre Cherrybrook NSW 2126",
    "addr:housenumber":"shop 10",
    "addr:postcode":"2126",
    "iso:country":"AU",
    "sg:address":"Shop 10 Cherrybrook Shopping Centre",
    "sg:city":"Cherrybrook",
    "sg:classifiers":[
        {
            "category":"Shopping",
            "subcategory":"Clothing, Apparel, & Fashions",
            "type":"Retail Goods"
        }
    ],
    "sg:phone":"+61 2 9875 1790",
    "sg:postcode":"2126",
    "sg:province":"NSW",
    "sg:tags":[
        "lady",
        "wear"
    ],
    "wof:name":"Wombat Boutiques",
    "wof:placetype":"venue"
},
  "geometry": {"coordinates":[151.049758911,-33.7338485718],"type":"Point"}
}