{
  "type": "Feature",
  "properties": {
    "addr:full":"9 Sorrell Pl Queanbeyan NSW 2620",
    "addr:housenumber":"9",
    "addr:postcode":"2620",
    "addr:street":"Sorrell Pl",
    "iso:country":"AU",
    "sg:address":"9 Sorrell Pl",
    "sg:city":"Queanbeyan",
    "sg:classifiers":[
        {
            "category":"Home & Garden",
            "subcategory":"Carpets & Floor Coverings",
            "type":"Retail Goods"
        }
    ],
    "sg:phone":"+61 2 6297 3762",
    "sg:postcode":"2620",
    "sg:province":"NSW",
    "sg:tags":[
        "layer",
        "planner"
    ],
    "wof:name":"Hately R P",
    "wof:placetype":"venue"
},
  "geometry": {"coordinates":[149.236404419,-35.3634681702],"type":"Point"}
}