{
  "type": "Feature",
  "properties": {
    "iso:country":"AU",
    "sg:address":"17 Allambie La",
    "sg:city":"Rasmussen",
    "sg:classifiers":[
        {
            "category":"Education",
            "subcategory":"Kindergarten",
            "type":"Public Place"
        }
    ],
    "sg:phone":"+61 7 4789 0600",
    "sg:postcode":"4815",
    "sg:province":"QLD",
    "sg:tags":[
        "pre-schools"
    ],
    "wof:name":"St. Anna's Early Education Centre",
    "wof:placetype":"venue"
},
  "geometry": {"coordinates":[146.728928,-19.367256],"type":"Point"}
}