{
  "type": "Feature",
  "properties": {
    "addr:full":"49- 51 Gregory Tce Spring Hill QLD 4000",
    "addr:housenumber":"51",
    "addr:postcode":"4000",
    "addr:street":"Gregory Tce",
    "iso:country":"AU",
    "sg:address":"49- 51 Gregory Tce",
    "sg:city":"Spring Hill",
    "sg:classifiers":[
        {
            "category":"Social Services",
            "subcategory":"Retirement Home",
            "type":"Services"
        }
    ],
    "sg:phone":"+61 7 3839 5168",
    "sg:postcode":"4000",
    "sg:province":"QLD",
    "sg:tags":[
        "decoration",
        "supplier",
        "contractor"
    ],
    "wof:name":"Balloons Galore",
    "wof:placetype":"venue"
},
  "geometry": {"coordinates":[153.02386474599999,-27.4625301361],"type":"Point"}
}