{
  "type": "Feature",
  "properties": {
    "iso:country":"AU",
    "sg:address":"2 Spinifex St",
    "sg:city":"Cairnlea",
    "sg:classifiers":[
        {
            "category":"Building & Trades",
            "subcategory":"Construction",
            "type":"Services"
        }
    ],
    "sg:phone":"+61 413 419 313",
    "sg:postcode":"3023",
    "sg:province":"VIC",
    "sg:tags":[
        "contractor"
    ],
    "wof:name":"Sircon Homes",
    "wof:placetype":"venue"
},
  "geometry": {"coordinates":[144.77795399999999,-37.753651],"type":"Point"}
}