{
  "type": "Feature",
  "properties": {
    "addr:full":"Shop 5 Smiths Lake NSW 2428",
    "addr:housenumber":"shop 5",
    "addr:postcode":"2428",
    "addr:street":"Smiths Lake",
    "iso:country":"AU",
    "sg:address":"Shop 5",
    "sg:city":"Smiths Lake",
    "sg:classifiers":[
        {
            "category":"Personal",
            "subcategory":"Beauty Salon",
            "type":"Services"
        }
    ],
    "sg:phone":"+61 2 6554 4600",
    "sg:postcode":"2428",
    "sg:province":"NSW",
    "sg:tags":[
        "hairdresser"
    ],
    "wof:name":"Kirsti's Hair & Beauty Salon",
    "wof:placetype":"venue"
},
  "geometry": {"coordinates":[152.52981600000001,-32.184563],"type":"Point"}
}