{
  "type": "Feature",
  "properties": {
    "addr:full":"59 Smith St Naracoorte SA 5271",
    "addr:housenumber":"59",
    "addr:postcode":"5271",
    "addr:street":"Smith St",
    "iso:country":"AU",
    "sg:address":"59 Smith St",
    "sg:city":"Naracoorte",
    "sg:classifiers":[
        {
            "category":"Real Estate",
            "subcategory":"Real Estate Agent",
            "type":"Services"
        }
    ],
    "sg:phone":"+61 8 8762 0088",
    "sg:postcode":"5271",
    "sg:province":"SA",
    "wof:name":"Overall & Brammer Real Estate Pty Ltd",
    "wof:placetype":"venue"
},
  "geometry": {"coordinates":[140.73951700000001,-36.956654],"type":"Point"}
}