{
  "type": "Feature",
  "properties": {
    "iso:country":"AU",
    "sg:address":"Wommara Ave",
    "sg:city":"Belmont North",
    "sg:classifiers":[
        {
            "category":"Building & Trades",
            "subcategory":"Cleaning & Sanitation",
            "type":"Services"
        }
    ],
    "sg:phone":"+61 2 4945 5010",
    "sg:postcode":"2280",
    "sg:province":"NSW",
    "sg:tags":[
        "industrial",
        "commercial",
        "contractor"
    ],
    "wof:name":"McCumiskey S & P Cleaning & Maintenance Service",
    "wof:placetype":"venue"
},
  "geometry": {"coordinates":[151.66732788100001,-33.0216217041],"type":"Point"}
}