{
  "type": "Feature",
  "properties": {
    "addr:full":"63 Boundary Rd Dubbo NSW 2830",
    "addr:housenumber":"63",
    "addr:postcode":"2830",
    "addr:street":"Boundary Rd",
    "iso:country":"AU",
    "sg:address":"63 Boundary Rd",
    "sg:city":"Dubbo",
    "sg:classifiers":[
        {
            "category":"Fast Food",
            "type":"Food & Drink"
        }
    ],
    "sg:phone":"+61 2 6882 3332",
    "sg:postcode":"2830",
    "sg:province":"NSW",
    "sg:tags":[
        "away",
        "take"
    ],
    "wof:name":"Grove Takeaway The",
    "wof:placetype":"venue"
},
  "geometry": {"coordinates":[148.605560303,-32.2672462463],"type":"Point"}
}