{
  "type": "Feature",
  "properties": {
    "iso:country":"AU",
    "sg:address":"Beerwah Market Pl",
    "sg:city":"Beerwah",
    "sg:classifiers":[
        {
            "category":"Health Services",
            "subcategory":"Optometrist",
            "type":"Services"
        }
    ],
    "sg:phone":"+61 7 5494 0300",
    "sg:postcode":"4519",
    "sg:province":"QLD",
    "wof:name":"Premier Optique",
    "wof:placetype":"venue"
},
  "geometry": {"coordinates":[152.96725499999999,-26.811001],"type":"Point"}
}