{
  "type": "Feature",
  "properties": {
    "addr:full":"58b Greenhill Rd Wayville SA 5034",
    "addr:housenumber":"58b",
    "addr:postcode":"5034",
    "addr:street":"Greenhill Rd",
    "iso:country":"AU",
    "sg:address":"58b Greenhill Rd",
    "sg:city":"Wayville",
    "sg:classifiers":[
        {
            "category":"Banks & Credit Unions",
            "subcategory":"Financial Services",
            "type":"Services"
        }
    ],
    "sg:phone":"+61 8 8373 5691",
    "sg:postcode":"5034",
    "sg:province":"SA",
    "sg:tags":[
        "advisory",
        "planning",
        "retirement"
    ],
    "wof:name":"Financial Guidance For Women Pty Ltd T/As Your Money Centre",
    "wof:placetype":"venue"
},
  "geometry": {"coordinates":[138.59315490700001,-34.9418373108],"type":"Point"}
}