{
  "type": "Feature",
  "properties": {
    "iso:country":"AU",
    "sg:address":"RMB 78- 76 Vineyard Rd",
    "sg:city":"Mulgoa",
    "sg:classifiers":[
        {
            "category":"Building & Trades",
            "subcategory":"Construction",
            "type":"Services"
        }
    ],
    "sg:phone":"+61 418 977 479",
    "sg:postcode":"2745",
    "sg:province":"NSW",
    "sg:tags":[
        "contractor"
    ],
    "wof:name":"Mulgoa Valley Bricklaying",
    "wof:placetype":"venue"
},
  "geometry": {"coordinates":[150.67842102,-33.8379554749],"type":"Point"}
}