{
  "type": "Feature",
  "properties": {
    "addr:full":"Office 1, 2 Market St Merimbula NSW 2548",
    "addr:housenumber":"2",
    "addr:postcode":"2548",
    "addr:street":"Market St",
    "iso:country":"AU",
    "sg:address":"Office 1, 2 Market St",
    "sg:city":"Merimbula",
    "sg:classifiers":[
        {
            "category":"Professional",
            "subcategory":"Detective & Security Services",
            "type":"Services"
        }
    ],
    "sg:phone":"+61 2 6495 1616",
    "sg:postcode":"2548",
    "sg:province":"NSW",
    "sg:tags":[
        "consultant",
        "system"
    ],
    "wof:name":"Transcash Security",
    "wof:placetype":"venue"
},
  "geometry": {"coordinates":[149.910812378,-36.8894424438],"type":"Point"}
}