{
  "type": "Feature",
  "properties": {
    "addr:full":"104 Ferntree Gully Rd Oakleigh VIC 3166",
    "addr:housenumber":"104",
    "addr:postcode":"3166",
    "addr:street":"Ferntree Gully Rd",
    "iso:country":"AU",
    "sg:address":"104 Ferntree Gully Rd",
    "sg:city":"Oakleigh",
    "sg:classifiers":[
        {
            "category":"Sports & Exercise",
            "subcategory":"Gym",
            "type":"Entertainment"
        }
    ],
    "sg:phone":"+61 3 9548 8787",
    "sg:postcode":"3166",
    "sg:province":"VIC",
    "sg:tags":[
        "health",
        "fitness"
    ],
    "wof:name":"adam & eve natural fitness",
    "wof:placetype":"venue"
},
  "geometry": {"coordinates":[145.111053467,-37.8975410461],"type":"Point"}
}