{
  "type": "Feature",
  "properties": {
    "addr:full":"29 Cherry St Ballina NSW 2478",
    "addr:housenumber":"29",
    "addr:postcode":"2478",
    "addr:street":"Cherry St",
    "iso:country":"AU",
    "sg:address":"29 Cherry St",
    "sg:city":"Ballina",
    "sg:classifiers":[
        {
            "category":"Personal",
            "subcategory":"Beauty Salon",
            "type":"Services"
        }
    ],
    "sg:phone":"+61 2 6686 8886",
    "sg:postcode":"2478",
    "sg:province":"NSW",
    "sg:tags":[
        "hairdresser"
    ],
    "wof:name":"acutabove#",
    "wof:placetype":"venue"
},
  "geometry": {"coordinates":[153.561157227,-28.8714504242],"type":"Point"}
}