{
  "type": "Feature",
  "properties": {
    "addr:full":"Shop 1097 Westfield Shoppingtown The Kingsway Miranda NSW 2228",
    "addr:housenumber":"1097",
    "addr:postcode":"2228",
    "addr:street":"Westfield Shoppingtown The Kingsway",
    "iso:country":"AU",
    "sg:address":"Shop 1097 Westfield Shoppingtown The Kingsway",
    "sg:city":"Miranda",
    "sg:classifiers":[
        {
            "category":"Professional",
            "subcategory":"Computer Services",
            "type":"Services"
        }
    ],
    "sg:phone":"+61 2 9531 0110",
    "sg:postcode":"2228",
    "sg:province":"NSW",
    "sg:tags":[
        "package",
        "software"
    ],
    "wof:name":"Electronics Boutique",
    "wof:placetype":"venue"
},
  "geometry": {"coordinates":[151.102493286,-34.033908844],"type":"Point"}
}