{
  "type": "Feature",
  "properties": {
    "iso:country":"AU",
    "sg:address":"PO Box 158",
    "sg:city":"Buderim",
    "sg:classifiers":[
        {
            "category":"Organizations",
            "subcategory":"Community Association",
            "type":"Services"
        }
    ],
    "sg:phone":"+61 7 5445 3310",
    "sg:postcode":"4556",
    "sg:province":"QLD",
    "sg:tags":[
        "club",
        "senior",
        "citizen"
    ],
    "wof:name":"Association of Independent Retirees Inc.",
    "wof:placetype":"venue"
},
  "geometry": {"coordinates":[153.09310913100001,-26.6773891449],"type":"Point"}
}