{
  "type": "Feature",
  "properties": {
    "addr:full":"Zamia St Northcliffe WA 6262",
    "addr:postcode":"6262",
    "addr:street":"Zamia St",
    "iso:country":"AU",
    "sg:address":"Zamia St",
    "sg:city":"Northcliffe",
    "sg:classifiers":[
        {
            "category":"Education",
            "subcategory":"School",
            "type":"Public Place"
        }
    ],
    "sg:phone":"+61 8 9776 7055",
    "sg:postcode":"6262",
    "sg:province":"WA",
    "sg:tags":[
        "state",
        "except",
        "nsw"
    ],
    "wof:name":"Northcliffe District High School",
    "wof:placetype":"venue"
},
  "geometry": {"coordinates":[116.117446899,-34.6330566406],"type":"Point"}
}