{
  "type": "Feature",
  "properties": {
    "iso:country":"AU",
    "sg:address":"87 Malta St",
    "sg:city":"Fairfield",
    "sg:classifiers":[
        {
            "category":"Communications",
            "subcategory":"Television Station",
            "type":"Services"
        }
    ],
    "sg:phone":"+61 2 9755 7222",
    "sg:postcode":"2165",
    "sg:province":"NSW",
    "sg:tags":[
        "wholesaler",
        "wire",
        "mfrs",
        "electric",
        "cable"
    ],
    "wof:name":"Newtech Cnc Pty Ltd",
    "wof:placetype":"venue"
},
  "geometry": {"coordinates":[150.975463867,-33.8745689392],"type":"Point"}
}