{
  "type": "Feature",
  "properties": {
    "addr:full":"82 Byamee St Dapto NSW 2530",
    "addr:housenumber":"82",
    "addr:postcode":"2530",
    "addr:street":"Byamee St",
    "iso:country":"AU",
    "sg:address":"82 Byamee St",
    "sg:city":"Dapto",
    "sg:classifiers":[
        {
            "category":"Real Estate",
            "subcategory":"Real Estate Agent",
            "type":"Services"
        }
    ],
    "sg:phone":"+61 410 484 220",
    "sg:postcode":"2530",
    "sg:province":"NSW",
    "sg:tags":[
        "handyman's",
        "equipment",
        "hire",
        "builders",
        "contractor"
    ],
    "wof:name":"Cameron's Concrete Pumping",
    "wof:placetype":"venue"
},
  "geometry": {"coordinates":[150.797607422,-34.495388031],"type":"Point"}
}