{
  "type": "Feature",
  "properties": {
    "addr:full":"20 Payneham Rd Stepney SA 5069",
    "addr:housenumber":"20",
    "addr:postcode":"5069",
    "addr:street":"Payneham Rd",
    "iso:country":"AU",
    "sg:address":"20 Payneham Rd",
    "sg:city":"Stepney",
    "sg:classifiers":[
        {
            "category":"Professional",
            "subcategory":"Computer Services",
            "type":"Services"
        }
    ],
    "sg:phone":"+61 8 8362 3561",
    "sg:postcode":"5069",
    "sg:province":"SA",
    "sg:tags":[
        "package",
        "software"
    ],
    "wof:name":"Etico Business Solutions Pty Ltd",
    "wof:placetype":"venue"
},
  "geometry": {"coordinates":[138.62391662600001,-34.9144897461],"type":"Point"}
}