{
  "type": "Feature",
  "properties": {
    "addr:full":"284 Frankston-Flinders Rd Frankston South VIC 3199",
    "addr:housenumber":"284",
    "addr:postcode":"3199",
    "addr:street":"Frankston-Flinders Rd",
    "iso:country":"AU",
    "sg:address":"284 Frankston-Flinders Rd",
    "sg:city":"Frankston South",
    "sg:classifiers":[
        {
            "category":"Communications",
            "subcategory":"Film & Video Production",
            "type":"Services"
        }
    ],
    "sg:phone":"+61 3 5971 4567",
    "sg:postcode":"3199",
    "sg:province":"VIC",
    "sg:tags":[
        "dvd",
        "library"
    ],
    "wof:name":"Video Ezy",
    "wof:placetype":"venue"
},
  "geometry": {"coordinates":[145.14039611800001,-38.1828384399],"type":"Point"}
}