{
  "type": "Feature",
  "properties": {
    "addr:full":"Ennismore Denneys Rd Wycheproof VIC 3527",
    "addr:postcode":"3527",
    "addr:street":"Ennismore Denneys Rd",
    "iso:country":"AU",
    "sg:address":"Ennismore Denneys Rd",
    "sg:city":"Wycheproof",
    "sg:classifiers":[
        {
            "category":"Farming",
            "subcategory":"Farm",
            "type":"Manufacturing & Wholesale Goods"
        }
    ],
    "sg:phone":"+61 3 5493 7374",
    "sg:postcode":"3527",
    "sg:province":"VIC",
    "sg:tags":[
        "farmer"
    ],
    "wof:name":"Denney A D",
    "wof:placetype":"venue"
},
  "geometry": {"coordinates":[143.225494,-36.08107],"type":"Point"}
}