{
  "type": "Feature",
  "properties": {
    "iso:country":"AU",
    "sg:address":"129 Elizabeth St",
    "sg:city":"Brisbane",
    "sg:classifiers":[
        {
            "category":"Shopping",
            "subcategory":"Clothing, Apparel, & Fashions",
            "type":"Retail Goods"
        }
    ],
    "sg:phone":"+61 7 3229 2488",
    "sg:postcode":"4000",
    "sg:province":"QLD",
    "sg:tags":[
        "uniform"
    ],
    "wof:name":"NNT Uniforms",
    "wof:placetype":"venue"
},
  "geometry": {"coordinates":[153.02619934099999,-27.470407486],"type":"Point"}
}