{
  "type": "Feature",
  "properties": {
    "iso:country":"AU",
    "sg:address":"Cnr Svendson & Sturt Sts",
    "sg:city":"Westcourt",
    "sg:classifiers":[
        {
            "category":"Retail",
            "subcategory":"Auto Repair",
            "type":"Services"
        }
    ],
    "sg:phone":"+61 7 4031 3755",
    "sg:postcode":"4870",
    "sg:province":"QLD",
    "sg:tags":[
        "repairer",
        "motor",
        "engineer"
    ],
    "wof:name":"Auto Ezy Service Centre",
    "wof:placetype":"venue"
},
  "geometry": {"coordinates":[145.75497436500001,-16.9359893799],"type":"Point"}
}