{
  "type": "Feature",
  "properties": {
    "addr:full":"Dukes Highway Service Rd Bordertown SA 5268",
    "addr:postcode":"5268",
    "addr:street":"Dukes Highway Service Rd",
    "iso:country":"AU",
    "sg:address":"Dukes Highway Service Rd",
    "sg:city":"Bordertown",
    "sg:phone":"+61 1800 039 069",
    "sg:postcode":"5268",
    "sg:province":"SA",
    "wof:name":"S & K Pfeiffer Agencies",
    "wof:placetype":"venue"
},
  "geometry": {"coordinates":[140.784988,-36.308887],"type":"Point"}
}