{
  "type": "Feature",
  "properties": {
    "addr:full":"Shop 103 Epping Plz Epping VIC 3076",
    "addr:housenumber":"103",
    "addr:postcode":"3076",
    "addr:street":"Epping Plz",
    "iso:country":"AU",
    "sg:address":"Shop 103",
    "sg:city":"Epping Plz Epping",
    "sg:classifiers":[
        {
            "category":"Shopping",
            "subcategory":"Shoes",
            "type":"Retail Goods"
        }
    ],
    "sg:phone":"+61 3 9401 2099",
    "sg:postcode":"3076",
    "sg:province":"VIC",
    "sg:tags":[
        "footwear"
    ],
    "wof:name":"Kearney Shoes",
    "wof:placetype":"venue"
},
  "geometry": {"coordinates":[145.02813720699999,-37.6259613037],"type":"Point"}
}