{
  "type": "Feature",
  "properties": {
    "addr:full":"181 Faraday Rd Padstow NSW 2211",
    "addr:housenumber":"181",
    "addr:postcode":"2211",
    "addr:street":"Faraday Rd",
    "iso:country":"AU",
    "sg:address":"181 Faraday Rd",
    "sg:city":"Padstow",
    "sg:classifiers":[
        {
            "category":"Building & Trades",
            "subcategory":"Plumbing",
            "type":"Services"
        }
    ],
    "sg:phone":"+61 2 9771 9954",
    "sg:postcode":"2211",
    "sg:province":"NSW",
    "sg:tags":[
        "plumber",
        "gasfitters"
    ],
    "wof:name":"Precision Plumbing Contractors Pty Ltd",
    "wof:placetype":"venue"
},
  "geometry": {"coordinates":[151.02683999999999,-33.96471],"type":"Point"}
}