{
  "type": "Feature",
  "properties": {
    "addr:full":"279 Treasure Rd Welshpool WA 6106",
    "addr:housenumber":"279",
    "addr:postcode":"6106",
    "addr:street":"Treasure Rd",
    "iso:country":"AU",
    "sg:address":"279 Treasure Rd",
    "sg:city":"Welshpool",
    "sg:classifiers":[
        {
            "category":"Utilities",
            "subcategory":"Natural Gas",
            "type":"Services"
        }
    ],
    "sg:phone":"+61 8 9407 9757",
    "sg:postcode":"6106",
    "sg:province":"WA",
    "sg:tags":[
        "supplier"
    ],
    "wof:name":"Gas Guys",
    "wof:placetype":"venue"
},
  "geometry": {"coordinates":[115.948348999,-31.9931564331],"type":"Point"}
}