{
  "type": "Feature",
  "properties": {
    "addr:full":"PO Box 71 Narrabundah ACT 2604",
    "addr:postcode":"2604",
    "iso:country":"AU",
    "sg:address":"PO Box 71",
    "sg:city":"Narrabundah",
    "sg:classifiers":[
        {
            "category":"Building & Trades",
            "subcategory":"Construction",
            "type":"Services"
        }
    ],
    "sg:phone":"+61 405 298 506",
    "sg:postcode":"2604",
    "sg:province":"ACT",
    "sg:tags":[
        "repair",
        "maintenance",
        "contractor"
    ],
    "wof:name":"Needham Building Services & Maintenance",
    "wof:placetype":"venue"
},
  "geometry": {"coordinates":[149.15237426799999,-35.3312416077],"type":"Point"}
}