{
  "type": "Feature",
  "properties": {
    "iso:country":"AU",
    "sg:address":"72 Westfield Drv",
    "sg:city":"Westbrook",
    "sg:classifiers":[
        {
            "category":"Building & Trades",
            "subcategory":"Construction",
            "type":"Services"
        }
    ],
    "sg:phone":"+61 7 4630 6066",
    "sg:postcode":"4350",
    "sg:province":"QLD",
    "sg:tags":[
        "earth",
        "excavating",
        "moving",
        "contractor"
    ],
    "wof:name":"A Ace Bobcat Service",
    "wof:placetype":"venue"
},
  "geometry": {"coordinates":[151.869705,-27.602497],"type":"Point"}
}