{
  "type": "Feature",
  "properties": {
    "addr:full":"72 Westfield Drv Westbrook QLD 4350",
    "addr:housenumber":"72",
    "addr:postcode":"4350",
    "addr:street":"Westfield Drv",
    "iso:country":"AU",
    "sg:address":"72 Westfield Drv",
    "sg:city":"Westbrook",
    "sg:classifiers":[
        {
            "category":"Building & Trades",
            "subcategory":"Construction",
            "type":"Services"
        }
    ],
    "sg:phone":"+61 7 4630 6066",
    "sg:postcode":"4350",
    "sg:province":"QLD",
    "sg:tags":[
        "earth",
        "excavating",
        "moving",
        "contractor"
    ],
    "wof:name":"A Ace Bobcat Service",
    "wof:placetype":"venue"
},
  "geometry": {"coordinates":[151.86970500000001,-27.602497],"type":"Point"}
}