{
  "type": "Feature",
  "properties": {
    "iso:country":"AU",
    "sg:address":"Cnr Main Rd West & West Esplanade",
    "sg:city":"St Albans",
    "sg:classifiers":[
        {
            "category":"Professional",
            "subcategory":"Computer Services",
            "type":"Services"
        }
    ],
    "sg:phone":"+61 3 9310 7203",
    "sg:postcode":"3021",
    "sg:province":"VIC",
    "sg:tags":[
        "repairs",
        "upgrade",
        "equipment"
    ],
    "wof:name":"Amexcom Pty Ltd",
    "wof:placetype":"venue"
},
  "geometry": {"coordinates":[144.778946,-37.741882],"type":"Point"}
}