{
  "type": "Feature",
  "properties": {
    "addr:full":"21 Jaybell St Salisbury QLD 4107",
    "addr:housenumber":"21",
    "addr:postcode":"4107",
    "addr:street":"Jaybell St",
    "iso:country":"AU",
    "sg:address":"21 Jaybell St",
    "sg:city":"Salisbury",
    "sg:classifiers":[
        {
            "category":"Home & Garden",
            "subcategory":"Furniture",
            "type":"Retail Goods"
        }
    ],
    "sg:phone":"+61 7 3849 3576",
    "sg:postcode":"4107",
    "sg:province":"QLD",
    "sg:tags":[
        "business"
    ],
    "wof:name":"Commercial Furniture Supplies",
    "wof:placetype":"venue"
},
  "geometry": {"coordinates":[153.037765503,-27.5428981781],"type":"Point"}
}