{
  "type": "Feature",
  "properties": {
    "addr:full":"Unit 1, Level 1, 563 Bilsen Rd Geebung QLD 4034",
    "addr:housenumber":"563",
    "addr:postcode":"4034",
    "addr:street":"Bilsen Rd",
    "iso:country":"AU",
    "sg:address":"Unit 1, Level 1, 563 Bilsen Rd",
    "sg:city":"Geebung",
    "sg:classifiers":[
        {
            "category":"Professional",
            "subcategory":"Testing Lab",
            "type":"Services"
        }
    ],
    "sg:phone":"+61 7 3865 6666",
    "sg:postcode":"4034",
    "sg:province":"QLD",
    "sg:tags":[
        "soil",
        "investigation"
    ],
    "wof:name":"Environmental Earth Sciences",
    "wof:placetype":"venue"
},
  "geometry": {"coordinates":[153.05766299999999,-27.363018],"type":"Point"}
}