{
  "type": "Feature",
  "properties": {
    "iso:country":"AU",
    "sg:address":"Yamba Rd",
    "sg:city":"Yamba",
    "sg:classifiers":[
        {
            "category":"Arena",
            "subcategory":"Indoor Arena",
            "type":"Entertainment"
        }
    ],
    "sg:phone":"+61 2 6646 8673",
    "sg:postcode":"2464",
    "sg:province":"NSW",
    "sg:tags":[
        "club",
        "angling"
    ],
    "wof:name":"Grafton District Anglers Club",
    "wof:placetype":"venue"
},
  "geometry": {"coordinates":[153.32157898,-29.4285964966],"type":"Point"}
}