{
  "type": "Feature",
  "properties": {
    "addr:full":"2/ 28 Sawtell Rd Sawtell NSW 2452",
    "addr:housenumber":"/ 28",
    "addr:postcode":"2452",
    "addr:street":"Sawtell Rd",
    "iso:country":"AU",
    "sg:address":"2/ 28 Sawtell Rd",
    "sg:city":"Sawtell",
    "sg:classifiers":[
        {
            "category":"Travel",
            "subcategory":"Travel Agent",
            "type":"Entertainment"
        }
    ],
    "sg:phone":"+61 2 6658 1835",
    "sg:postcode":"2452",
    "sg:province":"NSW",
    "sg:tags":[
        "consultant"
    ],
    "wof:name":"Toormina- Sawtell Travel Service",
    "wof:placetype":"venue"
},
  "geometry": {"coordinates":[153.10032699999999,-30.352232],"type":"Point"}
}