{
  "type": "Feature",
  "properties": {
    "iso:country":"AU",
    "sg:address":"George Rd",
    "sg:city":"Salamander Bay",
    "sg:classifiers":[
        {
            "category":"Home & Garden",
            "subcategory":"Building Materials",
            "type":"Retail Goods"
        }
    ],
    "sg:phone":"+61 2 4982 0422",
    "sg:postcode":"2317",
    "sg:province":"NSW",
    "sg:tags":[
        "pre-mixed",
        "concrete"
    ],
    "wof:name":"Boral Country-Concrete & Quarries",
    "wof:placetype":"venue"
},
  "geometry": {"coordinates":[152.07695,-32.727329],"type":"Point"}
}