{
  "type": "Feature",
  "properties": {
    "addr:full":"GPO Box 9939 Melbourne VIC 3001",
    "addr:postcode":"3001",
    "iso:country":"AU",
    "sg:address":"GPO Box 9939",
    "sg:city":"Melbourne",
    "sg:classifiers":[
        {
            "category":"Insurance",
            "subcategory":"Hazard Insurance",
            "type":"Services"
        }
    ],
    "sg:phone":"+61 3 9679 0533",
    "sg:postcode":"3001",
    "sg:province":"VIC",
    "sg:tags":[
        "fire",
        "accident",
        "marine"
    ],
    "wof:name":"Internet Insurance Brokers(Australia)Pty Ltd",
    "wof:placetype":"venue"
},
  "geometry": {"coordinates":[144.963165283,-37.814250946],"type":"Point"}
}