{
  "type": "Feature",
  "properties": {
    "addr:full":"Lvl1/ 66 Hindley St Adelaide SA 5000",
    "addr:postcode":"5000",
    "addr:street":"St",
    "iso:country":"AU",
    "sg:address":"Lvl1/ 66 Hindley St",
    "sg:city":"Adelaide",
    "sg:classifiers":[
        {
            "category":"Arts & Performance",
            "subcategory":"Art Gallery",
            "type":"Entertainment"
        }
    ],
    "sg:phone":"+61 8 8410 0008",
    "sg:postcode":"5000",
    "sg:province":"SA",
    "wof:name":"Avalon Gallery",
    "wof:placetype":"venue"
},
  "geometry": {"coordinates":[138.59788513199999,-34.9229393005],"type":"Point"}
}