{
  "type": "Feature",
  "properties": {
    "iso:country":"AU",
    "sg:address":"226 Beveridge St",
    "sg:city":"Swan Hill",
    "sg:classifiers":[
        {
            "category":"Professional",
            "subcategory":"Management & Consulting",
            "type":"Services"
        }
    ],
    "sg:phone":"+61 3 5453 3220",
    "sg:postcode":"3585",
    "sg:province":"NSW",
    "sg:tags":[
        "consultant",
        "energy"
    ],
    "wof:name":"Alastair McDonald Design & Drafting",
    "wof:placetype":"venue"
},
  "geometry": {"coordinates":[143.55894499999999,-35.342545],"type":"Point"}
}