{
  "type": "Feature",
  "properties": {
    "iso:country":"AU",
    "sg:address":"34 Condamine St",
    "sg:city":"Dalby",
    "sg:classifiers":[
        {
            "category":"Professional",
            "subcategory":"Accounting & Tax Preparation",
            "type":"Services"
        }
    ],
    "sg:phone":"+61 7 4672 4555",
    "sg:postcode":"4405",
    "sg:province":"QLD",
    "sg:tags":[
        "accountant",
        "auditor"
    ],
    "wof:name":"Lever Accountants",
    "wof:placetype":"venue"
},
  "geometry": {"coordinates":[151.26596069300001,-27.1786327362],"type":"Point"}
}