{
  "type": "Feature",
  "properties": {
    "iso:country":"AU",
    "sg:address":"55 Morotai Pde",
    "sg:city":"Heidelberg West",
    "sg:classifiers":[
        {
            "category":"Building & Trades",
            "subcategory":"Plumbing",
            "type":"Services"
        }
    ],
    "sg:phone":"+61 3 9457 5509",
    "sg:postcode":"3081",
    "sg:province":"VIC",
    "sg:tags":[
        "plumber",
        "gasfitters"
    ],
    "wof:name":"J & B Plumbing",
    "wof:placetype":"venue"
},
  "geometry": {"coordinates":[145.04327392600001,-37.7445411682],"type":"Point"}
}