{
  "type": "Feature",
  "properties": {
    "addr:full":"73 Belmont Rd Kenwick WA 6107",
    "addr:housenumber":"73",
    "addr:postcode":"6107",
    "addr:street":"Belmont Rd",
    "iso:country":"AU",
    "sg:address":"73 Belmont Rd",
    "sg:city":"Kenwick",
    "sg:classifiers":[
        {
            "category":"Deli",
            "type":"Food & Drink"
        }
    ],
    "sg:phone":"+61 8 9459 2438",
    "sg:postcode":"6107",
    "sg:province":"WA",
    "sg:tags":[
        "delicatessen"
    ],
    "wof:name":"Kenwick Village Deli",
    "wof:placetype":"venue"
},
  "geometry": {"coordinates":[115.98204040500001,-32.0341835022],"type":"Point"}
}