{
  "type": "Feature",
  "properties": {
    "addr:full":"Weebar Rd Drouin VIC 3818",
    "addr:postcode":"3818",
    "addr:street":"Weebar Rd",
    "iso:country":"AU",
    "sg:address":"Weebar Rd",
    "sg:city":"Drouin",
    "sg:classifiers":[
        {
            "category":"Farming",
            "subcategory":"Farm",
            "type":"Manufacturing & Wholesale Goods"
        }
    ],
    "sg:phone":"+61 3 5625 1865",
    "sg:postcode":"3818",
    "sg:province":"VIC",
    "sg:tags":[
        "farmer"
    ],
    "wof:name":"Walters G D & A K",
    "wof:placetype":"venue"
},
  "geometry": {"coordinates":[145.85522499999999,-38.142399],"type":"Point"}
}