{
  "type": "Feature",
  "properties": {
    "iso:country":"AU",
    "sg:address":"Cnr Ashbourton St & Warrego St Albion Park",
    "sg:city":"Albion Park",
    "sg:classifiers":[
        {
            "category":"Education",
            "subcategory":"Kindergarten",
            "type":"Public Place"
        }
    ],
    "sg:phone":"+61 2 4257 5681",
    "sg:postcode":"2527",
    "sg:province":"NSW",
    "sg:tags":[
        "pre-schools"
    ],
    "wof:name":"Mt Terry Pre-School",
    "wof:placetype":"venue"
},
  "geometry": {"coordinates":[150.77914428700001,-34.5892486572],"type":"Point"}
}