{
  "type": "Feature",
  "properties": {
    "iso:country":"AU",
    "sg:address":"134 Hampshire Rd",
    "sg:city":"Sunshine",
    "sg:classifiers":[
        {
            "category":"Retail",
            "subcategory":"Auto Repair",
            "type":"Services"
        }
    ],
    "sg:phone":"+61 3 9311 2386",
    "sg:postcode":"3020",
    "sg:province":"VIC",
    "sg:tags":[
        "beater",
        "painter",
        "panel"
    ],
    "wof:name":"Hampshire Panels",
    "wof:placetype":"venue"
},
  "geometry": {"coordinates":[144.832077,-37.788197],"type":"Point"}
}