{
  "type": "Feature",
  "properties": {
    "addr:full":"23 Lorilet St Peregian Beach QLD 4573",
    "addr:housenumber":"23",
    "addr:postcode":"4573",
    "addr:street":"Lorilet St",
    "iso:country":"AU",
    "sg:address":"23 Lorilet St",
    "sg:city":"Peregian Beach",
    "sg:classifiers":[
        {
            "category":"Home & Garden",
            "subcategory":"Building Materials",
            "type":"Retail Goods"
        }
    ],
    "sg:phone":"+61 7 5448 1913",
    "sg:postcode":"4573",
    "sg:province":"QLD",
    "sg:tags":[
        "decorative",
        "coating"
    ],
    "wof:name":"Blackburn P & M J",
    "wof:placetype":"venue"
},
  "geometry": {"coordinates":[153.097275,-26.46225],"type":"Point"}
}