{
  "type": "Feature",
  "properties": {
    "addr:full":"23 Grant St Fingal TAS 7214",
    "addr:housenumber":"23",
    "addr:postcode":"7214",
    "addr:street":"Grant St",
    "iso:country":"AU",
    "sg:address":"23 Grant St",
    "sg:city":"Fingal",
    "sg:classifiers":[
        {
            "category":"Communications",
            "type":"Services"
        }
    ],
    "sg:phone":"+61 3 6374 2274",
    "sg:postcode":"7214",
    "sg:province":"TAS",
    "sg:tags":[
        "equipment",
        "satellite"
    ],
    "wof:name":"North East Communications & Electronic Services",
    "wof:placetype":"venue"
},
  "geometry": {"coordinates":[147.96919299999999,-41.639759],"type":"Point"}
}