{
  "type": "Feature",
  "properties": {
    "addr:full":"306 Windsor St Richmond NSW 2753",
    "addr:housenumber":"306",
    "addr:postcode":"2753",
    "addr:street":"Windsor St",
    "iso:country":"AU",
    "sg:address":"306 Windsor St",
    "sg:city":"Richmond",
    "sg:classifiers":[
        {
            "category":"Real Estate",
            "subcategory":"Real Estate Agent",
            "type":"Services"
        }
    ],
    "sg:phone":"+61 2 4578 3933",
    "sg:postcode":"2753",
    "sg:province":"NSW",
    "wof:name":"Thompsons The Real Estate People",
    "wof:placetype":"venue"
},
  "geometry": {"coordinates":[150.749633789,-33.5963249207],"type":"Point"}
}