{
  "type": "Feature",
  "properties": {
    "addr:full":"822 George St Broadway NSW 2007",
    "addr:housenumber":"822",
    "addr:postcode":"2007",
    "addr:street":"George St",
    "iso:country":"AU",
    "sg:address":"822 George St",
    "sg:city":"Broadway",
    "sg:classifiers":[
        {
            "category":"Health Services",
            "subcategory":"Doctor",
            "type":"Services"
        }
    ],
    "sg:phone":"+61 2 9212 2733",
    "sg:postcode":"2007",
    "sg:province":"NSW",
    "sg:tags":[
        "medical",
        "practitioner"
    ],
    "wof:name":"Health 24 Medical Centres Pty Ltd",
    "wof:placetype":"venue"
},
  "geometry": {"coordinates":[151.20257568400001,-33.8840408325],"type":"Point"}
}