{
  "type": "Feature",
  "properties": {
    "addr:full":"3/ 17 Bon Mace Cl Berkeley Vale NSW 2261",
    "addr:housenumber":"/ 17",
    "addr:postcode":"2261",
    "addr:street":"Cl",
    "iso:country":"AU",
    "sg:address":"3/ 17 Bon Mace Cl",
    "sg:city":"Berkeley Vale",
    "sg:classifiers":[
        {
            "category":"Home & Garden",
            "subcategory":"Hardware",
            "type":"Retail Goods"
        }
    ],
    "sg:phone":"+61 2 4388 3955",
    "sg:postcode":"2261",
    "sg:province":"NSW",
    "sg:tags":[
        "tarpaulin"
    ],
    "wof:name":"Industrial Textile Fabrications",
    "wof:placetype":"venue"
},
  "geometry": {"coordinates":[151.43858299999999,-33.344639],"type":"Point"}
}