{
  "type": "Feature",
  "properties": {
    "addr:full":"509 Riversdale Rd Camberwell VIC 3124",
    "addr:housenumber":"509",
    "addr:postcode":"3124",
    "addr:street":"Riversdale Rd",
    "iso:country":"AU",
    "sg:address":"509 Riversdale Rd",
    "sg:city":"Camberwell",
    "sg:classifiers":[
        {
            "category":"Restaurant",
            "type":"Food & Drink"
        }
    ],
    "sg:phone":"+61 3 9882 3618",
    "sg:postcode":"3124",
    "sg:province":"VIC",
    "wof:name":"Dozo Japanese Restaurant",
    "wof:placetype":"venue"
},
  "geometry": {"coordinates":[145.05732727,-37.8312911987],"type":"Point"}
}