{
  "type": "Feature",
  "properties": {
    "iso:country":"AU",
    "sg:address":"570 Canterbury Rd",
    "sg:city":"Belmore",
    "sg:classifiers":[
        {
            "category":"Home & Garden",
            "subcategory":"Carpets & Floor Coverings",
            "type":"Retail Goods"
        }
    ],
    "sg:phone":"+61 2 9787 2655",
    "sg:postcode":"2192",
    "sg:province":"NSW",
    "wof:name":"Malki Carpets Pty Ltd",
    "wof:placetype":"venue"
},
  "geometry": {"coordinates":[151.09715299999999,-33.921371],"type":"Point"}
}