{
  "type": "Feature",
  "properties": {
    "addr:full":"Suite 12b, Jacobs Court, 1 Jacobs St Bankstown NSW 2200",
    "addr:housenumber":"12b;1",
    "addr:postcode":"2200",
    "addr:street":"Jacobs Court;St",
    "iso:country":"AU",
    "sg:address":"Suite 12b, Jacobs Court, 1 Jacobs St",
    "sg:city":"Bankstown",
    "sg:classifiers":[
        {
            "category":"Health Services",
            "subcategory":"Doctor",
            "type":"Services"
        }
    ],
    "sg:phone":"+61 2 9796 2266",
    "sg:postcode":"2200",
    "sg:province":"NSW",
    "sg:tags":[
        "medical",
        "practitioner"
    ],
    "wof:name":"Helprin Garry A",
    "wof:placetype":"venue"
},
  "geometry": {"coordinates":[151.036957,-33.915752],"type":"Point"}
}