{
  "type": "Feature",
  "properties": {
    "iso:country":"AU",
    "sg:address":"557 Centre Rd",
    "sg:city":"Bentleigh",
    "sg:classifiers":[
        {
            "category":"Retail",
            "subcategory":"Event Space",
            "type":"Services"
        }
    ],
    "sg:phone":"+61 3 9557 4387",
    "sg:postcode":"3204",
    "sg:province":"VIC",
    "sg:tags":[
        "venue",
        "reception",
        "wedding"
    ],
    "wof:name":"Bentleigh Coppins",
    "wof:placetype":"venue"
},
  "geometry": {"coordinates":[145.04977400000001,-37.919785],"type":"Point"}
}