{
  "type": "Feature",
  "properties": {
    "iso:country":"AU",
    "sg:address":"33 Jells Rd",
    "sg:city":"Cheltenham",
    "sg:classifiers":[
        {
            "category":"Building & Trades",
            "subcategory":"Construction",
            "type":"Services"
        }
    ],
    "sg:phone":"+61 422 927 501",
    "sg:postcode":"3192",
    "sg:province":"VIC",
    "sg:tags":[
        "joiner",
        "carpenter"
    ],
    "wof:name":"Phe Mitre Edge",
    "wof:placetype":"venue"
},
  "geometry": {"coordinates":[145.080535889,-37.9638710022],"type":"Point"}
}