{
  "type": "Feature",
  "properties": {
    "iso:country":"AU",
    "sg:address":"22 Letchworth Centre Ave",
    "sg:city":"Salter Point",
    "sg:classifiers":[
        {
            "category":"Sports & Exercise",
            "subcategory":"Gym",
            "type":"Entertainment"
        }
    ],
    "sg:phone":"+61 422 713 787",
    "sg:postcode":"6152",
    "sg:province":"WA",
    "sg:tags":[
        "health",
        "fitness"
    ],
    "wof:name":"Kim Rodda",
    "wof:placetype":"venue"
},
  "geometry": {"coordinates":[115.871178,-32.021954],"type":"Point"}
}