{
  "type": "Feature",
  "properties": {
    "addr:full":"1 Wyuna St Rosebud VIC 3939",
    "addr:housenumber":"1",
    "addr:postcode":"3939",
    "addr:street":"Wyuna St",
    "iso:country":"AU",
    "sg:address":"1 Wyuna St",
    "sg:city":"Rosebud",
    "sg:classifiers":[
        {
            "category":"Social Services",
            "subcategory":"Adult Care",
            "type":"Services"
        }
    ],
    "sg:phone":"+61 3 5986 3322",
    "sg:postcode":"3939",
    "sg:province":"VIC",
    "sg:tags":[
        "aged"
    ],
    "wof:name":"Regis Grange",
    "wof:placetype":"venue"
},
  "geometry": {"coordinates":[144.882324219,-38.3699111938],"type":"Point"}
}