{
  "type": "Feature",
  "properties": {
    "addr:full":"Unit 2/ 2 Noonan Rd Ingleburn NSW 2565",
    "addr:housenumber":"2",
    "addr:postcode":"2565",
    "addr:street":"Noonan Rd",
    "iso:country":"AU",
    "sg:address":"Unit 2/ 2 Noonan Rd",
    "sg:city":"Ingleburn",
    "sg:classifiers":[
        {
            "category":"Retail",
            "subcategory":"Auto Repair",
            "type":"Services"
        }
    ],
    "sg:phone":"+61 2 9618 0422",
    "sg:postcode":"2565",
    "sg:province":"NSW",
    "sg:tags":[
        "repairer",
        "motor",
        "engineer"
    ],
    "wof:name":"Ultra Tune",
    "wof:placetype":"venue"
},
  "geometry": {"coordinates":[150.862380981,-33.9878807068],"type":"Point"}
}