{
  "type": "Feature",
  "properties": {
    "addr:full":"Guerin St Busselton WA 6280",
    "addr:postcode":"6280",
    "addr:street":"Guerin St",
    "iso:country":"AU",
    "sg:address":"Guerin St",
    "sg:city":"Busselton",
    "sg:classifiers":[
        {
            "category":"Shopping",
            "subcategory":"Pets & Pet Supplies",
            "type":"Retail Goods"
        }
    ],
    "sg:phone":"+61 8 9752 1433",
    "sg:postcode":"6280",
    "sg:province":"WA",
    "sg:tags":[
        "food"
    ],
    "wof:name":"Busselton Veterinary Hospital",
    "wof:placetype":"venue"
},
  "geometry": {"coordinates":[115.38186645499999,-33.6371879578],"type":"Point"}
}