{
  "type": "Feature",
  "properties": {
    "addr:full":"525 Little Yarra Rd Gladysdale VIC 3797",
    "addr:housenumber":"525",
    "addr:postcode":"3797",
    "addr:street":"Little Yarra Rd",
    "iso:country":"AU",
    "sg:address":"525 Little Yarra Rd",
    "sg:city":"Gladysdale",
    "sg:classifiers":[
        {
            "category":"Shopping",
            "subcategory":"Books",
            "type":"Retail Goods"
        }
    ],
    "sg:phone":"+61 3 5966 6287",
    "sg:postcode":"3797",
    "sg:province":"VIC",
    "sg:tags":[
        "wholesaler",
        "canvas",
        "mfrs"
    ],
    "wof:name":"Little Yarra Canvas",
    "wof:placetype":"venue"
},
  "geometry": {"coordinates":[145.6144104,-37.7825202942],"type":"Point"}
}