{
  "type": "Feature",
  "properties": {
    "addr:full":"45 West St Mt Isa QLD 4825",
    "addr:housenumber":"45",
    "addr:postcode":"4825",
    "addr:street":"West St",
    "iso:country":"AU",
    "sg:address":"45 West St",
    "sg:city":"Mt Isa",
    "sg:classifiers":[
        {
            "category":"Travel",
            "subcategory":"Hotels & Motels",
            "type":"Entertainment"
        }
    ],
    "sg:phone":"+61 7 4743 2311",
    "sg:postcode":"4825",
    "sg:province":"QLD",
    "wof:name":"Mercure Inn Outback",
    "wof:placetype":"venue"
},
  "geometry": {"coordinates":[139.49079900000001,-20.722954],"type":"Point"}
}