{
  "type": "Feature",
  "properties": {
    "addr:full":"98 Main Rd Moonah TAS 7009",
    "addr:housenumber":"98",
    "addr:postcode":"7009",
    "addr:street":"Main Rd",
    "iso:country":"AU",
    "sg:address":"98 Main Rd",
    "sg:city":"Moonah",
    "sg:classifiers":[
        {
            "category":"Shopping",
            "subcategory":"Discount & Variety Stores",
            "type":"Retail Goods"
        }
    ],
    "sg:phone":"+61 3 6228 7100",
    "sg:postcode":"7009",
    "sg:province":"TAS",
    "sg:tags":[
        "shop",
        "adult"
    ],
    "wof:name":"Adultshop.com",
    "wof:placetype":"venue"
},
  "geometry": {"coordinates":[147.294677734,-42.8466300964],"type":"Point"}
}