{
  "type": "Feature",
  "properties": {
    "addr:full":"PO Box 2202 Bendigo VIC 3554",
    "addr:postcode":"3554",
    "iso:country":"AU",
    "sg:address":"PO Box 2202",
    "sg:city":"Bendigo",
    "sg:classifiers":[
        {
            "category":"Professional",
            "subcategory":"Detective & Security Services",
            "type":"Services"
        }
    ],
    "sg:phone":"+61 408 441 305",
    "sg:postcode":"3554",
    "sg:province":"VIC",
    "sg:tags":[
        "consultant",
        "system"
    ],
    "wof:name":"A&R Electrical Services",
    "wof:placetype":"venue"
},
  "geometry": {"coordinates":[144.28007507300001,-36.7584915161],"type":"Point"}
}