{
  "type": "Feature",
  "properties": {
    "iso:country":"AU",
    "sg:address":"107 Derby St",
    "sg:city":"Tullamarine",
    "sg:classifiers":[
        {
            "category":"Insurance",
            "subcategory":"Insurance Agent",
            "type":"Services"
        }
    ],
    "sg:phone":"+61 3 9335 5555",
    "sg:postcode":"3043",
    "sg:province":"VIC",
    "sg:tags":[
        "baggage"
    ],
    "wof:name":"Fastair Consolidators Pty Ltd",
    "wof:placetype":"venue"
},
  "geometry": {"coordinates":[144.87051391599999,-37.6862449646],"type":"Point"}
}