{
  "type": "Feature",
  "properties": {
    "iso:country":"AU",
    "sg:address":"PO Box 5292",
    "sg:city":"Chittaway Bay",
    "sg:classifiers":[
        {
            "category":"Banks & Credit Unions",
            "subcategory":"Financial Services",
            "type":"Services"
        }
    ],
    "sg:phone":"+61 408 436 043",
    "sg:postcode":"2261",
    "sg:province":"NSW",
    "sg:tags":[
        "assistance",
        "roadside"
    ],
    "wof:name":"Central Coast Breakdown Services",
    "wof:placetype":"venue"
},
  "geometry": {"coordinates":[151.496353,-33.358421],"type":"Point"}
}