{
  "type": "Feature",
  "properties": {
    "addr:full":"122 Crescent Rd Newport NSW 2106",
    "addr:housenumber":"122",
    "addr:postcode":"2106",
    "addr:street":"Crescent Rd",
    "iso:country":"AU",
    "sg:address":"122 Crescent Rd",
    "sg:city":"Newport",
    "sg:classifiers":[
        {
            "category":"Autos & Motor Vehicles",
            "subcategory":"Boat Sales",
            "type":"Retail Goods"
        }
    ],
    "sg:phone":"+61 411 231 230",
    "sg:postcode":"2106",
    "sg:province":"NSW",
    "sg:tags":[
        "yacht"
    ],
    "wof:name":"Coastwide Marine Consultancy",
    "wof:placetype":"venue"
},
  "geometry": {"coordinates":[151.31112670900001,-33.6647644043],"type":"Point"}
}