{
  "type": "Feature",
  "properties": {
    "addr:full":"94 George St Avalon NSW 2107",
    "addr:housenumber":"94",
    "addr:postcode":"2107",
    "addr:street":"George St",
    "iso:country":"AU",
    "sg:address":"94 George St",
    "sg:city":"Avalon",
    "sg:classifiers":[
        {
            "category":"Recreation",
            "subcategory":"Marina",
            "type":"Entertainment"
        }
    ],
    "sg:phone":"+61 2 9918 2331",
    "sg:postcode":"2107",
    "sg:province":"NSW",
    "wof:name":"Careel Bay Marina",
    "wof:placetype":"venue"
},
  "geometry": {"coordinates":[151.32220459000001,-33.6210784912],"type":"Point"}
}