{
  "type": "Feature",
  "properties": {
    "iso:country":"AU",
    "sg:address":"PO Box 548",
    "sg:city":"Leongatha",
    "sg:classifiers":[
        {
            "category":"Professional",
            "subcategory":"Computer Services",
            "type":"Services"
        }
    ],
    "sg:phone":"+61 408 629 417",
    "sg:postcode":"3953",
    "sg:province":"VIC",
    "sg:tags":[
        "training"
    ],
    "wof:name":"Gippsland Train One 2 One",
    "wof:placetype":"venue"
},
  "geometry": {"coordinates":[145.94703674300001,-38.4758605957],"type":"Point"}
}