{
  "type": "Feature",
  "properties": {
    "addr:full":"Shop 6 .01A MLC Centre Sydney NSW 2000",
    "addr:housenumber":"shop 6",
    "addr:postcode":"2000",
    "addr:street":"Mlc",
    "iso:country":"AU",
    "sg:address":"Shop 6",
    "sg:city":".01A MLC Centre Sydney",
    "sg:classifiers":[
        {
            "category":"Cafe",
            "type":"Food & Drink"
        }
    ],
    "sg:phone":"+61 2 9231 3151",
    "sg:postcode":"2000",
    "sg:province":"NSW",
    "wof:name":"L&#039;Espresso Stop",
    "wof:placetype":"venue"
},
  "geometry": {"coordinates":[151.210006714,-33.8695793152],"type":"Point"}
}