{
  "type": "Feature",
  "properties": {
    "addr:full":"Shop 6, The Central Corner Central Ave Nowra South NSW 2541",
    "addr:housenumber":"shop 6",
    "addr:postcode":"2541",
    "addr:street":"The Central Corner Central Ave",
    "iso:country":"AU",
    "sg:address":"Shop 6, The Central Corner Central Ave",
    "sg:city":"Nowra South",
    "sg:phone":"+61 2 4423 5353",
    "sg:postcode":"2541",
    "sg:province":"NSW",
    "wof:name":"Aquaclean Filters",
    "wof:placetype":"venue"
},
  "geometry": {"coordinates":[150.59349060100001,-34.9131202698],"type":"Point"}
}