{
  "type": "Feature",
  "properties": {
    "addr:full":"Commercial Rd Tarnagulla VIC 3551",
    "addr:postcode":"3551",
    "addr:street":"Commercial Rd",
    "iso:country":"AU",
    "sg:address":"Commercial Rd",
    "sg:city":"Tarnagulla",
    "sg:classifiers":[
        {
            "category":"Manufacturing",
            "subcategory":"Glass & Minerals",
            "type":"Manufacturing & Wholesale Goods"
        }
    ],
    "sg:phone":"+61 3 5438 7428",
    "sg:postcode":"3551",
    "sg:province":"VIC",
    "sg:tags":[
        "exploration"
    ],
    "wof:name":"Reef Mining N.L.",
    "wof:placetype":"venue"
},
  "geometry": {"coordinates":[143.82899475100001,-36.7678718567],"type":"Point"}
}