{
  "type": "Feature",
  "properties": {
    "addr:full":"71 Burwood Rd Burwood NSW 2134",
    "addr:housenumber":"71",
    "addr:postcode":"2134",
    "addr:street":"Burwood Rd",
    "iso:country":"AU",
    "sg:address":"71 Burwood Rd",
    "sg:city":"Burwood",
    "sg:classifiers":[
        {
            "category":"Professional",
            "subcategory":"Accounting & Tax Preparation",
            "type":"Services"
        }
    ],
    "sg:phone":"+61 2 9744 2077",
    "sg:postcode":"2134",
    "sg:province":"NSW",
    "sg:tags":[
        "consultant",
        "taxation"
    ],
    "wof:name":"P. A. Tax & Accounting Pty Ltd",
    "wof:placetype":"venue"
},
  "geometry": {"coordinates":[151.10392761200001,-33.875415802],"type":"Point"}
}