{
  "type": "Feature",
  "properties": {
    "addr:full":"37 Berg St Blacktown NSW 2148",
    "addr:postcode":"2148",
    "addr:street":"Berg St",
    "iso:country":"AU",
    "sg:address":"37 Berg St",
    "sg:city":"Blacktown",
    "sg:classifiers":[
        {
            "category":"Health Services",
            "subcategory":"Health Practitioner",
            "type":"Services"
        }
    ],
    "sg:phone":"+61 2 9622 3651",
    "sg:postcode":"2148",
    "sg:province":"NSW",
    "sg:tags":[
        "naturopath"
    ],
    "wof:name":"Dierkes Wilhelm",
    "wof:placetype":"venue"
},
  "geometry": {"coordinates":[150.91294860799999,-33.786945343],"type":"Point"}
}