{
  "type": "Feature",
  "properties": {
    "iso:country":"AU",
    "sg:address":"23 Quinns Rd",
    "sg:city":"Bushfield",
    "sg:classifiers":[
        {
            "category":"Building & Trades",
            "subcategory":"Plumbing",
            "type":"Services"
        }
    ],
    "sg:phone":"+61 3 5562 6594",
    "sg:postcode":"3281",
    "sg:province":"VIC",
    "sg:tags":[
        "plumber",
        "gasfitters"
    ],
    "wof:name":"Beveridge John",
    "wof:placetype":"venue"
},
  "geometry": {"coordinates":[142.505004883,-38.3212356567],"type":"Point"}
}