{
  "type": "Feature",
  "properties": {
    "addr:full":"Cnr Kenyons Rd & Arcadia St Merrylands NSW 2160",
    "addr:postcode":"2160",
    "addr:street":"Cnr Kenyons Rd & Arcadia St",
    "iso:country":"AU",
    "sg:address":"Cnr Kenyons Rd & Arcadia St",
    "sg:city":"Merrylands",
    "sg:classifiers":[
        {
            "category":"Retail",
            "subcategory":"Auto Repair",
            "type":"Services"
        }
    ],
    "sg:phone":"+61 2 9637 4342",
    "sg:postcode":"2160",
    "sg:province":"NSW",
    "sg:tags":[
        "repairer",
        "motor",
        "engineer"
    ],
    "wof:name":"A. Merrylands Auto Radiator Service",
    "wof:placetype":"venue"
},
  "geometry": {"coordinates":[150.975997925,-33.8356208801],"type":"Point"}
}