{
  "type": "Feature",
  "properties": {
    "addr:full":"145 Wallace St Braidwood NSW 2622",
    "addr:housenumber":"145",
    "addr:postcode":"2622",
    "addr:street":"Wallace St",
    "iso:country":"AU",
    "sg:address":"145 Wallace St",
    "sg:city":"Braidwood",
    "sg:classifiers":[
        {
            "category":"Travel",
            "subcategory":"Hotels & Motels",
            "type":"Entertainment"
        }
    ],
    "sg:phone":"+61 2 4842 2488",
    "sg:postcode":"2622",
    "sg:province":"NSW",
    "sg:tags":[
        "accommodation"
    ],
    "wof:name":"Royal Mail Hotel",
    "wof:placetype":"venue"
},
  "geometry": {"coordinates":[149.801177978,-35.4369506836],"type":"Point"}
}