{
  "type": "Feature",
  "properties": {
    "addr:full":"Unit 4, 2 Kenworth Pl Brendale QLD 4500",
    "addr:housenumber":"2",
    "addr:postcode":"4500",
    "addr:street":"Kenworth Pl",
    "iso:country":"AU",
    "sg:address":"Unit 4, 2 Kenworth Pl",
    "sg:city":"Brendale",
    "sg:classifiers":[
        {
            "category":"Manufacturing",
            "subcategory":"Electronics",
            "type":"Manufacturing & Wholesale Goods"
        }
    ],
    "sg:phone":"+61 7 3205 8922",
    "sg:postcode":"4500",
    "sg:province":"QLD",
    "sg:tags":[
        "wholesaler",
        "equipment",
        "part",
        "mfrs",
        "refrigeration"
    ],
    "wof:name":"Actrol Parts",
    "wof:placetype":"venue"
},
  "geometry": {"coordinates":[152.988449097,-27.3249721527],"type":"Point"}
}