{
  "type": "Feature",
  "properties": {
    "addr:full":"Unit 6/ 17 Parkedge Rd Sunshine Beach QLD 4567",
    "addr:housenumber":"17",
    "addr:postcode":"4567",
    "addr:street":"Parkedge Rd",
    "iso:country":"AU",
    "sg:address":"Unit 6/ 17 Parkedge Rd",
    "sg:city":"Sunshine Beach",
    "sg:classifiers":[
        {
            "category":"Shopping",
            "subcategory":"Beauty & Cosmetics",
            "type":"Retail Goods"
        }
    ],
    "sg:phone":"+61 7 5474 5545",
    "sg:postcode":"4567",
    "sg:province":"QLD",
    "sg:tags":[
        "equipment",
        "salon",
        "supply"
    ],
    "wof:name":"Roiie Design Australia",
    "wof:placetype":"venue"
},
  "geometry": {"coordinates":[153.107254028,-26.4006137848],"type":"Point"}
}