{
  "type": "Feature",
  "properties": {
    "addr:full":"128 Pfingst St Goondiwindi QLD 4390",
    "addr:housenumber":"128",
    "addr:postcode":"4390",
    "addr:street":"Pfingst St",
    "iso:country":"AU",
    "sg:address":"128 Pfingst St",
    "sg:city":"Goondiwindi",
    "sg:classifiers":[
        {
            "category":"Personal",
            "type":"Services"
        }
    ],
    "sg:phone":"+61 409 340 950",
    "sg:postcode":"4390",
    "sg:province":"QLD",
    "sg:tags":[
        "wallpapering",
        "wallcovering"
    ],
    "wof:name":"Wright Graham Painting Contractor",
    "wof:placetype":"venue"
},
  "geometry": {"coordinates":[150.31690979000001,-28.5473308563],"type":"Point"}
}