{
  "type": "Feature",
  "properties": {
    "addr:full":"18 Milburn Rd Gymea NSW 2227",
    "addr:housenumber":"18",
    "addr:postcode":"2227",
    "addr:street":"Milburn Rd",
    "iso:country":"AU",
    "sg:address":"18 Milburn Rd",
    "sg:city":"Gymea",
    "sg:classifiers":[
        {
            "category":"Education",
            "subcategory":"Kindergarten",
            "type":"Public Place"
        }
    ],
    "sg:phone":"+61 2 9524 2477",
    "sg:postcode":"2227",
    "sg:province":"NSW",
    "sg:tags":[
        "pre-schools"
    ],
    "wof:name":"Tom Thumb Kindergarten",
    "wof:placetype":"venue"
},
  "geometry": {"coordinates":[151.08651733400001,-34.0288200378],"type":"Point"}
}