{
  "type": "Feature",
  "properties": {
    "iso:country":"AU",
    "sg:address":"105 Shenton Rd",
    "sg:city":"Swanbourne",
    "sg:classifiers":[
        {
            "category":"Arts & Performance",
            "subcategory":"Dance",
            "type":"Entertainment"
        }
    ],
    "sg:phone":"+61 8 9286 4727",
    "sg:postcode":"6010",
    "sg:province":"WA",
    "sg:tags":[
        "theatrical",
        "ballet",
        "tuition"
    ],
    "wof:name":"Dance Classique",
    "wof:placetype":"venue"
},
  "geometry": {"coordinates":[115.76914978000001,-31.9802341461],"type":"Point"}
}