{
  "type": "Feature",
  "properties": {
    "addr:full":"Suite 7, 70 Walkerville Tce Walkerville SA 5081",
    "addr:housenumber":"70",
    "addr:postcode":"5081",
    "addr:street":"Walkerville Tce",
    "iso:country":"AU",
    "sg:address":"Suite 7, 70 Walkerville Tce",
    "sg:city":"Walkerville",
    "sg:classifiers":[
        {
            "category":"Communications",
            "type":"Services"
        }
    ],
    "sg:phone":"+61 8 8342 5200",
    "sg:postcode":"5081",
    "sg:province":"SA",
    "sg:tags":[
        "translation"
    ],
    "wof:name":"Translation Consultants International",
    "wof:placetype":"venue"
},
  "geometry": {"coordinates":[138.61492919899999,-34.8972396851],"type":"Point"}
}