{
  "type": "Feature",
  "properties": {
    "iso:country":"AU",
    "sg:address":"Cnr Ramsgate Rd",
    "sg:city":"& Grand Parade Ramsgate",
    "sg:classifiers":[
        {
            "category":"Retail",
            "subcategory":"Auto Repair",
            "type":"Services"
        }
    ],
    "sg:phone":"+61 2 9583 9729",
    "sg:postcode":"2217",
    "sg:province":"NSW",
    "sg:tags":[
        "repairer",
        "motor",
        "engineer"
    ],
    "wof:name":"Shell Auto Care",
    "wof:placetype":"venue"
},
  "geometry": {"coordinates":[151.13807678200001,-33.9843978882],"type":"Point"}
}