{
  "type": "Feature",
  "properties": {
    "addr:full":"52 Commercial St Kaniva VIC 3419",
    "addr:housenumber":"52",
    "addr:postcode":"3419",
    "addr:street":"Commercial St",
    "iso:country":"AU",
    "sg:address":"52 Commercial St",
    "sg:city":"Kaniva",
    "sg:classifiers":[
        {
            "category":"Cafe",
            "type":"Food & Drink"
        }
    ],
    "sg:phone":"+61 3 5392 2570",
    "sg:postcode":"3419",
    "sg:province":"VIC",
    "wof:name":"Morning Loaf Bakery-Kaniva",
    "wof:placetype":"venue"
},
  "geometry": {"coordinates":[141.23922729500001,-36.3786659241],"type":"Point"}
}