{
  "type": "Feature",
  "properties": {
    "iso:country":"AU",
    "sg:address":"Level 1/115 Sailors Bay Rd Suite 2B",
    "sg:city":"Northbridge",
    "sg:classifiers":[
        {
            "category":"Health Services",
            "subcategory":"Doctor",
            "type":"Services"
        }
    ],
    "sg:phone":"+61 2 9958 7104",
    "sg:postcode":"2063",
    "sg:province":"NSW",
    "sg:tags":[
        "medical",
        "practitioner"
    ],
    "wof:name":"Northbridge Medical Practice",
    "wof:placetype":"venue"
},
  "geometry": {"coordinates":[151.211959839,-33.811126709],"type":"Point"}
}