{
  "type": "Feature",
  "properties": {
    "iso:country":"AU",
    "sg:address":"Shop 316b Redbank Plaza, 1 Collingwood Dr",
    "sg:city":"Redbank",
    "sg:classifiers":[
        {
            "category":"Shopping",
            "subcategory":"Optical Goods",
            "type":"Retail Goods"
        }
    ],
    "sg:phone":"+61 7 3818 7700",
    "sg:postcode":"4301",
    "sg:province":"QLD",
    "sg:tags":[
        "dispenser",
        "prescription"
    ],
    "wof:name":"Value Plus Eyewear",
    "wof:placetype":"venue"
},
  "geometry": {"coordinates":[152.85017395,-27.6409759521],"type":"Point"}
}