{
  "type": "Feature",
  "properties": {
    "addr:full":"74 Tenth Ave Inglewood WA 6052",
    "addr:housenumber":"74",
    "addr:postcode":"6052",
    "addr:street":"Tenth Ave",
    "iso:country":"AU",
    "sg:address":"74 Tenth Ave",
    "sg:city":"Inglewood",
    "sg:classifiers":[
        {
            "category":"Building & Trades",
            "subcategory":"Construction",
            "type":"Services"
        }
    ],
    "sg:phone":"+61 8 9371 7242",
    "sg:postcode":"6052",
    "sg:province":"WA",
    "sg:tags":[
        "renovation",
        "alterations",
        "extension",
        "contractor"
    ],
    "wof:name":"Reliable Building Services",
    "wof:placetype":"venue"
},
  "geometry": {"coordinates":[115.88855743400001,-31.9226303101],"type":"Point"}
}