{
  "type": "Feature",
  "properties": {
    "addr:full":"PO Box 8630 Gold Coast Mail Centre QLD 9726",
    "addr:postcode":"9726",
    "addr:street":"Coast",
    "iso:country":"AU",
    "sg:address":"PO Box 8630",
    "sg:city":"Gold Coast Mail Centre",
    "sg:classifiers":[
        {
            "category":"Insurance",
            "subcategory":"Insurance Agent",
            "type":"Services"
        }
    ],
    "sg:phone":"+61 7 3391 4066",
    "sg:postcode":"9726",
    "sg:province":"QLD",
    "wof:name":"Elm Financial Services",
    "wof:placetype":"venue"
},
  "geometry": {"coordinates":[153.44924926799999,-28.0854701996],"type":"Point"}
}