{
  "type": "Feature",
  "properties": {
    "addr:full":"Shop 60-61 Eastgate Shopping Centre, 71 -91 Spring Street Bondi Junction NSW 2022",
    "addr:housenumber":"60-61;71 -91",
    "addr:postcode":"2022",
    "addr:street":"Eastgate Shopping;Spring Street",
    "iso:country":"AU",
    "sg:address":"Shop 60-61 Eastgate Shopping Centre, 71",
    "sg:city":"-91 Spring Street Bondi Junction",
    "sg:classifiers":[
        {
            "category":"Shopping",
            "subcategory":"Shoes",
            "type":"Retail Goods"
        }
    ],
    "sg:phone":"+61 2 9387 7073",
    "sg:postcode":"2022",
    "sg:province":"NSW",
    "sg:tags":[
        "footwear"
    ],
    "wof:name":"Payless Shoes Pty Limited",
    "wof:placetype":"venue"
},
  "geometry": {"coordinates":[151.24928283700001,-33.8926544189],"type":"Point"}
}