{
  "type": "Feature",
  "properties": {
    "iso:country":"AU",
    "sg:address":"163 Mossfiel Drv",
    "sg:city":"Hoppers Crossing",
    "sg:classifiers":[
        {
            "category":"Health Services",
            "subcategory":"Health Practitioner",
            "type":"Services"
        }
    ],
    "sg:phone":"+61 3 9748 0855",
    "sg:postcode":"3029",
    "sg:province":"VIC",
    "sg:tags":[
        "physiotherapist"
    ],
    "wof:name":"Newman Christina",
    "wof:placetype":"venue"
},
  "geometry": {"coordinates":[144.703049,-37.864742],"type":"Point"}
}