{
  "type": "Feature",
  "properties": {
    "iso:country":"AU",
    "sg:address":"3A Fink St",
    "sg:city":"Preston",
    "sg:classifiers":[
        {
            "category":"Wholesale",
            "subcategory":"Apparel",
            "type":"Manufacturing & Wholesale Goods"
        }
    ],
    "sg:phone":"+61 3 9489 5499",
    "sg:postcode":"3072",
    "sg:province":"VIC",
    "sg:tags":[
        "wholesaler",
        "mfrs",
        "uniform"
    ],
    "wof:name":"MDR Global Trading Pty Ltd",
    "wof:placetype":"venue"
},
  "geometry": {"coordinates":[145.02806091299999,-37.7530479431],"type":"Point"}
}