{
  "type": "Feature",
  "properties": {
    "iso:country":"AU",
    "sg:address":"26c Harrison St",
    "sg:city":"Cardiff",
    "sg:classifiers":[
        {
            "category":"Retail",
            "subcategory":"Veterinary Services",
            "type":"Services"
        }
    ],
    "sg:phone":"+61 2 4954 7055",
    "sg:postcode":"2285",
    "sg:province":"NSW",
    "sg:tags":[
        "surgeon"
    ],
    "wof:name":"Cornwell Andrew",
    "wof:placetype":"venue"
},
  "geometry": {"coordinates":[151.660400391,-32.939617157],"type":"Point"}
}