{
  "type": "Feature",
  "properties": {
    "iso:country":"AU",
    "sg:address":"PO Box 3021",
    "sg:city":"Sunnybank South",
    "sg:classifiers":[
        {
            "category":"Banks & Credit Unions",
            "subcategory":"Investment Brokerage",
            "type":"Services"
        }
    ],
    "sg:phone":"+61 7 3345 8667",
    "sg:postcode":"4109",
    "sg:province":"QLD",
    "sg:tags":[
        "debt",
        "collection"
    ],
    "wof:name":"Accounts Management QLD Roylin Pty Ltd",
    "wof:placetype":"venue"
},
  "geometry": {"coordinates":[153.06077575699999,-27.5878391266],"type":"Point"}
}