{
  "type": "Feature",
  "properties": {
    "iso:country":"AU",
    "sg:address":"31 Web Rd",
    "sg:city":"Narre Warren",
    "sg:classifiers":[
        {
            "category":"Health Services",
            "subcategory":"Dentist",
            "type":"Services"
        }
    ],
    "sg:phone":"+61 1300 661 159",
    "sg:postcode":"3805",
    "sg:province":"VIC",
    "wof:name":"A Whiter Smiley",
    "wof:placetype":"venue"
},
  "geometry": {"coordinates":[145.304077,-38.025574],"type":"Point"}
}