{
  "type": "Feature",
  "properties": {
    "addr:full":"Suite 6, Sunshine Coast Priv. Hsptl, Medical Centr Buderim QLD 4556",
    "addr:postcode":"4556",
    "addr:street":"Sunshine",
    "iso:country":"AU",
    "sg:address":"Suite 6, Sunshine Coast Priv. Hsptl, Medical Centr",
    "sg:city":"Buderim",
    "sg:classifiers":[
        {
            "category":"Banks & Credit Unions",
            "subcategory":"Financial Services",
            "type":"Services"
        }
    ],
    "sg:phone":"+61 7 5477 5400",
    "sg:postcode":"4556",
    "sg:province":"QLD",
    "sg:tags":[
        "surgeon",
        "oral",
        "dental",
        "maxillofacial"
    ],
    "wof:name":"Ian G Young Oral & Maxillofacial Surgeon",
    "wof:placetype":"venue"
},
  "geometry": {"coordinates":[153.094802856,-26.6795597076],"type":"Point"}
}