{
  "type": "Feature",
  "properties": {
    "addr:full":"70 Woolana Ave Budgewoi NSW 2262",
    "addr:housenumber":"70",
    "addr:postcode":"2262",
    "addr:street":"Woolana Ave",
    "iso:country":"AU",
    "sg:address":"70 Woolana Ave",
    "sg:city":"Budgewoi",
    "sg:classifiers":[
        {
            "category":"Professional",
            "subcategory":"Computer Services",
            "type":"Services"
        }
    ],
    "sg:phone":"+61 2 4390 3565",
    "sg:postcode":"2262",
    "sg:province":"NSW",
    "sg:tags":[
        "training"
    ],
    "wof:name":"CTD",
    "wof:placetype":"venue"
},
  "geometry": {"coordinates":[151.550354,-33.231621],"type":"Point"}
}