{
  "type": "Feature",
  "properties": {
    "iso:country":"AU",
    "sg:address":"2 Pamela St",
    "sg:city":"Mt Isa",
    "sg:classifiers":[
        {
            "category":"Manufacturing",
            "subcategory":"Motor Vehicles & Parts",
            "type":"Manufacturing & Wholesale Goods"
        }
    ],
    "sg:phone":"+61 7 4743 6882",
    "sg:postcode":"4825",
    "sg:province":"QLD",
    "sg:tags":[
        "replacement"
    ],
    "wof:name":"Roger Locke & Co",
    "wof:placetype":"venue"
},
  "geometry": {"coordinates":[139.496185,-20.729912],"type":"Point"}
}