{
  "type": "Feature",
  "properties": {
    "iso:country":"AU",
    "sg:address":"Shop 2, 1273 Hay St",
    "sg:city":"West Perth",
    "sg:classifiers":[
        {
            "category":"Shopping",
            "subcategory":"Gifts & Souvenirs",
            "type":"Retail Goods"
        }
    ],
    "sg:phone":"+61 8 9321 3025",
    "sg:postcode":"6005",
    "sg:province":"WA",
    "sg:tags":[
        "greeting",
        "card"
    ],
    "wof:name":"Face Dances Cards & Gifts",
    "wof:placetype":"venue"
},
  "geometry": {"coordinates":[115.840103149,-31.9478874207],"type":"Point"}
}