{
  "type": "Feature",
  "properties": {
    "addr:full":"160 Garden St Tamworth NSW 2340",
    "addr:housenumber":"160",
    "addr:postcode":"2340",
    "addr:street":"Garden St",
    "iso:country":"AU",
    "sg:address":"160 Garden St",
    "sg:city":"Tamworth",
    "sg:classifiers":[
        {
            "category":"Professional",
            "type":"Services"
        }
    ],
    "sg:phone":"+61 2 6765 8684",
    "sg:postcode":"2340",
    "sg:province":"NSW",
    "sg:tags":[
        "courier"
    ],
    "wof:name":"Phantom Frieght & Courier Service",
    "wof:placetype":"venue"
},
  "geometry": {"coordinates":[150.902053833,-31.1207675934],"type":"Point"}
}