{
  "type": "Feature",
  "properties": {
    "iso:country":"AU",
    "sg:address":"34/140 Crimea Rd",
    "sg:city":"Marsfield",
    "sg:classifiers":[
        {
            "category":"Building & Trades",
            "subcategory":"Pest Control",
            "type":"Services"
        }
    ],
    "sg:phone":"+61 412 117 623",
    "sg:postcode":"2122",
    "sg:province":"NSW",
    "sg:tags":[
        "technical",
        "consultant"
    ],
    "wof:name":"Paul Esler Technical Services",
    "wof:placetype":"venue"
},
  "geometry": {"coordinates":[151.10081481899999,-33.7658462524],"type":"Point"}
}