{
  "type": "Feature",
  "properties": {
    "iso:country":"AU",
    "sg:address":"Lvl 4/ 493 St Kilda Rd",
    "sg:city":"Melbourne",
    "sg:classifiers":[
        {
            "category":"Professional",
            "subcategory":"Computer Services",
            "type":"Services"
        }
    ],
    "sg:phone":"+61 3 9821 4800",
    "sg:postcode":"3004",
    "sg:province":"VIC",
    "sg:tags":[
        "consultant",
        "system"
    ],
    "wof:name":"Red Wahoo Pty Ltd",
    "wof:placetype":"venue"
},
  "geometry": {"coordinates":[144.97817993199999,-37.8423423767],"type":"Point"}
}