{
  "type": "Feature",
  "properties": {
    "addr:full":"33 Parraweena Rd Taren Point NSW 2229",
    "addr:housenumber":"33",
    "addr:postcode":"2229",
    "addr:street":"Parraweena Rd",
    "iso:country":"AU",
    "sg:address":"33 Parraweena Rd",
    "sg:city":"Taren Point",
    "sg:classifiers":[
        {
            "category":"Retail",
            "subcategory":"Auto Repair",
            "type":"Services"
        }
    ],
    "sg:phone":"+61 2 9524 4522",
    "sg:postcode":"2229",
    "sg:province":"NSW",
    "sg:tags":[
        "repairer",
        "motor",
        "engineer"
    ],
    "wof:name":"Marlow Injection Correction",
    "wof:placetype":"venue"
},
  "geometry": {"coordinates":[151.12594604500001,-34.0259628296],"type":"Point"}
}