{
  "type": "Feature",
  "properties": {
    "iso:country":"AU",
    "sg:address":"PO Box 7116",
    "sg:city":"Dubbo",
    "sg:classifiers":[
        {
            "category":"Building & Trades",
            "subcategory":"Construction",
            "type":"Services"
        }
    ],
    "sg:phone":"+61 418 636 174",
    "sg:postcode":"2830",
    "sg:province":"NSW",
    "sg:tags":[
        "brick",
        "paving"
    ],
    "wof:name":"National Paving",
    "wof:placetype":"venue"
},
  "geometry": {"coordinates":[148.60118102999999,-32.2478713989],"type":"Point"}
}