{
  "type": "Feature",
  "properties": {
    "addr:full":"11 Aitkenhead St Bundaberg QLD 4670",
    "addr:housenumber":"11",
    "addr:postcode":"4670",
    "addr:street":"Aitkenhead St",
    "iso:country":"AU",
    "sg:address":"11 Aitkenhead St",
    "sg:city":"Bundaberg",
    "sg:classifiers":[
        {
            "category":"Professional",
            "subcategory":"Detective & Security Services",
            "type":"Services"
        }
    ],
    "sg:phone":"+61 7 4153 3322",
    "sg:postcode":"4670",
    "sg:province":"QLD",
    "sg:tags":[
        "equipment",
        "window",
        "doors"
    ],
    "wof:name":"Advantage Screens & Blinds",
    "wof:placetype":"venue"
},
  "geometry": {"coordinates":[152.37327575699999,-24.8538246155],"type":"Point"}
}