{
  "type": "Feature",
  "properties": {
    "iso:country":"AU",
    "sg:address":"12 Waratah St",
    "sg:city":"Leichhardt",
    "sg:classifiers":[
        {
            "category":"Building & Trades",
            "subcategory":"Landscaping Services",
            "type":"Services"
        }
    ],
    "sg:phone":"+61 2 9568 4512",
    "sg:postcode":"2040",
    "sg:province":"NSW",
    "sg:tags":[
        "consultant"
    ],
    "wof:name":"Urban Splash Pty Ltd",
    "wof:placetype":"venue"
},
  "geometry": {"coordinates":[151.160385,-33.88052],"type":"Point"}
}