{
  "type": "Feature",
  "properties": {
    "addr:full":"310 Punchbowl Rd Belfield NSW 2191",
    "addr:housenumber":"310",
    "addr:postcode":"2191",
    "addr:street":"Punchbowl Rd",
    "iso:country":"AU",
    "sg:address":"310 Punchbowl Rd",
    "sg:city":"Belfield",
    "sg:classifiers":[
        {
            "category":"Personal",
            "subcategory":"Beauty Salon",
            "type":"Services"
        }
    ],
    "sg:phone":"+61 2 9758 8339",
    "sg:postcode":"2191",
    "sg:province":"NSW",
    "wof:name":"Smooth Laser & Beauty Pty Ltd",
    "wof:placetype":"venue"
},
  "geometry": {"coordinates":[151.08395385700001,-33.90209198],"type":"Point"}
}