{
  "type": "Feature",
  "properties": {
    "iso:country":"AU",
    "sg:address":"52 Plume St",
    "sg:city":"Redcliffe",
    "sg:classifiers":[
        {
            "category":"Organizations",
            "subcategory":"Professional Association",
            "type":"Services"
        }
    ],
    "sg:phone":"+61 7 3883 2625",
    "sg:postcode":"4020",
    "sg:province":"QLD",
    "sg:tags":[
        "web",
        "internet"
    ],
    "wof:name":"Argonyx Studios",
    "wof:placetype":"venue"
},
  "geometry": {"coordinates":[153.104492,-27.233555],"type":"Point"}
}