{
  "type": "Feature",
  "properties": {
    "addr:full":"Studio 124 George St Redfern NSW 2016",
    "addr:housenumber":"124",
    "addr:postcode":"2016",
    "addr:street":"George St",
    "iso:country":"AU",
    "sg:address":"Studio 124 George St",
    "sg:city":"Redfern",
    "sg:classifiers":[
        {
            "category":"Personal",
            "subcategory":"Adult",
            "type":"Services"
        }
    ],
    "sg:phone":"+61 2 9319 6991",
    "sg:postcode":"2016",
    "sg:province":"NSW",
    "sg:tags":[
        "vic",
        "except",
        "state",
        "escort",
        "social",
        "qld"
    ],
    "wof:name":"Mayfair Escort Service",
    "wof:placetype":"venue"
},
  "geometry": {"coordinates":[151.20191955600001,-33.8930435181],"type":"Point"}
}