{
  "type": "Feature",
  "properties": {
    "addr:full":"Kentish Rd Evanston Heights SA 5116",
    "addr:postcode":"5116",
    "addr:street":"Kentish Rd",
    "iso:country":"AU",
    "sg:address":"Kentish Rd",
    "sg:city":"Evanston Heights",
    "sg:classifiers":[
        {
            "category":"Building & Trades",
            "subcategory":"Construction",
            "type":"Services"
        }
    ],
    "sg:phone":"+61 8 8522 6099",
    "sg:postcode":"5116",
    "sg:province":"SA",
    "sg:tags":[
        "renovation",
        "alterations",
        "extension",
        "contractor"
    ],
    "wof:name":"Stoakes Homes Pty Ltd",
    "wof:placetype":"venue"
},
  "geometry": {"coordinates":[138.740966797,-34.640750885],"type":"Point"}
}