{
  "type": "Feature",
  "properties": {
    "addr:full":"122 Mulgrave Rd Parramatta Park QLD 4870",
    "addr:housenumber":"122",
    "addr:postcode":"4870",
    "addr:street":"Mulgrave Rd",
    "iso:country":"AU",
    "sg:address":"122 Mulgrave Rd",
    "sg:city":"Parramatta Park",
    "sg:classifiers":[
        {
            "category":"Education",
            "subcategory":"School",
            "type":"Public Place"
        }
    ],
    "sg:phone":"+61 7 4042 8111",
    "sg:postcode":"4870",
    "sg:province":"QLD",
    "sg:tags":[
        "state",
        "except",
        "nsw"
    ],
    "wof:name":"Parramatta Primary School",
    "wof:placetype":"venue"
},
  "geometry": {"coordinates":[145.76255798299999,-16.9260978699],"type":"Point"}
}