{
  "type": "Feature",
  "properties": {
    "addr:full":"Cnr Tottenham & Wolseley Sts Buranda QLD 4102",
    "addr:postcode":"4102",
    "addr:street":"Sts",
    "iso:country":"AU",
    "sg:address":"Cnr Tottenham & Wolseley Sts",
    "sg:city":"Buranda",
    "sg:classifiers":[
        {
            "category":"Travel",
            "subcategory":"Hotels & Motels",
            "type":"Entertainment"
        }
    ],
    "sg:phone":"+61 7 3391 0081",
    "sg:postcode":"4102",
    "sg:province":"QLD",
    "wof:name":"Tottenham Court Accommodation",
    "wof:placetype":"venue"
},
  "geometry": {"coordinates":[153.03593444800001,-27.500043869],"type":"Point"}
}