{
  "type": "Feature",
  "properties": {
    "iso:country":"AU",
    "sg:address":"16 Industrial Ave",
    "sg:city":"Stratford",
    "sg:classifiers":[
        {
            "category":"Wholesale",
            "subcategory":"Machinery & Supplies",
            "type":"Manufacturing & Wholesale Goods"
        }
    ],
    "sg:phone":"+61 7 4058 1639",
    "sg:postcode":"4870",
    "sg:province":"QLD",
    "sg:tags":[
        "distributor",
        "crane",
        "mfrs"
    ],
    "wof:name":"R V Fabrications",
    "wof:placetype":"venue"
},
  "geometry": {"coordinates":[145.737625122,-16.8724899292],"type":"Point"}
}