{
  "type": "Feature",
  "properties": {
    "addr:full":"27 Alexandra Pde Fitzroy North VIC 3068",
    "addr:housenumber":"27",
    "addr:postcode":"3068",
    "addr:street":"Alexandra Pde",
    "iso:country":"AU",
    "sg:address":"27 Alexandra Pde",
    "sg:city":"Fitzroy North",
    "sg:classifiers":[
        {
            "category":"Banks & Credit Unions",
            "subcategory":"Bureau De Change",
            "type":"Services"
        }
    ],
    "sg:phone":"+61 1800 335 860",
    "sg:postcode":"3068",
    "sg:province":"VIC",
    "sg:tags":[
        "planning",
        "family"
    ],
    "wof:name":"Billings Family Life Centre",
    "wof:placetype":"venue"
},
  "geometry": {"coordinates":[144.98666381800001,-37.7937240601],"type":"Point"}
}