{
  "type": "Feature",
  "properties": {
    "iso:country":"AU",
    "sg:address":"555 Newcastle St",
    "sg:city":"West Perth",
    "sg:classifiers":[
        {
            "category":"Structure",
            "subcategory":"Office Building",
            "type":"Public Place"
        }
    ],
    "sg:phone":"+61 8 9422 1999",
    "sg:postcode":"6005",
    "sg:province":"WA",
    "sg:tags":[
        "equipment",
        "system",
        "drainage"
    ],
    "wof:name":"Atlantis Drainage Systems",
    "wof:placetype":"venue"
},
  "geometry": {"coordinates":[115.848182678,-31.9401607513],"type":"Point"}
}