{
  "type": "Feature",
  "properties": {
    "addr:full":"10c Seaflower Crs Craigie WA 6025",
    "addr:housenumber":"10c",
    "addr:postcode":"6025",
    "addr:street":"Seaflower Crs",
    "iso:country":"AU",
    "sg:address":"10c Seaflower Crs",
    "sg:city":"Craigie",
    "sg:classifiers":[
        {
            "category":"Education",
            "subcategory":"Music School",
            "type":"Public Place"
        }
    ],
    "sg:phone":"+61 8 9401 2561",
    "sg:postcode":"6025",
    "sg:province":"WA",
    "sg:tags":[
        "teacher"
    ],
    "wof:name":"Fisher Dawn",
    "wof:placetype":"venue"
},
  "geometry": {"coordinates":[115.767143249,-31.7867298126],"type":"Point"}
}