{
  "type": "Feature",
  "properties": {
    "addr:full":"13 Bourke St Bunbury WA 6230",
    "addr:housenumber":"13",
    "addr:postcode":"6230",
    "addr:street":"Bourke St",
    "iso:country":"AU",
    "sg:address":"13 Bourke St",
    "sg:city":"Bunbury",
    "sg:classifiers":[
        {
            "category":"Retail",
            "subcategory":"Auto Repair",
            "type":"Services"
        }
    ],
    "sg:phone":"+61 8 9721 4555",
    "sg:postcode":"6230",
    "sg:province":"WA",
    "sg:tags":[
        "engine",
        "reconditioning"
    ],
    "wof:name":"G.T.S. Engine Reconditioning",
    "wof:placetype":"venue"
},
  "geometry": {"coordinates":[115.642662,-33.334587],"type":"Point"}
}