{
  "type": "Feature",
  "properties": {
    "addr:full":"41 Bacon St Moranbah QLD 4744",
    "addr:housenumber":"41",
    "addr:postcode":"4744",
    "addr:street":"Bacon St",
    "iso:country":"AU",
    "sg:address":"41 Bacon St",
    "sg:city":"Moranbah",
    "sg:classifiers":[
        {
            "category":"Autos & Motor Vehicles",
            "subcategory":"Auto Supplies",
            "type":"Retail Goods"
        }
    ],
    "sg:phone":"+61 7 4941 8472",
    "sg:postcode":"4744",
    "sg:province":"QLD",
    "sg:tags":[
        "battery",
        "automotive"
    ],
    "wof:name":"Coal City Auto Repairs & Spares",
    "wof:placetype":"venue"
},
  "geometry": {"coordinates":[148.04112243599999,-21.9992694855],"type":"Point"}
}