{
  "type": "Feature",
  "properties": {
    "addr:full":"58 Mason St Campbellfield VIC 3061",
    "addr:housenumber":"58",
    "addr:postcode":"3061",
    "addr:street":"Mason St",
    "iso:country":"AU",
    "sg:address":"58 Mason St",
    "sg:city":"Campbellfield",
    "sg:classifiers":[
        {
            "category":"Retail",
            "subcategory":"Auto Repair",
            "type":"Services"
        }
    ],
    "sg:phone":"+61 3 9357 9898",
    "sg:postcode":"3061",
    "sg:province":"VIC",
    "sg:tags":[
        "beater",
        "painter",
        "panel"
    ],
    "wof:name":"Salih Body Works Pty Ltd",
    "wof:placetype":"venue"
},
  "geometry": {"coordinates":[144.96701049800001,-37.6715240479],"type":"Point"}
}