{
  "type": "Feature",
  "properties": {
    "addr:full":"117 East Boundary Rd Bentleigh East VIC 3165",
    "addr:housenumber":"117",
    "addr:postcode":"3165",
    "addr:street":"East Boundary Rd",
    "iso:country":"AU",
    "sg:address":"117 East Boundary Rd",
    "sg:city":"Bentleigh East",
    "sg:classifiers":[
        {
            "category":"Building & Trades",
            "subcategory":"Cleaning & Sanitation",
            "type":"Services"
        }
    ],
    "sg:phone":"+61 3 9579 4680",
    "sg:postcode":"3165",
    "sg:province":"VIC",
    "sg:tags":[
        "window"
    ],
    "wof:name":"Peter James",
    "wof:placetype":"venue"
},
  "geometry": {"coordinates":[145.05804443400001,-37.9248161316],"type":"Point"}
}