{
  "type": "Feature",
  "properties": {
    "addr:full":"17 Shauna Crs Mt Keira NSW 2500",
    "addr:housenumber":"17",
    "addr:postcode":"2500",
    "addr:street":"Shauna Crs",
    "iso:country":"AU",
    "sg:address":"17 Shauna Crs",
    "sg:city":"Mt Keira",
    "sg:classifiers":[
        {
            "category":"Retail",
            "subcategory":"Driving School",
            "type":"Services"
        }
    ],
    "sg:phone":"+61 428 292 551",
    "sg:postcode":"2500",
    "sg:province":"NSW",
    "wof:name":"Alan Gilmore",
    "wof:placetype":"venue"
},
  "geometry": {"coordinates":[150.85952800000001,-34.41608],"type":"Point"}
}