{
  "type": "Feature",
  "properties": {
    "iso:country":"AU",
    "sg:address":"4 Charlotte St",
    "sg:city":"Ashfield",
    "sg:classifiers":[
        {
            "category":"Health Services",
            "subcategory":"Dentist",
            "type":"Services"
        }
    ],
    "sg:phone":"+61 2 9716 7180",
    "sg:postcode":"2131",
    "sg:province":"NSW",
    "wof:name":"Ashfield Dental Clinic",
    "wof:placetype":"venue"
},
  "geometry": {"coordinates":[151.125488281,-33.8870315552],"type":"Point"}
}