{
  "type": "Feature",
  "properties": {
    "iso:country":"AU",
    "sg:address":"90 Kelly St",
    "sg:city":"Scone",
    "sg:classifiers":[
        {
            "category":"Personal",
            "subcategory":"Massage",
            "type":"Services"
        }
    ],
    "sg:phone":"+61 411 089 180",
    "sg:postcode":"2337",
    "sg:province":"NSW",
    "sg:tags":[
        "therapy"
    ],
    "wof:name":"Melissa Givney Remedial Massage Therapy",
    "wof:placetype":"venue"
},
  "geometry": {"coordinates":[150.868484497,-32.0469322205],"type":"Point"}
}