{
  "type": "Feature",
  "properties": {
    "iso:country":"AU",
    "sg:address":"41 Glenmorgan St",
    "sg:city":"Keperra",
    "sg:classifiers":[
        {
            "category":"Building & Trades",
            "subcategory":"Pest Control",
            "type":"Services"
        }
    ],
    "sg:phone":"+61 413 123 634",
    "sg:postcode":"4054",
    "sg:province":"QLD",
    "sg:tags":[
        "technical",
        "consultant"
    ],
    "wof:name":"Audio Art",
    "wof:placetype":"venue"
},
  "geometry": {"coordinates":[152.949386597,-27.413848877],"type":"Point"}
}