{
  "type": "Feature",
  "properties": {
    "iso:country":"AU",
    "sg:address":"82 Clarke St",
    "sg:city":"South Melbourne",
    "sg:classifiers":[
        {
            "category":"Retail",
            "subcategory":"Auto Repair",
            "type":"Services"
        }
    ],
    "sg:phone":"+61 3 9690 5022",
    "sg:postcode":"3205",
    "sg:province":"VIC",
    "sg:tags":[
        "repairer",
        "motor",
        "engineer"
    ],
    "wof:name":"Brewster's Ted Automotive Services",
    "wof:placetype":"venue"
},
  "geometry": {"coordinates":[144.960571,-37.830296],"type":"Point"}
}