{
  "type": "Feature",
  "properties": {
    "addr:full":"1/ 87 Wickham Tce Brisbane QLD 4000",
    "addr:housenumber":"/ 87",
    "addr:postcode":"4000",
    "addr:street":"Wickham Tce",
    "iso:country":"AU",
    "sg:address":"1/ 87 Wickham Tce",
    "sg:city":"Brisbane",
    "sg:classifiers":[
        {
            "category":"Health Services",
            "subcategory":"Doctor",
            "type":"Services"
        }
    ],
    "sg:phone":"+61 7 3839 4244",
    "sg:postcode":"4000",
    "sg:province":"QLD",
    "sg:tags":[
        "medical",
        "practitioner"
    ],
    "wof:name":"Earwaker J.W.S. Dr.",
    "wof:placetype":"venue"
},
  "geometry": {"coordinates":[153.02684020999999,-27.4644565582],"type":"Point"}
}