{
  "type": "Feature",
  "properties": {
    "addr:full":"742 Newcastle St Leederville WA 6007",
    "addr:housenumber":"742",
    "addr:postcode":"6007",
    "addr:street":"Newcastle St",
    "iso:country":"AU",
    "sg:address":"742 Newcastle St",
    "sg:city":"Leederville",
    "sg:classifiers":[
        {
            "category":"Travel",
            "subcategory":"Hotels & Motels",
            "type":"Entertainment"
        }
    ],
    "sg:phone":"+61 8 9286 0150",
    "sg:postcode":"6007",
    "sg:province":"WA",
    "sg:tags":[
        "pub"
    ],
    "wof:name":"Leederville The",
    "wof:placetype":"venue"
},
  "geometry": {"coordinates":[115.845779419,-31.939245224],"type":"Point"}
}