{
  "type": "Feature",
  "properties": {
    "iso:country":"AU",
    "sg:address":"Barraba Rd",
    "sg:city":"Bundarra",
    "sg:classifiers":[
        {
            "category":"Manufacturing",
            "subcategory":"Lumber",
            "type":"Manufacturing & Wholesale Goods"
        }
    ],
    "sg:phone":"+61 2 6723 7399",
    "sg:postcode":"2359",
    "sg:province":"NSW",
    "sg:tags":[
        "sawmillers"
    ],
    "wof:name":"Bundarra & District Sawmill",
    "wof:placetype":"venue"
},
  "geometry": {"coordinates":[151.063064575,-30.1782531738],"type":"Point"}
}