{
  "type": "Feature",
  "properties": {
    "addr:full":"Production St Bundaberg QLD 4670",
    "addr:postcode":"4670",
    "addr:street":"Production St",
    "iso:country":"AU",
    "sg:address":"Production St",
    "sg:city":"Bundaberg",
    "sg:classifiers":[
        {
            "category":"Retail",
            "subcategory":"Car Wash",
            "type":"Services"
        }
    ],
    "sg:phone":"+61 7 4153 1071",
    "sg:postcode":"4670",
    "sg:province":"QLD",
    "sg:tags":[
        "bitumen",
        "spraying"
    ],
    "wof:name":"Boral Asphalt",
    "wof:placetype":"venue"
},
  "geometry": {"coordinates":[152.329681397,-24.8893260956],"type":"Point"}
}