{
  "type": "Feature",
  "properties": {
    "iso:country":"AU",
    "sg:address":"Latona St",
    "sg:city":"West Pymble",
    "sg:classifiers":[
        {
            "category":"Professional",
            "subcategory":"Engineering",
            "type":"Services"
        }
    ],
    "sg:phone":"+61 2 9488 8635",
    "sg:postcode":"2073",
    "sg:province":"NSW",
    "sg:tags":[
        "engineer",
        "structural"
    ],
    "wof:name":"Geoff Hopkins & Associates Pty Ltd",
    "wof:placetype":"venue"
},
  "geometry": {"coordinates":[151.13142395,-33.7553787231],"type":"Point"}
}