{
  "type": "Feature",
  "properties": {
    "addr:full":"33 Burnie St Clovelly NSW 2031",
    "addr:housenumber":"33",
    "addr:postcode":"2031",
    "addr:street":"Burnie St",
    "iso:country":"AU",
    "sg:address":"33 Burnie St",
    "sg:city":"Clovelly",
    "sg:classifiers":[
        {
            "category":"Professional",
            "subcategory":"Detective & Security Services",
            "type":"Services"
        }
    ],
    "sg:phone":"+61 2 9664 6644",
    "sg:postcode":"2031",
    "sg:province":"NSW",
    "sg:tags":[
        "guard",
        "patrol"
    ],
    "wof:name":"Australia Wide Security Brokers Pty Ltd",
    "wof:placetype":"venue"
},
  "geometry": {"coordinates":[151.26222229000001,-33.9120025635],"type":"Point"}
}