{
  "type": "Feature",
  "properties": {
    "addr:full":"12 Aldinga St Brendale QLD 4500",
    "addr:housenumber":"12",
    "addr:postcode":"4500",
    "addr:street":"Aldinga St",
    "iso:country":"AU",
    "sg:address":"12 Aldinga St",
    "sg:city":"Brendale",
    "sg:classifiers":[
        {
            "category":"Manufacturing",
            "subcategory":"Furniture",
            "type":"Manufacturing & Wholesale Goods"
        }
    ],
    "sg:phone":"+61 7 3889 9993",
    "sg:postcode":"4500",
    "sg:province":"QLD",
    "sg:tags":[
        "builder",
        "designer",
        "custom"
    ],
    "wof:name":"Robert Dunlop Woodcraft",
    "wof:placetype":"venue"
},
  "geometry": {"coordinates":[152.97918701200001,-27.3186225891],"type":"Point"}
}