{
  "type": "Feature",
  "properties": {
    "addr:full":"3/ 9 Delatour St Coconut Grove NT 0810",
    "addr:housenumber":"/ 9",
    "addr:postcode":"0810",
    "addr:street":"Delatour St",
    "iso:country":"AU",
    "sg:address":"3/ 9 Delatour St",
    "sg:city":"Coconut Grove",
    "sg:classifiers":[
        {
            "category":"Autos & Motor Vehicles",
            "subcategory":"Auto Supplies",
            "type":"Retail Goods"
        }
    ],
    "sg:phone":"+61 8 8985 1176",
    "sg:postcode":"0810",
    "sg:province":"NT",
    "sg:tags":[
        "accessory"
    ],
    "wof:name":"Freddys Car Installations",
    "wof:placetype":"venue"
},
  "geometry": {"coordinates":[130.85496520999999,-12.4014129639],"type":"Point"}
}