{
  "type": "Feature",
  "properties": {
    "addr:full":"933 Whitehorse Rd Box Hill VIC 3128",
    "addr:housenumber":"933",
    "addr:postcode":"3128",
    "addr:street":"Whitehorse Rd",
    "iso:country":"AU",
    "sg:address":"933 Whitehorse Rd",
    "sg:city":"Box Hill",
    "sg:classifiers":[
        {
            "category":"Professional",
            "subcategory":"Computer Services",
            "type":"Services"
        }
    ],
    "sg:phone":"+61 3 9898 0252",
    "sg:postcode":"3128",
    "sg:province":"VIC",
    "sg:tags":[
        "repairs",
        "upgrade",
        "equipment"
    ],
    "wof:name":"I Mint",
    "wof:placetype":"venue"
},
  "geometry": {"coordinates":[145.12278747600001,-37.8176498413],"type":"Point"}
}