{
  "type": "Feature",
  "properties": {
    "addr:full":"U4/ 5 Moorlands Rd Ingleburn NSW 2565",
    "addr:housenumber":"5",
    "addr:postcode":"2565",
    "addr:street":"U4 /;Moorlands Rd",
    "iso:country":"AU",
    "sg:address":"U4/ 5 Moorlands Rd",
    "sg:city":"Ingleburn",
    "sg:classifiers":[
        {
            "category":"Home & Garden",
            "subcategory":"Building Materials",
            "type":"Retail Goods"
        }
    ],
    "sg:phone":"+61 2 8796 5300",
    "sg:postcode":"2565",
    "sg:province":"NSW",
    "sg:tags":[
        "ventilating",
        "equipment",
        "system"
    ],
    "wof:name":"Twista Industries Pty Ltd",
    "wof:placetype":"venue"
},
  "geometry": {"coordinates":[150.85382080100001,-34.0023803711],"type":"Point"}
}