{
  "type": "Feature",
  "properties": {
    "iso:country":"AU",
    "sg:address":"9 Collingwood St",
    "sg:city":"Dianella",
    "sg:classifiers":[
        {
            "category":"Professional",
            "subcategory":"Art Services",
            "type":"Services"
        }
    ],
    "sg:phone":"+61 8 9275 6889",
    "sg:postcode":"6059",
    "sg:province":"WA",
    "sg:tags":[
        "decorator",
        "painter"
    ],
    "wof:name":"Cinquegrana A",
    "wof:placetype":"venue"
},
  "geometry": {"coordinates":[115.877937317,-31.8853321075],"type":"Point"}
}