{
  "type": "Feature",
  "properties": {
    "addr:full":"103 Kensington Rd Norwood SA 5067",
    "addr:housenumber":"103",
    "addr:postcode":"5067",
    "addr:street":"Kensington Rd",
    "iso:country":"AU",
    "sg:address":"103 Kensington Rd",
    "sg:city":"Norwood",
    "sg:classifiers":[
        {
            "category":"Professional",
            "subcategory":"Accounting & Tax Preparation",
            "type":"Services"
        }
    ],
    "sg:phone":"+61 8 8364 1300",
    "sg:postcode":"5067",
    "sg:province":"SA",
    "sg:tags":[
        "accountant",
        "auditor"
    ],
    "wof:name":"Macklin David R",
    "wof:placetype":"venue"
},
  "geometry": {"coordinates":[138.63323974599999,-34.9272041321],"type":"Point"}
}