{
  "type": "Feature",
  "properties": {
    "iso:country":"AU",
    "sg:address":"Unit 1/ 18 Tolmer Pl",
    "sg:city":"Springwood",
    "sg:classifiers":[
        {
            "category":"Home & Garden",
            "subcategory":"Building Materials",
            "type":"Retail Goods"
        }
    ],
    "sg:phone":"+61 1300 666 232",
    "sg:postcode":"4127",
    "sg:province":"QLD",
    "sg:tags":[
        "fitting",
        "door"
    ],
    "wof:name":"Albany Door Systems",
    "wof:placetype":"venue"
},
  "geometry": {"coordinates":[153.13168335,-27.6257171631],"type":"Point"}
}