{
  "type": "Feature",
  "properties": {
    "addr:full":"7a Jedda Rd Balcatta WA 6021",
    "addr:housenumber":"7a",
    "addr:postcode":"6021",
    "addr:street":"Jedda Rd",
    "iso:country":"AU",
    "sg:address":"7a Jedda Rd",
    "sg:city":"Balcatta",
    "sg:classifiers":[
        {
            "category":"Personal",
            "type":"Services"
        }
    ],
    "sg:phone":"+61 8 9344 4720",
    "sg:postcode":"6021",
    "sg:province":"WA",
    "sg:tags":[
        "gift"
    ],
    "wof:name":"Bramsen Imports",
    "wof:placetype":"venue"
},
  "geometry": {"coordinates":[115.83036041299999,-31.8840236664],"type":"Point"}
}