{
  "type": "Feature",
  "properties": {
    "iso:country":"AU",
    "sg:address":"79 Queens Rd",
    "sg:city":"Everton Hills",
    "sg:classifiers":[
        {
            "category":"Government",
            "subcategory":"Court House",
            "type":"Public Place"
        }
    ],
    "sg:phone":"+61 7 3353 0796",
    "sg:postcode":"4053",
    "sg:province":"QLD",
    "sg:tags":[
        "personal",
        "marriage",
        "family",
        "counselling"
    ],
    "wof:name":"Hills Wesleyan Family Support Service",
    "wof:placetype":"venue"
},
  "geometry": {"coordinates":[152.98164367699999,-27.3868560791],"type":"Point"}
}