{
  "type": "Feature",
  "properties": {
    "addr:full":"5a / 2a Victoria Avenue Castle Hill NSW 2154",
    "addr:housenumber":"5a / 2a",
    "addr:postcode":"2154",
    "addr:street":"Victoria Avenue",
    "iso:country":"AU",
    "sg:address":"5a / 2a Victoria Avenue",
    "sg:city":"Castle Hill",
    "sg:classifiers":[
        {
            "category":"Autos & Motor Vehicles",
            "subcategory":"Auto Supplies",
            "type":"Retail Goods"
        }
    ],
    "sg:phone":"+61 2 9899 5207",
    "sg:postcode":"2154",
    "sg:province":"NSW",
    "sg:tags":[
        "slot",
        "car",
        "equipment"
    ],
    "wof:name":"Hobbies In The Hills",
    "wof:placetype":"venue"
},
  "geometry": {"coordinates":[150.98342895499999,-33.7371292114],"type":"Point"}
}