{
  "type": "Feature",
  "properties": {
    "iso:country":"AU",
    "sg:address":"189 Beecroft Rd",
    "sg:city":"Cheltenham",
    "sg:classifiers":[
        {
            "category":"Autos & Motor Vehicles",
            "subcategory":"Boat Sales",
            "type":"Retail Goods"
        }
    ],
    "sg:phone":"+61 2 9868 6911",
    "sg:postcode":"2119",
    "sg:province":"NSW",
    "sg:tags":[
        "yacht"
    ],
    "wof:name":"Portable Boats Australia",
    "wof:placetype":"venue"
},
  "geometry": {"coordinates":[151.075317383,-33.7587127686],"type":"Point"}
}