{
  "type": "Feature",
  "properties": {
    "iso:country":"AU",
    "sg:address":"Cnr Eddy Ave & Pitt St",
    "sg:city":"Sydney",
    "sg:classifiers":[
        {
            "category":"Travel",
            "subcategory":"Travel Agent",
            "type":"Entertainment"
        }
    ],
    "sg:phone":"+61 2 9281 9366",
    "sg:postcode":"2000",
    "sg:province":"NSW",
    "sg:tags":[
        "tour",
        "holiday",
        "adventure"
    ],
    "wof:name":"Sydney Coach Terminal The",
    "wof:placetype":"venue"
},
  "geometry": {"coordinates":[151.20591735799999,-33.8816108704],"type":"Point"}
}