{
  "type": "Feature",
  "properties": {
    "addr:full":"1290 Ballarto Rd Cranbourne VIC 3977",
    "addr:postcode":"1290;3977",
    "addr:street":"Ballarto Rd",
    "iso:country":"AU",
    "sg:address":"1290 Ballarto Rd",
    "sg:city":"Cranbourne",
    "sg:classifiers":[
        {
            "category":"Building & Trades",
            "subcategory":"Construction",
            "type":"Services"
        }
    ],
    "sg:phone":"+61 1300 307 266",
    "sg:postcode":"3977",
    "sg:province":"VIC",
    "sg:tags":[
        "home",
        "air conditioning"
    ],
    "wof:name":"Complete Climate Control Systems",
    "wof:placetype":"venue"
},
  "geometry": {"coordinates":[145.300872803,-38.1305427551],"type":"Point"}
}