{
  "type": "Feature",
  "properties": {
    "iso:country":"AU",
    "sg:address":"600 Station St",
    "sg:city":"Box Hill",
    "sg:classifiers":[
        {
            "category":"Fast Food",
            "type":"Food & Drink"
        }
    ],
    "sg:phone":"+61 3 9890 7522",
    "sg:postcode":"3128",
    "sg:province":"VIC",
    "sg:tags":[
        "away",
        "take"
    ],
    "wof:name":"La Porchetta",
    "wof:placetype":"venue"
},
  "geometry": {"coordinates":[145.12385559099999,-37.8188209534],"type":"Point"}
}