{
  "type": "Feature",
  "properties": {
    "addr:full":"GPO Box 1461 Darwin NT 0800",
    "addr:postcode":"nt 0800",
    "iso:country":"AU",
    "sg:address":"GPO Box 1461",
    "sg:city":"Darwin",
    "sg:classifiers":[
        {
            "category":"Real Estate",
            "subcategory":"Architect",
            "type":"Services"
        }
    ],
    "sg:phone":"+61 8 8981 6466",
    "sg:postcode":"0800",
    "sg:province":"NT",
    "sg:tags":[
        "building",
        "designer"
    ],
    "wof:name":"Draftlink",
    "wof:placetype":"venue"
},
  "geometry": {"coordinates":[130.84231567399999,-12.4620399475],"type":"Point"}
}