{
  "type": "Feature",
  "properties": {
    "addr:full":"Shop 7/ 23 Southpine Rd Alderley QLD 4051",
    "addr:housenumber":"shop 7 / 23",
    "addr:postcode":"4051",
    "addr:street":"Southpine Rd",
    "iso:country":"AU",
    "sg:address":"Shop 7/ 23 Southpine Rd",
    "sg:city":"Alderley",
    "sg:classifiers":[
        {
            "category":"Personal",
            "subcategory":"Beauty Salon",
            "type":"Services"
        }
    ],
    "sg:phone":"+61 7 3856 5845",
    "sg:postcode":"4051",
    "sg:province":"QLD",
    "sg:tags":[
        "hairdresser"
    ],
    "wof:name":"Janets Angel Salon",
    "wof:placetype":"venue"
},
  "geometry": {"coordinates":[152.99920654300001,-27.4246997833],"type":"Point"}
}