{
  "type": "Feature",
  "properties": {
    "addr:full":"U3/ 2 Baltic Crt Maddington WA 6109",
    "addr:housenumber":"2",
    "addr:postcode":"6109",
    "addr:street":"U3 /;Baltic Crt",
    "iso:country":"AU",
    "sg:address":"U3/ 2 Baltic Crt",
    "sg:city":"Maddington",
    "sg:classifiers":[
        {
            "category":"Sports & Exercise",
            "subcategory":"Race Track",
            "type":"Entertainment"
        }
    ],
    "sg:phone":"+61 8 9452 7806",
    "sg:postcode":"6109",
    "sg:province":"WA",
    "sg:tags":[
        "access",
        "cover",
        "grating"
    ],
    "wof:name":"First Time Fabrication Pty Ltd",
    "wof:placetype":"venue"
},
  "geometry": {"coordinates":[115.99356079099999,-32.0347747803],"type":"Point"}
}