{
  "type": "Feature",
  "properties": {
    "iso:country":"AU",
    "sg:address":"U1/ 6 Moore St",
    "sg:city":"Birmingham Gardens",
    "sg:classifiers":[
        {
            "category":"Personal",
            "subcategory":"Beauty Salon",
            "type":"Services"
        }
    ],
    "sg:phone":"+61 2 4951 1233",
    "sg:postcode":"2287",
    "sg:province":"NSW",
    "sg:tags":[
        "hairdresser"
    ],
    "wof:name":"Unified Hair Artistry",
    "wof:placetype":"venue"
},
  "geometry": {"coordinates":[151.69424438499999,-32.8959197998],"type":"Point"}
}