{
  "type": "Feature",
  "properties": {
    "iso:country":"AU",
    "sg:address":"7 Fourth Ave",
    "sg:city":"Sandgate",
    "sg:classifiers":[
        {
            "category":"Shopping",
            "subcategory":"Clothing, Apparel, & Fashions",
            "type":"Retail Goods"
        }
    ],
    "sg:phone":"+61 7 3269 2255",
    "sg:postcode":"4017",
    "sg:province":"QLD",
    "sg:tags":[
        "lady",
        "wear"
    ],
    "wof:name":"Fourth Avenue Fashions",
    "wof:placetype":"venue"
},
  "geometry": {"coordinates":[153.06906127900001,-27.3187026978],"type":"Point"}
}