{
  "type": "Feature",
  "properties": {
    "addr:full":"30 Derribong St Trangie NSW 2823",
    "addr:housenumber":"30",
    "addr:postcode":"2823",
    "addr:street":"Derribong St",
    "iso:country":"AU",
    "sg:address":"30 Derribong St",
    "sg:city":"Trangie",
    "sg:classifiers":[
        {
            "category":"Government",
            "subcategory":"Post Office",
            "type":"Public Place"
        }
    ],
    "sg:phone":"+61 2 6888 7197",
    "sg:postcode":"2823",
    "sg:province":"NSW",
    "sg:tags":[
        "postal"
    ],
    "wof:name":"Australia Post",
    "wof:placetype":"venue"
},
  "geometry": {"coordinates":[147.98031616200001,-32.031703949],"type":"Point"}
}