{
  "type": "Feature",
  "properties": {
    "addr:full":"William Rd Berry Springs NT 0837",
    "addr:postcode":"nt 0837",
    "addr:street":"William Rd",
    "iso:country":"AU",
    "sg:address":"William Rd",
    "sg:city":"Berry Springs",
    "sg:classifiers":[
        {
            "category":"Real Estate",
            "subcategory":"Architect",
            "type":"Services"
        }
    ],
    "sg:phone":"+61 8 8988 6360",
    "sg:postcode":"0837",
    "sg:province":"NT",
    "sg:tags":[
        "building",
        "designer"
    ],
    "wof:name":"Adept Services (NT) Pty Ltd",
    "wof:placetype":"venue"
},
  "geometry": {"coordinates":[130.96821600000001,-12.723589],"type":"Point"}
}