{
  "type": "Feature",
  "properties": {
    "iso:country":"AU",
    "sg:address":"92b Arizona Rd",
    "sg:city":"Charmhaven",
    "sg:classifiers":[
        {
            "category":"Autos & Motor Vehicles",
            "subcategory":"Motorcycle Sales",
            "type":"Retail Goods"
        }
    ],
    "sg:phone":"+61 2 4394 0599",
    "sg:postcode":"2263",
    "sg:province":"NSW",
    "sg:tags":[
        "outboard"
    ],
    "wof:name":"Trueblue Marine Services",
    "wof:placetype":"venue"
},
  "geometry": {"coordinates":[151.49032600000001,-33.231586],"type":"Point"}
}