{
  "type": "Feature",
  "properties": {
    "addr:full":"Lot 1 McIntyre Way Bomaderry NSW 2541",
    "addr:housenumber":"1",
    "addr:postcode":"2541",
    "addr:street":"Mcintyre Way",
    "iso:country":"AU",
    "sg:address":"Lot 1",
    "sg:city":"McIntyre Way Bomaderry",
    "sg:classifiers":[
        {
            "category":"Autos & Motor Vehicles",
            "subcategory":"Auto Supplies",
            "type":"Retail Goods"
        }
    ],
    "sg:phone":"+61 2 4423 4611",
    "sg:postcode":"2541",
    "sg:province":"NSW",
    "sg:tags":[
        "battery",
        "automotive"
    ],
    "wof:name":"Ken Nicholls Auto Electrical & Air Conditioning",
    "wof:placetype":"venue"
},
  "geometry": {"coordinates":[150.61135864299999,-34.8460655212],"type":"Point"}
}