{
  "type": "Feature",
  "properties": {
    "addr:full":"4 Newland Drv West Beach SA 5024",
    "addr:housenumber":"4",
    "addr:postcode":"5024",
    "addr:street":"Newland Drv",
    "iso:country":"AU",
    "sg:address":"4 Newland Drv",
    "sg:city":"West Beach",
    "sg:classifiers":[
        {
            "category":"Real Estate",
            "subcategory":"Real Estate Agent",
            "type":"Services"
        }
    ],
    "sg:phone":"+61 8 8356 3851",
    "sg:postcode":"5024",
    "sg:province":"SA",
    "wof:name":"Joan Mutton Real Estate",
    "wof:placetype":"venue"
},
  "geometry": {"coordinates":[138.50663757300001,-34.938331604],"type":"Point"}
}