{
  "type": "Feature",
  "properties": {
    "addr:full":"PO Box 160 Hampton Park VIC 3976",
    "addr:postcode":"3976",
    "iso:country":"AU",
    "sg:address":"PO Box 160",
    "sg:city":"Hampton Park",
    "sg:classifiers":[
        {
            "category":"Building & Trades",
            "subcategory":"Construction",
            "type":"Services"
        }
    ],
    "sg:phone":"+61 418 127 585",
    "sg:postcode":"3976",
    "sg:province":"VIC",
    "sg:tags":[
        "fencing",
        "contractor"
    ],
    "wof:name":"Lyndsy's Fencing",
    "wof:placetype":"venue"
},
  "geometry": {"coordinates":[145.26762390100001,-38.0422897339],"type":"Point"}
}