{
  "type": "Feature",
  "properties": {
    "iso:country":"AU",
    "sg:address":"23 Rowles Drv",
    "sg:city":"Maryborough",
    "sg:classifiers":[
        {
            "category":"Personal",
            "subcategory":"Beauty Salon",
            "type":"Services"
        }
    ],
    "sg:phone":"+61 3 5460 5332",
    "sg:postcode":"3465",
    "sg:province":"VIC",
    "wof:name":"Murray Sharon",
    "wof:placetype":"venue"
},
  "geometry": {"coordinates":[143.745559692,-37.0274353027],"type":"Point"}
}