{
  "type": "Feature",
  "properties": {
    "iso:country":"AU",
    "sg:address":"10 Jitra Pl",
    "sg:city":"Tanah Merah",
    "sg:classifiers":[
        {
            "category":"Home & Garden",
            "subcategory":"Carpets & Floor Coverings",
            "type":"Retail Goods"
        }
    ],
    "sg:phone":"+61 413 876 193",
    "sg:postcode":"4128",
    "sg:province":"QLD",
    "sg:tags":[
        "tile",
        "wall",
        "layer"
    ],
    "wof:name":"Dragon Tiling",
    "wof:placetype":"venue"
},
  "geometry": {"coordinates":[153.17312622099999,-27.6801185608],"type":"Point"}
}