{
  "type": "Feature",
  "properties": {
    "addr:full":"Palm Trees Rd Ravensbourne QLD 4352",
    "addr:postcode":"4352",
    "addr:street":"Trees Rd",
    "iso:country":"AU",
    "sg:address":"Palm Trees Rd",
    "sg:city":"Ravensbourne",
    "sg:classifiers":[
        {
            "category":"Farming",
            "subcategory":"Farm",
            "type":"Manufacturing & Wholesale Goods"
        }
    ],
    "sg:phone":"+61 7 4697 8191",
    "sg:postcode":"4352",
    "sg:province":"QLD",
    "sg:tags":[
        "farmer"
    ],
    "wof:name":"Perseverence Farming Co",
    "wof:placetype":"venue"
},
  "geometry": {"coordinates":[152.18594400000001,-27.337139],"type":"Point"}
}