{
  "type": "Feature",
  "properties": {
    "addr:full":"27 Amiens St Lithgow NSW 2790",
    "addr:housenumber":"27",
    "addr:postcode":"2790",
    "addr:street":"Amiens St",
    "iso:country":"AU",
    "sg:address":"27 Amiens St",
    "sg:city":"Lithgow",
    "sg:classifiers":[
        {
            "category":"Home & Garden",
            "subcategory":"Carpets & Floor Coverings",
            "type":"Retail Goods"
        }
    ],
    "sg:phone":"+61 2 6353 1095",
    "sg:postcode":"2790",
    "sg:province":"NSW",
    "sg:tags":[
        "tile",
        "wall"
    ],
    "wof:name":"Schwertzberger Uri",
    "wof:placetype":"venue"
},
  "geometry": {"coordinates":[150.13453674300001,-33.4938163757],"type":"Point"}
}