{
  "type": "Feature",
  "properties": {
    "addr:full":"Unit 4, 182 Manns Rd Gosford West NSW 2250",
    "addr:housenumber":"182",
    "addr:postcode":"2250",
    "addr:street":"Manns Rd",
    "iso:country":"AU",
    "sg:address":"Unit 4, 182 Manns Rd",
    "sg:city":"Gosford West",
    "sg:classifiers":[
        {
            "category":"Building & Trades",
            "subcategory":"Construction",
            "type":"Services"
        }
    ],
    "sg:phone":"+61 1300 559 533",
    "sg:postcode":"2250",
    "sg:province":"NSW",
    "sg:tags":[
        "home",
        "air conditioning"
    ],
    "wof:name":"Brisbane Water Air Conditioning Pty Ltd",
    "wof:placetype":"venue"
},
  "geometry": {"coordinates":[151.319488525,-33.4242134094],"type":"Point"}
}