{
  "type": "Feature",
  "properties": {
    "iso:country":"AU",
    "sg:address":"U 4/ 5 Johnstone Rd",
    "sg:city":"Brendale",
    "sg:classifiers":[
        {
            "category":"Home & Garden",
            "subcategory":"Building Materials",
            "type":"Retail Goods"
        }
    ],
    "sg:phone":"+61 7 3205 4757",
    "sg:postcode":"4500",
    "sg:province":"QLD",
    "sg:tags":[
        "balustrading"
    ],
    "wof:name":"McIntyre Stainless",
    "wof:placetype":"venue"
},
  "geometry": {"coordinates":[152.98797607399999,-27.3214206696],"type":"Point"}
}