{
  "type": "Feature",
  "properties": {
    "iso:country":"AU",
    "sg:address":"15 Bay St",
    "sg:city":"Double Bay",
    "sg:classifiers":[
        {
            "category":"Personal",
            "subcategory":"Day Spa",
            "type":"Services"
        }
    ],
    "sg:phone":"+61 2 9328 5501",
    "sg:postcode":"2028",
    "sg:province":"NSW",
    "wof:name":"Angsana Spa Double Bay Sydney",
    "wof:placetype":"venue"
},
  "geometry": {"coordinates":[151.241577148,-33.8780975342],"type":"Point"}
}