{
  "type": "Feature",
  "properties": {
    "addr:full":"95 Crown St Wollongong NSW 2500",
    "addr:housenumber":"95",
    "addr:postcode":"2500",
    "addr:street":"Crown St",
    "iso:country":"AU",
    "sg:address":"95 Crown St",
    "sg:city":"Wollongong",
    "sg:classifiers":[
        {
            "category":"Real Estate",
            "subcategory":"Developer",
            "type":"Services"
        }
    ],
    "sg:phone":"+61 2 4228 4200",
    "sg:postcode":"2500",
    "sg:province":"NSW",
    "sg:tags":[
        "development"
    ],
    "wof:name":"Sebvell Living",
    "wof:placetype":"venue"
},
  "geometry": {"coordinates":[150.897659,-34.42569],"type":"Point"}
}