{
  "type": "Feature",
  "properties": {
    "addr:full":"shop 2/ 9 Kulin Way Mandurah WA 6210",
    "addr:housenumber":"shop 2 / 9",
    "addr:postcode":"6210",
    "addr:street":"Kulin Way",
    "iso:country":"AU",
    "sg:address":"shop 2/ 9 Kulin Way",
    "sg:city":"Mandurah",
    "sg:classifiers":[
        {
            "category":"Sports & Exercise",
            "subcategory":"Gym",
            "type":"Entertainment"
        }
    ],
    "sg:phone":"+61 438 909 981",
    "sg:postcode":"6210",
    "sg:province":"WA",
    "sg:tags":[
        "health",
        "fitness"
    ],
    "wof:name":"Hoddinott Sue",
    "wof:placetype":"venue"
},
  "geometry": {"coordinates":[115.74028,-32.513439],"type":"Point"}
}