{
  "type": "Feature",
  "properties": {
    "iso:country":"AU",
    "sg:address":"449 Moorabool St",
    "sg:city":"South Geelong",
    "sg:classifiers":[
        {
            "category":"Autos & Motor Vehicles",
            "subcategory":"Auto Supplies",
            "type":"Retail Goods"
        }
    ],
    "sg:phone":"+61 3 5229 6833",
    "sg:postcode":"3220",
    "sg:province":"VIC",
    "sg:tags":[
        "tyre"
    ],
    "wof:name":"Advantage Geelong",
    "wof:placetype":"venue"
},
  "geometry": {"coordinates":[144.354675,-38.160774],"type":"Point"}
}