{
  "type": "Feature",
  "properties": {
    "iso:country":"AU",
    "sg:address":"1 Narrogal Crt",
    "sg:city":"Ocean Shores",
    "sg:classifiers":[
        {
            "category":"Retail",
            "subcategory":"Storage",
            "type":"Services"
        }
    ],
    "sg:phone":"+61 2 6680 1158",
    "sg:postcode":"2483",
    "sg:province":"NSW",
    "sg:tags":[
        "removal",
        "furniture"
    ],
    "wof:name":"Beyond Byron Removals",
    "wof:placetype":"venue"
},
  "geometry": {"coordinates":[153.51637268100001,-28.4881706238],"type":"Point"}
}