{
  "type": "Feature",
  "properties": {
    "addr:full":"Broad St Eugowra NSW 2806",
    "addr:postcode":"2806",
    "addr:street":"Broad St",
    "iso:country":"AU",
    "sg:address":"Broad St",
    "sg:city":"Eugowra",
    "sg:classifiers":[
        {
            "category":"Travel",
            "subcategory":"Hotels & Motels",
            "type":"Entertainment"
        }
    ],
    "sg:phone":"+61 2 6859 2253",
    "sg:postcode":"2806",
    "sg:province":"NSW",
    "sg:tags":[
        "accommodation"
    ],
    "wof:name":"Fat Lamb Hotel",
    "wof:placetype":"venue"
},
  "geometry": {"coordinates":[148.368743897,-33.4270095825],"type":"Point"}
}