{
  "type": "Feature",
  "properties": {
    "addr:full":"423- 425 Princes Hwy Rockdale NSW 2216",
    "addr:housenumber":"425",
    "addr:postcode":"2216",
    "addr:street":"Princes Hwy",
    "iso:country":"AU",
    "sg:address":"423- 425 Princes Hwy",
    "sg:city":"Rockdale",
    "sg:classifiers":[
        {
            "category":"Personal",
            "type":"Services"
        }
    ],
    "sg:phone":"+61 2 9597 3311",
    "sg:postcode":"2216",
    "sg:province":"NSW",
    "sg:tags":[
        "gift"
    ],
    "wof:name":"A. Allmans Quality Flowers & Gift Baskets For All Occasions (Since 1936) Member Of Interflora",
    "wof:placetype":"venue"
},
  "geometry": {"coordinates":[151.137787,-33.958721],"type":"Point"}
}