{
  "type": "Feature",
  "properties": {
    "addr:full":"Shp5/ 82 Beach St Woolgoolga NSW 2456",
    "addr:housenumber":"82",
    "addr:postcode":"2456",
    "addr:street":"Beach St",
    "iso:country":"AU",
    "sg:address":"Shp5/ 82 Beach St",
    "sg:city":"Woolgoolga",
    "sg:classifiers":[
        {
            "category":"Ice Cream",
            "type":"Food & Drink"
        }
    ],
    "sg:phone":"+61 2 6654 9854",
    "sg:postcode":"2456",
    "sg:province":"NSW",
    "sg:tags":[
        "retail"
    ],
    "wof:name":"Passions Ice Cream Shop",
    "wof:placetype":"venue"
},
  "geometry": {"coordinates":[153.20053100000001,-30.06328],"type":"Point"}
}