{
  "type": "Feature",
  "properties": {
    "addr:full":"1 Sharman Crt Bentleigh VIC 3204",
    "addr:housenumber":"1",
    "addr:postcode":"3204",
    "addr:street":"Sharman Crt",
    "iso:country":"AU",
    "sg:address":"1 Sharman Crt",
    "sg:city":"Bentleigh",
    "sg:classifiers":[
        {
            "category":"Professional",
            "subcategory":"Business Services",
            "type":"Services"
        }
    ],
    "sg:phone":"+61 3 9557 7323",
    "sg:postcode":"3204",
    "sg:province":"VIC",
    "sg:tags":[
        "drafting"
    ],
    "wof:name":"Bentleigh Drafting Service",
    "wof:placetype":"venue"
},
  "geometry": {"coordinates":[145.04968299999999,-37.921757],"type":"Point"}
}