{
  "type": "Feature",
  "properties": {
    "addr:full":"333 Walter Rd Morley WA 6062",
    "addr:housenumber":"333",
    "addr:postcode":"6062",
    "addr:street":"Walter Rd",
    "iso:country":"AU",
    "sg:address":"333 Walter Rd",
    "sg:city":"Morley",
    "sg:classifiers":[
        {
            "category":"Autos & Motor Vehicles",
            "subcategory":"Auto Supplies",
            "type":"Retail Goods"
        }
    ],
    "sg:phone":"+61 8 9276 4090",
    "sg:postcode":"6062",
    "sg:province":"WA",
    "sg:tags":[
        "battery",
        "automotive"
    ],
    "wof:name":"Scorpion Auto & Batteries",
    "wof:placetype":"venue"
},
  "geometry": {"coordinates":[115.891059876,-31.8979473114],"type":"Point"}
}