{
  "type": "Feature",
  "properties": {
    "iso:country":"AU",
    "sg:address":"14 Fisher Rd",
    "sg:city":"Dee Why",
    "sg:classifiers":[
        {
            "category":"Shopping",
            "subcategory":"Computers & Home Electronics",
            "type":"Retail Goods"
        }
    ],
    "sg:phone":"+61 2 9972 2622",
    "sg:postcode":"2099",
    "sg:province":"NSW",
    "sg:tags":[
        "hardware",
        "equipment"
    ],
    "wof:name":"Softhard Computers Pty Ltd",
    "wof:placetype":"venue"
},
  "geometry": {"coordinates":[151.28468322800001,-33.7532157898],"type":"Point"}
}