{
  "type": "Feature",
  "properties": {
    "addr:full":"2 Lake Tobin Crs Greenwith SA 5125",
    "addr:housenumber":"2",
    "addr:postcode":"5125",
    "addr:street":"Lake Tobin Crs",
    "iso:country":"AU",
    "sg:address":"2 Lake Tobin Crs",
    "sg:city":"Greenwith",
    "sg:classifiers":[
        {
            "category":"Building & Trades",
            "subcategory":"Plumbing",
            "type":"Services"
        }
    ],
    "sg:phone":"+61 413 645 283",
    "sg:postcode":"5125",
    "sg:province":"SA",
    "sg:tags":[
        "plumber",
        "gasfitters"
    ],
    "wof:name":"Chris Martin Plumbing Services",
    "wof:placetype":"venue"
},
  "geometry": {"coordinates":[138.718917847,-34.7696914673],"type":"Point"}
}