{
  "type": "Feature",
  "properties": {
    "addr:full":"Unit4 141 George Rd Salamander Bay NSW 2317",
    "addr:housenumber":"141",
    "addr:postcode":"2317",
    "addr:street":"George Rd",
    "iso:country":"AU",
    "sg:address":"Unit4 141 George Rd",
    "sg:city":"Salamander Bay",
    "sg:classifiers":[
        {
            "category":"Retail",
            "subcategory":"Repair Shop",
            "type":"Services"
        }
    ],
    "sg:phone":"+61 2 4984 6698",
    "sg:postcode":"2317",
    "sg:province":"NSW",
    "sg:tags":[
        "upholsterer"
    ],
    "wof:name":"Action Auto Upholstery & Marine Canvas",
    "wof:placetype":"venue"
},
  "geometry": {"coordinates":[152.07841500000001,-32.72628],"type":"Point"}
}