{
  "type": "Feature",
  "properties": {
    "addr:full":"12 Stretton Pl Balcatta WA 6021",
    "addr:housenumber":"12",
    "addr:postcode":"6021",
    "addr:street":"Pl",
    "iso:country":"AU",
    "sg:address":"12 Stretton Pl",
    "sg:city":"Balcatta",
    "sg:classifiers":[
        {
            "category":"Manufacturing",
            "subcategory":"Furniture",
            "type":"Manufacturing & Wholesale Goods"
        }
    ],
    "sg:phone":"+61 8 9240 9000",
    "sg:postcode":"6021",
    "sg:province":"WA",
    "sg:tags":[
        "builder",
        "designer",
        "custom"
    ],
    "wof:name":"International Cabinet's",
    "wof:placetype":"venue"
},
  "geometry": {"coordinates":[115.805717468,-31.8615646362],"type":"Point"}
}