{
  "type": "Feature",
  "properties": {
    "addr:full":"35 Stewart St Devonport TAS 7310",
    "addr:housenumber":"35",
    "addr:postcode":"7310",
    "addr:street":"Stewart St",
    "iso:country":"AU",
    "sg:address":"35 Stewart St",
    "sg:city":"Devonport",
    "sg:classifiers":[
        {
            "category":"Shopping",
            "subcategory":"Clothing, Apparel, & Fashions",
            "type":"Retail Goods"
        }
    ],
    "sg:phone":"+61 3 6424 2331",
    "sg:postcode":"7310",
    "sg:province":"TAS",
    "sg:tags":[
        "menswear"
    ],
    "wof:name":"Vin Reece Menswear",
    "wof:placetype":"venue"
},
  "geometry": {"coordinates":[146.36085510300001,-41.1800842285],"type":"Point"}
}