{
  "type": "Feature",
  "properties": {
    "addr:full":"23 Victoria Ave Concord West NSW 2138",
    "addr:housenumber":"23",
    "addr:postcode":"2138",
    "addr:street":"Victoria Ave",
    "iso:country":"AU",
    "sg:address":"23 Victoria Ave",
    "sg:city":"Concord West",
    "sg:classifiers":[
        {
            "category":"Real Estate",
            "subcategory":"Real Estate Services",
            "type":"Services"
        }
    ],
    "sg:phone":"+61 2 9743 1877",
    "sg:postcode":"2138",
    "sg:province":"NSW",
    "sg:tags":[
        "valuer"
    ],
    "wof:name":"Macquarie Bell Pty Limited",
    "wof:placetype":"venue"
},
  "geometry": {"coordinates":[151.086990356,-33.847869873],"type":"Point"}
}