{
  "type": "Feature",
  "properties": {
    "iso:country":"AU",
    "sg:address":"Victoria Rd",
    "sg:city":"Parramatta",
    "sg:classifiers":[
        {
            "category":"Banks & Credit Unions",
            "subcategory":"Bank",
            "type":"Services"
        }
    ],
    "sg:phone":"+61 1300 555 929",
    "sg:postcode":"1740",
    "sg:province":"NSW",
    "wof:name":"Finance House",
    "wof:placetype":"venue"
},
  "geometry": {"coordinates":[151.003448486,-33.8169593811],"type":"Point"}
}