{
  "type": "Feature",
  "properties": {
    "addr:full":"Hayman Rd Bentley WA 6102",
    "addr:postcode":"6102",
    "addr:street":"Hayman Rd",
    "iso:country":"AU",
    "sg:address":"Hayman Rd",
    "sg:city":"Bentley",
    "sg:classifiers":[
        {
            "category":"Restaurant",
            "type":"Food & Drink"
        }
    ],
    "sg:phone":"+61 8 9267 7219",
    "sg:postcode":"6102",
    "sg:province":"WA",
    "wof:name":"Bentley Pines Restaurant",
    "wof:placetype":"venue"
},
  "geometry": {"coordinates":[115.90007782000001,-32.0078125],"type":"Point"}
}