{
  "type": "Feature",
  "properties": {
    "iso:country":"AU",
    "sg:address":"11 Rankin St",
    "sg:city":"Altona",
    "sg:classifiers":[
        {
            "category":"Personal",
            "subcategory":"Beauty Salon",
            "type":"Services"
        }
    ],
    "sg:phone":"+61 3 9315 0777",
    "sg:postcode":"3018",
    "sg:province":"VIC",
    "sg:tags":[
        "hairdresser"
    ],
    "wof:name":"Michelle & Theresa Hairdressing",
    "wof:placetype":"venue"
},
  "geometry": {"coordinates":[144.81614685100001,-37.8683586121],"type":"Point"}
}