{
  "type": "Feature",
  "properties": {
    "addr:full":"34 Meredith St Bankstown NSW 2200",
    "addr:housenumber":"34",
    "addr:postcode":"2200",
    "addr:street":"Meredith St",
    "iso:country":"AU",
    "sg:address":"34 Meredith St",
    "sg:city":"Bankstown",
    "sg:classifiers":[
        {
            "category":"Health Services",
            "subcategory":"Doctor",
            "type":"Services"
        }
    ],
    "sg:phone":"+61 2 9796 1192",
    "sg:postcode":"2200",
    "sg:province":"NSW",
    "sg:tags":[
        "medical",
        "practitioner"
    ],
    "wof:name":"Patapanian Harry",
    "wof:placetype":"venue"
},
  "geometry": {"coordinates":[151.03157043499999,-33.9150810242],"type":"Point"}
}