{
  "type": "Feature",
  "properties": {
    "addr:full":"Unit 3/ 14 South St Wodonga VIC 3690",
    "addr:postcode":"3690",
    "addr:street":"14 South St",
    "iso:country":"AU",
    "sg:address":"Unit 3/ 14 South St",
    "sg:city":"Wodonga",
    "sg:classifiers":[
        {
            "category":"Utilities",
            "subcategory":"Telephone",
            "type":"Services"
        }
    ],
    "sg:phone":"+61 1300 850 698",
    "sg:postcode":"3690",
    "sg:province":"VIC",
    "sg:tags":[
        "installation",
        "system",
        "maintenance"
    ],
    "sg:website":"http://www.tcsrdirect.com.au",
    "wof:name":"TCS-R-Direct",
    "wof:placetype":"venue"
},
  "geometry": {"coordinates":[146.89028930699999,-36.1189727783],"type":"Point"}
}