{
  "type": "Feature",
  "properties": {
    "addr:full":"160 Norton St Leichhardt NSW 2040",
    "addr:housenumber":"160",
    "addr:postcode":"2040",
    "addr:street":"Norton St",
    "iso:country":"AU",
    "sg:address":"160 Norton St",
    "sg:city":"Leichhardt",
    "sg:classifiers":[
        {
            "category":"Personal",
            "subcategory":"Beauty Salon",
            "type":"Services"
        }
    ],
    "sg:phone":"+61 2 9569 8046",
    "sg:postcode":"2040",
    "sg:province":"NSW",
    "sg:tags":[
        "hairdresser"
    ],
    "wof:name":"Claire Hair Studio",
    "wof:placetype":"venue"
},
  "geometry": {"coordinates":[151.15666200000001,-33.881668],"type":"Point"}
}