{
  "type": "Feature",
  "properties": {
    "iso:country":"AU",
    "sg:address":"32B Studpark Shopng Cntr Stud Rd",
    "sg:city":"Rowville",
    "sg:classifiers":[
        {
            "category":"Professional",
            "subcategory":"Accounting & Tax Preparation",
            "type":"Services"
        }
    ],
    "sg:phone":"+61 3 9764 0295",
    "sg:postcode":"3178",
    "sg:province":"VIC",
    "sg:tags":[
        "consultant",
        "taxation"
    ],
    "wof:name":"H&R Block",
    "wof:placetype":"venue"
},
  "geometry": {"coordinates":[145.233917236,-37.9236564636],"type":"Point"}
}