{
  "type": "Feature",
  "properties": {
    "iso:country":"AU",
    "sg:address":"L2/ 135 Fullarton Rd",
    "sg:city":"Rose Park",
    "sg:classifiers":[
        {
            "category":"Banks & Credit Unions",
            "subcategory":"Financial Services",
            "type":"Services"
        }
    ],
    "sg:phone":"+61 8 8332 4700",
    "sg:postcode":"5067",
    "sg:province":"SA",
    "sg:tags":[
        "planning"
    ],
    "wof:name":"Proxima Financial Planning",
    "wof:placetype":"venue"
},
  "geometry": {"coordinates":[138.62384033199999,-34.9281463623],"type":"Point"}
}