{
  "type": "Feature",
  "properties": {
    "addr:full":"Shop 345 Killarney Vale Arcade Wyong Rd Killarney Vale NSW 2261",
    "addr:housenumber":"345",
    "addr:postcode":"2261",
    "addr:street":"Wyong Rd",
    "iso:country":"AU",
    "sg:address":"Shop 345 Killarney Vale Arcade Wyong Rd",
    "sg:city":"Killarney Vale",
    "sg:classifiers":[
        {
            "category":"Health Services",
            "subcategory":"Doctor",
            "type":"Services"
        }
    ],
    "sg:phone":"+61 2 4940 8069",
    "sg:postcode":"2261",
    "sg:province":"NSW",
    "sg:tags":[
        "medical",
        "practitioner"
    ],
    "wof:name":"Manning Jane Dr",
    "wof:placetype":"venue"
},
  "geometry": {"coordinates":[151.46009799999999,-33.364826],"type":"Point"}
}