{
  "type": "Feature",
  "properties": {
    "addr:full":"157 High St Wodonga VIC 3690",
    "addr:housenumber":"157",
    "addr:postcode":"3690",
    "addr:street":"High St",
    "iso:country":"AU",
    "sg:address":"157 High St",
    "sg:city":"Wodonga",
    "sg:classifiers":[
        {
            "category":"Shopping",
            "subcategory":"Stationery & Office Supplies",
            "type":"Retail Goods"
        }
    ],
    "sg:phone":"+61 2 6024 4155",
    "sg:postcode":"3690",
    "sg:province":"VIC",
    "wof:name":"Wodonga Office Supplies",
    "wof:placetype":"venue"
},
  "geometry": {"coordinates":[146.88798523,-36.1240005493],"type":"Point"}
}