{
  "type": "Feature",
  "properties": {
    "addr:full":"59 Toorak Ave Mt Stuart TAS 7000",
    "addr:housenumber":"59",
    "addr:postcode":"7000",
    "addr:street":"Toorak Ave Mt",
    "iso:country":"AU",
    "sg:address":"59 Toorak Ave",
    "sg:city":"Mt Stuart",
    "sg:classifiers":[
        {
            "category":"Personal",
            "subcategory":"Beauty Salon",
            "type":"Services"
        }
    ],
    "sg:phone":"+61 3 6228 5368",
    "sg:postcode":"7000",
    "sg:province":"TAS",
    "sg:tags":[
        "hairdresser"
    ],
    "wof:name":"Aces Hair Studio",
    "wof:placetype":"venue"
},
  "geometry": {"coordinates":[147.305252075,-42.8707466125],"type":"Point"}
}