{
  "type": "Feature",
  "properties": {
    "iso:country":"AU",
    "sg:address":"8 Lackey St",
    "sg:city":"Summer Hill (Sydney)",
    "sg:classifiers":[
        {
            "category":"Health Services",
            "subcategory":"Dentist",
            "type":"Services"
        }
    ],
    "sg:phone":"+61 2 9798 7707",
    "sg:postcode":"2130",
    "sg:province":"NSW",
    "wof:name":"Alexis Maria Dr",
    "wof:placetype":"venue"
},
  "geometry": {"coordinates":[151.13856506400001,-33.8907394409],"type":"Point"}
}