{
  "type": "Feature",
  "properties": {
    "addr:full":"Unit 1/ 10 Marshall St Dapto NSW 2530",
    "addr:housenumber":"10",
    "addr:postcode":"2530",
    "addr:street":"Marshall St",
    "iso:country":"AU",
    "sg:address":"Unit 1/ 10 Marshall St",
    "sg:city":"Dapto",
    "sg:classifiers":[
        {
            "category":"Retail",
            "subcategory":"Auto Repair",
            "type":"Services"
        }
    ],
    "sg:phone":"+61 2 4261 2487",
    "sg:postcode":"2530",
    "sg:province":"NSW",
    "sg:tags":[
        "clutch",
        "brake"
    ],
    "wof:name":"Wollongong Clutch & Brake",
    "wof:placetype":"venue"
},
  "geometry": {"coordinates":[150.79209899899999,-34.49477005],"type":"Point"}
}