{
  "type": "Feature",
  "properties": {
    "addr:full":"11 Coolgardie St Sunnybank Hills QLD 4109",
    "addr:housenumber":"11",
    "addr:postcode":"4109",
    "addr:street":"Coolgardie St",
    "iso:country":"AU",
    "sg:address":"11 Coolgardie St",
    "sg:city":"Sunnybank Hills",
    "sg:classifiers":[
        {
            "category":"Shopping",
            "subcategory":"Bridal",
            "type":"Retail Goods"
        }
    ],
    "sg:phone":"+61 7 3344 6058",
    "sg:postcode":"4109",
    "sg:province":"QLD",
    "sg:tags":[
        "hire",
        "wear"
    ],
    "wof:name":"Mary Hannah Glamour",
    "wof:placetype":"venue"
},
  "geometry": {"coordinates":[153.04498290999999,-27.5841140747],"type":"Point"}
}