{
  "type": "Feature",
  "properties": {
    "addr:full":"48a Lipson St Port Adelaide SA 5015",
    "addr:housenumber":"48a",
    "addr:postcode":"5015",
    "addr:street":"Lipson St",
    "iso:country":"AU",
    "sg:address":"48a Lipson St",
    "sg:city":"Port Adelaide",
    "sg:classifiers":[
        {
            "category":"Professional",
            "type":"Services"
        }
    ],
    "sg:phone":"+61 8 8241 1555",
    "sg:postcode":"5015",
    "sg:province":"SA",
    "sg:tags":[
        "transport"
    ],
    "wof:name":"Ezy Transport Solutions Pty Ltd",
    "wof:placetype":"venue"
},
  "geometry": {"coordinates":[138.510040283,-34.8488769531],"type":"Point"}
}