{
  "type": "Feature",
  "properties": {
    "addr:full":"2A Lucca Rd, North Wyong NSW 2259",
    "addr:housenumber":"2a",
    "addr:postcode":"2259",
    "addr:street":"Lucca Rd North",
    "iso:country":"AU",
    "sg:address":"2A Lucca Rd, North",
    "sg:city":"Wyong",
    "sg:classifiers":[
        {
            "category":"Retail",
            "subcategory":"Storage",
            "type":"Services"
        }
    ],
    "sg:phone":"+61 2 4353 0333",
    "sg:postcode":"2259",
    "sg:province":"NSW",
    "sg:tags":[
        "removal",
        "furniture"
    ],
    "wof:name":"North Wyong Self Storage World",
    "wof:placetype":"venue"
},
  "geometry": {"coordinates":[151.41911315900001,-33.3097610474],"type":"Point"}
}