{
  "type": "Feature",
  "properties": {
    "iso:country":"AU",
    "sg:address":"Unit 3/ 49 Sterling Rd",
    "sg:city":"Minchinbury",
    "sg:classifiers":[
        {
            "category":"Retail",
            "subcategory":"Storage",
            "type":"Services"
        }
    ],
    "sg:phone":"+61 2 9832 7631",
    "sg:postcode":"2770",
    "sg:province":"NSW",
    "sg:tags":[
        "shelving",
        "system"
    ],
    "wof:name":"Warehouse By Design Pty Ltd",
    "wof:placetype":"venue"
},
  "geometry": {"coordinates":[150.815475464,-33.7821350098],"type":"Point"}
}