{
  "type": "Feature",
  "properties": {
    "addr:full":"12 Mcllwraith St Wetherill Park NSW 2164",
    "addr:housenumber":"12",
    "addr:postcode":"2164",
    "addr:street":"Mcllwraith St",
    "iso:country":"AU",
    "sg:address":"12 Mcllwraith St",
    "sg:city":"Wetherill Park",
    "sg:classifiers":[
        {
            "category":"Home & Garden",
            "subcategory":"Carpets & Floor Coverings",
            "type":"Retail Goods"
        }
    ],
    "sg:phone":"+61 3 9872 6963",
    "sg:postcode":"2164",
    "sg:province":"NSW",
    "sg:tags":[
        "laying",
        "supply"
    ],
    "wof:name":"Australian Flooring Supplies",
    "wof:placetype":"venue"
},
  "geometry": {"coordinates":[150.890792847,-33.8500099182],"type":"Point"}
}