{
  "type": "Feature",
  "properties": {
    "addr:full":"355 Hay St Subiaco WA 6008",
    "addr:housenumber":"355",
    "addr:postcode":"6008",
    "addr:street":"Hay St",
    "iso:country":"AU",
    "sg:address":"355 Hay St",
    "sg:city":"Subiaco",
    "sg:classifiers":[
        {
            "category":"Retail",
            "subcategory":"Funeral Services",
            "type":"Services"
        }
    ],
    "sg:phone":"+61 8 9381 6133",
    "sg:postcode":"6008",
    "sg:province":"WA",
    "sg:tags":[
        "cremation"
    ],
    "wof:name":"Prosser Scott & Co Pty Ltd",
    "wof:placetype":"venue"
},
  "geometry": {"coordinates":[115.82724761999999,-31.9471702576],"type":"Point"}
}