{
  "type": "Feature",
  "properties": {
    "addr:full":"Factory 6 101- 107 Wedgewood Rd Hallam VIC 3803",
    "addr:housenumber":"101 107",
    "addr:postcode":"3803",
    "addr:street":"Wedgewood Rd",
    "iso:country":"AU",
    "sg:address":"Factory 6 101- 107 Wedgewood Rd",
    "sg:city":"Hallam",
    "sg:classifiers":[
        {
            "category":"Building & Trades",
            "subcategory":"Construction",
            "type":"Services"
        }
    ],
    "sg:phone":"+61 3 9796 4711",
    "sg:postcode":"3803",
    "sg:province":"VIC",
    "sg:tags":[
        "tennis court",
        "repair"
    ],
    "wof:name":"A1 Enterprises",
    "wof:placetype":"venue"
},
  "geometry": {"coordinates":[145.257446289,-38.0052032471],"type":"Point"}
}