{
  "type": "Feature",
  "properties": {
    "addr:full":"The Mews, Suite 7/ 11-13 Bundaroo St Bowral NSW 2576",
    "addr:housenumber":"7 / 11-13",
    "addr:postcode":"2576",
    "addr:street":"Bundaroo St",
    "iso:country":"AU",
    "sg:address":"The Mews, Suite 7/ 11-13 Bundaroo St",
    "sg:city":"Bowral",
    "sg:classifiers":[
        {
            "category":"Health Services",
            "subcategory":"Dentist",
            "type":"Services"
        }
    ],
    "sg:phone":"+61 2 4861 6217",
    "sg:postcode":"2576",
    "sg:province":"NSW",
    "wof:name":"Kline Patrick W",
    "wof:placetype":"venue"
},
  "geometry": {"coordinates":[150.419067383,-34.4768409729],"type":"Point"}
}