{
  "type": "Feature",
  "properties": {
    "addr:full":"Level 5, 2 Mill St Perth WA 6000",
    "addr:housenumber":"2",
    "addr:postcode":"6000",
    "addr:street":"Mill St",
    "iso:country":"AU",
    "sg:address":"Level 5, 2 Mill St",
    "sg:city":"Perth",
    "sg:classifiers":[
        {
            "category":"Social Services",
            "subcategory":"Child Care",
            "type":"Services"
        }
    ],
    "sg:phone":"+61 8 9429 6444",
    "sg:postcode":"6000",
    "sg:province":"WA",
    "sg:tags":[
        "fleet",
        "management"
    ],
    "wof:name":"GE Fleet Services",
    "wof:placetype":"venue"
},
  "geometry": {"coordinates":[115.852630615,-31.954957962],"type":"Point"}
}