{
  "type": "Feature",
  "properties": {
    "iso:country":"AU",
    "sg:address":"32 Myers St",
    "sg:city":"Geelong",
    "sg:classifiers":[
        {
            "category":"Health Services",
            "subcategory":"Health Practitioner",
            "type":"Services"
        }
    ],
    "sg:phone":"+61 3 5233 8376",
    "sg:postcode":"3220",
    "sg:province":"VIC",
    "sg:tags":[
        "alternative"
    ],
    "wof:name":"Buteyko Victoria",
    "wof:placetype":"venue"
},
  "geometry": {"coordinates":[144.354706,-38.150284],"type":"Point"}
}