{
  "type": "Feature",
  "properties": {
    "iso:country":"AU",
    "sg:address":"Suite 6 Deakin Sports Therapy Cntr, Denison St (Cn",
    "sg:city":"Deakin",
    "sg:classifiers":[
        {
            "category":"Health Services",
            "subcategory":"Chiropractor",
            "type":"Services"
        }
    ],
    "sg:phone":"+61 2 6281 7337",
    "sg:postcode":"2600",
    "sg:province":"ACT",
    "sg:website":"http://www.chiropractors.asn.au",
    "wof:name":"Deakin Chiropractic/ Joanne Saducas-Dimarhos & Joshua Shea",
    "wof:placetype":"venue"
},
  "geometry": {"coordinates":[149.09771728499999,-35.3149108887],"type":"Point"}
}