{
  "type": "Feature",
  "properties": {
    "addr:full":"Unit 8, 46 Buffalo St Gladesville NSW 2111",
    "addr:housenumber":"46",
    "addr:postcode":"2111",
    "addr:street":"Buffalo St",
    "iso:country":"AU",
    "sg:address":"Unit 8, 46 Buffalo St",
    "sg:city":"Gladesville",
    "sg:classifiers":[
        {
            "category":"Shopping",
            "subcategory":"Stationery & Office Supplies",
            "type":"Retail Goods"
        }
    ],
    "sg:phone":"+61 1800 888 021",
    "sg:postcode":"2111",
    "sg:province":"NSW",
    "sg:tags":[
        "packaging",
        "material"
    ],
    "wof:name":"Marketmakers Accessories Pty Ltd",
    "wof:placetype":"venue"
},
  "geometry": {"coordinates":[151.12127685600001,-33.8173713684],"type":"Point"}
}