{
  "type": "Feature",
  "properties": {
    "iso:country":"AU",
    "sg:address":"55 Norfolk Rd",
    "sg:city":"Marion",
    "sg:classifiers":[
        {
            "category":"Retail",
            "subcategory":"Auto Repair",
            "type":"Services"
        }
    ],
    "sg:phone":"+61 8 8298 7144",
    "sg:postcode":"5043",
    "sg:province":"SA",
    "sg:tags":[
        "repairer",
        "motor",
        "engineer"
    ],
    "wof:name":"Auto Carburettor Services Pty Ltd",
    "wof:placetype":"venue"
},
  "geometry": {"coordinates":[138.55682400000001,-35.013615],"type":"Point"}
}