{
  "type": "Feature",
  "properties": {
    "addr:full":"19 Fisher Ave Ryde NSW 2112",
    "addr:housenumber":"19",
    "addr:postcode":"2112",
    "addr:street":"Fisher Ave",
    "iso:country":"AU",
    "sg:address":"19 Fisher Ave",
    "sg:city":"Ryde",
    "sg:classifiers":[
        {
            "category":"Building & Trades",
            "subcategory":"Cleaning & Sanitation",
            "type":"Services"
        }
    ],
    "sg:phone":"+61 2 9888 6451",
    "sg:postcode":"2112",
    "sg:province":"NSW",
    "sg:tags":[
        "industrial",
        "commercial",
        "contractor"
    ],
    "wof:name":"A.M.J. Cleaning Services Pty Ltd",
    "wof:placetype":"venue"
},
  "geometry": {"coordinates":[151.11915588400001,-33.8018341064],"type":"Point"}
}