{
  "type": "Feature",
  "properties": {
    "addr:full":"215 Somerton Rd Roxburgh Park VIC 3064",
    "addr:housenumber":"215",
    "addr:postcode":"3064",
    "addr:street":"Somerton Rd",
    "iso:country":"AU",
    "sg:address":"215 Somerton Rd",
    "sg:city":"Roxburgh Park",
    "sg:classifiers":[
        {
            "category":"Autos & Motor Vehicles",
            "subcategory":"Automobile Sales",
            "type":"Retail Goods"
        }
    ],
    "sg:phone":"+61 3 9930 4444",
    "sg:postcode":"3064",
    "sg:province":"VIC",
    "sg:tags":[
        "car",
        "new"
    ],
    "wof:name":"Mantello Holden (Roxburgh Park)",
    "wof:placetype":"venue"
},
  "geometry": {"coordinates":[144.931274414,-37.6410446167],"type":"Point"}
}