{
  "type": "Feature",
  "properties": {
    "addr:full":"10 Blackbutt Crt Tewantin QLD 4565",
    "addr:housenumber":"10",
    "addr:postcode":"4565",
    "addr:street":"Blackbutt Crt",
    "iso:country":"AU",
    "sg:address":"10 Blackbutt Crt",
    "sg:city":"Tewantin",
    "sg:classifiers":[
        {
            "category":"Building & Trades",
            "subcategory":"Construction",
            "type":"Services"
        }
    ],
    "sg:phone":"+61 7 5474 4587",
    "sg:postcode":"4565",
    "sg:province":"QLD",
    "sg:tags":[
        "mural"
    ],
    "wof:name":"Splash Art",
    "wof:placetype":"venue"
},
  "geometry": {"coordinates":[153.02296447800001,-26.3858642578],"type":"Point"}
}