{
  "type": "Feature",
  "properties": {
    "iso:country":"AU",
    "sg:address":"11 Marine Pde",
    "sg:city":"Abbotsford",
    "sg:classifiers":[
        {
            "category":"Professional",
            "subcategory":"Art Services",
            "type":"Services"
        }
    ],
    "sg:phone":"+61 3 9417 0999",
    "sg:postcode":"3067",
    "sg:province":"VIC",
    "sg:tags":[
        "decorator",
        "painter"
    ],
    "wof:name":"Mulholland Restorations",
    "wof:placetype":"venue"
},
  "geometry": {"coordinates":[145.00047302199999,-37.8033638],"type":"Point"}
}