{
  "type": "Feature",
  "properties": {
    "addr:full":"12 Bent St Mukinbudin WA 6479",
    "addr:housenumber":"12",
    "addr:postcode":"6479",
    "addr:street":"Bent St",
    "iso:country":"AU",
    "sg:address":"12 Bent St",
    "sg:city":"Mukinbudin",
    "sg:classifiers":[
        {
            "category":"Wholesale",
            "subcategory":"Farm Supplies",
            "type":"Manufacturing & Wholesale Goods"
        }
    ],
    "sg:phone":"+61 8 9047 1111",
    "sg:postcode":"6479",
    "sg:province":"WA",
    "sg:tags":[
        "equipment"
    ],
    "wof:name":"Hutton & Northey Mukinbudin",
    "wof:placetype":"venue"
},
  "geometry": {"coordinates":[118.209701538,-30.91547966],"type":"Point"}
}