{
  "type": "Feature",
  "properties": {
    "addr:full":"1 Harrow Rd St Peters SA 5069",
    "addr:housenumber":"1",
    "addr:postcode":"5069",
    "addr:street":"Harrow Rd",
    "iso:country":"AU",
    "sg:address":"1 Harrow Rd St",
    "sg:city":"Peters",
    "sg:classifiers":[
        {
            "category":"Autos & Motor Vehicles",
            "subcategory":"Fuel & Gas Station",
            "type":"Retail Goods"
        }
    ],
    "sg:phone":"+61 8 8362 1112",
    "sg:postcode":"5069",
    "sg:province":"SA",
    "wof:name":"BP St Peters Car Wash",
    "wof:placetype":"venue"
},
  "geometry": {"coordinates":[138.62448120100001,-34.9131278992],"type":"Point"}
}