{
  "type": "Feature",
  "properties": {
    "iso:country":"AU",
    "sg:address":"220 Commercial St",
    "sg:city":"East Mt Gambier",
    "sg:classifiers":[
        {
            "category":"Home & Garden",
            "subcategory":"Furniture",
            "type":"Retail Goods"
        }
    ],
    "sg:phone":"+61 8 8725 5547",
    "sg:postcode":"5290",
    "sg:province":"SA",
    "sg:tags":[
        "business"
    ],
    "wof:name":"Eddies",
    "wof:placetype":"venue"
},
  "geometry": {"coordinates":[140.797836,-37.833977],"type":"Point"}
}