{
  "type": "Feature",
  "properties": {
    "iso:country":"AU",
    "sg:address":"54 Wermol St",
    "sg:city":"Kurri Kurri",
    "sg:classifiers":[
        {
            "category":"Manufacturing",
            "subcategory":"Metals",
            "type":"Manufacturing & Wholesale Goods"
        }
    ],
    "sg:phone":"+61 2 4936 4976",
    "sg:postcode":"2327",
    "sg:province":"NSW",
    "sg:tags":[
        "steel",
        "fabricator",
        "mfrs"
    ],
    "wof:name":"Anderson R & D",
    "wof:placetype":"venue"
},
  "geometry": {"coordinates":[151.47532653799999,-32.8096389771],"type":"Point"}
}