{
  "type": "Feature",
  "properties": {
    "iso:country":"AU",
    "sg:address":"81 Dundas Crt",
    "sg:city":"Phillip",
    "sg:classifiers":[
        {
            "category":"Professional",
            "subcategory":"Accounting & Tax Preparation",
            "type":"Services"
        }
    ],
    "sg:phone":"+61 2 6282 2202",
    "sg:postcode":"2606",
    "sg:province":"ACT",
    "sg:tags":[
        "consultant",
        "taxation"
    ],
    "wof:name":"Income Tax & GST Experts",
    "wof:placetype":"venue"
},
  "geometry": {"coordinates":[149.08900451700001,-35.3544082642],"type":"Point"}
}