{
  "type": "Feature",
  "properties": {
    "addr:full":"54 Bombala St Cooma NSW 2630",
    "addr:housenumber":"54",
    "addr:postcode":"2630",
    "addr:street":"Bombala St",
    "iso:country":"AU",
    "sg:address":"54 Bombala St",
    "sg:city":"Cooma",
    "sg:classifiers":[
        {
            "category":"Retail",
            "subcategory":"Auto Repair",
            "type":"Services"
        }
    ],
    "sg:phone":"+61 2 6452 2246",
    "sg:postcode":"2630",
    "sg:province":"NSW",
    "sg:tags":[
        "wheel",
        "balancing",
        "alignment"
    ],
    "wof:name":"Cooma Steering & Suspension",
    "wof:placetype":"venue"
},
  "geometry": {"coordinates":[149.126586914,-36.2339782715],"type":"Point"}
}