{
  "type": "Feature",
  "properties": {
    "iso:country":"AU",
    "sg:address":"Wycombe Clinic 144 Wycombe Rd",
    "sg:city":"Neutral Bay",
    "sg:classifiers":[
        {
            "category":"Health Services",
            "subcategory":"Doctor",
            "type":"Services"
        }
    ],
    "sg:phone":"+61 2 9950 9838",
    "sg:postcode":"2089",
    "sg:province":"NSW",
    "sg:tags":[
        "medical",
        "practitioner"
    ],
    "wof:name":"Unsen Gabriella Dr",
    "wof:placetype":"venue"
},
  "geometry": {"coordinates":[151.22207641599999,-33.8321456909],"type":"Point"}
}