{
  "type": "Feature",
  "properties": {
    "iso:country":"AU",
    "sg:address":"90 Barkly Hwy",
    "sg:city":"Mt Isa",
    "sg:classifiers":[
        {
            "category":"Retail",
            "subcategory":"Auto Rental",
            "type":"Services"
        }
    ],
    "sg:phone":"+61 7 4743 3651",
    "sg:postcode":"4825",
    "sg:province":"QLD",
    "sg:tags":[
        "bus",
        "truck"
    ],
    "wof:name":"Meteor Car & Truck Rentals",
    "wof:placetype":"venue"
},
  "geometry": {"coordinates":[139.486008,-20.699259],"type":"Point"}
}