{
  "type": "Feature",
  "properties": {
    "addr:full":"113 Slater St Colac VIC 3250",
    "addr:housenumber":"113",
    "addr:postcode":"3250",
    "addr:street":"Slater St",
    "iso:country":"AU",
    "sg:address":"113 Slater St",
    "sg:city":"Colac",
    "sg:classifiers":[
        {
            "category":"Commercial Area",
            "type":"Public Place"
        }
    ],
    "sg:phone":"+61 428 877 260",
    "sg:postcode":"3250",
    "sg:province":"VIC",
    "sg:tags":[
        "heavy",
        "carrier"
    ],
    "wof:name":"Wazzas Water Cartage",
    "wof:placetype":"venue"
},
  "geometry": {"coordinates":[143.587234,-38.361942],"type":"Point"}
}