{
  "type": "Feature",
  "properties": {
    "addr:full":"54 Lorimer St Crib Point VIC 3919",
    "addr:housenumber":"54",
    "addr:postcode":"3919",
    "addr:street":"Lorimer St",
    "iso:country":"AU",
    "sg:address":"54 Lorimer St",
    "sg:city":"Crib Point",
    "sg:classifiers":[
        {
            "category":"Building & Trades",
            "subcategory":"Construction",
            "type":"Services"
        }
    ],
    "sg:phone":"+61 3 5983 8126",
    "sg:postcode":"3919",
    "sg:province":"VIC",
    "sg:tags":[
        "plasterboard",
        "plasterer",
        "fixer"
    ],
    "wof:name":"D J Northcote",
    "wof:placetype":"venue"
},
  "geometry": {"coordinates":[145.20294189399999,-38.3558731079],"type":"Point"}
}