{
  "type": "Feature",
  "properties": {
    "addr:full":"48 Brisbane St Launceston TAS 7250",
    "addr:housenumber":"48",
    "addr:postcode":"7250",
    "addr:street":"Brisbane St",
    "iso:country":"AU",
    "sg:address":"48 Brisbane St",
    "sg:city":"Launceston",
    "sg:classifiers":[
        {
            "category":"Real Estate",
            "subcategory":"Real Estate Agent",
            "type":"Services"
        }
    ],
    "sg:phone":"+61 3 6332 6400",
    "sg:postcode":"7250",
    "sg:province":"TAS",
    "sg:website":"http://www.harrisonhumphreys.com.au",
    "wof:name":"Harrison Humphreys Real Estate",
    "wof:placetype":"venue"
},
  "geometry": {"coordinates":[147.14093017600001,-41.4358520508],"type":"Point"}
}