{
  "type": "Feature",
  "properties": {
    "addr:full":"24 Chisholm Crs Kewdale WA 6105",
    "addr:housenumber":"24",
    "addr:postcode":"6105",
    "addr:street":"Chisholm Crs",
    "iso:country":"AU",
    "sg:address":"24 Chisholm Crs",
    "sg:city":"Kewdale",
    "sg:classifiers":[
        {
            "category":"Wholesale",
            "subcategory":"Scrap",
            "type":"Manufacturing & Wholesale Goods"
        }
    ],
    "sg:phone":"+61 8 9352 1900",
    "sg:postcode":"6105",
    "sg:province":"WA",
    "sg:tags":[
        "merchant",
        "metal"
    ],
    "wof:name":"Smorgon Steel",
    "wof:placetype":"venue"
},
  "geometry": {"coordinates":[115.927200317,-31.9781608582],"type":"Point"}
}