{
  "type": "Feature",
  "properties": {
    "iso:country":"AU",
    "sg:address":"17 Bowen Bridge Rd",
    "sg:city":"Herston",
    "sg:classifiers":[
        {
            "category":"Professional",
            "subcategory":"Computer Services",
            "type":"Services"
        }
    ],
    "sg:phone":"+61 1300 887 868",
    "sg:postcode":"4006",
    "sg:province":"QLD",
    "sg:tags":[
        "package",
        "software"
    ],
    "wof:name":"Cashflow Manager",
    "wof:placetype":"venue"
},
  "geometry": {"coordinates":[153.029586792,-27.4470176697],"type":"Point"}
}