{
  "type": "Feature",
  "properties": {
    "addr:full":"cnr Croydon St. & Milton Rd Toowong QLD 4066",
    "addr:postcode":"4066",
    "addr:street":"Cnr Croydon St. & Milton Rd",
    "iso:country":"AU",
    "sg:address":"cnr Croydon St. & Milton Rd",
    "sg:city":"Toowong",
    "sg:classifiers":[
        {
            "category":"Retail",
            "subcategory":"Self-service Laundry",
            "type":"Services"
        }
    ],
    "sg:phone":"+61 406 891 935",
    "sg:postcode":"4066",
    "sg:province":"QLD",
    "wof:name":"Toowong Coin Laundromat",
    "wof:placetype":"venue"
},
  "geometry": {"coordinates":[152.98931884800001,-27.4784793854],"type":"Point"}
}