{
  "type": "Feature",
  "properties": {
    "iso:country":"AU",
    "sg:address":"Ground Floor 10 Valentine Ave",
    "sg:city":"Parramatta",
    "sg:classifiers":[
        {
            "category":"Real Estate",
            "subcategory":"Real Estate Services",
            "type":"Services"
        }
    ],
    "sg:phone":"+61 2 9895 7278",
    "sg:postcode":"2150",
    "sg:province":"NSW",
    "sg:tags":[
        "valuer"
    ],
    "wof:name":"State Valuation Office",
    "wof:placetype":"venue"
},
  "geometry": {"coordinates":[151.00668335,-33.8193397522],"type":"Point"}
}