{
  "type": "Feature",
  "properties": {
    "addr:full":"67 North Lake Rd Myaree WA 6154",
    "addr:housenumber":"67",
    "addr:postcode":"6154",
    "addr:street":"North Lake Rd",
    "iso:country":"AU",
    "sg:address":"67 North Lake Rd",
    "sg:city":"Myaree",
    "sg:classifiers":[
        {
            "category":"Food & Beverages",
            "subcategory":"Supermarket",
            "type":"Retail Goods"
        }
    ],
    "sg:phone":"+61 8 9330 6635",
    "sg:postcode":"6154",
    "sg:province":"WA",
    "sg:tags":[
        "grocery",
        "store"
    ],
    "wof:name":"Supa IGA",
    "wof:placetype":"venue"
},
  "geometry": {"coordinates":[115.81558200000001,-32.039154],"type":"Point"}
}