{
  "type": "Feature",
  "properties": {
    "addr:full":"PO Box 2003 Mareeba QLD 4880",
    "addr:postcode":"4880",
    "iso:country":"AU",
    "sg:address":"PO Box 2003",
    "sg:city":"Mareeba",
    "sg:classifiers":[
        {
            "category":"Professional",
            "subcategory":"Detective & Security Services",
            "type":"Services"
        }
    ],
    "sg:phone":"+61 7 4092 7612",
    "sg:postcode":"4880",
    "sg:province":"QLD",
    "sg:tags":[
        "consultant",
        "system"
    ],
    "wof:name":"Fingerlock Security Systems",
    "wof:placetype":"venue"
},
  "geometry": {"coordinates":[145.425704956,-17.0136604309],"type":"Point"}
}