{
  "type": "Feature",
  "properties": {
    "addr:full":"10 Melba Crt Mt Ommaney QLD 4074",
    "addr:housenumber":"10",
    "addr:postcode":"4074",
    "addr:street":"Melba Crt Mt Ommaney",
    "iso:country":"AU",
    "sg:address":"10 Melba Crt",
    "sg:city":"Mt Ommaney",
    "sg:classifiers":[
        {
            "category":"Building & Trades",
            "subcategory":"Construction",
            "type":"Services"
        }
    ],
    "sg:phone":"+61 7 3376 2083",
    "sg:postcode":"4074",
    "sg:province":"QLD",
    "sg:tags":[
        "contractor"
    ],
    "wof:name":"Kozij Constructions Pty Ltd",
    "wof:placetype":"venue"
},
  "geometry": {"coordinates":[152.93336486800001,-27.5423202515],"type":"Point"}
}