{
  "type": "Feature",
  "properties": {
    "iso:country":"AU",
    "sg:address":"Shop 20 Cessnock Plaza Keene St",
    "sg:city":"Cessnock",
    "sg:classifiers":[
        {
            "category":"Food & Beverages",
            "subcategory":"Bakery",
            "type":"Retail Goods"
        }
    ],
    "sg:phone":"+61 2 4991 7770",
    "sg:postcode":"2325",
    "sg:province":"NSW",
    "sg:tags":[
        "baker"
    ],
    "wof:name":"Thompson & Son's Bakery",
    "wof:placetype":"venue"
},
  "geometry": {"coordinates":[151.35406494099999,-32.8343925476],"type":"Point"}
}