{
  "type": "Feature",
  "properties": {
    "iso:country":"AU",
    "sg:address":"Benalla Rd",
    "sg:city":"Shepparton",
    "sg:classifiers":[
        {
            "category":"Manufacturing",
            "subcategory":"Building Materials",
            "type":"Manufacturing & Wholesale Goods"
        }
    ],
    "sg:phone":"+61 3 5821 2898",
    "sg:postcode":"3630",
    "sg:province":"VIC",
    "sg:tags":[
        "concrete",
        "product"
    ],
    "wof:name":"Boral Resources (Country)",
    "wof:placetype":"venue"
},
  "geometry": {"coordinates":[145.43011474599999,-36.387840271],"type":"Point"}
}