{
  "type": "Feature",
  "properties": {
    "addr:full":"Shp 7 , Air Raid Tavern Cntr Moruya NSW 2537",
    "addr:housenumber":"7",
    "addr:postcode":"2537",
    "addr:street":"Air Raid;Cntr",
    "iso:country":"AU",
    "sg:address":"Shp 7",
    "sg:city":", Air Raid Tavern Cntr Moruya",
    "sg:classifiers":[
        {
            "category":"Health Services",
            "subcategory":"Health Practitioner",
            "type":"Services"
        }
    ],
    "sg:phone":"+61 2 4474 0244",
    "sg:postcode":"2537",
    "sg:province":"NSW",
    "sg:tags":[
        "physiotherapist"
    ],
    "wof:name":"Andrew Bonatakis Physiotherapy",
    "wof:placetype":"venue"
},
  "geometry": {"coordinates":[150.080688477,-35.9107589722],"type":"Point"}
}