{
  "type": "Feature",
  "properties": {
    "iso:country":"AU",
    "sg:address":"10 Cummins Pl",
    "sg:city":"Broken Hill",
    "sg:classifiers":[
        {
            "category":"Professional",
            "subcategory":"Art Services",
            "type":"Services"
        }
    ],
    "sg:phone":"+61 417 775 887",
    "sg:postcode":"2880",
    "sg:province":"NSW",
    "sg:tags":[
        "decorator",
        "painter"
    ],
    "wof:name":"Milne & Vincent Painters & Decorators and Signs & Signs",
    "wof:placetype":"venue"
},
  "geometry": {"coordinates":[141.445602417,-31.9487380981],"type":"Point"}
}