{
  "type": "Feature",
  "properties": {
    "iso:country":"AU",
    "sg:address":"390 South Rd",
    "sg:city":"Richmond",
    "sg:classifiers":[
        {
            "category":"Retail",
            "subcategory":"Auto Repair",
            "type":"Services"
        }
    ],
    "sg:phone":"+61 8 8234 1033",
    "sg:postcode":"5033",
    "sg:province":"SA",
    "sg:tags":[
        "electrical"
    ],
    "wof:name":"Matlin Auto Pty Ltd",
    "wof:placetype":"venue"
},
  "geometry": {"coordinates":[138.570709228,-34.9405174255],"type":"Point"}
}