{
  "type": "Feature",
  "properties": {
    "addr:full":"456- 458 Cross Rd Glandore SA 5037",
    "addr:housenumber":"458",
    "addr:postcode":"5037",
    "addr:street":"Cross Rd",
    "iso:country":"AU",
    "sg:address":"456- 458 Cross Rd",
    "sg:city":"Glandore",
    "sg:classifiers":[
        {
            "category":"Professional",
            "subcategory":"Computer Services",
            "type":"Services"
        }
    ],
    "sg:phone":"+61 8 8292 5400",
    "sg:postcode":"5037",
    "sg:province":"SA",
    "sg:tags":[
        "equipment",
        "networking",
        "installation"
    ],
    "wof:name":"Mr Networks",
    "wof:placetype":"venue"
},
  "geometry": {"coordinates":[138.57203674300001,-34.9670906067],"type":"Point"}
}