{
  "type": "Feature",
  "properties": {
    "addr:full":"8 Stewart Drv Cannonvale QLD 4802",
    "addr:housenumber":"8",
    "addr:postcode":"4802",
    "addr:street":"Stewart Drv",
    "iso:country":"AU",
    "sg:address":"8 Stewart Drv",
    "sg:city":"Cannonvale",
    "sg:classifiers":[
        {
            "category":"Building & Trades",
            "subcategory":"Landscaping Services",
            "type":"Services"
        }
    ],
    "sg:phone":"+61 7 4946 6517",
    "sg:postcode":"4802",
    "sg:province":"QLD",
    "sg:tags":[
        "consultant"
    ],
    "wof:name":"William- Graham:Boulton",
    "wof:placetype":"venue"
},
  "geometry": {"coordinates":[148.69418335,-20.2735729218],"type":"Point"}
}