{
  "type": "Feature",
  "properties": {
    "iso:country":"AU",
    "sg:address":"Mildura Plaza Shop 19A Mildura Plaza Shop/Cntr",
    "sg:city":"Mildura",
    "sg:classifiers":[
        {
            "category":"Shopping",
            "subcategory":"Clothing, Apparel, & Fashions",
            "type":"Retail Goods"
        }
    ],
    "sg:phone":"+61 3 5022 7001",
    "sg:postcode":"3500",
    "sg:province":"VIC",
    "sg:tags":[
        "menswear"
    ],
    "wof:name":"Roger David",
    "wof:placetype":"venue"
},
  "geometry": {"coordinates":[142.154098511,-34.2107391357],"type":"Point"}
}