{
  "type": "Feature",
  "properties": {
    "iso:country":"AU",
    "sg:address":"265 Ross St",
    "sg:city":"Port Melbourne",
    "sg:classifiers":[
        {
            "category":"Building & Trades",
            "subcategory":"Plumbing",
            "type":"Services"
        }
    ],
    "sg:phone":"+61 412 112 114",
    "sg:postcode":"3207",
    "sg:province":"VIC",
    "sg:tags":[
        "plumber",
        "gasfitters"
    ],
    "wof:name":"Valiant Plumbing",
    "wof:placetype":"venue"
},
  "geometry": {"coordinates":[144.941605,-37.832844],"type":"Point"}
}