{
  "type": "Feature",
  "properties": {
    "iso:country":"AU",
    "sg:address":"4 Sharp St",
    "sg:city":"Hoppers Crossing",
    "sg:classifiers":[
        {
            "category":"Fast Food",
            "type":"Food & Drink"
        }
    ],
    "sg:phone":"+61 3 9749 1066",
    "sg:postcode":"3029",
    "sg:province":"VIC",
    "sg:tags":[
        "away",
        "take"
    ],
    "wof:name":"Franky's Pizza",
    "wof:placetype":"venue"
},
  "geometry": {"coordinates":[144.68620300000001,-37.874481],"type":"Point"}
}