{
  "type": "Feature",
  "properties": {
    "iso:country":"AU",
    "sg:address":"25 Heales Rd",
    "sg:city":"Lara",
    "sg:classifiers":[
        {
            "category":"Professional",
            "subcategory":"Testing Lab",
            "type":"Services"
        }
    ],
    "sg:phone":"+61 3 5275 9560",
    "sg:postcode":"3212",
    "sg:province":"VIC",
    "sg:tags":[
        "soil",
        "investigation"
    ],
    "wof:name":"CWM Enviro SCIENCE Pty Ltd",
    "wof:placetype":"venue"
},
  "geometry": {"coordinates":[144.388137817,-38.0515213013],"type":"Point"}
}