{
  "type": "Feature",
  "properties": {
    "iso:country":"AU",
    "sg:address":"Grundy Ave",
    "sg:city":"Nyora",
    "sg:classifiers":[
        {
            "category":"Education",
            "subcategory":"School",
            "type":"Public Place"
        }
    ],
    "sg:phone":"+61 3 5659 6240",
    "sg:postcode":"3987",
    "sg:province":"VIC",
    "sg:tags":[
        "state",
        "except",
        "nsw"
    ],
    "wof:name":"Nyora Primary School",
    "wof:placetype":"venue"
},
  "geometry": {"coordinates":[145.67471313499999,-38.3364334106],"type":"Point"}
}