{
  "type": "Feature",
  "properties": {
    "addr:full":"53 Barrabool Rd Highton VIC 3216",
    "addr:housenumber":"53",
    "addr:postcode":"3216",
    "addr:street":"Barrabool Rd",
    "iso:country":"AU",
    "sg:address":"53 Barrabool Rd",
    "sg:city":"Highton",
    "sg:classifiers":[
        {
            "category":"Shopping",
            "subcategory":"Jewelry",
            "type":"Retail Goods"
        }
    ],
    "sg:phone":"+61 3 5245 7555",
    "sg:postcode":"3216",
    "sg:province":"VIC",
    "sg:tags":[
        "jeweller"
    ],
    "wof:name":"Williams Peter Jeweller",
    "wof:placetype":"venue"
},
  "geometry": {"coordinates":[144.32623290999999,-38.1705093384],"type":"Point"}
}