{
  "type": "Feature",
  "properties": {
    "addr:full":"15 Rowena Pl Cherrybrook NSW 2126",
    "addr:housenumber":"15",
    "addr:postcode":"2126",
    "addr:street":"Rowena Pl",
    "iso:country":"AU",
    "sg:address":"15 Rowena Pl",
    "sg:city":"Cherrybrook",
    "sg:classifiers":[
        {
            "category":"Wholesale",
            "subcategory":"Non-durable Goods",
            "type":"Manufacturing & Wholesale Goods"
        }
    ],
    "sg:phone":"+61 2 9875 1492",
    "sg:postcode":"2126",
    "sg:province":"NSW",
    "sg:tags":[
        "wholesaler",
        "craft",
        "mfrs"
    ],
    "wof:name":"Libran Enterprise Paper Tole",
    "wof:placetype":"venue"
},
  "geometry": {"coordinates":[151.034225464,-33.7204208374],"type":"Point"}
}