{
  "type": "Feature",
  "properties": {
    "addr:full":"931 Fernleigh Rd Brooklet NSW 2479",
    "addr:housenumber":"931",
    "addr:postcode":"2479",
    "addr:street":"Fernleigh Rd",
    "iso:country":"AU",
    "sg:address":"931 Fernleigh Rd",
    "sg:city":"Brooklet",
    "sg:classifiers":[
        {
            "category":"Travel",
            "subcategory":"Hotels & Motels",
            "type":"Entertainment"
        }
    ],
    "sg:phone":"+61 1800 023 966",
    "sg:postcode":"2479",
    "sg:province":"NSW",
    "wof:name":"Golden Chain Motor Inns Head Office",
    "wof:placetype":"venue"
},
  "geometry": {"coordinates":[153.50782775900001,-28.7326335907],"type":"Point"}
}