{
  "type": "Feature",
  "properties": {
    "iso:country":"AU",
    "sg:address":"Shop 3/ 2 Yalumba St",
    "sg:city":"Kingston",
    "sg:classifiers":[
        {
            "category":"Personal",
            "subcategory":"Beauty Salon",
            "type":"Services"
        }
    ],
    "sg:phone":"+61 7 3208 9154",
    "sg:postcode":"4114",
    "sg:province":"QLD",
    "sg:tags":[
        "hairdresser"
    ],
    "wof:name":"The Barbers Hut",
    "wof:placetype":"venue"
},
  "geometry": {"coordinates":[153.098114014,-27.6590385437],"type":"Point"}
}