{
  "type": "Feature",
  "properties": {
    "iso:country":"AU",
    "sg:address":"117 Robey St",
    "sg:city":"Mascot",
    "sg:classifiers":[
        {
            "category":"Retail",
            "subcategory":"Auto Repair",
            "type":"Services"
        }
    ],
    "sg:phone":"+61 2 9667 1570",
    "sg:postcode":"2020",
    "sg:province":"NSW",
    "sg:tags":[
        "electrical"
    ],
    "wof:name":"Austral Auto Electrics Pty Ltd",
    "wof:placetype":"venue"
},
  "geometry": {"coordinates":[151.18800354000001,-33.9307632446],"type":"Point"}
}