{
  "type": "Feature",
  "properties": {
    "iso:country":"AU",
    "sg:address":"Highland Shopng Cntr 222 Target Hill Rd",
    "sg:city":"Greenwith",
    "sg:classifiers":[
        {
            "category":"Health Services",
            "subcategory":"Doctor",
            "type":"Services"
        }
    ],
    "sg:phone":"+61 8 8289 6911",
    "sg:postcode":"5125",
    "sg:province":"SA",
    "sg:tags":[
        "medical",
        "practitioner"
    ],
    "wof:name":"Paul Andre",
    "wof:placetype":"venue"
},
  "geometry": {"coordinates":[138.71286,-34.772034],"type":"Point"}
}