{
  "type": "Feature",
  "properties": {
    "iso:country":"AU",
    "sg:address":"272 Pinjarra Rd",
    "sg:city":"Mandurah",
    "sg:classifiers":[
        {
            "category":"Health Services",
            "subcategory":"Chiropractor",
            "type":"Services"
        }
    ],
    "sg:phone":"+61 8 9535 1619",
    "sg:postcode":"6210",
    "sg:province":"WA",
    "wof:name":"Peel Chiropractic Centre",
    "wof:placetype":"venue"
},
  "geometry": {"coordinates":[115.781418,-32.554104],"type":"Point"}
}