{
  "type": "Feature",
  "properties": {
    "iso:country":"AU",
    "sg:address":"3 Norwood Crs",
    "sg:city":"Moonee Ponds",
    "sg:classifiers":[
        {
            "category":"Personal",
            "subcategory":"Beauty Salon",
            "type":"Services"
        }
    ],
    "sg:phone":"+61 3 9370 6897",
    "sg:postcode":"3039",
    "sg:province":"VIC",
    "wof:name":"Novita Beauty Salon",
    "wof:placetype":"venue"
},
  "geometry": {"coordinates":[144.92941300000001,-37.786469],"type":"Point"}
}