{
  "type": "Feature",
  "properties": {
    "iso:country":"AU",
    "sg:address":"17 Richards Rd",
    "sg:city":"Hoppers Crossing",
    "sg:classifiers":[
        {
            "category":"Building & Trades",
            "subcategory":"Construction",
            "type":"Services"
        }
    ],
    "sg:phone":"+61 3 9360 0809",
    "sg:postcode":"3029",
    "sg:province":"VIC",
    "sg:tags":[
        "repairing",
        "window"
    ],
    "wof:name":"Wizard Windscreens",
    "wof:placetype":"venue"
},
  "geometry": {"coordinates":[144.728027,-37.865543],"type":"Point"}
}