{
  "type": "Feature",
  "properties": {
    "addr:full":"6 Park St Albion QLD 4010",
    "addr:housenumber":"6",
    "addr:postcode":"4010",
    "addr:street":"Park St",
    "iso:country":"AU",
    "sg:address":"6 Park St",
    "sg:city":"Albion",
    "sg:classifiers":[
        {
            "category":"Banks & Credit Unions",
            "subcategory":"Investment Brokerage",
            "type":"Services"
        }
    ],
    "sg:phone":"+61 1300 137 155",
    "sg:postcode":"4010",
    "sg:province":"QLD",
    "sg:tags":[
        "broker"
    ],
    "wof:name":"Brisbane Car Brokers Pty Ltd",
    "wof:placetype":"venue"
},
  "geometry": {"coordinates":[153.04408264200001,-27.4387645721],"type":"Point"}
}