{
  "type": "Feature",
  "properties": {
    "iso:country":"AU",
    "sg:address":"7/ 35 Stockton St",
    "sg:city":"Nelson Bay",
    "sg:classifiers":[
        {
            "category":"Professional",
            "subcategory":"Accounting & Tax Preparation",
            "type":"Services"
        }
    ],
    "sg:phone":"+61 2 4984 4580",
    "sg:postcode":"2315",
    "sg:province":"NSW",
    "sg:tags":[
        "accountant",
        "auditor"
    ],
    "wof:name":"Cooper Damien J",
    "wof:placetype":"venue"
},
  "geometry": {"coordinates":[152.143295,-32.723526],"type":"Point"}
}