{
  "type": "Feature",
  "properties": {
    "addr:full":"11 Ann St Toowoomba QLD 4350",
    "addr:housenumber":"11",
    "addr:postcode":"4350",
    "addr:street":"Ann St",
    "iso:country":"AU",
    "sg:address":"11 Ann St",
    "sg:city":"Toowoomba",
    "sg:classifiers":[
        {
            "category":"Retail",
            "subcategory":"Driving School",
            "type":"Services"
        }
    ],
    "sg:phone":"+61 7 4638 9449",
    "sg:postcode":"4350",
    "sg:province":"QLD",
    "wof:name":"Alert Driving School",
    "wof:placetype":"venue"
},
  "geometry": {"coordinates":[151.954971,-27.556484],"type":"Point"}
}