{
  "type": "Feature",
  "properties": {
    "addr:full":"181 Queen St St Marys NSW 2760",
    "addr:housenumber":"181",
    "addr:postcode":"2760",
    "addr:street":"Queen St",
    "iso:country":"AU",
    "sg:address":"181 Queen St",
    "sg:city":"St Marys",
    "sg:classifiers":[
        {
            "category":"Real Estate",
            "subcategory":"Real Estate Agent",
            "type":"Services"
        }
    ],
    "sg:phone":"+61 2 9673 4422",
    "sg:postcode":"2760",
    "sg:province":"NSW",
    "wof:name":"Professionals St Marys",
    "wof:placetype":"venue"
},
  "geometry": {"coordinates":[150.77476501500001,-33.7623901367],"type":"Point"}
}