{
  "type": "Feature",
  "properties": {
    "addr:full":"37 Watton St Werribee VIC 3030",
    "addr:housenumber":"37",
    "addr:postcode":"3030",
    "addr:street":"Watton St",
    "iso:country":"AU",
    "sg:address":"37 Watton St",
    "sg:city":"Werribee",
    "sg:classifiers":[
        {
            "category":"Food & Beverages",
            "subcategory":"Bakery",
            "type":"Retail Goods"
        }
    ],
    "sg:phone":"+61 3 9742 4719",
    "sg:postcode":"3030",
    "sg:province":"VIC",
    "sg:tags":[
        "baker"
    ],
    "wof:name":"Sunny Tran",
    "wof:placetype":"venue"
},
  "geometry": {"coordinates":[144.662643,-37.900726],"type":"Point"}
}