{
  "type": "Feature",
  "properties": {
    "iso:country":"AU",
    "sg:address":"Shop 1, 620 Moggill Rd",
    "sg:city":"Chapel Hill",
    "sg:classifiers":[
        {
            "category":"Fast Food",
            "type":"Food & Drink"
        }
    ],
    "sg:phone":"+61 7 3878 1566",
    "sg:postcode":"4069",
    "sg:province":"QLD",
    "sg:tags":[
        "away",
        "take"
    ],
    "wof:name":"Royal Sri Thai Restaurant",
    "wof:placetype":"venue"
},
  "geometry": {"coordinates":[152.960861206,-27.5054416656],"type":"Point"}
}