{
  "type": "Feature",
  "properties": {
    "addr:full":"22 Henry St Geelong East VIC 3219",
    "addr:housenumber":"22",
    "addr:postcode":"3219",
    "addr:street":"Henry St",
    "iso:country":"AU",
    "sg:address":"22 Henry St",
    "sg:city":"Geelong East",
    "sg:classifiers":[
        {
            "category":"Insurance",
            "subcategory":"Life Insurance",
            "type":"Services"
        }
    ],
    "sg:phone":"+61 1800 654 571",
    "sg:postcode":"3219",
    "sg:province":"VIC",
    "wof:name":"John McVilly Financial Solutions",
    "wof:placetype":"venue"
},
  "geometry": {"coordinates":[144.369628906,-38.1557197571],"type":"Point"}
}