{
  "type": "Feature",
  "properties": {
    "addr:full":"19 Port Kembla Drv Bibra Lake WA 6163",
    "addr:housenumber":"19",
    "addr:postcode":"6163",
    "addr:street":"Port Kembla Drv",
    "iso:country":"AU",
    "sg:address":"19 Port Kembla Drv",
    "sg:city":"Bibra Lake",
    "sg:classifiers":[
        {
            "category":"Retail",
            "subcategory":"Veterinary Services",
            "type":"Services"
        }
    ],
    "sg:phone":"+61 8 9434 2243",
    "sg:postcode":"6163",
    "sg:province":"WA",
    "sg:tags":[
        "surgeon"
    ],
    "wof:name":"Yangebup Animal Hospital",
    "wof:placetype":"venue"
},
  "geometry": {"coordinates":[115.80127,-32.095322],"type":"Point"}
}