{
  "type": "Feature",
  "properties": {
    "addr:full":"606 Glenferrie Rd Hawthorn VIC 3122",
    "addr:housenumber":"606",
    "addr:postcode":"3122",
    "addr:street":"Glenferrie Rd",
    "iso:country":"AU",
    "sg:address":"606 Glenferrie Rd",
    "sg:city":"Hawthorn",
    "sg:classifiers":[
        {
            "category":"Personal",
            "subcategory":"Beauty Salon",
            "type":"Services"
        }
    ],
    "sg:phone":"+61 3 9818 5302",
    "sg:postcode":"3122",
    "sg:province":"VIC",
    "sg:tags":[
        "hairdresser"
    ],
    "wof:name":"Talking Heads",
    "wof:placetype":"venue"
},
  "geometry": {"coordinates":[145.03526306099999,-37.82396698],"type":"Point"}
}