{
  "type": "Feature",
  "properties": {
    "iso:country":"AU",
    "sg:address":"28 Atchinson St",
    "sg:city":"St Leonards",
    "sg:classifiers":[
        {
            "category":"Professional",
            "subcategory":"Employment Agencies",
            "type":"Services"
        }
    ],
    "sg:phone":"+61 2 9438 1234",
    "sg:postcode":"2065",
    "sg:province":"NSW",
    "sg:tags":[
        "provider",
        "internet"
    ],
    "wof:name":"Microplex",
    "wof:placetype":"venue"
},
  "geometry": {"coordinates":[151.197387695,-33.8227577209],"type":"Point"}
}