{
  "type": "Feature",
  "properties": {
    "iso:country":"AU",
    "sg:address":"Lot 16 Papps Rd",
    "sg:city":"Brunswick Junction",
    "sg:classifiers":[
        {
            "category":"Retail",
            "subcategory":"Auto Repair",
            "type":"Services"
        }
    ],
    "sg:phone":"+61 8 9726 1431",
    "sg:postcode":"6224",
    "sg:province":"WA",
    "sg:tags":[
        "repairer",
        "motor",
        "engineer"
    ],
    "wof:name":"Brunswick Diesels",
    "wof:placetype":"venue"
},
  "geometry": {"coordinates":[115.839691,-33.252102],"type":"Point"}
}