{
  "type": "Feature",
  "properties": {
    "addr:full":"Post Office Building 36 Llewellyn St Merewether NSW 2291",
    "addr:housenumber":"36",
    "addr:postcode":"2291",
    "addr:street":"Llewellyn St",
    "iso:country":"AU",
    "sg:address":"Post Office Building 36 Llewellyn St",
    "sg:city":"Merewether",
    "sg:classifiers":[
        {
            "category":"Professional",
            "subcategory":"Accounting & Tax Preparation",
            "type":"Services"
        }
    ],
    "sg:phone":"+61 2 4963 3291",
    "sg:postcode":"2291",
    "sg:province":"NSW",
    "sg:tags":[
        "consultant",
        "taxation"
    ],
    "wof:name":"Webber Accountants",
    "wof:placetype":"venue"
},
  "geometry": {"coordinates":[151.75135803200001,-32.9417915344],"type":"Point"}
}