{
  "type": "Feature",
  "properties": {
    "addr:full":"2 Isles Drv Coffs Harbour NSW 2450",
    "addr:housenumber":"2",
    "addr:postcode":"2450",
    "addr:street":"Isles Drv",
    "iso:country":"AU",
    "sg:address":"2 Isles Drv",
    "sg:city":"Coffs Harbour",
    "sg:classifiers":[
        {
            "category":"Wholesale",
            "subcategory":"Metals & Minerals",
            "type":"Manufacturing & Wholesale Goods"
        }
    ],
    "sg:phone":"+61 2 6648 7111",
    "sg:postcode":"2450",
    "sg:province":"NSW",
    "sg:tags":[
        "steel",
        "merchant"
    ],
    "wof:name":"Metalcorp Steel",
    "wof:placetype":"venue"
},
  "geometry": {"coordinates":[153.08377100000001,-30.319859],"type":"Point"}
}