{
  "type": "Feature",
  "properties": {
    "iso:country":"AU",
    "sg:address":"17 Brisbane Rd",
    "sg:city":"Gympie",
    "sg:classifiers":[
        {
            "category":"Wholesale",
            "subcategory":"Auto Parts",
            "type":"Manufacturing & Wholesale Goods"
        }
    ],
    "sg:phone":"+61 7 5483 9311",
    "sg:postcode":"4570",
    "sg:province":"QLD",
    "sg:tags":[
        "tyre"
    ],
    "wof:name":"Advance Tyres",
    "wof:placetype":"venue"
},
  "geometry": {"coordinates":[152.677658081,-26.2008457184],"type":"Point"}
}