{
  "type": "Feature",
  "properties": {
    "addr:full":"Unit 4 , 4 Narabang Way Belrose NSW 2085",
    "addr:housenumber":"4",
    "addr:postcode":"2085",
    "addr:street":"Narabang Way",
    "iso:country":"AU",
    "sg:address":"Unit 4",
    "sg:city":", 4 Narabang Way Belrose",
    "sg:classifiers":[
        {
            "category":"Manufacturing",
            "subcategory":"Retail Goods",
            "type":"Manufacturing & Wholesale Goods"
        }
    ],
    "sg:phone":"+61 2 9450 0995",
    "sg:postcode":"2085",
    "sg:province":"NSW",
    "sg:tags":[
        "merchant",
        "pump",
        "mfrs"
    ],
    "wof:name":"Prominent Fluid Controls",
    "wof:placetype":"venue"
},
  "geometry": {"coordinates":[151.21232605,-33.7051506042],"type":"Point"}
}