{
  "type": "Feature",
  "properties": {
    "addr:full":"PO Box 463 Joondalup Pte Boxes WA 6919",
    "addr:postcode":"6919",
    "iso:country":"AU",
    "sg:address":"PO Box 463",
    "sg:city":"Joondalup Pte Boxes",
    "sg:classifiers":[
        {
            "category":"Building & Trades",
            "subcategory":"Construction",
            "type":"Services"
        }
    ],
    "sg:phone":"+61 8 9301 2411",
    "sg:postcode":"6919",
    "sg:province":"WA",
    "sg:tags":[
        "home",
        "air conditioning"
    ],
    "wof:name":"Coolquip",
    "wof:placetype":"venue"
},
  "geometry": {"coordinates":[115.769889831,-31.7465190887],"type":"Point"}
}