{
  "type": "Feature",
  "properties": {
    "addr:full":"34 Deniliquin St Tocumwal NSW 2714",
    "addr:housenumber":"34",
    "addr:postcode":"2714",
    "addr:street":"Deniliquin St",
    "iso:country":"AU",
    "sg:address":"34 Deniliquin St",
    "sg:city":"Tocumwal",
    "sg:classifiers":[
        {
            "category":"Transit Center",
            "subcategory":"Passenger",
            "type":"Transportation"
        }
    ],
    "sg:phone":"+61 3 5874 2082",
    "sg:postcode":"2714",
    "sg:province":"NSW",
    "sg:tags":[
        "retail",
        "toiletry",
        "perfume"
    ],
    "wof:name":"Tocumwal Pharmacy",
    "wof:placetype":"venue"
},
  "geometry": {"coordinates":[145.56637573200001,-35.8120384216],"type":"Point"}
}