{
  "type": "Feature",
  "properties": {
    "addr:full":"100 Victoria St West End (Brisbane) QLD 4101",
    "addr:housenumber":"100",
    "addr:postcode":"4101",
    "addr:street":"Victoria St",
    "iso:country":"AU",
    "sg:address":"100 Victoria St",
    "sg:city":"West End (Brisbane)",
    "sg:classifiers":[
        {
            "category":"Professional",
            "subcategory":"Business Services",
            "type":"Services"
        }
    ],
    "sg:phone":"+61 1300 559 195",
    "sg:postcode":"4101",
    "sg:province":"QLD",
    "sg:tags":[
        "record",
        "management",
        "storage"
    ],
    "wof:name":"Decipha Pty Ltd",
    "wof:placetype":"venue"
},
  "geometry": {"coordinates":[153.00294494600001,-27.4824066162],"type":"Point"}
}