{
  "type": "Feature",
  "properties": {
    "addr:full":"14 Russell Drysdale Crs Conder ACT 2906",
    "addr:housenumber":"14",
    "addr:postcode":"2906",
    "addr:street":"Russell Drysdale Crs",
    "iso:country":"AU",
    "sg:address":"14 Russell Drysdale Crs",
    "sg:city":"Conder",
    "sg:classifiers":[
        {
            "category":"Building & Trades",
            "subcategory":"Construction",
            "type":"Services"
        }
    ],
    "sg:phone":"+61 2 6294 3088",
    "sg:postcode":"2906",
    "sg:province":"ACT",
    "sg:tags":[
        "renovation",
        "alterations",
        "extension",
        "contractor"
    ],
    "wof:name":"All Carpentry Services",
    "wof:placetype":"venue"
},
  "geometry": {"coordinates":[149.09780883799999,-35.4583282471],"type":"Point"}
}