{
  "type": "Feature",
  "properties": {
    "iso:country":"AU",
    "sg:address":"25 Enmore Rd",
    "sg:city":"Newtown",
    "sg:classifiers":[
        {
            "category":"Retail",
            "subcategory":"Funeral Services",
            "type":"Services"
        }
    ],
    "sg:phone":"+61 2 9557 2873",
    "sg:postcode":"2042",
    "sg:province":"NSW",
    "sg:tags":[
        "director"
    ],
    "wof:name":"Raymond Maurice F",
    "wof:placetype":"venue"
},
  "geometry": {"coordinates":[151.17558299999999,-33.89875],"type":"Point"}
}