{
  "type": "Feature",
  "properties": {
    "addr:full":"69 Salamanca Pl Hobart TAS 7000",
    "addr:housenumber":"69",
    "addr:postcode":"7000",
    "addr:street":"Salamanca Pl",
    "iso:country":"AU",
    "sg:address":"69 Salamanca Pl",
    "sg:city":"Hobart",
    "sg:classifiers":[
        {
            "category":"Bars & Pubs",
            "subcategory":"Dive Bar",
            "type":"Food & Drink"
        }
    ],
    "sg:phone":"+61 3 6234 1711",
    "sg:postcode":"7000",
    "sg:province":"TAS",
    "sg:tags":[
        "knitwear",
        "retail"
    ],
    "wof:name":"Tasmanian Woollen Co",
    "wof:placetype":"venue"
},
  "geometry": {"coordinates":[147.33380126899999,-42.8868370056],"type":"Point"}
}