{
  "type": "Feature",
  "properties": {
    "iso:country":"AU",
    "sg:address":"80 Morrow Pl",
    "sg:city":"Bathurst",
    "sg:classifiers":[
        {
            "category":"Shopping",
            "subcategory":"Musical Instruments",
            "type":"Retail Goods"
        }
    ],
    "sg:phone":"+61 2 6332 2354",
    "sg:postcode":"2795",
    "sg:province":"NSW",
    "sg:tags":[
        "musician",
        "agent"
    ],
    "wof:name":"Narelle & Roy Turner",
    "wof:placetype":"venue"
},
  "geometry": {"coordinates":[149.53689575199999,-33.4170837402],"type":"Point"}
}