{
  "type": "Feature",
  "properties": {
    "iso:country":"AU",
    "sg:address":"Shp3/ 113 Main Rd",
    "sg:city":"Moonah",
    "sg:classifiers":[
        {
            "category":"Banks & Credit Unions",
            "subcategory":"Financial Services",
            "type":"Services"
        }
    ],
    "sg:phone":"+61 3 6228 9466",
    "sg:postcode":"7009",
    "sg:province":"TAS",
    "sg:tags":[
        "financier"
    ],
    "wof:name":"2 Easy Loans",
    "wof:placetype":"venue"
},
  "geometry": {"coordinates":[147.294647217,-42.8460922241],"type":"Point"}
}