{
  "type": "Feature",
  "properties": {
    "addr:full":"PO Box 302 Kenmore QLD 4069",
    "addr:postcode":"4069",
    "iso:country":"AU",
    "sg:address":"PO Box 302",
    "sg:city":"Kenmore",
    "sg:classifiers":[
        {
            "category":"Building & Trades",
            "subcategory":"Landscaping Services",
            "type":"Services"
        }
    ],
    "sg:phone":"+61 411 557 688",
    "sg:postcode":"4069",
    "sg:province":"QLD",
    "sg:tags":[
        "designer",
        "landscape",
        "contractor"
    ],
    "wof:name":"P & L Landscaping Pty Ltd",
    "wof:placetype":"venue"
},
  "geometry": {"coordinates":[152.93849182100001,-27.508430481],"type":"Point"}
}