{
  "type": "Feature",
  "properties": {
    "addr:full":"117 Russell St Morley WA 6062",
    "addr:housenumber":"117",
    "addr:postcode":"6062",
    "addr:street":"Russell St",
    "iso:country":"AU",
    "sg:address":"117 Russell St",
    "sg:city":"Morley",
    "sg:classifiers":[
        {
            "category":"Food & Beverages",
            "subcategory":"Meat & Fish",
            "type":"Retail Goods"
        }
    ],
    "sg:phone":"+61 8 9275 2000",
    "sg:postcode":"6062",
    "sg:province":"WA",
    "sg:tags":[
        "seafood"
    ],
    "wof:name":"Morley Fish Factory",
    "wof:placetype":"venue"
},
  "geometry": {"coordinates":[115.898620605,-31.8999938965],"type":"Point"}
}