{
  "type": "Feature",
  "properties": {
    "addr:full":"27 Booner St Hawks Nest NSW 2324",
    "addr:housenumber":"27",
    "addr:postcode":"2324",
    "addr:street":"Booner St",
    "iso:country":"AU",
    "sg:address":"27 Booner St",
    "sg:city":"Hawks Nest",
    "sg:classifiers":[
        {
            "category":"Real Estate",
            "subcategory":"Real Estate Agent",
            "type":"Services"
        }
    ],
    "sg:phone":"+61 2 4997 0427",
    "sg:postcode":"2324",
    "sg:province":"NSW",
    "wof:name":"L J Hooker",
    "wof:placetype":"venue"
},
  "geometry": {"coordinates":[152.175094605,-32.6722068787],"type":"Point"}
}