{
  "type": "Feature",
  "properties": {
    "addr:full":"14 Farrell Crs Winnellie NT 0820",
    "addr:housenumber":"14",
    "addr:postcode":"nt 0820",
    "addr:street":"Farrell Crs",
    "iso:country":"AU",
    "sg:address":"14 Farrell Crs",
    "sg:city":"Winnellie",
    "sg:classifiers":[
        {
            "category":"Building & Trades",
            "subcategory":"Electrical",
            "type":"Services"
        }
    ],
    "sg:phone":"+61 8 8984 4535",
    "sg:postcode":"0820",
    "sg:province":"NT",
    "sg:tags":[
        "repair",
        "generator",
        "electric",
        "motor"
    ],
    "wof:name":"North Australian Mechanical & Electrical Services",
    "wof:placetype":"venue"
},
  "geometry": {"coordinates":[130.89439392099999,-12.4263296127],"type":"Point"}
}