{
  "type": "Feature",
  "properties": {
    "addr:full":"Cnr Rokeby & Roberts Rds Subiaco WA 6008",
    "addr:postcode":"6008",
    "addr:street":"Cnr",
    "iso:country":"AU",
    "sg:address":"Cnr Rokeby & Roberts Rds",
    "sg:city":"Subiaco",
    "sg:classifiers":[
        {
            "category":"Building & Trades",
            "subcategory":"Landscaping Services",
            "type":"Services"
        }
    ],
    "sg:phone":"+61 8 9382 2498",
    "sg:postcode":"6008",
    "sg:province":"WA",
    "sg:tags":[
        "market"
    ],
    "wof:name":"Subiaco Pavilion Markets",
    "wof:placetype":"venue"
},
  "geometry": {"coordinates":[115.824012756,-31.9468021393],"type":"Point"}
}