{
  "type": "Feature",
  "properties": {
    "addr:full":"433 Argent St Broken Hill NSW 2880",
    "addr:housenumber":"433",
    "addr:postcode":"2880",
    "addr:street":"Argent St",
    "iso:country":"AU",
    "sg:address":"433 Argent St",
    "sg:city":"Broken Hill",
    "sg:classifiers":[
        {
            "category":"Shopping",
            "subcategory":"Music",
            "type":"Retail Goods"
        }
    ],
    "sg:phone":"+61 8 8088 4840",
    "sg:postcode":"2880",
    "sg:province":"NSW",
    "sg:tags":[
        "instrument",
        "musical"
    ],
    "wof:name":"Broken Hill Music Centre",
    "wof:placetype":"venue"
},
  "geometry": {"coordinates":[141.468826294,-31.956451416],"type":"Point"}
}