{
  "type": "Feature",
  "properties": {
    "iso:country":"AU",
    "sg:address":"8/ 161 Malabar Rd",
    "sg:city":"South Coogee",
    "sg:classifiers":[
        {
            "category":"Social Services",
            "subcategory":"Child Care",
            "type":"Services"
        }
    ],
    "sg:phone":"+61 400 418 448",
    "sg:postcode":"2034",
    "sg:province":"NSW",
    "sg:tags":[
        "childbirth"
    ],
    "wof:name":"Essential Birth Consulting",
    "wof:placetype":"venue"
},
  "geometry": {"coordinates":[151.25694274899999,-33.9319839478],"type":"Point"}
}