{
  "type": "Feature",
  "properties": {
    "addr:full":"Suit 5/ Dickson Chmbrs Dickson ACT 2602",
    "addr:postcode":"2602",
    "iso:country":"AU",
    "sg:address":"Suit 5/ Dickson Chmbrs",
    "sg:city":"Dickson",
    "sg:classifiers":[
        {
            "category":"Health Services",
            "subcategory":"Doctor",
            "type":"Services"
        }
    ],
    "sg:phone":"+61 2 6248 7996",
    "sg:postcode":"2602",
    "sg:province":"ACT",
    "sg:tags":[
        "medical",
        "practitioner"
    ],
    "wof:name":"Mayne Laverty Pathology Collection Centres",
    "wof:placetype":"venue"
},
  "geometry": {"coordinates":[149.138015747,-35.2501411438],"type":"Point"}
}