{
  "type": "Feature",
  "properties": {
    "addr:full":"Suite 3- 7 Moon St Ballina NSW 2478",
    "addr:housenumber":"7",
    "addr:postcode":"2478",
    "addr:street":"Moon St",
    "iso:country":"AU",
    "sg:address":"Suite 3- 7 Moon St",
    "sg:city":"Ballina",
    "sg:classifiers":[
        {
            "category":"Wholesale",
            "subcategory":"Medical Equipment & Supplies",
            "type":"Manufacturing & Wholesale Goods"
        }
    ],
    "sg:phone":"+61 1800 351 333",
    "sg:postcode":"2478",
    "sg:province":"NSW",
    "sg:tags":[
        "aids",
        "hearing"
    ],
    "wof:name":"Advanced Hearing Aid Specialists",
    "wof:placetype":"venue"
},
  "geometry": {"coordinates":[153.55938720699999,-28.8697757721],"type":"Point"}
}