{
  "type": "Feature",
  "properties": {
    "addr:full":"Shop 23 Centro Buranda, Cnr Ipswich Rd & Cornwall St Buranda QLD 4102",
    "addr:housenumber":"shop 23",
    "addr:postcode":"4102",
    "addr:street":"Ipswich Rd & Cornwall St",
    "iso:country":"AU",
    "sg:address":"Shop 23 Centro Buranda, Cnr Ipswich Rd & Cornwall St",
    "sg:city":"Buranda",
    "sg:classifiers":[
        {
            "category":"Travel",
            "subcategory":"Travel Agent",
            "type":"Entertainment"
        }
    ],
    "sg:phone":"+61 13 18 66",
    "sg:postcode":"4102",
    "sg:province":"QLD",
    "sg:tags":[
        "consultant"
    ],
    "wof:name":"Flight Centre",
    "wof:placetype":"venue"
},
  "geometry": {"coordinates":[153.03518676799999,-27.5005073547],"type":"Point"}
}