{
  "type": "Feature",
  "properties": {
    "addr:full":"5 Kadina Crt Mooroolbark VIC 3138",
    "addr:housenumber":"5",
    "addr:postcode":"3138",
    "addr:street":"Kadina Crt",
    "iso:country":"AU",
    "sg:address":"5 Kadina Crt",
    "sg:city":"Mooroolbark",
    "sg:classifiers":[
        {
            "category":"Building & Trades",
            "subcategory":"Construction",
            "type":"Services"
        }
    ],
    "sg:phone":"+61 419 273 787",
    "sg:postcode":"3138",
    "sg:province":"VIC",
    "sg:tags":[
        "contractor"
    ],
    "wof:name":"R.J. Stallworthy Builder",
    "wof:placetype":"venue"
},
  "geometry": {"coordinates":[145.321136475,-37.7702903748],"type":"Point"}
}