{
  "type": "Feature",
  "properties": {
    "addr:full":"66 Crown St Richmond VIC 3121",
    "addr:housenumber":"66",
    "addr:postcode":"3121",
    "addr:street":"Crown St",
    "iso:country":"AU",
    "sg:address":"66 Crown St",
    "sg:city":"Richmond",
    "sg:classifiers":[
        {
            "category":"Professional",
            "subcategory":"Art Services",
            "type":"Services"
        }
    ],
    "sg:phone":"+61 3 9428 3235",
    "sg:postcode":"3121",
    "sg:province":"VIC",
    "sg:tags":[
        "decorator",
        "painter"
    ],
    "wof:name":"Jack Kelly & Son Pty Ltd",
    "wof:placetype":"venue"
},
  "geometry": {"coordinates":[145.013061523,-37.8173332214],"type":"Point"}
}