{
  "type": "Feature",
  "properties": {
    "addr:full":"Unit 7, 42 Burnside Rd Ormeau QLD 4208",
    "addr:housenumber":"42",
    "addr:postcode":"4208",
    "addr:street":"Burnside Rd",
    "iso:country":"AU",
    "sg:address":"Unit 7, 42 Burnside Rd",
    "sg:city":"Ormeau",
    "sg:classifiers":[
        {
            "category":"Professional",
            "type":"Services"
        }
    ],
    "sg:phone":"+61 7 3382 7578",
    "sg:postcode":"4208",
    "sg:province":"QLD",
    "sg:tags":[
        "spray",
        "painting"
    ],
    "wof:name":"Luxury Furniture Finishes",
    "wof:placetype":"venue"
},
  "geometry": {"coordinates":[153.240234375,-27.7554340363],"type":"Point"}
}