{
  "type": "Feature",
  "properties": {
    "addr:full":"PO Box 2178 Gateshead NSW 2290",
    "addr:postcode":"2290",
    "iso:country":"AU",
    "sg:address":"PO Box 2178",
    "sg:city":"Gateshead",
    "sg:classifiers":[
        {
            "category":"Building & Trades",
            "subcategory":"Construction",
            "type":"Services"
        }
    ],
    "sg:phone":"+61 2 4969 2866",
    "sg:postcode":"2290",
    "sg:province":"NSW",
    "sg:tags":[
        "contractor"
    ],
    "wof:name":"Litchfield Roofing (Australia) Pty Ltd",
    "wof:placetype":"venue"
},
  "geometry": {"coordinates":[151.686676025,-32.9817504883],"type":"Point"}
}