{
  "type": "Feature",
  "properties": {
    "iso:country":"AU",
    "sg:address":"Cnr Lauderdale & Narre Warren North Rds",
    "sg:city":"Narre Warren North",
    "sg:classifiers":[
        {
            "category":"Manufacturing",
            "subcategory":"Motor Vehicles & Parts",
            "type":"Manufacturing & Wholesale Goods"
        }
    ],
    "sg:phone":"+61 3 9705 8800",
    "sg:postcode":"3804",
    "sg:province":"VIC",
    "sg:tags":[
        "replacement"
    ],
    "wof:name":"Autobarn Pty Ltd",
    "wof:placetype":"venue"
},
  "geometry": {"coordinates":[145.30734252900001,-38.0235099792],"type":"Point"}
}