{
  "type": "Feature",
  "properties": {
    "iso:country":"AU",
    "sg:address":"258 Highett Rd",
    "sg:city":"Highett",
    "sg:classifiers":[
        {
            "category":"Health Services",
            "subcategory":"Doctor",
            "type":"Services"
        }
    ],
    "sg:phone":"+61 3 9555 2177",
    "sg:postcode":"3190",
    "sg:province":"VIC",
    "sg:tags":[
        "medical",
        "practitioner"
    ],
    "wof:name":"Wenig Maury",
    "wof:placetype":"venue"
},
  "geometry": {"coordinates":[145.03892517099999,-37.948513031],"type":"Point"}
}