{
  "type": "Feature",
  "properties": {
    "addr:full":"464 Banna Ave Griffith NSW 2680",
    "addr:housenumber":"464",
    "addr:postcode":"2680",
    "addr:street":"Banna Ave",
    "iso:country":"AU",
    "sg:address":"464 Banna Ave",
    "sg:city":"Griffith",
    "sg:classifiers":[
        {
            "category":"Professional",
            "subcategory":"Accounting & Tax Preparation",
            "type":"Services"
        }
    ],
    "sg:phone":"+61 2 6964 4880",
    "sg:postcode":"2680",
    "sg:province":"NSW",
    "sg:tags":[
        "consultant",
        "taxation"
    ],
    "wof:name":"The Income Tax Professionals",
    "wof:placetype":"venue"
},
  "geometry": {"coordinates":[146.05978400000001,-34.289406],"type":"Point"}
}