{
  "type": "Feature",
  "properties": {
    "addr:full":"8 Gourlay Ave Balgowlah NSW 2093",
    "addr:housenumber":"8",
    "addr:postcode":"2093",
    "addr:street":"Gourlay Ave",
    "iso:country":"AU",
    "sg:address":"8 Gourlay Ave",
    "sg:city":"Balgowlah",
    "sg:classifiers":[
        {
            "category":"Professional",
            "subcategory":"Art Services",
            "type":"Services"
        }
    ],
    "sg:phone":"+61 2 9948 6124",
    "sg:postcode":"2093",
    "sg:province":"NSW",
    "sg:tags":[
        "graphic",
        "designer"
    ],
    "wof:name":"Ivana McAlpine Design Pty Ltd",
    "wof:placetype":"venue"
},
  "geometry": {"coordinates":[151.26559448200001,-33.800655365],"type":"Point"}
}