{
  "type": "Feature",
  "properties": {
    "iso:country":"AU",
    "sg:address":"45 Lt Boundary Rd",
    "sg:city":"Brooklyn",
    "sg:classifiers":[
        {
            "category":"Wholesale",
            "subcategory":"Machinery & Supplies",
            "type":"Manufacturing & Wholesale Goods"
        }
    ],
    "sg:phone":"+61 3 9314 2511",
    "sg:postcode":"3025",
    "sg:province":"VIC",
    "wof:name":"Maker F A Pty Ltd",
    "wof:placetype":"venue"
},
  "geometry": {"coordinates":[144.82612599999999,-37.838341],"type":"Point"}
}