{
  "type": "Feature",
  "properties": {
    "iso:country":"AU",
    "sg:address":"458 Pacific Hwy",
    "sg:city":"Wyong",
    "sg:classifiers":[
        {
            "category":"Banks & Credit Unions",
            "subcategory":"Financial Services",
            "type":"Services"
        }
    ],
    "sg:phone":"+61 2 4351 5477",
    "sg:postcode":"2259",
    "sg:province":"NSW",
    "sg:tags":[
        "loan",
        "finance",
        "mortgage"
    ],
    "wof:name":"HLE Financial Dynamics",
    "wof:placetype":"venue"
},
  "geometry": {"coordinates":[151.45289611800001,-33.2709732056],"type":"Point"}
}