{
  "type": "Feature",
  "properties": {
    "addr:full":"6 MacArthur Ave Padbury WA 6025",
    "addr:housenumber":"6",
    "addr:postcode":"6025",
    "addr:street":"Macarthur Ave",
    "iso:country":"AU",
    "sg:address":"6 MacArthur Ave",
    "sg:city":"Padbury",
    "sg:classifiers":[
        {
            "category":"Utilities",
            "subcategory":"Electric",
            "type":"Services"
        }
    ],
    "sg:phone":"+61 8 9403 0229",
    "sg:postcode":"6025",
    "sg:province":"WA",
    "sg:tags":[
        "electrical",
        "contractor"
    ],
    "wof:name":"Andrew J",
    "wof:placetype":"venue"
},
  "geometry": {"coordinates":[115.767417908,-31.7952613831],"type":"Point"}
}