{
  "type": "Feature",
  "properties": {
    "addr:full":"169 Johnson St Maffra VIC 3860",
    "addr:housenumber":"169",
    "addr:postcode":"3860",
    "addr:street":"Johnson St",
    "iso:country":"AU",
    "sg:address":"169 Johnson St",
    "sg:city":"Maffra",
    "sg:classifiers":[
        {
            "category":"Autos & Motor Vehicles",
            "subcategory":"Auto Supplies",
            "type":"Retail Goods"
        }
    ],
    "sg:phone":"+61 3 5147 1000",
    "sg:postcode":"3860",
    "sg:province":"VIC",
    "sg:tags":[
        "part",
        "cycles",
        "accessory"
    ],
    "wof:name":"Country Motorcycles",
    "wof:placetype":"venue"
},
  "geometry": {"coordinates":[146.978424072,-37.9687156677],"type":"Point"}
}