{
  "type": "Feature",
  "properties": {
    "addr:full":"Lvl 5, 71- 75 Archer St Chatswood NSW 2067",
    "addr:housenumber":"71 75",
    "addr:postcode":"2067",
    "addr:street":"Archer St",
    "iso:country":"AU",
    "sg:address":"Lvl 5, 71- 75 Archer St",
    "sg:city":"Chatswood",
    "sg:classifiers":[
        {
            "category":"Professional",
            "subcategory":"Accounting & Tax Preparation",
            "type":"Services"
        }
    ],
    "sg:phone":"+61 2 9413 4772",
    "sg:postcode":"2067",
    "sg:province":"NSW",
    "sg:tags":[
        "accountant",
        "auditor"
    ],
    "wof:name":"Cantwell & Co",
    "wof:placetype":"venue"
},
  "geometry": {"coordinates":[151.18557739299999,-33.7957267761],"type":"Point"}
}