{
  "type": "Feature",
  "properties": {
    "addr:full":"622 St Kilda Rd Melbourne VIC 3000",
    "addr:housenumber":"622",
    "addr:postcode":"3000",
    "addr:street":"St Kilda Rd",
    "iso:country":"AU",
    "sg:address":"622 St Kilda Rd",
    "sg:city":"Melbourne",
    "sg:classifiers":[
        {
            "category":"Manufacturing",
            "subcategory":"Food",
            "type":"Manufacturing & Wholesale Goods"
        }
    ],
    "sg:phone":"+61 3 9533 2244",
    "sg:postcode":"3000",
    "sg:province":"VIC",
    "sg:tags":[
        "function",
        "catering"
    ],
    "wof:name":"Subway",
    "wof:placetype":"venue"
},
  "geometry": {"coordinates":[144.98135375999999,-37.8531417847],"type":"Point"}
}