{
  "type": "Feature",
  "properties": {
    "addr:full":"78 Bayview St Runaway Bay QLD 4216",
    "addr:housenumber":"78",
    "addr:postcode":"4216",
    "addr:street":"Bayview St",
    "iso:country":"AU",
    "sg:address":"78 Bayview St",
    "sg:city":"Runaway Bay",
    "sg:classifiers":[
        {
            "category":"Health Services",
            "subcategory":"Doctor",
            "type":"Services"
        }
    ],
    "sg:phone":"+61 7 5528 9111",
    "sg:postcode":"4216",
    "sg:province":"QLD",
    "sg:tags":[
        "medical",
        "practitioner"
    ],
    "wof:name":"Runaway Bay General Practice",
    "wof:placetype":"venue"
},
  "geometry": {"coordinates":[153.40415954599999,-27.9217128754],"type":"Point"}
}