{
  "type": "Feature",
  "properties": {
    "iso:country":"AU",
    "sg:address":"36c Aitken St",
    "sg:city":"Gisborne",
    "sg:classifiers":[
        {
            "category":"Personal",
            "subcategory":"Beauty Salon",
            "type":"Services"
        }
    ],
    "sg:phone":"+61 3 5428 2424",
    "sg:postcode":"3437",
    "sg:province":"VIC",
    "sg:tags":[
        "hairdresser"
    ],
    "wof:name":"Marinelli\"s Hair Studio",
    "wof:placetype":"venue"
},
  "geometry": {"coordinates":[144.590866089,-37.4873924255],"type":"Point"}
}