{
  "type": "Feature",
  "properties": {
    "addr:full":"3 Howard St Nambour QLD 4560",
    "addr:housenumber":"3",
    "addr:postcode":"4560",
    "addr:street":"Howard St",
    "iso:country":"AU",
    "sg:address":"3 Howard St",
    "sg:city":"Nambour",
    "sg:classifiers":[
        {
            "category":"Real Estate",
            "subcategory":"Real Estate Agent",
            "type":"Services"
        }
    ],
    "sg:phone":"+61 7 5441 5442",
    "sg:postcode":"4560",
    "sg:province":"QLD",
    "wof:name":"Elders Nambour",
    "wof:placetype":"venue"
},
  "geometry": {"coordinates":[152.96310424800001,-26.6265716553],"type":"Point"}
}