{
  "type": "Feature",
  "properties": {
    "addr:full":"260 Inspiration Drv Wangara WA 6065",
    "addr:housenumber":"260",
    "addr:postcode":"6065",
    "addr:street":"Inspiration Drv",
    "iso:country":"AU",
    "sg:address":"260 Inspiration Drv",
    "sg:city":"Wangara",
    "sg:classifiers":[
        {
            "category":"Ferry Terminal",
            "type":"Transportation"
        }
    ],
    "sg:phone":"+61 1800 249 168",
    "sg:postcode":"6065",
    "sg:province":"WA",
    "sg:tags":[
        "mixing",
        "concrete",
        "vibrator",
        "equipment"
    ],
    "wof:name":"Batchcrete International Pty Ltd",
    "wof:placetype":"venue"
},
  "geometry": {"coordinates":[115.834159851,-31.7997322083],"type":"Point"}
}