{
  "type": "Feature",
  "properties": {
    "iso:country":"AU",
    "sg:address":"313 New St",
    "sg:city":"Brighton",
    "sg:classifiers":[
        {
            "category":"Health Services",
            "subcategory":"Dentist",
            "type":"Services"
        }
    ],
    "sg:phone":"+61 3 9593 1578",
    "sg:postcode":"3186",
    "sg:province":"VIC",
    "wof:name":"Needham Susan Dr",
    "wof:placetype":"venue"
},
  "geometry": {"coordinates":[144.992843628,-37.9052009583],"type":"Point"}
}