{
  "type": "Feature",
  "properties": {
    "iso:country":"AU",
    "sg:address":"68 Moss St",
    "sg:city":"Springwood",
    "sg:classifiers":[
        {
            "category":"Autos & Motor Vehicles",
            "subcategory":"Auto Supplies",
            "type":"Retail Goods"
        }
    ],
    "sg:phone":"+61 7 3808 7850",
    "sg:postcode":"4127",
    "sg:province":"QLD",
    "sg:tags":[
        "part",
        "cycles",
        "accessory"
    ],
    "sg:website":"http://www.teammoto.com.au",
    "wof:name":"Team Moto Motorcycles",
    "wof:placetype":"venue"
},
  "geometry": {"coordinates":[153.123657227,-27.6213264465],"type":"Point"}
}