{
  "type": "Feature",
  "properties": {
    "iso:country":"AU",
    "sg:address":"20 Skyring St",
    "sg:city":"Bundaberg",
    "sg:classifiers":[
        {
            "category":"Education",
            "subcategory":"Vocational School",
            "type":"Public Place"
        }
    ],
    "sg:phone":"+61 7 4151 7507",
    "sg:postcode":"4670",
    "sg:province":"QLD",
    "sg:tags":[
        "finishing",
        "modelling"
    ],
    "wof:name":"Cynthia Hoogstraten",
    "wof:placetype":"venue"
},
  "geometry": {"coordinates":[152.36958313,-24.8623409271],"type":"Point"}
}