{
  "type": "Feature",
  "properties": {
    "addr:full":"Yeranda Darkum Rd Mullaway NSW 2456",
    "addr:postcode":"2456",
    "addr:street":"Darkum Rd",
    "iso:country":"AU",
    "sg:address":"Yeranda Darkum Rd",
    "sg:city":"Mullaway",
    "sg:classifiers":[
        {
            "category":"Utilities",
            "subcategory":"Mobile Phone",
            "type":"Services"
        }
    ],
    "sg:phone":"+61 2 6654 8071",
    "sg:postcode":"2456",
    "sg:province":"NSW",
    "sg:tags":[
        "aviation",
        "consultant"
    ],
    "wof:name":"AviPro-Aviation Professional Services Pty Ltd",
    "wof:placetype":"venue"
},
  "geometry": {"coordinates":[153.19773900000001,-30.077871],"type":"Point"}
}