{
  "type": "Feature",
  "properties": {
    "addr:full":"876 Mt Alexandra Rd Moonee Ponds VIC 3039",
    "addr:housenumber":"876",
    "addr:postcode":"3039",
    "addr:street":"Mt Alexandra Rd",
    "iso:country":"AU",
    "sg:address":"876 Mt Alexandra Rd",
    "sg:city":"Moonee Ponds",
    "sg:classifiers":[
        {
            "category":"Autos & Motor Vehicles",
            "subcategory":"Fuel & Gas Station",
            "type":"Retail Goods"
        }
    ],
    "sg:phone":"+61 3 9370 1139",
    "sg:postcode":"3039",
    "sg:province":"VIC",
    "wof:name":"Mobil Oil Australia Pty Ltd",
    "wof:placetype":"venue"
},
  "geometry": {"coordinates":[144.91952499999999,-37.757381],"type":"Point"}
}