{
  "type": "Feature",
  "properties": {
    "addr:full":"12 Flinders Drv Cape Jervis SA 5204",
    "addr:housenumber":"12",
    "addr:postcode":"5204",
    "addr:street":"Flinders Drv",
    "iso:country":"AU",
    "sg:address":"12 Flinders Drv",
    "sg:city":"Cape Jervis",
    "sg:classifiers":[
        {
            "category":"Recreation",
            "subcategory":"Fishing",
            "type":"Entertainment"
        }
    ],
    "sg:phone":"+61 8 8598 0326",
    "sg:postcode":"5204",
    "sg:province":"SA",
    "sg:tags":[
        "trip"
    ],
    "wof:name":"Lands and Pro Charters",
    "wof:placetype":"venue"
},
  "geometry": {"coordinates":[138.11253356899999,-35.6040611267],"type":"Point"}
}