{
  "type": "Feature",
  "properties": {
    "addr:full":"21 Lissner St Toowong QLD 4066",
    "addr:housenumber":"21",
    "addr:postcode":"4066",
    "addr:street":"Lissner St",
    "iso:country":"AU",
    "sg:address":"21 Lissner St",
    "sg:city":"Toowong",
    "sg:classifiers":[
        {
            "category":"Banks & Credit Unions",
            "subcategory":"Investment Brokerage",
            "type":"Services"
        }
    ],
    "sg:phone":"+61 7 3217 7244",
    "sg:postcode":"4066",
    "sg:province":"QLD",
    "sg:tags":[
        "finance",
        "broker"
    ],
    "wof:name":"Sample & Partners",
    "wof:placetype":"venue"
},
  "geometry": {"coordinates":[152.99107360799999,-27.4840984344],"type":"Point"}
}