{
  "type": "Feature",
  "properties": {
    "addr:full":"Ground Floor 303 Adelaide St Brisbane QLD 4001",
    "addr:housenumber":"303",
    "addr:postcode":"4001",
    "addr:street":"Adelaide St",
    "iso:country":"AU",
    "sg:address":"Ground Floor 303 Adelaide St",
    "sg:city":"Brisbane",
    "sg:classifiers":[
        {
            "category":"Organizations",
            "subcategory":"Membership Organization",
            "type":"Services"
        }
    ],
    "sg:phone":"+61 7 3234 0190",
    "sg:postcode":"4001",
    "sg:province":"QLD",
    "sg:tags":[
        "support",
        "health",
        "organisation"
    ],
    "wof:name":"Queensland Community Services & Health Industries Training Council Inc.",
    "wof:placetype":"venue"
},
  "geometry": {"coordinates":[153.02932739299999,-27.4652633667],"type":"Point"}
}