{
  "type": "Feature",
  "properties": {
    "addr:full":"Narcotic Creek Rd Chewko QLD 4880",
    "addr:postcode":"4880",
    "addr:street":"Creek Rd",
    "iso:country":"AU",
    "sg:address":"Narcotic Creek Rd",
    "sg:city":"Chewko",
    "sg:classifiers":[
        {
            "category":"Farming",
            "subcategory":"Farm",
            "type":"Manufacturing & Wholesale Goods"
        }
    ],
    "sg:phone":"+61 7 4093 3885",
    "sg:postcode":"4880",
    "sg:province":"QLD",
    "sg:tags":[
        "farmer"
    ],
    "wof:name":"Cabassi A",
    "wof:placetype":"venue"
},
  "geometry": {"coordinates":[145.358474731,-17.0815696716],"type":"Point"}
}