{
  "type": "Feature",
  "properties": {
    "addr:full":"91 Hartnett Drv Seaford VIC 3198",
    "addr:housenumber":"91",
    "addr:postcode":"3198",
    "addr:street":"Hartnett Drv",
    "iso:country":"AU",
    "sg:address":"91 Hartnett Drv",
    "sg:city":"Seaford",
    "sg:classifiers":[
        {
            "category":"Wholesale",
            "subcategory":"Electrical",
            "type":"Manufacturing & Wholesale Goods"
        }
    ],
    "sg:phone":"+61 3 9782 4611",
    "sg:postcode":"3198",
    "sg:province":"VIC",
    "sg:tags":[
        "wholesaler"
    ],
    "wof:name":"AWM Electrical",
    "wof:placetype":"venue"
},
  "geometry": {"coordinates":[145.14059448200001,-38.1187095642],"type":"Point"}
}