{
  "type": "Feature",
  "properties": {
    "iso:country":"AU",
    "sg:address":"Lot 7/ 85 Rowe La",
    "sg:city":"Cedar Creek",
    "sg:classifiers":[
        {
            "category":"Utilities",
            "subcategory":"Telephone",
            "type":"Services"
        }
    ],
    "sg:phone":"+61 7 5546 4616",
    "sg:postcode":"4520",
    "sg:province":"QLD",
    "sg:tags":[
        "installation",
        "system",
        "maintenance"
    ],
    "wof:name":"Monterey Communications",
    "wof:placetype":"venue"
},
  "geometry": {"coordinates":[152.796753,-27.32493],"type":"Point"}
}