{
  "type": "Feature",
  "properties": {
    "addr:full":"113 Winifred St Oak Park VIC 3046",
    "addr:housenumber":"113",
    "addr:postcode":"3046",
    "addr:street":"Winifred St",
    "iso:country":"AU",
    "sg:address":"113 Winifred St",
    "sg:city":"Oak Park",
    "sg:classifiers":[
        {
            "category":"Building & Trades",
            "subcategory":"Construction",
            "type":"Services"
        }
    ],
    "sg:phone":"+61 3 9304 2428",
    "sg:postcode":"3046",
    "sg:province":"VIC",
    "sg:tags":[
        "polishing",
        "sanding",
        "floor"
    ],
    "wof:name":"Nicks Sanding & Polishing",
    "wof:placetype":"venue"
},
  "geometry": {"coordinates":[144.910430908,-37.7169799805],"type":"Point"}
}