{
  "type": "Feature",
  "properties": {
    "addr:full":"202 Church St Richmond VIC 3121",
    "addr:housenumber":"202",
    "addr:postcode":"3121",
    "addr:street":"Church St",
    "iso:country":"AU",
    "sg:address":"202 Church St",
    "sg:city":"Richmond",
    "sg:classifiers":[
        {
            "category":"Personal",
            "subcategory":"Beauty Salon",
            "type":"Services"
        }
    ],
    "sg:phone":"+61 3 9428 1666",
    "sg:postcode":"3121",
    "sg:province":"VIC",
    "sg:tags":[
        "hairdresser"
    ],
    "wof:name":"Pinky Hair Salon",
    "wof:placetype":"venue"
},
  "geometry": {"coordinates":[144.99928283700001,-37.817024231],"type":"Point"}
}