{
  "type": "Feature",
  "properties": {
    "addr:full":"Cnr Nicklin Way & Wyandra Drv Kawana QLD 4701",
    "addr:postcode":"4701",
    "addr:street":"Cnr Nicklin Way & Wyandra Drv",
    "iso:country":"AU",
    "sg:address":"Cnr Nicklin Way & Wyandra Drv",
    "sg:city":"Kawana",
    "sg:classifiers":[
        {
            "category":"Retail",
            "subcategory":"Auto Repair",
            "type":"Services"
        }
    ],
    "sg:phone":"+61 7 5493 4282",
    "sg:postcode":"4701",
    "sg:province":"QLD",
    "sg:tags":[
        "clutch",
        "brake"
    ],
    "wof:name":"BP Car Care",
    "wof:placetype":"venue"
},
  "geometry": {"coordinates":[150.51556396500001,-23.3370304108],"type":"Point"}
}