{
  "type": "Feature",
  "properties": {
    "addr:full":"Cnr High St & Orrong Rd Armadale VIC 3143",
    "addr:postcode":"3143",
    "addr:street":"High St & Orrong Rd",
    "iso:country":"AU",
    "sg:address":"Cnr High St & Orrong Rd",
    "sg:city":"Armadale",
    "sg:classifiers":[
        {
            "category":"Food & Beverages",
            "subcategory":"Groceries & Convenience Stores",
            "type":"Retail Goods"
        }
    ],
    "sg:phone":"+61 3 9510 2132",
    "sg:postcode":"3143",
    "sg:province":"VIC",
    "wof:name":"7-Eleven Stores Pty Ltd",
    "wof:placetype":"venue"
},
  "geometry": {"coordinates":[145.01965332,-37.8553466797],"type":"Point"}
}