{
  "type": "Feature",
  "properties": {
    "iso:country":"AU",
    "sg:address":"7 Malcolm Crt",
    "sg:city":"Ringwood East",
    "sg:classifiers":[
        {
            "category":"Health Services",
            "subcategory":"Health Practitioner",
            "type":"Services"
        }
    ],
    "sg:phone":"+61 3 9879 2145",
    "sg:postcode":"3135",
    "sg:province":"VIC",
    "sg:tags":[
        "psychologist"
    ],
    "wof:name":"Dowling Peter Dr",
    "wof:placetype":"venue"
},
  "geometry": {"coordinates":[145.25534057600001,-37.8188323975],"type":"Point"}
}