{
  "type": "Feature",
  "properties": {
    "addr:full":"62 Doggett St Newstead QLD 4006",
    "addr:housenumber":"62",
    "addr:postcode":"4006",
    "addr:street":"Doggett St",
    "iso:country":"AU",
    "sg:address":"62 Doggett St",
    "sg:city":"Newstead",
    "sg:classifiers":[
        {
            "category":"Ice Cream",
            "type":"Food & Drink"
        }
    ],
    "sg:phone":"+61 7 3257 0414",
    "sg:postcode":"4006",
    "sg:province":"QLD",
    "sg:tags":[
        "retail"
    ],
    "wof:name":"Cold Rock Ice Creamery",
    "wof:placetype":"venue"
},
  "geometry": {"coordinates":[153.04339599599999,-27.4530124664],"type":"Point"}
}