{
  "type": "Feature",
  "properties": {
    "addr:full":"Union Rd Albury North NSW 2640",
    "addr:postcode":"2640",
    "addr:street":"Union Rd",
    "iso:country":"AU",
    "sg:address":"Union Rd",
    "sg:city":"Albury North",
    "sg:classifiers":[
        {
            "category":"Retail",
            "subcategory":"Funeral Services",
            "type":"Services"
        }
    ],
    "sg:phone":"+61 2 6025 1764",
    "sg:postcode":"2640",
    "sg:province":"NSW",
    "sg:tags":[
        "cremation"
    ],
    "wof:name":"Glenmorus Gardens",
    "wof:placetype":"venue"
},
  "geometry": {"coordinates":[146.89942932100001,-36.0457878113],"type":"Point"}
}