{
  "type": "Feature",
  "properties": {
    "addr:full":"23 Chandos St St Leonards NSW 2065",
    "addr:housenumber":"23",
    "addr:postcode":"2065",
    "addr:street":"Chandos St",
    "iso:country":"AU",
    "sg:address":"23 Chandos St",
    "sg:city":"St Leonards",
    "sg:classifiers":[
        {
            "category":"Professional",
            "subcategory":"Employment Agencies",
            "type":"Services"
        }
    ],
    "sg:phone":"+61 2 9439 1725",
    "sg:postcode":"2065",
    "sg:province":"NSW",
    "sg:tags":[
        "model"
    ],
    "wof:name":"Asian Model & Talent Agency",
    "wof:placetype":"venue"
},
  "geometry": {"coordinates":[151.196365356,-33.8221549988],"type":"Point"}
}