{
  "type": "Feature",
  "properties": {
    "iso:country":"AU",
    "sg:address":"PO Box 32",
    "sg:city":"Prospect",
    "sg:classifiers":[
        {
            "category":"Autos & Motor Vehicles",
            "subcategory":"Automobile Sales",
            "type":"Retail Goods"
        }
    ],
    "sg:phone":"+61 412 707 636",
    "sg:postcode":"7250",
    "sg:province":"TAS",
    "sg:tags":[
        "equipment",
        "trailer"
    ],
    "wof:name":"B.S.C. Truck & Bus Parts",
    "wof:placetype":"venue"
},
  "geometry": {"coordinates":[147.13926696799999,-41.4683914185],"type":"Point"}
}