{
  "type": "Feature",
  "properties": {
    "iso:country":"AU",
    "sg:address":"10 Joel Drv",
    "sg:city":"Old Bar",
    "sg:classifiers":[
        {
            "category":"Professional",
            "subcategory":"Computer Services",
            "type":"Services"
        }
    ],
    "sg:phone":"+61 2 6557 4442",
    "sg:postcode":"2430",
    "sg:province":"NSW",
    "sg:tags":[
        "repairs",
        "upgrade",
        "equipment"
    ],
    "wof:name":"Three D Info Tech",
    "wof:placetype":"venue"
},
  "geometry": {"coordinates":[152.583786,-31.970261],"type":"Point"}
}