{
  "type": "Feature",
  "properties": {
    "iso:country":"AU",
    "sg:address":"64- 68 Shepherd St",
    "sg:city":"Marrickville",
    "sg:classifiers":[
        {
            "category":"Social Services",
            "subcategory":"Retirement Home",
            "type":"Services"
        }
    ],
    "sg:phone":"+61 2 9572 5222",
    "sg:postcode":"2204",
    "sg:province":"NSW",
    "sg:tags":[
        "t-shirt",
        "supplier"
    ],
    "wof:name":"Hyper-Active Merchandising",
    "wof:placetype":"venue"
},
  "geometry": {"coordinates":[151.162552,-33.904987],"type":"Point"}
}