{
  "type": "Feature",
  "properties": {
    "addr:full":"Bunbury City Plaza Cnr Spencer St & Forrest Ave Bunbury WA 6230",
    "addr:postcode":"6230",
    "addr:street":"Cnr Spencer St & Forrest Ave",
    "iso:country":"AU",
    "sg:address":"Bunbury City Plaza Cnr Spencer St & Forrest Ave",
    "sg:city":"Bunbury",
    "sg:classifiers":[
        {
            "category":"Shopping",
            "subcategory":"Bicycles & Sporting Goods",
            "type":"Retail Goods"
        }
    ],
    "sg:phone":"+61 8 9792 5505",
    "sg:postcode":"6230",
    "sg:province":"WA",
    "sg:tags":[
        "dance",
        "accessory",
        "wear",
        "supply"
    ],
    "wof:name":"Stepping Out",
    "wof:placetype":"venue"
},
  "geometry": {"coordinates":[115.64167,-33.352669],"type":"Point"}
}