{
  "type": "Feature",
  "properties": {
    "addr:full":"14 Wandarri Rd Kenthurst NSW 2156",
    "addr:housenumber":"14",
    "addr:postcode":"2156",
    "addr:street":"Wandarri Rd",
    "iso:country":"AU",
    "sg:address":"14 Wandarri Rd",
    "sg:city":"Kenthurst",
    "sg:classifiers":[
        {
            "category":"Farming",
            "subcategory":"Nursery",
            "type":"Manufacturing & Wholesale Goods"
        }
    ],
    "sg:phone":"+61 415 379 276",
    "sg:postcode":"2156",
    "sg:province":"NSW",
    "wof:name":"House of Hedges",
    "wof:placetype":"venue"
},
  "geometry": {"coordinates":[150.988677978,-33.6506958008],"type":"Point"}
}