{
  "type": "Feature",
  "properties": {
    "iso:country":"AU",
    "sg:address":"23 Roberts Ave",
    "sg:city":"Horsham",
    "sg:classifiers":[
        {
            "category":"Education",
            "subcategory":"Kindergarten",
            "type":"Public Place"
        }
    ],
    "sg:phone":"+61 3 5382 3027",
    "sg:postcode":"3400",
    "sg:province":"VIC",
    "sg:tags":[
        "pre-schools"
    ],
    "wof:name":"Roberts Ave Kindergarten",
    "wof:placetype":"venue"
},
  "geometry": {"coordinates":[142.20123290999999,-36.7143783569],"type":"Point"}
}