{
  "type": "Feature",
  "properties": {
    "addr:full":"5 Elizabeth Cook Drv Rankin Park NSW 2287",
    "addr:housenumber":"5",
    "addr:postcode":"2287",
    "addr:street":"Elizabeth Cook Drv Rankin",
    "iso:country":"AU",
    "sg:address":"5 Elizabeth Cook Drv",
    "sg:city":"Rankin Park",
    "sg:classifiers":[
        {
            "category":"Farming",
            "subcategory":"Fish & Marine Products",
            "type":"Manufacturing & Wholesale Goods"
        }
    ],
    "sg:phone":"+61 2 4952 4525",
    "sg:postcode":"2287",
    "sg:province":"NSW",
    "sg:tags":[
        "supplier",
        "oyster",
        "farmer"
    ],
    "wof:name":"Col Hoade",
    "wof:placetype":"venue"
},
  "geometry": {"coordinates":[151.67814636200001,-32.9251976013],"type":"Point"}
}