{
  "type": "Feature",
  "properties": {
    "addr:full":"9 Vennard St Garbutt QLD 4814",
    "addr:housenumber":"9",
    "addr:postcode":"4814",
    "addr:street":"Vennard St",
    "iso:country":"AU",
    "sg:address":"9 Vennard St",
    "sg:city":"Garbutt",
    "sg:classifiers":[
        {
            "category":"Building & Trades",
            "subcategory":"Construction",
            "type":"Services"
        }
    ],
    "sg:phone":"+61 7 4779 1144",
    "sg:postcode":"4814",
    "sg:province":"QLD",
    "sg:tags":[
        "joinery"
    ],
    "wof:name":"Reeves F H",
    "wof:placetype":"venue"
},
  "geometry": {"coordinates":[146.75512699999999,-19.26989],"type":"Point"}
}