{
  "type": "Feature",
  "properties": {
    "addr:full":"65 Kalang Rd Elanora Heights NSW 2101",
    "addr:housenumber":"65",
    "addr:postcode":"2101",
    "addr:street":"Kalang Rd",
    "iso:country":"AU",
    "sg:address":"65 Kalang Rd",
    "sg:city":"Elanora Heights",
    "sg:classifiers":[
        {
            "category":"Personal",
            "subcategory":"Beauty Salon",
            "type":"Services"
        }
    ],
    "sg:phone":"+61 2 9913 1610",
    "sg:postcode":"2101",
    "sg:province":"NSW",
    "sg:tags":[
        "hairdresser"
    ],
    "wof:name":"F M B Hair & Makeup Studio",
    "wof:placetype":"venue"
},
  "geometry": {"coordinates":[151.280136,-33.695774],"type":"Point"}
}