{
  "type": "Feature",
  "properties": {
    "addr:full":"94 Cobalt St Carole Park QLD 4300",
    "addr:housenumber":"94",
    "addr:postcode":"4300",
    "addr:street":"Cobalt St",
    "iso:country":"AU",
    "sg:address":"94 Cobalt St",
    "sg:city":"Carole Park",
    "sg:classifiers":[
        {
            "category":"Manufacturing",
            "subcategory":"Metals",
            "type":"Manufacturing & Wholesale Goods"
        }
    ],
    "sg:phone":"+61 7 3271 1066",
    "sg:postcode":"4300",
    "sg:province":"QLD",
    "sg:tags":[
        "sheet",
        "worker"
    ],
    "wof:name":"Galvin Engineering Pty Ltd",
    "wof:placetype":"venue"
},
  "geometry": {"coordinates":[152.93663024899999,-27.6227474213],"type":"Point"}
}