{
  "type": "Feature",
  "properties": {
    "iso:country":"AU",
    "sg:address":"347 Settlement Rd",
    "sg:city":"Thomastown",
    "sg:classifiers":[
        {
            "category":"Communications",
            "type":"Services"
        }
    ],
    "sg:phone":"+61 3 9465 9399",
    "sg:postcode":"3074",
    "sg:province":"VIC",
    "sg:tags":[
        "equipment",
        "radio"
    ],
    "wof:name":"JNB Electronics",
    "wof:placetype":"venue"
},
  "geometry": {"coordinates":[145.02090454099999,-37.6888504028],"type":"Point"}
}