{
  "type": "Feature",
  "properties": {
    "iso:country":"AU",
    "sg:address":"Unit 8 605 Kingsford Smith Drv",
    "sg:city":"Hamilton",
    "sg:classifiers":[
        {
            "category":"Banks & Credit Unions",
            "subcategory":"Bank",
            "type":"Services"
        }
    ],
    "sg:phone":"+61 7 3868 3090",
    "sg:postcode":"4007",
    "sg:province":"QLD",
    "sg:tags":[
        "equipment",
        "sale",
        "point"
    ],
    "wof:name":"Goodson Imports Pty Ltd",
    "wof:placetype":"venue"
},
  "geometry": {"coordinates":[153.075653,-27.435644],"type":"Point"}
}