{
  "type": "Feature",
  "properties": {
    "addr:full":"21 Richardson St Edge Hill QLD 4870",
    "addr:housenumber":"21",
    "addr:postcode":"4870",
    "addr:street":"Richardson St",
    "iso:country":"AU",
    "sg:address":"21 Richardson St",
    "sg:city":"Edge Hill",
    "sg:classifiers":[
        {
            "category":"Building & Trades",
            "subcategory":"Construction",
            "type":"Services"
        }
    ],
    "sg:phone":"+61 412 965 962",
    "sg:postcode":"4870",
    "sg:province":"QLD",
    "sg:tags":[
        "contractor"
    ],
    "wof:name":"Doug James Carpentry",
    "wof:placetype":"venue"
},
  "geometry": {"coordinates":[145.73968505900001,-16.9058895111],"type":"Point"}
}