{
  "type": "Feature",
  "properties": {
    "iso:country":"AU",
    "sg:address":"3 Kauri Pl",
    "sg:city":"Whittlesea",
    "sg:classifiers":[
        {
            "category":"Building & Trades",
            "subcategory":"Construction",
            "type":"Services"
        }
    ],
    "sg:phone":"+61 419 598 506",
    "sg:postcode":"3757",
    "sg:province":"VIC",
    "sg:tags":[
        "installation",
        "air conditioning"
    ],
    "wof:name":"Epping Heating & Cooling",
    "wof:placetype":"venue"
},
  "geometry": {"coordinates":[145.11189300000001,-37.50639],"type":"Point"}
}