{
  "type": "Feature",
  "properties": {
    "iso:country":"AU",
    "sg:address":"Unit 2 / 45 Tradelink Rd",
    "sg:city":"Hillcrest",
    "sg:classifiers":[
        {
            "category":"Manufacturing",
            "subcategory":"Furniture",
            "type":"Manufacturing & Wholesale Goods"
        }
    ],
    "sg:phone":"+61 7 3800 6288",
    "sg:postcode":"4118",
    "sg:province":"QLD",
    "sg:tags":[
        "builder",
        "designer",
        "custom"
    ],
    "wof:name":"Silkwood Furniture Designs",
    "wof:placetype":"venue"
},
  "geometry": {"coordinates":[153.0340271,-27.6648159027],"type":"Point"}
}