{
  "type": "Feature",
  "properties": {
    "iso:country":"AU",
    "sg:address":"41 Fairfield Forum St",
    "sg:city":"Fairfield",
    "sg:classifiers":[
        {
            "category":"Deli",
            "type":"Food & Drink"
        }
    ],
    "sg:phone":"+61 2 9755 0580",
    "sg:postcode":"2165",
    "sg:province":"NSW",
    "sg:tags":[
        "delicatessen"
    ],
    "wof:name":"Cut Price Deli",
    "wof:placetype":"venue"
},
  "geometry": {"coordinates":[150.971893311,-33.8685150146],"type":"Point"}
}