{
  "type": "Feature",
  "properties": {
    "addr:full":"1 Tea Tree Ave Currumbin QLD 4223",
    "addr:housenumber":"1",
    "addr:postcode":"4223",
    "addr:street":"Tea Tree Ave",
    "iso:country":"AU",
    "sg:address":"1 Tea Tree Ave",
    "sg:city":"Currumbin",
    "sg:classifiers":[
        {
            "category":"Professional",
            "subcategory":"Detective & Security Services",
            "type":"Services"
        }
    ],
    "sg:phone":"+61 411 691 930",
    "sg:postcode":"4223",
    "sg:province":"QLD",
    "sg:tags":[
        "equipment",
        "window",
        "doors"
    ],
    "wof:name":"Anderson, Gordon",
    "wof:placetype":"venue"
},
  "geometry": {"coordinates":[153.47201538100001,-28.1451377869],"type":"Point"}
}