{
  "type": "Feature",
  "properties": {
    "addr:full":"6 Stereo Pde Mt Eliza VIC 3930",
    "addr:housenumber":"6",
    "addr:postcode":"3930",
    "addr:street":"Stereo Pde",
    "iso:country":"AU",
    "sg:address":"6 Stereo Pde",
    "sg:city":"Mt Eliza",
    "sg:classifiers":[
        {
            "category":"Building & Trades",
            "subcategory":"Landscaping Services",
            "type":"Services"
        }
    ],
    "sg:phone":"+61 3 9775 4880",
    "sg:postcode":"3930",
    "sg:province":"VIC",
    "sg:tags":[
        "consultant"
    ],
    "wof:name":"B R Jackson Holdings Pty Ltd",
    "wof:placetype":"venue"
},
  "geometry": {"coordinates":[145.073562622,-38.1861457825],"type":"Point"}
}