{
  "type": "Feature",
  "properties": {
    "iso:country":"AU",
    "sg:address":"117 Waterdale Rd",
    "sg:city":"Ivanhoe",
    "sg:classifiers":[
        {
            "category":"Health Services",
            "subcategory":"Doctor",
            "type":"Services"
        }
    ],
    "sg:phone":"+61 3 8508 9000",
    "sg:postcode":"3079",
    "sg:province":"VIC",
    "sg:tags":[
        "medical",
        "practitioner"
    ],
    "wof:name":"Lucas J P",
    "wof:placetype":"venue"
},
  "geometry": {"coordinates":[145.04328918499999,-37.7668113708],"type":"Point"}
}