{
  "type": "Feature",
  "properties": {
    "addr:full":"Factory 1/ 20 Lanyon St Dandenong VIC 3175",
    "addr:housenumber":"/ 20",
    "addr:postcode":"3175",
    "addr:street":"Lanyon St",
    "iso:country":"AU",
    "sg:address":"Factory 1/ 20 Lanyon St",
    "sg:city":"Dandenong",
    "sg:classifiers":[
        {
            "category":"Retail",
            "subcategory":"Auto Repair",
            "type":"Services"
        }
    ],
    "sg:phone":"+61 3 9791 9239",
    "sg:postcode":"3175",
    "sg:province":"VIC",
    "sg:tags":[
        "sport",
        "motor"
    ],
    "wof:name":"Top Notch Racecars",
    "wof:placetype":"venue"
},
  "geometry": {"coordinates":[145.22129821799999,-38.018573761],"type":"Point"}
}