{
  "type": "Feature",
  "properties": {
    "iso:country":"AU",
    "sg:address":"15 Eastern Beach Rd",
    "sg:city":"Geelong",
    "sg:classifiers":[
        {
            "category":"Retail",
            "subcategory":"Event Space",
            "type":"Services"
        }
    ],
    "sg:phone":"+61 3 5229 3110",
    "sg:postcode":"3220",
    "sg:province":"VIC",
    "sg:tags":[
        "venue",
        "reception",
        "wedding"
    ],
    "wof:name":"Le Parisien",
    "wof:placetype":"venue"
},
  "geometry": {"coordinates":[144.364059,-38.144737],"type":"Point"}
}