{
  "type": "Feature",
  "properties": {
    "addr:full":"Winthrop Ave Crawley WA 6009",
    "addr:postcode":"6009",
    "addr:street":"Winthrop Ave",
    "iso:country":"AU",
    "sg:address":"Winthrop Ave",
    "sg:city":"Crawley",
    "sg:classifiers":[
        {
            "category":"Government",
            "subcategory":"City Hall",
            "type":"Public Place"
        }
    ],
    "sg:phone":"+61 8 9273 3203",
    "sg:postcode":"6009",
    "sg:province":"WA",
    "wof:name":"Currie Hall",
    "wof:placetype":"venue"
},
  "geometry": {"coordinates":[115.818039,-31.975601],"type":"Point"}
}