{
  "type": "Feature",
  "properties": {
    "iso:country":"AU",
    "sg:address":"1 Mersey Main Rd",
    "sg:city":"Spreyton",
    "sg:classifiers":[
        {
            "category":"Education",
            "subcategory":"School",
            "type":"Public Place"
        }
    ],
    "sg:phone":"+61 3 6427 2075",
    "sg:postcode":"7310",
    "sg:province":"TAS",
    "sg:tags":[
        "state",
        "except",
        "nsw"
    ],
    "wof:name":"Spreyton Primary School",
    "wof:placetype":"venue"
},
  "geometry": {"coordinates":[146.34417724599999,-41.2111778259],"type":"Point"}
}