{
  "type": "Feature",
  "properties": {
    "addr:full":"14- 18 Research Drv Croydon South VIC 3136",
    "addr:housenumber":"18",
    "addr:postcode":"3136",
    "addr:street":"Research Drv",
    "iso:country":"AU",
    "sg:address":"14- 18 Research Drv",
    "sg:city":"Croydon South",
    "sg:classifiers":[
        {
            "category":"Home & Garden",
            "subcategory":"Household Appliances",
            "type":"Retail Goods"
        }
    ],
    "sg:phone":"+61 3 9761 6466",
    "sg:postcode":"3136",
    "sg:province":"VIC",
    "sg:tags":[
        "heating",
        "system"
    ],
    "wof:name":"Heat Charm",
    "wof:placetype":"venue"
},
  "geometry": {"coordinates":[145.29017639200001,-37.8172683716],"type":"Point"}
}