{
  "type": "Feature",
  "properties": {
    "addr:full":"77 Bassett St Mona Vale NSW 2103",
    "addr:housenumber":"77",
    "addr:postcode":"2103",
    "addr:street":"Bassett St",
    "iso:country":"AU",
    "sg:address":"77 Bassett St",
    "sg:city":"Mona Vale",
    "sg:classifiers":[
        {
            "category":"Autos & Motor Vehicles",
            "subcategory":"Boat Sales",
            "type":"Retail Goods"
        }
    ],
    "sg:phone":"+61 2 9997 7722",
    "sg:postcode":"2103",
    "sg:province":"NSW",
    "sg:tags":[
        "builder",
        "yacht",
        "repairer"
    ],
    "wof:name":"McConaghy Boats",
    "wof:placetype":"venue"
},
  "geometry": {"coordinates":[151.306930542,-33.6717758179],"type":"Point"}
}