{
  "type": "Feature",
  "properties": {
    "addr:full":"PO Box 773 Ryde Private Boxes NSW 1680",
    "addr:postcode":"1680",
    "addr:street":"Ryde",
    "iso:country":"AU",
    "sg:address":"PO Box 773",
    "sg:city":"Ryde Private Boxes",
    "sg:classifiers":[
        {
            "category":"Professional",
            "subcategory":"Detective & Security Services",
            "type":"Services"
        }
    ],
    "sg:phone":"+61 1300 655 009",
    "sg:postcode":"1680",
    "sg:province":"NSW",
    "sg:tags":[
        "consultant",
        "system"
    ],
    "wof:name":"Central Monitoring Services Pty Ltd",
    "wof:placetype":"venue"
},
  "geometry": {"coordinates":[151.104934692,-33.8129501343],"type":"Point"}
}