{
  "type": "Feature",
  "properties": {
    "addr:full":"U11/ 41 Holder Way Malaga WA 6090",
    "addr:postcode":"6090",
    "addr:street":"/ 41 Holder Way",
    "iso:country":"AU",
    "sg:address":"U11/ 41 Holder Way",
    "sg:city":"Malaga",
    "sg:classifiers":[
        {
            "category":"Retail",
            "subcategory":"Auto Repair",
            "type":"Services"
        }
    ],
    "sg:phone":"+61 8 9248 1444",
    "sg:postcode":"6090",
    "sg:province":"WA",
    "sg:tags":[
        "repairer",
        "motor",
        "engineer"
    ],
    "wof:name":"Autocare Malaga",
    "wof:placetype":"venue"
},
  "geometry": {"coordinates":[115.893203735,-31.8585243225],"type":"Point"}
}