{
  "type": "Feature",
  "properties": {
    "iso:country":"AU",
    "sg:address":"81 Racecourse Rd",
    "sg:city":"Hamilton",
    "sg:classifiers":[
        {
            "category":"Shopping",
            "subcategory":"Clothing, Apparel, & Fashions",
            "type":"Retail Goods"
        }
    ],
    "sg:phone":"+61 7 3268 4913",
    "sg:postcode":"4007",
    "sg:province":"QLD",
    "sg:tags":[
        "boutique"
    ],
    "wof:name":"Flash Boutique",
    "wof:placetype":"venue"
},
  "geometry": {"coordinates":[153.065048,-27.435558],"type":"Point"}
}