{
  "type": "Feature",
  "properties": {
    "iso:country":"AU",
    "sg:address":"19 George St",
    "sg:city":"Parramatta",
    "sg:classifiers":[
        {
            "category":"Travel",
            "subcategory":"Hotels & Motels",
            "type":"Entertainment"
        }
    ],
    "sg:phone":"+61 2 9635 8043",
    "sg:postcode":"2150",
    "sg:province":"NSW",
    "sg:tags":[
        "accommodation"
    ],
    "wof:name":"WoolpacK Hotel",
    "wof:placetype":"venue"
},
  "geometry": {"coordinates":[151.01731872600001,-33.8339653015],"type":"Point"}
}