{
  "type": "Feature",
  "properties": {
    "iso:country":"AU",
    "sg:address":"1 Dale St",
    "sg:city":"Fairfield",
    "sg:classifiers":[
        {
            "category":"Health Services",
            "subcategory":"Doctor",
            "type":"Services"
        }
    ],
    "sg:phone":"+61 2 9727 4274",
    "sg:postcode":"2165",
    "sg:province":"NSW",
    "sg:tags":[
        "medical",
        "practitioner"
    ],
    "wof:name":"Singh David",
    "wof:placetype":"venue"
},
  "geometry": {"coordinates":[150.958251953,-33.8722457886],"type":"Point"}
}