{
  "type": "Feature",
  "properties": {
    "addr:full":"38 Borilla St Emerald QLD 4720",
    "addr:housenumber":"38",
    "addr:postcode":"4720",
    "addr:street":"Borilla St",
    "iso:country":"AU",
    "sg:address":"38 Borilla St",
    "sg:city":"Emerald",
    "sg:classifiers":[
        {
            "category":"Autos & Motor Vehicles",
            "subcategory":"Automobile Sales",
            "type":"Retail Goods"
        }
    ],
    "sg:phone":"+61 7 4987 9999",
    "sg:postcode":"4720",
    "sg:province":"QLD",
    "sg:tags":[
        "car",
        "new"
    ],
    "wof:name":"Reef City Ford",
    "wof:placetype":"venue"
},
  "geometry": {"coordinates":[148.16189600000001,-23.525557],"type":"Point"}
}