{
  "type": "Feature",
  "properties": {
    "iso:country":"AU",
    "sg:address":"38 Borilla St",
    "sg:city":"Emerald",
    "sg:classifiers":[
        {
            "category":"Autos & Motor Vehicles",
            "subcategory":"Automobile Sales",
            "type":"Retail Goods"
        }
    ],
    "sg:phone":"+61 7 4987 9999",
    "sg:postcode":"4720",
    "sg:province":"QLD",
    "sg:tags":[
        "car",
        "new"
    ],
    "wof:name":"Reef City Ford",
    "wof:placetype":"venue"
},
  "geometry": {"coordinates":[148.161896,-23.525557],"type":"Point"}
}