{
  "type": "Feature",
  "properties": {
    "addr:full":"44 North Rd Newport VIC 3015",
    "addr:housenumber":"44",
    "addr:postcode":"3015",
    "addr:street":"North Rd",
    "iso:country":"AU",
    "sg:address":"44 North Rd",
    "sg:city":"Newport",
    "sg:classifiers":[
        {
            "category":"Professional",
            "subcategory":"Engineering",
            "type":"Services"
        }
    ],
    "sg:phone":"+61 3 9398 0067",
    "sg:postcode":"3015",
    "sg:province":"VIC",
    "sg:tags":[
        "consulting",
        "engineer"
    ],
    "wof:name":"Wilson D & Associates Pty Ltd",
    "wof:placetype":"venue"
},
  "geometry": {"coordinates":[144.890869141,-37.8447914124],"type":"Point"}
}