{
  "type": "Feature",
  "properties": {
    "addr:full":"Five Bough Rd Leeton NSW 2705",
    "addr:postcode":"2705",
    "addr:street":"Five Bough Rd",
    "iso:country":"AU",
    "sg:address":"Five Bough Rd",
    "sg:city":"Leeton",
    "sg:classifiers":[
        {
            "category":"Wholesale",
            "subcategory":"Furniture",
            "type":"Manufacturing & Wholesale Goods"
        }
    ],
    "sg:phone":"+61 2 6953 3419",
    "sg:postcode":"2705",
    "sg:province":"NSW",
    "sg:tags":[
        "wholesaler",
        "mfrs"
    ],
    "wof:name":"Warren G Bradley",
    "wof:placetype":"venue"
},
  "geometry": {"coordinates":[146.40620422399999,-34.5520401001],"type":"Point"}
}