{
  "type": "Feature",
  "properties": {
    "addr:full":"Unit 3/ 2 Mill Rd Campbelltown NSW 2560",
    "addr:housenumber":"2",
    "addr:postcode":"2560",
    "addr:street":"Mill Rd",
    "iso:country":"AU",
    "sg:address":"Unit 3/ 2 Mill Rd",
    "sg:city":"Campbelltown",
    "sg:classifiers":[
        {
            "category":"Home & Garden",
            "subcategory":"Carpets & Floor Coverings",
            "type":"Retail Goods"
        }
    ],
    "sg:phone":"+61 2 4626 7455",
    "sg:postcode":"2560",
    "sg:province":"NSW",
    "sg:tags":[
        "tile",
        "wall"
    ],
    "wof:name":"Campbelltown Slate & Stone",
    "wof:placetype":"venue"
},
  "geometry": {"coordinates":[150.82351684599999,-34.0510559082],"type":"Point"}
}