{
  "type": "Feature",
  "properties": {
    "iso:country":"AU",
    "sg:address":"7 Warrain Ave",
    "sg:city":"Rosebud",
    "sg:classifiers":[
        {
            "category":"Building & Trades",
            "subcategory":"Construction",
            "type":"Services"
        }
    ],
    "sg:phone":"+61 409 215 745",
    "sg:postcode":"3939",
    "sg:province":"VIC",
    "sg:tags":[
        "earth",
        "excavating",
        "moving",
        "contractor"
    ],
    "wof:name":"John P Kirby Excavations",
    "wof:placetype":"venue"
},
  "geometry": {"coordinates":[144.93089294399999,-38.3795051575],"type":"Point"}
}