{
  "type": "Feature",
  "properties": {
    "addr:full":"2/ 216 Queens St St Marys NSW 2760",
    "addr:housenumber":"/ 216",
    "addr:postcode":"2760",
    "addr:street":"Queens St",
    "iso:country":"AU",
    "sg:address":"2/ 216 Queens St St",
    "sg:city":"Marys",
    "sg:classifiers":[
        {
            "category":"Banks & Credit Unions",
            "subcategory":"Financial Services",
            "type":"Services"
        }
    ],
    "sg:phone":"+61 1300 781 863",
    "sg:postcode":"2760",
    "sg:province":"NSW",
    "sg:tags":[
        "loan",
        "finance",
        "mortgage"
    ],
    "wof:name":"Home Loans Made Easy",
    "wof:placetype":"venue"
},
  "geometry": {"coordinates":[150.77377319300001,-33.768913269],"type":"Point"}
}