{
  "type": "Feature",
  "properties": {
    "addr:full":"1 Maroondah Hwy Ringwood VIC 3134",
    "addr:housenumber":"1",
    "addr:postcode":"3134",
    "addr:street":"Maroondah Hwy",
    "iso:country":"AU",
    "sg:address":"1 Maroondah Hwy",
    "sg:city":"Ringwood",
    "sg:classifiers":[
        {
            "category":"Building & Trades",
            "subcategory":"Landscaping Services",
            "type":"Services"
        }
    ],
    "sg:phone":"+61 3 9883 5656",
    "sg:postcode":"3134",
    "sg:province":"VIC",
    "sg:tags":[
        "stump",
        "tree",
        "felling",
        "removal"
    ],
    "wof:name":"Oakfern Tree Care Pty Ltd",
    "wof:placetype":"venue"
},
  "geometry": {"coordinates":[145.213653564,-37.8170661926],"type":"Point"}
}