{
  "type": "Feature",
  "properties": {
    "addr:full":"301 Wanneroo Rd Balcatta WA 6021",
    "addr:housenumber":"301",
    "addr:postcode":"6021",
    "addr:street":"Wanneroo Rd",
    "iso:country":"AU",
    "sg:address":"301 Wanneroo Rd",
    "sg:city":"Balcatta",
    "sg:classifiers":[
        {
            "category":"Health Services",
            "subcategory":"Medical Lab",
            "type":"Services"
        }
    ],
    "sg:phone":"+61 8 9344 6071",
    "sg:postcode":"6021",
    "sg:province":"WA",
    "sg:tags":[
        "laboratory",
        "dental"
    ],
    "wof:name":"Parrish Dental Lab",
    "wof:placetype":"venue"
},
  "geometry": {"coordinates":[115.834373474,-31.8809242249],"type":"Point"}
}