{
  "type": "Feature",
  "properties": {
    "addr:full":"346 Ferntree Gully Rd Notting Hill VIC 3168",
    "addr:housenumber":"346",
    "addr:postcode":"3168",
    "addr:street":"Ferntree Gully Rd",
    "iso:country":"AU",
    "sg:address":"346 Ferntree Gully Rd",
    "sg:city":"Notting Hill",
    "sg:classifiers":[
        {
            "category":"Professional",
            "subcategory":"Printing & Photocopies",
            "type":"Services"
        }
    ],
    "sg:phone":"+61 3 9543 8122",
    "sg:postcode":"3168",
    "sg:province":"VIC",
    "sg:tags":[
        "photocopying"
    ],
    "wof:name":"Snap Printing",
    "wof:placetype":"venue"
},
  "geometry": {"coordinates":[145.137817383,-37.9007415771],"type":"Point"}
}