{
  "type": "Feature",
  "properties": {
    "addr:full":"1/ 89 Winton Rd Joondalup WA 6027",
    "addr:housenumber":"/ 89",
    "addr:postcode":"6027",
    "addr:street":"Winton Rd",
    "iso:country":"AU",
    "sg:address":"1/ 89 Winton Rd",
    "sg:city":"Joondalup",
    "sg:classifiers":[
        {
            "category":"Real Estate",
            "subcategory":"Real Estate Agent",
            "type":"Services"
        }
    ],
    "sg:phone":"+61 8 9300 2055",
    "sg:postcode":"6027",
    "sg:province":"WA",
    "wof:name":"First National Real Estate Network",
    "wof:placetype":"venue"
},
  "geometry": {"coordinates":[115.75968170199999,-31.7442913055],"type":"Point"}
}