{
  "type": "Feature",
  "properties": {
    "addr:full":"1 Meagher St Chippendale NSW 2008",
    "addr:housenumber":"1",
    "addr:postcode":"2008",
    "addr:street":"Meagher St",
    "iso:country":"AU",
    "sg:address":"1 Meagher St",
    "sg:city":"Chippendale",
    "sg:classifiers":[
        {
            "category":"Travel",
            "subcategory":"Hotels & Motels",
            "type":"Entertainment"
        }
    ],
    "sg:phone":"+61 2 9319 4133",
    "sg:postcode":"2008",
    "sg:province":"NSW",
    "sg:tags":[
        "accommodation"
    ],
    "wof:name":"Metro Inns",
    "wof:placetype":"venue"
},
  "geometry": {"coordinates":[151.19921875,-33.8875160217],"type":"Point"}
}