{
  "type": "Feature",
  "properties": {
    "addr:full":"2/ 33 Rowe St Eastwood NSW 2122",
    "addr:housenumber":"/ 33",
    "addr:postcode":"2122",
    "addr:street":"Rowe St",
    "iso:country":"AU",
    "sg:address":"2/ 33 Rowe St",
    "sg:city":"Eastwood",
    "sg:classifiers":[
        {
            "category":"Health Services",
            "subcategory":"Doctor",
            "type":"Services"
        }
    ],
    "sg:phone":"+61 2 9874 8306",
    "sg:postcode":"2122",
    "sg:province":"NSW",
    "sg:tags":[
        "medical",
        "practitioner"
    ],
    "wof:name":"Shin B J",
    "wof:placetype":"venue"
},
  "geometry": {"coordinates":[151.08497619600001,-33.7906303406],"type":"Point"}
}