{
  "type": "Feature",
  "properties": {
    "addr:full":"57b Smythe St Rockingham WA 6168",
    "addr:housenumber":"57b",
    "addr:postcode":"6168",
    "addr:street":"Smythe St",
    "iso:country":"AU",
    "sg:address":"57b Smythe St",
    "sg:city":"Rockingham",
    "sg:classifiers":[
        {
            "category":"Government",
            "subcategory":"Court House",
            "type":"Public Place"
        }
    ],
    "sg:phone":"+61 8 9592 7489",
    "sg:postcode":"6168",
    "sg:province":"WA",
    "sg:tags":[
        "personal",
        "marriage",
        "family",
        "counselling"
    ],
    "wof:name":"Palm Beach Counselling & Natural Healing Services",
    "wof:placetype":"venue"
},
  "geometry": {"coordinates":[115.736237,-32.275665],"type":"Point"}
}