{
  "type": "Feature",
  "properties": {
    "addr:full":"41 George St Launceston TAS 7250",
    "addr:housenumber":"41",
    "addr:postcode":"7250",
    "addr:street":"George St",
    "iso:country":"AU",
    "sg:address":"41 George St",
    "sg:city":"Launceston",
    "sg:classifiers":[
        {
            "category":"Cafe",
            "type":"Food & Drink"
        }
    ],
    "sg:phone":"+61 3 6334 3488",
    "sg:postcode":"7250",
    "sg:province":"TAS",
    "wof:name":"Rossilli Cafe",
    "wof:placetype":"venue"
},
  "geometry": {"coordinates":[147.139602661,-41.4349708557],"type":"Point"}
}