{
  "type": "Feature",
  "properties": {
    "addr:full":"68 Noble Ave Greenacre NSW 2190",
    "addr:housenumber":"68",
    "addr:postcode":"2190",
    "addr:street":"Noble Ave",
    "iso:country":"AU",
    "sg:address":"68 Noble Ave",
    "sg:city":"Greenacre",
    "sg:classifiers":[
        {
            "category":"Food & Beverages",
            "subcategory":"Groceries & Convenience Stores",
            "type":"Retail Goods"
        }
    ],
    "sg:phone":"+61 2 9707 3406",
    "sg:postcode":"2190",
    "sg:province":"NSW",
    "wof:name":"Greenacre Mixed Business",
    "wof:placetype":"venue"
},
  "geometry": {"coordinates":[151.051254,-33.911831],"type":"Point"}
}