{
  "type": "Feature",
  "properties": {
    "addr:full":"2 Alfred St Dubbo NSW 2830",
    "addr:housenumber":"2",
    "addr:postcode":"2830",
    "addr:street":"Alfred St",
    "iso:country":"AU",
    "sg:address":"2 Alfred St",
    "sg:city":"Dubbo",
    "sg:classifiers":[
        {
            "category":"Travel",
            "subcategory":"Hostel",
            "type":"Entertainment"
        }
    ],
    "sg:phone":"+61 2 6882 5254",
    "sg:postcode":"2830",
    "sg:province":"NSW",
    "sg:tags":[
        "home"
    ],
    "wof:name":"Dubbo Youth Refuge",
    "wof:placetype":"venue"
},
  "geometry": {"coordinates":[148.59602355999999,-32.2472229004],"type":"Point"}
}