{
  "type": "Feature",
  "properties": {
    "addr:full":"34 Edward St Kingaroy QLD 4610",
    "addr:housenumber":"34",
    "addr:postcode":"4610",
    "addr:street":"Edward St",
    "iso:country":"AU",
    "sg:address":"34 Edward St",
    "sg:city":"Kingaroy",
    "sg:classifiers":[
        {
            "category":"Building & Trades",
            "subcategory":"Construction",
            "type":"Services"
        }
    ],
    "sg:phone":"+61 7 4162 4734",
    "sg:postcode":"4610",
    "sg:province":"QLD",
    "sg:tags":[
        "renovation",
        "alterations",
        "extension",
        "contractor"
    ],
    "wof:name":"Steve Hart Builder",
    "wof:placetype":"venue"
},
  "geometry": {"coordinates":[151.83917236299999,-26.5359344482],"type":"Point"}
}