{
  "type": "Feature",
  "properties": {
    "addr:full":"631 Waterdale Rd Heidelberg West VIC 3081",
    "addr:housenumber":"631",
    "addr:postcode":"3081",
    "addr:street":"Waterdale Rd",
    "iso:country":"AU",
    "sg:address":"631 Waterdale Rd",
    "sg:city":"Heidelberg West",
    "sg:classifiers":[
        {
            "category":"Communications",
            "type":"Services"
        }
    ],
    "sg:phone":"+61 3 9499 2186",
    "sg:postcode":"3081",
    "sg:province":"VIC",
    "sg:tags":[
        "public",
        "system",
        "address"
    ],
    "wof:name":"Fawcett Sound Systems",
    "wof:placetype":"venue"
},
  "geometry": {"coordinates":[145.049102783,-37.7337646484],"type":"Point"}
}