{
  "type": "Feature",
  "properties": {
    "addr:full":"33 Woodland St Essendon VIC 3040",
    "addr:housenumber":"33",
    "addr:postcode":"3040",
    "addr:street":"Woodland St",
    "iso:country":"AU",
    "sg:address":"33 Woodland St",
    "sg:city":"Essendon",
    "sg:classifiers":[
        {
            "category":"Personal",
            "subcategory":"Beauty Salon",
            "type":"Services"
        }
    ],
    "sg:phone":"+61 3 9379 9053",
    "sg:postcode":"3040",
    "sg:province":"VIC",
    "sg:tags":[
        "hairdresser"
    ],
    "wof:name":"Crew 33 Hairdesigners",
    "wof:placetype":"venue"
},
  "geometry": {"coordinates":[144.925689697,-37.743309021],"type":"Point"}
}