{
  "type": "Feature",
  "properties": {
    "addr:full":"141 Ibis St Longreach QLD 4730",
    "addr:housenumber":"141",
    "addr:postcode":"4730",
    "addr:street":"Ibis St",
    "iso:country":"AU",
    "sg:address":"141 Ibis St",
    "sg:city":"Longreach",
    "sg:classifiers":[
        {
            "category":"Shopping",
            "subcategory":"Computers & Home Electronics",
            "type":"Retail Goods"
        }
    ],
    "sg:phone":"+61 7 4658 0500",
    "sg:postcode":"4730",
    "sg:province":"QLD",
    "sg:tags":[
        "global",
        "positioning",
        "system"
    ],
    "wof:name":"Access Electronics",
    "wof:placetype":"venue"
},
  "geometry": {"coordinates":[144.24411000000001,-23.442648],"type":"Point"}
}