{
  "type": "Feature",
  "properties": {
    "iso:country":"AU",
    "sg:address":"Level 2 Harbourside Shopng Cntr",
    "sg:city":"Darling Harbour",
    "sg:classifiers":[
        {
            "category":"Fast Food",
            "type":"Food & Drink"
        }
    ],
    "sg:phone":"+61 2 9212 6655",
    "sg:postcode":"2000",
    "sg:province":"NSW",
    "sg:tags":[
        "away",
        "take"
    ],
    "wof:name":"Wok On Inn Noodle Bar",
    "wof:placetype":"venue"
},
  "geometry": {"coordinates":[151.19822692899999,-33.8725891113],"type":"Point"}
}