{
  "type": "Feature",
  "properties": {
    "addr:full":"121 Blackburn Rd Mt Waverley VIC 3149",
    "addr:housenumber":"121",
    "addr:postcode":"3149",
    "addr:street":"Blackburn Rd",
    "iso:country":"AU",
    "sg:address":"121 Blackburn Rd",
    "sg:city":"Mt Waverley",
    "sg:classifiers":[
        {
            "category":"Utilities",
            "subcategory":"Sewage",
            "type":"Services"
        }
    ],
    "sg:phone":"+61 3 9802 9071",
    "sg:postcode":"3149",
    "sg:province":"VIC",
    "sg:tags":[
        "arboriculturist"
    ],
    "wof:name":"PSY Pty Ltd",
    "wof:placetype":"venue"
},
  "geometry": {"coordinates":[145.14935302699999,-37.8662872314],"type":"Point"}
}