{
  "type": "Feature",
  "properties": {
    "addr:full":"27 Elizabeth St Maitland SA 5573",
    "addr:housenumber":"27",
    "addr:postcode":"5573",
    "addr:street":"Elizabeth St",
    "iso:country":"AU",
    "sg:address":"27 Elizabeth St",
    "sg:city":"Maitland",
    "sg:classifiers":[
        {
            "category":"Professional",
            "subcategory":"Accounting & Tax Preparation",
            "type":"Services"
        }
    ],
    "sg:phone":"+61 8 8832 2642",
    "sg:postcode":"5573",
    "sg:province":"SA",
    "sg:tags":[
        "consultant",
        "taxation"
    ],
    "wof:name":"Peter J Hallett",
    "wof:placetype":"venue"
},
  "geometry": {"coordinates":[137.672927856,-34.3737487793],"type":"Point"}
}